{
  "type": "Feature",
  "properties": {
    "iso:country":"AT",
    "sg:address":"Ludwig-Lassl-Str 2",
    "sg:city":"Wattens",
    "sg:orig_category":"Optiker",
    "sg:phone":"+43 5224 57280",
    "sg:postcode":"6112",
    "sg:province":"Tirol",
    "wof:name":"Optik F Wechselberger GmbH",
    "wof:placetype":"venue"
},
  "geometry": {"coordinates":[11.5929822922,47.2959671021],"type":"Point"}
}