{
  "type": "Feature",
  "properties": {
    "addr:full":"Europastr 64 Judenburg Steiermark 8750",
    "addr:housenumber":"64",
    "addr:postcode":"8750",
    "addr:street":"Europastr",
    "iso:country":"AT",
    "sg:address":"Europastr 64",
    "sg:city":"Judenburg",
    "sg:orig_category":"Genossenschaften",
    "sg:phone":"+43 3572 84906",
    "sg:postcode":"8750",
    "sg:province":"Steiermark",
    "wof:name":"Gemeinn\u00fctzige Siedlungsgenossenschaft d Arbeiter- und Angestellten",
    "wof:placetype":"venue"
},
  "geometry": {"coordinates":[14.6759586334,47.1759109497],"type":"Point"}
}