{
  "type": "Feature",
  "properties": {
    "iso:country":"AT",
    "sg:address":"Mozartstrasse 7",
    "sg:city":"Linz",
    "sg:classifiers":[
        {
            "category":"Banks & Credit Unions",
            "subcategory":"Investment Brokerage",
            "type":"Services"
        }
    ],
    "sg:phone":"+43 732 655515",
    "sg:postcode":"4020",
    "sg:province":"Ober\u00f6sterreich",
    "sg:tags":[
        "case",
        "spectacle"
    ],
    "sg:website":"marik.at",
    "wof:name":"Optik Marik Handelsges.m.b.H.",
    "wof:placetype":"venue"
},
  "geometry": {"coordinates":[14.2916688919,48.301322937],"type":"Point"}
}