{
  "type": "Feature",
  "properties": {
    "addr:full":"null Business/Park Heiligenkreuz im Lafnitztal Burgenland 7561",
    "addr:postcode":"7561",
    "iso:country":"AT",
    "sg:address":"null Business/Park",
    "sg:city":"Heiligenkreuz im Lafnitztal",
    "sg:orig_category":"Polizei U Gendarmerie",
    "sg:phone":"+43 4359 1331211",
    "sg:postcode":"7561",
    "sg:province":"Burgenland",
    "wof:name":"Gendarmerieposten",
    "wof:placetype":"venue"
},
  "geometry": {"coordinates":[16.2584495544,46.9887466431],"type":"Point"}
}