{
  "type": "Feature",
  "properties": {
    "addr:full":"Kircheng 10 Pischeldorf K\u00e4rnten 9064",
    "addr:housenumber":"10",
    "addr:postcode":"9064",
    "addr:street":"Kircheng;Kaernten",
    "iso:country":"AT",
    "sg:address":"Kircheng 10",
    "sg:city":"Pischeldorf",
    "sg:orig_category":"Transportunternehmen",
    "sg:phone":"+43 4224 2496",
    "sg:postcode":"9064",
    "sg:province":"K\u00e4rnten",
    "wof:name":"Lagler Transporte GmbH",
    "wof:placetype":"venue"
},
  "geometry": {"coordinates":[14.4182958603,46.6833152771],"type":"Point"}
}