{
  "type": "Feature",
  "properties": {
    "addr:full":"Pr\u00e4lat-Biedermann-G 5 Kautzen Nieder\u00f6sterreich 3851",
    "addr:housenumber":"5",
    "addr:postcode":"3851",
    "addr:street":"Praelat-Biedermann-G",
    "iso:country":"AT",
    "sg:address":"Pr\u00e4lat-Biedermann-G 5",
    "sg:city":"Kautzen",
    "sg:orig_category":"Autoreparatur",
    "sg:phone":"+43 4328 6426101",
    "sg:postcode":"3851",
    "sg:province":"Nieder\u00f6sterreich",
    "wof:name":"Samm Dietmar",
    "wof:placetype":"venue"
},
  "geometry": {"coordinates":[15.2348060608,48.9324493408],"type":"Point"}
}