{
  "type": "Feature",
  "properties": {
    "addr:full":"Hauptstr 3 Schwertberg Ober\u00f6sterreich 4311",
    "addr:housenumber":"3",
    "addr:postcode":"4311",
    "addr:street":"Hauptstr",
    "iso:country":"AT",
    "sg:address":"Hauptstr 3",
    "sg:city":"Schwertberg",
    "sg:orig_category":"Fleischhauereien",
    "sg:phone":"+43 7262 612530",
    "sg:postcode":"4311",
    "sg:province":"Ober\u00f6sterreich",
    "wof:name":"K\u00fcrmayr Fleisch und Wurstwaren KG",
    "wof:placetype":"venue"
},
  "geometry": {"coordinates":[14.5819311142,48.2744445801],"type":"Point"}
}