{
  "type": "Feature",
  "properties": {
    "addr:full":"Stadlg 2 Enns Ober\u00f6sterreich 4470",
    "addr:housenumber":"2",
    "addr:postcode":"4470",
    "addr:street":"Stadlg",
    "iso:country":"AT",
    "sg:address":"Stadlg 2",
    "sg:city":"Enns",
    "sg:orig_category":"Lebensmittel / Einzelhandel",
    "sg:phone":"+43 7223 84571",
    "sg:postcode":"4470",
    "sg:province":"Ober\u00f6sterreich",
    "wof:name":"Billa AG",
    "wof:placetype":"venue"
},
  "geometry": {"coordinates":[14.4792346954,48.2137947083],"type":"Point"}
}