{
  "type": "Feature",
  "properties": {
    "addr:full":"Laaer Str. 7-9  Korneuburg Nieder\u00f6sterreich 2100",
    "addr:postcode":"2100",
    "addr:street":"Str. 7-9",
    "iso:country":"AT",
    "sg:address":"Laaer Str. 7-9 ",
    "sg:city":"Korneuburg",
    "sg:classifiers":[
        {
            "category":"Professional",
            "subcategory":"Engineering",
            "type":"Services"
        }
    ],
    "sg:phone":"+43 4322 62626010",
    "sg:postcode":"2100",
    "sg:province":"Nieder\u00f6sterreich",
    "sg:tags":[
        "machine",
        "-",
        "mechanical"
    ],
    "wof:name":"SHIMADZU HANDELS GMBH",
    "wof:placetype":"venue"
},
  "geometry": {"coordinates":[16.3325920105,48.3459358215],"type":"Point"}
}