{
  "type": "Feature",
  "properties": {
    "iso:country":"AT",
    "sg:address":"Fuggerweg 1",
    "sg:city":"Kirchdorf in Tirol",
    "sg:classifiers":[
        {
            "category":"Professional",
            "subcategory":"Computer Services",
            "type":"Services"
        }
    ],
    "sg:phone":"+43 5352 64526",
    "sg:postcode":"6382",
    "sg:province":"Tirol",
    "sg:tags":[
        "software"
    ],
    "wof:name":"Frie\u00dfinger H PC & S",
    "wof:placetype":"venue"
},
  "geometry": {"coordinates":[12.4348087311,47.5428237915],"type":"Point"}
}