{
  "type": "Feature",
  "properties": {
    "addr:full":"Daponteg 7 Wien Wien 1030",
    "addr:housenumber":"7",
    "addr:postcode":"1030",
    "addr:street":"Daponteg",
    "iso:country":"AT",
    "sg:address":"Daponteg 7",
    "sg:city":"Wien",
    "sg:orig_category":"Limousinen",
    "sg:phone":"+43 4317 142203",
    "sg:postcode":"1030",
    "sg:province":"Wien",
    "sg:website":"adls.at",
    "wof:name":"A.D.L.S. Austrian Driver Limousine Service - Mario Schiansky GmbH",
    "wof:placetype":"venue"
},
  "geometry": {"coordinates":[16.388469696,48.1979522705],"type":"Point"}
}