{
  "type": "Feature",
  "properties": {
    "addr:full":"Kornsteinpl 4 Hallein Salzburg 5400",
    "addr:housenumber":"4",
    "addr:postcode":"5400",
    "addr:street":"Kornsteinpl;Salzburg",
    "iso:country":"AT",
    "sg:address":"Kornsteinpl 4",
    "sg:city":"Hallein",
    "sg:orig_category":"Trachtenbekleidung",
    "sg:phone":"+43 6245 86032",
    "sg:postcode":"5400",
    "sg:province":"Salzburg",
    "wof:name":"Herzerl Stub'n",
    "wof:placetype":"venue"
},
  "geometry": {"coordinates":[13.0926084518,47.6822853088],"type":"Point"}
}