{
  "type": "Feature",
  "properties": {
    "iso:country":"AT",
    "sg:address":"Staudach 29",
    "sg:city":"Kitzb\u00fchel",
    "sg:orig_category":"Weberei- U Spinnereibedarf",
    "sg:phone":"+43 4353 5671796",
    "sg:postcode":"6370",
    "sg:province":"Tirol",
    "wof:name":"CMF Consulting Fl\u00fccken OEG",
    "wof:placetype":"venue"
},
  "geometry": {"coordinates":[12.4043426514,47.4283447266],"type":"Point"}
}