{
  "type": "Feature",
  "properties": {
    "addr:full":"Alte Landstr 1 Bludenz Vorarlberg 6700",
    "addr:housenumber":"1",
    "addr:postcode":"6700",
    "addr:street":"Alte Landstr",
    "iso:country":"AT",
    "sg:address":"Alte Landstr 1",
    "sg:city":"Bludenz",
    "sg:orig_category":"Friseure U Frisiersalons",
    "sg:phone":"+43 5552 62891",
    "sg:postcode":"6700",
    "sg:province":"Vorarlberg",
    "wof:name":"Frisiersalon Rita",
    "wof:placetype":"venue"
},
  "geometry": {"coordinates":[9.8187408447,47.1580123901],"type":"Point"}
}