{
  "type": "Feature",
  "properties": {
    "addr:full":"Hauptpl 14 Bad Radkersburg Steiermark 8490",
    "addr:housenumber":"14",
    "addr:postcode":"8490",
    "addr:street":"Hauptpl",
    "iso:country":"AT",
    "sg:address":"Hauptpl 14",
    "sg:city":"Bad Radkersburg",
    "sg:orig_category":"Tourismusinformation U -Organisationen",
    "sg:phone":"+43 4334 7625450",
    "sg:postcode":"8490",
    "sg:province":"Steiermark",
    "wof:name":"Tourismusverband Bad Radkersburg",
    "wof:placetype":"venue"
},
  "geometry": {"coordinates":[15.9877853394,46.6874160767],"type":"Point"}
}