{
  "type": "Feature",
  "properties": {
    "addr:full":"Marktpl 1 Waizenkirchen Ober\u00f6sterreich 4730",
    "addr:housenumber":"1",
    "addr:postcode":"4730",
    "addr:street":"Marktpl",
    "iso:country":"AT",
    "sg:address":"Marktpl 1",
    "sg:city":"Waizenkirchen",
    "sg:orig_category":"Non-Classified Establishments",
    "sg:phone":"+43 7277 23540",
    "sg:postcode":"4730",
    "sg:province":"Ober\u00f6sterreich",
    "wof:name":"Pfarramt",
    "wof:placetype":"venue"
},
  "geometry": {"coordinates":[13.8565502167,48.3296508789],"type":"Point"}
}