{
  "type": "Feature",
  "properties": {
    "addr:full":"Obergro\u00dfau 97 Sinabelkirchen Steiermark 8261",
    "addr:housenumber":"97",
    "addr:postcode":"8261",
    "addr:street":"Obergrossau",
    "iso:country":"AT",
    "sg:address":"Obergro\u00dfau 97",
    "sg:city":"Sinabelkirchen",
    "sg:orig_category":"Blumeneinzelhandel",
    "sg:phone":"+43 3118 8365",
    "sg:postcode":"8261",
    "sg:province":"Steiermark",
    "wof:name":"Blumen Seidl",
    "wof:placetype":"venue"
},
  "geometry": {"coordinates":[15.7927932739,47.1007003784],"type":"Point"}
}