{
  "type": "Feature",
  "properties": {
    "iso:country":"AT",
    "sg:address":"Nr 208",
    "sg:city":"Rotenturm an der Pinka",
    "sg:orig_category":"Museen / Ausstellungen",
    "sg:phone":"+43 3352 34020",
    "sg:postcode":"7501",
    "sg:province":"Burgenland",
    "wof:name":"Unterwarter Heimathaus",
    "wof:placetype":"venue"
},
  "geometry": {"coordinates":[16.2445240021,47.25233078],"type":"Point"}
}