{
  "type": "Feature",
  "properties": {
    "addr:full":"Dorfstrasse 47 Bad Kleinkirchheim K\u00e4rnten 9546",
    "addr:housenumber":"47",
    "addr:postcode":"9546",
    "addr:street":"Dorfstrasse",
    "iso:country":"AT",
    "sg:address":"Dorfstrasse 47",
    "sg:city":"Bad Kleinkirchheim",
    "sg:classifiers":[
        {
            "category":"Sports & Exercise",
            "subcategory":"Bicycle Rental",
            "type":"Entertainment"
        }
    ],
    "sg:phone":"+43 4240 3460",
    "sg:postcode":"9546",
    "sg:province":"K\u00e4rnten",
    "sg:tags":[
        "equipment",
        "athletics"
    ],
    "sg:website":"sport-gruber.net",
    "wof:name":"Arno Gruber Sport & Mode GmbH & Co KG",
    "wof:placetype":"venue"
},
  "geometry": {"coordinates":[13.7789411545,46.8130722046],"type":"Point"}
}