{
  "type": "Feature",
  "properties": {
    "addr:full":"Brunnstubeng 39 Bisamberg Nieder\u00f6sterreich 2102",
    "addr:housenumber":"39",
    "addr:postcode":"2102",
    "addr:street":"Brunnstubeng",
    "iso:country":"AT",
    "sg:address":"Brunnstubeng 39",
    "sg:city":"Bisamberg",
    "sg:classifiers":[
        {
            "category":"Military Area",
            "subcategory":"Army Base",
            "type":"Public Place"
        }
    ],
    "sg:phone":"+43 4322 6263397",
    "sg:postcode":"2102",
    "sg:province":"Nieder\u00f6sterreich",
    "sg:tags":[
        "shiatsu"
    ],
    "wof:name":"Shiatsu - Praxis - Renate Schmid u Christian Antoni",
    "wof:placetype":"venue"
},
  "geometry": {"coordinates":[16.370973587,48.3329162598],"type":"Point"}
}