{
  "type": "Feature",
  "properties": {
    "addr:full":"Peterskirchen 19 Peterskirchen Ober\u00f6sterreich 4743",
    "addr:housenumber":"19",
    "addr:postcode":"4743",
    "addr:street":"Peterskirchen",
    "iso:country":"AT",
    "sg:address":"Peterskirchen 19",
    "sg:city":"Peterskirchen",
    "sg:classifiers":[
        {
            "category":"Retail",
            "subcategory":"Repair Shop",
            "type":"Services"
        }
    ],
    "sg:phone":"+43 7750 3417",
    "sg:postcode":"4743",
    "sg:province":"Ober\u00f6sterreich",
    "sg:tags":[
        "agricultural",
        "machinery"
    ],
    "wof:name":"Sternbauer Inh. Franz Flotzinger",
    "wof:placetype":"venue"
},
  "geometry": {"coordinates":[13.5469799042,48.2378959656],"type":"Point"}
}