{
  "type": "Feature",
  "properties": {
    "addr:full":"Nr 45 Gro\u00dfharras Nieder\u00f6sterreich 2034",
    "addr:postcode":"2034",
    "addr:street":"Nr 45",
    "iso:country":"AT",
    "sg:address":"Nr 45",
    "sg:city":"Gro\u00dfharras",
    "sg:orig_category":"Flugschulen",
    "sg:phone":"+43 2526 7381",
    "sg:postcode":"2034",
    "sg:province":"Nieder\u00f6sterreich",
    "wof:name":"Aerial Helicopter Bedarfsflugunternehmen GmbH",
    "wof:placetype":"venue"
},
  "geometry": {"coordinates":[16.2465991974,48.6635169983],"type":"Point"}
}