{
  "type": "Feature",
  "properties": {
    "addr:full":"Felberstr 100/6 Wien Wien 1150",
    "addr:housenumber":"100 / 6",
    "addr:postcode":"1150",
    "iso:country":"AT",
    "sg:address":"Felberstr 100/6",
    "sg:city":"Wien",
    "sg:orig_category":"Installationsunternehmen",
    "sg:phone":"+43 1 5971237",
    "sg:postcode":"1150",
    "sg:province":"Wien",
    "wof:name":"Smutny Karin GesmbH",
    "wof:placetype":"venue"
},
  "geometry": {"coordinates":[16.3213806152,48.1937141418],"type":"Point"}
}