{
  "type": "Feature",
  "properties": {
    "iso:country":"AT",
    "sg:address":"Wallerer Str 20",
    "sg:city":"Wels",
    "sg:orig_category":"Blumeneinzelhandel",
    "sg:phone":"+43 7242 224430",
    "sg:postcode":"4600",
    "sg:province":"Ober\u00f6sterreich",
    "wof:name":"Blumen M\u00fchlberger",
    "wof:placetype":"venue"
},
  "geometry": {"coordinates":[14.0221509933,48.1690216064],"type":"Point"}
}