{
  "type": "Feature",
  "properties": {
    "iso:country":"AT",
    "sg:address":"Grenzstr 35",
    "sg:city":"Wals",
    "sg:orig_category":"Gitter",
    "sg:phone":"+43 662 850722",
    "sg:postcode":"5071",
    "sg:province":"Salzburg",
    "wof:name":"Sommer Harald Ing GesmbH",
    "wof:placetype":"venue"
},
  "geometry": {"coordinates":[12.9848947525,47.8120155334],"type":"Point"}
}