{
  "type": "Feature",
  "properties": {
    "iso:country":"AT",
    "sg:address":"Sierninger Str 19",
    "sg:city":"Steyr",
    "sg:orig_category":"Maler, Anstreicher U Lackierer",
    "sg:phone":"+43 4372 5270034",
    "sg:postcode":"4400",
    "sg:province":"Ober\u00f6sterreich",
    "wof:name":"FIT-Maler GmbH",
    "wof:placetype":"venue"
},
  "geometry": {"coordinates":[14.4178943634,48.0437316895],"type":"Point"}
}