{
  "type": "Feature",
  "properties": {
    "addr:full":"Neusch\u00f6nauer Hptstr 47a Steyr Ober\u00f6sterreich 4400",
    "addr:housenumber":"47a",
    "addr:postcode":"4400",
    "addr:street":"Oberoesterreich",
    "iso:country":"AT",
    "sg:address":"Neusch\u00f6nauer Hptstr 47a",
    "sg:city":"Steyr",
    "sg:orig_category":"Physiotherapie",
    "sg:phone":"+43 664 9221865",
    "sg:postcode":"4400",
    "sg:province":"Ober\u00f6sterreich",
    "wof:name":"Haller Barbara Dipl-PT - Akupunktmasseurin",
    "wof:placetype":"venue"
},
  "geometry": {"coordinates":[14.4193296432,48.0391807556],"type":"Point"}
}