{
  "type": "Feature",
  "properties": {
    "addr:full":"Wienerherberger Str 30 Ebergassing Nieder\u00f6sterreich 2435",
    "addr:postcode":"2435",
    "addr:street":"Str 30",
    "iso:country":"AT",
    "sg:address":"Wienerherberger Str 30",
    "sg:city":"Ebergassing",
    "sg:orig_category":"Gemeinden",
    "sg:phone":"+43 2230 2259",
    "sg:postcode":"2435",
    "sg:province":"Nieder\u00f6sterreich",
    "wof:name":"Gemeinde Ebergassing - Wienerherberg",
    "wof:placetype":"venue"
},
  "geometry": {"coordinates":[16.5510978699,48.0581512451],"type":"Point"}
}