{
  "type": "Feature",
  "properties": {
    "iso:country":"AT",
    "sg:address":"Bundesstr. 44 ",
    "sg:city":"Volders",
    "sg:classifiers":[
        {
            "category":"Wholesale",
            "subcategory":"Drugs",
            "type":"Manufacturing & Wholesale Goods"
        }
    ],
    "sg:phone":"+43 4352 24576780",
    "sg:postcode":"6111",
    "sg:province":"Tirol",
    "sg:tags":[
        "chemical",
        "pharmaceutical"
    ],
    "wof:name":"IMMODAL PHARMAKA GESMBH",
    "wof:placetype":"venue"
},
  "geometry": {"coordinates":[11.5602693558,47.2855110168],"type":"Point"}
}