{
  "type": "Feature",
  "properties": {
    "iso:country":"AT",
    "sg:address":"Linzer Bundesstr 46",
    "sg:city":"Gnigl",
    "sg:orig_category":"Tapezierer U Dekorateure",
    "sg:phone":"+43 662 643608",
    "sg:postcode":"5023",
    "sg:province":"Salzburg",
    "wof:name":"Brugger Hans",
    "wof:placetype":"venue"
},
  "geometry": {"coordinates":[13.0695819855,47.8150138855],"type":"Point"}
}