{
  "type": "Feature",
  "properties": {
    "iso:country":"AT",
    "sg:address":"Krummbaumg 12",
    "sg:city":"Wien",
    "sg:orig_category":"Textilwaren / Erzeugung U Gro\u00c3\u0178handel",
    "sg:phone":"+43 1 2146078",
    "sg:postcode":"1020",
    "sg:province":"Wien",
    "wof:name":"Jatic & M\u00fcller Warenhandels-GmbH",
    "wof:placetype":"venue"
},
  "geometry": {"coordinates":[16.3771305084,48.2167510986],"type":"Point"}
}