{
  "type": "Feature",
  "properties": {
    "iso:country":"AT",
    "sg:address":"Nr 5",
    "sg:city":"Gutau",
    "sg:orig_category":"Pensionen / Privatzimmer",
    "sg:phone":"+43 7946 6384",
    "sg:postcode":"4293",
    "sg:province":"Ober\u00f6sterreich",
    "wof:name":"Ferienhof Kerschbaummayr",
    "wof:placetype":"venue"
},
  "geometry": {"coordinates":[14.6128253937,48.4172897339],"type":"Point"}
}