{
  "type": "Feature",
  "properties": {
    "addr:full":"Fadingerstr 16 Waizenkirchen Ober\u00f6sterreich 4730",
    "addr:housenumber":"16",
    "addr:postcode":"4730",
    "addr:street":"Fadingerstr",
    "iso:country":"AT",
    "sg:address":"Fadingerstr 16",
    "sg:city":"Waizenkirchen",
    "sg:orig_category":"Elektroinstallationsunternehmen",
    "sg:phone":"+43 7277 22230",
    "sg:postcode":"4730",
    "sg:province":"Ober\u00f6sterreich",
    "wof:name":"Petric Max",
    "wof:placetype":"venue"
},
  "geometry": {"coordinates":[13.8585166931,48.3317146301],"type":"Point"}
}