{
  "type": "Feature",
  "properties": {
    "iso:country":"AT",
    "sg:address":"Steigtalstr 26",
    "sg:city":"Leoben",
    "sg:orig_category":"Lebensmittel / Einzelhandel",
    "sg:phone":"+43 3842 267170",
    "sg:postcode":"8700",
    "sg:province":"Steiermark",
    "wof:name":"ADEG-Markt Walter Schuss",
    "wof:placetype":"venue"
},
  "geometry": {"coordinates":[15.098944664,47.3600082397],"type":"Point"}
}