{
  "type": "Feature",
  "properties": {
    "addr:full":"Rosenweg 15 Bodensdorf K\u00e4rnten 9551",
    "addr:housenumber":"15",
    "addr:postcode":"9551",
    "addr:street":"Rosenweg;Kaernten",
    "iso:country":"AT",
    "sg:address":"Rosenweg 15",
    "sg:city":"Bodensdorf",
    "sg:orig_category":"Elektroinstallationsunternehmen",
    "sg:phone":"+43 4365 05550894",
    "sg:postcode":"9551",
    "sg:province":"K\u00e4rnten",
    "wof:name":"Elektro Hofmeister & Skumautz OEG",
    "wof:placetype":"venue"
},
  "geometry": {"coordinates":[13.9662322998,46.6844406128],"type":"Point"}
}