{
  "type": "Feature",
  "properties": {
    "addr:full":"Bahnhofstrasse 1 Asten Ober\u00f6sterreich 4481",
    "addr:housenumber":"1",
    "addr:postcode":"4481",
    "addr:street":"Bahnhofstrasse",
    "iso:country":"AT",
    "sg:address":"Bahnhofstrasse 1",
    "sg:city":"Asten",
    "sg:classifiers":[
        {
            "category":"Home & Garden",
            "subcategory":"Carpets & Floor Coverings",
            "type":"Retail Goods"
        }
    ],
    "sg:phone":"+43 7224 67090",
    "sg:postcode":"4481",
    "sg:province":"Ober\u00f6sterreich",
    "sg:tags":[
        "blind",
        "nut",
        "rivet"
    ],
    "sg:website":"kvt-koenig.at",
    "wof:name":"Koenig Austria GmbH",
    "wof:placetype":"venue"
},
  "geometry": {"coordinates":[14.4001426697,48.2255210876],"type":"Point"}
}