{
  "type": "Feature",
  "properties": {
    "iso:country":"AT",
    "sg:address":"Rathauspl 2/Pyhrnpark",
    "sg:city":"Liezen",
    "sg:orig_category":"Gesundheitsvorsorge",
    "sg:phone":"+43 3612 21066",
    "sg:postcode":"8940",
    "sg:province":"Steiermark",
    "wof:name":"Vital Center",
    "wof:placetype":"venue"
},
  "geometry": {"coordinates":[14.2413349152,47.5672111511],"type":"Point"}
}