{
  "type": "Feature",
  "properties": {
    "iso:country":"AT",
    "sg:address":"Rennfeldweg 6",
    "sg:city":"Bruck an der Mur",
    "sg:orig_category":"Bauunternehmen",
    "sg:phone":"+43 4338 6255283",
    "sg:postcode":"8600",
    "sg:province":"Steiermark",
    "wof:name":"Schneller BaugesmbH",
    "wof:placetype":"venue"
},
  "geometry": {"coordinates":[15.2885513306,47.4151039124],"type":"Point"}
}