{
  "type": "Feature",
  "properties": {
    "addr:full":"Weissenkircherstrasse 17 Graz Steiermark 8020",
    "addr:housenumber":"17",
    "addr:postcode":"8020",
    "addr:street":"Weissenkircherstrasse",
    "iso:country":"AT",
    "sg:address":"Weissenkircherstrasse 17",
    "sg:city":"Graz",
    "sg:classifiers":[
        {
            "category":"Home & Garden",
            "subcategory":"Home Furnishings",
            "type":"Retail Goods"
        }
    ],
    "sg:phone":"+43 316 572954",
    "sg:postcode":"8020",
    "sg:province":"Steiermark",
    "sg:tags":[
        "textile"
    ],
    "wof:name":"Dr. Rudolf K\u00fchnfels Handelsagentur",
    "wof:placetype":"venue"
},
  "geometry": {"coordinates":[15.3996915817,47.0699615479],"type":"Point"}
}