{
  "type": "Feature",
  "properties": {
    "addr:full":"Salzburger Str 15 Gallspach Ober\u00f6sterreich 4713",
    "addr:housenumber":"15",
    "addr:postcode":"4713",
    "addr:street":"Salzburger Str",
    "iso:country":"AT",
    "sg:address":"Salzburger Str 15",
    "sg:city":"Gallspach",
    "sg:orig_category":"Pensionen / Privatzimmer",
    "sg:phone":"+43 7248 62394",
    "sg:postcode":"4713",
    "sg:province":"Ober\u00f6sterreich",
    "wof:name":"Wiesinger Maria",
    "wof:placetype":"venue"
},
  "geometry": {"coordinates":[13.8072128296,48.2052154541],"type":"Point"}
}