{
  "type": "Feature",
  "properties": {
    "addr:full":"Speisinger Str 4 Wien Wien 1130",
    "addr:housenumber":"4",
    "addr:postcode":"1130",
    "addr:street":"Str",
    "iso:country":"AT",
    "sg:address":"Speisinger Str 4",
    "sg:city":"Wien",
    "sg:orig_category":"Werbeagenturen",
    "sg:phone":"+43 1 80423830",
    "sg:postcode":"1130",
    "sg:province":"Wien",
    "wof:name":"IDEEN GesmbH",
    "wof:placetype":"venue"
},
  "geometry": {"coordinates":[16.28465271,48.1728401184],"type":"Point"}
}