{
  "type": "Feature",
  "properties": {
    "addr:full":"Lendpl 21 Graz Steiermark 8020",
    "addr:housenumber":"21",
    "addr:postcode":"8020",
    "addr:street":"Lendpl",
    "iso:country":"AT",
    "sg:address":"Lendpl 21",
    "sg:city":"Graz",
    "sg:orig_category":"Polizei U Gendarmerie",
    "sg:phone":"+43 4331 68885410",
    "sg:postcode":"8020",
    "sg:province":"Steiermark",
    "wof:name":"Polizeiwachzimmer",
    "wof:placetype":"venue"
},
  "geometry": {"coordinates":[15.4289960861,47.0762519836],"type":"Point"}
}