{
  "type": "Feature",
  "properties": {
    "iso:country":"AT",
    "sg:address":"Braunstr 19",
    "sg:city":"Baden",
    "sg:classifiers":[
        {
            "category":"Retail",
            "subcategory":"Event Space",
            "type":"Services"
        }
    ],
    "sg:phone":"+43 4322 5245843",
    "sg:postcode":"2500",
    "sg:province":"Nieder\u00f6sterreich",
    "sg:tags":[
        "hand-",
        "u",
        "fu\u00c3\u0178pflege"
    ],
    "wof:name":"Studio Helga",
    "wof:placetype":"venue"
},
  "geometry": {"coordinates":[16.2506332397,48.0100212097],"type":"Point"}
}