{
  "type": "Feature",
  "properties": {
    "iso:country":"AT",
    "sg:address":"Sollingerg 23",
    "sg:city":"Wien",
    "sg:orig_category":"Transportunternehmen",
    "sg:phone":"+43 664 2054537",
    "sg:postcode":"1190",
    "sg:province":"Wien",
    "wof:name":"Transporte Dede Agg\u00fcn KEG",
    "wof:placetype":"venue"
},
  "geometry": {"coordinates":[16.3351325989,48.2429389954],"type":"Point"}
}