{
  "type": "Feature",
  "properties": {
    "iso:country":"AT",
    "sg:address":"Winkl-Schattseite 2f",
    "sg:city":"St. Johann in Tirol",
    "sg:classifiers":[
        {
            "category":"Home & Garden",
            "subcategory":"Building Materials",
            "type":"Retail Goods"
        }
    ],
    "sg:phone":"+43 5352 63525",
    "sg:postcode":"6380",
    "sg:province":"Tirol",
    "sg:tags":[
        "installation",
        "electric"
    ],
    "wof:name":"Andreas Daxauer GesmbH",
    "wof:placetype":"venue"
},
  "geometry": {"coordinates":[12.4480142593,47.5165023804],"type":"Point"}
}