{
  "type": "Feature",
  "properties": {
    "addr:full":"Kreuzschied 141 Neukirchen am Gro\u00dfvenediger Salzburg 5741",
    "addr:housenumber":"141",
    "addr:postcode":"5741",
    "addr:street":"Salzburg",
    "iso:country":"AT",
    "sg:address":"Kreuzschied 141",
    "sg:city":"Neukirchen am Gro\u00dfvenediger",
    "sg:orig_category":"Tischlereien",
    "sg:phone":"+43 4365 6563420",
    "sg:postcode":"5741",
    "sg:province":"Salzburg",
    "wof:name":"Lechner Anton",
    "wof:placetype":"venue"
},
  "geometry": {"coordinates":[12.2727975845,47.2516708374],"type":"Point"}
}