{
  "type": "Feature",
  "properties": {
    "addr:full":"Seilerweg 28 Krems an der Donau Nieder\u00f6sterreich 3500",
    "addr:housenumber":"28",
    "addr:postcode":"3500",
    "addr:street":"Seilerweg",
    "iso:country":"AT",
    "sg:address":"Seilerweg 28",
    "sg:city":"Krems an der Donau",
    "sg:orig_category":"Leder",
    "sg:phone":"+43 2732 73520",
    "sg:postcode":"3500",
    "sg:province":"Nieder\u00f6sterreich",
    "wof:name":"Gruber Gerhard",
    "wof:placetype":"venue"
},
  "geometry": {"coordinates":[15.5885457993,48.4237289429],"type":"Point"}
}