{
  "type": "Feature",
  "properties": {
    "addr:full":"Berghofstr 3 Waidhofen an der Ybbs Nieder\u00f6sterreich 3340",
    "addr:housenumber":"3",
    "addr:postcode":"3340",
    "addr:street":"Berghofstr",
    "iso:country":"AT",
    "sg:address":"Berghofstr 3",
    "sg:city":"Waidhofen an der Ybbs",
    "sg:orig_category":"Geigen",
    "sg:phone":"+43 4374 4255374",
    "sg:postcode":"3340",
    "sg:province":"Nieder\u00f6sterreich",
    "wof:name":"Ivan Peter - Atelier f Geigenbau",
    "wof:placetype":"venue"
},
  "geometry": {"coordinates":[14.7814922333,47.9607696533],"type":"Point"}
}