{
  "type": "Feature",
  "properties": {
    "addr:full":"Rechte Wienzeile 9a Wien Wien 1040",
    "addr:housenumber":"9a",
    "addr:postcode":"1040",
    "addr:street":"Rechte Wienzeile",
    "iso:country":"AT",
    "sg:address":"Rechte Wienzeile 9a",
    "sg:city":"Wien",
    "sg:classifiers":[
        {
            "category":"Home & Garden",
            "subcategory":"Building Materials",
            "type":"Retail Goods"
        }
    ],
    "sg:phone":"+43 1 5878557",
    "sg:postcode":"1040",
    "sg:province":"Wien",
    "sg:tags":[
        "tile",
        "ceramic"
    ],
    "wof:name":"Johann Schefer Ges.m.b.H.",
    "wof:placetype":"venue"
},
  "geometry": {"coordinates":[16.364900589,48.1988792419],"type":"Point"}
}