{
  "type": "Feature",
  "properties": {
    "addr:full":"Erlaaer Str 34 Wien Wien 1230",
    "addr:postcode":"1230",
    "addr:street":"Str 34",
    "iso:country":"AT",
    "sg:address":"Erlaaer Str 34",
    "sg:city":"Wien",
    "sg:orig_category":"Alteisen U Altmetalle",
    "sg:phone":"+43 1 8698561",
    "sg:postcode":"1230",
    "sg:province":"Wien",
    "wof:name":"Kisielewski Wilhelm",
    "wof:placetype":"venue"
},
  "geometry": {"coordinates":[16.3014907837,48.1471290588],"type":"Point"}
}