{
  "type": "Feature",
  "properties": {
    "addr:full":"Oskar-Kokoschka-Pl 2 Wien Wien 1010",
    "addr:housenumber":"2",
    "addr:postcode":"1010",
    "addr:street":"Oskar-Kokoschka-Pl",
    "iso:country":"AT",
    "sg:address":"Oskar-Kokoschka-Pl 2",
    "sg:city":"Wien",
    "sg:orig_category":"Betriebs- U Fernverpflegung",
    "sg:phone":"+43 4317 186695",
    "sg:postcode":"1010",
    "sg:province":"Wien",
    "wof:name":"\u00f6sterreichische Mensen BetriebsgesmbH",
    "wof:placetype":"venue"
},
  "geometry": {"coordinates":[16.3829936981,48.208480835],"type":"Point"}
}