{
  "type": "Feature",
  "properties": {
    "addr:full":"Steinamangerstr 8 Pinkafeld Burgenland 7423",
    "addr:housenumber":"8",
    "addr:postcode":"7423",
    "addr:street":"Steinamangerstr",
    "iso:country":"AT",
    "sg:address":"Steinamangerstr 8",
    "sg:city":"Pinkafeld",
    "sg:orig_category":"Tankstellen",
    "sg:phone":"+43 3357 46231",
    "sg:postcode":"7423",
    "sg:province":"Burgenland",
    "wof:name":"OMV Tankstelle",
    "wof:placetype":"venue"
},
  "geometry": {"coordinates":[16.1251239777,47.3636474609],"type":"Point"}
}