{
  "type": "Feature",
  "properties": {
    "iso:country":"AT",
    "sg:address":"Industriestra\u00dfe 19",
    "sg:city":"St. Johann im Pongau",
    "sg:classifiers":[
        {
            "category":"Professional",
            "subcategory":"Engineering",
            "type":"Services"
        }
    ],
    "sg:phone":"+43 4364 124394",
    "sg:postcode":"5600",
    "sg:province":"Salzburg",
    "sg:tags":[
        "machine",
        "-",
        "mechanical"
    ],
    "wof:name":"KGT K\u00c4LTE- & GASTROTECHNIK GMBH",
    "wof:placetype":"venue"
},
  "geometry": {"coordinates":[13.2002429962,47.3538169861],"type":"Point"}
}