{
  "type": "Feature",
  "properties": {
    "addr:full":"Johann Strau\u00df-G 2 Purkersdorf Nieder\u00f6sterreich 3002",
    "addr:housenumber":"2",
    "addr:postcode":"3002",
    "iso:country":"AT",
    "sg:address":"Johann Strau\u00df-G 2",
    "sg:city":"Purkersdorf",
    "sg:orig_category":"Immobilienmakler",
    "sg:phone":"+43 2231 629800",
    "sg:postcode":"3002",
    "sg:province":"Nieder\u00f6sterreich",
    "wof:name":"Kirnberger Bautr\u00e4ger GmbH",
    "wof:placetype":"venue"
},
  "geometry": {"coordinates":[16.1864490509,48.2114257812],"type":"Point"}
}