{
  "type": "Feature",
  "properties": {
    "iso:country":"AT",
    "sg:address":"Schattentratten 2",
    "sg:city":"Wolfsberg",
    "sg:classifiers":[
        {
            "category":"Internet Cafe",
            "subcategory":"None",
            "type":"Food & Drink"
        }
    ],
    "sg:phone":"+43 650 8630545",
    "sg:postcode":"9400",
    "sg:province":"K\u00e4rnten",
    "wof:name":"Leopold & Hasenbichler OEG",
    "wof:placetype":"venue"
},
  "geometry": {"coordinates":[14.8267412186,46.8319320679],"type":"Point"}
}