{
  "type": "Feature",
  "properties": {
    "addr:full":"Zeller Str 4 Mittersill Salzburg 5730",
    "addr:housenumber":"4",
    "addr:postcode":"5730",
    "addr:street":"Zeller Str;Salzburg",
    "iso:country":"AT",
    "sg:address":"Zeller Str 4",
    "sg:city":"Mittersill",
    "sg:orig_category":"Textilwaren / Einzelhandel",
    "sg:phone":"+43 6562 6680",
    "sg:postcode":"5730",
    "sg:province":"Salzburg",
    "wof:name":"Scharler Georg",
    "wof:placetype":"venue"
},
  "geometry": {"coordinates":[12.4830560684,47.2828216553],"type":"Point"}
}