{
  "type": "Feature",
  "properties": {
    "addr:full":"Aspach 1 Eberschwang Ober\u00f6sterreich 4906",
    "addr:housenumber":"1",
    "addr:postcode":"4906",
    "addr:street":"Aspach",
    "iso:country":"AT",
    "sg:address":"Aspach 1",
    "sg:city":"Eberschwang",
    "sg:orig_category":"Bodenuntersuchungen",
    "sg:phone":"+43 7753 2101",
    "sg:postcode":"4906",
    "sg:province":"Ober\u00f6sterreich",
    "wof:name":"Griesmaier Karl",
    "wof:placetype":"venue"
},
  "geometry": {"coordinates":[13.5566301346,48.1758155823],"type":"Point"}
}