{
  "type": "Feature",
  "properties": {
    "addr:full":"Frankg 1 Wien Wien 1090",
    "addr:housenumber":"1",
    "addr:postcode":"1090",
    "addr:street":"Frankg",
    "iso:country":"AT",
    "sg:address":"Frankg 1",
    "sg:city":"Wien",
    "sg:orig_category":"Institute",
    "sg:phone":"+43 4314 27740901",
    "sg:postcode":"1090",
    "sg:province":"Wien",
    "wof:name":"Institut f \u00e4gyptologie",
    "wof:placetype":"venue"
},
  "geometry": {"coordinates":[16.3573074341,48.2153091431],"type":"Point"}
}