{
  "type": "Feature",
  "properties": {
    "addr:full":"Pfarrgasse 64 Wien Wien 1230",
    "addr:housenumber":"64",
    "addr:postcode":"1230",
    "addr:street":"Pfarrgasse",
    "iso:country":"AT",
    "sg:address":"Pfarrgasse 64",
    "sg:city":"Wien",
    "sg:classifiers":[
        {
            "category":"Bus Stop",
            "subcategory":"None",
            "type":"Transportation"
        }
    ],
    "sg:phone":"+43 1 61655300",
    "sg:postcode":"1230",
    "sg:province":"Wien",
    "sg:tags":[
        "pipe",
        "aluminium"
    ],
    "wof:name":"METALKA HandelsgmbH",
    "wof:placetype":"venue"
},
  "geometry": {"coordinates":[16.3408870697,48.1379051208],"type":"Point"}
}