{
  "type": "Feature",
  "properties": {
    "addr:full":"Haydnstr 10 Salzburg Salzburg 5020",
    "addr:housenumber":"10",
    "addr:postcode":"5020",
    "addr:street":"Haydnstr;Salzburg",
    "iso:country":"AT",
    "sg:address":"Haydnstr 10",
    "sg:city":"Salzburg",
    "sg:orig_category":"Papier- U Schreibwaren / Einzelhandel",
    "sg:phone":"+43 662 870684",
    "sg:postcode":"5020",
    "sg:province":"Salzburg",
    "wof:name":"Haremza Renate",
    "wof:placetype":"venue"
},
  "geometry": {"coordinates":[13.0458478928,47.8066864014],"type":"Point"}
}