{
  "type": "Feature",
  "properties": {
    "addr:full":"Hauptstr 3 Gr\u00f6dig Salzburg 5082",
    "addr:housenumber":"3",
    "addr:postcode":"5082",
    "addr:street":"Hauptstr;Salzburg",
    "iso:country":"AT",
    "sg:address":"Hauptstr 3",
    "sg:city":"Gr\u00f6dig",
    "sg:orig_category":"Bibliotheken",
    "sg:phone":"+43 6246 73005",
    "sg:postcode":"5082",
    "sg:province":"Salzburg",
    "wof:name":"B\u00fccherei d Marktgemeinde Gr\u00f6dig",
    "wof:placetype":"venue"
},
  "geometry": {"coordinates":[-76.2684555054,37.4373283386],"type":"Point"}
}