{
  "type": "Feature",
  "properties": {
    "iso:country":"AT",
    "sg:address":"Nestroypl 1/32",
    "sg:city":"Wien",
    "sg:orig_category":"Farb-, Stil- U Typberatung",
    "sg:phone":"+43 699 10894598",
    "sg:postcode":"1020",
    "sg:province":"Wien",
    "wof:name":"Schober Claudia - Ganzheitliche Farbberatung",
    "wof:placetype":"venue"
},
  "geometry": {"coordinates":[16.3848514557,48.2143974304],"type":"Point"}
}