{
  "type": "Feature",
  "properties": {
    "addr:full":"Dr.-Hans-Lechner-Strasse 13 Wals Salzburg 5071",
    "addr:housenumber":"13",
    "addr:postcode":"5071",
    "addr:street":"Dr.-Hans-Lechner-Strasse;Salzburg",
    "iso:country":"AT",
    "sg:address":"Dr.-Hans-Lechner-Strasse 13",
    "sg:city":"Wals",
    "sg:classifiers":[
        {
            "category":"Banks & Credit Unions",
            "subcategory":"Investment Brokerage",
            "type":"Services"
        }
    ],
    "sg:phone":"+43 662 852222",
    "sg:postcode":"5071",
    "sg:province":"Salzburg",
    "sg:tags":[
        "bearing",
        "ball"
    ],
    "sg:website":"nilsson.co.at",
    "wof:name":"G. O. Nilsson Ges.m.b.H.",
    "wof:placetype":"venue"
},
  "geometry": {"coordinates":[12.9942169189,47.8120040894],"type":"Point"}
}