{
  "type": "Feature",
  "properties": {
    "iso:country":"AT",
    "sg:address":"Lohbachufer 6",
    "sg:city":"Innsbruck",
    "sg:orig_category":"Berufsschulen",
    "sg:phone":"+43 512 284533",
    "sg:postcode":"6020",
    "sg:province":"Tirol",
    "wof:name":"Tiroler Fachberufsschule f Elektrotechnik",
    "wof:placetype":"venue"
},
  "geometry": {"coordinates":[11.3583669662,47.2643013],"type":"Point"}
}