{
  "type": "Feature",
  "properties": {
    "iso:country":"AT",
    "sg:address":"Erdberger L\u00e4nde 36-48",
    "sg:city":"Wien",
    "sg:orig_category":"Autobusunternehmen",
    "sg:phone":"+43 1 711070",
    "sg:postcode":"1030",
    "sg:province":"Wien",
    "wof:name":"Postauto Competence-Center \u00f6sterreich",
    "wof:placetype":"venue"
},
  "geometry": {"coordinates":[16.4070186615,48.1999588013],"type":"Point"}
}