{
  "type": "Feature",
  "properties": {
    "addr:full":"Alois-Wessely-Pl 6 Bernstein Burgenland 7434",
    "addr:housenumber":"6",
    "addr:postcode":"7434",
    "addr:street":"Alois-Wessely-Pl",
    "iso:country":"AT",
    "sg:address":"Alois-Wessely-Pl 6",
    "sg:city":"Bernstein",
    "sg:orig_category":"Gemeinden",
    "sg:phone":"+43 3354 6502",
    "sg:postcode":"7434",
    "sg:province":"Burgenland",
    "wof:name":"Gemeindeamt Bernstein",
    "wof:placetype":"venue"
},
  "geometry": {"coordinates":[16.257900238,47.4055404663],"type":"Point"}
}