{
  "type": "Feature",
  "properties": {
    "iso:country":"AT",
    "sg:address":"Thomas Bohrer-Str 7",
    "sg:city":"Klagenfurt",
    "sg:orig_category":"Spielautomaten",
    "sg:phone":"+43 4346 34107870",
    "sg:postcode":"9020",
    "sg:province":"K\u00e4rnten",
    "wof:name":"Gastronomie- u Unterhaltungselektronik Betriebs GmbH",
    "wof:placetype":"venue"
},
  "geometry": {"coordinates":[14.3701639175,46.6316947937],"type":"Point"}
}