{
  "type": "Feature",
  "properties": {
    "addr:full":"Hauptstr 40 Gedersdorf Nieder\u00f6sterreich 3494",
    "addr:housenumber":"40",
    "addr:postcode":"3494",
    "addr:street":"Hauptstr",
    "iso:country":"AT",
    "sg:address":"Hauptstr 40",
    "sg:city":"Gedersdorf",
    "sg:orig_category":"Weine / Einzelhandel",
    "sg:phone":"+43 2735 8318",
    "sg:postcode":"3494",
    "sg:province":"Nieder\u00f6sterreich",
    "wof:name":"Steinbatz Franz",
    "wof:placetype":"venue"
},
  "geometry": {"coordinates":[15.6969642639,48.4305419922],"type":"Point"}
}