{
  "type": "Feature",
  "properties": {
    "addr:full":"Gewerbestrasse 3 St. Marienkirchen Ober\u00f6sterreich 4774",
    "addr:housenumber":"3",
    "addr:postcode":"4774",
    "addr:street":"Gewerbestrasse",
    "iso:country":"AT",
    "sg:address":"Gewerbestrasse 3",
    "sg:city":"St. Marienkirchen",
    "sg:classifiers":[
        {
            "category":"Manufacturing",
            "subcategory":"Tools & Machinery",
            "type":"Manufacturing & Wholesale Goods"
        }
    ],
    "sg:phone":"+43 7711 316150",
    "sg:postcode":"4774",
    "sg:province":"Ober\u00f6sterreich",
    "sg:tags":[
        "part",
        "turned",
        "cnc"
    ],
    "sg:website":"milltech.at",
    "wof:name":"Milltech GmbH",
    "wof:placetype":"venue"
},
  "geometry": {"coordinates":[13.4512290955,48.3879585266],"type":"Point"}
}