{
  "type": "Feature",
  "properties": {
    "addr:full":"Roseggerkai 5 Graz Steiermark 8010",
    "addr:housenumber":"5",
    "addr:postcode":"8010",
    "addr:street":"Roseggerkai",
    "iso:country":"AT",
    "sg:address":"Roseggerkai 5",
    "sg:city":"Graz",
    "sg:orig_category":"Optiker",
    "sg:phone":"+43 316 8143220",
    "sg:postcode":"8010",
    "sg:province":"Steiermark",
    "wof:name":"Rantascha Peter Optik",
    "wof:placetype":"venue"
},
  "geometry": {"coordinates":[15.4357872009,47.065776825],"type":"Point"}
}