{
  "type": "Feature",
  "properties": {
    "addr:full":"Stockenhuberweg 12 Linz Ober\u00f6sterreich 4040",
    "addr:housenumber":"12",
    "addr:postcode":"4040",
    "addr:street":"Stockenhuberweg",
    "iso:country":"AT",
    "sg:address":"Stockenhuberweg 12",
    "sg:city":"Linz",
    "sg:orig_category":"Damenmoden",
    "sg:phone":"+43 4373 2251182",
    "sg:postcode":"4040",
    "sg:province":"Ober\u00f6sterreich",
    "wof:name":"Gruener Rabe - Gewaender mit Seide u Spitze - Mag Sonja Tauber",
    "wof:placetype":"venue"
},
  "geometry": {"coordinates":[14.329867363,48.3268966675],"type":"Point"}
}