{
  "type": "Feature",
  "properties": {
    "iso:country":"AT",
    "sg:address":"Rettenbach 270",
    "sg:city":"S\u00f6lden",
    "sg:classifiers":[
        {
            "category":"Taxi",
            "type":"Transportation"
        }
    ],
    "sg:phone":"+43 4352 543600",
    "sg:postcode":"6450",
    "sg:province":"Tirol",
    "sg:tags":[
        "personentransporte",
        "u"
    ],
    "wof:name":"Taxi Gurschler Serafin",
    "wof:placetype":"venue"
},
  "geometry": {"coordinates":[11.0101947784,46.9675750732],"type":"Point"}
}