{
  "type": "Feature",
  "properties": {
    "iso:country":"AT",
    "sg:address":"Oberlaaer Strasse 316",
    "sg:classifiers":[
        {
            "category":"Military Area",
            "subcategory":"Air Force Base",
            "type":"Public Place"
        }
    ],
    "sg:phone":"+43 1 61668070",
    "sg:postcode":"1232",
    "sg:tags":[
        "bearing",
        "sealing",
        "graphite",
        "ring",
        "carbon"
    ],
    "sg:website":"schunk-materials.at",
    "wof:name":"Schunk Wien Ges.m.b.H.",
    "wof:placetype":"venue"
},
  "geometry": {"coordinates":[16.3556747437,48.1498184204],"type":"Point"}
}