{
  "type": "Feature",
  "properties": {
    "addr:full":"Bahnstr 2 Aspang-Markt Nieder\u00f6sterreich 2870",
    "addr:housenumber":"2",
    "addr:postcode":"2870",
    "addr:street":"Bahnstr;Niederoesterreich",
    "iso:country":"AT",
    "sg:address":"Bahnstr 2",
    "sg:city":"Aspang-Markt",
    "sg:orig_category":"Glasereien",
    "sg:phone":"+43 2642 523190",
    "sg:postcode":"2870",
    "sg:province":"Nieder\u00f6sterreich",
    "wof:name":"Huber Josef GesmbH",
    "wof:placetype":"venue"
},
  "geometry": {"coordinates":[16.0906543732,47.5562934875],"type":"Point"}
}