{
  "type": "Feature",
  "properties": {
    "addr:full":"Trosselsdorf 4219",
    "addr:postcode":"4219",
    "addr:street":"Trosselsdorf",
    "iso:country":"AT",
    "sg:address":"Trosselsdorf",
    "sg:orig_category":"Feuerwehren",
    "sg:phone":"+43 7941 8526",
    "sg:postcode":"4219",
    "wof:name":"Freiwillige Feuerwehr Trosselsdorf",
    "wof:placetype":"venue"
},
  "geometry": {"coordinates":[14.4640197754,48.4205207825],"type":"Point"}
}