{
  "type": "Feature",
  "properties": {
    "addr:full":"Rathauspassage 3 Stockerau Nieder\u00f6sterreich 2000",
    "addr:housenumber":"3",
    "addr:postcode":"2000",
    "addr:street":"Rathauspassage",
    "iso:country":"AT",
    "sg:address":"Rathauspassage 3",
    "sg:city":"Stockerau",
    "sg:orig_category":"Modellbau",
    "sg:phone":"+43 2266 61088",
    "sg:postcode":"2000",
    "sg:province":"Nieder\u00f6sterreich",
    "wof:name":"Speed & Sport Modellbau",
    "wof:placetype":"venue"
},
  "geometry": {"coordinates":[16.2073516846,48.3849372864],"type":"Point"}
}