{
  "type": "Feature",
  "properties": {
    "addr:full":"Franz-Groi\u00df-G 20 Marchegg Nieder\u00f6sterreich 2293",
    "addr:housenumber":"20",
    "addr:postcode":"2293",
    "addr:street":"Franz-Groiss-G",
    "iso:country":"AT",
    "sg:address":"Franz-Groi\u00df-G 20",
    "sg:city":"Marchegg",
    "sg:orig_category":"Rauchfangkehrer",
    "sg:phone":"+43 2285 7300",
    "sg:postcode":"2293",
    "sg:province":"Nieder\u00f6sterreich",
    "wof:name":"Schicker Georg Ing",
    "wof:placetype":"venue"
},
  "geometry": {"coordinates":[16.9062099457,48.2770805359],"type":"Point"}
}