{
  "type": "Feature",
  "properties": {
    "iso:country":"AT",
    "sg:address":"Kircheng 2",
    "sg:city":"Deutsch Brodersdorf",
    "sg:orig_category":"Garten- U Landschaftsgestaltung",
    "sg:phone":"+43 4322 557455",
    "sg:postcode":"2443",
    "sg:province":"Nieder\u00f6sterreich",
    "wof:name":"Richter Rasen GmbH",
    "wof:placetype":"venue"
},
  "geometry": {"coordinates":[16.4722042084,47.9383773804],"type":"Point"}
}