{
  "type": "Feature",
  "properties": {
    "addr:full":"Stadtpl 2 Grein Ober\u00f6sterreich 4360",
    "addr:housenumber":"2",
    "addr:postcode":"4360",
    "addr:street":"Stadtpl",
    "iso:country":"AT",
    "sg:address":"Stadtpl 2",
    "sg:city":"Grein",
    "sg:orig_category":"Rauchfangkehrer",
    "sg:phone":"+43 7268 70330",
    "sg:postcode":"4360",
    "sg:province":"Ober\u00f6sterreich",
    "wof:name":"Geyrhofer Helmut",
    "wof:placetype":"venue"
},
  "geometry": {"coordinates":[14.8545036316,48.2274932861],"type":"Point"}
}