{
  "type": "Feature",
  "properties": {
    "addr:full":"Dorf 570 Lech Vorarlberg 6764",
    "addr:housenumber":"570",
    "addr:postcode":"6764",
    "addr:street":"Dorf",
    "iso:country":"AT",
    "sg:address":"Dorf 570",
    "sg:city":"Lech",
    "sg:orig_category":"Appartements / Ferienwohnungen",
    "sg:phone":"+43 5583 42120",
    "sg:postcode":"6764",
    "sg:province":"Vorarlberg",
    "wof:name":"Appart Haus Altana",
    "wof:placetype":"venue"
},
  "geometry": {"coordinates":[10.1417798996,47.2082939148],"type":"Point"}
}