{
  "type": "Feature",
  "properties": {
    "iso:country":"AT",
    "sg:address":"Industriestr 11",
    "sg:city":"Spittal an der Drau",
    "sg:orig_category":"Fliesen U Platten",
    "sg:phone":"+43 4347 62611410",
    "sg:postcode":"9800",
    "sg:province":"K\u00e4rnten",
    "wof:name":"Nessl Harry GmbH",
    "wof:placetype":"venue"
},
  "geometry": {"coordinates":[13.524684906,46.7842445374],"type":"Point"}
}