{
  "type": "Feature",
  "properties": {
    "iso:country":"AT",
    "sg:address":"Laxenburger Str 250",
    "sg:city":"Wien",
    "sg:orig_category":"Feinkost",
    "sg:phone":"+43 1 81585050",
    "sg:postcode":"1100",
    "sg:province":"Wien",
    "wof:name":"Wojnars Wiener Leckerbissen Delikatessenerzeugung GmbH",
    "wof:placetype":"venue"
},
  "geometry": {"coordinates":[16.3638362885,48.1536712646],"type":"Point"}
}