{
  "type": "Feature",
  "properties": {
    "addr:full":"Lifehausstr 24 Walding Ober\u00f6sterreich 4111",
    "addr:housenumber":"24",
    "addr:postcode":"4111",
    "addr:street":"Lifehausstr",
    "iso:country":"AT",
    "sg:address":"Lifehausstr 24",
    "sg:city":"Walding",
    "sg:orig_category":"Psychotherapie",
    "sg:phone":"+43 7234 83220",
    "sg:postcode":"4111",
    "sg:province":"Ober\u00f6sterreich",
    "wof:name":"Schallauer Maximilian Dr",
    "wof:placetype":"venue"
},
  "geometry": {"coordinates":[14.1624689102,48.3593902588],"type":"Point"}
}