{
  "type": "Feature",
  "properties": {
    "addr:full":"Stadlerstr 19 Linz Ober\u00f6sterreich 4020",
    "addr:housenumber":"19",
    "addr:postcode":"4020",
    "addr:street":"Stadlerstr",
    "iso:country":"AT",
    "sg:address":"Stadlerstr 19",
    "sg:city":"Linz",
    "sg:orig_category":"Tabaktrafiken",
    "sg:phone":"+43 732 342489",
    "sg:postcode":"4020",
    "sg:province":"Ober\u00f6sterreich",
    "wof:name":"Lummerstorfer Karl",
    "wof:placetype":"venue"
},
  "geometry": {"coordinates":[14.2920799255,48.2693862915],"type":"Point"}
}