{
  "type": "Feature",
  "properties": {
    "addr:full":"Hauptstr 10 Siegendorf im Burgenland Burgenland 7011",
    "addr:housenumber":"10",
    "addr:postcode":"7011",
    "addr:street":"Hauptstr",
    "iso:country":"AT",
    "sg:address":"Hauptstr 10",
    "sg:city":"Siegendorf im Burgenland",
    "sg:orig_category":"Tankstellen",
    "sg:phone":"+43 4326 8748104",
    "sg:postcode":"7011",
    "sg:province":"Burgenland",
    "wof:name":"Disk -Tankstelle",
    "wof:placetype":"venue"
},
  "geometry": {"coordinates":[16.5141143799,47.764541626],"type":"Point"}
}