{
  "type": "Feature",
  "properties": {
    "iso:country":"AT",
    "sg:address":"Schulg 11",
    "sg:city":"Dornbirn",
    "sg:orig_category":"Boutiquen",
    "sg:phone":"+43 5572 27260",
    "sg:postcode":"6850",
    "sg:province":"Vorarlberg",
    "wof:name":"Boutique Cecil",
    "wof:placetype":"venue"
},
  "geometry": {"coordinates":[9.7409343719,47.4124107361],"type":"Point"}
}