{
  "type": "Feature",
  "properties": {
    "addr:full":"Josef Hiebl-Str 14 Hausmening Nieder\u00f6sterreich 3363",
    "addr:housenumber":"14",
    "addr:postcode":"3363",
    "iso:country":"AT",
    "sg:address":"Josef Hiebl-Str 14",
    "sg:city":"Hausmening",
    "sg:orig_category":"Feuerwehren",
    "sg:phone":"+43 7475 522220",
    "sg:postcode":"3363",
    "sg:province":"Nieder\u00f6sterreich",
    "wof:name":"Freiwillige Feuerwehr Ulmerfeld-Hausmening",
    "wof:placetype":"venue"
},
  "geometry": {"coordinates":[14.8137149811,48.0781707764],"type":"Point"}
}