{
  "type": "Feature",
  "properties": {
    "iso:country":"AT",
    "sg:address":"Schmiedg 14",
    "sg:city":"Zeltweg",
    "sg:orig_category":"Bauunternehmen",
    "sg:phone":"+43 3577 22235",
    "sg:postcode":"8740",
    "sg:province":"Steiermark",
    "wof:name":"STRABAG AG",
    "wof:placetype":"venue"
},
  "geometry": {"coordinates":[14.7447319031,47.1931610107],"type":"Point"}
}