{
  "type": "Feature",
  "properties": {
    "addr:full":"Anningerstr 27 Guntramsdorf Nieder\u00f6sterreich 2353",
    "addr:housenumber":"27",
    "addr:postcode":"2353",
    "addr:street":"Anningerstr",
    "iso:country":"AT",
    "sg:address":"Anningerstr 27",
    "sg:city":"Guntramsdorf",
    "sg:orig_category":"Handelsagenturen",
    "sg:phone":"+43 2236 52228",
    "sg:postcode":"2353",
    "sg:province":"Nieder\u00f6sterreich",
    "wof:name":"Schmid Karl",
    "wof:placetype":"venue"
},
  "geometry": {"coordinates":[16.3042831421,48.0496139526],"type":"Point"}
}