{
  "type": "Feature",
  "properties": {
    "addr:full":"Vordere Achm\u00fchlerstr 11 Dornbirn Vorarlberg 6850",
    "addr:housenumber":"11",
    "addr:postcode":"6850",
    "addr:street":"Vordere Achmuehlerstr",
    "iso:country":"AT",
    "sg:address":"Vordere Achm\u00fchlerstr 11",
    "sg:city":"Dornbirn",
    "sg:orig_category":"Blumeneinzelhandel",
    "sg:phone":"+43 5572 22744",
    "sg:postcode":"6850",
    "sg:province":"Vorarlberg",
    "wof:name":"F\u00e4ssler Christoph",
    "wof:placetype":"venue"
},
  "geometry": {"coordinates":[9.7437801361,47.4131889343],"type":"Point"}
}