{
  "type": "Feature",
  "properties": {
    "iso:country":"AT",
    "sg:address":"Luckenberg 2",
    "sg:city":"Gunskirchen",
    "sg:orig_category":"Fische U Fischwaren / Erzeugung U Gro\u00c3\u0178handel",
    "sg:phone":"+43 7246 6386",
    "sg:postcode":"4623",
    "sg:province":"Ober\u00f6sterreich",
    "wof:name":"Holzinger Fischverarbeitungs GesmbH",
    "wof:placetype":"venue"
},
  "geometry": {"coordinates":[13.9017410278,48.1260871887],"type":"Point"}
}