{
  "type": "Feature",
  "properties": {
    "addr:full":"Unterlungitz 26 Hartberg Steiermark 8230",
    "addr:housenumber":"26",
    "addr:postcode":"8230",
    "addr:street":"Unterlungitz",
    "iso:country":"AT",
    "sg:address":"Unterlungitz 26",
    "sg:city":"Hartberg",
    "sg:classifiers":[
        {
            "category":"Military Area",
            "subcategory":"Air Force Base",
            "type":"Public Place"
        }
    ],
    "sg:phone":"+43 3332 65161",
    "sg:postcode":"8230",
    "sg:province":"Steiermark",
    "sg:tags":[
        "dock",
        "leveller",
        "ramp",
        "loading"
    ],
    "sg:website":"starlever.com",
    "wof:name":"STARLEVER Produktions- und Vertriebs Ges.b.m.H.",
    "wof:placetype":"venue"
},
  "geometry": {"coordinates":[15.9727478027,47.2819519043],"type":"Point"}
}