{
  "type": "Feature",
  "properties": {
    "addr:full":"Hafeng 20/11 Wien Wien 1030",
    "addr:housenumber":"20 / 11",
    "addr:postcode":"1030",
    "addr:street":"Hafeng",
    "iso:country":"AT",
    "sg:address":"Hafeng 20/11",
    "sg:city":"Wien",
    "sg:orig_category":"Tonstudios",
    "sg:phone":"+43 4317 980245",
    "sg:postcode":"1030",
    "sg:province":"Wien",
    "sg:website":"unartproduktion.at",
    "wof:name":"UnartProduktion Bild- u Tontr\u00e4gerproduktion Gauls Kinderlieder",
    "wof:placetype":"venue"
},
  "geometry": {"coordinates":[16.3937187195,48.1919555664],"type":"Point"}
}