{
  "type": "Feature",
  "properties": {
    "iso:country":"AT",
    "sg:address":"Ludwig-Walter-Strasse 26a",
    "sg:city":"Villach",
    "sg:classifiers":[
        {
            "category":"Manufacturing",
            "subcategory":"Wood Products",
            "type":"Manufacturing & Wholesale Goods"
        }
    ],
    "sg:phone":"+43 4242 431070",
    "sg:postcode":"9500",
    "sg:province":"K\u00e4rnten",
    "sg:tags":[
        "gate",
        "made",
        "door"
    ],
    "wof:name":"Abau Parkettmarkt in Villach Sternig & Gallob GmbH",
    "wof:placetype":"venue"
},
  "geometry": {"coordinates":[13.8525867462,46.6076393127],"type":"Point"}
}