{
  "type": "Feature",
  "properties": {
    "addr:full":"Untergrubstr 20 Elixhausen Salzburg 5161",
    "addr:housenumber":"20",
    "addr:postcode":"5161",
    "addr:street":"Untergrubstr;Salzburg",
    "iso:country":"AT",
    "sg:address":"Untergrubstr 20",
    "sg:city":"Elixhausen",
    "sg:orig_category":"Installationsunternehmen, Dachdeckereien",
    "sg:phone":"+43 662 480276",
    "sg:postcode":"5161",
    "sg:province":"Salzburg",
    "sg:website":"andreas-kreiseder.at",
    "wof:name":"Kreiseder Andreas GesmbH & Co KG",
    "wof:placetype":"venue"
},
  "geometry": {"coordinates":[13.0679979324,47.8656196594],"type":"Point"}
}