{
  "type": "Feature",
  "properties": {
    "addr:full":"Ungerfeldg 15 Kindberg Steiermark 8650",
    "addr:housenumber":"15",
    "addr:postcode":"8650",
    "addr:street":"Ungerfeldg",
    "iso:country":"AT",
    "sg:address":"Ungerfeldg 15",
    "sg:city":"Kindberg",
    "sg:orig_category":"Sportschulen",
    "sg:phone":"+43 676 5136080",
    "sg:postcode":"8650",
    "sg:province":"Steiermark",
    "wof:name":"WingTsun Selbstverteidigungsschulen",
    "wof:placetype":"venue"
},
  "geometry": {"coordinates":[15.4422693253,47.5013809204],"type":"Point"}
}