{
  "type": "Feature",
  "properties": {
    "addr:full":"Kaserneng 6 St. Magdalen K\u00e4rnten 9524",
    "addr:housenumber":"6",
    "addr:postcode":"9524",
    "addr:street":"Kaserneng;Kaernten",
    "iso:country":"AT",
    "sg:address":"Kaserneng 6",
    "sg:city":"St. Magdalen",
    "sg:orig_category":"Armaturen / Erzeugung U Gro\u00c3\u0178handel",
    "sg:phone":"+43 4342 42411810",
    "sg:postcode":"9524",
    "sg:province":"K\u00e4rnten",
    "wof:name":"Schmidt Armaturen Zweigniederlassung der Flowserve (Austria) GmbH",
    "wof:placetype":"venue"
},
  "geometry": {"coordinates":[13.9121189117,46.6102218628],"type":"Point"}
}