{
  "type": "Feature",
  "properties": {
    "iso:country":"AT",
    "sg:address":"Nr 37",
    "sg:city":"Anger",
    "sg:orig_category":"Tabaktrafiken",
    "sg:phone":"+43 3175 2228",
    "sg:postcode":"8184",
    "sg:province":"Steiermark",
    "wof:name":"Felberbauer Christine",
    "wof:placetype":"venue"
},
  "geometry": {"coordinates":[15.7057800293,47.2626419067],"type":"Point"}
}