{
  "type": "Feature",
  "properties": {
    "iso:country":"AT",
    "sg:address":"Rosenh\u00fcgelstr 19",
    "sg:city":"Wien",
    "sg:orig_category":"Juweliere, Gold- U Silberschmiede",
    "sg:phone":"+43 1 8037160",
    "sg:postcode":"1120",
    "sg:province":"Wien",
    "wof:name":"Reichhart Sandra",
    "wof:placetype":"venue"
},
  "geometry": {"coordinates":[16.3290939331,48.1824874878],"type":"Point"}
}