{
  "type": "Feature",
  "properties": {
    "iso:country":"AT",
    "sg:address":"Europapl 2",
    "sg:city":"Linz",
    "sg:orig_category":"Werbeagenturen",
    "sg:phone":"+43 732 348635",
    "sg:postcode":"4020",
    "sg:province":"Ober\u00f6sterreich",
    "wof:name":"Wazek Agentur f Werbung und Marketing",
    "wof:placetype":"venue"
},
  "geometry": {"coordinates":[14.3035211563,48.2988967896],"type":"Point"}
}