{
  "type": "Feature",
  "properties": {
    "addr:full":"Rosenhof 26p Pertisau Tirol 6213",
    "addr:housenumber":"26p",
    "addr:postcode":"6213",
    "addr:street":"Rosenhof",
    "iso:country":"AT",
    "sg:address":"Rosenhof 26p",
    "sg:city":"Pertisau",
    "sg:orig_category":"Tischlereien",
    "sg:phone":"+43 4366 44468443",
    "sg:postcode":"6213",
    "sg:province":"Tirol",
    "wof:name":"Wiedemann Herbert",
    "wof:placetype":"venue"
},
  "geometry": {"coordinates":[11.6961479187,47.4396896362],"type":"Point"}
}