{
  "type": "Feature",
  "properties": {
    "addr:full":"Siedlerzeile 3 Thening Ober\u00f6sterreich 4062",
    "addr:housenumber":"3",
    "addr:postcode":"4062",
    "addr:street":"Siedlerzeile;Oberoesterreich",
    "iso:country":"AT",
    "sg:address":"Siedlerzeile 3",
    "sg:city":"Thening",
    "sg:classifiers":[
        {
            "category":"Communications",
            "subcategory":"Television Station",
            "type":"Services"
        }
    ],
    "sg:phone":"+43 676 5103678",
    "sg:postcode":"4062",
    "sg:province":"Ober\u00f6sterreich",
    "sg:tags":[
        "picture",
        "archive",
        "digital"
    ],
    "sg:website":"bilderbox.de",
    "wof:name":"Bildagentur Bilder Box",
    "wof:placetype":"venue"
},
  "geometry": {"coordinates":[14.1671743393,48.2550582886],"type":"Point"}
}