{
  "type": "Feature",
  "properties": {
    "addr:full":"Glaserweg 25 Lustenau Vorarlberg 6890",
    "addr:housenumber":"25",
    "addr:postcode":"6890",
    "addr:street":"Glaserweg",
    "iso:country":"AT",
    "sg:address":"Glaserweg 25",
    "sg:city":"Lustenau",
    "sg:orig_category":"Abschleppdienste",
    "sg:phone":"+43 4355 7783281",
    "sg:postcode":"6890",
    "sg:province":"Vorarlberg",
    "wof:name":"V\u00f6gel Helmut KG",
    "wof:placetype":"venue"
},
  "geometry": {"coordinates":[9.6655902863,47.4166297913],"type":"Point"}
}