{
  "type": "Feature",
  "properties": {
    "iso:country":"AT",
    "sg:address":"Steigenteschg",
    "sg:city":"Wien",
    "sg:orig_category":"Sportanlagen",
    "sg:phone":"+43 1 2036109",
    "sg:postcode":"1220",
    "sg:province":"Wien",
    "wof:name":"Sportanlage d Stadt Wien (MA 51) ,Meissnerstr-Steigenteschg",
    "wof:placetype":"venue"
},
  "geometry": {"coordinates":[16.4377555847,48.2462615967],"type":"Point"}
}