{
  "type": "Feature",
  "properties": {
    "addr:full":"Kreuzstr 13 Treibach-Althofen K\u00e4rnten 9330",
    "addr:housenumber":"13",
    "addr:postcode":"9330",
    "addr:street":"Kreuzstr;Kaernten",
    "iso:country":"AT",
    "sg:address":"Kreuzstr 13",
    "sg:city":"Treibach-Althofen",
    "sg:orig_category":"Damenmoden",
    "sg:phone":"+43 4262 2137",
    "sg:postcode":"9330",
    "sg:province":"K\u00e4rnten",
    "wof:name":"Damenmoden Berger",
    "wof:placetype":"venue"
},
  "geometry": {"coordinates":[14.4693078995,46.8707351685],"type":"Point"}
}