{
  "type": "Feature",
  "properties": {
    "addr:full":"Am Zunderfeld 12 Wilhering Ober\u00f6sterreich 4073",
    "addr:housenumber":"12",
    "addr:postcode":"4073",
    "addr:street":"Am Zunderfeld",
    "iso:country":"AT",
    "sg:address":"Am Zunderfeld 12",
    "sg:city":"Wilhering",
    "sg:orig_category":"Ingenieurkonsulenten / Zivilingenieure",
    "sg:phone":"+43 7274 7888",
    "sg:postcode":"4073",
    "sg:province":"Ober\u00f6sterreich",
    "wof:name":"Kutzenberger Harald Dipl-Ing",
    "wof:placetype":"venue"
},
  "geometry": {"coordinates":[14.154630661,48.2829666138],"type":"Point"}
}