{
  "type": "Feature",
  "properties": {
    "iso:country":"AT",
    "sg:address":"Himberger Str 11",
    "sg:city":"Schwechat",
    "sg:orig_category":"Tanzschulen",
    "sg:phone":"+43 664 2411358",
    "sg:postcode":"2320",
    "sg:province":"Nieder\u00f6sterreich",
    "sg:website":"schellander.net",
    "wof:name":"Tanzschule Schellander",
    "wof:placetype":"venue"
},
  "geometry": {"coordinates":[16.4756145477,48.1376075745],"type":"Point"}
}