{
  "type": "Feature",
  "properties": {
    "iso:country":"AT",
    "sg:address":"R\u00f6merstr 22",
    "sg:city":"Brixlegg",
    "sg:orig_category":"Friseure U Frisiersalons",
    "sg:phone":"+43 5337 62748",
    "sg:postcode":"6230",
    "sg:province":"Tirol",
    "wof:name":"Schiferer Erich",
    "wof:placetype":"venue"
},
  "geometry": {"coordinates":[11.8808231354,47.4292221069],"type":"Point"}
}