{
  "type": "Feature",
  "properties": {
    "addr:full":"Felderg 47 Klosterneuburg Nieder\u00f6sterreich 3400",
    "addr:housenumber":"47",
    "addr:postcode":"3400",
    "addr:street":"Felderg;Niederoesterreich",
    "iso:country":"AT",
    "sg:address":"Felderg 47",
    "sg:city":"Klosterneuburg",
    "sg:orig_category":"Ingenieurkonsulenten / Zivilingenieure",
    "sg:phone":"+43 664 3830775",
    "sg:postcode":"3400",
    "sg:province":"Nieder\u00f6sterreich",
    "wof:name":"Beitl Markus Dipl-Ing",
    "wof:placetype":"venue"
},
  "geometry": {"coordinates":[16.3191204071,48.2921676636],"type":"Point"}
}