{
  "type": "Feature",
  "properties": {
    "addr:full":"Reitherspitzstr 577 Seefeld in Tirol Tirol 6100",
    "addr:housenumber":"577",
    "addr:postcode":"6100",
    "addr:street":"Seefeld;Tirol",
    "iso:country":"AT",
    "sg:address":"Reitherspitzstr 577",
    "sg:city":"Seefeld in Tirol",
    "sg:orig_category":"Pensionen / Privatzimmer",
    "sg:phone":"+43 4352 122988",
    "sg:postcode":"6100",
    "sg:province":"Tirol",
    "wof:name":"Haus Lia",
    "wof:placetype":"venue"
},
  "geometry": {"coordinates":[11.1961679459,47.3264656067],"type":"Point"}
}