{
  "type": "Feature",
  "properties": {
    "addr:full":"Neulerchenfelder Str 75 Wien Wien 1160",
    "addr:postcode":"1160",
    "addr:street":"Str 75",
    "iso:country":"AT",
    "sg:address":"Neulerchenfelder Str 75",
    "sg:city":"Wien",
    "sg:orig_category":"Lebensmittel / Einzelhandel",
    "sg:phone":"+43 1 4804521",
    "sg:postcode":"1160",
    "sg:province":"Wien",
    "wof:name":"Billa AG",
    "wof:placetype":"venue"
},
  "geometry": {"coordinates":[16.3292827606,48.2120094299],"type":"Point"}
}