{
  "type": "Feature",
  "properties": {
    "iso:country":"AT",
    "sg:address":"Schopperweg 17",
    "sg:city":"Oberndorf",
    "sg:orig_category":"Installationsunternehmen",
    "sg:phone":"+43 4362 7242960",
    "sg:postcode":"5110",
    "sg:province":"Salzburg",
    "wof:name":"Wolf Walter",
    "wof:placetype":"venue"
},
  "geometry": {"coordinates":[12.9324121475,47.9407920837],"type":"Point"}
}