{
  "type": "Feature",
  "properties": {
    "iso:country":"AT",
    "sg:address":"Nr 146",
    "sg:city":"Alland",
    "sg:classifiers":[
        {
            "category":"Health Services",
            "subcategory":"Nursing And Care Facility",
            "type":"Services"
        }
    ],
    "sg:phone":"+43 2258 26300",
    "sg:postcode":"2534",
    "sg:province":"Nieder\u00f6sterreich",
    "sg:tags":[
        "rehabilitation"
    ],
    "wof:name":"Rehabilitationszentrum f Diabetiker d PensionsVersAnstalt d Arbeiter Alland",
    "wof:placetype":"venue"
},
  "geometry": {"coordinates":[16.0783996582,48.0584259033],"type":"Point"}
}