{
  "type": "Feature",
  "properties": {
    "iso:country":"AT",
    "sg:address":"Nr 71",
    "sg:city":"Gr\u00fcnbach",
    "sg:orig_category":"Gemeinden",
    "sg:phone":"+43 4379 42728130",
    "sg:postcode":"4264",
    "sg:province":"Ober\u00f6sterreich",
    "wof:name":"Gemeindeamt Gr\u00fcnbach",
    "wof:placetype":"venue"
},
  "geometry": {"coordinates":[166.9221496582,-0.5282999873],"type":"Point"}
}