{
  "type": "Feature",
  "properties": {
    "iso:country":"AT",
    "sg:address":"Drorygasse 21",
    "sg:city":"Wien",
    "sg:orig_category":"Finanzen, Versicherungen",
    "sg:postcode":"1030",
    "sg:province":"Wien",
    "sg:website":"http://www.wu-wien.ac.at/usr/h88/h8851631/",
    "wof:name":"Versicherungsb\u00fcro BAKIR & KUPFER",
    "wof:placetype":"venue"
},
  "geometry": {"coordinates":[16.4042892456,48.198474884],"type":"Point"}
}