{
  "type": "Feature",
  "properties": {
    "addr:full":"Wolfgangg 33 Wien Wien 1120",
    "addr:housenumber":"33",
    "addr:postcode":"1120",
    "addr:street":"Wolfgangg",
    "iso:country":"AT",
    "sg:address":"Wolfgangg 33",
    "sg:city":"Wien",
    "sg:orig_category":"Exporteure U Importeure",
    "sg:phone":"+43 664 1822821",
    "sg:postcode":"1120",
    "sg:province":"Wien",
    "wof:name":"Contrad Austria Ing Gabriel Nader",
    "wof:placetype":"venue"
},
  "geometry": {"coordinates":[16.3433094025,48.1819343567],"type":"Point"}
}