{
  "type": "Feature",
  "properties": {
    "addr:full":"Hans-Brenner-Weg 15 Telfs Tirol 6410",
    "addr:housenumber":"15",
    "addr:postcode":"6410",
    "addr:street":"Hans-Brenner-Weg;Tirol",
    "iso:country":"AT",
    "sg:address":"Hans-Brenner-Weg 15",
    "sg:city":"Telfs",
    "sg:orig_category":"Psychotherapie",
    "sg:phone":"+43 4352 6263786",
    "sg:postcode":"6410",
    "sg:province":"Tirol",
    "wof:name":"Ernst Werner Univ Prof Mag DDr",
    "wof:placetype":"venue"
},
  "geometry": {"coordinates":[11.0647649765,47.3086585999],"type":"Point"}
}