{
  "type": "Feature",
  "properties": {
    "addr:full":"Marktpl 4 Wies Steiermark 8551",
    "addr:housenumber":"4",
    "addr:postcode":"8551",
    "addr:street":"Marktpl",
    "iso:country":"AT",
    "sg:address":"Marktpl 4",
    "sg:city":"Wies",
    "sg:orig_category":"Musikunterricht",
    "sg:phone":"+43 3465 3344",
    "sg:postcode":"8551",
    "sg:province":"Steiermark",
    "wof:name":"Musikschule",
    "wof:placetype":"venue"
},
  "geometry": {"coordinates":[15.2704257965,46.718372345],"type":"Point"}
}