{
  "type": "Feature",
  "properties": {
    "addr:full":"Antiesenweg 28 Aurolzm\u00fcnster Ober\u00f6sterreich 4971",
    "addr:housenumber":"28",
    "addr:postcode":"4971",
    "addr:street":"Antiesenweg;Oberoesterreich",
    "iso:country":"AT",
    "sg:address":"Antiesenweg 28",
    "sg:city":"Aurolzm\u00fcnster",
    "sg:orig_category":"Fenster",
    "sg:phone":"+43 7752 80999",
    "sg:postcode":"4971",
    "sg:province":"Ober\u00f6sterreich",
    "wof:name":"Huemer Thomas",
    "wof:placetype":"venue"
},
  "geometry": {"coordinates":[13.4587993622,48.2443962097],"type":"Point"}
}