{
  "type": "Feature",
  "properties": {
    "addr:full":"Nr 128 Waldenstein Nieder\u00f6sterreich 3961",
    "addr:postcode":"3961",
    "addr:street":"Nr;Waldenstein Niederoesterreich",
    "iso:country":"AT",
    "sg:address":"Nr 128",
    "sg:city":"Waldenstein",
    "sg:orig_category":"Unternehmensberatung",
    "sg:phone":"+43 664 9214716",
    "sg:postcode":"3961",
    "sg:province":"Nieder\u00f6sterreich",
    "wof:name":"HASITA Unternehmensberatungs GmbH",
    "wof:placetype":"venue"
},
  "geometry": {"coordinates":[15.0196552277,48.7288703918],"type":"Point"}
}