{
  "type": "Feature",
  "properties": {
    "addr:full":"Innsbrucker Str 464 Scharnitz Tirol 6108",
    "addr:housenumber":"464",
    "addr:postcode":"6108",
    "addr:street":"Scharnitz Tirol",
    "iso:country":"AT",
    "sg:address":"Innsbrucker Str 464",
    "sg:city":"Scharnitz",
    "sg:orig_category":"Tankstellen",
    "sg:phone":"+43 4352 13201822",
    "sg:postcode":"6108",
    "sg:province":"Tirol",
    "wof:name":"Reinpold Walter SB Tanken & Waschen",
    "wof:placetype":"venue"
},
  "geometry": {"coordinates":[11.2620210648,47.3881416321],"type":"Point"}
}