{
  "type": "Feature",
  "properties": {
    "addr:full":"Grazer Str 4 Kapfenberg Steiermark 8605",
    "addr:housenumber":"4",
    "addr:postcode":"8605",
    "addr:street":"Str",
    "iso:country":"AT",
    "sg:address":"Grazer Str 4",
    "sg:city":"Kapfenberg",
    "sg:orig_category":"Restaurants: Chinesisch",
    "sg:phone":"+43 4338 6221628",
    "sg:postcode":"8605",
    "sg:province":"Steiermark",
    "wof:name":"Drache & Ph\u00f6nix",
    "wof:placetype":"venue"
},
  "geometry": {"coordinates":[15.2887201309,47.4389572144],"type":"Point"}
}