{
  "type": "Feature",
  "properties": {
    "addr:full":"Paulustorg 5 Graz Steiermark 8010",
    "addr:housenumber":"5",
    "addr:postcode":"8010",
    "addr:street":"Paulustorg",
    "iso:country":"AT",
    "sg:address":"Paulustorg 5",
    "sg:city":"Graz",
    "sg:orig_category":"Altwaren",
    "sg:phone":"+43 316 845443",
    "sg:postcode":"8010",
    "sg:province":"Steiermark",
    "wof:name":"Alt Paulustor",
    "wof:placetype":"venue"
},
  "geometry": {"coordinates":[15.4398126602,47.074256897],"type":"Point"}
}