{
  "type": "Feature",
  "properties": {
    "addr:full":"Arzill 41 Imst Tirol 6460",
    "addr:housenumber":"41",
    "addr:postcode":"6460",
    "addr:street":"Arzill;Tirol",
    "iso:country":"AT",
    "sg:address":"Arzill 41",
    "sg:city":"Imst",
    "sg:orig_category":"Freizeit, Spiel U Spa\u00c3\u0178",
    "sg:phone":"+43 4354 12660",
    "sg:postcode":"6460",
    "sg:province":"Tirol",
    "sg:website":"http://www.tirolnet.co.at/ah/ski/ski.htm",
    "wof:name":"Skigebiete in \u00d6sterreich",
    "wof:placetype":"venue"
},
  "geometry": {"coordinates":[10.7471818924,47.2354927063],"type":"Point"}
}