{
  "type": "Feature",
  "properties": {
    "addr:full":"Am Ru\u00dfbach 1 Schleinbach Nieder\u00f6sterreich 2123",
    "addr:housenumber":"1",
    "addr:postcode":"2123",
    "addr:street":"Am Russbach",
    "iso:country":"AT",
    "sg:address":"Am Ru\u00dfbach 1",
    "sg:city":"Schleinbach",
    "sg:orig_category":"Flaschen",
    "sg:phone":"+43 4322 4520180",
    "sg:postcode":"2123",
    "sg:province":"Nieder\u00f6sterreich",
    "wof:name":"Kugler Verschl\u00fcsse",
    "wof:placetype":"venue"
},
  "geometry": {"coordinates":[16.4917793274,48.446018219],"type":"Point"}
}