{
  "type": "Feature",
  "properties": {
    "addr:full":"Malchbachg 29 Imst Tirol 6460",
    "addr:housenumber":"29",
    "addr:postcode":"6460",
    "addr:street":"Malchbachg;Tirol",
    "iso:country":"AT",
    "sg:address":"Malchbachg 29",
    "sg:city":"Imst",
    "sg:orig_category":"Futtermittel",
    "sg:phone":"+43 5412 63343",
    "sg:postcode":"6460",
    "sg:province":"Tirol",
    "wof:name":"Gasser Richard",
    "wof:placetype":"venue"
},
  "geometry": {"coordinates":[10.7372846603,47.2450141907],"type":"Point"}
}