{
  "type": "Feature",
  "properties": {
    "addr:full":"Wassergasse 1 Ternitz Nieder\u00f6sterreich 2630",
    "addr:housenumber":"1",
    "addr:postcode":"2630",
    "addr:street":"Wassergasse",
    "iso:country":"AT",
    "sg:address":"Wassergasse 1",
    "sg:city":"Ternitz",
    "sg:classifiers":[
        {
            "category":"Wholesale",
            "subcategory":"Metals & Minerals",
            "type":"Manufacturing & Wholesale Goods"
        }
    ],
    "sg:phone":"+43 2630 351700",
    "sg:postcode":"2630",
    "sg:province":"Nieder\u00f6sterreich",
    "sg:tags":[
        "band",
        "blade",
        "saw",
        "machining"
    ],
    "sg:website":"amada.at",
    "wof:name":"Amada Austria GmbH",
    "wof:placetype":"venue"
},
  "geometry": {"coordinates":[16.0410747528,47.7151870728],"type":"Point"}
}