{
  "type": "Feature",
  "properties": {
    "addr:full":"Unterer Markt 12 Gresten Nieder\u00f6sterreich 3264",
    "addr:housenumber":"12",
    "addr:postcode":"3264",
    "addr:street":"Unterer Markt",
    "iso:country":"AT",
    "sg:address":"Unterer Markt 12",
    "sg:city":"Gresten",
    "sg:orig_category":"Unterhaltungselektronik / Einzelhandel",
    "sg:phone":"+43 7487 2730",
    "sg:postcode":"3264",
    "sg:province":"Nieder\u00f6sterreich",
    "wof:name":"Beck Wilhelm",
    "wof:placetype":"venue"
},
  "geometry": {"coordinates":[15.0263528824,47.9838066101],"type":"Point"}
}