{
  "type": "Feature",
  "properties": {
    "iso:country":"AT",
    "sg:address":"Brixentaler Str 61",
    "sg:city":"W\u00f6rgl",
    "sg:orig_category":"Lebensmittel / Einzelhandel",
    "sg:phone":"+43 5332 748970",
    "sg:postcode":"6300",
    "sg:province":"Tirol",
    "wof:name":"SPAR \u00f6sterreichische Warenhandels-AG",
    "wof:placetype":"venue"
},
  "geometry": {"coordinates":[-69.3131027222,-51.6091995239],"type":"Point"}
}