{
  "type": "Feature",
  "properties": {
    "addr:full":"Oberer Stadtpl 16 Kufstein Tirol 6330",
    "addr:housenumber":"16",
    "addr:postcode":"6330",
    "addr:street":"Oberer Stadtpl;Tirol",
    "iso:country":"AT",
    "sg:address":"Oberer Stadtpl 16",
    "sg:city":"Kufstein",
    "sg:orig_category":"Handarbeiten",
    "sg:phone":"+43 5372 62362",
    "sg:postcode":"6330",
    "sg:province":"Tirol",
    "wof:name":"Handarbeitsinsel Edmund Weickenmeier",
    "wof:placetype":"venue"
},
  "geometry": {"coordinates":[12.170343399,47.5821914673],"type":"Point"}
}