{
  "type": "Feature",
  "properties": {
    "addr:full":"Dreihackeng 4 Wien Wien 1090",
    "addr:housenumber":"4",
    "addr:postcode":"1090",
    "addr:street":"Dreihackeng",
    "iso:country":"AT",
    "sg:address":"Dreihackeng 4",
    "sg:city":"Wien",
    "sg:orig_category":"Psychologen",
    "sg:phone":"+43 1 3197970",
    "sg:postcode":"1090",
    "sg:province":"Wien",
    "wof:name":"Tomicich Gabriele Mag",
    "wof:placetype":"venue"
},
  "geometry": {"coordinates":[16.3546409607,48.226184845],"type":"Point"}
}