{
  "type": "Feature",
  "properties": {
    "iso:country":"AT",
    "sg:address":"Niedernhaag 31",
    "sg:city":"Haag am Hausruck",
    "sg:classifiers":[
        {
            "category":"Shopping",
            "type":"Retail Goods"
        }
    ],
    "sg:phone":"+43 4377 3241410",
    "sg:postcode":"4680",
    "sg:province":"Ober\u00f6sterreich",
    "sg:tags":[
        "finished",
        "-",
        "metallic"
    ],
    "wof:name":"MKW-IOT GMBH",
    "wof:placetype":"venue"
},
  "geometry": {"coordinates":[13.6544837952,48.1915779114],"type":"Point"}
}