{
  "type": "Feature",
  "properties": {
    "iso:country":"AT",
    "sg:address":"Treiet 5 ",
    "sg:city":"Klaus-Weiler",
    "sg:classifiers":[
        {
            "category":"Food & Beverages",
            "subcategory":"Groceries & Convenience Stores",
            "type":"Retail Goods"
        }
    ],
    "sg:phone":"+43 4355 2362442",
    "sg:postcode":"6833",
    "sg:province":"Vorarlberg",
    "sg:tags":[
        "product",
        "related"
    ],
    "wof:name":"GEORG MANGOLD KG",
    "wof:placetype":"venue"
},
  "geometry": {"coordinates":[9.6477680206,47.3043441772],"type":"Point"}
}