{
  "type": "Feature",
  "properties": {
    "addr:full":"Linzer Str 272 Wien Wien 1140",
    "addr:housenumber":"272",
    "addr:postcode":"1140",
    "addr:street":"Linzer Str",
    "iso:country":"AT",
    "sg:address":"Linzer Str 272",
    "sg:city":"Wien",
    "sg:orig_category":"Elektroinstallationsunternehmen",
    "sg:phone":"+43 1 4165500",
    "sg:postcode":"1140",
    "sg:province":"Wien",
    "wof:name":"Elektro Koffler GesmbH",
    "wof:placetype":"venue"
},
  "geometry": {"coordinates":[16.2781734467,48.1962890625],"type":"Point"}
}