{
  "type": "Feature",
  "properties": {
    "addr:full":"Stelzhamerstr 1A Steyr Ober\u00f6sterreich 4400",
    "addr:housenumber":"1a",
    "addr:postcode":"4400",
    "addr:street":"Stelzhamerstr;Oberoesterreich",
    "iso:country":"AT",
    "sg:address":"Stelzhamerstr 1A",
    "sg:city":"Steyr",
    "sg:classifiers":[
        {
            "category":"Organizations",
            "subcategory":"Political Organization",
            "type":"Services"
        }
    ],
    "sg:phone":"+43 4372 5242266",
    "sg:postcode":"4400",
    "sg:province":"Ober\u00f6sterreich",
    "sg:tags":[
        "mediation"
    ],
    "wof:name":"Poduschka AnwaltsGmbH",
    "wof:placetype":"venue"
},
  "geometry": {"coordinates":[14.4115829468,48.0366363525],"type":"Point"}
}