{
  "type": "Feature",
  "properties": {
    "addr:full":"Reuchlinstr 35a Linz Ober\u00f6sterreich 4020",
    "addr:housenumber":"35a",
    "addr:postcode":"4020",
    "addr:street":"Reuchlinstr",
    "iso:country":"AT",
    "sg:address":"Reuchlinstr 35a",
    "sg:city":"Linz",
    "sg:orig_category":"Steuerberatung",
    "sg:phone":"+43 4373 26063610",
    "sg:postcode":"4020",
    "sg:province":"Ober\u00f6sterreich",
    "wof:name":"MGI Linz Steuerberatung GmbH",
    "wof:placetype":"venue"
},
  "geometry": {"coordinates":[14.2956008911,48.2827796936],"type":"Point"}
}