{
  "type": "Feature",
  "properties": {
    "iso:country":"AT",
    "sg:address":"Ferdinand Hanusch-Pl 1/302",
    "sg:city":"Salzburg",
    "sg:orig_category":"Finanz- U Wirtschaftsberatung",
    "sg:phone":"+43 662 652021",
    "sg:postcode":"5020",
    "sg:province":"Salzburg",
    "wof:name":"Licon Liquid Consulting GmbH",
    "wof:placetype":"venue"
},
  "geometry": {"coordinates":[13.0423240662,47.8124580383],"type":"Point"}
}