{
  "type": "Feature",
  "properties": {
    "addr:full":"Quellenstr 111 Wien Wien 1100",
    "addr:housenumber":"111",
    "addr:postcode":"1100",
    "iso:country":"AT",
    "sg:address":"Quellenstr 111",
    "sg:city":"Wien",
    "sg:orig_category":"Schleifereien",
    "sg:phone":"+43 1 6073717",
    "sg:postcode":"1100",
    "sg:province":"Wien",
    "wof:name":"Compostella Johann",
    "wof:placetype":"venue"
},
  "geometry": {"coordinates":[16.3780155182,48.1751823425],"type":"Point"}
}