{
  "type": "Feature",
  "properties": {
    "iso:country":"AT",
    "sg:address":"Laubichl 141",
    "sg:city":"Mayrhofen",
    "sg:orig_category":"Pensionen / Privatzimmer",
    "sg:phone":"+43 5285 6293230",
    "sg:postcode":"6290",
    "sg:province":"Tirol",
    "wof:name":"Pension Birkenhof",
    "wof:placetype":"venue"
},
  "geometry": {"coordinates":[11.8669586182,47.1720924377],"type":"Point"}
}