{
  "type": "Feature",
  "properties": {
    "iso:country":"AT",
    "sg:address":"Kaufmannstr 17/21",
    "sg:city":"Innsbruck",
    "sg:orig_category":"Fu\u00c3\u0178pflege U Fu\u00c3\u0178pflegesalons",
    "sg:phone":"+43 4351 2399339",
    "sg:postcode":"6020",
    "sg:province":"Tirol",
    "wof:name":"Fu\u00dfpflege Oase Heide Rupp",
    "wof:placetype":"venue"
},
  "geometry": {"coordinates":[11.416639328,47.2578811646],"type":"Point"}
}