{
  "type": "Feature",
  "properties": {
    "addr:full":"Rotensterng 28 Wien Wien 1020",
    "addr:housenumber":"28",
    "addr:postcode":"1020",
    "addr:street":"Rotensterng",
    "iso:country":"AT",
    "sg:address":"Rotensterng 28",
    "sg:city":"Wien",
    "sg:orig_category":"Betten",
    "sg:phone":"+43 1 2142745",
    "sg:postcode":"1020",
    "sg:province":"Wien",
    "sg:website":"ergonomiestudio.com",
    "wof:name":"Wohnstudio Zeissel",
    "wof:placetype":"venue"
},
  "geometry": {"coordinates":[16.385099411,48.216758728],"type":"Point"}
}