{
  "type": "Feature",
  "properties": {
    "addr:full":"Kempfstr 2 Klagenfurt K\u00e4rnten 9020",
    "addr:housenumber":"2",
    "addr:postcode":"9020",
    "addr:street":"Kempfstr;Kaernten",
    "iso:country":"AT",
    "sg:address":"Kempfstr 2",
    "sg:city":"Klagenfurt",
    "sg:orig_category":"Bilderrahmen",
    "sg:phone":"+43 676 9262627",
    "sg:postcode":"9020",
    "sg:province":"K\u00e4rnten",
    "wof:name":"GM-TECH Style & News",
    "wof:placetype":"venue"
},
  "geometry": {"coordinates":[14.3119678497,46.6185417175],"type":"Point"}
}