{
  "type": "Feature",
  "properties": {
    "addr:full":"Postpl 36 Pfunds Tirol 6542",
    "addr:housenumber":"36",
    "addr:postcode":"6542",
    "addr:street":"Postpl;Tirol",
    "iso:country":"AT",
    "sg:address":"Postpl 36",
    "sg:city":"Pfunds",
    "sg:orig_category":"Friseure U Frisiersalons",
    "sg:phone":"+43 4354 745293",
    "sg:postcode":"6542",
    "sg:province":"Tirol",
    "wof:name":"Kofler Helmut",
    "wof:placetype":"venue"
},
  "geometry": {"coordinates":[10.5369300842,46.9696540833],"type":"Point"}
}