{
  "type": "Feature",
  "properties": {
    "addr:full":"Wiener Str Kapfenberg Steiermark 8605",
    "addr:postcode":"8605",
    "addr:street":"Str",
    "iso:country":"AT",
    "sg:address":"Wiener Str",
    "sg:city":"Kapfenberg",
    "sg:orig_category":"Gewerkschaften",
    "sg:phone":"+43 3862 22649",
    "sg:postcode":"8605",
    "sg:province":"Steiermark",
    "wof:name":"Gewerkschaft Metall-Bergbau-Energie - Ortsgruppe Kapfenberg",
    "wof:placetype":"venue"
},
  "geometry": {"coordinates":[15.3111209869,47.4510612488],"type":"Point"}
}