{
  "type": "Feature",
  "properties": {
    "addr:full":"Nr 91 Abtenau Salzburg 5441",
    "addr:postcode":"5441",
    "addr:street":"Nr 91;Salzburg",
    "iso:country":"AT",
    "sg:address":"Nr 91",
    "sg:city":"Abtenau",
    "sg:orig_category":"Installationsunternehmen",
    "sg:phone":"+43 664 4642101",
    "sg:postcode":"5441",
    "sg:province":"Salzburg",
    "wof:name":"Zwilling Helmut - Installationen",
    "wof:placetype":"venue"
},
  "geometry": {"coordinates":[13.3463459015,47.5636177063],"type":"Point"}
}