{
  "type": "Feature",
  "properties": {
    "addr:full":"Langwiesweg 19 Bergheim Salzburg 5101",
    "addr:housenumber":"19",
    "addr:postcode":"5101",
    "addr:street":"Langwiesweg;Salzburg",
    "iso:country":"AT",
    "sg:address":"Langwiesweg 19",
    "sg:city":"Bergheim",
    "sg:orig_category":"Pensionen / Privatzimmer",
    "sg:phone":"+43 662 454820",
    "sg:postcode":"5101",
    "sg:province":"Salzburg",
    "wof:name":"Haus Lisi",
    "wof:placetype":"venue"
},
  "geometry": {"coordinates":[13.0283203125,47.8381538391],"type":"Point"}
}