{
  "type": "Feature",
  "properties": {
    "addr:full":"Fontanastr 1 Wien Wien 1100",
    "addr:housenumber":"1",
    "addr:postcode":"1100",
    "addr:street":"Fontanastr",
    "iso:country":"AT",
    "sg:address":"Fontanastr 1",
    "sg:city":"Wien",
    "sg:orig_category":"Fluggesellschaften",
    "sg:phone":"+43 1 79567196",
    "sg:postcode":"1100",
    "sg:province":"Wien",
    "wof:name":"United Airlines",
    "wof:placetype":"venue"
},
  "geometry": {"coordinates":[16.4094734192,48.1402702332],"type":"Point"}
}