{
  "type": "Feature",
  "properties": {
    "addr:full":"Raimundgasse 18  Pernitz Nieder\u00f6sterreich 2763",
    "addr:housenumber":"18",
    "addr:postcode":"2763",
    "addr:street":"Raimundgasse",
    "iso:country":"AT",
    "sg:address":"Raimundgasse 18 ",
    "sg:city":"Pernitz",
    "sg:orig_category":"CarpenterS Work Supraregional",
    "sg:phone":"+43 2632 72214",
    "sg:postcode":"2763",
    "sg:province":"Nieder\u00f6sterreich",
    "sg:website":"www.panzenboeck.at",
    "wof:name":"Panzenb\u00f6ck GmbH & Co KG",
    "wof:placetype":"venue"
},
  "geometry": {"coordinates":[15.9551534653,47.8967475891],"type":"Point"}
}