{
  "type": "Feature",
  "properties": {
    "iso:country":"AT",
    "sg:address":"Ardaggerstr 91",
    "sg:city":"Amstetten",
    "sg:orig_category":"Farben U Lacke / Einzelhandel",
    "sg:phone":"+43 4367 65371853",
    "sg:postcode":"3300",
    "sg:province":"Nieder\u00f6sterreich",
    "wof:name":"Farben & Lacke Wiesner",
    "wof:placetype":"venue"
},
  "geometry": {"coordinates":[14.8660001755,48.1333312988],"type":"Point"}
}