{
  "type": "Feature",
  "properties": {
    "addr:full":"Alter Pl 18 Klagenfurt K\u00e4rnten 9020",
    "addr:housenumber":"18",
    "addr:postcode":"9020",
    "addr:street":"Alter Pl;Kaernten",
    "iso:country":"AT",
    "sg:address":"Alter Pl 18",
    "sg:city":"Klagenfurt",
    "sg:orig_category":"Optiker",
    "sg:phone":"+43 463 508489",
    "sg:postcode":"9020",
    "sg:province":"K\u00e4rnten",
    "wof:name":"Pearle \u00f6sterreich GmbH",
    "wof:placetype":"venue"
},
  "geometry": {"coordinates":[14.3098058701,46.6252822876],"type":"Point"}
}