{
  "type": "Feature",
  "properties": {
    "addr:full":"Kaisersch\u00fctzenstr 2 Schwanenstadt Ober\u00f6sterreich 4690",
    "addr:housenumber":"2",
    "addr:postcode":"4690",
    "addr:street":"Kaiserschuetzenstr",
    "iso:country":"AT",
    "sg:address":"Kaisersch\u00fctzenstr 2",
    "sg:city":"Schwanenstadt",
    "sg:orig_category":"Geschenkartikel",
    "sg:phone":"+43 76733094",
    "sg:postcode":"4690",
    "sg:province":"Ober\u00f6sterreich",
    "wof:name":"Artwork Kunstguss GmbH",
    "wof:placetype":"venue"
},
  "geometry": {"coordinates":[13.7731847763,48.0545158386],"type":"Point"}
}