{
  "type": "Feature",
  "properties": {
    "addr:full":"Rudolfinergasse, 16 - 18 -  Wien Wien 1190",
    "addr:housenumber":"16 18",
    "addr:postcode":"1190",
    "addr:street":"Rudolfinergasse",
    "iso:country":"AT",
    "sg:address":"Rudolfinergasse, 16 - 18 - ",
    "sg:city":"Wien",
    "sg:classifiers":[
        {
            "category":"Professional",
            "subcategory":"Art Services",
            "type":"Services"
        }
    ],
    "sg:phone":"+43 4313 698853",
    "sg:postcode":"1190",
    "sg:province":"Wien",
    "sg:tags":[
        "export-import"
    ],
    "wof:name":"Algeria Embassy",
    "wof:placetype":"venue"
},
  "geometry": {"coordinates":[16.3468532562,48.2443389893],"type":"Point"}
}