{
  "type": "Feature",
  "properties": {
    "iso:country":"AT",
    "sg:address":"Pflanzeng 16",
    "sg:city":"Graz",
    "sg:orig_category":"Institute",
    "sg:phone":"+43 4331 67247660",
    "sg:postcode":"8020",
    "sg:province":"Steiermark",
    "wof:name":"Institut f Arbeitsmarktbetreuung u -forschung Steiermark",
    "wof:placetype":"venue"
},
  "geometry": {"coordinates":[15.4290428162,47.0792121887],"type":"Point"}
}