{
  "type": "Feature",
  "properties": {
    "iso:country":"AT",
    "sg:address":"Kahlspergstr 1",
    "sg:city":"Oberalm",
    "sg:orig_category":"Banken U Sparkassen",
    "sg:phone":"+43 4362 45855710",
    "sg:postcode":"5411",
    "sg:province":"Salzburg",
    "wof:name":"Raiffeisenkasse Oberalm-Puch regGenmbH",
    "wof:placetype":"venue"
},
  "geometry": {"coordinates":[13.0987224579,47.7000312805],"type":"Point"}
}