{
  "type": "Feature",
  "properties": {
    "addr:full":"Koloniestr 77-81 Wien Wien 1210",
    "addr:postcode":"77-81;1210",
    "iso:country":"AT",
    "sg:address":"Koloniestr 77-81",
    "sg:city":"Wien",
    "sg:orig_category":"Maschinenhandel",
    "sg:phone":"+43 1 29210630",
    "sg:postcode":"1210",
    "sg:province":"Wien",
    "wof:name":"Roigk Maschinen",
    "wof:placetype":"venue"
},
  "geometry": {"coordinates":[16.3977870941,48.2734909058],"type":"Point"}
}