{
  "type": "Feature",
  "properties": {
    "addr:full":"Johann Offner-Str 22 Wolfsberg K\u00e4rnten 9400",
    "addr:housenumber":"22",
    "addr:postcode":"9400",
    "addr:street":"Wolfsberg Kaernten",
    "iso:country":"AT",
    "sg:address":"Johann Offner-Str 22",
    "sg:city":"Wolfsberg",
    "sg:orig_category":"Physiotherapie",
    "sg:phone":"+43 4352 30901",
    "sg:postcode":"9400",
    "sg:province":"K\u00e4rnten",
    "wof:name":"Zaminer Wolfgang Dipl-PT",
    "wof:placetype":"venue"
},
  "geometry": {"coordinates":[14.8457107544,46.8374633789],"type":"Point"}
}