{
  "type": "Feature",
  "properties": {
    "addr:full":"Landstr 4 Radenthein K\u00e4rnten 9545",
    "addr:housenumber":"4",
    "addr:postcode":"9545",
    "addr:street":"Landstr;Kaernten",
    "iso:country":"AT",
    "sg:address":"Landstr 4",
    "sg:city":"Radenthein",
    "sg:orig_category":"Schlossereien",
    "sg:phone":"+43 4246 25370",
    "sg:postcode":"9545",
    "sg:province":"K\u00e4rnten",
    "wof:name":"Strobl Othmar",
    "wof:placetype":"venue"
},
  "geometry": {"coordinates":[13.7077484131,46.8018341064],"type":"Point"}
}