{
  "type": "Feature",
  "properties": {
    "addr:full":"Prasslerg 23 Salzburg Salzburg 5020",
    "addr:housenumber":"23",
    "addr:postcode":"5020",
    "addr:street":"Prasslerg;Salzburg",
    "iso:country":"AT",
    "sg:address":"Prasslerg 23",
    "sg:city":"Salzburg",
    "sg:orig_category":"Massagen",
    "sg:phone":"+43 662 824677",
    "sg:postcode":"5020",
    "sg:province":"Salzburg",
    "wof:name":"Bohusch Heidrun - Massageinstitut",
    "wof:placetype":"venue"
},
  "geometry": {"coordinates":[13.0130090714,47.7879371643],"type":"Point"}
}