{
  "type": "Feature",
  "properties": {
    "addr:full":"Neuwaldegger Str 39 Wien Wien 1170",
    "addr:postcode":"1170",
    "addr:street":"Str 39",
    "iso:country":"AT",
    "sg:address":"Neuwaldegger Str 39",
    "sg:city":"Wien",
    "sg:classifiers":[
        {
            "category":"Professional",
            "subcategory":"Computer Services",
            "type":"Services"
        }
    ],
    "sg:phone":"+43 1 4805071",
    "sg:postcode":"1170",
    "sg:province":"Wien",
    "sg:tags":[
        "software"
    ],
    "wof:name":"Schnell Heinrich Ing",
    "wof:placetype":"venue"
},
  "geometry": {"coordinates":[16.2845592499,48.2382850647],"type":"Point"}
}