{
  "type": "Feature",
  "properties": {
    "addr:full":"Irma v Troll-Str 16 Salzburg Salzburg 5020",
    "addr:housenumber":"16",
    "addr:postcode":"5020",
    "addr:street":"Troll-Str;Salzburg",
    "iso:country":"AT",
    "sg:address":"Irma v Troll-Str 16",
    "sg:city":"Salzburg",
    "sg:orig_category":"Webdesign, Desk Top Publishing",
    "sg:phone":"+43 662 831979",
    "sg:postcode":"5020",
    "sg:province":"Salzburg",
    "sg:website":"www.more.co.at",
    "wof:name":"Reiter Monika",
    "wof:placetype":"venue"
},
  "geometry": {"coordinates":[13.0433769226,47.8006744385],"type":"Point"}
}