{
  "type": "Feature",
  "properties": {
    "iso:country":"AT",
    "sg:address":"Billrothstr 31",
    "sg:city":"Wien",
    "sg:orig_category":"Tabaktrafiken",
    "sg:phone":"+43 1 3680804",
    "sg:postcode":"1190",
    "sg:province":"Wien",
    "wof:name":"Cetin Sabati",
    "wof:placetype":"venue"
},
  "geometry": {"coordinates":[16.3492145538,48.236164093],"type":"Point"}
}