{
  "type": "Feature",
  "properties": {
    "addr:full":"In der Stille 11 Natters Tirol 6161",
    "addr:housenumber":"11",
    "addr:postcode":"6161",
    "addr:street":"In Der Stille;Tirol",
    "iso:country":"AT",
    "sg:address":"In der Stille 11",
    "sg:city":"Natters",
    "sg:orig_category":"Ingenieurkonsulenten / Zivilingenieure",
    "sg:phone":"+43 512 5469190",
    "sg:postcode":"6161",
    "sg:province":"Tirol",
    "wof:name":"Brunnsteiner Alfred Dipl-Ing",
    "wof:placetype":"venue"
},
  "geometry": {"coordinates":[11.3686246872,47.2365684509],"type":"Point"}
}