{
  "type": "Feature",
  "properties": {
    "addr:full":"Wind Baumgartner-Str 1 Zistersdorf Nieder\u00f6sterreich 2225",
    "addr:housenumber":"1",
    "addr:postcode":"2225",
    "addr:street":"Baumgartner-Str;Niederoesterreich",
    "iso:country":"AT",
    "sg:address":"Wind Baumgartner-Str 1",
    "sg:city":"Zistersdorf",
    "sg:orig_category":"Rettungsdienste",
    "sg:phone":"+43 2532 2400",
    "sg:postcode":"2225",
    "sg:province":"Nieder\u00f6sterreich",
    "wof:name":"Rotes Kreuz \u00d6sterr Bezirksstelle Zistersdorf",
    "wof:placetype":"venue"
},
  "geometry": {"coordinates":[16.7535743713,48.5491981506],"type":"Point"}
}