{
  "type": "Feature",
  "properties": {
    "addr:full":"Sch\u00e4rdinger Str 36 Aurolzm\u00fcnster Ober\u00f6sterreich 4971",
    "addr:postcode":"4971",
    "addr:street":"Str 36 Aurolzmuenster Oberoesterreich",
    "iso:country":"AT",
    "sg:address":"Sch\u00e4rdinger Str 36",
    "sg:city":"Aurolzm\u00fcnster",
    "sg:classifiers":[
        {
            "category":"Utilities",
            "subcategory":"Recycling",
            "type":"Services"
        }
    ],
    "sg:phone":"+43 4377 5284844",
    "sg:postcode":"4971",
    "sg:province":"Ober\u00f6sterreich",
    "wof:name":"REG Recycling- u Entsorgungs GmbH",
    "wof:placetype":"venue"
},
  "geometry": {"coordinates":[13.4528245926,48.2498931885],"type":"Point"}
}