{
  "type": "Feature",
  "properties": {
    "iso:country":"AT",
    "sg:address":"Wallersberg 31",
    "sg:city":"Griffen",
    "sg:classifiers":[
        {
            "category":"Building & Trades",
            "subcategory":"Construction",
            "type":"Services"
        }
    ],
    "sg:phone":"+43 4233 29700",
    "sg:postcode":"9112",
    "sg:province":"K\u00e4rnten",
    "sg:tags":[
        "machine"
    ],
    "sg:website":"matex.at",
    "wof:name":"MATEX Industrieanlagen GmbH",
    "wof:placetype":"venue"
},
  "geometry": {"coordinates":[14.7277650833,46.7022132874],"type":"Point"}
}