{
  "type": "Feature",
  "properties": {
    "addr:full":"Landstr 82a Hard Vorarlberg 6971",
    "addr:housenumber":"82a",
    "addr:postcode":"6971",
    "addr:street":"Landstr",
    "iso:country":"AT",
    "sg:address":"Landstr 82a",
    "sg:city":"Hard",
    "sg:orig_category":"Exporteure U Importeure",
    "sg:phone":"+43 4355 7479450",
    "sg:postcode":"6971",
    "sg:province":"Vorarlberg",
    "wof:name":"Makwana Ansuya Import-Export",
    "wof:placetype":"venue"
},
  "geometry": {"coordinates":[9.6819238663,47.480796814],"type":"Point"}
}