{
  "type": "Feature",
  "properties": {
    "addr:full":"Unterdorf 30 Reutte Tirol 6600",
    "addr:housenumber":"30",
    "addr:postcode":"6600",
    "addr:street":"Unterdorf;Tirol",
    "iso:country":"AT",
    "sg:address":"Unterdorf 30",
    "sg:city":"Reutte",
    "sg:orig_category":"Familien / Beratung",
    "sg:phone":"+43 4356 7265382",
    "sg:postcode":"6600",
    "sg:province":"Tirol",
    "wof:name":"Ehe- u Familienberatung Lechaschau",
    "wof:placetype":"venue"
},
  "geometry": {"coordinates":[10.7058334351,47.4972267151],"type":"Point"}
}