{
  "type": "Feature",
  "properties": {
    "iso:country":"AT",
    "sg:address":"Andreas-Hofer-Pl 17",
    "sg:city":"Graz",
    "sg:orig_category":"Steuerberatung",
    "sg:phone":"+43 4331 68260820",
    "sg:postcode":"8010",
    "sg:province":"Steiermark",
    "wof:name":"Corti & Partner Steuer- u Unternehmensberatungs GmbH",
    "wof:placetype":"venue"
},
  "geometry": {"coordinates":[15.4363231659,47.0686645508],"type":"Point"}
}