{
  "type": "Feature",
  "properties": {
    "iso:country":"AT",
    "sg:address":"Sonnwendstr 21",
    "sg:city":"Waidring",
    "sg:orig_category":"Unterhaltungselektronik / Einzelhandel",
    "sg:phone":"+43 5353 5420",
    "sg:postcode":"6384",
    "sg:province":"Tirol",
    "wof:name":"Divisek Reinhold",
    "wof:placetype":"venue"
},
  "geometry": {"coordinates":[12.5749826431,47.5829429626],"type":"Point"}
}