{
  "type": "Feature",
  "properties": {
    "iso:country":"AT",
    "sg:address":"Sommerhaidenweg 134",
    "sg:city":"Wien",
    "sg:orig_category":"Gie\u00c3\u0178ereien",
    "sg:phone":"+43 1 4402893",
    "sg:postcode":"1190",
    "sg:province":"Wien",
    "wof:name":"AUROM HandelsgesmbH",
    "wof:placetype":"venue"
},
  "geometry": {"coordinates":[16.2889194489,48.2508850098],"type":"Point"}
}