{
  "type": "Feature",
  "properties": {
    "addr:full":"Kreuzg 20b Innsbruck Tirol 6020",
    "addr:housenumber":"20b",
    "addr:postcode":"6020",
    "addr:street":"Kreuzg;Tirol",
    "iso:country":"AT",
    "sg:address":"Kreuzg 20b",
    "sg:city":"Innsbruck",
    "sg:orig_category":"Mineralien",
    "sg:phone":"+43 512 262479",
    "sg:postcode":"6020",
    "sg:province":"Tirol",
    "wof:name":"Pawlowski Olaf",
    "wof:placetype":"venue"
},
  "geometry": {"coordinates":[11.4239835739,47.2804985046],"type":"Point"}
}