{
  "type": "Feature",
  "properties": {
    "addr:full":"Linieng 29 Wien Wien 1060",
    "addr:housenumber":"29",
    "addr:postcode":"1060",
    "addr:street":"Linieng",
    "iso:country":"AT",
    "sg:address":"Linieng 29",
    "sg:city":"Wien",
    "sg:orig_category":"Zahntechnische Laboratorien",
    "sg:phone":"+43 1 5971271",
    "sg:postcode":"1060",
    "sg:province":"Wien",
    "wof:name":"\u00f6hner Werner",
    "wof:placetype":"venue"
},
  "geometry": {"coordinates":[16.3429603577,48.1918334961],"type":"Point"}
}