{
  "type": "Feature",
  "properties": {
    "iso:country":"AT",
    "sg:address":"Bischofstr 7",
    "sg:city":"Linz",
    "sg:classifiers":[
        {
            "category":"Shopping",
            "subcategory":"Thrift Store",
            "type":"Retail Goods"
        }
    ],
    "sg:phone":"+43 732 781986",
    "sg:postcode":"4020",
    "sg:province":"Ober\u00f6sterreich",
    "sg:tags":[
        "second-hand-shops"
    ],
    "wof:name":"Verein Arge f Obdachlose - Tr\u00f6dlerladen",
    "wof:placetype":"venue"
},
  "geometry": {"coordinates":[14.2886362076,48.3016853333],"type":"Point"}
}