{
  "type": "Feature",
  "properties": {
    "iso:country":"AT",
    "sg:address":"Seestr 27",
    "sg:city":"Podersdorf am See",
    "sg:orig_category":"Fleischhauereien",
    "sg:phone":"+43 2177 20025",
    "sg:postcode":"7141",
    "sg:province":"Burgenland",
    "wof:name":"Meiringer Julius",
    "wof:placetype":"venue"
},
  "geometry": {"coordinates":[16.835018158,47.8557243347],"type":"Point"}
}