{
  "type": "Feature",
  "properties": {
    "addr:full":"Poschacher Str. 35  Linz Ober\u00f6sterreich 4020",
    "addr:postcode":"4020",
    "addr:street":"Str. 35",
    "iso:country":"AT",
    "sg:address":"Poschacher Str. 35 ",
    "sg:city":"Linz",
    "sg:classifiers":[
        {
            "category":"Food & Beverages",
            "subcategory":"Groceries & Convenience Stores",
            "type":"Retail Goods"
        }
    ],
    "sg:phone":"+43 4373 26979",
    "sg:postcode":"4020",
    "sg:province":"Ober\u00f6sterreich",
    "sg:tags":[
        "drink"
    ],
    "wof:name":"BRAU UNION \u00d6STERREICH AG",
    "wof:placetype":"venue"
},
  "geometry": {"coordinates":[14.3092384338,48.2861099243],"type":"Point"}
}