{
  "type": "Feature",
  "properties": {
    "addr:full":"Nr 4 Oberw\u00f6lz Steiermark 8832",
    "addr:postcode":"8832",
    "addr:street":"Nr;Oberwoelz",
    "iso:country":"AT",
    "sg:address":"Nr 4",
    "sg:city":"Oberw\u00f6lz",
    "sg:orig_category":"Volksschulen",
    "sg:phone":"+43 4335 818288",
    "sg:postcode":"8832",
    "sg:province":"Steiermark",
    "wof:name":"Volksschule",
    "wof:placetype":"venue"
},
  "geometry": {"coordinates":[14.2811422348,47.20337677],"type":"Point"}
}