{
  "type": "Feature",
  "properties": {
    "addr:full":"MEZ Einkaufszentrum Bad Gleichenberg Steiermark 8344",
    "addr:postcode":"8344",
    "addr:street":"Mez",
    "iso:country":"AT",
    "sg:address":"MEZ Einkaufszentrum",
    "sg:city":"Bad Gleichenberg",
    "sg:orig_category":"Optiker",
    "sg:phone":"+43 800 6784537",
    "sg:postcode":"8344",
    "sg:province":"Steiermark",
    "wof:name":"Brillen Optik Ruck",
    "wof:placetype":"venue"
},
  "geometry": {"coordinates":[15.9038906097,46.8549499512],"type":"Point"}
}