{
  "type": "Feature",
  "properties": {
    "addr:full":"Faberstr 18 Salzburg Salzburg 5020",
    "addr:housenumber":"18",
    "addr:postcode":"5020",
    "addr:street":"Faberstr;Salzburg",
    "iso:country":"AT",
    "sg:address":"Faberstr 18",
    "sg:city":"Salzburg",
    "sg:orig_category":"Beratungsstellen",
    "sg:phone":"+43 662 8888319",
    "sg:postcode":"5020",
    "sg:province":"Salzburg",
    "wof:name":"AHA Bildungsberatung",
    "wof:placetype":"venue"
},
  "geometry": {"coordinates":[13.043510437,47.8079681396],"type":"Point"}
}