{
  "type": "Feature",
  "properties": {
    "addr:full":"Braunauer Str 22 Ried im Innkreis Ober\u00f6sterreich 4910",
    "addr:postcode":"4910",
    "addr:street":"Str 22",
    "iso:country":"AT",
    "sg:address":"Braunauer Str 22",
    "sg:city":"Ried im Innkreis",
    "sg:orig_category":"Autohandel",
    "sg:phone":"+43 7752 80577",
    "sg:postcode":"4910",
    "sg:province":"Ober\u00f6sterreich",
    "wof:name":"Daxl Gottfried GesmbH & Co",
    "wof:placetype":"venue"
},
  "geometry": {"coordinates":[13.4776191711,48.2061386108],"type":"Point"}
}