{
  "type": "Feature",
  "properties": {
    "iso:country":"AT",
    "sg:address":"Hauptstr 119",
    "sg:city":"Hagenberg im M\u00fchlkreis",
    "sg:orig_category":"Steuerungstechnik",
    "sg:phone":"+43 4372 363343310",
    "sg:postcode":"4232",
    "sg:province":"Ober\u00f6sterreich",
    "wof:name":"ubitronix system solutions gmbH",
    "wof:placetype":"venue"
},
  "geometry": {"coordinates":[14.5148801804,48.370174408],"type":"Point"}
}