{
  "type": "Feature",
  "properties": {
    "addr:full":"Anzengruberstr 47 Wien Wien 1140",
    "addr:housenumber":"47",
    "addr:postcode":"1140",
    "addr:street":"Anzengruberstr",
    "iso:country":"AT",
    "sg:address":"Anzengruberstr 47",
    "sg:city":"Wien",
    "sg:orig_category":"Psychologen",
    "sg:phone":"+43 1 9797282",
    "sg:postcode":"1140",
    "sg:province":"Wien",
    "wof:name":"Katzbeck Christian Mag",
    "wof:placetype":"venue"
},
  "geometry": {"coordinates":[16.2331924438,48.211151123],"type":"Point"}
}