{
  "type": "Feature",
  "properties": {
    "iso:country":"AT",
    "sg:address":"Franz Rumpler-Str 14",
    "sg:city":"Klosterneuburg",
    "sg:orig_category":"Non-Classified Establishments",
    "sg:phone":"+43 2243 32411",
    "sg:postcode":"3400",
    "sg:province":"Nieder\u00f6sterreich",
    "wof:name":"Evangelisches Pfarramt",
    "wof:placetype":"venue"
},
  "geometry": {"coordinates":[16.3241786957,48.3018035889],"type":"Point"}
}