{
  "type": "Feature",
  "properties": {
    "addr:full":"Ranser Feld 18 Aldrans Tirol 6071",
    "addr:housenumber":"18",
    "addr:postcode":"6071",
    "addr:street":"Ranser Feld;Tirol",
    "iso:country":"AT",
    "sg:address":"Ranser Feld 18",
    "sg:city":"Aldrans",
    "sg:orig_category":"Gesundheit / Allgemeine Informationsstellen",
    "sg:phone":"+43 512 394265",
    "sg:postcode":"6071",
    "sg:province":"Tirol",
    "wof:name":"Feldenkrais Methode - Dipl Ing Gerhard Wurnig",
    "wof:placetype":"venue"
},
  "geometry": {"coordinates":[11.4446716309,47.2445640564],"type":"Point"}
}