{
  "type": "Feature",
  "properties": {
    "addr:full":"Am Wachberg 3 Melk Nieder\u00f6sterreich 3390",
    "addr:housenumber":"3",
    "addr:postcode":"3390",
    "addr:street":"Am Wachberg",
    "iso:country":"AT",
    "sg:address":"Am Wachberg 3",
    "sg:city":"Melk",
    "sg:classifiers":[
        {
            "category":"Travel",
            "subcategory":"Hotels & Motels",
            "type":"Entertainment"
        }
    ],
    "sg:phone":"+43 2752 52531",
    "sg:postcode":"3390",
    "sg:province":"Nieder\u00f6sterreich",
    "sg:website":"hotel-wachau.at",
    "wof:name":"Hotel Pension Wachau - Fam Hipfinger",
    "wof:placetype":"venue"
},
  "geometry": {"coordinates":[15.3516254425,48.2230491638],"type":"Point"}
}