{
  "type": "Feature",
  "properties": {
    "addr:full":"Fischer v Erlach-G 1 Graz Steiermark 8010",
    "addr:housenumber":"1",
    "addr:postcode":"8010",
    "addr:street":"Erlach-G",
    "iso:country":"AT",
    "sg:address":"Fischer v Erlach-G 1",
    "sg:city":"Graz",
    "sg:orig_category":"Zahntechnische Laboratorien",
    "sg:phone":"+43 316 8356510",
    "sg:postcode":"8010",
    "sg:province":"Steiermark",
    "wof:name":"Dentallabor Bernd Sommerbauer GmbH",
    "wof:placetype":"venue"
},
  "geometry": {"coordinates":[15.4431800842,47.0685653687],"type":"Point"}
}