{
  "type": "Feature",
  "properties": {
    "addr:full":"St Georgener Str 1 Wildon Steiermark 8410",
    "addr:housenumber":"1",
    "addr:postcode":"8410",
    "addr:street":"St Georgener Str;Steiermark",
    "iso:country":"AT",
    "sg:address":"St Georgener Str 1",
    "sg:city":"Wildon",
    "sg:orig_category":"Lebensmittel / Einzelhandel",
    "sg:phone":"+43 3182 25500",
    "sg:postcode":"8410",
    "sg:province":"Steiermark",
    "wof:name":"Spar-Markt Platzer GesmbH",
    "wof:placetype":"venue"
},
  "geometry": {"coordinates":[15.5204496384,46.8867225647],"type":"Point"}
}