{
  "type": "Feature",
  "properties": {
    "iso:country":"AT",
    "sg:address":"Schied 86 ",
    "sg:city":"Gro\u00dfarl",
    "sg:classifiers":[
        {
            "category":"Home & Garden",
            "subcategory":"Home Furnishings",
            "type":"Retail Goods"
        }
    ],
    "sg:phone":"+43 4364 14260",
    "sg:postcode":"5611",
    "sg:province":"Salzburg",
    "sg:tags":[
        "household"
    ],
    "wof:name":"PETER HETTEGGER GESMBH & CO KG",
    "wof:placetype":"venue"
},
  "geometry": {"coordinates":[13.200799942,47.2642707825],"type":"Point"}
}