{
  "type": "Feature",
  "properties": {
    "addr:full":"Li\u00df Jerzens Tirol 6474",
    "addr:postcode":"6474",
    "addr:street":"Liss Jerzens",
    "iso:country":"AT",
    "sg:address":"Li\u00df",
    "sg:city":"Jerzens",
    "sg:classifiers":[
        {
            "category":"Park",
            "subcategory":"Provincial",
            "type":"Public Place"
        }
    ],
    "sg:phone":"+43 4354 1486910",
    "sg:postcode":"6474",
    "sg:province":"Tirol",
    "sg:tags":[
        "u",
        "ski-",
        "snowboardschulen"
    ],
    "wof:name":"Schischule Hochzeiger-Pitztal",
    "wof:placetype":"venue"
},
  "geometry": {"coordinates":[10.7465543747,47.1491737366],"type":"Point"}
}