{
  "type": "Feature",
  "properties": {
    "iso:country":"AT",
    "sg:address":"K\u00f6nigsbrunng 11",
    "sg:city":"M\u00fcrzzuschlag",
    "sg:orig_category":"Politische Parteien",
    "sg:phone":"+43 3852 2439",
    "sg:postcode":"8680",
    "sg:province":"Steiermark",
    "wof:name":"\u00f6VP - Bezirksparteileitung",
    "wof:placetype":"venue"
},
  "geometry": {"coordinates":[15.6699981689,47.6057052612],"type":"Point"}
}