{
  "type": "Feature",
  "properties": {
    "addr:full":"Bundesstr 27 Rankweil Vorarlberg 6830",
    "addr:housenumber":"27",
    "addr:postcode":"6830",
    "addr:street":"Bundesstr",
    "iso:country":"AT",
    "sg:address":"Bundesstr 27",
    "sg:city":"Rankweil",
    "sg:orig_category":"Autoreparatur",
    "sg:phone":"+43 5522 72214",
    "sg:postcode":"6830",
    "sg:province":"Vorarlberg",
    "wof:name":"T\u00fcrtscher Alois",
    "wof:placetype":"venue"
},
  "geometry": {"coordinates":[9.6167545319,47.2766647339],"type":"Point"}
}