{
  "type": "Feature",
  "properties": {
    "addr:full":"Ottakringer Str 94 Wien Wien 1170",
    "addr:postcode":"1170",
    "addr:street":"Str 94",
    "iso:country":"AT",
    "sg:address":"Ottakringer Str 94",
    "sg:city":"Wien",
    "sg:classifiers":[
        {
            "category":"Personal",
            "subcategory":"Adult",
            "type":"Services"
        }
    ],
    "sg:phone":"+43 1 4819181",
    "sg:postcode":"1170",
    "sg:province":"Wien",
    "sg:tags":[
        "sex-shops"
    ],
    "wof:name":"EROTIK - FETISH - VIDEO - SHOP",
    "wof:placetype":"venue"
},
  "geometry": {"coordinates":[16.327583313,48.2136497498],"type":"Point"}
}