{
  "type": "Feature",
  "properties": {
    "iso:country":"AT",
    "sg:address":"Simmeringer Hauptstrasse 52",
    "sg:city":"Wien",
    "sg:classifiers":[
        {
            "category":"Home & Garden",
            "subcategory":"Home Furnishings",
            "type":"Retail Goods"
        }
    ],
    "sg:phone":"+43 1 7493173",
    "sg:postcode":"1110",
    "sg:province":"Wien",
    "sg:tags":[
        "track",
        "curtain"
    ],
    "wof:name":"Gottfried Freudensprung",
    "wof:placetype":"venue"
},
  "geometry": {"coordinates":[16.4335365295,48.1585578918],"type":"Point"}
}