{
  "type": "Feature",
  "properties": {
    "addr:full":"Im H\u00fchnersteig 13-15 4017",
    "addr:housenumber":"13-15",
    "addr:postcode":"4017",
    "addr:street":"Im Huehnersteig",
    "iso:country":"AT",
    "sg:address":"Im H\u00fchnersteig 13-15",
    "sg:classifiers":[
        {
            "category":"Transit Center",
            "subcategory":"Freight",
            "type":"Transportation"
        }
    ],
    "sg:phone":"+43 732 7703210",
    "sg:postcode":"4017",
    "sg:tags":[
        "forwarding",
        "agency"
    ],
    "wof:name":"Heinrich Deinhammer - Internationale Spedition",
    "wof:placetype":"venue"
},
  "geometry": {"coordinates":[14.3174934387,48.304901123],"type":"Point"}
}