{
  "type": "Feature",
  "properties": {
    "addr:full":"Kirchenpl 18 Peuerbach Ober\u00f6sterreich 4722",
    "addr:housenumber":"18",
    "addr:postcode":"4722",
    "addr:street":"Kirchenpl",
    "iso:country":"AT",
    "sg:address":"Kirchenpl 18",
    "sg:city":"Peuerbach",
    "sg:orig_category":"Bibliotheken",
    "sg:phone":"+43 7276 29219",
    "sg:postcode":"4722",
    "sg:province":"Ober\u00f6sterreich",
    "wof:name":"\u00f6ffentl B\u00fccherei d Pfarre Peuerbach",
    "wof:placetype":"venue"
},
  "geometry": {"coordinates":[13.772808075,48.3446388245],"type":"Point"}
}