{
  "type": "Feature",
  "properties": {
    "addr:full":"Nr 27 Ried im Oberinntal Tirol 6531",
    "addr:postcode":"6531",
    "addr:street":"Nr 27;Tirol",
    "iso:country":"AT",
    "sg:address":"Nr 27",
    "sg:city":"Ried im Oberinntal",
    "sg:orig_category":"Bauunternehmen",
    "sg:phone":"+43 5472 20258",
    "sg:postcode":"6531",
    "sg:province":"Tirol",
    "wof:name":"M3 Plan und Bau GmbH",
    "wof:placetype":"venue"
},
  "geometry": {"coordinates":[10.654545784,47.0553817749],"type":"Point"}
}