{
  "type": "Feature",
  "properties": {
    "addr:full":"Gewerbepark 1 Saxen Ober\u00f6sterreich 4351",
    "addr:housenumber":"1",
    "addr:postcode":"4351",
    "addr:street":"Gewerbepark",
    "iso:country":"AT",
    "sg:address":"Gewerbepark 1",
    "sg:city":"Saxen",
    "sg:orig_category":"Transportunternehmen",
    "sg:phone":"+43 7269 766330",
    "sg:postcode":"4351",
    "sg:province":"Ober\u00f6sterreich",
    "wof:name":"Schlager GmbH",
    "wof:placetype":"venue"
},
  "geometry": {"coordinates":[14.7900476456,48.2081375122],"type":"Point"}
}