{
  "type": "Feature",
  "properties": {
    "addr:full":"Schumacherstr 1 Salzburg Salzburg 5020",
    "addr:housenumber":"1",
    "addr:postcode":"5020",
    "addr:street":"Schumacherstr;Salzburg",
    "iso:country":"AT",
    "sg:address":"Schumacherstr 1",
    "sg:city":"Salzburg",
    "sg:orig_category":"Non-Classified Establishments",
    "sg:phone":"+43 4366 2442261",
    "sg:postcode":"5020",
    "sg:province":"Salzburg",
    "wof:name":"ECL B\u00fcroartikel u Recycling GmbH",
    "wof:placetype":"venue"
},
  "geometry": {"coordinates":[13.026222229,47.8117790222],"type":"Point"}
}