{
  "type": "Feature",
  "properties": {
    "iso:country":"AT",
    "sg:address":"Nr 59",
    "sg:city":"Hohenzell",
    "sg:orig_category":"Gabelstapler",
    "sg:phone":"+43 7752 85700",
    "sg:postcode":"4921",
    "sg:province":"Ober\u00f6sterreich",
    "wof:name":"Gabelstapler Spitzer",
    "wof:placetype":"venue"
},
  "geometry": {"coordinates":[13.5438690186,48.1930618286],"type":"Point"}
}