{
  "type": "Feature",
  "properties": {
    "addr:full":"Pradler Str 20 Innsbruck Tirol 6020",
    "addr:housenumber":"20",
    "addr:postcode":"6020",
    "addr:street":"Pradler Str;Tirol",
    "iso:country":"AT",
    "sg:address":"Pradler Str 20",
    "sg:city":"Innsbruck",
    "sg:orig_category":"Sporthallen",
    "sg:phone":"+43 4351 2341121",
    "sg:postcode":"6020",
    "sg:province":"Tirol",
    "wof:name":"Turn- u Sporthalle Leitgebschule",
    "wof:placetype":"venue"
},
  "geometry": {"coordinates":[11.4080400467,47.2673606873],"type":"Point"}
}