{
  "type": "Feature",
  "properties": {
    "addr:full":"Hauptstr 240 Grafendorf Steiermark 8232",
    "addr:housenumber":"240",
    "addr:postcode":"8232",
    "addr:street":"Hauptstr",
    "iso:country":"AT",
    "sg:address":"Hauptstr 240",
    "sg:city":"Grafendorf",
    "sg:orig_category":"Autoreparatur",
    "sg:phone":"+43 4333 3822750",
    "sg:postcode":"8232",
    "sg:province":"Steiermark",
    "wof:name":"Harmtodt J Hdl u Kfz-Rep Betriebs GesmbH",
    "wof:placetype":"venue"
},
  "geometry": {"coordinates":[15.991060257,47.3353843689],"type":"Point"}
}