{
  "type": "Feature",
  "properties": {
    "iso:country":"AT",
    "sg:address":"An der Bundesstrasse 6",
    "sg:city":"Korneuburg",
    "sg:classifiers":[
        {
            "category":"Utilities",
            "subcategory":"Natural Gas",
            "type":"Services"
        }
    ],
    "sg:phone":"+43 2262 7000",
    "sg:postcode":"2100",
    "sg:province":"Nieder\u00f6sterreich",
    "sg:tags":[
        "acetylene"
    ],
    "sg:website":"flaga.at",
    "wof:name":"Flaga GmbH",
    "wof:placetype":"venue"
},
  "geometry": {"coordinates":[16.3329143524,48.3437843323],"type":"Point"}
}