{
  "type": "Feature",
  "properties": {
    "iso:country":"AT",
    "sg:address":"Fuchsrain 29",
    "sg:city":"Innsbruck",
    "sg:orig_category":"Behinderungen / Leben Mit Behinderungen",
    "sg:phone":"+43 512 560494",
    "sg:postcode":"6020",
    "sg:province":"Tirol",
    "wof:name":"Lebenshilfe Tirol - Werkst\u00e4tte Haus Wilten",
    "wof:placetype":"venue"
},
  "geometry": {"coordinates":[11.4281978607,47.2796096802],"type":"Point"}
}