{
  "type": "Feature",
  "properties": {
    "addr:full":"Lauzilg 15 Graz Steiermark 8020",
    "addr:housenumber":"15",
    "addr:postcode":"8020",
    "addr:street":"Lauzilg",
    "iso:country":"AT",
    "sg:address":"Lauzilg 15",
    "sg:city":"Graz",
    "sg:orig_category":"Dachdeckereien",
    "sg:phone":"+43 316 271534",
    "sg:postcode":"8020",
    "sg:province":"Steiermark",
    "sg:website":"www.rath-dach.at",
    "wof:name":"Rath Dach GmbH & Co KG",
    "wof:placetype":"venue"
},
  "geometry": {"coordinates":[15.434053421,47.0459632874],"type":"Point"}
}