{
  "type": "Feature",
  "properties": {
    "addr:full":"Kitzsteinhornstr 3 Zell am See Salzburg 5700",
    "addr:housenumber":"3",
    "addr:postcode":"5700",
    "addr:street":"Kitzsteinhornstr;Salzburg",
    "iso:country":"AT",
    "sg:address":"Kitzsteinhornstr 3",
    "sg:city":"Zell am See",
    "sg:classifiers":[
        {
            "category":"Travel",
            "subcategory":"Hotels & Motels",
            "type":"Entertainment"
        }
    ],
    "sg:phone":"+43 6542 572630",
    "sg:postcode":"5700",
    "sg:province":"Salzburg",
    "wof:name":"Pinzgauerhof",
    "wof:placetype":"venue"
},
  "geometry": {"coordinates":[12.7932386398,47.3027305603],"type":"Point"}
}