{
  "type": "Feature",
  "properties": {
    "addr:full":"Pfarrg 10 Hofkirchen im M\u00fchlkreis Ober\u00f6sterreich 4142",
    "addr:housenumber":"10",
    "addr:postcode":"4142",
    "addr:street":"Pfarrg;Im Muehlkreis Oberoesterreich",
    "iso:country":"AT",
    "sg:address":"Pfarrg 10",
    "sg:city":"Hofkirchen im M\u00fchlkreis",
    "sg:orig_category":"Non-Classified Establishments",
    "sg:phone":"+43 7285 205",
    "sg:postcode":"4142",
    "sg:province":"Ober\u00f6sterreich",
    "wof:name":"Pfarramt Hofkirchen",
    "wof:placetype":"venue"
},
  "geometry": {"coordinates":[13.8117761612,48.4831466675],"type":"Point"}
}