{
  "type": "Feature",
  "properties": {
    "addr:full":"Bischofstr 4A Linz Ober\u00f6sterreich 4020",
    "addr:housenumber":"4a",
    "addr:postcode":"4020",
    "addr:street":"Bischofstr",
    "iso:country":"AT",
    "sg:address":"Bischofstr 4A",
    "sg:city":"Linz",
    "sg:orig_category":"Fotografen",
    "sg:phone":"+43 732 794433",
    "sg:postcode":"4020",
    "sg:province":"Ober\u00f6sterreich",
    "sg:website":"newart.at",
    "wof:name":"New Art Studio",
    "wof:placetype":"venue"
},
  "geometry": {"coordinates":[14.2885980606,48.3019714355],"type":"Point"}
}