{
  "type": "Feature",
  "properties": {
    "addr:full":"Heinfeld 53 Ilz Steiermark 8262",
    "addr:housenumber":"53",
    "addr:postcode":"8262",
    "addr:street":"Heinfeld",
    "iso:country":"AT",
    "sg:address":"Heinfeld 53",
    "sg:city":"Ilz",
    "sg:classifiers":[
        {
            "category":"Building & Trades",
            "subcategory":"Landscaping Services",
            "type":"Services"
        }
    ],
    "sg:phone":"+43 3385 249",
    "sg:postcode":"8262",
    "sg:province":"Steiermark",
    "sg:tags":[
        "earth",
        "moving"
    ],
    "wof:name":"Heinrich GesmbH",
    "wof:placetype":"venue"
},
  "geometry": {"coordinates":[15.9260549545,47.086479187],"type":"Point"}
}