{
  "type": "Feature",
  "properties": {
    "addr:full":"Neustiftstr 2 Frauenkirchen Burgenland 7132",
    "addr:housenumber":"2",
    "addr:postcode":"7132",
    "addr:street":"Neustiftstr",
    "iso:country":"AT",
    "sg:address":"Neustiftstr 2",
    "sg:city":"Frauenkirchen",
    "sg:orig_category":"Lebensmittel / Einzelhandel",
    "sg:phone":"+43 2172 7117",
    "sg:postcode":"7132",
    "sg:province":"Burgenland",
    "wof:name":"SPAR \u00f6sterreichische Warenhandels-AG",
    "wof:placetype":"venue"
},
  "geometry": {"coordinates":[16.9221992493,47.8378181458],"type":"Point"}
}