{
  "type": "Feature",
  "properties": {
    "addr:full":"Wagramer Str 4 Wien Wien 1220",
    "addr:housenumber":"4",
    "addr:postcode":"1220",
    "addr:street":"Str",
    "iso:country":"AT",
    "sg:address":"Wagramer Str 4",
    "sg:city":"Wien",
    "sg:orig_category":"Immobilienverwaltungen",
    "sg:phone":"+43 1 2639770",
    "sg:postcode":"1220",
    "sg:province":"Wien",
    "wof:name":"ARWAG Hausbetreuungs -u BetriebsgesmbH - Au\u00dfenstelle Hochhaus Neue Donau",
    "wof:placetype":"venue"
},
  "geometry": {"coordinates":[16.4150791168,48.2309494019],"type":"Point"}
}