{
  "type": "Feature",
  "properties": {
    "addr:full":"Hauptpl 17 Bruck an der Leitha Nieder\u00f6sterreich 2460",
    "addr:housenumber":"17",
    "addr:postcode":"2460",
    "addr:street":"Hauptpl",
    "iso:country":"AT",
    "sg:address":"Hauptpl 17",
    "sg:city":"Bruck an der Leitha",
    "sg:orig_category":"\u00c3\u201erzte / F Allgemeinmedizin",
    "sg:phone":"+43 2162 627900",
    "sg:postcode":"2460",
    "sg:province":"Nieder\u00f6sterreich",
    "wof:name":"Jutz Gunther MedR Dr",
    "wof:placetype":"venue"
},
  "geometry": {"coordinates":[16.7793292999,48.0252952576],"type":"Point"}
}