{
  "type": "Feature",
  "properties": {
    "addr:full":"Gutshofweg 8 Innsbruck Tirol 6020",
    "addr:housenumber":"8",
    "addr:postcode":"6020",
    "addr:street":"Gutshofweg;Tirol",
    "iso:country":"AT",
    "sg:address":"Gutshofweg 8",
    "sg:city":"Innsbruck",
    "sg:orig_category":"Non-Classified Establishments",
    "sg:phone":"+43 512 344411",
    "sg:postcode":"6020",
    "sg:province":"Tirol",
    "wof:name":"Evangelisches Pfarramt Innsbruck-Ost",
    "wof:placetype":"venue"
},
  "geometry": {"coordinates":[11.4173021317,47.2724571228],"type":"Point"}
}