{
  "type": "Feature",
  "properties": {
    "iso:country":"AT",
    "sg:address":"Nr 39",
    "sg:city":"Weilbach",
    "sg:orig_category":"Kosmetikanwendungsberatung",
    "sg:phone":"+43 7757 6142",
    "sg:postcode":"4984",
    "sg:province":"Ober\u00f6sterreich",
    "wof:name":"Channoine Cosmetic - Christine Wagner",
    "wof:placetype":"venue"
},
  "geometry": {"coordinates":[13.3731956482,48.2770767212],"type":"Point"}
}