{
  "type": "Feature",
  "properties": {
    "addr:full":"Bludesch Vorarlberg 6719",
    "addr:postcode":"6719",
    "iso:country":"AT",
    "sg:city":"Bludesch",
    "sg:orig_category":"Feuerwehren",
    "sg:phone":"+43 5550 3310",
    "sg:postcode":"6719",
    "sg:province":"Vorarlberg",
    "wof:name":"Feuerwehr Bludesch",
    "wof:placetype":"venue"
},
  "geometry": {"coordinates":[9.7409362793,47.1968688965],"type":"Point"}
}