{
  "type": "Feature",
  "properties": {
    "addr:full":"Linke Wienzeile 38 Wien Wien 1060",
    "addr:housenumber":"38",
    "addr:postcode":"1060",
    "addr:street":"Linke Wienzeile",
    "iso:country":"AT",
    "sg:address":"Linke Wienzeile 38",
    "sg:city":"Wien",
    "sg:orig_category":"Banken U Sparkassen",
    "sg:phone":"+43 5 050531950",
    "sg:postcode":"1060",
    "sg:province":"Wien",
    "wof:name":"Bank Austria Creditanstalt AG",
    "wof:placetype":"venue"
},
  "geometry": {"coordinates":[16.3594303131,48.1974601746],"type":"Point"}
}