{
  "type": "Feature",
  "properties": {
    "iso:country":"AT",
    "sg:address":"Nr 31",
    "sg:city":"Sallingberg",
    "sg:orig_category":"Banken U Sparkassen",
    "sg:phone":"+43 4328 778374",
    "sg:postcode":"3525",
    "sg:province":"Nieder\u00f6sterreich",
    "wof:name":"Raiffeisenkasse Salingberg regGenmbH",
    "wof:placetype":"venue"
},
  "geometry": {"coordinates":[15.2333440781,48.4661941528],"type":"Point"}
}