{
  "type": "Feature",
  "properties": {
    "addr:full":"Nr 186 Grafendorf Steiermark 8232",
    "addr:postcode":"8232",
    "addr:street":"Nr",
    "iso:country":"AT",
    "sg:address":"Nr 186",
    "sg:city":"Grafendorf",
    "sg:orig_category":"Armaturen / Erzeugung U Gro\u00c3\u0178handel",
    "sg:phone":"+43 4333 3833658",
    "sg:postcode":"8232",
    "sg:province":"Steiermark",
    "wof:name":"Meibes System-Technik GmbH Heizungs- u Solarzubeh\u00f6r",
    "wof:placetype":"venue"
},
  "geometry": {"coordinates":[15.9914007187,47.3399276733],"type":"Point"}
}