{
  "type": "Feature",
  "properties": {
    "addr:full":"Donaustr 11 Au Ober\u00f6sterreich 4332",
    "addr:housenumber":"11",
    "addr:postcode":"4332",
    "addr:street":"Donaustr",
    "iso:country":"AT",
    "sg:address":"Donaustr 11",
    "sg:city":"Au",
    "sg:orig_category":"Maschinenhandel",
    "sg:phone":"+43 4372 6258419",
    "sg:postcode":"4332",
    "sg:province":"Ober\u00f6sterreich",
    "wof:name":"WE-Fensterbautechnik GmbH",
    "wof:placetype":"venue"
},
  "geometry": {"coordinates":[14.5866470337,48.2245254517],"type":"Point"}
}