{
  "type": "Feature",
  "properties": {
    "iso:country":"AT",
    "sg:address":"Eibingweg 371",
    "sg:city":"Saalbach",
    "sg:orig_category":"Pensionen / Privatzimmer",
    "sg:phone":"+43 6541 71190",
    "sg:postcode":"5753",
    "sg:province":"Salzburg",
    "wof:name":"Pension Ingeborg",
    "wof:placetype":"venue"
},
  "geometry": {"coordinates":[12.6367301941,47.3899307251],"type":"Point"}
}