{
  "type": "Feature",
  "properties": {
    "addr:full":"Fellengattner Str 8 Frastanz Vorarlberg 6820",
    "addr:housenumber":"8",
    "addr:postcode":"6820",
    "addr:street":"Str",
    "iso:country":"AT",
    "sg:address":"Fellengattner Str 8",
    "sg:city":"Frastanz",
    "sg:orig_category":"Biologische Produkte",
    "sg:phone":"+43 4355 2283329",
    "sg:postcode":"6820",
    "sg:province":"Vorarlberg",
    "wof:name":"Dittmann Handels- u Vertriebsagentur",
    "wof:placetype":"venue"
},
  "geometry": {"coordinates":[9.600856781,47.2271690369],"type":"Point"}
}