{
  "type": "Feature",
  "properties": {
    "addr:full":"Hauptpl 21 Leibnitz Steiermark 8430",
    "addr:housenumber":"21",
    "addr:postcode":"8430",
    "addr:street":"Hauptpl;Steiermark",
    "iso:country":"AT",
    "sg:address":"Hauptpl 21",
    "sg:city":"Leibnitz",
    "sg:orig_category":"Tabaktrafiken",
    "sg:phone":"+43 3452 8249077",
    "sg:postcode":"8430",
    "sg:province":"Steiermark",
    "wof:name":"Kappaun Karl Mag",
    "wof:placetype":"venue"
},
  "geometry": {"coordinates":[15.5391960144,46.781578064],"type":"Point"}
}