{
  "type": "Feature",
  "properties": {
    "addr:full":"Hofmanng 7 Wien Wien 1180",
    "addr:housenumber":"7",
    "addr:postcode":"1180",
    "addr:street":"Hofmanng",
    "iso:country":"AT",
    "sg:address":"Hofmanng 7",
    "sg:city":"Wien",
    "sg:orig_category":"Tonstudios",
    "sg:phone":"+43 1 4091089",
    "sg:postcode":"1180",
    "sg:province":"Wien",
    "wof:name":"Tonstudio Dorfner",
    "wof:placetype":"venue"
},
  "geometry": {"coordinates":[16.344367981,48.2229385376],"type":"Point"}
}