{
  "type": "Feature",
  "properties": {
    "addr:full":"Hans-Heppenheimer-Str 14 Rohrendorf Nieder\u00f6sterreich 3495",
    "addr:housenumber":"14",
    "addr:postcode":"3495",
    "addr:street":"Hans-Heppenheimer-Str",
    "iso:country":"AT",
    "sg:address":"Hans-Heppenheimer-Str 14",
    "sg:city":"Rohrendorf",
    "sg:orig_category":"Tischlereien",
    "sg:phone":"+43 4327 32838900",
    "sg:postcode":"3495",
    "sg:province":"Nieder\u00f6sterreich",
    "wof:name":"Krimshandl Franz",
    "wof:placetype":"venue"
},
  "geometry": {"coordinates":[15.6641645432,48.4231491089],"type":"Point"}
}