{
  "type": "Feature",
  "properties": {
    "addr:full":"Welser Str 7-9 Leonding Ober\u00f6sterreich 4060",
    "addr:postcode":"4060",
    "addr:street":"Str 7-9",
    "iso:country":"AT",
    "sg:address":"Welser Str 7-9",
    "sg:city":"Leonding",
    "sg:orig_category":"Personalbereitstellung",
    "sg:phone":"+43 732 676677",
    "sg:postcode":"4060",
    "sg:province":"Ober\u00f6sterreich",
    "wof:name":"Anlagenconsulting TRANSFER Personalleasing Industriemontagen",
    "wof:placetype":"venue"
},
  "geometry": {"coordinates":[14.2652177811,48.2675132751],"type":"Point"}
}