{
  "type": "Feature",
  "properties": {
    "addr:full":"Kaiser F Josef-Str 2 Bad Gastein Salzburg 5640",
    "addr:housenumber":"2",
    "addr:postcode":"5640",
    "addr:street":"Josef-Str;Salzburg",
    "iso:country":"AT",
    "sg:address":"Kaiser F Josef-Str 2",
    "sg:city":"Bad Gastein",
    "sg:orig_category":"Appartements / Ferienwohnungen",
    "sg:phone":"+43 6434 24030",
    "sg:postcode":"5640",
    "sg:province":"Salzburg",
    "wof:name":"Appartementhotel Haus Sponfeldner",
    "wof:placetype":"venue"
},
  "geometry": {"coordinates":[13.1355514526,47.1145439148],"type":"Point"}
}