{
  "type": "Feature",
  "properties": {
    "addr:full":"Rotenturmstr 25 Wien Wien 1010",
    "addr:housenumber":"25",
    "addr:postcode":"1010",
    "addr:street":"Rotenturmstr",
    "iso:country":"AT",
    "sg:address":"Rotenturmstr 25",
    "sg:city":"Wien",
    "sg:orig_category":"Architekten",
    "sg:phone":"+43 1 53302120",
    "sg:postcode":"1010",
    "sg:province":"Wien",
    "wof:name":"Lintl Arch Prof ZT-GesmbH",
    "wof:placetype":"venue"
},
  "geometry": {"coordinates":[16.3755130768,48.211227417],"type":"Point"}
}