{
  "type": "Feature",
  "properties": {
    "addr:full":"Waldweg 11 Kirchberg an der Pielach Nieder\u00f6sterreich 3204",
    "addr:housenumber":"11",
    "addr:postcode":"3204",
    "addr:street":"Waldweg",
    "iso:country":"AT",
    "sg:address":"Waldweg 11",
    "sg:city":"Kirchberg an der Pielach",
    "sg:orig_category":"Musikgruppen",
    "sg:phone":"+43 4327 227000",
    "sg:postcode":"3204",
    "sg:province":"Nieder\u00f6sterreich",
    "wof:name":"Die Schlo\u00dfkogler",
    "wof:placetype":"venue"
},
  "geometry": {"coordinates":[15.431096077,48.0229492188],"type":"Point"}
}