{
  "type": "Feature",
  "properties": {
    "addr:full":"Neugeb\u00e4udestr 13 Wien Wien 1110",
    "addr:housenumber":"13",
    "addr:postcode":"1110",
    "addr:street":"Neugebaeudestr",
    "iso:country":"AT",
    "sg:address":"Neugeb\u00e4udestr 13",
    "sg:city":"Wien",
    "sg:orig_category":"Schlossereien",
    "sg:phone":"+43 1 7692315",
    "sg:postcode":"1110",
    "sg:province":"Wien",
    "wof:name":"Weingart Peter Ing",
    "wof:placetype":"venue"
},
  "geometry": {"coordinates":[16.431722641,48.1625556946],"type":"Point"}
}