{
  "type": "Feature",
  "properties": {
    "addr:full":"Siegfried-Marcus-Str 9 Biedermannsdorf Nieder\u00f6sterreich 2362",
    "addr:housenumber":"9",
    "addr:postcode":"2362",
    "addr:street":"Siegfried-Marcus-Str",
    "iso:country":"AT",
    "sg:address":"Siegfried-Marcus-Str 9",
    "sg:city":"Biedermannsdorf",
    "sg:orig_category":"Gasversorgungsunternehmen",
    "sg:phone":"+43 2236 76265",
    "sg:postcode":"2362",
    "sg:province":"Nieder\u00f6sterreich",
    "wof:name":"Premaberg Industrieanlagen GesmbH",
    "wof:placetype":"venue"
},
  "geometry": {"coordinates":[16.34608078,48.083366394],"type":"Point"}
}