{
  "type": "Feature",
  "properties": {
    "addr:full":"Marokkanergasse 18/1 Wien Wien 1030",
    "addr:housenumber":"18 / 1",
    "addr:postcode":"1030",
    "addr:street":"Marokkanergasse",
    "iso:country":"AT",
    "sg:address":"Marokkanergasse 18/1",
    "sg:city":"Wien",
    "sg:classifiers":[
        {
            "category":"Professional",
            "subcategory":"Printing & Photocopies",
            "type":"Services"
        }
    ],
    "sg:phone":"+43 1 71210570",
    "sg:postcode":"1030",
    "sg:province":"Wien",
    "sg:tags":[
        "newspaper",
        "publisher"
    ],
    "sg:website":"www.zurzeit.at",
    "wof:name":"W3 Verlagsges.m.b.H.",
    "wof:placetype":"venue"
},
  "geometry": {"coordinates":[16.3802089691,48.1977424622],"type":"Point"}
}