{
  "type": "Feature",
  "properties": {
    "addr:full":"Gr\u00fcnburger Str 109 Adlwang Ober\u00f6sterreich 4541",
    "addr:housenumber":"109",
    "addr:postcode":"4541",
    "addr:street":"Str",
    "iso:country":"AT",
    "sg:address":"Gr\u00fcnburger Str 109",
    "sg:city":"Adlwang",
    "sg:orig_category":"Schneidereien",
    "sg:phone":"+43 7258 29529",
    "sg:postcode":"4541",
    "sg:province":"Ober\u00f6sterreich",
    "wof:name":"Modeatelier Petra Kapfer-S\u00f6llradl",
    "wof:placetype":"venue"
},
  "geometry": {"coordinates":[14.2176198959,47.9920692444],"type":"Point"}
}