{
  "type": "Feature",
  "properties": {
    "iso:country":"AT",
    "sg:address":"Pl\u00f6ven 5",
    "sg:city":"Telfes im Stubai",
    "sg:orig_category":"Metallwaren / Erzeugung U Gro\u00c3\u0178handel",
    "sg:phone":"+43 4352 2562330",
    "sg:postcode":"6165",
    "sg:province":"Tirol",
    "wof:name":"Hutter Walter",
    "wof:placetype":"venue"
},
  "geometry": {"coordinates":[11.3586997986,47.1647262573],"type":"Point"}
}