{
  "type": "Feature",
  "properties": {
    "addr:full":"Schorfen 1 Tulfes Tirol 6075",
    "addr:housenumber":"1",
    "addr:postcode":"6075",
    "addr:street":"Schorfen;Tirol",
    "iso:country":"AT",
    "sg:address":"Schorfen 1",
    "sg:city":"Tulfes",
    "sg:classifiers":[
        {
            "category":"Restaurant",
            "type":"Food & Drink"
        }
    ],
    "sg:phone":"+43 5223 78342",
    "sg:postcode":"6075",
    "sg:province":"Tirol",
    "wof:name":"Ghetta Willhelm",
    "wof:placetype":"venue"
},
  "geometry": {"coordinates":[11.5335226059,47.2598762512],"type":"Point"}
}