{
  "type": "Feature",
  "properties": {
    "addr:full":"Forster Str 70 Kalsdorf Steiermark 8401",
    "addr:postcode":"8401",
    "addr:street":"Str 70",
    "iso:country":"AT",
    "sg:address":"Forster Str 70",
    "sg:city":"Kalsdorf",
    "sg:classifiers":[
        {
            "category":"Travel",
            "subcategory":"Hotels & Motels",
            "type":"Entertainment"
        }
    ],
    "sg:phone":"+43 3135 57600",
    "sg:postcode":"8401",
    "sg:province":"Steiermark",
    "wof:name":"OEKOTEL KALSDORF",
    "wof:placetype":"venue"
},
  "geometry": {"coordinates":[15.4603672028,46.9723892212],"type":"Point"}
}