{
  "type": "Feature",
  "properties": {
    "iso:country":"AT",
    "sg:address":"Bahnhofstr 43",
    "sg:city":"Zeltweg",
    "sg:orig_category":"Blumeneinzelhandel",
    "sg:phone":"+43 3577 22655",
    "sg:postcode":"8740",
    "sg:province":"Steiermark",
    "wof:name":"Blumen Scherngell Dietmar",
    "wof:placetype":"venue"
},
  "geometry": {"coordinates":[14.7539243698,47.1898994446],"type":"Point"}
}