{
  "type": "Feature",
  "properties": {
    "addr:full":"Walser Str 56 Riezlern Vorarlberg 6991",
    "addr:postcode":"6991",
    "addr:street":"Str 56",
    "iso:country":"AT",
    "sg:address":"Walser Str 56",
    "sg:city":"Riezlern",
    "sg:classifiers":[
        {
            "category":"Travel",
            "subcategory":"Hotels & Motels",
            "type":"Entertainment"
        }
    ],
    "sg:phone":"+43 4355 1752070",
    "sg:postcode":"6991",
    "sg:province":"Vorarlberg",
    "wof:name":"Traube Hotel",
    "wof:placetype":"venue"
},
  "geometry": {"coordinates":[10.1859445572,47.3575744629],"type":"Point"}
}