{
  "type": "Feature",
  "properties": {
    "addr:full":"Unterkrumbach 206 Krumbach Vorarlberg 6942",
    "addr:housenumber":"206",
    "addr:postcode":"6942",
    "addr:street":"Unterkrumbach",
    "iso:country":"AT",
    "sg:address":"Unterkrumbach 206",
    "sg:city":"Krumbach",
    "sg:classifiers":[
        {
            "category":"Taxi",
            "type":"Transportation"
        }
    ],
    "sg:phone":"+43 4355 1382700",
    "sg:postcode":"6942",
    "sg:province":"Vorarlberg",
    "sg:tags":[
        "personentransporte",
        "u"
    ],
    "wof:name":"Schedler Max",
    "wof:placetype":"venue"
},
  "geometry": {"coordinates":[9.933930397,47.4854354858],"type":"Point"}
}