{
  "type": "Feature",
  "properties": {
    "iso:country":"AT",
    "sg:address":"Takern II 180",
    "sg:city":"St. Margarethen an der Raab",
    "sg:orig_category":"Elektroinstallationsunternehmen",
    "sg:phone":"+43 4331 154602",
    "sg:postcode":"8321",
    "sg:province":"Steiermark",
    "wof:name":"F\u00fcrndrath Josef",
    "wof:placetype":"venue"
},
  "geometry": {"coordinates":[15.7803869247,47.0522918701],"type":"Point"}
}