{
  "type": "Feature",
  "properties": {
    "iso:country":"AT",
    "sg:address":"Holzhauserg 3",
    "sg:city":"Wien",
    "sg:classifiers":[
        {
            "category":"Professional",
            "subcategory":"Computer Services",
            "type":"Services"
        }
    ],
    "sg:phone":"+43 1 2198700",
    "sg:postcode":"1020",
    "sg:province":"Wien",
    "sg:tags":[
        "software"
    ],
    "wof:name":"antitachyon - Manalo & Willner OEG",
    "wof:placetype":"venue"
},
  "geometry": {"coordinates":[16.3889350891,48.2203559875],"type":"Point"}
}