{
  "type": "Feature",
  "properties": {
    "addr:full":"Kaiser-Josef-Str 18 Purkersdorf Nieder\u00f6sterreich 3002",
    "addr:housenumber":"18",
    "addr:postcode":"3002",
    "addr:street":"Kaiser-Josef-Str",
    "iso:country":"AT",
    "sg:address":"Kaiser-Josef-Str 18",
    "sg:city":"Purkersdorf",
    "sg:orig_category":"Textilreinigung",
    "sg:phone":"+43 4322 3164185",
    "sg:postcode":"3002",
    "sg:province":"Nieder\u00f6sterreich",
    "wof:name":"Diana Selbstbedienung Wasch- u Putzereibetrieb Rudolf Mayer & Co OHG",
    "wof:placetype":"venue"
},
  "geometry": {"coordinates":[16.1728401184,48.2066421509],"type":"Point"}
}