{
  "type": "Feature",
  "properties": {
    "addr:full":"Hauptstr 63 Schleinbach Nieder\u00f6sterreich 2123",
    "addr:housenumber":"63",
    "addr:postcode":"2123",
    "addr:street":"Hauptstr",
    "iso:country":"AT",
    "sg:address":"Hauptstr 63",
    "sg:city":"Schleinbach",
    "sg:orig_category":"Volksschulen",
    "sg:phone":"+43 2245 89588",
    "sg:postcode":"2123",
    "sg:province":"Nieder\u00f6sterreich",
    "wof:name":"Volksschule Hochleithen",
    "wof:placetype":"venue"
},
  "geometry": {"coordinates":[16.4917793274,48.446018219],"type":"Point"}
}