{
  "type": "Feature",
  "properties": {
    "addr:full":"Eipeldauerstr 38/3/3 Wien Wien 1220",
    "addr:housenumber":"38 / 3 / 3",
    "addr:postcode":"1220",
    "addr:street":"Eipeldauerstr",
    "iso:country":"AT",
    "sg:address":"Eipeldauerstr 38/3/3",
    "sg:city":"Wien",
    "sg:orig_category":"Ingenieurkonsulenten / Zivilingenieure",
    "sg:phone":"+43 1 2033181",
    "sg:postcode":"1220",
    "sg:province":"Wien",
    "wof:name":"Oppolzer Johann Dipl-Ing",
    "wof:placetype":"venue"
},
  "geometry": {"coordinates":[16.444606781,48.2497138977],"type":"Point"}
}