{
  "type": "Feature",
  "properties": {
    "addr:full":"Grieskirchner Str 77 Wels Ober\u00f6sterreich 4600",
    "addr:housenumber":"77",
    "addr:postcode":"4600",
    "addr:street":"Str;Oberoesterreich",
    "iso:country":"AT",
    "sg:address":"Grieskirchner Str 77",
    "sg:city":"Wels",
    "sg:orig_category":"Friseure U Frisiersalons",
    "sg:phone":"+43 4372 4226978",
    "sg:postcode":"4600",
    "sg:province":"Ober\u00f6sterreich",
    "wof:name":"Frisierstube Doris - Dornst\u00e4dter Doris",
    "wof:placetype":"venue"
},
  "geometry": {"coordinates":[14.0218734741,48.1756591797],"type":"Point"}
}