{
  "type": "Feature",
  "properties": {
    "iso:country":"AT",
    "sg:address":"Nr 66",
    "sg:city":"St. Andr\u00e4",
    "sg:orig_category":"Tabaktrafiken",
    "sg:phone":"+43 4358 3893",
    "sg:postcode":"9433",
    "sg:province":"K\u00e4rnten",
    "wof:name":"Hambaumer Walburga",
    "wof:placetype":"venue"
},
  "geometry": {"coordinates":[14.821849823,46.7685317993],"type":"Point"}
}