{
  "type": "Feature",
  "properties": {
    "addr:full":"Bahnhof 151 Bezau Vorarlberg 6870",
    "addr:housenumber":"151",
    "addr:postcode":"6870",
    "addr:street":"Bahnhof",
    "iso:country":"AT",
    "sg:address":"Bahnhof 151",
    "sg:city":"Bezau",
    "sg:orig_category":"Transportunternehmen",
    "sg:phone":"+43 5514 2221",
    "sg:postcode":"6870",
    "sg:province":"Vorarlberg",
    "wof:name":"Ratz Jakob",
    "wof:placetype":"venue"
},
  "geometry": {"coordinates":[9.89752388,47.3811302185],"type":"Point"}
}