{
  "type": "Feature",
  "properties": {
    "iso:country":"AT",
    "sg:address":"Langackerg 11",
    "sg:city":"Wien",
    "sg:orig_category":"Heurigen / Buschenschank",
    "sg:phone":"+43 1 3203002",
    "sg:postcode":"1190",
    "sg:province":"Wien",
    "wof:name":"Wolf-K\u00f6ller",
    "wof:placetype":"venue"
},
  "geometry": {"coordinates":[16.3462333679,48.2563514709],"type":"Point"}
}