{
  "type": "Feature",
  "properties": {
    "iso:country":"AT",
    "sg:address":"Hauptstr 109",
    "sg:city":"Paternion",
    "sg:orig_category":"Lebensmittel / Einzelhandel",
    "sg:phone":"+43 4245 44805",
    "sg:postcode":"9711",
    "sg:province":"K\u00e4rnten",
    "wof:name":"ADEG Markt GmbH",
    "wof:placetype":"venue"
},
  "geometry": {"coordinates":[13.634970665,46.7136726379],"type":"Point"}
}