{
  "type": "Feature",
  "properties": {
    "addr:full":"Pradler Strasse 81 Innsbruck Tirol 6020",
    "addr:housenumber":"81",
    "addr:postcode":"6020",
    "addr:street":"Pradler Strasse;Tirol",
    "iso:country":"AT",
    "sg:address":"Pradler Strasse 81",
    "sg:city":"Innsbruck",
    "sg:classifiers":[
        {
            "category":"Communications",
            "subcategory":"Television Station",
            "type":"Services"
        }
    ],
    "sg:phone":"+43 512 343546",
    "sg:postcode":"6020",
    "sg:province":"Tirol",
    "sg:tags":[
        "array",
        "satellite",
        "aerial",
        "reception",
        "antenna"
    ],
    "wof:name":"Elektro Kranebitter",
    "wof:placetype":"venue"
},
  "geometry": {"coordinates":[11.4110136032,47.2631988525],"type":"Point"}
}