{
  "type": "Feature",
  "properties": {
    "iso:country":"AT",
    "sg:address":"Gigerg 1",
    "sg:city":"Wien",
    "sg:orig_category":"Lottokollekturen",
    "sg:phone":"+43 1 7120578",
    "sg:postcode":"1030",
    "sg:province":"Wien",
    "wof:name":"Freis Margit",
    "wof:placetype":"venue"
},
  "geometry": {"coordinates":[16.384979248,48.207698822],"type":"Point"}
}