{
  "type": "Feature",
  "properties": {
    "addr:full":"Wiener Str 86 Gloggnitz Nieder\u00f6sterreich 2640",
    "addr:postcode":"2640",
    "addr:street":"Niederoesterreich",
    "iso:country":"AT",
    "sg:address":"Wiener Str 86",
    "sg:city":"Gloggnitz",
    "sg:classifiers":[
        {
            "category":"Restaurant",
            "type":"Food & Drink"
        }
    ],
    "sg:phone":"+43 2662 40846",
    "sg:postcode":"2640",
    "sg:province":"Nieder\u00f6sterreich",
    "sg:tags":[
        "pizzeria"
    ],
    "wof:name":"Pizzeria-Ristorante il CAMINO",
    "wof:placetype":"venue"
},
  "geometry": {"coordinates":[15.954413414,47.6725921631],"type":"Point"}
}