{
  "type": "Feature",
  "properties": {
    "addr:full":"Quellenstr 74 Wien Wien 1100",
    "addr:housenumber":"74",
    "addr:postcode":"1100",
    "addr:street":"Quellenstr",
    "iso:country":"AT",
    "sg:address":"Quellenstr 74",
    "sg:city":"Wien",
    "sg:orig_category":"Transportunternehmen",
    "sg:phone":"+43 660 6516578",
    "sg:postcode":"1100",
    "sg:province":"Wien",
    "wof:name":"Drago Anin D Priocic KEG",
    "wof:placetype":"venue"
},
  "geometry": {"coordinates":[16.375787735,48.1755943298],"type":"Point"}
}