{
  "type": "Feature",
  "properties": {
    "addr:full":"Tanzwiese 14b Freistadt Ober\u00f6sterreich 4240",
    "addr:housenumber":"14b",
    "addr:postcode":"4240",
    "addr:street":"Tanzwiese",
    "iso:country":"AT",
    "sg:address":"Tanzwiese 14b",
    "sg:city":"Freistadt",
    "sg:orig_category":"Erdarbeiten",
    "sg:phone":"+43 699 11080881",
    "sg:postcode":"4240",
    "sg:province":"Ober\u00f6sterreich",
    "wof:name":"Andreas Pintar Baggerungen & Planierungen",
    "wof:placetype":"venue"
},
  "geometry": {"coordinates":[14.5046749115,48.5088806152],"type":"Point"}
}