{
  "type": "Feature",
  "properties": {
    "iso:country":"AT",
    "sg:address":"Gewerbestr 5",
    "sg:city":"Schweiggers",
    "sg:orig_category":"Autobusunternehmen",
    "sg:phone":"+43 2829 72710",
    "sg:postcode":"3931",
    "sg:province":"Nieder\u00f6sterreich",
    "wof:name":"Huber Josef GesmbH",
    "wof:placetype":"venue"
},
  "geometry": {"coordinates":[15.0664148331,48.6720962524],"type":"Point"}
}