{
  "type": "Feature",
  "properties": {
    "addr:full":"Pfeningberg 29 Krems an der Donau Nieder\u00f6sterreich 3500",
    "addr:housenumber":"29",
    "addr:postcode":"3500",
    "addr:street":"Pfeningberg",
    "iso:country":"AT",
    "sg:address":"Pfeningberg 29",
    "sg:city":"Krems an der Donau",
    "sg:classifiers":[
        {
            "category":"Communications",
            "subcategory":"Film & Video Production",
            "type":"Services"
        }
    ],
    "sg:phone":"+43 2732 71078",
    "sg:postcode":"3500",
    "sg:province":"Nieder\u00f6sterreich",
    "sg:tags":[
        "stove",
        "tiled",
        "accessory"
    ],
    "wof:name":"Herbert Sch\u00f6n",
    "wof:placetype":"venue"
},
  "geometry": {"coordinates":[15.5965108871,48.4088058472],"type":"Point"}
}