{
  "type": "Feature",
  "properties": {
    "iso:country":"AT",
    "sg:address":"Wollzeile 4",
    "sg:city":"Wien",
    "sg:classifiers":[
        {
            "category":"Government",
            "subcategory":"Fire Station",
            "type":"Public Place"
        }
    ],
    "sg:phone":"+43 1 5126268",
    "sg:postcode":"1010",
    "sg:province":"Wien",
    "sg:tags":[
        "altar",
        "fitting",
        "sanctuary"
    ],
    "wof:name":"Josef Janauschek & Comp",
    "wof:placetype":"venue"
},
  "geometry": {"coordinates":[16.374004364,48.2092018127],"type":"Point"}
}