{
  "type": "Feature",
  "properties": {
    "addr:full":"Nr 188 Saalbach Salzburg 5753",
    "addr:postcode":"5753",
    "addr:street":"Nr 188;Salzburg",
    "iso:country":"AT",
    "sg:address":"Nr 188",
    "sg:city":"Saalbach",
    "sg:orig_category":"Schlossereien",
    "sg:phone":"+43 6541 66450",
    "sg:postcode":"5753",
    "sg:province":"Salzburg",
    "wof:name":"Moser GesmbH",
    "wof:placetype":"venue"
},
  "geometry": {"coordinates":[12.6367301941,47.3899307251],"type":"Point"}
}