{
  "type": "Feature",
  "properties": {
    "addr:full":"Siezenheimer Strasse 41 Salzburg Salzburg 5020",
    "addr:housenumber":"41",
    "addr:postcode":"5020",
    "addr:street":"Siezenheimer Strasse;Salzburg",
    "iso:country":"AT",
    "sg:address":"Siezenheimer Strasse 41",
    "sg:city":"Salzburg",
    "sg:classifiers":[
        {
            "category":"Building & Trades",
            "subcategory":"Construction",
            "type":"Services"
        }
    ],
    "sg:phone":"+43 662 439340",
    "sg:postcode":"5020",
    "sg:province":"Salzburg",
    "sg:tags":[
        "flat",
        "steep",
        "roof",
        "waterproofing"
    ],
    "sg:website":"aquarex-sbg.at",
    "wof:name":"Aquarex Ges.m.b.H.",
    "wof:placetype":"venue"
},
  "geometry": {"coordinates":[13.0098085403,47.8059654236],"type":"Point"}
}