{
  "type": "Feature",
  "properties": {
    "addr:full":"Beckmanngasse 17 Wien Wien 1140",
    "addr:housenumber":"17",
    "addr:postcode":"1140",
    "addr:street":"Beckmanngasse",
    "iso:country":"AT",
    "sg:address":"Beckmanngasse 17",
    "sg:city":"Wien",
    "sg:classifiers":[
        {
            "category":"Farming",
            "subcategory":"Berry Farm",
            "type":"Manufacturing & Wholesale Goods"
        }
    ],
    "sg:phone":"+43 1 9822444",
    "sg:postcode":"1140",
    "sg:province":"Wien",
    "sg:tags":[
        "austrian",
        "wine"
    ],
    "wof:name":"OKE- Oberkleidererzeugung Ges.m.b.H",
    "wof:placetype":"venue"
},
  "geometry": {"coordinates":[16.3117694855,48.1926002502],"type":"Point"}
}