{
  "type": "Feature",
  "properties": {
    "addr:full":"Bahnhofstr 2 Ybbs an der Donau Nieder\u00f6sterreich 3370",
    "addr:housenumber":"2",
    "addr:postcode":"3370",
    "addr:street":"Bahnhofstr",
    "iso:country":"AT",
    "sg:address":"Bahnhofstr 2",
    "sg:city":"Ybbs an der Donau",
    "sg:orig_category":"Autoreparatur",
    "sg:phone":"+43 7412 52420",
    "sg:postcode":"3370",
    "sg:province":"Nieder\u00f6sterreich",
    "wof:name":"Januschkowetz Alois GesmbH",
    "wof:placetype":"venue"
},
  "geometry": {"coordinates":[15.0831537247,48.1758422852],"type":"Point"}
}