{
  "type": "Feature",
  "properties": {
    "addr:full":"Messererstr 16 Gr\u00fcnburg Ober\u00f6sterreich 4594",
    "addr:housenumber":"16",
    "addr:postcode":"4594",
    "addr:street":"Messererstr;Oberoesterreich",
    "iso:country":"AT",
    "sg:address":"Messererstr 16",
    "sg:city":"Gr\u00fcnburg",
    "sg:orig_category":"Installationsunternehmen",
    "sg:phone":"+43 7257 7223",
    "sg:postcode":"4594",
    "sg:province":"Ober\u00f6sterreich",
    "wof:name":"Augustin Walter Konz. Installations-Unternehmen f. Wasser u. Sanit\u00e4re Anlagen",
    "wof:placetype":"venue"
},
  "geometry": {"coordinates":[14.2625169754,47.9721374512],"type":"Point"}
}