{
  "type": "Feature",
  "properties": {
    "addr:full":"Nr 2 Treibach-Althofen K\u00e4rnten 9330",
    "addr:postcode":"9330",
    "addr:street":"Nr;Treibach-Althofen",
    "iso:country":"AT",
    "sg:address":"Nr 2",
    "sg:city":"Treibach-Althofen",
    "sg:orig_category":"Umwelttechnik",
    "sg:phone":"+43 4342 6225200",
    "sg:postcode":"9330",
    "sg:province":"K\u00e4rnten",
    "wof:name":"CEF-Austria International DI Dr Fleischhacker - Akkreditierte Pr\u00fcf- u \u00dcberwachungsstelle",
    "wof:placetype":"venue"
},
  "geometry": {"coordinates":[14.469953537,46.8701858521],"type":"Point"}
}