{
  "type": "Feature",
  "properties": {
    "iso:country":"AT",
    "sg:address":"Spitalg 16-20",
    "sg:city":"Allentsteig",
    "sg:orig_category":"Rettungsdienste",
    "sg:phone":"+43 2824 22440",
    "sg:postcode":"3804",
    "sg:province":"Nieder\u00f6sterreich",
    "wof:name":"Rotes Kreuz \u00f6sterr Bezirksstelle Allentsteig",
    "wof:placetype":"venue"
},
  "geometry": {"coordinates":[15.3292703629,48.6954879761],"type":"Point"}
}