{
  "type": "Feature",
  "properties": {
    "iso:country":"AT",
    "sg:address":"Leuzenhofg 6/12",
    "sg:city":"Graz",
    "sg:orig_category":"Psychotherapie",
    "sg:phone":"+43 316 716362",
    "sg:postcode":"8020",
    "sg:province":"Steiermark",
    "wof:name":"Friess Annemarie",
    "wof:placetype":"venue"
},
  "geometry": {"coordinates":[15.4182453156,47.0819358826],"type":"Point"}
}