{
  "type": "Feature",
  "properties": {
    "iso:country":"AT",
    "sg:address":"Speckbacherstr 15",
    "sg:city":"St. Johann in Tirol",
    "sg:orig_category":"Psychologen",
    "sg:phone":"+43 4353 5264668",
    "sg:postcode":"6380",
    "sg:province":"Tirol",
    "wof:name":"Posch Rita Mag",
    "wof:placetype":"venue"
},
  "geometry": {"coordinates":[12.4271974564,47.5212898254],"type":"Point"}
}