{
  "type": "Feature",
  "properties": {
    "addr:full":"Altenmarktstr 10 Neumarkt an der Ybbs Nieder\u00f6sterreich 3371",
    "addr:housenumber":"10;3371",
    "addr:street":"Altenmarktstr;Niederoesterreich",
    "iso:country":"AT",
    "sg:address":"Altenmarktstr 10",
    "sg:city":"Neumarkt an der Ybbs",
    "sg:orig_category":"Musikgruppen",
    "sg:phone":"+43 7412 55199",
    "sg:postcode":"3371",
    "sg:province":"Nieder\u00f6sterreich",
    "wof:name":"Musikverein Neumarkt a d Ybbs",
    "wof:placetype":"venue"
},
  "geometry": {"coordinates":[15.0610456467,48.1427879333],"type":"Point"}
}