{
  "type": "Feature",
  "properties": {
    "addr:full":"Burgg 32 Judenburg Steiermark 8750",
    "addr:housenumber":"32",
    "addr:postcode":"8750",
    "addr:street":"Burgg",
    "iso:country":"AT",
    "sg:address":"Burgg 32",
    "sg:city":"Judenburg",
    "sg:orig_category":"Apotheken",
    "sg:phone":"+43 4335 72820690",
    "sg:postcode":"8750",
    "sg:province":"Steiermark",
    "wof:name":"Stadt - Apotheke Mag pharm Dr Peter Gall KG",
    "wof:placetype":"venue"
},
  "geometry": {"coordinates":[14.6568222046,47.1684570312],"type":"Point"}
}