{
  "type": "Feature",
  "properties": {
    "addr:full":"Nr 198 Mariahof Steiermark 8812",
    "addr:postcode":"8812",
    "addr:street":"Nr 198",
    "iso:country":"AT",
    "sg:address":"Nr 198",
    "sg:city":"Mariahof",
    "sg:orig_category":"Elektroinstallationsunternehmen",
    "sg:phone":"+43 3584 2102",
    "sg:postcode":"8812",
    "sg:province":"Steiermark",
    "wof:name":"M\u00fchltaler Franz",
    "wof:placetype":"venue"
},
  "geometry": {"coordinates":[14.3994102478,47.0992660522],"type":"Point"}
}