{
  "type": "Feature",
  "properties": {
    "addr:full":"Pfarrangerweg Matrei in Osttirol Tirol 9971",
    "addr:postcode":"9971",
    "addr:street":"Pfarrangerweg",
    "iso:country":"AT",
    "sg:address":"Pfarrangerweg",
    "sg:city":"Matrei in Osttirol",
    "sg:orig_category":"Behinderungen / Leben Mit Behinderungen",
    "sg:phone":"+43 4875 6045",
    "sg:postcode":"9971",
    "sg:province":"Tirol",
    "wof:name":"Lebenshilfe Tirol - Werkst\u00e4tte",
    "wof:placetype":"venue"
},
  "geometry": {"coordinates":[12.5425128937,46.9974784851],"type":"Point"}
}