{
  "type": "Feature",
  "properties": {
    "addr:full":"Wiener Str 60 Wiener Neustadt Nieder\u00f6sterreich 2700",
    "addr:postcode":"2700",
    "addr:street":"60",
    "iso:country":"AT",
    "sg:address":"Wiener Str 60",
    "sg:city":"Wiener Neustadt",
    "sg:classifiers":[
        {
            "category":"Restaurant",
            "type":"Food & Drink"
        }
    ],
    "sg:phone":"+43 4326 2284330",
    "sg:postcode":"2700",
    "sg:province":"Nieder\u00f6sterreich",
    "sg:tags":[
        "pizzeria"
    ],
    "wof:name":"Pizzeria Bella Italia",
    "wof:placetype":"venue"
},
  "geometry": {"coordinates":[16.2453861237,47.8176498413],"type":"Point"}
}