{
  "type": "Feature",
  "properties": {
    "addr:full":"Reitern 67 Steeg Ober\u00f6sterreich 4823",
    "addr:housenumber":"67",
    "addr:postcode":"4823",
    "addr:street":"Reitern",
    "iso:country":"AT",
    "sg:address":"Reitern 67",
    "sg:city":"Steeg",
    "sg:orig_category":"Beschriftungen",
    "sg:phone":"+43 6135 7618",
    "sg:postcode":"4823",
    "sg:province":"Ober\u00f6sterreich",
    "wof:name":"Pilz - Werbeagentur",
    "wof:placetype":"venue"
},
  "geometry": {"coordinates":[13.6535558701,47.5907554626],"type":"Point"}
}