{
  "type": "Feature",
  "properties": {
    "iso:country":"AT",
    "sg:address":"Gutenhofer Str 32",
    "sg:city":"Himberg",
    "sg:orig_category":"Feuerwehren",
    "sg:phone":"+43 2235 86722",
    "sg:postcode":"2325",
    "sg:province":"Nieder\u00f6sterreich",
    "wof:name":"Freiwillige Feuerwehr Himberg",
    "wof:placetype":"venue"
},
  "geometry": {"coordinates":[16.4449443817,48.0769348145],"type":"Point"}
}