{
  "type": "Feature",
  "properties": {
    "addr:full":"Fischnalerstr 18 Innsbruck Tirol 6020",
    "addr:housenumber":"18",
    "addr:postcode":"6020",
    "addr:street":"Fischnalerstr;Tirol",
    "iso:country":"AT",
    "sg:address":"Fischnalerstr 18",
    "sg:city":"Innsbruck",
    "sg:orig_category":"Werbeagenturen",
    "sg:phone":"+43 512 273161",
    "sg:postcode":"6020",
    "sg:province":"Tirol",
    "wof:name":"Bernhart Johanna KEG",
    "wof:placetype":"venue"
},
  "geometry": {"coordinates":[11.3791885376,47.2610588074],"type":"Point"}
}