{
  "type": "Feature",
  "properties": {
    "addr:full":"Puntigamer Str 24 Liebenau Steiermark 8041",
    "addr:housenumber":"24",
    "addr:postcode":"8041",
    "addr:street":"Str",
    "iso:country":"AT",
    "sg:address":"Puntigamer Str 24",
    "sg:city":"Liebenau",
    "sg:orig_category":"Transportunternehmen",
    "sg:phone":"+43 4331 6472414",
    "sg:postcode":"8041",
    "sg:province":"Steiermark",
    "wof:name":"Friedl Markus",
    "wof:placetype":"venue"
},
  "geometry": {"coordinates":[15.455370903,47.0382881165],"type":"Point"}
}