{
  "type": "Feature",
  "properties": {
    "addr:full":"Kilianstrasse 5 Wartberg an der Krems Ober\u00f6sterreich 4552",
    "addr:housenumber":"5",
    "addr:postcode":"4552",
    "addr:street":"Kilianstrasse",
    "iso:country":"AT",
    "sg:address":"Kilianstrasse 5",
    "sg:city":"Wartberg an der Krems",
    "sg:orig_category":"Blanking, Punching, Stamping, Embossing And Drawing Dies, Progressive Dies",
    "sg:phone":"+43 7587 7999",
    "sg:postcode":"4552",
    "sg:province":"Ober\u00f6sterreich",
    "sg:website":"bestform.at",
    "wof:name":"Bestform Werkzeuge GmbH",
    "wof:placetype":"venue"
},
  "geometry": {"coordinates":[14.1199712753,47.9888877869],"type":"Point"}
}