{
  "type": "Feature",
  "properties": {
    "addr:full":"Wilhelminenstr 40 Wien Wien 1160",
    "addr:housenumber":"40",
    "addr:postcode":"1160",
    "addr:street":"Wilhelminenstr",
    "iso:country":"AT",
    "sg:address":"Wilhelminenstr 40",
    "sg:city":"Wien",
    "sg:orig_category":"Blumeneinzelhandel",
    "sg:phone":"+43 4314 803877",
    "sg:postcode":"1160",
    "sg:province":"Wien",
    "wof:name":"Blumen Andre Stadler",
    "wof:placetype":"venue"
},
  "geometry": {"coordinates":[16.3154792786,48.2167320251],"type":"Point"}
}