{
  "type": "Feature",
  "properties": {
    "addr:full":"Oberdorf 1 Weng im Innkreis Ober\u00f6sterreich 4952",
    "addr:housenumber":"1",
    "addr:postcode":"4952",
    "addr:street":"Oberdorf",
    "iso:country":"AT",
    "sg:address":"Oberdorf 1",
    "sg:city":"Weng im Innkreis",
    "sg:classifiers":[
        {
            "category":"Utilities",
            "subcategory":"Natural Gas",
            "type":"Services"
        }
    ],
    "sg:phone":"+43 7723 50120",
    "sg:postcode":"4952",
    "sg:province":"Ober\u00f6sterreich",
    "sg:tags":[
        "fertilizer",
        "biological"
    ],
    "sg:website":"agrarprofi.de",
    "wof:name":"Lagerhaus Auer KG",
    "wof:placetype":"venue"
},
  "geometry": {"coordinates":[13.1799316406,48.233417511],"type":"Point"}
}