{
  "type": "Feature",
  "properties": {
    "iso:country":"AT",
    "sg:address":"Laaer Str 1",
    "sg:city":"Ernstbrunn",
    "sg:orig_category":"Bibliotheken",
    "sg:phone":"+43 2576 30173",
    "sg:postcode":"2115",
    "sg:province":"Nieder\u00f6sterreich",
    "wof:name":"Gemeindeb\u00fccherei Ernstbrunn",
    "wof:placetype":"venue"
},
  "geometry": {"coordinates":[16.3610057831,48.5296974182],"type":"Point"}
}