{
  "type": "Feature",
  "properties": {
    "addr:full":"Nr 12 Mallnitz K\u00e4rnten 9822",
    "addr:postcode":"9822",
    "addr:street":"Nr;Mallnitz Kaernten",
    "iso:country":"AT",
    "sg:address":"Nr 12",
    "sg:city":"Mallnitz",
    "sg:orig_category":"Volksschulen",
    "sg:phone":"+43 4347 84716",
    "sg:postcode":"9822",
    "sg:province":"K\u00e4rnten",
    "wof:name":"Volksschule",
    "wof:placetype":"venue"
},
  "geometry": {"coordinates":[13.1692886353,46.9889678955],"type":"Point"}
}