{
  "type": "Feature",
  "properties": {
    "addr:full":"Pelikanstrasse 4 Pucking Ober\u00f6sterreich 4055",
    "addr:housenumber":"4",
    "addr:postcode":"4055",
    "addr:street":"Pelikanstrasse",
    "iso:country":"AT",
    "sg:address":"Pelikanstrasse 4",
    "sg:city":"Pucking",
    "sg:classifiers":[
        {
            "category":"Military Area",
            "subcategory":"Armory",
            "type":"Public Place"
        }
    ],
    "sg:phone":"+43 7229 883500",
    "sg:postcode":"4055",
    "sg:province":"Ober\u00f6sterreich",
    "sg:tags":[
        "changing",
        "cubicle"
    ],
    "sg:website":"bau-set.at",
    "wof:name":"Bau-Set Holzm\u00fcller + Handle Ges.m.b.H.",
    "wof:placetype":"venue"
},
  "geometry": {"coordinates":[14.2105789185,48.1924858093],"type":"Point"}
}