{
  "type": "Feature",
  "properties": {
    "iso:country":"AT",
    "sg:address":"Dammstr 67A",
    "sg:city":"Wolfurt",
    "sg:classifiers":[
        {
            "category":"Home & Garden",
            "subcategory":"Garden Supply",
            "type":"Retail Goods"
        }
    ],
    "sg:phone":"+43 4355 7453294",
    "sg:postcode":"6922",
    "sg:province":"Vorarlberg",
    "sg:tags":[
        "schotter",
        "sand",
        "u"
    ],
    "wof:name":"Gasser Helmut Kies- u Sandgewinnung, Erdbewegung, Transporte GesmbH & Co KG",
    "wof:placetype":"venue"
},
  "geometry": {"coordinates":[9.7374095917,47.4842033386],"type":"Point"}
}