{
  "type": "Feature",
  "properties": {
    "addr:full":"Hauptstr 28 Kopfing im Innkreis Ober\u00f6sterreich 4794",
    "addr:housenumber":"28",
    "addr:postcode":"4794",
    "addr:street":"Hauptstr;Im Innkreis",
    "iso:country":"AT",
    "sg:address":"Hauptstr 28",
    "sg:city":"Kopfing im Innkreis",
    "sg:classifiers":[
        {
            "category":"Internet Cafe",
            "subcategory":"None",
            "type":"Food & Drink"
        }
    ],
    "sg:phone":"+43 4366 41546759",
    "sg:postcode":"4794",
    "sg:province":"Ober\u00f6sterreich",
    "wof:name":"Maier & Niessner Web Info Systems KEG",
    "wof:placetype":"venue"
},
  "geometry": {"coordinates":[13.6581401825,48.4399528503],"type":"Point"}
}