{
  "type": "Feature",
  "properties": {
    "iso:country":"AT",
    "sg:address":"Florian-Berndl-G 44",
    "sg:city":"Wien",
    "sg:orig_category":"Chemikalien",
    "sg:phone":"+43 1 2034041",
    "sg:postcode":"1220",
    "sg:province":"Wien",
    "wof:name":"Prochema HandelsgesmbH",
    "wof:placetype":"venue"
},
  "geometry": {"coordinates":[16.4332466125,48.2340545654],"type":"Point"}
}