{
  "type": "Feature",
  "properties": {
    "addr:full":"Anger 421 Litzelsdorf Burgenland 7532",
    "addr:housenumber":"421",
    "addr:postcode":"7532",
    "addr:street":"Anger",
    "iso:country":"AT",
    "sg:address":"Anger 421",
    "sg:city":"Litzelsdorf",
    "sg:orig_category":"Bauunternehmen",
    "sg:phone":"+43 4333 582224",
    "sg:postcode":"7532",
    "sg:province":"Burgenland",
    "wof:name":"Hochwarter Hoch- Tief- u StahlbetonbaugesmbH",
    "wof:placetype":"venue"
},
  "geometry": {"coordinates":[16.1587600708,47.2126274109],"type":"Point"}
}