{
  "type": "Feature",
  "properties": {
    "addr:full":"Rathauspl 1 Leobersdorf Nieder\u00f6sterreich 2544",
    "addr:housenumber":"1",
    "addr:postcode":"2544",
    "addr:street":"Rathauspl",
    "iso:country":"AT",
    "sg:address":"Rathauspl 1",
    "sg:city":"Leobersdorf",
    "sg:orig_category":"Gemeinden",
    "sg:phone":"+43 2256 623960",
    "sg:postcode":"2544",
    "sg:province":"Nieder\u00f6sterreich",
    "wof:name":"Gemeindeamt Marktgemeinde Leobersdorf",
    "wof:placetype":"venue"
},
  "geometry": {"coordinates":[16.2169094086,47.9288444519],"type":"Point"}
}