{
  "type": "Feature",
  "properties": {
    "addr:full":"Nr 68 Mureck Steiermark 8480",
    "addr:postcode":"8480",
    "addr:street":"Nr",
    "iso:country":"AT",
    "sg:address":"Nr 68",
    "sg:city":"Mureck",
    "sg:orig_category":"Tischlereien",
    "sg:phone":"+43 4334 722604",
    "sg:postcode":"8480",
    "sg:province":"Steiermark",
    "wof:name":"Fink Rudolf",
    "wof:placetype":"venue"
},
  "geometry": {"coordinates":[15.7676620483,46.7260055542],"type":"Point"}
}