{
  "type": "Feature",
  "properties": {
    "addr:full":"Alte Poststr 152 Graz Steiermark 8020",
    "addr:housenumber":"152",
    "addr:postcode":"8020",
    "iso:country":"AT",
    "sg:address":"Alte Poststr 152",
    "sg:city":"Graz",
    "sg:classifiers":[
        {
            "category":"Internet Cafe",
            "subcategory":"None",
            "type":"Food & Drink"
        }
    ],
    "sg:phone":"+43 316 70960",
    "sg:postcode":"8020",
    "sg:province":"Steiermark",
    "wof:name":"TPI / ComCare",
    "wof:placetype":"venue"
},
  "geometry": {"coordinates":[15.4093513489,47.0691299438],"type":"Point"}
}