{
  "type": "Feature",
  "properties": {
    "addr:full":"Mariahilfer Str 126 Wien Wien 1070",
    "addr:housenumber":"126",
    "addr:postcode":"1070",
    "iso:country":"AT",
    "sg:address":"Mariahilfer Str 126",
    "sg:city":"Wien",
    "sg:orig_category":"Tabaktrafiken",
    "sg:phone":"+43 1 5262410",
    "sg:postcode":"1070",
    "sg:province":"Wien",
    "wof:name":"Bittermann Friederike",
    "wof:placetype":"venue"
},
  "geometry": {"coordinates":[16.3403701782,48.1961288452],"type":"Point"}
}