{
  "type": "Feature",
  "properties": {
    "addr:full":"F\u00f6hrenweg 1 Hallwang Salzburg 5300",
    "addr:housenumber":"1",
    "addr:postcode":"5300",
    "addr:street":"Foehrenweg;Salzburg",
    "iso:country":"AT",
    "sg:address":"F\u00f6hrenweg 1",
    "sg:city":"Hallwang",
    "sg:orig_category":"Elektrotechnik, Elektroinstallationsunternehmen",
    "sg:phone":"+43 662 6641610",
    "sg:postcode":"5300",
    "sg:province":"Salzburg",
    "wof:name":"E-TEAM Friedrich Lehner - Elektrotechnik",
    "wof:placetype":"venue"
},
  "geometry": {"coordinates":[13.0853147507,47.8517684937],"type":"Point"}
}