{
  "type": "Feature",
  "properties": {
    "iso:country":"AT",
    "sg:address":"Kirchenpl 1",
    "sg:city":"Hafnerbach",
    "sg:orig_category":"Non-Classified Establishments",
    "sg:phone":"+43 2749 2279",
    "sg:postcode":"3386",
    "sg:province":"Nieder\u00f6sterreich",
    "wof:name":"Pfarramt",
    "wof:placetype":"venue"
},
  "geometry": {"coordinates":[15.4880743027,48.2166900635],"type":"Point"}
}