{
  "type": "Feature",
  "properties": {
    "addr:full":"Hubergutstrasse 14b Steyr Ober\u00f6sterreich 4400",
    "addr:housenumber":"14b",
    "addr:postcode":"4400",
    "addr:street":"Hubergutstrasse;Oberoesterreich",
    "iso:country":"AT",
    "sg:address":"Hubergutstrasse 14b",
    "sg:city":"Steyr",
    "sg:classifiers":[
        {
            "category":"Ferry Terminal",
            "type":"Transportation"
        }
    ],
    "sg:phone":"+43 7252 41684",
    "sg:postcode":"4400",
    "sg:province":"Ober\u00f6sterreich",
    "sg:tags":[
        "nitride",
        "tool",
        "boron",
        "cbn",
        "cubic"
    ],
    "sg:website":"dibo.at",
    "wof:name":"DIBO Diamantwerkzeuge GmbH",
    "wof:placetype":"venue"
},
  "geometry": {"coordinates":[14.4243021011,48.0288925171],"type":"Point"}
}