{
  "type": "Feature",
  "properties": {
    "addr:full":"Ge\u00dflg 7 Wien Wien 1230",
    "addr:housenumber":"7",
    "addr:postcode":"1230",
    "addr:street":"Gesslg",
    "iso:country":"AT",
    "sg:address":"Ge\u00dflg 7",
    "sg:city":"Wien",
    "sg:orig_category":"Geschenkartikel",
    "sg:phone":"+43 4318 874201",
    "sg:postcode":"1230",
    "sg:province":"Wien",
    "sg:website":"dieseidenstrasse.at",
    "wof:name":"Die Seidenstrasse Viveca Hameder",
    "wof:placetype":"venue"
},
  "geometry": {"coordinates":[16.2822799683,48.1347465515],"type":"Point"}
}