{
  "type": "Feature",
  "properties": {
    "addr:full":"Goisern 172 Bad Goisern Ober\u00f6sterreich 4822",
    "addr:housenumber":"172",
    "addr:postcode":"4822",
    "addr:street":"Goisern",
    "iso:country":"AT",
    "sg:address":"Goisern 172",
    "sg:city":"Bad Goisern",
    "sg:classifiers":[
        {
            "category":"Building & Trades",
            "subcategory":"Plumbing",
            "type":"Services"
        }
    ],
    "sg:phone":"+43 6135 8445",
    "sg:postcode":"4822",
    "sg:province":"Ober\u00f6sterreich",
    "sg:tags":[
        "supraregional",
        "gas"
    ],
    "wof:name":"Andreas Winterauer",
    "wof:placetype":"venue"
},
  "geometry": {"coordinates":[13.6114711761,47.6528816223],"type":"Point"}
}