{
  "type": "Feature",
  "properties": {
    "addr:full":"Praterstr 33 Wien Wien 1020",
    "addr:housenumber":"33",
    "addr:postcode":"1020",
    "addr:street":"Praterstr",
    "iso:country":"AT",
    "sg:address":"Praterstr 33",
    "sg:city":"Wien",
    "sg:orig_category":"Lebensmittel / Einzelhandel",
    "sg:phone":"+43 1 2164422",
    "sg:postcode":"1020",
    "sg:province":"Wien",
    "wof:name":"Gestio Lebensmittel AG",
    "wof:placetype":"venue"
},
  "geometry": {"coordinates":[16.3844356537,48.2147674561],"type":"Point"}
}