{
  "type": "Feature",
  "properties": {
    "iso:country":"AT",
    "sg:address":"Nr 72",
    "sg:city":"Orth an der Donau",
    "sg:orig_category":"Handelsagenturen",
    "sg:phone":"+43 4322 122546",
    "sg:postcode":"2304",
    "sg:province":"Nieder\u00f6sterreich",
    "wof:name":"Grasl Walter",
    "wof:placetype":"venue"
},
  "geometry": {"coordinates":[16.6618881226,48.1524505615],"type":"Point"}
}