{
  "type": "Feature",
  "properties": {
    "addr:full":"Nikolaus-August-Otto-Str 7 Wiener Neustadt Nieder\u00f6sterreich 2700",
    "addr:housenumber":"7",
    "addr:postcode":"2700",
    "addr:street":"Nikolaus-August-Otto-Str",
    "iso:country":"AT",
    "sg:address":"Nikolaus-August-Otto-Str 7",
    "sg:city":"Wiener Neustadt",
    "sg:orig_category":"Sicherheitstechnik",
    "sg:phone":"+43 4326 2224255",
    "sg:postcode":"2700",
    "sg:province":"Nieder\u00f6sterreich",
    "sg:website":"explosioncontrol.com",
    "wof:name":"EXCO Erzeugung von explosionsverhinderndem F\u00fcllmaterial",
    "wof:placetype":"venue"
},
  "geometry": {"coordinates":[16.2491436005,47.8424339294],"type":"Point"}
}