{
  "type": "Feature",
  "properties": {
    "addr:full":"Alleestr 30 Walchsee Tirol 6344",
    "addr:housenumber":"30",
    "addr:postcode":"6344",
    "addr:street":"Alleestr;Tirol",
    "iso:country":"AT",
    "sg:address":"Alleestr 30",
    "sg:city":"Walchsee",
    "sg:orig_category":"Massageschulen U -Kurse",
    "sg:phone":"+43 5374 52450",
    "sg:postcode":"6344",
    "sg:province":"Tirol",
    "wof:name":"Massageschule Dr-Vodder-Schule",
    "wof:placetype":"venue"
},
  "geometry": {"coordinates":[12.3169164658,47.6534347534],"type":"Point"}
}