{
  "type": "Feature",
  "properties": {
    "addr:full":"Hauptstr 63 Kobersdorf Burgenland 7332",
    "addr:housenumber":"63",
    "addr:postcode":"7332",
    "addr:street":"Hauptstr",
    "iso:country":"AT",
    "sg:address":"Hauptstr 63",
    "sg:city":"Kobersdorf",
    "sg:orig_category":"Bauunternehmen",
    "sg:phone":"+43 2618 20140",
    "sg:postcode":"7332",
    "sg:province":"Burgenland",
    "wof:name":"STEINER BAU GmbH",
    "wof:placetype":"venue"
},
  "geometry": {"coordinates":[16.3972415924,47.5933189392],"type":"Point"}
}