{
  "type": "Feature",
  "properties": {
    "addr:full":"Kundratstr 3 Wien Wien 1100",
    "addr:housenumber":"3",
    "addr:postcode":"1100",
    "addr:street":"Kundratstr",
    "iso:country":"AT",
    "sg:address":"Kundratstr 3",
    "sg:city":"Wien",
    "sg:orig_category":"Beratungsstellen",
    "sg:phone":"+43 4316 01915454",
    "sg:postcode":"1100",
    "sg:province":"Wien",
    "wof:name":"M\u00e4nner Gesundheitszentrum im Sozialmedizinischen Zentrum S\u00fcd",
    "wof:placetype":"venue"
},
  "geometry": {"coordinates":[16.34856987,48.1747398376],"type":"Point"}
}