{
  "type": "Feature",
  "properties": {
    "addr:full":"Wipplingerstr 15 Wien Wien 1010",
    "addr:housenumber":"15",
    "addr:postcode":"1010",
    "addr:street":"Wipplingerstr",
    "iso:country":"AT",
    "sg:address":"Wipplingerstr 15",
    "sg:city":"Wien",
    "sg:orig_category":"Fotoapparate U -Artikel / Einzelhandel",
    "sg:phone":"+43 1 53362810",
    "sg:postcode":"1010",
    "sg:province":"Wien",
    "wof:name":"Hartlauer HandelsgesmbH",
    "wof:placetype":"venue"
},
  "geometry": {"coordinates":[16.3695335388,48.2121696472],"type":"Point"}
}