{
  "type": "Feature",
  "properties": {
    "addr:full":"Geusaugasse 41 Wien Wien 1030",
    "addr:housenumber":"41",
    "addr:postcode":"1030",
    "addr:street":"Geusaugasse",
    "iso:country":"AT",
    "sg:address":"Geusaugasse 41",
    "sg:city":"Wien",
    "sg:classifiers":[
        {
            "category":"Autos & Motor Vehicles",
            "subcategory":"Fuel & Gas Station",
            "type":"Retail Goods"
        }
    ],
    "sg:phone":"+43 1 7134674",
    "sg:postcode":"1030",
    "sg:province":"Wien",
    "sg:tags":[
        "appliance",
        "heating"
    ],
    "wof:name":"Bican Ges.m.b.H.",
    "wof:placetype":"venue"
},
  "geometry": {"coordinates":[16.39453125,48.2038154602],"type":"Point"}
}