{
  "type": "Feature",
  "properties": {
    "addr:full":"H\u00f6henweg 7 Hallwang Salzburg 5300",
    "addr:housenumber":"7",
    "addr:postcode":"5300",
    "addr:street":"Hoehenweg;Salzburg",
    "iso:country":"AT",
    "sg:address":"H\u00f6henweg 7",
    "sg:city":"Hallwang",
    "sg:orig_category":"Holzhandel",
    "sg:phone":"+43 662 661895",
    "sg:postcode":"5300",
    "sg:province":"Salzburg",
    "wof:name":"Westa HandelsgesmbH",
    "wof:placetype":"venue"
},
  "geometry": {"coordinates":[13.0907793045,47.8326797485],"type":"Point"}
}