{
  "type": "Feature",
  "properties": {
    "addr:full":"Unterpurkla 30 Unterpurkla Steiermark 8484",
    "addr:housenumber":"30",
    "addr:postcode":"8484",
    "addr:street":"Unterpurkla",
    "iso:country":"AT",
    "sg:address":"Unterpurkla 30",
    "sg:city":"Unterpurkla",
    "sg:classifiers":[
        {
            "category":"Home & Garden",
            "subcategory":"Carpets & Floor Coverings",
            "type":"Retail Goods"
        }
    ],
    "sg:phone":"+43 3475 2255",
    "sg:postcode":"8484",
    "sg:province":"Steiermark",
    "sg:tags":[
        "grout",
        "adhesive",
        "tiles"
    ],
    "sg:website":"fliesen-semlitsch.at",
    "wof:name":"Rudolf Semlitsch",
    "wof:placetype":"venue"
},
  "geometry": {"coordinates":[15.90346241,46.7319793701],"type":"Point"}
}