{
  "type": "Feature",
  "properties": {
    "addr:full":"Gemeindeweg 47 Gerasdorf Nieder\u00f6sterreich 2201",
    "addr:housenumber":"47",
    "addr:postcode":"2201",
    "addr:street":"Gemeindeweg",
    "iso:country":"AT",
    "sg:address":"Gemeindeweg 47",
    "sg:city":"Gerasdorf",
    "sg:classifiers":[
        {
            "category":"Professional",
            "subcategory":"Computer Services",
            "type":"Services"
        }
    ],
    "sg:phone":"+43 2246 3389",
    "sg:postcode":"2201",
    "sg:province":"Nieder\u00f6sterreich",
    "sg:tags":[
        "software"
    ],
    "wof:name":"Schneider Brigitte GesmbH",
    "wof:placetype":"venue"
},
  "geometry": {"coordinates":[16.4487266541,48.2962036133],"type":"Point"}
}