{
  "type": "Feature",
  "properties": {
    "addr:full":"Linzer Str 26 Enns Ober\u00f6sterreich 4470",
    "addr:housenumber":"26",
    "addr:postcode":"4470",
    "addr:street":"Linzer Str",
    "iso:country":"AT",
    "sg:address":"Linzer Str 26",
    "sg:city":"Enns",
    "sg:orig_category":"Friseure U Frisiersalons",
    "sg:phone":"+43 7223 83822",
    "sg:postcode":"4470",
    "sg:province":"Ober\u00f6sterreich",
    "wof:name":"Friseur Gabi Inh Gabriele Blatterer",
    "wof:placetype":"venue"
},
  "geometry": {"coordinates":[14.4766674042,48.2147369385],"type":"Point"}
}