{
  "type": "Feature",
  "properties": {
    "addr:full":"Neubaustr 25 St. Valentin Nieder\u00f6sterreich 4300",
    "addr:housenumber":"25",
    "addr:postcode":"4300",
    "addr:street":"Neubaustr",
    "iso:country":"AT",
    "sg:address":"Neubaustr 25",
    "sg:city":"St. Valentin",
    "sg:orig_category":"Rettungsdienste",
    "sg:phone":"+43 7435 522440",
    "sg:postcode":"4300",
    "sg:province":"Nieder\u00f6sterreich",
    "wof:name":"Rotes Kreuz \u00f6sterr Bezirksstelle St Valentin",
    "wof:placetype":"venue"
},
  "geometry": {"coordinates":[14.5267114639,48.1767807007],"type":"Point"}
}