{
  "type": "Feature",
  "properties": {
    "addr:full":"Sparbach 4 Vitis Nieder\u00f6sterreich 3902",
    "addr:housenumber":"4",
    "addr:postcode":"3902",
    "addr:street":"Sparbach",
    "iso:country":"AT",
    "sg:address":"Sparbach 4",
    "sg:city":"Vitis",
    "sg:orig_category":"Ingenieurkonsulenten / Zivilingenieure",
    "sg:phone":"+43 2841 86590",
    "sg:postcode":"3902",
    "sg:province":"Nieder\u00f6sterreich",
    "wof:name":"Schaller Michael Dipl-Ing",
    "wof:placetype":"venue"
},
  "geometry": {"coordinates":[15.2154846191,48.748260498],"type":"Point"}
}