{
  "type": "Feature",
  "properties": {
    "iso:country":"AT",
    "sg:address":"Erzherzog-Rainer-Ring 14",
    "sg:city":"Baden",
    "sg:orig_category":"Handelsagenturen",
    "sg:phone":"+43 4322 52259286",
    "sg:postcode":"2500",
    "sg:province":"Nieder\u00f6sterreich",
    "wof:name":"Agentur Stollek",
    "wof:placetype":"venue"
},
  "geometry": {"coordinates":[16.2319717407,48.0082588196],"type":"Point"}
}