{
  "type": "Feature",
  "properties": {
    "iso:country":"AT",
    "sg:address":"Werk-VI-Str 57/Objekt 64",
    "sg:city":"Kapfenberg",
    "sg:orig_category":"Schlossereien",
    "sg:phone":"+43 4338 62321510",
    "sg:postcode":"8605",
    "sg:province":"Steiermark",
    "wof:name":"MBS Metallbau Scheiflinger GmbH",
    "wof:placetype":"venue"
},
  "geometry": {"coordinates":[15.3362779617,47.4528312683],"type":"Point"}
}