{
  "type": "Feature",
  "properties": {
    "addr:full":"Brigittenauer L\u00e4nde 42 Wien Wien 1200",
    "addr:housenumber":"42",
    "addr:postcode":"1200",
    "iso:country":"AT",
    "sg:address":"Brigittenauer L\u00e4nde 42",
    "sg:city":"Wien",
    "sg:orig_category":"Behinderungen / Leben Mit Behinderungen",
    "sg:phone":"+43 1 3326134",
    "sg:postcode":"1200",
    "sg:province":"Wien",
    "wof:name":"\u00f6sterreichischer Behindertensportverband",
    "wof:placetype":"venue"
},
  "geometry": {"coordinates":[16.3658695221,48.2281265259],"type":"Point"}
}