{
  "type": "Feature",
  "properties": {
    "addr:full":"Garnisong 4 Wien Wien 1090",
    "addr:housenumber":"4",
    "addr:postcode":"1090",
    "addr:street":"Garnisong",
    "iso:country":"AT",
    "sg:address":"Garnisong 4",
    "sg:city":"Wien",
    "sg:orig_category":"Immobilienverwaltungen",
    "sg:phone":"+43 1 4068103",
    "sg:postcode":"1090",
    "sg:province":"Wien",
    "wof:name":"Mc MAHON Immobilienverwertung GmbH",
    "wof:placetype":"venue"
},
  "geometry": {"coordinates":[16.3567638397,48.2150840759],"type":"Point"}
}