{
  "type": "Feature",
  "properties": {
    "addr:full":"Schulg 17 Fernitz Steiermark 8072",
    "addr:housenumber":"17",
    "addr:postcode":"8072",
    "addr:street":"Schulg",
    "iso:country":"AT",
    "sg:address":"Schulg 17",
    "sg:city":"Fernitz",
    "sg:orig_category":"Volksschulen",
    "sg:phone":"+43 3135 524800",
    "sg:postcode":"8072",
    "sg:province":"Steiermark",
    "wof:name":"Volksschule",
    "wof:placetype":"venue"
},
  "geometry": {"coordinates":[15.5020198822,46.9724388123],"type":"Point"}
}