{
  "type": "Feature",
  "properties": {
    "addr:full":"Haller Str. 233  Innsbruck Tirol 6020",
    "addr:housenumber":"233",
    "addr:postcode":"6020",
    "addr:street":"Str.;Tirol",
    "iso:country":"AT",
    "sg:address":"Haller Str. 233 ",
    "sg:city":"Innsbruck",
    "sg:classifiers":[
        {
            "category":"Autos & Motor Vehicles",
            "subcategory":"Automobile Sales",
            "type":"Retail Goods"
        }
    ],
    "sg:phone":"+43 4351 2264265",
    "sg:postcode":"6020",
    "sg:province":"Tirol",
    "sg:tags":[
        "motor-cars"
    ],
    "wof:name":"AUTOHAUS PRAXMARER GMBH",
    "wof:placetype":"venue"
},
  "geometry": {"coordinates":[11.4405231476,47.2769546509],"type":"Point"}
}