{
  "type": "Feature",
  "properties": {
    "addr:full":"Schulg 1 Weibern Ober\u00f6sterreich 4675",
    "addr:housenumber":"1",
    "addr:postcode":"4675",
    "addr:street":"Schulg;Oberoesterreich",
    "iso:country":"AT",
    "sg:address":"Schulg 1",
    "sg:city":"Weibern",
    "sg:orig_category":"Volksschulen",
    "sg:phone":"+43 7732 2524",
    "sg:postcode":"4675",
    "sg:province":"Ober\u00f6sterreich",
    "wof:name":"Volksschule",
    "wof:placetype":"venue"
},
  "geometry": {"coordinates":[13.701883316,48.1824684143],"type":"Point"}
}