{
  "type": "Feature",
  "properties": {
    "iso:country":"AT",
    "sg:address":"Donauw\u00f6rther Str 1",
    "sg:city":"Perchtoldsdorf",
    "sg:orig_category":"Physiotherapie",
    "sg:phone":"+43 4367 63738001",
    "sg:postcode":"2380",
    "sg:province":"Nieder\u00f6sterreich",
    "wof:name":"Fuchs Hermann Zentrum f orthop Schmerztherapie",
    "wof:placetype":"venue"
},
  "geometry": {"coordinates":[16.2697257996,48.1173057556],"type":"Point"}
}