{
  "type": "Feature",
  "properties": {
    "addr:full":"W\u00e4hringer Str 133 Wien Wien 1180",
    "addr:housenumber":"133",
    "addr:postcode":"1180",
    "addr:street":"Str",
    "iso:country":"AT",
    "sg:address":"W\u00e4hringer Str 133",
    "sg:city":"Wien",
    "sg:orig_category":"Musikagenturen",
    "sg:phone":"+43 1 4056502",
    "sg:postcode":"1180",
    "sg:province":"Wien",
    "wof:name":"Rosee Brigitte",
    "wof:placetype":"venue"
},
  "geometry": {"coordinates":[16.337474823,48.2276153564],"type":"Point"}
}