{
  "type": "Feature",
  "properties": {
    "iso:country":"AT",
    "sg:address":"Favoritenstr 88",
    "sg:city":"Wien",
    "sg:orig_category":"Friseure U Frisiersalons",
    "sg:phone":"+43 4319 559505",
    "sg:postcode":"1100",
    "sg:province":"Wien",
    "wof:name":"Jung Walter Haare - Make Up - Styling",
    "wof:placetype":"venue"
},
  "geometry": {"coordinates":[16.3749237061,48.1817626953],"type":"Point"}
}