{
  "type": "Feature",
  "properties": {
    "addr:full":"Erlachweg 3 Braunau am Inn Ober\u00f6sterreich 5280",
    "addr:housenumber":"3",
    "addr:postcode":"5280",
    "addr:street":"Erlachweg",
    "iso:country":"AT",
    "sg:address":"Erlachweg 3",
    "sg:city":"Braunau am Inn",
    "sg:orig_category":"Versicherungsunternehmen",
    "sg:phone":"+43 7722 8960",
    "sg:postcode":"5280",
    "sg:province":"Ober\u00f6sterreich",
    "wof:name":"Allianz Elementar Versicherungs-AG",
    "wof:placetype":"venue"
},
  "geometry": {"coordinates":[13.0449733734,48.2525634766],"type":"Point"}
}