{
  "type": "Feature",
  "properties": {
    "addr:full":"Sindelarg 88 Wien Wien 1100",
    "addr:housenumber":"88",
    "addr:postcode":"1100",
    "addr:street":"Sindelarg",
    "iso:country":"AT",
    "sg:address":"Sindelarg 88",
    "sg:city":"Wien",
    "sg:orig_category":"Bremsen- U Kupplungsdienste",
    "sg:phone":"+43 1 68811020",
    "sg:postcode":"1100",
    "sg:province":"Wien",
    "wof:name":"Klimek Gerhard",
    "wof:placetype":"venue"
},
  "geometry": {"coordinates":[16.4064483643,48.1544685364],"type":"Point"}
}