{
  "type": "Feature",
  "properties": {
    "iso:country":"AT",
    "sg:address":"Nr 85",
    "sg:city":"Maria Elend",
    "sg:classifiers":[
        {
            "category":"Taxi",
            "type":"Transportation"
        }
    ],
    "sg:phone":"+43 4342 538798",
    "sg:postcode":"9182",
    "sg:province":"K\u00e4rnten",
    "sg:tags":[
        "personentransporte",
        "u"
    ],
    "wof:name":"Taxi Rath",
    "wof:placetype":"venue"
},
  "geometry": {"coordinates":[14.0826892853,46.5308189392],"type":"Point"}
}