{
  "type": "Feature",
  "properties": {
    "addr:full":"Karawankenblickstr 161 Klagenfurt K\u00e4rnten 9020",
    "addr:housenumber":"161",
    "addr:postcode":"9020",
    "addr:street":"Kaernten",
    "iso:country":"AT",
    "sg:address":"Karawankenblickstr 161",
    "sg:city":"Klagenfurt",
    "sg:orig_category":"Gerichtsdolmetscher",
    "sg:phone":"+43 463 229665",
    "sg:postcode":"9020",
    "sg:province":"K\u00e4rnten",
    "wof:name":"Marschner Arnulf Prof",
    "wof:placetype":"venue"
},
  "geometry": {"coordinates":[14.2929410934,46.6041641235],"type":"Point"}
}