{
  "type": "Feature",
  "properties": {
    "addr:full":"Michaelerstrasse 18/2 Wien Wien 1180",
    "addr:housenumber":"18 / 2",
    "addr:postcode":"1180",
    "addr:street":"Michaelerstrasse",
    "iso:country":"AT",
    "sg:address":"Michaelerstrasse 18/2",
    "sg:city":"Wien",
    "sg:classifiers":[
        {
            "category":"Government",
            "subcategory":"Department Of Motor Vehicles",
            "type":"Public Place"
        }
    ],
    "sg:phone":"+43 676 3319436",
    "sg:postcode":"1180",
    "sg:province":"Wien",
    "sg:tags":[
        "truck",
        "purpose"
    ],
    "wof:name":"Cheresi Constantin",
    "wof:placetype":"venue"
},
  "geometry": {"coordinates":[16.3467483521,48.2290725708],"type":"Point"}
}