{
  "type": "Feature",
  "properties": {
    "addr:full":"St. Veiter Str 54 St. Veit Steiermark 8046",
    "addr:housenumber":"54",
    "addr:postcode":"8046",
    "addr:street":"St. Veiter Str",
    "iso:country":"AT",
    "sg:address":"St. Veiter Str 54",
    "sg:city":"St. Veit",
    "sg:orig_category":"Familien / Beratung",
    "sg:phone":"+43 4331 6692917",
    "sg:postcode":"8046",
    "sg:province":"Steiermark",
    "wof:name":"Czerwinka & Czerwinka OEG",
    "wof:placetype":"venue"
},
  "geometry": {"coordinates":[15.4134197235,47.1140403748],"type":"Point"}
}