{
  "type": "Feature",
  "properties": {
    "addr:full":"Herreng 6 Judenburg Steiermark 8750",
    "addr:housenumber":"6",
    "addr:postcode":"8750",
    "addr:street":"Herreng",
    "iso:country":"AT",
    "sg:address":"Herreng 6",
    "sg:city":"Judenburg",
    "sg:orig_category":"Elektroinstallationsunternehmen",
    "sg:phone":"+43 4335 7282201",
    "sg:postcode":"8750",
    "sg:province":"Steiermark",
    "wof:name":"Pichler Johann",
    "wof:placetype":"venue"
},
  "geometry": {"coordinates":[14.659910202,47.1692047119],"type":"Point"}
}