{
  "type": "Feature",
  "properties": {
    "iso:country":"AT",
    "sg:address":"M\u00fchlg 5",
    "sg:city":"Hornstein",
    "sg:orig_category":"Alteisen U Altmetalle",
    "sg:phone":"+43 2689 2283",
    "sg:postcode":"7053",
    "sg:province":"Burgenland",
    "wof:name":"Pincolits Herbert",
    "wof:placetype":"venue"
},
  "geometry": {"coordinates":[16.442199707,47.8792800903],"type":"Point"}
}