{
  "type": "Feature",
  "properties": {
    "addr:full":"Vogelh\u00e4ndlerpl 4 St. Peter in der Au Nieder\u00f6sterreich 3352",
    "addr:housenumber":"4",
    "addr:postcode":"3352",
    "addr:street":"Vogelhaendlerpl",
    "iso:country":"AT",
    "sg:address":"Vogelh\u00e4ndlerpl 4",
    "sg:city":"St. Peter in der Au",
    "sg:orig_category":"Hauptschulen",
    "sg:phone":"+43 7477 4400040",
    "sg:postcode":"3352",
    "sg:province":"Nieder\u00f6sterreich",
    "wof:name":"Hauptschule",
    "wof:placetype":"venue"
},
  "geometry": {"coordinates":[14.6209287643,48.0450897217],"type":"Point"}
}