{
  "type": "Feature",
  "properties": {
    "iso:country":"AT",
    "sg:address":"Kierlinger Str 9",
    "sg:city":"Klosterneuburg",
    "sg:orig_category":"Maschinenhandel",
    "sg:phone":"+43 2243 37254",
    "sg:postcode":"3400",
    "sg:province":"Nieder\u00f6sterreich",
    "wof:name":"Zisser Alois",
    "wof:placetype":"venue"
},
  "geometry": {"coordinates":[16.3209018707,48.3073577881],"type":"Point"}
}