{
  "type": "Feature",
  "properties": {
    "addr:full":"Karlauer Str 29 Graz Steiermark 8020",
    "addr:housenumber":"29",
    "addr:postcode":"8020",
    "addr:street":"Str",
    "iso:country":"AT",
    "sg:address":"Karlauer Str 29",
    "sg:city":"Graz",
    "sg:orig_category":"Autovermietung",
    "sg:phone":"+43 316 713741",
    "sg:postcode":"8020",
    "sg:province":"Steiermark",
    "wof:name":"Autoverleih Schnedlitz GesmbH",
    "wof:placetype":"venue"
},
  "geometry": {"coordinates":[15.4339323044,47.0576629639],"type":"Point"}
}