{
  "type": "Feature",
  "properties": {
    "addr:full":"Nachdemsee 15 Altm\u00fcnster Ober\u00f6sterreich 4813",
    "addr:housenumber":"15",
    "addr:postcode":"4813",
    "addr:street":"Nachdemsee;Oberoesterreich",
    "iso:country":"AT",
    "sg:address":"Nachdemsee 15",
    "sg:city":"Altm\u00fcnster",
    "sg:classifiers":[
        {
            "category":"Home & Garden",
            "subcategory":"Kitchen Supply",
            "type":"Retail Goods"
        }
    ],
    "sg:phone":"+43 761287134",
    "sg:postcode":"4813",
    "sg:province":"Ober\u00f6sterreich",
    "sg:tags":[
        "fitted"
    ],
    "wof:name":"Herbert Johann Gaigg",
    "wof:placetype":"venue"
},
  "geometry": {"coordinates":[13.7722702026,47.8836936951],"type":"Point"}
}