{
  "type": "Feature",
  "properties": {
    "addr:full":"Bahnhofstr 1 Saalfelden am Steinernen Meer Salzburg 5760",
    "addr:housenumber":"1",
    "addr:postcode":"5760",
    "addr:street":"Bahnhofstr",
    "iso:country":"AT",
    "sg:address":"Bahnhofstr 1",
    "sg:city":"Saalfelden am Steinernen Meer",
    "sg:orig_category":"Tabaktrafiken",
    "sg:phone":"+43 6582 72649",
    "sg:postcode":"5760",
    "sg:province":"Salzburg",
    "wof:name":"Kohlbacher Ingeborg",
    "wof:placetype":"venue"
},
  "geometry": {"coordinates":[12.8468427658,47.4270591736],"type":"Point"}
}