{
  "type": "Feature",
  "properties": {
    "iso:country":"AT",
    "sg:address":"Wiener Str 9",
    "sg:city":"Enns",
    "sg:orig_category":"Handarbeiten",
    "sg:phone":"+43 7223 87945",
    "sg:postcode":"4470",
    "sg:province":"Ober\u00f6sterreich",
    "wof:name":"Bockm\u00fcller Renate",
    "wof:placetype":"venue"
},
  "geometry": {"coordinates":[14.4791498184,48.2126502991],"type":"Point"}
}