{
  "type": "Feature",
  "properties": {
    "addr:full":"Lieserstegg 7 Spittal an der Drau K\u00e4rnten 9800",
    "addr:housenumber":"7",
    "addr:postcode":"9800",
    "addr:street":"Lieserstegg;Kaernten",
    "iso:country":"AT",
    "sg:address":"Lieserstegg 7",
    "sg:city":"Spittal an der Drau",
    "sg:orig_category":"Textilreinigung",
    "sg:phone":"+43 4762 2564",
    "sg:postcode":"9800",
    "sg:province":"K\u00e4rnten",
    "wof:name":"Zm\u00f6lnig Hans",
    "wof:placetype":"venue"
},
  "geometry": {"coordinates":[13.4983558655,46.799243927],"type":"Point"}
}