{
  "type": "Feature",
  "properties": {
    "addr:full":"Durisolstrasse 7 / Top 6A Wels Ober\u00f6sterreich 4600",
    "addr:housenumber":"7 / top 6a",
    "addr:postcode":"4600",
    "addr:street":"Durisolstrasse;Oberoesterreich",
    "iso:country":"AT",
    "sg:address":"Durisolstrasse 7 / Top 6A",
    "sg:city":"Wels",
    "sg:orig_category":"Medien, Zeitungen And Zeitschriften",
    "sg:phone":"+43 4372 4254052",
    "sg:postcode":"4600",
    "sg:province":"Ober\u00f6sterreich",
    "sg:website":"http://www.welsheute.at/",
    "wof:name":"Wels Heute e. V.",
    "wof:placetype":"venue"
},
  "geometry": {"coordinates":[13.9685125351,48.1398696899],"type":"Point"}
}