{
  "type": "Feature",
  "properties": {
    "iso:country":"AT",
    "sg:address":"Steinbauergasse 23",
    "sg:city":"Wien",
    "sg:classifiers":[
        {
            "category":"Banks & Credit Unions",
            "subcategory":"Investment Brokerage",
            "type":"Services"
        }
    ],
    "sg:phone":"+43 1 9610146",
    "sg:postcode":"1120",
    "sg:province":"Wien",
    "sg:tags":[
        "processing",
        "data",
        "system"
    ],
    "sg:website":"sem-edv.at",
    "wof:name":"SEM Studio of Engineering and Management Ing. T. R. Z\u00f6chling",
    "wof:placetype":"venue"
},
  "geometry": {"coordinates":[16.3419971466,48.1825561523],"type":"Point"}
}