{
  "type": "Feature",
  "properties": {
    "addr:full":"St Berthold-Allee 5 Garsten Ober\u00f6sterreich 4451",
    "addr:housenumber":"5",
    "addr:postcode":"4451",
    "addr:street":"Garsten Oberoesterreich",
    "iso:country":"AT",
    "sg:address":"St Berthold-Allee 5",
    "sg:city":"Garsten",
    "sg:orig_category":"Elektroinstallationsunternehmen",
    "sg:phone":"+43 7252 52660",
    "sg:postcode":"4451",
    "sg:province":"Ober\u00f6sterreich",
    "wof:name":"Bern\u00f6gger GesmbH",
    "wof:placetype":"venue"
},
  "geometry": {"coordinates":[14.407283783,48.0236244202],"type":"Point"}
}