{
  "type": "Feature",
  "properties": {
    "addr:full":"Kapellenpl 1 M\u00fcllendorf Burgenland 7052",
    "addr:housenumber":"1",
    "addr:postcode":"7052",
    "addr:street":"Kapellenpl",
    "iso:country":"AT",
    "sg:address":"Kapellenpl 1",
    "sg:city":"M\u00fcllendorf",
    "sg:orig_category":"Marketingberatung",
    "sg:phone":"+43 2682 64557",
    "sg:postcode":"7052",
    "sg:province":"Burgenland",
    "wof:name":"Initiative Handwerk Marketing GesmbH",
    "wof:placetype":"venue"
},
  "geometry": {"coordinates":[16.4614658356,47.837928772],"type":"Point"}
}