{
  "type": "Feature",
  "properties": {
    "addr:full":"Aussichtsweg 19 Seewalchen am Attersee Ober\u00f6sterreich 4863",
    "addr:housenumber":"19",
    "addr:postcode":"4863",
    "addr:street":"Aussichtsweg",
    "iso:country":"AT",
    "sg:address":"Aussichtsweg 19",
    "sg:city":"Seewalchen am Attersee",
    "sg:classifiers":[
        {
            "category":"Professional",
            "subcategory":"Business Services",
            "type":"Services"
        }
    ],
    "sg:phone":"+43 76626466",
    "sg:postcode":"4863",
    "sg:province":"Ober\u00f6sterreich",
    "sg:tags":[
        "agency",
        "export"
    ],
    "wof:name":"Migro Import-, Export - Handelsges. Michal & Co",
    "wof:placetype":"venue"
},
  "geometry": {"coordinates":[13.5948867798,47.9516067505],"type":"Point"}
}