{
  "type": "Feature",
  "properties": {
    "addr:full":"Berghamer Weg 13 Leonding Ober\u00f6sterreich 4060",
    "addr:housenumber":"13",
    "addr:postcode":"4060",
    "addr:street":"Berghamer Weg",
    "iso:country":"AT",
    "sg:address":"Berghamer Weg 13",
    "sg:city":"Leonding",
    "sg:orig_category":"Finanz- U Wirtschaftsberatung",
    "sg:phone":"+43 4366 45050225",
    "sg:postcode":"4060",
    "sg:province":"Ober\u00f6sterreich",
    "wof:name":"Die Online-Berater",
    "wof:placetype":"venue"
},
  "geometry": {"coordinates":[14.2424125671,48.2784194946],"type":"Point"}
}