{
  "type": "Feature",
  "properties": {
    "iso:country":"AT",
    "sg:address":"Bundesstr 72",
    "sg:city":"Wimpassing im Schwarzatale",
    "sg:orig_category":"Eisenwaren",
    "sg:phone":"+43 4326 3038423",
    "sg:postcode":"2632",
    "sg:province":"Nieder\u00f6sterreich",
    "wof:name":"Zingl GmbH",
    "wof:placetype":"venue"
},
  "geometry": {"coordinates":[16.0231189728,47.6981201172],"type":"Point"}
}