{
  "type": "Feature",
  "properties": {
    "addr:full":"Lilienbergg 13 Wien Wien 1130",
    "addr:housenumber":"13",
    "addr:postcode":"1130",
    "addr:street":"Lilienbergg",
    "iso:country":"AT",
    "sg:address":"Lilienbergg 13",
    "sg:city":"Wien",
    "sg:orig_category":"Elektronik",
    "sg:phone":"+43 1 40308120",
    "sg:postcode":"1130",
    "sg:province":"Wien",
    "wof:name":"Knap Wolfgang GesmbH & Co KG",
    "wof:placetype":"venue"
},
  "geometry": {"coordinates":[16.2599525452,48.1958198547],"type":"Point"}
}