{
  "type": "Feature",
  "properties": {
    "addr:full":"Kirchg 6 St. Michael in Obersteiermark Steiermark 8770",
    "addr:housenumber":"6",
    "addr:postcode":"8770",
    "addr:street":"Kirchg",
    "iso:country":"AT",
    "sg:address":"Kirchg 6",
    "sg:city":"St. Michael in Obersteiermark",
    "sg:orig_category":"Familien / Beratung",
    "sg:phone":"+43 4338 432381",
    "sg:postcode":"8770",
    "sg:province":"Steiermark",
    "wof:name":"Mutterberatung",
    "wof:placetype":"venue"
},
  "geometry": {"coordinates":[15.0223493576,47.3374519348],"type":"Point"}
}