{
  "type": "Feature",
  "properties": {
    "addr:full":"Mariahilfer Str 38-40 Wien Wien 1070",
    "addr:postcode":"38-40;1070",
    "addr:street":"Str",
    "iso:country":"AT",
    "sg:address":"Mariahilfer Str 38-40",
    "sg:city":"Wien",
    "sg:orig_category":"Bars-Cafes",
    "sg:phone":"+43 1 5241377",
    "sg:postcode":"1070",
    "sg:province":"Wien",
    "wof:name":"City Lights - Eserova Irfan",
    "wof:placetype":"venue"
},
  "geometry": {"coordinates":[16.3540267944,48.1999588013],"type":"Point"}
}