{
  "type": "Feature",
  "properties": {
    "addr:full":"D\u00f6llacher Str 2 Liezen Steiermark 8940",
    "addr:housenumber":"2",
    "addr:postcode":"8940",
    "addr:street":"Str",
    "iso:country":"AT",
    "sg:address":"D\u00f6llacher Str 2",
    "sg:city":"Liezen",
    "sg:orig_category":"Farben U Lacke / Erzeugung U Gro\u00c3\u0178handel",
    "sg:phone":"+43 4336 12237850",
    "sg:postcode":"8940",
    "sg:province":"Steiermark",
    "wof:name":"Christ Ludwig & Co GesmbH",
    "wof:placetype":"venue"
},
  "geometry": {"coordinates":[14.2413349152,47.5672111511],"type":"Point"}
}