{
  "type": "Feature",
  "properties": {
    "addr:full":"Schlickg 2 Wien Wien 1090",
    "addr:housenumber":"2",
    "addr:postcode":"1090",
    "addr:street":"Schlickg",
    "iso:country":"AT",
    "sg:address":"Schlickg 2",
    "sg:city":"Wien",
    "sg:orig_category":"Optiker",
    "sg:phone":"+43 1 3179108",
    "sg:postcode":"1090",
    "sg:province":"Wien",
    "wof:name":"Binder Johann GesmbH",
    "wof:placetype":"venue"
},
  "geometry": {"coordinates":[16.3648166656,48.2183074951],"type":"Point"}
}