{
  "type": "Feature",
  "properties": {
    "addr:full":"Lob\u00e4ckerstr 67 Eisenstadt Burgenland 7000",
    "addr:housenumber":"67",
    "addr:postcode":"7000",
    "addr:street":"Lobaeckerstr",
    "iso:country":"AT",
    "sg:address":"Lob\u00e4ckerstr 67",
    "sg:city":"Eisenstadt",
    "sg:orig_category":"Transportbeton",
    "sg:phone":"+43 2682 68224",
    "sg:postcode":"7000",
    "sg:province":"Burgenland",
    "wof:name":"Lieferbeton GesmbH",
    "wof:placetype":"venue"
},
  "geometry": {"coordinates":[16.5424289703,47.8296012878],"type":"Point"}
}