{
  "type": "Feature",
  "properties": {
    "iso:country":"AT",
    "sg:address":"Linzer G 55",
    "sg:city":"Salzburg",
    "sg:orig_category":"Psychotherapie",
    "sg:phone":"+43 664 3824365",
    "sg:postcode":"5020",
    "sg:province":"Salzburg",
    "wof:name":"Burtscher-W\u00e4ger Monika Dr",
    "wof:placetype":"venue"
},
  "geometry": {"coordinates":[13.0489768982,47.8046264648],"type":"Point"}
}