{
  "type": "Feature",
  "properties": {
    "addr:full":"Nr 66 Stallhofen Steiermark 8152",
    "addr:postcode":"8152",
    "addr:street":"Nr",
    "iso:country":"AT",
    "sg:address":"Nr 66",
    "sg:city":"Stallhofen",
    "sg:classifiers":[
        {
            "category":"Restaurant",
            "type":"Food & Drink"
        }
    ],
    "sg:phone":"+43 4331 4226011",
    "sg:postcode":"8152",
    "sg:province":"Steiermark",
    "sg:tags":[
        "pizzeria"
    ],
    "wof:name":"Restaurant-Pizzeria zum Pflasterstein",
    "wof:placetype":"venue"
},
  "geometry": {"coordinates":[15.2755184174,47.0200767517],"type":"Point"}
}