{
  "type": "Feature",
  "properties": {
    "addr:full":"Blechturmgasse 31 Wien Wien 1050",
    "addr:housenumber":"31",
    "addr:postcode":"1050",
    "addr:street":"Blechturmgasse",
    "iso:country":"AT",
    "sg:address":"Blechturmgasse 31",
    "sg:city":"Wien",
    "sg:classifiers":[
        {
            "category":"Shopping",
            "subcategory":"Clothing, Apparel, & Fashions",
            "type":"Retail Goods"
        }
    ],
    "sg:phone":"+43 4315 444125",
    "sg:postcode":"1050",
    "sg:province":"Wien",
    "sg:tags":[
        "clothing",
        "accessory"
    ],
    "wof:name":"MARIE SLAMA & SOHN OHG",
    "wof:placetype":"venue"
},
  "geometry": {"coordinates":[16.3650588989,48.1874160767],"type":"Point"}
}