{
  "type": "Feature",
  "properties": {
    "addr:full":"Hauptstr 29 Gallneukirchen Ober\u00f6sterreich 4210",
    "addr:housenumber":"29",
    "addr:postcode":"4210",
    "addr:street":"Hauptstr;Oberoesterreich",
    "iso:country":"AT",
    "sg:address":"Hauptstr 29",
    "sg:city":"Gallneukirchen",
    "sg:orig_category":"Elektroinstallationsunternehmen",
    "sg:phone":"+43 7235 63264",
    "sg:postcode":"4210",
    "sg:province":"Ober\u00f6sterreich",
    "wof:name":"Prandst\u00f6tter Klaus",
    "wof:placetype":"venue"
},
  "geometry": {"coordinates":[14.4167718887,48.3540077209],"type":"Point"}
}