{
  "type": "Feature",
  "properties": {
    "addr:full":"Goethepl 2 Zwentendorf an der Donau Nieder\u00f6sterreich 3435",
    "addr:housenumber":"2",
    "addr:postcode":"3435",
    "addr:street":"Goethepl",
    "iso:country":"AT",
    "sg:address":"Goethepl 2",
    "sg:city":"Zwentendorf an der Donau",
    "sg:orig_category":"Volksschulen",
    "sg:phone":"+43 4322 772278",
    "sg:postcode":"3435",
    "sg:province":"Nieder\u00f6sterreich",
    "wof:name":"Volksschule",
    "wof:placetype":"venue"
},
  "geometry": {"coordinates":[15.9115142822,48.3450660706],"type":"Point"}
}