{
  "type": "Feature",
  "properties": {
    "addr:full":"Hauptstr 17 Peuerbach Ober\u00f6sterreich 4722",
    "addr:housenumber":"17",
    "addr:postcode":"4722",
    "addr:street":"Hauptstr",
    "iso:country":"AT",
    "sg:address":"Hauptstr 17",
    "sg:city":"Peuerbach",
    "sg:orig_category":"Damenmoden",
    "sg:phone":"+43 7276 2331",
    "sg:postcode":"4722",
    "sg:province":"Ober\u00f6sterreich",
    "wof:name":"Kindlinger GesmbH",
    "wof:placetype":"venue"
},
  "geometry": {"coordinates":[13.7715091705,48.3445968628],"type":"Point"}
}