{
  "type": "Feature",
  "properties": {
    "addr:full":"Nr 35 Linz Ober\u00f6sterreich 4040",
    "addr:postcode":"4040",
    "addr:street":"Nr 35",
    "iso:country":"AT",
    "sg:address":"Nr 35",
    "sg:city":"Linz",
    "sg:orig_category":"Psychotherapie",
    "sg:phone":"+43 676 7892451",
    "sg:postcode":"4040",
    "sg:province":"Ober\u00f6sterreich",
    "wof:name":"Frank Michaela Mag M.A.",
    "wof:placetype":"venue"
},
  "geometry": {"coordinates":[14.2578554153,48.3602561951],"type":"Point"}
}