{
  "type": "Feature",
  "properties": {
    "addr:full":"Ada-Christen-G 9 Wien Wien 1100",
    "addr:housenumber":"9",
    "addr:postcode":"1100",
    "addr:street":"Ada-Christen-G",
    "iso:country":"AT",
    "sg:address":"Ada-Christen-G 9",
    "sg:city":"Wien",
    "sg:orig_category":"Volkshochschulen",
    "sg:phone":"+43 4316 885582",
    "sg:postcode":"1100",
    "sg:province":"Wien",
    "wof:name":"Volkshochschule Favoriten",
    "wof:placetype":"venue"
},
  "geometry": {"coordinates":[16.3837585449,48.1490478516],"type":"Point"}
}