{
  "type": "Feature",
  "properties": {
    "addr:full":"Sackg 6 Werndorf Steiermark 8402",
    "addr:housenumber":"6",
    "addr:postcode":"8402",
    "addr:street":"Sackg",
    "iso:country":"AT",
    "sg:address":"Sackg 6",
    "sg:city":"Werndorf",
    "sg:orig_category":"Unterhaltungselektronik / Einzelhandel",
    "sg:phone":"+43 4331 3552707",
    "sg:postcode":"8402",
    "sg:province":"Steiermark",
    "wof:name":"Videopartner KEG",
    "wof:placetype":"venue"
},
  "geometry": {"coordinates":[15.4851284027,46.9367523193],"type":"Point"}
}