{
  "type": "Feature",
  "properties": {
    "addr:full":"Clerfaytg 8 Wien Wien 1170",
    "addr:housenumber":"8",
    "addr:postcode":"1170",
    "addr:street":"Clerfaytg",
    "iso:country":"AT",
    "sg:address":"Clerfaytg 8",
    "sg:city":"Wien",
    "sg:orig_category":"Textilreinigung",
    "sg:phone":"+43 1 48636710",
    "sg:postcode":"1170",
    "sg:province":"Wien",
    "wof:name":"Wlasak Franz GesmbH",
    "wof:placetype":"venue"
},
  "geometry": {"coordinates":[16.3233661652,48.2216262817],"type":"Point"}
}