{
  "type": "Feature",
  "properties": {
    "addr:full":"Nu\u00dfdorfer Pl 5 Wien Wien 1190",
    "addr:housenumber":"5",
    "addr:postcode":"1190",
    "addr:street":"Nussdorfer Pl",
    "iso:country":"AT",
    "sg:address":"Nu\u00dfdorfer Pl 5",
    "sg:city":"Wien",
    "sg:orig_category":"Banken U Sparkassen",
    "sg:phone":"+43 4350 50530650",
    "sg:postcode":"1190",
    "sg:province":"Wien",
    "wof:name":"Bank Austria Creditanstalt AG",
    "wof:placetype":"venue"
},
  "geometry": {"coordinates":[16.3493022919,48.2389793396],"type":"Point"}
}