{
  "type": "Feature",
  "properties": {
    "addr:full":"Hauptstr 43 Rottenmann Steiermark 8786",
    "addr:housenumber":"43",
    "addr:postcode":"8786",
    "addr:street":"Hauptstr",
    "iso:country":"AT",
    "sg:address":"Hauptstr 43",
    "sg:city":"Rottenmann",
    "sg:orig_category":"Blumeneinzelhandel",
    "sg:phone":"+43 664 1806476",
    "sg:postcode":"8786",
    "sg:province":"Steiermark",
    "wof:name":"Monika's Blumenladen",
    "wof:placetype":"venue"
},
  "geometry": {"coordinates":[14.3600521088,47.5258369446],"type":"Point"}
}