{
  "type": "Feature",
  "properties": {
    "addr:full":"Wimberg 36 Adnet Salzburg 5421",
    "addr:housenumber":"36",
    "addr:postcode":"5421",
    "addr:street":"Wimberg;Salzburg",
    "iso:country":"AT",
    "sg:address":"Wimberg 36",
    "sg:city":"Adnet",
    "sg:orig_category":"Erdarbeiten",
    "sg:phone":"+43 664 5108452",
    "sg:postcode":"5421",
    "sg:province":"Salzburg",
    "wof:name":"Skotnik G\u00fcnter Baggerunternehmen",
    "wof:placetype":"venue"
},
  "geometry": {"coordinates":[13.1488342285,47.7026939392],"type":"Point"}
}