{
  "type": "Feature",
  "properties": {
    "iso:country":"AT",
    "sg:address":"Nr 64",
    "sg:city":"T\u00f6sens",
    "sg:orig_category":"Installationsunternehmen",
    "sg:phone":"+43 5477 466",
    "sg:postcode":"6541",
    "sg:province":"Tirol",
    "wof:name":"Regensburger Reinhard",
    "wof:placetype":"venue"
},
  "geometry": {"coordinates":[166.9221496582,-0.5282999873],"type":"Point"}
}