{
  "type": "Feature",
  "properties": {
    "addr:full":"Flughafenstr 16 Klagenfurt K\u00e4rnten 9020",
    "addr:housenumber":"16",
    "addr:postcode":"9020",
    "addr:street":"Flughafenstr;Kaernten",
    "iso:country":"AT",
    "sg:address":"Flughafenstr 16",
    "sg:city":"Klagenfurt",
    "sg:orig_category":"Bestattungsunternehmen",
    "sg:phone":"+43 4346 3440077",
    "sg:postcode":"9020",
    "sg:province":"K\u00e4rnten",
    "sg:website":"pax.at",
    "wof:name":"Pax Bestattungs- u Grabst\u00e4ttenfachbetrieb GesmbH",
    "wof:placetype":"venue"
},
  "geometry": {"coordinates":[14.3185596466,46.6499481201],"type":"Point"}
}