{
  "type": "Feature",
  "properties": {
    "addr:full":"Luechstr 55 Kirchbichl Tirol 6322",
    "addr:housenumber":"55",
    "addr:postcode":"6322",
    "addr:street":"Luechstr;Tirol",
    "iso:country":"AT",
    "sg:address":"Luechstr 55",
    "sg:city":"Kirchbichl",
    "sg:orig_category":"Tischlereien",
    "sg:phone":"+43 5332 73886",
    "sg:postcode":"6322",
    "sg:province":"Tirol",
    "wof:name":"Bellmann Albert",
    "wof:placetype":"venue"
},
  "geometry": {"coordinates":[12.1374168396,47.4821968079],"type":"Point"}
}