{
  "type": "Feature",
  "properties": {
    "iso:country":"AT",
    "sg:address":"Industriegel\u00e4nde 1",
    "sg:city":"Donnerskirchen",
    "sg:classifiers":[
        {
            "category":"Ice Cream",
            "type":"Food & Drink"
        }
    ],
    "sg:phone":"+43 2683 8383",
    "sg:postcode":"7082",
    "sg:province":"Burgenland",
    "sg:tags":[
        "barrier"
    ],
    "sg:website":"asp-psa.at",
    "wof:name":"A.S.P. Delta Plus Austria GmbH.",
    "wof:placetype":"venue"
},
  "geometry": {"coordinates":[16.6494483948,47.8743286133],"type":"Point"}
}