{
  "type": "Feature",
  "properties": {
    "addr:full":"Fieberbrunn Tirol 6391",
    "addr:postcode":"6391",
    "iso:country":"AT",
    "sg:city":"Fieberbrunn",
    "sg:orig_category":"Feuerwehren",
    "sg:phone":"+43 5354 56692",
    "sg:postcode":"6391",
    "sg:province":"Tirol",
    "wof:name":"Freiwillige Feuerwehr Fieberbrunn - Zeughaus Pfaffenschwendt",
    "wof:placetype":"venue"
},
  "geometry": {"coordinates":[12.5448112488,47.4751586914],"type":"Point"}
}