{
  "type": "Feature",
  "properties": {
    "addr:full":"Fernpa\u00dfstr 2 Nassereith Tirol 6465",
    "addr:housenumber":"2",
    "addr:postcode":"6465",
    "addr:street":"Fernpassstr;Tirol",
    "iso:country":"AT",
    "sg:address":"Fernpa\u00dfstr 2",
    "sg:city":"Nassereith",
    "sg:orig_category":"Werbegestalter",
    "sg:phone":"+43 5265 5434",
    "sg:postcode":"6465",
    "sg:province":"Tirol",
    "wof:name":"Reklama Werbetechnik - Harald B\u00f6ss",
    "wof:placetype":"venue"
},
  "geometry": {"coordinates":[10.8377714157,47.3145332336],"type":"Point"}
}