{
  "type": "Feature",
  "properties": {
    "iso:country":"AT",
    "sg:address":"Nr 179",
    "sg:city":"Friedberg",
    "sg:orig_category":"Werbeartikel U -Geschenke",
    "sg:phone":"+43 4333 3924146",
    "sg:postcode":"8240",
    "sg:province":"Steiermark",
    "wof:name":"PromOcean Werbeartikel GmbH",
    "wof:placetype":"venue"
},
  "geometry": {"coordinates":[16.0580654144,47.4416236877],"type":"Point"}
}