{
  "type": "Feature",
  "properties": {
    "iso:country":"AT",
    "sg:address":"Nr 120",
    "sg:city":"Lainbach",
    "sg:orig_category":"Elektroinstallationsunternehmen",
    "sg:phone":"+43 4336 332567",
    "sg:postcode":"8921",
    "sg:province":"Steiermark",
    "wof:name":"M\u00fcllner Elektro GesmbH",
    "wof:placetype":"venue"
},
  "geometry": {"coordinates":[14.7634248734,47.6528511047],"type":"Point"}
}