{
  "type": "Feature",
  "properties": {
    "addr:full":"Nr 4 Fehring Steiermark 8350",
    "addr:postcode":"8350",
    "addr:street":"Nr",
    "iso:country":"AT",
    "sg:address":"Nr 4",
    "sg:city":"Fehring",
    "sg:orig_category":"Gutsverwaltungen",
    "sg:phone":"+43 4331 5523110",
    "sg:postcode":"8350",
    "sg:province":"Steiermark",
    "wof:name":"Pscheidl GesmbH",
    "wof:placetype":"venue"
},
  "geometry": {"coordinates":[16.066734314,46.9451332092],"type":"Point"}
}