{
  "type": "Feature",
  "properties": {
    "iso:country":"AT",
    "sg:address":"Dr.-Karl-Renner-Str 36",
    "sg:city":"Enns",
    "sg:orig_category":"Steinmetzbetriebe",
    "sg:phone":"+43 7223 80798",
    "sg:postcode":"4470",
    "sg:province":"Ober\u00f6sterreich",
    "wof:name":"Osmanoski Steinbau OEG",
    "wof:placetype":"venue"
},
  "geometry": {"coordinates":[14.4745101929,48.2136802673],"type":"Point"}
}