{
  "type": "Feature",
  "properties": {
    "addr:full":"Seminarstr 22 Andritz Steiermark 8045",
    "addr:housenumber":"22",
    "addr:postcode":"8045",
    "addr:street":"Seminarstr",
    "iso:country":"AT",
    "sg:address":"Seminarstr 22",
    "sg:city":"Andritz",
    "sg:orig_category":"Werbeagenturen",
    "sg:phone":"+43 316 677755",
    "sg:postcode":"8045",
    "sg:province":"Steiermark",
    "wof:name":"ActionScouts.Com",
    "wof:placetype":"venue"
},
  "geometry": {"coordinates":[15.4430732727,47.1044578552],"type":"Point"}
}