{
  "type": "Feature",
  "properties": {
    "addr:full":"Nr 20 Rabenstein an der Pielach Nieder\u00f6sterreich 3203",
    "addr:postcode":"3203",
    "addr:street":"Nr 20",
    "iso:country":"AT",
    "sg:address":"Nr 20",
    "sg:city":"Rabenstein an der Pielach",
    "sg:classifiers":[
        {
            "category":"Travel",
            "subcategory":"Hotels & Motels",
            "type":"Entertainment"
        }
    ],
    "sg:phone":"+43 2722 2281",
    "sg:postcode":"3203",
    "sg:province":"Nieder\u00f6sterreich",
    "wof:name":"Hotel Steinschalerhof",
    "wof:placetype":"venue"
},
  "geometry": {"coordinates":[15.4653377533,48.0646781921],"type":"Point"}
}