{
  "type": "Feature",
  "properties": {
    "addr:full":"Hauptpl 1 Pinkafeld Burgenland 7423",
    "addr:housenumber":"1",
    "addr:postcode":"7423",
    "addr:street":"Hauptpl",
    "iso:country":"AT",
    "sg:address":"Hauptpl 1",
    "sg:city":"Pinkafeld",
    "sg:orig_category":"Museen / Ausstellungen",
    "sg:phone":"+43 3357 4235121",
    "sg:postcode":"7423",
    "sg:province":"Burgenland",
    "wof:name":"Stadtmuseum Pinkafeld",
    "wof:placetype":"venue"
},
  "geometry": {"coordinates":[16.1243915558,47.3719596863],"type":"Point"}
}