{
  "type": "Feature",
  "properties": {
    "addr:full":"Nr 15 Traismauer Nieder\u00f6sterreich 3133",
    "addr:postcode":"3133",
    "addr:street":"Nr 15",
    "iso:country":"AT",
    "sg:address":"Nr 15",
    "sg:city":"Traismauer",
    "sg:orig_category":"Banken U Sparkassen",
    "sg:phone":"+43 4359 50053200",
    "sg:postcode":"3133",
    "sg:province":"Nieder\u00f6sterreich",
    "wof:name":"Raiffeisenbank Region St. P\u00f6lten regGenmbH - Bankstelle Nu\u00dfdorf",
    "wof:placetype":"venue"
},
  "geometry": {"coordinates":[15.7439002991,48.34973526],"type":"Point"}
}