{
  "type": "Feature",
  "properties": {
    "addr:full":"Van Swieten-G 8 Wien Wien 1090",
    "addr:housenumber":"8",
    "addr:postcode":"1090",
    "iso:country":"AT",
    "sg:address":"Van Swieten-G 8",
    "sg:city":"Wien",
    "sg:orig_category":"Pensionen / Privatzimmer, Appartements / Ferienwohnungen",
    "sg:phone":"+43 1 40936800",
    "sg:postcode":"1090",
    "sg:province":"Wien",
    "sg:website":"members.aon.at/pension-ring",
    "wof:name":"Appartement-Pension 700 Meter zum RING",
    "wof:placetype":"venue"
},
  "geometry": {"coordinates":[16.3563537598,48.2186050415],"type":"Point"}
}