{
  "type": "Feature",
  "properties": {
    "iso:country":"AT",
    "sg:address":"Schillerstr 2",
    "sg:city":"Bregenz",
    "sg:orig_category":"Bildungsservice / Allgemeine Informationsstellen",
    "sg:phone":"+43 5574 45538",
    "sg:postcode":"6900",
    "sg:province":"Vorarlberg",
    "wof:name":"Frauengetriebe Verein, Informations- und Bildungszentrum f Frauen",
    "wof:placetype":"venue"
},
  "geometry": {"coordinates":[9.7499265671,47.5054016113],"type":"Point"}
}