{
  "type": "Feature",
  "properties": {
    "addr:full":"Mistelbacher Strasse 8 Ernstbrunn Nieder\u00f6sterreich 2115",
    "addr:housenumber":"8",
    "addr:postcode":"2115",
    "addr:street":"Mistelbacher Strasse",
    "iso:country":"AT",
    "sg:address":"Mistelbacher Strasse 8",
    "sg:city":"Ernstbrunn",
    "sg:classifiers":[
        {
            "category":"Building & Trades",
            "subcategory":"Plumbing",
            "type":"Services"
        }
    ],
    "sg:phone":"+43 2576 2236",
    "sg:postcode":"2115",
    "sg:province":"Nieder\u00f6sterreich",
    "sg:tags":[
        "supraregional",
        "gas"
    ],
    "wof:name":"Ing. Harald Wolf",
    "wof:placetype":"venue"
},
  "geometry": {"coordinates":[16.3656806946,48.5270690918],"type":"Point"}
}