{
  "type": "Feature",
  "properties": {
    "addr:full":"Museumstr 5 Wien Wien 1070",
    "addr:housenumber":"5",
    "addr:postcode":"1070",
    "addr:street":"Museumstr",
    "iso:country":"AT",
    "sg:address":"Museumstr 5",
    "sg:city":"Wien",
    "sg:orig_category":"Energieberatung U -Untersuchung",
    "sg:phone":"+43 4315 2375110",
    "sg:postcode":"1070",
    "sg:province":"Wien",
    "sg:website":"oekv-energy.at",
    "wof:name":"\u00f6sterreichischer Energiekonsumenten-Verband (\u00f6EKV)",
    "wof:placetype":"venue"
},
  "geometry": {"coordinates":[16.3561401367,48.205242157],"type":"Point"}
}