{
  "type": "Feature",
  "properties": {
    "addr:full":"Bodenfeldg 9a Graz Steiermark 8020",
    "addr:housenumber":"9a",
    "addr:postcode":"8020",
    "addr:street":"Bodenfeldg",
    "iso:country":"AT",
    "sg:address":"Bodenfeldg 9a",
    "sg:city":"Graz",
    "sg:classifiers":[
        {
            "category":"Home & Garden",
            "subcategory":"Building Materials",
            "type":"Retail Goods"
        }
    ],
    "sg:phone":"+43 4331 6586575",
    "sg:postcode":"8020",
    "sg:province":"Steiermark",
    "sg:tags":[
        "baustoffe",
        "-material",
        "u"
    ],
    "wof:name":"Mapei GesmbH",
    "wof:placetype":"venue"
},
  "geometry": {"coordinates":[15.4059410095,47.0755577087],"type":"Point"}
}