{
  "type": "Feature",
  "properties": {
    "addr:full":"Nr 14 Krenglbach Ober\u00f6sterreich 4631",
    "addr:postcode":"4631",
    "addr:street":"Nr 14",
    "iso:country":"AT",
    "sg:address":"Nr 14",
    "sg:city":"Krenglbach",
    "sg:orig_category":"Non-Classified Establishments",
    "sg:phone":"+43 5 91334182",
    "sg:postcode":"4631",
    "sg:province":"Ober\u00f6sterreich",
    "wof:name":"Gendarmerieposten Krenglbach",
    "wof:placetype":"venue"
},
  "geometry": {"coordinates":[13.9558620453,48.2057304382],"type":"Point"}
}