{
  "type": "Feature",
  "properties": {
    "addr:full":"Fellingerg 5 Graz Steiermark 8020",
    "addr:housenumber":"5",
    "addr:postcode":"8020",
    "addr:street":"Fellingerg",
    "iso:country":"AT",
    "sg:address":"Fellingerg 5",
    "sg:city":"Graz",
    "sg:orig_category":"Zahntechnische Laboratorien",
    "sg:phone":"+43 316 718500",
    "sg:postcode":"8020",
    "sg:province":"Steiermark",
    "wof:name":"Sonnleitner Siegfried",
    "wof:placetype":"venue"
},
  "geometry": {"coordinates":[15.432557106,47.0749702454],"type":"Point"}
}