{
  "type": "Feature",
  "properties": {
    "addr:full":"Druckereistr 24 Gmunden Ober\u00f6sterreich 4810",
    "addr:housenumber":"24",
    "addr:postcode":"4810",
    "addr:street":"Druckereistr;Oberoesterreich",
    "iso:country":"AT",
    "sg:address":"Druckereistr 24",
    "sg:city":"Gmunden",
    "sg:orig_category":"\u00c3\u201enderungsschneidereien",
    "sg:phone":"+43 761265779",
    "sg:postcode":"4810",
    "sg:province":"Ober\u00f6sterreich",
    "wof:name":"Staudinger Christine",
    "wof:placetype":"venue"
},
  "geometry": {"coordinates":[13.7902708054,47.9267578125],"type":"Point"}
}