{
  "type": "Feature",
  "properties": {
    "iso:country":"AT",
    "sg:address":"Imming 9b",
    "sg:city":"Schlitters",
    "sg:orig_category":"Blumengro\u00c3\u0178handel",
    "sg:phone":"+43 5288 87155",
    "sg:postcode":"6262",
    "sg:province":"Tirol",
    "wof:name":"Sch\u00e4rer Hugo",
    "wof:placetype":"venue"
},
  "geometry": {"coordinates":[11.8616275787,47.3727111816],"type":"Point"}
}