{
  "type": "Feature",
  "properties": {
    "addr:full":"Schenkendorfg 35 Wien Wien 1210",
    "addr:housenumber":"35",
    "addr:postcode":"1210",
    "addr:street":"Schenkendorfg",
    "iso:country":"AT",
    "sg:address":"Schenkendorfg 35",
    "sg:city":"Wien",
    "sg:orig_category":"Zahntechnische Laboratorien",
    "sg:phone":"+43 1 2708014",
    "sg:postcode":"1210",
    "sg:province":"Wien",
    "wof:name":"Tiller OEG",
    "wof:placetype":"venue"
},
  "geometry": {"coordinates":[16.4094390869,48.2555770874],"type":"Point"}
}