{
  "type": "Feature",
  "properties": {
    "addr:full":"Pfongauer Str. 17 Neumarkt am Wallersee Salzburg 5202",
    "addr:postcode":"5202",
    "addr:street":"Str. 17;Salzburg",
    "iso:country":"AT",
    "sg:address":"Pfongauer Str. 17",
    "sg:city":"Neumarkt am Wallersee",
    "sg:classifiers":[
        {
            "category":"Wholesale",
            "subcategory":"Drugs",
            "type":"Manufacturing & Wholesale Goods"
        }
    ],
    "sg:phone":"+43 4362 1666390",
    "sg:postcode":"5202",
    "sg:province":"Salzburg",
    "sg:tags":[
        "chemical",
        "pharmaceutical"
    ],
    "wof:name":"\u00d6STERR. ANTI-GERM & CO GES.MBH",
    "wof:placetype":"venue"
},
  "geometry": {"coordinates":[13.2305240631,47.9500579834],"type":"Point"}
}