{
  "type": "Feature",
  "properties": {
    "addr:full":"Konrad-von-Tulln-G 7 Tulln an der Donau Nieder\u00f6sterreich 3430",
    "addr:housenumber":"7",
    "addr:postcode":"3430",
    "addr:street":"Konrad-Von-Tulln-G",
    "iso:country":"AT",
    "sg:address":"Konrad-von-Tulln-G 7",
    "sg:city":"Tulln an der Donau",
    "sg:orig_category":"Schlossereien",
    "sg:phone":"+43 4322 7262265",
    "sg:postcode":"3430",
    "sg:province":"Nieder\u00f6sterreich",
    "wof:name":"Neumayer Rudolf",
    "wof:placetype":"venue"
},
  "geometry": {"coordinates":[16.0480194092,48.329498291],"type":"Point"}
}