{
  "type": "Feature",
  "properties": {
    "iso:country":"AT",
    "sg:address":"K\u00f6nigshofstr 35",
    "sg:city":"Feldkirch",
    "sg:orig_category":"Dachdeckereien",
    "sg:phone":"+43 5522 72308",
    "sg:postcode":"6800",
    "sg:province":"Vorarlberg",
    "wof:name":"Lins Josef GesmbH & Co",
    "wof:placetype":"venue"
},
  "geometry": {"coordinates":[9.5967845917,47.2381515503],"type":"Point"}
}