{
  "type": "Feature",
  "properties": {
    "iso:country":"AT",
    "sg:address":"Unterberg 111",
    "sg:city":"Zell am Ziller",
    "sg:orig_category":"Tischlereien",
    "sg:phone":"+43 5282 4286",
    "sg:postcode":"6280",
    "sg:province":"Tirol",
    "wof:name":"Tischlerei Haas-Tipotsch",
    "wof:placetype":"venue"
},
  "geometry": {"coordinates":[11.8900289536,47.2202682495],"type":"Point"}
}