{
  "type": "Feature",
  "properties": {
    "addr:full":"Bundesstr 2 Schwanberg Steiermark 8541",
    "addr:housenumber":"2",
    "addr:postcode":"8541",
    "addr:street":"Bundesstr",
    "iso:country":"AT",
    "sg:address":"Bundesstr 2",
    "sg:city":"Schwanberg",
    "sg:orig_category":"Installationsunternehmen",
    "sg:phone":"+43 3467 7655",
    "sg:postcode":"8541",
    "sg:province":"Steiermark",
    "wof:name":"M\u00fcnzer GesmbH",
    "wof:placetype":"venue"
},
  "geometry": {"coordinates":[15.2063331604,46.7575798035],"type":"Point"}
}