{
  "type": "Feature",
  "properties": {
    "addr:full":"Gumpendorfer Strasse 32 Wien Wien 1060",
    "addr:housenumber":"32",
    "addr:postcode":"1060",
    "addr:street":"Gumpendorfer Strasse",
    "iso:country":"AT",
    "sg:address":"Gumpendorfer Strasse 32",
    "sg:city":"Wien",
    "sg:classifiers":[
        {
            "category":"Building & Trades",
            "subcategory":"Cleaning & Sanitation",
            "type":"Services"
        }
    ],
    "sg:phone":"+43 1 5875455",
    "sg:postcode":"1060",
    "sg:province":"Wien",
    "sg:tags":[
        "room",
        "clean"
    ],
    "wof:name":"Leopoldine Hudetz Ges.m.b.H.",
    "wof:placetype":"venue"
},
  "geometry": {"coordinates":[16.3579559326,48.1989326477],"type":"Point"}
}