{
  "type": "Feature",
  "properties": {
    "addr:full":"Dorfstr 56 Latschach ober dem Faaker See K\u00e4rnten 9582",
    "addr:housenumber":"56",
    "addr:postcode":"9582",
    "addr:street":"Dorfstr",
    "iso:country":"AT",
    "sg:address":"Dorfstr 56",
    "sg:city":"Latschach ober dem Faaker See",
    "sg:orig_category":"Pensionen / Privatzimmer",
    "sg:phone":"+43 4342 542159",
    "sg:postcode":"9582",
    "sg:province":"K\u00e4rnten",
    "wof:name":"Pension Riki",
    "wof:placetype":"venue"
},
  "geometry": {"coordinates":[13.9258356094,46.5633735657],"type":"Point"}
}