{
  "type": "Feature",
  "properties": {
    "addr:full":"Kreuzweg 8 Gramastetten Ober\u00f6sterreich 4201",
    "addr:housenumber":"8",
    "addr:postcode":"4201",
    "addr:street":"Kreuzweg",
    "iso:country":"AT",
    "sg:address":"Kreuzweg 8",
    "sg:city":"Gramastetten",
    "sg:orig_category":"Elektroinstallationsunternehmen",
    "sg:phone":"+43 7239 8727",
    "sg:postcode":"4201",
    "sg:province":"Ober\u00f6sterreich",
    "wof:name":"M\u00f6stl Rudolf GmbH - Elektrotechnik",
    "wof:placetype":"venue"
},
  "geometry": {"coordinates":[14.1955966949,48.3755645752],"type":"Point"}
}