{
  "type": "Feature",
  "properties": {
    "addr:full":"Hollenzen 78-79 Mayrhofen Tirol 6290",
    "addr:postcode":"78-79;6290",
    "addr:street":"Hollenzen;Tirol",
    "iso:country":"AT",
    "sg:address":"Hollenzen 78-79",
    "sg:city":"Mayrhofen",
    "sg:orig_category":"Appartements / Ferienwohnungen",
    "sg:phone":"+43 4352 8563336",
    "sg:postcode":"6290",
    "sg:province":"Tirol",
    "wof:name":"Rahm Max u Anna",
    "wof:placetype":"venue"
},
  "geometry": {"coordinates":[11.8698949814,47.1862487793],"type":"Point"}
}