{
  "type": "Feature",
  "properties": {
    "addr:full":"Schwanbachg 7 Schwanenstadt Ober\u00f6sterreich 4690",
    "addr:housenumber":"7",
    "addr:postcode":"4690",
    "addr:street":"Schwanbachg",
    "iso:country":"AT",
    "sg:address":"Schwanbachg 7",
    "sg:city":"Schwanenstadt",
    "sg:orig_category":"Rauchfangkehrer",
    "sg:phone":"+43 76732345",
    "sg:postcode":"4690",
    "sg:province":"Ober\u00f6sterreich",
    "wof:name":"Wiesauer Alfred",
    "wof:placetype":"venue"
},
  "geometry": {"coordinates":[13.7708091736,48.0526657104],"type":"Point"}
}