{
  "type": "Feature",
  "properties": {
    "addr:full":"Operng 36/40 Wien Wien 1040",
    "addr:housenumber":"36 / 40",
    "addr:postcode":"1040",
    "addr:street":"Operng",
    "iso:country":"AT",
    "sg:address":"Operng 36/40",
    "sg:city":"Wien",
    "sg:orig_category":"Immobilienmakler",
    "sg:phone":"+43 1 5867224",
    "sg:postcode":"1040",
    "sg:province":"Wien",
    "wof:name":"Supp Ernst Mag",
    "wof:placetype":"venue"
},
  "geometry": {"coordinates":[16.3654708862,48.1972084045],"type":"Point"}
}