{
  "type": "Feature",
  "properties": {
    "addr:full":"Hietzinger Kai 95 Wien Wien 1130",
    "addr:housenumber":"95",
    "addr:postcode":"1130",
    "addr:street":"Hietzinger Kai",
    "iso:country":"AT",
    "sg:address":"Hietzinger Kai 95",
    "sg:city":"Wien",
    "sg:orig_category":"Immobilienmakler",
    "sg:phone":"+43 1 8761474",
    "sg:postcode":"1130",
    "sg:province":"Wien",
    "wof:name":"Weinwurm Jutta",
    "wof:placetype":"venue"
},
  "geometry": {"coordinates":[16.2905750275,48.190196991],"type":"Point"}
}