{
  "type": "Feature",
  "properties": {
    "addr:full":"Haslach 4 Gleinst\u00e4tten Steiermark 8443",
    "addr:housenumber":"4",
    "addr:postcode":"8443",
    "addr:street":"Haslach",
    "iso:country":"AT",
    "sg:address":"Haslach 4",
    "sg:city":"Gleinst\u00e4tten",
    "sg:orig_category":"Pensionen / Privatzimmer",
    "sg:phone":"+43 3457 3391",
    "sg:postcode":"8443",
    "sg:province":"Steiermark",
    "wof:name":"Seniorenpension Sch\u00f6nblick Inh Horst Kasper",
    "wof:placetype":"venue"
},
  "geometry": {"coordinates":[15.349240303,46.7488517761],"type":"Point"}
}