{
  "type": "Feature",
  "properties": {
    "addr:full":"Kirchstr 12 Patsch Tirol 6082",
    "addr:housenumber":"12",
    "addr:postcode":"6082",
    "addr:street":"Kirchstr;Tirol",
    "iso:country":"AT",
    "sg:address":"Kirchstr 12",
    "sg:city":"Patsch",
    "sg:orig_category":"Farb-, Stil- U Typberatung",
    "sg:phone":"+43 512 378148",
    "sg:postcode":"6082",
    "sg:province":"Tirol",
    "wof:name":"Color Me Beautiful - Troger-Ager Lydia",
    "wof:placetype":"venue"
},
  "geometry": {"coordinates":[11.4147930145,47.2041053772],"type":"Point"}
}