{
  "type": "Feature",
  "properties": {
    "addr:full":"Sankt Georgen ob Murau 41 St. Georgen ob Murau Steiermark 8861",
    "addr:housenumber":"41",
    "addr:postcode":"8861",
    "addr:street":"Ob Murau",
    "iso:country":"AT",
    "sg:address":"Sankt Georgen ob Murau 41",
    "sg:city":"St. Georgen ob Murau",
    "sg:orig_category":"Planing Chips",
    "sg:phone":"+43 3537 2450",
    "sg:postcode":"8861",
    "sg:province":"Steiermark",
    "wof:name":"Franz Krobath",
    "wof:placetype":"venue"
},
  "geometry": {"coordinates":[14.0940704346,47.105014801],"type":"Point"}
}