{
  "type": "Feature",
  "properties": {
    "addr:full":"Griesg 25/IV Salzburg Salzburg 5020",
    "addr:housenumber":"25 / iv",
    "addr:postcode":"5020",
    "addr:street":"Griesg;Salzburg",
    "iso:country":"AT",
    "sg:address":"Griesg 25/IV",
    "sg:city":"Salzburg",
    "sg:orig_category":"Psychotherapie",
    "sg:phone":"+43 699 12763748",
    "sg:postcode":"5020",
    "sg:province":"Salzburg",
    "wof:name":"Mackinger Herbert Univ Doz Dr",
    "wof:placetype":"venue"
},
  "geometry": {"coordinates":[13.0433769226,47.8006744385],"type":"Point"}
}