{
  "type": "Feature",
  "properties": {
    "iso:country":"AT",
    "sg:address":"Gagering 1",
    "sg:city":"F\u00fcgen",
    "sg:orig_category":"Pensionen / Privatzimmer",
    "sg:phone":"+43 4352 8862613",
    "sg:postcode":"6263",
    "sg:province":"Tirol",
    "wof:name":"Brunner Helga",
    "wof:placetype":"venue"
},
  "geometry": {"coordinates":[11.8522386551,47.3594703674],"type":"Point"}
}