{
  "type": "Feature",
  "properties": {
    "addr:full":"Waidhofner Str 33 Ertl Nieder\u00f6sterreich 3355",
    "addr:housenumber":"33",
    "addr:postcode":"3355",
    "addr:street":"Str",
    "iso:country":"AT",
    "sg:address":"Waidhofner Str 33",
    "sg:city":"Ertl",
    "sg:orig_category":"Fenster",
    "sg:phone":"+43 7477 7363",
    "sg:postcode":"3355",
    "sg:province":"Nieder\u00f6sterreich",
    "wof:name":"Fr\u00fchwald Franz",
    "wof:placetype":"venue"
},
  "geometry": {"coordinates":[14.6452665329,47.9628410339],"type":"Point"}
}