{
  "type": "Feature",
  "properties": {
    "iso:country":"AT",
    "sg:address":"Herreng 18",
    "sg:city":"Rechnitz",
    "sg:orig_category":"Sonnenstudios",
    "sg:phone":"+43 3363 79745",
    "sg:postcode":"7471",
    "sg:province":"Burgenland",
    "wof:name":"Gabi's Sonnenstudio",
    "wof:placetype":"venue"
},
  "geometry": {"coordinates":[16.4391059875,47.3045043945],"type":"Point"}
}