{
  "type": "Feature",
  "properties": {
    "addr:full":"Kolpingweg 7 Leibnitz Steiermark 8430",
    "addr:housenumber":"7",
    "addr:postcode":"8430",
    "addr:street":"Kolpingweg;Steiermark",
    "iso:country":"AT",
    "sg:address":"Kolpingweg 7",
    "sg:city":"Leibnitz",
    "sg:orig_category":"Textilwaren / Erzeugung U Gro\u00c3\u0178handel",
    "sg:phone":"+43 4334 5282909",
    "sg:postcode":"8430",
    "sg:province":"Steiermark",
    "wof:name":"Textil Sgerm - Wolfgang Sgerm KG",
    "wof:placetype":"venue"
},
  "geometry": {"coordinates":[15.5416612625,46.77684021],"type":"Point"}
}