{
  "type": "Feature",
  "properties": {
    "addr:full":"Ebnerstr 4 Traisen Nieder\u00f6sterreich 3160",
    "addr:housenumber":"4",
    "addr:postcode":"3160",
    "addr:street":"Ebnerstr",
    "iso:country":"AT",
    "sg:address":"Ebnerstr 4",
    "sg:city":"Traisen",
    "sg:orig_category":"Banken U Sparkassen",
    "sg:phone":"+43 5 010073049",
    "sg:postcode":"3160",
    "sg:province":"Nieder\u00f6sterreich",
    "wof:name":"Sparkasse Nieder\u00f6sterreich Mitte West AG",
    "wof:placetype":"venue"
},
  "geometry": {"coordinates":[15.621761322,48.0469703674],"type":"Point"}
}