{
  "type": "Feature",
  "properties": {
    "iso:country":"AT",
    "sg:address":"Gleisdorfer G 3",
    "sg:city":"Graz",
    "sg:classifiers":[
        {
            "category":"Restaurant",
            "type":"Food & Drink"
        }
    ],
    "sg:phone":"+43 4331 6815460",
    "sg:postcode":"8010",
    "sg:province":"Steiermark",
    "wof:name":"Pastini Casa Della Pasta",
    "wof:placetype":"venue"
},
  "geometry": {"coordinates":[15.4441013336,47.067905426],"type":"Point"}
}