{
  "type": "Feature",
  "properties": {
    "addr:full":"Florentin-Wehner-Weg 30a Ehrwald Tirol 6632",
    "addr:housenumber":"30a",
    "addr:postcode":"6632",
    "addr:street":"Florentin-Wehner-Weg;Tirol",
    "iso:country":"AT",
    "sg:address":"Florentin-Wehner-Weg 30a",
    "sg:city":"Ehrwald",
    "sg:orig_category":"Rauchfangkehrer",
    "sg:phone":"+43 5673 3436",
    "sg:postcode":"6632",
    "sg:province":"Tirol",
    "wof:name":"Wilhelm Hermann",
    "wof:placetype":"venue"
},
  "geometry": {"coordinates":[10.9177694321,47.3964385986],"type":"Point"}
}