{
  "type": "Feature",
  "properties": {
    "addr:full":"St Nikolaus-G 6 Innsbruck Tirol 6020",
    "addr:housenumber":"6",
    "addr:postcode":"6020",
    "addr:street":"Tirol",
    "iso:country":"AT",
    "sg:address":"St Nikolaus-G 6",
    "sg:city":"Innsbruck",
    "sg:orig_category":"Medizintechnik",
    "sg:phone":"+43 512 2782250",
    "sg:postcode":"6020",
    "sg:province":"Tirol",
    "wof:name":"Medi-Nova Medizintechnik und EinrichtungsgesmbH",
    "wof:placetype":"venue"
},
  "geometry": {"coordinates":[11.3923931122,47.2722587585],"type":"Point"}
}