{
  "type": "Feature",
  "properties": {
    "addr:full":"Hangstr 24a Spittal an der Drau K\u00e4rnten 9800",
    "addr:housenumber":"24a",
    "addr:postcode":"9800",
    "addr:street":"Hangstr;Kaernten",
    "iso:country":"AT",
    "sg:address":"Hangstr 24a",
    "sg:city":"Spittal an der Drau",
    "sg:orig_category":"Bauunternehmen",
    "sg:phone":"+43 4762 45362",
    "sg:postcode":"9800",
    "sg:province":"K\u00e4rnten",
    "wof:name":"Kostmann GesmbH",
    "wof:placetype":"venue"
},
  "geometry": {"coordinates":[13.4905672073,46.8041343689],"type":"Point"}
}