{
  "type": "Feature",
  "properties": {
    "addr:full":"Fischerweg 18 Seeboden K\u00e4rnten 9871",
    "addr:housenumber":"18",
    "addr:postcode":"9871",
    "addr:street":"Fischerweg;Kaernten",
    "iso:country":"AT",
    "sg:address":"Fischerweg 18",
    "sg:city":"Seeboden",
    "sg:orig_category":"Betriebsbeteiligungen",
    "sg:phone":"+43 4762 82292",
    "sg:postcode":"9871",
    "sg:province":"K\u00e4rnten",
    "wof:name":"Egger GmbH",
    "wof:placetype":"venue"
},
  "geometry": {"coordinates":[13.5063896179,46.8149108887],"type":"Point"}
}