{
  "type": "Feature",
  "properties": {
    "addr:full":"Bessemerstrasse 38 Wien Wien 1210",
    "addr:housenumber":"38",
    "addr:postcode":"1210",
    "addr:street":"Bessemerstrasse",
    "iso:country":"AT",
    "sg:address":"Bessemerstrasse 38",
    "sg:city":"Wien",
    "sg:orig_category":"Internet-Design, Web-Design",
    "sg:phone":"+43 1 2595860",
    "sg:postcode":"1210",
    "sg:province":"Wien",
    "sg:website":"webbetreuung.com",
    "wof:name":"webbetreuung.com",
    "wof:placetype":"venue"
},
  "geometry": {"coordinates":[16.413640976,48.2571754456],"type":"Point"}
}