{
  "type": "Feature",
  "properties": {
    "addr:full":"Lawogstr 19 Leonstein Ober\u00f6sterreich 4592",
    "addr:housenumber":"19",
    "addr:postcode":"4592",
    "addr:street":"Lawogstr",
    "iso:country":"AT",
    "sg:address":"Lawogstr 19",
    "sg:city":"Leonstein",
    "sg:orig_category":"Autoreparatur",
    "sg:phone":"+43 4375 843813",
    "sg:postcode":"4592",
    "sg:province":"Ober\u00f6sterreich",
    "wof:name":"DENK Automobile - Wolfgang Denk",
    "wof:placetype":"venue"
},
  "geometry": {"coordinates":[14.2316293716,47.8819274902],"type":"Point"}
}