{
  "type": "Feature",
  "properties": {
    "addr:full":"Mittertorstr 47a Mureck Steiermark 8480",
    "addr:housenumber":"47a",
    "addr:postcode":"8480",
    "addr:street":"Mittertorstr",
    "iso:country":"AT",
    "sg:address":"Mittertorstr 47a",
    "sg:city":"Mureck",
    "sg:orig_category":"Zahntechnische Laboratorien",
    "sg:phone":"+43 3472 2662",
    "sg:postcode":"8480",
    "sg:province":"Steiermark",
    "wof:name":"Innovative Zahntechnik Michael Gombocz",
    "wof:placetype":"venue"
},
  "geometry": {"coordinates":[15.7819709778,46.713306427],"type":"Point"}
}