{
  "type": "Feature",
  "properties": {
    "addr:full":"Hauptpl. 32 Kittsee Burgenland 2421",
    "addr:housenumber":"32",
    "addr:postcode":"2421",
    "addr:street":"Hauptpl.",
    "iso:country":"AT",
    "sg:address":"Hauptpl. 32",
    "sg:city":"Kittsee",
    "sg:classifiers":[
        {
            "category":"Communications",
            "subcategory":"Television Station",
            "type":"Services"
        }
    ],
    "sg:phone":"+43 4321 4323130",
    "sg:postcode":"2421",
    "sg:province":"Burgenland",
    "sg:tags":[
        "audio-visual"
    ],
    "wof:name":"RICHARD KUNI GES.MBH",
    "wof:placetype":"venue"
},
  "geometry": {"coordinates":[17.0654258728,48.0912971497],"type":"Point"}
}