{
  "type": "Feature",
  "properties": {
    "addr:full":"Lengbachl 19 Altlengbach Nieder\u00f6sterreich 3033",
    "addr:housenumber":"19",
    "addr:postcode":"3033",
    "addr:street":"Lengbachl",
    "iso:country":"AT",
    "sg:address":"Lengbachl 19",
    "sg:city":"Altlengbach",
    "sg:classifiers":[
        {
            "category":"Manufacturing",
            "subcategory":"Wood Products",
            "type":"Manufacturing & Wholesale Goods"
        }
    ],
    "sg:phone":"+43 2774 6279",
    "sg:postcode":"3033",
    "sg:province":"Nieder\u00f6sterreich",
    "sg:tags":[
        "chair-legs"
    ],
    "wof:name":"Josef Gutscher",
    "wof:placetype":"venue"
},
  "geometry": {"coordinates":[15.9633178711,48.148979187],"type":"Point"}
}