{
  "type": "Feature",
  "properties": {
    "iso:country":"AT",
    "sg:address":"Nr 32",
    "sg:city":"Allentsteig",
    "sg:orig_category":"Biologische Produkte",
    "sg:phone":"+43 2824 27372",
    "sg:postcode":"3804",
    "sg:province":"Nieder\u00f6sterreich",
    "wof:name":"Marksteiner Ernst",
    "wof:placetype":"venue"
},
  "geometry": {"coordinates":[15.3292703629,48.6954879761],"type":"Point"}
}