{
  "type": "Feature",
  "properties": {
    "iso:country":"AT",
    "sg:address":"Margetinstrasse 8c",
    "sg:city":"Wien",
    "sg:classifiers":[
        {
            "category":"Professional",
            "subcategory":"Advertising",
            "type":"Services"
        }
    ],
    "sg:phone":"+43 1 7674818",
    "sg:postcode":"1110",
    "sg:province":"Wien",
    "sg:tags":[
        "materials",
        "electronic"
    ],
    "sg:website":"wis.co.at",
    "wof:name":"WIS Werbeinformationssysteme Vertriebs GmbH",
    "wof:placetype":"venue"
},
  "geometry": {"coordinates":[16.4700317383,48.1669692993],"type":"Point"}
}