{
  "type": "Feature",
  "properties": {
    "addr:full":"Inzersdorfer Str 111 Wien Wien 1100",
    "addr:housenumber":"111",
    "addr:postcode":"1100",
    "iso:country":"AT",
    "sg:address":"Inzersdorfer Str 111",
    "sg:city":"Wien",
    "sg:orig_category":"Holzbearbeitungsmaschinen U -Werkzeuge",
    "sg:phone":"+43 4316 021049",
    "sg:postcode":"1100",
    "sg:province":"Wien",
    "wof:name":"Gr\u00f6ger Walter",
    "wof:placetype":"venue"
},
  "geometry": {"coordinates":[16.3597927094,48.1732254028],"type":"Point"}
}