{
  "type": "Feature",
  "properties": {
    "addr:full":"Hauptstrasse 130 Zams Tirol 6511",
    "addr:housenumber":"130",
    "addr:postcode":"6511",
    "addr:street":"Hauptstrasse;Tirol",
    "iso:country":"AT",
    "sg:address":"Hauptstrasse 130",
    "sg:city":"Zams",
    "sg:classifiers":[
        {
            "category":"Home & Garden",
            "subcategory":"Hardware",
            "type":"Retail Goods"
        }
    ],
    "sg:phone":"+43 5442 62673",
    "sg:postcode":"6511",
    "sg:province":"Tirol",
    "sg:tags":[
        "steel",
        "banister"
    ],
    "wof:name":"Otto Platter GmbH",
    "wof:placetype":"venue"
},
  "geometry": {"coordinates":[10.5869445801,47.1634597778],"type":"Point"}
}