{
  "type": "Feature",
  "properties": {
    "iso:country":"AT",
    "sg:address":"Pattighamried 3",
    "sg:city":"Ried im Innkreis",
    "sg:orig_category":"Tischlereien",
    "sg:phone":"+43 7752 85048",
    "sg:postcode":"4910",
    "sg:province":"Ober\u00f6sterreich",
    "wof:name":"Lindlbauer Franz Xaver",
    "wof:placetype":"venue"
},
  "geometry": {"coordinates":[13.4673995972,48.1712760925],"type":"Point"}
}