{
  "type": "Feature",
  "properties": {
    "addr:full":"Aigner Str 16 Salzburg Salzburg 5020",
    "addr:housenumber":"16",
    "addr:postcode":"5020",
    "addr:street":"Str;Salzburg",
    "iso:country":"AT",
    "sg:address":"Aigner Str 16",
    "sg:city":"Salzburg",
    "sg:orig_category":"Restaurants: Chinesisch",
    "sg:phone":"+43 662 622695",
    "sg:postcode":"5020",
    "sg:province":"Salzburg",
    "wof:name":"Chinesische Mauer Chinarestaurant Lin",
    "wof:placetype":"venue"
},
  "geometry": {"coordinates":[13.0670518875,47.7974967957],"type":"Point"}
}