{
  "type": "Feature",
  "properties": {
    "addr:full":"Diesseits 139 St. Martin im Innkreis Ober\u00f6sterreich 4973",
    "addr:housenumber":"139",
    "addr:postcode":"4973",
    "addr:street":"Diesseits",
    "iso:country":"AT",
    "sg:address":"Diesseits 139",
    "sg:city":"St. Martin im Innkreis",
    "sg:orig_category":"Werbegestalter",
    "sg:phone":"+43 4377 517305",
    "sg:postcode":"4973",
    "sg:province":"Ober\u00f6sterreich",
    "wof:name":"Haury Helmut",
    "wof:placetype":"venue"
},
  "geometry": {"coordinates":[13.4381246567,48.2940559387],"type":"Point"}
}