{
  "type": "Feature",
  "properties": {
    "addr:full":"Marktpl 11 Haslach an der M\u00fchl Ober\u00f6sterreich 4170",
    "addr:housenumber":"11",
    "addr:postcode":"4170",
    "addr:street":"Marktpl;Oberoesterreich",
    "iso:country":"AT",
    "sg:address":"Marktpl 11",
    "sg:city":"Haslach an der M\u00fchl",
    "sg:orig_category":"Elektroinstallationsunternehmen",
    "sg:phone":"+43 7289 713740",
    "sg:postcode":"4170",
    "sg:province":"Ober\u00f6sterreich",
    "wof:name":"Schmid Nikolaus",
    "wof:placetype":"venue"
},
  "geometry": {"coordinates":[14.0405731201,48.5751647949],"type":"Point"}
}