{
  "type": "Feature",
  "properties": {
    "addr:full":"Hausbach 1 Ellmau Tirol 6352",
    "addr:housenumber":"1",
    "addr:postcode":"6352",
    "addr:street":"Hausbach;Tirol",
    "iso:country":"AT",
    "sg:address":"Hausbach 1",
    "sg:city":"Ellmau",
    "sg:orig_category":"Autohandel",
    "sg:phone":"+43 5358 2711",
    "sg:postcode":"6352",
    "sg:province":"Tirol",
    "wof:name":"Autocenter Fieg GesmbH",
    "wof:placetype":"venue"
},
  "geometry": {"coordinates":[12.314414978,47.5192680359],"type":"Point"}
}