{
  "type": "Feature",
  "properties": {
    "iso:country":"AT",
    "sg:address":"Franz-Josef-Str 15",
    "sg:city":"Salzburg",
    "sg:orig_category":"Telekommunikation",
    "sg:phone":"+43 662 93090903",
    "sg:postcode":"5020",
    "sg:province":"Salzburg",
    "wof:name":"ClientLogic HandelsgesmbH",
    "wof:placetype":"venue"
},
  "geometry": {"coordinates":[13.0451221466,47.8073883057],"type":"Point"}
}