{
  "type": "Feature",
  "properties": {
    "addr:full":"Apetloner Str 40 Illmitz Burgenland 7142",
    "addr:postcode":"7142",
    "addr:street":"Str 40 Illmitz",
    "iso:country":"AT",
    "sg:address":"Apetloner Str 40",
    "sg:city":"Illmitz",
    "sg:orig_category":"Lebensmittel / Einzelhandel",
    "sg:phone":"+43 4321 7526003",
    "sg:postcode":"7142",
    "sg:province":"Burgenland",
    "wof:name":"Billa AG",
    "wof:placetype":"venue"
},
  "geometry": {"coordinates":[16.8082962036,47.7598724365],"type":"Point"}
}