{
  "type": "Feature",
  "properties": {
    "addr:full":"Allerheiligenpl 16 Wien Wien 1200",
    "addr:housenumber":"16",
    "addr:postcode":"1200",
    "addr:street":"Allerheiligenpl",
    "iso:country":"AT",
    "sg:address":"Allerheiligenpl 16",
    "sg:city":"Wien",
    "sg:orig_category":"Friseure U Frisiersalons",
    "sg:phone":"+43 1 3344925",
    "sg:postcode":"1200",
    "sg:province":"Wien",
    "wof:name":"Schenk Sonja",
    "wof:placetype":"venue"
},
  "geometry": {"coordinates":[16.3864440918,48.2380447388],"type":"Point"}
}