{
  "type": "Feature",
  "properties": {
    "addr:full":"Fabrikgasse 15 Felixdorf Nieder\u00f6sterreich 2603",
    "addr:housenumber":"15",
    "addr:postcode":"2603",
    "addr:street":"Fabrikgasse",
    "iso:country":"AT",
    "sg:address":"Fabrikgasse 15",
    "sg:city":"Felixdorf",
    "sg:classifiers":[
        {
            "category":"Structure",
            "subcategory":"Office Building",
            "type":"Public Place"
        }
    ],
    "sg:phone":"+43 2628 65330",
    "sg:postcode":"2603",
    "sg:province":"Nieder\u00f6sterreich",
    "sg:tags":[
        "industrial",
        "assembly"
    ],
    "sg:website":"mdesign3.at",
    "wof:name":"G&K - Metallbau GmbH",
    "wof:placetype":"venue"
},
  "geometry": {"coordinates":[16.2460193634,47.8873825073],"type":"Point"}
}