{
  "type": "Feature",
  "properties": {
    "addr:full":"Achstr 12 Altach Vorarlberg 6844",
    "addr:housenumber":"12",
    "addr:postcode":"6844",
    "addr:street":"Achstr",
    "iso:country":"AT",
    "sg:address":"Achstr 12",
    "sg:city":"Altach",
    "sg:orig_category":"Drogerien",
    "sg:phone":"+43 5576 72573",
    "sg:postcode":"6844",
    "sg:province":"Vorarlberg",
    "wof:name":"Jochum Siegfried GesmbH",
    "wof:placetype":"venue"
},
  "geometry": {"coordinates":[9.6537132263,47.3537826538],"type":"Point"}
}