{
  "type": "Feature",
  "properties": {
    "addr:full":"Bahnhofstr 54 Traun Ober\u00f6sterreich 4050",
    "addr:housenumber":"54",
    "addr:postcode":"4050",
    "addr:street":"Bahnhofstr",
    "iso:country":"AT",
    "sg:address":"Bahnhofstr 54",
    "sg:city":"Traun",
    "sg:orig_category":"Autoreparatur",
    "sg:phone":"+43 7229 65995",
    "sg:postcode":"4050",
    "sg:province":"Ober\u00f6sterreich",
    "wof:name":"Pum Erwin",
    "wof:placetype":"venue"
},
  "geometry": {"coordinates":[14.2503128052,48.222694397],"type":"Point"}
}