{
  "type": "Feature",
  "properties": {
    "addr:full":"Inffeldg 16a Graz Steiermark 8010",
    "addr:housenumber":"16a",
    "addr:postcode":"8010",
    "addr:street":"Inffeldg",
    "iso:country":"AT",
    "sg:address":"Inffeldg 16a",
    "sg:city":"Graz",
    "sg:orig_category":"Institute",
    "sg:phone":"+43 316 8735514",
    "sg:postcode":"8010",
    "sg:province":"Steiermark",
    "wof:name":"Inst f Angewandte Informationsverarbeitung und Kommunikationstechnologie",
    "wof:placetype":"venue"
},
  "geometry": {"coordinates":[15.4585018158,47.0584373474],"type":"Point"}
}