{
  "type": "Feature",
  "properties": {
    "addr:full":"Linieng 52/16 Wien Wien 1060",
    "addr:housenumber":"52 / 16",
    "addr:postcode":"1060",
    "addr:street":"Linieng",
    "iso:country":"AT",
    "sg:address":"Linieng 52/16",
    "sg:city":"Wien",
    "sg:orig_category":"Lebens- U Sozialberatung",
    "sg:phone":"+43 1 5965253",
    "sg:postcode":"1060",
    "sg:province":"Wien",
    "wof:name":"Strouhal Edith - Lebensberatung Meditation Bachbl\u00fcten",
    "wof:placetype":"venue"
},
  "geometry": {"coordinates":[16.3398303986,48.1913795471],"type":"Point"}
}