{
  "type": "Feature",
  "properties": {
    "addr:full":"Hauptpl 25 Schweiggers Nieder\u00f6sterreich 3931",
    "addr:housenumber":"25",
    "addr:postcode":"3931",
    "addr:street":"Hauptpl",
    "iso:country":"AT",
    "sg:address":"Hauptpl 25",
    "sg:city":"Schweiggers",
    "sg:orig_category":"Gemeinden",
    "sg:phone":"+43 4328 298234",
    "sg:postcode":"3931",
    "sg:province":"Nieder\u00f6sterreich",
    "wof:name":"Gemeindeamt Schweiggers",
    "wof:placetype":"venue"
},
  "geometry": {"coordinates":[15.0631551743,48.6674423218],"type":"Point"}
}