{
  "type": "Feature",
  "properties": {
    "addr:full":"Nr 51 Neuhaus Ober\u00f6sterreich 4114",
    "addr:postcode":"4114",
    "addr:street":"Nr;Neuhaus",
    "iso:country":"AT",
    "sg:address":"Nr 51",
    "sg:city":"Neuhaus",
    "sg:classifiers":[
        {
            "category":"Internet Cafe",
            "subcategory":"None",
            "type":"Food & Drink"
        }
    ],
    "sg:phone":"+43 7232 209720",
    "sg:postcode":"4114",
    "sg:province":"Ober\u00f6sterreich",
    "wof:name":"DCP.Gilligsberger - Internet-Anwendungen",
    "wof:placetype":"venue"
},
  "geometry": {"coordinates":[166.9221496582,-0.5282999873],"type":"Point"}
}