{
  "type": "Feature",
  "properties": {
    "addr:full":"Nr 102b Kalwang Steiermark 8775",
    "addr:postcode":"8775",
    "addr:street":"Nr",
    "iso:country":"AT",
    "sg:address":"Nr 102b",
    "sg:city":"Kalwang",
    "sg:orig_category":"Baumschulen",
    "sg:phone":"+43 3846 86930",
    "sg:postcode":"8775",
    "sg:province":"Steiermark",
    "wof:name":"LIECO - Liechtenstein ForstpflanzengesmbH",
    "wof:placetype":"venue"
},
  "geometry": {"coordinates":[14.7566070557,47.4275856018],"type":"Point"}
}