{
  "type": "Feature",
  "properties": {
    "addr:full":"Hauptpl 1 Ybbs an der Donau Nieder\u00f6sterreich 3370",
    "addr:housenumber":"1",
    "addr:postcode":"3370",
    "addr:street":"Hauptpl",
    "iso:country":"AT",
    "sg:address":"Hauptpl 1",
    "sg:city":"Ybbs an der Donau",
    "sg:orig_category":"Bestattungsunternehmen",
    "sg:phone":"+43 4374 1255451",
    "sg:postcode":"3370",
    "sg:province":"Nieder\u00f6sterreich",
    "wof:name":"St\u00e4dtische Bestattung Ybbs - Hochreiter",
    "wof:placetype":"venue"
},
  "geometry": {"coordinates":[15.0851297379,48.17710495],"type":"Point"}
}