{
  "type": "Feature",
  "properties": {
    "addr:full":"G\u00f6tschka 27 Neumarkt im M\u00fchlkreis Ober\u00f6sterreich 4212",
    "addr:housenumber":"27",
    "addr:postcode":"4212",
    "addr:street":"Goetschka",
    "iso:country":"AT",
    "sg:address":"G\u00f6tschka 27",
    "sg:city":"Neumarkt im M\u00fchlkreis",
    "sg:orig_category":"Glasereien",
    "sg:phone":"+43 4379 418262",
    "sg:postcode":"4212",
    "sg:province":"Ober\u00f6sterreich",
    "wof:name":"Gst\u00f6ttenbauer Glas GesmbH & Co KG",
    "wof:placetype":"venue"
},
  "geometry": {"coordinates":[14.4865856171,48.400302887],"type":"Point"}
}