{
  "type": "Feature",
  "properties": {
    "addr:full":"Grauer-Stein-Weg 49 Innsbruck Tirol 6020",
    "addr:housenumber":"49",
    "addr:postcode":"6020",
    "addr:street":"Grauer-Stein-Weg;Tirol",
    "iso:country":"AT",
    "sg:address":"Grauer-Stein-Weg 49",
    "sg:city":"Innsbruck",
    "sg:orig_category":"Autohandel",
    "sg:phone":"+43 512 276277",
    "sg:postcode":"6020",
    "sg:province":"Tirol",
    "wof:name":"Reimair Hansj\u00f6rg OEG",
    "wof:placetype":"venue"
},
  "geometry": {"coordinates":[11.3621063232,47.2664718628],"type":"Point"}
}