{
  "type": "Feature",
  "properties": {
    "addr:full":"Weiglstr 11 Pottenbrunn Nieder\u00f6sterreich 3140",
    "addr:housenumber":"11",
    "addr:postcode":"3140",
    "addr:street":"Weiglstr;Niederoesterreich",
    "iso:country":"AT",
    "sg:address":"Weiglstr 11",
    "sg:city":"Pottenbrunn",
    "sg:orig_category":"Non-Classified Establishments",
    "sg:phone":"+43 2742 42219",
    "sg:postcode":"3140",
    "sg:province":"Nieder\u00f6sterreich",
    "wof:name":"Pfarramt",
    "wof:placetype":"venue"
},
  "geometry": {"coordinates":[15.6910429001,48.2378120422],"type":"Point"}
}