{
  "type": "Feature",
  "properties": {
    "iso:country":"AT",
    "sg:address":"Raiffeisenplatz 1 ",
    "sg:city":"Bruck an der Leitha",
    "sg:classifiers":[
        {
            "category":"Banks & Credit Unions",
            "subcategory":"Bank",
            "type":"Services"
        }
    ],
    "sg:phone":"+43 4321 62625550",
    "sg:postcode":"2460",
    "sg:province":"Nieder\u00f6sterreich",
    "sg:tags":[
        "banking",
        "institution"
    ],
    "wof:name":"RAIFFEISEN REGIONALBANK BRUCK",
    "wof:placetype":"venue"
},
  "geometry": {"coordinates":[16.7775001526,48.0220108032],"type":"Point"}
}