{
  "type": "Feature",
  "properties": {
    "addr:full":"Braidlandstrasse 10 Leonding Ober\u00f6sterreich 4060",
    "addr:housenumber":"10",
    "addr:postcode":"4060",
    "addr:street":"Braidlandstrasse",
    "iso:country":"AT",
    "sg:address":"Braidlandstrasse 10",
    "sg:city":"Leonding",
    "sg:classifiers":[
        {
            "category":"Organizations",
            "subcategory":"Non-profit Organization",
            "type":"Services"
        }
    ],
    "sg:phone":"+43 732 374566",
    "sg:postcode":"4060",
    "sg:province":"Ober\u00f6sterreich",
    "sg:tags":[
        "alarm",
        "system"
    ],
    "wof:name":"Auer Dieter Michael B\u00fcro f\u00fcr Elektrotechnik",
    "wof:placetype":"venue"
},
  "geometry": {"coordinates":[14.2626810074,48.2510986328],"type":"Point"}
}