{
  "type": "Feature",
  "properties": {
    "iso:country":"AT",
    "sg:address":"Max Tendler-Str 14",
    "sg:city":"Leoben",
    "sg:orig_category":"Non-Classified Establishments",
    "sg:phone":"+43 3842 427560",
    "sg:postcode":"8700",
    "sg:province":"Steiermark",
    "wof:name":"Agrarbezirksbeh\u00f6rde Leoben",
    "wof:placetype":"venue"
},
  "geometry": {"coordinates":[15.0925016403,47.3825187683],"type":"Point"}
}