{
  "type": "Feature",
  "properties": {
    "iso:country":"AT",
    "sg:address":"Keinerg 10",
    "sg:city":"Wien",
    "sg:orig_category":"Zeitungen U Zeitschriften",
    "sg:phone":"+43 4317 121348",
    "sg:postcode":"1030",
    "sg:province":"Wien",
    "wof:name":"Lewak Elisabeth",
    "wof:placetype":"venue"
},
  "geometry": {"coordinates":[16.3983688354,48.1975975037],"type":"Point"}
}