{
  "type": "Feature",
  "properties": {
    "addr:full":"Rheinstr 16 Bregenz Vorarlberg 6900",
    "addr:housenumber":"16",
    "addr:postcode":"6900",
    "addr:street":"Rheinstr",
    "iso:country":"AT",
    "sg:address":"Rheinstr 16",
    "sg:city":"Bregenz",
    "sg:orig_category":"Physiotherapie",
    "sg:phone":"+43 5574 58963",
    "sg:postcode":"6900",
    "sg:province":"Vorarlberg",
    "wof:name":"Crnjac Mario Dipl-PT",
    "wof:placetype":"venue"
},
  "geometry": {"coordinates":[9.7290897369,47.497428894],"type":"Point"}
}