{
  "type": "Feature",
  "properties": {
    "iso:country":"AT",
    "sg:address":"Nr 5",
    "sg:city":"Zirl",
    "sg:classifiers":[
        {
            "category":"Home & Garden",
            "subcategory":"Garden Supply",
            "type":"Retail Goods"
        }
    ],
    "sg:phone":"+43 4352 3852203",
    "sg:postcode":"6170",
    "sg:province":"Tirol",
    "sg:tags":[
        "schotter",
        "sand",
        "u"
    ],
    "wof:name":"Plattner & Co",
    "wof:placetype":"venue"
},
  "geometry": {"coordinates":[101.7013626099,26.3987903595],"type":"Point"}
}