{
  "type": "Feature",
  "properties": {
    "addr:full":"Dr Glatz-Str 30 Innsbruck Tirol 6020",
    "addr:housenumber":"30",
    "addr:postcode":"6020",
    "addr:street":"Tirol",
    "iso:country":"AT",
    "sg:address":"Dr Glatz-Str 30",
    "sg:city":"Innsbruck",
    "sg:orig_category":"Lebensmittel / Einzelhandel",
    "sg:phone":"+43 512 399902",
    "sg:postcode":"6020",
    "sg:province":"Tirol",
    "wof:name":"Billa AG",
    "wof:placetype":"venue"
},
  "geometry": {"coordinates":[11.4150524139,47.2589492798],"type":"Point"}
}