{
  "type": "Feature",
  "properties": {
    "addr:full":"Nr 77 Neudau Steiermark 8292",
    "addr:postcode":"8292",
    "addr:street":"Nr",
    "iso:country":"AT",
    "sg:address":"Nr 77",
    "sg:city":"Neudau",
    "sg:orig_category":"Volksschulen",
    "sg:phone":"+43 4333 582716",
    "sg:postcode":"8292",
    "sg:province":"Steiermark",
    "wof:name":"Volksschule",
    "wof:placetype":"venue"
},
  "geometry": {"coordinates":[16.1003761292,47.1778526306],"type":"Point"}
}