{
  "type": "Feature",
  "properties": {
    "addr:full":"Eberhartweg 17 Saalbach Salzburg 5753",
    "addr:housenumber":"17",
    "addr:postcode":"5753",
    "addr:street":"Eberhartweg;Salzburg",
    "iso:country":"AT",
    "sg:address":"Eberhartweg 17",
    "sg:city":"Saalbach",
    "sg:orig_category":"Appartements / Ferienwohnungen",
    "sg:phone":"+43 6541 72430",
    "sg:postcode":"5753",
    "sg:province":"Salzburg",
    "wof:name":"Appartement Rapoltgut",
    "wof:placetype":"venue"
},
  "geometry": {"coordinates":[12.6361532211,47.393157959],"type":"Point"}
}