{
  "type": "Feature",
  "properties": {
    "addr:full":"Hofwiese 23 Kirchschlag in der Buckligen Welt Nieder\u00f6sterreich 2860",
    "addr:housenumber":"23",
    "addr:postcode":"2860",
    "addr:street":"Hofwiese",
    "iso:country":"AT",
    "sg:address":"Hofwiese 23",
    "sg:city":"Kirchschlag in der Buckligen Welt",
    "sg:orig_category":"Physiotherapie",
    "sg:phone":"+43 664 1821622",
    "sg:postcode":"2860",
    "sg:province":"Nieder\u00f6sterreich",
    "wof:name":"Rudolf Anita Dipl-PT",
    "wof:placetype":"venue"
},
  "geometry": {"coordinates":[16.2781600952,47.4934043884],"type":"Point"}
}