{
  "type": "Feature",
  "properties": {
    "addr:full":"Industriestr 17 Arnoldstein K\u00e4rnten 9601",
    "addr:housenumber":"17",
    "addr:postcode":"9601",
    "addr:street":"Industriestr;Kaernten",
    "iso:country":"AT",
    "sg:address":"Industriestr 17",
    "sg:city":"Arnoldstein",
    "sg:orig_category":"Abfallentsorgung U -Verwertung",
    "sg:phone":"+43 4255 39900",
    "sg:postcode":"9601",
    "sg:province":"K\u00e4rnten",
    "sg:website":"www.abrg.at",
    "wof:name":"ABRG Asamer-Becker Recycling GmbH",
    "wof:placetype":"venue"
},
  "geometry": {"coordinates":[13.6929159164,46.5535774231],"type":"Point"}
}