{
  "type": "Feature",
  "properties": {
    "addr:full":"Jedlersdorfer Pl 27 Wien Wien 1210",
    "addr:housenumber":"27",
    "addr:postcode":"1210",
    "addr:street":"Jedlersdorfer Pl",
    "iso:country":"AT",
    "sg:address":"Jedlersdorfer Pl 27",
    "sg:city":"Wien",
    "sg:orig_category":"Autospenglereien",
    "sg:phone":"+43 1 2921466",
    "sg:postcode":"1210",
    "sg:province":"Wien",
    "wof:name":"Lindinger & Co",
    "wof:placetype":"venue"
},
  "geometry": {"coordinates":[16.4091491699,48.2827262878],"type":"Point"}
}