{
  "type": "Feature",
  "properties": {
    "addr:full":"Svetelskystr 5 Wien Wien 1110",
    "addr:housenumber":"5",
    "addr:postcode":"1110",
    "addr:street":"Svetelskystr",
    "iso:country":"AT",
    "sg:address":"Svetelskystr 5",
    "sg:city":"Wien",
    "sg:orig_category":"Volksschulen",
    "sg:phone":"+43 1 7687860111",
    "sg:postcode":"1110",
    "sg:province":"Wien",
    "wof:name":"Volksschule d Stadt Wien",
    "wof:placetype":"venue"
},
  "geometry": {"coordinates":[16.4622211456,48.1548881531],"type":"Point"}
}