{
  "type": "Feature",
  "properties": {
    "addr:full":"H\u00f6rzberg 2 Andorf Ober\u00f6sterreich 4770",
    "addr:housenumber":"2",
    "addr:postcode":"4770",
    "addr:street":"Hoerzberg",
    "iso:country":"AT",
    "sg:address":"H\u00f6rzberg 2",
    "sg:city":"Andorf",
    "sg:orig_category":"Baumschulen",
    "sg:phone":"+43 7766 2319",
    "sg:postcode":"4770",
    "sg:province":"Ober\u00f6sterreich",
    "wof:name":"Pichler Johann",
    "wof:placetype":"venue"
},
  "geometry": {"coordinates":[13.5776348114,48.371761322],"type":"Point"}
}