{
  "type": "Feature",
  "properties": {
    "addr:full":"Ponauer Str 11b/23 Spittal an der Drau K\u00e4rnten 9800",
    "addr:housenumber":"11b / 23",
    "addr:postcode":"9800",
    "addr:street":"Str;Kaernten",
    "iso:country":"AT",
    "sg:address":"Ponauer Str 11b/23",
    "sg:city":"Spittal an der Drau",
    "sg:orig_category":"Raumausstattung",
    "sg:phone":"+43 4367 66072366",
    "sg:postcode":"9800",
    "sg:province":"K\u00e4rnten",
    "wof:name":"Wohnausstattung Komiszar",
    "wof:placetype":"venue"
},
  "geometry": {"coordinates":[13.4988708496,46.7901763916],"type":"Point"}
}