{
  "type": "Feature",
  "properties": {
    "addr:full":"Lafnitz 261  Lafnitz Steiermark 8233",
    "addr:housenumber":"261",
    "addr:postcode":"8233",
    "addr:street":"Lafnitz",
    "iso:country":"AT",
    "sg:address":"Lafnitz 261 ",
    "sg:city":"Lafnitz",
    "sg:classifiers":[
        {
            "category":"Home & Garden",
            "subcategory":"Carpets & Floor Coverings",
            "type":"Retail Goods"
        }
    ],
    "sg:phone":"+43 3338 3987",
    "sg:postcode":"8233",
    "sg:province":"Steiermark",
    "sg:tags":[
        "supraregional",
        "flooring"
    ],
    "wof:name":"Werner Schantl GesmbH",
    "wof:placetype":"venue"
},
  "geometry": {"coordinates":[16.0214118958,47.3531990051],"type":"Point"}
}