{
  "type": "Feature",
  "properties": {
    "addr:full":"Feldkellerg 10 Wien Wien 1130",
    "addr:housenumber":"10",
    "addr:postcode":"1130",
    "addr:street":"Feldkellerg",
    "iso:country":"AT",
    "sg:address":"Feldkellerg 10",
    "sg:city":"Wien",
    "sg:orig_category":"Bastelbedarf",
    "sg:phone":"+43 4318 048840",
    "sg:postcode":"1130",
    "sg:province":"Wien",
    "wof:name":"Bastel - Insel Stepanek Michaela",
    "wof:placetype":"venue"
},
  "geometry": {"coordinates":[16.2871112823,48.1699752808],"type":"Point"}
}