{
  "type": "Feature",
  "properties": {
    "addr:full":"Runastr 8 Feldkirch Vorarlberg 6800",
    "addr:housenumber":"8",
    "addr:postcode":"6800",
    "addr:street":"Runastr",
    "iso:country":"AT",
    "sg:address":"Runastr 8",
    "sg:city":"Feldkirch",
    "sg:orig_category":"Lebensmittel / Einzelhandel",
    "sg:phone":"+43 5522 79552",
    "sg:postcode":"6800",
    "sg:province":"Vorarlberg",
    "wof:name":"ADEG Aktiv Markt",
    "wof:placetype":"venue"
},
  "geometry": {"coordinates":[9.5967845917,47.2381515503],"type":"Point"}
}