{
  "type": "Feature",
  "properties": {
    "addr:full":"Dorfstr 27 Fohnsdorf Steiermark 8753",
    "addr:housenumber":"27",
    "addr:postcode":"8753",
    "addr:street":"Dorfstr",
    "iso:country":"AT",
    "sg:address":"Dorfstr 27",
    "sg:city":"Fohnsdorf",
    "sg:orig_category":"Pensionen / Privatzimmer",
    "sg:phone":"+43 4335 732210",
    "sg:postcode":"8753",
    "sg:province":"Steiermark",
    "wof:name":"K\u00f6ck Helmut Dipl Ing Land- u Forstwirtschaft - Fremdenzimmer",
    "wof:placetype":"venue"
},
  "geometry": {"coordinates":[14.6780195236,47.2084732056],"type":"Point"}
}