{
  "type": "Feature",
  "properties": {
    "addr:full":"Blumauergasse 28 Steyr Ober\u00f6sterreich 4400",
    "addr:housenumber":"28",
    "addr:postcode":"4400",
    "addr:street":"Blumauergasse;Oberoesterreich",
    "iso:country":"AT",
    "sg:address":"Blumauergasse 28",
    "sg:city":"Steyr",
    "sg:classifiers":[
        {
            "category":"Wholesale",
            "subcategory":"Plants",
            "type":"Manufacturing & Wholesale Goods"
        }
    ],
    "sg:phone":"+43 7252 43112",
    "sg:postcode":"4400",
    "sg:province":"Ober\u00f6sterreich",
    "sg:tags":[
        "screen",
        "printing"
    ],
    "sg:website":"gbm.at",
    "wof:name":"Staufer & Havelka Golden Builders Media KEG",
    "wof:placetype":"venue"
},
  "geometry": {"coordinates":[14.4107666016,48.0400733948],"type":"Point"}
}