{
  "type": "Feature",
  "properties": {
    "addr:full":"St Veit-G 70 Wien Wien 1130",
    "addr:housenumber":"70",
    "addr:postcode":"1130",
    "iso:country":"AT",
    "sg:address":"St Veit-G 70",
    "sg:city":"Wien",
    "sg:classifiers":[
        {
            "category":"Shopping",
            "subcategory":"Party Supplies",
            "type":"Retail Goods"
        }
    ],
    "sg:phone":"+43 1 8774636",
    "sg:postcode":"1130",
    "sg:province":"Wien",
    "sg:tags":[
        "u",
        "lichtanlagen",
        "ton-"
    ],
    "wof:name":"Audio Project GmbH",
    "wof:placetype":"venue"
},
  "geometry": {"coordinates":[16.2866897583,48.1898384094],"type":"Point"}
}