{
  "type": "Feature",
  "properties": {
    "addr:full":"Lagerg 348 Puntigam Steiermark 8055",
    "addr:housenumber":"348",
    "addr:postcode":"8055",
    "iso:country":"AT",
    "sg:address":"Lagerg 348",
    "sg:city":"Puntigam",
    "sg:classifiers":[
        {
            "category":"Home & Garden",
            "subcategory":"Building Materials",
            "type":"Retail Goods"
        }
    ],
    "sg:phone":"+43 4331 6242663",
    "sg:postcode":"8055",
    "sg:province":"Steiermark",
    "sg:tags":[
        "baustoffe",
        "-material",
        "u"
    ],
    "wof:name":"WeGo Systembaustoffe Austria GmbH",
    "wof:placetype":"venue"
},
  "geometry": {"coordinates":[15.4419784546,47.0390739441],"type":"Point"}
}