{
  "type": "Feature",
  "properties": {
    "addr:full":"Gr\u00fcnaug 23 Prellenkirchen Nieder\u00f6sterreich 2472",
    "addr:housenumber":"23",
    "addr:postcode":"2472",
    "addr:street":"Gruenaug",
    "iso:country":"AT",
    "sg:address":"Gr\u00fcnaug 23",
    "sg:city":"Prellenkirchen",
    "sg:orig_category":"Hunde- U Katzensalons",
    "sg:phone":"+43 4367 66035413",
    "sg:postcode":"2472",
    "sg:province":"Nieder\u00f6sterreich",
    "wof:name":"Saibl Andrea",
    "wof:placetype":"venue"
},
  "geometry": {"coordinates":[16.9520206451,48.0750274658],"type":"Point"}
}