{
  "type": "Feature",
  "properties": {
    "addr:full":"Wiener Str 11 Mattersburg Burgenland 7210",
    "addr:housenumber":"11",
    "addr:postcode":"7210",
    "iso:country":"AT",
    "sg:address":"Wiener Str 11",
    "sg:city":"Mattersburg",
    "sg:orig_category":"Fahrschulen",
    "sg:phone":"+43 2626 62596",
    "sg:postcode":"7210",
    "sg:province":"Burgenland",
    "sg:website":"www.fahrschule-gaal.at",
    "wof:name":"Fahrschule Gaal",
    "wof:placetype":"venue"
},
  "geometry": {"coordinates":[16.3953895569,47.738193512],"type":"Point"}
}