{
  "type": "Feature",
  "properties": {
    "addr:full":"Kircheng 44 Wien Wien 1070",
    "addr:housenumber":"44",
    "addr:postcode":"1070",
    "addr:street":"Kircheng",
    "iso:country":"AT",
    "sg:address":"Kircheng 44",
    "sg:city":"Wien",
    "sg:orig_category":"Vinotheken",
    "sg:phone":"+43 1 5235828",
    "sg:postcode":"1070",
    "sg:province":"Wien",
    "wof:name":"DER GALLIER - Keppler",
    "wof:placetype":"venue"
},
  "geometry": {"coordinates":[16.3518047333,48.2044754028],"type":"Point"}
}