{
  "type": "Feature",
  "properties": {
    "iso:country":"AT",
    "sg:address":"Einhornweg 1",
    "sg:city":"Mils",
    "sg:orig_category":"Werbeagenturen",
    "sg:phone":"+43 5223 46993",
    "sg:postcode":"6068",
    "sg:province":"Tirol",
    "wof:name":"rotschopf-werbegrafik und design E. Sagmeister",
    "wof:placetype":"venue"
},
  "geometry": {"coordinates":[-99.4334869385,42.926410675],"type":"Point"}
}