{
  "type": "Feature",
  "properties": {
    "addr:full":"Lessingg 1 Strasshof an der Nordbahn Nieder\u00f6sterreich 2231",
    "addr:housenumber":"1",
    "addr:postcode":"2231",
    "addr:street":"Lessingg",
    "iso:country":"AT",
    "sg:address":"Lessingg 1",
    "sg:city":"Strasshof an der Nordbahn",
    "sg:orig_category":"Steinmetzbetriebe",
    "sg:phone":"+43 4322 874470",
    "sg:postcode":"2231",
    "sg:province":"Nieder\u00f6sterreich",
    "wof:name":"Angelus Steinmetzmeister GmbH",
    "wof:placetype":"venue"
},
  "geometry": {"coordinates":[16.6356391907,48.3160018921],"type":"Point"}
}