{
  "type": "Feature",
  "properties": {
    "iso:country":"AT",
    "sg:address":"Teucht 19",
    "sg:city":"Peuerbach",
    "sg:orig_category":"Tischlereien",
    "sg:phone":"+43 7276 22670",
    "sg:postcode":"4722",
    "sg:province":"Ober\u00f6sterreich",
    "wof:name":"Eichlberger Leopold",
    "wof:placetype":"venue"
},
  "geometry": {"coordinates":[13.7597970963,48.3709030151],"type":"Point"}
}