{
  "type": "Feature",
  "properties": {
    "iso:country":"AT",
    "sg:address":"Lanersbach 441",
    "sg:city":"Tux",
    "sg:orig_category":"Pensionen / Privatzimmer",
    "sg:phone":"+43 5287 87248",
    "sg:postcode":"6293",
    "sg:province":"Tirol",
    "wof:name":"G\u00e4stehaus Dorfschmiede",
    "wof:placetype":"venue"
},
  "geometry": {"coordinates":[11.6970243454,47.1270294189],"type":"Point"}
}