{
  "type": "Feature",
  "properties": {
    "addr:full":"Bahnstr 40 Kirchberg am Wagram Nieder\u00f6sterreich 3470",
    "addr:housenumber":"40",
    "addr:postcode":"3470",
    "addr:street":"Bahnstr",
    "iso:country":"AT",
    "sg:address":"Bahnstr 40",
    "sg:city":"Kirchberg am Wagram",
    "sg:orig_category":"Non-Classified Establishments",
    "sg:phone":"+43 2279 23370",
    "sg:postcode":"3470",
    "sg:province":"Nieder\u00f6sterreich",
    "wof:name":"Stra\u00dfenmeisterei Kirchberg am Wagram",
    "wof:placetype":"venue"
},
  "geometry": {"coordinates":[15.8943061829,48.4285430908],"type":"Point"}
}