{
  "type": "Feature",
  "properties": {
    "addr:full":"Rosentaler Str 99H Klagenfurt K\u00e4rnten 9020",
    "addr:postcode":"9020",
    "addr:street":"Str 99H;Kaernten",
    "iso:country":"AT",
    "sg:address":"Rosentaler Str 99H",
    "sg:city":"Klagenfurt",
    "sg:orig_category":"Gastronomie- U Hoteleinrichtungen",
    "sg:phone":"+43 4346 3310720",
    "sg:postcode":"9020",
    "sg:province":"K\u00e4rnten",
    "wof:name":"GASTROMAX Gastronomiemaschinen",
    "wof:placetype":"venue"
},
  "geometry": {"coordinates":[14.3002729416,46.6096496582],"type":"Point"}
}