{
  "type": "Feature",
  "properties": {
    "iso:country":"AT",
    "sg:address":"Linzer Str 33-35",
    "sg:city":"Ottensheim",
    "sg:orig_category":"Holzhandel",
    "sg:phone":"+43 4372 34822590",
    "sg:postcode":"4100",
    "sg:province":"Ober\u00f6sterreich",
    "wof:name":"Wagner Ernst Holz u Handels GmbH",
    "wof:placetype":"venue"
},
  "geometry": {"coordinates":[14.1799039841,48.3338470459],"type":"Point"}
}