{
  "type": "Feature",
  "properties": {
    "iso:country":"AT",
    "sg:address":"Eichenweg 9",
    "sg:city":"Fu\u00dfach",
    "sg:orig_category":"Werbeagenturen",
    "sg:phone":"+43 5578 7940",
    "sg:postcode":"6972",
    "sg:province":"Vorarlberg",
    "wof:name":"B\u00f6ckle & Gmeiner Agentur f Werbung und Kommunikation GmbH",
    "wof:placetype":"venue"
},
  "geometry": {"coordinates":[-79.8480834961,39.8919715881],"type":"Point"}
}