{
  "type": "Feature",
  "properties": {
    "iso:country":"AT",
    "sg:address":"Nr 170",
    "sg:city":"Gerlos",
    "sg:orig_category":"Appartements / Ferienwohnungen",
    "sg:phone":"+43 4352 845252",
    "sg:postcode":"6281",
    "sg:province":"Tirol",
    "wof:name":"Haus Heimat",
    "wof:placetype":"venue"
},
  "geometry": {"coordinates":[12.0359144211,47.2256088257],"type":"Point"}
}