{
  "type": "Feature",
  "properties": {
    "addr:full":"Nr 93 Wei\u00dfbriach K\u00e4rnten 9622",
    "addr:postcode":"9622",
    "addr:street":"Nr;Weissbriach Kaernten",
    "iso:country":"AT",
    "sg:address":"Nr 93",
    "sg:city":"Wei\u00dfbriach",
    "sg:orig_category":"Friseure U Frisiersalons",
    "sg:phone":"+43 4342 862420",
    "sg:postcode":"9622",
    "sg:province":"K\u00e4rnten",
    "wof:name":"Fris\u00f6r Enzi",
    "wof:placetype":"venue"
},
  "geometry": {"coordinates":[9.6596899033,47.818321228],"type":"Point"}
}