{
  "type": "Feature",
  "properties": {
    "iso:country":"AT",
    "sg:address":"Ketzerg. 342-344 ",
    "sg:city":"Wien",
    "sg:classifiers":[
        {
            "category":"Food & Beverages",
            "subcategory":"Groceries & Convenience Stores",
            "type":"Retail Goods"
        }
    ],
    "sg:phone":"+43 4318 8044",
    "sg:postcode":"1230",
    "sg:province":"Wien",
    "sg:tags":[
        "product",
        "related"
    ],
    "wof:name":"J. & H. P\u00d6HL OHG",
    "wof:placetype":"venue"
},
  "geometry": {"coordinates":[16.2645359039,48.1338768005],"type":"Point"}
}