{
  "type": "Feature",
  "properties": {
    "addr:full":"St Leonharder Str 24 Waidhofen an der Ybbs Nieder\u00f6sterreich 3340",
    "addr:postcode":"3340",
    "addr:street":"St;Str 24",
    "iso:country":"AT",
    "sg:address":"St Leonharder Str 24",
    "sg:city":"Waidhofen an der Ybbs",
    "sg:orig_category":"Feuerwehren",
    "sg:phone":"+43 7442 7360",
    "sg:postcode":"3340",
    "sg:province":"Nieder\u00f6sterreich",
    "wof:name":"Freiwillige Feuerwehr St Leonhard/Wald",
    "wof:placetype":"venue"
},
  "geometry": {"coordinates":[14.7743349075,47.9616470337],"type":"Point"}
}