{
  "type": "Feature",
  "properties": {
    "addr:full":"Wiedner Hauptstrasse 52 Wien Wien 1040",
    "addr:housenumber":"52",
    "addr:postcode":"1040",
    "addr:street":"Wiedner Hauptstrasse",
    "iso:country":"AT",
    "sg:address":"Wiedner Hauptstrasse 52",
    "sg:city":"Wien",
    "sg:classifiers":[
        {
            "category":"Autos & Motor Vehicles",
            "subcategory":"Auto Supplies",
            "type":"Retail Goods"
        }
    ],
    "sg:phone":"+43 1 58786840",
    "sg:postcode":"1040",
    "sg:province":"Wien",
    "sg:tags":[
        "automobile",
        "accessory"
    ],
    "sg:website":"wiesenthal.at",
    "wof:name":"Wiesenthal & Co Bergstaller GmbH",
    "wof:placetype":"venue"
},
  "geometry": {"coordinates":[16.3664855957,48.1926269531],"type":"Point"}
}