{
  "type": "Feature",
  "properties": {
    "addr:full":"Wolferner Str 24 St. Florian Ober\u00f6sterreich 4490",
    "addr:housenumber":"24",
    "addr:postcode":"4490",
    "addr:street":"Str",
    "iso:country":"AT",
    "sg:address":"Wolferner Str 24",
    "sg:city":"St. Florian",
    "sg:orig_category":"Lebensmittel / Erzeugung U Gro\u00c3\u0178handel",
    "sg:phone":"+43 4372 244018",
    "sg:postcode":"4490",
    "sg:province":"Ober\u00f6sterreich",
    "wof:name":"Vinz Trade HandelsgesmbH",
    "wof:placetype":"venue"
},
  "geometry": {"coordinates":[14.3493080139,48.216003418],"type":"Point"}
}