{
  "type": "Feature",
  "properties": {
    "addr:full":"Rettenbacher Str 4B Mariatrost Steiermark 8044",
    "addr:postcode":"8044",
    "addr:street":"Str 4B",
    "iso:country":"AT",
    "sg:address":"Rettenbacher Str 4B",
    "sg:city":"Mariatrost",
    "sg:orig_category":"Tennisschulen",
    "sg:phone":"+43 316 392555",
    "sg:postcode":"8044",
    "sg:province":"Steiermark",
    "wof:name":"Tennisschule Pramberger OEG",
    "wof:placetype":"venue"
},
  "geometry": {"coordinates":[15.4900388718,47.1405334473],"type":"Point"}
}