{
  "type": "Feature",
  "properties": {
    "iso:country":"AT",
    "sg:address":"Schiffamtsgasse 11",
    "sg:city":"Wien",
    "sg:classifiers":[
        {
            "category":"Manufacturing",
            "subcategory":"Furniture",
            "type":"Manufacturing & Wholesale Goods"
        }
    ],
    "sg:phone":"+43 1 2144889",
    "sg:postcode":"1020",
    "sg:province":"Wien",
    "sg:tags":[
        "bedroom"
    ],
    "wof:name":"Hoffellner Ges.m.b.H.",
    "wof:placetype":"venue"
},
  "geometry": {"coordinates":[16.3748950958,48.2191085815],"type":"Point"}
}