{
  "type": "Feature",
  "properties": {
    "addr:full":"Oberlaaer Str 78 Wien Wien 1100",
    "addr:postcode":"1100",
    "addr:street":"Str 78",
    "iso:country":"AT",
    "sg:address":"Oberlaaer Str 78",
    "sg:city":"Wien",
    "sg:orig_category":"Esoterik",
    "sg:phone":"+43 1 689756612",
    "sg:postcode":"1100",
    "sg:province":"Wien",
    "wof:name":"SOLARIS Spirituelle Edition",
    "wof:placetype":"venue"
},
  "geometry": {"coordinates":[16.397354126,48.1382713318],"type":"Point"}
}