{
  "type": "Feature",
  "properties": {
    "addr:full":"Mariahilfer Strasse 124 Wien Wien 1070",
    "addr:housenumber":"124",
    "addr:postcode":"1070",
    "addr:street":"Mariahilfer Strasse",
    "iso:country":"AT",
    "sg:address":"Mariahilfer Strasse 124",
    "sg:city":"Wien",
    "sg:classifiers":[
        {
            "category":"Banks & Credit Unions",
            "subcategory":"Investment Brokerage",
            "type":"Services"
        }
    ],
    "sg:phone":"+43 1 525710",
    "sg:postcode":"1070",
    "sg:province":"Wien",
    "sg:tags":[
        "case",
        "spectacle"
    ],
    "sg:website":"pearle.at",
    "wof:name":"Pearle \u00d6sterreich GmbH",
    "wof:placetype":"venue"
},
  "geometry": {"coordinates":[16.3411388397,48.1962966919],"type":"Point"}
}