{
  "type": "Feature",
  "properties": {
    "addr:full":"Maxglaner Hauptstr 14 Salzburg Salzburg 5020",
    "addr:housenumber":"14",
    "addr:postcode":"5020",
    "addr:street":"Maxglaner Hauptstr;Salzburg",
    "iso:country":"AT",
    "sg:address":"Maxglaner Hauptstr 14",
    "sg:city":"Salzburg",
    "sg:orig_category":"Fleischhauereien",
    "sg:phone":"+43 662 827825",
    "sg:postcode":"5020",
    "sg:province":"Salzburg",
    "wof:name":"Wimmer Roman Fleischhauerei GesmbH & Co KG",
    "wof:placetype":"venue"
},
  "geometry": {"coordinates":[13.0238771439,47.796421051],"type":"Point"}
}