{
  "type": "Feature",
  "properties": {
    "addr:full":"Niederbahn 3e Dornbirn Vorarlberg 6850",
    "addr:housenumber":"3e",
    "addr:postcode":"6850",
    "addr:street":"Niederbahn",
    "iso:country":"AT",
    "sg:address":"Niederbahn 3e",
    "sg:city":"Dornbirn",
    "sg:classifiers":[
        {
            "category":"Professional",
            "subcategory":"Computer Services",
            "type":"Services"
        }
    ],
    "sg:phone":"+43 664 5356459",
    "sg:postcode":"6850",
    "sg:province":"Vorarlberg",
    "sg:tags":[
        "software"
    ],
    "wof:name":"QSoft - Software-Entwicklung",
    "wof:placetype":"venue"
},
  "geometry": {"coordinates":[9.7271203995,47.3978118896],"type":"Point"}
}