{
  "type": "Feature",
  "properties": {
    "iso:country":"AT",
    "sg:address":"Leharg 9-11",
    "sg:city":"Wien",
    "sg:orig_category":"Werbeagenturen",
    "sg:phone":"+43 1 588460",
    "sg:postcode":"1060",
    "sg:province":"Wien",
    "wof:name":"Demner, Merlicek & Bergmann WerbegesmbH",
    "wof:placetype":"venue"
},
  "geometry": {"coordinates":[16.362953186,48.1996803284],"type":"Point"}
}