{
  "type": "Feature",
  "properties": {
    "addr:full":"Nr 17 Kasten Nieder\u00f6sterreich 3072",
    "addr:postcode":"3072",
    "addr:street":"Nr;Kasten Niederoesterreich",
    "iso:country":"AT",
    "sg:address":"Nr 17",
    "sg:city":"Kasten",
    "sg:orig_category":"Volksschulen",
    "sg:phone":"+43 2744 7533",
    "sg:postcode":"3072",
    "sg:province":"Nieder\u00f6sterreich",
    "wof:name":"Volksschule",
    "wof:placetype":"venue"
},
  "geometry": {"coordinates":[166.9221496582,-0.5282999873],"type":"Point"}
}