{
  "type": "Feature",
  "properties": {
    "addr:full":"Industriegeb. Medraz 12 Fulpmes Tirol 6166",
    "addr:housenumber":"12",
    "addr:postcode":"6166",
    "addr:street":"Medraz;Tirol",
    "iso:country":"AT",
    "sg:address":"Industriegeb. Medraz 12",
    "sg:city":"Fulpmes",
    "sg:classifiers":[
        {
            "category":"Professional",
            "subcategory":"Engineering",
            "type":"Services"
        }
    ],
    "sg:phone":"+43 4352 2562166",
    "sg:postcode":"6166",
    "sg:province":"Tirol",
    "sg:tags":[
        "machine",
        "-",
        "mechanical"
    ],
    "wof:name":"SCHWEIGER FULPMES GMBH",
    "wof:placetype":"venue"
},
  "geometry": {"coordinates":[11.3390579224,47.13539505],"type":"Point"}
}