{
  "type": "Feature",
  "properties": {
    "addr:full":"Nikolaus-Gassner-Str 321 Kaprun Salzburg 5710",
    "addr:housenumber":"321",
    "addr:postcode":"5710",
    "addr:street":"Kaprun Salzburg",
    "iso:country":"AT",
    "sg:address":"Nikolaus-Gassner-Str 321",
    "sg:city":"Kaprun",
    "sg:orig_category":"Tourismusunternehmen",
    "sg:phone":"+43 6547 200192320",
    "sg:postcode":"5710",
    "sg:province":"Salzburg",
    "wof:name":"Tauern Touristik GmbH",
    "wof:placetype":"venue"
},
  "geometry": {"coordinates":[12.7501354218,47.2671508789],"type":"Point"}
}