{
  "type": "Feature",
  "properties": {
    "addr:full":"Hochstadl 190 Kaindorf Steiermark 8224",
    "addr:housenumber":"190",
    "addr:postcode":"8224",
    "iso:country":"AT",
    "sg:address":"Hochstadl 190",
    "sg:city":"Kaindorf",
    "sg:orig_category":"Lebensmittelmaschinen",
    "sg:phone":"+43 4333 3427830",
    "sg:postcode":"8224",
    "sg:province":"Steiermark",
    "wof:name":"Karner B\u00e4ckereitechnik GmbH & Co KG",
    "wof:placetype":"venue"
},
  "geometry": {"coordinates":[15.9089851379,47.2246704102],"type":"Point"}
}