{
  "type": "Feature",
  "properties": {
    "iso:country":"AT",
    "sg:address":"Bahnstr 9",
    "sg:city":"Langenlois",
    "sg:orig_category":"Umwelttechnik",
    "sg:phone":"+43 2734 2442",
    "sg:postcode":"3550",
    "sg:province":"Nieder\u00f6sterreich",
    "wof:name":"Wolf GmbH",
    "wof:placetype":"venue"
},
  "geometry": {"coordinates":[15.678609848,48.473903656],"type":"Point"}
}