{
  "type": "Feature",
  "properties": {
    "addr:full":"Sonnleitenstr 3 Eugendorf Salzburg 5301",
    "addr:housenumber":"3",
    "addr:postcode":"5301",
    "addr:street":"Sonnleitenstr;Salzburg",
    "iso:country":"AT",
    "sg:address":"Sonnleitenstr 3",
    "sg:city":"Eugendorf",
    "sg:orig_category":"Pensionen / Privatzimmer",
    "sg:phone":"+43 6221 7713",
    "sg:postcode":"5301",
    "sg:province":"Salzburg",
    "wof:name":"Pension Schwaighofen",
    "wof:placetype":"venue"
},
  "geometry": {"coordinates":[13.1381559372,47.8313522339],"type":"Point"}
}