{
  "type": "Feature",
  "properties": {
    "addr:full":"Angererweg 47 Tulfes Tirol 6075",
    "addr:housenumber":"47",
    "addr:postcode":"6075",
    "addr:street":"Angererweg;Tirol",
    "iso:country":"AT",
    "sg:address":"Angererweg 47",
    "sg:city":"Tulfes",
    "sg:orig_category":"Raumgestaltung",
    "sg:phone":"+43 5223 78757",
    "sg:postcode":"6075",
    "sg:province":"Tirol",
    "wof:name":"K\u00f6ssler Alois",
    "wof:placetype":"venue"
},
  "geometry": {"coordinates":[11.5357542038,47.2585258484],"type":"Point"}
}