{
  "type": "Feature",
  "properties": {
    "iso:country":"AT",
    "sg:address":"Eckenried 9",
    "sg:city":"Innsbruck",
    "sg:orig_category":"Pensionen / Privatzimmer",
    "sg:phone":"+43 512 267319",
    "sg:postcode":"6020",
    "sg:province":"Tirol",
    "wof:name":"Pension Eckenried",
    "wof:placetype":"venue"
},
  "geometry": {"coordinates":[11.4057121277,47.2835502625],"type":"Point"}
}