{
  "type": "Feature",
  "properties": {
    "addr:full":"Laudachtal 13 Gschwandt Ober\u00f6sterreich 4816",
    "addr:housenumber":"13",
    "addr:postcode":"4816",
    "addr:street":"Laudachtal",
    "iso:country":"AT",
    "sg:address":"Laudachtal 13",
    "sg:city":"Gschwandt",
    "sg:classifiers":[
        {
            "category":"Manufacturing",
            "subcategory":"Wood Products",
            "type":"Manufacturing & Wholesale Goods"
        }
    ],
    "sg:phone":"+43 761263697",
    "sg:postcode":"4816",
    "sg:province":"Ober\u00f6sterreich",
    "sg:tags":[
        "lumber"
    ],
    "wof:name":"Karl Riedler",
    "wof:placetype":"venue"
},
  "geometry": {"coordinates":[13.8697462082,47.9225502014],"type":"Point"}
}