{
  "type": "Feature",
  "properties": {
    "addr:full":"Weisselg 8 Wien Wien 1210",
    "addr:housenumber":"8",
    "addr:postcode":"1210",
    "addr:street":"Weisselg",
    "iso:country":"AT",
    "sg:address":"Weisselg 8",
    "sg:city":"Wien",
    "sg:orig_category":"Zeitungen U Zeitschriften",
    "sg:phone":"+43 1 27886100",
    "sg:postcode":"1210",
    "sg:province":"Wien",
    "wof:name":"Pressezentrum Floridsdorf VerlagsgesmbH & Co KG",
    "wof:placetype":"venue"
},
  "geometry": {"coordinates":[16.3991603851,48.2607650757],"type":"Point"}
}