{
  "type": "Feature",
  "properties": {
    "iso:country":"AT",
    "sg:address":"Villacher Str 28c",
    "sg:city":"Spittal an der Drau",
    "sg:orig_category":"Reifen U Reifendienste",
    "sg:phone":"+43 4347 6222360",
    "sg:postcode":"9800",
    "sg:province":"K\u00e4rnten",
    "wof:name":"HP-Reifendienst GmbH",
    "wof:placetype":"venue"
},
  "geometry": {"coordinates":[13.5045747757,46.7934265137],"type":"Point"}
}