{
  "type": "Feature",
  "properties": {
    "addr:full":"Bismarckstr 12 F\u00fcrstenfeld Steiermark 8280",
    "addr:housenumber":"12",
    "addr:postcode":"8280",
    "addr:street":"Bismarckstr",
    "iso:country":"AT",
    "sg:address":"Bismarckstr 12",
    "sg:city":"F\u00fcrstenfeld",
    "sg:orig_category":"Politische Parteien",
    "sg:phone":"+43 4333 82523410",
    "sg:postcode":"8280",
    "sg:province":"Steiermark",
    "wof:name":"SP\u00f6 Bezirksorganisation F\u00fcrstenfeld",
    "wof:placetype":"venue"
},
  "geometry": {"coordinates":[16.0767974854,47.0502052307],"type":"Point"}
}