{
  "type": "Feature",
  "properties": {
    "iso:country":"AT",
    "sg:address":"Nr 79",
    "sg:city":"Eggenburg",
    "sg:classifiers":[
        {
            "category":"Communications",
            "subcategory":"Film & Video Production",
            "type":"Services"
        }
    ],
    "sg:phone":"+43 2984 23149",
    "sg:postcode":"3730",
    "sg:province":"Nieder\u00f6sterreich",
    "sg:tags":[
        "multimedia"
    ],
    "wof:name":"mediaDesign Podolsky & Partner OEG",
    "wof:placetype":"venue"
},
  "geometry": {"coordinates":[15.8164758682,48.64320755],"type":"Point"}
}