{
  "type": "Feature",
  "properties": {
    "addr:full":"Florian Gr\u00f6ger-Str 7 Klagenfurt K\u00e4rnten 9020",
    "addr:housenumber":"7",
    "addr:postcode":"9020",
    "addr:street":"Kaernten",
    "iso:country":"AT",
    "sg:address":"Florian Gr\u00f6ger-Str 7",
    "sg:city":"Klagenfurt",
    "sg:orig_category":"Anlagenbau U -Technik",
    "sg:phone":"+43 463 500600",
    "sg:postcode":"9020",
    "sg:province":"K\u00e4rnten",
    "wof:name":"PGA Putz-Granitzer Anlagenbau GesmbH",
    "wof:placetype":"venue"
},
  "geometry": {"coordinates":[14.3071517944,46.6162605286],"type":"Point"}
}