{
  "type": "Feature",
  "properties": {
    "addr:full":"Vinzenzg 14 Wien Wien 1180",
    "addr:housenumber":"14",
    "addr:postcode":"1180",
    "addr:street":"Vinzenzg",
    "iso:country":"AT",
    "sg:address":"Vinzenzg 14",
    "sg:city":"Wien",
    "sg:orig_category":"Architekten",
    "sg:phone":"+43 1 4021322",
    "sg:postcode":"1180",
    "sg:province":"Wien",
    "wof:name":"Strauss Gert Dipl-Ing",
    "wof:placetype":"venue"
},
  "geometry": {"coordinates":[16.3355102539,48.2260360718],"type":"Point"}
}