{
  "type": "Feature",
  "properties": {
    "addr:full":"Strau\u00dfg 11 Leoben Steiermark 8700",
    "addr:housenumber":"11",
    "addr:postcode":"8700",
    "addr:street":"Straussg",
    "iso:country":"AT",
    "sg:address":"Strau\u00dfg 11",
    "sg:city":"Leoben",
    "sg:orig_category":"Fotografen",
    "sg:phone":"+43 4338 4243116",
    "sg:postcode":"8700",
    "sg:province":"Steiermark",
    "wof:name":"Foto Freisinger KG",
    "wof:placetype":"venue"
},
  "geometry": {"coordinates":[15.0931959152,47.3800048828],"type":"Point"}
}