{
  "type": "Feature",
  "properties": {
    "iso:country":"AT",
    "sg:address":"Marktpl 5",
    "sg:city":"Br\u00fcckl",
    "sg:orig_category":"Textilwaren / Einzelhandel",
    "sg:phone":"+43 4214 5107",
    "sg:postcode":"9371",
    "sg:province":"K\u00e4rnten",
    "wof:name":"TPS",
    "wof:placetype":"venue"
},
  "geometry": {"coordinates":[14.5315961838,46.7484893799],"type":"Point"}
}