{
  "type": "Feature",
  "properties": {
    "addr:full":"Bazulstr 76 Nenzing Vorarlberg 6710",
    "addr:housenumber":"76",
    "addr:postcode":"6710",
    "addr:street":"Bazulstr",
    "iso:country":"AT",
    "sg:address":"Bazulstr 76",
    "sg:city":"Nenzing",
    "sg:orig_category":"Werbeagenturen",
    "sg:phone":"+43 5525 64712",
    "sg:postcode":"6710",
    "sg:province":"Vorarlberg",
    "wof:name":"Riener ITS",
    "wof:placetype":"venue"
},
  "geometry": {"coordinates":[9.6971750259,47.181968689],"type":"Point"}
}