{
  "type": "Feature",
  "properties": {
    "iso:country":"AT",
    "sg:address":"Wachtbergstr 80",
    "sg:city":"Weyregg am Attersee",
    "sg:orig_category":"Bergbahnen",
    "sg:phone":"+43 76642635",
    "sg:postcode":"4852",
    "sg:province":"Ober\u00f6sterreich",
    "wof:name":"Wachtberglifte Weyregg Schiverein Wachtberg",
    "wof:placetype":"venue"
},
  "geometry": {"coordinates":[13.5787305832,47.8968429565],"type":"Point"}
}