{
  "type": "Feature",
  "properties": {
    "addr:full":"Schillerstr 16 Gleisdorf Steiermark 8200",
    "addr:housenumber":"16",
    "addr:postcode":"8200",
    "addr:street":"Schillerstr",
    "iso:country":"AT",
    "sg:address":"Schillerstr 16",
    "sg:city":"Gleisdorf",
    "sg:orig_category":"Videotheken",
    "sg:phone":"+43 4331 125424",
    "sg:postcode":"8200",
    "sg:province":"Steiermark",
    "wof:name":"Conny-Shop - H\u00fcbler Elisabeth",
    "wof:placetype":"venue"
},
  "geometry": {"coordinates":[15.7087192535,47.1032562256],"type":"Point"}
}