{
  "type": "Feature",
  "properties": {
    "iso:country":"AT",
    "sg:address":"Landstr 1",
    "sg:city":"Lochau",
    "sg:orig_category":"Lebensmittel / Erzeugung U Gro\u00c3\u0178handel",
    "sg:phone":"+43 4355 74422050",
    "sg:postcode":"6911",
    "sg:province":"Vorarlberg",
    "wof:name":"Breganzia Konserven GmbH & Co KG",
    "wof:placetype":"venue"
},
  "geometry": {"coordinates":[9.7517232895,47.5308685303],"type":"Point"}
}