{
  "type": "Feature",
  "properties": {
    "addr:full":"Industriegel\u00e4nde, Zone A12 Fulpmes Tirol 6166",
    "addr:postcode":"6166",
    "addr:street":"A12;Tirol",
    "iso:country":"AT",
    "sg:address":"Industriegel\u00e4nde, Zone A12",
    "sg:city":"Fulpmes",
    "sg:orig_category":"Fodder Steamers",
    "sg:phone":"+43 5225 62166",
    "sg:postcode":"6166",
    "sg:province":"Tirol",
    "wof:name":"Ing. Schweiger Fulpmes Ges.m.b.H.",
    "wof:placetype":"venue"
},
  "geometry": {"coordinates":[11.3487129211,47.1532936096],"type":"Point"}
}