{
  "type": "Feature",
  "properties": {
    "addr:full":"K\u00f6nigstetter Str 144 Tulln an der Donau Nieder\u00f6sterreich 3430",
    "addr:housenumber":"144",
    "addr:postcode":"3430",
    "addr:street":"Str",
    "iso:country":"AT",
    "sg:address":"K\u00f6nigstetter Str 144",
    "sg:city":"Tulln an der Donau",
    "sg:orig_category":"Autohandel",
    "sg:phone":"+43 2272 61930",
    "sg:postcode":"3430",
    "sg:province":"Nieder\u00f6sterreich",
    "wof:name":"Autohaus Gr\u00fchbaum GmbH",
    "wof:placetype":"venue"
},
  "geometry": {"coordinates":[16.0838279724,48.3189163208],"type":"Point"}
}