{
  "type": "Feature",
  "properties": {
    "addr:full":"Gerbergasse 35 Villach K\u00e4rnten 9500",
    "addr:housenumber":"35",
    "addr:postcode":"9500",
    "addr:street":"Gerbergasse;Kaernten",
    "iso:country":"AT",
    "sg:address":"Gerbergasse 35",
    "sg:city":"Villach",
    "sg:classifiers":[
        {
            "category":"Manufacturing",
            "subcategory":"Wood Products",
            "type":"Manufacturing & Wholesale Goods"
        }
    ],
    "sg:phone":"+43 4242 242260",
    "sg:postcode":"9500",
    "sg:province":"K\u00e4rnten",
    "sg:tags":[
        "chair",
        "lift"
    ],
    "wof:name":"de Pretis Ges.m.b.H.",
    "wof:placetype":"venue"
},
  "geometry": {"coordinates":[13.8496961594,46.6123161316],"type":"Point"}
}