{
  "type": "Feature",
  "properties": {
    "addr:full":"Nettingsdorfer Str 34 Haid Ober\u00f6sterreich 4053",
    "addr:housenumber":"34",
    "addr:postcode":"4053",
    "addr:street":"Str",
    "iso:country":"AT",
    "sg:address":"Nettingsdorfer Str 34",
    "sg:city":"Haid",
    "sg:orig_category":"Wasserbetten",
    "sg:phone":"+43 7229 81180",
    "sg:postcode":"4053",
    "sg:province":"Ober\u00f6sterreich",
    "wof:name":"Jakob Wasserbetten",
    "wof:placetype":"venue"
},
  "geometry": {"coordinates":[14.2510099411,48.2047348022],"type":"Point"}
}