{
  "type": "Feature",
  "properties": {
    "addr:full":"Stelzhamerstr 8 Gallspach Ober\u00f6sterreich 4713",
    "addr:housenumber":"8",
    "addr:postcode":"4713",
    "addr:street":"Stelzhamerstr",
    "iso:country":"AT",
    "sg:address":"Stelzhamerstr 8",
    "sg:city":"Gallspach",
    "sg:orig_category":"Volksschulen",
    "sg:phone":"+43 4372 4861949",
    "sg:postcode":"4713",
    "sg:province":"Ober\u00f6sterreich",
    "wof:name":"Volksschule",
    "wof:placetype":"venue"
},
  "geometry": {"coordinates":[13.8085098267,48.2088050842],"type":"Point"}
}