{
  "type": "Feature",
  "properties": {
    "addr:full":"Wimmerg 13/21 Wien Wien 1050",
    "addr:housenumber":"13 / 21",
    "addr:postcode":"1050",
    "addr:street":"Wimmerg",
    "iso:country":"AT",
    "sg:address":"Wimmerg 13/21",
    "sg:city":"Wien",
    "sg:orig_category":"Werbeagenturen",
    "sg:phone":"+43 4367 63831667",
    "sg:postcode":"1050",
    "sg:province":"Wien",
    "wof:name":"Hafner Clemens",
    "wof:placetype":"venue"
},
  "geometry": {"coordinates":[16.3586044312,48.1848487854],"type":"Point"}
}