{
  "type": "Feature",
  "properties": {
    "addr:full":"Anger 232 Lech Vorarlberg 6764",
    "addr:housenumber":"232",
    "addr:postcode":"6764",
    "addr:street":"Anger",
    "iso:country":"AT",
    "sg:address":"Anger 232",
    "sg:city":"Lech",
    "sg:orig_category":"Appartements / Ferienwohnungen",
    "sg:phone":"+43 5583 2365",
    "sg:postcode":"6764",
    "sg:province":"Vorarlberg",
    "wof:name":"Appartementhaus Amrei",
    "wof:placetype":"venue"
},
  "geometry": {"coordinates":[10.1481189728,47.2123756409],"type":"Point"}
}