{
  "type": "Feature",
  "properties": {
    "addr:full":"Mairbachweg 10 Hatting Tirol 6402",
    "addr:housenumber":"10",
    "addr:postcode":"6402",
    "addr:street":"Mairbachweg;Tirol",
    "iso:country":"AT",
    "sg:address":"Mairbachweg 10",
    "sg:city":"Hatting",
    "sg:orig_category":"Stickereien",
    "sg:phone":"+43 4352 3886328",
    "sg:postcode":"6402",
    "sg:province":"Tirol",
    "wof:name":"Springer Elke",
    "wof:placetype":"venue"
},
  "geometry": {"coordinates":[11.1646604538,47.2767372131],"type":"Point"}
}