{
  "type": "Feature",
  "properties": {
    "addr:full":"Vogelweider Str 50 Wels Ober\u00f6sterreich 4600",
    "addr:housenumber":"50",
    "addr:postcode":"4600",
    "addr:street":"Str;Oberoesterreich",
    "iso:country":"AT",
    "sg:address":"Vogelweider Str 50",
    "sg:city":"Wels",
    "sg:classifiers":[
        {
            "category":"Manufacturing",
            "subcategory":"Rubber & Plastics",
            "type":"Manufacturing & Wholesale Goods"
        }
    ],
    "sg:phone":"+43 4372 42413",
    "sg:postcode":"4600",
    "sg:province":"Ober\u00f6sterreich",
    "wof:name":"TEUFELBERGER GMBH",
    "wof:placetype":"venue"
},
  "geometry": {"coordinates":[14.0077142715,48.1651878357],"type":"Point"}
}