{
  "type": "Feature",
  "properties": {
    "addr:full":"Fockyg 51/5A Wien Wien 1120",
    "addr:housenumber":"51 / 5a",
    "addr:postcode":"1120",
    "addr:street":"Fockyg",
    "iso:country":"AT",
    "sg:address":"Fockyg 51/5A",
    "sg:city":"Wien",
    "sg:orig_category":"Elektroinstallationsunternehmen",
    "sg:phone":"+43 1 8128449",
    "sg:postcode":"1120",
    "sg:province":"Wien",
    "wof:name":"Dettloff Andreas",
    "wof:placetype":"venue"
},
  "geometry": {"coordinates":[16.3435783386,48.1800384521],"type":"Point"}
}