{
  "type": "Feature",
  "properties": {
    "iso:country":"AT",
    "sg:address":"Bozener Pl 1",
    "sg:city":"Lienz",
    "sg:orig_category":"Bankomat-Standorte",
    "sg:phone":"+43 4348 5266880",
    "sg:postcode":"9900",
    "sg:province":"Tirol",
    "wof:name":"Bankomat d PSK 9900 Lienz Osttirol",
    "wof:placetype":"venue"
},
  "geometry": {"coordinates":[12.7701654434,46.8289527893],"type":"Point"}
}