{
  "type": "Feature",
  "properties": {
    "addr:full":"Wallpachg 4 Hall in Tirol Tirol 6060",
    "addr:housenumber":"4",
    "addr:postcode":"6060",
    "addr:street":"Wallpachg;Tirol",
    "iso:country":"AT",
    "sg:address":"Wallpachg 4",
    "sg:city":"Hall in Tirol",
    "sg:orig_category":"Optiker",
    "sg:phone":"+43 4352 2356788",
    "sg:postcode":"6060",
    "sg:province":"Tirol",
    "wof:name":"Miller Optik GesmbH",
    "wof:placetype":"venue"
},
  "geometry": {"coordinates":[11.5078468323,47.282283783],"type":"Point"}
}