{
  "type": "Feature",
  "properties": {
    "addr:full":"Nr 72 Unterkohlst\u00e4tten Burgenland 7435",
    "addr:postcode":"7435",
    "addr:street":"Nr 72 Unterkohlstaetten",
    "iso:country":"AT",
    "sg:address":"Nr 72",
    "sg:city":"Unterkohlst\u00e4tten",
    "sg:orig_category":"Feuerwehren",
    "sg:phone":"+43 3354 20055",
    "sg:postcode":"7435",
    "sg:province":"Burgenland",
    "wof:name":"Feuerwehr G\u00fcnseck",
    "wof:placetype":"venue"
},
  "geometry": {"coordinates":[166.9221496582,-0.5282999873],"type":"Point"}
}