{
  "type": "Feature",
  "properties": {
    "iso:country":"AT",
    "sg:address":"Hauptstr 58",
    "sg:city":"Bad Deutsch Altenburg",
    "sg:classifiers":[
        {
            "category":"Farming",
            "subcategory":"Livestock Farm",
            "type":"Manufacturing & Wholesale Goods"
        }
    ],
    "sg:phone":"+43 2165 62925",
    "sg:postcode":"2405",
    "sg:province":"Nieder\u00f6sterreich",
    "sg:tags":[
        "-handel",
        "viehzucht",
        "u"
    ],
    "wof:name":"Kammlander Rudolf",
    "wof:placetype":"venue"
},
  "geometry": {"coordinates":[16.9441585541,48.119884491],"type":"Point"}
}