{
  "type": "Feature",
  "properties": {
    "addr:full":"Rettenbergerg 1 Wattens Tirol 6112",
    "addr:housenumber":"1",
    "addr:postcode":"6112",
    "addr:street":"Rettenbergerg;Tirol",
    "iso:country":"AT",
    "sg:address":"Rettenbergerg 1",
    "sg:city":"Wattens",
    "sg:orig_category":"Textilwaren / Einzelhandel",
    "sg:phone":"+43 5224 56555",
    "sg:postcode":"6112",
    "sg:province":"Tirol",
    "wof:name":"Paulina Moden",
    "wof:placetype":"venue"
},
  "geometry": {"coordinates":[11.5925893784,47.2907905579],"type":"Point"}
}