{
  "type": "Feature",
  "properties": {
    "iso:country":"AT",
    "sg:address":"Leonhardspl 4",
    "sg:city":"Feldkirch",
    "sg:orig_category":"Freizeit- U Sportbekleidung",
    "sg:phone":"+43 5522 74340",
    "sg:postcode":"6800",
    "sg:province":"Vorarlberg",
    "wof:name":"HERVIS Sport- und ModegesmbH",
    "wof:placetype":"venue"
},
  "geometry": {"coordinates":[9.5969562531,47.2355308533],"type":"Point"}
}