{
  "type": "Feature",
  "properties": {
    "addr:full":"Nr 82 Dorfstetten Nieder\u00f6sterreich 4392",
    "addr:postcode":"4392",
    "addr:street":"Nr 82",
    "iso:country":"AT",
    "sg:address":"Nr 82",
    "sg:city":"Dorfstetten",
    "sg:orig_category":"Gemeinden",
    "sg:phone":"+43 7260 8255",
    "sg:postcode":"4392",
    "sg:province":"Nieder\u00f6sterreich",
    "wof:name":"Gemeindeamt Dorfstetten",
    "wof:placetype":"venue"
},
  "geometry": {"coordinates":[14.9821662903,48.32629776],"type":"Point"}
}