{
  "type": "Feature",
  "properties": {
    "iso:country":"AT",
    "sg:address":"Mandlg 24",
    "sg:city":"Wien",
    "sg:orig_category":"Lottokollekturen",
    "sg:phone":"+43 1 8134360",
    "sg:postcode":"1120",
    "sg:province":"Wien",
    "wof:name":"Fischer Renate",
    "wof:placetype":"venue"
},
  "geometry": {"coordinates":[16.3290939331,48.1824874878],"type":"Point"}
}