{
  "type": "Feature",
  "properties": {
    "iso:country":"AT",
    "sg:address":"Jahnstr 5",
    "sg:city":"Spittal an der Drau",
    "sg:orig_category":"Bildungsservice / Allgemeine Informationsstellen",
    "sg:phone":"+43 4762 351200",
    "sg:postcode":"9800",
    "sg:province":"K\u00e4rnten",
    "wof:name":"Berufsinformationszentrum Spittal/Drau",
    "wof:placetype":"venue"
},
  "geometry": {"coordinates":[13.4967288971,46.7969284058],"type":"Point"}
}