{
  "type": "Feature",
  "properties": {
    "iso:country":"AT",
    "sg:address":"Faberstr 8",
    "sg:city":"Seekirchen am Wallersee",
    "sg:orig_category":"Feng-Shui, Tischlereien",
    "sg:phone":"+43 6212 2253",
    "sg:postcode":"5201",
    "sg:province":"Salzburg",
    "sg:website":"www.salzburg-online.at/simmerstatter/index.htm",
    "wof:name":"Simmerstatter Tischlerei",
    "wof:placetype":"venue"
},
  "geometry": {"coordinates":[13.1246042252,47.8954963684],"type":"Point"}
}