{
  "type": "Feature",
  "properties": {
    "addr:full":"Klagenfurter Str 6 Eberstein K\u00e4rnten 9372",
    "addr:housenumber":"6",
    "addr:postcode":"9372",
    "addr:street":"Str;Kaernten",
    "iso:country":"AT",
    "sg:address":"Klagenfurter Str 6",
    "sg:city":"Eberstein",
    "sg:orig_category":"Autoreparatur",
    "sg:phone":"+43 4264 31410",
    "sg:postcode":"9372",
    "sg:province":"K\u00e4rnten",
    "wof:name":"Pliemitscher Auto GesmbH",
    "wof:placetype":"venue"
},
  "geometry": {"coordinates":[14.5572032928,46.8041419983],"type":"Point"}
}