{
  "type": "Feature",
  "properties": {
    "iso:country":"AT",
    "sg:address":"Aschauerweg 140",
    "sg:city":"Going am Wilden Kaiser",
    "sg:orig_category":"Pensionen / Privatzimmer",
    "sg:phone":"+43 4353 582315",
    "sg:postcode":"6353",
    "sg:province":"Tirol",
    "wof:name":"H\u00f6ck-Hechenberger Haus B\u00e4rfeld",
    "wof:placetype":"venue"
},
  "geometry": {"coordinates":[12.3452701569,47.519821167],"type":"Point"}
}