{
  "type": "Feature",
  "properties": {
    "addr:full":"Hainprechting 32 Schwanenstadt Ober\u00f6sterreich 4690",
    "addr:housenumber":"32",
    "addr:postcode":"4690",
    "addr:street":"Hainprechting",
    "iso:country":"AT",
    "sg:address":"Hainprechting 32",
    "sg:city":"Schwanenstadt",
    "sg:classifiers":[
        {
            "category":"Home & Garden",
            "subcategory":"Building Materials",
            "type":"Retail Goods"
        }
    ],
    "sg:phone":"+43 76732544",
    "sg:postcode":"4690",
    "sg:province":"Ober\u00f6sterreich",
    "sg:tags":[
        "baustoffe",
        "-material",
        "u"
    ],
    "wof:name":"Himmelreicher Ernst - Baustahlarmierungen",
    "wof:placetype":"venue"
},
  "geometry": {"coordinates":[13.7680673599,48.0458335876],"type":"Point"}
}