{
  "type": "Feature",
  "properties": {
    "addr:full":"Fabrikg 2 Ober-Grafendorf Nieder\u00f6sterreich 3200",
    "addr:housenumber":"2",
    "addr:postcode":"3200",
    "addr:street":"Fabrikg",
    "iso:country":"AT",
    "sg:address":"Fabrikg 2",
    "sg:city":"Ober-Grafendorf",
    "sg:orig_category":"Tabaktrafiken",
    "sg:phone":"+43 4327 472383",
    "sg:postcode":"3200",
    "sg:province":"Nieder\u00f6sterreich",
    "wof:name":"Steindl Rita u Franz",
    "wof:placetype":"venue"
},
  "geometry": {"coordinates":[15.5444049835,48.1507606506],"type":"Point"}
}