{
  "type": "Feature",
  "properties": {
    "addr:full":"Gramartstr 122 Innsbruck Tirol 6020",
    "addr:housenumber":"122",
    "addr:postcode":"6020",
    "addr:street":"Tirol",
    "iso:country":"AT",
    "sg:address":"Gramartstr 122",
    "sg:city":"Innsbruck",
    "sg:orig_category":"Baumeister",
    "sg:phone":"+43 512 282557",
    "sg:postcode":"6020",
    "sg:province":"Tirol",
    "wof:name":"Eller Gottfried",
    "wof:placetype":"venue"
},
  "geometry": {"coordinates":[11.3799037933,47.2813720703],"type":"Point"}
}