{
  "type": "Feature",
  "properties": {
    "addr:full":"Wagnerstr 45 Hinterbr\u00fchl Nieder\u00f6sterreich 2371",
    "addr:housenumber":"45",
    "addr:postcode":"2371",
    "addr:street":"Wagnerstr;Niederoesterreich",
    "iso:country":"AT",
    "sg:address":"Wagnerstr 45",
    "sg:city":"Hinterbr\u00fchl",
    "sg:orig_category":"Handelsagenturen",
    "sg:phone":"+43 2236 48515",
    "sg:postcode":"2371",
    "sg:province":"Nieder\u00f6sterreich",
    "wof:name":"Predex HandelsgesmbH",
    "wof:placetype":"venue"
},
  "geometry": {"coordinates":[16.2645244598,48.0889778137],"type":"Point"}
}