{
  "type": "Feature",
  "properties": {
    "addr:full":"Hohenstaufeng 9 Wien Wien 1010",
    "addr:housenumber":"9",
    "addr:postcode":"1010",
    "addr:street":"Hohenstaufeng",
    "iso:country":"AT",
    "sg:address":"Hohenstaufeng 9",
    "sg:city":"Wien",
    "sg:orig_category":"Institute",
    "sg:phone":"+43 1 427737401",
    "sg:postcode":"1010",
    "sg:province":"Wien",
    "wof:name":"Institut f Wirtschaftwissenschaften d Universit\u00e4t Wien",
    "wof:placetype":"venue"
},
  "geometry": {"coordinates":[16.3657169342,48.2138061523],"type":"Point"}
}