{
  "type": "Feature",
  "properties": {
    "iso:country":"AT",
    "sg:address":"Zieglerg 1/31",
    "sg:city":"Wien",
    "sg:classifiers":[
        {
            "category":"Wholesale",
            "subcategory":"Stationery",
            "type":"Manufacturing & Wholesale Goods"
        }
    ],
    "sg:phone":"+43 1 5952772",
    "sg:postcode":"1070",
    "sg:province":"Wien",
    "sg:tags":[
        "sport-",
        "u",
        "sponsoring-agenturen"
    ],
    "wof:name":"MPM Sponsoring Consulting GesmbH",
    "wof:placetype":"venue"
},
  "geometry": {"coordinates":[16.3456172943,48.1973266602],"type":"Point"}
}