{
  "type": "Feature",
  "properties": {
    "addr:full":"Albrechtgasse 1 Graz Steiermark 8010",
    "addr:housenumber":"1",
    "addr:postcode":"8010",
    "addr:street":"Albrechtgasse",
    "iso:country":"AT",
    "sg:address":"Albrechtgasse 1",
    "sg:city":"Graz",
    "sg:classifiers":[
        {
            "category":"Professional",
            "type":"Services"
        }
    ],
    "sg:phone":"+43 316 80490",
    "sg:postcode":"8010",
    "sg:province":"Steiermark",
    "sg:tags":[
        "catering"
    ],
    "sg:website":"grazercongress.co.at",
    "wof:name":"Grazer Congress Ges.m.b.H.",
    "wof:placetype":"venue"
},
  "geometry": {"coordinates":[15.437702179,47.0701332092],"type":"Point"}
}