{
  "type": "Feature",
  "properties": {
    "addr:full":"Mondweg 14 Haid Ober\u00f6sterreich 4053",
    "addr:housenumber":"14",
    "addr:postcode":"4053",
    "addr:street":"Mondweg",
    "iso:country":"AT",
    "sg:address":"Mondweg 14",
    "sg:city":"Haid",
    "sg:orig_category":"Weine / Gro\u00c3\u0178handel",
    "sg:phone":"+43 676 5131959",
    "sg:postcode":"4053",
    "sg:province":"Ober\u00f6sterreich",
    "wof:name":"Weinspezialit\u00e4ten Lothar Friedrich",
    "wof:placetype":"venue"
},
  "geometry": {"coordinates":[14.2510099411,48.2047348022],"type":"Point"}
}