{
  "type": "Feature",
  "properties": {
    "addr:full":"Eltendorf 81 Eltendorf Burgenland 7562",
    "addr:housenumber":"81",
    "addr:postcode":"7562",
    "addr:street":"Eltendorf",
    "iso:country":"AT",
    "sg:address":"Eltendorf 81",
    "sg:city":"Eltendorf",
    "sg:classifiers":[
        {
            "category":"Building & Trades",
            "subcategory":"Landscaping Services",
            "type":"Services"
        }
    ],
    "sg:phone":"+43 3325 2226",
    "sg:postcode":"7562",
    "sg:province":"Burgenland",
    "sg:tags":[
        "dredging"
    ],
    "wof:name":"Holler Schotterwerke GmbH",
    "wof:placetype":"venue"
},
  "geometry": {"coordinates":[16.1961231232,47.0080184937],"type":"Point"}
}