{
  "type": "Feature",
  "properties": {
    "addr:full":"Karlauer Str 71 Graz Steiermark 8020",
    "addr:housenumber":"71",
    "addr:postcode":"8020",
    "addr:street":"Str",
    "iso:country":"AT",
    "sg:address":"Karlauer Str 71",
    "sg:city":"Graz",
    "sg:orig_category":"Abschleppdienste",
    "sg:phone":"+43 316 7123820",
    "sg:postcode":"8020",
    "sg:province":"Steiermark",
    "wof:name":"Pirnath & Co GesmbH - Abschleppzentrale",
    "wof:placetype":"venue"
},
  "geometry": {"coordinates":[15.4310388565,47.0595474243],"type":"Point"}
}