{
  "type": "Feature",
  "properties": {
    "addr:full":"Wiener Str 75 Kapfenberg Steiermark 8605",
    "addr:postcode":"8605",
    "addr:street":"75",
    "iso:country":"AT",
    "sg:address":"Wiener Str 75",
    "sg:city":"Kapfenberg",
    "sg:orig_category":"Lebensmittel / Einzelhandel",
    "sg:phone":"+43 4338 6227837",
    "sg:postcode":"8605",
    "sg:province":"Steiermark",
    "wof:name":"Billa AG",
    "wof:placetype":"venue"
},
  "geometry": {"coordinates":[15.299115181,47.445930481],"type":"Point"}
}