{
  "type": "Feature",
  "properties": {
    "addr:full":"Znaimer Str 33-35 Hollabrunn Nieder\u00f6sterreich 2020",
    "addr:postcode":"33-35;2020",
    "addr:street":"Str;Niederoesterreich",
    "iso:country":"AT",
    "sg:address":"Znaimer Str 33-35",
    "sg:city":"Hollabrunn",
    "sg:orig_category":"Installationsunternehmen",
    "sg:phone":"+43 2952 21360",
    "sg:postcode":"2020",
    "sg:province":"Nieder\u00f6sterreich",
    "wof:name":"Recher Karl Roman",
    "wof:placetype":"venue"
},
  "geometry": {"coordinates":[16.0766620636,48.568195343],"type":"Point"}
}