{
  "type": "Feature",
  "properties": {
    "addr:full":"Au\u00dferweg 152 Matrei am Brenner Tirol 6143",
    "addr:housenumber":"152",
    "addr:postcode":"6143",
    "addr:street":"Ausserweg;Am Brenner",
    "iso:country":"AT",
    "sg:address":"Au\u00dferweg 152",
    "sg:city":"Matrei am Brenner",
    "sg:classifiers":[
        {
            "category":"Home & Garden",
            "subcategory":"Hardware",
            "type":"Retail Goods"
        }
    ],
    "sg:phone":"+43 5273 7336",
    "sg:postcode":"6143",
    "sg:province":"Tirol",
    "sg:tags":[
        "agricultural",
        "implement"
    ],
    "wof:name":"Leopold Jenewein",
    "wof:placetype":"venue"
},
  "geometry": {"coordinates":[11.4604654312,47.1421813965],"type":"Point"}
}