{
  "type": "Feature",
  "properties": {
    "addr:full":"Valierg 15 Innsbruck Tirol 6020",
    "addr:housenumber":"15",
    "addr:postcode":"6020",
    "addr:street":"Valierg;Tirol",
    "iso:country":"AT",
    "sg:address":"Valierg 15",
    "sg:city":"Innsbruck",
    "sg:orig_category":"Molkereien U Molkereiprodukte",
    "sg:phone":"+43 512 3210",
    "sg:postcode":"6020",
    "sg:province":"Tirol",
    "wof:name":"Tirol Milch regGenmbH",
    "wof:placetype":"venue"
},
  "geometry": {"coordinates":[11.4315757751,47.2682685852],"type":"Point"}
}