{
  "type": "Feature",
  "properties": {
    "iso:country":"AT",
    "sg:address":"Westbahnstr 60",
    "sg:city":"Mauer-\u00d6hling",
    "sg:orig_category":"Filmproduktionen",
    "sg:phone":"+43 4374 7553698",
    "sg:postcode":"3362",
    "sg:province":"Nieder\u00f6sterreich",
    "wof:name":"Langer Bruno - Filmproduktionen und Handel",
    "wof:placetype":"venue"
},
  "geometry": {"coordinates":[14.8031997681,48.0966186523],"type":"Point"}
}