{
  "type": "Feature",
  "properties": {
    "iso:country":"AT",
    "sg:address":"Kendling 2",
    "sg:city":"Feldkirchen",
    "sg:orig_category":"Elektroinstallationsunternehmen",
    "sg:phone":"+43 7748 2571",
    "sg:postcode":"5143",
    "sg:province":"Ober\u00f6sterreich",
    "wof:name":"Wengler Franz",
    "wof:placetype":"venue"
},
  "geometry": {"coordinates":[13.0446195602,48.0679512024],"type":"Point"}
}