{
  "type": "Feature",
  "properties": {
    "iso:country":"AT",
    "sg:address":"Breitenfurter Str 383",
    "sg:city":"Wien",
    "sg:orig_category":"Friseure U Frisiersalons",
    "sg:phone":"+43 1 8695105",
    "sg:postcode":"1230",
    "sg:province":"Wien",
    "wof:name":"Top Hair Angela Inh Angela Knopfloch",
    "wof:placetype":"venue"
},
  "geometry": {"coordinates":[16.287569046,48.1375083923],"type":"Point"}
}