{
  "type": "Feature",
  "properties": {
    "iso:country":"AT",
    "sg:address":"F\u00fcrstenweg 9",
    "sg:city":"Anif",
    "sg:orig_category":"Architekturmodellbau",
    "sg:phone":"+43 6246 729600",
    "sg:postcode":"5081",
    "sg:province":"Salzburg",
    "wof:name":"Mitterhauser Axel",
    "wof:placetype":"venue"
},
  "geometry": {"coordinates":[13.0639257431,47.7499694824],"type":"Point"}
}