{
  "type": "Feature",
  "properties": {
    "addr:full":"Lorettostrasse 8a Hall in Tirol Tirol 6060",
    "addr:housenumber":"8a",
    "addr:postcode":"6060",
    "addr:street":"Lorettostrasse;Tirol",
    "iso:country":"AT",
    "sg:address":"Lorettostrasse 8a",
    "sg:city":"Hall in Tirol",
    "sg:classifiers":[
        {
            "category":"Home & Garden",
            "subcategory":"Building Materials",
            "type":"Retail Goods"
        }
    ],
    "sg:phone":"+43 5223 52701",
    "sg:postcode":"6060",
    "sg:province":"Tirol",
    "sg:tags":[
        "aluminium",
        "gutter"
    ],
    "wof:name":"J\u00fcrgen Hudej",
    "wof:placetype":"venue"
},
  "geometry": {"coordinates":[11.4819173813,47.2770004272],"type":"Point"}
}