{
  "type": "Feature",
  "properties": {
    "iso:country":"AT",
    "sg:address":"Quellenstr 16",
    "sg:city":"Bregenz",
    "sg:orig_category":"Werbeagenturen",
    "sg:phone":"+43 5574 46141",
    "sg:postcode":"6900",
    "sg:province":"Vorarlberg",
    "wof:name":"Unternehmen Werbung - Schneider & Partner GmbH",
    "wof:placetype":"venue"
},
  "geometry": {"coordinates":[9.7349319458,47.5014457703],"type":"Point"}
}