{
  "type": "Feature",
  "properties": {
    "addr:full":"Hauptstr 20 Aschbach Markt Nieder\u00f6sterreich 3361",
    "addr:housenumber":"20",
    "addr:postcode":"3361",
    "addr:street":"Hauptstr",
    "iso:country":"AT",
    "sg:address":"Hauptstr 20",
    "sg:city":"Aschbach Markt",
    "sg:orig_category":"Innenarchitekten",
    "sg:phone":"+43 7476 77378",
    "sg:postcode":"3361",
    "sg:province":"Nieder\u00f6sterreich",
    "wof:name":"Roszkopf Hubert Arch Mag",
    "wof:placetype":"venue"
},
  "geometry": {"coordinates":[14.7092866898,48.0622901917],"type":"Point"}
}