{
  "type": "Feature",
  "properties": {
    "iso:country":"AT",
    "sg:address":"Hauptpl 2",
    "sg:city":"Perg",
    "sg:orig_category":"Blumeneinzelhandel",
    "sg:phone":"+43 7262 572832",
    "sg:postcode":"4320",
    "sg:province":"Ober\u00f6sterreich",
    "wof:name":"Blumenecke Poldi",
    "wof:placetype":"venue"
},
  "geometry": {"coordinates":[14.633272171,48.2504882812],"type":"Point"}
}