{
  "type": "Feature",
  "properties": {
    "addr:full":"Albertsham Eberschwang Ober\u00f6sterreich 4906",
    "addr:postcode":"4906",
    "addr:street":"Oberoesterreich",
    "iso:country":"AT",
    "sg:address":"Albertsham",
    "sg:city":"Eberschwang",
    "sg:orig_category":"Bergbahnen",
    "sg:phone":"+43 7753 2727",
    "sg:postcode":"4906",
    "sg:province":"Ober\u00f6sterreich",
    "wof:name":"Schilift Eberschwanger GesmbH",
    "wof:placetype":"venue"
},
  "geometry": {"coordinates":[13.6017866135,48.1439437866],"type":"Point"}
}