{
  "type": "Feature",
  "properties": {
    "addr:full":"Salzachweg 17 Elsbethen-Glasenbach Salzburg 5061",
    "addr:housenumber":"17",
    "addr:postcode":"5061",
    "addr:street":"Salzachweg",
    "iso:country":"AT",
    "sg:address":"Salzachweg 17",
    "sg:city":"Elsbethen-Glasenbach",
    "sg:orig_category":"Maler, Anstreicher U Lackierer",
    "sg:phone":"+43 662 636020",
    "sg:postcode":"5061",
    "sg:province":"Salzburg",
    "wof:name":"Wilhelm K GesmbH & Co KG",
    "wof:placetype":"venue"
},
  "geometry": {"coordinates":[13.0756177902,47.7688674927],"type":"Point"}
}