{
  "type": "Feature",
  "properties": {
    "addr:full":"Otto Probst-Pl 2/4 Wien Wien 1100",
    "addr:housenumber":"2 / 4",
    "addr:postcode":"1100",
    "addr:street":"Probst-Pl",
    "iso:country":"AT",
    "sg:address":"Otto Probst-Pl 2/4",
    "sg:city":"Wien",
    "sg:orig_category":"Lebens- U Sozialberatung",
    "sg:phone":"+43 1 616044011",
    "sg:postcode":"1100",
    "sg:province":"Wien",
    "wof:name":"MAG ELF - Kinder- und Jugendpsychologische Beratungsstelle f\u00fcr den 10. Bezirk",
    "wof:placetype":"venue"
},
  "geometry": {"coordinates":[16.3492717743,48.1541404724],"type":"Point"}
}