{
  "type": "Feature",
  "properties": {
    "iso:country":"AT",
    "sg:address":"Stadtpl 19",
    "sg:city":"Eferding",
    "sg:orig_category":"Damenmoden",
    "sg:phone":"+43 4372 7222055",
    "sg:postcode":"4070",
    "sg:province":"Ober\u00f6sterreich",
    "wof:name":"Palmers Verkaufsstelle - Inh Eva Derndorfer",
    "wof:placetype":"venue"
},
  "geometry": {"coordinates":[14.0235080719,48.3085327148],"type":"Point"}
}