{
  "type": "Feature",
  "properties": {
    "addr:full":"Graben 28 Linz Ober\u00f6sterreich 4020",
    "addr:housenumber":"28",
    "addr:postcode":"4020",
    "addr:street":"Graben",
    "iso:country":"AT",
    "sg:address":"Graben 28",
    "sg:city":"Linz",
    "sg:orig_category":"Samen U Saatgut",
    "sg:phone":"+43 732 773220",
    "sg:postcode":"4020",
    "sg:province":"Ober\u00f6sterreich",
    "wof:name":"E. BRUCKSCHWEIGER KG",
    "wof:placetype":"venue"
},
  "geometry": {"coordinates":[14.2889308929,48.3049125671],"type":"Point"}
}