{
  "type": "Feature",
  "properties": {
    "addr:full":"Dorfstr 3 Fuschl am See Salzburg 5330",
    "addr:housenumber":"3",
    "addr:postcode":"5330",
    "addr:street":"Dorfstr",
    "iso:country":"AT",
    "sg:address":"Dorfstr 3",
    "sg:city":"Fuschl am See",
    "sg:orig_category":"Trachtenbekleidung",
    "sg:phone":"+43 6226 83340",
    "sg:postcode":"5330",
    "sg:province":"Salzburg",
    "wof:name":"Rupertihaus-Fashion Gastberger",
    "wof:placetype":"venue"
},
  "geometry": {"coordinates":[13.3015546799,47.79637146],"type":"Point"}
}