{
  "type": "Feature",
  "properties": {
    "addr:full":"Neustiftg 27 Wien Wien 1070",
    "addr:housenumber":"27",
    "addr:postcode":"1070",
    "addr:street":"Neustiftg",
    "iso:country":"AT",
    "sg:address":"Neustiftg 27",
    "sg:city":"Wien",
    "sg:orig_category":"Galerien",
    "sg:phone":"+43 1 5224878",
    "sg:postcode":"1070",
    "sg:province":"Wien",
    "wof:name":"Galerie St Ulrich",
    "wof:placetype":"venue"
},
  "geometry": {"coordinates":[16.3529586792,48.2052345276],"type":"Point"}
}