{
  "type": "Feature",
  "properties": {
    "addr:full":"Bahnstr 22 Matzen Nieder\u00f6sterreich 2243",
    "addr:housenumber":"22",
    "addr:postcode":"2243",
    "addr:street":"Bahnstr",
    "iso:country":"AT",
    "sg:address":"Bahnstr 22",
    "sg:city":"Matzen",
    "sg:orig_category":"Zimmereien",
    "sg:phone":"+43 2289 2239",
    "sg:postcode":"2243",
    "sg:province":"Nieder\u00f6sterreich",
    "wof:name":"Kumhofer Manfred",
    "wof:placetype":"venue"
},
  "geometry": {"coordinates":[16.7000808716,48.3978004456],"type":"Point"}
}