{
  "type": "Feature",
  "properties": {
    "addr:full":"Fichteng 8 Sollenau Nieder\u00f6sterreich 2601",
    "addr:housenumber":"8",
    "addr:postcode":"2601",
    "addr:street":"Fichteng",
    "iso:country":"AT",
    "sg:address":"Fichteng 8",
    "sg:city":"Sollenau",
    "sg:orig_category":"Spenglereien",
    "sg:phone":"+43 4326 2862578",
    "sg:postcode":"2601",
    "sg:province":"Nieder\u00f6sterreich",
    "wof:name":"Morais Richard",
    "wof:placetype":"venue"
},
  "geometry": {"coordinates":[16.2494049072,47.8965682983],"type":"Point"}
}