{
  "type": "Feature",
  "properties": {
    "addr:full":"Buschg 4 Wei\u00dfkirchen an der Traun Ober\u00f6sterreich 4616",
    "addr:housenumber":"4",
    "addr:postcode":"4616",
    "addr:street":"Buschg",
    "iso:country":"AT",
    "sg:address":"Buschg 4",
    "sg:city":"Wei\u00dfkirchen an der Traun",
    "sg:orig_category":"Baumschulen",
    "sg:phone":"+43 7243 56120",
    "sg:postcode":"4616",
    "sg:province":"Ober\u00f6sterreich",
    "wof:name":"Brillinger Helmut",
    "wof:placetype":"venue"
},
  "geometry": {"coordinates":[14.1128911972,48.1659088135],"type":"Point"}
}