{
  "type": "Feature",
  "properties": {
    "addr:full":"Gewerbepark 56 Feistritz an der Drau K\u00e4rnten 9710",
    "addr:housenumber":"56",
    "addr:postcode":"9710",
    "addr:street":"Gewerbepark",
    "iso:country":"AT",
    "sg:address":"Gewerbepark 56",
    "sg:city":"Feistritz an der Drau",
    "sg:orig_category":"Industrieanlagenbau U -Planung",
    "sg:phone":"+43 4342 4542070",
    "sg:postcode":"9710",
    "sg:province":"K\u00e4rnten",
    "wof:name":"Piplan Industrieanlagen Planungs- u Montage GesmbH",
    "wof:placetype":"venue"
},
  "geometry": {"coordinates":[13.66314888,46.7018623352],"type":"Point"}
}