{
  "type": "Feature",
  "properties": {
    "iso:country":"AT",
    "sg:address":"Moosweg 1",
    "sg:city":"Lermoos",
    "sg:orig_category":"Appartements / Ferienwohnungen",
    "sg:phone":"+43 5673 2826",
    "sg:postcode":"6631",
    "sg:province":"Tirol",
    "wof:name":"Ferienhaus Enzian",
    "wof:placetype":"venue"
},
  "geometry": {"coordinates":[10.8878116608,47.4006195068],"type":"Point"}
}