{
  "type": "Feature",
  "properties": {
    "addr:full":"Windbachg 13 Bad Fischau Nieder\u00f6sterreich 2721",
    "addr:housenumber":"13",
    "addr:postcode":"2721",
    "addr:street":"Windbachg",
    "iso:country":"AT",
    "sg:address":"Windbachg 13",
    "sg:city":"Bad Fischau",
    "sg:orig_category":"Abbruchunternehmen",
    "sg:phone":"+43 4326 392293",
    "sg:postcode":"2721",
    "sg:province":"Nieder\u00f6sterreich",
    "sg:website":"leeb-trans.at",
    "wof:name":"Leeb Rudolf GmbH",
    "wof:placetype":"venue"
},
  "geometry": {"coordinates":[16.1673069,47.8290863037],"type":"Point"}
}