{
  "type": "Feature",
  "properties": {
    "addr:full":"Defreggerstr 37 Innsbruck Tirol 6020",
    "addr:housenumber":"37",
    "addr:postcode":"6020",
    "addr:street":"Defreggerstr;Tirol",
    "iso:country":"AT",
    "sg:address":"Defreggerstr 37",
    "sg:city":"Innsbruck",
    "sg:orig_category":"Dekorationen",
    "sg:phone":"+43 512 562768",
    "sg:postcode":"6020",
    "sg:province":"Tirol",
    "wof:name":"Deco Design Franz Heumader",
    "wof:placetype":"venue"
},
  "geometry": {"coordinates":[11.4118347168,47.2658805847],"type":"Point"}
}