{
  "type": "Feature",
  "properties": {
    "addr:full":"Marktstr 48 Dornbirn Vorarlberg 6850",
    "addr:housenumber":"48",
    "addr:postcode":"6850",
    "addr:street":"Marktstr",
    "iso:country":"AT",
    "sg:address":"Marktstr 48",
    "sg:city":"Dornbirn",
    "sg:orig_category":"Fotoausarbeitungen",
    "sg:phone":"+43 5572 334480",
    "sg:postcode":"6850",
    "sg:province":"Vorarlberg",
    "wof:name":"Kodak GmbH",
    "wof:placetype":"venue"
},
  "geometry": {"coordinates":[9.7417831421,47.4084281921],"type":"Point"}
}