{
  "type": "Feature",
  "properties": {
    "addr:full":"Znaimer Str 7 Retz Nieder\u00f6sterreich 2070",
    "addr:housenumber":"7",
    "addr:postcode":"2070",
    "addr:street":"Str",
    "iso:country":"AT",
    "sg:address":"Znaimer Str 7",
    "sg:city":"Retz",
    "sg:orig_category":"Politische Parteien",
    "sg:phone":"+43 2942 2250",
    "sg:postcode":"2070",
    "sg:province":"Nieder\u00f6sterreich",
    "wof:name":"\u00f6sterreichische Volkspartei (\u00f6VP)",
    "wof:placetype":"venue"
},
  "geometry": {"coordinates":[15.9515581131,48.758140564],"type":"Point"}
}