{
  "type": "Feature",
  "properties": {
    "iso:country":"AT",
    "sg:address":"Baien 116",
    "sg:city":"Bezau",
    "sg:orig_category":"Zimmereien",
    "sg:phone":"+43 4355 142209",
    "sg:postcode":"6870",
    "sg:province":"Vorarlberg",
    "wof:name":"Kaufmann Michael",
    "wof:placetype":"venue"
},
  "geometry": {"coordinates":[9.8884248734,47.3781547546],"type":"Point"}
}