{
  "type": "Feature",
  "properties": {
    "addr:full":"Nr 312 Markt Allhau Burgenland 7411",
    "addr:postcode":"7411",
    "addr:street":"Nr",
    "iso:country":"AT",
    "sg:address":"Nr 312",
    "sg:city":"Markt Allhau",
    "sg:orig_category":"Behinderungen / Leben Mit Behinderungen",
    "sg:phone":"+43 4333 567864",
    "sg:postcode":"7411",
    "sg:province":"Burgenland",
    "wof:name":"Verein Bungis-Malko f Behinderte u Nichtbehinderte gemeinsam im S\u00fcdburgenland",
    "wof:placetype":"venue"
},
  "geometry": {"coordinates":[16.0806007385,47.2934417725],"type":"Point"}
}