{
  "type": "Feature",
  "properties": {
    "addr:full":"Wredepl 2 Mondsee Ober\u00f6sterreich 5310",
    "addr:housenumber":"2",
    "addr:postcode":"5310",
    "addr:street":"Wredepl;Oberoesterreich",
    "iso:country":"AT",
    "sg:address":"Wredepl 2",
    "sg:city":"Mondsee",
    "sg:orig_category":"Gemeinden",
    "sg:phone":"+43 6232 22650",
    "sg:postcode":"5310",
    "sg:province":"Ober\u00f6sterreich",
    "wof:name":"Gemeinde St Lorenz",
    "wof:placetype":"venue"
},
  "geometry": {"coordinates":[13.3504571915,47.8555679321],"type":"Point"}
}