{
  "type": "Feature",
  "properties": {
    "addr:full":"Siebensterng 33 Wien Wien 1070",
    "addr:housenumber":"33",
    "addr:postcode":"1070",
    "addr:street":"Siebensterng",
    "iso:country":"AT",
    "sg:address":"Siebensterng 33",
    "sg:city":"Wien",
    "sg:orig_category":"Beschriftungen",
    "sg:phone":"+43 4315 235655",
    "sg:postcode":"1070",
    "sg:province":"Wien",
    "sg:website":"diewerkstatt.net",
    "wof:name":"Haslinger Stempel + Schilder - Michael Waismayer",
    "wof:placetype":"venue"
},
  "geometry": {"coordinates":[16.3510112762,48.2021408081],"type":"Point"}
}