{
  "type": "Feature",
  "properties": {
    "addr:full":"Gnas 66 Gnas Steiermark 8342",
    "addr:housenumber":"66",
    "addr:postcode":"8342",
    "addr:street":"Gnas",
    "iso:country":"AT",
    "sg:address":"Gnas 66",
    "sg:city":"Gnas",
    "sg:classifiers":[
        {
            "category":"Education",
            "subcategory":"Special Training",
            "type":"Public Place"
        }
    ],
    "sg:phone":"+43 3151 2217",
    "sg:postcode":"8342",
    "sg:province":"Steiermark",
    "sg:tags":[
        "bread"
    ],
    "wof:name":"Josef Stangl KG",
    "wof:placetype":"venue"
},
  "geometry": {"coordinates":[15.8259248734,46.8740234375],"type":"Point"}
}