{
  "type": "Feature",
  "properties": {
    "addr:full":"Donau-City-Str 11-13 Wien Wien 1220",
    "addr:postcode":"11-13;1220",
    "iso:country":"AT",
    "sg:address":"Donau-City-Str 11-13",
    "sg:city":"Wien",
    "sg:orig_category":"Immobilienverwaltungen",
    "sg:phone":"+43 1 2697372",
    "sg:postcode":"1220",
    "sg:province":"Wien",
    "wof:name":"PMSC Regional Franchise Services GmbH",
    "wof:placetype":"venue"
},
  "geometry": {"coordinates":[16.4112682343,48.2333602905],"type":"Point"}
}