{
  "type": "Feature",
  "properties": {
    "addr:full":"Untere Dorfstr 18 Serfaus Tirol 6534",
    "addr:housenumber":"18",
    "addr:postcode":"6534",
    "addr:street":"Untere Dorfstr;Tirol",
    "iso:country":"AT",
    "sg:address":"Untere Dorfstr 18",
    "sg:city":"Serfaus",
    "sg:classifiers":[
        {
            "category":"Travel",
            "subcategory":"Hotels & Motels",
            "type":"Entertainment"
        }
    ],
    "sg:phone":"+43 4354 766336",
    "sg:postcode":"6534",
    "sg:province":"Tirol",
    "wof:name":"Sportcafe Astoria",
    "wof:placetype":"venue"
},
  "geometry": {"coordinates":[10.6061258316,47.0379295349],"type":"Point"}
}