{
  "type": "Feature",
  "properties": {
    "addr:full":"Hauptpl 17 Waidhofen an der Thaya Nieder\u00f6sterreich 3830",
    "addr:housenumber":"17",
    "addr:postcode":"3830",
    "addr:street":"Hauptpl",
    "iso:country":"AT",
    "sg:address":"Hauptpl 17",
    "sg:city":"Waidhofen an der Thaya",
    "sg:orig_category":"Massagen",
    "sg:phone":"+43 4366 41647171",
    "sg:postcode":"3830",
    "sg:province":"Nieder\u00f6sterreich",
    "wof:name":"ENERGIETEMPEL Andrea Schremser",
    "wof:placetype":"venue"
},
  "geometry": {"coordinates":[15.2860021591,48.8149909973],"type":"Point"}
}