{
  "type": "Feature",
  "properties": {
    "addr:full":"K\u00e4rntner Str 3 Arnoldstein K\u00e4rnten 9601",
    "addr:housenumber":"3",
    "addr:postcode":"9601",
    "addr:street":"Str;Kaernten",
    "iso:country":"AT",
    "sg:address":"K\u00e4rntner Str 3",
    "sg:city":"Arnoldstein",
    "sg:orig_category":"Tankstellen",
    "sg:phone":"+43 4255 2550",
    "sg:postcode":"9601",
    "sg:province":"K\u00e4rnten",
    "wof:name":"Shell Austria GmbH",
    "wof:placetype":"venue"
},
  "geometry": {"coordinates":[13.701584816,46.5500564575],"type":"Point"}
}