{
  "type": "Feature",
  "properties": {
    "iso:country":"AT",
    "sg:address":"Mariatroster Str 31",
    "sg:city":"Kroisbach",
    "sg:orig_category":"Apotheken",
    "sg:phone":"+43 316 323047",
    "sg:postcode":"8043",
    "sg:province":"Steiermark",
    "sg:website":"lobe.at",
    "wof:name":"Apotheke Zu Mariatrost",
    "wof:placetype":"venue"
},
  "geometry": {"coordinates":[15.4600124359,47.0904808044],"type":"Point"}
}