{
  "type": "Feature",
  "properties": {
    "addr:full":"Nr 21 Gargellen Vorarlberg 6787",
    "addr:postcode":"6787",
    "addr:street":"Nr",
    "iso:country":"AT",
    "sg:address":"Nr 21",
    "sg:city":"Gargellen",
    "sg:orig_category":"Bars-Cafes",
    "sg:phone":"+43 5557 2421",
    "sg:postcode":"6787",
    "sg:province":"Vorarlberg",
    "wof:name":"Cafe-Bar Schirmeria",
    "wof:placetype":"venue"
},
  "geometry": {"coordinates":[9.9181804657,46.9698066711],"type":"Point"}
}