{
  "type": "Feature",
  "properties": {
    "addr:full":"Hauptstr 19/8/6 Hinterbr\u00fchl Nieder\u00f6sterreich 2371",
    "addr:housenumber":"19 / 8 / 6",
    "addr:postcode":"2371",
    "addr:street":"Hauptstr;Hinterbruehl Niederoesterreich",
    "iso:country":"AT",
    "sg:address":"Hauptstr 19/8/6",
    "sg:city":"Hinterbr\u00fchl",
    "sg:orig_category":"Ergotherapie",
    "sg:phone":"+43 2236 866029",
    "sg:postcode":"2371",
    "sg:province":"Nieder\u00f6sterreich",
    "wof:name":"Scharbert Christian",
    "wof:placetype":"venue"
},
  "geometry": {"coordinates":[16.2549362183,48.0872993469],"type":"Point"}
}