{
  "type": "Feature",
  "properties": {
    "addr:full":"Niederreitern 17 Engerwitzdorf Ober\u00f6sterreich 4209",
    "addr:housenumber":"17",
    "addr:postcode":"4209",
    "addr:street":"Niederreitern",
    "iso:country":"AT",
    "sg:address":"Niederreitern 17",
    "sg:city":"Engerwitzdorf",
    "sg:classifiers":[
        {
            "category":"Building & Trades",
            "subcategory":"Pest Control",
            "type":"Services"
        }
    ],
    "sg:phone":"+43 7235 631280",
    "sg:postcode":"4209",
    "sg:province":"Ober\u00f6sterreich",
    "sg:tags":[
        "battery",
        "construction",
        "machinery"
    ],
    "wof:name":"Johann Buchmayr",
    "wof:placetype":"venue"
},
  "geometry": {"coordinates":[14.4413757324,48.3437614441],"type":"Point"}
}