{
  "type": "Feature",
  "properties": {
    "addr:full":"Juchartstr 2 Hard Vorarlberg 6971",
    "addr:housenumber":"2",
    "addr:postcode":"6971",
    "addr:street":"Juchartstr",
    "iso:country":"AT",
    "sg:address":"Juchartstr 2",
    "sg:city":"Hard",
    "sg:orig_category":"Feinmechanik",
    "sg:phone":"+43 4355 7472571",
    "sg:postcode":"6971",
    "sg:province":"Vorarlberg",
    "wof:name":"Tuschka Friedrich KG",
    "wof:placetype":"venue"
},
  "geometry": {"coordinates":[9.7039031982,47.4901657104],"type":"Point"}
}