{
  "type": "Feature",
  "properties": {
    "addr:full":"Eduard-Bodem-G 9 Innsbruck Tirol 6020",
    "addr:housenumber":"9",
    "addr:postcode":"6020",
    "addr:street":"Eduard-Bodem-G;Tirol",
    "iso:country":"AT",
    "sg:address":"Eduard-Bodem-G 9",
    "sg:city":"Innsbruck",
    "sg:orig_category":"Eisenwaren",
    "sg:phone":"+43 512 336010",
    "sg:postcode":"6020",
    "sg:province":"Tirol",
    "wof:name":"Schachermayer Gro\u00dfhandelsgesmbH",
    "wof:placetype":"venue"
},
  "geometry": {"coordinates":[11.434419632,47.2663612366],"type":"Point"}
}