{
  "type": "Feature",
  "properties": {
    "addr:full":"M\u00fchlwangstr 20 Gmunden Ober\u00f6sterreich 4810",
    "addr:housenumber":"20",
    "addr:postcode":"4810",
    "addr:street":"Muehlwangstr;Oberoesterreich",
    "iso:country":"AT",
    "sg:address":"M\u00fchlwangstr 20",
    "sg:city":"Gmunden",
    "sg:orig_category":"Tankstellen",
    "sg:phone":"+43 761264320",
    "sg:postcode":"4810",
    "sg:province":"Ober\u00f6sterreich",
    "wof:name":"OMV AG",
    "wof:placetype":"venue"
},
  "geometry": {"coordinates":[13.7981462479,47.918598175],"type":"Point"}
}