{
  "type": "Feature",
  "properties": {
    "addr:full":"Bremschlstr 35 B\u00fcrs Vorarlberg 6706",
    "addr:housenumber":"35",
    "addr:postcode":"6706",
    "addr:street":"Bremschlstr",
    "iso:country":"AT",
    "sg:address":"Bremschlstr 35",
    "sg:city":"B\u00fcrs",
    "sg:orig_category":"Autohandel",
    "sg:phone":"+43 5552 64036",
    "sg:postcode":"6706",
    "sg:province":"Vorarlberg",
    "wof:name":"Ellensohn Manfred GesmbH",
    "wof:placetype":"venue"
},
  "geometry": {"coordinates":[9.8191871643,47.1478538513],"type":"Point"}
}