{
  "type": "Feature",
  "properties": {
    "addr:full":"Unterkramsach 83 Kramsach Tirol 6233",
    "addr:housenumber":"83",
    "addr:postcode":"6233",
    "addr:street":"Unterkramsach;Tirol",
    "iso:country":"AT",
    "sg:address":"Unterkramsach 83",
    "sg:city":"Kramsach",
    "sg:orig_category":"Tischlereien",
    "sg:phone":"+43 5337 93271",
    "sg:postcode":"6233",
    "sg:province":"Tirol",
    "wof:name":"Fahrmair Christian",
    "wof:placetype":"venue"
},
  "geometry": {"coordinates":[11.8889398575,47.4436988831],"type":"Point"}
}