{
  "type": "Feature",
  "properties": {
    "iso:country":"AT",
    "sg:address":"Stern\u00e4ckerweg 16",
    "sg:city":"Liebenau",
    "sg:orig_category":"Steuerberatung",
    "sg:phone":"+43 316 472030",
    "sg:postcode":"8041",
    "sg:province":"Steiermark",
    "wof:name":"Adlbauer & Adlbauer Wirtschaftstreuhandgesellschaft Steuerberatungsgesellschaft OEG",
    "wof:placetype":"venue"
},
  "geometry": {"coordinates":[15.4644603729,47.0393486023],"type":"Point"}
}