{
  "type": "Feature",
  "properties": {
    "addr:full":"Alserbachstr 37 Wien Wien 1090",
    "addr:housenumber":"37",
    "addr:postcode":"1090",
    "addr:street":"Alserbachstr",
    "iso:country":"AT",
    "sg:address":"Alserbachstr 37",
    "sg:city":"Wien",
    "sg:orig_category":"Lederwaren / Einzelhandel",
    "sg:phone":"+43 4313 176576",
    "sg:postcode":"1090",
    "sg:province":"Wien",
    "wof:name":"Lederwaren Zur Friedensbr\u00fccke",
    "wof:placetype":"venue"
},
  "geometry": {"coordinates":[16.3633441925,48.2265663147],"type":"Point"}
}