{
  "type": "Feature",
  "properties": {
    "addr:full":"Seepromenade 2-4 Seeboden K\u00e4rnten 9871",
    "addr:housenumber":"2-4",
    "addr:postcode":"9871",
    "addr:street":"Seepromenade;Kaernten",
    "iso:country":"AT",
    "sg:address":"Seepromenade 2-4",
    "sg:city":"Seeboden",
    "sg:classifiers":[
        {
            "category":"Travel",
            "subcategory":"Hotels & Motels",
            "type":"Entertainment"
        }
    ],
    "sg:phone":"+43 4762 81500",
    "sg:postcode":"9871",
    "sg:province":"K\u00e4rnten",
    "wof:name":"Strandhotel Koller",
    "wof:placetype":"venue"
},
  "geometry": {"coordinates":[13.5170173645,46.8148841858],"type":"Point"}
}