{
  "type": "Feature",
  "properties": {
    "addr:full":"Rudolf-Hans-Bartsch-G 9 Leibnitz Steiermark 8430",
    "addr:housenumber":"9",
    "addr:postcode":"8430",
    "addr:street":"Rudolf-Hans-Bartsch-G;Steiermark",
    "iso:country":"AT",
    "sg:address":"Rudolf-Hans-Bartsch-G 9",
    "sg:city":"Leibnitz",
    "sg:orig_category":"Fahrschulen",
    "sg:phone":"+43 4334 5282138",
    "sg:postcode":"8430",
    "sg:province":"Steiermark",
    "wof:name":"Fahrschule Mayer",
    "wof:placetype":"venue"
},
  "geometry": {"coordinates":[15.5352783203,46.7804870605],"type":"Point"}
}