{
  "type": "Feature",
  "properties": {
    "addr:full":"Hauptstr 29 Tullnerbach Nieder\u00f6sterreich 3013",
    "addr:housenumber":"29",
    "addr:postcode":"3013",
    "addr:street":"Hauptstr",
    "iso:country":"AT",
    "sg:address":"Hauptstr 29",
    "sg:city":"Tullnerbach",
    "sg:orig_category":"Hunde- U Katzensalons",
    "sg:phone":"+43 4365 05275389",
    "sg:postcode":"3013",
    "sg:province":"Nieder\u00f6sterreich",
    "wof:name":"Hundesalon Naomi Inh Birgit Taxb\u00f6ck",
    "wof:placetype":"venue"
},
  "geometry": {"coordinates":[16.095533371,48.1846351624],"type":"Point"}
}