{
  "type": "Feature",
  "properties": {
    "iso:country":"AT",
    "sg:address":"Oberfeldweg 18",
    "sg:city":"Oetz",
    "sg:orig_category":"Pensionen / Privatzimmer",
    "sg:phone":"+43 5252 6683",
    "sg:postcode":"6433",
    "sg:province":"Tirol",
    "wof:name":"G\u00e4stehaus Michael",
    "wof:placetype":"venue"
},
  "geometry": {"coordinates":[10.8994350433,47.202091217],"type":"Point"}
}