{
  "type": "Feature",
  "properties": {
    "iso:country":"AT",
    "sg:address":"Am Steinh\u00fcgel 46",
    "sg:city":"St. Oswald",
    "sg:classifiers":[
        {
            "category":"Taxi",
            "type":"Transportation"
        }
    ],
    "sg:phone":"+43 4379 457406",
    "sg:postcode":"4271",
    "sg:province":"Ober\u00f6sterreich",
    "sg:tags":[
        "personentransporte",
        "u"
    ],
    "wof:name":"Taxi-Mietwagen Inh Johannes Steininger",
    "wof:placetype":"venue"
},
  "geometry": {"coordinates":[14.5865678787,48.5007896423],"type":"Point"}
}