{
  "type": "Feature",
  "properties": {
    "addr:full":"Hauptstr 4 Kirchberg in Tirol Tirol 6365",
    "addr:housenumber":"4",
    "addr:postcode":"6365",
    "addr:street":"Hauptstr;Tirol",
    "iso:country":"AT",
    "sg:address":"Hauptstr 4",
    "sg:city":"Kirchberg in Tirol",
    "sg:orig_category":"Fotografen",
    "sg:phone":"+43 5357 2414",
    "sg:postcode":"6365",
    "sg:province":"Tirol",
    "wof:name":"Foto Lisbet vorm Foto Max",
    "wof:placetype":"venue"
},
  "geometry": {"coordinates":[12.3150405884,47.4478187561],"type":"Point"}
}