{
  "type": "Feature",
  "properties": {
    "addr:full":"Rohr 46 Feldbach Steiermark 8330",
    "addr:housenumber":"46",
    "addr:postcode":"8330",
    "addr:street":"Rohr",
    "iso:country":"AT",
    "sg:address":"Rohr 46",
    "sg:city":"Feldbach",
    "sg:classifiers":[
        {
            "category":"Food & Beverages",
            "subcategory":"Groceries & Convenience Stores",
            "type":"Retail Goods"
        }
    ],
    "sg:phone":"+43 3115 2315",
    "sg:postcode":"8330",
    "sg:province":"Steiermark",
    "sg:tags":[
        "product",
        "fat-free"
    ],
    "wof:name":"K\u00f6gler KG",
    "wof:placetype":"venue"
},
  "geometry": {"coordinates":[15.8557338715,46.9628982544],"type":"Point"}
}