{
  "type": "Feature",
  "properties": {
    "addr:full":"Nr 10 Rappottenstein Nieder\u00f6sterreich 3911",
    "addr:postcode":"3911",
    "addr:street":"Nr 10 Rappottenstein",
    "iso:country":"AT",
    "sg:address":"Nr 10",
    "sg:city":"Rappottenstein",
    "sg:orig_category":"Hauptschulen",
    "sg:phone":"+43 2828 8302",
    "sg:postcode":"3911",
    "sg:province":"Nieder\u00f6sterreich",
    "wof:name":"Hauptschule",
    "wof:placetype":"venue"
},
  "geometry": {"coordinates":[15.0787200928,48.521648407],"type":"Point"}
}