{
  "type": "Feature",
  "properties": {
    "iso:country":"AT",
    "sg:address":"Klopstockg 5",
    "sg:city":"Wien",
    "sg:orig_category":"Autohandel",
    "sg:phone":"+43 4314 860138",
    "sg:postcode":"1160",
    "sg:province":"Wien",
    "sg:website":"peugeot-decker.at",
    "wof:name":"Decker Hanns Autoreparatur u Handel GesmbH",
    "wof:placetype":"venue"
},
  "geometry": {"coordinates":[16.3222255707,48.2157936096],"type":"Point"}
}