{
  "type": "Feature",
  "properties": {
    "iso:country":"AT",
    "sg:address":"Rainerstr 16",
    "sg:city":"Salzburg",
    "sg:orig_category":"Tabaktrafiken",
    "sg:phone":"+43 662 885125",
    "sg:postcode":"5020",
    "sg:province":"Salzburg",
    "wof:name":"Pendelin Roman",
    "wof:placetype":"venue"
},
  "geometry": {"coordinates":[13.04164505,47.8092384338],"type":"Point"}
}