{
  "type": "Feature",
  "properties": {
    "iso:country":"AT",
    "sg:address":"Josef-Jessernigg-Str 19",
    "sg:city":"Stockerau",
    "sg:orig_category":"Logistik",
    "sg:phone":"+43 4322 6672020",
    "sg:postcode":"2000",
    "sg:province":"Nieder\u00f6sterreich",
    "wof:name":"NextPharma Logistics GmbH",
    "wof:placetype":"venue"
},
  "geometry": {"coordinates":[16.237701416,48.3875579834],"type":"Point"}
}