{
  "type": "Feature",
  "properties": {
    "addr:full":"Gaglhamer Weg 48 Bergheim Salzburg 5101",
    "addr:housenumber":"48",
    "addr:postcode":"5101",
    "addr:street":"Gaglhamer Weg;Salzburg",
    "iso:country":"AT",
    "sg:address":"Gaglhamer Weg 48",
    "sg:city":"Bergheim",
    "sg:orig_category":"Installationsunternehmen",
    "sg:phone":"+43 662 451504",
    "sg:postcode":"5101",
    "sg:province":"Salzburg",
    "wof:name":"Waser GmbH",
    "wof:placetype":"venue"
},
  "geometry": {"coordinates":[13.0477848053,47.8324012756],"type":"Point"}
}