{
  "type": "Feature",
  "properties": {
    "iso:country":"AT",
    "sg:address":"Liechtensteinklammstr 12",
    "sg:city":"St. Johann im Pongau",
    "sg:classifiers":[
        {
            "category":"Travel",
            "subcategory":"Hotels & Motels",
            "type":"Entertainment"
        }
    ],
    "sg:phone":"+43 4364 1242510",
    "sg:postcode":"5600",
    "sg:province":"Salzburg",
    "wof:name":"Hotel Lerch",
    "wof:placetype":"venue"
},
  "geometry": {"coordinates":[13.1985960007,47.3423728943],"type":"Point"}
}