{
  "type": "Feature",
  "properties": {
    "addr:full":"Dorf 3 Kaltenbach Tirol 6272",
    "addr:housenumber":"3",
    "addr:postcode":"6272",
    "addr:street":"Dorf",
    "iso:country":"AT",
    "sg:address":"Dorf 3",
    "sg:city":"Kaltenbach",
    "sg:orig_category":"Lebensmittel / Einzelhandel",
    "sg:phone":"+43 5283 2389",
    "sg:postcode":"6272",
    "sg:province":"Tirol",
    "wof:name":"Braunegger KG",
    "wof:placetype":"venue"
},
  "geometry": {"coordinates":[11.8869342804,47.2909164429],"type":"Point"}
}