{
  "type": "Feature",
  "properties": {
    "addr:full":"Lechtaler Str 17 Reutte Tirol 6600",
    "addr:postcode":"6600",
    "addr:street":"Str 17;Tirol",
    "iso:country":"AT",
    "sg:address":"Lechtaler Str 17",
    "sg:city":"Reutte",
    "sg:orig_category":"Lebensmittel / Einzelhandel",
    "sg:phone":"+43 5672 62215",
    "sg:postcode":"6600",
    "sg:province":"Tirol",
    "wof:name":"SPAR \u00f6sterreichische Warenhandels-AG",
    "wof:placetype":"venue"
},
  "geometry": {"coordinates":[10.7035427094,47.4825592041],"type":"Point"}
}