{
  "type": "Feature",
  "properties": {
    "addr:full":"Schottenfeldg 71 Wien Wien 1070",
    "addr:housenumber":"71",
    "addr:postcode":"1070",
    "addr:street":"Schottenfeldg",
    "iso:country":"AT",
    "sg:address":"Schottenfeldg 71",
    "sg:city":"Wien",
    "sg:orig_category":"Steuerberatung",
    "sg:phone":"+43 1 52669300",
    "sg:postcode":"1070",
    "sg:province":"Wien",
    "wof:name":"Maier Wolfgang F Mag",
    "wof:placetype":"venue"
},
  "geometry": {"coordinates":[16.3429203033,48.2040176392],"type":"Point"}
}