{
  "type": "Feature",
  "properties": {
    "addr:full":"R\u00f6merg 34 Wien Wien 1160",
    "addr:housenumber":"34",
    "addr:postcode":"1160",
    "addr:street":"Roemerg",
    "iso:country":"AT",
    "sg:address":"R\u00f6merg 34",
    "sg:city":"Wien",
    "sg:orig_category":"Steuerberatung",
    "sg:phone":"+43 1 48983830",
    "sg:postcode":"1160",
    "sg:province":"Wien",
    "wof:name":"Hausch Karl",
    "wof:placetype":"venue"
},
  "geometry": {"coordinates":[16.2961292267,48.214931488],"type":"Point"}
}