{
  "type": "Feature",
  "properties": {
    "iso:country":"AT",
    "sg:address":"Nr 11",
    "sg:city":"Warth",
    "sg:orig_category":"Lebensmittel / Einzelhandel",
    "sg:phone":"+43 2629 2367",
    "sg:postcode":"2831",
    "sg:province":"Nieder\u00f6sterreich",
    "wof:name":"Spar-Markt Koller Franz",
    "wof:placetype":"venue"
},
  "geometry": {"coordinates":[16.1355209351,47.6589164734],"type":"Point"}
}