{
  "type": "Feature",
  "properties": {
    "addr:full":"Wiener Str 52 St. Florian Ober\u00f6sterreich 4490",
    "addr:housenumber":"52",
    "addr:postcode":"4490",
    "addr:street":"St.;Oberoesterreich",
    "iso:country":"AT",
    "sg:address":"Wiener Str 52",
    "sg:city":"St. Florian",
    "sg:orig_category":"Tabaktrafiken",
    "sg:phone":"+43 7224 4610",
    "sg:postcode":"4490",
    "sg:province":"Ober\u00f6sterreich",
    "wof:name":"Perndl Gabriele",
    "wof:placetype":"venue"
},
  "geometry": {"coordinates":[14.3921613693,48.2091903687],"type":"Point"}
}