{
  "type": "Feature",
  "properties": {
    "iso:country":"AT",
    "sg:address":"Robert-Frey-Str 14/4",
    "sg:city":"Wattens",
    "sg:orig_category":"Stuckateure U Trockenausbauer",
    "sg:phone":"+43 4366 44209299",
    "sg:postcode":"6112",
    "sg:province":"Tirol",
    "wof:name":"Habernig Franz",
    "wof:placetype":"venue"
},
  "geometry": {"coordinates":[11.5846643448,47.2945518494],"type":"Point"}
}