{
  "type": "Feature",
  "properties": {
    "addr:full":"Sonnenfeld 16 Niklasdorf Steiermark 8712",
    "addr:housenumber":"16",
    "addr:postcode":"8712",
    "addr:street":"Sonnenfeld",
    "iso:country":"AT",
    "sg:address":"Sonnenfeld 16",
    "sg:city":"Niklasdorf",
    "sg:orig_category":"Anlagenbau U -Technik",
    "sg:phone":"+43 4338 4282756",
    "sg:postcode":"8712",
    "sg:province":"Steiermark",
    "wof:name":"EBE Maschinenhandel u Anlagenbau GesmbH",
    "wof:placetype":"venue"
},
  "geometry": {"coordinates":[15.1409435272,47.3992004395],"type":"Point"}
}