{
  "type": "Feature",
  "properties": {
    "addr:full":"Zelfenstr 51 Tschagguns Vorarlberg 6774",
    "addr:housenumber":"51",
    "addr:postcode":"6774",
    "addr:street":"Zelfenstr",
    "iso:country":"AT",
    "sg:address":"Zelfenstr 51",
    "sg:city":"Tschagguns",
    "sg:orig_category":"Pensionen / Privatzimmer",
    "sg:phone":"+43 5556 73325",
    "sg:postcode":"6774",
    "sg:province":"Vorarlberg",
    "wof:name":"Haus Margret",
    "wof:placetype":"venue"
},
  "geometry": {"coordinates":[9.9089756012,47.0725097656],"type":"Point"}
}