{
  "type": "Feature",
  "properties": {
    "addr:full":"Kreischberg Talstation St. Georgen ob Murau Steiermark 8861",
    "addr:postcode":"8861",
    "addr:street":"Georgen",
    "iso:country":"AT",
    "sg:address":"Kreischberg Talstation",
    "sg:city":"St. Georgen ob Murau",
    "sg:classifiers":[
        {
            "category":"Park",
            "subcategory":"Provincial",
            "type":"Public Place"
        }
    ],
    "sg:phone":"+43 4335 37316",
    "sg:postcode":"8861",
    "sg:province":"Steiermark",
    "sg:tags":[
        "u",
        "ski-",
        "snowboardschulen"
    ],
    "wof:name":"Snowboardschule Suli",
    "wof:placetype":"venue"
},
  "geometry": {"coordinates":[14.0415802002,47.0663909912],"type":"Point"}
}