{
  "type": "Feature",
  "properties": {
    "addr:full":"Nr 426 Aflenz Kurort Steiermark 8623",
    "addr:postcode":"8623",
    "addr:street":"Nr 426",
    "iso:country":"AT",
    "sg:address":"Nr 426",
    "sg:city":"Aflenz Kurort",
    "sg:orig_category":"Banken U Sparkassen",
    "sg:phone":"+43 4338 6124440",
    "sg:postcode":"8623",
    "sg:province":"Steiermark",
    "wof:name":"Bankomat d Raiffeisenbank Turnau-Aflenz-Etmi\u00dfl",
    "wof:placetype":"venue"
},
  "geometry": {"coordinates":[15.2384824753,47.5437736511],"type":"Point"}
}