{
  "type": "Feature",
  "properties": {
    "addr:full":"Auf der Halde 1 Leonding Ober\u00f6sterreich 4060",
    "addr:housenumber":"1",
    "addr:postcode":"4060",
    "addr:street":"Auf Der Halde",
    "iso:country":"AT",
    "sg:address":"Auf der Halde 1",
    "sg:city":"Leonding",
    "sg:orig_category":"Ingenieurkonsulenten / Zivilingenieure",
    "sg:phone":"+43 732 781061",
    "sg:postcode":"4060",
    "sg:province":"Ober\u00f6sterreich",
    "wof:name":"Schm\u00f6ller Emil Prof Dipl-Ing",
    "wof:placetype":"venue"
},
  "geometry": {"coordinates":[14.2639694214,48.2919120789],"type":"Point"}
}