{
  "type": "Feature",
  "properties": {
    "iso:country":"AT",
    "sg:address":"Grundauerweg 15",
    "sg:city":"Baden",
    "sg:orig_category":"Immobilienverwaltungen",
    "sg:phone":"+43 4322 529010",
    "sg:postcode":"2500",
    "sg:province":"Nieder\u00f6sterreich",
    "wof:name":"MEDICALPARK Liegenschaftsbetriebs- und besitzgesellschaft mbH",
    "wof:placetype":"venue"
},
  "geometry": {"coordinates":[16.2557163239,47.997013092],"type":"Point"}
}