{
  "type": "Feature",
  "properties": {
    "addr:full":"Parhamerpl 18 Wien Wien 1170",
    "addr:housenumber":"18",
    "addr:postcode":"1170",
    "addr:street":"Parhamerpl",
    "iso:country":"AT",
    "sg:address":"Parhamerpl 18",
    "sg:city":"Wien",
    "sg:orig_category":"Nachhilfe U Lernbetreuung",
    "sg:phone":"+43 676 845009229",
    "sg:postcode":"1170",
    "sg:province":"Wien",
    "wof:name":"Lernfreunde Nachhilfe & Lern- Coaching",
    "wof:placetype":"venue"
},
  "geometry": {"coordinates":[16.3276996613,48.2162895203],"type":"Point"}
}