{
  "type": "Feature",
  "properties": {
    "addr:full":"Flurg 3 Trofaiach Steiermark 8793",
    "addr:housenumber":"3",
    "addr:postcode":"8793",
    "addr:street":"Flurg",
    "iso:country":"AT",
    "sg:address":"Flurg 3",
    "sg:city":"Trofaiach",
    "sg:orig_category":"Tischlereien",
    "sg:phone":"+43 3847 2548",
    "sg:postcode":"8793",
    "sg:province":"Steiermark",
    "wof:name":"Rieger Manfred",
    "wof:placetype":"venue"
},
  "geometry": {"coordinates":[15.0089483261,47.4190979004],"type":"Point"}
}