{
  "type": "Feature",
  "properties": {
    "addr:full":"Seitenbachweg 15  Gnigl Salzburg 5023",
    "addr:housenumber":"15",
    "addr:postcode":"5023",
    "addr:street":"Seitenbachweg",
    "iso:country":"AT",
    "sg:address":"Seitenbachweg 15 ",
    "sg:city":"Gnigl",
    "sg:classifiers":[
        {
            "category":"Professional",
            "subcategory":"Advertising",
            "type":"Services"
        }
    ],
    "sg:phone":"+43 4366 2663273",
    "sg:postcode":"5023",
    "sg:province":"Salzburg",
    "sg:tags":[
        "communication",
        "medium"
    ],
    "wof:name":"SALZBURGER PRESSEAGENTUR GMBH & CO KG",
    "wof:placetype":"venue"
},
  "geometry": {"coordinates":[13.075504303,47.8233604431],"type":"Point"}
}