{
  "type": "Feature",
  "properties": {
    "addr:full":"Lambrechtg 13 Baden Nieder\u00f6sterreich 2500",
    "addr:housenumber":"13",
    "addr:postcode":"2500",
    "addr:street":"Lambrechtg;Niederoesterreich",
    "iso:country":"AT",
    "sg:address":"Lambrechtg 13",
    "sg:city":"Baden",
    "sg:orig_category":"Steuerberatung",
    "sg:phone":"+43 2252 81479",
    "sg:postcode":"2500",
    "sg:province":"Nieder\u00f6sterreich",
    "wof:name":"Dippelreiter Inge Mag",
    "wof:placetype":"venue"
},
  "geometry": {"coordinates":[16.2473735809,48.0041885376],"type":"Point"}
}