{
  "type": "Feature",
  "properties": {
    "addr:full":"Anton Krieger-G 140 Wien Wien 1230",
    "addr:housenumber":"140",
    "addr:postcode":"1230",
    "iso:country":"AT",
    "sg:address":"Anton Krieger-G 140",
    "sg:city":"Wien",
    "sg:orig_category":"Psychotherapie",
    "sg:phone":"+43 1 8887677",
    "sg:postcode":"1230",
    "sg:province":"Wien",
    "wof:name":"Sch\u00f6ny Alfred Mag",
    "wof:placetype":"venue"
},
  "geometry": {"coordinates":[16.2637348175,48.1441917419],"type":"Point"}
}