{
  "type": "Feature",
  "properties": {
    "addr:full":"Oberboden 6 Himmelberg K\u00e4rnten 9562",
    "addr:housenumber":"6",
    "addr:postcode":"9562",
    "addr:street":"Oberboden;Himmelberg Kaernten",
    "iso:country":"AT",
    "sg:address":"Oberboden 6",
    "sg:city":"Himmelberg",
    "sg:orig_category":"Stahlbau",
    "sg:phone":"+43 4276 25560",
    "sg:postcode":"9562",
    "sg:province":"K\u00e4rnten",
    "wof:name":"Buttazoni GmbH - Stahlbau Montagen",
    "wof:placetype":"venue"
},
  "geometry": {"coordinates":[14.0372676849,46.7478256226],"type":"Point"}
}