{
  "type": "Feature",
  "properties": {
    "addr:full":"Gumpling 68 Ostermiething Ober\u00f6sterreich 5121",
    "addr:housenumber":"68",
    "addr:postcode":"5121",
    "addr:street":"Gumpling",
    "iso:country":"AT",
    "sg:address":"Gumpling 68",
    "sg:city":"Ostermiething",
    "sg:orig_category":"Handelsagenturen",
    "sg:phone":"+43 6278 7567",
    "sg:postcode":"5121",
    "sg:province":"Ober\u00f6sterreich",
    "wof:name":"Macher Elwine",
    "wof:placetype":"venue"
},
  "geometry": {"coordinates":[12.8649787903,48.044883728],"type":"Point"}
}