{
  "type": "Feature",
  "properties": {
    "addr:full":"Markt 95 St. Gallen Steiermark 8933",
    "addr:housenumber":"95",
    "addr:postcode":"8933",
    "addr:street":"Markt",
    "iso:country":"AT",
    "sg:address":"Markt 95",
    "sg:city":"St. Gallen",
    "sg:orig_category":"Tabaktrafiken",
    "sg:phone":"+43 3632 338",
    "sg:postcode":"8933",
    "sg:province":"Steiermark",
    "wof:name":"Hermann Christine",
    "wof:placetype":"venue"
},
  "geometry": {"coordinates":[14.6171894073,47.6916503906],"type":"Point"}
}