{
  "type": "Feature",
  "properties": {
    "iso:country":"AT",
    "sg:address":"Latschau",
    "sg:city":"Tschagguns",
    "sg:orig_category":"Feuerwehren",
    "sg:phone":"+43 5556 74121",
    "sg:postcode":"6774",
    "sg:province":"Vorarlberg",
    "wof:name":"Feuerwehr Latschau",
    "wof:placetype":"venue"
},
  "geometry": {"coordinates":[9.8734397888,47.0744514465],"type":"Point"}
}