{
  "type": "Feature",
  "properties": {
    "addr:full":"Nr 41 Ainet Tirol 9951",
    "addr:postcode":"9951",
    "addr:street":"Nr 41",
    "iso:country":"AT",
    "sg:address":"Nr 41",
    "sg:city":"Ainet",
    "sg:classifiers":[
        {
            "category":"Recreation",
            "type":"Entertainment"
        }
    ],
    "sg:phone":"+43 4348 535231",
    "sg:postcode":"9951",
    "sg:province":"Tirol",
    "sg:tags":[
        "sport",
        "adventure"
    ],
    "wof:name":"A Messner Raft Company",
    "wof:placetype":"venue"
},
  "geometry": {"coordinates":[12.6879796982,46.8666038513],"type":"Point"}
}