{
  "type": "Feature",
  "properties": {
    "addr:full":"Hauptpl 9 Mank Nieder\u00f6sterreich 3240",
    "addr:housenumber":"9",
    "addr:postcode":"3240",
    "addr:street":"Hauptpl;Niederoesterreich",
    "iso:country":"AT",
    "sg:address":"Hauptpl 9",
    "sg:city":"Mank",
    "sg:orig_category":"Tabaktrafiken",
    "sg:phone":"+43 2755 2461",
    "sg:postcode":"3240",
    "sg:province":"Nieder\u00f6sterreich",
    "wof:name":"Scheibelhofer Herbert",
    "wof:placetype":"venue"
},
  "geometry": {"coordinates":[15.3412923813,48.1120033264],"type":"Point"}
}