{
  "type": "Feature",
  "properties": {
    "iso:country":"AT",
    "sg:city":"Korneuburg",
    "sg:classifiers":[
        {
            "category":"Taxi",
            "type":"Transportation"
        }
    ],
    "sg:phone":"+43 2262 6910",
    "sg:postcode":"2100",
    "sg:province":"Nieder\u00f6sterreich",
    "sg:tags":[
        "furniture"
    ],
    "sg:website":"sobolak.com",
    "wof:name":"Peter Sobolak Ges.m.b.H.",
    "wof:placetype":"venue"
},
  "geometry": {"coordinates":[16.3230648041,48.3774147034],"type":"Point"}
}