{
  "type": "Feature",
  "properties": {
    "addr:full":"Wimsbacher Str 20 Stadl-Paura Ober\u00f6sterreich 4651",
    "addr:postcode":"4651",
    "addr:street":"Str 20 Stadl-Paura",
    "iso:country":"AT",
    "sg:address":"Wimsbacher Str 20",
    "sg:city":"Stadl-Paura",
    "sg:orig_category":"Holzhandel",
    "sg:phone":"+43 7245 217060",
    "sg:postcode":"4651",
    "sg:province":"Ober\u00f6sterreich",
    "wof:name":"Neuhofer Holz-Import-Export GesmbH",
    "wof:placetype":"venue"
},
  "geometry": {"coordinates":[13.88048172,48.0830116272],"type":"Point"}
}