{
  "type": "Feature",
  "properties": {
    "addr:full":"Hofsteigstrasse 7 Wolfurt-Bahnhof Vorarlberg 6960",
    "addr:housenumber":"7",
    "addr:postcode":"6960",
    "addr:street":"Hofsteigstrasse",
    "iso:country":"AT",
    "sg:address":"Hofsteigstrasse 7",
    "sg:city":"Wolfurt-Bahnhof",
    "sg:classifiers":[
        {
            "category":"Manufacturing",
            "subcategory":"Musical Instruments",
            "type":"Manufacturing & Wholesale Goods"
        }
    ],
    "sg:phone":"+43 5574 71345",
    "sg:postcode":"6960",
    "sg:province":"Vorarlberg",
    "sg:tags":[
        "brass",
        "mouth",
        "bell"
    ],
    "sg:website":"musik-hinteregger.at",
    "wof:name":"Musik Hinteregger Ges.m.b.H.",
    "wof:placetype":"venue"
},
  "geometry": {"coordinates":[9.7515535355,47.466583252],"type":"Point"}
}