{
  "type": "Feature",
  "properties": {
    "iso:country":"AT",
    "sg:address":"Niederschremser Str 1",
    "sg:city":"Schrems",
    "sg:orig_category":"Brauereien",
    "sg:phone":"+43 2853 772750",
    "sg:postcode":"3943",
    "sg:province":"Nieder\u00f6sterreich",
    "wof:name":"Brauerei Schrems",
    "wof:placetype":"venue"
},
  "geometry": {"coordinates":[15.067568779,48.7891845703],"type":"Point"}
}