{
  "type": "Feature",
  "properties": {
    "addr:full":"Franz Josefs Kai 15 Wien Wien 1010",
    "addr:housenumber":"15",
    "addr:postcode":"1010",
    "iso:country":"AT",
    "sg:address":"Franz Josefs Kai 15",
    "sg:city":"Wien",
    "sg:classifiers":[
        {
            "category":"Shopping",
            "subcategory":"Clothing, Apparel, & Fashions",
            "type":"Retail Goods"
        }
    ],
    "sg:phone":"+43 4315 335269",
    "sg:postcode":"1010",
    "sg:province":"Wien",
    "sg:tags":[
        "clothes"
    ],
    "wof:name":"M\u00dcLLBAUER HUT UND MODE GESMBH",
    "wof:placetype":"venue"
},
  "geometry": {"coordinates":[16.3776168823,48.2112998962],"type":"Point"}
}