{
  "type": "Feature",
  "properties": {
    "iso:country":"AT",
    "sg:address":"Hauptstr 16",
    "sg:city":"Hinterbr\u00fchl",
    "sg:orig_category":"Installationsunternehmen",
    "sg:phone":"+43 4322 36864178",
    "sg:postcode":"2371",
    "sg:province":"Nieder\u00f6sterreich",
    "wof:name":"Haas Gustav",
    "wof:placetype":"venue"
},
  "geometry": {"coordinates":[16.2555236816,48.0866966248],"type":"Point"}
}