{
  "type": "Feature",
  "properties": {
    "addr:full":"Hauptstr 16 Hinterbr\u00fchl Nieder\u00f6sterreich 2371",
    "addr:housenumber":"16",
    "addr:postcode":"2371",
    "addr:street":"Hauptstr;Niederoesterreich",
    "iso:country":"AT",
    "sg:address":"Hauptstr 16",
    "sg:city":"Hinterbr\u00fchl",
    "sg:orig_category":"Installationsunternehmen",
    "sg:phone":"+43 4322 36864178",
    "sg:postcode":"2371",
    "sg:province":"Nieder\u00f6sterreich",
    "wof:name":"Haas Gustav",
    "wof:placetype":"venue"
},
  "geometry": {"coordinates":[16.2555236816,48.0866966248],"type":"Point"}
}