{
  "type": "Feature",
  "properties": {
    "addr:full":"Fiechterweg 4 Kolsass Tirol 6114",
    "addr:housenumber":"4",
    "addr:postcode":"6114",
    "addr:street":"Fiechterweg;Tirol",
    "iso:country":"AT",
    "sg:address":"Fiechterweg 4",
    "sg:city":"Kolsass",
    "sg:orig_category":"Volksschulen",
    "sg:phone":"+43 5224 68153",
    "sg:postcode":"6114",
    "sg:province":"Tirol",
    "wof:name":"Volksschule",
    "wof:placetype":"venue"
},
  "geometry": {"coordinates":[11.6341152191,47.2991828918],"type":"Point"}
}