{
  "type": "Feature",
  "properties": {
    "addr:full":"Leystr 2-4 Wien Wien 1200",
    "addr:housenumber":"2-4",
    "addr:postcode":"1200",
    "addr:street":"Leystr",
    "iso:country":"AT",
    "sg:address":"Leystr 2-4",
    "sg:city":"Wien",
    "sg:orig_category":"Lebensmittel / Einzelhandel",
    "sg:phone":"+43 1 9612015",
    "sg:postcode":"1200",
    "sg:province":"Wien",
    "wof:name":"Billa AG",
    "wof:placetype":"venue"
},
  "geometry": {"coordinates":[16.3747463226,48.2481765747],"type":"Point"}
}