{
  "type": "Feature",
  "properties": {
    "addr:full":"Brixentaler Str 3 Hopfgarten im Brixental Tirol 6361",
    "addr:housenumber":"3",
    "addr:postcode":"6361",
    "addr:street":"Str;Tirol",
    "iso:country":"AT",
    "sg:address":"Brixentaler Str 3",
    "sg:city":"Hopfgarten im Brixental",
    "sg:classifiers":[
        {
            "category":"Professional",
            "type":"Services"
        }
    ],
    "sg:phone":"+43 5335 2154",
    "sg:postcode":"6361",
    "sg:province":"Tirol",
    "sg:tags":[
        "leasing"
    ],
    "wof:name":"Pletzer Anton Leasing- und Verwaltungs-GmbH",
    "wof:placetype":"venue"
},
  "geometry": {"coordinates":[12.1584234238,47.4481773376],"type":"Point"}
}