{
  "type": "Feature",
  "properties": {
    "iso:country":"AT",
    "sg:address":"Zenzi H\u00f6lzl-Str 2a",
    "sg:city":"Gloggnitz",
    "sg:orig_category":"Hauskrankenpflege / Heimhilfe",
    "sg:phone":"+43 2662 454500",
    "sg:postcode":"2640",
    "sg:province":"Nieder\u00f6sterreich",
    "wof:name":"Hilfswerk Gloggnitz - Hilfe und Pflege daheim",
    "wof:placetype":"venue"
},
  "geometry": {"coordinates":[15.949215889,47.6749916077],"type":"Point"}
}