{
  "type": "Feature",
  "properties": {
    "addr:full":"Brauhausstr 49 Schwechat Nieder\u00f6sterreich 2320",
    "addr:housenumber":"49",
    "addr:postcode":"2320",
    "addr:street":"Brauhausstr;Niederoesterreich",
    "iso:country":"AT",
    "sg:address":"Brauhausstr 49",
    "sg:city":"Schwechat",
    "sg:orig_category":"Sonnenstudios",
    "sg:phone":"+43 1 7062055",
    "sg:postcode":"2320",
    "sg:province":"Nieder\u00f6sterreich",
    "wof:name":"Br\u00e4unungsinsel Rannersdorf",
    "wof:placetype":"venue"
},
  "geometry": {"coordinates":[16.4654903412,48.1286468506],"type":"Point"}
}