{
  "type": "Feature",
  "properties": {
    "addr:full":"Gallmeyerg 6/2/2 Wien Wien 1190",
    "addr:housenumber":"6 / 2 / 2",
    "addr:postcode":"1190",
    "addr:street":"Gallmeyerg",
    "iso:country":"AT",
    "sg:address":"Gallmeyerg 6/2/2",
    "sg:city":"Wien",
    "sg:orig_category":"Matratzen",
    "sg:phone":"+43 4369 910511379",
    "sg:postcode":"1190",
    "sg:province":"Wien",
    "wof:name":"Matratzenreinigung Mag Reinhard Gutmann",
    "wof:placetype":"venue"
},
  "geometry": {"coordinates":[16.3493022919,48.2389793396],"type":"Point"}
}