{
  "type": "Feature",
  "properties": {
    "addr:full":"Nr 38 Brunn an der Wild Nieder\u00f6sterreich 3595",
    "addr:postcode":"3595",
    "addr:street":"Nr 38",
    "iso:country":"AT",
    "sg:address":"Nr 38",
    "sg:city":"Brunn an der Wild",
    "sg:orig_category":"Transportunternehmen",
    "sg:phone":"+43 2989 2232",
    "sg:postcode":"3595",
    "sg:province":"Nieder\u00f6sterreich",
    "wof:name":"Allram Norbert",
    "wof:placetype":"venue"
},
  "geometry": {"coordinates":[15.5209503174,48.6939620972],"type":"Point"}
}