{
  "type": "Feature",
  "properties": {
    "iso:country":"AT",
    "sg:address":"Herreng 16",
    "sg:city":"Graz",
    "sg:orig_category":"Tourismusinformation U -Organisationen",
    "sg:phone":"+43 316 80750",
    "sg:postcode":"8010",
    "sg:province":"Steiermark",
    "wof:name":"Graz Tourismus GesmbH Graz-Steiermarkinformation",
    "wof:placetype":"venue"
},
  "geometry": {"coordinates":[15.4397230148,47.0699234009],"type":"Point"}
}