{
  "type": "Feature",
  "properties": {
    "addr:full":"Grazer Str 14 Mureck Steiermark 8480",
    "addr:postcode":"8480",
    "addr:street":"Str",
    "iso:country":"AT",
    "sg:address":"Grazer Str 14",
    "sg:city":"Mureck",
    "sg:orig_category":"\u00c3\u201erzte / F Allgemeinmedizin",
    "sg:phone":"+43 3472 37503",
    "sg:postcode":"8480",
    "sg:province":"Steiermark",
    "wof:name":"Dorner Helen Dr",
    "wof:placetype":"venue"
},
  "geometry": {"coordinates":[15.7698850632,46.7079544067],"type":"Point"}
}