{
  "type": "Feature",
  "properties": {
    "iso:country":"AT",
    "sg:address":"Argentinierstr 48",
    "sg:city":"Wien",
    "sg:classifiers":[
        {
            "category":"Restaurant",
            "type":"Food & Drink"
        }
    ],
    "sg:phone":"+43 1 5032774",
    "sg:postcode":"1040",
    "sg:province":"Wien",
    "wof:name":"Brandtner Georg",
    "wof:placetype":"venue"
},
  "geometry": {"coordinates":[16.3759994507,48.1891479492],"type":"Point"}
}