{
  "type": "Feature",
  "properties": {
    "iso:country":"AT",
    "sg:address":"Frax 524",
    "sg:city":"M\u00fcnster",
    "sg:orig_category":"\u00c3\u201erzte / F Allgemeinmedizin",
    "sg:phone":"+43 5337 8250",
    "sg:postcode":"6232",
    "sg:province":"Tirol",
    "wof:name":"Geiger Alexander Dr",
    "wof:placetype":"venue"
},
  "geometry": {"coordinates":[11.8125801086,47.4356613159],"type":"Point"}
}