{
  "type": "Feature",
  "properties": {
    "addr:full":"Leonhardstr 42 Graz Steiermark 8010",
    "addr:housenumber":"42",
    "addr:postcode":"8010",
    "addr:street":"Leonhardstr",
    "iso:country":"AT",
    "sg:address":"Leonhardstr 42",
    "sg:city":"Graz",
    "sg:orig_category":"Schuhreparatur",
    "sg:phone":"+43 4331 6325533",
    "sg:postcode":"8010",
    "sg:province":"Steiermark",
    "wof:name":"Schuh- u Schl\u00fcssel-Sofortdienst Negro Alfred",
    "wof:placetype":"venue"
},
  "geometry": {"coordinates":[15.4536190033,47.0729751587],"type":"Point"}
}