{
  "type": "Feature",
  "properties": {
    "iso:country":"AT",
    "sg:address":"Niederottnang 145",
    "sg:city":"Ottnang am Hausruck",
    "sg:orig_category":"Installationsunternehmen",
    "sg:phone":"+43 767673500",
    "sg:postcode":"4901",
    "sg:province":"Ober\u00f6sterreich",
    "wof:name":"H\u00f6dlmoser Franz GesmbH & Co KG",
    "wof:placetype":"venue"
},
  "geometry": {"coordinates":[13.6627902985,48.0965843201],"type":"Point"}
}