{
  "type": "Feature",
  "properties": {
    "addr:full":"Dr.-Zimmermann-Str 4 Bad Hofgastein Salzburg 5630",
    "addr:housenumber":"4",
    "addr:postcode":"5630",
    "addr:street":"Dr.-Zimmermann-Str;Salzburg",
    "iso:country":"AT",
    "sg:address":"Dr.-Zimmermann-Str 4",
    "sg:city":"Bad Hofgastein",
    "sg:orig_category":"Appartements / Ferienwohnungen",
    "sg:phone":"+43 4364 3263320",
    "sg:postcode":"5630",
    "sg:province":"Salzburg",
    "wof:name":"Ferienappartements L u S Lafenthaler",
    "wof:placetype":"venue"
},
  "geometry": {"coordinates":[13.1015796661,47.1699867249],"type":"Point"}
}