{
  "type": "Feature",
  "properties": {
    "addr:full":"Gleichenberger Str 3 St. Stefan im Rosental Steiermark 8083",
    "addr:housenumber":"3",
    "addr:postcode":"8083",
    "addr:street":"Str",
    "iso:country":"AT",
    "sg:address":"Gleichenberger Str 3",
    "sg:city":"St. Stefan im Rosental",
    "sg:orig_category":"Entfeuchtungen",
    "sg:phone":"+43 4331 1681444",
    "sg:postcode":"8083",
    "sg:province":"Steiermark",
    "sg:website":"trockentechnik.at",
    "wof:name":"Zach Alfred",
    "wof:placetype":"venue"
},
  "geometry": {"coordinates":[15.7199144363,46.8988227844],"type":"Point"}
}