{
  "type": "Feature",
  "properties": {
    "addr:full":"D\u00f6blinger Hauptstrasse 22 Wien Wien 1190",
    "addr:housenumber":"22",
    "addr:postcode":"1190",
    "addr:street":"Hauptstrasse",
    "iso:country":"AT",
    "sg:address":"D\u00f6blinger Hauptstrasse 22",
    "sg:city":"Wien",
    "sg:classifiers":[
        {
            "category":"Professional",
            "subcategory":"Advertising",
            "type":"Services"
        }
    ],
    "sg:phone":"+43 1 3696069",
    "sg:postcode":"1190",
    "sg:province":"Wien",
    "wof:name":"Dr. Ludwig Diess B\u00fcro f\u00fcr sozial- und wirtschafts-wi ssenschaftliche Studien",
    "wof:placetype":"venue"
},
  "geometry": {"coordinates":[16.3530235291,48.2341346741],"type":"Point"}
}