{
  "type": "Feature",
  "properties": {
    "iso:country":"AT",
    "sg:address":"Hauptpl 1",
    "sg:city":"Ertl",
    "sg:orig_category":"Gemeinden",
    "sg:phone":"+43 7477 72010",
    "sg:postcode":"3355",
    "sg:province":"Nieder\u00f6sterreich",
    "wof:name":"Gemeindeamt Ertl",
    "wof:placetype":"venue"
},
  "geometry": {"coordinates":[14.6313562393,47.9772796631],"type":"Point"}
}