{
  "type": "Feature",
  "properties": {
    "addr:full":"Nr 610a Edelschrott Steiermark 8583",
    "addr:postcode":"8583",
    "addr:street":"Nr",
    "iso:country":"AT",
    "sg:address":"Nr 610a",
    "sg:city":"Edelschrott",
    "sg:orig_category":"Waren Aller Art",
    "sg:phone":"+43 4331 4580064",
    "sg:postcode":"8583",
    "sg:province":"Steiermark",
    "wof:name":"VDOT-Woldrich",
    "wof:placetype":"venue"
},
  "geometry": {"coordinates":[15.0517597198,47.0216178894],"type":"Point"}
}