{
  "type": "Feature",
  "properties": {
    "addr:full":"Seestr 37 Neusiedl am See Burgenland 7100",
    "addr:housenumber":"37",
    "addr:postcode":"7100",
    "addr:street":"Seestr",
    "iso:country":"AT",
    "sg:address":"Seestr 37",
    "sg:city":"Neusiedl am See",
    "sg:orig_category":"Garten- U Landschaftsgestaltung",
    "sg:phone":"+43 4321 6785340",
    "sg:postcode":"7100",
    "sg:province":"Burgenland",
    "wof:name":"Dolezal Christian Ing",
    "wof:placetype":"venue"
},
  "geometry": {"coordinates":[16.8453102112,47.940071106],"type":"Point"}
}