{
  "type": "Feature",
  "properties": {
    "addr:full":"Herreng 23 Bludenz Vorarlberg 6700",
    "addr:housenumber":"23",
    "addr:postcode":"6700",
    "addr:street":"Herreng",
    "iso:country":"AT",
    "sg:address":"Herreng 23",
    "sg:city":"Bludenz",
    "sg:orig_category":"Werbeagenturen",
    "sg:phone":"+43 5552 32570",
    "sg:postcode":"6700",
    "sg:province":"Vorarlberg",
    "wof:name":"Wachter Design",
    "wof:placetype":"venue"
},
  "geometry": {"coordinates":[9.8216791153,47.1567420959],"type":"Point"}
}