{
  "type": "Feature",
  "properties": {
    "addr:full":"Marktpl 6 Heiligenkreuz am Waasen Steiermark 8081",
    "addr:housenumber":"6",
    "addr:postcode":"8081",
    "addr:street":"Marktpl",
    "iso:country":"AT",
    "sg:address":"Marktpl 6",
    "sg:city":"Heiligenkreuz am Waasen",
    "sg:orig_category":"Polizei U Gendarmerie",
    "sg:phone":"+43 4359 1336167",
    "sg:postcode":"8081",
    "sg:province":"Steiermark",
    "wof:name":"Gendarmerieposten",
    "wof:placetype":"venue"
},
  "geometry": {"coordinates":[15.5848884583,46.9565734863],"type":"Point"}
}