{
  "type": "Feature",
  "properties": {
    "addr:full":"Bezegg 527 Bezau Vorarlberg 6870",
    "addr:housenumber":"527",
    "addr:postcode":"6870",
    "iso:country":"AT",
    "sg:address":"Bezegg 527",
    "sg:city":"Bezau",
    "sg:orig_category":"Tischlereien",
    "sg:phone":"+43 5514 2933",
    "sg:postcode":"6870",
    "sg:province":"Vorarlberg",
    "wof:name":"D\u00fcnser Kaspar",
    "wof:placetype":"venue"
},
  "geometry": {"coordinates":[9.9026212692,47.3876495361],"type":"Point"}
}