{
  "type": "Feature",
  "properties": {
    "iso:country":"AT",
    "sg:address":"Rathauspl 4-6",
    "sg:city":"Gmunden",
    "sg:orig_category":"Bekleidung / Einzelhandel",
    "sg:phone":"+43 7612649940",
    "sg:postcode":"4810",
    "sg:province":"Ober\u00f6sterreich",
    "wof:name":"Forstinger Mode KG",
    "wof:placetype":"venue"
},
  "geometry": {"coordinates":[13.7992916107,47.9184150696],"type":"Point"}
}