{
  "type": "Feature",
  "properties": {
    "iso:country":"AT",
    "sg:address":"Rathausstr 19",
    "sg:city":"Wien",
    "sg:orig_category":"Strick- U Wirkwaren / Erzeugung U Gro\u00c3\u0178handel",
    "sg:phone":"+43 4314 064207",
    "sg:postcode":"1010",
    "sg:province":"Wien",
    "wof:name":"Nossek Renate Strickwarenerzeugung GesmbH",
    "wof:placetype":"venue"
},
  "geometry": {"coordinates":[16.357006073,48.2137870789],"type":"Point"}
}