{
  "type": "Feature",
  "properties": {
    "addr:full":"Gortipohl 75e St. Gallenkirch Vorarlberg 6791",
    "addr:housenumber":"75e",
    "addr:postcode":"6791",
    "addr:street":"Gortipohl",
    "iso:country":"AT",
    "sg:address":"Gortipohl 75e",
    "sg:city":"St. Gallenkirch",
    "sg:classifiers":[
        {
            "category":"Professional",
            "subcategory":"Art Services",
            "type":"Services"
        }
    ],
    "sg:phone":"+43 5557 6410",
    "sg:postcode":"6791",
    "sg:province":"Vorarlberg",
    "sg:tags":[
        "metalwork"
    ],
    "wof:name":"Karl Mangard Kunstschmiede",
    "wof:placetype":"venue"
},
  "geometry": {"coordinates":[10.0059900284,47.0049667358],"type":"Point"}
}