{
  "type": "Feature",
  "properties": {
    "addr:full":"Zachg 12 Wien Wien 1220",
    "addr:housenumber":"12",
    "addr:postcode":"1220",
    "addr:street":"Zachg",
    "iso:country":"AT",
    "sg:address":"Zachg 12",
    "sg:city":"Wien",
    "sg:orig_category":"Autospenglereien",
    "sg:phone":"+43 1 2823314",
    "sg:postcode":"1220",
    "sg:province":"Wien",
    "wof:name":"Walouch G\u00fcnter",
    "wof:placetype":"venue"
},
  "geometry": {"coordinates":[16.4889259338,48.2163352966],"type":"Point"}
}