{
  "type": "Feature",
  "properties": {
    "iso:country":"AT",
    "sg:address":"Gro\u00dfendorf 52",
    "sg:city":"Ried im Traunkreis",
    "sg:orig_category":"Gesundheitsvorsorge",
    "sg:phone":"+43 4366 02130121",
    "sg:postcode":"4551",
    "sg:province":"Ober\u00f6sterreich",
    "wof:name":"M\u00f6rtenhuber Sabine",
    "wof:placetype":"venue"
},
  "geometry": {"coordinates":[14.0738592148,48.0253601074],"type":"Point"}
}