{
  "type": "Feature",
  "properties": {
    "addr:full":"Nr 112 Wildsch\u00f6nau-Oberau Tirol 6311",
    "addr:postcode":"6311",
    "addr:street":"Nr 112 Wildschoenau-Oberau Tirol",
    "iso:country":"AT",
    "sg:address":"Nr 112",
    "sg:city":"Wildsch\u00f6nau-Oberau",
    "sg:orig_category":"Autobusunternehmen",
    "sg:phone":"+43 5339 8144",
    "sg:postcode":"6311",
    "sg:province":"Tirol",
    "sg:website":"riedmann-reisen.at",
    "wof:name":"Riedmann-Reisen",
    "wof:placetype":"venue"
},
  "geometry": {"coordinates":[12.0532751083,47.4453582764],"type":"Point"}
}