{
  "type": "Feature",
  "properties": {
    "addr:full":"Gewerbepark 561/1 Serfaus Tirol 6534",
    "addr:housenumber":"561 / 1",
    "addr:postcode":"6534",
    "addr:street":"Gewerbepark;Tirol",
    "iso:country":"AT",
    "sg:address":"Gewerbepark 561/1",
    "sg:city":"Serfaus",
    "sg:orig_category":"Tischlereien",
    "sg:phone":"+43 5476 6156",
    "sg:postcode":"6534",
    "sg:province":"Tirol",
    "wof:name":"Kirschner Richard",
    "wof:placetype":"venue"
},
  "geometry": {"coordinates":[10.6053447723,47.0386734009],"type":"Point"}
}