{
  "type": "Feature",
  "properties": {
    "addr:full":"Biedermanngasse 28 Wien Wien 1120",
    "addr:housenumber":"28",
    "addr:postcode":"1120",
    "addr:street":"Biedermanngasse",
    "iso:country":"AT",
    "sg:address":"Biedermanngasse 28",
    "sg:city":"Wien",
    "sg:classifiers":[
        {
            "category":"Professional",
            "subcategory":"Engineering",
            "type":"Services"
        }
    ],
    "sg:phone":"+43 4318 048502",
    "sg:postcode":"1120",
    "sg:province":"Wien",
    "sg:tags":[
        "machine",
        "-",
        "mechanical"
    ],
    "wof:name":"SCHIESSL-K\u00c4LTE GES.MBH",
    "wof:placetype":"venue"
},
  "geometry": {"coordinates":[16.3137016296,48.164024353],"type":"Point"}
}