{
  "type": "Feature",
  "properties": {
    "addr:full":"Museumstr 11 Linz Ober\u00f6sterreich 4020",
    "addr:housenumber":"11",
    "addr:postcode":"4020",
    "addr:street":"Museumstr",
    "iso:country":"AT",
    "sg:address":"Museumstr 11",
    "sg:city":"Linz",
    "sg:orig_category":"Reiseveranstalter",
    "sg:phone":"+43 732 796965",
    "sg:postcode":"4020",
    "sg:province":"Ober\u00f6sterreich",
    "wof:name":"TUI Reiseveranstaltungs-GesmbH",
    "wof:placetype":"venue"
},
  "geometry": {"coordinates":[14.2915439606,48.3058853149],"type":"Point"}
}