{
  "type": "Feature",
  "properties": {
    "iso:country":"AT",
    "sg:address":"Lehmanng 25/2",
    "sg:city":"Wien",
    "sg:orig_category":"Personalbereitstellung",
    "sg:phone":"+43 1 9904174",
    "sg:postcode":"1230",
    "sg:province":"Wien",
    "wof:name":"Jomos",
    "wof:placetype":"venue"
},
  "geometry": {"coordinates":[16.278093338,48.1364097595],"type":"Point"}
}