{
  "type": "Feature",
  "properties": {
    "addr:full":"Bahnstr 177 Neulengbach Nieder\u00f6sterreich 3040",
    "addr:housenumber":"177",
    "addr:postcode":"3040",
    "iso:country":"AT",
    "sg:address":"Bahnstr 177",
    "sg:city":"Neulengbach",
    "sg:orig_category":"Bodenverlegung",
    "sg:phone":"+43 4327 7252126",
    "sg:postcode":"3040",
    "sg:province":"Nieder\u00f6sterreich",
    "wof:name":"P.B.I.",
    "wof:placetype":"venue"
},
  "geometry": {"coordinates":[15.9012355804,48.1978721619],"type":"Point"}
}