{
  "type": "Feature",
  "properties": {
    "addr:full":"Palmayg 8 Wien Wien 1130",
    "addr:housenumber":"8",
    "addr:postcode":"1130",
    "addr:street":"Palmayg",
    "iso:country":"AT",
    "sg:address":"Palmayg 8",
    "sg:city":"Wien",
    "sg:orig_category":"Physiotherapie",
    "sg:phone":"+43 1 8885223",
    "sg:postcode":"1130",
    "sg:province":"Wien",
    "wof:name":"Sabor Susanne Dipl-Phys",
    "wof:placetype":"venue"
},
  "geometry": {"coordinates":[16.3013801575,48.18592453],"type":"Point"}
}