{
  "type": "Feature",
  "properties": {
    "addr:full":"Seybelgasse 12 A Wien Wien 1230",
    "addr:housenumber":"12 a",
    "addr:postcode":"1230",
    "addr:street":"Seybelgasse",
    "iso:country":"AT",
    "sg:address":"Seybelgasse 12 A",
    "sg:city":"Wien",
    "sg:classifiers":[
        {
            "category":"Manufacturing",
            "subcategory":"Tools & Machinery",
            "type":"Manufacturing & Wholesale Goods"
        }
    ],
    "sg:phone":"+43 4318 6943210",
    "sg:postcode":"1230",
    "sg:province":"Wien",
    "sg:tags":[
        "environment",
        "equipment",
        "-"
    ],
    "wof:name":"DSB ANLAGENBAU GMBH",
    "wof:placetype":"venue"
},
  "geometry": {"coordinates":[16.2886695862,48.1358222961],"type":"Point"}
}