{
  "type": "Feature",
  "properties": {
    "iso:country":"AT",
    "sg:address":"Knutzingstr 12",
    "sg:city":"Eugendorf",
    "sg:orig_category":"Maschinenreparatur",
    "sg:phone":"+43 6225 20292",
    "sg:postcode":"5301",
    "sg:province":"Salzburg",
    "sg:website":"www.amp-technik.com",
    "wof:name":"AMP Industrietechnik - Pirkner Andreas",
    "wof:placetype":"venue"
},
  "geometry": {"coordinates":[13.1435699463,47.8630104065],"type":"Point"}
}