{
  "type": "Feature",
  "properties": {
    "addr:full":"Gabelsbergerstr 23 Innsbruck Tirol 6020",
    "addr:housenumber":"23",
    "addr:postcode":"6020",
    "addr:street":"Gabelsbergerstr;Tirol",
    "iso:country":"AT",
    "sg:address":"Gabelsbergerstr 23",
    "sg:city":"Innsbruck",
    "sg:orig_category":"Autoersatzteile",
    "sg:phone":"+43 512 394689",
    "sg:postcode":"6020",
    "sg:province":"Tirol",
    "wof:name":"Drivers All F Miller KEG",
    "wof:placetype":"venue"
},
  "geometry": {"coordinates":[11.4116353989,47.266166687],"type":"Point"}
}