{
  "type": "Feature",
  "properties": {
    "iso:country":"AT",
    "sg:address":"Gerasdorfer Str 55",
    "sg:city":"Wien",
    "sg:orig_category":"Handelsagenturen",
    "sg:phone":"+43 1 2929236",
    "sg:postcode":"1210",
    "sg:province":"Wien",
    "wof:name":"Tomacek Herbert",
    "wof:placetype":"venue"
},
  "geometry": {"coordinates":[16.4172401428,48.2836723328],"type":"Point"}
}