{
  "type": "Feature",
  "properties": {
    "iso:country":"AT",
    "sg:address":"Terminalstr 25",
    "sg:city":"Wels",
    "sg:orig_category":"Stra\u00c3\u0178enbau",
    "sg:phone":"+43 4372 42469910",
    "sg:postcode":"4600",
    "sg:province":"Ober\u00f6sterreich",
    "wof:name":"Reisner & Wolff Engineering GesmbH",
    "wof:placetype":"venue"
},
  "geometry": {"coordinates":[14.0537672043,48.1817359924],"type":"Point"}
}