{
  "type": "Feature",
  "properties": {
    "addr:full":"Grazer Str 36 Lebring Steiermark 8403",
    "addr:housenumber":"36",
    "addr:postcode":"8403",
    "addr:street":"Str",
    "iso:country":"AT",
    "sg:address":"Grazer Str 36",
    "sg:city":"Lebring",
    "sg:classifiers":[
        {
            "category":"Restaurant",
            "type":"Food & Drink"
        }
    ],
    "sg:phone":"+43 4331 822521",
    "sg:postcode":"8403",
    "sg:province":"Steiermark",
    "wof:name":"Restaurant - Gollner",
    "wof:placetype":"venue"
},
  "geometry": {"coordinates":[15.5284414291,46.8636741638],"type":"Point"}
}