{
  "type": "Feature",
  "properties": {
    "addr:full":"Rabenhof 11 St. Veit am Vogau Steiermark 8423",
    "addr:housenumber":"11",
    "addr:postcode":"8423",
    "addr:street":"Rabenhof",
    "iso:country":"AT",
    "sg:address":"Rabenhof 11",
    "sg:city":"St. Veit am Vogau",
    "sg:classifiers":[
        {
            "category":"Autos & Motor Vehicles",
            "subcategory":"Auto Supplies",
            "type":"Retail Goods"
        }
    ],
    "sg:phone":"+43 3453 3525",
    "sg:postcode":"8423",
    "sg:province":"Steiermark",
    "sg:tags":[
        "automobile",
        "painting"
    ],
    "wof:name":"Franz Thiersch\u00e4dl",
    "wof:placetype":"venue"
},
  "geometry": {"coordinates":[15.6490602493,46.7503929138],"type":"Point"}
}