{
  "type": "Feature",
  "properties": {
    "addr:full":"Gschwandnergasse 32 Wien Wien 1170",
    "addr:housenumber":"32",
    "addr:postcode":"1170",
    "addr:street":"Gschwandnergasse",
    "iso:country":"AT",
    "sg:address":"Gschwandnergasse 32",
    "sg:city":"Wien",
    "sg:classifiers":[
        {
            "category":"Manufacturing",
            "subcategory":"Printing",
            "type":"Manufacturing & Wholesale Goods"
        }
    ],
    "sg:phone":"+43 1 4858024",
    "sg:postcode":"1170",
    "sg:province":"Wien",
    "sg:tags":[
        "house",
        "book"
    ],
    "wof:name":"Angerer & G\u00f6schl Unternehmensbetriebsgesellschaft & Co Druckerei u. Handelsges.m.b.H.",
    "wof:placetype":"venue"
},
  "geometry": {"coordinates":[16.3249053955,48.2181091309],"type":"Point"}
}