{
  "type": "Feature",
  "properties": {
    "iso:country":"AT",
    "sg:address":"Hennersdorfer Str 38",
    "sg:city":"Leopoldsdorf",
    "sg:orig_category":"Holdinggesellschaften",
    "sg:phone":"+43 4322 35477510",
    "sg:postcode":"2333",
    "sg:province":"Nieder\u00f6sterreich",
    "wof:name":"AV Holding Beteiligungs-GmbH",
    "wof:placetype":"venue"
},
  "geometry": {"coordinates":[16.3969554901,48.1145591736],"type":"Point"}
}