{
  "type": "Feature",
  "properties": {
    "iso:country":"AT",
    "sg:address":"Pichlarner Str 91",
    "sg:city":"Irdning",
    "sg:orig_category":"Blumeneinzelhandel",
    "sg:phone":"+43 4336 82224380",
    "sg:postcode":"8952",
    "sg:province":"Steiermark",
    "wof:name":"blumen & co der pranzl Inh Leitner-Krainz Ulrike",
    "wof:placetype":"venue"
},
  "geometry": {"coordinates":[14.1145563126,47.5044136047],"type":"Point"}
}