{
  "type": "Feature",
  "properties": {
    "addr:full":"Anton Bruckner-Str 2 Ansfelden Ober\u00f6sterreich 4052",
    "addr:housenumber":"2",
    "addr:postcode":"4052",
    "iso:country":"AT",
    "sg:address":"Anton Bruckner-Str 2",
    "sg:city":"Ansfelden",
    "sg:orig_category":"Garten- U Landschaftsgestaltung",
    "sg:phone":"+43 4372 2983044",
    "sg:postcode":"4052",
    "sg:province":"Ober\u00f6sterreich",
    "sg:website":"gruen-braeuer.at",
    "wof:name":"Br\u00e4uer",
    "wof:placetype":"venue"
},
  "geometry": {"coordinates":[14.2917165756,48.2122535706],"type":"Point"}
}