{
  "type": "Feature",
  "properties": {
    "addr:full":"Seeg 26 Illmitz Burgenland 7142",
    "addr:housenumber":"26",
    "addr:postcode":"7142",
    "addr:street":"Seeg",
    "iso:country":"AT",
    "sg:address":"Seeg 26",
    "sg:city":"Illmitz",
    "sg:orig_category":"Pensionen / Privatzimmer",
    "sg:phone":"+43 4321 752735",
    "sg:postcode":"7142",
    "sg:province":"Burgenland",
    "wof:name":"G\u00e4stehaus Zum See - Ursula u Franz Fleischhacker",
    "wof:placetype":"venue"
},
  "geometry": {"coordinates":[16.7998695374,47.7619514465],"type":"Point"}
}