{
  "type": "Feature",
  "properties": {
    "iso:country":"AT",
    "sg:address":"Holzschachen 22",
    "sg:city":"Weistrach",
    "sg:classifiers":[
        {
            "category":"Home & Garden",
            "subcategory":"Home Furnishings",
            "type":"Retail Goods"
        }
    ],
    "sg:phone":"+43 4374 77423470",
    "sg:postcode":"3351",
    "sg:province":"Nieder\u00f6sterreich",
    "sg:tags":[
        "household"
    ],
    "wof:name":"KORNM\u00dcLLER GES.MBH & CO KG",
    "wof:placetype":"venue"
},
  "geometry": {"coordinates":[14.5837316513,48.0553855896],"type":"Point"}
}