{
  "type": "Feature",
  "properties": {
    "addr:full":"Bahnhofstr 10 St. Veit an der Glan K\u00e4rnten 9300",
    "addr:housenumber":"10",
    "addr:postcode":"9300",
    "addr:street":"Bahnhofstr;Kaernten",
    "iso:country":"AT",
    "sg:address":"Bahnhofstr 10",
    "sg:city":"St. Veit an der Glan",
    "sg:orig_category":"Versicherungsunternehmen",
    "sg:phone":"+43 4212 24150",
    "sg:postcode":"9300",
    "sg:province":"K\u00e4rnten",
    "wof:name":"K\u00e4rntner Landesversicherung auf Gegenseitigkeit",
    "wof:placetype":"venue"
},
  "geometry": {"coordinates":[14.3614196777,46.7676582336],"type":"Point"}
}