{
  "type": "Feature",
  "properties": {
    "iso:country":"AT",
    "sg:address":"Ringmauerg 13",
    "sg:city":"Villach",
    "sg:orig_category":"Psychotherapie",
    "sg:phone":"+43 664 2430338",
    "sg:postcode":"9500",
    "sg:province":"K\u00e4rnten",
    "wof:name":"Rainer Astrid Mag phil Dipl DA & EMB",
    "wof:placetype":"venue"
},
  "geometry": {"coordinates":[13.8426589966,46.6147727966],"type":"Point"}
}