{
  "type": "Feature",
  "properties": {
    "addr:full":"Wiesenweg 4 Deutschlandsberg Steiermark 8530",
    "addr:housenumber":"4",
    "addr:postcode":"8530",
    "addr:street":"Wiesenweg",
    "iso:country":"AT",
    "sg:address":"Wiesenweg 4",
    "sg:city":"Deutschlandsberg",
    "sg:orig_category":"\u00c3\u201erzte / F Allgemeinmedizin",
    "sg:phone":"+43 3462 64640",
    "sg:postcode":"8530",
    "sg:province":"Steiermark",
    "wof:name":"Feil Franz Dr",
    "wof:placetype":"venue"
},
  "geometry": {"coordinates":[15.2175369263,46.8112182617],"type":"Point"}
}