{
  "type": "Feature",
  "properties": {
    "addr:full":"Villacher Str 30 Spittal an der Drau K\u00e4rnten 9800",
    "addr:housenumber":"30",
    "addr:postcode":"9800",
    "addr:street":"Str;Kaernten",
    "iso:country":"AT",
    "sg:address":"Villacher Str 30",
    "sg:city":"Spittal an der Drau",
    "sg:orig_category":"Friseure U Frisiersalons",
    "sg:phone":"+43 4347 623410",
    "sg:postcode":"9800",
    "sg:province":"K\u00e4rnten",
    "wof:name":"Stuppnig Wolfgang",
    "wof:placetype":"venue"
},
  "geometry": {"coordinates":[13.5060043335,46.7925376892],"type":"Point"}
}