{
  "type": "Feature",
  "properties": {
    "addr:full":"Schmiedgraben 7 Linz Ober\u00f6sterreich 4040",
    "addr:housenumber":"7",
    "addr:postcode":"4040",
    "addr:street":"Schmiedgraben",
    "iso:country":"AT",
    "sg:address":"Schmiedgraben 7",
    "sg:city":"Linz",
    "sg:orig_category":"Tischlereien",
    "sg:phone":"+43 4372 396217",
    "sg:postcode":"4040",
    "sg:province":"Ober\u00f6sterreich",
    "wof:name":"Lindenberger GmbH",
    "wof:placetype":"venue"
},
  "geometry": {"coordinates":[14.281955719,48.3150138855],"type":"Point"}
}