{
  "type": "Feature",
  "properties": {
    "addr:full":"Hauptstr 6 Ternitz Nieder\u00f6sterreich 2630",
    "addr:housenumber":"6",
    "addr:postcode":"2630",
    "addr:street":"Hauptstr",
    "iso:country":"AT",
    "sg:address":"Hauptstr 6",
    "sg:city":"Ternitz",
    "sg:orig_category":"Banken U Sparkassen",
    "sg:phone":"+43 2630 382200",
    "sg:postcode":"2630",
    "sg:province":"Nieder\u00f6sterreich",
    "wof:name":"Raiffeisenbank Neunkirchen-Schwarzatal-Mitte regGenmbH",
    "wof:placetype":"venue"
},
  "geometry": {"coordinates":[16.0368499756,47.7153396606],"type":"Point"}
}