{
  "type": "Feature",
  "properties": {
    "addr:full":"Ghedinastr 9 Matrei in Osttirol Tirol 9971",
    "addr:housenumber":"9",
    "addr:postcode":"9971",
    "addr:street":"Ghedinastr;Tirol",
    "iso:country":"AT",
    "sg:address":"Ghedinastr 9",
    "sg:city":"Matrei in Osttirol",
    "sg:orig_category":"Non-Classified Establishments",
    "sg:phone":"+43 4875 6435",
    "sg:postcode":"9971",
    "sg:province":"Tirol",
    "wof:name":"Christliche Gemeinschaft Osttirol",
    "wof:placetype":"venue"
},
  "geometry": {"coordinates":[12.5397977829,47.0034599304],"type":"Point"}
}