{
  "type": "Feature",
  "properties": {
    "addr:full":"Nr 5 Euratsfeld Nieder\u00f6sterreich 3324",
    "addr:postcode":"3324",
    "addr:street":"Nr;Niederoesterreich",
    "iso:country":"AT",
    "sg:address":"Nr 5",
    "sg:city":"Euratsfeld",
    "sg:orig_category":"Non-Classified Establishments",
    "sg:phone":"+43 7474 2690",
    "sg:postcode":"3324",
    "sg:province":"Nieder\u00f6sterreich",
    "wof:name":"Bittner Ernst",
    "wof:placetype":"venue"
},
  "geometry": {"coordinates":[166.9221496582,-0.5282999873],"type":"Point"}
}