{
  "type": "Feature",
  "properties": {
    "iso:country":"AT",
    "sg:address":"Maggstr 15",
    "sg:city":"St. Peter",
    "sg:orig_category":"Farben U Lacke / Einzelhandel, Farben U Lacke / Erzeugung U Gro\u00c3\u0178handel",
    "sg:phone":"+43 316 4011220",
    "sg:postcode":"8042",
    "sg:province":"Steiermark",
    "wof:name":"Toyfl J GesmbH",
    "wof:placetype":"venue"
},
  "geometry": {"coordinates":[15.4792480469,47.0365753174],"type":"Point"}
}