{
  "type": "Feature",
  "properties": {
    "addr:full":"Ragnitzstr 177 Ragnitz Steiermark 8047",
    "addr:housenumber":"177",
    "addr:postcode":"8047",
    "iso:country":"AT",
    "sg:address":"Ragnitzstr 177",
    "sg:city":"Ragnitz",
    "sg:orig_category":"Textilreinigung",
    "sg:phone":"+43 316 303214",
    "sg:postcode":"8047",
    "sg:province":"Steiermark",
    "wof:name":"Zotter Helmut",
    "wof:placetype":"venue"
},
  "geometry": {"coordinates":[15.4983921051,47.0768508911],"type":"Point"}
}