{
  "type": "Feature",
  "properties": {
    "addr:full":"Nr 21 Echsenbach Nieder\u00f6sterreich 3903",
    "addr:postcode":"3903",
    "addr:street":"Nr;Echsenbach",
    "iso:country":"AT",
    "sg:address":"Nr 21",
    "sg:city":"Echsenbach",
    "sg:orig_category":"Diskotheken",
    "sg:phone":"+43 2849 3180",
    "sg:postcode":"3903",
    "sg:province":"Nieder\u00f6sterreich",
    "wof:name":"Rendezvous",
    "wof:placetype":"venue"
},
  "geometry": {"coordinates":[15.2179679871,48.717666626],"type":"Point"}
}