{
  "type": "Feature",
  "properties": {
    "addr:full":"Breitenfurter Str 77 Wien Wien 1120",
    "addr:postcode":"1120",
    "addr:street":"Str 77",
    "iso:country":"AT",
    "sg:address":"Breitenfurter Str 77",
    "sg:city":"Wien",
    "sg:orig_category":"Autovermietung",
    "sg:phone":"+43 4318 0420110",
    "sg:postcode":"1120",
    "sg:province":"Wien",
    "wof:name":"Autovermietung Charterline GmbH",
    "wof:placetype":"venue"
},
  "geometry": {"coordinates":[16.3197917938,48.168182373],"type":"Point"}
}