{
  "type": "Feature",
  "properties": {
    "iso:country":"AT",
    "sg:address":"Donaufelder Str 8",
    "sg:city":"Wien",
    "sg:orig_category":"Optiker",
    "sg:phone":"+43 1 2785150",
    "sg:postcode":"1210",
    "sg:province":"Wien",
    "wof:name":"Gutstein Optik GmbH",
    "wof:placetype":"venue"
},
  "geometry": {"coordinates":[16.4090194702,48.2545700073],"type":"Point"}
}