{
  "type": "Feature",
  "properties": {
    "addr:full":"Innsbrucker Bundesstr 53 Salzburg Salzburg 5020",
    "addr:housenumber":"53",
    "addr:postcode":"5020",
    "addr:street":"Salzburg",
    "iso:country":"AT",
    "sg:address":"Innsbrucker Bundesstr 53",
    "sg:city":"Salzburg",
    "sg:orig_category":"Massagen",
    "sg:phone":"+43 4366 43912067",
    "sg:postcode":"5020",
    "sg:province":"Salzburg",
    "wof:name":"Maxglaner Massageinstitut Salama",
    "wof:placetype":"venue"
},
  "geometry": {"coordinates":[13.0173873901,47.8017654419],"type":"Point"}
}