{
  "type": "Feature",
  "properties": {
    "iso:country":"AT",
    "sg:address":"Schulstr 15",
    "sg:city":"Pasching",
    "sg:orig_category":"Non-Classified Establishments",
    "sg:phone":"+43 7221 880150",
    "sg:postcode":"4061",
    "sg:province":"Ober\u00f6sterreich",
    "wof:name":"Pfarramt",
    "wof:placetype":"venue"
},
  "geometry": {"coordinates":[14.2002134323,48.2579727173],"type":"Point"}
}