{
  "type": "Feature",
  "properties": {
    "addr:full":"Lerchenfelder Str 70-72 Wien Wien 1080",
    "addr:postcode":"70-72;1080",
    "addr:street":"Lerchenfelder Str",
    "iso:country":"AT",
    "sg:address":"Lerchenfelder Str 70-72",
    "sg:city":"Wien",
    "sg:orig_category":"Massagen",
    "sg:phone":"+43 1 5240333",
    "sg:postcode":"1080",
    "sg:province":"Wien",
    "wof:name":"Massagefachinstitut Robert B",
    "wof:placetype":"venue"
},
  "geometry": {"coordinates":[16.3466720581,48.2070236206],"type":"Point"}
}