{
  "type": "Feature",
  "properties": {
    "addr:full":"Wickenburgg 18-20 Wien Wien 1080",
    "addr:postcode":"18-20;1080",
    "iso:country":"AT",
    "sg:address":"Wickenburgg 18-20",
    "sg:city":"Wien",
    "sg:orig_category":"Weiterbildungsinstitute M Allg U Berufl Bildungsangebot",
    "sg:phone":"+43 1 4088008",
    "sg:postcode":"1080",
    "sg:province":"Wien",
    "wof:name":"Fortbildungszentrum Strafvollzug",
    "wof:placetype":"venue"
},
  "geometry": {"coordinates":[16.3541603088,48.2136039734],"type":"Point"}
}