{
  "type": "Feature",
  "properties": {
    "addr:full":"St. Magdalener Str 91/4 St. Magdalen K\u00e4rnten 9524",
    "addr:housenumber":"91 / 4",
    "addr:postcode":"9524",
    "addr:street":"St.;Str;Kaernten",
    "iso:country":"AT",
    "sg:address":"St. Magdalener Str 91/4",
    "sg:city":"St. Magdalen",
    "sg:classifiers":[
        {
            "category":"Professional",
            "subcategory":"Computer Services",
            "type":"Services"
        }
    ],
    "sg:phone":"+43 664 3407494",
    "sg:postcode":"9524",
    "sg:province":"K\u00e4rnten",
    "sg:tags":[
        "software"
    ],
    "wof:name":"INDIsoftware",
    "wof:placetype":"venue"
},
  "geometry": {"coordinates":[13.8855457306,46.6142272949],"type":"Point"}
}