{
  "type": "Feature",
  "properties": {
    "addr:full":"Klagenfurter Str 3 Liebenfels K\u00e4rnten 9556",
    "addr:housenumber":"3",
    "addr:postcode":"9556",
    "addr:street":"Str;Kaernten",
    "iso:country":"AT",
    "sg:address":"Klagenfurter Str 3",
    "sg:city":"Liebenfels",
    "sg:orig_category":"Feuerwehren",
    "sg:phone":"+43 4215 2122",
    "sg:postcode":"9556",
    "sg:province":"K\u00e4rnten",
    "wof:name":"Freiwillige Feuerwehr Liebenfels",
    "wof:placetype":"venue"
},
  "geometry": {"coordinates":[14.2875375748,46.7376098633],"type":"Point"}
}