{
  "type": "Feature",
  "properties": {
    "addr:full":"Oberhof 1 Metnitz K\u00e4rnten 9363",
    "addr:housenumber":"1",
    "addr:postcode":"9363",
    "addr:street":"Oberhof;Kaernten",
    "iso:country":"AT",
    "sg:address":"Oberhof 1",
    "sg:city":"Metnitz",
    "sg:orig_category":"Lebensmittel / Einzelhandel",
    "sg:phone":"+43 4267 359",
    "sg:postcode":"9363",
    "sg:province":"K\u00e4rnten",
    "wof:name":"Spar-Markt Inh Erika Wolfger",
    "wof:placetype":"venue"
},
  "geometry": {"coordinates":[14.1433849335,46.9685401917],"type":"Point"}
}