{
  "type": "Feature",
  "properties": {
    "addr:full":"Nr 143 Rangersdorf K\u00e4rnten 9833",
    "addr:housenumber":"9833",
    "addr:street":"Nr",
    "iso:country":"AT",
    "sg:address":"Nr 143",
    "sg:city":"Rangersdorf",
    "sg:orig_category":"Innenausbau",
    "sg:phone":"+43 4822 7244",
    "sg:postcode":"9833",
    "sg:province":"K\u00e4rnten",
    "wof:name":"WSG Innenausbau GesmbH",
    "wof:placetype":"venue"
},
  "geometry": {"coordinates":[12.9637470245,46.8620872498],"type":"Point"}
}