{
  "type": "Feature",
  "properties": {
    "addr:full":"Larocheg 27 Wien Wien 1130",
    "addr:housenumber":"27",
    "addr:postcode":"1130",
    "addr:street":"Larocheg",
    "iso:country":"AT",
    "sg:address":"Larocheg 27",
    "sg:city":"Wien",
    "sg:orig_category":"Ingenieurkonsulenten / Zivilingenieure",
    "sg:phone":"+43 1 8779798",
    "sg:postcode":"1130",
    "sg:province":"Wien",
    "wof:name":"Hanisch Dipl-Ing ZT KEG",
    "wof:placetype":"venue"
},
  "geometry": {"coordinates":[16.2857208252,48.1849937439],"type":"Point"}
}