{
  "type": "Feature",
  "properties": {
    "addr:full":"Getreideg 3 Klagenfurt K\u00e4rnten 9020",
    "addr:housenumber":"3",
    "addr:postcode":"9020",
    "addr:street":"Getreideg;Kaernten",
    "iso:country":"AT",
    "sg:address":"Getreideg 3",
    "sg:city":"Klagenfurt",
    "sg:orig_category":"Steuerberatung",
    "sg:phone":"+43 463 579190",
    "sg:postcode":"9020",
    "sg:province":"K\u00e4rnten",
    "wof:name":"Naebe G\u00fcnter & Partner SteuerberatungsgesmbH",
    "wof:placetype":"venue"
},
  "geometry": {"coordinates":[14.3118343353,46.6250152588],"type":"Point"}
}