{
  "type": "Feature",
  "properties": {
    "addr:full":"Kle\u00dfheimer Allee 93 Salzburg Salzburg 5020",
    "addr:housenumber":"93",
    "addr:postcode":"5020",
    "addr:street":"Klessheimer Allee;Salzburg",
    "iso:country":"AT",
    "sg:address":"Kle\u00dfheimer Allee 93",
    "sg:city":"Salzburg",
    "sg:orig_category":"Schwangerenberatung / Geburtsvorbereitung",
    "sg:phone":"+43 662 440074",
    "sg:postcode":"5020",
    "sg:province":"Salzburg",
    "wof:name":"Elternberatung",
    "wof:placetype":"venue"
},
  "geometry": {"coordinates":[13.0050935745,47.8116645813],"type":"Point"}
}