{
  "type": "Feature",
  "properties": {
    "addr:full":"Manker Str 4 Kilb Nieder\u00f6sterreich 3233",
    "addr:housenumber":"4",
    "addr:postcode":"3233",
    "addr:street":"Str",
    "iso:country":"AT",
    "sg:address":"Manker Str 4",
    "sg:city":"Kilb",
    "sg:orig_category":"Sattler U Riemer",
    "sg:phone":"+43 4327 487237",
    "sg:postcode":"3233",
    "sg:province":"Nieder\u00f6sterreich",
    "wof:name":"Katzengruber Anton",
    "wof:placetype":"venue"
},
  "geometry": {"coordinates":[15.4051856995,48.1007461548],"type":"Point"}
}