{
  "type": "Feature",
  "properties": {
    "iso:country":"AT",
    "sg:address":"Linzer Str 141",
    "sg:city":"Marchtrenk",
    "sg:orig_category":"Metallbau",
    "sg:phone":"+43 7243 582220",
    "sg:postcode":"4614",
    "sg:province":"Ober\u00f6sterreich",
    "wof:name":"Hammerschmid Christian",
    "wof:placetype":"venue"
},
  "geometry": {"coordinates":[14.1369838715,48.1961746216],"type":"Point"}
}