{
  "type": "Feature",
  "properties": {
    "addr:full":"Ein\u00f6dstr 39 Pfaffst\u00e4tten Nieder\u00f6sterreich 2511",
    "addr:housenumber":"39",
    "addr:postcode":"2511",
    "addr:street":"Einoedstr;Niederoesterreich",
    "iso:country":"AT",
    "sg:address":"Ein\u00f6dstr 39",
    "sg:city":"Pfaffst\u00e4tten",
    "sg:classifiers":[
        {
            "category":"Taxi",
            "type":"Transportation"
        }
    ],
    "sg:phone":"+43 4322 5288388",
    "sg:postcode":"2511",
    "sg:province":"Nieder\u00f6sterreich",
    "sg:tags":[
        "personentransporte",
        "u"
    ],
    "wof:name":"Hirsch Robert",
    "wof:placetype":"venue"
},
  "geometry": {"coordinates":[-80.22747802729999,40.6339416504],"type":"Point"}
}