{
  "type": "Feature",
  "properties": {
    "iso:country":"AT",
    "sg:address":"Gilmstr 23",
    "sg:city":"Linz",
    "sg:orig_category":"Bauunternehmen",
    "sg:phone":"+43 4373 26616010",
    "sg:postcode":"4020",
    "sg:province":"Ober\u00f6sterreich",
    "wof:name":"Bau Know How Hofmeister GmbH & Co KEG",
    "wof:placetype":"venue"
},
  "geometry": {"coordinates":[14.3159608841,48.2930679321],"type":"Point"}
}