{
  "type": "Feature",
  "properties": {
    "iso:country":"AT",
    "sg:address":"Gemeindebergg 63-65",
    "sg:city":"Wien",
    "sg:orig_category":"Baumpflege, -Schutz U -Chirurgie",
    "sg:phone":"+43 4318 799999",
    "sg:postcode":"1130",
    "sg:province":"Wien",
    "wof:name":"Noll Otto",
    "wof:placetype":"venue"
},
  "geometry": {"coordinates":[16.2629928589,48.1778717041],"type":"Point"}
}