{
  "type": "Feature",
  "properties": {
    "addr:full":"Reitdorf 69 Flachau Salzburg 5542",
    "addr:housenumber":"69",
    "addr:postcode":"5542",
    "addr:street":"Reitdorf;Salzburg",
    "iso:country":"AT",
    "sg:address":"Reitdorf 69",
    "sg:city":"Flachau",
    "sg:orig_category":"Pensionen / Privatzimmer",
    "sg:phone":"+43 6457 2264",
    "sg:postcode":"5542",
    "sg:province":"Salzburg",
    "wof:name":"Pension Koller",
    "wof:placetype":"venue"
},
  "geometry": {"coordinates":[13.3865442276,47.3692092896],"type":"Point"}
}