{
  "type": "Feature",
  "properties": {
    "addr:full":"Ges\u00e4use Bundesstr 26 Liezen Steiermark 8940",
    "addr:housenumber":"26",
    "addr:postcode":"8940",
    "iso:country":"AT",
    "sg:address":"Ges\u00e4use Bundesstr 26",
    "sg:city":"Liezen",
    "sg:orig_category":"Betten",
    "sg:phone":"+43 3612 240090",
    "sg:postcode":"8940",
    "sg:province":"Steiermark",
    "wof:name":"D\u00e4nisches Bettenlager HandelsgesmbH",
    "wof:placetype":"venue"
},
  "geometry": {"coordinates":[14.2806739807,47.5633392334],"type":"Point"}
}