{
  "type": "Feature",
  "properties": {
    "addr:full":"Nr 179 Mogersdorf Burgenland 8382",
    "addr:postcode":"8382",
    "addr:street":"Nr 179 Mogersdorf",
    "iso:country":"AT",
    "sg:address":"Nr 179",
    "sg:city":"Mogersdorf",
    "sg:orig_category":"Polizei U Gendarmerie",
    "sg:phone":"+43 4359 1331215",
    "sg:postcode":"8382",
    "sg:province":"Burgenland",
    "wof:name":"Gendarmerie Grenz\u00fcberwachungsposten",
    "wof:placetype":"venue"
},
  "geometry": {"coordinates":[16.2301654816,46.9476585388],"type":"Point"}
}