{
  "type": "Feature",
  "properties": {
    "addr:full":"Dorrekstr 2 Hallein Salzburg 5400",
    "addr:housenumber":"2",
    "addr:postcode":"5400",
    "addr:street":"Dorrekstr;Salzburg",
    "iso:country":"AT",
    "sg:address":"Dorrekstr 2",
    "sg:city":"Hallein",
    "sg:orig_category":"Feng-Shui",
    "sg:phone":"+43 6245 75545",
    "sg:postcode":"5400",
    "sg:province":"Salzburg",
    "wof:name":"Balance Institut Freuen - Schaffenrath Ulrike",
    "wof:placetype":"venue"
},
  "geometry": {"coordinates":[13.0926103592,47.6814613342],"type":"Point"}
}