{
  "type": "Feature",
  "properties": {
    "iso:country":"AT",
    "sg:address":"Nr 155",
    "sg:city":"Weitensfeld",
    "sg:orig_category":"Bauunternehmen",
    "sg:phone":"+43 4265 2900",
    "sg:postcode":"9344",
    "sg:province":"K\u00e4rnten",
    "wof:name":"Merl Adolf",
    "wof:placetype":"venue"
},
  "geometry": {"coordinates":[14.193403244,46.8474197388],"type":"Point"}
}