{
  "type": "Feature",
  "properties": {
    "iso:country":"AT",
    "sg:address":"Ketzerg. 4 ",
    "sg:city":"Wien",
    "sg:classifiers":[
        {
            "category":"Manufacturing",
            "subcategory":"Paper Products",
            "type":"Manufacturing & Wholesale Goods"
        }
    ],
    "sg:phone":"+43 4318 63060",
    "sg:postcode":"1230",
    "sg:province":"Wien",
    "sg:tags":[
        "cardboard"
    ],
    "wof:name":"MOSBURGER GMBH",
    "wof:placetype":"venue"
},
  "geometry": {"coordinates":[16.3187599182,48.1258354187],"type":"Point"}
}