{
  "type": "Feature",
  "properties": {
    "iso:country":"AT",
    "sg:address":"Opernring 9",
    "sg:city":"Graz",
    "sg:orig_category":"Fotoapparate U -Artikel / Einzelhandel",
    "sg:phone":"+43 316 829900",
    "sg:postcode":"8010",
    "sg:province":"Steiermark",
    "sg:website":"www.classiccamera.at",
    "wof:name":"Classic Camera Glawogger & H\u00f6lzl OEG",
    "wof:placetype":"venue"
},
  "geometry": {"coordinates":[15.4437236786,47.0681762695],"type":"Point"}
}