{
  "type": "Feature",
  "properties": {
    "iso:country":"AT",
    "sg:address":"Wiedner Hauptstr 73",
    "sg:city":"Wien",
    "sg:orig_category":"Institute",
    "sg:phone":"+43 1 50300501700",
    "sg:postcode":"1040",
    "sg:province":"Wien",
    "wof:name":"Austria Perspektiv - Ein Institut der \u00f6sterreichischen Wirtschaft",
    "wof:placetype":"venue"
},
  "geometry": {"coordinates":[16.365486145,48.1888427734],"type":"Point"}
}