{
  "type": "Feature",
  "properties": {
    "addr:full":"Wiedner Hauptstr 73 Wien Wien 1040",
    "addr:housenumber":"73",
    "addr:postcode":"1040",
    "addr:street":"Hauptstr",
    "iso:country":"AT",
    "sg:address":"Wiedner Hauptstr 73",
    "sg:city":"Wien",
    "sg:orig_category":"Institute",
    "sg:phone":"+43 1 50300501700",
    "sg:postcode":"1040",
    "sg:province":"Wien",
    "wof:name":"Austria Perspektiv - Ein Institut der \u00f6sterreichischen Wirtschaft",
    "wof:placetype":"venue"
},
  "geometry": {"coordinates":[16.365486145,48.1888427734],"type":"Point"}
}