{
  "type": "Feature",
  "properties": {
    "addr:full":"Hauptpl 2 Baden Nieder\u00f6sterreich 2500",
    "addr:housenumber":"2",
    "addr:postcode":"2500",
    "addr:street":"Hauptpl;Niederoesterreich",
    "iso:country":"AT",
    "sg:address":"Hauptpl 2",
    "sg:city":"Baden",
    "sg:orig_category":"Tabaktrafiken",
    "sg:phone":"+43 2252 48669",
    "sg:postcode":"2500",
    "sg:province":"Nieder\u00f6sterreich",
    "wof:name":"Meixner Erwin",
    "wof:placetype":"venue"
},
  "geometry": {"coordinates":[16.2341079712,48.007976532],"type":"Point"}
}