{
  "type": "Feature",
  "properties": {
    "iso:country":"AT",
    "sg:address":"Sch\u00e4rdinger Str 1",
    "sg:city":"St. Marienkirchen",
    "sg:orig_category":"Gemeinden",
    "sg:phone":"+43 4377 112254",
    "sg:postcode":"4774",
    "sg:province":"Ober\u00f6sterreich",
    "wof:name":"Gemeindeamt St Marienkirchen bei Sch\u00e4rding",
    "wof:placetype":"venue"
},
  "geometry": {"coordinates":[13.4512290955,48.3879585266],"type":"Point"}
}