{
  "type": "Feature",
  "properties": {
    "addr:full":"Hauptstr 26 Gaspoltshofen Ober\u00f6sterreich 4673",
    "addr:housenumber":"26",
    "addr:postcode":"4673",
    "addr:street":"Hauptstr",
    "iso:country":"AT",
    "sg:address":"Hauptstr 26",
    "sg:city":"Gaspoltshofen",
    "sg:orig_category":"Tabaktrafiken",
    "sg:phone":"+43 7735 6864",
    "sg:postcode":"4673",
    "sg:province":"Ober\u00f6sterreich",
    "wof:name":"Haslinger Ingrid",
    "wof:placetype":"venue"
},
  "geometry": {"coordinates":[13.736664772,48.1420593262],"type":"Point"}
}