{
  "type": "Feature",
  "properties": {
    "iso:country":"AT",
    "sg:address":"Rudolf Henke-Str 7",
    "sg:city":"Wien",
    "sg:classifiers":[
        {
            "category":"Professional",
            "subcategory":"Computer Services",
            "type":"Services"
        }
    ],
    "sg:phone":"+43 1 97921950",
    "sg:postcode":"1140",
    "sg:province":"Wien",
    "sg:tags":[
        "software"
    ],
    "wof:name":"Aigner Herbert",
    "wof:placetype":"venue"
},
  "geometry": {"coordinates":[16.2400054932,48.2054748535],"type":"Point"}
}