{
  "type": "Feature",
  "properties": {
    "iso:country":"AT",
    "sg:address":"Turnwiesen 10/1",
    "sg:city":"St. Florian",
    "sg:orig_category":"Massagen",
    "sg:phone":"+43 4367 67744838",
    "sg:postcode":"4490",
    "sg:province":"Ober\u00f6sterreich",
    "wof:name":"Mobile Massage & Energetik Regina Kapeller",
    "wof:placetype":"venue"
},
  "geometry": {"coordinates":[14.3731927872,48.2028274536],"type":"Point"}
}