{
  "type": "Feature",
  "properties": {
    "addr:full":"Nr 3 Regau Ober\u00f6sterreich 4844",
    "addr:postcode":"4844",
    "addr:street":"Nr;Regau Oberoesterreich",
    "iso:country":"AT",
    "sg:address":"Nr 3",
    "sg:city":"Regau",
    "sg:orig_category":"Tabaktrafiken",
    "sg:phone":"+43 767223396",
    "sg:postcode":"4844",
    "sg:province":"Ober\u00f6sterreich",
    "wof:name":"Holzinger Ingrid",
    "wof:placetype":"venue"
},
  "geometry": {"coordinates":[13.689125061,47.9909744263],"type":"Point"}
}