{
  "type": "Feature",
  "properties": {
    "addr:full":"Lerchenfeldstr 9 Timelkam Ober\u00f6sterreich 4850",
    "addr:housenumber":"9",
    "addr:postcode":"4850",
    "addr:street":"Lerchenfeldstr",
    "iso:country":"AT",
    "sg:address":"Lerchenfeldstr 9",
    "sg:city":"Timelkam",
    "sg:orig_category":"Blumeneinzelhandel",
    "sg:phone":"+43 767292082",
    "sg:postcode":"4850",
    "sg:province":"Ober\u00f6sterreich",
    "wof:name":"Blumen Gebetsroither",
    "wof:placetype":"venue"
},
  "geometry": {"coordinates":[13.6096162796,48.0019683838],"type":"Point"}
}