{
  "type": "Feature",
  "properties": {
    "iso:country":"AT",
    "sg:address":"Rathauspl 16",
    "sg:city":"Rust",
    "sg:orig_category":"Non-Classified Establishments",
    "sg:phone":"+43 2685 295",
    "sg:postcode":"7071",
    "sg:province":"Burgenland",
    "wof:name":"Pfarramt",
    "wof:placetype":"venue"
},
  "geometry": {"coordinates":[16.6748313904,47.8000793457],"type":"Point"}
}