{
  "type": "Feature",
  "properties": {
    "addr:full":"Nr 41a Bad Hofgastein Salzburg 5630",
    "addr:housenumber":"41a",
    "addr:postcode":"5630",
    "addr:street":"Nr;Salzburg",
    "iso:country":"AT",
    "sg:address":"Nr 41a",
    "sg:city":"Bad Hofgastein",
    "sg:classifiers":[
        {
            "category":"Professional",
            "subcategory":"Computer Services",
            "type":"Services"
        }
    ],
    "sg:phone":"+43 6432 85095",
    "sg:postcode":"5630",
    "sg:province":"Salzburg",
    "sg:tags":[
        "software"
    ],
    "wof:name":"ProSelect - Weilharter Wolfgang",
    "wof:placetype":"venue"
},
  "geometry": {"coordinates":[13.1028347015,47.1707115173],"type":"Point"}
}