{
  "type": "Feature",
  "properties": {
    "iso:country":"AT",
    "sg:address":"Nr 125",
    "sg:city":"St. Stefan ob Stainz",
    "sg:classifiers":[
        {
            "category":"Taxi",
            "type":"Transportation"
        }
    ],
    "sg:phone":"+43 4334 636404",
    "sg:postcode":"8511",
    "sg:province":"Steiermark",
    "sg:tags":[
        "personentransporte",
        "u"
    ],
    "wof:name":"Taxi Prall",
    "wof:placetype":"venue"
},
  "geometry": {"coordinates":[15.2549381256,46.9294662476],"type":"Point"}
}