{
  "type": "Feature",
  "properties": {
    "addr:full":"Gewerbestr 15 Wiener Neudorf Nieder\u00f6sterreich 2351",
    "addr:housenumber":"15",
    "addr:postcode":"2351",
    "addr:street":"Gewerbestr",
    "iso:country":"AT",
    "sg:address":"Gewerbestr 15",
    "sg:city":"Wiener Neudorf",
    "sg:orig_category":"Architekten",
    "sg:phone":"+43 2236 62170",
    "sg:postcode":"2351",
    "sg:province":"Nieder\u00f6sterreich",
    "wof:name":"Kronreif & Partner ZT GesmbH",
    "wof:placetype":"venue"
},
  "geometry": {"coordinates":[16.3183326721,48.0863113403],"type":"Point"}
}