{
  "type": "Feature",
  "properties": {
    "iso:country":"AT",
    "sg:address":"Burgstall 363",
    "sg:city":"Mayrhofen",
    "sg:orig_category":"Appartements / Ferienwohnungen",
    "sg:phone":"+43 4352 8563383",
    "sg:postcode":"6290",
    "sg:province":"Tirol",
    "wof:name":"Ferienwohnung Gredler",
    "wof:placetype":"venue"
},
  "geometry": {"coordinates":[11.8624277115,47.1670684814],"type":"Point"}
}