{
  "type": "Feature",
  "properties": {
    "addr:full":"Oetzerau Oetz Tirol 6433",
    "addr:postcode":"6433",
    "addr:street":"Oetzerau;Tirol",
    "iso:country":"AT",
    "sg:address":"Oetzerau",
    "sg:city":"Oetz",
    "sg:orig_category":"Feuerwehren",
    "sg:phone":"+43 5252 2177",
    "sg:postcode":"6433",
    "sg:province":"Tirol",
    "wof:name":"Freiwillige Feuerwehr",
    "wof:placetype":"venue"
},
  "geometry": {"coordinates":[10.8796701431,47.2123718262],"type":"Point"}
}