{
  "type": "Feature",
  "properties": {
    "addr:full":"Hausgrundweg 4 Wien Wien 1220",
    "addr:housenumber":"4",
    "addr:postcode":"1220",
    "addr:street":"Hausgrundweg",
    "iso:country":"AT",
    "sg:address":"Hausgrundweg 4",
    "sg:city":"Wien",
    "sg:orig_category":"Lebensmittel / Einzelhandel",
    "sg:phone":"+43 4312 821373",
    "sg:postcode":"1220",
    "sg:province":"Wien",
    "wof:name":"SPAR \u00f6sterreichische Warenhandels-AG",
    "wof:placetype":"venue"
},
  "geometry": {"coordinates":[16.4558525085,48.2275543213],"type":"Point"}
}