{
  "type": "Feature",
  "properties": {
    "iso:country":"AT",
    "sg:address":"Konrad-Lorenz-Str 20",
    "sg:city":"Tulln an der Donau",
    "sg:orig_category":"Forschungsinstitute",
    "sg:phone":"+43 2272 66280109",
    "sg:postcode":"3430",
    "sg:province":"Nieder\u00f6sterreich",
    "wof:name":"Universit\u00e4t f Bodenkultur Wien-Department IFA-Tulln-Interuniversit\u00e4res Forschungsinstitut",
    "wof:placetype":"venue"
},
  "geometry": {"coordinates":[16.0654659271,48.320640564],"type":"Point"}
}