{
  "type": "Feature",
  "properties": {
    "iso:country":"AT",
    "sg:address":"Kielmannsegg 14",
    "sg:city":"Korneuburg",
    "sg:orig_category":"Physiotherapie",
    "sg:phone":"+43 2262 61588",
    "sg:postcode":"2100",
    "sg:province":"Nieder\u00f6sterreich",
    "wof:name":"Lennarts Elisabeth Dipl-PT",
    "wof:placetype":"venue"
},
  "geometry": {"coordinates":[16.3382377625,48.3414421082],"type":"Point"}
}