{
  "type": "Feature",
  "properties": {
    "addr:full":"Grazer Str 44 Wiener Neustadt Nieder\u00f6sterreich 2700",
    "addr:postcode":"2700",
    "addr:street":"Str 44",
    "iso:country":"AT",
    "sg:address":"Grazer Str 44",
    "sg:city":"Wiener Neustadt",
    "sg:orig_category":"Bars-Cafes",
    "sg:phone":"+43 2622 66050",
    "sg:postcode":"2700",
    "sg:province":"Nieder\u00f6sterreich",
    "wof:name":"Legenstein GesmbH",
    "wof:placetype":"venue"
},
  "geometry": {"coordinates":[16.2470188141,47.8172111511],"type":"Point"}
}