{
  "type": "Feature",
  "properties": {
    "addr:full":"Koppstrasse 27-29 Wien Wien 1160",
    "addr:postcode":"27-29;1160",
    "addr:street":"Koppstrasse",
    "iso:country":"AT",
    "sg:address":"Koppstrasse 27-29",
    "sg:city":"Wien",
    "sg:classifiers":[
        {
            "category":"Banks & Credit Unions",
            "subcategory":"Investment Brokerage",
            "type":"Services"
        }
    ],
    "sg:phone":"+43 1 49258210",
    "sg:postcode":"1160",
    "sg:province":"Wien",
    "sg:tags":[
        "bag",
        "briefcase"
    ],
    "sg:website":"schneiders-vienna.at",
    "wof:name":"Schneiders Vienna Ges.m.b.H.",
    "wof:placetype":"venue"
},
  "geometry": {"coordinates":[16.3306064606,48.2069778442],"type":"Point"}
}