{
  "type": "Feature",
  "properties": {
    "addr:full":"Landstr 3 Lochau Vorarlberg 6911",
    "addr:housenumber":"3",
    "addr:postcode":"6911",
    "addr:street":"Landstr",
    "iso:country":"AT",
    "sg:address":"Landstr 3",
    "sg:city":"Lochau",
    "sg:classifiers":[
        {
            "category":"Utilities",
            "subcategory":"Refuse",
            "type":"Services"
        }
    ],
    "sg:phone":"+43 5574 44151",
    "sg:postcode":"6911",
    "sg:province":"Vorarlberg",
    "sg:tags":[
        "catering"
    ],
    "wof:name":"CAT&CO Catering-Partyservice",
    "wof:placetype":"venue"
},
  "geometry": {"coordinates":[9.7513332367,47.5309257507],"type":"Point"}
}