{
  "type": "Feature",
  "properties": {
    "addr:full":"Bernreit 26 Rohrbach an der G\u00f6lsen Nieder\u00f6sterreich 3163",
    "addr:housenumber":"26",
    "addr:postcode":"3163",
    "addr:street":"Bernreit;Niederoesterreich",
    "iso:country":"AT",
    "sg:address":"Bernreit 26",
    "sg:city":"Rohrbach an der G\u00f6lsen",
    "sg:orig_category":"Cad/Cae/Cam/Cim-Systeme",
    "sg:phone":"+43 2764 77099",
    "sg:postcode":"3163",
    "sg:province":"Nieder\u00f6sterreich",
    "wof:name":"INDAT Eberl & Leopold OEG",
    "wof:placetype":"venue"
},
  "geometry": {"coordinates":[15.7436361313,48.0416183472],"type":"Point"}
}