{
  "type": "Feature",
  "properties": {
    "iso:country":"AT",
    "sg:address":"Mayrhansenstr 30",
    "sg:city":"Leonding",
    "sg:orig_category":"Installationsunternehmen",
    "sg:phone":"+43 732 670081",
    "sg:postcode":"4060",
    "sg:province":"Ober\u00f6sterreich",
    "wof:name":"Eibensteiner Rudolf",
    "wof:placetype":"venue"
},
  "geometry": {"coordinates":[14.2523241043,48.2761917114],"type":"Point"}
}