{
  "type": "Feature",
  "properties": {
    "iso:country":"AT",
    "sg:address":"Untere Hauptstr 39",
    "sg:city":"Illmitz",
    "sg:orig_category":"Pensionen / Privatzimmer",
    "sg:phone":"+43 2175 3555",
    "sg:postcode":"7142",
    "sg:province":"Burgenland",
    "wof:name":"G\u00e4stehaus Schwalbennest Fam W\u00fcger",
    "wof:placetype":"venue"
},
  "geometry": {"coordinates":[16.7995376587,47.7586631775],"type":"Point"}
}