{
  "type": "Feature",
  "properties": {
    "iso:country":"AT",
    "sg:address":"Schlo\u00df",
    "sg:city":"Eckartsau",
    "sg:orig_category":"Forstverwaltungen",
    "sg:phone":"+43 2214 2240",
    "sg:postcode":"2305",
    "sg:province":"Nieder\u00f6sterreich",
    "wof:name":"Nationalpark-Forstverwaltung Eckartsau d \u00f6sterr Bundesforste AG",
    "wof:placetype":"venue"
},
  "geometry": {"coordinates":[16.7903671265,48.13697052],"type":"Point"}
}