{
  "type": "Feature",
  "properties": {
    "addr:full":"Franzosengraben 12 Wien Wien 1030",
    "addr:housenumber":"12",
    "addr:postcode":"1030",
    "addr:street":"Franzosengraben",
    "iso:country":"AT",
    "sg:address":"Franzosengraben 12",
    "sg:city":"Wien",
    "sg:orig_category":"Bekleidung / Erzeugung U Gro\u00c3\u0178handel",
    "sg:phone":"+43 1 7969700",
    "sg:postcode":"1030",
    "sg:province":"Wien",
    "wof:name":"EHAG Modevertrieb GmbH",
    "wof:placetype":"venue"
},
  "geometry": {"coordinates":[16.4138774872,48.1881790161],"type":"Point"}
}