{
  "type": "Feature",
  "properties": {
    "addr:full":"Schillinghofstrasse 41 Gnigl Salzburg 5023",
    "addr:housenumber":"41",
    "addr:postcode":"5023",
    "addr:street":"Schillinghofstrasse",
    "iso:country":"AT",
    "sg:address":"Schillinghofstrasse 41",
    "sg:city":"Gnigl",
    "sg:classifiers":[
        {
            "category":"Organizations",
            "subcategory":"Religious Organization",
            "type":"Services"
        }
    ],
    "sg:phone":"+43 662 640649",
    "sg:postcode":"5023",
    "sg:province":"Salzburg",
    "sg:tags":[
        "items",
        "brass",
        "artisan"
    ],
    "sg:website":"otto-baeuml.at",
    "wof:name":"Otto B\u00e4uml G\u00fcrtlerei",
    "wof:placetype":"venue"
},
  "geometry": {"coordinates":[13.0647859573,47.8196792603],"type":"Point"}
}