{
  "type": "Feature",
  "properties": {
    "addr:full":"G\u00f6sser Str 5 Leoben Steiermark 8700",
    "addr:housenumber":"5",
    "addr:postcode":"8700",
    "addr:street":"Str",
    "iso:country":"AT",
    "sg:address":"G\u00f6sser Str 5",
    "sg:city":"Leoben",
    "sg:orig_category":"Non-Classified Establishments",
    "sg:phone":"+43 3842 27204",
    "sg:postcode":"8700",
    "sg:province":"Steiermark",
    "wof:name":"Evangelisch-Freikirchliche Gemeinde",
    "wof:placetype":"venue"
},
  "geometry": {"coordinates":[15.0939130783,47.3785667419],"type":"Point"}
}