{
  "type": "Feature",
  "properties": {
    "iso:country":"AT",
    "sg:address":"Villacher Str 55",
    "sg:city":"Velden am W\u00f6rther See",
    "sg:orig_category":"Tankstellen",
    "sg:phone":"+43 4342 742482",
    "sg:postcode":"9220",
    "sg:province":"K\u00e4rnten",
    "wof:name":"Agip Austria GmbH",
    "wof:placetype":"venue"
},
  "geometry": {"coordinates":[14.0306739807,46.6117210388],"type":"Point"}
}