{
  "type": "Feature",
  "properties": {
    "addr:full":"Tiefenbachg 14 Schwechat Nieder\u00f6sterreich 2320",
    "addr:housenumber":"14",
    "addr:postcode":"2320",
    "addr:street":"Tiefenbachg;Niederoesterreich",
    "iso:country":"AT",
    "sg:address":"Tiefenbachg 14",
    "sg:city":"Schwechat",
    "sg:orig_category":"Werbegrafik- U Grafik-Design",
    "sg:phone":"+43 1 7065310",
    "sg:postcode":"2320",
    "sg:province":"Nieder\u00f6sterreich",
    "wof:name":"Kopleder KEG",
    "wof:placetype":"venue"
},
  "geometry": {"coordinates":[16.4804897308,48.1430053711],"type":"Point"}
}