{
  "type": "Feature",
  "properties": {
    "addr:full":"Unterstinkenbrunn Nieder\u00f6sterreich 2154",
    "addr:postcode":"2154",
    "addr:street":"Niederoesterreich",
    "iso:country":"AT",
    "sg:city":"Unterstinkenbrunn",
    "sg:orig_category":"Feuerwehren",
    "sg:phone":"+43 2522 88217",
    "sg:postcode":"2154",
    "sg:province":"Nieder\u00f6sterreich",
    "wof:name":"Freiwillige Feuerwehr Gaubitsch",
    "wof:placetype":"venue"
},
  "geometry": {"coordinates":[16.3802204132,48.6551513672],"type":"Point"}
}