{
  "type": "Feature",
  "properties": {
    "addr:full":"Oberhoferstr 34 Mistelbach Nieder\u00f6sterreich 2130",
    "addr:housenumber":"34",
    "addr:postcode":"2130",
    "addr:street":"Oberhoferstr;Niederoesterreich",
    "iso:country":"AT",
    "sg:address":"Oberhoferstr 34",
    "sg:city":"Mistelbach",
    "sg:orig_category":"Politische Parteien",
    "sg:phone":"+43 2572 4287",
    "sg:postcode":"2130",
    "sg:province":"Nieder\u00f6sterreich",
    "wof:name":"Freiheitliches B\u00fcndnisb\u00fcro Weinviertel",
    "wof:placetype":"venue"
},
  "geometry": {"coordinates":[16.5723075867,48.5722045898],"type":"Point"}
}