{
  "type": "Feature",
  "properties": {
    "addr:full":"Bahnhof Spielfeld Steiermark 8471",
    "addr:postcode":"8471",
    "iso:country":"AT",
    "sg:address":"Bahnhof",
    "sg:city":"Spielfeld",
    "sg:orig_category":"Non-Classified Establishments",
    "sg:phone":"+43 5 91336174",
    "sg:postcode":"8471",
    "sg:province":"Steiermark",
    "wof:name":"Bundesgendarmerie Grenzkontrollstelle Spielfeld-Bahnhof",
    "wof:placetype":"venue"
},
  "geometry": {"coordinates":[15.6304121017,46.7054443359],"type":"Point"}
}