{
  "type": "Feature",
  "properties": {
    "addr:full":"Stadtpl 16 Schwanenstadt Ober\u00f6sterreich 4690",
    "addr:housenumber":"16",
    "addr:postcode":"4690",
    "addr:street":"Stadtpl",
    "iso:country":"AT",
    "sg:address":"Stadtpl 16",
    "sg:city":"Schwanenstadt",
    "sg:orig_category":"Bekleidung / Einzelhandel",
    "sg:phone":"+43 76735090",
    "sg:postcode":"4690",
    "sg:province":"Ober\u00f6sterreich",
    "wof:name":"Sicka-Kleidung Johann Sickinger GmbH",
    "wof:placetype":"venue"
},
  "geometry": {"coordinates":[13.7744493484,48.055065155],"type":"Point"}
}