{
  "type": "Feature",
  "properties": {
    "iso:country":"AT",
    "sg:address":"Johann-B\u00f6hm-Str 35a",
    "sg:city":"Kapfenberg",
    "sg:orig_category":"Lebensmittel / Einzelhandel",
    "sg:phone":"+43 4338 62234640",
    "sg:postcode":"8605",
    "sg:province":"Steiermark",
    "wof:name":"ADEG Aktiv Markt",
    "wof:placetype":"venue"
},
  "geometry": {"coordinates":[15.3106584549,47.4477844238],"type":"Point"}
}