{
  "type": "Feature",
  "properties": {
    "addr:full":"Gmundner Str 4 Schwanenstadt Ober\u00f6sterreich 4690",
    "addr:housenumber":"4",
    "addr:postcode":"4690",
    "addr:street":"Str",
    "iso:country":"AT",
    "sg:address":"Gmundner Str 4",
    "sg:city":"Schwanenstadt",
    "sg:orig_category":"Tabaktrafiken",
    "sg:phone":"+43 76732923",
    "sg:postcode":"4690",
    "sg:province":"Ober\u00f6sterreich",
    "wof:name":"Deixler Alfred jr",
    "wof:placetype":"venue"
},
  "geometry": {"coordinates":[13.7775392532,48.0508384705],"type":"Point"}
}