{
  "type": "Feature",
  "properties": {
    "addr:full":"Gallerweg 18 Lannach Steiermark 8502",
    "addr:housenumber":"18",
    "addr:postcode":"8502",
    "addr:street":"Gallerweg",
    "iso:country":"AT",
    "sg:address":"Gallerweg 18",
    "sg:city":"Lannach",
    "sg:orig_category":"Friseure U Frisiersalons",
    "sg:phone":"+43 3136 81041",
    "sg:postcode":"8502",
    "sg:province":"Steiermark",
    "wof:name":"Fris\u00f6r Christin",
    "wof:placetype":"venue"
},
  "geometry": {"coordinates":[15.3312129974,46.9467582703],"type":"Point"}
}