{
  "type": "Feature",
  "properties": {
    "iso:country":"AT",
    "sg:address":"Hauptstr 24",
    "sg:city":"Mannersdorf an der Rabnitz",
    "sg:orig_category":"Fleischhauereien",
    "sg:phone":"+43 2611 2205",
    "sg:postcode":"7444",
    "sg:province":"Burgenland",
    "wof:name":"T\u00f6pfer Ernst",
    "wof:placetype":"venue"
},
  "geometry": {"coordinates":[16.5268306732,47.4284439087],"type":"Point"}
}