{
  "type": "Feature",
  "properties": {
    "addr:full":"Margaretenstr. 112 Wien Wien 1050",
    "addr:housenumber":"112",
    "addr:postcode":"1050",
    "iso:country":"AT",
    "sg:address":"Margaretenstr. 112",
    "sg:city":"Wien",
    "sg:classifiers":[
        {
            "category":"Wholesale",
            "subcategory":"Machinery & Supplies",
            "type":"Manufacturing & Wholesale Goods"
        }
    ],
    "sg:phone":"+43 4315 46260",
    "sg:postcode":"1050",
    "sg:province":"Wien",
    "sg:tags":[
        "equipment",
        "-",
        "instrument",
        "measurement"
    ],
    "wof:name":"SCHIEBEL ELEKTRONISCHE GER\u00c4TE GMBH",
    "wof:placetype":"venue"
},
  "geometry": {"coordinates":[16.3540210724,48.1888504028],"type":"Point"}
}