{
  "type": "Feature",
  "properties": {
    "addr:full":"Bergwerkstr. 22 PF 126  Schwaz Tirol 6130",
    "addr:housenumber":"22",
    "addr:postcode":"126;6130",
    "addr:street":"Bergwerkstr.;Tirol",
    "iso:country":"AT",
    "sg:address":"Bergwerkstr. 22 PF 126 ",
    "sg:city":"Schwaz",
    "sg:classifiers":[
        {
            "category":"Wholesale",
            "subcategory":"Drugs",
            "type":"Manufacturing & Wholesale Goods"
        }
    ],
    "sg:phone":"+43 4352 4269220",
    "sg:postcode":"6130",
    "sg:province":"Tirol",
    "sg:tags":[
        "chemical",
        "pharmaceutical"
    ],
    "wof:name":"ADLER - WERK LACKFABRICK JOHANN BERGHOFER GESMBH & CO KG",
    "wof:placetype":"venue"
},
  "geometry": {"coordinates":[11.7071990967,47.3454208374],"type":"Point"}
}