{
  "type": "Feature",
  "properties": {
    "addr:full":"Lastenstr 2 Ferlach K\u00e4rnten 9170",
    "addr:housenumber":"2",
    "addr:postcode":"9170",
    "addr:street":"Lastenstr;Kaernten",
    "iso:country":"AT",
    "sg:address":"Lastenstr 2",
    "sg:city":"Ferlach",
    "sg:orig_category":"Installationsunternehmen",
    "sg:phone":"+43 4227 22080",
    "sg:postcode":"9170",
    "sg:province":"K\u00e4rnten",
    "wof:name":"Berger Sanit\u00e4r- und HeizungsgesmbH",
    "wof:placetype":"venue"
},
  "geometry": {"coordinates":[14.3045148849,46.525062561],"type":"Point"}
}