{
  "type": "Feature",
  "properties": {
    "addr:full":"Sobieskig 29/3/33 Wien Wien 1090",
    "addr:housenumber":"29 / 3 / 33",
    "addr:postcode":"1090",
    "addr:street":"Sobieskig",
    "iso:country":"AT",
    "sg:address":"Sobieskig 29/3/33",
    "sg:city":"Wien",
    "sg:orig_category":"Werbeagenturen",
    "sg:phone":"+43 1 3157460",
    "sg:postcode":"1090",
    "sg:province":"Wien",
    "wof:name":"Stella KEG",
    "wof:placetype":"venue"
},
  "geometry": {"coordinates":[16.351474762,48.2234115601],"type":"Point"}
}