{
  "type": "Feature",
  "properties": {
    "addr:full":"Bahnstr 12 Altach Vorarlberg 6844",
    "addr:housenumber":"12",
    "addr:postcode":"6844",
    "addr:street":"Bahnstr",
    "iso:country":"AT",
    "sg:address":"Bahnstr 12",
    "sg:city":"Altach",
    "sg:orig_category":"Innenausbau",
    "sg:phone":"+43 5576 725910",
    "sg:postcode":"6844",
    "sg:province":"Vorarlberg",
    "wof:name":"Ender Manfred",
    "wof:placetype":"venue"
},
  "geometry": {"coordinates":[9.6515579224,47.352306366],"type":"Point"}
}