{
  "type": "Feature",
  "properties": {
    "addr:full":"Matthias-Felser-Str 25 Waidhofen an der Thaya Nieder\u00f6sterreich 3830",
    "addr:housenumber":"25",
    "addr:postcode":"3830",
    "addr:street":"Matthias-Felser-Str",
    "iso:country":"AT",
    "sg:address":"Matthias-Felser-Str 25",
    "sg:city":"Waidhofen an der Thaya",
    "sg:orig_category":"Genossenschaften",
    "sg:phone":"+43 4328 42525420",
    "sg:postcode":"3830",
    "sg:province":"Nieder\u00f6sterreich",
    "wof:name":"Waldviertler Fleischervereinigung regGenmbH",
    "wof:placetype":"venue"
},
  "geometry": {"coordinates":[15.2806100845,48.8188400269],"type":"Point"}
}