{
  "type": "Feature",
  "properties": {
    "iso:country":"AT",
    "sg:address":"Bahnhofstr 7",
    "sg:city":"Ottensheim",
    "sg:orig_category":"Non-Classified Establishments",
    "sg:phone":"+43 5 91334337",
    "sg:postcode":"4100",
    "sg:province":"Ober\u00f6sterreich",
    "wof:name":"Gendarmerieposten",
    "wof:placetype":"venue"
},
  "geometry": {"coordinates":[14.1755514145,48.3334999084],"type":"Point"}
}