{
  "type": "Feature",
  "properties": {
    "addr:full":"Steinbachstr 388 Gamlitz Steiermark 8462",
    "addr:housenumber":"388",
    "addr:postcode":"8462",
    "iso:country":"AT",
    "sg:address":"Steinbachstr 388",
    "sg:city":"Gamlitz",
    "sg:orig_category":"Erdbau",
    "sg:phone":"+43 3453 4248",
    "sg:postcode":"8462",
    "sg:province":"Steiermark",
    "wof:name":"Grabner Alois",
    "wof:placetype":"venue"
},
  "geometry": {"coordinates":[15.5304460526,46.6918067932],"type":"Point"}
}