{
  "type": "Feature",
  "properties": {
    "addr:full":"Widmanng 7 Villach K\u00e4rnten 9500",
    "addr:housenumber":"7",
    "addr:postcode":"9500",
    "addr:street":"Widmanng;Kaernten",
    "iso:country":"AT",
    "sg:address":"Widmanng 7",
    "sg:city":"Villach",
    "sg:orig_category":"Handarbeiten",
    "sg:phone":"+43 4342 42210049",
    "sg:postcode":"9500",
    "sg:province":"K\u00e4rnten",
    "wof:name":"Handarbeiten Sabrina",
    "wof:placetype":"venue"
},
  "geometry": {"coordinates":[13.8448858261,46.615322113],"type":"Point"}
}