{
  "type": "Feature",
  "properties": {
    "addr:full":"Mittelberg 4 Langenlois Nieder\u00f6sterreich 3550",
    "addr:housenumber":"4",
    "addr:postcode":"3550",
    "addr:street":"Mittelberg",
    "iso:country":"AT",
    "sg:address":"Mittelberg 4",
    "sg:city":"Langenlois",
    "sg:orig_category":"Baumaschinenverleih",
    "sg:phone":"+43 2734 70090",
    "sg:postcode":"3550",
    "sg:province":"Nieder\u00f6sterreich",
    "wof:name":"entfeuchter.at.gmbh",
    "wof:placetype":"venue"
},
  "geometry": {"coordinates":[15.5758371353,48.5058670044],"type":"Point"}
}