{
  "type": "Feature",
  "properties": {
    "iso:country":"AT",
    "sg:address":"Feldg 48-50",
    "sg:city":"Tribuswinkel",
    "sg:orig_category":"Maler, Anstreicher U Lackierer",
    "sg:phone":"+43 4322 5287681",
    "sg:postcode":"2512",
    "sg:province":"Nieder\u00f6sterreich",
    "wof:name":"Schmidt Helmut GesmbH",
    "wof:placetype":"venue"
},
  "geometry": {"coordinates":[16.2946853638,47.9884490967],"type":"Point"}
}