{
  "type": "Feature",
  "properties": {
    "addr:full":"Einsiedlerweg 12 Kroisbach Steiermark 8043",
    "addr:housenumber":"12",
    "addr:postcode":"8043",
    "addr:street":"Einsiedlerweg",
    "iso:country":"AT",
    "sg:address":"Einsiedlerweg 12",
    "sg:city":"Kroisbach",
    "sg:orig_category":"Steuerberatung",
    "sg:phone":"+43 316 382451",
    "sg:postcode":"8043",
    "sg:province":"Steiermark",
    "wof:name":"Lackner Erhard",
    "wof:placetype":"venue"
},
  "geometry": {"coordinates":[15.4568243027,47.0957489014],"type":"Point"}
}