{
  "type": "Feature",
  "properties": {
    "addr:full":"Litschauer Str 1 Gm\u00fcnd Nieder\u00f6sterreich 3950",
    "addr:housenumber":"1",
    "addr:postcode":"3950",
    "addr:street":"Str;Niederoesterreich",
    "iso:country":"AT",
    "sg:address":"Litschauer Str 1",
    "sg:city":"Gm\u00fcnd",
    "sg:orig_category":"Beton- U Betonsteinwerke",
    "sg:phone":"+43 2852 51559",
    "sg:postcode":"3950",
    "sg:province":"Nieder\u00f6sterreich",
    "wof:name":"Graf Beton & Recycling GmbH & Co KG",
    "wof:placetype":"venue"
},
  "geometry": {"coordinates":[14.9831171036,48.772983551],"type":"Point"}
}