{
  "type": "Feature",
  "properties": {
    "addr:full":"Grafendorfstr 20 Frohnleiten Steiermark 8130",
    "addr:housenumber":"20",
    "addr:postcode":"8130",
    "addr:street":"Grafendorfstr",
    "iso:country":"AT",
    "sg:address":"Grafendorfstr 20",
    "sg:city":"Frohnleiten",
    "sg:orig_category":"Tischlereien",
    "sg:phone":"+43 4331 2624270",
    "sg:postcode":"8130",
    "sg:province":"Steiermark",
    "wof:name":"Holzapfel Dominikus",
    "wof:placetype":"venue"
},
  "geometry": {"coordinates":[15.3297405243,47.2688484192],"type":"Point"}
}