{
  "type": "Feature",
  "properties": {
    "iso:country":"AT",
    "sg:address":"Budweiser Str 5",
    "sg:city":"Schrems",
    "sg:orig_category":"Tischlereien",
    "sg:phone":"+43 2853 77238",
    "sg:postcode":"3943",
    "sg:province":"Nieder\u00f6sterreich",
    "wof:name":"Stanek Edeltraud",
    "wof:placetype":"venue"
},
  "geometry": {"coordinates":[15.0714254379,48.7929534912],"type":"Point"}
}