{
  "type": "Feature",
  "properties": {
    "iso:country":"AT",
    "sg:address":"Davidstrasse 23",
    "sg:city":"Eferding",
    "sg:classifiers":[
        {
            "category":"Professional",
            "subcategory":"Business Services",
            "type":"Services"
        }
    ],
    "sg:phone":"+43 7272 6114",
    "sg:postcode":"4070",
    "sg:province":"Ober\u00f6sterreich",
    "sg:website":"buero-extern.at",
    "wof:name":"B\u00dcRO EXTERN, Monika Lanzersdorfer",
    "wof:placetype":"venue"
},
  "geometry": {"coordinates":[14.0234451294,48.3086395264],"type":"Point"}
}