{
  "type": "Feature",
  "properties": {
    "addr:full":"Oberwirt 365 M\u00fchlbach am Hochk\u00f6nig Salzburg 5505",
    "addr:housenumber":"365",
    "addr:postcode":"5505",
    "addr:street":"Oberwirt",
    "iso:country":"AT",
    "sg:address":"Oberwirt 365",
    "sg:city":"M\u00fchlbach am Hochk\u00f6nig",
    "sg:orig_category":"Erdarbeiten",
    "sg:phone":"+43 6467 7857",
    "sg:postcode":"5505",
    "sg:province":"Salzburg",
    "wof:name":"Mair Michael",
    "wof:placetype":"venue"
},
  "geometry": {"coordinates":[-82.265586853,37.4296951294],"type":"Point"}
}