{
  "type": "Feature",
  "properties": {
    "addr:full":"Makartstr 53 Traun Ober\u00f6sterreich 4050",
    "addr:housenumber":"53",
    "addr:postcode":"4050",
    "addr:street":"Makartstr",
    "iso:country":"AT",
    "sg:address":"Makartstr 53",
    "sg:city":"Traun",
    "sg:orig_category":"Lebens- U Sozialberatung",
    "sg:phone":"+43 4365 06201431",
    "sg:postcode":"4050",
    "sg:province":"Ober\u00f6sterreich",
    "wof:name":"Glieder Veronika - Three In One Concepts Stressmanagement",
    "wof:placetype":"venue"
},
  "geometry": {"coordinates":[14.2740621567,48.2342910767],"type":"Point"}
}