{
  "type": "Feature",
  "properties": {
    "addr:full":"Giselherg 11 Wien Wien 1150",
    "addr:housenumber":"11",
    "addr:postcode":"1150",
    "addr:street":"Giselherg",
    "iso:country":"AT",
    "sg:address":"Giselherg 11",
    "sg:city":"Wien",
    "sg:orig_category":"Lebensmittel / Einzelhandel",
    "sg:phone":"+43 1 9820454",
    "sg:postcode":"1150",
    "sg:province":"Wien",
    "wof:name":"Billa AG",
    "wof:placetype":"venue"
},
  "geometry": {"coordinates":[16.3289337158,48.2034873962],"type":"Point"}
}