{
  "type": "Feature",
  "properties": {
    "addr:full":"Badg 1 Oberwart Burgenland 7400",
    "addr:housenumber":"1",
    "addr:postcode":"7400",
    "addr:street":"Badg",
    "iso:country":"AT",
    "sg:address":"Badg 1",
    "sg:city":"Oberwart",
    "sg:orig_category":"Restaurants: Chinesisch",
    "sg:phone":"+43 3352 33438",
    "sg:postcode":"7400",
    "sg:province":"Burgenland",
    "wof:name":"China-Restaurant Chinesische Mauer",
    "wof:placetype":"venue"
},
  "geometry": {"coordinates":[16.2131557465,47.2876167297],"type":"Point"}
}