{
  "type": "Feature",
  "properties": {
    "iso:country":"AT",
    "sg:address":"Favoritenstrasse 93",
    "sg:city":"Wien",
    "sg:classifiers":[
        {
            "category":"Professional",
            "subcategory":"Advertising",
            "type":"Services"
        }
    ],
    "sg:phone":"+43 1 60239120",
    "sg:postcode":"1100",
    "sg:province":"Wien",
    "sg:tags":[
        "agency"
    ],
    "sg:website":"saz.at",
    "wof:name":"SAZ Marketing Services Ges.m.b.H.",
    "wof:placetype":"venue"
},
  "geometry": {"coordinates":[16.3762798309,48.1794090271],"type":"Point"}
}