{
  "type": "Feature",
  "properties": {
    "iso:country":"AT",
    "sg:address":"Pius Parsch-Pl 11/3",
    "sg:city":"Wien",
    "sg:orig_category":"Grafische Maschinen U Reparaturen",
    "sg:phone":"+43 1 2781909",
    "sg:postcode":"1210",
    "sg:province":"Wien",
    "wof:name":"AL-JIBAIE GRAPHISCHE SYSTEME KEG",
    "wof:placetype":"venue"
},
  "geometry": {"coordinates":[16.3999290466,48.258014679],"type":"Point"}
}