{
  "type": "Feature",
  "properties": {
    "iso:country":"AT",
    "sg:address":"Schiffbaustrasse 14",
    "sg:city":"Linz",
    "sg:classifiers":[
        {
            "category":"Building & Trades",
            "subcategory":"Cleaning & Sanitation",
            "type":"Services"
        }
    ],
    "sg:phone":"+43 732 774205",
    "sg:postcode":"4020",
    "sg:province":"Ober\u00f6sterreich",
    "sg:tags":[
        "boiler"
    ],
    "wof:name":"Kessel-Nessl Inh. Harald Fuchs",
    "wof:placetype":"venue"
},
  "geometry": {"coordinates":[14.3089799881,48.3175468445],"type":"Point"}
}