{
  "type": "Feature",
  "properties": {
    "addr:full":"Kaerntnerring 2 -  1015",
    "addr:housenumber":"2",
    "addr:postcode":"1015",
    "addr:street":"Kaerntnerring",
    "iso:country":"AT",
    "sg:address":"Kaerntnerring 2 - ",
    "sg:classifiers":[
        {
            "category":"Professional",
            "subcategory":"Art Services",
            "type":"Services"
        }
    ],
    "sg:phone":"+43 4315 058666",
    "sg:postcode":"1015",
    "sg:tags":[
        "export-import"
    ],
    "sg:website":"http://www.indianembassy.at",
    "wof:name":"India Embassy",
    "wof:placetype":"venue"
},
  "geometry": {"coordinates":[16.369966507,48.2020378113],"type":"Point"}
}