{
  "type": "Feature",
  "properties": {
    "addr:full":"Anton-Bruckner-Str 10 Ansfelden Ober\u00f6sterreich 4052",
    "addr:housenumber":"10",
    "addr:postcode":"4052",
    "addr:street":"Anton-Bruckner-Str",
    "iso:country":"AT",
    "sg:address":"Anton-Bruckner-Str 10",
    "sg:city":"Ansfelden",
    "sg:orig_category":"Kinderbetreuung",
    "sg:phone":"+43 7229 78138",
    "sg:postcode":"4052",
    "sg:province":"Ober\u00f6sterreich",
    "wof:name":"Hort der Ober\u00f6sterreichischen Kinderfreunde",
    "wof:placetype":"venue"
},
  "geometry": {"coordinates":[14.2885599136,48.2113800049],"type":"Point"}
}