{
  "type": "Feature",
  "properties": {
    "iso:country":"AT",
    "sg:address":"Hafnerstr 4",
    "sg:city":"Mistelbach",
    "sg:orig_category":"Lederwaren / Einzelhandel",
    "sg:phone":"+43 2572 24730",
    "sg:postcode":"2130",
    "sg:province":"Nieder\u00f6sterreich",
    "wof:name":"Klein Werner GesmbH",
    "wof:placetype":"venue"
},
  "geometry": {"coordinates":[16.5720615387,48.5681152344],"type":"Point"}
}