{
  "type": "Feature",
  "properties": {
    "addr:full":"Bachweg 8a Frankenburg am Hausruck Ober\u00f6sterreich 4873",
    "addr:housenumber":"8a",
    "addr:postcode":"4873",
    "addr:street":"Bachweg",
    "iso:country":"AT",
    "sg:address":"Bachweg 8a",
    "sg:city":"Frankenburg am Hausruck",
    "sg:classifiers":[
        {
            "category":"Personal",
            "subcategory":"Sauna",
            "type":"Services"
        }
    ],
    "sg:phone":"+43 76835022",
    "sg:postcode":"4873",
    "sg:province":"Ober\u00f6sterreich",
    "sg:tags":[
        "u",
        "dampfbad"
    ],
    "wof:name":"TPI Handels GesmbH - Infrarot W\u00e4rmekabinen",
    "wof:placetype":"venue"
},
  "geometry": {"coordinates":[13.4921588898,48.0664749146],"type":"Point"}
}