{
  "type": "Feature",
  "properties": {
    "addr:full":"Nr 209a Zellerndorf Nieder\u00f6sterreich 2051",
    "addr:postcode":"2051",
    "addr:street":"Nr",
    "iso:country":"AT",
    "sg:address":"Nr 209a",
    "sg:city":"Zellerndorf",
    "sg:orig_category":"Schneidereien",
    "sg:phone":"+43 2945 27069",
    "sg:postcode":"2051",
    "sg:province":"Nieder\u00f6sterreich",
    "wof:name":"Jagenteufel Franz",
    "wof:placetype":"venue"
},
  "geometry": {"coordinates":[15.9825706482,48.696598053],"type":"Point"}
}