{
  "type": "Feature",
  "properties": {
    "addr:full":"Am Pichl 1 Kapfenberg Steiermark 8605",
    "addr:housenumber":"1",
    "addr:postcode":"8605",
    "addr:street":"Am Pichl",
    "iso:country":"AT",
    "sg:address":"Am Pichl 1",
    "sg:city":"Kapfenberg",
    "sg:orig_category":"Autobusunternehmen",
    "sg:phone":"+43 3862 33559",
    "sg:postcode":"8605",
    "sg:province":"Steiermark",
    "wof:name":"Schutti Franz",
    "wof:placetype":"venue"
},
  "geometry": {"coordinates":[15.3207111359,47.4581184387],"type":"Point"}
}