{
  "type": "Feature",
  "properties": {
    "addr:full":"Dechantswiese 9 Radstadt Salzburg 5550",
    "addr:housenumber":"9",
    "addr:postcode":"5550",
    "addr:street":"Dechantswiese;Salzburg",
    "iso:country":"AT",
    "sg:address":"Dechantswiese 9",
    "sg:city":"Radstadt",
    "sg:orig_category":"Gartenbaubedarf",
    "sg:phone":"+43 6452 6493",
    "sg:postcode":"5550",
    "sg:province":"Salzburg",
    "wof:name":"Blumi Blumenerdenerzeugung GesmbH",
    "wof:placetype":"venue"
},
  "geometry": {"coordinates":[13.4911575317,47.3860969543],"type":"Point"}
}