{
  "type": "Feature",
  "properties": {
    "addr:full":"Rumersdorf 11 Niederkappel Ober\u00f6sterreich 4133",
    "addr:housenumber":"11",
    "addr:postcode":"4133",
    "addr:street":"Rumersdorf",
    "iso:country":"AT",
    "sg:address":"Rumersdorf 11",
    "sg:city":"Niederkappel",
    "sg:orig_category":"Transportunternehmen",
    "sg:phone":"+43 7286 8517",
    "sg:postcode":"4133",
    "sg:province":"Ober\u00f6sterreich",
    "wof:name":"Aichbauer Franz und Friedrich Aichbauer GesnbR",
    "wof:placetype":"venue"
},
  "geometry": {"coordinates":[13.8661851883,48.4629745483],"type":"Point"}
}