{
  "type": "Feature",
  "properties": {
    "addr:full":"Rosenhof 181 St. Stefan ob Stainz Steiermark 8511",
    "addr:housenumber":"181",
    "addr:postcode":"8511",
    "addr:street":"Rosenhof",
    "iso:country":"AT",
    "sg:address":"Rosenhof 181",
    "sg:city":"St. Stefan ob Stainz",
    "sg:orig_category":"Garten- U Landschaftsgestaltung",
    "sg:phone":"+43 4366 43207070",
    "sg:postcode":"8511",
    "sg:province":"Steiermark",
    "wof:name":"Feichtinger Erwin Mag",
    "wof:placetype":"venue"
},
  "geometry": {"coordinates":[15.2257862091,46.9417800903],"type":"Point"}
}