{
  "type": "Feature",
  "properties": {
    "addr:full":"Niederottnang 35 Ottnang am Hausruck Ober\u00f6sterreich 4901",
    "addr:housenumber":"35",
    "addr:postcode":"4901",
    "addr:street":"Niederottnang",
    "iso:country":"AT",
    "sg:address":"Niederottnang 35",
    "sg:city":"Ottnang am Hausruck",
    "sg:orig_category":"Autohandel",
    "sg:phone":"+43 76767454",
    "sg:postcode":"4901",
    "sg:province":"Ober\u00f6sterreich",
    "wof:name":"Schmidt Franz Josef",
    "wof:placetype":"venue"
},
  "geometry": {"coordinates":[13.6609239578,48.0962753296],"type":"Point"}
}