{
  "type": "Feature",
  "properties": {
    "addr:full":"Sporg 20 Graz Steiermark 8010",
    "addr:housenumber":"20",
    "addr:postcode":"8010",
    "addr:street":"Sporg",
    "iso:country":"AT",
    "sg:address":"Sporg 20",
    "sg:city":"Graz",
    "sg:orig_category":"Boutiquen",
    "sg:phone":"+43 316 825041",
    "sg:postcode":"8010",
    "sg:province":"Steiermark",
    "wof:name":"Geschenk & Mode Handels GmbH",
    "wof:placetype":"venue"
},
  "geometry": {"coordinates":[15.4391031265,47.0723152161],"type":"Point"}
}