{
  "type": "Feature",
  "properties": {
    "addr:full":"Karolineng 23 Wien Wien 1040",
    "addr:housenumber":"23",
    "addr:postcode":"1040",
    "addr:street":"Karolineng",
    "iso:country":"AT",
    "sg:address":"Karolineng 23",
    "sg:city":"Wien",
    "sg:orig_category":"Textilreinigung",
    "sg:phone":"+43 1 5041621",
    "sg:postcode":"1040",
    "sg:province":"Wien",
    "wof:name":"Niederkorn Christian - Moderne Textilreinigung",
    "wof:placetype":"venue"
},
  "geometry": {"coordinates":[16.3745155334,48.1899757385],"type":"Point"}
}