{
  "type": "Feature",
  "properties": {
    "addr:full":"Tiroler Str 75 Silz Tirol 6424",
    "addr:postcode":"6424",
    "addr:street":"Str 75;Tirol",
    "iso:country":"AT",
    "sg:address":"Tiroler Str 75",
    "sg:city":"Silz",
    "sg:orig_category":"Installationsunternehmen",
    "sg:phone":"+43 5263 64280",
    "sg:postcode":"6424",
    "sg:province":"Tirol",
    "wof:name":"Heizung Sanit\u00e4re Daniel Gatterer GmbH",
    "wof:placetype":"venue"
},
  "geometry": {"coordinates":[10.9284324646,47.2658042908],"type":"Point"}
}