{
  "type": "Feature",
  "properties": {
    "addr:full":"Hauptstr 59 F\u00fcgen Tirol 6263",
    "addr:housenumber":"59",
    "addr:postcode":"6263",
    "addr:street":"Hauptstr;Tirol",
    "iso:country":"AT",
    "sg:address":"Hauptstr 59",
    "sg:city":"F\u00fcgen",
    "sg:orig_category":"Waren Aller Art",
    "sg:phone":"+43 4365 07772616",
    "sg:postcode":"6263",
    "sg:province":"Tirol",
    "wof:name":"NA SO WAS 75-Cent-Shop",
    "wof:placetype":"venue"
},
  "geometry": {"coordinates":[11.8509092331,47.3445549011],"type":"Point"}
}