{
  "type": "Feature",
  "properties": {
    "addr:full":"Billrothstr 42 Wien Wien 1190",
    "addr:housenumber":"42",
    "addr:postcode":"1190",
    "addr:street":"Billrothstr",
    "iso:country":"AT",
    "sg:address":"Billrothstr 42",
    "sg:city":"Wien",
    "sg:orig_category":"Umstandsmoden",
    "sg:phone":"+43 1 3685284",
    "sg:postcode":"1190",
    "sg:province":"Wien",
    "sg:website":"mamamode.at",
    "wof:name":"Cinderella Kindermoden-Umstandsmoden S Jeschko",
    "wof:placetype":"venue"
},
  "geometry": {"coordinates":[16.3493938446,48.2397117615],"type":"Point"}
}