{
  "type": "Feature",
  "properties": {
    "addr:full":"Industriezone 30 Imst Tirol 6460",
    "addr:housenumber":"30",
    "addr:postcode":"6460",
    "addr:street":"Industriezone;Tirol",
    "iso:country":"AT",
    "sg:address":"Industriezone 30",
    "sg:city":"Imst",
    "sg:orig_category":"Bekleidung / Einzelhandel",
    "sg:phone":"+43 5412 62539",
    "sg:postcode":"6460",
    "sg:province":"Tirol",
    "wof:name":"Stigger Herlinde GesmbH & Co KG",
    "wof:placetype":"venue"
},
  "geometry": {"coordinates":[10.737487793,47.2392234802],"type":"Point"}
}