{
  "type": "Feature",
  "properties": {
    "iso:country":"AT",
    "sg:address":"Seilerg 4/3",
    "sg:city":"Wien",
    "sg:orig_category":"Friseure U Frisiersalons",
    "sg:phone":"+43 4315 124992",
    "sg:postcode":"1010",
    "sg:province":"Wien",
    "wof:name":"Unger Markus Hairstyling",
    "wof:placetype":"venue"
},
  "geometry": {"coordinates":[16.3708648682,48.2077217102],"type":"Point"}
}