{
  "type": "Feature",
  "properties": {
    "iso:country":"AT",
    "sg:address":"Hetzendorfer Str 56",
    "sg:city":"Wien",
    "sg:classifiers":[
        {
            "category":"Internet Cafe",
            "subcategory":"None",
            "type":"Food & Drink"
        }
    ],
    "sg:phone":"+43 1 4803725",
    "sg:postcode":"1120",
    "sg:province":"Wien",
    "wof:name":"Mc Web - Walter Asperl",
    "wof:placetype":"venue"
},
  "geometry": {"coordinates":[16.3139247894,48.1658973694],"type":"Point"}
}