{
  "type": "Feature",
  "properties": {
    "addr:full":"Nr 26 Pettenbach Ober\u00f6sterreich 4643",
    "addr:postcode":"4643",
    "addr:street":"Nr;Oberoesterreich",
    "iso:country":"AT",
    "sg:address":"Nr 26",
    "sg:city":"Pettenbach",
    "sg:orig_category":"Tischlereien",
    "sg:phone":"+43 7586 8892",
    "sg:postcode":"4643",
    "sg:province":"Ober\u00f6sterreich",
    "wof:name":"Purrer Kurt",
    "wof:placetype":"venue"
},
  "geometry": {"coordinates":[14.0165214539,47.9612464905],"type":"Point"}
}