{
  "type": "Feature",
  "properties": {
    "addr:full":"Kleistg 29 Wien Wien 1030",
    "addr:housenumber":"29",
    "addr:postcode":"1030",
    "addr:street":"Kleistg",
    "iso:country":"AT",
    "sg:address":"Kleistg 29",
    "sg:city":"Wien",
    "sg:orig_category":"Tanzschulen",
    "sg:phone":"+43 4312 086622",
    "sg:postcode":"1030",
    "sg:province":"Wien",
    "wof:name":"Angelita Inh Angelova Antonia",
    "wof:placetype":"venue"
},
  "geometry": {"coordinates":[16.3890361786,48.1890525818],"type":"Point"}
}