{
  "type": "Feature",
  "properties": {
    "iso:country":"AT",
    "sg:address":"Johann Elias-Str 3",
    "sg:city":"Salzburg",
    "sg:classifiers":[
        {
            "category":"Taxi",
            "type":"Transportation"
        }
    ],
    "sg:phone":"+43 4366 2625269",
    "sg:postcode":"5020",
    "sg:province":"Salzburg",
    "sg:tags":[
        "personentransporte",
        "u"
    ],
    "wof:name":"Wegscheider Werner",
    "wof:placetype":"venue"
},
  "geometry": {"coordinates":[13.073928833,47.7749710083],"type":"Point"}
}