{
  "type": "Feature",
  "properties": {
    "iso:country":"AT",
    "sg:address":"Am Hof 12",
    "sg:city":"Wien",
    "sg:classifiers":[
        {
            "category":"Restaurant",
            "type":"Food & Drink"
        }
    ],
    "sg:phone":"+43 1 5339102",
    "sg:postcode":"1010",
    "sg:province":"Wien",
    "wof:name":"Urbanikeller",
    "wof:placetype":"venue"
},
  "geometry": {"coordinates":[16.3684062958,48.2113876343],"type":"Point"}
}