{
  "type": "Feature",
  "properties": {
    "addr:full":"Schirmerstrasse 28 Leonding Ober\u00f6sterreich 4060",
    "addr:housenumber":"28",
    "addr:postcode":"4060",
    "addr:street":"Schirmerstrasse",
    "iso:country":"AT",
    "sg:address":"Schirmerstrasse 28",
    "sg:city":"Leonding",
    "sg:orig_category":"Equipment For Air-Raid Shelters",
    "sg:phone":"+43 732 3840270",
    "sg:postcode":"4060",
    "sg:province":"Ober\u00f6sterreich",
    "sg:website":"goetzloff.at",
    "wof:name":"Goetzloff GmbH, EUROLITE Produkte",
    "wof:placetype":"venue"
},
  "geometry": {"coordinates":[14.2722625732,48.2529182434],"type":"Point"}
}