{
  "type": "Feature",
  "properties": {
    "addr:full":"Hans Liebherr-Str 15 Telfs Tirol 6410",
    "addr:housenumber":"15",
    "addr:postcode":"6410",
    "addr:street":"Tirol",
    "iso:country":"AT",
    "sg:address":"Hans Liebherr-Str 15",
    "sg:city":"Telfs",
    "sg:orig_category":"Autoreparatur",
    "sg:phone":"+43 5262 65530",
    "sg:postcode":"6410",
    "sg:province":"Tirol",
    "wof:name":"Kornherr Kurt",
    "wof:placetype":"venue"
},
  "geometry": {"coordinates":[11.0954046249,47.3146743774],"type":"Point"}
}