{
  "type": "Feature",
  "properties": {
    "addr:full":"Wettersteinstr 24 Ehrwald Tirol 6632",
    "addr:housenumber":"24",
    "addr:postcode":"6632",
    "addr:street":"Wettersteinstr;Tirol",
    "iso:country":"AT",
    "sg:address":"Wettersteinstr 24",
    "sg:city":"Ehrwald",
    "sg:classifiers":[
        {
            "category":"Travel",
            "subcategory":"Hotels & Motels",
            "type":"Entertainment"
        }
    ],
    "sg:phone":"+43 5673 22250",
    "sg:postcode":"6632",
    "sg:province":"Tirol",
    "wof:name":"Spielmann's Hotel",
    "wof:placetype":"venue"
},
  "geometry": {"coordinates":[10.9249649048,47.3999862671],"type":"Point"}
}