{
  "type": "Feature",
  "properties": {
    "addr:full":"Schlo\u00dfstr 33 Salzburg Salzburg 5020",
    "addr:housenumber":"33",
    "addr:postcode":"5020",
    "addr:street":"Schlossstr;Salzburg",
    "iso:country":"AT",
    "sg:address":"Schlo\u00dfstr 33",
    "sg:city":"Salzburg",
    "sg:orig_category":"Tischlereien",
    "sg:phone":"+43 662 642428",
    "sg:postcode":"5020",
    "sg:province":"Salzburg",
    "wof:name":"Bacher Raimund",
    "wof:placetype":"venue"
},
  "geometry": {"coordinates":[13.0740699768,47.8060722351],"type":"Point"}
}