{
  "type": "Feature",
  "properties": {
    "addr:full":"Parkstr 10 Knittelfeld Steiermark 8720",
    "addr:housenumber":"10",
    "addr:postcode":"8720",
    "addr:street":"Parkstr",
    "iso:country":"AT",
    "sg:address":"Parkstr 10",
    "sg:city":"Knittelfeld",
    "sg:orig_category":"Ingenieurkonsulenten / Zivilingenieure",
    "sg:phone":"+43 3512 82648",
    "sg:postcode":"8720",
    "sg:province":"Steiermark",
    "wof:name":"Hohenwarter Johann Dipl-Ing",
    "wof:placetype":"venue"
},
  "geometry": {"coordinates":[14.8269376755,47.2121887207],"type":"Point"}
}