{
  "type": "Feature",
  "properties": {
    "iso:country":"AT",
    "sg:address":"Markgraf R\u00fcdiger-Str 12",
    "sg:city":"Wien",
    "sg:orig_category":"Musikverlage",
    "sg:phone":"+43 1 4191432",
    "sg:postcode":"1150",
    "sg:province":"Wien",
    "wof:name":"Kent Unlimited",
    "wof:placetype":"venue"
},
  "geometry": {"coordinates":[16.3320903778,48.2006416321],"type":"Point"}
}