{
  "type": "Feature",
  "properties": {
    "addr:full":"Vigilg 20 Thaur Tirol 6065",
    "addr:housenumber":"20",
    "addr:postcode":"6065",
    "addr:street":"Vigilg;Tirol",
    "iso:country":"AT",
    "sg:address":"Vigilg 20",
    "sg:city":"Thaur",
    "sg:orig_category":"Zahntechnische Laboratorien",
    "sg:phone":"+43 5223 492698",
    "sg:postcode":"6065",
    "sg:province":"Tirol",
    "wof:name":"Dentallabor Oberm\u00fcller",
    "wof:placetype":"venue"
},
  "geometry": {"coordinates":[11.4796199799,47.295375824],"type":"Point"}
}