{
  "type": "Feature",
  "properties": {
    "addr:full":"Nr 1 Hirnsdorf Steiermark 8221",
    "addr:postcode":"8221",
    "addr:street":"Nr;Hirnsdorf",
    "iso:country":"AT",
    "sg:address":"Nr 1",
    "sg:city":"Hirnsdorf",
    "sg:orig_category":"Paletten / Erzeugung U Gro\u00c3\u0178handel",
    "sg:phone":"+43 4331 1322820",
    "sg:postcode":"8221",
    "sg:province":"Steiermark",
    "sg:website":"schafler-holz.at",
    "wof:name":"Schafler A u E Holzindustrie",
    "wof:placetype":"venue"
},
  "geometry": {"coordinates":[15.827246666,47.1935882568],"type":"Point"}
}