{
  "type": "Feature",
  "properties": {
    "addr:full":"Franz-Reisch-Str 4 Kitzb\u00fchel Tirol 6370",
    "addr:housenumber":"4",
    "addr:postcode":"6370",
    "addr:street":"Franz-Reisch-Str;Tirol",
    "iso:country":"AT",
    "sg:address":"Franz-Reisch-Str 4",
    "sg:city":"Kitzb\u00fchel",
    "sg:orig_category":"Lebensmittel / Einzelhandel",
    "sg:phone":"+43 4353 5666001",
    "sg:postcode":"6370",
    "sg:province":"Tirol",
    "wof:name":"Billa AG",
    "wof:placetype":"venue"
},
  "geometry": {"coordinates":[12.3891296387,47.4459342957],"type":"Point"}
}