{
  "type": "Feature",
  "properties": {
    "addr:full":"Salzgries 10 Wien Wien 1010",
    "addr:housenumber":"10",
    "addr:postcode":"1010",
    "addr:street":"Salzgries",
    "iso:country":"AT",
    "sg:address":"Salzgries 10",
    "sg:city":"Wien",
    "sg:classifiers":[
        {
            "category":"Shopping",
            "subcategory":"Gifts & Souvenirs",
            "type":"Retail Goods"
        }
    ],
    "sg:phone":"+43 1 8924136",
    "sg:postcode":"1010",
    "sg:province":"Wien",
    "wof:name":"Souvenirworld Handels GmbH",
    "wof:placetype":"venue"
},
  "geometry": {"coordinates":[16.371761322,48.2133331299],"type":"Point"}
}