{
  "type": "Feature",
  "properties": {
    "addr:full":"Angererweg 16 Tulfes Tirol 6075",
    "addr:housenumber":"16",
    "addr:postcode":"6075",
    "addr:street":"Angererweg;Tirol",
    "iso:country":"AT",
    "sg:address":"Angererweg 16",
    "sg:city":"Tulfes",
    "sg:orig_category":"Pensionen / Privatzimmer",
    "sg:phone":"+43 5223 78326",
    "sg:postcode":"6075",
    "sg:province":"Tirol",
    "wof:name":"G\u00e4stehaus Tannerhof",
    "wof:placetype":"venue"
},
  "geometry": {"coordinates":[11.5357542038,47.2585258484],"type":"Point"}
}