{
  "type": "Feature",
  "properties": {
    "addr:full":"Harrachg 2 Graz Steiermark 8010",
    "addr:housenumber":"2",
    "addr:postcode":"8010",
    "addr:street":"Harrachg",
    "iso:country":"AT",
    "sg:address":"Harrachg 2",
    "sg:city":"Graz",
    "sg:orig_category":"\u00c3\u201erzte / F Allgemeinmedizin",
    "sg:phone":"+43 676 4145602",
    "sg:postcode":"8010",
    "sg:province":"Steiermark",
    "sg:website":"drjudithhacker.info",
    "wof:name":"Hacker Judith Dr",
    "wof:placetype":"venue"
},
  "geometry": {"coordinates":[15.4455471039,47.0758552551],"type":"Point"}
}