{
  "type": "Feature",
  "properties": {
    "iso:country":"AT",
    "sg:address":"Uferweg 14",
    "sg:city":"Frauental an der La\u00dfnitz",
    "sg:orig_category":"Webdesign",
    "sg:phone":"+43 4365 08483386",
    "sg:postcode":"8523",
    "sg:province":"Steiermark",
    "wof:name":"web2future.at - Aldrian & P\u00f6ltl KEG",
    "wof:placetype":"venue"
},
  "geometry": {"coordinates":[15.2629184723,46.8258323669],"type":"Point"}
}