{
  "type": "Feature",
  "properties": {
    "addr:full":"Hegerg 20 Wien Wien 1030",
    "addr:housenumber":"20",
    "addr:postcode":"1030",
    "addr:street":"Hegerg",
    "iso:country":"AT",
    "sg:address":"Hegerg 20",
    "sg:city":"Wien",
    "sg:orig_category":"Volksschulen",
    "sg:phone":"+43 1 7986104",
    "sg:postcode":"1030",
    "sg:province":"Wien",
    "wof:name":"Schulen d Stadt Wien",
    "wof:placetype":"venue"
},
  "geometry": {"coordinates":[16.3892288208,48.1914863586],"type":"Point"}
}