{
  "type": "Feature",
  "properties": {
    "addr:full":"Hauptstr 4 Stegersbach Burgenland 7551",
    "addr:housenumber":"4",
    "addr:postcode":"7551",
    "addr:street":"Hauptstr",
    "iso:country":"AT",
    "sg:address":"Hauptstr 4",
    "sg:city":"Stegersbach",
    "sg:orig_category":"Bauunternehmen",
    "sg:phone":"+43 3326 52333",
    "sg:postcode":"7551",
    "sg:province":"Burgenland",
    "wof:name":"ADLER W Bau-GmbH",
    "wof:placetype":"venue"
},
  "geometry": {"coordinates":[16.1671142578,47.158618927],"type":"Point"}
}