{
  "type": "Feature",
  "properties": {
    "addr:full":"Dr Karl Renner-Pl 7 Attnang-Puchheim Ober\u00f6sterreich 4800",
    "addr:housenumber":"7",
    "addr:postcode":"4800",
    "addr:street":"Dr;Renner-Pl",
    "iso:country":"AT",
    "sg:address":"Dr Karl Renner-Pl 7",
    "sg:city":"Attnang-Puchheim",
    "sg:orig_category":"Banken U Sparkassen",
    "sg:phone":"+43 5 010040062",
    "sg:postcode":"4800",
    "sg:province":"Ober\u00f6sterreich",
    "wof:name":"Allgemeine Sparkasse Ober\u00f6sterreich Bank AG",
    "wof:placetype":"venue"
},
  "geometry": {"coordinates":[13.7213153839,48.0121116638],"type":"Point"}
}