{
  "type": "Feature",
  "properties": {
    "iso:country":"AT",
    "sg:address":"Schulstr 4",
    "sg:city":"Neidling",
    "sg:orig_category":"Musikunterricht",
    "sg:phone":"+43 2741 7588",
    "sg:postcode":"3110",
    "sg:province":"Nieder\u00f6sterreich",
    "wof:name":"Musikschule Neidling",
    "wof:placetype":"venue"
},
  "geometry": {"coordinates":[15.5581502914,48.2391738892],"type":"Point"}
}