{
  "type": "Feature",
  "properties": {
    "iso:country":"AT",
    "sg:address":"J\u00e4gerweg 4",
    "sg:city":"Wels",
    "sg:orig_category":"Lehrmittel",
    "sg:phone":"+43 4372 4246640",
    "sg:postcode":"4600",
    "sg:province":"Ober\u00f6sterreich",
    "wof:name":"Ebner Hubert Verlags GmbH",
    "wof:placetype":"venue"
},
  "geometry": {"coordinates":[14.0434646606,48.154712677],"type":"Point"}
}