{
  "type": "Feature",
  "properties": {
    "addr:full":"J\u00e4gerweg 4 Wels Ober\u00f6sterreich 4600",
    "addr:housenumber":"4",
    "addr:postcode":"4600",
    "addr:street":"Jaegerweg;Oberoesterreich",
    "iso:country":"AT",
    "sg:address":"J\u00e4gerweg 4",
    "sg:city":"Wels",
    "sg:orig_category":"Lehrmittel",
    "sg:phone":"+43 4372 4246640",
    "sg:postcode":"4600",
    "sg:province":"Ober\u00f6sterreich",
    "wof:name":"Ebner Hubert Verlags GmbH",
    "wof:placetype":"venue"
},
  "geometry": {"coordinates":[14.0434646606,48.154712677],"type":"Point"}
}