{
  "type": "Feature",
  "properties": {
    "addr:full":"Waagg 4 Wien Wien 1040",
    "addr:housenumber":"4",
    "addr:postcode":"1040",
    "addr:street":"Waagg",
    "iso:country":"AT",
    "sg:address":"Waagg 4",
    "sg:city":"Wien",
    "sg:orig_category":"\u00c3\u201erzte / F Allgemeinmedizin",
    "sg:phone":"+43 1 5879174",
    "sg:postcode":"1040",
    "sg:province":"Wien",
    "wof:name":"Hofmann-Pantlitschko Andrea Dr",
    "wof:placetype":"venue"
},
  "geometry": {"coordinates":[16.3662281036,48.1951408386],"type":"Point"}
}