{
  "type": "Feature",
  "properties": {
    "addr:full":"Klagenfurter Str 24 Villach K\u00e4rnten 9500",
    "addr:housenumber":"24",
    "addr:postcode":"9500",
    "addr:street":"Str;Kaernten",
    "iso:country":"AT",
    "sg:address":"Klagenfurter Str 24",
    "sg:city":"Villach",
    "sg:orig_category":"Friseure U Frisiersalons",
    "sg:phone":"+43 4342 42216641",
    "sg:postcode":"9500",
    "sg:province":"K\u00e4rnten",
    "wof:name":"Das Traum-Haarstudio",
    "wof:placetype":"venue"
},
  "geometry": {"coordinates":[13.8515396118,46.6176338196],"type":"Point"}
}