{
  "type": "Feature",
  "properties": {
    "addr:full":"Wiesenweg 53 Rohrmoos-Untertal Steiermark 8971",
    "addr:housenumber":"53",
    "addr:postcode":"8971",
    "addr:street":"Wiesenweg",
    "iso:country":"AT",
    "sg:address":"Wiesenweg 53",
    "sg:city":"Rohrmoos-Untertal",
    "sg:orig_category":"Pensionen / Privatzimmer",
    "sg:phone":"+43 4336 8761258",
    "sg:postcode":"8971",
    "sg:province":"Steiermark",
    "wof:name":"Rettenbacher Franz",
    "wof:placetype":"venue"
},
  "geometry": {"coordinates":[13.6753616333,47.3862915039],"type":"Point"}
}