{
  "type": "Feature",
  "properties": {
    "addr:full":"Amstettner Str 1 Seitenstetten Nieder\u00f6sterreich 3353",
    "addr:housenumber":"1",
    "addr:postcode":"3353",
    "addr:street":"Str",
    "iso:country":"AT",
    "sg:address":"Amstettner Str 1",
    "sg:city":"Seitenstetten",
    "sg:orig_category":"\u00c3\u201erzte / F Allgemeinmedizin",
    "sg:phone":"+43 7477 433110",
    "sg:postcode":"3353",
    "sg:province":"Nieder\u00f6sterreich",
    "wof:name":"Derfler Ernst Dr",
    "wof:placetype":"venue"
},
  "geometry": {"coordinates":[14.6547966003,48.0366401672],"type":"Point"}
}