{
  "type": "Feature",
  "properties": {
    "addr:full":"Nr 32 Vitis Nieder\u00f6sterreich 3902",
    "addr:postcode":"3902",
    "addr:street":"Nr;Niederoesterreich",
    "iso:country":"AT",
    "sg:address":"Nr 32",
    "sg:city":"Vitis",
    "sg:orig_category":"Datenverarbeitung",
    "sg:phone":"+43 2841 20030",
    "sg:postcode":"3902",
    "sg:province":"Nieder\u00f6sterreich",
    "wof:name":"fab4minds Informationstechnik GmbH",
    "wof:placetype":"venue"
},
  "geometry": {"coordinates":[15.183391571,48.7590255737],"type":"Point"}
}