{
  "type": "Feature",
  "properties": {
    "addr:full":"Hauptstr 8 St. Paul im Lavanttal K\u00e4rnten 9470",
    "addr:housenumber":"8",
    "addr:postcode":"9470",
    "addr:street":"Hauptstr",
    "iso:country":"AT",
    "sg:address":"Hauptstr 8",
    "sg:city":"St. Paul im Lavanttal",
    "sg:orig_category":"Bars-Cafes",
    "sg:phone":"+43 4357 3616",
    "sg:postcode":"9470",
    "sg:province":"K\u00e4rnten",
    "wof:name":"Cafe Bar 122 Loibnegger Heinz Peter",
    "wof:placetype":"venue"
},
  "geometry": {"coordinates":[14.8694839478,46.7011795044],"type":"Point"}
}