{
  "type": "Feature",
  "properties": {
    "iso:country":"AT",
    "sg:address":"Gewerbestr 2",
    "sg:city":"Uttendorf",
    "sg:orig_category":"Holzbearbeitungsmaschinen U -Werkzeuge",
    "sg:phone":"+43 4377 244191",
    "sg:postcode":"5261",
    "sg:province":"Ober\u00f6sterreich",
    "wof:name":"Z\u00f6ttl Willi",
    "wof:placetype":"venue"
},
  "geometry": {"coordinates":[13.1211032867,48.1652984619],"type":"Point"}
}