{
  "type": "Feature",
  "properties": {
    "addr:full":"Viktringer Pl 7 Klagenfurt-Viktring K\u00e4rnten 9073",
    "addr:housenumber":"7",
    "addr:postcode":"9073",
    "addr:street":"Viktringer Pl;Kaernten",
    "iso:country":"AT",
    "sg:address":"Viktringer Pl 7",
    "sg:city":"Klagenfurt-Viktring",
    "sg:orig_category":"Fitnesscenter",
    "sg:phone":"+43 4346 3282300",
    "sg:postcode":"9073",
    "sg:province":"K\u00e4rnten",
    "wof:name":"Atrium - Sauna u Squash Center",
    "wof:placetype":"venue"
},
  "geometry": {"coordinates":[14.2694349289,46.5940246582],"type":"Point"}
}