{
  "type": "Feature",
  "properties": {
    "iso:country":"AT",
    "sg:address":"Ludwig-Binder-Str 13",
    "sg:city":"Gleisdorf",
    "sg:orig_category":"Personalbereitstellung",
    "sg:phone":"+43 4331 12385120",
    "sg:postcode":"8200",
    "sg:province":"Steiermark",
    "wof:name":"MANPOWER Personalservice GmbH",
    "wof:placetype":"venue"
},
  "geometry": {"coordinates":[15.7068510056,47.1058273315],"type":"Point"}
}