{
  "type": "Feature",
  "properties": {
    "addr:full":"Markomannenstr 13 Wien Wien 1220",
    "addr:housenumber":"13",
    "addr:postcode":"1220",
    "addr:street":"Markomannenstr",
    "iso:country":"AT",
    "sg:address":"Markomannenstr 13",
    "sg:city":"Wien",
    "sg:orig_category":"Maler, Anstreicher U Lackierer",
    "sg:phone":"+43 4313 197477",
    "sg:postcode":"1220",
    "sg:province":"Wien",
    "wof:name":"Praher u Math\u00e4 MalereibetriebsgesmbH",
    "wof:placetype":"venue"
},
  "geometry": {"coordinates":[16.4569396973,48.2531661987],"type":"Point"}
}