{
  "type": "Feature",
  "properties": {
    "iso:country":"AT",
    "sg:address":"Hauptstr 13",
    "sg:city":"Gallneukirchen",
    "sg:orig_category":"Restaurants: Chinesisch",
    "sg:phone":"+43 7235 64284",
    "sg:postcode":"4210",
    "sg:province":"Ober\u00f6sterreich",
    "wof:name":"China-Restaurant Long Yuan",
    "wof:placetype":"venue"
},
  "geometry": {"coordinates":[14.4156188965,48.3529815674],"type":"Point"}
}