{
  "type": "Feature",
  "properties": {
    "addr:full":"Adolf Czettel-G 3 Wien Wien 1160",
    "addr:housenumber":"3",
    "addr:postcode":"1160",
    "iso:country":"AT",
    "sg:address":"Adolf Czettel-G 3",
    "sg:city":"Wien",
    "sg:orig_category":"Werbegrafik- U Grafik-Design",
    "sg:phone":"+43 1 78698980",
    "sg:postcode":"1160",
    "sg:province":"Wien",
    "wof:name":"b quadrat",
    "wof:placetype":"venue"
},
  "geometry": {"coordinates":[16.307756424,48.2051963806],"type":"Point"}
}