{
  "type": "Feature",
  "properties": {
    "addr:full":"Marianneng 17 Wien Wien 1090",
    "addr:housenumber":"17",
    "addr:postcode":"1090",
    "addr:street":"Marianneng",
    "iso:country":"AT",
    "sg:address":"Marianneng 17",
    "sg:city":"Wien",
    "sg:orig_category":"Medizintechnik",
    "sg:phone":"+43 1 40262510",
    "sg:postcode":"1090",
    "sg:province":"Wien",
    "wof:name":"Reiner Carl GmbH",
    "wof:placetype":"venue"
},
  "geometry": {"coordinates":[16.3484020233,48.2159500122],"type":"Point"}
}