{
  "type": "Feature",
  "properties": {
    "addr:full":"Oberdorf 14 Heiterwang Tirol 6611",
    "addr:housenumber":"14",
    "addr:postcode":"6611",
    "addr:street":"Oberdorf;Tirol",
    "iso:country":"AT",
    "sg:address":"Oberdorf 14",
    "sg:city":"Heiterwang",
    "sg:orig_category":"Non-Classified Establishments",
    "sg:phone":"+43 5674 5629",
    "sg:postcode":"6611",
    "sg:province":"Tirol",
    "wof:name":"Pfarramt",
    "wof:placetype":"venue"
},
  "geometry": {"coordinates":[10.7468833923,47.4442520142],"type":"Point"}
}