{
  "type": "Feature",
  "properties": {
    "addr:full":"Strandg 17 Podersdorf am See Burgenland 7141",
    "addr:housenumber":"17",
    "addr:postcode":"7141",
    "addr:street":"Strandg",
    "iso:country":"AT",
    "sg:address":"Strandg 17",
    "sg:city":"Podersdorf am See",
    "sg:orig_category":"Appartements / Ferienwohnungen",
    "sg:phone":"+43 2177 2950",
    "sg:postcode":"7141",
    "sg:province":"Burgenland",
    "wof:name":"Lackner Martina",
    "wof:placetype":"venue"
},
  "geometry": {"coordinates":[16.8289680481,47.8552856445],"type":"Point"}
}