{
  "type": "Feature",
  "properties": {
    "addr:full":"Nr 18 Weiten Nieder\u00f6sterreich 3653",
    "addr:postcode":"3653",
    "addr:street":"Nr 18",
    "iso:country":"AT",
    "sg:address":"Nr 18",
    "sg:city":"Weiten",
    "sg:orig_category":"Fenster",
    "sg:phone":"+43 4327 5880915",
    "sg:postcode":"3653",
    "sg:province":"Nieder\u00f6sterreich",
    "wof:name":"Kurnik Johannes",
    "wof:placetype":"venue"
},
  "geometry": {"coordinates":[15.275894165,48.3244972229],"type":"Point"}
}