{
  "type": "Feature",
  "properties": {
    "iso:country":"AT",
    "sg:address":"Theaterg 3",
    "sg:city":"Gmunden",
    "sg:orig_category":"Apotheken",
    "sg:phone":"+43 7612645100",
    "sg:postcode":"4810",
    "sg:province":"Ober\u00f6sterreich",
    "wof:name":"See Apotheke Mag pharm K Grobstein",
    "wof:placetype":"venue"
},
  "geometry": {"coordinates":[13.799077034,47.9181861877],"type":"Point"}
}