{
  "type": "Feature",
  "properties": {
    "addr:full":"Mantlerg 45 Wien Wien 1130",
    "addr:housenumber":"45",
    "addr:postcode":"1130",
    "addr:street":"Mantlerg",
    "iso:country":"AT",
    "sg:address":"Mantlerg 45",
    "sg:city":"Wien",
    "sg:orig_category":"Architekten",
    "sg:phone":"+43 1 7283282",
    "sg:postcode":"1130",
    "sg:province":"Wien",
    "wof:name":"Brauner Wolfgang Arch Dipl-Ing",
    "wof:placetype":"venue"
},
  "geometry": {"coordinates":[16.2801532745,48.1906852722],"type":"Point"}
}