{
  "type": "Feature",
  "properties": {
    "iso:country":"AT",
    "sg:address":"Wieden-Klausen 16",
    "sg:city":"Straden",
    "sg:orig_category":"Pensionen / Privatzimmer",
    "sg:phone":"+43 3473 73400",
    "sg:postcode":"8345",
    "sg:province":"Steiermark",
    "wof:name":"Landhaus Bender",
    "wof:placetype":"venue"
},
  "geometry": {"coordinates":[15.8508939743,46.7938499451],"type":"Point"}
}