{
  "type": "Feature",
  "properties": {
    "addr:full":"Lerchenfelder G\u00fcrtel 43/5/2 Wien Wien 1160",
    "addr:housenumber":"43 / 5 / 2",
    "addr:postcode":"1160",
    "addr:street":"Lerchenfelder",
    "iso:country":"AT",
    "sg:address":"Lerchenfelder G\u00fcrtel 43/5/2",
    "sg:city":"Wien",
    "sg:classifiers":[
        {
            "category":"Professional",
            "subcategory":"Engineering",
            "type":"Services"
        }
    ],
    "sg:phone":"+43 1 8974122",
    "sg:postcode":"1160",
    "sg:province":"Wien",
    "sg:tags":[
        "organizational",
        "information",
        "consulting",
        "technology"
    ],
    "sg:website":"punkt.at",
    "wof:name":"punkt.Intelligente Informationszug\u00e4nge OEG",
    "wof:placetype":"venue"
},
  "geometry": {"coordinates":[16.2961292267,48.214931488],"type":"Point"}
}