{
  "type": "Feature",
  "properties": {
    "iso:country":"AT",
    "sg:address":"Industriestr 13",
    "sg:city":"Gro\u00df-Enzersdorf",
    "sg:orig_category":"Installationsunternehmen",
    "sg:phone":"+43 2249 7440",
    "sg:postcode":"2301",
    "sg:province":"Nieder\u00f6sterreich",
    "wof:name":"TWG Installationen K\u00e4lte Klima Ing",
    "wof:placetype":"venue"
},
  "geometry": {"coordinates":[16.571144104,48.1929702759],"type":"Point"}
}