{
  "type": "Feature",
  "properties": {
    "iso:country":"AT",
    "sg:address":"Sachsenplatz 4-6",
    "sg:city":"Wien",
    "sg:classifiers":[
        {
            "category":"Professional",
            "subcategory":"Art Services",
            "type":"Services"
        }
    ],
    "sg:phone":"+43 1 33024270",
    "sg:postcode":"1200",
    "sg:province":"Wien",
    "sg:tags":[
        "book",
        "artist"
    ],
    "sg:website":"boehlau.at",
    "wof:name":"B\u00f6hlau Verlag Ges.m.b.H. & Co KG",
    "wof:placetype":"venue"
},
  "geometry": {"coordinates":[16.3758735657,48.2318344116],"type":"Point"}
}