{
  "type": "Feature",
  "properties": {
    "addr:full":"Neubergham 18 St. Peter am Hart Ober\u00f6sterreich 4963",
    "addr:housenumber":"18",
    "addr:postcode":"4963",
    "addr:street":"Neubergham",
    "iso:country":"AT",
    "sg:address":"Neubergham 18",
    "sg:city":"St. Peter am Hart",
    "sg:orig_category":"Fassaden",
    "sg:phone":"+43 7722 65326",
    "sg:postcode":"4963",
    "sg:province":"Ober\u00f6sterreich",
    "wof:name":"Penias & Team",
    "wof:placetype":"venue"
},
  "geometry": {"coordinates":[13.1215143204,48.2605628967],"type":"Point"}
}