{
  "type": "Feature",
  "properties": {
    "addr:full":"Werksgasse 57 Rottenmann Steiermark 8786",
    "addr:housenumber":"57",
    "addr:postcode":"8786",
    "addr:street":"Werksgasse",
    "iso:country":"AT",
    "sg:address":"Werksgasse 57",
    "sg:city":"Rottenmann",
    "sg:orig_category":"Bottle Coolers",
    "sg:phone":"+43 3614 24510",
    "sg:postcode":"8786",
    "sg:province":"Steiermark",
    "sg:website":"aht.at",
    "wof:name":"AHT Cooling Systems GmbH & Co KG",
    "wof:placetype":"venue"
},
  "geometry": {"coordinates":[14.3548202515,47.5259361267],"type":"Point"}
}