{
  "type": "Feature",
  "properties": {
    "addr:full":"Gschwandnerg 26-28 Wien Wien 1170",
    "addr:postcode":"26-28;1170",
    "iso:country":"AT",
    "sg:address":"Gschwandnerg 26-28",
    "sg:city":"Wien",
    "sg:orig_category":"Ingenieurkonsulenten / Zivilingenieure",
    "sg:phone":"+43 1 48935520",
    "sg:postcode":"1170",
    "sg:province":"Wien",
    "wof:name":"Siegl Karl Dipl-Ing",
    "wof:placetype":"venue"
},
  "geometry": {"coordinates":[16.3246059418,48.2174377441],"type":"Point"}
}