{
  "type": "Feature",
  "properties": {
    "iso:country":"AT",
    "sg:address":"Angerner Bundesstr",
    "sg:city":"Deutsch Wagram",
    "sg:orig_category":"Lebensmittel / Einzelhandel",
    "sg:phone":"+43 4322 4720109",
    "sg:postcode":"2232",
    "sg:province":"Nieder\u00f6sterreich",
    "wof:name":"Hofer KG",
    "wof:placetype":"venue"
},
  "geometry": {"coordinates":[16.5584506989,48.2957572937],"type":"Point"}
}