{
  "type": "Feature",
  "properties": {
    "addr:full":"Landstr 76/3 Linz Ober\u00f6sterreich 4020",
    "addr:housenumber":"76 / 3",
    "addr:postcode":"4020",
    "addr:street":"Landstr",
    "iso:country":"AT",
    "sg:address":"Landstr 76/3",
    "sg:city":"Linz",
    "sg:orig_category":"Psychotherapie",
    "sg:phone":"+43 4373 2606768",
    "sg:postcode":"4020",
    "sg:province":"Ober\u00f6sterreich",
    "wof:name":"Dunzinger Michael Dr",
    "wof:placetype":"venue"
},
  "geometry": {"coordinates":[14.2915210724,48.2969894409],"type":"Point"}
}