{
  "type": "Feature",
  "properties": {
    "addr:full":"Trattnachtalstrasse 1a Grieskirchen Ober\u00f6sterreich 4710",
    "addr:housenumber":"1a",
    "addr:postcode":"4710",
    "addr:street":"Trattnachtalstrasse",
    "iso:country":"AT",
    "sg:address":"Trattnachtalstrasse 1a",
    "sg:city":"Grieskirchen",
    "sg:orig_category":"Furniture, General",
    "sg:phone":"+43 7248 62744",
    "sg:postcode":"4710",
    "sg:province":"Ober\u00f6sterreich",
    "wof:name":"Peter Pachner",
    "wof:placetype":"venue"
},
  "geometry": {"coordinates":[13.8203735352,48.2365760803],"type":"Point"}
}