{
  "type": "Feature",
  "properties": {
    "addr:full":"Schulstr 10 Gresten Nieder\u00f6sterreich 3264",
    "addr:housenumber":"10",
    "addr:postcode":"3264",
    "addr:street":"Schulstr",
    "iso:country":"AT",
    "sg:address":"Schulstr 10",
    "sg:city":"Gresten",
    "sg:orig_category":"Dachdeckereien",
    "sg:phone":"+43 7487 2001",
    "sg:postcode":"3264",
    "sg:province":"Nieder\u00f6sterreich",
    "wof:name":"HA & HO Dachprofi GmbH",
    "wof:placetype":"venue"
},
  "geometry": {"coordinates":[15.0256729126,47.9860305786],"type":"Point"}
}