{
  "type": "Feature",
  "properties": {
    "addr:full":"Aichegg 39a Schwanberg Steiermark 8541",
    "addr:housenumber":"39a",
    "addr:postcode":"8541",
    "addr:street":"Aichegg",
    "iso:country":"AT",
    "sg:address":"Aichegg 39a",
    "sg:city":"Schwanberg",
    "sg:orig_category":"Physiotherapie",
    "sg:phone":"+43 3467 78300",
    "sg:postcode":"8541",
    "sg:province":"Steiermark",
    "wof:name":"Kiegerl Gabriele Dipl-PT",
    "wof:placetype":"venue"
},
  "geometry": {"coordinates":[15.2062101364,46.766998291],"type":"Point"}
}