{
  "type": "Feature",
  "properties": {
    "addr:full":"Riegerting 6 Mehrnbach Ober\u00f6sterreich 4941",
    "addr:housenumber":"6",
    "addr:postcode":"4941",
    "addr:street":"Riegerting",
    "iso:country":"AT",
    "sg:address":"Riegerting 6",
    "sg:city":"Mehrnbach",
    "sg:classifiers":[
        {
            "category":"Taxi",
            "type":"Transportation"
        }
    ],
    "sg:phone":"+43 4366 43412658",
    "sg:postcode":"4941",
    "sg:province":"Ober\u00f6sterreich",
    "sg:tags":[
        "personentransporte",
        "u"
    ],
    "wof:name":"M & M Taxi u Mietwagen GesmbH",
    "wof:placetype":"venue"
},
  "geometry": {"coordinates":[13.403418541,48.1779556274],"type":"Point"}
}