{
  "type": "Feature",
  "properties": {
    "addr:full":"St. Georgener Str 4 Wildon Steiermark 8410",
    "addr:housenumber":"4",
    "addr:postcode":"8410",
    "addr:street":"St. Georgener Str;Steiermark",
    "iso:country":"AT",
    "sg:address":"St. Georgener Str 4",
    "sg:city":"Wildon",
    "sg:orig_category":"Feinkost",
    "sg:phone":"+43 3182 3287",
    "sg:postcode":"8410",
    "sg:province":"Steiermark",
    "wof:name":"Mitteregger Renate",
    "wof:placetype":"venue"
},
  "geometry": {"coordinates":[15.5214958191,46.8868408203],"type":"Point"}
}