{
  "type": "Feature",
  "properties": {
    "iso:country":"AT",
    "sg:address":"St. Georgener Str 4",
    "sg:city":"Wildon",
    "sg:orig_category":"Feinkost",
    "sg:phone":"+43 3182 3287",
    "sg:postcode":"8410",
    "sg:province":"Steiermark",
    "wof:name":"Mitteregger Renate",
    "wof:placetype":"venue"
},
  "geometry": {"coordinates":[15.5214958191,46.8868408203],"type":"Point"}
}