{
  "type": "Feature",
  "properties": {
    "iso:country":"AT",
    "sg:address":"Melicharstrasse 4a",
    "sg:city":"Linz",
    "sg:classifiers":[
        {
            "category":"Professional",
            "subcategory":"Advertising",
            "type":"Services"
        }
    ],
    "sg:phone":"+43 732 651488",
    "sg:postcode":"4020",
    "sg:province":"Ober\u00f6sterreich",
    "sg:tags":[
        "article",
        "porcelain",
        "ceramic"
    ],
    "sg:website":"photokeramik.at",
    "wof:name":"Josef G\u00fcnthner Ges.m.b.H. Glas- und Porzellanmalerei Porzellanfotos",
    "wof:placetype":"venue"
},
  "geometry": {"coordinates":[14.2997226715,48.2885169983],"type":"Point"}
}