{
  "type": "Feature",
  "properties": {
    "addr:full":"Pinnisweg 44 Neustift im Stubaital Tirol 6167",
    "addr:housenumber":"44",
    "addr:postcode":"6167",
    "addr:street":"Pinnisweg;Tirol",
    "iso:country":"AT",
    "sg:address":"Pinnisweg 44",
    "sg:city":"Neustift im Stubaital",
    "sg:orig_category":"Lebensmittel / Einzelhandel",
    "sg:phone":"+43 5226 2318",
    "sg:postcode":"6167",
    "sg:province":"Tirol",
    "wof:name":"Spar Markt Inh Horst Kindl",
    "wof:placetype":"venue"
},
  "geometry": {"coordinates":[11.32654953,47.1181564331],"type":"Point"}
}