{
  "type": "Feature",
  "properties": {
    "addr:full":"Claudiastr 24 Innsbruck Tirol 6020",
    "addr:housenumber":"24",
    "addr:postcode":"6020",
    "addr:street":"Claudiastr;Tirol",
    "iso:country":"AT",
    "sg:address":"Claudiastr 24",
    "sg:city":"Innsbruck",
    "sg:orig_category":"Friseure U Frisiersalons",
    "sg:phone":"+43 4351 2565938",
    "sg:postcode":"6020",
    "sg:province":"Tirol",
    "wof:name":"Coiffeur Cazzonelli",
    "wof:placetype":"venue"
},
  "geometry": {"coordinates":[11.4054403305,47.2752990723],"type":"Point"}
}