{
  "type": "Feature",
  "properties": {
    "addr:full":"Esterhazyg 19 Wien Wien 1060",
    "addr:housenumber":"19",
    "addr:postcode":"1060",
    "addr:street":"Esterhazyg",
    "iso:country":"AT",
    "sg:address":"Esterhazyg 19",
    "sg:city":"Wien",
    "sg:orig_category":"Werbegestalter",
    "sg:phone":"+43 1 5860852",
    "sg:postcode":"1060",
    "sg:province":"Wien",
    "wof:name":"Heinzle Lothar Dipl-Graph Mag",
    "wof:placetype":"venue"
},
  "geometry": {"coordinates":[16.350069046,48.1960945129],"type":"Point"}
}