{
  "type": "Feature",
  "properties": {
    "addr:full":"Kirchg 8 Feldkirchen in K\u00e4rnten K\u00e4rnten 9560",
    "addr:housenumber":"8",
    "addr:postcode":"9560",
    "addr:street":"Kirchg;Kaernten",
    "iso:country":"AT",
    "sg:address":"Kirchg 8",
    "sg:city":"Feldkirchen in K\u00e4rnten",
    "sg:orig_category":"Bauunternehmen",
    "sg:phone":"+43 4342 7639230",
    "sg:postcode":"9560",
    "sg:province":"K\u00e4rnten",
    "wof:name":"Aktivbau Bau GmbH",
    "wof:placetype":"venue"
},
  "geometry": {"coordinates":[14.0925807953,46.7250442505],"type":"Point"}
}