{
  "type": "Feature",
  "properties": {
    "addr:full":"Nr 133 Steinhaus Ober\u00f6sterreich 4641",
    "addr:postcode":"4641",
    "addr:street":"Nr 133",
    "iso:country":"AT",
    "sg:address":"Nr 133",
    "sg:city":"Steinhaus",
    "sg:orig_category":"Lichtwerbung",
    "sg:phone":"+43 7242 27263",
    "sg:postcode":"4641",
    "sg:province":"Ober\u00f6sterreich",
    "wof:name":"GMB Exklusivwerbung Handelsagentur Brummaier OEG",
    "wof:placetype":"venue"
},
  "geometry": {"coordinates":[14.0203199387,48.1157035828],"type":"Point"}
}