{
  "type": "Feature",
  "properties": {
    "iso:country":"AT",
    "sg:address":"Karl-Morre-Str 58",
    "sg:city":"Graz",
    "sg:orig_category":"Musikunterricht",
    "sg:phone":"+43 4331 6573163",
    "sg:postcode":"8020",
    "sg:province":"Steiermark",
    "wof:name":"Johann-Joseph-Fux-Konservatorium",
    "wof:placetype":"venue"
},
  "geometry": {"coordinates":[15.4007701874,47.0667800903],"type":"Point"}
}