{
  "type": "Feature",
  "properties": {
    "iso:country":"AT",
    "sg:address":"Rablstrasse 25",
    "sg:city":"Wels",
    "sg:classifiers":[
        {
            "category":"Manufacturing",
            "subcategory":"Jewelry",
            "type":"Manufacturing & Wholesale Goods"
        }
    ],
    "sg:phone":"+43 7242 445150",
    "sg:postcode":"4600",
    "sg:province":"Ober\u00f6sterreich",
    "sg:tags":[
        "jewellery",
        "fancy"
    ],
    "wof:name":"HERMEX-BIJOU Hermann Hufnagl",
    "wof:placetype":"venue"
},
  "geometry": {"coordinates":[14.0219202042,48.1604499817],"type":"Point"}
}