{
  "type": "Feature",
  "properties": {
    "addr:full":"Josef Meinrad-Weg 1 Gro\u00dfgmain Salzburg 5084",
    "addr:housenumber":"1",
    "addr:postcode":"5084",
    "addr:street":"Meinrad-Weg;Salzburg",
    "iso:country":"AT",
    "sg:address":"Josef Meinrad-Weg 1",
    "sg:city":"Gro\u00dfgmain",
    "sg:orig_category":"Non-Classified Establishments",
    "sg:phone":"+43 6247 82450",
    "sg:postcode":"5084",
    "sg:province":"Salzburg",
    "wof:name":"Pfarramt",
    "wof:placetype":"venue"
},
  "geometry": {"coordinates":[12.0809497833,48.0439414978],"type":"Point"}
}