{
  "type": "Feature",
  "properties": {
    "addr:full":"Auweg 29 Flaurling Tirol 6403",
    "addr:housenumber":"29",
    "addr:postcode":"6403",
    "addr:street":"Auweg;Tirol",
    "iso:country":"AT",
    "sg:address":"Auweg 29",
    "sg:city":"Flaurling",
    "sg:orig_category":"Spenglereien",
    "sg:phone":"+43 5262 63856",
    "sg:postcode":"6403",
    "sg:province":"Tirol",
    "wof:name":"Dosch Martin",
    "wof:placetype":"venue"
},
  "geometry": {"coordinates":[11.1401786804,47.2888565063],"type":"Point"}
}