{
  "type": "Feature",
  "properties": {
    "addr:full":"Burgg 105-107 Wien Wien 1070",
    "addr:housenumber":"105-107",
    "addr:postcode":"1070",
    "iso:country":"AT",
    "sg:address":"Burgg 105-107",
    "sg:city":"Wien",
    "sg:orig_category":"Lebensmittel / Einzelhandel",
    "sg:phone":"+43 1 9291711",
    "sg:postcode":"1070",
    "sg:province":"Wien",
    "wof:name":"MONDO Lebensmitteldiskonter",
    "wof:placetype":"venue"
},
  "geometry": {"coordinates":[16.3409252167,48.2042732239],"type":"Point"}
}