{
  "type": "Feature",
  "properties": {
    "addr:full":"Gurten Ober\u00f6sterreich 4942",
    "addr:postcode":"4942",
    "addr:street":"Oberoesterreich",
    "iso:country":"AT",
    "sg:city":"Gurten",
    "sg:orig_category":"Volksschulen",
    "sg:phone":"+43 7757 661420",
    "sg:postcode":"4942",
    "sg:province":"Ober\u00f6sterreich",
    "wof:name":"Volksschule",
    "wof:placetype":"venue"
},
  "geometry": {"coordinates":[13.381606102,48.2210769653],"type":"Point"}
}