{
  "type": "Feature",
  "properties": {
    "iso:country":"AT",
    "sg:address":"Paulanerg 7",
    "sg:city":"Wien",
    "sg:orig_category":"Friseure U Frisiersalons",
    "sg:phone":"+43 4315 863427",
    "sg:postcode":"1040",
    "sg:province":"Wien",
    "wof:name":"Kamm Schere & Elisabeth",
    "wof:placetype":"venue"
},
  "geometry": {"coordinates":[16.3666801453,48.1957588196],"type":"Point"}
}