{
  "type": "Feature",
  "properties": {
    "addr:full":"Wollzeile 5 Wien Wien 1010",
    "addr:housenumber":"5",
    "addr:postcode":"1010",
    "addr:street":"Wollzeile",
    "iso:country":"AT",
    "sg:address":"Wollzeile 5",
    "sg:city":"Wien",
    "sg:orig_category":"Boutiquen",
    "sg:phone":"+43 1 5132112",
    "sg:postcode":"1010",
    "sg:province":"Wien",
    "wof:name":"Scholz Heidi",
    "wof:placetype":"venue"
},
  "geometry": {"coordinates":[16.3743095398,48.2093887329],"type":"Point"}
}