{
  "type": "Feature",
  "properties": {
    "iso:country":"AT",
    "sg:address":"Schillerstr 26",
    "sg:city":"Lienz",
    "sg:orig_category":"Fenster",
    "sg:phone":"+43 4852 64982",
    "sg:postcode":"9900",
    "sg:province":"Tirol",
    "wof:name":"Pontiller Edith",
    "wof:placetype":"venue"
},
  "geometry": {"coordinates":[12.7801904678,46.8308181763],"type":"Point"}
}