{
  "type": "Feature",
  "properties": {
    "addr:full":"Ruster Str 93 Eisenstadt Burgenland 7000",
    "addr:postcode":"7000",
    "addr:street":"Str 93",
    "iso:country":"AT",
    "sg:address":"Ruster Str 93",
    "sg:city":"Eisenstadt",
    "sg:orig_category":"Elektroinstallationsunternehmen",
    "sg:phone":"+43 2682 72217",
    "sg:postcode":"7000",
    "sg:province":"Burgenland",
    "wof:name":"Elektro Gradinger Christian",
    "wof:placetype":"venue"
},
  "geometry": {"coordinates":[16.5248508453,47.840511322],"type":"Point"}
}