{
  "type": "Feature",
  "properties": {
    "iso:country":"AT",
    "sg:address":"Niederland 75",
    "sg:city":"Unken",
    "sg:orig_category":"Tapezierer U Dekorateure",
    "sg:phone":"+43 6589 42560",
    "sg:postcode":"5091",
    "sg:province":"Salzburg",
    "wof:name":"Herbst Gerhard",
    "wof:placetype":"venue"
},
  "geometry": {"coordinates":[12.7346830368,47.6553764343],"type":"Point"}
}