{
  "type": "Feature",
  "properties": {
    "addr:full":"Dr.-L.-Jungfer-Str. Feistritz im Rosental K\u00e4rnten 9181",
    "addr:postcode":"9181",
    "addr:street":"Kaernten",
    "iso:country":"AT",
    "sg:address":"Dr.-L.-Jungfer-Str.",
    "sg:city":"Feistritz im Rosental",
    "sg:classifiers":[
        {
            "category":"Shopping",
            "subcategory":"Computers & Home Electronics",
            "type":"Retail Goods"
        }
    ],
    "sg:phone":"+43 4342 282036",
    "sg:postcode":"9181",
    "sg:province":"K\u00e4rnten",
    "sg:tags":[
        "electronic",
        "electrical",
        "equipment"
    ],
    "wof:name":"B\u00c4REN BATTERIE GES.MBH",
    "wof:placetype":"venue"
},
  "geometry": {"coordinates":[14.1687097549,46.523349762],"type":"Point"}
}