{
  "type": "Feature",
  "properties": {
    "addr:full":"Quellenstr 167 Wien Wien 1100",
    "addr:housenumber":"167",
    "addr:postcode":"1100",
    "iso:country":"AT",
    "sg:address":"Quellenstr 167",
    "sg:city":"Wien",
    "sg:orig_category":"Friseure U Frisiersalons",
    "sg:phone":"+43 1 6023185",
    "sg:postcode":"1100",
    "sg:province":"Wien",
    "wof:name":"Rolland Hairtrend",
    "wof:placetype":"venue"
},
  "geometry": {"coordinates":[16.3662147522,48.1760215759],"type":"Point"}
}