{
  "type": "Feature",
  "properties": {
    "iso:country":"AT",
    "sg:address":"Hauptstr 29",
    "sg:city":"Admont",
    "sg:orig_category":"Farben U Lacke / Einzelhandel",
    "sg:phone":"+43 4336 132811",
    "sg:postcode":"8911",
    "sg:province":"Steiermark",
    "wof:name":"Feuchter Farben OEG",
    "wof:placetype":"venue"
},
  "geometry": {"coordinates":[14.4607601166,47.5766487122],"type":"Point"}
}