{
  "type": "Feature",
  "properties": {
    "addr:full":"Wiener Str 622 Gars am Kamp Nieder\u00f6sterreich 3571",
    "addr:housenumber":"622",
    "addr:postcode":"3571",
    "iso:country":"AT",
    "sg:address":"Wiener Str 622",
    "sg:city":"Gars am Kamp",
    "sg:orig_category":"Lebensmittel / Einzelhandel",
    "sg:phone":"+43 2985 30703",
    "sg:postcode":"3571",
    "sg:province":"Nieder\u00f6sterreich",
    "wof:name":"Billa AG",
    "wof:placetype":"venue"
},
  "geometry": {"coordinates":[15.6756095886,48.598285675],"type":"Point"}
}