{
  "type": "Feature",
  "properties": {
    "addr:full":"Handelsstrasse 16 St. Veit an der Glan K\u00e4rnten 9300",
    "addr:housenumber":"16",
    "addr:postcode":"9300",
    "addr:street":"Handelsstrasse;Kaernten",
    "iso:country":"AT",
    "sg:address":"Handelsstrasse 16",
    "sg:city":"St. Veit an der Glan",
    "sg:classifiers":[
        {
            "category":"Professional",
            "subcategory":"Testing Lab",
            "type":"Services"
        }
    ],
    "sg:phone":"+43 4212 72026",
    "sg:postcode":"9300",
    "sg:province":"K\u00e4rnten",
    "sg:tags":[
        "test",
        "leak",
        "stand"
    ],
    "sg:website":"hemar-kanal.at",
    "wof:name":"HEMAR Ortungs- und Sanierungstechnik Ges.m.b.H.",
    "wof:placetype":"venue"
},
  "geometry": {"coordinates":[14.3486328125,46.7586326599],"type":"Point"}
}