{
  "type": "Feature",
  "properties": {
    "iso:country":"AT",
    "sg:address":"Leobersdorfer Strasse 26 ",
    "sg:city":"Berndorf",
    "sg:orig_category":"Seat Adjusting Systems For Vehicles Oem",
    "sg:phone":"+43 2672 835400",
    "sg:postcode":"2560",
    "sg:province":"Nieder\u00f6sterreich",
    "sg:website":"schukra.com",
    "wof:name":"Schukra Berndorf Ges.m.b.H.",
    "wof:placetype":"venue"
},
  "geometry": {"coordinates":[16.1215400696,47.9436302185],"type":"Point"}
}