{
  "type": "Feature",
  "properties": {
    "addr:full":"Triester Str. 203 1232",
    "addr:housenumber":"203",
    "addr:postcode":"1232",
    "addr:street":"Str.",
    "iso:country":"AT",
    "sg:address":"Triester Str. 203",
    "sg:classifiers":[
        {
            "category":"Professional",
            "subcategory":"Engineering",
            "type":"Services"
        }
    ],
    "sg:phone":"+43 4316 6797710",
    "sg:postcode":"1232",
    "sg:tags":[
        "machine",
        "-",
        "mechanical"
    ],
    "wof:name":"THEODOR R. RIST GMBH",
    "wof:placetype":"venue"
},
  "geometry": {"coordinates":[16.3355102539,48.1495018005],"type":"Point"}
}