{
  "type": "Feature",
  "properties": {
    "addr:full":"Siebenbrunnengasse 21 Wien Wien 1050",
    "addr:housenumber":"21",
    "addr:postcode":"1050",
    "addr:street":"Siebenbrunnengasse",
    "iso:country":"AT",
    "sg:address":"Siebenbrunnengasse 21",
    "sg:city":"Wien",
    "sg:orig_category":"Bildung And Forschung, Museen",
    "sg:phone":"+43 1 54665268",
    "sg:postcode":"1050",
    "sg:province":"Wien",
    "sg:website":"http://www.schwarzer.at",
    "wof:name":"Verlagsb\u00fcro Schwarzer",
    "wof:placetype":"venue"
},
  "geometry": {"coordinates":[16.3586845398,48.1871795654],"type":"Point"}
}