{
  "type": "Feature",
  "properties": {
    "addr:full":"Nr 40 Neudau Steiermark 8292",
    "addr:postcode":"8292",
    "addr:street":"Nr",
    "iso:country":"AT",
    "sg:address":"Nr 40",
    "sg:city":"Neudau",
    "sg:classifiers":[
        {
            "category":"Taxi",
            "type":"Transportation"
        }
    ],
    "sg:phone":"+43 4333 2654588",
    "sg:postcode":"8292",
    "sg:province":"Steiermark",
    "sg:tags":[
        "personentransporte",
        "u"
    ],
    "wof:name":"Gmoser Barbara",
    "wof:placetype":"venue"
},
  "geometry": {"coordinates":[16.1066532135,47.1972007751],"type":"Point"}
}