{
  "type": "Feature",
  "properties": {
    "addr:full":"Marktstr 20 Gro\u00df St. Florian Steiermark 8522",
    "addr:housenumber":"20",
    "addr:postcode":"8522",
    "addr:street":"Marktstr",
    "iso:country":"AT",
    "sg:address":"Marktstr 20",
    "sg:city":"Gro\u00df St. Florian",
    "sg:orig_category":"Non-Classified Establishments",
    "sg:phone":"+43 4334 642201",
    "sg:postcode":"8522",
    "sg:province":"Steiermark",
    "wof:name":"Draxler GesmbH",
    "wof:placetype":"venue"
},
  "geometry": {"coordinates":[-87.6220169067,34.8752098083],"type":"Point"}
}