{
  "type": "Feature",
  "properties": {
    "addr:full":"Haller Str 41 Innsbruck Tirol 6020",
    "addr:postcode":"6020",
    "addr:street":"Str 41;Tirol",
    "iso:country":"AT",
    "sg:address":"Haller Str 41",
    "sg:city":"Innsbruck",
    "sg:orig_category":"Tischlereien",
    "sg:phone":"+43 512 206068",
    "sg:postcode":"6020",
    "sg:province":"Tirol",
    "wof:name":"mg-interior",
    "wof:placetype":"venue"
},
  "geometry": {"coordinates":[11.4111700058,47.2803649902],"type":"Point"}
}