{
  "type": "Feature",
  "properties": {
    "addr:full":"Industriestrasse West 9 Kapfenberg Steiermark 8605",
    "addr:housenumber":"9",
    "addr:postcode":"8605",
    "addr:street":"Industriestrasse West",
    "iso:country":"AT",
    "sg:address":"Industriestrasse West 9",
    "sg:city":"Kapfenberg",
    "sg:classifiers":[
        {
            "category":"Professional",
            "subcategory":"Computer Services",
            "type":"Services"
        }
    ],
    "sg:phone":"+43 3862 335820",
    "sg:postcode":"8605",
    "sg:province":"Steiermark",
    "sg:tags":[
        "shredding",
        "file"
    ],
    "wof:name":"PAREK Papierverwertungs Ges.m.b.H.",
    "wof:placetype":"venue"
},
  "geometry": {"coordinates":[15.3425960541,47.4565429688],"type":"Point"}
}