{
  "type": "Feature",
  "properties": {
    "iso:country":"AT",
    "sg:address":"Nr 36",
    "sg:city":"Hirschegg",
    "sg:orig_category":"Volksschulen",
    "sg:phone":"+43 3141 2209",
    "sg:postcode":"8584",
    "sg:province":"Steiermark",
    "wof:name":"Volksschule",
    "wof:placetype":"venue"
},
  "geometry": {"coordinates":[14.9580583572,47.0195808411],"type":"Point"}
}