{
  "type": "Feature",
  "properties": {
    "iso:country":"AT",
    "sg:address":"Schachnern 39",
    "sg:city":"Heiligenblut",
    "sg:orig_category":"Sportschulen",
    "sg:phone":"+43 4366 43035829",
    "sg:postcode":"9844",
    "sg:province":"K\u00e4rnten",
    "wof:name":"Gassner Engelbert",
    "wof:placetype":"venue"
},
  "geometry": {"coordinates":[12.8756971359,47.0236473083],"type":"Point"}
}