{
  "type": "Feature",
  "properties": {
    "addr:full":"Grillparzerstr 51 Linz Ober\u00f6sterreich 4020",
    "addr:housenumber":"51",
    "addr:postcode":"4020",
    "addr:street":"Grillparzerstr",
    "iso:country":"AT",
    "sg:address":"Grillparzerstr 51",
    "sg:city":"Linz",
    "sg:orig_category":"Reinigungsservice",
    "sg:phone":"+43 732 650533",
    "sg:postcode":"4020",
    "sg:province":"Ober\u00f6sterreich",
    "wof:name":"Huemer Elefantenstark GmbH & Co KG",
    "wof:placetype":"venue"
},
  "geometry": {"coordinates":[14.3005275726,48.2897262573],"type":"Point"}
}