{
  "type": "Feature",
  "properties": {
    "addr:full":"Hauptstr 94 Lannach Steiermark 8502",
    "addr:housenumber":"94",
    "addr:postcode":"8502",
    "addr:street":"Hauptstr",
    "iso:country":"AT",
    "sg:address":"Hauptstr 94",
    "sg:city":"Lannach",
    "sg:orig_category":"Feuerwehren",
    "sg:phone":"+43 3136 82452",
    "sg:postcode":"8502",
    "sg:province":"Steiermark",
    "wof:name":"Freiwillige Feuerwehr Blumegg-Teipl",
    "wof:placetype":"venue"
},
  "geometry": {"coordinates":[15.316570282,46.9398117065],"type":"Point"}
}