{
  "type": "Feature",
  "properties": {
    "iso:country":"AT",
    "sg:address":"Erinnerungsstr 1",
    "sg:city":"Mauthausen",
    "sg:orig_category":"Museen / Ausstellungen",
    "sg:phone":"+43 7238 22690",
    "sg:postcode":"4310",
    "sg:province":"Ober\u00f6sterreich",
    "wof:name":"KZ-Gedenkst\u00e4tte Mauthausen",
    "wof:placetype":"venue"
},
  "geometry": {"coordinates":[14.5004549026,48.2559013367],"type":"Point"}
}