{
  "type": "Feature",
  "properties": {
    "addr:full":"Bundesstr 368 Bad Goisern Ober\u00f6sterreich 4822",
    "addr:housenumber":"368",
    "addr:postcode":"4822",
    "iso:country":"AT",
    "sg:address":"Bundesstr 368",
    "sg:city":"Bad Goisern",
    "sg:orig_category":"Apotheken",
    "sg:phone":"+43 6135 72200",
    "sg:postcode":"4822",
    "sg:province":"Ober\u00f6sterreich",
    "wof:name":"Edelwei\u00df-Apotheke Magpharm Helmut Schreiber",
    "wof:placetype":"venue"
},
  "geometry": {"coordinates":[13.6089878082,47.6587486267],"type":"Point"}
}