{
  "type": "Feature",
  "properties": {
    "addr:full":"Willendorfer Str 150 Willendorf am Steinfelde Nieder\u00f6sterreich 2732",
    "addr:housenumber":"150",
    "addr:postcode":"2732",
    "addr:street":"Niederoesterreich",
    "iso:country":"AT",
    "sg:address":"Willendorfer Str 150",
    "sg:city":"Willendorf am Steinfelde",
    "sg:orig_category":"Gemeinden",
    "sg:phone":"+43 2620 24100",
    "sg:postcode":"2732",
    "sg:province":"Nieder\u00f6sterreich",
    "wof:name":"Gemeinde W\u00fcrflach",
    "wof:placetype":"venue"
},
  "geometry": {"coordinates":[16.0567207336,47.7846221924],"type":"Point"}
}