{
  "type": "Feature",
  "properties": {
    "addr:full":"Wiener Str 6 Hainburg an der Donau Nieder\u00f6sterreich 2410",
    "addr:housenumber":"6",
    "addr:postcode":"2410",
    "iso:country":"AT",
    "sg:address":"Wiener Str 6",
    "sg:city":"Hainburg an der Donau",
    "sg:orig_category":"Damenmoden",
    "sg:phone":"+43 4321 6565223",
    "sg:postcode":"2410",
    "sg:province":"Nieder\u00f6sterreich",
    "wof:name":"BLAUE LAGUNE MODELLE - Exklusive Designer Damenmode - Modedesignerin Alena Svobodova",
    "wof:placetype":"venue"
},
  "geometry": {"coordinates":[16.9403018951,48.1469421387],"type":"Point"}
}