{
  "type": "Feature",
  "properties": {
    "addr:full":"Gr\u00fcnauer Str 8 Hofstetten Nieder\u00f6sterreich 3202",
    "addr:postcode":"3202",
    "addr:street":"Str 8",
    "iso:country":"AT",
    "sg:address":"Gr\u00fcnauer Str 8",
    "sg:city":"Hofstetten",
    "sg:orig_category":"Rettungsdienste",
    "sg:phone":"+43 2723 82440",
    "sg:postcode":"3202",
    "sg:province":"Nieder\u00f6sterreich",
    "wof:name":"Rotes Kreuz \u00f6sterr Ortsstelle Hofstetten-Gr\u00fcnau",
    "wof:placetype":"venue"
},
  "geometry": {"coordinates":[15.4798202515,48.0778617859],"type":"Point"}
}