{
  "type": "Feature",
  "properties": {
    "iso:country":"AT",
    "sg:address":"Leonhardstr 93",
    "sg:city":"Graz",
    "sg:orig_category":"Tabaktrafiken",
    "sg:phone":"+43 316 321472",
    "sg:postcode":"8010",
    "sg:province":"Steiermark",
    "wof:name":"Reischer Edda",
    "wof:placetype":"venue"
},
  "geometry": {"coordinates":[15.4582824707,47.0753517151],"type":"Point"}
}