{
  "type": "Feature",
  "properties": {
    "addr:full":"Nr 1 u 65 Heiligenblut K\u00e4rnten 9844",
    "addr:housenumber":"65",
    "addr:postcode":"9844",
    "addr:street":"Nr;Kaernten",
    "iso:country":"AT",
    "sg:address":"Nr 1 u 65",
    "sg:city":"Heiligenblut",
    "sg:orig_category":"Appartements / Ferienwohnungen",
    "sg:phone":"+43 4348 2427370",
    "sg:postcode":"9844",
    "sg:province":"K\u00e4rnten",
    "wof:name":"Appartement Angerer",
    "wof:placetype":"venue"
},
  "geometry": {"coordinates":[-89.4839172363,38.1467819214],"type":"Point"}
}