{
  "type": "Feature",
  "properties": {
    "addr:full":"Nr 8 St. Martin an der Raab Burgenland 8383",
    "addr:housenumber":"8",
    "addr:postcode":"8383",
    "addr:street":"Nr",
    "iso:country":"AT",
    "sg:address":"Nr 8",
    "sg:city":"St. Martin an der Raab",
    "sg:orig_category":"Stahlbau",
    "sg:phone":"+43 4333 2948922",
    "sg:postcode":"8383",
    "sg:province":"Burgenland",
    "wof:name":"Lang Karl u Sohn",
    "wof:placetype":"venue"
},
  "geometry": {"coordinates":[16.1334457397,46.9210014343],"type":"Point"}
}