{
  "type": "Feature",
  "properties": {
    "addr:full":"Prunnerstr 8 Freistadt Ober\u00f6sterreich 4240",
    "addr:housenumber":"8",
    "addr:postcode":"4240",
    "addr:street":"Prunnerstr",
    "iso:country":"AT",
    "sg:address":"Prunnerstr 8",
    "sg:city":"Freistadt",
    "sg:orig_category":"Handelsagenturen",
    "sg:phone":"+43 7942 72484",
    "sg:postcode":"4240",
    "sg:province":"Ober\u00f6sterreich",
    "wof:name":"Mink de Fritz",
    "wof:placetype":"venue"
},
  "geometry": {"coordinates":[14.5038700104,48.499874115],"type":"Point"}
}