{
  "type": "Feature",
  "properties": {
    "addr:full":"Galinastrasse 29 Frastanz Vorarlberg 6820",
    "addr:housenumber":"29",
    "addr:postcode":"6820",
    "addr:street":"Galinastrasse",
    "iso:country":"AT",
    "sg:address":"Galinastrasse 29",
    "sg:city":"Frastanz",
    "sg:orig_category":"Fork Lift Truck Attachments",
    "sg:phone":"+43 5522 51170",
    "sg:postcode":"6820",
    "sg:province":"Vorarlberg",
    "sg:website":"stapler-mueller.com",
    "wof:name":"M\u00dcLLER - STAPLER GesmbH",
    "wof:placetype":"venue"
},
  "geometry": {"coordinates":[9.6481847763,47.2145118713],"type":"Point"}
}