{
  "type": "Feature",
  "properties": {
    "addr:full":"Eiseng 10 Dornbirn Vorarlberg 6850",
    "addr:housenumber":"10",
    "addr:postcode":"6850",
    "addr:street":"Eiseng",
    "iso:country":"AT",
    "sg:address":"Eiseng 10",
    "sg:city":"Dornbirn",
    "sg:orig_category":"Friseure U Frisiersalons",
    "sg:phone":"+43 4355 7229966",
    "sg:postcode":"6850",
    "sg:province":"Vorarlberg",
    "wof:name":"Haarstudio La Vita",
    "wof:placetype":"venue"
},
  "geometry": {"coordinates":[9.7442932129,47.4154701233],"type":"Point"}
}