{
  "type": "Feature",
  "properties": {
    "addr:full":"Gobelsburger Strasse 23 Langenlois Nieder\u00f6sterreich 3550",
    "addr:housenumber":"23",
    "addr:postcode":"3550",
    "addr:street":"Gobelsburger Strasse",
    "iso:country":"AT",
    "sg:address":"Gobelsburger Strasse 23",
    "sg:city":"Langenlois",
    "sg:classifiers":[
        {
            "category":"Government",
            "subcategory":"Fire Station",
            "type":"Public Place"
        }
    ],
    "sg:phone":"+43 2734 3539",
    "sg:postcode":"3550",
    "sg:province":"Nieder\u00f6sterreich",
    "sg:tags":[
        "alloy",
        "light",
        "aluminium",
        "processing"
    ],
    "sg:website":"spenglerei-wutzl.at",
    "wof:name":"Alfred Wutzl",
    "wof:placetype":"venue"
},
  "geometry": {"coordinates":[15.6879558563,48.4690322876],"type":"Point"}
}