{
  "type": "Feature",
  "properties": {
    "addr:full":"Thorer Str 4 Saalfelden am Steinernen Meer Salzburg 5760",
    "addr:housenumber":"4",
    "addr:postcode":"5760",
    "addr:street":"Str",
    "iso:country":"AT",
    "sg:address":"Thorer Str 4",
    "sg:city":"Saalfelden am Steinernen Meer",
    "sg:classifiers":[
        {
            "category":"Restaurant",
            "type":"Food & Drink"
        }
    ],
    "sg:phone":"+43 6582 74197",
    "sg:postcode":"5760",
    "sg:province":"Salzburg",
    "wof:name":"Hasenauer Peter",
    "wof:placetype":"venue"
},
  "geometry": {"coordinates":[12.8389968872,47.4247322083],"type":"Point"}
}