{
  "type": "Feature",
  "properties": {
    "iso:country":"AT",
    "sg:address":"Oberkrimml 118",
    "sg:city":"Krimml",
    "sg:orig_category":"Pensionen / Privatzimmer",
    "sg:phone":"+43 6564 72950",
    "sg:postcode":"5743",
    "sg:province":"Salzburg",
    "wof:name":"G\u00e4stehaus Waltl",
    "wof:placetype":"venue"
},
  "geometry": {"coordinates":[12.173828125,47.2177658081],"type":"Point"}
}