{
  "type": "Feature",
  "properties": {
    "addr:full":"Halleng. 2b Wiener Neustadt Nieder\u00f6sterreich 2700",
    "addr:housenumber":"2b",
    "addr:postcode":"2700",
    "addr:street":"Halleng.",
    "iso:country":"AT",
    "sg:address":"Halleng. 2b",
    "sg:city":"Wiener Neustadt",
    "sg:classifiers":[
        {
            "category":"Professional",
            "subcategory":"Engineering",
            "type":"Services"
        }
    ],
    "sg:phone":"+43 4326 22232190",
    "sg:postcode":"2700",
    "sg:province":"Nieder\u00f6sterreich",
    "sg:tags":[
        "machine",
        "-",
        "mechanical"
    ],
    "wof:name":"MICAN & STOISSER GMBH",
    "wof:placetype":"venue"
},
  "geometry": {"coordinates":[16.239402771,47.8055496216],"type":"Point"}
}