{
  "type": "Feature",
  "properties": {
    "addr:full":"Parkstr 13 Bad Hofgastein Salzburg 5630",
    "addr:housenumber":"13",
    "addr:postcode":"5630",
    "addr:street":"Parkstr;Salzburg",
    "iso:country":"AT",
    "sg:address":"Parkstr 13",
    "sg:city":"Bad Hofgastein",
    "sg:classifiers":[
        {
            "category":"Travel",
            "subcategory":"Hotels & Motels",
            "type":"Entertainment"
        }
    ],
    "sg:phone":"+43 6432 84750",
    "sg:postcode":"5630",
    "sg:province":"Salzburg",
    "wof:name":"Hotel Alpina",
    "wof:placetype":"venue"
},
  "geometry": {"coordinates":[13.0999393463,47.1725196838],"type":"Point"}
}