{
  "type": "Feature",
  "properties": {
    "addr:full":"Gussstahlwerkstr 23  Judenburg Steiermark 8750",
    "addr:housenumber":"23",
    "addr:postcode":"8750",
    "addr:street":"Gussstahlwerkstr",
    "iso:country":"AT",
    "sg:address":"Gussstahlwerkstr 23 ",
    "sg:city":"Judenburg",
    "sg:classifiers":[
        {
            "category":"Manufacturing",
            "subcategory":"Metals",
            "type":"Manufacturing & Wholesale Goods"
        }
    ],
    "sg:phone":"+43 4335 72859000",
    "sg:postcode":"8750",
    "sg:province":"Steiermark",
    "sg:tags":[
        "processing"
    ],
    "wof:name":"WUPPERMANN AUSTRIA GESMBH",
    "wof:placetype":"venue"
},
  "geometry": {"coordinates":[14.6659517288,47.1744346619],"type":"Point"}
}