{
  "type": "Feature",
  "properties": {
    "iso:country":"AT",
    "sg:address":"Thermenstr 4",
    "sg:city":"Bad Kleinkirchheim",
    "sg:orig_category":"Gesundheitsvorsorge",
    "sg:phone":"+43 4342 407440",
    "sg:postcode":"9546",
    "sg:province":"K\u00e4rnten",
    "wof:name":"Hotel Pulverer Thermenwelt",
    "wof:placetype":"venue"
},
  "geometry": {"coordinates":[13.780005455,46.8140525818],"type":"Point"}
}