{
  "type": "Feature",
  "properties": {
    "addr:full":"Fuxmageng 12 Hall in Tirol Tirol 6060",
    "addr:housenumber":"12",
    "addr:postcode":"6060",
    "addr:street":"Fuxmageng;Tirol",
    "iso:country":"AT",
    "sg:address":"Fuxmageng 12",
    "sg:city":"Hall in Tirol",
    "sg:orig_category":"Werbeagenturen",
    "sg:phone":"+43 5223 425900",
    "sg:postcode":"6060",
    "sg:province":"Tirol",
    "wof:name":"Media IV Kommunikations-GmbH",
    "wof:placetype":"venue"
},
  "geometry": {"coordinates":[11.5041303635,47.2847747803],"type":"Point"}
}