{
  "type": "Feature",
  "properties": {
    "addr:full":"Linzer Str 10 Melk Nieder\u00f6sterreich 3390",
    "addr:housenumber":"10",
    "addr:postcode":"3390",
    "addr:street":"Linzer Str",
    "iso:country":"AT",
    "sg:address":"Linzer Str 10",
    "sg:city":"Melk",
    "sg:orig_category":"Alternativtherapie",
    "sg:phone":"+43 2752 50087",
    "sg:postcode":"3390",
    "sg:province":"Nieder\u00f6sterreich",
    "wof:name":"Limberger Margot",
    "wof:placetype":"venue"
},
  "geometry": {"coordinates":[15.3281440735,48.2267875671],"type":"Point"}
}