{
  "type": "Feature",
  "properties": {
    "iso:country":"AT",
    "sg:city":"Kappl",
    "sg:classifiers":[
        {
            "category":"Restaurant",
            "type":"Food & Drink"
        }
    ],
    "sg:phone":"+43 5445 6617",
    "sg:postcode":"6555",
    "sg:province":"Tirol",
    "wof:name":"Bergrestaurant Neue Dias-Alpe",
    "wof:placetype":"venue"
},
  "geometry": {"coordinates":[10.3749132156,47.0630874634],"type":"Point"}
}