{
  "type": "Feature",
  "properties": {
    "addr:full":"Seitenstetteng 3 Wien Wien 1010",
    "addr:housenumber":"3",
    "addr:postcode":"1010",
    "addr:street":"Seitenstetteng",
    "iso:country":"AT",
    "sg:address":"Seitenstetteng 3",
    "sg:city":"Wien",
    "sg:orig_category":"Bars-Cafes",
    "sg:phone":"+43 1 5353387",
    "sg:postcode":"1010",
    "sg:province":"Wien",
    "wof:name":"Rasputin Bar",
    "wof:placetype":"venue"
},
  "geometry": {"coordinates":[16.3746318817,48.2118339539],"type":"Point"}
}