{
  "type": "Feature",
  "properties": {
    "addr:full":"Rettenbachweg 12 Altenmarkt im Pongau Salzburg 5541",
    "addr:housenumber":"12",
    "addr:postcode":"5541",
    "addr:street":"Rettenbachweg;Salzburg",
    "iso:country":"AT",
    "sg:address":"Rettenbachweg 12",
    "sg:city":"Altenmarkt im Pongau",
    "sg:orig_category":"Pensionen / Privatzimmer",
    "sg:phone":"+43 6452 6578",
    "sg:postcode":"5541",
    "sg:province":"Salzburg",
    "wof:name":"Stranger Markus",
    "wof:placetype":"venue"
},
  "geometry": {"coordinates":[13.4336938858,47.3637466431],"type":"Point"}
}