{
  "type": "Feature",
  "properties": {
    "addr:full":"Winklern 8 Irdning Steiermark 8952",
    "addr:housenumber":"8",
    "addr:postcode":"8952",
    "addr:street":"Winklern",
    "iso:country":"AT",
    "sg:address":"Winklern 8",
    "sg:city":"Irdning",
    "sg:orig_category":"Pensionen / Privatzimmer",
    "sg:phone":"+43 3682 26189",
    "sg:postcode":"8952",
    "sg:province":"Steiermark",
    "wof:name":"Lutzmann Maria und Erwin",
    "wof:placetype":"venue"
},
  "geometry": {"coordinates":[14.1031150818,47.5052604675],"type":"Point"}
}