{
  "type": "Feature",
  "properties": {
    "addr:full":"Hallestr 29 Linz Ober\u00f6sterreich 4030",
    "addr:housenumber":"29",
    "addr:postcode":"4030",
    "addr:street":"Hallestr",
    "iso:country":"AT",
    "sg:address":"Hallestr 29",
    "sg:city":"Linz",
    "sg:orig_category":"Filteranlagen",
    "sg:phone":"+43 732 313813",
    "sg:postcode":"4030",
    "sg:province":"Ober\u00f6sterreich",
    "wof:name":"UAS United Air Specialists",
    "wof:placetype":"venue"
},
  "geometry": {"coordinates":[14.3072395325,48.2471199036],"type":"Point"}
}