{
  "type": "Feature",
  "properties": {
    "addr:full":"Rauhholzstr 8A Hard Vorarlberg 6971",
    "addr:housenumber":"8a",
    "addr:postcode":"6971",
    "addr:street":"Rauhholzstr",
    "iso:country":"AT",
    "sg:address":"Rauhholzstr 8A",
    "sg:city":"Hard",
    "sg:orig_category":"Erdbau",
    "sg:phone":"+43 5574 525177",
    "sg:postcode":"6971",
    "sg:province":"Vorarlberg",
    "wof:name":"greentex-international",
    "wof:placetype":"venue"
},
  "geometry": {"coordinates":[9.6990213394,47.4897918701],"type":"Point"}
}