{
  "type": "Feature",
  "properties": {
    "iso:country":"AT",
    "sg:address":"Nr 3",
    "sg:city":"Soboth",
    "sg:orig_category":"Rettungsdienste",
    "sg:phone":"+43 3460 344",
    "sg:postcode":"8554",
    "sg:province":"Steiermark",
    "wof:name":"\u00f6sterreichische Wasserrettung - Einsatzltg Wolfsberg",
    "wof:placetype":"venue"
},
  "geometry": {"coordinates":[15.0756845474,46.6809768677],"type":"Point"}
}