{
  "type": "Feature",
  "properties": {
    "addr:full":"Marktg 14a Kufstein Tirol 6330",
    "addr:housenumber":"14a",
    "addr:postcode":"6330",
    "addr:street":"Marktg;Tirol",
    "iso:country":"AT",
    "sg:address":"Marktg 14a",
    "sg:city":"Kufstein",
    "sg:classifiers":[
        {
            "category":"Travel",
            "subcategory":"Hotels & Motels",
            "type":"Entertainment"
        }
    ],
    "sg:phone":"+43 5372 62396",
    "sg:postcode":"6330",
    "sg:province":"Tirol",
    "wof:name":"Hotel Zipferkeller",
    "wof:placetype":"venue"
},
  "geometry": {"coordinates":[12.1717987061,47.5847892761],"type":"Point"}
}