{
  "type": "Feature",
  "properties": {
    "iso:country":"AT",
    "sg:address":"Linzer Str 1",
    "sg:city":"Gallspach",
    "sg:classifiers":[
        {
            "category":"Travel",
            "subcategory":"Hotels & Motels",
            "type":"Entertainment"
        }
    ],
    "sg:phone":"+43 7248 62631",
    "sg:postcode":"4713",
    "sg:province":"Ober\u00f6sterreich",
    "wof:name":"Hotel Linzerhof",
    "wof:placetype":"venue"
},
  "geometry": {"coordinates":[13.8142986298,48.2068138123],"type":"Point"}
}