{
  "type": "Feature",
  "properties": {
    "addr:full":"Badner Str 144 Alland Nieder\u00f6sterreich 2534",
    "addr:housenumber":"144;2534",
    "addr:street":"Alland Niederoesterreich",
    "iso:country":"AT",
    "sg:address":"Badner Str 144",
    "sg:city":"Alland",
    "sg:orig_category":"Transportunternehmen",
    "sg:phone":"+43 2258 2208",
    "sg:postcode":"2534",
    "sg:province":"Nieder\u00f6sterreich",
    "wof:name":"Koch Josef",
    "wof:placetype":"venue"
},
  "geometry": {"coordinates":[16.0783996582,48.0584259033],"type":"Point"}
}