{
  "type": "Feature",
  "properties": {
    "addr:full":"Europark Europastr 1 5016",
    "addr:housenumber":"1",
    "addr:postcode":"5016",
    "addr:street":"Europastr",
    "iso:country":"AT",
    "sg:address":"Europark Europastr 1",
    "sg:orig_category":"Freizeit- U Sportbekleidung",
    "sg:phone":"+43 4366 24352840",
    "sg:postcode":"5016",
    "wof:name":"HERVIS Sport- u ModegesmbH",
    "wof:placetype":"venue"
},
  "geometry": {"coordinates":[13.0433702469,47.8006706238],"type":"Point"}
}