{
  "type": "Feature",
  "properties": {
    "iso:country":"AT",
    "sg:address":"Auf der Gugl 3",
    "sg:city":"Linz",
    "sg:orig_category":"Personalbereitstellung",
    "sg:phone":"+43 732 6902557",
    "sg:postcode":"4020",
    "sg:province":"Ober\u00f6sterreich",
    "wof:name":"Maschinenring Personal Leasing regGenmbH",
    "wof:placetype":"venue"
},
  "geometry": {"coordinates":[14.282746315,48.2920875549],"type":"Point"}
}