{
  "type": "Feature",
  "properties": {
    "addr:full":"Angererhofstr 21 Moosburg K\u00e4rnten 9062",
    "addr:housenumber":"21",
    "addr:postcode":"9062",
    "addr:street":"Angererhofstr;Kaernten",
    "iso:country":"AT",
    "sg:address":"Angererhofstr 21",
    "sg:city":"Moosburg",
    "sg:orig_category":"Pensionen / Privatzimmer",
    "sg:phone":"+43 4272 830530",
    "sg:postcode":"9062",
    "sg:province":"K\u00e4rnten",
    "wof:name":"Angererhof Reiterpension GesmbH Nfg OEG",
    "wof:placetype":"venue"
},
  "geometry": {"coordinates":[14.1629152298,46.6526107788],"type":"Point"}
}