{
  "type": "Feature",
  "properties": {
    "iso:country":"AT",
    "sg:address":"Wiener Str 150",
    "sg:city":"Spillern",
    "sg:orig_category":"Steinmetzbetriebe",
    "sg:phone":"+43 2266 81614",
    "sg:postcode":"2104",
    "sg:province":"Nieder\u00f6sterreich",
    "wof:name":"Polgar GesmbH",
    "wof:placetype":"venue"
},
  "geometry": {"coordinates":[16.2721004486,48.3758201599],"type":"Point"}
}