{
  "type": "Feature",
  "properties": {
    "iso:country":"AT",
    "sg:address":"Seestr 24",
    "sg:city":"Mitterbach am Erlaufsee",
    "sg:orig_category":"Bergbahnen",
    "sg:phone":"+43 4338 8241720",
    "sg:postcode":"3224",
    "sg:province":"Nieder\u00f6sterreich",
    "wof:name":"Bergbahnen Mitterbach GmbH",
    "wof:placetype":"venue"
},
  "geometry": {"coordinates":[15.28956604,47.8109512329],"type":"Point"}
}