{
  "type": "Feature",
  "properties": {
    "addr:full":"Audorf 17 Pichl Steiermark 8973",
    "addr:housenumber":"17",
    "addr:postcode":"8973",
    "addr:street":"Audorf",
    "iso:country":"AT",
    "sg:address":"Audorf 17",
    "sg:city":"Pichl",
    "sg:orig_category":"Pensionen / Privatzimmer",
    "sg:phone":"+43 4364 547435",
    "sg:postcode":"8973",
    "sg:province":"Steiermark",
    "wof:name":"Pension Kristall",
    "wof:placetype":"venue"
},
  "geometry": {"coordinates":[13.5935468674,47.3928794861],"type":"Point"}
}