{
  "type": "Feature",
  "properties": {
    "addr:full":"Langg 24 Imst Tirol 6460",
    "addr:housenumber":"24",
    "addr:postcode":"6460",
    "addr:street":"Langg;Tirol",
    "iso:country":"AT",
    "sg:address":"Langg 24",
    "sg:city":"Imst",
    "sg:orig_category":"Technische Gase",
    "sg:phone":"+43 5412 68713",
    "sg:postcode":"6460",
    "sg:province":"Tirol",
    "wof:name":"Linde Gas GmbH - Auslieferungslager",
    "wof:placetype":"venue"
},
  "geometry": {"coordinates":[10.737487793,47.2392234802],"type":"Point"}
}