{
  "type": "Feature",
  "properties": {
    "iso:country":"AT",
    "sg:address":"Bergmannpl 3",
    "sg:city":"Petzenkirchen",
    "sg:orig_category":"Tabaktrafiken",
    "sg:phone":"+43 7416 52574",
    "sg:postcode":"3252",
    "sg:province":"Nieder\u00f6sterreich",
    "wof:name":"Eder Franz",
    "wof:placetype":"venue"
},
  "geometry": {"coordinates":[15.1534757614,48.1436576843],"type":"Point"}
}