{
  "type": "Feature",
  "properties": {
    "addr:full":"Leobersdorfer Str 119 Berndorf Nieder\u00f6sterreich 2560",
    "addr:housenumber":"119",
    "addr:postcode":"2560",
    "addr:street":"Berndorf Niederoesterreich",
    "iso:country":"AT",
    "sg:address":"Leobersdorfer Str 119",
    "sg:city":"Berndorf",
    "sg:orig_category":"Restaurants: Chinesisch",
    "sg:phone":"+43 2672 84801",
    "sg:postcode":"2560",
    "sg:province":"Nieder\u00f6sterreich",
    "wof:name":"China-Restaurant Ciao",
    "wof:placetype":"venue"
},
  "geometry": {"coordinates":[16.1051998138,47.8947486877],"type":"Point"}
}