{
  "type": "Feature",
  "properties": {
    "addr:full":"Werderg 40 Neunkirchen Nieder\u00f6sterreich 2620",
    "addr:housenumber":"40",
    "addr:postcode":"2620",
    "addr:street":"Werderg",
    "iso:country":"AT",
    "sg:address":"Werderg 40",
    "sg:city":"Neunkirchen",
    "sg:orig_category":"Astrologie",
    "sg:phone":"+43 4326 3567656",
    "sg:postcode":"2620",
    "sg:province":"Nieder\u00f6sterreich",
    "wof:name":"Astro-Service",
    "wof:placetype":"venue"
},
  "geometry": {"coordinates":[16.1022720337,47.7216911316],"type":"Point"}
}