{
  "type": "Feature",
  "properties": {
    "addr:full":"Alma-Rose-G 2 Wien Wien 1100",
    "addr:housenumber":"2",
    "addr:postcode":"1100",
    "addr:street":"Alma-Rose-G",
    "iso:country":"AT",
    "sg:address":"Alma-Rose-G 2",
    "sg:city":"Wien",
    "sg:orig_category":"Damenmoden",
    "sg:phone":"+43 4316 893515",
    "sg:postcode":"1100",
    "sg:province":"Wien",
    "wof:name":"KiK Textilien u Non-Food GesmbH",
    "wof:placetype":"venue"
},
  "geometry": {"coordinates":[16.3922996521,48.145942688],"type":"Point"}
}