{
  "type": "Feature",
  "properties": {
    "addr:full":"Braunauer Str 7 Altheim Ober\u00f6sterreich 4950",
    "addr:housenumber":"7",
    "addr:postcode":"4950",
    "addr:street":"Str",
    "iso:country":"AT",
    "sg:address":"Braunauer Str 7",
    "sg:city":"Altheim",
    "sg:orig_category":"Gemeinden",
    "sg:phone":"+43 7723 422550",
    "sg:postcode":"4950",
    "sg:province":"Ober\u00f6sterreich",
    "wof:name":"Stadtamt Altheim",
    "wof:placetype":"venue"
},
  "geometry": {"coordinates":[13.2292366028,48.2488212585],"type":"Point"}
}