{
  "type": "Feature",
  "properties": {
    "addr:full":"Ignaz-Mayer-Strasse 13 Linz Ober\u00f6sterreich 4020",
    "addr:housenumber":"13",
    "addr:postcode":"4020",
    "addr:street":"Ignaz-Mayer-Strasse",
    "iso:country":"AT",
    "sg:address":"Ignaz-Mayer-Strasse 13",
    "sg:city":"Linz",
    "sg:classifiers":[
        {
            "category":"Banks & Credit Unions",
            "subcategory":"Investment Brokerage",
            "type":"Services"
        }
    ],
    "sg:phone":"+43 732 772326",
    "sg:postcode":"4020",
    "sg:province":"Ober\u00f6sterreich",
    "sg:tags":[
        "ball",
        "valve"
    ],
    "wof:name":"atec Armaturen Ges.m.b.H.",
    "wof:placetype":"venue"
},
  "geometry": {"coordinates":[14.3211040497,48.308719635],"type":"Point"}
}