{
  "type": "Feature",
  "properties": {
    "addr:full":"Van-Swieten-G 6 Wien Wien 1090",
    "addr:housenumber":"6",
    "addr:postcode":"1090",
    "addr:street":"Van-Swieten-G",
    "iso:country":"AT",
    "sg:address":"Van-Swieten-G 6",
    "sg:city":"Wien",
    "sg:classifiers":[
        {
            "category":"Restaurant",
            "type":"Food & Drink"
        }
    ],
    "sg:phone":"+43 1 4069063",
    "sg:postcode":"1090",
    "sg:province":"Wien",
    "wof:name":"Proll Brigitte",
    "wof:placetype":"venue"
},
  "geometry": {"coordinates":[16.3561840057,48.218547821],"type":"Point"}
}