{
  "type": "Feature",
  "properties": {
    "addr:full":"Werndlstr 19 Gallspach Ober\u00f6sterreich 4713",
    "addr:housenumber":"19",
    "addr:postcode":"4713",
    "addr:street":"Werndlstr",
    "iso:country":"AT",
    "sg:address":"Werndlstr 19",
    "sg:city":"Gallspach",
    "sg:orig_category":"Adressen- U Telefonbuchverlage",
    "sg:phone":"+43 7248 635000",
    "sg:postcode":"4713",
    "sg:province":"Ober\u00f6sterreich",
    "wof:name":"Bauadressen Neuhofer Heinz",
    "wof:placetype":"venue"
},
  "geometry": {"coordinates":[13.8193941116,48.2038192749],"type":"Point"}
}