{
  "type": "Feature",
  "properties": {
    "addr:full":"Nr 5 Klaffer am Hochficht Ober\u00f6sterreich 4163",
    "addr:postcode":"4163",
    "addr:street":"Nr",
    "iso:country":"AT",
    "sg:address":"Nr 5",
    "sg:city":"Klaffer am Hochficht",
    "sg:orig_category":"\u00c3\u201erzte / F Allgemeinmedizin",
    "sg:phone":"+43 7288 6504",
    "sg:postcode":"4163",
    "sg:province":"Ober\u00f6sterreich",
    "wof:name":"Hietler Rudolf Dr",
    "wof:placetype":"venue"
},
  "geometry": {"coordinates":[13.8818359375,48.6953315735],"type":"Point"}
}