{
  "type": "Feature",
  "properties": {
    "addr:full":"Fadingerpl 6 Linz Ober\u00f6sterreich 4030",
    "addr:housenumber":"6",
    "addr:postcode":"4030",
    "addr:street":"Fadingerpl",
    "iso:country":"AT",
    "sg:address":"Fadingerpl 6",
    "sg:city":"Linz",
    "sg:orig_category":"Tabaktrafiken",
    "sg:phone":"+43 732 309374",
    "sg:postcode":"4030",
    "sg:province":"Ober\u00f6sterreich",
    "wof:name":"Kraft Ingrid",
    "wof:placetype":"venue"
},
  "geometry": {"coordinates":[14.2933139801,48.3037872314],"type":"Point"}
}