{
  "type": "Feature",
  "properties": {
    "addr:full":"Nr 20 Fresach K\u00e4rnten 9712",
    "addr:postcode":"9712",
    "addr:street":"Nr 20;Kaernten",
    "iso:country":"AT",
    "sg:address":"Nr 20",
    "sg:city":"Fresach",
    "sg:orig_category":"Pensionen / Privatzimmer",
    "sg:phone":"+43 4342 454713",
    "sg:postcode":"9712",
    "sg:province":"K\u00e4rnten",
    "wof:name":"Stanahof - Karin Baumgartner",
    "wof:placetype":"venue"
},
  "geometry": {"coordinates":[13.6881408691,46.7136497498],"type":"Point"}
}