{
  "type": "Feature",
  "properties": {
    "addr:full":"Libellenweg 5 Wolfsberg K\u00e4rnten 9400",
    "addr:housenumber":"5;kaernten",
    "addr:postcode":"9400",
    "addr:street":"Libellenweg",
    "iso:country":"AT",
    "sg:address":"Libellenweg 5",
    "sg:city":"Wolfsberg",
    "sg:orig_category":"Zahntechnische Laboratorien",
    "sg:phone":"+43 4343 524166",
    "sg:postcode":"9400",
    "sg:province":"K\u00e4rnten",
    "wof:name":"Rothleitner Hans",
    "wof:placetype":"venue"
},
  "geometry": {"coordinates":[14.8327255249,46.8399734497],"type":"Point"}
}