{
  "type": "Feature",
  "properties": {
    "addr:full":"Technologiepark 17 Perg Ober\u00f6sterreich 4320",
    "addr:housenumber":"17",
    "addr:postcode":"4320",
    "addr:street":"Technologiepark",
    "iso:country":"AT",
    "sg:address":"Technologiepark 17",
    "sg:city":"Perg",
    "sg:classifiers":[
        {
            "category":"Professional",
            "subcategory":"Computer Services",
            "type":"Services"
        }
    ],
    "sg:phone":"+43 7262 93963230",
    "sg:postcode":"4320",
    "sg:province":"Ober\u00f6sterreich",
    "sg:tags":[
        "software"
    ],
    "wof:name":"Oppix Engineering / DI FH Johannes Oppitz",
    "wof:placetype":"venue"
},
  "geometry": {"coordinates":[14.6340551376,48.2500610352],"type":"Point"}
}