{
  "type": "Feature",
  "properties": {
    "addr:full":"Fasang 46 Wien Wien 1030",
    "addr:housenumber":"46",
    "addr:postcode":"1030",
    "addr:street":"Fasang",
    "iso:country":"AT",
    "sg:address":"Fasang 46",
    "sg:city":"Wien",
    "sg:orig_category":"Studentenheime",
    "sg:phone":"+43 1 79835080",
    "sg:postcode":"1030",
    "sg:province":"Wien",
    "wof:name":"Studentinnenheim Marienanstalt",
    "wof:placetype":"venue"
},
  "geometry": {"coordinates":[16.3851108551,48.1893043518],"type":"Point"}
}