{
  "type": "Feature",
  "properties": {
    "iso:country":"AT",
    "sg:address":"Bahnhofstr 12",
    "sg:city":"M\u00fcrzhofen",
    "sg:orig_category":"Erdarbeiten",
    "sg:phone":"+43 4338 642430",
    "sg:postcode":"8644",
    "sg:province":"Steiermark",
    "wof:name":"Ratajc Alois",
    "wof:placetype":"venue"
},
  "geometry": {"coordinates":[15.3976221085,47.4822311401],"type":"Point"}
}