{
  "type": "Feature",
  "properties": {
    "addr:full":"Schwenkgasse 31 Wien Wien 1120",
    "addr:housenumber":"31",
    "addr:postcode":"1120",
    "addr:street":"Schwenkgasse",
    "iso:country":"AT",
    "sg:address":"Schwenkgasse 31",
    "sg:city":"Wien",
    "sg:classifiers":[
        {
            "category":"Shopping",
            "subcategory":"Stationery & Office Supplies",
            "type":"Retail Goods"
        }
    ],
    "sg:phone":"+43 664 2244756",
    "sg:postcode":"1120",
    "sg:province":"Wien",
    "sg:tags":[
        "copier",
        "photocopiers"
    ],
    "sg:website":"kopiergeraete-nueber.at",
    "wof:name":"KOPIERGER\u00c4TE - Wilhelm Nueber",
    "wof:placetype":"venue"
},
  "geometry": {"coordinates":[16.3206577301,48.1766052246],"type":"Point"}
}