{
  "type": "Feature",
  "properties": {
    "addr:full":"Liebenauer Hauptstr 2-6 Liebenau Steiermark 8041",
    "addr:housenumber":"2-6",
    "addr:postcode":"8041",
    "addr:street":"Hauptstr",
    "iso:country":"AT",
    "sg:address":"Liebenauer Hauptstr 2-6",
    "sg:city":"Liebenau",
    "sg:orig_category":"Logistik",
    "sg:phone":"+43 316 428798",
    "sg:postcode":"8041",
    "sg:province":"Steiermark",
    "wof:name":"Top Mehrwert Logistik GMBH & Co KG",
    "wof:placetype":"venue"
},
  "geometry": {"coordinates":[15.4557781219,47.0470581055],"type":"Point"}
}