{
  "type": "Feature",
  "properties": {
    "iso:country":"AT",
    "sg:address":"Landstr 10",
    "sg:city":"Linz",
    "sg:orig_category":"Optiker",
    "sg:phone":"+43 732 772400",
    "sg:postcode":"4020",
    "sg:province":"Ober\u00f6sterreich",
    "sg:website":"www.geier-optik.at",
    "wof:name":"Geier-Optik GesmbH & Co KG",
    "wof:placetype":"venue"
},
  "geometry": {"coordinates":[14.2886323929,48.3032455444],"type":"Point"}
}