{
  "type": "Feature",
  "properties": {
    "iso:country":"AT",
    "sg:address":"Bahnstr 65",
    "sg:city":"Katzelsdorf",
    "sg:orig_category":"Schlossereien",
    "sg:phone":"+43 2622 4416316",
    "sg:postcode":"2801",
    "sg:province":"Nieder\u00f6sterreich",
    "wof:name":"Metall-Tec",
    "wof:placetype":"venue"
},
  "geometry": {"coordinates":[16.2657413483,47.7912826538],"type":"Point"}
}