{
  "type": "Feature",
  "properties": {
    "addr:full":"Kreuzstr 8 Sulz-R\u00f6this Vorarlberg 6832",
    "addr:housenumber":"8",
    "addr:postcode":"6832",
    "addr:street":"Kreuzstr",
    "iso:country":"AT",
    "sg:address":"Kreuzstr 8",
    "sg:city":"Sulz-R\u00f6this",
    "sg:orig_category":"Altbausanierungen",
    "sg:phone":"+43 4355 2244632",
    "sg:postcode":"6832",
    "sg:province":"Vorarlberg",
    "wof:name":"Kn\u00fcnz Georg u Angelika",
    "wof:placetype":"venue"
},
  "geometry": {"coordinates":[9.6576385498,47.2838249207],"type":"Point"}
}