{
  "type": "Feature",
  "properties": {
    "addr:full":"Austr 16 Lauterach Vorarlberg 6923",
    "addr:housenumber":"16",
    "addr:postcode":"6923",
    "addr:street":"Austr",
    "iso:country":"AT",
    "sg:address":"Austr 16",
    "sg:city":"Lauterach",
    "sg:orig_category":"Immobilienmakler",
    "sg:phone":"+43 5574 63152",
    "sg:postcode":"6923",
    "sg:province":"Vorarlberg",
    "wof:name":"D\u00f6rler Immobilien OEG",
    "wof:placetype":"venue"
},
  "geometry": {"coordinates":[9.7217922211,47.471862793],"type":"Point"}
}