{
  "type": "Feature",
  "properties": {
    "addr:full":"Grazer Vorstadt 82 Voitsberg Steiermark 8570",
    "addr:housenumber":"82",
    "addr:postcode":"8570",
    "addr:street":"Grazer Vorstadt",
    "iso:country":"AT",
    "sg:address":"Grazer Vorstadt 82",
    "sg:city":"Voitsberg",
    "sg:orig_category":"Fleischhauereien",
    "sg:phone":"+43 3142 28170",
    "sg:postcode":"8570",
    "sg:province":"Steiermark",
    "wof:name":"Schirnhofer-Breisler GesmbH - Shop in Shop",
    "wof:placetype":"venue"
},
  "geometry": {"coordinates":[15.1605911255,47.043674469],"type":"Point"}
}