{
  "type": "Feature",
  "properties": {
    "addr:full":"Medrazer Str 11 Fulpmes Tirol 6166",
    "addr:postcode":"6166",
    "addr:street":"Str 11;Tirol",
    "iso:country":"AT",
    "sg:address":"Medrazer Str 11",
    "sg:city":"Fulpmes",
    "sg:classifiers":[
        {
            "category":"Restaurant",
            "type":"Food & Drink"
        }
    ],
    "sg:phone":"+43 5225 63140",
    "sg:postcode":"6166",
    "sg:province":"Tirol",
    "wof:name":"Cafe-Restaurant Pavillion",
    "wof:placetype":"venue"
},
  "geometry": {"coordinates":[11.348482132,47.1508712769],"type":"Point"}
}