{
  "type": "Feature",
  "properties": {
    "iso:country":"AT",
    "sg:city":"Greifenburg",
    "sg:orig_category":"Hauskrankenpflege / Heimhilfe",
    "sg:phone":"+43 676 876518133",
    "sg:postcode":"9761",
    "sg:province":"K\u00e4rnten",
    "wof:name":"Mobile Pflegedienste/ Hauskrankenpflege",
    "wof:placetype":"venue"
},
  "geometry": {"coordinates":[13.1805706024,46.7507743835],"type":"Point"}
}