{
  "type": "Feature",
  "properties": {
    "iso:country":"AT",
    "sg:address":"Bahnstr. 34",
    "sg:city":"Gattendorf",
    "sg:classifiers":[
        {
            "category":"Professional",
            "subcategory":"Engineering",
            "type":"Services"
        }
    ],
    "sg:phone":"+43 4321 426925",
    "sg:postcode":"2474",
    "sg:province":"Burgenland",
    "sg:tags":[
        "machine",
        "-",
        "mechanical"
    ],
    "wof:name":"ALU HEBETECHNIK GMBH",
    "wof:placetype":"venue"
},
  "geometry": {"coordinates":[16.9796504974,48.0122566223],"type":"Point"}
}