{
  "type": "Feature",
  "properties": {
    "iso:country":"AT",
    "sg:address":"Nr 231",
    "sg:city":"Pruggern",
    "sg:classifiers":[
        {
            "category":"Taxi",
            "type":"Transportation"
        }
    ],
    "sg:phone":"+43 4336 8523985",
    "sg:postcode":"8965",
    "sg:province":"Steiermark",
    "sg:tags":[
        "personentransporte",
        "u"
    ],
    "wof:name":"Stocker Herbert - Taxi",
    "wof:placetype":"venue"
},
  "geometry": {"coordinates":[13.8756341934,47.4231910706],"type":"Point"}
}