{
  "type": "Feature",
  "properties": {
    "addr:full":"Zollerg 6 Wien Wien 1070",
    "addr:housenumber":"6",
    "addr:postcode":"1070",
    "addr:street":"Zollerg",
    "iso:country":"AT",
    "sg:address":"Zollerg 6",
    "sg:city":"Wien",
    "sg:classifiers":[
        {
            "category":"Restaurant",
            "type":"Food & Drink"
        }
    ],
    "sg:phone":"+43 1 5225940",
    "sg:postcode":"1070",
    "sg:province":"Wien",
    "sg:tags":[
        "pizzeria"
    ],
    "wof:name":"Dal Capitano",
    "wof:placetype":"venue"
},
  "geometry": {"coordinates":[16.3511581421,48.1995201111],"type":"Point"}
}