{
  "type": "Feature",
  "properties": {
    "addr:full":"Stuwerstr 27b Wien Wien 1020",
    "addr:housenumber":"27b",
    "addr:postcode":"1020",
    "addr:street":"Stuwerstr",
    "iso:country":"AT",
    "sg:address":"Stuwerstr 27b",
    "sg:city":"Wien",
    "sg:orig_category":"Damenmoden",
    "sg:phone":"+43 4317 280444",
    "sg:postcode":"1020",
    "sg:province":"Wien",
    "wof:name":"Gaitzenauer Walter",
    "wof:placetype":"venue"
},
  "geometry": {"coordinates":[16.4028606415,48.2189331055],"type":"Point"}
}