{
  "type": "Feature",
  "properties": {
    "addr:full":"Leonfeldner Str 279 Linz Ober\u00f6sterreich 4040",
    "addr:housenumber":"279",
    "addr:postcode":"4040",
    "iso:country":"AT",
    "sg:address":"Leonfeldner Str 279",
    "sg:city":"Linz",
    "sg:orig_category":"Textilreinigung",
    "sg:phone":"+43 732 25014432",
    "sg:postcode":"4040",
    "sg:province":"Ober\u00f6sterreich",
    "wof:name":"EDER Textilreinigung GesmbH & Co KG",
    "wof:placetype":"venue"
},
  "geometry": {"coordinates":[14.2924938202,48.3478126526],"type":"Point"}
}