{
  "type": "Feature",
  "properties": {
    "iso:country":"AT",
    "sg:address":"Schloeglgasse, 10 - ",
    "sg:city":"Wien",
    "sg:classifiers":[
        {
            "category":"Professional",
            "subcategory":"Art Services",
            "type":"Services"
        }
    ],
    "sg:phone":"+43 4318 040537",
    "sg:postcode":"1120",
    "sg:province":"Wien",
    "sg:tags":[
        "export-import"
    ],
    "wof:name":"Costa Rica General Consulate",
    "wof:placetype":"venue"
},
  "geometry": {"coordinates":[16.3147697449,48.1677742004],"type":"Point"}
}