{
  "type": "Feature",
  "properties": {
    "addr:full":"Nr 182 Unterrohr Steiermark 8294",
    "addr:postcode":"8294",
    "addr:street":"Nr 182",
    "iso:country":"AT",
    "sg:address":"Nr 182",
    "sg:city":"Unterrohr",
    "sg:orig_category":"\u00c3\u201erzte / F Allgemeinmedizin",
    "sg:phone":"+43 4333 3281110",
    "sg:postcode":"8294",
    "sg:province":"Steiermark",
    "wof:name":"Handler Karin Dr",
    "wof:placetype":"venue"
},
  "geometry": {"coordinates":[16.051525116,47.2475013733],"type":"Point"}
}