{
  "type": "Feature",
  "properties": {
    "addr:full":"Landsgraben 3 Ebensee Ober\u00f6sterreich 4802",
    "addr:housenumber":"3",
    "addr:postcode":"4802",
    "addr:street":"Landsgraben",
    "iso:country":"AT",
    "sg:address":"Landsgraben 3",
    "sg:city":"Ebensee",
    "sg:orig_category":"Pensionen / Privatzimmer",
    "sg:phone":"+43 6133 5389",
    "sg:postcode":"4802",
    "sg:province":"Ober\u00f6sterreich",
    "sg:website":"traunsee.at/pension-sybille",
    "wof:name":"Pension Sybille Sabine Bachler",
    "wof:placetype":"venue"
},
  "geometry": {"coordinates":[13.7663259506,47.7916107178],"type":"Point"}
}