{
  "type": "Feature",
  "properties": {
    "addr:full":"Hauptpl 31 Feldbach Steiermark 8330",
    "addr:housenumber":"31",
    "addr:postcode":"8330",
    "addr:street":"Hauptpl",
    "iso:country":"AT",
    "sg:address":"Hauptpl 31",
    "sg:city":"Feldbach",
    "sg:orig_category":"Banken U Sparkassen",
    "sg:phone":"+43 3152 30030",
    "sg:postcode":"8330",
    "sg:province":"Steiermark",
    "wof:name":"S\u00fcdoststeirische Sparkasse AG",
    "wof:placetype":"venue"
},
  "geometry": {"coordinates":[15.888876915,46.9544906616],"type":"Point"}
}