{
  "type": "Feature",
  "properties": {
    "addr:full":"Hauzendorf 22 Greifenburg K\u00e4rnten 9761",
    "addr:housenumber":"22",
    "addr:postcode":"9761",
    "addr:street":"Hauzendorf;Kaernten",
    "iso:country":"AT",
    "sg:address":"Hauzendorf 22",
    "sg:city":"Greifenburg",
    "sg:orig_category":"Non-Classified Establishments",
    "sg:phone":"+43 4712 2590",
    "sg:postcode":"9761",
    "sg:province":"K\u00e4rnten",
    "wof:name":"Stra\u00dfenmeisterei Greifenburg",
    "wof:placetype":"venue"
},
  "geometry": {"coordinates":[13.1637048721,46.7486495972],"type":"Point"}
}