{
  "type": "Feature",
  "properties": {
    "addr:full":"Ketzerg 324 Wien Wien 1230",
    "addr:housenumber":"324",
    "addr:postcode":"1230",
    "iso:country":"AT",
    "sg:address":"Ketzerg 324",
    "sg:city":"Wien",
    "sg:orig_category":"Maler, Anstreicher U Lackierer",
    "sg:phone":"+43 1 8651671",
    "sg:postcode":"1230",
    "sg:province":"Wien",
    "wof:name":"Malermeisterbetrieb Sch\u00f6ngrundner Hermann",
    "wof:placetype":"venue"
},
  "geometry": {"coordinates":[16.2716827393,48.1339302063],"type":"Point"}
}