{
  "type": "Feature",
  "properties": {
    "addr:full":"Ludwig-Boltzmann-Str 2 Neusiedl am See Burgenland 7100",
    "addr:housenumber":"2",
    "addr:postcode":"7100",
    "addr:street":"Ludwig-Boltzmann-Str",
    "iso:country":"AT",
    "sg:address":"Ludwig-Boltzmann-Str 2",
    "sg:city":"Neusiedl am See",
    "sg:orig_category":"Ingenieurkonsulenten / Zivilingenieure",
    "sg:phone":"+43 2167 90103660",
    "sg:postcode":"7100",
    "sg:province":"Burgenland",
    "wof:name":"Bichler & Kolbe ZT-GmbH",
    "wof:placetype":"venue"
},
  "geometry": {"coordinates":[16.841583252,47.9705352783],"type":"Point"}
}