{
  "type": "Feature",
  "properties": {
    "iso:country":"AT",
    "sg:address":"Marktpl 22",
    "sg:city":"Frankenburg am Hausruck",
    "sg:orig_category":"Banken U Sparkassen",
    "sg:phone":"+43 4350 10049001",
    "sg:postcode":"4873",
    "sg:province":"Ober\u00f6sterreich",
    "wof:name":"Sparkasse Frankenmarkt AG",
    "wof:placetype":"venue"
},
  "geometry": {"coordinates":[13.4919214249,48.0678405762],"type":"Point"}
}