{
  "type": "Feature",
  "properties": {
    "addr:full":"Richard Wagner-Pl 17 Wien Wien 1160",
    "addr:housenumber":"17",
    "addr:postcode":"1160",
    "iso:country":"AT",
    "sg:address":"Richard Wagner-Pl 17",
    "sg:city":"Wien",
    "sg:orig_category":"Autoersatzteile",
    "sg:phone":"+43 1 4801071",
    "sg:postcode":"1160",
    "sg:province":"Wien",
    "wof:name":"Top Autoteile HandelsgesmbH",
    "wof:placetype":"venue"
},
  "geometry": {"coordinates":[16.3276481628,48.2104110718],"type":"Point"}
}