{
  "type": "Feature",
  "properties": {
    "iso:country":"AT",
    "sg:address":"Eisenfeldstr 2a",
    "sg:city":"Wels",
    "sg:orig_category":"Restaurants: Amerikanisch",
    "sg:phone":"+43 7242 206999",
    "sg:postcode":"4600",
    "sg:province":"Ober\u00f6sterreich",
    "wof:name":"McDonald's Restaurant - McDrive",
    "wof:placetype":"venue"
},
  "geometry": {"coordinates":[14.0389261246,48.1654472351],"type":"Point"}
}