{
  "type": "Feature",
  "properties": {
    "addr:full":"Karmeliterpl 3 Graz Steiermark 8010",
    "addr:housenumber":"3",
    "addr:postcode":"8010",
    "addr:street":"Karmeliterpl",
    "iso:country":"AT",
    "sg:address":"Karmeliterpl 3",
    "sg:city":"Graz",
    "sg:classifiers":[
        {
            "category":"Retail",
            "subcategory":"Storage",
            "type":"Services"
        }
    ],
    "sg:phone":"+43 4331 68774028",
    "sg:postcode":"8010",
    "sg:province":"Steiermark",
    "sg:tags":[
        "archive"
    ],
    "wof:name":"Landesarchiv Steiermark",
    "wof:placetype":"venue"
},
  "geometry": {"coordinates":[15.4410161972,47.074005127],"type":"Point"}
}