{
  "type": "Feature",
  "properties": {
    "iso:country":"AT",
    "sg:address":"Liechtensteinstr 7",
    "sg:city":"Mistelbach",
    "sg:orig_category":"Werbeagenturen",
    "sg:phone":"+43 2572 20834",
    "sg:postcode":"2130",
    "sg:province":"Nieder\u00f6sterreich",
    "wof:name":"Pixel dreams new media design",
    "wof:placetype":"venue"
},
  "geometry": {"coordinates":[16.5768508911,48.5677185059],"type":"Point"}
}