{
  "type": "Feature",
  "properties": {
    "iso:country":"AT",
    "sg:address":"Kirschentalg 10a",
    "sg:city":"Innsbruck",
    "sg:orig_category":"Psychotherapie",
    "sg:phone":"+43 512 272607",
    "sg:postcode":"6020",
    "sg:province":"Tirol",
    "wof:name":"Gressenberger Walter Dr",
    "wof:placetype":"venue"
},
  "geometry": {"coordinates":[11.3874559402,47.2687034607],"type":"Point"}
}