{
  "type": "Feature",
  "properties": {
    "iso:country":"AT",
    "sg:address":"Hornweg 15",
    "sg:city":"St. Johann in Tirol",
    "sg:orig_category":"Pensionen / Privatzimmer",
    "sg:phone":"+43 4353 5262515",
    "sg:postcode":"6380",
    "sg:province":"Tirol",
    "wof:name":"Mimm G\u00fcnther",
    "wof:placetype":"venue"
},
  "geometry": {"coordinates":[12.4262933731,47.5172309875],"type":"Point"}
}