{
  "type": "Feature",
  "properties": {
    "iso:country":"AT",
    "sg:address":"Europastr 5",
    "sg:city":"Vitis",
    "sg:orig_category":"Fleischhauereien",
    "sg:phone":"+43 4328 4180500",
    "sg:postcode":"3902",
    "sg:province":"Nieder\u00f6sterreich",
    "wof:name":"Fleischveredelungszentrum Waldviertel GmbH",
    "wof:placetype":"venue"
},
  "geometry": {"coordinates":[15.1952314377,48.7574195862],"type":"Point"}
}