{
  "type": "Feature",
  "properties": {
    "addr:full":"Leitenberger Str 8 Bad Ischl Ober\u00f6sterreich 4820",
    "addr:housenumber":"8",
    "addr:postcode":"4820",
    "addr:street":"Str;Oberoesterreich",
    "iso:country":"AT",
    "sg:address":"Leitenberger Str 8",
    "sg:city":"Bad Ischl",
    "sg:orig_category":"Handelsagenturen",
    "sg:phone":"+43 6132 27531",
    "sg:postcode":"4820",
    "sg:province":"Ober\u00f6sterreich",
    "wof:name":"Textilagentur Kreinecker",
    "wof:placetype":"venue"
},
  "geometry": {"coordinates":[13.6181192398,47.7136764526],"type":"Point"}
}