{
  "type": "Feature",
  "properties": {
    "addr:full":"Nr 55 Ottnang am Hausruck Ober\u00f6sterreich 4901",
    "addr:postcode":"4901",
    "addr:street":"Nr",
    "iso:country":"AT",
    "sg:address":"Nr 55",
    "sg:city":"Ottnang am Hausruck",
    "sg:orig_category":"Innenausbau",
    "sg:phone":"+43 767675080",
    "sg:postcode":"4901",
    "sg:province":"Ober\u00f6sterreich",
    "wof:name":"Lederhilger R GmbH",
    "wof:placetype":"venue"
},
  "geometry": {"coordinates":[13.6660804749,48.0968818665],"type":"Point"}
}