{
  "type": "Feature",
  "properties": {
    "addr:full":"Wasendorfer Weg 9a Judenburg Steiermark 8750",
    "addr:housenumber":"9a",
    "addr:postcode":"8750",
    "addr:street":"Wasendorfer Weg",
    "iso:country":"AT",
    "sg:address":"Wasendorfer Weg 9a",
    "sg:city":"Judenburg",
    "sg:orig_category":"Brennstoffe",
    "sg:phone":"+43 3572 843380",
    "sg:postcode":"8750",
    "sg:province":"Steiermark",
    "wof:name":"Rumpold Energie & Brennstoffhandels GmbH",
    "wof:placetype":"venue"
},
  "geometry": {"coordinates":[14.6664619446,47.1778411865],"type":"Point"}
}