{
  "type": "Feature",
  "properties": {
    "addr:full":"Otto-Gl\u00f6ckel-Str 10 Gr\u00f6dig Salzburg 5082",
    "addr:housenumber":"10",
    "addr:postcode":"5082",
    "addr:street":"Otto-Gloeckel-Str",
    "iso:country":"AT",
    "sg:address":"Otto-Gl\u00f6ckel-Str 10",
    "sg:city":"Gr\u00f6dig",
    "sg:orig_category":"Hauptschulen",
    "sg:phone":"+43 4362 46721050",
    "sg:postcode":"5082",
    "sg:province":"Salzburg",
    "wof:name":"Hauptschule",
    "wof:placetype":"venue"
},
  "geometry": {"coordinates":[-76.2684555054,37.4373283386],"type":"Point"}
}