{
  "type": "Feature",
  "properties": {
    "iso:country":"AT",
    "sg:address":"Brauhausstr 47",
    "sg:city":"Schwechat",
    "sg:orig_category":"Fleischhauereien",
    "sg:phone":"+43 1 7077363",
    "sg:postcode":"2320",
    "sg:province":"Nieder\u00f6sterreich",
    "wof:name":"Bomer Alfred",
    "wof:placetype":"venue"
},
  "geometry": {"coordinates":[16.4655685425,48.1288223267],"type":"Point"}
}