{
  "type": "Feature",
  "properties": {
    "addr:full":"Innsbrucker Bundesstrasse 79b Salzburg Salzburg 5020",
    "addr:housenumber":"79b",
    "addr:postcode":"5020",
    "addr:street":"Innsbrucker Bundesstrasse;Salzburg",
    "iso:country":"AT",
    "sg:address":"Innsbrucker Bundesstrasse 79b",
    "sg:city":"Salzburg",
    "sg:classifiers":[
        {
            "category":"Professional",
            "subcategory":"Art Services",
            "type":"Services"
        }
    ],
    "sg:phone":"+43 662 8239140",
    "sg:postcode":"5020",
    "sg:province":"Salzburg",
    "sg:tags":[
        "print"
    ],
    "sg:website":"lalineaprint.at",
    "wof:name":"la linea Druckerei Ges.m.b.H.",
    "wof:placetype":"venue"
},
  "geometry": {"coordinates":[13.0107049942,47.799407959],"type":"Point"}
}