{
  "type": "Feature",
  "properties": {
    "iso:country":"AT",
    "sg:address":"Wallackstrasse 1",
    "sg:city":"Bruck an der Gro\u00dfglocknerstra\u00dfe",
    "sg:classifiers":[
        {
            "category":"Manufacturing",
            "subcategory":"Glass & Minerals",
            "type":"Manufacturing & Wholesale Goods"
        }
    ],
    "sg:phone":"+43 6545 7217",
    "sg:postcode":"5671",
    "sg:province":"Salzburg",
    "sg:tags":[
        "design"
    ],
    "wof:name":"Adolf Linhart",
    "wof:placetype":"venue"
},
  "geometry": {"coordinates":[12.8223514557,47.2856216431],"type":"Point"}
}