{
  "type": "Feature",
  "properties": {
    "iso:country":"AT",
    "sg:address":"Kerschham 26",
    "sg:city":"Lochen",
    "sg:classifiers":[
        {
            "category":"Manufacturing",
            "subcategory":"Wood Products",
            "type":"Manufacturing & Wholesale Goods"
        }
    ],
    "sg:phone":"+43 7747 40090",
    "sg:postcode":"5221",
    "sg:province":"Ober\u00f6sterreich",
    "sg:tags":[
        "case"
    ],
    "wof:name":"Rudolf Winkler-Rieder",
    "wof:placetype":"venue"
},
  "geometry": {"coordinates":[13.1280651093,48.0320739746],"type":"Point"}
}