{
  "type": "Feature",
  "properties": {
    "addr:full":"Schmiedg 30 Zeltweg Steiermark 8740",
    "addr:housenumber":"30",
    "addr:postcode":"8740",
    "addr:street":"Schmiedg",
    "iso:country":"AT",
    "sg:address":"Schmiedg 30",
    "sg:city":"Zeltweg",
    "sg:orig_category":"Architekten",
    "sg:phone":"+43 3577 241150",
    "sg:postcode":"8740",
    "sg:province":"Steiermark",
    "wof:name":"Kapfenberger Peter Arch Dipl-Ing",
    "wof:placetype":"venue"
},
  "geometry": {"coordinates":[14.744468689,47.1943473816],"type":"Point"}
}