{
  "type": "Feature",
  "properties": {
    "addr:full":"Annagasse 5 Wien Wien 1010",
    "addr:housenumber":"5",
    "addr:postcode":"1010",
    "addr:street":"Annagasse",
    "iso:country":"AT",
    "sg:address":"Annagasse 5",
    "sg:city":"Wien",
    "sg:classifiers":[
        {
            "category":"Retail",
            "subcategory":"Event Space",
            "type":"Services"
        }
    ],
    "sg:phone":"+43 1 5136633000",
    "sg:postcode":"1010",
    "sg:province":"Wien",
    "sg:tags":[
        "telecommunication"
    ],
    "sg:website":"winag.com",
    "wof:name":"WiNAG.com",
    "wof:placetype":"venue"
},
  "geometry": {"coordinates":[16.3720397949,48.204460144],"type":"Point"}
}