{
  "type": "Feature",
  "properties": {
    "iso:country":"AT",
    "sg:address":"Siezenheimer Str 35",
    "sg:city":"Salzburg",
    "sg:orig_category":"Steuerberatung",
    "sg:phone":"+43 662 8349910",
    "sg:postcode":"5020",
    "sg:province":"Salzburg",
    "wof:name":"Heger Hans Michael",
    "wof:placetype":"venue"
},
  "geometry": {"coordinates":[13.0105524063,47.805480957],"type":"Point"}
}