{
  "type": "Feature",
  "properties": {
    "iso:country":"AT",
    "sg:address":"Josef-\u00f6sterreicher-G 22/2",
    "sg:city":"Wien",
    "sg:orig_category":"Psychotherapie",
    "sg:phone":"+43 1 9570294",
    "sg:postcode":"1230",
    "sg:province":"Wien",
    "wof:name":"Riedl Werner",
    "wof:placetype":"venue"
},
  "geometry": {"coordinates":[16.3009567261,48.1459846497],"type":"Point"}
}