{
  "type": "Feature",
  "properties": {
    "iso:country":"AT",
    "sg:address":"Bl\u00fctenstr 15",
    "sg:city":"Linz",
    "sg:classifiers":[
        {
            "category":"Professional",
            "subcategory":"Computer Services",
            "type":"Services"
        }
    ],
    "sg:phone":"+43 732 72730",
    "sg:postcode":"4040",
    "sg:province":"Ober\u00f6sterreich",
    "sg:tags":[
        "software"
    ],
    "wof:name":"CSC Computer Sciences Consulting Austria AG",
    "wof:placetype":"venue"
},
  "geometry": {"coordinates":[14.2578554153,48.3602561951],"type":"Point"}
}