{
  "type": "Feature",
  "properties": {
    "iso:country":"AT",
    "sg:address":"Thurnfeldg 4a",
    "sg:city":"Hall in Tirol",
    "sg:classifiers":[
        {
            "category":"Organizations",
            "subcategory":"Political Organization",
            "type":"Services"
        }
    ],
    "sg:phone":"+43 664 2554177",
    "sg:postcode":"6060",
    "sg:province":"Tirol",
    "sg:tags":[
        "mediation"
    ],
    "wof:name":"solutio ...faire Konfliktregelung durch Mediation",
    "wof:placetype":"venue"
},
  "geometry": {"coordinates":[11.5099096298,47.2834091187],"type":"Point"}
}