{
  "type": "Feature",
  "properties": {
    "addr:full":"Jakob-Prandtauer-Strasse 1 W\u00f6rgl Tirol 6300",
    "addr:housenumber":"1",
    "addr:postcode":"6300",
    "addr:street":"Jakob-Prandtauer-Strasse;Tirol",
    "iso:country":"AT",
    "sg:address":"Jakob-Prandtauer-Strasse 1",
    "sg:city":"W\u00f6rgl",
    "sg:classifiers":[
        {
            "category":"Professional",
            "subcategory":"Advertising",
            "type":"Services"
        }
    ],
    "sg:phone":"+43 5332 78730",
    "sg:postcode":"6300",
    "sg:province":"Tirol",
    "sg:tags":[
        "article",
        "plexiglas"
    ],
    "sg:website":"geotec-at.com",
    "wof:name":"GEOtec Zeichen- und Kunststofftechnik GmbH",
    "wof:placetype":"venue"
},
  "geometry": {"coordinates":[-69.3131027222,-51.6091995239],"type":"Point"}
}