{
  "type": "Feature",
  "properties": {
    "addr:full":"Wienerstrasse 82 Gumpoldskirchen Nieder\u00f6sterreich 2352",
    "addr:housenumber":"82",
    "addr:postcode":"2352",
    "addr:street":"Wienerstrasse",
    "iso:country":"AT",
    "sg:address":"Wienerstrasse 82",
    "sg:city":"Gumpoldskirchen",
    "sg:classifiers":[
        {
            "category":"Industrial Area",
            "type":"Public Place"
        }
    ],
    "sg:phone":"+43 2252 63550",
    "sg:postcode":"2352",
    "sg:province":"Nieder\u00f6sterreich",
    "sg:tags":[
        "hose"
    ],
    "sg:website":"schlauchtechnik-mayerhofer.at/",
    "wof:name":"Ing. Mayerhofer GmbH Werksvertretungen",
    "wof:placetype":"venue"
},
  "geometry": {"coordinates":[16.2822322845,48.0432739258],"type":"Point"}
}