{
  "type": "Feature",
  "properties": {
    "addr:full":"Hauptstr 83 Gro\u00dfpetersdorf Burgenland 7503",
    "addr:housenumber":"83",
    "addr:postcode":"7503",
    "addr:street":"Hauptstr",
    "iso:country":"AT",
    "sg:address":"Hauptstr 83",
    "sg:city":"Gro\u00dfpetersdorf",
    "sg:orig_category":"Tabaktrafiken",
    "sg:phone":"+43 3362 7164",
    "sg:postcode":"7503",
    "sg:province":"Burgenland",
    "wof:name":"Kalcsics Sabine",
    "wof:placetype":"venue"
},
  "geometry": {"coordinates":[12.1167001724,54.1500015259],"type":"Point"}
}