{
  "type": "Feature",
  "properties": {
    "addr:full":"Feldg 5 Neustadtl Nieder\u00f6sterreich 3323",
    "addr:housenumber":"5",
    "addr:postcode":"3323",
    "addr:street":"Feldg",
    "iso:country":"AT",
    "sg:address":"Feldg 5",
    "sg:city":"Neustadtl",
    "sg:orig_category":"Hauptschulen",
    "sg:phone":"+43 7471 7003",
    "sg:postcode":"3323",
    "sg:province":"Nieder\u00f6sterreich",
    "wof:name":"Hauptschule",
    "wof:placetype":"venue"
},
  "geometry": {"coordinates":[20.3330097198,47.9864997864],"type":"Point"}
}