{
  "type": "Feature",
  "properties": {
    "iso:country":"AT",
    "sg:address":"Johannesstr 3",
    "sg:city":"Maria Enzersdorf",
    "sg:classifiers":[
        {
            "category":"Organizations",
            "subcategory":"Community Association",
            "type":"Services"
        }
    ],
    "sg:phone":"+43 664 1839912",
    "sg:postcode":"2344",
    "sg:province":"Nieder\u00f6sterreich",
    "sg:tags":[
        "relation",
        "public"
    ],
    "wof:name":"Domus Communications",
    "wof:placetype":"venue"
},
  "geometry": {"coordinates":[16.2828788757,48.09608078],"type":"Point"}
}