{
  "type": "Feature",
  "properties": {
    "addr:full":"Prager Strasse 280 Wien Wien 1210",
    "addr:housenumber":"280",
    "addr:postcode":"1210",
    "addr:street":"Prager Strasse",
    "iso:country":"AT",
    "sg:address":"Prager Strasse 280",
    "sg:city":"Wien",
    "sg:classifiers":[
        {
            "category":"Banks & Credit Unions",
            "subcategory":"Investment Brokerage",
            "type":"Services"
        }
    ],
    "sg:phone":"+43 1 29240200",
    "sg:postcode":"1210",
    "sg:province":"Wien",
    "sg:tags":[
        "flange",
        "collar"
    ],
    "sg:website":"asahydraulik.com",
    "wof:name":"asa hydraulik Ges.m.b.H.",
    "wof:placetype":"venue"
},
  "geometry": {"coordinates":[16.382642746,48.2886238098],"type":"Point"}
}