{
  "type": "Feature",
  "properties": {
    "addr:full":"Ingen Housz-G 4 Wien Wien 1090",
    "addr:housenumber":"4",
    "addr:postcode":"1090",
    "addr:street":"Housz-G",
    "iso:country":"AT",
    "sg:address":"Ingen Housz-G 4",
    "sg:city":"Wien",
    "sg:orig_category":"Steuerberatung",
    "sg:phone":"+43 1 3178910",
    "sg:postcode":"1090",
    "sg:province":"Wien",
    "wof:name":"AMCUR Consulting",
    "wof:placetype":"venue"
},
  "geometry": {"coordinates":[16.363401413,48.2271537781],"type":"Point"}
}