{
  "type": "Feature",
  "properties": {
    "addr:full":"Linzer Str 1 Enns Ober\u00f6sterreich 4470",
    "addr:housenumber":"1",
    "addr:postcode":"4470",
    "addr:street":"Linzer Str",
    "iso:country":"AT",
    "sg:address":"Linzer Str 1",
    "sg:city":"Enns",
    "sg:orig_category":"Boutiquen",
    "sg:phone":"+43 7223 81203",
    "sg:postcode":"4470",
    "sg:province":"Ober\u00f6sterreich",
    "wof:name":"Madonna Moden",
    "wof:placetype":"venue"
},
  "geometry": {"coordinates":[14.4788627625,48.2139778137],"type":"Point"}
}