{
  "type": "Feature",
  "properties": {
    "addr:full":"Oberganderweg 4 St. Anton am Arlberg Tirol 6580",
    "addr:housenumber":"4",
    "addr:postcode":"6580",
    "addr:street":"Oberganderweg;Tirol",
    "iso:country":"AT",
    "sg:address":"Oberganderweg 4",
    "sg:city":"St. Anton am Arlberg",
    "sg:orig_category":"Pensionen / Privatzimmer",
    "sg:phone":"+43 5446 2574",
    "sg:postcode":"6580",
    "sg:province":"Tirol",
    "wof:name":"J\u00e4gerhof",
    "wof:placetype":"venue"
},
  "geometry": {"coordinates":[10.3014698029,47.1444892883],"type":"Point"}
}