{
  "type": "Feature",
  "properties": {
    "addr:full":"Gredlerstr 4 Wien Wien 1020",
    "addr:housenumber":"4",
    "addr:postcode":"1020",
    "addr:street":"Gredlerstr",
    "iso:country":"AT",
    "sg:address":"Gredlerstr 4",
    "sg:city":"Wien",
    "sg:orig_category":"Bauunternehmen",
    "sg:phone":"+43 1 2147307",
    "sg:postcode":"1020",
    "sg:province":"Wien",
    "wof:name":"Sigma.Pro - ProjektentwicklungsgesmbH",
    "wof:placetype":"venue"
},
  "geometry": {"coordinates":[16.3788528442,48.2136535645],"type":"Point"}
}