{
  "type": "Feature",
  "properties": {
    "addr:full":"Aussen 106 Kirchberg am Wechsel Nieder\u00f6sterreich 2880",
    "addr:housenumber":"106",
    "addr:postcode":"2880",
    "addr:street":"Aussen",
    "iso:country":"AT",
    "sg:address":"Aussen 106",
    "sg:city":"Kirchberg am Wechsel",
    "sg:classifiers":[
        {
            "category":"Building & Trades",
            "subcategory":"Electrical",
            "type":"Services"
        }
    ],
    "sg:phone":"+43 2641 2220",
    "sg:postcode":"2880",
    "sg:province":"Nieder\u00f6sterreich",
    "sg:tags":[
        "installation"
    ],
    "wof:name":"Elektrizit\u00e4tswerke Eisenhuber GMBH & Co KG",
    "wof:placetype":"venue"
},
  "geometry": {"coordinates":[16.020275116,47.6081848145],"type":"Point"}
}