{
  "type": "Feature",
  "properties": {
    "addr:full":"Krong 8 Wien Wien 1050",
    "addr:housenumber":"8",
    "addr:postcode":"1050",
    "addr:street":"Krong",
    "iso:country":"AT",
    "sg:address":"Krong 8",
    "sg:city":"Wien",
    "sg:orig_category":"Audiovisuelle Produktionen",
    "sg:phone":"+43 4319 294000",
    "sg:postcode":"1050",
    "sg:province":"Wien",
    "wof:name":"av-design audiovisuelle Design- u Produktions GmbH",
    "wof:placetype":"venue"
},
  "geometry": {"coordinates":[16.3628501892,48.1922874451],"type":"Point"}
}