{
  "type": "Feature",
  "properties": {
    "iso:country":"AT",
    "sg:address":"Reiherweg 23",
    "sg:city":"Haid",
    "sg:classifiers":[
        {
            "category":"Professional",
            "subcategory":"Art Services",
            "type":"Services"
        }
    ],
    "sg:phone":"+43 7229 81882",
    "sg:postcode":"4053",
    "sg:province":"Ober\u00f6sterreich",
    "sg:tags":[
        "designer"
    ],
    "wof:name":"ZACH DESIGN",
    "wof:placetype":"venue"
},
  "geometry": {"coordinates":[14.2627820969,48.2154464722],"type":"Point"}
}