{
  "type": "Feature",
  "properties": {
    "addr:full":"Raiffeisenpl 1 Ternberg Ober\u00f6sterreich 4452",
    "addr:housenumber":"1",
    "addr:postcode":"4452",
    "addr:street":"Raiffeisenpl",
    "iso:country":"AT",
    "sg:address":"Raiffeisenpl 1",
    "sg:city":"Ternberg",
    "sg:orig_category":"Fu\u00c3\u0178pflege U Fu\u00c3\u0178pflegesalons",
    "sg:phone":"+43 7256 71400",
    "sg:postcode":"4452",
    "sg:province":"Ober\u00f6sterreich",
    "wof:name":"Hohlrieder Gabriele/Bichler Karin - Fusspflege-Kosmetiksalon",
    "wof:placetype":"venue"
},
  "geometry": {"coordinates":[14.3548488617,47.9463920593],"type":"Point"}
}