{
  "type": "Feature",
  "properties": {
    "addr:full":"Bundesstr 135 Werndorf Steiermark 8402",
    "addr:housenumber":"135",
    "addr:postcode":"8402",
    "iso:country":"AT",
    "sg:address":"Bundesstr 135",
    "sg:city":"Werndorf",
    "sg:orig_category":"Gemeinden",
    "sg:phone":"+43 3135 543030",
    "sg:postcode":"8402",
    "sg:province":"Steiermark",
    "wof:name":"Gemeindeamt Werndorf",
    "wof:placetype":"venue"
},
  "geometry": {"coordinates":[15.4817962646,46.9220314026],"type":"Point"}
}