{
  "type": "Feature",
  "properties": {
    "addr:full":"Bachlechnerstr 21-23 Innsbruck Tirol 6020",
    "addr:housenumber":"21-23",
    "addr:postcode":"6020",
    "addr:street":"Tirol",
    "iso:country":"AT",
    "sg:address":"Bachlechnerstr 21-23",
    "sg:city":"Innsbruck",
    "sg:orig_category":"Dachdeckereien",
    "sg:phone":"+43 4351 22815520",
    "sg:postcode":"6020",
    "sg:province":"Tirol",
    "wof:name":"Zschiegner Hermann GesmbH",
    "wof:placetype":"venue"
},
  "geometry": {"coordinates":[11.3759212494,47.2614021301],"type":"Point"}
}