{
  "type": "Feature",
  "properties": {
    "addr:full":"Albrechtstr 60-62 Klosterneuburg Nieder\u00f6sterreich 3400",
    "addr:housenumber":"60-62",
    "addr:postcode":"3400",
    "addr:street":"Niederoesterreich",
    "iso:country":"AT",
    "sg:address":"Albrechtstr 60-62",
    "sg:city":"Klosterneuburg",
    "sg:orig_category":"Transportunternehmen",
    "sg:phone":"+43 2243 32829",
    "sg:postcode":"3400",
    "sg:province":"Nieder\u00f6sterreich",
    "wof:name":"Zeisel Ernst Inh Heinz Zerfass",
    "wof:placetype":"venue"
},
  "geometry": {"coordinates":[16.3191699982,48.3113136292],"type":"Point"}
}