{
  "type": "Feature",
  "properties": {
    "addr:full":"Burgg 134 Judenburg Steiermark 8750",
    "addr:housenumber":"134",
    "addr:postcode":"8750",
    "iso:country":"AT",
    "sg:address":"Burgg 134",
    "sg:city":"Judenburg",
    "sg:orig_category":"Autoreparatur",
    "sg:phone":"+43 3572 824100",
    "sg:postcode":"8750",
    "sg:province":"Steiermark",
    "wof:name":"Eibegger Werner GmbH",
    "wof:placetype":"venue"
},
  "geometry": {"coordinates":[14.6332101822,47.1718254089],"type":"Point"}
}