{
  "type": "Feature",
  "properties": {
    "addr:full":"Nr 57 Freinberg Ober\u00f6sterreich 4785",
    "addr:postcode":"4785",
    "addr:street":"Nr;Freinberg",
    "iso:country":"AT",
    "sg:address":"Nr 57",
    "sg:city":"Freinberg",
    "sg:orig_category":"Transportunternehmen",
    "sg:phone":"+43 4377 1381060",
    "sg:postcode":"4785",
    "sg:province":"Ober\u00f6sterreich",
    "wof:name":"Schmied Transport GesmbH & Co KG",
    "wof:placetype":"venue"
},
  "geometry": {"coordinates":[13.5144405365,48.5661468506],"type":"Point"}
}