{
  "type": "Feature",
  "properties": {
    "addr:full":"Burgg 9 Klagenfurt K\u00e4rnten 9020",
    "addr:housenumber":"9",
    "addr:postcode":"9020",
    "addr:street":"Burgg;Kaernten",
    "iso:country":"AT",
    "sg:address":"Burgg 9",
    "sg:city":"Klagenfurt",
    "sg:orig_category":"Versicherungsunternehmen",
    "sg:phone":"+43 463 58290",
    "sg:postcode":"9020",
    "sg:province":"K\u00e4rnten",
    "wof:name":"Interunfall Versicherung-AG",
    "wof:placetype":"venue"
},
  "geometry": {"coordinates":[14.30946064,46.6244316101],"type":"Point"}
}