{
  "type": "Feature",
  "properties": {
    "iso:country":"AT",
    "sg:address":"Landstra\u00dfer Hauptstr 130",
    "sg:city":"Wien",
    "sg:orig_category":"Papier- U Schreibwaren / Einzelhandel",
    "sg:phone":"+43 1 7133742",
    "sg:postcode":"1030",
    "sg:province":"Wien",
    "wof:name":"Pfannhauser Erich",
    "wof:placetype":"venue"
},
  "geometry": {"coordinates":[16.3963775635,48.1955680847],"type":"Point"}
}