{
  "type": "Feature",
  "properties": {
    "iso:country":"AT",
    "sg:address":"P\u00f6llach 76",
    "sg:city":"St. Gilgen",
    "sg:orig_category":"Abfallentsorgung U -Verwertung",
    "sg:phone":"+43 4362 2725520",
    "sg:postcode":"5340",
    "sg:province":"Salzburg",
    "wof:name":"A S A Containertransport GesmbH",
    "wof:placetype":"venue"
},
  "geometry": {"coordinates":[13.3508062363,47.7790718079],"type":"Point"}
}