{
  "type": "Feature",
  "properties": {
    "iso:country":"AT",
    "sg:address":"Bahng 29-33",
    "sg:city":"Wiener Neustadt",
    "sg:classifiers":[
        {
            "category":"Travel",
            "subcategory":"Hotels & Motels",
            "type":"Entertainment"
        }
    ],
    "sg:phone":"+43 2622 241340",
    "sg:postcode":"2700",
    "sg:province":"Nieder\u00f6sterreich",
    "wof:name":"Corvinus Hotel",
    "wof:placetype":"venue"
},
  "geometry": {"coordinates":[16.2379951477,47.8111915588],"type":"Point"}
}