{
  "type": "Feature",
  "properties": {
    "addr:full":"Bahnhofstr 10 Ternberg Ober\u00f6sterreich 4452",
    "addr:housenumber":"10",
    "addr:postcode":"4452",
    "addr:street":"Bahnhofstr",
    "iso:country":"AT",
    "sg:address":"Bahnhofstr 10",
    "sg:city":"Ternberg",
    "sg:orig_category":"Metallwaren / Einzelhandel",
    "sg:phone":"+43 7256 20097",
    "sg:postcode":"4452",
    "sg:province":"Ober\u00f6sterreich",
    "wof:name":"ab Metallwaren GmbH",
    "wof:placetype":"venue"
},
  "geometry": {"coordinates":[14.3555994034,47.9499778748],"type":"Point"}
}