{
  "type": "Feature",
  "properties": {
    "addr:full":"Glaser Str 32a Aigen Salzburg 5026",
    "addr:postcode":"5026",
    "addr:street":"Str 32A;Salzburg",
    "iso:country":"AT",
    "sg:address":"Glaser Str 32a",
    "sg:city":"Aigen",
    "sg:orig_category":"Spirituosen / Erzeugung U Gro\u00c3\u0178handel",
    "sg:phone":"+43 662 623234",
    "sg:postcode":"5026",
    "sg:province":"Salzburg",
    "wof:name":"Schnaps-Express-Schwab",
    "wof:placetype":"venue"
},
  "geometry": {"coordinates":[13.0871562958,47.777923584],"type":"Point"}
}