{
  "type": "Feature",
  "properties": {
    "addr:full":"Trattnachtalstr 25 Grieskirchen Ober\u00f6sterreich 4710",
    "addr:housenumber":"25",
    "addr:postcode":"4710",
    "addr:street":"Trattnachtalstr",
    "iso:country":"AT",
    "sg:address":"Trattnachtalstr 25",
    "sg:city":"Grieskirchen",
    "sg:orig_category":"Erdarbeiten",
    "sg:phone":"+43 4372 48625640",
    "sg:postcode":"4710",
    "sg:province":"Ober\u00f6sterreich",
    "wof:name":"Felbermayr Bau GmbH & Co KG",
    "wof:placetype":"venue"
},
  "geometry": {"coordinates":[13.8142347336,48.2371253967],"type":"Point"}
}