{
  "type": "Feature",
  "properties": {
    "addr:full":"Gewerbezone 2 Bleiburg K\u00e4rnten 9150",
    "addr:housenumber":"2",
    "addr:postcode":"9150",
    "addr:street":"Gewerbezone;Kaernten",
    "iso:country":"AT",
    "sg:address":"Gewerbezone 2",
    "sg:city":"Bleiburg",
    "sg:classifiers":[
        {
            "category":"Community Center",
            "subcategory":"Senior",
            "type":"Public Place"
        }
    ],
    "sg:phone":"+43 4235 4235",
    "sg:postcode":"9150",
    "sg:province":"K\u00e4rnten",
    "sg:tags":[
        "tile",
        "wall",
        "ceramic"
    ],
    "wof:name":"Leopold Prutej",
    "wof:placetype":"venue"
},
  "geometry": {"coordinates":[14.799115181,46.5901870728],"type":"Point"}
}