{
  "type": "Feature",
  "properties": {
    "iso:country":"AT",
    "sg:address":"St Veiter Str 4",
    "sg:city":"Klagenfurt",
    "sg:orig_category":"Lebensmittel / Einzelhandel",
    "sg:phone":"+43 463 516511",
    "sg:postcode":"9020",
    "sg:province":"K\u00e4rnten",
    "wof:name":"MONDO Lebensmitteldiskonter",
    "wof:placetype":"venue"
},
  "geometry": {"coordinates":[14.3029489517,46.6278991699],"type":"Point"}
}