{
  "type": "Feature",
  "properties": {
    "iso:country":"AT",
    "sg:address":"R\u00f6merweg 11",
    "sg:city":"Windischgarsten",
    "sg:orig_category":"Volkshochschulen",
    "sg:phone":"+43 7562 5373",
    "sg:postcode":"4580",
    "sg:province":"Ober\u00f6sterreich",
    "wof:name":"Volkshochschule Ober\u00f6sterreich gemeinn\u00fctzige Bildungs-GmbH d AK f O\u00d6",
    "wof:placetype":"venue"
},
  "geometry": {"coordinates":[14.3275403976,47.7224311829],"type":"Point"}
}