{
  "type": "Feature",
  "properties": {
    "addr:full":"Heiligenst\u00e4dter Str 11-25 Wien Wien 1190",
    "addr:postcode":"11-25;1190",
    "addr:street":"Str",
    "iso:country":"AT",
    "sg:address":"Heiligenst\u00e4dter Str 11-25",
    "sg:city":"Wien",
    "sg:orig_category":"Tischlereimaschinen U -Bedarf",
    "sg:phone":"+43 4313 693108",
    "sg:postcode":"1190",
    "sg:province":"Wien",
    "wof:name":"Bao-Generalvertrieb Karlitzky",
    "wof:placetype":"venue"
},
  "geometry": {"coordinates":[16.3561878204,48.2333450317],"type":"Point"}
}