{
  "type": "Feature",
  "properties": {
    "addr:full":"Hauptstr 37 St. Johann im Pongau Salzburg 5600",
    "addr:housenumber":"37",
    "addr:postcode":"5600",
    "addr:street":"Hauptstr;Salzburg",
    "iso:country":"AT",
    "sg:address":"Hauptstr 37",
    "sg:city":"St. Johann im Pongau",
    "sg:orig_category":"Immobilienverwaltungen",
    "sg:phone":"+43 6412 60720",
    "sg:postcode":"5600",
    "sg:province":"Salzburg",
    "sg:website":"kappacher-immobilien.at",
    "wof:name":"Kappacher H & P KEG",
    "wof:placetype":"venue"
},
  "geometry": {"coordinates":[13.202501297,47.3490104675],"type":"Point"}
}