{
  "type": "Feature",
  "properties": {
    "iso:country":"AT",
    "sg:address":"Oberstein 9",
    "sg:city":"St. Martin am Tennengebirge",
    "sg:orig_category":"Autobusunternehmen",
    "sg:phone":"+43 4364 637364",
    "sg:postcode":"5522",
    "sg:province":"Salzburg",
    "sg:website":"busreisen-schober.at",
    "wof:name":"Autobusunternehmen Schober Hans-Peter",
    "wof:placetype":"venue"
},
  "geometry": {"coordinates":[13.3807420731,47.4529037476],"type":"Point"}
}