{
  "type": "Feature",
  "properties": {
    "addr:full":"Gf\u00f6hler Strasse 4 Lengenfeld Nieder\u00f6sterreich 3552",
    "addr:housenumber":"4",
    "addr:postcode":"3552",
    "addr:street":"Gfoehler Strasse",
    "iso:country":"AT",
    "sg:address":"Gf\u00f6hler Strasse 4",
    "sg:city":"Lengenfeld",
    "sg:classifiers":[
        {
            "category":"Home & Garden",
            "subcategory":"Furniture",
            "type":"Retail Goods"
        }
    ],
    "sg:phone":"+43 2719 2264",
    "sg:postcode":"3552",
    "sg:province":"Nieder\u00f6sterreich",
    "sg:tags":[
        "bathroom"
    ],
    "wof:name":"Hannes Steinschaden",
    "wof:placetype":"venue"
},
  "geometry": {"coordinates":[15.598359108,48.4714813232],"type":"Point"}
}