{
  "type": "Feature",
  "properties": {
    "addr:full":"Scheibe 6 Neustift im Stubaital Tirol 6167",
    "addr:housenumber":"6",
    "addr:postcode":"6167",
    "addr:street":"Scheibe;Tirol",
    "iso:country":"AT",
    "sg:address":"Scheibe 6",
    "sg:city":"Neustift im Stubaital",
    "sg:orig_category":"Sportschulen",
    "sg:phone":"+43 4352 262983",
    "sg:postcode":"6167",
    "sg:province":"Tirol",
    "wof:name":"Bergf\u00fchrerb\u00fcro Stubai",
    "wof:placetype":"venue"
},
  "geometry": {"coordinates":[11.297369957,47.1076812744],"type":"Point"}
}