{
  "type": "Feature",
  "properties": {
    "iso:country":"AT",
    "sg:address":"K\u00fchnsdorf Nord 53",
    "sg:city":"K\u00fchnsdorf",
    "sg:orig_category":"Unterhaltungselektronik / Einzelhandel",
    "sg:phone":"+43 4232 8610",
    "sg:postcode":"9125",
    "sg:province":"K\u00e4rnten",
    "wof:name":"Susnik Erwin",
    "wof:placetype":"venue"
},
  "geometry": {"coordinates":[14.6333837509,46.6243171692],"type":"Point"}
}