{
  "type": "Feature",
  "properties": {
    "addr:full":"Sch\u00fcttaupl 22-23 Wien Wien 1220",
    "addr:postcode":"22-23;1220",
    "iso:country":"AT",
    "sg:address":"Sch\u00fcttaupl 22-23",
    "sg:city":"Wien",
    "sg:orig_category":"Banken U Sparkassen",
    "sg:phone":"+43 1 26335770",
    "sg:postcode":"1220",
    "sg:province":"Wien",
    "wof:name":"Raiffeisenlandesbank N\u00d6-Wien AG",
    "wof:placetype":"venue"
},
  "geometry": {"coordinates":[16.444606781,48.2497138977],"type":"Point"}
}