{
  "type": "Feature",
  "properties": {
    "addr:full":"Liechtensteiner Strasse 21 Feldkirch Vorarlberg 6800",
    "addr:housenumber":"21",
    "addr:postcode":"6800",
    "addr:street":"Liechtensteiner Strasse",
    "iso:country":"AT",
    "sg:address":"Liechtensteiner Strasse 21",
    "sg:city":"Feldkirch",
    "sg:classifiers":[
        {
            "category":"Bars & Pubs",
            "subcategory":"Wine Bar",
            "type":"Food & Drink"
        }
    ],
    "sg:phone":"+43 5522 733330",
    "sg:postcode":"6800",
    "sg:province":"Vorarlberg",
    "sg:tags":[
        "cake"
    ],
    "wof:name":"Jakob Schnell Ges.m.b.H. & Co KG",
    "wof:placetype":"venue"
},
  "geometry": {"coordinates":[9.5908041,47.2362251282],"type":"Point"}
}