{
  "type": "Feature",
  "properties": {
    "iso:country":"AT",
    "sg:address":"Hauptstr 98",
    "sg:city":"Kaltenleutgeben",
    "sg:orig_category":"Installationsunternehmen",
    "sg:phone":"+43 2238 71249",
    "sg:postcode":"2391",
    "sg:province":"Nieder\u00f6sterreich",
    "wof:name":"Witti Helmut",
    "wof:placetype":"venue"
},
  "geometry": {"coordinates":[16.1973934174,48.1161193848],"type":"Point"}
}