{
  "type": "Feature",
  "properties": {
    "addr:full":"Nr 10 Neukirchen Ober\u00f6sterreich 4671",
    "addr:postcode":"4671",
    "addr:street":"Nr 10",
    "iso:country":"AT",
    "sg:address":"Nr 10",
    "sg:city":"Neukirchen",
    "sg:orig_category":"Bierlokale-Pubs",
    "sg:phone":"+43 7735 723150",
    "sg:postcode":"4671",
    "sg:province":"Ober\u00f6sterreich",
    "wof:name":"Waschrumpl-Pub",
    "wof:placetype":"venue"
},
  "geometry": {"coordinates":[13.8145751953,48.0997619629],"type":"Point"}
}