{
  "type": "Feature",
  "properties": {
    "addr:full":"Untere Donaustr 27 Wien Wien 1020",
    "addr:housenumber":"27",
    "addr:postcode":"1020",
    "addr:street":"Untere Donaustr",
    "iso:country":"AT",
    "sg:address":"Untere Donaustr 27",
    "sg:city":"Wien",
    "sg:orig_category":"Markt- U Meinungsforschung",
    "sg:phone":"+43 4312 127368",
    "sg:postcode":"1020",
    "sg:province":"Wien",
    "wof:name":"Spitalsky Alfred - Marktforschung und Regionalprognostik",
    "wof:placetype":"venue"
},
  "geometry": {"coordinates":[16.38463974,48.2128334045],"type":"Point"}
}