{
  "type": "Feature",
  "properties": {
    "addr:full":"Lerchenauer Str 8/1 Lauterach Vorarlberg 6923",
    "addr:housenumber":"8 / 1",
    "addr:postcode":"6923",
    "addr:street":"Str",
    "iso:country":"AT",
    "sg:address":"Lerchenauer Str 8/1",
    "sg:city":"Lauterach",
    "sg:orig_category":"Feinkost",
    "sg:phone":"+43 5574 89888",
    "sg:postcode":"6923",
    "sg:province":"Vorarlberg",
    "wof:name":"Leo's W\u00e4lder und K\u00e4rntner Spezialit\u00e4ten",
    "wof:placetype":"venue"
},
  "geometry": {"coordinates":[9.7281761169,47.4734458923],"type":"Point"}
}