{
  "type": "Feature",
  "properties": {
    "iso:country":"AT",
    "sg:address":"Mariazeller Str 23",
    "sg:city":"Hofstetten",
    "sg:orig_category":"Forstverwaltungen",
    "sg:phone":"+43 2723 8821",
    "sg:postcode":"3202",
    "sg:province":"Nieder\u00f6sterreich",
    "wof:name":"Limberger Dietmar Ing",
    "wof:placetype":"venue"
},
  "geometry": {"coordinates":[15.4798202515,48.0778617859],"type":"Point"}
}