{
  "type": "Feature",
  "properties": {
    "addr:full":"Sch\u00f6rgelg 80 Graz Steiermark 8010",
    "addr:housenumber":"80",
    "addr:postcode":"8010",
    "addr:street":"Schoergelg",
    "iso:country":"AT",
    "sg:address":"Sch\u00f6rgelg 80",
    "sg:city":"Graz",
    "sg:orig_category":"Tabaktrafiken",
    "sg:phone":"+43 316 826217",
    "sg:postcode":"8010",
    "sg:province":"Steiermark",
    "wof:name":"Enge Wolfgang",
    "wof:placetype":"venue"
},
  "geometry": {"coordinates":[15.4624214172,47.0661811829],"type":"Point"}
}