{
  "type": "Feature",
  "properties": {
    "addr:full":"Schleifm\u00fchlg 2 Wien Wien 1040",
    "addr:housenumber":"2",
    "addr:postcode":"1040",
    "addr:street":"Schleifmuehlg",
    "iso:country":"AT",
    "sg:address":"Schleifm\u00fchlg 2",
    "sg:city":"Wien",
    "sg:orig_category":"Waren Aller Art",
    "sg:phone":"+43 1 5811607",
    "sg:postcode":"1040",
    "sg:province":"Wien",
    "wof:name":"P\u00f6tsch Manfred",
    "wof:placetype":"venue"
},
  "geometry": {"coordinates":[16.3671455383,48.1940345764],"type":"Point"}
}