{
  "type": "Feature",
  "properties": {
    "iso:country":"AT",
    "sg:address":"Ritter-von-Ghega-Weg 2",
    "sg:city":"St. Lorenzen im M\u00fcrztal",
    "sg:orig_category":"Tischlereien",
    "sg:phone":"+43 4338 642560",
    "sg:postcode":"8642",
    "sg:province":"Steiermark",
    "wof:name":"Grilz-Holz",
    "wof:placetype":"venue"
},
  "geometry": {"coordinates":[15.3644638062,47.4826698303],"type":"Point"}
}