{
  "type": "Feature",
  "properties": {
    "addr:full":"Hauptstr 1 Mattersburg Burgenland 7210",
    "addr:housenumber":"1",
    "addr:postcode":"7210",
    "addr:street":"Hauptstr",
    "iso:country":"AT",
    "sg:address":"Hauptstr 1",
    "sg:city":"Mattersburg",
    "sg:orig_category":"Reifen U Reifendienste",
    "sg:phone":"+43 4326 2662337",
    "sg:postcode":"7210",
    "sg:province":"Burgenland",
    "wof:name":"Koller Gerhard",
    "wof:placetype":"venue"
},
  "geometry": {"coordinates":[16.3978614807,47.736530304],"type":"Point"}
}