{
  "type": "Feature",
  "properties": {
    "addr:full":"Edelhof 9 Haag Nieder\u00f6sterreich 3350",
    "addr:housenumber":"9",
    "addr:postcode":"3350",
    "addr:street":"Edelhof",
    "iso:country":"AT",
    "sg:address":"Edelhof 9",
    "sg:city":"Haag",
    "sg:orig_category":"Garten- U Landschaftsgestaltung",
    "sg:phone":"+43 4366 41626642",
    "sg:postcode":"3350",
    "sg:province":"Nieder\u00f6sterreich",
    "wof:name":"Wiesinger Gartengestaltung",
    "wof:placetype":"venue"
},
  "geometry": {"coordinates":[14.5464019775,48.1186103821],"type":"Point"}
}