{
  "type": "Feature",
  "properties": {
    "addr:full":"Waldstr 29 Munderfing Ober\u00f6sterreich 5222",
    "addr:housenumber":"29",
    "addr:postcode":"5222",
    "addr:street":"Waldstr",
    "iso:country":"AT",
    "sg:address":"Waldstr 29",
    "sg:city":"Munderfing",
    "sg:orig_category":"Tischlereien",
    "sg:phone":"+43 7744 6352",
    "sg:postcode":"5222",
    "sg:province":"Ober\u00f6sterreich",
    "wof:name":"Fuchs Werner",
    "wof:placetype":"venue"
},
  "geometry": {"coordinates":[13.1860990524,48.065738678],"type":"Point"}
}