{
  "type": "Feature",
  "properties": {
    "addr:full":"Linzer Str 8 Kirchdorf an der Krems Ober\u00f6sterreich 4560",
    "addr:housenumber":"8",
    "addr:postcode":"4560",
    "addr:street":"Linzer Str",
    "iso:country":"AT",
    "sg:address":"Linzer Str 8",
    "sg:city":"Kirchdorf an der Krems",
    "sg:orig_category":"Personalbereitstellung",
    "sg:phone":"+43 4375 8261635",
    "sg:postcode":"4560",
    "sg:province":"Ober\u00f6sterreich",
    "wof:name":"Actron Personalleasing GmbH",
    "wof:placetype":"venue"
},
  "geometry": {"coordinates":[14.1218137741,47.907749176],"type":"Point"}
}