{
  "type": "Feature",
  "properties": {
    "addr:full":"Blutschwitzerweg 33 Fulpmes Tirol 6166",
    "addr:housenumber":"33",
    "addr:postcode":"6166",
    "addr:street":"Blutschwitzerweg;Tirol",
    "iso:country":"AT",
    "sg:address":"Blutschwitzerweg 33",
    "sg:city":"Fulpmes",
    "sg:orig_category":"Architekten",
    "sg:phone":"+43 5225 63633",
    "sg:postcode":"6166",
    "sg:province":"Tirol",
    "wof:name":"Arch Visu Kr\u00f6sbacher, Zirler KEG",
    "wof:placetype":"venue"
},
  "geometry": {"coordinates":[11.3463611603,47.1386909485],"type":"Point"}
}