{
  "type": "Feature",
  "properties": {
    "addr:full":"Austrasse 25a Jenbach Tirol 6200",
    "addr:housenumber":"25a",
    "addr:postcode":"6200",
    "addr:street":"Austrasse;Tirol",
    "iso:country":"AT",
    "sg:address":"Austrasse 25a",
    "sg:city":"Jenbach",
    "sg:classifiers":[
        {
            "category":"Recreation",
            "subcategory":"Amusement Park",
            "type":"Entertainment"
        }
    ],
    "sg:phone":"+43 5244 64617",
    "sg:postcode":"6200",
    "sg:province":"Tirol",
    "sg:tags":[
        "equipment"
    ],
    "sg:website":"art-rock.com",
    "wof:name":"Art Rock Kletterw\u00e4nde GesmbH",
    "wof:placetype":"venue"
},
  "geometry": {"coordinates":[11.7837657928,47.3884773254],"type":"Point"}
}