{
  "type": "Feature",
  "properties": {
    "addr:full":"Siccardsburgg 4 Wien Wien 1100",
    "addr:housenumber":"4",
    "addr:postcode":"1100",
    "addr:street":"Siccardsburgg",
    "iso:country":"AT",
    "sg:address":"Siccardsburgg 4",
    "sg:city":"Wien",
    "sg:orig_category":"Handelsagenturen",
    "sg:phone":"+43 1 9139050",
    "sg:postcode":"1100",
    "sg:province":"Wien",
    "wof:name":"Sch\u00fctzenauer Peter",
    "wof:placetype":"venue"
},
  "geometry": {"coordinates":[16.3709697723,48.1809616089],"type":"Point"}
}