{
  "type": "Feature",
  "properties": {
    "iso:country":"AT",
    "sg:address":"Fabriksg 6",
    "sg:city":"Neunkirchen",
    "sg:orig_category":"Notare",
    "sg:phone":"+43 2635 624370",
    "sg:postcode":"2620",
    "sg:province":"Nieder\u00f6sterreich",
    "wof:name":"Feichtinger Johannes Dr",
    "wof:placetype":"venue"
},
  "geometry": {"coordinates":[16.0824928284,47.7212486267],"type":"Point"}
}