{
  "type": "Feature",
  "properties": {
    "addr:full":"St. Peter 40 Freistadt Ober\u00f6sterreich 4240",
    "addr:housenumber":"40",
    "addr:postcode":"4240",
    "addr:street":"St. Peter",
    "iso:country":"AT",
    "sg:address":"St. Peter 40",
    "sg:city":"Freistadt",
    "sg:classifiers":[
        {
            "category":"Banks & Credit Unions",
            "subcategory":"Financial Services",
            "type":"Services"
        }
    ],
    "sg:phone":"+43 7942 732420",
    "sg:postcode":"4240",
    "sg:province":"Ober\u00f6sterreich",
    "sg:tags":[
        "finance",
        "industry",
        "banking",
        "accounting",
        "insurance",
        "software"
    ],
    "sg:website":"finanz-software.com",
    "wof:name":"Walter Lang Finanzsoftware GmbH",
    "wof:placetype":"venue"
},
  "geometry": {"coordinates":[14.4899368286,48.5122070312],"type":"Point"}
}