{
  "type": "Feature",
  "properties": {
    "addr:full":"Schubertviertel 38 St. Valentin Nieder\u00f6sterreich 4300",
    "addr:housenumber":"38",
    "addr:postcode":"4300",
    "addr:street":"Schubertviertel",
    "iso:country":"AT",
    "sg:address":"Schubertviertel 38",
    "sg:city":"St. Valentin",
    "sg:orig_category":"Steuerberatung",
    "sg:phone":"+43 4374 3552294",
    "sg:postcode":"4300",
    "sg:province":"Nieder\u00f6sterreich",
    "wof:name":"Traunsteiner Wirtschafts- u SteuerberatungsgmbH",
    "wof:placetype":"venue"
},
  "geometry": {"coordinates":[14.526889801,48.1722984314],"type":"Point"}
}