{
  "type": "Feature",
  "properties": {
    "addr:full":"Garteng 10 Bad Fischau Nieder\u00f6sterreich 2721",
    "addr:housenumber":"10",
    "addr:postcode":"2721",
    "addr:street":"Garteng",
    "iso:country":"AT",
    "sg:address":"Garteng 10",
    "sg:city":"Bad Fischau",
    "sg:orig_category":"Finanz- U Wirtschaftsberatung",
    "sg:phone":"+43 4326 3920045",
    "sg:postcode":"2721",
    "sg:province":"Nieder\u00f6sterreich",
    "wof:name":"Allgemeine Finanzberatung Gerhardus OEG",
    "wof:placetype":"venue"
},
  "geometry": {"coordinates":[16.1669158936,47.8277206421],"type":"Point"}
}