{
  "type": "Feature",
  "properties": {
    "addr:full":"Nr 46 Stein an der Enns Steiermark 8961",
    "addr:postcode":"8961",
    "addr:street":"Nr 46",
    "iso:country":"AT",
    "sg:address":"Nr 46",
    "sg:city":"Stein an der Enns",
    "sg:orig_category":"Banken U Sparkassen",
    "sg:phone":"+43 4336 8522263",
    "sg:postcode":"8961",
    "sg:province":"Steiermark",
    "wof:name":"Bankomat d Raiffeisenbank Stein an der Enns",
    "wof:placetype":"venue"
},
  "geometry": {"coordinates":[13.9389886856,47.3949966431],"type":"Point"}
}