{
  "type": "Feature",
  "properties": {
    "addr:full":"Schindlerg 28 Wien Wien 1180",
    "addr:housenumber":"28",
    "addr:postcode":"1180",
    "addr:street":"Schindlerg",
    "iso:country":"AT",
    "sg:address":"Schindlerg 28",
    "sg:city":"Wien",
    "sg:orig_category":"Werbeagenturen",
    "sg:phone":"+43 1 5338880",
    "sg:postcode":"1180",
    "sg:province":"Wien",
    "wof:name":"Herzog's Werbeagentur GmbH",
    "wof:placetype":"venue"
},
  "geometry": {"coordinates":[16.3253307343,48.2303390503],"type":"Point"}
}