{
  "type": "Feature",
  "properties": {
    "addr:full":"Lerchenfelder Str 6a Neumarkt am Wallersee Salzburg 5202",
    "addr:housenumber":"6a",
    "addr:postcode":"5202",
    "addr:street":"Lerchenfelder Str;Salzburg",
    "iso:country":"AT",
    "sg:address":"Lerchenfelder Str 6a",
    "sg:city":"Neumarkt am Wallersee",
    "sg:orig_category":"Maler, Anstreicher U Lackierer",
    "sg:phone":"+43 4362 167229",
    "sg:postcode":"5202",
    "sg:province":"Salzburg",
    "wof:name":"Kravanja Hubert Malermeister",
    "wof:placetype":"venue"
},
  "geometry": {"coordinates":[13.2282543182,47.9495582581],"type":"Point"}
}