{
  "type": "Feature",
  "properties": {
    "addr:full":"Nr 334 Reichraming Ober\u00f6sterreich 4462",
    "addr:postcode":"4462",
    "addr:street":"Nr 334",
    "iso:country":"AT",
    "sg:address":"Nr 334",
    "sg:city":"Reichraming",
    "sg:orig_category":"Holzhandel",
    "sg:phone":"+43 664 3112685",
    "sg:postcode":"4462",
    "sg:province":"Ober\u00f6sterreich",
    "wof:name":"Haider Walter",
    "wof:placetype":"venue"
},
  "geometry": {"coordinates":[14.4618120193,47.8909645081],"type":"Point"}
}