{
  "type": "Feature",
  "properties": {
    "addr:full":"Nr 7 Steinbach am Attersee Ober\u00f6sterreich 4853",
    "addr:postcode":"4853",
    "addr:street":"Nr",
    "iso:country":"AT",
    "sg:address":"Nr 7",
    "sg:city":"Steinbach am Attersee",
    "sg:orig_category":"Volksschulen",
    "sg:phone":"+43 4376 63329",
    "sg:postcode":"4853",
    "sg:province":"Ober\u00f6sterreich",
    "wof:name":"Volksschule",
    "wof:placetype":"venue"
},
  "geometry": {"coordinates":[13.5459318161,47.8310089111],"type":"Point"}
}