{
  "type": "Feature",
  "properties": {
    "addr:full":"Breite G 8 Illmitz Burgenland 7142",
    "addr:housenumber":"8",
    "addr:postcode":"7142",
    "addr:street":"Breite G",
    "iso:country":"AT",
    "sg:address":"Breite G 8",
    "sg:city":"Illmitz",
    "sg:orig_category":"Bauunternehmen",
    "sg:phone":"+43 4366 42341729",
    "sg:postcode":"7142",
    "sg:province":"Burgenland",
    "wof:name":"Bauservice GmbH",
    "wof:placetype":"venue"
},
  "geometry": {"coordinates":[16.8047523499,47.7627334595],"type":"Point"}
}