{
  "type": "Feature",
  "properties": {
    "iso:country":"AT",
    "sg:address":"Industriestr 17",
    "sg:city":"Haid",
    "sg:orig_category":"Offsetdruckereien",
    "sg:phone":"+43 7229 882760",
    "sg:postcode":"4053",
    "sg:province":"Ober\u00f6sterreich",
    "wof:name":"Orbis Druckerei- und Verlags GesmbH",
    "wof:placetype":"venue"
},
  "geometry": {"coordinates":[14.2602996826,48.2097244263],"type":"Point"}
}