{
  "type": "Feature",
  "properties": {
    "addr:full":"Im Pyrach 26 Steyr Ober\u00f6sterreich 4400",
    "addr:housenumber":"26",
    "addr:postcode":"4400",
    "addr:street":"Im Pyrach;Oberoesterreich",
    "iso:country":"AT",
    "sg:address":"Im Pyrach 26",
    "sg:city":"Steyr",
    "sg:orig_category":"Psychologen",
    "sg:phone":"+43 7252 5150012",
    "sg:postcode":"4400",
    "sg:province":"Ober\u00f6sterreich",
    "wof:name":"Psychologische Praxis Hausjell Siegfried Mag",
    "wof:placetype":"venue"
},
  "geometry": {"coordinates":[14.4118242264,48.0264091492],"type":"Point"}
}