{
  "type": "Feature",
  "properties": {
    "iso:country":"AT",
    "sg:address":"Praterstr 43",
    "sg:city":"Wien",
    "sg:orig_category":"Elektroinstallationsunternehmen",
    "sg:phone":"+43 1 2169880",
    "sg:postcode":"1020",
    "sg:province":"Wien",
    "wof:name":"Wolf Peter",
    "wof:placetype":"venue"
},
  "geometry": {"coordinates":[16.3857917786,48.2156906128],"type":"Point"}
}