{
  "type": "Feature",
  "properties": {
    "addr:full":"Hauptstr 14 Trofaiach Steiermark 8793",
    "addr:housenumber":"14",
    "addr:postcode":"8793",
    "addr:street":"Hauptstr",
    "iso:country":"AT",
    "sg:address":"Hauptstr 14",
    "sg:city":"Trofaiach",
    "sg:orig_category":"Maler, Anstreicher U Lackierer",
    "sg:phone":"+43 4338 4738454",
    "sg:postcode":"8793",
    "sg:province":"Steiermark",
    "wof:name":"Malerbetrieb Mayer Peter",
    "wof:placetype":"venue"
},
  "geometry": {"coordinates":[15.0142402649,47.4208145142],"type":"Point"}
}