{
  "type": "Feature",
  "properties": {
    "iso:country":"AT",
    "sg:address":"Marktpl 2",
    "sg:city":"Gallneukirchen",
    "sg:orig_category":"Eisenwaren",
    "sg:phone":"+43 7235 62333",
    "sg:postcode":"4210",
    "sg:province":"Ober\u00f6sterreich",
    "wof:name":"Tanzer Helga",
    "wof:placetype":"venue"
},
  "geometry": {"coordinates":[14.4159469604,48.3528175354],"type":"Point"}
}