{
  "type": "Feature",
  "properties": {
    "iso:country":"AT",
    "sg:address":"Robinigstr 26a",
    "sg:city":"Salzburg",
    "sg:orig_category":"Waagen / Reparatur U Service",
    "sg:phone":"+43 662 8750510",
    "sg:postcode":"5020",
    "sg:province":"Salzburg",
    "wof:name":"Gassner Wiege & Me\u00dftechnik GesmbH",
    "wof:placetype":"venue"
},
  "geometry": {"coordinates":[13.0598201752,47.811164856],"type":"Point"}
}