{
  "type": "Feature",
  "properties": {
    "addr:full":"Hauptstr 64 Ulrichskirchen Nieder\u00f6sterreich 2122",
    "addr:housenumber":"64",
    "addr:postcode":"2122",
    "addr:street":"Hauptstr",
    "iso:country":"AT",
    "sg:address":"Hauptstr 64",
    "sg:city":"Ulrichskirchen",
    "sg:orig_category":"Non-Classified Establishments",
    "sg:phone":"+43 2245 5648",
    "sg:postcode":"2122",
    "sg:province":"Nieder\u00f6sterreich",
    "wof:name":"Hackl Josef",
    "wof:placetype":"venue"
},
  "geometry": {"coordinates":[100.3978805542,14.8663101196],"type":"Point"}
}