{
  "type": "Feature",
  "properties": {
    "addr:full":"Heid Werk-Str 4 Stockerau Nieder\u00f6sterreich 2000",
    "addr:housenumber":"4",
    "addr:postcode":"2000",
    "iso:country":"AT",
    "sg:address":"Heid Werk-Str 4",
    "sg:city":"Stockerau",
    "sg:orig_category":"Werbeagenturen",
    "sg:phone":"+43 2266 72173",
    "sg:postcode":"2000",
    "sg:province":"Nieder\u00f6sterreich",
    "wof:name":"Lasertext - Alfred Kn\u00f6ttner",
    "wof:placetype":"venue"
},
  "geometry": {"coordinates":[16.224773407,48.395450592],"type":"Point"}
}