{
  "type": "Feature",
  "properties": {
    "addr:full":"Nr 38 Waldstein Steiermark 8122",
    "addr:postcode":"8122",
    "addr:street":"Nr",
    "iso:country":"AT",
    "sg:address":"Nr 38",
    "sg:city":"Waldstein",
    "sg:orig_category":"Volksschulen",
    "sg:phone":"+43 4331 252680",
    "sg:postcode":"8122",
    "sg:province":"Steiermark",
    "wof:name":"Volksschule",
    "wof:placetype":"venue"
},
  "geometry": {"coordinates":[15.266037941,47.2401618958],"type":"Point"}
}