{
  "type": "Feature",
  "properties": {
    "iso:country":"AT",
    "sg:address":"M\u00f6ltschacher Weg 25a",
    "sg:city":"Villach",
    "sg:orig_category":"Fassaden",
    "sg:phone":"+43 4242 582650",
    "sg:postcode":"9500",
    "sg:province":"K\u00e4rnten",
    "wof:name":"WIS Trockenbau GmbH",
    "wof:placetype":"venue"
},
  "geometry": {"coordinates":[13.8232192993,46.6059494019],"type":"Point"}
}