{
  "type": "Feature",
  "properties": {
    "iso:country":"AT",
    "sg:address":"Schulpl 1",
    "sg:city":"S\u00f6ding",
    "sg:orig_category":"Volksschulen",
    "sg:phone":"+43 3137 613015",
    "sg:postcode":"8561",
    "sg:province":"Steiermark",
    "wof:name":"Volksschule Fridolin Rolke",
    "wof:placetype":"venue"
},
  "geometry": {"coordinates":[-83.2143249512,37.9002723694],"type":"Point"}
}