{
  "type": "Feature",
  "properties": {
    "addr:full":"Bahnstr 4 Pottendorf Nieder\u00f6sterreich 2486",
    "addr:housenumber":"4",
    "addr:postcode":"2486",
    "addr:street":"Bahnstr",
    "iso:country":"AT",
    "sg:address":"Bahnstr 4",
    "sg:city":"Pottendorf",
    "sg:orig_category":"Tabaktrafiken",
    "sg:phone":"+43 2623 73425",
    "sg:postcode":"2486",
    "sg:province":"Nieder\u00f6sterreich",
    "wof:name":"Tschida Renate",
    "wof:placetype":"venue"
},
  "geometry": {"coordinates":[16.3870849609,47.9086990356],"type":"Point"}
}