{
  "type": "Feature",
  "properties": {
    "addr:full":"Donaugasse 3 Zwentendorf an der Donau Nieder\u00f6sterreich 3435",
    "addr:housenumber":"3",
    "addr:postcode":"3435",
    "addr:street":"Donaugasse",
    "iso:country":"AT",
    "sg:address":"Donaugasse 3",
    "sg:city":"Zwentendorf an der Donau",
    "sg:classifiers":[
        {
            "category":"Structure",
            "subcategory":"Building",
            "type":"Public Place"
        }
    ],
    "sg:phone":"+43 2277 2229",
    "sg:postcode":"3435",
    "sg:province":"Nieder\u00f6sterreich",
    "sg:tags":[
        "apartment"
    ],
    "sg:website":"ruka.at",
    "wof:name":"RUKA-HOLZBAU GesmbH",
    "wof:placetype":"venue"
},
  "geometry": {"coordinates":[15.9228792191,48.3426322937],"type":"Point"}
}