{
  "type": "Feature",
  "properties": {
    "iso:country":"AT",
    "sg:address":"Kaiser-Franz-Ring 8",
    "sg:city":"Baden",
    "sg:orig_category":"Immobilienmakler",
    "sg:phone":"+43 4322 5242700",
    "sg:postcode":"2500",
    "sg:province":"Nieder\u00f6sterreich",
    "wof:name":"AURA Liegenschafts- u Objektverwertung GesmbH",
    "wof:placetype":"venue"
},
  "geometry": {"coordinates":[16.2330322266,48.0096740723],"type":"Point"}
}