{
  "type": "Feature",
  "properties": {
    "addr:full":"Seeweg 14 Neumarkt am Wallersee Salzburg 5202",
    "addr:housenumber":"14",
    "addr:postcode":"5202",
    "addr:street":"Seeweg;Salzburg",
    "iso:country":"AT",
    "sg:address":"Seeweg 14",
    "sg:city":"Neumarkt am Wallersee",
    "sg:orig_category":"Polytechnische Schulen",
    "sg:phone":"+43 4362 164403",
    "sg:postcode":"5202",
    "sg:province":"Salzburg",
    "wof:name":"Polytechnische Schule",
    "wof:placetype":"venue"
},
  "geometry": {"coordinates":[13.2213230133,47.9425697327],"type":"Point"}
}