{
  "type": "Feature",
  "properties": {
    "addr:full":"Hauptpl 8 Retz Nieder\u00f6sterreich 2070",
    "addr:housenumber":"8",
    "addr:postcode":"2070",
    "addr:street":"Hauptpl",
    "iso:country":"AT",
    "sg:address":"Hauptpl 8",
    "sg:city":"Retz",
    "sg:orig_category":"Physiotherapie",
    "sg:phone":"+43 4367 69185971",
    "sg:postcode":"2070",
    "sg:province":"Nieder\u00f6sterreich",
    "wof:name":"Heller Jutta Dipl-PT",
    "wof:placetype":"venue"
},
  "geometry": {"coordinates":[15.9521751404,48.7570457458],"type":"Point"}
}