{
  "type": "Feature",
  "properties": {
    "addr:full":"Nr 34 Neumarkt im M\u00fchlkreis Ober\u00f6sterreich 4212",
    "addr:postcode":"4212",
    "addr:street":"Nr 34",
    "iso:country":"AT",
    "sg:address":"Nr 34",
    "sg:city":"Neumarkt im M\u00fchlkreis",
    "sg:orig_category":"Feuerwehren",
    "sg:phone":"+43 7941 7025",
    "sg:postcode":"4212",
    "sg:province":"Ober\u00f6sterreich",
    "wof:name":"Freiwillige Feuerwehr Lamm",
    "wof:placetype":"venue"
},
  "geometry": {"coordinates":[14.4839353561,48.4275016785],"type":"Point"}
}