{
  "type": "Feature",
  "properties": {
    "addr:full":"Dovskyg 5 Wien Wien 1130",
    "addr:housenumber":"5",
    "addr:postcode":"1130",
    "addr:street":"Dovskyg",
    "iso:country":"AT",
    "sg:address":"Dovskyg 5",
    "sg:city":"Wien",
    "sg:orig_category":"Baumeister",
    "sg:phone":"+43 4318 0499010",
    "sg:postcode":"1130",
    "sg:province":"Wien",
    "wof:name":"Kern Gernot MAS - Stadtbaumeister",
    "wof:placetype":"venue"
},
  "geometry": {"coordinates":[16.292137146,48.1746711731],"type":"Point"}
}