{
  "type": "Feature",
  "properties": {
    "addr:full":"Vorwald 7 Patergassen K\u00e4rnten 9564",
    "addr:housenumber":"7",
    "addr:postcode":"9564",
    "addr:street":"Vorwald;Kaernten",
    "iso:country":"AT",
    "sg:address":"Vorwald 7",
    "sg:city":"Patergassen",
    "sg:orig_category":"Physiotherapie",
    "sg:phone":"+43 4342 752970",
    "sg:postcode":"9564",
    "sg:province":"K\u00e4rnten",
    "wof:name":"Hofmeister Birgit Dipl-PT",
    "wof:placetype":"venue"
},
  "geometry": {"coordinates":[13.8319253922,46.8631591797],"type":"Point"}
}