{
  "type": "Feature",
  "properties": {
    "addr:full":"Innrain 25 Innsbruck Tirol 6020",
    "addr:housenumber":"25",
    "addr:postcode":"6020",
    "addr:street":"Innrain;Tirol",
    "iso:country":"AT",
    "sg:address":"Innrain 25",
    "sg:city":"Innsbruck",
    "sg:classifiers":[
        {
            "category":"Retail",
            "subcategory":"Event Space",
            "type":"Services"
        }
    ],
    "sg:phone":"+43 512 582343",
    "sg:postcode":"6020",
    "sg:province":"Tirol",
    "sg:tags":[
        "hand-",
        "u",
        "fu\u00c3\u0178pflege"
    ],
    "wof:name":"Burgauner Franz",
    "wof:placetype":"venue"
},
  "geometry": {"coordinates":[11.3894109726,47.2656211853],"type":"Point"}
}