{
  "type": "Feature",
  "properties": {
    "iso:country":"AT",
    "sg:address":"Baumkircherstr 3",
    "sg:city":"Graz",
    "sg:orig_category":"Dichtungen",
    "sg:phone":"+43 316 711089",
    "sg:postcode":"8020",
    "sg:province":"Steiermark",
    "wof:name":"Polyflon HandelsgesmbH Dicht u- Me\u00dftechnik",
    "wof:placetype":"venue"
},
  "geometry": {"coordinates":[15.4203977585,47.072429657],"type":"Point"}
}