{
  "type": "Feature",
  "properties": {
    "iso:country":"AT",
    "sg:address":"Edlastr 6",
    "sg:city":"Weissenbach an der Triesting",
    "sg:orig_category":"Installationsunternehmen",
    "sg:phone":"+43 4326 74873720",
    "sg:postcode":"2564",
    "sg:province":"Nieder\u00f6sterreich",
    "wof:name":"Krenn Josef Ing GesmbH",
    "wof:placetype":"venue"
},
  "geometry": {"coordinates":[16.0328083038,47.98595047],"type":"Point"}
}