{
  "type": "Feature",
  "properties": {
    "iso:country":"AT",
    "sg:address":"Hauptpl 33",
    "sg:city":"Tulln an der Donau",
    "sg:orig_category":"Gesundheit / Allgemeine Informationsstellen",
    "sg:phone":"+43 2272 902539452",
    "sg:postcode":"3430",
    "sg:province":"Nieder\u00f6sterreich",
    "wof:name":"Gesundheitsamt - Amtsarzt",
    "wof:placetype":"venue"
},
  "geometry": {"coordinates":[16.0523777008,48.331237793],"type":"Point"}
}