{
  "type": "Feature",
  "properties": {
    "addr:full":"Gleisdorfer G 6 Graz Steiermark 8010",
    "addr:housenumber":"6",
    "addr:postcode":"8010",
    "addr:street":"Gleisdorfer G",
    "iso:country":"AT",
    "sg:address":"Gleisdorfer G 6",
    "sg:city":"Graz",
    "sg:orig_category":"Architekten",
    "sg:phone":"+43 316 813169",
    "sg:postcode":"8010",
    "sg:province":"Steiermark",
    "wof:name":"ortlos architects",
    "wof:placetype":"venue"
},
  "geometry": {"coordinates":[15.4447746277,47.0677909851],"type":"Point"}
}