{
  "type": "Feature",
  "properties": {
    "addr:full":"Am Sonnenhang 25 Reifnitz K\u00e4rnten 9081",
    "addr:housenumber":"25",
    "addr:postcode":"9081",
    "addr:street":"Am Sonnenhang;Kaernten",
    "iso:country":"AT",
    "sg:address":"Am Sonnenhang 25",
    "sg:city":"Reifnitz",
    "sg:classifiers":[
        {
            "category":"Travel",
            "subcategory":"Hotels & Motels",
            "type":"Entertainment"
        }
    ],
    "sg:phone":"+43 4273 24850",
    "sg:postcode":"9081",
    "sg:province":"K\u00e4rnten",
    "wof:name":"Hotel Haus am Wald",
    "wof:placetype":"venue"
},
  "geometry": {"coordinates":[14.1857004166,46.6044998169],"type":"Point"}
}