{
  "type": "Feature",
  "properties": {
    "iso:country":"AT",
    "sg:address":"Ennsfeldstr 11",
    "sg:city":"Linz",
    "sg:orig_category":"Tabaktrafiken",
    "sg:phone":"+43 732 317600",
    "sg:postcode":"4030",
    "sg:province":"Ober\u00f6sterreich",
    "wof:name":"T\u00e4ubel Manuela",
    "wof:placetype":"venue"
},
  "geometry": {"coordinates":[14.3379573822,48.2437286377],"type":"Point"}
}