{
  "type": "Feature",
  "properties": {
    "addr:full":"Bauernmarkt 1 Wien Wien 1010",
    "addr:housenumber":"1",
    "addr:postcode":"1010",
    "addr:street":"Bauernmarkt",
    "iso:country":"AT",
    "sg:address":"Bauernmarkt 1",
    "sg:city":"Wien",
    "sg:orig_category":"Boutiquen",
    "sg:phone":"+43 1 5335260",
    "sg:postcode":"1010",
    "sg:province":"Wien",
    "wof:name":"Mila HandelsgesmbH",
    "wof:placetype":"venue"
},
  "geometry": {"coordinates":[16.3709659576,48.2094078064],"type":"Point"}
}