{
  "type": "Feature",
  "properties": {
    "addr:full":"H\u00f6lzli 8a Ehrwald Tirol 6632",
    "addr:housenumber":"8a",
    "addr:postcode":"6632",
    "addr:street":"Hoelzli;Tirol",
    "iso:country":"AT",
    "sg:address":"H\u00f6lzli 8a",
    "sg:city":"Ehrwald",
    "sg:orig_category":"Appartements / Ferienwohnungen",
    "sg:phone":"+43 4356 733609",
    "sg:postcode":"6632",
    "sg:province":"Tirol",
    "wof:name":"Schmitz Markus",
    "wof:placetype":"venue"
},
  "geometry": {"coordinates":[10.923784256,47.3966903687],"type":"Point"}
}