{
  "type": "Feature",
  "properties": {
    "addr:full":"Nordbahnstr 36 Wien Wien 1020",
    "addr:housenumber":"36",
    "addr:postcode":"1020",
    "addr:street":"Nordbahnstr",
    "iso:country":"AT",
    "sg:address":"Nordbahnstr 36",
    "sg:city":"Wien",
    "sg:orig_category":"Chemikalien",
    "sg:phone":"+43 1 2186360",
    "sg:postcode":"1020",
    "sg:province":"Wien",
    "wof:name":"Baker Petrolite HandelsgesmbH",
    "wof:placetype":"venue"
},
  "geometry": {"coordinates":[16.3892269135,48.2228660583],"type":"Point"}
}