{
  "type": "Feature",
  "properties": {
    "addr:full":"Linzer Str 22 Schwanenstadt Ober\u00f6sterreich 4690",
    "addr:housenumber":"22",
    "addr:postcode":"4690",
    "addr:street":"Linzer Str",
    "iso:country":"AT",
    "sg:address":"Linzer Str 22",
    "sg:city":"Schwanenstadt",
    "sg:orig_category":"Tankstellen",
    "sg:phone":"+43 76736472",
    "sg:postcode":"4690",
    "sg:province":"Ober\u00f6sterreich",
    "wof:name":"OMV AG - Ottokar Kreuzer",
    "wof:placetype":"venue"
},
  "geometry": {"coordinates":[13.7803869247,48.0576820374],"type":"Point"}
}