{
  "type": "Feature",
  "properties": {
    "iso:country":"AT",
    "sg:address":"Sensenwerkgasse 4d",
    "sg:city":"Judenburg",
    "sg:classifiers":[
        {
            "category":"Home & Garden",
            "subcategory":"Building Materials",
            "type":"Retail Goods"
        }
    ],
    "sg:phone":"+43 3572 83282",
    "sg:postcode":"8750",
    "sg:province":"Steiermark",
    "sg:tags":[
        "aluminium",
        "gutter"
    ],
    "wof:name":"Roland Schilcher",
    "wof:placetype":"venue"
},
  "geometry": {"coordinates":[14.6677036285,47.1709976196],"type":"Point"}
}