{
  "type": "Feature",
  "properties": {
    "addr:full":"Invalidenstr 10 Wien Wien 1030",
    "addr:housenumber":"10",
    "addr:postcode":"1030",
    "addr:street":"Invalidenstr",
    "iso:country":"AT",
    "sg:address":"Invalidenstr 10",
    "sg:city":"Wien",
    "sg:orig_category":"Garagen Parkgaragen",
    "sg:phone":"+43 1 7139402",
    "sg:postcode":"1030",
    "sg:province":"Wien",
    "wof:name":"Wipark Garagen AG",
    "wof:placetype":"venue"
},
  "geometry": {"coordinates":[16.3845252991,48.2046318054],"type":"Point"}
}