{
  "type": "Feature",
  "properties": {
    "addr:full":"Rudolfspl 2/17 Wien Wien 1010",
    "addr:housenumber":"2 / 17",
    "addr:postcode":"1010",
    "addr:street":"Rudolfspl",
    "iso:country":"AT",
    "sg:address":"Rudolfspl 2/17",
    "sg:city":"Wien",
    "sg:orig_category":"Immobilienmakler",
    "sg:phone":"+43 1 5333080",
    "sg:postcode":"1010",
    "sg:province":"Wien",
    "wof:name":"Besitztum Immobilien GesmbH",
    "wof:placetype":"venue"
},
  "geometry": {"coordinates":[16.3714504242,48.2147941589],"type":"Point"}
}