{
  "type": "Feature",
  "properties": {
    "addr:full":"Vogelweiderstr. 44a  Salzburg Salzburg 5020",
    "addr:housenumber":"44a",
    "addr:postcode":"5020",
    "addr:street":"Vogelweiderstr.;Salzburg",
    "iso:country":"AT",
    "sg:address":"Vogelweiderstr. 44a ",
    "sg:city":"Salzburg",
    "sg:classifiers":[
        {
            "category":"Food & Beverages",
            "subcategory":"Groceries & Convenience Stores",
            "type":"Retail Goods"
        }
    ],
    "sg:phone":"+43 4366 28830210",
    "sg:postcode":"5020",
    "sg:province":"Salzburg",
    "sg:tags":[
        "drink"
    ],
    "wof:name":"HENKELL & S\u00d6HNLEIN KG",
    "wof:placetype":"venue"
},
  "geometry": {"coordinates":[13.0544376373,47.812461853],"type":"Point"}
}