{
  "type": "Feature",
  "properties": {
    "addr:full":"Nr 5 Unterlamm Steiermark 8352",
    "addr:postcode":"8352",
    "addr:street":"Nr;Unterlamm",
    "iso:country":"AT",
    "sg:address":"Nr 5",
    "sg:city":"Unterlamm",
    "sg:orig_category":"Volksschulen",
    "sg:phone":"+43 4331 558218",
    "sg:postcode":"8352",
    "sg:province":"Steiermark",
    "wof:name":"Volksschule",
    "wof:placetype":"venue"
},
  "geometry": {"coordinates":[16.0573005676,46.9795761108],"type":"Point"}
}