{
  "type": "Feature",
  "properties": {
    "iso:country":"AT",
    "sg:address":"Unterpinswang 75",
    "sg:city":"Reutte",
    "sg:orig_category":"Beton- U Betonsteinwerke",
    "sg:phone":"+43 4356 7720147",
    "sg:postcode":"6600",
    "sg:province":"Tirol",
    "wof:name":"Asphalt u Beton GmbH Nfg OHG Betonmischanlage",
    "wof:placetype":"venue"
},
  "geometry": {"coordinates":[10.6667900085,47.5451202393],"type":"Point"}
}