{
  "type": "Feature",
  "properties": {
    "iso:country":"AT",
    "sg:address":"Schl\u00f6\u00dfleweg 1",
    "sg:city":"M\u00e4der",
    "sg:orig_category":"Waren Aller Art",
    "sg:phone":"+43 5523 6479217",
    "sg:postcode":"6841",
    "sg:province":"Vorarlberg",
    "wof:name":"Weltladen",
    "wof:placetype":"venue"
},
  "geometry": {"coordinates":[-92.94867706300001,31.5349597931],"type":"Point"}
}