{
  "type": "Feature",
  "properties": {
    "iso:country":"AT",
    "sg:address":"Hartmanng 1",
    "sg:city":"Wien",
    "sg:orig_category":"Sporthallen",
    "sg:phone":"+43 1 5440000",
    "sg:postcode":"1050",
    "sg:province":"Wien",
    "wof:name":"Tischtennishalle Margareten",
    "wof:placetype":"venue"
},
  "geometry": {"coordinates":[16.3639392853,48.1876678467],"type":"Point"}
}