{
  "type": "Feature",
  "properties": {
    "addr:full":"Wiener Str 13-15 Oberwart Burgenland 7400",
    "addr:housenumber":"13-15",
    "addr:postcode":"7400",
    "iso:country":"AT",
    "sg:address":"Wiener Str 13-15",
    "sg:city":"Oberwart",
    "sg:orig_category":"Lebensmittel / Einzelhandel",
    "sg:phone":"+43 3352 38432",
    "sg:postcode":"7400",
    "sg:province":"Burgenland",
    "wof:name":"SPAR \u00f6sterreichische Warenhandels-AG",
    "wof:placetype":"venue"
},
  "geometry": {"coordinates":[16.2092113495,47.2895393372],"type":"Point"}
}