{
  "type": "Feature",
  "properties": {
    "iso:country":"AT",
    "sg:address":"Schulstrasse 74/5",
    "sg:city":"Uttendorf",
    "sg:classifiers":[
        {
            "category":"Military Area",
            "subcategory":"Air Force Base",
            "type":"Public Place"
        }
    ],
    "sg:phone":"+43 7724 3233",
    "sg:postcode":"5261",
    "sg:province":"Ober\u00f6sterreich",
    "sg:tags":[
        "attic",
        "stair"
    ],
    "wof:name":"Christian Reisinger",
    "wof:placetype":"venue"
},
  "geometry": {"coordinates":[13.1229696274,48.1637763977],"type":"Point"}
}