{
  "type": "Feature",
  "properties": {
    "addr:full":"Feldkirchner Str 12 Stra\u00dfgang Steiermark 8054",
    "addr:housenumber":"12",
    "addr:postcode":"8054",
    "addr:street":"Str",
    "iso:country":"AT",
    "sg:address":"Feldkirchner Str 12",
    "sg:city":"Stra\u00dfgang",
    "sg:orig_category":"Fahrzeugbau",
    "sg:phone":"+43 316 281569",
    "sg:postcode":"8054",
    "sg:province":"Steiermark",
    "wof:name":"Schemitsch Josef Fahrzeugbau GesmbH",
    "wof:placetype":"venue"
},
  "geometry": {"coordinates":[15.4022321701,47.0099945068],"type":"Point"}
}