{
  "type": "Feature",
  "properties": {
    "iso:country":"AT",
    "sg:address":"Ohlsdorfer Str 1",
    "sg:city":"Gmunden",
    "sg:orig_category":"Pensionen / Privatzimmer",
    "sg:phone":"+43 761263222",
    "sg:postcode":"4810",
    "sg:province":"Ober\u00f6sterreich",
    "wof:name":"Pension Egger Fam Lobing",
    "wof:placetype":"venue"
},
  "geometry": {"coordinates":[13.795715332,47.9287414551],"type":"Point"}
}