{
  "type": "Feature",
  "properties": {
    "addr:full":"Brachsenweg 20 Linz Ober\u00f6sterreich 4030",
    "addr:housenumber":"20",
    "addr:postcode":"4030",
    "addr:street":"Brachsenweg",
    "iso:country":"AT",
    "sg:address":"Brachsenweg 20",
    "sg:city":"Linz",
    "sg:orig_category":"Baumaschinenverleih",
    "sg:phone":"+43 732 320932",
    "sg:postcode":"4030",
    "sg:province":"Ober\u00f6sterreich",
    "wof:name":"Stark OEG",
    "wof:placetype":"venue"
},
  "geometry": {"coordinates":[14.3502693176,48.2536735535],"type":"Point"}
}