{
  "type": "Feature",
  "properties": {
    "iso:country":"AT",
    "sg:address":"Maxglaner Hauptstr 31",
    "sg:city":"Salzburg",
    "sg:orig_category":"Blumeneinzelhandel",
    "sg:phone":"+43 662 827421",
    "sg:postcode":"5020",
    "sg:province":"Salzburg",
    "wof:name":"Daringer Margit",
    "wof:placetype":"venue"
},
  "geometry": {"coordinates":[13.021900177,47.7973327637],"type":"Point"}
}