{
  "type": "Feature",
  "properties": {
    "addr:full":"Dauphinestr 17 Linz Ober\u00f6sterreich 4030",
    "addr:housenumber":"17",
    "addr:postcode":"4030",
    "addr:street":"Dauphinestr",
    "iso:country":"AT",
    "sg:address":"Dauphinestr 17",
    "sg:city":"Linz",
    "sg:orig_category":"Tabaktrafiken",
    "sg:phone":"+43 732 304067",
    "sg:postcode":"4030",
    "sg:province":"Ober\u00f6sterreich",
    "wof:name":"Springer Margarete",
    "wof:placetype":"venue"
},
  "geometry": {"coordinates":[14.3135738373,48.2528266907],"type":"Point"}
}