{
  "type": "Feature",
  "properties": {
    "addr:full":"An der Viehhoferin 16 Pressbaum Nieder\u00f6sterreich 3021",
    "addr:housenumber":"16",
    "addr:postcode":"3021",
    "addr:street":"An Der Viehhoferin;Niederoesterreich",
    "iso:country":"AT",
    "sg:address":"An der Viehhoferin 16",
    "sg:city":"Pressbaum",
    "sg:orig_category":"Sonnenstudios",
    "sg:phone":"+43 2233 55631",
    "sg:postcode":"3021",
    "sg:province":"Nieder\u00f6sterreich",
    "wof:name":"Beauty-Salon Sandra",
    "wof:placetype":"venue"
},
  "geometry": {"coordinates":[16.0678405762,48.1812705994],"type":"Point"}
}