{
  "type": "Feature",
  "properties": {
    "iso:country":"AT",
    "sg:address":"Gruberfeldstr 41",
    "sg:city":"Gnigl",
    "sg:classifiers":[
        {
            "category":"Shopping",
            "subcategory":"Gifts & Souvenirs",
            "type":"Retail Goods"
        }
    ],
    "sg:phone":"+43 662 640035",
    "sg:postcode":"5023",
    "sg:province":"Salzburg",
    "wof:name":"Girst Dieter",
    "wof:placetype":"venue"
},
  "geometry": {"coordinates":[13.1085100174,47.8237304688],"type":"Point"}
}