{
  "type": "Feature",
  "properties": {
    "addr:full":"Graben 21b Linz Ober\u00f6sterreich 4020",
    "addr:housenumber":"21b",
    "addr:postcode":"4020",
    "addr:street":"Graben",
    "iso:country":"AT",
    "sg:address":"Graben 21b",
    "sg:city":"Linz",
    "sg:orig_category":"Bastelbedarf",
    "sg:phone":"+43 732 783253",
    "sg:postcode":"4020",
    "sg:province":"Ober\u00f6sterreich",
    "wof:name":"Bastelparadies Haslberger-Freund",
    "wof:placetype":"venue"
},
  "geometry": {"coordinates":[14.2893457413,48.3047599792],"type":"Point"}
}