{
  "type": "Feature",
  "properties": {
    "addr:full":"Walfischgasse 14 Wien Wien 1010",
    "addr:housenumber":"14",
    "addr:postcode":"1010",
    "addr:street":"Walfischgasse",
    "iso:country":"AT",
    "sg:address":"Walfischgasse 14",
    "sg:city":"Wien",
    "sg:orig_category":"Dvd Films",
    "sg:phone":"+43 1 5129844",
    "sg:postcode":"1010",
    "sg:province":"Wien",
    "wof:name":"EAI Film-, Produktions- Beratungs- und Verlagsges.m.b.H.",
    "wof:placetype":"venue"
},
  "geometry": {"coordinates":[16.3731384277,48.2028236389],"type":"Point"}
}