{
  "type": "Feature",
  "properties": {
    "iso:country":"AT",
    "sg:address":"Nr 258",
    "sg:city":"Kitzb\u00fchel",
    "sg:classifiers":[
        {
            "category":"Travel",
            "subcategory":"Hotels & Motels",
            "type":"Entertainment"
        }
    ],
    "sg:phone":"+43 4353 56652420",
    "sg:postcode":"6370",
    "sg:province":"Tirol",
    "wof:name":"Gesundheits- Bio u Nichtraucherhotel Florian",
    "wof:placetype":"venue"
},
  "geometry": {"coordinates":[106.0698394775,30.7620105743],"type":"Point"}
}