{
  "type": "Feature",
  "properties": {
    "addr:full":"Hauptpl 8-9 Neunkirchen Nieder\u00f6sterreich 2620",
    "addr:housenumber":"8-9",
    "addr:postcode":"2620",
    "addr:street":"Hauptpl",
    "iso:country":"AT",
    "sg:address":"Hauptpl 8-9",
    "sg:city":"Neunkirchen",
    "sg:orig_category":"Fotoapparate U -Artikel / Einzelhandel",
    "sg:phone":"+43 4326 3562131",
    "sg:postcode":"2620",
    "sg:province":"Nieder\u00f6sterreich",
    "wof:name":"Niedermeyer GmbH",
    "wof:placetype":"venue"
},
  "geometry": {"coordinates":[16.0805091858,47.7212333679],"type":"Point"}
}