{
  "type": "Feature",
  "properties": {
    "addr:full":"Pirching 1 Heiligenkreuz am Waasen Steiermark 8081",
    "addr:housenumber":"1",
    "addr:postcode":"8081",
    "addr:street":"Pirching",
    "iso:country":"AT",
    "sg:address":"Pirching 1",
    "sg:city":"Heiligenkreuz am Waasen",
    "sg:classifiers":[
        {
            "category":"Bars & Pubs",
            "subcategory":"Nightclub",
            "type":"Food & Drink"
        }
    ],
    "sg:phone":"+43 4331 342207",
    "sg:postcode":"8081",
    "sg:province":"Steiermark",
    "sg:tags":[
        "cake",
        "bread"
    ],
    "wof:name":"FERDINAND TESCHL GESMBH",
    "wof:placetype":"venue"
},
  "geometry": {"coordinates":[15.5885505676,46.9553413391],"type":"Point"}
}