{
  "type": "Feature",
  "properties": {
    "addr:full":"Lainzer Str 131 Wien Wien 1130",
    "addr:housenumber":"131",
    "addr:postcode":"1130",
    "iso:country":"AT",
    "sg:address":"Lainzer Str 131",
    "sg:city":"Wien",
    "sg:orig_category":"Boutiquen",
    "sg:phone":"+43 1 8041796",
    "sg:postcode":"1130",
    "sg:province":"Wien",
    "wof:name":"TRUSSARDI",
    "wof:placetype":"venue"
},
  "geometry": {"coordinates":[16.2841129303,48.1776885986],"type":"Point"}
}