{
  "type": "Feature",
  "properties": {
    "addr:full":"Rauterpl 3 Matrei in Osttirol Tirol 9971",
    "addr:housenumber":"3",
    "addr:postcode":"9971",
    "addr:street":"Rauterpl;Tirol",
    "iso:country":"AT",
    "sg:address":"Rauterpl 3",
    "sg:city":"Matrei in Osttirol",
    "sg:classifiers":[
        {
            "category":"Travel",
            "subcategory":"Hotels & Motels",
            "type":"Entertainment"
        }
    ],
    "sg:phone":"+43 4348 756611",
    "sg:postcode":"9971",
    "sg:province":"Tirol",
    "wof:name":"Hotel-Pension Rauter",
    "wof:placetype":"venue"
},
  "geometry": {"coordinates":[12.5387115479,47.0014572144],"type":"Point"}
}