{
  "type": "Feature",
  "properties": {
    "iso:country":"AT",
    "sg:address":"Obere Augartenstr 18a/Stg 4/T\u00fcr 22",
    "sg:city":"Wien",
    "sg:orig_category":"Psychotherapie",
    "sg:phone":"+43 1 3107371",
    "sg:postcode":"1020",
    "sg:province":"Wien",
    "wof:name":"Blach Gabriele Mag",
    "wof:placetype":"venue"
},
  "geometry": {"coordinates":[16.3802642822,48.2153701782],"type":"Point"}
}