{
  "type": "Feature",
  "properties": {
    "addr:full":"VOEST-ALPINE-Str 7 BG 45 Linz Ober\u00f6sterreich 4020",
    "addr:housenumber":"7 bg 45",
    "addr:postcode":"4020",
    "addr:street":"Voest-Alpine-Str",
    "iso:country":"AT",
    "sg:address":"VOEST-ALPINE-Str 7 BG 45",
    "sg:city":"Linz",
    "sg:orig_category":"Datenverarbeitung",
    "sg:phone":"+43 4373 269874131",
    "sg:postcode":"4020",
    "sg:province":"Ober\u00f6sterreich",
    "sg:website":"vai.at",
    "wof:name":"AIS Advanced Information Services GmbH & Co",
    "wof:placetype":"venue"
},
  "geometry": {"coordinates":[14.3003749847,48.3187637329],"type":"Point"}
}