{
  "type": "Feature",
  "properties": {
    "addr:full":"L\u00e4rcheng 10 Ternitz Nieder\u00f6sterreich 2630",
    "addr:housenumber":"10",
    "addr:postcode":"2630",
    "addr:street":"Laercheng",
    "iso:country":"AT",
    "sg:address":"L\u00e4rcheng 10",
    "sg:city":"Ternitz",
    "sg:orig_category":"Baumeister",
    "sg:phone":"+43 2630 386500",
    "sg:postcode":"2630",
    "sg:province":"Nieder\u00f6sterreich",
    "wof:name":"Berl-Bau GesmbH",
    "wof:placetype":"venue"
},
  "geometry": {"coordinates":[16.0530948639,47.7123374939],"type":"Point"}
}