{
  "type": "Feature",
  "properties": {
    "iso:country":"AT",
    "sg:address":"Dornbacher Str 65",
    "sg:city":"Wien",
    "sg:classifiers":[
        {
            "category":"Organizations",
            "subcategory":"Community Association",
            "type":"Services"
        }
    ],
    "sg:phone":"+43 4312 310132",
    "sg:postcode":"1170",
    "sg:province":"Wien",
    "sg:tags":[
        "relation",
        "public"
    ],
    "wof:name":"CommuniCom",
    "wof:placetype":"venue"
},
  "geometry": {"coordinates":[16.2968044281,48.2290916443],"type":"Point"}
}