{
  "type": "Feature",
  "properties": {
    "addr:full":"Ottakringer Str 101 Wien Wien 1160",
    "addr:housenumber":"101",
    "addr:postcode":"1160",
    "iso:country":"AT",
    "sg:address":"Ottakringer Str 101",
    "sg:city":"Wien",
    "sg:orig_category":"Metallwaren / Erzeugung U Gro\u00c3\u0178handel",
    "sg:phone":"+43 4314 862420",
    "sg:postcode":"1160",
    "sg:province":"Wien",
    "sg:website":"metallprofile.at",
    "wof:name":"Mayer-Hautmann",
    "wof:placetype":"venue"
},
  "geometry": {"coordinates":[16.3213710785,48.2133712769],"type":"Point"}
}