{
  "type": "Feature",
  "properties": {
    "addr:full":"Philipsstr. 27  Lebring Steiermark 8403",
    "addr:housenumber":"27",
    "addr:postcode":"8403",
    "addr:street":"Philipsstr.",
    "iso:country":"AT",
    "sg:address":"Philipsstr. 27 ",
    "sg:city":"Lebring",
    "sg:classifiers":[
        {
            "category":"Professional",
            "subcategory":"Computer Services",
            "type":"Services"
        }
    ],
    "sg:phone":"+43 4331 8272510",
    "sg:postcode":"8403",
    "sg:province":"Steiermark",
    "sg:tags":[
        "information",
        "technology"
    ],
    "wof:name":"LG. PHILIPS DISPLAYS AUSTRIA GMBH",
    "wof:placetype":"venue"
},
  "geometry": {"coordinates":[15.5333652496,46.84765625],"type":"Point"}
}