{
  "type": "Feature",
  "properties": {
    "addr:full":"Hauptstr 5 Admont Steiermark 8911",
    "addr:housenumber":"5",
    "addr:postcode":"8911",
    "addr:street":"Hauptstr",
    "iso:country":"AT",
    "sg:address":"Hauptstr 5",
    "sg:city":"Admont",
    "sg:orig_category":"Marketingberatung",
    "sg:phone":"+43 3613 20015",
    "sg:postcode":"8911",
    "sg:province":"Steiermark",
    "wof:name":"M\u00fcnch J\u00fcrgen - Marketing & Vertriebsagentur",
    "wof:placetype":"venue"
},
  "geometry": {"coordinates":[14.4607601166,47.5766487122],"type":"Point"}
}