{
  "type": "Feature",
  "properties": {
    "addr:full":"Jaxstrasse 2-4 Linz Ober\u00f6sterreich 4020",
    "addr:housenumber":"2-4",
    "addr:postcode":"4020",
    "addr:street":"Jaxstrasse",
    "iso:country":"AT",
    "sg:address":"Jaxstrasse 2-4",
    "sg:city":"Linz",
    "sg:classifiers":[
        {
            "category":"Professional",
            "subcategory":"Advertising",
            "type":"Services"
        }
    ],
    "sg:phone":"+43 732 6050380",
    "sg:postcode":"4020",
    "sg:province":"Ober\u00f6sterreich",
    "sg:tags":[
        "agency"
    ],
    "sg:website":"sps-marketing.com",
    "wof:name":"SCHRANGL PRESLMAYER SCHAURHOFER Marketing GmbH",
    "wof:placetype":"venue"
},
  "geometry": {"coordinates":[14.3101100922,48.2894935608],"type":"Point"}
}