{
  "type": "Feature",
  "properties": {
    "addr:full":"K\u00e4rntner Str 341 Neuhart Steiermark 8053",
    "addr:housenumber":"341",
    "addr:postcode":"neuhart;8053",
    "addr:street":"Str",
    "iso:country":"AT",
    "sg:address":"K\u00e4rntner Str 341",
    "sg:city":"Neuhart",
    "sg:orig_category":"Me\u00c3\u0178-, Steuer- U Regeltechnik",
    "sg:phone":"+43 316 2834340",
    "sg:postcode":"8053",
    "sg:province":"Steiermark",
    "wof:name":"Schrack Energietechnik GmbH",
    "wof:placetype":"venue"
},
  "geometry": {"coordinates":[15.3952732086,47.0450782776],"type":"Point"}
}