{
  "type": "Feature",
  "properties": {
    "iso:country":"AT",
    "sg:address":"Haggenm\u00fcllerg 8",
    "sg:city":"Wiener Neustadt",
    "sg:orig_category":"Baumeister",
    "sg:phone":"+43 2622 236020",
    "sg:postcode":"2700",
    "sg:province":"Nieder\u00f6sterreich",
    "wof:name":"Ebner Michael Ing Bmstr Planungs GmbH",
    "wof:placetype":"venue"
},
  "geometry": {"coordinates":[16.2455158234,47.8128814697],"type":"Point"}
}