{
  "type": "Feature",
  "properties": {
    "addr:full":"Korneuburg Nieder\u00f6sterreich 2100",
    "addr:postcode":"2100",
    "addr:street":"Niederoesterreich",
    "iso:country":"AT",
    "sg:city":"Korneuburg",
    "sg:classifiers":[
        {
            "category":"Structure",
            "subcategory":"Bridge",
            "type":"Public Place"
        }
    ],
    "sg:phone":"+43 2262 66784",
    "sg:postcode":"2100",
    "sg:province":"Nieder\u00f6sterreich",
    "sg:tags":[
        "construction"
    ],
    "wof:name":"Reinhart Eisler Ges.m.b.H.",
    "wof:placetype":"venue"
},
  "geometry": {"coordinates":[16.3230648041,48.3774147034],"type":"Point"}
}