{
  "type": "Feature",
  "properties": {
    "iso:country":"AT",
    "sg:address":"Feuringweg 36",
    "sg:city":"Brixen im Thale",
    "sg:classifiers":[
        {
            "category":"Restaurant",
            "type":"Food & Drink"
        }
    ],
    "sg:phone":"+43 5334 8381",
    "sg:postcode":"6364",
    "sg:province":"Tirol",
    "wof:name":"Loipenstub'n",
    "wof:placetype":"venue"
},
  "geometry": {"coordinates":[12.2673711777,47.4465179443],"type":"Point"}
}