{
  "type": "Feature",
  "properties": {
    "iso:country":"AT",
    "sg:address":"Freimoosstrasse 1",
    "sg:city":"Neumarkt in Steiermark",
    "sg:classifiers":[
        {
            "category":"Building & Trades",
            "subcategory":"Plumbing",
            "type":"Services"
        }
    ],
    "sg:phone":"+43 3584 2134",
    "sg:postcode":"8820",
    "sg:province":"Steiermark",
    "sg:tags":[
        "supraregional",
        "gas"
    ],
    "sg:website":"griedl.at",
    "wof:name":"gas-wasser-heizung Klaus Griedl",
    "wof:placetype":"venue"
},
  "geometry": {"coordinates":[14.434176445,47.0689888],"type":"Point"}
}