{
  "type": "Feature",
  "properties": {
    "addr:full":"Linzer Str 28 Enns Ober\u00f6sterreich 4470",
    "addr:housenumber":"28",
    "addr:postcode":"4470",
    "addr:street":"Linzer Str",
    "iso:country":"AT",
    "sg:address":"Linzer Str 28",
    "sg:city":"Enns",
    "sg:orig_category":"Boutiquen",
    "sg:phone":"+43 7223 83246",
    "sg:postcode":"4470",
    "sg:province":"Ober\u00f6sterreich",
    "wof:name":"Boutique 42 und mehr",
    "wof:placetype":"venue"
},
  "geometry": {"coordinates":[14.4765291214,48.214679718],"type":"Point"}
}