{
  "type": "Feature",
  "properties": {
    "addr:full":"Kehlhof 24 Abtenau Salzburg 5441",
    "addr:housenumber":"24",
    "addr:postcode":"5441",
    "addr:street":"Kehlhof;Salzburg",
    "iso:country":"AT",
    "sg:address":"Kehlhof 24",
    "sg:city":"Abtenau",
    "sg:orig_category":"Werbeagenturen",
    "sg:phone":"+43 4369 914242400",
    "sg:postcode":"5441",
    "sg:province":"Salzburg",
    "wof:name":"BUCHEGGER & DOERFEL OEG",
    "wof:placetype":"venue"
},
  "geometry": {"coordinates":[13.3463354111,47.5727653503],"type":"Point"}
}