{
  "type": "Feature",
  "properties": {
    "addr:full":"Hietzinger Hauptstr. 22 Wien Wien 1130",
    "addr:housenumber":"22",
    "addr:postcode":"1130",
    "addr:street":"Hietzinger Hauptstr.",
    "iso:country":"AT",
    "sg:address":"Hietzinger Hauptstr. 22",
    "sg:city":"Wien",
    "sg:classifiers":[
        {
            "category":"Manufacturing",
            "subcategory":"Printing",
            "type":"Manufacturing & Wholesale Goods"
        }
    ],
    "sg:phone":"+43 4318 776102",
    "sg:postcode":"1130",
    "sg:province":"Wien",
    "sg:tags":[
        "publishing"
    ],
    "wof:name":"GODAI BUCHHANDEL GESMBH",
    "wof:placetype":"venue"
},
  "geometry": {"coordinates":[16.3002529144,48.1864051819],"type":"Point"}
}