{
  "type": "Feature",
  "properties": {
    "iso:country":"AT",
    "sg:address":"Furter Zaunweg 6A/1",
    "sg:city":"Innsbruck",
    "sg:orig_category":"Physiotherapie",
    "sg:phone":"+43 512 360397",
    "sg:postcode":"6020",
    "sg:province":"Tirol",
    "wof:name":"Winder Ulrike Dipl-PT",
    "wof:placetype":"venue"
},
  "geometry": {"coordinates":[11.4075126648,47.2677612305],"type":"Point"}
}