{
  "type": "Feature",
  "properties": {
    "addr:full":"Dr.-Stumpf-Str 10a Innsbruck Tirol 6020",
    "addr:housenumber":"10a",
    "addr:postcode":"6020",
    "addr:street":"Dr.-Stumpf-Str;Tirol",
    "iso:country":"AT",
    "sg:address":"Dr.-Stumpf-Str 10a",
    "sg:city":"Innsbruck",
    "sg:orig_category":"Webdesign",
    "sg:phone":"+43 4369 927399061",
    "sg:postcode":"6020",
    "sg:province":"Tirol",
    "wof:name":"Sinus",
    "wof:placetype":"venue"
},
  "geometry": {"coordinates":[11.3746595383,47.2571220398],"type":"Point"}
}