{
  "type": "Feature",
  "properties": {
    "iso:country":"AT",
    "sg:address":"Roseggerstr 10a",
    "sg:city":"Traun",
    "sg:orig_category":"Autosattlereien",
    "sg:phone":"+43 7229 51518",
    "sg:postcode":"4050",
    "sg:province":"Ober\u00f6sterreich",
    "wof:name":"Autosattlerei Weiss Harald",
    "wof:placetype":"venue"
},
  "geometry": {"coordinates":[14.2595787048,48.240486145],"type":"Point"}
}