{
  "type": "Feature",
  "properties": {
    "addr:full":"Haidinger Str 35c Buchkirchen Ober\u00f6sterreich 4611",
    "addr:postcode":"4611",
    "addr:street":"Str 35C",
    "iso:country":"AT",
    "sg:address":"Haidinger Str 35c",
    "sg:city":"Buchkirchen",
    "sg:orig_category":"Zahntechnische Laboratorien",
    "sg:phone":"+43 7242 36098",
    "sg:postcode":"4611",
    "sg:province":"Ober\u00f6sterreich",
    "wof:name":"Fachlabor f Modellgu\u00dftechnik - L\u00fcer Ilse",
    "wof:placetype":"venue"
},
  "geometry": {"coordinates":[14.0022449493,48.2093429565],"type":"Point"}
}