{
  "type": "Feature",
  "properties": {
    "addr:full":"Waltendorfer Hauptstr 180 St. Peter Steiermark 8042",
    "addr:housenumber":"180",
    "addr:postcode":"8042",
    "addr:street":"Waltendorfer Hauptstr",
    "iso:country":"AT",
    "sg:address":"Waltendorfer Hauptstr 180",
    "sg:city":"St. Peter",
    "sg:orig_category":"Architekten",
    "sg:phone":"+43 4331 6471113",
    "sg:postcode":"8042",
    "sg:province":"Steiermark",
    "wof:name":"Wigand Hans-Jochen Arch Dipl-Ing",
    "wof:placetype":"venue"
},
  "geometry": {"coordinates":[15.4911289215,47.0698928833],"type":"Point"}
}