{
  "type": "Feature",
  "properties": {
    "iso:country":"AT",
    "sg:address":"Nr 44",
    "sg:city":"Unternberg",
    "sg:orig_category":"Pensionen / Privatzimmer",
    "sg:phone":"+43 4364 746203",
    "sg:postcode":"5585",
    "sg:province":"Salzburg",
    "wof:name":"Pension Frimlhof",
    "wof:placetype":"venue"
},
  "geometry": {"coordinates":[13.8729801178,47.0779304504],"type":"Point"}
}