{
  "type": "Feature",
  "properties": {
    "iso:country":"AT",
    "sg:address":"Nikolaipl 2",
    "sg:city":"Villach",
    "sg:orig_category":"Personalbereitstellung",
    "sg:phone":"+43 4242 216066",
    "sg:postcode":"9500",
    "sg:province":"K\u00e4rnten",
    "wof:name":"Manpower Austria Tempor\u00e4rpersonal GesmbH",
    "wof:placetype":"venue"
},
  "geometry": {"coordinates":[13.8488874435,46.6156463623],"type":"Point"}
}