{
  "type": "Feature",
  "properties": {
    "addr:full":"Gr\u00fcnbachstr 26 Bachmanning Ober\u00f6sterreich 4672",
    "addr:housenumber":"26",
    "addr:postcode":"4672",
    "addr:street":"Gruenbachstr",
    "iso:country":"AT",
    "sg:address":"Gr\u00fcnbachstr 26",
    "sg:city":"Bachmanning",
    "sg:orig_category":"Messe- U Ausstellungsbau U -Gestaltung",
    "sg:phone":"+43 7735 62340",
    "sg:postcode":"4672",
    "sg:province":"Ober\u00f6sterreich",
    "wof:name":"ICS Messestandbau GesmbH",
    "wof:placetype":"venue"
},
  "geometry": {"coordinates":[13.7944488525,48.1298942566],"type":"Point"}
}