{
  "type": "Feature",
  "properties": {
    "addr:full":"Oberer Stadtpl 5a Kufstein Tirol 6330",
    "addr:housenumber":"5a",
    "addr:postcode":"6330",
    "addr:street":"Oberer Stadtpl;Tirol",
    "iso:country":"AT",
    "sg:address":"Oberer Stadtpl 5a",
    "sg:city":"Kufstein",
    "sg:orig_category":"Tennisschulen",
    "sg:phone":"+43 664 2260344",
    "sg:postcode":"6330",
    "sg:province":"Tirol",
    "wof:name":"Tennisschule Reinhard Doll",
    "wof:placetype":"venue"
},
  "geometry": {"coordinates":[12.1708278656,47.5828208923],"type":"Point"}
}