{
  "type": "Feature",
  "properties": {
    "addr:full":"Nr 45 Puchenstuben Nieder\u00f6sterreich 3214",
    "addr:postcode":"3214",
    "addr:street":"Nr;Puchenstuben",
    "iso:country":"AT",
    "sg:address":"Nr 45",
    "sg:city":"Puchenstuben",
    "sg:orig_category":"Feuerwehren",
    "sg:phone":"+43 2726 267",
    "sg:postcode":"3214",
    "sg:province":"Nieder\u00f6sterreich",
    "wof:name":"Freiwillige Feuerwehr Puchenstuben",
    "wof:placetype":"venue"
},
  "geometry": {"coordinates":[15.2873277664,47.9275436401],"type":"Point"}
}