{
  "type": "Feature",
  "properties": {
    "addr:full":"Gemeindepl 7 Hargelsberg Ober\u00f6sterreich 4483",
    "addr:housenumber":"7",
    "addr:postcode":"4483",
    "addr:street":"Gemeindepl",
    "iso:country":"AT",
    "sg:address":"Gemeindepl 7",
    "sg:city":"Hargelsberg",
    "sg:orig_category":"Banken U Sparkassen",
    "sg:phone":"+43 4372 2572140",
    "sg:postcode":"4483",
    "sg:province":"Ober\u00f6sterreich",
    "wof:name":"Raiffeisenbank Enns regGenmbH",
    "wof:placetype":"venue"
},
  "geometry": {"coordinates":[14.4240636826,48.1483192444],"type":"Point"}
}