{
  "type": "Feature",
  "properties": {
    "addr:full":"Stadtgraben 2 Hall in Tirol Tirol 6060",
    "addr:housenumber":"2",
    "addr:postcode":"6060",
    "addr:street":"Stadtgraben;Tirol",
    "iso:country":"AT",
    "sg:address":"Stadtgraben 2",
    "sg:city":"Hall in Tirol",
    "sg:orig_category":"Friseure U Frisiersalons",
    "sg:phone":"+43 4352 2343725",
    "sg:postcode":"6060",
    "sg:province":"Tirol",
    "wof:name":"Drack Christa",
    "wof:placetype":"venue"
},
  "geometry": {"coordinates":[11.5044622421,47.2810440063],"type":"Point"}
}