{
  "type": "Feature",
  "properties": {
    "addr:full":"Rosenstrasse 1 Alkoven Ober\u00f6sterreich 4072",
    "addr:housenumber":"1",
    "addr:postcode":"4072",
    "addr:street":"Rosenstrasse",
    "iso:country":"AT",
    "sg:address":"Rosenstrasse 1",
    "sg:city":"Alkoven",
    "sg:classifiers":[
        {
            "category":"Banks & Credit Unions",
            "subcategory":"Investment Brokerage",
            "type":"Services"
        }
    ],
    "sg:phone":"+43 7274 7620",
    "sg:postcode":"4072",
    "sg:province":"Ober\u00f6sterreich",
    "sg:tags":[
        "curtain",
        "rod",
        "accessory"
    ],
    "wof:name":"Josef Steineder",
    "wof:placetype":"venue"
},
  "geometry": {"coordinates":[14.1205282211,48.2893295288],"type":"Point"}
}