{
  "type": "Feature",
  "properties": {
    "iso:country":"AT",
    "sg:address":"Garteng 8",
    "sg:city":"Trieben",
    "sg:orig_category":"Glasereien",
    "sg:phone":"+43 4336 1523410",
    "sg:postcode":"8784",
    "sg:province":"Steiermark",
    "wof:name":"Matlschweiger Franz u Sohn KG",
    "wof:placetype":"venue"
},
  "geometry": {"coordinates":[14.4840450287,47.4863471985],"type":"Point"}
}