{
  "type": "Feature",
  "properties": {
    "addr:full":"Humboldtstrasse 39 Linz Ober\u00f6sterreich 4020",
    "addr:housenumber":"39",
    "addr:postcode":"4020",
    "addr:street":"Humboldtstrasse",
    "iso:country":"AT",
    "sg:address":"Humboldtstrasse 39",
    "sg:city":"Linz",
    "sg:classifiers":[
        {
            "category":"Real Estate",
            "subcategory":"Surveying",
            "type":"Services"
        }
    ],
    "sg:phone":"+43 732 651571",
    "sg:postcode":"4020",
    "sg:province":"Ober\u00f6sterreich",
    "sg:tags":[
        "concrete",
        "balcony"
    ],
    "wof:name":"Alutechnik Matauschek",
    "wof:placetype":"venue"
},
  "geometry": {"coordinates":[14.296002388,48.297088623],"type":"Point"}
}