{
  "type": "Feature",
  "properties": {
    "addr:full":"Tullner Str 16 Michelhausen Nieder\u00f6sterreich 3451",
    "addr:housenumber":"16",
    "addr:postcode":"3451",
    "addr:street":"Str",
    "iso:country":"AT",
    "sg:address":"Tullner Str 16",
    "sg:city":"Michelhausen",
    "sg:orig_category":"Gemeinden",
    "sg:phone":"+43 2275 5241",
    "sg:postcode":"3451",
    "sg:province":"Nieder\u00f6sterreich",
    "wof:name":"Gemeindeamt Michelhausen",
    "wof:placetype":"venue"
},
  "geometry": {"coordinates":[15.9408874512,48.2900276184],"type":"Point"}
}