{
  "type": "Feature",
  "properties": {
    "iso:country":"AT",
    "sg:address":"Adolf-Kolping-Gasse 8",
    "sg:city":"Klagenfurt",
    "sg:classifiers":[
        {
            "category":"Retail",
            "subcategory":"Repair Shop",
            "type":"Services"
        }
    ],
    "sg:phone":"+43 463 51364818",
    "sg:postcode":"9020",
    "sg:province":"K\u00e4rnten",
    "sg:tags":[
        "appliance",
        "electrical"
    ],
    "wof:name":"Ranacher Peter, Service Werkst\u00e4tte B\u00fcgelger\u00e4te-N\u00e4hmaschinen-Reinigungs",
    "wof:placetype":"venue"
},
  "geometry": {"coordinates":[14.3046474457,46.6223678589],"type":"Point"}
}