{
  "type": "Feature",
  "properties": {
    "iso:country":"AT",
    "sg:address":"Sonnenweg 9",
    "sg:city":"Eugendorf",
    "sg:orig_category":"Physiotherapie",
    "sg:phone":"+43 4362 257798",
    "sg:postcode":"5301",
    "sg:province":"Salzburg",
    "wof:name":"Fachpraxis f Physiotherapie u Osteopathie - H. Stemeseder",
    "wof:placetype":"venue"
},
  "geometry": {"coordinates":[13.124420166,47.8642616272],"type":"Point"}
}