{
  "type": "Feature",
  "properties": {
    "addr:full":"Losenheimer Str 53 Puchberg am Schneeberg Nieder\u00f6sterreich 2734",
    "addr:housenumber":"53",
    "addr:postcode":"2734",
    "addr:street":"Str",
    "iso:country":"AT",
    "sg:address":"Losenheimer Str 53",
    "sg:city":"Puchberg am Schneeberg",
    "sg:orig_category":"Elektroinstallationsunternehmen",
    "sg:phone":"+43 4326 3632700",
    "sg:postcode":"2734",
    "sg:province":"Nieder\u00f6sterreich",
    "wof:name":"Gschaider Eduard",
    "wof:placetype":"venue"
},
  "geometry": {"coordinates":[15.8554935455,47.7877235413],"type":"Point"}
}