{
  "type": "Feature",
  "properties": {
    "addr:full":"Grazer Str 29-31 Theresienfeld Nieder\u00f6sterreich 2604",
    "addr:postcode":"29-31;2604",
    "addr:street":"Str",
    "iso:country":"AT",
    "sg:address":"Grazer Str 29-31",
    "sg:city":"Theresienfeld",
    "sg:orig_category":"Dunstabzugshauben",
    "sg:phone":"+43 4326 2271158",
    "sg:postcode":"2604",
    "sg:province":"Nieder\u00f6sterreich",
    "wof:name":"Pietsch Klaudius Dipl-Ing",
    "wof:placetype":"venue"
},
  "geometry": {"coordinates":[16.2474021912,47.8553657532],"type":"Point"}
}