{
  "type": "Feature",
  "properties": {
    "addr:full":"Unternberg 6 Neufelden Ober\u00f6sterreich 4120",
    "addr:housenumber":"6",
    "addr:postcode":"4120",
    "addr:street":"Unternberg",
    "iso:country":"AT",
    "sg:address":"Unternberg 6",
    "sg:city":"Neufelden",
    "sg:classifiers":[
        {
            "category":"Travel",
            "subcategory":"Hotels & Motels",
            "type":"Entertainment"
        }
    ],
    "sg:phone":"+43 4372 8262580",
    "sg:postcode":"4120",
    "sg:province":"Ober\u00f6sterreich",
    "sg:website":"muehltalhof.com",
    "wof:name":"Genie\u00dferhotel Restaurant M\u00fchltalhof",
    "wof:placetype":"venue"
},
  "geometry": {"coordinates":[14.0021400452,48.4810905457],"type":"Point"}
}