{
  "type": "Feature",
  "properties": {
    "iso:country":"AT",
    "sg:address":"Bachleiten 2",
    "sg:city":"Neukirchen an der Enknach",
    "sg:orig_category":"Schneidereien",
    "sg:phone":"+43 7729 2358",
    "sg:postcode":"5145",
    "sg:province":"Ober\u00f6sterreich",
    "wof:name":"Bernroider Hans",
    "wof:placetype":"venue"
},
  "geometry": {"coordinates":[13.0817890167,48.1556587219],"type":"Point"}
}