{
  "type": "Feature",
  "properties": {
    "addr:full":"Hauptstr 32 Eisenstadt Burgenland 7000",
    "addr:housenumber":"32",
    "addr:postcode":"7000",
    "addr:street":"Hauptstr",
    "iso:country":"AT",
    "sg:address":"Hauptstr 32",
    "sg:city":"Eisenstadt",
    "sg:orig_category":"Tabaktrafiken",
    "sg:phone":"+43 2682 62476",
    "sg:postcode":"7000",
    "sg:province":"Burgenland",
    "wof:name":"Sommer Eva",
    "wof:placetype":"venue"
},
  "geometry": {"coordinates":[16.5239181519,47.8463287354],"type":"Point"}
}