{
  "type": "Feature",
  "properties": {
    "addr:full":"Gries 8 Lermoos Tirol 6631",
    "addr:housenumber":"8",
    "addr:postcode":"6631",
    "addr:street":"Gries;Tirol",
    "iso:country":"AT",
    "sg:address":"Gries 8",
    "sg:city":"Lermoos",
    "sg:classifiers":[
        {
            "category":"Structure",
            "subcategory":"Tunnel",
            "type":"Public Place"
        }
    ],
    "sg:phone":"+43 5673 3777",
    "sg:postcode":"6631",
    "sg:province":"Tirol",
    "sg:tags":[
        "aluminium",
        "fence"
    ],
    "wof:name":"Erich M\u00fcller",
    "wof:placetype":"venue"
},
  "geometry": {"coordinates":[10.8708305359,47.4058380127],"type":"Point"}
}