{
  "type": "Feature",
  "properties": {
    "iso:country":"AT",
    "sg:address":"Nr 23",
    "sg:city":"M\u00fchlen",
    "sg:orig_category":"Tischlereien",
    "sg:phone":"+43 3586 2364",
    "sg:postcode":"8822",
    "sg:province":"Steiermark",
    "wof:name":"Wurzer Karl",
    "wof:placetype":"venue"
},
  "geometry": {"coordinates":[5.9043102264,49.874370575],"type":"Point"}
}