{
  "type": "Feature",
  "properties": {
    "iso:country":"AT",
    "sg:address":"Anton-Schneider-Strasse 8",
    "sg:city":"Bregenz",
    "sg:classifiers":[
        {
            "category":"Shopping",
            "subcategory":"Clothing, Apparel, & Fashions",
            "type":"Retail Goods"
        }
    ],
    "sg:phone":"+43 5574 42298",
    "sg:postcode":"6900",
    "sg:province":"Vorarlberg",
    "sg:tags":[
        "equestrian",
        "clothes"
    ],
    "wof:name":"Gebr\u00fcder Burger Textilhandelsges.m.b.H.",
    "wof:placetype":"venue"
},
  "geometry": {"coordinates":[9.7477083206,47.5032234192],"type":"Point"}
}