{
  "type": "Feature",
  "properties": {
    "iso:country":"AT",
    "sg:address":"Nr 43",
    "sg:city":"Taufkirchen an der Trattnach",
    "sg:orig_category":"Banken U Sparkassen",
    "sg:phone":"+43 4377 3426310",
    "sg:postcode":"4715",
    "sg:province":"Ober\u00f6sterreich",
    "wof:name":"Raiffeisenbank Region Grieskirchen regGenmbH",
    "wof:placetype":"venue"
},
  "geometry": {"coordinates":[13.7491598129,48.2472038269],"type":"Point"}
}