{
  "type": "Feature",
  "properties": {
    "addr:full":"Leopold-H\u00f6rbinger-Str 6 Leobersdorf Nieder\u00f6sterreich 2544",
    "addr:housenumber":"6",
    "addr:postcode":"2544",
    "addr:street":"Leopold-Hoerbinger-Str",
    "iso:country":"AT",
    "sg:address":"Leopold-H\u00f6rbinger-Str 6",
    "sg:city":"Leobersdorf",
    "sg:orig_category":"Heurigen / Buschenschank",
    "sg:phone":"+43 4322 5663759",
    "sg:postcode":"2544",
    "sg:province":"Nieder\u00f6sterreich",
    "wof:name":"Zum Weinstadl - Erwin u Andrea Mehlstaub",
    "wof:placetype":"venue"
},
  "geometry": {"coordinates":[16.2139568329,47.9321708679],"type":"Point"}
}