{
  "type": "Feature",
  "properties": {
    "addr:full":"Alpenbadstr 2 Liezen Steiermark 8940",
    "addr:housenumber":"2",
    "addr:postcode":"8940",
    "addr:street":"Alpenbadstr",
    "iso:country":"AT",
    "sg:address":"Alpenbadstr 2",
    "sg:city":"Liezen",
    "sg:classifiers":[
        {
            "category":"Travel",
            "subcategory":"Hotels & Motels",
            "type":"Entertainment"
        }
    ],
    "sg:phone":"+43 3612 25222",
    "sg:postcode":"8940",
    "sg:province":"Steiermark",
    "wof:name":"Hotel Liezenerhof",
    "wof:placetype":"venue"
},
  "geometry": {"coordinates":[14.2424707413,47.5713348389],"type":"Point"}
}