{
  "type": "Feature",
  "properties": {
    "iso:country":"AT",
    "sg:address":"Nr 43",
    "sg:city":"St. Andr\u00e4",
    "sg:orig_category":"Bauunternehmen",
    "sg:phone":"+43 4358 3606",
    "sg:postcode":"9433",
    "sg:province":"K\u00e4rnten",
    "wof:name":"Brunner Stefan",
    "wof:placetype":"venue"
},
  "geometry": {"coordinates":[14.8218545914,46.7685317993],"type":"Point"}
}