{
  "type": "Feature",
  "properties": {
    "addr:full":"Kreuzg 1a Tschagguns Vorarlberg 6774",
    "addr:housenumber":"1a",
    "addr:postcode":"6774",
    "addr:street":"Kreuzg",
    "iso:country":"AT",
    "sg:address":"Kreuzg 1a",
    "sg:city":"Tschagguns",
    "sg:orig_category":"Fleischhauereien",
    "sg:phone":"+43 4355 5675241",
    "sg:postcode":"6774",
    "sg:province":"Vorarlberg",
    "wof:name":"Salzgeber GmbH & Co KG",
    "wof:placetype":"venue"
},
  "geometry": {"coordinates":[9.9031639099,47.077796936],"type":"Point"}
}