{
  "type": "Feature",
  "properties": {
    "addr:full":"Westuferstr 43 St. Kanzian am Klopeiner See K\u00e4rnten 9122",
    "addr:housenumber":"43",
    "addr:postcode":"9122",
    "addr:street":"Westuferstr;Kaernten",
    "iso:country":"AT",
    "sg:address":"Westuferstr 43",
    "sg:city":"St. Kanzian am Klopeiner See",
    "sg:orig_category":"Pensionen / Privatzimmer",
    "sg:phone":"+43 4342 392403",
    "sg:postcode":"9122",
    "sg:province":"K\u00e4rnten",
    "wof:name":"Jesse Franziska",
    "wof:placetype":"venue"
},
  "geometry": {"coordinates":[14.5720672607,46.6040725708],"type":"Point"}
}