{
  "type": "Feature",
  "properties": {
    "iso:country":"AT",
    "sg:address":"Hauptpl 1",
    "sg:city":"Unterach am Attersee",
    "sg:orig_category":"Lebensmittel / Einzelhandel",
    "sg:phone":"+43 766560010",
    "sg:postcode":"4866",
    "sg:province":"Ober\u00f6sterreich",
    "wof:name":"Spar-Markt Inh Christian Hieke",
    "wof:placetype":"venue"
},
  "geometry": {"coordinates":[13.4876689911,47.8040618896],"type":"Point"}
}