{
  "type": "Feature",
  "properties": {
    "addr:full":"Laudonstrasse 39 Klagenfurt K\u00e4rnten 9020",
    "addr:housenumber":"39",
    "addr:postcode":"9020",
    "addr:street":"Laudonstrasse;Kaernten",
    "iso:country":"AT",
    "sg:address":"Laudonstrasse 39",
    "sg:city":"Klagenfurt",
    "sg:classifiers":[
        {
            "category":"Wholesale",
            "subcategory":"Medical Equipment & Supplies",
            "type":"Manufacturing & Wholesale Goods"
        }
    ],
    "sg:phone":"+43 463 41675",
    "sg:postcode":"9020",
    "sg:province":"K\u00e4rnten",
    "sg:tags":[
        "hospital",
        "requisite"
    ],
    "sg:website":"glinik.at",
    "wof:name":"GLINIK Ges.m.b.H.",
    "wof:placetype":"venue"
},
  "geometry": {"coordinates":[14.3120803833,46.6614227295],"type":"Point"}
}