{
  "type": "Feature",
  "properties": {
    "iso:country":"AT",
    "sg:address":"Hafnerstr 1-3",
    "sg:city":"Krummnu\u00dfbaum",
    "sg:orig_category":"Schamottewaren",
    "sg:phone":"+43 2757 24010",
    "sg:postcode":"3375",
    "sg:province":"Nieder\u00f6sterreich",
    "wof:name":"Rath August jun GmbH Chamottewaren und Thon\u00f6fenfabrik",
    "wof:placetype":"venue"
},
  "geometry": {"coordinates":[-90.31578063960001,39.3304100037],"type":"Point"}
}