{
  "type": "Feature",
  "properties": {
    "addr:full":"Roseggerstr 12 Bruck an der Mur Steiermark 8600",
    "addr:housenumber":"12",
    "addr:postcode":"8600",
    "addr:street":"Roseggerstr",
    "iso:country":"AT",
    "sg:address":"Roseggerstr 12",
    "sg:city":"Bruck an der Mur",
    "sg:orig_category":"Psychotherapie",
    "sg:phone":"+43 4338 6252618",
    "sg:postcode":"8600",
    "sg:province":"Steiermark",
    "wof:name":"Bernhauser Hemma Mag",
    "wof:placetype":"venue"
},
  "geometry": {"coordinates":[15.2710800171,47.4096488953],"type":"Point"}
}