{
  "type": "Feature",
  "properties": {
    "addr:full":"Nr 14a Ebenau Salzburg 5323",
    "addr:postcode":"5323",
    "addr:street":"Nr 14A;Salzburg",
    "iso:country":"AT",
    "sg:address":"Nr 14a",
    "sg:city":"Ebenau",
    "sg:orig_category":"Geschenkartikel",
    "sg:phone":"+43 6221 8012",
    "sg:postcode":"5323",
    "sg:province":"Salzburg",
    "wof:name":"Hofer Trends GesmbH",
    "wof:placetype":"venue"
},
  "geometry": {"coordinates":[13.1745538712,47.7922706604],"type":"Point"}
}