{
  "type": "Feature",
  "properties": {
    "addr:full":"Lach 20 Braunau am Inn Ober\u00f6sterreich 5280",
    "addr:housenumber":"20",
    "addr:postcode":"5280",
    "addr:street":"Lach",
    "iso:country":"AT",
    "sg:address":"Lach 20",
    "sg:city":"Braunau am Inn",
    "sg:classifiers":[
        {
            "category":"Home & Garden",
            "subcategory":"Building Materials",
            "type":"Retail Goods"
        }
    ],
    "sg:phone":"+43 7722 87564",
    "sg:postcode":"5280",
    "sg:province":"Ober\u00f6sterreich",
    "sg:tags":[
        "gravel",
        "crushed"
    ],
    "sg:website":"moser-beton.at",
    "wof:name":"Franz Moser GmbH",
    "wof:placetype":"venue"
},
  "geometry": {"coordinates":[13.068567276,48.2565689087],"type":"Point"}
}