{
  "type": "Feature",
  "properties": {
    "addr:full":"Schulg 11 Oberloisdorf Burgenland 7451",
    "addr:housenumber":"11",
    "addr:postcode":"7451",
    "addr:street":"Schulg",
    "iso:country":"AT",
    "sg:address":"Schulg 11",
    "sg:city":"Oberloisdorf",
    "sg:orig_category":"Feuerwehren",
    "sg:phone":"+43 2611 3438",
    "sg:postcode":"7451",
    "sg:province":"Burgenland",
    "wof:name":"Freiwillige Feuerwehr Oberloisdorf",
    "wof:placetype":"venue"
},
  "geometry": {"coordinates":[16.5079555511,47.4441566467],"type":"Point"}
}