{
  "type": "Feature",
  "properties": {
    "iso:country":"AT",
    "sg:address":"Neuhofen im Innkreis 35",
    "sg:city":"Ried im Innkreis",
    "sg:classifiers":[
        {
            "category":"Home & Garden",
            "subcategory":"Building Materials",
            "type":"Retail Goods"
        }
    ],
    "sg:phone":"+43 7752 82884",
    "sg:postcode":"4910",
    "sg:province":"Ober\u00f6sterreich",
    "sg:tags":[
        "beer",
        "furniture"
    ],
    "sg:website":"chwala.at",
    "wof:name":"Ernst Chwala",
    "wof:placetype":"venue"
},
  "geometry": {"coordinates":[13.4900550842,48.2098655701],"type":"Point"}
}