{
  "type": "Feature",
  "properties": {
    "iso:country":"AT",
    "sg:address":"Mitterg 26",
    "sg:city":"Bruck an der Mur",
    "sg:orig_category":"Friseure U Frisiersalons",
    "sg:phone":"+43 4338 6251786",
    "sg:postcode":"8600",
    "sg:province":"Steiermark",
    "wof:name":"Hair Company by Andrea Weghofer",
    "wof:placetype":"venue"
},
  "geometry": {"coordinates":[15.2725257874,47.4105491638],"type":"Point"}
}