{
  "type": "Feature",
  "properties": {
    "iso:country":"AT",
    "sg:address":"Eponastr 5",
    "sg:city":"Bregenz",
    "sg:orig_category":"Unternehmensberatung",
    "sg:phone":"+43 5574 45561",
    "sg:postcode":"6900",
    "sg:province":"Vorarlberg",
    "wof:name":"B\u00fcro f Export Marketing",
    "wof:placetype":"venue"
},
  "geometry": {"coordinates":[9.7493000031,47.5002250671],"type":"Point"}
}