{
  "type": "Feature",
  "properties": {
    "iso:country":"AT",
    "sg:address":"Volkertpl 1",
    "sg:city":"Wien",
    "sg:classifiers":[
        {
            "category":"Professional",
            "subcategory":"Computer Services",
            "type":"Services"
        }
    ],
    "sg:phone":"+43 4312 165828",
    "sg:postcode":"1020",
    "sg:province":"Wien",
    "sg:tags":[
        "software"
    ],
    "wof:name":"Prager Karl M. - Nachrichtenelektronik",
    "wof:placetype":"venue"
},
  "geometry": {"coordinates":[16.3853530884,48.2229766846],"type":"Point"}
}