{
  "type": "Feature",
  "properties": {
    "addr:full":"Murm\u00fchlweg 8 Gratwein Steiermark 8112",
    "addr:housenumber":"8",
    "addr:postcode":"8112",
    "addr:street":"Murmuehlweg",
    "iso:country":"AT",
    "sg:address":"Murm\u00fchlweg 8",
    "sg:city":"Gratwein",
    "sg:orig_category":"Holzhandel",
    "sg:phone":"+43 4331 2452256",
    "sg:postcode":"8112",
    "sg:province":"Steiermark",
    "wof:name":"Hechenblaickner M Holzhandels-GesmbH",
    "wof:placetype":"venue"
},
  "geometry": {"coordinates":[15.3184213638,47.1293487549],"type":"Point"}
}