{
  "type": "Feature",
  "properties": {
    "iso:country":"AT",
    "sg:address":"Gaisberg 11",
    "sg:city":"Salzburg",
    "sg:classifiers":[
        {
            "category":"Travel",
            "subcategory":"Hotels & Motels",
            "type":"Entertainment"
        }
    ],
    "sg:phone":"+43 662 641510",
    "sg:postcode":"5020",
    "sg:province":"Salzburg",
    "sg:website":"kobenzl.at",
    "wof:name":"Hotel Kobenzl",
    "wof:placetype":"venue"
},
  "geometry": {"coordinates":[13.0662193298,47.8012924194],"type":"Point"}
}