{
  "type": "Feature",
  "properties": {
    "addr:full":"Penzinger Str 135/21 Wien Wien 1140",
    "addr:housenumber":"135 / 21",
    "addr:postcode":"1140",
    "iso:country":"AT",
    "sg:address":"Penzinger Str 135/21",
    "sg:city":"Wien",
    "sg:orig_category":"Tonstudios",
    "sg:phone":"+43 1 8948950",
    "sg:postcode":"1140",
    "sg:province":"Wien",
    "wof:name":"Waveland Tonstudio",
    "wof:placetype":"venue"
},
  "geometry": {"coordinates":[16.2942295074,48.1910552979],"type":"Point"}
}