{
  "type": "Feature",
  "properties": {
    "iso:country":"AT",
    "sg:address":"Gazeile 7",
    "sg:city":"Schrems",
    "sg:orig_category":"Sonnenstudios",
    "sg:phone":"+43 2853 72922",
    "sg:postcode":"3943",
    "sg:province":"Nieder\u00f6sterreich",
    "wof:name":"Anrosi Kutschera KEG",
    "wof:placetype":"venue"
},
  "geometry": {"coordinates":[15.0736427307,48.7933425903],"type":"Point"}
}