{
  "type": "Feature",
  "properties": {
    "addr:full":"Huebenweg Steinach am Brenner Tirol 6150",
    "addr:postcode":"6150",
    "addr:street":"Huebenweg;Tirol",
    "iso:country":"AT",
    "sg:address":"Huebenweg",
    "sg:city":"Steinach am Brenner",
    "sg:orig_category":"Bergbahnen",
    "sg:phone":"+43 5272 63330",
    "sg:postcode":"6150",
    "sg:province":"Tirol",
    "wof:name":"Steinacher Bergbahnen AG",
    "wof:placetype":"venue"
},
  "geometry": {"coordinates":[11.4647006989,47.0901031494],"type":"Point"}
}