{
  "type": "Feature",
  "properties": {
    "addr:full":"Leiteg 2 Villach K\u00e4rnten 9500",
    "addr:housenumber":"2",
    "addr:postcode":"9500",
    "addr:street":"Leiteg;Kaernten",
    "iso:country":"AT",
    "sg:address":"Leiteg 2",
    "sg:city":"Villach",
    "sg:orig_category":"Schmieden U Schmiedeeisenelemente",
    "sg:phone":"+43 4342 42214196",
    "sg:postcode":"9500",
    "sg:province":"K\u00e4rnten",
    "wof:name":"Kunstschmiede u moderne Metallgestaltung Markus Scherr KEG",
    "wof:placetype":"venue"
},
  "geometry": {"coordinates":[13.8491945267,46.618106842],"type":"Point"}
}