{
  "type": "Feature",
  "properties": {
    "iso:country":"AT",
    "sg:address":"Thumegger Strasse 17",
    "sg:city":"Salzburg",
    "sg:classifiers":[
        {
            "category":"Coffee & Tea",
            "type":"Food & Drink"
        }
    ],
    "sg:phone":"+43 662 820933",
    "sg:postcode":"5020",
    "sg:province":"Salzburg",
    "sg:tags":[
        "roasted"
    ],
    "wof:name":"Friedhelm Hanusch",
    "wof:placetype":"venue"
},
  "geometry": {"coordinates":[13.0466766357,47.7831802368],"type":"Point"}
}