{
  "type": "Feature",
  "properties": {
    "addr:full":"Alaudag 7/23/23 Wien Wien 1100",
    "addr:housenumber":"7 / 23 / 23",
    "addr:postcode":"1100",
    "addr:street":"Alaudag",
    "iso:country":"AT",
    "sg:address":"Alaudag 7/23/23",
    "sg:city":"Wien",
    "sg:orig_category":"Tonstudios, Ton- U Lichtanlagen",
    "sg:phone":"+43 664 1606770",
    "sg:postcode":"1100",
    "sg:province":"Wien",
    "sg:website":"www.viennapowerstation.at",
    "wof:name":"Vienna Power Station",
    "wof:placetype":"venue"
},
  "geometry": {"coordinates":[16.3744049072,48.1782684326],"type":"Point"}
}