{
  "type": "Feature",
  "properties": {
    "iso:country":"AT",
    "sg:address":"Triesterstrasse 388 - 390",
    "sg:city":"Puntigam",
    "sg:classifiers":[
        {
            "category":"Manufacturing",
            "subcategory":"Motor Vehicles & Parts",
            "type":"Manufacturing & Wholesale Goods"
        }
    ],
    "sg:phone":"+43 316 2955460",
    "sg:postcode":"8055",
    "sg:province":"Steiermark",
    "sg:tags":[
        "pipe",
        "exhaust"
    ],
    "sg:website":"teamstyria.at",
    "wof:name":"Team Styria Werkst\u00e4tten GmbH",
    "wof:placetype":"venue"
},
  "geometry": {"coordinates":[15.4343233109,47.0261268616],"type":"Point"}
}