{
  "type": "Feature",
  "properties": {
    "addr:full":"Hauptpl 39 Leibnitz Steiermark 8430",
    "addr:housenumber":"39",
    "addr:postcode":"8430",
    "addr:street":"Hauptpl;Steiermark",
    "iso:country":"AT",
    "sg:address":"Hauptpl 39",
    "sg:city":"Leibnitz",
    "sg:orig_category":"Non-Classified Establishments",
    "sg:phone":"+43 3452 82979",
    "sg:postcode":"8430",
    "sg:province":"Steiermark",
    "wof:name":"Kapuziner Kloster",
    "wof:placetype":"venue"
},
  "geometry": {"coordinates":[15.5371236801,46.7806892395],"type":"Point"}
}