{
  "type": "Feature",
  "properties": {
    "addr:full":"Hittnerg 8 St. Andr\u00e4-W\u00f6rdern Nieder\u00f6sterreich 3423",
    "addr:housenumber":"8",
    "addr:postcode":"3423",
    "addr:street":"Hittnerg",
    "iso:country":"AT",
    "sg:address":"Hittnerg 8",
    "sg:city":"St. Andr\u00e4-W\u00f6rdern",
    "sg:orig_category":"Unternehmensberatung",
    "sg:phone":"+43 4322 4232486",
    "sg:postcode":"3423",
    "sg:province":"Nieder\u00f6sterreich",
    "wof:name":"Hampl Peter Dipl-Ing",
    "wof:placetype":"venue"
},
  "geometry": {"coordinates":[16.2101764679,48.3275222778],"type":"Point"}
}