{
  "type": "Feature",
  "properties": {
    "addr:full":"Nr 27 Waldstein Steiermark 8122",
    "addr:postcode":"8122",
    "addr:street":"Nr",
    "iso:country":"AT",
    "sg:address":"Nr 27",
    "sg:city":"Waldstein",
    "sg:orig_category":"Forstverwaltungen",
    "sg:phone":"+43 3125 22630",
    "sg:postcode":"8122",
    "sg:province":"Steiermark",
    "wof:name":"Forstamt Prinz Liechtenstein GesnbR",
    "wof:placetype":"venue"
},
  "geometry": {"coordinates":[15.266037941,47.2401618958],"type":"Point"}
}