{
  "type": "Feature",
  "properties": {
    "iso:country":"AT",
    "sg:address":"Hauptstr 166",
    "sg:city":"Strasshof an der Nordbahn",
    "sg:orig_category":"Tankstellen",
    "sg:phone":"+43 4322 872306",
    "sg:postcode":"2231",
    "sg:province":"Nieder\u00f6sterreich",
    "wof:name":"Agip Austria GmbH",
    "wof:placetype":"venue"
},
  "geometry": {"coordinates":[16.6365356445,48.3160095215],"type":"Point"}
}