{
  "type": "Feature",
  "properties": {
    "iso:country":"AT",
    "sg:address":"Stadtpl 5",
    "sg:city":"Grieskirchen",
    "sg:orig_category":"Chemikalien",
    "sg:phone":"+43 4366 44510063",
    "sg:postcode":"4710",
    "sg:province":"Ober\u00f6sterreich",
    "wof:name":"IMPEX Trading GmbH",
    "wof:placetype":"venue"
},
  "geometry": {"coordinates":[13.8306980133,48.2348480225],"type":"Point"}
}