{
  "type": "Feature",
  "properties": {
    "iso:country":"AT",
    "sg:address":"Auhofstr. 168",
    "sg:city":"Wien",
    "sg:orig_category":"Dienstleistungen, Druck U Beschriftungen",
    "sg:phone":"+43 1 8778496",
    "sg:postcode":"1130",
    "sg:province":"Wien",
    "sg:website":"http://members.aon.at/fotostudio-gartner/index.htm",
    "wof:name":"Fotografen",
    "wof:placetype":"venue"
},
  "geometry": {"coordinates":[16.2668228149,48.1929016113],"type":"Point"}
}