{
  "type": "Feature",
  "properties": {
    "addr:full":"Spitalstr 31 Oberpullendorf Burgenland 7350",
    "addr:housenumber":"31",
    "addr:postcode":"7350",
    "addr:street":"Spitalstr",
    "iso:country":"AT",
    "sg:address":"Spitalstr 31",
    "sg:city":"Oberpullendorf",
    "sg:orig_category":"Hauskrankenpflege / Heimhilfe",
    "sg:phone":"+43 4326 1243126",
    "sg:postcode":"7350",
    "sg:province":"Burgenland",
    "wof:name":"Burgenl\u00e4ndisches Hilfswerk",
    "wof:placetype":"venue"
},
  "geometry": {"coordinates":[16.5063056946,47.5047416687],"type":"Point"}
}