{
  "type": "Feature",
  "properties": {
    "addr:full":"K\u00f6rnerstr 6 Spittal an der Drau K\u00e4rnten 9800",
    "addr:housenumber":"6",
    "addr:postcode":"9800",
    "addr:street":"Koernerstr;Kaernten",
    "iso:country":"AT",
    "sg:address":"K\u00f6rnerstr 6",
    "sg:city":"Spittal an der Drau",
    "sg:orig_category":"Brauereien",
    "sg:phone":"+43 4762 20260",
    "sg:postcode":"9800",
    "sg:province":"K\u00e4rnten",
    "wof:name":"Brau Union \u00f6sterreich AG",
    "wof:placetype":"venue"
},
  "geometry": {"coordinates":[13.489988327,46.7938728333],"type":"Point"}
}