{
  "type": "Feature",
  "properties": {
    "iso:country":"AT",
    "sg:address":"Dinstlstr 5",
    "sg:city":"Krems an der Donau",
    "sg:orig_category":"Textilreinigung",
    "sg:phone":"+43 4327 3283686",
    "sg:postcode":"3500",
    "sg:province":"Nieder\u00f6sterreich",
    "wof:name":"Regina Textilreinigungs GesmbH",
    "wof:placetype":"venue"
},
  "geometry": {"coordinates":[15.6030464172,48.410358429],"type":"Point"}
}