{
  "type": "Feature",
  "properties": {
    "addr:full":"Gartenstr 7 Bludenz Vorarlberg 6700",
    "addr:housenumber":"7",
    "addr:postcode":"6700",
    "addr:street":"Gartenstr",
    "iso:country":"AT",
    "sg:address":"Gartenstr 7",
    "sg:city":"Bludenz",
    "sg:orig_category":"Fleischhauereien",
    "sg:phone":"+43 5552 62846",
    "sg:postcode":"6700",
    "sg:province":"Vorarlberg",
    "wof:name":"Lindner Karl",
    "wof:placetype":"venue"
},
  "geometry": {"coordinates":[9.8198604584,47.153465271],"type":"Point"}
}