{
  "type": "Feature",
  "properties": {
    "iso:country":"AT",
    "sg:address":"Kapellenweg 4",
    "sg:city":"Vorchdorf",
    "sg:orig_category":"Steuerberatung",
    "sg:phone":"+43 76145350",
    "sg:postcode":"4655",
    "sg:province":"Ober\u00f6sterreich",
    "wof:name":"Schachinger Karoline Mag",
    "wof:placetype":"venue"
},
  "geometry": {"coordinates":[13.9236927032,48.003742218],"type":"Point"}
}