{
  "type": "Feature",
  "properties": {
    "addr:full":"Salzburger Str 1 Bruck an der Gro\u00dfglocknerstra\u00dfe Salzburg 5671",
    "addr:housenumber":"1",
    "addr:postcode":"5671",
    "addr:street":"Salzburger Str;Grossglocknerstrasse Salzburg",
    "iso:country":"AT",
    "sg:address":"Salzburger Str 1",
    "sg:city":"Bruck an der Gro\u00dfglocknerstra\u00dfe",
    "sg:classifiers":[
        {
            "category":"Travel",
            "subcategory":"Hotels & Motels",
            "type":"Entertainment"
        }
    ],
    "sg:phone":"+43 4365 4574580",
    "sg:postcode":"5671",
    "sg:province":"Salzburg",
    "wof:name":"Hotel-Gasthof Lukashansl",
    "wof:placetype":"venue"
},
  "geometry": {"coordinates":[12.8251152039,47.2872962952],"type":"Point"}
}