{
  "type": "Feature",
  "properties": {
    "addr:full":"Zierleitengasse 75a Wien Wien 1190",
    "addr:housenumber":"75a",
    "addr:postcode":"1190",
    "addr:street":"Zierleitengasse",
    "iso:country":"AT",
    "sg:address":"Zierleitengasse 75a",
    "sg:city":"Wien",
    "sg:classifiers":[
        {
            "category":"Communications",
            "subcategory":"Film & Video Production",
            "type":"Services"
        }
    ],
    "sg:phone":"+43 1 4402928",
    "sg:postcode":"1190",
    "sg:province":"Wien",
    "wof:name":"Peter Oberleithner",
    "wof:placetype":"venue"
},
  "geometry": {"coordinates":[16.2885532379,48.2563285828],"type":"Point"}
}