{
  "type": "Feature",
  "properties": {
    "iso:country":"AT",
    "sg:address":"Peter-Rosegger-Str 381",
    "sg:city":"Stainach",
    "sg:orig_category":"Psychologen",
    "sg:phone":"+43 3682 24776",
    "sg:postcode":"8950",
    "sg:province":"Steiermark",
    "wof:name":"Wesner Maria Dr",
    "wof:placetype":"venue"
},
  "geometry": {"coordinates":[14.1162147522,47.5335426331],"type":"Point"}
}