{
  "type": "Feature",
  "properties": {
    "addr:full":"Rainergasse 16 Wien Wien 1040",
    "addr:housenumber":"16",
    "addr:postcode":"1040",
    "addr:street":"Rainergasse",
    "iso:country":"AT",
    "sg:address":"Rainergasse 16",
    "sg:city":"Wien",
    "sg:classifiers":[
        {
            "category":"Manufacturing",
            "subcategory":"Leather Goods",
            "type":"Manufacturing & Wholesale Goods"
        }
    ],
    "sg:phone":"+43 1 5053811",
    "sg:postcode":"1040",
    "sg:province":"Wien",
    "sg:tags":[
        "briefcase"
    ],
    "sg:website":"mrasek.at",
    "wof:name":"Mrasek GmbH",
    "wof:placetype":"venue"
},
  "geometry": {"coordinates":[16.3694725037,48.1894264221],"type":"Point"}
}