{
  "type": "Feature",
  "properties": {
    "iso:country":"AT",
    "sg:address":"Favoritenstr 204",
    "sg:city":"Wien",
    "sg:orig_category":"Tabaktrafiken",
    "sg:phone":"+43 1 6024803",
    "sg:postcode":"1100",
    "sg:province":"Wien",
    "wof:name":"Dreier Brigitte",
    "wof:placetype":"venue"
},
  "geometry": {"coordinates":[16.3822116852,48.1637268066],"type":"Point"}
}