{
  "type": "Feature",
  "properties": {
    "addr:full":"Ebentaler Strasse 133 Klagenfurt K\u00e4rnten 9020",
    "addr:housenumber":"133",
    "addr:postcode":"9020",
    "addr:street":"Ebentaler Strasse;Kaernten",
    "iso:country":"AT",
    "sg:address":"Ebentaler Strasse 133",
    "sg:city":"Klagenfurt",
    "sg:orig_category":"Drying Cabinets",
    "sg:phone":"+43 463 38480",
    "sg:postcode":"9020",
    "sg:province":"K\u00e4rnten",
    "wof:name":"J. Zimmer Maschinenbau Ges.m.b.H.",
    "wof:placetype":"venue"
},
  "geometry": {"coordinates":[14.3364639282,46.6160964966],"type":"Point"}
}