{
  "type": "Feature",
  "properties": {
    "iso:country":"AT",
    "sg:address":"Sylvester-Jordan-Str 5",
    "sg:city":"Axams",
    "sg:orig_category":"Architekten",
    "sg:phone":"+43 5234 688730",
    "sg:postcode":"6094",
    "sg:province":"Tirol",
    "wof:name":"Architekturb\u00fcro Dr Georg Cernusca",
    "wof:placetype":"venue"
},
  "geometry": {"coordinates":[11.2793731689,47.2312889099],"type":"Point"}
}