{
  "type": "Feature",
  "properties": {
    "iso:country":"AT",
    "sg:address":"Mariahilfer Str 192",
    "sg:city":"Wien",
    "sg:orig_category":"Notare",
    "sg:phone":"+43 1 8923762",
    "sg:postcode":"1150",
    "sg:province":"Wien",
    "wof:name":"Gratzl Johann Mag",
    "wof:placetype":"venue"
},
  "geometry": {"coordinates":[16.3268451691,48.1915245056],"type":"Point"}
}