{
  "type": "Feature",
  "properties": {
    "addr:full":"Taborstr 25 Wien Wien 1020",
    "addr:postcode":"1020",
    "iso:country":"AT",
    "sg:address":"Taborstr 25",
    "sg:city":"Wien",
    "sg:orig_category":"Textilreinigung",
    "sg:phone":"+43 1 2197790",
    "sg:postcode":"1020",
    "sg:province":"Wien",
    "wof:name":"ZWO 24 Textilpflege GmbH",
    "wof:placetype":"venue"
},
  "geometry": {"coordinates":[16.3805923462,48.2173881531],"type":"Point"}
}