{
  "type": "Feature",
  "properties": {
    "addr:full":"Bahnstrasse 11 Obersiebenbrunn Nieder\u00f6sterreich 2283",
    "addr:housenumber":"11",
    "addr:postcode":"2283",
    "addr:street":"Bahnstrasse;Niederoesterreich",
    "iso:country":"AT",
    "sg:address":"Bahnstrasse 11",
    "sg:city":"Obersiebenbrunn",
    "sg:classifiers":[
        {
            "category":"Utilities",
            "subcategory":"Natural Gas",
            "type":"Services"
        }
    ],
    "sg:phone":"+43 2286 2213",
    "sg:postcode":"2283",
    "sg:province":"Nieder\u00f6sterreich",
    "sg:tags":[
        "heater",
        "direct",
        "electric"
    ],
    "wof:name":"Johann Huber",
    "wof:placetype":"venue"
},
  "geometry": {"coordinates":[16.7019634247,48.2607002258],"type":"Point"}
}