{
  "type": "Feature",
  "properties": {
    "addr:full":"Breitenfurter Str 91 Wien Wien 1120",
    "addr:postcode":"1120",
    "addr:street":"Str 91",
    "iso:country":"AT",
    "sg:address":"Breitenfurter Str 91",
    "sg:city":"Wien",
    "sg:orig_category":"Steuerberatung",
    "sg:phone":"+43 4318 046314",
    "sg:postcode":"1120",
    "sg:province":"Wien",
    "wof:name":"Schema Wirtschaftstreuhand Steuerberatung GmbH & Co. KEG",
    "wof:placetype":"venue"
},
  "geometry": {"coordinates":[16.3182849884,48.1668128967],"type":"Point"}
}