{
  "type": "Feature",
  "properties": {
    "iso:country":"AT",
    "sg:address":"Bahnhofstrasse 48",
    "sg:city":"Schwarzach",
    "sg:classifiers":[
        {
            "category":"Manufacturing",
            "subcategory":"Rubber & Plastics",
            "type":"Manufacturing & Wholesale Goods"
        }
    ],
    "sg:phone":"+43 5572 58714",
    "sg:postcode":"6858",
    "sg:province":"Vorarlberg",
    "sg:tags":[
        "article"
    ],
    "wof:name":"Stadelmann Kunststoffe KG",
    "wof:placetype":"venue"
},
  "geometry": {"coordinates":[9.7551393509,47.4459686279],"type":"Point"}
}