{
  "type": "Feature",
  "properties": {
    "addr:full":"Seeauerweg 1 Linz Ober\u00f6sterreich 4020",
    "addr:housenumber":"1",
    "addr:postcode":"4020",
    "addr:street":"Seeauerweg",
    "iso:country":"AT",
    "sg:address":"Seeauerweg 1",
    "sg:city":"Linz",
    "sg:orig_category":"Volksschulen",
    "sg:phone":"+43 732 670016",
    "sg:postcode":"4020",
    "sg:province":"Ober\u00f6sterreich",
    "wof:name":"Volksschule 32 Keferfeldschule",
    "wof:placetype":"venue"
},
  "geometry": {"coordinates":[14.278670311,48.2757225037],"type":"Point"}
}