{
  "type": "Feature",
  "properties": {
    "addr:full":"Ellenbogen 210 Bezau Vorarlberg 6870",
    "addr:housenumber":"210",
    "addr:postcode":"6870",
    "addr:street":"Ellenbogen",
    "iso:country":"AT",
    "sg:address":"Ellenbogen 210",
    "sg:city":"Bezau",
    "sg:classifiers":[
        {
            "category":"Retail",
            "subcategory":"Driving School",
            "type":"Services"
        }
    ],
    "sg:phone":"+43 5514 2205",
    "sg:postcode":"6870",
    "sg:province":"Vorarlberg",
    "sg:tags":[
        "wood",
        "logging"
    ],
    "wof:name":"Rudolf Natter GmbH & Co KG",
    "wof:placetype":"venue"
},
  "geometry": {"coordinates":[9.8968400955,47.3801116943],"type":"Point"}
}