{
  "type": "Feature",
  "properties": {
    "iso:country":"AT",
    "sg:address":"Schenkelbachweg 32",
    "sg:city":"Wels",
    "sg:orig_category":"Unternehmensberatung",
    "sg:phone":"+43 7242 67855",
    "sg:postcode":"4600",
    "sg:province":"Ober\u00f6sterreich",
    "wof:name":"Enn\u00f6ckl Wolfgang Dr",
    "wof:placetype":"venue"
},
  "geometry": {"coordinates":[14.0406608582,48.1584472656],"type":"Point"}
}