{
  "type": "Feature",
  "properties": {
    "iso:country":"AT",
    "sg:address":"Blumauerg 2",
    "sg:city":"Steyr",
    "sg:orig_category":"Tabaktrafiken",
    "sg:phone":"+43 7252 42906",
    "sg:postcode":"4400",
    "sg:province":"Ober\u00f6sterreich",
    "wof:name":"Missbauer Andreas",
    "wof:placetype":"venue"
},
  "geometry": {"coordinates":[14.4183540344,48.0414810181],"type":"Point"}
}