{
  "type": "Feature",
  "properties": {
    "addr:full":"Hohenbrunner Strasse 5 St. Florian Ober\u00f6sterreich 4490",
    "addr:housenumber":"5",
    "addr:postcode":"4490",
    "addr:street":"Hohenbrunner Strasse",
    "iso:country":"AT",
    "sg:address":"Hohenbrunner Strasse 5",
    "sg:city":"St. Florian",
    "sg:classifiers":[
        {
            "category":"Wholesale",
            "subcategory":"Furniture",
            "type":"Manufacturing & Wholesale Goods"
        }
    ],
    "sg:phone":"+43 7224 8901",
    "sg:postcode":"4490",
    "sg:province":"Ober\u00f6sterreich",
    "sg:tags":[
        "agency",
        "timber"
    ],
    "sg:website":"leibl.at",
    "wof:name":"Leibl KG",
    "wof:placetype":"venue"
},
  "geometry": {"coordinates":[14.3439302444,48.1942443848],"type":"Point"}
}