{
  "type": "Feature",
  "properties": {
    "addr:full":"Bahnhofstrasse 15 Bludenz Vorarlberg 6700",
    "addr:housenumber":"15",
    "addr:postcode":"6700",
    "addr:street":"Bahnhofstrasse",
    "iso:country":"AT",
    "sg:address":"Bahnhofstrasse 15",
    "sg:city":"Bludenz",
    "sg:classifiers":[
        {
            "category":"Wholesale",
            "subcategory":"Medical Equipment & Supplies",
            "type":"Manufacturing & Wholesale Goods"
        }
    ],
    "sg:phone":"+43 5552 65369",
    "sg:postcode":"6700",
    "sg:province":"Vorarlberg",
    "sg:tags":[
        "device",
        "therapy-rehabilitation",
        "fitness-physical"
    ],
    "sg:website":"sanitaetshaus-werner.at",
    "wof:name":"Sanit\u00e4tshaus WERNER",
    "wof:placetype":"venue"
},
  "geometry": {"coordinates":[9.8176136017,47.1552886963],"type":"Point"}
}