{
  "type": "Feature",
  "properties": {
    "iso:country":"AT",
    "sg:address":"Ledererg. 35",
    "sg:city":"Wien",
    "sg:classifiers":[
        {
            "category":"Wholesale",
            "subcategory":"Machinery & Supplies",
            "type":"Manufacturing & Wholesale Goods"
        }
    ],
    "sg:phone":"+43 4314 038120",
    "sg:postcode":"1080",
    "sg:province":"Wien",
    "sg:tags":[
        "equipment",
        "precision"
    ],
    "wof:name":"LAIMER & CO GESMBH",
    "wof:placetype":"venue"
},
  "geometry": {"coordinates":[16.3480682373,48.2138442993],"type":"Point"}
}