{
  "type": "Feature",
  "properties": {
    "addr:full":"Richard Strauss-Str 18 Wien Wien 1230",
    "addr:housenumber":"18",
    "addr:postcode":"1230",
    "iso:country":"AT",
    "sg:address":"Richard Strauss-Str 18",
    "sg:city":"Wien",
    "sg:orig_category":"Tischlereien, Parkettschleifereien U -Versiegelungen, Fu\u00c3\u0178bodenschleifereien U -Versiegelung, Parket",
    "sg:phone":"+43 1 6163415",
    "sg:postcode":"1230",
    "sg:province":"Wien",
    "sg:website":"www.fpparkett.at",
    "wof:name":"FP Parkett - Technik GmbH",
    "wof:placetype":"venue"
},
  "geometry": {"coordinates":[16.3391094208,48.1431617737],"type":"Point"}
}