{
  "type": "Feature",
  "properties": {
    "addr:full":"Rainbergstr 14 Rauris Salzburg 5661",
    "addr:housenumber":"14",
    "addr:postcode":"5661",
    "addr:street":"Rainbergstr;Salzburg",
    "iso:country":"AT",
    "sg:address":"Rainbergstr 14",
    "sg:city":"Rauris",
    "sg:orig_category":"Pensionen / Privatzimmer",
    "sg:phone":"+43 6544 6310",
    "sg:postcode":"5661",
    "sg:province":"Salzburg",
    "wof:name":"Pension Lindenhof",
    "wof:placetype":"venue"
},
  "geometry": {"coordinates":[12.9975032806,47.2265663147],"type":"Point"}
}