{
  "type": "Feature",
  "properties": {
    "addr:full":"Innrain 107/3 Innsbruck Tirol 6020",
    "addr:housenumber":"107 / 3",
    "addr:postcode":"6020",
    "addr:street":"Innrain;Tirol",
    "iso:country":"AT",
    "sg:address":"Innrain 107/3",
    "sg:city":"Innsbruck",
    "sg:orig_category":"Massagen",
    "sg:phone":"+43 512 571202",
    "sg:postcode":"6020",
    "sg:province":"Tirol",
    "wof:name":"Mathoi Bettina",
    "wof:placetype":"venue"
},
  "geometry": {"coordinates":[11.3800573349,47.2582473755],"type":"Point"}
}