{
  "type": "Feature",
  "properties": {
    "iso:country":"AT",
    "sg:address":"Haydnstr 8",
    "sg:city":"Salzburg",
    "sg:orig_category":"Psychologen",
    "sg:phone":"+43 662 873021",
    "sg:postcode":"5020",
    "sg:province":"Salzburg",
    "wof:name":"Thaler Eva Maria Mag Dr",
    "wof:placetype":"venue"
},
  "geometry": {"coordinates":[13.0459251404,47.8065681458],"type":"Point"}
}