{
  "type": "Feature",
  "properties": {
    "addr:full":"Praterstrasse, 58 - 33 -  Wien Wien 1020",
    "addr:housenumber":"58 33",
    "addr:postcode":"1020",
    "addr:street":"Praterstrasse",
    "iso:country":"AT",
    "sg:address":"Praterstrasse, 58 - 33 - ",
    "sg:city":"Wien",
    "sg:classifiers":[
        {
            "category":"Professional",
            "subcategory":"Art Services",
            "type":"Services"
        }
    ],
    "sg:phone":"+43 1 2181338",
    "sg:postcode":"1020",
    "sg:province":"Wien",
    "sg:tags":[
        "export-import"
    ],
    "wof:name":"Malta Consulate Honorary",
    "wof:placetype":"venue"
},
  "geometry": {"coordinates":[16.3876094818,48.2162246704],"type":"Point"}
}