{
  "type": "Feature",
  "properties": {
    "addr:full":"Hiersdorf 58 Wartberg an der Krems Ober\u00f6sterreich 4552",
    "addr:housenumber":"58",
    "addr:postcode":"4552",
    "addr:street":"Hiersdorf",
    "iso:country":"AT",
    "sg:address":"Hiersdorf 58",
    "sg:city":"Wartberg an der Krems",
    "sg:classifiers":[
        {
            "category":"Banks & Credit Unions",
            "subcategory":"Investment Brokerage",
            "type":"Services"
        }
    ],
    "sg:phone":"+43 7587 76830",
    "sg:postcode":"4552",
    "sg:province":"Ober\u00f6sterreich",
    "sg:tags":[
        "ceiling",
        "covering"
    ],
    "sg:website":"mayr-raum.at",
    "wof:name":"Mayr - Raumgestaltung - Kachel\u00f6fen Ges.m.b.H.",
    "wof:placetype":"venue"
},
  "geometry": {"coordinates":[14.1169395447,47.9891700745],"type":"Point"}
}