{
  "type": "Feature",
  "properties": {
    "iso:country":"AT",
    "sg:address":"Blindeng 25",
    "sg:city":"Wien",
    "sg:classifiers":[
        {
            "category":"Shopping",
            "subcategory":"Party Supplies",
            "type":"Retail Goods"
        }
    ],
    "sg:phone":"+43 1 40941440",
    "sg:postcode":"1080",
    "sg:province":"Wien",
    "sg:tags":[
        "u",
        "lichtanlagen",
        "ton-"
    ],
    "wof:name":"GGEKKO Thomas Gehringer",
    "wof:placetype":"venue"
},
  "geometry": {"coordinates":[16.3399868011,48.2102394104],"type":"Point"}
}