{
  "type": "Feature",
  "properties": {
    "addr:full":"Gustav-Renker-Str 6 Villach K\u00e4rnten 9500",
    "addr:housenumber":"6",
    "addr:postcode":"9500",
    "addr:street":"Gustav-Renker-Str;Kaernten",
    "iso:country":"AT",
    "sg:address":"Gustav-Renker-Str 6",
    "sg:city":"Villach",
    "sg:orig_category":"Installationsunternehmen",
    "sg:phone":"+43 4242 54413",
    "sg:postcode":"9500",
    "sg:province":"K\u00e4rnten",
    "wof:name":"Teppan Franz GmbH",
    "wof:placetype":"venue"
},
  "geometry": {"coordinates":[13.8060922623,46.6130180359],"type":"Point"}
}