{
  "type": "Feature",
  "properties": {
    "iso:country":"AT",
    "sg:address":"W\u00e4hringer Str 138",
    "sg:city":"Wien",
    "sg:orig_category":"Damenmoden",
    "sg:phone":"+43 1 4702212",
    "sg:postcode":"1180",
    "sg:province":"Wien",
    "wof:name":"G G Internationale Mode",
    "wof:placetype":"venue"
},
  "geometry": {"coordinates":[16.3400878906,48.2271690369],"type":"Point"}
}