{
  "type": "Feature",
  "properties": {
    "addr:full":"Marktpl 4 Wagna Steiermark 8435",
    "addr:housenumber":"4",
    "addr:postcode":"8435",
    "addr:street":"Marktpl",
    "iso:country":"AT",
    "sg:address":"Marktpl 4",
    "sg:city":"Wagna",
    "sg:orig_category":"Gemeinden",
    "sg:phone":"+43 3452 825820",
    "sg:postcode":"8435",
    "sg:province":"Steiermark",
    "wof:name":"Marktgemeinde Wagna",
    "wof:placetype":"venue"
},
  "geometry": {"coordinates":[15.5572938919,46.7654647827],"type":"Point"}
}