{
  "type": "Feature",
  "properties": {
    "iso:country":"AT",
    "sg:address":"Clusiusg 9",
    "sg:city":"Wien",
    "sg:orig_category":"Maler, Anstreicher U Lackierer",
    "sg:phone":"+43 4313 1791540",
    "sg:postcode":"1090",
    "sg:province":"Wien",
    "wof:name":"Beilner Karl Heinz",
    "wof:placetype":"venue"
},
  "geometry": {"coordinates":[16.3647327423,48.2259368896],"type":"Point"}
}