{
  "type": "Feature",
  "properties": {
    "addr:full":"Amlacher Weg 19 Spittal an der Drau K\u00e4rnten 9800",
    "addr:housenumber":"19",
    "addr:postcode":"9800",
    "addr:street":"Amlacher Weg;Kaernten",
    "iso:country":"AT",
    "sg:address":"Amlacher Weg 19",
    "sg:city":"Spittal an der Drau",
    "sg:classifiers":[
        {
            "category":"Utilities",
            "subcategory":"Mobile Phone",
            "type":"Services"
        }
    ],
    "sg:phone":"+43 4762 2714",
    "sg:postcode":"9800",
    "sg:province":"K\u00e4rnten",
    "sg:tags":[
        "insulation",
        "blow-in"
    ],
    "wof:name":"Florian Bautechnic GesmbH",
    "wof:placetype":"venue"
},
  "geometry": {"coordinates":[13.486869812,46.8216552734],"type":"Point"}
}