{
  "type": "Feature",
  "properties": {
    "addr:full":"Wagerberg 7 Bad Waltersdorf Steiermark 8271",
    "addr:housenumber":"7",
    "addr:postcode":"8271",
    "addr:street":"Wagerberg",
    "iso:country":"AT",
    "sg:address":"Wagerberg 7",
    "sg:city":"Bad Waltersdorf",
    "sg:orig_category":"Pensionen / Privatzimmer",
    "sg:phone":"+43 4333 332543",
    "sg:postcode":"8271",
    "sg:province":"Steiermark",
    "wof:name":"Heschl Josef",
    "wof:placetype":"venue"
},
  "geometry": {"coordinates":[16.0317058563,47.167755127],"type":"Point"}
}