{
  "type": "Feature",
  "properties": {
    "addr:full":"Piaristeng 47 Wien Wien 1080",
    "addr:housenumber":"47",
    "addr:postcode":"1080",
    "addr:street":"Piaristeng",
    "iso:country":"AT",
    "sg:address":"Piaristeng 47",
    "sg:city":"Wien",
    "sg:orig_category":"Bauunternehmen",
    "sg:phone":"+43 4314 090698",
    "sg:postcode":"1080",
    "sg:province":"Wien",
    "wof:name":"EGM Erzetic Bau GmbH",
    "wof:placetype":"venue"
},
  "geometry": {"coordinates":[16.3500022888,48.2111778259],"type":"Point"}
}