{
  "type": "Feature",
  "properties": {
    "addr:full":"Nr 170 Prutz Tirol 6522",
    "addr:postcode":"6522",
    "addr:street":"Nr 170;Tirol",
    "iso:country":"AT",
    "sg:address":"Nr 170",
    "sg:city":"Prutz",
    "sg:orig_category":"Polytechnische Schulen",
    "sg:phone":"+43 5472 2455",
    "sg:postcode":"6522",
    "sg:province":"Tirol",
    "wof:name":"Polytechnische Schule",
    "wof:placetype":"venue"
},
  "geometry": {"coordinates":[10.6638202667,47.0765533447],"type":"Point"}
}