{
  "type": "Feature",
  "properties": {
    "addr:full":"Industriestr Eisenstadt Burgenland 7000",
    "addr:postcode":"7000",
    "iso:country":"AT",
    "sg:address":"Industriestr",
    "sg:city":"Eisenstadt",
    "sg:orig_category":"Speditionen",
    "sg:phone":"+43 2682 72783",
    "sg:postcode":"7000",
    "sg:province":"Burgenland",
    "wof:name":"Royalspeed SpeditionsgesmbH",
    "wof:placetype":"venue"
},
  "geometry": {"coordinates":[16.5406150818,47.8331184387],"type":"Point"}
}