{
  "type": "Feature",
  "properties": {
    "addr:full":"Obere Fellacher Str 36 Villach K\u00e4rnten 9500",
    "addr:housenumber":"36",
    "addr:postcode":"9500",
    "addr:street":"Obere Fellacher Str;Kaernten",
    "iso:country":"AT",
    "sg:address":"Obere Fellacher Str 36",
    "sg:city":"Villach",
    "sg:classifiers":[
        {
            "category":"Professional",
            "subcategory":"Management & Consulting",
            "type":"Services"
        }
    ],
    "sg:phone":"+43 4242 58010",
    "sg:postcode":"9500",
    "sg:province":"K\u00e4rnten",
    "wof:name":"Sorger Reinhard",
    "wof:placetype":"venue"
},
  "geometry": {"coordinates":[13.8155755997,46.6307296753],"type":"Point"}
}