{
  "type": "Feature",
  "properties": {
    "addr:full":"Gaswerkstr 103 Graz Steiermark 8020",
    "addr:housenumber":"103",
    "addr:postcode":"8020",
    "iso:country":"AT",
    "sg:address":"Gaswerkstr 103",
    "sg:city":"Graz",
    "sg:orig_category":"Immobilienverwaltungen",
    "sg:phone":"+43 316 583401",
    "sg:postcode":"8020",
    "sg:province":"Steiermark",
    "wof:name":"J.H. Beteiligungs- und Vermietungs GesmbH",
    "wof:placetype":"venue"
},
  "geometry": {"coordinates":[15.4034509659,47.0599517822],"type":"Point"}
}