{
  "type": "Feature",
  "properties": {
    "iso:country":"AT",
    "sg:address":"Blattlfeldstr 1/28",
    "sg:city":"Saalfelden am Steinernen Meer",
    "sg:orig_category":"\u00c3\u201erzte / F Allgemeinmedizin",
    "sg:phone":"+43 4365 82733430",
    "sg:postcode":"5760",
    "sg:province":"Salzburg",
    "wof:name":"Gradl Harald Dr",
    "wof:placetype":"venue"
},
  "geometry": {"coordinates":[12.8519220352,47.425491333],"type":"Point"}
}