{
  "type": "Feature",
  "properties": {
    "addr:full":"Nr 126 Klaus an der Pyhrnbahn Ober\u00f6sterreich 4564",
    "addr:postcode":"4564",
    "addr:street":"Nr;Klaus",
    "iso:country":"AT",
    "sg:address":"Nr 126",
    "sg:city":"Klaus an der Pyhrnbahn",
    "sg:orig_category":"Banken U Sparkassen",
    "sg:phone":"+43 4375 85381",
    "sg:postcode":"4564",
    "sg:province":"Ober\u00f6sterreich",
    "wof:name":"Raiffeisenbank Klaus regGenmbH",
    "wof:placetype":"venue"
},
  "geometry": {"coordinates":[14.1580152512,47.8330459595],"type":"Point"}
}