{
  "type": "Feature",
  "properties": {
    "addr:full":"Kaiser F Josef-Str 11 Innsbruck Tirol 6020",
    "addr:housenumber":"11",
    "addr:postcode":"6020",
    "addr:street":"Josef-Str;Tirol",
    "iso:country":"AT",
    "sg:address":"Kaiser F Josef-Str 11",
    "sg:city":"Innsbruck",
    "sg:orig_category":"\u00c3\u201erzte / F Allgemeinmedizin",
    "sg:phone":"+43 512 561151",
    "sg:postcode":"6020",
    "sg:province":"Tirol",
    "wof:name":"Handle Walter Dr",
    "wof:placetype":"venue"
},
  "geometry": {"coordinates":[11.38925457,47.2629051208],"type":"Point"}
}