{
  "type": "Feature",
  "properties": {
    "addr:full":"Sch\u00f6nbrunnerstra\u00dfe 61/B12 Vienna 1050",
    "addr:housenumber":"61 / b12",
    "addr:postcode":"1050",
    "addr:street":"Schoenbrunnerstrasse;Vienna",
    "iso:country":"AT",
    "sg:address":"Sch\u00f6nbrunnerstra\u00dfe 61/B12",
    "sg:city":"Vienna",
    "sg:classifiers":[
        {
            "category":"Professional",
            "subcategory":"Computer Services",
            "type":"Services"
        }
    ],
    "sg:postcode":"1050",
    "sg:tags":[
        "socialaggregation",
        "socialmedia",
        "socialnetwork",
        "tumblelog",
        "microblogging",
        "europe",
        "yeurope",
        "lifestream",
        "seedcamp",
        "seedcamp-2008"
    ],
    "sg:website":"http://soup.io",
    "wof:name":"Soup.io",
    "wof:placetype":"venue"
},
  "geometry": {"coordinates":[16.3556341,48.1911225],"type":"Point"}
}