{
  "type": "Feature",
  "properties": {
    "iso:country":"AT",
    "sg:address":"Hauptstrasse 2 ",
    "sg:city":"Spitz",
    "sg:classifiers":[
        {
            "category":"Home & Garden",
            "subcategory":"Kitchen Supply",
            "type":"Retail Goods"
        }
    ],
    "sg:phone":"+43 2713 2353",
    "sg:postcode":"3620",
    "sg:province":"Nieder\u00f6sterreich",
    "sg:tags":[
        "household",
        "electric",
        "cooker"
    ],
    "wof:name":"Ing. Gottfried Eibl",
    "wof:placetype":"venue"
},
  "geometry": {"coordinates":[15.4154644012,48.3647994995],"type":"Point"}
}