{
  "type": "Feature",
  "properties": {
    "addr:full":"Zehentstr 13 Sulz-R\u00f6this Vorarlberg 6832",
    "addr:housenumber":"13",
    "addr:postcode":"6832",
    "addr:street":"Zehentstr",
    "iso:country":"AT",
    "sg:address":"Zehentstr 13",
    "sg:city":"Sulz-R\u00f6this",
    "sg:orig_category":"Maler, Anstreicher U Lackierer",
    "sg:phone":"+43 4355 2247612",
    "sg:postcode":"6832",
    "sg:province":"Vorarlberg",
    "wof:name":"Watzenegger Manfred",
    "wof:placetype":"venue"
},
  "geometry": {"coordinates":[-76.7671127319,39.2538833618],"type":"Point"}
}