{
  "type": "Feature",
  "properties": {
    "addr:full":"Bilgeristr 18 Innsbruck-Igls Tirol 6080",
    "addr:housenumber":"18",
    "addr:postcode":"6080",
    "addr:street":"Bilgeristr",
    "iso:country":"AT",
    "sg:address":"Bilgeristr 18",
    "sg:city":"Innsbruck-Igls",
    "sg:classifiers":[
        {
            "category":"Park",
            "subcategory":"Provincial",
            "type":"Public Place"
        }
    ],
    "sg:phone":"+43 4351 2377383",
    "sg:postcode":"6080",
    "sg:province":"Tirol",
    "sg:tags":[
        "u",
        "ski-",
        "snowboardschulen"
    ],
    "wof:name":"Skischule Igls-Patscherkofel",
    "wof:placetype":"venue"
},
  "geometry": {"coordinates":[11.4128961563,47.2298698425],"type":"Point"}
}