{
  "type": "Feature",
  "properties": {
    "iso:country":"AT",
    "sg:address":"Ambrosig 10",
    "sg:city":"Oberwart",
    "sg:orig_category":"Biologische Produkte",
    "sg:phone":"+43 3352 32687",
    "sg:postcode":"7400",
    "sg:province":"Burgenland",
    "wof:name":"Oberwarter Bauernladen",
    "wof:placetype":"venue"
},
  "geometry": {"coordinates":[16.2131557465,47.2876167297],"type":"Point"}
}