{
  "type": "Feature",
  "properties": {
    "iso:country":"AT",
    "sg:address":"Wuhrweg 10",
    "sg:city":"Schruns",
    "sg:orig_category":"Pensionen / Privatzimmer",
    "sg:phone":"+43 5556 73328",
    "sg:postcode":"6780",
    "sg:province":"Vorarlberg",
    "wof:name":"Vergrassa",
    "wof:placetype":"venue"
},
  "geometry": {"coordinates":[9.9242219925,47.0725898743],"type":"Point"}
}