{
  "type": "Feature",
  "properties": {
    "addr:full":"Kaiser-Josef-Pl 24 Wels Ober\u00f6sterreich 4600",
    "addr:housenumber":"24",
    "addr:postcode":"4600",
    "addr:street":"Kaiser-Josef-Pl;Oberoesterreich",
    "iso:country":"AT",
    "sg:address":"Kaiser-Josef-Pl 24",
    "sg:city":"Wels",
    "sg:orig_category":"Ingenieurkonsulenten / Zivilingenieure",
    "sg:phone":"+43 664 4227011",
    "sg:postcode":"4600",
    "sg:province":"Ober\u00f6sterreich",
    "wof:name":"Marschallinger Wolfgang Dipl-Ing",
    "wof:placetype":"venue"
},
  "geometry": {"coordinates":[14.0215835571,48.1586875916],"type":"Point"}
}