{
  "type": "Feature",
  "properties": {
    "addr:full":"Langackerweg 26 Hard Vorarlberg 6971",
    "addr:housenumber":"26",
    "addr:postcode":"6971",
    "addr:street":"Langackerweg",
    "iso:country":"AT",
    "sg:address":"Langackerweg 26",
    "sg:city":"Hard",
    "sg:orig_category":"Tischlereien",
    "sg:phone":"+43 5574 76080",
    "sg:postcode":"6971",
    "sg:province":"Vorarlberg",
    "wof:name":"Jochum Peter",
    "wof:placetype":"venue"
},
  "geometry": {"coordinates":[9.690823555,47.4815177917],"type":"Point"}
}