{
  "type": "Feature",
  "properties": {
    "addr:full":"Kufsteiner Wald 27 Kufstein Tirol 6330",
    "addr:housenumber":"27",
    "addr:postcode":"6330",
    "addr:street":"Kufsteiner Wald;Tirol",
    "iso:country":"AT",
    "sg:address":"Kufsteiner Wald 27",
    "sg:city":"Kufstein",
    "sg:orig_category":"Beschichtungen",
    "sg:phone":"+43 5372 61717",
    "sg:postcode":"6330",
    "sg:province":"Tirol",
    "wof:name":"CBC Color Beschichtungs Center GesmbH",
    "wof:placetype":"venue"
},
  "geometry": {"coordinates":[12.1349201202,47.5561599731],"type":"Point"}
}