{
  "type": "Feature",
  "properties": {
    "iso:country":"AT",
    "sg:address":"Nr 17",
    "sg:city":"Ferndorf",
    "sg:orig_category":"Lebensmittel / Einzelhandel",
    "sg:phone":"+43 4245 2825",
    "sg:postcode":"9702",
    "sg:province":"K\u00e4rnten",
    "wof:name":"ADEG Aktiv Unterberger",
    "wof:placetype":"venue"
},
  "geometry": {"coordinates":[13.6259946823,46.7364959717],"type":"Point"}
}