{
  "type": "Feature",
  "properties": {
    "addr:full":"Heinestrasse 16 Wien Wien 1020",
    "addr:housenumber":"16",
    "addr:postcode":"1020",
    "addr:street":"Heinestrasse",
    "iso:country":"AT",
    "sg:address":"Heinestrasse 16",
    "sg:city":"Wien",
    "sg:classifiers":[
        {
            "category":"Shopping",
            "subcategory":"Computers & Home Electronics",
            "type":"Retail Goods"
        }
    ],
    "sg:phone":"+43 1 2162717",
    "sg:postcode":"1020",
    "sg:province":"Wien",
    "sg:tags":[
        "individual",
        "software"
    ],
    "sg:website":"procon.co.at",
    "wof:name":"Procon Data Datenverarbeitung Ges.m.b.H.",
    "wof:placetype":"venue"
},
  "geometry": {"coordinates":[16.3847637177,48.2207870483],"type":"Point"}
}