{
  "type": "Feature",
  "properties": {
    "addr:full":"Sackstr 17 Graz Steiermark 8010",
    "addr:housenumber":"17",
    "addr:postcode":"8010",
    "addr:street":"Sackstr",
    "iso:country":"AT",
    "sg:address":"Sackstr 17",
    "sg:city":"Graz",
    "sg:classifiers":[
        {
            "category":"Retail",
            "subcategory":"Storage",
            "type":"Services"
        }
    ],
    "sg:phone":"+43 316 8303350",
    "sg:postcode":"8010",
    "sg:province":"Steiermark",
    "sg:tags":[
        "archive"
    ],
    "wof:name":"Bild- und Tonarchiv im Landesmuseum Joanneum",
    "wof:placetype":"venue"
},
  "geometry": {"coordinates":[15.436085701,47.0726737976],"type":"Point"}
}