{
  "type": "Feature",
  "properties": {
    "addr:full":"Brunnenweg 11 Kirchdorf an der Krems Ober\u00f6sterreich 4560",
    "addr:housenumber":"11",
    "addr:postcode":"4560",
    "addr:street":"Brunnenweg",
    "iso:country":"AT",
    "sg:address":"Brunnenweg 11",
    "sg:city":"Kirchdorf an der Krems",
    "sg:orig_category":"Physiotherapie",
    "sg:phone":"+43 4375 8261662",
    "sg:postcode":"4560",
    "sg:province":"Ober\u00f6sterreich",
    "wof:name":"Physio Pro Aktiv",
    "wof:placetype":"venue"
},
  "geometry": {"coordinates":[14.1184892654,47.9012107849],"type":"Point"}
}