{
  "type": "Feature",
  "properties": {
    "addr:full":"Bahnstr 7 Pottenstein Nieder\u00f6sterreich 2563",
    "addr:housenumber":"7",
    "addr:postcode":"2563",
    "addr:street":"Bahnstr",
    "iso:country":"AT",
    "sg:address":"Bahnstr 7",
    "sg:city":"Pottenstein",
    "sg:orig_category":"Dachdeckereien",
    "sg:phone":"+43 2672 82427",
    "sg:postcode":"2563",
    "sg:province":"Nieder\u00f6sterreich",
    "wof:name":"Reiter M & Co GmbH",
    "wof:placetype":"venue"
},
  "geometry": {"coordinates":[16.0916671753,47.9597854614],"type":"Point"}
}