{
  "type": "Feature",
  "properties": {
    "addr:full":"Niederhofstr 3 Wien Wien 1120",
    "addr:housenumber":"3",
    "addr:postcode":"1120",
    "addr:street":"Niederhofstr",
    "iso:country":"AT",
    "sg:address":"Niederhofstr 3",
    "sg:city":"Wien",
    "sg:orig_category":"Friseure U Frisiersalons",
    "sg:phone":"+43 4318 128373",
    "sg:postcode":"1120",
    "sg:province":"Wien",
    "wof:name":"Dress 4hair - Coiffeur",
    "wof:placetype":"venue"
},
  "geometry": {"coordinates":[16.3363704681,48.1808509827],"type":"Point"}
}