{
  "type": "Feature",
  "properties": {
    "addr:full":"Schmiedgutstr 55 Bad Aussee Steiermark 8990",
    "addr:housenumber":"55",
    "addr:postcode":"8990",
    "addr:street":"Schmiedgutstr",
    "iso:country":"AT",
    "sg:address":"Schmiedgutstr 55",
    "sg:city":"Bad Aussee",
    "sg:orig_category":"Psychotherapie",
    "sg:phone":"+43 4366 45286446",
    "sg:postcode":"8990",
    "sg:province":"Steiermark",
    "wof:name":"Glaser Heide",
    "wof:placetype":"venue"
},
  "geometry": {"coordinates":[13.7704200745,47.6169471741],"type":"Point"}
}