{
  "type": "Feature",
  "properties": {
    "addr:full":"Prof.-August-Schreilechner-Weg 10 Mariapfarr Salzburg 5571",
    "addr:housenumber":"10",
    "addr:postcode":"5571",
    "addr:street":"Prof.-August-Schreilechner-Weg;Salzburg",
    "iso:country":"AT",
    "sg:address":"Prof.-August-Schreilechner-Weg 10",
    "sg:city":"Mariapfarr",
    "sg:orig_category":"Gemeinden",
    "sg:phone":"+43 4364 7382120",
    "sg:postcode":"5571",
    "sg:province":"Salzburg",
    "wof:name":"Gemeindeamt Mariapfarr",
    "wof:placetype":"venue"
},
  "geometry": {"coordinates":[13.743106842,47.1499786377],"type":"Point"}
}