{
  "type": "Feature",
  "properties": {
    "addr:full":"Maxquellg 2 Bad Ischl Ober\u00f6sterreich 4820",
    "addr:housenumber":"2",
    "addr:postcode":"4820",
    "addr:street":"Maxquellg",
    "iso:country":"AT",
    "sg:address":"Maxquellg 2",
    "sg:city":"Bad Ischl",
    "sg:orig_category":"Fahrschulen",
    "sg:phone":"+43 6132 23405",
    "sg:postcode":"4820",
    "sg:province":"Ober\u00f6sterreich",
    "wof:name":"Fahrschule Hausherr",
    "wof:placetype":"venue"
},
  "geometry": {"coordinates":[13.6281099319,47.7097206116],"type":"Point"}
}