{
  "type": "Feature",
  "properties": {
    "addr:full":"Dominicusweg 3 Salzburg Salzburg 5020",
    "addr:housenumber":"3",
    "addr:postcode":"5020",
    "addr:street":"Dominicusweg;Salzburg",
    "iso:country":"AT",
    "sg:address":"Dominicusweg 3",
    "sg:city":"Salzburg",
    "sg:orig_category":"Bekleidung / Erzeugung U Gro\u00c3\u0178handel",
    "sg:phone":"+43 4366 2820335",
    "sg:postcode":"5020",
    "sg:province":"Salzburg",
    "wof:name":"Krejci Hans",
    "wof:placetype":"venue"
},
  "geometry": {"coordinates":[13.0377616882,47.7804908752],"type":"Point"}
}