{
  "type": "Feature",
  "properties": {
    "iso:country":"AT",
    "sg:address":"Beheimg 23",
    "sg:city":"Wien",
    "sg:orig_category":"Steuerungstechnik",
    "sg:phone":"+43 1 4081823",
    "sg:postcode":"1170",
    "sg:province":"Wien",
    "wof:name":"AUS-TRONIC HandelsgesmbH",
    "wof:placetype":"venue"
},
  "geometry": {"coordinates":[16.3364696503,48.2195472717],"type":"Point"}
}