{
  "type": "Feature",
  "properties": {
    "addr:full":"Hauptstr 60 Tullnerbach Nieder\u00f6sterreich 3013",
    "addr:housenumber":"60",
    "addr:postcode":"3013",
    "addr:street":"Hauptstr",
    "iso:country":"AT",
    "sg:address":"Hauptstr 60",
    "sg:city":"Tullnerbach",
    "sg:orig_category":"Drogerien",
    "sg:phone":"+43 2233 56575",
    "sg:postcode":"3013",
    "sg:province":"Nieder\u00f6sterreich",
    "wof:name":"dm drogerie markt GmbH",
    "wof:placetype":"venue"
},
  "geometry": {"coordinates":[16.0923900604,48.1843605042],"type":"Point"}
}