{
  "type": "Feature",
  "properties": {
    "addr:full":"Sinzingerstrasse 2 Ach Ober\u00f6sterreich 5122",
    "addr:housenumber":"2",
    "addr:postcode":"5122",
    "addr:street":"Sinzingerstrasse;Ach Oberoesterreich",
    "iso:country":"AT",
    "sg:address":"Sinzingerstrasse 2",
    "sg:city":"Ach",
    "sg:classifiers":[
        {
            "category":"Building & Trades",
            "subcategory":"Equipment Rental",
            "type":"Services"
        }
    ],
    "sg:phone":"+43 7727 2282",
    "sg:postcode":"5122",
    "sg:province":"Ober\u00f6sterreich",
    "sg:tags":[
        "event"
    ],
    "wof:name":"Aloisia Sinzinger",
    "wof:placetype":"venue"
},
  "geometry": {"coordinates":[12.8356866837,48.1494560242],"type":"Point"}
}