{
  "type": "Feature",
  "properties": {
    "addr:full":"Deckerg 1 Wien Wien 1120",
    "addr:housenumber":"1",
    "addr:postcode":"1120",
    "addr:street":"Deckerg",
    "iso:country":"AT",
    "sg:address":"Deckerg 1",
    "sg:city":"Wien",
    "sg:orig_category":"Volksschulen",
    "sg:phone":"+43 1 8150181",
    "sg:postcode":"1120",
    "sg:province":"Wien",
    "wof:name":"Schulen d Stadt Wien",
    "wof:placetype":"venue"
},
  "geometry": {"coordinates":[16.3388156891,48.1782646179],"type":"Point"}
}