{
  "type": "Feature",
  "properties": {
    "addr:full":"Kroisgrabenweg 2 Frauental an der La\u00dfnitz Steiermark 8523",
    "addr:housenumber":"2",
    "addr:postcode":"8523",
    "addr:street":"Kroisgrabenweg",
    "iso:country":"AT",
    "sg:address":"Kroisgrabenweg 2",
    "sg:city":"Frauental an der La\u00dfnitz",
    "sg:orig_category":"Baumaschinenverleih",
    "sg:phone":"+43 4334 624222",
    "sg:postcode":"8523",
    "sg:province":"Steiermark",
    "wof:name":"Trummer Franziska",
    "wof:placetype":"venue"
},
  "geometry": {"coordinates":[15.2661094666,46.8022956848],"type":"Point"}
}