{
  "type": "Feature",
  "properties": {
    "addr:full":"Unterlungitz 99 Hartberg Steiermark 8230",
    "addr:housenumber":"99",
    "addr:postcode":"8230",
    "addr:street":"Unterlungitz",
    "iso:country":"AT",
    "sg:address":"Unterlungitz 99",
    "sg:city":"Hartberg",
    "sg:classifiers":[
        {
            "category":"Military Area",
            "subcategory":"Air Force Base",
            "type":"Public Place"
        }
    ],
    "sg:phone":"+43 3332 65390",
    "sg:postcode":"8230",
    "sg:province":"Steiermark",
    "sg:tags":[
        "candle",
        "ear"
    ],
    "sg:website":"htb.at/user/somo",
    "wof:name":"Wachswaren Kurt Dobrowa",
    "wof:placetype":"venue"
},
  "geometry": {"coordinates":[15.9727478027,47.2819519043],"type":"Point"}
}