{
  "type": "Feature",
  "properties": {
    "iso:country":"AT",
    "sg:address":"Marktpl 2",
    "sg:city":"Lambach",
    "sg:classifiers":[
        {
            "category":"Restaurant",
            "type":"Food & Drink"
        }
    ],
    "sg:phone":"+43 7245 20976",
    "sg:postcode":"4650",
    "sg:province":"Ober\u00f6sterreich",
    "sg:tags":[
        "pizzeria"
    ],
    "wof:name":"PIZZERIA GIOVANNI",
    "wof:placetype":"venue"
},
  "geometry": {"coordinates":[13.8740978241,48.0909881592],"type":"Point"}
}