{
  "type": "Feature",
  "properties": {
    "iso:country":"AT",
    "sg:address":"Eggenberg 17",
    "sg:city":"Vorchdorf",
    "sg:orig_category":"Montagen U Montagetechnik",
    "sg:phone":"+43 4376 147108",
    "sg:postcode":"4655",
    "sg:province":"Ober\u00f6sterreich",
    "wof:name":"Schlattner Montage GesmbH",
    "wof:placetype":"venue"
},
  "geometry": {"coordinates":[13.9219179153,47.9906425476],"type":"Point"}
}