{
  "type": "Feature",
  "properties": {
    "addr:full":"Goldschlagstr 117-119 Wien Wien 1150",
    "addr:housenumber":"117-119",
    "addr:postcode":"1150",
    "iso:country":"AT",
    "sg:address":"Goldschlagstr 117-119",
    "sg:city":"Wien",
    "sg:orig_category":"Dachdeckereien",
    "sg:phone":"+43 4319 823402",
    "sg:postcode":"1150",
    "sg:province":"Wien",
    "wof:name":"Reco Fassadenbau GesmbH",
    "wof:placetype":"venue"
},
  "geometry": {"coordinates":[16.3147125244,48.1948547363],"type":"Point"}
}