{
  "type": "Feature",
  "properties": {
    "addr:full":"Haidfeldstr 33 Leonding Ober\u00f6sterreich 4060",
    "addr:housenumber":"33",
    "addr:postcode":"4060",
    "addr:street":"Haidfeldstr",
    "iso:country":"AT",
    "sg:address":"Haidfeldstr 33",
    "sg:city":"Leonding",
    "sg:classifiers":[
        {
            "category":"Professional",
            "subcategory":"Computer Services",
            "type":"Services"
        }
    ],
    "sg:phone":"+43 4373 2673559",
    "sg:postcode":"4060",
    "sg:province":"Ober\u00f6sterreich",
    "sg:tags":[
        "software"
    ],
    "wof:name":"DELPHI Software West GesmbH",
    "wof:placetype":"venue"
},
  "geometry": {"coordinates":[14.2599143982,48.2564353943],"type":"Point"}
}