{
  "type": "Feature",
  "properties": {
    "addr:full":"Bahnhofstr 26 Bleiburg K\u00e4rnten 9150",
    "addr:housenumber":"26",
    "addr:postcode":"9150",
    "addr:street":"Bahnhofstr;Kaernten",
    "iso:country":"AT",
    "sg:address":"Bahnhofstr 26",
    "sg:city":"Bleiburg",
    "sg:orig_category":"Trachtenbekleidung",
    "sg:phone":"+43 4235 2132",
    "sg:postcode":"9150",
    "sg:province":"K\u00e4rnten",
    "wof:name":"Trachten Erika Komplettausstatter von Vereinen",
    "wof:placetype":"venue"
},
  "geometry": {"coordinates":[14.7975254059,46.5854682922],"type":"Point"}
}