{
  "type": "Feature",
  "properties": {
    "addr:full":"Bro\u00dfwaldengasse 12 Bregenz Vorarlberg 6900",
    "addr:housenumber":"12",
    "addr:postcode":"6900",
    "addr:street":"Brosswaldengasse",
    "iso:country":"AT",
    "sg:address":"Bro\u00dfwaldengasse 12",
    "sg:city":"Bregenz",
    "sg:classifiers":[
        {
            "category":"Professional",
            "subcategory":"Advertising",
            "type":"Services"
        }
    ],
    "sg:phone":"+43 5574 436480",
    "sg:postcode":"6900",
    "sg:province":"Vorarlberg",
    "sg:tags":[
        "agency"
    ],
    "sg:website":"konzett.com",
    "wof:name":"Konzett GmbH",
    "wof:placetype":"venue"
},
  "geometry": {"coordinates":[9.7331104279,47.5011291504],"type":"Point"}
}