{
  "type": "Feature",
  "properties": {
    "addr:full":"Hauptstr 97 Jetzelsdorf Nieder\u00f6sterreich 2053",
    "addr:housenumber":"97",
    "addr:postcode":"2053",
    "addr:street":"Hauptstr;Niederoesterreich",
    "iso:country":"AT",
    "sg:address":"Hauptstr 97",
    "sg:city":"Jetzelsdorf",
    "sg:orig_category":"Installationsunternehmen",
    "sg:phone":"+43 2944 8637",
    "sg:postcode":"2053",
    "sg:province":"Nieder\u00f6sterreich",
    "wof:name":"Rupp Herbert",
    "wof:placetype":"venue"
},
  "geometry": {"coordinates":[16.056646347,48.7062911987],"type":"Point"}
}