{
  "type": "Feature",
  "properties": {
    "addr:full":"Schulstr 5 Wartberg ob der Aist Ober\u00f6sterreich 4224",
    "addr:housenumber":"5",
    "addr:postcode":"4224",
    "addr:street":"Schulstr",
    "iso:country":"AT",
    "sg:address":"Schulstr 5",
    "sg:city":"Wartberg ob der Aist",
    "sg:orig_category":"Kinderbetreuung",
    "sg:phone":"+43 7236 21010",
    "sg:postcode":"4224",
    "sg:province":"Ober\u00f6sterreich",
    "wof:name":"Hort der Marktgemeinde Wartberg",
    "wof:placetype":"venue"
},
  "geometry": {"coordinates":[14.5105085373,48.3494987488],"type":"Point"}
}