{
  "type": "Feature",
  "properties": {
    "addr:full":"Brucknerstr 51 Graz Steiermark 8010",
    "addr:housenumber":"51",
    "addr:postcode":"8010",
    "addr:street":"Brucknerstr",
    "iso:country":"AT",
    "sg:address":"Brucknerstr 51",
    "sg:city":"Graz",
    "sg:orig_category":"Volksschulen",
    "sg:phone":"+43 316 472428",
    "sg:postcode":"8010",
    "sg:province":"Steiermark",
    "wof:name":"Volksschule Neufeld",
    "wof:placetype":"venue"
},
  "geometry": {"coordinates":[15.4608440399,47.0563392639],"type":"Point"}
}