{
  "type": "Feature",
  "properties": {
    "iso:country":"AT",
    "sg:address":"Kr\u00e4utlerweg 42",
    "sg:city":"Salzburg",
    "sg:classifiers":[
        {
            "category":"Professional",
            "subcategory":"Engineering",
            "type":"Services"
        }
    ],
    "sg:phone":"+43 4366 28249630",
    "sg:postcode":"5020",
    "sg:province":"Salzburg",
    "sg:tags":[
        "machine",
        "-",
        "mechanical"
    ],
    "wof:name":"RUDOLF HOLZMANN OHG",
    "wof:placetype":"venue"
},
  "geometry": {"coordinates":[13.0069570541,47.7780342102],"type":"Point"}
}