{
  "type": "Feature",
  "properties": {
    "addr:full":"Nr 124 Anger Steiermark 8184",
    "addr:postcode":"8184",
    "addr:street":"Nr 124",
    "iso:country":"AT",
    "sg:address":"Nr 124",
    "sg:city":"Anger",
    "sg:orig_category":"Blumeneinzelhandel",
    "sg:phone":"+43 4331 752275",
    "sg:postcode":"8184",
    "sg:province":"Steiermark",
    "wof:name":"Kubat Gerhard",
    "wof:placetype":"venue"
},
  "geometry": {"coordinates":[15.7057800293,47.2626419067],"type":"Point"}
}