{
  "type": "Feature",
  "properties": {
    "addr:full":"Leutascher Str 770 Seefeld in Tirol Tirol 6100",
    "addr:housenumber":"770",
    "addr:postcode":"6100",
    "addr:street":"Seefeld;Tirol",
    "iso:country":"AT",
    "sg:address":"Leutascher Str 770",
    "sg:city":"Seefeld in Tirol",
    "sg:orig_category":"Rettungsdienste",
    "sg:phone":"+43 5212 24000",
    "sg:postcode":"6100",
    "sg:province":"Tirol",
    "wof:name":"Rotes Kreuz \u00d6sterr Ortsstelle Seefeld",
    "wof:placetype":"venue"
},
  "geometry": {"coordinates":[11.1787643433,47.3372306824],"type":"Point"}
}