{
  "type": "Feature",
  "properties": {
    "iso:country":"AT",
    "sg:address":"Wiener Str 36",
    "sg:city":"Wiener Neustadt",
    "sg:orig_category":"Boutiquen",
    "sg:phone":"+43 2622 23610",
    "sg:postcode":"2700",
    "sg:province":"Nieder\u00f6sterreich",
    "wof:name":"TOM TAILOR Men",
    "wof:placetype":"venue"
},
  "geometry": {"coordinates":[16.2442512512,47.8153076172],"type":"Point"}
}