{
  "type": "Feature",
  "properties": {
    "addr:full":"Stadiong 10 Wien Wien 1010",
    "addr:housenumber":"10",
    "addr:postcode":"1010",
    "addr:street":"Stadiong",
    "iso:country":"AT",
    "sg:address":"Stadiong 10",
    "sg:city":"Wien",
    "sg:orig_category":"Bankomat-Standorte",
    "sg:phone":"+43 1 404340",
    "sg:postcode":"1010",
    "sg:province":"Wien",
    "wof:name":"Bankomat d IMMO-Bank AG",
    "wof:placetype":"venue"
},
  "geometry": {"coordinates":[16.3555698395,48.2094192505],"type":"Point"}
}