{
  "type": "Feature",
  "properties": {
    "iso:country":"AT",
    "sg:address":"Hauptstr 20",
    "sg:city":"Hieflau",
    "sg:orig_category":"Tabaktrafiken",
    "sg:phone":"+43 3634 238",
    "sg:postcode":"8920",
    "sg:province":"Steiermark",
    "wof:name":"Wei\u00df Helga",
    "wof:placetype":"venue"
},
  "geometry": {"coordinates":[14.7455244064,47.6050643921],"type":"Point"}
}