{
  "type": "Feature",
  "properties": {
    "iso:country":"AT",
    "sg:address":"Hauptstr 4 EKZ",
    "sg:city":"Seekirchen am Wallersee",
    "sg:orig_category":"Drogerien",
    "sg:phone":"+43 4362 1230277",
    "sg:postcode":"5201",
    "sg:province":"Salzburg",
    "wof:name":"dm drogerie markt GmbH",
    "wof:placetype":"venue"
},
  "geometry": {"coordinates":[13.1259384155,47.8936538696],"type":"Point"}
}