{
  "type": "Feature",
  "properties": {
    "addr:full":"Burgg 1 Schwaz Tirol 6130",
    "addr:housenumber":"1",
    "addr:postcode":"6130",
    "addr:street":"Burgg;Tirol",
    "iso:country":"AT",
    "sg:address":"Burgg 1",
    "sg:city":"Schwaz",
    "sg:orig_category":"Bars-Cafes",
    "sg:phone":"+43 5242 65360",
    "sg:postcode":"6130",
    "sg:province":"Tirol",
    "wof:name":"Bar-Cafe Luce",
    "wof:placetype":"venue"
},
  "geometry": {"coordinates":[11.7083187103,47.344707489],"type":"Point"}
}