{
  "type": "Feature",
  "properties": {
    "addr:full":"B\u00f6hlerg 18 Sollenau Nieder\u00f6sterreich 2601",
    "addr:housenumber":"18",
    "addr:postcode":"2601",
    "addr:street":"Boehlerg",
    "iso:country":"AT",
    "sg:address":"B\u00f6hlerg 18",
    "sg:city":"Sollenau",
    "sg:orig_category":"Maler, Anstreicher U Lackierer",
    "sg:phone":"+43 4326 2862450",
    "sg:postcode":"2601",
    "sg:province":"Nieder\u00f6sterreich",
    "wof:name":"Kopeszky Arnold",
    "wof:placetype":"venue"
},
  "geometry": {"coordinates":[16.2494049072,47.8965682983],"type":"Point"}
}