{
  "type": "Feature",
  "properties": {
    "iso:country":"AT",
    "sg:address":"Im S\u00fcdpark 194",
    "sg:city":"Linz",
    "sg:orig_category":"Bakery Concepts",
    "sg:phone":"+43 732 305707",
    "sg:postcode":"4030",
    "sg:province":"Ober\u00f6sterreich",
    "wof:name":"B\u00c4KO-\u00d6STERREICH Gro\u00dfeinkauf der B\u00e4cker und Konditoren reg.Gen.m.b.H.",
    "wof:placetype":"venue"
},
  "geometry": {"coordinates":[14.3069601059,48.2325248718],"type":"Point"}
}