{
  "type": "Feature",
  "properties": {
    "addr:full":"Wiener Strasse 6  Baden Nieder\u00f6sterreich 2500",
    "addr:housenumber":"6",
    "addr:postcode":"2500",
    "addr:street":"Wiener Strasse;Niederoesterreich",
    "iso:country":"AT",
    "sg:address":"Wiener Strasse 6 ",
    "sg:city":"Baden",
    "sg:classifiers":[
        {
            "category":"Building & Trades",
            "subcategory":"Plumbing",
            "type":"Services"
        }
    ],
    "sg:phone":"+43 2252 89719",
    "sg:postcode":"2500",
    "sg:province":"Nieder\u00f6sterreich",
    "sg:tags":[
        "supraregional",
        "gas"
    ],
    "wof:name":"Peter Novoszad",
    "wof:placetype":"venue"
},
  "geometry": {"coordinates":[16.2419567108,48.009727478],"type":"Point"}
}