{
  "type": "Feature",
  "properties": {
    "addr:full":"Nr 13 Mariapfarr Salzburg 5571",
    "addr:postcode":"5571",
    "addr:street":"Nr 13;Salzburg",
    "iso:country":"AT",
    "sg:address":"Nr 13",
    "sg:city":"Mariapfarr",
    "sg:orig_category":"Pensionen / Privatzimmer",
    "sg:phone":"+43 6473 7013",
    "sg:postcode":"5571",
    "sg:province":"Salzburg",
    "wof:name":"Gruber Robert",
    "wof:placetype":"venue"
},
  "geometry": {"coordinates":[166.9221496582,-0.5282999873],"type":"Point"}
}