{
  "type": "Feature",
  "properties": {
    "addr:full":"Amraser Str 24B Innsbruck Tirol 6020",
    "addr:housenumber":"24b",
    "addr:postcode":"6020",
    "addr:street":"Amraser Str;Tirol",
    "iso:country":"AT",
    "sg:address":"Amraser Str 24B",
    "sg:city":"Innsbruck",
    "sg:orig_category":"Lebensmittel / Einzelhandel",
    "sg:phone":"+43 512 589473",
    "sg:postcode":"6020",
    "sg:province":"Tirol",
    "wof:name":"Dany's Snack \u00f6sterreich GmbH",
    "wof:placetype":"venue"
},
  "geometry": {"coordinates":[11.4225673676,47.2613677979],"type":"Point"}
}