{
  "type": "Feature",
  "properties": {
    "iso:country":"AT",
    "sg:address":"Loferer Str 27",
    "sg:city":"Saalfelden am Steinernen Meer",
    "sg:orig_category":"Schlankheitsinstitute",
    "sg:phone":"+43 6582 75747",
    "sg:postcode":"5760",
    "sg:province":"Salzburg",
    "wof:name":"Figuretics Mag Jacek Stalmach",
    "wof:placetype":"venue"
},
  "geometry": {"coordinates":[12.8467054367,47.4283180237],"type":"Point"}
}