{
  "type": "Feature",
  "properties": {
    "iso:country":"AT",
    "sg:address":"Bahnstrasse 42",
    "sg:city":"Theresienfeld",
    "sg:classifiers":[
        {
            "category":"Manufacturing",
            "subcategory":"Glass & Minerals",
            "type":"Manufacturing & Wholesale Goods"
        }
    ],
    "sg:phone":"+43 2622 71960",
    "sg:postcode":"2604",
    "sg:province":"Nieder\u00f6sterreich",
    "sg:tags":[
        "cutter"
    ],
    "wof:name":"Zimmermann Bauglas GmbH",
    "wof:placetype":"venue"
},
  "geometry": {"coordinates":[16.2331447601,47.8623275757],"type":"Point"}
}