{
  "type": "Feature",
  "properties": {
    "addr:full":"Grazer Str 184 P\u00f6llau Steiermark 8225",
    "addr:housenumber":"184",
    "addr:postcode":"8225",
    "addr:street":"Poellau Steiermark",
    "iso:country":"AT",
    "sg:address":"Grazer Str 184",
    "sg:city":"P\u00f6llau",
    "sg:orig_category":"Werbeagenturen",
    "sg:phone":"+43 3335 46653",
    "sg:postcode":"8225",
    "sg:province":"Steiermark",
    "wof:name":"Werbeagentur Maiq - Kaufmann Michael",
    "wof:placetype":"venue"
},
  "geometry": {"coordinates":[15.8337945938,47.301990509],"type":"Point"}
}