{
  "type": "Feature",
  "properties": {
    "addr:full":"Marcusstr. 8-10 Freistadt Ober\u00f6sterreich 4240",
    "addr:housenumber":"8-10",
    "addr:postcode":"4240",
    "iso:country":"AT",
    "sg:address":"Marcusstr. 8-10",
    "sg:city":"Freistadt",
    "sg:classifiers":[
        {
            "category":"Professional",
            "subcategory":"Advertising",
            "type":"Services"
        }
    ],
    "sg:phone":"+43 4379 42776770",
    "sg:postcode":"4240",
    "sg:province":"Ober\u00f6sterreich",
    "sg:tags":[
        "communication",
        "medium"
    ],
    "wof:name":"HAPPY-FOTO GMBH & CO KG",
    "wof:placetype":"venue"
},
  "geometry": {"coordinates":[14.5048284531,48.498790741],"type":"Point"}
}