{
  "type": "Feature",
  "properties": {
    "addr:full":"Manhartstr 85 Stockerau Nieder\u00f6sterreich 2000",
    "addr:housenumber":"85",
    "addr:postcode":"2000",
    "addr:street":"Manhartstr",
    "iso:country":"AT",
    "sg:address":"Manhartstr 85",
    "sg:city":"Stockerau",
    "sg:orig_category":"Maschinenhandel",
    "sg:phone":"+43 2266 64041",
    "sg:postcode":"2000",
    "sg:province":"Nieder\u00f6sterreich",
    "wof:name":"Augustin Otto",
    "wof:placetype":"venue"
},
  "geometry": {"coordinates":[16.2157974243,48.3893737793],"type":"Point"}
}