{
  "type": "Feature",
  "properties": {
    "addr:full":"Hans Gasser-Pl 6B Villach K\u00e4rnten 9500",
    "addr:housenumber":"6b",
    "addr:postcode":"9500",
    "addr:street":"Gasser-Pl;Kaernten",
    "iso:country":"AT",
    "sg:address":"Hans Gasser-Pl 6B",
    "sg:city":"Villach",
    "sg:orig_category":"Friseure U Frisiersalons",
    "sg:phone":"+43 4242 56509",
    "sg:postcode":"9500",
    "sg:province":"K\u00e4rnten",
    "wof:name":"Frisiersalon Stauber",
    "wof:placetype":"venue"
},
  "geometry": {"coordinates":[13.8423032761,46.6123504639],"type":"Point"}
}