{
  "type": "Feature",
  "properties": {
    "addr:full":"Dorf 34 Aldrans Tirol 6071",
    "addr:housenumber":"34",
    "addr:postcode":"6071",
    "addr:street":"Dorf;Tirol",
    "iso:country":"AT",
    "sg:address":"Dorf 34",
    "sg:city":"Aldrans",
    "sg:orig_category":"Abfallentsorgung U -Verwertung",
    "sg:phone":"+43 512 361576",
    "sg:postcode":"6071",
    "sg:province":"Tirol",
    "wof:name":"Abfallbeseitigungsverband-S\u00fcd\u00f6st",
    "wof:placetype":"venue"
},
  "geometry": {"coordinates":[11.4461297989,47.2511863708],"type":"Point"}
}