{
  "type": "Feature",
  "properties": {
    "addr:full":"Pillersdorf 55 Schrattenthal Nieder\u00f6sterreich 2073",
    "addr:housenumber":"55",
    "addr:postcode":"2073",
    "addr:street":"Pillersdorf",
    "iso:country":"AT",
    "sg:address":"Pillersdorf 55",
    "sg:city":"Schrattenthal",
    "sg:classifiers":[
        {
            "category":"Shopping",
            "subcategory":"Used Merchandise",
            "type":"Retail Goods"
        }
    ],
    "sg:phone":"+43 2946 8234",
    "sg:postcode":"2073",
    "sg:province":"Nieder\u00f6sterreich",
    "sg:tags":[
        "agricultural",
        "machinery"
    ],
    "wof:name":"Karl Peschka",
    "wof:placetype":"venue"
},
  "geometry": {"coordinates":[15.9088430405,48.7167282104],"type":"Point"}
}