{
  "type": "Feature",
  "properties": {
    "addr:full":"Nr 1 Liebenfels K\u00e4rnten 9556",
    "addr:postcode":"9556",
    "addr:street":"Nr;Kaernten",
    "iso:country":"AT",
    "sg:address":"Nr 1",
    "sg:city":"Liebenfels",
    "sg:orig_category":"Bildhauer",
    "sg:phone":"+43 4215 2307",
    "sg:postcode":"9556",
    "sg:province":"K\u00e4rnten",
    "sg:website":"stracke-art.com",
    "wof:name":"Stracke Wolfgang Mag",
    "wof:placetype":"venue"
},
  "geometry": {"coordinates":[14.2895402908,46.7378463745],"type":"Point"}
}