{
  "type": "Feature",
  "properties": {
    "iso:country":"AT",
    "sg:address":"G\u00f6lsentalstr 49",
    "sg:city":"St. Veit an der G\u00f6lsen",
    "sg:orig_category":"Tabaktrafiken",
    "sg:phone":"+43 4327 632606",
    "sg:postcode":"3161",
    "sg:province":"Nieder\u00f6sterreich",
    "wof:name":"Hinterh\u00f6lzl Gabriele",
    "wof:placetype":"venue"
},
  "geometry": {"coordinates":[15.6629753113,48.0460968018],"type":"Point"}
}