{
  "type": "Feature",
  "properties": {
    "addr:full":"Pestalozzig 3 Wien Wien 1010",
    "addr:housenumber":"3",
    "addr:postcode":"1010",
    "addr:street":"Pestalozzig",
    "iso:country":"AT",
    "sg:address":"Pestalozzig 3",
    "sg:city":"Wien",
    "sg:orig_category":"Datenverarbeitung",
    "sg:phone":"+43 5 010012231",
    "sg:postcode":"1010",
    "sg:province":"Wien",
    "wof:name":"EB-IT Erste Bank Informations-Technologie GesmbH",
    "wof:placetype":"venue"
},
  "geometry": {"coordinates":[16.3757038116,48.2015304565],"type":"Point"}
}