{
  "type": "Feature",
  "properties": {
    "iso:country":"AT",
    "sg:address":"Ottakringer Str. 34-36 ",
    "sg:city":"Wien",
    "sg:classifiers":[
        {
            "category":"Travel",
            "subcategory":"Travel Agent",
            "type":"Entertainment"
        }
    ],
    "sg:phone":"+43 4314 0455",
    "sg:postcode":"1170",
    "sg:province":"Wien",
    "sg:tags":[
        "business"
    ],
    "wof:name":"BARCINO HOTEL BETRIEBS GMBH",
    "wof:placetype":"venue"
},
  "geometry": {"coordinates":[16.3366394043,48.2149925232],"type":"Point"}
}