{
  "type": "Feature",
  "properties": {
    "addr:full":"Glorietteg. 8  Wien Wien 1130",
    "addr:housenumber":"8",
    "addr:postcode":"1130",
    "addr:street":"Glorietteg.",
    "iso:country":"AT",
    "sg:address":"Glorietteg. 8 ",
    "sg:city":"Wien",
    "sg:classifiers":[
        {
            "category":"Building & Trades",
            "subcategory":"Construction",
            "type":"Services"
        }
    ],
    "sg:phone":"+43 4318 776629",
    "sg:postcode":"1130",
    "sg:province":"Wien",
    "sg:tags":[
        "work",
        "public"
    ],
    "wof:name":"INSOND GESMBH",
    "wof:placetype":"venue"
},
  "geometry": {"coordinates":[16.2960395813,48.1816673279],"type":"Point"}
}