{
  "type": "Feature",
  "properties": {
    "addr:full":"Kirchenweg 38/16 St. P\u00f6lten Nieder\u00f6sterreich 3100",
    "addr:housenumber":"38 / 16",
    "addr:postcode":"3100",
    "addr:street":"Kirchenweg;St. Poelten",
    "iso:country":"AT",
    "sg:address":"Kirchenweg 38/16",
    "sg:city":"St. P\u00f6lten",
    "sg:orig_category":"Datenverarbeitung",
    "sg:phone":"+43 4369 910912106",
    "sg:postcode":"3100",
    "sg:province":"Nieder\u00f6sterreich",
    "wof:name":"Voak Pierre",
    "wof:placetype":"venue"
},
  "geometry": {"coordinates":[15.6240940094,48.2076377869],"type":"Point"}
}