{
  "type": "Feature",
  "properties": {
    "iso:country":"AT",
    "sg:address":"Wieslweg 5",
    "sg:city":"Saalbach",
    "sg:classifiers":[
        {
            "category":"Taxi",
            "type":"Transportation"
        }
    ],
    "sg:phone":"+43 6541 7163",
    "sg:postcode":"5753",
    "sg:province":"Salzburg",
    "sg:tags":[
        "personentransporte",
        "u"
    ],
    "wof:name":"Schmidhofer Taxi",
    "wof:placetype":"venue"
},
  "geometry": {"coordinates":[12.6367301941,47.3899307251],"type":"Point"}
}