{
  "type": "Feature",
  "properties": {
    "addr:full":"Seilerg 12 Innsbruck Tirol 6020",
    "addr:housenumber":"12",
    "addr:postcode":"6020",
    "addr:street":"Seilerg;Tirol",
    "iso:country":"AT",
    "sg:address":"Seilerg 12",
    "sg:city":"Innsbruck",
    "sg:classifiers":[
        {
            "category":"Restaurant",
            "type":"Food & Drink"
        }
    ],
    "sg:phone":"+43 4351 2583046",
    "sg:postcode":"6020",
    "sg:province":"Tirol",
    "wof:name":"Papa Joe's Grill Cantina Bar",
    "wof:placetype":"venue"
},
  "geometry": {"coordinates":[11.3918323517,47.2677955627],"type":"Point"}
}