{
  "type": "Feature",
  "properties": {
    "addr:full":"Gartenweg 1 Traismauer Nieder\u00f6sterreich 3133",
    "addr:housenumber":"1",
    "addr:postcode":"3133",
    "addr:street":"Gartenweg",
    "iso:country":"AT",
    "sg:address":"Gartenweg 1",
    "sg:city":"Traismauer",
    "sg:orig_category":"Schlossereien",
    "sg:phone":"+43 4327 838461",
    "sg:postcode":"3133",
    "sg:province":"Nieder\u00f6sterreich",
    "wof:name":"Maurer Schlosserei KEG",
    "wof:placetype":"venue"
},
  "geometry": {"coordinates":[15.7121982574,48.3675384521],"type":"Point"}
}