{
  "type": "Feature",
  "properties": {
    "addr:full":"Nr 1 M\u00fcrzsteg Steiermark 8693",
    "addr:postcode":"8693",
    "addr:street":"Nr",
    "iso:country":"AT",
    "sg:address":"Nr 1",
    "sg:city":"M\u00fcrzsteg",
    "sg:orig_category":"Waren Aller Art",
    "sg:phone":"+43 4338 592117",
    "sg:postcode":"8693",
    "sg:province":"Steiermark",
    "wof:name":"Kiefer GmbH",
    "wof:placetype":"venue"
},
  "geometry": {"coordinates":[15.4915561676,47.6754341125],"type":"Point"}
}