{
  "type": "Feature",
  "properties": {
    "addr:full":"Gewerbepark 2 Imst Tirol 6460",
    "addr:housenumber":"2",
    "addr:postcode":"6460",
    "addr:street":"Gewerbepark;Tirol",
    "iso:country":"AT",
    "sg:address":"Gewerbepark 2",
    "sg:city":"Imst",
    "sg:orig_category":"Autohandel",
    "sg:phone":"+43 5412 66000",
    "sg:postcode":"6460",
    "sg:province":"Tirol",
    "wof:name":"Autohaus Goidinger GmbH",
    "wof:placetype":"venue"
},
  "geometry": {"coordinates":[10.7439823151,47.2177314758],"type":"Point"}
}