{
  "type": "Feature",
  "properties": {
    "iso:country":"AT",
    "sg:address":"Brunner Str. 44-50",
    "sg:classifiers":[
        {
            "category":"Banks & Credit Unions",
            "subcategory":"Financial Services",
            "type":"Services"
        }
    ],
    "sg:phone":"+43 4318 6631",
    "sg:postcode":"1231",
    "sg:tags":[
        "banking",
        "finance",
        "insurance"
    ],
    "wof:name":"MAN SONDERFAHRZEUGE AG",
    "wof:placetype":"venue"
},
  "geometry": {"coordinates":[16.2934799194,48.1539306641],"type":"Point"}
}