{
  "type": "Feature",
  "properties": {
    "addr:full":"Dr Ludwig Leber-Str 5 Mariazell Steiermark 8630",
    "addr:housenumber":"5",
    "addr:postcode":"8630",
    "addr:street":"Dr;Leber-Str",
    "iso:country":"AT",
    "sg:address":"Dr Ludwig Leber-Str 5",
    "sg:city":"Mariazell",
    "sg:orig_category":"Autoreparatur",
    "sg:phone":"+43 3882 2535",
    "sg:postcode":"8630",
    "sg:province":"Steiermark",
    "wof:name":"Fleischmann Kurt",
    "wof:placetype":"venue"
},
  "geometry": {"coordinates":[15.315735817,47.7730484009],"type":"Point"}
}