{
  "type": "Feature",
  "properties": {
    "addr:full":"Kupelwieserg 10/5 Wien Wien 1130",
    "addr:housenumber":"10 / 5",
    "addr:postcode":"1130",
    "addr:street":"Kupelwieserg",
    "iso:country":"AT",
    "sg:address":"Kupelwieserg 10/5",
    "sg:city":"Wien",
    "sg:classifiers":[
        {
            "category":"Professional",
            "subcategory":"Computer Services",
            "type":"Services"
        }
    ],
    "sg:phone":"+43 1 87762370",
    "sg:postcode":"1130",
    "sg:province":"Wien",
    "sg:tags":[
        "software"
    ],
    "wof:name":"Krisch Christian",
    "wof:placetype":"venue"
},
  "geometry": {"coordinates":[16.2922420502,48.1849441528],"type":"Point"}
}