{
  "type": "Feature",
  "properties": {
    "addr:full":"Sagl 43 Telfs Tirol 6410",
    "addr:housenumber":"43",
    "addr:postcode":"6410",
    "addr:street":"Tirol",
    "iso:country":"AT",
    "sg:address":"Sagl 43",
    "sg:city":"Telfs",
    "sg:orig_category":"Holzhandel",
    "sg:phone":"+43 5262 62150",
    "sg:postcode":"6410",
    "sg:province":"Tirol",
    "wof:name":"Neuner Georg",
    "wof:placetype":"venue"
},
  "geometry": {"coordinates":[11.0812282562,47.3138275146],"type":"Point"}
}