{
  "type": "Feature",
  "properties": {
    "addr:full":"Marcusstr 4 Wels Ober\u00f6sterreich 4600",
    "addr:housenumber":"4",
    "addr:postcode":"4600",
    "addr:street":"Marcusstr;Oberoesterreich",
    "iso:country":"AT",
    "sg:address":"Marcusstr 4",
    "sg:city":"Wels",
    "sg:orig_category":"Autobusunternehmen",
    "sg:phone":"+43 7242 416260",
    "sg:postcode":"4600",
    "sg:province":"Ober\u00f6sterreich",
    "wof:name":"sabtours Buscenter Nfg GmbH & Co KG",
    "wof:placetype":"venue"
},
  "geometry": {"coordinates":[14.0522441864,48.1603431702],"type":"Point"}
}