{
  "type": "Feature",
  "properties": {
    "iso:country":"AT",
    "sg:address":"Carl v Linde-Str 12",
    "sg:city":"Lambach",
    "sg:orig_category":"Holzbearbeitungsmaschinen U -Werkzeuge",
    "sg:phone":"+43 7245 2300",
    "sg:postcode":"4650",
    "sg:province":"Ober\u00f6sterreich",
    "sg:website":"www.ottpaul.com",
    "wof:name":"Ott Paul GesmbH",
    "wof:placetype":"venue"
},
  "geometry": {"coordinates":[13.8729896545,48.0909690857],"type":"Point"}
}