{
  "type": "Feature",
  "properties": {
    "addr:full":"Nr 124 Wagrain Salzburg 5602",
    "addr:postcode":"5602",
    "addr:street":"Nr 124;Salzburg",
    "iso:country":"AT",
    "sg:address":"Nr 124",
    "sg:city":"Wagrain",
    "sg:orig_category":"Tourismusinformation U -Organisationen",
    "sg:phone":"+43 4364 18206",
    "sg:postcode":"5602",
    "sg:province":"Salzburg",
    "wof:name":"Tourismusverband Kleinarl",
    "wof:placetype":"venue"
},
  "geometry": {"coordinates":[13.2964773178,47.3332366943],"type":"Point"}
}