{
  "type": "Feature",
  "properties": {
    "addr:full":"Kaiser-Josef-Pl Stand 9 Graz Steiermark 8010",
    "addr:housenumber":"9",
    "addr:postcode":"8010",
    "addr:street":"Stand",
    "iso:country":"AT",
    "sg:address":"Kaiser-Josef-Pl Stand 9",
    "sg:city":"Graz",
    "sg:orig_category":"Fleischhauereien",
    "sg:phone":"+43 316 826205",
    "sg:postcode":"8010",
    "sg:province":"Steiermark",
    "wof:name":"Rinner Fleischwaren GmbH",
    "wof:placetype":"venue"
},
  "geometry": {"coordinates":[15.4461050034,47.0682106018],"type":"Point"}
}