{
  "type": "Feature",
  "properties": {
    "iso:country":"AT",
    "sg:address":"Halleiner Landesstr 99",
    "sg:city":"Oberalm",
    "sg:orig_category":"Zahntechnische Laboratorien",
    "sg:phone":"+43 6245 854270",
    "sg:postcode":"5411",
    "sg:province":"Salzburg",
    "wof:name":"Dentaltechnik L O S Meisterbetrieb GesmbH",
    "wof:placetype":"venue"
},
  "geometry": {"coordinates":[13.0925598145,47.707649231],"type":"Point"}
}