{
  "type": "Feature",
  "properties": {
    "addr:full":"Platzl 112a Leutasch Tirol 6105",
    "addr:housenumber":"112a",
    "addr:postcode":"6105",
    "addr:street":"Platzl;Tirol",
    "iso:country":"AT",
    "sg:address":"Platzl 112a",
    "sg:city":"Leutasch",
    "sg:orig_category":"Tischlereien",
    "sg:phone":"+43 5214 6833",
    "sg:postcode":"6105",
    "sg:province":"Tirol",
    "wof:name":"Stocker Hannes",
    "wof:placetype":"venue"
},
  "geometry": {"coordinates":[11.1378164291,47.363067627],"type":"Point"}
}