{
  "type": "Feature",
  "properties": {
    "addr:full":"Sonnbergstr 3 Perchtoldsdorf Nieder\u00f6sterreich 2380",
    "addr:housenumber":"3",
    "addr:postcode":"2380",
    "addr:street":"Sonnbergstr",
    "iso:country":"AT",
    "sg:address":"Sonnbergstr 3",
    "sg:city":"Perchtoldsdorf",
    "sg:orig_category":"Fernseh- U Radiogesellschaften",
    "sg:phone":"+43 1 863120",
    "sg:postcode":"2380",
    "sg:province":"Nieder\u00f6sterreich",
    "wof:name":"Trans World Radio-Europe",
    "wof:placetype":"venue"
},
  "geometry": {"coordinates":[16.2593994141,48.1222801208],"type":"Point"}
}