{
  "type": "Feature",
  "properties": {
    "addr:full":"Kapellenweg 17 Voitsberg Steiermark 8570",
    "addr:housenumber":"17",
    "addr:postcode":"8570",
    "addr:street":"Kapellenweg",
    "iso:country":"AT",
    "sg:address":"Kapellenweg 17",
    "sg:city":"Voitsberg",
    "sg:orig_category":"Massagen",
    "sg:phone":"+43 3142 25395",
    "sg:postcode":"8570",
    "sg:province":"Steiermark",
    "wof:name":"Pungersek Rosina - Bioenergetisches Institut",
    "wof:placetype":"venue"
},
  "geometry": {"coordinates":[15.1790409088,47.0452041626],"type":"Point"}
}