{
  "type": "Feature",
  "properties": {
    "iso:country":"AT",
    "sg:address":"Kremsbr\u00fccke 4",
    "sg:city":"Kremsbr\u00fccke",
    "sg:classifiers":[
        {
            "category":"Building & Trades",
            "subcategory":"Landscaping Services",
            "type":"Services"
        }
    ],
    "sg:phone":"+43 4735 81010",
    "sg:postcode":"9862",
    "sg:province":"K\u00e4rnten",
    "sg:tags":[
        "dredging"
    ],
    "wof:name":"Aichholzer u. Kohlmaier Sand- und Kiesgewinnung Ges.m.b.H. & Co KG",
    "wof:placetype":"venue"
},
  "geometry": {"coordinates":[6.3016200066,53.2206306458],"type":"Point"}
}