{
  "type": "Feature",
  "properties": {
    "addr:full":"D\u00f6blinger Hauptstr 32/14 Wien Wien 1190",
    "addr:housenumber":"32 / 14",
    "addr:postcode":"1190",
    "addr:street":"Hauptstr",
    "iso:country":"AT",
    "sg:address":"D\u00f6blinger Hauptstr 32/14",
    "sg:city":"Wien",
    "sg:orig_category":"Telekommunikation",
    "sg:phone":"+43 1 9711133",
    "sg:postcode":"1190",
    "sg:province":"Wien",
    "sg:website":"www.worldcard.at",
    "wof:name":"World Card Networks International Inc. - Zweigniederlassung Austria",
    "wof:placetype":"venue"
},
  "geometry": {"coordinates":[16.3532848358,48.2352981567],"type":"Point"}
}