{
  "type": "Feature",
  "properties": {
    "iso:country":"AT",
    "sg:address":"Niederbrunnernstr 13",
    "sg:city":"Sierning",
    "sg:orig_category":"Schokolade U Schokoladewaren",
    "sg:phone":"+43 4366 42216430",
    "sg:postcode":"4522",
    "sg:province":"Ober\u00f6sterreich",
    "wof:name":"H & H Chocolademanufactur GmbH - Schafmilchschokolade",
    "wof:placetype":"venue"
},
  "geometry": {"coordinates":[14.3348178864,48.0829925537],"type":"Point"}
}