{
  "type": "Feature",
  "properties": {
    "addr:full":"Mariahilfer Str 29 Wien Wien 1060",
    "addr:postcode":"1060",
    "addr:street":"Str 29",
    "iso:country":"AT",
    "sg:address":"Mariahilfer Str 29",
    "sg:city":"Wien",
    "sg:orig_category":"Telekommunikation",
    "sg:phone":"+43 800 699889",
    "sg:postcode":"1060",
    "sg:province":"Wien",
    "wof:name":"ONE World Mariahilf 2",
    "wof:placetype":"venue"
},
  "geometry": {"coordinates":[16.357635498,48.2006340027],"type":"Point"}
}