{
  "type": "Feature",
  "properties": {
    "iso:country":"AT",
    "sg:address":"Dorfstr 60",
    "sg:city":"Waidring",
    "sg:orig_category":"Pensionen / Privatzimmer",
    "sg:phone":"+43 5353 5377",
    "sg:postcode":"6384",
    "sg:province":"Tirol",
    "wof:name":"Pension Berta",
    "wof:placetype":"venue"
},
  "geometry": {"coordinates":[12.5584354401,47.587928772],"type":"Point"}
}