{
  "type": "Feature",
  "properties": {
    "addr:full":"10.-Oktober-Pl 13 Bleiburg K\u00e4rnten 9150",
    "addr:housenumber":"13",
    "addr:postcode":"9150",
    "addr:street":"10.-Oktober-Pl;Kaernten",
    "iso:country":"AT",
    "sg:address":"10.-Oktober-Pl 13",
    "sg:city":"Bleiburg",
    "sg:orig_category":"Banken U Sparkassen",
    "sg:phone":"+43 4342 3525210",
    "sg:postcode":"9150",
    "sg:province":"K\u00e4rnten",
    "wof:name":"Raiffeisenbank Bleiburg regGenmbH",
    "wof:placetype":"venue"
},
  "geometry": {"coordinates":[14.7981109619,46.5900154114],"type":"Point"}
}