{
  "type": "Feature",
  "properties": {
    "addr:full":"Gewerbepark Serfaus Tirol 6534",
    "addr:postcode":"6534",
    "addr:street":"Gewerbepark Serfaus",
    "iso:country":"AT",
    "sg:address":"Gewerbepark",
    "sg:city":"Serfaus",
    "sg:orig_category":"Tischlereien",
    "sg:phone":"+43 5476 6730",
    "sg:postcode":"6534",
    "sg:province":"Tirol",
    "wof:name":"Erhart Franz",
    "wof:placetype":"venue"
},
  "geometry": {"coordinates":[10.6053447723,47.0386734009],"type":"Point"}
}