{
  "type": "Feature",
  "properties": {
    "addr:full":"K\u00e4rntner Ring 18 Wien Wien 1010",
    "addr:housenumber":"18",
    "addr:postcode":"1010",
    "addr:street":"Kaerntner Ring",
    "iso:country":"AT",
    "sg:address":"K\u00e4rntner Ring 18",
    "sg:city":"Wien",
    "sg:orig_category":"Fluggesellschaften",
    "sg:phone":"+43 51789",
    "sg:postcode":"1010",
    "sg:province":"Wien",
    "wof:name":"Austrian Airlines - Kundenb\u00fcro",
    "wof:placetype":"venue"
},
  "geometry": {"coordinates":[16.3738574982,48.2013206482],"type":"Point"}
}