{
  "type": "Feature",
  "properties": {
    "addr:full":"Hauptstr 12 Aspang-Markt Nieder\u00f6sterreich 2870",
    "addr:housenumber":"12",
    "addr:postcode":"2870",
    "addr:street":"Hauptstr;Niederoesterreich",
    "iso:country":"AT",
    "sg:address":"Hauptstr 12",
    "sg:city":"Aspang-Markt",
    "sg:orig_category":"Elektroinstallationsunternehmen",
    "sg:phone":"+43 2642 525620",
    "sg:postcode":"2870",
    "sg:province":"Nieder\u00f6sterreich",
    "wof:name":"Schwarzmann Elektro GesmbH",
    "wof:placetype":"venue"
},
  "geometry": {"coordinates":[16.0904312134,47.5545845032],"type":"Point"}
}