{
  "type": "Feature",
  "properties": {
    "addr:full":"Sonnenbergstr 14 N\u00fcziders Vorarlberg 6714",
    "addr:housenumber":"14",
    "addr:postcode":"6714",
    "addr:street":"Sonnenbergstr",
    "iso:country":"AT",
    "sg:address":"Sonnenbergstr 14",
    "sg:city":"N\u00fcziders",
    "sg:orig_category":"Gemeinden",
    "sg:phone":"+43 5552 622410",
    "sg:postcode":"6714",
    "sg:province":"Vorarlberg",
    "wof:name":"Gemeinde N\u00fcziders",
    "wof:placetype":"venue"
},
  "geometry": {"coordinates":[9.7986869812,47.174331665],"type":"Point"}
}