{
  "type": "Feature",
  "properties": {
    "addr:full":"Hauptstr 10 Launsdorf K\u00e4rnten 9314",
    "addr:housenumber":"10",
    "addr:postcode":"9314",
    "addr:street":"Hauptstr;Kaernten",
    "iso:country":"AT",
    "sg:address":"Hauptstr 10",
    "sg:city":"Launsdorf",
    "sg:orig_category":"Elektroinstallationsunternehmen",
    "sg:phone":"+43 4213 20970",
    "sg:postcode":"9314",
    "sg:province":"K\u00e4rnten",
    "wof:name":"Dobraunig Erwin Ing GesmbH",
    "wof:placetype":"venue"
},
  "geometry": {"coordinates":[14.4556798935,46.7681236267],"type":"Point"}
}