{
  "type": "Feature",
  "properties": {
    "addr:full":"Ledererg 40 Linz Ober\u00f6sterreich 4020",
    "addr:housenumber":"40",
    "addr:postcode":"4020",
    "addr:street":"Ledererg",
    "iso:country":"AT",
    "sg:address":"Ledererg 40",
    "sg:city":"Linz",
    "sg:orig_category":"Tabaktrafiken",
    "sg:phone":"+43 732 770063",
    "sg:postcode":"4020",
    "sg:province":"Ober\u00f6sterreich",
    "wof:name":"Pils Angelika",
    "wof:placetype":"venue"
},
  "geometry": {"coordinates":[14.2986345291,48.3093109131],"type":"Point"}
}