{
  "type": "Feature",
  "properties": {
    "addr:full":"St Peter-Str 18 Bludenz Vorarlberg 6700",
    "addr:housenumber":"18",
    "addr:postcode":"6700",
    "iso:country":"AT",
    "sg:address":"St Peter-Str 18",
    "sg:city":"Bludenz",
    "sg:orig_category":"Blumeneinzelhandel",
    "sg:phone":"+43 5552 325270",
    "sg:postcode":"6700",
    "sg:province":"Vorarlberg",
    "wof:name":"HOTZ Blumen",
    "wof:placetype":"venue"
},
  "geometry": {"coordinates":[9.828332901,47.1469230652],"type":"Point"}
}