{
  "type": "Feature",
  "properties": {
    "iso:country":"AT",
    "sg:address":"Margaretenstr 106",
    "sg:city":"Wien",
    "sg:orig_category":"Friseure U Frisiersalons",
    "sg:phone":"+43 4315 481720",
    "sg:postcode":"1050",
    "sg:province":"Wien",
    "wof:name":"Buchner Ernst",
    "wof:placetype":"venue"
},
  "geometry": {"coordinates":[16.35505867,48.1893081665],"type":"Point"}
}