{
  "type": "Feature",
  "properties": {
    "addr:full":"Nr 33 Breitenbach am Inn Tirol 6252",
    "addr:postcode":"6252",
    "addr:street":"Nr 33;Tirol",
    "iso:country":"AT",
    "sg:address":"Nr 33",
    "sg:city":"Breitenbach am Inn",
    "sg:orig_category":"Bauunternehmen",
    "sg:phone":"+43 5338 8136",
    "sg:postcode":"6252",
    "sg:province":"Tirol",
    "wof:name":"Kern Dipl Ing Erich KG",
    "wof:placetype":"venue"
},
  "geometry": {"coordinates":[11.973446846,47.4788246155],"type":"Point"}
}