{
  "type": "Feature",
  "properties": {
    "addr:full":"Nr 58 Kl\u00f6ch Steiermark 8493",
    "addr:postcode":"8493",
    "addr:street":"Nr 58 Kloech Steiermark",
    "iso:country":"AT",
    "sg:address":"Nr 58",
    "sg:city":"Kl\u00f6ch",
    "sg:orig_category":"Baumschulen",
    "sg:phone":"+43 3475 2394",
    "sg:postcode":"8493",
    "sg:province":"Steiermark",
    "wof:name":"Fr\u00fchwirth Franz",
    "wof:placetype":"venue"
},
  "geometry": {"coordinates":[15.967171669,46.7641334534],"type":"Point"}
}