{
  "type": "Feature",
  "properties": {
    "addr:full":"Erdbergstr 10 Wien Wien 1030",
    "addr:housenumber":"10",
    "addr:postcode":"1030",
    "addr:street":"Erdbergstr",
    "iso:country":"AT",
    "sg:address":"Erdbergstr 10",
    "sg:city":"Wien",
    "sg:orig_category":"Friseure U Frisiersalons",
    "sg:phone":"+43 4317 151714",
    "sg:postcode":"1030",
    "sg:province":"Wien",
    "wof:name":"Fris\u00f6r Haarideen",
    "wof:placetype":"venue"
},
  "geometry": {"coordinates":[16.3938350677,48.2024765015],"type":"Point"}
}