{
  "type": "Feature",
  "properties": {
    "addr:full":"Eberndorfer Str 16 St. Kanzian am Klopeiner See K\u00e4rnten 9122",
    "addr:housenumber":"16",
    "addr:postcode":"9122",
    "addr:street":"Str;Kaernten",
    "iso:country":"AT",
    "sg:address":"Eberndorfer Str 16",
    "sg:city":"St. Kanzian am Klopeiner See",
    "sg:classifiers":[
        {
            "category":"Taxi",
            "type":"Transportation"
        }
    ],
    "sg:phone":"+43 4342 392328",
    "sg:postcode":"9122",
    "sg:province":"K\u00e4rnten",
    "sg:tags":[
        "personentransporte",
        "u"
    ],
    "wof:name":"Olip Hans",
    "wof:placetype":"venue"
},
  "geometry": {"coordinates":[14.5984601974,46.6166000366],"type":"Point"}
}