{
  "type": "Feature",
  "properties": {
    "addr:full":"L\u00e4rchenweg 27 Deutschlandsberg Steiermark 8530",
    "addr:housenumber":"27",
    "addr:postcode":"8530",
    "addr:street":"Laerchenweg",
    "iso:country":"AT",
    "sg:address":"L\u00e4rchenweg 27",
    "sg:city":"Deutschlandsberg",
    "sg:orig_category":"Maschinenbau",
    "sg:phone":"+43 3462 5155",
    "sg:postcode":"8530",
    "sg:province":"Steiermark",
    "wof:name":"Ernegger OEG",
    "wof:placetype":"venue"
},
  "geometry": {"coordinates":[15.1824817657,46.8353157043],"type":"Point"}
}