{
  "type": "Feature",
  "properties": {
    "addr:full":"Arlbergstr 101/5 Bregenz Vorarlberg 6900",
    "addr:housenumber":"101 / 5",
    "addr:postcode":"6900",
    "iso:country":"AT",
    "sg:address":"Arlbergstr 101/5",
    "sg:city":"Bregenz",
    "sg:orig_category":"Alternativtherapie",
    "sg:phone":"+43 5574 54060",
    "sg:postcode":"6900",
    "sg:province":"Vorarlberg",
    "wof:name":"Huber Gerda",
    "wof:placetype":"venue"
},
  "geometry": {"coordinates":[9.7336120605,47.4921150208],"type":"Point"}
}