{
  "type": "Feature",
  "properties": {
    "iso:country":"AT",
    "sg:address":"Fr\u00f6belgasse 9",
    "sg:city":"Wien",
    "sg:orig_category":"ChildrenS Furniture",
    "sg:phone":"+43 1 4931699",
    "sg:postcode":"1160",
    "sg:province":"Wien",
    "wof:name":"Josef Plachy KG Tischlermeister",
    "wof:placetype":"venue"
},
  "geometry": {"coordinates":[16.3303966522,48.2054748535],"type":"Point"}
}