{
  "type": "Feature",
  "properties": {
    "iso:country":"AT",
    "sg:address":"Stiftingtalstr 169",
    "sg:city":"Graz",
    "sg:orig_category":"Non-Classified Establishments",
    "sg:phone":"+43 316 321395",
    "sg:postcode":"8010",
    "sg:province":"Steiermark",
    "wof:name":"Kongregation der Schwestern v d Unbefleckten Empf\u00e4ngnis in Vorau",
    "wof:placetype":"venue"
},
  "geometry": {"coordinates":[15.4846954346,47.0898628235],"type":"Point"}
}