{
  "type": "Feature",
  "properties": {
    "addr:full":"Ing.-Gomperz-Weg 13 St. Anton am Arlberg Tirol 6580",
    "addr:housenumber":"13",
    "addr:postcode":"6580",
    "addr:street":"Ing.-Gomperz-Weg;Tirol",
    "iso:country":"AT",
    "sg:address":"Ing.-Gomperz-Weg 13",
    "sg:city":"St. Anton am Arlberg",
    "sg:orig_category":"Pensionen / Privatzimmer",
    "sg:phone":"+43 5446 2650",
    "sg:postcode":"6580",
    "sg:province":"Tirol",
    "wof:name":"Haus Bacherspitze",
    "wof:placetype":"venue"
},
  "geometry": {"coordinates":[10.2640428543,47.127532959],"type":"Point"}
}