{
  "type": "Feature",
  "properties": {
    "addr:full":"Am Kuhberg 6 Horn Nieder\u00f6sterreich 3580",
    "addr:housenumber":"6",
    "addr:postcode":"3580",
    "addr:street":"Am Kuhberg;Niederoesterreich",
    "iso:country":"AT",
    "sg:address":"Am Kuhberg 6",
    "sg:city":"Horn",
    "sg:orig_category":"Damenmoden",
    "sg:phone":"+43 2982 30422",
    "sg:postcode":"3580",
    "sg:province":"Nieder\u00f6sterreich",
    "wof:name":"KiK Textilien und Non-Food GesmbH",
    "wof:placetype":"venue"
},
  "geometry": {"coordinates":[15.6349153519,48.665851593],"type":"Point"}
}