{
  "type": "Feature",
  "properties": {
    "addr:full":"Feldstr 24 Seewalchen am Attersee Ober\u00f6sterreich 4863",
    "addr:housenumber":"24",
    "addr:postcode":"4863",
    "addr:street":"Feldstr",
    "iso:country":"AT",
    "sg:address":"Feldstr 24",
    "sg:city":"Seewalchen am Attersee",
    "sg:orig_category":"Baumeister",
    "sg:phone":"+43 4376 6223500",
    "sg:postcode":"4863",
    "sg:province":"Ober\u00f6sterreich",
    "wof:name":"Ploner Johann Ing",
    "wof:placetype":"venue"
},
  "geometry": {"coordinates":[13.5930891037,47.9521331787],"type":"Point"}
}