{
  "type": "Feature",
  "properties": {
    "addr:full":"Hauptstrasse 17 Berndorf Nieder\u00f6sterreich 2560",
    "addr:housenumber":"17",
    "addr:postcode":"2560",
    "addr:street":"Hauptstrasse",
    "iso:country":"AT",
    "sg:address":"Hauptstrasse 17",
    "sg:city":"Berndorf",
    "sg:classifiers":[
        {
            "category":"Building & Trades",
            "subcategory":"Electrical",
            "type":"Services"
        }
    ],
    "sg:phone":"+43 2672 83324",
    "sg:postcode":"2560",
    "sg:province":"Nieder\u00f6sterreich",
    "sg:tags":[
        "house",
        "material",
        "installation",
        "electric",
        "prefabricated"
    ],
    "wof:name":"W. P. Fastl Ges.m.b.H",
    "wof:placetype":"venue"
},
  "geometry": {"coordinates":[16.1547107697,47.93775177],"type":"Point"}
}