{
  "type": "Feature",
  "properties": {
    "addr:full":"Platz 407 Mellau Vorarlberg 6881",
    "addr:housenumber":"407",
    "addr:postcode":"6881",
    "addr:street":"Platz",
    "iso:country":"AT",
    "sg:address":"Platz 407",
    "sg:city":"Mellau",
    "sg:orig_category":"Appartements / Ferienwohnungen",
    "sg:phone":"+43 4355 182256",
    "sg:postcode":"6881",
    "sg:province":"Vorarlberg",
    "wof:name":"Bischofberger Appartements",
    "wof:placetype":"venue"
},
  "geometry": {"coordinates":[9.881570816,47.3503112793],"type":"Point"}
}