{
  "type": "Feature",
  "properties": {
    "addr:full":"Schaumburgerg 15 Wien Wien 1040",
    "addr:housenumber":"15",
    "addr:postcode":"1040",
    "addr:street":"Schaumburgerg",
    "iso:country":"AT",
    "sg:address":"Schaumburgerg 15",
    "sg:city":"Wien",
    "sg:orig_category":"Physiotherapie",
    "sg:phone":"+43 4366 42533799",
    "sg:postcode":"1040",
    "sg:province":"Wien",
    "wof:name":"Kerschbaumer Bernhard",
    "wof:placetype":"venue"
},
  "geometry": {"coordinates":[16.3689746857,48.1899604797],"type":"Point"}
}