{
  "type": "Feature",
  "properties": {
    "addr:full":"Nr 35 Schwand im Innkreis Ober\u00f6sterreich 5134",
    "addr:postcode":"5134",
    "addr:street":"Nr",
    "iso:country":"AT",
    "sg:address":"Nr 35",
    "sg:city":"Schwand im Innkreis",
    "sg:orig_category":"Maler, Anstreicher U Lackierer",
    "sg:phone":"+43 4377 286032",
    "sg:postcode":"5134",
    "sg:province":"Ober\u00f6sterreich",
    "wof:name":"Melchiori Kurt",
    "wof:placetype":"venue"
},
  "geometry": {"coordinates":[12.9669046402,48.1785736084],"type":"Point"}
}