{
  "type": "Feature",
  "properties": {
    "iso:country":"AT",
    "sg:address":"Bichlnweg 9a",
    "sg:city":"Kitzb\u00fchel",
    "sg:orig_category":"Physiotherapie",
    "sg:phone":"+43 5356 75313",
    "sg:postcode":"6370",
    "sg:province":"Tirol",
    "wof:name":"Haselwanter Claudia Dipl-PT",
    "wof:placetype":"venue"
},
  "geometry": {"coordinates":[12.4043874741,47.4372673035],"type":"Point"}
}