{
  "type": "Feature",
  "properties": {
    "iso:country":"AT",
    "sg:address":"Hofsteigstr 75",
    "sg:city":"Schwarzach",
    "sg:orig_category":"Banken U Sparkassen",
    "sg:phone":"+43 4355 72582550",
    "sg:postcode":"6858",
    "sg:province":"Vorarlberg",
    "wof:name":"Raiffeisenbank am Hofsteig Bankstelle Schwarzach regGenmbH",
    "wof:placetype":"venue"
},
  "geometry": {"coordinates":[9.7624254227,47.4436035156],"type":"Point"}
}