{
  "type": "Feature",
  "properties": {
    "addr:full":"Nr 66a Kaltenbach Tirol 6272",
    "addr:postcode":"6272",
    "addr:street":"Nr 66A Kaltenbach",
    "iso:country":"AT",
    "sg:address":"Nr 66a",
    "sg:city":"Kaltenbach",
    "sg:orig_category":"Betonbohr- U -Schneidedienst",
    "sg:phone":"+43 5283 3555",
    "sg:postcode":"6272",
    "sg:province":"Tirol",
    "wof:name":"Asphalt- und Betonschneidetechnik Tipotsch Manfred GmbH & Co KEG",
    "wof:placetype":"venue"
},
  "geometry": {"coordinates":[11.8752498627,47.2923049927],"type":"Point"}
}