{
  "type": "Feature",
  "properties": {
    "addr:full":"Nr 20 Stra\u00dfwalchen Salzburg 5204",
    "addr:postcode":"5204",
    "addr:street":"Nr",
    "iso:country":"AT",
    "sg:address":"Nr 20",
    "sg:city":"Stra\u00dfwalchen",
    "sg:orig_category":"Maschinenhandel",
    "sg:phone":"+43 6215 6341",
    "sg:postcode":"5204",
    "sg:province":"Salzburg",
    "wof:name":"Stadler Rudolf MaschinenhandelgesmbH",
    "wof:placetype":"venue"
},
  "geometry": {"coordinates":[13.2546854019,47.9797363281],"type":"Point"}
}