{
  "type": "Feature",
  "properties": {
    "addr:full":"Linke Glanzeile 17 Salzburg Salzburg 5020",
    "addr:housenumber":"17",
    "addr:postcode":"5020",
    "addr:street":"Linke Glanzeile;Salzburg",
    "iso:country":"AT",
    "sg:address":"Linke Glanzeile 17",
    "sg:city":"Salzburg",
    "sg:orig_category":"Etiketten",
    "sg:phone":"+43 662 434368",
    "sg:postcode":"5020",
    "sg:province":"Salzburg",
    "wof:name":"H\u00e4rtl Sibylle",
    "wof:placetype":"venue"
},
  "geometry": {"coordinates":[13.0247116089,47.8155593872],"type":"Point"}
}