{
  "type": "Feature",
  "properties": {
    "addr:full":"Hopfgarten in Defereggen Tirol 9961",
    "addr:postcode":"9961",
    "addr:street":"Tirol",
    "iso:country":"AT",
    "sg:city":"Hopfgarten in Defereggen",
    "sg:orig_category":"Non-Classified Establishments",
    "sg:phone":"+43 4872 5372",
    "sg:postcode":"9961",
    "sg:province":"Tirol",
    "wof:name":"Pfarramt",
    "wof:placetype":"venue"
},
  "geometry": {"coordinates":[12.5194997787,46.9212799072],"type":"Point"}
}