{
  "type": "Feature",
  "properties": {
    "addr:full":"Tischlerstrasse 7 Bad Hall Ober\u00f6sterreich 4540",
    "addr:housenumber":"7",
    "addr:postcode":"4540",
    "addr:street":"Tischlerstrasse",
    "iso:country":"AT",
    "sg:address":"Tischlerstrasse 7",
    "sg:city":"Bad Hall",
    "sg:classifiers":[
        {
            "category":"Government",
            "subcategory":"Police Station",
            "type":"Public Place"
        }
    ],
    "sg:phone":"+43 7258 5353",
    "sg:postcode":"4540",
    "sg:province":"Ober\u00f6sterreich",
    "sg:tags":[
        "industrial",
        "installation"
    ],
    "sg:website":"tomic.de",
    "wof:name":"Tomic Versorgungstechnik Ges.m.b.H.",
    "wof:placetype":"venue"
},
  "geometry": {"coordinates":[14.1890516281,48.0295333862],"type":"Point"}
}