{
  "type": "Feature",
  "properties": {
    "iso:country":"AT",
    "sg:address":"Hofsteigstr 15",
    "sg:city":"Wolfurt",
    "sg:orig_category":"Werbegestalter",
    "sg:phone":"+43 5574 61861",
    "sg:postcode":"6922",
    "sg:province":"Vorarlberg",
    "wof:name":"Zimmermann Heinz",
    "wof:placetype":"venue"
},
  "geometry": {"coordinates":[9.7518491745,47.4656600952],"type":"Point"}
}