{
  "type": "Feature",
  "properties": {
    "addr:full":"Wartingerg 37-39 Graz Steiermark 8010",
    "addr:postcode":"37-39;8010",
    "iso:country":"AT",
    "sg:address":"Wartingerg 37-39",
    "sg:city":"Graz",
    "sg:orig_category":"Holdinggesellschaften",
    "sg:phone":"+43 316 60000",
    "sg:postcode":"8010",
    "sg:province":"Steiermark",
    "wof:name":"Trend Konzernholding AG",
    "wof:placetype":"venue"
},
  "geometry": {"coordinates":[15.4345979691,47.0788040161],"type":"Point"}
}