{
  "type": "Feature",
  "properties": {
    "iso:country":"AT",
    "sg:address":"Bl\u00fctenstrasse 2",
    "sg:city":"Linz",
    "sg:classifiers":[
        {
            "category":"Structure",
            "subcategory":"Bridge",
            "type":"Public Place"
        }
    ],
    "sg:phone":"+43 732 7105450",
    "sg:postcode":"4040",
    "sg:province":"Ober\u00f6sterreich",
    "sg:tags":[
        "trolley",
        "inspection"
    ],
    "sg:website":"alba.at",
    "wof:name":"Albatros Engineering GmbH.",
    "wof:placetype":"venue"
},
  "geometry": {"coordinates":[14.2578554153,48.3602561951],"type":"Point"}
}