{
  "type": "Feature",
  "properties": {
    "addr:full":"Josef-Weislein-Str 5 Hollabrunn Nieder\u00f6sterreich 2020",
    "addr:housenumber":"5",
    "addr:postcode":"2020",
    "addr:street":"Josef-Weislein-Str",
    "iso:country":"AT",
    "sg:address":"Josef-Weislein-Str 5",
    "sg:city":"Hollabrunn",
    "sg:orig_category":"Sportanlagen",
    "sg:phone":"+43 2952 333530",
    "sg:postcode":"2020",
    "sg:province":"Nieder\u00f6sterreich",
    "wof:name":"Kunsteisbahn Hollabrunn",
    "wof:placetype":"venue"
},
  "geometry": {"coordinates":[16.0747642517,48.5592308044],"type":"Point"}
}