{
  "type": "Feature",
  "properties": {
    "iso:country":"AT",
    "sg:address":"Brunng. 13",
    "sg:city":"St. P\u00f6lten",
    "sg:classifiers":[
        {
            "category":"Sports & Exercise",
            "subcategory":"Playing Field",
            "type":"Entertainment"
        }
    ],
    "sg:phone":"+43 4327 4273187",
    "sg:postcode":"3100",
    "sg:province":"Nieder\u00f6sterreich",
    "sg:tags":[
        "game"
    ],
    "wof:name":"CITY-ZOO",
    "wof:placetype":"venue"
},
  "geometry": {"coordinates":[11.8208999634,47.7790718079],"type":"Point"}
}