{
  "type": "Feature",
  "properties": {
    "addr:full":"Spielbergstr 38 Fieberbrunn Tirol 6391",
    "addr:housenumber":"38",
    "addr:postcode":"6391",
    "addr:street":"Spielbergstr;Tirol",
    "iso:country":"AT",
    "sg:address":"Spielbergstr 38",
    "sg:city":"Fieberbrunn",
    "sg:orig_category":"Autoreparatur",
    "sg:phone":"+43 5354 56412",
    "sg:postcode":"6391",
    "sg:province":"Tirol",
    "wof:name":"Liebhart Herbert",
    "wof:placetype":"venue"
},
  "geometry": {"coordinates":[12.5493125916,47.4745483398],"type":"Point"}
}