{
  "type": "Feature",
  "properties": {
    "addr:full":"Pfarrg 3 Freistadt Ober\u00f6sterreich 4240",
    "addr:housenumber":"3",
    "addr:postcode":"4240",
    "addr:street":"Pfarrg",
    "iso:country":"AT",
    "sg:address":"Pfarrg 3",
    "sg:city":"Freistadt",
    "sg:orig_category":"Versicherungsunternehmen",
    "sg:phone":"+43 7942 73993",
    "sg:postcode":"4240",
    "sg:province":"Ober\u00f6sterreich",
    "wof:name":"Der Anker Allgemeine Versicherung AG",
    "wof:placetype":"venue"
},
  "geometry": {"coordinates":[14.5042285919,48.5108680725],"type":"Point"}
}