{
  "type": "Feature",
  "properties": {
    "iso:country":"AT",
    "sg:address":"Nr 2",
    "sg:city":"Lebring",
    "sg:orig_category":"Finanz- U Wirtschaftsberatung",
    "sg:phone":"+43 664 1528008",
    "sg:postcode":"8403",
    "sg:province":"Steiermark",
    "wof:name":"Bertram F\u00f6tsch - selbst\u00e4ndiger W\u00fcstenrotberater",
    "wof:placetype":"venue"
},
  "geometry": {"coordinates":[15.5376806259,46.8533821106],"type":"Point"}
}