{
  "type": "Feature",
  "properties": {
    "iso:country":"AT",
    "sg:address":"Favoritenstr 20",
    "sg:city":"Wien",
    "sg:orig_category":"Altwaren",
    "sg:phone":"+43 4315 039800",
    "sg:postcode":"1040",
    "sg:province":"Wien",
    "wof:name":"Leonardo Altwarenhandel - Slobodan Djordjevic",
    "wof:placetype":"venue"
},
  "geometry": {"coordinates":[16.3698635101,48.1939582825],"type":"Point"}
}