{
  "type": "Feature",
  "properties": {
    "addr:full":"Kaiserstr 92 Wien Wien 1070",
    "addr:housenumber":"92",
    "addr:postcode":"1070",
    "addr:street":"Kaiserstr",
    "iso:country":"AT",
    "sg:address":"Kaiserstr 92",
    "sg:city":"Wien",
    "sg:orig_category":"Lebensmittel / Einzelhandel",
    "sg:phone":"+43 1 5265005",
    "sg:postcode":"1070",
    "sg:province":"Wien",
    "wof:name":"Hofer KG",
    "wof:placetype":"venue"
},
  "geometry": {"coordinates":[16.3398094177,48.2064971924],"type":"Point"}
}