{
  "type": "Feature",
  "properties": {
    "iso:country":"AT",
    "sg:address":"Gewerbepark 30",
    "sg:city":"Baumgartenberg",
    "sg:classifiers":[
        {
            "category":"Manufacturing",
            "subcategory":"Rubber & Plastics",
            "type":"Manufacturing & Wholesale Goods"
        }
    ],
    "sg:phone":"+43 4372 697570",
    "sg:postcode":"4342",
    "sg:province":"Ober\u00f6sterreich",
    "wof:name":"HUECK FOLIEN GES.MBH",
    "wof:placetype":"venue"
},
  "geometry": {"coordinates":[14.745724678,48.2092475891],"type":"Point"}
}