{
  "type": "Feature",
  "properties": {
    "addr:full":"Arkadenpl 1 Kufstein Tirol 6330",
    "addr:housenumber":"1",
    "addr:postcode":"6330",
    "addr:street":"Arkadenpl;Tirol",
    "iso:country":"AT",
    "sg:address":"Arkadenpl 1",
    "sg:city":"Kufstein",
    "sg:classifiers":[
        {
            "category":"Travel",
            "subcategory":"Hotels & Motels",
            "type":"Entertainment"
        }
    ],
    "sg:phone":"+43 5372 69440",
    "sg:postcode":"6330",
    "sg:province":"Tirol",
    "wof:name":"Hotel Thaler",
    "wof:placetype":"venue"
},
  "geometry": {"coordinates":[12.171959877,47.5821914673],"type":"Point"}
}