{
  "type": "Feature",
  "properties": {
    "iso:country":"AT",
    "sg:address":"Alois-Czedik-Gasse 1/16",
    "sg:city":"Wien",
    "sg:classifiers":[
        {
            "category":"Wholesale",
            "subcategory":"Electrical",
            "type":"Manufacturing & Wholesale Goods"
        }
    ],
    "sg:phone":"+43 1 5771020",
    "sg:postcode":"1140",
    "sg:province":"Wien",
    "sg:tags":[
        "component"
    ],
    "sg:website":"flashmedia.at",
    "wof:name":"FLASH MEDIA Handels GmbH",
    "wof:placetype":"venue"
},
  "geometry": {"coordinates":[16.212228775,48.2093086243],"type":"Point"}
}