{
  "type": "Feature",
  "properties": {
    "addr:full":"Schadekg 5 Wien Wien 1060",
    "addr:housenumber":"5",
    "addr:postcode":"1060",
    "addr:street":"Schadekg",
    "iso:country":"AT",
    "sg:address":"Schadekg 5",
    "sg:city":"Wien",
    "sg:orig_category":"Fotografen",
    "sg:phone":"+43 1 5864242",
    "sg:postcode":"1060",
    "sg:province":"Wien",
    "wof:name":"Themessl Curt - Fotostudio",
    "wof:placetype":"venue"
},
  "geometry": {"coordinates":[16.3505783081,48.1979904175],"type":"Point"}
}