{
  "type": "Feature",
  "properties": {
    "addr:full":"Marktpl 19 Linz Ober\u00f6sterreich 4020",
    "addr:housenumber":"19",
    "addr:postcode":"4020",
    "addr:street":"Marktpl",
    "iso:country":"AT",
    "sg:address":"Marktpl 19",
    "sg:city":"Linz",
    "sg:orig_category":"Molkereien U Molkereiprodukte",
    "sg:phone":"+43 4373 2654822",
    "sg:postcode":"4020",
    "sg:province":"Ober\u00f6sterreich",
    "wof:name":"Fromagerie - KGM Consulting & Traiding GmbH",
    "wof:placetype":"venue"
},
  "geometry": {"coordinates":[14.3004188538,48.3002281189],"type":"Point"}
}