{
  "type": "Feature",
  "properties": {
    "iso:country":"AT",
    "sg:address":"Sportplatzstr 41",
    "sg:city":"Thalgau",
    "sg:orig_category":"Wach- U Sicherheitsunternehmen",
    "sg:phone":"+43 6235 6327",
    "sg:postcode":"5303",
    "sg:province":"Salzburg",
    "wof:name":"Keil Angelo Transportbegleitung",
    "wof:placetype":"venue"
},
  "geometry": {"coordinates":[13.250500679,47.8383293152],"type":"Point"}
}