{
  "type": "Feature",
  "properties": {
    "addr:full":"Murtalstr 488 St. Michael im Lungau Salzburg 5582",
    "addr:housenumber":"488",
    "addr:postcode":"5582",
    "addr:street":"Salzburg",
    "iso:country":"AT",
    "sg:address":"Murtalstr 488",
    "sg:city":"St. Michael im Lungau",
    "sg:orig_category":"Steuerberatung",
    "sg:phone":"+43 4364 77200200",
    "sg:postcode":"5582",
    "sg:province":"Salzburg",
    "wof:name":"Sch\u00f6berl Karl-Heinz Mag",
    "wof:placetype":"venue"
},
  "geometry": {"coordinates":[13.6339998245,47.0962028503],"type":"Point"}
}