{
  "type": "Feature",
  "properties": {
    "addr:full":"Aderstr 17 Timelkam Ober\u00f6sterreich 4850",
    "addr:housenumber":"17",
    "addr:postcode":"4850",
    "addr:street":"Aderstr",
    "iso:country":"AT",
    "sg:address":"Aderstr 17",
    "sg:city":"Timelkam",
    "sg:orig_category":"Furniere",
    "sg:phone":"+43 4376 7292365",
    "sg:postcode":"4850",
    "sg:province":"Ober\u00f6sterreich",
    "wof:name":"Grabner J Furniere GmbH",
    "wof:placetype":"venue"
},
  "geometry": {"coordinates":[13.6065063477,47.9999351501],"type":"Point"}
}