{
  "type": "Feature",
  "properties": {
    "addr:full":"Auffach 265 Wildsch\u00f6nau-Auffach Tirol 6313",
    "addr:housenumber":"265",
    "addr:postcode":"6313",
    "addr:street":"Auffach;Tirol",
    "iso:country":"AT",
    "sg:address":"Auffach 265",
    "sg:city":"Wildsch\u00f6nau-Auffach",
    "sg:orig_category":"Werbegrafik- U Grafik-Design",
    "sg:phone":"+43 5339 2569",
    "sg:postcode":"6313",
    "sg:province":"Tirol",
    "wof:name":"MG Design",
    "wof:placetype":"venue"
},
  "geometry": {"coordinates":[12.0360631943,47.4098701477],"type":"Point"}
}