{
  "type": "Feature",
  "properties": {
    "addr:full":"Fleischhackerg 18 Wien Wien 1230",
    "addr:housenumber":"18",
    "addr:postcode":"1230",
    "addr:street":"Fleischhackerg",
    "iso:country":"AT",
    "sg:address":"Fleischhackerg 18",
    "sg:city":"Wien",
    "sg:orig_category":"Gastronomie- U Hoteleinrichtungen",
    "sg:phone":"+43 4318 898429",
    "sg:postcode":"1230",
    "sg:province":"Wien",
    "wof:name":"Hertl Renate",
    "wof:placetype":"venue"
},
  "geometry": {"coordinates":[16.284822464,48.1562576294],"type":"Point"}
}