{
  "type": "Feature",
  "properties": {
    "addr:full":"Bayrhammerg 9 Ried im Innkreis Ober\u00f6sterreich 4910",
    "addr:housenumber":"9",
    "addr:postcode":"4910",
    "addr:street":"Bayrhammerg",
    "iso:country":"AT",
    "sg:address":"Bayrhammerg 9",
    "sg:city":"Ried im Innkreis",
    "sg:orig_category":"Tabaktrafiken",
    "sg:phone":"+43 7752 82669",
    "sg:postcode":"4910",
    "sg:province":"Ober\u00f6sterreich",
    "wof:name":"Fuchs Johanna",
    "wof:placetype":"venue"
},
  "geometry": {"coordinates":[13.4866447449,48.2087173462],"type":"Point"}
}