{
  "type": "Feature",
  "properties": {
    "addr:full":"Rheinf\u00e4hre 31 Hohenems Vorarlberg 6845",
    "addr:housenumber":"31",
    "addr:postcode":"6845",
    "addr:street":"Rheinfaehre",
    "iso:country":"AT",
    "sg:address":"Rheinf\u00e4hre 31",
    "sg:city":"Hohenems",
    "sg:orig_category":"Restaurants: Chinesisch",
    "sg:phone":"+43 5576 76951",
    "sg:postcode":"6845",
    "sg:province":"Vorarlberg",
    "wof:name":"China-Restaurant Oriental",
    "wof:placetype":"venue"
},
  "geometry": {"coordinates":[9.6646471024,47.365852356],"type":"Point"}
}