{
  "type": "Feature",
  "properties": {
    "addr:full":"Waldeggstr 111/6 Linz Ober\u00f6sterreich 4020",
    "addr:housenumber":"111 / 6",
    "addr:postcode":"4020",
    "iso:country":"AT",
    "sg:address":"Waldeggstr 111/6",
    "sg:city":"Linz",
    "sg:orig_category":"Unternehmensberatung",
    "sg:phone":"+43 732 601800",
    "sg:postcode":"4020",
    "sg:province":"Ober\u00f6sterreich",
    "wof:name":"IGP Consulting & Training - Institut f ganzheitliche Pers\u00f6nlichkeitsentfaltung Dr Pelger",
    "wof:placetype":"venue"
},
  "geometry": {"coordinates":[14.2810811996,48.2817420959],"type":"Point"}
}