{
  "type": "Feature",
  "properties": {
    "iso:country":"AT",
    "sg:address":"Rainstadl 370",
    "sg:city":"S\u00f6lden",
    "sg:classifiers":[
        {
            "category":"Travel",
            "subcategory":"Hotels & Motels",
            "type":"Entertainment"
        }
    ],
    "sg:phone":"+43 5254 5030",
    "sg:postcode":"6450",
    "sg:province":"Tirol",
    "wof:name":"Hotel S\u00f6lderhof",
    "wof:placetype":"venue"
},
  "geometry": {"coordinates":[11.0104351044,46.9718132019],"type":"Point"}
}