{
  "type": "Feature",
  "properties": {
    "iso:country":"AT",
    "sg:address":"Untere Hauptstr 9",
    "sg:city":"Wilhelmsburg an der Traisen",
    "sg:orig_category":"Fotografen",
    "sg:phone":"+43 4327 465052",
    "sg:postcode":"3150",
    "sg:province":"Nieder\u00f6sterreich",
    "wof:name":"Fotostudio - Hans Schindlecker",
    "wof:placetype":"venue"
},
  "geometry": {"coordinates":[15.6057605743,48.1068954468],"type":"Point"}
}