{
  "type": "Feature",
  "properties": {
    "addr:full":"Widnau 2 Feldkirch Vorarlberg 6800",
    "addr:housenumber":"2",
    "addr:postcode":"6800",
    "addr:street":"Widnau",
    "iso:country":"AT",
    "sg:address":"Widnau 2",
    "sg:city":"Feldkirch",
    "sg:orig_category":"Gewerkschaften",
    "sg:phone":"+43 4355 22355332",
    "sg:postcode":"6800",
    "sg:province":"Vorarlberg",
    "wof:name":"Gewerkschaft d Bau- u Holzarbeiter",
    "wof:placetype":"venue"
},
  "geometry": {"coordinates":[9.5972738266,47.2395210266],"type":"Point"}
}