{
  "type": "Feature",
  "properties": {
    "addr:full":"Zullerstrasse 7 Innsbruck Tirol 6020",
    "addr:housenumber":"7",
    "addr:postcode":"6020",
    "addr:street":"Zullerstrasse;Tirol",
    "iso:country":"AT",
    "sg:address":"Zullerstrasse 7",
    "sg:city":"Innsbruck",
    "sg:orig_category":"Inhalation Equipment",
    "sg:phone":"+43 512 587426",
    "sg:postcode":"6020",
    "sg:province":"Tirol",
    "sg:website":"w-kern.at",
    "wof:name":"Wilhelm Kern",
    "wof:placetype":"venue"
},
  "geometry": {"coordinates":[11.388463974,47.2576789856],"type":"Point"}
}