{
  "type": "Feature",
  "properties": {
    "addr:full":"Linzer Str. 191-193 Gablitz Nieder\u00f6sterreich 3003",
    "addr:postcode":"191-193;3003",
    "addr:street":"Linzer Str.;Niederoesterreich",
    "iso:country":"AT",
    "sg:address":"Linzer Str. 191-193",
    "sg:city":"Gablitz",
    "sg:classifiers":[
        {
            "category":"Wholesale",
            "subcategory":"Drugs",
            "type":"Manufacturing & Wholesale Goods"
        }
    ],
    "sg:phone":"+43 4322 3165141",
    "sg:postcode":"3003",
    "sg:province":"Nieder\u00f6sterreich",
    "sg:tags":[
        "chemical",
        "pharmaceutical"
    ],
    "wof:name":"PEROLIN GES.MBH",
    "wof:placetype":"venue"
},
  "geometry": {"coordinates":[16.1355495453,48.2398033142],"type":"Point"}
}