{
  "type": "Feature",
  "properties": {
    "addr:full":"Wiener Str 66a Wilfersdorf Nieder\u00f6sterreich 2193",
    "addr:housenumber":"66a",
    "addr:postcode":"2193",
    "addr:street":"Str",
    "iso:country":"AT",
    "sg:address":"Wiener Str 66a",
    "sg:city":"Wilfersdorf",
    "sg:orig_category":"Transportunternehmen",
    "sg:phone":"+43 2573 23290",
    "sg:postcode":"2193",
    "sg:province":"Nieder\u00f6sterreich",
    "wof:name":"Hofer Ing Dachfachmarkt - Holzhandel- und Transporte GmbH",
    "wof:placetype":"venue"
},
  "geometry": {"coordinates":[16.6402683258,48.5776824951],"type":"Point"}
}