{
  "type": "Feature",
  "properties": {
    "addr:full":"Polsenz 13 Eferding Ober\u00f6sterreich 4070",
    "addr:housenumber":"13",
    "addr:postcode":"4070",
    "addr:street":"Polsenz",
    "iso:country":"AT",
    "sg:address":"Polsenz 13",
    "sg:city":"Eferding",
    "sg:classifiers":[
        {
            "category":"Structure",
            "subcategory":"Office Building",
            "type":"Public Place"
        }
    ],
    "sg:phone":"+43 7272 24440",
    "sg:postcode":"4070",
    "sg:province":"Ober\u00f6sterreich",
    "sg:tags":[
        "brick",
        "ceiling",
        "module"
    ],
    "sg:website":"leitl.at",
    "wof:name":"Leitl Ziegel Ges.m.b.H. & Co KG",
    "wof:placetype":"venue"
},
  "geometry": {"coordinates":[14.0234451294,48.3086395264],"type":"Point"}
}