{
  "type": "Feature",
  "properties": {
    "addr:full":"Nr 174 Feichten Tirol 6524",
    "addr:postcode":"6524",
    "addr:street":"Nr;Feichten Tirol",
    "iso:country":"AT",
    "sg:address":"Nr 174",
    "sg:city":"Feichten",
    "sg:orig_category":"Pensionen / Privatzimmer",
    "sg:phone":"+43 4354 75212",
    "sg:postcode":"6524",
    "sg:province":"Tirol",
    "wof:name":"Penz Thomas",
    "wof:placetype":"venue"
},
  "geometry": {"coordinates":[10.7479600906,47.0302619934],"type":"Point"}
}