{
  "type": "Feature",
  "properties": {
    "iso:country":"AT",
    "sg:address":"Poststr 4",
    "sg:city":"Pasching",
    "sg:orig_category":"Elektrotechnik",
    "sg:phone":"+43 7229 51155",
    "sg:postcode":"4061",
    "sg:province":"Ober\u00f6sterreich",
    "wof:name":"ROWA-MOSER Handels GmbH",
    "wof:placetype":"venue"
},
  "geometry": {"coordinates":[14.2342939377,48.2404899597],"type":"Point"}
}