{
  "type": "Feature",
  "properties": {
    "addr:full":"Herbststrasse 43 Wien Wien 1160",
    "addr:housenumber":"43",
    "addr:postcode":"1160",
    "addr:street":"Herbststrasse",
    "iso:country":"AT",
    "sg:address":"Herbststrasse 43",
    "sg:city":"Wien",
    "sg:classifiers":[
        {
            "category":"Organizations",
            "subcategory":"Labor Organization",
            "type":"Services"
        }
    ],
    "sg:phone":"+43 1 4942117",
    "sg:postcode":"1160",
    "sg:province":"Wien",
    "sg:tags":[
        "information",
        "technology",
        "administration",
        "municipal"
    ],
    "wof:name":"G\u00f6tzinger KEG",
    "wof:placetype":"venue"
},
  "geometry": {"coordinates":[16.3279266357,48.2060966492],"type":"Point"}
}