{
  "type": "Feature",
  "properties": {
    "addr:full":"Unterer Breitenweg 24 St. Peter Steiermark 8042",
    "addr:housenumber":"24",
    "addr:postcode":"8042",
    "addr:street":"Unterer Breitenweg",
    "iso:country":"AT",
    "sg:address":"Unterer Breitenweg 24",
    "sg:city":"St. Peter",
    "sg:orig_category":"Montagen U Montagetechnik",
    "sg:phone":"+43 316 461519",
    "sg:postcode":"8042",
    "sg:province":"Steiermark",
    "wof:name":"STC Montage- und VertriebsgesmbH",
    "wof:placetype":"venue"
},
  "geometry": {"coordinates":[15.4830827713,47.0628204346],"type":"Point"}
}