{
  "type": "Feature",
  "properties": {
    "iso:country":"AT",
    "sg:address":"Hauptstr 37",
    "sg:city":"Mattersburg",
    "sg:orig_category":"Ingenieurkonsulenten / Zivilingenieure",
    "sg:phone":"+43 2626 62179",
    "sg:postcode":"7210",
    "sg:province":"Burgenland",
    "wof:name":"Prost Manfred Prof Dipl-Ing",
    "wof:placetype":"venue"
},
  "geometry": {"coordinates":[16.3955955505,47.7348709106],"type":"Point"}
}