{
  "type": "Feature",
  "properties": {
    "addr:full":"Treietstr. 10  Klaus-Weiler Vorarlberg 6833",
    "addr:housenumber":"10",
    "addr:postcode":"6833",
    "addr:street":"Treietstr.",
    "iso:country":"AT",
    "sg:address":"Treietstr. 10 ",
    "sg:city":"Klaus-Weiler",
    "sg:classifiers":[
        {
            "category":"Manufacturing",
            "subcategory":"Rubber & Plastics",
            "type":"Manufacturing & Wholesale Goods"
        }
    ],
    "sg:phone":"+43 4355 235040",
    "sg:postcode":"6833",
    "sg:province":"Vorarlberg",
    "wof:name":"CARCOUSTICS AUSTRIA GMBH",
    "wof:placetype":"venue"
},
  "geometry": {"coordinates":[9.6312599182,47.3071975708],"type":"Point"}
}