{
  "type": "Feature",
  "properties": {
    "iso:country":"AT",
    "sg:address":"Mariazeller G 10",
    "sg:city":"Maria Enzersdorf",
    "sg:orig_category":"Fleischhauereien",
    "sg:phone":"+43 2236 23316",
    "sg:postcode":"2344",
    "sg:province":"Nieder\u00f6sterreich",
    "wof:name":"Schwab Gerhard",
    "wof:placetype":"venue"
},
  "geometry": {"coordinates":[16.2829189301,48.099357605],"type":"Point"}
}