{
  "type": "Feature",
  "properties": {
    "addr:full":"Querstr 8 Traun Ober\u00f6sterreich 4050",
    "addr:housenumber":"8",
    "addr:postcode":"4050",
    "addr:street":"Querstr",
    "iso:country":"AT",
    "sg:address":"Querstr 8",
    "sg:city":"Traun",
    "sg:orig_category":"Immobilienmakler",
    "sg:phone":"+43 7229 91122",
    "sg:postcode":"4050",
    "sg:province":"Ober\u00f6sterreich",
    "wof:name":"CBA Immobilia GmbH",
    "wof:placetype":"venue"
},
  "geometry": {"coordinates":[14.2049303055,48.2135391235],"type":"Point"}
}