{
  "type": "Feature",
  "properties": {
    "addr:full":"Hadikg 124 Wien Wien 1140",
    "addr:housenumber":"124",
    "addr:postcode":"1140",
    "iso:country":"AT",
    "sg:address":"Hadikg 124",
    "sg:city":"Wien",
    "sg:orig_category":"Friseure U Frisiersalons",
    "sg:phone":"+43 4318 948107",
    "sg:postcode":"1140",
    "sg:province":"Wien",
    "wof:name":"Gutmann Maria",
    "wof:placetype":"venue"
},
  "geometry": {"coordinates":[16.2956886292,48.1899833679],"type":"Point"}
}