{
  "type": "Feature",
  "properties": {
    "addr:full":"Einsiedlerg 15-17 Wien Wien 1050",
    "addr:postcode":"15-17;1050",
    "iso:country":"AT",
    "sg:address":"Einsiedlerg 15-17",
    "sg:city":"Wien",
    "sg:classifiers":[
        {
            "category":"Organizations",
            "subcategory":"Political Organization",
            "type":"Services"
        }
    ],
    "sg:phone":"+43 1 5457618",
    "sg:postcode":"1050",
    "sg:province":"Wien",
    "sg:tags":[
        "mediation"
    ],
    "wof:name":"Derflinger-Paar Maria Dr",
    "wof:placetype":"venue"
},
  "geometry": {"coordinates":[16.3502159119,48.1839904785],"type":"Point"}
}