{
  "type": "Feature",
  "properties": {
    "iso:country":"AT",
    "sg:address":"Nr 15",
    "sg:city":"St. Leonhard am Forst",
    "sg:orig_category":"Biologische Produkte",
    "sg:phone":"+43 2755 7404",
    "sg:postcode":"3243",
    "sg:province":"Nieder\u00f6sterreich",
    "wof:name":"Karner & Stefan OEG",
    "wof:placetype":"venue"
},
  "geometry": {"coordinates":[9.785900116,47.8096809387],"type":"Point"}
}