{
  "type": "Feature",
  "properties": {
    "addr:full":"Bahnhofstr 3 Prambachkirchen Ober\u00f6sterreich 4731",
    "addr:housenumber":"3",
    "addr:postcode":"4731",
    "addr:street":"Bahnhofstr",
    "iso:country":"AT",
    "sg:address":"Bahnhofstr 3",
    "sg:city":"Prambachkirchen",
    "sg:orig_category":"Friseure U Frisiersalons",
    "sg:phone":"+43 4372 773303",
    "sg:postcode":"4731",
    "sg:province":"Ober\u00f6sterreich",
    "wof:name":"Friseursalon Ulli Humer",
    "wof:placetype":"venue"
},
  "geometry": {"coordinates":[13.9003171921,48.3176460266],"type":"Point"}
}