{
  "type": "Feature",
  "properties": {
    "addr:full":"Sillian 117 Sillian Tirol 9920",
    "addr:housenumber":"117",
    "addr:postcode":"9920",
    "addr:street":"Sillian;Tirol",
    "iso:country":"AT",
    "sg:address":"Sillian 117",
    "sg:city":"Sillian",
    "sg:orig_category":"Hospital Equipment",
    "sg:phone":"+43 4842 67770",
    "sg:postcode":"9920",
    "sg:province":"Tirol",
    "sg:website":"kvt.at",
    "wof:name":"Krautgasser Versorgungstechnik GmbH",
    "wof:placetype":"venue"
},
  "geometry": {"coordinates":[12.4253540039,46.7489280701],"type":"Point"}
}