{
  "type": "Feature",
  "properties": {
    "iso:country":"AT",
    "sg:address":"Wegbachstr 2",
    "sg:city":"Waizenkirchen",
    "sg:orig_category":"Lebensmittel / Einzelhandel",
    "sg:phone":"+43 4372 7727792",
    "sg:postcode":"4730",
    "sg:province":"Ober\u00f6sterreich",
    "wof:name":"Billa AG",
    "wof:placetype":"venue"
},
  "geometry": {"coordinates":[13.8564119339,48.3294448853],"type":"Point"}
}