{
  "type": "Feature",
  "properties": {
    "addr:full":"Brauhausstr 40 Schwechat Nieder\u00f6sterreich 2320",
    "addr:housenumber":"40",
    "addr:postcode":"2320",
    "addr:street":"Brauhausstr;Niederoesterreich",
    "iso:country":"AT",
    "sg:address":"Brauhausstr 40",
    "sg:city":"Schwechat",
    "sg:classifiers":[
        {
            "category":"Taxi",
            "type":"Transportation"
        }
    ],
    "sg:phone":"+43 1 7073100",
    "sg:postcode":"2320",
    "sg:province":"Nieder\u00f6sterreich",
    "sg:tags":[
        "personentransporte",
        "u"
    ],
    "wof:name":"Jetbus Airport Shuttle",
    "wof:placetype":"venue"
},
  "geometry": {"coordinates":[16.4726104736,48.1411590576],"type":"Point"}
}