{
  "type": "Feature",
  "properties": {
    "iso:country":"AT",
    "sg:address":"Haslach 55",
    "sg:city":"Zell am Ziller",
    "sg:orig_category":"Appartements / Ferienwohnungen",
    "sg:phone":"+43 4352 822579",
    "sg:postcode":"6280",
    "sg:province":"Tirol",
    "wof:name":"Ferienwohnung Pfund",
    "wof:placetype":"venue"
},
  "geometry": {"coordinates":[11.9009542465,47.2434043884],"type":"Point"}
}