{
  "type": "Feature",
  "properties": {
    "addr:full":"Haslach 55 Zell am Ziller Tirol 6280",
    "addr:housenumber":"55",
    "addr:postcode":"6280",
    "addr:street":"Haslach;Tirol",
    "iso:country":"AT",
    "sg:address":"Haslach 55",
    "sg:city":"Zell am Ziller",
    "sg:orig_category":"Appartements / Ferienwohnungen",
    "sg:phone":"+43 4352 822579",
    "sg:postcode":"6280",
    "sg:province":"Tirol",
    "wof:name":"Ferienwohnung Pfund",
    "wof:placetype":"venue"
},
  "geometry": {"coordinates":[11.9009542465,47.2434043884],"type":"Point"}
}