{
  "type": "Feature",
  "properties": {
    "iso:country":"AT",
    "sg:address":"Mozartstr 9",
    "sg:city":"Linz",
    "sg:classifiers":[
        {
            "category":"Professional",
            "subcategory":"Computer Services",
            "type":"Services"
        }
    ],
    "sg:phone":"+43 732 775115",
    "sg:postcode":"4020",
    "sg:province":"Ober\u00f6sterreich",
    "sg:tags":[
        "software"
    ],
    "wof:name":"dvo Software Entwicklungs- und Vertriebs-GmbH",
    "wof:placetype":"venue"
},
  "geometry": {"coordinates":[14.2919368744,48.3013877869],"type":"Point"}
}