{
  "type": "Feature",
  "properties": {
    "addr:full":"Pimminghofstr 11 Wartberg an der Krems Ober\u00f6sterreich 4552",
    "addr:housenumber":"11",
    "addr:postcode":"4552",
    "addr:street":"Pimminghofstr",
    "iso:country":"AT",
    "sg:address":"Pimminghofstr 11",
    "sg:city":"Wartberg an der Krems",
    "sg:orig_category":"Tischlereien",
    "sg:phone":"+43 4375 877667",
    "sg:postcode":"4552",
    "sg:province":"Ober\u00f6sterreich",
    "wof:name":"Limberger Karl",
    "wof:placetype":"venue"
},
  "geometry": {"coordinates":[14.110906601,47.9772109985],"type":"Point"}
}