{
  "type": "Feature",
  "properties": {
    "addr:full":"Brunnthalg 30 Hollabrunn Nieder\u00f6sterreich 2020",
    "addr:housenumber":"30",
    "addr:postcode":"2020",
    "addr:street":"Brunnthalg",
    "iso:country":"AT",
    "sg:address":"Brunnthalg 30",
    "sg:city":"Hollabrunn",
    "sg:orig_category":"Gewerkschaften",
    "sg:phone":"+43 2952 2433",
    "sg:postcode":"2020",
    "sg:province":"Nieder\u00f6sterreich",
    "wof:name":"\u00f6sterreichischer Gewerkschaftsbund",
    "wof:placetype":"venue"
},
  "geometry": {"coordinates":[16.0739173889,48.565662384],"type":"Point"}
}