{
  "type": "Feature",
  "properties": {
    "addr:full":"Hafenstr 65 Krems an der Donau Nieder\u00f6sterreich 3500",
    "addr:housenumber":"65",
    "addr:postcode":"3500",
    "addr:street":"Hafenstr",
    "iso:country":"AT",
    "sg:address":"Hafenstr 65",
    "sg:city":"Krems an der Donau",
    "sg:orig_category":"Autohandel",
    "sg:phone":"+43 2732 836620",
    "sg:postcode":"3500",
    "sg:province":"Nieder\u00f6sterreich",
    "wof:name":"Kneth 1-2-3 GesmbH",
    "wof:placetype":"venue"
},
  "geometry": {"coordinates":[15.6288442612,48.4095954895],"type":"Point"}
}