{
  "type": "Feature",
  "properties": {
    "iso:country":"AT",
    "sg:address":"Sauboden 58",
    "sg:city":"Arriach",
    "sg:orig_category":"Autobusunternehmen",
    "sg:phone":"+43 4247 8564",
    "sg:postcode":"9543",
    "sg:province":"K\u00e4rnten",
    "wof:name":"Klammer Ingrid",
    "wof:placetype":"venue"
},
  "geometry": {"coordinates":[13.8445301056,46.7298355103],"type":"Point"}
}