{
  "type": "Feature",
  "properties": {
    "addr:full":"Derschstrasse 38 Ladendorf Nieder\u00f6sterreich 2126",
    "addr:housenumber":"38",
    "addr:postcode":"2126",
    "addr:street":"Derschstrasse",
    "iso:country":"AT",
    "sg:address":"Derschstrasse 38",
    "sg:city":"Ladendorf",
    "sg:orig_category":"Curve Conveyors",
    "sg:phone":"+43 2575 2304",
    "sg:postcode":"2126",
    "sg:province":"Nieder\u00f6sterreich",
    "sg:website":"contibelt.com",
    "wof:name":"CONTIBELT Band Systeme GmbH",
    "wof:placetype":"venue"
},
  "geometry": {"coordinates":[16.4832038879,48.5351066589],"type":"Point"}
}