{
  "type": "Feature",
  "properties": {
    "iso:country":"AT",
    "sg:address":"Nr 151",
    "sg:city":"St. Georgen am Steinfelde",
    "sg:orig_category":"Installationsmaterialien",
    "sg:phone":"+43 4327 4228326",
    "sg:postcode":"3151",
    "sg:province":"Nieder\u00f6sterreich",
    "wof:name":"Ratzenberger Haustechnik-Installations GmbH",
    "wof:placetype":"venue"
},
  "geometry": {"coordinates":[15.6132936478,48.1385231018],"type":"Point"}
}