{
  "type": "Feature",
  "properties": {
    "iso:country":"AT",
    "sg:address":"Brunecker Str 2a",
    "sg:city":"Innsbruck",
    "sg:classifiers":[
        {
            "category":"Travel",
            "subcategory":"Hotels & Motels",
            "type":"Entertainment"
        }
    ],
    "sg:phone":"+43 4351 2586432",
    "sg:postcode":"6020",
    "sg:province":"Tirol",
    "sg:website":"lady-o.at",
    "wof:name":"Nightclub Lady-O",
    "wof:placetype":"venue"
},
  "geometry": {"coordinates":[11.4009437561,47.2663726807],"type":"Point"}
}