{
  "type": "Feature",
  "properties": {
    "addr:full":"Lunzerstr 64 Linz Ober\u00f6sterreich 4030",
    "addr:housenumber":"64",
    "addr:postcode":"4030",
    "addr:street":"Lunzerstr",
    "iso:country":"AT",
    "sg:address":"Lunzerstr 64",
    "sg:city":"Linz",
    "sg:orig_category":"Umwelttechnik",
    "sg:phone":"+43 732 69890",
    "sg:postcode":"4030",
    "sg:province":"Ober\u00f6sterreich",
    "wof:name":"AE Energietechnik GmbH",
    "wof:placetype":"venue"
},
  "geometry": {"coordinates":[14.3253498077,48.2576217651],"type":"Point"}
}