{
  "type": "Feature",
  "properties": {
    "iso:country":"AT",
    "sg:address":"Franz-Stelzhamer-Str 20",
    "sg:city":"Braunau am Inn",
    "sg:orig_category":"Autoverwertung",
    "sg:phone":"+43 699 11304361",
    "sg:postcode":"5280",
    "sg:province":"Ober\u00f6sterreich",
    "wof:name":"Autoverwertung Pippa",
    "wof:placetype":"venue"
},
  "geometry": {"coordinates":[13.0549602509,48.2603263855],"type":"Point"}
}