{
  "type": "Feature",
  "properties": {
    "addr:full":"Hansi-Niese-Weg 8 Wien Wien 1130",
    "addr:housenumber":"8",
    "addr:postcode":"1130",
    "addr:street":"Hansi-Niese-Weg",
    "iso:country":"AT",
    "sg:address":"Hansi-Niese-Weg 8",
    "sg:city":"Wien",
    "sg:classifiers":[
        {
            "category":"Communications",
            "subcategory":"Film & Video Production",
            "type":"Services"
        }
    ],
    "sg:phone":"+43 1 8045234",
    "sg:postcode":"1130",
    "sg:province":"Wien",
    "sg:tags":[
        "application",
        "software",
        "cad/cam/cae"
    ],
    "sg:website":"pipeflowsoft.com",
    "wof:name":"Pipeflow Software Hydraulische Informationssysteme GmbH",
    "wof:placetype":"venue"
},
  "geometry": {"coordinates":[16.2866134644,48.1789245605],"type":"Point"}
}