{
  "type": "Feature",
  "properties": {
    "addr:full":"Klappholzstr 12/11 Innsbruck Tirol 6020",
    "addr:housenumber":"12 / 11",
    "addr:postcode":"6020",
    "addr:street":"Klappholzstr;Tirol",
    "iso:country":"AT",
    "sg:address":"Klappholzstr 12/11",
    "sg:city":"Innsbruck",
    "sg:orig_category":"Transportunternehmen",
    "sg:phone":"+43 512 391333",
    "sg:postcode":"6020",
    "sg:province":"Tirol",
    "wof:name":"Rabeder Oswald",
    "wof:placetype":"venue"
},
  "geometry": {"coordinates":[11.4184732437,47.2700309753],"type":"Point"}
}