{
  "type": "Feature",
  "properties": {
    "iso:country":"AT",
    "sg:address":"Gudrunstr 184/6",
    "sg:city":"Wien",
    "sg:orig_category":"Baumeister",
    "sg:phone":"+43 4316 418462",
    "sg:postcode":"1100",
    "sg:province":"Wien",
    "wof:name":"HARVIS Export u Import GmbH",
    "wof:placetype":"venue"
},
  "geometry": {"coordinates":[16.3628425598,48.1790924072],"type":"Point"}
}