{
  "type": "Feature",
  "properties": {
    "addr:full":"Schlo\u00dfpl 5 Oberpullendorf Burgenland 7350",
    "addr:housenumber":"5",
    "addr:postcode":"7350",
    "addr:street":"Schlosspl",
    "iso:country":"AT",
    "sg:address":"Schlo\u00dfpl 5",
    "sg:city":"Oberpullendorf",
    "sg:orig_category":"Raumgestaltung",
    "sg:phone":"+43 4326 1242377",
    "sg:postcode":"7350",
    "sg:province":"Burgenland",
    "wof:name":"Probszt - Raum & Raum",
    "wof:placetype":"venue"
},
  "geometry": {"coordinates":[16.5033950806,47.5031051636],"type":"Point"}
}