{
  "type": "Feature",
  "properties": {
    "addr:full":"Steindorf Au 3 Niedernsill Salzburg 5722",
    "addr:housenumber":"3",
    "addr:postcode":"5722",
    "addr:street":"Steindorf Au;Salzburg",
    "iso:country":"AT",
    "sg:address":"Steindorf Au 3",
    "sg:city":"Niedernsill",
    "sg:orig_category":"Schneidereien",
    "sg:phone":"+43 6548 8166",
    "sg:postcode":"5722",
    "sg:province":"Salzburg",
    "wof:name":"Obernosterer Cornelia - Trachtenschneiderei",
    "wof:placetype":"venue"
},
  "geometry": {"coordinates":[12.641872406,47.2853507996],"type":"Point"}
}