{
  "type": "Feature",
  "properties": {
    "iso:country":"AT",
    "sg:address":"Salzstr 2",
    "sg:city":"Stadl-Paura",
    "sg:orig_category":"Banken U Sparkassen",
    "sg:phone":"+43 4372 4532218",
    "sg:postcode":"4651",
    "sg:province":"Ober\u00f6sterreich",
    "wof:name":"Raiffeisenbank Edt-Lambach regGenmbH",
    "wof:placetype":"venue"
},
  "geometry": {"coordinates":[13.8610296249,48.0822753906],"type":"Point"}
}