{
  "type": "Feature",
  "properties": {
    "addr:full":"Friedrich Lintner-Pl 3 Gablitz Nieder\u00f6sterreich 3003",
    "addr:housenumber":"3",
    "addr:postcode":"3003",
    "iso:country":"AT",
    "sg:address":"Friedrich Lintner-Pl 3",
    "sg:city":"Gablitz",
    "sg:orig_category":"Fernsehservice",
    "sg:phone":"+43 2231 66284",
    "sg:postcode":"3003",
    "sg:province":"Nieder\u00f6sterreich",
    "wof:name":"Electronic Paschek",
    "wof:placetype":"venue"
},
  "geometry": {"coordinates":[16.1656627655,48.2190132141],"type":"Point"}
}