{
  "type": "Feature",
  "properties": {
    "addr:full":"Wirtschaftspark 7.Str Kematen an der Ybbs Nieder\u00f6sterreich 3331",
    "addr:housenumber":"7.str",
    "addr:postcode":"3331",
    "addr:street":"Wirtschaftspark;Niederoesterreich",
    "iso:country":"AT",
    "sg:address":"Wirtschaftspark 7.Str",
    "sg:city":"Kematen an der Ybbs",
    "sg:orig_category":"Beton- U Betonsteinwerke",
    "sg:phone":"+43 4374 7677766",
    "sg:postcode":"3331",
    "sg:province":"Nieder\u00f6sterreich",
    "wof:name":"Betonkurier - Transportbeton GmbH",
    "wof:placetype":"venue"
},
  "geometry": {"coordinates":[14.7680454254,48.0269813538],"type":"Point"}
}