{
  "type": "Feature",
  "properties": {
    "addr:full":"Zeleborg 24 Wien Wien 1120",
    "addr:housenumber":"24",
    "addr:postcode":"1120",
    "addr:street":"Zeleborg",
    "iso:country":"AT",
    "sg:address":"Zeleborg 24",
    "sg:city":"Wien",
    "sg:orig_category":"Pumpen",
    "sg:phone":"+43 1 81365080",
    "sg:postcode":"1120",
    "sg:province":"Wien",
    "sg:website":"metso.com",
    "wof:name":"Metso Minerals (Austria) GmbH",
    "wof:placetype":"venue"
},
  "geometry": {"coordinates":[16.330915451,48.1775169373],"type":"Point"}
}