{
  "type": "Feature",
  "properties": {
    "addr:full":"Mahlerstr 13 Wien Wien 1010",
    "addr:housenumber":"13",
    "addr:postcode":"1010",
    "addr:street":"Mahlerstr",
    "iso:country":"AT",
    "sg:address":"Mahlerstr 13",
    "sg:city":"Wien",
    "sg:classifiers":[
        {
            "category":"Restaurant",
            "type":"Food & Drink"
        }
    ],
    "sg:phone":"+43 1 5128961",
    "sg:postcode":"1010",
    "sg:province":"Wien",
    "wof:name":"Restaurant Die Spedition",
    "wof:placetype":"venue"
},
  "geometry": {"coordinates":[16.3731575012,48.2024917603],"type":"Point"}
}