{
  "type": "Feature",
  "properties": {
    "iso:country":"AT",
    "sg:address":"Nr 32",
    "sg:city":"Niederndorf",
    "sg:orig_category":"Banken U Sparkassen",
    "sg:phone":"+43 4353 73613300",
    "sg:postcode":"6342",
    "sg:province":"Tirol",
    "wof:name":"Raiffeisenbank Niederndorf-Walchsee regGenmbH",
    "wof:placetype":"venue"
},
  "geometry": {"coordinates":[12.2141237259,47.6500205994],"type":"Point"}
}