{
  "type": "Feature",
  "properties": {
    "addr:full":"Frankenburger Str 13 Ried im Innkreis Ober\u00f6sterreich 4910",
    "addr:postcode":"4910",
    "addr:street":"Str 13",
    "iso:country":"AT",
    "sg:address":"Frankenburger Str 13",
    "sg:city":"Ried im Innkreis",
    "sg:orig_category":"\u00c3\u201erzte / F Allgemeinmedizin",
    "sg:phone":"+43 7752 88880",
    "sg:postcode":"4910",
    "sg:province":"Ober\u00f6sterreich",
    "wof:name":"Dirisamer Hildegard Dr",
    "wof:placetype":"venue"
},
  "geometry": {"coordinates":[13.4829378128,48.2035865784],"type":"Point"}
}