{
  "type": "Feature",
  "properties": {
    "addr:full":"Egethen 1a Altach Vorarlberg 6844",
    "addr:housenumber":"1a",
    "addr:postcode":"6844",
    "addr:street":"Egethen",
    "iso:country":"AT",
    "sg:address":"Egethen 1a",
    "sg:city":"Altach",
    "sg:orig_category":"Metallbe- U -Verarbeitung",
    "sg:phone":"+43 5576 42572",
    "sg:postcode":"6844",
    "sg:province":"Vorarlberg",
    "wof:name":"SCHLEIF-TEC Kunibert M\u00fcller",
    "wof:placetype":"venue"
},
  "geometry": {"coordinates":[9.6414108276,47.3536643982],"type":"Point"}
}