{
  "type": "Feature",
  "properties": {
    "iso:country":"AT",
    "sg:address":"Adalbert Stifter-Str 34",
    "sg:city":"Wien",
    "sg:orig_category":"Tabaktrafiken",
    "sg:phone":"+43 1 3322501",
    "sg:postcode":"1200",
    "sg:province":"Wien",
    "wof:name":"Hofmeister Viktor",
    "wof:placetype":"venue"
},
  "geometry": {"coordinates":[16.3707370758,48.2402191162],"type":"Point"}
}