{
  "type": "Feature",
  "properties": {
    "addr:full":"Michael-Hainisch-Str 53 Lichtenw\u00f6rth Nieder\u00f6sterreich 2493",
    "addr:housenumber":"53",
    "addr:postcode":"2493",
    "addr:street":"Michael-Hainisch-Str;Niederoesterreich",
    "iso:country":"AT",
    "sg:address":"Michael-Hainisch-Str 53",
    "sg:city":"Lichtenw\u00f6rth",
    "sg:orig_category":"Eisen",
    "sg:phone":"+43 4326 2276166",
    "sg:postcode":"2493",
    "sg:province":"Nieder\u00f6sterreich",
    "sg:website":"eisenwolf.at",
    "wof:name":"Wolf Andreas GmbH & Co KG",
    "wof:placetype":"venue"
},
  "geometry": {"coordinates":[16.2962799072,47.8375015259],"type":"Point"}
}