{
  "type": "Feature",
  "properties": {
    "iso:country":"AT",
    "sg:address":"Joseph-Mohr-Str 2",
    "sg:city":"Oberndorf",
    "sg:orig_category":"Drogerien",
    "sg:phone":"+43 4362 726730",
    "sg:postcode":"5110",
    "sg:province":"Salzburg",
    "wof:name":"dm drogerie markt GmbH",
    "wof:placetype":"venue"
},
  "geometry": {"coordinates":[12.9429292679,47.9437179565],"type":"Point"}
}