{
  "type": "Feature",
  "properties": {
    "addr:full":"Preyhsg 4 Pfaffst\u00e4tten Nieder\u00f6sterreich 2511",
    "addr:housenumber":"4",
    "addr:postcode":"2511",
    "addr:street":"Preyhsg;Niederoesterreich",
    "iso:country":"AT",
    "sg:address":"Preyhsg 4",
    "sg:city":"Pfaffst\u00e4tten",
    "sg:orig_category":"\u00c3\u201erzte / F Allgemeinmedizin",
    "sg:phone":"+43 4322 5285120",
    "sg:postcode":"2511",
    "sg:province":"Nieder\u00f6sterreich",
    "wof:name":"Hofst\u00e4dter Rudolf Dr",
    "wof:placetype":"venue"
},
  "geometry": {"coordinates":[-80.2287368774,40.6490936279],"type":"Point"}
}