{
  "type": "Feature",
  "properties": {
    "addr:full":"Brunfeldstr 2 Heidenreichstein Nieder\u00f6sterreich 3860",
    "addr:housenumber":"2",
    "addr:postcode":"3860",
    "addr:street":"Brunfeldstr",
    "iso:country":"AT",
    "sg:address":"Brunfeldstr 2",
    "sg:city":"Heidenreichstein",
    "sg:classifiers":[
        {
            "category":"Professional",
            "subcategory":"Printing & Photocopies",
            "type":"Services"
        }
    ],
    "sg:phone":"+43 4328 6252278",
    "sg:postcode":"3860",
    "sg:province":"Nieder\u00f6sterreich",
    "wof:name":"ING CHRISTIAN JANETSCHEK",
    "wof:placetype":"venue"
},
  "geometry": {"coordinates":[15.1201248169,48.8675308228],"type":"Point"}
}