{
  "type": "Feature",
  "properties": {
    "addr:full":"Dietrichg 46 Wien Wien 1030",
    "addr:housenumber":"46",
    "addr:postcode":"1030",
    "addr:street":"Dietrichg",
    "iso:country":"AT",
    "sg:address":"Dietrichg 46",
    "sg:city":"Wien",
    "sg:orig_category":"Tabaktrafiken",
    "sg:phone":"+43 1 7120635",
    "sg:postcode":"1030",
    "sg:province":"Wien",
    "wof:name":"Gruber Hannelore",
    "wof:placetype":"venue"
},
  "geometry": {"coordinates":[16.4068412781,48.1973686218],"type":"Point"}
}