{
  "type": "Feature",
  "properties": {
    "addr:full":"Peter Jordan Strasse, 66 -  Wien Wien 1190",
    "addr:housenumber":"66",
    "addr:postcode":"1190",
    "addr:street":"Peter Jordan Strasse",
    "iso:country":"AT",
    "sg:address":"Peter Jordan Strasse, 66 - ",
    "sg:city":"Wien",
    "sg:classifiers":[
        {
            "category":"Professional",
            "subcategory":"Art Services",
            "type":"Services"
        }
    ],
    "sg:phone":"+43 4313 681455",
    "sg:postcode":"1190",
    "sg:province":"Wien",
    "sg:tags":[
        "export-import"
    ],
    "wof:name":"UAE Embassy",
    "wof:placetype":"venue"
},
  "geometry": {"coordinates":[16.3391304016,48.2370986938],"type":"Point"}
}