{
  "type": "Feature",
  "properties": {
    "addr:full":"Hauptstr 58 Eggendorf Nieder\u00f6sterreich 2492",
    "addr:housenumber":"58",
    "addr:postcode":"2492",
    "addr:street":"Hauptstr",
    "iso:country":"AT",
    "sg:address":"Hauptstr 58",
    "sg:city":"Eggendorf",
    "sg:orig_category":"Tabaktrafiken",
    "sg:phone":"+43 2622 73227",
    "sg:postcode":"2492",
    "sg:province":"Nieder\u00f6sterreich",
    "wof:name":"Schwarzott Josef",
    "wof:placetype":"venue"
},
  "geometry": {"coordinates":[16.3187427521,47.8564910889],"type":"Point"}
}