{
  "type": "Feature",
  "properties": {
    "addr:full":"Gruberstr 82 Linz Ober\u00f6sterreich 4020",
    "addr:housenumber":"82",
    "addr:postcode":"4020",
    "addr:street":"Gruberstr",
    "iso:country":"AT",
    "sg:address":"Gruberstr 82",
    "sg:city":"Linz",
    "sg:classifiers":[
        {
            "category":"Retail",
            "subcategory":"Event Space",
            "type":"Services"
        }
    ],
    "sg:phone":"+43 4373 2770172",
    "sg:postcode":"4020",
    "sg:province":"Ober\u00f6sterreich",
    "sg:tags":[
        "hand-",
        "u",
        "fu\u00c3\u0178pflege"
    ],
    "wof:name":"Fu\u00dfpflege Helga",
    "wof:placetype":"venue"
},
  "geometry": {"coordinates":[14.300236702,48.3035507202],"type":"Point"}
}