{
  "type": "Feature",
  "properties": {
    "addr:full":"Kauerg 10/3 Wien Wien 1150",
    "addr:housenumber":"10 / 3",
    "addr:postcode":"1150",
    "addr:street":"Kauerg",
    "iso:country":"AT",
    "sg:address":"Kauerg 10/3",
    "sg:city":"Wien",
    "sg:orig_category":"Ingenieurkonsulenten / Zivilingenieure",
    "sg:phone":"+43 1 89260200",
    "sg:postcode":"1150",
    "sg:province":"Wien",
    "wof:name":"Silwester Alfred Dipl-Ing",
    "wof:placetype":"venue"
},
  "geometry": {"coordinates":[16.3237171173,48.191608429],"type":"Point"}
}