{
  "type": "Feature",
  "properties": {
    "addr:full":"Haggenm\u00fcllerg 16 Wiener Neustadt Nieder\u00f6sterreich 2700",
    "addr:housenumber":"16",
    "addr:postcode":"2700",
    "addr:street":"Haggenmuellerg",
    "iso:country":"AT",
    "sg:address":"Haggenm\u00fcllerg 16",
    "sg:city":"Wiener Neustadt",
    "sg:orig_category":"Bastelbedarf",
    "sg:phone":"+43 2622 22656",
    "sg:postcode":"2700",
    "sg:province":"Nieder\u00f6sterreich",
    "wof:name":"Lechner Johann - Zum Holzwurm",
    "wof:placetype":"venue"
},
  "geometry": {"coordinates":[16.2455158234,47.8128814697],"type":"Point"}
}