{
  "type": "Feature",
  "properties": {
    "addr:full":"Wr Neust\u00e4dter Str 99 Sollenau Nieder\u00f6sterreich 2601",
    "addr:housenumber":"99",
    "addr:postcode":"2601",
    "addr:street":"Str",
    "iso:country":"AT",
    "sg:address":"Wr Neust\u00e4dter Str 99",
    "sg:city":"Sollenau",
    "sg:orig_category":"Autohandel",
    "sg:phone":"+43 4326 2862144",
    "sg:postcode":"2601",
    "sg:province":"Nieder\u00f6sterreich",
    "wof:name":"Kahriman KEG",
    "wof:placetype":"venue"
},
  "geometry": {"coordinates":[16.2494049072,47.8965682983],"type":"Point"}
}