{
  "type": "Feature",
  "properties": {
    "addr:full":"Schwefel 33 Dornbirn Vorarlberg 6850",
    "addr:housenumber":"33",
    "addr:postcode":"6850",
    "addr:street":"Schwefel",
    "iso:country":"AT",
    "sg:address":"Schwefel 33",
    "sg:city":"Dornbirn",
    "sg:classifiers":[
        {
            "category":"Manufacturing",
            "subcategory":"Rubber & Plastics",
            "type":"Manufacturing & Wholesale Goods"
        }
    ],
    "sg:phone":"+43 4355 7224666",
    "sg:postcode":"6850",
    "sg:province":"Vorarlberg",
    "wof:name":"GUMMI RAAB REIFENHANDEL GMBH",
    "wof:placetype":"venue"
},
  "geometry": {"coordinates":[9.7415266037,47.4238586426],"type":"Point"}
}