{
  "type": "Feature",
  "properties": {
    "addr:full":"Auersthaler Weg 20 Markgrafneusiedl Nieder\u00f6sterreich 2282",
    "addr:housenumber":"20",
    "addr:postcode":"2282",
    "addr:street":"Auersthaler Weg",
    "iso:country":"AT",
    "sg:address":"Auersthaler Weg 20",
    "sg:city":"Markgrafneusiedl",
    "sg:classifiers":[
        {
            "category":"Taxi",
            "type":"Transportation"
        }
    ],
    "sg:phone":"+43 664 3344411",
    "sg:postcode":"2282",
    "sg:province":"Nieder\u00f6sterreich",
    "sg:tags":[
        "personentransporte",
        "u"
    ],
    "wof:name":"B\u00e4ck Stefan",
    "wof:placetype":"venue"
},
  "geometry": {"coordinates":[16.6272907257,48.2720108032],"type":"Point"}
}