{
  "type": "Feature",
  "properties": {
    "addr:full":"Hauptstr 9 Inzing Tirol 6401",
    "addr:housenumber":"9",
    "addr:postcode":"6401",
    "addr:street":"Hauptstr;Tirol",
    "iso:country":"AT",
    "sg:address":"Hauptstr 9",
    "sg:city":"Inzing",
    "sg:orig_category":"Tabaktrafiken",
    "sg:phone":"+43 5238 87488",
    "sg:postcode":"6401",
    "sg:province":"Tirol",
    "wof:name":"Wimmer Regina",
    "wof:placetype":"venue"
},
  "geometry": {"coordinates":[11.1983394623,47.2737197876],"type":"Point"}
}