{
  "type": "Feature",
  "properties": {
    "addr:full":"Klosterneuburger Str 67 Wien Wien 1200",
    "addr:postcode":"1200",
    "addr:street":"Str 67",
    "iso:country":"AT",
    "sg:address":"Klosterneuburger Str 67",
    "sg:city":"Wien",
    "sg:orig_category":"Baumeister",
    "sg:phone":"+43 1 3748371",
    "sg:postcode":"1200",
    "sg:province":"Wien",
    "wof:name":"M\u00fcllner H BaugesmbH",
    "wof:placetype":"venue"
},
  "geometry": {"coordinates":[16.3659133911,48.2324981689],"type":"Point"}
}