{
  "type": "Feature",
  "properties": {
    "addr:full":"Alserbachstr 14-16 Wien Wien 1090",
    "addr:postcode":"14-16;1090",
    "iso:country":"AT",
    "sg:address":"Alserbachstr 14-16",
    "sg:city":"Wien",
    "sg:orig_category":"Non-Classified Establishments",
    "sg:phone":"+43 1 3190701",
    "sg:postcode":"1090",
    "sg:province":"Wien",
    "wof:name":"APCS Power Clearing and Settlement AG",
    "wof:placetype":"venue"
},
  "geometry": {"coordinates":[16.3575649261,48.2247314453],"type":"Point"}
}