{
  "type": "Feature",
  "properties": {
    "iso:country":"AT",
    "sg:address":"K\u00f6nigsberger Str 24",
    "sg:city":"Pinkafeld",
    "sg:orig_category":"Rauchfangkehrer",
    "sg:phone":"+43 3357 42535",
    "sg:postcode":"7423",
    "sg:province":"Burgenland",
    "wof:name":"L\u00f6ffler Peter",
    "wof:placetype":"venue"
},
  "geometry": {"coordinates":[16.124250412,47.3718299866],"type":"Point"}
}