{
  "type": "Feature",
  "properties": {
    "addr:full":"Alberweg 12 M\u00e4der Vorarlberg 6841",
    "addr:housenumber":"12",
    "addr:postcode":"6841",
    "addr:street":"Alberweg",
    "iso:country":"AT",
    "sg:address":"Alberweg 12",
    "sg:city":"M\u00e4der",
    "sg:orig_category":"Berufsbekleidung / Einzelhandel",
    "sg:phone":"+43 5523 628850",
    "sg:postcode":"6841",
    "sg:province":"Vorarlberg",
    "sg:website":"robe.at",
    "wof:name":"Robe Berufsbekleidung",
    "wof:placetype":"venue"
},
  "geometry": {"coordinates":[-68.92627716059999,45.3928260803],"type":"Point"}
}