{
  "type": "Feature",
  "properties": {
    "addr:full":"Broth\u00e4uslweg 2 Eugendorf Salzburg 5301",
    "addr:housenumber":"2",
    "addr:postcode":"salzburg 5301",
    "addr:street":"Brothaeuslweg",
    "iso:country":"AT",
    "sg:address":"Broth\u00e4uslweg 2",
    "sg:city":"Eugendorf",
    "sg:orig_category":"Parksysteme U Parkraumbewirtschaftung",
    "sg:phone":"+43 6225 72350",
    "sg:postcode":"5301",
    "sg:province":"Salzburg",
    "wof:name":"AUTOPARKSYSTEME GmbH & Co KG",
    "wof:placetype":"venue"
},
  "geometry": {"coordinates":[13.130777359,47.8658370972],"type":"Point"}
}