{
  "type": "Feature",
  "properties": {
    "iso:country":"AT",
    "sg:address":"Jahnstr 20",
    "sg:city":"Bregenz",
    "sg:orig_category":"Damenmoden",
    "sg:phone":"+43 5574 44477",
    "sg:postcode":"6900",
    "sg:province":"Vorarlberg",
    "wof:name":"Monari BBG Fashion GesmbH",
    "wof:placetype":"venue"
},
  "geometry": {"coordinates":[9.7453517914,47.5031433105],"type":"Point"}
}