{
  "type": "Feature",
  "properties": {
    "addr:full":"Grafenhof Dorf 11 Schwarzach im Pongau Salzburg 5620",
    "addr:housenumber":"11",
    "addr:postcode":"5620",
    "addr:street":"Dorf;Salzburg",
    "iso:country":"AT",
    "sg:address":"Grafenhof Dorf 11",
    "sg:city":"Schwarzach im Pongau",
    "sg:orig_category":"Rettungsdienste",
    "sg:phone":"+43 664 3077880",
    "sg:postcode":"5620",
    "sg:province":"Salzburg",
    "wof:name":"\u00f6sterreichische Wasserrettung",
    "wof:placetype":"venue"
},
  "geometry": {"coordinates":[13.1771211624,47.3269119263],"type":"Point"}
}