{
  "type": "Feature",
  "properties": {
    "iso:country":"AT",
    "sg:address":"Neunkirchner Str 57e-f",
    "sg:city":"Wiener Neustadt",
    "sg:orig_category":"Autohandel",
    "sg:phone":"+43 2622 236800",
    "sg:postcode":"2700",
    "sg:province":"Nieder\u00f6sterreich",
    "sg:website":"www.hoenigmann.co.at",
    "wof:name":"H\u00f6nigmann Mazda",
    "wof:placetype":"venue"
},
  "geometry": {"coordinates":[16.2455158234,47.8128814697],"type":"Point"}
}