{
  "type": "Feature",
  "properties": {
    "addr:full":"Spittelwiese 2 Linz Ober\u00f6sterreich 4020",
    "addr:housenumber":"2",
    "addr:postcode":"4020",
    "addr:street":"Spittelwiese",
    "iso:country":"AT",
    "sg:address":"Spittelwiese 2",
    "sg:city":"Linz",
    "sg:orig_category":"Pelze U Pelzwaren",
    "sg:phone":"+43 732 774685",
    "sg:postcode":"4020",
    "sg:province":"Ober\u00f6sterreich",
    "wof:name":"Maier-Pelze",
    "wof:placetype":"venue"
},
  "geometry": {"coordinates":[14.2886190414,48.3029823303],"type":"Point"}
}