{
  "type": "Feature",
  "properties": {
    "addr:full":"Samerg 23a Salzburg Salzburg 5020",
    "addr:housenumber":"23a",
    "addr:postcode":"5020",
    "addr:street":"Samerg;Salzburg",
    "iso:country":"AT",
    "sg:address":"Samerg 23a",
    "sg:city":"Salzburg",
    "sg:orig_category":"Autolackierereien",
    "sg:phone":"+43 662 879634",
    "sg:postcode":"5020",
    "sg:province":"Salzburg",
    "sg:website":"dunhofer.at",
    "wof:name":"Dunhofer GesmbH",
    "wof:placetype":"venue"
},
  "geometry": {"coordinates":[13.0597333908,47.8159675598],"type":"Point"}
}