{
  "type": "Feature",
  "properties": {
    "iso:country":"AT",
    "sg:address":"Nr 47",
    "sg:city":"Grafenschlag",
    "sg:orig_category":"Gemeinden",
    "sg:phone":"+43 2875 8325",
    "sg:postcode":"3912",
    "sg:province":"Nieder\u00f6sterreich",
    "wof:name":"Gemeindeamt Grafenschlag",
    "wof:placetype":"venue"
},
  "geometry": {"coordinates":[15.1683778763,48.5006027222],"type":"Point"}
}