{
  "type": "Feature",
  "properties": {
    "addr:full":"Hauptpl 14 Mattersburg Burgenland 7210",
    "addr:housenumber":"14",
    "addr:postcode":"7210",
    "addr:street":"Hauptpl",
    "iso:country":"AT",
    "sg:address":"Hauptpl 14",
    "sg:city":"Mattersburg",
    "sg:orig_category":"Non-Classified Establishments",
    "sg:phone":"+43 2626 63341",
    "sg:postcode":"7210",
    "sg:province":"Burgenland",
    "wof:name":"Katholische Jugend und Jungschar Regionalstelle",
    "wof:placetype":"venue"
},
  "geometry": {"coordinates":[16.3987731934,47.7371559143],"type":"Point"}
}