{
  "type": "Feature",
  "properties": {
    "addr:full":"Pfarrpl 5 Klagenfurt K\u00e4rnten 9020",
    "addr:housenumber":"5",
    "addr:postcode":"9020",
    "addr:street":"Pfarrpl;Kaernten",
    "iso:country":"AT",
    "sg:address":"Pfarrpl 5",
    "sg:city":"Klagenfurt",
    "sg:orig_category":"Biologische Produkte",
    "sg:phone":"+43 463 502649",
    "sg:postcode":"9020",
    "sg:province":"K\u00e4rnten",
    "wof:name":"Naturkost Helgard Quendler",
    "wof:placetype":"venue"
},
  "geometry": {"coordinates":[14.3070802689,46.6260910034],"type":"Point"}
}