{
  "type": "Feature",
  "properties": {
    "addr:full":"Linzer Str 1a Gablitz Nieder\u00f6sterreich 3003",
    "addr:housenumber":"1a",
    "addr:postcode":"3003",
    "addr:street":"Linzer Str",
    "iso:country":"AT",
    "sg:address":"Linzer Str 1a",
    "sg:city":"Gablitz",
    "sg:orig_category":"Tankstellen",
    "sg:phone":"+43 2231 65316",
    "sg:postcode":"3003",
    "sg:province":"Nieder\u00f6sterreich",
    "wof:name":"OMV AG",
    "wof:placetype":"venue"
},
  "geometry": {"coordinates":[16.1654930115,48.2189407349],"type":"Point"}
}