{
  "type": "Feature",
  "properties": {
    "addr:full":"Th\u00fcrnlhofstr 30 Wien Wien 1110",
    "addr:housenumber":"30",
    "addr:postcode":"1110",
    "addr:street":"Thuernlhofstr",
    "iso:country":"AT",
    "sg:address":"Th\u00fcrnlhofstr 30",
    "sg:city":"Wien",
    "sg:orig_category":"Lebensmittel / Einzelhandel",
    "sg:phone":"+43 1 7672165",
    "sg:postcode":"1110",
    "sg:province":"Wien",
    "wof:name":"ADEG Aktiv Markt",
    "wof:placetype":"venue"
},
  "geometry": {"coordinates":[16.4197444916,48.1709709167],"type":"Point"}
}