{
  "type": "Feature",
  "properties": {
    "iso:country":"AT",
    "sg:address":"Silberwaldstr 67",
    "sg:city":"Strasshof an der Nordbahn",
    "sg:orig_category":"Dekorationsartikel",
    "sg:phone":"+43 664 2336728",
    "sg:postcode":"2231",
    "sg:province":"Nieder\u00f6sterreich",
    "wof:name":"Bernhard Emanuele - Dekorelemente aus Stein",
    "wof:placetype":"venue"
},
  "geometry": {"coordinates":[16.6668205261,48.322479248],"type":"Point"}
}