{
  "type": "Feature",
  "properties": {
    "addr:full":"Telfeser Landstr 111 Telfes im Stubai Tirol 6165",
    "addr:housenumber":"111",
    "addr:postcode":"6165",
    "addr:street":"Telfeser Landstr;Tirol",
    "iso:country":"AT",
    "sg:address":"Telfeser Landstr 111",
    "sg:city":"Telfes im Stubai",
    "sg:orig_category":"Fitnesscenter",
    "sg:phone":"+43 5225 65253",
    "sg:postcode":"6165",
    "sg:province":"Tirol",
    "wof:name":"Fitne\u00dfcenter Life Line",
    "wof:placetype":"venue"
},
  "geometry": {"coordinates":[11.3553962708,47.1593132019],"type":"Point"}
}