{
  "type": "Feature",
  "properties": {
    "addr:full":"Burgg 7 St. Veit an der Glan K\u00e4rnten 9300",
    "addr:housenumber":"7",
    "addr:postcode":"9300",
    "addr:street":"Burgg;Kaernten",
    "iso:country":"AT",
    "sg:address":"Burgg 7",
    "sg:city":"St. Veit an der Glan",
    "sg:orig_category":"Rauchfangkehrer",
    "sg:phone":"+43 4212 2114",
    "sg:postcode":"9300",
    "sg:province":"K\u00e4rnten",
    "wof:name":"Verderber Michael",
    "wof:placetype":"venue"
},
  "geometry": {"coordinates":[14.3590183258,46.7687759399],"type":"Point"}
}