{
  "type": "Feature",
  "properties": {
    "addr:full":"Industriestr 30 Zwettl Nieder\u00f6sterreich 3910",
    "addr:housenumber":"30",
    "addr:postcode":"3910",
    "addr:street":"Industriestr;Niederoesterreich",
    "iso:country":"AT",
    "sg:address":"Industriestr 30",
    "sg:city":"Zwettl",
    "sg:orig_category":"Restaurants: Amerikanisch",
    "sg:phone":"+43 2822 57052",
    "sg:postcode":"3910",
    "sg:province":"Nieder\u00f6sterreich",
    "wof:name":"McDonald's Restaurant - McDrive",
    "wof:placetype":"venue"
},
  "geometry": {"coordinates":[15.190779686,48.6002082825],"type":"Point"}
}