{
  "type": "Feature",
  "properties": {
    "addr:full":"G\u00e4nsackerweg 14 Serfaus Tirol 6534",
    "addr:housenumber":"14",
    "addr:postcode":"6534",
    "addr:street":"Gaensackerweg;Tirol",
    "iso:country":"AT",
    "sg:address":"G\u00e4nsackerweg 14",
    "sg:city":"Serfaus",
    "sg:orig_category":"Pensionen / Privatzimmer",
    "sg:phone":"+43 5476 6247",
    "sg:postcode":"6534",
    "sg:province":"Tirol",
    "wof:name":"Haus Elke",
    "wof:placetype":"venue"
},
  "geometry": {"coordinates":[10.6055402756,47.0392112732],"type":"Point"}
}