{
  "type": "Feature",
  "properties": {
    "addr:full":"Bahnhofstr 2 Tulln an der Donau Nieder\u00f6sterreich 3430",
    "addr:housenumber":"2",
    "addr:postcode":"3430",
    "addr:street":"Bahnhofstr",
    "iso:country":"AT",
    "sg:address":"Bahnhofstr 2",
    "sg:city":"Tulln an der Donau",
    "sg:orig_category":"Leder",
    "sg:phone":"+43 2272 62831",
    "sg:postcode":"3430",
    "sg:province":"Nieder\u00f6sterreich",
    "wof:name":"Beinhardt Veronika",
    "wof:placetype":"venue"
},
  "geometry": {"coordinates":[16.0534992218,48.330745697],"type":"Point"}
}