{
  "type": "Feature",
  "properties": {
    "addr:full":"Dr.-Alfred-Kranich-Pl 1 Pinkafeld Burgenland 7423",
    "addr:housenumber":"1",
    "addr:postcode":"7423",
    "addr:street":"Dr.-Alfred-Kranich-Pl",
    "iso:country":"AT",
    "sg:address":"Dr.-Alfred-Kranich-Pl 1",
    "sg:city":"Pinkafeld",
    "sg:orig_category":"Zeitungen U Zeitschriften / Vertrieb",
    "sg:phone":"+43 4333 5743508",
    "sg:postcode":"7423",
    "sg:province":"Burgenland",
    "wof:name":"Mediaprint Zeitungs- u Zeitschriftenverlag GesmbH & Co KG",
    "wof:placetype":"venue"
},
  "geometry": {"coordinates":[16.1242046356,47.3633270264],"type":"Point"}
}