{
  "type": "Feature",
  "properties": {
    "addr:full":"J\u00e4gerstr 62-64 Wien Wien 1200",
    "addr:postcode":"62-64;1200",
    "iso:country":"AT",
    "sg:address":"J\u00e4gerstr 62-64",
    "sg:city":"Wien",
    "sg:orig_category":"Papier- U Schreibwaren / Einzelhandel",
    "sg:phone":"+43 4313 324372",
    "sg:postcode":"1200",
    "sg:province":"Wien",
    "wof:name":"Dudaschek Inge",
    "wof:placetype":"venue"
},
  "geometry": {"coordinates":[16.370634079,48.2357139587],"type":"Point"}
}