{
  "type": "Feature",
  "properties": {
    "addr:full":"Forsthausstr 13 Wolfsgraben Nieder\u00f6sterreich 3012",
    "addr:housenumber":"13",
    "addr:postcode":"3012",
    "addr:street":"Forsthausstr",
    "iso:country":"AT",
    "sg:address":"Forsthausstr 13",
    "sg:city":"Wolfsgraben",
    "sg:orig_category":"Hausbetreuung",
    "sg:phone":"+43 4366 44538493",
    "sg:postcode":"3012",
    "sg:province":"Nieder\u00f6sterreich",
    "wof:name":"Embacher J u P Puskaric OEG",
    "wof:placetype":"venue"
},
  "geometry": {"coordinates":[16.1121311188,48.1531181335],"type":"Point"}
}