{
  "type": "Feature",
  "properties": {
    "addr:full":"Ginzkeystr 25 Wels Ober\u00f6sterreich 4600",
    "addr:housenumber":"25",
    "addr:postcode":"4600",
    "addr:street":"Ginzkeystr;Oberoesterreich",
    "iso:country":"AT",
    "sg:address":"Ginzkeystr 25",
    "sg:city":"Wels",
    "sg:orig_category":"Papierwaren / Erzeugung U Gro\u00c3\u0178handel",
    "sg:phone":"+43 4372 4257908",
    "sg:postcode":"4600",
    "sg:province":"Ober\u00f6sterreich",
    "wof:name":"PBS Logitek Dienstleistungen GmbH",
    "wof:placetype":"venue"
},
  "geometry": {"coordinates":[14.0607414246,48.1790084839],"type":"Point"}
}