{
  "type": "Feature",
  "properties": {
    "addr:full":"Maria-Gailer-Strasse 34 Villach K\u00e4rnten 9500",
    "addr:housenumber":"34",
    "addr:postcode":"9500",
    "addr:street":"Maria-Gailer-Strasse;Kaernten",
    "iso:country":"AT",
    "sg:address":"Maria-Gailer-Strasse 34",
    "sg:city":"Villach",
    "sg:classifiers":[
        {
            "category":"Home & Garden",
            "subcategory":"Home Furnishings",
            "type":"Retail Goods"
        }
    ],
    "sg:phone":"+43 4242 310550",
    "sg:postcode":"9500",
    "sg:province":"K\u00e4rnten",
    "sg:tags":[
        "air-conditioners"
    ],
    "sg:website":"eisbaer.cc",
    "wof:name":"Eisb\u00e4r AIR TEC Entfeuchtungstechnik K\u00e4lte- und Klimatechnik Ges.m.b.H.",
    "wof:placetype":"venue"
},
  "geometry": {"coordinates":[13.8672418594,46.6045227051],"type":"Point"}
}