{
  "type": "Feature",
  "properties": {
    "addr:full":"Hauptstr 34 Tullnerbach Nieder\u00f6sterreich 3013",
    "addr:housenumber":"34",
    "addr:postcode":"3013",
    "addr:street":"Hauptstr",
    "iso:country":"AT",
    "sg:address":"Hauptstr 34",
    "sg:city":"Tullnerbach",
    "sg:orig_category":"Feuerwehren",
    "sg:phone":"+43 2233 53822",
    "sg:postcode":"3013",
    "sg:province":"Nieder\u00f6sterreich",
    "wof:name":"Freiwillige Feuerwehr Tullnerbach",
    "wof:placetype":"venue"
},
  "geometry": {"coordinates":[16.0989456177,48.1844787598],"type":"Point"}
}