{
  "type": "Feature",
  "properties": {
    "iso:country":"AT",
    "sg:address":"Graf-Starhemberg-G 7",
    "sg:city":"Wien",
    "sg:orig_category":"Psychotherapie",
    "sg:phone":"+43 1 8659904",
    "sg:postcode":"1040",
    "sg:province":"Wien",
    "wof:name":"Hadinger Boglarka Mag Dr",
    "wof:placetype":"venue"
},
  "geometry": {"coordinates":[16.3689365387,48.1916351318],"type":"Point"}
}