{
  "type": "Feature",
  "properties": {
    "iso:country":"AT",
    "sg:address":"Nr 20",
    "sg:city":"Weissenbach an der Triesting",
    "sg:orig_category":"Non-Classified Establishments",
    "sg:phone":"+43 2674 88233",
    "sg:postcode":"2564",
    "sg:province":"Nieder\u00f6sterreich",
    "wof:name":"Singer - Ei",
    "wof:placetype":"venue"
},
  "geometry": {"coordinates":[16.0380496979,47.9819335938],"type":"Point"}
}