{
  "type": "Feature",
  "properties": {
    "addr:full":"Schellingg 1/3 Wien Wien 1010",
    "addr:housenumber":"1 / 3",
    "addr:postcode":"1010",
    "addr:street":"Schellingg",
    "iso:country":"AT",
    "sg:address":"Schellingg 1/3",
    "sg:city":"Wien",
    "sg:orig_category":"Bauunternehmen",
    "sg:phone":"+43 1 51346570",
    "sg:postcode":"1010",
    "sg:province":"Wien",
    "wof:name":"Studio Proksch Bauplanungs GesmbH",
    "wof:placetype":"venue"
},
  "geometry": {"coordinates":[16.3760948181,48.2049331665],"type":"Point"}
}