{
  "type": "Feature",
  "properties": {
    "addr:full":"Lindenstr 11 Gmunden Ober\u00f6sterreich 4810",
    "addr:housenumber":"11",
    "addr:postcode":"4810",
    "addr:street":"Lindenstr;Oberoesterreich",
    "iso:country":"AT",
    "sg:address":"Lindenstr 11",
    "sg:city":"Gmunden",
    "sg:orig_category":"Volksschulen",
    "sg:phone":"+43 761274334",
    "sg:postcode":"4810",
    "sg:province":"Ober\u00f6sterreich",
    "wof:name":"Volksschule Brahmsschule",
    "wof:placetype":"venue"
},
  "geometry": {"coordinates":[13.7832431793,47.9195861816],"type":"Point"}
}