{
  "type": "Feature",
  "properties": {
    "addr:full":"Linzer Str 44 Freistadt Ober\u00f6sterreich 4240",
    "addr:housenumber":"44",
    "addr:postcode":"4240",
    "addr:street":"Linzer Str",
    "iso:country":"AT",
    "sg:address":"Linzer Str 44",
    "sg:city":"Freistadt",
    "sg:orig_category":"Tankstellen",
    "sg:phone":"+43 7942 75096",
    "sg:postcode":"4240",
    "sg:province":"Ober\u00f6sterreich",
    "wof:name":"Shell Austria GmbH",
    "wof:placetype":"venue"
},
  "geometry": {"coordinates":[14.5018558502,48.5024757385],"type":"Point"}
}