{
  "type": "Feature",
  "properties": {
    "addr:full":"Fleischmarkt 5/2 Klagenfurt K\u00e4rnten 9020",
    "addr:housenumber":"5 / 2",
    "addr:postcode":"9020",
    "addr:street":"Fleischmarkt;Kaernten",
    "iso:country":"AT",
    "sg:address":"Fleischmarkt 5/2",
    "sg:city":"Klagenfurt",
    "sg:orig_category":"Werbeagenturen",
    "sg:phone":"+43 463 597464",
    "sg:postcode":"9020",
    "sg:province":"K\u00e4rnten",
    "wof:name":"Art & Marketing Werbeagentur Pressefotografie",
    "wof:placetype":"venue"
},
  "geometry": {"coordinates":[14.310090065,46.6250152588],"type":"Point"}
}