{
  "type": "Feature",
  "properties": {
    "addr:full":"K\u00e4rntner Str 13-15 Wien Wien 1010",
    "addr:postcode":"13-15;1010",
    "addr:street":"Str",
    "iso:country":"AT",
    "sg:address":"K\u00e4rntner Str 13-15",
    "sg:city":"Wien",
    "sg:orig_category":"Steuerberatung",
    "sg:phone":"+43 1 51255250",
    "sg:postcode":"1010",
    "sg:province":"Wien",
    "sg:website":"www.atb-wt.at",
    "wof:name":"ATB Treuhand SteuerberatungsgesmbH",
    "wof:placetype":"venue"
},
  "geometry": {"coordinates":[16.3726119995,48.2018814087],"type":"Point"}
}