{
  "type": "Feature",
  "properties": {
    "addr:full":"Bommenweg 10 Hard Vorarlberg 6971",
    "addr:housenumber":"10",
    "addr:postcode":"6971",
    "addr:street":"Bommenweg",
    "iso:country":"AT",
    "sg:address":"Bommenweg 10",
    "sg:city":"Hard",
    "sg:orig_category":"Montagen U Montagetechnik",
    "sg:phone":"+43 5574 72732",
    "sg:postcode":"6971",
    "sg:province":"Vorarlberg",
    "wof:name":"Perfekt Service - Fink Carmen",
    "wof:placetype":"venue"
},
  "geometry": {"coordinates":[9.6914234161,47.4789772034],"type":"Point"}
}