{
  "type": "Feature",
  "properties": {
    "addr:full":"Templstr 4 Innsbruck Tirol 6020",
    "addr:housenumber":"4",
    "addr:postcode":"6020",
    "addr:street":"Templstr;Tirol",
    "iso:country":"AT",
    "sg:address":"Templstr 4",
    "sg:city":"Innsbruck",
    "sg:orig_category":"Lebens- U Sozialberatung",
    "sg:phone":"+43 4351 2391254",
    "sg:postcode":"6020",
    "sg:province":"Tirol",
    "wof:name":"Chesi Elisabeth - Dipl Mal- u Gestaltungstherapeutin - Biographieberatung",
    "wof:placetype":"venue"
},
  "geometry": {"coordinates":[11.3933696747,47.261177063],"type":"Point"}
}