{
  "type": "Feature",
  "properties": {
    "addr:full":"Hauptpl 11 Bruck an der Leitha Nieder\u00f6sterreich 2460",
    "addr:housenumber":"11",
    "addr:postcode":"2460",
    "addr:street":"Hauptpl",
    "iso:country":"AT",
    "sg:address":"Hauptpl 11",
    "sg:city":"Bruck an der Leitha",
    "sg:orig_category":"Bandagen U Bandagisten",
    "sg:phone":"+43 4321 6263128",
    "sg:postcode":"2460",
    "sg:province":"Nieder\u00f6sterreich",
    "wof:name":"Illek-Sanag GesmbH",
    "wof:placetype":"venue"
},
  "geometry": {"coordinates":[16.7791118622,48.0262184143],"type":"Point"}
}