{
  "type": "Feature",
  "properties": {
    "addr:full":"Favoritenstrasse 173/1 und 2 Wien Wien 1100",
    "addr:housenumber":"173 / 1 und 2",
    "addr:postcode":"1100",
    "addr:street":"Favoritenstrasse",
    "iso:country":"AT",
    "sg:address":"Favoritenstrasse 173/1 und 2",
    "sg:city":"Wien",
    "sg:classifiers":[
        {
            "category":"Government",
            "subcategory":"Fire Station",
            "type":"Public Place"
        }
    ],
    "sg:phone":"+43 1 6410713",
    "sg:postcode":"1100",
    "sg:province":"Wien",
    "sg:tags":[
        "extinguisher",
        "automatic"
    ],
    "sg:website":"brand-ex.at",
    "wof:name":"Brandex Feuerschutz GmbH",
    "wof:placetype":"venue"
},
  "geometry": {"coordinates":[16.3744049072,48.1782684326],"type":"Point"}
}