{
  "type": "Feature",
  "properties": {
    "addr:full":"Dr Franz Ferchl-Str 12/1 Hallein Salzburg 5400",
    "addr:housenumber":"12 / 1",
    "addr:postcode":"5400",
    "addr:street":"Dr;Ferchl-Str;Salzburg",
    "iso:country":"AT",
    "sg:address":"Dr Franz Ferchl-Str 12/1",
    "sg:city":"Hallein",
    "sg:orig_category":"Non-Classified Establishments",
    "sg:phone":"+43 6245 850940",
    "sg:postcode":"5400",
    "sg:province":"Salzburg",
    "wof:name":"Kirchenbeitragsstelle",
    "wof:placetype":"venue"
},
  "geometry": {"coordinates":[13.091586113,47.6805381775],"type":"Point"}
}