{
  "type": "Feature",
  "properties": {
    "addr:full":"Deutschlandsberg Steiermark 8530",
    "addr:postcode":"8530",
    "iso:country":"AT",
    "sg:city":"Deutschlandsberg",
    "sg:orig_category":"Volksschulen",
    "sg:phone":"+43 3462 2885",
    "sg:postcode":"8530",
    "sg:province":"Steiermark",
    "wof:name":"Volksschule Wildbach",
    "wof:placetype":"venue"
},
  "geometry": {"coordinates":[15.2126283646,46.8138923645],"type":"Point"}
}