{
  "type": "Feature",
  "properties": {
    "addr:full":"Nr 518 Bad Ischl Ober\u00f6sterreich 4820",
    "addr:postcode":"4820",
    "addr:street":"Nr",
    "iso:country":"AT",
    "sg:address":"Nr 518",
    "sg:city":"Bad Ischl",
    "sg:orig_category":"Spielwaren U Spiele",
    "sg:phone":"+43 4361 3222400",
    "sg:postcode":"4820",
    "sg:province":"Ober\u00f6sterreich",
    "wof:name":"MUKI Handels- u DienstleistungsgesmbH",
    "wof:placetype":"venue"
},
  "geometry": {"coordinates":[13.6257123947,47.711971283],"type":"Point"}
}