{
  "type": "Feature",
  "properties": {
    "addr:full":"Krauseg 12 Wien Wien 1110",
    "addr:housenumber":"12",
    "addr:postcode":"1110",
    "addr:street":"Krauseg",
    "iso:country":"AT",
    "sg:address":"Krauseg 12",
    "sg:city":"Wien",
    "sg:orig_category":"Fu\u00c3\u0178bodenheizungen",
    "sg:phone":"+43 1 74942740",
    "sg:postcode":"1110",
    "sg:province":"Wien",
    "wof:name":"VMH Vertriebsges Moderner Heizungstechnik GesmbH",
    "wof:placetype":"venue"
},
  "geometry": {"coordinates":[16.4197406769,48.1743049622],"type":"Point"}
}