{
  "type": "Feature",
  "properties": {
    "addr:full":"Schwarzenberg 5 Ybbsitz Nieder\u00f6sterreich 3341",
    "addr:housenumber":"5",
    "addr:postcode":"3341",
    "addr:street":"Schwarzenberg",
    "iso:country":"AT",
    "sg:address":"Schwarzenberg 5",
    "sg:city":"Ybbsitz",
    "sg:orig_category":"Bohrunternehmen",
    "sg:phone":"+43 4366 42425003",
    "sg:postcode":"3341",
    "sg:province":"Nieder\u00f6sterreich",
    "wof:name":"Pichler Bohrtechnik GmbH",
    "wof:placetype":"venue"
},
  "geometry": {"coordinates":[14.8502159119,47.959854126],"type":"Point"}
}