{
  "type": "Feature",
  "properties": {
    "addr:full":"Schulgasse 4 St. P\u00f6lten Nieder\u00f6sterreich 3100",
    "addr:housenumber":"4",
    "addr:postcode":"3100",
    "addr:street":"Schulgasse",
    "iso:country":"AT",
    "sg:address":"Schulgasse 4",
    "sg:city":"St. P\u00f6lten",
    "sg:classifiers":[
        {
            "category":"Building & Trades",
            "subcategory":"Plumbing",
            "type":"Services"
        }
    ],
    "sg:phone":"+43 2742 77165",
    "sg:postcode":"3100",
    "sg:province":"Nieder\u00f6sterreich",
    "sg:tags":[
        "tub",
        "bath"
    ],
    "wof:name":"Josef Wildburger Installations GesmbH & Co KG",
    "wof:placetype":"venue"
},
  "geometry": {"coordinates":[-76.07303619379999,41.7845001221],"type":"Point"}
}