{
  "type": "Feature",
  "properties": {
    "addr:full":"Bundesstr 39 Unterrabnitz Burgenland 7371",
    "addr:housenumber":"39",
    "addr:postcode":"7371",
    "addr:street":"Bundesstr",
    "iso:country":"AT",
    "sg:address":"Bundesstr 39",
    "sg:city":"Unterrabnitz",
    "sg:orig_category":"Banken U Sparkassen",
    "sg:phone":"+43 4326 168716",
    "sg:postcode":"7371",
    "sg:province":"Burgenland",
    "wof:name":"Raiffeisenbezirksbank Oberpullendorf regGenmbH",
    "wof:placetype":"venue"
},
  "geometry": {"coordinates":[16.4176635742,47.4473457336],"type":"Point"}
}