{
  "type": "Feature",
  "properties": {
    "addr:full":"Untere Hafnerzeile 3 Freistadt Ober\u00f6sterreich 4240",
    "addr:housenumber":"3",
    "addr:postcode":"4240",
    "addr:street":"Untere Hafnerzeile",
    "iso:country":"AT",
    "sg:address":"Untere Hafnerzeile 3",
    "sg:city":"Freistadt",
    "sg:orig_category":"Lebensmittel / Einzelhandel",
    "sg:phone":"+43 7942 76300",
    "sg:postcode":"4240",
    "sg:province":"Ober\u00f6sterreich",
    "wof:name":"N\u00f6stler Gerlinde",
    "wof:placetype":"venue"
},
  "geometry": {"coordinates":[14.5079631805,48.5124092102],"type":"Point"}
}