{
  "type": "Feature",
  "properties": {
    "addr:full":"Wiener Str 31 Langenlois Nieder\u00f6sterreich 3550",
    "addr:postcode":"3550",
    "addr:street":"Niederoesterreich",
    "iso:country":"AT",
    "sg:address":"Wiener Str 31",
    "sg:city":"Langenlois",
    "sg:orig_category":"Lebensmittel / Einzelhandel",
    "sg:phone":"+43 2734 32260",
    "sg:postcode":"3550",
    "sg:province":"Nieder\u00f6sterreich",
    "wof:name":"SPAR \u00f6sterreichische Warenhandels-AG",
    "wof:placetype":"venue"
},
  "geometry": {"coordinates":[15.6806364059,48.4717445374],"type":"Point"}
}