{
  "type": "Feature",
  "properties": {
    "iso:country":"AT",
    "sg:address":"Perchtoldsdorfer Str 21",
    "sg:city":"Wien",
    "sg:orig_category":"Fotoapparate U -Artikel / Erzeugung U Gro\u00c3\u0178handel",
    "sg:phone":"+43 4318 693989",
    "sg:postcode":"1230",
    "sg:province":"Wien",
    "wof:name":"Hacker GesmbH",
    "wof:placetype":"venue"
},
  "geometry": {"coordinates":[16.2816581726,48.1330032349],"type":"Point"}
}