{
  "type": "Feature",
  "properties": {
    "iso:country":"AT",
    "sg:address":"Z\u00f6pflweg 1",
    "sg:city":"Brixen im Thale",
    "sg:orig_category":"Pensionen / Privatzimmer",
    "sg:phone":"+43 5334 8677",
    "sg:postcode":"6364",
    "sg:province":"Tirol",
    "wof:name":"Waldrast",
    "wof:placetype":"venue"
},
  "geometry": {"coordinates":[12.2644786835,47.4384422302],"type":"Point"}
}