{
  "type": "Feature",
  "properties": {
    "addr:full":"Kurhausstr 9a Bad Leonfelden Ober\u00f6sterreich 4190",
    "addr:housenumber":"9a",
    "addr:postcode":"4190",
    "addr:street":"Kurhausstr",
    "iso:country":"AT",
    "sg:address":"Kurhausstr 9a",
    "sg:city":"Bad Leonfelden",
    "sg:orig_category":"Polytechnische Schulen",
    "sg:phone":"+43 7213 65600",
    "sg:postcode":"4190",
    "sg:province":"Ober\u00f6sterreich",
    "wof:name":"Polytechnische Schule",
    "wof:placetype":"venue"
},
  "geometry": {"coordinates":[14.2892913818,48.5215682983],"type":"Point"}
}