{
  "type": "Feature",
  "properties": {
    "iso:country":"AT",
    "sg:address":"Feldbacher Str 3",
    "sg:city":"Gleisdorf",
    "sg:orig_category":"Lichttechnik",
    "sg:phone":"+43 4331 1238111",
    "sg:postcode":"8200",
    "sg:province":"Steiermark",
    "wof:name":"deco & lights Stra\u00dfen- und Weihnachtsbeleuchtung GmbH",
    "wof:placetype":"venue"
},
  "geometry": {"coordinates":[15.7152442932,47.1016540527],"type":"Point"}
}