{
  "type": "Feature",
  "properties": {
    "iso:country":"AT",
    "sg:address":"M\u00f6nchhofer Str 2-4",
    "sg:city":"Frauenkirchen",
    "sg:orig_category":"Autohandel",
    "sg:phone":"+43 4321 7223800",
    "sg:postcode":"7132",
    "sg:province":"Burgenland",
    "wof:name":"Berger Manfred GesmbH",
    "wof:placetype":"venue"
},
  "geometry": {"coordinates":[16.9299201965,47.8410148621],"type":"Point"}
}