{
  "type": "Feature",
  "properties": {
    "addr:full":"St.-Peter-G\u00fcrtel 10 St. Peter Steiermark 8042",
    "addr:housenumber":"10",
    "addr:postcode":"8042",
    "addr:street":"St.-Peter-Guertel",
    "iso:country":"AT",
    "sg:address":"St.-Peter-G\u00fcrtel 10",
    "sg:city":"St. Peter",
    "sg:orig_category":"Zoologiebedarf",
    "sg:phone":"+43 4331 6409030",
    "sg:postcode":"8042",
    "sg:province":"Steiermark",
    "wof:name":"Fressnapf Handels GmbH",
    "wof:placetype":"venue"
},
  "geometry": {"coordinates":[15.4814271927,47.0514221191],"type":"Point"}
}