{
  "type": "Feature",
  "properties": {
    "iso:country":"AT",
    "sg:address":"Kirchpl 5",
    "sg:city":"Gratkorn",
    "sg:orig_category":"Fu\u00c3\u0178pflege U Fu\u00c3\u0178pflegesalons",
    "sg:phone":"+43 4331 2425370",
    "sg:postcode":"8101",
    "sg:province":"Steiermark",
    "wof:name":"Fu\u00dfpflege Waltraud Spedel - Kilzer",
    "wof:placetype":"venue"
},
  "geometry": {"coordinates":[15.3503952026,47.1348075867],"type":"Point"}
}