{
  "type": "Feature",
  "properties": {
    "addr:full":"Endresstr 71 Wien Wien 1230",
    "addr:housenumber":"71",
    "addr:postcode":"1230",
    "addr:street":"Endresstr",
    "iso:country":"AT",
    "sg:address":"Endresstr 71",
    "sg:city":"Wien",
    "sg:orig_category":"Elektronik",
    "sg:phone":"+43 1 8898565",
    "sg:postcode":"1230",
    "sg:province":"Wien",
    "wof:name":"Tomscha-Towo Josef Elektronic KEG",
    "wof:placetype":"venue"
},
  "geometry": {"coordinates":[16.2776813507,48.1487731934],"type":"Point"}
}