{
  "type": "Feature",
  "properties": {
    "addr:full":"Bauhofweg 5 Kautzen Nieder\u00f6sterreich 3851",
    "addr:housenumber":"5",
    "addr:postcode":"3851",
    "addr:street":"Bauhofweg",
    "iso:country":"AT",
    "sg:address":"Bauhofweg 5",
    "sg:city":"Kautzen",
    "sg:orig_category":"Holzbe U -Verarbeitung",
    "sg:phone":"+43 4328 64261980",
    "sg:postcode":"3851",
    "sg:province":"Nieder\u00f6sterreich",
    "wof:name":"Trocknungszentrum Kautzen GmbH",
    "wof:placetype":"venue"
},
  "geometry": {"coordinates":[15.2431707382,48.929473877],"type":"Point"}
}