{
  "type": "Feature",
  "properties": {
    "addr:full":"Feldstr 7a Innsbruck Tirol 6020",
    "addr:housenumber":"7a",
    "addr:postcode":"6020",
    "addr:street":"Feldstr;Tirol",
    "iso:country":"AT",
    "sg:address":"Feldstr 7a",
    "sg:city":"Innsbruck",
    "sg:orig_category":"Speditionen",
    "sg:phone":"+43 4351 25739200",
    "sg:postcode":"6020",
    "sg:province":"Tirol",
    "wof:name":"Gebr\u00fcder Weiss GmbH - Transport u Logistik",
    "wof:placetype":"venue"
},
  "geometry": {"coordinates":[11.3904037476,47.2545585632],"type":"Point"}
}