{
  "type": "Feature",
  "properties": {
    "addr:full":"Neulerchenfelder Str 93 Wien Wien 1160",
    "addr:postcode":"1160",
    "addr:street":"Str 93",
    "iso:country":"AT",
    "sg:address":"Neulerchenfelder Str 93",
    "sg:city":"Wien",
    "sg:classifiers":[
        {
            "category":"Home & Garden",
            "subcategory":"Kitchen Supply",
            "type":"Retail Goods"
        }
    ],
    "sg:phone":"+43 1 4819200",
    "sg:postcode":"1160",
    "sg:province":"Wien",
    "sg:tags":[
        "espresso-",
        "u",
        "kaffeemaschinen"
    ],
    "wof:name":"Sebastiani & Co GesmbH",
    "wof:placetype":"venue"
},
  "geometry": {"coordinates":[16.3266353607,48.2127075195],"type":"Point"}
}