{
  "type": "Feature",
  "properties": {
    "addr:full":"Kohlmarkt 7 Wien Wien 1010",
    "addr:housenumber":"7",
    "addr:postcode":"1010",
    "addr:street":"Kohlmarkt",
    "iso:country":"AT",
    "sg:address":"Kohlmarkt 7",
    "sg:city":"Wien",
    "sg:orig_category":"Bekleidung / Einzelhandel",
    "sg:phone":"+43 1 5336053",
    "sg:postcode":"1010",
    "sg:province":"Wien",
    "wof:name":"La robe Modellhaus Josef Weithofer & Co GesmbH",
    "wof:placetype":"venue"
},
  "geometry": {"coordinates":[16.367767334,48.2086868286],"type":"Point"}
}