{
  "type": "Feature",
  "properties": {
    "iso:country":"AT",
    "sg:address":"Lindenstr 11",
    "sg:city":"P\u00f6chlarn",
    "sg:orig_category":"Gabelstapler",
    "sg:phone":"+43 2757 7471",
    "sg:postcode":"3380",
    "sg:province":"Nieder\u00f6sterreich",
    "wof:name":"Staplertechnik Salzer KG",
    "wof:placetype":"venue"
},
  "geometry": {"coordinates":[-79.38526153559999,41.2145881653],"type":"Point"}
}