{
  "type": "Feature",
  "properties": {
    "addr:full":"Letzeb\u00fchelweg 1 6807",
    "addr:housenumber":"1",
    "addr:postcode":"6807",
    "addr:street":"Letzebuehelweg",
    "iso:country":"AT",
    "sg:address":"Letzeb\u00fchelweg 1",
    "sg:orig_category":"Handelsagenturen",
    "sg:phone":"+43 5522 77551",
    "sg:postcode":"6807",
    "wof:name":"Greiner Karl",
    "wof:placetype":"venue"
},
  "geometry": {"coordinates":[9.5832996368,47.2332992554],"type":"Point"}
}