{
  "type": "Feature",
  "properties": {
    "addr:full":"Bartensteingasse 5 Wien Wien 1010",
    "addr:housenumber":"5",
    "addr:postcode":"1010",
    "addr:street":"Bartensteingasse",
    "iso:country":"AT",
    "sg:address":"Bartensteingasse 5",
    "sg:city":"Wien",
    "sg:classifiers":[
        {
            "category":"Professional",
            "subcategory":"Management & Consulting",
            "type":"Services"
        }
    ],
    "sg:phone":"+43 1 40276080",
    "sg:postcode":"1010",
    "sg:province":"Wien",
    "sg:tags":[
        "hr",
        "resource",
        "consultancy",
        "human"
    ],
    "sg:website":"pendlpiswanger.co.at",
    "wof:name":"Dr. Pendl & Dr. Piswanger GesmbH.",
    "wof:placetype":"venue"
},
  "geometry": {"coordinates":[16.3563194275,48.2081756592],"type":"Point"}
}