{
  "type": "Feature",
  "properties": {
    "addr:full":"Neusiedler Str 28 Eisenstadt Burgenland 7000",
    "addr:postcode":"7000",
    "addr:street":"Str 28",
    "iso:country":"AT",
    "sg:address":"Neusiedler Str 28",
    "sg:city":"Eisenstadt",
    "sg:orig_category":"Installationsunternehmen",
    "sg:phone":"+43 2682 621450",
    "sg:postcode":"7000",
    "sg:province":"Burgenland",
    "wof:name":"Schandl Johannes Ing & G\u00fcnther GesmbH",
    "wof:placetype":"venue"
},
  "geometry": {"coordinates":[16.530046463,47.846698761],"type":"Point"}
}