{
  "type": "Feature",
  "properties": {
    "addr:full":"Tr\u00f6lsberg 26 Freistadt Ober\u00f6sterreich 4240",
    "addr:housenumber":"26",
    "addr:postcode":"4240",
    "addr:street":"Troelsberg",
    "iso:country":"AT",
    "sg:address":"Tr\u00f6lsberg 26",
    "sg:city":"Freistadt",
    "sg:classifiers":[
        {
            "category":"Shopping",
            "subcategory":"Party Supplies",
            "type":"Retail Goods"
        }
    ],
    "sg:phone":"+43 650 7604988",
    "sg:postcode":"4240",
    "sg:province":"Ober\u00f6sterreich",
    "sg:tags":[
        "u",
        "lichtanlagen",
        "ton-"
    ],
    "wof:name":"Kinz Gerald",
    "wof:placetype":"venue"
},
  "geometry": {"coordinates":[14.5049953461,48.5119857788],"type":"Point"}
}