{
  "type": "Feature",
  "properties": {
    "iso:country":"AT",
    "sg:address":"Hauptpl 1",
    "sg:city":"Bruck an der Leitha",
    "sg:orig_category":"Optiker",
    "sg:phone":"+43 2162 650630",
    "sg:postcode":"2460",
    "sg:province":"Nieder\u00f6sterreich",
    "wof:name":"Optik Bastel GesmbH",
    "wof:placetype":"venue"
},
  "geometry": {"coordinates":[16.7785186768,48.0247802734],"type":"Point"}
}