{
  "type": "Feature",
  "properties": {
    "addr:full":"Nr 115 Altenmarkt-Thenneberg Nieder\u00f6sterreich 2571",
    "addr:postcode":"2571",
    "addr:street":"Nr 115 Altenmarkt-Thenneberg",
    "iso:country":"AT",
    "sg:address":"Nr 115",
    "sg:city":"Altenmarkt-Thenneberg",
    "sg:orig_category":"Tischlereien",
    "sg:phone":"+43 2673 2619",
    "sg:postcode":"2571",
    "sg:province":"Nieder\u00f6sterreich",
    "wof:name":"Stricker Erwin",
    "wof:placetype":"venue"
},
  "geometry": {"coordinates":[166.9221496582,-0.5282999873],"type":"Point"}
}