{
  "type": "Feature",
  "properties": {
    "addr:full":"Siedlerstr 5a Gnigl Salzburg 5023",
    "addr:housenumber":"5a",
    "addr:postcode":"5023",
    "addr:street":"Siedlerstr",
    "iso:country":"AT",
    "sg:address":"Siedlerstr 5a",
    "sg:city":"Gnigl",
    "sg:orig_category":"Hufschmiede",
    "sg:phone":"+43 664 3805286",
    "sg:postcode":"5023",
    "sg:province":"Salzburg",
    "wof:name":"Leitner Franz",
    "wof:placetype":"venue"
},
  "geometry": {"coordinates":[13.0674133301,47.817741394],"type":"Point"}
}