{
  "type": "Feature",
  "properties": {
    "addr:full":"Ziernfeldg 6 Graz Steiermark 8010",
    "addr:housenumber":"6",
    "addr:postcode":"8010",
    "addr:street":"Ziernfeldg",
    "iso:country":"AT",
    "sg:address":"Ziernfeldg 6",
    "sg:city":"Graz",
    "sg:orig_category":"Architekten",
    "sg:phone":"+43 316 323124",
    "sg:postcode":"8010",
    "sg:province":"Steiermark",
    "wof:name":"Meister Emo Arch Dipl-Ing",
    "wof:placetype":"venue"
},
  "geometry": {"coordinates":[15.4541282654,47.088886261],"type":"Point"}
}