{
  "type": "Feature",
  "properties": {
    "addr:full":"Gewerbepark 23 Hart Steiermark 8075",
    "addr:housenumber":"23",
    "addr:postcode":"8075",
    "addr:street":"Gewerbepark",
    "iso:country":"AT",
    "sg:address":"Gewerbepark 23",
    "sg:city":"Hart",
    "sg:orig_category":"Metallbau",
    "sg:phone":"+43 316 4930500",
    "sg:postcode":"8075",
    "sg:province":"Steiermark",
    "sg:website":"kern-metall.at",
    "wof:name":"Kern Metalltechnik GesmbH",
    "wof:placetype":"venue"
},
  "geometry": {"coordinates":[15.5126905441,47.0424766541],"type":"Point"}
}