{
  "type": "Feature",
  "properties": {
    "addr:full":"Villacher Str 213 Feistritz an der Drau K\u00e4rnten 9710",
    "addr:housenumber":"213",
    "addr:postcode":"9710",
    "addr:street":"Str",
    "iso:country":"AT",
    "sg:address":"Villacher Str 213",
    "sg:city":"Feistritz an der Drau",
    "sg:orig_category":"Fleischhauereien",
    "sg:phone":"+43 4342 452276",
    "sg:postcode":"9710",
    "sg:province":"K\u00e4rnten",
    "wof:name":"Sandriesser Josef",
    "wof:placetype":"venue"
},
  "geometry": {"coordinates":[13.66314888,46.7018623352],"type":"Point"}
}