{
  "type": "Feature",
  "properties": {
    "addr:full":"Kirchdorf 8a Gaspoltshofen Ober\u00f6sterreich 4673",
    "addr:housenumber":"8a",
    "addr:postcode":"4673",
    "addr:street":"Kirchdorf",
    "iso:country":"AT",
    "sg:address":"Kirchdorf 8a",
    "sg:city":"Gaspoltshofen",
    "sg:orig_category":"Fliesen U Platten",
    "sg:phone":"+43 4377 356610",
    "sg:postcode":"4673",
    "sg:province":"Ober\u00f6sterreich",
    "wof:name":"Oberhumer Rosemarie",
    "wof:placetype":"venue"
},
  "geometry": {"coordinates":[13.7399692535,48.1421432495],"type":"Point"}
}