{
  "type": "Feature",
  "properties": {
    "addr:full":"Angerer Str 2-6 Wien Wien 1210",
    "addr:postcode":"1210",
    "addr:street":"Str 2-6",
    "iso:country":"AT",
    "sg:address":"Angerer Str 2-6",
    "sg:city":"Wien",
    "sg:orig_category":"Garagen Parkgaragen",
    "sg:phone":"+43 1 2711316",
    "sg:postcode":"1210",
    "sg:province":"Wien",
    "wof:name":"APCOA Parking Austria AG",
    "wof:placetype":"venue"
},
  "geometry": {"coordinates":[16.3993778229,48.2597503662],"type":"Point"}
}