{
  "type": "Feature",
  "properties": {
    "addr:full":"Bozner Pl 6 Innsbruck Tirol 6020",
    "addr:housenumber":"6",
    "addr:postcode":"6020",
    "addr:street":"Bozner Pl;Tirol",
    "iso:country":"AT",
    "sg:address":"Bozner Pl 6",
    "sg:city":"Innsbruck",
    "sg:orig_category":"Rettungsdienste",
    "sg:phone":"+43 512 5082260",
    "sg:postcode":"6020",
    "sg:province":"Tirol",
    "wof:name":"Landesregierung Katastrophen- und Zivilschutz",
    "wof:placetype":"venue"
},
  "geometry": {"coordinates":[11.3976402283,47.2645683289],"type":"Point"}
}