{
  "type": "Feature",
  "properties": {
    "addr:full":"Nr 8 St. Peter in der Au Nieder\u00f6sterreich 3352",
    "addr:housenumber":"8",
    "addr:postcode":"3352",
    "addr:street":"Nr",
    "iso:country":"AT",
    "sg:address":"Nr 8",
    "sg:city":"St. Peter in der Au",
    "sg:orig_category":"Non-Classified Establishments",
    "sg:phone":"+43 7252 30686",
    "sg:postcode":"3352",
    "sg:province":"Nieder\u00f6sterreich",
    "wof:name":"Pfarramt",
    "wof:placetype":"venue"
},
  "geometry": {"coordinates":[116.9264297485,28.3459606171],"type":"Point"}
}