{
  "type": "Feature",
  "properties": {
    "iso:country":"AT",
    "sg:address":"Mayr-Melnhof-Gasse 5",
    "sg:city":"Salzburg",
    "sg:classifiers":[
        {
            "category":"Structure",
            "subcategory":"Building",
            "type":"Public Place"
        }
    ],
    "sg:phone":"+43 662 628655",
    "sg:postcode":"5020",
    "sg:province":"Salzburg",
    "sg:tags":[
        "equipment",
        "greenhouse",
        "system",
        "automation"
    ],
    "wof:name":"Rabensteiner Werksvertretung",
    "wof:placetype":"venue"
},
  "geometry": {"coordinates":[13.0638599396,47.7981948853],"type":"Point"}
}