{
  "type": "Feature",
  "properties": {
    "addr:full":"R\u00f6sslepark 2 Feldkirch Vorarlberg 6800",
    "addr:housenumber":"2",
    "addr:postcode":"6800",
    "addr:street":"Roesslepark",
    "iso:country":"AT",
    "sg:address":"R\u00f6sslepark 2",
    "sg:city":"Feldkirch",
    "sg:orig_category":"Bilderrahmen",
    "sg:phone":"+43 5522 723170",
    "sg:postcode":"6800",
    "sg:province":"Vorarlberg",
    "wof:name":"Althof Kunst & Rahmen",
    "wof:placetype":"venue"
},
  "geometry": {"coordinates":[9.5967845917,47.2381515503],"type":"Point"}
}