{
  "type": "Feature",
  "properties": {
    "addr:full":"Stanglhofweg 9 Linz Ober\u00f6sterreich 4020",
    "addr:housenumber":"9",
    "addr:postcode":"4020",
    "addr:street":"Stanglhofweg",
    "iso:country":"AT",
    "sg:address":"Stanglhofweg 9",
    "sg:city":"Linz",
    "sg:orig_category":"Feldenkraismethode",
    "sg:phone":"+43 4369 911884845",
    "sg:postcode":"4020",
    "sg:province":"Ober\u00f6sterreich",
    "wof:name":"Nagl Svila",
    "wof:placetype":"venue"
},
  "geometry": {"coordinates":[14.2725868225,48.2926940918],"type":"Point"}
}