{
  "type": "Feature",
  "properties": {
    "addr:full":"Raiffeisenstr. 131-133 Liebenau Steiermark 8041",
    "addr:postcode":"131-133;8041",
    "iso:country":"AT",
    "sg:address":"Raiffeisenstr. 131-133",
    "sg:city":"Liebenau",
    "sg:classifiers":[
        {
            "category":"Wholesale",
            "subcategory":"Machinery & Supplies",
            "type":"Manufacturing & Wholesale Goods"
        }
    ],
    "sg:phone":"+43 4331 64710130",
    "sg:postcode":"8041",
    "sg:province":"Steiermark",
    "sg:tags":[
        "equipment",
        "precision"
    ],
    "wof:name":"BUCHHOLZER & PARTNER GMBH",
    "wof:placetype":"venue"
},
  "geometry": {"coordinates":[15.4531917572,47.0455741882],"type":"Point"}
}