{
  "type": "Feature",
  "properties": {
    "addr:full":"Waaggasse 5 Wien Wien 1040",
    "addr:housenumber":"5",
    "addr:postcode":"1040",
    "addr:street":"Waaggasse",
    "iso:country":"AT",
    "sg:address":"Waaggasse 5",
    "sg:city":"Wien",
    "sg:classifiers":[
        {
            "category":"Professional",
            "subcategory":"Engineering",
            "type":"Services"
        }
    ],
    "sg:phone":"+43 1 58725420",
    "sg:postcode":"1040",
    "sg:province":"Wien",
    "sg:tags":[
        "audio",
        "video",
        "film"
    ],
    "wof:name":"Team-Film-Produktion Ges.m.b.H. & Co KG",
    "wof:placetype":"venue"
},
  "geometry": {"coordinates":[16.3660392761,48.1949005127],"type":"Point"}
}