{
  "type": "Feature",
  "properties": {
    "addr:full":"Schulg 100 Warth Nieder\u00f6sterreich 2831",
    "addr:housenumber":"100",
    "addr:postcode":"2831",
    "addr:street":"Warth",
    "iso:country":"AT",
    "sg:address":"Schulg 100",
    "sg:city":"Warth",
    "sg:orig_category":"Musikunterricht",
    "sg:phone":"+43 4326 293257",
    "sg:postcode":"2831",
    "sg:province":"Nieder\u00f6sterreich",
    "wof:name":"Musikschule Warth-Scheiblingkirchen",
    "wof:placetype":"venue"
},
  "geometry": {"coordinates":[16.1336307526,47.6579818726],"type":"Point"}
}