{
  "type": "Feature",
  "properties": {
    "addr:full":"Stauseestrasse 66  Forchtenstein Burgenland 7212",
    "addr:housenumber":"66",
    "addr:postcode":"7212",
    "addr:street":"Stauseestrasse",
    "iso:country":"AT",
    "sg:address":"Stauseestrasse 66 ",
    "sg:city":"Forchtenstein",
    "sg:classifiers":[
        {
            "category":"Building & Trades",
            "subcategory":"Plumbing",
            "type":"Services"
        }
    ],
    "sg:phone":"+43 2626 66085",
    "sg:postcode":"7212",
    "sg:province":"Burgenland",
    "sg:tags":[
        "supraregional",
        "gas"
    ],
    "wof:name":"Roland Knoll",
    "wof:placetype":"venue"
},
  "geometry": {"coordinates":[16.355594635,47.7113952637],"type":"Point"}
}