{
  "type": "Feature",
  "properties": {
    "addr:full":"St.-Martin-Str 14 Dornbirn Vorarlberg 6850",
    "addr:housenumber":"14",
    "addr:postcode":"6850",
    "addr:street":"St.-Martin-Str",
    "iso:country":"AT",
    "sg:address":"St.-Martin-Str 14",
    "sg:city":"Dornbirn",
    "sg:orig_category":"Werbeagenturen",
    "sg:phone":"+43 5572 26664",
    "sg:postcode":"6850",
    "sg:province":"Vorarlberg",
    "sg:website":"fjm.at",
    "wof:name":"Flax, Jutz, M\u00e4tzler Werbeagentur GesmbH & Co",
    "wof:placetype":"venue"
},
  "geometry": {"coordinates":[9.7454090118,47.4081802368],"type":"Point"}
}