{
  "type": "Feature",
  "properties": {
    "iso:country":"AT",
    "sg:address":"Kolbegasse 73",
    "sg:city":"Wien",
    "sg:classifiers":[
        {
            "category":"Shopping",
            "subcategory":"Jewelry",
            "type":"Retail Goods"
        }
    ],
    "sg:phone":"+43 1 610760",
    "sg:postcode":"1230",
    "sg:province":"Wien",
    "sg:tags":[
        "fashion",
        "jewellery"
    ],
    "wof:name":"Hans Andersen Ges.m.b.H.",
    "wof:placetype":"venue"
},
  "geometry": {"coordinates":[16.3591041565,48.1450767517],"type":"Point"}
}