{
  "type": "Feature",
  "properties": {
    "addr:full":"Hauptstr 73 Eichgraben Nieder\u00f6sterreich 3032",
    "addr:housenumber":"73",
    "addr:postcode":"3032",
    "addr:street":"Hauptstr",
    "iso:country":"AT",
    "sg:address":"Hauptstr 73",
    "sg:city":"Eichgraben",
    "sg:orig_category":"Friseure U Frisiersalons",
    "sg:phone":"+43 4327 7346336",
    "sg:postcode":"3032",
    "sg:province":"Nieder\u00f6sterreich",
    "wof:name":"Sedlak Regina",
    "wof:placetype":"venue"
},
  "geometry": {"coordinates":[15.984331131,48.1720809937],"type":"Point"}
}