{
  "type": "Feature",
  "properties": {
    "addr:full":"Gewerbestr 20 Satteins Vorarlberg 6822",
    "addr:housenumber":"20",
    "addr:postcode":"6822",
    "addr:street":"Gewerbestr",
    "iso:country":"AT",
    "sg:address":"Gewerbestr 20",
    "sg:city":"Satteins",
    "sg:orig_category":"Fischzucht",
    "sg:phone":"+43 4355 248412",
    "sg:postcode":"6822",
    "sg:province":"Vorarlberg",
    "wof:name":"Forellenzucht G\u00fcfel",
    "wof:placetype":"venue"
},
  "geometry": {"coordinates":[9.6571817398,47.2229270935],"type":"Point"}
}