{
  "type": "Feature",
  "properties": {
    "addr:full":"Burgg 46 Wien Wien 1070",
    "addr:housenumber":"46",
    "addr:postcode":"1070",
    "addr:street":"Burgg",
    "iso:country":"AT",
    "sg:address":"Burgg 46",
    "sg:city":"Wien",
    "sg:orig_category":"Pelze U Pelzwaren",
    "sg:phone":"+43 4315 239028",
    "sg:postcode":"1070",
    "sg:province":"Wien",
    "wof:name":"Pelze Konecky",
    "wof:placetype":"venue"
},
  "geometry": {"coordinates":[16.34973526,48.2044525146],"type":"Point"}
}