{
  "type": "Feature",
  "properties": {
    "iso:country":"AT",
    "sg:address":"Eisenhammerweg 46",
    "sg:city":"Villach",
    "sg:classifiers":[
        {
            "category":"Taxi",
            "type":"Transportation"
        }
    ],
    "sg:phone":"+43 4366 49045515",
    "sg:postcode":"9500",
    "sg:province":"K\u00e4rnten",
    "sg:tags":[
        "personentransporte",
        "u"
    ],
    "wof:name":"Taxi Leitner KEG",
    "wof:placetype":"venue"
},
  "geometry": {"coordinates":[13.8294696808,46.6264457703],"type":"Point"}
}