{
  "type": "Feature",
  "properties": {
    "addr:full":"Diefenbachg 35-41  Wien Wien 1150",
    "addr:postcode":"35-41;1150",
    "iso:country":"AT",
    "sg:address":"Diefenbachg 35-41 ",
    "sg:city":"Wien",
    "sg:classifiers":[
        {
            "category":"Wholesale",
            "subcategory":"Drugs",
            "type":"Manufacturing & Wholesale Goods"
        }
    ],
    "sg:phone":"+43 4318 9418100",
    "sg:postcode":"1150",
    "sg:province":"Wien",
    "sg:tags":[
        "chemical",
        "pharmaceutical"
    ],
    "wof:name":"ROHM AND HAAS AUSTRIA GESMBH",
    "wof:placetype":"venue"
},
  "geometry": {"coordinates":[16.3324775696,48.1852989197],"type":"Point"}
}