{
  "type": "Feature",
  "properties": {
    "addr:full":"Faberstrasse 28 Brixlegg Tirol 6230",
    "addr:housenumber":"28",
    "addr:postcode":"6230",
    "addr:street":"Faberstrasse;Tirol",
    "iso:country":"AT",
    "sg:address":"Faberstrasse 28",
    "sg:city":"Brixlegg",
    "sg:classifiers":[
        {
            "category":"Community Center",
            "subcategory":"Senior",
            "type":"Public Place"
        }
    ],
    "sg:phone":"+43 5337 64711",
    "sg:postcode":"6230",
    "sg:province":"Tirol",
    "sg:tags":[
        "front",
        "wood",
        "door"
    ],
    "wof:name":"Johannes Bangheri",
    "wof:placetype":"venue"
},
  "geometry": {"coordinates":[11.8874111176,47.4239501953],"type":"Point"}
}