{
  "type": "Feature",
  "properties": {
    "addr:full":"Sonnbergstr 27 Freistadt Ober\u00f6sterreich 4240",
    "addr:housenumber":"27",
    "addr:postcode":"4240",
    "addr:street":"Sonnbergstr",
    "iso:country":"AT",
    "sg:address":"Sonnbergstr 27",
    "sg:city":"Freistadt",
    "sg:orig_category":"Rauchfangkehrer",
    "sg:phone":"+43 7942 77499",
    "sg:postcode":"4240",
    "sg:province":"Ober\u00f6sterreich",
    "wof:name":"Straub G\u00fcnter",
    "wof:placetype":"venue"
},
  "geometry": {"coordinates":[14.4937038422,48.515045166],"type":"Point"}
}