{
  "type": "Feature",
  "properties": {
    "addr:full":"Kellau 153 Kuchl Salzburg 5431",
    "addr:housenumber":"153",
    "addr:postcode":"5431",
    "addr:street":"Kellau;Salzburg",
    "iso:country":"AT",
    "sg:address":"Kellau 153",
    "sg:city":"Kuchl",
    "sg:orig_category":"Matratzen",
    "sg:phone":"+43 6244 33630",
    "sg:postcode":"5431",
    "sg:province":"Salzburg",
    "wof:name":"Elastica Matratzen Schaumstoffe-Zubeh\u00f6r GesmbH",
    "wof:placetype":"venue"
},
  "geometry": {"coordinates":[13.1438808441,47.625667572],"type":"Point"}
}