{
  "type": "Feature",
  "properties": {
    "iso:country":"AT",
    "sg:address":"Schmidberg 10",
    "sg:city":"Hargelsberg",
    "sg:classifiers":[
        {
            "category":"Home & Garden",
            "subcategory":"Building Materials",
            "type":"Retail Goods"
        }
    ],
    "sg:phone":"+43 7225 7391",
    "sg:postcode":"4483",
    "sg:province":"Ober\u00f6sterreich",
    "sg:tags":[
        "installation",
        "electric"
    ],
    "sg:website":"sl-elektro.at",
    "wof:name":"S & L Elektro GmbH",
    "wof:placetype":"venue"
},
  "geometry": {"coordinates":[14.4256868362,48.1508216858],"type":"Point"}
}