{
  "type": "Feature",
  "properties": {
    "addr:full":"Nr 314 Passail Steiermark 8162",
    "addr:postcode":"8162",
    "addr:street":"Nr",
    "iso:country":"AT",
    "sg:address":"Nr 314",
    "sg:city":"Passail",
    "sg:orig_category":"Imkereien",
    "sg:phone":"+43 3179 23788",
    "sg:postcode":"8162",
    "sg:province":"Steiermark",
    "wof:name":"Kreiner Almenland-Imkerei",
    "wof:placetype":"venue"
},
  "geometry": {"coordinates":[-75.768447876,39.7801780701],"type":"Point"}
}