{
  "type": "Feature",
  "properties": {
    "iso:country":"AT",
    "sg:address":"Vorwald 15",
    "sg:city":"Patergassen",
    "sg:classifiers":[
        {
            "category":"Building & Trades",
            "subcategory":"Construction",
            "type":"Services"
        }
    ],
    "sg:phone":"+43 4275 370",
    "sg:postcode":"9564",
    "sg:province":"K\u00e4rnten",
    "sg:tags":[
        "installation",
        "air-conditioning",
        "system"
    ],
    "wof:name":"Ewald Niederbichler",
    "wof:placetype":"venue"
},
  "geometry": {"coordinates":[13.8319253922,46.8631591797],"type":"Point"}
}