{
  "type": "Feature",
  "properties": {
    "iso:country":"AT",
    "sg:address":"Mariahilfer Str 62",
    "sg:city":"Wien",
    "sg:orig_category":"Lederbekleidung",
    "sg:phone":"+43 1 5238352",
    "sg:postcode":"1070",
    "sg:province":"Wien",
    "wof:name":"Leder Studio Kihssl",
    "wof:placetype":"venue"
},
  "geometry": {"coordinates":[16.35115242,48.1988639832],"type":"Point"}
}