{
  "type": "Feature",
  "properties": {
    "addr:full":"Auf der Trift 7 Eggendorf Nieder\u00f6sterreich 2492",
    "addr:housenumber":"7",
    "addr:postcode":"2492",
    "addr:street":"Auf Der Trift",
    "iso:country":"AT",
    "sg:address":"Auf der Trift 7",
    "sg:city":"Eggendorf",
    "sg:orig_category":"Autoreparatur",
    "sg:phone":"+43 2622 732740",
    "sg:postcode":"2492",
    "sg:province":"Nieder\u00f6sterreich",
    "wof:name":"Streyc Erich",
    "wof:placetype":"venue"
},
  "geometry": {"coordinates":[16.3227787018,47.8605766296],"type":"Point"}
}