{
  "type": "Feature",
  "properties": {
    "addr:full":"Nr 43 Maria Schmolln Ober\u00f6sterreich 5241",
    "addr:postcode":"5241",
    "addr:street":"Nr;Maria",
    "iso:country":"AT",
    "sg:address":"Nr 43",
    "sg:city":"Maria Schmolln",
    "sg:orig_category":"Autoreparatur",
    "sg:phone":"+43 7743 2215",
    "sg:postcode":"5241",
    "sg:province":"Ober\u00f6sterreich",
    "wof:name":"Autohaus Erich Priewasser",
    "wof:placetype":"venue"
},
  "geometry": {"coordinates":[13.2180109024,48.1389541626],"type":"Point"}
}