{
  "type": "Feature",
  "properties": {
    "addr:full":"Rennbahnstr 17 Salzburg Salzburg 5020",
    "addr:housenumber":"17",
    "addr:postcode":"5020",
    "addr:street":"Rennbahnstr;Salzburg",
    "iso:country":"AT",
    "sg:address":"Rennbahnstr 17",
    "sg:city":"Salzburg",
    "sg:orig_category":"Lebens- U Sozialberatung",
    "sg:phone":"+43 662 626702",
    "sg:postcode":"5020",
    "sg:province":"Salzburg",
    "wof:name":"Gordon-Oberhofer Susanne Mag",
    "wof:placetype":"venue"
},
  "geometry": {"coordinates":[13.0667562485,47.7960739136],"type":"Point"}
}