{
  "type": "Feature",
  "properties": {
    "addr:full":"Radetzkystr 116b Hohenems Vorarlberg 6845",
    "addr:housenumber":"116b",
    "addr:postcode":"6845",
    "iso:country":"AT",
    "sg:address":"Radetzkystr 116b",
    "sg:city":"Hohenems",
    "sg:orig_category":"Autoreparatur",
    "sg:phone":"+43 5576 73330",
    "sg:postcode":"6845",
    "sg:province":"Vorarlberg",
    "wof:name":"Glopper Garage",
    "wof:placetype":"venue"
},
  "geometry": {"coordinates":[9.6996612549,47.3765792847],"type":"Point"}
}