{
  "type": "Feature",
  "properties": {
    "addr:full":"Schulstr 128 F\u00fcgen Tirol 6263",
    "addr:housenumber":"128",
    "addr:postcode":"6263",
    "addr:street":"Fuegen Tirol",
    "iso:country":"AT",
    "sg:address":"Schulstr 128",
    "sg:city":"F\u00fcgen",
    "sg:orig_category":"Volksschulen",
    "sg:phone":"+43 5288 62335",
    "sg:postcode":"6263",
    "sg:province":"Tirol",
    "wof:name":"Volksschule",
    "wof:placetype":"venue"
},
  "geometry": {"coordinates":[11.8472137451,47.3460960388],"type":"Point"}
}