{
  "type": "Feature",
  "properties": {
    "iso:country":"AT",
    "sg:address":"V\u00f6cklabrucker Str 26",
    "sg:city":"Ampflwang im Hausruckwald",
    "sg:orig_category":"Fleischhauereien",
    "sg:phone":"+43 4376 752232",
    "sg:postcode":"4843",
    "sg:province":"Ober\u00f6sterreich",
    "wof:name":"Firzinger Rupert",
    "wof:placetype":"venue"
},
  "geometry": {"coordinates":[13.5672531128,48.0894012451],"type":"Point"}
}