{
  "type": "Feature",
  "properties": {
    "addr:full":"Bundesstrasse 6-8 Klaus-Weiler Vorarlberg 6833",
    "addr:housenumber":"6-8",
    "addr:postcode":"6833",
    "addr:street":"Bundesstrasse",
    "iso:country":"AT",
    "sg:address":"Bundesstrasse 6-8",
    "sg:city":"Klaus-Weiler",
    "sg:classifiers":[
        {
            "category":"Professional",
            "subcategory":"Advertising",
            "type":"Services"
        }
    ],
    "sg:phone":"+43 5523 58562",
    "sg:postcode":"6833",
    "sg:province":"Vorarlberg",
    "sg:tags":[
        "athletic"
    ],
    "wof:name":"Ridi Grafik Art Design",
    "wof:placetype":"venue"
},
  "geometry": {"coordinates":[9.6528644562,47.3032798767],"type":"Point"}
}