{
  "type": "Feature",
  "properties": {
    "addr:full":"Reichenfels K\u00e4rnten 9463",
    "addr:postcode":"9463",
    "iso:country":"AT",
    "sg:city":"Reichenfels",
    "sg:orig_category":"Bestattungsunternehmen",
    "sg:phone":"+43 4359 22210",
    "sg:postcode":"9463",
    "sg:province":"K\u00e4rnten",
    "wof:name":"St\u00e4dtische Bestattung Wolfsberg - Zweigstelle Reichenfels",
    "wof:placetype":"venue"
},
  "geometry": {"coordinates":[14.7406215668,47.0075035095],"type":"Point"}
}