{
  "type": "Feature",
  "properties": {
    "addr:full":"Linzer Str 37 Braunau am Inn Ober\u00f6sterreich 5280",
    "addr:housenumber":"37",
    "addr:postcode":"5280",
    "addr:street":"Linzer Str",
    "iso:country":"AT",
    "sg:address":"Linzer Str 37",
    "sg:city":"Braunau am Inn",
    "sg:orig_category":"Physiotherapie",
    "sg:phone":"+43 4377 2264273",
    "sg:postcode":"5280",
    "sg:province":"Ober\u00f6sterreich",
    "wof:name":"Physio Aktiv - Schmid Christian",
    "wof:placetype":"venue"
},
  "geometry": {"coordinates":[13.0378026962,48.2595825195],"type":"Point"}
}