{
  "type": "Feature",
  "properties": {
    "addr:full":"Nr 395 Roppen Tirol 6426",
    "addr:postcode":"6426",
    "addr:street":"Nr 395;Tirol",
    "iso:country":"AT",
    "sg:address":"Nr 395",
    "sg:city":"Roppen",
    "sg:orig_category":"Asphaltierungen",
    "sg:phone":"+43 5417 56860",
    "sg:postcode":"6426",
    "sg:province":"Tirol",
    "wof:name":"Teerag-Asdag AG",
    "wof:placetype":"venue"
},
  "geometry": {"coordinates":[10.8198480606,47.2171440125],"type":"Point"}
}