{
  "type": "Feature",
  "properties": {
    "addr:full":"Ostwerkg 38 Judenburg Steiermark 8750",
    "addr:housenumber":"38",
    "addr:postcode":"8750",
    "addr:street":"Ostwerkg",
    "iso:country":"AT",
    "sg:address":"Ostwerkg 38",
    "sg:city":"Judenburg",
    "sg:classifiers":[
        {
            "category":"Taxi",
            "type":"Transportation"
        }
    ],
    "sg:phone":"+43 4335 7285700",
    "sg:postcode":"8750",
    "sg:province":"Steiermark",
    "sg:tags":[
        "personentransporte",
        "u"
    ],
    "wof:name":"Schwarz Gerlinde",
    "wof:placetype":"venue"
},
  "geometry": {"coordinates":[14.6691112518,47.1778488159],"type":"Point"}
}