{
  "type": "Feature",
  "properties": {
    "addr:full":"Rosentaler Strasse 42 Velden am W\u00f6rther See K\u00e4rnten 9220",
    "addr:housenumber":"42",
    "addr:postcode":"9220",
    "addr:street":"Rosentaler Strasse;Kaernten",
    "iso:country":"AT",
    "sg:address":"Rosentaler Strasse 42",
    "sg:city":"Velden am W\u00f6rther See",
    "sg:classifiers":[
        {
            "category":"Shopping",
            "subcategory":"Books",
            "type":"Retail Goods"
        }
    ],
    "sg:phone":"+43 4274 51683",
    "sg:postcode":"9220",
    "sg:province":"K\u00e4rnten",
    "sg:website":"relimedien.com",
    "wof:name":"Paraclet Multimedia",
    "wof:placetype":"venue"
},
  "geometry": {"coordinates":[14.041557312,46.609172821],"type":"Point"}
}