{
  "type": "Feature",
  "properties": {
    "addr:full":"Nr 6 Mistelbach Nieder\u00f6sterreich 2130",
    "addr:postcode":"2130",
    "addr:street":"Nr;Niederoesterreich",
    "iso:country":"AT",
    "sg:address":"Nr 6",
    "sg:city":"Mistelbach",
    "sg:orig_category":"Hausbetreuung",
    "sg:phone":"+43 650 9615897",
    "sg:postcode":"2130",
    "sg:province":"Nieder\u00f6sterreich",
    "wof:name":"Haus-Service - Buchner-Uhl",
    "wof:placetype":"venue"
},
  "geometry": {"coordinates":[119.9737319946,31.7901992798],"type":"Point"}
}