{
  "type": "Feature",
  "properties": {
    "iso:country":"AT",
    "sg:address":"Grazer Str 82",
    "sg:city":"Kapfenberg",
    "sg:orig_category":"Politische Parteien",
    "sg:phone":"+43 3862 24974",
    "sg:postcode":"8605",
    "sg:province":"Steiermark",
    "wof:name":"Sozialdemokratische Partei \u00d6sterreichs",
    "wof:placetype":"venue"
},
  "geometry": {"coordinates":[15.2817077637,47.4372253418],"type":"Point"}
}