{
  "type": "Feature",
  "properties": {
    "addr:full":"Eberweis 14 Heidenreichstein Nieder\u00f6sterreich 3860",
    "addr:housenumber":"14",
    "addr:postcode":"3860",
    "addr:street":"Eberweis",
    "iso:country":"AT",
    "sg:address":"Eberweis 14",
    "sg:city":"Heidenreichstein",
    "sg:classifiers":[
        {
            "category":"Farming",
            "subcategory":"Livestock Farm",
            "type":"Manufacturing & Wholesale Goods"
        }
    ],
    "sg:phone":"+43 4328 6253400",
    "sg:postcode":"3860",
    "sg:province":"Nieder\u00f6sterreich",
    "sg:tags":[
        "-handel",
        "viehzucht",
        "u"
    ],
    "wof:name":"Granner Franz",
    "wof:placetype":"venue"
},
  "geometry": {"coordinates":[15.0861291885,48.881690979],"type":"Point"}
}