{
  "type": "Feature",
  "properties": {
    "addr:full":"Firnweg 2 Saalfelden am Steinernen Meer Salzburg 5760",
    "addr:housenumber":"2",
    "addr:postcode":"5760",
    "addr:street":"Firnweg",
    "iso:country":"AT",
    "sg:address":"Firnweg 2",
    "sg:city":"Saalfelden am Steinernen Meer",
    "sg:orig_category":"Maler, Anstreicher U Lackierer",
    "sg:phone":"+43 6582 73669",
    "sg:postcode":"5760",
    "sg:province":"Salzburg",
    "wof:name":"Schreder Josef",
    "wof:placetype":"venue"
},
  "geometry": {"coordinates":[12.8375492096,47.4256591797],"type":"Point"}
}