{
  "type": "Feature",
  "properties": {
    "addr:full":"Nonntaler Hauptstr 42a Salzburg Salzburg 5020",
    "addr:housenumber":"42a",
    "addr:postcode":"5020",
    "addr:street":"Nonntaler Hauptstr;Salzburg",
    "iso:country":"AT",
    "sg:address":"Nonntaler Hauptstr 42a",
    "sg:city":"Salzburg",
    "sg:orig_category":"Vinotheken",
    "sg:phone":"+43 662 8295100",
    "sg:postcode":"5020",
    "sg:province":"Salzburg",
    "wof:name":"Kremslehner GesmbH",
    "wof:placetype":"venue"
},
  "geometry": {"coordinates":[13.0490150452,47.7910079956],"type":"Point"}
}