{
  "type": "Feature",
  "properties": {
    "iso:country":"AT",
    "sg:address":"Schubertstr 15",
    "sg:city":"Kufstein",
    "sg:classifiers":[
        {
            "category":"Shopping",
            "subcategory":"Bicycles & Sporting Goods",
            "type":"Retail Goods"
        }
    ],
    "sg:phone":"+43 4353 7264396",
    "sg:postcode":"6330",
    "sg:province":"Tirol",
    "sg:tags":[
        "munition",
        "u",
        "waffen"
    ],
    "wof:name":"Waffen Furtschegger",
    "wof:placetype":"venue"
},
  "geometry": {"coordinates":[12.1626720428,47.5818214417],"type":"Point"}
}