{
  "type": "Feature",
  "properties": {
    "addr:full":"Am Corso 27 Velden am W\u00f6rther See K\u00e4rnten 9220",
    "addr:housenumber":"27",
    "addr:postcode":"9220",
    "addr:street":"Am Corso;Kaernten",
    "iso:country":"AT",
    "sg:address":"Am Corso 27",
    "sg:city":"Velden am W\u00f6rther See",
    "sg:orig_category":"Werbeagenturen",
    "sg:phone":"+43 4365 07072270",
    "sg:postcode":"9220",
    "sg:province":"K\u00e4rnten",
    "wof:name":"Atelier Bolesch Inh Helmut Bolesch",
    "wof:placetype":"venue"
},
  "geometry": {"coordinates":[14.0423069,46.6139907837],"type":"Point"}
}