{
  "type": "Feature",
  "properties": {
    "addr:full":"Nr 127 Ramsau am Dachstein Steiermark 8972",
    "addr:postcode":"8972",
    "addr:street":"Nr 127",
    "iso:country":"AT",
    "sg:address":"Nr 127",
    "sg:city":"Ramsau am Dachstein",
    "sg:orig_category":"\u00c3\u201erzte / F Allgemeinmedizin",
    "sg:phone":"+43 3687 81081",
    "sg:postcode":"8972",
    "sg:province":"Steiermark",
    "wof:name":"Harwald Heinz Dr",
    "wof:placetype":"venue"
},
  "geometry": {"coordinates":[13.6525297165,47.4214515686],"type":"Point"}
}