{
  "type": "Feature",
  "properties": {
    "iso:country":"AT",
    "sg:address":"Haferg 9",
    "sg:city":"Wels",
    "sg:orig_category":"Weinstuben",
    "sg:phone":"+43 4372 4245187",
    "sg:postcode":"4600",
    "sg:province":"Ober\u00f6sterreich",
    "wof:name":"Weinstube Neumayr",
    "wof:placetype":"venue"
},
  "geometry": {"coordinates":[14.0264720917,48.1565246582],"type":"Point"}
}