{
  "type": "Feature",
  "properties": {
    "iso:country":"AT",
    "sg:address":"Nr 40",
    "sg:city":"Gresten",
    "sg:orig_category":"Farben U Lacke / Erzeugung U Gro\u00c3\u0178handel",
    "sg:phone":"+43 4374 872600",
    "sg:postcode":"3264",
    "sg:province":"Nieder\u00f6sterreich",
    "wof:name":"Dekor Farbenerzeugungs GmbH",
    "wof:placetype":"venue"
},
  "geometry": {"coordinates":[15.0260295868,47.9850082397],"type":"Point"}
}