{
  "type": "Feature",
  "properties": {
    "addr:full":"Bundesstr 3 Fohnsdorf Steiermark 8753",
    "addr:housenumber":"3",
    "addr:postcode":"8753",
    "addr:street":"Bundesstr",
    "iso:country":"AT",
    "sg:address":"Bundesstr 3",
    "sg:city":"Fohnsdorf",
    "sg:orig_category":"Transportunternehmen",
    "sg:phone":"+43 4335 7282990",
    "sg:postcode":"8753",
    "sg:province":"Steiermark",
    "wof:name":"Zechner Transport GesmbH",
    "wof:placetype":"venue"
},
  "geometry": {"coordinates":[14.6799926758,47.1830558777],"type":"Point"}
}