{
  "type": "Feature",
  "properties": {
    "iso:country":"AT",
    "sg:address":"Schmiedg 20",
    "sg:city":"Leibnitz",
    "sg:orig_category":"Fliesen- U Plattenverlegungen",
    "sg:phone":"+43 4334 5271160",
    "sg:postcode":"8430",
    "sg:province":"Steiermark",
    "wof:name":"Preschern GesmbH",
    "wof:placetype":"venue"
},
  "geometry": {"coordinates":[15.5392131805,46.7801246643],"type":"Point"}
}