{
  "type": "Feature",
  "properties": {
    "addr:full":"Bundesstr 2a Steinhaus am Semmering Steiermark 8685",
    "addr:housenumber":"2a",
    "addr:postcode":"8685",
    "addr:street":"Bundesstr",
    "iso:country":"AT",
    "sg:address":"Bundesstr 2a",
    "sg:city":"Steinhaus am Semmering",
    "sg:orig_category":"Banken U Sparkassen",
    "sg:phone":"+43 4326 647004",
    "sg:postcode":"8685",
    "sg:province":"Steiermark",
    "wof:name":"Sparkasse M\u00fcrzzuschlag",
    "wof:placetype":"venue"
},
  "geometry": {"coordinates":[15.7889738083,47.6206817627],"type":"Point"}
}