{
  "type": "Feature",
  "properties": {
    "addr:full":"Westbahnstrasse 55 St. Valentin Nieder\u00f6sterreich 4300",
    "addr:housenumber":"55",
    "addr:postcode":"4300",
    "addr:street":"Westbahnstrasse",
    "iso:country":"AT",
    "sg:address":"Westbahnstrasse 55",
    "sg:city":"St. Valentin",
    "sg:classifiers":[
        {
            "category":"Retail",
            "subcategory":"Auto Rental",
            "type":"Services"
        }
    ],
    "sg:phone":"+43 7435 591500",
    "sg:postcode":"4300",
    "sg:province":"Nieder\u00f6sterreich",
    "sg:tags":[
        "car",
        "transport"
    ],
    "wof:name":"G\u00fcnter Hittinger",
    "wof:placetype":"venue"
},
  "geometry": {"coordinates":[14.5178194046,48.1902770996],"type":"Point"}
}