{
  "type": "Feature",
  "properties": {
    "iso:country":"AT",
    "sg:address":"Brunng 1",
    "sg:city":"Anif",
    "sg:classifiers":[
        {
            "category":"Restaurant",
            "type":"Food & Drink"
        }
    ],
    "sg:phone":"+43 6246 7241115",
    "sg:postcode":"5081",
    "sg:province":"Salzburg",
    "wof:name":"Friesacher's Einkehr",
    "wof:placetype":"venue"
},
  "geometry": {"coordinates":[13.0646266937,47.7512779236],"type":"Point"}
}