{
  "type": "Feature",
  "properties": {
    "addr:full":"Nr 6 Wei\u00dfkirchen in Steiermark Steiermark 8741",
    "addr:housenumber":"8741",
    "addr:street":"Nr",
    "iso:country":"AT",
    "sg:address":"Nr 6",
    "sg:city":"Wei\u00dfkirchen in Steiermark",
    "sg:orig_category":"Behinderungen / Leben Mit Behinderungen",
    "sg:phone":"+43 3577 82443",
    "sg:postcode":"8741",
    "sg:province":"Steiermark",
    "wof:name":"Lebenshilfe Steiermark",
    "wof:placetype":"venue"
},
  "geometry": {"coordinates":[166.9221496582,-0.5282999873],"type":"Point"}
}