{
  "type": "Feature",
  "properties": {
    "addr:full":"Welser Str 24 Leonding Ober\u00f6sterreich 4060",
    "addr:postcode":"4060",
    "addr:street":"Str 24",
    "iso:country":"AT",
    "sg:address":"Welser Str 24",
    "sg:city":"Leonding",
    "sg:orig_category":"Forschungsinstitute",
    "sg:phone":"+43 732 682364",
    "sg:postcode":"4060",
    "sg:province":"Ober\u00f6sterreich",
    "wof:name":"Schukra Forschungs- und Entwicklungs Ing Wilhelm Schuster GmbH",
    "wof:placetype":"venue"
},
  "geometry": {"coordinates":[14.2688293457,48.2712593079],"type":"Point"}
}