{
  "type": "Feature",
  "properties": {
    "addr:full":"Oberkienberg 16 Thomasroith Ober\u00f6sterreich 4905",
    "addr:housenumber":"16",
    "addr:postcode":"4905",
    "addr:street":"Oberkienberg;Oberoesterreich",
    "iso:country":"AT",
    "sg:address":"Oberkienberg 16",
    "sg:city":"Thomasroith",
    "sg:orig_category":"Maschinenbau",
    "sg:phone":"+43 767650010",
    "sg:postcode":"4905",
    "sg:province":"Ober\u00f6sterreich",
    "wof:name":"samo Maschinenbau GmbH",
    "wof:placetype":"venue"
},
  "geometry": {"coordinates":[13.617026329,48.083366394],"type":"Point"}
}