{
  "type": "Feature",
  "properties": {
    "iso:country":"AT",
    "sg:address":"Ketzerg 65",
    "sg:city":"Wien",
    "sg:orig_category":"Physikalische Institute",
    "sg:phone":"+43 1 69987650",
    "sg:postcode":"1230",
    "sg:province":"Wien",
    "wof:name":"Kienbacher Thomas Dr",
    "wof:placetype":"venue"
},
  "geometry": {"coordinates":[16.311466217,48.1272354126],"type":"Point"}
}