{
  "type": "Feature",
  "properties": {
    "addr:full":"Hauptstr 31 Gablitz Nieder\u00f6sterreich 3003",
    "addr:housenumber":"31",
    "addr:postcode":"3003",
    "addr:street":"Hauptstr",
    "iso:country":"AT",
    "sg:address":"Hauptstr 31",
    "sg:city":"Gablitz",
    "sg:orig_category":"Feuerwehren",
    "sg:phone":"+43 2231 63410",
    "sg:postcode":"3003",
    "sg:province":"Nieder\u00f6sterreich",
    "wof:name":"Freiwillige Feuerwehr Gablitz",
    "wof:placetype":"venue"
},
  "geometry": {"coordinates":[16.1513957977,48.2291984558],"type":"Point"}
}