{
  "type": "Feature",
  "properties": {
    "addr:full":"Weidenstr 6B Gunskirchen Ober\u00f6sterreich 4623",
    "addr:housenumber":"6b",
    "addr:postcode":"4623",
    "addr:street":"Weidenstr",
    "iso:country":"AT",
    "sg:address":"Weidenstr 6B",
    "sg:city":"Gunskirchen",
    "sg:orig_category":"Handelsagenturen",
    "sg:phone":"+43 7246 8457",
    "sg:postcode":"4623",
    "sg:province":"Ober\u00f6sterreich",
    "wof:name":"Mittendorfer Alfred",
    "wof:placetype":"venue"
},
  "geometry": {"coordinates":[13.937204361,48.1289100647],"type":"Point"}
}