{
  "type": "Feature",
  "properties": {
    "addr:full":"Michaelipassage Hartberg Steiermark 8230",
    "addr:postcode":"8230",
    "iso:country":"AT",
    "sg:address":"Michaelipassage",
    "sg:city":"Hartberg",
    "sg:orig_category":"Damenmoden",
    "sg:phone":"+43 4333 3263138",
    "sg:postcode":"8230",
    "sg:province":"Steiermark",
    "wof:name":"Textilhof",
    "wof:placetype":"venue"
},
  "geometry": {"coordinates":[15.9689769745,47.2798042297],"type":"Point"}
}