{
  "type": "Feature",
  "properties": {
    "addr:full":"Kircheng 4-6 Korneuburg Nieder\u00f6sterreich 2100",
    "addr:housenumber":"4-6",
    "addr:postcode":"2100",
    "addr:street":"Kircheng;Niederoesterreich",
    "iso:country":"AT",
    "sg:address":"Kircheng 4-6",
    "sg:city":"Korneuburg",
    "sg:classifiers":[
        {
            "category":"Restaurant",
            "type":"Food & Drink"
        }
    ],
    "sg:phone":"+43 2262 74593",
    "sg:postcode":"2100",
    "sg:province":"Nieder\u00f6sterreich",
    "wof:name":"il barolo - Restaurant-Vinothek",
    "wof:placetype":"venue"
},
  "geometry": {"coordinates":[16.3348197937,48.3453903198],"type":"Point"}
}