{
  "type": "Feature",
  "properties": {
    "addr:full":"Schrott-Fiechtl-Str 30 Vomp Tirol 6134",
    "addr:housenumber":"30",
    "addr:postcode":"6134",
    "addr:street":"Schrott-Fiechtl-Str;Tirol",
    "iso:country":"AT",
    "sg:address":"Schrott-Fiechtl-Str 30",
    "sg:city":"Vomp",
    "sg:orig_category":"Baumaschinenverleih",
    "sg:phone":"+43 5242 66973",
    "sg:postcode":"6134",
    "sg:province":"Tirol",
    "sg:website":"bohrmaschinenverleih.com",
    "wof:name":"Seebacher Emmerich",
    "wof:placetype":"venue"
},
  "geometry": {"coordinates":[11.6968860626,47.3464279175],"type":"Point"}
}