{
  "type": "Feature",
  "properties": {
    "addr:full":"Greinerg 42 Wien Wien 1190",
    "addr:housenumber":"42",
    "addr:postcode":"1190",
    "addr:street":"Greinerg",
    "iso:country":"AT",
    "sg:address":"Greinerg 42",
    "sg:city":"Wien",
    "sg:classifiers":[
        {
            "category":"Retail",
            "subcategory":"Event Space",
            "type":"Services"
        }
    ],
    "sg:phone":"+43 4313 703667",
    "sg:postcode":"1190",
    "sg:province":"Wien",
    "sg:tags":[
        "hand-",
        "u",
        "fu\u00c3\u0178pflege"
    ],
    "wof:name":"Sanitas Hand u Fu\u00dfpflege",
    "wof:placetype":"venue"
},
  "geometry": {"coordinates":[16.3652534485,48.2596282959],"type":"Point"}
}