{
  "type": "Feature",
  "properties": {
    "addr:full":"Pfarrstr 267 Mariapfarr Salzburg 5571",
    "addr:housenumber":"267",
    "addr:postcode":"5571",
    "addr:street":"Mariapfarr Salzburg",
    "iso:country":"AT",
    "sg:address":"Pfarrstr 267",
    "sg:city":"Mariapfarr",
    "sg:orig_category":"Installationsunternehmen",
    "sg:phone":"+43 6473 8381",
    "sg:postcode":"5571",
    "sg:province":"Salzburg",
    "wof:name":"Holzer GmbH & Co KG",
    "wof:placetype":"venue"
},
  "geometry": {"coordinates":[13.7467956543,47.1496734619],"type":"Point"}
}