{
  "type": "Feature",
  "properties": {
    "iso:country":"AT",
    "sg:address":"Franz H\u00f6nig-Str 7",
    "sg:city":"Ried im Innkreis",
    "sg:orig_category":"Badezimmer U Badezimmereinrichtungen",
    "sg:phone":"+43 4377 528088611",
    "sg:postcode":"4910",
    "sg:province":"Ober\u00f6sterreich",
    "wof:name":"\u00d6AG Handelsbeteiligungs AG Gesch\u00e4ftsbereich \u00d6AG Sanit\u00e4r- u Heizungsgro\u00dfhandel",
    "wof:placetype":"venue"
},
  "geometry": {"coordinates":[13.4868593216,48.2054405212],"type":"Point"}
}