{
  "type": "Feature",
  "properties": {
    "addr:full":"Esterhazystrasse 15 Hallein Salzburg 5400",
    "addr:housenumber":"15",
    "addr:postcode":"5400",
    "addr:street":"Esterhazystrasse;Salzburg",
    "iso:country":"AT",
    "sg:address":"Esterhazystrasse 15",
    "sg:city":"Hallein",
    "sg:classifiers":[
        {
            "category":"Wholesale",
            "subcategory":"Office Equipment",
            "type":"Manufacturing & Wholesale Goods"
        }
    ],
    "sg:phone":"+43 6245 78870",
    "sg:postcode":"5400",
    "sg:province":"Salzburg",
    "sg:tags":[
        "furniture"
    ],
    "wof:name":"Richard M\u00fcller Betriebseinrichtungen",
    "wof:placetype":"venue"
},
  "geometry": {"coordinates":[13.0950832367,47.6907691956],"type":"Point"}
}