{
  "type": "Feature",
  "properties": {
    "addr:full":"Hosla 3 Unterrabnitz Burgenland 7371",
    "addr:housenumber":"3",
    "addr:postcode":"7371",
    "addr:street":"Hosla",
    "iso:country":"AT",
    "sg:address":"Hosla 3",
    "sg:city":"Unterrabnitz",
    "sg:orig_category":"Tischlereien",
    "sg:phone":"+43 2616 8728",
    "sg:postcode":"7371",
    "sg:province":"Burgenland",
    "wof:name":"Janisch Christian",
    "wof:placetype":"venue"
},
  "geometry": {"coordinates":[16.4100131989,47.4457054138],"type":"Point"}
}