{
  "type": "Feature",
  "properties": {
    "addr:full":"Gewerbestr 4 St. Veit an der Glan K\u00e4rnten 9300",
    "addr:housenumber":"4",
    "addr:postcode":"9300",
    "addr:street":"Gewerbestr;Kaernten",
    "iso:country":"AT",
    "sg:address":"Gewerbestr 4",
    "sg:city":"St. Veit an der Glan",
    "sg:orig_category":"Autoreparatur",
    "sg:phone":"+43 4212 27810",
    "sg:postcode":"9300",
    "sg:province":"K\u00e4rnten",
    "wof:name":"Freithofnig Josef",
    "wof:placetype":"venue"
},
  "geometry": {"coordinates":[14.3538818359,46.7599258423],"type":"Point"}
}