{
  "type": "Feature",
  "properties": {
    "addr:full":"Hauptstrasse 46 Strem Burgenland 7522",
    "addr:housenumber":"46",
    "addr:postcode":"7522",
    "addr:street":"Hauptstrasse",
    "iso:country":"AT",
    "sg:address":"Hauptstrasse 46",
    "sg:city":"Strem",
    "sg:orig_category":"Furniture, General",
    "sg:phone":"+43 3324 7223",
    "sg:postcode":"7522",
    "sg:province":"Burgenland",
    "sg:website":"tischler-schweizer.at",
    "wof:name":"Stefan Schweitzer",
    "wof:placetype":"venue"
},
  "geometry": {"coordinates":[16.4143295288,47.0483589172],"type":"Point"}
}