{
  "type": "Feature",
  "properties": {
    "addr:full":"Bahnhofpl 4 Bludenz Vorarlberg 6700",
    "addr:housenumber":"4",
    "addr:postcode":"6700",
    "addr:street":"Bahnhofpl",
    "iso:country":"AT",
    "sg:address":"Bahnhofpl 4",
    "sg:city":"Bludenz",
    "sg:classifiers":[
        {
            "category":"Restaurant",
            "type":"Food & Drink"
        }
    ],
    "sg:phone":"+43 5552 31104",
    "sg:postcode":"6700",
    "sg:province":"Vorarlberg",
    "sg:tags":[
        "pizzeria"
    ],
    "wof:name":"Il Paradios - italienisches Spezialit\u00e4tenrestaurant",
    "wof:placetype":"venue"
},
  "geometry": {"coordinates":[9.8157367706,47.1548652649],"type":"Point"}
}