{
  "type": "Feature",
  "properties": {
    "addr:full":"Petraschg 3 Wien Wien 1200",
    "addr:housenumber":"3",
    "addr:postcode":"1200",
    "addr:street":"Petraschg",
    "iso:country":"AT",
    "sg:address":"Petraschg 3",
    "sg:city":"Wien",
    "sg:orig_category":"Mietautos",
    "sg:phone":"+43 1 3343100",
    "sg:postcode":"1200",
    "sg:province":"Wien",
    "wof:name":"Mietwagen Neudeck GesmbH",
    "wof:placetype":"venue"
},
  "geometry": {"coordinates":[16.3719139099,48.2282218933],"type":"Point"}
}