{
  "type": "Feature",
  "properties": {
    "addr:full":"Hauptpl 9/3/2 Wiener Neustadt Nieder\u00f6sterreich 2700",
    "addr:housenumber":"9 / 3 / 2",
    "addr:postcode":"2700",
    "addr:street":"Hauptpl",
    "iso:country":"AT",
    "sg:address":"Hauptpl 9/3/2",
    "sg:city":"Wiener Neustadt",
    "sg:orig_category":"Steuerberatung",
    "sg:phone":"+43 2622 212720",
    "sg:postcode":"2700",
    "sg:province":"Nieder\u00f6sterreich",
    "wof:name":"Lang Kurz Pollross OEG",
    "wof:placetype":"venue"
},
  "geometry": {"coordinates":[16.2455158234,47.8128814697],"type":"Point"}
}