{
  "type": "Feature",
  "properties": {
    "addr:full":"Jahnstr 12 Innsbruck Tirol 6020",
    "addr:housenumber":"12",
    "addr:postcode":"6020",
    "addr:street":"Jahnstr;Tirol",
    "iso:country":"AT",
    "sg:address":"Jahnstr 12",
    "sg:city":"Innsbruck",
    "sg:orig_category":"Installationsunternehmen",
    "sg:phone":"+43 512 573557",
    "sg:postcode":"6020",
    "sg:province":"Tirol",
    "wof:name":"Riedle Max Ing KG",
    "wof:placetype":"venue"
},
  "geometry": {"coordinates":[11.4042291641,47.2692832947],"type":"Point"}
}