{
  "type": "Feature",
  "properties": {
    "addr:full":"Kinderspitalg 4 Wien Wien 1090",
    "addr:housenumber":"4",
    "addr:postcode":"1090",
    "addr:street":"Kinderspitalg",
    "iso:country":"AT",
    "sg:address":"Kinderspitalg 4",
    "sg:city":"Wien",
    "sg:orig_category":"Friseure U Frisiersalons",
    "sg:phone":"+43 1 4087875",
    "sg:postcode":"1090",
    "sg:province":"Wien",
    "wof:name":"Coiffeur Cut Noir",
    "wof:placetype":"venue"
},
  "geometry": {"coordinates":[16.3451080322,48.2157783508],"type":"Point"}
}