{
  "type": "Feature",
  "properties": {
    "iso:country":"AT",
    "sg:city":"Eisenstadt",
    "sg:orig_category":"Paketdienste, Logistik, Speditionen",
    "sg:phone":"+43 810 221133",
    "sg:postcode":"7000",
    "sg:province":"Burgenland",
    "wof:name":"\u00d6BB-G\u00fcterverkehr - Rail Cargo Austria",
    "wof:placetype":"venue"
},
  "geometry": {"coordinates":[16.5189552307,47.8455657959],"type":"Point"}
}