{
  "type": "Feature",
  "properties": {
    "addr:full":"Ragnitzstr 64 Ragnitz Steiermark 8047",
    "addr:housenumber":"64",
    "addr:postcode":"8047",
    "addr:street":"Ragnitzstr",
    "iso:country":"AT",
    "sg:address":"Ragnitzstr 64",
    "sg:city":"Ragnitz",
    "sg:orig_category":"Politische Parteien",
    "sg:phone":"+43 316 304612",
    "sg:postcode":"8047",
    "sg:province":"Steiermark",
    "wof:name":"Sozialdemokratische Partei \u00d6sterreichs LdsOrg Stmk",
    "wof:placetype":"venue"
},
  "geometry": {"coordinates":[15.4804210663,47.0786705017],"type":"Point"}
}