{
  "type": "Feature",
  "properties": {
    "addr:full":"Piccostr 26a Villach K\u00e4rnten 9500",
    "addr:housenumber":"26a",
    "addr:postcode":"9500",
    "addr:street":"Piccostr;Kaernten",
    "iso:country":"AT",
    "sg:address":"Piccostr 26a",
    "sg:city":"Villach",
    "sg:orig_category":"Holzbearbeitungsmaschinen U -Werkzeuge",
    "sg:phone":"+43 4342 42431431",
    "sg:postcode":"9500",
    "sg:province":"K\u00e4rnten",
    "sg:website":"members.aon.at/maschinen.schack",
    "wof:name":"Schack Maschinenzentrum",
    "wof:placetype":"venue"
},
  "geometry": {"coordinates":[13.8574676514,46.6204376221],"type":"Point"}
}