{
  "type": "Feature",
  "properties": {
    "iso:country":"AT",
    "sg:address":"Goldschlagstrasse 114",
    "sg:city":"Wien",
    "sg:classifiers":[
        {
            "category":"Manufacturing",
            "subcategory":"Tools & Machinery",
            "type":"Manufacturing & Wholesale Goods"
        }
    ],
    "sg:phone":"+43 1 9823303",
    "sg:postcode":"1150",
    "sg:province":"Wien",
    "sg:tags":[
        "machining",
        "cnc"
    ],
    "wof:name":"Mechanische Werkst\u00e4tte Walter Buczolich GmbH",
    "wof:placetype":"venue"
},
  "geometry": {"coordinates":[16.3158092499,48.1948776245],"type":"Point"}
}