{
  "type": "Feature",
  "properties": {
    "addr:full":"Laaben 143 Laaben Nieder\u00f6sterreich 3053",
    "addr:housenumber":"143",
    "addr:postcode":"3053",
    "addr:street":"Laaben;Laaben Niederoesterreich",
    "iso:country":"AT",
    "sg:address":"Laaben 143",
    "sg:city":"Laaben",
    "sg:classifiers":[
        {
            "category":"Manufacturing",
            "subcategory":"Furniture",
            "type":"Manufacturing & Wholesale Goods"
        }
    ],
    "sg:phone":"+43 2774 8214",
    "sg:postcode":"3053",
    "sg:province":"Nieder\u00f6sterreich",
    "sg:tags":[
        "beech"
    ],
    "wof:name":"Peter Praschl-Bichler",
    "wof:placetype":"venue"
},
  "geometry": {"coordinates":[15.8808193207,48.1025161743],"type":"Point"}
}