{
  "type": "Feature",
  "properties": {
    "iso:country":"AT",
    "sg:address":"Eggenberger Allee 89",
    "sg:city":"Graz",
    "sg:orig_category":"Weine / Gro\u00c3\u0178handel",
    "sg:phone":"+43 316 5766000",
    "sg:postcode":"8020",
    "sg:province":"Steiermark",
    "wof:name":"Pfrimer Peter - Weine GmbH",
    "wof:placetype":"venue"
},
  "geometry": {"coordinates":[15.3959760666,47.0720214844],"type":"Point"}
}