{
  "type": "Feature",
  "properties": {
    "addr:full":"St. Veiter Str 118 Klagenfurt K\u00e4rnten 9020",
    "addr:housenumber":"118",
    "addr:postcode":"9020",
    "addr:street":"St. Veiter Str;Kaernten",
    "iso:country":"AT",
    "sg:address":"St. Veiter Str 118",
    "sg:city":"Klagenfurt",
    "sg:orig_category":"Estriche",
    "sg:phone":"+43 463 42439",
    "sg:postcode":"9020",
    "sg:province":"K\u00e4rnten",
    "wof:name":"Estriche Wiltschnig",
    "wof:placetype":"venue"
},
  "geometry": {"coordinates":[14.3134241104,46.6383056641],"type":"Point"}
}