{
  "type": "Feature",
  "properties": {
    "addr:full":"Pontenstr 20 Lustenau Vorarlberg 6890",
    "addr:housenumber":"20",
    "addr:postcode":"6890",
    "addr:street":"Pontenstr",
    "iso:country":"AT",
    "sg:address":"Pontenstr 20",
    "sg:city":"Lustenau",
    "sg:orig_category":"Bibliotheken",
    "sg:phone":"+43 5577 83292",
    "sg:postcode":"6890",
    "sg:province":"Vorarlberg",
    "wof:name":"Arbeiterkammer-Bibliothek",
    "wof:placetype":"venue"
},
  "geometry": {"coordinates":[9.6551837921,47.4297790527],"type":"Point"}
}