{
  "type": "Feature",
  "properties": {
    "iso:country":"AT",
    "sg:address":"Untere Hauptstr 21",
    "sg:city":"Hohenruppersdorf",
    "sg:orig_category":"Feuerwehren",
    "sg:phone":"+43 2574 8322",
    "sg:postcode":"2223",
    "sg:province":"Nieder\u00f6sterreich",
    "wof:name":"Freiwillige Feuerwehr Hohenruppersdorf",
    "wof:placetype":"venue"
},
  "geometry": {"coordinates":[16.655210495,48.4612617493],"type":"Point"}
}