{
  "type": "Feature",
  "properties": {
    "addr:full":"Lechenweg 62 Rietz Tirol 6421",
    "addr:housenumber":"62",
    "addr:postcode":"6421",
    "addr:street":"Lechenweg;Tirol",
    "iso:country":"AT",
    "sg:address":"Lechenweg 62",
    "sg:city":"Rietz",
    "sg:orig_category":"Beteiligungen U Finanzierungen",
    "sg:phone":"+43 4352 6264080",
    "sg:postcode":"6421",
    "sg:province":"Tirol",
    "wof:name":"Schrott Erika - W\u00fcstenrot",
    "wof:placetype":"venue"
},
  "geometry": {"coordinates":[11.0220098495,47.2840194702],"type":"Point"}
}