{
  "type": "Feature",
  "properties": {
    "addr:full":"Hallegger Str 152 W\u00f6lfnitz K\u00e4rnten 9061",
    "addr:housenumber":"152",
    "addr:postcode":"9061",
    "addr:street":"Woelfnitz Kaernten",
    "iso:country":"AT",
    "sg:address":"Hallegger Str 152",
    "sg:city":"W\u00f6lfnitz",
    "sg:orig_category":"Pensionen / Privatzimmer",
    "sg:phone":"+43 463 49716",
    "sg:postcode":"9061",
    "sg:province":"K\u00e4rnten",
    "wof:name":"Gut Hallegg G\u00e4stehaus",
    "wof:placetype":"venue"
},
  "geometry": {"coordinates":[14.2418298721,46.6486663818],"type":"Point"}
}