{
  "type": "Feature",
  "properties": {
    "addr:full":"P\u00f6ttschinger Str. 19  Neud\u00f6rfl Burgenland 7201",
    "addr:housenumber":"19",
    "addr:postcode":"neudoerfl;7201",
    "addr:street":"Str.",
    "iso:country":"AT",
    "sg:address":"P\u00f6ttschinger Str. 19 ",
    "sg:city":"Neud\u00f6rfl",
    "sg:classifiers":[
        {
            "category":"Professional",
            "subcategory":"Printing & Photocopies",
            "type":"Services"
        }
    ],
    "sg:phone":"+43 4326 22772340",
    "sg:postcode":"7201",
    "sg:province":"Burgenland",
    "wof:name":"GERALD FRAUENBERGER",
    "wof:placetype":"venue"
},
  "geometry": {"coordinates":[-101.6332702637,46.3577537537],"type":"Point"}
}