{
  "type": "Feature",
  "properties": {
    "addr:full":"Liechtensteinstr 3a G\u00fcnselsdorf Nieder\u00f6sterreich 2525",
    "addr:housenumber":"3a",
    "addr:postcode":"2525",
    "addr:street":"Liechtensteinstr;Niederoesterreich",
    "iso:country":"AT",
    "sg:address":"Liechtensteinstr 3a",
    "sg:city":"G\u00fcnselsdorf",
    "sg:orig_category":"Banken U Sparkassen",
    "sg:phone":"+43 4322 5620273",
    "sg:postcode":"2525",
    "sg:province":"Nieder\u00f6sterreich",
    "wof:name":"Vereinigte Volksbanken Baden-M\u00f6dling-Liesing registrierte GmbH",
    "wof:placetype":"venue"
},
  "geometry": {"coordinates":[16.2546329498,47.9343070984],"type":"Point"}
}