{
  "type": "Feature",
  "properties": {
    "addr:full":"Kiesstr. 14  Marchtrenk Ober\u00f6sterreich 4614",
    "addr:housenumber":"14",
    "addr:postcode":"4614",
    "addr:street":"Kiesstr.",
    "iso:country":"AT",
    "sg:address":"Kiesstr. 14 ",
    "sg:city":"Marchtrenk",
    "sg:classifiers":[
        {
            "category":"Real Estate",
            "subcategory":"Surveying",
            "type":"Services"
        }
    ],
    "sg:phone":"+43 4372 43537960",
    "sg:postcode":"4614",
    "sg:province":"Ober\u00f6sterreich",
    "sg:tags":[
        "equipment",
        "material",
        "good",
        "-",
        "handling"
    ],
    "wof:name":"EURO SHOP BAU GESMBH",
    "wof:placetype":"venue"
},
  "geometry": {"coordinates":[14.1426334381,48.1943397522],"type":"Point"}
}