{
  "type": "Feature",
  "properties": {
    "addr:full":"Seilerg 26 Gmunden Ober\u00f6sterreich 4810",
    "addr:housenumber":"26",
    "addr:postcode":"4810",
    "addr:street":"Seilerg;Oberoesterreich",
    "iso:country":"AT",
    "sg:address":"Seilerg 26",
    "sg:city":"Gmunden",
    "sg:orig_category":"Architekten",
    "sg:phone":"+43 761267438",
    "sg:postcode":"4810",
    "sg:province":"Ober\u00f6sterreich",
    "wof:name":"Eder Harald Arch Dipl-Ing",
    "wof:placetype":"venue"
},
  "geometry": {"coordinates":[13.7986011505,47.9215621948],"type":"Point"}
}