{
  "type": "Feature",
  "properties": {
    "addr:full":"Kirchenplatz 7 Wien Wien 1230",
    "addr:housenumber":"7",
    "addr:postcode":"1230",
    "addr:street":"Kirchenplatz",
    "iso:country":"AT",
    "sg:address":"Kirchenplatz 7",
    "sg:city":"Wien",
    "sg:classifiers":[
        {
            "category":"Manufacturing",
            "subcategory":"Glass & Minerals",
            "type":"Manufacturing & Wholesale Goods"
        }
    ],
    "sg:phone":"+43 1 8659428",
    "sg:postcode":"1230",
    "sg:province":"Wien",
    "sg:tags":[
        "processing",
        "mirror"
    ],
    "wof:name":"Krammer-Verglasungen Ges.m.b.H.",
    "wof:placetype":"venue"
},
  "geometry": {"coordinates":[16.2940368652,48.1475257874],"type":"Point"}
}