{
  "type": "Feature",
  "properties": {
    "addr:full":"Thannstr 20a St. Florian Ober\u00f6sterreich 4490",
    "addr:housenumber":"20a",
    "addr:postcode":"4490",
    "addr:street":"Thannstr",
    "iso:country":"AT",
    "sg:address":"Thannstr 20a",
    "sg:city":"St. Florian",
    "sg:orig_category":"Fotografen",
    "sg:phone":"+43 7224 47770",
    "sg:postcode":"4490",
    "sg:province":"Ober\u00f6sterreich",
    "wof:name":"Fotostudio Lang Manfred GmbH",
    "wof:placetype":"venue"
},
  "geometry": {"coordinates":[14.3799533844,48.2007522583],"type":"Point"}
}