{
  "type": "Feature",
  "properties": {
    "addr:full":"Industriezone 48 Imst Tirol 6460",
    "addr:housenumber":"48",
    "addr:postcode":"6460",
    "addr:street":"Industriezone;Tirol",
    "iso:country":"AT",
    "sg:address":"Industriezone 48",
    "sg:city":"Imst",
    "sg:orig_category":"Elektroinstallationsunternehmen",
    "sg:phone":"+43 5412 62333",
    "sg:postcode":"6460",
    "sg:province":"Tirol",
    "wof:name":"EKG Elektro Krismer Gerhard",
    "wof:placetype":"venue"
},
  "geometry": {"coordinates":[10.7284212112,47.2182159424],"type":"Point"}
}