{
  "type": "Feature",
  "properties": {
    "addr:full":"Heinestr 1/5 Wien Wien 1020",
    "addr:housenumber":"1 / 5",
    "addr:postcode":"1020",
    "addr:street":"Heinestr",
    "iso:country":"AT",
    "sg:address":"Heinestr 1/5",
    "sg:city":"Wien",
    "sg:orig_category":"Telefonmarketing",
    "sg:phone":"+43 1 2145108",
    "sg:postcode":"1020",
    "sg:province":"Wien",
    "wof:name":"AUT Call Center",
    "wof:placetype":"venue"
},
  "geometry": {"coordinates":[16.3827724457,48.2223510742],"type":"Point"}
}