{
  "type": "Feature",
  "properties": {
    "addr:full":"Engelsbergg 4 Wien Wien 1030",
    "addr:housenumber":"4",
    "addr:postcode":"1030",
    "addr:street":"Engelsbergg",
    "iso:country":"AT",
    "sg:address":"Engelsbergg 4",
    "sg:city":"Wien",
    "sg:orig_category":"Physiotherapie",
    "sg:phone":"+43 4317 136979",
    "sg:postcode":"1030",
    "sg:province":"Wien",
    "wof:name":"Stockenhuber Felix Univ Prof Dr",
    "wof:placetype":"venue"
},
  "geometry": {"coordinates":[16.3879470825,48.1985740662],"type":"Point"}
}