{
  "type": "Feature",
  "properties": {
    "iso:country":"AT",
    "sg:address":"Plan\u00f6tzenhofstr 10",
    "sg:city":"Innsbruck",
    "sg:orig_category":"Architekten",
    "sg:phone":"+43 512 284522",
    "sg:postcode":"6020",
    "sg:province":"Tirol",
    "wof:name":"Fritz Norbert Arch Mag",
    "wof:placetype":"venue"
},
  "geometry": {"coordinates":[11.3700008392,47.270450592],"type":"Point"}
}