{
  "type": "Feature",
  "properties": {
    "iso:country":"AT",
    "sg:address":"St. Veiter Str 118",
    "sg:city":"St. Veit",
    "sg:orig_category":"Rauchfangsanierungen U -Ausschleifungen",
    "sg:phone":"+43 4331 6697973",
    "sg:postcode":"8046",
    "sg:province":"Steiermark",
    "wof:name":"Biber-Bau Hoch-Tief u KaminbaugesmbH",
    "wof:placetype":"venue"
},
  "geometry": {"coordinates":[15.4119844437,47.1186981201],"type":"Point"}
}