{
  "type": "Feature",
  "properties": {
    "addr:full":"Torkelg\u00e4ssele 2 Rankweil Vorarlberg 6830",
    "addr:housenumber":"2",
    "addr:postcode":"6830",
    "addr:street":"Torkelgaessele",
    "iso:country":"AT",
    "sg:address":"Torkelg\u00e4ssele 2",
    "sg:city":"Rankweil",
    "sg:orig_category":"Autospenglereien",
    "sg:phone":"+43 5522 47862",
    "sg:postcode":"6830",
    "sg:province":"Vorarlberg",
    "wof:name":"Schratter Norbert",
    "wof:placetype":"venue"
},
  "geometry": {"coordinates":[9.6407709122,47.2686576843],"type":"Point"}
}