{
  "type": "Feature",
  "properties": {
    "addr:full":"Feuerbachgasse 30c/14  Graz Steiermark 8020",
    "addr:housenumber":"30c / 14",
    "addr:postcode":"8020",
    "addr:street":"Feuerbachgasse",
    "iso:country":"AT",
    "sg:address":"Feuerbachgasse 30c/14 ",
    "sg:city":"Graz",
    "sg:classifiers":[
        {
            "category":"Professional",
            "subcategory":"Engineering",
            "type":"Services"
        }
    ],
    "sg:phone":"+43 316 8734970",
    "sg:postcode":"8020",
    "sg:province":"Steiermark",
    "sg:tags":[
        "development",
        "microsystems",
        "mst",
        "technology",
        "manufacturing"
    ],
    "sg:website":"www.microinnova.com",
    "wof:name":"Microinnova Dr. Kirschneck KEG",
    "wof:placetype":"venue"
},
  "geometry": {"coordinates":[15.4317312241,47.0683288574],"type":"Point"}
}