{
  "type": "Feature",
  "properties": {
    "addr:full":"Oberbergham 8 Gaspoltshofen Ober\u00f6sterreich 4673",
    "addr:housenumber":"8",
    "addr:postcode":"4673",
    "addr:street":"Oberbergham",
    "iso:country":"AT",
    "sg:address":"Oberbergham 8",
    "sg:city":"Gaspoltshofen",
    "sg:orig_category":"Betriebseinrichtungen",
    "sg:phone":"+43 7735 20269",
    "sg:postcode":"4673",
    "sg:province":"Ober\u00f6sterreich",
    "wof:name":"Mirwald Reiner",
    "wof:placetype":"venue"
},
  "geometry": {"coordinates":[13.7462205887,48.1437759399],"type":"Point"}
}