{
  "type": "Feature",
  "properties": {
    "addr:full":"Industriestr 2b Freistadt Ober\u00f6sterreich 4240",
    "addr:housenumber":"2b",
    "addr:postcode":"4240",
    "addr:street":"Industriestr",
    "iso:country":"AT",
    "sg:address":"Industriestr 2b",
    "sg:city":"Freistadt",
    "sg:orig_category":"Bekleidung / Einzelhandel",
    "sg:phone":"+43 4379 4272670",
    "sg:postcode":"4240",
    "sg:province":"Ober\u00f6sterreich",
    "wof:name":"C & A Mode GesmbH & Co KG - C & A Mode FMZ",
    "wof:placetype":"venue"
},
  "geometry": {"coordinates":[14.5021314621,48.4971580505],"type":"Point"}
}