{
  "type": "Feature",
  "properties": {
    "addr:full":"Pichl Ober\u00f6sterreich 4632",
    "addr:postcode":"4632",
    "iso:country":"AT",
    "sg:city":"Pichl",
    "sg:orig_category":"Feuerwehren",
    "sg:phone":"+43 7247 6979",
    "sg:postcode":"4632",
    "sg:province":"Ober\u00f6sterreich",
    "wof:name":"Freiwillige Feuerwehr Geisensheim",
    "wof:placetype":"venue"
},
  "geometry": {"coordinates":[13.9220018387,48.1965713501],"type":"Point"}
}