{
  "type": "Feature",
  "properties": {
    "addr:full":"Sch\u00f6pfstr 5 Innsbruck Tirol 6020",
    "addr:housenumber":"5",
    "addr:postcode":"6020",
    "addr:street":"Schoepfstr;Tirol",
    "iso:country":"AT",
    "sg:address":"Sch\u00f6pfstr 5",
    "sg:city":"Innsbruck",
    "sg:orig_category":"Beratungsstellen",
    "sg:phone":"+43 4351 259030",
    "sg:postcode":"6020",
    "sg:province":"Tirol",
    "wof:name":"Euro Biz + Job-Center International - EURES",
    "wof:placetype":"venue"
},
  "geometry": {"coordinates":[11.3930826187,47.2593727112],"type":"Point"}
}