{
  "type": "Feature",
  "properties": {
    "iso:country":"AT",
    "sg:address":"Lindacher Str 21",
    "sg:city":"Vorchdorf",
    "sg:orig_category":"Werbeagenturen",
    "sg:phone":"+43 761421236",
    "sg:postcode":"4655",
    "sg:province":"Ober\u00f6sterreich",
    "wof:name":"Rauch Armin",
    "wof:placetype":"venue"
},
  "geometry": {"coordinates":[13.9149360657,48.0037155151],"type":"Point"}
}