{
  "type": "Feature",
  "properties": {
    "addr:full":"Landstr 17-25 Linz Ober\u00f6sterreich 4020",
    "addr:postcode":"17-25;4020",
    "addr:street":"Landstr;Oberoesterreich",
    "iso:country":"AT",
    "sg:address":"Landstr 17-25",
    "sg:city":"Linz",
    "sg:orig_category":"Friseure U Frisiersalons",
    "sg:phone":"+43 4373 2779997",
    "sg:postcode":"4020",
    "sg:province":"Ober\u00f6sterreich",
    "wof:name":"LOOK Franchise Haar Mode Service GmbH",
    "wof:placetype":"venue"
},
  "geometry": {"coordinates":[14.2893562317,48.3029212952],"type":"Point"}
}