{
  "type": "Feature",
  "properties": {
    "addr:full":"Nr 8 Kitzb\u00fchel Tirol 6370",
    "addr:postcode":"6370",
    "addr:street":"Nr;Kitzbuehel Tirol",
    "iso:country":"AT",
    "sg:address":"Nr 8",
    "sg:city":"Kitzb\u00fchel",
    "sg:classifiers":[
        {
            "category":"Restaurant",
            "type":"Food & Drink"
        }
    ],
    "sg:phone":"+43 5356 65295",
    "sg:postcode":"6370",
    "sg:province":"Tirol",
    "wof:name":"Restaurant Dorfstube",
    "wof:placetype":"venue"
},
  "geometry": {"coordinates":[106.0698394775,30.7620105743],"type":"Point"}
}