{
  "type": "Feature",
  "properties": {
    "addr:full":"Neusiedler Str 18 Purbach am Neusiedler See Burgenland 7083",
    "addr:housenumber":"18",
    "addr:postcode":"7083",
    "addr:street":"Str",
    "iso:country":"AT",
    "sg:address":"Neusiedler Str 18",
    "sg:city":"Purbach am Neusiedler See",
    "sg:orig_category":"Tischlereien",
    "sg:phone":"+43 4326 835124",
    "sg:postcode":"7083",
    "sg:province":"Burgenland",
    "wof:name":"Fr\u00f6ch Peter",
    "wof:placetype":"venue"
},
  "geometry": {"coordinates":[16.6978187561,47.9165229797],"type":"Point"}
}