{
  "type": "Feature",
  "properties": {
    "addr:full":"Penzinger Str 11-13 Wien Wien 1140",
    "addr:postcode":"11-13;1140",
    "addr:street":"Str",
    "iso:country":"AT",
    "sg:address":"Penzinger Str 11-13",
    "sg:city":"Wien",
    "sg:orig_category":"Botschaften",
    "sg:phone":"+43 1 8943741",
    "sg:postcode":"1140",
    "sg:province":"Wien",
    "wof:name":"Botschaft der Tschechischen Republik",
    "wof:placetype":"venue"
},
  "geometry": {"coordinates":[16.3126907349,48.18957901],"type":"Point"}
}