{
  "type": "Feature",
  "properties": {
    "addr:full":"Meldemannstr 12-14 Wien Wien 1200",
    "addr:postcode":"12-14;1200",
    "iso:country":"AT",
    "sg:address":"Meldemannstr 12-14",
    "sg:city":"Wien",
    "sg:orig_category":"Beratungsstellen",
    "sg:phone":"+43 1 3313420310",
    "sg:postcode":"1200",
    "sg:province":"Wien",
    "wof:name":"MAG ELF - Regionalstellen Rechtsf\u00fcrsorge f d 20 Bez",
    "wof:placetype":"venue"
},
  "geometry": {"coordinates":[16.3765392303,48.2408676147],"type":"Point"}
}