{
  "type": "Feature",
  "properties": {
    "addr:full":"Grund\u00e4ckerg 38 Wien Wien 1100",
    "addr:housenumber":"38",
    "addr:postcode":"1100",
    "addr:street":"Grundaeckerg",
    "iso:country":"AT",
    "sg:address":"Grund\u00e4ckerg 38",
    "sg:city":"Wien",
    "sg:orig_category":"Restaurants: Chinesisch",
    "sg:phone":"+43 1 6897617",
    "sg:postcode":"1100",
    "sg:province":"Wien",
    "wof:name":"Asia Restaurant Oberlaa",
    "wof:placetype":"venue"
},
  "geometry": {"coordinates":[16.392906189,48.1397819519],"type":"Point"}
}