{
  "type": "Feature",
  "properties": {
    "iso:country":"AT",
    "sg:address":"Nr 6",
    "sg:city":"Riedau",
    "sg:orig_category":"Banken U Sparkassen",
    "sg:phone":"+43 4377 648363",
    "sg:postcode":"4752",
    "sg:province":"Ober\u00f6sterreich",
    "wof:name":"Raiffeisenbank Raab regGenmbH",
    "wof:placetype":"venue"
},
  "geometry": {"coordinates":[13.6335010529,48.3028488159],"type":"Point"}
}