{
  "type": "Feature",
  "properties": {
    "addr:full":"Nonntaler Hauptstr 47 Salzburg Salzburg 5020",
    "addr:housenumber":"47",
    "addr:postcode":"5020",
    "addr:street":"Nonntaler Hauptstr;Salzburg",
    "iso:country":"AT",
    "sg:address":"Nonntaler Hauptstr 47",
    "sg:city":"Salzburg",
    "sg:classifiers":[
        {
            "category":"Restaurant",
            "type":"Food & Drink"
        }
    ],
    "sg:phone":"+43 4366 2834760",
    "sg:postcode":"5020",
    "sg:province":"Salzburg",
    "wof:name":"Ristorante - Pizzeria - da Giacomo",
    "wof:placetype":"venue"
},
  "geometry": {"coordinates":[13.0506372452,47.7893180847],"type":"Point"}
}