{
  "type": "Feature",
  "properties": {
    "iso:country":"AT",
    "sg:address":"Heiligenkreuzer Str 182",
    "sg:city":"Sittendorf",
    "sg:orig_category":"Holzhandel",
    "sg:phone":"+43 2237 8481",
    "sg:postcode":"2393",
    "sg:province":"Nieder\u00f6sterreich",
    "wof:name":"Tromayer Heinrich",
    "wof:placetype":"venue"
},
  "geometry": {"coordinates":[16.1902313232,48.074596405],"type":"Point"}
}