{
  "type": "Feature",
  "properties": {
    "addr:full":"Amerlingstr 9 Wien Wien 1060",
    "addr:housenumber":"9",
    "addr:postcode":"1060",
    "addr:street":"Amerlingstr",
    "iso:country":"AT",
    "sg:address":"Amerlingstr 9",
    "sg:city":"Wien",
    "sg:orig_category":"Brautkleider U -Artikel",
    "sg:phone":"+43 4315 816967",
    "sg:postcode":"1060",
    "sg:province":"Wien",
    "wof:name":"Brautmoden Belinda",
    "wof:placetype":"venue"
},
  "geometry": {"coordinates":[16.3509178162,48.1970176697],"type":"Point"}
}