{
  "type": "Feature",
  "properties": {
    "addr:full":"Hauptpl 28 Tulln an der Donau Nieder\u00f6sterreich 3430",
    "addr:housenumber":"28",
    "addr:postcode":"3430",
    "addr:street":"Hauptpl",
    "iso:country":"AT",
    "sg:address":"Hauptpl 28",
    "sg:city":"Tulln an der Donau",
    "sg:orig_category":"Finanz- U Wirtschaftsberatung",
    "sg:phone":"+43 4366 41005050",
    "sg:postcode":"3430",
    "sg:province":"Nieder\u00f6sterreich",
    "wof:name":"Eurosystem Finanzplanung",
    "wof:placetype":"venue"
},
  "geometry": {"coordinates":[16.0516815186,48.331401825],"type":"Point"}
}