{
  "type": "Feature",
  "properties": {
    "addr:full":"Wiedeng 5 Zistersdorf Nieder\u00f6sterreich 2225",
    "addr:housenumber":"5",
    "addr:postcode":"2225",
    "addr:street":"Wiedeng;Niederoesterreich",
    "iso:country":"AT",
    "sg:address":"Wiedeng 5",
    "sg:city":"Zistersdorf",
    "sg:orig_category":"Installationsunternehmen",
    "sg:phone":"+43 2532 24540",
    "sg:postcode":"2225",
    "sg:province":"Nieder\u00f6sterreich",
    "wof:name":"Geyder Manfred Ing",
    "wof:placetype":"venue"
},
  "geometry": {"coordinates":[16.7662963867,48.5451278687],"type":"Point"}
}