{
  "type": "Feature",
  "properties": {
    "addr:full":"Hans-Kloepfer-Str 4 Mureck Steiermark 8480",
    "addr:housenumber":"4",
    "addr:postcode":"8480",
    "addr:street":"Hans-Kloepfer-Str",
    "iso:country":"AT",
    "sg:address":"Hans-Kloepfer-Str 4",
    "sg:city":"Mureck",
    "sg:orig_category":"Bestattungsunternehmen",
    "sg:phone":"+43 664 3000011",
    "sg:postcode":"8480",
    "sg:province":"Steiermark",
    "wof:name":"Thiersch\u00e4dl Johann GesmbH",
    "wof:placetype":"venue"
},
  "geometry": {"coordinates":[15.7788009644,46.7085800171],"type":"Point"}
}