{
  "type": "Feature",
  "properties": {
    "addr:full":"Waidhofner Str 2 Amstetten Nieder\u00f6sterreich 3300",
    "addr:housenumber":"2",
    "addr:postcode":"3300",
    "addr:street":"Str;Niederoesterreich",
    "iso:country":"AT",
    "sg:address":"Waidhofner Str 2",
    "sg:city":"Amstetten",
    "sg:orig_category":"Feuerwehren",
    "sg:phone":"+43 7472 611800",
    "sg:postcode":"3300",
    "sg:province":"Nieder\u00f6sterreich",
    "wof:name":"Feuerwehr Greinsfurth",
    "wof:placetype":"venue"
},
  "geometry": {"coordinates":[14.845416069,48.1099586487],"type":"Point"}
}