{
  "type": "Feature",
  "properties": {
    "iso:country":"AT",
    "sg:address":"Innsbrucker Bundesstr 95",
    "sg:city":"Salzburg",
    "sg:orig_category":"Fluggesellschaften",
    "sg:phone":"+43 4366 28545110",
    "sg:postcode":"5020",
    "sg:province":"Salzburg",
    "wof:name":"Austrian Airlines Group",
    "wof:placetype":"venue"
},
  "geometry": {"coordinates":[12.9956769943,47.79347229],"type":"Point"}
}