{
  "type": "Feature",
  "properties": {
    "iso:country":"AT",
    "sg:address":"Mayrwiesstr. 8 ",
    "sg:city":"Hallwang",
    "sg:classifiers":[
        {
            "category":"Manufacturing",
            "subcategory":"Metals",
            "type":"Manufacturing & Wholesale Goods"
        }
    ],
    "sg:phone":"+43 4366 26648300",
    "sg:postcode":"5300",
    "sg:province":"Salzburg",
    "sg:tags":[
        "metallurgy",
        "metalworking"
    ],
    "wof:name":"GU BAUBESCHL\u00c4GE AUSTRIA GMBH",
    "wof:placetype":"venue"
},
  "geometry": {"coordinates":[13.0817546844,47.8326148987],"type":"Point"}
}