{
  "type": "Feature",
  "properties": {
    "addr:full":"Gro\u00dfe Sperlgasse 2 Wien Wien 1020",
    "addr:housenumber":"2",
    "addr:postcode":"1020",
    "addr:street":"Sperlgasse",
    "iso:country":"AT",
    "sg:address":"Gro\u00dfe Sperlgasse 2",
    "sg:city":"Wien",
    "sg:orig_category":"Illumination Design, Planning, And Architecture",
    "sg:phone":"+43 650 9953590",
    "sg:postcode":"1020",
    "sg:province":"Wien",
    "sg:website":"licht2000.com",
    "wof:name":"LICHT 2000, Peter Lumpe",
    "wof:placetype":"venue"
},
  "geometry": {"coordinates":[16.3783855438,48.216178894],"type":"Point"}
}