{
  "type": "Feature",
  "properties": {
    "addr:full":"Zeppelinstr 2 Linz Ober\u00f6sterreich 4030",
    "addr:housenumber":"2",
    "addr:postcode":"4030",
    "addr:street":"Zeppelinstr",
    "iso:country":"AT",
    "sg:address":"Zeppelinstr 2",
    "sg:city":"Linz",
    "sg:orig_category":"Bestattungsunternehmen",
    "sg:phone":"+43 732 34006711",
    "sg:postcode":"4030",
    "sg:province":"Ober\u00f6sterreich",
    "wof:name":"Bestattung Kleinm\u00fcnchen",
    "wof:placetype":"venue"
},
  "geometry": {"coordinates":[14.3215913773,48.2565689087],"type":"Point"}
}