{
  "type": "Feature",
  "properties": {
    "addr:full":"Dr.-Reinhard-Machold-Str 1 St. Lorenzen im M\u00fcrztal Steiermark 8642",
    "addr:housenumber":"1",
    "addr:postcode":"8642",
    "addr:street":"Dr.-Reinhard-Machold-Str",
    "iso:country":"AT",
    "sg:address":"Dr.-Reinhard-Machold-Str 1",
    "sg:city":"St. Lorenzen im M\u00fcrztal",
    "sg:orig_category":"Lebensmittel / Einzelhandel",
    "sg:phone":"+43 4338 6234547",
    "sg:postcode":"8642",
    "sg:province":"Steiermark",
    "wof:name":"Hofer KG",
    "wof:placetype":"venue"
},
  "geometry": {"coordinates":[15.3459949493,47.4691505432],"type":"Point"}
}