{
  "type": "Feature",
  "properties": {
    "addr:full":"Barthold-St\u00fcrgkh-Str 7-9 Bad Radkersburg Steiermark 8490",
    "addr:housenumber":"7-9",
    "addr:postcode":"8490",
    "addr:street":"Barthold-Stuergkh-Str",
    "iso:country":"AT",
    "sg:address":"Barthold-St\u00fcrgkh-Str 7-9",
    "sg:city":"Bad Radkersburg",
    "sg:orig_category":"Berufsschulen",
    "sg:phone":"+43 3476 25410",
    "sg:postcode":"8490",
    "sg:province":"Steiermark",
    "wof:name":"Landesberufsschule",
    "wof:placetype":"venue"
},
  "geometry": {"coordinates":[15.9888820648,46.6908340454],"type":"Point"}
}