{
  "type": "Feature",
  "properties": {
    "addr:full":"Nr 23 Annaberg Nieder\u00f6sterreich 3222",
    "addr:postcode":"3222",
    "addr:street":"Nr;Annaberg",
    "iso:country":"AT",
    "sg:address":"Nr 23",
    "sg:city":"Annaberg",
    "sg:orig_category":"Bergbahnen",
    "sg:phone":"+43 4327 288477",
    "sg:postcode":"3222",
    "sg:province":"Nieder\u00f6sterreich",
    "wof:name":"Annaberger Liftbetriebs-GesmbH",
    "wof:placetype":"venue"
},
  "geometry": {"coordinates":[15.3757600784,47.8717384338],"type":"Point"}
}