{
  "type": "Feature",
  "properties": {
    "addr:full":"Grazer Str 28 Wolfsberg K\u00e4rnten 9400",
    "addr:housenumber":"28;kaernten",
    "addr:postcode":"9400",
    "addr:street":"Str",
    "iso:country":"AT",
    "sg:address":"Grazer Str 28",
    "sg:city":"Wolfsberg",
    "sg:orig_category":"Schlossereien",
    "sg:phone":"+43 4352 37480",
    "sg:postcode":"9400",
    "sg:province":"K\u00e4rnten",
    "wof:name":"Kollmann Franz",
    "wof:placetype":"venue"
},
  "geometry": {"coordinates":[14.8433551788,46.8449668884],"type":"Point"}
}