{
  "type": "Feature",
  "properties": {
    "iso:country":"AT",
    "sg:address":"Wiener Strasse 52",
    "sg:city":"Wiener Neustadt",
    "sg:classifiers":[
        {
            "category":"Manufacturing",
            "subcategory":"Jewelry",
            "type":"Manufacturing & Wholesale Goods"
        }
    ],
    "sg:phone":"+43 2622 86464",
    "sg:postcode":"2700",
    "sg:province":"Nieder\u00f6sterreich",
    "sg:tags":[
        "bangle",
        "bracelet"
    ],
    "sg:website":"kundkedelsteine.at",
    "wof:name":"K.&K. Edelstein-GesmbH",
    "wof:placetype":"venue"
},
  "geometry": {"coordinates":[16.2449913025,47.816783905],"type":"Point"}
}