{
  "type": "Feature",
  "properties": {
    "addr:full":"Hochtennstr 48 Zell am See Salzburg 5700",
    "addr:housenumber":"48",
    "addr:postcode":"5700",
    "addr:street":"Hochtennstr;Salzburg",
    "iso:country":"AT",
    "sg:address":"Hochtennstr 48",
    "sg:city":"Zell am See",
    "sg:orig_category":"\u00c3\u201erzte / F Allgemeinmedizin",
    "sg:phone":"+43 4365 03385111",
    "sg:postcode":"5700",
    "sg:province":"Salzburg",
    "wof:name":"Cerny-Kleber Adelheid Dr med",
    "wof:placetype":"venue"
},
  "geometry": {"coordinates":[12.7996683121,47.2968215942],"type":"Point"}
}