{
  "type": "Feature",
  "properties": {
    "addr:full":"Rosenegg 59 Fieberbrunn Tirol 6391",
    "addr:housenumber":"59",
    "addr:postcode":"6391",
    "addr:street":"Rosenegg;Tirol",
    "iso:country":"AT",
    "sg:address":"Rosenegg 59",
    "sg:city":"Fieberbrunn",
    "sg:orig_category":"Lebensmittel / Einzelhandel",
    "sg:phone":"+43 5354 56204",
    "sg:postcode":"6391",
    "sg:province":"Tirol",
    "wof:name":"Kaufhaus Schwaiger SPAR-Markt",
    "wof:placetype":"venue"
},
  "geometry": {"coordinates":[12.5311937332,47.4870223999],"type":"Point"}
}