{
  "type": "Feature",
  "properties": {
    "iso:country":"AT",
    "sg:address":"Hauptpl 16",
    "sg:city":"Eibiswald",
    "sg:orig_category":"Banken U Sparkassen",
    "sg:phone":"+43 4334 66422060",
    "sg:postcode":"8552",
    "sg:province":"Steiermark",
    "wof:name":"Steierm\u00e4rkische Bank u Sparkassen AG",
    "wof:placetype":"venue"
},
  "geometry": {"coordinates":[15.2274599075,46.6824150085],"type":"Point"}
}