{
  "type": "Feature",
  "properties": {
    "iso:country":"AT",
    "sg:address":"Ybbsitzer Str 68",
    "sg:city":"Waidhofen an der Ybbs",
    "sg:orig_category":"Maschinenvermietung U -Verleih",
    "sg:phone":"+43 4374 4254825",
    "sg:postcode":"3340",
    "sg:province":"Nieder\u00f6sterreich",
    "wof:name":"Maschinen u Betriebshilfering Ybbstal",
    "wof:placetype":"venue"
},
  "geometry": {"coordinates":[14.7818260193,47.9570426941],"type":"Point"}
}