{
  "type": "Feature",
  "properties": {
    "addr:full":"Trientlg 68 Innsbruck Tirol 6020",
    "addr:housenumber":"68",
    "addr:postcode":"6020",
    "addr:street":"Trientlg;Tirol",
    "iso:country":"AT",
    "sg:address":"Trientlg 68",
    "sg:city":"Innsbruck",
    "sg:orig_category":"Tischlereien",
    "sg:phone":"+43 512 3413900",
    "sg:postcode":"6020",
    "sg:province":"Tirol",
    "sg:website":"www.sumper.at",
    "wof:name":"Bau- und M\u00f6beltischlerei Sumper",
    "wof:placetype":"venue"
},
  "geometry": {"coordinates":[11.4399738312,47.2669830322],"type":"Point"}
}