{
  "type": "Feature",
  "properties": {
    "addr:full":"Tulpenweg 11 Lieserbr\u00fccke K\u00e4rnten 9851",
    "addr:housenumber":"11",
    "addr:postcode":"9851",
    "addr:street":"Tulpenweg;Kaernten",
    "iso:country":"AT",
    "sg:address":"Tulpenweg 11",
    "sg:city":"Lieserbr\u00fccke",
    "sg:orig_category":"Montagen U Montagetechnik",
    "sg:phone":"+43 4347 6244149",
    "sg:postcode":"9851",
    "sg:province":"K\u00e4rnten",
    "wof:name":"Brugger Siegfried",
    "wof:placetype":"venue"
},
  "geometry": {"coordinates":[13.482583046,46.8351669312],"type":"Point"}
}