{
  "type": "Feature",
  "properties": {
    "iso:country":"AT",
    "sg:city":"St. Georgen im Attergau",
    "sg:orig_category":"Feuerwehren",
    "sg:phone":"+43 76676339",
    "sg:postcode":"4880",
    "sg:province":"Ober\u00f6sterreich",
    "wof:name":"Freiwillige Feuerwehr Hipping",
    "wof:placetype":"venue"
},
  "geometry": {"coordinates":[13.4666595459,47.9512176514],"type":"Point"}
}