{
  "type": "Feature",
  "properties": {
    "addr:full":"Industriestr 21 Himberg Nieder\u00f6sterreich 2325",
    "addr:housenumber":"21",
    "addr:postcode":"2325",
    "addr:street":"Industriestr",
    "iso:country":"AT",
    "sg:address":"Industriestr 21",
    "sg:city":"Himberg",
    "sg:orig_category":"Chemikalien",
    "sg:phone":"+43 2235 862660",
    "sg:postcode":"2325",
    "sg:province":"Nieder\u00f6sterreich",
    "wof:name":"B\u00f6hm Franz Dr Ing GesmbH",
    "wof:placetype":"venue"
},
  "geometry": {"coordinates":[16.4492797852,48.0781288147],"type":"Point"}
}