{
  "type": "Feature",
  "properties": {
    "iso:country":"AT",
    "sg:address":"Nr 77",
    "sg:city":"Waidhofen an der Ybbs",
    "sg:orig_category":"Fenster",
    "sg:phone":"+43 4374 42524440",
    "sg:postcode":"3340",
    "sg:province":"Nieder\u00f6sterreich",
    "wof:name":"KLINGER - WIMHOFER GmbH",
    "wof:placetype":"venue"
},
  "geometry": {"coordinates":[14.7743349075,47.9616470337],"type":"Point"}
}