{
  "type": "Feature",
  "properties": {
    "addr:full":"Lanser Str 29 Aldrans Tirol 6071",
    "addr:postcode":"6071",
    "addr:street":"Str 29;Tirol",
    "iso:country":"AT",
    "sg:address":"Lanser Str 29",
    "sg:city":"Aldrans",
    "sg:orig_category":"Psychotherapie",
    "sg:phone":"+43 512 392751",
    "sg:postcode":"6071",
    "sg:province":"Tirol",
    "wof:name":"Steixner Andr\u00e4 Dr",
    "wof:placetype":"venue"
},
  "geometry": {"coordinates":[11.4355430603,47.2441101074],"type":"Point"}
}