{
  "type": "Feature",
  "properties": {
    "addr:full":"Hauptstr 46 Ravelsbach Nieder\u00f6sterreich 3720",
    "addr:housenumber":"46",
    "addr:postcode":"3720",
    "addr:street":"Hauptstr",
    "iso:country":"AT",
    "sg:address":"Hauptstr 46",
    "sg:city":"Ravelsbach",
    "sg:orig_category":"Zimmereien",
    "sg:phone":"+43 2958 82451",
    "sg:postcode":"3720",
    "sg:province":"Nieder\u00f6sterreich",
    "wof:name":"Bahnholzer Leopold",
    "wof:placetype":"venue"
},
  "geometry": {"coordinates":[15.8433189392,48.5502815247],"type":"Point"}
}