{
  "type": "Feature",
  "properties": {
    "addr:full":"Nr 190 Anger Steiermark 8184",
    "addr:postcode":"8184",
    "addr:street":"Nr 190",
    "iso:country":"AT",
    "sg:address":"Nr 190",
    "sg:city":"Anger",
    "sg:orig_category":"Landwirtschaftliche Produkte",
    "sg:phone":"+43 3175 22140",
    "sg:postcode":"8184",
    "sg:province":"Steiermark",
    "wof:name":"Stutenmilchgest\u00fct T\u00f6chterlehof Derler KEG",
    "wof:placetype":"venue"
},
  "geometry": {"coordinates":[15.7057800293,47.2626419067],"type":"Point"}
}