{
  "type": "Feature",
  "properties": {
    "iso:country":"AT",
    "sg:address":"Graben 19",
    "sg:city":"Wien",
    "sg:orig_category":"Beteiligungen U Finanzierungen",
    "sg:phone":"+43 1 53219600",
    "sg:postcode":"1010",
    "sg:province":"Wien",
    "wof:name":"Drei i Austria GmbH",
    "wof:placetype":"venue"
},
  "geometry": {"coordinates":[16.3684940338,48.2094993591],"type":"Point"}
}