{
  "type": "Feature",
  "properties": {
    "addr:full":"Lindeng 16 Linz Ober\u00f6sterreich 4040",
    "addr:housenumber":"16",
    "addr:postcode":"4040",
    "addr:street":"Lindeng",
    "iso:country":"AT",
    "sg:address":"Lindeng 16",
    "sg:city":"Linz",
    "sg:orig_category":"Blumeneinzelhandel",
    "sg:phone":"+43 732 730238",
    "sg:postcode":"4040",
    "sg:province":"Ober\u00f6sterreich",
    "wof:name":"Blumen - Schatz",
    "wof:placetype":"venue"
},
  "geometry": {"coordinates":[14.2876853943,48.3234710693],"type":"Point"}
}