{
  "type": "Feature",
  "properties": {
    "addr:full":"Achenstr 12 Mondsee Ober\u00f6sterreich 5310",
    "addr:housenumber":"12",
    "addr:postcode":"5310",
    "addr:street":"Achenstr;Oberoesterreich",
    "iso:country":"AT",
    "sg:address":"Achenstr 12",
    "sg:city":"Mondsee",
    "sg:orig_category":"Massagen",
    "sg:phone":"+43 4362 325365",
    "sg:postcode":"5310",
    "sg:province":"Ober\u00f6sterreich",
    "wof:name":"Macheiner Andrea",
    "wof:placetype":"venue"
},
  "geometry": {"coordinates":[13.3339939117,47.8291358948],"type":"Point"}
}