{
  "type": "Feature",
  "properties": {
    "iso:country":"AT",
    "sg:address":"Gewerbepark 1",
    "sg:city":"Hall in Tirol",
    "sg:classifiers":[
        {
            "category":"Home & Garden",
            "subcategory":"Building Materials",
            "type":"Retail Goods"
        }
    ],
    "sg:phone":"+43 5223 42776",
    "sg:postcode":"6060",
    "sg:province":"Tirol",
    "sg:tags":[
        "banister"
    ],
    "wof:name":"Ing. G\u00fcnther Wurzinger Ges.m.b.H.",
    "wof:placetype":"venue"
},
  "geometry": {"coordinates":[11.50440979,47.2799415588],"type":"Point"}
}