{
  "type": "Feature",
  "properties": {
    "iso:country":"AT",
    "sg:address":"Nr 237",
    "sg:city":"Kirchbach in Steiermark",
    "sg:orig_category":"Lebensmittel / Einzelhandel",
    "sg:phone":"+43 3116 27698",
    "sg:postcode":"8082",
    "sg:province":"Steiermark",
    "wof:name":"Zielpunkt Warenhandel GmbH & Co KG",
    "wof:placetype":"venue"
},
  "geometry": {"coordinates":[15.6588878632,46.937297821],"type":"Point"}
}