{
  "type": "Feature",
  "properties": {
    "addr:full":"Engerthstr 200 Wien Wien 1020",
    "addr:housenumber":"200",
    "addr:postcode":"1020",
    "iso:country":"AT",
    "sg:address":"Engerthstr 200",
    "sg:city":"Wien",
    "sg:orig_category":"Waren Aller Art",
    "sg:phone":"+43 1 7281674",
    "sg:postcode":"1020",
    "sg:province":"Wien",
    "wof:name":"Ritter Andrzej",
    "wof:placetype":"venue"
},
  "geometry": {"coordinates":[16.4052219391,48.2227478027],"type":"Point"}
}