{
  "type": "Feature",
  "properties": {
    "addr:full":"Museumstr 5 Innsbruck Tirol 6020",
    "addr:housenumber":"5",
    "addr:postcode":"6020",
    "addr:street":"Museumstr;Tirol",
    "iso:country":"AT",
    "sg:address":"Museumstr 5",
    "sg:city":"Innsbruck",
    "sg:orig_category":"Friseure U Frisiersalons",
    "sg:phone":"+43 4351 2583850",
    "sg:postcode":"6020",
    "sg:province":"Tirol",
    "wof:name":"Salon Schiessl",
    "wof:placetype":"venue"
},
  "geometry": {"coordinates":[11.3955097198,47.2671165466],"type":"Point"}
}