{
  "type": "Feature",
  "properties": {
    "addr:full":"Angerer Str 17 Wien Wien 1210",
    "addr:postcode":"1210",
    "addr:street":"Str 17",
    "iso:country":"AT",
    "sg:address":"Angerer Str 17",
    "sg:city":"Wien",
    "sg:orig_category":"Friseure U Frisiersalons",
    "sg:phone":"+43 1 2789029",
    "sg:postcode":"1210",
    "sg:province":"Wien",
    "wof:name":"Hanni Frisurentreffpunkt Inh Hans Johanna",
    "wof:placetype":"venue"
},
  "geometry": {"coordinates":[16.4043121338,48.2577857971],"type":"Point"}
}