{
  "type": "Feature",
  "properties": {
    "addr:full":"Sonnbichl 12 Reith im Alpbachtal Tirol 6235",
    "addr:housenumber":"12",
    "addr:postcode":"6235",
    "addr:street":"Sonnbichl;Alpbachtal Tirol",
    "iso:country":"AT",
    "sg:address":"Sonnbichl 12",
    "sg:city":"Reith im Alpbachtal",
    "sg:orig_category":"Volksschulen",
    "sg:phone":"+43 5337 63888",
    "sg:postcode":"6235",
    "sg:province":"Tirol",
    "wof:name":"Volksschule",
    "wof:placetype":"venue"
},
  "geometry": {"coordinates":[11.8788099289,47.4204406738],"type":"Point"}
}