{
  "type": "Feature",
  "properties": {
    "iso:country":"AT",
    "sg:address":"Maria Theresien-Str 5",
    "sg:city":"Innsbruck",
    "sg:orig_category":"Steuerberatung",
    "sg:phone":"+43 512 5605890",
    "sg:postcode":"6020",
    "sg:province":"Tirol",
    "wof:name":"Lentsch Ernst Mag",
    "wof:placetype":"venue"
},
  "geometry": {"coordinates":[11.3938970566,47.2668533325],"type":"Point"}
}