{
  "type": "Feature",
  "properties": {
    "addr:full":"Merowingerstr 5 Rankweil Vorarlberg 6830",
    "addr:housenumber":"5",
    "addr:postcode":"6830",
    "addr:street":"Merowingerstr",
    "iso:country":"AT",
    "sg:address":"Merowingerstr 5",
    "sg:city":"Rankweil",
    "sg:orig_category":"Raumausstattung",
    "sg:phone":"+43 5522 441730",
    "sg:postcode":"6830",
    "sg:province":"Vorarlberg",
    "wof:name":"Loretz Josef",
    "wof:placetype":"venue"
},
  "geometry": {"coordinates":[9.6281661987,47.2719573975],"type":"Point"}
}