{
  "type": "Feature",
  "properties": {
    "iso:country":"AT",
    "sg:address":"Salzburger Strasse 13",
    "sg:city":"Schwanenstadt",
    "sg:classifiers":[
        {
            "category":"Transit Center",
            "subcategory":"Freight",
            "type":"Transportation"
        }
    ],
    "sg:phone":"+43 767369700",
    "sg:postcode":"4690",
    "sg:province":"Ober\u00f6sterreich",
    "sg:tags":[
        "auger",
        "horizontal",
        "drilling",
        "vertical",
        "earth"
    ],
    "sg:website":"schierl.at",
    "wof:name":"Johann Schierl & Sohn Ges.m.b.H.",
    "wof:placetype":"venue"
},
  "geometry": {"coordinates":[13.7714977264,48.0533447266],"type":"Point"}
}