{
  "type": "Feature",
  "properties": {
    "addr:full":"Mitterfeldstr 6 Amstetten Nieder\u00f6sterreich 3300",
    "addr:housenumber":"6",
    "addr:postcode":"3300",
    "addr:street":"Mitterfeldstr;Niederoesterreich",
    "iso:country":"AT",
    "sg:address":"Mitterfeldstr 6",
    "sg:city":"Amstetten",
    "sg:orig_category":"Autohandel",
    "sg:phone":"+43 7472 649620",
    "sg:postcode":"3300",
    "sg:province":"Nieder\u00f6sterreich",
    "sg:website":"waldheim.co.at",
    "wof:name":"Waldheim Autohandels GesmbH",
    "wof:placetype":"venue"
},
  "geometry": {"coordinates":[14.8906841278,48.1231956482],"type":"Point"}
}