{
  "type": "Feature",
  "properties": {
    "addr:full":"Hauptpl 2 Waidhofen an der Ybbs Nieder\u00f6sterreich 3340",
    "addr:housenumber":"2",
    "addr:postcode":"3340",
    "addr:street":"Hauptpl",
    "iso:country":"AT",
    "sg:address":"Hauptpl 2",
    "sg:city":"Waidhofen an der Ybbs",
    "sg:orig_category":"Friseure U Frisiersalons",
    "sg:phone":"+43 4374 4253543",
    "sg:postcode":"3340",
    "sg:province":"Nieder\u00f6sterreich",
    "wof:name":"Krejcarek Klaus",
    "wof:placetype":"venue"
},
  "geometry": {"coordinates":[14.7797498703,47.9582481384],"type":"Point"}
}