{
  "type": "Feature",
  "properties": {
    "addr:full":"Universit\u00e4tsstr 27 Innsbruck Tirol 6020",
    "addr:housenumber":"27",
    "addr:postcode":"6020",
    "addr:street":"Universitaetsstr;Tirol",
    "iso:country":"AT",
    "sg:address":"Universit\u00e4tsstr 27",
    "sg:city":"Innsbruck",
    "sg:orig_category":"Bilderrahmen",
    "sg:phone":"+43 512 589170",
    "sg:postcode":"6020",
    "sg:province":"Tirol",
    "wof:name":"Bilderrahmen Jakubitzka",
    "wof:placetype":"venue"
},
  "geometry": {"coordinates":[11.4006500244,47.2691459656],"type":"Point"}
}