{
  "type": "Feature",
  "properties": {
    "iso:country":"AT",
    "sg:address":"Mariahilfer Str 69",
    "sg:city":"Wien",
    "sg:orig_category":"Bankomat-Standorte",
    "sg:phone":"+43 5 010020061",
    "sg:postcode":"1060",
    "sg:province":"Wien",
    "wof:name":"Bankomat d Erste Bank d oesterreichischen Sparkasse AG",
    "wof:placetype":"venue"
},
  "geometry": {"coordinates":[16.3512172699,48.1987113953],"type":"Point"}
}