{
  "type": "Feature",
  "properties": {
    "iso:country":"AT",
    "sg:address":"Taubeng 6",
    "sg:city":"Steinakirchen am Forst",
    "sg:orig_category":"Friseure U Frisiersalons",
    "sg:phone":"+43 4374 8876678",
    "sg:postcode":"3261",
    "sg:province":"Nieder\u00f6sterreich",
    "wof:name":"Resch Herta",
    "wof:placetype":"venue"
},
  "geometry": {"coordinates":[15.0508737564,48.067817688],"type":"Point"}
}