{
  "type": "Feature",
  "properties": {
    "addr:full":"Heinrichstr 29 Graz Steiermark 8010",
    "addr:housenumber":"29",
    "addr:postcode":"8010",
    "addr:street":"Heinrichstr",
    "iso:country":"AT",
    "sg:address":"Heinrichstr 29",
    "sg:city":"Graz",
    "sg:orig_category":"Schuhreparatur",
    "sg:phone":"+43 4331 6356093",
    "sg:postcode":"8010",
    "sg:province":"Steiermark",
    "wof:name":"Minuten-Service Schuh- u Schl\u00fcssel-Sofortdienst",
    "wof:placetype":"venue"
},
  "geometry": {"coordinates":[15.4482383728,47.0792198181],"type":"Point"}
}