{
  "type": "Feature",
  "properties": {
    "iso:country":"AT",
    "sg:address":"Sonnseite 122",
    "sg:city":"Going am Wilden Kaiser",
    "sg:classifiers":[
        {
            "category":"Professional",
            "subcategory":"Engineering",
            "type":"Services"
        }
    ],
    "sg:phone":"+43 4353 583142",
    "sg:postcode":"6353",
    "sg:province":"Tirol",
    "sg:tags":[
        "machine",
        "-",
        "mechanical"
    ],
    "wof:name":"FEYERSINGER GESMBH",
    "wof:placetype":"venue"
},
  "geometry": {"coordinates":[12.3470821381,47.5151405334],"type":"Point"}
}