{
  "type": "Feature",
  "properties": {
    "iso:country":"AT",
    "sg:address":"Im Stadtfeld 1",
    "sg:city":"Retz",
    "sg:orig_category":"Non-Classified Establishments",
    "sg:phone":"+43 2942 22430",
    "sg:postcode":"2070",
    "sg:province":"Nieder\u00f6sterreich",
    "wof:name":"Stra\u00dfenmeisterei Retz",
    "wof:placetype":"venue"
},
  "geometry": {"coordinates":[15.9611358643,48.7535247803],"type":"Point"}
}