{
  "type": "Feature",
  "properties": {
    "addr:full":"Zellerstr. 3  Wels Ober\u00f6sterreich 4600",
    "addr:housenumber":"3",
    "addr:postcode":"4600",
    "addr:street":"Zellerstr.;Oberoesterreich",
    "iso:country":"AT",
    "sg:address":"Zellerstr. 3 ",
    "sg:city":"Wels",
    "sg:classifiers":[
        {
            "category":"Shopping",
            "subcategory":"Stationery & Office Supplies",
            "type":"Retail Goods"
        }
    ],
    "sg:phone":"+43 4372 4246673",
    "sg:postcode":"4600",
    "sg:province":"Ober\u00f6sterreich",
    "sg:tags":[
        "professional"
    ],
    "wof:name":"POHL & CO KG",
    "wof:placetype":"venue"
},
  "geometry": {"coordinates":[14.0030994415,48.1664657593],"type":"Point"}
}