{
  "type": "Feature",
  "properties": {
    "addr:full":"L\u00e4rchenstr 32 Wels Ober\u00f6sterreich 4600",
    "addr:housenumber":"32",
    "addr:postcode":"4600",
    "addr:street":"Laerchenstr;Oberoesterreich",
    "iso:country":"AT",
    "sg:address":"L\u00e4rchenstr 32",
    "sg:city":"Wels",
    "sg:orig_category":"Drechslereien",
    "sg:phone":"+43 650 7203572",
    "sg:postcode":"4600",
    "sg:province":"Ober\u00f6sterreich",
    "wof:name":"Kunstdrechslerei Johann Deutsch",
    "wof:placetype":"venue"
},
  "geometry": {"coordinates":[14.0001411438,48.145450592],"type":"Point"}
}