{
  "type": "Feature",
  "properties": {
    "iso:country":"AT",
    "sg:address":"An der Wehr 1",
    "sg:city":"Gramatneusiedl",
    "sg:orig_category":"Waren Aller Art",
    "sg:phone":"+43 2234 80625",
    "sg:postcode":"2440",
    "sg:province":"Nieder\u00f6sterreich",
    "wof:name":"Sieghart Franz",
    "wof:placetype":"venue"
},
  "geometry": {"coordinates":[16.5166568756,47.991230011],"type":"Point"}
}