{
  "type": "Feature",
  "properties": {
    "addr:full":"Weidach 368a Leutasch Tirol 6105",
    "addr:housenumber":"368a",
    "addr:postcode":"6105",
    "addr:street":"Weidach;Tirol",
    "iso:country":"AT",
    "sg:address":"Weidach 368a",
    "sg:city":"Leutasch",
    "sg:orig_category":"Appartements / Ferienwohnungen",
    "sg:phone":"+43 4352 146673",
    "sg:postcode":"6105",
    "sg:province":"Tirol",
    "wof:name":"Ferienhaus Wanner",
    "wof:placetype":"venue"
},
  "geometry": {"coordinates":[11.1513023376,47.3726921082],"type":"Point"}
}