{
  "type": "Feature",
  "properties": {
    "iso:country":"AT",
    "sg:address":"Tamariskeng 102/57",
    "sg:city":"Wien",
    "sg:orig_category":"Physiotherapie",
    "sg:phone":"+43 1 2835701",
    "sg:postcode":"1220",
    "sg:province":"Wien",
    "wof:name":"Pawlowsky Ursula",
    "wof:placetype":"venue"
},
  "geometry": {"coordinates":[16.4689331055,48.2218360901],"type":"Point"}
}