{
  "type": "Feature",
  "properties": {
    "iso:country":"AT",
    "sg:address":"Nr 101",
    "sg:city":"Flaurling",
    "sg:orig_category":"Handelsagenturen",
    "sg:phone":"+43 5238 88715",
    "sg:postcode":"6403",
    "sg:province":"Tirol",
    "wof:name":"Eichelberger Dietmar",
    "wof:placetype":"venue"
},
  "geometry": {"coordinates":[11.1237049103,47.2917556763],"type":"Point"}
}