{
  "type": "Feature",
  "properties": {
    "addr:full":"Albert Sch\u00f6pf-Str 44 Linz Ober\u00f6sterreich 4020",
    "addr:housenumber":"44",
    "addr:postcode":"4020",
    "iso:country":"AT",
    "sg:address":"Albert Sch\u00f6pf-Str 44",
    "sg:city":"Linz",
    "sg:orig_category":"Reinigungsservice",
    "sg:phone":"+43 732 370666",
    "sg:postcode":"4020",
    "sg:province":"Ober\u00f6sterreich",
    "wof:name":"Stein 2000 Denkmal-, Fassaden-Geb\u00e4ude Reinigungs- und HandelsgesmbH",
    "wof:placetype":"venue"
},
  "geometry": {"coordinates":[14.2855110168,48.2655029297],"type":"Point"}
}