{
  "type": "Feature",
  "properties": {
    "iso:country":"AT",
    "sg:address":"Bahngasse 20",
    "sg:city":"Wiener Neustadt",
    "sg:orig_category":"Freizeit, Spiel U Spa\u00c3\u0178",
    "sg:phone":"+43 4366 43389009",
    "sg:postcode":"2700",
    "sg:province":"Nieder\u00f6sterreich",
    "sg:website":"http://members.magnet.at/segeln",
    "wof:name":"Segelschule und Yachtsport Martin Kempf",
    "wof:placetype":"venue"
},
  "geometry": {"coordinates":[8.1344404221,49.3539199829],"type":"Point"}
}