{
  "type": "Feature",
  "properties": {
    "addr:full":"Mariahilfer Str 66 Wien Wien 1070",
    "addr:postcode":"1070",
    "addr:street":"Str 66",
    "iso:country":"AT",
    "sg:address":"Mariahilfer Str 66",
    "sg:city":"Wien",
    "sg:orig_category":"Damenmoden",
    "sg:phone":"+43 1 9241285",
    "sg:postcode":"1070",
    "sg:province":"Wien",
    "wof:name":"JAY MODEN Handels GesmbH",
    "wof:placetype":"venue"
},
  "geometry": {"coordinates":[16.3504753113,48.1986198425],"type":"Point"}
}