{
  "type": "Feature",
  "properties": {
    "iso:country":"AT",
    "sg:address":"Linzer G 50",
    "sg:city":"Salzburg",
    "sg:orig_category":"Spielwaren U Spiele",
    "sg:phone":"+43 662 871453",
    "sg:postcode":"5020",
    "sg:province":"Salzburg",
    "wof:name":"Christine's Geschenke - Puppenhausbau",
    "wof:placetype":"venue"
},
  "geometry": {"coordinates":[13.0475893021,47.8036727905],"type":"Point"}
}