{
  "type": "Feature",
  "properties": {
    "iso:country":"AT",
    "sg:address":"Sch\u00fctzpassage 72",
    "sg:city":"Obertauern",
    "sg:orig_category":"Trachtenbekleidung",
    "sg:phone":"+43 4364 5620069",
    "sg:postcode":"5562",
    "sg:province":"Salzburg",
    "wof:name":"Tauernpass Oppeneiger KEG",
    "wof:placetype":"venue"
},
  "geometry": {"coordinates":[13.5611753464,47.2483558655],"type":"Point"}
}