{
  "type": "Feature",
  "properties": {
    "addr:full":"Heidenfeldstr 26 Villach K\u00e4rnten 9500",
    "addr:housenumber":"26",
    "addr:postcode":"9500",
    "addr:street":"Heidenfeldstr;Kaernten",
    "iso:country":"AT",
    "sg:address":"Heidenfeldstr 26",
    "sg:city":"Villach",
    "sg:orig_category":"Volksschulen",
    "sg:phone":"+43 4242 3354510",
    "sg:postcode":"9500",
    "sg:province":"K\u00e4rnten",
    "wof:name":"Volksschule 6 - Auen",
    "wof:placetype":"venue"
},
  "geometry": {"coordinates":[13.8467359543,46.6007652283],"type":"Point"}
}