{
  "type": "Feature",
  "properties": {
    "addr:full":"Strau\u00dfg 10 Leoben Steiermark 8700",
    "addr:housenumber":"10",
    "addr:postcode":"8700",
    "addr:street":"Straussg",
    "iso:country":"AT",
    "sg:address":"Strau\u00dfg 10",
    "sg:city":"Leoben",
    "sg:orig_category":"Handarbeiten",
    "sg:phone":"+43 3842 42005",
    "sg:postcode":"8700",
    "sg:province":"Steiermark",
    "wof:name":"Woll-Paradies Inh Christine Donik",
    "wof:placetype":"venue"
},
  "geometry": {"coordinates":[15.0936374664,47.3799858093],"type":"Point"}
}