{
  "type": "Feature",
  "properties": {
    "addr:full":"Ennsgasse 7-11  Wien Wien 1020",
    "addr:housenumber":"7-11",
    "addr:postcode":"1020",
    "addr:street":"Ennsgasse",
    "iso:country":"AT",
    "sg:address":"Ennsgasse 7-11 ",
    "sg:city":"Wien",
    "sg:classifiers":[
        {
            "category":"Building & Trades",
            "subcategory":"Plumbing",
            "type":"Services"
        }
    ],
    "sg:phone":"+43 1 7280558",
    "sg:postcode":"1020",
    "sg:province":"Wien",
    "sg:tags":[
        "supraregional",
        "gas"
    ],
    "sg:website":"www.riedel.co.at",
    "wof:name":"Peter Riedel Ges.m.b.H.",
    "wof:placetype":"venue"
},
  "geometry": {"coordinates":[16.4013004303,48.2218360901],"type":"Point"}
}