{
  "type": "Feature",
  "properties": {
    "addr:full":"Frauentalerstrasse 100 Deutschlandsberg Steiermark 8530",
    "addr:housenumber":"100",
    "addr:postcode":"8530",
    "addr:street":"Frauentalerstrasse",
    "iso:country":"AT",
    "sg:address":"Frauentalerstrasse 100",
    "sg:city":"Deutschlandsberg",
    "sg:classifiers":[
        {
            "category":"Education",
            "subcategory":"Vocational School",
            "type":"Public Place"
        }
    ],
    "sg:phone":"+43 3462 68000",
    "sg:postcode":"8530",
    "sg:province":"Steiermark",
    "sg:tags":[
        "assembly",
        "testing",
        "printed",
        "circuit",
        "pcb",
        "board"
    ],
    "sg:website":"seidel.at",
    "wof:name":"SEIDEL Elektronik GmbH",
    "wof:placetype":"venue"
},
  "geometry": {"coordinates":[15.2323141098,46.8204841614],"type":"Point"}
}