{
  "type": "Feature",
  "properties": {
    "addr:full":"Forstern 5 Burgkirchen Ober\u00f6sterreich 5274",
    "addr:housenumber":"5",
    "addr:postcode":"5274",
    "addr:street":"Forstern",
    "iso:country":"AT",
    "sg:address":"Forstern 5",
    "sg:city":"Burgkirchen",
    "sg:classifiers":[
        {
            "category":"Manufacturing",
            "subcategory":"Metals",
            "type":"Manufacturing & Wholesale Goods"
        }
    ],
    "sg:phone":"+43 4377 2425250",
    "sg:postcode":"5274",
    "sg:province":"Ober\u00f6sterreich",
    "sg:tags":[
        "metallurgy",
        "metalworking"
    ],
    "wof:name":"LUGMAYR F\u00dcREDER GESMBH",
    "wof:placetype":"venue"
},
  "geometry": {"coordinates":[13.0977916718,48.2098236084],"type":"Point"}
}