{
  "type": "Feature",
  "properties": {
    "iso:country":"AT",
    "sg:address":"Br\u00fcnner Str. 140-146 ",
    "sg:city":"Gerasdorf",
    "sg:classifiers":[
        {
            "category":"Autos & Motor Vehicles",
            "subcategory":"Automobile Sales",
            "type":"Retail Goods"
        }
    ],
    "sg:phone":"+43 4322 4633600",
    "sg:postcode":"2201",
    "sg:province":"Nieder\u00f6sterreich",
    "sg:tags":[
        "industrial"
    ],
    "wof:name":"GERHARD FEITZINGER",
    "wof:placetype":"venue"
},
  "geometry": {"coordinates":[16.4562244415,48.3326835632],"type":"Point"}
}