{
  "type": "Feature",
  "properties": {
    "addr:full":"Laaber Holzweg 41 Braunau am Inn Ober\u00f6sterreich 5280",
    "addr:housenumber":"41",
    "addr:postcode":"5280",
    "addr:street":"Laaber Holzweg",
    "iso:country":"AT",
    "sg:address":"Laaber Holzweg 41",
    "sg:city":"Braunau am Inn",
    "sg:orig_category":"Physiotherapie",
    "sg:phone":"+43 7722 62780",
    "sg:postcode":"5280",
    "sg:province":"Ober\u00f6sterreich",
    "wof:name":"Hantscher Ulrike Dipl-PT",
    "wof:placetype":"venue"
},
  "geometry": {"coordinates":[13.0458917618,48.2558288574],"type":"Point"}
}