{
  "type": "Feature",
  "properties": {
    "addr:full":"Herzog-Leopold-Str 20 Wiener Neustadt Nieder\u00f6sterreich 2700",
    "addr:housenumber":"20",
    "addr:postcode":"2700",
    "addr:street":"Herzog-Leopold-Str",
    "iso:country":"AT",
    "sg:address":"Herzog-Leopold-Str 20",
    "sg:city":"Wiener Neustadt",
    "sg:orig_category":"Damenmoden",
    "sg:phone":"+43 2622 29849",
    "sg:postcode":"2700",
    "sg:province":"Nieder\u00f6sterreich",
    "wof:name":"Street One",
    "wof:placetype":"venue"
},
  "geometry": {"coordinates":[16.2408218384,47.8135452271],"type":"Point"}
}