{
  "type": "Feature",
  "properties": {
    "iso:country":"AT",
    "sg:address":"Wexstr 24/27",
    "sg:city":"Wien",
    "sg:orig_category":"Immobilienverwaltungen",
    "sg:phone":"+43 1 3742977",
    "sg:postcode":"1200",
    "sg:province":"Wien",
    "wof:name":"B\u00f6sm\u00fcller Immobilienverwaltungs GmbH",
    "wof:placetype":"venue"
},
  "geometry": {"coordinates":[16.368888855,48.2359428406],"type":"Point"}
}