{
  "type": "Feature",
  "properties": {
    "addr:full":"Walser Str 15 Wals Salzburg 5071",
    "addr:postcode":"5071",
    "addr:street":"Str 15;Salzburg",
    "iso:country":"AT",
    "sg:address":"Walser Str 15",
    "sg:city":"Wals",
    "sg:classifiers":[
        {
            "category":"Travel",
            "subcategory":"Hotels & Motels",
            "type":"Entertainment"
        }
    ],
    "sg:phone":"+43 662 8509270",
    "sg:postcode":"5071",
    "sg:province":"Salzburg",
    "wof:name":"Austria Classic Hotel Walserwirt",
    "wof:placetype":"venue"
},
  "geometry": {"coordinates":[12.9668092728,47.787612915],"type":"Point"}
}