{
  "type": "Feature",
  "properties": {
    "addr:full":"Bahnweg 5 Rietz Tirol 6421",
    "addr:housenumber":"5",
    "addr:postcode":"6421",
    "addr:street":"Bahnweg;Tirol",
    "iso:country":"AT",
    "sg:address":"Bahnweg 5",
    "sg:city":"Rietz",
    "sg:classifiers":[
        {
            "category":"Home & Garden",
            "subcategory":"Carpets & Floor Coverings",
            "type":"Retail Goods"
        }
    ],
    "sg:phone":"+43 5262 62210",
    "sg:postcode":"6421",
    "sg:province":"Tirol",
    "sg:tags":[
        "cotton"
    ],
    "sg:website":"rietzer.at",
    "wof:name":"Rietzer Teppichweberei GesmbH",
    "wof:placetype":"venue"
},
  "geometry": {"coordinates":[11.0241537094,47.2922744751],"type":"Point"}
}