{
  "type": "Feature",
  "properties": {
    "addr:full":"Hauptstr 170 Wien Wien 1140",
    "addr:housenumber":"170",
    "addr:postcode":"1140",
    "addr:street":"Hauptstr",
    "iso:country":"AT",
    "sg:address":"Hauptstr 170",
    "sg:city":"Wien",
    "sg:orig_category":"Architekten",
    "sg:phone":"+43 1 9796680",
    "sg:postcode":"1140",
    "sg:province":"Wien",
    "wof:name":"Giller Alfred Arch Dipl-Ing",
    "wof:placetype":"venue"
},
  "geometry": {"coordinates":[16.2049713135,48.2055244446],"type":"Point"}
}