{
  "type": "Feature",
  "properties": {
    "addr:full":"Gest\u00fcthof 46 Murau Steiermark 8850",
    "addr:housenumber":"46",
    "addr:postcode":"8850",
    "addr:street":"Gestuethof",
    "iso:country":"AT",
    "sg:address":"Gest\u00fcthof 46",
    "sg:city":"Murau",
    "sg:orig_category":"Forstverwaltungen",
    "sg:phone":"+43 3532 2485",
    "sg:postcode":"8850",
    "sg:province":"Steiermark",
    "wof:name":"Schwarzenbergsche Forstdirektion Murau",
    "wof:placetype":"venue"
},
  "geometry": {"coordinates":[14.1716346741,47.1107406616],"type":"Point"}
}