{
  "type": "Feature",
  "properties": {
    "iso:country":"AT",
    "sg:address":"Setzg 28b",
    "sg:city":"Bisamberg",
    "sg:orig_category":"Fotografen",
    "sg:phone":"+43 4322 6263556",
    "sg:postcode":"2102",
    "sg:province":"Nieder\u00f6sterreich",
    "wof:name":"Foto Liesl Biber",
    "wof:placetype":"venue"
},
  "geometry": {"coordinates":[16.3544807434,48.3280982971],"type":"Point"}
}