{
  "type": "Feature",
  "properties": {
    "addr:full":"Rauchenwarther Str 5 Himberg Nieder\u00f6sterreich 2325",
    "addr:housenumber":"5",
    "addr:postcode":"2325",
    "addr:street":"Str",
    "iso:country":"AT",
    "sg:address":"Rauchenwarther Str 5",
    "sg:city":"Himberg",
    "sg:orig_category":"Beschriftungen",
    "sg:phone":"+43 2235 86001",
    "sg:postcode":"2325",
    "sg:province":"Nieder\u00f6sterreich",
    "wof:name":"Top Works Graphicals Grafik-Beschriftung-Textildruck",
    "wof:placetype":"venue"
},
  "geometry": {"coordinates":[16.4495697021,48.0833740234],"type":"Point"}
}