{
  "type": "Feature",
  "properties": {
    "iso:country":"AT",
    "sg:address":"Wr Neust\u00e4dter Str 2",
    "sg:city":"Pitten",
    "sg:orig_category":"Maschinenbau",
    "sg:phone":"+43 2627 83880",
    "sg:postcode":"2823",
    "sg:province":"Nieder\u00f6sterreich",
    "wof:name":"Macon Automatisierungstechnik",
    "wof:placetype":"venue"
},
  "geometry": {"coordinates":[16.18658638,47.7162742615],"type":"Point"}
}