{
  "type": "Feature",
  "properties": {
    "addr:full":"Lindbergstr 1 Scheifling Steiermark 8811",
    "addr:housenumber":"1",
    "addr:postcode":"8811",
    "addr:street":"Lindbergstr",
    "iso:country":"AT",
    "sg:address":"Lindbergstr 1",
    "sg:city":"Scheifling",
    "sg:orig_category":"Transportunternehmen",
    "sg:phone":"+43 4335 822223",
    "sg:postcode":"8811",
    "sg:province":"Steiermark",
    "wof:name":"Gradischnig Erich GmbH",
    "wof:placetype":"venue"
},
  "geometry": {"coordinates":[14.3983974457,47.1586227417],"type":"Point"}
}