{
  "type": "Feature",
  "properties": {
    "addr:full":"Kremser Str 19 Spitz Nieder\u00f6sterreich 3620",
    "addr:housenumber":"19",
    "addr:postcode":"3620",
    "addr:street":"Str",
    "iso:country":"AT",
    "sg:address":"Kremser Str 19",
    "sg:city":"Spitz",
    "sg:classifiers":[
        {
            "category":"Travel",
            "subcategory":"Hotels & Motels",
            "type":"Entertainment"
        }
    ],
    "sg:phone":"+43 2713 23560",
    "sg:postcode":"3620",
    "sg:province":"Nieder\u00f6sterreich",
    "wof:name":"Barock-Landhof Inh Burkhardt",
    "wof:placetype":"venue"
},
  "geometry": {"coordinates":[15.4161281586,48.3652954102],"type":"Point"}
}