{
  "type": "Feature",
  "properties": {
    "addr:full":"Wagram 1 Pasching Ober\u00f6sterreich 4061",
    "addr:housenumber":"1",
    "addr:postcode":"4061",
    "addr:street":"Wagram;Oberoesterreich",
    "iso:country":"AT",
    "sg:address":"Wagram 1",
    "sg:city":"Pasching",
    "sg:orig_category":"Sondermaschinenbau",
    "sg:phone":"+43 7229 876800",
    "sg:postcode":"4061",
    "sg:province":"Ober\u00f6sterreich",
    "wof:name":"ECON Maschinenbau und Steuerungstechnik GmbH",
    "wof:placetype":"venue"
},
  "geometry": {"coordinates":[14.2197446823,48.2391357422],"type":"Point"}
}