{
  "type": "Feature",
  "properties": {
    "addr:full":"Bahnstr 1 Wallern im Burgenland Burgenland 7151",
    "addr:housenumber":"1",
    "addr:postcode":"7151",
    "addr:street":"Bahnstr",
    "iso:country":"AT",
    "sg:address":"Bahnstr 1",
    "sg:city":"Wallern im Burgenland",
    "sg:orig_category":"Bankomat-Standorte",
    "sg:phone":"+43 4321 742226",
    "sg:postcode":"7151",
    "sg:province":"Burgenland",
    "wof:name":"Bankomat d Raiffeisenbank Wallern regGenmbH",
    "wof:placetype":"venue"
},
  "geometry": {"coordinates":[16.9357280731,47.7252883911],"type":"Point"}
}