{
  "type": "Feature",
  "properties": {
    "addr:full":"Bundesstr 115 Lauterach Vorarlberg 6923",
    "addr:housenumber":"115",
    "addr:postcode":"6923",
    "iso:country":"AT",
    "sg:address":"Bundesstr 115",
    "sg:city":"Lauterach",
    "sg:orig_category":"Unterhaltungselektronik / Einzelhandel",
    "sg:phone":"+43 4355 74735540",
    "sg:postcode":"6923",
    "sg:province":"Vorarlberg",
    "wof:name":"Wober GesmbH & Co KG",
    "wof:placetype":"venue"
},
  "geometry": {"coordinates":[9.7284240723,47.4666633606],"type":"Point"}
}