{
  "type": "Feature",
  "properties": {
    "addr:full":"Binderg 6 Graz Steiermark 8010",
    "addr:housenumber":"6",
    "addr:postcode":"8010",
    "addr:street":"Binderg",
    "iso:country":"AT",
    "sg:address":"Binderg 6",
    "sg:city":"Graz",
    "sg:orig_category":"Boutiquen",
    "sg:phone":"+43 316 835613",
    "sg:postcode":"8010",
    "sg:province":"Steiermark",
    "wof:name":"Mode Hannelore Kirchner",
    "wof:placetype":"venue"
},
  "geometry": {"coordinates":[15.4418296814,47.0708045959],"type":"Point"}
}