{
  "type": "Feature",
  "properties": {
    "iso:country":"AT",
    "sg:address":"Tauernstr 17",
    "sg:city":"Bad Hofgastein",
    "sg:orig_category":"Pensionen / Privatzimmer",
    "sg:phone":"+43 6432 6705",
    "sg:postcode":"5630",
    "sg:province":"Salzburg",
    "wof:name":"Haus St Rupertus",
    "wof:placetype":"venue"
},
  "geometry": {"coordinates":[13.1035499573,47.1717681885],"type":"Point"}
}