{
  "type": "Feature",
  "properties": {
    "addr:full":"Rudigierstr 10 Linz Ober\u00f6sterreich 4020",
    "addr:housenumber":"10",
    "addr:postcode":"4020",
    "addr:street":"Rudigierstr",
    "iso:country":"AT",
    "sg:address":"Rudigierstr 10",
    "sg:city":"Linz",
    "sg:orig_category":"Forstverwaltungen",
    "sg:phone":"+43 732 772670",
    "sg:postcode":"4020",
    "sg:province":"Ober\u00f6sterreich",
    "wof:name":"Domkapitel Linz",
    "wof:placetype":"venue"
},
  "geometry": {"coordinates":[14.2878227234,48.3005332947],"type":"Point"}
}