{
  "type": "Feature",
  "properties": {
    "addr:full":"Egger-Lienz-Str 30 Innsbruck Tirol 6020",
    "addr:housenumber":"30",
    "addr:postcode":"6020",
    "addr:street":"Egger-Lienz-Str;Tirol",
    "iso:country":"AT",
    "sg:address":"Egger-Lienz-Str 30",
    "sg:city":"Innsbruck",
    "sg:orig_category":"Tabaktrafiken",
    "sg:phone":"+43 512 564390",
    "sg:postcode":"6020",
    "sg:province":"Tirol",
    "wof:name":"Jabinger Ludwig Mag",
    "wof:placetype":"venue"
},
  "geometry": {"coordinates":[11.3895988464,47.2564315796],"type":"Point"}
}