{
  "type": "Feature",
  "properties": {
    "iso:country":"AT",
    "sg:address":"Am Weiher 153",
    "sg:city":"Sulz im Wienerwald",
    "sg:classifiers":[
        {
            "category":"Building & Trades",
            "subcategory":"Electrical",
            "type":"Services"
        }
    ],
    "sg:phone":"+43 2258 8416",
    "sg:postcode":"2392",
    "sg:province":"Nieder\u00f6sterreich",
    "sg:tags":[
        "installation"
    ],
    "wof:name":"Erich Plach",
    "wof:placetype":"venue"
},
  "geometry": {"coordinates":[16.1391887665,48.1020393372],"type":"Point"}
}