{
  "type": "Feature",
  "properties": {
    "iso:country":"AT",
    "sg:address":"Gasteiner Str 40",
    "sg:city":"Bischofshofen",
    "sg:orig_category":"Elektroinstallationsunternehmen",
    "sg:phone":"+43 6462 3138",
    "sg:postcode":"5500",
    "sg:province":"Salzburg",
    "wof:name":"Schmidhuber Walter",
    "wof:placetype":"venue"
},
  "geometry": {"coordinates":[13.2164154053,47.4112319946],"type":"Point"}
}