{
  "type": "Feature",
  "properties": {
    "addr:full":"Steyrer Str. 44  Haag Nieder\u00f6sterreich 3350",
    "addr:postcode":"3350",
    "addr:street":"Str. 44 Haag Niederoesterreich",
    "iso:country":"AT",
    "sg:address":"Steyrer Str. 44 ",
    "sg:city":"Haag",
    "sg:classifiers":[
        {
            "category":"Autos & Motor Vehicles",
            "subcategory":"Automobile Sales",
            "type":"Retail Goods"
        }
    ],
    "sg:phone":"+43 4374 34424800",
    "sg:postcode":"3350",
    "sg:province":"Nieder\u00f6sterreich",
    "sg:tags":[
        "motor-cars"
    ],
    "wof:name":"\u00d6LLINGER GESMBH & CO KG",
    "wof:placetype":"venue"
},
  "geometry": {"coordinates":[14.5653553009,48.1121940613],"type":"Point"}
}