{
  "type": "Feature",
  "properties": {
    "addr:full":"Hauptstr 38 Tullnerbach Nieder\u00f6sterreich 3013",
    "addr:housenumber":"38",
    "addr:postcode":"3013",
    "addr:street":"Hauptstr",
    "iso:country":"AT",
    "sg:address":"Hauptstr 38",
    "sg:city":"Tullnerbach",
    "sg:orig_category":"Tischlereien",
    "sg:phone":"+43 2233 52377",
    "sg:postcode":"3013",
    "sg:province":"Nieder\u00f6sterreich",
    "wof:name":"Knassm\u00fcller Andreas GesmbH",
    "wof:placetype":"venue"
},
  "geometry": {"coordinates":[16.0979404449,48.1845054626],"type":"Point"}
}