{
  "type": "Feature",
  "properties": {
    "addr:full":"Fuchsgraben 21 Oberneukirchen Ober\u00f6sterreich 4181",
    "addr:housenumber":"21",
    "addr:postcode":"4181",
    "addr:street":"Fuchsgraben",
    "iso:country":"AT",
    "sg:address":"Fuchsgraben 21",
    "sg:city":"Oberneukirchen",
    "sg:orig_category":"Tischlereien",
    "sg:phone":"+43 7212 71830",
    "sg:postcode":"4181",
    "sg:province":"Ober\u00f6sterreich",
    "wof:name":"Stehrer Hermann",
    "wof:placetype":"venue"
},
  "geometry": {"coordinates":[14.2205896378,48.474937439],"type":"Point"}
}