{
  "type": "Feature",
  "properties": {
    "addr:full":"Brunnackerweg 7 Fiss Tirol 6533",
    "addr:housenumber":"7",
    "addr:postcode":"6533",
    "addr:street":"Brunnackerweg;Tirol",
    "iso:country":"AT",
    "sg:address":"Brunnackerweg 7",
    "sg:city":"Fiss",
    "sg:orig_category":"Appartements / Ferienwohnungen",
    "sg:phone":"+43 5476 6700",
    "sg:postcode":"6533",
    "sg:province":"Tirol",
    "wof:name":"Aquarius",
    "wof:placetype":"venue"
},
  "geometry": {"coordinates":[10.621178627,47.0544815063],"type":"Point"}
}