{
  "type": "Feature",
  "properties": {
    "iso:country":"AT",
    "sg:address":"Hauptpl 33",
    "sg:city":"Neusiedl am See",
    "sg:orig_category":"Psychologen",
    "sg:phone":"+43 2167 8560",
    "sg:postcode":"7100",
    "sg:province":"Burgenland",
    "wof:name":"Horvath-Nowotny Irene Dr",
    "wof:placetype":"venue"
},
  "geometry": {"coordinates":[16.8418292999,47.949546814],"type":"Point"}
}