{
  "type": "Feature",
  "properties": {
    "addr:full":"Hauptstr 97 Neufeld an der Leitha Burgenland 2491",
    "addr:housenumber":"97",
    "addr:postcode":"2491",
    "addr:street":"Hauptstr",
    "iso:country":"AT",
    "sg:address":"Hauptstr 97",
    "sg:city":"Neufeld an der Leitha",
    "sg:orig_category":"Feuerwehren",
    "sg:phone":"+43 2624 55867",
    "sg:postcode":"2491",
    "sg:province":"Burgenland",
    "wof:name":"Freiwillige Feuerwehr Neufeld a d Leitha",
    "wof:placetype":"venue"
},
  "geometry": {"coordinates":[16.3775081635,47.8616333008],"type":"Point"}
}