{
  "type": "Feature",
  "properties": {
    "iso:country":"AT",
    "sg:address":"Traunuferstr 98",
    "sg:city":"Ansfelden",
    "sg:orig_category":"Non-Classified Establishments",
    "sg:phone":"+43 7229 870470",
    "sg:postcode":"4052",
    "sg:province":"Ober\u00f6sterreich",
    "wof:name":"Stra\u00dfenmeisterei Ansfelden",
    "wof:placetype":"venue"
},
  "geometry": {"coordinates":[14.2834072113,48.217754364],"type":"Point"}
}