{
  "type": "Feature",
  "properties": {
    "addr:full":"Traunuferstr 98 Ansfelden Ober\u00f6sterreich 4052",
    "addr:housenumber":"98",
    "addr:postcode":"4052",
    "addr:street":"Traunuferstr",
    "iso:country":"AT",
    "sg:address":"Traunuferstr 98",
    "sg:city":"Ansfelden",
    "sg:orig_category":"Non-Classified Establishments",
    "sg:phone":"+43 7229 870470",
    "sg:postcode":"4052",
    "sg:province":"Ober\u00f6sterreich",
    "wof:name":"Stra\u00dfenmeisterei Ansfelden",
    "wof:placetype":"venue"
},
  "geometry": {"coordinates":[14.2834072113,48.217754364],"type":"Point"}
}