{
  "type": "Feature",
  "properties": {
    "addr:full":"Hauptplatz 8  Deutschlandsberg Steiermark 8530",
    "addr:housenumber":"8",
    "addr:postcode":"8530",
    "addr:street":"Hauptplatz",
    "iso:country":"AT",
    "sg:address":"Hauptplatz 8 ",
    "sg:city":"Deutschlandsberg",
    "sg:classifiers":[
        {
            "category":"Personal",
            "subcategory":"Shoe Repair & Shine",
            "type":"Services"
        }
    ],
    "sg:phone":"+43 4334 622109",
    "sg:postcode":"8530",
    "sg:province":"Steiermark",
    "sg:tags":[
        "leather"
    ],
    "wof:name":"KISBERK GES. MBH",
    "wof:placetype":"venue"
},
  "geometry": {"coordinates":[15.2152938843,46.8152503967],"type":"Point"}
}