{
  "type": "Feature",
  "properties": {
    "addr:full":"Rotenturmstr 16-18 Wien Wien 1010",
    "addr:postcode":"16-18;1010",
    "iso:country":"AT",
    "sg:address":"Rotenturmstr 16-18",
    "sg:city":"Wien",
    "sg:orig_category":"Banken U Sparkassen",
    "sg:phone":"+43 1 316200",
    "sg:postcode":"1010",
    "sg:province":"Wien",
    "wof:name":"INVESCO Asset Management \u00d6sterreich GmbH",
    "wof:placetype":"venue"
},
  "geometry": {"coordinates":[16.3751735687,48.2107200623],"type":"Point"}
}