{
  "type": "Feature",
  "properties": {
    "addr:full":"Linden 108 St. Georgen am Walde Ober\u00f6sterreich 4372",
    "addr:housenumber":"108",
    "addr:postcode":"4372",
    "addr:street":"Linden",
    "iso:country":"AT",
    "sg:address":"Linden 108",
    "sg:city":"St. Georgen am Walde",
    "sg:orig_category":"Lebensmittel / Einzelhandel",
    "sg:phone":"+43 4379 543001",
    "sg:postcode":"4372",
    "sg:province":"Ober\u00f6sterreich",
    "wof:name":"Haas Wolfgang Nah & Frisch",
    "wof:placetype":"venue"
},
  "geometry": {"coordinates":[14.909696579,48.3667907715],"type":"Point"}
}