{
  "type": "Feature",
  "properties": {
    "addr:full":"Genochpl 3 Wien Wien 1220",
    "addr:housenumber":"3",
    "addr:postcode":"1220",
    "addr:street":"Genochpl",
    "iso:country":"AT",
    "sg:address":"Genochpl 3",
    "sg:city":"Wien",
    "sg:orig_category":"Elektroinstallationsunternehmen",
    "sg:phone":"+43 4312 852556",
    "sg:postcode":"1220",
    "sg:province":"Wien",
    "wof:name":"Br\u00e4uer Christian - Elektrotechnik",
    "wof:placetype":"venue"
},
  "geometry": {"coordinates":[16.4560184479,48.2282447815],"type":"Point"}
}