{
  "type": "Feature",
  "properties": {
    "addr:full":"Mitterg 23 Bruck an der Mur Steiermark 8600",
    "addr:housenumber":"23",
    "addr:postcode":"8600",
    "addr:street":"Mitterg",
    "iso:country":"AT",
    "sg:address":"Mitterg 23",
    "sg:city":"Bruck an der Mur",
    "sg:orig_category":"Bars-Cafes",
    "sg:phone":"+43 4338 6256661",
    "sg:postcode":"8600",
    "sg:province":"Steiermark",
    "wof:name":"Musetti Caffe",
    "wof:placetype":"venue"
},
  "geometry": {"coordinates":[15.2726583481,47.4108428955],"type":"Point"}
}