{
  "type": "Feature",
  "properties": {
    "addr:full":"Bahnhofstr 39b Ried im Innkreis Ober\u00f6sterreich 4910",
    "addr:housenumber":"39b",
    "addr:postcode":"4910",
    "addr:street":"Bahnhofstr",
    "iso:country":"AT",
    "sg:address":"Bahnhofstr 39b",
    "sg:city":"Ried im Innkreis",
    "sg:classifiers":[
        {
            "category":"Internet Cafe",
            "subcategory":"None",
            "type":"Food & Drink"
        }
    ],
    "sg:phone":"+43 4377 5270696",
    "sg:postcode":"4910",
    "sg:province":"Ober\u00f6sterreich",
    "sg:tags":[
        "internet-provider"
    ],
    "wof:name":"MICROLAB GmbH & Co KEG",
    "wof:placetype":"venue"
},
  "geometry": {"coordinates":[13.4892349243,48.2040634155],"type":"Point"}
}