{
  "type": "Feature",
  "properties": {
    "addr:full":"Dr.-Grobben-Str 1 Schwanenstadt Ober\u00f6sterreich 4690",
    "addr:housenumber":"1",
    "addr:postcode":"4690",
    "addr:street":"Dr.-Grobben-Str",
    "iso:country":"AT",
    "sg:address":"Dr.-Grobben-Str 1",
    "sg:city":"Schwanenstadt",
    "sg:orig_category":"Speditionen",
    "sg:phone":"+43 4376 7375595",
    "sg:postcode":"4690",
    "sg:province":"Ober\u00f6sterreich",
    "wof:name":"NOWA Spedition GmbH",
    "wof:placetype":"venue"
},
  "geometry": {"coordinates":[13.7680511475,48.0470275879],"type":"Point"}
}