{
  "type": "Feature",
  "properties": {
    "addr:full":"Sommerholz 33 Neumarkt am Wallersee Salzburg 5202",
    "addr:housenumber":"33",
    "addr:postcode":"5202",
    "addr:street":"Sommerholz;Salzburg",
    "iso:country":"AT",
    "sg:address":"Sommerholz 33",
    "sg:city":"Neumarkt am Wallersee",
    "sg:orig_category":"Innenausbau",
    "sg:phone":"+43 4362 166720",
    "sg:postcode":"5202",
    "sg:province":"Salzburg",
    "wof:name":"Koller Matthias",
    "wof:placetype":"venue"
},
  "geometry": {"coordinates":[13.2678756714,47.936164856],"type":"Point"}
}