{
  "type": "Feature",
  "properties": {
    "iso:country":"AT",
    "sg:address":"Dorfstr 58",
    "sg:city":"St. Anton am Arlberg",
    "sg:classifiers":[
        {
            "category":"Restaurant",
            "type":"Food & Drink"
        }
    ],
    "sg:phone":"+43 5446 2218",
    "sg:postcode":"6580",
    "sg:province":"Tirol",
    "wof:name":"Restaurant Amalis",
    "wof:placetype":"venue"
},
  "geometry": {"coordinates":[10.2665328979,47.1294975281],"type":"Point"}
}