{
  "type": "Feature",
  "properties": {
    "addr:full":"Ulrichstr 6 Eichgraben Nieder\u00f6sterreich 3032",
    "addr:housenumber":"6",
    "addr:postcode":"3032",
    "addr:street":"Ulrichstr",
    "iso:country":"AT",
    "sg:address":"Ulrichstr 6",
    "sg:city":"Eichgraben",
    "sg:orig_category":"Alarmanlagen U Sicherheitssysteme, Sicherheitstechnik",
    "sg:phone":"+43 4327 7344700",
    "sg:postcode":"3032",
    "sg:province":"Nieder\u00f6sterreich",
    "wof:name":"EUROPLEX - idR Sicherheitstechnik",
    "wof:placetype":"venue"
},
  "geometry": {"coordinates":[15.9845380783,48.1872138977],"type":"Point"}
}