{
  "type": "Feature",
  "properties": {
    "iso:country":"AT",
    "sg:address":"Obere Dorfstr 3",
    "sg:city":"Fiss",
    "sg:classifiers":[
        {
            "category":"Restaurant",
            "type":"Food & Drink"
        }
    ],
    "sg:phone":"+43 5476 53055",
    "sg:postcode":"6533",
    "sg:province":"Tirol",
    "sg:tags":[
        "pizzeria"
    ],
    "wof:name":"Restaurant Paletti",
    "wof:placetype":"venue"
},
  "geometry": {"coordinates":[10.6167602539,47.056438446],"type":"Point"}
}