{
  "type": "Feature",
  "properties": {
    "addr:full":"Faulmanng 8 Wien Wien 1040",
    "addr:housenumber":"8",
    "addr:postcode":"1040",
    "addr:street":"Faulmanng",
    "iso:country":"AT",
    "sg:address":"Faulmanng 8",
    "sg:city":"Wien",
    "sg:orig_category":"Markt- U Meinungsforschung",
    "sg:phone":"+43 1 58546230",
    "sg:postcode":"1040",
    "sg:province":"Wien",
    "wof:name":"InterConnection Marketing & Information Consulting GesmbH",
    "wof:placetype":"venue"
},
  "geometry": {"coordinates":[16.3653278351,48.1990776062],"type":"Point"}
}