{
  "type": "Feature",
  "properties": {
    "iso:country":"AT",
    "sg:address":"Ro\u00dfmarkt 37",
    "sg:city":"Grieskirchen",
    "sg:orig_category":"Mauertrockenlegungen",
    "sg:phone":"+43 4372 4862590",
    "sg:postcode":"4710",
    "sg:province":"Ober\u00f6sterreich",
    "sg:website":"veinal.at",
    "wof:name":"Veinal \u00f6sterreich",
    "wof:placetype":"venue"
},
  "geometry": {"coordinates":[13.8257322311,48.2358856201],"type":"Point"}
}