{
  "type": "Feature",
  "properties": {
    "addr:full":"Engerthstr 91 Wien Wien 1200",
    "addr:housenumber":"91",
    "addr:postcode":"1200",
    "addr:street":"Engerthstr",
    "iso:country":"AT",
    "sg:address":"Engerthstr 91",
    "sg:city":"Wien",
    "sg:classifiers":[
        {
            "category":"Shopping",
            "subcategory":"Thrift Store",
            "type":"Retail Goods"
        }
    ],
    "sg:phone":"+43 4319 258888",
    "sg:postcode":"1200",
    "sg:province":"Wien",
    "sg:tags":[
        "second-hand-shops"
    ],
    "sg:website":"cashstore.at",
    "wof:name":"Cash Store Second Hand Shop",
    "wof:placetype":"venue"
},
  "geometry": {"coordinates":[16.3868217468,48.2386817932],"type":"Point"}
}