{
  "type": "Feature",
  "properties": {
    "addr:full":"Nr 8 Unterpurkla Steiermark 8484",
    "addr:postcode":"8484",
    "addr:street":"Nr;Unterpurkla",
    "iso:country":"AT",
    "sg:address":"Nr 8",
    "sg:city":"Unterpurkla",
    "sg:orig_category":"Genossenschaften",
    "sg:phone":"+43 4366 43356716",
    "sg:postcode":"8484",
    "sg:province":"Steiermark",
    "wof:name":"Arbeitsgemeinschaft steirischer K\u00fcrbisbauern regGenmbH",
    "wof:placetype":"venue"
},
  "geometry": {"coordinates":[15.8910417557,46.7629318237],"type":"Point"}
}