{
  "type": "Feature",
  "properties": {
    "addr:full":"Gewerbestr 1 Litschau Nieder\u00f6sterreich 3874",
    "addr:housenumber":"1",
    "addr:postcode":"3874",
    "addr:street":"Gewerbestr",
    "iso:country":"AT",
    "sg:address":"Gewerbestr 1",
    "sg:city":"Litschau",
    "sg:orig_category":"Hunde U Hundeartikel",
    "sg:phone":"+43 4328 655007",
    "sg:postcode":"3874",
    "sg:province":"Nieder\u00f6sterreich",
    "wof:name":"Pet-Snacks-HandelsgesmbH",
    "wof:placetype":"venue"
},
  "geometry": {"coordinates":[15.0423736572,48.9402503967],"type":"Point"}
}