{
  "type": "Feature",
  "properties": {
    "iso:country":"AT",
    "sg:address":"Alberto Susat-Str 12",
    "sg:city":"Aigen",
    "sg:orig_category":"Unternehmensberatung",
    "sg:phone":"+43 662 629620",
    "sg:postcode":"5026",
    "sg:province":"Salzburg",
    "wof:name":"Gutwirth Uwe Mag",
    "wof:placetype":"venue"
},
  "geometry": {"coordinates":[13.0767192841,47.7864685059],"type":"Point"}
}