{
  "type": "Feature",
  "properties": {
    "iso:country":"AT",
    "sg:address":"Liesinger Flur-G 3",
    "sg:city":"Wien",
    "sg:orig_category":"Montagen U Montagetechnik",
    "sg:phone":"+43 1 8658410",
    "sg:postcode":"1230",
    "sg:province":"Wien",
    "wof:name":"Klobutschar Ing GesmbH",
    "wof:placetype":"venue"
},
  "geometry": {"coordinates":[16.3058834076,48.1360054016],"type":"Point"}
}