{
  "type": "Feature",
  "properties": {
    "addr:full":"Gaullacherg 7 Wien Wien 1160",
    "addr:housenumber":"7",
    "addr:postcode":"1160",
    "addr:street":"Gaullacherg",
    "iso:country":"AT",
    "sg:address":"Gaullacherg 7",
    "sg:city":"Wien",
    "sg:orig_category":"Papier / Erzeugung U Gro\u00c3\u0178handel",
    "sg:phone":"+43 4314 0750610",
    "sg:postcode":"1160",
    "sg:province":"Wien",
    "wof:name":"W.A.B. Bienenstein Organisationssysteme Vertriebs GmbH",
    "wof:placetype":"venue"
},
  "geometry": {"coordinates":[16.3376789093,48.2115287781],"type":"Point"}
}