{
  "type": "Feature",
  "properties": {
    "iso:country":"AT",
    "sg:address":"Hauptpl 16",
    "sg:city":"Feldkirchen in K\u00e4rnten",
    "sg:classifiers":[
        {
            "category":"Professional",
            "subcategory":"Computer Services",
            "type":"Services"
        }
    ],
    "sg:phone":"+43 4342 7630660",
    "sg:postcode":"9560",
    "sg:province":"K\u00e4rnten",
    "sg:tags":[
        "software"
    ],
    "wof:name":"Innotech Betriebstechnik GesmbH",
    "wof:placetype":"venue"
},
  "geometry": {"coordinates":[14.092338562,46.723815918],"type":"Point"}
}