{
  "type": "Feature",
  "properties": {
    "addr:full":"Leondinger Str 23 Traun Ober\u00f6sterreich 4050",
    "addr:postcode":"4050",
    "addr:street":"Str 23",
    "iso:country":"AT",
    "sg:address":"Leondinger Str 23",
    "sg:city":"Traun",
    "sg:orig_category":"Reinigungsservice",
    "sg:phone":"+43 4366 41811887",
    "sg:postcode":"4050",
    "sg:province":"Ober\u00f6sterreich",
    "wof:name":"Nimas Bau- u Handels GmbH",
    "wof:placetype":"venue"
},
  "geometry": {"coordinates":[14.2601146698,48.2419242859],"type":"Point"}
}