{
  "type": "Feature",
  "properties": {
    "addr:full":"Uferstr 42 Oberndorf Salzburg 5110",
    "addr:housenumber":"42",
    "addr:postcode":"5110",
    "addr:street":"Uferstr",
    "iso:country":"AT",
    "sg:address":"Uferstr 42",
    "sg:city":"Oberndorf",
    "sg:orig_category":"Elektronik",
    "sg:phone":"+43 4362 7255530",
    "sg:postcode":"5110",
    "sg:province":"Salzburg",
    "wof:name":"Forstner Electronics GesmbH",
    "wof:placetype":"venue"
},
  "geometry": {"coordinates":[12.9399595261,47.9383010864],"type":"Point"}
}