{
  "type": "Feature",
  "properties": {
    "addr:full":"Nr 218 Deutsch Goritz Steiermark 8483",
    "addr:postcode":"8483",
    "addr:street":"Nr",
    "iso:country":"AT",
    "sg:address":"Nr 218",
    "sg:city":"Deutsch Goritz",
    "sg:orig_category":"Tischlereien",
    "sg:phone":"+43 3474 8298",
    "sg:postcode":"8483",
    "sg:province":"Steiermark",
    "wof:name":"Tax Werner",
    "wof:placetype":"venue"
},
  "geometry": {"coordinates":[15.8294000626,46.7518081665],"type":"Point"}
}