{
  "type": "Feature",
  "properties": {
    "addr:full":"Bauernfeldstr 29 Graz Steiermark 8020",
    "addr:housenumber":"29",
    "addr:postcode":"8020",
    "addr:street":"Bauernfeldstr",
    "iso:country":"AT",
    "sg:address":"Bauernfeldstr 29",
    "sg:city":"Graz",
    "sg:orig_category":"Innenausbau",
    "sg:phone":"+43 4366 43143847",
    "sg:postcode":"8020",
    "sg:province":"Steiermark",
    "wof:name":"Innenausbau Basic KEG",
    "wof:placetype":"venue"
},
  "geometry": {"coordinates":[15.4012117386,47.0644454956],"type":"Point"}
}