{
  "type": "Feature",
  "properties": {
    "addr:full":"Goldegg 26/14 Wien Wien 1040",
    "addr:housenumber":"26 / 14",
    "addr:postcode":"1040",
    "addr:street":"Goldegg",
    "iso:country":"AT",
    "sg:address":"Goldegg 26/14",
    "sg:city":"Wien",
    "sg:orig_category":"Architekten",
    "sg:phone":"+43 1 5041377",
    "sg:postcode":"1040",
    "sg:province":"Wien",
    "wof:name":"Heistinger Helmut Arch Ing Mag",
    "wof:placetype":"venue"
},
  "geometry": {"coordinates":[16.3754348755,48.1895599365],"type":"Point"}
}