{
  "type": "Feature",
  "properties": {
    "addr:full":"Erzherzog-Carl-Str 11 Deutsch Wagram Nieder\u00f6sterreich 2232",
    "addr:housenumber":"11",
    "addr:postcode":"2232",
    "addr:street":"Erzherzog-Carl-Str",
    "iso:country":"AT",
    "sg:address":"Erzherzog-Carl-Str 11",
    "sg:city":"Deutsch Wagram",
    "sg:orig_category":"Bauunternehmen",
    "sg:phone":"+43 4322 4722050",
    "sg:postcode":"2232",
    "sg:province":"Nieder\u00f6sterreich",
    "wof:name":"Vogl Michael Bauunternehmung u Baustoffwerke GmbH",
    "wof:placetype":"venue"
},
  "geometry": {"coordinates":[16.5568218231,48.2964324951],"type":"Point"}
}