{
  "type": "Feature",
  "properties": {
    "addr:full":"Waldrandweg 10 Velden am W\u00f6rther See K\u00e4rnten 9220",
    "addr:housenumber":"10",
    "addr:postcode":"9220",
    "addr:street":"Waldrandweg;Kaernten",
    "iso:country":"AT",
    "sg:address":"Waldrandweg 10",
    "sg:city":"Velden am W\u00f6rther See",
    "sg:orig_category":"Werbeagenturen",
    "sg:phone":"+43 4342 744990",
    "sg:postcode":"9220",
    "sg:province":"K\u00e4rnten",
    "wof:name":"Arnold Motorsport",
    "wof:placetype":"venue"
},
  "geometry": {"coordinates":[14.0553617477,46.6025733948],"type":"Point"}
}