{
  "type": "Feature",
  "properties": {
    "addr:full":"Boschstr 24/17 Wien Wien 1190",
    "addr:housenumber":"24 / 17",
    "addr:postcode":"1190",
    "addr:street":"Boschstr",
    "iso:country":"AT",
    "sg:address":"Boschstr 24/17",
    "sg:city":"Wien",
    "sg:orig_category":"Tonstudios",
    "sg:phone":"+43 1 3704061",
    "sg:postcode":"1190",
    "sg:province":"Wien",
    "wof:name":"MEIASOUND Smiler Kreativstudio",
    "wof:placetype":"venue"
},
  "geometry": {"coordinates":[16.3660850525,48.2523994446],"type":"Point"}
}