{
  "type": "Feature",
  "properties": {
    "addr:full":"Rokitanskygasse 40/24 Wien Wien 1170",
    "addr:housenumber":"40 / 24",
    "addr:postcode":"1170",
    "addr:street":"Rokitanskygasse",
    "iso:country":"AT",
    "sg:address":"Rokitanskygasse 40/24",
    "sg:city":"Wien",
    "sg:orig_category":"Internet, Alle Internetdienstleistungen",
    "sg:phone":"+43 1 4847725",
    "sg:postcode":"1170",
    "sg:province":"Wien",
    "sg:website":"http://www.HernalsOnline.at/",
    "wof:name":"VIP - Vienna Internet Partners",
    "wof:placetype":"venue"
},
  "geometry": {"coordinates":[16.3310775757,48.2249183655],"type":"Point"}
}