{
  "type": "Feature",
  "properties": {
    "iso:country":"AT",
    "sg:address":"Rainer Str 8a",
    "sg:city":"Wels",
    "sg:orig_category":"Friseure U Frisiersalons",
    "sg:phone":"+43 7242 44739",
    "sg:postcode":"4600",
    "sg:province":"Ober\u00f6sterreich",
    "wof:name":"Salon Continental & Haarboutique Inh Johanna Traunm\u00fcller",
    "wof:placetype":"venue"
},
  "geometry": {"coordinates":[14.0224399567,48.1616172791],"type":"Point"}
}