{
  "type": "Feature",
  "properties": {
    "iso:country":"AT",
    "sg:address":"Marktpl 5",
    "sg:city":"Lambach",
    "sg:orig_category":"Spielwaren U Spiele",
    "sg:phone":"+43 4372 4532237",
    "sg:postcode":"4650",
    "sg:province":"Ober\u00f6sterreich",
    "wof:name":"W\u00f6ss Andrea",
    "wof:placetype":"venue"
},
  "geometry": {"coordinates":[13.873670578,48.0909690857],"type":"Point"}
}