{
  "type": "Feature",
  "properties": {
    "addr:full":"Waldgebiet 636 Rechnitz Burgenland 7471",
    "addr:housenumber":"636",
    "addr:postcode":"7471",
    "iso:country":"AT",
    "sg:address":"Waldgebiet 636",
    "sg:city":"Rechnitz",
    "sg:orig_category":"Forstverwaltungen",
    "sg:phone":"+43 3363 792010",
    "sg:postcode":"7471",
    "sg:province":"Burgenland",
    "wof:name":"Batthyany Christof",
    "wof:placetype":"venue"
},
  "geometry": {"coordinates":[16.4007129669,47.3378410339],"type":"Point"}
}