{
  "type": "Feature",
  "properties": {
    "addr:full":"Hauptpl 6 Gm\u00fcnd K\u00e4rnten 9853",
    "addr:housenumber":"6",
    "addr:postcode":"9853",
    "addr:street":"Hauptpl;Kaernten",
    "iso:country":"AT",
    "sg:address":"Hauptpl 6",
    "sg:city":"Gm\u00fcnd",
    "sg:orig_category":"Bankomat-Standorte",
    "sg:phone":"+43 4732 23100",
    "sg:postcode":"9853",
    "sg:province":"K\u00e4rnten",
    "wof:name":"Bankomat d Raiffeisenbank Liesertal",
    "wof:placetype":"venue"
},
  "geometry": {"coordinates":[13.5357646942,46.9070549011],"type":"Point"}
}