{
  "type": "Feature",
  "properties": {
    "addr:full":"Stadtpl 9 Steyr Ober\u00f6sterreich 4400",
    "addr:housenumber":"9",
    "addr:postcode":"4400",
    "addr:street":"Stadtpl;Oberoesterreich",
    "iso:country":"AT",
    "sg:address":"Stadtpl 9",
    "sg:city":"Steyr",
    "sg:orig_category":"Immobilienmakler",
    "sg:phone":"+43 7252 455930",
    "sg:postcode":"4400",
    "sg:province":"Ober\u00f6sterreich",
    "wof:name":"Alpen Real Immobilienmakler GesmbH",
    "wof:placetype":"venue"
},
  "geometry": {"coordinates":[14.4199953079,48.0398864746],"type":"Point"}
}