{
  "type": "Feature",
  "properties": {
    "iso:country":"AT",
    "sg:address":"Obachgasse 10",
    "sg:city":"Wien",
    "sg:classifiers":[
        {
            "category":"Professional",
            "subcategory":"Advertising",
            "type":"Services"
        }
    ],
    "sg:phone":"+43 1 31917060",
    "sg:postcode":"1220",
    "sg:province":"Wien",
    "sg:tags":[
        "poster"
    ],
    "sg:website":"leukauf.at",
    "wof:name":"Walter Leukauf Ges.m.b.H.",
    "wof:placetype":"venue"
},
  "geometry": {"coordinates":[16.4605827332,48.2556190491],"type":"Point"}
}