{
  "type": "Feature",
  "properties": {
    "addr:full":"Bamberger Amthof Feldkirchen in K\u00e4rnten K\u00e4rnten 9560",
    "addr:postcode":"9560",
    "addr:street":"Amthof;Kaernten",
    "iso:country":"AT",
    "sg:address":"Bamberger Amthof",
    "sg:city":"Feldkirchen in K\u00e4rnten",
    "sg:orig_category":"Musikunterricht",
    "sg:phone":"+43 4342 762169",
    "sg:postcode":"9560",
    "sg:province":"K\u00e4rnten",
    "wof:name":"Bezirksmusikschule Feldkirchen",
    "wof:placetype":"venue"
},
  "geometry": {"coordinates":[14.0920295715,46.7234268188],"type":"Point"}
}