{
  "type": "Feature",
  "properties": {
    "addr:full":"Bucherweg 4 Jochberg Tirol 6373",
    "addr:housenumber":"4",
    "addr:postcode":"6373",
    "addr:street":"Bucherweg;Tirol",
    "iso:country":"AT",
    "sg:address":"Bucherweg 4",
    "sg:city":"Jochberg",
    "sg:orig_category":"Installationsunternehmen",
    "sg:phone":"+43 5355 20060",
    "sg:postcode":"6373",
    "sg:province":"Tirol",
    "wof:name":"Fuchs Hans",
    "wof:placetype":"venue"
},
  "geometry": {"coordinates":[12.4218158722,47.3752403259],"type":"Point"}
}