{
  "type": "Feature",
  "properties": {
    "addr:full":"G\u00f6lsentalstr 59 St. Veit an der G\u00f6lsen Nieder\u00f6sterreich 3161",
    "addr:housenumber":"59",
    "addr:postcode":"3161",
    "addr:street":"Goelsentalstr;Niederoesterreich",
    "iso:country":"AT",
    "sg:address":"G\u00f6lsentalstr 59",
    "sg:city":"St. Veit an der G\u00f6lsen",
    "sg:orig_category":"Fitnesscenter",
    "sg:phone":"+43 4327 633406",
    "sg:postcode":"3161",
    "sg:province":"Nieder\u00f6sterreich",
    "wof:name":"Fitnesscenter Reisenbichler",
    "wof:placetype":"venue"
},
  "geometry": {"coordinates":[15.6694297791,48.0433006287],"type":"Point"}
}