{
  "type": "Feature",
  "properties": {
    "iso:country":"AT",
    "sg:address":"Marktstr 31",
    "sg:city":"Taxenbach",
    "sg:orig_category":"Fleischhauereien",
    "sg:phone":"+43 6543 20345",
    "sg:postcode":"5660",
    "sg:province":"Salzburg",
    "wof:name":"Blersch Hagen",
    "wof:placetype":"venue"
},
  "geometry": {"coordinates":[12.9639863968,47.292755127],"type":"Point"}
}