{
  "type": "Feature",
  "properties": {
    "addr:full":"Kirchbergstr 4 Wilfersdorf Nieder\u00f6sterreich 2193",
    "addr:housenumber":"4",
    "addr:postcode":"2193",
    "addr:street":"Kirchbergstr",
    "iso:country":"AT",
    "sg:address":"Kirchbergstr 4",
    "sg:city":"Wilfersdorf",
    "sg:classifiers":[
        {
            "category":"Home & Garden",
            "subcategory":"Garden Supply",
            "type":"Retail Goods"
        }
    ],
    "sg:phone":"+43 2573 2663",
    "sg:postcode":"2193",
    "sg:province":"Nieder\u00f6sterreich",
    "sg:tags":[
        "schotter",
        "sand",
        "u"
    ],
    "wof:name":"Hofer Franz jun",
    "wof:placetype":"venue"
},
  "geometry": {"coordinates":[16.6396484375,48.5844154358],"type":"Point"}
}