{
  "type": "Feature",
  "properties": {
    "iso:country":"AT",
    "sg:address":"Am Heumarkt 5",
    "sg:city":"Wien",
    "sg:classifiers":[
        {
            "category":"Restaurant",
            "type":"Food & Drink"
        }
    ],
    "sg:phone":"+43 1 713710210",
    "sg:postcode":"1030",
    "sg:province":"Wien",
    "wof:name":"Wirtshaus am Stadtpark",
    "wof:placetype":"venue"
},
  "geometry": {"coordinates":[16.3814544678,48.2027587891],"type":"Point"}
}