{
  "type": "Feature",
  "properties": {
    "addr:full":"Bundesstr 114 Nenzing Vorarlberg 6710",
    "addr:housenumber":"114",
    "addr:postcode":"6710",
    "iso:country":"AT",
    "sg:address":"Bundesstr 114",
    "sg:city":"Nenzing",
    "sg:orig_category":"Fliesen U Platten",
    "sg:phone":"+43 4355 25623950",
    "sg:postcode":"6710",
    "sg:province":"Vorarlberg",
    "sg:website":"beck.at",
    "wof:name":"Fliesen Beck GesmbH & Co KG",
    "wof:placetype":"venue"
},
  "geometry": {"coordinates":[9.7039403915,47.1887016296],"type":"Point"}
}