{
  "type": "Feature",
  "properties": {
    "addr:full":"Liebenauer Hauptstrasse 284 Liebenau Steiermark 8041",
    "addr:housenumber":"284",
    "addr:postcode":"8041",
    "addr:street":"Liebenauer Hauptstrasse",
    "iso:country":"AT",
    "sg:address":"Liebenauer Hauptstrasse 284",
    "sg:city":"Liebenau",
    "sg:classifiers":[
        {
            "category":"Home & Garden",
            "subcategory":"Building Materials",
            "type":"Retail Goods"
        }
    ],
    "sg:phone":"+43 316 401124",
    "sg:postcode":"8041",
    "sg:province":"Steiermark",
    "sg:tags":[
        "glass",
        "enclosures",
        "balcony"
    ],
    "sg:website":"top-10.at/glas/meisl",
    "wof:name":"Glas Meisl Isolierglas Ges.m.b.H.",
    "wof:placetype":"venue"
},
  "geometry": {"coordinates":[15.469291687,47.0227088928],"type":"Point"}
}