{
  "type": "Feature",
  "properties": {
    "iso:country":"AT",
    "sg:address":"Ludwig-Vogl-Str 25d",
    "sg:city":"Mattighofen",
    "sg:orig_category":"Schlossereien",
    "sg:phone":"+43 4377 4231567",
    "sg:postcode":"5230",
    "sg:province":"Ober\u00f6sterreich",
    "wof:name":"Kraus Herbert",
    "wof:placetype":"venue"
},
  "geometry": {"coordinates":[13.1457071304,48.0989112854],"type":"Point"}
}