{
  "type": "Feature",
  "properties": {
    "addr:full":"Vorstadt 3 Oberneukirchen Ober\u00f6sterreich 4181",
    "addr:housenumber":"3",
    "addr:postcode":"4181",
    "addr:street":"Vorstadt",
    "iso:country":"AT",
    "sg:address":"Vorstadt 3",
    "sg:city":"Oberneukirchen",
    "sg:orig_category":"Volksschulen",
    "sg:phone":"+43 7212 7003",
    "sg:postcode":"4181",
    "sg:province":"Ober\u00f6sterreich",
    "wof:name":"Volksschule",
    "wof:placetype":"venue"
},
  "geometry": {"coordinates":[14.2252950668,48.4647903442],"type":"Point"}
}