{
  "type": "Feature",
  "properties": {
    "addr:full":"Mattersburger Str 50 Eisenstadt Burgenland 7000",
    "addr:postcode":"7000",
    "addr:street":"Str 50",
    "iso:country":"AT",
    "sg:address":"Mattersburger Str 50",
    "sg:city":"Eisenstadt",
    "sg:orig_category":"Geschenkartikel",
    "sg:phone":"+43 2682 64418",
    "sg:postcode":"7000",
    "sg:province":"Burgenland",
    "wof:name":"Smile On",
    "wof:placetype":"venue"
},
  "geometry": {"coordinates":[16.5219173431,47.8293647766],"type":"Point"}
}