{
  "type": "Feature",
  "properties": {
    "addr:full":"Hauptpl 1 Liebenfels K\u00e4rnten 9556",
    "addr:housenumber":"1",
    "addr:postcode":"9556",
    "addr:street":"Hauptpl;Kaernten",
    "iso:country":"AT",
    "sg:address":"Hauptpl 1",
    "sg:city":"Liebenfels",
    "sg:orig_category":"Bankomat-Standorte",
    "sg:phone":"+43 4215 22570",
    "sg:postcode":"9556",
    "sg:province":"K\u00e4rnten",
    "wof:name":"Bankomat d Raiffeisen-Bezirksbank St Veit a d Glan-Feldkirchen",
    "wof:placetype":"venue"
},
  "geometry": {"coordinates":[14.2891607285,46.7383956909],"type":"Point"}
}