{
  "type": "Feature",
  "properties": {
    "addr:full":"Maurer Hauptpl 11 Wien Wien 1230",
    "addr:housenumber":"11",
    "addr:postcode":"1230",
    "iso:country":"AT",
    "sg:address":"Maurer Hauptpl 11",
    "sg:city":"Wien",
    "sg:orig_category":"Raumausstattung",
    "sg:phone":"+43 1 8885708",
    "sg:postcode":"1230",
    "sg:province":"Wien",
    "wof:name":"Sch\u00f6rghuber Gertrude",
    "wof:placetype":"venue"
},
  "geometry": {"coordinates":[16.2671794891,48.1510353088],"type":"Point"}
}