{
  "type": "Feature",
  "properties": {
    "addr:full":"Hauptplatz 1 Neuhaus Nieder\u00f6sterreich 2565",
    "addr:housenumber":"1",
    "addr:postcode":"2565",
    "addr:street":"Hauptplatz",
    "iso:country":"AT",
    "sg:address":"Hauptplatz 1",
    "sg:city":"Neuhaus",
    "sg:classifiers":[
        {
            "category":"Home & Garden",
            "subcategory":"Building Materials",
            "type":"Retail Goods"
        }
    ],
    "sg:phone":"+43 2258 25750",
    "sg:postcode":"2565",
    "sg:province":"Nieder\u00f6sterreich",
    "sg:tags":[
        "gravel",
        "crushed"
    ],
    "wof:name":"Leopold Ottersb\u00f6ck Ges.m.b.H.",
    "wof:placetype":"venue"
},
  "geometry": {"coordinates":[16.0459594727,47.9961662292],"type":"Point"}
}