{
  "type": "Feature",
  "properties": {
    "addr:full":"Marktpl 8 Kremsm\u00fcnster Ober\u00f6sterreich 4550",
    "addr:housenumber":"8",
    "addr:postcode":"4550",
    "addr:street":"Marktpl;Oberoesterreich",
    "iso:country":"AT",
    "sg:address":"Marktpl 8",
    "sg:city":"Kremsm\u00fcnster",
    "sg:orig_category":"Bankomat-Standorte",
    "sg:phone":"+43 7583 53550",
    "sg:postcode":"4550",
    "sg:province":"Ober\u00f6sterreich",
    "wof:name":"Bankomat d Raiffeisenbank Kremsm\u00fcnster regGenmbH",
    "wof:placetype":"venue"
},
  "geometry": {"coordinates":[14.1323518753,48.0539398193],"type":"Point"}
}