{
  "type": "Feature",
  "properties": {
    "addr:full":"Freihofgasse 1 Wien Wien 1190",
    "addr:housenumber":"1",
    "addr:postcode":"1190",
    "addr:street":"Freihofgasse",
    "iso:country":"AT",
    "sg:address":"Freihofgasse 1",
    "sg:city":"Wien",
    "sg:classifiers":[
        {
            "category":"Wholesale",
            "subcategory":"Beer",
            "type":"Manufacturing & Wholesale Goods"
        }
    ],
    "sg:phone":"+43 1 37021070",
    "sg:postcode":"1190",
    "sg:province":"Wien",
    "sg:website":"8ung.at/nussdorfer.bier",
    "wof:name":"Nussdorfer Nahrungs- und Genussmittel Ges.m.b.H.",
    "wof:placetype":"venue"
},
  "geometry": {"coordinates":[16.3660182953,48.261177063],"type":"Point"}
}