{
  "type": "Feature",
  "properties": {
    "iso:country":"AT",
    "sg:address":"Steinerstr 244",
    "sg:city":"Wals",
    "sg:classifiers":[
        {
            "category":"Home & Garden",
            "subcategory":"Garden Supply",
            "type":"Retail Goods"
        }
    ],
    "sg:phone":"+43 4366 2852284",
    "sg:postcode":"5071",
    "sg:province":"Salzburg",
    "sg:tags":[
        "schotter",
        "sand",
        "u"
    ],
    "wof:name":"Kies Trans GesmbH",
    "wof:placetype":"venue"
},
  "geometry": {"coordinates":[12.9561634064,47.7883682251],"type":"Point"}
}