{
  "type": "Feature",
  "properties": {
    "addr:full":"Franz-Martin-Strasse 2  Salzburg Salzburg 5020",
    "addr:housenumber":"2",
    "addr:postcode":"5020",
    "addr:street":"Franz-Martin-Strasse;Salzburg",
    "iso:country":"AT",
    "sg:address":"Franz-Martin-Strasse 2 ",
    "sg:city":"Salzburg",
    "sg:classifiers":[
        {
            "category":"Structure",
            "subcategory":"Tower",
            "type":"Public Place"
        }
    ],
    "sg:phone":"+43 662 432481",
    "sg:postcode":"5020",
    "sg:province":"Salzburg",
    "sg:tags":[
        "awning",
        "marquee"
    ],
    "wof:name":"Meinhart Sonnenschutzanlagen",
    "wof:placetype":"venue"
},
  "geometry": {"coordinates":[13.0349321365,47.8163948059],"type":"Point"}
}