{
  "type": "Feature",
  "properties": {
    "iso:country":"AT",
    "sg:address":"Korntheuerg 3",
    "sg:city":"Wien",
    "sg:orig_category":"Autoreparatur",
    "sg:phone":"+43 1 3681345",
    "sg:postcode":"1190",
    "sg:province":"Wien",
    "wof:name":"Rupp Herbert GesmbH",
    "wof:placetype":"venue"
},
  "geometry": {"coordinates":[16.3628253937,48.2447357178],"type":"Point"}
}