{
  "type": "Feature",
  "properties": {
    "addr:full":"Windm\u00fchlg 9 Wien Wien 1060",
    "addr:housenumber":"9",
    "addr:postcode":"1060",
    "addr:street":"Windmuehlg",
    "iso:country":"AT",
    "sg:address":"Windm\u00fchlg 9",
    "sg:city":"Wien",
    "sg:orig_category":"Bergsportartikel",
    "sg:phone":"+43 1 5875787",
    "sg:postcode":"1060",
    "sg:province":"Wien",
    "wof:name":"M\u00f6rtz R Inh L Riedl",
    "wof:placetype":"venue"
},
  "geometry": {"coordinates":[16.3504657745,48.1947135925],"type":"Point"}
}