{
  "type": "Feature",
  "properties": {
    "iso:country":"AT",
    "sg:address":"Buchauerstrasse 104",
    "sg:city":"St. Gallen",
    "sg:orig_category":"Assembly Of Plastic Modules",
    "sg:phone":"+43 3632 522",
    "sg:postcode":"8933",
    "sg:province":"Steiermark",
    "sg:website":"hkt.st",
    "wof:name":"HAIDER Kunststofftechnik GmbH",
    "wof:placetype":"venue"
},
  "geometry": {"coordinates":[14.6177816391,47.6849517822],"type":"Point"}
}