{
  "type": "Feature",
  "properties": {
    "iso:country":"AT",
    "sg:address":"Bundesstr 25",
    "sg:city":"Arbing",
    "sg:orig_category":"Autohandel",
    "sg:phone":"+43 7269 75800",
    "sg:postcode":"4341",
    "sg:province":"Ober\u00f6sterreich",
    "wof:name":"Panhofer Auto GesmbH",
    "wof:placetype":"venue"
},
  "geometry": {"coordinates":[14.7029752731,48.2269172668],"type":"Point"}
}