{
  "type": "Feature",
  "properties": {
    "iso:country":"AT",
    "sg:address":"Sch\u00f6rgelg 10",
    "sg:city":"Graz",
    "sg:orig_category":"Friseure U Frisiersalons",
    "sg:phone":"+43 4331 6829414",
    "sg:postcode":"8010",
    "sg:province":"Steiermark",
    "wof:name":"Salon Schnittpunkt",
    "wof:placetype":"venue"
},
  "geometry": {"coordinates":[15.4493017197,47.0663032532],"type":"Point"}
}