{
  "type": "Feature",
  "properties": {
    "addr:full":"Merangasse 70 Graz Steiermark 8010",
    "addr:housenumber":"70",
    "addr:postcode":"8010",
    "addr:street":"Merangasse",
    "iso:country":"AT",
    "sg:address":"Merangasse 70",
    "sg:city":"Graz",
    "sg:orig_category":"Internet, Internetmagazine - Ezine",
    "sg:phone":"+43 4331 6388301",
    "sg:postcode":"8010",
    "sg:province":"Steiermark",
    "sg:website":"http://www.freeyellow.com/members2/expertinfo",
    "wof:name":"BUSINESS KONZEPT",
    "wof:placetype":"venue"
},
  "geometry": {"coordinates":[15.4573450089,47.071018219],"type":"Point"}
}