{
  "type": "Feature",
  "properties": {
    "addr:full":"Boschstrasse 24/10 Wien Wien 1190",
    "addr:housenumber":"24 / 10",
    "addr:postcode":"1190",
    "addr:street":"Boschstrasse",
    "iso:country":"AT",
    "sg:address":"Boschstrasse 24/10",
    "sg:city":"Wien",
    "sg:classifiers":[
        {
            "category":"Autos & Motor Vehicles",
            "subcategory":"Fuel & Gas Station",
            "type":"Retail Goods"
        }
    ],
    "sg:phone":"+43 1 3703688",
    "sg:postcode":"1190",
    "sg:province":"Wien",
    "sg:tags":[
        "appliance",
        "heating"
    ],
    "wof:name":"Ing. Friedrich Jiranek",
    "wof:placetype":"venue"
},
  "geometry": {"coordinates":[16.3660850525,48.2523994446],"type":"Point"}
}