{
  "type": "Feature",
  "properties": {
    "iso:country":"AT",
    "sg:address":"Salzburger Str 323",
    "sg:city":"Linz",
    "sg:orig_category":"Holdinggesellschaften",
    "sg:phone":"+43 4373 237310",
    "sg:postcode":"4030",
    "sg:province":"Ober\u00f6sterreich",
    "wof:name":"BRVZ Bau- Rechen- u Verwaltungszentrum GesmbH",
    "wof:placetype":"venue"
},
  "geometry": {"coordinates":[14.2728939056,48.2506256104],"type":"Point"}
}