{
  "type": "Feature",
  "properties": {
    "addr:full":"Salzburger Str 16 St. Johann im Pongau Salzburg 5600",
    "addr:housenumber":"16",
    "addr:postcode":"5600",
    "addr:street":"Salzburger Str;Salzburg",
    "iso:country":"AT",
    "sg:address":"Salzburger Str 16",
    "sg:city":"St. Johann im Pongau",
    "sg:classifiers":[
        {
            "category":"Restaurant",
            "type":"Food & Drink"
        }
    ],
    "sg:phone":"+43 6412 4834",
    "sg:postcode":"5600",
    "sg:province":"Salzburg",
    "wof:name":"Kika Buffet",
    "wof:placetype":"venue"
},
  "geometry": {"coordinates":[13.2004003525,47.3573570251],"type":"Point"}
}