{
  "type": "Feature",
  "properties": {
    "iso:country":"AT",
    "sg:address":"Gewerbeparkstr 3",
    "sg:city":"Gr\u00fcnbach am Schneeberg",
    "sg:orig_category":"Reifen U Reifendienste",
    "sg:phone":"+43 2637 3171",
    "sg:postcode":"2733",
    "sg:province":"Nieder\u00f6sterreich",
    "wof:name":"Reifen Pfalzer",
    "wof:placetype":"venue"
},
  "geometry": {"coordinates":[15.989030838,47.7962532043],"type":"Point"}
}