{
  "type": "Feature",
  "properties": {
    "addr:full":"Johann-Puch-Str 5 Steyr Ober\u00f6sterreich 4400",
    "addr:housenumber":"5",
    "addr:postcode":"4400",
    "addr:street":"Johann-Puch-Str;Oberoesterreich",
    "iso:country":"AT",
    "sg:address":"Johann-Puch-Str 5",
    "sg:city":"Steyr",
    "sg:orig_category":"\u00c3\u201erzte / F Allgemeinmedizin",
    "sg:phone":"+43 7252 72024",
    "sg:postcode":"4400",
    "sg:province":"Ober\u00f6sterreich",
    "wof:name":"Schlo\u00dfbauer Gerhard Dr",
    "wof:placetype":"venue"
},
  "geometry": {"coordinates":[14.4212627411,48.0500450134],"type":"Point"}
}