{
  "type": "Feature",
  "properties": {
    "iso:country":"AT",
    "sg:address":"Elterleinpl 4",
    "sg:city":"Wien",
    "sg:orig_category":"Notare",
    "sg:phone":"+43 1 40777770",
    "sg:postcode":"1170",
    "sg:province":"Wien",
    "wof:name":"\u00d6ffentliche Notare - Berger - Lunzer - Wimmer Partnerschaft",
    "wof:placetype":"venue"
},
  "geometry": {"coordinates":[16.331987381,48.2179412842],"type":"Point"}
}