{
  "type": "Feature",
  "properties": {
    "addr:full":"Hans-Steger-G 12/16 Wien Wien 1220",
    "addr:housenumber":"12 / 16",
    "addr:postcode":"1220",
    "addr:street":"Hans-Steger-G",
    "iso:country":"AT",
    "sg:address":"Hans-Steger-G 12/16",
    "sg:city":"Wien",
    "sg:classifiers":[
        {
            "category":"Professional",
            "subcategory":"Computer Services",
            "type":"Services"
        }
    ],
    "sg:phone":"+43 4365 07519858",
    "sg:postcode":"1220",
    "sg:province":"Wien",
    "sg:tags":[
        "software"
    ],
    "wof:name":"INTERSOFT KEG",
    "wof:placetype":"venue"
},
  "geometry": {"coordinates":[16.4547176361,48.2253837585],"type":"Point"}
}