{
  "type": "Feature",
  "properties": {
    "iso:country":"AT",
    "sg:address":"Sauerbrunnstr 61",
    "sg:city":"Stainz",
    "sg:classifiers":[
        {
            "category":"Internet Cafe",
            "subcategory":"None",
            "type":"Food & Drink"
        }
    ],
    "sg:phone":"+43 3463 70051",
    "sg:postcode":"8510",
    "sg:province":"Steiermark",
    "wof:name":"symlink - Christian Bretterklieber",
    "wof:placetype":"venue"
},
  "geometry": {"coordinates":[15.253455162,46.8979682922],"type":"Point"}
}