{
  "type": "Feature",
  "properties": {
    "addr:full":"Nr 26 St. Kanzian am Klopeiner See K\u00e4rnten 9122",
    "addr:postcode":"9122",
    "addr:street":"Nr 26;Kaernten",
    "iso:country":"AT",
    "sg:address":"Nr 26",
    "sg:city":"St. Kanzian am Klopeiner See",
    "sg:orig_category":"Pensionen / Privatzimmer",
    "sg:phone":"+43 4239 2569",
    "sg:postcode":"9122",
    "sg:province":"K\u00e4rnten",
    "wof:name":"Pension Weitendorferhof",
    "wof:placetype":"venue"
},
  "geometry": {"coordinates":[14.5756397247,46.6140594482],"type":"Point"}
}