{
  "type": "Feature",
  "properties": {
    "addr:full":"Josef Wolfik-Str 5 Stockerau Nieder\u00f6sterreich 2000",
    "addr:housenumber":"5",
    "addr:postcode":"2000",
    "addr:street":"Wolfik-Str",
    "iso:country":"AT",
    "sg:address":"Josef Wolfik-Str 5",
    "sg:city":"Stockerau",
    "sg:orig_category":"Offsetdruckereien",
    "sg:phone":"+43 2266 63243",
    "sg:postcode":"2000",
    "sg:province":"Nieder\u00f6sterreich",
    "wof:name":"Druck & Copie Typesetter Christiane B\u00f6ck",
    "wof:placetype":"venue"
},
  "geometry": {"coordinates":[16.2063541412,48.3844337463],"type":"Point"}
}