{
  "type": "Feature",
  "properties": {
    "addr:full":"Holdernach 292 Kappl Tirol 6555",
    "addr:housenumber":"292",
    "addr:postcode":"6555",
    "addr:street":"Holdernach;Tirol",
    "iso:country":"AT",
    "sg:address":"Holdernach 292",
    "sg:city":"Kappl",
    "sg:orig_category":"Fliesen U Platten",
    "sg:phone":"+43 5445 6155",
    "sg:postcode":"6555",
    "sg:province":"Tirol",
    "wof:name":"Schmid Rudolf GesmbH",
    "wof:placetype":"venue"
},
  "geometry": {"coordinates":[10.421710968,47.0746383667],"type":"Point"}
}