{
  "type": "Feature",
  "properties": {
    "iso:country":"AT",
    "sg:address":"Nr 42",
    "sg:city":"Zissersdorf",
    "sg:orig_category":"Schaukastensysteme",
    "sg:phone":"+43 4329 1588380",
    "sg:postcode":"2094",
    "sg:province":"Nieder\u00f6sterreich",
    "wof:name":"Alpenland Schaukastensysteme",
    "wof:placetype":"venue"
},
  "geometry": {"coordinates":[15.580288887,48.8460426331],"type":"Point"}
}