{
  "type": "Feature",
  "properties": {
    "iso:country":"AT",
    "sg:address":"Rehweg 8",
    "sg:city":"Drobollach am Faaker See",
    "sg:orig_category":"Pensionen / Privatzimmer",
    "sg:phone":"+43 4342 543476",
    "sg:postcode":"9580",
    "sg:province":"K\u00e4rnten",
    "wof:name":"Baumann Josefine",
    "wof:placetype":"venue"
},
  "geometry": {"coordinates":[13.9087610245,46.5913658142],"type":"Point"}
}