{
  "type": "Feature",
  "properties": {
    "iso:country":"AT",
    "sg:address":"Ro\u00dfmarkt 5",
    "sg:city":"Wolfsegg am Hausruck",
    "sg:orig_category":"Tischlereien",
    "sg:phone":"+43 76767334",
    "sg:postcode":"4902",
    "sg:province":"Ober\u00f6sterreich",
    "wof:name":"Kinberger Ludwig",
    "wof:placetype":"venue"
},
  "geometry": {"coordinates":[13.6748504639,48.1072502136],"type":"Point"}
}