{
  "type": "Feature",
  "properties": {
    "addr:full":"Am Bahnhof 26 Wies Steiermark 8551",
    "addr:housenumber":"26",
    "addr:postcode":"8551",
    "addr:street":"Am Bahnhof",
    "iso:country":"AT",
    "sg:address":"Am Bahnhof 26",
    "sg:city":"Wies",
    "sg:orig_category":"Anlagenbau U -Technik",
    "sg:phone":"+43 4334 652513",
    "sg:postcode":"8551",
    "sg:province":"Steiermark",
    "wof:name":"K\u00f6rner Chemieanlagenbau GesmbH",
    "wof:placetype":"venue"
},
  "geometry": {"coordinates":[15.2578115463,46.7189331055],"type":"Point"}
}