{
  "type": "Feature",
  "properties": {
    "addr:full":"Greith 35 Kitzeck im Sausal Steiermark 8442",
    "addr:housenumber":"35",
    "addr:postcode":"8442",
    "addr:street":"Greith",
    "iso:country":"AT",
    "sg:address":"Greith 35",
    "sg:city":"Kitzeck im Sausal",
    "sg:orig_category":"Appartements / Ferienwohnungen",
    "sg:phone":"+43 4334 563064",
    "sg:postcode":"8442",
    "sg:province":"Steiermark",
    "wof:name":"Schwarz Hans u Rosemarie",
    "wof:placetype":"venue"
},
  "geometry": {"coordinates":[15.4475059509,46.7878723145],"type":"Point"}
}