{
  "type": "Feature",
  "properties": {
    "addr:full":"H\u00f6henstr 70 Telfs Tirol 6410",
    "addr:housenumber":"70",
    "addr:postcode":"6410",
    "addr:street":"Hoehenstr;Tirol",
    "iso:country":"AT",
    "sg:address":"H\u00f6henstr 70",
    "sg:city":"Telfs",
    "sg:orig_category":"Mineralien",
    "sg:phone":"+43 4366 45165885",
    "sg:postcode":"6410",
    "sg:province":"Tirol",
    "wof:name":"Hausen Christian",
    "wof:placetype":"venue"
},
  "geometry": {"coordinates":[11.0733299255,47.3195304871],"type":"Point"}
}