{
  "type": "Feature",
  "properties": {
    "addr:full":"Universit\u00e4tsstr 98Top 3 Klagenfurt K\u00e4rnten 9020",
    "addr:housenumber":"3",
    "addr:postcode":"9020",
    "addr:street":"Kaernten",
    "iso:country":"AT",
    "sg:address":"Universit\u00e4tsstr 98Top 3",
    "sg:city":"Klagenfurt",
    "sg:orig_category":"Friseure U Frisiersalons",
    "sg:phone":"+43 463 25686",
    "sg:postcode":"9020",
    "sg:province":"K\u00e4rnten",
    "wof:name":"Naturfriseur",
    "wof:placetype":"venue"
},
  "geometry": {"coordinates":[14.2678461075,46.6179847717],"type":"Point"}
}