{
  "type": "Feature",
  "properties": {
    "addr:full":"Hainfelder Str 16 Pottenstein Nieder\u00f6sterreich 2563",
    "addr:postcode":"2563",
    "addr:street":"Str 16",
    "iso:country":"AT",
    "sg:address":"Hainfelder Str 16",
    "sg:city":"Pottenstein",
    "sg:orig_category":"Fleischhauereien",
    "sg:phone":"+43 2672 82415",
    "sg:postcode":"2563",
    "sg:province":"Nieder\u00f6sterreich",
    "wof:name":"Hoppel Johann",
    "wof:placetype":"venue"
},
  "geometry": {"coordinates":[16.0947227478,47.9603347778],"type":"Point"}
}