{
  "type": "Feature",
  "properties": {
    "addr:full":"Franzosengraben 4 Wien Wien 1030",
    "addr:housenumber":"4",
    "addr:postcode":"1030",
    "addr:street":"Franzosengraben",
    "iso:country":"AT",
    "sg:address":"Franzosengraben 4",
    "sg:city":"Wien",
    "sg:orig_category":"Reifen U Reifendienste",
    "sg:phone":"+43 1 79844880",
    "sg:postcode":"1030",
    "sg:province":"Wien",
    "sg:website":"www.reifenkohout.at",
    "wof:name":"Reifen Kohout GesmbH & Co KG",
    "wof:placetype":"venue"
},
  "geometry": {"coordinates":[16.41472435,48.1888961792],"type":"Point"}
}