{
  "type": "Feature",
  "properties": {
    "iso:country":"AT",
    "sg:address":"G\u00fcrtel 21",
    "sg:city":"Scheibbs",
    "sg:orig_category":"Nachhilfe U Lernbetreuung",
    "sg:phone":"+43 4374 824300450",
    "sg:postcode":"3270",
    "sg:province":"Nieder\u00f6sterreich",
    "wof:name":"Hilfswerk \u00f6tscherland - Rund ums Lernen",
    "wof:placetype":"venue"
},
  "geometry": {"coordinates":[15.1676197052,48.0055198669],"type":"Point"}
}