{
  "type": "Feature",
  "properties": {
    "addr:full":"Josef Mayburger Kai 114  Salzburg Salzburg 5020",
    "addr:housenumber":"114",
    "addr:postcode":"5020",
    "addr:street":"Kai;Salzburg",
    "iso:country":"AT",
    "sg:address":"Josef Mayburger Kai 114 ",
    "sg:city":"Salzburg",
    "sg:classifiers":[
        {
            "category":"Food & Beverages",
            "subcategory":"Bakery",
            "type":"Retail Goods"
        }
    ],
    "sg:phone":"+43 4366 24583510",
    "sg:postcode":"5020",
    "sg:province":"Salzburg",
    "sg:tags":[
        "grain",
        "cereal"
    ],
    "wof:name":"CAMBRIDGE DI\u00c4T VERTRIEB GMBH",
    "wof:placetype":"venue"
},
  "geometry": {"coordinates":[13.0350046158,47.8218040466],"type":"Point"}
}