{
  "type": "Feature",
  "properties": {
    "addr:full":"Hauptstr 75 Grafenstein K\u00e4rnten 9131",
    "addr:housenumber":"75",
    "addr:postcode":"9131",
    "addr:street":"Hauptstr;Kaernten",
    "iso:country":"AT",
    "sg:address":"Hauptstr 75",
    "sg:city":"Grafenstein",
    "sg:orig_category":"Rauchfangkehrer",
    "sg:phone":"+43 4225 2291",
    "sg:postcode":"9131",
    "sg:province":"K\u00e4rnten",
    "wof:name":"Gritsch Heribert",
    "wof:placetype":"venue"
},
  "geometry": {"coordinates":[14.4651279449,46.6134376526],"type":"Point"}
}