{
  "type": "Feature",
  "properties": {
    "addr:full":"Kirchbergg 7/2 Wien Wien 1070",
    "addr:housenumber":"7 / 2",
    "addr:postcode":"1070",
    "addr:street":"Kirchbergg",
    "iso:country":"AT",
    "sg:address":"Kirchbergg 7/2",
    "sg:city":"Wien",
    "sg:classifiers":[
        {
            "category":"Organizations",
            "subcategory":"Community Association",
            "type":"Services"
        }
    ],
    "sg:phone":"+43 1 5856069",
    "sg:postcode":"1070",
    "sg:province":"Wien",
    "sg:tags":[
        "relation",
        "public"
    ],
    "wof:name":"SCIENCE COMMUNICATIONS - Sch\u00fctz & Martos GmbH",
    "wof:placetype":"venue"
},
  "geometry": {"coordinates":[16.356004715,48.2028388977],"type":"Point"}
}