{
  "type": "Feature",
  "properties": {
    "addr:full":"Unterer Plattenweg 30 Kroisbach Steiermark 8043",
    "addr:housenumber":"30",
    "addr:postcode":"8043",
    "addr:street":"Unterer Plattenweg",
    "iso:country":"AT",
    "sg:address":"Unterer Plattenweg 30",
    "sg:city":"Kroisbach",
    "sg:orig_category":"Ingenieurkonsulenten / Zivilingenieure",
    "sg:phone":"+43 316 3839420",
    "sg:postcode":"8043",
    "sg:province":"Steiermark",
    "wof:name":"Fidler Gerhard Dipl-Ing",
    "wof:placetype":"venue"
},
  "geometry": {"coordinates":[15.4597177505,47.0943412781],"type":"Point"}
}