{
  "type": "Feature",
  "properties": {
    "addr:full":"B\u00fcrgerspitalgasse 28 Wien Wien 1060",
    "addr:housenumber":"28",
    "addr:postcode":"1060",
    "addr:street":"Buergerspitalgasse",
    "iso:country":"AT",
    "sg:address":"B\u00fcrgerspitalgasse 28",
    "sg:city":"Wien",
    "sg:classifiers":[
        {
            "category":"Professional",
            "subcategory":"Art Services",
            "type":"Services"
        }
    ],
    "sg:phone":"+43 1 59713020",
    "sg:postcode":"1060",
    "sg:province":"Wien",
    "sg:tags":[
        "agency",
        "artist"
    ],
    "sg:website":"swingtime-entertainment.com",
    "wof:name":"Neuer Ges.m.b.H.",
    "wof:placetype":"venue"
},
  "geometry": {"coordinates":[16.3504657745,48.1947135925],"type":"Point"}
}