{
  "type": "Feature",
  "properties": {
    "addr:full":"Laubenbachgegend 3 Frankenfels Nieder\u00f6sterreich 3213",
    "addr:housenumber":"3",
    "addr:postcode":"3213",
    "addr:street":"Laubenbachgegend;Niederoesterreich",
    "iso:country":"AT",
    "sg:address":"Laubenbachgegend 3",
    "sg:city":"Frankenfels",
    "sg:classifiers":[
        {
            "category":"Manufacturing",
            "subcategory":"Wood Products",
            "type":"Manufacturing & Wholesale Goods"
        }
    ],
    "sg:phone":"+43 2725 280",
    "sg:postcode":"3213",
    "sg:province":"Nieder\u00f6sterreich",
    "sg:tags":[
        "lumber"
    ],
    "sg:website":"firma-gabauer.at",
    "wof:name":"Gabauer Ges.m.b.H.",
    "wof:placetype":"venue"
},
  "geometry": {"coordinates":[15.2800912857,47.959072113],"type":"Point"}
}