{
  "type": "Feature",
  "properties": {
    "addr:full":"Neustiftg 7 Zillingtal Burgenland 7034",
    "addr:housenumber":"7",
    "addr:postcode":"7034",
    "addr:street":"Neustiftg",
    "iso:country":"AT",
    "sg:address":"Neustiftg 7",
    "sg:city":"Zillingtal",
    "sg:orig_category":"Handelsagenturen",
    "sg:phone":"+43 664 4328390",
    "sg:postcode":"7034",
    "sg:province":"Burgenland",
    "wof:name":"Handelsagentur Ekart",
    "wof:placetype":"venue"
},
  "geometry": {"coordinates":[16.40284729,47.8129882812],"type":"Point"}
}