{
  "type": "Feature",
  "properties": {
    "addr:full":"Laudachweg 14 Vorchdorf Ober\u00f6sterreich 4655",
    "addr:housenumber":"14",
    "addr:postcode":"4655",
    "addr:street":"Laudachweg",
    "iso:country":"AT",
    "sg:address":"Laudachweg 14",
    "sg:city":"Vorchdorf",
    "sg:orig_category":"Freizeitangebote U -Einrichtungen",
    "sg:phone":"+43 761471776",
    "sg:postcode":"4655",
    "sg:province":"Ober\u00f6sterreich",
    "wof:name":"Jugendzentrum Vorchdorf",
    "wof:placetype":"venue"
},
  "geometry": {"coordinates":[13.9226808548,47.9999885559],"type":"Point"}
}