{
  "type": "Feature",
  "properties": {
    "addr:full":"Hunnenweg 3 Eisenstadt Burgenland 7000",
    "addr:housenumber":"3",
    "addr:postcode":"7000",
    "addr:street":"Hunnenweg",
    "iso:country":"AT",
    "sg:address":"Hunnenweg 3",
    "sg:city":"Eisenstadt",
    "sg:orig_category":"Werbeagenturen",
    "sg:phone":"+43 699 10810410",
    "sg:postcode":"7000",
    "sg:province":"Burgenland",
    "wof:name":"MONDWERK grafik.typographie.illustration",
    "wof:placetype":"venue"
},
  "geometry": {"coordinates":[16.5434608459,47.8507118225],"type":"Point"}
}