{
  "type": "Feature",
  "properties": {
    "addr:full":"Waltherg 17 Wiener Neustadt Nieder\u00f6sterreich 2700",
    "addr:housenumber":"17",
    "addr:postcode":"2700",
    "addr:street":"Waltherg",
    "iso:country":"AT",
    "sg:address":"Waltherg 17",
    "sg:city":"Wiener Neustadt",
    "sg:orig_category":"Physiotherapie",
    "sg:phone":"+43 2622 66872",
    "sg:postcode":"2700",
    "sg:province":"Nieder\u00f6sterreich",
    "wof:name":"Kusebauch-Galley Sylvia Dipl-PT",
    "wof:placetype":"venue"
},
  "geometry": {"coordinates":[16.2389583588,47.8065299988],"type":"Point"}
}