{
  "type": "Feature",
  "properties": {
    "iso:country":"AT",
    "sg:address":"Rohrbacher Str 58",
    "sg:city":"Neunkirchen",
    "sg:orig_category":"Glasereien",
    "sg:phone":"+43 2635 6195913",
    "sg:postcode":"2620",
    "sg:province":"Nieder\u00f6sterreich",
    "wof:name":"Rigler Helmut GesmbH",
    "wof:placetype":"venue"
},
  "geometry": {"coordinates":[16.0727100372,47.7270965576],"type":"Point"}
}