{
  "type": "Feature",
  "properties": {
    "addr:full":"Reichholz 5 Weyregg am Attersee Ober\u00f6sterreich 4852",
    "addr:housenumber":"5",
    "addr:postcode":"4852",
    "addr:street":"Reichholz",
    "iso:country":"AT",
    "sg:address":"Reichholz 5",
    "sg:city":"Weyregg am Attersee",
    "sg:orig_category":"Appartements / Ferienwohnungen",
    "sg:phone":"+43 76642833",
    "sg:postcode":"4852",
    "sg:province":"Ober\u00f6sterreich",
    "wof:name":"Oberperfler Johann",
    "wof:placetype":"venue"
},
  "geometry": {"coordinates":[13.5808563232,47.8892097473],"type":"Point"}
}