{
  "type": "Feature",
  "properties": {
    "addr:full":"Nr 170 St. Michael im Burgenland Burgenland 7535",
    "addr:postcode":"7535",
    "addr:street":"Nr 170",
    "iso:country":"AT",
    "sg:address":"Nr 170",
    "sg:city":"St. Michael im Burgenland",
    "sg:orig_category":"Appartements / Ferienwohnungen",
    "sg:phone":"+43 4333 272880",
    "sg:postcode":"7535",
    "sg:province":"Burgenland",
    "wof:name":"Ferienwohnungen Frey",
    "wof:placetype":"venue"
},
  "geometry": {"coordinates":[16.2269554138,47.1333656311],"type":"Point"}
}