{
  "type": "Feature",
  "properties": {
    "iso:country":"AT",
    "sg:address":"Dresdner Str 114",
    "sg:city":"Wien",
    "sg:orig_category":"Medizintechnik",
    "sg:phone":"+43 1 3742650",
    "sg:postcode":"1200",
    "sg:province":"Wien",
    "wof:name":"INTEC Medizintechnik GmbH",
    "wof:placetype":"venue"
},
  "geometry": {"coordinates":[16.3852500916,48.231716156],"type":"Point"}
}