{
  "type": "Feature",
  "properties": {
    "addr:full":"Defreggerstr 27 Innsbruck Tirol 6020",
    "addr:housenumber":"27",
    "addr:postcode":"6020",
    "addr:street":"Defreggerstr;Tirol",
    "iso:country":"AT",
    "sg:address":"Defreggerstr 27",
    "sg:city":"Innsbruck",
    "sg:orig_category":"Reinigungsservice",
    "sg:phone":"+43 512 341433",
    "sg:postcode":"6020",
    "sg:province":"Tirol",
    "wof:name":"Geb\u00e4udereinigung Moser",
    "wof:placetype":"venue"
},
  "geometry": {"coordinates":[11.4103431702,47.2654762268],"type":"Point"}
}