{
  "type": "Feature",
  "properties": {
    "iso:country":"AT",
    "sg:address":"Dorfweg 9",
    "sg:city":"Hall in Tirol",
    "sg:classifiers":[
        {
            "category":"Banks & Credit Unions",
            "subcategory":"Investment Brokerage",
            "type":"Services"
        }
    ],
    "sg:phone":"+43 512 347018",
    "sg:postcode":"6060",
    "sg:province":"Tirol",
    "sg:tags":[
        "absorption",
        "refrigerator"
    ],
    "sg:website":"sparer.com",
    "wof:name":"Edmund Sparer",
    "wof:placetype":"venue"
},
  "geometry": {"coordinates":[11.5065698624,47.2818107605],"type":"Point"}
}