{
  "type": "Feature",
  "properties": {
    "addr:full":"Dorfpl 3a Zell am Ziller Tirol 6280",
    "addr:housenumber":"3a",
    "addr:postcode":"6280",
    "addr:street":"Dorfpl;Tirol",
    "iso:country":"AT",
    "sg:address":"Dorfpl 3a",
    "sg:city":"Zell am Ziller",
    "sg:orig_category":"Apotheken",
    "sg:phone":"+43 4352 8226410",
    "sg:postcode":"6280",
    "sg:province":"Tirol",
    "wof:name":"Apotheke Gerlosstein Mag pharm E Kienzl KG",
    "wof:placetype":"venue"
},
  "geometry": {"coordinates":[11.882062912,47.2332878113],"type":"Point"}
}