{
  "type": "Feature",
  "properties": {
    "addr:full":"Walchegg 2 Vorderstoder Ober\u00f6sterreich 4574",
    "addr:housenumber":"2",
    "addr:postcode":"4574",
    "addr:street":"Walchegg",
    "iso:country":"AT",
    "sg:address":"Walchegg 2",
    "sg:city":"Vorderstoder",
    "sg:orig_category":"Pensionen / Privatzimmer",
    "sg:phone":"+43 7562 7669",
    "sg:postcode":"4574",
    "sg:province":"Ober\u00f6sterreich",
    "wof:name":"Ferienhof Kernhof Fam Lotter",
    "wof:placetype":"venue"
},
  "geometry": {"coordinates":[14.2017669678,47.7264251709],"type":"Point"}
}