{
  "type": "Feature",
  "properties": {
    "addr:full":"Steinhof 81 Berndorf Nieder\u00f6sterreich 2560",
    "addr:housenumber":"81",
    "addr:postcode":"2560",
    "addr:street":"Steinhof",
    "iso:country":"AT",
    "sg:address":"Steinhof 81",
    "sg:city":"Berndorf",
    "sg:classifiers":[
        {
            "category":"Home & Garden",
            "subcategory":"Building Materials",
            "type":"Retail Goods"
        }
    ],
    "sg:phone":"+43 2672 823620",
    "sg:postcode":"2560",
    "sg:province":"Nieder\u00f6sterreich",
    "sg:tags":[
        "gravel",
        "crushed"
    ],
    "wof:name":"Dolomitsandwerk GmbH & Co KG",
    "wof:placetype":"venue"
},
  "geometry": {"coordinates":[16.090341568,47.936832428],"type":"Point"}
}