{
  "type": "Feature",
  "properties": {
    "addr:full":"Kohlpl 10 Reutte Tirol 6600",
    "addr:housenumber":"10",
    "addr:postcode":"6600",
    "addr:street":"Kohlpl;Tirol",
    "iso:country":"AT",
    "sg:address":"Kohlpl 10",
    "sg:city":"Reutte",
    "sg:orig_category":"Spenglereien",
    "sg:phone":"+43 5672 71732",
    "sg:postcode":"6600",
    "sg:province":"Tirol",
    "wof:name":"Strigl Reinhard",
    "wof:placetype":"venue"
},
  "geometry": {"coordinates":[10.7174072266,47.5068626404],"type":"Point"}
}