{
  "type": "Feature",
  "properties": {
    "addr:full":"Mandellstr 3/II Graz Steiermark 8010",
    "addr:housenumber":"3 / ii",
    "addr:postcode":"8010",
    "addr:street":"Mandellstr",
    "iso:country":"AT",
    "sg:address":"Mandellstr 3/II",
    "sg:city":"Graz",
    "sg:orig_category":"Beratungsstellen",
    "sg:phone":"+43 316 8298760",
    "sg:postcode":"8010",
    "sg:province":"Steiermark",
    "wof:name":"Schulpsychologische Beratungsstelle d Landesschulrates f Stmk",
    "wof:placetype":"venue"
},
  "geometry": {"coordinates":[15.4431800842,47.0685653687],"type":"Point"}
}