{
  "type": "Feature",
  "properties": {
    "addr:full":"Anna-Hensler-Str 17 Klaus-Weiler Vorarlberg 6833",
    "addr:housenumber":"17",
    "addr:postcode":"6833",
    "addr:street":"Anna-Hensler-Str",
    "iso:country":"AT",
    "sg:address":"Anna-Hensler-Str 17",
    "sg:city":"Klaus-Weiler",
    "sg:orig_category":"Volksschulen",
    "sg:phone":"+43 5523 52780",
    "sg:postcode":"6833",
    "sg:province":"Vorarlberg",
    "wof:name":"Volksschule",
    "wof:placetype":"venue"
},
  "geometry": {"coordinates":[9.6467790604,47.3089675903],"type":"Point"}
}