{
  "type": "Feature",
  "properties": {
    "iso:country":"AT",
    "sg:address":"Nr 55",
    "sg:city":"Jungholz",
    "sg:orig_category":"Volksschulen",
    "sg:phone":"+43 4356 7681214",
    "sg:postcode":"6691",
    "sg:province":"Tirol",
    "wof:name":"Volksschule",
    "wof:placetype":"venue"
},
  "geometry": {"coordinates":[10.4475097656,47.5729103088],"type":"Point"}
}