{
  "type": "Feature",
  "properties": {
    "iso:country":"AT",
    "sg:address":"Freibacher Str 15",
    "sg:city":"Ferlach",
    "sg:orig_category":"Non-Classified Establishments",
    "sg:phone":"+43 4227 5006",
    "sg:postcode":"9170",
    "sg:province":"K\u00e4rnten",
    "wof:name":"Evangelikale Gemeinde",
    "wof:placetype":"venue"
},
  "geometry": {"coordinates":[14.301817894,46.5298538208],"type":"Point"}
}