{
  "type": "Feature",
  "properties": {
    "addr:full":"Lindenstr 18 Innsbruck Tirol 6020",
    "addr:housenumber":"18",
    "addr:postcode":"6020",
    "addr:street":"Lindenstr;Tirol",
    "iso:country":"AT",
    "sg:address":"Lindenstr 18",
    "sg:city":"Innsbruck",
    "sg:classifiers":[
        {
            "category":"Building & Trades",
            "subcategory":"Pest Control",
            "type":"Services"
        }
    ],
    "sg:phone":"+43 4351 2394269",
    "sg:postcode":"6020",
    "sg:province":"Tirol",
    "sg:tags":[
        "zuckerkrankheit",
        "/",
        "diabetes"
    ],
    "wof:name":"\u00d6sterr Diabetikervereinigung Tirol - Referat f Kinder u Jugendliche - Leitung Frau Freitag",
    "wof:placetype":"venue"
},
  "geometry": {"coordinates":[11.4121170044,47.263458252],"type":"Point"}
}