{
  "type": "Feature",
  "properties": {
    "addr:full":"Adolf-Kolping-Gasse 2/III Graz Steiermark 8010",
    "addr:housenumber":"2 / iii",
    "addr:postcode":"8010",
    "addr:street":"Adolf-Kolping-Gasse",
    "iso:country":"AT",
    "sg:address":"Adolf-Kolping-Gasse 2/III",
    "sg:city":"Graz",
    "sg:classifiers":[
        {
            "category":"Professional",
            "subcategory":"Advertising",
            "type":"Services"
        }
    ],
    "sg:phone":"+43 316 814301",
    "sg:postcode":"8010",
    "sg:province":"Steiermark",
    "sg:tags":[
        "agency"
    ],
    "sg:website":"josefundmaria.at",
    "wof:name":"Josef Rauch & Heribert Maria Schurz Werbe-, Marketing - Beratungsges.m.b.H.",
    "wof:placetype":"venue"
},
  "geometry": {"coordinates":[15.4427099228,47.0629768372],"type":"Point"}
}