{
  "type": "Feature",
  "properties": {
    "addr:full":"Eckwaldweg 6 Altenmarkt im Pongau Salzburg 5541",
    "addr:housenumber":"6",
    "addr:postcode":"5541",
    "addr:street":"Eckwaldweg;Salzburg",
    "iso:country":"AT",
    "sg:address":"Eckwaldweg 6",
    "sg:city":"Altenmarkt im Pongau",
    "sg:orig_category":"Appartements / Ferienwohnungen",
    "sg:phone":"+43 4364 527558",
    "sg:postcode":"5541",
    "sg:province":"Salzburg",
    "wof:name":"Schaidlhof Familie Warter",
    "wof:placetype":"venue"
},
  "geometry": {"coordinates":[13.4421358109,47.3745727539],"type":"Point"}
}