{
  "type": "Feature",
  "properties": {
    "addr:full":"Linke W\u00f6glerin 3 Sulz im Wienerwald Nieder\u00f6sterreich 2392",
    "addr:housenumber":"3",
    "addr:postcode":"2392",
    "addr:street":"Linke Woeglerin",
    "iso:country":"AT",
    "sg:address":"Linke W\u00f6glerin 3",
    "sg:city":"Sulz im Wienerwald",
    "sg:orig_category":"Tischlereien",
    "sg:phone":"+43 2238 8214",
    "sg:postcode":"2392",
    "sg:province":"Nieder\u00f6sterreich",
    "wof:name":"Hacker Herbert",
    "wof:placetype":"venue"
},
  "geometry": {"coordinates":[16.1391887665,48.1020393372],"type":"Point"}
}