{
  "type": "Feature",
  "properties": {
    "addr:full":"Marktpl 12 Haslach an der M\u00fchl Ober\u00f6sterreich 4170",
    "addr:housenumber":"12",
    "addr:postcode":"4170",
    "addr:street":"Marktpl;Oberoesterreich",
    "iso:country":"AT",
    "sg:address":"Marktpl 12",
    "sg:city":"Haslach an der M\u00fchl",
    "sg:orig_category":"Spielwaren U Spiele",
    "sg:phone":"+43 4372 8972148",
    "sg:postcode":"4170",
    "sg:province":"Ober\u00f6sterreich",
    "wof:name":"La Le Lu Spielwaren",
    "wof:placetype":"venue"
},
  "geometry": {"coordinates":[14.0404863358,48.5751724243],"type":"Point"}
}