{
  "type": "Feature",
  "properties": {
    "addr:full":"M\u00fchlgrub 125 Bad Hall Ober\u00f6sterreich 4540",
    "addr:housenumber":"125",
    "addr:postcode":"4540",
    "iso:country":"AT",
    "sg:address":"M\u00fchlgrub 125",
    "sg:city":"Bad Hall",
    "sg:classifiers":[
        {
            "category":"Home & Garden",
            "subcategory":"Carpets & Floor Coverings",
            "type":"Retail Goods"
        }
    ],
    "sg:phone":"+43 7258 2286",
    "sg:postcode":"4540",
    "sg:province":"Ober\u00f6sterreich",
    "sg:tags":[
        "stone",
        "natural",
        "panel"
    ],
    "wof:name":"Natursteinverbau Inh. R. Stadlbauer",
    "wof:placetype":"venue"
},
  "geometry": {"coordinates":[14.2057199478,48.0356216431],"type":"Point"}
}