{
  "type": "Feature",
  "properties": {
    "iso:country":"AT",
    "sg:address":"Murlingengasse 7",
    "sg:city":"Wien",
    "sg:classifiers":[
        {
            "category":"Professional",
            "subcategory":"Computer Services",
            "type":"Services"
        }
    ],
    "sg:phone":"+43 1 8173670",
    "sg:postcode":"1120",
    "sg:province":"Wien",
    "sg:tags":[
        "services",
        "consulting",
        "internet"
    ],
    "sg:website":"pixelpoems.com",
    "wof:name":"Pixelpoems Andreas Spannbauer KEG",
    "wof:placetype":"venue"
},
  "geometry": {"coordinates":[16.3433837891,48.1779403687],"type":"Point"}
}