{
  "type": "Feature",
  "properties": {
    "iso:country":"AT",
    "sg:address":"Glemmtaler Landesstr 178",
    "sg:city":"Hinterglemm",
    "sg:orig_category":"Pensionen / Privatzimmer",
    "sg:phone":"+43 6541 6356",
    "sg:postcode":"5754",
    "sg:province":"Salzburg",
    "wof:name":"Pension Alpina",
    "wof:placetype":"venue"
},
  "geometry": {"coordinates":[12.5967702866,47.3807373047],"type":"Point"}
}