{
  "type": "Feature",
  "properties": {
    "addr:full":"Harl 91 Puch Steiermark 8182",
    "addr:housenumber":"91",
    "addr:postcode":"8182",
    "addr:street":"Harl",
    "iso:country":"AT",
    "sg:address":"Harl 91",
    "sg:city":"Puch",
    "sg:orig_category":"Installationsunternehmen",
    "sg:phone":"+43 4331 7741000",
    "sg:postcode":"8182",
    "sg:province":"Steiermark",
    "sg:website":"krobath.com",
    "wof:name":"Krobath Ferdinand KG",
    "wof:placetype":"venue"
},
  "geometry": {"coordinates":[15.7093105316,47.243473053],"type":"Point"}
}