{
  "type": "Feature",
  "properties": {
    "iso:country":"AT",
    "sg:address":"Nr 160",
    "sg:city":"Nauders",
    "sg:classifiers":[
        {
            "category":"Travel",
            "subcategory":"Hotels & Motels",
            "type":"Entertainment"
        }
    ],
    "sg:phone":"+43 4354 7387704",
    "sg:postcode":"6543",
    "sg:province":"Tirol",
    "wof:name":"Alpenhotel Naudererhof",
    "wof:placetype":"venue"
},
  "geometry": {"coordinates":[10.4996595383,46.8896980286],"type":"Point"}
}