{
  "type": "Feature",
  "properties": {
    "iso:country":"AT",
    "sg:address":"Franz-Josef-Str 9",
    "sg:city":"Feldbach",
    "sg:orig_category":"Banken U Sparkassen",
    "sg:phone":"+43 4350 2038330",
    "sg:postcode":"8330",
    "sg:province":"Steiermark",
    "wof:name":"GE Money Bank GmbH",
    "wof:placetype":"venue"
},
  "geometry": {"coordinates":[15.8884496689,46.955821991],"type":"Point"}
}