{
  "type": "Feature",
  "properties": {
    "addr:full":"Nr 115 Steinach am Brenner Tirol 6150",
    "addr:postcode":"6150",
    "addr:street":"Nr 115;Tirol",
    "iso:country":"AT",
    "sg:address":"Nr 115",
    "sg:city":"Steinach am Brenner",
    "sg:orig_category":"Volksschulen",
    "sg:phone":"+43 5276 241",
    "sg:postcode":"6150",
    "sg:province":"Tirol",
    "wof:name":"Volksschule",
    "wof:placetype":"venue"
},
  "geometry": {"coordinates":[11.466711998,47.0918159485],"type":"Point"}
}