{
  "type": "Feature",
  "properties": {
    "addr:full":"Sophiengutstrasse 32 Linz Ober\u00f6sterreich 4020",
    "addr:housenumber":"32",
    "addr:postcode":"4020",
    "addr:street":"Sophiengutstrasse",
    "iso:country":"AT",
    "sg:address":"Sophiengutstrasse 32",
    "sg:city":"Linz",
    "sg:classifiers":[
        {
            "category":"Communications",
            "type":"Services"
        }
    ],
    "sg:phone":"+43 732 608119",
    "sg:postcode":"4020",
    "sg:province":"Ober\u00f6sterreich",
    "sg:tags":[
        "translation"
    ],
    "wof:name":"Ismail Hazim Yarkin",
    "wof:placetype":"venue"
},
  "geometry": {"coordinates":[14.2823877335,48.2895317078],"type":"Point"}
}