{
  "type": "Feature",
  "properties": {
    "addr:full":"Gewerbepark S\u00fcd 11 Kufstein Tirol 6330",
    "addr:housenumber":"11",
    "addr:postcode":"6330",
    "addr:street":"Gewerbepark Sued;Tirol",
    "iso:country":"AT",
    "sg:address":"Gewerbepark S\u00fcd 11",
    "sg:city":"Kufstein",
    "sg:orig_category":"Steuerungstechnik",
    "sg:phone":"+43 5372 653150",
    "sg:postcode":"6330",
    "sg:province":"Tirol",
    "wof:name":"Lenze Deto Drive Systems GmbH & Co KG",
    "wof:placetype":"venue"
},
  "geometry": {"coordinates":[12.157579422,47.5645561218],"type":"Point"}
}