{
  "type": "Feature",
  "properties": {
    "addr:full":"Himberger Str 25 Schwechat Nieder\u00f6sterreich 2320",
    "addr:postcode":"2320",
    "addr:street":"Str 25 Schwechat Niederoesterreich",
    "iso:country":"AT",
    "sg:address":"Himberger Str 25",
    "sg:city":"Schwechat",
    "sg:orig_category":"Reinigungsservice",
    "sg:phone":"+43 1 7061670",
    "sg:postcode":"2320",
    "sg:province":"Nieder\u00f6sterreich",
    "wof:name":"TRASH-KILLERS Reinigung Bojanic KEG",
    "wof:placetype":"venue"
},
  "geometry": {"coordinates":[16.4742794037,48.1361694336],"type":"Point"}
}