{
  "type": "Feature",
  "properties": {
    "addr:full":"Sandbichlweg 1 Kematen in Tirol Tirol 6175",
    "addr:housenumber":"1",
    "addr:postcode":"6175",
    "addr:street":"Sandbichlweg;Tirol",
    "iso:country":"AT",
    "sg:address":"Sandbichlweg 1",
    "sg:city":"Kematen in Tirol",
    "sg:orig_category":"Tabaktrafiken",
    "sg:phone":"+43 5232 3503",
    "sg:postcode":"6175",
    "sg:province":"Tirol",
    "wof:name":"Anfang Maria",
    "wof:placetype":"venue"
},
  "geometry": {"coordinates":[11.273692131,47.2562255859],"type":"Point"}
}