{
  "type": "Feature",
  "properties": {
    "addr:full":"Pernedt 30 K\u00f6nigswiesen Ober\u00f6sterreich 4280",
    "addr:housenumber":"30",
    "addr:postcode":"4280",
    "addr:street":"Pernedt;Oberoesterreich",
    "iso:country":"AT",
    "sg:address":"Pernedt 30",
    "sg:city":"K\u00f6nigswiesen",
    "sg:orig_category":"Bauunternehmen",
    "sg:phone":"+43 7955 6695",
    "sg:postcode":"4280",
    "sg:province":"Ober\u00f6sterreich",
    "wof:name":"Wiesinger Bau GmbH",
    "wof:placetype":"venue"
},
  "geometry": {"coordinates":[14.839838028,48.4059944153],"type":"Point"}
}