{
  "type": "Feature",
  "properties": {
    "addr:full":"Freundorf 97 Klaffer am Hochficht Ober\u00f6sterreich 4163",
    "addr:housenumber":"97",
    "addr:postcode":"4163",
    "addr:street":"Freundorf",
    "iso:country":"AT",
    "sg:address":"Freundorf 97",
    "sg:city":"Klaffer am Hochficht",
    "sg:orig_category":"Bauunternehmen",
    "sg:phone":"+43 7288 8414",
    "sg:postcode":"4163",
    "sg:province":"Ober\u00f6sterreich",
    "wof:name":"Binder BaugesmbH",
    "wof:placetype":"venue"
},
  "geometry": {"coordinates":[13.8915748596,48.7072372437],"type":"Point"}
}