{
  "type": "Feature",
  "properties": {
    "addr:full":"Stemolakg 29 Wien Wien 1220",
    "addr:housenumber":"29",
    "addr:postcode":"1220",
    "addr:street":"Stemolakg",
    "iso:country":"AT",
    "sg:address":"Stemolakg 29",
    "sg:city":"Wien",
    "sg:orig_category":"Werbegrafik- U Grafik-Design",
    "sg:phone":"+43 1 2856108",
    "sg:postcode":"1220",
    "sg:province":"Wien",
    "wof:name":"Hauk Friedrich",
    "wof:placetype":"venue"
},
  "geometry": {"coordinates":[16.4930896759,48.2398300171],"type":"Point"}
}