{
  "type": "Feature",
  "properties": {
    "iso:country":"AT",
    "sg:address":"M\u00fchlbachstrasse 16",
    "sg:city":"Wilhering",
    "sg:classifiers":[
        {
            "category":"Manufacturing",
            "subcategory":"Wood Products",
            "type":"Manufacturing & Wholesale Goods"
        }
    ],
    "sg:phone":"+43 7226 2714",
    "sg:postcode":"4073",
    "sg:province":"Ober\u00f6sterreich",
    "sg:tags":[
        "gate",
        "made",
        "door"
    ],
    "wof:name":"Rudolf Kirchmeir",
    "wof:placetype":"venue"
},
  "geometry": {"coordinates":[14.1893806458,48.3233795166],"type":"Point"}
}