{
  "type": "Feature",
  "properties": {
    "addr:full":"Kardinal-Piffl-Pl 4 Breitenfurt Nieder\u00f6sterreich 2384",
    "addr:housenumber":"4",
    "addr:postcode":"2384",
    "addr:street":"Kardinal-Piffl-Pl",
    "iso:country":"AT",
    "sg:address":"Kardinal-Piffl-Pl 4",
    "sg:city":"Breitenfurt",
    "sg:orig_category":"\u00c3\u201erzte / F Allgemeinmedizin",
    "sg:phone":"+43 2239 44440",
    "sg:postcode":"2384",
    "sg:province":"Nieder\u00f6sterreich",
    "wof:name":"Senft Michael Dr",
    "wof:placetype":"venue"
},
  "geometry": {"coordinates":[16.1366653442,48.1402282715],"type":"Point"}
}