{
  "type": "Feature",
  "properties": {
    "addr:full":"Adolf-Pichler-Str 9a Kufstein Tirol 6330",
    "addr:housenumber":"9a",
    "addr:postcode":"6330",
    "addr:street":"Adolf-Pichler-Str;Tirol",
    "iso:country":"AT",
    "sg:address":"Adolf-Pichler-Str 9a",
    "sg:city":"Kufstein",
    "sg:orig_category":"Tischlereien",
    "sg:phone":"+43 5372 62972",
    "sg:postcode":"6330",
    "sg:province":"Tirol",
    "wof:name":"Greiderer Karl",
    "wof:placetype":"venue"
},
  "geometry": {"coordinates":[12.1736631393,47.5870323181],"type":"Point"}
}