{
  "type": "Feature",
  "properties": {
    "addr:full":"Trattfelderstr 56 Stra\u00dfgang Steiermark 8054",
    "addr:housenumber":"56",
    "addr:postcode":"8054",
    "addr:street":"Trattfelderstr",
    "iso:country":"AT",
    "sg:address":"Trattfelderstr 56",
    "sg:city":"Stra\u00dfgang",
    "sg:classifiers":[
        {
            "category":"Professional",
            "subcategory":"Computer Services",
            "type":"Services"
        }
    ],
    "sg:phone":"+43 316 286783",
    "sg:postcode":"8054",
    "sg:province":"Steiermark",
    "sg:tags":[
        "software"
    ],
    "wof:name":"Peinsipp Gerhard Mag",
    "wof:placetype":"venue"
},
  "geometry": {"coordinates":[15.4010896683,47.0373458862],"type":"Point"}
}