{
  "type": "Feature",
  "properties": {
    "addr:full":"Nr 7 St. Martin im M\u00fchlkreis Ober\u00f6sterreich 4113",
    "addr:housenumber":"7",
    "addr:postcode":"4113",
    "addr:street":"Nr;Im Muehlkreis Oberoesterreich",
    "iso:country":"AT",
    "sg:address":"Nr 7",
    "sg:city":"St. Martin im M\u00fchlkreis",
    "sg:orig_category":"Psychotherapie",
    "sg:phone":"+43 4372 32238311",
    "sg:postcode":"4113",
    "sg:province":"Ober\u00f6sterreich",
    "wof:name":"Br\u00e4u Reinhold Mag",
    "wof:placetype":"venue"
},
  "geometry": {"coordinates":[14.0391530991,48.4157409668],"type":"Point"}
}