{
  "type": "Feature",
  "properties": {
    "iso:country":"AT",
    "sg:address":"Obere Landstr 5",
    "sg:city":"Krems an der Donau",
    "sg:orig_category":"Unterhaltungselektronik / Reparatur",
    "sg:phone":"+43 2732 855970",
    "sg:postcode":"3500",
    "sg:province":"Nieder\u00f6sterreich",
    "wof:name":"Novotny Franz Radiodoktor Nfg F Novotny GesmbH",
    "wof:placetype":"venue"
},
  "geometry": {"coordinates":[15.5994825363,48.4108695984],"type":"Point"}
}