{
  "type": "Feature",
  "properties": {
    "addr:full":"Weihburgg 4 Wien Wien 1010",
    "addr:housenumber":"4",
    "addr:postcode":"1010",
    "addr:street":"Weihburgg",
    "iso:country":"AT",
    "sg:address":"Weihburgg 4",
    "sg:city":"Wien",
    "sg:orig_category":"Papier- U Schreibwaren / Einzelhandel",
    "sg:phone":"+43 1 5335075",
    "sg:postcode":"1010",
    "sg:province":"Wien",
    "sg:website":"www.huber-lerner.at",
    "wof:name":"Huber & Lerner",
    "wof:placetype":"venue"
},
  "geometry": {"coordinates":[16.3722133636,48.2069129944],"type":"Point"}
}