{
  "type": "Feature",
  "properties": {
    "addr:full":"Hauptstr 34 Maria Enzersdorf Nieder\u00f6sterreich 2344",
    "addr:housenumber":"34",
    "addr:postcode":"2344",
    "addr:street":"Hauptstr",
    "iso:country":"AT",
    "sg:address":"Hauptstr 34",
    "sg:city":"Maria Enzersdorf",
    "sg:orig_category":"Tabaktrafiken",
    "sg:phone":"+43 2236 28312",
    "sg:postcode":"2344",
    "sg:province":"Nieder\u00f6sterreich",
    "wof:name":"Heger Veronika",
    "wof:placetype":"venue"
},
  "geometry": {"coordinates":[16.2839927673,48.0988883972],"type":"Point"}
}