{
  "type": "Feature",
  "properties": {
    "addr:full":"Hauptstr 4/1 Oberpullendorf Burgenland 7350",
    "addr:housenumber":"4 / 1",
    "addr:postcode":"7350",
    "addr:street":"Hauptstr",
    "iso:country":"AT",
    "sg:address":"Hauptstr 4/1",
    "sg:city":"Oberpullendorf",
    "sg:orig_category":"Weiterbildungsinstitute M Allg U Berufl Bildungsangebot",
    "sg:phone":"+43 2612 46063",
    "sg:postcode":"7350",
    "sg:province":"Burgenland",
    "wof:name":"Mentor Management Entwicklung Organisation GmbH & Co",
    "wof:placetype":"venue"
},
  "geometry": {"coordinates":[16.5047950745,47.5015602112],"type":"Point"}
}