{
  "type": "Feature",
  "properties": {
    "addr:full":"Dorf 37 Ellmau Tirol 6352",
    "addr:housenumber":"37",
    "addr:postcode":"6352",
    "addr:street":"Dorf;Tirol",
    "iso:country":"AT",
    "sg:address":"Dorf 37",
    "sg:city":"Ellmau",
    "sg:orig_category":"Damenmoden",
    "sg:phone":"+43 5358 4067",
    "sg:postcode":"6352",
    "sg:province":"Tirol",
    "wof:name":"Sectury Outlet - Kress Anita",
    "wof:placetype":"venue"
},
  "geometry": {"coordinates":[12.304233551,47.5135993958],"type":"Point"}
}