{
  "type": "Feature",
  "properties": {
    "addr:full":"G\u00fcnselsdorfer Strasse 3b Leobersdorf Nieder\u00f6sterreich 2544",
    "addr:housenumber":"3b",
    "addr:postcode":"2544",
    "addr:street":"Guenselsdorfer Strasse",
    "iso:country":"AT",
    "sg:address":"G\u00fcnselsdorfer Strasse 3b",
    "sg:city":"Leobersdorf",
    "sg:classifiers":[
        {
            "category":"Community Center",
            "subcategory":"Senior",
            "type":"Public Place"
        }
    ],
    "sg:phone":"+43 2256 620110",
    "sg:postcode":"2544",
    "sg:province":"Nieder\u00f6sterreich",
    "sg:tags":[
        "pen",
        "ball",
        "point"
    ],
    "sg:website":"jolly.co.at",
    "wof:name":"Brevillier-Urban Schreibwarenfabrik Ges.m.b.H.",
    "wof:placetype":"venue"
},
  "geometry": {"coordinates":[16.2165107727,47.9286613464],"type":"Point"}
}