{
  "type": "Feature",
  "properties": {
    "addr:full":"Nr 8 G\u00fcssing Burgenland 7540",
    "addr:postcode":"7540",
    "addr:street":"Nr;Guessing",
    "iso:country":"AT",
    "sg:address":"Nr 8",
    "sg:city":"G\u00fcssing",
    "sg:orig_category":"Volksschulen",
    "sg:phone":"+43 3322 440940",
    "sg:postcode":"7540",
    "sg:province":"Burgenland",
    "wof:name":"Volksschule",
    "wof:placetype":"venue"
},
  "geometry": {"coordinates":[16.3241195679,47.0592803955],"type":"Point"}
}