{
  "type": "Feature",
  "properties": {
    "addr:full":"Nr 20 Radmer Steiermark 8795",
    "addr:postcode":"8795",
    "addr:street":"Nr",
    "iso:country":"AT",
    "sg:address":"Nr 20",
    "sg:city":"Radmer",
    "sg:orig_category":"Tabaktrafiken",
    "sg:phone":"+43 3635 2336",
    "sg:postcode":"8795",
    "sg:province":"Steiermark",
    "wof:name":"Wachauer Frieda",
    "wof:placetype":"venue"
},
  "geometry": {"coordinates":[14.7611942291,47.5443954468],"type":"Point"}
}