{
  "type": "Feature",
  "properties": {
    "addr:full":"Zaunscherbg 2 Wien Wien 1210",
    "addr:housenumber":"2",
    "addr:postcode":"1210",
    "addr:street":"Zaunscherbg",
    "iso:country":"AT",
    "sg:address":"Zaunscherbg 2",
    "sg:city":"Wien",
    "sg:orig_category":"Non-Classified Establishments",
    "sg:phone":"+43 1 27153703",
    "sg:postcode":"1210",
    "sg:province":"Wien",
    "wof:name":"Kirchenbeitragsstelle Floridsdorf",
    "wof:placetype":"venue"
},
  "geometry": {"coordinates":[16.4003391266,48.2583770752],"type":"Point"}
}