{
  "type": "Feature",
  "properties": {
    "iso:country":"AT",
    "sg:address":"Reinprechtsdorf Str 18",
    "sg:city":"Wien",
    "sg:orig_category":"Fleisch-, Wurst- U Selchwaren / Erzeugung U Gro\u00c3\u0178handel",
    "sg:phone":"+43 1 5482363",
    "sg:postcode":"1050",
    "sg:province":"Wien",
    "wof:name":"F\u00fcco FleischverarbeitungsgesmbH",
    "wof:placetype":"venue"
},
  "geometry": {"coordinates":[16.3566360474,48.1834144592],"type":"Point"}
}