{
  "type": "Feature",
  "properties": {
    "addr:full":"Hauptstr. 52 Dra\u00dfburg Burgenland 7021",
    "addr:housenumber":"52",
    "addr:postcode":"7021",
    "addr:street":"Hauptstr.",
    "iso:country":"AT",
    "sg:address":"Hauptstr. 52",
    "sg:city":"Dra\u00dfburg",
    "sg:classifiers":[
        {
            "category":"Home & Garden",
            "subcategory":"Home Furnishings",
            "type":"Retail Goods"
        }
    ],
    "sg:phone":"+43 4326 862279",
    "sg:postcode":"7021",
    "sg:province":"Burgenland",
    "sg:tags":[
        "household"
    ],
    "wof:name":"DIPL. ING. ROBERT ARTNER",
    "wof:placetype":"venue"
},
  "geometry": {"coordinates":[16.5047454834,47.7362327576],"type":"Point"}
}