{
  "type": "Feature",
  "properties": {
    "iso:country":"AT",
    "sg:address":"T\u00fcrkenschanzg 13",
    "sg:city":"Klosterneuburg",
    "sg:orig_category":"Unternehmensberatung",
    "sg:phone":"+43 4366 42007869",
    "sg:postcode":"3400",
    "sg:province":"Nieder\u00f6sterreich",
    "wof:name":"Goldemund Consulting und Training",
    "wof:placetype":"venue"
},
  "geometry": {"coordinates":[16.3252258301,48.3049087524],"type":"Point"}
}