{
  "type": "Feature",
  "properties": {
    "addr:full":"Kreuzner Str 16 Grein Ober\u00f6sterreich 4360",
    "addr:housenumber":"16",
    "addr:postcode":"4360",
    "addr:street":"Str",
    "iso:country":"AT",
    "sg:address":"Kreuzner Str 16",
    "sg:city":"Grein",
    "sg:orig_category":"Farben U Lacke / Einzelhandel",
    "sg:phone":"+43 4372 687017",
    "sg:postcode":"4360",
    "sg:province":"Ober\u00f6sterreich",
    "wof:name":"FARBEN WAHL GmbH",
    "wof:placetype":"venue"
},
  "geometry": {"coordinates":[14.8547706604,48.2269058228],"type":"Point"}
}