{
  "type": "Feature",
  "properties": {
    "addr:full":"Garteng 21 Wien Wien 1050",
    "addr:housenumber":"21",
    "addr:postcode":"1050",
    "addr:street":"Garteng",
    "iso:country":"AT",
    "sg:address":"Garteng 21",
    "sg:city":"Wien",
    "sg:orig_category":"Werbegrafik- U Grafik-Design",
    "sg:phone":"+43 4315 863040",
    "sg:postcode":"1050",
    "sg:province":"Wien",
    "wof:name":"Krall Klaus GmbH",
    "wof:placetype":"venue"
},
  "geometry": {"coordinates":[16.3579769135,48.1903457642],"type":"Point"}
}