{
  "type": "Feature",
  "properties": {
    "addr:full":"Ferdinand-Weyrer-Strasse 5 Innsbruck Tirol 6020",
    "addr:housenumber":"5",
    "addr:postcode":"6020",
    "addr:street":"Ferdinand-Weyrer-Strasse;Tirol",
    "iso:country":"AT",
    "sg:address":"Ferdinand-Weyrer-Strasse 5",
    "sg:city":"Innsbruck",
    "sg:classifiers":[
        {
            "category":"Home & Garden",
            "subcategory":"Building Materials",
            "type":"Retail Goods"
        }
    ],
    "sg:phone":"+43 512 204622",
    "sg:postcode":"6020",
    "sg:province":"Tirol",
    "sg:tags":[
        "railing",
        "balcony"
    ],
    "wof:name":"Edgar Eckm\u00fcller",
    "wof:placetype":"venue"
},
  "geometry": {"coordinates":[11.4111366272,47.2809867859],"type":"Point"}
}