{
  "type": "Feature",
  "properties": {
    "iso:country":"AT",
    "sg:address":"Trutsch 17",
    "sg:city":"Satteins",
    "sg:orig_category":"Schleifereien",
    "sg:phone":"+43 5524 8363",
    "sg:postcode":"6822",
    "sg:province":"Vorarlberg",
    "wof:name":"Gutschner Karl",
    "wof:placetype":"venue"
},
  "geometry": {"coordinates":[9.6763134003,47.2202949524],"type":"Point"}
}