{
  "type": "Feature",
  "properties": {
    "addr:full":"Linke Wienzeile 120 Wien Wien 1060",
    "addr:housenumber":"120",
    "addr:postcode":"1060",
    "addr:street":"Linke Wienzeile",
    "iso:country":"AT",
    "sg:address":"Linke Wienzeile 120",
    "sg:city":"Wien",
    "sg:classifiers":[
        {
            "category":"Professional",
            "type":"Services"
        }
    ],
    "sg:phone":"+43 5 010076700",
    "sg:postcode":"1060",
    "sg:province":"Wien",
    "sg:tags":[
        "leasing"
    ],
    "wof:name":"EBV-Leasing GesmbH & Co KG",
    "wof:placetype":"venue"
},
  "geometry": {"coordinates":[16.3529834747,48.1914138794],"type":"Point"}
}