{
  "type": "Feature",
  "properties": {
    "addr:full":"Nr 7 Niederkappel Ober\u00f6sterreich 4133",
    "addr:postcode":"4133",
    "addr:street":"Nr;Oberoesterreich",
    "iso:country":"AT",
    "sg:address":"Nr 7",
    "sg:city":"Niederkappel",
    "sg:orig_category":"Tischlereien",
    "sg:phone":"+43 7286 8508",
    "sg:postcode":"4133",
    "sg:province":"Ober\u00f6sterreich",
    "wof:name":"Altendorfer Stefan",
    "wof:placetype":"venue"
},
  "geometry": {"coordinates":[13.8806123734,48.4651412964],"type":"Point"}
}