{
  "type": "Feature",
  "properties": {
    "iso:country":"AT",
    "sg:address":"Jahnstrasse 10-12",
    "sg:city":"F\u00fcrstenfeld",
    "sg:classifiers":[
        {
            "category":"Banks & Credit Unions",
            "subcategory":"Investment Brokerage",
            "type":"Services"
        }
    ],
    "sg:phone":"+43 3382 537800",
    "sg:postcode":"8280",
    "sg:province":"Steiermark",
    "sg:tags":[
        "development",
        "electronics"
    ],
    "sg:website":"tecwings.at",
    "wof:name":"Tecwings F\u00fcrstenfeld Elektronikproduktion GmbH",
    "wof:placetype":"venue"
},
  "geometry": {"coordinates":[16.0858306885,47.0384902954],"type":"Point"}
}