{
  "type": "Feature",
  "properties": {
    "addr:full":"Gewerbestr 1 Anthering Salzburg 5102",
    "addr:housenumber":"1",
    "addr:postcode":"5102",
    "addr:street":"Gewerbestr;Salzburg",
    "iso:country":"AT",
    "sg:address":"Gewerbestr 1",
    "sg:city":"Anthering",
    "sg:orig_category":"Bauunternehmen",
    "sg:phone":"+43 6223 3090",
    "sg:postcode":"5102",
    "sg:province":"Salzburg",
    "wof:name":"Hinteregger G & S\u00f6hne BaugesmbH",
    "wof:placetype":"venue"
},
  "geometry": {"coordinates":[13.0102014542,47.8665924072],"type":"Point"}
}