{
  "type": "Feature",
  "properties": {
    "addr:full":"Kalkgrund 28 Rohrbach Burgenland 7222",
    "addr:housenumber":"28",
    "addr:postcode":"7222",
    "addr:street":"Kalkgrund",
    "iso:country":"AT",
    "sg:address":"Kalkgrund 28",
    "sg:city":"Rohrbach",
    "sg:classifiers":[
        {
            "category":"Banks & Credit Unions",
            "subcategory":"Atm",
            "type":"Services"
        }
    ],
    "sg:phone":"+43 2626 67934",
    "sg:postcode":"7222",
    "sg:province":"Burgenland",
    "sg:tags":[
        "dispersion",
        "cast"
    ],
    "wof:name":"FP Bau GesmbH",
    "wof:placetype":"venue"
},
  "geometry": {"coordinates":[16.4360523224,47.7022247314],"type":"Point"}
}