{
  "type": "Feature",
  "properties": {
    "addr:full":"Hellweg 12 Altenfelden Ober\u00f6sterreich 4121",
    "addr:housenumber":"12",
    "addr:postcode":"4121",
    "addr:street":"Hellweg",
    "iso:country":"AT",
    "sg:address":"Hellweg 12",
    "sg:city":"Altenfelden",
    "sg:orig_category":"Bauunternehmen",
    "sg:phone":"+43 7282 6463",
    "sg:postcode":"4121",
    "sg:province":"Ober\u00f6sterreich",
    "wof:name":"Vierlinger Johann",
    "wof:placetype":"venue"
},
  "geometry": {"coordinates":[13.9724969864,48.4868621826],"type":"Point"}
}