{
  "type": "Feature",
  "properties": {
    "addr:full":"Hauptstr 6a St. Lorenzen im M\u00fcrztal Steiermark 8642",
    "addr:housenumber":"6a",
    "addr:postcode":"8642",
    "addr:street":"Hauptstr",
    "iso:country":"AT",
    "sg:address":"Hauptstr 6a",
    "sg:city":"St. Lorenzen im M\u00fcrztal",
    "sg:orig_category":"Feuerwehren",
    "sg:phone":"+43 3864 2190",
    "sg:postcode":"8642",
    "sg:province":"Steiermark",
    "wof:name":"Freiwillige Feuerwehr St Lorenzen i M\u00fcrztal",
    "wof:placetype":"venue"
},
  "geometry": {"coordinates":[15.3701543808,47.4817695618],"type":"Point"}
}