{
  "type": "Feature",
  "properties": {
    "addr:full":"Obere Windflach 27 Schenkenfelden Ober\u00f6sterreich 4192",
    "addr:housenumber":"27",
    "addr:postcode":"4192",
    "addr:street":"Obere Windflach",
    "iso:country":"AT",
    "sg:address":"Obere Windflach 27",
    "sg:city":"Schenkenfelden",
    "sg:orig_category":"Handelsagenturen",
    "sg:phone":"+43 7214 70200",
    "sg:postcode":"4192",
    "sg:province":"Ober\u00f6sterreich",
    "wof:name":"Techpro Handelsagentur Peter Fraisl - Bauteil Lagerungen",
    "wof:placetype":"venue"
},
  "geometry": {"coordinates":[14.3717470169,48.5053672791],"type":"Point"}
}