{
  "type": "Feature",
  "properties": {
    "addr:full":"Gstill 10 Patsch Tirol 6082",
    "addr:housenumber":"10",
    "addr:postcode":"6082",
    "addr:street":"Gstill;Tirol",
    "iso:country":"AT",
    "sg:address":"Gstill 10",
    "sg:city":"Patsch",
    "sg:orig_category":"Lebens- U Sozialberatung",
    "sg:phone":"+43 699 18855415",
    "sg:postcode":"6082",
    "sg:province":"Tirol",
    "wof:name":"Felder Markus Mag - Klinisch- und Gesundheitspsychologischer- und Legasthenietrainer",
    "wof:placetype":"venue"
},
  "geometry": {"coordinates":[11.4187345505,47.2056159973],"type":"Point"}
}