{
  "type": "Feature",
  "properties": {
    "addr:full":"Badg 22 Bad Deutsch Altenburg Nieder\u00f6sterreich 2405",
    "addr:housenumber":"22",
    "addr:postcode":"2405",
    "addr:street":"Badg",
    "iso:country":"AT",
    "sg:address":"Badg 22",
    "sg:city":"Bad Deutsch Altenburg",
    "sg:orig_category":"Pensionen / Privatzimmer",
    "sg:phone":"+43 4321 6562763",
    "sg:postcode":"2405",
    "sg:province":"Nieder\u00f6sterreich",
    "wof:name":"Madle Walter",
    "wof:placetype":"venue"
},
  "geometry": {"coordinates":[16.9053001404,48.1338043213],"type":"Point"}
}