{
  "type": "Feature",
  "properties": {
    "addr:full":"Weingartshofstrasse 37-39 Linz Ober\u00f6sterreich 4020",
    "addr:postcode":"37-39;4020",
    "addr:street":"Weingartshofstrasse;Oberoesterreich",
    "iso:country":"AT",
    "sg:address":"Weingartshofstrasse 37-39",
    "sg:city":"Linz",
    "sg:classifiers":[
        {
            "category":"Banks & Credit Unions",
            "subcategory":"Bureau De Change",
            "type":"Services"
        }
    ],
    "sg:phone":"+43 732 6978",
    "sg:postcode":"4020",
    "sg:province":"Ober\u00f6sterreich",
    "sg:tags":[
        "control",
        "regulation",
        "digital",
        "system",
        "automation"
    ],
    "sg:website":"industrieinformatik.com",
    "wof:name":"Industrie Informatik GmbH",
    "wof:placetype":"venue"
},
  "geometry": {"coordinates":[14.2881507874,48.2916870117],"type":"Point"}
}