{
  "type": "Feature",
  "properties": {
    "addr:full":"Schernbergstr 16 Radstadt Salzburg 5550",
    "addr:housenumber":"16",
    "addr:postcode":"5550",
    "addr:street":"Schernbergstr;Salzburg",
    "iso:country":"AT",
    "sg:address":"Schernbergstr 16",
    "sg:city":"Radstadt",
    "sg:orig_category":"Textilreinigung",
    "sg:phone":"+43 6452 7497",
    "sg:postcode":"5550",
    "sg:province":"Salzburg",
    "wof:name":"W\u00fchrer KEG",
    "wof:placetype":"venue"
},
  "geometry": {"coordinates":[13.4648675919,47.3847923279],"type":"Point"}
}