{
  "type": "Feature",
  "properties": {
    "addr:full":"Pradler Str 30 Innsbruck Tirol 6020",
    "addr:housenumber":"30",
    "addr:postcode":"6020",
    "addr:street":"Pradler Str;Tirol",
    "iso:country":"AT",
    "sg:address":"Pradler Str 30",
    "sg:city":"Innsbruck",
    "sg:orig_category":"Altwaren",
    "sg:phone":"+43 512 341589",
    "sg:postcode":"6020",
    "sg:province":"Tirol",
    "wof:name":"Tr\u00f6dlerei Pradler Flohmarkt",
    "wof:placetype":"venue"
},
  "geometry": {"coordinates":[11.4089422226,47.2658805847],"type":"Point"}
}