{
  "type": "Feature",
  "properties": {
    "iso:country":"AT",
    "sg:address":"Nr 53",
    "sg:city":"Piesendorf",
    "sg:orig_category":"Spenglereien",
    "sg:phone":"+43 6549 7613",
    "sg:postcode":"5721",
    "sg:province":"Salzburg",
    "wof:name":"Rieder Anton",
    "wof:placetype":"venue"
},
  "geometry": {"coordinates":[12.7159004211,47.2918968201],"type":"Point"}
}