{
  "type": "Feature",
  "properties": {
    "iso:country":"AT",
    "sg:address":"Durisolstr 7/50",
    "sg:city":"Wels",
    "sg:orig_category":"Ingenieurkonsulenten / Zivilingenieure",
    "sg:phone":"+43 676 9497553",
    "sg:postcode":"4600",
    "sg:province":"Ober\u00f6sterreich",
    "wof:name":"K\u00f6pl Michael Dipl-Ing",
    "wof:placetype":"venue"
},
  "geometry": {"coordinates":[14.0079917908,48.1509475708],"type":"Point"}
}