{
  "type": "Feature",
  "properties": {
    "iso:country":"AT",
    "sg:address":"Inkustrasse 7",
    "sg:city":"Klosterneuburg",
    "sg:classifiers":[
        {
            "category":"Shopping",
            "subcategory":"Antiques",
            "type":"Retail Goods"
        }
    ],
    "sg:phone":"+43 2243 33880",
    "sg:postcode":"3400",
    "sg:province":"Nieder\u00f6sterreich",
    "sg:tags":[
        "lighting"
    ],
    "sg:website":"kalmarlighting.com",
    "wof:name":"J. T. Kalmar GmbH",
    "wof:placetype":"venue"
},
  "geometry": {"coordinates":[16.3416252136,48.2906112671],"type":"Point"}
}