{
  "type": "Feature",
  "properties": {
    "addr:full":"Eyblerg 1 Wien Wien 1190",
    "addr:housenumber":"1",
    "addr:postcode":"1190",
    "addr:street":"Eyblerg",
    "iso:country":"AT",
    "sg:address":"Eyblerg 1",
    "sg:city":"Wien",
    "sg:orig_category":"Non-Classified Establishments",
    "sg:phone":"+43 1 4401340",
    "sg:postcode":"1190",
    "sg:province":"Wien",
    "wof:name":"Pfarramt Neustift am Walde",
    "wof:placetype":"venue"
},
  "geometry": {"coordinates":[16.3031654358,48.2505683899],"type":"Point"}
}