{
  "type": "Feature",
  "properties": {
    "addr:full":"Kirchenpl 4 Bad Hofgastein Salzburg 5630",
    "addr:housenumber":"4",
    "addr:postcode":"5630",
    "addr:street":"Kirchenpl;Salzburg",
    "iso:country":"AT",
    "sg:address":"Kirchenpl 4",
    "sg:city":"Bad Hofgastein",
    "sg:classifiers":[
        {
            "category":"Travel",
            "subcategory":"Hotels & Motels",
            "type":"Entertainment"
        }
    ],
    "sg:phone":"+43 4364 3262600",
    "sg:postcode":"5630",
    "sg:province":"Salzburg",
    "sg:website":"bergwelthotels.at/altepost",
    "wof:name":"Hotel - Restaurant Alte Post - Fam. Hainzer",
    "wof:placetype":"venue"
},
  "geometry": {"coordinates":[13.1073598862,47.1709022522],"type":"Point"}
}