{
  "type": "Feature",
  "properties": {
    "iso:country":"AT",
    "sg:address":"Nr 19",
    "sg:city":"Ladendorf",
    "sg:orig_category":"Tischlereien",
    "sg:phone":"+43 2575 8448",
    "sg:postcode":"2126",
    "sg:province":"Nieder\u00f6sterreich",
    "wof:name":"Schwab Wohndesign",
    "wof:placetype":"venue"
},
  "geometry": {"coordinates":[16.4927768707,48.5335197449],"type":"Point"}
}