{
  "type": "Feature",
  "properties": {
    "addr:full":"Opernring 7 Wien Wien 1010",
    "addr:housenumber":"7",
    "addr:postcode":"1010",
    "addr:street":"Opernring",
    "iso:country":"AT",
    "sg:address":"Opernring 7",
    "sg:city":"Wien",
    "sg:orig_category":"Immobilienmakler",
    "sg:phone":"+43 4317 108383",
    "sg:postcode":"1010",
    "sg:province":"Wien",
    "wof:name":"Wohn-Partner Fertighaus-Immobilien-VertriebsgesmbH",
    "wof:placetype":"venue"
},
  "geometry": {"coordinates":[16.3675498962,48.2025680542],"type":"Point"}
}