{
  "type": "Feature",
  "properties": {
    "iso:country":"AT",
    "sg:address":"Hauptstrasse 9",
    "sg:city":"Scharnstein",
    "sg:classifiers":[
        {
            "category":"Home & Garden",
            "subcategory":"Carpets & Floor Coverings",
            "type":"Retail Goods"
        }
    ],
    "sg:phone":"+43 76157801",
    "sg:postcode":"4644",
    "sg:province":"Ober\u00f6sterreich",
    "sg:tags":[
        "carpeting"
    ],
    "sg:website":"grueneerde.at",
    "wof:name":"Gr\u00fcne Erde GmbH",
    "wof:placetype":"venue"
},
  "geometry": {"coordinates":[13.9614448547,47.9049606323],"type":"Point"}
}