{
  "type": "Feature",
  "properties": {
    "addr:full":"Gentzg 66 Wien Wien 1180",
    "addr:housenumber":"66",
    "addr:postcode":"1180",
    "addr:street":"Gentzg",
    "iso:country":"AT",
    "sg:address":"Gentzg 66",
    "sg:city":"Wien",
    "sg:classifiers":[
        {
            "category":"Organizations",
            "subcategory":"Political Organization",
            "type":"Services"
        }
    ],
    "sg:phone":"+43 1 4705822",
    "sg:postcode":"1180",
    "sg:province":"Wien",
    "sg:tags":[
        "mediation"
    ],
    "wof:name":"komarek konfliktmediation - Mag Andrea Komarek",
    "wof:placetype":"venue"
},
  "geometry": {"coordinates":[16.3400268555,48.2277526855],"type":"Point"}
}