{
  "type": "Feature",
  "properties": {
    "addr:full":"Breitenauer Str 30 Breitenau am Hochlantsch Steiermark 8614",
    "addr:housenumber":"30",
    "addr:postcode":"8614",
    "addr:street":"Breitenauer Str",
    "iso:country":"AT",
    "sg:address":"Breitenauer Str 30",
    "sg:city":"Breitenau am Hochlantsch",
    "sg:orig_category":"Autohandel",
    "sg:phone":"+43 4338 662217",
    "sg:postcode":"8614",
    "sg:province":"Steiermark",
    "wof:name":"Wiltschnigg Hermann",
    "wof:placetype":"venue"
},
  "geometry": {"coordinates":[15.4259214401,47.3903923035],"type":"Point"}
}