{
  "type": "Feature",
  "properties": {
    "addr:full":"Neuhof Parz 45 Ottenschlag Nieder\u00f6sterreich 3631",
    "addr:housenumber":"45",
    "addr:postcode":"3631",
    "addr:street":"Parz",
    "iso:country":"AT",
    "sg:address":"Neuhof Parz 45",
    "sg:city":"Ottenschlag",
    "sg:orig_category":"Bauunternehmen",
    "sg:phone":"+43 4328 7265010",
    "sg:postcode":"3631",
    "sg:province":"Nieder\u00f6sterreich",
    "wof:name":"M\u00f6rth GesmbH",
    "wof:placetype":"venue"
},
  "geometry": {"coordinates":[15.2205476761,48.4242744446],"type":"Point"}
}