{
  "type": "Feature",
  "properties": {
    "addr:full":"Steinfeldg 12 Guntramsdorf Nieder\u00f6sterreich 2353",
    "addr:housenumber":"12",
    "addr:postcode":"2353",
    "addr:street":"Steinfeldg",
    "iso:country":"AT",
    "sg:address":"Steinfeldg 12",
    "sg:city":"Guntramsdorf",
    "sg:orig_category":"Pensionen / Privatzimmer",
    "sg:phone":"+43 2236 53490",
    "sg:postcode":"2353",
    "sg:province":"Nieder\u00f6sterreich",
    "wof:name":"Fr\u00fchst\u00fcckspension Herta Csar",
    "wof:placetype":"venue"
},
  "geometry": {"coordinates":[16.3097419739,48.0446014404],"type":"Point"}
}