{
  "type": "Feature",
  "properties": {
    "addr:full":"Gewerbepark 4 Gramastetten Ober\u00f6sterreich 4201",
    "addr:housenumber":"4",
    "addr:postcode":"4201",
    "addr:street":"Gewerbepark",
    "iso:country":"AT",
    "sg:address":"Gewerbepark 4",
    "sg:city":"Gramastetten",
    "sg:orig_category":"Elektronik",
    "sg:phone":"+43 7239 57700",
    "sg:postcode":"4201",
    "sg:province":"Ober\u00f6sterreich",
    "wof:name":"Eisner Manfred Ing Industrieelektronik GesmbH",
    "wof:placetype":"venue"
},
  "geometry": {"coordinates":[14.2140483856,48.3714942932],"type":"Point"}
}