{
  "type": "Feature",
  "properties": {
    "iso:country":"AT",
    "sg:address":"Nr 44",
    "sg:city":"Jenig",
    "sg:orig_category":"Appartements / Ferienwohnungen",
    "sg:phone":"+43 4342 852020",
    "sg:postcode":"9631",
    "sg:province":"K\u00e4rnten",
    "sg:website":"marat-cc.at",
    "wof:name":"marat consulting company - Bernhard Maurer",
    "wof:placetype":"venue"
},
  "geometry": {"coordinates":[13.2537050247,46.6278686523],"type":"Point"}
}