{
  "type": "Feature",
  "properties": {
    "addr:full":"Ramsaustr 5 Bad Goisern Ober\u00f6sterreich 4822",
    "addr:housenumber":"5",
    "addr:postcode":"4822",
    "addr:street":"Ramsaustr",
    "iso:country":"AT",
    "sg:address":"Ramsaustr 5",
    "sg:city":"Bad Goisern",
    "sg:orig_category":"Friseure U Frisiersalons",
    "sg:phone":"+43 4361 358696",
    "sg:postcode":"4822",
    "sg:province":"Ober\u00f6sterreich",
    "wof:name":"Fellner Elisabeth - Friseursalon Er & Sie",
    "wof:placetype":"venue"
},
  "geometry": {"coordinates":[13.617351532,47.6391677856],"type":"Point"}
}