{
  "type": "Feature",
  "properties": {
    "iso:country":"AT",
    "sg:address":"Feuersang 212",
    "sg:city":"Flachau",
    "sg:classifiers":[
        {
            "category":"Travel",
            "subcategory":"Hotels & Motels",
            "type":"Entertainment"
        }
    ],
    "sg:phone":"+43 6457 26920",
    "sg:postcode":"5542",
    "sg:province":"Salzburg",
    "wof:name":"Apparthotel Dachsteinblick",
    "wof:placetype":"venue"
},
  "geometry": {"coordinates":[13.3938770294,47.3675460815],"type":"Point"}
}