{
  "type": "Feature",
  "properties": {
    "addr:full":"Vorderreuthe 139 Bezau Vorarlberg 6870",
    "addr:housenumber":"139",
    "addr:postcode":"6870",
    "addr:street":"Vorderreuthe",
    "iso:country":"AT",
    "sg:address":"Vorderreuthe 139",
    "sg:city":"Bezau",
    "sg:orig_category":"Volksschulen",
    "sg:phone":"+43 5514 3159",
    "sg:postcode":"6870",
    "sg:province":"Vorarlberg",
    "wof:name":"Volksschule",
    "wof:placetype":"venue"
},
  "geometry": {"coordinates":[9.8937654495,47.3704986572],"type":"Point"}
}