{
  "type": "Feature",
  "properties": {
    "addr:full":"Georg Bucher-Str 10 Axams Tirol 6094",
    "addr:housenumber":"10",
    "addr:postcode":"6094",
    "addr:street":"Tirol",
    "iso:country":"AT",
    "sg:address":"Georg Bucher-Str 10",
    "sg:city":"Axams",
    "sg:orig_category":"Appartements / Ferienwohnungen",
    "sg:phone":"+43 5234 68736",
    "sg:postcode":"6094",
    "sg:province":"Tirol",
    "wof:name":"Zimmermann Josef",
    "wof:placetype":"venue"
},
  "geometry": {"coordinates":[11.2769212723,47.2309837341],"type":"Point"}
}