{
  "type": "Feature",
  "properties": {
    "addr:full":"Gr\u00f6retgasse 20 Wien Wien 1110",
    "addr:housenumber":"20",
    "addr:postcode":"1110",
    "addr:street":"Groeretgasse",
    "iso:country":"AT",
    "sg:address":"Gr\u00f6retgasse 20",
    "sg:city":"Wien",
    "sg:classifiers":[
        {
            "category":"Transit Center",
            "subcategory":"Freight",
            "type":"Transportation"
        }
    ],
    "sg:phone":"+43 1 7691525",
    "sg:postcode":"1110",
    "sg:province":"Wien",
    "sg:tags":[
        "towing",
        "trailer"
    ],
    "sg:website":"mietanhaenger.at/",
    "wof:name":"Andreas Breunh\u00f6lder und Ing. Friedrich Ungerb\u00f6ck GnbR",
    "wof:placetype":"venue"
},
  "geometry": {"coordinates":[16.4197444916,48.1709709167],"type":"Point"}
}