{
  "type": "Feature",
  "properties": {
    "iso:country":"AT",
    "sg:address":"Piloteng 106",
    "sg:city":"Wien",
    "sg:classifiers":[
        {
            "category":"Professional",
            "subcategory":"Computer Services",
            "type":"Services"
        }
    ],
    "sg:phone":"+43 1 28232620",
    "sg:postcode":"1220",
    "sg:province":"Wien",
    "sg:tags":[
        "software"
    ],
    "wof:name":"HSBAU EDV-GesmbH",
    "wof:placetype":"venue"
},
  "geometry": {"coordinates":[16.4927024841,48.2191619873],"type":"Point"}
}