{
  "type": "Feature",
  "properties": {
    "addr:full":"Gumpendorfer Str 108 Wien Wien 1060",
    "addr:housenumber":"108",
    "addr:postcode":"1060",
    "iso:country":"AT",
    "sg:address":"Gumpendorfer Str 108",
    "sg:city":"Wien",
    "sg:orig_category":"Unternehmensberatung",
    "sg:phone":"+43 1 599883003",
    "sg:postcode":"1060",
    "sg:province":"Wien",
    "wof:name":"Homacon KrankenhausberatunggmbH",
    "wof:placetype":"venue"
},
  "geometry": {"coordinates":[16.3457717896,48.1909179688],"type":"Point"}
}