{
  "type": "Feature",
  "properties": {
    "addr:full":"Wiener Strasse 46 Kapfenberg Steiermark 8605",
    "addr:housenumber":"46",
    "addr:postcode":"8605",
    "addr:street":"Wiener Strasse",
    "iso:country":"AT",
    "sg:address":"Wiener Strasse 46",
    "sg:city":"Kapfenberg",
    "sg:classifiers":[
        {
            "category":"Building & Trades",
            "subcategory":"Electrical",
            "type":"Services"
        }
    ],
    "sg:phone":"+43 3862 227060",
    "sg:postcode":"8605",
    "sg:province":"Steiermark",
    "sg:tags":[
        "plants",
        "plant",
        "industrial",
        "buildings",
        "construction"
    ],
    "wof:name":"Knorr Technik GmbH",
    "wof:placetype":"venue"
},
  "geometry": {"coordinates":[15.2918567657,47.4439163208],"type":"Point"}
}