{
  "type": "Feature",
  "properties": {
    "iso:country":"AT",
    "sg:address":"Nr 120",
    "sg:city":"St. Peter am Ottersbach",
    "sg:orig_category":"Tischlereien",
    "sg:phone":"+43 4334 772348",
    "sg:postcode":"8093",
    "sg:province":"Steiermark",
    "wof:name":"Schantl Friedrich",
    "wof:placetype":"venue"
},
  "geometry": {"coordinates":[15.7594327927,46.79920578],"type":"Point"}
}