{
  "type": "Feature",
  "properties": {
    "addr:full":"Schiefeck 3 Treubach Ober\u00f6sterreich 5272",
    "addr:housenumber":"3",
    "addr:postcode":"5272",
    "addr:street":"Schiefeck",
    "iso:country":"AT",
    "sg:address":"Schiefeck 3",
    "sg:city":"Treubach",
    "sg:orig_category":"Dachdeckereien",
    "sg:phone":"+43 7724 8005",
    "sg:postcode":"5272",
    "sg:province":"Ober\u00f6sterreich",
    "wof:name":"Uttenthaler Dachdeckerei und Spenglerei GmbH",
    "wof:placetype":"venue"
},
  "geometry": {"coordinates":[13.2190093994,48.1971855164],"type":"Point"}
}