{
  "type": "Feature",
  "properties": {
    "addr:full":"Wiener Str 58 Wiener Neustadt Nieder\u00f6sterreich 2700",
    "addr:postcode":"2700",
    "addr:street":"58",
    "iso:country":"AT",
    "sg:address":"Wiener Str 58",
    "sg:city":"Wiener Neustadt",
    "sg:orig_category":"Tabaktrafiken",
    "sg:phone":"+43 2622 22412",
    "sg:postcode":"2700",
    "sg:province":"Nieder\u00f6sterreich",
    "wof:name":"Ziegler Wolfgang",
    "wof:placetype":"venue"
},
  "geometry": {"coordinates":[16.2453174591,47.8174324036],"type":"Point"}
}