{
  "type": "Feature",
  "properties": {
    "addr:full":"Reuttener Str 22 Reutte Tirol 6600",
    "addr:postcode":"6600",
    "addr:street":"Str 22;Tirol",
    "iso:country":"AT",
    "sg:address":"Reuttener Str 22",
    "sg:city":"Reutte",
    "sg:orig_category":"Appartements / Ferienwohnungen",
    "sg:phone":"+43 5672 71037",
    "sg:postcode":"6600",
    "sg:province":"Tirol",
    "wof:name":"Moosbrugger Mary",
    "wof:placetype":"venue"
},
  "geometry": {"coordinates":[10.7091884613,47.4786148071],"type":"Point"}
}