{
  "type": "Feature",
  "properties": {
    "iso:country":"AT",
    "sg:address":"Nr 20",
    "sg:city":"Strallegg",
    "sg:orig_category":"Sportanlagen",
    "sg:phone":"+43 4331 743496",
    "sg:postcode":"8192",
    "sg:province":"Steiermark",
    "wof:name":"MOTOCROSS - WAGENRANCH",
    "wof:placetype":"venue"
},
  "geometry": {"coordinates":[15.7248001099,47.4109153748],"type":"Point"}
}