{
  "type": "Feature",
  "properties": {
    "addr:full":"Schimmelsprungg 35 Gars am Kamp Nieder\u00f6sterreich 3571",
    "addr:housenumber":"35",
    "addr:postcode":"3571",
    "addr:street":"Schimmelsprungg",
    "iso:country":"AT",
    "sg:address":"Schimmelsprungg 35",
    "sg:city":"Gars am Kamp",
    "sg:orig_category":"Pensionen / Privatzimmer",
    "sg:phone":"+43 2985 2135",
    "sg:postcode":"3571",
    "sg:province":"Nieder\u00f6sterreich",
    "wof:name":"Traint Helga",
    "wof:placetype":"venue"
},
  "geometry": {"coordinates":[15.6495923996,48.5852928162],"type":"Point"}
}