{
  "type": "Feature",
  "properties": {
    "iso:country":"AT",
    "sg:address":"Hauptstr 50",
    "sg:city":"St. Michael im Burgenland",
    "sg:classifiers":[
        {
            "category":"Professional",
            "subcategory":"Computer Services",
            "type":"Services"
        }
    ],
    "sg:phone":"+43 664 1627923",
    "sg:postcode":"7535",
    "sg:province":"Burgenland",
    "sg:tags":[
        "software"
    ],
    "wof:name":"Softwareentwicklung Tonnhofer & Knor OEG",
    "wof:placetype":"venue"
},
  "geometry": {"coordinates":[16.2690849304,47.1263465881],"type":"Point"}
}