{
  "type": "Feature",
  "properties": {
    "addr:full":"Erdbergstr 97/13 Wien Wien 1030",
    "addr:housenumber":"97 / 13",
    "addr:postcode":"1030",
    "addr:street":"Erdbergstr",
    "iso:country":"AT",
    "sg:address":"Erdbergstr 97/13",
    "sg:city":"Wien",
    "sg:orig_category":"Tonanlagen / Vermietung",
    "sg:phone":"+43 1 2724545",
    "sg:postcode":"1030",
    "sg:province":"Wien",
    "wof:name":"Kerschbaum Albin Ing",
    "wof:placetype":"venue"
},
  "geometry": {"coordinates":[16.4041881561,48.1969718933],"type":"Point"}
}