{
  "type": "Feature",
  "properties": {
    "addr:full":"Am Viktor-Hof 1 Kappel am Krappfeld K\u00e4rnten 9321",
    "addr:housenumber":"1",
    "addr:postcode":"9321",
    "addr:street":"Am Viktor-Hof;Kaernten",
    "iso:country":"AT",
    "sg:address":"Am Viktor-Hof 1",
    "sg:city":"Kappel am Krappfeld",
    "sg:classifiers":[
        {
            "category":"Utilities",
            "subcategory":"Electric",
            "type":"Services"
        }
    ],
    "sg:phone":"+43 4342 6248270",
    "sg:postcode":"9321",
    "sg:province":"K\u00e4rnten",
    "sg:tags":[
        "energy"
    ],
    "wof:name":"SOLARIS SONNENENERGIESYSTEME GESMBH",
    "wof:placetype":"venue"
},
  "geometry": {"coordinates":[14.4860048294,46.8377075195],"type":"Point"}
}