{
  "type": "Feature",
  "properties": {
    "iso:country":"AT",
    "sg:address":"Daimlerstr 12",
    "sg:city":"Linz",
    "sg:orig_category":"Banken U Sparkassen",
    "sg:phone":"+43 4373 23800270",
    "sg:postcode":"4030",
    "sg:province":"Ober\u00f6sterreich",
    "wof:name":"Raiffeisenbank Kleinm\u00fcnchen/Linz regGenmbH",
    "wof:placetype":"venue"
},
  "geometry": {"coordinates":[14.286403656,48.2515716553],"type":"Point"}
}