{
  "type": "Feature",
  "properties": {
    "addr:full":"Bahnhofstr 19 Spittal an der Drau K\u00e4rnten 9800",
    "addr:housenumber":"19",
    "addr:postcode":"9800",
    "addr:street":"Bahnhofstr;Kaernten",
    "iso:country":"AT",
    "sg:address":"Bahnhofstr 19",
    "sg:city":"Spittal an der Drau",
    "sg:orig_category":"Offsetdruckereien",
    "sg:phone":"+43 4762 2543",
    "sg:postcode":"9800",
    "sg:province":"K\u00e4rnten",
    "wof:name":"Petz-Druck GesmbH",
    "wof:placetype":"venue"
},
  "geometry": {"coordinates":[13.4905490875,46.7970733643],"type":"Point"}
}