{
  "type": "Feature",
  "properties": {
    "addr:full":"Irlachring 14 Seekirchen am Wallersee Salzburg 5201",
    "addr:housenumber":"14",
    "addr:postcode":"5201",
    "addr:street":"Irlachring;Salzburg",
    "iso:country":"AT",
    "sg:address":"Irlachring 14",
    "sg:city":"Seekirchen am Wallersee",
    "sg:orig_category":"Transportunternehmen",
    "sg:phone":"+43 6212 2424",
    "sg:postcode":"5201",
    "sg:province":"Salzburg",
    "wof:name":"Ausweger Josef",
    "wof:placetype":"venue"
},
  "geometry": {"coordinates":[13.1218862534,47.9047470093],"type":"Point"}
}