{
  "type": "Feature",
  "properties": {
    "addr:full":"Flachg 14-16 Wien Wien 1150",
    "addr:postcode":"14-16;1150",
    "iso:country":"AT",
    "sg:address":"Flachg 14-16",
    "sg:city":"Wien",
    "sg:orig_category":"Galvanisieranstalten",
    "sg:phone":"+43 1 9822418",
    "sg:postcode":"1150",
    "sg:province":"Wien",
    "wof:name":"Kudrna GesmbH",
    "wof:placetype":"venue"
},
  "geometry": {"coordinates":[16.3140945435,48.1946182251],"type":"Point"}
}