{
  "type": "Feature",
  "properties": {
    "addr:full":"Schmidg 11 Krems an der Donau Nieder\u00f6sterreich 3500",
    "addr:housenumber":"11",
    "addr:postcode":"3500",
    "addr:street":"Schmidg",
    "iso:country":"AT",
    "sg:address":"Schmidg 11",
    "sg:city":"Krems an der Donau",
    "sg:orig_category":"Alternativtherapie",
    "sg:phone":"+43 4327 3279852",
    "sg:postcode":"3500",
    "sg:province":"Nieder\u00f6sterreich",
    "wof:name":"Naturheilkunde J\u00fcrgen Kainz",
    "wof:placetype":"venue"
},
  "geometry": {"coordinates":[15.5962438583,48.4104919434],"type":"Point"}
}