{
  "type": "Feature",
  "properties": {
    "addr:full":"Grazer Str 311 Pischelsdorf in Steiermark Steiermark 8212",
    "addr:housenumber":"311",
    "addr:postcode":"8212",
    "addr:street":"Pischelsdorf In",
    "iso:country":"AT",
    "sg:address":"Grazer Str 311",
    "sg:city":"Pischelsdorf in Steiermark",
    "sg:orig_category":"Maler, Anstreicher U Lackierer",
    "sg:phone":"+43 4331 1325450",
    "sg:postcode":"8212",
    "sg:province":"Steiermark",
    "wof:name":"Kaser Heimo",
    "wof:placetype":"venue"
},
  "geometry": {"coordinates":[15.8019390106,47.170124054],"type":"Point"}
}