{
  "type": "Feature",
  "properties": {
    "addr:full":"Steinbruch 43 Bad Ischl Ober\u00f6sterreich 4820",
    "addr:housenumber":"43",
    "addr:postcode":"4820",
    "addr:street":"Steinbruch",
    "iso:country":"AT",
    "sg:address":"Steinbruch 43",
    "sg:city":"Bad Ischl",
    "sg:orig_category":"Pensionen / Privatzimmer",
    "sg:phone":"+43 6132 23535",
    "sg:postcode":"4820",
    "sg:province":"Ober\u00f6sterreich",
    "wof:name":"Fr\u00fchst\u00fcckspension Villa Schratt",
    "wof:placetype":"venue"
},
  "geometry": {"coordinates":[13.6046543121,47.718296051],"type":"Point"}
}