{
  "type": "Feature",
  "properties": {
    "addr:full":"Margaretenstr 38 Wien Wien 1040",
    "addr:housenumber":"38",
    "addr:postcode":"1040",
    "addr:street":"Margaretenstr",
    "iso:country":"AT",
    "sg:address":"Margaretenstr 38",
    "sg:city":"Wien",
    "sg:orig_category":"Fliesen- U Plattenverlegungen",
    "sg:phone":"+43 1 5875111",
    "sg:postcode":"1040",
    "sg:province":"Wien",
    "wof:name":"Saco HandelsgesmbH",
    "wof:placetype":"venue"
},
  "geometry": {"coordinates":[16.3640384674,48.1957588196],"type":"Point"}
}