{
  "type": "Feature",
  "properties": {
    "addr:full":"Br\u00e4unerstr 2 Wien Wien 1010",
    "addr:housenumber":"2",
    "addr:postcode":"1010",
    "addr:street":"Braeunerstr",
    "iso:country":"AT",
    "sg:address":"Br\u00e4unerstr 2",
    "sg:city":"Wien",
    "sg:orig_category":"Boutiquen",
    "sg:phone":"+43 1 5335098",
    "sg:postcode":"1010",
    "sg:province":"Wien",
    "wof:name":"Tramontana Claudia Couture",
    "wof:placetype":"venue"
},
  "geometry": {"coordinates":[16.369342804,48.2085838318],"type":"Point"}
}