{
  "type": "Feature",
  "properties": {
    "addr:full":"Nr 55 Ried im Traunkreis Ober\u00f6sterreich 4551",
    "addr:postcode":"4551",
    "addr:street":"Nr 55",
    "iso:country":"AT",
    "sg:address":"Nr 55",
    "sg:city":"Ried im Traunkreis",
    "sg:orig_category":"Biologische Produkte",
    "sg:phone":"+43 7588 6446",
    "sg:postcode":"4551",
    "sg:province":"Ober\u00f6sterreich",
    "wof:name":"CONA HandelsgesmbH",
    "wof:placetype":"venue"
},
  "geometry": {"coordinates":[14.0738592148,48.0253601074],"type":"Point"}
}