{
  "type": "Feature",
  "properties": {
    "iso:country":"AT",
    "sg:address":"Nr 3",
    "sg:city":"Schwarzenberg am B\u00f6hmerwald",
    "sg:orig_category":"Autovermietung",
    "sg:phone":"+43 7280 302",
    "sg:postcode":"4164",
    "sg:province":"Ober\u00f6sterreich",
    "wof:name":"W\u00f6ss Franz Racing",
    "wof:placetype":"venue"
},
  "geometry": {"coordinates":[8.3865814209,48.600189209],"type":"Point"}
}