{
  "type": "Feature",
  "properties": {
    "addr:full":"Operng 6 Wien Wien 1010",
    "addr:housenumber":"6",
    "addr:postcode":"1010",
    "addr:street":"Operng",
    "iso:country":"AT",
    "sg:address":"Operng 6",
    "sg:city":"Wien",
    "sg:orig_category":"Banken U Sparkassen",
    "sg:phone":"+43 1 514400",
    "sg:postcode":"1010",
    "sg:province":"Wien",
    "wof:name":"Bank Austria Creditanstalt Handelsbank AG",
    "wof:placetype":"venue"
},
  "geometry": {"coordinates":[16.3680896759,48.2033081055],"type":"Point"}
}