{
  "type": "Feature",
  "properties": {
    "addr:full":"Pontlatzer Str 39 Innsbruck Tirol 6020",
    "addr:postcode":"6020",
    "addr:street":"Str 39;Tirol",
    "iso:country":"AT",
    "sg:address":"Pontlatzer Str 39",
    "sg:city":"Innsbruck",
    "sg:orig_category":"Tonanlagen / Vermietung",
    "sg:phone":"+43 4351 2261071",
    "sg:postcode":"6020",
    "sg:province":"Tirol",
    "wof:name":"Clear Sound Veranstaltungstechnik u Tonstudio",
    "wof:placetype":"venue"
},
  "geometry": {"coordinates":[11.4411964417,47.2753105164],"type":"Point"}
}