{
  "type": "Feature",
  "properties": {
    "iso:country":"AT",
    "sg:address":"Adalbert-Stifter-Str 16",
    "sg:city":"Ried im Innkreis",
    "sg:orig_category":"Bilder",
    "sg:phone":"+43 7752 82424",
    "sg:postcode":"4910",
    "sg:province":"Ober\u00f6sterreich",
    "wof:name":"Motion-World Ges.mb.H. Wechselbilder - Wackelbilder - Kippbilder",
    "wof:placetype":"venue"
},
  "geometry": {"coordinates":[13.484749794,48.203540802],"type":"Point"}
}