{
  "type": "Feature",
  "properties": {
    "iso:country":"AT",
    "sg:address":"Nr 31",
    "sg:city":"Sierndorf",
    "sg:orig_category":"Transportunternehmen",
    "sg:phone":"+43 4322 672403",
    "sg:postcode":"2011",
    "sg:province":"Nieder\u00f6sterreich",
    "wof:name":"Summerer & Sohn GesmbH",
    "wof:placetype":"venue"
},
  "geometry": {"coordinates":[16.1676559448,48.4293861389],"type":"Point"}
}