{
  "type": "Feature",
  "properties": {
    "addr:full":"Hauptstr 57a Guntramsdorf Nieder\u00f6sterreich 2353",
    "addr:housenumber":"57a",
    "addr:postcode":"2353",
    "addr:street":"Hauptstr",
    "iso:country":"AT",
    "sg:address":"Hauptstr 57a",
    "sg:city":"Guntramsdorf",
    "sg:orig_category":"Elektroinstallationsunternehmen",
    "sg:phone":"+43 2236 53273",
    "sg:postcode":"2353",
    "sg:province":"Nieder\u00f6sterreich",
    "wof:name":"Sommerbauer Ernst",
    "wof:placetype":"venue"
},
  "geometry": {"coordinates":[16.316204071,48.0488128662],"type":"Point"}
}