{
  "type": "Feature",
  "properties": {
    "addr:full":"M\u00f6slestrasse 15 Altach Vorarlberg 6844",
    "addr:housenumber":"15",
    "addr:postcode":"6844",
    "addr:street":"Moeslestrasse",
    "iso:country":"AT",
    "sg:address":"M\u00f6slestrasse 15",
    "sg:city":"Altach",
    "sg:orig_category":"Elastic Fabrics, Knitted Fabrics, Ribbons, Laces, Cords And Braiding",
    "sg:phone":"+43 5576 721790",
    "sg:postcode":"6844",
    "sg:province":"Vorarlberg",
    "wof:name":"Weber Ges.m.b.H.",
    "wof:placetype":"venue"
},
  "geometry": {"coordinates":[9.6469326019,47.3485603333],"type":"Point"}
}