{
  "type": "Feature",
  "properties": {
    "iso:country":"AT",
    "sg:address":"Grieskai 10",
    "sg:city":"Graz",
    "sg:orig_category":"Beteiligungen U Finanzierungen",
    "sg:phone":"+43 810 001080",
    "sg:postcode":"8020",
    "sg:province":"Steiermark",
    "wof:name":"GIS Geb\u00fchren Info Service GmbH - Service Center Graz (f Stmk)",
    "wof:placetype":"venue"
},
  "geometry": {"coordinates":[15.4344854355,47.0698165894],"type":"Point"}
}