{
  "type": "Feature",
  "properties": {
    "iso:country":"AT",
    "sg:address":"Heid-Werkstrasse 4",
    "sg:city":"Stockerau",
    "sg:classifiers":[
        {
            "category":"Home & Garden",
            "subcategory":"Hardware",
            "type":"Retail Goods"
        }
    ],
    "sg:phone":"+43 2266 6990",
    "sg:postcode":"2000",
    "sg:province":"Nieder\u00f6sterreich",
    "sg:tags":[
        "agricultural",
        "implement"
    ],
    "sg:website":"cimbria.at",
    "wof:name":"Cimbria Heid GmbH",
    "wof:placetype":"venue"
},
  "geometry": {"coordinates":[16.224773407,48.395450592],"type":"Point"}
}