{
  "type": "Feature",
  "properties": {
    "iso:country":"AT",
    "sg:address":"Nr 127",
    "sg:city":"Graden",
    "sg:classifiers":[
        {
            "category":"Travel",
            "subcategory":"Hotels & Motels",
            "type":"Entertainment"
        }
    ],
    "sg:phone":"+43 4331 4423800",
    "sg:postcode":"8593",
    "sg:province":"Steiermark",
    "wof:name":"Bergwirt Hotel-Pension",
    "wof:placetype":"venue"
},
  "geometry": {"coordinates":[15.033780098,47.132598877],"type":"Point"}
}