{
  "type": "Feature",
  "properties": {
    "addr:full":"Falkenburg 177 Irdning Steiermark 8952",
    "addr:housenumber":"177",
    "addr:postcode":"8952",
    "iso:country":"AT",
    "sg:address":"Falkenburg 177",
    "sg:city":"Irdning",
    "sg:orig_category":"Optische Artikel",
    "sg:phone":"+43 676 4195272",
    "sg:postcode":"8952",
    "sg:province":"Steiermark",
    "wof:name":"Schuster Johannes",
    "wof:placetype":"venue"
},
  "geometry": {"coordinates":[14.0990781784,47.5013122559],"type":"Point"}
}