{
  "type": "Feature",
  "properties": {
    "addr:full":"Muhrhoferweg 1-5 Wien Wien 1110",
    "addr:housenumber":"1-5",
    "addr:postcode":"1110",
    "addr:street":"Muhrhoferweg",
    "iso:country":"AT",
    "sg:address":"Muhrhoferweg 1-5",
    "sg:city":"Wien",
    "sg:orig_category":"Fleischhauereien",
    "sg:phone":"+43 1 7675424",
    "sg:postcode":"1110",
    "sg:province":"Wien",
    "wof:name":"Schirnhofer-Breisler GesmbH - Shop in Shop",
    "wof:placetype":"venue"
},
  "geometry": {"coordinates":[16.4690990448,48.1547012329],"type":"Point"}
}