{
  "type": "Feature",
  "properties": {
    "addr:full":"Nr 88A Bernstein Burgenland 7434",
    "addr:housenumber":"88a",
    "addr:postcode":"7434",
    "addr:street":"Nr",
    "iso:country":"AT",
    "sg:address":"Nr 88A",
    "sg:city":"Bernstein",
    "sg:orig_category":"Transportunternehmen",
    "sg:phone":"+43 3354 7367",
    "sg:postcode":"7434",
    "sg:province":"Burgenland",
    "wof:name":"Schranz Transportunternehmen",
    "wof:placetype":"venue"
},
  "geometry": {"coordinates":[16.2558078766,47.4056777954],"type":"Point"}
}