{
  "type": "Feature",
  "properties": {
    "addr:full":"Volksstr 5 Steyr Ober\u00f6sterreich 4400",
    "addr:housenumber":"5",
    "addr:postcode":"4400",
    "addr:street":"Volksstr;Oberoesterreich",
    "iso:country":"AT",
    "sg:address":"Volksstr 5",
    "sg:city":"Steyr",
    "sg:orig_category":"Tanzschulen",
    "sg:phone":"+43 7355 6548",
    "sg:postcode":"4400",
    "sg:province":"Ober\u00f6sterreich",
    "wof:name":"Hofer Klaus",
    "wof:placetype":"venue"
},
  "geometry": {"coordinates":[14.4110937119,48.0372085571],"type":"Point"}
}