{
  "type": "Feature",
  "properties": {
    "addr:full":"Joseph-Haydn-Pl 6 Bad Tatzmannsdorf Burgenland 7431",
    "addr:housenumber":"6",
    "addr:postcode":"7431",
    "addr:street":"Joseph-Haydn-Pl",
    "iso:country":"AT",
    "sg:address":"Joseph-Haydn-Pl 6",
    "sg:city":"Bad Tatzmannsdorf",
    "sg:classifiers":[
        {
            "category":"Travel",
            "subcategory":"Hotels & Motels",
            "type":"Entertainment"
        }
    ],
    "sg:phone":"+43 3353 84280",
    "sg:postcode":"7431",
    "sg:province":"Burgenland",
    "wof:name":"Hotel-Restaurant Zum Kastell",
    "wof:placetype":"venue"
},
  "geometry": {"coordinates":[16.2301044464,47.3330001831],"type":"Point"}
}