{
  "type": "Feature",
  "properties": {
    "addr:full":"Daringerg 12-20/Stg 9 Wien Wien 1190",
    "addr:housenumber":"12-20 / stg 9",
    "addr:postcode":"1190",
    "iso:country":"AT",
    "sg:address":"Daringerg 12-20/Stg 9",
    "sg:city":"Wien",
    "sg:orig_category":"Rauchfangkehrer",
    "sg:phone":"+43 1 2707778",
    "sg:postcode":"1190",
    "sg:province":"Wien",
    "wof:name":"Weidhofer Harald & Co KG",
    "wof:placetype":"venue"
},
  "geometry": {"coordinates":[16.3493022919,48.2389793396],"type":"Point"}
}