{
  "type": "Feature",
  "properties": {
    "addr:full":"Am Modenapark 2 Wien Wien 1030",
    "addr:housenumber":"2",
    "addr:postcode":"1030",
    "addr:street":"Am Modenapark",
    "iso:country":"AT",
    "sg:address":"Am Modenapark 2",
    "sg:city":"Wien",
    "sg:orig_category":"Garagen Parkgaragen",
    "sg:phone":"+43 1 7133346",
    "sg:postcode":"1030",
    "sg:province":"Wien",
    "wof:name":"MODENAPARKGARAGE - Inh Mag Martin Stippert",
    "wof:placetype":"venue"
},
  "geometry": {"coordinates":[16.3829116821,48.2005462646],"type":"Point"}
}