{
  "type": "Feature",
  "properties": {
    "addr:full":"Innrain 91 Scharnitz Tirol 6108",
    "addr:housenumber":"91",
    "addr:postcode":"6108",
    "addr:street":"Innrain;Tirol",
    "iso:country":"AT",
    "sg:address":"Innrain 91",
    "sg:city":"Scharnitz",
    "sg:orig_category":"Pensionen / Privatzimmer",
    "sg:phone":"+43 5213 5253",
    "sg:postcode":"6108",
    "sg:province":"Tirol",
    "wof:name":"G\u00e4stehaus Urwalek",
    "wof:placetype":"venue"
},
  "geometry": {"coordinates":[11.2646799088,47.3903579712],"type":"Point"}
}