{
  "type": "Feature",
  "properties": {
    "addr:full":"Gewerbering 2 Gramatneusiedl Nieder\u00f6sterreich 2440",
    "addr:housenumber":"2",
    "addr:postcode":"2440",
    "addr:street":"Gewerbering",
    "iso:country":"AT",
    "sg:address":"Gewerbering 2",
    "sg:city":"Gramatneusiedl",
    "sg:orig_category":"Autoglas",
    "sg:phone":"+43 2234 79977",
    "sg:postcode":"2440",
    "sg:province":"Nieder\u00f6sterreich",
    "wof:name":"Pilkington AGR Austria GmbH",
    "wof:placetype":"venue"
},
  "geometry": {"coordinates":[16.4571857452,48.0128631592],"type":"Point"}
}