{
  "type": "Feature",
  "properties": {
    "addr:full":"Johannespl 6-8/II Imst Tirol 6460",
    "addr:housenumber":"6-8 / ii",
    "addr:postcode":"6460",
    "addr:street":"Johannespl;Tirol",
    "iso:country":"AT",
    "sg:address":"Johannespl 6-8/II",
    "sg:city":"Imst",
    "sg:orig_category":"Psychologen",
    "sg:phone":"+43 4369 910156806",
    "sg:postcode":"6460",
    "sg:province":"Tirol",
    "wof:name":"Kr\u00f6ss Nathalie Mag",
    "wof:placetype":"venue"
},
  "geometry": {"coordinates":[10.737487793,47.2392234802],"type":"Point"}
}