{
  "type": "Feature",
  "properties": {
    "addr:full":"Hirtenberger Str 21 Leobersdorf Nieder\u00f6sterreich 2544",
    "addr:postcode":"2544",
    "addr:street":"Str 21",
    "iso:country":"AT",
    "sg:address":"Hirtenberger Str 21",
    "sg:city":"Leobersdorf",
    "sg:orig_category":"Fleischhauereien",
    "sg:phone":"+43 2256 62957",
    "sg:postcode":"2544",
    "sg:province":"Nieder\u00f6sterreich",
    "wof:name":"Schirnhofer-Breisler GesmbH - Shop in Shop",
    "wof:placetype":"venue"
},
  "geometry": {"coordinates":[16.2213821411,47.9349327087],"type":"Point"}
}