{
  "type": "Feature",
  "properties": {
    "addr:full":"Mitterstr 295 Feldkirchen Steiermark 8073",
    "addr:housenumber":"295",
    "addr:postcode":"8073",
    "iso:country":"AT",
    "sg:address":"Mitterstr 295",
    "sg:city":"Feldkirchen",
    "sg:orig_category":"Transportunternehmen",
    "sg:phone":"+43 664 1003954",
    "sg:postcode":"8073",
    "sg:province":"Steiermark",
    "wof:name":"Genssler Joachim",
    "wof:placetype":"venue"
},
  "geometry": {"coordinates":[15.4257850647,46.9982147217],"type":"Point"}
}