{
  "type": "Feature",
  "properties": {
    "iso:country":"AT",
    "sg:address":"Wiener Str 65",
    "sg:city":"Kapfenberg",
    "sg:orig_category":"Steinmetzbetriebe",
    "sg:phone":"+43 3862 224520",
    "sg:postcode":"8605",
    "sg:province":"Steiermark",
    "wof:name":"Matschy Stein & Design - Ing Johann Matschy",
    "wof:placetype":"venue"
},
  "geometry": {"coordinates":[15.2975091934,47.4457588196],"type":"Point"}
}