{
  "type": "Feature",
  "properties": {
    "addr:full":"Gm\u00fcnder Str 16 Litschau Nieder\u00f6sterreich 3874",
    "addr:housenumber":"16",
    "addr:postcode":"3874",
    "addr:street":"Str",
    "iso:country":"AT",
    "sg:address":"Gm\u00fcnder Str 16",
    "sg:city":"Litschau",
    "sg:orig_category":"Holzbau",
    "sg:phone":"+43 2865 3830",
    "sg:postcode":"3874",
    "sg:province":"Nieder\u00f6sterreich",
    "wof:name":"Brandl Holzbau GmbH",
    "wof:placetype":"venue"
},
  "geometry": {"coordinates":[15.0453643799,48.9441757202],"type":"Point"}
}