{
  "type": "Feature",
  "properties": {
    "addr:full":"Kirchstr 4 G\u00f6fis Vorarlberg 6811",
    "addr:housenumber":"4",
    "addr:postcode":"6811",
    "addr:street":"Kirchstr",
    "iso:country":"AT",
    "sg:address":"Kirchstr 4",
    "sg:city":"G\u00f6fis",
    "sg:orig_category":"Sonnenstudios",
    "sg:phone":"+43 5522 73340",
    "sg:postcode":"6811",
    "sg:province":"Vorarlberg",
    "wof:name":"List Massageinstitut",
    "wof:placetype":"venue"
},
  "geometry": {"coordinates":[-90.2028045654,36.7827301025],"type":"Point"}
}