{
  "type": "Feature",
  "properties": {
    "addr:full":"Voglerweg 18 Telfs Tirol 6410",
    "addr:housenumber":"18",
    "addr:postcode":"6410",
    "addr:street":"Voglerweg;Tirol",
    "iso:country":"AT",
    "sg:address":"Voglerweg 18",
    "sg:city":"Telfs",
    "sg:orig_category":"Waren Aller Art",
    "sg:phone":"+43 5262 654110",
    "sg:postcode":"6410",
    "sg:province":"Tirol",
    "wof:name":"Handels-Marketing GesmbH",
    "wof:placetype":"venue"
},
  "geometry": {"coordinates":[11.0770206451,47.3220291138],"type":"Point"}
}