{
  "type": "Feature",
  "properties": {
    "addr:full":"Plantagenweg 4 Langenzersdorf Nieder\u00f6sterreich 2103",
    "addr:housenumber":"4",
    "addr:postcode":"2103",
    "addr:street":"Plantagenweg",
    "iso:country":"AT",
    "sg:address":"Plantagenweg 4",
    "sg:city":"Langenzersdorf",
    "sg:orig_category":"Self Storage",
    "sg:phone":"+43 4322 4430900",
    "sg:postcode":"2103",
    "sg:province":"Nieder\u00f6sterreich",
    "sg:website":"selfstorage.at",
    "wof:name":"SelfStorage-Dein Lager LagervermietungsgesmbH",
    "wof:placetype":"venue"
},
  "geometry": {"coordinates":[16.3680419922,48.2897758484],"type":"Point"}
}