{
  "type": "Feature",
  "properties": {
    "addr:full":"Pokeritschstr 9a Klagenfurt K\u00e4rnten 9020",
    "addr:housenumber":"9a",
    "addr:postcode":"9020",
    "addr:street":"Pokeritschstr;Kaernten",
    "iso:country":"AT",
    "sg:address":"Pokeritschstr 9a",
    "sg:city":"Klagenfurt",
    "sg:orig_category":"Reifen U Reifendienste",
    "sg:phone":"+43 4346 33100310",
    "sg:postcode":"9020",
    "sg:province":"K\u00e4rnten",
    "wof:name":"Klagenfurter Reifen Stadl Anton Widmann",
    "wof:placetype":"venue"
},
  "geometry": {"coordinates":[14.3645610809,46.6319503784],"type":"Point"}
}