{
  "type": "Feature",
  "properties": {
    "addr:full":"Kehlhof 8 Abtenau Salzburg 5441",
    "addr:housenumber":"8",
    "addr:postcode":"5441",
    "addr:street":"Kehlhof;Salzburg",
    "iso:country":"AT",
    "sg:address":"Kehlhof 8",
    "sg:city":"Abtenau",
    "sg:orig_category":"Pensionen / Privatzimmer",
    "sg:phone":"+43 6243 2445",
    "sg:postcode":"5441",
    "sg:province":"Salzburg",
    "wof:name":"Edhof",
    "wof:placetype":"venue"
},
  "geometry": {"coordinates":[13.3463354111,47.5727653503],"type":"Point"}
}