{
  "type": "Feature",
  "properties": {
    "iso:country":"AT",
    "sg:address":"Dorfpl 16",
    "sg:city":"Waldneukirchen",
    "sg:orig_category":"Friseure U Frisiersalons",
    "sg:phone":"+43 7258 3875",
    "sg:postcode":"4595",
    "sg:province":"Ober\u00f6sterreich",
    "wof:name":"Friseur Heidi Hahn",
    "wof:placetype":"venue"
},
  "geometry": {"coordinates":[14.2613801956,47.9969558716],"type":"Point"}
}