{
  "type": "Feature",
  "properties": {
    "addr:full":"Schl\u00f6gelg 24 Wiener Neustadt Nieder\u00f6sterreich 2700",
    "addr:housenumber":"24",
    "addr:postcode":"2700",
    "addr:street":"Schloegelg",
    "iso:country":"AT",
    "sg:address":"Schl\u00f6gelg 24",
    "sg:city":"Wiener Neustadt",
    "sg:orig_category":"Hobbyvereine",
    "sg:phone":"+43 2622 27996",
    "sg:postcode":"2700",
    "sg:province":"Nieder\u00f6sterreich",
    "wof:name":"Naturfreunde \u00f6sterreich",
    "wof:placetype":"venue"
},
  "geometry": {"coordinates":[16.2469558716,47.8146629333],"type":"Point"}
}