{
  "type": "Feature",
  "properties": {
    "addr:full":"Dorfstr 14 Kundl Tirol 6250",
    "addr:housenumber":"14",
    "addr:postcode":"6250",
    "addr:street":"Dorfstr;Tirol",
    "iso:country":"AT",
    "sg:address":"Dorfstr 14",
    "sg:city":"Kundl",
    "sg:orig_category":"Bankomat-Standorte",
    "sg:phone":"+43 5338 72440",
    "sg:postcode":"6250",
    "sg:province":"Tirol",
    "wof:name":"Bankomat d Raiffeisenbank Kundl regGenmbH",
    "wof:placetype":"venue"
},
  "geometry": {"coordinates":[11.9839687347,47.4682159424],"type":"Point"}
}