{
  "type": "Feature",
  "properties": {
    "addr:full":"Nr 37 Obergurgl Tirol 6456",
    "addr:postcode":"6456",
    "addr:street":"Nr;Tirol",
    "iso:country":"AT",
    "sg:address":"Nr 37",
    "sg:city":"Obergurgl",
    "sg:classifiers":[
        {
            "category":"Travel",
            "subcategory":"Hotels & Motels",
            "type":"Entertainment"
        }
    ],
    "sg:phone":"+43 5256 63250",
    "sg:postcode":"6456",
    "sg:province":"Tirol",
    "wof:name":"Hotel Hochfirst",
    "wof:placetype":"venue"
},
  "geometry": {"coordinates":[11.0263767242,46.8701171875],"type":"Point"}
}