{
  "type": "Feature",
  "properties": {
    "addr:full":"Kellerg 1 Potzneusiedl Burgenland 2473",
    "addr:housenumber":"1",
    "addr:postcode":"2473",
    "addr:street":"Kellerg",
    "iso:country":"AT",
    "sg:address":"Kellerg 1",
    "sg:city":"Potzneusiedl",
    "sg:orig_category":"Banken U Sparkassen",
    "sg:phone":"+43 2145 2289",
    "sg:postcode":"2473",
    "sg:province":"Burgenland",
    "wof:name":"Raiffeisenbank Parndorf-Neudorf-Potzneusiedl-Gattendorf reg GenmbH",
    "wof:placetype":"venue"
},
  "geometry": {"coordinates":[16.9453258514,48.0454025269],"type":"Point"}
}