{
  "type": "Feature",
  "properties": {
    "addr:full":"Am Berg 44 Maissau Nieder\u00f6sterreich 3712",
    "addr:housenumber":"44",
    "addr:postcode":"3712",
    "addr:street":"Am Berg",
    "iso:country":"AT",
    "sg:address":"Am Berg 44",
    "sg:city":"Maissau",
    "sg:classifiers":[
        {
            "category":"Restaurant",
            "type":"Food & Drink"
        }
    ],
    "sg:phone":"+43 2958 82334",
    "sg:postcode":"3712",
    "sg:province":"Nieder\u00f6sterreich",
    "wof:name":"Hotel-Landgasthof Zum Naderer",
    "wof:placetype":"venue"
},
  "geometry": {"coordinates":[15.8224430084,48.5744934082],"type":"Point"}
}