{
  "type": "Feature",
  "properties": {
    "addr:full":"Stafflerweg 3 Axams Tirol 6094",
    "addr:housenumber":"3",
    "addr:postcode":"6094",
    "addr:street":"Stafflerweg;Tirol",
    "iso:country":"AT",
    "sg:address":"Stafflerweg 3",
    "sg:city":"Axams",
    "sg:orig_category":"Installationsunternehmen",
    "sg:phone":"+43 5234 68402",
    "sg:postcode":"6094",
    "sg:province":"Tirol",
    "wof:name":"Hell Hans GmbH & Co KG",
    "wof:placetype":"venue"
},
  "geometry": {"coordinates":[11.2785587311,47.2319526672],"type":"Point"}
}