{
  "type": "Feature",
  "properties": {
    "addr:full":"Praterstr. 28 Wien Wien 1020",
    "addr:housenumber":"28",
    "addr:postcode":"1020",
    "addr:street":"Praterstr.",
    "iso:country":"AT",
    "sg:address":"Praterstr. 28",
    "sg:city":"Wien",
    "sg:classifiers":[
        {
            "category":"Travel",
            "subcategory":"Travel Agent",
            "type":"Entertainment"
        }
    ],
    "sg:phone":"+43 4312 11480",
    "sg:postcode":"1020",
    "sg:province":"Wien",
    "sg:tags":[
        "business"
    ],
    "wof:name":"HOMMERSON GMBH & CO. KG AHRODITE",
    "wof:placetype":"venue"
},
  "geometry": {"coordinates":[16.3839626312,48.2143058777],"type":"Point"}
}