{
  "type": "Feature",
  "properties": {
    "iso:country":"AT",
    "sg:address":"Dr.-Schober-Str 22",
    "sg:city":"Perg",
    "sg:orig_category":"Architekten",
    "sg:phone":"+43 7262 538630",
    "sg:postcode":"4320",
    "sg:province":"Ober\u00f6sterreich",
    "wof:name":"Quast Johannes Dipl-Ing",
    "wof:placetype":"venue"
},
  "geometry": {"coordinates":[14.6363430023,48.2502212524],"type":"Point"}
}