{
  "type": "Feature",
  "properties": {
    "iso:country":"AT",
    "sg:address":"M\u00fcnzgrabenstr 48",
    "sg:city":"Graz",
    "sg:classifiers":[
        {
            "category":"Travel",
            "subcategory":"Hotels & Motels",
            "type":"Entertainment"
        }
    ],
    "sg:phone":"+43 4331 6837766",
    "sg:postcode":"8010",
    "sg:province":"Steiermark",
    "sg:website":"stadthalle.co.at",
    "wof:name":"Hotel zur Stadthalle Inh Ing F Johannes",
    "wof:placetype":"venue"
},
  "geometry": {"coordinates":[15.4431800842,47.0685653687],"type":"Point"}
}