{
  "type": "Feature",
  "properties": {
    "addr:full":"Haidach 100 F\u00fcgen Tirol 6263",
    "addr:housenumber":"100",
    "addr:postcode":"6263",
    "addr:street":"Haidach;Tirol",
    "iso:country":"AT",
    "sg:address":"Haidach 100",
    "sg:city":"F\u00fcgen",
    "sg:orig_category":"Isoliermaterialien",
    "sg:phone":"+43 5288 64828",
    "sg:postcode":"6263",
    "sg:province":"Tirol",
    "wof:name":"Kemper N. Handelsvertretungen",
    "wof:placetype":"venue"
},
  "geometry": {"coordinates":[11.8419713974,47.3419494629],"type":"Point"}
}