{
  "type": "Feature",
  "properties": {
    "iso:country":"AT",
    "sg:address":"Nr 70b",
    "sg:city":"Gerlos",
    "sg:orig_category":"Tischlereien",
    "sg:phone":"+43 5284 531414",
    "sg:postcode":"6281",
    "sg:province":"Tirol",
    "wof:name":"Staudacher Alois KG",
    "wof:placetype":"venue"
},
  "geometry": {"coordinates":[12.0359144211,47.2256088257],"type":"Point"}
}