{
  "type": "Feature",
  "properties": {
    "addr:full":"Sonnenwendg. 30 Klagenfurt K\u00e4rnten 9020",
    "addr:housenumber":"30",
    "addr:postcode":"9020",
    "addr:street":"Sonnenwendg.;Kaernten",
    "iso:country":"AT",
    "sg:address":"Sonnenwendg. 30",
    "sg:city":"Klagenfurt",
    "sg:classifiers":[
        {
            "category":"Communications",
            "subcategory":"Newspaper",
            "type":"Services"
        }
    ],
    "sg:phone":"+43 4346 331457",
    "sg:postcode":"9020",
    "sg:province":"K\u00e4rnten",
    "sg:tags":[
        "advertising"
    ],
    "wof:name":"SELDEN & PARTNER GMBH",
    "wof:placetype":"venue"
},
  "geometry": {"coordinates":[14.3274202347,46.6254196167],"type":"Point"}
}