{
  "type": "Feature",
  "properties": {
    "addr:full":"Dr.-Karl-Liebleitner-Ring 1-3 Korneuburg Nieder\u00f6sterreich 2100",
    "addr:housenumber":"1-3",
    "addr:postcode":"2100",
    "addr:street":"Dr.-Karl-Liebleitner-Ring;Niederoesterreich",
    "iso:country":"AT",
    "sg:address":"Dr.-Karl-Liebleitner-Ring 1-3",
    "sg:city":"Korneuburg",
    "sg:orig_category":"Tischlereien",
    "sg:phone":"+43 4322 6272754",
    "sg:postcode":"2100",
    "sg:province":"Nieder\u00f6sterreich",
    "wof:name":"Hrabak Franz",
    "wof:placetype":"venue"
},
  "geometry": {"coordinates":[16.331325531,48.346370697],"type":"Point"}
}