{
  "type": "Feature",
  "properties": {
    "iso:country":"AT",
    "sg:address":"R\u00fctti 1",
    "sg:city":"Koblach",
    "sg:orig_category":"Garten- U Landschaftsgestaltung",
    "sg:phone":"+43 5523 636080",
    "sg:postcode":"6842",
    "sg:province":"Vorarlberg",
    "wof:name":"Der Staudeng\u00e4rtner",
    "wof:placetype":"venue"
},
  "geometry": {"coordinates":[9.6024236679,47.3305778503],"type":"Point"}
}