{
  "type": "Feature",
  "properties": {
    "iso:country":"AT",
    "sg:address":"Heizwerkstrasse 4",
    "sg:city":"Wien",
    "sg:classifiers":[
        {
            "category":"Wholesale",
            "subcategory":"Auto Parts",
            "type":"Manufacturing & Wholesale Goods"
        }
    ],
    "sg:phone":"+43 1 6157110",
    "sg:postcode":"1230",
    "sg:province":"Wien",
    "sg:tags":[
        "bent"
    ],
    "sg:website":"jantsch.com",
    "wof:name":"J. Jantsch & Co Ges.m.b.H.",
    "wof:placetype":"venue"
},
  "geometry": {"coordinates":[16.3667907715,48.1414718628],"type":"Point"}
}