{
  "type": "Feature",
  "properties": {
    "addr:full":"Nr 17 Pregarten Ober\u00f6sterreich 4230",
    "addr:postcode":"4230",
    "addr:street":"Nr 17",
    "iso:country":"AT",
    "sg:address":"Nr 17",
    "sg:city":"Pregarten",
    "sg:orig_category":"Volksschulen",
    "sg:phone":"+43 4372 363255",
    "sg:postcode":"4230",
    "sg:province":"Ober\u00f6sterreich",
    "wof:name":"Volksschule",
    "wof:placetype":"venue"
},
  "geometry": {"coordinates":[166.9221496582,-0.5282999873],"type":"Point"}
}