{
  "type": "Feature",
  "properties": {
    "addr:full":"W\u00e4hringer Str 76 Wien Wien 1090",
    "addr:postcode":"1090",
    "addr:street":"Str 76",
    "iso:country":"AT",
    "sg:address":"W\u00e4hringer Str 76",
    "sg:city":"Wien",
    "sg:orig_category":"Friseure U Frisiersalons",
    "sg:phone":"+43 1 31084990",
    "sg:postcode":"1090",
    "sg:province":"Wien",
    "sg:website":"www.petritsch.at",
    "wof:name":"Petritsch Hair Design",
    "wof:placetype":"venue"
},
  "geometry": {"coordinates":[16.3507595062,48.2240142822],"type":"Point"}
}