{
  "type": "Feature",
  "properties": {
    "addr:full":"Minorg 70 Wien Wien 1140",
    "addr:housenumber":"70",
    "addr:postcode":"1140",
    "addr:street":"Minorg",
    "iso:country":"AT",
    "sg:address":"Minorg 70",
    "sg:city":"Wien",
    "sg:orig_category":"Textilwaren / Erzeugung U Gro\u00c3\u0178handel",
    "sg:phone":"+43 1 9146560",
    "sg:postcode":"1140",
    "sg:province":"Wien",
    "wof:name":"Tabowin Repr\u00e4sentanzen & HandelsgesmbH",
    "wof:placetype":"venue"
},
  "geometry": {"coordinates":[16.2702960968,48.2014465332],"type":"Point"}
}