{
  "type": "Feature",
  "properties": {
    "addr:full":"Hans Czettel-Str 9 Gm\u00fcnd Nieder\u00f6sterreich 3950",
    "addr:housenumber":"9",
    "addr:postcode":"3950",
    "addr:street":"Czettel-Str;Niederoesterreich",
    "iso:country":"AT",
    "sg:address":"Hans Czettel-Str 9",
    "sg:city":"Gm\u00fcnd",
    "sg:orig_category":"Metallbau",
    "sg:phone":"+43 2852 51565",
    "sg:postcode":"3950",
    "sg:province":"Nieder\u00f6sterreich",
    "wof:name":"Z\u00f6hrer Buhmann Metall- und Anlagenbau GmbH",
    "wof:placetype":"venue"
},
  "geometry": {"coordinates":[14.9971628189,48.758014679],"type":"Point"}
}