{
  "type": "Feature",
  "properties": {
    "iso:country":"AT",
    "sg:address":"Wurlitzerg 3-7",
    "sg:city":"Wien",
    "sg:orig_category":"Cnc-Bearbeitungen",
    "sg:phone":"+43 4314 8633220",
    "sg:postcode":"1160",
    "sg:province":"Wien",
    "wof:name":"Trmal-Verbindungselemente",
    "wof:placetype":"venue"
},
  "geometry": {"coordinates":[16.3166427612,48.2122001648],"type":"Point"}
}