{
  "type": "Feature",
  "properties": {
    "iso:country":"AT",
    "sg:address":"Mehrerauer Str 38",
    "sg:city":"Bregenz",
    "sg:orig_category":"Lebensmittel / Einzelhandel",
    "sg:phone":"+43 5574 74313",
    "sg:postcode":"6900",
    "sg:province":"Vorarlberg",
    "wof:name":"ADEG Aktiv Markt",
    "wof:placetype":"venue"
},
  "geometry": {"coordinates":[9.7277851105,47.5028686523],"type":"Point"}
}