{
  "type": "Feature",
  "properties": {
    "addr:full":"Nr 154 Dellach K\u00e4rnten 9635",
    "addr:postcode":"9635",
    "addr:street":"Nr;Dellach Kaernten",
    "iso:country":"AT",
    "sg:address":"Nr 154",
    "sg:city":"Dellach",
    "sg:orig_category":"Installationsunternehmen",
    "sg:phone":"+43 4718 519",
    "sg:postcode":"9635",
    "sg:province":"K\u00e4rnten",
    "wof:name":"Kronabetter Karl",
    "wof:placetype":"venue"
},
  "geometry": {"coordinates":[13.0779047012,46.662311554],"type":"Point"}
}