{
  "type": "Feature",
  "properties": {
    "addr:full":"Scheiblberg 40 Rohrbach in Ober\u00f6sterreich Ober\u00f6sterreich 4150",
    "addr:housenumber":"40",
    "addr:postcode":"4150",
    "addr:street":"Scheiblberg",
    "iso:country":"AT",
    "sg:address":"Scheiblberg 40",
    "sg:city":"Rohrbach in Ober\u00f6sterreich",
    "sg:orig_category":"Solaranlagen",
    "sg:phone":"+43 4372 8989050",
    "sg:postcode":"4150",
    "sg:province":"Ober\u00f6sterreich",
    "wof:name":"Solar-Partner Energie- u Umwelttechnik GmbH",
    "wof:placetype":"venue"
},
  "geometry": {"coordinates":[13.9871826172,48.5583076477],"type":"Point"}
}