{
  "type": "Feature",
  "properties": {
    "iso:country":"AT",
    "sg:address":"Am Eisernen Tor 11",
    "sg:city":"Graz",
    "sg:orig_category":"Damenmoden",
    "sg:phone":"+43 316 817517",
    "sg:postcode":"8010",
    "sg:province":"Steiermark",
    "wof:name":"H & M Hennes & Mauritz GesmbH",
    "wof:placetype":"venue"
},
  "geometry": {"coordinates":[15.4413471222,47.0685386658],"type":"Point"}
}