{
  "type": "Feature",
  "properties": {
    "addr:full":"Bruenner Strasse 52 Wien Wien 1210",
    "addr:housenumber":"52",
    "addr:postcode":"1210",
    "addr:street":"Bruenner Strasse",
    "iso:country":"AT",
    "sg:address":"Bruenner Strasse 52",
    "sg:city":"Wien",
    "sg:orig_category":"Dienstleistungen, Telekommunikation",
    "sg:phone":"+43 4312 77280",
    "sg:postcode":"1210",
    "sg:province":"Wien",
    "sg:website":"http://www.one.at/",
    "wof:name":"Connect Austria GmbH",
    "wof:placetype":"venue"
},
  "geometry": {"coordinates":[16.4272193909,48.3085517883],"type":"Point"}
}