{
  "type": "Feature",
  "properties": {
    "iso:country":"AT",
    "sg:address":"Hauptplatz 32",
    "sg:city":"Kittsee",
    "sg:classifiers":[
        {
            "category":"Building & Trades",
            "subcategory":"Electrical",
            "type":"Services"
        }
    ],
    "sg:phone":"+43 2143 2313",
    "sg:postcode":"2421",
    "sg:province":"Burgenland",
    "sg:tags":[
        "installation"
    ],
    "wof:name":"Kuni Richard Ges.m.b.H. & Co KG",
    "wof:placetype":"venue"
},
  "geometry": {"coordinates":[17.0654258728,48.0912971497],"type":"Point"}
}