{
  "type": "Feature",
  "properties": {
    "iso:country":"AT",
    "sg:address":"Pesenbach 72",
    "sg:city":"Feldkirchen an der Donau",
    "sg:orig_category":"Schlossereien",
    "sg:phone":"+43 4369 910310375",
    "sg:postcode":"4101",
    "sg:province":"Ober\u00f6sterreich",
    "wof:name":"Traxler G\u00fcnter",
    "wof:placetype":"venue"
},
  "geometry": {"coordinates":[14.0729103088,48.3465118408],"type":"Point"}
}