{
  "type": "Feature",
  "properties": {
    "addr:full":"Kellertal 106a Telfs Tirol 6410",
    "addr:housenumber":"106a",
    "addr:postcode":"6410",
    "addr:street":"Tirol",
    "iso:country":"AT",
    "sg:address":"Kellertal 106a",
    "sg:city":"Telfs",
    "sg:orig_category":"Maler, Anstreicher U Lackierer",
    "sg:phone":"+43 4352 3884122",
    "sg:postcode":"6410",
    "sg:province":"Tirol",
    "wof:name":"M\u00e4rz Peter",
    "wof:placetype":"venue"
},
  "geometry": {"coordinates":[11.1506156921,47.2956314087],"type":"Point"}
}