{
  "type": "Feature",
  "properties": {
    "addr:full":"Pf.-Von-Gauer-Str. 75 Neumarkt am Wallersee Salzburg 5202",
    "addr:housenumber":"75",
    "addr:postcode":"5202",
    "addr:street":"Pf.-Von-Gauer-Str.;Salzburg",
    "iso:country":"AT",
    "sg:address":"Pf.-Von-Gauer-Str. 75",
    "sg:city":"Neumarkt am Wallersee",
    "sg:classifiers":[
        {
            "category":"Sports & Exercise",
            "subcategory":"Playing Field",
            "type":"Entertainment"
        }
    ],
    "sg:phone":"+43 4362 164147",
    "sg:postcode":"5202",
    "sg:province":"Salzburg",
    "sg:tags":[
        "game"
    ],
    "wof:name":"KOHLBAUER HANDELS GMBH",
    "wof:placetype":"venue"
},
  "geometry": {"coordinates":[13.2245721817,47.9449386597],"type":"Point"}
}