{
  "type": "Feature",
  "properties": {
    "addr:full":"Schwanenstadt Ober\u00f6sterreich 4690",
    "addr:postcode":"4690",
    "iso:country":"AT",
    "sg:city":"Schwanenstadt",
    "sg:orig_category":"Dienstleistungen, Recht",
    "sg:postcode":"4690",
    "sg:province":"Ober\u00f6sterreich",
    "sg:website":"http://www.jusline.at/jusline/jusRaNavMainN.html",
    "wof:name":"JUSLINE Austria: Rechtsanwaltsverzeichnis",
    "wof:placetype":"venue"
},
  "geometry": {"coordinates":[13.7731847763,48.0545158386],"type":"Point"}
}