{
  "type": "Feature",
  "properties": {
    "iso:country":"AT",
    "sg:address":"Reisnerstr 30",
    "sg:city":"Wien",
    "sg:orig_category":"Psychotherapie",
    "sg:phone":"+43 1 7133957",
    "sg:postcode":"1030",
    "sg:province":"Wien",
    "wof:name":"Grossmann-Garger Brigitte Dr",
    "wof:placetype":"venue"
},
  "geometry": {"coordinates":[16.3836193085,48.1999168396],"type":"Point"}
}