{
  "type": "Feature",
  "properties": {
    "addr:full":"Preysingg 30 Wien Wien 1150",
    "addr:housenumber":"30",
    "addr:postcode":"1150",
    "addr:street":"Preysingg",
    "iso:country":"AT",
    "sg:address":"Preysingg 30",
    "sg:city":"Wien",
    "sg:orig_category":"Immobilienmakler",
    "sg:phone":"+43 1 9825395",
    "sg:postcode":"1150",
    "sg:province":"Wien",
    "wof:name":"Leukauf Immobilien GesmbH",
    "wof:placetype":"venue"
},
  "geometry": {"coordinates":[16.3262329102,48.1983070374],"type":"Point"}
}