{
  "type": "Feature",
  "properties": {
    "addr:full":"Walser Str 24 Riezlern Vorarlberg 6991",
    "addr:postcode":"6991",
    "addr:street":"Str 24",
    "iso:country":"AT",
    "sg:address":"Walser Str 24",
    "sg:city":"Riezlern",
    "sg:orig_category":"Tankstellen",
    "sg:phone":"+43 4355 1752560",
    "sg:postcode":"6991",
    "sg:province":"Vorarlberg",
    "wof:name":"Kohl Johannes",
    "wof:placetype":"venue"
},
  "geometry": {"coordinates":[10.1910686493,47.3606338501],"type":"Point"}
}