{
  "type": "Feature",
  "properties": {
    "addr:full":"Rossakg 16 Wien Wien 1230",
    "addr:housenumber":"16",
    "addr:postcode":"1230",
    "addr:street":"Rossakg",
    "iso:country":"AT",
    "sg:address":"Rossakg 16",
    "sg:city":"Wien",
    "sg:orig_category":"Gitter",
    "sg:phone":"+43 4316 652222",
    "sg:postcode":"1230",
    "sg:province":"Wien",
    "wof:name":"P\u00f6sniker Franz - Holzgittererzeugung",
    "wof:placetype":"venue"
},
  "geometry": {"coordinates":[16.329284668,48.1471061707],"type":"Point"}
}