{
  "type": "Feature",
  "properties": {
    "iso:country":"AT",
    "sg:address":"Kolpingstr. 15",
    "sg:city":"Wien",
    "sg:classifiers":[
        {
            "category":"Shopping",
            "subcategory":"Computers & Home Electronics",
            "type":"Retail Goods"
        }
    ],
    "sg:phone":"+43 4316 1621800",
    "sg:postcode":"1230",
    "sg:province":"Wien",
    "sg:tags":[
        "electronic",
        "electrical",
        "equipment"
    ],
    "wof:name":"ING. FRANZ SCHMACHTL KG",
    "wof:placetype":"venue"
},
  "geometry": {"coordinates":[16.3443851471,48.139957428],"type":"Point"}
}