{
  "type": "Feature",
  "properties": {
    "addr:full":"Schiesstattstrasse 23 St. Andr\u00e4 K\u00e4rnten 9433",
    "addr:housenumber":"23",
    "addr:postcode":"9433",
    "addr:street":"Schiesstattstrasse;Kaernten",
    "iso:country":"AT",
    "sg:address":"Schiesstattstrasse 23",
    "sg:city":"St. Andr\u00e4",
    "sg:classifiers":[
        {
            "category":"Professional",
            "subcategory":"Art Services",
            "type":"Services"
        }
    ],
    "sg:phone":"+43 4358 2389",
    "sg:postcode":"9433",
    "sg:province":"K\u00e4rnten",
    "sg:tags":[
        "artistic",
        "glazings"
    ],
    "sg:website":"glas-prinz.at",
    "wof:name":"Glas Prinz",
    "wof:placetype":"venue"
},
  "geometry": {"coordinates":[14.8203630447,46.7648353577],"type":"Point"}
}