{
  "type": "Feature",
  "properties": {
    "addr:full":"Teschnerg 4 Wien Wien 1180",
    "addr:housenumber":"4",
    "addr:postcode":"1180",
    "addr:street":"Teschnerg",
    "iso:country":"AT",
    "sg:address":"Teschnerg 4",
    "sg:city":"Wien",
    "sg:orig_category":"Installationsunternehmen",
    "sg:phone":"+43 1 4021706",
    "sg:postcode":"1180",
    "sg:province":"Wien",
    "wof:name":"Mann Herbert",
    "wof:placetype":"venue"
},
  "geometry": {"coordinates":[16.3362388611,48.2234573364],"type":"Point"}
}