{
  "type": "Feature",
  "properties": {
    "addr:full":"Hetzendorfer Str 80 Wien Wien 1120",
    "addr:postcode":"1120",
    "addr:street":"Str 80",
    "iso:country":"AT",
    "sg:address":"Hetzendorfer Str 80",
    "sg:city":"Wien",
    "sg:orig_category":"Boutiquen",
    "sg:phone":"+43 1 8026294",
    "sg:postcode":"1120",
    "sg:province":"Wien",
    "wof:name":"La Piccolezza",
    "wof:placetype":"venue"
},
  "geometry": {"coordinates":[16.3105602264,48.1670608521],"type":"Point"}
}