{
  "type": "Feature",
  "properties": {
    "iso:country":"AT",
    "sg:address":"Maierh\u00f6fen 1A",
    "sg:city":"St. Veit an der G\u00f6lsen",
    "sg:orig_category":"Autohandel",
    "sg:phone":"+43 2763 77043",
    "sg:postcode":"3161",
    "sg:province":"Nieder\u00f6sterreich",
    "wof:name":"Renz Josef",
    "wof:placetype":"venue"
},
  "geometry": {"coordinates":[15.6694297791,48.0433006287],"type":"Point"}
}