{
  "type": "Feature",
  "properties": {
    "addr:full":"Uga 79 Dam\u00fcls Vorarlberg 6884",
    "addr:housenumber":"79",
    "addr:postcode":"6884",
    "addr:street":"Damuels Vorarlberg",
    "iso:country":"AT",
    "sg:address":"Uga 79",
    "sg:city":"Dam\u00fcls",
    "sg:orig_category":"Pensionen / Privatzimmer",
    "sg:phone":"+43 5510 286",
    "sg:postcode":"6884",
    "sg:province":"Vorarlberg",
    "wof:name":"Pension Johanna",
    "wof:placetype":"venue"
},
  "geometry": {"coordinates":[32.304649353,1.3651900291],"type":"Point"}
}