{
  "type": "Feature",
  "properties": {
    "addr:full":"Brunner Str 59/Obj 59 Wien Wien 1230",
    "addr:housenumber":"59 / obj 59",
    "addr:postcode":"1230",
    "addr:street":"Str",
    "iso:country":"AT",
    "sg:address":"Brunner Str 59/Obj 59",
    "sg:city":"Wien",
    "sg:orig_category":"Luftentfeuchter U -Entfeuchtungsanlagen",
    "sg:phone":"+43 4316 1642980",
    "sg:postcode":"1230",
    "sg:province":"Wien",
    "sg:website":"munters.at",
    "wof:name":"Munters GmbH Zweigniederlassung Wien",
    "wof:placetype":"venue"
},
  "geometry": {"coordinates":[16.2822799683,48.1347465515],"type":"Point"}
}