{
  "type": "Feature",
  "properties": {
    "addr:full":"Gentzg 55 Wien Wien 1180",
    "addr:housenumber":"55",
    "addr:postcode":"1180",
    "addr:street":"Gentzg",
    "iso:country":"AT",
    "sg:address":"Gentzg 55",
    "sg:city":"Wien",
    "sg:orig_category":"\u00c3\u201enderungsschneidereien",
    "sg:phone":"+43 4314 701333",
    "sg:postcode":"1180",
    "sg:province":"Wien",
    "wof:name":"Kreci Renate",
    "wof:placetype":"venue"
},
  "geometry": {"coordinates":[16.341375351,48.2272224426],"type":"Point"}
}