{
  "type": "Feature",
  "properties": {
    "addr:full":"Schopenhauerstrasse 36 Wien Wien 1180",
    "addr:housenumber":"36",
    "addr:postcode":"1180",
    "addr:street":"Schopenhauerstrasse",
    "iso:country":"AT",
    "sg:address":"Schopenhauerstrasse 36",
    "sg:city":"Wien",
    "sg:classifiers":[
        {
            "category":"Professional",
            "subcategory":"Advertising",
            "type":"Services"
        }
    ],
    "sg:phone":"+43 1 4081835",
    "sg:postcode":"1180",
    "sg:province":"Wien",
    "sg:tags":[
        "articles"
    ],
    "sg:website":"imagesnack.at",
    "wof:name":"Imagedrink & snack",
    "wof:placetype":"venue"
},
  "geometry": {"coordinates":[16.3427295685,48.2241668701],"type":"Point"}
}