{
  "type": "Feature",
  "properties": {
    "addr:full":"Wehrstrasse 22 Rohrbach an der G\u00f6lsen Nieder\u00f6sterreich 3163",
    "addr:housenumber":"22",
    "addr:postcode":"3163",
    "addr:street":"Wehrstrasse;Niederoesterreich",
    "iso:country":"AT",
    "sg:address":"Wehrstrasse 22",
    "sg:city":"Rohrbach an der G\u00f6lsen",
    "sg:classifiers":[
        {
            "category":"Structure",
            "subcategory":"Bridge",
            "type":"Public Place"
        }
    ],
    "sg:phone":"+43 2764 2354",
    "sg:postcode":"3163",
    "sg:province":"Nieder\u00f6sterreich",
    "sg:tags":[
        "construction"
    ],
    "wof:name":"Kohl & Sohn Transport GesmbH & Baumeister",
    "wof:placetype":"venue"
},
  "geometry": {"coordinates":[15.7436361313,48.0416183472],"type":"Point"}
}