{
  "type": "Feature",
  "properties": {
    "addr:full":"Marktpl 5 Prinzersdorf Nieder\u00f6sterreich 3385",
    "addr:housenumber":"5",
    "addr:postcode":"3385",
    "addr:street":"Marktpl",
    "iso:country":"AT",
    "sg:address":"Marktpl 5",
    "sg:city":"Prinzersdorf",
    "sg:orig_category":"Betonerzeugnisse",
    "sg:phone":"+43 2749 2346",
    "sg:postcode":"3385",
    "sg:province":"Nieder\u00f6sterreich",
    "wof:name":"Zahorik Martin",
    "wof:placetype":"venue"
},
  "geometry": {"coordinates":[15.5544900894,48.1992416382],"type":"Point"}
}