{
  "type": "Feature",
  "properties": {
    "addr:full":"Breitenfurter Str 381A Wien Wien 1230",
    "addr:postcode":"1230",
    "addr:street":"Str 381A",
    "iso:country":"AT",
    "sg:address":"Breitenfurter Str 381A",
    "sg:city":"Wien",
    "sg:orig_category":"Freizeit- U Sportbekleidung",
    "sg:phone":"+43 4318 691691",
    "sg:postcode":"1230",
    "sg:province":"Wien",
    "wof:name":"P3 Sportswear",
    "wof:placetype":"venue"
},
  "geometry": {"coordinates":[16.2878227234,48.1376876831],"type":"Point"}
}