{
  "type": "Feature",
  "properties": {
    "addr:full":"Dreihackeng 6 Wien Wien 1090",
    "addr:housenumber":"6",
    "addr:postcode":"1090",
    "addr:street":"Dreihackeng",
    "iso:country":"AT",
    "sg:address":"Dreihackeng 6",
    "sg:city":"Wien",
    "sg:orig_category":"Tischlereien",
    "sg:phone":"+43 1 3192643",
    "sg:postcode":"1090",
    "sg:province":"Wien",
    "wof:name":"Broz Robert",
    "wof:placetype":"venue"
},
  "geometry": {"coordinates":[16.3541717529,48.2262496948],"type":"Point"}
}