{
  "type": "Feature",
  "properties": {
    "iso:country":"AT",
    "sg:address":"Anton-Reichel-Strasse 14",
    "sg:city":"St. Veit an der Glan",
    "sg:classifiers":[
        {
            "category":"Banks & Credit Unions",
            "subcategory":"Bureau De Change",
            "type":"Services"
        }
    ],
    "sg:phone":"+43 4212 71386",
    "sg:postcode":"9300",
    "sg:province":"K\u00e4rnten",
    "sg:tags":[
        "flat",
        "construction",
        "roof"
    ],
    "wof:name":"Sch\u00f6ffmann Dachdeckerei-Spenglerei GmbH",
    "wof:placetype":"venue"
},
  "geometry": {"coordinates":[14.3577518463,46.7791061401],"type":"Point"}
}