{
  "type": "Feature",
  "properties": {
    "addr:full":"Blumeng 312 Gamlitz Steiermark 8462",
    "addr:housenumber":"312",
    "addr:postcode":"8462",
    "iso:country":"AT",
    "sg:address":"Blumeng 312",
    "sg:city":"Gamlitz",
    "sg:orig_category":"Selbstklebefolien U -Papiere",
    "sg:phone":"+43 4366 44927870",
    "sg:postcode":"8462",
    "sg:province":"Steiermark",
    "wof:name":"Sunfoil - Autofolien",
    "wof:placetype":"venue"
},
  "geometry": {"coordinates":[15.5574016571,46.7226448059],"type":"Point"}
}