{
  "type": "Feature",
  "properties": {
    "addr:full":"Viehhauser Str 25 Wals Salzburg 5071",
    "addr:postcode":"5071",
    "addr:street":"Str 25;Salzburg",
    "iso:country":"AT",
    "sg:address":"Viehhauser Str 25",
    "sg:city":"Wals",
    "sg:orig_category":"Landwirtschaftliche Produkte",
    "sg:phone":"+43 662 852251",
    "sg:postcode":"5071",
    "sg:province":"Salzburg",
    "wof:name":"Gerl Josef",
    "wof:placetype":"venue"
},
  "geometry": {"coordinates":[12.9858551025,47.7852973938],"type":"Point"}
}