{
  "type": "Feature",
  "properties": {
    "addr:full":"Zwettler G 6 Krems an der Donau Nieder\u00f6sterreich 3500",
    "addr:housenumber":"6",
    "addr:postcode":"3500",
    "addr:street":"Zwettler G",
    "iso:country":"AT",
    "sg:address":"Zwettler G 6",
    "sg:city":"Krems an der Donau",
    "sg:orig_category":"Weine / Einzelhandel",
    "sg:phone":"+43 2732 76154",
    "sg:postcode":"3500",
    "sg:province":"Nieder\u00f6sterreich",
    "wof:name":"Weinbau St\u00f6ger",
    "wof:placetype":"venue"
},
  "geometry": {"coordinates":[15.6222877502,48.4144172668],"type":"Point"}
}