{
  "type": "Feature",
  "properties": {
    "iso:country":"AT",
    "sg:address":"Kallham 55",
    "sg:city":"Neumarkt im Hausruckkreis",
    "sg:classifiers":[
        {
            "category":"Home & Garden",
            "subcategory":"Household Appliances",
            "type":"Retail Goods"
        }
    ],
    "sg:phone":"+43 7733 67140",
    "sg:postcode":"4720",
    "sg:province":"Ober\u00f6sterreich",
    "sg:tags":[
        "electric"
    ],
    "wof:name":"Karl Heinz Demmelmayr",
    "wof:placetype":"venue"
},
  "geometry": {"coordinates":[13.7368049622,48.2686347961],"type":"Point"}
}