{
  "type": "Feature",
  "properties": {
    "addr:full":"Stettner Str 50a Eugendorf Salzburg 5301",
    "addr:postcode":"5301",
    "addr:street":"Str 50A Eugendorf",
    "iso:country":"AT",
    "sg:address":"Stettner Str 50a",
    "sg:city":"Eugendorf",
    "sg:orig_category":"Transportunternehmen",
    "sg:phone":"+43 6225 8260",
    "sg:postcode":"5301",
    "sg:province":"Salzburg",
    "wof:name":"M\u00f6sl Anton",
    "wof:placetype":"venue"
},
  "geometry": {"coordinates":[13.1400928497,47.8523178101],"type":"Point"}
}