{
  "type": "Feature",
  "properties": {
    "addr:full":"Karolingerstr 20 Maria Saal K\u00e4rnten 9063",
    "addr:housenumber":"20",
    "addr:postcode":"9063",
    "addr:street":"Karolingerstr",
    "iso:country":"AT",
    "sg:address":"Karolingerstr 20",
    "sg:city":"Maria Saal",
    "sg:orig_category":"Elektroinstallationsunternehmen",
    "sg:phone":"+43 4223 2037",
    "sg:postcode":"9063",
    "sg:province":"K\u00e4rnten",
    "wof:name":"Elektro Nagele Johann",
    "wof:placetype":"venue"
},
  "geometry": {"coordinates":[14.3169736862,46.6845664978],"type":"Point"}
}