{
  "type": "Feature",
  "properties": {
    "addr:full":"Nr 36 Deutsch Wagram Nieder\u00f6sterreich 2232",
    "addr:postcode":"2232",
    "addr:street":"Nr",
    "iso:country":"AT",
    "sg:address":"Nr 36",
    "sg:city":"Deutsch Wagram",
    "sg:classifiers":[
        {
            "category":"Taxi",
            "type":"Transportation"
        }
    ],
    "sg:phone":"+43 2247 2461",
    "sg:postcode":"2232",
    "sg:province":"Nieder\u00f6sterreich",
    "sg:tags":[
        "personentransporte",
        "u"
    ],
    "wof:name":"Eipeldauer Friedrich",
    "wof:placetype":"venue"
},
  "geometry": {"coordinates":[16.5652046204,48.2991485596],"type":"Point"}
}