{
  "type": "Feature",
  "properties": {
    "iso:country":"AT",
    "sg:address":"Mollardg 19/Hof",
    "sg:city":"Wien",
    "sg:orig_category":"Zahntechnische Laboratorien",
    "sg:phone":"+43 4315 970341",
    "sg:postcode":"1060",
    "sg:province":"Wien",
    "wof:name":"Lochmann Martin",
    "wof:placetype":"venue"
},
  "geometry": {"coordinates":[16.3504657745,48.1947135925],"type":"Point"}
}