{
  "type": "Feature",
  "properties": {
    "addr:full":"Moritschstr 2 Villach K\u00e4rnten 9500",
    "addr:housenumber":"2",
    "addr:postcode":"9500",
    "addr:street":"Moritschstr;Kaernten",
    "iso:country":"AT",
    "sg:address":"Moritschstr 2",
    "sg:city":"Villach",
    "sg:orig_category":"Unternehmensberatung",
    "sg:phone":"+43 4242 21234",
    "sg:postcode":"9500",
    "sg:province":"K\u00e4rnten",
    "wof:name":"iXat Unternehmensberatung Ing Michael Kucher",
    "wof:placetype":"venue"
},
  "geometry": {"coordinates":[13.8465118408,46.6121330261],"type":"Point"}
}