{
  "type": "Feature",
  "properties": {
    "addr:full":"Zollgasse 10 Dornbirn Vorarlberg 6850",
    "addr:housenumber":"10",
    "addr:postcode":"6850",
    "addr:street":"Zollgasse",
    "iso:country":"AT",
    "sg:address":"Zollgasse 10",
    "sg:city":"Dornbirn",
    "sg:classifiers":[
        {
            "category":"Professional",
            "subcategory":"Accounting & Tax Preparation",
            "type":"Services"
        }
    ],
    "sg:phone":"+43 5572 38010",
    "sg:postcode":"6850",
    "sg:province":"Vorarlberg",
    "sg:tags":[
        "payroll"
    ],
    "sg:website":"vrz.net",
    "wof:name":"VRZ Informatik Ges.m.b.H.",
    "wof:placetype":"venue"
},
  "geometry": {"coordinates":[9.7370138168,47.4159584045],"type":"Point"}
}