{
  "type": "Feature",
  "properties": {
    "addr:full":"Nr 70 Bad Kreuzen Ober\u00f6sterreich 4362",
    "addr:housenumber":"70",
    "addr:postcode":"4362",
    "addr:street":"Nr",
    "iso:country":"AT",
    "sg:address":"Nr 70",
    "sg:city":"Bad Kreuzen",
    "sg:orig_category":"Holzhandel",
    "sg:phone":"+43 7266 62290",
    "sg:postcode":"4362",
    "sg:province":"Ober\u00f6sterreich",
    "wof:name":"Wenigwieser Josef - S\u00e4gerestholzhandel",
    "wof:placetype":"venue"
},
  "geometry": {"coordinates":[14.8063306808,48.267124176],"type":"Point"}
}