{
  "type": "Feature",
  "properties": {
    "iso:country":"AT",
    "sg:address":"Tirolweg 10",
    "sg:city":"Tulfes",
    "sg:orig_category":"Erdbau",
    "sg:phone":"+43 5223 78089",
    "sg:postcode":"6075",
    "sg:province":"Tirol",
    "wof:name":"K\u00f6\u00dfler Hermann",
    "wof:placetype":"venue"
},
  "geometry": {"coordinates":[11.5363512039,47.257774353],"type":"Point"}
}