{
  "type": "Feature",
  "properties": {
    "addr:full":"Kapf 1 Sulz-R\u00f6this Vorarlberg 6832",
    "addr:housenumber":"1",
    "addr:postcode":"6832",
    "addr:street":"Kapf",
    "iso:country":"AT",
    "sg:address":"Kapf 1",
    "sg:city":"Sulz-R\u00f6this",
    "sg:orig_category":"Weiterbildungsinstitute M Allg U Berufl Bildungsangebot",
    "sg:phone":"+43 4355 22442900",
    "sg:postcode":"6832",
    "sg:province":"Vorarlberg",
    "sg:website":"bildungshaus-batschuns.at",
    "wof:name":"Bildungshaus Batschuns",
    "wof:placetype":"venue"
},
  "geometry": {"coordinates":[9.6654367447,47.2804832458],"type":"Point"}
}