{
  "type": "Feature",
  "properties": {
    "addr:full":"Rennbahng 4 Wiener Neustadt Nieder\u00f6sterreich 2700",
    "addr:housenumber":"4",
    "addr:postcode":"2700",
    "addr:street":"Rennbahng",
    "iso:country":"AT",
    "sg:address":"Rennbahng 4",
    "sg:city":"Wiener Neustadt",
    "sg:orig_category":"Lehrmittel",
    "sg:phone":"+43 2622 61642",
    "sg:postcode":"2700",
    "sg:province":"Nieder\u00f6sterreich",
    "wof:name":"M.E.M.O.-Lehrmittel",
    "wof:placetype":"venue"
},
  "geometry": {"coordinates":[16.2653999329,47.8174781799],"type":"Point"}
}