{
  "type": "Feature",
  "properties": {
    "addr:full":"Eduard-Klinger-Strasse 15 St. Andr\u00e4-W\u00f6rdern Nieder\u00f6sterreich 3423",
    "addr:housenumber":"15",
    "addr:postcode":"3423",
    "addr:street":"Eduard-Klinger-Strasse",
    "iso:country":"AT",
    "sg:address":"Eduard-Klinger-Strasse 15",
    "sg:city":"St. Andr\u00e4-W\u00f6rdern",
    "sg:classifiers":[
        {
            "category":"Real Estate",
            "subcategory":"Real Estate Services",
            "type":"Services"
        }
    ],
    "sg:phone":"+43 2242 38100",
    "sg:postcode":"3423",
    "sg:province":"Nieder\u00f6sterreich",
    "sg:tags":[
        "enclosure"
    ],
    "sg:website":"tobias.at",
    "wof:name":"Adolf Tobias GmbH",
    "wof:placetype":"venue"
},
  "geometry": {"coordinates":[16.1998901367,48.3315086365],"type":"Point"}
}