{
  "type": "Feature",
  "properties": {
    "addr:full":"Carl-Hofmann-Weg 35 Heidenreichstein Nieder\u00f6sterreich 3860",
    "addr:housenumber":"35",
    "addr:postcode":"3860",
    "addr:street":"Carl-Hofmann-Weg",
    "iso:country":"AT",
    "sg:address":"Carl-Hofmann-Weg 35",
    "sg:city":"Heidenreichstein",
    "sg:orig_category":"Glaswaren",
    "sg:phone":"+43 4328 6252472",
    "sg:postcode":"3860",
    "sg:province":"Nieder\u00f6sterreich",
    "wof:name":"Galerie Kunst & Glas Thomas Zeh",
    "wof:placetype":"venue"
},
  "geometry": {"coordinates":[15.1124000549,48.8631324768],"type":"Point"}
}