{
  "type": "Feature",
  "properties": {
    "iso:country":"AT",
    "sg:address":"Grabenstr 5",
    "sg:city":"Fohnsdorf",
    "sg:orig_category":"Handelsagenturen",
    "sg:phone":"+43 4335 732231",
    "sg:postcode":"8753",
    "sg:province":"Steiermark",
    "wof:name":"R. Kienzl GesmbH",
    "wof:placetype":"venue"
},
  "geometry": {"coordinates":[14.6775064468,47.2093963623],"type":"Point"}
}