{
  "type": "Feature",
  "properties": {
    "addr:full":"Neumarkt im Hausruckkreis Ober\u00f6sterreich 4720",
    "addr:postcode":"4720",
    "addr:street":"Oberoesterreich",
    "iso:country":"AT",
    "sg:city":"Neumarkt im Hausruckkreis",
    "sg:orig_category":"Feuerwehren",
    "sg:phone":"+43 4377 336545",
    "sg:postcode":"4720",
    "sg:province":"Ober\u00f6sterreich",
    "wof:name":"Freiwillige Feuerwehr Aschau",
    "wof:placetype":"venue"
},
  "geometry": {"coordinates":[13.7142972946,48.3056373596],"type":"Point"}
}