{
  "type": "Feature",
  "properties": {
    "addr:full":"Im Weingarten 1 Schwarzach Vorarlberg 6858",
    "addr:housenumber":"1",
    "addr:postcode":"6858",
    "addr:street":"Im Weingarten",
    "iso:country":"AT",
    "sg:address":"Im Weingarten 1",
    "sg:city":"Schwarzach",
    "sg:orig_category":"Steuerberatung",
    "sg:phone":"+43 5572 586550",
    "sg:postcode":"6858",
    "sg:province":"Vorarlberg",
    "wof:name":"Schertler Franz Anton Mag Dr",
    "wof:placetype":"venue"
},
  "geometry": {"coordinates":[9.7618913651,47.4434051514],"type":"Point"}
}