{
  "type": "Feature",
  "properties": {
    "addr:full":"Br\u00fcnner Str 6 Poysdorf Nieder\u00f6sterreich 2170",
    "addr:housenumber":"6",
    "addr:postcode":"2170",
    "addr:street":"Str",
    "iso:country":"AT",
    "sg:address":"Br\u00fcnner Str 6",
    "sg:city":"Poysdorf",
    "sg:orig_category":"Bodenverlegung",
    "sg:phone":"+43 2552 2643",
    "sg:postcode":"2170",
    "sg:province":"Nieder\u00f6sterreich",
    "wof:name":"Raab Manfred",
    "wof:placetype":"venue"
},
  "geometry": {"coordinates":[16.6295757294,48.668674469],"type":"Point"}
}