{
  "type": "Feature",
  "properties": {
    "addr:full":"Neubauer in Hub 2 Mettmach Ober\u00f6sterreich 4931",
    "addr:housenumber":"2",
    "addr:postcode":"4931",
    "iso:country":"AT",
    "sg:address":"Neubauer in Hub 2",
    "sg:city":"Mettmach",
    "sg:orig_category":"Handelsagenturen",
    "sg:phone":"+43 7755 5250",
    "sg:postcode":"4931",
    "sg:province":"Ober\u00f6sterreich",
    "wof:name":"Spindler Josef - L\u00fcftungen - Grassamen",
    "wof:placetype":"venue"
},
  "geometry": {"coordinates":[13.3445558548,48.1723632812],"type":"Point"}
}