{
  "type": "Feature",
  "properties": {
    "addr:full":"Bachlechnerstrasse 23 Innsbruck Tirol 6020",
    "addr:housenumber":"23",
    "addr:postcode":"6020",
    "addr:street":"Bachlechnerstrasse;Tirol",
    "iso:country":"AT",
    "sg:address":"Bachlechnerstrasse 23",
    "sg:city":"Innsbruck",
    "sg:classifiers":[
        {
            "category":"Building & Trades",
            "subcategory":"Construction",
            "type":"Services"
        }
    ],
    "sg:phone":"+43 512 2817170",
    "sg:postcode":"6020",
    "sg:province":"Tirol",
    "sg:tags":[
        "energy",
        "concept"
    ],
    "sg:website":"energiebig.com",
    "wof:name":"Energiebig Energie- und Umwelttechnik GmbH",
    "wof:placetype":"venue"
},
  "geometry": {"coordinates":[11.3757457733,47.2616958618],"type":"Point"}
}