{
  "type": "Feature",
  "properties": {
    "addr:full":"Konstantpl 1 St. Thomas am Blasenstein Ober\u00f6sterreich 4364",
    "addr:housenumber":"1",
    "addr:postcode":"4364",
    "addr:street":"Konstantpl;Am Blasenstein",
    "iso:country":"AT",
    "sg:address":"Konstantpl 1",
    "sg:city":"St. Thomas am Blasenstein",
    "sg:orig_category":"Arbeitsschutz U Arbeitsschutzartikel",
    "sg:phone":"+43 4372 6557220",
    "sg:postcode":"4364",
    "sg:province":"Ober\u00f6sterreich",
    "sg:website":"konstant.co.at",
    "wof:name":"KONSTANT Arbeitsschutz GmbH",
    "wof:placetype":"venue"
},
  "geometry": {"coordinates":[14.7615709305,48.3127861023],"type":"Point"}
}