{
  "type": "Feature",
  "properties": {
    "iso:country":"AT",
    "sg:address":"Nr 10",
    "sg:city":"Lichtenau",
    "sg:orig_category":"Holzhandel",
    "sg:phone":"+43 2718 6116",
    "sg:postcode":"3522",
    "sg:province":"Nieder\u00f6sterreich",
    "wof:name":"Steindl Franz",
    "wof:placetype":"venue"
},
  "geometry": {"coordinates":[15.391368866,48.4974708557],"type":"Point"}
}