{
  "type": "Feature",
  "properties": {
    "iso:country":"AT",
    "sg:address":"SC Seiersberg 3",
    "sg:city":"Puntigam",
    "sg:orig_category":"Einkaufszentren",
    "sg:phone":"+43 316 296137",
    "sg:postcode":"8055",
    "sg:province":"Steiermark",
    "wof:name":"Shopping City Seiersberg Centerverwaltung",
    "wof:placetype":"venue"
},
  "geometry": {"coordinates":[15.3990154266,47.0103302002],"type":"Point"}
}