{
  "type": "Feature",
  "properties": {
    "iso:country":"AT",
    "sg:address":"Luna 69 ",
    "sg:city":"Kundl",
    "sg:classifiers":[
        {
            "category":"Professional",
            "subcategory":"Engineering",
            "type":"Services"
        }
    ],
    "sg:phone":"+43 4353 3872700",
    "sg:postcode":"6250",
    "sg:province":"Tirol",
    "sg:tags":[
        "machine",
        "-",
        "mechanical"
    ],
    "wof:name":"OTTO DALNODAR KG",
    "wof:placetype":"venue"
},
  "geometry": {"coordinates":[12.0143556595,47.471408844],"type":"Point"}
}