{
  "type": "Feature",
  "properties": {
    "addr:full":"Nr 70 St. Michael im Lungau Salzburg 5582",
    "addr:postcode":"5582",
    "addr:street":"Nr 70",
    "iso:country":"AT",
    "sg:address":"Nr 70",
    "sg:city":"St. Michael im Lungau",
    "sg:orig_category":"Holzbe U -Verarbeitung",
    "sg:phone":"+43 4364 7776660",
    "sg:postcode":"5582",
    "sg:province":"Salzburg",
    "wof:name":"Moser Holzindustrie GesmbH",
    "wof:placetype":"venue"
},
  "geometry": {"coordinates":[166.9221496582,-0.5282999873],"type":"Point"}
}