{
  "type": "Feature",
  "properties": {
    "addr:full":"Schulstr 2 Windischgarsten Ober\u00f6sterreich 4580",
    "addr:housenumber":"2",
    "addr:postcode":"4580",
    "addr:street":"Schulstr",
    "iso:country":"AT",
    "sg:address":"Schulstr 2",
    "sg:city":"Windischgarsten",
    "sg:orig_category":"Friseure U Frisiersalons",
    "sg:phone":"+43 7562 20789",
    "sg:postcode":"4580",
    "sg:province":"Ober\u00f6sterreich",
    "wof:name":"Coiffeur Haarzone",
    "wof:placetype":"venue"
},
  "geometry": {"coordinates":[14.3274412155,47.721496582],"type":"Point"}
}