{
  "type": "Feature",
  "properties": {
    "addr:full":"Kramerg 9 Imst Tirol 6460",
    "addr:housenumber":"9",
    "addr:postcode":"6460",
    "addr:street":"Kramerg;Tirol",
    "iso:country":"AT",
    "sg:address":"Kramerg 9",
    "sg:city":"Imst",
    "sg:orig_category":"Versicherungsunternehmen",
    "sg:phone":"+43 5412 64800",
    "sg:postcode":"6460",
    "sg:province":"Tirol",
    "wof:name":"Donau Versicherung",
    "wof:placetype":"venue"
},
  "geometry": {"coordinates":[10.7392416,47.2407035828],"type":"Point"}
}