{
  "type": "Feature",
  "properties": {
    "addr:full":"Quellenstrasse 45 Bregenz Vorarlberg 6900",
    "addr:housenumber":"45",
    "addr:postcode":"6900",
    "addr:street":"Quellenstrasse",
    "iso:country":"AT",
    "sg:address":"Quellenstrasse 45",
    "sg:city":"Bregenz",
    "sg:classifiers":[
        {
            "category":"Structure",
            "subcategory":"Building",
            "type":"Public Place"
        }
    ],
    "sg:phone":"+43 5574 42979",
    "sg:postcode":"6900",
    "sg:province":"Vorarlberg",
    "sg:tags":[
        "apartment"
    ],
    "wof:name":"Zimmermann Bau GmbH",
    "wof:placetype":"venue"
},
  "geometry": {"coordinates":[9.7341928482,47.4997215271],"type":"Point"}
}