{
  "type": "Feature",
  "properties": {
    "addr:full":"Hauptstr 14 Sch\u00f6rfling am Attersee Ober\u00f6sterreich 4861",
    "addr:housenumber":"14",
    "addr:postcode":"4861",
    "addr:street":"Hauptstr;Am",
    "iso:country":"AT",
    "sg:address":"Hauptstr 14",
    "sg:city":"Sch\u00f6rfling am Attersee",
    "sg:orig_category":"Fernsehservice",
    "sg:phone":"+43 4376 628264",
    "sg:postcode":"4861",
    "sg:province":"Ober\u00f6sterreich",
    "wof:name":"Wiener Alwis",
    "wof:placetype":"venue"
},
  "geometry": {"coordinates":[13.5950536728,47.9473228455],"type":"Point"}
}