{
  "type": "Feature",
  "properties": {
    "addr:full":"Nr 25 Zederhaus Salzburg 5584",
    "addr:postcode":"5584",
    "addr:street":"Nr;Zederhaus",
    "iso:country":"AT",
    "sg:address":"Nr 25",
    "sg:city":"Zederhaus",
    "sg:orig_category":"Gemeinden",
    "sg:phone":"+43 6478 2260",
    "sg:postcode":"5584",
    "sg:province":"Salzburg",
    "wof:name":"Gemeindeamt Zederhaus",
    "wof:placetype":"venue"
},
  "geometry": {"coordinates":[13.5075616837,47.1524772644],"type":"Point"}
}