{
  "type": "Feature",
  "properties": {
    "iso:country":"AT",
    "sg:address":"Siebererweg 535",
    "sg:city":"Saalbach",
    "sg:orig_category":"Werbeagenturen",
    "sg:phone":"+43 6541 7738",
    "sg:postcode":"5753",
    "sg:province":"Salzburg",
    "wof:name":"Die Ideenwerkstatt Werbeagentur GmbH",
    "wof:placetype":"venue"
},
  "geometry": {"coordinates":[12.6487350464,47.3878211975],"type":"Point"}
}