{
  "type": "Feature",
  "properties": {
    "iso:country":"AT",
    "sg:address":"Sala 4",
    "sg:city":"Dornbirn",
    "sg:orig_category":"Architekten",
    "sg:phone":"+43 5572 21925",
    "sg:postcode":"6850",
    "sg:province":"Vorarlberg",
    "wof:name":"Moosbrugger Bartholom\u00e4us Arch Dipl-Ing",
    "wof:placetype":"venue"
},
  "geometry": {"coordinates":[9.7385082245,47.4142189026],"type":"Point"}
}