{
  "type": "Feature",
  "properties": {
    "addr:full":"Markt 48 Golling an der Salzach Salzburg 5440",
    "addr:housenumber":"48",
    "addr:postcode":"5440",
    "addr:street":"Markt",
    "iso:country":"AT",
    "sg:address":"Markt 48",
    "sg:city":"Golling an der Salzach",
    "sg:classifiers":[
        {
            "category":"Travel",
            "subcategory":"Hotels & Motels",
            "type":"Entertainment"
        }
    ],
    "sg:phone":"+43 6244 43720",
    "sg:postcode":"5440",
    "sg:province":"Salzburg",
    "wof:name":"Hotel Gasthof Goldener Ochs",
    "wof:placetype":"venue"
},
  "geometry": {"coordinates":[13.1683273315,47.5987052917],"type":"Point"}
}