{
  "type": "Feature",
  "properties": {
    "addr:full":"Laudong 28 Wien Wien 1080",
    "addr:housenumber":"28",
    "addr:postcode":"1080",
    "addr:street":"Laudong",
    "iso:country":"AT",
    "sg:address":"Laudong 28",
    "sg:city":"Wien",
    "sg:orig_category":"Eisenwaren",
    "sg:phone":"+43 1 4061907",
    "sg:postcode":"1080",
    "sg:province":"Wien",
    "wof:name":"Klimesch Viktor",
    "wof:placetype":"venue"
},
  "geometry": {"coordinates":[16.3488864899,48.2133750916],"type":"Point"}
}