{
  "type": "Feature",
  "properties": {
    "addr:full":"Poloplaststrasse 1 Leonding Ober\u00f6sterreich 4060",
    "addr:housenumber":"1",
    "addr:postcode":"4060",
    "addr:street":"Poloplaststrasse",
    "iso:country":"AT",
    "sg:address":"Poloplaststrasse 1",
    "sg:city":"Leonding",
    "sg:classifiers":[
        {
            "category":"Manufacturing",
            "subcategory":"Rubber & Plastics",
            "type":"Manufacturing & Wholesale Goods"
        }
    ],
    "sg:phone":"+43 732 38860",
    "sg:postcode":"4060",
    "sg:province":"Ober\u00f6sterreich",
    "sg:tags":[
        "conduit",
        "cap",
        "made",
        "cable",
        "protection"
    ],
    "sg:website":"poloplast.com",
    "wof:name":"POLOPLAST GmbH & Co KG",
    "wof:placetype":"venue"
},
  "geometry": {"coordinates":[14.2640657425,48.2540283203],"type":"Point"}
}