{
  "type": "Feature",
  "properties": {
    "iso:country":"AT",
    "sg:address":"Saxenegg 3",
    "sg:city":"M\u00fcnzbach",
    "sg:classifiers":[
        {
            "category":"Building & Trades",
            "subcategory":"Landscaping Services",
            "type":"Services"
        }
    ],
    "sg:phone":"+43 7264 4683",
    "sg:postcode":"4323",
    "sg:province":"Ober\u00f6sterreich",
    "sg:tags":[
        "earth",
        "moving"
    ],
    "sg:website":"grillnberger.at",
    "wof:name":"Erdbau Grillnberger",
    "wof:placetype":"venue"
},
  "geometry": {"coordinates":[14.7389383316,48.2862434387],"type":"Point"}
}