{
  "type": "Feature",
  "properties": {
    "addr:full":"Hintzerstr 9/4 Wien Wien 1030",
    "addr:housenumber":"9 / 4",
    "addr:postcode":"1030",
    "addr:street":"Hintzerstr",
    "iso:country":"AT",
    "sg:address":"Hintzerstr 9/4",
    "sg:city":"Wien",
    "sg:orig_category":"\u00c3\u201erzte / F Allgemeinmedizin",
    "sg:phone":"+43 1 7139550",
    "sg:postcode":"1030",
    "sg:province":"Wien",
    "wof:name":"Graf Wolfgang Friedrich DDr",
    "wof:placetype":"venue"
},
  "geometry": {"coordinates":[16.3907012939,48.2000312805],"type":"Point"}
}