{
  "type": "Feature",
  "properties": {
    "addr:full":"Volksgartenstr 5 Graz Steiermark 8020",
    "addr:housenumber":"5",
    "addr:postcode":"8020",
    "addr:street":"Volksgartenstr",
    "iso:country":"AT",
    "sg:address":"Volksgartenstr 5",
    "sg:city":"Graz",
    "sg:orig_category":"Restaurants: Japanisch",
    "sg:phone":"+43 316 718366",
    "sg:postcode":"8020",
    "sg:province":"Steiermark",
    "wof:name":"Restaurant Osaka",
    "wof:placetype":"venue"
},
  "geometry": {"coordinates":[15.4286727905,47.0719451904],"type":"Point"}
}