{
  "type": "Feature",
  "properties": {
    "iso:country":"AT",
    "sg:address":"Neuwaldegger Strasse 4A/1",
    "sg:city":"Wien",
    "sg:classifiers":[
        {
            "category":"Shopping",
            "subcategory":"Jewelry",
            "type":"Retail Goods"
        }
    ],
    "sg:phone":"+43 1 4892491",
    "sg:postcode":"1170",
    "sg:province":"Wien",
    "sg:tags":[
        "diamond"
    ],
    "sg:website":"carat-online.at",
    "wof:name":"carat-online.at",
    "wof:placetype":"venue"
},
  "geometry": {"coordinates":[16.2903347015,48.2358512878],"type":"Point"}
}