{
  "type": "Feature",
  "properties": {
    "addr:full":"Angerstr 2 Hadersdorf am Kamp Nieder\u00f6sterreich 3493",
    "addr:housenumber":"2",
    "addr:postcode":"3493",
    "addr:street":"Angerstr;Niederoesterreich",
    "iso:country":"AT",
    "sg:address":"Angerstr 2",
    "sg:city":"Hadersdorf am Kamp",
    "sg:orig_category":"Lebensmittel / Einzelhandel",
    "sg:phone":"+43 2735 2317",
    "sg:postcode":"3493",
    "sg:province":"Nieder\u00f6sterreich",
    "wof:name":"Spar-Markt Werner Friedl",
    "wof:placetype":"venue"
},
  "geometry": {"coordinates":[15.723487854,48.4618873596],"type":"Point"}
}