{
  "type": "Feature",
  "properties": {
    "iso:country":"AT",
    "sg:address":"Angerstr 2",
    "sg:city":"Hadersdorf am Kamp",
    "sg:orig_category":"Lebensmittel / Einzelhandel",
    "sg:phone":"+43 2735 2317",
    "sg:postcode":"3493",
    "sg:province":"Nieder\u00f6sterreich",
    "wof:name":"Spar-Markt Werner Friedl",
    "wof:placetype":"venue"
},
  "geometry": {"coordinates":[15.723487854,48.4618873596],"type":"Point"}
}