{
  "type": "Feature",
  "properties": {
    "iso:country":"AT",
    "sg:address":"Elisabethstr 3",
    "sg:city":"Baden",
    "sg:orig_category":"Institute",
    "sg:phone":"+43 4322 52481490",
    "sg:postcode":"2500",
    "sg:province":"Nieder\u00f6sterreich",
    "wof:name":"Hayder Werner Dr",
    "wof:placetype":"venue"
},
  "geometry": {"coordinates":[16.2367553711,48.0026817322],"type":"Point"}
}