{
  "type": "Feature",
  "properties": {
    "iso:country":"AT",
    "sg:address":"Europastr 15",
    "sg:city":"Langenrohr",
    "sg:orig_category":"Damenmoden",
    "sg:phone":"+43 2272 65648",
    "sg:postcode":"3442",
    "sg:province":"Nieder\u00f6sterreich",
    "wof:name":"NEW YORKER - NYer Hansen & Knapp KG",
    "wof:placetype":"venue"
},
  "geometry": {"coordinates":[16.0079441071,48.3082313538],"type":"Point"}
}