{
  "type": "Feature",
  "properties": {
    "addr:full":"Ziehrerstr 68a Liebenau Steiermark 8041",
    "addr:housenumber":"68a",
    "addr:postcode":"8041",
    "addr:street":"Ziehrerstr",
    "iso:country":"AT",
    "sg:address":"Ziehrerstr 68a",
    "sg:city":"Liebenau",
    "sg:orig_category":"Tankanlagen",
    "sg:phone":"+43 316 6770110",
    "sg:postcode":"8041",
    "sg:province":"Steiermark",
    "wof:name":"TANKTECHNIK GmbH",
    "wof:placetype":"venue"
},
  "geometry": {"coordinates":[15.4524564743,47.0395736694],"type":"Point"}
}