{
  "type": "Feature",
  "properties": {
    "iso:country":"AT",
    "sg:address":"Dr Karl Renner-Ring 3",
    "sg:city":"Wien",
    "sg:orig_category":"Politische Parteien",
    "sg:phone":"+43 1 401103471",
    "sg:postcode":"1010",
    "sg:province":"Wien",
    "wof:name":"Sozialdemokratische Partei \u00d6sterreichs (SP\u00d6)",
    "wof:placetype":"venue"
},
  "geometry": {"coordinates":[16.3597126007,48.2079582214],"type":"Point"}
}