{
  "type": "Feature",
  "properties": {
    "addr:full":"Lindenstr 11 Asten Ober\u00f6sterreich 4481",
    "addr:housenumber":"11",
    "addr:postcode":"4481",
    "addr:street":"Lindenstr",
    "iso:country":"AT",
    "sg:address":"Lindenstr 11",
    "sg:city":"Asten",
    "sg:classifiers":[
        {
            "category":"Taxi",
            "type":"Transportation"
        }
    ],
    "sg:phone":"+43 4366 43423267",
    "sg:postcode":"4481",
    "sg:province":"Ober\u00f6sterreich",
    "sg:tags":[
        "personentransporte",
        "u"
    ],
    "wof:name":"W\u00f6gerer Stephan",
    "wof:placetype":"venue"
},
  "geometry": {"coordinates":[14.4252891541,48.222530365],"type":"Point"}
}