{
  "type": "Feature",
  "properties": {
    "addr:full":"Hauptstr 462-470 Strasshof an der Nordbahn Nieder\u00f6sterreich 2231",
    "addr:housenumber":"462-470",
    "addr:postcode":"2231",
    "addr:street":"Hauptstr",
    "iso:country":"AT",
    "sg:address":"Hauptstr 462-470",
    "sg:city":"Strasshof an der Nordbahn",
    "sg:classifiers":[
        {
            "category":"Professional",
            "subcategory":"Management & Consulting",
            "type":"Services"
        }
    ],
    "sg:phone":"+43 2287 21187",
    "sg:postcode":"2231",
    "sg:province":"Nieder\u00f6sterreich",
    "wof:name":"EKABO Projektmanagement GesmbH",
    "wof:placetype":"venue"
},
  "geometry": {"coordinates":[16.6106395721,48.3223457336],"type":"Point"}
}