{
  "type": "Feature",
  "properties": {
    "addr:full":"Raabser Str 66 Eisgarn Nieder\u00f6sterreich 3862",
    "addr:housenumber":"66",
    "addr:postcode":"3862",
    "addr:street":"Str",
    "iso:country":"AT",
    "sg:address":"Raabser Str 66",
    "sg:city":"Eisgarn",
    "sg:orig_category":"Tischlereien",
    "sg:phone":"+43 2863 2410",
    "sg:postcode":"3862",
    "sg:province":"Nieder\u00f6sterreich",
    "wof:name":"Waldviertler Tischlerwerkstatt Ing Franz Eglau",
    "wof:placetype":"venue"
},
  "geometry": {"coordinates":[15.1070461273,48.9153137207],"type":"Point"}
}