{
  "type": "Feature",
  "properties": {
    "iso:country":"AT",
    "sg:address":"Hauptstr 44b",
    "sg:city":"Langenlois",
    "sg:orig_category":"Werbegestalter",
    "sg:phone":"+43 4367 65067720",
    "sg:postcode":"3550",
    "sg:province":"Nieder\u00f6sterreich",
    "wof:name":"Design-Work Gerhard Schwarz",
    "wof:placetype":"venue"
},
  "geometry": {"coordinates":[15.67689991,48.4733161926],"type":"Point"}
}