{
  "type": "Feature",
  "properties": {
    "iso:country":"AT",
    "sg:address":"Wiener Str 8",
    "sg:city":"Linz",
    "sg:orig_category":"Optiker",
    "sg:phone":"+43 732 651537",
    "sg:postcode":"4020",
    "sg:province":"Ober\u00f6sterreich",
    "wof:name":"Freudenthaler Wolfgang",
    "wof:placetype":"venue"
},
  "geometry": {"coordinates":[14.2975320816,48.2899436951],"type":"Point"}
}