{
  "type": "Feature",
  "properties": {
    "iso:country":"AT",
    "sg:address":"Franz-Josef-Str 20",
    "sg:city":"Salzburg",
    "sg:orig_category":"Psychotherapie",
    "sg:phone":"+43 662 636209",
    "sg:postcode":"5020",
    "sg:province":"Salzburg",
    "wof:name":"Fichtinger Burgi",
    "wof:placetype":"venue"
},
  "geometry": {"coordinates":[13.0481290817,47.8062782288],"type":"Point"}
}