{
  "type": "Feature",
  "properties": {
    "addr:full":"Haldenweg 33 Bludenz Vorarlberg 6700",
    "addr:housenumber":"33",
    "addr:postcode":"6700",
    "addr:street":"Haldenweg",
    "iso:country":"AT",
    "sg:address":"Haldenweg 33",
    "sg:city":"Bludenz",
    "sg:orig_category":"Psychotherapie",
    "sg:phone":"+43 5552 66945",
    "sg:postcode":"6700",
    "sg:province":"Vorarlberg",
    "wof:name":"Br\u00fcstle Martin",
    "wof:placetype":"venue"
},
  "geometry": {"coordinates":[9.838139534,47.1538887024],"type":"Point"}
}