{
  "type": "Feature",
  "properties": {
    "iso:country":"AT",
    "sg:address":"Wiener Str 140",
    "sg:city":"Klosterneuburg",
    "sg:orig_category":"Dekorationen",
    "sg:phone":"+43 664 2077877",
    "sg:postcode":"3400",
    "sg:province":"Nieder\u00f6sterreich",
    "wof:name":"deco7",
    "wof:placetype":"venue"
},
  "geometry": {"coordinates":[16.3357887268,48.294631958],"type":"Point"}
}