{
  "type": "Feature",
  "properties": {
    "addr:full":"Rosensteing 82 Wien Wien 1170",
    "addr:housenumber":"82",
    "addr:postcode":"1170",
    "addr:street":"Rosensteing",
    "iso:country":"AT",
    "sg:address":"Rosensteing 82",
    "sg:city":"Wien",
    "sg:orig_category":"Psychotherapie",
    "sg:phone":"+43 1 4859649",
    "sg:postcode":"1170",
    "sg:province":"Wien",
    "wof:name":"Hocher Irene",
    "wof:placetype":"venue"
},
  "geometry": {"coordinates":[16.3288650513,48.2232322693],"type":"Point"}
}