{
  "type": "Feature",
  "properties": {
    "addr:full":"Pierrong 12 Wien Wien 1140",
    "addr:housenumber":"12",
    "addr:postcode":"1140",
    "addr:street":"Pierrong",
    "iso:country":"AT",
    "sg:address":"Pierrong 12",
    "sg:city":"Wien",
    "sg:orig_category":"Handelsagenturen",
    "sg:phone":"+43 1 9148676",
    "sg:postcode":"1140",
    "sg:province":"Wien",
    "wof:name":"Rosenfeld Robert Ing",
    "wof:placetype":"venue"
},
  "geometry": {"coordinates":[16.2734928131,48.1958084106],"type":"Point"}
}