{
  "type": "Feature",
  "properties": {
    "addr:full":"Moosanger 944 Wenns Tirol 6473",
    "addr:housenumber":"944",
    "addr:postcode":"6473",
    "addr:street":"Moosanger;Tirol",
    "iso:country":"AT",
    "sg:address":"Moosanger 944",
    "sg:city":"Wenns",
    "sg:orig_category":"Architekten",
    "sg:phone":"+43 5414 862380",
    "sg:postcode":"6473",
    "sg:province":"Tirol",
    "wof:name":"Zangerle Helmut Bmstr Planungsb\u00fcro f Hochbau",
    "wof:placetype":"venue"
},
  "geometry": {"coordinates":[10.7312002182,47.1684265137],"type":"Point"}
}