{
  "type": "Feature",
  "properties": {
    "iso:country":"AT",
    "sg:address":"Bundesstr 212",
    "sg:city":"Wimpassing im Schwarzatale",
    "sg:orig_category":"Autohandel",
    "sg:phone":"+43 4326 3035848",
    "sg:postcode":"2632",
    "sg:province":"Nieder\u00f6sterreich",
    "wof:name":"Happy-Car Haider",
    "wof:placetype":"venue"
},
  "geometry": {"coordinates":[16.0169219971,47.6945152283],"type":"Point"}
}