{
  "type": "Feature",
  "properties": {
    "iso:country":"AT",
    "sg:address":"Ernst-Wlattnig-Gasse 20",
    "sg:city":"Klagenfurt",
    "sg:classifiers":[
        {
            "category":"Home & Garden",
            "subcategory":"Building Materials",
            "type":"Retail Goods"
        }
    ],
    "sg:phone":"+43 463 25218",
    "sg:postcode":"9020",
    "sg:province":"K\u00e4rnten",
    "sg:tags":[
        "installation",
        "electric"
    ],
    "wof:name":"Elektro Salcher GmbH",
    "wof:placetype":"venue"
},
  "geometry": {"coordinates":[14.2961158752,46.6073265076],"type":"Point"}
}