{
  "type": "Feature",
  "properties": {
    "iso:country":"AT",
    "sg:city":"Neumarkt im M\u00fchlkreis",
    "sg:orig_category":"Feuerwehren",
    "sg:phone":"+43 7941 8625",
    "sg:postcode":"4212",
    "sg:province":"Ober\u00f6sterreich",
    "wof:name":"Freiwillige Feuerwehr Matzelsdorf",
    "wof:placetype":"venue"
},
  "geometry": {"coordinates":[14.4839353561,48.4275016785],"type":"Point"}
}