{
  "type": "Feature",
  "properties": {
    "addr:full":"Nr 14 Seekirchen am Wallersee Salzburg 5201",
    "addr:postcode":"5201",
    "addr:street":"Nr 14;Salzburg",
    "iso:country":"AT",
    "sg:address":"Nr 14",
    "sg:city":"Seekirchen am Wallersee",
    "sg:orig_category":"Appartements / Ferienwohnungen",
    "sg:phone":"+43 4362 196464",
    "sg:postcode":"5201",
    "sg:province":"Salzburg",
    "wof:name":"Strasser Maria u Jakob",
    "wof:placetype":"venue"
},
  "geometry": {"coordinates":[13.1259384155,47.8936538696],"type":"Point"}
}