{
  "type": "Feature",
  "properties": {
    "addr:full":"W\u00e4hringer Str 169-171 Wien Wien 1180",
    "addr:housenumber":"169-171",
    "addr:postcode":"1180",
    "addr:street":"Str",
    "iso:country":"AT",
    "sg:address":"W\u00e4hringer Str 169-171",
    "sg:city":"Wien",
    "sg:orig_category":"Holzdecken U Wandverkleidungen",
    "sg:phone":"+43 4314 707707",
    "sg:postcode":"1180",
    "sg:province":"Wien",
    "sg:website":"wohnenmitgefuehl.at",
    "wof:name":"Lerch Reinhard",
    "wof:placetype":"venue"
},
  "geometry": {"coordinates":[16.3320617676,48.2287025452],"type":"Point"}
}