{
  "type": "Feature",
  "properties": {
    "addr:full":"Werben 19 Koblach Vorarlberg 6842",
    "addr:housenumber":"19",
    "addr:postcode":"6842",
    "addr:street":"Werben",
    "iso:country":"AT",
    "sg:address":"Werben 19",
    "sg:city":"Koblach",
    "sg:classifiers":[
        {
            "category":"Military Area",
            "subcategory":"Air Force Base",
            "type":"Public Place"
        }
    ],
    "sg:phone":"+43 5523 62851",
    "sg:postcode":"6842",
    "sg:province":"Vorarlberg",
    "sg:tags":[
        "window",
        "skylight",
        "dormer"
    ],
    "sg:website":"peterdach.at",
    "wof:name":"Peter GmbH & Co KG",
    "wof:placetype":"venue"
},
  "geometry": {"coordinates":[9.6057043076,47.3298797607],"type":"Point"}
}