{
  "type": "Feature",
  "properties": {
    "addr:full":"Sandbauernstr 46 Steyr Ober\u00f6sterreich 4400",
    "addr:housenumber":"46",
    "addr:postcode":"4400",
    "addr:street":"Sandbauernstr;Oberoesterreich",
    "iso:country":"AT",
    "sg:address":"Sandbauernstr 46",
    "sg:city":"Steyr",
    "sg:orig_category":"Psychotherapie",
    "sg:phone":"+43 664 2124393",
    "sg:postcode":"4400",
    "sg:province":"Ober\u00f6sterreich",
    "wof:name":"Bayer-Daschill Karin Dr",
    "wof:placetype":"venue"
},
  "geometry": {"coordinates":[14.3982276917,48.0327568054],"type":"Point"}
}