{
  "type": "Feature",
  "properties": {
    "addr:full":"Seilerg 6 Wien Wien 1010",
    "addr:housenumber":"6",
    "addr:postcode":"1010",
    "addr:street":"Seilerg",
    "iso:country":"AT",
    "sg:address":"Seilerg 6",
    "sg:city":"Wien",
    "sg:orig_category":"Banken U Sparkassen",
    "sg:phone":"+43 1 5132022",
    "sg:postcode":"1010",
    "sg:province":"Wien",
    "wof:name":"Landesbank Baden-W\u00fcrttemberg",
    "wof:placetype":"venue"
},
  "geometry": {"coordinates":[16.3707313538,48.2075157166],"type":"Point"}
}