{
  "type": "Feature",
  "properties": {
    "addr:full":"Mitterkleinarl Ployerg 1 Kleinarl Salzburg 5603",
    "addr:housenumber":"1",
    "addr:postcode":"5603",
    "addr:street":"Ployerg;Salzburg",
    "iso:country":"AT",
    "sg:address":"Mitterkleinarl Ployerg 1",
    "sg:city":"Kleinarl",
    "sg:orig_category":"Appartements / Ferienwohnungen",
    "sg:phone":"+43 4364 182410",
    "sg:postcode":"5603",
    "sg:province":"Salzburg",
    "wof:name":"Schwaighofer Balthasar",
    "wof:placetype":"venue"
},
  "geometry": {"coordinates":[13.3195962906,47.2775421143],"type":"Point"}
}