{
  "type": "Feature",
  "properties": {
    "addr:full":"Nr 67 Velden am W\u00f6rther See K\u00e4rnten 9220",
    "addr:postcode":"9220",
    "addr:street":"Nr 67;Kaernten",
    "iso:country":"AT",
    "sg:address":"Nr 67",
    "sg:city":"Velden am W\u00f6rther See",
    "sg:orig_category":"Bodenverlegung",
    "sg:phone":"+43 4274 4141",
    "sg:postcode":"9220",
    "sg:province":"K\u00e4rnten",
    "wof:name":"Oswirt Gerhard Taraflex Fu\u00dfbodentechnik GmbH",
    "wof:placetype":"venue"
},
  "geometry": {"coordinates":[14.0429868698,46.6151618958],"type":"Point"}
}