{
  "type": "Feature",
  "properties": {
    "iso:country":"AT",
    "sg:address":"Kircheng 4a",
    "sg:city":"Steyregg",
    "sg:orig_category":"Lebens- U Sozialberatung",
    "sg:phone":"+43 4373 2641384",
    "sg:postcode":"4221",
    "sg:province":"Ober\u00f6sterreich",
    "wof:name":"Sozialberatung der Stadtgmeinde Steyregg",
    "wof:placetype":"venue"
},
  "geometry": {"coordinates":[14.3692979813,48.2852706909],"type":"Point"}
}