{
  "type": "Feature",
  "properties": {
    "iso:country":"AT",
    "sg:address":"Reicharten 41",
    "sg:city":"Langen",
    "sg:orig_category":"Genossenschaften",
    "sg:phone":"+43 4355 7544420",
    "sg:postcode":"6932",
    "sg:province":"Vorarlberg",
    "wof:name":"Bio-Bauern Sulzberg-Bregenzerwald regGenmbH",
    "wof:placetype":"venue"
},
  "geometry": {"coordinates":[9.8273859024,47.5082244873],"type":"Point"}
}