{
  "type": "Feature",
  "properties": {
    "iso:country":"AT",
    "sg:address":"Klamer Str 1",
    "sg:city":"M\u00fcnzbach",
    "sg:orig_category":"Tischlereien",
    "sg:phone":"+43 7264 4516",
    "sg:postcode":"4323",
    "sg:province":"Ober\u00f6sterreich",
    "wof:name":"Viehb\u00f6ck Josef",
    "wof:placetype":"venue"
},
  "geometry": {"coordinates":[14.7213573456,48.2709083557],"type":"Point"}
}