{
  "type": "Feature",
  "properties": {
    "iso:country":"AT",
    "sg:address":"Hauptpl 10",
    "sg:city":"Deutschlandsberg",
    "sg:orig_category":"Fleischhauereien",
    "sg:phone":"+43 3462 264214",
    "sg:postcode":"8530",
    "sg:province":"Steiermark",
    "wof:name":"Kollar GesmbH",
    "wof:placetype":"venue"
},
  "geometry": {"coordinates":[15.2150774002,46.8151855469],"type":"Point"}
}