{
  "type": "Feature",
  "properties": {
    "addr:full":"Latschaustr 22 Tschagguns Vorarlberg 6774",
    "addr:housenumber":"22",
    "addr:postcode":"6774",
    "addr:street":"Latschaustr",
    "iso:country":"AT",
    "sg:address":"Latschaustr 22",
    "sg:city":"Tschagguns",
    "sg:classifiers":[
        {
            "category":"Travel",
            "subcategory":"Hotels & Motels",
            "type":"Entertainment"
        }
    ],
    "sg:phone":"+43 4355 5672557",
    "sg:postcode":"6774",
    "sg:province":"Vorarlberg",
    "wof:name":"Alpenparkhotel",
    "wof:placetype":"venue"
},
  "geometry": {"coordinates":[9.8973083496,47.0751037598],"type":"Point"}
}