{
  "type": "Feature",
  "properties": {
    "addr:full":"Semmeringg 22 Wiener Neustadt Nieder\u00f6sterreich 2700",
    "addr:housenumber":"22",
    "addr:postcode":"2700",
    "addr:street":"Semmeringg",
    "iso:country":"AT",
    "sg:address":"Semmeringg 22",
    "sg:city":"Wiener Neustadt",
    "sg:orig_category":"Rauchfangkehrer",
    "sg:phone":"+43 2622 25737",
    "sg:postcode":"2700",
    "sg:province":"Nieder\u00f6sterreich",
    "wof:name":"P\u00f6lzgutter Horst Peter",
    "wof:placetype":"venue"
},
  "geometry": {"coordinates":[16.2283172607,47.8108711243],"type":"Point"}
}