{
  "type": "Feature",
  "properties": {
    "addr:full":"Hinterschweigerstrasse 8 Wels Ober\u00f6sterreich 4600",
    "addr:housenumber":"8",
    "addr:postcode":"4600",
    "addr:street":"Hinterschweigerstrasse;Oberoesterreich",
    "iso:country":"AT",
    "sg:address":"Hinterschweigerstrasse 8",
    "sg:city":"Wels",
    "sg:classifiers":[
        {
            "category":"Retail",
            "subcategory":"Storage",
            "type":"Services"
        }
    ],
    "sg:phone":"+43 7242 65985",
    "sg:postcode":"4600",
    "sg:province":"Ober\u00f6sterreich",
    "sg:tags":[
        "transport",
        "groupage"
    ],
    "wof:name":"Paul Japek Ges.m.b.H.",
    "wof:placetype":"venue"
},
  "geometry": {"coordinates":[14.0129585266,48.1606521606],"type":"Point"}
}