{
  "type": "Feature",
  "properties": {
    "addr:full":"Schlambart 2 Gunskirchen Ober\u00f6sterreich 4623",
    "addr:housenumber":"2",
    "addr:postcode":"4623",
    "addr:street":"Schlambart",
    "iso:country":"AT",
    "sg:address":"Schlambart 2",
    "sg:city":"Gunskirchen",
    "sg:orig_category":"Raumausstattung",
    "sg:phone":"+43 7246 8968",
    "sg:postcode":"4623",
    "sg:province":"Ober\u00f6sterreich",
    "wof:name":"Mayrdorfer Sabine",
    "wof:placetype":"venue"
},
  "geometry": {"coordinates":[13.9325361252,48.1563606262],"type":"Point"}
}