{
  "type": "Feature",
  "properties": {
    "addr:full":"K\u00e4rntner Str 80 Lienz Tirol 9900",
    "addr:postcode":"9900",
    "addr:street":"Str 80;Tirol",
    "iso:country":"AT",
    "sg:address":"K\u00e4rntner Str 80",
    "sg:city":"Lienz",
    "sg:orig_category":"Lebensmittel / Einzelhandel",
    "sg:phone":"+43 4348 52688900",
    "sg:postcode":"9900",
    "sg:province":"Tirol",
    "wof:name":"SPAR \u00f6sterreichische Warenhandels-AG",
    "wof:placetype":"venue"
},
  "geometry": {"coordinates":[12.7684783936,46.8281173706],"type":"Point"}
}