{
  "type": "Feature",
  "properties": {
    "addr:full":"Landstr 19 Lochau Vorarlberg 6911",
    "addr:housenumber":"19",
    "addr:postcode":"6911",
    "addr:street":"Landstr",
    "iso:country":"AT",
    "sg:address":"Landstr 19",
    "sg:city":"Lochau",
    "sg:orig_category":"Physiotherapie",
    "sg:phone":"+43 664 4302520",
    "sg:postcode":"6911",
    "sg:province":"Vorarlberg",
    "wof:name":"Feuerstein David",
    "wof:placetype":"venue"
},
  "geometry": {"coordinates":[9.7513694763,47.5294303894],"type":"Point"}
}