{
  "type": "Feature",
  "properties": {
    "addr:full":"Neuhaus 9  Neuhaus Ober\u00f6sterreich 4114",
    "addr:housenumber":"9",
    "addr:postcode":"4114",
    "addr:street":"Neuhaus",
    "iso:country":"AT",
    "sg:address":"Neuhaus 9 ",
    "sg:city":"Neuhaus",
    "sg:classifiers":[
        {
            "category":"Manufacturing",
            "subcategory":"Printing",
            "type":"Manufacturing & Wholesale Goods"
        }
    ],
    "sg:phone":"+43 4372 3230650",
    "sg:postcode":"4114",
    "sg:province":"Ober\u00f6sterreich",
    "sg:tags":[
        "publishing"
    ],
    "wof:name":"TIME SYSTEM GESMBH & CO KG",
    "wof:placetype":"venue"
},
  "geometry": {"coordinates":[15.1827497482,47.7893333435],"type":"Point"}
}