{
  "type": "Feature",
  "properties": {
    "addr:full":"Kreuzwieseng 12 Wien Wien 1170",
    "addr:housenumber":"12",
    "addr:postcode":"1170",
    "addr:street":"Kreuzwieseng",
    "iso:country":"AT",
    "sg:address":"Kreuzwieseng 12",
    "sg:city":"Wien",
    "sg:orig_category":"Ingenieurkonsulenten / Zivilingenieure",
    "sg:phone":"+43 1 4868979",
    "sg:postcode":"1170",
    "sg:province":"Wien",
    "wof:name":"Langer Rudolf Dipl-Ing",
    "wof:placetype":"venue"
},
  "geometry": {"coordinates":[16.2937641144,48.2363700867],"type":"Point"}
}