{
  "type": "Feature",
  "properties": {
    "addr:full":"Pfaffendorf 11 Pichl Ober\u00f6sterreich 4632",
    "addr:housenumber":"11",
    "addr:postcode":"4632",
    "addr:street":"Pfaffendorf",
    "iso:country":"AT",
    "sg:address":"Pfaffendorf 11",
    "sg:city":"Pichl",
    "sg:orig_category":"Estriche",
    "sg:phone":"+43 4372 4781570",
    "sg:postcode":"4632",
    "sg:province":"Ober\u00f6sterreich",
    "sg:website":"floortec.at",
    "wof:name":"Floortec Estrich- u Belagverlegung GmbH",
    "wof:placetype":"venue"
},
  "geometry": {"coordinates":[13.9166889191,48.1922302246],"type":"Point"}
}