{
  "type": "Feature",
  "properties": {
    "addr:full":"Burger Str 29 Leonding Ober\u00f6sterreich 4060",
    "addr:postcode":"4060",
    "addr:street":"Str 29",
    "iso:country":"AT",
    "sg:address":"Burger Str 29",
    "sg:city":"Leonding",
    "sg:orig_category":"Me\u00c3\u0178-, Steuer- U Regeltechnik",
    "sg:phone":"+43 732 770177",
    "sg:postcode":"4060",
    "sg:province":"Ober\u00f6sterreich",
    "sg:website":"www.stip.at",
    "wof:name":"Stipanitz Wolfgang Ing",
    "wof:placetype":"venue"
},
  "geometry": {"coordinates":[14.2517223358,48.2851524353],"type":"Point"}
}