{
  "type": "Feature",
  "properties": {
    "addr:full":"Koflergasse 16/1 Wien Wien 1120",
    "addr:housenumber":"16 / 1",
    "addr:postcode":"1120",
    "addr:street":"Koflergasse",
    "iso:country":"AT",
    "sg:address":"Koflergasse 16/1",
    "sg:city":"Wien",
    "sg:classifiers":[
        {
            "category":"Communications",
            "subcategory":"Television Station",
            "type":"Services"
        }
    ],
    "sg:phone":"+43 1 8128862",
    "sg:postcode":"1120",
    "sg:province":"Wien",
    "sg:tags":[
        "array",
        "satellite",
        "aerial",
        "reception",
        "antenna"
    ],
    "wof:name":"Peham Handels KEG",
    "wof:placetype":"venue"
},
  "geometry": {"coordinates":[16.3430042267,48.1812591553],"type":"Point"}
}