{
  "type": "Feature",
  "properties": {
    "addr:full":"Reinprechtsdorfer Strasse 6 Wien Wien 1050",
    "addr:housenumber":"6",
    "addr:postcode":"1050",
    "addr:street":"Reinprechtsdorfer Strasse",
    "iso:country":"AT",
    "sg:address":"Reinprechtsdorfer Strasse 6",
    "sg:city":"Wien",
    "sg:classifiers":[
        {
            "category":"Home & Garden",
            "subcategory":"Building Materials",
            "type":"Retail Goods"
        }
    ],
    "sg:phone":"+43 1 5485611",
    "sg:postcode":"1050",
    "sg:province":"Wien",
    "sg:tags":[
        "installation",
        "electric"
    ],
    "wof:name":"Marics Ges.m.b.H.",
    "wof:placetype":"venue"
},
  "geometry": {"coordinates":[16.3577728271,48.1822433472],"type":"Point"}
}