{
  "type": "Feature",
  "properties": {
    "addr:full":"Hauptpl 19 Stegersbach Burgenland 7551",
    "addr:housenumber":"19",
    "addr:postcode":"7551",
    "addr:street":"Hauptpl",
    "iso:country":"AT",
    "sg:address":"Hauptpl 19",
    "sg:city":"Stegersbach",
    "sg:orig_category":"Textilwaren / Einzelhandel",
    "sg:phone":"+43 3326 52161",
    "sg:postcode":"7551",
    "sg:province":"Burgenland",
    "wof:name":"TPS",
    "wof:placetype":"venue"
},
  "geometry": {"coordinates":[16.1668586731,47.1598358154],"type":"Point"}
}