{
  "type": "Feature",
  "properties": {
    "addr:full":"Nr 5 St. Leonhard am Forst Nieder\u00f6sterreich 3243",
    "addr:housenumber":"5",
    "addr:postcode":"3243",
    "addr:street":"Nr",
    "iso:country":"AT",
    "sg:address":"Nr 5",
    "sg:city":"St. Leonhard am Forst",
    "sg:orig_category":"Massagen",
    "sg:phone":"+43 676 7777004",
    "sg:postcode":"3243",
    "sg:province":"Nieder\u00f6sterreich",
    "wof:name":"H\u00f6rmann Evelin - life-touch",
    "wof:placetype":"venue"
},
  "geometry": {"coordinates":[166.9221496582,-0.5282999873],"type":"Point"}
}