{
  "type": "Feature",
  "properties": {
    "addr:full":"Ragnitzstr 126 Ragnitz Steiermark 8047",
    "addr:housenumber":"126",
    "addr:postcode":"8047",
    "iso:country":"AT",
    "sg:address":"Ragnitzstr 126",
    "sg:city":"Ragnitz",
    "sg:orig_category":"Massagen",
    "sg:phone":"+43 316 303797",
    "sg:postcode":"8047",
    "sg:province":"Steiermark",
    "wof:name":"Massage-Fachinstitut Karin Schneider",
    "wof:placetype":"venue"
},
  "geometry": {"coordinates":[15.4861698151,47.0780601501],"type":"Point"}
}