{
  "type": "Feature",
  "properties": {
    "addr:full":"Weinberggasse 8 Buchkirchen Ober\u00f6sterreich 4611",
    "addr:housenumber":"8",
    "addr:postcode":"4611",
    "addr:street":"Weinberggasse",
    "iso:country":"AT",
    "sg:address":"Weinberggasse 8",
    "sg:city":"Buchkirchen",
    "sg:classifiers":[
        {
            "category":"Military Area",
            "subcategory":"Armory",
            "type":"Public Place"
        }
    ],
    "sg:phone":"+43 664 5117695",
    "sg:postcode":"4611",
    "sg:province":"Ober\u00f6sterreich",
    "sg:tags":[
        "cartridge"
    ],
    "wof:name":"H. Prischl",
    "wof:placetype":"venue"
},
  "geometry": {"coordinates":[14.0001096725,48.2349586487],"type":"Point"}
}