{
  "type": "Feature",
  "properties": {
    "addr:full":"Obere Landstr 21 Krems an der Donau Nieder\u00f6sterreich 3500",
    "addr:housenumber":"21",
    "addr:postcode":"3500",
    "addr:street":"Obere Landstr",
    "iso:country":"AT",
    "sg:address":"Obere Landstr 21",
    "sg:city":"Krems an der Donau",
    "sg:orig_category":"Boutiquen",
    "sg:phone":"+43 2732 82229",
    "sg:postcode":"3500",
    "sg:province":"Nieder\u00f6sterreich",
    "wof:name":"Boutique Scala Lechner-Hofbauer KEG",
    "wof:placetype":"venue"
},
  "geometry": {"coordinates":[15.5975942612,48.4102096558],"type":"Point"}
}