{
  "type": "Feature",
  "properties": {
    "addr:full":"Galgenau 32 Freistadt Ober\u00f6sterreich 4240",
    "addr:housenumber":"32",
    "addr:postcode":"4240",
    "addr:street":"Galgenau",
    "iso:country":"AT",
    "sg:address":"Galgenau 32",
    "sg:city":"Freistadt",
    "sg:orig_category":"Versuchsanstalten",
    "sg:phone":"+43 4379 4273255",
    "sg:postcode":"4240",
    "sg:province":"Ober\u00f6sterreich",
    "wof:name":"\u00f6sterreichische Agentur f Gesundheit- u Ern\u00e4hrungssicherheit GmbH - Versuchsstation",
    "wof:placetype":"venue"
},
  "geometry": {"coordinates":[14.4971780777,48.4902763367],"type":"Point"}
}