{
  "type": "Feature",
  "properties": {
    "addr:full":"Krumpentaler Strasse 18 Eisenerz Steiermark 8790",
    "addr:housenumber":"18",
    "addr:postcode":"8790",
    "addr:street":"Krumpentaler Strasse",
    "iso:country":"AT",
    "sg:address":"Krumpentaler Strasse 18",
    "sg:city":"Eisenerz",
    "sg:classifiers":[
        {
            "category":"Building & Trades",
            "subcategory":"Plumbing",
            "type":"Services"
        }
    ],
    "sg:phone":"+43 3848 2431",
    "sg:postcode":"8790",
    "sg:province":"Steiermark",
    "sg:tags":[
        "supraregional",
        "gas"
    ],
    "wof:name":"Karl-Heinz Zarzer",
    "wof:placetype":"venue"
},
  "geometry": {"coordinates":[14.8879909515,47.5401153564],"type":"Point"}
}