{
  "type": "Feature",
  "properties": {
    "iso:country":"AT",
    "sg:city":"Steyr",
    "sg:orig_category":"Feuerwehren",
    "sg:phone":"+43 7252 73563",
    "sg:postcode":"4400",
    "sg:province":"Ober\u00f6sterreich",
    "wof:name":"Freiwillige Feuerwehr M\u00fcnichholz",
    "wof:placetype":"venue"
},
  "geometry": {"coordinates":[14.4237537384,48.0219917297],"type":"Point"}
}