{
  "type": "Feature",
  "properties": {
    "iso:country":"AT",
    "sg:address":"Genotteallee 11",
    "sg:city":"Villach",
    "sg:orig_category":"Feinkost",
    "sg:phone":"+43 4242 24470",
    "sg:postcode":"9500",
    "sg:province":"K\u00e4rnten",
    "wof:name":"Wuzella Ingrid",
    "wof:placetype":"venue"
},
  "geometry": {"coordinates":[13.8421001434,46.6219215393],"type":"Point"}
}