{
  "type": "Feature",
  "properties": {
    "addr:full":"H\u00f6fleiner Str 16 Bruck an der Leitha Nieder\u00f6sterreich 2460",
    "addr:postcode":"2460",
    "addr:street":"Str 16",
    "iso:country":"AT",
    "sg:address":"H\u00f6fleiner Str 16",
    "sg:city":"Bruck an der Leitha",
    "sg:orig_category":"Tourismusinformation U -Organisationen",
    "sg:phone":"+43 4321 6262221",
    "sg:postcode":"2460",
    "sg:province":"Nieder\u00f6sterreich",
    "wof:name":"Tourismusb\u00fcro der Stadtgemeinde Bruck a d Leitha",
    "wof:placetype":"venue"
},
  "geometry": {"coordinates":[16.7815227509,48.029914856],"type":"Point"}
}