{
  "type": "Feature",
  "properties": {
    "addr:full":"Friedhofstrasse 2 Baden Nieder\u00f6sterreich 2500",
    "addr:housenumber":"2",
    "addr:postcode":"2500",
    "addr:street":"Friedhofstrasse;Niederoesterreich",
    "iso:country":"AT",
    "sg:address":"Friedhofstrasse 2",
    "sg:city":"Baden",
    "sg:classifiers":[
        {
            "category":"Health Services",
            "subcategory":"Nursing And Care Facility",
            "type":"Services"
        }
    ],
    "sg:phone":"+43 2252 87946",
    "sg:postcode":"2500",
    "sg:province":"Nieder\u00f6sterreich",
    "sg:tags":[
        "restoration",
        "gold-plating",
        "cross",
        "grave"
    ],
    "wof:name":"Eduard K\u00f6ssler GmbH",
    "wof:placetype":"venue"
},
  "geometry": {"coordinates":[16.2358875275,47.9972610474],"type":"Point"}
}