{
  "type": "Feature",
  "properties": {
    "addr:full":"Schmiedg 8 Brixen im Thale Tirol 6364",
    "addr:housenumber":"8",
    "addr:postcode":"6364",
    "addr:street":"Schmiedg;Tirol",
    "iso:country":"AT",
    "sg:address":"Schmiedg 8",
    "sg:city":"Brixen im Thale",
    "sg:orig_category":"Appartements / Ferienwohnungen",
    "sg:phone":"+43 5334 6840",
    "sg:postcode":"6364",
    "sg:province":"Tirol",
    "wof:name":"Hirzinger Cilli",
    "wof:placetype":"venue"
},
  "geometry": {"coordinates":[12.2403783798,47.4465103149],"type":"Point"}
}