{
  "type": "Feature",
  "properties": {
    "addr:full":"Hauptstr 2 Sattledt Ober\u00f6sterreich 4642",
    "addr:housenumber":"2",
    "addr:postcode":"4642",
    "addr:street":"Hauptstr",
    "iso:country":"AT",
    "sg:address":"Hauptstr 2",
    "sg:city":"Sattledt",
    "sg:orig_category":"Tankstellen",
    "sg:phone":"+43 4372 448782",
    "sg:postcode":"4642",
    "sg:province":"Ober\u00f6sterreich",
    "wof:name":"BP Austria Marketing GmbH",
    "wof:placetype":"venue"
},
  "geometry": {"coordinates":[14.0517253876,48.0731811523],"type":"Point"}
}