{
  "type": "Feature",
  "properties": {
    "addr:full":"Villacher Str 34-36/1/6 Spittal an der Drau K\u00e4rnten 9800",
    "addr:housenumber":"34-36 / 1 / 6",
    "addr:postcode":"9800",
    "addr:street":"Str;Kaernten",
    "iso:country":"AT",
    "sg:address":"Villacher Str 34-36/1/6",
    "sg:city":"Spittal an der Drau",
    "sg:orig_category":"Physiotherapie",
    "sg:phone":"+43 4762 4999",
    "sg:postcode":"9800",
    "sg:province":"K\u00e4rnten",
    "wof:name":"Sommeregger Birgit Dipl-PT",
    "wof:placetype":"venue"
},
  "geometry": {"coordinates":[13.4968900681,46.7977409363],"type":"Point"}
}