{
  "type": "Feature",
  "properties": {
    "iso:country":"AT",
    "sg:address":"Milser Str 41",
    "sg:city":"Hall in Tirol",
    "sg:orig_category":"Zahntechnische Laboratorien",
    "sg:phone":"+43 5223 53937",
    "sg:postcode":"6060",
    "sg:province":"Tirol",
    "wof:name":"Struggl Werner",
    "wof:placetype":"venue"
},
  "geometry": {"coordinates":[11.514380455,47.2827301025],"type":"Point"}
}