{
  "type": "Feature",
  "properties": {
    "addr:full":"Hans-Gerstmayr-Str 2 Steyr Ober\u00f6sterreich 4400",
    "addr:housenumber":"2",
    "addr:postcode":"4400",
    "addr:street":"Hans-Gerstmayr-Str;Oberoesterreich",
    "iso:country":"AT",
    "sg:address":"Hans-Gerstmayr-Str 2",
    "sg:city":"Steyr",
    "sg:orig_category":"Lebensmittel / Erzeugung U Gro\u00c3\u0178handel",
    "sg:phone":"+43 4372 52731700",
    "sg:postcode":"4400",
    "sg:province":"Ober\u00f6sterreich",
    "wof:name":"Almauer F GesmbH",
    "wof:placetype":"venue"
},
  "geometry": {"coordinates":[14.4178438187,48.0562973022],"type":"Point"}
}