{
  "type": "Feature",
  "properties": {
    "addr:full":"Westbahnstr 39 Wien Wien 1070",
    "addr:housenumber":"39",
    "addr:postcode":"1070",
    "addr:street":"Westbahnstr",
    "iso:country":"AT",
    "sg:address":"Westbahnstr 39",
    "sg:city":"Wien",
    "sg:orig_category":"Fleischhauereien",
    "sg:phone":"+43 1 5233417",
    "sg:postcode":"1070",
    "sg:province":"Wien",
    "wof:name":"Anzb\u00f6ck Alfred",
    "wof:placetype":"venue"
},
  "geometry": {"coordinates":[16.3398551941,48.2016525269],"type":"Point"}
}