{
  "type": "Feature",
  "properties": {
    "addr:full":"H\u00f6ttinger Auffahrt 5 Innsbruck Tirol 6020",
    "addr:housenumber":"5",
    "addr:postcode":"6020",
    "addr:street":"Auffahrt;Tirol",
    "iso:country":"AT",
    "sg:address":"H\u00f6ttinger Auffahrt 5",
    "sg:city":"Innsbruck",
    "sg:classifiers":[
        {
            "category":"Professional",
            "subcategory":"Advertising",
            "type":"Services"
        }
    ],
    "sg:phone":"+43 512 290088",
    "sg:postcode":"6020",
    "sg:province":"Tirol",
    "sg:tags":[
        "newspaper",
        "journal"
    ],
    "sg:website":"econova.at",
    "wof:name":"Christoph Loreck KG",
    "wof:placetype":"venue"
},
  "geometry": {"coordinates":[11.3798847198,47.2662773132],"type":"Point"}
}