{
  "type": "Feature",
  "properties": {
    "addr:full":"Breitau 4 St. Gallen Steiermark 8933",
    "addr:housenumber":"4",
    "addr:postcode":"8933",
    "addr:street":"Breitau",
    "iso:country":"AT",
    "sg:address":"Breitau 4",
    "sg:city":"St. Gallen",
    "sg:orig_category":"Appartements / Ferienwohnungen",
    "sg:phone":"+43 3632 439",
    "sg:postcode":"8933",
    "sg:province":"Steiermark",
    "wof:name":"Peterbauernhof",
    "wof:placetype":"venue"
},
  "geometry": {"coordinates":[14.6172552109,47.6922798157],"type":"Point"}
}