{
  "type": "Feature",
  "properties": {
    "addr:full":"Weitersfelden 110 Weitersfelden Ober\u00f6sterreich 4272",
    "addr:housenumber":"110",
    "addr:postcode":"4272",
    "addr:street":"Weitersfelden",
    "iso:country":"AT",
    "sg:address":"Weitersfelden 110",
    "sg:city":"Weitersfelden",
    "sg:orig_category":"Natural Bedding",
    "sg:phone":"+43 7952 85880",
    "sg:postcode":"4272",
    "sg:province":"Ober\u00f6sterreich",
    "sg:website":"textilwerkstatt.at",
    "wof:name":"Textilwerkstatt Weitersfelden, Punkenhofer KEG",
    "wof:placetype":"venue"
},
  "geometry": {"coordinates":[14.7250175476,48.4773635864],"type":"Point"}
}