{
  "type": "Feature",
  "properties": {
    "addr:full":"Maria-Theresien-Str 38 Innsbruck Tirol 6020",
    "addr:housenumber":"38",
    "addr:postcode":"6020",
    "addr:street":"Maria-Theresien-Str;Tirol",
    "iso:country":"AT",
    "sg:address":"Maria-Theresien-Str 38",
    "sg:city":"Innsbruck",
    "sg:orig_category":"Institute",
    "sg:phone":"+43 512 583373",
    "sg:postcode":"6020",
    "sg:province":"Tirol",
    "wof:name":"Italienisches Kulturinstitut",
    "wof:placetype":"venue"
},
  "geometry": {"coordinates":[11.3945922852,47.2644195557],"type":"Point"}
}