{
  "type": "Feature",
  "properties": {
    "addr:full":"Pottendorfer Str 45 Wiener Neustadt Nieder\u00f6sterreich 2700",
    "addr:postcode":"2700",
    "addr:street":"Str 45",
    "iso:country":"AT",
    "sg:address":"Pottendorfer Str 45",
    "sg:city":"Wiener Neustadt",
    "sg:orig_category":"Restaurants: Amerikanisch",
    "sg:phone":"+43 2622 29835",
    "sg:postcode":"2700",
    "sg:province":"Nieder\u00f6sterreich",
    "wof:name":"McDonald's Restaurant - McDrive",
    "wof:placetype":"venue"
},
  "geometry": {"coordinates":[16.2536087036,47.8272514343],"type":"Point"}
}