{
  "type": "Feature",
  "properties": {
    "addr:full":"Beethoveng 4-6 Mauerbach Nieder\u00f6sterreich 3001",
    "addr:housenumber":"4-6",
    "addr:postcode":"3001",
    "addr:street":"Beethoveng",
    "iso:country":"AT",
    "sg:address":"Beethoveng 4-6",
    "sg:city":"Mauerbach",
    "sg:orig_category":"Immobilienverwaltungen",
    "sg:phone":"+43 1 5774400",
    "sg:postcode":"3001",
    "sg:province":"Nieder\u00f6sterreich",
    "wof:name":"IKK Immobilienkanzlei Mag Kutschera KEG",
    "wof:placetype":"venue"
},
  "geometry": {"coordinates":[16.1895961761,48.2400894165],"type":"Point"}
}