{
  "type": "Feature",
  "properties": {
    "addr:full":"Industriezentrum N\u00f6 S\u00fcd Stra\u00dfe 14 Obj 32 2355",
    "addr:housenumber":"14 obj 32",
    "addr:postcode":"2355",
    "addr:street":"Industriezentrum Noe Sued Strasse",
    "iso:country":"AT",
    "sg:address":"Industriezentrum N\u00f6 S\u00fcd Stra\u00dfe 14 Obj 32",
    "sg:orig_category":"Speditionen",
    "sg:phone":"+43 4322 36625550",
    "sg:postcode":"2355",
    "wof:name":"BTG Spedition u Logistik GmbH",
    "wof:placetype":"venue"
},
  "geometry": {"coordinates":[16.3183326721,48.0863113403],"type":"Point"}
}