{
  "type": "Feature",
  "properties": {
    "iso:country":"AT",
    "sg:address":"Hans-Sachs-Str 133",
    "sg:city":"Wels",
    "sg:orig_category":"Autoreparatur",
    "sg:phone":"+43 7242 462370",
    "sg:postcode":"4600",
    "sg:province":"Ober\u00f6sterreich",
    "sg:website":"www.geyrhofer.bmw.at",
    "wof:name":"Geyrhofer Hans & Sohn GesmbH",
    "wof:placetype":"venue"
},
  "geometry": {"coordinates":[14.0454101562,48.1694793701],"type":"Point"}
}