{
  "type": "Feature",
  "properties": {
    "addr:full":"Rochusg 10 Wien Wien 1030",
    "addr:housenumber":"10",
    "addr:postcode":"1030",
    "addr:street":"Rochusg",
    "iso:country":"AT",
    "sg:address":"Rochusg 10",
    "sg:city":"Wien",
    "sg:orig_category":"Pelze U Pelzwaren",
    "sg:phone":"+43 4317 129090",
    "sg:postcode":"1030",
    "sg:province":"Wien",
    "wof:name":"Pelzmoden Christine Reiter",
    "wof:placetype":"venue"
},
  "geometry": {"coordinates":[16.3896427155,48.2014884949],"type":"Point"}
}