{
  "type": "Feature",
  "properties": {
    "addr:full":"Hauptstr 20 St. Valentin Nieder\u00f6sterreich 4300",
    "addr:housenumber":"20",
    "addr:postcode":"4300",
    "addr:street":"Hauptstr",
    "iso:country":"AT",
    "sg:address":"Hauptstr 20",
    "sg:city":"St. Valentin",
    "sg:orig_category":"Glasereien",
    "sg:phone":"+43 7435 521010",
    "sg:postcode":"4300",
    "sg:province":"Nieder\u00f6sterreich",
    "wof:name":"Fuchshuber Wolfgang GesmbH",
    "wof:placetype":"venue"
},
  "geometry": {"coordinates":[14.5293016434,48.175163269],"type":"Point"}
}