{
  "type": "Feature",
  "properties": {
    "iso:country":"AT",
    "sg:address":"Morgenstrasse 3",
    "sg:city":"Lustenau",
    "sg:orig_category":"Dancing Dresses, Dancing Articles",
    "sg:phone":"+43 5577 86910",
    "sg:postcode":"6890",
    "sg:province":"Vorarlberg",
    "sg:website":"ernessa.com",
    "wof:name":"ERNESSA - Austria",
    "wof:placetype":"venue"
},
  "geometry": {"coordinates":[9.6589107513,47.4229774475],"type":"Point"}
}