{
  "type": "Feature",
  "properties": {
    "addr:full":"Kirchpl 1 Steinfeld K\u00e4rnten 9754",
    "addr:housenumber":"1",
    "addr:postcode":"9754",
    "addr:street":"Kirchpl",
    "iso:country":"AT",
    "sg:address":"Kirchpl 1",
    "sg:city":"Steinfeld",
    "sg:orig_category":"Non-Classified Establishments",
    "sg:phone":"+43 4717 248",
    "sg:postcode":"9754",
    "sg:province":"K\u00e4rnten",
    "wof:name":"Pfarramt",
    "wof:placetype":"venue"
},
  "geometry": {"coordinates":[13.2469968796,46.7583580017],"type":"Point"}
}