{
  "type": "Feature",
  "properties": {
    "iso:country":"AT",
    "sg:address":"Dauphinestr 78",
    "sg:city":"Linz",
    "sg:classifiers":[
        {
            "category":"Professional",
            "subcategory":"Computer Services",
            "type":"Services"
        }
    ],
    "sg:phone":"+43 4373 2313378",
    "sg:postcode":"4030",
    "sg:province":"Ober\u00f6sterreich",
    "sg:tags":[
        "software"
    ],
    "wof:name":"St\u00f6ckl Dr u Dr Maasz OEG",
    "wof:placetype":"venue"
},
  "geometry": {"coordinates":[14.308508873,48.2538604736],"type":"Point"}
}