{
  "type": "Feature",
  "properties": {
    "addr:full":"Sickenbergg 6/3 Wien Wien 1190",
    "addr:housenumber":"6 / 3",
    "addr:postcode":"1190",
    "addr:street":"Sickenbergg",
    "iso:country":"AT",
    "sg:address":"Sickenbergg 6/3",
    "sg:city":"Wien",
    "sg:classifiers":[
        {
            "category":"Commercial Area",
            "type":"Public Place"
        }
    ],
    "sg:phone":"+43 1 3708390",
    "sg:postcode":"1190",
    "sg:province":"Wien",
    "sg:tags":[
        "e-commerce"
    ],
    "wof:name":"atwork information technology Pohl Toni",
    "wof:placetype":"venue"
},
  "geometry": {"coordinates":[16.3660736084,48.2581367493],"type":"Point"}
}