{
  "type": "Feature",
  "properties": {
    "iso:country":"AT",
    "sg:address":"Ganglgutstra\u00dfe 131",
    "sg:city":"Traun",
    "sg:orig_category":"Immobilien U Baugewerbe, Baugewerbe",
    "sg:postcode":"4050",
    "sg:province":"Ober\u00f6sterreich",
    "sg:website":"http://www.internorm.com",
    "wof:name":"Internorm Fenster AG",
    "wof:placetype":"venue"
},
  "geometry": {"coordinates":[14.2384881973,48.221572876],"type":"Point"}
}