{
  "type": "Feature",
  "properties": {
    "addr:full":"Schranne 8 Wallern an der Trattnach Ober\u00f6sterreich 4702",
    "addr:housenumber":"8",
    "addr:postcode":"4702",
    "addr:street":"Schranne",
    "iso:country":"AT",
    "sg:address":"Schranne 8",
    "sg:city":"Wallern an der Trattnach",
    "sg:orig_category":"Friseure U Frisiersalons",
    "sg:phone":"+43 4372 4948160",
    "sg:postcode":"4702",
    "sg:province":"Ober\u00f6sterreich",
    "wof:name":"Haarstudio Eva Sonntag",
    "wof:placetype":"venue"
},
  "geometry": {"coordinates":[13.9466199875,48.230670929],"type":"Point"}
}