{
  "type": "Feature",
  "properties": {
    "iso:country":"AT",
    "sg:address":"Nr 163",
    "sg:city":"St. Johann in der Haide",
    "sg:orig_category":"Polizei U Gendarmerie",
    "sg:phone":"+43 4359 1336238",
    "sg:postcode":"8295",
    "sg:province":"Steiermark",
    "wof:name":"Autobahngendarmerie",
    "wof:placetype":"venue"
},
  "geometry": {"coordinates":[16.0245819092,47.2807769775],"type":"Point"}
}