{
  "type": "Feature",
  "properties": {
    "addr:full":"Fiziastr 2 Liebenau Steiermark 8041",
    "addr:housenumber":"2",
    "addr:postcode":"8041",
    "addr:street":"Fiziastr",
    "iso:country":"AT",
    "sg:address":"Fiziastr 2",
    "sg:city":"Liebenau",
    "sg:orig_category":"Werbeagenturen",
    "sg:phone":"+43 699 17001717",
    "sg:postcode":"8041",
    "sg:province":"Steiermark",
    "wof:name":"Gollmaier Christian KEG",
    "wof:placetype":"venue"
},
  "geometry": {"coordinates":[15.4473743439,47.0443725586],"type":"Point"}
}