{
  "type": "Feature",
  "properties": {
    "addr:full":"Teiritzstr 6 Korneuburg Nieder\u00f6sterreich 2100",
    "addr:housenumber":"6",
    "addr:postcode":"2100",
    "addr:street":"Teiritzstr;Niederoesterreich",
    "iso:country":"AT",
    "sg:address":"Teiritzstr 6",
    "sg:city":"Korneuburg",
    "sg:orig_category":"Damenmoden",
    "sg:phone":"+43 4322 6262021",
    "sg:postcode":"2100",
    "sg:province":"Nieder\u00f6sterreich",
    "wof:name":"KiK Textilien u Non-Food GesmbH",
    "wof:placetype":"venue"
},
  "geometry": {"coordinates":[16.3408164978,48.3516731262],"type":"Point"}
}