{
  "type": "Feature",
  "properties": {
    "addr:full":"Marktpl 2 Pinkafeld Burgenland 7423",
    "addr:housenumber":"2",
    "addr:postcode":"7423",
    "addr:street":"Marktpl",
    "iso:country":"AT",
    "sg:address":"Marktpl 2",
    "sg:city":"Pinkafeld",
    "sg:orig_category":"Fleischhauereien",
    "sg:phone":"+43 3357 422630",
    "sg:postcode":"7423",
    "sg:province":"Burgenland",
    "wof:name":"Ebner Josef",
    "wof:placetype":"venue"
},
  "geometry": {"coordinates":[16.1231021881,47.3712234497],"type":"Point"}
}