{
  "type": "Feature",
  "properties": {
    "addr:full":"W\u00e4hringer Str 118 Wien Wien 1180",
    "addr:housenumber":"118",
    "addr:postcode":"1180",
    "addr:street":"Str",
    "iso:country":"AT",
    "sg:address":"W\u00e4hringer Str 118",
    "sg:city":"Wien",
    "sg:orig_category":"Bettwaren",
    "sg:phone":"+43 1 4796984",
    "sg:postcode":"1180",
    "sg:province":"Wien",
    "wof:name":"Gans GesmbH",
    "wof:placetype":"venue"
},
  "geometry": {"coordinates":[16.3437137604,48.2265319824],"type":"Point"}
}