{
  "type": "Feature",
  "properties": {
    "addr:full":"Lambacher Str 4 Gunskirchen Ober\u00f6sterreich 4623",
    "addr:housenumber":"4",
    "addr:postcode":"4623",
    "addr:street":"Str",
    "iso:country":"AT",
    "sg:address":"Lambacher Str 4",
    "sg:city":"Gunskirchen",
    "sg:orig_category":"Musikunterricht",
    "sg:phone":"+43 7246 7660",
    "sg:postcode":"4623",
    "sg:province":"Ober\u00f6sterreich",
    "wof:name":"Landesmusikschule Stadl-Paura",
    "wof:placetype":"venue"
},
  "geometry": {"coordinates":[13.9417762756,48.1323242188],"type":"Point"}
}