{
  "type": "Feature",
  "properties": {
    "addr:full":"Industriestr 24 Gerasdorf Nieder\u00f6sterreich 2201",
    "addr:housenumber":"24",
    "addr:postcode":"2201",
    "addr:street":"Industriestr",
    "iso:country":"AT",
    "sg:address":"Industriestr 24",
    "sg:city":"Gerasdorf",
    "sg:orig_category":"Reifen U Reifendienste, Autoreparatur",
    "sg:phone":"+43 2246 34280",
    "sg:postcode":"2201",
    "sg:province":"Nieder\u00f6sterreich",
    "sg:website":"www.niederreiter.at",
    "wof:name":"Niederreiter Robert",
    "wof:placetype":"venue"
},
  "geometry": {"coordinates":[16.4708862305,48.2990150452],"type":"Point"}
}