{
  "type": "Feature",
  "properties": {
    "addr:full":"Gr\u00fcnau im Almtal 48 Gr\u00fcnau im Almtal Ober\u00f6sterreich 4645",
    "addr:housenumber":"48",
    "addr:postcode":"4645",
    "addr:street":"Im Almtal",
    "iso:country":"AT",
    "sg:address":"Gr\u00fcnau im Almtal 48",
    "sg:city":"Gr\u00fcnau im Almtal",
    "sg:classifiers":[
        {
            "category":"Manufacturing",
            "subcategory":"Wood Products",
            "type":"Manufacturing & Wholesale Goods"
        }
    ],
    "sg:phone":"+43 76168215",
    "sg:postcode":"4645",
    "sg:province":"Ober\u00f6sterreich",
    "sg:tags":[
        "lumber"
    ],
    "wof:name":"Heinrich Drack, S\u00e4gewerk und Holzhandel OHG Inh. Walter und Emma Bammer",
    "wof:placetype":"venue"
},
  "geometry": {"coordinates":[173.85847473140001,-39.453868866],"type":"Point"}
}