{
  "type": "Feature",
  "properties": {
    "addr:full":"Simmeringer Hauptstrasse 108 A/2 Wien Wien 1110",
    "addr:housenumber":"108 a / 2",
    "addr:postcode":"1110",
    "addr:street":"Simmeringer Hauptstrasse",
    "iso:country":"AT",
    "sg:address":"Simmeringer Hauptstrasse 108 A/2",
    "sg:city":"Wien",
    "sg:classifiers":[
        {
            "category":"Professional",
            "subcategory":"Computer Services",
            "type":"Services"
        }
    ],
    "sg:phone":"+43 1 7436163",
    "sg:postcode":"1110",
    "sg:province":"Wien",
    "sg:tags":[
        "development",
        "software"
    ],
    "sg:website":"iod.at",
    "wof:name":"Internet-Online-Dienste Ges.m.b.H.",
    "wof:placetype":"venue"
},
  "geometry": {"coordinates":[16.4335365295,48.1585578918],"type":"Point"}
}