{
  "type": "Feature",
  "properties": {
    "addr:full":"Schie\u00dfstattstr 21 Salzburg Salzburg 5020",
    "addr:housenumber":"21",
    "addr:postcode":"5020",
    "addr:street":"Schiessstattstr;Salzburg",
    "iso:country":"AT",
    "sg:address":"Schie\u00dfstattstr 21",
    "sg:city":"Salzburg",
    "sg:orig_category":"Genossenschaften",
    "sg:phone":"+43 4366 2432512",
    "sg:postcode":"5020",
    "sg:province":"Salzburg",
    "wof:name":"WAG Wohnungsanlagen GmbH - Gesch\u00e4ftsstelle Salzburg",
    "wof:placetype":"venue"
},
  "geometry": {"coordinates":[13.0333375931,47.8136405945],"type":"Point"}
}