{
  "type": "Feature",
  "properties": {
    "iso:country":"AT",
    "sg:address":"Weinberg 95",
    "sg:city":"Miklauzhof",
    "sg:orig_category":"Friseure U Frisiersalons",
    "sg:phone":"+43 4342 372058",
    "sg:postcode":"9133",
    "sg:province":"K\u00e4rnten",
    "wof:name":"Keschar Hildegard",
    "wof:placetype":"venue"
},
  "geometry": {"coordinates":[14.6061134338,46.5438575745],"type":"Point"}
}