{
  "type": "Feature",
  "properties": {
    "iso:country":"AT",
    "sg:address":"Eduard-Bodem-G 3",
    "sg:city":"Innsbruck",
    "sg:orig_category":"Massagen",
    "sg:phone":"+43 699 10029143",
    "sg:postcode":"6020",
    "sg:province":"Tirol",
    "wof:name":"Massage Lunardon Eva",
    "wof:placetype":"venue"
},
  "geometry": {"coordinates":[11.434296608,47.2653923035],"type":"Point"}
}