{
  "type": "Feature",
  "properties": {
    "addr:full":"Hauptstr 3 Oberpullendorf Burgenland 7350",
    "addr:housenumber":"3",
    "addr:postcode":"7350",
    "addr:street":"Hauptstr",
    "iso:country":"AT",
    "sg:address":"Hauptstr 3",
    "sg:city":"Oberpullendorf",
    "sg:orig_category":"Boutiquen",
    "sg:phone":"+43 2612 42485",
    "sg:postcode":"7350",
    "sg:province":"Burgenland",
    "wof:name":"Hot Line Trendmode",
    "wof:placetype":"venue"
},
  "geometry": {"coordinates":[16.5051841736,47.5016365051],"type":"Point"}
}