{
  "type": "Feature",
  "properties": {
    "addr:full":"Hellbrunner Str 2 Anif Salzburg 5081",
    "addr:housenumber":"2",
    "addr:postcode":"5081",
    "addr:street":"Str;Salzburg",
    "iso:country":"AT",
    "sg:address":"Hellbrunner Str 2",
    "sg:city":"Anif",
    "sg:orig_category":"Fenster",
    "sg:phone":"+43 4362 4677129",
    "sg:postcode":"5081",
    "sg:province":"Salzburg",
    "wof:name":"Hagenauer Paul GmbH Josko Fenster u T\u00fcrenstudio",
    "wof:placetype":"venue"
},
  "geometry": {"coordinates":[13.0668735504,47.7480888367],"type":"Point"}
}