{
  "type": "Feature",
  "properties": {
    "addr:full":"Obere Hauptstr 176 St. Ruprecht an der Raab Steiermark 8181",
    "addr:housenumber":"176",
    "addr:postcode":"8181",
    "addr:street":"Obere Hauptstr",
    "iso:country":"AT",
    "sg:address":"Obere Hauptstr 176",
    "sg:city":"St. Ruprecht an der Raab",
    "sg:orig_category":"Tischlereien",
    "sg:phone":"+43 4331 782363",
    "sg:postcode":"8181",
    "sg:province":"Steiermark",
    "wof:name":"Purkarthofer Karl",
    "wof:placetype":"venue"
},
  "geometry": {"coordinates":[15.6614179611,47.1615867615],"type":"Point"}
}