{
  "type": "Feature",
  "properties": {
    "addr:full":"Schulhausg 8 Ferlach K\u00e4rnten 9170",
    "addr:housenumber":"8",
    "addr:postcode":"9170",
    "addr:street":"Schulhausg;Kaernten",
    "iso:country":"AT",
    "sg:address":"Schulhausg 8",
    "sg:city":"Ferlach",
    "sg:orig_category":"Zahntechnische Laboratorien",
    "sg:phone":"+43 4227 5150",
    "sg:postcode":"9170",
    "sg:province":"K\u00e4rnten",
    "wof:name":"Machac Paul jr",
    "wof:placetype":"venue"
},
  "geometry": {"coordinates":[14.3021011353,46.5284881592],"type":"Point"}
}