{
  "type": "Feature",
  "properties": {
    "addr:full":"Am See 1 Maria Lankowitz Steiermark 8591",
    "addr:housenumber":"1",
    "addr:postcode":"8591",
    "addr:street":"Am See",
    "iso:country":"AT",
    "sg:address":"Am See 1",
    "sg:city":"Maria Lankowitz",
    "sg:orig_category":"Freizeitangebote U -Einrichtungen",
    "sg:phone":"+43 4331 447095970",
    "sg:postcode":"8591",
    "sg:province":"Steiermark",
    "wof:name":"Freizeitinsel Piberstein Sportpark GesmbH",
    "wof:placetype":"venue"
},
  "geometry": {"coordinates":[15.0689926147,47.058795929],"type":"Point"}
}