{
  "type": "Feature",
  "properties": {
    "iso:country":"AT",
    "sg:address":"Teichwiese 12",
    "sg:city":"Lackenhof",
    "sg:classifiers":[
        {
            "category":"Park",
            "subcategory":"Provincial",
            "type":"Public Place"
        }
    ],
    "sg:phone":"+43 4374 805828",
    "sg:postcode":"3295",
    "sg:province":"Nieder\u00f6sterreich",
    "sg:tags":[
        "u",
        "ski-",
        "snowboardschulen"
    ],
    "wof:name":"Schischule Total",
    "wof:placetype":"venue"
},
  "geometry": {"coordinates":[15.1543798447,47.8704185486],"type":"Point"}
}