{
  "type": "Feature",
  "properties": {
    "iso:country":"AT",
    "sg:address":"Joetsustr 2",
    "sg:city":"Lilienfeld",
    "sg:orig_category":"Feuerwehren",
    "sg:phone":"+43 2762 53888",
    "sg:postcode":"3180",
    "sg:province":"Nieder\u00f6sterreich",
    "wof:name":"Freiwillige Feuerwehr Schrambach",
    "wof:placetype":"venue"
},
  "geometry": {"coordinates":[15.5709295273,47.9981422424],"type":"Point"}
}