{
  "type": "Feature",
  "properties": {
    "iso:country":"AT",
    "sg:address":"Seideng 16",
    "sg:city":"Wien",
    "sg:orig_category":"Garagen Parkgaragen",
    "sg:phone":"+43 4315 230471",
    "sg:postcode":"1070",
    "sg:province":"Wien",
    "wof:name":"Autoparkplatz Neubau Martin Kretzner GmbH",
    "wof:placetype":"venue"
},
  "geometry": {"coordinates":[16.3439540863,48.2004890442],"type":"Point"}
}