{
  "type": "Feature",
  "properties": {
    "iso:country":"AT",
    "sg:address":"8.Mai-Str 41",
    "sg:city":"Klagenfurt",
    "sg:orig_category":"Physiotherapie",
    "sg:phone":"+43 463 51110011",
    "sg:postcode":"9020",
    "sg:province":"K\u00e4rnten",
    "wof:name":"Aktiv Physiotherapie und Pr\u00e4vention GmbH",
    "wof:placetype":"venue"
},
  "geometry": {"coordinates":[14.3117847443,46.6232910156],"type":"Point"}
}