{
  "type": "Feature",
  "properties": {
    "addr:full":"Kaiserbergstr 16 Kufstein Tirol 6330",
    "addr:housenumber":"16",
    "addr:postcode":"6330",
    "addr:street":"Kaiserbergstr;Tirol",
    "iso:country":"AT",
    "sg:address":"Kaiserbergstr 16",
    "sg:city":"Kufstein",
    "sg:orig_category":"Spirituosen / Erzeugung U Gro\u00c3\u0178handel",
    "sg:phone":"+43 5372 62711",
    "sg:postcode":"6330",
    "sg:province":"Tirol",
    "wof:name":"Brennerei Kronthaler GmbH & Co KG",
    "wof:placetype":"venue"
},
  "geometry": {"coordinates":[12.1723241806,47.5856933594],"type":"Point"}
}