{
  "type": "Feature",
  "properties": {
    "addr:full":"Obere Str 45 Schiltern Nieder\u00f6sterreich 3553",
    "addr:housenumber":"45",
    "addr:postcode":"3553",
    "addr:street":"Obere Str;Niederoesterreich",
    "iso:country":"AT",
    "sg:address":"Obere Str 45",
    "sg:city":"Schiltern",
    "sg:classifiers":[
        {
            "category":"Utilities",
            "subcategory":"Refuse",
            "type":"Services"
        }
    ],
    "sg:phone":"+43 664 1531914",
    "sg:postcode":"3553",
    "sg:province":"Nieder\u00f6sterreich",
    "sg:tags":[
        "catering"
    ],
    "sg:website":"gattingers.at",
    "wof:name":"Gattinger's Catering Service",
    "wof:placetype":"venue"
},
  "geometry": {"coordinates":[15.617143631,48.5187683105],"type":"Point"}
}