{
  "type": "Feature",
  "properties": {
    "iso:country":"AT",
    "sg:address":"Pestalozzistr 19",
    "sg:city":"Krieglach",
    "sg:orig_category":"Transportunternehmen",
    "sg:phone":"+43 3855 2213",
    "sg:postcode":"8670",
    "sg:province":"Steiermark",
    "wof:name":"Allmer Peter GesmbH",
    "wof:placetype":"venue"
},
  "geometry": {"coordinates":[15.5582551956,47.5459251404],"type":"Point"}
}