{
  "type": "Feature",
  "properties": {
    "addr:full":"Markt 99 St. Marein Steiermark 8323",
    "addr:housenumber":"99",
    "addr:postcode":"8323",
    "addr:street":"Markt",
    "iso:country":"AT",
    "sg:address":"Markt 99",
    "sg:city":"St. Marein",
    "sg:orig_category":"Feuerwehren",
    "sg:phone":"+43 3119 2022",
    "sg:postcode":"8323",
    "sg:province":"Steiermark",
    "wof:name":"Freiwillige Feuerwehr St Marein b Graz",
    "wof:placetype":"venue"
},
  "geometry": {"coordinates":[15.6941776276,47.0135116577],"type":"Point"}
}