{
  "type": "Feature",
  "properties": {
    "iso:country":"AT",
    "sg:address":"Bahnhofstrasse 1",
    "sg:city":"Gleisdorf",
    "sg:classifiers":[
        {
            "category":"Professional",
            "type":"Services"
        }
    ],
    "sg:phone":"+43 3112 87080",
    "sg:postcode":"8200",
    "sg:province":"Steiermark",
    "sg:tags":[
        "catering"
    ],
    "wof:name":"Hofer & Partner OEG",
    "wof:placetype":"venue"
},
  "geometry": {"coordinates":[15.7046737671,47.1034049988],"type":"Point"}
}