{
  "type": "Feature",
  "properties": {
    "iso:country":"AT",
    "sg:address":"St. Veiter Str 144",
    "sg:city":"St. Veit",
    "sg:orig_category":"Telefonanlagen",
    "sg:phone":"+43 4331 6698043",
    "sg:postcode":"8046",
    "sg:province":"Steiermark",
    "sg:website":"perfectsound.at",
    "wof:name":"Perfect Phone",
    "wof:placetype":"venue"
},
  "geometry": {"coordinates":[15.4116888046,47.1217651367],"type":"Point"}
}