{
  "type": "Feature",
  "properties": {
    "addr:full":"Josef Ferschner-Str 38 Traiskirchen Nieder\u00f6sterreich 2514",
    "addr:housenumber":"38",
    "addr:postcode":"2514",
    "addr:street":"Niederoesterreich",
    "iso:country":"AT",
    "sg:address":"Josef Ferschner-Str 38",
    "sg:city":"Traiskirchen",
    "sg:orig_category":"\u00c3\u201erzte / F Allgemeinmedizin",
    "sg:phone":"+43 2252 521770",
    "sg:postcode":"2514",
    "sg:province":"Nieder\u00f6sterreich",
    "wof:name":"Schimbach Hans Dr",
    "wof:placetype":"venue"
},
  "geometry": {"coordinates":[16.292388916,48.0168838501],"type":"Point"}
}