{
  "type": "Feature",
  "properties": {
    "addr:full":"Belgierg 6 Graz Steiermark 8020",
    "addr:housenumber":"6",
    "addr:postcode":"8020",
    "addr:street":"Belgierg",
    "iso:country":"AT",
    "sg:address":"Belgierg 6",
    "sg:city":"Graz",
    "sg:classifiers":[
        {
            "category":"Professional",
            "subcategory":"Computer Services",
            "type":"Services"
        }
    ],
    "sg:phone":"+43 4331 67202400",
    "sg:postcode":"8020",
    "sg:province":"Steiermark",
    "sg:tags":[
        "software"
    ],
    "wof:name":"Inbox.cc",
    "wof:placetype":"venue"
},
  "geometry": {"coordinates":[15.4334468842,47.0697441101],"type":"Point"}
}