{
  "type": "Feature",
  "properties": {
    "iso:country":"AT",
    "sg:address":"Taborstr 38",
    "sg:city":"Wien",
    "sg:orig_category":"Fitnesscenter",
    "sg:phone":"+43 1 2169933",
    "sg:postcode":"1020",
    "sg:province":"Wien",
    "wof:name":"FITNESSCENTER KAMERGI KEG",
    "wof:placetype":"venue"
},
  "geometry": {"coordinates":[16.3809528351,48.2186813354],"type":"Point"}
}