{
  "type": "Feature",
  "properties": {
    "iso:country":"AT",
    "sg:address":"Hauptpl 29",
    "sg:city":"Neumarkt in Steiermark",
    "sg:orig_category":"Bankomat-Standorte",
    "sg:phone":"+43 4335 8424200",
    "sg:postcode":"8820",
    "sg:province":"Steiermark",
    "wof:name":"Bankomat d Steierm\u00e4rkische Bank- u Sparkassen AG",
    "wof:placetype":"venue"
},
  "geometry": {"coordinates":[14.4265766144,47.0727157593],"type":"Point"}
}