{
  "type": "Feature",
  "properties": {
    "addr:full":"Hauptplatz 21 Leibnitz Steiermark 8430",
    "addr:housenumber":"21",
    "addr:postcode":"8430",
    "addr:street":"Hauptplatz;Steiermark",
    "iso:country":"AT",
    "sg:address":"Hauptplatz 21",
    "sg:city":"Leibnitz",
    "sg:classifiers":[
        {
            "category":"Real Estate",
            "subcategory":"Architect",
            "type":"Services"
        }
    ],
    "sg:phone":"+43 4334 5282490",
    "sg:postcode":"8430",
    "sg:province":"Steiermark",
    "sg:tags":[
        "textile",
        "clothing"
    ],
    "wof:name":"KARL KAPPAUN GMBH",
    "wof:placetype":"venue"
},
  "geometry": {"coordinates":[15.5391960144,46.781578064],"type":"Point"}
}