{
  "type": "Feature",
  "properties": {
    "addr:full":"Breinberg Nord 58 Neumarkt am Wallersee Salzburg 5202",
    "addr:housenumber":"58",
    "addr:postcode":"5202",
    "addr:street":"Breinberg Nord;Salzburg",
    "iso:country":"AT",
    "sg:address":"Breinberg Nord 58",
    "sg:city":"Neumarkt am Wallersee",
    "sg:orig_category":"Fundraising-Agenturen",
    "sg:phone":"+43 4362 1620250",
    "sg:postcode":"5202",
    "sg:province":"Salzburg",
    "wof:name":"BUS Wesser GmbH",
    "wof:placetype":"venue"
},
  "geometry": {"coordinates":[13.2369756699,47.9486351013],"type":"Point"}
}