{
  "type": "Feature",
  "properties": {
    "addr:full":"Schulstr 7 Offenhausen Ober\u00f6sterreich 4625",
    "addr:housenumber":"7",
    "addr:postcode":"4625",
    "addr:street":"Schulstr",
    "iso:country":"AT",
    "sg:address":"Schulstr 7",
    "sg:city":"Offenhausen",
    "sg:orig_category":"Bauunternehmen",
    "sg:phone":"+43 7247 61610",
    "sg:postcode":"4625",
    "sg:province":"Ober\u00f6sterreich",
    "wof:name":"Reinthaler Josef Bauunternehmung GesmbH & Co KG",
    "wof:placetype":"venue"
},
  "geometry": {"coordinates":[13.8382234573,48.1571006775],"type":"Point"}
}