{
  "type": "Feature",
  "properties": {
    "addr:full":"Gewerbeparkstr. 9  Anif Salzburg 5081",
    "addr:housenumber":"9",
    "addr:postcode":"5081",
    "addr:street":"Gewerbeparkstr.;Salzburg",
    "iso:country":"AT",
    "sg:address":"Gewerbeparkstr. 9 ",
    "sg:city":"Anif",
    "sg:classifiers":[
        {
            "category":"Manufacturing",
            "subcategory":"Metals",
            "type":"Manufacturing & Wholesale Goods"
        }
    ],
    "sg:phone":"+43 4362 46720910",
    "sg:postcode":"5081",
    "sg:province":"Salzburg",
    "sg:tags":[
        "metallurgy",
        "metalworking"
    ],
    "wof:name":"WALTER WERKZEUGE SALZBURG GES.MBH",
    "wof:placetype":"venue"
},
  "geometry": {"coordinates":[13.0639257431,47.7499694824],"type":"Point"}
}