{
  "type": "Feature",
  "properties": {
    "iso:country":"AT",
    "sg:address":"Rennweg 77",
    "sg:city":"Brunn am Gebirge",
    "sg:orig_category":"Maschinenbau",
    "sg:phone":"+43 4322 3636544",
    "sg:postcode":"2345",
    "sg:province":"Nieder\u00f6sterreich",
    "wof:name":"Emba Machinery",
    "wof:placetype":"venue"
},
  "geometry": {"coordinates":[16.3012218475,48.1078567505],"type":"Point"}
}