{
  "type": "Feature",
  "properties": {
    "addr:full":"Nr 132 Kleinreifling Ober\u00f6sterreich 4464",
    "addr:postcode":"4464",
    "addr:street":"Nr 132",
    "iso:country":"AT",
    "sg:address":"Nr 132",
    "sg:city":"Kleinreifling",
    "sg:orig_category":"Volksschulen",
    "sg:phone":"+43 4373 57255",
    "sg:postcode":"4464",
    "sg:province":"Ober\u00f6sterreich",
    "wof:name":"Volksschule",
    "wof:placetype":"venue"
},
  "geometry": {"coordinates":[14.6398630142,47.8204917908],"type":"Point"}
}