{
  "type": "Feature",
  "properties": {
    "addr:full":"Nr 37 Herzogsdorf Ober\u00f6sterreich 4175",
    "addr:postcode":"4175",
    "addr:street":"Nr;Oberoesterreich",
    "iso:country":"AT",
    "sg:address":"Nr 37",
    "sg:city":"Herzogsdorf",
    "sg:orig_category":"Gemeinden",
    "sg:phone":"+43 7231 22550",
    "sg:postcode":"4175",
    "sg:province":"Ober\u00f6sterreich",
    "wof:name":"Gemeinde Herzogsdorf",
    "wof:placetype":"venue"
},
  "geometry": {"coordinates":[14.1121921539,48.4299697876],"type":"Point"}
}