{
  "type": "Feature",
  "properties": {
    "addr:full":"Handelsstr 13 Herzogenburg Nieder\u00f6sterreich 3130",
    "addr:housenumber":"13",
    "addr:postcode":"3130",
    "addr:street":"Handelsstr",
    "iso:country":"AT",
    "sg:address":"Handelsstr 13",
    "sg:city":"Herzogenburg",
    "sg:orig_category":"Autoreparatur",
    "sg:phone":"+43 2782 86920",
    "sg:postcode":"3130",
    "sg:province":"Nieder\u00f6sterreich",
    "wof:name":"Demir Erdem",
    "wof:placetype":"venue"
},
  "geometry": {"coordinates":[15.685423851,48.266494751],"type":"Point"}
}