{
  "type": "Feature",
  "properties": {
    "addr:full":"Florianiweg 7 Rosegg K\u00e4rnten 9232",
    "addr:housenumber":"7",
    "addr:postcode":"9232",
    "addr:street":"Florianiweg;Kaernten",
    "iso:country":"AT",
    "sg:address":"Florianiweg 7",
    "sg:city":"Rosegg",
    "sg:orig_category":"Rauchfangkehrer",
    "sg:phone":"+43 4274 3457",
    "sg:postcode":"9232",
    "sg:province":"K\u00e4rnten",
    "wof:name":"Hiebler Johann KG",
    "wof:placetype":"venue"
},
  "geometry": {"coordinates":[14.0191650391,46.5893783569],"type":"Point"}
}