{
  "type": "Feature",
  "properties": {
    "addr:full":"Eschb\u00fchel 28 Dornbirn Vorarlberg 6850",
    "addr:housenumber":"28",
    "addr:postcode":"6850",
    "addr:street":"Eschbuehel",
    "iso:country":"AT",
    "sg:address":"Eschb\u00fchel 28",
    "sg:city":"Dornbirn",
    "sg:classifiers":[
        {
            "category":"Professional",
            "subcategory":"Management & Consulting",
            "type":"Services"
        }
    ],
    "sg:phone":"+43 5572 29065",
    "sg:postcode":"6850",
    "sg:province":"Vorarlberg",
    "wof:name":"Wintersteiger Walter Dr",
    "wof:placetype":"venue"
},
  "geometry": {"coordinates":[9.7437801361,47.4131889343],"type":"Point"}
}