{
  "type": "Feature",
  "properties": {
    "iso:country":"AT",
    "sg:address":"Kirchst\u00e4ttstr 25",
    "sg:city":"Obertrum am See",
    "sg:orig_category":"Energietechnik",
    "sg:phone":"+43 4362 197240",
    "sg:postcode":"5162",
    "sg:province":"Salzburg",
    "wof:name":"Energie & Elektrotechnik P\u00f6tzelsberger Friedrich",
    "wof:placetype":"venue"
},
  "geometry": {"coordinates":[13.0706195831,47.9369812012],"type":"Point"}
}