{
  "type": "Feature",
  "properties": {
    "addr:full":"Hauptstr 4 Donnerskirchen Burgenland 7082",
    "addr:housenumber":"4",
    "addr:postcode":"7082",
    "addr:street":"Hauptstr",
    "iso:country":"AT",
    "sg:address":"Hauptstr 4",
    "sg:city":"Donnerskirchen",
    "sg:orig_category":"Apotheken",
    "sg:phone":"+43 2683 85420",
    "sg:postcode":"7082",
    "sg:province":"Burgenland",
    "wof:name":"Apotheke z Schutzengel Mag pharm Wolfgang Bencic",
    "wof:placetype":"venue"
},
  "geometry": {"coordinates":[16.6463336945,47.8944625854],"type":"Point"}
}