{
  "type": "Feature",
  "properties": {
    "addr:full":"Markt 1 Werfen Salzburg 5450",
    "addr:housenumber":"1",
    "addr:postcode":"5450",
    "addr:street":"Markt;Salzburg",
    "iso:country":"AT",
    "sg:address":"Markt 1",
    "sg:city":"Werfen",
    "sg:orig_category":"Transportunternehmen",
    "sg:phone":"+43 6468 5348",
    "sg:postcode":"5450",
    "sg:province":"Salzburg",
    "wof:name":"Gebr\u00fcder Rettenbacher Transporte GesmbH & Co KG",
    "wof:placetype":"venue"
},
  "geometry": {"coordinates":[13.1858072281,47.4797897339],"type":"Point"}
}