{
  "type": "Feature",
  "properties": {
    "addr:full":"Grimmingg 24a Liezen Steiermark 8940",
    "addr:housenumber":"24a",
    "addr:postcode":"8940",
    "addr:street":"Grimmingg",
    "iso:country":"AT",
    "sg:address":"Grimmingg 24a",
    "sg:city":"Liezen",
    "sg:orig_category":"Friseure U Frisiersalons",
    "sg:phone":"+43 4336 1222368",
    "sg:postcode":"8940",
    "sg:province":"Steiermark",
    "wof:name":"Stadtfriseur Uhl",
    "wof:placetype":"venue"
},
  "geometry": {"coordinates":[14.23645401,47.5680847168],"type":"Point"}
}