{
  "type": "Feature",
  "properties": {
    "iso:country":"AT",
    "sg:address":"Nr 39",
    "sg:city":"Kirchbichl",
    "sg:orig_category":"Transportunternehmen",
    "sg:phone":"+43 5332 56860",
    "sg:postcode":"6322",
    "sg:province":"Tirol",
    "wof:name":"GFG-G\u00fcterfracht GesmbH",
    "wof:placetype":"venue"
},
  "geometry": {"coordinates":[12.0880002975,47.5128707886],"type":"Point"}
}