{
  "type": "Feature",
  "properties": {
    "addr:full":"Harder Str 78 Lauterach Vorarlberg 6923",
    "addr:housenumber":"78",
    "addr:postcode":"6923",
    "addr:street":"Str",
    "iso:country":"AT",
    "sg:address":"Harder Str 78",
    "sg:city":"Lauterach",
    "sg:orig_category":"Fleischereimaschinen U -Einrichtungen",
    "sg:phone":"+43 4367 63033900",
    "sg:postcode":"6923",
    "sg:province":"Vorarlberg",
    "wof:name":"Klopfer Peter Handelsagentur Fa Vivotec",
    "wof:placetype":"venue"
},
  "geometry": {"coordinates":[9.7155561447,47.4843482971],"type":"Point"}
}