{
  "type": "Feature",
  "properties": {
    "addr:full":"Traunuferstr 117 Ansfelden Ober\u00f6sterreich 4052",
    "addr:housenumber":"117",
    "addr:postcode":"4052",
    "iso:country":"AT",
    "sg:address":"Traunuferstr 117",
    "sg:city":"Ansfelden",
    "sg:classifiers":[
        {
            "category":"Home & Garden",
            "subcategory":"Building Materials",
            "type":"Retail Goods"
        }
    ],
    "sg:phone":"+43 7229 78525",
    "sg:postcode":"4052",
    "sg:province":"Ober\u00f6sterreich",
    "sg:tags":[
        "baustoffe",
        "-material",
        "u"
    ],
    "wof:name":"Beinkofer GesmbH & Co KG",
    "wof:placetype":"venue"
},
  "geometry": {"coordinates":[14.2763233185,48.2121543884],"type":"Point"}
}