{
  "type": "Feature",
  "properties": {
    "addr:full":"Tabor 7 Bad Radkersburg Steiermark 8490",
    "addr:housenumber":"7",
    "addr:postcode":"8490",
    "addr:street":"Tabor",
    "iso:country":"AT",
    "sg:address":"Tabor 7",
    "sg:city":"Bad Radkersburg",
    "sg:orig_category":"Rauchfangkehrer",
    "sg:phone":"+43 4334 762890",
    "sg:postcode":"8490",
    "sg:province":"Steiermark",
    "wof:name":"Merlini Peter",
    "wof:placetype":"venue"
},
  "geometry": {"coordinates":[15.9879426956,46.6895828247],"type":"Point"}
}