{
  "type": "Feature",
  "properties": {
    "addr:full":"Gstan Au 35 Finkenberg Tirol 6292",
    "addr:housenumber":"35",
    "addr:postcode":"6292",
    "addr:street":"Gstan Au",
    "iso:country":"AT",
    "sg:address":"Gstan Au 35",
    "sg:city":"Finkenberg",
    "sg:orig_category":"Pensionen / Privatzimmer",
    "sg:phone":"+43 5285 62062",
    "sg:postcode":"6292",
    "sg:province":"Tirol",
    "wof:name":"Haus Alexandra",
    "wof:placetype":"venue"
},
  "geometry": {"coordinates":[11.8239097595,47.153465271],"type":"Point"}
}