{
  "type": "Feature",
  "properties": {
    "iso:country":"AT",
    "sg:address":"Nr 1",
    "sg:city":"Artstetten",
    "sg:orig_category":"Werbeagenturen",
    "sg:phone":"+43 7413 81611",
    "sg:postcode":"3661",
    "sg:province":"Nieder\u00f6sterreich",
    "wof:name":"WEB POiNT : media design Christian Kipperer",
    "wof:placetype":"venue"
},
  "geometry": {"coordinates":[15.2035694122,48.243057251],"type":"Point"}
}