{
  "type": "Feature",
  "properties": {
    "addr:full":"Burgg 5 Laa an der Thaya Nieder\u00f6sterreich 2136",
    "addr:housenumber":"5",
    "addr:postcode":"2136",
    "addr:street":"Burgg",
    "iso:country":"AT",
    "sg:address":"Burgg 5",
    "sg:city":"Laa an der Thaya",
    "sg:orig_category":"Leder",
    "sg:phone":"+43 4325 222397",
    "sg:postcode":"2136",
    "sg:province":"Nieder\u00f6sterreich",
    "wof:name":"Lederwerkst\u00e4tte - Inh E Birkenheuer",
    "wof:placetype":"venue"
},
  "geometry": {"coordinates":[16.3847236633,48.7252502441],"type":"Point"}
}