{
  "type": "Feature",
  "properties": {
    "addr:full":"Hauptpl 1 Hartberg Steiermark 8230",
    "addr:housenumber":"1",
    "addr:postcode":"8230",
    "addr:street":"Hauptpl",
    "iso:country":"AT",
    "sg:address":"Hauptpl 1",
    "sg:city":"Hartberg",
    "sg:orig_category":"Damenmoden",
    "sg:phone":"+43 4333 32626630",
    "sg:postcode":"8230",
    "sg:province":"Steiermark",
    "wof:name":"Stibor Damenmode",
    "wof:placetype":"venue"
},
  "geometry": {"coordinates":[15.969042778,47.2808189392],"type":"Point"}
}