{
  "type": "Feature",
  "properties": {
    "addr:full":"Enge G 16 Steyr Ober\u00f6sterreich 4400",
    "addr:housenumber":"16",
    "addr:postcode":"4400",
    "addr:street":"Enge G;Oberoesterreich",
    "iso:country":"AT",
    "sg:address":"Enge G 16",
    "sg:city":"Steyr",
    "sg:orig_category":"Bekleidung / Einzelhandel",
    "sg:phone":"+43 7252 54117",
    "sg:postcode":"4400",
    "sg:province":"Ober\u00f6sterreich",
    "wof:name":"Sch\u00f6ps Richard & Co AG",
    "wof:placetype":"venue"
},
  "geometry": {"coordinates":[14.4201889038,48.0410118103],"type":"Point"}
}