{
  "type": "Feature",
  "properties": {
    "addr:full":"Dr Hans Kloepfer-G 4 Stra\u00dfgang Steiermark 8054",
    "addr:housenumber":"4",
    "addr:postcode":"8054",
    "addr:street":"Dr;Kloepfer-G",
    "iso:country":"AT",
    "sg:address":"Dr Hans Kloepfer-G 4",
    "sg:city":"Stra\u00dfgang",
    "sg:orig_category":"Maler, Anstreicher U Lackierer",
    "sg:phone":"+43 316 271139",
    "sg:postcode":"8054",
    "sg:province":"Steiermark",
    "wof:name":"Lackner Stefan",
    "wof:placetype":"venue"
},
  "geometry": {"coordinates":[15.3875703812,46.9973869324],"type":"Point"}
}