{
  "type": "Feature",
  "properties": {
    "addr:full":"Kollerbergweg 33 Wetzelsdorf Steiermark 8052",
    "addr:housenumber":"33",
    "addr:postcode":"8052",
    "addr:street":"Kollerbergweg",
    "iso:country":"AT",
    "sg:address":"Kollerbergweg 33",
    "sg:city":"Wetzelsdorf",
    "sg:orig_category":"\u00c3\u201erzte / F Allgemeinmedizin",
    "sg:phone":"+43 316 5823560",
    "sg:postcode":"8052",
    "sg:province":"Steiermark",
    "wof:name":"Gollowitsch Petra Dr",
    "wof:placetype":"venue"
},
  "geometry": {"coordinates":[15.3833503723,47.0610198975],"type":"Point"}
}