{
  "type": "Feature",
  "properties": {
    "addr:full":"Altmannsdorfer Strasse 309-311 Wien Wien 1230",
    "addr:housenumber":"309-311",
    "addr:postcode":"1230",
    "addr:street":"Altmannsdorfer Strasse",
    "iso:country":"AT",
    "sg:address":"Altmannsdorfer Strasse 309-311",
    "sg:city":"Wien",
    "sg:classifiers":[
        {
            "category":"Professional",
            "subcategory":"Advertising",
            "type":"Services"
        }
    ],
    "sg:phone":"+43 1 66783130",
    "sg:postcode":"1230",
    "sg:province":"Wien",
    "sg:tags":[
        "marketing",
        "direct"
    ],
    "sg:website":"mpsdirect.at",
    "wof:name":"MPS Marketing & Produktion Service GmbH",
    "wof:placetype":"venue"
},
  "geometry": {"coordinates":[16.3240337372,48.1408996582],"type":"Point"}
}