{
  "type": "Feature",
  "properties": {
    "addr:full":"Trimmelkam 112 St. Pantaleon Ober\u00f6sterreich 5120",
    "addr:housenumber":"112",
    "addr:postcode":"5120",
    "addr:street":"Trimmelkam;Pantaleon Oberoesterreich",
    "iso:country":"AT",
    "sg:address":"Trimmelkam 112",
    "sg:city":"St. Pantaleon",
    "sg:classifiers":[
        {
            "category":"Home & Garden",
            "subcategory":"Building Materials",
            "type":"Retail Goods"
        }
    ],
    "sg:phone":"+43 6277 7892",
    "sg:postcode":"5120",
    "sg:province":"Ober\u00f6sterreich",
    "sg:tags":[
        "installation",
        "electric"
    ],
    "wof:name":"Botz Elektro GmbH",
    "wof:placetype":"venue"
},
  "geometry": {"coordinates":[12.8765659332,48.0256004333],"type":"Point"}
}