{
  "type": "Feature",
  "properties": {
    "addr:full":"Stadionstr 31 Judenburg Steiermark 8750",
    "addr:housenumber":"31",
    "addr:postcode":"8750",
    "addr:street":"Stadionstr",
    "iso:country":"AT",
    "sg:address":"Stadionstr 31",
    "sg:city":"Judenburg",
    "sg:orig_category":"Fliesen- U Plattenverlegungen",
    "sg:phone":"+43 4335 7242517",
    "sg:postcode":"8750",
    "sg:province":"Steiermark",
    "wof:name":"Rastovic KEG",
    "wof:placetype":"venue"
},
  "geometry": {"coordinates":[14.6794471741,47.1765670776],"type":"Point"}
}