{
  "type": "Feature",
  "properties": {
    "addr:full":"Bergstrasse 14 Sulz-R\u00f6this Vorarlberg 6832",
    "addr:housenumber":"14",
    "addr:postcode":"6832",
    "addr:street":"Bergstrasse",
    "iso:country":"AT",
    "sg:address":"Bergstrasse 14",
    "sg:city":"Sulz-R\u00f6this",
    "sg:classifiers":[
        {
            "category":"Manufacturing",
            "subcategory":"Electronics",
            "type":"Manufacturing & Wholesale Goods"
        }
    ],
    "sg:phone":"+43 5522 41826",
    "sg:postcode":"6832",
    "sg:province":"Vorarlberg",
    "sg:tags":[
        "amplifier"
    ],
    "sg:website":"elsner-electronic.com",
    "wof:name":"Peter Elsner Electronic Equipment",
    "wof:placetype":"venue"
},
  "geometry": {"coordinates":[9.6652698517,47.287361145],"type":"Point"}
}