{
  "type": "Feature",
  "properties": {
    "addr:full":"Hof 14 Brixen im Thale Tirol 6364",
    "addr:housenumber":"14",
    "addr:postcode":"6364",
    "addr:street":"Hof;Tirol",
    "iso:country":"AT",
    "sg:address":"Hof 14",
    "sg:city":"Brixen im Thale",
    "sg:orig_category":"Pensionen / Privatzimmer",
    "sg:phone":"+43 5334 6748",
    "sg:postcode":"6364",
    "sg:province":"Tirol",
    "wof:name":"Ferienhof Kloo",
    "wof:placetype":"venue"
},
  "geometry": {"coordinates":[12.2406949997,47.4479141235],"type":"Point"}
}