{
  "type": "Feature",
  "properties": {
    "addr:full":"Burgfrieden 7 Hall in Tirol Tirol 6060",
    "addr:housenumber":"7",
    "addr:postcode":"6060",
    "addr:street":"Burgfrieden;Tirol",
    "iso:country":"AT",
    "sg:address":"Burgfrieden 7",
    "sg:city":"Hall in Tirol",
    "sg:orig_category":"Tischlereien",
    "sg:phone":"+43 5223 44485",
    "sg:postcode":"6060",
    "sg:province":"Tirol",
    "wof:name":"Sillaber Ralf",
    "wof:placetype":"venue"
},
  "geometry": {"coordinates":[11.4858236313,47.2778511047],"type":"Point"}
}