{
  "type": "Feature",
  "properties": {
    "addr:full":"Breitenfurter Str 213 Wien Wien 1230",
    "addr:housenumber":"213",
    "addr:postcode":"1230",
    "addr:street":"Str",
    "iso:country":"AT",
    "sg:address":"Breitenfurter Str 213",
    "sg:city":"Wien",
    "sg:orig_category":"Autoreparatur",
    "sg:phone":"+43 1 8042142",
    "sg:postcode":"1230",
    "sg:province":"Wien",
    "wof:name":"Walter Karl",
    "wof:placetype":"venue"
},
  "geometry": {"coordinates":[16.3057746887,48.1572723389],"type":"Point"}
}