{
  "type": "Feature",
  "properties": {
    "addr:full":"Laverangasse 40 Wien Wien 1130",
    "addr:housenumber":"40",
    "addr:postcode":"1130",
    "addr:street":"Laverangasse",
    "iso:country":"AT",
    "sg:address":"Laverangasse 40",
    "sg:city":"Wien",
    "sg:classifiers":[
        {
            "category":"Professional",
            "subcategory":"Advertising",
            "type":"Services"
        }
    ],
    "sg:phone":"+43 1 80443120",
    "sg:postcode":"1130",
    "sg:province":"Wien",
    "sg:tags":[
        "marketing",
        "direct"
    ],
    "wof:name":"AUSPITZ & PARTNER KEG",
    "wof:placetype":"venue"
},
  "geometry": {"coordinates":[16.293390274,48.1655502319],"type":"Point"}
}