{
  "type": "Feature",
  "properties": {
    "addr:full":"Nr 41 Herzogenburg Nieder\u00f6sterreich 3130",
    "addr:postcode":"3130",
    "addr:street":"Nr 41",
    "iso:country":"AT",
    "sg:address":"Nr 41",
    "sg:city":"Herzogenburg",
    "sg:classifiers":[
        {
            "category":"Professional",
            "subcategory":"Computer Services",
            "type":"Services"
        }
    ],
    "sg:phone":"+43 2782 824430",
    "sg:postcode":"3130",
    "sg:province":"Nieder\u00f6sterreich",
    "sg:tags":[
        "software"
    ],
    "wof:name":"Emsenhuber Informatik",
    "wof:placetype":"venue"
},
  "geometry": {"coordinates":[15.6948232651,48.2849159241],"type":"Point"}
}