{
  "type": "Feature",
  "properties": {
    "addr:full":"Ehgartenweg 2 Hof Salzburg 5322",
    "addr:housenumber":"2",
    "addr:postcode":"5322",
    "addr:street":"Ehgartenweg;Salzburg",
    "iso:country":"AT",
    "sg:address":"Ehgartenweg 2",
    "sg:city":"Hof",
    "sg:orig_category":"Elektroinstallationsunternehmen",
    "sg:phone":"+43 6229 2966",
    "sg:postcode":"5322",
    "sg:province":"Salzburg",
    "wof:name":"Sch\u00f6ndorfer Franz",
    "wof:placetype":"venue"
},
  "geometry": {"coordinates":[13.1949329376,47.8195037842],"type":"Point"}
}