{
  "type": "Feature",
  "properties": {
    "addr:full":"Hietzinger Hauptstr 34 Wien Wien 1130",
    "addr:housenumber":"34",
    "addr:postcode":"1130",
    "addr:street":"Hietzinger Hauptstr",
    "iso:country":"AT",
    "sg:address":"Hietzinger Hauptstr 34",
    "sg:city":"Wien",
    "sg:orig_category":"Bauunternehmen",
    "sg:phone":"+43 1 8779441",
    "sg:postcode":"1130",
    "sg:province":"Wien",
    "wof:name":"Durst Hugo Dipl-Ing GmbH",
    "wof:placetype":"venue"
},
  "geometry": {"coordinates":[16.297498703,48.1867980957],"type":"Point"}
}