{
  "type": "Feature",
  "properties": {
    "iso:country":"AT",
    "sg:address":"Obere Dorfstr 3",
    "sg:city":"Fiss",
    "sg:orig_category":"Webdesign",
    "sg:phone":"+43 5476 6661",
    "sg:postcode":"6533",
    "sg:province":"Tirol",
    "wof:name":"PaleSoft",
    "wof:placetype":"venue"
},
  "geometry": {"coordinates":[10.6167602539,47.056438446],"type":"Point"}
}