{
  "type": "Feature",
  "properties": {
    "addr:full":"Platzg 4 Fiss Tirol 6533",
    "addr:housenumber":"4",
    "addr:postcode":"6533",
    "addr:street":"Platzg;Tirol",
    "iso:country":"AT",
    "sg:address":"Platzg 4",
    "sg:city":"Fiss",
    "sg:classifiers":[
        {
            "category":"Travel",
            "subcategory":"Hotels & Motels",
            "type":"Entertainment"
        }
    ],
    "sg:phone":"+43 4354 7664060",
    "sg:postcode":"6533",
    "sg:province":"Tirol",
    "wof:name":"Alt-Fiss Restaurant",
    "wof:placetype":"venue"
},
  "geometry": {"coordinates":[10.6214017868,47.05626297],"type":"Point"}
}