{
  "type": "Feature",
  "properties": {
    "iso:country":"AT",
    "sg:address":"Wiener Strasse 112",
    "sg:city":"Gars am Kamp",
    "sg:orig_category":"CarpenterS Work Supraregional",
    "sg:phone":"+43 2985 22350",
    "sg:postcode":"3571",
    "sg:province":"Nieder\u00f6sterreich",
    "wof:name":"Aschauer Zimmerei Ges.m.b.H.",
    "wof:placetype":"venue"
},
  "geometry": {"coordinates":[15.6438341141,48.6148757935],"type":"Point"}
}