{
  "type": "Feature",
  "properties": {
    "addr:full":"Am Spitz 2-3 Wien Wien 1210",
    "addr:housenumber":"2-3",
    "addr:postcode":"1210",
    "addr:street":"Am Spitz",
    "iso:country":"AT",
    "sg:address":"Am Spitz 2-3",
    "sg:city":"Wien",
    "sg:orig_category":"Weiterbildungsinstitute M Allg U Berufl Bildungsangebot",
    "sg:phone":"+43 1 2700634",
    "sg:postcode":"1210",
    "sg:province":"Wien",
    "wof:name":"Wifi Wien Wirtschaftsf\u00f6rderungsinstitut d Wirtschaftskammer Wien",
    "wof:placetype":"venue"
},
  "geometry": {"coordinates":[16.3976707458,48.2577209473],"type":"Point"}
}