{
  "type": "Feature",
  "properties": {
    "addr:full":"Hauptstr 1 Pernitz Nieder\u00f6sterreich 2763",
    "addr:housenumber":"1",
    "addr:postcode":"2763",
    "addr:street":"Hauptstr",
    "iso:country":"AT",
    "sg:address":"Hauptstr 1",
    "sg:city":"Pernitz",
    "sg:orig_category":"Holzbau",
    "sg:phone":"+43 2632 72331",
    "sg:postcode":"2763",
    "sg:province":"Nieder\u00f6sterreich",
    "wof:name":"Ruesch Johannes",
    "wof:placetype":"venue"
},
  "geometry": {"coordinates":[15.9560413361,47.8907661438],"type":"Point"}
}