{
  "type": "Feature",
  "properties": {
    "addr:full":"Seecorso 84 Velden am W\u00f6rther See K\u00e4rnten 9220",
    "addr:housenumber":"84",
    "addr:postcode":"9220",
    "addr:street":"Seecorso;Kaernten",
    "iso:country":"AT",
    "sg:address":"Seecorso 84",
    "sg:city":"Velden am W\u00f6rther See",
    "sg:orig_category":"Appartements / Ferienwohnungen",
    "sg:phone":"+43 4274 2080",
    "sg:postcode":"9220",
    "sg:province":"K\u00e4rnten",
    "wof:name":"Appartements Schwarzvilla",
    "wof:placetype":"venue"
},
  "geometry": {"coordinates":[14.0561056137,46.6099662781],"type":"Point"}
}