{
  "type": "Feature",
  "properties": {
    "addr:full":"Hietzinger Hauptstrasse 108 Wien Wien 1130",
    "addr:housenumber":"108",
    "addr:postcode":"1130",
    "addr:street":"Hietzinger Hauptstrasse",
    "iso:country":"AT",
    "sg:address":"Hietzinger Hauptstrasse 108",
    "sg:city":"Wien",
    "sg:classifiers":[
        {
            "category":"Home & Garden",
            "subcategory":"Carpets & Floor Coverings",
            "type":"Retail Goods"
        }
    ],
    "sg:phone":"+43 1 8779314",
    "sg:postcode":"1130",
    "sg:province":"Wien",
    "sg:tags":[
        "carpeting"
    ],
    "sg:website":"malerei-nimmerrichter.at",
    "wof:name":"Franz Nimmerrichter",
    "wof:placetype":"venue"
},
  "geometry": {"coordinates":[16.2785758972,48.1877708435],"type":"Point"}
}