{
  "type": "Feature",
  "properties": {
    "addr:full":"Bleierweg Kirchschlag in der Buckligen Welt Nieder\u00f6sterreich 2860",
    "addr:postcode":"2860",
    "addr:street":"Bleierweg",
    "iso:country":"AT",
    "sg:address":"Bleierweg",
    "sg:city":"Kirchschlag in der Buckligen Welt",
    "sg:orig_category":"Lebensmittel / Einzelhandel",
    "sg:phone":"+43 2646 2475",
    "sg:postcode":"2860",
    "sg:province":"Nieder\u00f6sterreich",
    "wof:name":"Billa AG",
    "wof:placetype":"venue"
},
  "geometry": {"coordinates":[16.287563324,47.4941253662],"type":"Point"}
}