{
  "type": "Feature",
  "properties": {
    "addr:full":"Geiselbergstr 17-19/3/5 Wien Wien 1110",
    "addr:housenumber":"17-19 / 3 / 5",
    "addr:postcode":"1110",
    "iso:country":"AT",
    "sg:address":"Geiselbergstr 17-19/3/5",
    "sg:city":"Wien",
    "sg:orig_category":"Auskunfteien",
    "sg:phone":"+43 4315 88610",
    "sg:postcode":"1110",
    "sg:province":"Wien",
    "sg:website":"dbaustria.com",
    "wof:name":"Dun & Bradstreet Information Services GmbH",
    "wof:placetype":"venue"
},
  "geometry": {"coordinates":[16.4197444916,48.1709709167],"type":"Point"}
}