{
  "type": "Feature",
  "properties": {
    "addr:full":"Gamlitzer Strasse 126 Ehrenhausen Steiermark 8461",
    "addr:housenumber":"126",
    "addr:postcode":"8461",
    "addr:street":"Gamlitzer Strasse",
    "iso:country":"AT",
    "sg:address":"Gamlitzer Strasse 126",
    "sg:city":"Ehrenhausen",
    "sg:orig_category":"Apparatus, Containers, Tanks, Vessels, And Boilers Of Stainless Steel",
    "sg:phone":"+43 3453 2265",
    "sg:postcode":"8461",
    "sg:province":"Steiermark",
    "sg:website":"muehlfellner.at",
    "wof:name":"M\u00fchlfellner Tankbauges.m.b.H.",
    "wof:placetype":"venue"
},
  "geometry": {"coordinates":[15.5851249695,46.7201652527],"type":"Point"}
}