{
  "type": "Feature",
  "properties": {
    "addr:full":"Kaiserebersdorferstr 256 Wien Wien 1110",
    "addr:housenumber":"256",
    "addr:postcode":"1110",
    "iso:country":"AT",
    "sg:address":"Kaiserebersdorferstr 256",
    "sg:city":"Wien",
    "sg:orig_category":"Beschriftungen",
    "sg:phone":"+43 4317 698518",
    "sg:postcode":"1110",
    "sg:province":"Wien",
    "wof:name":"Jungmann Schriften - Wiener Schilderhersteller",
    "wof:placetype":"venue"
},
  "geometry": {"coordinates":[16.459154129,48.1600494385],"type":"Point"}
}