{
  "type": "Feature",
  "properties": {
    "addr:full":"Torricelligasse 37 Wien Wien 1140",
    "addr:housenumber":"37",
    "addr:postcode":"1140",
    "addr:street":"Torricelligasse",
    "iso:country":"AT",
    "sg:address":"Torricelligasse 37",
    "sg:city":"Wien",
    "sg:orig_category":"Immobilien U Baugewerbe, Baugewerbe",
    "sg:phone":"+43 1 4165040",
    "sg:postcode":"1140",
    "sg:province":"Wien",
    "sg:website":"http://www.algo.at/khs",
    "wof:name":"Sperling GmbH",
    "wof:placetype":"venue"
},
  "geometry": {"coordinates":[16.2927188873,48.204498291],"type":"Point"}
}