{
  "type": "Feature",
  "properties": {
    "iso:country":"AT",
    "sg:address":"Alfred-Hiermann-Pl",
    "sg:city":"G\u00f6tzendorf an der Leitha",
    "sg:orig_category":"Musikgruppen",
    "sg:phone":"+43 4321 698389",
    "sg:postcode":"2434",
    "sg:province":"Nieder\u00f6sterreich",
    "wof:name":"Musikverein G\u00f6tzendorf",
    "wof:placetype":"venue"
},
  "geometry": {"coordinates":[-101.6332702637,46.3577537537],"type":"Point"}
}