{
  "type": "Feature",
  "properties": {
    "addr:full":"Auland 27 Reith Tirol 6103",
    "addr:housenumber":"27",
    "addr:postcode":"6103",
    "addr:street":"Auland",
    "iso:country":"AT",
    "sg:address":"Auland 27",
    "sg:city":"Reith",
    "sg:orig_category":"Installationsunternehmen",
    "sg:phone":"+43 5212 3189",
    "sg:postcode":"6103",
    "sg:province":"Tirol",
    "wof:name":"Riedle M Ing Installationen GmbH",
    "wof:placetype":"venue"
},
  "geometry": {"coordinates":[11.1990633011,47.3142662048],"type":"Point"}
}