{
  "type": "Feature",
  "properties": {
    "addr:full":"Prager Str 11 Horn Nieder\u00f6sterreich 3580",
    "addr:housenumber":"11",
    "addr:postcode":"3580",
    "addr:street":"Str",
    "iso:country":"AT",
    "sg:address":"Prager Str 11",
    "sg:city":"Horn",
    "sg:orig_category":"Politische Parteien",
    "sg:phone":"+43 2982 2407",
    "sg:postcode":"3580",
    "sg:province":"Nieder\u00f6sterreich",
    "wof:name":"\u00d6sterreichische Volkspartei (\u00d6VP)",
    "wof:placetype":"venue"
},
  "geometry": {"coordinates":[15.6550559998,48.6626167297],"type":"Point"}
}