{
  "type": "Feature",
  "properties": {
    "addr:full":"Passauer Str 5 M\u00fcnzkirchen Ober\u00f6sterreich 4792",
    "addr:housenumber":"5",
    "addr:postcode":"4792",
    "addr:street":"Str;Oberoesterreich",
    "iso:country":"AT",
    "sg:address":"Passauer Str 5",
    "sg:city":"M\u00fcnzkirchen",
    "sg:orig_category":"Glasereien",
    "sg:phone":"+43 7716 6498",
    "sg:postcode":"4792",
    "sg:province":"Ober\u00f6sterreich",
    "wof:name":"Glas Bauer",
    "wof:placetype":"venue"
},
  "geometry": {"coordinates":[13.5540037155,48.4814529419],"type":"Point"}
}