{
  "type": "Feature",
  "properties": {
    "iso:country":"AT",
    "sg:address":"Mansauraweg 3",
    "sg:city":"Vandans",
    "sg:orig_category":"Pensionen / Privatzimmer",
    "sg:phone":"+43 5556 75421",
    "sg:postcode":"6773",
    "sg:province":"Vorarlberg",
    "wof:name":"Haus Gra\u00df",
    "wof:placetype":"venue"
},
  "geometry": {"coordinates":[9.8616828918,47.0930404663],"type":"Point"}
}