{
  "type": "Feature",
  "properties": {
    "addr:full":"Mariazeller Str 106 Traisen Nieder\u00f6sterreich 3160",
    "addr:housenumber":"106",
    "addr:postcode":"3160",
    "addr:street":"Str",
    "iso:country":"AT",
    "sg:address":"Mariazeller Str 106",
    "sg:city":"Traisen",
    "sg:orig_category":"Webdesign",
    "sg:phone":"+43 4365 08508751",
    "sg:postcode":"3160",
    "sg:province":"Nieder\u00f6sterreich",
    "wof:name":"Creativ-Webdesign Norbert Schuster",
    "wof:placetype":"venue"
},
  "geometry": {"coordinates":[15.6081314087,48.0376319885],"type":"Point"}
}