{
  "type": "Feature",
  "properties": {
    "addr:full":"Alte Landstr 45 Frastanz Vorarlberg 6820",
    "addr:housenumber":"45",
    "addr:postcode":"6820",
    "addr:street":"Alte Landstr",
    "iso:country":"AT",
    "sg:address":"Alte Landstr 45",
    "sg:city":"Frastanz",
    "sg:orig_category":"Installationsunternehmen",
    "sg:phone":"+43 5522 518610",
    "sg:postcode":"6820",
    "sg:province":"Vorarlberg",
    "wof:name":"Keckeis Armin Installations GmbH",
    "wof:placetype":"venue"
},
  "geometry": {"coordinates":[9.6244659424,47.2234611511],"type":"Point"}
}