{
  "type": "Feature",
  "properties": {
    "iso:country":"AT",
    "sg:address":"Entalweg 706",
    "sg:city":"Kaprun",
    "sg:classifiers":[
        {
            "category":"Manufacturing",
            "subcategory":"Glass & Minerals",
            "type":"Manufacturing & Wholesale Goods"
        }
    ],
    "sg:phone":"+43 6547 8720",
    "sg:postcode":"5710",
    "sg:province":"Salzburg",
    "sg:tags":[
        "industrial",
        "working"
    ],
    "wof:name":"Josef Hartl GmbH & Co KG",
    "wof:placetype":"venue"
},
  "geometry": {"coordinates":[12.7435646057,47.262966156],"type":"Point"}
}