{
  "type": "Feature",
  "properties": {
    "addr:full":"Rathausg 5 Weiz Steiermark 8160",
    "addr:housenumber":"5",
    "addr:postcode":"8160",
    "addr:street":"Rathausg",
    "iso:country":"AT",
    "sg:address":"Rathausg 5",
    "sg:city":"Weiz",
    "sg:orig_category":"Apotheken",
    "sg:phone":"+43 3172 2287",
    "sg:postcode":"8160",
    "sg:province":"Steiermark",
    "wof:name":"APOTHEKE zur MARIAHILF Mag pharm H Krenn KG",
    "wof:placetype":"venue"
},
  "geometry": {"coordinates":[15.6215696335,47.2169532776],"type":"Point"}
}