{
  "type": "Feature",
  "properties": {
    "addr:full":"Huban 139 Doren Vorarlberg 6933",
    "addr:housenumber":"139",
    "addr:postcode":"6933",
    "addr:street":"Huban",
    "iso:country":"AT",
    "sg:address":"Huban 139",
    "sg:city":"Doren",
    "sg:orig_category":"Genossenschaften",
    "sg:phone":"+43 5516 2001",
    "sg:postcode":"6933",
    "sg:province":"Vorarlberg",
    "wof:name":"Sennereigenossenschaft Huban regGenmbH",
    "wof:placetype":"venue"
},
  "geometry": {"coordinates":[9.8966245651,47.4967956543],"type":"Point"}
}