{
  "type": "Feature",
  "properties": {
    "iso:country":"AT",
    "sg:address":"Stockerauer Str 19",
    "sg:city":"Korneuburg",
    "sg:orig_category":"Fahrschulen",
    "sg:phone":"+43 4322 6272866",
    "sg:postcode":"2100",
    "sg:province":"Nieder\u00f6sterreich",
    "sg:website":"fahrschule-zimmerer.at",
    "wof:name":"Fahrschule ZIMMERER Stockerau Au\u00dfenkurse",
    "wof:placetype":"venue"
},
  "geometry": {"coordinates":[16.33152771,48.3447151184],"type":"Point"}
}