{
  "type": "Feature",
  "properties": {
    "addr:full":"Schwarzenhaidestr 103 Wien Wien 1230",
    "addr:housenumber":"103",
    "addr:postcode":"1230",
    "iso:country":"AT",
    "sg:address":"Schwarzenhaidestr 103",
    "sg:city":"Wien",
    "sg:orig_category":"Rohrsanierungen",
    "sg:phone":"+43 4369 924321191",
    "sg:postcode":"1230",
    "sg:province":"Wien",
    "wof:name":"DDS Rohrtechnik",
    "wof:placetype":"venue"
},
  "geometry": {"coordinates":[16.3241386414,48.1448707581],"type":"Point"}
}