{
  "type": "Feature",
  "properties": {
    "addr:full":"Thomas-Alva-Edison-Strasse 2 Eisenstadt Burgenland 7000",
    "addr:housenumber":"2",
    "addr:postcode":"7000",
    "addr:street":"Thomas-Alva-Edison-Strasse",
    "iso:country":"AT",
    "sg:address":"Thomas-Alva-Edison-Strasse 2",
    "sg:city":"Eisenstadt",
    "sg:classifiers":[
        {
            "category":"Utilities",
            "subcategory":"Cable",
            "type":"Services"
        }
    ],
    "sg:phone":"+43 2682 7048140",
    "sg:postcode":"7000",
    "sg:province":"Burgenland",
    "sg:tags":[
        "integrated",
        "solution",
        "software"
    ],
    "sg:website":"icodex.com",
    "wof:name":"ICODEX Software AG",
    "wof:placetype":"venue"
},
  "geometry": {"coordinates":[16.532875061,47.8289451599],"type":"Point"}
}