{
  "type": "Feature",
  "properties": {
    "addr:full":"Ortweinpl 10 Graz Steiermark 8010",
    "addr:housenumber":"10",
    "addr:postcode":"8010",
    "addr:street":"Ortweinpl",
    "iso:country":"AT",
    "sg:address":"Ortweinpl 10",
    "sg:city":"Graz",
    "sg:orig_category":"Architekten",
    "sg:phone":"+43 316 814294",
    "sg:postcode":"8010",
    "sg:province":"Steiermark",
    "wof:name":"Alchitekten Atelier",
    "wof:placetype":"venue"
},
  "geometry": {"coordinates":[15.4444847107,47.0636825562],"type":"Point"}
}