{
  "type": "Feature",
  "properties": {
    "addr:full":"Franzbergstr 35 Poysbrunn Nieder\u00f6sterreich 2161",
    "addr:housenumber":"35",
    "addr:postcode":"2161",
    "addr:street":"Franzbergstr;Niederoesterreich",
    "iso:country":"AT",
    "sg:address":"Franzbergstr 35",
    "sg:city":"Poysbrunn",
    "sg:orig_category":"Lebensmittel / Einzelhandel",
    "sg:phone":"+43 2554 85657",
    "sg:postcode":"2161",
    "sg:province":"Nieder\u00f6sterreich",
    "wof:name":"Wolf Waltraud",
    "wof:placetype":"venue"
},
  "geometry": {"coordinates":[16.6254558563,48.7178382874],"type":"Point"}
}