{
  "type": "Feature",
  "properties": {
    "addr:full":"Mitterndorf 1 Traunkirchen Ober\u00f6sterreich 4801",
    "addr:housenumber":"1",
    "addr:postcode":"4801",
    "addr:street":"Mitterndorf",
    "iso:country":"AT",
    "sg:address":"Mitterndorf 1",
    "sg:city":"Traunkirchen",
    "sg:orig_category":"\u00c3\u201erzte / F Allgemeinmedizin",
    "sg:phone":"+43 76173323",
    "sg:postcode":"4801",
    "sg:province":"Ober\u00f6sterreich",
    "wof:name":"Junk G\u00fcnther Dr",
    "wof:placetype":"venue"
},
  "geometry": {"coordinates":[13.7784748077,47.8529586792],"type":"Point"}
}