{
  "type": "Feature",
  "properties": {
    "addr:full":"Grazer Str 16 Leibnitz Steiermark 8430",
    "addr:postcode":"8430",
    "addr:street":"Str 16;Steiermark",
    "iso:country":"AT",
    "sg:address":"Grazer Str 16",
    "sg:city":"Leibnitz",
    "sg:orig_category":"Transportunternehmen",
    "sg:phone":"+43 3452 71233",
    "sg:postcode":"8430",
    "sg:province":"Steiermark",
    "wof:name":"Prietl G\u00fcnther",
    "wof:placetype":"venue"
},
  "geometry": {"coordinates":[15.5444097519,46.8062553406],"type":"Point"}
}