{
  "type": "Feature",
  "properties": {
    "addr:full":"Grafenweg 1 Lustenau Vorarlberg 6890",
    "addr:housenumber":"1",
    "addr:postcode":"6890",
    "addr:street":"Grafenweg",
    "iso:country":"AT",
    "sg:address":"Grafenweg 1",
    "sg:city":"Lustenau",
    "sg:orig_category":"Chemisch-Technische Produkte",
    "sg:phone":"+43 5577 87301",
    "sg:postcode":"6890",
    "sg:province":"Vorarlberg",
    "wof:name":"Hagen Helmut OEG",
    "wof:placetype":"venue"
},
  "geometry": {"coordinates":[9.660033226,47.4415397644],"type":"Point"}
}