{
  "type": "Feature",
  "properties": {
    "addr:full":"Gm\u00fcnder Str 28 Schrems Nieder\u00f6sterreich 3943",
    "addr:postcode":"3943",
    "addr:street":"Str;Schrems",
    "iso:country":"AT",
    "sg:address":"Gm\u00fcnder Str 28",
    "sg:city":"Schrems",
    "sg:orig_category":"Tankstellen",
    "sg:phone":"+43 2853 773170",
    "sg:postcode":"3943",
    "sg:province":"Nieder\u00f6sterreich",
    "wof:name":"BP Austria Marketing GmbH",
    "wof:placetype":"venue"
},
  "geometry": {"coordinates":[15.0714254379,48.7929534912],"type":"Point"}
}