{
  "type": "Feature",
  "properties": {
    "addr:full":"Zeller Str 26 Mittersill Salzburg 5730",
    "addr:housenumber":"26",
    "addr:postcode":"5730",
    "addr:street":"Zeller Str;Salzburg",
    "iso:country":"AT",
    "sg:address":"Zeller Str 26",
    "sg:city":"Mittersill",
    "sg:orig_category":"Tankstellen",
    "sg:phone":"+43 6562 5819",
    "sg:postcode":"5730",
    "sg:province":"Salzburg",
    "wof:name":"AVANTI TankstellenbetriebsgesmbH",
    "wof:placetype":"venue"
},
  "geometry": {"coordinates":[12.4922151566,47.2852478027],"type":"Point"}
}