{
  "type": "Feature",
  "properties": {
    "addr:full":"Fillgraderg 16 Wien Wien 1060",
    "addr:housenumber":"16",
    "addr:postcode":"1060",
    "addr:street":"Fillgraderg",
    "iso:country":"AT",
    "sg:address":"Fillgraderg 16",
    "sg:city":"Wien",
    "sg:orig_category":"Architekten",
    "sg:phone":"+43 1 5814936",
    "sg:postcode":"1060",
    "sg:province":"Wien",
    "wof:name":"Krismer Werner Mag",
    "wof:placetype":"venue"
},
  "geometry": {"coordinates":[16.3580932617,48.1997680664],"type":"Point"}
}