{
  "type": "Feature",
  "properties": {
    "iso:country":"AT",
    "sg:address":"Nr 68",
    "sg:city":"Sch\u00f6der",
    "sg:orig_category":"Transportunternehmen",
    "sg:phone":"+43 4335 368442",
    "sg:postcode":"8844",
    "sg:province":"Steiermark",
    "wof:name":"Dengg Arnold",
    "wof:placetype":"venue"
},
  "geometry": {"coordinates":[166.9221496582,-0.5282999873],"type":"Point"}
}