{
  "type": "Feature",
  "properties": {
    "addr:full":"Sportallee 1 Neuhofen an der Krems Ober\u00f6sterreich 4501",
    "addr:housenumber":"1",
    "addr:postcode":"4501",
    "addr:street":"Sportallee",
    "iso:country":"AT",
    "sg:address":"Sportallee 1",
    "sg:city":"Neuhofen an der Krems",
    "sg:orig_category":"Architekten",
    "sg:phone":"+43 4372 277000",
    "sg:postcode":"4501",
    "sg:province":"Ober\u00f6sterreich",
    "wof:name":"Architekturb\u00fcro Stefan K\u00f6glberger ZT GmbH",
    "wof:placetype":"venue"
},
  "geometry": {"coordinates":[14.2312583923,48.138217926],"type":"Point"}
}