{
  "type": "Feature",
  "properties": {
    "addr:full":"H\u00fctteldorfer Str 103 Wien Wien 1150",
    "addr:housenumber":"103",
    "addr:postcode":"1150",
    "addr:street":"Str",
    "iso:country":"AT",
    "sg:address":"H\u00fctteldorfer Str 103",
    "sg:city":"Wien",
    "sg:orig_category":"Fotografen",
    "sg:phone":"+43 1 7862626",
    "sg:postcode":"1150",
    "sg:province":"Wien",
    "wof:name":"Garbelotto Foto",
    "wof:placetype":"venue"
},
  "geometry": {"coordinates":[16.3320903778,48.2006416321],"type":"Point"}
}