{
  "type": "Feature",
  "properties": {
    "addr:full":"Nr 168 Aschau Tirol 6274",
    "addr:postcode":"6274",
    "addr:street":"Nr;Aschau Tirol",
    "iso:country":"AT",
    "sg:address":"Nr 168",
    "sg:city":"Aschau",
    "sg:orig_category":"Appartements / Ferienwohnungen",
    "sg:phone":"+43 4352 824929",
    "sg:postcode":"6274",
    "sg:province":"Tirol",
    "wof:name":"Ferienwohnungen Wildauer",
    "wof:placetype":"venue"
},
  "geometry": {"coordinates":[11.8959445953,47.2627754211],"type":"Point"}
}