{
  "type": "Feature",
  "properties": {
    "iso:country":"AT",
    "sg:address":"Magdalensbergsdlg 188",
    "sg:city":"Lavam\u00fcnd",
    "sg:orig_category":"Tischlereien",
    "sg:phone":"+43 664 2347371",
    "sg:postcode":"9473",
    "sg:province":"K\u00e4rnten",
    "wof:name":"Pajnik Simon",
    "wof:placetype":"venue"
},
  "geometry": {"coordinates":[9.4356002808,47.2144508362],"type":"Point"}
}