{
  "type": "Feature",
  "properties": {
    "addr:full":"Rettenbachweg 1 Bad Ischl Ober\u00f6sterreich 4820",
    "addr:housenumber":"1",
    "addr:postcode":"4820",
    "addr:street":"Rettenbachweg",
    "iso:country":"AT",
    "sg:address":"Rettenbachweg 1",
    "sg:city":"Bad Ischl",
    "sg:orig_category":"Restaurants: Chinesisch",
    "sg:phone":"+43 6132 28063",
    "sg:postcode":"4820",
    "sg:province":"Ober\u00f6sterreich",
    "wof:name":"Asiatisches Spezialit\u00e4tenrestaurant Umeko",
    "wof:placetype":"venue"
},
  "geometry": {"coordinates":[13.6285858154,47.7147979736],"type":"Point"}
}