{
  "type": "Feature",
  "properties": {
    "iso:country":"AT",
    "sg:address":"Laboratoriumstr 46",
    "sg:city":"Neuhart",
    "sg:orig_category":"Fleischhauereien",
    "sg:phone":"+43 316 278932",
    "sg:postcode":"8053",
    "sg:province":"Steiermark",
    "wof:name":"Schlintl Karl",
    "wof:placetype":"venue"
},
  "geometry": {"coordinates":[15.4071426392,47.0520935059],"type":"Point"}
}