{
  "type": "Feature",
  "properties": {
    "addr:full":"Hauptstr 16 Ebensee Ober\u00f6sterreich 4802",
    "addr:housenumber":"16",
    "addr:postcode":"4802",
    "addr:street":"Hauptstr",
    "iso:country":"AT",
    "sg:address":"Hauptstr 16",
    "sg:city":"Ebensee",
    "sg:orig_category":"Damenmoden",
    "sg:phone":"+43 6133 4454",
    "sg:postcode":"4802",
    "sg:province":"Ober\u00f6sterreich",
    "wof:name":"L2 Mode",
    "wof:placetype":"venue"
},
  "geometry": {"coordinates":[13.7718019485,47.8111877441],"type":"Point"}
}