{
  "type": "Feature",
  "properties": {
    "addr:full":"Winterzeile 7 Bad Pirawarth Nieder\u00f6sterreich 2222",
    "addr:housenumber":"7",
    "addr:postcode":"2222",
    "addr:street":"Winterzeile;Niederoesterreich",
    "iso:country":"AT",
    "sg:address":"Winterzeile 7",
    "sg:city":"Bad Pirawarth",
    "sg:orig_category":"Landwirtschaftliche Produkte",
    "sg:phone":"+43 2574 2105",
    "sg:postcode":"2222",
    "sg:province":"Nieder\u00f6sterreich",
    "wof:name":"Kaufmann Josef",
    "wof:placetype":"venue"
},
  "geometry": {"coordinates":[16.5898761749,48.4616088867],"type":"Point"}
}