{
  "type": "Feature",
  "properties": {
    "iso:country":"AT",
    "sg:address":"Nr 80",
    "sg:city":"Vorau",
    "sg:orig_category":"Unterhaltungselektronik / Einzelhandel",
    "sg:phone":"+43 3337 41110",
    "sg:postcode":"8250",
    "sg:province":"Steiermark",
    "wof:name":"Kriegsauer Josef GesmbH",
    "wof:placetype":"venue"
},
  "geometry": {"coordinates":[15.8873929977,47.4056854248],"type":"Point"}
}