{
  "type": "Feature",
  "properties": {
    "addr:full":"Dr.-Arthur-Lemisch-Str 5 St. Veit an der Glan K\u00e4rnten 9300",
    "addr:housenumber":"5",
    "addr:postcode":"9300",
    "addr:street":"Dr.-Arthur-Lemisch-Str;Kaernten",
    "iso:country":"AT",
    "sg:address":"Dr.-Arthur-Lemisch-Str 5",
    "sg:city":"St. Veit an der Glan",
    "sg:orig_category":"Weiterbildungsinstitute M Allg U Berufl Bildungsangebot",
    "sg:phone":"+43 4367 67093909",
    "sg:postcode":"9300",
    "sg:province":"K\u00e4rnten",
    "wof:name":"Bildungszentrum St Veit a d Glan",
    "wof:placetype":"venue"
},
  "geometry": {"coordinates":[14.3605365753,46.7704925537],"type":"Point"}
}