{
  "type": "Feature",
  "properties": {
    "addr:full":"Unterdorf 1 Reutte Tirol 6600",
    "addr:housenumber":"1",
    "addr:postcode":"6600",
    "addr:street":"Unterdorf;Tirol",
    "iso:country":"AT",
    "sg:address":"Unterdorf 1",
    "sg:city":"Reutte",
    "sg:orig_category":"Speditionen",
    "sg:phone":"+43 5672 62746",
    "sg:postcode":"6600",
    "sg:province":"Tirol",
    "wof:name":"KK+M Koler, Kuhn & Merk SpeditionsgmbH",
    "wof:placetype":"venue"
},
  "geometry": {"coordinates":[10.7058334351,47.4972267151],"type":"Point"}
}