{
  "type": "Feature",
  "properties": {
    "addr:full":"Bahnhofstr 19 Enns Ober\u00f6sterreich 4470",
    "addr:postcode":"4470",
    "addr:street":"Bahnhofstr 19",
    "iso:country":"AT",
    "sg:address":"Bahnhofstr 19",
    "sg:city":"Enns",
    "sg:orig_category":"Erdarbeiten",
    "sg:phone":"+43 4372 2384364",
    "sg:postcode":"4470",
    "sg:province":"Ober\u00f6sterreich",
    "wof:name":"Haiss Gerhard",
    "wof:placetype":"venue"
},
  "geometry": {"coordinates":[14.4675827026,48.2200317383],"type":"Point"}
}