{
  "type": "Feature",
  "properties": {
    "addr:full":"Liechtensteinstr 12 Hohenau an der March Nieder\u00f6sterreich 2273",
    "addr:housenumber":"12",
    "addr:postcode":"2273",
    "addr:street":"Liechtensteinstr",
    "iso:country":"AT",
    "sg:address":"Liechtensteinstr 12",
    "sg:city":"Hohenau an der March",
    "sg:orig_category":"Lebensmittel / Einzelhandel",
    "sg:phone":"+43 2535 2275",
    "sg:postcode":"2273",
    "sg:province":"Nieder\u00f6sterreich",
    "wof:name":"MONDO Lebensmitteldiskonter",
    "wof:placetype":"venue"
},
  "geometry": {"coordinates":[16.9079875946,48.6064949036],"type":"Point"}
}