{
  "type": "Feature",
  "properties": {
    "addr:full":"Linzer Str 51 Freistadt Ober\u00f6sterreich 4240",
    "addr:housenumber":"51",
    "addr:postcode":"4240",
    "addr:street":"Linzer Str",
    "iso:country":"AT",
    "sg:address":"Linzer Str 51",
    "sg:city":"Freistadt",
    "sg:orig_category":"Lebensmittel / Einzelhandel",
    "sg:phone":"+43 7942 74580",
    "sg:postcode":"4240",
    "sg:province":"Ober\u00f6sterreich",
    "wof:name":"Billa AG",
    "wof:placetype":"venue"
},
  "geometry": {"coordinates":[14.5030870438,48.4995498657],"type":"Point"}
}