{
  "type": "Feature",
  "properties": {
    "addr:full":"Puchweg 3 Voitsberg Steiermark 8570",
    "addr:housenumber":"3",
    "addr:postcode":"8570",
    "addr:street":"Puchweg",
    "iso:country":"AT",
    "sg:address":"Puchweg 3",
    "sg:city":"Voitsberg",
    "sg:orig_category":"Installationsunternehmen",
    "sg:phone":"+43 3142 22388",
    "sg:postcode":"8570",
    "sg:province":"Steiermark",
    "wof:name":"Wurzinger Karl",
    "wof:placetype":"venue"
},
  "geometry": {"coordinates":[15.1462364197,47.0429000854],"type":"Point"}
}