{
  "type": "Feature",
  "properties": {
    "iso:country":"AT",
    "sg:address":"Innsbruck Bundesstr 71",
    "sg:city":"Salzburg",
    "sg:orig_category":"Immobilienmakler",
    "sg:phone":"+43 662 432559",
    "sg:postcode":"5020",
    "sg:province":"Salzburg",
    "wof:name":"Team 4 Immobilien GmbH",
    "wof:placetype":"venue"
},
  "geometry": {"coordinates":[13.0133476257,47.8005867004],"type":"Point"}
}