{
  "type": "Feature",
  "properties": {
    "iso:country":"AT",
    "sg:address":"Dr.-Theodor-K\u00f6rner-Str 13",
    "sg:city":"Trumau",
    "sg:orig_category":"Garten- U Landschaftsgestaltung",
    "sg:phone":"+43 4369 912562528",
    "sg:postcode":"2521",
    "sg:province":"Nieder\u00f6sterreich",
    "wof:name":"Binder Eduard",
    "wof:placetype":"venue"
},
  "geometry": {"coordinates":[16.3431034088,47.9942359924],"type":"Point"}
}