{
  "type": "Feature",
  "properties": {
    "addr:full":"Nr 119 Asparn an der Zaya Nieder\u00f6sterreich 2151",
    "addr:postcode":"2151",
    "addr:street":"Nr 119",
    "iso:country":"AT",
    "sg:address":"Nr 119",
    "sg:city":"Asparn an der Zaya",
    "sg:orig_category":"Maler, Anstreicher U Lackierer",
    "sg:phone":"+43 4366 43762703",
    "sg:postcode":"2151",
    "sg:province":"Nieder\u00f6sterreich",
    "wof:name":"K\u00f6rbel Manfred",
    "wof:placetype":"venue"
},
  "geometry": {"coordinates":[16.4961643219,48.5871963501],"type":"Point"}
}