{
  "type": "Feature",
  "properties": {
    "addr:full":"Dorfstr 16 Westendorf Tirol 6363",
    "addr:housenumber":"16",
    "addr:postcode":"6363",
    "addr:street":"Dorfstr;Tirol",
    "iso:country":"AT",
    "sg:address":"Dorfstr 16",
    "sg:city":"Westendorf",
    "sg:orig_category":"Freizeit- U Sportbekleidung",
    "sg:phone":"+43 4353 346511",
    "sg:postcode":"6363",
    "sg:province":"Tirol",
    "wof:name":"Dieter's Sport Shop GesmbH",
    "wof:placetype":"venue"
},
  "geometry": {"coordinates":[12.2132339478,47.4310073853],"type":"Point"}
}