{
  "type": "Feature",
  "properties": {
    "addr:full":"Inprugg 37 Neulengbach Nieder\u00f6sterreich 3040",
    "addr:housenumber":"37",
    "addr:postcode":"3040",
    "addr:street":"Inprugg",
    "iso:country":"AT",
    "sg:address":"Inprugg 37",
    "sg:city":"Neulengbach",
    "sg:orig_category":"Autohandel",
    "sg:phone":"+43 2772 52169",
    "sg:postcode":"3040",
    "sg:province":"Nieder\u00f6sterreich",
    "wof:name":"J\u00e4ger Heinrich",
    "wof:placetype":"venue"
},
  "geometry": {"coordinates":[15.9116754532,48.2122955322],"type":"Point"}
}