{
  "type": "Feature",
  "properties": {
    "addr:full":"Gm\u00fcnder Str 185 Hoheneich Nieder\u00f6sterreich 3945",
    "addr:housenumber":"185",
    "addr:postcode":"3945",
    "addr:street":"Str",
    "iso:country":"AT",
    "sg:address":"Gm\u00fcnder Str 185",
    "sg:city":"Hoheneich",
    "sg:orig_category":"Psychologen",
    "sg:phone":"+43 2852 52278",
    "sg:postcode":"3945",
    "sg:province":"Nieder\u00f6sterreich",
    "wof:name":"Weissensteiner Herbert Dr",
    "wof:placetype":"venue"
},
  "geometry": {"coordinates":[15.0258569717,48.7716026306],"type":"Point"}
}