{
  "type": "Feature",
  "properties": {
    "addr:full":"G\u00e4llegasse 11a Gnigl Salzburg 5023",
    "addr:housenumber":"11a",
    "addr:postcode":"5023",
    "addr:street":"Gaellegasse",
    "iso:country":"AT",
    "sg:address":"G\u00e4llegasse 11a",
    "sg:city":"Gnigl",
    "sg:orig_category":"Loden",
    "sg:phone":"+43 662 6602830",
    "sg:postcode":"5023",
    "sg:province":"Salzburg",
    "sg:website":"moser-bekleidung.at",
    "wof:name":"H. Moser Bekleidung Ges.m.b.H.",
    "wof:placetype":"venue"
},
  "geometry": {"coordinates":[13.06985569,47.8202171326],"type":"Point"}
}