{
  "type": "Feature",
  "properties": {
    "addr:full":"Nr 84 Ro\u00dfleithen Ober\u00f6sterreich 4575",
    "addr:postcode":"4575",
    "addr:street":"Nr 84",
    "iso:country":"AT",
    "sg:address":"Nr 84",
    "sg:city":"Ro\u00dfleithen",
    "sg:orig_category":"Baumeister",
    "sg:phone":"+43 7562 8005",
    "sg:postcode":"4575",
    "sg:province":"Ober\u00f6sterreich",
    "wof:name":"M\u00f6sslberger Georg Ing",
    "wof:placetype":"venue"
},
  "geometry": {"coordinates":[166.9221496582,-0.5282999873],"type":"Point"}
}