{
  "type": "Feature",
  "properties": {
    "iso:country":"AT",
    "sg:address":"Wilhelminenstr. 28-30",
    "sg:city":"Wien",
    "sg:classifiers":[
        {
            "category":"Shopping",
            "type":"Retail Goods"
        }
    ],
    "sg:phone":"+43 4314 8123790",
    "sg:postcode":"1160",
    "sg:province":"Wien",
    "sg:tags":[
        "finished",
        "-",
        "metallic"
    ],
    "wof:name":"GEORG SENFT GES.MBH",
    "wof:placetype":"venue"
},
  "geometry": {"coordinates":[16.3174324036,48.2164535522],"type":"Point"}
}