{
  "type": "Feature",
  "properties": {
    "addr:full":"Helenenstr 22 Baden Nieder\u00f6sterreich 2500",
    "addr:housenumber":"22",
    "addr:postcode":"2500",
    "addr:street":"Helenenstr;Niederoesterreich",
    "iso:country":"AT",
    "sg:address":"Helenenstr 22",
    "sg:city":"Baden",
    "sg:orig_category":"Psychotherapie",
    "sg:phone":"+43 2252 81877",
    "sg:postcode":"2500",
    "sg:province":"Nieder\u00f6sterreich",
    "wof:name":"Fiala Viktor Mag Dr",
    "wof:placetype":"venue"
},
  "geometry": {"coordinates":[16.220790863,48.0061721802],"type":"Point"}
}