{
  "type": "Feature",
  "properties": {
    "iso:country":"AT",
    "sg:address":"Aichholzgasse 14 ",
    "sg:city":"Wien",
    "sg:classifiers":[
        {
            "category":"Building & Trades",
            "subcategory":"Plumbing",
            "type":"Services"
        }
    ],
    "sg:phone":"+43 1 8136569",
    "sg:postcode":"1120",
    "sg:province":"Wien",
    "sg:tags":[
        "supraregional",
        "gas"
    ],
    "wof:name":"Josef Kozak",
    "wof:placetype":"venue"
},
  "geometry": {"coordinates":[16.3242874146,48.1813201904],"type":"Point"}
}