{
  "type": "Feature",
  "properties": {
    "iso:country":"AT",
    "sg:address":"Schallmooser Hptstr 13",
    "sg:city":"Salzburg",
    "sg:classifiers":[
        {
            "category":"Travel",
            "subcategory":"Hotels & Motels",
            "type":"Entertainment"
        }
    ],
    "sg:phone":"+43 662 8816810",
    "sg:postcode":"5020",
    "sg:province":"Salzburg",
    "wof:name":"Cordial Theater Hotel Salzburg",
    "wof:placetype":"venue"
},
  "geometry": {"coordinates":[13.0516862869,47.805606842],"type":"Point"}
}