{
  "type": "Feature",
  "properties": {
    "addr:full":"Gewerbestrasse 22 Wels Ober\u00f6sterreich 4600",
    "addr:housenumber":"22",
    "addr:postcode":"4600",
    "addr:street":"Gewerbestrasse;Oberoesterreich",
    "iso:country":"AT",
    "sg:address":"Gewerbestrasse 22",
    "sg:city":"Wels",
    "sg:classifiers":[
        {
            "category":"Building & Trades",
            "subcategory":"Plumbing",
            "type":"Services"
        }
    ],
    "sg:phone":"+43 7242 63647",
    "sg:postcode":"4600",
    "sg:province":"Ober\u00f6sterreich",
    "sg:tags":[
        "supraregional",
        "gas"
    ],
    "sg:website":"karl-schick.at",
    "wof:name":"Karl Schick Ges.m.b.H.",
    "wof:placetype":"venue"
},
  "geometry": {"coordinates":[13.9685125351,48.1398696899],"type":"Point"}
}