{
  "type": "Feature",
  "properties": {
    "addr:full":"Oberfeichten 1 Steinbach am Attersee Ober\u00f6sterreich 4853",
    "addr:housenumber":"1",
    "addr:postcode":"4853",
    "addr:street":"Oberfeichten",
    "iso:country":"AT",
    "sg:address":"Oberfeichten 1",
    "sg:city":"Steinbach am Attersee",
    "sg:orig_category":"Appartements / Ferienwohnungen",
    "sg:phone":"+43 7663259",
    "sg:postcode":"4853",
    "sg:province":"Ober\u00f6sterreich",
    "wof:name":"Ferienhof Feichtinger Fam Zopf",
    "wof:placetype":"venue"
},
  "geometry": {"coordinates":[13.5735473633,47.8415794373],"type":"Point"}
}