{
  "type": "Feature",
  "properties": {
    "addr:full":"Wichnerstr 10 Bludenz Vorarlberg 6700",
    "addr:housenumber":"10",
    "addr:postcode":"6700",
    "addr:street":"Wichnerstr",
    "iso:country":"AT",
    "sg:address":"Wichnerstr 10",
    "sg:city":"Bludenz",
    "sg:orig_category":"Textilwaren / Einzelhandel",
    "sg:phone":"+43 4355 5266777",
    "sg:postcode":"6700",
    "sg:province":"Vorarlberg",
    "wof:name":"NKD",
    "wof:placetype":"venue"
},
  "geometry": {"coordinates":[9.820025444,47.1551704407],"type":"Point"}
}