{
  "type": "Feature",
  "properties": {
    "addr:full":"Laberlweg 19 Wien Wien 1220",
    "addr:housenumber":"19",
    "addr:postcode":"1220",
    "addr:street":"Laberlweg",
    "iso:country":"AT",
    "sg:address":"Laberlweg 19",
    "sg:city":"Wien",
    "sg:classifiers":[
        {
            "category":"Building & Trades",
            "subcategory":"Pest Control",
            "type":"Services"
        }
    ],
    "sg:phone":"+43 1 2633656",
    "sg:postcode":"1220",
    "sg:province":"Wien",
    "sg:tags":[
        "delivery",
        "gastronomy",
        "hotels"
    ],
    "sg:website":"schinakl.com",
    "wof:name":"Urs Auzinger",
    "wof:placetype":"venue"
},
  "geometry": {"coordinates":[16.4242305756,48.2292785645],"type":"Point"}
}