{
  "type": "Feature",
  "properties": {
    "addr:full":"Friedhofg 336/1 Heidenreichstein Nieder\u00f6sterreich 3860",
    "addr:housenumber":"336 / 1",
    "addr:postcode":"3860",
    "iso:country":"AT",
    "sg:address":"Friedhofg 336/1",
    "sg:city":"Heidenreichstein",
    "sg:orig_category":"Lebensmittel / Einzelhandel",
    "sg:phone":"+43 2862 52691",
    "sg:postcode":"3860",
    "sg:province":"Nieder\u00f6sterreich",
    "wof:name":"Billa AG",
    "wof:placetype":"venue"
},
  "geometry": {"coordinates":[15.1167097092,48.872089386],"type":"Point"}
}