{
  "type": "Feature",
  "properties": {
    "iso:country":"AT",
    "sg:address":"Mildepl 7",
    "sg:city":"Wien",
    "sg:orig_category":"Politische Parteien",
    "sg:phone":"+43 1 4847954",
    "sg:postcode":"1160",
    "sg:province":"Wien",
    "wof:name":"Sozialdemokratische Partei \u00f6sterreichs Sektion 16/19/20",
    "wof:placetype":"venue"
},
  "geometry": {"coordinates":[16.3124275208,48.2159118652],"type":"Point"}
}