{
  "type": "Feature",
  "properties": {
    "addr:full":"Putzleinsdorf Ober\u00f6sterreich 4134",
    "addr:postcode":"4134",
    "iso:country":"AT",
    "sg:city":"Putzleinsdorf",
    "sg:orig_category":"Feuerwehren",
    "sg:phone":"+43 7286 827617",
    "sg:postcode":"4134",
    "sg:province":"Ober\u00f6sterreich",
    "wof:name":"Freiwillige Feuerwehr Putzleinsdorf",
    "wof:placetype":"venue"
},
  "geometry": {"coordinates":[13.8730602264,48.5167007446],"type":"Point"}
}