{
  "type": "Feature",
  "properties": {
    "addr:full":"Lehnergutstr 16 Leonding Ober\u00f6sterreich 4060",
    "addr:housenumber":"16",
    "addr:postcode":"4060",
    "addr:street":"Lehnergutstr",
    "iso:country":"AT",
    "sg:address":"Lehnergutstr 16",
    "sg:city":"Leonding",
    "sg:orig_category":"Non-Classified Establishments",
    "sg:phone":"+43 732 671750",
    "sg:postcode":"4060",
    "sg:province":"Ober\u00f6sterreich",
    "wof:name":"Evangelisches Pfarramt",
    "wof:placetype":"venue"
},
  "geometry": {"coordinates":[14.2530059814,48.2774238586],"type":"Point"}
}