{
  "type": "Feature",
  "properties": {
    "addr:full":"Hauptpl 7 Kirchdorf an der Krems Ober\u00f6sterreich 4560",
    "addr:housenumber":"7",
    "addr:postcode":"4560",
    "addr:street":"Hauptpl",
    "iso:country":"AT",
    "sg:address":"Hauptpl 7",
    "sg:city":"Kirchdorf an der Krems",
    "sg:orig_category":"Politische Parteien",
    "sg:phone":"+43 4375 8262056",
    "sg:postcode":"4560",
    "sg:province":"Ober\u00f6sterreich",
    "wof:name":"Sozialdemokratische Partei \u00f6sterreichs (SP\u00f6)",
    "wof:placetype":"venue"
},
  "geometry": {"coordinates":[14.1228322983,47.9052124023],"type":"Point"}
}