{
  "type": "Feature",
  "properties": {
    "iso:country":"AT",
    "sg:address":"Weidenweg 4",
    "sg:city":"Perg",
    "sg:orig_category":"Montagen U Montagetechnik",
    "sg:phone":"+43 7262 54573",
    "sg:postcode":"4320",
    "sg:province":"Ober\u00f6sterreich",
    "wof:name":"Brunner & Gaisrucker OEG",
    "wof:placetype":"venue"
},
  "geometry": {"coordinates":[14.6447238922,48.2435760498],"type":"Point"}
}