{
  "type": "Feature",
  "properties": {
    "addr:full":"Rathauspl 8 Villach K\u00e4rnten 9500",
    "addr:housenumber":"8",
    "addr:postcode":"9500",
    "addr:street":"Rathauspl;Kaernten",
    "iso:country":"AT",
    "sg:address":"Rathauspl 8",
    "sg:city":"Villach",
    "sg:orig_category":"Handarbeiten",
    "sg:phone":"+43 4242 24614",
    "sg:postcode":"9500",
    "sg:province":"K\u00e4rnten",
    "wof:name":"Gregori Lieselotte",
    "wof:placetype":"venue"
},
  "geometry": {"coordinates":[13.8466386795,46.6130485535],"type":"Point"}
}