{
  "type": "Feature",
  "properties": {
    "addr:full":"Hauptstr 27 Rosental an der Kainach Steiermark 8582",
    "addr:housenumber":"27",
    "addr:postcode":"8582",
    "addr:street":"Hauptstr",
    "iso:country":"AT",
    "sg:address":"Hauptstr 27",
    "sg:city":"Rosental an der Kainach",
    "sg:orig_category":"Steuerberatung",
    "sg:phone":"+43 4331 42273500",
    "sg:postcode":"8582",
    "sg:province":"Steiermark",
    "wof:name":"Schmidt Klaus Dr",
    "wof:placetype":"venue"
},
  "geometry": {"coordinates":[15.1233062744,47.0527267456],"type":"Point"}
}