{
  "type": "Feature",
  "properties": {
    "iso:country":"AT",
    "sg:address":"Warmbader Str 5",
    "sg:city":"Villach",
    "sg:orig_category":"Fu\u00c3\u0178bodenheizungen",
    "sg:phone":"+43 4242 31033",
    "sg:postcode":"9500",
    "sg:province":"K\u00e4rnten",
    "wof:name":"Wikinger Produktentwicklung GesmbH",
    "wof:placetype":"venue"
},
  "geometry": {"coordinates":[13.8350982666,46.5997200012],"type":"Point"}
}