{
  "type": "Feature",
  "properties": {
    "addr:full":"Au 1 Bad Wimsbach-Neydharting Ober\u00f6sterreich 4654",
    "addr:housenumber":"1",
    "addr:postcode":"4654",
    "addr:street":"Au",
    "iso:country":"AT",
    "sg:address":"Au 1",
    "sg:city":"Bad Wimsbach-Neydharting",
    "sg:orig_category":"Maschinenbau",
    "sg:phone":"+43 7245 25722",
    "sg:postcode":"4654",
    "sg:province":"Ober\u00f6sterreich",
    "wof:name":"Kowarik Siegfried",
    "wof:placetype":"venue"
},
  "geometry": {"coordinates":[13.9088029861,48.055103302],"type":"Point"}
}