{
  "type": "Feature",
  "properties": {
    "addr:full":"Gentzgasse 112 Wien Wien 1180",
    "addr:housenumber":"112",
    "addr:postcode":"1180",
    "addr:street":"Gentzgasse",
    "iso:country":"AT",
    "sg:address":"Gentzgasse 112",
    "sg:city":"Wien",
    "sg:classifiers":[
        {
            "category":"Home & Garden",
            "subcategory":"Home Furnishings",
            "type":"Retail Goods"
        }
    ],
    "sg:phone":"+43 1 4702701",
    "sg:postcode":"1180",
    "sg:province":"Wien",
    "sg:tags":[
        "candle"
    ],
    "wof:name":"Lebens-Raum",
    "wof:placetype":"venue"
},
  "geometry": {"coordinates":[16.3349475861,48.2290077209],"type":"Point"}
}