{
  "type": "Feature",
  "properties": {
    "addr:full":"Bahnhofstrasse 30 Birkfeld Steiermark 8190",
    "addr:housenumber":"30",
    "addr:postcode":"8190",
    "addr:street":"Bahnhofstrasse",
    "iso:country":"AT",
    "sg:address":"Bahnhofstrasse 30",
    "sg:city":"Birkfeld",
    "sg:orig_category":"CarpenterS Work Supraregional",
    "sg:phone":"+43 3174 4575",
    "sg:postcode":"8190",
    "sg:province":"Steiermark",
    "sg:website":"stuecklberger.at",
    "wof:name":"St\u00fccklberger Ges.m.b.H.",
    "wof:placetype":"venue"
},
  "geometry": {"coordinates":[15.6989297867,47.3523788452],"type":"Point"}
}