{
  "type": "Feature",
  "properties": {
    "iso:country":"AT",
    "sg:address":"Kirchstr 10",
    "sg:city":"Lustenau",
    "sg:orig_category":"Lebensmittel / Einzelhandel",
    "sg:phone":"+43 5577 89095",
    "sg:postcode":"6890",
    "sg:province":"Vorarlberg",
    "wof:name":"Karabulut",
    "wof:placetype":"venue"
},
  "geometry": {"coordinates":[9.6556348801,47.427444458],"type":"Point"}
}