{
  "type": "Feature",
  "properties": {
    "addr:full":"Dietersdorf 48 Wundschuh Steiermark 8142",
    "addr:housenumber":"48",
    "addr:postcode":"8142",
    "addr:street":"Dietersdorf",
    "iso:country":"AT",
    "sg:address":"Dietersdorf 48",
    "sg:city":"Wundschuh",
    "sg:orig_category":"Tischlereien",
    "sg:phone":"+43 3136 52772",
    "sg:postcode":"8142",
    "sg:province":"Steiermark",
    "wof:name":"Knes Albin",
    "wof:placetype":"venue"
},
  "geometry": {"coordinates":[15.4498796463,46.9254493713],"type":"Point"}
}