{
  "type": "Feature",
  "properties": {
    "iso:country":"AT",
    "sg:address":"Anton-Wallner-Str 5",
    "sg:city":"Zell am See",
    "sg:orig_category":"Autovermietung",
    "sg:phone":"+43 4366 44307455",
    "sg:postcode":"5700",
    "sg:province":"Salzburg",
    "wof:name":"Trike & Car Center",
    "wof:placetype":"venue"
},
  "geometry": {"coordinates":[12.7973823547,47.3243370056],"type":"Point"}
}