{
  "type": "Feature",
  "properties": {
    "addr:full":"Dametzstr 10 Linz Ober\u00f6sterreich 4020",
    "addr:housenumber":"10",
    "addr:postcode":"4020",
    "addr:street":"Dametzstr",
    "iso:country":"AT",
    "sg:address":"Dametzstr 10",
    "sg:city":"Linz",
    "sg:orig_category":"Lebensmittel / Einzelhandel",
    "sg:phone":"+43 732 771511",
    "sg:postcode":"4020",
    "sg:province":"Ober\u00f6sterreich",
    "wof:name":"Hong Kong Shop Inh Chang HandelsgesmbH",
    "wof:placetype":"venue"
},
  "geometry": {"coordinates":[14.2907495499,48.3040733337],"type":"Point"}
}