{
  "type": "Feature",
  "properties": {
    "addr:full":"Wallensteinstr 68 Wien Wien 1200",
    "addr:housenumber":"68",
    "addr:postcode":"1200",
    "addr:street":"Wallensteinstr",
    "iso:country":"AT",
    "sg:address":"Wallensteinstr 68",
    "sg:city":"Wien",
    "sg:orig_category":"Maler, Anstreicher U Lackierer",
    "sg:phone":"+43 4313 329915",
    "sg:postcode":"1200",
    "sg:province":"Wien",
    "wof:name":"Rosenberg C u G GesmbH",
    "wof:placetype":"venue"
},
  "geometry": {"coordinates":[16.3772125244,48.2311096191],"type":"Point"}
}