{
  "type": "Feature",
  "properties": {
    "iso:country":"AT",
    "sg:address":"Carola-Blome-Str 7",
    "sg:city":"Salzburg",
    "sg:orig_category":"Reinigungsbedarf U Reinigungsmittel",
    "sg:phone":"+43 4366 24343420",
    "sg:postcode":"5020",
    "sg:province":"Salzburg",
    "wof:name":"TCDO-Produktions GmbH",
    "wof:placetype":"venue"
},
  "geometry": {"coordinates":[13.0034513474,47.8240776062],"type":"Point"}
}