{
  "type": "Feature",
  "properties": {
    "addr:full":"Trientlg 70 Innsbruck Tirol 6020",
    "addr:housenumber":"70",
    "addr:postcode":"6020",
    "addr:street":"Trientlg;Tirol",
    "iso:country":"AT",
    "sg:address":"Trientlg 70",
    "sg:city":"Innsbruck",
    "sg:orig_category":"Installationsunternehmen",
    "sg:phone":"+43 512 347627",
    "sg:postcode":"6020",
    "sg:province":"Tirol",
    "wof:name":"Haustechnik Steiner Innsbruck",
    "wof:placetype":"venue"
},
  "geometry": {"coordinates":[11.4414749146,47.2664299011],"type":"Point"}
}