{
  "type": "Feature",
  "properties": {
    "addr:full":"Tannenweg 44 Ansfelden Ober\u00f6sterreich 4052",
    "addr:housenumber":"44",
    "addr:postcode":"4052",
    "addr:street":"Tannenweg",
    "iso:country":"AT",
    "sg:address":"Tannenweg 44",
    "sg:city":"Ansfelden",
    "sg:orig_category":"Blumenbinder",
    "sg:phone":"+43 732 310940",
    "sg:postcode":"4052",
    "sg:province":"Ober\u00f6sterreich",
    "wof:name":"Blumenstudio - Haslgr\u00fcbler Manuela - Blumenbilder",
    "wof:placetype":"venue"
},
  "geometry": {"coordinates":[14.2955389023,48.2209129333],"type":"Point"}
}