{
  "type": "Feature",
  "properties": {
    "addr:full":"Nr 238 Mariahof Steiermark 8812",
    "addr:postcode":"8812",
    "addr:street":"Nr 238",
    "iso:country":"AT",
    "sg:address":"Nr 238",
    "sg:city":"Mariahof",
    "sg:orig_category":"Pensionen / Privatzimmer",
    "sg:phone":"+43 3584 2631",
    "sg:postcode":"8812",
    "sg:province":"Steiermark",
    "wof:name":"K\u00f6lbl Elvira",
    "wof:placetype":"venue"
},
  "geometry": {"coordinates":[14.3994102478,47.0992660522],"type":"Point"}
}