{
  "type": "Feature",
  "properties": {
    "addr:full":"Margarethenweg 19 Linz Ober\u00f6sterreich 4020",
    "addr:housenumber":"19",
    "addr:postcode":"4020",
    "addr:street":"Margarethenweg",
    "iso:country":"AT",
    "sg:address":"Margarethenweg 19",
    "sg:city":"Linz",
    "sg:orig_category":"Ingenieurkonsulenten / Zivilingenieure",
    "sg:phone":"+43 4373 27973600",
    "sg:postcode":"4020",
    "sg:province":"Ober\u00f6sterreich",
    "wof:name":"Pospischek Kurt Dipl-Ing",
    "wof:placetype":"venue"
},
  "geometry": {"coordinates":[14.2620754242,48.3022613525],"type":"Point"}
}