{
  "type": "Feature",
  "properties": {
    "iso:country":"AT",
    "sg:address":"Florian-Waldauf-Str 1",
    "sg:city":"Kolsass",
    "sg:orig_category":"Molkereien U Molkereiprodukte",
    "sg:phone":"+43 4352 2467406",
    "sg:postcode":"6114",
    "sg:province":"Tirol",
    "wof:name":"Milchstern K\u00e4serei u Handels-GmbH",
    "wof:placetype":"venue"
},
  "geometry": {"coordinates":[11.6301212311,47.3009262085],"type":"Point"}
}