{
  "type": "Feature",
  "properties": {
    "addr:full":"Grenzweg 3 Gerasdorf Nieder\u00f6sterreich 2201",
    "addr:housenumber":"3",
    "addr:postcode":"2201",
    "addr:street":"Grenzweg",
    "iso:country":"AT",
    "sg:address":"Grenzweg 3",
    "sg:city":"Gerasdorf",
    "sg:orig_category":"Friseure U Frisiersalons",
    "sg:phone":"+43 4322 462170",
    "sg:postcode":"2201",
    "sg:province":"Nieder\u00f6sterreich",
    "wof:name":"Frisiersalon Ilona",
    "wof:placetype":"venue"
},
  "geometry": {"coordinates":[16.447725296,48.2883033752],"type":"Point"}
}