{
  "type": "Feature",
  "properties": {
    "addr:full":"null Forsteralm Gaflenz Ober\u00f6sterreich 3334",
    "addr:postcode":"3334",
    "addr:street":"Oberoesterreich",
    "iso:country":"AT",
    "sg:address":"null Forsteralm",
    "sg:city":"Gaflenz",
    "sg:classifiers":[
        {
            "category":"Park",
            "subcategory":"Provincial",
            "type":"Public Place"
        }
    ],
    "sg:phone":"+43 4373 53300",
    "sg:postcode":"3334",
    "sg:province":"Ober\u00f6sterreich",
    "sg:tags":[
        "u",
        "ski-",
        "snowboardschulen"
    ],
    "wof:name":"Schischule Forsteralm",
    "wof:placetype":"venue"
},
  "geometry": {"coordinates":[14.7584428787,47.897808075],"type":"Point"}
}