{
  "type": "Feature",
  "properties": {
    "iso:country":"AT",
    "sg:address":"Lerchenfeld 25",
    "sg:city":"Lockenhaus",
    "sg:orig_category":"Textilwaren / Einzelhandel",
    "sg:phone":"+43 2616 22650",
    "sg:postcode":"7442",
    "sg:province":"Burgenland",
    "wof:name":"Goldfeder GesmbH",
    "wof:placetype":"venue"
},
  "geometry": {"coordinates":[16.4097213745,47.407371521],"type":"Point"}
}