{
  "type": "Feature",
  "properties": {
    "addr:full":"Nr 79 Kirchbach in Steiermark Steiermark 8082",
    "addr:postcode":"8082",
    "addr:street":"Nr",
    "iso:country":"AT",
    "sg:address":"Nr 79",
    "sg:city":"Kirchbach in Steiermark",
    "sg:classifiers":[
        {
            "category":"Internet Cafe",
            "subcategory":"None",
            "type":"Food & Drink"
        }
    ],
    "sg:phone":"+43 3116 21089",
    "sg:postcode":"8082",
    "sg:province":"Steiermark",
    "sg:tags":[
        "internet-provider"
    ],
    "wof:name":"IFO.net Internet Service GmbH",
    "wof:placetype":"venue"
},
  "geometry": {"coordinates":[15.6588878632,46.937297821],"type":"Point"}
}