{
  "type": "Feature",
  "properties": {
    "addr:full":"Oberndorfer Str 54 Kirchbichl Tirol 6322",
    "addr:housenumber":"54",
    "addr:postcode":"6322",
    "addr:street":"Oberndorfer Str;Tirol",
    "iso:country":"AT",
    "sg:address":"Oberndorfer Str 54",
    "sg:city":"Kirchbichl",
    "sg:classifiers":[
        {
            "category":"Farming",
            "subcategory":"Livestock Farm",
            "type":"Manufacturing & Wholesale Goods"
        }
    ],
    "sg:phone":"+43 5332 87140",
    "sg:postcode":"6322",
    "sg:province":"Tirol",
    "sg:tags":[
        "-handel",
        "viehzucht",
        "u"
    ],
    "wof:name":"Huber Max",
    "wof:placetype":"venue"
},
  "geometry": {"coordinates":[12.0850296021,47.5078582764],"type":"Point"}
}