{
  "type": "Feature",
  "properties": {
    "addr:full":"Gumpendorfer Str 69 Wien Wien 1060",
    "addr:postcode":"1060",
    "addr:street":"Str 69",
    "iso:country":"AT",
    "sg:address":"Gumpendorfer Str 69",
    "sg:city":"Wien",
    "sg:orig_category":"Zeitungen U Zeitschriften",
    "sg:phone":"+43 4319 719462",
    "sg:postcode":"1060",
    "sg:province":"Wien",
    "wof:name":"VOLLTEXT Verlag GmbH",
    "wof:placetype":"venue"
},
  "geometry": {"coordinates":[16.3511886597,48.1952209473],"type":"Point"}
}