{
  "type": "Feature",
  "properties": {
    "addr:full":"Horvathgasse 15 Wien Wien 1160",
    "addr:housenumber":"15",
    "addr:postcode":"1160",
    "addr:street":"Horvathgasse",
    "iso:country":"AT",
    "sg:address":"Horvathgasse 15",
    "sg:city":"Wien",
    "sg:classifiers":[
        {
            "category":"Military Area",
            "subcategory":"Air Force Base",
            "type":"Public Place"
        }
    ],
    "sg:phone":"+43 1 7899135",
    "sg:postcode":"1160",
    "sg:province":"Wien",
    "sg:tags":[
        "earth",
        "system"
    ],
    "sg:website":"blitzfranz.at",
    "wof:name":"Blitz-Franz Langer KEG",
    "wof:placetype":"venue"
},
  "geometry": {"coordinates":[16.305847168,48.2056274414],"type":"Point"}
}