{
  "type": "Feature",
  "properties": {
    "addr:full":"Gewerbepark 7 Steinerkirchen an der Traun Ober\u00f6sterreich 4652",
    "addr:housenumber":"7",
    "addr:postcode":"4652",
    "addr:street":"Gewerbepark",
    "iso:country":"AT",
    "sg:address":"Gewerbepark 7",
    "sg:city":"Steinerkirchen an der Traun",
    "sg:classifiers":[
        {
            "category":"Banks & Credit Unions",
            "subcategory":"Bureau De Change",
            "type":"Services"
        }
    ],
    "sg:phone":"+43 7245 25967",
    "sg:postcode":"4652",
    "sg:province":"Ober\u00f6sterreich",
    "sg:tags":[
        "flat",
        "construction",
        "roof"
    ],
    "wof:name":"Gerhard Schiffer",
    "wof:placetype":"venue"
},
  "geometry": {"coordinates":[13.9176454544,48.0750389099],"type":"Point"}
}