{
  "type": "Feature",
  "properties": {
    "addr:full":"Obere Hauptstr 63 Tadten Burgenland 7162",
    "addr:housenumber":"63",
    "addr:postcode":"7162",
    "addr:street":"Obere Hauptstr",
    "iso:country":"AT",
    "sg:address":"Obere Hauptstr 63",
    "sg:city":"Tadten",
    "sg:orig_category":"Tankstellen",
    "sg:phone":"+43 2176 3353",
    "sg:postcode":"7162",
    "sg:province":"Burgenland",
    "wof:name":"Diskont-Tankstelle",
    "wof:placetype":"venue"
},
  "geometry": {"coordinates":[16.9836425781,47.7655029297],"type":"Point"}
}