{
  "type": "Feature",
  "properties": {
    "addr:full":"Haydng 10 Graz Steiermark 8010",
    "addr:housenumber":"10",
    "addr:postcode":"8010",
    "addr:street":"Haydng",
    "iso:country":"AT",
    "sg:address":"Haydng 10",
    "sg:city":"Graz",
    "sg:orig_category":"Galerien",
    "sg:phone":"+43 316 819330",
    "sg:postcode":"8010",
    "sg:province":"Steiermark",
    "wof:name":"balthasar Galerie",
    "wof:placetype":"venue"
},
  "geometry": {"coordinates":[15.4487266541,47.0693855286],"type":"Point"}
}