{
  "type": "Feature",
  "properties": {
    "iso:country":"AT",
    "sg:address":"Bogen 10",
    "sg:city":"Tannheim",
    "sg:classifiers":[
        {
            "category":"Restaurant",
            "type":"Food & Drink"
        }
    ],
    "sg:phone":"+43 5675 6293",
    "sg:postcode":"6675",
    "sg:province":"Tirol",
    "wof:name":"Restaurant Vilsalpsee",
    "wof:placetype":"venue"
},
  "geometry": {"coordinates":[10.5200738907,47.4932174683],"type":"Point"}
}