{
  "type": "Feature",
  "properties": {
    "iso:country":"AT",
    "sg:address":"Woll\u00f6ster 60",
    "sg:city":"Mauerkirchen",
    "sg:classifiers":[
        {
            "category":"Home & Garden",
            "subcategory":"Building Materials",
            "type":"Retail Goods"
        }
    ],
    "sg:phone":"+43 7724 2121",
    "sg:postcode":"5270",
    "sg:province":"Ober\u00f6sterreich",
    "sg:tags":[
        "garage",
        "door"
    ],
    "wof:name":"GPG Girlinger KEG",
    "wof:placetype":"venue"
},
  "geometry": {"coordinates":[13.1354646683,48.1907691956],"type":"Point"}
}