{
  "type": "Feature",
  "properties": {
    "addr:full":"Lehnerg 4 Wien Wien 1230",
    "addr:housenumber":"4",
    "addr:postcode":"1230",
    "addr:street":"Lehnerg",
    "iso:country":"AT",
    "sg:address":"Lehnerg 4",
    "sg:city":"Wien",
    "sg:orig_category":"Mess-, Steuer- U Regeltechnik",
    "sg:phone":"+43 4318 80560",
    "sg:postcode":"1230",
    "sg:province":"Wien",
    "wof:name":"Endress + Hauser GesmbH",
    "wof:placetype":"venue"
},
  "geometry": {"coordinates":[16.2831935883,48.1382522583],"type":"Point"}
}