{
  "type": "Feature",
  "properties": {
    "addr:full":"Murhofstr 14 Judendorf-Stra\u00dfengel Steiermark 8111",
    "addr:housenumber":"14",
    "addr:postcode":"8111",
    "addr:street":"Murhofstr",
    "iso:country":"AT",
    "sg:address":"Murhofstr 14",
    "sg:city":"Judendorf-Stra\u00dfengel",
    "sg:orig_category":"Transportunternehmen",
    "sg:phone":"+43 664 2413706",
    "sg:postcode":"8111",
    "sg:province":"Steiermark",
    "wof:name":"L\u00f6ffler Manfred",
    "wof:placetype":"venue"
},
  "geometry": {"coordinates":[15.3421258926,47.1205291748],"type":"Point"}
}