{
  "type": "Feature",
  "properties": {
    "iso:country":"AT",
    "sg:address":"D\u00f6llacher Str 7",
    "sg:city":"Liezen",
    "sg:orig_category":"Elektroinstallationsunternehmen",
    "sg:phone":"+43 4336 12227770",
    "sg:postcode":"8940",
    "sg:province":"Steiermark",
    "wof:name":"Elektro Wei\u00dfensteiner GmbH",
    "wof:placetype":"venue"
},
  "geometry": {"coordinates":[14.2413349152,47.5672111511],"type":"Point"}
}