{
  "type": "Feature",
  "properties": {
    "iso:country":"AT",
    "sg:address":"Elisabethg 36",
    "sg:city":"Klosterneuburg",
    "sg:orig_category":"Installationsunternehmen",
    "sg:phone":"+43 2243 22105",
    "sg:postcode":"3400",
    "sg:province":"Nieder\u00f6sterreich",
    "wof:name":"Weiss Alfred",
    "wof:placetype":"venue"
},
  "geometry": {"coordinates":[16.2952518463,48.2943534851],"type":"Point"}
}