{
  "type": "Feature",
  "properties": {
    "iso:country":"AT",
    "sg:address":"Karl-Zanger-Str 8",
    "sg:city":"Absam",
    "sg:orig_category":"Spenglereien",
    "sg:phone":"+43 4352 2356273",
    "sg:postcode":"6067",
    "sg:province":"Tirol",
    "sg:website":"posch-klaus.at",
    "wof:name":"Posch Klaus",
    "wof:placetype":"venue"
},
  "geometry": {"coordinates":[11.5053319931,47.2930755615],"type":"Point"}
}