{
  "type": "Feature",
  "properties": {
    "addr:full":"Herzog-Leopold-Str 10 Wiener Neustadt Nieder\u00f6sterreich 2700",
    "addr:housenumber":"10",
    "addr:postcode":"2700",
    "addr:street":"Herzog-Leopold-Str",
    "iso:country":"AT",
    "sg:address":"Herzog-Leopold-Str 10",
    "sg:city":"Wiener Neustadt",
    "sg:orig_category":"Mineralien",
    "sg:phone":"+43 4366 41508544",
    "sg:postcode":"2700",
    "sg:province":"Nieder\u00f6sterreich",
    "wof:name":"Wukonig Minerals OEG",
    "wof:placetype":"venue"
},
  "geometry": {"coordinates":[16.2415122986,47.813457489],"type":"Point"}
}