{
  "type": "Feature",
  "properties": {
    "addr:full":"Kirchenpl 12 Ternberg Ober\u00f6sterreich 4452",
    "addr:housenumber":"12",
    "addr:postcode":"4452",
    "addr:street":"Kirchenpl",
    "iso:country":"AT",
    "sg:address":"Kirchenpl 12",
    "sg:city":"Ternberg",
    "sg:orig_category":"Gemeinden",
    "sg:phone":"+43 7256 60010",
    "sg:postcode":"4452",
    "sg:province":"Ober\u00f6sterreich",
    "wof:name":"Gemeindeamt Ternberg",
    "wof:placetype":"venue"
},
  "geometry": {"coordinates":[14.3571195602,47.9458580017],"type":"Point"}
}