{
  "type": "Feature",
  "properties": {
    "addr:full":"Kreuzwieseng 9 Wien Wien 1170",
    "addr:housenumber":"9",
    "addr:postcode":"1170",
    "addr:street":"Kreuzwieseng",
    "iso:country":"AT",
    "sg:address":"Kreuzwieseng 9",
    "sg:city":"Wien",
    "sg:orig_category":"Non-Classified Establishments",
    "sg:phone":"+43 1 48625500",
    "sg:postcode":"1170",
    "sg:province":"Wien",
    "wof:name":"Missionsschwestern K\u00f6nigin d Apostel - Krankenpflegerschwestern",
    "wof:placetype":"venue"
},
  "geometry": {"coordinates":[16.2937927246,48.2367095947],"type":"Point"}
}