{
  "type": "Feature",
  "properties": {
    "addr:full":"Weiherstr 2 Bregenz Vorarlberg 6900",
    "addr:housenumber":"2",
    "addr:postcode":"6900",
    "addr:street":"Weiherstr",
    "iso:country":"AT",
    "sg:address":"Weiherstr 2",
    "sg:city":"Bregenz",
    "sg:orig_category":"Fotografen",
    "sg:phone":"+43 4369 911110855",
    "sg:postcode":"6900",
    "sg:province":"Vorarlberg",
    "wof:name":"Fotograf Weissengruber Matthias",
    "wof:placetype":"venue"
},
  "geometry": {"coordinates":[9.7438602448,47.5030784607],"type":"Point"}
}