{
  "type": "Feature",
  "properties": {
    "addr:full":"Frauenstiftg 8 Wien Wien 1210",
    "addr:housenumber":"8",
    "addr:postcode":"1210",
    "addr:street":"Frauenstiftg",
    "iso:country":"AT",
    "sg:address":"Frauenstiftg 8",
    "sg:city":"Wien",
    "sg:orig_category":"Fliesen- U Plattenverlegungen",
    "sg:phone":"+43 1 2926543",
    "sg:postcode":"1210",
    "sg:province":"Wien",
    "wof:name":"RABAS Keramische Raumgestaltung",
    "wof:placetype":"venue"
},
  "geometry": {"coordinates":[16.4071388245,48.2768554688],"type":"Point"}
}