{
  "type": "Feature",
  "properties": {
    "addr:full":"Leopoldstr. 17 Innsbruck Tirol 6020",
    "addr:housenumber":"17",
    "addr:postcode":"6020",
    "addr:street":"Leopoldstr.;Tirol",
    "iso:country":"AT",
    "sg:address":"Leopoldstr. 17",
    "sg:city":"Innsbruck",
    "sg:classifiers":[
        {
            "category":"Banks & Credit Unions",
            "subcategory":"Financial Services",
            "type":"Services"
        }
    ],
    "sg:phone":"+43 4351 2598400",
    "sg:postcode":"6020",
    "sg:province":"Tirol",
    "sg:tags":[
        "banking",
        "finance",
        "insurance"
    ],
    "wof:name":"MERKUR VERSICHERUNG AG",
    "wof:placetype":"venue"
},
  "geometry": {"coordinates":[11.39564991,47.2603187561],"type":"Point"}
}