{
  "type": "Feature",
  "properties": {
    "iso:country":"AT",
    "sg:address":"Feldkreuzstr 1a",
    "sg:city":"Rum",
    "sg:orig_category":"Physiotherapie",
    "sg:phone":"+43 4366 45045071",
    "sg:postcode":"6063",
    "sg:province":"Tirol",
    "wof:name":"Klema Astrid Dipl-PT",
    "wof:placetype":"venue"
},
  "geometry": {"coordinates":[11.4517993927,47.2853889465],"type":"Point"}
}