{
  "type": "Feature",
  "properties": {
    "iso:country":"AT",
    "sg:address":"Webereiweg 8",
    "sg:city":"Hallein",
    "sg:classifiers":[
        {
            "category":"Internet Cafe",
            "subcategory":"None",
            "type":"Food & Drink"
        }
    ],
    "sg:phone":"+43 664 3557564",
    "sg:postcode":"5400",
    "sg:province":"Salzburg",
    "wof:name":"IMAGE Kommunikationsdesign GmbH",
    "wof:placetype":"venue"
},
  "geometry": {"coordinates":[13.0748195648,47.7285957336],"type":"Point"}
}