{
  "type": "Feature",
  "properties": {
    "addr:full":"Marktpl 12 Dornbirn Vorarlberg 6850",
    "addr:housenumber":"12",
    "addr:postcode":"6850",
    "addr:street":"Marktpl",
    "iso:country":"AT",
    "sg:address":"Marktpl 12",
    "sg:city":"Dornbirn",
    "sg:orig_category":"Damenmoden",
    "sg:phone":"+43 5572 36840",
    "sg:postcode":"6850",
    "sg:province":"Vorarlberg",
    "wof:name":"Blue Handels GmbH",
    "wof:placetype":"venue"
},
  "geometry": {"coordinates":[9.7424716949,47.4137382507],"type":"Point"}
}