{
  "type": "Feature",
  "properties": {
    "addr:full":"Seebarner Str 1a Korneuburg Nieder\u00f6sterreich 2100",
    "addr:postcode":"2100",
    "addr:street":"Str 1A",
    "iso:country":"AT",
    "sg:address":"Seebarner Str 1a",
    "sg:city":"Korneuburg",
    "sg:orig_category":"Feuerwehren",
    "sg:phone":"+43 2262 673420",
    "sg:postcode":"2100",
    "sg:province":"Nieder\u00f6sterreich",
    "wof:name":"Freiwillige Feuerwehr Stetten",
    "wof:placetype":"venue"
},
  "geometry": {"coordinates":[16.3830814362,48.3688278198],"type":"Point"}
}