{
  "type": "Feature",
  "properties": {
    "addr:full":"Schmiedingerstr 67 Salzburg Salzburg 5020",
    "addr:housenumber":"67",
    "addr:postcode":"5020",
    "addr:street":"Schmiedingerstr;Salzburg",
    "iso:country":"AT",
    "sg:address":"Schmiedingerstr 67",
    "sg:city":"Salzburg",
    "sg:orig_category":"Transportunternehmen",
    "sg:phone":"+43 662 4362800",
    "sg:postcode":"5020",
    "sg:province":"Salzburg",
    "wof:name":"Vega International Car Transport and Logistic Trading GesmbH",
    "wof:placetype":"venue"
},
  "geometry": {"coordinates":[13.022321701,47.8280982971],"type":"Point"}
}