{
  "type": "Feature",
  "properties": {
    "addr:full":"Augustinerg 11a Salzburg Salzburg 5020",
    "addr:housenumber":"11a",
    "addr:postcode":"5020",
    "addr:street":"Augustinerg;Salzburg",
    "iso:country":"AT",
    "sg:address":"Augustinerg 11a",
    "sg:city":"Salzburg",
    "sg:classifiers":[
        {
            "category":"Restaurant",
            "type":"Food & Drink"
        }
    ],
    "sg:phone":"+43 662 844477",
    "sg:postcode":"5020",
    "sg:province":"Salzburg",
    "wof:name":"Fortmann Evamarie",
    "wof:placetype":"venue"
},
  "geometry": {"coordinates":[13.0321149826,47.802444458],"type":"Point"}
}