{
  "type": "Feature",
  "properties": {
    "addr:full":"Steinachstr 24 Bregenz Vorarlberg 6900",
    "addr:housenumber":"24",
    "addr:postcode":"6900",
    "addr:street":"Steinachstr",
    "iso:country":"AT",
    "sg:address":"Steinachstr 24",
    "sg:city":"Bregenz",
    "sg:orig_category":"Weine / Einzelhandel",
    "sg:phone":"+43 5574 76081",
    "sg:postcode":"6900",
    "sg:province":"Vorarlberg",
    "wof:name":"Schelling Heinz",
    "wof:placetype":"venue"
},
  "geometry": {"coordinates":[9.7173156738,47.4895744324],"type":"Point"}
}