{
  "type": "Feature",
  "properties": {
    "iso:country":"AT",
    "sg:address":"Silberg 16",
    "sg:city":"Rietz",
    "sg:orig_category":"Erdarbeiten",
    "sg:phone":"+43 5262 62727",
    "sg:postcode":"6421",
    "sg:province":"Tirol",
    "wof:name":"Prantl Harald",
    "wof:placetype":"venue"
},
  "geometry": {"coordinates":[11.0309400558,47.286151886],"type":"Point"}
}