{
  "type": "Feature",
  "properties": {
    "addr:full":"Robinigstrasse 93 Salzburg Salzburg 5020",
    "addr:housenumber":"93",
    "addr:postcode":"5020",
    "addr:street":"Robinigstrasse;Salzburg",
    "iso:country":"AT",
    "sg:address":"Robinigstrasse 93",
    "sg:city":"Salzburg",
    "sg:classifiers":[
        {
            "category":"Professional",
            "subcategory":"Accounting & Tax Preparation",
            "type":"Services"
        }
    ],
    "sg:phone":"+43 662 4550090",
    "sg:postcode":"5020",
    "sg:province":"Salzburg",
    "sg:tags":[
        "audit",
        "environmental",
        "protection"
    ],
    "sg:website":"intergeo-consulting.com",
    "wof:name":"INTERGEO Umwelttechnologie und Abfallwirtschaft GmbH",
    "wof:placetype":"venue"
},
  "geometry": {"coordinates":[13.0579252243,47.822593689],"type":"Point"}
}