{
  "type": "Feature",
  "properties": {
    "iso:country":"AT",
    "sg:address":"Bergstrasse 41",
    "sg:city":"Haslach an der M\u00fchl",
    "sg:classifiers":[
        {
            "category":"Shopping",
            "subcategory":"Department Store",
            "type":"Retail Goods"
        }
    ],
    "sg:phone":"+43 7289 710390",
    "sg:postcode":"4170",
    "sg:province":"Ober\u00f6sterreich",
    "sg:tags":[
        "linen",
        "bed"
    ],
    "wof:name":"Hermann Bayer",
    "wof:placetype":"venue"
},
  "geometry": {"coordinates":[14.1033849716,48.5675315857],"type":"Point"}
}