{
  "type": "Feature",
  "properties": {
    "addr:full":"Hauptstrasse 30 Ruprechtshofen Nieder\u00f6sterreich 3244",
    "addr:housenumber":"30",
    "addr:postcode":"3244",
    "addr:street":"Hauptstrasse",
    "iso:country":"AT",
    "sg:address":"Hauptstrasse 30",
    "sg:city":"Ruprechtshofen",
    "sg:classifiers":[
        {
            "category":"Sports & Exercise",
            "subcategory":"Stables",
            "type":"Entertainment"
        }
    ],
    "sg:phone":"+43 2756 2488",
    "sg:postcode":"3244",
    "sg:province":"Nieder\u00f6sterreich",
    "sg:tags":[
        "equipment"
    ],
    "wof:name":"Prankl GmbH",
    "wof:placetype":"venue"
},
  "geometry": {"coordinates":[15.2820205688,48.1398048401],"type":"Point"}
}