{
  "type": "Feature",
  "properties": {
    "addr:full":"Mahlerstr 11/2 Wien Wien 1010",
    "addr:housenumber":"11 / 2",
    "addr:postcode":"1010",
    "addr:street":"Mahlerstr",
    "iso:country":"AT",
    "sg:address":"Mahlerstr 11/2",
    "sg:city":"Wien",
    "sg:orig_category":"Gastronomie- U Hotelbetriebsgesellschaften",
    "sg:phone":"+43 1 5130772",
    "sg:postcode":"1010",
    "sg:province":"Wien",
    "wof:name":"ROSSO E NERO Gastst\u00e4ttenbetriebsgesmbH",
    "wof:placetype":"venue"
},
  "geometry": {"coordinates":[16.3727397919,48.202583313],"type":"Point"}
}