{
  "type": "Feature",
  "properties": {
    "addr:full":"Glash\u00fcttenstr 2 Reichenau im M\u00fchlkreis Ober\u00f6sterreich 4204",
    "addr:housenumber":"2",
    "addr:postcode":"4204",
    "addr:street":"Glashuettenstr;Im Muehlkreis Oberoesterreich",
    "iso:country":"AT",
    "sg:address":"Glash\u00fcttenstr 2",
    "sg:city":"Reichenau im M\u00fchlkreis",
    "sg:orig_category":"Volksschulen",
    "sg:phone":"+43 4372 118262",
    "sg:postcode":"4204",
    "sg:province":"Ober\u00f6sterreich",
    "wof:name":"Volksschule",
    "wof:placetype":"venue"
},
  "geometry": {"coordinates":[14.3493795395,48.4560813904],"type":"Point"}
}