{
  "type": "Feature",
  "properties": {
    "addr:full":"Krugerstr. 6 Wien Wien 1010",
    "addr:housenumber":"6",
    "addr:postcode":"1010",
    "addr:street":"Krugerstr.",
    "iso:country":"AT",
    "sg:address":"Krugerstr. 6",
    "sg:city":"Wien",
    "sg:classifiers":[
        {
            "category":"Manufacturing",
            "subcategory":"Glass & Minerals",
            "type":"Manufacturing & Wholesale Goods"
        }
    ],
    "sg:phone":"+43 4315 1232920",
    "sg:postcode":"1010",
    "sg:province":"Wien",
    "wof:name":"CONTACTA KONTAKTLINSEN GES.MBH",
    "wof:placetype":"venue"
},
  "geometry": {"coordinates":[16.3713932037,48.2037887573],"type":"Point"}
}