{
  "type": "Feature",
  "properties": {
    "addr:full":"Neumayrgasse 6 Wien Wien 1160",
    "addr:housenumber":"6",
    "addr:postcode":"1160",
    "addr:street":"Neumayrgasse",
    "iso:country":"AT",
    "sg:address":"Neumayrgasse 6",
    "sg:city":"Wien",
    "sg:classifiers":[
        {
            "category":"Retail",
            "subcategory":"Car Wash",
            "type":"Services"
        }
    ],
    "sg:phone":"+43 1 49209180",
    "sg:postcode":"1160",
    "sg:province":"Wien",
    "sg:tags":[
        "machine",
        "cigarette",
        "vending"
    ],
    "sg:website":"aba-system.at",
    "wof:name":"ABA-System Allgemeine Badische Automatenfabrik Thr\u00f6ner und Schneiderei Ges.m.b.H. & Co Ges.m.b.H.",
    "wof:placetype":"venue"
},
  "geometry": {"coordinates":[16.3339633942,48.2046546936],"type":"Point"}
}