{
  "type": "Feature",
  "properties": {
    "addr:full":"Elise Lehner-Weg 5 Gallneukirchen Ober\u00f6sterreich 4210",
    "addr:housenumber":"5",
    "addr:postcode":"4210",
    "addr:street":"Lehner-Weg;Oberoesterreich",
    "iso:country":"AT",
    "sg:address":"Elise Lehner-Weg 5",
    "sg:city":"Gallneukirchen",
    "sg:orig_category":"Tankstellen",
    "sg:phone":"+43 7235 63806",
    "sg:postcode":"4210",
    "sg:province":"Ober\u00f6sterreich",
    "wof:name":"S D C Service- und Distributionscenter GmbH",
    "wof:placetype":"venue"
},
  "geometry": {"coordinates":[14.4095087051,48.350479126],"type":"Point"}
}