{
  "type": "Feature",
  "properties": {
    "addr:full":"Halleiner Landesstrasse 30 Puch Salzburg 5412",
    "addr:housenumber":"30",
    "addr:postcode":"5412",
    "addr:street":"Halleiner Landesstrasse;Salzburg",
    "iso:country":"AT",
    "sg:address":"Halleiner Landesstrasse 30",
    "sg:city":"Puch",
    "sg:classifiers":[
        {
            "category":"Government",
            "subcategory":"Department Of Motor Vehicles",
            "type":"Public Place"
        }
    ],
    "sg:phone":"+43 6245 83258",
    "sg:postcode":"5412",
    "sg:province":"Salzburg",
    "sg:tags":[
        "truck",
        "purpose"
    ],
    "wof:name":"Anton Perlinger Transportunternehmen",
    "wof:placetype":"venue"
},
  "geometry": {"coordinates":[13.0907640457,47.7168502808],"type":"Point"}
}