{
  "type": "Feature",
  "properties": {
    "addr:full":"Wiener Str 27 Petzenkirchen Nieder\u00f6sterreich 3252",
    "addr:postcode":"3252",
    "addr:street":"Niederoesterreich",
    "iso:country":"AT",
    "sg:address":"Wiener Str 27",
    "sg:city":"Petzenkirchen",
    "sg:orig_category":"Erdarbeiten",
    "sg:phone":"+43 4367 684338620",
    "sg:postcode":"3252",
    "sg:province":"Nieder\u00f6sterreich",
    "wof:name":"Rauner GesmbH",
    "wof:placetype":"venue"
},
  "geometry": {"coordinates":[15.1548547745,48.1444473267],"type":"Point"}
}