{
  "type": "Feature",
  "properties": {
    "addr:full":"Sendlweg 7b Salzburg Salzburg 5020",
    "addr:housenumber":"7b",
    "addr:postcode":"5020",
    "addr:street":"Sendlweg;Salzburg",
    "iso:country":"AT",
    "sg:address":"Sendlweg 7b",
    "sg:city":"Salzburg",
    "sg:orig_category":"Werbegestalter",
    "sg:phone":"+43 662 830013",
    "sg:postcode":"5020",
    "sg:province":"Salzburg",
    "wof:name":"Acryltechnik Steinacher GesmbH & Co KG",
    "wof:placetype":"venue"
},
  "geometry": {"coordinates":[13.0163841248,47.7715911865],"type":"Point"}
}