{
  "type": "Feature",
  "properties": {
    "addr:full":"Salzburger Str 14 St. Johann in Tirol Tirol 6380",
    "addr:housenumber":"14",
    "addr:postcode":"6380",
    "addr:street":"Salzburger Str;Tirol",
    "iso:country":"AT",
    "sg:address":"Salzburger Str 14",
    "sg:city":"St. Johann in Tirol",
    "sg:orig_category":"Rettungsdienste",
    "sg:phone":"+43 5352 621550",
    "sg:postcode":"6380",
    "sg:province":"Tirol",
    "wof:name":"Rotes Kreuz \u00d6sterr Ortsstelle St Johann",
    "wof:placetype":"venue"
},
  "geometry": {"coordinates":[12.4232492447,47.5246162415],"type":"Point"}
}