{
  "type": "Feature",
  "properties": {
    "iso:country":"AT",
    "sg:address":"Wienerbergstr 28",
    "sg:city":"Wien",
    "sg:orig_category":"Blumeneinzelhandel",
    "sg:phone":"+43 1 8157322",
    "sg:postcode":"1120",
    "sg:province":"Wien",
    "wof:name":"Nadja's Blumenzauber",
    "wof:placetype":"venue"
},
  "geometry": {"coordinates":[16.3317222595,48.1717185974],"type":"Point"}
}