{
  "type": "Feature",
  "properties": {
    "addr:full":"Gu\u00dfhausstr 25-29 Wien Wien 1040",
    "addr:postcode":"25-29;1040",
    "iso:country":"AT",
    "sg:address":"Gu\u00dfhausstr 25-29",
    "sg:city":"Wien",
    "sg:orig_category":"Institute",
    "sg:phone":"+43 4315 880136601",
    "sg:postcode":"1040",
    "sg:province":"Wien",
    "wof:name":"Institut f Sensor- u Aktuatorsysteme",
    "wof:placetype":"venue"
},
  "geometry": {"coordinates":[16.3671455383,48.1940345764],"type":"Point"}
}