{
  "type": "Feature",
  "properties": {
    "addr:full":"Nr 12 Maria Taferl Nieder\u00f6sterreich 3672",
    "addr:postcode":"3672",
    "addr:street":"Nr;Maria",
    "iso:country":"AT",
    "sg:address":"Nr 12",
    "sg:city":"Maria Taferl",
    "sg:orig_category":"Friseure U Frisiersalons",
    "sg:phone":"+43 4374 136707",
    "sg:postcode":"3672",
    "sg:province":"Nieder\u00f6sterreich",
    "wof:name":"Fris\u00f6r - FOR YOU",
    "wof:placetype":"venue"
},
  "geometry": {"coordinates":[15.1574277878,48.2252922058],"type":"Point"}
}