{
  "type": "Feature",
  "properties": {
    "iso:country":"AT",
    "sg:address":"Sepp Innerkofler-Str 8",
    "sg:city":"Lienz",
    "sg:orig_category":"Freizeit- U Sportbekleidung",
    "sg:phone":"+43 4348 5271706",
    "sg:postcode":"9900",
    "sg:province":"Tirol",
    "wof:name":"Body & Fashion Shop",
    "wof:placetype":"venue"
},
  "geometry": {"coordinates":[12.7616062164,46.8253097534],"type":"Point"}
}