{
  "type": "Feature",
  "properties": {
    "addr:full":"Nr 88 Himmelberg K\u00e4rnten 9562",
    "addr:postcode":"9562",
    "addr:street":"Nr;Himmelberg Kaernten",
    "iso:country":"AT",
    "sg:address":"Nr 88",
    "sg:city":"Himmelberg",
    "sg:orig_category":"Tischlereien",
    "sg:phone":"+43 4276 2686",
    "sg:postcode":"9562",
    "sg:province":"K\u00e4rnten",
    "wof:name":"Gattol Josef",
    "wof:placetype":"venue"
},
  "geometry": {"coordinates":[14.0372676849,46.7478256226],"type":"Point"}
}