{
  "type": "Feature",
  "properties": {
    "addr:full":"Itzlinger Hauptstr 89a Salzburg Salzburg 5020",
    "addr:housenumber":"89a",
    "addr:postcode":"5020",
    "addr:street":"Itzlinger Hauptstr;Salzburg",
    "iso:country":"AT",
    "sg:address":"Itzlinger Hauptstr 89a",
    "sg:city":"Salzburg",
    "sg:orig_category":"Tabaktrafiken",
    "sg:phone":"+43 662 450798",
    "sg:postcode":"5020",
    "sg:province":"Salzburg",
    "wof:name":"Weiss Klaus Ing",
    "wof:placetype":"venue"
},
  "geometry": {"coordinates":[13.0381317139,47.8254508972],"type":"Point"}
}