{
  "type": "Feature",
  "properties": {
    "addr:full":"Hainburgerstr. 34a Wien Wien 1030",
    "addr:housenumber":"34a",
    "addr:postcode":"1030",
    "addr:street":"Hainburgerstr.",
    "iso:country":"AT",
    "sg:address":"Hainburgerstr. 34a",
    "sg:city":"Wien",
    "sg:classifiers":[
        {
            "category":"Manufacturing",
            "subcategory":"Paper Products",
            "type":"Manufacturing & Wholesale Goods"
        }
    ],
    "sg:phone":"+43 4317 127090",
    "sg:postcode":"1030",
    "sg:province":"Wien",
    "sg:tags":[
        "cardboard"
    ],
    "wof:name":"POLO AG",
    "wof:placetype":"venue"
},
  "geometry": {"coordinates":[16.395734787,48.1998901367],"type":"Point"}
}