{
  "type": "Feature",
  "properties": {
    "iso:country":"AT",
    "sg:address":"Wiener Str 22",
    "sg:city":"Oberwart",
    "sg:orig_category":"Tischlereien",
    "sg:phone":"+43 3352 33981",
    "sg:postcode":"7400",
    "sg:province":"Burgenland",
    "wof:name":"Bencsics Dieter GmbH Planungsstudio",
    "wof:placetype":"venue"
},
  "geometry": {"coordinates":[16.2081222534,47.2908325195],"type":"Point"}
}