{
  "type": "Feature",
  "properties": {
    "iso:country":"AT",
    "sg:address":"Bahnhofstr 7",
    "sg:city":"Micheldorf in Ober\u00f6sterreich",
    "sg:orig_category":"Reifen U Reifendienste",
    "sg:phone":"+43 4375 8261002",
    "sg:postcode":"4563",
    "sg:province":"Ober\u00f6sterreich",
    "wof:name":"Reifen Wondraschek GesmbH",
    "wof:placetype":"venue"
},
  "geometry": {"coordinates":[14.1281375885,47.8808517456],"type":"Point"}
}