{
  "type": "Feature",
  "properties": {
    "addr:full":"Markt 54 Kuchl Salzburg 5431",
    "addr:housenumber":"54",
    "addr:postcode":"5431",
    "addr:street":"Markt;Salzburg",
    "iso:country":"AT",
    "sg:address":"Markt 54",
    "sg:city":"Kuchl",
    "sg:orig_category":"Volksschulen",
    "sg:phone":"+43 6244 6250",
    "sg:postcode":"5431",
    "sg:province":"Salzburg",
    "wof:name":"Volksschule",
    "wof:placetype":"venue"
},
  "geometry": {"coordinates":[13.1441526413,47.6261138916],"type":"Point"}
}