{
  "type": "Feature",
  "properties": {
    "iso:country":"AT",
    "sg:address":"Rohrerstr 35",
    "sg:city":"Zell am Ziller",
    "sg:orig_category":"Pensionen / Privatzimmer",
    "sg:phone":"+43 5282 7169",
    "sg:postcode":"6280",
    "sg:province":"Tirol",
    "wof:name":"Pension Rohrmoser",
    "wof:placetype":"venue"
},
  "geometry": {"coordinates":[11.8893575668,47.235332489],"type":"Point"}
}