{
  "type": "Feature",
  "properties": {
    "iso:country":"AT",
    "sg:address":"Draschestr 94",
    "sg:city":"Wien",
    "sg:orig_category":"Bauunternehmen",
    "sg:phone":"+43 1 6174643",
    "sg:postcode":"1230",
    "sg:province":"Wien",
    "wof:name":"SANIER TECHNIK BaugmbH",
    "wof:placetype":"venue"
},
  "geometry": {"coordinates":[16.3484153748,48.1496162415],"type":"Point"}
}