{
  "type": "Feature",
  "properties": {
    "addr:full":"Walser Str 28 Riezlern Vorarlberg 6991",
    "addr:postcode":"6991",
    "addr:street":"Str 28",
    "iso:country":"AT",
    "sg:address":"Walser Str 28",
    "sg:city":"Riezlern",
    "sg:orig_category":"Pensionen / Privatzimmer",
    "sg:phone":"+43 4355 175206",
    "sg:postcode":"6991",
    "sg:province":"Vorarlberg",
    "wof:name":"Haus Kasimir",
    "wof:placetype":"venue"
},
  "geometry": {"coordinates":[10.1899766922,47.3596305847],"type":"Point"}
}