{
  "type": "Feature",
  "properties": {
    "addr:full":"Nr 460/1 Warth Nieder\u00f6sterreich 2831",
    "addr:housenumber":"1",
    "addr:postcode":"2831",
    "addr:street":"Nr 460 /",
    "iso:country":"AT",
    "sg:address":"Nr 460/1",
    "sg:city":"Warth",
    "sg:orig_category":"Quarz U Quarzsand",
    "sg:phone":"+43 4326 297223",
    "sg:postcode":"2831",
    "sg:province":"Nieder\u00f6sterreich",
    "wof:name":"Quarzit-Sandwerke Feichtinger GesmbH & Co KG",
    "wof:placetype":"venue"
},
  "geometry": {"coordinates":[166.9221496582,-0.5282999873],"type":"Point"}
}