{
  "type": "Feature",
  "properties": {
    "iso:country":"AT",
    "sg:address":"H\u00e4gelingasse 4-6",
    "sg:city":"Wien",
    "sg:orig_category":"Basketware",
    "sg:phone":"+43 1 981890",
    "sg:postcode":"1140",
    "sg:province":"Wien",
    "sg:website":"braille.at",
    "wof:name":"\u00d6sterr. Blinden- und Sehbehindertenverband Landesgruppe Wien, N\u00d6 und Bgld.",
    "wof:placetype":"venue"
},
  "geometry": {"coordinates":[16.3081245422,48.1993865967],"type":"Point"}
}