{
  "type": "Feature",
  "properties": {
    "addr:full":"Widerhofergasse 4 Wien Wien 1090",
    "addr:housenumber":"4",
    "addr:postcode":"1090",
    "addr:street":"Widerhofergasse",
    "iso:country":"AT",
    "sg:address":"Widerhofergasse 4",
    "sg:city":"Wien",
    "sg:classifiers":[
        {
            "category":"Health Services",
            "subcategory":"Clinic",
            "type":"Services"
        }
    ],
    "sg:phone":"+43 1 31732260",
    "sg:postcode":"1090",
    "sg:province":"Wien",
    "sg:tags":[
        "joint",
        "articulated"
    ],
    "sg:website":"schuetz.at",
    "wof:name":"Arthur Sch\u00fctz & Co",
    "wof:placetype":"venue"
},
  "geometry": {"coordinates":[16.354385376,48.2230873108],"type":"Point"}
}