{
  "type": "Feature",
  "properties": {
    "addr:full":"Ahornstr 857 Mayrhofen Tirol 6290",
    "addr:housenumber":"857",
    "addr:postcode":"6290",
    "addr:street":"Mayrhofen Tirol",
    "iso:country":"AT",
    "sg:address":"Ahornstr 857",
    "sg:city":"Mayrhofen",
    "sg:orig_category":"Textilreinigung",
    "sg:phone":"+43 5285 62981",
    "sg:postcode":"6290",
    "sg:province":"Tirol",
    "wof:name":"Pico bello Inh Georg Dielacher",
    "wof:placetype":"venue"
},
  "geometry": {"coordinates":[11.8612279892,47.1614761353],"type":"Point"}
}