{
  "type": "Feature",
  "properties": {
    "addr:full":"P\u00f6tschnerg 36 Baden Nieder\u00f6sterreich 2500",
    "addr:housenumber":"36",
    "addr:postcode":"2500",
    "addr:street":"Poetschnerg;Niederoesterreich",
    "iso:country":"AT",
    "sg:address":"P\u00f6tschnerg 36",
    "sg:city":"Baden",
    "sg:orig_category":"Non-Classified Establishments",
    "sg:phone":"+43 2252 44906",
    "sg:postcode":"2500",
    "sg:province":"Nieder\u00f6sterreich",
    "wof:name":"Schweitzer Gerd",
    "wof:placetype":"venue"
},
  "geometry": {"coordinates":[16.2145595551,47.9845733643],"type":"Point"}
}