{
  "type": "Feature",
  "properties": {
    "addr:full":"Mauthausener Str 4 St. Georgen an der Gusen Ober\u00f6sterreich 4222",
    "addr:housenumber":"4",
    "addr:postcode":"4222",
    "addr:street":"Str",
    "iso:country":"AT",
    "sg:address":"Mauthausener Str 4",
    "sg:city":"St. Georgen an der Gusen",
    "sg:orig_category":"Heurigen / Buschenschank",
    "sg:phone":"+43 4372 3763131",
    "sg:postcode":"4222",
    "sg:province":"Ober\u00f6sterreich",
    "wof:name":"Stopplziaga",
    "wof:placetype":"venue"
},
  "geometry": {"coordinates":[14.4493637085,48.271812439],"type":"Point"}
}