{
  "type": "Feature",
  "properties": {
    "addr:full":"Aub\u00f6ckpl 13 Bad Ischl Ober\u00f6sterreich 4820",
    "addr:housenumber":"13",
    "addr:postcode":"4820",
    "addr:street":"Auboeckpl",
    "iso:country":"AT",
    "sg:address":"Aub\u00f6ckpl 13",
    "sg:city":"Bad Ischl",
    "sg:orig_category":"Geschenkartikel",
    "sg:phone":"+43 6132 24018",
    "sg:postcode":"4820",
    "sg:province":"Ober\u00f6sterreich",
    "wof:name":"Paper Box Vertriebs GmbH",
    "wof:placetype":"venue"
},
  "geometry": {"coordinates":[13.6226682663,47.7109718323],"type":"Point"}
}