{
  "type": "Feature",
  "properties": {
    "addr:full":"Hauptstr 90 Reichenau an der Rax Nieder\u00f6sterreich 2651",
    "addr:housenumber":"90",
    "addr:postcode":"2651",
    "addr:street":"Hauptstr",
    "iso:country":"AT",
    "sg:address":"Hauptstr 90",
    "sg:city":"Reichenau an der Rax",
    "sg:classifiers":[
        {
            "category":"Restaurant",
            "type":"Food & Drink"
        }
    ],
    "sg:phone":"+43 2666 55361",
    "sg:postcode":"2651",
    "sg:province":"Nieder\u00f6sterreich",
    "sg:tags":[
        "pizzeria"
    ],
    "wof:name":"Pizzeria Luigi",
    "wof:placetype":"venue"
},
  "geometry": {"coordinates":[15.8369703293,47.6980552673],"type":"Point"}
}