{
  "type": "Feature",
  "properties": {
    "addr:full":"Rosaliastr 90 Bad Erlach Nieder\u00f6sterreich 2822",
    "addr:housenumber":"90",
    "addr:postcode":"2822",
    "addr:street":"Rosaliastr",
    "iso:country":"AT",
    "sg:address":"Rosaliastr 90",
    "sg:city":"Bad Erlach",
    "sg:orig_category":"Spenglereien",
    "sg:phone":"+43 2627 46363",
    "sg:postcode":"2822",
    "sg:province":"Nieder\u00f6sterreich",
    "wof:name":"Binder Johann",
    "wof:placetype":"venue"
},
  "geometry": {"coordinates":[16.2261257172,47.7260856628],"type":"Point"}
}