{
  "type": "Feature",
  "properties": {
    "addr:full":"Zehnerg\u00fcrtel 12-24/1. OG/Fischapark Wiener Neustadt Nieder\u00f6sterreich 2700",
    "addr:housenumber":"12-24 / 1 og",
    "addr:postcode":"2700",
    "addr:street":"Niederoesterreich",
    "iso:country":"AT",
    "sg:address":"Zehnerg\u00fcrtel 12-24/1. OG/Fischapark",
    "sg:city":"Wiener Neustadt",
    "sg:orig_category":"Telekommunikation",
    "sg:phone":"+43 800 664300",
    "sg:postcode":"2700",
    "sg:province":"Nieder\u00f6sterreich",
    "wof:name":"A1-Shop Wiener Neustadt",
    "wof:placetype":"venue"
},
  "geometry": {"coordinates":[16.2455158234,47.8128814697],"type":"Point"}
}