{
  "type": "Feature",
  "properties": {
    "iso:country":"AT",
    "sg:address":"Garnisong 10",
    "sg:city":"Wien",
    "sg:orig_category":"Lebensmittel / Erzeugung U Gro\u00c3\u0178handel",
    "sg:phone":"+43 1 4089433",
    "sg:postcode":"1090",
    "sg:province":"Wien",
    "wof:name":"Paprika Hatschek GesmbH",
    "wof:placetype":"venue"
},
  "geometry": {"coordinates":[16.3569602966,48.215927124],"type":"Point"}
}