{
  "type": "Feature",
  "properties": {
    "addr:full":"Mariatroster Str 239 Mariatrost Steiermark 8044",
    "addr:housenumber":"239",
    "addr:postcode":"8044",
    "iso:country":"AT",
    "sg:address":"Mariatroster Str 239",
    "sg:city":"Mariatrost",
    "sg:orig_category":"Lebensmittel / Einzelhandel",
    "sg:phone":"+43 316 393336",
    "sg:postcode":"8044",
    "sg:province":"Steiermark",
    "wof:name":"MONDO Lebensmitteldiskonter",
    "wof:placetype":"venue"
},
  "geometry": {"coordinates":[15.4809732437,47.1019134521],"type":"Point"}
}