{
  "type": "Feature",
  "properties": {
    "addr:full":"Khleslpl 1 Wien Wien 1120",
    "addr:housenumber":"1",
    "addr:postcode":"1120",
    "addr:street":"Khleslpl",
    "iso:country":"AT",
    "sg:address":"Khleslpl 1",
    "sg:city":"Wien",
    "sg:orig_category":"Alarmanlagen U Sicherheitssysteme",
    "sg:phone":"+43 4318 0487010",
    "sg:postcode":"1120",
    "sg:province":"Wien",
    "wof:name":"Laubender GesmbH",
    "wof:placetype":"venue"
},
  "geometry": {"coordinates":[16.3225479126,48.1629333496],"type":"Point"}
}