{
  "type": "Feature",
  "properties": {
    "addr:full":"Rudolf-Kunst-G 20a Linz Ober\u00f6sterreich 4030",
    "addr:housenumber":"20a",
    "addr:postcode":"4030",
    "addr:street":"Rudolf-Kunst-G",
    "iso:country":"AT",
    "sg:address":"Rudolf-Kunst-G 20a",
    "sg:city":"Linz",
    "sg:orig_category":"Biologische Produkte",
    "sg:phone":"+43 4366 01606660",
    "sg:postcode":"4030",
    "sg:province":"Ober\u00f6sterreich",
    "wof:name":"Stangl Alexandra - BabysNature",
    "wof:placetype":"venue"
},
  "geometry": {"coordinates":[14.3270282745,48.2371025085],"type":"Point"}
}