{
  "type": "Feature",
  "properties": {
    "iso:country":"AT",
    "sg:address":"Gaadner Str 5d",
    "sg:city":"Hinterbr\u00fchl",
    "sg:classifiers":[
        {
            "category":"Taxi",
            "type":"Transportation"
        }
    ],
    "sg:phone":"+43 4322 3653500",
    "sg:postcode":"2371",
    "sg:province":"Nieder\u00f6sterreich",
    "sg:tags":[
        "personentransporte",
        "u"
    ],
    "wof:name":"Taxi Petermair",
    "wof:placetype":"venue"
},
  "geometry": {"coordinates":[16.2340278625,48.0803947449],"type":"Point"}
}