{
  "type": "Feature",
  "properties": {
    "addr:full":"Glockeng 1 Wien Wien 1020",
    "addr:housenumber":"1",
    "addr:postcode":"1020",
    "addr:street":"Glockeng",
    "iso:country":"AT",
    "sg:address":"Glockeng 1",
    "sg:city":"Wien",
    "sg:orig_category":"Immobilienverwaltungen",
    "sg:phone":"+43 1 21402110",
    "sg:postcode":"1020",
    "sg:province":"Wien",
    "wof:name":"Roschka Ewald GesmbH",
    "wof:placetype":"venue"
},
  "geometry": {"coordinates":[16.3811721802,48.2173156738],"type":"Point"}
}