{
  "type": "Feature",
  "properties": {
    "addr:full":"Loibacher Str 26 Bleiburg K\u00e4rnten 9150",
    "addr:housenumber":"26",
    "addr:postcode":"9150",
    "addr:street":"Str;Kaernten",
    "iso:country":"AT",
    "sg:address":"Loibacher Str 26",
    "sg:city":"Bleiburg",
    "sg:orig_category":"Autohandel",
    "sg:phone":"+43 4235 3580",
    "sg:postcode":"9150",
    "sg:province":"K\u00e4rnten",
    "wof:name":"Slanitsch Gottfried",
    "wof:placetype":"venue"
},
  "geometry": {"coordinates":[14.798119545,46.5817146301],"type":"Point"}
}