{
  "type": "Feature",
  "properties": {
    "iso:country":"AT",
    "sg:address":"Kirchenpl 6",
    "sg:city":"Aspang-Markt",
    "sg:orig_category":"Non-Classified Establishments",
    "sg:phone":"+43 2642 52209",
    "sg:postcode":"2870",
    "sg:province":"Nieder\u00f6sterreich",
    "wof:name":"Pfarramt Ober-Aspang",
    "wof:placetype":"venue"
},
  "geometry": {"coordinates":[16.0917396545,47.5551300049],"type":"Point"}
}