{
  "type": "Feature",
  "properties": {
    "addr:full":"Stadtpl 35 Klosterneuburg Nieder\u00f6sterreich 3400",
    "addr:housenumber":"35",
    "addr:postcode":"3400",
    "addr:street":"Stadtpl;Niederoesterreich",
    "iso:country":"AT",
    "sg:address":"Stadtpl 35",
    "sg:city":"Klosterneuburg",
    "sg:orig_category":"Fu\u00c3\u0178pflege U Fu\u00c3\u0178pflegesalons",
    "sg:phone":"+43 4322 4332575",
    "sg:postcode":"3400",
    "sg:province":"Nieder\u00f6sterreich",
    "wof:name":"Obermeissner Elfriede",
    "wof:placetype":"venue"
},
  "geometry": {"coordinates":[16.3231773376,48.3088111877],"type":"Point"}
}