{
  "type": "Feature",
  "properties": {
    "addr:full":"Sittich 4 Feldkirchen in K\u00e4rnten K\u00e4rnten 9560",
    "addr:housenumber":"4",
    "addr:postcode":"9560",
    "addr:street":"Sittich;Kaernten",
    "iso:country":"AT",
    "sg:address":"Sittich 4",
    "sg:city":"Feldkirchen in K\u00e4rnten",
    "sg:orig_category":"Pensionen / Privatzimmer",
    "sg:phone":"+43 4276 39104",
    "sg:postcode":"9560",
    "sg:province":"K\u00e4rnten",
    "wof:name":"Walker Johann",
    "wof:placetype":"venue"
},
  "geometry": {"coordinates":[14.1293039322,46.7057800293],"type":"Point"}
}