{
  "type": "Feature",
  "properties": {
    "iso:country":"AT",
    "sg:address":"Hauptpl 15",
    "sg:city":"Leibnitz",
    "sg:orig_category":"Bekleidung / Einzelhandel",
    "sg:phone":"+43 3452 71230",
    "sg:postcode":"8430",
    "sg:province":"Steiermark",
    "wof:name":"Pongratz Rudolf",
    "wof:placetype":"venue"
},
  "geometry": {"coordinates":[15.5396194458,46.7817649841],"type":"Point"}
}