{
  "type": "Feature",
  "properties": {
    "iso:country":"AT",
    "sg:address":"Hans-Taborsky-Str 2",
    "sg:city":"Gramatneusiedl",
    "sg:orig_category":"Bleche U Blechwaren",
    "sg:phone":"+43 4322 34740080",
    "sg:postcode":"2440",
    "sg:province":"Nieder\u00f6sterreich",
    "wof:name":"Taborsky VertriebsgesmbH & Co KG",
    "wof:placetype":"venue"
},
  "geometry": {"coordinates":[16.4830169678,48.0366287231],"type":"Point"}
}