{
  "type": "Feature",
  "properties": {
    "addr:full":"Zerzerhaus 28 Ried im Oberinntal Tirol 6531",
    "addr:housenumber":"28",
    "addr:postcode":"6531",
    "addr:street":"Zerzerhaus;Tirol",
    "iso:country":"AT",
    "sg:address":"Zerzerhaus 28",
    "sg:city":"Ried im Oberinntal",
    "sg:orig_category":"Physiotherapie",
    "sg:phone":"+43 4354 7220297",
    "sg:postcode":"6531",
    "sg:province":"Tirol",
    "wof:name":"Physiotherapie Ried Ltg Dipl PT Markus Hangl",
    "wof:placetype":"venue"
},
  "geometry": {"coordinates":[10.654545784,47.0553817749],"type":"Point"}
}