{
  "type": "Feature",
  "properties": {
    "addr:full":"Lindaustr 2 Fehring Steiermark 8350",
    "addr:housenumber":"2",
    "addr:postcode":"8350",
    "addr:street":"Lindaustr",
    "iso:country":"AT",
    "sg:address":"Lindaustr 2",
    "sg:city":"Fehring",
    "sg:orig_category":"Bauunternehmen",
    "sg:phone":"+43 4331 5523820",
    "sg:postcode":"8350",
    "sg:province":"Steiermark",
    "wof:name":"Pongratz Bau GesmbH",
    "wof:placetype":"venue"
},
  "geometry": {"coordinates":[16.021276474,46.9412117004],"type":"Point"}
}