{
  "type": "Feature",
  "properties": {
    "iso:country":"AT",
    "sg:address":"Grazer Str 2",
    "sg:city":"Stainz",
    "sg:classifiers":[
        {
            "category":"Travel",
            "subcategory":"Hotels & Motels",
            "type":"Entertainment"
        }
    ],
    "sg:phone":"+43 3463 21150",
    "sg:postcode":"8510",
    "sg:province":"Steiermark",
    "wof:name":"Stainzerhof",
    "wof:placetype":"venue"
},
  "geometry": {"coordinates":[15.2648105621,46.8945960999],"type":"Point"}
}