{
  "type": "Feature",
  "properties": {
    "addr:full":"Rosenegg 69 Fieberbrunn Tirol 6391",
    "addr:housenumber":"69",
    "addr:postcode":"6391",
    "addr:street":"Rosenegg;Tirol",
    "iso:country":"AT",
    "sg:address":"Rosenegg 69",
    "sg:city":"Fieberbrunn",
    "sg:orig_category":"Pensionen / Privatzimmer",
    "sg:phone":"+43 5354 56227",
    "sg:postcode":"6391",
    "sg:province":"Tirol",
    "wof:name":"Brunner Katharina",
    "wof:placetype":"venue"
},
  "geometry": {"coordinates":[12.5328598022,47.4859085083],"type":"Point"}
}