{
  "type": "Feature",
  "properties": {
    "iso:country":"AT",
    "sg:address":"Hollabrunner Str 1",
    "sg:city":"Hollabrunn",
    "sg:orig_category":"Gutsverwaltungen",
    "sg:phone":"+43 2952 24170",
    "sg:postcode":"2020",
    "sg:province":"Nieder\u00f6sterreich",
    "wof:name":"Sedlar Siegfried Ing",
    "wof:placetype":"venue"
},
  "geometry": {"coordinates":[16.0669784546,48.6014022827],"type":"Point"}
}