{
  "type": "Feature",
  "properties": {
    "addr:full":"Schulweg 5 St. Georgen an der Leys Nieder\u00f6sterreich 3282",
    "addr:housenumber":"5",
    "addr:postcode":"3282",
    "addr:street":"Schulweg",
    "iso:country":"AT",
    "sg:address":"Schulweg 5",
    "sg:city":"St. Georgen an der Leys",
    "sg:orig_category":"Volksschulen",
    "sg:phone":"+43 4374 8246204",
    "sg:postcode":"3282",
    "sg:province":"Nieder\u00f6sterreich",
    "wof:name":"Volksschule",
    "wof:placetype":"venue"
},
  "geometry": {"coordinates":[15.2266483307,48.0319633484],"type":"Point"}
}