{
  "type": "Feature",
  "properties": {
    "iso:country":"AT",
    "sg:address":"Neuwaldegger Str 18-18a",
    "sg:city":"Wien",
    "sg:orig_category":"Studentenheime",
    "sg:phone":"+43 1 488000",
    "sg:postcode":"1170",
    "sg:province":"Wien",
    "wof:name":"Tiroler Studentenheim",
    "wof:placetype":"venue"
},
  "geometry": {"coordinates":[16.288143158,48.2369499207],"type":"Point"}
}