{
  "type": "Feature",
  "properties": {
    "addr:full":"Fabriksg 7 Neunkirchen Nieder\u00f6sterreich 2620",
    "addr:housenumber":"7",
    "addr:postcode":"2620",
    "addr:street":"Fabriksg",
    "iso:country":"AT",
    "sg:address":"Fabriksg 7",
    "sg:city":"Neunkirchen",
    "sg:orig_category":"Restaurants: Italienisch",
    "sg:phone":"+43 2635 64957",
    "sg:postcode":"2620",
    "sg:province":"Nieder\u00f6sterreich",
    "wof:name":"Ristorante zum Italiener",
    "wof:placetype":"venue"
},
  "geometry": {"coordinates":[16.0823383331,47.7215080261],"type":"Point"}
}