{
  "type": "Feature",
  "properties": {
    "iso:country":"AT",
    "sg:address":"Fabriksg 7",
    "sg:city":"Neunkirchen",
    "sg:orig_category":"Restaurants: Italienisch",
    "sg:phone":"+43 2635 64957",
    "sg:postcode":"2620",
    "sg:province":"Nieder\u00f6sterreich",
    "wof:name":"Ristorante zum Italiener",
    "wof:placetype":"venue"
},
  "geometry": {"coordinates":[16.0823383331,47.7215080261],"type":"Point"}
}