{
  "type": "Feature",
  "properties": {
    "iso:country":"AT",
    "sg:address":"Kaiserstr 31",
    "sg:city":"Bregenz",
    "sg:orig_category":"Damenmoden",
    "sg:phone":"+43 5574 52171",
    "sg:postcode":"6900",
    "sg:province":"Vorarlberg",
    "wof:name":"Blue Handels GmbH",
    "wof:placetype":"venue"
},
  "geometry": {"coordinates":[9.7453794479,47.5035133362],"type":"Point"}
}