{
  "type": "Feature",
  "properties": {
    "iso:country":"AT",
    "sg:address":"Nr 37",
    "sg:city":"Altenburg",
    "sg:orig_category":"Autohandel",
    "sg:phone":"+43 2989 8267",
    "sg:postcode":"3591",
    "sg:province":"Nieder\u00f6sterreich",
    "wof:name":"Eisenhauer Robert",
    "wof:placetype":"venue"
},
  "geometry": {"coordinates":[15.5944595337,48.647315979],"type":"Point"}
}