{
  "type": "Feature",
  "properties": {
    "addr:full":"Egelseestr. 52/b Feldkirch Vorarlberg 6800",
    "addr:housenumber":"52 / b",
    "addr:postcode":"6800",
    "addr:street":"Egelseestr.",
    "iso:country":"AT",
    "sg:address":"Egelseestr. 52/b",
    "sg:city":"Feldkirch",
    "sg:orig_category":"Dienstleistungen, Sonstige Dienstleistungen",
    "sg:phone":"+43 4355 2232201",
    "sg:postcode":"6800",
    "sg:province":"Vorarlberg",
    "sg:website":"http://www.geiger-international.com/",
    "wof:name":"Geiger International Austria Emergency Humanitarian Aid",
    "wof:placetype":"venue"
},
  "geometry": {"coordinates":[9.5775699615,47.2391967773],"type":"Point"}
}