{
  "type": "Feature",
  "properties": {
    "addr:full":"Untere Hauptstr 27 St. Ruprecht an der Raab Steiermark 8181",
    "addr:housenumber":"27",
    "addr:postcode":"8181",
    "addr:street":"Untere Hauptstr",
    "iso:country":"AT",
    "sg:address":"Untere Hauptstr 27",
    "sg:city":"St. Ruprecht an der Raab",
    "sg:orig_category":"Gemeinden",
    "sg:phone":"+43 4331 7822180",
    "sg:postcode":"8181",
    "sg:province":"Steiermark",
    "wof:name":"Marktgemeinde St Ruprecht an der Raab",
    "wof:placetype":"venue"
},
  "geometry": {"coordinates":[15.6614179611,47.1615867615],"type":"Point"}
}