{
  "type": "Feature",
  "properties": {
    "addr:full":"Nr 330 W\u00f6rgl Tirol 6300",
    "addr:postcode":"6300",
    "addr:street":"Nr;Woergl Tirol",
    "iso:country":"AT",
    "sg:address":"Nr 330",
    "sg:city":"W\u00f6rgl",
    "sg:orig_category":"Musikgruppen",
    "sg:phone":"+43 4367 682563095",
    "sg:postcode":"6300",
    "sg:province":"Tirol",
    "wof:name":"Schlossberg Quintett",
    "wof:placetype":"venue"
},
  "geometry": {"coordinates":[12.1438121796,47.4709892273],"type":"Point"}
}