{
  "type": "Feature",
  "properties": {
    "addr:full":"Steyrer Str 47 Haag Nieder\u00f6sterreich 3350",
    "addr:postcode":"3350",
    "addr:street":"Str 47 Haag Niederoesterreich",
    "iso:country":"AT",
    "sg:address":"Steyrer Str 47",
    "sg:city":"Haag",
    "sg:orig_category":"Baumschulen",
    "sg:phone":"+43 7434 428350",
    "sg:postcode":"3350",
    "sg:province":"Nieder\u00f6sterreich",
    "wof:name":"Offenberger J\u00fcrgen",
    "wof:placetype":"venue"
},
  "geometry": {"coordinates":[14.5653495789,48.1121902466],"type":"Point"}
}