{
  "type": "Feature",
  "properties": {
    "addr:full":"Dorfstr 31 Leibnitz Steiermark 8430",
    "addr:housenumber":"31",
    "addr:postcode":"8430",
    "addr:street":"Dorfstr;Steiermark",
    "iso:country":"AT",
    "sg:address":"Dorfstr 31",
    "sg:city":"Leibnitz",
    "sg:orig_category":"Tore, Metallbau",
    "sg:phone":"+43 3452 860310",
    "sg:postcode":"8430",
    "sg:province":"Steiermark",
    "wof:name":"Holler - Tore Leibnitz",
    "wof:placetype":"venue"
},
  "geometry": {"coordinates":[15.5377645493,46.7811355591],"type":"Point"}
}