{
  "type": "Feature",
  "properties": {
    "addr:full":"Webergasse 9 Wien Wien 1200",
    "addr:housenumber":"9",
    "addr:postcode":"1200",
    "addr:street":"Webergasse",
    "iso:country":"AT",
    "sg:address":"Webergasse 9",
    "sg:city":"Wien",
    "sg:classifiers":[
        {
            "category":"Building & Trades",
            "subcategory":"Plumbing",
            "type":"Services"
        }
    ],
    "sg:phone":"+43 1 3306129",
    "sg:postcode":"1200",
    "sg:province":"Wien",
    "sg:tags":[
        "use",
        "ball",
        "chain"
    ],
    "sg:website":"armaturen-kosti.at",
    "wof:name":"Kosti Armaturen Handelsges.m.b.H. & Co KG",
    "wof:placetype":"venue"
},
  "geometry": {"coordinates":[16.3664226532,48.2290077209],"type":"Point"}
}