{
  "type": "Feature",
  "properties": {
    "addr:full":"B\u00f6hmdorf 7 Reichenthal Ober\u00f6sterreich 4193",
    "addr:housenumber":"7",
    "addr:postcode":"4193",
    "addr:street":"Boehmdorf",
    "iso:country":"AT",
    "sg:address":"B\u00f6hmdorf 7",
    "sg:city":"Reichenthal",
    "sg:orig_category":"Tischlereien",
    "sg:phone":"+43 7214 42320",
    "sg:postcode":"4193",
    "sg:province":"Ober\u00f6sterreich",
    "wof:name":"P\u00fchringer Tischlerei GmbH & Co KG",
    "wof:placetype":"venue"
},
  "geometry": {"coordinates":[14.3846139908,48.5433959961],"type":"Point"}
}