{
  "type": "Feature",
  "properties": {
    "iso:country":"AT",
    "sg:address":"Ressavarstr 4b",
    "sg:city":"Hartberg",
    "sg:orig_category":"Installationsunternehmen",
    "sg:phone":"+43 4333 32633700",
    "sg:postcode":"8230",
    "sg:province":"Steiermark",
    "sg:website":"krobath.com",
    "wof:name":"Krobath Ferdinand KG",
    "wof:placetype":"venue"
},
  "geometry": {"coordinates":[15.9662446976,47.2753868103],"type":"Point"}
}