{
  "type": "Feature",
  "properties": {
    "iso:country":"AT",
    "sg:address":"Habichen 30",
    "sg:city":"Oetz",
    "sg:orig_category":"Pensionen / Privatzimmer",
    "sg:phone":"+43 4352 526649",
    "sg:postcode":"6433",
    "sg:province":"Tirol",
    "wof:name":"Haus Almrausch",
    "wof:placetype":"venue"
},
  "geometry": {"coordinates":[10.9066972733,47.1899032593],"type":"Point"}
}