{
  "type": "Feature",
  "properties": {
    "addr:full":"Bernsteinstr 4 Hohenau an der March Nieder\u00f6sterreich 2273",
    "addr:housenumber":"4",
    "addr:postcode":"2273",
    "addr:street":"Bernsteinstr",
    "iso:country":"AT",
    "sg:address":"Bernsteinstr 4",
    "sg:city":"Hohenau an der March",
    "sg:orig_category":"Lebensmittel / Einzelhandel",
    "sg:phone":"+43 2535 3472",
    "sg:postcode":"2273",
    "sg:province":"Nieder\u00f6sterreich",
    "wof:name":"Billa AG",
    "wof:placetype":"venue"
},
  "geometry": {"coordinates":[16.9009399414,48.602897644],"type":"Point"}
}