{
  "type": "Feature",
  "properties": {
    "addr:full":"Jauerburgg. 25 Graz Steiermark 8010",
    "addr:housenumber":"25",
    "addr:postcode":"8010",
    "addr:street":"Jauerburgg.",
    "iso:country":"AT",
    "sg:address":"Jauerburgg. 25",
    "sg:city":"Graz",
    "sg:classifiers":[
        {
            "category":"Professional",
            "subcategory":"Engineering",
            "type":"Services"
        }
    ],
    "sg:phone":"+43 4331 6462140",
    "sg:postcode":"8010",
    "sg:province":"Steiermark",
    "sg:tags":[
        "machine",
        "-",
        "mechanical"
    ],
    "wof:name":"REPROTE AM HANSBAUER GES.MBH",
    "wof:placetype":"venue"
},
  "geometry": {"coordinates":[15.451880455,47.0512809753],"type":"Point"}
}