{
  "type": "Feature",
  "properties": {
    "addr:full":"Industriestrasse A6 Brunn am Gebirge Nieder\u00f6sterreich 2345",
    "addr:postcode":"2345",
    "addr:street":"Industriestrasse A6;Niederoesterreich",
    "iso:country":"AT",
    "sg:address":"Industriestrasse A6",
    "sg:city":"Brunn am Gebirge",
    "sg:classifiers":[
        {
            "category":"Banks & Credit Unions",
            "subcategory":"Investment Brokerage",
            "type":"Services"
        }
    ],
    "sg:phone":"+43 2236 3781000",
    "sg:postcode":"2345",
    "sg:province":"Nieder\u00f6sterreich",
    "sg:tags":[
        "fence"
    ],
    "sg:website":"toitoi.at",
    "wof:name":"TOI TOI Mobile Sanit\u00e4rsysteme Ges.m.b.H.",
    "wof:placetype":"venue"
},
  "geometry": {"coordinates":[16.2839355469,48.107170105],"type":"Point"}
}