{
  "type": "Feature",
  "properties": {
    "addr:full":"Premlechnerg 12 Wien Wien 1120",
    "addr:housenumber":"12",
    "addr:postcode":"1120",
    "addr:street":"Premlechnerg",
    "iso:country":"AT",
    "sg:address":"Premlechnerg 12",
    "sg:city":"Wien",
    "sg:orig_category":"Lebens- U Sozialberatung",
    "sg:phone":"+43 664 2603700",
    "sg:postcode":"1120",
    "sg:province":"Wien",
    "wof:name":"Lebensberatung S Manauschek",
    "wof:placetype":"venue"
},
  "geometry": {"coordinates":[16.3004436493,48.1687927246],"type":"Point"}
}