{
  "type": "Feature",
  "properties": {
    "addr:full":"Hauptpl 4 F\u00fcrstenfeld Steiermark 8280",
    "addr:housenumber":"4",
    "addr:postcode":"8280",
    "addr:street":"Hauptpl",
    "iso:country":"AT",
    "sg:address":"Hauptpl 4",
    "sg:city":"F\u00fcrstenfeld",
    "sg:orig_category":"Notare",
    "sg:phone":"+43 4333 82516510",
    "sg:postcode":"8280",
    "sg:province":"Steiermark",
    "sg:website":"notar-huber.at",
    "wof:name":"Huber Walter Dr",
    "wof:placetype":"venue"
},
  "geometry": {"coordinates":[16.0759105682,47.0514831543],"type":"Point"}
}