{
  "type": "Feature",
  "properties": {
    "addr:full":"Flirstr 25 Landeck Tirol 6500",
    "addr:housenumber":"25",
    "addr:postcode":"6500",
    "addr:street":"Flirstr;Tirol",
    "iso:country":"AT",
    "sg:address":"Flirstr 25",
    "sg:city":"Landeck",
    "sg:orig_category":"Lebensmittel / Einzelhandel",
    "sg:phone":"+43 4354 4263488",
    "sg:postcode":"6500",
    "sg:province":"Tirol",
    "wof:name":"Hofer KG",
    "wof:placetype":"venue"
},
  "geometry": {"coordinates":[10.6277132034,47.1200027466],"type":"Point"}
}