{
  "type": "Feature",
  "properties": {
    "iso:country":"AT",
    "sg:address":"Hauptstr 135",
    "sg:city":"Schattendorf",
    "sg:orig_category":"Tischlereien",
    "sg:phone":"+43 2686 2139",
    "sg:postcode":"7022",
    "sg:province":"Burgenland",
    "wof:name":"Pinter Johann",
    "wof:placetype":"venue"
},
  "geometry": {"coordinates":[16.5124759674,47.7124900818],"type":"Point"}
}