{
  "type": "Feature",
  "properties": {
    "iso:country":"AT",
    "sg:address":"Franz-Josef-Str 9",
    "sg:city":"Perchtoldsdorf",
    "sg:orig_category":"Biologische Produkte",
    "sg:phone":"+43 1 8650114",
    "sg:postcode":"2380",
    "sg:province":"Nieder\u00f6sterreich",
    "wof:name":"gwandstubn - Naturtextilien-Wellnessschuhe",
    "wof:placetype":"venue"
},
  "geometry": {"coordinates":[16.2671413422,48.1201400757],"type":"Point"}
}