{
  "type": "Feature",
  "properties": {
    "addr:full":"Kleindorf 7 Flattach K\u00e4rnten 9831",
    "addr:housenumber":"7",
    "addr:postcode":"9831",
    "addr:street":"Kleindorf;Kaernten",
    "iso:country":"AT",
    "sg:address":"Kleindorf 7",
    "sg:city":"Flattach",
    "sg:orig_category":"Pensionen / Privatzimmer",
    "sg:phone":"+43 4785 236",
    "sg:postcode":"9831",
    "sg:province":"K\u00e4rnten",
    "wof:name":"Pension Maier",
    "wof:placetype":"venue"
},
  "geometry": {"coordinates":[13.1141176224,46.9356651306],"type":"Point"}
}