{
  "type": "Feature",
  "properties": {
    "iso:country":"AT",
    "sg:address":"Karl-Tornay-G 28",
    "sg:city":"Wien",
    "sg:orig_category":"Lebensmittel / Einzelhandel",
    "sg:phone":"+43 1 6091712",
    "sg:postcode":"1230",
    "sg:province":"Wien",
    "wof:name":"MONDO Lebensmitteldiskonter",
    "wof:placetype":"venue"
},
  "geometry": {"coordinates":[16.3160800934,48.1319999695],"type":"Point"}
}