{
  "type": "Feature",
  "properties": {
    "addr:full":"Himmelpfortg 22 Wien Wien 1010",
    "addr:housenumber":"22",
    "addr:postcode":"1010",
    "addr:street":"Himmelpfortg",
    "iso:country":"AT",
    "sg:address":"Himmelpfortg 22",
    "sg:city":"Wien",
    "sg:orig_category":"Friseure U Frisiersalons",
    "sg:phone":"+43 4315 124413",
    "sg:postcode":"1010",
    "sg:province":"Wien",
    "wof:name":"2 for Hair Inh Krcsar Stefan",
    "wof:placetype":"venue"
},
  "geometry": {"coordinates":[16.3751487732,48.2046432495],"type":"Point"}
}