{
  "type": "Feature",
  "properties": {
    "addr:full":"Itter 480 Andelsbuch Vorarlberg 6866",
    "addr:housenumber":"480",
    "addr:postcode":"6866",
    "addr:street":"Itter",
    "iso:country":"AT",
    "sg:address":"Itter 480",
    "sg:city":"Andelsbuch",
    "sg:orig_category":"Pensionen / Privatzimmer",
    "sg:phone":"+43 5512 2149",
    "sg:postcode":"6866",
    "sg:province":"Vorarlberg",
    "wof:name":"G\u00e4stehaus Eichengrund",
    "wof:placetype":"venue"
},
  "geometry": {"coordinates":[9.8938789368,47.4094085693],"type":"Point"}
}