{
  "type": "Feature",
  "properties": {
    "addr:full":"Thomas-Ri\u00df-Weg 10 Stams Tirol 6422",
    "addr:housenumber":"10",
    "addr:postcode":"6422",
    "addr:street":"Thomas-Riss-Weg;Tirol",
    "iso:country":"AT",
    "sg:address":"Thomas-Ri\u00df-Weg 10",
    "sg:city":"Stams",
    "sg:orig_category":"Hauptschulen",
    "sg:phone":"+43 5263 6471",
    "sg:postcode":"6422",
    "sg:province":"Tirol",
    "wof:name":"Hauptschule",
    "wof:placetype":"venue"
},
  "geometry": {"coordinates":[10.9847640991,47.2760047913],"type":"Point"}
}