{
  "type": "Feature",
  "properties": {
    "addr:full":"Pergersee 6/7 Trausdorf an der Wulka Burgenland 7061",
    "addr:housenumber":"6 / 7",
    "addr:postcode":"7061",
    "addr:street":"Pergersee",
    "iso:country":"AT",
    "sg:address":"Pergersee 6/7",
    "sg:city":"Trausdorf an der Wulka",
    "sg:classifiers":[
        {
            "category":"Restaurant",
            "type":"Food & Drink"
        }
    ],
    "sg:phone":"+43 4326 8263190",
    "sg:postcode":"7061",
    "sg:province":"Burgenland",
    "sg:tags":[
        "pizzeria"
    ],
    "wof:name":"Pizza Oase",
    "wof:placetype":"venue"
},
  "geometry": {"coordinates":[16.5581493378,47.8141136169],"type":"Point"}
}