{
  "type": "Feature",
  "properties": {
    "addr:full":"Gymelsdorfer G 6 Wiener Neustadt Nieder\u00f6sterreich 2700",
    "addr:housenumber":"6",
    "addr:postcode":"2700",
    "addr:street":"Gymelsdorfer G",
    "iso:country":"AT",
    "sg:address":"Gymelsdorfer G 6",
    "sg:city":"Wiener Neustadt",
    "sg:orig_category":"Ingenieurkonsulenten / Zivilingenieure",
    "sg:phone":"+43 2622 236950",
    "sg:postcode":"2700",
    "sg:province":"Nieder\u00f6sterreich",
    "wof:name":"M\u00fcller Franz S Dipl-Ing Ziviltechniker GmbH",
    "wof:placetype":"venue"
},
  "geometry": {"coordinates":[16.2415904999,47.80626297],"type":"Point"}
}