{
  "type": "Feature",
  "properties": {
    "addr:full":"Niederachen 18 K\u00f6ssen Tirol 6345",
    "addr:housenumber":"18",
    "addr:postcode":"6345",
    "addr:street":"Niederachen;Tirol",
    "iso:country":"AT",
    "sg:address":"Niederachen 18",
    "sg:city":"K\u00f6ssen",
    "sg:orig_category":"Pensionen / Privatzimmer",
    "sg:phone":"+43 5375 6383",
    "sg:postcode":"6345",
    "sg:province":"Tirol",
    "wof:name":"Pension Aigner",
    "wof:placetype":"venue"
},
  "geometry": {"coordinates":[12.736749649,47.760848999],"type":"Point"}
}