{
  "type": "Feature",
  "properties": {
    "addr:full":"Kematen am Innbach 94 Kematen am Innbach Ober\u00f6sterreich 4633",
    "addr:housenumber":"94",
    "addr:postcode":"4633",
    "addr:street":"Kematen;Innbach",
    "iso:country":"AT",
    "sg:address":"Kematen am Innbach 94",
    "sg:city":"Kematen am Innbach",
    "sg:classifiers":[
        {
            "category":"Retail",
            "subcategory":"Auto Repair",
            "type":"Services"
        }
    ],
    "sg:phone":"+43 7247 8840",
    "sg:postcode":"4633",
    "sg:province":"Ober\u00f6sterreich",
    "sg:tags":[
        "car",
        "lacquer"
    ],
    "sg:website":"swcolor.de",
    "wof:name":"SW Color Lacke GmbH",
    "wof:placetype":"venue"
},
  "geometry": {"coordinates":[13.8624000549,48.176700592],"type":"Point"}
}