{
  "type": "Feature",
  "properties": {
    "iso:country":"AT",
    "sg:address":"Ungarstr 12",
    "sg:city":"Feldbach",
    "sg:classifiers":[
        {
            "category":"Travel",
            "subcategory":"Hotels & Motels",
            "type":"Entertainment"
        }
    ],
    "sg:phone":"+43 4331 5222050",
    "sg:postcode":"8330",
    "sg:province":"Steiermark",
    "wof:name":"Hotel Csejtei",
    "wof:placetype":"venue"
},
  "geometry": {"coordinates":[15.8905563354,46.9505691528],"type":"Point"}
}