{
  "type": "Feature",
  "properties": {
    "iso:country":"AT",
    "sg:address":"Wallnerstr 54",
    "sg:city":"Eichgraben",
    "sg:orig_category":"Steuerberatung",
    "sg:phone":"+43 4327 7344228",
    "sg:postcode":"3032",
    "sg:province":"Nieder\u00f6sterreich",
    "wof:name":"Foff Roman MMag Dr",
    "wof:placetype":"venue"
},
  "geometry": {"coordinates":[15.9835920334,48.1718025208],"type":"Point"}
}