{
  "type": "Feature",
  "properties": {
    "iso:country":"AT",
    "sg:address":"Hauptstr 45",
    "sg:city":"Wolkersdorf im Weinviertel",
    "sg:orig_category":"Elektroinstallationsunternehmen",
    "sg:phone":"+43 2245 203130",
    "sg:postcode":"2120",
    "sg:province":"Nieder\u00f6sterreich",
    "wof:name":"FEB Fahrleitungs und Elektrobau GmbH",
    "wof:placetype":"venue"
},
  "geometry": {"coordinates":[16.5238132477,48.3693504333],"type":"Point"}
}