{
  "type": "Feature",
  "properties": {
    "addr:full":"Schulweg 2 Kollerschlag Ober\u00f6sterreich 4154",
    "addr:housenumber":"2",
    "addr:postcode":"4154",
    "addr:street":"Schulweg",
    "iso:country":"AT",
    "sg:address":"Schulweg 2",
    "sg:city":"Kollerschlag",
    "sg:orig_category":"Volksschulen",
    "sg:phone":"+43 7287 8141",
    "sg:postcode":"4154",
    "sg:province":"Ober\u00f6sterreich",
    "wof:name":"Volksschule",
    "wof:placetype":"venue"
},
  "geometry": {"coordinates":[13.8412981033,48.6042289734],"type":"Point"}
}