{
  "type": "Feature",
  "properties": {
    "iso:country":"AT",
    "sg:address":"Gartenring 6",
    "sg:city":"Traismauer",
    "sg:orig_category":"Banken U Sparkassen",
    "sg:phone":"+43 4327 8362970",
    "sg:postcode":"3133",
    "sg:province":"Nieder\u00f6sterreich",
    "wof:name":"Sparkasse Traismauer",
    "wof:placetype":"venue"
},
  "geometry": {"coordinates":[15.7462873459,48.3505516052],"type":"Point"}
}