{
  "type": "Feature",
  "properties": {
    "addr:full":"Faschinastrasse 10 Th\u00fcringen Vorarlberg 6712",
    "addr:housenumber":"10",
    "addr:postcode":"6712",
    "addr:street":"Faschinastrasse",
    "iso:country":"AT",
    "sg:address":"Faschinastrasse 10",
    "sg:city":"Th\u00fcringen",
    "sg:orig_category":"ChildrenS Furniture",
    "sg:phone":"+43 5550 2214",
    "sg:postcode":"6712",
    "sg:province":"Vorarlberg",
    "sg:website":"tischlereistuchly.at",
    "wof:name":"Othmar Stuchly",
    "wof:placetype":"venue"
},
  "geometry": {"coordinates":[9.764840126,47.2014541626],"type":"Point"}
}