{
  "type": "Feature",
  "properties": {
    "addr:full":"Linzer Str 33 Linz Ober\u00f6sterreich 4040",
    "addr:housenumber":"33",
    "addr:postcode":"4040",
    "addr:street":"Linzer Str",
    "iso:country":"AT",
    "sg:address":"Linzer Str 33",
    "sg:city":"Linz",
    "sg:orig_category":"Psychotherapie",
    "sg:phone":"+43 732 252822",
    "sg:postcode":"4040",
    "sg:province":"Ober\u00f6sterreich",
    "wof:name":"Rittmannsberger Brigitte",
    "wof:placetype":"venue"
},
  "geometry": {"coordinates":[14.2993783951,48.3333244324],"type":"Point"}
}