{
  "type": "Feature",
  "properties": {
    "addr:full":"Krenglbacher Str 1 Krenglbach Ober\u00f6sterreich 4631",
    "addr:housenumber":"1",
    "addr:postcode":"4631",
    "addr:street":"Str",
    "iso:country":"AT",
    "sg:address":"Krenglbacher Str 1",
    "sg:city":"Krenglbach",
    "sg:orig_category":"Stra\u00c3\u0178enbau",
    "sg:phone":"+43 664 1221535",
    "sg:postcode":"4631",
    "sg:province":"Ober\u00f6sterreich",
    "wof:name":"LICHT & PLANUNG - Exl Ernst",
    "wof:placetype":"venue"
},
  "geometry": {"coordinates":[13.955406189,48.2055511475],"type":"Point"}
}