{
  "type": "Feature",
  "properties": {
    "addr:full":"Farbentalerweg 21 Fritzens Tirol 6122",
    "addr:housenumber":"21",
    "addr:postcode":"6122",
    "addr:street":"Farbentalerweg;Tirol",
    "iso:country":"AT",
    "sg:address":"Farbentalerweg 21",
    "sg:city":"Fritzens",
    "sg:orig_category":"Transportunternehmen",
    "sg:phone":"+43 5224 51832",
    "sg:postcode":"6122",
    "sg:province":"Tirol",
    "wof:name":"Bauhofer Hans",
    "wof:placetype":"venue"
},
  "geometry": {"coordinates":[11.5853767395,47.3069915771],"type":"Point"}
}