{
  "type": "Feature",
  "properties": {
    "iso:country":"AT",
    "sg:address":"Raiffeisenstr 5",
    "sg:city":"Munderfing",
    "sg:orig_category":"Banken U Sparkassen",
    "sg:phone":"+43 4377 446310",
    "sg:postcode":"5222",
    "sg:province":"Ober\u00f6sterreich",
    "wof:name":"Raiffeisenbank Mattigtal regGenmbH",
    "wof:placetype":"venue"
},
  "geometry": {"coordinates":[13.1820926666,48.06508255],"type":"Point"}
}