{
  "type": "Feature",
  "properties": {
    "iso:country":"AT",
    "sg:address":"Am Marbach 193",
    "sg:city":"Sittendorf",
    "sg:orig_category":"Abfallentsorgung U -Verwertung",
    "sg:phone":"+43 4322 3720771",
    "sg:postcode":"2393",
    "sg:province":"Nieder\u00f6sterreich",
    "wof:name":"Gemeinde Wienerwald - Altstoffsammelzentrum und Bauhof",
    "wof:placetype":"venue"
},
  "geometry": {"coordinates":[16.1902313232,48.074596405],"type":"Point"}
}