{
  "type": "Feature",
  "properties": {
    "addr:full":"Bahnstr 2a Gramatneusiedl Nieder\u00f6sterreich 2440",
    "addr:housenumber":"2a",
    "addr:postcode":"2440",
    "addr:street":"Bahnstr",
    "iso:country":"AT",
    "sg:address":"Bahnstr 2a",
    "sg:city":"Gramatneusiedl",
    "sg:orig_category":"Gemeinden",
    "sg:phone":"+43 2234 722050",
    "sg:postcode":"2440",
    "sg:province":"Nieder\u00f6sterreich",
    "wof:name":"Gemeindeamt Gramatneusiedl",
    "wof:placetype":"venue"
},
  "geometry": {"coordinates":[16.4901771545,48.0292549133],"type":"Point"}
}