{
  "type": "Feature",
  "properties": {
    "iso:country":"AT",
    "sg:address":"Triester Str 22",
    "sg:city":"Neunkirchen",
    "sg:orig_category":"Fleischhauereien",
    "sg:phone":"+43 2635 65322",
    "sg:postcode":"2620",
    "sg:province":"Nieder\u00f6sterreich",
    "wof:name":"Zinschitz Franz",
    "wof:placetype":"venue"
},
  "geometry": {"coordinates":[16.0783119202,47.7189407349],"type":"Point"}
}