{
  "type": "Feature",
  "properties": {
    "iso:country":"AT",
    "sg:address":"Grillenweg 13",
    "sg:city":"Linz",
    "sg:orig_category":"Tauchsportschulen U -Vereine",
    "sg:phone":"+43 732 309315",
    "sg:postcode":"4030",
    "sg:province":"Ober\u00f6sterreich",
    "wof:name":"Kissler Josef - Tauchschule ATLANTIS",
    "wof:placetype":"venue"
},
  "geometry": {"coordinates":[14.30493927,48.2528991699],"type":"Point"}
}