{
  "type": "Feature",
  "properties": {
    "addr:full":"Hagenstr 20 Linz Ober\u00f6sterreich 4040",
    "addr:housenumber":"20",
    "addr:postcode":"4040",
    "addr:street":"Hagenstr",
    "iso:country":"AT",
    "sg:address":"Hagenstr 20",
    "sg:city":"Linz",
    "sg:orig_category":"Unternehmensberatung",
    "sg:phone":"+43 732 738341",
    "sg:postcode":"4040",
    "sg:province":"Ober\u00f6sterreich",
    "sg:website":"catro.at",
    "wof:name":"Catro BetriebsberatungsgesmbH",
    "wof:placetype":"venue"
},
  "geometry": {"coordinates":[14.2711896896,48.3113822937],"type":"Point"}
}