{
  "type": "Feature",
  "properties": {
    "addr:full":"H\u00f6rndl 54 Ostermiething Ober\u00f6sterreich 5121",
    "addr:housenumber":"54",
    "addr:postcode":"5121",
    "addr:street":"Hoerndl",
    "iso:country":"AT",
    "sg:address":"H\u00f6rndl 54",
    "sg:city":"Ostermiething",
    "sg:classifiers":[
        {
            "category":"Home & Garden",
            "subcategory":"Household Appliances",
            "type":"Retail Goods"
        }
    ],
    "sg:phone":"+43 6278 8747",
    "sg:postcode":"5121",
    "sg:province":"Ober\u00f6sterreich",
    "sg:tags":[
        "electric"
    ],
    "wof:name":"Norbert Schuster Elektrotechnik",
    "wof:placetype":"venue"
},
  "geometry": {"coordinates":[12.8289651871,48.0465812683],"type":"Point"}
}