{
  "type": "Feature",
  "properties": {
    "addr:full":"Feldbacher Str 2 Gleisdorf Steiermark 8200",
    "addr:housenumber":"2",
    "addr:postcode":"8200",
    "addr:street":"Str",
    "iso:country":"AT",
    "sg:address":"Feldbacher Str 2",
    "sg:city":"Gleisdorf",
    "sg:orig_category":"Biologische Produkte",
    "sg:phone":"+43 3112 36666",
    "sg:postcode":"8200",
    "sg:province":"Steiermark",
    "wof:name":"Bio-Laden Mona Gratzer",
    "wof:placetype":"venue"
},
  "geometry": {"coordinates":[15.7145938873,47.1017074585],"type":"Point"}
}