{
  "type": "Feature",
  "properties": {
    "addr:full":"Taxerweg 15 Radstadt Salzburg 5550",
    "addr:housenumber":"15",
    "addr:postcode":"5550",
    "addr:street":"Taxerweg;Salzburg",
    "iso:country":"AT",
    "sg:address":"Taxerweg 15",
    "sg:city":"Radstadt",
    "sg:orig_category":"Appartements / Ferienwohnungen",
    "sg:phone":"+43 6452 75320",
    "sg:postcode":"5550",
    "sg:province":"Salzburg",
    "wof:name":"Kleintaxerhof",
    "wof:placetype":"venue"
},
  "geometry": {"coordinates":[13.4728536606,47.3739738464],"type":"Point"}
}