{
  "type": "Feature",
  "properties": {
    "addr:full":"R\u00f6merstrasse 13 Bregenz Vorarlberg 6900",
    "addr:housenumber":"13",
    "addr:postcode":"6900",
    "addr:street":"Roemerstrasse",
    "iso:country":"AT",
    "sg:address":"R\u00f6merstrasse 13",
    "sg:city":"Bregenz",
    "sg:classifiers":[
        {
            "category":"Wholesale",
            "subcategory":"Office Equipment",
            "type":"Manufacturing & Wholesale Goods"
        }
    ],
    "sg:phone":"+43 5574 433410",
    "sg:postcode":"6900",
    "sg:province":"Vorarlberg",
    "sg:website":"sautter.at",
    "wof:name":"Sautter GmbH & Co - alles f\u00fcrs B\u00fcro",
    "wof:placetype":"venue"
},
  "geometry": {"coordinates":[9.7449626923,47.501499176],"type":"Point"}
}