{
  "type": "Feature",
  "properties": {
    "iso:country":"AT",
    "sg:address":"Dreihackeng 26",
    "sg:city":"Graz",
    "sg:classifiers":[
        {
            "category":"Taxi",
            "type":"Transportation"
        }
    ],
    "sg:phone":"+43 4366 44225532",
    "sg:postcode":"8020",
    "sg:province":"Steiermark",
    "sg:tags":[
        "personentransporte",
        "u"
    ],
    "wof:name":"Ledinek Robert",
    "wof:placetype":"venue"
},
  "geometry": {"coordinates":[15.4284353256,47.0676727295],"type":"Point"}
}