{
  "type": "Feature",
  "properties": {
    "iso:country":"AT",
    "sg:address":"Margaretenstr 70",
    "sg:city":"Wien",
    "sg:orig_category":"Schauspielschulen",
    "sg:phone":"+43 1 5852133",
    "sg:postcode":"1050",
    "sg:province":"Wien",
    "sg:website":"schauspielschule.at",
    "wof:name":"Act & Fun - das schauspielstudio",
    "wof:placetype":"venue"
},
  "geometry": {"coordinates":[16.3604698181,48.1927757263],"type":"Point"}
}