{
  "type": "Feature",
  "properties": {
    "addr:full":"Europapl 1 Lienz Tirol 9900",
    "addr:housenumber":"1",
    "addr:postcode":"9900",
    "addr:street":"Europapl;Tirol",
    "iso:country":"AT",
    "sg:address":"Europapl 1",
    "sg:city":"Lienz",
    "sg:orig_category":"Tourismusinformation U -Organisationen",
    "sg:phone":"+43 4348 52652650",
    "sg:postcode":"9900",
    "sg:province":"Tirol",
    "wof:name":"Tourismusverband Lienzer Dolomiten",
    "wof:placetype":"venue"
},
  "geometry": {"coordinates":[12.7686367035,46.82862854],"type":"Point"}
}