{
  "type": "Feature",
  "properties": {
    "addr:full":"Marktstr 46 Dornbirn Vorarlberg 6850",
    "addr:housenumber":"46",
    "addr:postcode":"6850",
    "addr:street":"Marktstr",
    "iso:country":"AT",
    "sg:address":"Marktstr 46",
    "sg:city":"Dornbirn",
    "sg:orig_category":"Bierlokale-Pubs",
    "sg:phone":"+43 5572 24425",
    "sg:postcode":"6850",
    "sg:province":"Vorarlberg",
    "wof:name":"Sherlock-Holmes-Pub",
    "wof:placetype":"venue"
},
  "geometry": {"coordinates":[9.7418384552,47.4085845947],"type":"Point"}
}