{
  "type": "Feature",
  "properties": {
    "addr:full":"Harterfeldstr 2b Leonding Ober\u00f6sterreich 4060",
    "addr:housenumber":"2b",
    "addr:postcode":"4060",
    "addr:street":"Harterfeldstr",
    "iso:country":"AT",
    "sg:address":"Harterfeldstr 2b",
    "sg:city":"Leonding",
    "sg:orig_category":"Banken U Sparkassen",
    "sg:phone":"+43 732 6713730",
    "sg:postcode":"4060",
    "sg:province":"Ober\u00f6sterreich",
    "wof:name":"Raiffeisenbank Leonding regGenmbH",
    "wof:placetype":"venue"
},
  "geometry": {"coordinates":[14.2571659088,48.2644691467],"type":"Point"}
}