{
  "type": "Feature",
  "properties": {
    "addr:full":"Isidor-Trautzl-Str 12 Baden Nieder\u00f6sterreich 2500",
    "addr:housenumber":"12",
    "addr:postcode":"2500",
    "addr:street":"Isidor-Trautzl-Str;Niederoesterreich",
    "iso:country":"AT",
    "sg:address":"Isidor-Trautzl-Str 12",
    "sg:city":"Baden",
    "sg:orig_category":"Beteiligungen U Finanzierungen",
    "sg:phone":"+43 4322 5284954",
    "sg:postcode":"2500",
    "sg:province":"Nieder\u00f6sterreich",
    "wof:name":"Parzer Finanzconsulting",
    "wof:placetype":"venue"
},
  "geometry": {"coordinates":[16.2407398224,47.9967193604],"type":"Point"}
}