{
  "type": "Feature",
  "properties": {
    "addr:full":"K\u00e4rntner Str 17/1b Wien Wien 1010",
    "addr:housenumber":"17 / 1b",
    "addr:postcode":"1010",
    "addr:street":"Str",
    "iso:country":"AT",
    "sg:address":"K\u00e4rntner Str 17/1b",
    "sg:city":"Wien",
    "sg:orig_category":"Werbeagenturen",
    "sg:phone":"+43 4319 551467",
    "sg:postcode":"1010",
    "sg:province":"Wien",
    "wof:name":"4 e Event Entertainment GmbH",
    "wof:placetype":"venue"
},
  "geometry": {"coordinates":[16.3737068176,48.2016677856],"type":"Point"}
}