{
  "type": "Feature",
  "properties": {
    "addr:full":"Nr 30 Aich-Assach Steiermark 8966",
    "addr:postcode":"8966",
    "addr:street":"Nr;Aich-Assach",
    "iso:country":"AT",
    "sg:address":"Nr 30",
    "sg:city":"Aich-Assach",
    "sg:orig_category":"Non-Classified Establishments",
    "sg:phone":"+43 3686 4343",
    "sg:postcode":"8966",
    "sg:province":"Steiermark",
    "wof:name":"Pfarramt",
    "wof:placetype":"venue"
},
  "geometry": {"coordinates":[13.8196287155,47.4196052551],"type":"Point"}
}