{
  "type": "Feature",
  "properties": {
    "addr:full":"Stelzhamerstrasse 32 Traun Ober\u00f6sterreich 4050",
    "addr:housenumber":"32",
    "addr:postcode":"4050",
    "addr:street":"Stelzhamerstrasse",
    "iso:country":"AT",
    "sg:address":"Stelzhamerstrasse 32",
    "sg:city":"Traun",
    "sg:classifiers":[
        {
            "category":"Military Area",
            "subcategory":"Air Force Base",
            "type":"Public Place"
        }
    ],
    "sg:phone":"+43 7229 62446",
    "sg:postcode":"4050",
    "sg:province":"Ober\u00f6sterreich",
    "sg:tags":[
        "dock",
        "leveller",
        "ramp",
        "loading"
    ],
    "wof:name":"Franz Lepschi",
    "wof:placetype":"venue"
},
  "geometry": {"coordinates":[14.2574462891,48.2385101318],"type":"Point"}
}