{
  "type": "Feature",
  "properties": {
    "addr:full":"T\u00e4nzlg 2 Bad Ischl Ober\u00f6sterreich 4820",
    "addr:housenumber":"2",
    "addr:postcode":"4820",
    "addr:street":"Taenzlg",
    "iso:country":"AT",
    "sg:address":"T\u00e4nzlg 2",
    "sg:city":"Bad Ischl",
    "sg:classifiers":[
        {
            "category":"Internet Cafe",
            "subcategory":"None",
            "type":"Food & Drink"
        }
    ],
    "sg:phone":"+43 6132 22722",
    "sg:postcode":"4820",
    "sg:province":"Ober\u00f6sterreich",
    "wof:name":"MyWell Content & Communication Services GmbH",
    "wof:placetype":"venue"
},
  "geometry": {"coordinates":[13.6177759171,47.7097473145],"type":"Point"}
}