{
  "type": "Feature",
  "properties": {
    "addr:full":"Stubenrg. 2  Wien Wien 1010",
    "addr:housenumber":"2",
    "addr:postcode":"1010",
    "addr:street":"Stubenrg.",
    "iso:country":"AT",
    "sg:address":"Stubenrg. 2 ",
    "sg:city":"Wien",
    "sg:classifiers":[
        {
            "category":"Travel",
            "subcategory":"Travel Agent",
            "type":"Entertainment"
        }
    ],
    "sg:phone":"+43 4315 125291",
    "sg:postcode":"1010",
    "sg:province":"Wien",
    "sg:tags":[
        "business"
    ],
    "wof:name":"HOTEL-PENSION ARENBERG",
    "wof:placetype":"venue"
},
  "geometry": {"coordinates":[16.3824501038,48.2107048035],"type":"Point"}
}