{
  "type": "Feature",
  "properties": {
    "addr:full":"Steindorf 204 Stra\u00dfwalchen Salzburg 5204",
    "addr:housenumber":"204",
    "addr:postcode":"5204",
    "addr:street":"Steindorf;Salzburg",
    "iso:country":"AT",
    "sg:address":"Steindorf 204",
    "sg:city":"Stra\u00dfwalchen",
    "sg:orig_category":"Autoersatzteile",
    "sg:phone":"+43 6215 51520",
    "sg:postcode":"5204",
    "sg:province":"Salzburg",
    "wof:name":"Forstinger Handel und Service GmbH",
    "wof:placetype":"venue"
},
  "geometry": {"coordinates":[13.2277984619,47.9570655823],"type":"Point"}
}