{
  "type": "Feature",
  "properties": {
    "addr:full":"St. Lorenzen 37 Scheifling Steiermark 8811",
    "addr:housenumber":"37",
    "addr:postcode":"8811",
    "addr:street":"St. Lorenzen",
    "iso:country":"AT",
    "sg:address":"St. Lorenzen 37",
    "sg:city":"Scheifling",
    "sg:orig_category":"ChildrenS Furniture",
    "sg:phone":"+43 3582 23570",
    "sg:postcode":"8811",
    "sg:province":"Steiermark",
    "wof:name":"Erwin und Ing. Robert Wagner Ges.m.b.H. & Co KG",
    "wof:placetype":"venue"
},
  "geometry": {"coordinates":[14.4103889465,47.1504631042],"type":"Point"}
}