{
  "type": "Feature",
  "properties": {
    "addr:full":"Joseph-Mohr-Str 8 Oberndorf Salzburg 5110",
    "addr:housenumber":"8",
    "addr:postcode":"5110",
    "addr:street":"Joseph-Mohr-Str",
    "iso:country":"AT",
    "sg:address":"Joseph-Mohr-Str 8",
    "sg:city":"Oberndorf",
    "sg:orig_category":"Hauptschulen",
    "sg:phone":"+43 4362 7272930",
    "sg:postcode":"5110",
    "sg:province":"Salzburg",
    "wof:name":"Hauptschule",
    "wof:placetype":"venue"
},
  "geometry": {"coordinates":[12.9440908432,47.9444389343],"type":"Point"}
}