{
  "type": "Feature",
  "properties": {
    "addr:full":"Rathauspl 2 Herzogenburg Nieder\u00f6sterreich 3130",
    "addr:housenumber":"2",
    "addr:postcode":"3130",
    "addr:street":"Rathauspl",
    "iso:country":"AT",
    "sg:address":"Rathauspl 2",
    "sg:city":"Herzogenburg",
    "sg:orig_category":"\u00c3\u201erzte / F Allgemeinmedizin",
    "sg:phone":"+43 4327 8283140",
    "sg:postcode":"3130",
    "sg:province":"Nieder\u00f6sterreich",
    "wof:name":"Seidler Sophia Dr",
    "wof:placetype":"venue"
},
  "geometry": {"coordinates":[15.6947412491,48.2848014832],"type":"Point"}
}