{
  "type": "Feature",
  "properties": {
    "addr:full":"Gries 21 Lermoos Tirol 6631",
    "addr:housenumber":"21",
    "addr:postcode":"6631",
    "addr:street":"Gries;Tirol",
    "iso:country":"AT",
    "sg:address":"Gries 21",
    "sg:city":"Lermoos",
    "sg:orig_category":"Appartements / Ferienwohnungen",
    "sg:phone":"+43 4356 733244",
    "sg:postcode":"6631",
    "sg:province":"Tirol",
    "wof:name":"Via Claudia - Scheidle Ferdinand",
    "wof:placetype":"venue"
},
  "geometry": {"coordinates":[10.8674707413,47.4073448181],"type":"Point"}
}