{
  "type": "Feature",
  "properties": {
    "addr:full":"Hauptstrasse 15 Stockerau Nieder\u00f6sterreich 2000",
    "addr:housenumber":"15",
    "addr:postcode":"2000",
    "addr:street":"Hauptstrasse",
    "iso:country":"AT",
    "sg:address":"Hauptstrasse 15",
    "sg:city":"Stockerau",
    "sg:classifiers":[
        {
            "category":"Building & Trades",
            "subcategory":"Plumbing",
            "type":"Services"
        }
    ],
    "sg:phone":"+43 2266 63437",
    "sg:postcode":"2000",
    "sg:province":"Nieder\u00f6sterreich",
    "sg:tags":[
        "supraregional",
        "gas"
    ],
    "sg:website":"hsa.co.at",
    "wof:name":"HSA Scharrenbroich Ges.m.b.H. Heizung, Sanit\u00e4r u. Alternativenergie",
    "wof:placetype":"venue"
},
  "geometry": {"coordinates":[16.2102985382,48.3852043152],"type":"Point"}
}