{
  "type": "Feature",
  "properties": {
    "iso:country":"AT",
    "sg:address":"Bahnhofstr 6",
    "sg:city":"Stockerau",
    "sg:orig_category":"Notare",
    "sg:phone":"+43 2266 624540",
    "sg:postcode":"2000",
    "sg:province":"Nieder\u00f6sterreich",
    "wof:name":"Hetfleisch Michael Dr",
    "wof:placetype":"venue"
},
  "geometry": {"coordinates":[16.2102870941,48.3842391968],"type":"Point"}
}