{
  "type": "Feature",
  "properties": {
    "addr:full":"Gschwend 175 Langen Vorarlberg 6932",
    "addr:housenumber":"175",
    "addr:postcode":"6932",
    "addr:street":"Gschwend",
    "iso:country":"AT",
    "sg:address":"Gschwend 175",
    "sg:city":"Langen",
    "sg:classifiers":[
        {
            "category":"Government",
            "subcategory":"Post Office",
            "type":"Public Place"
        }
    ],
    "sg:phone":"+43 4355 754472",
    "sg:postcode":"6932",
    "sg:province":"Vorarlberg",
    "sg:tags":[
        "-handel",
        "tierzucht",
        "u"
    ],
    "wof:name":"Pfanner Josef",
    "wof:placetype":"venue"
},
  "geometry": {"coordinates":[9.8273859024,47.5082244873],"type":"Point"}
}