{
  "type": "Feature",
  "properties": {
    "addr:full":"Quellenstr 99 Wien Wien 1100",
    "addr:housenumber":"99",
    "addr:postcode":"1100",
    "addr:street":"Quellenstr",
    "iso:country":"AT",
    "sg:address":"Quellenstr 99",
    "sg:city":"Wien",
    "sg:orig_category":"Nachhilfe U Lernbetreuung",
    "sg:phone":"+43 1 6023921",
    "sg:postcode":"1100",
    "sg:province":"Wien",
    "wof:name":"MAS Nachhilfe",
    "wof:placetype":"venue"
},
  "geometry": {"coordinates":[16.3803024292,48.1750221252],"type":"Point"}
}