{
  "type": "Feature",
  "properties": {
    "addr:full":"Riedg 73 Innsbruck Tirol 6020",
    "addr:housenumber":"73",
    "addr:postcode":"6020",
    "addr:street":"Riedg;Tirol",
    "iso:country":"AT",
    "sg:address":"Riedg 73",
    "sg:city":"Innsbruck",
    "sg:orig_category":"Isolierungen",
    "sg:phone":"+43 512 274251",
    "sg:postcode":"6020",
    "sg:province":"Tirol",
    "wof:name":"Grabner Robert",
    "wof:placetype":"venue"
},
  "geometry": {"coordinates":[11.3913040161,47.2679977417],"type":"Point"}
}