{
  "type": "Feature",
  "properties": {
    "addr:full":"Stadtpl 33 Braunau am Inn Ober\u00f6sterreich 5280",
    "addr:housenumber":"33",
    "addr:postcode":"5280",
    "addr:street":"Stadtpl",
    "iso:country":"AT",
    "sg:address":"Stadtpl 33",
    "sg:city":"Braunau am Inn",
    "sg:orig_category":"Immobilienverwaltungen",
    "sg:phone":"+43 7722 64608",
    "sg:postcode":"5280",
    "sg:province":"Ober\u00f6sterreich",
    "wof:name":"Realb\u00fcro Dr Schmid GesmbH",
    "wof:placetype":"venue"
},
  "geometry": {"coordinates":[13.0353679657,48.2574539185],"type":"Point"}
}