{
  "type": "Feature",
  "properties": {
    "addr:full":"Salzburger Str 39 Oberndorf Salzburg 5110",
    "addr:housenumber":"39",
    "addr:postcode":"5110",
    "addr:street":"Salzburger Str",
    "iso:country":"AT",
    "sg:address":"Salzburger Str 39",
    "sg:city":"Oberndorf",
    "sg:orig_category":"Autoreparatur",
    "sg:phone":"+43 4362 724229",
    "sg:postcode":"5110",
    "sg:province":"Salzburg",
    "wof:name":"H\u00f6felsauer Josef",
    "wof:placetype":"venue"
},
  "geometry": {"coordinates":[12.9435129166,47.937713623],"type":"Point"}
}