{
  "type": "Feature",
  "properties": {
    "addr:full":"Wiener Str 5 M\u00fcnchendorf Nieder\u00f6sterreich 2482",
    "addr:postcode":"2482",
    "addr:street":"Niederoesterreich",
    "iso:country":"AT",
    "sg:address":"Wiener Str 5",
    "sg:city":"M\u00fcnchendorf",
    "sg:orig_category":"Massagen",
    "sg:phone":"+43 2259 7231",
    "sg:postcode":"2482",
    "sg:province":"Nieder\u00f6sterreich",
    "wof:name":"Massageinstitut - Karin Wamser",
    "wof:placetype":"venue"
},
  "geometry": {"coordinates":[16.380689621,48.0333747864],"type":"Point"}
}