{
  "type": "Feature",
  "properties": {
    "addr:full":"Im Paradiesgartl 21 Steinabr\u00fcckl Nieder\u00f6sterreich 2751",
    "addr:housenumber":"21",
    "addr:postcode":"2751",
    "addr:street":"Im Paradiesgartl;Niederoesterreich",
    "iso:country":"AT",
    "sg:address":"Im Paradiesgartl 21",
    "sg:city":"Steinabr\u00fcckl",
    "sg:orig_category":"Massagen",
    "sg:phone":"+43 2622 43189",
    "sg:postcode":"2751",
    "sg:province":"Nieder\u00f6sterreich",
    "wof:name":"Partl Dorothea",
    "wof:placetype":"venue"
},
  "geometry": {"coordinates":[16.206243515,47.8692245483],"type":"Point"}
}