{
  "type": "Feature",
  "properties": {
    "addr:full":"Erzherzog-Friedrich-Str 7 Halbturn Burgenland 7131",
    "addr:housenumber":"7",
    "addr:postcode":"7131",
    "addr:street":"Erzherzog-Friedrich-Str",
    "iso:country":"AT",
    "sg:address":"Erzherzog-Friedrich-Str 7",
    "sg:city":"Halbturn",
    "sg:orig_category":"Fleischhauereien",
    "sg:phone":"+43 4321 728053",
    "sg:postcode":"7131",
    "sg:province":"Burgenland",
    "wof:name":"Etl Josef",
    "wof:placetype":"venue"
},
  "geometry": {"coordinates":[16.9741859436,47.8707275391],"type":"Point"}
}