{
  "type": "Feature",
  "properties": {
    "addr:full":"Amraser Str 124 Innsbruck Tirol 6020",
    "addr:housenumber":"124",
    "addr:postcode":"6020",
    "addr:street":"Amraser Str;Tirol",
    "iso:country":"AT",
    "sg:address":"Amraser Str 124",
    "sg:city":"Innsbruck",
    "sg:orig_category":"Handelsagenturen",
    "sg:phone":"+43 512 344745",
    "sg:postcode":"6020",
    "sg:province":"Tirol",
    "wof:name":"Macher Alois",
    "wof:placetype":"venue"
},
  "geometry": {"coordinates":[11.4201421738,47.2601661682],"type":"Point"}
}