{
  "type": "Feature",
  "properties": {
    "iso:country":"AT",
    "sg:address":"Vorstadtweg 3",
    "sg:city":"Horn",
    "sg:orig_category":"Autoreparatur",
    "sg:phone":"+43 2982 30222",
    "sg:postcode":"3580",
    "sg:province":"Nieder\u00f6sterreich",
    "wof:name":"Kaufmann Gerhard",
    "wof:placetype":"venue"
},
  "geometry": {"coordinates":[15.6547317505,48.6672477722],"type":"Point"}
}