{
  "type": "Feature",
  "properties": {
    "addr:full":"Rathauspl 1 Villach K\u00e4rnten 9500",
    "addr:housenumber":"1",
    "addr:postcode":"9500",
    "addr:street":"Rathauspl;Kaernten",
    "iso:country":"AT",
    "sg:address":"Rathauspl 1",
    "sg:city":"Villach",
    "sg:classifiers":[
        {
            "category":"Arts & Performance",
            "subcategory":"Theater",
            "type":"Entertainment"
        }
    ],
    "sg:phone":"+43 4242 22583",
    "sg:postcode":"9500",
    "sg:province":"K\u00e4rnten",
    "wof:name":"Theater neueb\u00fchnevillach",
    "wof:placetype":"venue"
},
  "geometry": {"coordinates":[13.8463611603,46.6128692627],"type":"Point"}
}