{
  "type": "Feature",
  "properties": {
    "addr:full":"Flachauer Str 132 Flachau Salzburg 5542",
    "addr:housenumber":"132",
    "addr:postcode":"5542",
    "addr:street":"Flachau Salzburg",
    "iso:country":"AT",
    "sg:address":"Flachauer Str 132",
    "sg:city":"Flachau",
    "sg:orig_category":"Pensionen / Privatzimmer",
    "sg:phone":"+43 6457 2323",
    "sg:postcode":"5542",
    "sg:province":"Salzburg",
    "wof:name":"Klabacher Johanna",
    "wof:placetype":"venue"
},
  "geometry": {"coordinates":[13.3894634247,47.3601913452],"type":"Point"}
}