{
  "type": "Feature",
  "properties": {
    "addr:full":"Favoritenstr 16 Wien Wien 1040",
    "addr:housenumber":"16",
    "addr:postcode":"1040",
    "addr:street":"Favoritenstr",
    "iso:country":"AT",
    "sg:address":"Favoritenstr 16",
    "sg:city":"Wien",
    "sg:orig_category":"Immobilienmakler",
    "sg:phone":"+43 1 5037330",
    "sg:postcode":"1040",
    "sg:province":"Wien",
    "wof:name":"IMMOMAX Walter Fichtinger",
    "wof:placetype":"venue"
},
  "geometry": {"coordinates":[16.3695335388,48.1944198608],"type":"Point"}
}