{
  "type": "Feature",
  "properties": {
    "addr:full":"Hauptpl 7 St. Martin an der Raab Burgenland 8383",
    "addr:housenumber":"7",
    "addr:postcode":"8383",
    "addr:street":"Hauptpl",
    "iso:country":"AT",
    "sg:address":"Hauptpl 7",
    "sg:city":"St. Martin an der Raab",
    "sg:orig_category":"Gemeinden",
    "sg:phone":"+43 4333 2945366",
    "sg:postcode":"8383",
    "sg:province":"Burgenland",
    "wof:name":"Gemeindeamt St Martin an der Raab",
    "wof:placetype":"venue"
},
  "geometry": {"coordinates":[16.1337680817,46.9206161499],"type":"Point"}
}