{
  "type": "Feature",
  "properties": {
    "addr:full":"Dorf 155 Lech Vorarlberg 6764",
    "addr:housenumber":"155",
    "addr:postcode":"6764",
    "addr:street":"Dorf",
    "iso:country":"AT",
    "sg:address":"Dorf 155",
    "sg:city":"Lech",
    "sg:orig_category":"Pensionen / Privatzimmer",
    "sg:phone":"+43 5583 3554",
    "sg:postcode":"6764",
    "sg:province":"Vorarlberg",
    "wof:name":"Pension Chesa Rosa",
    "wof:placetype":"venue"
},
  "geometry": {"coordinates":[10.1413106918,47.207408905],"type":"Point"}
}