{
  "type": "Feature",
  "properties": {
    "addr:full":"Kesselstrasse 42 Wolfurt-Bahnhof Vorarlberg 6960",
    "addr:housenumber":"42",
    "addr:postcode":"6960",
    "addr:street":"Kesselstrasse",
    "iso:country":"AT",
    "sg:address":"Kesselstrasse 42",
    "sg:city":"Wolfurt-Bahnhof",
    "sg:orig_category":"Standard Components For Die And Mould Making",
    "sg:phone":"+43 5574 67060",
    "sg:postcode":"6960",
    "sg:province":"Vorarlberg",
    "sg:website":"meusburger-norm.com",
    "wof:name":"Meusburger Georg GmbH & Co",
    "wof:placetype":"venue"
},
  "geometry": {"coordinates":[9.744799614,47.4522171021],"type":"Point"}
}