{
  "type": "Feature",
  "properties": {
    "addr:full":"M\u00fchlbachg 18 Traiskirchen Nieder\u00f6sterreich 2514",
    "addr:housenumber":"18",
    "addr:postcode":"2514",
    "addr:street":"Muehlbachg;Niederoesterreich",
    "iso:country":"AT",
    "sg:address":"M\u00fchlbachg 18",
    "sg:city":"Traiskirchen",
    "sg:orig_category":"Abfallentsorgung U -Verwertung",
    "sg:phone":"+43 4322 52523580",
    "sg:postcode":"2514",
    "sg:province":"Nieder\u00f6sterreich",
    "wof:name":"Dumag Brennertechnologie GesmbH",
    "wof:placetype":"venue"
},
  "geometry": {"coordinates":[16.2946777344,48.0138092041],"type":"Point"}
}