{
  "type": "Feature",
  "properties": {
    "addr:full":"Niedere-Munde-Str 15 Telfs Tirol 6410",
    "addr:housenumber":"15",
    "addr:postcode":"6410",
    "addr:street":"Niedere-Munde-Str;Tirol",
    "iso:country":"AT",
    "sg:address":"Niedere-Munde-Str 15",
    "sg:city":"Telfs",
    "sg:orig_category":"Werbegrafik- U Grafik-Design",
    "sg:phone":"+43 4352 62612540",
    "sg:postcode":"6410",
    "sg:province":"Tirol",
    "wof:name":"brandmaier fuetsch - grafische auseinandersetzung",
    "wof:placetype":"venue"
},
  "geometry": {"coordinates":[11.0641241074,47.3117485046],"type":"Point"}
}