{
  "type": "Feature",
  "properties": {
    "addr:full":"Andreas-Hofer-Str 11 Absam Tirol 6067",
    "addr:housenumber":"11",
    "addr:postcode":"6067",
    "addr:street":"Andreas-Hofer-Str;Tirol",
    "iso:country":"AT",
    "sg:address":"Andreas-Hofer-Str 11",
    "sg:city":"Absam",
    "sg:orig_category":"Holzbe U -Verarbeitung",
    "sg:phone":"+43 4352 2343666",
    "sg:postcode":"6067",
    "sg:province":"Tirol",
    "wof:name":"PSP - TRANSFORM",
    "wof:placetype":"venue"
},
  "geometry": {"coordinates":[11.5178050995,47.3016281128],"type":"Point"}
}