{
  "type": "Feature",
  "properties": {
    "addr:full":"Trostg 4 Wiener Neustadt Nieder\u00f6sterreich 2700",
    "addr:housenumber":"4",
    "addr:postcode":"2700",
    "addr:street":"Trostg",
    "iso:country":"AT",
    "sg:address":"Trostg 4",
    "sg:city":"Wiener Neustadt",
    "sg:orig_category":"Autohandel",
    "sg:phone":"+43 4326 2282896",
    "sg:postcode":"2700",
    "sg:province":"Nieder\u00f6sterreich",
    "wof:name":"Mercedes-Benz \u00f6sterreich VertriebsgesmbH",
    "wof:placetype":"venue"
},
  "geometry": {"coordinates":[16.2330150604,47.8130531311],"type":"Point"}
}