{
  "type": "Feature",
  "properties": {
    "iso:country":"AT",
    "sg:address":"Hauptstr 8",
    "sg:city":"Maria Anzbach",
    "sg:orig_category":"Fleischhauereien",
    "sg:phone":"+43 2772 52488",
    "sg:postcode":"3034",
    "sg:province":"Nieder\u00f6sterreich",
    "wof:name":"Gradinger Josef",
    "wof:placetype":"venue"
},
  "geometry": {"coordinates":[15.9220132828,48.1918258667],"type":"Point"}
}