{
  "type": "Feature",
  "properties": {
    "addr:full":"Nr 105 Eibiswald Steiermark 8552",
    "addr:postcode":"8552",
    "addr:street":"Nr 105",
    "iso:country":"AT",
    "sg:address":"Nr 105",
    "sg:city":"Eibiswald",
    "sg:orig_category":"Maler, Anstreicher U Lackierer",
    "sg:phone":"+43 4334 6642247",
    "sg:postcode":"8552",
    "sg:province":"Steiermark",
    "wof:name":"Galler Karl",
    "wof:placetype":"venue"
},
  "geometry": {"coordinates":[15.2274599075,46.6824150085],"type":"Point"}
}