{
  "type": "Feature",
  "properties": {
    "addr:full":"Goethestr 8a Leopoldsdorf Nieder\u00f6sterreich 2333",
    "addr:housenumber":"8a",
    "addr:postcode":"2333",
    "addr:street":"Goethestr",
    "iso:country":"AT",
    "sg:address":"Goethestr 8a",
    "sg:city":"Leopoldsdorf",
    "sg:orig_category":"Architekten",
    "sg:phone":"+43 4366 45255654",
    "sg:postcode":"2333",
    "sg:province":"Nieder\u00f6sterreich",
    "wof:name":"Gschlacht Richard Arch Mag",
    "wof:placetype":"venue"
},
  "geometry": {"coordinates":[16.383436203,48.1126098633],"type":"Point"}
}