{
  "type": "Feature",
  "properties": {
    "addr:full":"Unterlandshaag 2 Feldkirchen an der Donau Ober\u00f6sterreich 4101",
    "addr:housenumber":"2",
    "addr:postcode":"4101",
    "addr:street":"Unterlandshaag",
    "iso:country":"AT",
    "sg:address":"Unterlandshaag 2",
    "sg:city":"Feldkirchen an der Donau",
    "sg:orig_category":"Feuerwehren",
    "sg:phone":"+43 7233 7612",
    "sg:postcode":"4101",
    "sg:province":"Ober\u00f6sterreich",
    "wof:name":"Freiwillige Feuerwehr Landshaag",
    "wof:placetype":"venue"
},
  "geometry": {"coordinates":[14.0289306641,48.3615989685],"type":"Point"}
}