{
  "type": "Feature",
  "properties": {
    "iso:country":"AT",
    "sg:address":"Untere Viaduktg 10",
    "sg:city":"Wien",
    "sg:orig_category":"Steuerberatung",
    "sg:phone":"+43 1 7135269",
    "sg:postcode":"1030",
    "sg:province":"Wien",
    "wof:name":"Orth Wilfried Mag",
    "wof:placetype":"venue"
},
  "geometry": {"coordinates":[16.3867740631,48.2064819336],"type":"Point"}
}