{
  "type": "Feature",
  "properties": {
    "addr:full":"Kaiserstr 8 Wien Wien 1070",
    "addr:housenumber":"8",
    "addr:postcode":"1070",
    "addr:street":"Kaiserstr",
    "iso:country":"AT",
    "sg:address":"Kaiserstr 8",
    "sg:city":"Wien",
    "sg:orig_category":"Unternehmensberatung",
    "sg:phone":"+43 1 40285050",
    "sg:postcode":"1070",
    "sg:province":"Wien",
    "wof:name":"ICG Infora Consulting Group GmbH",
    "wof:placetype":"venue"
},
  "geometry": {"coordinates":[16.3416099548,48.1972198486],"type":"Point"}
}