{
  "type": "Feature",
  "properties": {
    "addr:full":"Gumpling 24 Ostermiething Ober\u00f6sterreich 5121",
    "addr:housenumber":"24",
    "addr:postcode":"5121",
    "addr:street":"Gumpling",
    "iso:country":"AT",
    "sg:address":"Gumpling 24",
    "sg:city":"Ostermiething",
    "sg:orig_category":"Steuerberatung",
    "sg:phone":"+43 4362 786375",
    "sg:postcode":"5121",
    "sg:province":"Ober\u00f6sterreich",
    "wof:name":"Hager Christine",
    "wof:placetype":"venue"
},
  "geometry": {"coordinates":[12.8649787903,48.044883728],"type":"Point"}
}