{
  "type": "Feature",
  "properties": {
    "addr:full":"Mozartstrasse 3 Linz Ober\u00f6sterreich 4020",
    "addr:housenumber":"3",
    "addr:postcode":"4020",
    "addr:street":"Mozartstrasse",
    "iso:country":"AT",
    "sg:address":"Mozartstrasse 3",
    "sg:city":"Linz",
    "sg:classifiers":[
        {
            "category":"Communications",
            "type":"Services"
        }
    ],
    "sg:phone":"+43 732 7751100",
    "sg:postcode":"4020",
    "sg:province":"Ober\u00f6sterreich",
    "sg:tags":[
        "services",
        "polish",
        "translation"
    ],
    "wof:name":"Dr. Binder KEG",
    "wof:placetype":"venue"
},
  "geometry": {"coordinates":[14.2911329269,48.3011932373],"type":"Point"}
}