{
  "type": "Feature",
  "properties": {
    "addr:full":"Mitterg\u00f6ming 12  Oberndorf Salzburg 5110",
    "addr:housenumber":"12",
    "addr:postcode":"5110",
    "addr:street":"Mittergoeming",
    "iso:country":"AT",
    "sg:address":"Mitterg\u00f6ming 12 ",
    "sg:city":"Oberndorf",
    "sg:classifiers":[
        {
            "category":"Professional",
            "subcategory":"Printing & Photocopies",
            "type":"Services"
        }
    ],
    "sg:phone":"+43 4362 724102",
    "sg:postcode":"5110",
    "sg:province":"Salzburg",
    "wof:name":"OBERDORFER DRUCKEREI GMBH",
    "wof:placetype":"venue"
},
  "geometry": {"coordinates":[12.9325675964,47.9608917236],"type":"Point"}
}