{
  "type": "Feature",
  "properties": {
    "addr:full":"C Plattner-Str 22 Imst Tirol 6460",
    "addr:housenumber":"22",
    "addr:postcode":"6460",
    "addr:street":"Imst Tirol",
    "iso:country":"AT",
    "sg:address":"C Plattner-Str 22",
    "sg:city":"Imst",
    "sg:orig_category":"Metallwaren / Erzeugung U Gro\u00c3\u0178handel",
    "sg:phone":"+43 5412 612021",
    "sg:postcode":"6460",
    "sg:province":"Tirol",
    "wof:name":"Neubauer Werksvertretungen GmbH",
    "wof:placetype":"venue"
},
  "geometry": {"coordinates":[10.7361364365,47.2380714417],"type":"Point"}
}