{
  "type": "Feature",
  "properties": {
    "addr:full":"Bundesstr 212 Wimpassing im Schwarzatale Nieder\u00f6sterreich 2632",
    "addr:housenumber":"212",
    "addr:postcode":"2632",
    "addr:street":"Wimpassing",
    "iso:country":"AT",
    "sg:address":"Bundesstr 212",
    "sg:city":"Wimpassing im Schwarzatale",
    "sg:orig_category":"Autohandel",
    "sg:phone":"+43 2630 35848",
    "sg:postcode":"2632",
    "sg:province":"Nieder\u00f6sterreich",
    "wof:name":"Happy-Car Haider",
    "wof:placetype":"venue"
},
  "geometry": {"coordinates":[16.0090656281,47.6862220764],"type":"Point"}
}