{
  "type": "Feature",
  "properties": {
    "iso:country":"AT",
    "sg:address":"Widldorf 40",
    "sg:city":"Neumarkt im Hausruckkreis",
    "sg:classifiers":[
        {
            "category":"Manufacturing",
            "subcategory":"Rubber & Plastics",
            "type":"Manufacturing & Wholesale Goods"
        }
    ],
    "sg:phone":"+43 7733 6219",
    "sg:postcode":"4720",
    "sg:province":"Ober\u00f6sterreich",
    "sg:tags":[
        "processing"
    ],
    "wof:name":"Kutec - Kunststofftechnik Werner Oberndorfinger",
    "wof:placetype":"venue"
},
  "geometry": {"coordinates":[13.7403049469,48.2708816528],"type":"Point"}
}