{
  "type": "Feature",
  "properties": {
    "iso:country":"AT",
    "sg:address":"Nikolaus-Gassner-Str 403",
    "sg:city":"Kaprun",
    "sg:orig_category":"Pensionen / Privatzimmer",
    "sg:phone":"+43 6547 8287",
    "sg:postcode":"5710",
    "sg:province":"Salzburg",
    "wof:name":"Fr\u00fchst\u00fcckspension Elisabeth",
    "wof:placetype":"venue"
},
  "geometry": {"coordinates":[12.7501354218,47.2671508789],"type":"Point"}
}