{
  "type": "Feature",
  "properties": {
    "addr:full":"Johannespl 2 Lienz Tirol 9900",
    "addr:housenumber":"2",
    "addr:postcode":"9900",
    "addr:street":"Johannespl;Tirol",
    "iso:country":"AT",
    "sg:address":"Johannespl 2",
    "sg:city":"Lienz",
    "sg:orig_category":"Lederwaren / Einzelhandel",
    "sg:phone":"+43 4852 62622",
    "sg:postcode":"9900",
    "sg:province":"Tirol",
    "wof:name":"Leitner Gebr\u00fcder",
    "wof:placetype":"venue"
},
  "geometry": {"coordinates":[12.7673282623,46.8297615051],"type":"Point"}
}