{
  "type": "Feature",
  "properties": {
    "addr:full":"Stubenbastei 10 Wien Wien 1010",
    "addr:housenumber":"10",
    "addr:postcode":"1010",
    "addr:street":"Stubenbastei",
    "iso:country":"AT",
    "sg:address":"Stubenbastei 10",
    "sg:city":"Wien",
    "sg:classifiers":[
        {
            "category":"Restaurant",
            "type":"Food & Drink"
        }
    ],
    "sg:phone":"+43 1 5124319",
    "sg:postcode":"1010",
    "sg:province":"Wien",
    "wof:name":"Bastei-Beisl",
    "wof:placetype":"venue"
},
  "geometry": {"coordinates":[16.3776950836,48.20652771],"type":"Point"}
}