{
  "type": "Feature",
  "properties": {
    "addr:full":"Oberer Markt 14 Kefermarkt Ober\u00f6sterreich 4292",
    "addr:housenumber":"14",
    "addr:postcode":"4292",
    "addr:street":"Oberer Markt",
    "iso:country":"AT",
    "sg:address":"Oberer Markt 14",
    "sg:city":"Kefermarkt",
    "sg:orig_category":"Dachdeckereien",
    "sg:phone":"+43 4379 4762290",
    "sg:postcode":"4292",
    "sg:province":"Ober\u00f6sterreich",
    "wof:name":"Aistleitner Josef GesmbH",
    "wof:placetype":"venue"
},
  "geometry": {"coordinates":[14.5375242233,48.4426116943],"type":"Point"}
}