{
  "type": "Feature",
  "properties": {
    "addr:full":"IZ Burgerfeld 3 Wilhelmsburg an der Traisen Nieder\u00f6sterreich 3150",
    "addr:housenumber":"3",
    "addr:postcode":"3150",
    "addr:street":"Burgerfeld",
    "iso:country":"AT",
    "sg:address":"IZ Burgerfeld 3",
    "sg:city":"Wilhelmsburg an der Traisen",
    "sg:orig_category":"Solartechnik",
    "sg:phone":"+43 2746 24300",
    "sg:postcode":"3150",
    "sg:province":"Nieder\u00f6sterreich",
    "wof:name":"Solkav Alternative Energie Systeme GesmbH",
    "wof:placetype":"venue"
},
  "geometry": {"coordinates":[15.6558494568,48.0672073364],"type":"Point"}
}