{
  "type": "Feature",
  "properties": {
    "addr:full":"Mariahilfer Str 81/II/5a Wien Wien 1060",
    "addr:housenumber":"81 / ii / 5a",
    "addr:postcode":"1060",
    "addr:street":"Str",
    "iso:country":"AT",
    "sg:address":"Mariahilfer Str 81/II/5a",
    "sg:city":"Wien",
    "sg:classifiers":[
        {
            "category":"Internet Cafe",
            "subcategory":"None",
            "type":"Food & Drink"
        }
    ],
    "sg:phone":"+43 1 58576070",
    "sg:postcode":"1060",
    "sg:province":"Wien",
    "wof:name":"WORX Multimedia Consulting GmbH",
    "wof:placetype":"venue"
},
  "geometry": {"coordinates":[16.3504657745,48.1947135925],"type":"Point"}
}