{
  "type": "Feature",
  "properties": {
    "iso:country":"AT",
    "sg:address":"Sonnendorf 20",
    "sg:city":"Kufstein",
    "sg:orig_category":"Pensionen / Privatzimmer",
    "sg:phone":"+43 5372 58220",
    "sg:postcode":"6330",
    "sg:province":"Tirol",
    "wof:name":"Pension Perle Tirols",
    "wof:placetype":"venue"
},
  "geometry": {"coordinates":[12.141330719,47.5373344421],"type":"Point"}
}