{
  "type": "Feature",
  "properties": {
    "iso:country":"AT",
    "sg:address":"Hauptstr 3",
    "sg:city":"Neuhaus am Klausenbach",
    "sg:orig_category":"Volksschulen",
    "sg:phone":"+43 4333 292412",
    "sg:postcode":"8385",
    "sg:province":"Burgenland",
    "wof:name":"Volksschule",
    "wof:placetype":"venue"
},
  "geometry": {"coordinates":[16.031124115,46.8689193726],"type":"Point"}
}