{
  "type": "Feature",
  "properties": {
    "addr:full":"Wienerbergstr 7 Wien Wien 1100",
    "addr:housenumber":"7",
    "addr:postcode":"1100",
    "addr:street":"Wienerbergstr",
    "iso:country":"AT",
    "sg:address":"Wienerbergstr 7",
    "sg:city":"Wien",
    "sg:orig_category":"Garagen Parkgaragen",
    "sg:phone":"+43 1 6003022500",
    "sg:postcode":"1100",
    "sg:province":"Wien",
    "sg:website":"wipark.com",
    "wof:name":"Wipark Garagen AG",
    "wof:placetype":"venue"
},
  "geometry": {"coordinates":[16.3470554352,48.1692352295],"type":"Point"}
}