{
  "type": "Feature",
  "properties": {
    "iso:country":"AT",
    "sg:address":"Haniflg 11",
    "sg:city":"St. Andr\u00e4 am Zicksee",
    "sg:orig_category":"Feuerwehren",
    "sg:phone":"+43 2176 2047",
    "sg:postcode":"7161",
    "sg:province":"Burgenland",
    "wof:name":"Freiwillige Feuerwehr St Andr\u00e4",
    "wof:placetype":"venue"
},
  "geometry": {"coordinates":[16.9444923401,47.7845726013],"type":"Point"}
}