{
  "type": "Feature",
  "properties": {
    "iso:country":"AT",
    "sg:address":"Eiseng 18",
    "sg:city":"Dornbirn",
    "sg:orig_category":"Datenverarbeitung",
    "sg:phone":"+43 4355 72247810",
    "sg:postcode":"6850",
    "sg:province":"Vorarlberg",
    "wof:name":"Furtenbach Florian",
    "wof:placetype":"venue"
},
  "geometry": {"coordinates":[9.7457847595,47.4170303345],"type":"Point"}
}