{
  "type": "Feature",
  "properties": {
    "addr:full":"Innsbrucker Bundesstr 19 Salzburg Salzburg 5020",
    "addr:housenumber":"19",
    "addr:postcode":"5020",
    "addr:street":"Salzburg",
    "iso:country":"AT",
    "sg:address":"Innsbrucker Bundesstr 19",
    "sg:city":"Salzburg",
    "sg:orig_category":"Blumeneinzelhandel",
    "sg:phone":"+43 4366 2440897",
    "sg:postcode":"5020",
    "sg:province":"Salzburg",
    "wof:name":"Blumen Neumayer",
    "wof:placetype":"venue"
},
  "geometry": {"coordinates":[13.0230169296,47.8052482605],"type":"Point"}
}