{
  "type": "Feature",
  "properties": {
    "addr:full":"Lanersbach 340 Tux Tirol 6293",
    "addr:housenumber":"340",
    "addr:postcode":"6293",
    "addr:street":"Lanersbach;Tirol",
    "iso:country":"AT",
    "sg:address":"Lanersbach 340",
    "sg:city":"Tux",
    "sg:orig_category":"Pensionen / Privatzimmer",
    "sg:phone":"+43 5287 874880",
    "sg:postcode":"6293",
    "sg:province":"Tirol",
    "wof:name":"Ferienhof Mittendorf",
    "wof:placetype":"venue"
},
  "geometry": {"coordinates":[11.6970243454,47.1270294189],"type":"Point"}
}