{
  "type": "Feature",
  "properties": {
    "addr:full":"H\u00f6rbach 43 Gaspoltshofen Ober\u00f6sterreich 4673",
    "addr:housenumber":"43",
    "addr:postcode":"4673",
    "addr:street":"Hoerbach",
    "iso:country":"AT",
    "sg:address":"H\u00f6rbach 43",
    "sg:city":"Gaspoltshofen",
    "sg:orig_category":"Dedusting Systems",
    "sg:phone":"+43 7735 80200",
    "sg:postcode":"4673",
    "sg:province":"Ober\u00f6sterreich",
    "sg:website":"clean-air-systems.com",
    "wof:name":"LHS Clean Air Systems GmbH",
    "wof:placetype":"venue"
},
  "geometry": {"coordinates":[13.7366924286,48.1424674988],"type":"Point"}
}