{
  "type": "Feature",
  "properties": {
    "addr:full":"Harder Str 68 Lauterach Vorarlberg 6923",
    "addr:housenumber":"68",
    "addr:postcode":"6923",
    "addr:street":"Str",
    "iso:country":"AT",
    "sg:address":"Harder Str 68",
    "sg:city":"Lauterach",
    "sg:orig_category":"Reifen U Reifendienste",
    "sg:phone":"+43 4355 7471528",
    "sg:postcode":"6923",
    "sg:province":"Vorarlberg",
    "wof:name":"Fischer Reifen GmbH",
    "wof:placetype":"venue"
},
  "geometry": {"coordinates":[9.7180223465,47.4837532043],"type":"Point"}
}