{
  "type": "Feature",
  "properties": {
    "addr:full":"Favoritenstr 36 Wien Wien 1040",
    "addr:housenumber":"36",
    "addr:postcode":"1040",
    "addr:street":"Favoritenstr",
    "iso:country":"AT",
    "sg:address":"Favoritenstr 36",
    "sg:city":"Wien",
    "sg:classifiers":[
        {
            "category":"Military Area",
            "subcategory":"Army Base",
            "type":"Public Place"
        }
    ],
    "sg:phone":"+43 1 5043705",
    "sg:postcode":"1040",
    "sg:province":"Wien",
    "sg:tags":[
        "shop"
    ],
    "sg:website":"www.us-army-shop.at",
    "wof:name":"US-Army-Shop",
    "wof:placetype":"venue"
},
  "geometry": {"coordinates":[16.3709201813,48.191570282],"type":"Point"}
}