{
  "type": "Feature",
  "properties": {
    "iso:country":"AT",
    "sg:address":"Bahnhofstr 12",
    "sg:city":"Asten",
    "sg:orig_category":"Fahrzeugbau",
    "sg:phone":"+43 7224 655180",
    "sg:postcode":"4481",
    "sg:province":"Ober\u00f6sterreich",
    "wof:name":"Meiller GmbH - Fahrzeugtechnik",
    "wof:placetype":"venue"
},
  "geometry": {"coordinates":[14.4027795792,48.2339286804],"type":"Point"}
}