{
  "type": "Feature",
  "properties": {
    "iso:country":"AT",
    "sg:address":"Wiedner Hauptstr 62",
    "sg:city":"Wien",
    "sg:orig_category":"Maler, Anstreicher U Lackierer",
    "sg:phone":"+43 4315 8732520",
    "sg:postcode":"1040",
    "sg:province":"Wien",
    "wof:name":"Rod Eduard GesmbH",
    "wof:placetype":"venue"
},
  "geometry": {"coordinates":[16.3662490845,48.1908226013],"type":"Point"}
}