{
  "type": "Feature",
  "properties": {
    "addr:full":"Nr 64 Obdach Steiermark 8742",
    "addr:postcode":"8742",
    "addr:street":"Nr",
    "iso:country":"AT",
    "sg:address":"Nr 64",
    "sg:city":"Obdach",
    "sg:orig_category":"Autobusunternehmen",
    "sg:phone":"+43 3578 3395",
    "sg:postcode":"8742",
    "sg:province":"Steiermark",
    "wof:name":"Freigassner Peter",
    "wof:placetype":"venue"
},
  "geometry": {"coordinates":[14.6953725815,47.0679969788],"type":"Point"}
}