{
  "type": "Feature",
  "properties": {
    "addr:full":"Brunnfeldweg 24 Oetz Tirol 6433",
    "addr:housenumber":"24",
    "addr:postcode":"6433",
    "addr:street":"Brunnfeldweg;Tirol",
    "iso:country":"AT",
    "sg:address":"Brunnfeldweg 24",
    "sg:city":"Oetz",
    "sg:orig_category":"Appartements / Ferienwohnungen",
    "sg:phone":"+43 4352 526496",
    "sg:postcode":"6433",
    "sg:province":"Tirol",
    "wof:name":"Brunnfeld Ferienwohnungen",
    "wof:placetype":"venue"
},
  "geometry": {"coordinates":[10.8924303055,47.2060585022],"type":"Point"}
}