{
  "type": "Feature",
  "properties": {
    "addr:full":"Haratzm\u00fcllerstr 76a Steyr Ober\u00f6sterreich 4400",
    "addr:housenumber":"76a",
    "addr:postcode":"4400",
    "addr:street":"Haratzmuellerstr;Oberoesterreich",
    "iso:country":"AT",
    "sg:address":"Haratzm\u00fcllerstr 76a",
    "sg:city":"Steyr",
    "sg:orig_category":"Werbegestalter",
    "sg:phone":"+43 7252 51454",
    "sg:postcode":"4400",
    "sg:province":"Ober\u00f6sterreich",
    "wof:name":"DEKO - IDEEN",
    "wof:placetype":"venue"
},
  "geometry": {"coordinates":[14.4193296432,48.0391807556],"type":"Point"}
}