{
  "type": "Feature",
  "properties": {
    "addr:full":"Tadtener Str 18 St. Andr\u00e4 am Zicksee Burgenland 7161",
    "addr:housenumber":"18",
    "addr:postcode":"7161",
    "addr:street":"Str",
    "iso:country":"AT",
    "sg:address":"Tadtener Str 18",
    "sg:city":"St. Andr\u00e4 am Zicksee",
    "sg:orig_category":"Pensionen / Privatzimmer",
    "sg:phone":"+43 2176 2360",
    "sg:postcode":"7161",
    "sg:province":"Burgenland",
    "wof:name":"Lang Josef",
    "wof:placetype":"venue"
},
  "geometry": {"coordinates":[16.9483470917,47.7865333557],"type":"Point"}
}