{
  "type": "Feature",
  "properties": {
    "addr:full":"Pfanghofweg 122 Andritz Steiermark 8045",
    "addr:housenumber":"122",
    "addr:postcode":"8045",
    "addr:street":"Pfanghofweg",
    "iso:country":"AT",
    "sg:address":"Pfanghofweg 122",
    "sg:city":"Andritz",
    "sg:orig_category":"Anlagenbau U -Technik",
    "sg:phone":"+43 4331 6696076",
    "sg:postcode":"8045",
    "sg:province":"Steiermark",
    "wof:name":"INTAMIN Austria GmbH",
    "wof:placetype":"venue"
},
  "geometry": {"coordinates":[15.44302845,47.1185188293],"type":"Point"}
}