{
  "type": "Feature",
  "properties": {
    "addr:full":"null B68 St. Margarethen an der Raab Steiermark 8321",
    "addr:postcode":"8321",
    "addr:street":"St. Margarethen An Der",
    "iso:country":"AT",
    "sg:address":"null B68",
    "sg:city":"St. Margarethen an der Raab",
    "sg:orig_category":"Lebensmittel / Einzelhandel",
    "sg:phone":"+43 4331 154791",
    "sg:postcode":"8321",
    "sg:province":"Steiermark",
    "wof:name":"Billa AG",
    "wof:placetype":"venue"
},
  "geometry": {"coordinates":[15.7473144531,47.0454750061],"type":"Point"}
}