{
  "type": "Feature",
  "properties": {
    "iso:country":"AT",
    "sg:address":"Kulming 2",
    "sg:city":"Pischelsdorf in Steiermark",
    "sg:classifiers":[
        {
            "category":"Taxi",
            "type":"Transportation"
        }
    ],
    "sg:phone":"+43 4331 133892",
    "sg:postcode":"8212",
    "sg:province":"Steiermark",
    "sg:tags":[
        "personentransporte",
        "u"
    ],
    "wof:name":"Darnhofer Johann",
    "wof:placetype":"venue"
},
  "geometry": {"coordinates":[15.7788448334,47.1712989807],"type":"Point"}
}