{
  "type": "Feature",
  "properties": {
    "addr:full":"Haselb\u00f6ckau 26 Schlierbach Ober\u00f6sterreich 4553",
    "addr:housenumber":"26",
    "addr:postcode":"4553",
    "addr:street":"Haselboeckau",
    "iso:country":"AT",
    "sg:address":"Haselb\u00f6ckau 26",
    "sg:city":"Schlierbach",
    "sg:orig_category":"Pensionen / Privatzimmer",
    "sg:phone":"+43 7582 81609",
    "sg:postcode":"4553",
    "sg:province":"Ober\u00f6sterreich",
    "wof:name":"Ferienhof Zehetner",
    "wof:placetype":"venue"
},
  "geometry": {"coordinates":[14.1006679535,47.9532928467],"type":"Point"}
}