{
  "type": "Feature",
  "properties": {
    "iso:country":"AT",
    "sg:address":"Waltersdorfer Str 2",
    "sg:city":"Baden",
    "sg:orig_category":"Baumeister",
    "sg:phone":"+43 2252 259807",
    "sg:postcode":"2500",
    "sg:province":"Nieder\u00f6sterreich",
    "wof:name":"ARCUS Baudienstleistungen Brauner & Partner OEG",
    "wof:placetype":"venue"
},
  "geometry": {"coordinates":[16.2431564331,48.0027961731],"type":"Point"}
}