{
  "type": "Feature",
  "properties": {
    "addr:full":"Werkstr. 5 Th\u00fcringen Vorarlberg 6712",
    "addr:housenumber":"5",
    "addr:postcode":"6712",
    "addr:street":"Werkstr.",
    "iso:country":"AT",
    "sg:address":"Werkstr. 5",
    "sg:city":"Th\u00fcringen",
    "sg:classifiers":[
        {
            "category":"Shopping",
            "subcategory":"Crafts & Fabrics",
            "type":"Retail Goods"
        }
    ],
    "sg:phone":"+43 4355 5023110",
    "sg:postcode":"6712",
    "sg:province":"Vorarlberg",
    "sg:tags":[
        "linen"
    ],
    "wof:name":"TISCA-TEXTIL GES.MBH & CO KG",
    "wof:placetype":"venue"
},
  "geometry": {"coordinates":[9.7719192505,47.1959533691],"type":"Point"}
}