{
  "type": "Feature",
  "properties": {
    "addr:full":"Max-Mell-G 1 Kalsdorf Steiermark 8401",
    "addr:housenumber":"1",
    "addr:postcode":"8401",
    "addr:street":"Max-Mell-G",
    "iso:country":"AT",
    "sg:address":"Max-Mell-G 1",
    "sg:city":"Kalsdorf",
    "sg:orig_category":"Installationsunternehmen",
    "sg:phone":"+43 4331 35527720",
    "sg:postcode":"8401",
    "sg:province":"Steiermark",
    "wof:name":"Kornh\u00e4usl Karlheinz",
    "wof:placetype":"venue"
},
  "geometry": {"coordinates":[15.4725732803,46.9717979431],"type":"Point"}
}