{
  "type": "Feature",
  "properties": {
    "iso:country":"AT",
    "sg:address":"Nr 8",
    "sg:city":"Alland",
    "sg:orig_category":"Personalbereitstellung",
    "sg:phone":"+43 2258 2350",
    "sg:postcode":"2534",
    "sg:province":"Nieder\u00f6sterreich",
    "wof:name":"Raith Josef",
    "wof:placetype":"venue"
},
  "geometry": {"coordinates":[16.0783996582,48.0584259033],"type":"Point"}
}