{
  "type": "Feature",
  "properties": {
    "addr:full":"Nr 64 Esternberg Ober\u00f6sterreich 4092",
    "addr:postcode":"4092",
    "addr:street":"Nr;Oberoesterreich",
    "iso:country":"AT",
    "sg:address":"Nr 64",
    "sg:city":"Esternberg",
    "sg:orig_category":"Autoreparatur",
    "sg:phone":"+43 7714 6200",
    "sg:postcode":"4092",
    "sg:province":"Ober\u00f6sterreich",
    "wof:name":"Dullinger Konrad",
    "wof:placetype":"venue"
},
  "geometry": {"coordinates":[13.5718803406,48.5439147949],"type":"Point"}
}