{
  "type": "Feature",
  "properties": {
    "addr:full":"Niederhart 22 F\u00fcgen Tirol 6263",
    "addr:housenumber":"22",
    "addr:postcode":"6263",
    "addr:street":"Niederhart;Tirol",
    "iso:country":"AT",
    "sg:address":"Niederhart 22",
    "sg:city":"F\u00fcgen",
    "sg:orig_category":"Musikgruppen",
    "sg:phone":"+43 664 5542293",
    "sg:postcode":"6263",
    "sg:province":"Tirol",
    "wof:name":"Luggi l\u00e4ndl & modern - Eder Ludwig - Alleinunterhalter",
    "wof:placetype":"venue"
},
  "geometry": {"coordinates":[11.8686199188,47.3540496826],"type":"Point"}
}