{
  "type": "Feature",
  "properties": {
    "addr:full":"Stra\u00dfganger Str 433 Graz Steiermark 8020",
    "addr:housenumber":"433",
    "addr:postcode":"8020",
    "iso:country":"AT",
    "sg:address":"Stra\u00dfganger Str 433",
    "sg:city":"Graz",
    "sg:orig_category":"Farben U Lacke / Einzelhandel",
    "sg:phone":"+43 316 253330",
    "sg:postcode":"8020",
    "sg:province":"Steiermark",
    "wof:name":"Farbenwelt Graz",
    "wof:placetype":"venue"
},
  "geometry": {"coordinates":[15.3966569901,47.0621604919],"type":"Point"}
}