{
  "type": "Feature",
  "properties": {
    "addr:full":"Brunnenfeldstrasse 15 Linz Ober\u00f6sterreich 4030",
    "addr:housenumber":"15",
    "addr:postcode":"4030",
    "addr:street":"Brunnenfeldstrasse",
    "iso:country":"AT",
    "sg:address":"Brunnenfeldstrasse 15",
    "sg:city":"Linz",
    "sg:classifiers":[
        {
            "category":"Health Services",
            "subcategory":"Medical Lab",
            "type":"Services"
        }
    ],
    "sg:phone":"+43 732 301002",
    "sg:postcode":"4030",
    "sg:province":"Ober\u00f6sterreich",
    "sg:tags":[
        "disinfection",
        "room",
        "cleaning"
    ],
    "wof:name":"HEDA REINIGUNGSDIENST Ges.m.b.H.",
    "wof:placetype":"venue"
},
  "geometry": {"coordinates":[14.3152618408,48.2643013],"type":"Point"}
}