{
  "type": "Feature",
  "properties": {
    "addr:full":"Waagg 2 Wien Wien 1040",
    "addr:housenumber":"2",
    "addr:postcode":"1040",
    "addr:street":"Waagg",
    "iso:country":"AT",
    "sg:address":"Waagg 2",
    "sg:city":"Wien",
    "sg:orig_category":"Werbeagenturen",
    "sg:phone":"+43 1 5851104",
    "sg:postcode":"1040",
    "sg:province":"Wien",
    "wof:name":"November Glatz-Deuretzbacher KEG",
    "wof:placetype":"venue"
},
  "geometry": {"coordinates":[16.3669013977,48.194896698],"type":"Point"}
}