{
  "type": "Feature",
  "properties": {
    "iso:country":"AT",
    "sg:address":"Zeller Str. 89 ",
    "sg:city":"Mittersill",
    "sg:classifiers":[
        {
            "category":"Autos & Motor Vehicles",
            "subcategory":"Boat Sales",
            "type":"Retail Goods"
        }
    ],
    "sg:phone":"+43 4365 626253",
    "sg:postcode":"5730",
    "sg:province":"Salzburg",
    "wof:name":"AUTO HUBER GMBH",
    "wof:placetype":"venue"
},
  "geometry": {"coordinates":[12.4892902374,47.285030365],"type":"Point"}
}