{
  "type": "Feature",
  "properties": {
    "iso:country":"AT",
    "sg:address":"L\u00f6blichg 2",
    "sg:city":"Klosterneuburg",
    "sg:orig_category":"Polizei U Gendarmerie",
    "sg:phone":"+43 4359 1333237",
    "sg:postcode":"3400",
    "sg:province":"Nieder\u00f6sterreich",
    "wof:name":"Gendarmerie",
    "wof:placetype":"venue"
},
  "geometry": {"coordinates":[16.310087204,48.291305542],"type":"Point"}
}