{
  "type": "Feature",
  "properties": {
    "addr:full":"Grenzlandstr 1 Gm\u00fcnd Nieder\u00f6sterreich 3950",
    "addr:housenumber":"1",
    "addr:postcode":"3950",
    "addr:street":"Grenzlandstr;Niederoesterreich",
    "iso:country":"AT",
    "sg:address":"Grenzlandstr 1",
    "sg:city":"Gm\u00fcnd",
    "sg:orig_category":"Tischlereien",
    "sg:phone":"+43 2852 513480",
    "sg:postcode":"3950",
    "sg:province":"Nieder\u00f6sterreich",
    "wof:name":"Herzog Erich",
    "wof:placetype":"venue"
},
  "geometry": {"coordinates":[14.9793682098,48.7809753418],"type":"Point"}
}