{
  "type": "Feature",
  "properties": {
    "addr:full":"Gewerbestr 113 Etsdorf am Kamp Nieder\u00f6sterreich 3492",
    "addr:housenumber":"113",
    "addr:postcode":"3492",
    "addr:street":"Kamp",
    "iso:country":"AT",
    "sg:address":"Gewerbestr 113",
    "sg:city":"Etsdorf am Kamp",
    "sg:orig_category":"Autohandel",
    "sg:phone":"+43 676 6204266",
    "sg:postcode":"3492",
    "sg:province":"Nieder\u00f6sterreich",
    "wof:name":"Trondl Manfred KFZ-Handel",
    "wof:placetype":"venue"
},
  "geometry": {"coordinates":[15.7606449127,48.4489593506],"type":"Point"}
}