{
  "type": "Feature",
  "properties": {
    "addr:full":"Neubauerweg 2 Neubau Nieder\u00f6sterreich 2125",
    "addr:housenumber":"2",
    "addr:postcode":"2125",
    "addr:street":"Neubauerweg",
    "iso:country":"AT",
    "sg:address":"Neubauerweg 2",
    "sg:city":"Neubau",
    "sg:orig_category":"Transportunternehmen",
    "sg:phone":"+43 2575 2959",
    "sg:postcode":"2125",
    "sg:province":"Nieder\u00f6sterreich",
    "wof:name":"Meister KG",
    "wof:placetype":"venue"
},
  "geometry": {"coordinates":[16.5057144165,48.4846687317],"type":"Point"}
}