{
  "type": "Feature",
  "properties": {
    "addr:full":"Achauer Str 25 Maria Lanzendorf Nieder\u00f6sterreich 2326",
    "addr:housenumber":"25",
    "addr:postcode":"2326",
    "addr:street":"Str",
    "iso:country":"AT",
    "sg:address":"Achauer Str 25",
    "sg:city":"Maria Lanzendorf",
    "sg:orig_category":"Autoverwertung",
    "sg:phone":"+43 2235 47787",
    "sg:postcode":"2326",
    "sg:province":"Nieder\u00f6sterreich",
    "wof:name":"Leuthner Kurt",
    "wof:placetype":"venue"
},
  "geometry": {"coordinates":[16.4144306183,48.0922584534],"type":"Point"}
}