{
  "type": "Feature",
  "properties": {
    "iso:country":"AT",
    "sg:address":"Lothringenstr. 2 ",
    "sg:city":"Neuhofen an der Krems",
    "sg:classifiers":[
        {
            "category":"Manufacturing",
            "subcategory":"Metals",
            "type":"Manufacturing & Wholesale Goods"
        }
    ],
    "sg:phone":"+43 4372 275225",
    "sg:postcode":"4501",
    "sg:province":"Ober\u00f6sterreich",
    "sg:tags":[
        "metallurgy",
        "metalworking"
    ],
    "wof:name":"HAIRONVILLE AUSTRIA GES.MBH",
    "wof:placetype":"venue"
},
  "geometry": {"coordinates":[14.2216892242,48.1582984924],"type":"Point"}
}