{
  "type": "Feature",
  "properties": {
    "addr:full":"Agerstr 11 Lenzing Ober\u00f6sterreich 4860",
    "addr:housenumber":"11",
    "addr:postcode":"4860",
    "addr:street":"Agerstr",
    "iso:country":"AT",
    "sg:address":"Agerstr 11",
    "sg:city":"Lenzing",
    "sg:orig_category":"Abfallentsorgung U -Verwertung",
    "sg:phone":"+43 4376 7294917",
    "sg:postcode":"4860",
    "sg:province":"Ober\u00f6sterreich",
    "wof:name":"Altstoffsammelzentrum Lenzing",
    "wof:placetype":"venue"
},
  "geometry": {"coordinates":[13.6083650589,47.970375061],"type":"Point"}
}