{
  "type": "Feature",
  "properties": {
    "iso:country":"AT",
    "sg:address":"Sauerhofstr 42",
    "sg:city":"Baden",
    "sg:orig_category":"Finanz- U Wirtschaftsberatung",
    "sg:phone":"+43 4322 5223845",
    "sg:postcode":"2500",
    "sg:province":"Nieder\u00f6sterreich",
    "wof:name":"Schwabe - Ley & Greiner GmbH",
    "wof:placetype":"venue"
},
  "geometry": {"coordinates":[16.2255687714,47.9994354248],"type":"Point"}
}