{
  "type": "Feature",
  "properties": {
    "iso:country":"AT",
    "sg:address":"Industriegebiet Outlet Center 68-69",
    "sg:city":"Parndorf",
    "sg:orig_category":"Bekleidung / Erzeugung U Gro\u00c3\u0178handel",
    "sg:phone":"+43 4321 6620895",
    "sg:postcode":"7111",
    "sg:province":"Burgenland",
    "wof:name":"Hilfiger Stores GesmbH",
    "wof:placetype":"venue"
},
  "geometry": {"coordinates":[16.8575897217,47.9981613159],"type":"Point"}
}