{
  "type": "Feature",
  "properties": {
    "addr:full":"Hauptstr 46 Ried am Riederberg Nieder\u00f6sterreich 3004",
    "addr:housenumber":"46",
    "addr:postcode":"3004",
    "addr:street":"Hauptstr",
    "iso:country":"AT",
    "sg:address":"Hauptstr 46",
    "sg:city":"Ried am Riederberg",
    "sg:orig_category":"Psychotherapie",
    "sg:phone":"+43 4322 712283",
    "sg:postcode":"3004",
    "sg:province":"Nieder\u00f6sterreich",
    "wof:name":"Zehetbauer Carina Dr",
    "wof:placetype":"venue"
},
  "geometry": {"coordinates":[16.0648078918,48.253780365],"type":"Point"}
}