{
  "type": "Feature",
  "properties": {
    "addr:full":"Handelskai 94-96, Millenium Tower  Wien Wien 1200",
    "addr:housenumber":"94-96",
    "addr:postcode":"1200",
    "addr:street":"Handelskai",
    "iso:country":"AT",
    "sg:address":"Handelskai 94-96, Millenium Tower ",
    "sg:city":"Wien",
    "sg:classifiers":[
        {
            "category":"Manufacturing",
            "subcategory":"Metals",
            "type":"Manufacturing & Wholesale Goods"
        }
    ],
    "sg:phone":"+43 1 240250",
    "sg:postcode":"1200",
    "sg:province":"Wien",
    "sg:tags":[
        "aluminium"
    ],
    "wof:name":"MFC Commodities GmbH",
    "wof:placetype":"venue"
},
  "geometry": {"coordinates":[16.3734645844,48.2306060791],"type":"Point"}
}