{
  "type": "Feature",
  "properties": {
    "addr:full":"Drautendorf 48 Niederwaldkirchen Ober\u00f6sterreich 4174",
    "addr:housenumber":"48",
    "addr:postcode":"4174",
    "addr:street":"Drautendorf",
    "iso:country":"AT",
    "sg:address":"Drautendorf 48",
    "sg:city":"Niederwaldkirchen",
    "sg:orig_category":"Elektronische Bauelemente U Bauteile",
    "sg:phone":"+43 4372 3131310",
    "sg:postcode":"4174",
    "sg:province":"Ober\u00f6sterreich",
    "wof:name":"Vogt electronic Austria GmbH",
    "wof:placetype":"venue"
},
  "geometry": {"coordinates":[14.061214447,48.4547958374],"type":"Point"}
}