{
  "type": "Feature",
  "properties": {
    "iso:country":"AT",
    "sg:address":"Kernstr 2",
    "sg:city":"Wien",
    "sg:orig_category":"\u00c3\u201erzte / F Allgemeinmedizin",
    "sg:phone":"+43 1 8044011",
    "sg:postcode":"1120",
    "sg:province":"Wien",
    "wof:name":"Charwat Gertraude MedR Dr",
    "wof:placetype":"venue"
},
  "geometry": {"coordinates":[16.2982368469,48.1702537537],"type":"Point"}
}