{
  "type": "Feature",
  "properties": {
    "iso:country":"AT",
    "sg:address":"Br\u00fcndlangerweg 12",
    "sg:city":"Lienz",
    "sg:orig_category":"Patentdienste U -Verwertung",
    "sg:phone":"+43 4348 5272674",
    "sg:postcode":"9900",
    "sg:province":"Tirol",
    "wof:name":"Brain Flash Patententwicklungs GmbH",
    "wof:placetype":"venue"
},
  "geometry": {"coordinates":[12.7684783936,46.8281173706],"type":"Point"}
}