{
  "type": "Feature",
  "properties": {
    "iso:country":"AT",
    "sg:address":"Odoakerg 22/14",
    "sg:city":"Wien",
    "sg:orig_category":"Telefonanlagen",
    "sg:phone":"+43 4312 310000",
    "sg:postcode":"1160",
    "sg:province":"Wien",
    "wof:name":"Audio Communication Tonproduktion Harald M\u00e4dicke",
    "wof:placetype":"venue"
},
  "geometry": {"coordinates":[16.3089828491,48.2164382935],"type":"Point"}
}