{
  "type": "Feature",
  "properties": {
    "addr:full":"Reinprechtsdorf Str 36 Wien Wien 1050",
    "addr:housenumber":"36",
    "addr:postcode":"1050",
    "addr:street":"Reinprechtsdorf Str",
    "iso:country":"AT",
    "sg:address":"Reinprechtsdorf Str 36",
    "sg:city":"Wien",
    "sg:orig_category":"Tabaktrafiken",
    "sg:phone":"+43 1 5457990",
    "sg:postcode":"1050",
    "sg:province":"Wien",
    "wof:name":"Hofmeister Alfred",
    "wof:placetype":"venue"
},
  "geometry": {"coordinates":[16.3546161652,48.1853981018],"type":"Point"}
}