{
  "type": "Feature",
  "properties": {
    "addr:full":"Nr 57 Gro\u00dfwilfersdorf Steiermark 8263",
    "addr:postcode":"8263",
    "addr:street":"Nr",
    "iso:country":"AT",
    "sg:address":"Nr 57",
    "sg:city":"Gro\u00dfwilfersdorf",
    "sg:orig_category":"Autohandel",
    "sg:phone":"+43 4366 42352073",
    "sg:postcode":"8263",
    "sg:province":"Steiermark",
    "wof:name":"Auto Zentrum Gro\u00dfwilfersdorf",
    "wof:placetype":"venue"
},
  "geometry": {"coordinates":[15.9948101044,47.0773239136],"type":"Point"}
}