{
  "type": "Feature",
  "properties": {
    "addr:full":"Kirchensteig 3 Gloggnitz Nieder\u00f6sterreich 2640",
    "addr:housenumber":"3",
    "addr:postcode":"2640",
    "addr:street":"Kirchensteig",
    "iso:country":"AT",
    "sg:address":"Kirchensteig 3",
    "sg:city":"Gloggnitz",
    "sg:orig_category":"Tourismusinformation U -Organisationen",
    "sg:phone":"+43 2662 43000",
    "sg:postcode":"2640",
    "sg:province":"Nieder\u00f6sterreich",
    "wof:name":"Schlo\u00df Gloggnitz -Tourismusinformation",
    "wof:placetype":"venue"
},
  "geometry": {"coordinates":[15.9288082123,47.6739616394],"type":"Point"}
}