{
  "type": "Feature",
  "properties": {
    "addr:full":"Wagramer Str DZ Top 139 Wien Wien 1220",
    "addr:housenumber":"139",
    "addr:postcode":"1220",
    "addr:street":"Str Dz Top",
    "iso:country":"AT",
    "sg:address":"Wagramer Str DZ Top 139",
    "sg:city":"Wien",
    "sg:orig_category":"Bekleidung / Einzelhandel",
    "sg:phone":"+43 1 20256500",
    "sg:postcode":"1220",
    "sg:province":"Wien",
    "wof:name":"KBS Kleider Bauer Betriebs-GmbH",
    "wof:placetype":"venue"
},
  "geometry": {"coordinates":[16.444606781,48.2497138977],"type":"Point"}
}