{
  "type": "Feature",
  "properties": {
    "addr:full":"Wiener Str 18 Wiener Neustadt Nieder\u00f6sterreich 2700",
    "addr:postcode":"2700",
    "addr:street":"18",
    "iso:country":"AT",
    "sg:address":"Wiener Str 18",
    "sg:city":"Wiener Neustadt",
    "sg:orig_category":"Damenmoden",
    "sg:phone":"+43 2622 83024",
    "sg:postcode":"2700",
    "sg:province":"Nieder\u00f6sterreich",
    "wof:name":"Vero Moda",
    "wof:placetype":"venue"
},
  "geometry": {"coordinates":[16.2440795898,47.8144111633],"type":"Point"}
}