{
  "type": "Feature",
  "properties": {
    "addr:full":"Nr 35 Ruden K\u00e4rnten 9113",
    "addr:postcode":"9113",
    "addr:street":"Nr;Kaernten",
    "iso:country":"AT",
    "sg:address":"Nr 35",
    "sg:city":"Ruden",
    "sg:orig_category":"Non-Classified Establishments",
    "sg:phone":"+43 5 91332152",
    "sg:postcode":"9113",
    "sg:province":"K\u00e4rnten",
    "wof:name":"Gendarmerieposten",
    "wof:placetype":"venue"
},
  "geometry": {"coordinates":[14.7703266144,46.6569061279],"type":"Point"}
}