{
  "type": "Feature",
  "properties": {
    "addr:full":"Nr 148 Semriach Steiermark 8102",
    "addr:postcode":"8102",
    "addr:street":"Nr 148",
    "iso:country":"AT",
    "sg:address":"Nr 148",
    "sg:city":"Semriach",
    "sg:orig_category":"Tischlereien",
    "sg:phone":"+43 3127 82850",
    "sg:postcode":"8102",
    "sg:province":"Steiermark",
    "wof:name":"Dallago Max Holzbau GesmbH & Co KG",
    "wof:placetype":"venue"
},
  "geometry": {"coordinates":[15.4031257629,47.217502594],"type":"Point"}
}