{
  "type": "Feature",
  "properties": {
    "addr:full":"Nr 8 Weilbach Ober\u00f6sterreich 4984",
    "addr:postcode":"4984",
    "addr:street":"Nr;Oberoesterreich",
    "iso:country":"AT",
    "sg:address":"Nr 8",
    "sg:city":"Weilbach",
    "sg:orig_category":"Volksschulen",
    "sg:phone":"+43 7757 6488",
    "sg:postcode":"4984",
    "sg:province":"Ober\u00f6sterreich",
    "wof:name":"Volksschule",
    "wof:placetype":"venue"
},
  "geometry": {"coordinates":[13.3731956482,48.2770767212],"type":"Point"}
}