{
  "type": "Feature",
  "properties": {
    "addr:full":"Sportplatzweg 8 Mieming Tirol 6414",
    "addr:housenumber":"8",
    "addr:postcode":"6414",
    "addr:street":"Sportplatzweg;Tirol",
    "iso:country":"AT",
    "sg:address":"Sportplatzweg 8",
    "sg:city":"Mieming",
    "sg:orig_category":"Autoreparatur",
    "sg:phone":"+43 5264 5056",
    "sg:postcode":"6414",
    "sg:province":"Tirol",
    "wof:name":"Auto Josef Soraperra KEG",
    "wof:placetype":"venue"
},
  "geometry": {"coordinates":[10.9804544449,47.2974433899],"type":"Point"}
}