{
  "type": "Feature",
  "properties": {
    "addr:full":"Nr 24 Thernberg Nieder\u00f6sterreich 2832",
    "addr:postcode":"2832",
    "addr:street":"Nr 24 Thernberg",
    "iso:country":"AT",
    "sg:address":"Nr 24",
    "sg:city":"Thernberg",
    "sg:orig_category":"Forstverwaltungen",
    "sg:phone":"+43 2629 3601",
    "sg:postcode":"2832",
    "sg:province":"Nieder\u00f6sterreich",
    "wof:name":"Lilian Tuider",
    "wof:placetype":"venue"
},
  "geometry": {"coordinates":[16.1771736145,47.6614875793],"type":"Point"}
}