{
  "type": "Feature",
  "properties": {
    "addr:full":"Im Dorf 8 M\u00f6derbrugg Steiermark 8763",
    "addr:housenumber":"8",
    "addr:postcode":"8763",
    "addr:street":"Im Dorf",
    "iso:country":"AT",
    "sg:address":"Im Dorf 8",
    "sg:city":"M\u00f6derbrugg",
    "sg:orig_category":"Tankstellen",
    "sg:phone":"+43 4335 712203",
    "sg:postcode":"8763",
    "sg:province":"Steiermark",
    "wof:name":"Pottmann-Steinerberger - Cafe-Shop",
    "wof:placetype":"venue"
},
  "geometry": {"coordinates":[14.480966568,47.2830429077],"type":"Point"}
}