{
  "type": "Feature",
  "properties": {
    "iso:country":"AT",
    "sg:address":"Landesstrasse 5",
    "sg:city":"Henndorf am Wallersee",
    "sg:classifiers":[
        {
            "category":"Home & Garden",
            "subcategory":"Building Materials",
            "type":"Retail Goods"
        }
    ],
    "sg:phone":"+43 6214 8551",
    "sg:postcode":"5302",
    "sg:province":"Salzburg",
    "sg:tags":[
        "steel",
        "balcony"
    ],
    "wof:name":"Johann Ebner KG",
    "wof:placetype":"venue"
},
  "geometry": {"coordinates":[13.1893196106,47.9001312256],"type":"Point"}
}