{
  "type": "Feature",
  "properties": {
    "addr:full":"Neulerchenfelder Str 34 Wien Wien 1160",
    "addr:postcode":"1160",
    "addr:street":"Str 34",
    "iso:country":"AT",
    "sg:address":"Neulerchenfelder Str 34",
    "sg:city":"Wien",
    "sg:orig_category":"Banken U Sparkassen",
    "sg:phone":"+43 4314 055481",
    "sg:postcode":"1160",
    "sg:province":"Wien",
    "wof:name":"Bankomat d Volksbank Wien AG",
    "wof:placetype":"venue"
},
  "geometry": {"coordinates":[16.3347854614,48.2113647461],"type":"Point"}
}