{
  "type": "Feature",
  "properties": {
    "iso:country":"AT",
    "sg:address":"Dr Schroll-Str 12",
    "sg:city":"Klagenfurt-Viktring",
    "sg:classifiers":[
        {
            "category":"Travel",
            "subcategory":"Hotels & Motels",
            "type":"Entertainment"
        }
    ],
    "sg:phone":"+43 463 282426",
    "sg:postcode":"9073",
    "sg:province":"K\u00e4rnten",
    "wof:name":"Online Reservation Systems GmbH - Nethotels Carinthia",
    "wof:placetype":"venue"
},
  "geometry": {"coordinates":[14.2722606659,46.5953330994],"type":"Point"}
}