{
  "type": "Feature",
  "properties": {
    "iso:country":"AT",
    "sg:address":"Italiener Str 15",
    "sg:city":"Villach",
    "sg:orig_category":"Gesundheitsvorsorge",
    "sg:phone":"+43 4242 217317",
    "sg:postcode":"9500",
    "sg:province":"K\u00e4rnten",
    "wof:name":"geps Zentrum f aktive Gesundheitspflege",
    "wof:placetype":"venue"
},
  "geometry": {"coordinates":[13.8436727524,46.6107177734],"type":"Point"}
}