{
  "type": "Feature",
  "properties": {
    "addr:full":"Rossaug. 5 Innsbruck Tirol 6020",
    "addr:housenumber":"5",
    "addr:postcode":"6020",
    "addr:street":"Rossaug.;Tirol",
    "iso:country":"AT",
    "sg:address":"Rossaug. 5",
    "sg:city":"Innsbruck",
    "sg:orig_category":"Miscellaneous Products",
    "sg:phone":"+43 4351 2345331",
    "sg:postcode":"6020",
    "sg:province":"Tirol",
    "wof:name":"INNVERLAG INNSBRUCK GMBH & CO KG",
    "wof:placetype":"venue"
},
  "geometry": {"coordinates":[11.4320735931,47.2725906372],"type":"Point"}
}