{
  "type": "Feature",
  "properties": {
    "iso:country":"AT",
    "sg:address":"Haslach 69",
    "sg:city":"Gleinst\u00e4tten",
    "sg:orig_category":"Autobusunternehmen",
    "sg:phone":"+43 3457 2485",
    "sg:postcode":"8443",
    "sg:province":"Steiermark",
    "wof:name":"Resch Johann",
    "wof:placetype":"venue"
},
  "geometry": {"coordinates":[15.349240303,46.7488517761],"type":"Point"}
}