{
  "type": "Feature",
  "properties": {
    "addr:full":"Nr 33 Krakaudorf Steiermark 8854",
    "addr:postcode":"8854",
    "addr:street":"Nr",
    "iso:country":"AT",
    "sg:address":"Nr 33",
    "sg:city":"Krakaudorf",
    "sg:classifiers":[
        {
            "category":"Travel",
            "subcategory":"Hotels & Motels",
            "type":"Entertainment"
        }
    ],
    "sg:phone":"+43 3535 82700",
    "sg:postcode":"8854",
    "sg:province":"Steiermark",
    "wof:name":"Hotel-Restaurant Stigenwirth",
    "wof:placetype":"venue"
},
  "geometry": {"coordinates":[13.9644861221,47.1889724731],"type":"Point"}
}