{
  "type": "Feature",
  "properties": {
    "addr:full":"Am Concorde Park 1b6/Top 106 Schwechat Nieder\u00f6sterreich 2320",
    "addr:housenumber":"1b6 / top 106",
    "addr:postcode":"2320",
    "addr:street":"Am Concorde Park;Niederoesterreich",
    "iso:country":"AT",
    "sg:address":"Am Concorde Park 1b6/Top 106",
    "sg:city":"Schwechat",
    "sg:classifiers":[
        {
            "category":"Shopping",
            "subcategory":"Computers & Home Electronics",
            "type":"Retail Goods"
        }
    ],
    "sg:phone":"+43 1 70132701",
    "sg:postcode":"2320",
    "sg:province":"Nieder\u00f6sterreich",
    "sg:tags":[
        "system",
        "automation"
    ],
    "sg:website":"www.zwick.de",
    "wof:name":"Zwick Materialpr\u00fcfung Vertriebsb\u00fcro \u00d6sterreich",
    "wof:placetype":"venue"
},
  "geometry": {"coordinates":[16.4771652222,48.1398735046],"type":"Point"}
}