{
  "type": "Feature",
  "properties": {
    "addr:full":"Gewerbestr 6 Br\u00fcckl K\u00e4rnten 9371",
    "addr:housenumber":"6",
    "addr:postcode":"9371",
    "addr:street":"Gewerbestr;Kaernten",
    "iso:country":"AT",
    "sg:address":"Gewerbestr 6",
    "sg:city":"Br\u00fcckl",
    "sg:orig_category":"Elektroinstallationsunternehmen",
    "sg:phone":"+43 4214 3350",
    "sg:postcode":"9371",
    "sg:province":"K\u00e4rnten",
    "wof:name":"Elektro Jellitsch",
    "wof:placetype":"venue"
},
  "geometry": {"coordinates":[14.5312738419,46.7499046326],"type":"Point"}
}