{
  "type": "Feature",
  "properties": {
    "iso:country":"AT",
    "sg:address":"Unterer Stadtpl 13",
    "sg:city":"Kufstein",
    "sg:orig_category":"Boutiquen",
    "sg:phone":"+43 5372 61741",
    "sg:postcode":"6330",
    "sg:province":"Tirol",
    "wof:name":"Boutique Carat",
    "wof:placetype":"venue"
},
  "geometry": {"coordinates":[12.168923378,47.5830612183],"type":"Point"}
}