{
  "type": "Feature",
  "properties": {
    "addr:full":"Linzer Str 251 Wien Wien 1140",
    "addr:housenumber":"251",
    "addr:postcode":"1140",
    "addr:street":"Linzer Str",
    "iso:country":"AT",
    "sg:address":"Linzer Str 251",
    "sg:city":"Wien",
    "sg:orig_category":"Raumausstattung",
    "sg:phone":"+43 4319 859780",
    "sg:postcode":"1140",
    "sg:province":"Wien",
    "sg:website":"kreinhoefner.at",
    "wof:name":"Kreinh\u00f6fner Franz",
    "wof:placetype":"venue"
},
  "geometry": {"coordinates":[16.2847175598,48.194694519],"type":"Point"}
}