{
  "type": "Feature",
  "properties": {
    "iso:country":"AT",
    "sg:address":"Maisweg 13",
    "sg:city":"Engerwitzdorf",
    "sg:orig_category":"Waagen / Einzelhandel",
    "sg:phone":"+43 7235 641340",
    "sg:postcode":"4209",
    "sg:province":"Ober\u00f6sterreich",
    "wof:name":"Wimmer Manfred",
    "wof:placetype":"venue"
},
  "geometry": {"coordinates":[14.4395523071,48.3551101685],"type":"Point"}
}