{
  "type": "Feature",
  "properties": {
    "addr:full":"Neuer Pl 13 Klagenfurt K\u00e4rnten 9020",
    "addr:housenumber":"13",
    "addr:postcode":"9020",
    "addr:street":"Neuer Pl;Kaernten",
    "iso:country":"AT",
    "sg:address":"Neuer Pl 13",
    "sg:city":"Klagenfurt",
    "sg:orig_category":"Damenmoden",
    "sg:phone":"+43 463 5130940",
    "sg:postcode":"9020",
    "sg:province":"K\u00e4rnten",
    "wof:name":"C & A Mode GesmbH & Co KG",
    "wof:placetype":"venue"
},
  "geometry": {"coordinates":[14.3076295853,46.6234741211],"type":"Point"}
}