{
  "type": "Feature",
  "properties": {
    "addr:full":"Gletscherm\u00fchlstr 2 Bad Gastein Salzburg 5640",
    "addr:housenumber":"2",
    "addr:postcode":"5640",
    "addr:street":"Gletschermuehlstr;Salzburg",
    "iso:country":"AT",
    "sg:address":"Gletscherm\u00fchlstr 2",
    "sg:city":"Bad Gastein",
    "sg:orig_category":"Pensionen / Privatzimmer",
    "sg:phone":"+43 6434 2324",
    "sg:postcode":"5640",
    "sg:province":"Salzburg",
    "wof:name":"Fr\u00fchst\u00fcckspension Golker",
    "wof:placetype":"venue"
},
  "geometry": {"coordinates":[13.1339550018,47.1185417175],"type":"Point"}
}