{
  "type": "Feature",
  "properties": {
    "addr:full":"Altstadt 8 Linz Ober\u00f6sterreich 4020",
    "addr:housenumber":"8",
    "addr:postcode":"4020",
    "addr:street":"Altstadt",
    "iso:country":"AT",
    "sg:address":"Altstadt 8",
    "sg:city":"Linz",
    "sg:orig_category":"Psychotherapie",
    "sg:phone":"+43 732 738645",
    "sg:postcode":"4020",
    "sg:province":"Ober\u00f6sterreich",
    "wof:name":"Ahammer Beatrix Mag",
    "wof:placetype":"venue"
},
  "geometry": {"coordinates":[14.2841596603,48.305431366],"type":"Point"}
}