{
  "type": "Feature",
  "properties": {
    "addr:full":"Krottendorf 24 Kirchham Ober\u00f6sterreich 4656",
    "addr:housenumber":"24",
    "addr:postcode":"4656",
    "addr:street":"Krottendorf",
    "iso:country":"AT",
    "sg:address":"Krottendorf 24",
    "sg:city":"Kirchham",
    "sg:orig_category":"Garten- U Landschaftsgestaltung",
    "sg:phone":"+43 76192359",
    "sg:postcode":"4656",
    "sg:province":"Ober\u00f6sterreich",
    "wof:name":"Danner Elke",
    "wof:placetype":"venue"
},
  "geometry": {"coordinates":[13.8794260025,47.9475860596],"type":"Point"}
}