{
  "type": "Feature",
  "properties": {
    "iso:country":"AT",
    "sg:address":"Riegerting",
    "sg:city":"Mehrnbach",
    "sg:orig_category":"Feuerwehren",
    "sg:phone":"+43 4377 5288222",
    "sg:postcode":"4941",
    "sg:province":"Ober\u00f6sterreich",
    "wof:name":"Freiwillige Feuerwehr Riegerting",
    "wof:placetype":"venue"
},
  "geometry": {"coordinates":[13.4035701752,48.1778640747],"type":"Point"}
}