{
  "type": "Feature",
  "properties": {
    "iso:country":"AT",
    "sg:address":"Parz/734/1",
    "sg:city":"Waldhausen",
    "sg:orig_category":"Holzhandel",
    "sg:phone":"+43 2877 7143",
    "sg:postcode":"3914",
    "sg:province":"Nieder\u00f6sterreich",
    "wof:name":"Euro Timber HandelsgesmbH",
    "wof:placetype":"venue"
},
  "geometry": {"coordinates":[15.2610387802,48.5218048096],"type":"Point"}
}