{
  "type": "Feature",
  "properties": {
    "iso:country":"AT",
    "sg:address":"Autobahn A 22",
    "sg:city":"Stockerau",
    "sg:orig_category":"Tankstellen",
    "sg:phone":"+43 2266 63287",
    "sg:postcode":"2000",
    "sg:province":"Nieder\u00f6sterreich",
    "wof:name":"OMV AG",
    "wof:placetype":"venue"
},
  "geometry": {"coordinates":[16.2074947357,48.3848304749],"type":"Point"}
}