{
  "type": "Feature",
  "properties": {
    "addr:full":"Hauptstr 53a Seekirchen am Wallersee Salzburg 5201",
    "addr:housenumber":"53a",
    "addr:postcode":"5201",
    "addr:street":"Hauptstr;Salzburg",
    "iso:country":"AT",
    "sg:address":"Hauptstr 53a",
    "sg:city":"Seekirchen am Wallersee",
    "sg:classifiers":[
        {
            "category":"Professional",
            "subcategory":"Computer Services",
            "type":"Services"
        }
    ],
    "sg:phone":"+43 4362 122132",
    "sg:postcode":"5201",
    "sg:province":"Salzburg",
    "sg:tags":[
        "software"
    ],
    "wof:name":"K\u00f6ckerbauer Wolfgang Ing",
    "wof:placetype":"venue"
},
  "geometry": {"coordinates":[13.1231775284,47.8959617615],"type":"Point"}
}