{
  "type": "Feature",
  "properties": {
    "addr:full":"Zeughausstr 2 Burgkirchen Ober\u00f6sterreich 5274",
    "addr:housenumber":"2",
    "addr:postcode":"5274",
    "addr:street":"Zeughausstr",
    "iso:country":"AT",
    "sg:address":"Zeughausstr 2",
    "sg:city":"Burgkirchen",
    "sg:orig_category":"Feuerwehren",
    "sg:phone":"+43 7724 3923",
    "sg:postcode":"5274",
    "sg:province":"Ober\u00f6sterreich",
    "wof:name":"Feuerwehr Burgkirchen",
    "wof:placetype":"venue"
},
  "geometry": {"coordinates":[13.1033363342,48.2063713074],"type":"Point"}
}