{
  "type": "Feature",
  "properties": {
    "addr:full":"Donau-City-Str 6/10 Stock Wien Wien 1220",
    "addr:housenumber":"6 / 10",
    "addr:postcode":"1220",
    "addr:street":"Donau-City-Str",
    "iso:country":"AT",
    "sg:address":"Donau-City-Str 6/10 Stock",
    "sg:city":"Wien",
    "sg:orig_category":"Medizintechnik",
    "sg:phone":"+43 1 26016",
    "sg:postcode":"1220",
    "sg:province":"Wien",
    "wof:name":"General Electric GesmbH Nfg OHG",
    "wof:placetype":"venue"
},
  "geometry": {"coordinates":[16.444606781,48.2497138977],"type":"Point"}
}