{
  "type": "Feature",
  "properties": {
    "addr:full":"Reitdorfer Str 182 Flachau Salzburg 5542",
    "addr:housenumber":"182",
    "addr:postcode":"5542",
    "addr:street":"Str;Salzburg",
    "iso:country":"AT",
    "sg:address":"Reitdorfer Str 182",
    "sg:city":"Flachau",
    "sg:orig_category":"Appartements / Ferienwohnungen",
    "sg:phone":"+43 4364 5733749",
    "sg:postcode":"5542",
    "sg:province":"Salzburg",
    "wof:name":"Aparthotel Pichler",
    "wof:placetype":"venue"
},
  "geometry": {"coordinates":[13.3960180283,47.3768577576],"type":"Point"}
}