{
  "type": "Feature",
  "properties": {
    "addr:full":"Linzer Str 6 Haag Nieder\u00f6sterreich 3350",
    "addr:housenumber":"6",
    "addr:postcode":"3350",
    "addr:street":"Linzer Str",
    "iso:country":"AT",
    "sg:address":"Linzer Str 6",
    "sg:city":"Haag",
    "sg:orig_category":"Restaurants: Chinesisch",
    "sg:phone":"+43 7434 44856",
    "sg:postcode":"3350",
    "sg:province":"Nieder\u00f6sterreich",
    "wof:name":"China Restaurant - Cheng & Ye GesmbH",
    "wof:placetype":"venue"
},
  "geometry": {"coordinates":[14.5649414062,48.111541748],"type":"Point"}
}