{
  "type": "Feature",
  "properties": {
    "addr:full":"Zellerhofstrasse 8 Lunz am See Nieder\u00f6sterreich 3293",
    "addr:housenumber":"8",
    "addr:postcode":"3293",
    "addr:street":"Zellerhofstrasse;Niederoesterreich",
    "iso:country":"AT",
    "sg:address":"Zellerhofstrasse 8",
    "sg:city":"Lunz am See",
    "sg:classifiers":[
        {
            "category":"Shopping",
            "subcategory":"Luggage & Leather Goods",
            "type":"Retail Goods"
        }
    ],
    "sg:phone":"+43 7486 8360",
    "sg:postcode":"3293",
    "sg:province":"Nieder\u00f6sterreich",
    "sg:tags":[
        "cap"
    ],
    "sg:website":"lunz.at/schneidereibuben",
    "wof:name":"Emmerich Buben",
    "wof:placetype":"venue"
},
  "geometry": {"coordinates":[15.0341939926,47.8608932495],"type":"Point"}
}