{
  "type": "Feature",
  "properties": {
    "addr:full":"Kuglg 39 Kramsach Tirol 6233",
    "addr:housenumber":"39",
    "addr:postcode":"6233",
    "addr:street":"Kuglg;Tirol",
    "iso:country":"AT",
    "sg:address":"Kuglg 39",
    "sg:city":"Kramsach",
    "sg:orig_category":"Autobusunternehmen",
    "sg:phone":"+43 5337 66077",
    "sg:postcode":"6233",
    "sg:province":"Tirol",
    "wof:name":"Lanzinger Busreisen GmbH",
    "wof:placetype":"venue"
},
  "geometry": {"coordinates":[11.8832015991,47.4460906982],"type":"Point"}
}