{
  "type": "Feature",
  "properties": {
    "addr:full":"Blankenberg 7 Sierning Ober\u00f6sterreich 4522",
    "addr:housenumber":"7",
    "addr:postcode":"4522",
    "addr:street":"Blankenberg",
    "iso:country":"AT",
    "sg:address":"Blankenberg 7",
    "sg:city":"Sierning",
    "sg:orig_category":"Waren Aller Art",
    "sg:phone":"+43 7259 5300",
    "sg:postcode":"4522",
    "sg:province":"Ober\u00f6sterreich",
    "wof:name":"Dewanger GesmbH",
    "wof:placetype":"venue"
},
  "geometry": {"coordinates":[14.2998399734,48.0387916565],"type":"Point"}
}