{
  "type": "Feature",
  "properties": {
    "addr:full":"Lengenfelder Str 2 Lengenfeld Nieder\u00f6sterreich 3552",
    "addr:housenumber":"2",
    "addr:postcode":"3552",
    "addr:street":"Str",
    "iso:country":"AT",
    "sg:address":"Lengenfelder Str 2",
    "sg:city":"Lengenfeld",
    "sg:orig_category":"Feuerwehren",
    "sg:phone":"+43 2719 2580",
    "sg:postcode":"3552",
    "sg:province":"Nieder\u00f6sterreich",
    "wof:name":"Freiwillige Feuerwehr Stratzing",
    "wof:placetype":"venue"
},
  "geometry": {"coordinates":[15.6048431396,48.450302124],"type":"Point"}
}