{
  "type": "Feature",
  "properties": {
    "addr:full":"Danfossstrasse 8 Guntramsdorf Nieder\u00f6sterreich 2353",
    "addr:housenumber":"8",
    "addr:postcode":"2353",
    "addr:street":"Danfossstrasse",
    "iso:country":"AT",
    "sg:address":"Danfossstrasse 8",
    "sg:city":"Guntramsdorf",
    "sg:classifiers":[
        {
            "category":"Autos & Motor Vehicles",
            "subcategory":"Fuel & Gas Station",
            "type":"Retail Goods"
        }
    ],
    "sg:phone":"+43 2236 5040",
    "sg:postcode":"2353",
    "sg:province":"Nieder\u00f6sterreich",
    "sg:tags":[
        "control",
        "electric",
        "speed",
        "devices",
        "controller",
        "electronic"
    ],
    "sg:website":"danfoss.com",
    "wof:name":"Danfoss Ges.m.b.H.",
    "wof:placetype":"venue"
},
  "geometry": {"coordinates":[16.3081054688,48.0558662415],"type":"Point"}
}