{
  "type": "Feature",
  "properties": {
    "addr:full":"Dr.-Kraitschek-Gasse 7-9 Pottendorf Nieder\u00f6sterreich 2486",
    "addr:housenumber":"7-9",
    "addr:postcode":"2486",
    "addr:street":"Dr.-Kraitschek-Gasse",
    "iso:country":"AT",
    "sg:address":"Dr.-Kraitschek-Gasse 7-9",
    "sg:city":"Pottendorf",
    "sg:classifiers":[
        {
            "category":"Home & Garden",
            "subcategory":"Carpets & Floor Coverings",
            "type":"Retail Goods"
        }
    ],
    "sg:phone":"+43 2623 733000",
    "sg:postcode":"2486",
    "sg:province":"Nieder\u00f6sterreich",
    "sg:tags":[
        "carpeting"
    ],
    "sg:website":"eniacarpets.at",
    "wof:name":"Enia Carpet Austria Gesellschaft m.b.H.",
    "wof:placetype":"venue"
},
  "geometry": {"coordinates":[16.391746521,47.9055137634],"type":"Point"}
}