{
  "type": "Feature",
  "properties": {
    "addr:full":"Ranser Feld 22 Aldrans Tirol 6071",
    "addr:housenumber":"22",
    "addr:postcode":"6071",
    "addr:street":"Ranser Feld;Tirol",
    "iso:country":"AT",
    "sg:address":"Ranser Feld 22",
    "sg:city":"Aldrans",
    "sg:orig_category":"Schneidereien",
    "sg:phone":"+43 4351 2346074",
    "sg:postcode":"6071",
    "sg:province":"Tirol",
    "wof:name":"Modellsalon Brigitte",
    "wof:placetype":"venue"
},
  "geometry": {"coordinates":[11.4444980621,47.2448272705],"type":"Point"}
}