{
  "type": "Feature",
  "properties": {
    "iso:country":"AT",
    "sg:address":"10.Oktober-Str 32",
    "sg:city":"M\u00f6llbr\u00fccke",
    "sg:orig_category":"Unterhaltungselektronik / Einzelhandel",
    "sg:phone":"+43 4347 692744",
    "sg:postcode":"9813",
    "sg:province":"K\u00e4rnten",
    "wof:name":"Tele Video Point Inh Karl-Heinz Wallner",
    "wof:placetype":"venue"
},
  "geometry": {"coordinates":[13.3718185425,46.8317222595],"type":"Point"}
}