{
  "type": "Feature",
  "properties": {
    "addr:full":"Mucharg 4 Lienz Tirol 9900",
    "addr:housenumber":"4",
    "addr:postcode":"9900",
    "addr:street":"Mucharg;Tirol",
    "iso:country":"AT",
    "sg:address":"Mucharg 4",
    "sg:city":"Lienz",
    "sg:orig_category":"Bibliotheken",
    "sg:phone":"+43 4852 63972",
    "sg:postcode":"9900",
    "sg:province":"Tirol",
    "wof:name":"B\u00fccherei Lienz",
    "wof:placetype":"venue"
},
  "geometry": {"coordinates":[12.7657079697,46.8305015564],"type":"Point"}
}