{
  "type": "Feature",
  "properties": {
    "iso:country":"AT",
    "sg:address":"Franz-Samwald-Str 24",
    "sg:city":"Ternitz",
    "sg:orig_category":"Energietechnik",
    "sg:phone":"+43 2630 37320",
    "sg:postcode":"2630",
    "sg:province":"Nieder\u00f6sterreich",
    "wof:name":"Schranz Adolf",
    "wof:placetype":"venue"
},
  "geometry": {"coordinates":[16.0149402618,47.7022285461],"type":"Point"}
}