{
  "type": "Feature",
  "properties": {
    "addr:full":"Franz-Samwald-Str 24 Ternitz Nieder\u00f6sterreich 2630",
    "addr:housenumber":"24",
    "addr:postcode":"2630",
    "addr:street":"Franz-Samwald-Str",
    "iso:country":"AT",
    "sg:address":"Franz-Samwald-Str 24",
    "sg:city":"Ternitz",
    "sg:orig_category":"Energietechnik",
    "sg:phone":"+43 2630 37320",
    "sg:postcode":"2630",
    "sg:province":"Nieder\u00f6sterreich",
    "wof:name":"Schranz Adolf",
    "wof:placetype":"venue"
},
  "geometry": {"coordinates":[16.0149402618,47.7022285461],"type":"Point"}
}