{
  "type": "Feature",
  "properties": {
    "addr:full":"L H Jungnickel-Str 11 Villach K\u00e4rnten 9500",
    "addr:housenumber":"11",
    "addr:postcode":"9500",
    "addr:street":"Kaernten",
    "iso:country":"AT",
    "sg:address":"L H Jungnickel-Str 11",
    "sg:city":"Villach",
    "sg:orig_category":"Elektronik",
    "sg:phone":"+43 4242 58470",
    "sg:postcode":"9500",
    "sg:province":"K\u00e4rnten",
    "wof:name":"ECB E-Consulting Brunner - Ing Armin Brunner",
    "wof:placetype":"venue"
},
  "geometry": {"coordinates":[13.8283967972,46.6166801453],"type":"Point"}
}