{
  "type": "Feature",
  "properties": {
    "addr:full":"Speckbacherstr 20 St. Johann in Tirol Tirol 6380",
    "addr:housenumber":"20",
    "addr:postcode":"6380",
    "addr:street":"Speckbacherstr;Tirol",
    "iso:country":"AT",
    "sg:address":"Speckbacherstr 20",
    "sg:city":"St. Johann in Tirol",
    "sg:orig_category":"Boutiquen",
    "sg:phone":"+43 4353 5262506",
    "sg:postcode":"6380",
    "sg:province":"Tirol",
    "wof:name":"Cecil - Shop",
    "wof:placetype":"venue"
},
  "geometry": {"coordinates":[12.4257287979,47.5205230713],"type":"Point"}
}