{
  "type": "Feature",
  "properties": {
    "iso:country":"AT",
    "sg:address":"Esterhazypl 1",
    "sg:city":"Rattersdorf-Liebing",
    "sg:orig_category":"Lebensmittel / Einzelhandel",
    "sg:phone":"+43 2611 2317",
    "sg:postcode":"7443",
    "sg:province":"Burgenland",
    "wof:name":"ADEG - Schlapschy",
    "wof:placetype":"venue"
},
  "geometry": {"coordinates":[16.4945831299,47.4136657715],"type":"Point"}
}