{
  "type": "Feature",
  "properties": {
    "addr:full":"Pyburg 68 Ennsdorf Nieder\u00f6sterreich 4482",
    "addr:housenumber":"68",
    "addr:postcode":"4482",
    "addr:street":"Pyburg",
    "iso:country":"AT",
    "sg:address":"Pyburg 68",
    "sg:city":"Ennsdorf",
    "sg:orig_category":"Estriche",
    "sg:phone":"+43 4367 66097063",
    "sg:postcode":"4482",
    "sg:province":"Nieder\u00f6sterreich",
    "wof:name":"Floimayr Karl Styroporgranulaterzeugung u Aufbringung",
    "wof:placetype":"venue"
},
  "geometry": {"coordinates":[14.5264797211,48.2271881104],"type":"Point"}
}