{
  "type": "Feature",
  "properties": {
    "addr:full":"Steinbichlstr 41 Pinsdorf Ober\u00f6sterreich 4812",
    "addr:housenumber":"41",
    "addr:postcode":"4812",
    "addr:street":"Steinbichlstr",
    "iso:country":"AT",
    "sg:address":"Steinbichlstr 41",
    "sg:city":"Pinsdorf",
    "sg:orig_category":"Physiotherapie",
    "sg:phone":"+43 664 5312800",
    "sg:postcode":"4812",
    "sg:province":"Ober\u00f6sterreich",
    "wof:name":"H\u00f6ller Ursula Dipl-PT",
    "wof:placetype":"venue"
},
  "geometry": {"coordinates":[13.7744626999,47.9250907898],"type":"Point"}
}