{
  "type": "Feature",
  "properties": {
    "addr:full":"Unterer Pl 10 Eberstein K\u00e4rnten 9372",
    "addr:housenumber":"10",
    "addr:postcode":"9372",
    "addr:street":"Unterer Pl;Kaernten",
    "iso:country":"AT",
    "sg:address":"Unterer Pl 10",
    "sg:city":"Eberstein",
    "sg:orig_category":"Banken U Sparkassen",
    "sg:phone":"+43 5 010030830",
    "sg:postcode":"9372",
    "sg:province":"K\u00e4rnten",
    "wof:name":"K\u00e4rntner Sparkasse AG",
    "wof:placetype":"venue"
},
  "geometry": {"coordinates":[14.5582609177,46.8075752258],"type":"Point"}
}