{
  "type": "Feature",
  "properties": {
    "addr:full":"Walchen 166 Piesendorf Salzburg 5721",
    "addr:housenumber":"166",
    "addr:postcode":"5721",
    "addr:street":"Walchen;Salzburg",
    "iso:country":"AT",
    "sg:address":"Walchen 166",
    "sg:city":"Piesendorf",
    "sg:orig_category":"Bergbahnen",
    "sg:phone":"+43 6549 7331",
    "sg:postcode":"5721",
    "sg:province":"Salzburg",
    "wof:name":"Piesendorfer Fremdenverkehrsf\u00f6rderungsgesmbH",
    "wof:placetype":"venue"
},
  "geometry": {"coordinates":[12.6913766861,47.2882194519],"type":"Point"}
}