{
  "type": "Feature",
  "properties": {
    "iso:country":"AT",
    "sg:address":"Schlosserweg 76",
    "sg:city":"Hermagor",
    "sg:orig_category":"Pensionen / Privatzimmer",
    "sg:phone":"+43 4285 81160",
    "sg:postcode":"9620",
    "sg:province":"K\u00e4rnten",
    "wof:name":"Haus Alpina",
    "wof:placetype":"venue"
},
  "geometry": {"coordinates":[-81.4354095459,26.5363197327],"type":"Point"}
}