{
  "type": "Feature",
  "properties": {
    "iso:country":"AT",
    "sg:address":"Bahnhofstr 17",
    "sg:city":"Bischofshofen",
    "sg:orig_category":"Biologische Produkte",
    "sg:phone":"+43 4364 625051",
    "sg:postcode":"5500",
    "sg:province":"Salzburg",
    "wof:name":"Schmied Gabriele s' Wurzelwerk Naturkostladen",
    "wof:placetype":"venue"
},
  "geometry": {"coordinates":[13.218419075,47.4170684814],"type":"Point"}
}