{
  "type": "Feature",
  "properties": {
    "iso:country":"AT",
    "sg:address":"R\u00f6thelstein 46",
    "sg:city":"Mixnitz",
    "sg:classifiers":[
        {
            "category":"Structure",
            "subcategory":"Building",
            "type":"Public Place"
        }
    ],
    "sg:phone":"+43 3867 8181",
    "sg:postcode":"8131",
    "sg:province":"Steiermark",
    "sg:tags":[
        "apartment"
    ],
    "sg:website":"hoppaus-hasslinger.at",
    "wof:name":"Baumeister Ing. Hoppaus & Dipl.-Ing. Hasslinger Bauges.m.b.H.",
    "wof:placetype":"venue"
},
  "geometry": {"coordinates":[15.3676347733,47.3086738586],"type":"Point"}
}