{
  "type": "Feature",
  "properties": {
    "iso:country":"AT",
    "sg:address":"Reisenbauerring 2a",
    "sg:city":"Wiener Neudorf",
    "sg:orig_category":"Banken U Sparkassen",
    "sg:phone":"+43 4350 10020243",
    "sg:postcode":"2351",
    "sg:province":"Nieder\u00f6sterreich",
    "wof:name":"Bankomat d Erste Bank d oesterreichischen Sparkassen AG",
    "wof:placetype":"venue"
},
  "geometry": {"coordinates":[16.3114547729,48.0882606506],"type":"Point"}
}