{
  "type": "Feature",
  "properties": {
    "addr:full":"Siebenhirtenstr 13a Wien Wien 1230",
    "addr:housenumber":"13a",
    "addr:postcode":"1230",
    "addr:street":"Siebenhirtenstr",
    "iso:country":"AT",
    "sg:address":"Siebenhirtenstr 13a",
    "sg:city":"Wien",
    "sg:orig_category":"Autohandel",
    "sg:phone":"+43 1 8652919",
    "sg:postcode":"1230",
    "sg:province":"Wien",
    "wof:name":"Auto Bit Grzegorz Zawadzki KEG",
    "wof:placetype":"venue"
},
  "geometry": {"coordinates":[16.2906856537,48.1341018677],"type":"Point"}
}