{
  "type": "Feature",
  "properties": {
    "addr:full":"Sparkassenpl 4a Leibnitz Steiermark 8430",
    "addr:housenumber":"4a",
    "addr:postcode":"8430",
    "addr:street":"Sparkassenpl;Steiermark",
    "iso:country":"AT",
    "sg:address":"Sparkassenpl 4a",
    "sg:city":"Leibnitz",
    "sg:orig_category":"Tourismusinformation U -Organisationen",
    "sg:phone":"+43 3452 76711",
    "sg:postcode":"8430",
    "sg:province":"Steiermark",
    "wof:name":"Tourismusregionalverband S\u00fcdsteirisches Weinland",
    "wof:placetype":"venue"
},
  "geometry": {"coordinates":[15.537648201,46.7818946838],"type":"Point"}
}