{
  "type": "Feature",
  "properties": {
    "addr:full":"Nr 71 Ramsau am Dachstein Steiermark 8972",
    "addr:postcode":"8972",
    "addr:street":"Nr",
    "iso:country":"AT",
    "sg:address":"Nr 71",
    "sg:city":"Ramsau am Dachstein",
    "sg:classifiers":[
        {
            "category":"Travel",
            "subcategory":"Hotels & Motels",
            "type":"Entertainment"
        }
    ],
    "sg:phone":"+43 3687 81758",
    "sg:postcode":"8972",
    "sg:province":"Steiermark",
    "sg:website":"knollhof.at",
    "wof:name":"Hotel Knollhof",
    "wof:placetype":"venue"
},
  "geometry": {"coordinates":[13.6525297165,47.4214515686],"type":"Point"}
}