{
  "type": "Feature",
  "properties": {
    "addr:full":"Bundesstr 17 Schwarzach im Pongau Salzburg 5620",
    "addr:housenumber":"17",
    "addr:postcode":"5620",
    "addr:street":"Bundesstr;Salzburg",
    "iso:country":"AT",
    "sg:address":"Bundesstr 17",
    "sg:city":"Schwarzach im Pongau",
    "sg:orig_category":"Lebensmittel / Einzelhandel",
    "sg:phone":"+43 4364 154355",
    "sg:postcode":"5620",
    "sg:province":"Salzburg",
    "wof:name":"ADEG Aktiv Markt",
    "wof:placetype":"venue"
},
  "geometry": {"coordinates":[13.1511507034,47.321231842],"type":"Point"}
}