{
  "type": "Feature",
  "properties": {
    "iso:country":"AT",
    "sg:address":"Gumpendorfer Str 5A",
    "sg:city":"Wien",
    "sg:orig_category":"Teppiche / Einzelhandel",
    "sg:phone":"+43 1 5868095",
    "sg:postcode":"1060",
    "sg:province":"Wien",
    "wof:name":"Futon Werkstatt Reinhard Greil",
    "wof:placetype":"venue"
},
  "geometry": {"coordinates":[16.3619022369,48.2005882263],"type":"Point"}
}