{
  "type": "Feature",
  "properties": {
    "addr:full":"Lochbachstr 9 Lauterach Vorarlberg 6923",
    "addr:housenumber":"9",
    "addr:postcode":"6923",
    "addr:street":"Lochbachstr",
    "iso:country":"AT",
    "sg:address":"Lochbachstr 9",
    "sg:city":"Lauterach",
    "sg:orig_category":"Tischlereien",
    "sg:phone":"+43 4355 7472810",
    "sg:postcode":"6923",
    "sg:province":"Vorarlberg",
    "wof:name":"Stadler Michael",
    "wof:placetype":"venue"
},
  "geometry": {"coordinates":[9.7166528702,47.4817199707],"type":"Point"}
}