{
  "type": "Feature",
  "properties": {
    "addr:full":"Richard Strauss-Strasse 6 1232",
    "addr:housenumber":"6",
    "addr:postcode":"1232",
    "addr:street":"Richard Strauss-Strasse",
    "iso:country":"AT",
    "sg:address":"Richard Strauss-Strasse 6",
    "sg:orig_category":"Fittings, Valves",
    "sg:phone":"+43 1 61615410",
    "sg:postcode":"1232",
    "sg:website":"gur-valves.com",
    "wof:name":"Gur Armaturenvertriebs GmbH",
    "wof:placetype":"venue"
},
  "geometry": {"coordinates":[16.342092514,48.1469841003],"type":"Point"}
}