{
  "type": "Feature",
  "properties": {
    "iso:country":"AT",
    "sg:address":"Sechshauser Str 17/2/8",
    "sg:city":"Wien",
    "sg:orig_category":"Feng-Shui",
    "sg:phone":"+43 699 18929293",
    "sg:postcode":"1150",
    "sg:province":"Wien",
    "wof:name":"Schraml Claudia Ing - Feng Shui - Qigong - Reiki",
    "wof:placetype":"venue"
},
  "geometry": {"coordinates":[16.3320903778,48.2006416321],"type":"Point"}
}