{
  "type": "Feature",
  "properties": {
    "iso:country":"AT",
    "sg:address":"Dorf 36",
    "sg:city":"Kitzb\u00fchel",
    "sg:orig_category":"Volksschulen",
    "sg:phone":"+43 5356 75433",
    "sg:postcode":"6370",
    "sg:province":"Tirol",
    "wof:name":"Volksschule",
    "wof:placetype":"venue"
},
  "geometry": {"coordinates":[12.3446426392,47.4752044678],"type":"Point"}
}