{
  "type": "Feature",
  "properties": {
    "addr:full":"Rainerstr 14 Linz Ober\u00f6sterreich 4020",
    "addr:housenumber":"14",
    "addr:postcode":"4020",
    "addr:street":"Rainerstr",
    "iso:country":"AT",
    "sg:address":"Rainerstr 14",
    "sg:city":"Linz",
    "sg:orig_category":"Werbegrafik- U Grafik-Design",
    "sg:phone":"+43 732 6606660",
    "sg:postcode":"4020",
    "sg:province":"Ober\u00f6sterreich",
    "wof:name":"Atelier Theo Freund konzeptionelle Grafik und Werbegestaltung",
    "wof:placetype":"venue"
},
  "geometry": {"coordinates":[14.2900476456,48.2968177795],"type":"Point"}
}