{
  "type": "Feature",
  "properties": {
    "addr:full":"Strubergasse 51b/13 Salzburg Salzburg 5020",
    "addr:housenumber":"51b / 13",
    "addr:postcode":"5020",
    "addr:street":"Strubergasse;Salzburg",
    "iso:country":"AT",
    "sg:address":"Strubergasse 51b/13",
    "sg:city":"Salzburg",
    "sg:classifiers":[
        {
            "category":"Professional",
            "subcategory":"Research",
            "type":"Services"
        }
    ],
    "sg:phone":"+43 662 433657",
    "sg:postcode":"5020",
    "sg:province":"Salzburg",
    "sg:tags":[
        "opinion",
        "market"
    ],
    "wof:name":"Worte & Daten",
    "wof:placetype":"venue"
},
  "geometry": {"coordinates":[13.0272350311,47.8086662292],"type":"Point"}
}