{
  "type": "Feature",
  "properties": {
    "addr:full":"Nordbahnstr 7 Laa an der Thaya Nieder\u00f6sterreich 2136",
    "addr:housenumber":"7",
    "addr:postcode":"2136",
    "addr:street":"Nordbahnstr",
    "iso:country":"AT",
    "sg:address":"Nordbahnstr 7",
    "sg:city":"Laa an der Thaya",
    "sg:orig_category":"Papier- U Schreibwaren / Einzelhandel",
    "sg:phone":"+43 4325 228109",
    "sg:postcode":"2136",
    "sg:province":"Nieder\u00f6sterreich",
    "wof:name":"Leiss Marlene",
    "wof:placetype":"venue"
},
  "geometry": {"coordinates":[16.3844299316,48.7194366455],"type":"Point"}
}