{
  "type": "Feature",
  "properties": {
    "iso:country":"AT",
    "sg:address":"Greiner Str 2-4",
    "sg:city":"Kremsm\u00fcnster",
    "sg:orig_category":"Lebensmittel / Einzelhandel",
    "sg:phone":"+43 7583 6150",
    "sg:postcode":"4550",
    "sg:province":"Ober\u00f6sterreich",
    "wof:name":"Billa AG",
    "wof:placetype":"venue"
},
  "geometry": {"coordinates":[14.1326446533,48.0500106812],"type":"Point"}
}