{
  "type": "Feature",
  "properties": {
    "iso:country":"AT",
    "sg:address":"Ebentaler Str. 133",
    "sg:city":"Klagenfurt",
    "sg:orig_category":"Miscellaneous Products",
    "sg:phone":"+43 4346 338480",
    "sg:postcode":"9020",
    "sg:province":"K\u00e4rnten",
    "wof:name":"ZIMMER MASCHINENBAU GES.MBH",
    "wof:placetype":"venue"
},
  "geometry": {"coordinates":[14.3364639282,46.6160964966],"type":"Point"}
}