{
  "type": "Feature",
  "properties": {
    "addr:full":"Raxalpe Prein an der Rax Nieder\u00f6sterreich 2654",
    "addr:postcode":"2654",
    "addr:street":"Niederoesterreich",
    "iso:country":"AT",
    "sg:address":"Raxalpe",
    "sg:city":"Prein an der Rax",
    "sg:orig_category":"Rettungsdienste",
    "sg:phone":"+43 2665 381",
    "sg:postcode":"2654",
    "sg:province":"Nieder\u00f6sterreich",
    "wof:name":"Bergrettungsdienst",
    "wof:placetype":"venue"
},
  "geometry": {"coordinates":[15.7649822235,47.6742324829],"type":"Point"}
}