{
  "type": "Feature",
  "properties": {
    "iso:country":"AT",
    "sg:address":"Kreutzerhofstr 11",
    "sg:city":"Gloggnitz",
    "sg:orig_category":"Hausbetreuung",
    "sg:phone":"+43 2662 46646",
    "sg:postcode":"2640",
    "sg:province":"Nieder\u00f6sterreich",
    "wof:name":"Haus + Garten Service Kurt Stingl",
    "wof:placetype":"venue"
},
  "geometry": {"coordinates":[15.9717645645,47.6843757629],"type":"Point"}
}