{
  "type": "Feature",
  "properties": {
    "iso:country":"AT",
    "sg:address":"Kirchplatz 7 ",
    "sg:city":"Kolsass",
    "sg:classifiers":[
        {
            "category":"Shopping",
            "subcategory":"Clothing, Apparel, & Fashions",
            "type":"Retail Goods"
        }
    ],
    "sg:phone":"+43 4352 44680",
    "sg:postcode":"6114",
    "sg:province":"Tirol",
    "sg:tags":[
        "clothes"
    ],
    "wof:name":"WESENJAK MODE GMBH",
    "wof:placetype":"venue"
},
  "geometry": {"coordinates":[11.630944252,47.300403595],"type":"Point"}
}