{
  "type": "Feature",
  "properties": {
    "addr:full":"Florian-Geyer-G 2-4/37/8 Wien Wien 1100",
    "addr:housenumber":"2-4 / 37 / 8",
    "addr:postcode":"1100",
    "addr:street":"Florian-Geyer-G",
    "iso:country":"AT",
    "sg:address":"Florian-Geyer-G 2-4/37/8",
    "sg:city":"Wien",
    "sg:classifiers":[
        {
            "category":"Internet Cafe",
            "subcategory":"None",
            "type":"Food & Drink"
        }
    ],
    "sg:phone":"+43 1 9135007",
    "sg:postcode":"1100",
    "sg:province":"Wien",
    "sg:tags":[
        "internet-provider"
    ],
    "wof:name":"Mair und Schl\u00f6mmer Data Services OEG",
    "wof:placetype":"venue"
},
  "geometry": {"coordinates":[16.3744049072,48.1782684326],"type":"Point"}
}