{
  "type": "Feature",
  "properties": {
    "addr:full":"Gr\u00fcnbach Ober\u00f6sterreich 4264",
    "addr:postcode":"4264",
    "addr:street":"Oberoesterreich",
    "iso:country":"AT",
    "sg:city":"Gr\u00fcnbach",
    "sg:orig_category":"Feuerwehren",
    "sg:phone":"+43 7942 72844",
    "sg:postcode":"4264",
    "sg:province":"Ober\u00f6sterreich",
    "wof:name":"Freiwillige Feuerwehr Lichtenau",
    "wof:placetype":"venue"
},
  "geometry": {"coordinates":[14.5116863251,48.5539093018],"type":"Point"}
}