{
  "type": "Feature",
  "properties": {
    "addr:full":"Gesellenhausstr 5 Linz Ober\u00f6sterreich 4020",
    "addr:housenumber":"5",
    "addr:postcode":"4020",
    "addr:street":"Gesellenhausstr",
    "iso:country":"AT",
    "sg:address":"Gesellenhausstr 5",
    "sg:city":"Linz",
    "sg:classifiers":[
        {
            "category":"Travel",
            "subcategory":"Hotels & Motels",
            "type":"Entertainment"
        }
    ],
    "sg:phone":"+43 732 661690",
    "sg:postcode":"4020",
    "sg:province":"Ober\u00f6sterreich",
    "sg:website":"oberoesterreich.at/kolping-linz",
    "wof:name":"Hotel Kolping GesmbH",
    "wof:placetype":"venue"
},
  "geometry": {"coordinates":[14.2893533707,48.298248291],"type":"Point"}
}