{
  "type": "Feature",
  "properties": {
    "iso:country":"AT",
    "sg:address":"Stelzhamerg 4/9",
    "sg:city":"Wien",
    "sg:orig_category":"Zeitungen U Zeitschriften / Vertrieb",
    "sg:phone":"+43 4315 3503000",
    "sg:postcode":"1030",
    "sg:province":"Wien",
    "wof:name":"Besser Wohnen - Die \u00f6sterr Wohnzeitschrift - Redaktion",
    "wof:placetype":"venue"
},
  "geometry": {"coordinates":[16.3843021393,48.2075080872],"type":"Point"}
}