{
  "type": "Feature",
  "properties": {
    "addr:full":"Gassing 1 St. Lorenzen im M\u00fcrztal Steiermark 8642",
    "addr:housenumber":"1",
    "addr:postcode":"8642",
    "addr:street":"Gassing",
    "iso:country":"AT",
    "sg:address":"Gassing 1",
    "sg:city":"St. Lorenzen im M\u00fcrztal",
    "sg:classifiers":[
        {
            "category":"Building & Trades",
            "subcategory":"Plumbing",
            "type":"Services"
        }
    ],
    "sg:phone":"+43 3862 31317",
    "sg:postcode":"8642",
    "sg:province":"Steiermark",
    "sg:tags":[
        "supraregional",
        "gas"
    ],
    "wof:name":"GWH Installationsges.m.b.H.",
    "wof:placetype":"venue"
},
  "geometry": {"coordinates":[15.3405542374,47.482963562],"type":"Point"}
}