{
  "type": "Feature",
  "properties": {
    "addr:full":"B\u00f6cksteiner Bundesstr 5 Bad Gastein Salzburg 5640",
    "addr:housenumber":"5",
    "addr:postcode":"5640",
    "addr:street":"Bundesstr;Salzburg",
    "iso:country":"AT",
    "sg:address":"B\u00f6cksteiner Bundesstr 5",
    "sg:city":"Bad Gastein",
    "sg:orig_category":"Banken U Sparkassen",
    "sg:phone":"+43 4364 3421220",
    "sg:postcode":"5640",
    "sg:province":"Salzburg",
    "wof:name":"Bankomat d Raiffeisenbank Gastein regGenmbH",
    "wof:placetype":"venue"
},
  "geometry": {"coordinates":[13.1349172592,47.1082839966],"type":"Point"}
}