{
  "type": "Feature",
  "properties": {
    "addr:full":"Johannesgasse 3 Wien Wien 1010",
    "addr:housenumber":"3",
    "addr:postcode":"1010",
    "addr:street":"Johannesgasse",
    "iso:country":"AT",
    "sg:address":"Johannesgasse 3",
    "sg:city":"Wien",
    "sg:orig_category":"Accessories For Track Construction Machinery",
    "sg:phone":"+43 1 515720",
    "sg:postcode":"1010",
    "sg:province":"Wien",
    "wof:name":"Franz Plasser Bahnbaumaschinen - Industrieges.m.b.H.",
    "wof:placetype":"venue"
},
  "geometry": {"coordinates":[16.3713741302,48.2053146362],"type":"Point"}
}