{
  "type": "Feature",
  "properties": {
    "addr:full":"Kaplanstr 10 Tulln an der Donau Nieder\u00f6sterreich 3430",
    "addr:housenumber":"10",
    "addr:postcode":"3430",
    "addr:street":"Kaplanstr",
    "iso:country":"AT",
    "sg:address":"Kaplanstr 10",
    "sg:city":"Tulln an der Donau",
    "sg:orig_category":"Autobusunternehmen",
    "sg:phone":"+43 4322 7261770",
    "sg:postcode":"3430",
    "sg:province":"Nieder\u00f6sterreich",
    "wof:name":"Flor Rudolf - Busreisen GesmbH",
    "wof:placetype":"venue"
},
  "geometry": {"coordinates":[16.0770606995,48.3269805908],"type":"Point"}
}