{
  "type": "Feature",
  "properties": {
    "addr:full":"Italiener Str 24a Villach K\u00e4rnten 9500",
    "addr:housenumber":"24a",
    "addr:postcode":"9500",
    "addr:street":"Str;Kaernten",
    "iso:country":"AT",
    "sg:address":"Italiener Str 24a",
    "sg:city":"Villach",
    "sg:orig_category":"Fluggesellschaften",
    "sg:phone":"+43 664 1000669",
    "sg:postcode":"9500",
    "sg:province":"K\u00e4rnten",
    "wof:name":"EUROP STAR Aircraft GmbH",
    "wof:placetype":"venue"
},
  "geometry": {"coordinates":[13.8429031372,46.6096115112],"type":"Point"}
}