{
  "type": "Feature",
  "properties": {
    "addr:full":"Annaberg Annaberg Salzburg 5524",
    "addr:postcode":"5524",
    "iso:country":"AT",
    "sg:address":"Annaberg",
    "sg:city":"Annaberg",
    "sg:classifiers":[
        {
            "category":"Manufacturing",
            "subcategory":"Wood Products",
            "type":"Manufacturing & Wholesale Goods"
        }
    ],
    "sg:phone":"+43 6463 8169",
    "sg:postcode":"5524",
    "sg:province":"Salzburg",
    "sg:tags":[
        "lumber"
    ],
    "wof:name":"S\u00e4gewerk Moser Betriebs GmbH",
    "wof:placetype":"venue"
},
  "geometry": {"coordinates":[13.4311275482,47.5239715576],"type":"Point"}
}