{
  "type": "Feature",
  "properties": {
    "iso:country":"AT",
    "sg:address":"Nr 3",
    "sg:city":"Rottenegg",
    "sg:orig_category":"Architekten",
    "sg:phone":"+43 7234 87306",
    "sg:postcode":"4112",
    "sg:province":"Ober\u00f6sterreich",
    "wof:name":"Angermeier Magnus Dipl-Ing",
    "wof:placetype":"venue"
},
  "geometry": {"coordinates":[14.1296854019,48.3839187622],"type":"Point"}
}