{
  "type": "Feature",
  "properties": {
    "addr:full":"Markt 40 Neufelden Ober\u00f6sterreich 4120",
    "addr:housenumber":"40",
    "addr:postcode":"4120",
    "addr:street":"Markt",
    "iso:country":"AT",
    "sg:address":"Markt 40",
    "sg:city":"Neufelden",
    "sg:orig_category":"Polizei U Gendarmerie",
    "sg:phone":"+43 4359 1334256",
    "sg:postcode":"4120",
    "sg:province":"Ober\u00f6sterreich",
    "wof:name":"Gendarmerie",
    "wof:placetype":"venue"
},
  "geometry": {"coordinates":[13.9992780685,48.4841842651],"type":"Point"}
}