{
  "type": "Feature",
  "properties": {
    "addr:full":"Kasernenstr. 9 Eisenstadt Burgenland 7000",
    "addr:housenumber":"9",
    "addr:postcode":"7000",
    "addr:street":"Kasernenstr.",
    "iso:country":"AT",
    "sg:address":"Kasernenstr. 9",
    "sg:city":"Eisenstadt",
    "sg:classifiers":[
        {
            "category":"Utilities",
            "subcategory":"Electric",
            "type":"Services"
        }
    ],
    "sg:phone":"+43 4326 8290000",
    "sg:postcode":"7000",
    "sg:province":"Burgenland",
    "sg:tags":[
        "electricity"
    ],
    "wof:name":"BEWAG BURGENL\u00c4NDISCHE ELEKTRIZIT\u00c4TSWIRTSCHAFTS-AG",
    "wof:placetype":"venue"
},
  "geometry": {"coordinates":[16.5376815796,47.8542518616],"type":"Point"}
}