{
  "type": "Feature",
  "properties": {
    "iso:country":"AT",
    "sg:address":"Werdenbergerstr 3",
    "sg:city":"Lustenau",
    "sg:orig_category":"Schlossereien",
    "sg:phone":"+43 4355 7784122",
    "sg:postcode":"6890",
    "sg:province":"Vorarlberg",
    "wof:name":"Vetter Walter",
    "wof:placetype":"venue"
},
  "geometry": {"coordinates":[9.6595907211,47.4417152405],"type":"Point"}
}