{
  "type": "Feature",
  "properties": {
    "addr:full":"Operng 20b/31 Wien Wien 1040",
    "addr:housenumber":"20b / 31",
    "addr:postcode":"1040",
    "addr:street":"Operng",
    "iso:country":"AT",
    "sg:address":"Operng 20b/31",
    "sg:city":"Wien",
    "sg:orig_category":"Elektronische Bauelemente U Bauteile",
    "sg:phone":"+43 4315 8770700",
    "sg:postcode":"1040",
    "sg:province":"Wien",
    "sg:website":"infineon.com/austria",
    "wof:name":"Infineon Technologies Austria AG",
    "wof:placetype":"venue"
},
  "geometry": {"coordinates":[16.3665828705,48.1995887756],"type":"Point"}
}