{
  "type": "Feature",
  "properties": {
    "addr:full":"Dorfnerstr 33/1 Melk Nieder\u00f6sterreich 3390",
    "addr:housenumber":"33 / 1",
    "addr:postcode":"3390",
    "addr:street":"Dorfnerstr",
    "iso:country":"AT",
    "sg:address":"Dorfnerstr 33/1",
    "sg:city":"Melk",
    "sg:orig_category":"Dachdeckereien",
    "sg:phone":"+43 4327 5254466",
    "sg:postcode":"3390",
    "sg:province":"Nieder\u00f6sterreich",
    "wof:name":"Bauer Gregor",
    "wof:placetype":"venue"
},
  "geometry": {"coordinates":[15.3267946243,48.2211418152],"type":"Point"}
}