{
  "type": "Feature",
  "properties": {
    "iso:country":"AT",
    "sg:address":"Nr 48",
    "sg:city":"Gundersheim",
    "sg:orig_category":"Schmieden U Schmiedeeisenelemente",
    "sg:phone":"+43 4718 349",
    "sg:postcode":"9634",
    "sg:province":"K\u00e4rnten",
    "wof:name":"Thurner Georg",
    "wof:placetype":"venue"
},
  "geometry": {"coordinates":[13.117225647,46.6481666565],"type":"Point"}
}