{
  "type": "Feature",
  "properties": {
    "addr:full":"Geblerg 65 Wien Wien 1170",
    "addr:housenumber":"65",
    "addr:postcode":"1170",
    "addr:street":"Geblerg",
    "iso:country":"AT",
    "sg:address":"Geblerg 65",
    "sg:city":"Wien",
    "sg:orig_category":"Tischlereien",
    "sg:phone":"+43 1 4084114",
    "sg:postcode":"1170",
    "sg:province":"Wien",
    "wof:name":"K\u00fchschelm Peter",
    "wof:placetype":"venue"
},
  "geometry": {"coordinates":[16.330871582,48.2163505554],"type":"Point"}
}