{
  "type": "Feature",
  "properties": {
    "iso:country":"AT",
    "sg:address":"Rheinstr 39",
    "sg:city":"M\u00e4der",
    "sg:orig_category":"Installationsunternehmen",
    "sg:phone":"+43 5523 51664",
    "sg:postcode":"6841",
    "sg:province":"Vorarlberg",
    "wof:name":"Wurzer Installationen GesmbH",
    "wof:placetype":"venue"
},
  "geometry": {"coordinates":[-73.08963012700001,41.3234443665],"type":"Point"}
}