{
  "type": "Feature",
  "properties": {
    "iso:country":"AT",
    "sg:address":"K\u00e4rntner Str 75",
    "sg:city":"Lienz",
    "sg:orig_category":"Blumeneinzelhandel",
    "sg:phone":"+43 4852 64388",
    "sg:postcode":"9900",
    "sg:province":"Tirol",
    "wof:name":"Unterscheider G\u00e4rtnerei Inh Waltraud Wolf",
    "wof:placetype":"venue"
},
  "geometry": {"coordinates":[12.7684783936,46.8281173706],"type":"Point"}
}