{
  "type": "Feature",
  "properties": {
    "addr:full":"Walser Str 27 Riezlern Vorarlberg 6991",
    "addr:postcode":"6991",
    "addr:street":"Str 27",
    "iso:country":"AT",
    "sg:address":"Walser Str 27",
    "sg:city":"Riezlern",
    "sg:classifiers":[
        {
            "category":"Travel",
            "subcategory":"Hotels & Motels",
            "type":"Entertainment"
        }
    ],
    "sg:phone":"+43 4355 175603",
    "sg:postcode":"6991",
    "sg:province":"Vorarlberg",
    "wof:name":"Hotel Jagdhof",
    "wof:placetype":"venue"
},
  "geometry": {"coordinates":[10.1906061172,47.3591346741],"type":"Point"}
}