{
  "type": "Feature",
  "properties": {
    "addr:full":"Kinkstr 7 Kufstein Tirol 6330",
    "addr:housenumber":"7",
    "addr:postcode":"6330",
    "addr:street":"Kinkstr;Tirol",
    "iso:country":"AT",
    "sg:address":"Kinkstr 7",
    "sg:city":"Kufstein",
    "sg:orig_category":"Textilwaren / Einzelhandel",
    "sg:phone":"+43 4353 7261155",
    "sg:postcode":"6330",
    "sg:province":"Tirol",
    "wof:name":"NKD",
    "wof:placetype":"venue"
},
  "geometry": {"coordinates":[12.1705617905,47.581073761],"type":"Point"}
}