{
  "type": "Feature",
  "properties": {
    "addr:full":"Mauthausner Str 32 Enns Ober\u00f6sterreich 4470",
    "addr:postcode":"4470",
    "addr:street":"Str 32",
    "iso:country":"AT",
    "sg:address":"Mauthausner Str 32",
    "sg:city":"Enns",
    "sg:orig_category":"Graveure",
    "sg:phone":"+43 664 5917910",
    "sg:postcode":"4470",
    "sg:province":"Ober\u00f6sterreich",
    "wof:name":"Puchner Wolfgang",
    "wof:placetype":"venue"
},
  "geometry": {"coordinates":[14.4821529388,48.2174377441],"type":"Point"}
}