{
  "type": "Feature",
  "properties": {
    "addr:full":"Innstr 2 Jenbach Tirol 6200",
    "addr:housenumber":"2",
    "addr:postcode":"6200",
    "addr:street":"Innstr;Tirol",
    "iso:country":"AT",
    "sg:address":"Innstr 2",
    "sg:city":"Jenbach",
    "sg:orig_category":"Schlossereien",
    "sg:phone":"+43 676 3061836",
    "sg:postcode":"6200",
    "sg:province":"Tirol",
    "wof:name":"Jaud Alois",
    "wof:placetype":"venue"
},
  "geometry": {"coordinates":[11.7754659653,47.3846664429],"type":"Point"}
}