{
  "type": "Feature",
  "properties": {
    "addr:full":"Dorfstr 26 Terfens Tirol 6123",
    "addr:housenumber":"26",
    "addr:postcode":"6123",
    "addr:street":"Dorfstr;Tirol",
    "iso:country":"AT",
    "sg:address":"Dorfstr 26",
    "sg:city":"Terfens",
    "sg:orig_category":"Tischlereien",
    "sg:phone":"+43 5224 68351",
    "sg:postcode":"6123",
    "sg:province":"Tirol",
    "wof:name":"Schallhart Max",
    "wof:placetype":"venue"
},
  "geometry": {"coordinates":[11.6455173492,47.3237075806],"type":"Point"}
}