{
  "type": "Feature",
  "properties": {
    "addr:full":"Gustav Kramer-Str 8 Kapfenberg Steiermark 8605",
    "addr:housenumber":"8",
    "addr:postcode":"8605",
    "iso:country":"AT",
    "sg:address":"Gustav Kramer-Str 8",
    "sg:city":"Kapfenberg",
    "sg:orig_category":"Feuerwehren",
    "sg:phone":"+43 3862 23481",
    "sg:postcode":"8605",
    "sg:province":"Steiermark",
    "wof:name":"Freiwillige Feuerwehr Kapfenberg-Diemlach",
    "wof:placetype":"venue"
},
  "geometry": {"coordinates":[15.2760286331,47.4332542419],"type":"Point"}
}