{
  "type": "Feature",
  "properties": {
    "addr:full":"Hauptstr 13 Kobersdorf Burgenland 7332",
    "addr:housenumber":"13",
    "addr:postcode":"7332",
    "addr:street":"Hauptstr",
    "iso:country":"AT",
    "sg:address":"Hauptstr 13",
    "sg:city":"Kobersdorf",
    "sg:orig_category":"\u00c3\u201erzte / F Allgemeinmedizin",
    "sg:phone":"+43 2618 86670",
    "sg:postcode":"7332",
    "sg:province":"Burgenland",
    "wof:name":"Horvatits Thomas Dr",
    "wof:placetype":"venue"
},
  "geometry": {"coordinates":[16.3920860291,47.5955505371],"type":"Point"}
}