{
  "type": "Feature",
  "properties": {
    "addr:full":"Nr 64 St. Martin am Tennengebirge Salzburg 5522",
    "addr:postcode":"5522",
    "addr:street":"Nr 64",
    "iso:country":"AT",
    "sg:address":"Nr 64",
    "sg:city":"St. Martin am Tennengebirge",
    "sg:orig_category":"Banken U Sparkassen",
    "sg:phone":"+43 4364 6373130",
    "sg:postcode":"5522",
    "sg:province":"Salzburg",
    "wof:name":"Bankomat d Raiffeisenkasse H\u00fcttau-St Martin-Niedernfritz regGenmbH",
    "wof:placetype":"venue"
},
  "geometry": {"coordinates":[13.3810081482,47.4648284912],"type":"Point"}
}