{
  "type": "Feature",
  "properties": {
    "iso:country":"AT",
    "sg:address":"Kollwitzgasse 13",
    "sg:city":"Liebenau",
    "sg:orig_category":"Internet, Internetmarketing",
    "sg:postcode":"8041",
    "sg:province":"Steiermark",
    "sg:website":"http://www.mediawatch.at",
    "wof:name":"media.watch Internet-Agentur f\u00fcr Online-Marketing",
    "wof:placetype":"venue"
},
  "geometry": {"coordinates":[15.4515361786,47.044883728],"type":"Point"}
}