{
  "type": "Feature",
  "properties": {
    "addr:full":"Wahlbergg 3 Wien Wien 1140",
    "addr:housenumber":"3",
    "addr:postcode":"1140",
    "addr:street":"Wahlbergg",
    "iso:country":"AT",
    "sg:address":"Wahlbergg 3",
    "sg:city":"Wien",
    "sg:orig_category":"Autohandel",
    "sg:phone":"+43 1 9111436",
    "sg:postcode":"1140",
    "sg:province":"Wien",
    "wof:name":"Trendl Adolf",
    "wof:placetype":"venue"
},
  "geometry": {"coordinates":[16.2628669739,48.2057647705],"type":"Point"}
}