{
  "type": "Feature",
  "properties": {
    "addr:full":"Sternberger Weg 26 Wernberg K\u00e4rnten 9241",
    "addr:housenumber":"26",
    "addr:postcode":"9241",
    "addr:street":"Sternberger Weg;Kaernten",
    "iso:country":"AT",
    "sg:address":"Sternberger Weg 26",
    "sg:city":"Wernberg",
    "sg:orig_category":"Pensionen / Privatzimmer",
    "sg:phone":"+43 4342 522173",
    "sg:postcode":"9241",
    "sg:province":"K\u00e4rnten",
    "wof:name":"Fremdenpension Sternbergheim",
    "wof:placetype":"venue"
},
  "geometry": {"coordinates":[13.984459877,46.6274223328],"type":"Point"}
}