{
  "type": "Feature",
  "properties": {
    "addr:full":"Radetzkystr 6 Wien Wien 1030",
    "addr:housenumber":"6",
    "addr:postcode":"1030",
    "addr:street":"Radetzkystr",
    "iso:country":"AT",
    "sg:address":"Radetzkystr 6",
    "sg:city":"Wien",
    "sg:orig_category":"Schlossereien",
    "sg:phone":"+43 1 7131165",
    "sg:postcode":"1030",
    "sg:province":"Wien",
    "wof:name":"PICARD Sicherheitsschl\u00f6sser",
    "wof:placetype":"venue"
},
  "geometry": {"coordinates":[16.3885822296,48.2109298706],"type":"Point"}
}