{
  "type": "Feature",
  "properties": {
    "addr:full":"Grabersdorf 59 Gnas Steiermark 8342",
    "addr:housenumber":"59",
    "addr:postcode":"8342",
    "addr:street":"Grabersdorf",
    "iso:country":"AT",
    "sg:address":"Grabersdorf 59",
    "sg:city":"Gnas",
    "sg:classifiers":[
        {
            "category":"Home & Garden",
            "subcategory":"Building Materials",
            "type":"Retail Goods"
        }
    ],
    "sg:phone":"+43 3151 8717",
    "sg:postcode":"8342",
    "sg:province":"Steiermark",
    "sg:tags":[
        "wood",
        "banister"
    ],
    "sg:website":"mueller-stiegen.com",
    "wof:name":"Franz M\u00fcller & Co KG",
    "wof:placetype":"venue"
},
  "geometry": {"coordinates":[15.8265724182,46.8743095398],"type":"Point"}
}