{
  "type": "Feature",
  "properties": {
    "iso:country":"AT",
    "sg:address":"Bahnhofstr",
    "sg:city":"Fehring",
    "sg:orig_category":"Lebensmittel / Einzelhandel",
    "sg:phone":"+43 3155 3513",
    "sg:postcode":"8350",
    "sg:province":"Steiermark",
    "wof:name":"Billa AG",
    "wof:placetype":"venue"
},
  "geometry": {"coordinates":[16.0122318268,46.9393730164],"type":"Point"}
}