{
  "type": "Feature",
  "properties": {
    "addr:full":"Rotkreuzg 1 Klosterneuburg Nieder\u00f6sterreich 3400",
    "addr:housenumber":"1",
    "addr:postcode":"3400",
    "addr:street":"Rotkreuzg;Niederoesterreich",
    "iso:country":"AT",
    "sg:address":"Rotkreuzg 1",
    "sg:city":"Klosterneuburg",
    "sg:classifiers":[
        {
            "category":"Taxi",
            "type":"Transportation"
        }
    ],
    "sg:phone":"+43 4322 4383800",
    "sg:postcode":"3400",
    "sg:province":"Nieder\u00f6sterreich",
    "sg:tags":[
        "personentransporte",
        "u"
    ],
    "wof:name":"Br\u00e4uer Josef",
    "wof:placetype":"venue"
},
  "geometry": {"coordinates":[16.2406959534,48.3141479492],"type":"Point"}
}