{
  "type": "Feature",
  "properties": {
    "addr:full":"Kreuzbergpromenade 10 Salzburg Salzburg 5020",
    "addr:housenumber":"10",
    "addr:postcode":"5020",
    "addr:street":"Kreuzbergpromenade;Salzburg",
    "iso:country":"AT",
    "sg:address":"Kreuzbergpromenade 10",
    "sg:city":"Salzburg",
    "sg:classifiers":[
        {
            "category":"Communications",
            "subcategory":"Film & Video Production",
            "type":"Services"
        }
    ],
    "sg:phone":"+43 662 641050",
    "sg:postcode":"5020",
    "sg:province":"Salzburg",
    "sg:tags":[
        "information",
        "consulting",
        "technology"
    ],
    "sg:website":"itsolutions.at",
    "wof:name":"IT Solutions & webspider Kampmueller Christian",
    "wof:placetype":"venue"
},
  "geometry": {"coordinates":[13.0814971924,47.8011436462],"type":"Point"}
}