{
  "type": "Feature",
  "properties": {
    "addr:full":"Lunzerstr Linz Ober\u00f6sterreich 4030",
    "addr:postcode":"4030",
    "addr:street":"Oberoesterreich",
    "iso:country":"AT",
    "sg:address":"Lunzerstr",
    "sg:city":"Linz",
    "sg:orig_category":"Tankstellen",
    "sg:phone":"+43 732 306954",
    "sg:postcode":"4030",
    "sg:province":"Ober\u00f6sterreich",
    "wof:name":"OMV AG",
    "wof:placetype":"venue"
},
  "geometry": {"coordinates":[14.3245849609,48.2574539185],"type":"Point"}
}