{
  "type": "Feature",
  "properties": {
    "iso:country":"AT",
    "sg:address":"Nonntaler Hauptstr 72",
    "sg:city":"Salzburg",
    "sg:orig_category":"Ingenieurkonsulenten / Zivilingenieure",
    "sg:phone":"+43 662 829346",
    "sg:postcode":"5020",
    "sg:province":"Salzburg",
    "wof:name":"Prosch Helmut Dipl-Ing",
    "wof:placetype":"venue"
},
  "geometry": {"coordinates":[13.0514745712,47.7866859436],"type":"Point"}
}