{
  "type": "Feature",
  "properties": {
    "addr:full":"Welser Str 42 Leonding Ober\u00f6sterreich 4060",
    "addr:postcode":"4060",
    "addr:street":"Str 42",
    "iso:country":"AT",
    "sg:address":"Welser Str 42",
    "sg:city":"Leonding",
    "sg:orig_category":"Institute",
    "sg:phone":"+43 732 6725090",
    "sg:postcode":"4060",
    "sg:province":"Ober\u00f6sterreich",
    "wof:name":"Institut f Verfahrenstechnik",
    "wof:placetype":"venue"
},
  "geometry": {"coordinates":[14.2662401199,48.2691383362],"type":"Point"}
}