{
  "type": "Feature",
  "properties": {
    "addr:full":"Schulg 75 Breitenwaida Nieder\u00f6sterreich 2014",
    "addr:housenumber":"75",
    "addr:postcode":"2014",
    "addr:street":"Schulg",
    "iso:country":"AT",
    "sg:address":"Schulg 75",
    "sg:city":"Breitenwaida",
    "sg:orig_category":"Volksschulen",
    "sg:phone":"+43 2954 2034",
    "sg:postcode":"2014",
    "sg:province":"Nieder\u00f6sterreich",
    "wof:name":"Volksschule",
    "wof:placetype":"venue"
},
  "geometry": {"coordinates":[16.0679798126,48.5152282715],"type":"Point"}
}