{
  "type": "Feature",
  "properties": {
    "addr:full":"Asperner Heldenpl 3 Wien Wien 1220",
    "addr:housenumber":"3",
    "addr:postcode":"1220",
    "addr:street":"Heldenpl",
    "iso:country":"AT",
    "sg:address":"Asperner Heldenpl 3",
    "sg:city":"Wien",
    "sg:orig_category":"Volksschulen",
    "sg:phone":"+43 1 2821499",
    "sg:postcode":"1220",
    "sg:province":"Wien",
    "wof:name":"Schulen d Stadt Wien",
    "wof:placetype":"venue"
},
  "geometry": {"coordinates":[16.4837627411,48.2177200317],"type":"Point"}
}