{
  "type": "Feature",
  "properties": {
    "addr:full":"Turnerg 14 Wien Wien 1150",
    "addr:housenumber":"14",
    "addr:postcode":"1150",
    "addr:street":"Turnerg",
    "iso:country":"AT",
    "sg:address":"Turnerg 14",
    "sg:city":"Wien",
    "sg:orig_category":"Unternehmensberatung",
    "sg:phone":"+43 1 89342430",
    "sg:postcode":"1150",
    "sg:province":"Wien",
    "wof:name":"K-Data Datenverarbeitungs- und Betriebsberatung Dworak KEG",
    "wof:placetype":"venue"
},
  "geometry": {"coordinates":[16.3359146118,48.191242218],"type":"Point"}
}