{
  "type": "Feature",
  "properties": {
    "iso:country":"AT",
    "sg:address":"Friedhofstrasse 4",
    "sg:city":"Langenzersdorf",
    "sg:classifiers":[
        {
            "category":"Wholesale",
            "subcategory":"Construction Materials",
            "type":"Manufacturing & Wholesale Goods"
        }
    ],
    "sg:phone":"+43 2244 4337",
    "sg:postcode":"2103",
    "sg:province":"Nieder\u00f6sterreich",
    "sg:tags":[
        "bridge",
        "temporary",
        "materials",
        "crown"
    ],
    "wof:name":"Gerald R\u00f6kl",
    "wof:placetype":"venue"
},
  "geometry": {"coordinates":[16.3609886169,48.3058853149],"type":"Point"}
}