{
  "type": "Feature",
  "properties": {
    "addr:full":"Sch\u00f6nbrunner Str 264/18 Wien Wien 1120",
    "addr:housenumber":"264 / 18",
    "addr:postcode":"1120",
    "addr:street":"Str",
    "iso:country":"AT",
    "sg:address":"Sch\u00f6nbrunner Str 264/18",
    "sg:city":"Wien",
    "sg:classifiers":[
        {
            "category":"Professional",
            "subcategory":"Management & Consulting",
            "type":"Services"
        }
    ],
    "sg:phone":"+43 1 9453144",
    "sg:postcode":"1120",
    "sg:province":"Wien",
    "sg:tags":[
        "supervision"
    ],
    "wof:name":"Friedl Dagmar",
    "wof:placetype":"venue"
},
  "geometry": {"coordinates":[16.3290939331,48.1824874878],"type":"Point"}
}