{
  "type": "Feature",
  "properties": {
    "addr:full":"Gurten 50 Gurten Ober\u00f6sterreich 4942",
    "addr:housenumber":"50",
    "addr:postcode":"4942",
    "addr:street":"Gurten",
    "iso:country":"AT",
    "sg:address":"Gurten 50",
    "sg:city":"Gurten",
    "sg:classifiers":[
        {
            "category":"Retail",
            "subcategory":"Repair Shop",
            "type":"Services"
        }
    ],
    "sg:phone":"+43 7757 6228",
    "sg:postcode":"4942",
    "sg:province":"Ober\u00f6sterreich",
    "sg:tags":[
        "agricultural",
        "machinery"
    ],
    "sg:website":"gefra.at",
    "wof:name":"Gerhard Frauscher",
    "wof:placetype":"venue"
},
  "geometry": {"coordinates":[13.3449907303,48.2406616211],"type":"Point"}
}