{
  "type": "Feature",
  "properties": {
    "addr:full":"Hetzendorfer Str. 18-22  Wien Wien 1120",
    "addr:postcode":"18-22;1120",
    "addr:street":"Str.",
    "iso:country":"AT",
    "sg:address":"Hetzendorfer Str. 18-22 ",
    "sg:city":"Wien",
    "sg:classifiers":[
        {
            "category":"Manufacturing",
            "subcategory":"Paper Products",
            "type":"Manufacturing & Wholesale Goods"
        }
    ],
    "sg:phone":"+43 4318 0493030",
    "sg:postcode":"1120",
    "sg:province":"Wien",
    "sg:tags":[
        "cardboard"
    ],
    "wof:name":"E. DAHM & BR\u00dcDER",
    "wof:placetype":"venue"
},
  "geometry": {"coordinates":[16.3196811676,48.1630630493],"type":"Point"}
}