{
  "type": "Feature",
  "properties": {
    "addr:full":"B\u00f6senbacher Str 185 Frauental an der La\u00dfnitz Steiermark 8523",
    "addr:housenumber":"185",
    "addr:postcode":"8523",
    "addr:street":"Str",
    "iso:country":"AT",
    "sg:address":"B\u00f6senbacher Str 185",
    "sg:city":"Frauental an der La\u00dfnitz",
    "sg:orig_category":"Musikgruppen",
    "sg:phone":"+43 4367 65205290",
    "sg:postcode":"8523",
    "sg:province":"Steiermark",
    "wof:name":"Top West - Gregor M\u00f6rth",
    "wof:placetype":"venue"
},
  "geometry": {"coordinates":[15.2503499985,46.8269424438],"type":"Point"}
}