{
  "type": "Feature",
  "properties": {
    "addr:full":"Kreuzbichl 1 Volders Tirol 6111",
    "addr:housenumber":"1",
    "addr:postcode":"6111",
    "addr:street":"Kreuzbichl;Tirol",
    "iso:country":"AT",
    "sg:address":"Kreuzbichl 1",
    "sg:city":"Volders",
    "sg:orig_category":"Speditionen",
    "sg:phone":"+43 5224 51111",
    "sg:postcode":"6111",
    "sg:province":"Tirol",
    "wof:name":"Wechselberger Andreas",
    "wof:placetype":"venue"
},
  "geometry": {"coordinates":[11.5817279816,47.2899894714],"type":"Point"}
}