{
  "type": "Feature",
  "properties": {
    "iso:country":"AT",
    "sg:address":"Bahnhofsdlg 19",
    "sg:city":"Steyregg",
    "sg:orig_category":"Rauchfangkehrer",
    "sg:phone":"+43 732 641293",
    "sg:postcode":"4221",
    "sg:province":"Ober\u00f6sterreich",
    "wof:name":"Schonka J\u00fcrgen - Bezirksrauchfangkehrermeister",
    "wof:placetype":"venue"
},
  "geometry": {"coordinates":[14.3730096817,48.2857704163],"type":"Point"}
}