{
  "type": "Feature",
  "properties": {
    "addr:full":"B\u00fchelweg 3 N\u00fcziders Vorarlberg 6714",
    "addr:housenumber":"3",
    "addr:postcode":"6714",
    "addr:street":"Buehelweg",
    "iso:country":"AT",
    "sg:address":"B\u00fchelweg 3",
    "sg:city":"N\u00fcziders",
    "sg:classifiers":[
        {
            "category":"Travel",
            "subcategory":"Hotels & Motels",
            "type":"Entertainment"
        }
    ],
    "sg:phone":"+43 5552 642440",
    "sg:postcode":"6714",
    "sg:province":"Vorarlberg",
    "wof:name":"Daneu Hotel GmbH",
    "wof:placetype":"venue"
},
  "geometry": {"coordinates":[99.3196716309,26.6176605225],"type":"Point"}
}