{
  "type": "Feature",
  "properties": {
    "addr:full":"Nr 8 Rappottenstein Nieder\u00f6sterreich 3911",
    "addr:postcode":"3911",
    "addr:street":"Nr;Rappottenstein Niederoesterreich",
    "iso:country":"AT",
    "sg:address":"Nr 8",
    "sg:city":"Rappottenstein",
    "sg:orig_category":"Pensionen / Privatzimmer",
    "sg:phone":"+43 2828 8247",
    "sg:postcode":"3911",
    "sg:province":"Nieder\u00f6sterreich",
    "wof:name":"Spitaler-Steininger Christina",
    "wof:placetype":"venue"
},
  "geometry": {"coordinates":[15.0947465897,48.5537414551],"type":"Point"}
}