{
  "type": "Feature",
  "properties": {
    "iso:country":"AT",
    "sg:address":"Rohrg 11",
    "sg:city":"Baden",
    "sg:orig_category":"Bauunternehmen",
    "sg:phone":"+43 2252 85923",
    "sg:postcode":"2500",
    "sg:province":"Nieder\u00f6sterreich",
    "wof:name":"Friesenbiller G\u00fcnter GmbH",
    "wof:placetype":"venue"
},
  "geometry": {"coordinates":[16.2430667877,48.0009078979],"type":"Point"}
}