{
  "type": "Feature",
  "properties": {
    "addr:full":"Pfaffenbergsdlg 246 Amstetten Nieder\u00f6sterreich 3300",
    "addr:housenumber":"246",
    "addr:postcode":"3300",
    "addr:street":"Niederoesterreich",
    "iso:country":"AT",
    "sg:address":"Pfaffenbergsdlg 246",
    "sg:city":"Amstetten",
    "sg:orig_category":"Erdarbeiten",
    "sg:phone":"+43 7479 6308",
    "sg:postcode":"3300",
    "sg:province":"Nieder\u00f6sterreich",
    "wof:name":"Haider Johann",
    "wof:placetype":"venue"
},
  "geometry": {"coordinates":[14.8706607819,48.1244812012],"type":"Point"}
}