{
  "type": "Feature",
  "properties": {
    "addr:full":"Bauern 6 Altach Vorarlberg 6844",
    "addr:housenumber":"6",
    "addr:postcode":"6844",
    "addr:street":"Bauern",
    "iso:country":"AT",
    "sg:address":"Bauern 6",
    "sg:city":"Altach",
    "sg:orig_category":"Tankstellen",
    "sg:phone":"+43 5576 72535",
    "sg:postcode":"6844",
    "sg:province":"Vorarlberg",
    "wof:name":"OMV AG",
    "wof:placetype":"venue"
},
  "geometry": {"coordinates":[9.6614561081,47.3529701233],"type":"Point"}
}