{
  "type": "Feature",
  "properties": {
    "addr:full":"Salzachtal Bundesstr. 240 Anif Salzburg 5081",
    "addr:housenumber":"240",
    "addr:postcode":"5081",
    "addr:street":"Anif Salzburg",
    "iso:country":"AT",
    "sg:address":"Salzachtal Bundesstr. 240",
    "sg:city":"Anif",
    "sg:orig_category":"Dienstleistungen, Fotografie, Grafik U Design",
    "sg:phone":"+43 4306 246",
    "sg:postcode":"5081",
    "sg:province":"Salzburg",
    "sg:website":"http://www.kiska.at/index.htm",
    "wof:name":"KISKA creative industries",
    "wof:placetype":"venue"
},
  "geometry": {"coordinates":[13.0663318634,47.7352714539],"type":"Point"}
}