{
  "type": "Feature",
  "properties": {
    "addr:full":"Sp\u00e4thg 1 Salzburg Salzburg 5020",
    "addr:housenumber":"1",
    "addr:postcode":"5020",
    "addr:street":"Spaethg;Salzburg",
    "iso:country":"AT",
    "sg:address":"Sp\u00e4thg 1",
    "sg:city":"Salzburg",
    "sg:orig_category":"Gesundheit / Allgemeine Informationsstellen",
    "sg:phone":"+43 676 5990309",
    "sg:postcode":"5020",
    "sg:province":"Salzburg",
    "wof:name":"BirthDay - Geburtsvorbereitung in Modulen - Nachsorge",
    "wof:placetype":"venue"
},
  "geometry": {"coordinates":[13.0299844742,47.7963485718],"type":"Point"}
}