{
  "type": "Feature",
  "properties": {
    "addr:full":"Nr 19 Statzendorf Nieder\u00f6sterreich 3125",
    "addr:postcode":"3125",
    "addr:street":"Nr;Niederoesterreich",
    "iso:country":"AT",
    "sg:address":"Nr 19",
    "sg:city":"Statzendorf",
    "sg:orig_category":"Banken U Sparkassen",
    "sg:phone":"+43 4327 862278",
    "sg:postcode":"3125",
    "sg:province":"Nieder\u00f6sterreich",
    "wof:name":"Sparkasse Herzogenburg-Neulengbach",
    "wof:placetype":"venue"
},
  "geometry": {"coordinates":[15.6410522461,48.3081512451],"type":"Point"}
}