{
  "type": "Feature",
  "properties": {
    "addr:full":"Anton-Hagl-G 14/1 Gablitz Nieder\u00f6sterreich 3003",
    "addr:housenumber":"14 / 1",
    "addr:postcode":"3003",
    "addr:street":"Anton-Hagl-G",
    "iso:country":"AT",
    "sg:address":"Anton-Hagl-G 14/1",
    "sg:city":"Gablitz",
    "sg:orig_category":"Telekommunikation",
    "sg:phone":"+43 4322 3168367",
    "sg:postcode":"3003",
    "sg:province":"Nieder\u00f6sterreich",
    "wof:name":"TriCoTel Telekom GmbH",
    "wof:placetype":"venue"
},
  "geometry": {"coordinates":[16.1525478363,48.23072052],"type":"Point"}
}