{
  "type": "Feature",
  "properties": {
    "iso:country":"AT",
    "sg:address":"Dorfstr 17",
    "sg:city":"Niedernsill",
    "sg:orig_category":"Non-Classified Establishments",
    "sg:phone":"+43 6548 82380",
    "sg:postcode":"5722",
    "sg:province":"Salzburg",
    "wof:name":"Pfarramt",
    "wof:placetype":"venue"
},
  "geometry": {"coordinates":[12.6483974457,47.2805175781],"type":"Point"}
}