{
  "type": "Feature",
  "properties": {
    "addr:full":"Schubertstr 6 Graz Steiermark 8010",
    "addr:housenumber":"6",
    "addr:postcode":"8010",
    "addr:street":"Schubertstr",
    "iso:country":"AT",
    "sg:address":"Schubertstr 6",
    "sg:city":"Graz",
    "sg:orig_category":"Institute",
    "sg:phone":"+43 316 3808880",
    "sg:postcode":"8010",
    "sg:province":"Steiermark",
    "wof:name":"Inst f Pharmazeutische Technologie Karl Franzens Universit\u00e4t",
    "wof:placetype":"venue"
},
  "geometry": {"coordinates":[15.4515895844,47.0768089294],"type":"Point"}
}