{
  "type": "Feature",
  "properties": {
    "addr:full":"Hauptstr 1 Bad Erlach Nieder\u00f6sterreich 2822",
    "addr:housenumber":"1",
    "addr:postcode":"2822",
    "addr:street":"Hauptstr",
    "iso:country":"AT",
    "sg:address":"Hauptstr 1",
    "sg:city":"Bad Erlach",
    "sg:orig_category":"Tabaktrafiken",
    "sg:phone":"+43 4326 2748456",
    "sg:postcode":"2822",
    "sg:province":"Nieder\u00f6sterreich",
    "wof:name":"Panis Monika",
    "wof:placetype":"venue"
},
  "geometry": {"coordinates":[16.2147636414,47.7273368835],"type":"Point"}
}