{
  "type": "Feature",
  "properties": {
    "addr:full":"Tiergartenstr 39 Innsbruck Tirol 6020",
    "addr:housenumber":"39",
    "addr:postcode":"6020",
    "addr:street":"Tiergartenstr;Tirol",
    "iso:country":"AT",
    "sg:address":"Tiergartenstr 39",
    "sg:city":"Innsbruck",
    "sg:classifiers":[
        {
            "category":"Organizations",
            "subcategory":"Political Organization",
            "type":"Services"
        }
    ],
    "sg:phone":"+43 650 7307000",
    "sg:postcode":"6020",
    "sg:province":"Tirol",
    "sg:tags":[
        "mediation"
    ],
    "wof:name":"Streiter Christoph",
    "wof:placetype":"venue"
},
  "geometry": {"coordinates":[11.3677740097,47.2587547302],"type":"Point"}
}