{
  "type": "Feature",
  "properties": {
    "addr:full":"Bundesstr 31 Jois Burgenland 7093",
    "addr:housenumber":"31",
    "addr:postcode":"7093",
    "addr:street":"Bundesstr",
    "iso:country":"AT",
    "sg:address":"Bundesstr 31",
    "sg:city":"Jois",
    "sg:orig_category":"Autohandel",
    "sg:phone":"+43 2160 8344",
    "sg:postcode":"7093",
    "sg:province":"Burgenland",
    "wof:name":"Marczinger Friedrich",
    "wof:placetype":"venue"
},
  "geometry": {"coordinates":[16.7975940704,47.9644737244],"type":"Point"}
}