{
  "type": "Feature",
  "properties": {
    "addr:full":"Heum\u00f6ser Dornbirn Vorarlberg 6850",
    "addr:postcode":"6850",
    "iso:country":"AT",
    "sg:address":"Heum\u00f6ser",
    "sg:city":"Dornbirn",
    "sg:orig_category":"Bergbahnen",
    "sg:phone":"+43 5576 74386",
    "sg:postcode":"6850",
    "sg:province":"Vorarlberg",
    "wof:name":"Schilift Ebnit",
    "wof:placetype":"venue"
},
  "geometry": {"coordinates":[9.7437801361,47.4131889343],"type":"Point"}
}