{
  "type": "Feature",
  "properties": {
    "addr:full":"Sch\u00fctzeng 1 Wien Wien 1030",
    "addr:housenumber":"1",
    "addr:postcode":"1030",
    "addr:street":"Schuetzeng",
    "iso:country":"AT",
    "sg:address":"Sch\u00fctzeng 1",
    "sg:city":"Wien",
    "sg:classifiers":[
        {
            "category":"Professional",
            "subcategory":"Art Services",
            "type":"Services"
        }
    ],
    "sg:phone":"+43 1 7105511",
    "sg:postcode":"1030",
    "sg:province":"Wien",
    "sg:tags":[
        "designer"
    ],
    "wof:name":"Alisher Design GesmbH",
    "wof:placetype":"venue"
},
  "geometry": {"coordinates":[16.4025096893,48.1936683655],"type":"Point"}
}