{
  "type": "Feature",
  "properties": {
    "addr:full":"Obere Donaustrasse 35 Wien Wien 1020",
    "addr:housenumber":"35",
    "addr:postcode":"1020",
    "addr:street":"Obere Donaustrasse",
    "iso:country":"AT",
    "sg:address":"Obere Donaustrasse 35",
    "sg:city":"Wien",
    "sg:classifiers":[
        {
            "category":"Professional",
            "subcategory":"Advertising",
            "type":"Services"
        }
    ],
    "sg:phone":"+43 1 3300310",
    "sg:postcode":"1020",
    "sg:province":"Wien",
    "sg:tags":[
        "article",
        "porcelain",
        "ceramic"
    ],
    "sg:website":"schloegl.at",
    "wof:name":"G\u00fcnter Schl\u00f6gl",
    "wof:placetype":"venue"
},
  "geometry": {"coordinates":[16.3696556091,48.2207374573],"type":"Point"}
}