{
  "type": "Feature",
  "properties": {
    "addr:full":"Untere Hauptstr 162 Gamlitz Steiermark 8462",
    "addr:housenumber":"162",
    "addr:postcode":"8462",
    "addr:street":"Untere Hauptstr",
    "iso:country":"AT",
    "sg:address":"Untere Hauptstr 162",
    "sg:city":"Gamlitz",
    "sg:orig_category":"\u00c3\u201enderungsschneidereien",
    "sg:phone":"+43 4334 534237",
    "sg:postcode":"8462",
    "sg:province":"Steiermark",
    "wof:name":"\u00e4nderungsschneiderei Trunk Renate",
    "wof:placetype":"venue"
},
  "geometry": {"coordinates":[15.5583257675,46.7215309143],"type":"Point"}
}