{
  "type": "Feature",
  "properties": {
    "addr:full":"Diehlg 50 Wien Wien 1050",
    "addr:housenumber":"50",
    "addr:postcode":"1050",
    "addr:street":"Diehlg",
    "iso:country":"AT",
    "sg:address":"Diehlg 50",
    "sg:city":"Wien",
    "sg:classifiers":[
        {
            "category":"Professional",
            "subcategory":"Management & Consulting",
            "type":"Services"
        }
    ],
    "sg:phone":"+43 699 11885533",
    "sg:postcode":"1050",
    "sg:province":"Wien",
    "wof:name":"MANAGEMENT",
    "wof:placetype":"venue"
},
  "geometry": {"coordinates":[16.3584918976,48.19165802],"type":"Point"}
}