{
  "type": "Feature",
  "properties": {
    "addr:full":"Wiener Str 20 Asten Ober\u00f6sterreich 4481",
    "addr:housenumber":"20",
    "addr:postcode":"4481",
    "iso:country":"AT",
    "sg:address":"Wiener Str 20",
    "sg:city":"Asten",
    "sg:orig_category":"Banken U Sparkassen",
    "sg:phone":"+43 7224 66263",
    "sg:postcode":"4481",
    "sg:province":"Ober\u00f6sterreich",
    "wof:name":"VKB-Bank Volkskreditbank AG",
    "wof:placetype":"venue"
},
  "geometry": {"coordinates":[14.4196271896,48.2187538147],"type":"Point"}
}