{
  "type": "Feature",
  "properties": {
    "addr:full":"Neustrasse 8 Sierning Ober\u00f6sterreich 4522",
    "addr:housenumber":"8",
    "addr:postcode":"4522",
    "addr:street":"Neustrasse",
    "iso:country":"AT",
    "sg:address":"Neustrasse 8",
    "sg:city":"Sierning",
    "sg:orig_category":"Dual Inline Package Dip Switches",
    "sg:phone":"+43 7259 2366",
    "sg:postcode":"4522",
    "sg:province":"Ober\u00f6sterreich",
    "wof:name":"ROKA Schaltanlagenbau Ges.m.b.H.",
    "wof:placetype":"venue"
},
  "geometry": {"coordinates":[14.3085136414,48.0438079834],"type":"Point"}
}