{
  "type": "Feature",
  "properties": {
    "addr:full":"Friedmanngasse 4 Wien Wien 1160",
    "addr:housenumber":"4",
    "addr:postcode":"1160",
    "addr:street":"Friedmanngasse",
    "iso:country":"AT",
    "sg:address":"Friedmanngasse 4",
    "sg:city":"Wien",
    "sg:classifiers":[
        {
            "category":"Manufacturing",
            "subcategory":"Wood Products",
            "type":"Manufacturing & Wholesale Goods"
        }
    ],
    "sg:phone":"+43 1 4063321",
    "sg:postcode":"1160",
    "sg:province":"Wien",
    "sg:tags":[
        "solid",
        "ceiling",
        "made",
        "panel"
    ],
    "wof:name":"Ing.Mag.Dr. Hans Kremer",
    "wof:placetype":"venue"
},
  "geometry": {"coordinates":[16.337890625,48.2123908997],"type":"Point"}
}