{
  "type": "Feature",
  "properties": {
    "iso:country":"AT",
    "sg:address":"M\u00f6llersdorfer Str 1",
    "sg:city":"Guntramsdorf",
    "sg:orig_category":"Non-Classified Establishments",
    "sg:phone":"+43 2236 53507",
    "sg:postcode":"2353",
    "sg:province":"Nieder\u00f6sterreich",
    "wof:name":"Pfarramt Guntramsdorf",
    "wof:placetype":"venue"
},
  "geometry": {"coordinates":[16.3135509491,48.0464630127],"type":"Point"}
}