{
  "type": "Feature",
  "properties": {
    "addr:full":"Nr 198 Stubenberg am See Steiermark 8223",
    "addr:postcode":"8223",
    "addr:street":"Nr;Stubenberg Am See Steiermark",
    "iso:country":"AT",
    "sg:address":"Nr 198",
    "sg:city":"Stubenberg am See",
    "sg:orig_category":"Zahntechnische Laboratorien",
    "sg:phone":"+43 3176 87370",
    "sg:postcode":"8223",
    "sg:province":"Steiermark",
    "wof:name":"Strasser Rudolf",
    "wof:placetype":"venue"
},
  "geometry": {"coordinates":[15.8099899292,47.2565307617],"type":"Point"}
}