{
  "type": "Feature",
  "properties": {
    "addr:full":"Klagenfurter Str 46 Velden am W\u00f6rther See K\u00e4rnten 9220",
    "addr:postcode":"9220",
    "addr:street":"Str 46;Kaernten",
    "iso:country":"AT",
    "sg:address":"Klagenfurter Str 46",
    "sg:city":"Velden am W\u00f6rther See",
    "sg:orig_category":"Appartements / Ferienwohnungen",
    "sg:phone":"+43 4274 39770",
    "sg:postcode":"9220",
    "sg:province":"K\u00e4rnten",
    "wof:name":"Villa Christa - Inh Stecher Christa",
    "wof:placetype":"venue"
},
  "geometry": {"coordinates":[14.0557088852,46.6187744141],"type":"Point"}
}