{
  "type": "Feature",
  "properties": {
    "addr:full":"M\u00f6wenstr 9 Salzburg Salzburg 5020",
    "addr:housenumber":"9",
    "addr:postcode":"5020",
    "addr:street":"Moewenstr;Salzburg",
    "iso:country":"AT",
    "sg:address":"M\u00f6wenstr 9",
    "sg:city":"Salzburg",
    "sg:orig_category":"Tischlereien",
    "sg:phone":"+43 676 5668476",
    "sg:postcode":"5020",
    "sg:province":"Salzburg",
    "wof:name":"Montagetischler Gebr\u00fcder Rohun OEG",
    "wof:placetype":"venue"
},
  "geometry": {"coordinates":[13.0349378586,47.8250236511],"type":"Point"}
}