{
  "type": "Feature",
  "properties": {
    "iso:country":"AT",
    "sg:address":"Erlachg 95",
    "sg:city":"Wien",
    "sg:orig_category":"Psychotherapie",
    "sg:phone":"+43 1 6032828",
    "sg:postcode":"1100",
    "sg:province":"Wien",
    "wof:name":"Schmoll Dieter",
    "wof:placetype":"venue"
},
  "geometry": {"coordinates":[16.3742923737,48.1770706177],"type":"Point"}
}