{
  "type": "Feature",
  "properties": {
    "addr:full":"Bethleng 6 Wien Wien 1120",
    "addr:housenumber":"6",
    "addr:postcode":"1120",
    "addr:street":"Bethleng",
    "iso:country":"AT",
    "sg:address":"Bethleng 6",
    "sg:city":"Wien",
    "sg:orig_category":"Waren Aller Art",
    "sg:phone":"+43 1 8042175",
    "sg:postcode":"1120",
    "sg:province":"Wien",
    "wof:name":"Pekarek HandelsgesmbH",
    "wof:placetype":"venue"
},
  "geometry": {"coordinates":[16.3093776703,48.1696548462],"type":"Point"}
}