{
  "type": "Feature",
  "properties": {
    "addr:full":"Himmelberger Str 4a Feldkirchen in K\u00e4rnten K\u00e4rnten 9560",
    "addr:postcode":"9560",
    "addr:street":"Str 4A;Kaernten",
    "iso:country":"AT",
    "sg:address":"Himmelberger Str 4a",
    "sg:city":"Feldkirchen in K\u00e4rnten",
    "sg:orig_category":"Glasereien",
    "sg:phone":"+43 4342 762098",
    "sg:postcode":"9560",
    "sg:province":"K\u00e4rnten",
    "wof:name":"Laggner-Glas GmbH",
    "wof:placetype":"venue"
},
  "geometry": {"coordinates":[14.088640213,46.7254295349],"type":"Point"}
}