{
  "type": "Feature",
  "properties": {
    "addr:full":"Kirchheimer Weg 6 Bad Kleinkirchheim K\u00e4rnten 9546",
    "addr:housenumber":"6",
    "addr:postcode":"9546",
    "addr:street":"Kirchheimer Weg",
    "iso:country":"AT",
    "sg:address":"Kirchheimer Weg 6",
    "sg:city":"Bad Kleinkirchheim",
    "sg:classifiers":[
        {
            "category":"Travel",
            "subcategory":"Hotels & Motels",
            "type":"Entertainment"
        }
    ],
    "sg:phone":"+43 4240 4520",
    "sg:postcode":"9546",
    "sg:province":"K\u00e4rnten",
    "wof:name":"Harmony Hotel Pr\u00e4gant BetriebsgesmbH & Co KG",
    "wof:placetype":"venue"
},
  "geometry": {"coordinates":[13.7976551056,46.8146514893],"type":"Point"}
}