{
  "type": "Feature",
  "properties": {
    "addr:full":"G\u00e4nsebl\u00fcmchenweg 12 Wien Wien 1220",
    "addr:housenumber":"12",
    "addr:postcode":"1220",
    "addr:street":"Gaensebluemchenweg",
    "iso:country":"AT",
    "sg:address":"G\u00e4nsebl\u00fcmchenweg 12",
    "sg:city":"Wien",
    "sg:orig_category":"Isolierungen",
    "sg:phone":"+43 1 7343276",
    "sg:postcode":"1220",
    "sg:province":"Wien",
    "wof:name":"Schmid Alexandra Isolierungen GmbH",
    "wof:placetype":"venue"
},
  "geometry": {"coordinates":[16.444606781,48.2497138977],"type":"Point"}
}