{
  "type": "Feature",
  "properties": {
    "iso:country":"AT",
    "sg:address":"Immenweg 1",
    "sg:city":"Sitzenberg-Reidling",
    "sg:orig_category":"Imkereien",
    "sg:phone":"+43 2276 2885",
    "sg:postcode":"3454",
    "sg:province":"Nieder\u00f6sterreich",
    "wof:name":"Sch\u00e4ffel Karl",
    "wof:placetype":"venue"
},
  "geometry": {"coordinates":[15.8134250641,48.3164482117],"type":"Point"}
}