{
  "type": "Feature",
  "properties": {
    "addr:full":"Rosbachstr 586 Kaprun Salzburg 5710",
    "addr:housenumber":"586",
    "addr:postcode":"5710",
    "addr:street":"Kaprun Salzburg",
    "iso:country":"AT",
    "sg:address":"Rosbachstr 586",
    "sg:city":"Kaprun",
    "sg:orig_category":"Pensionen / Privatzimmer",
    "sg:phone":"+43 6547 71450",
    "sg:postcode":"5710",
    "sg:province":"Salzburg",
    "wof:name":"Appartements Johannahof",
    "wof:placetype":"venue"
},
  "geometry": {"coordinates":[12.7681894302,47.2716789246],"type":"Point"}
}