{
  "type": "Feature",
  "properties": {
    "iso:country":"AT",
    "sg:address":"Universit\u00e4tsstr 4",
    "sg:city":"Wien",
    "sg:orig_category":"Bilderrahmen",
    "sg:phone":"+43 1 5818446",
    "sg:postcode":"1090",
    "sg:province":"Wien",
    "wof:name":"HYPARTS Peter Franz Wimberger KEG",
    "wof:placetype":"venue"
},
  "geometry": {"coordinates":[16.3578090668,48.2146148682],"type":"Point"}
}