{
  "type": "Feature",
  "properties": {
    "addr:full":"Markt 17 Neufelden Ober\u00f6sterreich 4120",
    "addr:housenumber":"17",
    "addr:postcode":"4120",
    "addr:street":"Markt",
    "iso:country":"AT",
    "sg:address":"Markt 17",
    "sg:city":"Neufelden",
    "sg:orig_category":"Lebensmittel / Einzelhandel",
    "sg:phone":"+43 7282 6250",
    "sg:postcode":"4120",
    "sg:province":"Ober\u00f6sterreich",
    "wof:name":"Adek aktiv Markt",
    "wof:placetype":"venue"
},
  "geometry": {"coordinates":[14.0008211136,48.4846382141],"type":"Point"}
}