{
  "type": "Feature",
  "properties": {
    "addr:full":"Wiesensteig 49/2 Villach K\u00e4rnten 9500",
    "addr:housenumber":"49 / 2",
    "addr:postcode":"9500",
    "addr:street":"Wiesensteig;Kaernten",
    "iso:country":"AT",
    "sg:address":"Wiesensteig 49/2",
    "sg:city":"Villach",
    "sg:orig_category":"Fotografen",
    "sg:phone":"+43 664 1354224",
    "sg:postcode":"9500",
    "sg:province":"K\u00e4rnten",
    "wof:name":"H\u00f6her Oskar",
    "wof:placetype":"venue"
},
  "geometry": {"coordinates":[13.8228721619,46.6181488037],"type":"Point"}
}