{
  "type": "Feature",
  "properties": {
    "addr:full":"Krottendorf 161 Krottendorf-Gaisfeld Steiermark 8564",
    "addr:housenumber":"161",
    "addr:postcode":"krottendorf-gaisfeld;8564",
    "addr:street":"Krottendorf",
    "iso:country":"AT",
    "sg:address":"Krottendorf 161",
    "sg:city":"Krottendorf-Gaisfeld",
    "sg:orig_category":"Non-Classified Establishments",
    "sg:phone":"+43 5 91336194",
    "sg:postcode":"8564",
    "sg:province":"Steiermark",
    "wof:name":"Gendarmerieposten",
    "wof:placetype":"venue"
},
  "geometry": {"coordinates":[15.1982555389,47.002872467],"type":"Point"}
}