{
  "type": "Feature",
  "properties": {
    "addr:full":"Reichsstr 9 Lustenau Vorarlberg 6890",
    "addr:housenumber":"9",
    "addr:postcode":"6890",
    "addr:street":"Reichsstr",
    "iso:country":"AT",
    "sg:address":"Reichsstr 9",
    "sg:city":"Lustenau",
    "sg:orig_category":"Landwirtschaftliche Produkte",
    "sg:phone":"+43 4355 7782207",
    "sg:postcode":"6890",
    "sg:province":"Vorarlberg",
    "wof:name":"Heu- u Christbaumgro\u00dfhandel Alge",
    "wof:placetype":"venue"
},
  "geometry": {"coordinates":[9.6499481201,47.4316520691],"type":"Point"}
}