{
  "type": "Feature",
  "properties": {
    "addr:full":"Weikersdorfer Str 5b Wiener Neustadt Nieder\u00f6sterreich 2700",
    "addr:postcode":"2700",
    "addr:street":"Str 5B",
    "iso:country":"AT",
    "sg:address":"Weikersdorfer Str 5b",
    "sg:city":"Wiener Neustadt",
    "sg:classifiers":[
        {
            "category":"Taxi",
            "type":"Transportation"
        }
    ],
    "sg:phone":"+43 4326 2225406",
    "sg:postcode":"2700",
    "sg:province":"Nieder\u00f6sterreich",
    "sg:tags":[
        "personentransporte",
        "u"
    ],
    "wof:name":"Lovasz Franz",
    "wof:placetype":"venue"
},
  "geometry": {"coordinates":[16.2298374176,47.8083877563],"type":"Point"}
}