{
  "type": "Feature",
  "properties": {
    "addr:full":"Wiener Str 72 P\u00f6chlarn Nieder\u00f6sterreich 3380",
    "addr:postcode":"3380",
    "addr:street":"72 Poechlarn",
    "iso:country":"AT",
    "sg:address":"Wiener Str 72",
    "sg:city":"P\u00f6chlarn",
    "sg:orig_category":"Handarbeiten",
    "sg:phone":"+43 2757 46710",
    "sg:postcode":"3380",
    "sg:province":"Nieder\u00f6sterreich",
    "wof:name":"Elisa-Gro\u00dfhandels GmbH",
    "wof:placetype":"venue"
},
  "geometry": {"coordinates":[-79.38526153559999,41.2145881653],"type":"Point"}
}