{
  "type": "Feature",
  "properties": {
    "addr:full":"Hauptpl 6 Friedberg Steiermark 8240",
    "addr:housenumber":"6",
    "addr:postcode":"8240",
    "addr:street":"Hauptpl",
    "iso:country":"AT",
    "sg:address":"Hauptpl 6",
    "sg:city":"Friedberg",
    "sg:classifiers":[
        {
            "category":"Travel",
            "subcategory":"Hotels & Motels",
            "type":"Entertainment"
        }
    ],
    "sg:phone":"+43 4333 39225100",
    "sg:postcode":"8240",
    "sg:province":"Steiermark",
    "wof:name":"Schwarzer Adler",
    "wof:placetype":"venue"
},
  "geometry": {"coordinates":[16.0575752258,47.4417915344],"type":"Point"}
}