{
  "type": "Feature",
  "properties": {
    "addr:full":"Triester Str 2 Wien Wien 1100",
    "addr:housenumber":"2",
    "addr:postcode":"1100",
    "addr:street":"Str",
    "iso:country":"AT",
    "sg:address":"Triester Str 2",
    "sg:city":"Wien",
    "sg:orig_category":"Installationsmaterialien",
    "sg:phone":"+43 1 6001065",
    "sg:postcode":"1100",
    "sg:province":"Wien",
    "wof:name":"\u00d6AG Handelsbeteiligungs AG Gesch\u00e4ftsbereich \u00d6AG Sanit\u00e4r- und Heizungsgro\u00dfhandel",
    "wof:placetype":"venue"
},
  "geometry": {"coordinates":[16.3580875397,48.1796836853],"type":"Point"}
}