{
  "type": "Feature",
  "properties": {
    "iso:country":"AT",
    "sg:address":"Petzoldstr. 6",
    "sg:city":"Linz",
    "sg:classifiers":[
        {
            "category":"Professional",
            "subcategory":"Advertising",
            "type":"Services"
        }
    ],
    "sg:phone":"+43 4373 2784949",
    "sg:postcode":"4020",
    "sg:province":"Ober\u00f6sterreich",
    "sg:tags":[
        "communication",
        "medium"
    ],
    "wof:name":"DIREKTA DRUCKEREI & DIREKTMARKETING GESMBH & CO KG",
    "wof:placetype":"venue"
},
  "geometry": {"coordinates":[14.302945137,48.3155670166],"type":"Point"}
}