{
  "type": "Feature",
  "properties": {
    "iso:country":"AT",
    "sg:address":"R\u00f6merstr 9",
    "sg:city":"Bregenz",
    "sg:orig_category":"Volkshochschulen",
    "sg:phone":"+43 5574 525240",
    "sg:postcode":"6900",
    "sg:province":"Vorarlberg",
    "sg:website":"vol.at/Volkshochschule",
    "wof:name":"Volkshochschule",
    "wof:placetype":"venue"
},
  "geometry": {"coordinates":[9.7452926636,47.5016136169],"type":"Point"}
}