{
  "type": "Feature",
  "properties": {
    "addr:full":"D\u00f6blinger Hauptstr 17 Wien Wien 1190",
    "addr:housenumber":"17",
    "addr:postcode":"1190",
    "addr:street":"Hauptstr",
    "iso:country":"AT",
    "sg:address":"D\u00f6blinger Hauptstr 17",
    "sg:city":"Wien",
    "sg:classifiers":[
        {
            "category":"Internet Cafe",
            "subcategory":"None",
            "type":"Food & Drink"
        }
    ],
    "sg:phone":"+43 4313 502633",
    "sg:postcode":"1190",
    "sg:province":"Wien",
    "wof:name":"Revisage Davor Hinger KEG",
    "wof:placetype":"venue"
},
  "geometry": {"coordinates":[16.3529567719,48.2355804443],"type":"Point"}
}