{
  "type": "Feature",
  "properties": {
    "addr:full":"Hernalser Hauptstr 32-34 Wien Wien 1170",
    "addr:postcode":"32-34;1170",
    "addr:street":"Hernalser Hauptstr",
    "iso:country":"AT",
    "sg:address":"Hernalser Hauptstr 32-34",
    "sg:city":"Wien",
    "sg:orig_category":"Tankstellen",
    "sg:phone":"+43 1 40646490",
    "sg:postcode":"1170",
    "sg:province":"Wien",
    "wof:name":"BP Austria Marketing GmbH",
    "wof:placetype":"venue"
},
  "geometry": {"coordinates":[16.3382663727,48.2172698975],"type":"Point"}
}