{
  "type": "Feature",
  "properties": {
    "addr:full":"Franz-Josefs-Kai 65 Wien Wien 1010",
    "addr:housenumber":"65",
    "addr:postcode":"1010",
    "addr:street":"Franz-Josefs-Kai",
    "iso:country":"AT",
    "sg:address":"Franz-Josefs-Kai 65",
    "sg:city":"Wien",
    "sg:orig_category":"\u00c3\u201erzte / F Allgemeinmedizin",
    "sg:phone":"+43 1 3175384",
    "sg:postcode":"1010",
    "sg:province":"Wien",
    "wof:name":"Schmidt Christine MR Dr med univ",
    "wof:placetype":"venue"
},
  "geometry": {"coordinates":[16.3702507019,48.2173690796],"type":"Point"}
}