{
  "type": "Feature",
  "properties": {
    "addr:full":"Oberhauser Str 15 Enns Ober\u00f6sterreich 4470",
    "addr:postcode":"4470",
    "addr:street":"Str 15",
    "iso:country":"AT",
    "sg:address":"Oberhauser Str 15",
    "sg:city":"Enns",
    "sg:orig_category":"Metallwaren / Erzeugung U Gro\u00c3\u0178handel",
    "sg:phone":"+43 4372 23849260",
    "sg:postcode":"4470",
    "sg:province":"Ober\u00f6sterreich",
    "wof:name":"Hapu Metallwaren GmbH & Co KG",
    "wof:placetype":"venue"
},
  "geometry": {"coordinates":[14.4579648972,48.2199668884],"type":"Point"}
}