{
  "type": "Feature",
  "properties": {
    "iso:country":"AT",
    "sg:address":"Mistlberg 80",
    "sg:city":"Tragwein",
    "sg:classifiers":[
        {
            "category":"Professional",
            "type":"Services"
        }
    ],
    "sg:phone":"+43 7263 882940",
    "sg:postcode":"4284",
    "sg:province":"Ober\u00f6sterreich",
    "sg:tags":[
        "mould",
        "construction"
    ],
    "wof:name":"Johann Haunschmidt GmbH",
    "wof:placetype":"venue"
},
  "geometry": {"coordinates":[14.5943670273,48.3415794373],"type":"Point"}
}