{
  "type": "Feature",
  "properties": {
    "addr:full":"Kolpingstr 20 Wien Wien 1230",
    "addr:housenumber":"20",
    "addr:postcode":"1230",
    "addr:street":"Kolpingstr",
    "iso:country":"AT",
    "sg:address":"Kolpingstr 20",
    "sg:city":"Wien",
    "sg:orig_category":"Juwelier- U Uhrmacherbedarf",
    "sg:phone":"+43 1 61627000",
    "sg:postcode":"1230",
    "sg:province":"Wien",
    "wof:name":"Schembera & Co GmbH",
    "wof:placetype":"venue"
},
  "geometry": {"coordinates":[16.343214035,48.1385498047],"type":"Point"}
}