{
  "type": "Feature",
  "properties": {
    "addr:full":"Oberhofsdlg 401 Admont Steiermark 8911",
    "addr:housenumber":"401",
    "addr:postcode":"8911",
    "addr:street":"Oberhofsdlg",
    "iso:country":"AT",
    "sg:address":"Oberhofsdlg 401",
    "sg:city":"Admont",
    "sg:orig_category":"Blumeneinzelhandel",
    "sg:phone":"+43 3613 2277",
    "sg:postcode":"8911",
    "sg:province":"Steiermark",
    "wof:name":"Zechner Sabine Blumenstube und G\u00e4rtnerei",
    "wof:placetype":"venue"
},
  "geometry": {"coordinates":[14.4609088898,47.5760040283],"type":"Point"}
}