{
  "type": "Feature",
  "properties": {
    "addr:full":"Hauptpl 21 Sitzendorf an der Schmida Nieder\u00f6sterreich 3714",
    "addr:housenumber":"21",
    "addr:postcode":"3714",
    "addr:street":"Hauptpl",
    "iso:country":"AT",
    "sg:address":"Hauptpl 21",
    "sg:city":"Sitzendorf an der Schmida",
    "sg:orig_category":"Friseure U Frisiersalons",
    "sg:phone":"+43 4366 43336244",
    "sg:postcode":"3714",
    "sg:province":"Nieder\u00f6sterreich",
    "wof:name":"Hengstberger Sabine - Mobilfriseur",
    "wof:placetype":"venue"
},
  "geometry": {"coordinates":[15.9412727356,48.5979576111],"type":"Point"}
}