{
  "type": "Feature",
  "properties": {
    "iso:country":"AT",
    "sg:address":"Dorf 130",
    "sg:city":"Finkenberg",
    "sg:classifiers":[
        {
            "category":"Park",
            "subcategory":"Provincial",
            "type":"Public Place"
        }
    ],
    "sg:phone":"+43 5285 62671",
    "sg:postcode":"6292",
    "sg:province":"Tirol",
    "sg:tags":[
        "u",
        "ski-",
        "snowboardschulen"
    ],
    "sg:website":"www.skischulesunny.at",
    "wof:name":"Skischule Sunny Finkenberg Inh Franz Stock",
    "wof:placetype":"venue"
},
  "geometry": {"coordinates":[11.8246116638,47.1548347473],"type":"Point"}
}