{
  "type": "Feature",
  "properties": {
    "iso:country":"AT",
    "sg:address":"M\u00fchldorfstr 3",
    "sg:city":"Mondsee",
    "sg:orig_category":"Beratungsstellen",
    "sg:phone":"+43 6232 6145",
    "sg:postcode":"5310",
    "sg:province":"Ober\u00f6sterreich",
    "wof:name":"Beyrer Petra",
    "wof:placetype":"venue"
},
  "geometry": {"coordinates":[13.349562645,47.855255127],"type":"Point"}
}