{
  "type": "Feature",
  "properties": {
    "addr:full":"Mariahilfer Str 45 Wien Wien 1060",
    "addr:postcode":"1060",
    "addr:street":"Str 45",
    "iso:country":"AT",
    "sg:address":"Mariahilfer Str 45",
    "sg:city":"Wien",
    "sg:orig_category":"Pelze U Pelzwaren",
    "sg:phone":"+43 4315 877370",
    "sg:postcode":"1060",
    "sg:province":"Wien",
    "wof:name":"Vogue Pelze - Tuscher Johanna",
    "wof:placetype":"venue"
},
  "geometry": {"coordinates":[16.3549919128,48.2000007629],"type":"Point"}
}