{
  "type": "Feature",
  "properties": {
    "addr:full":"Neusiedler Str 32 Eisenstadt Burgenland 7000",
    "addr:postcode":"7000",
    "addr:street":"Str 32",
    "iso:country":"AT",
    "sg:address":"Neusiedler Str 32",
    "sg:city":"Eisenstadt",
    "sg:orig_category":"Boutiquen",
    "sg:phone":"+43 2682 75757",
    "sg:postcode":"7000",
    "sg:province":"Burgenland",
    "wof:name":"Boutique Lady Schick",
    "wof:placetype":"venue"
},
  "geometry": {"coordinates":[16.5307693481,47.8469085693],"type":"Point"}
}