{
  "type": "Feature",
  "properties": {
    "addr:full":"Max-Mell-G 5 Kalsdorf Steiermark 8401",
    "addr:housenumber":"5",
    "addr:postcode":"8401",
    "addr:street":"Max-Mell-G",
    "iso:country":"AT",
    "sg:address":"Max-Mell-G 5",
    "sg:city":"Kalsdorf",
    "sg:orig_category":"Maler, Anstreicher U Lackierer",
    "sg:phone":"+43 4331 3554569",
    "sg:postcode":"8401",
    "sg:province":"Steiermark",
    "wof:name":"Rischar Malerbetrieb u Fassadenanstriche",
    "wof:placetype":"venue"
},
  "geometry": {"coordinates":[15.4719438553,46.9716567993],"type":"Point"}
}