{
  "type": "Feature",
  "properties": {
    "addr:full":"Margaretenstr 21 Wien Wien 1040",
    "addr:housenumber":"21",
    "addr:postcode":"1040",
    "addr:street":"Margaretenstr",
    "iso:country":"AT",
    "sg:address":"Margaretenstr 21",
    "sg:city":"Wien",
    "sg:orig_category":"Ingenieurkonsulenten / Zivilingenieure",
    "sg:phone":"+43 1 5815277",
    "sg:postcode":"1040",
    "sg:province":"Wien",
    "wof:name":"P\u00fcchl Gernot Prof Dipl-Ing",
    "wof:placetype":"venue"
},
  "geometry": {"coordinates":[16.3649406433,48.1959686279],"type":"Point"}
}