{
  "type": "Feature",
  "properties": {
    "addr:full":"Dopschstr Wien Wien 1210",
    "addr:postcode":"1210",
    "iso:country":"AT",
    "sg:address":"Dopschstr",
    "sg:city":"Wien",
    "sg:orig_category":"Non-Classified Establishments",
    "sg:phone":"+43 1 2582720",
    "sg:postcode":"1210",
    "sg:province":"Wien",
    "wof:name":"TAXI-TEL Standplatztelefon Betriebs GmbH",
    "wof:placetype":"venue"
},
  "geometry": {"coordinates":[16.4447345734,48.2699661255],"type":"Point"}
}