{
  "type": "Feature",
  "properties": {
    "addr:full":"Schulh\u00e4usl 211 Alpbach Tirol 6236",
    "addr:housenumber":"211",
    "addr:postcode":"6236",
    "addr:street":"Alpbach Tirol",
    "iso:country":"AT",
    "sg:address":"Schulh\u00e4usl 211",
    "sg:city":"Alpbach",
    "sg:orig_category":"Lebensmittel / Einzelhandel",
    "sg:phone":"+43 5336 5884",
    "sg:postcode":"6236",
    "sg:province":"Tirol",
    "wof:name":"Spar-Markt Inh Georg Reichs\u00f6llner",
    "wof:placetype":"venue"
},
  "geometry": {"coordinates":[11.9435110092,47.3986091614],"type":"Point"}
}