{
  "type": "Feature",
  "properties": {
    "addr:full":"Grazer Str 134 Leibnitz Steiermark 8430",
    "addr:housenumber":"134",
    "addr:postcode":"8430",
    "addr:street":"Steiermark",
    "iso:country":"AT",
    "sg:address":"Grazer Str 134",
    "sg:city":"Leibnitz",
    "sg:orig_category":"Tankstellen",
    "sg:phone":"+43 3452 83783",
    "sg:postcode":"8430",
    "sg:province":"Steiermark",
    "wof:name":"OMV AG",
    "wof:placetype":"venue"
},
  "geometry": {"coordinates":[15.5383825302,46.7938842773],"type":"Point"}
}