{
  "type": "Feature",
  "properties": {
    "iso:country":"AT",
    "sg:address":"Koaserbauerstrasse 18",
    "sg:city":"Gmunden",
    "sg:classifiers":[
        {
            "category":"Manufacturing",
            "subcategory":"Motor Vehicles & Parts",
            "type":"Manufacturing & Wholesale Goods"
        }
    ],
    "sg:phone":"+43 7612649020",
    "sg:postcode":"4810",
    "sg:province":"Ober\u00f6sterreich",
    "sg:tags":[
        "component",
        "hydraulic"
    ],
    "sg:website":"grampelhuber.at",
    "wof:name":"Grampelhuber Ges.m.b.H.",
    "wof:placetype":"venue"
},
  "geometry": {"coordinates":[13.8146009445,47.9267234802],"type":"Point"}
}