{
  "type": "Feature",
  "properties": {
    "addr:full":"Wienergrabenstr 307 Kaltenleutgeben Nieder\u00f6sterreich 2391",
    "addr:housenumber":"307",
    "addr:postcode":"2391",
    "iso:country":"AT",
    "sg:address":"Wienergrabenstr 307",
    "sg:city":"Kaltenleutgeben",
    "sg:classifiers":[
        {
            "category":"Restaurant",
            "type":"Food & Drink"
        }
    ],
    "sg:phone":"+43 2238 71314",
    "sg:postcode":"2391",
    "sg:province":"Nieder\u00f6sterreich",
    "wof:name":"Wiener-H\u00fctte",
    "wof:placetype":"venue"
},
  "geometry": {"coordinates":[16.2155265808,48.1251907349],"type":"Point"}
}