{
  "type": "Feature",
  "properties": {
    "addr:full":"Hauptpl 13 Mank Nieder\u00f6sterreich 3240",
    "addr:housenumber":"13",
    "addr:postcode":"3240",
    "addr:street":"Hauptpl;Niederoesterreich",
    "iso:country":"AT",
    "sg:address":"Hauptpl 13",
    "sg:city":"Mank",
    "sg:orig_category":"Zahntechnische Laboratorien",
    "sg:phone":"+43 2755 21022",
    "sg:postcode":"3240",
    "sg:province":"Nieder\u00f6sterreich",
    "wof:name":"Hiesberger & Zellhofer OEG",
    "wof:placetype":"venue"
},
  "geometry": {"coordinates":[15.3417243958,48.112071991],"type":"Point"}
}