{
  "type": "Feature",
  "properties": {
    "iso:country":"AT",
    "sg:address":"Nr 69",
    "sg:city":"Brand",
    "sg:orig_category":"Imkereien",
    "sg:phone":"+43 4328 597595",
    "sg:postcode":"3873",
    "sg:province":"Nieder\u00f6sterreich",
    "wof:name":"Imkerei Hermann u Petra Fischer",
    "wof:placetype":"venue"
},
  "geometry": {"coordinates":[146.71984863279999,-38.3033790588],"type":"Point"}
}