{
  "type": "Feature",
  "properties": {
    "iso:country":"AT",
    "sg:address":"Bayernstra\u00dfe 376 ",
    "sg:city":"Wals",
    "sg:classifiers":[
        {
            "category":"Building & Trades",
            "subcategory":"Construction",
            "type":"Services"
        }
    ],
    "sg:phone":"+43 4366 2853337",
    "sg:postcode":"5071",
    "sg:province":"Salzburg",
    "sg:tags":[
        "work",
        "public"
    ],
    "wof:name":"FRITZ & CO BAU GMBH",
    "wof:placetype":"venue"
},
  "geometry": {"coordinates":[12.9693145752,47.7897644043],"type":"Point"}
}