{
  "type": "Feature",
  "properties": {
    "addr:full":"Marktpl 3 Pregarten Ober\u00f6sterreich 4230",
    "addr:housenumber":"3",
    "addr:postcode":"4230",
    "addr:street":"Marktpl",
    "iso:country":"AT",
    "sg:address":"Marktpl 3",
    "sg:city":"Pregarten",
    "sg:orig_category":"Bars-Cafes",
    "sg:phone":"+43 699 11499321",
    "sg:postcode":"4230",
    "sg:province":"Ober\u00f6sterreich",
    "wof:name":"American Bar",
    "wof:placetype":"venue"
},
  "geometry": {"coordinates":[14.530371666,48.3547058105],"type":"Point"}
}