{
  "type": "Feature",
  "properties": {
    "addr:full":"Abelstr 8 Aschach an der Donau Ober\u00f6sterreich 4082",
    "addr:housenumber":"8",
    "addr:postcode":"4082",
    "addr:street":"Abelstr",
    "iso:country":"AT",
    "sg:address":"Abelstr 8",
    "sg:city":"Aschach an der Donau",
    "sg:orig_category":"Lebensmittel / Einzelhandel",
    "sg:phone":"+43 7273 6013",
    "sg:postcode":"4082",
    "sg:province":"Ober\u00f6sterreich",
    "wof:name":"SPAR \u00f6sterreichische Warenhandels-AG",
    "wof:placetype":"venue"
},
  "geometry": {"coordinates":[14.0232467651,48.364151001],"type":"Point"}
}