{
  "type": "Feature",
  "properties": {
    "iso:country":"AT",
    "sg:address":"Glockenspielpl 5",
    "sg:city":"Graz",
    "sg:orig_category":"Damenmoden",
    "sg:phone":"+43 316 828986",
    "sg:postcode":"8010",
    "sg:province":"Steiermark",
    "wof:name":"Oxyd Men & Woman Fashion Shop",
    "wof:placetype":"venue"
},
  "geometry": {"coordinates":[15.4412002563,47.0710716248],"type":"Point"}
}