{
  "type": "Feature",
  "properties": {
    "addr:full":"Rotkreuzstr 73b Lustenau Vorarlberg 6890",
    "addr:housenumber":"73b",
    "addr:postcode":"6890",
    "addr:street":"Rotkreuzstr",
    "iso:country":"AT",
    "sg:address":"Rotkreuzstr 73b",
    "sg:city":"Lustenau",
    "sg:orig_category":"Erdarbeiten",
    "sg:phone":"+43 5577 87196",
    "sg:postcode":"6890",
    "sg:province":"Vorarlberg",
    "wof:name":"Hollenstein Albert",
    "wof:placetype":"venue"
},
  "geometry": {"coordinates":[9.6646528244,47.4441833496],"type":"Point"}
}