{
  "type": "Feature",
  "properties": {
    "iso:country":"AT",
    "sg:address":"W\u00e4hringer Str 68",
    "sg:city":"Wien",
    "sg:orig_category":"Technischer Zeichenbedarf",
    "sg:phone":"+43 1 3107199",
    "sg:postcode":"1090",
    "sg:province":"Wien",
    "wof:name":"Rotring Fachzentrum Exler-Fiedler",
    "wof:placetype":"venue"
},
  "geometry": {"coordinates":[16.3517532349,48.2234191895],"type":"Point"}
}