{
  "type": "Feature",
  "properties": {
    "addr:full":"St\u00e4ttermayerg 30 Wien Wien 1150",
    "addr:housenumber":"30",
    "addr:postcode":"1150",
    "addr:street":"Staettermayerg",
    "iso:country":"AT",
    "sg:address":"St\u00e4ttermayerg 30",
    "sg:city":"Wien",
    "sg:classifiers":[
        {
            "category":"Professional",
            "subcategory":"Computer Services",
            "type":"Services"
        }
    ],
    "sg:phone":"+43 4312 1555",
    "sg:postcode":"1150",
    "sg:province":"Wien",
    "sg:tags":[
        "software"
    ],
    "sg:website":"hs-soft.com",
    "wof:name":"H & S Heilig u Schubert Software AG",
    "wof:placetype":"venue"
},
  "geometry": {"coordinates":[16.3271064758,48.1986351013],"type":"Point"}
}