{
  "type": "Feature",
  "properties": {
    "addr:full":"Klammg 163 Willendorf am Steinfelde Nieder\u00f6sterreich 2732",
    "addr:housenumber":"163",
    "addr:postcode":"2732",
    "addr:street":"Niederoesterreich",
    "iso:country":"AT",
    "sg:address":"Klammg 163",
    "sg:city":"Willendorf am Steinfelde",
    "sg:orig_category":"Tischlereien",
    "sg:phone":"+43 2620 2480",
    "sg:postcode":"2732",
    "sg:province":"Nieder\u00f6sterreich",
    "wof:name":"Hochegger Friedrich",
    "wof:placetype":"venue"
},
  "geometry": {"coordinates":[16.0511684418,47.7775154114],"type":"Point"}
}