{
  "type": "Feature",
  "properties": {
    "addr:full":"Schulg 1 Inzing Tirol 6401",
    "addr:housenumber":"1",
    "addr:postcode":"6401",
    "addr:street":"Schulg;Tirol",
    "iso:country":"AT",
    "sg:address":"Schulg 1",
    "sg:city":"Inzing",
    "sg:orig_category":"Volksschulen",
    "sg:phone":"+43 5238 88939",
    "sg:postcode":"6401",
    "sg:province":"Tirol",
    "wof:name":"Volksschule",
    "wof:placetype":"venue"
},
  "geometry": {"coordinates":[11.2036771774,47.2706336975],"type":"Point"}
}