{
  "type": "Feature",
  "properties": {
    "addr:full":"Mitterg 7 Saalfelden am Steinernen Meer Salzburg 5760",
    "addr:housenumber":"7",
    "addr:postcode":"5760",
    "addr:street":"Mitterg",
    "iso:country":"AT",
    "sg:address":"Mitterg 7",
    "sg:city":"Saalfelden am Steinernen Meer",
    "sg:orig_category":"Optiker",
    "sg:phone":"+43 6582 73110",
    "sg:postcode":"5760",
    "sg:province":"Salzburg",
    "wof:name":"Optik G\u00fcnther",
    "wof:placetype":"venue"
},
  "geometry": {"coordinates":[12.8480529785,47.4268913269],"type":"Point"}
}