{
  "type": "Feature",
  "properties": {
    "addr:full":"Furtm\u00fchlstr 2 Bergheim Salzburg 5101",
    "addr:housenumber":"2",
    "addr:postcode":"5101",
    "addr:street":"Furtmuehlstr;Salzburg",
    "iso:country":"AT",
    "sg:address":"Furtm\u00fchlstr 2",
    "sg:city":"Bergheim",
    "sg:orig_category":"\u00c3\u201erzte / F Allgemeinmedizin",
    "sg:phone":"+43 662 4599300",
    "sg:postcode":"5101",
    "sg:province":"Salzburg",
    "wof:name":"Bliem Ernst Dr",
    "wof:placetype":"venue"
},
  "geometry": {"coordinates":[13.0230998993,47.8411369324],"type":"Point"}
}