{
  "type": "Feature",
  "properties": {
    "addr:full":"Dorfstr 20 M\u00fchldorf Nieder\u00f6sterreich 3622",
    "addr:housenumber":"20",
    "addr:postcode":"3622",
    "addr:street":"Dorfstr;Niederoesterreich",
    "iso:country":"AT",
    "sg:address":"Dorfstr 20",
    "sg:city":"M\u00fchldorf",
    "sg:classifiers":[
        {
            "category":"Home & Garden",
            "subcategory":"Building Materials",
            "type":"Retail Goods"
        }
    ],
    "sg:phone":"+43 4327 138444",
    "sg:postcode":"3622",
    "sg:province":"Nieder\u00f6sterreich",
    "sg:tags":[
        "baustoffe",
        "-material",
        "u"
    ],
    "wof:name":"Baustoffe Maierhofer Inh Renate Raidl",
    "wof:placetype":"venue"
},
  "geometry": {"coordinates":[15.3126392365,48.3611946106],"type":"Point"}
}