{
  "type": "Feature",
  "properties": {
    "addr:full":"Reisnerstr 5/3 Wien Wien 1030",
    "addr:housenumber":"5 / 3",
    "addr:postcode":"1030",
    "addr:street":"Reisnerstr",
    "iso:country":"AT",
    "sg:address":"Reisnerstr 5/3",
    "sg:city":"Wien",
    "sg:orig_category":"Zementwerke",
    "sg:phone":"+43 1 71852770",
    "sg:postcode":"1030",
    "sg:province":"Wien",
    "wof:name":"Wietersdorfer & Peggauer Zementwerke GmbH",
    "wof:placetype":"venue"
},
  "geometry": {"coordinates":[16.3825263977,48.2025642395],"type":"Point"}
}