{
  "type": "Feature",
  "properties": {
    "addr:full":"Patergassen 61 Patergassen K\u00e4rnten 9564",
    "addr:housenumber":"61",
    "addr:postcode":"9564",
    "addr:street":"Patergassen;Kaernten",
    "iso:country":"AT",
    "sg:address":"Patergassen 61",
    "sg:city":"Patergassen",
    "sg:classifiers":[
        {
            "category":"Home & Garden",
            "subcategory":"Household Appliances",
            "type":"Retail Goods"
        }
    ],
    "sg:phone":"+43 4275 438",
    "sg:postcode":"9564",
    "sg:province":"K\u00e4rnten",
    "sg:tags":[
        "electric"
    ],
    "wof:name":"Franz Schiestl",
    "wof:placetype":"venue"
},
  "geometry": {"coordinates":[13.8648099899,46.8177032471],"type":"Point"}
}