{
  "type": "Feature",
  "properties": {
    "iso:country":"AT",
    "sg:address":"Nr 67",
    "sg:city":"Wald am Schoberpa\u00df",
    "sg:orig_category":"Bauunternehmen",
    "sg:phone":"+43 3834 308",
    "sg:postcode":"8781",
    "sg:province":"Steiermark",
    "wof:name":"NF BaugesmbH",
    "wof:placetype":"venue"
},
  "geometry": {"coordinates":[14.6748695374,47.44921875],"type":"Point"}
}