{
  "type": "Feature",
  "properties": {
    "addr:full":"Jochberg 6 Hollersbach im Pinzgau Salzburg 5731",
    "addr:housenumber":"6",
    "addr:postcode":"5731",
    "addr:street":"Jochberg;Salzburg",
    "iso:country":"AT",
    "sg:address":"Jochberg 6",
    "sg:city":"Hollersbach im Pinzgau",
    "sg:orig_category":"Appartements / Ferienwohnungen",
    "sg:phone":"+43 4365 628181",
    "sg:postcode":"5731",
    "sg:province":"Salzburg",
    "wof:name":"Bauernhof Lahn - Alois u Brigitte Riedlsberger",
    "wof:placetype":"venue"
},
  "geometry": {"coordinates":[12.4078435898,47.2886810303],"type":"Point"}
}