{
  "type": "Feature",
  "properties": {
    "addr:full":"Kaufmannstr. 25  Innsbruck Tirol 6020",
    "addr:housenumber":"25",
    "addr:postcode":"6020",
    "addr:street":"Kaufmannstr.;Tirol",
    "iso:country":"AT",
    "sg:address":"Kaufmannstr. 25 ",
    "sg:city":"Innsbruck",
    "sg:classifiers":[
        {
            "category":"Shopping",
            "type":"Retail Goods"
        }
    ],
    "sg:phone":"+43 4351 2343241",
    "sg:postcode":"6020",
    "sg:province":"Tirol",
    "sg:tags":[
        "finished",
        "-",
        "metallic"
    ],
    "wof:name":"FRANZ GRADISCHEGG GMBH & CO KG",
    "wof:placetype":"venue"
},
  "geometry": {"coordinates":[11.4151592255,47.2574920654],"type":"Point"}
}