{
  "type": "Feature",
  "properties": {
    "addr:full":"Nr 42 Zell am Ziller Tirol 6280",
    "addr:postcode":"6280",
    "addr:street":"Nr 42;Tirol",
    "iso:country":"AT",
    "sg:address":"Nr 42",
    "sg:city":"Zell am Ziller",
    "sg:orig_category":"Volksschulen",
    "sg:phone":"+43 4352 8231064",
    "sg:postcode":"6280",
    "sg:province":"Tirol",
    "wof:name":"Volksschule",
    "wof:placetype":"venue"
},
  "geometry": {"coordinates":[11.8819503784,47.2331733704],"type":"Point"}
}