{
  "type": "Feature",
  "properties": {
    "iso:country":"AT",
    "sg:address":"Singerstrasse 2",
    "sg:city":"Wien",
    "sg:classifiers":[
        {
            "category":"Shopping",
            "subcategory":"Books",
            "type":"Retail Goods"
        }
    ],
    "sg:phone":"+43 1 51325540",
    "sg:postcode":"1010",
    "sg:province":"Wien",
    "sg:website":"readersdigest.at",
    "wof:name":"Reader's Digest Verlag DAS BESTE Ges.m.b.H.",
    "wof:placetype":"venue"
},
  "geometry": {"coordinates":[16.371925354,48.2077713013],"type":"Point"}
}