{
  "type": "Feature",
  "properties": {
    "addr:full":"Renng 12 Wien Wien 1010",
    "addr:housenumber":"12",
    "addr:postcode":"1010",
    "addr:street":"Renng",
    "iso:country":"AT",
    "sg:address":"Renng 12",
    "sg:city":"Wien",
    "sg:orig_category":"Marketingberatung",
    "sg:phone":"+43 4313 194341",
    "sg:postcode":"1010",
    "sg:province":"Wien",
    "wof:name":"M+MM Marketing u Medien Management - Dr Wolfgang Brandstetter",
    "wof:placetype":"venue"
},
  "geometry": {"coordinates":[16.3674583435,48.2127532959],"type":"Point"}
}