{
  "type": "Feature",
  "properties": {
    "iso:country":"AT",
    "sg:address":"Gudrunstr 167",
    "sg:city":"Wien",
    "sg:orig_category":"Tanzsport",
    "sg:phone":"+43 1 6062788",
    "sg:postcode":"1100",
    "sg:province":"Wien",
    "sg:website":"dance-design.at",
    "wof:name":"Dance & Design",
    "wof:placetype":"venue"
},
  "geometry": {"coordinates":[16.3679218292,48.178565979],"type":"Point"}
}