{
  "type": "Feature",
  "properties": {
    "addr:full":"Gernlandweg 49 Leonding Ober\u00f6sterreich 4060",
    "addr:housenumber":"49",
    "addr:postcode":"4060",
    "addr:street":"Gernlandweg",
    "iso:country":"AT",
    "sg:address":"Gernlandweg 49",
    "sg:city":"Leonding",
    "sg:orig_category":"Werbegrafik- U Grafik-Design",
    "sg:phone":"+43 4373 2670221",
    "sg:postcode":"4060",
    "sg:province":"Ober\u00f6sterreich",
    "wof:name":"mind & media Harald Obermayr Werbegrafik, Design und Druckproduktion",
    "wof:placetype":"venue"
},
  "geometry": {"coordinates":[14.2545976639,48.2782859802],"type":"Point"}
}