{
  "type": "Feature",
  "properties": {
    "iso:country":"AT",
    "sg:address":"Schaidaweg 2",
    "sg:city":"Ferlach",
    "sg:orig_category":"Holzgro\u00c3\u0178handel",
    "sg:phone":"+43 4227 2260",
    "sg:postcode":"9170",
    "sg:province":"K\u00e4rnten",
    "wof:name":"Jaritz S Holzindustrie GesmbH & Co KG",
    "wof:placetype":"venue"
},
  "geometry": {"coordinates":[14.3020458221,46.522026062],"type":"Point"}
}