{
  "type": "Feature",
  "properties": {
    "addr:full":"Maisberg 91 Ybbsitz Nieder\u00f6sterreich 3341",
    "addr:housenumber":"91",
    "addr:postcode":"3341",
    "addr:street":"Maisberg",
    "iso:country":"AT",
    "sg:address":"Maisberg 91",
    "sg:city":"Ybbsitz",
    "sg:classifiers":[
        {
            "category":"Manufacturing",
            "subcategory":"Rubber & Plastics",
            "type":"Manufacturing & Wholesale Goods"
        }
    ],
    "sg:phone":"+43 4374 43884240",
    "sg:postcode":"3341",
    "sg:province":"Nieder\u00f6sterreich",
    "wof:name":"JOH. FUCHS & SOHN GMBH",
    "wof:placetype":"venue"
},
  "geometry": {"coordinates":[14.8291940689,47.9430580139],"type":"Point"}
}