{
  "type": "Feature",
  "properties": {
    "addr:full":"Rudolf-Wilfingseder-Str 18 Ried im Innkreis Ober\u00f6sterreich 4910",
    "addr:housenumber":"18",
    "addr:postcode":"4910",
    "addr:street":"Rudolf-Wilfingseder-Str",
    "iso:country":"AT",
    "sg:address":"Rudolf-Wilfingseder-Str 18",
    "sg:city":"Ried im Innkreis",
    "sg:orig_category":"Rauchfangkehrer",
    "sg:phone":"+43 4367 66188713",
    "sg:postcode":"4910",
    "sg:province":"Ober\u00f6sterreich",
    "wof:name":"Schulz Manfred",
    "wof:placetype":"venue"
},
  "geometry": {"coordinates":[13.4918117523,48.2139511108],"type":"Point"}
}