{
  "type": "Feature",
  "properties": {
    "addr:full":"Edelseestr 46 Birkfeld Steiermark 8190",
    "addr:housenumber":"46",
    "addr:postcode":"8190",
    "addr:street":"Edelseestr",
    "iso:country":"AT",
    "sg:address":"Edelseestr 46",
    "sg:city":"Birkfeld",
    "sg:orig_category":"Friseure U Frisiersalons",
    "sg:phone":"+43 4331 744597",
    "sg:postcode":"8190",
    "sg:province":"Steiermark",
    "wof:name":"Luger Susanne",
    "wof:placetype":"venue"
},
  "geometry": {"coordinates":[15.7004671097,47.3539505005],"type":"Point"}
}