{
  "type": "Feature",
  "properties": {
    "addr:full":"Sebastianstr 37 Oggau Burgenland 7063",
    "addr:housenumber":"37",
    "addr:postcode":"7063",
    "addr:street":"Sebastianstr",
    "iso:country":"AT",
    "sg:address":"Sebastianstr 37",
    "sg:city":"Oggau",
    "sg:orig_category":"Bankomat-Standorte",
    "sg:phone":"+43 2685 7241",
    "sg:postcode":"7063",
    "sg:province":"Burgenland",
    "wof:name":"Bankomat d Raiffeisenkasse Oggau regGenmbH",
    "wof:placetype":"venue"
},
  "geometry": {"coordinates":[16.6664543152,47.8346443176],"type":"Point"}
}