{
  "type": "Feature",
  "properties": {
    "addr:full":"Wiener Str 30 M\u00fcrzzuschlag Steiermark 8680",
    "addr:postcode":"8680",
    "addr:street":"30",
    "iso:country":"AT",
    "sg:address":"Wiener Str 30",
    "sg:city":"M\u00fcrzzuschlag",
    "sg:orig_category":"Biologische Produkte",
    "sg:phone":"+43 4338 522169",
    "sg:postcode":"8680",
    "sg:province":"Steiermark",
    "wof:name":"Quelle Shop und Bioladen Inh Kempf Nicole",
    "wof:placetype":"venue"
},
  "geometry": {"coordinates":[16.3542709351,48.159198761],"type":"Point"}
}