{
  "type": "Feature",
  "properties": {
    "addr:full":"Schl\u00fchslmayrstr 81 Steyr Ober\u00f6sterreich 4400",
    "addr:housenumber":"81",
    "addr:postcode":"4400",
    "addr:street":"Schluehslmayrstr;Oberoesterreich",
    "iso:country":"AT",
    "sg:address":"Schl\u00fchslmayrstr 81",
    "sg:city":"Steyr",
    "sg:classifiers":[
        {
            "category":"Restaurant",
            "type":"Food & Drink"
        }
    ],
    "sg:phone":"+43 7252 52686",
    "sg:postcode":"4400",
    "sg:province":"Ober\u00f6sterreich",
    "sg:tags":[
        "pizzeria"
    ],
    "wof:name":"Pizzeria Diele am Berg",
    "wof:placetype":"venue"
},
  "geometry": {"coordinates":[14.4193296432,48.0391807556],"type":"Point"}
}