{
  "type": "Feature",
  "properties": {
    "addr:full":"Vorgartenstr 107 Wien Wien 1200",
    "addr:housenumber":"107",
    "addr:postcode":"1200",
    "iso:country":"AT",
    "sg:address":"Vorgartenstr 107",
    "sg:city":"Wien",
    "sg:orig_category":"Lebensmittel / Einzelhandel",
    "sg:phone":"+43 1 9612071",
    "sg:postcode":"1200",
    "sg:province":"Wien",
    "wof:name":"Billa AG",
    "wof:placetype":"venue"
},
  "geometry": {"coordinates":[16.3910541534,48.2333526611],"type":"Point"}
}