{
  "type": "Feature",
  "properties": {
    "iso:country":"AT",
    "sg:address":"Stahlstr 1",
    "sg:city":"Weiz",
    "sg:orig_category":"Bauunternehmen",
    "sg:phone":"+43 3172 2925290",
    "sg:postcode":"8160",
    "sg:province":"Steiermark",
    "wof:name":"Land-Haus-Bau GesmbH",
    "wof:placetype":"venue"
},
  "geometry": {"coordinates":[15.6485481262,47.197769165],"type":"Point"}
}