{
  "type": "Feature",
  "properties": {
    "addr:full":"Bachg 3a Horitschon Burgenland 7312",
    "addr:housenumber":"3a",
    "addr:postcode":"7312",
    "addr:street":"Bachg",
    "iso:country":"AT",
    "sg:address":"Bachg 3a",
    "sg:city":"Horitschon",
    "sg:orig_category":"Hauptschulen",
    "sg:phone":"+43 2610 42200",
    "sg:postcode":"7312",
    "sg:province":"Burgenland",
    "wof:name":"Hauptschule",
    "wof:placetype":"venue"
},
  "geometry": {"coordinates":[16.546628952,47.58751297],"type":"Point"}
}