{
  "type": "Feature",
  "properties": {
    "addr:full":"Einsiedlerpl 4/2A Wien Wien 1050",
    "addr:housenumber":"4 / 2a",
    "addr:postcode":"1050",
    "addr:street":"Einsiedlerpl",
    "iso:country":"AT",
    "sg:address":"Einsiedlerpl 4/2A",
    "sg:city":"Wien",
    "sg:orig_category":"Raumausstattung",
    "sg:phone":"+43 4315 483200",
    "sg:postcode":"1050",
    "sg:province":"Wien",
    "wof:name":"Aucon Kunstwerk GesmbH",
    "wof:placetype":"venue"
},
  "geometry": {"coordinates":[16.3501682281,48.1865005493],"type":"Point"}
}