{
  "type": "Feature",
  "properties": {
    "addr:full":"Oberer Stadtpl 28 Waidhofen an der Ybbs Nieder\u00f6sterreich 3340",
    "addr:housenumber":"28",
    "addr:postcode":"3340",
    "addr:street":"Oberer Stadtpl",
    "iso:country":"AT",
    "sg:address":"Oberer Stadtpl 28",
    "sg:city":"Waidhofen an der Ybbs",
    "sg:classifiers":[
        {
            "category":"Professional",
            "subcategory":"Testing Lab",
            "type":"Services"
        }
    ],
    "sg:phone":"+43 4374 425110",
    "sg:postcode":"3340",
    "sg:province":"Nieder\u00f6sterreich",
    "sg:tags":[
        "magistrate"
    ],
    "wof:name":"Magistrat d Stadt Waidhofen a d Ybbs",
    "wof:placetype":"venue"
},
  "geometry": {"coordinates":[14.7744646072,47.9612197876],"type":"Point"}
}