{
  "type": "Feature",
  "properties": {
    "addr:full":"Haitzenthal 18 Frankenmarkt Ober\u00f6sterreich 4890",
    "addr:housenumber":"18",
    "addr:postcode":"4890",
    "addr:street":"Haitzenthal;Oberoesterreich",
    "iso:country":"AT",
    "sg:address":"Haitzenthal 18",
    "sg:city":"Frankenmarkt",
    "sg:orig_category":"Non-Classified Establishments",
    "sg:phone":"+43 664 4025001",
    "sg:postcode":"4890",
    "sg:province":"Ober\u00f6sterreich",
    "wof:name":"Kostic Andreas",
    "wof:placetype":"venue"
},
  "geometry": {"coordinates":[13.4322376251,47.9801101685],"type":"Point"}
}