{
  "type": "Feature",
  "properties": {
    "addr:full":"Am Bergl 38 Kramsach Tirol 6233",
    "addr:housenumber":"38",
    "addr:postcode":"6233",
    "addr:street":"Am Bergl;Tirol",
    "iso:country":"AT",
    "sg:address":"Am Bergl 38",
    "sg:city":"Kramsach",
    "sg:orig_category":"Pensionen / Privatzimmer",
    "sg:phone":"+43 5337 62823",
    "sg:postcode":"6233",
    "sg:province":"Tirol",
    "wof:name":"Rupprechter Margarete - Haus Silvia",
    "wof:placetype":"venue"
},
  "geometry": {"coordinates":[11.874792099,47.4437065125],"type":"Point"}
}