{
  "type": "Feature",
  "properties": {
    "iso:country":"AT",
    "sg:address":"Hauptstr 29",
    "sg:city":"Stockerau",
    "sg:orig_category":"Esoterik",
    "sg:phone":"+43 2266 65475",
    "sg:postcode":"2000",
    "sg:province":"Nieder\u00f6sterreich",
    "wof:name":"Schatzkisterl",
    "wof:placetype":"venue"
},
  "geometry": {"coordinates":[16.2118721008,48.38539505],"type":"Point"}
}