{
  "type": "Feature",
  "properties": {
    "iso:country":"AT",
    "sg:address":"Finkenweg 4c",
    "sg:city":"St. Veit an der Glan",
    "sg:orig_category":"Brunnen U Brunnenbau",
    "sg:phone":"+43 4366 44106977",
    "sg:postcode":"9300",
    "sg:province":"K\u00e4rnten",
    "wof:name":"S & K Brunnenbohr GesmbH",
    "wof:placetype":"venue"
},
  "geometry": {"coordinates":[14.3820867538,46.7539787292],"type":"Point"}
}