{
  "type": "Feature",
  "properties": {
    "addr:full":"Sternwartestrasse 69 Wien Wien 1180",
    "addr:housenumber":"69",
    "addr:postcode":"1180",
    "addr:street":"Sternwartestrasse",
    "iso:country":"AT",
    "sg:address":"Sternwartestrasse 69",
    "sg:city":"Wien",
    "sg:classifiers":[
        {
            "category":"Professional",
            "subcategory":"Advertising",
            "type":"Services"
        }
    ],
    "sg:phone":"+43 1 4789294",
    "sg:postcode":"1180",
    "sg:province":"Wien",
    "sg:tags":[
        "agency"
    ],
    "wof:name":"Studio Weber Werbeges.m.b.H.",
    "wof:placetype":"venue"
},
  "geometry": {"coordinates":[16.3373622894,48.2318534851],"type":"Point"}
}