{
  "type": "Feature",
  "properties": {
    "iso:country":"AT",
    "sg:address":"Marktstr 5",
    "sg:city":"St. Anna am Aigen",
    "sg:orig_category":"Gemeinden",
    "sg:phone":"+43 4331 5822120",
    "sg:postcode":"8354",
    "sg:province":"Steiermark",
    "wof:name":"Marktgemeinde St Anna am Aigen",
    "wof:placetype":"venue"
},
  "geometry": {"coordinates":[15.9744796753,46.833404541],"type":"Point"}
}