{
  "type": "Feature",
  "properties": {
    "addr:full":"Tegetthoffpl 3/3 Graz Steiermark 8010",
    "addr:housenumber":"3 / 3",
    "addr:postcode":"8010",
    "addr:street":"Tegetthoffpl",
    "iso:country":"AT",
    "sg:address":"Tegetthoffpl 3/3",
    "sg:city":"Graz",
    "sg:orig_category":"Ingenieurkonsulenten / Zivilingenieure",
    "sg:phone":"+43 316 38248810",
    "sg:postcode":"8010",
    "sg:province":"Steiermark",
    "wof:name":"P\u00f6tscher Reinhard Dipl-Ing",
    "wof:placetype":"venue"
},
  "geometry": {"coordinates":[15.4583101273,47.0763053894],"type":"Point"}
}