{
  "type": "Feature",
  "properties": {
    "iso:country":"AT",
    "sg:address":"Birkfelder Str 10",
    "sg:city":"Weiz",
    "sg:orig_category":"Boutiquen",
    "sg:phone":"+43 3172 41471",
    "sg:postcode":"8160",
    "sg:province":"Steiermark",
    "wof:name":"Moda fiori",
    "wof:placetype":"venue"
},
  "geometry": {"coordinates":[15.6276073456,47.2171821594],"type":"Point"}
}