{
  "type": "Feature",
  "properties": {
    "iso:country":"AT",
    "sg:address":"Burggasse 4",
    "sg:city":"Graz",
    "sg:classifiers":[
        {
            "category":"Wholesale",
            "subcategory":"Beer",
            "type":"Manufacturing & Wholesale Goods"
        }
    ],
    "sg:phone":"+43 316 821950",
    "sg:postcode":"8010",
    "sg:province":"Steiermark",
    "wof:name":"DOM-BR\u00c4U Ges.m.b.H. & CO KG",
    "wof:placetype":"venue"
},
  "geometry": {"coordinates":[15.4434490204,47.071182251],"type":"Point"}
}