{
  "type": "Feature",
  "properties": {
    "addr:full":"Poschacherstr 5 Mauthausen Ober\u00f6sterreich 4310",
    "addr:housenumber":"5",
    "addr:postcode":"4310",
    "addr:street":"Poschacherstr",
    "iso:country":"AT",
    "sg:address":"Poschacherstr 5",
    "sg:city":"Mauthausen",
    "sg:orig_category":"Bekleidung / Einzelhandel",
    "sg:phone":"+43 7238 5828",
    "sg:postcode":"4310",
    "sg:province":"Ober\u00f6sterreich",
    "wof:name":"adessa Moden GmbH",
    "wof:placetype":"venue"
},
  "geometry": {"coordinates":[14.5266342163,48.2399368286],"type":"Point"}
}