{
  "type": "Feature",
  "properties": {
    "addr:full":"Arzberg 41 Reichraming Ober\u00f6sterreich 4462",
    "addr:housenumber":"41",
    "addr:postcode":"4462",
    "addr:street":"Arzberg",
    "iso:country":"AT",
    "sg:address":"Arzberg 41",
    "sg:city":"Reichraming",
    "sg:orig_category":"Erdarbeiten",
    "sg:phone":"+43 7254 84240",
    "sg:postcode":"4462",
    "sg:province":"Ober\u00f6sterreich",
    "wof:name":"St\u00f6ger Josef",
    "wof:placetype":"venue"
},
  "geometry": {"coordinates":[14.4778909683,47.8970909119],"type":"Point"}
}