{
  "type": "Feature",
  "properties": {
    "addr:full":"Reithoferweg 196 Wals Salzburg 5071",
    "addr:housenumber":"196",
    "addr:postcode":"5071",
    "addr:street":"Wals Salzburg",
    "iso:country":"AT",
    "sg:address":"Reithoferweg 196",
    "sg:city":"Wals",
    "sg:orig_category":"Steinmetzbetriebe",
    "sg:phone":"+43 4366 2851042",
    "sg:postcode":"5071",
    "sg:province":"Salzburg",
    "wof:name":"Keil Rudolf",
    "wof:placetype":"venue"
},
  "geometry": {"coordinates":[12.9680995941,47.7894973755],"type":"Point"}
}