{
  "type": "Feature",
  "properties": {
    "addr:full":"Salzburger Str 44 Schwanenstadt Ober\u00f6sterreich 4690",
    "addr:housenumber":"44",
    "addr:postcode":"4690",
    "addr:street":"Salzburger Str",
    "iso:country":"AT",
    "sg:address":"Salzburger Str 44",
    "sg:city":"Schwanenstadt",
    "sg:orig_category":"Beschriftungen",
    "sg:phone":"+43 4376 737344",
    "sg:postcode":"4690",
    "sg:province":"Ober\u00f6sterreich",
    "wof:name":"Partners Heidinger GesmbH",
    "wof:placetype":"venue"
},
  "geometry": {"coordinates":[13.7615003586,48.0476951599],"type":"Point"}
}