{
  "type": "Feature",
  "properties": {
    "addr:full":"Gewerbestr 5 G\u00fcnselsdorf Nieder\u00f6sterreich 2525",
    "addr:housenumber":"5",
    "addr:postcode":"2525",
    "addr:street":"Gewerbestr;Niederoesterreich",
    "iso:country":"AT",
    "sg:address":"Gewerbestr 5",
    "sg:city":"G\u00fcnselsdorf",
    "sg:orig_category":"Gabelstapler",
    "sg:phone":"+43 4322 5620248",
    "sg:postcode":"2525",
    "sg:province":"Nieder\u00f6sterreich",
    "wof:name":"Schwarzer Gabelstapler Handel u Service GmbH",
    "wof:placetype":"venue"
},
  "geometry": {"coordinates":[16.2488250732,47.9430007935],"type":"Point"}
}