{
  "type": "Feature",
  "properties": {
    "addr:full":"Nr 40 Mondsee Ober\u00f6sterreich 5310",
    "addr:postcode":"5310",
    "addr:street":"Nr;Oberoesterreich",
    "iso:country":"AT",
    "sg:address":"Nr 40",
    "sg:city":"Mondsee",
    "sg:orig_category":"Appartements / Ferienwohnungen",
    "sg:phone":"+43 4362 327383",
    "sg:postcode":"5310",
    "sg:province":"Ober\u00f6sterreich",
    "wof:name":"Edtmoar",
    "wof:placetype":"venue"
},
  "geometry": {"coordinates":[13.349562645,47.855255127],"type":"Point"}
}