{
  "type": "Feature",
  "properties": {
    "iso:country":"AT",
    "sg:address":"Oskar-Helmer-Str 15",
    "sg:city":"Stockerau",
    "sg:orig_category":"Werbegrafik- U Grafik-Design",
    "sg:phone":"+43 4322 6661664",
    "sg:postcode":"2000",
    "sg:province":"Nieder\u00f6sterreich",
    "wof:name":"Embacher Josef Ing",
    "wof:placetype":"venue"
},
  "geometry": {"coordinates":[16.2254314423,48.3934135437],"type":"Point"}
}