{
  "type": "Feature",
  "properties": {
    "iso:country":"AT",
    "sg:address":"Markt 50",
    "sg:city":"M\u00fchldorf",
    "sg:orig_category":"Maler, Anstreicher U Lackierer",
    "sg:phone":"+43 2713 8258",
    "sg:postcode":"3622",
    "sg:province":"Nieder\u00f6sterreich",
    "wof:name":"Fuchs Josef",
    "wof:placetype":"venue"
},
  "geometry": {"coordinates":[15.6017103195,48.0229492188],"type":"Point"}
}