{
  "type": "Feature",
  "properties": {
    "addr:full":"Fischamender Str 12 Bruck an der Leitha Nieder\u00f6sterreich 2460",
    "addr:postcode":"2460",
    "addr:street":"Str 12",
    "iso:country":"AT",
    "sg:address":"Fischamender Str 12",
    "sg:city":"Bruck an der Leitha",
    "sg:orig_category":"Beratungsstellen",
    "sg:phone":"+43 2162 683930",
    "sg:postcode":"2460",
    "sg:province":"Nieder\u00f6sterreich",
    "wof:name":"Agrar Beratung-Service Tatzber & Trapl & Wimmer OEG",
    "wof:placetype":"venue"
},
  "geometry": {"coordinates":[16.7781772614,48.0290031433],"type":"Point"}
}