{
  "type": "Feature",
  "properties": {
    "addr:full":"Gartenstr 1-5 Dietmanns Nieder\u00f6sterreich 3813",
    "addr:housenumber":"1-5",
    "addr:postcode":"3813",
    "addr:street":"Gartenstr;Niederoesterreich",
    "iso:country":"AT",
    "sg:address":"Gartenstr 1-5",
    "sg:city":"Dietmanns",
    "sg:orig_category":"Webereien U Spinnereien",
    "sg:phone":"+43 4328 4723850",
    "sg:postcode":"3813",
    "sg:province":"Nieder\u00f6sterreich",
    "wof:name":"Zeindl GmbH Bandweberei u F\u00e4rberei",
    "wof:placetype":"venue"
},
  "geometry": {"coordinates":[15.3903989792,48.7909698486],"type":"Point"}
}