{
  "type": "Feature",
  "properties": {
    "addr:full":"Hauptstr 3 Obdach Steiermark 8742",
    "addr:housenumber":"3",
    "addr:postcode":"8742",
    "addr:street":"Hauptstr",
    "iso:country":"AT",
    "sg:address":"Hauptstr 3",
    "sg:city":"Obdach",
    "sg:classifiers":[
        {
            "category":"Restaurant",
            "type":"Food & Drink"
        }
    ],
    "sg:phone":"+43 3578 2857",
    "sg:postcode":"8742",
    "sg:province":"Steiermark",
    "wof:name":"Arge f Restaurierung und Konservierung",
    "wof:placetype":"venue"
},
  "geometry": {"coordinates":[14.6933050156,47.0735206604],"type":"Point"}
}