{
  "type": "Feature",
  "properties": {
    "iso:country":"AT",
    "sg:address":"Rathaus",
    "sg:city":"M\u00fcllendorf",
    "sg:orig_category":"\u00c3\u201erzte / F Allgemeinmedizin",
    "sg:phone":"+43 2682 625500",
    "sg:postcode":"7052",
    "sg:province":"Burgenland",
    "wof:name":"Jandrisovits Reinhold Dr",
    "wof:placetype":"venue"
},
  "geometry": {"coordinates":[147.3165588379,-43.0075187683],"type":"Point"}
}