{
  "type": "Feature",
  "properties": {
    "addr:full":"Trift 2 Sieggraben Burgenland 7223",
    "addr:housenumber":"2",
    "addr:postcode":"sieggraben;7223",
    "addr:street":"Trift",
    "iso:country":"AT",
    "sg:address":"Trift 2",
    "sg:city":"Sieggraben",
    "sg:orig_category":"Holzgro\u00c3\u0178handel",
    "sg:phone":"+43 4326 2126303",
    "sg:postcode":"7223",
    "sg:province":"Burgenland",
    "wof:name":"F\u00fcrsatz KEG",
    "wof:placetype":"venue"
},
  "geometry": {"coordinates":[16.3795700073,47.6481323242],"type":"Point"}
}