{
  "type": "Feature",
  "properties": {
    "addr:full":"Lindach 2 Allhaming Ober\u00f6sterreich 4511",
    "addr:housenumber":"2",
    "addr:postcode":"4511",
    "addr:street":"Lindach",
    "iso:country":"AT",
    "sg:address":"Lindach 2",
    "sg:city":"Allhaming",
    "sg:orig_category":"Schmieden U Schmiedeeisenelemente",
    "sg:phone":"+43 4372 277149",
    "sg:postcode":"4511",
    "sg:province":"Ober\u00f6sterreich",
    "wof:name":"Fischer Alois",
    "wof:placetype":"venue"
},
  "geometry": {"coordinates":[14.183131218,48.1577796936],"type":"Point"}
}