{
  "type": "Feature",
  "properties": {
    "iso:country":"AT",
    "sg:address":"Seenstr 11",
    "sg:city":"Reifnitz",
    "sg:orig_category":"Baumeister",
    "sg:phone":"+43 4273 22160",
    "sg:postcode":"9081",
    "sg:province":"K\u00e4rnten",
    "wof:name":"Sztriberny BaugesmbH & Co KG",
    "wof:placetype":"venue"
},
  "geometry": {"coordinates":[14.1812505722,46.6054878235],"type":"Point"}
}