{
  "type": "Feature",
  "properties": {
    "addr:full":"Lotte-Lehmann-Promenade 4 Aigen Salzburg 5026",
    "addr:housenumber":"4",
    "addr:postcode":"5026",
    "addr:street":"Lotte-Lehmann-Promenade;Salzburg",
    "iso:country":"AT",
    "sg:address":"Lotte-Lehmann-Promenade 4",
    "sg:city":"Aigen",
    "sg:orig_category":"Lebens- U Sozialberatung",
    "sg:phone":"+43 4366 2640746",
    "sg:postcode":"5026",
    "sg:province":"Salzburg",
    "wof:name":"Verein Panama - Lebensberatungszentrum",
    "wof:placetype":"venue"
},
  "geometry": {"coordinates":[13.0899562836,47.7863197327],"type":"Point"}
}