{
  "type": "Feature",
  "properties": {
    "addr:full":"Eduard-Huebmer-G 522 Pitten Nieder\u00f6sterreich 2823",
    "addr:housenumber":"522",
    "addr:postcode":"2823",
    "iso:country":"AT",
    "sg:address":"Eduard-Huebmer-G 522",
    "sg:city":"Pitten",
    "sg:orig_category":"Transportunternehmen",
    "sg:phone":"+43 2627 82279",
    "sg:postcode":"2823",
    "sg:province":"Nieder\u00f6sterreich",
    "wof:name":"Geyer Johann",
    "wof:placetype":"venue"
},
  "geometry": {"coordinates":[16.18658638,47.7162742615],"type":"Point"}
}