{
  "type": "Feature",
  "properties": {
    "addr:full":"Manker Str 18 Bischofstetten Nieder\u00f6sterreich 3232",
    "addr:postcode":"3232",
    "addr:street":"Str;Niederoesterreich",
    "iso:country":"AT",
    "sg:address":"Manker Str 18",
    "sg:city":"Bischofstetten",
    "sg:orig_category":"Zelte / Vermietung",
    "sg:phone":"+43 2748 83830",
    "sg:postcode":"3232",
    "sg:province":"Nieder\u00f6sterreich",
    "wof:name":"Happy Promotion Kusdat & Stadlbauer GesmbH",
    "wof:placetype":"venue"
},
  "geometry": {"coordinates":[15.4658403397,48.1215286255],"type":"Point"}
}