{
  "type": "Feature",
  "properties": {
    "addr:full":"Hauptstr 19 Blindenmarkt Nieder\u00f6sterreich 3372",
    "addr:housenumber":"19",
    "addr:postcode":"3372",
    "addr:street":"Hauptstr",
    "iso:country":"AT",
    "sg:address":"Hauptstr 19",
    "sg:city":"Blindenmarkt",
    "sg:orig_category":"Tabaktrafiken",
    "sg:phone":"+43 7473 2289",
    "sg:postcode":"3372",
    "sg:province":"Nieder\u00f6sterreich",
    "wof:name":"Weginger Heidemarie",
    "wof:placetype":"venue"
},
  "geometry": {"coordinates":[14.9896306992,48.1285247803],"type":"Point"}
}