{
  "type": "Feature",
  "properties": {
    "addr:full":"Seecorso 40 Velden am W\u00f6rther See K\u00e4rnten 9220",
    "addr:housenumber":"40",
    "addr:postcode":"9220",
    "addr:street":"Seecorso;Kaernten",
    "iso:country":"AT",
    "sg:address":"Seecorso 40",
    "sg:city":"Velden am W\u00f6rther See",
    "sg:classifiers":[
        {
            "category":"Travel",
            "subcategory":"Hotels & Motels",
            "type":"Entertainment"
        }
    ],
    "sg:phone":"+43 4342 7426910",
    "sg:postcode":"9220",
    "sg:province":"K\u00e4rnten",
    "wof:name":"Sporthotel Berger",
    "wof:placetype":"venue"
},
  "geometry": {"coordinates":[14.0464696884,46.6097297668],"type":"Point"}
}