{
  "type": "Feature",
  "properties": {
    "iso:country":"AT",
    "sg:address":"Neder 322",
    "sg:city":"Gries am Brenner",
    "sg:orig_category":"Bergbahnen",
    "sg:phone":"+43 4352 7487270",
    "sg:postcode":"6156",
    "sg:province":"Tirol",
    "wof:name":"Grieser Bergbahnen GesmbH",
    "wof:placetype":"venue"
},
  "geometry": {"coordinates":[11.4745445251,47.033531189],"type":"Point"}
}