{
  "type": "Feature",
  "properties": {
    "iso:country":"AT",
    "sg:address":"Mariahilfbergl 17",
    "sg:city":"Brixlegg",
    "sg:orig_category":"Tischlereien",
    "sg:phone":"+43 5337 63024",
    "sg:postcode":"6230",
    "sg:province":"Tirol",
    "wof:name":"Knapp Reto",
    "wof:placetype":"venue"
},
  "geometry": {"coordinates":[11.8818359375,47.432346344],"type":"Point"}
}