{
  "type": "Feature",
  "properties": {
    "addr:full":"Dornacher Str 37 Linz Ober\u00f6sterreich 4040",
    "addr:postcode":"4040",
    "addr:street":"Str 37",
    "iso:country":"AT",
    "sg:address":"Dornacher Str 37",
    "sg:city":"Linz",
    "sg:classifiers":[
        {
            "category":"Restaurant",
            "type":"Food & Drink"
        }
    ],
    "sg:phone":"+43 732 253312",
    "sg:postcode":"4040",
    "sg:province":"Ober\u00f6sterreich",
    "wof:name":"Restaurant Moby Dick",
    "wof:placetype":"venue"
},
  "geometry": {"coordinates":[14.3021841049,48.3337936401],"type":"Point"}
}