{
  "type": "Feature",
  "properties": {
    "addr:full":"Linzer Str 35 Braunau am Inn Ober\u00f6sterreich 5280",
    "addr:housenumber":"35",
    "addr:postcode":"5280",
    "addr:street":"Linzer Str",
    "iso:country":"AT",
    "sg:address":"Linzer Str 35",
    "sg:city":"Braunau am Inn",
    "sg:orig_category":"Pensionen / Privatzimmer",
    "sg:phone":"+43 4377 22633960",
    "sg:postcode":"5280",
    "sg:province":"Ober\u00f6sterreich",
    "wof:name":"Hannak Heinz u Margarethe - KOMFORTZIMMER",
    "wof:placetype":"venue"
},
  "geometry": {"coordinates":[13.0377016068,48.259563446],"type":"Point"}
}