{
  "type": "Feature",
  "properties": {
    "addr:full":"Bundesstr 41 Weitra Nieder\u00f6sterreich 3970",
    "addr:housenumber":"41",
    "addr:postcode":"3970",
    "addr:street":"Bundesstr",
    "iso:country":"AT",
    "sg:address":"Bundesstr 41",
    "sg:city":"Weitra",
    "sg:orig_category":"Lebensmittel / Einzelhandel",
    "sg:phone":"+43 2856 3312",
    "sg:postcode":"3970",
    "sg:province":"Nieder\u00f6sterreich",
    "wof:name":"Zielpunkt Warenhandel GmbH & Co KG",
    "wof:placetype":"venue"
},
  "geometry": {"coordinates":[14.8928060532,48.7005844116],"type":"Point"}
}