{
  "type": "Feature",
  "properties": {
    "addr:full":"Wildentalstr 4 Mittelberg Vorarlberg 6993",
    "addr:housenumber":"4",
    "addr:postcode":"6993",
    "addr:street":"Wildentalstr",
    "iso:country":"AT",
    "sg:address":"Wildentalstr 4",
    "sg:city":"Mittelberg",
    "sg:orig_category":"Pensionen / Privatzimmer",
    "sg:phone":"+43 4355 176586",
    "sg:postcode":"6993",
    "sg:province":"Vorarlberg",
    "wof:name":"Landhaus Almrausch",
    "wof:placetype":"venue"
},
  "geometry": {"coordinates":[10.1513948441,47.3178863525],"type":"Point"}
}