{
  "type": "Feature",
  "properties": {
    "addr:full":"Hauptstr 21 Ernsthofen Nieder\u00f6sterreich 4432",
    "addr:housenumber":"21",
    "addr:postcode":"4432",
    "addr:street":"Hauptstr",
    "iso:country":"AT",
    "sg:address":"Hauptstr 21",
    "sg:city":"Ernsthofen",
    "sg:orig_category":"Gemeinden",
    "sg:phone":"+43 7435 84500",
    "sg:postcode":"4432",
    "sg:province":"Nieder\u00f6sterreich",
    "wof:name":"Gemeindeamt Ernsthofen",
    "wof:placetype":"venue"
},
  "geometry": {"coordinates":[14.4826898575,48.1266059875],"type":"Point"}
}