{
  "type": "Feature",
  "properties": {
    "iso:country":"AT",
    "sg:address":"Rennhammerg 1",
    "sg:city":"Schwaz",
    "sg:orig_category":"Papier / Erzeugung U Gro\u00c3\u0178handel",
    "sg:phone":"+43 5242 65901",
    "sg:postcode":"6130",
    "sg:province":"Tirol",
    "wof:name":"Seier Walter KEG",
    "wof:placetype":"venue"
},
  "geometry": {"coordinates":[11.7111692429,47.3479995728],"type":"Point"}
}