{
  "type": "Feature",
  "properties": {
    "addr:full":"Hernalser Hauptstr 101-105 Wien Wien 1170",
    "addr:postcode":"101-105;1170",
    "addr:street":"Hernalser Hauptstr",
    "iso:country":"AT",
    "sg:address":"Hernalser Hauptstr 101-105",
    "sg:city":"Wien",
    "sg:orig_category":"Bettwaren",
    "sg:phone":"+43 4314 861328",
    "sg:postcode":"1170",
    "sg:province":"Wien",
    "wof:name":"Betten D\u00f6rr",
    "wof:placetype":"venue"
},
  "geometry": {"coordinates":[16.3258724213,48.2193984985],"type":"Point"}
}