{
  "type": "Feature",
  "properties": {
    "addr:full":"Grazer Str 37 Gratkorn Steiermark 8101",
    "addr:postcode":"8101",
    "addr:street":"Str 37",
    "iso:country":"AT",
    "sg:address":"Grazer Str 37",
    "sg:city":"Gratkorn",
    "sg:orig_category":"Non-Classified Establishments",
    "sg:phone":"+43 3124 22333",
    "sg:postcode":"8101",
    "sg:province":"Steiermark",
    "wof:name":"Gendarmerieposten",
    "wof:placetype":"venue"
},
  "geometry": {"coordinates":[15.343832016,47.1294784546],"type":"Point"}
}