{
  "type": "Feature",
  "properties": {
    "addr:full":"Unterer Stadtpl 19 Kufstein Tirol 6330",
    "addr:housenumber":"19",
    "addr:postcode":"6330",
    "addr:street":"Unterer Stadtpl;Tirol",
    "iso:country":"AT",
    "sg:address":"Unterer Stadtpl 19",
    "sg:city":"Kufstein",
    "sg:orig_category":"Bars-Cafes",
    "sg:phone":"+43 5372 71704",
    "sg:postcode":"6330",
    "sg:province":"Tirol",
    "wof:name":"Ground Zero",
    "wof:placetype":"venue"
},
  "geometry": {"coordinates":[12.1694374084,47.5831222534],"type":"Point"}
}