{
  "type": "Feature",
  "properties": {
    "addr:full":"Nr 262 Edelschrott Steiermark 8583",
    "addr:postcode":"8583",
    "addr:street":"Nr;Edelschrott",
    "iso:country":"AT",
    "sg:address":"Nr 262",
    "sg:city":"Edelschrott",
    "sg:orig_category":"Druckereien",
    "sg:phone":"+43 4369 912426480",
    "sg:postcode":"8583",
    "sg:province":"Steiermark",
    "wof:name":"quaxi.com (G\u00f6ssler KEG)",
    "wof:placetype":"venue"
},
  "geometry": {"coordinates":[15.0517597198,47.0216178894],"type":"Point"}
}