{
  "type": "Feature",
  "properties": {
    "addr:full":"Cobenzlg 42/Top 15 Wien Wien 1190",
    "addr:housenumber":"42 / top 15",
    "addr:postcode":"1190",
    "addr:street":"Cobenzlg",
    "iso:country":"AT",
    "sg:address":"Cobenzlg 42/Top 15",
    "sg:city":"Wien",
    "sg:orig_category":"Datenverarbeitung",
    "sg:phone":"+43 1 3288456",
    "sg:postcode":"1190",
    "sg:province":"Wien",
    "wof:name":"Cardio Data-Systems Datenmanagement GmbH",
    "wof:placetype":"venue"
},
  "geometry": {"coordinates":[16.3493022919,48.2389793396],"type":"Point"}
}