{
  "type": "Feature",
  "properties": {
    "addr:full":"Lindenstr 12 Innsbruck Tirol 6020",
    "addr:housenumber":"12",
    "addr:postcode":"6020",
    "addr:street":"Lindenstr;Tirol",
    "iso:country":"AT",
    "sg:address":"Lindenstr 12",
    "sg:city":"Innsbruck",
    "sg:orig_category":"Tapezierer U Dekorateure",
    "sg:phone":"+43 4351 2343209",
    "sg:postcode":"6020",
    "sg:province":"Tirol",
    "wof:name":"Oberkofler Thomas",
    "wof:placetype":"venue"
},
  "geometry": {"coordinates":[11.4118919373,47.263759613],"type":"Point"}
}