{
  "type": "Feature",
  "properties": {
    "iso:country":"AT",
    "sg:address":"St.-Berthold-Allee 23",
    "sg:city":"Garsten",
    "sg:orig_category":"Apotheken",
    "sg:phone":"+43 7252 531310",
    "sg:postcode":"4451",
    "sg:province":"Ober\u00f6sterreich",
    "wof:name":"St Berthold-Apotheke Magpharm Susanne Wimmer & Co KG",
    "wof:placetype":"venue"
},
  "geometry": {"coordinates":[14.4070587158,48.025718689],"type":"Point"}
}