{
  "type": "Feature",
  "properties": {
    "iso:country":"AT",
    "sg:address":"Hauptstr 6",
    "sg:city":"Kottingbrunn",
    "sg:orig_category":"Behindertenhilfsmittel",
    "sg:phone":"+43 2252 761140",
    "sg:postcode":"2542",
    "sg:province":"Nieder\u00f6sterreich",
    "wof:name":"Hobi-Behindertenhilfsmittel GesmbH",
    "wof:placetype":"venue"
},
  "geometry": {"coordinates":[16.2297782898,47.9526367188],"type":"Point"}
}