{
  "type": "Feature",
  "properties": {
    "addr:full":"Judendorfer Str. 27 Gratwein Steiermark 8112",
    "addr:postcode":"8112",
    "addr:street":"Str.",
    "iso:country":"AT",
    "sg:address":"Judendorfer Str. 27",
    "sg:city":"Gratwein",
    "sg:classifiers":[
        {
            "category":"Shopping",
            "subcategory":"Stationery & Office Supplies",
            "type":"Retail Goods"
        }
    ],
    "sg:phone":"+43 4331 24516500",
    "sg:postcode":"8112",
    "sg:province":"Steiermark",
    "sg:tags":[
        "professional"
    ],
    "wof:name":"MERKSCHA GESMBH",
    "wof:placetype":"venue"
},
  "geometry": {"coordinates":[15.3240289688,47.1272392273],"type":"Point"}
}