{
  "type": "Feature",
  "properties": {
    "addr:full":"F\u00e4rberg 32 Wilhelmsburg an der Traisen Nieder\u00f6sterreich 3150",
    "addr:housenumber":"32",
    "addr:postcode":"3150",
    "addr:street":"Faerberg;An",
    "iso:country":"AT",
    "sg:address":"F\u00e4rberg 32",
    "sg:city":"Wilhelmsburg an der Traisen",
    "sg:orig_category":"Polizei U Gendarmerie",
    "sg:phone":"+43 4359 1333177",
    "sg:postcode":"3150",
    "sg:province":"Nieder\u00f6sterreich",
    "wof:name":"Gendarmerie",
    "wof:placetype":"venue"
},
  "geometry": {"coordinates":[15.6061897278,48.1053657532],"type":"Point"}
}