{
  "type": "Feature",
  "properties": {
    "addr:full":"Moserg 7 Wien Wien 1090",
    "addr:housenumber":"7",
    "addr:postcode":"1090",
    "addr:street":"Moserg",
    "iso:country":"AT",
    "sg:address":"Moserg 7",
    "sg:city":"Wien",
    "sg:orig_category":"Elektroinstallationsunternehmen",
    "sg:phone":"+43 1 3190274",
    "sg:postcode":"1090",
    "sg:province":"Wien",
    "wof:name":"Elektro Weber",
    "wof:placetype":"venue"
},
  "geometry": {"coordinates":[16.3661632538,48.2215995789],"type":"Point"}
}