{
  "type": "Feature",
  "properties": {
    "addr:full":"Friedhofg 5 Grieskirchen Ober\u00f6sterreich 4710",
    "addr:housenumber":"5",
    "addr:postcode":"4710",
    "addr:street":"Friedhofg",
    "iso:country":"AT",
    "sg:address":"Friedhofg 5",
    "sg:city":"Grieskirchen",
    "sg:orig_category":"Papier- U Schreibwaren / Einzelhandel",
    "sg:phone":"+43 7248 62206",
    "sg:postcode":"4710",
    "sg:province":"Ober\u00f6sterreich",
    "wof:name":"Wimmer Margit",
    "wof:placetype":"venue"
},
  "geometry": {"coordinates":[13.8316574097,48.2332420349],"type":"Point"}
}