{
  "type": "Feature",
  "properties": {
    "addr:full":"Silvrettastr 4 Schruns Vorarlberg 6780",
    "addr:housenumber":"4",
    "addr:postcode":"6780",
    "addr:street":"Silvrettastr",
    "iso:country":"AT",
    "sg:address":"Silvrettastr 4",
    "sg:city":"Schruns",
    "sg:orig_category":"Drogerien",
    "sg:phone":"+43 4355 5672571",
    "sg:postcode":"6780",
    "sg:province":"Vorarlberg",
    "wof:name":"Drogerie Ganahl",
    "wof:placetype":"venue"
},
  "geometry": {"coordinates":[9.9203548431,47.079498291],"type":"Point"}
}