{
  "type": "Feature",
  "properties": {
    "addr:full":"Nr 71b Kaltenbach Tirol 6272",
    "addr:postcode":"6272",
    "addr:street":"Nr 71B",
    "iso:country":"AT",
    "sg:address":"Nr 71b",
    "sg:city":"Kaltenbach",
    "sg:orig_category":"Appartements / Ferienwohnungen",
    "sg:phone":"+43 4352 832455",
    "sg:postcode":"6272",
    "sg:province":"Tirol",
    "wof:name":"Haus Dichtl",
    "wof:placetype":"venue"
},
  "geometry": {"coordinates":[11.8752498627,47.2923049927],"type":"Point"}
}