{
  "type": "Feature",
  "properties": {
    "addr:full":"Billrothstr. 22  Wien Wien 1190",
    "addr:housenumber":"22",
    "addr:postcode":"1190",
    "addr:street":"Billrothstr.",
    "iso:country":"AT",
    "sg:address":"Billrothstr. 22 ",
    "sg:city":"Wien",
    "sg:classifiers":[
        {
            "category":"Banks & Credit Unions",
            "subcategory":"Bank",
            "type":"Services"
        }
    ],
    "sg:phone":"+43 4313 683350",
    "sg:postcode":"1190",
    "sg:province":"Wien",
    "sg:tags":[
        "banking",
        "institution"
    ],
    "wof:name":"BANK AUSTRIA CREDITANSTALT AG",
    "wof:placetype":"venue"
},
  "geometry": {"coordinates":[16.3492546082,48.2373123169],"type":"Point"}
}