{
  "type": "Feature",
  "properties": {
    "addr:full":"Langst\u00f6gerg 4 Klosterneuburg Nieder\u00f6sterreich 3400",
    "addr:housenumber":"4",
    "addr:postcode":"3400",
    "addr:street":"Langstoegerg;Niederoesterreich",
    "iso:country":"AT",
    "sg:address":"Langst\u00f6gerg 4",
    "sg:city":"Klosterneuburg",
    "sg:orig_category":"Feuerwehren",
    "sg:phone":"+43 2243 372220",
    "sg:postcode":"3400",
    "sg:province":"Nieder\u00f6sterreich",
    "wof:name":"Freiwillige Feuerwehr Klosterneuburg",
    "wof:placetype":"venue"
},
  "geometry": {"coordinates":[16.3214130402,48.3113861084],"type":"Point"}
}