{
  "type": "Feature",
  "properties": {
    "addr:full":"Kirchg 3 Dornbirn Vorarlberg 6850",
    "addr:housenumber":"3",
    "addr:postcode":"6850",
    "addr:street":"Kirchg",
    "iso:country":"AT",
    "sg:address":"Kirchg 3",
    "sg:city":"Dornbirn",
    "sg:orig_category":"Dekorationen",
    "sg:phone":"+43 5572 51735",
    "sg:postcode":"6850",
    "sg:province":"Vorarlberg",
    "wof:name":"Nussbaumer Markus Rosenrot & Allerlei",
    "wof:placetype":"venue"
},
  "geometry": {"coordinates":[9.7506217957,47.408821106],"type":"Point"}
}