{
  "type": "Feature",
  "properties": {
    "addr:full":"Hauptstr 28 Ebensee Ober\u00f6sterreich 4802",
    "addr:housenumber":"28",
    "addr:postcode":"4802",
    "addr:street":"Hauptstr",
    "iso:country":"AT",
    "sg:address":"Hauptstr 28",
    "sg:city":"Ebensee",
    "sg:orig_category":"\u00c3\u201erzte / F Allgemeinmedizin",
    "sg:phone":"+43 6133 8081",
    "sg:postcode":"4802",
    "sg:province":"Ober\u00f6sterreich",
    "wof:name":"B\u00f6hler Dietmar Dr",
    "wof:placetype":"venue"
},
  "geometry": {"coordinates":[13.7731227875,47.811580658],"type":"Point"}
}