{
  "type": "Feature",
  "properties": {
    "iso:country":"AT",
    "sg:address":"Salzburger Str 9",
    "sg:city":"Mattighofen",
    "sg:orig_category":"Architekten",
    "sg:phone":"+43 7742 23500",
    "sg:postcode":"5230",
    "sg:province":"Ober\u00f6sterreich",
    "wof:name":"Wierer Friedrich Mag arch",
    "wof:placetype":"venue"
},
  "geometry": {"coordinates":[13.1517324448,48.1008758545],"type":"Point"}
}