{
  "type": "Feature",
  "properties": {
    "addr:full":"Bayerhamerstrasse 20a Salzburg Salzburg 5020",
    "addr:housenumber":"20a",
    "addr:postcode":"5020",
    "addr:street":"Bayerhamerstrasse;Salzburg",
    "iso:country":"AT",
    "sg:address":"Bayerhamerstrasse 20a",
    "sg:city":"Salzburg",
    "sg:classifiers":[
        {
            "category":"Professional",
            "subcategory":"Credit Reporting & Collection",
            "type":"Services"
        }
    ],
    "sg:phone":"+43 662 8711880",
    "sg:postcode":"5020",
    "sg:province":"Salzburg",
    "sg:tags":[
        "debt",
        "agency"
    ],
    "sg:website":"akzepta.com",
    "wof:name":"AKZEPTA Inkasso GmbH & Co. KG",
    "wof:placetype":"venue"
},
  "geometry": {"coordinates":[13.0502443314,47.8137168884],"type":"Point"}
}