{
  "type": "Feature",
  "properties": {
    "addr:full":"Landstr 27 Fohnsdorf Steiermark 8753",
    "addr:housenumber":"27",
    "addr:postcode":"8753",
    "addr:street":"Landstr",
    "iso:country":"AT",
    "sg:address":"Landstr 27",
    "sg:city":"Fohnsdorf",
    "sg:orig_category":"Transportunternehmen",
    "sg:phone":"+43 3573 2437",
    "sg:postcode":"8753",
    "sg:province":"Steiermark",
    "wof:name":"Siebenb\u00e4ck & Partner KEG",
    "wof:placetype":"venue"
},
  "geometry": {"coordinates":[14.6866159439,47.2097053528],"type":"Point"}
}