{
  "type": "Feature",
  "properties": {
    "addr:full":"Nr 6 Obdach Steiermark 8742",
    "addr:postcode":"8742",
    "addr:street":"Nr",
    "iso:country":"AT",
    "sg:address":"Nr 6",
    "sg:city":"Obdach",
    "sg:orig_category":"Holzgro\u00c3\u0178handel",
    "sg:phone":"+43 4335 7840200",
    "sg:postcode":"8742",
    "sg:province":"Steiermark",
    "wof:name":"GBZ Holzindustrie GmbH",
    "wof:placetype":"venue"
},
  "geometry": {"coordinates":[14.6953725815,47.0679969788],"type":"Point"}
}