{
  "type": "Feature",
  "properties": {
    "addr:full":"Welser Str 120 Leonding Ober\u00f6sterreich 4060",
    "addr:housenumber":"120",
    "addr:postcode":"4060",
    "iso:country":"AT",
    "sg:address":"Welser Str 120",
    "sg:city":"Leonding",
    "sg:orig_category":"Autohandel",
    "sg:phone":"+43 732 6772770",
    "sg:postcode":"4060",
    "sg:province":"Ober\u00f6sterreich",
    "wof:name":"Baschinger GesmbH - Chrysler-Jeep Zentrum",
    "wof:placetype":"venue"
},
  "geometry": {"coordinates":[14.2422170639,48.2490005493],"type":"Point"}
}