{
  "type": "Feature",
  "properties": {
    "addr:full":"Gutauer Str 16 Pregarten Ober\u00f6sterreich 4230",
    "addr:postcode":"4230",
    "addr:street":"Str 16",
    "iso:country":"AT",
    "sg:address":"Gutauer Str 16",
    "sg:city":"Pregarten",
    "sg:orig_category":"Fahrschulen",
    "sg:phone":"+43 7236 7570",
    "sg:postcode":"4230",
    "sg:province":"Ober\u00f6sterreich",
    "wof:name":"Aub\u00f6ck Franz Ing",
    "wof:placetype":"venue"
},
  "geometry": {"coordinates":[14.530995369,48.3569793701],"type":"Point"}
}