{
  "type": "Feature",
  "properties": {
    "addr:full":"Innsbrucker Str 18 Schwaz Tirol 6130",
    "addr:postcode":"6130",
    "addr:street":"Str 18;Tirol",
    "iso:country":"AT",
    "sg:address":"Innsbrucker Str 18",
    "sg:city":"Schwaz",
    "sg:orig_category":"Drogerien",
    "sg:phone":"+43 5242 64993",
    "sg:postcode":"6130",
    "sg:province":"Tirol",
    "wof:name":"dm drogerie markt GmbH",
    "wof:placetype":"venue"
},
  "geometry": {"coordinates":[11.7075443268,47.343624115],"type":"Point"}
}