{
  "type": "Feature",
  "properties": {
    "addr:full":"Industriestrasse 13 Lannach Steiermark 8502",
    "addr:housenumber":"13",
    "addr:postcode":"8502",
    "addr:street":"Industriestrasse",
    "iso:country":"AT",
    "sg:address":"Industriestrasse 13",
    "sg:city":"Lannach",
    "sg:classifiers":[
        {
            "category":"Utilities",
            "subcategory":"Sewage",
            "type":"Services"
        }
    ],
    "sg:phone":"+43 3136 81626",
    "sg:postcode":"8502",
    "sg:province":"Steiermark",
    "sg:tags":[
        "cnc",
        "grinding"
    ],
    "sg:website":"bvt.at",
    "wof:name":"BVT Beschichtungs- u. Verschlei\u00dftechnik GesmbH",
    "wof:placetype":"venue"
},
  "geometry": {"coordinates":[15.3316164017,46.9533843994],"type":"Point"}
}