{
  "type": "Feature",
  "properties": {
    "addr:full":"Pfaffst\u00e4ttner Str 31 Traiskirchen Nieder\u00f6sterreich 2514",
    "addr:postcode":"2514",
    "addr:street":"Str 31",
    "iso:country":"AT",
    "sg:address":"Pfaffst\u00e4ttner Str 31",
    "sg:city":"Traiskirchen",
    "sg:orig_category":"Elektroinstallationsunternehmen",
    "sg:phone":"+43 2252 539110",
    "sg:postcode":"2514",
    "sg:province":"Nieder\u00f6sterreich",
    "wof:name":"Elektro Beyhl GesmbH",
    "wof:placetype":"venue"
},
  "geometry": {"coordinates":[16.2870731354,48.013469696],"type":"Point"}
}