{
  "type": "Feature",
  "properties": {
    "iso:country":"AT",
    "sg:address":"Oswaldiweg 1 - T\u00f6bring",
    "sg:city":"Treffen",
    "sg:classifiers":[
        {
            "category":"Arena",
            "subcategory":"Bull Ring",
            "type":"Entertainment"
        }
    ],
    "sg:phone":"+43 4248 2273",
    "sg:postcode":"9521",
    "sg:province":"K\u00e4rnten",
    "sg:tags":[
        "back-up"
    ],
    "wof:name":"J. M\u00f6ssler Draht- u. Blech Gesellschaft m.b.H. & Co KG",
    "wof:placetype":"venue"
},
  "geometry": {"coordinates":[13.8552322388,46.6679840088],"type":"Point"}
}