{
  "type": "Feature",
  "properties": {
    "addr:full":"Garnisong 15 Wien Wien 1090",
    "addr:housenumber":"15",
    "addr:postcode":"1090",
    "addr:street":"Garnisong",
    "iso:country":"AT",
    "sg:address":"Garnisong 15",
    "sg:city":"Wien",
    "sg:orig_category":"Logistik",
    "sg:phone":"+43 1 24800",
    "sg:postcode":"1090",
    "sg:province":"Wien",
    "wof:name":"Geldservice Austria - Cash Center Wien",
    "wof:placetype":"venue"
},
  "geometry": {"coordinates":[16.3558979034,48.217666626],"type":"Point"}
}