{
  "type": "Feature",
  "properties": {
    "addr:full":"Wiener Str 45 Stegersbach Burgenland 7551",
    "addr:postcode":"7551",
    "iso:country":"AT",
    "sg:address":"Wiener Str 45",
    "sg:city":"Stegersbach",
    "sg:orig_category":"Fahrzeugbau",
    "sg:phone":"+43 4333 26524650",
    "sg:postcode":"7551",
    "sg:province":"Burgenland",
    "wof:name":"Peischl Fahrzeugbau GesmbH",
    "wof:placetype":"venue"
},
  "geometry": {"coordinates":[16.1629581451,47.1677436829],"type":"Point"}
}