{
  "type": "Feature",
  "properties": {
    "addr:full":"Troststr 5-9 Wien Wien 1100",
    "addr:housenumber":"5-9",
    "addr:postcode":"1100",
    "addr:street":"Troststr",
    "iso:country":"AT",
    "sg:address":"Troststr 5-9",
    "sg:city":"Wien",
    "sg:orig_category":"Blumeneinzelhandel",
    "sg:phone":"+43 1 6023728",
    "sg:postcode":"1100",
    "sg:province":"Wien",
    "wof:name":"Blumen Evelyn",
    "wof:placetype":"venue"
},
  "geometry": {"coordinates":[16.3793849945,48.1687927246],"type":"Point"}
}