{
  "type": "Feature",
  "properties": {
    "addr:full":"Bodmerg 3 Wien Wien 1220",
    "addr:housenumber":"3",
    "addr:postcode":"1220",
    "addr:street":"Bodmerg",
    "iso:country":"AT",
    "sg:address":"Bodmerg 3",
    "sg:city":"Wien",
    "sg:orig_category":"Detekteien",
    "sg:phone":"+43 1 2807994",
    "sg:postcode":"1220",
    "sg:province":"Wien",
    "wof:name":"Leitner Sicherheits- und \u00dcberwachungstechnik",
    "wof:placetype":"venue"
},
  "geometry": {"coordinates":[16.4705657959,48.2276725769],"type":"Point"}
}