{
  "type": "Feature",
  "properties": {
    "iso:country":"AT",
    "sg:address":"D\u00f6blinger Hauptstr 11",
    "sg:city":"Wien",
    "sg:classifiers":[
        {
            "category":"Restaurant",
            "type":"Food & Drink"
        }
    ],
    "sg:phone":"+43 1 3695641",
    "sg:postcode":"1190",
    "sg:province":"Wien",
    "wof:name":"Cottage Stub'n",
    "wof:placetype":"venue"
},
  "geometry": {"coordinates":[16.3526191711,48.2344284058],"type":"Point"}
}