{
  "type": "Feature",
  "properties": {
    "iso:country":"AT",
    "sg:address":"Landstra\u00dfer Hauptstr 81",
    "sg:city":"Wien",
    "sg:orig_category":"Damenmoden",
    "sg:phone":"+43 4317 137789",
    "sg:postcode":"1030",
    "sg:province":"Wien",
    "wof:name":"Hambrusch Christoph",
    "wof:placetype":"venue"
},
  "geometry": {"coordinates":[16.393699646,48.2000274658],"type":"Point"}
}