{
  "type": "Feature",
  "properties": {
    "addr:full":"Kirchenpl 10 Obernberg am Inn Ober\u00f6sterreich 4982",
    "addr:housenumber":"10",
    "addr:postcode":"4982",
    "addr:street":"Kirchenpl",
    "iso:country":"AT",
    "sg:address":"Kirchenpl 10",
    "sg:city":"Obernberg am Inn",
    "sg:classifiers":[
        {
            "category":"Utilities",
            "subcategory":"Refuse",
            "type":"Services"
        }
    ],
    "sg:phone":"+43 664 1411908",
    "sg:postcode":"4982",
    "sg:province":"Ober\u00f6sterreich",
    "sg:tags":[
        "catering"
    ],
    "wof:name":"Draschl Richard",
    "wof:placetype":"venue"
},
  "geometry": {"coordinates":[13.3349962234,48.3207969666],"type":"Point"}
}