{
  "type": "Feature",
  "properties": {
    "addr:full":"Sautern 402 Schlierbach Ober\u00f6sterreich 4553",
    "addr:housenumber":"402",
    "addr:postcode":"4553",
    "addr:street":"Sautern",
    "iso:country":"AT",
    "sg:address":"Sautern 402",
    "sg:city":"Schlierbach",
    "sg:classifiers":[
        {
            "category":"Manufacturing",
            "subcategory":"Tools & Machinery",
            "type":"Manufacturing & Wholesale Goods"
        }
    ],
    "sg:phone":"+43 7582 37552",
    "sg:postcode":"4553",
    "sg:province":"Ober\u00f6sterreich",
    "sg:tags":[
        "part",
        "turned",
        "cnc"
    ],
    "sg:website":"bub.co.at",
    "wof:name":"B & B Ges.m.b.H.",
    "wof:placetype":"venue"
},
  "geometry": {"coordinates":[14.1066923141,47.9523391724],"type":"Point"}
}