{
  "type": "Feature",
  "properties": {
    "addr:full":"Traung 14 Wels Ober\u00f6sterreich 4600",
    "addr:housenumber":"14",
    "addr:postcode":"4600",
    "addr:street":"Traung;Oberoesterreich",
    "iso:country":"AT",
    "sg:address":"Traung 14",
    "sg:city":"Wels",
    "sg:orig_category":"Fitnesscenter",
    "sg:phone":"+43 7242 74471",
    "sg:postcode":"4600",
    "sg:province":"Ober\u00f6sterreich",
    "wof:name":"Fitness Company KEG",
    "wof:placetype":"venue"
},
  "geometry": {"coordinates":[14.025976181,48.1554069519],"type":"Point"}
}