{
  "type": "Feature",
  "properties": {
    "addr:full":"Linzer Str 250 Wien Wien 1140",
    "addr:housenumber":"250",
    "addr:postcode":"1140",
    "addr:street":"Linzer Str",
    "iso:country":"AT",
    "sg:address":"Linzer Str 250",
    "sg:city":"Wien",
    "sg:orig_category":"Friseure U Frisiersalons",
    "sg:phone":"+43 4319 149719",
    "sg:postcode":"1140",
    "sg:province":"Wien",
    "wof:name":"Hair Control",
    "wof:placetype":"venue"
},
  "geometry": {"coordinates":[16.281419754,48.1956329346],"type":"Point"}
}