{
  "type": "Feature",
  "properties": {
    "addr:full":"Ziegelofeng 20 Ziersdorf Nieder\u00f6sterreich 3710",
    "addr:housenumber":"20",
    "addr:postcode":"3710",
    "addr:street":"Ziegelofeng",
    "iso:country":"AT",
    "sg:address":"Ziegelofeng 20",
    "sg:city":"Ziersdorf",
    "sg:orig_category":"Anlagenbau U -Technik",
    "sg:phone":"+43 4329 5622630",
    "sg:postcode":"3710",
    "sg:province":"Nieder\u00f6sterreich",
    "wof:name":"Steinhofer Engelbert",
    "wof:placetype":"venue"
},
  "geometry": {"coordinates":[15.9255962372,48.525100708],"type":"Point"}
}