{
  "type": "Feature",
  "properties": {
    "addr:full":"NB Gr\u00e4n Tirol 6673",
    "addr:postcode":"6673",
    "iso:country":"AT",
    "sg:address":"NB",
    "sg:city":"Gr\u00e4n",
    "sg:orig_category":"Molkereien U Molkereiprodukte",
    "sg:phone":"+43 5675 6463",
    "sg:postcode":"6673",
    "sg:province":"Tirol",
    "wof:name":"Biedermann Otto HandelsgesmbH & Co KG",
    "wof:placetype":"venue"
},
  "geometry": {"coordinates":[10.5535697937,47.5023612976],"type":"Point"}
}