{
  "type": "Feature",
  "properties": {
    "iso:country":"AT",
    "sg:address":"Zw\u00f6lfaxinger Strasse 17",
    "sg:city":"Schwechat",
    "sg:classifiers":[
        {
            "category":"Arts & Performance",
            "subcategory":"Art Gallery",
            "type":"Entertainment"
        }
    ],
    "sg:phone":"+43 1 7075004",
    "sg:postcode":"2320",
    "sg:province":"Nieder\u00f6sterreich",
    "sg:tags":[
        "painting"
    ],
    "sg:website":"sukopp.com",
    "wof:name":"SUKOPP Theatermalerei GmbH",
    "wof:placetype":"venue"
},
  "geometry": {"coordinates":[16.4580783844,48.11536026],"type":"Point"}
}