{
  "type": "Feature",
  "properties": {
    "iso:country":"AT",
    "sg:address":"Panoramaweg 11",
    "sg:city":"Gro\u00df St. Florian",
    "sg:orig_category":"Pensionen / Privatzimmer",
    "sg:phone":"+43 4334 642346",
    "sg:postcode":"8522",
    "sg:province":"Steiermark",
    "wof:name":"Urlaub am Bauernhof Lamprecht Anneliese u Florian",
    "wof:placetype":"venue"
},
  "geometry": {"coordinates":[15.3171710968,46.8239822388],"type":"Point"}
}