{
  "type": "Feature",
  "properties": {
    "addr:full":"Arlerweg 5 Niedernsill Salzburg 5722",
    "addr:housenumber":"5",
    "addr:postcode":"5722",
    "addr:street":"Arlerweg;Salzburg",
    "iso:country":"AT",
    "sg:address":"Arlerweg 5",
    "sg:city":"Niedernsill",
    "sg:classifiers":[
        {
            "category":"Retail",
            "subcategory":"Event Space",
            "type":"Services"
        }
    ],
    "sg:phone":"+43 4365 488147",
    "sg:postcode":"5722",
    "sg:province":"Salzburg",
    "sg:tags":[
        "hand-",
        "u",
        "fu\u00c3\u0178pflege"
    ],
    "wof:name":"Hartl Irmgard",
    "wof:placetype":"venue"
},
  "geometry": {"coordinates":[12.6223516464,47.283241272],"type":"Point"}
}