{
  "type": "Feature",
  "properties": {
    "addr:full":"Altausseer Str 245 Bad Aussee Steiermark 8990",
    "addr:housenumber":"245",
    "addr:postcode":"8990",
    "iso:country":"AT",
    "sg:address":"Altausseer Str 245",
    "sg:city":"Bad Aussee",
    "sg:orig_category":"Pensionen / Privatzimmer",
    "sg:phone":"+43 3622 52484",
    "sg:postcode":"8990",
    "sg:province":"Steiermark",
    "wof:name":"Pension Stocker",
    "wof:placetype":"venue"
},
  "geometry": {"coordinates":[13.7786149979,47.6124725342],"type":"Point"}
}