{
  "type": "Feature",
  "properties": {
    "addr:full":"Hauptpl 8 Ober-Grafendorf Nieder\u00f6sterreich 3200",
    "addr:housenumber":"8",
    "addr:postcode":"3200",
    "addr:street":"Hauptpl",
    "iso:country":"AT",
    "sg:address":"Hauptpl 8",
    "sg:city":"Ober-Grafendorf",
    "sg:orig_category":"Fleischhauereien",
    "sg:phone":"+43 2747 2222",
    "sg:postcode":"3200",
    "sg:province":"Nieder\u00f6sterreich",
    "wof:name":"Ettl Fritz",
    "wof:placetype":"venue"
},
  "geometry": {"coordinates":[15.5445127487,48.1507568359],"type":"Point"}
}