{
  "type": "Feature",
  "properties": {
    "addr:full":"Kirchenpl 2 Halbturn Burgenland 7131",
    "addr:housenumber":"2",
    "addr:postcode":"7131",
    "addr:street":"Kirchenpl",
    "iso:country":"AT",
    "sg:address":"Kirchenpl 2",
    "sg:city":"Halbturn",
    "sg:orig_category":"Non-Classified Establishments",
    "sg:phone":"+43 2172 86320",
    "sg:postcode":"7131",
    "sg:province":"Burgenland",
    "wof:name":"Pfarramt",
    "wof:placetype":"venue"
},
  "geometry": {"coordinates":[16.9740753174,47.8713951111],"type":"Point"}
}