{
  "type": "Feature",
  "properties": {
    "iso:country":"AT",
    "sg:address":"Hans-Sachs-Str. 2",
    "sg:city":"Braunau am Inn",
    "sg:classifiers":[
        {
            "category":"Professional",
            "subcategory":"Engineering",
            "type":"Services"
        }
    ],
    "sg:phone":"+43 4377 2262959",
    "sg:postcode":"5280",
    "sg:province":"Ober\u00f6sterreich",
    "sg:tags":[
        "machine",
        "-",
        "mechanical"
    ],
    "wof:name":"LANG & CO.",
    "wof:placetype":"venue"
},
  "geometry": {"coordinates":[13.0451393127,48.2603187561],"type":"Point"}
}