{
  "type": "Feature",
  "properties": {
    "addr:full":"Deutschgasse 11 Wiener Neustadt Nieder\u00f6sterreich 2700",
    "addr:housenumber":"11",
    "addr:postcode":"2700",
    "addr:street":"Deutschgasse",
    "iso:country":"AT",
    "sg:address":"Deutschgasse 11",
    "sg:city":"Wiener Neustadt",
    "sg:classifiers":[
        {
            "category":"Social Services",
            "subcategory":"Adult Care",
            "type":"Services"
        }
    ],
    "sg:phone":"+43 2622 227100",
    "sg:postcode":"2700",
    "sg:province":"Nieder\u00f6sterreich",
    "sg:tags":[
        "limb",
        "artificial"
    ],
    "sg:website":"helnwein.at",
    "wof:name":"Helnwein Ges.m.b.H.",
    "wof:placetype":"venue"
},
  "geometry": {"coordinates":[16.2456550598,47.8152503967],"type":"Point"}
}