{
  "type": "Feature",
  "properties": {
    "addr:full":"St Georgener Str 180 Villach K\u00e4rnten 9500",
    "addr:housenumber":"180",
    "addr:postcode":"9500",
    "addr:street":"St Georgener Str;Kaernten",
    "iso:country":"AT",
    "sg:address":"St Georgener Str 180",
    "sg:city":"Villach",
    "sg:orig_category":"Innenarchitekten",
    "sg:phone":"+43 4242 57657",
    "sg:postcode":"9500",
    "sg:province":"K\u00e4rnten",
    "wof:name":"FORMidee Wolfgang Stani",
    "wof:placetype":"venue"
},
  "geometry": {"coordinates":[13.8089551926,46.6124763489],"type":"Point"}
}