{
  "type": "Feature",
  "properties": {
    "addr:full":"Innsbrucker Str 10 Brixlegg Tirol 6230",
    "addr:postcode":"6230",
    "addr:street":"Str 10;Tirol",
    "iso:country":"AT",
    "sg:address":"Innsbrucker Str 10",
    "sg:city":"Brixlegg",
    "sg:orig_category":"Physiotherapie",
    "sg:phone":"+43 4353 3764326",
    "sg:postcode":"6230",
    "sg:province":"Tirol",
    "wof:name":"Mandravelos Georges Dipl-PT",
    "wof:placetype":"venue"
},
  "geometry": {"coordinates":[11.8756837845,47.4271812439],"type":"Point"}
}