{
  "type": "Feature",
  "properties": {
    "addr:full":"O'Brien-G 34-44 Wien Wien 1210",
    "addr:postcode":"34-44;1210",
    "iso:country":"AT",
    "sg:address":"O'Brien-G 34-44",
    "sg:city":"Wien",
    "sg:orig_category":"Geschenkartikel",
    "sg:phone":"+43 1 2726556",
    "sg:postcode":"1210",
    "sg:province":"Wien",
    "wof:name":"Curiosity-Shop Halac",
    "wof:placetype":"venue"
},
  "geometry": {"coordinates":[16.415309906,48.2794799805],"type":"Point"}
}