{
  "type": "Feature",
  "properties": {
    "iso:country":"AT",
    "sg:address":"Salzackerstr 17",
    "sg:city":"Kindberg",
    "sg:orig_category":"Feuerwehren",
    "sg:phone":"+43 664 2348538",
    "sg:postcode":"8650",
    "sg:province":"Steiermark",
    "wof:name":"Freiwillige Feuerwehr",
    "wof:placetype":"venue"
},
  "geometry": {"coordinates":[15.4495258331,47.512928009],"type":"Point"}
}