{
  "type": "Feature",
  "properties": {
    "iso:country":"AT",
    "sg:address":"Fleschg 32",
    "sg:city":"Wien",
    "sg:orig_category":"Filmproduktionen",
    "sg:phone":"+43 1 8770887",
    "sg:postcode":"1130",
    "sg:province":"Wien",
    "wof:name":"Muhr TV",
    "wof:placetype":"venue"
},
  "geometry": {"coordinates":[16.2899532318,48.1899223328],"type":"Point"}
}