{
  "type": "Feature",
  "properties": {
    "iso:country":"AT",
    "sg:address":"Raxer Str 2",
    "sg:city":"Jennersdorf",
    "sg:orig_category":"Fleisch-, Wurst- U Selchwaren / Erzeugung U Gro\u00c3\u0178handel",
    "sg:phone":"+43 4333 2948479",
    "sg:postcode":"8380",
    "sg:province":"Burgenland",
    "wof:name":"Reiner Josef Steirische Manufaktur f\u00fcr Feinschmecker GmbH",
    "wof:placetype":"venue"
},
  "geometry": {"coordinates":[16.1437683105,46.9392814636],"type":"Point"}
}