{
  "type": "Feature",
  "properties": {
    "addr:full":"Nr 45 Fieberbrunn Tirol 6391",
    "addr:postcode":"6391",
    "addr:street":"Nr 45;Tirol",
    "iso:country":"AT",
    "sg:address":"Nr 45",
    "sg:city":"Fieberbrunn",
    "sg:orig_category":"Autohandel",
    "sg:phone":"+43 5354 56259",
    "sg:postcode":"6391",
    "sg:province":"Tirol",
    "wof:name":"Pfeiler Emmerich KG",
    "wof:placetype":"venue"
},
  "geometry": {"coordinates":[12.5448112488,47.4751586914],"type":"Point"}
}