{
  "type": "Feature",
  "properties": {
    "addr:full":"Obere Bahnstr 11 Spital am Semmering Steiermark 8684",
    "addr:housenumber":"11",
    "addr:postcode":"8684",
    "addr:street":"Obere Bahnstr",
    "iso:country":"AT",
    "sg:address":"Obere Bahnstr 11",
    "sg:city":"Spital am Semmering",
    "sg:orig_category":"Massagen",
    "sg:phone":"+43 3853 4851",
    "sg:postcode":"8684",
    "sg:province":"Steiermark",
    "wof:name":"Halmdienst Setsuko",
    "wof:placetype":"venue"
},
  "geometry": {"coordinates":[15.7441663742,47.6179695129],"type":"Point"}
}