{
  "type": "Feature",
  "properties": {
    "addr:full":"Alxingerg 6 Wien Wien 1100",
    "addr:housenumber":"6",
    "addr:postcode":"1100",
    "addr:street":"Alxingerg",
    "iso:country":"AT",
    "sg:address":"Alxingerg 6",
    "sg:city":"Wien",
    "sg:orig_category":"Non-Classified Establishments",
    "sg:phone":"+43 1 60445520",
    "sg:postcode":"1100",
    "sg:province":"Wien",
    "wof:name":"Missionskongregation d Dienerinnen des Hl Geistes",
    "wof:placetype":"venue"
},
  "geometry": {"coordinates":[16.3682880402,48.1807365417],"type":"Point"}
}