{
  "type": "Feature",
  "properties": {
    "addr:full":"Plus-Kauf-Strasse 11 Pasching Ober\u00f6sterreich 4061",
    "addr:housenumber":"11",
    "addr:postcode":"4061",
    "addr:street":"Plus-Kauf-Strasse;Oberoesterreich",
    "iso:country":"AT",
    "sg:address":"Plus-Kauf-Strasse 11",
    "sg:city":"Pasching",
    "sg:classifiers":[
        {
            "category":"Transit Center",
            "subcategory":"Freight",
            "type":"Transportation"
        }
    ],
    "sg:phone":"+43 7229 7710",
    "sg:postcode":"4061",
    "sg:province":"Ober\u00f6sterreich",
    "sg:tags":[
        "forwarding",
        "agency"
    ],
    "sg:website":"transdanubia.com",
    "wof:name":"TRANSDANUBIA Speditionsges.m.b.H.",
    "wof:placetype":"venue"
},
  "geometry": {"coordinates":[14.2359104156,48.2444572449],"type":"Point"}
}