{
  "type": "Feature",
  "properties": {
    "iso:country":"AT",
    "sg:address":"Untere Augartenstr 30",
    "sg:city":"Wien",
    "sg:orig_category":"Behinderungen / Leben Mit Behinderungen",
    "sg:phone":"+43 4312 1628320",
    "sg:postcode":"1020",
    "sg:province":"Wien",
    "wof:name":"\u00f6sterr Hilfswerk f Taubblinde u hochgradig H\u00f6r- u Sehbehinderte",
    "wof:placetype":"venue"
},
  "geometry": {"coordinates":[16.3736305237,48.2212371826],"type":"Point"}
}