{
  "type": "Feature",
  "properties": {
    "addr:full":"Mirnockstr 36 Millstatt K\u00e4rnten 9872",
    "addr:housenumber":"36",
    "addr:postcode":"9872",
    "addr:street":"Mirnockstr;Kaernten",
    "iso:country":"AT",
    "sg:address":"Mirnockstr 36",
    "sg:city":"Millstatt",
    "sg:orig_category":"Tabaktrafiken",
    "sg:phone":"+43 4766 2651",
    "sg:postcode":"9872",
    "sg:province":"K\u00e4rnten",
    "wof:name":"Haberl Hannelore",
    "wof:placetype":"venue"
},
  "geometry": {"coordinates":[13.5736217499,46.8041992188],"type":"Point"}
}