{
  "type": "Feature",
  "properties": {
    "iso:country":"AT",
    "sg:address":"Annenstr 59",
    "sg:city":"Graz",
    "sg:orig_category":"\u00c3\u201erzte / F Allgemeinmedizin",
    "sg:phone":"+43 316 713302",
    "sg:postcode":"8020",
    "sg:province":"Steiermark",
    "wof:name":"Grein Krista Dr",
    "wof:placetype":"venue"
},
  "geometry": {"coordinates":[15.4216423035,47.071231842],"type":"Point"}
}