{
  "type": "Feature",
  "properties": {
    "addr:full":"Kasernenstr 5B Wals Salzburg 5071",
    "addr:housenumber":"5b",
    "addr:postcode":"5071",
    "addr:street":"Kasernenstr;Salzburg",
    "iso:country":"AT",
    "sg:address":"Kasernenstr 5B",
    "sg:city":"Wals",
    "sg:classifiers":[
        {
            "category":"Restaurant",
            "type":"Food & Drink"
        }
    ],
    "sg:phone":"+43 662 854099",
    "sg:postcode":"5071",
    "sg:province":"Salzburg",
    "sg:tags":[
        "pizzeria"
    ],
    "wof:name":"Giorgio's Pizzeria",
    "wof:placetype":"venue"
},
  "geometry": {"coordinates":[12.9884386063,47.7929077148],"type":"Point"}
}