{
  "type": "Feature",
  "properties": {
    "addr:full":"Mayrweg 10 Aldrans Tirol 6071",
    "addr:housenumber":"10",
    "addr:postcode":"6071",
    "addr:street":"Mayrweg;Tirol",
    "iso:country":"AT",
    "sg:address":"Mayrweg 10",
    "sg:city":"Aldrans",
    "sg:orig_category":"Appartements / Ferienwohnungen",
    "sg:phone":"+43 512 348378",
    "sg:postcode":"6071",
    "sg:province":"Tirol",
    "wof:name":"Haus Ruhland",
    "wof:placetype":"venue"
},
  "geometry": {"coordinates":[11.4464635849,47.2481384277],"type":"Point"}
}