{
  "type": "Feature",
  "properties": {
    "addr:full":"Plobergerstr 7 Wels Ober\u00f6sterreich 4600",
    "addr:housenumber":"7",
    "addr:postcode":"4600",
    "addr:street":"Plobergerstr;Oberoesterreich",
    "iso:country":"AT",
    "sg:address":"Plobergerstr 7",
    "sg:city":"Wels",
    "sg:orig_category":"Polizei U Gendarmerie",
    "sg:phone":"+43 4372 42408530",
    "sg:postcode":"4600",
    "sg:province":"Ober\u00f6sterreich",
    "wof:name":"Gendarmerieposten Innere Stadt",
    "wof:placetype":"venue"
},
  "geometry": {"coordinates":[14.0234184265,48.1577453613],"type":"Point"}
}