{
  "type": "Feature",
  "properties": {
    "addr:full":"Freindorfer Str 40 Ansfelden Ober\u00f6sterreich 4052",
    "addr:postcode":"4052",
    "addr:street":"Str 40",
    "iso:country":"AT",
    "sg:address":"Freindorfer Str 40",
    "sg:city":"Ansfelden",
    "sg:orig_category":"Tischlereien",
    "sg:phone":"+43 732 3016600",
    "sg:postcode":"4052",
    "sg:province":"Ober\u00f6sterreich",
    "wof:name":"Anzinger Gilbert P",
    "wof:placetype":"venue"
},
  "geometry": {"coordinates":[14.3009033203,48.2302017212],"type":"Point"}
}