{
  "type": "Feature",
  "properties": {
    "iso:country":"AT",
    "sg:address":"Hauptstr 62",
    "sg:city":"Orth an der Donau",
    "sg:orig_category":"Blumeneinzelhandel",
    "sg:phone":"+43 4366 42305216",
    "sg:postcode":"2304",
    "sg:province":"Nieder\u00f6sterreich",
    "wof:name":"MJZ Floral Design - Michael J Zihr",
    "wof:placetype":"venue"
},
  "geometry": {"coordinates":[16.7171669006,48.1490631104],"type":"Point"}
}