{
  "type": "Feature",
  "properties": {
    "iso:country":"AT",
    "sg:address":"Bachg 3",
    "sg:city":"Dornbirn",
    "sg:orig_category":"Juweliere, Gold- U Silberschmiede",
    "sg:phone":"+43 5572 24366",
    "sg:postcode":"6850",
    "sg:province":"Vorarlberg",
    "wof:name":"Haberl & Ilg GesnbR",
    "wof:placetype":"venue"
},
  "geometry": {"coordinates":[9.7539968491,47.432220459],"type":"Point"}
}