{
  "type": "Feature",
  "properties": {
    "addr:full":"Geranienweg 1 Guntramsdorf Nieder\u00f6sterreich 2353",
    "addr:housenumber":"1",
    "addr:postcode":"2353",
    "addr:street":"Geranienweg",
    "iso:country":"AT",
    "sg:address":"Geranienweg 1",
    "sg:city":"Guntramsdorf",
    "sg:orig_category":"Ingenieurkonsulenten / Zivilingenieure",
    "sg:phone":"+43 2236 506106",
    "sg:postcode":"2353",
    "sg:province":"Nieder\u00f6sterreich",
    "wof:name":"Rausch Gerald Dipl-Ing",
    "wof:placetype":"venue"
},
  "geometry": {"coordinates":[16.3111476898,48.0423927307],"type":"Point"}
}