{
  "type": "Feature",
  "properties": {
    "addr:full":"Loquaipl 13 Wien Wien 1060",
    "addr:housenumber":"13",
    "addr:postcode":"1060",
    "addr:street":"Loquaipl",
    "iso:country":"AT",
    "sg:address":"Loquaipl 13",
    "sg:city":"Wien",
    "sg:orig_category":"Tai Chi, Tai Chi Chuan U Qi Gong",
    "sg:phone":"+43 1 5812951",
    "sg:postcode":"1060",
    "sg:province":"Wien",
    "wof:name":"Der Shaolinfriedenstempel",
    "wof:placetype":"venue"
},
  "geometry": {"coordinates":[16.348941803,48.1943740845],"type":"Point"}
}