{
  "type": "Feature",
  "properties": {
    "addr:full":"Nr 58 Fresach K\u00e4rnten 9712",
    "addr:postcode":"9712",
    "addr:street":"Nr 58;Kaernten",
    "iso:country":"AT",
    "sg:address":"Nr 58",
    "sg:city":"Fresach",
    "sg:orig_category":"Tischlereien",
    "sg:phone":"+43 4245 4843",
    "sg:postcode":"9712",
    "sg:province":"K\u00e4rnten",
    "wof:name":"Baumgartner Heinz",
    "wof:placetype":"venue"
},
  "geometry": {"coordinates":[13.6881408691,46.7136497498],"type":"Point"}
}