{
  "type": "Feature",
  "properties": {
    "addr:full":"Siemensstr 9 Linz Ober\u00f6sterreich 4030",
    "addr:housenumber":"9",
    "addr:postcode":"4030",
    "addr:street":"Siemensstr",
    "iso:country":"AT",
    "sg:address":"Siemensstr 9",
    "sg:city":"Linz",
    "sg:orig_category":"Tabaktrafiken",
    "sg:phone":"+43 732 380253",
    "sg:postcode":"4030",
    "sg:province":"Ober\u00f6sterreich",
    "wof:name":"Putzenlechner Wolfgang",
    "wof:placetype":"venue"
},
  "geometry": {"coordinates":[14.2832727432,48.2528457642],"type":"Point"}
}