{
  "type": "Feature",
  "properties": {
    "addr:full":"Donaug 4-6 Tulln an der Donau Nieder\u00f6sterreich 3430",
    "addr:housenumber":"4-6",
    "addr:postcode":"3430",
    "addr:street":"Donaug",
    "iso:country":"AT",
    "sg:address":"Donaug 4-6",
    "sg:city":"Tulln an der Donau",
    "sg:orig_category":"Politische Parteien",
    "sg:phone":"+43 2272 623640",
    "sg:postcode":"3430",
    "sg:province":"Nieder\u00f6sterreich",
    "wof:name":"\u00f6sterreichische Volkspartei",
    "wof:placetype":"venue"
},
  "geometry": {"coordinates":[16.0497398376,48.3306999207],"type":"Point"}
}