{
  "type": "Feature",
  "properties": {
    "addr:full":"Rudolf-Waisenhorn-G 20a Wien Wien 1230",
    "addr:housenumber":"20a",
    "addr:postcode":"1230",
    "addr:street":"Rudolf-Waisenhorn-G",
    "iso:country":"AT",
    "sg:address":"Rudolf-Waisenhorn-G 20a",
    "sg:city":"Wien",
    "sg:orig_category":"Autospenglereien",
    "sg:phone":"+43 1 8654382",
    "sg:postcode":"1230",
    "sg:province":"Wien",
    "wof:name":"Huber Herbert",
    "wof:placetype":"venue"
},
  "geometry": {"coordinates":[16.2840518951,48.1377868652],"type":"Point"}
}