{
  "type": "Feature",
  "properties": {
    "addr:full":"Unionstr 72 Linz Ober\u00f6sterreich 4020",
    "addr:housenumber":"72",
    "addr:postcode":"4020",
    "addr:street":"Unionstr",
    "iso:country":"AT",
    "sg:address":"Unionstr 72",
    "sg:city":"Linz",
    "sg:orig_category":"Pizzazustellungen",
    "sg:phone":"+43 4350 1010",
    "sg:postcode":"4020",
    "sg:province":"Ober\u00f6sterreich",
    "sg:website":"pizzamann.at",
    "wof:name":"Pizza Mann",
    "wof:placetype":"venue"
},
  "geometry": {"coordinates":[14.290137291,48.2836990356],"type":"Point"}
}