{
  "type": "Feature",
  "properties": {
    "addr:full":"Neue Schule 1 Ulrichskirchen Nieder\u00f6sterreich 2122",
    "addr:housenumber":"1",
    "addr:postcode":"2122",
    "addr:street":"Neue Schule",
    "iso:country":"AT",
    "sg:address":"Neue Schule 1",
    "sg:city":"Ulrichskirchen",
    "sg:orig_category":"Volksschulen",
    "sg:phone":"+43 2245 83018",
    "sg:postcode":"2122",
    "sg:province":"Nieder\u00f6sterreich",
    "wof:name":"Volksschule",
    "wof:placetype":"venue"
},
  "geometry": {"coordinates":[16.4932956696,48.4132575989],"type":"Point"}
}