{
  "type": "Feature",
  "properties": {
    "addr:full":"Wallensteinstr 35 Wien Wien 1200",
    "addr:housenumber":"35",
    "addr:postcode":"1200",
    "addr:street":"Wallensteinstr",
    "iso:country":"AT",
    "sg:address":"Wallensteinstr 35",
    "sg:city":"Wien",
    "sg:orig_category":"Textilreinigung",
    "sg:phone":"+43 1 3327403",
    "sg:postcode":"1200",
    "sg:province":"Wien",
    "wof:name":"Kaiser Rudolf GesmbH & Co KG",
    "wof:placetype":"venue"
},
  "geometry": {"coordinates":[16.3725242615,48.2304763794],"type":"Point"}
}