{
  "type": "Feature",
  "properties": {
    "iso:country":"AT",
    "sg:address":"Am Kuhberg 5 EKZ Horn",
    "sg:city":"Horn",
    "sg:classifiers":[
        {
            "category":"Restaurant",
            "type":"Food & Drink"
        }
    ],
    "sg:phone":"+43 4329 8230290",
    "sg:postcode":"3580",
    "sg:province":"Nieder\u00f6sterreich",
    "sg:tags":[
        "pizzeria"
    ],
    "wof:name":"Lekka Pizza & Bar",
    "wof:placetype":"venue"
},
  "geometry": {"coordinates":[15.6574287415,48.6637763977],"type":"Point"}
}