{
  "type": "Feature",
  "properties": {
    "iso:country":"AT",
    "sg:address":"Walter-Rudolf-Str 1",
    "sg:city":"Korneuburg",
    "sg:orig_category":"Autohandel",
    "sg:phone":"+43 4322 6268741",
    "sg:postcode":"2100",
    "sg:province":"Nieder\u00f6sterreich",
    "wof:name":"Jurkovic Michael",
    "wof:placetype":"venue"
},
  "geometry": {"coordinates":[16.3028507233,48.3651695251],"type":"Point"}
}