{
  "type": "Feature",
  "properties": {
    "addr:full":"S\u00e4gerweg 1 Klaus-Weiler Vorarlberg 6833",
    "addr:housenumber":"1",
    "addr:postcode":"6833",
    "addr:street":"Saegerweg",
    "iso:country":"AT",
    "sg:address":"S\u00e4gerweg 1",
    "sg:city":"Klaus-Weiler",
    "sg:orig_category":"Erdbau",
    "sg:phone":"+43 4355 2355007",
    "sg:postcode":"6833",
    "sg:province":"Vorarlberg",
    "wof:name":"Ludescher Armin",
    "wof:placetype":"venue"
},
  "geometry": {"coordinates":[9.652050972,47.3041305542],"type":"Point"}
}