{
  "type": "Feature",
  "properties": {
    "addr:full":"Maitschern 82 W\u00f6rschach Steiermark 8942",
    "addr:housenumber":"82",
    "addr:postcode":"8942",
    "addr:street":"Maitschern",
    "iso:country":"AT",
    "sg:address":"Maitschern 82",
    "sg:city":"W\u00f6rschach",
    "sg:orig_category":"Glasereien",
    "sg:phone":"+43 3682 25863",
    "sg:postcode":"8942",
    "sg:province":"Steiermark",
    "wof:name":"Glas Design - Walter Pracher",
    "wof:placetype":"venue"
},
  "geometry": {"coordinates":[14.1389322281,47.5462226868],"type":"Point"}
}