{
  "type": "Feature",
  "properties": {
    "addr:full":"Kniewas 17 St. Pankraz Ober\u00f6sterreich 4572",
    "addr:housenumber":"17",
    "addr:postcode":"4572",
    "addr:street":"Kniewas",
    "iso:country":"AT",
    "sg:address":"Kniewas 17",
    "sg:city":"St. Pankraz",
    "sg:orig_category":"Tourismusunternehmen",
    "sg:phone":"+43 4375 6531333",
    "sg:postcode":"4572",
    "sg:province":"Ober\u00f6sterreich",
    "wof:name":"Tourismusverband Klaus Steyrling Kniewas",
    "wof:placetype":"venue"
},
  "geometry": {"coordinates":[14.1707201004,47.7713508606],"type":"Point"}
}