{
  "type": "Feature",
  "properties": {
    "iso:country":"AT",
    "sg:address":"Wiener Str 47",
    "sg:city":"Friedberg",
    "sg:orig_category":"Elektrische Heizungen",
    "sg:phone":"+43 3339 24466",
    "sg:postcode":"8240",
    "sg:province":"Steiermark",
    "wof:name":"T-W-A Austria Elektrospeicherheizungen",
    "wof:placetype":"venue"
},
  "geometry": {"coordinates":[16.0580654144,47.4416236877],"type":"Point"}
}