{
  "type": "Feature",
  "properties": {
    "iso:country":"AT",
    "sg:address":"Alexander-Moser-Allee 13",
    "sg:city":"Bad Hofgastein",
    "sg:orig_category":"Friseure U Frisiersalons",
    "sg:phone":"+43 4364 327333",
    "sg:postcode":"5630",
    "sg:province":"Salzburg",
    "wof:name":"Hohenbergers Hair Design Inh Hans-Peter Hohenberger",
    "wof:placetype":"venue"
},
  "geometry": {"coordinates":[13.1078672409,47.1671867371],"type":"Point"}
}