{
  "type": "Feature",
  "properties": {
    "addr:full":"Holz 34 Behamberg Nieder\u00f6sterreich 4441",
    "addr:housenumber":"34",
    "addr:postcode":"4441",
    "addr:street":"Holz",
    "iso:country":"AT",
    "sg:address":"Holz 34",
    "sg:city":"Behamberg",
    "sg:orig_category":"Fliesen- U Plattenverlegungen",
    "sg:phone":"+43 7252 37012",
    "sg:postcode":"4441",
    "sg:province":"Nieder\u00f6sterreich",
    "wof:name":"Seyrlehner Max",
    "wof:placetype":"venue"
},
  "geometry": {"coordinates":[14.4762887955,48.0659141541],"type":"Point"}
}