{
  "type": "Feature",
  "properties": {
    "iso:country":"AT",
    "sg:address":"Auenfischerstrasse 38",
    "sg:city":"Wolfsberg",
    "sg:classifiers":[
        {
            "category":"Wholesale",
            "subcategory":"Construction Materials",
            "type":"Manufacturing & Wholesale Goods"
        }
    ],
    "sg:phone":"+43 4352 52473",
    "sg:postcode":"9400",
    "sg:province":"K\u00e4rnten",
    "sg:tags":[
        "dry",
        "system"
    ],
    "wof:name":"LICO-Isolierbau GmbH",
    "wof:placetype":"venue"
},
  "geometry": {"coordinates":[14.8431510925,46.8180351257],"type":"Point"}
}