{
  "type": "Feature",
  "properties": {
    "addr:full":"Eduard-Baumgartner-Str 16 Salzburg Salzburg 5020",
    "addr:housenumber":"16",
    "addr:postcode":"5020",
    "addr:street":"Eduard-Baumgartner-Str;Salzburg",
    "iso:country":"AT",
    "sg:address":"Eduard-Baumgartner-Str 16",
    "sg:city":"Salzburg",
    "sg:orig_category":"Finanz- U Wirtschaftsberatung",
    "sg:phone":"+43 4366 28415160",
    "sg:postcode":"5020",
    "sg:province":"Salzburg",
    "wof:name":"AIC Allgemeine Industrie Consulting GmbH",
    "wof:placetype":"venue"
},
  "geometry": {"coordinates":[13.0310144424,47.7995414734],"type":"Point"}
}