{
  "type": "Feature",
  "properties": {
    "addr:full":"Breunerg 27 G\u00f6sting Steiermark 8051",
    "addr:housenumber":"27",
    "addr:postcode":"8051",
    "addr:street":"Breunerg",
    "iso:country":"AT",
    "sg:address":"Breunerg 27",
    "sg:city":"G\u00f6sting",
    "sg:orig_category":"Exporteure U Importeure",
    "sg:phone":"+43 4331 6685539",
    "sg:postcode":"8051",
    "sg:province":"Steiermark",
    "wof:name":"RES HandelsgesmbH",
    "wof:placetype":"venue"
},
  "geometry": {"coordinates":[15.3983802795,47.0984611511],"type":"Point"}
}