{
  "type": "Feature",
  "properties": {
    "iso:country":"AT",
    "sg:address":"Garnisong 6/7A",
    "sg:city":"Wien",
    "sg:orig_category":"Webdesign",
    "sg:phone":"+43 1 2760897",
    "sg:postcode":"1090",
    "sg:province":"Wien",
    "wof:name":"meproduktion webdesign + corporate identity",
    "wof:placetype":"venue"
},
  "geometry": {"coordinates":[16.3568191528,48.2153053284],"type":"Point"}
}