{
  "type": "Feature",
  "properties": {
    "addr:full":"Nr 53 Virgen Tirol 9972",
    "addr:postcode":"9972",
    "addr:street":"Nr;Virgen Tirol",
    "iso:country":"AT",
    "sg:address":"Nr 53",
    "sg:city":"Virgen",
    "sg:orig_category":"Baumeister",
    "sg:phone":"+43 4348 7420040",
    "sg:postcode":"9972",
    "sg:province":"Tirol",
    "wof:name":"PB - BAU Baumeister Ing Paul Bacher",
    "wof:placetype":"venue"
},
  "geometry": {"coordinates":[12.4572124481,47.0033531189],"type":"Point"}
}