{
  "type": "Feature",
  "properties": {
    "addr:full":"Schmalkr\u00e4ftengasse 8 Purbach am Neusiedler See Burgenland 7083",
    "addr:housenumber":"8",
    "addr:postcode":"7083",
    "addr:street":"Schmalkraeftengasse",
    "iso:country":"AT",
    "sg:address":"Schmalkr\u00e4ftengasse 8",
    "sg:city":"Purbach am Neusiedler See",
    "sg:orig_category":"Canalisation",
    "sg:phone":"+43 2683 3492",
    "sg:postcode":"7083",
    "sg:province":"Burgenland",
    "wof:name":"EFN Bau GesmbH & Co KG",
    "wof:placetype":"venue"
},
  "geometry": {"coordinates":[16.6943721771,47.9160118103],"type":"Point"}
}