{
  "type": "Feature",
  "properties": {
    "addr:full":"Albrechtser Str 7a Gm\u00fcnd Nieder\u00f6sterreich 3950",
    "addr:postcode":"3950",
    "addr:street":"Str 7A Gmuend",
    "iso:country":"AT",
    "sg:address":"Albrechtser Str 7a",
    "sg:city":"Gm\u00fcnd",
    "sg:orig_category":"Reifen U Reifendienste",
    "sg:phone":"+43 2852 531910",
    "sg:postcode":"3950",
    "sg:province":"Nieder\u00f6sterreich",
    "wof:name":"Profi Reifen- und Autoservice GesmbH",
    "wof:placetype":"venue"
},
  "geometry": {"coordinates":[14.9883413315,48.7615013123],"type":"Point"}
}