{
  "type": "Feature",
  "properties": {
    "addr:full":"K\u00f6nig-Carol-Weg 4 Bad Gastein Salzburg 5640",
    "addr:housenumber":"4",
    "addr:postcode":"5640",
    "addr:street":"Koenig-Carol-Weg;Salzburg",
    "iso:country":"AT",
    "sg:address":"K\u00f6nig-Carol-Weg 4",
    "sg:city":"Bad Gastein",
    "sg:orig_category":"Pensionen / Privatzimmer",
    "sg:phone":"+43 6434 28820",
    "sg:postcode":"5640",
    "sg:province":"Salzburg",
    "wof:name":"Frohsinn Tanzcafe-Pension",
    "wof:placetype":"venue"
},
  "geometry": {"coordinates":[13.142988205,47.1231193542],"type":"Point"}
}