{
  "type": "Feature",
  "properties": {
    "iso:country":"AT",
    "sg:address":"Unter der Leithen 13",
    "sg:city":"Waidhofen an der Ybbs",
    "sg:orig_category":"Fassbindereien",
    "sg:phone":"+43 4374 4254513",
    "sg:postcode":"3340",
    "sg:province":"Nieder\u00f6sterreich",
    "wof:name":"Schneckenleitner Herbert",
    "wof:placetype":"venue"
},
  "geometry": {"coordinates":[14.7775363922,47.9595108032],"type":"Point"}
}