{
  "type": "Feature",
  "properties": {
    "addr:full":"Strebersdorfer Str 44 Langenzersdorf Nieder\u00f6sterreich 2103",
    "addr:postcode":"2103",
    "addr:street":"Str 44",
    "iso:country":"AT",
    "sg:address":"Strebersdorfer Str 44",
    "sg:city":"Langenzersdorf",
    "sg:orig_category":"Schilder",
    "sg:phone":"+43 2244 4490",
    "sg:postcode":"2103",
    "sg:province":"Nieder\u00f6sterreich",
    "wof:name":"Just Franz & S\u00f6hne",
    "wof:placetype":"venue"
},
  "geometry": {"coordinates":[16.3768234253,48.3000602722],"type":"Point"}
}