{
  "type": "Feature",
  "properties": {
    "iso:country":"AT",
    "sg:address":"Aspersdorfer Str 11",
    "sg:city":"Hollabrunn",
    "sg:orig_category":"Fliesen U Platten",
    "sg:phone":"+43 2952 22880",
    "sg:postcode":"2020",
    "sg:province":"Nieder\u00f6sterreich",
    "wof:name":"Schuster H KEG",
    "wof:placetype":"venue"
},
  "geometry": {"coordinates":[16.0783004761,48.5624580383],"type":"Point"}
}