{
  "type": "Feature",
  "properties": {
    "iso:country":"AT",
    "sg:address":"St. Peter-Hauptstra\u00dfe 98",
    "sg:city":"St. Peter",
    "sg:orig_category":"Immobilien U Baugewerbe, Bauhandwerk",
    "sg:phone":"+43 4303 16475363",
    "sg:postcode":"8042",
    "sg:province":"Steiermark",
    "sg:website":"http://www.kk-inter.net/Baubiologie/",
    "wof:name":"Haus der Baubiologie",
    "wof:placetype":"venue"
},
  "geometry": {"coordinates":[15.4779205322,47.0511703491],"type":"Point"}
}