{
  "type": "Feature",
  "properties": {
    "iso:country":"AT",
    "sg:address":"Krimpling 329",
    "sg:city":"Wals",
    "sg:orig_category":"Behinderungen / Leben Mit Behinderungen",
    "sg:phone":"+43 662 8503390",
    "sg:postcode":"5071",
    "sg:province":"Salzburg",
    "wof:name":"Lebenshilfe Salzburg gemeinn\u00fctzige GmbH",
    "wof:placetype":"venue"
},
  "geometry": {"coordinates":[12.9719104767,47.7888031006],"type":"Point"}
}