{
  "type": "Feature",
  "properties": {
    "addr:full":"Arnold Holm-G 1/21 Wien Wien 1100",
    "addr:housenumber":"1 / 21",
    "addr:postcode":"1100",
    "iso:country":"AT",
    "sg:address":"Arnold Holm-G 1/21",
    "sg:city":"Wien",
    "sg:classifiers":[
        {
            "category":"Taxi",
            "type":"Transportation"
        }
    ],
    "sg:phone":"+43 676 3004901",
    "sg:postcode":"1100",
    "sg:province":"Wien",
    "sg:tags":[
        "personentransporte",
        "u"
    ],
    "wof:name":"Schulz Ronald",
    "wof:placetype":"venue"
},
  "geometry": {"coordinates":[16.3853797913,48.1470947266],"type":"Point"}
}