{
  "type": "Feature",
  "properties": {
    "addr:full":"Feldkirchner Str 82 Klagenfurt K\u00e4rnten 9020",
    "addr:housenumber":"82",
    "addr:postcode":"9020",
    "addr:street":"Str;Kaernten",
    "iso:country":"AT",
    "sg:address":"Feldkirchner Str 82",
    "sg:city":"Klagenfurt",
    "sg:orig_category":"Medizinische Institute",
    "sg:phone":"+43 4346 34466440",
    "sg:postcode":"9020",
    "sg:province":"K\u00e4rnten",
    "wof:name":"Celedin Alfred Dr",
    "wof:placetype":"venue"
},
  "geometry": {"coordinates":[14.2955465317,46.6356506348],"type":"Point"}
}