{
  "type": "Feature",
  "properties": {
    "addr:full":"Schwendaustr 197a Mayrhofen Tirol 6290",
    "addr:housenumber":"197a",
    "addr:postcode":"6290",
    "addr:street":"Mayrhofen Tirol",
    "iso:country":"AT",
    "sg:address":"Schwendaustr 197a",
    "sg:city":"Mayrhofen",
    "sg:classifiers":[
        {
            "category":"Restaurant",
            "type":"Food & Drink"
        }
    ],
    "sg:phone":"+43 5285 62791",
    "sg:postcode":"6290",
    "sg:province":"Tirol",
    "wof:name":"Restaurant Tiroler Stub'n",
    "wof:placetype":"venue"
},
  "geometry": {"coordinates":[11.8630952835,47.1702690125],"type":"Point"}
}