{
  "type": "Feature",
  "properties": {
    "addr:full":"L\u00e4rchenhofweg 9 Radstadt Salzburg 5550",
    "addr:housenumber":"9",
    "addr:postcode":"5550",
    "addr:street":"Laerchenhofweg;Salzburg",
    "iso:country":"AT",
    "sg:address":"L\u00e4rchenhofweg 9",
    "sg:city":"Radstadt",
    "sg:orig_category":"Friseure U Frisiersalons",
    "sg:phone":"+43 6452 7130",
    "sg:postcode":"5550",
    "sg:province":"Salzburg",
    "wof:name":"Hubacek Ingrid",
    "wof:placetype":"venue"
},
  "geometry": {"coordinates":[13.4623041153,47.3886260986],"type":"Point"}
}