{
  "type": "Feature",
  "properties": {
    "addr:full":"Grabenstr 248 Andritz Steiermark 8045",
    "addr:housenumber":"248",
    "addr:postcode":"8045",
    "iso:country":"AT",
    "sg:address":"Grabenstr 248",
    "sg:city":"Andritz",
    "sg:orig_category":"Tankstellen",
    "sg:phone":"+43 316 682370",
    "sg:postcode":"8045",
    "sg:province":"Steiermark",
    "wof:name":"Esso Austria GmbH",
    "wof:placetype":"venue"
},
  "geometry": {"coordinates":[15.4193000793,47.0973205566],"type":"Point"}
}