{
  "type": "Feature",
  "properties": {
    "iso:country":"AT",
    "sg:address":"Waidmannsdorfer Str 135",
    "sg:city":"Klagenfurt",
    "sg:orig_category":"Lebensmittel / Einzelhandel",
    "sg:phone":"+43 4346 3261145",
    "sg:postcode":"9020",
    "sg:province":"K\u00e4rnten",
    "wof:name":"Hofer KG",
    "wof:placetype":"venue"
},
  "geometry": {"coordinates":[14.2912340164,46.6079101562],"type":"Point"}
}