{
  "type": "Feature",
  "properties": {
    "addr:full":"Lilieng 5 B\u00f6heimkirchen Nieder\u00f6sterreich 3071",
    "addr:housenumber":"5",
    "addr:postcode":"3071",
    "addr:street":"Lilieng;Niederoesterreich",
    "iso:country":"AT",
    "sg:address":"Lilieng 5",
    "sg:city":"B\u00f6heimkirchen",
    "sg:orig_category":"Filmproduktionen",
    "sg:phone":"+43 699 18947044",
    "sg:postcode":"3071",
    "sg:province":"Nieder\u00f6sterreich",
    "wof:name":"In Motion Filmproduktion Hans Pusswald",
    "wof:placetype":"venue"
},
  "geometry": {"coordinates":[7.7127490044,49.574382782],"type":"Point"}
}