{
  "type": "Feature",
  "properties": {
    "addr:full":"Kleinpertholz 65 Heidenreichstein Nieder\u00f6sterreich 3860",
    "addr:housenumber":"65",
    "addr:postcode":"3860",
    "addr:street":"Kleinpertholz",
    "iso:country":"AT",
    "sg:address":"Kleinpertholz 65",
    "sg:city":"Heidenreichstein",
    "sg:classifiers":[
        {
            "category":"Manufacturing",
            "subcategory":"Textiles",
            "type":"Manufacturing & Wholesale Goods"
        }
    ],
    "sg:phone":"+43 2862 52455",
    "sg:postcode":"3860",
    "sg:province":"Nieder\u00f6sterreich",
    "sg:tags":[
        "towel",
        "bath"
    ],
    "sg:website":"framsohn.at",
    "wof:name":"Framsohn- Frottier Amstetter Ges.m.b.H.",
    "wof:placetype":"venue"
},
  "geometry": {"coordinates":[15.1014652252,48.8576660156],"type":"Point"}
}