{
  "type": "Feature",
  "properties": {
    "iso:country":"AT",
    "sg:address":"Elisabethstr 31",
    "sg:city":"Graz",
    "sg:orig_category":"\u00c3\u201erzte / F Allgemeinmedizin",
    "sg:phone":"+43 316 386024",
    "sg:postcode":"8010",
    "sg:province":"Steiermark",
    "sg:website":"arco-vital.at",
    "wof:name":"Arco Dagmar Dr med",
    "wof:placetype":"venue"
},
  "geometry": {"coordinates":[15.4516096115,47.0750312805],"type":"Point"}
}