{
  "type": "Feature",
  "properties": {
    "addr:full":"Rathausplatz Dornbirn Vorarlberg 6850",
    "addr:postcode":"6850",
    "addr:street":"Rathausplatz",
    "iso:country":"AT",
    "sg:address":"Rathausplatz",
    "sg:city":"Dornbirn",
    "sg:classifiers":[
        {
            "category":"Banks & Credit Unions",
            "subcategory":"Bank",
            "type":"Services"
        }
    ],
    "sg:phone":"+43 4355 7238180",
    "sg:postcode":"6850",
    "sg:province":"Vorarlberg",
    "sg:tags":[
        "banking",
        "institution"
    ],
    "wof:name":"RAIFFEISENBANK DORNBIRN",
    "wof:placetype":"venue"
},
  "geometry": {"coordinates":[9.7440252304,47.413105011],"type":"Point"}
}