{
  "type": "Feature",
  "properties": {
    "addr:full":"H\u00f6ferweg 5 Neufelden Ober\u00f6sterreich 4120",
    "addr:housenumber":"5",
    "addr:postcode":"4120",
    "addr:street":"Hoeferweg",
    "iso:country":"AT",
    "sg:address":"H\u00f6ferweg 5",
    "sg:city":"Neufelden",
    "sg:orig_category":"Glasereien",
    "sg:phone":"+43 7282 5015",
    "sg:postcode":"4120",
    "sg:province":"Ober\u00f6sterreich",
    "wof:name":"Glas Falkner GmbH",
    "wof:placetype":"venue"
},
  "geometry": {"coordinates":[13.9973993301,48.483455658],"type":"Point"}
}