{
  "type": "Feature",
  "properties": {
    "addr:full":"Karolineng 22 Wien Wien 1040",
    "addr:housenumber":"22",
    "addr:postcode":"1040",
    "addr:street":"Karolineng",
    "iso:country":"AT",
    "sg:address":"Karolineng 22",
    "sg:city":"Wien",
    "sg:orig_category":"Immobilienmakler",
    "sg:phone":"+43 1 79629590",
    "sg:postcode":"1040",
    "sg:province":"Wien",
    "wof:name":"Aktivreal Immobilien VermittlungsgesmbH",
    "wof:placetype":"venue"
},
  "geometry": {"coordinates":[16.3745231628,48.1902580261],"type":"Point"}
}