{
  "type": "Feature",
  "properties": {
    "iso:country":"AT",
    "sg:address":"Hilfberg 36",
    "sg:city":"Mondsee",
    "sg:orig_category":"Psychologen",
    "sg:phone":"+43 6232 3530",
    "sg:postcode":"5310",
    "sg:province":"Ober\u00f6sterreich",
    "wof:name":"Schwanner Karin Dr phil",
    "wof:placetype":"venue"
},
  "geometry": {"coordinates":[13.3584957123,47.8536491394],"type":"Point"}
}