{
  "type": "Feature",
  "properties": {
    "addr:full":"Salzburger Str 142 Wels Ober\u00f6sterreich 4600",
    "addr:housenumber":"142",
    "addr:postcode":"4600",
    "addr:street":"Salzburger Str;Oberoesterreich",
    "iso:country":"AT",
    "sg:address":"Salzburger Str 142",
    "sg:city":"Wels",
    "sg:orig_category":"Schuhreparatur",
    "sg:phone":"+43 4365 08138282",
    "sg:postcode":"4600",
    "sg:province":"Ober\u00f6sterreich",
    "wof:name":"Schulz Johann Best Service -Schuhe & Taschen",
    "wof:placetype":"venue"
},
  "geometry": {"coordinates":[14.0035905838,48.1565704346],"type":"Point"}
}