{
  "type": "Feature",
  "properties": {
    "addr:full":"Hernalser Hauptstr 96 Wien Wien 1170",
    "addr:housenumber":"96",
    "addr:postcode":"1170",
    "addr:street":"Hernalser Hauptstr",
    "iso:country":"AT",
    "sg:address":"Hernalser Hauptstr 96",
    "sg:city":"Wien",
    "sg:orig_category":"Juwelen, Gold- U Silberwaren / Einzelhandel",
    "sg:phone":"+43 4314 868369",
    "sg:postcode":"1170",
    "sg:province":"Wien",
    "wof:name":"Wolf Alexander",
    "wof:placetype":"venue"
},
  "geometry": {"coordinates":[16.3280296326,48.2190055847],"type":"Point"}
}