{
  "type": "Feature",
  "properties": {
    "iso:country":"AT",
    "sg:address":"Au bei Brandstatt 8a",
    "sg:city":"Eferding",
    "sg:orig_category":"Raumausstattung",
    "sg:phone":"+43 7272 3144",
    "sg:postcode":"4070",
    "sg:province":"Ober\u00f6sterreich",
    "wof:name":"Raumausstattung Wiesinger GmbH",
    "wof:placetype":"venue"
},
  "geometry": {"coordinates":[14.0137748718,48.3373451233],"type":"Point"}
}