{
  "type": "Feature",
  "properties": {
    "addr:full":"Au bei Brandstatt 8a Eferding Ober\u00f6sterreich 4070",
    "addr:housenumber":"8a",
    "addr:postcode":"4070",
    "addr:street":"Au Bei Brandstatt",
    "iso:country":"AT",
    "sg:address":"Au bei Brandstatt 8a",
    "sg:city":"Eferding",
    "sg:orig_category":"Raumausstattung",
    "sg:phone":"+43 7272 3144",
    "sg:postcode":"4070",
    "sg:province":"Ober\u00f6sterreich",
    "wof:name":"Raumausstattung Wiesinger GmbH",
    "wof:placetype":"venue"
},
  "geometry": {"coordinates":[14.0137748718,48.3373451233],"type":"Point"}
}