{
  "type": "Feature",
  "properties": {
    "addr:full":"Ortsstr 3A Biedermannsdorf Nieder\u00f6sterreich 2362",
    "addr:housenumber":"3a",
    "addr:postcode":"2362",
    "addr:street":"Ortsstr",
    "iso:country":"AT",
    "sg:address":"Ortsstr 3A",
    "sg:city":"Biedermannsdorf",
    "sg:orig_category":"Unterhaltungselektronik / Reparatur",
    "sg:phone":"+43 2236 73118",
    "sg:postcode":"2362",
    "sg:province":"Nieder\u00f6sterreich",
    "wof:name":"Rief Electronic Service",
    "wof:placetype":"venue"
},
  "geometry": {"coordinates":[16.3520946503,48.0827026367],"type":"Point"}
}