{
  "type": "Feature",
  "properties": {
    "iso:country":"AT",
    "sg:address":"Haupt Str. 117 ",
    "sg:city":"Ladendorf",
    "sg:classifiers":[
        {
            "category":"Farming",
            "subcategory":"Livestock Farm",
            "type":"Manufacturing & Wholesale Goods"
        }
    ],
    "sg:phone":"+43 4325 752290",
    "sg:postcode":"2126",
    "sg:province":"Nieder\u00f6sterreich",
    "sg:tags":[
        "agriculture"
    ],
    "wof:name":"RUPP GES.MBH & CO KG",
    "wof:placetype":"venue"
},
  "geometry": {"coordinates":[16.4798126221,48.5322761536],"type":"Point"}
}