{
  "type": "Feature",
  "properties": {
    "iso:country":"AT",
    "sg:address":"Friedrich-Hebbel-G 4",
    "sg:city":"Graz",
    "sg:orig_category":"Immobilienverwaltungen",
    "sg:phone":"+43 316 8302510",
    "sg:postcode":"8010",
    "sg:province":"Steiermark",
    "sg:website":"immobilien-huber.at",
    "wof:name":"Huber Rudolf",
    "wof:placetype":"venue"
},
  "geometry": {"coordinates":[15.4584779739,47.0663566589],"type":"Point"}
}