{
  "type": "Feature",
  "properties": {
    "addr:full":"Steyrer Str 18 Weyer Ober\u00f6sterreich 3335",
    "addr:housenumber":"18",
    "addr:postcode":"3335",
    "addr:street":"Str",
    "iso:country":"AT",
    "sg:address":"Steyrer Str 18",
    "sg:city":"Weyer",
    "sg:orig_category":"Tischlereien",
    "sg:phone":"+43 7355 6224",
    "sg:postcode":"3335",
    "sg:province":"Ober\u00f6sterreich",
    "wof:name":"Hen\u00f6ckl Daniel",
    "wof:placetype":"venue"
},
  "geometry": {"coordinates":[14.6481456757,47.8535957336],"type":"Point"}
}