{
  "type": "Feature",
  "properties": {
    "addr:full":"Kinostr 3 Schneegattern Ober\u00f6sterreich 5212",
    "addr:housenumber":"3",
    "addr:postcode":"5212",
    "addr:street":"Kinostr",
    "iso:country":"AT",
    "sg:address":"Kinostr 3",
    "sg:city":"Schneegattern",
    "sg:orig_category":"Glasbe- U -Verarbeitung",
    "sg:phone":"+43 7746 3114",
    "sg:postcode":"5212",
    "sg:province":"Ober\u00f6sterreich",
    "wof:name":"B\u00f6hm Ernst",
    "wof:placetype":"venue"
},
  "geometry": {"coordinates":[13.294301033,48.0252685547],"type":"Point"}
}