{
  "type": "Feature",
  "properties": {
    "addr:full":"Klagenfurter Str 42 Villach K\u00e4rnten 9500",
    "addr:housenumber":"42",
    "addr:postcode":"9500",
    "addr:street":"Str;Kaernten",
    "iso:country":"AT",
    "sg:address":"Klagenfurter Str 42",
    "sg:city":"Villach",
    "sg:orig_category":"Wasserschadensanierung",
    "sg:phone":"+43 4342 4222929",
    "sg:postcode":"9500",
    "sg:province":"K\u00e4rnten",
    "wof:name":"MUNTERS Austria GmbH",
    "wof:placetype":"venue"
},
  "geometry": {"coordinates":[13.8539562225,46.6182518005],"type":"Point"}
}