{
  "type": "Feature",
  "properties": {
    "addr:full":"Markt 106 Kuchl Salzburg 5431",
    "addr:housenumber":"106",
    "addr:postcode":"5431",
    "addr:street":"Markt;Salzburg",
    "iso:country":"AT",
    "sg:address":"Markt 106",
    "sg:city":"Kuchl",
    "sg:orig_category":"Musikunterricht",
    "sg:phone":"+43 6244 77600",
    "sg:postcode":"5431",
    "sg:province":"Salzburg",
    "wof:name":"Musikschule Tennengau 2",
    "wof:placetype":"venue"
},
  "geometry": {"coordinates":[13.1441526413,47.6261138916],"type":"Point"}
}