{
  "type": "Feature",
  "properties": {
    "addr:full":"Heidlmayrweg 2 Bad Hall Ober\u00f6sterreich 4540",
    "addr:housenumber":"2",
    "addr:postcode":"4540",
    "addr:street":"Heidlmayrweg",
    "iso:country":"AT",
    "sg:address":"Heidlmayrweg 2",
    "sg:city":"Bad Hall",
    "sg:orig_category":"Wasseraufbereitung U -Reinigung",
    "sg:phone":"+43 4372 583040",
    "sg:postcode":"4540",
    "sg:province":"Ober\u00f6sterreich",
    "wof:name":"Fazeni Wassertechnologie ''feel good'' Produkte f\u00fcr ein gesundes Leben",
    "wof:placetype":"venue"
},
  "geometry": {"coordinates":[14.2007570267,48.0283050537],"type":"Point"}
}