{
  "type": "Feature",
  "properties": {
    "iso:country":"AT",
    "sg:address":"Gumppstr 55",
    "sg:city":"Innsbruck",
    "sg:orig_category":"Fotografen",
    "sg:phone":"+43 512 341271",
    "sg:postcode":"6020",
    "sg:province":"Tirol",
    "wof:name":"Foto Eliskases",
    "wof:placetype":"venue"
},
  "geometry": {"coordinates":[11.4145717621,47.2656440735],"type":"Point"}
}