{
  "type": "Feature",
  "properties": {
    "addr:full":"Hofkirchenstr 1 Salzburg Salzburg 5020",
    "addr:housenumber":"1",
    "addr:postcode":"5020",
    "addr:street":"Hofkirchenstr;Salzburg",
    "iso:country":"AT",
    "sg:address":"Hofkirchenstr 1",
    "sg:city":"Salzburg",
    "sg:classifiers":[
        {
            "category":"Internet Cafe",
            "subcategory":"None",
            "type":"Food & Drink"
        }
    ],
    "sg:phone":"+43 662 823651",
    "sg:postcode":"5020",
    "sg:province":"Salzburg",
    "wof:name":"Grill Franz - Netzwerkb\u00f6rse",
    "wof:placetype":"venue"
},
  "geometry": {"coordinates":[13.0503768921,47.7867126465],"type":"Point"}
}