{
  "type": "Feature",
  "properties": {
    "addr:full":"B\u00fcrg 4 Ternitz Nieder\u00f6sterreich 2630",
    "addr:housenumber":"4",
    "addr:postcode":"2630",
    "addr:street":"Buerg",
    "iso:country":"AT",
    "sg:address":"B\u00fcrg 4",
    "sg:city":"Ternitz",
    "sg:orig_category":"Garten- U Landschaftsgestaltung",
    "sg:phone":"+43 4367 66086895",
    "sg:postcode":"2630",
    "sg:province":"Nieder\u00f6sterreich",
    "wof:name":"Wodl & Mies OEG",
    "wof:placetype":"venue"
},
  "geometry": {"coordinates":[16.0209465027,47.7058067322],"type":"Point"}
}