{
  "type": "Feature",
  "properties": {
    "addr:full":"Beethoveng 41 Stockerau Nieder\u00f6sterreich 2000",
    "addr:housenumber":"41",
    "addr:postcode":"2000",
    "addr:street":"Beethoveng",
    "iso:country":"AT",
    "sg:address":"Beethoveng 41",
    "sg:city":"Stockerau",
    "sg:orig_category":"Rauchfangkehrer",
    "sg:phone":"+43 2266 65273",
    "sg:postcode":"2000",
    "sg:province":"Nieder\u00f6sterreich",
    "wof:name":"Seidl Wolfgang",
    "wof:placetype":"venue"
},
  "geometry": {"coordinates":[16.2187366486,48.3925285339],"type":"Point"}
}