{
  "type": "Feature",
  "properties": {
    "addr:full":"Murau Steiermark 8850",
    "addr:postcode":"8850",
    "iso:country":"AT",
    "sg:city":"Murau",
    "sg:orig_category":"Bergbahnen",
    "sg:phone":"+43 4335 3225550",
    "sg:postcode":"8850",
    "sg:province":"Steiermark",
    "wof:name":"Frauenalpe Lift GesmbH & Co KG",
    "wof:placetype":"venue"
},
  "geometry": {"coordinates":[14.1716346741,47.1107406616],"type":"Point"}
}