{
  "type": "Feature",
  "properties": {
    "iso:country":"AT",
    "sg:address":"Hauptstr 87",
    "sg:city":"Hagenberg im M\u00fchlkreis",
    "sg:orig_category":"Friseure U Frisiersalons",
    "sg:phone":"+43 4372 367010",
    "sg:postcode":"4232",
    "sg:province":"Ober\u00f6sterreich",
    "wof:name":"Zauner Norbert",
    "wof:placetype":"venue"
},
  "geometry": {"coordinates":[14.5186948776,48.3668289185],"type":"Point"}
}