{
  "type": "Feature",
  "properties": {
    "iso:country":"AT",
    "sg:address":"Nr 102",
    "sg:city":"Gro\u00dfwilfersdorf",
    "sg:orig_category":"Spenglereien",
    "sg:phone":"+43 3385 78010",
    "sg:postcode":"8263",
    "sg:province":"Steiermark",
    "wof:name":"Lagerhaus Gewerbebetriebe GmbH",
    "wof:placetype":"venue"
},
  "geometry": {"coordinates":[15.9948101044,47.0773239136],"type":"Point"}
}