{
  "type": "Feature",
  "properties": {
    "iso:country":"AT",
    "sg:address":"Hauptstr 59",
    "sg:city":"Neulengbach",
    "sg:orig_category":"Banken U Sparkassen",
    "sg:phone":"+43 2772 525750",
    "sg:postcode":"3040",
    "sg:province":"Nieder\u00f6sterreich",
    "wof:name":"Raiffeisenbank Neulengbach regGenmbH",
    "wof:placetype":"venue"
},
  "geometry": {"coordinates":[15.8699836731,48.1898918152],"type":"Point"}
}