{
  "type": "Feature",
  "properties": {
    "addr:full":"Paracelsusstr 2 Radenthein K\u00e4rnten 9545",
    "addr:housenumber":"2",
    "addr:postcode":"9545",
    "addr:street":"Paracelsusstr;Kaernten",
    "iso:country":"AT",
    "sg:address":"Paracelsusstr 2",
    "sg:city":"Radenthein",
    "sg:orig_category":"Apotheken",
    "sg:phone":"+43 4246 20550",
    "sg:postcode":"9545",
    "sg:province":"K\u00e4rnten",
    "wof:name":"Paracelsus-Apotheke Mag pharm Christina Herbrich",
    "wof:placetype":"venue"
},
  "geometry": {"coordinates":[13.6992111206,46.7990531921],"type":"Point"}
}