{
  "type": "Feature",
  "properties": {
    "addr:full":"Sparbersbachg 38 Graz Steiermark 8010",
    "addr:housenumber":"38",
    "addr:postcode":"8010",
    "addr:street":"Sparbersbachg",
    "iso:country":"AT",
    "sg:address":"Sparbersbachg 38",
    "sg:city":"Graz",
    "sg:classifiers":[
        {
            "category":"Retail",
            "subcategory":"Event Space",
            "type":"Services"
        }
    ],
    "sg:phone":"+43 4369 910361136",
    "sg:postcode":"8010",
    "sg:province":"Steiermark",
    "sg:tags":[
        "hand-",
        "u",
        "fu\u00c3\u0178pflege"
    ],
    "wof:name":"City Kosmetik",
    "wof:placetype":"venue"
},
  "geometry": {"coordinates":[15.4518299103,47.0681648254],"type":"Point"}
}