{
  "type": "Feature",
  "properties": {
    "iso:country":"AT",
    "sg:address":"Rofangarten 85",
    "sg:city":"Maurach",
    "sg:orig_category":"Pensionen / Privatzimmer",
    "sg:phone":"+43 4352 435383",
    "sg:postcode":"6212",
    "sg:province":"Tirol",
    "wof:name":"Fr\u00fchst\u00fcckspension Maria Unger",
    "wof:placetype":"venue"
},
  "geometry": {"coordinates":[11.7417268753,47.4292907715],"type":"Point"}
}