{
  "type": "Feature",
  "properties": {
    "iso:country":"AT",
    "sg:address":"Eduard-R\u00f6sch-Str 45",
    "sg:city":"Stockerau",
    "sg:orig_category":"Restaurants: Chinesisch",
    "sg:phone":"+43 2266 61175",
    "sg:postcode":"2000",
    "sg:province":"Nieder\u00f6sterreich",
    "wof:name":"China-Restaurant Sinohaus",
    "wof:placetype":"venue"
},
  "geometry": {"coordinates":[16.2238483429,48.3865432739],"type":"Point"}
}