{
  "type": "Feature",
  "properties": {
    "iso:country":"AT",
    "sg:address":"Magazinstr 10",
    "sg:city":"Wels",
    "sg:orig_category":"Lichttechnik",
    "sg:phone":"+43 7242 45862",
    "sg:postcode":"4600",
    "sg:province":"Ober\u00f6sterreich",
    "wof:name":"Vesovic & Co OEG Tontechnik - Lichttechnik Disco & Music Store",
    "wof:placetype":"venue"
},
  "geometry": {"coordinates":[14.0333251953,48.1646003723],"type":"Point"}
}