{
  "type": "Feature",
  "properties": {
    "addr:full":"Magazinstr 10 Wels Ober\u00f6sterreich 4600",
    "addr:housenumber":"10",
    "addr:postcode":"4600",
    "addr:street":"Magazinstr;Oberoesterreich",
    "iso:country":"AT",
    "sg:address":"Magazinstr 10",
    "sg:city":"Wels",
    "sg:orig_category":"Lichttechnik",
    "sg:phone":"+43 7242 45862",
    "sg:postcode":"4600",
    "sg:province":"Ober\u00f6sterreich",
    "wof:name":"Vesovic & Co OEG Tontechnik - Lichttechnik Disco & Music Store",
    "wof:placetype":"venue"
},
  "geometry": {"coordinates":[14.0333251953,48.1646003723],"type":"Point"}
}