{
  "type": "Feature",
  "properties": {
    "iso:country":"AT",
    "sg:address":"Carlbergerg. 68",
    "sg:city":"Wien",
    "sg:classifiers":[
        {
            "category":"Shopping",
            "subcategory":"Computers & Home Electronics",
            "type":"Retail Goods"
        }
    ],
    "sg:phone":"+43 4318 6935380",
    "sg:postcode":"1230",
    "sg:province":"Wien",
    "sg:tags":[
        "electronic",
        "electrical",
        "equipment"
    ],
    "wof:name":"TRILUX LEUCHTEN GESMBH",
    "wof:placetype":"venue"
},
  "geometry": {"coordinates":[16.3110637665,48.1408348083],"type":"Point"}
}