{
  "type": "Feature",
  "properties": {
    "addr:full":"Hinterberg 10 Hinterstoder Ober\u00f6sterreich 4573",
    "addr:housenumber":"10",
    "addr:postcode":"4573",
    "addr:street":"Hinterberg",
    "iso:country":"AT",
    "sg:address":"Hinterberg 10",
    "sg:city":"Hinterstoder",
    "sg:orig_category":"Appartements / Ferienwohnungen",
    "sg:phone":"+43 7564 5344",
    "sg:postcode":"4573",
    "sg:province":"Ober\u00f6sterreich",
    "wof:name":"Ferienhof Rinnergut Fam Prieler",
    "wof:placetype":"venue"
},
  "geometry": {"coordinates":[14.1314373016,47.6849784851],"type":"Point"}
}