{
  "type": "Feature",
  "properties": {
    "addr:full":"Nr 175 Strallegg Steiermark 8192",
    "addr:postcode":"8192",
    "addr:street":"Nr 175",
    "iso:country":"AT",
    "sg:address":"Nr 175",
    "sg:city":"Strallegg",
    "sg:orig_category":"Hauptschulen",
    "sg:phone":"+43 3174 2229",
    "sg:postcode":"8192",
    "sg:province":"Steiermark",
    "wof:name":"Hauptschule",
    "wof:placetype":"venue"
},
  "geometry": {"coordinates":[15.7248001099,47.4109153748],"type":"Point"}
}