{
  "type": "Feature",
  "properties": {
    "addr:full":"Quelleng 24 Lauterach Vorarlberg 6923",
    "addr:housenumber":"24",
    "addr:postcode":"6923",
    "addr:street":"Quelleng",
    "iso:country":"AT",
    "sg:address":"Quelleng 24",
    "sg:city":"Lauterach",
    "sg:orig_category":"Lebensmittel / Einzelhandel",
    "sg:phone":"+43 4355 748672020",
    "sg:postcode":"6923",
    "sg:province":"Vorarlberg",
    "wof:name":"Pichler Handels GesmbH",
    "wof:placetype":"venue"
},
  "geometry": {"coordinates":[9.7193717957,47.4765625],"type":"Point"}
}