{
  "type": "Feature",
  "properties": {
    "addr:full":"Kircheng 1 G\u00fcnselsdorf Nieder\u00f6sterreich 2525",
    "addr:housenumber":"1",
    "addr:postcode":"2525",
    "addr:street":"Kircheng;Niederoesterreich",
    "iso:country":"AT",
    "sg:address":"Kircheng 1",
    "sg:city":"G\u00fcnselsdorf",
    "sg:orig_category":"Tabaktrafiken",
    "sg:phone":"+43 4322 5663901",
    "sg:postcode":"2525",
    "sg:province":"Nieder\u00f6sterreich",
    "wof:name":"Wessiag Judith",
    "wof:placetype":"venue"
},
  "geometry": {"coordinates":[16.2538700104,47.9347572327],"type":"Point"}
}