{
  "type": "Feature",
  "properties": {
    "iso:country":"AT",
    "sg:address":"Strannersdorf 11",
    "sg:city":"Mank",
    "sg:classifiers":[
        {
            "category":"Wholesale",
            "subcategory":"Home Furnishings",
            "type":"Manufacturing & Wholesale Goods"
        }
    ],
    "sg:phone":"+43 2755 23830",
    "sg:postcode":"3240",
    "sg:province":"Nieder\u00f6sterreich",
    "sg:tags":[
        "chair"
    ],
    "sg:website":"san-design.at",
    "wof:name":"SAN-DESIGN Sandler & Co KG Polsterm\u00f6bel, Betten, St\u00fchle + Tische",
    "wof:placetype":"venue"
},
  "geometry": {"coordinates":[15.3293199539,48.1097755432],"type":"Point"}
}