{
  "type": "Feature",
  "properties": {
    "addr:full":"Haiden 60 Bad Ischl Ober\u00f6sterreich 4820",
    "addr:housenumber":"60",
    "addr:postcode":"4820",
    "addr:street":"Haiden",
    "iso:country":"AT",
    "sg:address":"Haiden 60",
    "sg:city":"Bad Ischl",
    "sg:orig_category":"Autoelektrik U -Ersatzteile",
    "sg:phone":"+43 4361 3223701",
    "sg:postcode":"4820",
    "sg:province":"Ober\u00f6sterreich",
    "wof:name":"Zewag KFZ Elektrik u Mechanik GmbH",
    "wof:placetype":"venue"
},
  "geometry": {"coordinates":[13.5800170898,47.7264595032],"type":"Point"}
}