{
  "type": "Feature",
  "properties": {
    "iso:country":"AT",
    "sg:address":"Haiden 60",
    "sg:city":"Bad Ischl",
    "sg:orig_category":"Autoelektrik U -Ersatzteile",
    "sg:phone":"+43 4361 3223701",
    "sg:postcode":"4820",
    "sg:province":"Ober\u00f6sterreich",
    "wof:name":"Zewag KFZ Elektrik u Mechanik GmbH",
    "wof:placetype":"venue"
},
  "geometry": {"coordinates":[13.5800170898,47.7264595032],"type":"Point"}
}