{
  "type": "Feature",
  "properties": {
    "addr:full":"Grazer Str 46 Mureck Steiermark 8480",
    "addr:postcode":"8480",
    "addr:street":"Str",
    "iso:country":"AT",
    "sg:address":"Grazer Str 46",
    "sg:city":"Mureck",
    "sg:classifiers":[
        {
            "category":"Home & Garden",
            "subcategory":"Building Materials",
            "type":"Retail Goods"
        }
    ],
    "sg:phone":"+43 4334 722106",
    "sg:postcode":"8480",
    "sg:province":"Steiermark",
    "sg:tags":[
        "baustoffe",
        "-material",
        "u"
    ],
    "wof:name":"Neubauer Karl",
    "wof:placetype":"venue"
},
  "geometry": {"coordinates":[15.7634353638,46.7066192627],"type":"Point"}
}