{
  "type": "Feature",
  "properties": {
    "iso:country":"AT",
    "sg:address":"Brucknerstr 4/2",
    "sg:city":"Wien",
    "sg:orig_category":"Schallplatten",
    "sg:phone":"+43 1 5048797",
    "sg:postcode":"1040",
    "sg:province":"Wien",
    "wof:name":"Waldmann Franz AG",
    "wof:placetype":"venue"
},
  "geometry": {"coordinates":[16.3746166229,48.199131012],"type":"Point"}
}