{
  "type": "Feature",
  "properties": {
    "iso:country":"AT",
    "sg:address":"Taubenweg 3",
    "sg:city":"Hard",
    "sg:orig_category":"Erdarbeiten",
    "sg:phone":"+43 5574 70334",
    "sg:postcode":"6971",
    "sg:province":"Vorarlberg",
    "wof:name":"Gasser Wolfgang",
    "wof:placetype":"venue"
},
  "geometry": {"coordinates":[9.690870285,47.4754180908],"type":"Point"}
}