{
  "type": "Feature",
  "properties": {
    "addr:full":"Josef-Egger-Str 3 Kufstein Tirol 6330",
    "addr:housenumber":"3",
    "addr:postcode":"6330",
    "addr:street":"Josef-Egger-Str;Tirol",
    "iso:country":"AT",
    "sg:address":"Josef-Egger-Str 3",
    "sg:city":"Kufstein",
    "sg:orig_category":"Psychotherapie",
    "sg:phone":"+43 5372 61334",
    "sg:postcode":"6330",
    "sg:province":"Tirol",
    "wof:name":"Naschberger Martina Mag",
    "wof:placetype":"venue"
},
  "geometry": {"coordinates":[12.1716575623,47.5816307068],"type":"Point"}
}