{
  "type": "Feature",
  "properties": {
    "iso:country":"AT",
    "sg:address":"Schweizer Str 23",
    "sg:city":"Rankweil",
    "sg:orig_category":"Lebensmittel / Einzelhandel",
    "sg:phone":"+43 5522 73321",
    "sg:postcode":"6830",
    "sg:province":"Vorarlberg",
    "wof:name":"Spar-Markt - Rudolf Br\u00e4ndle",
    "wof:placetype":"venue"
},
  "geometry": {"coordinates":[9.6431694031,47.2692146301],"type":"Point"}
}