{
  "type": "Feature",
  "properties": {
    "addr:full":"Alpilaweg 2 Tschagguns Vorarlberg 6774",
    "addr:housenumber":"2",
    "addr:postcode":"6774",
    "addr:street":"Alpilaweg",
    "iso:country":"AT",
    "sg:address":"Alpilaweg 2",
    "sg:city":"Tschagguns",
    "sg:orig_category":"Tischlereien",
    "sg:phone":"+43 5556 74535",
    "sg:postcode":"6774",
    "sg:province":"Vorarlberg",
    "wof:name":"Salzgeber Werner",
    "wof:placetype":"venue"
},
  "geometry": {"coordinates":[9.8999156952,47.0722007751],"type":"Point"}
}