{
  "type": "Feature",
  "properties": {
    "addr:full":"Lach 3b Braunau am Inn Ober\u00f6sterreich 5280",
    "addr:housenumber":"3b",
    "addr:postcode":"5280",
    "addr:street":"Lach;Oberoesterreich",
    "iso:country":"AT",
    "sg:address":"Lach 3b",
    "sg:city":"Braunau am Inn",
    "sg:orig_category":"Elektroinstallationsunternehmen",
    "sg:phone":"+43 7722 67622",
    "sg:postcode":"5280",
    "sg:province":"Ober\u00f6sterreich",
    "wof:name":"Stegfellner Klaus",
    "wof:placetype":"venue"
},
  "geometry": {"coordinates":[13.0547609329,48.2446899414],"type":"Point"}
}