{
  "type": "Feature",
  "properties": {
    "addr:full":"Florianistr 20 Zeltweg Steiermark 8740",
    "addr:housenumber":"20",
    "addr:postcode":"8740",
    "addr:street":"Florianistr",
    "iso:country":"AT",
    "sg:address":"Florianistr 20",
    "sg:city":"Zeltweg",
    "sg:orig_category":"Transportunternehmen",
    "sg:phone":"+43 3577 251030",
    "sg:postcode":"8740",
    "sg:province":"Steiermark",
    "wof:name":"Stibora Kope Raimund - Erdbewegung",
    "wof:placetype":"venue"
},
  "geometry": {"coordinates":[14.7348356247,47.18724823],"type":"Point"}
}