{
  "type": "Feature",
  "properties": {
    "addr:full":"Lainzer Str 166 Wien Wien 1130",
    "addr:housenumber":"166",
    "addr:postcode":"1130",
    "iso:country":"AT",
    "sg:address":"Lainzer Str 166",
    "sg:city":"Wien",
    "sg:orig_category":"Friseure U Frisiersalons",
    "sg:phone":"+43 1 8047747",
    "sg:postcode":"1130",
    "sg:province":"Wien",
    "wof:name":"Krejci Gertrude",
    "wof:placetype":"venue"
},
  "geometry": {"coordinates":[16.2840938568,48.174621582],"type":"Point"}
}