{
  "type": "Feature",
  "properties": {
    "addr:full":"Hauptpl 20/2 Spittal an der Drau K\u00e4rnten 9800",
    "addr:housenumber":"20 / 2",
    "addr:postcode":"9800",
    "addr:street":"Hauptpl;Kaernten",
    "iso:country":"AT",
    "sg:address":"Hauptpl 20/2",
    "sg:city":"Spittal an der Drau",
    "sg:orig_category":"Nachhilfe U Lernbetreuung",
    "sg:phone":"+43 4347 6244188",
    "sg:postcode":"9800",
    "sg:province":"K\u00e4rnten",
    "wof:name":"learnUP - Lern- u Trainingszentrum",
    "wof:placetype":"venue"
},
  "geometry": {"coordinates":[13.4968261719,46.7976112366],"type":"Point"}
}