{
  "type": "Feature",
  "properties": {
    "iso:country":"AT",
    "sg:address":"Badhausstr 28",
    "sg:city":"Innsbruck-Igls",
    "sg:orig_category":"Handelsagenturen",
    "sg:phone":"+43 512 378729",
    "sg:postcode":"6080",
    "sg:province":"Tirol",
    "wof:name":"Wenzl Eduard",
    "wof:placetype":"venue"
},
  "geometry": {"coordinates":[11.4177417755,47.2300605774],"type":"Point"}
}