{
  "type": "Feature",
  "properties": {
    "iso:country":"AT",
    "sg:address":"Viktor Arneitz-Weg 20",
    "sg:city":"Villach",
    "sg:classifiers":[
        {
            "category":"Retail",
            "subcategory":"Event Space",
            "type":"Services"
        }
    ],
    "sg:phone":"+43 4242 318158",
    "sg:postcode":"9500",
    "sg:province":"K\u00e4rnten",
    "sg:tags":[
        "hand-",
        "u",
        "fu\u00c3\u0178pflege"
    ],
    "wof:name":"Fu\u00dfpflege Inge",
    "wof:placetype":"venue"
},
  "geometry": {"coordinates":[13.861541748,46.5921440125],"type":"Point"}
}