{
  "type": "Feature",
  "properties": {
    "addr:full":"Nr 68 Strass im Zillertal Tirol 6261",
    "addr:postcode":"6261",
    "addr:street":"Nr;Strass;Zillertal Tirol",
    "iso:country":"AT",
    "sg:address":"Nr 68",
    "sg:city":"Strass im Zillertal",
    "sg:orig_category":"Tourismusinformation U -Organisationen",
    "sg:phone":"+43 4352 4463040",
    "sg:postcode":"6261",
    "sg:province":"Tirol",
    "wof:name":"Tourismusverband Strass",
    "wof:placetype":"venue"
},
  "geometry": {"coordinates":[11.8219985962,47.3957252502],"type":"Point"}
}