{
  "type": "Feature",
  "properties": {
    "addr:full":"Ritzenedt 2 Weitersfelden Ober\u00f6sterreich 4272",
    "addr:housenumber":"2",
    "addr:postcode":"4272",
    "addr:street":"Ritzenedt;Oberoesterreich",
    "iso:country":"AT",
    "sg:address":"Ritzenedt 2",
    "sg:city":"Weitersfelden",
    "sg:orig_category":"Steuerberatung",
    "sg:phone":"+43 4379 526209",
    "sg:postcode":"4272",
    "sg:province":"Ober\u00f6sterreich",
    "wof:name":"G\u00f6tzl Martin Dipl-Ing",
    "wof:placetype":"venue"
},
  "geometry": {"coordinates":[14.7131567001,48.4898986816],"type":"Point"}
}