{
  "type": "Feature",
  "properties": {
    "addr:full":"Garteng 11 G\u00fcssing Burgenland 7540",
    "addr:housenumber":"11",
    "addr:postcode":"7540",
    "addr:street":"Garteng",
    "iso:country":"AT",
    "sg:address":"Garteng 11",
    "sg:city":"G\u00fcssing",
    "sg:orig_category":"Architekten",
    "sg:phone":"+43 3322 433000",
    "sg:postcode":"7540",
    "sg:province":"Burgenland",
    "wof:name":"Schm\u00f6lzer Helena Mag arch",
    "wof:placetype":"venue"
},
  "geometry": {"coordinates":[16.3195438385,47.0593795776],"type":"Point"}
}