{
  "type": "Feature",
  "properties": {
    "addr:full":"Welser Strasse 31 Marchtrenk Ober\u00f6sterreich 4614",
    "addr:housenumber":"31",
    "addr:postcode":"4614",
    "addr:street":"Welser Strasse",
    "iso:country":"AT",
    "sg:address":"Welser Strasse 31",
    "sg:city":"Marchtrenk",
    "sg:classifiers":[
        {
            "category":"Manufacturing",
            "subcategory":"Furniture",
            "type":"Manufacturing & Wholesale Goods"
        }
    ],
    "sg:phone":"+43 7243 523700",
    "sg:postcode":"4614",
    "sg:province":"Ober\u00f6sterreich",
    "sg:tags":[
        "design"
    ],
    "sg:website":"ideenpavillon.at",
    "wof:name":"Ideenpavillon Design-Tischlerei Ges.m.b.H.",
    "wof:placetype":"venue"
},
  "geometry": {"coordinates":[14.1065273285,48.190700531],"type":"Point"}
}