{
  "type": "Feature",
  "properties": {
    "addr:full":"Hadikg 112 Wien Wien 1140",
    "addr:housenumber":"112",
    "addr:postcode":"1140",
    "iso:country":"AT",
    "sg:address":"Hadikg 112",
    "sg:city":"Wien",
    "sg:orig_category":"Friseure U Frisiersalons",
    "sg:phone":"+43 1 8945201",
    "sg:postcode":"1140",
    "sg:province":"Wien",
    "wof:name":"Wagner Josefine",
    "wof:placetype":"venue"
},
  "geometry": {"coordinates":[16.2968139648,48.1897392273],"type":"Point"}
}