{
  "type": "Feature",
  "properties": {
    "iso:country":"AT",
    "sg:address":"Ramseiden 170",
    "sg:city":"Saalfelden am Steinernen Meer",
    "sg:orig_category":"Pensionen / Privatzimmer",
    "sg:phone":"+43 6582 73279",
    "sg:postcode":"5760",
    "sg:province":"Salzburg",
    "wof:name":"Ramseiderhof",
    "wof:placetype":"venue"
},
  "geometry": {"coordinates":[12.8563690186,47.4244117737],"type":"Point"}
}