{
  "type": "Feature",
  "properties": {
    "addr:full":"Doerenkampg. 11  Wien Wien 1100",
    "addr:housenumber":"11",
    "addr:postcode":"1100",
    "addr:street":"Doerenkampg.",
    "iso:country":"AT",
    "sg:address":"Doerenkampg. 11 ",
    "sg:city":"Wien",
    "sg:classifiers":[
        {
            "category":"Wholesale",
            "subcategory":"Drugs",
            "type":"Manufacturing & Wholesale Goods"
        }
    ],
    "sg:phone":"+43 4316 8821610",
    "sg:postcode":"1100",
    "sg:province":"Wien",
    "sg:tags":[
        "chemical",
        "pharmaceutical"
    ],
    "wof:name":"KLOSTERFRAU GES.MBH",
    "wof:placetype":"venue"
},
  "geometry": {"coordinates":[16.3792057037,48.1416358948],"type":"Point"}
}