{
  "type": "Feature",
  "properties": {
    "iso:country":"AT",
    "sg:address":"Dr.-Stumpf-Str 122",
    "sg:city":"Innsbruck",
    "sg:orig_category":"Installationsunternehmen",
    "sg:phone":"+43 664 1013434",
    "sg:postcode":"6020",
    "sg:province":"Tirol",
    "wof:name":"Liner Michael Installation-Sanit\u00e4re-Heizung",
    "wof:placetype":"venue"
},
  "geometry": {"coordinates":[11.3653268814,47.2550392151],"type":"Point"}
}