{
  "type": "Feature",
  "properties": {
    "iso:country":"AT",
    "sg:address":"Hauptpl 5",
    "sg:city":"Ferlach",
    "sg:classifiers":[
        {
            "category":"Restaurant",
            "type":"Food & Drink"
        }
    ],
    "sg:phone":"+43 4227 5476",
    "sg:postcode":"9170",
    "sg:province":"K\u00e4rnten",
    "sg:tags":[
        "pizzeria"
    ],
    "wof:name":"Pizzeria Cara Mia",
    "wof:placetype":"venue"
},
  "geometry": {"coordinates":[14.3011713028,46.5265884399],"type":"Point"}
}