{
  "type": "Feature",
  "properties": {
    "addr:full":"Kirchg 1 K\u00f6ssen Tirol 6345",
    "addr:housenumber":"1",
    "addr:postcode":"6345",
    "addr:street":"Kirchg;Tirol",
    "iso:country":"AT",
    "sg:address":"Kirchg 1",
    "sg:city":"K\u00f6ssen",
    "sg:orig_category":"\u00c3\u201erzte / F Allgemeinmedizin",
    "sg:phone":"+43 5375 6703",
    "sg:postcode":"6345",
    "sg:province":"Tirol",
    "wof:name":"Dosch Peter Dr - Neuraltherapie",
    "wof:placetype":"venue"
},
  "geometry": {"coordinates":[12.4052600861,47.6695098877],"type":"Point"}
}