{
  "type": "Feature",
  "properties": {
    "addr:full":"Marktpl 13 Altheim Ober\u00f6sterreich 4950",
    "addr:housenumber":"13",
    "addr:postcode":"4950",
    "addr:street":"Marktpl",
    "iso:country":"AT",
    "sg:address":"Marktpl 13",
    "sg:city":"Altheim",
    "sg:classifiers":[
        {
            "category":"Travel",
            "subcategory":"Hotels & Motels",
            "type":"Entertainment"
        }
    ],
    "sg:phone":"+43 7723 422690",
    "sg:postcode":"4950",
    "sg:province":"Ober\u00f6sterreich",
    "wof:name":"Hotel Neum\u00fcller",
    "wof:placetype":"venue"
},
  "geometry": {"coordinates":[13.2322597504,48.2501029968],"type":"Point"}
}