{
  "type": "Feature",
  "properties": {
    "addr:full":"Herzog-Friedrich-Str 20 Innsbruck Tirol 6020",
    "addr:housenumber":"20",
    "addr:postcode":"6020",
    "addr:street":"Herzog-Friedrich-Str;Tirol",
    "iso:country":"AT",
    "sg:address":"Herzog-Friedrich-Str 20",
    "sg:city":"Innsbruck",
    "sg:orig_category":"Trachtenbekleidung",
    "sg:phone":"+43 512 560977",
    "sg:postcode":"6020",
    "sg:province":"Tirol",
    "wof:name":"Sportalm GesmbH",
    "wof:placetype":"venue"
},
  "geometry": {"coordinates":[11.3932409286,47.2680549622],"type":"Point"}
}