{
  "type": "Feature",
  "properties": {
    "addr:full":"Weinzerweg 5 Launsdorf K\u00e4rnten 9314",
    "addr:housenumber":"5",
    "addr:postcode":"9314",
    "addr:street":"Weinzerweg;Kaernten",
    "iso:country":"AT",
    "sg:address":"Weinzerweg 5",
    "sg:city":"Launsdorf",
    "sg:orig_category":"Metallbau",
    "sg:phone":"+43 4213 2217",
    "sg:postcode":"9314",
    "sg:province":"K\u00e4rnten",
    "wof:name":"Duller Herwig",
    "wof:placetype":"venue"
},
  "geometry": {"coordinates":[14.4554748535,46.7681846619],"type":"Point"}
}