{
  "type": "Feature",
  "properties": {
    "addr:full":"Andreas-Hofer-Str 30 Innsbruck Tirol 6020",
    "addr:housenumber":"30",
    "addr:postcode":"6020",
    "addr:street":"Andreas-Hofer-Str;Tirol",
    "iso:country":"AT",
    "sg:address":"Andreas-Hofer-Str 30",
    "sg:city":"Innsbruck",
    "sg:orig_category":"Apotheken",
    "sg:phone":"+43 512 5848610",
    "sg:postcode":"6020",
    "sg:province":"Tirol",
    "sg:website":"andreas-hofer.at",
    "wof:name":"Apotheke zum Andreas Hofer Magpharm Jakob Moncher KG",
    "wof:placetype":"venue"
},
  "geometry": {"coordinates":[11.3916339874,47.258266449],"type":"Point"}
}