{
  "type": "Feature",
  "properties": {
    "iso:country":"AT",
    "sg:address":"Glacisstr 65",
    "sg:city":"Graz",
    "sg:orig_category":"Feng-Shui",
    "sg:phone":"+43 316 772896",
    "sg:postcode":"8010",
    "sg:province":"Steiermark",
    "wof:name":"artquarium",
    "wof:placetype":"venue"
},
  "geometry": {"coordinates":[15.4472980499,47.069519043],"type":"Point"}
}