{
  "type": "Feature",
  "properties": {
    "addr:full":"Triester Str 354 Wien Wien 1230",
    "addr:housenumber":"354",
    "addr:postcode":"1230",
    "iso:country":"AT",
    "sg:address":"Triester Str 354",
    "sg:city":"Wien",
    "sg:orig_category":"Autospenglereien",
    "sg:phone":"+43 4316 991300",
    "sg:postcode":"1230",
    "sg:province":"Wien",
    "wof:name":"Stipsky Hans",
    "wof:placetype":"venue"
},
  "geometry": {"coordinates":[16.3191642761,48.1261978149],"type":"Point"}
}