{
  "type": "Feature",
  "properties": {
    "addr:full":"M\u00fchlen 62 M\u00fchlen Steiermark 8822",
    "addr:housenumber":"62",
    "addr:postcode":"8822",
    "addr:street":"Muehlen",
    "iso:country":"AT",
    "sg:address":"M\u00fchlen 62",
    "sg:city":"M\u00fchlen",
    "sg:classifiers":[
        {
            "category":"Transit Center",
            "subcategory":"Freight",
            "type":"Transportation"
        }
    ],
    "sg:phone":"+43 3586 2149",
    "sg:postcode":"8822",
    "sg:province":"Steiermark",
    "sg:tags":[
        "rail",
        "transport"
    ],
    "wof:name":"Walter Olschnegger KEG",
    "wof:placetype":"venue"
},
  "geometry": {"coordinates":[5.9043102264,49.874370575],"type":"Point"}
}