{
  "type": "Feature",
  "properties": {
    "addr:full":"Johann-Wolfgang-von-Goethe-Str 52 Traiskirchen Nieder\u00f6sterreich 2514",
    "addr:housenumber":"52",
    "addr:postcode":"2514",
    "addr:street":"Johann-Wolfgang-Von-Goethe-Str;Niederoesterreich",
    "iso:country":"AT",
    "sg:address":"Johann-Wolfgang-von-Goethe-Str 52",
    "sg:city":"Traiskirchen",
    "sg:orig_category":"Friseure U Frisiersalons",
    "sg:phone":"+43 4322 5252764",
    "sg:postcode":"2514",
    "sg:province":"Nieder\u00f6sterreich",
    "wof:name":"Biosthetik - Karin Moik",
    "wof:placetype":"venue"
},
  "geometry": {"coordinates":[16.2871589661,48.0211715698],"type":"Point"}
}