{
  "type": "Feature",
  "properties": {
    "iso:country":"AT",
    "sg:address":"Maxglaner Hauptstr 30",
    "sg:city":"Salzburg",
    "sg:orig_category":"Tonstudios, Webdesign, Werbeagenturen, Videoproduktionen, Multimedia, Werbegrafik- U Grafik-Design",
    "sg:phone":"+43 662 822782",
    "sg:postcode":"5020",
    "sg:province":"Salzburg",
    "sg:website":"www.delight-media.com",
    "wof:name":"Delight Media Productions & More",
    "wof:placetype":"venue"
},
  "geometry": {"coordinates":[13.0214080811,47.7972335815],"type":"Point"}
}