{
  "type": "Feature",
  "properties": {
    "addr:full":"Brunng 2 Wieselburg an der Erlauf Nieder\u00f6sterreich 3250",
    "addr:housenumber":"2",
    "addr:postcode":"3250",
    "addr:street":"Brunng",
    "iso:country":"AT",
    "sg:address":"Brunng 2",
    "sg:city":"Wieselburg an der Erlauf",
    "sg:orig_category":"Studentenheime",
    "sg:phone":"+43 4374 1654250",
    "sg:postcode":"3250",
    "sg:province":"Nieder\u00f6sterreich",
    "wof:name":"STUDENTENWOHNHEIM - Fam Porranzl",
    "wof:placetype":"venue"
},
  "geometry": {"coordinates":[15.1451377869,48.1284637451],"type":"Point"}
}