{
  "type": "Feature",
  "properties": {
    "addr:full":"Leobersdorfer Str 18 Berndorf Nieder\u00f6sterreich 2560",
    "addr:postcode":"2560",
    "addr:street":"Str 18",
    "iso:country":"AT",
    "sg:address":"Leobersdorfer Str 18",
    "sg:city":"Berndorf",
    "sg:orig_category":"Lebensmittel / Einzelhandel",
    "sg:phone":"+43 4326 7284848",
    "sg:postcode":"2560",
    "sg:province":"Nieder\u00f6sterreich",
    "wof:name":"Hofer KG",
    "wof:placetype":"venue"
},
  "geometry": {"coordinates":[16.1051998138,47.8947486877],"type":"Point"}
}