{
  "type": "Feature",
  "properties": {
    "addr:full":"Handwerkstr 5 Villach K\u00e4rnten 9500",
    "addr:housenumber":"5",
    "addr:postcode":"9500",
    "addr:street":"Handwerkstr;Kaernten",
    "iso:country":"AT",
    "sg:address":"Handwerkstr 5",
    "sg:city":"Villach",
    "sg:orig_category":"Motoreninstandsetzung",
    "sg:phone":"+43 4242 311450",
    "sg:postcode":"9500",
    "sg:province":"K\u00e4rnten",
    "wof:name":"Marko Willi",
    "wof:placetype":"venue"
},
  "geometry": {"coordinates":[13.8461608887,46.5962715149],"type":"Point"}
}