{
  "type": "Feature",
  "properties": {
    "iso:country":"AT",
    "sg:address":"Draupromenade 21",
    "sg:city":"Villach",
    "sg:orig_category":"Zahntechnische Laboratorien",
    "sg:phone":"+43 4242 217566",
    "sg:postcode":"9500",
    "sg:province":"K\u00e4rnten",
    "wof:name":"Dentalstudio Koszler & Weinstich OEG",
    "wof:placetype":"venue"
},
  "geometry": {"coordinates":[13.844039917,46.6170501709],"type":"Point"}
}