{
  "type": "Feature",
  "properties": {
    "addr:full":"Blechturmg 20 Wien Wien 1040",
    "addr:housenumber":"20",
    "addr:postcode":"1040",
    "addr:street":"Blechturmg",
    "iso:country":"AT",
    "sg:address":"Blechturmg 20",
    "sg:city":"Wien",
    "sg:orig_category":"Gerichtsdolmetscher",
    "sg:phone":"+43 1 5056699",
    "sg:postcode":"1040",
    "sg:province":"Wien",
    "wof:name":"Dissauer Margarete Mag",
    "wof:placetype":"venue"
},
  "geometry": {"coordinates":[16.3665847778,48.1863479614],"type":"Point"}
}