{
  "type": "Feature",
  "properties": {
    "addr:full":"Dr.-Erich-Loitzl-Str 34 Blumau-Neuri\u00dfhof Nieder\u00f6sterreich 2602",
    "addr:housenumber":"34",
    "addr:postcode":"2602",
    "addr:street":"Dr.-Erich-Loitzl-Str",
    "iso:country":"AT",
    "sg:address":"Dr.-Erich-Loitzl-Str 34",
    "sg:city":"Blumau-Neuri\u00dfhof",
    "sg:orig_category":"Unternehmensberatung",
    "sg:phone":"+43 699 18151810",
    "sg:postcode":"2602",
    "sg:province":"Nieder\u00f6sterreich",
    "wof:name":"CP-Consult Bugram OEG",
    "wof:placetype":"venue"
},
  "geometry": {"coordinates":[16.288105011,47.9151535034],"type":"Point"}
}