{
  "type": "Feature",
  "properties": {
    "iso:country":"AT",
    "sg:address":"Innsbruck Bundesstr 7",
    "sg:city":"Salzburg",
    "sg:orig_category":"Fitnesscenter",
    "sg:phone":"+43 662 435828",
    "sg:postcode":"5020",
    "sg:province":"Salzburg",
    "wof:name":"Damen-Fitnesstudio Aiglhof",
    "wof:placetype":"venue"
},
  "geometry": {"coordinates":[13.025349617,47.8054466248],"type":"Point"}
}