{
  "type": "Feature",
  "properties": {
    "addr:full":"Heidenwaldweg 2 Leibnitz Steiermark 8430",
    "addr:housenumber":"2",
    "addr:postcode":"8430",
    "addr:street":"Heidenwaldweg;Steiermark",
    "iso:country":"AT",
    "sg:address":"Heidenwaldweg 2",
    "sg:city":"Leibnitz",
    "sg:classifiers":[
        {
            "category":"Farming",
            "subcategory":"Fish & Marine Products",
            "type":"Manufacturing & Wholesale Goods"
        }
    ],
    "sg:phone":"+43 3452 843110",
    "sg:postcode":"8430",
    "sg:province":"Steiermark",
    "sg:tags":[
        "asphalt"
    ],
    "wof:name":"Asphaltlieferwerk Leibnitz Bauges.m.b.H.",
    "wof:placetype":"venue"
},
  "geometry": {"coordinates":[15.5377645493,46.7811355591],"type":"Point"}
}