{
  "type": "Feature",
  "properties": {
    "iso:country":"AT",
    "sg:address":"Schulg 2",
    "sg:city":"Pamhagen",
    "sg:orig_category":"Volksschulen",
    "sg:phone":"+43 2174 2117",
    "sg:postcode":"7152",
    "sg:province":"Burgenland",
    "wof:name":"Volksschule",
    "wof:placetype":"venue"
},
  "geometry": {"coordinates":[16.9034194946,47.6996498108],"type":"Point"}
}