{
  "type": "Feature",
  "properties": {
    "addr:full":"Hauptpl 73 St. Michael im Burgenland Burgenland 7535",
    "addr:housenumber":"73",
    "addr:postcode":"7535",
    "addr:street":"Hauptpl",
    "iso:country":"AT",
    "sg:address":"Hauptpl 73",
    "sg:city":"St. Michael im Burgenland",
    "sg:orig_category":"Elektroinstallationsunternehmen",
    "sg:phone":"+43 4333 272204",
    "sg:postcode":"7535",
    "sg:province":"Burgenland",
    "wof:name":"Hafner Ronald",
    "wof:placetype":"venue"
},
  "geometry": {"coordinates":[16.2694511414,47.127117157],"type":"Point"}
}