{
  "type": "Feature",
  "properties": {
    "addr:full":"Marktpl 3 Altenfelden Ober\u00f6sterreich 4121",
    "addr:housenumber":"3",
    "addr:postcode":"4121",
    "addr:street":"Marktpl",
    "iso:country":"AT",
    "sg:address":"Marktpl 3",
    "sg:city":"Altenfelden",
    "sg:orig_category":"Schmieden U Schmiedeeisenelemente",
    "sg:phone":"+43 4372 826266",
    "sg:postcode":"4121",
    "sg:province":"Ober\u00f6sterreich",
    "wof:name":"Hirsch Franz",
    "wof:placetype":"venue"
},
  "geometry": {"coordinates":[13.9696331024,48.4853057861],"type":"Point"}
}