{
  "type": "Feature",
  "properties": {
    "addr:full":"Julius-Welser-Strasse 15 Salzburg Salzburg 5020",
    "addr:housenumber":"15",
    "addr:postcode":"5020",
    "addr:street":"Julius-Welser-Strasse;Salzburg",
    "iso:country":"AT",
    "sg:address":"Julius-Welser-Strasse 15",
    "sg:city":"Salzburg",
    "sg:classifiers":[
        {
            "category":"Utilities",
            "subcategory":"Sewage",
            "type":"Services"
        }
    ],
    "sg:phone":"+43 662 434901",
    "sg:postcode":"5020",
    "sg:province":"Salzburg",
    "sg:tags":[
        "plant",
        "stp",
        "system",
        "treatment",
        "aeration"
    ],
    "sg:website":"sfcu.at",
    "wof:name":"SFC - Umwelttechnik GmbH",
    "wof:placetype":"venue"
},
  "geometry": {"coordinates":[13.0131597519,47.80676651],"type":"Point"}
}