{
  "type": "Feature",
  "properties": {
    "addr:full":"Nr 1 Hafnerbach Nieder\u00f6sterreich 3386",
    "addr:postcode":"3386",
    "addr:street":"Nr;Hafnerbach Niederoesterreich",
    "iso:country":"AT",
    "sg:address":"Nr 1",
    "sg:city":"Hafnerbach",
    "sg:classifiers":[
        {
            "category":"Farming",
            "subcategory":"Livestock Farm",
            "type":"Manufacturing & Wholesale Goods"
        }
    ],
    "sg:phone":"+43 4327 498046",
    "sg:postcode":"3386",
    "sg:province":"Nieder\u00f6sterreich",
    "sg:tags":[
        "-handel",
        "viehzucht",
        "u"
    ],
    "wof:name":"Holy Josef",
    "wof:placetype":"venue"
},
  "geometry": {"coordinates":[15.4880743027,48.2166900635],"type":"Point"}
}