{
  "type": "Feature",
  "properties": {
    "addr:full":"Stubenbastei 12 Wien Wien 1010",
    "addr:housenumber":"12",
    "addr:postcode":"1010",
    "addr:street":"Stubenbastei",
    "iso:country":"AT",
    "sg:address":"Stubenbastei 12",
    "sg:city":"Wien",
    "sg:orig_category":"Unternehmensberatung",
    "sg:phone":"+43 1 5133245",
    "sg:postcode":"1010",
    "sg:province":"Wien",
    "wof:name":"Bridge It Unternehmensberatung GmbH",
    "wof:placetype":"venue"
},
  "geometry": {"coordinates":[16.3775119781,48.2063407898],"type":"Point"}
}