{
  "type": "Feature",
  "properties": {
    "addr:full":"Veldenstrasse 10 Altenfelden Ober\u00f6sterreich 4121",
    "addr:housenumber":"10",
    "addr:postcode":"4121",
    "addr:street":"Veldenstrasse",
    "iso:country":"AT",
    "sg:address":"Veldenstrasse 10",
    "sg:city":"Altenfelden",
    "sg:classifiers":[
        {
            "category":"Building & Trades",
            "subcategory":"Electrical",
            "type":"Services"
        }
    ],
    "sg:phone":"+43 7282 5501",
    "sg:postcode":"4121",
    "sg:province":"Ober\u00f6sterreich",
    "sg:tags":[
        "work",
        "installation"
    ],
    "sg:website":"elektro-prechtl.at",
    "wof:name":"Johann Prechtl",
    "wof:placetype":"venue"
},
  "geometry": {"coordinates":[13.9712457657,48.4849624634],"type":"Point"}
}