{
  "type": "Feature",
  "properties": {
    "iso:country":"AT",
    "sg:address":"Stranach 85",
    "sg:city":"Mariapfarr",
    "sg:orig_category":"Installationsunternehmen",
    "sg:phone":"+43 6473 7403",
    "sg:postcode":"5571",
    "sg:province":"Salzburg",
    "wof:name":"Kerschhaggl Willi",
    "wof:placetype":"venue"
},
  "geometry": {"coordinates":[13.7428789139,47.1411170959],"type":"Point"}
}