{
  "type": "Feature",
  "properties": {
    "addr:full":"Johannesg 15/28 Wien Wien 1010",
    "addr:housenumber":"15 / 28",
    "addr:postcode":"1010",
    "addr:street":"Johannesg",
    "iso:country":"AT",
    "sg:address":"Johannesg 15/28",
    "sg:city":"Wien",
    "sg:orig_category":"Unternehmensberatung",
    "sg:phone":"+43 4319 432212",
    "sg:postcode":"1010",
    "sg:province":"Wien",
    "wof:name":"Consalto Corporate Identity",
    "wof:placetype":"venue"
},
  "geometry": {"coordinates":[16.3688049316,48.2025489807],"type":"Point"}
}