{
  "type": "Feature",
  "properties": {
    "addr:full":"Burgweg 8 Th\u00fcringen Vorarlberg 6712",
    "addr:housenumber":"8",
    "addr:postcode":"6712",
    "addr:street":"Burgweg",
    "iso:country":"AT",
    "sg:address":"Burgweg 8",
    "sg:city":"Th\u00fcringen",
    "sg:orig_category":"Raumausstattung",
    "sg:phone":"+43 5550 4965",
    "sg:postcode":"6712",
    "sg:province":"Vorarlberg",
    "wof:name":"Wrann Stefan",
    "wof:placetype":"venue"
},
  "geometry": {"coordinates":[9.7694635391,47.2011108398],"type":"Point"}
}