{
  "type": "Feature",
  "properties": {
    "addr:full":"Klosterwiesg 33 Graz Steiermark 8010",
    "addr:housenumber":"33",
    "addr:postcode":"8010",
    "addr:street":"Klosterwiesg",
    "iso:country":"AT",
    "sg:address":"Klosterwiesg 33",
    "sg:city":"Graz",
    "sg:orig_category":"Psychologen",
    "sg:phone":"+43 650 9720137",
    "sg:postcode":"8010",
    "sg:province":"Steiermark",
    "wof:name":"Klug Karin Dr",
    "wof:placetype":"venue"
},
  "geometry": {"coordinates":[15.4455919266,47.06407547],"type":"Point"}
}