{
  "type": "Feature",
  "properties": {
    "addr:full":"Lichtensteinerberg 3 St. Stefan ob Leoben Steiermark 8713",
    "addr:housenumber":"3",
    "addr:postcode":"8713",
    "addr:street":"Lichtensteinerberg",
    "iso:country":"AT",
    "sg:address":"Lichtensteinerberg 3",
    "sg:city":"St. Stefan ob Leoben",
    "sg:orig_category":"Non-Classified Establishments",
    "sg:phone":"+43 3832 2021",
    "sg:postcode":"8713",
    "sg:province":"Steiermark",
    "wof:name":"Schaffers Freilandeier",
    "wof:placetype":"venue"
},
  "geometry": {"coordinates":[14.9804811478,47.2987670898],"type":"Point"}
}