{
  "type": "Feature",
  "properties": {
    "iso:country":"AT",
    "sg:address":"Rettenbach 288",
    "sg:city":"S\u00f6lden",
    "sg:classifiers":[
        {
            "category":"Restaurant",
            "type":"Food & Drink"
        }
    ],
    "sg:phone":"+43 4352 54501120",
    "sg:postcode":"6450",
    "sg:province":"Tirol",
    "wof:name":"Bierhimml-Partyhaus",
    "wof:placetype":"venue"
},
  "geometry": {"coordinates":[11.0101947784,46.9675750732],"type":"Point"}
}