{
  "type": "Feature",
  "properties": {
    "addr:full":"Sankt Martin bei Lofer 201 St. Martin Salzburg 5092",
    "addr:housenumber":"201",
    "addr:postcode":"5092",
    "addr:street":"Sankt Martin Bei Lofer",
    "iso:country":"AT",
    "sg:address":"Sankt Martin bei Lofer 201",
    "sg:city":"St. Martin",
    "sg:classifiers":[
        {
            "category":"Building & Trades",
            "subcategory":"Plumbing",
            "type":"Services"
        }
    ],
    "sg:phone":"+43 6588 8626",
    "sg:postcode":"5092",
    "sg:province":"Salzburg",
    "sg:tags":[
        "supraregional",
        "gas"
    ],
    "wof:name":"Georg Hirschbichler Installationen",
    "wof:placetype":"venue"
},
  "geometry": {"coordinates":[12.7050590515,47.5667266846],"type":"Point"}
}