{
  "type": "Feature",
  "properties": {
    "addr:full":"Marcusstr 8-10 Freistadt Ober\u00f6sterreich 4240",
    "addr:housenumber":"8-10",
    "addr:postcode":"4240",
    "iso:country":"AT",
    "sg:address":"Marcusstr 8-10",
    "sg:city":"Freistadt",
    "sg:orig_category":"Fotoausarbeitungen",
    "sg:phone":"+43 7942 776770",
    "sg:postcode":"4240",
    "sg:province":"Ober\u00f6sterreich",
    "sg:website":"happy-foto.com",
    "wof:name":"HAPPY-FOTO GmbH - Fotoausarbeitung per Postversand",
    "wof:placetype":"venue"
},
  "geometry": {"coordinates":[14.5048284531,48.498790741],"type":"Point"}
}