{
  "type": "Feature",
  "properties": {
    "iso:country":"AT",
    "sg:address":"Weitraer Str 71",
    "sg:city":"Zwettl",
    "sg:orig_category":"Installationsunternehmen",
    "sg:phone":"+43 2822 526620",
    "sg:postcode":"3910",
    "sg:province":"Nieder\u00f6sterreich",
    "wof:name":"Jagsch Installationen",
    "wof:placetype":"venue"
},
  "geometry": {"coordinates":[15.1368551254,48.6106300354],"type":"Point"}
}