{
  "type": "Feature",
  "properties": {
    "addr:full":"Weitraer Str 30 Gm\u00fcnd Nieder\u00f6sterreich 3950",
    "addr:postcode":"3950",
    "addr:street":"Str 30 Gmuend",
    "iso:country":"AT",
    "sg:address":"Weitraer Str 30",
    "sg:city":"Gm\u00fcnd",
    "sg:orig_category":"Sonnenstudios",
    "sg:phone":"+43 2852 54587",
    "sg:postcode":"3950",
    "sg:province":"Nieder\u00f6sterreich",
    "wof:name":"Sonnenstudio Ursula P\u00fcchel",
    "wof:placetype":"venue"
},
  "geometry": {"coordinates":[14.9812021255,48.7694015503],"type":"Point"}
}