{
  "type": "Feature",
  "properties": {
    "iso:country":"AT",
    "sg:address":"Sindh\u00f6ring 7",
    "sg:city":"St. Martin im Innkreis",
    "sg:orig_category":"Metallbau",
    "sg:phone":"+43 4377 5183860",
    "sg:postcode":"4973",
    "sg:province":"Ober\u00f6sterreich",
    "wof:name":"Deschberger Georg",
    "wof:placetype":"venue"
},
  "geometry": {"coordinates":[13.4180746078,48.261505127],"type":"Point"}
}