{
  "type": "Feature",
  "properties": {
    "addr:full":"Mozartstr 1 Bad Schallerbach Ober\u00f6sterreich 4701",
    "addr:housenumber":"1",
    "addr:postcode":"4701",
    "addr:street":"Mozartstr",
    "iso:country":"AT",
    "sg:address":"Mozartstr 1",
    "sg:city":"Bad Schallerbach",
    "sg:orig_category":"Feuerwehren",
    "sg:phone":"+43 7249 42805",
    "sg:postcode":"4701",
    "sg:province":"Ober\u00f6sterreich",
    "wof:name":"Freiwillige Feuerwehr Bad Schallerbach",
    "wof:placetype":"venue"
},
  "geometry": {"coordinates":[13.919836998,48.231880188],"type":"Point"}
}