{
  "type": "Feature",
  "properties": {
    "addr:full":"Hauptstr 111a Breitenfurt Nieder\u00f6sterreich 2384",
    "addr:housenumber":"111a",
    "addr:postcode":"2384",
    "addr:street":"Hauptstr",
    "iso:country":"AT",
    "sg:address":"Hauptstr 111a",
    "sg:city":"Breitenfurt",
    "sg:classifiers":[
        {
            "category":"Home & Garden",
            "subcategory":"Building Materials",
            "type":"Retail Goods"
        }
    ],
    "sg:phone":"+43 4322 392313",
    "sg:postcode":"2384",
    "sg:province":"Nieder\u00f6sterreich",
    "sg:tags":[
        "baustoffe",
        "-material",
        "u"
    ],
    "wof:name":"Wollek GesmbH",
    "wof:placetype":"venue"
},
  "geometry": {"coordinates":[16.1829891205,48.134059906],"type":"Point"}
}