{
  "type": "Feature",
  "properties": {
    "iso:country":"AT",
    "sg:address":"Steinbauerg 18",
    "sg:city":"Wien",
    "sg:orig_category":"Blumeneinzelhandel",
    "sg:phone":"+43 4318 107024",
    "sg:postcode":"1120",
    "sg:province":"Wien",
    "wof:name":"Karin's Blumenwelt",
    "wof:placetype":"venue"
},
  "geometry": {"coordinates":[16.3427619934,48.1831245422],"type":"Point"}
}