{
  "type": "Feature",
  "properties": {
    "addr:full":"Nr 123 Pfaffenschlag Nieder\u00f6sterreich 3834",
    "addr:postcode":"3834",
    "addr:street":"Nr 123 Pfaffenschlag",
    "iso:country":"AT",
    "sg:address":"Nr 123",
    "sg:city":"Pfaffenschlag",
    "sg:orig_category":"Unterhaltungselektronik / Einzelhandel",
    "sg:phone":"+43 4328 486413",
    "sg:postcode":"3834",
    "sg:province":"Nieder\u00f6sterreich",
    "wof:name":"Schreiber Josef Gerald",
    "wof:placetype":"venue"
},
  "geometry": {"coordinates":[15.1466197968,48.8139076233],"type":"Point"}
}