{
  "type": "Feature",
  "properties": {
    "addr:full":"Nr 62 Schwertberg Ober\u00f6sterreich 4311",
    "addr:postcode":"4311",
    "addr:street":"Nr;Schwertberg",
    "iso:country":"AT",
    "sg:address":"Nr 62",
    "sg:city":"Schwertberg",
    "sg:orig_category":"Garten- U Landschaftsgestaltung",
    "sg:phone":"+43 4372 62617720",
    "sg:postcode":"4311",
    "sg:province":"Ober\u00f6sterreich",
    "wof:name":"Langeder Garten-Harmonie",
    "wof:placetype":"venue"
},
  "geometry": {"coordinates":[14.5817127228,48.2739906311],"type":"Point"}
}