{
  "type": "Feature",
  "properties": {
    "addr:full":"Josef-Moser-Strasse 1 Neuzeug Ober\u00f6sterreich 4523",
    "addr:housenumber":"1",
    "addr:postcode":"4523",
    "addr:street":"Josef-Moser-Strasse",
    "iso:country":"AT",
    "sg:address":"Josef-Moser-Strasse 1",
    "sg:city":"Neuzeug",
    "sg:classifiers":[
        {
            "category":"Banks & Credit Unions",
            "subcategory":"Investment Brokerage",
            "type":"Services"
        }
    ],
    "sg:phone":"+43 7259 2231",
    "sg:postcode":"4523",
    "sg:province":"Ober\u00f6sterreich",
    "sg:tags":[
        "curtain",
        "rod",
        "accessory"
    ],
    "wof:name":"Peter Hametner",
    "wof:placetype":"venue"
},
  "geometry": {"coordinates":[14.329126358,48.0435752869],"type":"Point"}
}