{
  "type": "Feature",
  "properties": {
    "iso:country":"AT",
    "sg:address":"Unterer Markt 11",
    "sg:city":"Reichenau im M\u00fchlkreis",
    "sg:orig_category":"Autovermietung",
    "sg:phone":"+43 4372 118208",
    "sg:postcode":"4204",
    "sg:province":"Ober\u00f6sterreich",
    "wof:name":"Wittibschlager Edeltraud",
    "wof:placetype":"venue"
},
  "geometry": {"coordinates":[14.3509836197,48.4557418823],"type":"Point"}
}