{
  "type": "Feature",
  "properties": {
    "addr:full":"Mautner Markhof-G 72 Wien Wien 1110",
    "addr:housenumber":"72",
    "addr:postcode":"1110",
    "iso:country":"AT",
    "sg:address":"Mautner Markhof-G 72",
    "sg:city":"Wien",
    "sg:orig_category":"Mauertrockenlegungen",
    "sg:phone":"+43 1 7434050",
    "sg:postcode":"1110",
    "sg:province":"Wien",
    "wof:name":"Hahn Franz Ing GesmbH",
    "wof:placetype":"venue"
},
  "geometry": {"coordinates":[16.4201850891,48.1735801697],"type":"Point"}
}