{
  "type": "Feature",
  "properties": {
    "addr:full":"Nr 220 Turnau Steiermark 8625",
    "addr:postcode":"8625",
    "addr:street":"Nr 220",
    "iso:country":"AT",
    "sg:address":"Nr 220",
    "sg:city":"Turnau",
    "sg:orig_category":"Rettungsdienste",
    "sg:phone":"+43 3863 22440",
    "sg:postcode":"8625",
    "sg:province":"Steiermark",
    "wof:name":"Rotes Kreuz \u00f6sterr Ortsstelle Turnau",
    "wof:placetype":"venue"
},
  "geometry": {"coordinates":[15.3370742798,47.5582237244],"type":"Point"}
}