{
  "type": "Feature",
  "properties": {
    "addr:full":"Spitalstr 2 Oberpullendorf Burgenland 7350",
    "addr:housenumber":"2",
    "addr:postcode":"7350",
    "addr:street":"Spitalstr",
    "iso:country":"AT",
    "sg:address":"Spitalstr 2",
    "sg:city":"Oberpullendorf",
    "sg:orig_category":"Textilreinigung",
    "sg:phone":"+43 4326 1242392",
    "sg:postcode":"7350",
    "sg:province":"Burgenland",
    "wof:name":"Textilreinigung Susi",
    "wof:placetype":"venue"
},
  "geometry": {"coordinates":[16.5049877167,47.5033721924],"type":"Point"}
}