{
  "type": "Feature",
  "properties": {
    "addr:full":"Wimbergstr 28 St. Peter am Wimberg Ober\u00f6sterreich 4171",
    "addr:housenumber":"28",
    "addr:postcode":"4171",
    "addr:street":"Wimbergstr",
    "iso:country":"AT",
    "sg:address":"Wimbergstr 28",
    "sg:city":"St. Peter am Wimberg",
    "sg:orig_category":"Raucherartikel",
    "sg:phone":"+43 4372 828138",
    "sg:postcode":"4171",
    "sg:province":"Ober\u00f6sterreich",
    "wof:name":"Cima GesmbH",
    "wof:placetype":"venue"
},
  "geometry": {"coordinates":[14.0769643784,48.5018310547],"type":"Point"}
}