{
  "type": "Feature",
  "properties": {
    "iso:country":"AT",
    "sg:address":"Wamprechtsham 42",
    "sg:city":"St. Willibald",
    "sg:classifiers":[
        {
            "category":"Building & Trades",
            "subcategory":"Plumbing",
            "type":"Services"
        }
    ],
    "sg:phone":"+43 7762 2875",
    "sg:postcode":"4762",
    "sg:province":"Ober\u00f6sterreich",
    "sg:tags":[
        "supraregional",
        "gas"
    ],
    "wof:name":"W\u00e4rmetechnik Hermann Reitinger GmbH",
    "wof:placetype":"venue"
},
  "geometry": {"coordinates":[13.6844568253,48.3733596802],"type":"Point"}
}