{
  "type": "Feature",
  "properties": {
    "iso:country":"AT",
    "sg:address":"Neubaug 48",
    "sg:city":"Deutschkreutz",
    "sg:orig_category":"Baumeister",
    "sg:phone":"+43 2613 80412",
    "sg:postcode":"7301",
    "sg:province":"Burgenland",
    "wof:name":"Sommer Johann Ing Dr",
    "wof:placetype":"venue"
},
  "geometry": {"coordinates":[16.6256313324,47.5992851257],"type":"Point"}
}