{
  "type": "Feature",
  "properties": {
    "addr:full":"Weyerngasse 41 Knittelfeld Steiermark 8720",
    "addr:housenumber":"41",
    "addr:postcode":"8720",
    "addr:street":"Weyerngasse",
    "iso:country":"AT",
    "sg:address":"Weyerngasse 41",
    "sg:city":"Knittelfeld",
    "sg:orig_category":"Fuel And Lubricant Pumps",
    "sg:phone":"+43 3512 71742",
    "sg:postcode":"8720",
    "sg:province":"Steiermark",
    "sg:website":"modelltechnik.at",
    "wof:name":"MTH Modelltechnik H\u00e4usl",
    "wof:placetype":"venue"
},
  "geometry": {"coordinates":[14.825627327,47.2053909302],"type":"Point"}
}