{
  "type": "Feature",
  "properties": {
    "addr:full":"Parndorfer Str Kiosk Bruck an der Leitha Nieder\u00f6sterreich 2460",
    "addr:postcode":"2460",
    "addr:street":"Niederoesterreich",
    "iso:country":"AT",
    "sg:address":"Parndorfer Str Kiosk",
    "sg:city":"Bruck an der Leitha",
    "sg:orig_category":"Tabaktrafiken",
    "sg:phone":"+43 2162 65347",
    "sg:postcode":"2460",
    "sg:province":"Nieder\u00f6sterreich",
    "wof:name":"Kath Gertrude",
    "wof:placetype":"venue"
},
  "geometry": {"coordinates":[16.7890758514,48.0195236206],"type":"Point"}
}