{
  "type": "Feature",
  "properties": {
    "addr:full":"Postg 2 Thalheim Steiermark 8754",
    "addr:housenumber":"2",
    "addr:postcode":"8754",
    "addr:street":"Postg",
    "iso:country":"AT",
    "sg:address":"Postg 2",
    "sg:city":"Thalheim",
    "sg:orig_category":"Holzwaren",
    "sg:phone":"+43 3579 2112",
    "sg:postcode":"8754",
    "sg:province":"Steiermark",
    "wof:name":"Sch\u00f6ttl G\u00fcnther Mag",
    "wof:placetype":"venue"
},
  "geometry": {"coordinates":[14.5908231735,47.1951637268],"type":"Point"}
}