{
  "type": "Feature",
  "properties": {
    "addr:full":"Tegetthoffstr 26 Linz Ober\u00f6sterreich 4020",
    "addr:housenumber":"26",
    "addr:postcode":"4020",
    "addr:street":"Tegetthoffstr",
    "iso:country":"AT",
    "sg:address":"Tegetthoffstr 26",
    "sg:city":"Linz",
    "sg:orig_category":"Behinderungen / Leben Mit Behinderungen",
    "sg:phone":"+43 732 652842",
    "sg:postcode":"4020",
    "sg:province":"Ober\u00f6sterreich",
    "wof:name":"Ober\u00f6sterreichischer Behindertensportverband",
    "wof:placetype":"venue"
},
  "geometry": {"coordinates":[14.2872638702,48.293838501],"type":"Point"}
}