{
  "type": "Feature",
  "properties": {
    "addr:full":"Osterleiteng 7a Wien Wien 1190",
    "addr:housenumber":"7a",
    "addr:postcode":"1190",
    "addr:street":"Osterleiteng",
    "iso:country":"AT",
    "sg:address":"Osterleiteng 7a",
    "sg:city":"Wien",
    "sg:orig_category":"Textilwaren / Erzeugung U Gro\u00c3\u0178handel",
    "sg:phone":"+43 1 36917740",
    "sg:postcode":"1190",
    "sg:province":"Wien",
    "wof:name":"Luif GesmbH",
    "wof:placetype":"venue"
},
  "geometry": {"coordinates":[16.3570899963,48.239818573],"type":"Point"}
}