{
  "type": "Feature",
  "properties": {
    "addr:full":"Oskar-Helmer-Str 63 Traiskirchen Nieder\u00f6sterreich 2514",
    "addr:housenumber":"63",
    "addr:postcode":"2514",
    "addr:street":"Oskar-Helmer-Str;Niederoesterreich",
    "iso:country":"AT",
    "sg:address":"Oskar-Helmer-Str 63",
    "sg:city":"Traiskirchen",
    "sg:classifiers":[
        {
            "category":"Professional",
            "subcategory":"Computer Services",
            "type":"Services"
        }
    ],
    "sg:phone":"+43 2252 563110",
    "sg:postcode":"2514",
    "sg:province":"Nieder\u00f6sterreich",
    "sg:tags":[
        "software"
    ],
    "wof:name":"Solid - Soft EDV GsmbH",
    "wof:placetype":"venue"
},
  "geometry": {"coordinates":[16.2881336212,48.0227813721],"type":"Point"}
}