{
  "type": "Feature",
  "properties": {
    "addr:full":"Dorf 39 Erl Tirol 6343",
    "addr:housenumber":"39",
    "addr:postcode":"6343",
    "addr:street":"Dorf;Tirol",
    "iso:country":"AT",
    "sg:address":"Dorf 39",
    "sg:city":"Erl",
    "sg:orig_category":"Tourismusinformation U -Organisationen",
    "sg:phone":"+43 4353 738117",
    "sg:postcode":"6343",
    "sg:province":"Tirol",
    "wof:name":"Tourismusverband Kufstein",
    "wof:placetype":"venue"
},
  "geometry": {"coordinates":[12.1794652939,47.682762146],"type":"Point"}
}