{
  "type": "Feature",
  "properties": {
    "iso:country":"AT",
    "sg:address":"Liebhartsg 4",
    "sg:city":"Wien",
    "sg:orig_category":"Drehereien",
    "sg:phone":"+43 1 49317160",
    "sg:postcode":"1160",
    "sg:province":"Wien",
    "wof:name":"G\u00fcntner & Schimek GmbH",
    "wof:placetype":"venue"
},
  "geometry": {"coordinates":[16.2933216095,48.2157440186],"type":"Point"}
}