{
  "type": "Feature",
  "properties": {
    "addr:full":"Unterfeldstr 11 Lauterach Vorarlberg 6923",
    "addr:housenumber":"11",
    "addr:postcode":"6923",
    "addr:street":"Unterfeldstr",
    "iso:country":"AT",
    "sg:address":"Unterfeldstr 11",
    "sg:city":"Lauterach",
    "sg:orig_category":"Blumeneinzelhandel",
    "sg:phone":"+43 4355 7476750",
    "sg:postcode":"6923",
    "sg:province":"Vorarlberg",
    "wof:name":"Pfeiffer-Blumen",
    "wof:placetype":"venue"
},
  "geometry": {"coordinates":[9.7207651138,47.4780044556],"type":"Point"}
}