{
  "type": "Feature",
  "properties": {
    "addr:full":"Dr.-Adolf-Sch\u00e4rf-Pl 7 Trieben Steiermark 8784",
    "addr:housenumber":"7",
    "addr:postcode":"8784",
    "addr:street":"Dr.-Adolf-Schaerf-Pl",
    "iso:country":"AT",
    "sg:address":"Dr.-Adolf-Sch\u00e4rf-Pl 7",
    "sg:city":"Trieben",
    "sg:orig_category":"Hauptschulen",
    "sg:phone":"+43 4336 1521001",
    "sg:postcode":"8784",
    "sg:province":"Steiermark",
    "wof:name":"Hauptschule",
    "wof:placetype":"venue"
},
  "geometry": {"coordinates":[14.488202095,47.4858207703],"type":"Point"}
}