{
  "type": "Feature",
  "properties": {
    "addr:full":"Stadelweg 5 Wundschuh Steiermark 8142",
    "addr:housenumber":"5",
    "addr:postcode":"8142",
    "addr:street":"Stadelweg",
    "iso:country":"AT",
    "sg:address":"Stadelweg 5",
    "sg:city":"Wundschuh",
    "sg:orig_category":"Bauunternehmen",
    "sg:phone":"+43 3135 55918",
    "sg:postcode":"8142",
    "sg:province":"Steiermark",
    "wof:name":"H\u00f6fler Bau GmbH",
    "wof:placetype":"venue"
},
  "geometry": {"coordinates":[15.4459695816,46.9407501221],"type":"Point"}
}