{
  "type": "Feature",
  "properties": {
    "addr:full":"Hauptstr 16 Untersiebenbrunn Nieder\u00f6sterreich 2284",
    "addr:housenumber":"16",
    "addr:postcode":"2284",
    "addr:street":"Hauptstr",
    "iso:country":"AT",
    "sg:address":"Hauptstr 16",
    "sg:city":"Untersiebenbrunn",
    "sg:orig_category":"Gemeinden",
    "sg:phone":"+43 2286 2320",
    "sg:postcode":"2284",
    "sg:province":"Nieder\u00f6sterreich",
    "wof:name":"Gemeinde Untersiebenbrunn",
    "wof:placetype":"venue"
},
  "geometry": {"coordinates":[16.7451381683,48.2558135986],"type":"Point"}
}