{
  "type": "Feature",
  "properties": {
    "addr:full":"Hirschenwies 53 Weitra Nieder\u00f6sterreich 3970",
    "addr:housenumber":"53",
    "addr:postcode":"3970",
    "addr:street":"Hirschenwies",
    "iso:country":"AT",
    "sg:address":"Hirschenwies 53",
    "sg:city":"Weitra",
    "sg:classifiers":[
        {
            "category":"Professional",
            "subcategory":"Advertising",
            "type":"Services"
        }
    ],
    "sg:phone":"+43 2858 5236",
    "sg:postcode":"3970",
    "sg:province":"Nieder\u00f6sterreich",
    "sg:tags":[
        "glass",
        "made",
        "gift",
        "crystal"
    ],
    "sg:website":"kristallstudio.at",
    "wof:name":"Hirschenwieser Bleikristall Erwin Weber",
    "wof:placetype":"venue"
},
  "geometry": {"coordinates":[14.8928060532,48.7005844116],"type":"Point"}
}