{
  "type": "Feature",
  "properties": {
    "addr:full":"Untere Hauptstr 16 Kohfidisch Burgenland 7512",
    "addr:housenumber":"16",
    "addr:postcode":"7512",
    "addr:street":"Untere Hauptstr",
    "iso:country":"AT",
    "sg:address":"Untere Hauptstr 16",
    "sg:city":"Kohfidisch",
    "sg:orig_category":"Non-Classified Establishments",
    "sg:phone":"+43 5 91331245",
    "sg:postcode":"7512",
    "sg:province":"Burgenland",
    "wof:name":"Gendarmerieposten",
    "wof:placetype":"venue"
},
  "geometry": {"coordinates":[16.3577880859,47.175037384],"type":"Point"}
}