{
  "type": "Feature",
  "properties": {
    "iso:country":"AT",
    "sg:address":"Ostbach 102a",
    "sg:city":"Leutasch",
    "sg:classifiers":[
        {
            "category":"Travel",
            "subcategory":"Hotels & Motels",
            "type":"Entertainment"
        }
    ],
    "sg:phone":"+43 5214 63040",
    "sg:postcode":"6105",
    "sg:province":"Tirol",
    "wof:name":"Alpenhotel Karwendel",
    "wof:placetype":"venue"
},
  "geometry": {"coordinates":[11.1333389282,47.3586730957],"type":"Point"}
}