{
  "type": "Feature",
  "properties": {
    "addr:full":"Moosfeldstr 1/B/4 Bergheim Salzburg 5101",
    "addr:housenumber":"1 / b / 4",
    "addr:postcode":"5101",
    "addr:street":"Moosfeldstr;Salzburg",
    "iso:country":"AT",
    "sg:address":"Moosfeldstr 1/B/4",
    "sg:city":"Bergheim",
    "sg:orig_category":"Bekleidung / Erzeugung U Gro\u00c3\u0178handel",
    "sg:phone":"+43 4366 2459531",
    "sg:postcode":"5101",
    "sg:province":"Salzburg",
    "wof:name":"Biondi Mode HandelsgmbH",
    "wof:placetype":"venue"
},
  "geometry": {"coordinates":[13.057888031,47.8406944275],"type":"Point"}
}