{
  "type": "Feature",
  "properties": {
    "iso:country":"AT",
    "sg:address":"Vordere Zollamtsstr 3",
    "sg:city":"Wien",
    "sg:orig_category":"Non-Classified Establishments",
    "sg:phone":"+43 1 711250",
    "sg:postcode":"1030",
    "sg:province":"Wien",
    "wof:name":"Punzierungsamt Wien II",
    "wof:placetype":"venue"
},
  "geometry": {"coordinates":[16.3849964142,48.2095031738],"type":"Point"}
}