{
  "type": "Feature",
  "properties": {
    "addr:full":"Dr.-Karl-Renner-Str 9 Eisenerz Steiermark 8790",
    "addr:housenumber":"9",
    "addr:postcode":"8790",
    "addr:street":"Dr.-Karl-Renner-Str",
    "iso:country":"AT",
    "sg:address":"Dr.-Karl-Renner-Str 9",
    "sg:city":"Eisenerz",
    "sg:orig_category":"Fleischhauereien",
    "sg:phone":"+43 3848 3095",
    "sg:postcode":"8790",
    "sg:province":"Steiermark",
    "wof:name":"Moser Franz",
    "wof:placetype":"venue"
},
  "geometry": {"coordinates":[14.8873815536,47.5409011841],"type":"Point"}
}