{
  "type": "Feature",
  "properties": {
    "addr:full":"Bichlstr 5 Kitzb\u00fchel Tirol 6370",
    "addr:housenumber":"5",
    "addr:postcode":"6370",
    "addr:street":"Bichlstr;Tirol",
    "iso:country":"AT",
    "sg:address":"Bichlstr 5",
    "sg:city":"Kitzb\u00fchel",
    "sg:orig_category":"Boutiquen",
    "sg:phone":"+43 5356 72033",
    "sg:postcode":"6370",
    "sg:province":"Tirol",
    "wof:name":"Esprit-Store Inh Johanna Wimmer KEG",
    "wof:placetype":"venue"
},
  "geometry": {"coordinates":[12.3925590515,47.4451675415],"type":"Point"}
}