{
  "type": "Feature",
  "properties": {
    "addr:full":"St Veiter Str 106 Klagenfurt K\u00e4rnten 9020",
    "addr:housenumber":"106",
    "addr:postcode":"9020",
    "addr:street":"St Veiter Str;Kaernten",
    "iso:country":"AT",
    "sg:address":"St Veiter Str 106",
    "sg:city":"Klagenfurt",
    "sg:orig_category":"Gesundheit / Allgemeine Informationsstellen",
    "sg:phone":"+43 699 19141914",
    "sg:postcode":"9020",
    "sg:province":"K\u00e4rnten",
    "wof:name":"REH-VITAL AUSTRIA Gesundheits- und Wellnessprodukte",
    "wof:placetype":"venue"
},
  "geometry": {"coordinates":[14.3128900528,46.6372718811],"type":"Point"}
}