{
  "type": "Feature",
  "properties": {
    "iso:country":"AT",
    "sg:address":"Tuchlauben 14",
    "sg:city":"Wien",
    "sg:orig_category":"Banken U Sparkassen",
    "sg:phone":"+43 4350 5333",
    "sg:postcode":"1010",
    "sg:province":"Wien",
    "wof:name":"BTV - Bank f\u00fcr Tirol und Vorarlberg AG",
    "wof:placetype":"venue"
},
  "geometry": {"coordinates":[16.3711624146,48.210483551],"type":"Point"}
}