{
  "type": "Feature",
  "properties": {
    "addr:full":"Baderg 5 Peuerbach Ober\u00f6sterreich 4722",
    "addr:housenumber":"5",
    "addr:postcode":"4722",
    "addr:street":"Baderg",
    "iso:country":"AT",
    "sg:address":"Baderg 5",
    "sg:city":"Peuerbach",
    "sg:orig_category":"Gemeinden",
    "sg:phone":"+43 7276 23010",
    "sg:postcode":"4722",
    "sg:province":"Ober\u00f6sterreich",
    "wof:name":"Gemeindeamt Steegen",
    "wof:placetype":"venue"
},
  "geometry": {"coordinates":[13.7729463577,48.3276634216],"type":"Point"}
}