{
  "type": "Feature",
  "properties": {
    "addr:full":"Schulg 10 Zeltweg Steiermark 8740",
    "addr:housenumber":"10",
    "addr:postcode":"8740",
    "addr:street":"Schulg",
    "iso:country":"AT",
    "sg:address":"Schulg 10",
    "sg:city":"Zeltweg",
    "sg:orig_category":"Friseure U Frisiersalons",
    "sg:phone":"+43 3577 26620",
    "sg:postcode":"8740",
    "sg:province":"Steiermark",
    "wof:name":"Hair & Style Friseur",
    "wof:placetype":"venue"
},
  "geometry": {"coordinates":[14.7505702972,47.1888504028],"type":"Point"}
}