{
  "type": "Feature",
  "properties": {
    "iso:country":"AT",
    "sg:address":"Wienerbergstr 25b",
    "sg:city":"Wien",
    "sg:classifiers":[
        {
            "category":"Home & Garden",
            "subcategory":"Building Materials",
            "type":"Retail Goods"
        }
    ],
    "sg:phone":"+43 4316 029655",
    "sg:postcode":"1100",
    "sg:province":"Wien",
    "sg:tags":[
        "baustoffe",
        "-material",
        "u"
    ],
    "wof:name":"Paul Werner GesmbH",
    "wof:placetype":"venue"
},
  "geometry": {"coordinates":[16.3402271271,48.1705436707],"type":"Point"}
}