{
  "type": "Feature",
  "properties": {
    "addr:full":"Hellbrunner Str 3 Salzburg Salzburg 5020",
    "addr:housenumber":"3",
    "addr:postcode":"5020",
    "addr:street":"Str;Salzburg",
    "iso:country":"AT",
    "sg:address":"Hellbrunner Str 3",
    "sg:city":"Salzburg",
    "sg:orig_category":"Architekten",
    "sg:phone":"+43 662 841712",
    "sg:postcode":"5020",
    "sg:province":"Salzburg",
    "wof:name":"ONE ROOM - Meinhart Karl Dipl Ing und Dipl Ing Huber Georg",
    "wof:placetype":"venue"
},
  "geometry": {"coordinates":[13.0545930862,47.7967071533],"type":"Point"}
}