{
  "type": "Feature",
  "properties": {
    "addr:full":"Dorfstr 297 Bramberg am Wildkogel Salzburg 5733",
    "addr:housenumber":"297",
    "addr:postcode":"5733",
    "addr:street":"Dorfstr;Salzburg",
    "iso:country":"AT",
    "sg:address":"Dorfstr 297",
    "sg:city":"Bramberg am Wildkogel",
    "sg:orig_category":"Pensionen / Privatzimmer",
    "sg:phone":"+43 4365 667349",
    "sg:postcode":"5733",
    "sg:province":"Salzburg",
    "wof:name":"Pension Hubertus",
    "wof:placetype":"venue"
},
  "geometry": {"coordinates":[12.3462018967,47.2723884583],"type":"Point"}
}