{
  "type": "Feature",
  "properties": {
    "iso:country":"AT",
    "sg:address":"Dorfstr 297",
    "sg:city":"Bramberg am Wildkogel",
    "sg:orig_category":"Pensionen / Privatzimmer",
    "sg:phone":"+43 4365 667349",
    "sg:postcode":"5733",
    "sg:province":"Salzburg",
    "wof:name":"Pension Hubertus",
    "wof:placetype":"venue"
},
  "geometry": {"coordinates":[12.3462018967,47.2723884583],"type":"Point"}
}