{
  "type": "Feature",
  "properties": {
    "addr:full":"H\u00f6tzlarn 2 St. Martin im Innkreis Ober\u00f6sterreich 4973",
    "addr:housenumber":"2",
    "addr:postcode":"4973",
    "addr:street":"Hoetzlarn",
    "iso:country":"AT",
    "sg:address":"H\u00f6tzlarn 2",
    "sg:city":"St. Martin im Innkreis",
    "sg:orig_category":"Autohandel",
    "sg:phone":"+43 4377 5181180",
    "sg:postcode":"4973",
    "sg:province":"Ober\u00f6sterreich",
    "wof:name":"Stranzinger Josef",
    "wof:placetype":"venue"
},
  "geometry": {"coordinates":[13.4180746078,48.261505127],"type":"Point"}
}