{
  "type": "Feature",
  "properties": {
    "addr:full":"Bauerng 41 Horitschon Burgenland 7312",
    "addr:housenumber":"41",
    "addr:postcode":"7312",
    "addr:street":"Bauerng",
    "iso:country":"AT",
    "sg:address":"Bauerng 41",
    "sg:city":"Horitschon",
    "sg:orig_category":"Volksschulen",
    "sg:phone":"+43 2610 43321",
    "sg:postcode":"7312",
    "sg:province":"Burgenland",
    "wof:name":"Volksschule",
    "wof:placetype":"venue"
},
  "geometry": {"coordinates":[16.5804424286,47.5922660828],"type":"Point"}
}