{
  "type": "Feature",
  "properties": {
    "addr:full":"Strelzhofg 60 Wiener Neustadt Nieder\u00f6sterreich 2700",
    "addr:housenumber":"60",
    "addr:postcode":"2700",
    "addr:street":"Strelzhofg",
    "iso:country":"AT",
    "sg:address":"Strelzhofg 60",
    "sg:city":"Wiener Neustadt",
    "sg:orig_category":"Bodenverlegung",
    "sg:phone":"+43 2622 87898",
    "sg:postcode":"2700",
    "sg:province":"Nieder\u00f6sterreich",
    "wof:name":"ARMORSTONES KIESBODEN GesmbH",
    "wof:placetype":"venue"
},
  "geometry": {"coordinates":[16.2217483521,47.8083610535],"type":"Point"}
}