{
  "type": "Feature",
  "properties": {
    "iso:country":"AT",
    "sg:address":"G\u00f6riach 79",
    "sg:city":"Pusarnitz",
    "sg:classifiers":[
        {
            "category":"Bars & Pubs",
            "subcategory":"Lounge",
            "type":"Food & Drink"
        }
    ],
    "sg:phone":"+43 4769 3124",
    "sg:postcode":"9812",
    "sg:province":"K\u00e4rnten",
    "sg:tags":[
        "aluminium",
        "railing"
    ],
    "wof:name":"Metallbau Johann Steiner",
    "wof:placetype":"venue"
},
  "geometry": {"coordinates":[13.4003372192,46.8415565491],"type":"Point"}
}