{
  "type": "Feature",
  "properties": {
    "addr:full":"Heinestr 23 Wien Wien 1020",
    "addr:housenumber":"23",
    "addr:postcode":"1020",
    "addr:street":"Heinestr",
    "iso:country":"AT",
    "sg:address":"Heinestr 23",
    "sg:city":"Wien",
    "sg:orig_category":"Bars-Cafes",
    "sg:phone":"+43 1 2168553",
    "sg:postcode":"1020",
    "sg:province":"Wien",
    "wof:name":"Bar Venusfalle",
    "wof:placetype":"venue"
},
  "geometry": {"coordinates":[16.3861026764,48.2203979492],"type":"Point"}
}