{
  "type": "Feature",
  "properties": {
    "addr:full":"Guckofenweg 1 Reichenfels K\u00e4rnten 9463",
    "addr:housenumber":"1",
    "addr:postcode":"9463",
    "addr:street":"Guckofenweg;Kaernten",
    "iso:country":"AT",
    "sg:address":"Guckofenweg 1",
    "sg:city":"Reichenfels",
    "sg:orig_category":"Transportunternehmen",
    "sg:phone":"+43 4359 2209",
    "sg:postcode":"9463",
    "sg:province":"K\u00e4rnten",
    "wof:name":"Peinsitt Johannes",
    "wof:placetype":"venue"
},
  "geometry": {"coordinates":[14.7386226654,47.0071792603],"type":"Point"}
}