{
  "type": "Feature",
  "properties": {
    "addr:full":"Billrothstr 79a Wien Wien 1190",
    "addr:housenumber":"79a",
    "addr:postcode":"1190",
    "addr:street":"Billrothstr",
    "iso:country":"AT",
    "sg:address":"Billrothstr 79a",
    "sg:city":"Wien",
    "sg:orig_category":"Boutiquen",
    "sg:phone":"+43 1 3206860",
    "sg:postcode":"1190",
    "sg:province":"Wien",
    "wof:name":"CACHIL",
    "wof:placetype":"venue"
},
  "geometry": {"coordinates":[16.3435668945,48.2451095581],"type":"Point"}
}