{
  "type": "Feature",
  "properties": {
    "addr:full":"Bahnhofstr 16 Scheifling Steiermark 8811",
    "addr:housenumber":"16",
    "addr:postcode":"8811",
    "addr:street":"Bahnhofstr",
    "iso:country":"AT",
    "sg:address":"Bahnhofstr 16",
    "sg:city":"Scheifling",
    "sg:orig_category":"Bauunternehmen",
    "sg:phone":"+43 3582 86330",
    "sg:postcode":"8811",
    "sg:province":"Steiermark",
    "wof:name":"Teerag-Asdag AG",
    "wof:placetype":"venue"
},
  "geometry": {"coordinates":[14.4183340073,47.1462097168],"type":"Point"}
}