{
  "type": "Feature",
  "properties": {
    "addr:full":"Grabeng 20 Baden Nieder\u00f6sterreich 2500",
    "addr:housenumber":"20",
    "addr:postcode":"2500",
    "addr:street":"Grabeng;Niederoesterreich",
    "iso:country":"AT",
    "sg:address":"Grabeng 20",
    "sg:city":"Baden",
    "sg:orig_category":"Eisenwaren",
    "sg:phone":"+43 2252 871400",
    "sg:postcode":"2500",
    "sg:province":"Nieder\u00f6sterreich",
    "wof:name":"Schumits L & Co GesmbH",
    "wof:placetype":"venue"
},
  "geometry": {"coordinates":[16.23554039,48.0083274841],"type":"Point"}
}