{
  "type": "Feature",
  "properties": {
    "addr:full":"Hauptstr 2 Deutschlandsberg Steiermark 8530",
    "addr:housenumber":"2",
    "addr:postcode":"8530",
    "addr:street":"Hauptstr",
    "iso:country":"AT",
    "sg:address":"Hauptstr 2",
    "sg:city":"Deutschlandsberg",
    "sg:orig_category":"Gemeinden",
    "sg:phone":"+43 3461 280",
    "sg:postcode":"8530",
    "sg:province":"Steiermark",
    "wof:name":"Gemeindeamt Trah\u00fctten",
    "wof:placetype":"venue"
},
  "geometry": {"coordinates":[15.1522769928,46.822971344],"type":"Point"}
}