{
  "type": "Feature",
  "properties": {
    "iso:country":"AT",
    "sg:address":"Nr 5a",
    "sg:city":"Kammern im Liesingtal",
    "sg:orig_category":"Paletten / Erzeugung U Gro\u00c3\u0178handel",
    "sg:phone":"+43 3844 20042",
    "sg:postcode":"8773",
    "sg:province":"Steiermark",
    "wof:name":"Lichtenegger Herbert",
    "wof:placetype":"venue"
},
  "geometry": {"coordinates":[14.9017133713,47.3931808472],"type":"Point"}
}