{
  "type": "Feature",
  "properties": {
    "iso:country":"AT",
    "sg:address":"Hubertusweg 1",
    "sg:city":"Finkenstein",
    "sg:orig_category":"Pensionen / Privatzimmer",
    "sg:phone":"+43 4254 2037",
    "sg:postcode":"9584",
    "sg:province":"K\u00e4rnten",
    "wof:name":"Haus Hubertus",
    "wof:placetype":"venue"
},
  "geometry": {"coordinates":[13.8712682724,46.5593566895],"type":"Point"}
}