{
  "type": "Feature",
  "properties": {
    "addr:full":"Hainfelder Str 9 Weissenbach an der Triesting Nieder\u00f6sterreich 2564",
    "addr:housenumber":"9",
    "addr:postcode":"2564",
    "addr:street":"Str;Niederoesterreich",
    "iso:country":"AT",
    "sg:address":"Hainfelder Str 9",
    "sg:city":"Weissenbach an der Triesting",
    "sg:orig_category":"Autohandel",
    "sg:phone":"+43 4367 64185760",
    "sg:postcode":"2564",
    "sg:province":"Nieder\u00f6sterreich",
    "wof:name":"Aky\u00fcz M Autohandel MAC",
    "wof:placetype":"venue"
},
  "geometry": {"coordinates":[16.0270557404,47.9907226562],"type":"Point"}
}