{
  "type": "Feature",
  "properties": {
    "addr:full":"Schweizer Str 40 Dornbirn Vorarlberg 6850",
    "addr:postcode":"6850",
    "addr:street":"Str 40",
    "iso:country":"AT",
    "sg:address":"Schweizer Str 40",
    "sg:city":"Dornbirn",
    "sg:orig_category":"Maschinenbau",
    "sg:phone":"+43 4355 723070",
    "sg:postcode":"6850",
    "sg:province":"Vorarlberg",
    "wof:name":"Ulmer GmbH Profil- und F\u00f6rdertechnik",
    "wof:placetype":"venue"
},
  "geometry": {"coordinates":[9.7213230133,47.3985671997],"type":"Point"}
}