{
  "type": "Feature",
  "properties": {
    "addr:full":"Nr 8 Persenbeug Nieder\u00f6sterreich 3680",
    "addr:postcode":"3680",
    "addr:street":"Nr;Niederoesterreich",
    "iso:country":"AT",
    "sg:address":"Nr 8",
    "sg:city":"Persenbeug",
    "sg:classifiers":[
        {
            "category":"Taxi",
            "type":"Transportation"
        }
    ],
    "sg:phone":"+43 4374 1252200",
    "sg:postcode":"3680",
    "sg:province":"Nieder\u00f6sterreich",
    "sg:tags":[
        "personentransporte",
        "u"
    ],
    "wof:name":"Ihr Taxi Gruber GmbH",
    "wof:placetype":"venue"
},
  "geometry": {"coordinates":[15.0793266296,48.1879043579],"type":"Point"}
}