{
  "type": "Feature",
  "properties": {
    "addr:full":"Nr 20 Gurk K\u00e4rnten 9342",
    "addr:postcode":"9342",
    "addr:street":"Nr;Gurk Kaernten",
    "iso:country":"AT",
    "sg:address":"Nr 20",
    "sg:city":"Gurk",
    "sg:orig_category":"Feuerwehren",
    "sg:phone":"+43 4266 8492",
    "sg:postcode":"9342",
    "sg:province":"K\u00e4rnten",
    "wof:name":"Freiwillige Feuerwehr Pisweg",
    "wof:placetype":"venue"
},
  "geometry": {"coordinates":[14.2920770645,46.8744773865],"type":"Point"}
}