{
  "type": "Feature",
  "properties": {
    "addr:full":"Gallmeyerg 5/16 Wien Wien 1190",
    "addr:housenumber":"5 / 16",
    "addr:postcode":"1190",
    "addr:street":"Gallmeyerg",
    "iso:country":"AT",
    "sg:address":"Gallmeyerg 5/16",
    "sg:city":"Wien",
    "sg:orig_category":"Farb-, Stil- U Typberatung",
    "sg:phone":"+43 664 2002990",
    "sg:postcode":"1190",
    "sg:province":"Wien",
    "wof:name":"Colour Consult Mag",
    "wof:placetype":"venue"
},
  "geometry": {"coordinates":[16.3573951721,48.246055603],"type":"Point"}
}