{
  "type": "Feature",
  "properties": {
    "addr:full":"Nr 3 Peterskirchen Ober\u00f6sterreich 4743",
    "addr:postcode":"4743",
    "addr:street":"Nr;Peterskirchen",
    "iso:country":"AT",
    "sg:address":"Nr 3",
    "sg:city":"Peterskirchen",
    "sg:orig_category":"Non-Classified Establishments",
    "sg:phone":"+43 7750 3412",
    "sg:postcode":"4743",
    "sg:province":"Ober\u00f6sterreich",
    "wof:name":"Pfarramt",
    "wof:placetype":"venue"
},
  "geometry": {"coordinates":[13.5469799042,48.2378959656],"type":"Point"}
}