{
  "type": "Feature",
  "properties": {
    "addr:full":"Stattersdorfer Hauptstr 10 St. P\u00f6lten Nieder\u00f6sterreich 3100",
    "addr:housenumber":"10",
    "addr:postcode":"3100",
    "addr:street":"Stattersdorfer Hauptstr",
    "iso:country":"AT",
    "sg:address":"Stattersdorfer Hauptstr 10",
    "sg:city":"St. P\u00f6lten",
    "sg:orig_category":"Bauunternehmen",
    "sg:phone":"+43 4350 6262428",
    "sg:postcode":"3100",
    "sg:province":"Nieder\u00f6sterreich",
    "wof:name":"Allgemeine Baugesellschaft A Porr AG",
    "wof:placetype":"venue"
},
  "geometry": {"coordinates":[15.6240940094,48.2076377869],"type":"Point"}
}