{
  "type": "Feature",
  "properties": {
    "iso:country":"AT",
    "sg:address":"Puitenweg 15",
    "sg:city":"Inzing",
    "sg:orig_category":"Exporteure U Importeure",
    "sg:phone":"+43 4352 3887347",
    "sg:postcode":"6401",
    "sg:province":"Tirol",
    "wof:name":"Tuma Walter",
    "wof:placetype":"venue"
},
  "geometry": {"coordinates":[11.2036771774,47.2706336975],"type":"Point"}
}