{
  "type": "Feature",
  "properties": {
    "addr:full":"Bahnhof Umgebung 2a Zirl Tirol 6170",
    "addr:housenumber":"2a",
    "addr:postcode":"6170",
    "addr:street":"Bahnhof Umgebung;Tirol",
    "iso:country":"AT",
    "sg:address":"Bahnhof Umgebung 2a",
    "sg:city":"Zirl",
    "sg:orig_category":"Bauunternehmen",
    "sg:phone":"+43 5238 52419",
    "sg:postcode":"6170",
    "sg:province":"Tirol",
    "sg:website":"www.hitthaller.at",
    "wof:name":"Hitthaller & Trixl Bau GesmbH",
    "wof:placetype":"venue"
},
  "geometry": {"coordinates":[11.2304697037,47.2669906616],"type":"Point"}
}