{
  "type": "Feature",
  "properties": {
    "addr:full":"Thumersbacher Str 9 Zell am See Salzburg 5700",
    "addr:housenumber":"9",
    "addr:postcode":"5700",
    "addr:street":"Str;Salzburg",
    "iso:country":"AT",
    "sg:address":"Thumersbacher Str 9",
    "sg:city":"Zell am See",
    "sg:orig_category":"Rettungsdienste",
    "sg:phone":"+43 6542 72919",
    "sg:postcode":"5700",
    "sg:province":"Salzburg",
    "wof:name":"Bergrettung - Leitstelle",
    "wof:placetype":"venue"
},
  "geometry": {"coordinates":[12.8040332794,47.3404464722],"type":"Point"}
}