{
  "type": "Feature",
  "properties": {
    "iso:country":"AT",
    "sg:address":"Ebentaler Strasse 100",
    "sg:city":"Klagenfurt",
    "sg:classifiers":[
        {
            "category":"Conference Center",
            "type":"Public Place"
        }
    ],
    "sg:phone":"+43 463 331310",
    "sg:postcode":"9020",
    "sg:province":"K\u00e4rnten",
    "sg:tags":[
        "chair",
        "easy"
    ],
    "wof:name":"Alexander Petritsch Ges.m.b.H.",
    "wof:placetype":"venue"
},
  "geometry": {"coordinates":[14.3338499069,46.6169242859],"type":"Point"}
}