{
  "type": "Feature",
  "properties": {
    "addr:full":"Alpenstr 6 Bad Hofgastein Salzburg 5630",
    "addr:housenumber":"6",
    "addr:postcode":"5630",
    "addr:street":"Alpenstr;Salzburg",
    "iso:country":"AT",
    "sg:address":"Alpenstr 6",
    "sg:city":"Bad Hofgastein",
    "sg:classifiers":[
        {
            "category":"Travel",
            "subcategory":"Hotels & Motels",
            "type":"Entertainment"
        }
    ],
    "sg:phone":"+43 4364 3266810",
    "sg:postcode":"5630",
    "sg:province":"Salzburg",
    "sg:website":"hotel-bismarck.com",
    "wof:name":"Hotel Bismarck",
    "wof:placetype":"venue"
},
  "geometry": {"coordinates":[13.1103839874,47.1677856445],"type":"Point"}
}