{
  "type": "Feature",
  "properties": {
    "addr:full":"Gmundner Str 1 Schwanenstadt Ober\u00f6sterreich 4690",
    "addr:housenumber":"1",
    "addr:postcode":"4690",
    "addr:street":"Str",
    "iso:country":"AT",
    "sg:address":"Gmundner Str 1",
    "sg:city":"Schwanenstadt",
    "sg:orig_category":"Blumeneinzelhandel",
    "sg:phone":"+43 76732921",
    "sg:postcode":"4690",
    "sg:province":"Ober\u00f6sterreich",
    "wof:name":"Seufer Wasserthal Alexander",
    "wof:placetype":"venue"
},
  "geometry": {"coordinates":[13.7770795822,48.0530395508],"type":"Point"}
}