{
  "type": "Feature",
  "properties": {
    "addr:full":"Hauptpl 38 Frohnleiten Steiermark 8130",
    "addr:housenumber":"38",
    "addr:postcode":"8130",
    "addr:street":"Hauptpl",
    "iso:country":"AT",
    "sg:address":"Hauptpl 38",
    "sg:city":"Frohnleiten",
    "sg:orig_category":"Boutiquen",
    "sg:phone":"+43 3126 4166",
    "sg:postcode":"8130",
    "sg:province":"Steiermark",
    "wof:name":"Boutique Elle",
    "wof:placetype":"venue"
},
  "geometry": {"coordinates":[15.3274116516,47.2710456848],"type":"Point"}
}