{
  "type": "Feature",
  "properties": {
    "addr:full":"Nr 56 Raggal Vorarlberg 6741",
    "addr:postcode":"6741",
    "addr:street":"Nr",
    "iso:country":"AT",
    "sg:address":"Nr 56",
    "sg:city":"Raggal",
    "sg:orig_category":"Genossenschaften",
    "sg:phone":"+43 5553 671",
    "sg:postcode":"6741",
    "sg:province":"Vorarlberg",
    "wof:name":"Maruler Bio-Sennerei regGenmbH",
    "wof:placetype":"venue"
},
  "geometry": {"coordinates":[9.8354673386,47.2117118835],"type":"Point"}
}