{
  "type": "Feature",
  "properties": {
    "addr:full":"Glacisstr 9 Graz Steiermark 8010",
    "addr:housenumber":"9",
    "addr:postcode":"8010",
    "addr:street":"Glacisstr",
    "iso:country":"AT",
    "sg:address":"Glacisstr 9",
    "sg:city":"Graz",
    "sg:orig_category":"Lebens- U Sozialberatung",
    "sg:phone":"+43 316 3373000",
    "sg:postcode":"8010",
    "sg:province":"Steiermark",
    "wof:name":"Mafalda - Beratungsstelle f M\u00e4dchen und junge Frauen",
    "wof:placetype":"venue"
},
  "geometry": {"coordinates":[15.4447660446,47.0767173767],"type":"Point"}
}