{
  "type": "Feature",
  "properties": {
    "addr:full":"Nr 11 St. Martin Salzburg 5092",
    "addr:postcode":"5092",
    "addr:street":"Nr 11",
    "iso:country":"AT",
    "sg:address":"Nr 11",
    "sg:city":"St. Martin",
    "sg:orig_category":"Pensionen / Privatzimmer",
    "sg:phone":"+43 6588 8622",
    "sg:postcode":"5092",
    "sg:province":"Salzburg",
    "wof:name":"Fr\u00fchst\u00fcckspension Schmuck",
    "wof:placetype":"venue"
},
  "geometry": {"coordinates":[12.7057151794,47.5662536621],"type":"Point"}
}