{
  "type": "Feature",
  "properties": {
    "addr:full":"Am Hausberg 1 Maria Enzersdorf Nieder\u00f6sterreich 2344",
    "addr:housenumber":"1",
    "addr:postcode":"2344",
    "addr:street":"Am Hausberg",
    "iso:country":"AT",
    "sg:address":"Am Hausberg 1",
    "sg:city":"Maria Enzersdorf",
    "sg:orig_category":"Hobbyvereine",
    "sg:phone":"+43 2236 24356",
    "sg:postcode":"2344",
    "sg:province":"Nieder\u00f6sterreich",
    "wof:name":"Pfadfindergruppe N\u00f6",
    "wof:placetype":"venue"
},
  "geometry": {"coordinates":[16.2684288025,48.0908851624],"type":"Point"}
}