{
  "type": "Feature",
  "properties": {
    "iso:country":"AT",
    "sg:address":"Kellermanng 5",
    "sg:city":"Wien",
    "sg:orig_category":"Psychotherapie",
    "sg:phone":"+43 1 5265328",
    "sg:postcode":"1070",
    "sg:province":"Wien",
    "wof:name":"Eisner-Aschauer C\u00e4cilia Karin",
    "wof:placetype":"venue"
},
  "geometry": {"coordinates":[16.3513736725,48.2060623169],"type":"Point"}
}