{
  "type": "Feature",
  "properties": {
    "addr:full":"Aredstr 22 Leobersdorf Nieder\u00f6sterreich 2544",
    "addr:housenumber":"22",
    "addr:postcode":"2544",
    "addr:street":"Aredstr",
    "iso:country":"AT",
    "sg:address":"Aredstr 22",
    "sg:city":"Leobersdorf",
    "sg:orig_category":"Dosieranlagen U -Pumpen",
    "sg:phone":"+43 2256 62180",
    "sg:postcode":"2544",
    "sg:province":"Nieder\u00f6sterreich",
    "wof:name":"Lutz Jesco GmbH",
    "wof:placetype":"venue"
},
  "geometry": {"coordinates":[16.1976070404,47.9272956848],"type":"Point"}
}