{
  "type": "Feature",
  "properties": {
    "addr:full":"Hasling 6 Goldegg Salzburg 5622",
    "addr:housenumber":"6",
    "addr:postcode":"5622",
    "addr:street":"Hasling;Salzburg",
    "iso:country":"AT",
    "sg:address":"Hasling 6",
    "sg:city":"Goldegg",
    "sg:orig_category":"Holzbau",
    "sg:phone":"+43 4366 43001268",
    "sg:postcode":"5622",
    "sg:province":"Salzburg",
    "wof:name":"Holzbau Martin Trattner",
    "wof:placetype":"venue"
},
  "geometry": {"coordinates":[13.099439621,47.3187294006],"type":"Point"}
}