{
  "type": "Feature",
  "properties": {
    "addr:full":"Nr. 15  Lochen Ober\u00f6sterreich 5221",
    "addr:postcode":"5221",
    "addr:street":"Oberoesterreich",
    "iso:country":"AT",
    "sg:address":"Nr. 15 ",
    "sg:city":"Lochen",
    "sg:classifiers":[
        {
            "category":"Banks & Credit Unions",
            "subcategory":"Investment Brokerage",
            "type":"Services"
        }
    ],
    "sg:phone":"+43 4377 458292",
    "sg:postcode":"5221",
    "sg:province":"Ober\u00f6sterreich",
    "sg:tags":[
        "-",
        "transport",
        "related"
    ],
    "wof:name":"HERBERT GR\u00d6MER",
    "wof:placetype":"venue"
},
  "geometry": {"coordinates":[13.1802692413,48.0075187683],"type":"Point"}
}