{
  "type": "Feature",
  "properties": {
    "iso:country":"AT",
    "sg:address":"Hauptstr 19",
    "sg:city":"Aigen im M\u00fchlkreis",
    "sg:orig_category":"Rettungsdienste",
    "sg:phone":"+43 7281 6244",
    "sg:postcode":"4160",
    "sg:province":"Ober\u00f6sterreich",
    "wof:name":"Rotes Kreuz \u00d6sterr Ortsstelle Aigen im M\u00fchlkreis",
    "wof:placetype":"venue"
},
  "geometry": {"coordinates":[13.9687719345,48.6440467834],"type":"Point"}
}