{
  "type": "Feature",
  "properties": {
    "iso:country":"AT",
    "sg:address":"Raiffeisenstr 97",
    "sg:city":"Graz",
    "sg:orig_category":"Speditionen",
    "sg:phone":"+43 316 4737370",
    "sg:postcode":"8010",
    "sg:province":"Steiermark",
    "wof:name":"Schneckenreither GesmbH",
    "wof:placetype":"venue"
},
  "geometry": {"coordinates":[15.4507369995,47.0487937927],"type":"Point"}
}