{
  "type": "Feature",
  "properties": {
    "iso:country":"AT",
    "sg:address":"Bahnhofstr 11",
    "sg:city":"Windischgarsten",
    "sg:orig_category":"Textilwaren / Einzelhandel",
    "sg:phone":"+43 4375 6220632",
    "sg:postcode":"4580",
    "sg:province":"Ober\u00f6sterreich",
    "wof:name":"NKD",
    "wof:placetype":"venue"
},
  "geometry": {"coordinates":[14.3282003403,47.7204093933],"type":"Point"}
}