{
  "type": "Feature",
  "properties": {
    "addr:full":"Staudg 70 Wien Wien 1180",
    "addr:housenumber":"70",
    "addr:postcode":"1180",
    "addr:street":"Staudg",
    "iso:country":"AT",
    "sg:address":"Staudg 70",
    "sg:city":"Wien",
    "sg:classifiers":[
        {
            "category":"Utilities",
            "subcategory":"Refuse",
            "type":"Services"
        }
    ],
    "sg:phone":"+43 4314 078119",
    "sg:postcode":"1180",
    "sg:province":"Wien",
    "sg:tags":[
        "catering"
    ],
    "sg:website":"catering.at",
    "wof:name":"Adventure Catering Eichinger & Scheiblauer OEG",
    "wof:placetype":"venue"
},
  "geometry": {"coordinates":[16.3445625305,48.2262420654],"type":"Point"}
}