{
  "type": "Feature",
  "properties": {
    "addr:full":"Tullner Str 4a St. Andr\u00e4-W\u00f6rdern Nieder\u00f6sterreich 3423",
    "addr:postcode":"3423",
    "addr:street":"Str 4A St.;Niederoesterreich",
    "iso:country":"AT",
    "sg:address":"Tullner Str 4a",
    "sg:city":"St. Andr\u00e4-W\u00f6rdern",
    "sg:orig_category":"Banken U Sparkassen",
    "sg:phone":"+43 4322 4232367",
    "sg:postcode":"3423",
    "sg:province":"Nieder\u00f6sterreich",
    "wof:name":"Tullnerfelder Volksbank regGenmbH",
    "wof:placetype":"venue"
},
  "geometry": {"coordinates":[16.2101764679,48.3275222778],"type":"Point"}
}