{
  "type": "Feature",
  "properties": {
    "addr:full":"Siegenfelder Weg 79 Heiligenkreuz im Wienerwald Nieder\u00f6sterreich 2532",
    "addr:housenumber":"79",
    "addr:postcode":"2532",
    "addr:street":"Siegenfelder Weg",
    "iso:country":"AT",
    "sg:address":"Siegenfelder Weg 79",
    "sg:city":"Heiligenkreuz im Wienerwald",
    "sg:orig_category":"Cleaning Agents, Neutral, Alkaline, Acidic",
    "sg:phone":"+43 2258 8381",
    "sg:postcode":"2532",
    "sg:province":"Nieder\u00f6sterreich",
    "sg:website":"user.xpoint.at/kasamas",
    "wof:name":"Kasamas Ges.m.b.H.",
    "wof:placetype":"venue"
},
  "geometry": {"coordinates":[16.1279754639,48.0560836792],"type":"Point"}
}