{
  "type": "Feature",
  "properties": {
    "addr:full":"Nr 138 Oberhofen im Inntal Tirol 6406",
    "addr:postcode":"6406",
    "addr:street":"Nr 138;Tirol",
    "iso:country":"AT",
    "sg:address":"Nr 138",
    "sg:city":"Oberhofen im Inntal",
    "sg:orig_category":"Innenausbau",
    "sg:phone":"+43 5262 63411",
    "sg:postcode":"6406",
    "sg:province":"Tirol",
    "wof:name":"Angermair G\u00fcnther",
    "wof:placetype":"venue"
},
  "geometry": {"coordinates":[11.0959024429,47.3035469055],"type":"Point"}
}