{
  "type": "Feature",
  "properties": {
    "addr:full":"Waidhofner Str 34 Amstetten Nieder\u00f6sterreich 3300",
    "addr:housenumber":"34",
    "addr:postcode":"3300",
    "addr:street":"Str;Niederoesterreich",
    "iso:country":"AT",
    "sg:address":"Waidhofner Str 34",
    "sg:city":"Amstetten",
    "sg:orig_category":"Fitnesscenter",
    "sg:phone":"+43 4374 7264456",
    "sg:postcode":"3300",
    "sg:province":"Nieder\u00f6sterreich",
    "wof:name":"Fitness- u Sportstudio Haas",
    "wof:placetype":"venue"
},
  "geometry": {"coordinates":[14.8657684326,48.121257782],"type":"Point"}
}