{
  "type": "Feature",
  "properties": {
    "iso:country":"AT",
    "sg:address":"Marktstr 4",
    "sg:city":"Dornbirn",
    "sg:orig_category":"Damenmoden",
    "sg:phone":"+43 5572 210165",
    "sg:postcode":"6850",
    "sg:province":"Vorarlberg",
    "wof:name":"Facona Fashion GmbH",
    "wof:placetype":"venue"
},
  "geometry": {"coordinates":[9.7424411774,47.4131584167],"type":"Point"}
}