{
  "type": "Feature",
  "properties": {
    "addr:full":"Alpendorf 11a St. Johann im Pongau Salzburg 5600",
    "addr:housenumber":"11a",
    "addr:postcode":"5600",
    "addr:street":"Alpendorf;Salzburg",
    "iso:country":"AT",
    "sg:address":"Alpendorf 11a",
    "sg:city":"St. Johann im Pongau",
    "sg:classifiers":[
        {
            "category":"Park",
            "subcategory":"Provincial",
            "type":"Public Place"
        }
    ],
    "sg:phone":"+43 4364 126743",
    "sg:postcode":"5600",
    "sg:province":"Salzburg",
    "sg:tags":[
        "u",
        "ski-",
        "snowboardschulen"
    ],
    "wof:name":"Skischule St. Johann-Alpendorf in Rot-Wei\u00df-Rot",
    "wof:placetype":"venue"
},
  "geometry": {"coordinates":[13.1962547302,47.3199462891],"type":"Point"}
}