{
  "type": "Feature",
  "properties": {
    "addr:full":"Khevenh\u00fcllerstr 6 Spittal an der Drau K\u00e4rnten 9800",
    "addr:housenumber":"6",
    "addr:postcode":"9800",
    "addr:street":"Khevenhuellerstr;Kaernten",
    "iso:country":"AT",
    "sg:address":"Khevenh\u00fcllerstr 6",
    "sg:city":"Spittal an der Drau",
    "sg:orig_category":"Lebensmittel / Einzelhandel",
    "sg:phone":"+43 4762 3035",
    "sg:postcode":"9800",
    "sg:province":"K\u00e4rnten",
    "wof:name":"Wandling Herwig",
    "wof:placetype":"venue"
},
  "geometry": {"coordinates":[13.4968900681,46.7977409363],"type":"Point"}
}