{
  "type": "Feature",
  "properties": {
    "addr:full":"Hauptstr 129 Kritzendorf Nieder\u00f6sterreich 3420",
    "addr:housenumber":"129",
    "addr:postcode":"3420",
    "addr:street":"Hauptstr",
    "iso:country":"AT",
    "sg:address":"Hauptstr 129",
    "sg:city":"Kritzendorf",
    "sg:orig_category":"Restaurants: Italienisch",
    "sg:phone":"+43 2243 33384",
    "sg:postcode":"3420",
    "sg:province":"Nieder\u00f6sterreich",
    "wof:name":"Restaurant Pizzeria Mera",
    "wof:placetype":"venue"
},
  "geometry": {"coordinates":[16.297454834,48.3364524841],"type":"Point"}
}