{
  "type": "Feature",
  "properties": {
    "addr:full":"Walther-von-der-Vogelweide-Str 32 St. Veit an der Glan K\u00e4rnten 9300",
    "addr:housenumber":"32",
    "addr:postcode":"9300",
    "addr:street":"Walther-Von-Der-Vogelweide-Str;Kaernten",
    "iso:country":"AT",
    "sg:address":"Walther-von-der-Vogelweide-Str 32",
    "sg:city":"St. Veit an der Glan",
    "sg:orig_category":"Werbegestalter",
    "sg:phone":"+43 4342 1239136",
    "sg:postcode":"9300",
    "sg:province":"K\u00e4rnten",
    "wof:name":"Mully Erwin",
    "wof:placetype":"venue"
},
  "geometry": {"coordinates":[14.3740386963,46.7686462402],"type":"Point"}
}