{
  "type": "Feature",
  "properties": {
    "iso:country":"AT",
    "sg:address":"Walther-von-der-Vogelweide-Str 32",
    "sg:city":"St. Veit an der Glan",
    "sg:orig_category":"Werbegestalter",
    "sg:phone":"+43 4342 1239136",
    "sg:postcode":"9300",
    "sg:province":"K\u00e4rnten",
    "wof:name":"Mully Erwin",
    "wof:placetype":"venue"
},
  "geometry": {"coordinates":[14.3740386963,46.7686462402],"type":"Point"}
}