{
  "type": "Feature",
  "properties": {
    "addr:full":"Ro\u00dfmarkt 2 Wolfsberg K\u00e4rnten 9400",
    "addr:housenumber":"2;kaernten",
    "addr:postcode":"9400",
    "addr:street":"Rossmarkt",
    "iso:country":"AT",
    "sg:address":"Ro\u00dfmarkt 2",
    "sg:city":"Wolfsberg",
    "sg:orig_category":"Freizeit, Erotik",
    "sg:phone":"+43 4352 2698",
    "sg:postcode":"9400",
    "sg:province":"K\u00e4rnten",
    "sg:website":"http://www.doelder.com",
    "wof:name":"Hotel D\u00f6lder",
    "wof:placetype":"venue"
},
  "geometry": {"coordinates":[14.8418502808,46.8402099609],"type":"Point"}
}