{
  "type": "Feature",
  "properties": {
    "addr:full":"Bundesstr 30 Wimpassing im Schwarzatale Nieder\u00f6sterreich 2632",
    "addr:housenumber":"30",
    "addr:postcode":"2632",
    "addr:street":"Bundesstr",
    "iso:country":"AT",
    "sg:address":"Bundesstr 30",
    "sg:city":"Wimpassing im Schwarzatale",
    "sg:orig_category":"Apotheken",
    "sg:phone":"+43 4326 3030936",
    "sg:postcode":"2632",
    "sg:province":"Nieder\u00f6sterreich",
    "wof:name":"Apotheke Wimpassing Mag pharm Friederike Riehs",
    "wof:placetype":"venue"
},
  "geometry": {"coordinates":[16.0294876099,47.7012023926],"type":"Point"}
}