{
  "type": "Feature",
  "properties": {
    "addr:full":"Clemens-Holzmeister-Str 34 Grafenstein K\u00e4rnten 9131",
    "addr:housenumber":"34",
    "addr:postcode":"9131",
    "addr:street":"Clemens-Holzmeister-Str;Kaernten",
    "iso:country":"AT",
    "sg:address":"Clemens-Holzmeister-Str 34",
    "sg:city":"Grafenstein",
    "sg:orig_category":"Volksschulen",
    "sg:phone":"+43 4342 252015",
    "sg:postcode":"9131",
    "sg:province":"K\u00e4rnten",
    "wof:name":"Volksschule",
    "wof:placetype":"venue"
},
  "geometry": {"coordinates":[14.4675064087,46.6160163879],"type":"Point"}
}