{
  "type": "Feature",
  "properties": {
    "addr:full":"Thomas-Bohrer-Str 7 Klagenfurt K\u00e4rnten 9020",
    "addr:housenumber":"7",
    "addr:postcode":"9020",
    "addr:street":"Thomas-Bohrer-Str;Kaernten",
    "iso:country":"AT",
    "sg:address":"Thomas-Bohrer-Str 7",
    "sg:city":"Klagenfurt",
    "sg:classifiers":[
        {
            "category":"Professional",
            "subcategory":"Computer Services",
            "type":"Services"
        }
    ],
    "sg:phone":"+43 463 445736",
    "sg:postcode":"9020",
    "sg:province":"K\u00e4rnten",
    "sg:tags":[
        "software"
    ],
    "wof:name":"IGD Software EntwicklungsgesmbH",
    "wof:placetype":"venue"
},
  "geometry": {"coordinates":[14.3701639175,46.6316947937],"type":"Point"}
}