{
  "type": "Feature",
  "properties": {
    "addr:full":"Gasteiner Str 79 Bischofshofen Salzburg 5500",
    "addr:housenumber":"79",
    "addr:postcode":"5500",
    "addr:street":"Gasteiner Str;Salzburg",
    "iso:country":"AT",
    "sg:address":"Gasteiner Str 79",
    "sg:city":"Bischofshofen",
    "sg:orig_category":"Autohandel",
    "sg:phone":"+43 6462 8133",
    "sg:postcode":"5500",
    "sg:province":"Salzburg",
    "wof:name":"Autohaus Br\u00fcggler",
    "wof:placetype":"venue"
},
  "geometry": {"coordinates":[13.2191038132,47.4057121277],"type":"Point"}
}