{
  "type": "Feature",
  "properties": {
    "addr:full":"Fl\u00f6tzerweg 140a Linz Ober\u00f6sterreich 4030",
    "addr:housenumber":"140a",
    "addr:postcode":"4030",
    "iso:country":"AT",
    "sg:address":"Fl\u00f6tzerweg 140a",
    "sg:city":"Linz",
    "sg:orig_category":"Friseure U Frisiersalons",
    "sg:phone":"+43 732 383888",
    "sg:postcode":"4030",
    "sg:province":"Ober\u00f6sterreich",
    "wof:name":"Mayrhofer-Officia",
    "wof:placetype":"venue"
},
  "geometry": {"coordinates":[14.2866592407,48.2492485046],"type":"Point"}
}