{
  "type": "Feature",
  "properties": {
    "iso:country":"AT",
    "sg:address":"Au 6",
    "sg:city":"St. Wolfgang im Salzkammergut",
    "sg:orig_category":"Pensionen / Privatzimmer",
    "sg:phone":"+43 6138 2912",
    "sg:postcode":"5360",
    "sg:province":"Ober\u00f6sterreich",
    "wof:name":"Altroiterhof Fam Strobl",
    "wof:placetype":"venue"
},
  "geometry": {"coordinates":[13.46393013,47.7326698303],"type":"Point"}
}