{
  "type": "Feature",
  "properties": {
    "iso:country":"AT",
    "sg:address":"Hauptstr 3",
    "sg:city":"Kirchberg in Tirol",
    "sg:orig_category":"Schneidereien",
    "sg:phone":"+43 4353 573696",
    "sg:postcode":"6365",
    "sg:province":"Tirol",
    "wof:name":"Kaletsch Elisabeth",
    "wof:placetype":"venue"
},
  "geometry": {"coordinates":[12.314991951,47.4473190308],"type":"Point"}
}