{
  "type": "Feature",
  "properties": {
    "iso:country":"AT",
    "sg:address":"Hundskehle 21",
    "sg:city":"Klosterneuburg",
    "sg:classifiers":[
        {
            "category":"Social Services",
            "subcategory":"Job Training",
            "type":"Services"
        }
    ],
    "sg:phone":"+43 2243 341400",
    "sg:postcode":"3400",
    "sg:province":"Nieder\u00f6sterreich",
    "sg:tags":[
        "software",
        "database"
    ],
    "sg:website":"gammadental.com",
    "wof:name":"Gamma Medizinisch-wissenschaftliche Fortbildungs-AG",
    "wof:placetype":"venue"
},
  "geometry": {"coordinates":[16.3251228333,48.3082313538],"type":"Point"}
}