{
  "type": "Feature",
  "properties": {
    "addr:full":"Dinghoferstrasse 38 Linz Ober\u00f6sterreich 4020",
    "addr:housenumber":"38",
    "addr:postcode":"4020",
    "addr:street":"Dinghoferstrasse",
    "iso:country":"AT",
    "sg:address":"Dinghoferstrasse 38",
    "sg:city":"Linz",
    "sg:classifiers":[
        {
            "category":"Building & Trades",
            "subcategory":"Cleaning & Sanitation",
            "type":"Services"
        }
    ],
    "sg:phone":"+43 732 6632820",
    "sg:postcode":"4020",
    "sg:province":"Ober\u00f6sterreich",
    "sg:tags":[
        "escalator"
    ],
    "sg:website":"reifrein.at",
    "wof:name":"REIF-REIN Reinigungs- und Umweltschutz Ges.m.b.H. & Co KG",
    "wof:placetype":"venue"
},
  "geometry": {"coordinates":[14.297627449,48.2992858887],"type":"Point"}
}