{
  "type": "Feature",
  "properties": {
    "addr:full":"Amonstr 1 Lunz am See Nieder\u00f6sterreich 3293",
    "addr:housenumber":"1",
    "addr:postcode":"3293",
    "addr:street":"Amonstr;Niederoesterreich",
    "iso:country":"AT",
    "sg:address":"Amonstr 1",
    "sg:city":"Lunz am See",
    "sg:orig_category":"Bekleidung / Einzelhandel",
    "sg:phone":"+43 7486 8217",
    "sg:postcode":"3293",
    "sg:province":"Nieder\u00f6sterreich",
    "wof:name":"Dinstl GmbH & Co KG",
    "wof:placetype":"venue"
},
  "geometry": {"coordinates":[15.026222229,47.8608856201],"type":"Point"}
}