{
  "type": "Feature",
  "properties": {
    "addr:full":"Achleit 227 W\u00f6rgl Tirol 6300",
    "addr:housenumber":"227",
    "addr:postcode":"6300",
    "addr:street":"Achleit;Tirol",
    "iso:country":"AT",
    "sg:address":"Achleit 227",
    "sg:city":"W\u00f6rgl",
    "sg:orig_category":"Erdarbeiten",
    "sg:phone":"+43 4365 04567867",
    "sg:postcode":"6300",
    "sg:province":"Tirol",
    "wof:name":"Lolacher Karl Erdbau",
    "wof:placetype":"venue"
},
  "geometry": {"coordinates":[12.041844368,47.4912414551],"type":"Point"}
}