{
  "type": "Feature",
  "properties": {
    "addr:full":"Pischeldorfer Str 221 Klagenfurt K\u00e4rnten 9020",
    "addr:housenumber":"221",
    "addr:postcode":"9020",
    "addr:street":"Kaernten",
    "iso:country":"AT",
    "sg:address":"Pischeldorfer Str 221",
    "sg:city":"Klagenfurt",
    "sg:orig_category":"Textilwaren / Einzelhandel",
    "sg:phone":"+43 463 419101",
    "sg:postcode":"9020",
    "sg:province":"K\u00e4rnten",
    "wof:name":"Happy Home C F Rakousky",
    "wof:placetype":"venue"
},
  "geometry": {"coordinates":[14.3420591354,46.6374092102],"type":"Point"}
}