{
  "type": "Feature",
  "properties": {
    "iso:country":"AT",
    "sg:address":"Rodarm 10",
    "sg:city":"Obertilliach",
    "sg:orig_category":"Appartements / Ferienwohnungen",
    "sg:phone":"+43 4847 5325",
    "sg:postcode":"9942",
    "sg:province":"Tirol",
    "wof:name":"G\u00e4stehaus Schneider",
    "wof:placetype":"venue"
},
  "geometry": {"coordinates":[12.6029996872,46.7095108032],"type":"Point"}
}