{
  "type": "Feature",
  "properties": {
    "addr:full":"M\u00fchlfeldstr 3a/5/3 Neunkirchen Nieder\u00f6sterreich 2620",
    "addr:housenumber":"3a / 5 / 3",
    "addr:postcode":"2620",
    "addr:street":"Muehlfeldstr",
    "iso:country":"AT",
    "sg:address":"M\u00fchlfeldstr 3a/5/3",
    "sg:city":"Neunkirchen",
    "sg:orig_category":"Filmproduktionen",
    "sg:phone":"+43 4366 07642883",
    "sg:postcode":"2620",
    "sg:province":"Nieder\u00f6sterreich",
    "wof:name":"Living Pictures Video- und Filmproduktion Manfred u Gerti Wei\u00df",
    "wof:placetype":"venue"
},
  "geometry": {"coordinates":[16.0980548859,47.7119560242],"type":"Point"}
}