{
  "type": "Feature",
  "properties": {
    "addr:full":"Jochberg 10 Hollersbach im Pinzgau Salzburg 5731",
    "addr:housenumber":"10",
    "addr:postcode":"5731",
    "addr:street":"Jochberg;Salzburg",
    "iso:country":"AT",
    "sg:address":"Jochberg 10",
    "sg:city":"Hollersbach im Pinzgau",
    "sg:orig_category":"Pensionen / Privatzimmer",
    "sg:phone":"+43 6562 8406",
    "sg:postcode":"5731",
    "sg:province":"Salzburg",
    "wof:name":"Astl Franz",
    "wof:placetype":"venue"
},
  "geometry": {"coordinates":[12.4078435898,47.2886810303],"type":"Point"}
}