{
  "type": "Feature",
  "properties": {
    "addr:full":"Bahnhofstr 28 Dornbirn Vorarlberg 6850",
    "addr:housenumber":"28",
    "addr:postcode":"6850",
    "addr:street":"Bahnhofstr",
    "iso:country":"AT",
    "sg:address":"Bahnhofstr 28",
    "sg:city":"Dornbirn",
    "sg:orig_category":"Blumeneinzelhandel",
    "sg:phone":"+43 5572 23687",
    "sg:postcode":"6850",
    "sg:province":"Vorarlberg",
    "wof:name":"H\u00e4rtl Siegfried",
    "wof:placetype":"venue"
},
  "geometry": {"coordinates":[9.7393932343,47.416759491],"type":"Point"}
}