{
  "type": "Feature",
  "properties": {
    "addr:full":"Kowaldstrasse 9 Voitsberg Steiermark 8570",
    "addr:housenumber":"9",
    "addr:postcode":"8570",
    "addr:street":"Kowaldstrasse",
    "iso:country":"AT",
    "sg:address":"Kowaldstrasse 9",
    "sg:city":"Voitsberg",
    "sg:classifiers":[
        {
            "category":"Government",
            "subcategory":"Department Of Motor Vehicles",
            "type":"Public Place"
        }
    ],
    "sg:phone":"+43 3142 228200",
    "sg:postcode":"8570",
    "sg:province":"Steiermark",
    "sg:tags":[
        "part",
        "bought-in"
    ],
    "sg:website":"bauer-automotive.at",
    "wof:name":"Bauer Automotive GmbH & Co KG",
    "wof:placetype":"venue"
},
  "geometry": {"coordinates":[15.1438846588,47.0449333191],"type":"Point"}
}