{
  "type": "Feature",
  "properties": {
    "addr:full":"Buchberg 39 Ebbs Tirol 6341",
    "addr:housenumber":"39",
    "addr:postcode":"6341",
    "addr:street":"Buchberg;Tirol",
    "iso:country":"AT",
    "sg:address":"Buchberg 39",
    "sg:city":"Ebbs",
    "sg:classifiers":[
        {
            "category":"Manufacturing",
            "subcategory":"Furniture",
            "type":"Manufacturing & Wholesale Goods"
        }
    ],
    "sg:phone":"+43 5373 43138",
    "sg:postcode":"6341",
    "sg:province":"Tirol",
    "sg:tags":[
        "bedroom"
    ],
    "sg:website":"buchauer.at",
    "wof:name":"Klaus Buchauer",
    "wof:placetype":"venue"
},
  "geometry": {"coordinates":[12.2144241333,47.6297264099],"type":"Point"}
}