{
  "type": "Feature",
  "properties": {
    "addr:full":"Nr 2 St. Michael K\u00e4rnten 9411",
    "addr:housenumber":"2",
    "addr:postcode":"9411",
    "addr:street":"Nr",
    "iso:country":"AT",
    "sg:address":"Nr 2",
    "sg:city":"St. Michael",
    "sg:orig_category":"Gutsverwaltungen",
    "sg:phone":"+43 4352 61063",
    "sg:postcode":"9411",
    "sg:province":"K\u00e4rnten",
    "wof:name":"Gut Himmelau",
    "wof:placetype":"venue"
},
  "geometry": {"coordinates":[14.8000583649,46.8348121643],"type":"Point"}
}