{
  "type": "Feature",
  "properties": {
    "iso:country":"AT",
    "sg:address":"Obermarkersdorf 174",
    "sg:city":"Schrattenthal",
    "sg:classifiers":[
        {
            "category":"Food & Beverages",
            "subcategory":"Groceries & Convenience Stores",
            "type":"Retail Goods"
        }
    ],
    "sg:phone":"+43 4329 4282520",
    "sg:postcode":"2073",
    "sg:province":"Nieder\u00f6sterreich",
    "sg:tags":[
        "drink"
    ],
    "wof:name":"HERBERT STUDENY",
    "wof:placetype":"venue"
},
  "geometry": {"coordinates":[15.8933439255,48.7559585571],"type":"Point"}
}