{
  "type": "Feature",
  "properties": {
    "addr:full":"Huttererstr 11 Ernstbrunn Nieder\u00f6sterreich 2115",
    "addr:housenumber":"11",
    "addr:postcode":"2115",
    "addr:street":"Huttererstr",
    "iso:country":"AT",
    "sg:address":"Huttererstr 11",
    "sg:city":"Ernstbrunn",
    "sg:orig_category":"Tischlereien",
    "sg:phone":"+43 2576 2231",
    "sg:postcode":"2115",
    "sg:province":"Nieder\u00f6sterreich",
    "wof:name":"Jaidhauser Wilhelm jun",
    "wof:placetype":"venue"
},
  "geometry": {"coordinates":[16.3590297699,48.5248451233],"type":"Point"}
}