{
  "type": "Feature",
  "properties": {
    "addr:full":"Hafnersteig 7 Wien Wien 1010",
    "addr:housenumber":"7",
    "addr:postcode":"1010",
    "addr:street":"Hafnersteig",
    "iso:country":"AT",
    "sg:address":"Hafnersteig 7",
    "sg:city":"Wien",
    "sg:orig_category":"Pensionen / Privatzimmer",
    "sg:phone":"+43 1 53329610",
    "sg:postcode":"1010",
    "sg:province":"Wien",
    "wof:name":"Christina",
    "wof:placetype":"venue"
},
  "geometry": {"coordinates":[16.3775444031,48.2112350464],"type":"Point"}
}