{
  "type": "Feature",
  "properties": {
    "addr:full":"Vinzenz-Brunner-Str 5 Silz Tirol 6424",
    "addr:housenumber":"5",
    "addr:postcode":"6424",
    "addr:street":"Vinzenz-Brunner-Str;Tirol",
    "iso:country":"AT",
    "sg:address":"Vinzenz-Brunner-Str 5",
    "sg:city":"Silz",
    "sg:orig_category":"Handelsagenturen",
    "sg:phone":"+43 5263 6250",
    "sg:postcode":"6424",
    "sg:province":"Tirol",
    "wof:name":"Schl\u00f6gl Peter",
    "wof:placetype":"venue"
},
  "geometry": {"coordinates":[10.935874939,47.2673072815],"type":"Point"}
}