{
  "type": "Feature",
  "properties": {
    "addr:full":"Reinlg 20 Wien Wien 1140",
    "addr:housenumber":"20",
    "addr:postcode":"1140",
    "addr:street":"Reinlg",
    "iso:country":"AT",
    "sg:address":"Reinlg 20",
    "sg:city":"Wien",
    "sg:orig_category":"Restaurants: Italienisch",
    "sg:phone":"+43 1 9855103",
    "sg:postcode":"1140",
    "sg:province":"Wien",
    "wof:name":"Ristorante San Marco",
    "wof:placetype":"venue"
},
  "geometry": {"coordinates":[16.2696990967,48.1994247437],"type":"Point"}
}