{
  "type": "Feature",
  "properties": {
    "addr:full":"Matschacher Str 283 Feistritz im Rosental K\u00e4rnten 9181",
    "addr:housenumber":"283",
    "addr:postcode":"9181",
    "addr:street":"Str",
    "iso:country":"AT",
    "sg:address":"Matschacher Str 283",
    "sg:city":"Feistritz im Rosental",
    "sg:orig_category":"Transportunternehmen",
    "sg:phone":"+43 4342 282688",
    "sg:postcode":"9181",
    "sg:province":"K\u00e4rnten",
    "wof:name":"Obiltschnig Hubert",
    "wof:placetype":"venue"
},
  "geometry": {"coordinates":[14.1664943695,46.521194458],"type":"Point"}
}