{
  "type": "Feature",
  "properties": {
    "iso:country":"AT",
    "sg:address":"Leum\u00fchle 1",
    "sg:city":"Eferding",
    "sg:orig_category":"Lebens- U Sozialberatung",
    "sg:phone":"+43 7272 59089",
    "sg:postcode":"4070",
    "sg:province":"Ober\u00f6sterreich",
    "wof:name":"SHV-Eferding-Sozialberatungsstelle",
    "wof:placetype":"venue"
},
  "geometry": {"coordinates":[14.0234451294,48.3086395264],"type":"Point"}
}