{
  "type": "Feature",
  "properties": {
    "iso:country":"AT",
    "sg:address":"Untere \u00d6dlitzer Strasse 6",
    "sg:city":"Berndorf",
    "sg:classifiers":[
        {
            "category":"Utilities",
            "subcategory":"Mobile Phone",
            "type":"Services"
        }
    ],
    "sg:phone":"+43 2672 83188",
    "sg:postcode":"2560",
    "sg:province":"Nieder\u00f6sterreich",
    "sg:tags":[
        "fan",
        "centrifugal"
    ],
    "sg:website":"ing-waldner.at",
    "wof:name":"Anlagen-u. Verfahrenstechnik Ing. Walter Waldner",
    "wof:placetype":"venue"
},
  "geometry": {"coordinates":[16.1541938782,47.9397506714],"type":"Point"}
}