{
  "type": "Feature",
  "properties": {
    "addr:full":"Schulstr 10 Wartberg an der Krems Ober\u00f6sterreich 4552",
    "addr:housenumber":"10",
    "addr:postcode":"4552",
    "addr:street":"Schulstr",
    "iso:country":"AT",
    "sg:address":"Schulstr 10",
    "sg:city":"Wartberg an der Krems",
    "sg:orig_category":"Volksschulen",
    "sg:phone":"+43 4375 87765630",
    "sg:postcode":"4552",
    "sg:province":"Ober\u00f6sterreich",
    "wof:name":"Volksschule",
    "wof:placetype":"venue"
},
  "geometry": {"coordinates":[14.1154050827,47.9895095825],"type":"Point"}
}