{
  "type": "Feature",
  "properties": {
    "addr:full":"Lindau 78 Bad Ischl Ober\u00f6sterreich 4820",
    "addr:housenumber":"78",
    "addr:postcode":"4820",
    "addr:street":"Lindau",
    "iso:country":"AT",
    "sg:address":"Lindau 78",
    "sg:city":"Bad Ischl",
    "sg:classifiers":[
        {
            "category":"Health Services",
            "subcategory":"Nursing And Care Facility",
            "type":"Services"
        }
    ],
    "sg:phone":"+43 4361 32242530",
    "sg:postcode":"4820",
    "sg:province":"Ober\u00f6sterreich",
    "sg:tags":[
        "rehabilitation"
    ],
    "wof:name":"Pensionsversicherungsanstalt - Sonderkrankenanstalt RZ Bad Ischl",
    "wof:placetype":"venue"
},
  "geometry": {"coordinates":[13.5874586105,47.7117652893],"type":"Point"}
}