{
  "type": "Feature",
  "properties": {
    "addr:full":"Rudolfstr 9 Linz Ober\u00f6sterreich 4040",
    "addr:housenumber":"9",
    "addr:postcode":"4040",
    "addr:street":"Rudolfstr",
    "iso:country":"AT",
    "sg:address":"Rudolfstr 9",
    "sg:city":"Linz",
    "sg:orig_category":"Tapezierer U Dekorateure",
    "sg:phone":"+43 732 719236",
    "sg:postcode":"4040",
    "sg:province":"Ober\u00f6sterreich",
    "wof:name":"Langfellner Rudolf",
    "wof:placetype":"venue"
},
  "geometry": {"coordinates":[14.2817192078,48.3107795715],"type":"Point"}
}