{
  "type": "Feature",
  "properties": {
    "addr:full":"Antonig 57 Wien Wien 1170",
    "addr:housenumber":"57",
    "addr:postcode":"1170",
    "addr:street":"Antonig",
    "iso:country":"AT",
    "sg:address":"Antonig 57",
    "sg:city":"Wien",
    "sg:orig_category":"Autoreparatur",
    "sg:phone":"+43 4314 061270",
    "sg:postcode":"1170",
    "sg:province":"Wien",
    "wof:name":"Autoservice u Karosseriereparaturdienst K.S.V. GesmbH",
    "wof:placetype":"venue"
},
  "geometry": {"coordinates":[16.3350028992,48.2235031128],"type":"Point"}
}