{
  "type": "Feature",
  "properties": {
    "addr:full":"Donaufelder Str 32 Wien Wien 1210",
    "addr:postcode":"1210",
    "addr:street":"Str 32",
    "iso:country":"AT",
    "sg:address":"Donaufelder Str 32",
    "sg:city":"Wien",
    "sg:orig_category":"Tapezierer U Dekorateure",
    "sg:phone":"+43 4312 781696",
    "sg:postcode":"1210",
    "sg:province":"Wien",
    "wof:name":"Ullmann Peter",
    "wof:placetype":"venue"
},
  "geometry": {"coordinates":[16.4121723175,48.2535934448],"type":"Point"}
}