{
  "type": "Feature",
  "properties": {
    "addr:full":"Rudi-Gier-Str. 5-7  Linz Ober\u00f6sterreich 4020",
    "addr:housenumber":"5-7",
    "addr:postcode":"4020",
    "addr:street":"Rudi-Gier-Str.",
    "iso:country":"AT",
    "sg:address":"Rudi-Gier-Str. 5-7 ",
    "sg:city":"Linz",
    "sg:classifiers":[
        {
            "category":"Banks & Credit Unions",
            "subcategory":"Bank",
            "type":"Services"
        }
    ],
    "sg:phone":"+43 4373 27637",
    "sg:postcode":"4020",
    "sg:province":"Ober\u00f6sterreich",
    "sg:tags":[
        "banking",
        "institution"
    ],
    "wof:name":"BANK VOLKSKREDIT BANK AG (VKB)",
    "wof:placetype":"venue"
},
  "geometry": {"coordinates":[14.2900009155,48.3006668091],"type":"Point"}
}