{
  "type": "Feature",
  "properties": {
    "iso:country":"AT",
    "sg:address":"Nr 7",
    "sg:city":"Oberneukirchen",
    "sg:orig_category":"Baumpflege, -Schutz U -Chirurgie",
    "sg:phone":"+43 4372 127459",
    "sg:postcode":"4181",
    "sg:province":"Ober\u00f6sterreich",
    "wof:name":"Hainberger Ulrich",
    "wof:placetype":"venue"
},
  "geometry": {"coordinates":[14.2268648148,48.4645423889],"type":"Point"}
}