{
  "type": "Feature",
  "properties": {
    "addr:full":"Schulhof 1 Wien Wien 1010",
    "addr:housenumber":"1",
    "addr:postcode":"1010",
    "addr:street":"Schulhof",
    "iso:country":"AT",
    "sg:address":"Schulhof 1",
    "sg:city":"Wien",
    "sg:orig_category":"Non-Classified Establishments",
    "sg:phone":"+43 1 5338394",
    "sg:postcode":"1010",
    "sg:province":"Wien",
    "wof:name":"Gastarbeiterseelsorge f Kroaten - Kroatische Katholische Mission",
    "wof:placetype":"venue"
},
  "geometry": {"coordinates":[16.3686141968,48.2109832764],"type":"Point"}
}