{
  "type": "Feature",
  "properties": {
    "addr:full":"Hatschekstr 1 Linz Ober\u00f6sterreich 4020",
    "addr:housenumber":"1",
    "addr:postcode":"4020",
    "addr:street":"Hatschekstr",
    "iso:country":"AT",
    "sg:address":"Hatschekstr 1",
    "sg:city":"Linz",
    "sg:orig_category":"Werbeagenturen",
    "sg:phone":"+43 732 344418",
    "sg:postcode":"4020",
    "sg:province":"Ober\u00f6sterreich",
    "sg:website":"www.schild-werbeteam.at",
    "wof:name":"Schild Werbeteam",
    "wof:placetype":"venue"
},
  "geometry": {"coordinates":[14.2944669724,48.2749595642],"type":"Point"}
}