{
  "type": "Feature",
  "properties": {
    "addr:full":"Stuben 502 Pfunds Tirol 6542",
    "addr:housenumber":"502",
    "addr:postcode":"6542",
    "addr:street":"Stuben;Tirol",
    "iso:country":"AT",
    "sg:address":"Stuben 502",
    "sg:city":"Pfunds",
    "sg:orig_category":"Banken U Sparkassen",
    "sg:phone":"+43 4354 7454880",
    "sg:postcode":"6542",
    "sg:province":"Tirol",
    "wof:name":"Volksbank Landeck regGenmbH",
    "wof:placetype":"venue"
},
  "geometry": {"coordinates":[10.535697937,46.968536377],"type":"Point"}
}