{
  "type": "Feature",
  "properties": {
    "addr:full":"St\u00f6berpl 1 Wien Wien 1160",
    "addr:housenumber":"1",
    "addr:postcode":"1160",
    "addr:street":"Stoeberpl",
    "iso:country":"AT",
    "sg:address":"St\u00f6berpl 1",
    "sg:city":"Wien",
    "sg:orig_category":"Maler, Anstreicher U Lackierer",
    "sg:phone":"+43 1 4861529",
    "sg:postcode":"1160",
    "sg:province":"Wien",
    "wof:name":"Frittum Werner",
    "wof:placetype":"venue"
},
  "geometry": {"coordinates":[16.3176193237,48.2214355469],"type":"Point"}
}