{
  "type": "Feature",
  "properties": {
    "addr:full":"Nr 145 Gerersdorf Burgenland 7542",
    "addr:postcode":"7542",
    "addr:street":"Nr 145",
    "iso:country":"AT",
    "sg:address":"Nr 145",
    "sg:city":"Gerersdorf",
    "sg:orig_category":"Filmproduktionen",
    "sg:phone":"+43 4333 2832300",
    "sg:postcode":"7542",
    "sg:province":"Burgenland",
    "wof:name":"Forum Film",
    "wof:placetype":"venue"
},
  "geometry": {"coordinates":[16.252620697,47.0685806274],"type":"Point"}
}