{
  "type": "Feature",
  "properties": {
    "iso:country":"AT",
    "sg:address":"Ybbsstr 13",
    "sg:city":"Blindenmarkt",
    "sg:orig_category":"Weine / Einzelhandel",
    "sg:phone":"+43 7473 2878",
    "sg:postcode":"3372",
    "sg:province":"Nieder\u00f6sterreich",
    "wof:name":"Steinacher Franz",
    "wof:placetype":"venue"
},
  "geometry": {"coordinates":[14.9494981766,48.1082038879],"type":"Point"}
}