{
  "type": "Feature",
  "properties": {
    "addr:full":"Linzer Gasse 38 Salzburg Salzburg 5020",
    "addr:housenumber":"38",
    "addr:postcode":"5020",
    "addr:street":"Linzer Gasse;Salzburg",
    "iso:country":"AT",
    "sg:address":"Linzer Gasse 38",
    "sg:city":"Salzburg",
    "sg:classifiers":[
        {
            "category":"Manufacturing",
            "subcategory":"Glass & Minerals",
            "type":"Manufacturing & Wholesale Goods"
        }
    ],
    "sg:phone":"+43 662 873621",
    "sg:postcode":"5020",
    "sg:province":"Salzburg",
    "sg:tags":[
        "crystal"
    ],
    "wof:name":"Paula Hubner Kristall",
    "wof:placetype":"venue"
},
  "geometry": {"coordinates":[13.0469751358,47.8031845093],"type":"Point"}
}