{
  "type": "Feature",
  "properties": {
    "addr:full":"M\u00fchlg 77 Hausleiten Nieder\u00f6sterreich 3464",
    "addr:housenumber":"77",
    "addr:postcode":"3464",
    "addr:street":"Muehlg",
    "iso:country":"AT",
    "sg:address":"M\u00fchlg 77",
    "sg:city":"Hausleiten",
    "sg:orig_category":"Landwirtschaftliche Produkte",
    "sg:phone":"+43 2265 7250",
    "sg:postcode":"3464",
    "sg:province":"Nieder\u00f6sterreich",
    "wof:name":"Bamberger Alois M\u00fchle GesmbH",
    "wof:placetype":"venue"
},
  "geometry": {"coordinates":[16.1025238037,48.393989563],"type":"Point"}
}