{
  "type": "Feature",
  "properties": {
    "addr:full":"Wiener Str 22 Wolkersdorf im Weinviertel Nieder\u00f6sterreich 2120",
    "addr:housenumber":"22",
    "addr:postcode":"2120",
    "iso:country":"AT",
    "sg:address":"Wiener Str 22",
    "sg:city":"Wolkersdorf im Weinviertel",
    "sg:orig_category":"\u00c3\u201enderungsschneidereien",
    "sg:phone":"+43 4366 41108545",
    "sg:postcode":"2120",
    "sg:province":"Nieder\u00f6sterreich",
    "wof:name":"\u00e4nderungsschneiderei Adem Mutlu",
    "wof:placetype":"venue"
},
  "geometry": {"coordinates":[16.513174057,48.3826942444],"type":"Point"}
}