{
  "type": "Feature",
  "properties": {
    "addr:full":"Schieferrollstr 21 Kundl Tirol 6250",
    "addr:housenumber":"21",
    "addr:postcode":"6250",
    "addr:street":"Schieferrollstr;Tirol",
    "iso:country":"AT",
    "sg:address":"Schieferrollstr 21",
    "sg:city":"Kundl",
    "sg:orig_category":"Tankstellen",
    "sg:phone":"+43 5338 861126",
    "sg:postcode":"6250",
    "sg:province":"Tirol",
    "wof:name":"JET Tankstelle",
    "wof:placetype":"venue"
},
  "geometry": {"coordinates":[11.9896039963,47.4672088623],"type":"Point"}
}