{
  "type": "Feature",
  "properties": {
    "addr:full":"Passauer Str 11 Tulbing Nieder\u00f6sterreich 3434",
    "addr:postcode":"3434",
    "addr:street":"Str 11",
    "iso:country":"AT",
    "sg:address":"Passauer Str 11",
    "sg:city":"Tulbing",
    "sg:orig_category":"Filmproduktionen",
    "sg:phone":"+43 664 3224587",
    "sg:postcode":"3434",
    "sg:province":"Nieder\u00f6sterreich",
    "wof:name":"REKA Film & Video Produktion",
    "wof:placetype":"venue"
},
  "geometry": {"coordinates":[16.1226959229,48.290435791],"type":"Point"}
}