{
  "type": "Feature",
  "properties": {
    "addr:full":"Sonnenberger Str 8 Frastanz Vorarlberg 6820",
    "addr:housenumber":"8",
    "addr:postcode":"6820",
    "addr:street":"Str",
    "iso:country":"AT",
    "sg:address":"Sonnenberger Str 8",
    "sg:city":"Frastanz",
    "sg:orig_category":"Hunde- U Katzensalons",
    "sg:phone":"+43 5522 53655",
    "sg:postcode":"6820",
    "sg:province":"Vorarlberg",
    "wof:name":"Hundesalon Dornig",
    "wof:placetype":"venue"
},
  "geometry": {"coordinates":[9.6308546066,47.2231445312],"type":"Point"}
}