{
  "type": "Feature",
  "properties": {
    "addr:full":"Prof Anton Lutz-Weg 3 Prambachkirchen Ober\u00f6sterreich 4731",
    "addr:housenumber":"3",
    "addr:postcode":"4731",
    "addr:street":"Prof Anton Lutz-Weg",
    "iso:country":"AT",
    "sg:address":"Prof Anton Lutz-Weg 3",
    "sg:city":"Prambachkirchen",
    "sg:orig_category":"Non-Classified Establishments",
    "sg:phone":"+43 7277 23080",
    "sg:postcode":"4731",
    "sg:province":"Ober\u00f6sterreich",
    "wof:name":"Pfarramt",
    "wof:placetype":"venue"
},
  "geometry": {"coordinates":[13.9048852921,48.3149261475],"type":"Point"}
}