{
  "type": "Feature",
  "properties": {
    "addr:full":"Karl-Berg-G 4 Radstadt Salzburg 5550",
    "addr:housenumber":"4",
    "addr:postcode":"5550",
    "addr:street":"Karl-Berg-G;Salzburg",
    "iso:country":"AT",
    "sg:address":"Karl-Berg-G 4",
    "sg:city":"Radstadt",
    "sg:orig_category":"Juwelen, Gold- U Silberwaren / Einzelhandel",
    "sg:phone":"+43 4364 526042",
    "sg:postcode":"5550",
    "sg:province":"Salzburg",
    "wof:name":"Uhrenschmuck - Schober",
    "wof:placetype":"venue"
},
  "geometry": {"coordinates":[13.4633998871,47.3851318359],"type":"Point"}
}