{
  "type": "Feature",
  "properties": {
    "iso:country":"AT",
    "sg:address":"Theaterg 2",
    "sg:city":"Salzburg",
    "sg:orig_category":"Feinkost",
    "sg:phone":"+43 662 872423",
    "sg:postcode":"5020",
    "sg:province":"Salzburg",
    "wof:name":"Wein & Tee K\u00f6lbl Heinrich",
    "wof:placetype":"venue"
},
  "geometry": {"coordinates":[13.0438737869,47.8024291992],"type":"Point"}
}