{
  "type": "Feature",
  "properties": {
    "addr:full":"Hauptpl 4 Ober-Grafendorf Nieder\u00f6sterreich 3200",
    "addr:housenumber":"4",
    "addr:postcode":"3200",
    "addr:street":"Hauptpl",
    "iso:country":"AT",
    "sg:address":"Hauptpl 4",
    "sg:city":"Ober-Grafendorf",
    "sg:orig_category":"Non-Classified Establishments",
    "sg:phone":"+43 5 91333160",
    "sg:postcode":"3200",
    "sg:province":"Nieder\u00f6sterreich",
    "wof:name":"Gendarmerie",
    "wof:placetype":"venue"
},
  "geometry": {"coordinates":[15.5445404053,48.150177002],"type":"Point"}
}