{
  "type": "Feature",
  "properties": {
    "addr:full":"Serviteng 7/1 Wien Wien 1090",
    "addr:housenumber":"7 / 1",
    "addr:postcode":"1090",
    "addr:street":"Serviteng",
    "iso:country":"AT",
    "sg:address":"Serviteng 7/1",
    "sg:city":"Wien",
    "sg:orig_category":"Tabaktrafiken",
    "sg:phone":"+43 1 3178290",
    "sg:postcode":"1090",
    "sg:province":"Wien",
    "wof:name":"Fries Silvia",
    "wof:placetype":"venue"
},
  "geometry": {"coordinates":[16.3640956879,48.2201461792],"type":"Point"}
}