{
  "type": "Feature",
  "properties": {
    "iso:country":"AT",
    "sg:address":"Innerleiten 12",
    "sg:city":"Ampflwang im Hausruckwald",
    "sg:orig_category":"Pensionen / Privatzimmer",
    "sg:phone":"+43 4376 752392",
    "sg:postcode":"4843",
    "sg:province":"Ober\u00f6sterreich",
    "wof:name":"Scho\u00dfleitner Sabine",
    "wof:placetype":"venue"
},
  "geometry": {"coordinates":[13.5528812408,48.0728607178],"type":"Point"}
}