{
  "type": "Feature",
  "properties": {
    "addr:full":"Goethestr 7 Linz Ober\u00f6sterreich 4020",
    "addr:housenumber":"7",
    "addr:postcode":"4020",
    "addr:street":"Goethestr",
    "iso:country":"AT",
    "sg:address":"Goethestr 7",
    "sg:city":"Linz",
    "sg:classifiers":[
        {
            "category":"Restaurant",
            "type":"Food & Drink"
        }
    ],
    "sg:phone":"+43 732 663437",
    "sg:postcode":"4020",
    "sg:province":"Ober\u00f6sterreich",
    "sg:tags":[
        "pizzeria"
    ],
    "wof:name":"Pizzeria Capri",
    "wof:placetype":"venue"
},
  "geometry": {"coordinates":[14.2931871414,48.2966461182],"type":"Point"}
}