{
  "type": "Feature",
  "properties": {
    "addr:full":"Irrsbergstrasse 11 Neumarkt am Wallersee Salzburg 5202",
    "addr:housenumber":"11",
    "addr:postcode":"5202",
    "addr:street":"Irrsbergstrasse;Salzburg",
    "iso:country":"AT",
    "sg:address":"Irrsbergstrasse 11",
    "sg:city":"Neumarkt am Wallersee",
    "sg:classifiers":[
        {
            "category":"Wholesale",
            "subcategory":"Construction Materials",
            "type":"Manufacturing & Wholesale Goods"
        }
    ],
    "sg:phone":"+43 6216 4567",
    "sg:postcode":"5202",
    "sg:province":"Salzburg",
    "sg:tags":[
        "dry",
        "system"
    ],
    "sg:website":"trockenbau-schartner.at",
    "wof:name":"Trockenbau Schartner GmbH",
    "wof:placetype":"venue"
},
  "geometry": {"coordinates":[13.248134613,47.9540634155],"type":"Point"}
}