{
  "type": "Feature",
  "properties": {
    "addr:full":"Durisolstr 12 Wels Ober\u00f6sterreich 4600",
    "addr:housenumber":"12",
    "addr:postcode":"4600",
    "addr:street":"Durisolstr;Oberoesterreich",
    "iso:country":"AT",
    "sg:address":"Durisolstr 12",
    "sg:city":"Wels",
    "sg:orig_category":"Anlagenbau U -Technik",
    "sg:phone":"+43 4372 42293830",
    "sg:postcode":"4600",
    "sg:province":"Ober\u00f6sterreich",
    "wof:name":"R\u00fcbig GesmbH & Co KG - Anlagentechnik",
    "wof:placetype":"venue"
},
  "geometry": {"coordinates":[14.0058965683,48.1490135193],"type":"Point"}
}