{
  "type": "Feature",
  "properties": {
    "iso:country":"AT",
    "sg:address":"Nr 1",
    "sg:city":"Thening",
    "sg:orig_category":"Paketdienste",
    "sg:phone":"+43 664 2834372",
    "sg:postcode":"4062",
    "sg:province":"Ober\u00f6sterreich",
    "wof:name":"Murauer Rudolf",
    "wof:placetype":"venue"
},
  "geometry": {"coordinates":[14.1588783264,48.2645797729],"type":"Point"}
}