{
  "type": "Feature",
  "properties": {
    "addr:full":"Nr 30 D\u00f6lsach Tirol 9991",
    "addr:postcode":"9991",
    "addr:street":"Nr 30 Doelsach Tirol",
    "iso:country":"AT",
    "sg:address":"Nr 30",
    "sg:city":"D\u00f6lsach",
    "sg:orig_category":"Gemeinden",
    "sg:phone":"+43 4852 65300",
    "sg:postcode":"9991",
    "sg:province":"Tirol",
    "wof:name":"Gemeindeamt Iselsberg-Stronach",
    "wof:placetype":"venue"
},
  "geometry": {"coordinates":[12.8408555984,46.8266830444],"type":"Point"}
}