{
  "type": "Feature",
  "properties": {
    "addr:full":"St. P\u00f6ltner Strasse 84 Kirchberg an der Pielach Nieder\u00f6sterreich 3204",
    "addr:housenumber":"84",
    "addr:postcode":"3204",
    "addr:street":"Poeltner Strasse",
    "iso:country":"AT",
    "sg:address":"St. P\u00f6ltner Strasse 84",
    "sg:city":"Kirchberg an der Pielach",
    "sg:classifiers":[
        {
            "category":"Manufacturing",
            "subcategory":"Metals",
            "type":"Manufacturing & Wholesale Goods"
        }
    ],
    "sg:phone":"+43 2722 20120",
    "sg:postcode":"3204",
    "sg:province":"Nieder\u00f6sterreich",
    "sg:tags":[
        "brass"
    ],
    "sg:website":"rottegg.at",
    "wof:name":"ROTHENEDER, THANNER & EGGER ROTTEGG OEG",
    "wof:placetype":"venue"
},
  "geometry": {"coordinates":[15.4310951233,48.025844574],"type":"Point"}
}