{
  "type": "Feature",
  "properties": {
    "addr:full":"Vogelweiderstr 65a Salzburg Salzburg 5020",
    "addr:housenumber":"65a",
    "addr:postcode":"5020",
    "addr:street":"Vogelweiderstr;Salzburg",
    "iso:country":"AT",
    "sg:address":"Vogelweiderstr 65a",
    "sg:city":"Salzburg",
    "sg:orig_category":"Glaswaren",
    "sg:phone":"+43 662 8713200",
    "sg:postcode":"5020",
    "sg:province":"Salzburg",
    "wof:name":"Pharma Glas Koniakowsky & Kuehr GesmbH",
    "wof:placetype":"venue"
},
  "geometry": {"coordinates":[13.0534906387,47.815158844],"type":"Point"}
}