{
  "type": "Feature",
  "properties": {
    "addr:full":"Leinsdorfer Str 8 Krumpendorf K\u00e4rnten 9201",
    "addr:housenumber":"8",
    "addr:postcode":"9201",
    "addr:street":"Str;Kaernten",
    "iso:country":"AT",
    "sg:address":"Leinsdorfer Str 8",
    "sg:city":"Krumpendorf",
    "sg:orig_category":"Pensionen / Privatzimmer",
    "sg:phone":"+43 4342 292296",
    "sg:postcode":"9201",
    "sg:province":"K\u00e4rnten",
    "wof:name":"Pension Zechnerhof",
    "wof:placetype":"venue"
},
  "geometry": {"coordinates":[14.2034807205,46.6255950928],"type":"Point"}
}