{
  "type": "Feature",
  "properties": {
    "iso:country":"AT",
    "sg:address":"Hofau 7",
    "sg:city":"Lambach",
    "sg:orig_category":"Blanking, Punching, Stamping, Embossing And Drawing Dies, Progressive Dies",
    "sg:phone":"+43 7245 24977",
    "sg:postcode":"4650",
    "sg:province":"Ober\u00f6sterreich",
    "sg:website":"bachl.co.at",
    "wof:name":"Erich Bachl Werkzeug- und Formenbau",
    "wof:placetype":"venue"
},
  "geometry": {"coordinates":[13.8900299072,48.0920562744],"type":"Point"}
}