{
  "type": "Feature",
  "properties": {
    "iso:country":"AT",
    "sg:address":"Waldmannsg 1a/6",
    "sg:city":"Kottingbrunn",
    "sg:orig_category":"Fotografen",
    "sg:phone":"+43 2252 76703",
    "sg:postcode":"2542",
    "sg:province":"Nieder\u00f6sterreich",
    "wof:name":"Wellenhofer Erich",
    "wof:placetype":"venue"
},
  "geometry": {"coordinates":[16.222530365,47.9438056946],"type":"Point"}
}