{
  "type": "Feature",
  "properties": {
    "addr:full":"S\u00f6llheimer Berg 8 Hallwang Salzburg 5300",
    "addr:housenumber":"8",
    "addr:postcode":"5300",
    "addr:street":"Berg;Salzburg",
    "iso:country":"AT",
    "sg:address":"S\u00f6llheimer Berg 8",
    "sg:city":"Hallwang",
    "sg:orig_category":"Immobilienmakler",
    "sg:phone":"+43 662 665363",
    "sg:postcode":"5300",
    "sg:province":"Salzburg",
    "wof:name":"Garant Immobilien - Alois Gr\u00fcnfelder",
    "wof:placetype":"venue"
},
  "geometry": {"coordinates":[13.0793800354,47.8400688171],"type":"Point"}
}