{
  "type": "Feature",
  "properties": {
    "iso:country":"AT",
    "sg:city":"H\u00fcttschlag",
    "sg:orig_category":"Feuerwehren",
    "sg:phone":"+43 6417 213",
    "sg:postcode":"5612",
    "sg:province":"Salzburg",
    "wof:name":"Feuerwehr H\u00fcttschlag",
    "wof:placetype":"venue"
},
  "geometry": {"coordinates":[105.8784332275,25.7993106842],"type":"Point"}
}