{
  "type": "Feature",
  "properties": {
    "iso:country":"AT",
    "sg:address":"Nisselg 5/3",
    "sg:city":"Wien",
    "sg:classifiers":[
        {
            "category":"Professional",
            "type":"Services"
        }
    ],
    "sg:phone":"+43 1 89721540",
    "sg:postcode":"1140",
    "sg:province":"Wien",
    "sg:tags":[
        "relocation"
    ],
    "sg:website":"stepvienna.at",
    "wof:name":"Step Vienna Int. Relocation Service",
    "wof:placetype":"venue"
},
  "geometry": {"coordinates":[16.3040046692,48.188747406],"type":"Point"}
}