{
  "type": "Feature",
  "properties": {
    "addr:full":"Kierlinger Str 3A Klosterneuburg Nieder\u00f6sterreich 3400",
    "addr:postcode":"3400",
    "addr:street":"Str 3A",
    "iso:country":"AT",
    "sg:address":"Kierlinger Str 3A",
    "sg:city":"Klosterneuburg",
    "sg:orig_category":"Immobilienmakler",
    "sg:phone":"+43 2243 38877",
    "sg:postcode":"3400",
    "sg:province":"Nieder\u00f6sterreich",
    "wof:name":"Winkler & Platteter Immobilienvermittlungs GmbH",
    "wof:placetype":"venue"
},
  "geometry": {"coordinates":[16.3218421936,48.3077125549],"type":"Point"}
}