{
  "type": "Feature",
  "properties": {
    "iso:country":"AT",
    "sg:address":"Bahnhofstr 23",
    "sg:city":"Tulln an der Donau",
    "sg:orig_category":"Notare",
    "sg:phone":"+43 2272 62352",
    "sg:postcode":"3430",
    "sg:province":"Nieder\u00f6sterreich",
    "wof:name":"Notarpartnerschaft HOFMANN & KASPAR",
    "wof:placetype":"venue"
},
  "geometry": {"coordinates":[16.0554447174,48.3285064697],"type":"Point"}
}