{
  "type": "Feature",
  "properties": {
    "addr:full":"Wiener Str 169 Linz Ober\u00f6sterreich 4020",
    "addr:housenumber":"169",
    "addr:postcode":"4020",
    "iso:country":"AT",
    "sg:address":"Wiener Str 169",
    "sg:city":"Linz",
    "sg:orig_category":"Sprechanlagen",
    "sg:phone":"+43 732 606699",
    "sg:postcode":"4020",
    "sg:province":"Ober\u00f6sterreich",
    "wof:name":"Dialog Elektroger\u00e4te VertriebsgesmbH",
    "wof:placetype":"venue"
},
  "geometry": {"coordinates":[14.3102931976,48.2791671753],"type":"Point"}
}