{
  "type": "Feature",
  "properties": {
    "iso:country":"AT",
    "sg:address":"Mauthausener Str 6",
    "sg:city":"St. Georgen an der Gusen",
    "sg:orig_category":"Lebensmittel / Einzelhandel",
    "sg:phone":"+43 4372 376407",
    "sg:postcode":"4222",
    "sg:province":"Ober\u00f6sterreich",
    "wof:name":"SPAR \u00f6sterreichische Warenhandels-AG",
    "wof:placetype":"venue"
},
  "geometry": {"coordinates":[14.4499158859,48.2717475891],"type":"Point"}
}