{
  "type": "Feature",
  "properties": {
    "addr:full":"Pierlstr 10 Klagenfurt K\u00e4rnten 9020",
    "addr:housenumber":"10",
    "addr:postcode":"9020",
    "addr:street":"Pierlstr;Kaernten",
    "iso:country":"AT",
    "sg:address":"Pierlstr 10",
    "sg:city":"Klagenfurt",
    "sg:orig_category":"Ingenieurkonsulenten / Zivilingenieure",
    "sg:phone":"+43 463 514610",
    "sg:postcode":"9020",
    "sg:province":"K\u00e4rnten",
    "wof:name":"Ogris Werner Dipl-Ing",
    "wof:placetype":"venue"
},
  "geometry": {"coordinates":[14.2940206528,46.625],"type":"Point"}
}