{
  "type": "Feature",
  "properties": {
    "addr:full":"Stelzhamerstr 8 Haid Ober\u00f6sterreich 4053",
    "addr:housenumber":"8",
    "addr:postcode":"4053",
    "addr:street":"Stelzhamerstr;Oberoesterreich",
    "iso:country":"AT",
    "sg:address":"Stelzhamerstr 8",
    "sg:city":"Haid",
    "sg:orig_category":"Umweltschutz",
    "sg:phone":"+43 664 3409308",
    "sg:postcode":"4053",
    "sg:province":"Ober\u00f6sterreich",
    "wof:name":"\u00f6ko-Tex - Eichenauer Thomas Dipl-Ing",
    "wof:placetype":"venue"
},
  "geometry": {"coordinates":[14.2581224442,48.203792572],"type":"Point"}
}