{
  "type": "Feature",
  "properties": {
    "addr:full":"Steinerkirchner Str 2 Sattledt Ober\u00f6sterreich 4642",
    "addr:housenumber":"2",
    "addr:postcode":"4642",
    "addr:street":"Str",
    "iso:country":"AT",
    "sg:address":"Steinerkirchner Str 2",
    "sg:city":"Sattledt",
    "sg:orig_category":"Graveure, Abzeichen U Embleme",
    "sg:phone":"+43 7244 20151",
    "sg:postcode":"4642",
    "sg:province":"Ober\u00f6sterreich",
    "sg:website":"www.lehner-sportpreise.at",
    "wof:name":"Lehner Karlheinz",
    "wof:placetype":"venue"
},
  "geometry": {"coordinates":[14.0442304611,48.0758018494],"type":"Point"}
}