{
  "type": "Feature",
  "properties": {
    "addr:full":"Abt-Karl-G 18/7 Wien Wien 1180",
    "addr:housenumber":"18 / 7",
    "addr:postcode":"1180",
    "addr:street":"Abt-Karl-G",
    "iso:country":"AT",
    "sg:address":"Abt-Karl-G 18/7",
    "sg:city":"Wien",
    "sg:classifiers":[
        {
            "category":"Organizations",
            "subcategory":"Community Association",
            "type":"Services"
        }
    ],
    "sg:phone":"+43 4319 581114",
    "sg:postcode":"1180",
    "sg:province":"Wien",
    "sg:tags":[
        "relation",
        "public"
    ],
    "wof:name":"Essential PR",
    "wof:placetype":"venue"
},
  "geometry": {"coordinates":[16.3403129578,48.2250671387],"type":"Point"}
}