{
  "type": "Feature",
  "properties": {
    "addr:full":"Hechtstr 5 Salzburg Salzburg 5020",
    "addr:housenumber":"5",
    "addr:postcode":"5020",
    "addr:street":"Hechtstr;Salzburg",
    "iso:country":"AT",
    "sg:address":"Hechtstr 5",
    "sg:city":"Salzburg",
    "sg:orig_category":"Bauunternehmen",
    "sg:phone":"+43 662 420213",
    "sg:postcode":"5020",
    "sg:province":"Salzburg",
    "wof:name":"Eco-Bau GmbH",
    "wof:placetype":"venue"
},
  "geometry": {"coordinates":[13.0155439377,47.8348579407],"type":"Point"}
}