{
  "type": "Feature",
  "properties": {
    "addr:full":"Hutterweg 1a Innsbruck Tirol 6020",
    "addr:housenumber":"1a",
    "addr:postcode":"6020",
    "addr:street":"Hutterweg;Tirol",
    "iso:country":"AT",
    "sg:address":"Hutterweg 1a",
    "sg:city":"Innsbruck",
    "sg:orig_category":"Politische Parteien",
    "sg:phone":"+43 512 286888",
    "sg:postcode":"6020",
    "sg:province":"Tirol",
    "wof:name":"Sozialdemokratische Partei \u00f6sterreichs -H\u00f6ttinger Volkshaus",
    "wof:placetype":"venue"
},
  "geometry": {"coordinates":[11.3816556931,47.2647514343],"type":"Point"}
}