{
  "type": "Feature",
  "properties": {
    "addr:full":"Am Donauspitz 4 Ybbs an der Donau Nieder\u00f6sterreich 3370",
    "addr:housenumber":"4",
    "addr:postcode":"3370",
    "addr:street":"Am Donauspitz",
    "iso:country":"AT",
    "sg:address":"Am Donauspitz 4",
    "sg:city":"Ybbs an der Donau",
    "sg:orig_category":"Alteisen U Altmetalle",
    "sg:phone":"+43 4374 12524850",
    "sg:postcode":"3370",
    "sg:province":"Nieder\u00f6sterreich",
    "wof:name":"Pengg Ybbs KG",
    "wof:placetype":"venue"
},
  "geometry": {"coordinates":[15.0917921066,48.1718444824],"type":"Point"}
}