{
  "type": "Feature",
  "properties": {
    "addr:full":"Industriestr 14 Feldkirchen in K\u00e4rnten K\u00e4rnten 9560",
    "addr:housenumber":"14",
    "addr:postcode":"9560",
    "addr:street":"Industriestr;Kaernten",
    "iso:country":"AT",
    "sg:address":"Industriestr 14",
    "sg:city":"Feldkirchen in K\u00e4rnten",
    "sg:orig_category":"Transportunternehmen",
    "sg:phone":"+43 4342 763037",
    "sg:postcode":"9560",
    "sg:province":"K\u00e4rnten",
    "wof:name":"Seebacher Anton",
    "wof:placetype":"venue"
},
  "geometry": {"coordinates":[14.1008958817,46.7201919556],"type":"Point"}
}