{
  "type": "Feature",
  "properties": {
    "addr:full":"Obermarkt 3 Reutte Tirol 6600",
    "addr:housenumber":"3",
    "addr:postcode":"6600",
    "addr:street":"Obermarkt;Tirol",
    "iso:country":"AT",
    "sg:address":"Obermarkt 3",
    "sg:city":"Reutte",
    "sg:orig_category":"Geschenkartikel",
    "sg:phone":"+43 5672 65094",
    "sg:postcode":"6600",
    "sg:province":"Tirol",
    "wof:name":"Weltladen",
    "wof:placetype":"venue"
},
  "geometry": {"coordinates":[10.7186384201,47.4890556335],"type":"Point"}
}