{
  "type": "Feature",
  "properties": {
    "addr:full":"Johannesfeldstr 15 Volders Tirol 6111",
    "addr:housenumber":"15",
    "addr:postcode":"6111",
    "addr:street":"Johannesfeldstr;Tirol",
    "iso:country":"AT",
    "sg:address":"Johannesfeldstr 15",
    "sg:city":"Volders",
    "sg:orig_category":"Transportunternehmen",
    "sg:phone":"+43 5224 535330",
    "sg:postcode":"6111",
    "sg:province":"Tirol",
    "wof:name":"Fluckinger Transport GesmbH",
    "wof:placetype":"venue"
},
  "geometry": {"coordinates":[11.5738334656,47.2910308838],"type":"Point"}
}