{
  "type": "Feature",
  "properties": {
    "addr:full":"Rauhensteingasse 7 Wien Wien 1010",
    "addr:housenumber":"7",
    "addr:postcode":"1010",
    "addr:street":"Rauhensteingasse",
    "iso:country":"AT",
    "sg:address":"Rauhensteingasse 7",
    "sg:city":"Wien",
    "sg:classifiers":[
        {
            "category":"Building & Trades",
            "subcategory":"Electrical",
            "type":"Services"
        }
    ],
    "sg:phone":"+43 1 5135381",
    "sg:postcode":"1010",
    "sg:province":"Wien",
    "sg:tags":[
        "disassembly",
        "assembly",
        "stand",
        "fair"
    ],
    "sg:website":"braunias.com",
    "wof:name":"Ernst M. Braunias",
    "wof:placetype":"venue"
},
  "geometry": {"coordinates":[16.3726139069,48.2059059143],"type":"Point"}
}