{
  "type": "Feature",
  "properties": {
    "addr:full":"Prinzingerstr 11 Salzburg Salzburg 5020",
    "addr:housenumber":"11",
    "addr:postcode":"5020",
    "addr:street":"Prinzingerstr;Salzburg",
    "iso:country":"AT",
    "sg:address":"Prinzingerstr 11",
    "sg:city":"Salzburg",
    "sg:orig_category":"Physiotherapie",
    "sg:phone":"+43 662 830430",
    "sg:postcode":"5020",
    "sg:province":"Salzburg",
    "wof:name":"Steffelbauer Nikolaus Dipl-PT",
    "wof:placetype":"venue"
},
  "geometry": {"coordinates":[13.0502796173,47.7831993103],"type":"Point"}
}