{
  "type": "Feature",
  "properties": {
    "addr:full":"Karolingerstr 36 Salzburg Salzburg 5020",
    "addr:housenumber":"36",
    "addr:postcode":"5020",
    "addr:street":"Karolingerstr;Salzburg",
    "iso:country":"AT",
    "sg:address":"Karolingerstr 36",
    "sg:city":"Salzburg",
    "sg:orig_category":"Unternehmensberatung",
    "sg:phone":"+43 662 826220",
    "sg:postcode":"5020",
    "sg:province":"Salzburg",
    "wof:name":"Gerin Consulting Group Unternehmens- und Wirtschaftsberatung GmbH",
    "wof:placetype":"venue"
},
  "geometry": {"coordinates":[13.0107984543,47.7926101685],"type":"Point"}
}