{
  "type": "Feature",
  "properties": {
    "addr:full":"Feldg 34 Scheibbs Nieder\u00f6sterreich 3270",
    "addr:housenumber":"34",
    "addr:postcode":"3270",
    "addr:street":"Feldg",
    "iso:country":"AT",
    "sg:address":"Feldg 34",
    "sg:city":"Scheibbs",
    "sg:orig_category":"Garten- U Landschaftsgestaltung",
    "sg:phone":"+43 7482 42113",
    "sg:postcode":"3270",
    "sg:province":"Nieder\u00f6sterreich",
    "wof:name":"Teufel Robert Dipl-Ing",
    "wof:placetype":"venue"
},
  "geometry": {"coordinates":[15.1676197052,48.0055198669],"type":"Point"}
}