{
  "type": "Feature",
  "properties": {
    "addr:full":"Phorusg 5 Wien Wien 1040",
    "addr:housenumber":"5",
    "addr:postcode":"1040",
    "addr:street":"Phorusg",
    "iso:country":"AT",
    "sg:address":"Phorusg 5",
    "sg:city":"Wien",
    "sg:orig_category":"Zeitungen U Zeitschriften",
    "sg:phone":"+43 1 5874948",
    "sg:postcode":"1040",
    "sg:province":"Wien",
    "wof:name":"Uhudla Verlag und Redaktion",
    "wof:placetype":"venue"
},
  "geometry": {"coordinates":[16.3671455383,48.1940345764],"type":"Point"}
}