{
  "type": "Feature",
  "properties": {
    "iso:country":"AT",
    "sg:address":"Nr 140",
    "sg:city":"Ardning",
    "sg:orig_category":"Spenglereien",
    "sg:phone":"+43 3612 7683",
    "sg:postcode":"8904",
    "sg:province":"Steiermark",
    "wof:name":"Maier Bruno Dachdeckerei & Spenglerei",
    "wof:placetype":"venue"
},
  "geometry": {"coordinates":[14.3644237518,47.5910682678],"type":"Point"}
}