{
  "type": "Feature",
  "properties": {
    "addr:full":"Nr 122 Haag Nieder\u00f6sterreich 3350",
    "addr:postcode":"3350",
    "addr:street":"Nr 122 Haag Niederoesterreich",
    "iso:country":"AT",
    "sg:address":"Nr 122",
    "sg:city":"Haag",
    "sg:orig_category":"Friseure U Frisiersalons",
    "sg:phone":"+43 7434 44559",
    "sg:postcode":"3350",
    "sg:province":"Nieder\u00f6sterreich",
    "wof:name":"Fris\u00f6r Manuela",
    "wof:placetype":"venue"
},
  "geometry": {"coordinates":[14.5653553009,48.1121940613],"type":"Point"}
}