{
  "type": "Feature",
  "properties": {
    "addr:full":"Industrieparkstr. 6-8  Mureck Steiermark 8480",
    "addr:housenumber":"6-8",
    "addr:postcode":"8480",
    "addr:street":"Industrieparkstr.",
    "iso:country":"AT",
    "sg:address":"Industrieparkstr. 6-8 ",
    "sg:city":"Mureck",
    "sg:classifiers":[
        {
            "category":"Manufacturing",
            "subcategory":"Metals",
            "type":"Manufacturing & Wholesale Goods"
        }
    ],
    "sg:phone":"+43 4334 723244",
    "sg:postcode":"8480",
    "sg:province":"Steiermark",
    "sg:tags":[
        "metallurgy",
        "metalworking"
    ],
    "wof:name":"PHELPSDODGE MEGNERZWEIER AUSTRIA GESMBH",
    "wof:placetype":"venue"
},
  "geometry": {"coordinates":[15.7678871155,46.7116622925],"type":"Point"}
}