{
  "type": "Feature",
  "properties": {
    "iso:country":"AT",
    "sg:address":"Being 6",
    "sg:city":"Wien",
    "sg:orig_category":"Autohandel",
    "sg:phone":"+43 1 9822366",
    "sg:postcode":"1150",
    "sg:province":"Wien",
    "wof:name":"K\u00f6stler Ernst GmbH",
    "wof:placetype":"venue"
},
  "geometry": {"coordinates":[16.3335952759,48.1975822449],"type":"Point"}
}