{
  "type": "Feature",
  "properties": {
    "addr:full":"Hammerpark 6 M\u00fcrzzuschlag Steiermark 8680",
    "addr:housenumber":"6",
    "addr:postcode":"8680",
    "addr:street":"Hammerpark",
    "iso:country":"AT",
    "sg:address":"Hammerpark 6",
    "sg:city":"M\u00fcrzzuschlag",
    "sg:orig_category":"Messerschmiede",
    "sg:phone":"+43 3852 2627",
    "sg:postcode":"8680",
    "sg:province":"Steiermark",
    "wof:name":"Mrvka Christian Ing",
    "wof:placetype":"venue"
},
  "geometry": {"coordinates":[15.6735134125,47.6063842773],"type":"Point"}
}