{
  "type": "Feature",
  "properties": {
    "iso:country":"AT",
    "sg:address":"Grazer Str 18",
    "sg:city":"Krieglach",
    "sg:orig_category":"Fotografen",
    "sg:phone":"+43 3855 45500",
    "sg:postcode":"8670",
    "sg:province":"Steiermark",
    "wof:name":"Ebner Andreas",
    "wof:placetype":"venue"
},
  "geometry": {"coordinates":[15.5594654083,47.5439910889],"type":"Point"}
}