{
  "type": "Feature",
  "properties": {
    "iso:country":"AT",
    "sg:address":"Schallmooser Hauptstr 43",
    "sg:city":"Salzburg",
    "sg:orig_category":"Restaurants: Chinesisch",
    "sg:phone":"+43 4366 2876069",
    "sg:postcode":"5020",
    "sg:province":"Salzburg",
    "wof:name":"Chinarestaurant Lili",
    "wof:placetype":"venue"
},
  "geometry": {"coordinates":[13.0553731918,47.8068771362],"type":"Point"}
}