{
  "type": "Feature",
  "properties": {
    "addr:full":"Hummelbergstr 54 Sulz-R\u00f6this Vorarlberg 6832",
    "addr:housenumber":"54",
    "addr:postcode":"6832",
    "addr:street":"Hummelbergstr",
    "iso:country":"AT",
    "sg:address":"Hummelbergstr 54",
    "sg:city":"Sulz-R\u00f6this",
    "sg:orig_category":"Non-Classified Establishments",
    "sg:phone":"+43 5 91338161",
    "sg:postcode":"6832",
    "sg:province":"Vorarlberg",
    "wof:name":"Sulz Gendarmerieposten",
    "wof:placetype":"venue"
},
  "geometry": {"coordinates":[9.65528965,47.2887992859],"type":"Point"}
}