{
  "type": "Feature",
  "properties": {
    "addr:full":"Dorf 62 Kirchberg in Tirol Tirol 6365",
    "addr:housenumber":"62",
    "addr:postcode":"6365",
    "addr:street":"Dorf;Tirol",
    "iso:country":"AT",
    "sg:address":"Dorf 62",
    "sg:city":"Kirchberg in Tirol",
    "sg:orig_category":"Volksschulen",
    "sg:phone":"+43 5357 8105",
    "sg:postcode":"6365",
    "sg:province":"Tirol",
    "wof:name":"Volksschule",
    "wof:placetype":"venue"
},
  "geometry": {"coordinates":[12.3126001358,47.4481315613],"type":"Point"}
}