{
  "type": "Feature",
  "properties": {
    "addr:full":"Angerweg 44 Inzing Tirol 6401",
    "addr:housenumber":"44",
    "addr:postcode":"6401",
    "addr:street":"Angerweg;Tirol",
    "iso:country":"AT",
    "sg:address":"Angerweg 44",
    "sg:city":"Inzing",
    "sg:orig_category":"Transportunternehmen",
    "sg:phone":"+43 5238 88109",
    "sg:postcode":"6401",
    "sg:province":"Tirol",
    "wof:name":"Witsch Hermann Transport KG",
    "wof:placetype":"venue"
},
  "geometry": {"coordinates":[11.204706192,47.271522522],"type":"Point"}
}