{
  "type": "Feature",
  "properties": {
    "iso:country":"AT",
    "sg:address":"Kirchenpl 1",
    "sg:city":"Hartkirchen",
    "sg:orig_category":"Gemeinden",
    "sg:phone":"+43 7273 8955",
    "sg:postcode":"4081",
    "sg:province":"Ober\u00f6sterreich",
    "wof:name":"Gemeindeamt Hartkirchen",
    "wof:placetype":"venue"
},
  "geometry": {"coordinates":[14.0033407211,48.3629112244],"type":"Point"}
}