{
  "type": "Feature",
  "properties": {
    "addr:full":"Schlo\u00dfberg 4 Attersee Ober\u00f6sterreich 4864",
    "addr:housenumber":"4",
    "addr:postcode":"4864",
    "addr:street":"Schlossberg",
    "iso:country":"AT",
    "sg:address":"Schlo\u00dfberg 4",
    "sg:city":"Attersee",
    "sg:orig_category":"Appartements / Ferienwohnungen",
    "sg:phone":"+43 76667718",
    "sg:postcode":"4864",
    "sg:province":"Ober\u00f6sterreich",
    "wof:name":"Villa Orleans",
    "wof:placetype":"venue"
},
  "geometry": {"coordinates":[13.5405187607,47.918006897],"type":"Point"}
}