{
  "type": "Feature",
  "properties": {
    "addr:full":"Krottendorfer Str 85 Stra\u00dfgang Steiermark 8054",
    "addr:housenumber":"85",
    "addr:postcode":"8054",
    "addr:street":"Str",
    "iso:country":"AT",
    "sg:address":"Krottendorfer Str 85",
    "sg:city":"Stra\u00dfgang",
    "sg:orig_category":"Spenglereien",
    "sg:phone":"+43 316 577094",
    "sg:postcode":"8054",
    "sg:province":"Steiermark",
    "wof:name":"Comfort Dach-Spenglerei- und Dachdeckerei GmbH",
    "wof:placetype":"venue"
},
  "geometry": {"coordinates":[15.3990154266,47.0103302002],"type":"Point"}
}