{
  "type": "Feature",
  "properties": {
    "addr:full":"Jenny Lind-G 1 Wien Wien 1100",
    "addr:housenumber":"1",
    "addr:postcode":"1100",
    "iso:country":"AT",
    "sg:address":"Jenny Lind-G 1",
    "sg:city":"Wien",
    "sg:orig_category":"Volksschulen",
    "sg:phone":"+43 1 6893354",
    "sg:postcode":"1100",
    "sg:province":"Wien",
    "wof:name":"ALF - Bildungswerkstatt",
    "wof:placetype":"venue"
},
  "geometry": {"coordinates":[16.3812255859,48.1531257629],"type":"Point"}
}