{
  "type": "Feature",
  "properties": {
    "addr:full":"Feldg 2 Scheibbs Nieder\u00f6sterreich 3270",
    "addr:housenumber":"2",
    "addr:postcode":"3270",
    "addr:street":"Feldg",
    "iso:country":"AT",
    "sg:address":"Feldg 2",
    "sg:city":"Scheibbs",
    "sg:orig_category":"Maler, Anstreicher U Lackierer",
    "sg:phone":"+43 4374 8242348",
    "sg:postcode":"3270",
    "sg:province":"Nieder\u00f6sterreich",
    "wof:name":"Wurm Peter",
    "wof:placetype":"venue"
},
  "geometry": {"coordinates":[15.1676197052,48.0055198669],"type":"Point"}
}