{
  "type": "Feature",
  "properties": {
    "addr:full":"Hauptstr 4 Strasshof an der Nordbahn Nieder\u00f6sterreich 2231",
    "addr:housenumber":"4",
    "addr:postcode":"2231",
    "addr:street":"Hauptstr",
    "iso:country":"AT",
    "sg:address":"Hauptstr 4",
    "sg:city":"Strasshof an der Nordbahn",
    "sg:orig_category":"Autoersatzteile",
    "sg:phone":"+43 4322 874849",
    "sg:postcode":"2231",
    "sg:province":"Nieder\u00f6sterreich",
    "wof:name":"Forstinger Handel und Service GmbH",
    "wof:placetype":"venue"
},
  "geometry": {"coordinates":[16.6082210541,48.3114089966],"type":"Point"}
}