{
  "type": "Feature",
  "properties": {
    "addr:full":"Nr 149 Stuhlfelden Salzburg 5724",
    "addr:postcode":"5724",
    "addr:street":"Nr;Stuhlfelden",
    "iso:country":"AT",
    "sg:address":"Nr 149",
    "sg:city":"Stuhlfelden",
    "sg:orig_category":"Autoreparatur",
    "sg:phone":"+43 6562 53950",
    "sg:postcode":"5724",
    "sg:province":"Salzburg",
    "wof:name":"Huber Klaus Kfz- und Werkst\u00e4ttengesmbH",
    "wof:placetype":"venue"
},
  "geometry": {"coordinates":[12.5289773941,47.2883834839],"type":"Point"}
}