{
  "type": "Feature",
  "properties": {
    "addr:full":"Leopold-Gattringer-Str 83b Brunn am Gebirge Nieder\u00f6sterreich 2345",
    "addr:housenumber":"83b",
    "addr:postcode":"2345",
    "addr:street":"Leopold-Gattringer-Str",
    "iso:country":"AT",
    "sg:address":"Leopold-Gattringer-Str 83b",
    "sg:city":"Brunn am Gebirge",
    "sg:orig_category":"Werbegrafik- U Grafik-Design",
    "sg:phone":"+43 4322 36337010",
    "sg:postcode":"2345",
    "sg:province":"Nieder\u00f6sterreich",
    "wof:name":"Hutter GesmbH",
    "wof:placetype":"venue"
},
  "geometry": {"coordinates":[16.276222229,48.1097602844],"type":"Point"}
}