{
  "type": "Feature",
  "properties": {
    "iso:country":"AT",
    "sg:address":"Buchbergg 1",
    "sg:city":"Neumarkt in Steiermark",
    "sg:orig_category":"Fotografen",
    "sg:phone":"+43 4335 842456",
    "sg:postcode":"8820",
    "sg:province":"Steiermark",
    "wof:name":"Fotostudio Wei\u00df",
    "wof:placetype":"venue"
},
  "geometry": {"coordinates":[14.4246883392,47.0734977722],"type":"Point"}
}