{
  "type": "Feature",
  "properties": {
    "addr:full":"D\u00f6blinger Hauptstr 13A Wien Wien 1190",
    "addr:housenumber":"13a",
    "addr:postcode":"1190",
    "addr:street":"Hauptstr",
    "iso:country":"AT",
    "sg:address":"D\u00f6blinger Hauptstr 13A",
    "sg:city":"Wien",
    "sg:orig_category":"Spenglereien",
    "sg:phone":"+43 1 3694946",
    "sg:postcode":"1190",
    "sg:province":"Wien",
    "wof:name":"Nikolai Spenglerei GesmbH",
    "wof:placetype":"venue"
},
  "geometry": {"coordinates":[16.3528442383,48.2351951599],"type":"Point"}
}