{
  "type": "Feature",
  "properties": {
    "addr:full":"Nr 3 Anger Steiermark 8184",
    "addr:housenumber":"3",
    "addr:postcode":"8184",
    "addr:street":"Nr",
    "iso:country":"AT",
    "sg:address":"Nr 3",
    "sg:city":"Anger",
    "sg:orig_category":"Non-Classified Establishments",
    "sg:phone":"+43 4331 752386",
    "sg:postcode":"8184",
    "sg:province":"Steiermark",
    "wof:name":"Strahlhofer Johannes Ing",
    "wof:placetype":"venue"
},
  "geometry": {"coordinates":[15.7057800293,47.2626419067],"type":"Point"}
}