{
  "type": "Feature",
  "properties": {
    "addr:full":"Rosenh\u00fcgelstr 117 Wien Wien 1120",
    "addr:housenumber":"117",
    "addr:postcode":"1120",
    "iso:country":"AT",
    "sg:address":"Rosenh\u00fcgelstr 117",
    "sg:city":"Wien",
    "sg:orig_category":"Transportunternehmen",
    "sg:phone":"+43 1 8041667",
    "sg:postcode":"1120",
    "sg:province":"Wien",
    "wof:name":"Burger GmbH",
    "wof:placetype":"venue"
},
  "geometry": {"coordinates":[16.3290939331,48.1824874878],"type":"Point"}
}