{
  "type": "Feature",
  "properties": {
    "addr:full":"B\u00fcrgerstr 14 Langkampfen Tirol 6336",
    "addr:housenumber":"14",
    "addr:postcode":"6336",
    "addr:street":"Buergerstr;Tirol",
    "iso:country":"AT",
    "sg:address":"B\u00fcrgerstr 14",
    "sg:city":"Langkampfen",
    "sg:orig_category":"Volksschulen",
    "sg:phone":"+43 5332 88109",
    "sg:postcode":"6336",
    "sg:province":"Tirol",
    "wof:name":"Volksschule Unterlangkampfen",
    "wof:placetype":"venue"
},
  "geometry": {"coordinates":[12.0865154266,47.5244979858],"type":"Point"}
}