{
  "type": "Feature",
  "properties": {
    "addr:full":"Nr 217 Preding Steiermark 8504",
    "addr:postcode":"8504",
    "addr:street":"Nr 217",
    "iso:country":"AT",
    "sg:address":"Nr 217",
    "sg:city":"Preding",
    "sg:orig_category":"Pumpen",
    "sg:phone":"+43 3185 32110",
    "sg:postcode":"8504",
    "sg:province":"Steiermark",
    "sg:website":"hagpumpen.at",
    "wof:name":"HAG Pumpen Wassertechnik",
    "wof:placetype":"venue"
},
  "geometry": {"coordinates":[15.4067401886,46.8597869873],"type":"Point"}
}