{
  "type": "Feature",
  "properties": {
    "iso:country":"AT",
    "sg:address":"Harder Strasse 25",
    "sg:city":"Lauterach",
    "sg:classifiers":[
        {
            "category":"Train Station",
            "subcategory":"Light Rail",
            "type":"Transportation"
        }
    ],
    "sg:phone":"+43 5574 71282",
    "sg:postcode":"6923",
    "sg:province":"Vorarlberg",
    "sg:tags":[
        "heavy",
        "escorting",
        "good",
        "vehicle"
    ],
    "sg:website":"schneidertransporte.at",
    "wof:name":"Eduard Schneider Transport GmbH",
    "wof:placetype":"venue"
},
  "geometry": {"coordinates":[9.7265367508,47.4832878113],"type":"Point"}
}