{
  "type": "Feature",
  "properties": {
    "addr:full":"Nr 4 S\u00e4usenstein Nieder\u00f6sterreich 3374",
    "addr:housenumber":"3374",
    "addr:street":"Nr;Saeusenstein Niederoesterreich",
    "iso:country":"AT",
    "sg:address":"Nr 4",
    "sg:city":"S\u00e4usenstein",
    "sg:orig_category":"Fleischhauereien",
    "sg:phone":"+43 4374 1254352",
    "sg:postcode":"3374",
    "sg:province":"Nieder\u00f6sterreich",
    "wof:name":"Dietl L\u00e4mmerschlachtung u Zerlegebetrieb GesmbH",
    "wof:placetype":"venue"
},
  "geometry": {"coordinates":[15.1166582108,48.1923294067],"type":"Point"}
}