{
  "type": "Feature",
  "properties": {
    "addr:full":"Stadtpl 29 Gm\u00fcnd Nieder\u00f6sterreich 3950",
    "addr:housenumber":"29",
    "addr:postcode":"3950",
    "addr:street":"Stadtpl;Niederoesterreich",
    "iso:country":"AT",
    "sg:address":"Stadtpl 29",
    "sg:city":"Gm\u00fcnd",
    "sg:orig_category":"Fotografen",
    "sg:phone":"+43 2852 52623",
    "sg:postcode":"3950",
    "sg:province":"Nieder\u00f6sterreich",
    "wof:name":"Fotostudio Kainz Leander",
    "wof:placetype":"venue"
},
  "geometry": {"coordinates":[14.9855232239,48.7731628418],"type":"Point"}
}