{
  "type": "Feature",
  "properties": {
    "addr:full":"Obere Wei\u00dfgerberstr 8 Wien Wien 1030",
    "addr:housenumber":"8",
    "addr:postcode":"1030",
    "addr:street":"Obere Weissgerberstr",
    "iso:country":"AT",
    "sg:address":"Obere Wei\u00dfgerberstr 8",
    "sg:city":"Wien",
    "sg:orig_category":"Me\u00c3\u0178-, Steuer- U Regeltechnik",
    "sg:phone":"+43 1 71263350",
    "sg:postcode":"1030",
    "sg:province":"Wien",
    "wof:name":"Techem Me\u00dftechnik GesmbH",
    "wof:placetype":"venue"
},
  "geometry": {"coordinates":[16.3882789612,48.2121200562],"type":"Point"}
}