{
  "type": "Feature",
  "properties": {
    "iso:country":"AT",
    "sg:address":"Maxglaner Hauptstr 24",
    "sg:city":"Salzburg",
    "sg:orig_category":"Tabaktrafiken",
    "sg:phone":"+43 662 834031",
    "sg:postcode":"5020",
    "sg:province":"Salzburg",
    "wof:name":"Rieder Ingrid",
    "wof:placetype":"venue"
},
  "geometry": {"coordinates":[13.0221214294,47.7969436646],"type":"Point"}
}