{
  "type": "Feature",
  "properties": {
    "iso:country":"AT",
    "sg:address":"Triester Str 291",
    "sg:city":"Feldkirchen",
    "sg:orig_category":"Tankstellen",
    "sg:phone":"+43 4331 3552238",
    "sg:postcode":"8073",
    "sg:province":"Steiermark",
    "wof:name":"Diskont Tankstelle",
    "wof:placetype":"venue"
},
  "geometry": {"coordinates":[15.4590864182,46.9866294861],"type":"Point"}
}