{
  "type": "Feature",
  "properties": {
    "addr:full":"Oberlend 121 Lend Salzburg 5651",
    "addr:housenumber":"121",
    "addr:postcode":"5651",
    "addr:street":"Oberlend;Salzburg",
    "iso:country":"AT",
    "sg:address":"Oberlend 121",
    "sg:city":"Lend",
    "sg:orig_category":"Unternehmensberatung",
    "sg:phone":"+43 4367 65822928",
    "sg:postcode":"5651",
    "sg:province":"Salzburg",
    "wof:name":"c o a c h i n g f o r y o u Karl Christian Filip",
    "wof:placetype":"venue"
},
  "geometry": {"coordinates":[13.0434465408,47.299446106],"type":"Point"}
}