{
  "type": "Feature",
  "properties": {
    "addr:full":"Ketzerg 271 Perchtoldsdorf Nieder\u00f6sterreich 2380",
    "addr:housenumber":"271",
    "addr:postcode":"2380",
    "iso:country":"AT",
    "sg:address":"Ketzerg 271",
    "sg:city":"Perchtoldsdorf",
    "sg:orig_category":"Tonstudios",
    "sg:phone":"+43 1 8697572",
    "sg:postcode":"2380",
    "sg:province":"Nieder\u00f6sterreich",
    "wof:name":"Klangwerk - Stefan Berndorfer",
    "wof:placetype":"venue"
},
  "geometry": {"coordinates":[16.2828388214,48.1305236816],"type":"Point"}
}