{
  "type": "Feature",
  "properties": {
    "addr:full":"Vierthalerstr 12 Mauerkirchen Ober\u00f6sterreich 5270",
    "addr:housenumber":"12",
    "addr:postcode":"5270",
    "addr:street":"Vierthalerstr",
    "iso:country":"AT",
    "sg:address":"Vierthalerstr 12",
    "sg:city":"Mauerkirchen",
    "sg:orig_category":"Behinderungen / Leben Mit Behinderungen",
    "sg:phone":"+43 4377 242315",
    "sg:postcode":"5270",
    "sg:province":"Ober\u00f6sterreich",
    "wof:name":"\u00f6ZIV - \u00f6sterreichischer Zivil-Invalidenverband",
    "wof:placetype":"venue"
},
  "geometry": {"coordinates":[13.1308231354,48.1935653687],"type":"Point"}
}