{
  "type": "Feature",
  "properties": {
    "addr:full":"Linzer G 60 Salzburg Salzburg 5020",
    "addr:housenumber":"60",
    "addr:postcode":"5020",
    "addr:street":"Linzer G;Salzburg",
    "iso:country":"AT",
    "sg:address":"Linzer G 60",
    "sg:city":"Salzburg",
    "sg:orig_category":"Bierlokale-Pubs",
    "sg:phone":"+43 662 876615",
    "sg:postcode":"5020",
    "sg:province":"Salzburg",
    "wof:name":"Wieninger Bier-Treff",
    "wof:placetype":"venue"
},
  "geometry": {"coordinates":[13.047961235,47.8039245605],"type":"Point"}
}