{
  "type": "Feature",
  "properties": {
    "addr:full":"Fabriksg. 15 Bad Erlach Nieder\u00f6sterreich 2822",
    "addr:housenumber":"15",
    "addr:postcode":"2822",
    "addr:street":"Fabriksg.",
    "iso:country":"AT",
    "sg:address":"Fabriksg. 15",
    "sg:city":"Bad Erlach",
    "sg:classifiers":[
        {
            "category":"Shopping",
            "subcategory":"Clothing, Apparel, & Fashions",
            "type":"Retail Goods"
        }
    ],
    "sg:phone":"+43 4326 27482130",
    "sg:postcode":"2822",
    "sg:province":"Nieder\u00f6sterreich",
    "sg:tags":[
        "clothes"
    ],
    "wof:name":"ING. ANDREAS JEITLER GMBH",
    "wof:placetype":"venue"
},
  "geometry": {"coordinates":[16.2177429199,47.7285728455],"type":"Point"}
}