{
  "type": "Feature",
  "properties": {
    "addr:full":"Hinterthal 68 Maria Alm am Steinernen Meer Salzburg 5761",
    "addr:housenumber":"68",
    "addr:postcode":"5761",
    "addr:street":"Hinterthal",
    "iso:country":"AT",
    "sg:address":"Hinterthal 68",
    "sg:city":"Maria Alm am Steinernen Meer",
    "sg:classifiers":[
        {
            "category":"Park",
            "subcategory":"Provincial",
            "type":"Public Place"
        }
    ],
    "sg:phone":"+43 4365 848110",
    "sg:postcode":"5761",
    "sg:province":"Salzburg",
    "sg:tags":[
        "u",
        "ski-",
        "snowboardschulen"
    ],
    "wof:name":"Schischule Hinterthal",
    "wof:placetype":"venue"
},
  "geometry": {"coordinates":[12.9839162827,47.4142532349],"type":"Point"}
}