{
  "type": "Feature",
  "properties": {
    "addr:full":"Sieveringer Str 47 Wien Wien 1190",
    "addr:housenumber":"47",
    "addr:postcode":"1190",
    "addr:street":"Sieveringer Str",
    "iso:country":"AT",
    "sg:address":"Sieveringer Str 47",
    "sg:city":"Wien",
    "sg:orig_category":"Steuerberatung",
    "sg:phone":"+43 1 3208423",
    "sg:postcode":"1190",
    "sg:province":"Wien",
    "wof:name":"Varga Georg",
    "wof:placetype":"venue"
},
  "geometry": {"coordinates":[16.3367404938,48.2463569641],"type":"Point"}
}