{
  "type": "Feature",
  "properties": {
    "addr:full":"Kirchensteig 7 Villach K\u00e4rnten 9500",
    "addr:housenumber":"7",
    "addr:postcode":"9500",
    "addr:street":"Kirchensteig;Kaernten",
    "iso:country":"AT",
    "sg:address":"Kirchensteig 7",
    "sg:city":"Villach",
    "sg:orig_category":"\u00c3\u201erzte / F Allgemeinmedizin",
    "sg:phone":"+43 4242 56556",
    "sg:postcode":"9500",
    "sg:province":"K\u00e4rnten",
    "wof:name":"Heindl Rolf Dr",
    "wof:placetype":"venue"
},
  "geometry": {"coordinates":[13.8329677582,46.6183929443],"type":"Point"}
}