{
  "type": "Feature",
  "properties": {
    "iso:country":"AT",
    "sg:address":"Deutschstr 25",
    "sg:city":"Wien",
    "sg:orig_category":"Rechenzentren",
    "sg:phone":"+43 1 61636060",
    "sg:postcode":"1230",
    "sg:province":"Wien",
    "wof:name":"Rechenzentrum Vostrovsky GmbH",
    "wof:placetype":"venue"
},
  "geometry": {"coordinates":[16.3582687378,48.141166687],"type":"Point"}
}