{
  "type": "Feature",
  "properties": {
    "addr:full":"Buchenweg 5 Pernegg an der Mur Steiermark 8132",
    "addr:housenumber":"5",
    "addr:postcode":"8132",
    "addr:street":"Buchenweg",
    "iso:country":"AT",
    "sg:address":"Buchenweg 5",
    "sg:city":"Pernegg an der Mur",
    "sg:orig_category":"Transportunternehmen",
    "sg:phone":"+43 3867 5035",
    "sg:postcode":"8132",
    "sg:province":"Steiermark",
    "wof:name":"Kahr Franz Transporte Holzhandel GesmbH",
    "wof:placetype":"venue"
},
  "geometry": {"coordinates":[15.3152141571,47.3658218384],"type":"Point"}
}