{
  "type": "Feature",
  "properties": {
    "addr:full":"Raxstr 97 Wien Wien 1100",
    "addr:housenumber":"97",
    "addr:postcode":"1100",
    "addr:street":"Raxstr",
    "iso:country":"AT",
    "sg:address":"Raxstr 97",
    "sg:city":"Wien",
    "sg:orig_category":"Fotografen",
    "sg:phone":"+43 1 6172171",
    "sg:postcode":"1100",
    "sg:province":"Wien",
    "wof:name":"Badegruber Stefan",
    "wof:placetype":"venue"
},
  "geometry": {"coordinates":[16.351890564,48.1687164307],"type":"Point"}
}