{
  "type": "Feature",
  "properties": {
    "iso:country":"AT",
    "sg:address":"Kirchengasse 2b",
    "sg:city":"Salzburg",
    "sg:classifiers":[
        {
            "category":"Shopping",
            "type":"Retail Goods"
        }
    ],
    "sg:phone":"+43 4366 2438086",
    "sg:postcode":"5020",
    "sg:province":"Salzburg",
    "sg:tags":[
        "finished",
        "-",
        "metallic"
    ],
    "wof:name":"FLOTZINGER & BRENNER GES.MBH",
    "wof:placetype":"venue"
},
  "geometry": {"coordinates":[13.044210434,47.8226394653],"type":"Point"}
}