{
  "type": "Feature",
  "properties": {
    "addr:full":"Schenkendorfg 1 Wien Wien 1210",
    "addr:housenumber":"1",
    "addr:postcode":"1210",
    "addr:street":"Schenkendorfg",
    "iso:country":"AT",
    "sg:address":"Schenkendorfg 1",
    "sg:city":"Wien",
    "sg:orig_category":"Lebensmittel / Einzelhandel",
    "sg:phone":"+43 1 2711103",
    "sg:postcode":"1210",
    "sg:province":"Wien",
    "wof:name":"Billa AG",
    "wof:placetype":"venue"
},
  "geometry": {"coordinates":[16.4055633545,48.257686615],"type":"Point"}
}