{
  "type": "Feature",
  "properties": {
    "addr:full":"Wiesenstr 18/4 Klaus-Weiler Vorarlberg 6833",
    "addr:housenumber":"18 / 4",
    "addr:postcode":"6833",
    "addr:street":"Wiesenstr;Klaus-Weiler Vorarlberg",
    "iso:country":"AT",
    "sg:address":"Wiesenstr 18/4",
    "sg:city":"Klaus-Weiler",
    "sg:classifiers":[
        {
            "category":"Home & Garden",
            "subcategory":"Building Materials",
            "type":"Retail Goods"
        }
    ],
    "sg:phone":"+43 4355 2355933",
    "sg:postcode":"6833",
    "sg:province":"Vorarlberg",
    "sg:tags":[
        "baustoffe",
        "-material",
        "u"
    ],
    "wof:name":"L\u00e4ngle Joachim M - Elements Bodensysteme Bauelemente",
    "wof:placetype":"venue"
},
  "geometry": {"coordinates":[9.6468400955,47.3021278381],"type":"Point"}
}