{
  "type": "Feature",
  "properties": {
    "iso:country":"AT",
    "sg:address":"D\u00f6rferstr 25",
    "sg:city":"Thaur",
    "sg:orig_category":"Transportunternehmen",
    "sg:phone":"+43 5223 4927610",
    "sg:postcode":"6065",
    "sg:province":"Tirol",
    "wof:name":"Sampt & S\u00f6hne Transporte GesmbH",
    "wof:placetype":"venue"
},
  "geometry": {"coordinates":[11.4739055634,47.2920532227],"type":"Point"}
}