{
  "type": "Feature",
  "properties": {
    "addr:full":"Hirschstr 18 Klagenfurt K\u00e4rnten 9020",
    "addr:housenumber":"18",
    "addr:postcode":"9020",
    "addr:street":"Hirschstr;Kaernten",
    "iso:country":"AT",
    "sg:address":"Hirschstr 18",
    "sg:city":"Klagenfurt",
    "sg:classifiers":[
        {
            "category":"Government",
            "subcategory":"Post Office",
            "type":"Public Place"
        }
    ],
    "sg:phone":"+43 4346 3366530",
    "sg:postcode":"9020",
    "sg:province":"K\u00e4rnten",
    "sg:tags":[
        "u",
        "-material",
        "dachdeckereibedarf"
    ],
    "wof:name":"Dach & Wand HandelsgesmbH & Co KG",
    "wof:placetype":"venue"
},
  "geometry": {"coordinates":[14.3160495758,46.6023902893],"type":"Point"}
}