{
  "type": "Feature",
  "properties": {
    "iso:country":"AT",
    "sg:address":"Kiebach 6",
    "sg:city":"Hofkirchen im Traunkreis",
    "sg:orig_category":"Fische U Fischwaren / Einzelhandel",
    "sg:phone":"+43 4372 257340",
    "sg:postcode":"4492",
    "sg:province":"Ober\u00f6sterreich",
    "wof:name":"Jagerbauer Fischspezialit\u00e4ten",
    "wof:placetype":"venue"
},
  "geometry": {"coordinates":[14.336148262,48.1324615479],"type":"Point"}
}