{
  "type": "Feature",
  "properties": {
    "addr:full":"Kornmarktstr 9 Bregenz Vorarlberg 6900",
    "addr:housenumber":"9",
    "addr:postcode":"6900",
    "addr:street":"Kornmarktstr",
    "iso:country":"AT",
    "sg:address":"Kornmarktstr 9",
    "sg:city":"Bregenz",
    "sg:orig_category":"\u00c3\u201erzte / F Allgemeinmedizin",
    "sg:phone":"+43 4355 7444273",
    "sg:postcode":"6900",
    "sg:province":"Vorarlberg",
    "wof:name":"Jungblut Thomas Dr",
    "wof:placetype":"venue"
},
  "geometry": {"coordinates":[9.7488307953,47.5053977966],"type":"Point"}
}