{
  "type": "Feature",
  "properties": {
    "addr:full":"Nr 37 Edelsbach Steiermark 8332",
    "addr:postcode":"8332",
    "addr:street":"Nr;Edelsbach",
    "iso:country":"AT",
    "sg:address":"Nr 37",
    "sg:city":"Edelsbach",
    "sg:orig_category":"Montagen U Montagetechnik",
    "sg:phone":"+43 4367 67387999",
    "sg:postcode":"8332",
    "sg:province":"Steiermark",
    "sg:website":"moebel-montagen-grein.at",
    "wof:name":"Grein Edwin",
    "wof:placetype":"venue"
},
  "geometry": {"coordinates":[15.8364782333,46.9893836975],"type":"Point"}
}