{
  "type": "Feature",
  "properties": {
    "iso:country":"AT",
    "sg:address":"K\u00f6glstr 19",
    "sg:city":"Linz",
    "sg:orig_category":"Fahrzeugbau",
    "sg:phone":"+43 732 792400",
    "sg:postcode":"4020",
    "sg:province":"Ober\u00f6sterreich",
    "wof:name":"Degelsegger Fahrzeugteile Handels GmbH",
    "wof:placetype":"venue"
},
  "geometry": {"coordinates":[14.2451400757,48.3018455505],"type":"Point"}
}