{
  "type": "Feature",
  "properties": {
    "addr:full":"Peischinger Strasse 71 Neunkirchen Nieder\u00f6sterreich 2620",
    "addr:housenumber":"71",
    "addr:postcode":"2620",
    "addr:street":"Peischinger Strasse",
    "iso:country":"AT",
    "sg:address":"Peischinger Strasse 71",
    "sg:city":"Neunkirchen",
    "sg:classifiers":[
        {
            "category":"Manufacturing",
            "subcategory":"Wood Products",
            "type":"Manufacturing & Wholesale Goods"
        }
    ],
    "sg:phone":"+43 2635 62553",
    "sg:postcode":"2620",
    "sg:province":"Nieder\u00f6sterreich",
    "sg:tags":[
        "lumber"
    ],
    "wof:name":"Felix Schwarz Ges.m.b.H.",
    "wof:placetype":"venue"
},
  "geometry": {"coordinates":[16.0975093842,47.7266464233],"type":"Point"}
}