{
  "type": "Feature",
  "properties": {
    "addr:full":"Unterp\u00fchret 4c Roitham Ober\u00f6sterreich 4661",
    "addr:housenumber":"4c",
    "addr:postcode":"4661",
    "addr:street":"Unterpuehret",
    "iso:country":"AT",
    "sg:address":"Unterp\u00fchret 4c",
    "sg:city":"Roitham",
    "sg:classifiers":[
        {
            "category":"Utilities",
            "subcategory":"Cable",
            "type":"Services"
        }
    ],
    "sg:phone":"+43 761332768",
    "sg:postcode":"4661",
    "sg:province":"Ober\u00f6sterreich",
    "sg:tags":[
        "wire",
        "erosion",
        "cnc",
        "machining"
    ],
    "wof:name":"Six KEG",
    "wof:placetype":"venue"
},
  "geometry": {"coordinates":[13.8226041794,48.0241851807],"type":"Point"}
}