{
  "type": "Feature",
  "properties": {
    "iso:country":"AT",
    "sg:address":"Lendkai 23",
    "sg:city":"Graz",
    "sg:orig_category":"Baumeister, Bauunternehmen",
    "sg:phone":"+43 316 713069",
    "sg:postcode":"8020",
    "sg:province":"Steiermark",
    "wof:name":"Langmann Heribert Bmstr Ing",
    "wof:placetype":"venue"
},
  "geometry": {"coordinates":[15.4338312149,47.0735397339],"type":"Point"}
}