{
  "type": "Feature",
  "properties": {
    "addr:full":"Schillerstr 15 Feldbach Steiermark 8330",
    "addr:housenumber":"15",
    "addr:postcode":"8330",
    "addr:street":"Schillerstr",
    "iso:country":"AT",
    "sg:address":"Schillerstr 15",
    "sg:city":"Feldbach",
    "sg:orig_category":"Bestattungsunternehmen",
    "sg:phone":"+43 3152 2476",
    "sg:postcode":"8330",
    "sg:province":"Steiermark",
    "wof:name":"Bestattung Feldbach",
    "wof:placetype":"venue"
},
  "geometry": {"coordinates":[15.88808918,46.9500465393],"type":"Point"}
}