{
  "type": "Feature",
  "properties": {
    "iso:country":"AT",
    "sg:address":"Hauptpl 10",
    "sg:city":"Liezen",
    "sg:orig_category":"Damenmoden",
    "sg:phone":"+43 3612 25380",
    "sg:postcode":"8940",
    "sg:province":"Steiermark",
    "wof:name":"Zimm Mode",
    "wof:placetype":"venue"
},
  "geometry": {"coordinates":[14.241815567,47.5673027039],"type":"Point"}
}