{
  "type": "Feature",
  "properties": {
    "addr:full":"Hessenbergstr 56 St. Peter-Freienstein Steiermark 8792",
    "addr:housenumber":"56",
    "addr:postcode":"8792",
    "addr:street":"Hessenbergstr",
    "iso:country":"AT",
    "sg:address":"Hessenbergstr 56",
    "sg:city":"St. Peter-Freienstein",
    "sg:orig_category":"Ingenieurkonsulenten / Zivilingenieure",
    "sg:phone":"+43 4338 338692",
    "sg:postcode":"8792",
    "sg:province":"Steiermark",
    "wof:name":"Hochegger Gottfried Ziv Ing Dipl Ing",
    "wof:placetype":"venue"
},
  "geometry": {"coordinates":[15.0082330704,47.3941307068],"type":"Point"}
}