{
  "type": "Feature",
  "properties": {
    "addr:full":"Annenstr 20 Graz Steiermark 8020",
    "addr:housenumber":"20",
    "addr:postcode":"8020",
    "addr:street":"Annenstr",
    "iso:country":"AT",
    "sg:address":"Annenstr 20",
    "sg:city":"Graz",
    "sg:orig_category":"Boutiquen",
    "sg:phone":"+43 316 714480",
    "sg:postcode":"8020",
    "sg:province":"Steiermark",
    "wof:name":"Your fashion",
    "wof:placetype":"venue"
},
  "geometry": {"coordinates":[15.4289474487,47.0712051392],"type":"Point"}
}