{
  "type": "Feature",
  "properties": {
    "addr:full":"Fischerh\u00e4uslweg 31 Innsbruck Tirol 6020",
    "addr:housenumber":"31",
    "addr:postcode":"6020",
    "addr:street":"Fischerhaeuslweg;Tirol",
    "iso:country":"AT",
    "sg:address":"Fischerh\u00e4uslweg 31",
    "sg:city":"Innsbruck",
    "sg:orig_category":"Lebensmittel / Einzelhandel",
    "sg:phone":"+43 512 2782960",
    "sg:postcode":"6020",
    "sg:province":"Tirol",
    "wof:name":"MPREIS WarenvertriebsgesmbH",
    "wof:placetype":"venue"
},
  "geometry": {"coordinates":[11.3913040161,47.2679977417],"type":"Point"}
}