{
  "type": "Feature",
  "properties": {
    "iso:country":"AT",
    "sg:address":"Linzer Str 14",
    "sg:city":"Lambach",
    "sg:orig_category":"Tankstellen",
    "sg:phone":"+43 7245 226050",
    "sg:postcode":"4650",
    "sg:province":"Ober\u00f6sterreich",
    "wof:name":"Avia Tankstelle",
    "wof:placetype":"venue"
},
  "geometry": {"coordinates":[13.8922805786,48.0952148438],"type":"Point"}
}