{
  "type": "Feature",
  "properties": {
    "addr:full":"Am Teichfeld 2 Sarleinsbach Ober\u00f6sterreich 4152",
    "addr:housenumber":"2",
    "addr:postcode":"4152",
    "addr:street":"Am Teichfeld",
    "iso:country":"AT",
    "sg:address":"Am Teichfeld 2",
    "sg:city":"Sarleinsbach",
    "sg:orig_category":"Tischlereien",
    "sg:phone":"+43 7283 82170",
    "sg:postcode":"4152",
    "sg:province":"Ober\u00f6sterreich",
    "wof:name":"Haslmaier Robert GesmbH",
    "wof:placetype":"venue"
},
  "geometry": {"coordinates":[13.9050512314,48.5455436707],"type":"Point"}
}