{
  "type": "Feature",
  "properties": {
    "addr:full":"Kalkofenstr 14A Haiming Tirol 6425",
    "addr:housenumber":"14a",
    "addr:postcode":"6425",
    "addr:street":"Kalkofenstr;Tirol",
    "iso:country":"AT",
    "sg:address":"Kalkofenstr 14A",
    "sg:city":"Haiming",
    "sg:classifiers":[
        {
            "category":"Restaurant",
            "type":"Food & Drink"
        }
    ],
    "sg:phone":"+43 5266 88862",
    "sg:postcode":"6425",
    "sg:province":"Tirol",
    "wof:name":"Restaurationswerkst\u00e4tte Martin Prantl",
    "wof:placetype":"venue"
},
  "geometry": {"coordinates":[10.8829746246,47.2520713806],"type":"Point"}
}