{
  "type": "Feature",
  "properties": {
    "iso:country":"AT",
    "sg:address":"Alte Hauptstr 68",
    "sg:city":"F\u00fcgen",
    "sg:orig_category":"Optiker",
    "sg:phone":"+43 5288 62905",
    "sg:postcode":"6263",
    "sg:province":"Tirol",
    "wof:name":"Ritzl Walter",
    "wof:placetype":"venue"
},
  "geometry": {"coordinates":[101.76634216310001,30.9142303467],"type":"Point"}
}