{
  "type": "Feature",
  "properties": {
    "addr:full":"Estepl 4/10 Wien Wien 1030",
    "addr:housenumber":"4 / 10",
    "addr:postcode":"1030",
    "addr:street":"Estepl",
    "iso:country":"AT",
    "sg:address":"Estepl 4/10",
    "sg:city":"Wien",
    "sg:orig_category":"Psychotherapie",
    "sg:phone":"+43 1 7109500",
    "sg:postcode":"1030",
    "sg:province":"Wien",
    "wof:name":"St\u00f6ger Irmgard Dr",
    "wof:placetype":"venue"
},
  "geometry": {"coordinates":[16.3899326324,48.2048606873],"type":"Point"}
}