{
  "type": "Feature",
  "properties": {
    "addr:full":"Subiacostr 22 Kremsm\u00fcnster Ober\u00f6sterreich 4550",
    "addr:housenumber":"22",
    "addr:postcode":"4550",
    "addr:street":"Subiacostr;Oberoesterreich",
    "iso:country":"AT",
    "sg:address":"Subiacostr 22",
    "sg:city":"Kremsm\u00fcnster",
    "sg:orig_category":"Non-Classified Establishments",
    "sg:phone":"+43 7583 5486",
    "sg:postcode":"4550",
    "sg:province":"Ober\u00f6sterreich",
    "wof:name":"Cursillo Di\u00f6zese Linz",
    "wof:placetype":"venue"
},
  "geometry": {"coordinates":[14.1204109192,48.0516815186],"type":"Point"}
}