{
  "type": "Feature",
  "properties": {
    "iso:country":"AT",
    "sg:address":"Carl-Blum-Strasse 3-5",
    "sg:city":"Wels",
    "sg:classifiers":[
        {
            "category":"Home & Garden",
            "subcategory":"Building Materials",
            "type":"Retail Goods"
        }
    ],
    "sg:phone":"+43 7242 45079",
    "sg:postcode":"4600",
    "sg:province":"Ober\u00f6sterreich",
    "sg:tags":[
        "antiglare",
        "blind",
        "roller"
    ],
    "sg:website":"weku.co.at",
    "wof:name":"WEKU Handelsges.m.b.H.",
    "wof:placetype":"venue"
},
  "geometry": {"coordinates":[14.032743454,48.1623687744],"type":"Point"}
}