{
  "type": "Feature",
  "properties": {
    "addr:full":"Hernalser Hauptstr 79 Wien Wien 1170",
    "addr:housenumber":"79",
    "addr:postcode":"1170",
    "addr:street":"Hernalser Hauptstr",
    "iso:country":"AT",
    "sg:address":"Hernalser Hauptstr 79",
    "sg:city":"Wien",
    "sg:orig_category":"Installationsunternehmen",
    "sg:phone":"+43 1 4869335",
    "sg:postcode":"1170",
    "sg:province":"Wien",
    "wof:name":"AHT Novak KEG",
    "wof:placetype":"venue"
},
  "geometry": {"coordinates":[16.3290729523,48.2183074951],"type":"Point"}
}