{
  "type": "Feature",
  "properties": {
    "addr:full":"Landstr. 27 Linz Ober\u00f6sterreich 4020",
    "addr:housenumber":"27",
    "addr:postcode":"4020",
    "addr:street":"Landstr.",
    "iso:country":"AT",
    "sg:address":"Landstr. 27",
    "sg:city":"Linz",
    "sg:classifiers":[
        {
            "category":"Bars & Pubs",
            "subcategory":"Nightclub",
            "type":"Food & Drink"
        }
    ],
    "sg:phone":"+43 4373 27716200",
    "sg:postcode":"4020",
    "sg:province":"Ober\u00f6sterreich",
    "sg:tags":[
        "cake",
        "bread"
    ],
    "wof:name":"HEINZ HOFMANN EV",
    "wof:placetype":"venue"
},
  "geometry": {"coordinates":[14.2897396088,48.3024559021],"type":"Point"}
}