{
  "type": "Feature",
  "properties": {
    "iso:country":"AT",
    "sg:address":"Seiserstrasse 6",
    "sg:city":"Kirchschlag in der Buckligen Welt",
    "sg:orig_category":"Borders Textil",
    "sg:phone":"+43 2646 25340",
    "sg:postcode":"2860",
    "sg:province":"Nieder\u00f6sterreich",
    "sg:website":"kwl.at",
    "wof:name":"KWL Textil GmbH",
    "wof:placetype":"venue"
},
  "geometry": {"coordinates":[16.2776756287,47.4919967651],"type":"Point"}
}