{
  "type": "Feature",
  "properties": {
    "addr:full":"Landstra\u00dfer Hauptstr 173-175 Wien Wien 1030",
    "addr:postcode":"173-175;1030",
    "addr:street":"Landstrasser Hauptstr",
    "iso:country":"AT",
    "sg:address":"Landstra\u00dfer Hauptstr 173-175",
    "sg:city":"Wien",
    "sg:orig_category":"Marmor U Marmorwaren, Heizungen",
    "sg:phone":"+43 1 7984349",
    "sg:postcode":"1030",
    "sg:province":"Wien",
    "wof:name":"Pospichal Der Marmorheizungsspezialist",
    "wof:placetype":"venue"
},
  "geometry": {"coordinates":[16.4008674622,48.1899337769],"type":"Point"}
}