{
  "type": "Feature",
  "properties": {
    "addr:full":"Schillerstr 37 Graz Steiermark 8010",
    "addr:housenumber":"37",
    "addr:postcode":"8010",
    "addr:street":"Schillerstr",
    "iso:country":"AT",
    "sg:address":"Schillerstr 37",
    "sg:city":"Graz",
    "sg:orig_category":"Bildhauer",
    "sg:phone":"+43 650 6699300",
    "sg:postcode":"8010",
    "sg:province":"Steiermark",
    "wof:name":"Preisegger Bernt",
    "wof:placetype":"venue"
},
  "geometry": {"coordinates":[15.4565172195,47.0701675415],"type":"Point"}
}