{
  "type": "Feature",
  "properties": {
    "iso:country":"AT",
    "sg:address":"Schnalla 51",
    "sg:city":"Ried im Innkreis",
    "sg:classifiers":[
        {
            "category":"Professional",
            "subcategory":"Printing & Photocopies",
            "type":"Services"
        }
    ],
    "sg:phone":"+43 7752 88388",
    "sg:postcode":"4910",
    "sg:province":"Ober\u00f6sterreich",
    "sg:tags":[
        "shop",
        "digital"
    ],
    "sg:website":"druckstore.at",
    "wof:name":"Bernard Ges.m.b.H.",
    "wof:placetype":"venue"
},
  "geometry": {"coordinates":[13.4947328568,48.222038269],"type":"Point"}
}