{
  "type": "Feature",
  "properties": {
    "addr:full":"Pergerstr 11a Baden Nieder\u00f6sterreich 2500",
    "addr:housenumber":"11a",
    "addr:postcode":"2500",
    "addr:street":"Pergerstr;Niederoesterreich",
    "iso:country":"AT",
    "sg:address":"Pergerstr 11a",
    "sg:city":"Baden",
    "sg:orig_category":"Blumeneinzelhandel",
    "sg:phone":"+43 2252 85456",
    "sg:postcode":"2500",
    "sg:province":"Nieder\u00f6sterreich",
    "wof:name":"Blumen Weil - Floristik Modern",
    "wof:placetype":"venue"
},
  "geometry": {"coordinates":[16.2310256958,48.0066223145],"type":"Point"}
}