{
  "type": "Feature",
  "properties": {
    "addr:full":"Bernhard-Schmidt-G 6 Gmunden Ober\u00f6sterreich 4810",
    "addr:housenumber":"6",
    "addr:postcode":"4810",
    "addr:street":"Bernhard-Schmidt-G;Oberoesterreich",
    "iso:country":"AT",
    "sg:address":"Bernhard-Schmidt-G 6",
    "sg:city":"Gmunden",
    "sg:orig_category":"Bauunternehmen",
    "sg:phone":"+43 761277689",
    "sg:postcode":"4810",
    "sg:province":"Ober\u00f6sterreich",
    "wof:name":"Ley H. & CO",
    "wof:placetype":"venue"
},
  "geometry": {"coordinates":[13.8074064255,47.9154052734],"type":"Point"}
}