{
  "type": "Feature",
  "properties": {
    "addr:full":"Tschamlerstr 3 Innsbruck Tirol 6020",
    "addr:housenumber":"3",
    "addr:postcode":"6020",
    "addr:street":"Tschamlerstr;Tirol",
    "iso:country":"AT",
    "sg:address":"Tschamlerstr 3",
    "sg:city":"Innsbruck",
    "sg:orig_category":"Werbegrafik- U Grafik-Design",
    "sg:phone":"+43 512 563468",
    "sg:postcode":"6020",
    "sg:province":"Tirol",
    "wof:name":"Cunst & Co",
    "wof:placetype":"venue"
},
  "geometry": {"coordinates":[11.3960475922,47.2580528259],"type":"Point"}
}