{
  "type": "Feature",
  "properties": {
    "addr:full":"Sdlg Frieden 9 Kitzb\u00fchel Tirol 6370",
    "addr:housenumber":"9",
    "addr:postcode":"6370",
    "addr:street":"Sdlg Frieden;Tirol",
    "iso:country":"AT",
    "sg:address":"Sdlg Frieden 9",
    "sg:city":"Kitzb\u00fchel",
    "sg:classifiers":[
        {
            "category":"Taxi",
            "type":"Transportation"
        }
    ],
    "sg:phone":"+43 5356 63500",
    "sg:postcode":"6370",
    "sg:province":"Tirol",
    "sg:tags":[
        "personentransporte",
        "u"
    ],
    "wof:name":"Taxi Silver Star",
    "wof:placetype":"venue"
},
  "geometry": {"coordinates":[12.3846111298,47.4698104858],"type":"Point"}
}