{
  "type": "Feature",
  "properties": {
    "addr:full":"Biburger Str 2 Mauerkirchen Ober\u00f6sterreich 5270",
    "addr:housenumber":"2",
    "addr:postcode":"5270",
    "addr:street":"Str",
    "iso:country":"AT",
    "sg:address":"Biburger Str 2",
    "sg:city":"Mauerkirchen",
    "sg:orig_category":"Schmieden U Schmiedeeisenelemente",
    "sg:phone":"+43 4377 2428580",
    "sg:postcode":"5270",
    "sg:province":"Ober\u00f6sterreich",
    "wof:name":"Reiseder Johann",
    "wof:placetype":"venue"
},
  "geometry": {"coordinates":[13.130197525,48.1897239685],"type":"Point"}
}