{
  "type": "Feature",
  "properties": {
    "addr:full":"1. Strasse 43 Kematen an der Ybbs Nieder\u00f6sterreich 3331",
    "addr:housenumber":"43",
    "addr:postcode":"3331",
    "addr:street":"Strasse",
    "iso:country":"AT",
    "sg:address":"1. Strasse 43",
    "sg:city":"Kematen an der Ybbs",
    "sg:orig_category":"CarpenterS Work Supraregional",
    "sg:phone":"+43 7448 2341",
    "sg:postcode":"3331",
    "sg:province":"Nieder\u00f6sterreich",
    "sg:website":"hennigler.at",
    "wof:name":"Martin Hennigler",
    "wof:placetype":"venue"
},
  "geometry": {"coordinates":[14.7576198578,48.0224990845],"type":"Point"}
}