{
  "type": "Feature",
  "properties": {
    "iso:country":"AT",
    "sg:address":"St.-Veit-G 14",
    "sg:city":"Wien",
    "sg:orig_category":"Immobilienverwaltungen",
    "sg:phone":"+43 1 87731470",
    "sg:postcode":"1130",
    "sg:province":"Wien",
    "wof:name":"Realkanzlei Leissner KG",
    "wof:placetype":"venue"
},
  "geometry": {"coordinates":[16.2833194733,48.1841621399],"type":"Point"}
}