{
  "type": "Feature",
  "properties": {
    "addr:full":"Aguntstr 15 Lienz Tirol 9900",
    "addr:housenumber":"15",
    "addr:postcode":"9900",
    "addr:street":"Aguntstr;Tirol",
    "iso:country":"AT",
    "sg:address":"Aguntstr 15",
    "sg:city":"Lienz",
    "sg:orig_category":"Zimmereien",
    "sg:phone":"+43 4348 52628000",
    "sg:postcode":"9900",
    "sg:province":"Tirol",
    "wof:name":"Unterluggauer Holzbau GesmbH",
    "wof:placetype":"venue"
},
  "geometry": {"coordinates":[12.7910442352,46.8253517151],"type":"Point"}
}