{
  "type": "Feature",
  "properties": {
    "iso:country":"AT",
    "sg:address":"Seebach 5",
    "sg:city":"Ebene Reichenau",
    "sg:orig_category":"Pensionen / Privatzimmer",
    "sg:phone":"+43 4275 342",
    "sg:postcode":"9565",
    "sg:province":"K\u00e4rnten",
    "wof:name":"Thurner-Seebacher Anni",
    "wof:placetype":"venue"
},
  "geometry": {"coordinates":[13.8937129974,46.8534355164],"type":"Point"}
}