{
  "type": "Feature",
  "properties": {
    "addr:full":"Vogelweider Pl Wels Ober\u00f6sterreich 4600",
    "addr:postcode":"4600",
    "addr:street":"Vogelweider Pl",
    "iso:country":"AT",
    "sg:address":"Vogelweider Pl",
    "sg:city":"Wels",
    "sg:orig_category":"Fliesen U Platten",
    "sg:phone":"+43 4372 4247594",
    "sg:postcode":"4600",
    "sg:province":"Ober\u00f6sterreich",
    "wof:name":"Kratochwil Gerhard",
    "wof:placetype":"venue"
},
  "geometry": {"coordinates":[14.0125999451,48.1647796631],"type":"Point"}
}