{
  "type": "Feature",
  "properties": {
    "addr:full":"Thoneben 90 Semriach Steiermark 8102",
    "addr:housenumber":"90",
    "addr:postcode":"8102",
    "addr:street":"Thoneben",
    "iso:country":"AT",
    "sg:address":"Thoneben 90",
    "sg:city":"Semriach",
    "sg:orig_category":"Tischlereien",
    "sg:phone":"+43 3127 22670",
    "sg:postcode":"8102",
    "sg:province":"Steiermark",
    "wof:name":"Pabst Johann",
    "wof:placetype":"venue"
},
  "geometry": {"coordinates":[15.3640708923,47.1877784729],"type":"Point"}
}