{
  "type": "Feature",
  "properties": {
    "addr:full":"Nederg 4 G\u00f6tzens Tirol 6091",
    "addr:housenumber":"4",
    "addr:postcode":"6091",
    "addr:street":"Nederg;Tirol",
    "iso:country":"AT",
    "sg:address":"Nederg 4",
    "sg:city":"G\u00f6tzens",
    "sg:orig_category":"Zimmereien",
    "sg:phone":"+43 5234 32701",
    "sg:postcode":"6091",
    "sg:province":"Tirol",
    "wof:name":"Holzbau Haid GmbH",
    "wof:placetype":"venue"
},
  "geometry": {"coordinates":[11.3024396896,47.237247467],"type":"Point"}
}