{
  "type": "Feature",
  "properties": {
    "iso:country":"AT",
    "sg:address":"Nederg 4",
    "sg:city":"G\u00f6tzens",
    "sg:orig_category":"Zimmereien",
    "sg:phone":"+43 5234 32701",
    "sg:postcode":"6091",
    "sg:province":"Tirol",
    "wof:name":"Holzbau Haid GmbH",
    "wof:placetype":"venue"
},
  "geometry": {"coordinates":[11.3024396896,47.237247467],"type":"Point"}
}