{
  "type": "Feature",
  "properties": {
    "addr:full":"Nr 173 G\u00fcssing Burgenland 7540",
    "addr:postcode":"7540",
    "addr:street":"Nr 173 Guessing",
    "iso:country":"AT",
    "sg:address":"Nr 173",
    "sg:city":"G\u00fcssing",
    "sg:orig_category":"Folien",
    "sg:phone":"+43 3322 44677",
    "sg:postcode":"7540",
    "sg:province":"Burgenland",
    "wof:name":"Bickel Objektausstattung Folientechnik und Folienrollos",
    "wof:placetype":"venue"
},
  "geometry": {"coordinates":[16.3241195679,47.0592803955],"type":"Point"}
}