{
  "type": "Feature",
  "properties": {
    "iso:country":"AT",
    "sg:address":"Welser Str 60",
    "sg:city":"Leonding",
    "sg:classifiers":[
        {
            "category":"Travel",
            "subcategory":"Hotels & Motels",
            "type":"Entertainment"
        }
    ],
    "sg:phone":"+43 732 6712120",
    "sg:postcode":"4060",
    "sg:province":"Ober\u00f6sterreich",
    "wof:name":"Hotel Kremstalerhof Inh Karl Weixelbaumer",
    "wof:placetype":"venue"
},
  "geometry": {"coordinates":[14.260515213,48.2644424438],"type":"Point"}
}