{
  "type": "Feature",
  "properties": {
    "addr:full":"Obermitterdorf 62 Ruden K\u00e4rnten 9113",
    "addr:housenumber":"62",
    "addr:postcode":"9113",
    "addr:street":"Obermitterdorf;Kaernten",
    "iso:country":"AT",
    "sg:address":"Obermitterdorf 62",
    "sg:city":"Ruden",
    "sg:orig_category":"Parkettbodenverlegung",
    "sg:phone":"+43 4342 34493",
    "sg:postcode":"9113",
    "sg:province":"K\u00e4rnten",
    "wof:name":"Kaspar Theodor",
    "wof:placetype":"venue"
},
  "geometry": {"coordinates":[14.7653160095,46.656665802],"type":"Point"}
}