{
  "type": "Feature",
  "properties": {
    "iso:country":"AT",
    "sg:address":"Linzer Strasse 2",
    "sg:city":"Zwettl an der Rodl",
    "sg:classifiers":[
        {
            "category":"Community Center",
            "subcategory":"Senior",
            "type":"Public Place"
        }
    ],
    "sg:phone":"+43 7212 6536",
    "sg:postcode":"4180",
    "sg:province":"Ober\u00f6sterreich",
    "sg:tags":[
        "front",
        "wood",
        "door"
    ],
    "wof:name":"Josef Weixelbaumer",
    "wof:placetype":"venue"
},
  "geometry": {"coordinates":[14.2715816498,48.4648475647],"type":"Point"}
}