{
  "type": "Feature",
  "properties": {
    "addr:full":"Engerthstr. 86  Wien Wien 1200",
    "addr:housenumber":"86",
    "addr:postcode":"1200",
    "addr:street":"Engerthstr.",
    "iso:country":"AT",
    "sg:address":"Engerthstr. 86 ",
    "sg:city":"Wien",
    "sg:classifiers":[
        {
            "category":"Shopping",
            "subcategory":"Clothing, Apparel, & Fashions",
            "type":"Retail Goods"
        }
    ],
    "sg:phone":"+43 4313 303248",
    "sg:postcode":"1200",
    "sg:province":"Wien",
    "sg:tags":[
        "clothes"
    ],
    "wof:name":"WEITHOFER WARENHANDELS GMBH",
    "wof:placetype":"venue"
},
  "geometry": {"coordinates":[16.3844833374,48.2403297424],"type":"Point"}
}