{
  "type": "Feature",
  "properties": {
    "addr:full":"Franz-Xaver-Grimm-Strasse 3 Oberndorf Salzburg 5110",
    "addr:housenumber":"3",
    "addr:postcode":"5110",
    "addr:street":"Franz-Xaver-Grimm-Strasse",
    "iso:country":"AT",
    "sg:address":"Franz-Xaver-Grimm-Strasse 3",
    "sg:city":"Oberndorf",
    "sg:classifiers":[
        {
            "category":"Food & Beverages",
            "subcategory":"Meat & Fish",
            "type":"Retail Goods"
        }
    ],
    "sg:phone":"+43 6272 7530",
    "sg:postcode":"5110",
    "sg:province":"Salzburg",
    "wof:name":"Franz Ablinger & Co. Fleischhauereibetrieb Ges.m.b.H.",
    "wof:placetype":"venue"
},
  "geometry": {"coordinates":[12.9325675964,47.9608917236],"type":"Point"}
}