{
  "type": "Feature",
  "properties": {
    "iso:country":"AT",
    "sg:address":"Badstrasse 3",
    "sg:city":"Metnitz",
    "sg:classifiers":[
        {
            "category":"Manufacturing",
            "subcategory":"Wood Products",
            "type":"Manufacturing & Wholesale Goods"
        }
    ],
    "sg:phone":"+43 4267 229",
    "sg:postcode":"9363",
    "sg:province":"K\u00e4rnten",
    "sg:tags":[
        "gutter",
        "made"
    ],
    "sg:website":"geyer-rundsaege.at",
    "wof:name":"Thomas Geyer Rundschnitz - S\u00e4gewerk",
    "wof:placetype":"venue"
},
  "geometry": {"coordinates":[14.2071895599,46.9811096191],"type":"Point"}
}