{
  "type": "Feature",
  "properties": {
    "addr:full":"10.-Oktober-Strasse 4 Hermagor K\u00e4rnten 9620",
    "addr:housenumber":"4",
    "addr:postcode":"9620",
    "addr:street":"10.-Oktober-Strasse;Kaernten",
    "iso:country":"AT",
    "sg:address":"10.-Oktober-Strasse 4",
    "sg:city":"Hermagor",
    "sg:classifiers":[
        {
            "category":"Communications",
            "subcategory":"Television Station",
            "type":"Services"
        }
    ],
    "sg:phone":"+43 4282 2067",
    "sg:postcode":"9620",
    "sg:province":"K\u00e4rnten",
    "sg:tags":[
        "set",
        "radio",
        "cable",
        "antenna"
    ],
    "wof:name":"Elektro Schuller GesmbH",
    "wof:placetype":"venue"
},
  "geometry": {"coordinates":[13.3708848953,46.6267433167],"type":"Point"}
}