{
  "type": "Feature",
  "properties": {
    "addr:full":"Schlo\u00df Altenhof 1 Hofkirchen im M\u00fchlkreis Ober\u00f6sterreich 4142",
    "addr:housenumber":"1",
    "addr:postcode":"4142",
    "addr:street":"Altenhof;Im Muehlkreis Oberoesterreich",
    "iso:country":"AT",
    "sg:address":"Schlo\u00df Altenhof 1",
    "sg:city":"Hofkirchen im M\u00fchlkreis",
    "sg:orig_category":"Forstverwaltungen",
    "sg:phone":"+43 4372 85262",
    "sg:postcode":"4142",
    "sg:province":"Ober\u00f6sterreich",
    "wof:name":"Salburg Norbert",
    "wof:placetype":"venue"
},
  "geometry": {"coordinates":[13.7809877396,48.5044822693],"type":"Point"}
}