{
  "type": "Feature",
  "properties": {
    "addr:full":"Nr 102 Unternberg Salzburg 5585",
    "addr:postcode":"5585",
    "addr:street":"Nr;Unternberg",
    "iso:country":"AT",
    "sg:address":"Nr 102",
    "sg:city":"Unternberg",
    "sg:orig_category":"Tischlereien",
    "sg:phone":"+43 4364 7462020",
    "sg:postcode":"5585",
    "sg:province":"Salzburg",
    "wof:name":"Tischlerei Doppler - Inh Maria Sampl",
    "wof:placetype":"venue"
},
  "geometry": {"coordinates":[13.740694046,47.1129188538],"type":"Point"}
}