{
  "type": "Feature",
  "properties": {
    "addr:full":"Antoniusgasse 46 Wolkersdorf im Weinviertel Nieder\u00f6sterreich 2120",
    "addr:housenumber":"46",
    "addr:postcode":"2120",
    "addr:street":"Antoniusgasse",
    "iso:country":"AT",
    "sg:address":"Antoniusgasse 46",
    "sg:city":"Wolkersdorf im Weinviertel",
    "sg:classifiers":[
        {
            "category":"Manufacturing",
            "subcategory":"Wood Products",
            "type":"Manufacturing & Wholesale Goods"
        }
    ],
    "sg:phone":"+43 2245 5546",
    "sg:postcode":"2120",
    "sg:province":"Nieder\u00f6sterreich",
    "sg:tags":[
        "firework",
        "pyrotechnic",
        "except"
    ],
    "sg:website":"mks-online.at",
    "wof:name":"MKS Kotzian Manfred",
    "wof:placetype":"venue"
},
  "geometry": {"coordinates":[16.5191764832,48.3707618713],"type":"Point"}
}