{
  "type": "Feature",
  "properties": {
    "addr:full":"Rudolf Krenn-G 91 Studenzen Steiermark 8322",
    "addr:housenumber":"91",
    "addr:postcode":"8322",
    "iso:country":"AT",
    "sg:address":"Rudolf Krenn-G 91",
    "sg:city":"Studenzen",
    "sg:orig_category":"Steuerberatung",
    "sg:phone":"+43 3115 22380",
    "sg:postcode":"8322",
    "sg:province":"Steiermark",
    "wof:name":"Seidnitzer Herbert",
    "wof:placetype":"venue"
},
  "geometry": {"coordinates":[15.7906103134,47.0232505798],"type":"Point"}
}