{
  "type": "Feature",
  "properties": {
    "addr:full":"Milser Str 21 Hall in Tirol Tirol 6060",
    "addr:housenumber":"21",
    "addr:postcode":"6060",
    "addr:street":"Milser Str;Tirol",
    "iso:country":"AT",
    "sg:address":"Milser Str 21",
    "sg:city":"Hall in Tirol",
    "sg:orig_category":"Institute",
    "sg:phone":"+43 5223 573040",
    "sg:postcode":"6060",
    "sg:province":"Tirol",
    "wof:name":"Arbeitsmedizinisches Zentrum",
    "wof:placetype":"venue"
},
  "geometry": {"coordinates":[11.514128685,47.2827453613],"type":"Point"}
}