{
  "type": "Feature",
  "properties": {
    "addr:full":"Salzburger Str 189 Wels Ober\u00f6sterreich 4600",
    "addr:housenumber":"189",
    "addr:postcode":"4600",
    "addr:street":"Salzburger Str;Oberoesterreich",
    "iso:country":"AT",
    "sg:address":"Salzburger Str 189",
    "sg:city":"Wels",
    "sg:orig_category":"Autohandel",
    "sg:phone":"+43 4372 42211638",
    "sg:postcode":"4600",
    "sg:province":"Ober\u00f6sterreich",
    "wof:name":"Fox Car - Pfitzner OEG",
    "wof:placetype":"venue"
},
  "geometry": {"coordinates":[13.9866762161,48.1528587341],"type":"Point"}
}