{
  "type": "Feature",
  "properties": {
    "addr:full":"Ortsweg 2 Wernberg K\u00e4rnten 9241",
    "addr:housenumber":"2",
    "addr:postcode":"9241",
    "addr:street":"Ortsweg;Kaernten",
    "iso:country":"AT",
    "sg:address":"Ortsweg 2",
    "sg:city":"Wernberg",
    "sg:classifiers":[
        {
            "category":"Travel",
            "subcategory":"Hotels & Motels",
            "type":"Entertainment"
        }
    ],
    "sg:phone":"+43 4252 2397",
    "sg:postcode":"9241",
    "sg:province":"K\u00e4rnten",
    "wof:name":"Hotel Tiroler Haus",
    "wof:placetype":"venue"
},
  "geometry": {"coordinates":[13.9548063278,46.6222877502],"type":"Point"}
}