{
  "type": "Feature",
  "properties": {
    "iso:country":"AT",
    "sg:address":"Nr 70",
    "sg:city":"Weitra",
    "sg:classifiers":[
        {
            "category":"Home & Garden",
            "subcategory":"Building Materials",
            "type":"Retail Goods"
        }
    ],
    "sg:phone":"+43 4328 5624310",
    "sg:postcode":"3970",
    "sg:province":"Nieder\u00f6sterreich",
    "sg:tags":[
        "baustoffe",
        "-material",
        "u"
    ],
    "wof:name":"Seidl Franz & Sohn GesmbH",
    "wof:placetype":"venue"
},
  "geometry": {"coordinates":[14.7980480194,48.7091217041],"type":"Point"}
}