{
  "type": "Feature",
  "properties": {
    "addr:full":"Billrothstr 86 Wien Wien 1190",
    "addr:housenumber":"86",
    "addr:postcode":"1190",
    "addr:street":"Billrothstr",
    "iso:country":"AT",
    "sg:address":"Billrothstr 86",
    "sg:city":"Wien",
    "sg:orig_category":"Installationsunternehmen",
    "sg:phone":"+43 4313 676655",
    "sg:postcode":"1190",
    "sg:province":"Wien",
    "wof:name":"Lipkovich Robert GesmbH",
    "wof:placetype":"venue"
},
  "geometry": {"coordinates":[16.3448104858,48.2445449829],"type":"Point"}
}