{
  "type": "Feature",
  "properties": {
    "addr:full":"Birkenweg 6 Waldzell Ober\u00f6sterreich 4924",
    "addr:housenumber":"6",
    "addr:postcode":"4924",
    "addr:street":"Birkenweg",
    "iso:country":"AT",
    "sg:address":"Birkenweg 6",
    "sg:city":"Waldzell",
    "sg:orig_category":"Pensionen / Privatzimmer",
    "sg:phone":"+43 7754 3033",
    "sg:postcode":"4924",
    "sg:province":"Ober\u00f6sterreich",
    "wof:name":"Ferienhof Hofbauerngut Fam Wimplinger",
    "wof:placetype":"venue"
},
  "geometry": {"coordinates":[13.4354944229,48.1288108826],"type":"Point"}
}