{
  "type": "Feature",
  "properties": {
    "iso:country":"AT",
    "sg:address":"Ignaz Harrer-Str 79a",
    "sg:city":"Salzburg",
    "sg:orig_category":"Bankomat-Standorte",
    "sg:phone":"+43 662 4304550",
    "sg:postcode":"5020",
    "sg:province":"Salzburg",
    "wof:name":"Bankomat d Salzburger Landes-Hypothekenbank AG",
    "wof:placetype":"venue"
},
  "geometry": {"coordinates":[13.0218896866,47.8130912781],"type":"Point"}
}