{
  "type": "Feature",
  "properties": {
    "iso:country":"AT",
    "sg:address":"Antoniusstr 12",
    "sg:city":"Lauterach",
    "sg:orig_category":"Transportunternehmen",
    "sg:phone":"+43 5574 85746",
    "sg:postcode":"6923",
    "sg:province":"Vorarlberg",
    "wof:name":"Augustin Karl TransportgesmbH",
    "wof:placetype":"venue"
},
  "geometry": {"coordinates":[9.7347421646,47.4770011902],"type":"Point"}
}