{
  "type": "Feature",
  "properties": {
    "iso:country":"AT",
    "sg:address":"Wintergasse 52",
    "sg:city":"Purkersdorf",
    "sg:orig_category":"Plastic Building Blocks",
    "sg:phone":"+43 1 8771884",
    "sg:postcode":"3002",
    "sg:province":"Nieder\u00f6sterreich",
    "sg:website":"lego.com",
    "wof:name":"Lego Handelsges.m.b.H.",
    "wof:placetype":"venue"
},
  "geometry": {"coordinates":[16.1971549988,48.2076377869],"type":"Point"}
}