{
  "type": "Feature",
  "properties": {
    "iso:country":"AT",
    "sg:address":"Znaimer Str 26",
    "sg:city":"Retz",
    "sg:orig_category":"Lastkraftwagen",
    "sg:phone":"+43 676 6206966",
    "sg:postcode":"2070",
    "sg:province":"Nieder\u00f6sterreich",
    "wof:name":"Waglechner Ronald",
    "wof:placetype":"venue"
},
  "geometry": {"coordinates":[15.9533014297,48.7603187561],"type":"Point"}
}