{
  "type": "Feature",
  "properties": {
    "iso:country":"AT",
    "sg:address":"L\u00e4rchenwiese 33",
    "sg:city":"Maurach",
    "sg:orig_category":"Pensionen / Privatzimmer",
    "sg:phone":"+43 5243 5403",
    "sg:postcode":"6212",
    "sg:province":"Tirol",
    "wof:name":"Pension Kurth",
    "wof:placetype":"venue"
},
  "geometry": {"coordinates":[11.749461174,47.4206123352],"type":"Point"}
}