{
  "type": "Feature",
  "properties": {
    "addr:full":"Alleestr 27 Walchsee Tirol 6344",
    "addr:housenumber":"27",
    "addr:postcode":"6344",
    "addr:street":"Alleestr;Tirol",
    "iso:country":"AT",
    "sg:address":"Alleestr 27",
    "sg:city":"Walchsee",
    "sg:orig_category":"Pensionen / Privatzimmer",
    "sg:phone":"+43 5374 5601",
    "sg:postcode":"6344",
    "sg:province":"Tirol",
    "wof:name":"Pension Claudia",
    "wof:placetype":"venue"
},
  "geometry": {"coordinates":[12.3169164658,47.6534347534],"type":"Point"}
}