{
  "type": "Feature",
  "properties": {
    "iso:country":"AT",
    "sg:address":"Josef-Wilberger-Str 1",
    "sg:city":"Innsbruck",
    "sg:orig_category":"Automatisierungstechnik",
    "sg:phone":"+43 4351 2262261",
    "sg:postcode":"6020",
    "sg:province":"Tirol",
    "wof:name":"Metal Work Pneumatic GmbH",
    "wof:placetype":"venue"
},
  "geometry": {"coordinates":[11.4327764511,47.2771148682],"type":"Point"}
}