{
  "type": "Feature",
  "properties": {
    "addr:full":"Josef-Wilberger-Str 1 Innsbruck Tirol 6020",
    "addr:housenumber":"1",
    "addr:postcode":"6020",
    "addr:street":"Josef-Wilberger-Str;Tirol",
    "iso:country":"AT",
    "sg:address":"Josef-Wilberger-Str 1",
    "sg:city":"Innsbruck",
    "sg:orig_category":"Automatisierungstechnik",
    "sg:phone":"+43 4351 2262261",
    "sg:postcode":"6020",
    "sg:province":"Tirol",
    "wof:name":"Metal Work Pneumatic GmbH",
    "wof:placetype":"venue"
},
  "geometry": {"coordinates":[11.4327764511,47.2771148682],"type":"Point"}
}