{
  "type": "Feature",
  "properties": {
    "addr:full":"Getreideg 47 Salzburg Salzburg 5020",
    "addr:housenumber":"47",
    "addr:postcode":"5020",
    "addr:street":"Getreideg;Salzburg",
    "iso:country":"AT",
    "sg:address":"Getreideg 47",
    "sg:city":"Salzburg",
    "sg:orig_category":"Wechselstuben",
    "sg:phone":"+43 662 843175",
    "sg:postcode":"5020",
    "sg:province":"Salzburg",
    "wof:name":"Master Change",
    "wof:placetype":"venue"
},
  "geometry": {"coordinates":[13.040148735,47.7999267578],"type":"Point"}
}