{
  "type": "Feature",
  "properties": {
    "addr:full":"Kaplanstr 11 Wels Ober\u00f6sterreich 4600",
    "addr:housenumber":"11",
    "addr:postcode":"4600",
    "addr:street":"Kaplanstr;Oberoesterreich",
    "iso:country":"AT",
    "sg:address":"Kaplanstr 11",
    "sg:city":"Wels",
    "sg:orig_category":"Holzbearbeitungsmaschinen U -Werkzeuge",
    "sg:phone":"+43 4372 4242812",
    "sg:postcode":"4600",
    "sg:province":"Ober\u00f6sterreich",
    "wof:name":"SPERL WERKZEUGTECHNIK GmbH & Co KG",
    "wof:placetype":"venue"
},
  "geometry": {"coordinates":[14.0492668152,48.1613311768],"type":"Point"}
}