{
  "type": "Feature",
  "properties": {
    "iso:country":"AT",
    "sg:address":"Am Koglerhang 1",
    "sg:city":"Niederwaldkirchen",
    "sg:orig_category":"Handelsagenturen",
    "sg:phone":"+43 4372 3133111",
    "sg:postcode":"4174",
    "sg:province":"Ober\u00f6sterreich",
    "wof:name":"OMB - Bartenstein",
    "wof:placetype":"venue"
},
  "geometry": {"coordinates":[14.0874767303,48.4508399963],"type":"Point"}
}