{
  "type": "Feature",
  "properties": {
    "addr:full":"M\u00fcnchner Str 30 Schwaz Tirol 6130",
    "addr:postcode":"6130",
    "addr:street":"Str 30;Tirol",
    "iso:country":"AT",
    "sg:address":"M\u00fcnchner Str 30",
    "sg:city":"Schwaz",
    "sg:orig_category":"Beteiligungen U Finanzierungen",
    "sg:phone":"+43 5242 73355",
    "sg:postcode":"6130",
    "sg:province":"Tirol",
    "wof:name":"INFINA GesmbH - Gesch\u00e4ftsstelle Schwaz - Mag Harald Draxl",
    "wof:placetype":"venue"
},
  "geometry": {"coordinates":[11.7071990967,47.3454208374],"type":"Point"}
}