{
  "type": "Feature",
  "properties": {
    "addr:full":"Kutschkerg 20 Wien Wien 1180",
    "addr:housenumber":"20",
    "addr:postcode":"1180",
    "addr:street":"Kutschkerg",
    "iso:country":"AT",
    "sg:address":"Kutschkerg 20",
    "sg:city":"Wien",
    "sg:orig_category":"Lebensmittel / Einzelhandel",
    "sg:phone":"+43 1 4033578",
    "sg:postcode":"1180",
    "sg:province":"Wien",
    "wof:name":"SPAR \u00f6sterreichische Warenhandels-AG",
    "wof:placetype":"venue"
},
  "geometry": {"coordinates":[16.3443946838,48.2240562439],"type":"Point"}
}