{
  "type": "Feature",
  "properties": {
    "iso:country":"AT",
    "sg:address":"Hauffg 3-5/3. OG",
    "sg:city":"Wien",
    "sg:classifiers":[
        {
            "category":"Professional",
            "subcategory":"Computer Services",
            "type":"Services"
        }
    ],
    "sg:phone":"+43 1 74965730",
    "sg:postcode":"1110",
    "sg:province":"Wien",
    "sg:tags":[
        "software"
    ],
    "wof:name":"GBC Dipl-Ing Gerhard Blauensteiner Computerl\u00f6sungen GesmbH",
    "wof:placetype":"venue"
},
  "geometry": {"coordinates":[16.4197444916,48.1709709167],"type":"Point"}
}