{
  "type": "Feature",
  "properties": {
    "addr:full":"Solvaystr 3 Ebensee Ober\u00f6sterreich 4802",
    "addr:housenumber":"3",
    "addr:postcode":"4802",
    "addr:street":"Solvaystr",
    "iso:country":"AT",
    "sg:address":"Solvaystr 3",
    "sg:city":"Ebensee",
    "sg:orig_category":"Farben U Lacke / Erzeugung U Gro\u00c3\u0178handel",
    "sg:phone":"+43 6133 5355",
    "sg:postcode":"4802",
    "sg:province":"Ober\u00f6sterreich",
    "wof:name":"Peter Thalhammer - ADLER Farbenmeister",
    "wof:placetype":"venue"
},
  "geometry": {"coordinates":[13.7726745605,47.8078842163],"type":"Point"}
}