{
  "type": "Feature",
  "properties": {
    "addr:full":"Maria Theresien-Str 8 Innsbruck Tirol 6020",
    "addr:housenumber":"8",
    "addr:postcode":"6020",
    "addr:street":"Tirol",
    "iso:country":"AT",
    "sg:address":"Maria Theresien-Str 8",
    "sg:city":"Innsbruck",
    "sg:classifiers":[
        {
            "category":"Arts & Performance",
            "subcategory":"Theater",
            "type":"Entertainment"
        }
    ],
    "sg:phone":"+43 512 585902",
    "sg:postcode":"6020",
    "sg:province":"Tirol",
    "wof:name":"Tiroler Volksb\u00fchne Blaas",
    "wof:placetype":"venue"
},
  "geometry": {"coordinates":[11.3936395645,47.2667007446],"type":"Point"}
}