{
  "type": "Feature",
  "properties": {
    "addr:full":"Hauptstr 16 Sch\u00f6rfling am Attersee Ober\u00f6sterreich 4861",
    "addr:housenumber":"16",
    "addr:postcode":"4861",
    "addr:street":"Hauptstr;Am",
    "iso:country":"AT",
    "sg:address":"Hauptstr 16",
    "sg:city":"Sch\u00f6rfling am Attersee",
    "sg:orig_category":"Friseure U Frisiersalons",
    "sg:phone":"+43 4376 622522",
    "sg:postcode":"4861",
    "sg:province":"Ober\u00f6sterreich",
    "wof:name":"Friseur Christine L\u00f6schenberger",
    "wof:placetype":"venue"
},
  "geometry": {"coordinates":[13.5950222015,47.9471740723],"type":"Point"}
}