{
  "type": "Feature",
  "properties": {
    "addr:full":"Gleichenberger Str 79 Feldbach Steiermark 8330",
    "addr:postcode":"8330",
    "addr:street":"Str 79",
    "iso:country":"AT",
    "sg:address":"Gleichenberger Str 79",
    "sg:city":"Feldbach",
    "sg:orig_category":"Abfallentsorgung U -Verwertung",
    "sg:phone":"+43 3152 270379",
    "sg:postcode":"8330",
    "sg:province":"Steiermark",
    "wof:name":"Altstoffsammelzentrum Feldbach",
    "wof:placetype":"venue"
},
  "geometry": {"coordinates":[15.9106760025,46.9493560791],"type":"Point"}
}