{
  "type": "Feature",
  "properties": {
    "addr:full":"Haager Str. 50a Steyr Ober\u00f6sterreich 4400",
    "addr:housenumber":"50a",
    "addr:postcode":"4400",
    "addr:street":"Haager Str.;Oberoesterreich",
    "iso:country":"AT",
    "sg:address":"Haager Str. 50a",
    "sg:city":"Steyr",
    "sg:classifiers":[
        {
            "category":"Manufacturing",
            "subcategory":"Paper Products",
            "type":"Manufacturing & Wholesale Goods"
        }
    ],
    "sg:phone":"+43 4372 52777810",
    "sg:postcode":"4400",
    "sg:province":"Ober\u00f6sterreich",
    "sg:tags":[
        "cardboard"
    ],
    "wof:name":"E. HANZLOVSKY GESMBH",
    "wof:placetype":"venue"
},
  "geometry": {"coordinates":[14.4514007568,48.0582923889],"type":"Point"}
}