{
  "type": "Feature",
  "properties": {
    "addr:full":"Nr 191 St. Andr\u00e4 K\u00e4rnten 9433",
    "addr:postcode":"9433",
    "addr:street":"Nr 191",
    "iso:country":"AT",
    "sg:address":"Nr 191",
    "sg:city":"St. Andr\u00e4",
    "sg:orig_category":"Fleischhauereien",
    "sg:phone":"+43 4358 2425",
    "sg:postcode":"9433",
    "sg:province":"K\u00e4rnten",
    "wof:name":"Kehraus Josef",
    "wof:placetype":"venue"
},
  "geometry": {"coordinates":[14.821849823,46.7685317993],"type":"Point"}
}