{
  "type": "Feature",
  "properties": {
    "addr:full":"Kalsdorfer Str 11 Feldkirchen Steiermark 8073",
    "addr:postcode":"8073",
    "addr:street":"Str 11",
    "iso:country":"AT",
    "sg:address":"Kalsdorfer Str 11",
    "sg:city":"Feldkirchen",
    "sg:orig_category":"Transportunternehmen",
    "sg:phone":"+43 316 2924240",
    "sg:postcode":"8073",
    "sg:province":"Steiermark",
    "wof:name":"Maric Transport GesmbH",
    "wof:placetype":"venue"
},
  "geometry": {"coordinates":[15.4482526779,46.9939193726],"type":"Point"}
}