{
  "type": "Feature",
  "properties": {
    "iso:country":"AT",
    "sg:address":"Gewerbestr. 25 ",
    "sg:city":"Eugendorf",
    "sg:classifiers":[
        {
            "category":"Wholesale",
            "subcategory":"Drugs",
            "type":"Manufacturing & Wholesale Goods"
        }
    ],
    "sg:phone":"+43 4362 2571180",
    "sg:postcode":"5301",
    "sg:province":"Salzburg",
    "sg:tags":[
        "chemical",
        "pharmaceutical"
    ],
    "wof:name":"BASF COATINGS REFINISH GMBH",
    "wof:placetype":"venue"
},
  "geometry": {"coordinates":[13.1345024109,47.8585548401],"type":"Point"}
}