{
  "type": "Feature",
  "properties": {
    "addr:full":"Lokalbahnstr 8 Neunkirchen Nieder\u00f6sterreich 2620",
    "addr:housenumber":"8",
    "addr:postcode":"2620",
    "addr:street":"Lokalbahnstr",
    "iso:country":"AT",
    "sg:address":"Lokalbahnstr 8",
    "sg:city":"Neunkirchen",
    "sg:orig_category":"Autobusunternehmen",
    "sg:phone":"+43 4326 35650500",
    "sg:postcode":"2620",
    "sg:province":"Nieder\u00f6sterreich",
    "wof:name":"Nemec Tours GesmbH",
    "wof:placetype":"venue"
},
  "geometry": {"coordinates":[16.0817832947,47.7241706848],"type":"Point"}
}