{
  "type": "Feature",
  "properties": {
    "iso:country":"AT",
    "sg:address":"Thie\u00dfenbach 2",
    "sg:city":"Scharnstein",
    "sg:orig_category":"Immobilienmakler",
    "sg:phone":"+43 76157884",
    "sg:postcode":"4644",
    "sg:province":"Ober\u00f6sterreich",
    "wof:name":"Rotky Paul Christian",
    "wof:placetype":"venue"
},
  "geometry": {"coordinates":[13.962269783,47.9045448303],"type":"Point"}
}