{
  "type": "Feature",
  "properties": {
    "addr:full":"Flugh Wien Schwechat Wien Wien 1300",
    "iso:country":"AT",
    "sg:address":"Flugh Wien Schwechat",
    "sg:city":"Wien",
    "sg:orig_category":"Autovermietung",
    "sg:phone":"+43 1 700733316",
    "sg:postcode":"1300",
    "sg:province":"Wien",
    "wof:name":"DENZELDRIVE Carsharing GmbH - Wien-Flughafen Schwechat",
    "wof:placetype":"venue"
},
  "geometry": {"coordinates":[16.5561008453,48.1137504578],"type":"Point"}
}