{
  "type": "Feature",
  "properties": {
    "iso:country":"AT",
    "sg:address":"Quellenstr 119",
    "sg:city":"Wien",
    "sg:orig_category":"Kontaktlinsenoptiker, Optiker",
    "sg:phone":"+43 1 6041297",
    "sg:postcode":"1100",
    "sg:province":"Wien",
    "wof:name":"ADLER V OPTIK Johann Ochs KEG",
    "wof:placetype":"venue"
},
  "geometry": {"coordinates":[16.376789093,48.1752662659],"type":"Point"}
}