{
  "type": "Feature",
  "properties": {
    "iso:country":"AT",
    "sg:address":"Auerspergstr 37",
    "sg:city":"Salzburg",
    "sg:orig_category":"Bauunternehmen",
    "sg:phone":"+43 662 8435310",
    "sg:postcode":"5020",
    "sg:province":"Salzburg",
    "wof:name":"Kainz Bau GesmbH & Co KG",
    "wof:placetype":"venue"
},
  "geometry": {"coordinates":[13.0464677811,47.8080444336],"type":"Point"}
}