{
  "type": "Feature",
  "properties": {
    "iso:country":"AT",
    "sg:address":"Kremstalstr 102",
    "sg:city":"Traun",
    "sg:orig_category":"Tankstellen",
    "sg:phone":"+43 7229 73213",
    "sg:postcode":"4050",
    "sg:province":"Ober\u00f6sterreich",
    "wof:name":"IQ-Diskont Tankstelle",
    "wof:placetype":"venue"
},
  "geometry": {"coordinates":[14.2348403931,48.231803894],"type":"Point"}
}