{
  "type": "Feature",
  "properties": {
    "addr:full":"Nr 115 St. Leonhard im Pitztal Tirol 6481",
    "addr:postcode":"6481",
    "addr:street":"Nr 115;Tirol",
    "iso:country":"AT",
    "sg:address":"Nr 115",
    "sg:city":"St. Leonhard im Pitztal",
    "sg:orig_category":"Gemeinden",
    "sg:phone":"+43 4354 1387201",
    "sg:postcode":"6481",
    "sg:province":"Tirol",
    "wof:name":"Gemeindeamt St Leonhard im Pitztal",
    "wof:placetype":"venue"
},
  "geometry": {"coordinates":[10.8461503983,47.0666313171],"type":"Point"}
}