{
  "type": "Feature",
  "properties": {
    "addr:full":"Palterndorfer Str 203 Dobermannsdorf Nieder\u00f6sterreich 2181",
    "addr:housenumber":"203",
    "addr:postcode":"2181",
    "addr:street":"Dobermannsdorf Niederoesterreich",
    "iso:country":"AT",
    "sg:address":"Palterndorfer Str 203",
    "sg:city":"Dobermannsdorf",
    "sg:orig_category":"Tischlereien",
    "sg:phone":"+43 2533 89457",
    "sg:postcode":"2181",
    "sg:province":"Nieder\u00f6sterreich",
    "wof:name":"Schuster Rudolf",
    "wof:placetype":"venue"
},
  "geometry": {"coordinates":[16.8241558075,48.5959396362],"type":"Point"}
}