{
  "type": "Feature",
  "properties": {
    "addr:full":"St. Margarethen 152 Jenbach Tirol 6200",
    "addr:housenumber":"152",
    "addr:postcode":"6200",
    "addr:street":"St. Margarethen;Tirol",
    "iso:country":"AT",
    "sg:address":"St. Margarethen 152",
    "sg:city":"Jenbach",
    "sg:orig_category":"Autohandel",
    "sg:phone":"+43 5244 624340",
    "sg:postcode":"6200",
    "sg:province":"Tirol",
    "wof:name":"Auto Linser GesmbH & Co KG",
    "wof:placetype":"venue"
},
  "geometry": {"coordinates":[11.7708826065,47.3827819824],"type":"Point"}
}