{
  "type": "Feature",
  "properties": {
    "iso:country":"AT",
    "sg:address":"Wimmersdorf 34",
    "sg:city":"Asperhofen",
    "sg:classifiers":[
        {
            "category":"Home & Garden",
            "subcategory":"Building Materials",
            "type":"Retail Goods"
        }
    ],
    "sg:phone":"+43 2772 58214",
    "sg:postcode":"3041",
    "sg:province":"Nieder\u00f6sterreich",
    "sg:tags":[
        "gravel",
        "crushed"
    ],
    "sg:website":"gnant.at",
    "wof:name":"Gnant Ges.m.b.H.",
    "wof:placetype":"venue"
},
  "geometry": {"coordinates":[15.9243936539,48.2437896729],"type":"Point"}
}