{
  "type": "Feature",
  "properties": {
    "iso:country":"AT",
    "sg:address":"Kaplanstr. 7",
    "sg:city":"Tulln an der Donau",
    "sg:classifiers":[
        {
            "category":"Manufacturing",
            "subcategory":"Tools & Machinery",
            "type":"Manufacturing & Wholesale Goods"
        }
    ],
    "sg:phone":"+43 4322 7263805",
    "sg:postcode":"3430",
    "sg:province":"Nieder\u00f6sterreich",
    "sg:tags":[
        "environment",
        "equipment",
        "-"
    ],
    "wof:name":"AWATEC ABWASSER TECHNIK GMBH",
    "wof:placetype":"venue"
},
  "geometry": {"coordinates":[16.07746315,48.3269958496],"type":"Point"}
}