{
  "type": "Feature",
  "properties": {
    "addr:full":"Rilkestr 20 Linz Ober\u00f6sterreich 4020",
    "addr:housenumber":"20",
    "addr:postcode":"4020",
    "addr:street":"Rilkestr",
    "iso:country":"AT",
    "sg:address":"Rilkestr 20",
    "sg:city":"Linz",
    "sg:orig_category":"Ingenieurkonsulenten / Zivilingenieure",
    "sg:phone":"+43 732 6515700",
    "sg:postcode":"4020",
    "sg:province":"Ober\u00f6sterreich",
    "wof:name":"Kurz Gerhard Dipl-Ing",
    "wof:placetype":"venue"
},
  "geometry": {"coordinates":[14.3016691208,48.2914619446],"type":"Point"}
}