{
  "type": "Feature",
  "properties": {
    "addr:full":"Batloggstr 36 Schruns Vorarlberg 6780",
    "addr:housenumber":"36",
    "addr:postcode":"6780",
    "addr:street":"Batloggstr",
    "iso:country":"AT",
    "sg:address":"Batloggstr 36",
    "sg:city":"Schruns",
    "sg:orig_category":"Ingenieurkonsulenten / Zivilingenieure",
    "sg:phone":"+43 5556 77844",
    "sg:postcode":"6780",
    "sg:province":"Vorarlberg",
    "wof:name":"VIGL CONSULT - Dipl-Ing Dr techn Alois Vigl",
    "wof:placetype":"venue"
},
  "geometry": {"coordinates":[9.9116353989,47.0791130066],"type":"Point"}
}