{
  "type": "Feature",
  "properties": {
    "iso:country":"AT",
    "sg:address":"Mariahilfer Str 156",
    "sg:city":"Wien",
    "sg:classifiers":[
        {
            "category":"Restaurant",
            "type":"Food & Drink"
        }
    ],
    "sg:phone":"+43 1 8923306",
    "sg:postcode":"1150",
    "sg:province":"Wien",
    "wof:name":"Wienerwald Restaurants GesmbH",
    "wof:placetype":"venue"
},
  "geometry": {"coordinates":[16.3339271545,48.1935272217],"type":"Point"}
}