{
  "type": "Feature",
  "properties": {
    "addr:full":"Ried 117 Gerlos Tirol 6281",
    "addr:housenumber":"117",
    "addr:postcode":"6281",
    "addr:street":"Ried;Gerlos Tirol",
    "iso:country":"AT",
    "sg:address":"Ried 117",
    "sg:city":"Gerlos",
    "sg:orig_category":"Pensionen / Privatzimmer",
    "sg:phone":"+43 5284 5311",
    "sg:postcode":"6281",
    "sg:province":"Tirol",
    "wof:name":"Ferienhof Gratzer",
    "wof:placetype":"venue"
},
  "geometry": {"coordinates":[12.0294218063,47.2245788574],"type":"Point"}
}