{
  "type": "Feature",
  "properties": {
    "addr:full":"Top 32 Oberpullendorf Burgenland 7350",
    "addr:postcode":"7350",
    "iso:country":"AT",
    "sg:address":"Top 32",
    "sg:city":"Oberpullendorf",
    "sg:orig_category":"Diskotheken",
    "sg:phone":"+43 2612 45694",
    "sg:postcode":"7350",
    "sg:province":"Burgenland",
    "wof:name":"Disco Marquee",
    "wof:placetype":"venue"
},
  "geometry": {"coordinates":[16.513759613,47.4956016541],"type":"Point"}
}