{
  "type": "Feature",
  "properties": {
    "addr:full":"Stattersdorf Hptstr 154 St. P\u00f6lten Nieder\u00f6sterreich 3100",
    "addr:housenumber":"154",
    "addr:postcode":"3100",
    "addr:street":"St. Poelten",
    "iso:country":"AT",
    "sg:address":"Stattersdorf Hptstr 154",
    "sg:city":"St. P\u00f6lten",
    "sg:orig_category":"Hunde- U Katzensalons",
    "sg:phone":"+43 2742 255980",
    "sg:postcode":"3100",
    "sg:province":"Nieder\u00f6sterreich",
    "wof:name":"Margit's Hundetrimm- und Schursalon",
    "wof:placetype":"venue"
},
  "geometry": {"coordinates":[15.6435899734,48.1820907593],"type":"Point"}
}