{
  "type": "Feature",
  "properties": {
    "addr:full":"Werner v Siemens-Str 2 Neutal Burgenland 7343",
    "addr:housenumber":"2",
    "addr:postcode":"7343",
    "addr:street":"Siemens-Str",
    "iso:country":"AT",
    "sg:address":"Werner v Siemens-Str 2",
    "sg:city":"Neutal",
    "sg:orig_category":"Decken- U Wandverkleidungen",
    "sg:phone":"+43 2618 27171",
    "sg:postcode":"7343",
    "sg:province":"Burgenland",
    "wof:name":"M.C.I. Metalldecken Produktions GmbH",
    "wof:placetype":"venue"
},
  "geometry": {"coordinates":[16.4449558258,47.5461082458],"type":"Point"}
}