{
  "type": "Feature",
  "properties": {
    "addr:full":"Hauptstr 25 St. Michael in Obersteiermark Steiermark 8770",
    "addr:housenumber":"25",
    "addr:postcode":"8770",
    "addr:street":"Hauptstr",
    "iso:country":"AT",
    "sg:address":"Hauptstr 25",
    "sg:city":"St. Michael in Obersteiermark",
    "sg:orig_category":"Gemeinden",
    "sg:phone":"+43 4338 4322440",
    "sg:postcode":"8770",
    "sg:province":"Steiermark",
    "wof:name":"Marktgemeinde St Michael in Obersteiermark",
    "wof:placetype":"venue"
},
  "geometry": {"coordinates":[15.014837265,47.3406715393],"type":"Point"}
}