{
  "type": "Feature",
  "properties": {
    "addr:full":"Oberer Stadtpl 33 Waidhofen an der Ybbs Nieder\u00f6sterreich 3340",
    "addr:housenumber":"33",
    "addr:postcode":"3340",
    "addr:street":"Oberer Stadtpl",
    "iso:country":"AT",
    "sg:address":"Oberer Stadtpl 33",
    "sg:city":"Waidhofen an der Ybbs",
    "sg:orig_category":"Bandagen U Bandagisten",
    "sg:phone":"+43 4374 42540230",
    "sg:postcode":"3340",
    "sg:province":"Nieder\u00f6sterreich",
    "wof:name":"M\u00fcller Florian",
    "wof:placetype":"venue"
},
  "geometry": {"coordinates":[14.774023056,47.9617271423],"type":"Point"}
}