{
  "type": "Feature",
  "properties": {
    "addr:full":"Nr 34 St. Pantaleon Ober\u00f6sterreich 5120",
    "addr:postcode":"5120",
    "addr:street":"Nr 34;Pantaleon Oberoesterreich",
    "iso:country":"AT",
    "sg:address":"Nr 34",
    "sg:city":"St. Pantaleon",
    "sg:orig_category":"Fleischhauereien",
    "sg:phone":"+43 4362 776401",
    "sg:postcode":"5120",
    "sg:province":"Ober\u00f6sterreich",
    "wof:name":"Veichtlbauer GesmbH",
    "wof:placetype":"venue"
},
  "geometry": {"coordinates":[12.8832397461,48.045375824],"type":"Point"}
}