{
  "type": "Feature",
  "properties": {
    "addr:full":"Salesianerg 10 Wien Wien 1030",
    "addr:housenumber":"10",
    "addr:postcode":"1030",
    "addr:street":"Salesianerg",
    "iso:country":"AT",
    "sg:address":"Salesianerg 10",
    "sg:city":"Wien",
    "sg:classifiers":[
        {
            "category":"Restaurant",
            "type":"Food & Drink"
        }
    ],
    "sg:phone":"+43 1 7142163",
    "sg:postcode":"1030",
    "sg:province":"Wien",
    "sg:tags":[
        "pizzeria"
    ],
    "wof:name":"Pizzeria Santa Lucia",
    "wof:placetype":"venue"
},
  "geometry": {"coordinates":[16.3808174133,48.1988143921],"type":"Point"}
}