{
  "type": "Feature",
  "properties": {
    "iso:country":"AT",
    "sg:address":"Joanneumring 18",
    "sg:city":"Graz",
    "sg:classifiers":[
        {
            "category":"Professional",
            "type":"Services"
        }
    ],
    "sg:phone":"+43 316 8051492",
    "sg:postcode":"8010",
    "sg:province":"Steiermark",
    "sg:tags":[
        "leasing"
    ],
    "wof:name":"HYPO Steiermark Kommunal- und Geb\u00e4udeleasing GmbH",
    "wof:placetype":"venue"
},
  "geometry": {"coordinates":[15.4389295578,47.066822052],"type":"Point"}
}