{
  "type": "Feature",
  "properties": {
    "addr:full":"Schaumannstr 34 Korneuburg Nieder\u00f6sterreich 2100",
    "addr:housenumber":"34",
    "addr:postcode":"2100",
    "addr:street":"Schaumannstr;Niederoesterreich",
    "iso:country":"AT",
    "sg:address":"Schaumannstr 34",
    "sg:city":"Korneuburg",
    "sg:orig_category":"Installationsunternehmen",
    "sg:phone":"+43 2262 756580",
    "sg:postcode":"2100",
    "sg:province":"Nieder\u00f6sterreich",
    "wof:name":"Kerschbaum Heinrich Ing GesmbH",
    "wof:placetype":"venue"
},
  "geometry": {"coordinates":[16.3330612183,48.3423194885],"type":"Point"}
}