{
  "type": "Feature",
  "properties": {
    "addr:full":"Br\u00fcnner Str 89 Gerasdorf Nieder\u00f6sterreich 2201",
    "addr:postcode":"2201",
    "addr:street":"Str 89",
    "iso:country":"AT",
    "sg:address":"Br\u00fcnner Str 89",
    "sg:city":"Gerasdorf",
    "sg:orig_category":"Autoersatzteile",
    "sg:phone":"+43 2246 27477",
    "sg:postcode":"2201",
    "sg:province":"Nieder\u00f6sterreich",
    "sg:website":"mh-autoteile.at",
    "wof:name":"MH Autoersatzteile Manfred Herrmann",
    "wof:placetype":"venue"
},
  "geometry": {"coordinates":[16.4708862305,48.2990150452],"type":"Point"}
}