{
  "type": "Feature",
  "properties": {
    "iso:country":"AT",
    "sg:address":"Eferdinger Str 25",
    "sg:city":"Wels",
    "sg:orig_category":"Papier- U Schreibwaren / Einzelhandel",
    "sg:phone":"+43 7242 46104",
    "sg:postcode":"4600",
    "sg:province":"Ober\u00f6sterreich",
    "wof:name":"Top Shop - B\u00fcro Schule Geschenke",
    "wof:placetype":"venue"
},
  "geometry": {"coordinates":[14.025478363,48.1709060669],"type":"Point"}
}