{
  "type": "Feature",
  "properties": {
    "addr:full":"Ketzergasse 101 Wien Wien 1230",
    "addr:housenumber":"101",
    "addr:postcode":"1230",
    "addr:street":"Ketzergasse",
    "iso:country":"AT",
    "sg:address":"Ketzergasse 101",
    "sg:city":"Wien",
    "sg:classifiers":[
        {
            "category":"Banks & Credit Unions",
            "subcategory":"Investment Brokerage",
            "type":"Services"
        }
    ],
    "sg:phone":"+43 1 8692462",
    "sg:postcode":"1230",
    "sg:province":"Wien",
    "sg:tags":[
        "case",
        "spectacle"
    ],
    "wof:name":"Helmut Hann",
    "wof:placetype":"venue"
},
  "geometry": {"coordinates":[16.3070316315,48.127696991],"type":"Point"}
}