{
  "type": "Feature",
  "properties": {
    "addr:full":"Inglitschstrasse 4 Klagenfurt K\u00e4rnten 9020",
    "addr:housenumber":"4",
    "addr:postcode":"9020",
    "addr:street":"Inglitschstrasse;Kaernten",
    "iso:country":"AT",
    "sg:address":"Inglitschstrasse 4",
    "sg:city":"Klagenfurt",
    "sg:classifiers":[
        {
            "category":"Home & Garden",
            "subcategory":"Furniture",
            "type":"Retail Goods"
        }
    ],
    "sg:phone":"+43 463 354550",
    "sg:postcode":"9020",
    "sg:province":"K\u00e4rnten",
    "sg:tags":[
        "baker",
        "work-benches"
    ],
    "wof:name":"Otto Mandl Ges.m.b.H.",
    "wof:placetype":"venue"
},
  "geometry": {"coordinates":[14.3430099487,46.6242370605],"type":"Point"}
}