{
  "type": "Feature",
  "properties": {
    "iso:country":"AT",
    "sg:address":"Prangerg 6-8",
    "sg:city":"St. Margarethen im Burgenland",
    "sg:orig_category":"Banken U Sparkassen",
    "sg:phone":"+43 4326 8022460",
    "sg:postcode":"7062",
    "sg:province":"Burgenland",
    "wof:name":"Raiffeisenbank St.Margarethen-Trausdorf-Oslip regGenmbH",
    "wof:placetype":"venue"
},
  "geometry": {"coordinates":[16.6067409515,47.8052177429],"type":"Point"}
}