{
  "type": "Feature",
  "properties": {
    "iso:country":"AT",
    "sg:address":"Saturnweg 3",
    "sg:city":"Haid",
    "sg:orig_category":"Non-Classified Establishments",
    "sg:phone":"+43 4366 43563884",
    "sg:postcode":"4053",
    "sg:province":"Ober\u00f6sterreich",
    "wof:name":"Schatzdorfer Willibald",
    "wof:placetype":"venue"
},
  "geometry": {"coordinates":[14.2510099411,48.2047348022],"type":"Point"}
}