{
  "type": "Feature",
  "properties": {
    "addr:full":"Silvrettastr 178 See Tirol 6553",
    "addr:housenumber":"178",
    "addr:postcode":"6553",
    "addr:street":"See Tirol",
    "iso:country":"AT",
    "sg:address":"Silvrettastr 178",
    "sg:city":"See",
    "sg:orig_category":"Bergbahnen",
    "sg:phone":"+43 5441 82880",
    "sg:postcode":"6553",
    "sg:province":"Tirol",
    "sg:website":"bergbahn.com",
    "wof:name":"Bergbahnen See GesmbH",
    "wof:placetype":"venue"
},
  "geometry": {"coordinates":[10.4631299973,47.0825309753],"type":"Point"}
}