{
  "type": "Feature",
  "properties": {
    "iso:country":"AT",
    "sg:address":"Auffach 282",
    "sg:city":"Wildsch\u00f6nau-Auffach",
    "sg:orig_category":"Ingenieurkonsulenten / Zivilingenieure",
    "sg:phone":"+43 5339 2769",
    "sg:postcode":"6313",
    "sg:province":"Tirol",
    "wof:name":"B\u00fcro f Wildtier\u00f6kologie regionale Landnutzung und Umweltplanung",
    "wof:placetype":"venue"
},
  "geometry": {"coordinates":[12.0360631943,47.4098701477],"type":"Point"}
}