{
  "type": "Feature",
  "properties": {
    "iso:country":"AT",
    "sg:address":"Hofnerstrasse 42b",
    "sg:city":"G\u00f6fis",
    "sg:classifiers":[
        {
            "category":"Building & Trades",
            "subcategory":"Equipment Rental",
            "type":"Services"
        }
    ],
    "sg:phone":"+43 5522 32918",
    "sg:postcode":"6811",
    "sg:province":"Vorarlberg",
    "sg:tags":[
        "adhesive",
        "industry",
        "sealant"
    ],
    "sg:website":"bgts.at",
    "wof:name":"BGTS Industrie- und Baubedarf",
    "wof:placetype":"venue"
},
  "geometry": {"coordinates":[-90.20757293699999,36.779548645],"type":"Point"}
}