{
  "type": "Feature",
  "properties": {
    "addr:full":"Kudlichweg 21 Stra\u00dfgang Steiermark 8054",
    "addr:housenumber":"21",
    "addr:postcode":"8054",
    "addr:street":"Kudlichweg",
    "iso:country":"AT",
    "sg:address":"Kudlichweg 21",
    "sg:city":"Stra\u00dfgang",
    "sg:orig_category":"Antriebstechnik",
    "sg:phone":"+43 316 2870820",
    "sg:postcode":"8054",
    "sg:province":"Steiermark",
    "wof:name":"Ulmer GmbH",
    "wof:placetype":"venue"
},
  "geometry": {"coordinates":[15.4081602097,47.0214004517],"type":"Point"}
}