{
  "type": "Feature",
  "properties": {
    "addr:full":"Werdenbergerstr 40a Bludenz Vorarlberg 6700",
    "addr:housenumber":"40a",
    "addr:postcode":"6700",
    "addr:street":"Werdenbergerstr",
    "iso:country":"AT",
    "sg:address":"Werdenbergerstr 40a",
    "sg:city":"Bludenz",
    "sg:orig_category":"Behinderungen / Leben Mit Behinderungen",
    "sg:phone":"+43 5552 68117",
    "sg:postcode":"6700",
    "sg:province":"Vorarlberg",
    "wof:name":"Beratungsstelle f\u00fcr H\u00f6rgesch\u00e4digte",
    "wof:placetype":"venue"
},
  "geometry": {"coordinates":[9.8177337646,47.1569290161],"type":"Point"}
}