{
  "type": "Feature",
  "properties": {
    "addr:full":"Achenpromenade 8 Kitzb\u00fchel Tirol 6370",
    "addr:housenumber":"8",
    "addr:postcode":"6370",
    "addr:street":"Achenpromenade;Tirol",
    "iso:country":"AT",
    "sg:address":"Achenpromenade 8",
    "sg:city":"Kitzb\u00fchel",
    "sg:orig_category":"Versicherungsunternehmen",
    "sg:phone":"+43 676 884001185",
    "sg:postcode":"6370",
    "sg:province":"Tirol",
    "wof:name":"Emberger Christoph - Regionalgesch\u00e4ftsstelle f\u00fcr die Deutsche Verm\u00f6gensberatung",
    "wof:placetype":"venue"
},
  "geometry": {"coordinates":[12.3975019455,47.4455909729],"type":"Point"}
}