{
  "type": "Feature",
  "properties": {
    "addr:full":"Hauptstr 40 Hermagor K\u00e4rnten 9620",
    "addr:housenumber":"40",
    "addr:postcode":"9620",
    "addr:street":"Hauptstr;Kaernten",
    "iso:country":"AT",
    "sg:address":"Hauptstr 40",
    "sg:city":"Hermagor",
    "sg:classifiers":[
        {
            "category":"Taxi",
            "type":"Transportation"
        }
    ],
    "sg:phone":"+43 4342 823066",
    "sg:postcode":"9620",
    "sg:province":"K\u00e4rnten",
    "sg:tags":[
        "personentransporte",
        "u"
    ],
    "wof:name":"Gratzer Taxi KEG",
    "wof:placetype":"venue"
},
  "geometry": {"coordinates":[13.3650894165,46.6276550293],"type":"Point"}
}