{
  "type": "Feature",
  "properties": {
    "iso:country":"AT",
    "sg:address":"Niederland 158",
    "sg:city":"Unken",
    "sg:orig_category":"Tourismusinformation U -Organisationen",
    "sg:phone":"+43 4365 894245",
    "sg:postcode":"5091",
    "sg:province":"Salzburg",
    "wof:name":"Tourismusverband Salzburger Saalachtal",
    "wof:placetype":"venue"
},
  "geometry": {"coordinates":[12.7301282883,47.6490058899],"type":"Point"}
}