{
  "type": "Feature",
  "properties": {
    "addr:full":"Lerchenfelder Str 29 Wien Wien 1070",
    "addr:housenumber":"29",
    "addr:postcode":"1070",
    "addr:street":"Lerchenfelder Str",
    "iso:country":"AT",
    "sg:address":"Lerchenfelder Str 29",
    "sg:city":"Wien",
    "sg:orig_category":"Apotheken",
    "sg:phone":"+43 1 5238179",
    "sg:postcode":"1070",
    "sg:province":"Wien",
    "wof:name":"Walfisch-Apotheke Mag pharm Gerhard Ellinger OHG",
    "wof:placetype":"venue"
},
  "geometry": {"coordinates":[16.3511657715,48.2061805725],"type":"Point"}
}