{
  "type": "Feature",
  "properties": {
    "addr:full":"Paracelsusg 37 Gablitz Nieder\u00f6sterreich 3003",
    "addr:housenumber":"37",
    "addr:postcode":"3003",
    "addr:street":"Paracelsusg",
    "iso:country":"AT",
    "sg:address":"Paracelsusg 37",
    "sg:city":"Gablitz",
    "sg:orig_category":"Architekten",
    "sg:phone":"+43 2231 67506",
    "sg:postcode":"3003",
    "sg:province":"Nieder\u00f6sterreich",
    "sg:website":"arch-jc.com",
    "wof:name":"Cichocki J\u00f6rg Arch Dipl-Ing",
    "wof:placetype":"venue"
},
  "geometry": {"coordinates":[16.148431778,48.2353858948],"type":"Point"}
}