{
  "type": "Feature",
  "properties": {
    "iso:country":"AT",
    "sg:address":"R\u00f6cklbrunnstr 2-4",
    "sg:city":"Salzburg",
    "sg:orig_category":"Lebensmittel / Einzelhandel",
    "sg:phone":"+43 662 870827",
    "sg:postcode":"5020",
    "sg:province":"Salzburg",
    "wof:name":"Zielpunkt Warenhandel GmbH & Co KG",
    "wof:placetype":"venue"
},
  "geometry": {"coordinates":[13.0650177002,47.8106269836],"type":"Point"}
}