{
  "type": "Feature",
  "properties": {
    "addr:full":"Emberg 38 Aschau Tirol 6274",
    "addr:housenumber":"38",
    "addr:postcode":"6274",
    "addr:street":"Emberg;Aschau Tirol",
    "iso:country":"AT",
    "sg:address":"Emberg 38",
    "sg:city":"Aschau",
    "sg:orig_category":"Appartements / Ferienwohnungen",
    "sg:phone":"+43 5283 3553",
    "sg:postcode":"6274",
    "sg:province":"Tirol",
    "wof:name":"Ferienhof Proscher",
    "wof:placetype":"venue"
},
  "geometry": {"coordinates":[11.8821372986,47.2790641785],"type":"Point"}
}