{
  "type": "Feature",
  "properties": {
    "iso:country":"AT",
    "sg:address":"Antonsg 2",
    "sg:city":"Baden",
    "sg:orig_category":"Drogerien",
    "sg:phone":"+43 2252 88397",
    "sg:postcode":"2500",
    "sg:province":"Nieder\u00f6sterreich",
    "wof:name":"Ramberger Erich",
    "wof:placetype":"venue"
},
  "geometry": {"coordinates":[16.237197876,48.0093193054],"type":"Point"}
}