{
  "type": "Feature",
  "properties": {
    "addr:full":"Veltlinerstr 4 Guntramsdorf Nieder\u00f6sterreich 2353",
    "addr:housenumber":"4",
    "addr:postcode":"2353",
    "addr:street":"Veltlinerstr",
    "iso:country":"AT",
    "sg:address":"Veltlinerstr 4",
    "sg:city":"Guntramsdorf",
    "sg:classifiers":[
        {
            "category":"Professional",
            "subcategory":"Computer Services",
            "type":"Services"
        }
    ],
    "sg:phone":"+43 2236 506240",
    "sg:postcode":"2353",
    "sg:province":"Nieder\u00f6sterreich",
    "sg:tags":[
        "software"
    ],
    "wof:name":"Stampfl & Co KEG",
    "wof:placetype":"venue"
},
  "geometry": {"coordinates":[16.3178043365,48.0596961975],"type":"Point"}
}