{
  "type": "Feature",
  "properties": {
    "addr:full":"Wiener Str 12 Enns Ober\u00f6sterreich 4470",
    "addr:postcode":"4470",
    "addr:street":"12",
    "iso:country":"AT",
    "sg:address":"Wiener Str 12",
    "sg:city":"Enns",
    "sg:orig_category":"Videotheken",
    "sg:phone":"+43 7223 85013",
    "sg:postcode":"4470",
    "sg:province":"Ober\u00f6sterreich",
    "wof:name":"Video Kistl",
    "wof:placetype":"venue"
},
  "geometry": {"coordinates":[14.4789428711,48.2123832703],"type":"Point"}
}