{
  "type": "Feature",
  "properties": {
    "addr:full":"Schie\u00dfstandg 32 St. Johann in Tirol Tirol 6380",
    "addr:housenumber":"32",
    "addr:postcode":"johann;6380",
    "addr:street":"Schiessstandg;Tirol",
    "iso:country":"AT",
    "sg:address":"Schie\u00dfstandg 32",
    "sg:city":"St. Johann in Tirol",
    "sg:orig_category":"Massagen",
    "sg:phone":"+43 5352 64657",
    "sg:postcode":"6380",
    "sg:province":"Tirol",
    "wof:name":"Schmidel Monika - Massagestudio",
    "wof:placetype":"venue"
},
  "geometry": {"coordinates":[12.4248065948,47.5192298889],"type":"Point"}
}