{
  "type": "Feature",
  "properties": {
    "iso:country":"AT",
    "sg:address":"Schie\u00dfstandg 32",
    "sg:city":"St. Johann in Tirol",
    "sg:orig_category":"Massagen",
    "sg:phone":"+43 5352 64657",
    "sg:postcode":"6380",
    "sg:province":"Tirol",
    "wof:name":"Schmidel Monika - Massagestudio",
    "wof:placetype":"venue"
},
  "geometry": {"coordinates":[12.4248065948,47.5192298889],"type":"Point"}
}