{
  "type": "Feature",
  "properties": {
    "addr:full":"Cumberlandstr 64 Gmunden Ober\u00f6sterreich 4810",
    "addr:housenumber":"64",
    "addr:postcode":"4810",
    "addr:street":"Cumberlandstr;Oberoesterreich",
    "iso:country":"AT",
    "sg:address":"Cumberlandstr 64",
    "sg:city":"Gmunden",
    "sg:orig_category":"Steuerungstechnik",
    "sg:phone":"+43 761272650",
    "sg:postcode":"4810",
    "sg:province":"Ober\u00f6sterreich",
    "wof:name":"SUN-Electronics GesmbH",
    "wof:placetype":"venue"
},
  "geometry": {"coordinates":[13.8087120056,47.9291191101],"type":"Point"}
}