{
  "type": "Feature",
  "properties": {
    "addr:full":"Heilbadstr 104 Seefeld in Tirol Tirol 6100",
    "addr:housenumber":"104",
    "addr:postcode":"6100",
    "addr:street":"Seefeld;Tirol",
    "iso:country":"AT",
    "sg:address":"Heilbadstr 104",
    "sg:city":"Seefeld in Tirol",
    "sg:classifiers":[
        {
            "category":"Travel",
            "subcategory":"Hotels & Motels",
            "type":"Entertainment"
        }
    ],
    "sg:phone":"+43 5212 26710",
    "sg:postcode":"6100",
    "sg:province":"Tirol",
    "wof:name":"Sport-Kur-Aktivzentrum Hotel Schneeweiss",
    "wof:placetype":"venue"
},
  "geometry": {"coordinates":[11.1953315735,47.3378143311],"type":"Point"}
}