{
  "type": "Feature",
  "properties": {
    "iso:country":"AT",
    "sg:address":"Reischau 8",
    "sg:city":"Neumarkt im Hausruckkreis",
    "sg:classifiers":[
        {
            "category":"Professional",
            "subcategory":"Computer Services",
            "type":"Services"
        }
    ],
    "sg:phone":"+43 7733 7878",
    "sg:postcode":"4720",
    "sg:province":"Ober\u00f6sterreich",
    "sg:tags":[
        "software"
    ],
    "wof:name":"Baumgartner Walter",
    "wof:placetype":"venue"
},
  "geometry": {"coordinates":[13.713467598,48.281955719],"type":"Point"}
}