{
  "type": "Feature",
  "properties": {
    "addr:full":"Marieng 2 Rattersdorf-Liebing Burgenland 7443",
    "addr:housenumber":"2",
    "addr:postcode":"7443",
    "addr:street":"Marieng",
    "iso:country":"AT",
    "sg:address":"Marieng 2",
    "sg:city":"Rattersdorf-Liebing",
    "sg:orig_category":"Transportunternehmen",
    "sg:phone":"+43 2611 2938",
    "sg:postcode":"7443",
    "sg:province":"Burgenland",
    "wof:name":"STG Silotransport GmbH",
    "wof:placetype":"venue"
},
  "geometry": {"coordinates":[16.4974098206,47.4072189331],"type":"Point"}
}