{
  "type": "Feature",
  "properties": {
    "iso:country":"AT",
    "sg:address":"Au\u00dferlitzstr 80",
    "sg:city":"Schruns",
    "sg:classifiers":[
        {
            "category":"Travel",
            "subcategory":"Hotels & Motels",
            "type":"Entertainment"
        }
    ],
    "sg:phone":"+43 4355 5677049",
    "sg:postcode":"6780",
    "sg:province":"Vorarlberg",
    "wof:name":"Hotel Vitaquelle Gauenstein",
    "wof:placetype":"venue"
},
  "geometry": {"coordinates":[9.9074554443,47.0924110413],"type":"Point"}
}