{
  "type": "Feature",
  "properties": {
    "addr:full":"Turmg 66 Leoben Steiermark 8700",
    "addr:housenumber":"66",
    "addr:postcode":"8700",
    "addr:street":"Turmg",
    "iso:country":"AT",
    "sg:address":"Turmg 66",
    "sg:city":"Leoben",
    "sg:orig_category":"Botendienste",
    "sg:phone":"+43 664 1603598",
    "sg:postcode":"8700",
    "sg:province":"Steiermark",
    "wof:name":"Aichmaier Thomas",
    "wof:placetype":"venue"
},
  "geometry": {"coordinates":[15.092965126,47.3590087891],"type":"Point"}
}