{
  "type": "Feature",
  "properties": {
    "addr:full":"Taubstummeng 2 Wien Wien 1040",
    "addr:housenumber":"2",
    "addr:postcode":"1040",
    "addr:street":"Taubstummeng",
    "iso:country":"AT",
    "sg:address":"Taubstummeng 2",
    "sg:city":"Wien",
    "sg:orig_category":"Finanz- U Wirtschaftsberatung",
    "sg:phone":"+43 1 5442822",
    "sg:postcode":"1040",
    "sg:province":"Wien",
    "wof:name":"Steirer Verm\u00f6gensberatungs GmbH",
    "wof:placetype":"venue"
},
  "geometry": {"coordinates":[16.3722839355,48.1955337524],"type":"Point"}
}