{
  "type": "Feature",
  "properties": {
    "iso:country":"AT",
    "sg:address":"Nr 2",
    "sg:city":"Franking",
    "sg:orig_category":"Friseure U Frisiersalons",
    "sg:phone":"+43 4362 778415",
    "sg:postcode":"5131",
    "sg:province":"Ober\u00f6sterreich",
    "wof:name":"Staffl u Gruber OEG",
    "wof:placetype":"venue"
},
  "geometry": {"coordinates":[-83.64116668699999,30.4663543701],"type":"Point"}
}