{
  "type": "Feature",
  "properties": {
    "iso:country":"AT",
    "sg:address":"Weidach 19",
    "sg:city":"Ebbs",
    "sg:orig_category":"Fleischhauereien",
    "sg:phone":"+43 5373 43299",
    "sg:postcode":"6341",
    "sg:province":"Tirol",
    "wof:name":"W\u00e4ger Franz",
    "wof:placetype":"venue"
},
  "geometry": {"coordinates":[12.2170228958,47.6378211975],"type":"Point"}
}