{
  "type": "Feature",
  "properties": {
    "iso:country":"AT",
    "sg:address":"Sandgrubenweg 32",
    "sg:city":"Bregenz",
    "sg:orig_category":"Baumeister",
    "sg:phone":"+43 5574 71888",
    "sg:postcode":"6900",
    "sg:province":"Vorarlberg",
    "wof:name":"Erath Bauunternehmen GesmbH",
    "wof:placetype":"venue"
},
  "geometry": {"coordinates":[9.7278194427,47.4939002991],"type":"Point"}
}