{
  "type": "Feature",
  "properties": {
    "addr:full":"Pfarrg 8 Baden Nieder\u00f6sterreich 2500",
    "addr:housenumber":"8",
    "addr:postcode":"2500",
    "addr:street":"Pfarrg;Niederoesterreich",
    "iso:country":"AT",
    "sg:address":"Pfarrg 8",
    "sg:city":"Baden",
    "sg:orig_category":"Fu\u00c3\u0178pflege U Fu\u00c3\u0178pflegesalons",
    "sg:phone":"+43 4322 5286789",
    "sg:postcode":"2500",
    "sg:province":"Nieder\u00f6sterreich",
    "wof:name":"Muchar Magda",
    "wof:placetype":"venue"
},
  "geometry": {"coordinates":[16.2351646423,48.0088195801],"type":"Point"}
}