{
  "type": "Feature",
  "properties": {
    "iso:country":"AT",
    "sg:address":"K\u00fcrschnerg 46",
    "sg:city":"Irdning",
    "sg:orig_category":"Telekommunikation",
    "sg:phone":"+43 3682 251000",
    "sg:postcode":"8952",
    "sg:province":"Steiermark",
    "sg:website":"haring-kommunikation.at",
    "wof:name":"Alcatel Anlagen Haring Kommunikationssysteme",
    "wof:placetype":"venue"
},
  "geometry": {"coordinates":[14.1031150818,47.5052604675],"type":"Point"}
}