{
  "type": "Feature",
  "properties": {
    "addr:full":"Johann-Steinb\u00f6ck-Str. 7 Brunn am Gebirge Nieder\u00f6sterreich 2345",
    "addr:housenumber":"7",
    "addr:postcode":"2345",
    "addr:street":"Johann-Steinboeck-Str.",
    "iso:country":"AT",
    "sg:address":"Johann-Steinb\u00f6ck-Str. 7",
    "sg:city":"Brunn am Gebirge",
    "sg:classifiers":[
        {
            "category":"Professional",
            "subcategory":"Engineering",
            "type":"Services"
        }
    ],
    "sg:phone":"+43 4322 3632148",
    "sg:postcode":"2345",
    "sg:province":"Nieder\u00f6sterreich",
    "sg:tags":[
        "machine",
        "-",
        "mechanical"
    ],
    "wof:name":"MAYER FRANZ JOSEF GESMBH",
    "wof:placetype":"venue"
},
  "geometry": {"coordinates":[16.3099155426,48.1094703674],"type":"Point"}
}