{
  "type": "Feature",
  "properties": {
    "iso:country":"AT",
    "sg:address":"Margetinstr 2",
    "sg:city":"Wien",
    "sg:orig_category":"Abschleppdienste",
    "sg:phone":"+43 4317 6766370",
    "sg:postcode":"1110",
    "sg:province":"Wien",
    "sg:website":"vienna-abschleppdienst.at",
    "wof:name":"Vienna Abschlepp- u Bergungsdienst GesmbH",
    "wof:placetype":"venue"
},
  "geometry": {"coordinates":[16.4721412659,48.1653022766],"type":"Point"}
}