{
  "type": "Feature",
  "properties": {
    "iso:country":"AT",
    "sg:address":"Dr.-Hittmair-Str 19",
    "sg:city":"Enns",
    "sg:classifiers":[
        {
            "category":"Restaurant",
            "type":"Food & Drink"
        }
    ],
    "sg:phone":"+43 7223 81479",
    "sg:postcode":"4470",
    "sg:province":"Ober\u00f6sterreich",
    "wof:name":"Reiss Kurt - Wandgebundene Techniken",
    "wof:placetype":"venue"
},
  "geometry": {"coordinates":[14.4672021866,48.2132987976],"type":"Point"}
}