{
  "type": "Feature",
  "properties": {
    "iso:country":"AT",
    "sg:address":"Fabrikstr 20",
    "sg:city":"Niklasdorf",
    "sg:orig_category":"Genossenschaften",
    "sg:phone":"+43 4338 4282520",
    "sg:postcode":"8712",
    "sg:province":"Steiermark",
    "wof:name":"Gemeinn\u00fctzige Wohnbau u Siedlungsgenossenschaft Niklasdorf regGenmbH",
    "wof:placetype":"venue"
},
  "geometry": {"coordinates":[15.1558761597,47.3967552185],"type":"Point"}
}