{
  "type": "Feature",
  "properties": {
    "addr:full":"Kupferg 1 Trautmannsdorf an der Leitha Nieder\u00f6sterreich 2454",
    "addr:housenumber":"1",
    "addr:postcode":"2454",
    "addr:street":"Kupferg",
    "iso:country":"AT",
    "sg:address":"Kupferg 1",
    "sg:city":"Trautmannsdorf an der Leitha",
    "sg:orig_category":"Gemeinden",
    "sg:phone":"+43 4321 6922460",
    "sg:postcode":"2454",
    "sg:province":"Nieder\u00f6sterreich",
    "wof:name":"Gemeindeamt d Marktgemeinde Trautmannsdorf an der Leitha",
    "wof:placetype":"venue"
},
  "geometry": {"coordinates":[16.6353855133,48.0211868286],"type":"Point"}
}