{
  "type": "Feature",
  "properties": {
    "addr:full":"Johannespl 4 Imst Tirol 6460",
    "addr:housenumber":"4",
    "addr:postcode":"6460",
    "addr:street":"Johannespl;Tirol",
    "iso:country":"AT",
    "sg:address":"Johannespl 4",
    "sg:city":"Imst",
    "sg:orig_category":"Tourismusinformation U -Organisationen",
    "sg:phone":"+43 5412 69100",
    "sg:postcode":"6460",
    "sg:province":"Tirol",
    "wof:name":"Tourismusverband Imst-Umgebung",
    "wof:placetype":"venue"
},
  "geometry": {"coordinates":[10.7389440536,47.2420158386],"type":"Point"}
}