{
  "type": "Feature",
  "properties": {
    "addr:full":"Linzer Str 11 Kematen an der Krems Ober\u00f6sterreich 4531",
    "addr:housenumber":"11",
    "addr:postcode":"4531",
    "addr:street":"Linzer Str",
    "iso:country":"AT",
    "sg:address":"Linzer Str 11",
    "sg:city":"Kematen an der Krems",
    "sg:orig_category":"Bestattungsunternehmen",
    "sg:phone":"+43 7228 7381",
    "sg:postcode":"4531",
    "sg:province":"Ober\u00f6sterreich",
    "wof:name":"Bestattung Beatrix Lang",
    "wof:placetype":"venue"
},
  "geometry": {"coordinates":[14.19227314,48.111076355],"type":"Point"}
}