{
  "type": "Feature",
  "properties": {
    "addr:full":"Gewerbepark 3 Mils Tirol 6068",
    "addr:housenumber":"3",
    "addr:postcode":"6068",
    "addr:street":"Gewerbepark;Tirol",
    "iso:country":"AT",
    "sg:address":"Gewerbepark 3",
    "sg:city":"Mils",
    "sg:orig_category":"Abwasseraufbereitung U -Reinigung",
    "sg:phone":"+43 5223 54977",
    "sg:postcode":"6068",
    "sg:province":"Tirol",
    "wof:name":"CrystalClear Membran-Service GmbH",
    "wof:placetype":"venue"
},
  "geometry": {"coordinates":[-99.4334869385,42.926410675],"type":"Point"}
}