{
  "type": "Feature",
  "properties": {
    "addr:full":"M\u00fchltalerstr 23 Leoben Steiermark 8700",
    "addr:housenumber":"23",
    "addr:postcode":"8700",
    "addr:street":"Muehltalerstr",
    "iso:country":"AT",
    "sg:address":"M\u00fchltalerstr 23",
    "sg:city":"Leoben",
    "sg:orig_category":"Tabaktrafiken",
    "sg:phone":"+43 3842 44658",
    "sg:postcode":"8700",
    "sg:province":"Steiermark",
    "wof:name":"Ortner Gertrude",
    "wof:placetype":"venue"
},
  "geometry": {"coordinates":[15.0960092545,47.3813095093],"type":"Point"}
}