{
  "type": "Feature",
  "properties": {
    "addr:full":"Ledererg 3 Villach K\u00e4rnten 9500",
    "addr:housenumber":"3",
    "addr:postcode":"9500",
    "addr:street":"Ledererg;Kaernten",
    "iso:country":"AT",
    "sg:address":"Ledererg 3",
    "sg:city":"Villach",
    "sg:orig_category":"Spielkasinos",
    "sg:phone":"+43 4242 216216",
    "sg:postcode":"9500",
    "sg:province":"K\u00e4rnten",
    "wof:name":"Stadtcasino Villach",
    "wof:placetype":"venue"
},
  "geometry": {"coordinates":[13.8473739624,46.6148681641],"type":"Point"}
}