{
  "type": "Feature",
  "properties": {
    "addr:full":"Dechant-Thaller-Strasse 34/37 Leibnitz Steiermark 8430",
    "addr:housenumber":"34 / 37",
    "addr:postcode":"8430",
    "addr:street":"Dechant-Thaller-Strasse;Steiermark",
    "iso:country":"AT",
    "sg:address":"Dechant-Thaller-Strasse 34/37",
    "sg:city":"Leibnitz",
    "sg:classifiers":[
        {
            "category":"Building & Trades",
            "subcategory":"Plumbing",
            "type":"Services"
        }
    ],
    "sg:phone":"+43 3452 70710",
    "sg:postcode":"8430",
    "sg:province":"Steiermark",
    "sg:tags":[
        "supraregional",
        "gas"
    ],
    "sg:website":"kindermann.co.at",
    "wof:name":"Bad-Heiztechnik Kindermann Ges.m.b.H.",
    "wof:placetype":"venue"
},
  "geometry": {"coordinates":[15.5404529572,46.7885818481],"type":"Point"}
}