{
  "type": "Feature",
  "properties": {
    "addr:full":"Lange Gasse 4 Wolfern Ober\u00f6sterreich 4493",
    "addr:housenumber":"4",
    "addr:postcode":"4493",
    "addr:street":"Lange Gasse",
    "iso:country":"AT",
    "sg:address":"Lange Gasse 4",
    "sg:city":"Wolfern",
    "sg:classifiers":[
        {
            "category":"Banks & Credit Unions",
            "subcategory":"Investment Brokerage",
            "type":"Services"
        }
    ],
    "sg:phone":"+43 7253 85610",
    "sg:postcode":"4493",
    "sg:province":"Ober\u00f6sterreich",
    "sg:tags":[
        "article",
        "occupational",
        "safety"
    ],
    "sg:website":"syria-trade.at",
    "wof:name":"CM-Styria-Trade",
    "wof:placetype":"venue"
},
  "geometry": {"coordinates":[14.3716459274,48.0764045715],"type":"Point"}
}