{
  "type": "Feature",
  "properties": {
    "iso:country":"AT",
    "sg:address":"Gr Petersdrfer Ldstr",
    "sg:city":"Kohfidisch",
    "sg:orig_category":"Lebensmittel / Einzelhandel",
    "sg:phone":"+43 3366 78341",
    "sg:postcode":"7512",
    "sg:province":"Burgenland",
    "wof:name":"SPAR \u00d6sterreichische Warenhandels-AG",
    "wof:placetype":"venue"
},
  "geometry": {"coordinates":[16.3575592041,47.1757698059],"type":"Point"}
}