{
  "type": "Feature",
  "properties": {
    "addr:full":"Betriebsstr 3 Gallneukirchen Ober\u00f6sterreich 4210",
    "addr:housenumber":"3",
    "addr:postcode":"4210",
    "addr:street":"Betriebsstr;Oberoesterreich",
    "iso:country":"AT",
    "sg:address":"Betriebsstr 3",
    "sg:city":"Gallneukirchen",
    "sg:orig_category":"Autohandel",
    "sg:phone":"+43 4372 3550247",
    "sg:postcode":"4210",
    "sg:province":"Ober\u00f6sterreich",
    "wof:name":"Autohaus Himmelbauer GmbH",
    "wof:placetype":"venue"
},
  "geometry": {"coordinates":[14.47219944,48.3578720093],"type":"Point"}
}