{
  "type": "Feature",
  "properties": {
    "addr:full":"Griesg 50 Ferlach K\u00e4rnten 9170",
    "addr:housenumber":"50",
    "addr:postcode":"9170",
    "addr:street":"Griesg;Kaernten",
    "iso:country":"AT",
    "sg:address":"Griesg 50",
    "sg:city":"Ferlach",
    "sg:orig_category":"Genossenschaften",
    "sg:phone":"+43 4227 2300",
    "sg:postcode":"9170",
    "sg:province":"K\u00e4rnten",
    "wof:name":"Landwirtschaftliche Genossenschaft regGenmbH",
    "wof:placetype":"venue"
},
  "geometry": {"coordinates":[14.3036928177,46.5358924866],"type":"Point"}
}