{
  "type": "Feature",
  "properties": {
    "addr:full":"Dorfweg 2 Latschach ober dem Faaker See K\u00e4rnten 9582",
    "addr:housenumber":"2",
    "addr:postcode":"9582",
    "addr:street":"Dorfweg",
    "iso:country":"AT",
    "sg:address":"Dorfweg 2",
    "sg:city":"Latschach ober dem Faaker See",
    "sg:orig_category":"Pensionen / Privatzimmer",
    "sg:phone":"+43 4342 542762",
    "sg:postcode":"9582",
    "sg:province":"K\u00e4rnten",
    "wof:name":"Ulbing Karl",
    "wof:placetype":"venue"
},
  "geometry": {"coordinates":[13.9248018265,46.5569229126],"type":"Point"}
}