{
  "type": "Feature",
  "properties": {
    "addr:full":"Nr 21 Achenkirch Tirol 6215",
    "addr:postcode":"6215",
    "addr:street":"Nr;Achenkirch Tirol",
    "iso:country":"AT",
    "sg:address":"Nr 21",
    "sg:city":"Achenkirch",
    "sg:orig_category":"Pensionen / Privatzimmer",
    "sg:phone":"+43 4352 48201",
    "sg:postcode":"6215",
    "sg:province":"Tirol",
    "wof:name":"Haus Obing",
    "wof:placetype":"venue"
},
  "geometry": {"coordinates":[11.7065629959,47.5290184021],"type":"Point"}
}