{
  "type": "Feature",
  "properties": {
    "addr:full":"Siedlungsstr 29 Pinsdorf Ober\u00f6sterreich 4812",
    "addr:housenumber":"29",
    "addr:postcode":"4812",
    "addr:street":"Siedlungsstr",
    "iso:country":"AT",
    "sg:address":"Siedlungsstr 29",
    "sg:city":"Pinsdorf",
    "sg:orig_category":"Erdarbeiten",
    "sg:phone":"+43 761270005",
    "sg:postcode":"4812",
    "sg:province":"Ober\u00f6sterreich",
    "wof:name":"Moser Franz",
    "wof:placetype":"venue"
},
  "geometry": {"coordinates":[13.7662830353,47.9340820312],"type":"Point"}
}