{
  "type": "Feature",
  "properties": {
    "iso:country":"AT",
    "sg:address":"Otto-Gl\u00f6ckel-Str 8",
    "sg:city":"Steyr",
    "sg:orig_category":"Friseure U Frisiersalons",
    "sg:phone":"+43 4372 5245125",
    "sg:postcode":"4400",
    "sg:province":"Ober\u00f6sterreich",
    "wof:name":"Haarstudio Silvia Winkelstr\u00f6ter",
    "wof:placetype":"venue"
},
  "geometry": {"coordinates":[14.4222707748,48.0328369141],"type":"Point"}
}