{
  "type": "Feature",
  "properties": {
    "iso:country":"AT",
    "sg:address":"Gu\u00dfstahlstr. 21",
    "sg:city":"Judenburg",
    "sg:classifiers":[
        {
            "category":"Shopping",
            "type":"Retail Goods"
        }
    ],
    "sg:phone":"+43 4335 727010",
    "sg:postcode":"8750",
    "sg:province":"Steiermark",
    "sg:tags":[
        "finished",
        "-",
        "metallic"
    ],
    "wof:name":"STYRIA FEDERN GESMBH",
    "wof:placetype":"venue"
},
  "geometry": {"coordinates":[14.6654052734,47.1746902466],"type":"Point"}
}