{
  "type": "Feature",
  "properties": {
    "addr:full":"Lindeng. 43 1071",
    "addr:housenumber":"43",
    "addr:postcode":"1071",
    "addr:street":"Lindeng.",
    "iso:country":"AT",
    "sg:address":"Lindeng. 43",
    "sg:classifiers":[
        {
            "category":"Manufacturing",
            "subcategory":"Paper Products",
            "type":"Manufacturing & Wholesale Goods"
        }
    ],
    "sg:phone":"+43 4315 2149",
    "sg:postcode":"1071",
    "sg:tags":[
        "cardboard"
    ],
    "wof:name":"ARGEV VERPACKUNGSVERWERTUNGS-GESMBH",
    "wof:placetype":"venue"
},
  "geometry": {"coordinates":[16.3490028381,48.1997108459],"type":"Point"}
}