{
  "type": "Feature",
  "properties": {
    "addr:full":"Kleinreithstr 3 Ohlsdorf Ober\u00f6sterreich 4694",
    "addr:housenumber":"3",
    "addr:postcode":"4694",
    "addr:street":"Kleinreithstr",
    "iso:country":"AT",
    "sg:address":"Kleinreithstr 3",
    "sg:city":"Ohlsdorf",
    "sg:orig_category":"Massagen",
    "sg:phone":"+43 761270848",
    "sg:postcode":"4694",
    "sg:province":"Ober\u00f6sterreich",
    "wof:name":"Muhr Peter",
    "wof:placetype":"venue"
},
  "geometry": {"coordinates":[13.7891645432,47.9443740845],"type":"Point"}
}