{
  "type": "Feature",
  "properties": {
    "iso:country":"AT",
    "sg:address":"Grubedt 10",
    "sg:city":"Moosbach",
    "sg:orig_category":"Automaten",
    "sg:phone":"+43 664 5532908",
    "sg:postcode":"5271",
    "sg:province":"Ober\u00f6sterreich",
    "wof:name":"Automaten Lois - Aufstellung - Verleih - Service",
    "wof:placetype":"venue"
},
  "geometry": {"coordinates":[13.1519069672,48.207195282],"type":"Point"}
}