{
  "type": "Feature",
  "properties": {
    "addr:full":"Biragog 15 Klosterneuburg Nieder\u00f6sterreich 3400",
    "addr:housenumber":"15",
    "addr:postcode":"3400",
    "addr:street":"Biragog;Niederoesterreich",
    "iso:country":"AT",
    "sg:address":"Biragog 15",
    "sg:city":"Klosterneuburg",
    "sg:orig_category":"Werbegrafik- U Grafik-Design",
    "sg:phone":"+43 2243 286710",
    "sg:postcode":"3400",
    "sg:province":"Nieder\u00f6sterreich",
    "wof:name":"Haslinger Wolfgang",
    "wof:placetype":"venue"
},
  "geometry": {"coordinates":[16.3353347778,48.3005752563],"type":"Point"}
}