{
  "type": "Feature",
  "properties": {
    "addr:full":"Rohrerstr 50 Zell am Ziller Tirol 6280",
    "addr:housenumber":"50",
    "addr:postcode":"6280",
    "addr:street":"Rohrerstr;Tirol",
    "iso:country":"AT",
    "sg:address":"Rohrerstr 50",
    "sg:city":"Zell am Ziller",
    "sg:orig_category":"Pensionen / Privatzimmer",
    "sg:phone":"+43 4352 827128",
    "sg:postcode":"6280",
    "sg:province":"Tirol",
    "wof:name":"G\u00e4stehaus Birkenheim",
    "wof:placetype":"venue"
},
  "geometry": {"coordinates":[11.8960132599,47.2368850708],"type":"Point"}
}