{
  "type": "Feature",
  "properties": {
    "addr:full":"Liechtensteinstr 10 Wien Wien 1090",
    "addr:housenumber":"10",
    "addr:postcode":"1090",
    "addr:street":"Liechtensteinstr",
    "iso:country":"AT",
    "sg:address":"Liechtensteinstr 10",
    "sg:city":"Wien",
    "sg:classifiers":[
        {
            "category":"Restaurant",
            "type":"Food & Drink"
        }
    ],
    "sg:phone":"+43 1 2764665",
    "sg:postcode":"1090",
    "sg:province":"Wien",
    "wof:name":"Steakhouse - Zum Wilden Stier",
    "wof:placetype":"venue"
},
  "geometry": {"coordinates":[16.3627090454,48.217124939],"type":"Point"}
}