{
  "type": "Feature",
  "properties": {
    "iso:country":"AT",
    "sg:address":"Billrothstr 6A",
    "sg:city":"Wien",
    "sg:orig_category":"Raumausstattung",
    "sg:phone":"+43 1 3680512",
    "sg:postcode":"1190",
    "sg:province":"Wien",
    "wof:name":"Schwab G & Co",
    "wof:placetype":"venue"
},
  "geometry": {"coordinates":[16.3512420654,48.2347183228],"type":"Point"}
}