{
  "type": "Feature",
  "properties": {
    "iso:country":"AT",
    "sg:address":"Nr 29",
    "sg:city":"St. Gerold",
    "sg:classifiers":[
        {
            "category":"Restaurant",
            "type":"Food & Drink"
        }
    ],
    "sg:phone":"+43 4355 50212118",
    "sg:postcode":"6722",
    "sg:province":"Vorarlberg",
    "wof:name":"Klosterkeller St Gerold d Propstei",
    "wof:placetype":"venue"
},
  "geometry": {"coordinates":[9.8162698746,47.220615387],"type":"Point"}
}