{
  "type": "Feature",
  "properties": {
    "addr:full":"Karl-Heilig-Str 7 Wattens Tirol 6112",
    "addr:housenumber":"7",
    "addr:postcode":"6112",
    "addr:street":"Karl-Heilig-Str;Tirol",
    "iso:country":"AT",
    "sg:address":"Karl-Heilig-Str 7",
    "sg:city":"Wattens",
    "sg:orig_category":"Schlossereien",
    "sg:phone":"+43 4352 2452495",
    "sg:postcode":"6112",
    "sg:province":"Tirol",
    "wof:name":"Perktold Bau- u Kunstschlosserei Thomas Perktold",
    "wof:placetype":"venue"
},
  "geometry": {"coordinates":[11.5875463486,47.2964134216],"type":"Point"}
}