{
  "type": "Feature",
  "properties": {
    "iso:country":"AT",
    "sg:address":"Wiener Str 5",
    "sg:city":"Waidhofen an der Ybbs",
    "sg:orig_category":"Versicherungsunternehmen",
    "sg:phone":"+43 4374 42555600",
    "sg:postcode":"3340",
    "sg:province":"Nieder\u00f6sterreich",
    "wof:name":"Generali Versicherung AG",
    "wof:placetype":"venue"
},
  "geometry": {"coordinates":[14.7724370956,47.9620666504],"type":"Point"}
}