{
  "type": "Feature",
  "properties": {
    "addr:full":"Moosham 26 Grieskirchen Ober\u00f6sterreich 4710",
    "addr:housenumber":"26",
    "addr:postcode":"4710",
    "addr:street":"Moosham",
    "iso:country":"AT",
    "sg:address":"Moosham 26",
    "sg:city":"Grieskirchen",
    "sg:orig_category":"Non-Classified Establishments",
    "sg:phone":"+43 7248 62585",
    "sg:postcode":"4710",
    "sg:province":"Ober\u00f6sterreich",
    "wof:name":"Stra\u00dfenmeisterei Grieskirchen",
    "wof:placetype":"venue"
},
  "geometry": {"coordinates":[13.8062534332,48.2323646545],"type":"Point"}
}