{
  "type": "Feature",
  "properties": {
    "iso:country":"AT",
    "sg:address":"Ketzerg 463",
    "sg:city":"Wien",
    "sg:orig_category":"Juweliere, Gold- U Silberschmiede",
    "sg:phone":"+43 4318 887208",
    "sg:postcode":"1230",
    "sg:province":"Wien",
    "sg:website":"preindl.com",
    "wof:name":"Preindl Andreas",
    "wof:placetype":"venue"
},
  "geometry": {"coordinates":[16.2579784393,48.1331863403],"type":"Point"}
}