{
  "type": "Feature",
  "properties": {
    "iso:country":"AT",
    "sg:address":"Wasserg 13",
    "sg:city":"Steinabr\u00fcckl",
    "sg:classifiers":[
        {
            "category":"Shopping",
            "subcategory":"Party Supplies",
            "type":"Retail Goods"
        }
    ],
    "sg:phone":"+43 4326 22433433",
    "sg:postcode":"2751",
    "sg:province":"Nieder\u00f6sterreich",
    "sg:tags":[
        "u",
        "lichtanlagen",
        "ton-"
    ],
    "wof:name":"GIS -Ela Ton- u Elektrotechnik",
    "wof:placetype":"venue"
},
  "geometry": {"coordinates":[16.2033901215,47.8688201904],"type":"Point"}
}