{
  "type": "Feature",
  "properties": {
    "iso:country":"AT",
    "sg:address":"Museumstr 28",
    "sg:city":"Innsbruck",
    "sg:classifiers":[
        {
            "category":"Restaurant",
            "type":"Food & Drink"
        }
    ],
    "sg:phone":"+43 512 583295",
    "sg:postcode":"6020",
    "sg:province":"Tirol",
    "wof:name":"Restaurant-Cafe Wilder Mann",
    "wof:placetype":"venue"
},
  "geometry": {"coordinates":[11.3989429474,47.2666664124],"type":"Point"}
}