{
  "type": "Feature",
  "properties": {
    "addr:full":"Feldg 5 Michelhausen Nieder\u00f6sterreich 3451",
    "addr:housenumber":"5",
    "addr:postcode":"3451",
    "addr:street":"Feldg",
    "iso:country":"AT",
    "sg:address":"Feldg 5",
    "sg:city":"Michelhausen",
    "sg:orig_category":"Garten- U Landschaftsgestaltung",
    "sg:phone":"+43 2275 5205",
    "sg:postcode":"3451",
    "sg:province":"Nieder\u00f6sterreich",
    "wof:name":"Lederleitner Gartenbau GmbH",
    "wof:placetype":"venue"
},
  "geometry": {"coordinates":[15.9400615692,48.2906227112],"type":"Point"}
}