{
  "type": "Feature",
  "properties": {
    "addr:full":"Zeillerg 65 Graz Steiermark 8020",
    "addr:housenumber":"65",
    "addr:postcode":"8020",
    "addr:street":"Zeillerg",
    "iso:country":"AT",
    "sg:address":"Zeillerg 65",
    "sg:city":"Graz",
    "sg:orig_category":"Maler, Anstreicher U Lackierer",
    "sg:phone":"+43 4331 6681418",
    "sg:postcode":"8020",
    "sg:province":"Steiermark",
    "wof:name":"Kovatschitz Eduard",
    "wof:placetype":"venue"
},
  "geometry": {"coordinates":[15.4245223999,47.0831947327],"type":"Point"}
}