{
  "type": "Feature",
  "properties": {
    "iso:country":"AT",
    "sg:address":"Rasing 16",
    "sg:city":"Mariazell",
    "sg:classifiers":[
        {
            "category":"Park",
            "subcategory":"Provincial",
            "type":"Public Place"
        }
    ],
    "sg:phone":"+43 4338 822860",
    "sg:postcode":"8630",
    "sg:province":"Steiermark",
    "sg:tags":[
        "u",
        "ski-",
        "snowboardschulen"
    ],
    "wof:name":"Ski- u Snowboardschule Amigos",
    "wof:placetype":"venue"
},
  "geometry": {"coordinates":[15.3102750778,47.7630500793],"type":"Point"}
}