{
  "type": "Feature",
  "properties": {
    "addr:full":"B\u00fcrgerspitalg 10 Wien Wien 1060",
    "addr:housenumber":"10",
    "addr:postcode":"1060",
    "addr:street":"Buergerspitalg",
    "iso:country":"AT",
    "sg:address":"B\u00fcrgerspitalg 10",
    "sg:city":"Wien",
    "sg:orig_category":"Personalbereitstellung",
    "sg:phone":"+43 1 595572640",
    "sg:postcode":"1060",
    "sg:province":"Wien",
    "wof:name":"ABP Personalbereitstellung GmbH",
    "wof:placetype":"venue"
},
  "geometry": {"coordinates":[16.3504657745,48.1947135925],"type":"Point"}
}