{
  "type": "Feature",
  "properties": {
    "addr:full":"Baumkirchnerring 6 Wiener Neustadt Nieder\u00f6sterreich 2700",
    "addr:housenumber":"6",
    "addr:postcode":"2700",
    "addr:street":"Baumkirchnerring",
    "iso:country":"AT",
    "sg:address":"Baumkirchnerring 6",
    "sg:city":"Wiener Neustadt",
    "sg:orig_category":"Banken U Sparkassen",
    "sg:phone":"+43 4326 22281610",
    "sg:postcode":"2700",
    "sg:province":"Nieder\u00f6sterreich",
    "wof:name":"Bank f Arbeit u Wirtschaft AG",
    "wof:placetype":"venue"
},
  "geometry": {"coordinates":[16.2419891357,47.816619873],"type":"Point"}
}