{
  "type": "Feature",
  "properties": {
    "iso:country":"AT",
    "sg:address":"Hietzinger Hauptstrasse 66/4",
    "sg:city":"Wien",
    "sg:orig_category":"Palladium",
    "sg:phone":"+43 1 87672970",
    "sg:postcode":"1130",
    "sg:province":"Wien",
    "wof:name":"Kernco PGM Trading AG",
    "wof:placetype":"venue"
},
  "geometry": {"coordinates":[16.2854347229,48.1874008179],"type":"Point"}
}