{
  "type": "Feature",
  "properties": {
    "iso:country":"AT",
    "sg:address":"Birkfelder Str 25",
    "sg:city":"Weiz",
    "sg:orig_category":"Friseure U Frisiersalons",
    "sg:phone":"+43 3172 2294",
    "sg:postcode":"8160",
    "sg:province":"Steiermark",
    "wof:name":"Fris\u00f6r Fragner GmbH",
    "wof:placetype":"venue"
},
  "geometry": {"coordinates":[15.6292076111,47.2182807922],"type":"Point"}
}