{
  "type": "Feature",
  "properties": {
    "iso:country":"AT",
    "sg:address":"Engerthstr 203",
    "sg:city":"Wien",
    "sg:orig_category":"Dolmetscher",
    "sg:phone":"+43 4317 291084",
    "sg:postcode":"1020",
    "sg:province":"Wien",
    "wof:name":"Shin Veronika Kyochun Dr",
    "wof:placetype":"venue"
},
  "geometry": {"coordinates":[16.4083633423,48.220905304],"type":"Point"}
}