{
  "type": "Feature",
  "properties": {
    "addr:full":"Pulverturmg 1 Wien Wien 1090",
    "addr:housenumber":"1",
    "addr:postcode":"1090",
    "addr:street":"Pulverturmg",
    "iso:country":"AT",
    "sg:address":"Pulverturmg 1",
    "sg:city":"Wien",
    "sg:orig_category":"Industrieanlagenbau U -Planung",
    "sg:phone":"+43 4313 177279",
    "sg:postcode":"1090",
    "sg:province":"Wien",
    "wof:name":"Matex Industrieanlagenprojektierungs- u VertriebsgesmbH",
    "wof:placetype":"venue"
},
  "geometry": {"coordinates":[16.3543281555,48.2289543152],"type":"Point"}
}