{
  "type": "Feature",
  "properties": {
    "iso:country":"AT",
    "sg:address":"Strandweg 26",
    "sg:city":"D\u00f6briach",
    "sg:classifiers":[
        {
            "category":"Restaurant",
            "type":"Food & Drink"
        }
    ],
    "sg:phone":"+43 4342 467187",
    "sg:postcode":"9873",
    "sg:province":"K\u00e4rnten",
    "wof:name":"Campingrestaurant Winkler",
    "wof:placetype":"venue"
},
  "geometry": {"coordinates":[9.6596899033,47.818321228],"type":"Point"}
}