{
  "type": "Feature",
  "properties": {
    "iso:country":"AT",
    "sg:address":"Hans-Sachs-G 5",
    "sg:city":"Graz",
    "sg:orig_category":"Schifffahrt",
    "sg:phone":"+43 316 7182700",
    "sg:postcode":"8010",
    "sg:province":"Steiermark",
    "wof:name":"Marinconsult SchiffsverwaltungsgesmbH",
    "wof:placetype":"venue"
},
  "geometry": {"coordinates":[15.4420537949,47.0690536499],"type":"Point"}
}