{
  "type": "Feature",
  "properties": {
    "addr:full":"Lachtengasse 55 Wiener Neustadt Nieder\u00f6sterreich 2700",
    "addr:housenumber":"55",
    "addr:postcode":"2700",
    "addr:street":"Lachtengasse",
    "iso:country":"AT",
    "sg:address":"Lachtengasse 55",
    "sg:city":"Wiener Neustadt",
    "sg:classifiers":[
        {
            "category":"Manufacturing",
            "subcategory":"Motor Vehicles & Parts",
            "type":"Manufacturing & Wholesale Goods"
        }
    ],
    "sg:phone":"+43 2622 213390",
    "sg:postcode":"2700",
    "sg:province":"Nieder\u00f6sterreich",
    "sg:tags":[
        "aluminium",
        "processing",
        "sheet"
    ],
    "sg:website":"geschuetzte-werkstaette-wr-neustadt.at",
    "wof:name":"Gesch\u00fctzte Werkst\u00e4tte Wiener Neustadt Ges.m.b.H.",
    "wof:placetype":"venue"
},
  "geometry": {"coordinates":[16.229850769,47.7943916321],"type":"Point"}
}