{
  "type": "Feature",
  "properties": {
    "iso:country":"AT",
    "sg:address":"Haselstauder Str 35",
    "sg:city":"Dornbirn",
    "sg:orig_category":"Fotografen",
    "sg:phone":"+43 5572 23578",
    "sg:postcode":"6850",
    "sg:province":"Vorarlberg",
    "wof:name":"Fotostudio Klaus",
    "wof:placetype":"venue"
},
  "geometry": {"coordinates":[9.7556447983,47.431224823],"type":"Point"}
}