{
  "type": "Feature",
  "properties": {
    "iso:country":"AT",
    "sg:address":"Landwiedstrasse 23",
    "sg:city":"Linz",
    "sg:classifiers":[
        {
            "category":"Home & Garden",
            "subcategory":"Building Materials",
            "type":"Retail Goods"
        }
    ],
    "sg:phone":"+43 732 6717930",
    "sg:postcode":"4020",
    "sg:province":"Ober\u00f6sterreich",
    "sg:tags":[
        "antiglare",
        "blind",
        "roller"
    ],
    "sg:website":"leuwico.com",
    "wof:name":"Leuwico B\u00fcroeinrichtungen GmbH",
    "wof:placetype":"venue"
},
  "geometry": {"coordinates":[14.2793016434,48.2753791809],"type":"Point"}
}