{
  "type": "Feature",
  "properties": {
    "iso:country":"AT",
    "sg:address":"Schulg 10",
    "sg:city":"Hofkirchen im M\u00fchlkreis",
    "sg:orig_category":"Hauptschulen",
    "sg:phone":"+43 7285 2980",
    "sg:postcode":"4142",
    "sg:province":"Ober\u00f6sterreich",
    "wof:name":"Hauptschule",
    "wof:placetype":"venue"
},
  "geometry": {"coordinates":[13.118016243,48.6795654297],"type":"Point"}
}