{
  "type": "Feature",
  "properties": {
    "addr:full":"Pantzerg 30 Wien Wien 1190",
    "addr:housenumber":"30",
    "addr:postcode":"1190",
    "addr:street":"Pantzerg",
    "iso:country":"AT",
    "sg:address":"Pantzerg 30",
    "sg:city":"Wien",
    "sg:orig_category":"Institute",
    "sg:phone":"+43 1 3699729",
    "sg:postcode":"1190",
    "sg:province":"Wien",
    "wof:name":"Institut f historische Familienforschung",
    "wof:placetype":"venue"
},
  "geometry": {"coordinates":[16.354675293,48.2361526489],"type":"Point"}
}