{
  "type": "Feature",
  "properties": {
    "addr:full":"Mexikosdlg 1 Neusiedl am See Burgenland 7100",
    "addr:housenumber":"1",
    "addr:postcode":"7100",
    "addr:street":"Mexikosdlg",
    "iso:country":"AT",
    "sg:address":"Mexikosdlg 1",
    "sg:city":"Neusiedl am See",
    "sg:orig_category":"Versuchsanstalten",
    "sg:phone":"+43 4321 678848",
    "sg:postcode":"7100",
    "sg:province":"Burgenland",
    "wof:name":"Gem\u00fcsebau-Versuchsanlage d H\u00f6heren Bundeslehr- u Versuchsanstalt f Gartenbau Sch\u00f6nbrunn",
    "wof:placetype":"venue"
},
  "geometry": {"coordinates":[16.841884613,47.9491081238],"type":"Point"}
}