{
  "type": "Feature",
  "properties": {
    "addr:full":"Nelkeng 8 Ebergassing Nieder\u00f6sterreich 2435",
    "addr:housenumber":"8",
    "addr:postcode":"2435",
    "addr:street":"Nelkeng",
    "iso:country":"AT",
    "sg:address":"Nelkeng 8",
    "sg:city":"Ebergassing",
    "sg:orig_category":"Massagen",
    "sg:phone":"+43 2234 72269",
    "sg:postcode":"2435",
    "sg:province":"Nieder\u00f6sterreich",
    "wof:name":"Wachter Helga Fachinstitut",
    "wof:placetype":"venue"
},
  "geometry": {"coordinates":[16.5140209198,48.0509757996],"type":"Point"}
}