{
  "type": "Feature",
  "properties": {
    "addr:full":"Timesbergerstr 21 Leonding Ober\u00f6sterreich 4060",
    "addr:housenumber":"21",
    "addr:postcode":"4060",
    "addr:street":"Timesbergerstr",
    "iso:country":"AT",
    "sg:address":"Timesbergerstr 21",
    "sg:city":"Leonding",
    "sg:orig_category":"Physiotherapie",
    "sg:phone":"+43 732 676211",
    "sg:postcode":"4060",
    "sg:province":"Ober\u00f6sterreich",
    "wof:name":"Sieberer Karin",
    "wof:placetype":"venue"
},
  "geometry": {"coordinates":[14.2609930038,48.2780609131],"type":"Point"}
}