{
  "type": "Feature",
  "properties": {
    "iso:country":"AT",
    "sg:address":"Amerling 119",
    "sg:city":"Kramsach",
    "sg:orig_category":"Holzgro\u00c3\u0178handel",
    "sg:phone":"+43 4353 37637330",
    "sg:postcode":"6233",
    "sg:province":"Tirol",
    "wof:name":"Frischeis J u A GesmbH",
    "wof:placetype":"venue"
},
  "geometry": {"coordinates":[11.8727703094,47.4360427856],"type":"Point"}
}