{
  "type": "Feature",
  "properties": {
    "iso:country":"AT",
    "sg:address":"Santle 476",
    "sg:city":"S\u00f6lden",
    "sg:classifiers":[
        {
            "category":"Manufacturing",
            "subcategory":"Wood Products",
            "type":"Manufacturing & Wholesale Goods"
        }
    ],
    "sg:phone":"+43 5254 22710",
    "sg:postcode":"6450",
    "sg:province":"Tirol",
    "sg:tags":[
        "made",
        "balcony"
    ],
    "sg:website":"www.zimmerei-klotz.at",
    "wof:name":"Zimmerei Klotz GmbH",
    "wof:placetype":"venue"
},
  "geometry": {"coordinates":[11.0098667145,46.9737968445],"type":"Point"}
}