{
  "type": "Feature",
  "properties": {
    "addr:full":"Scharnsteinerstrasse 1 Gmunden Ober\u00f6sterreich 4810",
    "addr:housenumber":"1",
    "addr:postcode":"4810",
    "addr:street":"Scharnsteinerstrasse;Oberoesterreich",
    "iso:country":"AT",
    "sg:address":"Scharnsteinerstrasse 1",
    "sg:city":"Gmunden",
    "sg:classifiers":[
        {
            "category":"Farming",
            "subcategory":"Berry Farm",
            "type":"Manufacturing & Wholesale Goods"
        }
    ],
    "sg:phone":"+43 76127840",
    "sg:postcode":"4810",
    "sg:province":"Ober\u00f6sterreich",
    "sg:tags":[
        "austrian",
        "wine"
    ],
    "sg:website":"wagnerweb.at/",
    "wof:name":"Rudolf Wagner KG Getr\u00e4nkegro\u00dfhandel",
    "wof:placetype":"venue"
},
  "geometry": {"coordinates":[13.8191995621,47.9258575439],"type":"Point"}
}