{
  "type": "Feature",
  "properties": {
    "iso:country":"AT",
    "sg:address":"Hubergutstr 14a",
    "sg:city":"Steyr",
    "sg:orig_category":"Reinigungsservice",
    "sg:phone":"+43 7252 45242",
    "sg:postcode":"4400",
    "sg:province":"Ober\u00f6sterreich",
    "wof:name":"DIW Instandhaltung GmbH",
    "wof:placetype":"venue"
},
  "geometry": {"coordinates":[14.4243021011,48.0288925171],"type":"Point"}
}