{
  "type": "Feature",
  "properties": {
    "iso:country":"AT",
    "sg:address":"Defreggerstr 38a",
    "sg:city":"Innsbruck",
    "sg:orig_category":"Institute",
    "sg:phone":"+43 512 392647",
    "sg:postcode":"6020",
    "sg:province":"Tirol",
    "wof:name":"Institut f Integrative Bildung",
    "wof:placetype":"venue"
},
  "geometry": {"coordinates":[11.4109239578,47.2653503418],"type":"Point"}
}