{
  "type": "Feature",
  "properties": {
    "addr:full":"Altstadt 18 Bruck an der Leitha Nieder\u00f6sterreich 2460",
    "addr:housenumber":"18",
    "addr:postcode":"2460",
    "addr:street":"Altstadt",
    "iso:country":"AT",
    "sg:address":"Altstadt 18",
    "sg:city":"Bruck an der Leitha",
    "sg:orig_category":"Restaurants: Amerikanisch",
    "sg:phone":"+43 4321 6269168",
    "sg:postcode":"2460",
    "sg:province":"Nieder\u00f6sterreich",
    "wof:name":"steak-House Western-Saloon",
    "wof:placetype":"venue"
},
  "geometry": {"coordinates":[16.7747612,48.0220794678],"type":"Point"}
}