{
  "type": "Feature",
  "properties": {
    "addr:full":"Franz Josef-Pl 7 Gmunden Ober\u00f6sterreich 4810",
    "addr:housenumber":"7",
    "addr:postcode":"4810",
    "addr:street":"Oberoesterreich",
    "iso:country":"AT",
    "sg:address":"Franz Josef-Pl 7",
    "sg:city":"Gmunden",
    "sg:orig_category":"Spielwaren U Spiele",
    "sg:phone":"+43 761263464",
    "sg:postcode":"4810",
    "sg:province":"Ober\u00f6sterreich",
    "wof:name":"Spielwaren Pusch K\u00f6lblinger Rastinger OHG",
    "wof:placetype":"venue"
},
  "geometry": {"coordinates":[13.7971391678,47.9176597595],"type":"Point"}
}