{
  "type": "Feature",
  "properties": {
    "addr:full":"Humboldtstr 39 Linz Ober\u00f6sterreich 4020",
    "addr:housenumber":"39",
    "addr:postcode":"4020",
    "addr:street":"Humboldtstr",
    "iso:country":"AT",
    "sg:address":"Humboldtstr 39",
    "sg:city":"Linz",
    "sg:orig_category":"Handelsagenturen",
    "sg:phone":"+43 732 654159",
    "sg:postcode":"4020",
    "sg:province":"Ober\u00f6sterreich",
    "wof:name":"Dunzinger Erika",
    "wof:placetype":"venue"
},
  "geometry": {"coordinates":[14.296002388,48.297088623],"type":"Point"}
}