{
  "type": "Feature",
  "properties": {
    "addr:full":"Nr 82 G\u00f6stling an der Ybbs Nieder\u00f6sterreich 3345",
    "addr:postcode":"3345",
    "addr:street":"Nr 82 Goestling An Der Ybbs",
    "iso:country":"AT",
    "sg:address":"Nr 82",
    "sg:city":"G\u00f6stling an der Ybbs",
    "sg:orig_category":"Tischlereien",
    "sg:phone":"+43 7484 2927",
    "sg:postcode":"3345",
    "sg:province":"Nieder\u00f6sterreich",
    "wof:name":"Zettel G\u00fcnter",
    "wof:placetype":"venue"
},
  "geometry": {"coordinates":[166.9221496582,-0.5282999873],"type":"Point"}
}