{
  "type": "Feature",
  "properties": {
    "addr:full":"Nr 22 Bad Kreuzen Ober\u00f6sterreich 4362",
    "addr:housenumber":"22",
    "addr:postcode":"4362",
    "addr:street":"Nr",
    "iso:country":"AT",
    "sg:address":"Nr 22",
    "sg:city":"Bad Kreuzen",
    "sg:orig_category":"Volksschulen",
    "sg:phone":"+43 7266 6202",
    "sg:postcode":"4362",
    "sg:province":"Ober\u00f6sterreich",
    "wof:name":"Volksschule Kreuzen",
    "wof:placetype":"venue"
},
  "geometry": {"coordinates":[14.8063306808,48.267124176],"type":"Point"}
}