{
  "type": "Feature",
  "properties": {
    "addr:full":"Gumpendorfer Str 72 Wien Wien 1060",
    "addr:postcode":"1060",
    "addr:street":"Str 72",
    "iso:country":"AT",
    "sg:address":"Gumpendorfer Str 72",
    "sg:city":"Wien",
    "sg:orig_category":"Immobilienverwaltungen",
    "sg:phone":"+43 1 59750600",
    "sg:postcode":"1060",
    "sg:province":"Wien",
    "sg:website":"www.metzger-estate.com",
    "wof:name":"MRG Metzger Realit\u00e4ten Gruppe",
    "wof:placetype":"venue"
},
  "geometry": {"coordinates":[16.3499889374,48.1944503784],"type":"Point"}
}