{
  "type": "Feature",
  "properties": {
    "addr:full":"Oberer Markt 8 Weyer Ober\u00f6sterreich 3335",
    "addr:housenumber":"8",
    "addr:postcode":"3335",
    "addr:street":"Oberer Markt",
    "iso:country":"AT",
    "sg:address":"Oberer Markt 8",
    "sg:city":"Weyer",
    "sg:orig_category":"Apotheken",
    "sg:phone":"+43 7355 64450",
    "sg:postcode":"3335",
    "sg:province":"Ober\u00f6sterreich",
    "wof:name":"Apotheke z Biber",
    "wof:placetype":"venue"
},
  "geometry": {"coordinates":[14.6637363434,47.8570480347],"type":"Point"}
}