{
  "type": "Feature",
  "properties": {
    "addr:full":"Feichtegger Wiese 1 Mariazell Steiermark 8630",
    "addr:housenumber":"1",
    "addr:postcode":"8630",
    "addr:street":"Feichtegger Wiese",
    "iso:country":"AT",
    "sg:address":"Feichtegger Wiese 1",
    "sg:city":"Mariazell",
    "sg:orig_category":"Feuerwehren",
    "sg:phone":"+43 664 5153310",
    "sg:postcode":"8630",
    "sg:province":"Steiermark",
    "wof:name":"Bezirksfeuerwehrkommando Bruck",
    "wof:placetype":"venue"
},
  "geometry": {"coordinates":[15.3227596283,47.7731781006],"type":"Point"}
}