{
  "type": "Feature",
  "properties": {
    "iso:country":"AT",
    "sg:address":"Nr 122",
    "sg:city":"Unterlamm",
    "sg:orig_category":"Non-Classified Establishments",
    "sg:phone":"+43 3155 8213",
    "sg:postcode":"8352",
    "sg:province":"Steiermark",
    "wof:name":"Pfarramt",
    "wof:placetype":"venue"
},
  "geometry": {"coordinates":[16.0573005676,46.9795761108],"type":"Point"}
}