{
  "type": "Feature",
  "properties": {
    "iso:country":"AT",
    "sg:address":"Pa\u00df-Thurn-Str 10",
    "sg:city":"Kitzb\u00fchel",
    "sg:orig_category":"Tischlereien",
    "sg:phone":"+43 4353 5664517",
    "sg:postcode":"6370",
    "sg:province":"Tirol",
    "wof:name":"P\u00f6ll G & W Bau- u M\u00f6beltischlerei GesmbH",
    "wof:placetype":"venue"
},
  "geometry": {"coordinates":[12.4196195602,47.4188957214],"type":"Point"}
}