{
  "type": "Feature",
  "properties": {
    "addr:full":"Pischeldorfer Str 179 Klagenfurt K\u00e4rnten 9020",
    "addr:housenumber":"179",
    "addr:postcode":"9020",
    "addr:street":"Kaernten",
    "iso:country":"AT",
    "sg:address":"Pischeldorfer Str 179",
    "sg:city":"Klagenfurt",
    "sg:orig_category":"Wasserschadensanierung",
    "sg:phone":"+43 463 338888",
    "sg:postcode":"9020",
    "sg:province":"K\u00e4rnten",
    "wof:name":"Munters Trocknungs-Service GesmbH",
    "wof:placetype":"venue"
},
  "geometry": {"coordinates":[14.3368453979,46.637462616],"type":"Point"}
}