{
  "type": "Feature",
  "properties": {
    "iso:country":"AT",
    "sg:address":"Kirschg 15",
    "sg:city":"Enzesfeld-Lindabrunn",
    "sg:orig_category":"Tischlereien",
    "sg:phone":"+43 2256 82352",
    "sg:postcode":"2551",
    "sg:province":"Nieder\u00f6sterreich",
    "wof:name":"Stockreiter Johannes",
    "wof:placetype":"venue"
},
  "geometry": {"coordinates":[16.1651268005,47.9127120972],"type":"Point"}
}