{
  "type": "Feature",
  "properties": {
    "iso:country":"AT",
    "sg:address":"Breitlahnerweg 285",
    "sg:city":"Mayrhofen",
    "sg:orig_category":"Maler, Anstreicher U Lackierer",
    "sg:phone":"+43 4352 8562762",
    "sg:postcode":"6290",
    "sg:province":"Tirol",
    "wof:name":"Erler Siegfried",
    "wof:placetype":"venue"
},
  "geometry": {"coordinates":[11.8704128265,47.166885376],"type":"Point"}
}