{
  "type": "Feature",
  "properties": {
    "addr:full":"Pouthongasse 3 Wien Wien 1150",
    "addr:housenumber":"3",
    "addr:postcode":"1150",
    "addr:street":"Pouthongasse",
    "iso:country":"AT",
    "sg:address":"Pouthongasse 3",
    "sg:city":"Wien",
    "sg:classifiers":[
        {
            "category":"Manufacturing",
            "subcategory":"Printing",
            "type":"Manufacturing & Wholesale Goods"
        }
    ],
    "sg:phone":"+43 1 9852149",
    "sg:postcode":"1150",
    "sg:province":"Wien",
    "sg:tags":[
        "house",
        "book"
    ],
    "wof:name":"Friedrich Brandstetter Ges.m.b.H.",
    "wof:placetype":"venue"
},
  "geometry": {"coordinates":[16.331237793,48.1967544556],"type":"Point"}
}