{
  "type": "Feature",
  "properties": {
    "addr:full":"G\u00f6stinger Str 221 G\u00f6sting Steiermark 8051",
    "addr:housenumber":"221",
    "addr:postcode":"8051",
    "addr:street":"Str",
    "iso:country":"AT",
    "sg:address":"G\u00f6stinger Str 221",
    "sg:city":"G\u00f6sting",
    "sg:classifiers":[
        {
            "category":"Professional",
            "subcategory":"Computer Services",
            "type":"Services"
        }
    ],
    "sg:phone":"+43 316 679551",
    "sg:postcode":"8051",
    "sg:province":"Steiermark",
    "sg:tags":[
        "software"
    ],
    "wof:name":"SKIM Schr\u00f6ttner & Kornschober OEG",
    "wof:placetype":"venue"
},
  "geometry": {"coordinates":[15.3930902481,47.098361969],"type":"Point"}
}