{
  "type": "Feature",
  "properties": {
    "addr:full":"Weizer Str 2 Birkfeld Steiermark 8190",
    "addr:housenumber":"2",
    "addr:postcode":"8190",
    "addr:street":"Str",
    "iso:country":"AT",
    "sg:address":"Weizer Str 2",
    "sg:city":"Birkfeld",
    "sg:orig_category":"Optiker",
    "sg:phone":"+43 3174 3670",
    "sg:postcode":"8190",
    "sg:province":"Steiermark",
    "wof:name":"Optik Groh",
    "wof:placetype":"venue"
},
  "geometry": {"coordinates":[15.6944322586,47.3544769287],"type":"Point"}
}