{
  "type": "Feature",
  "properties": {
    "addr:full":"Oberdorfer Str 1 Bruck an der Mur Steiermark 8600",
    "addr:housenumber":"1",
    "addr:postcode":"8600",
    "addr:street":"Oberdorfer Str",
    "iso:country":"AT",
    "sg:address":"Oberdorfer Str 1",
    "sg:city":"Bruck an der Mur",
    "sg:orig_category":"Friseure U Frisiersalons",
    "sg:phone":"+43 4338 6255560",
    "sg:postcode":"8600",
    "sg:province":"Steiermark",
    "wof:name":"Frisiersalon Rick",
    "wof:placetype":"venue"
},
  "geometry": {"coordinates":[15.2614870071,47.4113502502],"type":"Point"}
}