{
  "type": "Feature",
  "properties": {
    "iso:country":"AT",
    "sg:address":"Rathausstr 25",
    "sg:city":"Feld am See",
    "sg:orig_category":"Tourismusinformation U -Organisationen",
    "sg:phone":"+43 4342 462273",
    "sg:postcode":"9544",
    "sg:province":"K\u00e4rnten",
    "wof:name":"Fremdenverkehrsamt",
    "wof:placetype":"venue"
},
  "geometry": {"coordinates":[13.7480859756,46.7752227783],"type":"Point"}
}