{
  "type": "Feature",
  "properties": {
    "addr:full":"Hauptstr 42 Obdach Steiermark 8742",
    "addr:housenumber":"42",
    "addr:postcode":"8742",
    "addr:street":"Hauptstr",
    "iso:country":"AT",
    "sg:address":"Hauptstr 42",
    "sg:city":"Obdach",
    "sg:orig_category":"Lebensmittel / Einzelhandel",
    "sg:phone":"+43 4335 783120",
    "sg:postcode":"8742",
    "sg:province":"Steiermark",
    "wof:name":"Billa AG",
    "wof:placetype":"venue"
},
  "geometry": {"coordinates":[14.6959047318,47.0673217773],"type":"Point"}
}