{
  "type": "Feature",
  "properties": {
    "iso:country":"AT",
    "sg:address":"Fasanweg 4",
    "sg:city":"Gro\u00df-Enzersdorf",
    "sg:orig_category":"Handelsagenturen",
    "sg:phone":"+43 2249 3660",
    "sg:postcode":"2301",
    "sg:province":"Nieder\u00f6sterreich",
    "wof:name":"Zauner Christine",
    "wof:placetype":"venue"
},
  "geometry": {"coordinates":[16.5544166565,48.204788208],"type":"Point"}
}