{
  "type": "Feature",
  "properties": {
    "addr:full":"Saag 2 Ru\u00dfbach am Pa\u00df Gsch\u00fctt Salzburg 5442",
    "addr:housenumber":"2",
    "addr:postcode":"5442",
    "addr:street":"Saag;Am Pass Gschuett Salzburg",
    "iso:country":"AT",
    "sg:address":"Saag 2",
    "sg:city":"Ru\u00dfbach am Pa\u00df Gsch\u00fctt",
    "sg:orig_category":"Appartements / Ferienwohnungen",
    "sg:phone":"+43 6242 259",
    "sg:postcode":"5442",
    "sg:province":"Salzburg",
    "wof:name":"Kiblerhof",
    "wof:placetype":"venue"
},
  "geometry": {"coordinates":[13.4674339294,47.5948143005],"type":"Point"}
}