{
  "type": "Feature",
  "properties": {
    "iso:country":"AT",
    "sg:address":"Marktstr 22",
    "sg:city":"Krumbach",
    "sg:orig_category":"Baumeister",
    "sg:phone":"+43 2647 42072",
    "sg:postcode":"2851",
    "sg:province":"Nieder\u00f6sterreich",
    "wof:name":"Gutstein Johannes",
    "wof:placetype":"venue"
},
  "geometry": {"coordinates":[16.1937484741,47.5231895447],"type":"Point"}
}