{
  "type": "Feature",
  "properties": {
    "addr:full":"Wallpachg 2 Hall in Tirol Tirol 6060",
    "addr:housenumber":"2",
    "addr:postcode":"6060",
    "addr:street":"Wallpachg;Tirol",
    "iso:country":"AT",
    "sg:address":"Wallpachg 2",
    "sg:city":"Hall in Tirol",
    "sg:orig_category":"Blumeneinzelhandel",
    "sg:phone":"+43 4352 2352590",
    "sg:postcode":"6060",
    "sg:province":"Tirol",
    "wof:name":"Blumen Calovini",
    "wof:placetype":"venue"
},
  "geometry": {"coordinates":[11.5077896118,47.2819404602],"type":"Point"}
}