{
  "type": "Feature",
  "properties": {
    "iso:country":"AT",
    "sg:address":"NB",
    "sg:city":"Tannheim",
    "sg:orig_category":"Rettungsdienste",
    "sg:phone":"+43 5675 6555",
    "sg:postcode":"6675",
    "sg:province":"Tirol",
    "wof:name":"Rotes Kreuz \u00d6sterr Ortsstelle Tannheimertal",
    "wof:placetype":"venue"
},
  "geometry": {"coordinates":[10.5161399841,47.4993400574],"type":"Point"}
}