{
  "type": "Feature",
  "properties": {
    "addr:full":"PF 17 Gnigl Salzburg 5023",
    "addr:postcode":"5023",
    "iso:country":"AT",
    "sg:address":"PF 17",
    "sg:city":"Gnigl",
    "sg:orig_category":"Medien, Zeitungen And Zeitschriften",
    "sg:phone":"+43 4366 2662147",
    "sg:postcode":"5023",
    "sg:province":"Salzburg",
    "sg:website":"http://www.tpiweb.com",
    "wof:name":"tpi Transplant Information",
    "wof:placetype":"venue"
},
  "geometry": {"coordinates":[13.1081838608,47.8200416565],"type":"Point"}
}