{
  "type": "Feature",
  "properties": {
    "addr:full":"Werkstrasse 5 Ternitz Nieder\u00f6sterreich 2630",
    "addr:housenumber":"5",
    "addr:postcode":"2630",
    "addr:street":"Werkstrasse",
    "iso:country":"AT",
    "sg:address":"Werkstrasse 5",
    "sg:city":"Ternitz",
    "sg:classifiers":[
        {
            "category":"Retail",
            "subcategory":"Auto Repair",
            "type":"Services"
        }
    ],
    "sg:phone":"+43 2630 38212",
    "sg:postcode":"2630",
    "sg:province":"Nieder\u00f6sterreich",
    "sg:tags":[
        "retreading",
        "tyre"
    ],
    "wof:name":"Reifen Schober GmbH",
    "wof:placetype":"venue"
},
  "geometry": {"coordinates":[16.0376319885,47.7142715454],"type":"Point"}
}