{
  "type": "Feature",
  "properties": {
    "addr:full":"Hauptstr 118 Wien Wien 1140",
    "addr:housenumber":"118",
    "addr:postcode":"1140",
    "addr:street":"Hauptstr",
    "iso:country":"AT",
    "sg:address":"Hauptstr 118",
    "sg:city":"Wien",
    "sg:classifiers":[
        {
            "category":"Restaurant",
            "type":"Food & Drink"
        }
    ],
    "sg:phone":"+43 4319 794188",
    "sg:postcode":"1140",
    "sg:province":"Wien",
    "sg:tags":[
        "pizzeria"
    ],
    "wof:name":"Pizzeria Bardolino",
    "wof:placetype":"venue"
},
  "geometry": {"coordinates":[16.2148838043,48.2096595764],"type":"Point"}
}