{
  "type": "Feature",
  "properties": {
    "addr:full":"Quellenstr 26 Pernitz Nieder\u00f6sterreich 2763",
    "addr:housenumber":"26",
    "addr:postcode":"2763",
    "addr:street":"Quellenstr",
    "iso:country":"AT",
    "sg:address":"Quellenstr 26",
    "sg:city":"Pernitz",
    "sg:orig_category":"Friseure U Frisiersalons",
    "sg:phone":"+43 4326 3272382",
    "sg:postcode":"2763",
    "sg:province":"Nieder\u00f6sterreich",
    "wof:name":"Braune Maria",
    "wof:placetype":"venue"
},
  "geometry": {"coordinates":[15.9614334106,47.8925704956],"type":"Point"}
}