{
  "type": "Feature",
  "properties": {
    "iso:country":"AT",
    "sg:address":"Stadiongasse 4",
    "sg:city":"Wien",
    "sg:classifiers":[
        {
            "category":"Building & Trades",
            "subcategory":"Cleaning & Sanitation",
            "type":"Services"
        }
    ],
    "sg:phone":"+43 1 4051300",
    "sg:postcode":"1010",
    "sg:province":"Wien",
    "sg:tags":[
        "carpet"
    ],
    "wof:name":"Rex Reinigungsanstalt Alfred Thallmeyer Ges.m.b.H.",
    "wof:placetype":"venue"
},
  "geometry": {"coordinates":[16.3571586609,48.2092018127],"type":"Point"}
}