{
  "type": "Feature",
  "properties": {
    "addr:full":"Bonnamais 3 Sieghartskirchen Nieder\u00f6sterreich 3443",
    "addr:housenumber":"3",
    "addr:postcode":"3443",
    "addr:street":"Bonnamais;Niederoesterreich",
    "iso:country":"AT",
    "sg:address":"Bonnamais 3",
    "sg:city":"Sieghartskirchen",
    "sg:classifiers":[
        {
            "category":"Building & Trades",
            "subcategory":"Construction",
            "type":"Services"
        }
    ],
    "sg:phone":"+43 2274 8351",
    "sg:postcode":"3443",
    "sg:province":"Nieder\u00f6sterreich",
    "sg:tags":[
        "wall",
        "assembling",
        "roof"
    ],
    "wof:name":"Ludwig Hackl Ges.m.b.H.",
    "wof:placetype":"venue"
},
  "geometry": {"coordinates":[16.0201072693,48.2238922119],"type":"Point"}
}