{
  "type": "Feature",
  "properties": {
    "addr:full":"Anton-Ullrich-G 7 Heidenreichstein Nieder\u00f6sterreich 3860",
    "addr:housenumber":"7",
    "addr:postcode":"3860",
    "addr:street":"Anton-Ullrich-G",
    "iso:country":"AT",
    "sg:address":"Anton-Ullrich-G 7",
    "sg:city":"Heidenreichstein",
    "sg:orig_category":"Hauptschulen",
    "sg:phone":"+43 4328 6252169",
    "sg:postcode":"3860",
    "sg:province":"Nieder\u00f6sterreich",
    "wof:name":"Hauptschule Heidenreichstein u Polytechnischer Lehrgang",
    "wof:placetype":"venue"
},
  "geometry": {"coordinates":[15.1231460571,48.8657646179],"type":"Point"}
}