{
  "type": "Feature",
  "properties": {
    "iso:country":"AT",
    "sg:address":"Nr 24",
    "sg:city":"Kuchl",
    "sg:orig_category":"Pensionen / Privatzimmer",
    "sg:phone":"+43 6245 87924",
    "sg:postcode":"5431",
    "sg:province":"Salzburg",
    "wof:name":"Lienbacher Rupert & Hannelore",
    "wof:placetype":"venue"
},
  "geometry": {"coordinates":[13.1438808441,47.625667572],"type":"Point"}
}