{
  "type": "Feature",
  "properties": {
    "iso:country":"AT",
    "sg:address":"Philipsstrasse 46",
    "sg:city":"Lebring",
    "sg:classifiers":[
        {
            "category":"Banks & Credit Unions",
            "subcategory":"Investment Brokerage",
            "type":"Services"
        }
    ],
    "sg:phone":"+43 3182 44200",
    "sg:postcode":"8403",
    "sg:province":"Steiermark",
    "sg:tags":[
        "fork",
        "attached",
        "machine",
        "lift",
        "truck",
        "sweeping"
    ],
    "sg:website":"ecotech.at",
    "wof:name":"ECO TECHNOLOGIES Planungs-, Entwicklungs- und Handelsgesllschaft m.b.H.",
    "wof:placetype":"venue"
},
  "geometry": {"coordinates":[15.5262947083,46.8486251831],"type":"Point"}
}