{
  "type": "Feature",
  "properties": {
    "addr:full":"Brunner Str 71 Wien Wien 1230",
    "addr:postcode":"1230",
    "addr:street":"Str 71",
    "iso:country":"AT",
    "sg:address":"Brunner Str 71",
    "sg:city":"Wien",
    "sg:orig_category":"Lebensmittel / Einzelhandel",
    "sg:phone":"+43 1 8692105",
    "sg:postcode":"1230",
    "sg:province":"Wien",
    "wof:name":"Hofer KG",
    "wof:placetype":"venue"
},
  "geometry": {"coordinates":[16.2983894348,48.1379318237],"type":"Point"}
}