{
  "type": "Feature",
  "properties": {
    "iso:country":"AT",
    "sg:address":"Posthorng 2",
    "sg:city":"Wien",
    "sg:orig_category":"Tapezierer U Dekorateure",
    "sg:phone":"+43 1 7124253",
    "sg:postcode":"1030",
    "sg:province":"Wien",
    "wof:name":"Hertenberger Franz",
    "wof:placetype":"venue"
},
  "geometry": {"coordinates":[16.3872795105,48.2000350952],"type":"Point"}
}