{
  "type": "Feature",
  "properties": {
    "iso:country":"AT",
    "sg:address":"Seilerg 10",
    "sg:city":"Wien",
    "sg:orig_category":"Bekleidung / Einzelhandel",
    "sg:phone":"+43 1 5122241",
    "sg:postcode":"1010",
    "sg:province":"Wien",
    "wof:name":"M\u00fchlbauer Robert GmbH",
    "wof:placetype":"venue"
},
  "geometry": {"coordinates":[16.3706684113,48.2071762085],"type":"Point"}
}