{
  "type": "Feature",
  "properties": {
    "addr:full":"Porzellang 19 Wien Wien 1090",
    "addr:housenumber":"19",
    "addr:postcode":"1090",
    "addr:street":"Porzellang",
    "iso:country":"AT",
    "sg:address":"Porzellang 19",
    "sg:city":"Wien",
    "sg:orig_category":"Exporteure U Importeure",
    "sg:phone":"+43 1 3170169",
    "sg:postcode":"1090",
    "sg:province":"Wien",
    "wof:name":"Ilex Export Import GesmbH",
    "wof:placetype":"venue"
},
  "geometry": {"coordinates":[16.3612556458,48.2200431824],"type":"Point"}
}