{
  "type": "Feature",
  "properties": {
    "addr:full":"Hauptstr 4 Liezen Steiermark 8940",
    "addr:housenumber":"4",
    "addr:postcode":"8940",
    "addr:street":"Hauptstr",
    "iso:country":"AT",
    "sg:address":"Hauptstr 4",
    "sg:city":"Liezen",
    "sg:orig_category":"Nachhilfe U Lernbetreuung",
    "sg:phone":"+43 4336 1223183",
    "sg:postcode":"8940",
    "sg:province":"Steiermark",
    "wof:name":"Sch\u00fclerhilfe Claudia Kratochvil",
    "wof:placetype":"venue"
},
  "geometry": {"coordinates":[14.2430515289,47.5683021545],"type":"Point"}
}