{
  "type": "Feature",
  "properties": {
    "addr:full":"Alter Markt 4 Friedburg Ober\u00f6sterreich 5211",
    "addr:housenumber":"4",
    "addr:postcode":"5211",
    "addr:street":"Alter Markt",
    "iso:country":"AT",
    "sg:address":"Alter Markt 4",
    "sg:city":"Friedburg",
    "sg:orig_category":"Massagen",
    "sg:phone":"+43 7746 2209",
    "sg:postcode":"5211",
    "sg:province":"Ober\u00f6sterreich",
    "wof:name":"Vital Energetik Massagefachinstitut & Ern\u00e4hrungsberatung Johann Cserkits",
    "wof:placetype":"venue"
},
  "geometry": {"coordinates":[13.2395200729,48.020488739],"type":"Point"}
}