{
  "type": "Feature",
  "properties": {
    "addr:full":"Mariahilfer Str 103/4 Wien Wien 1060",
    "addr:housenumber":"103 / 4",
    "addr:postcode":"1060",
    "iso:country":"AT",
    "sg:address":"Mariahilfer Str 103/4",
    "sg:city":"Wien",
    "sg:classifiers":[
        {
            "category":"Professional",
            "subcategory":"Computer Services",
            "type":"Services"
        }
    ],
    "sg:phone":"+43 1 5955172",
    "sg:postcode":"1060",
    "sg:province":"Wien",
    "sg:tags":[
        "software"
    ],
    "wof:name":"Arikan GesmbH",
    "wof:placetype":"venue"
},
  "geometry": {"coordinates":[16.3452720642,48.1968421936],"type":"Point"}
}