{
  "type": "Feature",
  "properties": {
    "addr:full":"Kaplanstrasse 2 Mauthausen Ober\u00f6sterreich 4310",
    "addr:housenumber":"2",
    "addr:postcode":"4310",
    "addr:street":"Kaplanstrasse",
    "iso:country":"AT",
    "sg:address":"Kaplanstrasse 2",
    "sg:city":"Mauthausen",
    "sg:classifiers":[
        {
            "category":"Wholesale",
            "subcategory":"Painting Supplies",
            "type":"Manufacturing & Wholesale Goods"
        }
    ],
    "sg:phone":"+43 7262 61777",
    "sg:postcode":"4310",
    "sg:province":"Ober\u00f6sterreich",
    "sg:website":"malerei-gusenbauer.at",
    "wof:name":"Johann Gusenbauer",
    "wof:placetype":"venue"
},
  "geometry": {"coordinates":[14.5495710373,48.2436523438],"type":"Point"}
}