{
  "type": "Feature",
  "properties": {
    "addr:full":"Maxingstr Wien Wien 1130",
    "addr:postcode":"1130",
    "iso:country":"AT",
    "sg:address":"Maxingstr",
    "sg:city":"Wien",
    "sg:orig_category":"Non-Classified Establishments",
    "sg:phone":"+43 1 8775576",
    "sg:postcode":"1130",
    "sg:province":"Wien",
    "wof:name":"TAXI-TEL Standplatztelefon Betriebs GmbH",
    "wof:placetype":"venue"
},
  "geometry": {"coordinates":[16.3008956909,48.1852798462],"type":"Point"}
}