{
  "type": "Feature",
  "properties": {
    "addr:full":"Badstr 48 Eggersdorf Steiermark 8063",
    "addr:housenumber":"48",
    "addr:postcode":"8063",
    "addr:street":"Badstr",
    "iso:country":"AT",
    "sg:address":"Badstr 48",
    "sg:city":"Eggersdorf",
    "sg:orig_category":"Garten- U Landschaftsgestaltung",
    "sg:phone":"+43 4331 172442",
    "sg:postcode":"8063",
    "sg:province":"Steiermark",
    "wof:name":"Painer Peter Gartenparadies",
    "wof:placetype":"venue"
},
  "geometry": {"coordinates":[15.5886697769,47.1139793396],"type":"Point"}
}