{
  "type": "Feature",
  "properties": {
    "iso:country":"AT",
    "sg:address":"Hauptstr 9",
    "sg:city":"Hirm",
    "sg:orig_category":"Banken U Sparkassen",
    "sg:phone":"+43 2687 47266",
    "sg:postcode":"7024",
    "sg:province":"Burgenland",
    "wof:name":"Commerzialbank Mattersburg i Burgenland AG",
    "wof:placetype":"venue"
},
  "geometry": {"coordinates":[16.4556922913,47.7873153687],"type":"Point"}
}