{
  "type": "Feature",
  "properties": {
    "addr:full":"M\u00fcnzgrabenstr 174 Graz Steiermark 8010",
    "addr:housenumber":"174",
    "addr:postcode":"8010",
    "iso:country":"AT",
    "sg:address":"M\u00fcnzgrabenstr 174",
    "sg:city":"Graz",
    "sg:orig_category":"Hauskrankenpflege / Heimhilfe",
    "sg:phone":"+43 316 462075",
    "sg:postcode":"8010",
    "sg:province":"Steiermark",
    "wof:name":"Caritas der Di\u00f6zese Graz-Seckau",
    "wof:placetype":"venue"
},
  "geometry": {"coordinates":[15.4431800842,47.0685653687],"type":"Point"}
}