{
  "type": "Feature",
  "properties": {
    "iso:country":"AT",
    "sg:address":"Herbeckstr 86/4",
    "sg:city":"Wien",
    "sg:orig_category":"Optische Artikel",
    "sg:phone":"+43 1 3284705",
    "sg:postcode":"1180",
    "sg:province":"Wien",
    "wof:name":"Maghakian & Co OEG",
    "wof:placetype":"venue"
},
  "geometry": {"coordinates":[16.3190116882,48.2325057983],"type":"Point"}
}