{
  "type": "Feature",
  "properties": {
    "addr:full":"Josef Mohr-Weg 1 Wagrain Salzburg 5602",
    "addr:housenumber":"1",
    "addr:postcode":"5602",
    "addr:street":"Josef Mohr-Weg;Salzburg",
    "iso:country":"AT",
    "sg:address":"Josef Mohr-Weg 1",
    "sg:city":"Wagrain",
    "sg:orig_category":"Non-Classified Establishments",
    "sg:phone":"+43 6413 8214",
    "sg:postcode":"5602",
    "sg:province":"Salzburg",
    "wof:name":"Pfarramt",
    "wof:placetype":"venue"
},
  "geometry": {"coordinates":[13.3038883209,47.3331718445],"type":"Point"}
}