{
  "type": "Feature",
  "properties": {
    "iso:country":"AT",
    "sg:address":"Mariatroster Strasse 172 ",
    "sg:city":"Mariatrost",
    "sg:classifiers":[
        {
            "category":"Building & Trades",
            "subcategory":"Plumbing",
            "type":"Services"
        }
    ],
    "sg:phone":"+43 316 391508",
    "sg:postcode":"8044",
    "sg:province":"Steiermark",
    "sg:tags":[
        "supraregional",
        "gas"
    ],
    "wof:name":"Sanit\u00e4r - Heizung - Egger GmbH",
    "wof:placetype":"venue"
},
  "geometry": {"coordinates":[15.48250103,47.1022377014],"type":"Point"}
}