{
  "type": "Feature",
  "properties": {
    "addr:full":"Nr 14 Gallizien K\u00e4rnten 9132",
    "addr:postcode":"9132",
    "addr:street":"Nr 14;Kaernten",
    "iso:country":"AT",
    "sg:address":"Nr 14",
    "sg:city":"Gallizien",
    "sg:orig_category":"Holzwaren",
    "sg:phone":"+43 4221 2009",
    "sg:postcode":"9132",
    "sg:province":"K\u00e4rnten",
    "wof:name":"Silvex WarenhandelsgesmbH",
    "wof:placetype":"venue"
},
  "geometry": {"coordinates":[14.5081481934,46.5587844849],"type":"Point"}
}