{
  "type": "Feature",
  "properties": {
    "addr:full":"Garteng 24 Enzesfeld-Lindabrunn Nieder\u00f6sterreich 2551",
    "addr:housenumber":"24",
    "addr:postcode":"2551",
    "addr:street":"Garteng;Niederoesterreich",
    "iso:country":"AT",
    "sg:address":"Garteng 24",
    "sg:city":"Enzesfeld-Lindabrunn",
    "sg:orig_category":"Non-Classified Establishments",
    "sg:phone":"+43 2256 81281",
    "sg:postcode":"2551",
    "sg:province":"Nieder\u00f6sterreich",
    "wof:name":"Pfarramt",
    "wof:placetype":"venue"
},
  "geometry": {"coordinates":[16.1761207581,47.9199562073],"type":"Point"}
}