{
  "type": "Feature",
  "properties": {
    "addr:full":"Pottendorfer Str 12 Wiener Neustadt Nieder\u00f6sterreich 2700",
    "addr:postcode":"2700",
    "addr:street":"Str 12",
    "iso:country":"AT",
    "sg:address":"Pottendorfer Str 12",
    "sg:city":"Wiener Neustadt",
    "sg:orig_category":"Tabaktrafiken",
    "sg:phone":"+43 4326 2288045",
    "sg:postcode":"2700",
    "sg:province":"Nieder\u00f6sterreich",
    "wof:name":"Langer Franz",
    "wof:placetype":"venue"
},
  "geometry": {"coordinates":[16.2481613159,47.823097229],"type":"Point"}
}