{
  "type": "Feature",
  "properties": {
    "addr:full":"Heizwerkstr 6A Wien Wien 1230",
    "addr:housenumber":"6a",
    "addr:postcode":"1230",
    "addr:street":"Heizwerkstr",
    "iso:country":"AT",
    "sg:address":"Heizwerkstr 6A",
    "sg:city":"Wien",
    "sg:classifiers":[
        {
            "category":"Manufacturing",
            "subcategory":"Signs",
            "type":"Manufacturing & Wholesale Goods"
        }
    ],
    "sg:phone":"+43 1 6175599110",
    "sg:postcode":"1230",
    "sg:province":"Wien",
    "sg:tags":[
        "display"
    ],
    "wof:name":"ACTION.DISPLAY VertriebsgesmbH",
    "wof:placetype":"venue"
},
  "geometry": {"coordinates":[16.3642082214,48.1385993958],"type":"Point"}
}