{
  "type": "Feature",
  "properties": {
    "iso:country":"AT",
    "sg:address":"Hauptstr 82",
    "sg:city":"Lannach",
    "sg:orig_category":"Bestattungsunternehmen",
    "sg:phone":"+43 3136 81671",
    "sg:postcode":"8502",
    "sg:province":"Steiermark",
    "wof:name":"Pinter GesmbH",
    "wof:placetype":"venue"
},
  "geometry": {"coordinates":[15.316570282,46.9398117065],"type":"Point"}
}