{
  "type": "Feature",
  "properties": {
    "addr:full":"Gainfeldweg 25 Bischofshofen Salzburg 5500",
    "addr:housenumber":"25",
    "addr:postcode":"5500",
    "addr:street":"Gainfeldweg;Salzburg",
    "iso:country":"AT",
    "sg:address":"Gainfeldweg 25",
    "sg:city":"Bischofshofen",
    "sg:orig_category":"Tischlereien",
    "sg:phone":"+43 6462 8180",
    "sg:postcode":"5500",
    "sg:province":"Salzburg",
    "wof:name":"Kreuzberger Wolfgang",
    "wof:placetype":"venue"
},
  "geometry": {"coordinates":[13.2064800262,47.4165611267],"type":"Point"}
}