{
  "type": "Feature",
  "properties": {
    "iso:country":"AT",
    "sg:address":"Erdbergstr 41",
    "sg:city":"Wien",
    "sg:orig_category":"Restaurants: Chinesisch",
    "sg:phone":"+43 1 7121596",
    "sg:postcode":"1030",
    "sg:province":"Wien",
    "wof:name":"China-Restaurant Ping",
    "wof:placetype":"venue"
},
  "geometry": {"coordinates":[16.3979892731,48.2007217407],"type":"Point"}
}