{
  "type": "Feature",
  "properties": {
    "addr:full":"Ungarstr 6 Feldbach Steiermark 8330",
    "addr:housenumber":"6",
    "addr:postcode":"8330",
    "addr:street":"Ungarstr",
    "iso:country":"AT",
    "sg:address":"Ungarstr 6",
    "sg:city":"Feldbach",
    "sg:orig_category":"Biologische Produkte",
    "sg:phone":"+43 3152 6218",
    "sg:postcode":"8330",
    "sg:province":"Steiermark",
    "wof:name":"Naturkost Landsch\u00fctzer",
    "wof:placetype":"venue"
},
  "geometry": {"coordinates":[15.8901567459,46.9513816833],"type":"Point"}
}