{
  "type": "Feature",
  "properties": {
    "addr:full":"Linzer Str 167 Wels Ober\u00f6sterreich 4600",
    "addr:housenumber":"167",
    "addr:postcode":"4600",
    "addr:street":"Linzer Str;Oberoesterreich",
    "iso:country":"AT",
    "sg:address":"Linzer Str 167",
    "sg:city":"Wels",
    "sg:orig_category":"Autohandel",
    "sg:phone":"+43 7242 45673",
    "sg:postcode":"4600",
    "sg:province":"Ober\u00f6sterreich",
    "wof:name":"Bamminger Kraftfahrzeuge GesmbH",
    "wof:placetype":"venue"
},
  "geometry": {"coordinates":[14.050699234,48.169883728],"type":"Point"}
}