{
  "type": "Feature",
  "properties": {
    "addr:full":"Traunleiten 8a Traun Ober\u00f6sterreich 4050",
    "addr:housenumber":"8a",
    "addr:postcode":"4050",
    "addr:street":"Traunleiten",
    "iso:country":"AT",
    "sg:address":"Traunleiten 8a",
    "sg:city":"Traun",
    "sg:orig_category":"Bauunternehmen",
    "sg:phone":"+43 7229 732650",
    "sg:postcode":"4050",
    "sg:province":"Ober\u00f6sterreich",
    "wof:name":"Gebr\u00fcder Lang & Co BaugesmbH & Co KG",
    "wof:placetype":"venue"
},
  "geometry": {"coordinates":[14.2328777313,48.2283248901],"type":"Point"}
}