{
  "type": "Feature",
  "properties": {
    "iso:country":"AT",
    "sg:address":"Sonnleitn 14",
    "sg:city":"Pierbach",
    "sg:orig_category":"Biologische Produkte",
    "sg:phone":"+43 7267 8389",
    "sg:postcode":"4282",
    "sg:province":"Ober\u00f6sterreich",
    "wof:name":"Bio Frischdienst Braun Andrea",
    "wof:placetype":"venue"
},
  "geometry": {"coordinates":[14.7757263184,48.3511886597],"type":"Point"}
}