{
  "type": "Feature",
  "properties": {
    "iso:country":"AT",
    "sg:address":"Schwarzlm\u00fcllerweg 1a",
    "sg:city":"Stadl-Paura",
    "sg:orig_category":"Werbeagenturen",
    "sg:phone":"+43 7245 32980",
    "sg:postcode":"4651",
    "sg:province":"Ober\u00f6sterreich",
    "wof:name":"Werbeagentur Echo Park - Thomas Resch",
    "wof:placetype":"venue"
},
  "geometry": {"coordinates":[13.8692007065,48.086391449],"type":"Point"}
}