{
  "type": "Feature",
  "properties": {
    "addr:full":"Schwarzlm\u00fcllerweg 1a Stadl-Paura Ober\u00f6sterreich 4651",
    "addr:housenumber":"1a",
    "addr:postcode":"4651",
    "addr:street":"Schwarzlmuellerweg",
    "iso:country":"AT",
    "sg:address":"Schwarzlm\u00fcllerweg 1a",
    "sg:city":"Stadl-Paura",
    "sg:orig_category":"Werbeagenturen",
    "sg:phone":"+43 7245 32980",
    "sg:postcode":"4651",
    "sg:province":"Ober\u00f6sterreich",
    "wof:name":"Werbeagentur Echo Park - Thomas Resch",
    "wof:placetype":"venue"
},
  "geometry": {"coordinates":[13.8692007065,48.086391449],"type":"Point"}
}