{
  "type": "Feature",
  "properties": {
    "addr:full":"Kotzinastr 9 Linz Ober\u00f6sterreich 4030",
    "addr:housenumber":"9",
    "addr:postcode":"4030",
    "addr:street":"Kotzinastr",
    "iso:country":"AT",
    "sg:address":"Kotzinastr 9",
    "sg:city":"Linz",
    "sg:orig_category":"Automatisierungstechnik",
    "sg:phone":"+43 732 389090",
    "sg:postcode":"4030",
    "sg:province":"Ober\u00f6sterreich",
    "wof:name":"ROCKWELL Automation GesmbH",
    "wof:placetype":"venue"
},
  "geometry": {"coordinates":[14.2822799683,48.2410087585],"type":"Point"}
}