{
  "type": "Feature",
  "properties": {
    "iso:country":"AT",
    "sg:address":"Landstr 49",
    "sg:city":"Linz",
    "sg:classifiers":[
        {
            "category":"Restaurant",
            "type":"Food & Drink"
        }
    ],
    "sg:phone":"+43 732 773165",
    "sg:postcode":"4020",
    "sg:province":"Ober\u00f6sterreich",
    "wof:name":"JOSEF das Stadtbr\u00e4u",
    "wof:placetype":"venue"
},
  "geometry": {"coordinates":[14.2913150787,48.2994270325],"type":"Point"}
}