{
  "type": "Feature",
  "properties": {
    "iso:country":"AT",
    "sg:address":"Eduard-R\u00f6sch-Str 1",
    "sg:city":"Stockerau",
    "sg:orig_category":"Friseure U Frisiersalons",
    "sg:phone":"+43 4322 6662019",
    "sg:postcode":"2000",
    "sg:province":"Nieder\u00f6sterreich",
    "wof:name":"Steffal Traude",
    "wof:placetype":"venue"
},
  "geometry": {"coordinates":[16.2186717987,48.3866767883],"type":"Point"}
}