{
  "type": "Feature",
  "properties": {
    "addr:full":"Firmiang 33 Wien Wien 1130",
    "addr:housenumber":"33",
    "addr:postcode":"1130",
    "addr:street":"Firmiang",
    "iso:country":"AT",
    "sg:address":"Firmiang 33",
    "sg:city":"Wien",
    "sg:classifiers":[
        {
            "category":"Professional",
            "subcategory":"Computer Services",
            "type":"Services"
        }
    ],
    "sg:phone":"+43 676 6067959",
    "sg:postcode":"1130",
    "sg:province":"Wien",
    "sg:tags":[
        "software"
    ],
    "wof:name":"Steffek EDV-Softwareentwicklung",
    "wof:placetype":"venue"
},
  "geometry": {"coordinates":[16.2678070068,48.1903533936],"type":"Point"}
}