{
  "type": "Feature",
  "properties": {
    "iso:country":"AT",
    "sg:address":"Richard-Wagner-Pl 17",
    "sg:city":"Wien",
    "sg:classifiers":[
        {
            "category":"Restaurant",
            "type":"Food & Drink"
        }
    ],
    "sg:phone":"+43 1 4856757",
    "sg:postcode":"1160",
    "sg:province":"Wien",
    "sg:tags":[
        "pizzeria"
    ],
    "wof:name":"Filippo & Rafaele",
    "wof:placetype":"venue"
},
  "geometry": {"coordinates":[16.3276481628,48.2104110718],"type":"Point"}
}