{
  "type": "Feature",
  "properties": {
    "addr:full":"Gries 9 Taufkirchen an der Trattnach Ober\u00f6sterreich 4715",
    "addr:housenumber":"9",
    "addr:postcode":"4715",
    "addr:street":"Gries",
    "iso:country":"AT",
    "sg:address":"Gries 9",
    "sg:city":"Taufkirchen an der Trattnach",
    "sg:orig_category":"Brunnen U Brunnenbau",
    "sg:phone":"+43 4377 3440400",
    "sg:postcode":"4715",
    "sg:province":"Ober\u00f6sterreich",
    "wof:name":"Wagner GesmbH & Co KG",
    "wof:placetype":"venue"
},
  "geometry": {"coordinates":[13.7612895966,48.2477607727],"type":"Point"}
}