{
  "type": "Feature",
  "properties": {
    "addr:full":"Nr 37 M\u00fchldorf Nieder\u00f6sterreich 3622",
    "addr:postcode":"3622",
    "addr:street":"Nr 37 Muehldorf",
    "iso:country":"AT",
    "sg:address":"Nr 37",
    "sg:city":"M\u00fchldorf",
    "sg:orig_category":"Juweliere, Gold- U Silberschmiede",
    "sg:phone":"+43 2713 8290",
    "sg:postcode":"3622",
    "sg:province":"Nieder\u00f6sterreich",
    "wof:name":"Kersch Josef",
    "wof:placetype":"venue"
},
  "geometry": {"coordinates":[15.3469820023,48.3728370667],"type":"Point"}
}