{
  "type": "Feature",
  "properties": {
    "addr:full":"Obere Bahnstr 61 Graz Steiermark 8010",
    "addr:housenumber":"61",
    "addr:postcode":"8010",
    "addr:street":"Obere Bahnstr",
    "iso:country":"AT",
    "sg:address":"Obere Bahnstr 61",
    "sg:city":"Graz",
    "sg:orig_category":"Sprachschulen U -Unterricht",
    "sg:phone":"+43 4331 640760023",
    "sg:postcode":"8010",
    "sg:province":"Steiermark",
    "wof:name":"SMS - Sprache mit Spass",
    "wof:placetype":"venue"
},
  "geometry": {"coordinates":[15.4430809021,47.0575141907],"type":"Point"}
}