{
  "type": "Feature",
  "properties": {
    "iso:country":"AT",
    "sg:address":"Ghegahof 6",
    "sg:city":"Schwanenstadt",
    "sg:orig_category":"Elektroinstallationsunternehmen",
    "sg:phone":"+43 4376 7375262",
    "sg:postcode":"4690",
    "sg:province":"Ober\u00f6sterreich",
    "wof:name":"Elektro Stumpfl",
    "wof:placetype":"venue"
},
  "geometry": {"coordinates":[13.7791290283,48.0603942871],"type":"Point"}
}