{
  "type": "Feature",
  "properties": {
    "addr:full":"Puchbacher Str 204 Maria Lankowitz Steiermark 8591",
    "addr:housenumber":"204",
    "addr:postcode":"8591",
    "addr:street":"Str",
    "iso:country":"AT",
    "sg:address":"Puchbacher Str 204",
    "sg:city":"Maria Lankowitz",
    "sg:orig_category":"Gemeinden",
    "sg:phone":"+43 3144 34840",
    "sg:postcode":"8591",
    "sg:province":"Steiermark",
    "wof:name":"Marktgemeinde Maria Lankowitz",
    "wof:placetype":"venue"
},
  "geometry": {"coordinates":[15.0545196533,47.0492362976],"type":"Point"}
}