{
  "type": "Feature",
  "properties": {
    "iso:country":"AT",
    "sg:address":"Rosenau 2a",
    "sg:city":"Reutte",
    "sg:classifiers":[
        {
            "category":"Taxi",
            "type":"Transportation"
        }
    ],
    "sg:phone":"+43 4356 7262300",
    "sg:postcode":"6600",
    "sg:province":"Tirol",
    "sg:tags":[
        "personentransporte",
        "u"
    ],
    "wof:name":"Taxi Hornstein",
    "wof:placetype":"venue"
},
  "geometry": {"coordinates":[10.7185935974,47.4889183044],"type":"Point"}
}