{
  "type": "Feature",
  "properties": {
    "iso:country":"AT",
    "sg:city":"Tulfes",
    "sg:orig_category":"Bergbahnen",
    "sg:phone":"+43 4352 2378321",
    "sg:postcode":"6075",
    "sg:province":"Tirol",
    "wof:name":"Glungezerbahn GesmbH & Co KG",
    "wof:placetype":"venue"
},
  "geometry": {"coordinates":[11.5300703049,47.2568893433],"type":"Point"}
}