{
  "type": "Feature",
  "properties": {
    "iso:country":"AT",
    "sg:address":"Nr 60",
    "sg:city":"Yspertal",
    "sg:orig_category":"Telefonmarketing",
    "sg:phone":"+43 7415 20024",
    "sg:postcode":"3683",
    "sg:province":"Nieder\u00f6sterreich",
    "wof:name":"PIFA - Center",
    "wof:placetype":"venue"
},
  "geometry": {"coordinates":[15.065489769,48.282119751],"type":"Point"}
}