{
  "type": "Feature",
  "properties": {
    "addr:full":"Griesg 9 Klagenfurt K\u00e4rnten 9020",
    "addr:housenumber":"9",
    "addr:postcode":"9020",
    "addr:street":"Griesg;Kaernten",
    "iso:country":"AT",
    "sg:address":"Griesg 9",
    "sg:city":"Klagenfurt",
    "sg:orig_category":"Segelmachereien",
    "sg:phone":"+43 463 212930",
    "sg:postcode":"9020",
    "sg:province":"K\u00e4rnten",
    "wof:name":"Jessenig Robert",
    "wof:placetype":"venue"
},
  "geometry": {"coordinates":[14.3274202347,46.6254196167],"type":"Point"}
}