{
  "type": "Feature",
  "properties": {
    "iso:country":"AT",
    "sg:address":"Falkensteinstr 1",
    "sg:city":"Hofkirchen im M\u00fchlkreis",
    "sg:orig_category":"Autohandel",
    "sg:phone":"+43 4372 852180",
    "sg:postcode":"4142",
    "sg:province":"Ober\u00f6sterreich",
    "wof:name":"Kirchberger GesmbH",
    "wof:placetype":"venue"
},
  "geometry": {"coordinates":[13.8062992096,48.4843406677],"type":"Point"}
}