{
  "type": "Feature",
  "properties": {
    "addr:full":"Hauptstr 115 Alland Nieder\u00f6sterreich 2534",
    "addr:housenumber":"115",
    "addr:postcode":"2534",
    "addr:street":"Hauptstr",
    "iso:country":"AT",
    "sg:address":"Hauptstr 115",
    "sg:city":"Alland",
    "sg:orig_category":"Ergotherapie",
    "sg:phone":"+43 4367 67754566",
    "sg:postcode":"2534",
    "sg:province":"Nieder\u00f6sterreich",
    "wof:name":"Petershofer Sonja Dipl-ET",
    "wof:placetype":"venue"
},
  "geometry": {"coordinates":[16.0765991211,48.0571708679],"type":"Point"}
}