{
  "type": "Feature",
  "properties": {
    "addr:full":"Penknerg 3 Wilhelmsburg an der Traisen Nieder\u00f6sterreich 3150",
    "addr:housenumber":"3",
    "addr:postcode":"3150",
    "addr:street":"Penknerg",
    "iso:country":"AT",
    "sg:address":"Penknerg 3",
    "sg:city":"Wilhelmsburg an der Traisen",
    "sg:orig_category":"Sonderschulen",
    "sg:phone":"+43 2746 231544",
    "sg:postcode":"3150",
    "sg:province":"Nieder\u00f6sterreich",
    "wof:name":"Allgemeine Sonderschule",
    "wof:placetype":"venue"
},
  "geometry": {"coordinates":[15.6558494568,48.0672073364],"type":"Point"}
}