{
  "type": "Feature",
  "properties": {
    "addr:full":"Ferdinand-Hanusch-Str 17 Leoben Steiermark 8700",
    "addr:housenumber":"17",
    "addr:postcode":"8700",
    "addr:street":"Ferdinand-Hanusch-Str",
    "iso:country":"AT",
    "sg:address":"Ferdinand-Hanusch-Str 17",
    "sg:city":"Leoben",
    "sg:orig_category":"Bekleidung / Einzelhandel",
    "sg:phone":"+43 4338 4221226",
    "sg:postcode":"8700",
    "sg:province":"Steiermark",
    "wof:name":"Takko ModeMarkt GmbH",
    "wof:placetype":"venue"
},
  "geometry": {"coordinates":[15.0892753601,47.3706665039],"type":"Point"}
}