{
  "type": "Feature",
  "properties": {
    "addr:full":"Nr 43 Ligist Steiermark 8563",
    "addr:postcode":"8563",
    "addr:street":"Nr",
    "iso:country":"AT",
    "sg:address":"Nr 43",
    "sg:city":"Ligist",
    "sg:orig_category":"Non-Classified Establishments",
    "sg:phone":"+43 3143 2255",
    "sg:postcode":"8563",
    "sg:province":"Steiermark",
    "wof:name":"Pfarramt",
    "wof:placetype":"venue"
},
  "geometry": {"coordinates":[15.2067432404,46.9937019348],"type":"Point"}
}