{
  "type": "Feature",
  "properties": {
    "addr:full":"Retzhofer Str 12 Leibnitz Steiermark 8430",
    "addr:postcode":"8430",
    "addr:street":"Str 12;Steiermark",
    "iso:country":"AT",
    "sg:address":"Retzhofer Str 12",
    "sg:city":"Leibnitz",
    "sg:classifiers":[
        {
            "category":"Restaurant",
            "type":"Food & Drink"
        }
    ],
    "sg:phone":"+43 3452 73880",
    "sg:postcode":"8430",
    "sg:province":"Steiermark",
    "sg:tags":[
        "pizzeria"
    ],
    "wof:name":"Jartschitsch Johann",
    "wof:placetype":"venue"
},
  "geometry": {"coordinates":[15.54920578,46.7823066711],"type":"Point"}
}