{
  "type": "Feature",
  "properties": {
    "addr:full":"Siebenbrunneng 22 Wien Wien 1050",
    "addr:housenumber":"22",
    "addr:postcode":"1050",
    "addr:street":"Siebenbrunneng",
    "iso:country":"AT",
    "sg:address":"Siebenbrunneng 22",
    "sg:city":"Wien",
    "sg:orig_category":"Installationsunternehmen",
    "sg:phone":"+43 1 5441633",
    "sg:postcode":"1050",
    "sg:province":"Wien",
    "wof:name":"Steppi & Co",
    "wof:placetype":"venue"
},
  "geometry": {"coordinates":[16.3584403992,48.1873931885],"type":"Point"}
}