{
  "type": "Feature",
  "properties": {
    "addr:full":"M\u00fchlbachstr 35 Wilhering Ober\u00f6sterreich 4073",
    "addr:housenumber":"35",
    "addr:postcode":"4073",
    "addr:street":"Muehlbachstr",
    "iso:country":"AT",
    "sg:address":"M\u00fchlbachstr 35",
    "sg:city":"Wilhering",
    "sg:orig_category":"Pensionen / Privatzimmer",
    "sg:phone":"+43 7226 2238",
    "sg:postcode":"4073",
    "sg:province":"Ober\u00f6sterreich",
    "wof:name":"Wasmayer Josef und Frieda",
    "wof:placetype":"venue"
},
  "geometry": {"coordinates":[14.1893806458,48.3233795166],"type":"Point"}
}