{
  "type": "Feature",
  "properties": {
    "addr:full":"Hauptstr 8 Radenthein K\u00e4rnten 9545",
    "addr:housenumber":"8",
    "addr:postcode":"9545",
    "addr:street":"Hauptstr;Kaernten",
    "iso:country":"AT",
    "sg:address":"Hauptstr 8",
    "sg:city":"Radenthein",
    "sg:classifiers":[
        {
            "category":"Internet Cafe",
            "subcategory":"None",
            "type":"Food & Drink"
        }
    ],
    "sg:phone":"+43 4342 4629000",
    "sg:postcode":"9545",
    "sg:province":"K\u00e4rnten",
    "wof:name":"Hompagesparadies",
    "wof:placetype":"venue"
},
  "geometry": {"coordinates":[13.7073602676,46.8011398315],"type":"Point"}
}