{
  "type": "Feature",
  "properties": {
    "addr:full":"Rathstr 44-46 Wien Wien 1190",
    "addr:postcode":"44-46;1190",
    "iso:country":"AT",
    "sg:address":"Rathstr 44-46",
    "sg:city":"Wien",
    "sg:orig_category":"Heurigen / Buschenschank",
    "sg:phone":"+43 1 4402335",
    "sg:postcode":"1190",
    "sg:province":"Wien",
    "wof:name":"Wolff Heuriger",
    "wof:placetype":"venue"
},
  "geometry": {"coordinates":[16.3030357361,48.2510719299],"type":"Point"}
}