{
  "type": "Feature",
  "properties": {
    "addr:full":"Linzer Str 34 Windischgarsten Ober\u00f6sterreich 4580",
    "addr:housenumber":"34",
    "addr:postcode":"4580",
    "addr:street":"Linzer Str",
    "iso:country":"AT",
    "sg:address":"Linzer Str 34",
    "sg:city":"Windischgarsten",
    "sg:orig_category":"Lebensmittel / Einzelhandel",
    "sg:phone":"+43 4375 6220565",
    "sg:postcode":"4580",
    "sg:province":"Ober\u00f6sterreich",
    "wof:name":"Billa AG",
    "wof:placetype":"venue"
},
  "geometry": {"coordinates":[14.3216514587,47.7224159241],"type":"Point"}
}