{
  "type": "Feature",
  "properties": {
    "addr:full":"M\u00fcnzgrabenstrasse 92 Graz Steiermark 8010",
    "addr:housenumber":"92",
    "addr:postcode":"8010",
    "addr:street":"Muenzgrabenstrasse",
    "iso:country":"AT",
    "sg:address":"M\u00fcnzgrabenstrasse 92",
    "sg:city":"Graz",
    "sg:classifiers":[
        {
            "category":"Building & Trades",
            "subcategory":"Construction",
            "type":"Services"
        }
    ],
    "sg:phone":"+43 316 831040",
    "sg:postcode":"8010",
    "sg:province":"Steiermark",
    "sg:tags":[
        "interior",
        "work"
    ],
    "sg:website":"bau-mein-haus.at",
    "wof:name":"Bau mein Haus GmbH",
    "wof:placetype":"venue"
},
  "geometry": {"coordinates":[15.4431800842,47.0685653687],"type":"Point"}
}