{
  "type": "Feature",
  "properties": {
    "addr:full":"Marchfeldstr 14 Wien Wien 1200",
    "addr:housenumber":"14",
    "addr:postcode":"1200",
    "addr:street":"Marchfeldstr",
    "iso:country":"AT",
    "sg:address":"Marchfeldstr 14",
    "sg:city":"Wien",
    "sg:orig_category":"Fleischhauereien",
    "sg:phone":"+43 1 3305179",
    "sg:postcode":"1200",
    "sg:province":"Wien",
    "wof:name":"Schirnhofer-Breisler GesmbH - Shop in Shop",
    "wof:placetype":"venue"
},
  "geometry": {"coordinates":[16.378950119,48.2426567078],"type":"Point"}
}