{
  "type": "Feature",
  "properties": {
    "addr:full":"Franz-Part-Str 2 Raabs an der Thaya Nieder\u00f6sterreich 3820",
    "addr:housenumber":"2",
    "addr:postcode":"3820",
    "addr:street":"Franz-Part-Str",
    "iso:country":"AT",
    "sg:address":"Franz-Part-Str 2",
    "sg:city":"Raabs an der Thaya",
    "sg:orig_category":"Feuerwehren",
    "sg:phone":"+43 2846 73082",
    "sg:postcode":"3820",
    "sg:province":"Nieder\u00f6sterreich",
    "wof:name":"Abschnittsfeuerwehrkommando Raabs",
    "wof:placetype":"venue"
},
  "geometry": {"coordinates":[15.4875059128,48.8517150879],"type":"Point"}
}