{
  "type": "Feature",
  "properties": {
    "addr:full":"Hauptstr 29 Winden am See Burgenland 7092",
    "addr:housenumber":"29",
    "addr:postcode":"7092",
    "addr:street":"Hauptstr",
    "iso:country":"AT",
    "sg:address":"Hauptstr 29",
    "sg:city":"Winden am See",
    "sg:orig_category":"Weine / Einzelhandel",
    "sg:phone":"+43 2160 7324",
    "sg:postcode":"7092",
    "sg:province":"Burgenland",
    "wof:name":"Weinbau & G\u00e4stezimmer Fam B\u00f6cskei",
    "wof:placetype":"venue"
},
  "geometry": {"coordinates":[16.7543106079,47.9500465393],"type":"Point"}
}