{
  "type": "Feature",
  "properties": {
    "addr:full":"Dekan-Ellensohnweg 3 Tschagguns Vorarlberg 6774",
    "addr:housenumber":"3",
    "addr:postcode":"6774",
    "addr:street":"Dekan-Ellensohnweg",
    "iso:country":"AT",
    "sg:address":"Dekan-Ellensohnweg 3",
    "sg:city":"Tschagguns",
    "sg:orig_category":"Reisen, Tourismusinfo",
    "sg:phone":"+43 4305 55672457",
    "sg:postcode":"6774",
    "sg:province":"Vorarlberg",
    "sg:website":"http://www.tiscover.com/schruns/tschagguns",
    "wof:name":"Tourismusinformation Schruns/Tschagguns",
    "wof:placetype":"venue"
},
  "geometry": {"coordinates":[9.9015293121,47.0776405334],"type":"Point"}
}