{
  "type": "Feature",
  "properties": {
    "addr:full":"Staig 13 Schwanenstadt Ober\u00f6sterreich 4690",
    "addr:housenumber":"13",
    "addr:postcode":"4690",
    "addr:street":"Staig",
    "iso:country":"AT",
    "sg:address":"Staig 13",
    "sg:city":"Schwanenstadt",
    "sg:classifiers":[
        {
            "category":"Home & Garden",
            "subcategory":"Hardware",
            "type":"Retail Goods"
        }
    ],
    "sg:phone":"+43 76734900",
    "sg:postcode":"4690",
    "sg:province":"Ober\u00f6sterreich",
    "sg:tags":[
        "steel",
        "stainless",
        "banister"
    ],
    "sg:website":"mega-technik.at",
    "wof:name":"Mega Technik Sonderanfertigungen in Edelstahl Rostfrei",
    "wof:placetype":"venue"
},
  "geometry": {"coordinates":[13.7819442749,48.0625152588],"type":"Point"}
}