{
  "type": "Feature",
  "properties": {
    "addr:full":"Malerwiese 2 Schwaz Tirol 6130",
    "addr:housenumber":"2",
    "addr:postcode":"6130",
    "addr:street":"Malerwiese;Tirol",
    "iso:country":"AT",
    "sg:address":"Malerwiese 2",
    "sg:city":"Schwaz",
    "sg:orig_category":"Elektroinstallationsunternehmen",
    "sg:phone":"+43 5242 611900",
    "sg:postcode":"6130",
    "sg:province":"Tirol",
    "wof:name":"Leitinger KG - Elektrotechnische Anlagen",
    "wof:placetype":"venue"
},
  "geometry": {"coordinates":[11.7271375656,47.3516807556],"type":"Point"}
}