{
  "type": "Feature",
  "properties": {
    "addr:full":"Nr 56 Pottenbrunn Nieder\u00f6sterreich 3140",
    "addr:postcode":"3140",
    "addr:street":"Nr;Niederoesterreich",
    "iso:country":"AT",
    "sg:address":"Nr 56",
    "sg:city":"Pottenbrunn",
    "sg:orig_category":"Feuerwehren",
    "sg:phone":"+43 2784 77156",
    "sg:postcode":"3140",
    "sg:province":"Nieder\u00f6sterreich",
    "wof:name":"Freiwillige Feuerwehr",
    "wof:placetype":"venue"
},
  "geometry": {"coordinates":[15.6931371689,48.2390174866],"type":"Point"}
}