{
  "type": "Feature",
  "properties": {
    "iso:country":"AT",
    "sg:address":"Staufenweg 51",
    "sg:city":"Hallein",
    "sg:orig_category":"Alternativtherapie",
    "sg:phone":"+43 4362 4576110",
    "sg:postcode":"5400",
    "sg:province":"Salzburg",
    "wof:name":"Klebel Georg und Simone - Praxis f\u00fcr Atemtherapie",
    "wof:placetype":"venue"
},
  "geometry": {"coordinates":[13.0771083832,47.7293434143],"type":"Point"}
}