{
  "type": "Feature",
  "properties": {
    "iso:country":"AT",
    "sg:address":"Kaiserstr 81",
    "sg:city":"Wien",
    "sg:orig_category":"Estriche",
    "sg:phone":"+43 1 5243955",
    "sg:postcode":"1070",
    "sg:province":"Wien",
    "wof:name":"Schwebler Mathias GesmbH",
    "wof:placetype":"venue"
},
  "geometry": {"coordinates":[16.3397388458,48.2048377991],"type":"Point"}
}