{
  "type": "Feature",
  "properties": {
    "addr:full":"Rasing 10 Mariazell Steiermark 8630",
    "addr:housenumber":"10",
    "addr:postcode":"8630",
    "addr:street":"Rasing",
    "iso:country":"AT",
    "sg:address":"Rasing 10",
    "sg:city":"Mariazell",
    "sg:orig_category":"Lebensmittel / Einzelhandel",
    "sg:phone":"+43 3882 2733",
    "sg:postcode":"8630",
    "sg:province":"Steiermark",
    "wof:name":"Spar-Markt Sommerer Maria",
    "wof:placetype":"venue"
},
  "geometry": {"coordinates":[15.3102750778,47.7630500793],"type":"Point"}
}