{
  "type": "Feature",
  "properties": {
    "iso:country":"AT",
    "sg:address":"Franz-Martin-Str 22/7",
    "sg:city":"Salzburg",
    "sg:orig_category":"Gerichtsdolmetscher",
    "sg:phone":"+43 664 1743082",
    "sg:postcode":"5020",
    "sg:province":"Salzburg",
    "wof:name":"Kovacevic Mirjana Mag",
    "wof:placetype":"venue"
},
  "geometry": {"coordinates":[13.0318250656,47.8157539368],"type":"Point"}
}