{
  "type": "Feature",
  "properties": {
    "addr:full":"Obere Hauptstr 8 Sieggraben Burgenland 7223",
    "addr:housenumber":"8",
    "addr:postcode":"sieggraben;7223",
    "addr:street":"Obere Hauptstr",
    "iso:country":"AT",
    "sg:address":"Obere Hauptstr 8",
    "sg:city":"Sieggraben",
    "sg:orig_category":"Gemeinden",
    "sg:phone":"+43 2621 2200",
    "sg:postcode":"7223",
    "sg:province":"Burgenland",
    "wof:name":"Gemeindeamt Sieggraben",
    "wof:placetype":"venue"
},
  "geometry": {"coordinates":[16.379535675,47.650138855],"type":"Point"}
}