{
  "type": "Feature",
  "properties": {
    "addr:full":"Birkenhain 3 Lutzmannsburg Burgenland 7361",
    "addr:housenumber":"3",
    "addr:postcode":"7361",
    "addr:street":"Birkenhain",
    "iso:country":"AT",
    "sg:address":"Birkenhain 3",
    "sg:city":"Lutzmannsburg",
    "sg:orig_category":"Appartements / Ferienwohnungen",
    "sg:phone":"+43 664 1422481",
    "sg:postcode":"7361",
    "sg:province":"Burgenland",
    "wof:name":"Huber Rita",
    "wof:placetype":"venue"
},
  "geometry": {"coordinates":[16.631269455,47.4627494812],"type":"Point"}
}