{
  "type": "Feature",
  "properties": {
    "addr:full":"Bruck 39 Peuerbach Ober\u00f6sterreich 4722",
    "addr:housenumber":"39",
    "addr:postcode":"4722",
    "addr:street":"Bruck",
    "iso:country":"AT",
    "sg:address":"Bruck 39",
    "sg:city":"Peuerbach",
    "sg:classifiers":[
        {
            "category":"Structure",
            "subcategory":"Office Building",
            "type":"Public Place"
        }
    ],
    "sg:phone":"+43 7276 24150",
    "sg:postcode":"4722",
    "sg:province":"Ober\u00f6sterreich",
    "sg:tags":[
        "brick",
        "ceiling",
        "module"
    ],
    "sg:website":"eder.co.at",
    "wof:name":"Ziegelwerk Eder GmbH & Co KG",
    "wof:placetype":"venue"
},
  "geometry": {"coordinates":[13.7751941681,48.3219184875],"type":"Point"}
}