{
  "type": "Feature",
  "properties": {
    "addr:full":"Au 17 St. Wolfgang im Salzkammergut Ober\u00f6sterreich 5360",
    "addr:housenumber":"17",
    "addr:postcode":"5360",
    "addr:street":"Au",
    "iso:country":"AT",
    "sg:address":"Au 17",
    "sg:city":"St. Wolfgang im Salzkammergut",
    "sg:orig_category":"Appartements / Ferienwohnungen",
    "sg:phone":"+43 6138 2577",
    "sg:postcode":"5360",
    "sg:province":"Ober\u00f6sterreich",
    "wof:name":"Ferienhof Hauslbauer Fam Hinterberger",
    "wof:placetype":"venue"
},
  "geometry": {"coordinates":[13.4568576813,47.7380256653],"type":"Point"}
}