{
  "type": "Feature",
  "properties": {
    "addr:full":"Birkenstr 27 Wei\u00dfkirchen an der Traun Ober\u00f6sterreich 4616",
    "addr:housenumber":"27",
    "addr:postcode":"4616",
    "addr:street":"Birkenstr",
    "iso:country":"AT",
    "sg:address":"Birkenstr 27",
    "sg:city":"Wei\u00dfkirchen an der Traun",
    "sg:orig_category":"Druckereien",
    "sg:phone":"+43 4372 43567130",
    "sg:postcode":"4616",
    "sg:province":"Ober\u00f6sterreich",
    "wof:name":"Tampotech",
    "wof:placetype":"venue"
},
  "geometry": {"coordinates":[14.1099224091,48.1681785583],"type":"Point"}
}