{
  "type": "Feature",
  "properties": {
    "addr:full":"Nr 124 Predlitz Steiermark 8863",
    "addr:postcode":"8863",
    "addr:street":"Nr 124",
    "iso:country":"AT",
    "sg:address":"Nr 124",
    "sg:city":"Predlitz",
    "sg:orig_category":"Autohandel",
    "sg:phone":"+43 4335 3483050",
    "sg:postcode":"8863",
    "sg:province":"Steiermark",
    "wof:name":"Prodinger Horst u Wilhelmine",
    "wof:placetype":"venue"
},
  "geometry": {"coordinates":[13.910150528,47.0715103149],"type":"Point"}
}