{
  "type": "Feature",
  "properties": {
    "addr:full":"Ringstr 34 Wels Ober\u00f6sterreich 4600",
    "addr:housenumber":"34",
    "addr:postcode":"4600",
    "addr:street":"Ringstr;Oberoesterreich",
    "iso:country":"AT",
    "sg:address":"Ringstr 34",
    "sg:city":"Wels",
    "sg:orig_category":"Bars-Cafes",
    "sg:phone":"+43 7242 210558",
    "sg:postcode":"4600",
    "sg:province":"Ober\u00f6sterreich",
    "wof:name":"point bars & restaurants",
    "wof:placetype":"venue"
},
  "geometry": {"coordinates":[14.0265541077,48.1590194702],"type":"Point"}
}