{
  "type": "Feature",
  "properties": {
    "addr:full":"Raiffeisenpl 1 Bruck an der Leitha Nieder\u00f6sterreich 2460",
    "addr:housenumber":"1",
    "addr:postcode":"2460",
    "addr:street":"Raiffeisenpl",
    "iso:country":"AT",
    "sg:address":"Raiffeisenpl 1",
    "sg:city":"Bruck an der Leitha",
    "sg:orig_category":"Banken U Sparkassen",
    "sg:phone":"+43 4321 62625550",
    "sg:postcode":"2460",
    "sg:province":"Nieder\u00f6sterreich",
    "wof:name":"Bankomat der Raiffeisenbank Bruck-Carnuntum reg GenmbH",
    "wof:placetype":"venue"
},
  "geometry": {"coordinates":[16.7775001526,48.0220108032],"type":"Point"}
}