{
  "type": "Feature",
  "properties": {
    "iso:country":"AT",
    "sg:address":"Wegscheider Str 72",
    "sg:city":"Linz",
    "sg:orig_category":"Badezimmer U Badezimmereinrichtungen",
    "sg:phone":"+43 4373 237170111",
    "sg:postcode":"4020",
    "sg:province":"Ober\u00f6sterreich",
    "wof:name":"FLIESE creativ - Marianne Kastner - Villeroy & Boch Badplanung",
    "wof:placetype":"venue"
},
  "geometry": {"coordinates":[14.2727479935,48.2583847046],"type":"Point"}
}