{
  "type": "Feature",
  "properties": {
    "iso:country":"AT",
    "sg:address":"Ambros-Rieder-G 32A",
    "sg:city":"Perchtoldsdorf",
    "sg:orig_category":"\u00c3\u201erzte / F Allgemeinmedizin",
    "sg:phone":"+43 1 8676791",
    "sg:postcode":"2380",
    "sg:province":"Nieder\u00f6sterreich",
    "wof:name":"Achtsnit Herbert Dr",
    "wof:placetype":"venue"
},
  "geometry": {"coordinates":[16.265838623,48.125705719],"type":"Point"}
}