{
  "type": "Feature",
  "properties": {
    "addr:full":"Dorfstr 15 Maishofen Salzburg 5751",
    "addr:housenumber":"15",
    "addr:postcode":"5751",
    "addr:street":"Dorfstr;Salzburg",
    "iso:country":"AT",
    "sg:address":"Dorfstr 15",
    "sg:city":"Maishofen",
    "sg:orig_category":"Lebensmittel / Einzelhandel",
    "sg:phone":"+43 6542 682350",
    "sg:postcode":"5751",
    "sg:province":"Salzburg",
    "wof:name":"ADEG-Markt Maishofen",
    "wof:placetype":"venue"
},
  "geometry": {"coordinates":[12.8088197708,47.3604621887],"type":"Point"}
}