{
  "type": "Feature",
  "properties": {
    "addr:full":"Blumeng 19 Wien Wien 1170",
    "addr:housenumber":"19",
    "addr:postcode":"1170",
    "addr:street":"Blumeng",
    "iso:country":"AT",
    "sg:address":"Blumeng 19",
    "sg:city":"Wien",
    "sg:orig_category":"Psychotherapie",
    "sg:phone":"+43 1 4051391",
    "sg:postcode":"1170",
    "sg:province":"Wien",
    "wof:name":"Eiletz Silvin Dr",
    "wof:placetype":"venue"
},
  "geometry": {"coordinates":[16.336933136,48.2200737],"type":"Point"}
}