{
  "type": "Feature",
  "properties": {
    "iso:country":"AT",
    "sg:address":"Slamastr 34",
    "sg:city":"Wien",
    "sg:orig_category":"Sicherheitstechnik",
    "sg:phone":"+43 1 610330",
    "sg:postcode":"1230",
    "sg:province":"Wien",
    "wof:name":"Mader + Kranl GesmbH & Co KG",
    "wof:placetype":"venue"
},
  "geometry": {"coordinates":[16.3426322937,48.1370429993],"type":"Point"}
}