{
  "type": "Feature",
  "properties": {
    "addr:full":"Mittlerer Markt 9 Aschbach Markt Nieder\u00f6sterreich 3361",
    "addr:housenumber":"9",
    "addr:postcode":"3361",
    "addr:street":"Mittlerer Markt",
    "iso:country":"AT",
    "sg:address":"Mittlerer Markt 9",
    "sg:city":"Aschbach Markt",
    "sg:orig_category":"Lebensmittel / Einzelhandel",
    "sg:phone":"+43 7476 77626",
    "sg:postcode":"3361",
    "sg:province":"Nieder\u00f6sterreich",
    "wof:name":"Spar-Markt Inh Johann Spendou",
    "wof:placetype":"venue"
},
  "geometry": {"coordinates":[14.7514019012,48.0723228455],"type":"Point"}
}