{
  "type": "Feature",
  "properties": {
    "iso:country":"AT",
    "sg:address":"Dragonerstr 44",
    "sg:city":"Wels",
    "sg:orig_category":"Friseure U Frisiersalons",
    "sg:phone":"+43 4372 42224000",
    "sg:postcode":"4600",
    "sg:province":"Ober\u00f6sterreich",
    "wof:name":"Bella Vita",
    "wof:placetype":"venue"
},
  "geometry": {"coordinates":[14.0104637146,48.1558265686],"type":"Point"}
}