{
  "type": "Feature",
  "properties": {
    "iso:country":"AT",
    "sg:address":"Linzer Str 32",
    "sg:city":"Marchtrenk",
    "sg:orig_category":"Nagelstudios",
    "sg:phone":"+43 664 4008820",
    "sg:postcode":"4614",
    "sg:province":"Ober\u00f6sterreich",
    "wof:name":"YOUR PERFECT NAILS Nagelstudio",
    "wof:placetype":"venue"
},
  "geometry": {"coordinates":[14.1142215729,48.1904983521],"type":"Point"}
}