{
  "type": "Feature",
  "properties": {
    "addr:full":"Edelwei\u00dfstr 14b Asten Ober\u00f6sterreich 4481",
    "addr:housenumber":"14b",
    "addr:postcode":"4481",
    "addr:street":"Edelweissstr",
    "iso:country":"AT",
    "sg:address":"Edelwei\u00dfstr 14b",
    "sg:city":"Asten",
    "sg:orig_category":"Abfallentsorgung U -Verwertung",
    "sg:phone":"+43 4372 2467488",
    "sg:postcode":"4481",
    "sg:province":"Ober\u00f6sterreich",
    "wof:name":"Altstoffsammelzentrum Asten",
    "wof:placetype":"venue"
},
  "geometry": {"coordinates":[14.4112443924,48.2195396423],"type":"Point"}
}