{
  "type": "Feature",
  "properties": {
    "addr:full":"Franz-Josef-Pl 3 Gmunden Ober\u00f6sterreich 4810",
    "addr:housenumber":"3",
    "addr:postcode":"4810",
    "addr:street":"Franz-Josef-Pl;Oberoesterreich",
    "iso:country":"AT",
    "sg:address":"Franz-Josef-Pl 3",
    "sg:city":"Gmunden",
    "sg:classifiers":[
        {
            "category":"Restaurant",
            "type":"Food & Drink"
        }
    ],
    "sg:phone":"+43 761274970",
    "sg:postcode":"4810",
    "sg:province":"Ober\u00f6sterreich",
    "sg:tags":[
        "pizzeria"
    ],
    "wof:name":"Pizzeria Valentino",
    "wof:placetype":"venue"
},
  "geometry": {"coordinates":[13.7976875305,47.9179115295],"type":"Point"}
}