{
  "type": "Feature",
  "properties": {
    "addr:full":"Subiacostr 11 Kremsm\u00fcnster Ober\u00f6sterreich 4550",
    "addr:housenumber":"11",
    "addr:postcode":"4550",
    "addr:street":"Subiacostr;Oberoesterreich",
    "iso:country":"AT",
    "sg:address":"Subiacostr 11",
    "sg:city":"Kremsm\u00fcnster",
    "sg:classifiers":[
        {
            "category":"Taxi",
            "type":"Transportation"
        }
    ],
    "sg:phone":"+43 664 4018266",
    "sg:postcode":"4550",
    "sg:province":"Ober\u00f6sterreich",
    "sg:tags":[
        "personentransporte",
        "u"
    ],
    "wof:name":"Katzenschlager Leopold Taxi-Krankentransport",
    "wof:placetype":"venue"
},
  "geometry": {"coordinates":[14.1215744019,48.0517997742],"type":"Point"}
}