{
  "type": "Feature",
  "properties": {
    "addr:full":"Obkircherg 43/7 Wien Wien 1190",
    "addr:housenumber":"43 / 7",
    "addr:postcode":"1190",
    "addr:street":"Obkircherg",
    "iso:country":"AT",
    "sg:address":"Obkircherg 43/7",
    "sg:city":"Wien",
    "sg:classifiers":[
        {
            "category":"Restaurant",
            "type":"Food & Drink"
        }
    ],
    "sg:phone":"+43 1 3284245",
    "sg:postcode":"1190",
    "sg:province":"Wien",
    "wof:name":"Dr\u00e4xler Bettina Dr",
    "wof:placetype":"venue"
},
  "geometry": {"coordinates":[16.3421535492,48.245300293],"type":"Point"}
}