{
  "type": "Feature",
  "properties": {
    "addr:full":"Nr 4 Grafenstein K\u00e4rnten 9131",
    "addr:postcode":"9131",
    "addr:street":"Nr;Kaernten",
    "iso:country":"AT",
    "sg:address":"Nr 4",
    "sg:city":"Grafenstein",
    "sg:classifiers":[
        {
            "category":"Home & Garden",
            "subcategory":"Garden Supply",
            "type":"Retail Goods"
        }
    ],
    "sg:phone":"+43 4221 2120",
    "sg:postcode":"9131",
    "sg:province":"K\u00e4rnten",
    "sg:tags":[
        "schotter",
        "sand",
        "u"
    ],
    "wof:name":"Wallner Thomas Ing",
    "wof:placetype":"venue"
},
  "geometry": {"coordinates":[166.9221496582,-0.5282999873],"type":"Point"}
}