{
  "type": "Feature",
  "properties": {
    "iso:country":"AT",
    "sg:address":"Hadermarkt 100",
    "sg:city":"Ostermiething",
    "sg:orig_category":"Gemeinden",
    "sg:phone":"+43 6278 81790",
    "sg:postcode":"5121",
    "sg:province":"Ober\u00f6sterreich",
    "wof:name":"Gemeindeamt St Radegund",
    "wof:placetype":"venue"
},
  "geometry": {"coordinates":[12.7736721039,48.0894584656],"type":"Point"}
}