{
  "type": "Feature",
  "properties": {
    "iso:country":"AT",
    "sg:address":"Schie\u00dfstattstr 9",
    "sg:city":"Salzburg",
    "sg:orig_category":"Fahrschulen",
    "sg:phone":"+43 662 842527",
    "sg:postcode":"5020",
    "sg:province":"Salzburg",
    "sg:website":"easydrivers.at",
    "wof:name":"Easy-Drivers Fahrschule Mag Kurt Eigenstiller",
    "wof:placetype":"venue"
},
  "geometry": {"coordinates":[13.0341596603,47.8118629456],"type":"Point"}
}