{
  "type": "Feature",
  "properties": {
    "addr:full":"M\u00fchlg 56 Graz Steiermark 8020",
    "addr:housenumber":"56",
    "addr:postcode":"8020",
    "addr:street":"Muehlg",
    "iso:country":"AT",
    "sg:address":"M\u00fchlg 56",
    "sg:city":"Graz",
    "sg:orig_category":"Non-Classified Establishments",
    "sg:phone":"+43 316 722774",
    "sg:postcode":"8020",
    "sg:province":"Steiermark",
    "wof:name":"Presento Prazsky HandelsOEG",
    "wof:placetype":"venue"
},
  "geometry": {"coordinates":[15.4111499786,47.0689201355],"type":"Point"}
}