{
  "type": "Feature",
  "properties": {
    "addr:full":"M\u00f6nchsberg Salzburg Salzburg 5020",
    "addr:postcode":"5020",
    "addr:street":"Moenchsberg",
    "iso:country":"AT",
    "sg:address":"M\u00f6nchsberg",
    "sg:city":"Salzburg",
    "sg:orig_category":"Tabaktrafiken",
    "sg:phone":"+43 662 842298",
    "sg:postcode":"5020",
    "sg:province":"Salzburg",
    "wof:name":"M\u00f6nchsberg Kiosk",
    "wof:placetype":"venue"
},
  "geometry": {"coordinates":[13.0352754593,47.8045310974],"type":"Point"}
}