{
  "type": "Feature",
  "properties": {
    "addr:full":"Wolfgangseestr 11 Fuschl am See Salzburg 5330",
    "addr:housenumber":"11",
    "addr:postcode":"5330",
    "addr:street":"Wolfgangseestr",
    "iso:country":"AT",
    "sg:address":"Wolfgangseestr 11",
    "sg:city":"Fuschl am See",
    "sg:classifiers":[
        {
            "category":"Restaurant",
            "type":"Food & Drink"
        }
    ],
    "sg:phone":"+43 6226 8236",
    "sg:postcode":"5330",
    "sg:province":"Salzburg",
    "wof:name":"Brunnwirt",
    "wof:placetype":"venue"
},
  "geometry": {"coordinates":[13.3048992157,47.795841217],"type":"Point"}
}