{
  "type": "Feature",
  "properties": {
    "addr:full":"Feldstr 11 Gresten Nieder\u00f6sterreich 3264",
    "addr:housenumber":"11",
    "addr:postcode":"3264",
    "addr:street":"Feldstr",
    "iso:country":"AT",
    "sg:address":"Feldstr 11",
    "sg:city":"Gresten",
    "sg:orig_category":"Physiotherapie",
    "sg:phone":"+43 7487 7869",
    "sg:postcode":"3264",
    "sg:province":"Nieder\u00f6sterreich",
    "wof:name":"Hackl Daniela Dipl-PT",
    "wof:placetype":"venue"
},
  "geometry": {"coordinates":[15.0256595612,47.9897117615],"type":"Point"}
}