{
  "type": "Feature",
  "properties": {
    "addr:full":"Nr 73 Gries am Brenner Tirol 6156",
    "addr:postcode":"6156",
    "addr:street":"Nr;Tirol",
    "iso:country":"AT",
    "sg:address":"Nr 73",
    "sg:city":"Gries am Brenner",
    "sg:orig_category":"Hauptschulen",
    "sg:phone":"+43 5274 87291",
    "sg:postcode":"6156",
    "sg:province":"Tirol",
    "wof:name":"Hauptschule",
    "wof:placetype":"venue"
},
  "geometry": {"coordinates":[11.478723526,47.0383338928],"type":"Point"}
}