{
  "type": "Feature",
  "properties": {
    "addr:full":"Blumeng 3 Steinabr\u00fcckl Nieder\u00f6sterreich 2751",
    "addr:housenumber":"3",
    "addr:postcode":"2751",
    "addr:street":"Blumeng;Niederoesterreich",
    "iso:country":"AT",
    "sg:address":"Blumeng 3",
    "sg:city":"Steinabr\u00fcckl",
    "sg:orig_category":"Transportunternehmen",
    "sg:phone":"+43 4326 2243094",
    "sg:postcode":"2751",
    "sg:province":"Nieder\u00f6sterreich",
    "wof:name":"Kaindl Karl u Erika",
    "wof:placetype":"venue"
},
  "geometry": {"coordinates":[16.201713562,47.8727607727],"type":"Point"}
}