{
  "type": "Feature",
  "properties": {
    "addr:full":"Holz-Steiner-Str 6 Gerasdorf Nieder\u00f6sterreich 2201",
    "addr:housenumber":"6",
    "addr:postcode":"2201",
    "addr:street":"Holz-Steiner-Str",
    "iso:country":"AT",
    "sg:address":"Holz-Steiner-Str 6",
    "sg:city":"Gerasdorf",
    "sg:orig_category":"Reinigungsservice",
    "sg:phone":"+43 2246 27815",
    "sg:postcode":"2201",
    "sg:province":"Nieder\u00f6sterreich",
    "wof:name":"Chemometall Gebindereinigung KEG",
    "wof:placetype":"venue"
},
  "geometry": {"coordinates":[16.462053299,48.3396072388],"type":"Point"}
}