{
  "type": "Feature",
  "properties": {
    "iso:country":"AT",
    "sg:address":"R\u00f6merweg 38",
    "sg:city":"W\u00f6lfnitz",
    "sg:orig_category":"Kinderbetreuung",
    "sg:phone":"+43 463 40221",
    "sg:postcode":"9061",
    "sg:province":"K\u00e4rnten",
    "wof:name":"Hort W\u00f6lfnitz - Magistrat d Landeshauptstadt Klagenfurt",
    "wof:placetype":"venue"
},
  "geometry": {"coordinates":[14.2639198303,46.6675415039],"type":"Point"}
}