{
  "type": "Feature",
  "properties": {
    "addr:full":"Hauptplatz 9 Ampflwang im Hausruckwald Ober\u00f6sterreich 4843",
    "addr:housenumber":"9",
    "addr:postcode":"4843",
    "addr:street":"Hauptplatz",
    "iso:country":"AT",
    "sg:address":"Hauptplatz 9",
    "sg:city":"Ampflwang im Hausruckwald",
    "sg:classifiers":[
        {
            "category":"Banks & Credit Unions",
            "subcategory":"Bank",
            "type":"Services"
        }
    ],
    "sg:phone":"+43 767540050",
    "sg:postcode":"4843",
    "sg:province":"Ober\u00f6sterreich",
    "sg:tags":[
        "chain",
        "systems",
        "cable",
        "guide"
    ],
    "sg:website":"igus.at",
    "wof:name":"igus polymer Innovationen GmbH",
    "wof:placetype":"venue"
},
  "geometry": {"coordinates":[13.5656881332,48.0920219421],"type":"Point"}
}