{
  "type": "Feature",
  "properties": {
    "addr:full":"Im Kirchpark 1 Lustenau Vorarlberg 6890",
    "addr:housenumber":"1",
    "addr:postcode":"6890",
    "addr:street":"Im Kirchpark",
    "iso:country":"AT",
    "sg:address":"Im Kirchpark 1",
    "sg:city":"Lustenau",
    "sg:orig_category":"Blumeneinzelhandel",
    "sg:phone":"+43 5577 62861",
    "sg:postcode":"6890",
    "sg:province":"Vorarlberg",
    "wof:name":"Blumenhof - Blumen & Geschenke HandelsgmbH",
    "wof:placetype":"venue"
},
  "geometry": {"coordinates":[9.6584186554,47.4267921448],"type":"Point"}
}