{
  "type": "Feature",
  "properties": {
    "addr:full":"J Nepomuk Berger-Pl 3 Wien Wien 1160",
    "addr:housenumber":"3",
    "addr:postcode":"1160",
    "addr:street":"Berger-Pl",
    "iso:country":"AT",
    "sg:address":"J Nepomuk Berger-Pl 3",
    "sg:city":"Wien",
    "sg:orig_category":"Tabaktrafiken",
    "sg:phone":"+43 1 4866692",
    "sg:postcode":"1160",
    "sg:province":"Wien",
    "wof:name":"Topil Robert",
    "wof:placetype":"venue"
},
  "geometry": {"coordinates":[16.326631546,48.2126617432],"type":"Point"}
}