{
  "type": "Feature",
  "properties": {
    "addr:full":"Wiener Str 322 Linz Ober\u00f6sterreich 4030",
    "addr:housenumber":"322",
    "addr:postcode":"4030",
    "iso:country":"AT",
    "sg:address":"Wiener Str 322",
    "sg:city":"Linz",
    "sg:orig_category":"Stahlwaren",
    "sg:phone":"+43 732 3123630",
    "sg:postcode":"4030",
    "sg:province":"Ober\u00f6sterreich",
    "wof:name":"Kroneisl StahlhandelsgesmbH",
    "wof:placetype":"venue"
},
  "geometry": {"coordinates":[14.3184909821,48.2633094788],"type":"Point"}
}