{
  "type": "Feature",
  "properties": {
    "iso:country":"AT",
    "sg:address":"Helenenstr 5",
    "sg:city":"Baden",
    "sg:orig_category":"Familien / Beratung",
    "sg:phone":"+43 4322 52209111",
    "sg:postcode":"2500",
    "sg:province":"Nieder\u00f6sterreich",
    "wof:name":"Hilfswerk Zentrum f\u00fcr Beratung & Begleitung",
    "wof:placetype":"venue"
},
  "geometry": {"coordinates":[16.224521637,48.0064697266],"type":"Point"}
}