{
  "type": "Feature",
  "properties": {
    "iso:country":"AT",
    "sg:address":"Schw\u00f6bing 80",
    "sg:city":"Langenwang",
    "sg:orig_category":"Canalisation",
    "sg:phone":"+43 3854 3361",
    "sg:postcode":"8665",
    "sg:province":"Steiermark",
    "sg:website":"maschinenhof.at",
    "wof:name":"Maschinenhof Dipl-Ing Hainzl Ges.m.b.H.",
    "wof:placetype":"venue"
},
  "geometry": {"coordinates":[15.6079263687,47.5588340759],"type":"Point"}
}