{
  "type": "Feature",
  "properties": {
    "addr:full":"Dorf 230 Egg Vorarlberg 6863",
    "addr:housenumber":"230",
    "addr:postcode":"6863",
    "addr:street":"Dorf",
    "iso:country":"AT",
    "sg:address":"Dorf 230",
    "sg:city":"Egg",
    "sg:orig_category":"Tischlereien",
    "sg:phone":"+43 5512 23480",
    "sg:postcode":"6863",
    "sg:province":"Vorarlberg",
    "wof:name":"K\u00fchne Christoph",
    "wof:placetype":"venue"
},
  "geometry": {"coordinates":[9.897102356,47.4310417175],"type":"Point"}
}