{
  "type": "Feature",
  "properties": {
    "iso:country":"AT",
    "sg:address":"Jochberger Str. 18 ",
    "sg:city":"Kitzb\u00fchel",
    "sg:classifiers":[
        {
            "category":"Banks & Credit Unions",
            "subcategory":"Investment Brokerage",
            "type":"Services"
        }
    ],
    "sg:phone":"+43 4353 566060",
    "sg:postcode":"6370",
    "sg:province":"Tirol",
    "sg:tags":[
        "-",
        "transport",
        "related"
    ],
    "wof:name":"EUROTOURS INTERNATIONAL GES.MBH",
    "wof:placetype":"venue"
},
  "geometry": {"coordinates":[12.3983011246,47.443687439],"type":"Point"}
}