{
  "type": "Feature",
  "properties": {
    "addr:full":"Laaer Str 12 Korneuburg Nieder\u00f6sterreich 2100",
    "addr:postcode":"2100",
    "addr:street":"Str 12",
    "iso:country":"AT",
    "sg:address":"Laaer Str 12",
    "sg:city":"Korneuburg",
    "sg:classifiers":[
        {
            "category":"Travel",
            "subcategory":"Hotels & Motels",
            "type":"Entertainment"
        }
    ],
    "sg:phone":"+43 2262 721980",
    "sg:postcode":"2100",
    "sg:province":"Nieder\u00f6sterreich",
    "wof:name":"Hotel R\u00f6dl",
    "wof:placetype":"venue"
},
  "geometry": {"coordinates":[16.332408905,48.3454093933],"type":"Point"}
}