{
  "type": "Feature",
  "properties": {
    "addr:full":"Pfaffendorf 28 Pernersdorf-Pfaffendorf Nieder\u00f6sterreich 2052",
    "addr:housenumber":"28",
    "addr:postcode":"2052",
    "addr:street":"Pfaffendorf;Niederoesterreich",
    "iso:country":"AT",
    "sg:address":"Pfaffendorf 28",
    "sg:city":"Pernersdorf-Pfaffendorf",
    "sg:classifiers":[
        {
            "category":"Home & Garden",
            "subcategory":"Building Materials",
            "type":"Retail Goods"
        }
    ],
    "sg:phone":"+43 4329 448435",
    "sg:postcode":"2052",
    "sg:province":"Nieder\u00f6sterreich",
    "sg:tags":[
        "baustoffe",
        "-material",
        "u"
    ],
    "wof:name":"Gewinnbau Weiss",
    "wof:placetype":"venue"
},
  "geometry": {"coordinates":[16.0201530457,48.7005653381],"type":"Point"}
}