{
  "type": "Feature",
  "properties": {
    "addr:full":"Kugelbeerweg 3a Lochau Vorarlberg 6911",
    "addr:housenumber":"3a",
    "addr:postcode":"6911",
    "addr:street":"Kugelbeerweg",
    "iso:country":"AT",
    "sg:address":"Kugelbeerweg 3a",
    "sg:city":"Lochau",
    "sg:orig_category":"Molkereien U Molkereiprodukte",
    "sg:phone":"+43 4355 74464460",
    "sg:postcode":"6911",
    "sg:province":"Vorarlberg",
    "wof:name":"Rupp Cheese Innovation GmbH",
    "wof:placetype":"venue"
},
  "geometry": {"coordinates":[9.7483758926,47.526096344],"type":"Point"}
}