{
  "type": "Feature",
  "properties": {
    "addr:full":"Hietzinger Hauptstr 74 Wien Wien 1130",
    "addr:housenumber":"74",
    "addr:postcode":"1130",
    "addr:street":"Hietzinger Hauptstr",
    "iso:country":"AT",
    "sg:address":"Hietzinger Hauptstr 74",
    "sg:city":"Wien",
    "sg:classifiers":[
        {
            "category":"Professional",
            "type":"Services"
        }
    ],
    "sg:phone":"+43 1 870110",
    "sg:postcode":"1130",
    "sg:province":"Wien",
    "sg:tags":[
        "leasing"
    ],
    "wof:name":"AL-Allgemeine Immobilien AG",
    "wof:placetype":"venue"
},
  "geometry": {"coordinates":[16.2842311859,48.1874275208],"type":"Point"}
}