{
  "type": "Feature",
  "properties": {
    "addr:full":"Dorotheerg 6-8 Wien Wien 1010",
    "addr:housenumber":"6-8",
    "addr:postcode":"1010",
    "addr:street":"Dorotheerg",
    "iso:country":"AT",
    "sg:address":"Dorotheerg 6-8",
    "sg:city":"Wien",
    "sg:orig_category":"Juweliere, Gold- U Silberschmiede",
    "sg:phone":"+43 1 5339019",
    "sg:postcode":"1010",
    "sg:province":"Wien",
    "wof:name":"Seitner & Co OEG",
    "wof:placetype":"venue"
},
  "geometry": {"coordinates":[16.369758606,48.2080001831],"type":"Point"}
}