{
  "type": "Feature",
  "properties": {
    "addr:full":"Argentinierstr 40 Wien Wien 1040",
    "addr:housenumber":"40",
    "addr:postcode":"1040",
    "addr:street":"Argentinierstr",
    "iso:country":"AT",
    "sg:address":"Argentinierstr 40",
    "sg:city":"Wien",
    "sg:orig_category":"Immobilienverwaltungen",
    "sg:phone":"+43 1 5056507",
    "sg:postcode":"1040",
    "sg:province":"Wien",
    "wof:name":"Spies Johanna",
    "wof:placetype":"venue"
},
  "geometry": {"coordinates":[16.3749904633,48.1910934448],"type":"Point"}
}