{
  "type": "Feature",
  "properties": {
    "addr:full":"Unterberg 11 Gro\u00dfarl Salzburg 5611",
    "addr:housenumber":"11",
    "addr:postcode":"5611",
    "addr:street":"Unterberg;Salzburg",
    "iso:country":"AT",
    "sg:address":"Unterberg 11",
    "sg:city":"Gro\u00dfarl",
    "sg:orig_category":"Appartements / Ferienwohnungen",
    "sg:phone":"+43 4364 14550",
    "sg:postcode":"5611",
    "sg:province":"Salzburg",
    "wof:name":"Gruber Theresia u Rupert",
    "wof:placetype":"venue"
},
  "geometry": {"coordinates":[13.1961202621,47.2405586243],"type":"Point"}
}