{
  "type": "Feature",
  "properties": {
    "iso:country":"AT",
    "sg:address":"Linzer Str 107",
    "sg:city":"Marchtrenk",
    "sg:orig_category":"Friseure U Frisiersalons",
    "sg:phone":"+43 7243 52438",
    "sg:postcode":"4614",
    "sg:province":"Ober\u00f6sterreich",
    "wof:name":"Salon Karina",
    "wof:placetype":"venue"
},
  "geometry": {"coordinates":[14.1300868988,48.1946487427],"type":"Point"}
}