{
  "type": "Feature",
  "properties": {
    "addr:full":"Rosengasse 2 Feldkirch Vorarlberg 6800",
    "addr:housenumber":"2",
    "addr:postcode":"6800",
    "addr:street":"Rosengasse",
    "iso:country":"AT",
    "sg:address":"Rosengasse 2",
    "sg:city":"Feldkirch",
    "sg:classifiers":[
        {
            "category":"Arts & Performance",
            "subcategory":"Arts Center",
            "type":"Entertainment"
        }
    ],
    "sg:phone":"+43 5522 76157",
    "sg:postcode":"6800",
    "sg:province":"Vorarlberg",
    "sg:tags":[
        "print",
        "photographic",
        "digital"
    ],
    "sg:website":"walgaublatt.com",
    "wof:name":"RZ Regionalzeitung GmbH & Co KG",
    "wof:placetype":"venue"
},
  "geometry": {"coordinates":[9.5981616974,47.2369422913],"type":"Point"}
}