{
  "type": "Feature",
  "properties": {
    "addr:full":"Hagenbuchstr 20 Stra\u00dfgang Steiermark 8054",
    "addr:housenumber":"20",
    "addr:postcode":"8054",
    "addr:street":"Hagenbuchstr",
    "iso:country":"AT",
    "sg:address":"Hagenbuchstr 20",
    "sg:city":"Stra\u00dfgang",
    "sg:orig_category":"Lebensmittel / Erzeugung U Gro\u00c3\u0178handel",
    "sg:phone":"+43 316 2816120",
    "sg:postcode":"8054",
    "sg:province":"Steiermark",
    "wof:name":"Maurer Josefa Inh Wilfling",
    "wof:placetype":"venue"
},
  "geometry": {"coordinates":[15.3872480392,47.0020141602],"type":"Point"}
}