{
  "type": "Feature",
  "properties": {
    "iso:country":"AT",
    "sg:address":"Edith-Stein-Weg 2/II",
    "sg:city":"Innsbruck",
    "sg:orig_category":"Steuerberatung",
    "sg:phone":"+43 512 5625640",
    "sg:postcode":"6020",
    "sg:province":"Tirol",
    "wof:name":"Weinzierl Reinhold",
    "wof:placetype":"venue"
},
  "geometry": {"coordinates":[11.3977460861,47.2601776123],"type":"Point"}
}