{
  "type": "Feature",
  "properties": {
    "addr:full":"Nr 4 Hermagor K\u00e4rnten 9620",
    "addr:postcode":"9620",
    "addr:street":"Nr;Kaernten",
    "iso:country":"AT",
    "sg:address":"Nr 4",
    "sg:city":"Hermagor",
    "sg:classifiers":[
        {
            "category":"Travel",
            "subcategory":"Hotels & Motels",
            "type":"Entertainment"
        }
    ],
    "sg:phone":"+43 4282 33670",
    "sg:postcode":"9620",
    "sg:province":"K\u00e4rnten",
    "wof:name":"Hotel K\u00e4rntnerhof",
    "wof:placetype":"venue"
},
  "geometry": {"coordinates":[13.3051300049,46.6695404053],"type":"Point"}
}