{
  "type": "Feature",
  "properties": {
    "iso:country":"AT",
    "sg:address":"Wagingerstr 9",
    "sg:city":"Salzburg",
    "sg:orig_category":"Lebensmittel / Einzelhandel",
    "sg:phone":"+43 662 433716",
    "sg:postcode":"5020",
    "sg:province":"Salzburg",
    "wof:name":"Billa AG",
    "wof:placetype":"venue"
},
  "geometry": {"coordinates":[13.0229949951,47.8222198486],"type":"Point"}
}