{
  "type": "Feature",
  "properties": {
    "addr:full":"Gersthofer Str 51 Wien Wien 1180",
    "addr:postcode":"1180",
    "addr:street":"Str 51",
    "iso:country":"AT",
    "sg:address":"Gersthofer Str 51",
    "sg:city":"Wien",
    "sg:orig_category":"Bierlokale-Pubs",
    "sg:phone":"+43 4314 795800",
    "sg:postcode":"1180",
    "sg:province":"Wien",
    "wof:name":"Centimeter VI",
    "wof:placetype":"venue"
},
  "geometry": {"coordinates":[16.32853508,48.2308883667],"type":"Point"}
}