{
  "type": "Feature",
  "properties": {
    "addr:full":"Bahnhofstr 2 Saalfelden am Steinernen Meer Salzburg 5760",
    "addr:housenumber":"2",
    "addr:postcode":"5760",
    "addr:street":"Bahnhofstr",
    "iso:country":"AT",
    "sg:address":"Bahnhofstr 2",
    "sg:city":"Saalfelden am Steinernen Meer",
    "sg:orig_category":"Textilwaren / Einzelhandel",
    "sg:phone":"+43 6582 722740",
    "sg:postcode":"5760",
    "sg:province":"Salzburg",
    "wof:name":"Lederer Peter GesmbH & Co KG",
    "wof:placetype":"venue"
},
  "geometry": {"coordinates":[12.8465967178,47.4273071289],"type":"Point"}
}