{
  "type": "Feature",
  "properties": {
    "addr:full":"Elisabethstrasse 59 Wels Ober\u00f6sterreich 4600",
    "addr:housenumber":"59",
    "addr:postcode":"4600",
    "addr:street":"Elisabethstrasse;Oberoesterreich",
    "iso:country":"AT",
    "sg:address":"Elisabethstrasse 59",
    "sg:city":"Wels",
    "sg:orig_category":"Stable Ventilation Systems",
    "sg:phone":"+43 7242 46310",
    "sg:postcode":"4600",
    "sg:province":"Ober\u00f6sterreich",
    "wof:name":"Karg & Spindler KEG Stallbel\u00fcftungen",
    "wof:placetype":"venue"
},
  "geometry": {"coordinates":[14.0178194046,48.1742401123],"type":"Point"}
}