{
  "type": "Feature",
  "properties": {
    "addr:full":"Nr 42 Kl\u00f6ch Steiermark 8493",
    "addr:postcode":"8493",
    "addr:street":"Nr 42 Kloech Steiermark",
    "iso:country":"AT",
    "sg:address":"Nr 42",
    "sg:city":"Kl\u00f6ch",
    "sg:orig_category":"Pensionen / Privatzimmer",
    "sg:phone":"+43 3475 2833",
    "sg:postcode":"8493",
    "sg:province":"Steiermark",
    "wof:name":"Guttmann Gerhard",
    "wof:placetype":"venue"
},
  "geometry": {"coordinates":[15.967171669,46.7641334534],"type":"Point"}
}