{
  "type": "Feature",
  "properties": {
    "iso:country":"AT",
    "sg:address":"Europastr 2",
    "sg:city":"Salzburg",
    "sg:orig_category":"Werbeagenturen",
    "sg:phone":"+43 662 447028280",
    "sg:postcode":"5020",
    "sg:province":"Salzburg",
    "wof:name":"Multitakt",
    "wof:placetype":"venue"
},
  "geometry": {"coordinates":[13.006070137,47.8162689209],"type":"Point"}
}