{
  "type": "Feature",
  "properties": {
    "addr:full":"St. Ulrich 14 St. Martin im Innkreis Ober\u00f6sterreich 4973",
    "addr:housenumber":"14",
    "addr:postcode":"4973",
    "addr:street":"St. Ulrich",
    "iso:country":"AT",
    "sg:address":"St. Ulrich 14",
    "sg:city":"St. Martin im Innkreis",
    "sg:orig_category":"Transportunternehmen",
    "sg:phone":"+43 7751 61160",
    "sg:postcode":"4973",
    "sg:province":"Ober\u00f6sterreich",
    "wof:name":"Angleitner Franz GesmbH",
    "wof:placetype":"venue"
},
  "geometry": {"coordinates":[13.4232215881,48.2807769775],"type":"Point"}
}