{
  "type": "Feature",
  "properties": {
    "addr:full":"Stadtpl 5 Eferding Ober\u00f6sterreich 4070",
    "addr:housenumber":"5",
    "addr:postcode":"4070",
    "addr:street":"Stadtpl",
    "iso:country":"AT",
    "sg:address":"Stadtpl 5",
    "sg:city":"Eferding",
    "sg:orig_category":"Rauchfangkehrer",
    "sg:phone":"+43 7272 3788",
    "sg:postcode":"4070",
    "sg:province":"Ober\u00f6sterreich",
    "wof:name":"Emmerstorfer Heimo",
    "wof:placetype":"venue"
},
  "geometry": {"coordinates":[14.0237493515,48.3097038269],"type":"Point"}
}