{
  "type": "Feature",
  "properties": {
    "addr:full":"Lehen 12 Holzhausen Ober\u00f6sterreich 4615",
    "addr:housenumber":"12",
    "addr:postcode":"4615",
    "addr:street":"Lehen",
    "iso:country":"AT",
    "sg:address":"Lehen 12",
    "sg:city":"Holzhausen",
    "sg:orig_category":"Webdesign",
    "sg:phone":"+43 4372 4390305",
    "sg:postcode":"4615",
    "sg:province":"Ober\u00f6sterreich",
    "wof:name":"K\u00f6hrer EDV & Elektronik",
    "wof:placetype":"venue"
},
  "geometry": {"coordinates":[14.0907688141,48.2324790955],"type":"Point"}
}