{
  "type": "Feature",
  "properties": {
    "iso:country":"AT",
    "sg:address":"Wiener Str 12",
    "sg:city":"Brunn am Gebirge",
    "sg:orig_category":"Transportunternehmen",
    "sg:phone":"+43 2236 35321",
    "sg:postcode":"2345",
    "sg:province":"Nieder\u00f6sterreich",
    "wof:name":"Weissmann Heinrich",
    "wof:placetype":"venue"
},
  "geometry": {"coordinates":[16.2859249115,48.106098175],"type":"Point"}
}