{
  "type": "Feature",
  "properties": {
    "addr:full":"Wiedner Hauptstr 150 Wien Wien 1050",
    "addr:housenumber":"150",
    "addr:postcode":"1050",
    "addr:street":"Hauptstr",
    "iso:country":"AT",
    "sg:address":"Wiedner Hauptstr 150",
    "sg:city":"Wien",
    "sg:orig_category":"Dekorationsartikel",
    "sg:phone":"+43 4319 1443510",
    "sg:postcode":"1050",
    "sg:province":"Wien",
    "sg:website":"dekor-center.at",
    "wof:name":"Dekor Center Austria Handels GmbH",
    "wof:placetype":"venue"
},
  "geometry": {"coordinates":[16.3591957092,48.1824150085],"type":"Point"}
}