{
  "type": "Feature",
  "properties": {
    "iso:country":"AT",
    "sg:address":"Kittenbach 14",
    "sg:city":"Kirchbach in Steiermark",
    "sg:orig_category":"Gesundheit / Allgemeine Informationsstellen",
    "sg:phone":"+43 4366 45080706",
    "sg:postcode":"8082",
    "sg:province":"Steiermark",
    "sg:website":"dorn-breuss-gesellschaft.at",
    "wof:name":"\u00f6sterreichische Ges f Wirbeltherapie nach Dorn-Breuss uSanfte Wirbelregulation nach DrAuer",
    "wof:placetype":"venue"
},
  "geometry": {"coordinates":[15.6588878632,46.937297821],"type":"Point"}
}