{
  "type": "Feature",
  "properties": {
    "iso:country":"AT",
    "sg:address":"Dorf 10",
    "sg:city":"Niederkappel",
    "sg:orig_category":"Appartements / Ferienwohnungen",
    "sg:phone":"+43 7286 7994",
    "sg:postcode":"4133",
    "sg:province":"Ober\u00f6sterreich",
    "wof:name":"Ferienhof Ramesedt Fam Schlagnitweit",
    "wof:placetype":"venue"
},
  "geometry": {"coordinates":[13.8473796844,48.4547691345],"type":"Point"}
}