{
  "type": "Feature",
  "properties": {
    "addr:full":"Ketzerg 118 Wien Wien 1230",
    "addr:housenumber":"118",
    "addr:postcode":"1230",
    "iso:country":"AT",
    "sg:address":"Ketzerg 118",
    "sg:city":"Wien",
    "sg:classifiers":[
        {
            "category":"Manufacturing",
            "subcategory":"Signs",
            "type":"Manufacturing & Wholesale Goods"
        }
    ],
    "sg:phone":"+43 1 86969780",
    "sg:postcode":"1230",
    "sg:province":"Wien",
    "sg:tags":[
        "display"
    ],
    "wof:name":"PROPOS Display-HandelsgesmbH",
    "wof:placetype":"venue"
},
  "geometry": {"coordinates":[16.3009796143,48.1288642883],"type":"Point"}
}