{
  "type": "Feature",
  "properties": {
    "iso:country":"AT",
    "sg:address":"Am Waldrand 9",
    "sg:city":"Lieboch",
    "sg:orig_category":"Algicides",
    "sg:phone":"+43 3136 610170",
    "sg:postcode":"8501",
    "sg:province":"Steiermark",
    "sg:website":"aquaviva.at",
    "wof:name":"Minnova Mineralien Handelsges.m.b.H.",
    "wof:placetype":"venue"
},
  "geometry": {"coordinates":[15.3171796799,46.9864692688],"type":"Point"}
}