{
  "type": "Feature",
  "properties": {
    "addr:full":"Kaplanstr 2 Rum Tirol 6063",
    "addr:housenumber":"2",
    "addr:postcode":"6063",
    "addr:street":"Kaplanstr;Tirol",
    "iso:country":"AT",
    "sg:address":"Kaplanstr 2",
    "sg:city":"Rum",
    "sg:orig_category":"Elektroinstallationsunternehmen",
    "sg:phone":"+43 512 269833",
    "sg:postcode":"6063",
    "sg:province":"Tirol",
    "wof:name":"Hofer Hans",
    "wof:placetype":"venue"
},
  "geometry": {"coordinates":[11.4546880722,47.2771759033],"type":"Point"}
}