{
  "type": "Feature",
  "properties": {
    "addr:full":"Matzing 2 Neumarkt am Wallersee Salzburg 5202",
    "addr:housenumber":"2",
    "addr:postcode":"5202",
    "addr:street":"Matzing;Salzburg",
    "iso:country":"AT",
    "sg:address":"Matzing 2",
    "sg:city":"Neumarkt am Wallersee",
    "sg:orig_category":"Erdarbeiten",
    "sg:phone":"+43 4366 45125859",
    "sg:postcode":"5202",
    "sg:province":"Salzburg",
    "wof:name":"Baier Herbert",
    "wof:placetype":"venue"
},
  "geometry": {"coordinates":[13.2155532837,47.92735672],"type":"Point"}
}