{
  "type": "Feature",
  "properties": {
    "addr:full":"Ausseer Str 9-11 Liezen Steiermark 8940",
    "addr:housenumber":"9-11",
    "addr:postcode":"8940",
    "iso:country":"AT",
    "sg:address":"Ausseer Str 9-11",
    "sg:city":"Liezen",
    "sg:orig_category":"Restaurants: Chinesisch",
    "sg:phone":"+43 3612 26861",
    "sg:postcode":"8940",
    "sg:province":"Steiermark",
    "wof:name":"China-Restaurant Goldener Stern",
    "wof:placetype":"venue"
},
  "geometry": {"coordinates":[14.2413349152,47.5672111511],"type":"Point"}
}