{
  "type": "Feature",
  "properties": {
    "addr:full":"Hauptstr 14 Gablitz Nieder\u00f6sterreich 3003",
    "addr:housenumber":"14",
    "addr:postcode":"3003",
    "addr:street":"Hauptstr",
    "iso:country":"AT",
    "sg:address":"Hauptstr 14",
    "sg:city":"Gablitz",
    "sg:orig_category":"Massagen",
    "sg:phone":"+43 676 7315307",
    "sg:postcode":"3003",
    "sg:province":"Nieder\u00f6sterreich",
    "wof:name":"Energetische Therapien Karin Schrittwieser",
    "wof:placetype":"venue"
},
  "geometry": {"coordinates":[16.153427124,48.2275924683],"type":"Point"}
}