{
  "type": "Feature",
  "properties": {
    "addr:full":"Hauptpl 19 Perg Ober\u00f6sterreich 4320",
    "addr:housenumber":"19",
    "addr:postcode":"4320",
    "addr:street":"Hauptpl",
    "iso:country":"AT",
    "sg:address":"Hauptpl 19",
    "sg:city":"Perg",
    "sg:orig_category":"Immobilienmakler",
    "sg:phone":"+43 7262 54373",
    "sg:postcode":"4320",
    "sg:province":"Ober\u00f6sterreich",
    "wof:name":"VKB - Immobilien GesmbH",
    "wof:placetype":"venue"
},
  "geometry": {"coordinates":[14.6331787109,48.2496757507],"type":"Point"}
}