{
  "type": "Feature",
  "properties": {
    "addr:full":"Lorenz Walcher-Pl Reifnitz K\u00e4rnten 9081",
    "addr:housenumber":"9081",
    "iso:country":"AT",
    "sg:address":"Lorenz Walcher-Pl",
    "sg:city":"Reifnitz",
    "sg:orig_category":"Feuerwehren",
    "sg:phone":"+43 4273 2420",
    "sg:postcode":"9081",
    "sg:province":"K\u00e4rnten",
    "wof:name":"Feuerwehr Reifnitz",
    "wof:placetype":"venue"
},
  "geometry": {"coordinates":[14.1815433502,46.6068840027],"type":"Point"}
}