{
  "type": "Feature",
  "properties": {
    "addr:full":"Unterdorf Wenns Tirol 6473",
    "addr:postcode":"6473",
    "addr:street":"Unterdorf;Tirol",
    "iso:country":"AT",
    "sg:address":"Unterdorf",
    "sg:city":"Wenns",
    "sg:orig_category":"Non-Classified Establishments",
    "sg:phone":"+43 5414 87282",
    "sg:postcode":"6473",
    "sg:province":"Tirol",
    "wof:name":"Pfarramt",
    "wof:placetype":"venue"
},
  "geometry": {"coordinates":[10.7310600281,47.1709060669],"type":"Point"}
}