{
  "type": "Feature",
  "properties": {
    "iso:country":"AT",
    "sg:address":"Nr 30",
    "sg:city":"Riegersburg",
    "sg:orig_category":"Banken U Sparkassen",
    "sg:phone":"+43 4331 5382780",
    "sg:postcode":"8333",
    "sg:province":"Steiermark",
    "wof:name":"Bankomat d Raiffeisenbank Riegersburg-Breitenfeld regGenmbH",
    "wof:placetype":"venue"
},
  "geometry": {"coordinates":[15.9359292984,47.0007858276],"type":"Point"}
}