{
  "type": "Feature",
  "properties": {
    "addr:full":"Nr 87 Oberhofen im Inntal Tirol 6406",
    "addr:postcode":"6406",
    "addr:street":"Nr 87;Tirol",
    "iso:country":"AT",
    "sg:address":"Nr 87",
    "sg:city":"Oberhofen im Inntal",
    "sg:orig_category":"Volksschulen",
    "sg:phone":"+43 4352 6266301",
    "sg:postcode":"6406",
    "sg:province":"Tirol",
    "wof:name":"Volksschule",
    "wof:placetype":"venue"
},
  "geometry": {"coordinates":[11.0959024429,47.3035469055],"type":"Point"}
}