{
  "type": "Feature",
  "properties": {
    "iso:country":"AT",
    "sg:address":"Dr.-Zimmermann-Str 2",
    "sg:city":"Bad Hofgastein",
    "sg:classifiers":[
        {
            "category":"Travel",
            "subcategory":"Hotels & Motels",
            "type":"Entertainment"
        }
    ],
    "sg:phone":"+43 6432 83740",
    "sg:postcode":"5630",
    "sg:province":"Salzburg",
    "wof:name":"Hotel Carinthia",
    "wof:placetype":"venue"
},
  "geometry": {"coordinates":[13.1018323898,47.1697387695],"type":"Point"}
}