{
  "type": "Feature",
  "properties": {
    "addr:full":"Scharitzerstrasse 1a Linz Ober\u00f6sterreich 4020",
    "addr:housenumber":"1a",
    "addr:postcode":"4020",
    "addr:street":"Scharitzerstrasse",
    "iso:country":"AT",
    "sg:address":"Scharitzerstrasse 1a",
    "sg:city":"Linz",
    "sg:orig_category":"Software For Astrology",
    "sg:phone":"+43 732 656970",
    "sg:postcode":"4020",
    "sg:province":"Ober\u00f6sterreich",
    "sg:website":"astrocontact.at",
    "wof:name":"Astrocontact Software",
    "wof:placetype":"venue"
},
  "geometry": {"coordinates":[14.2929430008,48.2957038879],"type":"Point"}
}