{
  "type": "Feature",
  "properties": {
    "addr:full":"Keplerg 16 Wien Wien 1100",
    "addr:housenumber":"16",
    "addr:postcode":"1100",
    "addr:street":"Keplerg",
    "iso:country":"AT",
    "sg:address":"Keplerg 16",
    "sg:city":"Wien",
    "sg:orig_category":"Elektroinstallationsunternehmen",
    "sg:phone":"+43 1 6042523",
    "sg:postcode":"1100",
    "sg:province":"Wien",
    "wof:name":"F\u00fcrnsinn Harald GesmbH",
    "wof:placetype":"venue"
},
  "geometry": {"coordinates":[16.3747692108,48.1792602539],"type":"Point"}
}