{
  "type": "Feature",
  "properties": {
    "iso:country":"AT",
    "sg:address":"Sch\u00f6n 63",
    "sg:city":"Micheldorf in Ober\u00f6sterreich",
    "sg:classifiers":[
        {
            "category":"Professional",
            "subcategory":"Computer Services",
            "type":"Services"
        }
    ],
    "sg:phone":"+43 7582 52181",
    "sg:postcode":"4563",
    "sg:province":"Ober\u00f6sterreich",
    "sg:tags":[
        "software"
    ],
    "wof:name":"Edelsbacher Datenverarbeitung",
    "wof:placetype":"venue"
},
  "geometry": {"coordinates":[14.1334295273,47.877910614],"type":"Point"}
}