{
  "type": "Feature",
  "properties": {
    "addr:full":"Pfarrg 33 Eisenstadt Burgenland 7000",
    "addr:housenumber":"33",
    "addr:postcode":"7000",
    "addr:street":"Pfarrg",
    "iso:country":"AT",
    "sg:address":"Pfarrg 33",
    "sg:city":"Eisenstadt",
    "sg:orig_category":"Notare",
    "sg:phone":"+43 2682 638800",
    "sg:postcode":"7000",
    "sg:province":"Burgenland",
    "wof:name":"Sch\u00fcssler Edgar Dr",
    "wof:placetype":"venue"
},
  "geometry": {"coordinates":[16.5239887238,47.8456344604],"type":"Point"}
}