{
  "type": "Feature",
  "properties": {
    "addr:full":"Schlitters 57 Schlitters Tirol 6262",
    "addr:housenumber":"57",
    "addr:postcode":"6262",
    "addr:street":"Schlitters;Tirol",
    "iso:country":"AT",
    "sg:address":"Schlitters 57",
    "sg:city":"Schlitters",
    "sg:classifiers":[
        {
            "category":"Food & Beverages",
            "subcategory":"Cheese",
            "type":"Retail Goods"
        }
    ],
    "sg:phone":"+43 5288 72362",
    "sg:postcode":"6262",
    "sg:province":"Tirol",
    "wof:name":"Bergk\u00e4serei Zillertal Hirschhuber Alois",
    "wof:placetype":"venue"
},
  "geometry": {"coordinates":[11.839805603,47.3780670166],"type":"Point"}
}