{
  "type": "Feature",
  "properties": {
    "addr:full":"Marktpl 36 Obernberg am Inn Ober\u00f6sterreich 4982",
    "addr:housenumber":"36",
    "addr:postcode":"4982",
    "addr:street":"Marktpl",
    "iso:country":"AT",
    "sg:address":"Marktpl 36",
    "sg:city":"Obernberg am Inn",
    "sg:orig_category":"Polizei U Gendarmerie",
    "sg:phone":"+43 4359 1334244",
    "sg:postcode":"4982",
    "sg:province":"Ober\u00f6sterreich",
    "wof:name":"Gendarmerie",
    "wof:placetype":"venue"
},
  "geometry": {"coordinates":[13.3357620239,48.3217315674],"type":"Point"}
}