{
  "type": "Feature",
  "properties": {
    "iso:country":"AT",
    "sg:address":"Hauptstr 25",
    "sg:city":"Leopoldsdorf",
    "sg:orig_category":"Polizei U Gendarmerie",
    "sg:phone":"+43 4359 1333229",
    "sg:postcode":"2333",
    "sg:province":"Nieder\u00f6sterreich",
    "wof:name":"Gendarmerie",
    "wof:placetype":"venue"
},
  "geometry": {"coordinates":[16.3971195221,48.1081123352],"type":"Point"}
}