{
  "type": "Feature",
  "properties": {
    "addr:full":"Aub\u00f6ckallee 12 Langenlois Nieder\u00f6sterreich 3550",
    "addr:housenumber":"12",
    "addr:postcode":"3550",
    "addr:street":"Auboeckallee",
    "iso:country":"AT",
    "sg:address":"Aub\u00f6ckallee 12",
    "sg:city":"Langenlois",
    "sg:orig_category":"Volksschulen",
    "sg:phone":"+43 2734 2308",
    "sg:postcode":"3550",
    "sg:province":"Nieder\u00f6sterreich",
    "wof:name":"Volksschule",
    "wof:placetype":"venue"
},
  "geometry": {"coordinates":[15.6792354584,48.4721031189],"type":"Point"}
}