{
  "type": "Feature",
  "properties": {
    "addr:full":"Bundesstr 54 Aspang-Markt Nieder\u00f6sterreich 2870",
    "addr:housenumber":"54",
    "addr:postcode":"2870",
    "addr:street":"Bundesstr;Niederoesterreich",
    "iso:country":"AT",
    "sg:address":"Bundesstr 54",
    "sg:city":"Aspang-Markt",
    "sg:orig_category":"Tankstellen",
    "sg:phone":"+43 2642 52477",
    "sg:postcode":"2870",
    "sg:province":"Nieder\u00f6sterreich",
    "wof:name":"AVANTI TankstellenbetriebsgesmbH",
    "wof:placetype":"venue"
},
  "geometry": {"coordinates":[16.090839386,47.554725647],"type":"Point"}
}