{
  "type": "Feature",
  "properties": {
    "addr:full":"Aubauerstr 10 Gmunden Ober\u00f6sterreich 4810",
    "addr:housenumber":"10",
    "addr:postcode":"4810",
    "addr:street":"Aubauerstr;Oberoesterreich",
    "iso:country":"AT",
    "sg:address":"Aubauerstr 10",
    "sg:city":"Gmunden",
    "sg:orig_category":"Autobusunternehmen",
    "sg:phone":"+43 4376 12646130",
    "sg:postcode":"4810",
    "sg:province":"Ober\u00f6sterreich",
    "wof:name":"\u00f6BB-Postbus GmbH - Verkehrsstelle Gmunden",
    "wof:placetype":"venue"
},
  "geometry": {"coordinates":[13.7859973907,47.9302482605],"type":"Point"}
}