{
  "type": "Feature",
  "properties": {
    "addr:full":"Agerstr 20a Lenzing Ober\u00f6sterreich 4860",
    "addr:housenumber":"20a",
    "addr:postcode":"4860",
    "addr:street":"Agerstr",
    "iso:country":"AT",
    "sg:address":"Agerstr 20a",
    "sg:city":"Lenzing",
    "sg:orig_category":"Fenster",
    "sg:phone":"+43 4376 7295137",
    "sg:postcode":"4860",
    "sg:province":"Ober\u00f6sterreich",
    "wof:name":"Kofler Johann KEG",
    "wof:placetype":"venue"
},
  "geometry": {"coordinates":[13.6060819626,47.9698486328],"type":"Point"}
}