{
  "type": "Feature",
  "properties": {
    "addr:full":"Bahnhofstr 64 Uttendorf Salzburg 5723",
    "addr:housenumber":"64",
    "addr:postcode":"5723",
    "addr:street":"Bahnhofstr;Salzburg",
    "iso:country":"AT",
    "sg:address":"Bahnhofstr 64",
    "sg:city":"Uttendorf",
    "sg:orig_category":"Spielwaren U Spiele",
    "sg:phone":"+43 4365 638220",
    "sg:postcode":"5723",
    "sg:province":"Salzburg",
    "wof:name":"Gerhart Reinhold",
    "wof:placetype":"venue"
},
  "geometry": {"coordinates":[12.5743741989,47.2814178467],"type":"Point"}
}