{
  "type": "Feature",
  "properties": {
    "iso:country":"AT",
    "sg:address":"Hundsbichl 1 ",
    "sg:city":"Erpfendorf",
    "sg:classifiers":[
        {
            "category":"Government",
            "subcategory":"Fire Station",
            "type":"Public Place"
        }
    ],
    "sg:phone":"+43 5352 77007",
    "sg:postcode":"6383",
    "sg:province":"Tirol",
    "sg:tags":[
        "supraregional",
        "plant",
        "installation",
        "heating"
    ],
    "sg:website":"www.aignerwaerme.com",
    "wof:name":"L\u00e4ndliche Handwerker GesmbH",
    "wof:placetype":"venue"
},
  "geometry": {"coordinates":[12.4780540466,47.5758552551],"type":"Point"}
}