{
  "type": "Feature",
  "properties": {
    "addr:full":"Burgenlandstrasse 1a F\u00fcrstenfeld Steiermark 8280",
    "addr:housenumber":"1a",
    "addr:postcode":"8280",
    "addr:street":"Burgenlandstrasse",
    "iso:country":"AT",
    "sg:address":"Burgenlandstrasse 1a",
    "sg:city":"F\u00fcrstenfeld",
    "sg:classifiers":[
        {
            "category":"Shopping",
            "subcategory":"Computers & Home Electronics",
            "type":"Retail Goods"
        }
    ],
    "sg:phone":"+43 3382 523330",
    "sg:postcode":"8280",
    "sg:province":"Steiermark",
    "sg:tags":[
        "cable"
    ],
    "sg:website":"meier.at",
    "wof:name":"Ing. Julius Meier Elektro- und Radiounternehmen GmbH",
    "wof:placetype":"venue"
},
  "geometry": {"coordinates":[16.0807228088,47.0480728149],"type":"Point"}
}