{
  "type": "Feature",
  "properties": {
    "addr:full":"Neuberg 102 Filzmoos Salzburg 5532",
    "addr:housenumber":"102",
    "addr:postcode":"5532",
    "addr:street":"Neuberg;Salzburg",
    "iso:country":"AT",
    "sg:address":"Neuberg 102",
    "sg:city":"Filzmoos",
    "sg:orig_category":"Freizeitangebote U -Einrichtungen",
    "sg:phone":"+43 4364 5320044",
    "sg:postcode":"5532",
    "sg:province":"Salzburg",
    "wof:name":"Freizeitzentrum Filzmoos GmbH",
    "wof:placetype":"venue"
},
  "geometry": {"coordinates":[13.5203046799,47.4333534241],"type":"Point"}
}