{
  "type": "Feature",
  "properties": {
    "iso:country":"AT",
    "sg:address":"Hauptstr 39",
    "sg:city":"Arbing",
    "sg:orig_category":"Gemeinden",
    "sg:phone":"+43 7269 3750",
    "sg:postcode":"4341",
    "sg:province":"Ober\u00f6sterreich",
    "wof:name":"Gemeinde Arbing",
    "wof:placetype":"venue"
},
  "geometry": {"coordinates":[14.7005062103,48.2294616699],"type":"Point"}
}