{
  "type": "Feature",
  "properties": {
    "iso:country":"AT",
    "sg:address":"Wandstr 30",
    "sg:city":"Gr\u00fcnbach am Schneeberg",
    "sg:orig_category":"Orgel- U Harmoniumbau",
    "sg:phone":"+43 4326 372742",
    "sg:postcode":"2733",
    "sg:province":"Nieder\u00f6sterreich",
    "wof:name":"Allg\u00e4uer Christoph",
    "wof:placetype":"venue"
},
  "geometry": {"coordinates":[12.6405601501,50.5948791504],"type":"Point"}
}