{
  "type": "Feature",
  "properties": {
    "iso:country":"AT",
    "sg:address":"Haberlandtg 19",
    "sg:city":"Wien",
    "sg:orig_category":"Digitaldruck",
    "sg:phone":"+43 1 2870557",
    "sg:postcode":"1220",
    "sg:province":"Wien",
    "wof:name":"Com-Design",
    "wof:placetype":"venue"
},
  "geometry": {"coordinates":[16.4841861725,48.2199172974],"type":"Point"}
}