{
  "type": "Feature",
  "properties": {
    "addr:full":"Stadtpl 56 Wels Ober\u00f6sterreich 4600",
    "addr:housenumber":"56",
    "addr:postcode":"4600",
    "addr:street":"Stadtpl;Oberoesterreich",
    "iso:country":"AT",
    "sg:address":"Stadtpl 56",
    "sg:city":"Wels",
    "sg:orig_category":"Waagen / Einzelhandel",
    "sg:phone":"+43 7242 45288",
    "sg:postcode":"4600",
    "sg:province":"Ober\u00f6sterreich",
    "wof:name":"Waagen und Geschenk Gertraud Krenn",
    "wof:placetype":"venue"
},
  "geometry": {"coordinates":[14.023018837,48.156124115],"type":"Point"}
}