{
  "type": "Feature",
  "properties": {
    "addr:full":"Stadtpl 24 Braunau am Inn Ober\u00f6sterreich 5280",
    "addr:housenumber":"24",
    "addr:postcode":"5280",
    "addr:street":"Stadtpl",
    "iso:country":"AT",
    "sg:address":"Stadtpl 24",
    "sg:city":"Braunau am Inn",
    "sg:orig_category":"Bars-Cafes",
    "sg:phone":"+43 7722 65998",
    "sg:postcode":"5280",
    "sg:province":"Ober\u00f6sterreich",
    "wof:name":"City Treff",
    "wof:placetype":"venue"
},
  "geometry": {"coordinates":[13.0350532532,48.2575454712],"type":"Point"}
}