{
  "type": "Feature",
  "properties": {
    "addr:full":"Kolsass Tirol 6114",
    "addr:postcode":"6114",
    "addr:street":"Tirol",
    "iso:country":"AT",
    "sg:city":"Kolsass",
    "sg:orig_category":"Reisen, Tourismusinfo",
    "sg:postcode":"6114",
    "sg:province":"Tirol",
    "sg:website":"http://www.weer.at",
    "wof:name":"Tourismusverband Weer-Kolsass-Kolsassberg",
    "wof:placetype":"venue"
},
  "geometry": {"coordinates":[11.6313028336,47.3003616333],"type":"Point"}
}