{
  "type": "Feature",
  "properties": {
    "iso:country":"AT",
    "sg:address":"Stadlweg 25",
    "sg:city":"Innsbruck",
    "sg:classifiers":[
        {
            "category":"Internet Cafe",
            "subcategory":"None",
            "type":"Food & Drink"
        }
    ],
    "sg:phone":"+43 512 575797",
    "sg:postcode":"6020",
    "sg:province":"Tirol",
    "wof:name":"internetpeople by Mecon Entwicklungs- und Marketingsgesellschaft mbH",
    "wof:placetype":"venue"
},
  "geometry": {"coordinates":[11.4312591553,47.2671852112],"type":"Point"}
}