{
  "type": "Feature",
  "properties": {
    "addr:full":"Kasernstr 12 Graz Steiermark 8010",
    "addr:housenumber":"12",
    "addr:postcode":"8010",
    "addr:street":"Kasernstr",
    "iso:country":"AT",
    "sg:address":"Kasernstr 12",
    "sg:city":"Graz",
    "sg:orig_category":"Lebensmittel / Einzelhandel",
    "sg:phone":"+43 316 462927",
    "sg:postcode":"8010",
    "sg:province":"Steiermark",
    "wof:name":"Zielpunkt Warenhandel GmbH & Co KG",
    "wof:placetype":"venue"
},
  "geometry": {"coordinates":[15.4432115555,47.0528755188],"type":"Point"}
}