{
  "type": "Feature",
  "properties": {
    "iso:country":"AT",
    "sg:address":"Kircheng 44",
    "sg:city":"Wien",
    "sg:orig_category":"Altwaren",
    "sg:phone":"+43 1 5238477",
    "sg:postcode":"1070",
    "sg:province":"Wien",
    "wof:name":"Anno 1900 - V Netolitzky",
    "wof:placetype":"venue"
},
  "geometry": {"coordinates":[16.3518047333,48.2044754028],"type":"Point"}
}