{
  "type": "Feature",
  "properties": {
    "iso:country":"AT",
    "sg:address":"D\u00f6rferstrasse 28c ",
    "sg:city":"Thaur",
    "sg:classifiers":[
        {
            "category":"Building & Trades",
            "subcategory":"Plumbing",
            "type":"Services"
        }
    ],
    "sg:phone":"+43 5223 493499",
    "sg:postcode":"6065",
    "sg:province":"Tirol",
    "sg:tags":[
        "supraregional",
        "gas"
    ],
    "wof:name":"GWH-Installationen",
    "wof:placetype":"venue"
},
  "geometry": {"coordinates":[11.4727048874,47.2938156128],"type":"Point"}
}