{
  "type": "Feature",
  "properties": {
    "iso:country":"AT",
    "sg:address":"Marktplatz 25",
    "sg:city":"St. Peter in der Au",
    "sg:classifiers":[
        {
            "category":"Education",
            "subcategory":"Special Training",
            "type":"Public Place"
        }
    ],
    "sg:phone":"+43 7477 42452",
    "sg:postcode":"3352",
    "sg:province":"Nieder\u00f6sterreich",
    "sg:tags":[
        "bread"
    ],
    "wof:name":"Franz Bittner",
    "wof:placetype":"venue"
},
  "geometry": {"coordinates":[11.0879554749,48.5816650391],"type":"Point"}
}