{
  "type": "Feature",
  "properties": {
    "addr:full":"Wehrg 2 Kitzb\u00fchel Tirol 6370",
    "addr:housenumber":"2",
    "addr:postcode":"6370",
    "addr:street":"Wehrg;Tirol",
    "iso:country":"AT",
    "sg:address":"Wehrg 2",
    "sg:city":"Kitzb\u00fchel",
    "sg:classifiers":[
        {
            "category":"Restaurant",
            "type":"Food & Drink"
        }
    ],
    "sg:phone":"+43 5356 661270",
    "sg:postcode":"6370",
    "sg:province":"Tirol",
    "wof:name":"Unterbergerstub'n",
    "wof:placetype":"venue"
},
  "geometry": {"coordinates":[12.396856308,47.4438018799],"type":"Point"}
}