{
  "type": "Feature",
  "properties": {
    "iso:country":"AT",
    "sg:address":"Hauptstr 17",
    "sg:city":"Sattledt",
    "sg:orig_category":"Blumeneinzelhandel",
    "sg:phone":"+43 7244 8451",
    "sg:postcode":"4642",
    "sg:province":"Ober\u00f6sterreich",
    "wof:name":"Blumen Krenmayr",
    "wof:placetype":"venue"
},
  "geometry": {"coordinates":[14.0562334061,48.0738716125],"type":"Point"}
}