{
  "type": "Feature",
  "properties": {
    "iso:country":"AT",
    "sg:city":"Riedau",
    "sg:orig_category":"Feuerwehren",
    "sg:phone":"+43 7764 8222",
    "sg:postcode":"4752",
    "sg:province":"Ober\u00f6sterreich",
    "wof:name":"Freiwillige Feuerwehr Riedau",
    "wof:placetype":"venue"
},
  "geometry": {"coordinates":[13.6335010529,48.3028488159],"type":"Point"}
}