{
  "type": "Feature",
  "properties": {
    "iso:country":"AT",
    "sg:address":"Gschwend 341",
    "sg:city":"Alberschwende",
    "sg:orig_category":"Wagnereien",
    "sg:phone":"+43 5579 4206",
    "sg:postcode":"6861",
    "sg:province":"Vorarlberg",
    "wof:name":"Johler Gebr\u00fcder OEG",
    "wof:placetype":"venue"
},
  "geometry": {"coordinates":[9.8203773499,47.4521408081],"type":"Point"}
}