{
  "type": "Feature",
  "properties": {
    "addr:full":"Triester Strasse 12a Wien Wien 1100",
    "addr:housenumber":"12a",
    "addr:postcode":"1100",
    "addr:street":"Triester Strasse",
    "iso:country":"AT",
    "sg:address":"Triester Strasse 12a",
    "sg:city":"Wien",
    "sg:classifiers":[
        {
            "category":"Autos & Motor Vehicles",
            "subcategory":"Auto Supplies",
            "type":"Retail Goods"
        }
    ],
    "sg:phone":"+43 1 60427670",
    "sg:postcode":"1100",
    "sg:province":"Wien",
    "sg:tags":[
        "car",
        "trailer"
    ],
    "sg:website":"spedition-wilfing.at",
    "wof:name":"G\u00fcnter Wilfing Ges.m.b.H.",
    "wof:placetype":"venue"
},
  "geometry": {"coordinates":[16.3568172455,48.1775550842],"type":"Point"}
}