{
  "type": "Feature",
  "properties": {
    "iso:country":"AT",
    "sg:address":"M\u00fcllerbachstrasse 25",
    "sg:city":"Gschwandt",
    "sg:classifiers":[
        {
            "category":"Banks & Credit Unions",
            "subcategory":"Investment Brokerage",
            "type":"Services"
        }
    ],
    "sg:phone":"+43 7612777700",
    "sg:postcode":"4816",
    "sg:province":"Ober\u00f6sterreich",
    "sg:tags":[
        "traditional",
        "brace",
        "costume"
    ],
    "sg:website":"luisesteiner.at",
    "wof:name":"Luise Steiner Trachtenaccessoires GesmbH",
    "wof:placetype":"venue"
},
  "geometry": {"coordinates":[13.8447246552,47.9346351624],"type":"Point"}
}