{
  "type": "Feature",
  "properties": {
    "addr:full":"Lange Zeile 109a Neckenmarkt Burgenland 7311",
    "addr:housenumber":"109a",
    "addr:postcode":"7311",
    "addr:street":"Lange Zeile",
    "iso:country":"AT",
    "sg:address":"Lange Zeile 109a",
    "sg:city":"Neckenmarkt",
    "sg:orig_category":"Isolierungen",
    "sg:phone":"+43 2610 43211",
    "sg:postcode":"7311",
    "sg:province":"Burgenland",
    "wof:name":"Wittmann Franz",
    "wof:placetype":"venue"
},
  "geometry": {"coordinates":[16.5409317017,47.6024398804],"type":"Point"}
}