{
  "type": "Feature",
  "properties": {
    "addr:full":"Schallmooser Hptstr 54 Salzburg Salzburg 5020",
    "addr:housenumber":"54",
    "addr:postcode":"5020",
    "addr:street":"Schallmooser;Salzburg",
    "iso:country":"AT",
    "sg:address":"Schallmooser Hptstr 54",
    "sg:city":"Salzburg",
    "sg:orig_category":"Tabaktrafiken",
    "sg:phone":"+43 662 640699",
    "sg:postcode":"5020",
    "sg:province":"Salzburg",
    "wof:name":"Gastberger Erich",
    "wof:placetype":"venue"
},
  "geometry": {"coordinates":[13.0624198914,47.8076820374],"type":"Point"}
}