{
  "type": "Feature",
  "properties": {
    "addr:full":"Ziffererg 16 Wien Wien 1220",
    "addr:housenumber":"16",
    "addr:postcode":"1220",
    "addr:street":"Ziffererg",
    "iso:country":"AT",
    "sg:address":"Ziffererg 16",
    "sg:city":"Wien",
    "sg:orig_category":"Psychotherapie",
    "sg:phone":"+43 1 7746314",
    "sg:postcode":"1220",
    "sg:province":"Wien",
    "wof:name":"Bischof Brigitte Dr",
    "wof:placetype":"venue"
},
  "geometry": {"coordinates":[16.5339221954,48.2271766663],"type":"Point"}
}