{
  "type": "Feature",
  "properties": {
    "addr:full":"Lambrechtg 5 Wien Wien 1040",
    "addr:housenumber":"5",
    "addr:postcode":"1040",
    "addr:street":"Lambrechtg",
    "iso:country":"AT",
    "sg:address":"Lambrechtg 5",
    "sg:city":"Wien",
    "sg:orig_category":"Speditionen",
    "sg:phone":"+43 1 5851157",
    "sg:postcode":"1040",
    "sg:province":"Wien",
    "wof:name":"Spedition Trade Trans Holding GesmbH",
    "wof:placetype":"venue"
},
  "geometry": {"coordinates":[16.3650112152,48.1899452209],"type":"Point"}
}