{
  "type": "Feature",
  "properties": {
    "addr:full":"Kleine Neug 10/9 Wien Wien 1040",
    "addr:housenumber":"10 / 9",
    "addr:postcode":"1040",
    "iso:country":"AT",
    "sg:address":"Kleine Neug 10/9",
    "sg:city":"Wien",
    "sg:orig_category":"Psychotherapie",
    "sg:phone":"+43 4315 866665",
    "sg:postcode":"1040",
    "sg:province":"Wien",
    "wof:name":"Tauer Heinz Dr",
    "wof:placetype":"venue"
},
  "geometry": {"coordinates":[16.3628864288,48.1931800842],"type":"Point"}
}