{
  "type": "Feature",
  "properties": {
    "addr:full":"Hauptstr 34 Ternberg Ober\u00f6sterreich 4452",
    "addr:housenumber":"34",
    "addr:postcode":"4452",
    "addr:street":"Hauptstr",
    "iso:country":"AT",
    "sg:address":"Hauptstr 34",
    "sg:city":"Ternberg",
    "sg:orig_category":"Massagen",
    "sg:phone":"+43 7256 8884",
    "sg:postcode":"4452",
    "sg:province":"Ober\u00f6sterreich",
    "wof:name":"Reisinger Sylvia",
    "wof:placetype":"venue"
},
  "geometry": {"coordinates":[14.3559961319,47.9441795349],"type":"Point"}
}