{
  "type": "Feature",
  "properties": {
    "addr:full":"Schottenfeldg 90 Wien Wien 1070",
    "addr:housenumber":"90",
    "addr:postcode":"1070",
    "addr:street":"Schottenfeldg",
    "iso:country":"AT",
    "sg:address":"Schottenfeldg 90",
    "sg:city":"Wien",
    "sg:orig_category":"Werbegrafik- U Grafik-Design",
    "sg:phone":"+43 1 5221356",
    "sg:postcode":"1070",
    "sg:province":"Wien",
    "wof:name":"Grafikstudio Albert Scoma",
    "wof:placetype":"venue"
},
  "geometry": {"coordinates":[16.3434009552,48.2067184448],"type":"Point"}
}