{
  "type": "Feature",
  "properties": {
    "iso:country":"AT",
    "sg:address":"Florianig 36",
    "sg:city":"Wien",
    "sg:orig_category":"Antiquariate",
    "sg:phone":"+43 1 4023906",
    "sg:postcode":"1080",
    "sg:province":"Wien",
    "wof:name":"Fr\u00f6hlich Helmut",
    "wof:placetype":"venue"
},
  "geometry": {"coordinates":[16.3484554291,48.2120819092],"type":"Point"}
}