{
  "type": "Feature",
  "properties": {
    "addr:full":"Hirtenberger Strasse 37 Leobersdorf Nieder\u00f6sterreich 2544",
    "addr:housenumber":"37",
    "addr:postcode":"2544",
    "addr:street":"Hirtenberger Strasse",
    "iso:country":"AT",
    "sg:address":"Hirtenberger Strasse 37",
    "sg:city":"Leobersdorf",
    "sg:classifiers":[
        {
            "category":"Ferry Terminal",
            "type":"Transportation"
        }
    ],
    "sg:phone":"+43 2256 64510",
    "sg:postcode":"2544",
    "sg:province":"Nieder\u00f6sterreich",
    "sg:tags":[
        "casual",
        "shirt"
    ],
    "wof:name":"Romeo + Julia Handelsges.m.b.H.",
    "wof:placetype":"venue"
},
  "geometry": {"coordinates":[16.2094497681,47.9327468872],"type":"Point"}
}