{
  "type": "Feature",
  "properties": {
    "addr:full":"Brucknergasse 16 Altheim Ober\u00f6sterreich 4950",
    "addr:housenumber":"16",
    "addr:postcode":"4950",
    "addr:street":"Brucknergasse",
    "iso:country":"AT",
    "sg:address":"Brucknergasse 16",
    "sg:city":"Altheim",
    "sg:classifiers":[
        {
            "category":"Manufacturing",
            "subcategory":"Tools & Machinery",
            "type":"Manufacturing & Wholesale Goods"
        }
    ],
    "sg:phone":"+43 7723 42265",
    "sg:postcode":"4950",
    "sg:province":"Ober\u00f6sterreich",
    "sg:tags":[
        "boring",
        "drilling"
    ],
    "wof:name":"Mattes Werkzeuge GmbH & Co KG",
    "wof:placetype":"venue"
},
  "geometry": {"coordinates":[13.2320013046,48.2511253357],"type":"Point"}
}