{
  "type": "Feature",
  "properties": {
    "addr:full":"Lambacher Str 7 Vorchdorf Ober\u00f6sterreich 4655",
    "addr:housenumber":"7",
    "addr:postcode":"4655",
    "addr:street":"Str",
    "iso:country":"AT",
    "sg:address":"Lambacher Str 7",
    "sg:city":"Vorchdorf",
    "sg:orig_category":"Boutiquen",
    "sg:phone":"+43 761420004",
    "sg:postcode":"4655",
    "sg:province":"Ober\u00f6sterreich",
    "wof:name":"StoffweXel Deine Mode",
    "wof:placetype":"venue"
},
  "geometry": {"coordinates":[13.9219141006,48.0040245056],"type":"Point"}
}