{
  "type": "Feature",
  "properties": {
    "addr:full":"Bundesstr. West 5  Lockenhaus Burgenland 7442",
    "addr:housenumber":"5",
    "addr:postcode":"7442",
    "addr:street":"West",
    "iso:country":"AT",
    "sg:address":"Bundesstr. West 5 ",
    "sg:city":"Lockenhaus",
    "sg:classifiers":[
        {
            "category":"Autos & Motor Vehicles",
            "subcategory":"Automobile Sales",
            "type":"Retail Goods"
        }
    ],
    "sg:phone":"+43 4326 162034",
    "sg:postcode":"7442",
    "sg:province":"Burgenland",
    "sg:tags":[
        "motor-cars"
    ],
    "wof:name":"JOSEF KALKBRENNER",
    "wof:placetype":"venue"
},
  "geometry": {"coordinates":[16.4179973602,47.4065856934],"type":"Point"}
}