{
  "type": "Feature",
  "properties": {
    "iso:country":"AT",
    "sg:address":"Innsbrucker Str 5",
    "sg:city":"Schwaz",
    "sg:orig_category":"Bankomat-Standorte",
    "sg:phone":"+43 5 05333",
    "sg:postcode":"6130",
    "sg:province":"Tirol",
    "wof:name":"Bankomat d BTV - Bank f Tirol und Vorarlberg AG",
    "wof:placetype":"venue"
},
  "geometry": {"coordinates":[11.7082328796,47.3446960449],"type":"Point"}
}