{
  "type": "Feature",
  "properties": {
    "addr:full":"Sonnbergpl 7 Wien Wien 1190",
    "addr:housenumber":"7",
    "addr:postcode":"1190",
    "addr:street":"Sonnbergpl",
    "iso:country":"AT",
    "sg:address":"Sonnbergpl 7",
    "sg:city":"Wien",
    "sg:orig_category":"Banken U Sparkassen",
    "sg:phone":"+43 4313 2034530",
    "sg:postcode":"1190",
    "sg:province":"Wien",
    "wof:name":"Bank f Arbeit u Wirtschaft AG",
    "wof:placetype":"venue"
},
  "geometry": {"coordinates":[16.3415031433,48.2429618835],"type":"Point"}
}