{
  "type": "Feature",
  "properties": {
    "addr:full":"Pelzrain 517 Bezau Vorarlberg 6870",
    "addr:housenumber":"517",
    "addr:postcode":"6870",
    "addr:street":"Pelzrain",
    "iso:country":"AT",
    "sg:address":"Pelzrain 517",
    "sg:city":"Bezau",
    "sg:orig_category":"Friseure U Frisiersalons",
    "sg:phone":"+43 4355 142085",
    "sg:postcode":"6870",
    "sg:province":"Vorarlberg",
    "wof:name":"J\u00e4ger Fritz",
    "wof:placetype":"venue"
},
  "geometry": {"coordinates":[9.8894395828,47.3772888184],"type":"Point"}
}