{
  "type": "Feature",
  "properties": {
    "addr:full":"Leo-Mathauser-G 2 Wien Wien 1230",
    "addr:housenumber":"2",
    "addr:postcode":"1230",
    "addr:street":"Leo-Mathauser-G",
    "iso:country":"AT",
    "sg:address":"Leo-Mathauser-G 2",
    "sg:city":"Wien",
    "sg:orig_category":"Autohandel",
    "sg:phone":"+43 1 6994817",
    "sg:postcode":"1230",
    "sg:province":"Wien",
    "wof:name":"Unterweger Karl",
    "wof:placetype":"venue"
},
  "geometry": {"coordinates":[16.3217830658,48.1358718872],"type":"Point"}
}