{
  "type": "Feature",
  "properties": {
    "addr:full":"Firmiang 9-11 Wien Wien 1130",
    "addr:housenumber":"9-11",
    "addr:postcode":"1130",
    "iso:country":"AT",
    "sg:address":"Firmiang 9-11",
    "sg:city":"Wien",
    "sg:classifiers":[
        {
            "category":"Travel",
            "subcategory":"Hotels & Motels",
            "type":"Entertainment"
        }
    ],
    "sg:phone":"+43 1 87761090",
    "sg:postcode":"1130",
    "sg:province":"Wien",
    "wof:name":"Schneider-G\u00f6ssl Magdalena",
    "wof:placetype":"venue"
},
  "geometry": {"coordinates":[16.2673721313,48.1890411377],"type":"Point"}
}