{
  "type": "Feature",
  "properties": {
    "addr:full":"Baumgarten 46 Reichenau im M\u00fchlkreis Ober\u00f6sterreich 4204",
    "addr:housenumber":"46",
    "addr:postcode":"4204",
    "addr:street":"Baumgarten;Im Muehlkreis Oberoesterreich",
    "iso:country":"AT",
    "sg:address":"Baumgarten 46",
    "sg:city":"Reichenau im M\u00fchlkreis",
    "sg:orig_category":"Massagen",
    "sg:phone":"+43 4372 118711",
    "sg:postcode":"4204",
    "sg:province":"Ober\u00f6sterreich",
    "wof:name":"Sailer Irmgard - Harmonie f K\u00f6rper Geist u Seele",
    "wof:placetype":"venue"
},
  "geometry": {"coordinates":[14.3540039062,48.4218597412],"type":"Point"}
}