{
  "type": "Feature",
  "properties": {
    "addr:full":"Kurt Ohnsorg-Weg 2 Wien Wien 1220",
    "addr:housenumber":"2",
    "addr:postcode":"1220",
    "iso:country":"AT",
    "sg:address":"Kurt Ohnsorg-Weg 2",
    "sg:city":"Wien",
    "sg:orig_category":"Papier- U Schreibwaren / Einzelhandel",
    "sg:phone":"+43 1 2599255",
    "sg:postcode":"1220",
    "sg:province":"Wien",
    "wof:name":"Cizek Eva",
    "wof:placetype":"venue"
},
  "geometry": {"coordinates":[16.4392642975,48.260887146],"type":"Point"}
}