{
  "type": "Feature",
  "properties": {
    "addr:full":"Bahnhofstr 1 Schwarzach Vorarlberg 6858",
    "addr:housenumber":"1",
    "addr:postcode":"6858",
    "addr:street":"Bahnhofstr",
    "iso:country":"AT",
    "sg:address":"Bahnhofstr 1",
    "sg:city":"Schwarzach",
    "sg:orig_category":"Personalbereitstellung",
    "sg:phone":"+43 4355 7241885",
    "sg:postcode":"6858",
    "sg:province":"Vorarlberg",
    "wof:name":"Stradner Industriemontagen GmbH",
    "wof:placetype":"venue"
},
  "geometry": {"coordinates":[9.7622833252,47.4441719055],"type":"Point"}
}