{
  "type": "Feature",
  "properties": {
    "addr:full":"Badstr 255 Neulengbach Nieder\u00f6sterreich 3040",
    "addr:housenumber":"255",
    "addr:postcode":"3040",
    "iso:country":"AT",
    "sg:address":"Badstr 255",
    "sg:city":"Neulengbach",
    "sg:orig_category":"Audiovisuelle Produktionen",
    "sg:phone":"+43 4327 725125111",
    "sg:postcode":"3040",
    "sg:province":"Nieder\u00f6sterreich",
    "wof:name":"Audiovision u Handel - Musik und Buchverlag",
    "wof:placetype":"venue"
},
  "geometry": {"coordinates":[15.9015245438,48.1926956177],"type":"Point"}
}