{
  "type": "Feature",
  "properties": {
    "iso:country":"AT",
    "sg:address":"Waltend Hauptstr 47 A",
    "sg:city":"Graz",
    "sg:orig_category":"Orientteppiche",
    "sg:phone":"+43 316 424842",
    "sg:postcode":"8010",
    "sg:province":"Steiermark",
    "wof:name":"Orientteppich Corner",
    "wof:placetype":"venue"
},
  "geometry": {"coordinates":[15.471613884,47.0671882629],"type":"Point"}
}