{
  "type": "Feature",
  "properties": {
    "addr:full":"Prechtlerstr. 29  Grieskirchen Ober\u00f6sterreich 4710",
    "addr:housenumber":"29",
    "addr:postcode":"4710",
    "addr:street":"Prechtlerstr.",
    "iso:country":"AT",
    "sg:address":"Prechtlerstr. 29 ",
    "sg:city":"Grieskirchen",
    "sg:classifiers":[
        {
            "category":"Banks & Credit Unions",
            "subcategory":"Financial Services",
            "type":"Services"
        }
    ],
    "sg:phone":"+43 4372 48660060",
    "sg:postcode":"4710",
    "sg:province":"Ober\u00f6sterreich",
    "sg:tags":[
        "banking",
        "finance",
        "insurance"
    ],
    "wof:name":"GENERALI VERSICHERUNGS AG",
    "wof:placetype":"venue"
},
  "geometry": {"coordinates":[13.8330059052,48.2339897156],"type":"Point"}
}