{
  "type": "Feature",
  "properties": {
    "addr:full":"Bartensteing 16/4/5 Wieselburg an der Erlauf Nieder\u00f6sterreich 3250",
    "addr:housenumber":"16 / 4 / 5",
    "addr:postcode":"3250",
    "addr:street":"Bartensteing",
    "iso:country":"AT",
    "sg:address":"Bartensteing 16/4/5",
    "sg:city":"Wieselburg an der Erlauf",
    "sg:orig_category":"Tischlereien",
    "sg:phone":"+43 4365 05403797",
    "sg:postcode":"3250",
    "sg:province":"Nieder\u00f6sterreich",
    "wof:name":"Kalcher & Kowalczyk OEG",
    "wof:placetype":"venue"
},
  "geometry": {"coordinates":[15.1380252838,48.1304283142],"type":"Point"}
}