{
  "type": "Feature",
  "properties": {
    "iso:country":"AT",
    "sg:address":"Lehenhofweg 1",
    "sg:city":"Hallwang",
    "sg:classifiers":[
        {
            "category":"Farming",
            "subcategory":"Livestock Farm",
            "type":"Manufacturing & Wholesale Goods"
        }
    ],
    "sg:phone":"+43 662 661243",
    "sg:postcode":"5300",
    "sg:province":"Salzburg",
    "sg:tags":[
        "-handel",
        "viehzucht",
        "u"
    ],
    "wof:name":"Gruber A Vieh- und FleischhandelsgesmbH",
    "wof:placetype":"venue"
},
  "geometry": {"coordinates":[13.0900774002,47.834980011],"type":"Point"}
}