{
  "type": "Feature",
  "properties": {
    "iso:country":"AT",
    "sg:address":"Messnerstr 28",
    "sg:city":"Klagenfurt",
    "sg:classifiers":[
        {
            "category":"Home & Garden",
            "subcategory":"Building Materials",
            "type":"Retail Goods"
        }
    ],
    "sg:phone":"+43 463 71155",
    "sg:postcode":"9020",
    "sg:province":"K\u00e4rnten",
    "sg:tags":[
        "baustoffe",
        "-material",
        "u"
    ],
    "wof:name":"Rabitsch Paul",
    "wof:placetype":"venue"
},
  "geometry": {"coordinates":[14.4005689621,46.6274719238],"type":"Point"}
}