{
  "type": "Feature",
  "properties": {
    "addr:full":"Tiroler Str 64 Silz Tirol 6424",
    "addr:postcode":"6424",
    "addr:street":"Str 64;Tirol",
    "iso:country":"AT",
    "sg:address":"Tiroler Str 64",
    "sg:city":"Silz",
    "sg:orig_category":"Bestattungsunternehmen",
    "sg:phone":"+43 4352 636516",
    "sg:postcode":"6424",
    "sg:province":"Tirol",
    "wof:name":"Bestattung Kihr GmbH",
    "wof:placetype":"venue"
},
  "geometry": {"coordinates":[10.9299545288,47.2664604187],"type":"Point"}
}