{
  "type": "Feature",
  "properties": {
    "addr:full":"Bahnhofstr 8 Amstetten Nieder\u00f6sterreich 3300",
    "addr:housenumber":"8",
    "addr:postcode":"3300",
    "addr:street":"Bahnhofstr;Niederoesterreich",
    "iso:country":"AT",
    "sg:address":"Bahnhofstr 8",
    "sg:city":"Amstetten",
    "sg:orig_category":"Werbeagenturen",
    "sg:phone":"+43 7472 67521",
    "sg:postcode":"3300",
    "sg:province":"Nieder\u00f6sterreich",
    "wof:name":"ART ATTACK ING MAYERHOFER WERBEAGENTUR",
    "wof:placetype":"venue"
},
  "geometry": {"coordinates":[14.8782682419,48.12317276],"type":"Point"}
}