{
  "type": "Feature",
  "properties": {
    "addr:full":"Brucker Bundesstr 22 Zell am See Salzburg 5700",
    "addr:housenumber":"22",
    "addr:postcode":"5700",
    "addr:street":"Salzburg",
    "iso:country":"AT",
    "sg:address":"Brucker Bundesstr 22",
    "sg:city":"Zell am See",
    "sg:orig_category":"Druckereien",
    "sg:phone":"+43 6542 70336",
    "sg:postcode":"5700",
    "sg:province":"Salzburg",
    "sg:website":"druckerei-streitberger.at",
    "wof:name":"Streitberger Siegfried",
    "wof:placetype":"venue"
},
  "geometry": {"coordinates":[12.7948083878,47.3199577332],"type":"Point"}
}