{
  "type": "Feature",
  "properties": {
    "addr:full":"Bierbaumer Str 14 Unterpremst\u00e4tten Steiermark 8141",
    "addr:postcode":"8141",
    "addr:street":"Str 14 Unterpremstaetten Steiermark",
    "iso:country":"AT",
    "sg:address":"Bierbaumer Str 14",
    "sg:city":"Unterpremst\u00e4tten",
    "sg:orig_category":"Telekommunikation",
    "sg:phone":"+43 3136 53500",
    "sg:postcode":"8141",
    "sg:province":"Steiermark",
    "wof:name":"Muster Gerald",
    "wof:placetype":"venue"
},
  "geometry": {"coordinates":[15.4143791199,46.9660758972],"type":"Point"}
}