{
  "type": "Feature",
  "properties": {
    "addr:full":"Petschnitzen Eggerstr 19 Ledenitzen K\u00e4rnten 9581",
    "addr:housenumber":"19",
    "addr:postcode":"9581",
    "addr:street":"Kaernten",
    "iso:country":"AT",
    "sg:address":"Petschnitzen Eggerstr 19",
    "sg:city":"Ledenitzen",
    "sg:orig_category":"Pensionen / Privatzimmer",
    "sg:phone":"+43 4342 542322",
    "sg:postcode":"9581",
    "sg:province":"K\u00e4rnten",
    "wof:name":"Pension Theresienhof",
    "wof:placetype":"venue"
},
  "geometry": {"coordinates":[13.9657592773,46.5657997131],"type":"Point"}
}