{
  "type": "Feature",
  "properties": {
    "addr:full":"Nr 35 Pfarrwerfen Salzburg 5452",
    "addr:postcode":"5452",
    "addr:street":"Nr 35;Salzburg",
    "iso:country":"AT",
    "sg:address":"Nr 35",
    "sg:city":"Pfarrwerfen",
    "sg:orig_category":"Erdarbeiten",
    "sg:phone":"+43 6468 7422",
    "sg:postcode":"5452",
    "sg:province":"Salzburg",
    "wof:name":"Lottermoser Josef",
    "wof:placetype":"venue"
},
  "geometry": {"coordinates":[13.2045021057,47.457233429],"type":"Point"}
}