{
  "type": "Feature",
  "properties": {
    "addr:full":"Nonntaler Hauptstrasse 23 Salzburg Salzburg 5020",
    "addr:housenumber":"23",
    "addr:postcode":"5020",
    "addr:street":"Nonntaler Hauptstrasse;Salzburg",
    "iso:country":"AT",
    "sg:address":"Nonntaler Hauptstrasse 23",
    "sg:city":"Salzburg",
    "sg:classifiers":[
        {
            "category":"Home & Garden",
            "subcategory":"Home Furnishings",
            "type":"Retail Goods"
        }
    ],
    "sg:phone":"+43 662 842245",
    "sg:postcode":"5020",
    "sg:province":"Salzburg",
    "sg:tags":[
        "knob",
        "handle",
        "furniture"
    ],
    "sg:website":"susa-dog.com",
    "wof:name":"Helmut Enzinger",
    "wof:placetype":"venue"
},
  "geometry": {"coordinates":[13.0508260727,47.7941131592],"type":"Point"}
}