{
  "type": "Feature",
  "properties": {
    "addr:full":"Kaltenberg Strasse 34 Hart Steiermark 8075",
    "addr:housenumber":"34",
    "addr:postcode":"8075",
    "addr:street":"Kaltenberg Strasse",
    "iso:country":"AT",
    "sg:address":"Kaltenberg Strasse 34",
    "sg:city":"Hart",
    "sg:classifiers":[
        {
            "category":"Home & Garden",
            "subcategory":"Building Materials",
            "type":"Retail Goods"
        }
    ],
    "sg:phone":"+43 316 324223",
    "sg:postcode":"8075",
    "sg:province":"Steiermark",
    "sg:tags":[
        "fire-proof"
    ],
    "wof:name":"Magnolithe Ges.m.b.H.",
    "wof:placetype":"venue"
},
  "geometry": {"coordinates":[15.5431108475,47.0650596619],"type":"Point"}
}