{
  "type": "Feature",
  "properties": {
    "addr:full":"Schneebergstrasse 35 Puchberg am Schneeberg Nieder\u00f6sterreich 2734",
    "addr:housenumber":"35",
    "addr:postcode":"2734",
    "addr:street":"Schneebergstrasse",
    "iso:country":"AT",
    "sg:address":"Schneebergstrasse 35",
    "sg:city":"Puchberg am Schneeberg",
    "sg:classifiers":[
        {
            "category":"Military Area",
            "subcategory":"Air Force Base",
            "type":"Public Place"
        }
    ],
    "sg:phone":"+43 2636 2217",
    "sg:postcode":"2734",
    "sg:province":"Nieder\u00f6sterreich",
    "sg:tags":[
        "attic",
        "stair"
    ],
    "wof:name":"Ing. Franz Panzenb\u00f6ck KG",
    "wof:placetype":"venue"
},
  "geometry": {"coordinates":[15.9079437256,47.7894248962],"type":"Point"}
}