{
  "type": "Feature",
  "properties": {
    "addr:full":"Grazer Str 2 St. Stefan im Rosental Steiermark 8083",
    "addr:housenumber":"2",
    "addr:postcode":"8083",
    "addr:street":"Str",
    "iso:country":"AT",
    "sg:address":"Grazer Str 2",
    "sg:city":"St. Stefan im Rosental",
    "sg:orig_category":"Apotheken",
    "sg:phone":"+43 4331 1683440",
    "sg:postcode":"8083",
    "sg:province":"Steiermark",
    "wof:name":"Rosen-Apotheke u Drogerie",
    "wof:placetype":"venue"
},
  "geometry": {"coordinates":[15.7112693787,46.9041175842],"type":"Point"}
}