{
  "type": "Feature",
  "properties": {
    "addr:full":"Kreutererstr 49 Bad Ischl Ober\u00f6sterreich 4820",
    "addr:housenumber":"49",
    "addr:postcode":"4820",
    "addr:street":"Kreutererstr",
    "iso:country":"AT",
    "sg:address":"Kreutererstr 49",
    "sg:city":"Bad Ischl",
    "sg:orig_category":"Automaten",
    "sg:phone":"+43 664 2659948",
    "sg:postcode":"4820",
    "sg:province":"Ober\u00f6sterreich",
    "wof:name":"Automaten Loidl",
    "wof:placetype":"venue"
},
  "geometry": {"coordinates":[13.5960998535,47.7218399048],"type":"Point"}
}