{
  "type": "Feature",
  "properties": {
    "addr:full":"Landstr 56 Zwettl Nieder\u00f6sterreich 3910",
    "addr:housenumber":"56",
    "addr:postcode":"3910",
    "addr:street":"Landstr;Niederoesterreich",
    "iso:country":"AT",
    "sg:address":"Landstr 56",
    "sg:city":"Zwettl",
    "sg:orig_category":"Textilwaren / Einzelhandel",
    "sg:phone":"+43 2822 54004",
    "sg:postcode":"3910",
    "sg:province":"Nieder\u00f6sterreich",
    "wof:name":"Robl Marianne",
    "wof:placetype":"venue"
},
  "geometry": {"coordinates":[15.1657810211,48.6064720154],"type":"Point"}
}