{
  "type": "Feature",
  "properties": {
    "addr:full":"Dammstr 4/Im Achpark Lauterach Vorarlberg 6923",
    "addr:housenumber":"4 / im",
    "addr:postcode":"6923",
    "addr:street":"Dammstr;Achpark",
    "iso:country":"AT",
    "sg:address":"Dammstr 4/Im Achpark",
    "sg:city":"Lauterach",
    "sg:orig_category":"Blumeneinzelhandel",
    "sg:phone":"+43 5574 71472",
    "sg:postcode":"6923",
    "sg:province":"Vorarlberg",
    "wof:name":"Blumenhof - Blumen & Geschenke HandelsgmbH",
    "wof:placetype":"venue"
},
  "geometry": {"coordinates":[9.7314901352,47.4773216248],"type":"Point"}
}