{
  "type": "Feature",
  "properties": {
    "addr:full":"Wiesenberg 4 Pram Ober\u00f6sterreich 4742",
    "addr:housenumber":"4",
    "addr:postcode":"4742",
    "addr:street":"Wiesenberg",
    "iso:country":"AT",
    "sg:address":"Wiesenberg 4",
    "sg:city":"Pram",
    "sg:orig_category":"Massagen",
    "sg:phone":"+43 7736 6006",
    "sg:postcode":"4742",
    "sg:province":"Ober\u00f6sterreich",
    "wof:name":"Huber Anita",
    "wof:placetype":"venue"
},
  "geometry": {"coordinates":[13.6034326553,48.2324562073],"type":"Point"}
}