{
  "type": "Feature",
  "properties": {
    "addr:full":"Stiegergasse 12 Wien Wien 1150",
    "addr:housenumber":"12",
    "addr:postcode":"1150",
    "addr:street":"Stiegergasse",
    "iso:country":"AT",
    "sg:address":"Stiegergasse 12",
    "sg:city":"Wien",
    "sg:classifiers":[
        {
            "category":"Manufacturing",
            "subcategory":"Metals",
            "type":"Manufacturing & Wholesale Goods"
        }
    ],
    "sg:phone":"+43 1 8936707",
    "sg:postcode":"1150",
    "sg:province":"Wien",
    "sg:tags":[
        "cutting",
        "saws",
        "blade",
        "saw"
    ],
    "wof:name":"Johann Schweiger",
    "wof:placetype":"venue"
},
  "geometry": {"coordinates":[16.334154129,48.1868896484],"type":"Point"}
}