{
  "type": "Feature",
  "properties": {
    "addr:full":"Waldstr 27 Retz Nieder\u00f6sterreich 2070",
    "addr:housenumber":"27",
    "addr:postcode":"2070",
    "addr:street":"Waldstr",
    "iso:country":"AT",
    "sg:address":"Waldstr 27",
    "sg:city":"Retz",
    "sg:orig_category":"Weine / Einzelhandel",
    "sg:phone":"+43 4329 4231314",
    "sg:postcode":"2070",
    "sg:province":"Nieder\u00f6sterreich",
    "wof:name":"Stangl Siegfried",
    "wof:placetype":"venue"
},
  "geometry": {"coordinates":[15.9697294235,48.7837715149],"type":"Point"}
}