{
  "type": "Feature",
  "properties": {
    "iso:country":"AT",
    "sg:address":"Siebenhirtenstrasse 12",
    "sg:city":"Wien",
    "sg:classifiers":[
        {
            "category":"Banks & Credit Unions",
            "subcategory":"Investment Brokerage",
            "type":"Services"
        }
    ],
    "sg:phone":"+43 1 863750",
    "sg:postcode":"1230",
    "sg:province":"Wien",
    "sg:tags":[
        "batteries",
        "primary",
        "secondary"
    ],
    "sg:website":"at.varta.com",
    "wof:name":"\u00d6FA - Akkumulatoren Ges.m.b.H.",
    "wof:placetype":"venue"
},
  "geometry": {"coordinates":[16.290895462,48.1338005066],"type":"Point"}
}