{
  "type": "Feature",
  "properties": {
    "addr:full":"Favoritenstr 34 Wien Wien 1040",
    "addr:housenumber":"34",
    "addr:postcode":"1040",
    "addr:street":"Favoritenstr",
    "iso:country":"AT",
    "sg:address":"Favoritenstr 34",
    "sg:city":"Wien",
    "sg:orig_category":"Psychotherapie",
    "sg:phone":"+43 1 5052163",
    "sg:postcode":"1040",
    "sg:province":"Wien",
    "wof:name":"Fr\u00e4ser Renate",
    "wof:placetype":"venue"
},
  "geometry": {"coordinates":[16.3707332611,48.191986084],"type":"Point"}
}