{
  "type": "Feature",
  "properties": {
    "addr:full":"Seepromenade 50 D\u00f6briach K\u00e4rnten 9873",
    "addr:housenumber":"50",
    "addr:postcode":"9873",
    "addr:street":"Seepromenade;Kaernten",
    "iso:country":"AT",
    "sg:address":"Seepromenade 50",
    "sg:city":"D\u00f6briach",
    "sg:orig_category":"Appartements / Ferienwohnungen",
    "sg:phone":"+43 4342 4677740",
    "sg:postcode":"9873",
    "sg:province":"K\u00e4rnten",
    "wof:name":"Strandappartements Burgstaller",
    "wof:placetype":"venue"
},
  "geometry": {"coordinates":[9.6596899033,47.818321228],"type":"Point"}
}