{
  "type": "Feature",
  "properties": {
    "iso:country":"AT",
    "sg:address":"Reisnerstr 53",
    "sg:city":"Wien",
    "sg:orig_category":"Werbeagenturen",
    "sg:phone":"+43 1 7146685",
    "sg:postcode":"1030",
    "sg:province":"Wien",
    "wof:name":"Zement & Beton Handels- und WerbegesmbH",
    "wof:placetype":"venue"
},
  "geometry": {"coordinates":[16.3839073181,48.1966209412],"type":"Point"}
}