{
  "type": "Feature",
  "properties": {
    "addr:full":"Deutsch Goritz 113 Deutsch Goritz Steiermark 8483",
    "addr:housenumber":"113",
    "addr:postcode":"8483",
    "addr:street":"Deutsch Goritz",
    "iso:country":"AT",
    "sg:address":"Deutsch Goritz 113",
    "sg:city":"Deutsch Goritz",
    "sg:classifiers":[
        {
            "category":"Military Area",
            "subcategory":"Air Force Base",
            "type":"Public Place"
        }
    ],
    "sg:phone":"+43 3474 7364",
    "sg:postcode":"8483",
    "sg:province":"Steiermark",
    "sg:tags":[
        "appliance",
        "assembly",
        "electric"
    ],
    "wof:name":"Horwath & Bodenlenz Sanit\u00e4r B\u00e4der Heizung Ges.m.b.H.",
    "wof:placetype":"venue"
},
  "geometry": {"coordinates":[15.8311033249,46.7535629272],"type":"Point"}
}