{
  "type": "Feature",
  "properties": {
    "addr:full":"Nr 67 Eberschwang Ober\u00f6sterreich 4906",
    "addr:postcode":"4906",
    "addr:street":"Nr;Eberschwang",
    "iso:country":"AT",
    "sg:address":"Nr 67",
    "sg:city":"Eberschwang",
    "sg:orig_category":"Volksschulen",
    "sg:phone":"+43 4377 532009",
    "sg:postcode":"4906",
    "sg:province":"Ober\u00f6sterreich",
    "wof:name":"Volksschule",
    "wof:placetype":"venue"
},
  "geometry": {"coordinates":[13.5620698929,48.154460907],"type":"Point"}
}