{
  "type": "Feature",
  "properties": {
    "addr:full":"Hauptstr 414 Mayrhofen Tirol 6290",
    "addr:housenumber":"414",
    "addr:postcode":"6290",
    "addr:street":"Hauptstr;Tirol",
    "iso:country":"AT",
    "sg:address":"Hauptstr 414",
    "sg:city":"Mayrhofen",
    "sg:orig_category":"Appartements / Ferienwohnungen",
    "sg:phone":"+43 4352 8562215",
    "sg:postcode":"6290",
    "sg:province":"Tirol",
    "sg:website":"kostner.at",
    "wof:name":"Kostner Carl-Peter",
    "wof:placetype":"venue"
},
  "geometry": {"coordinates":[11.8632459641,47.1678237915],"type":"Point"}
}