{
  "type": "Feature",
  "properties": {
    "addr:full":"Nr 99 Gasen Steiermark 8616",
    "addr:postcode":"8616",
    "addr:street":"Nr",
    "iso:country":"AT",
    "sg:address":"Nr 99",
    "sg:city":"Gasen",
    "sg:orig_category":"Feuerwehren",
    "sg:phone":"+43 3171 222",
    "sg:postcode":"8616",
    "sg:province":"Steiermark",
    "wof:name":"Freiwillige Feuerwehr",
    "wof:placetype":"venue"
},
  "geometry": {"coordinates":[15.5710201263,47.3835105896],"type":"Point"}
}