{
  "type": "Feature",
  "properties": {
    "iso:country":"AT",
    "sg:address":"Nr 1",
    "sg:city":"Allhaming",
    "sg:orig_category":"Non-Classified Establishments",
    "sg:phone":"+43 7227 7105",
    "sg:postcode":"4511",
    "sg:province":"Ober\u00f6sterreich",
    "wof:name":"Pfarramt",
    "wof:placetype":"venue"
},
  "geometry": {"coordinates":[14.1709213257,48.152923584],"type":"Point"}
}