{
  "type": "Feature",
  "properties": {
    "iso:country":"AT",
    "sg:address":"Rieder Str 28",
    "sg:city":"Aurolzm\u00fcnster",
    "sg:orig_category":"Installationsunternehmen",
    "sg:phone":"+43 4377 5283615",
    "sg:postcode":"4971",
    "sg:province":"Ober\u00f6sterreich",
    "wof:name":"WELLCOM Haustechnik GmbH",
    "wof:placetype":"venue"
},
  "geometry": {"coordinates":[13.457529068,48.2449378967],"type":"Point"}
}