{
  "type": "Feature",
  "properties": {
    "iso:country":"AT",
    "sg:address":"Neuer Markt 18",
    "sg:city":"Zwettl",
    "sg:orig_category":"Tanzcafes",
    "sg:phone":"+43 2822 52866",
    "sg:postcode":"3910",
    "sg:province":"Nieder\u00f6sterreich",
    "wof:name":"Gschwantner Johann",
    "wof:placetype":"venue"
},
  "geometry": {"coordinates":[15.1683588028,48.6063423157],"type":"Point"}
}