{
  "type": "Feature",
  "properties": {
    "addr:full":"Swarovskistr 58 Wattens Tirol 6112",
    "addr:housenumber":"58",
    "addr:postcode":"6112",
    "addr:street":"Swarovskistr;Tirol",
    "iso:country":"AT",
    "sg:address":"Swarovskistr 58",
    "sg:city":"Wattens",
    "sg:orig_category":"Geschenkartikel",
    "sg:phone":"+43 5224 55550",
    "sg:postcode":"6112",
    "sg:province":"Tirol",
    "wof:name":"Crystalp Schmuck GmbH - Modeschmuck und Geschenkartikel",
    "wof:placetype":"venue"
},
  "geometry": {"coordinates":[11.5898303986,47.2984886169],"type":"Point"}
}