{
  "type": "Feature",
  "properties": {
    "iso:country":"AT",
    "sg:address":"Nr 88",
    "sg:city":"Berwang",
    "sg:orig_category":"Appartements / Ferienwohnungen",
    "sg:phone":"+43 5674 81510",
    "sg:postcode":"6622",
    "sg:province":"Tirol",
    "wof:name":"Alpenrose Appartements",
    "wof:placetype":"venue"
},
  "geometry": {"coordinates":[10.7468204498,47.4090003967],"type":"Point"}
}