{
  "type": "Feature",
  "properties": {
    "addr:full":"Schulg 10 Rechnitz Burgenland 7471",
    "addr:housenumber":"10",
    "addr:postcode":"7471",
    "addr:street":"Schulg",
    "iso:country":"AT",
    "sg:address":"Schulg 10",
    "sg:city":"Rechnitz",
    "sg:orig_category":"Musikunterricht",
    "sg:phone":"+43 3363 7931914",
    "sg:postcode":"7471",
    "sg:province":"Burgenland",
    "wof:name":"Musikschule",
    "wof:placetype":"venue"
},
  "geometry": {"coordinates":[16.4403247833,47.3056755066],"type":"Point"}
}