{
  "type": "Feature",
  "properties": {
    "addr:full":"Josef-Fuhs-Str 7 Bisamberg Nieder\u00f6sterreich 2102",
    "addr:housenumber":"7",
    "addr:postcode":"2102",
    "addr:street":"Josef-Fuhs-Str",
    "iso:country":"AT",
    "sg:address":"Josef-Fuhs-Str 7",
    "sg:city":"Bisamberg",
    "sg:orig_category":"Innenausbau",
    "sg:phone":"+43 4322 62629000",
    "sg:postcode":"2102",
    "sg:province":"Nieder\u00f6sterreich",
    "wof:name":"Veleta Rudolf Ing GesmbH & Co KG",
    "wof:placetype":"venue"
},
  "geometry": {"coordinates":[16.3687038422,48.3454933167],"type":"Point"}
}