{
  "type": "Feature",
  "properties": {
    "addr:full":"R\u00f6hrensteig 2 Drosendorf an der Thaya Nieder\u00f6sterreich 2095",
    "addr:housenumber":"2",
    "addr:postcode":"2095",
    "addr:street":"Roehrensteig;An Der Thaya",
    "iso:country":"AT",
    "sg:address":"R\u00f6hrensteig 2",
    "sg:city":"Drosendorf an der Thaya",
    "sg:orig_category":"Polizei U Gendarmerie",
    "sg:phone":"+43 4359 1333433",
    "sg:postcode":"2095",
    "sg:province":"Nieder\u00f6sterreich",
    "wof:name":"Gendarmerie Grenz\u00fcberwachungsposten",
    "wof:placetype":"venue"
},
  "geometry": {"coordinates":[15.6201000214,48.8681297302],"type":"Point"}
}