{
  "type": "Feature",
  "properties": {
    "addr:full":"Alte Landstr 39 Bludenz Vorarlberg 6700",
    "addr:housenumber":"39",
    "addr:postcode":"6700",
    "addr:street":"Alte Landstr",
    "iso:country":"AT",
    "sg:address":"Alte Landstr 39",
    "sg:city":"Bludenz",
    "sg:orig_category":"Druckereien",
    "sg:phone":"+43 4355 5262169",
    "sg:postcode":"6700",
    "sg:province":"Vorarlberg",
    "wof:name":"Druckerei Schuricht GesmbH",
    "wof:placetype":"venue"
},
  "geometry": {"coordinates":[9.8137798309,47.1612243652],"type":"Point"}
}