{
  "type": "Feature",
  "properties": {
    "addr:full":"Waldbachsteig 20 Wien Wien 1190",
    "addr:housenumber":"20",
    "addr:postcode":"1190",
    "addr:street":"Waldbachsteig",
    "iso:country":"AT",
    "sg:address":"Waldbachsteig 20",
    "sg:city":"Wien",
    "sg:orig_category":"Behinderungen / Leben Mit Behinderungen",
    "sg:phone":"+43 1 3188225",
    "sg:postcode":"1190",
    "sg:province":"Wien",
    "wof:name":"GIN Gemeinwesenintegration und Normalisierung",
    "wof:placetype":"venue"
},
  "geometry": {"coordinates":[16.349521637,48.2751159668],"type":"Point"}
}