{
  "type": "Feature",
  "properties": {
    "iso:country":"AT",
    "sg:address":"Heidenreichsteiner Str 27",
    "sg:city":"Waidhofen an der Thaya",
    "sg:orig_category":"Eisen",
    "sg:phone":"+43 4328 42526160",
    "sg:postcode":"3830",
    "sg:province":"Nieder\u00f6sterreich",
    "wof:name":"Roth Eisen HandelsgesmbH",
    "wof:placetype":"venue"
},
  "geometry": {"coordinates":[15.2769088745,48.8184928894],"type":"Point"}
}