{
  "type": "Feature",
  "properties": {
    "iso:country":"AT",
    "sg:address":"Hutweideng 7/2/2",
    "sg:city":"Wien",
    "sg:orig_category":"Nachhilfe U Lernbetreuung",
    "sg:phone":"+43 4313 680147",
    "sg:postcode":"1190",
    "sg:province":"Wien",
    "sg:website":"spanischunterricht.at",
    "wof:name":"Bagur Juan Carlos Spanischunterricht",
    "wof:placetype":"venue"
},
  "geometry": {"coordinates":[16.3493022919,48.2389793396],"type":"Point"}
}