{
  "type": "Feature",
  "properties": {
    "addr:full":"Schoberpa\u00df Bundesstr 51 Trieben Steiermark 8784",
    "addr:housenumber":"51",
    "addr:postcode":"8784",
    "iso:country":"AT",
    "sg:address":"Schoberpa\u00df Bundesstr 51",
    "sg:city":"Trieben",
    "sg:orig_category":"Billardcafes",
    "sg:phone":"+43 3615 3449",
    "sg:postcode":"8784",
    "sg:province":"Steiermark",
    "wof:name":"Billardzentrum K\u00f6",
    "wof:placetype":"venue"
},
  "geometry": {"coordinates":[14.4831371307,47.489025116],"type":"Point"}
}