{
  "type": "Feature",
  "properties": {
    "addr:full":"Jessenigstr 4 Velden am W\u00f6rther See K\u00e4rnten 9220",
    "addr:housenumber":"4",
    "addr:postcode":"9220",
    "addr:street":"Jessenigstr;Kaernten",
    "iso:country":"AT",
    "sg:address":"Jessenigstr 4",
    "sg:city":"Velden am W\u00f6rther See",
    "sg:orig_category":"Metalle U -Halbfabrikate",
    "sg:phone":"+43 4342 7441000",
    "sg:postcode":"9220",
    "sg:province":"K\u00e4rnten",
    "wof:name":"IMR - Mechatronic-Sondermaschinen GmbH",
    "wof:placetype":"venue"
},
  "geometry": {"coordinates":[13.9944562912,46.6043624878],"type":"Point"}
}