{
  "type": "Feature",
  "properties": {
    "iso:country":"AT",
    "sg:address":"Bader Moser-Str 30",
    "sg:city":"Micheldorf in Ober\u00f6sterreich",
    "sg:orig_category":"Bekleidung / Einzelhandel",
    "sg:phone":"+43 7582 60794",
    "sg:postcode":"4563",
    "sg:province":"Ober\u00f6sterreich",
    "wof:name":"adessa Moden GmbH",
    "wof:placetype":"venue"
},
  "geometry": {"coordinates":[14.1282281876,47.8756523132],"type":"Point"}
}