{
  "type": "Feature",
  "properties": {
    "iso:country":"AT",
    "sg:address":"Walgaustr 3a",
    "sg:city":"Sulz-R\u00f6this",
    "sg:classifiers":[
        {
            "category":"Professional",
            "subcategory":"Art Services",
            "type":"Services"
        }
    ],
    "sg:phone":"+43 4355 2248198",
    "sg:postcode":"6832",
    "sg:province":"Vorarlberg",
    "sg:tags":[
        "designer"
    ],
    "wof:name":"Divine Designs GmbH",
    "wof:placetype":"venue"
},
  "geometry": {"coordinates":[-111.49155426030001,39.7735061646],"type":"Point"}
}