{
  "type": "Feature",
  "properties": {
    "addr:full":"Wilhelm-Kienzl-Str 6 Bad Aussee Steiermark 8990",
    "addr:housenumber":"6",
    "addr:postcode":"8990",
    "addr:street":"Wilhelm-Kienzl-Str",
    "iso:country":"AT",
    "sg:address":"Wilhelm-Kienzl-Str 6",
    "sg:city":"Bad Aussee",
    "sg:orig_category":"Holzhandel",
    "sg:phone":"+43 4336 2252493",
    "sg:postcode":"8990",
    "sg:province":"Steiermark",
    "wof:name":"Haim Albert",
    "wof:placetype":"venue"
},
  "geometry": {"coordinates":[13.7685604095,47.607673645],"type":"Point"}
}