{
  "type": "Feature",
  "properties": {
    "addr:full":"Marinellig 13-15 Wien Wien 1020",
    "addr:postcode":"13-15;1020",
    "iso:country":"AT",
    "sg:address":"Marinellig 13-15",
    "sg:city":"Wien",
    "sg:orig_category":"Holzbearbeitungsmaschinen U -Werkzeuge",
    "sg:phone":"+43 1 2188534",
    "sg:postcode":"1020",
    "sg:province":"Wien",
    "wof:name":"Dollmann Norbert",
    "wof:placetype":"venue"
},
  "geometry": {"coordinates":[16.3879375458,48.2253227234],"type":"Point"}
}