{
  "type": "Feature",
  "properties": {
    "addr:full":"Griesingerg 26/6 Wien Wien 1140",
    "addr:housenumber":"26 / 6",
    "addr:postcode":"1140",
    "addr:street":"Griesingerg",
    "iso:country":"AT",
    "sg:address":"Griesingerg 26/6",
    "sg:city":"Wien",
    "sg:orig_category":"Steuerberatung",
    "sg:phone":"+43 1 9113134",
    "sg:postcode":"1140",
    "sg:province":"Wien",
    "wof:name":"Amon Andrea & Partner Buchhaltungsgesellschaft",
    "wof:placetype":"venue"
},
  "geometry": {"coordinates":[16.2753620148,48.2046585083],"type":"Point"}
}