{
  "type": "Feature",
  "properties": {
    "addr:full":"Untere Hauptstr 78 Wulkaprodersdorf Burgenland 7041",
    "addr:housenumber":"78",
    "addr:postcode":"7041",
    "addr:street":"Untere Hauptstr",
    "iso:country":"AT",
    "sg:address":"Untere Hauptstr 78",
    "sg:city":"Wulkaprodersdorf",
    "sg:orig_category":"Pensionen / Privatzimmer",
    "sg:phone":"+43 2687 62148",
    "sg:postcode":"7041",
    "sg:province":"Burgenland",
    "wof:name":"Wutschitz Herbert",
    "wof:placetype":"venue"
},
  "geometry": {"coordinates":[16.4852294922,47.7737312317],"type":"Point"}
}