{
  "type": "Feature",
  "properties": {
    "iso:country":"AT",
    "sg:address":"Berg 37",
    "sg:city":"Anthering",
    "sg:orig_category":"Fotografen",
    "sg:phone":"+43 6223 32960",
    "sg:postcode":"5102",
    "sg:province":"Salzburg",
    "sg:website":"schatzl.at",
    "wof:name":"Schatzl Bruno",
    "wof:placetype":"venue"
},
  "geometry": {"coordinates":[13.0322294235,47.8813858032],"type":"Point"}
}