{
  "type": "Feature",
  "properties": {
    "addr:full":"Meerbothstr 22 Villach K\u00e4rnten 9500",
    "addr:housenumber":"22",
    "addr:postcode":"9500",
    "addr:street":"Meerbothstr;Kaernten",
    "iso:country":"AT",
    "sg:address":"Meerbothstr 22",
    "sg:city":"Villach",
    "sg:classifiers":[
        {
            "category":"Restaurant",
            "type":"Food & Drink"
        }
    ],
    "sg:phone":"+43 4242 281050",
    "sg:postcode":"9500",
    "sg:province":"K\u00e4rnten",
    "sg:website":"restaurant-urbani.at",
    "wof:name":"Urbani-Weinstuben",
    "wof:placetype":"venue"
},
  "geometry": {"coordinates":[13.8516407013,46.6205635071],"type":"Point"}
}