{
  "type": "Feature",
  "properties": {
    "addr:full":"Niederkappel Ober\u00f6sterreich 4133",
    "addr:postcode":"4133",
    "iso:country":"AT",
    "sg:city":"Niederkappel",
    "sg:orig_category":"Volksschulen",
    "sg:phone":"+43 7286 8514",
    "sg:postcode":"4133",
    "sg:province":"Ober\u00f6sterreich",
    "wof:name":"Volksschule",
    "wof:placetype":"venue"
},
  "geometry": {"coordinates":[13.8806123734,48.4651412964],"type":"Point"}
}