{
  "type": "Feature",
  "properties": {
    "addr:full":"Untere Hauptstr 29 Maria Lanzendorf Nieder\u00f6sterreich 2326",
    "addr:housenumber":"29",
    "addr:postcode":"2326",
    "addr:street":"Untere Hauptstr",
    "iso:country":"AT",
    "sg:address":"Untere Hauptstr 29",
    "sg:city":"Maria Lanzendorf",
    "sg:orig_category":"Installationsunternehmen",
    "sg:phone":"+43 2235 42679",
    "sg:postcode":"2326",
    "sg:province":"Nieder\u00f6sterreich",
    "wof:name":"Schraml Johann",
    "wof:placetype":"venue"
},
  "geometry": {"coordinates":[16.4445037842,48.1107444763],"type":"Point"}
}