{
  "type": "Feature",
  "properties": {
    "iso:country":"AT",
    "sg:address":"Pfaffing 11",
    "sg:city":"Munderfing",
    "sg:orig_category":"Tauchsportschulen U -Vereine",
    "sg:phone":"+43 7744 8425",
    "sg:postcode":"5222",
    "sg:province":"Ober\u00f6sterreich",
    "wof:name":"Tauchschule Barth Michael",
    "wof:placetype":"venue"
},
  "geometry": {"coordinates":[13.1497793198,48.0647201538],"type":"Point"}
}