{
  "type": "Feature",
  "properties": {
    "addr:full":"Zamenhofstr 9 Linz Ober\u00f6sterreich 4020",
    "addr:housenumber":"9",
    "addr:postcode":"4020",
    "addr:street":"Zamenhofstr",
    "iso:country":"AT",
    "sg:address":"Zamenhofstr 9",
    "sg:city":"Linz",
    "sg:orig_category":"Zeitungen U Zeitschriften / Vertrieb",
    "sg:phone":"+43 4373 2696420",
    "sg:postcode":"4020",
    "sg:province":"Ober\u00f6sterreich",
    "wof:name":"PLM VertriebsgesmbH",
    "wof:placetype":"venue"
},
  "geometry": {"coordinates":[14.3157339096,48.2889671326],"type":"Point"}
}