{
  "type": "Feature",
  "properties": {
    "addr:full":"Bogenstr 3 Ybbs an der Donau Nieder\u00f6sterreich 3370",
    "addr:housenumber":"3",
    "addr:postcode":"3370",
    "addr:street":"Bogenstr",
    "iso:country":"AT",
    "sg:address":"Bogenstr 3",
    "sg:city":"Ybbs an der Donau",
    "sg:orig_category":"Fahrschulen",
    "sg:phone":"+43 7412 527110",
    "sg:postcode":"3370",
    "sg:province":"Nieder\u00f6sterreich",
    "wof:name":"Easy Drivers Ybbs, Fichtinger",
    "wof:placetype":"venue"
},
  "geometry": {"coordinates":[15.083398819,48.1744422913],"type":"Point"}
}