{
  "type": "Feature",
  "properties": {
    "iso:country":"AT",
    "sg:address":"Hart 13",
    "sg:city":"Leonding",
    "sg:classifiers":[
        {
            "category":"Organizations",
            "subcategory":"Community Association",
            "type":"Services"
        }
    ],
    "sg:phone":"+43 4373 2797310",
    "sg:postcode":"4060",
    "sg:province":"Ober\u00f6sterreich",
    "sg:tags":[
        "relation",
        "public"
    ],
    "sg:website":"softnomics.at",
    "wof:name":"Softnomics Jeschke GmbH & Co KEG Werbe-u PR-Agentur, Focus on Difference",
    "wof:placetype":"venue"
},
  "geometry": {"coordinates":[14.2491264343,48.2792434692],"type":"Point"}
}