{
  "type": "Feature",
  "properties": {
    "addr:full":"Seeblick 16 Walchsee Tirol 6344",
    "addr:housenumber":"16",
    "addr:postcode":"6344",
    "addr:street":"Seeblick;Tirol",
    "iso:country":"AT",
    "sg:address":"Seeblick 16",
    "sg:city":"Walchsee",
    "sg:orig_category":"Pensionen / Privatzimmer",
    "sg:phone":"+43 5374 5348",
    "sg:postcode":"6344",
    "sg:province":"Tirol",
    "wof:name":"Pension Daxer",
    "wof:placetype":"venue"
},
  "geometry": {"coordinates":[12.3116197586,47.6386260986],"type":"Point"}
}