{
  "type": "Feature",
  "properties": {
    "addr:full":"Seedorf 5 Weyregg am Attersee Ober\u00f6sterreich 4852",
    "addr:housenumber":"5",
    "addr:postcode":"4852",
    "addr:street":"Seedorf",
    "iso:country":"AT",
    "sg:address":"Seedorf 5",
    "sg:city":"Weyregg am Attersee",
    "sg:orig_category":"Pensionen / Privatzimmer",
    "sg:phone":"+43 76642220",
    "sg:postcode":"4852",
    "sg:province":"Ober\u00f6sterreich",
    "wof:name":"Huber Rosi",
    "wof:placetype":"venue"
},
  "geometry": {"coordinates":[13.5671405792,47.9026832581],"type":"Point"}
}