{
  "type": "Feature",
  "properties": {
    "addr:full":"Franz-Wolfram-Scherer-Str 38a Bergheim Salzburg 5101",
    "addr:housenumber":"38a",
    "addr:postcode":"5101",
    "addr:street":"Franz-Wolfram-Scherer-Str;Salzburg",
    "iso:country":"AT",
    "sg:address":"Franz-Wolfram-Scherer-Str 38a",
    "sg:city":"Bergheim",
    "sg:orig_category":"Transportunternehmen",
    "sg:phone":"+43 4366 2663090",
    "sg:postcode":"5101",
    "sg:province":"Salzburg",
    "wof:name":"Webersdorfer Theo GmbH",
    "wof:placetype":"venue"
},
  "geometry": {"coordinates":[13.0230998993,47.8411369324],"type":"Point"}
}