{
  "type": "Feature",
  "properties": {
    "addr:full":"Rebhuhnweg 5 Puntigam Steiermark 8055",
    "addr:housenumber":"5",
    "addr:postcode":"8055",
    "addr:street":"Rebhuhnweg",
    "iso:country":"AT",
    "sg:address":"Rebhuhnweg 5",
    "sg:city":"Puntigam",
    "sg:orig_category":"Baumpflege, -Schutz U -Chirurgie",
    "sg:phone":"+43 4331 6296310",
    "sg:postcode":"8055",
    "sg:province":"Steiermark",
    "wof:name":"Toni's Dienstleistungen",
    "wof:placetype":"venue"
},
  "geometry": {"coordinates":[15.4357566833,47.0356292725],"type":"Point"}
}