{
  "type": "Feature",
  "properties": {
    "addr:full":"Habertstr 7-9 Gmunden Ober\u00f6sterreich 4810",
    "addr:housenumber":"7-9",
    "addr:postcode":"4810",
    "addr:street":"Habertstr;Oberoesterreich",
    "iso:country":"AT",
    "sg:address":"Habertstr 7-9",
    "sg:city":"Gmunden",
    "sg:orig_category":"Hauptschulen",
    "sg:phone":"+43 761271284",
    "sg:postcode":"4810",
    "sg:province":"Ober\u00f6sterreich",
    "wof:name":"Hauptschule Hebbel",
    "wof:placetype":"venue"
},
  "geometry": {"coordinates":[13.7986679077,47.9199981689],"type":"Point"}
}