{
  "type": "Feature",
  "properties": {
    "addr:full":"F Reisenbichler-Str 2A Gmunden Ober\u00f6sterreich 4810",
    "addr:housenumber":"2a",
    "addr:postcode":"4810",
    "addr:street":"Oberoesterreich",
    "iso:country":"AT",
    "sg:address":"F Reisenbichler-Str 2A",
    "sg:city":"Gmunden",
    "sg:orig_category":"Marketingberatung",
    "sg:phone":"+43 761273330",
    "sg:postcode":"4810",
    "sg:province":"Ober\u00f6sterreich",
    "wof:name":"Harrer Marketing & Design Webdesign & Internet Consulting Team",
    "wof:placetype":"venue"
},
  "geometry": {"coordinates":[13.7870025635,47.9138031006],"type":"Point"}
}