{
  "type": "Feature",
  "properties": {
    "iso:country":"AT",
    "sg:address":"Freisingstr 8",
    "sg:city":"Innsbruck",
    "sg:orig_category":"Blumeneinzelhandel",
    "sg:phone":"+43 512 582152",
    "sg:postcode":"6020",
    "sg:province":"Tirol",
    "wof:name":"Petra's Blumenshop",
    "wof:placetype":"venue"
},
  "geometry": {"coordinates":[11.3871440887,47.2590255737],"type":"Point"}
}