{
  "type": "Feature",
  "properties": {
    "addr:full":"Dorfstr 40 Fritzens Tirol 6122",
    "addr:housenumber":"40",
    "addr:postcode":"6122",
    "addr:street":"Dorfstr;Tirol",
    "iso:country":"AT",
    "sg:address":"Dorfstr 40",
    "sg:city":"Fritzens",
    "sg:orig_category":"Elektroinstallationsunternehmen",
    "sg:phone":"+43 5224 514880",
    "sg:postcode":"6122",
    "sg:province":"Tirol",
    "wof:name":"Riwitec OEG",
    "wof:placetype":"venue"
},
  "geometry": {"coordinates":[11.5898456573,47.3061904907],"type":"Point"}
}