{
  "type": "Feature",
  "properties": {
    "addr:full":"Nr 21 Minihof-Liebau Burgenland 8384",
    "addr:postcode":"8384",
    "addr:street":"Nr;Minihof-Liebau",
    "iso:country":"AT",
    "sg:address":"Nr 21",
    "sg:city":"Minihof-Liebau",
    "sg:orig_category":"Volksschulen",
    "sg:phone":"+43 4333 292870",
    "sg:postcode":"8384",
    "sg:province":"Burgenland",
    "wof:name":"Volksschule",
    "wof:placetype":"venue"
},
  "geometry": {"coordinates":[16.0747261047,46.8825569153],"type":"Point"}
}