{
  "type": "Feature",
  "properties": {
    "addr:full":"Lastbergstr 64 Rekawinkel Nieder\u00f6sterreich 3031",
    "addr:housenumber":"64",
    "addr:postcode":"3031",
    "addr:street":"Lastbergstr",
    "iso:country":"AT",
    "sg:address":"Lastbergstr 64",
    "sg:city":"Rekawinkel",
    "sg:orig_category":"Tonstudios",
    "sg:phone":"+43 2233 536830",
    "sg:postcode":"3031",
    "sg:province":"Nieder\u00f6sterreich",
    "wof:name":"Teletone Audio- & Werbeproduktionen GesmbH",
    "wof:placetype":"venue"
},
  "geometry": {"coordinates":[16.0241127014,48.1794509888],"type":"Point"}
}