{
  "type": "Feature",
  "properties": {
    "addr:full":"Gnaninger Str 82 Fernitz Steiermark 8072",
    "addr:housenumber":"82",
    "addr:postcode":"8072",
    "addr:street":"Str",
    "iso:country":"AT",
    "sg:address":"Gnaninger Str 82",
    "sg:city":"Fernitz",
    "sg:orig_category":"Personalbereitstellung",
    "sg:phone":"+43 3135 47611",
    "sg:postcode":"8072",
    "sg:province":"Steiermark",
    "wof:name":"Leingruber Personalbereitstellung GmbH",
    "wof:placetype":"venue"
},
  "geometry": {"coordinates":[15.5299415588,46.9725418091],"type":"Point"}
}