{
  "type": "Feature",
  "properties": {
    "addr:full":"Untere Klaus 159 Schladming Steiermark 8970",
    "addr:housenumber":"159",
    "addr:postcode":"8970",
    "addr:street":"Untere Klaus",
    "iso:country":"AT",
    "sg:address":"Untere Klaus 159",
    "sg:city":"Schladming",
    "sg:orig_category":"Innenausbau",
    "sg:phone":"+43 3687 23181",
    "sg:postcode":"8970",
    "sg:province":"Steiermark",
    "wof:name":"Dirlinger Gerhard",
    "wof:placetype":"venue"
},
  "geometry": {"coordinates":[13.7011709213,47.4016685486],"type":"Point"}
}