{
  "type": "Feature",
  "properties": {
    "addr:full":"Wiener Str 18 Tulln an der Donau Nieder\u00f6sterreich 3430",
    "addr:postcode":"3430",
    "iso:country":"AT",
    "sg:address":"Wiener Str 18",
    "sg:city":"Tulln an der Donau",
    "sg:orig_category":"Juweliere, Gold- U Silberschmiede",
    "sg:phone":"+43 4322 7264760",
    "sg:postcode":"3430",
    "sg:province":"Nieder\u00f6sterreich",
    "wof:name":"Tullner Schmuckkastl - Grotschar GesmbH",
    "wof:placetype":"venue"
},
  "geometry": {"coordinates":[16.0562782288,48.3314857483],"type":"Point"}
}