{
  "type": "Feature",
  "properties": {
    "addr:full":"Br\u00e4uerg 13 Enns Ober\u00f6sterreich 4470",
    "addr:housenumber":"13",
    "addr:postcode":"4470",
    "addr:street":"Braeuerg",
    "iso:country":"AT",
    "sg:address":"Br\u00e4uerg 13",
    "sg:city":"Enns",
    "sg:orig_category":"Fotografen",
    "sg:phone":"+43 7223 83270",
    "sg:postcode":"4470",
    "sg:province":"Ober\u00f6sterreich",
    "wof:name":"Fotostudio Ulrike",
    "wof:placetype":"venue"
},
  "geometry": {"coordinates":[14.476858139,48.2139015198],"type":"Point"}
}