{
  "type": "Feature",
  "properties": {
    "addr:full":"Nr 5 St. Martin am Grimming Steiermark 8954",
    "addr:housenumber":"5",
    "addr:postcode":"8954",
    "addr:street":"Nr;Am Grimming Steiermark",
    "iso:country":"AT",
    "sg:address":"Nr 5",
    "sg:city":"St. Martin am Grimming",
    "sg:orig_category":"Appartements / Ferienwohnungen",
    "sg:phone":"+43 4336 842335",
    "sg:postcode":"8954",
    "sg:province":"Steiermark",
    "wof:name":"Christerbauerhof",
    "wof:placetype":"venue"
},
  "geometry": {"coordinates":[13.981344223,47.4888725281],"type":"Point"}
}