{
  "type": "Feature",
  "properties": {
    "addr:full":"Am Messezentrum 6 5021",
    "addr:housenumber":"6",
    "addr:postcode":"5021",
    "addr:street":"Am Messezentrum",
    "iso:country":"AT",
    "sg:address":"Am Messezentrum 6",
    "sg:orig_category":"Dienstleistungen, Messen U Veranstaltungen",
    "sg:phone":"+43 4306 2244770",
    "sg:postcode":"5021",
    "sg:website":"http://www.reedexpo.at",
    "wof:name":"Reed Messe Salzburg GmbH.",
    "wof:placetype":"venue"
},
  "geometry": {"coordinates":[13.0279626846,47.8223457336],"type":"Point"}
}