{
  "type": "Feature",
  "properties": {
    "addr:full":"G\u00e4rtnerstr 63 Wels Ober\u00f6sterreich 4600",
    "addr:housenumber":"63",
    "addr:postcode":"4600",
    "addr:street":"Gaertnerstr;Oberoesterreich",
    "iso:country":"AT",
    "sg:address":"G\u00e4rtnerstr 63",
    "sg:city":"Wels",
    "sg:orig_category":"Werbeagenturen",
    "sg:phone":"+43 699 12734020",
    "sg:postcode":"4600",
    "sg:province":"Ober\u00f6sterreich",
    "wof:name":"Bohensky & Pesendorfer OEG",
    "wof:placetype":"venue"
},
  "geometry": {"coordinates":[14.036532402,48.1700401306],"type":"Point"}
}