{
  "type": "Feature",
  "properties": {
    "addr:full":"Huglg 16 Wien Wien 1150",
    "addr:housenumber":"16",
    "addr:postcode":"1150",
    "addr:street":"Huglg",
    "iso:country":"AT",
    "sg:address":"Huglg 16",
    "sg:city":"Wien",
    "sg:orig_category":"Maler, Anstreicher U Lackierer",
    "sg:phone":"+43 4314 058306",
    "sg:postcode":"1150",
    "sg:province":"Wien",
    "wof:name":"Gros Hans Egon Dkfm Dr",
    "wof:placetype":"venue"
},
  "geometry": {"coordinates":[16.3260269165,48.1968803406],"type":"Point"}
}