{
  "type": "Feature",
  "properties": {
    "iso:country":"AT",
    "sg:address":"Fanny-El\u00dfler-G 3",
    "sg:city":"Eisenstadt",
    "sg:orig_category":"Textilwaren / Einzelhandel",
    "sg:phone":"+43 4326 8272172",
    "sg:postcode":"7000",
    "sg:province":"Burgenland",
    "wof:name":"KA International Eisenstadt Prasser Angela",
    "wof:placetype":"venue"
},
  "geometry": {"coordinates":[16.5234088898,47.8458900452],"type":"Point"}
}