{
  "type": "Feature",
  "properties": {
    "addr:full":"Hauptpl 16 Wieselburg an der Erlauf Nieder\u00f6sterreich 3250",
    "addr:housenumber":"16",
    "addr:postcode":"3250",
    "addr:street":"Hauptpl",
    "iso:country":"AT",
    "sg:address":"Hauptpl 16",
    "sg:city":"Wieselburg an der Erlauf",
    "sg:orig_category":"Banken U Sparkassen",
    "sg:phone":"+43 4374 16523060",
    "sg:postcode":"3250",
    "sg:province":"Nieder\u00f6sterreich",
    "wof:name":"Bankomat d Volksbank \u00f6tscherland regGenmbH",
    "wof:placetype":"venue"
},
  "geometry": {"coordinates":[15.138677597,48.1312637329],"type":"Point"}
}