{
  "type": "Feature",
  "properties": {
    "addr:full":"Ortnerg 7 Klosterneuburg Nieder\u00f6sterreich 3400",
    "addr:housenumber":"7",
    "addr:postcode":"3400",
    "addr:street":"Ortnerg;Niederoesterreich",
    "iso:country":"AT",
    "sg:address":"Ortnerg 7",
    "sg:city":"Klosterneuburg",
    "sg:orig_category":"Friseure U Frisiersalons",
    "sg:phone":"+43 4322 4325213",
    "sg:postcode":"3400",
    "sg:province":"Nieder\u00f6sterreich",
    "wof:name":"Frisierstube Martha",
    "wof:placetype":"venue"
},
  "geometry": {"coordinates":[16.3233089447,48.3051528931],"type":"Point"}
}