{
  "type": "Feature",
  "properties": {
    "addr:full":"Elisabethstr 5 Mauerbach Nieder\u00f6sterreich 3001",
    "addr:housenumber":"5",
    "addr:postcode":"3001",
    "addr:street":"Elisabethstr",
    "iso:country":"AT",
    "sg:address":"Elisabethstr 5",
    "sg:city":"Mauerbach",
    "sg:orig_category":"Sonnenschutzanlagen",
    "sg:phone":"+43 1 9792464",
    "sg:postcode":"3001",
    "sg:province":"Nieder\u00f6sterreich",
    "wof:name":"Qualytecs Handels-GmbH",
    "wof:placetype":"venue"
},
  "geometry": {"coordinates":[16.1642303467,48.2432403564],"type":"Point"}
}