{
  "type": "Feature",
  "properties": {
    "iso:country":"AT",
    "sg:address":"Nelkeng 3",
    "sg:city":"Wien",
    "sg:orig_category":"Tanzcafes",
    "sg:phone":"+43 1 5871233",
    "sg:postcode":"1060",
    "sg:province":"Wien",
    "wof:name":"Tanzcafe Jenseits",
    "wof:placetype":"venue"
},
  "geometry": {"coordinates":[16.3519020081,48.1984024048],"type":"Point"}
}