{
  "type": "Feature",
  "properties": {
    "addr:full":"Knoppen 16 Kainisch Steiermark 8984",
    "addr:housenumber":"16",
    "addr:postcode":"8984",
    "addr:street":"Knoppen",
    "iso:country":"AT",
    "sg:address":"Knoppen 16",
    "sg:city":"Kainisch",
    "sg:orig_category":"Tischlereien",
    "sg:phone":"+43 4336 2421142",
    "sg:postcode":"8984",
    "sg:province":"Steiermark",
    "wof:name":"Egger Franz jun",
    "wof:placetype":"venue"
},
  "geometry": {"coordinates":[13.8641996384,47.5671234131],"type":"Point"}
}