{
  "type": "Feature",
  "properties": {
    "addr:full":"Auf der Schanz 34A/5 Wien Wien 1230",
    "addr:housenumber":"34a / 5",
    "addr:postcode":"1230",
    "addr:street":"Auf Der Schanz",
    "iso:country":"AT",
    "sg:address":"Auf der Schanz 34A/5",
    "sg:city":"Wien",
    "sg:orig_category":"Marketingberatung",
    "sg:phone":"+43 1 3709607",
    "sg:postcode":"1230",
    "sg:province":"Wien",
    "wof:name":"Plus Media Marketing Services GmbH",
    "wof:placetype":"venue"
},
  "geometry": {"coordinates":[16.3063201904,48.1211738586],"type":"Point"}
}