{
  "type": "Feature",
  "properties": {
    "addr:full":"Jauring 120 Aflenz Kurort Steiermark 8623",
    "addr:housenumber":"120",
    "addr:postcode":"8623",
    "addr:street":"Jauring",
    "iso:country":"AT",
    "sg:address":"Jauring 120",
    "sg:city":"Aflenz Kurort",
    "sg:orig_category":"Transportunternehmen",
    "sg:phone":"+43 4338 6132133",
    "sg:postcode":"8623",
    "sg:province":"Steiermark",
    "wof:name":"Pierer-TransportgesmbH",
    "wof:placetype":"venue"
},
  "geometry": {"coordinates":[15.2517900467,47.5474700928],"type":"Point"}
}