{
  "type": "Feature",
  "properties": {
    "iso:country":"AT",
    "sg:address":"Sackstr 24",
    "sg:city":"Graz",
    "sg:orig_category":"Juweliere, Gold- U Silberschmiede",
    "sg:phone":"+43 4366 49033239",
    "sg:postcode":"8010",
    "sg:province":"Steiermark",
    "wof:name":"Hofer Schmuckatelier",
    "wof:placetype":"venue"
},
  "geometry": {"coordinates":[15.4359083176,47.0734977722],"type":"Point"}
}