{
  "type": "Feature",
  "properties": {
    "addr:full":"Mantlerg 26 Wien Wien 1130",
    "addr:housenumber":"26",
    "addr:postcode":"1130",
    "addr:street":"Mantlerg",
    "iso:country":"AT",
    "sg:address":"Mantlerg 26",
    "sg:city":"Wien",
    "sg:orig_category":"Hausbetreuung",
    "sg:phone":"+43 1 87667950",
    "sg:postcode":"1130",
    "sg:province":"Wien",
    "wof:name":"Seckar Andrea",
    "wof:placetype":"venue"
},
  "geometry": {"coordinates":[16.2804470062,48.1904373169],"type":"Point"}
}