{
  "type": "Feature",
  "properties": {
    "addr:full":"Gartenstr 52 Wilhering Ober\u00f6sterreich 4073",
    "addr:housenumber":"52",
    "addr:postcode":"4073",
    "addr:street":"Gartenstr",
    "iso:country":"AT",
    "sg:address":"Gartenstr 52",
    "sg:city":"Wilhering",
    "sg:orig_category":"Apotheken",
    "sg:phone":"+43 7226 20001",
    "sg:postcode":"4073",
    "sg:province":"Ober\u00f6sterreich",
    "wof:name":"Apotheke Wilhering",
    "wof:placetype":"venue"
},
  "geometry": {"coordinates":[14.1667995453,48.2991638184],"type":"Point"}
}