{
  "type": "Feature",
  "properties": {
    "addr:full":"Porzellang 22 Wien Wien 1090",
    "addr:housenumber":"22",
    "addr:postcode":"1090",
    "addr:street":"Porzellang",
    "iso:country":"AT",
    "sg:address":"Porzellang 22",
    "sg:city":"Wien",
    "sg:orig_category":"Architekten",
    "sg:phone":"+43 1 3195841",
    "sg:postcode":"1090",
    "sg:province":"Wien",
    "wof:name":"Ioannou Themistoklis Dipl-Ing",
    "wof:placetype":"venue"
},
  "geometry": {"coordinates":[16.3610229492,48.2207107544],"type":"Point"}
}