{
  "type": "Feature",
  "properties": {
    "iso:country":"AT",
    "sg:address":"Alser Str 51",
    "sg:city":"Wien",
    "sg:orig_category":"Handschuhe, Lederwaren / Einzelhandel",
    "sg:phone":"+43 4314 051332",
    "sg:postcode":"1080",
    "sg:province":"Wien",
    "wof:name":"Stadlbauer Renee",
    "wof:placetype":"venue"
},
  "geometry": {"coordinates":[16.3451404572,48.2151451111],"type":"Point"}
}