{
  "type": "Feature",
  "properties": {
    "addr:full":"Opernring 4 Wien Wien 1010",
    "addr:housenumber":"4",
    "addr:postcode":"1010",
    "addr:street":"Opernring",
    "iso:country":"AT",
    "sg:address":"Opernring 4",
    "sg:city":"Wien",
    "sg:orig_category":"Finanz- U Wirtschaftsberatung",
    "sg:phone":"+43 1 515930",
    "sg:postcode":"1010",
    "sg:province":"Wien",
    "wof:name":"fonds&co Fondsanteilsvermittlung AG",
    "wof:placetype":"venue"
},
  "geometry": {"coordinates":[16.367723465,48.202999115],"type":"Point"}
}