{
  "type": "Feature",
  "properties": {
    "addr:full":"Kircheng. 32 Feldkirchen in K\u00e4rnten K\u00e4rnten 9560",
    "addr:housenumber":"32",
    "addr:postcode":"9560",
    "addr:street":"Kircheng.;Kaernten",
    "iso:country":"AT",
    "sg:address":"Kircheng. 32",
    "sg:city":"Feldkirchen in K\u00e4rnten",
    "sg:classifiers":[
        {
            "category":"Professional",
            "subcategory":"Printing & Photocopies",
            "type":"Services"
        }
    ],
    "sg:phone":"+43 4342 762339",
    "sg:postcode":"9560",
    "sg:province":"K\u00e4rnten",
    "wof:name":"WULFENIA-DRUCK GES.MBH",
    "wof:placetype":"venue"
},
  "geometry": {"coordinates":[14.071928978,46.6842193604],"type":"Point"}
}