{
  "type": "Feature",
  "properties": {
    "addr:full":"Fasang 35-37 Wien Wien 1030",
    "addr:postcode":"35-37;1030",
    "iso:country":"AT",
    "sg:address":"Fasang 35-37",
    "sg:city":"Wien",
    "sg:orig_category":"Textilreinigung",
    "sg:phone":"+43 1 7983982",
    "sg:postcode":"1030",
    "sg:province":"Wien",
    "wof:name":"Hammerl & Hammerl GesmbH",
    "wof:placetype":"venue"
},
  "geometry": {"coordinates":[16.3858394623,48.1908950806],"type":"Point"}
}