{
  "type": "Feature",
  "properties": {
    "iso:country":"AT",
    "sg:address":"Nordlandstr. 1",
    "sg:city":"Amstetten",
    "sg:classifiers":[
        {
            "category":"Autos & Motor Vehicles",
            "subcategory":"Boat Sales",
            "type":"Retail Goods"
        }
    ],
    "sg:phone":"+43 4374 72685660",
    "sg:postcode":"3300",
    "sg:province":"Nieder\u00f6sterreich",
    "wof:name":"THERMAX GMBH",
    "wof:placetype":"venue"
},
  "geometry": {"coordinates":[14.8364677429,48.106552124],"type":"Point"}
}