{
  "type": "Feature",
  "properties": {
    "iso:country":"AT",
    "sg:address":"Seefeld 20",
    "sg:city":"Steinbach am Attersee",
    "sg:orig_category":"Appartements / Ferienwohnungen",
    "sg:phone":"+43 4376 63788",
    "sg:postcode":"4853",
    "sg:province":"Ober\u00f6sterreich",
    "wof:name":"Schwaiger Johannes",
    "wof:placetype":"venue"
},
  "geometry": {"coordinates":[13.5463905334,47.8399047852],"type":"Point"}
}