{
  "type": "Feature",
  "properties": {
    "addr:full":"Bundesstrasse 30 Tenneck Salzburg 5451",
    "addr:housenumber":"30",
    "addr:postcode":"5451",
    "addr:street":"Bundesstrasse;Salzburg",
    "iso:country":"AT",
    "sg:address":"Bundesstrasse 30",
    "sg:city":"Tenneck",
    "sg:classifiers":[
        {
            "category":"Manufacturing",
            "subcategory":"Building Materials",
            "type":"Manufacturing & Wholesale Goods"
        }
    ],
    "sg:phone":"+43 6468 77010",
    "sg:postcode":"5451",
    "sg:province":"Salzburg",
    "sg:tags":[
        "cement"
    ],
    "sg:website":"erberit.at",
    "wof:name":"Christian Ehrensberger Ges.m.b.H.",
    "wof:placetype":"venue"
},
  "geometry": {"coordinates":[13.1728010178,47.4982414246],"type":"Point"}
}