{
  "type": "Feature",
  "properties": {
    "addr:full":"Grazer Str 96 Wiener Neustadt Nieder\u00f6sterreich 2700",
    "addr:postcode":"2700",
    "addr:street":"Str 96",
    "iso:country":"AT",
    "sg:address":"Grazer Str 96",
    "sg:city":"Wiener Neustadt",
    "sg:orig_category":"Restaurants: Chinesisch",
    "sg:phone":"+43 2622 24470",
    "sg:postcode":"2700",
    "sg:province":"Nieder\u00f6sterreich",
    "wof:name":"China-Restaurant Lee-Dynasty",
    "wof:placetype":"venue"
},
  "geometry": {"coordinates":[16.2449645996,47.8110351562],"type":"Point"}
}