{
  "type": "Feature",
  "properties": {
    "addr:full":"Spingeserstr 14 Innsbruck Tirol 6020",
    "addr:housenumber":"14",
    "addr:postcode":"6020",
    "addr:street":"Spingeserstr;Tirol",
    "iso:country":"AT",
    "sg:address":"Spingeserstr 14",
    "sg:city":"Innsbruck",
    "sg:orig_category":"Non-Classified Establishments",
    "sg:phone":"+43 512 263124",
    "sg:postcode":"6020",
    "sg:province":"Tirol",
    "wof:name":"Pfarramt St Piu X",
    "wof:placetype":"venue"
},
  "geometry": {"coordinates":[11.4387817383,47.2744865417],"type":"Point"}
}