{
  "type": "Feature",
  "properties": {
    "addr:full":"Hieflauer Str 53a Eisenerz Steiermark 8790",
    "addr:housenumber":"53a",
    "addr:postcode":"8790",
    "addr:street":"Str",
    "iso:country":"AT",
    "sg:address":"Hieflauer Str 53a",
    "sg:city":"Eisenerz",
    "sg:orig_category":"Reifen U Reifendienste",
    "sg:phone":"+43 4338 482669",
    "sg:postcode":"8790",
    "sg:province":"Steiermark",
    "wof:name":"Reifen Service St\u00f6bbauer",
    "wof:placetype":"venue"
},
  "geometry": {"coordinates":[14.8717298508,47.5543670654],"type":"Point"}
}