{
  "type": "Feature",
  "properties": {
    "addr:full":"Haspelh\u00e4user 106 Kirchberg am Walde Nieder\u00f6sterreich 3932",
    "addr:housenumber":"106",
    "addr:postcode":"3932",
    "addr:street":"Kirchberg Am Walde",
    "iso:country":"AT",
    "sg:address":"Haspelh\u00e4user 106",
    "sg:city":"Kirchberg am Walde",
    "sg:orig_category":"Autoreparatur",
    "sg:phone":"+43 2854 3876",
    "sg:postcode":"3932",
    "sg:province":"Nieder\u00f6sterreich",
    "wof:name":"KFZ - Mayer",
    "wof:placetype":"venue"
},
  "geometry": {"coordinates":[15.1063957214,48.7351417542],"type":"Point"}
}