{
  "type": "Feature",
  "properties": {
    "addr:full":"Auf der Au 5 Bad Zell Ober\u00f6sterreich 4283",
    "addr:housenumber":"5",
    "addr:postcode":"4283",
    "addr:street":"Auf Der Au",
    "iso:country":"AT",
    "sg:address":"Auf der Au 5",
    "sg:city":"Bad Zell",
    "sg:orig_category":"Autobusunternehmen",
    "sg:phone":"+43 7263 7300",
    "sg:postcode":"4283",
    "sg:province":"Ober\u00f6sterreich",
    "wof:name":"Sunzenauer Alois",
    "wof:placetype":"venue"
},
  "geometry": {"coordinates":[14.6728191376,48.3500022888],"type":"Point"}
}