{
  "type": "Feature",
  "properties": {
    "addr:full":"Nr 137 Ehrenhausen Steiermark 8461",
    "addr:postcode":"8461",
    "addr:street":"Nr",
    "iso:country":"AT",
    "sg:address":"Nr 137",
    "sg:city":"Ehrenhausen",
    "sg:orig_category":"Massagen",
    "sg:phone":"+43 3453 7583",
    "sg:postcode":"8461",
    "sg:province":"Steiermark",
    "wof:name":"Vital Studio Ketschler Gerhard",
    "wof:placetype":"venue"
},
  "geometry": {"coordinates":[15.5848770142,46.7257270813],"type":"Point"}
}