{
  "type": "Feature",
  "properties": {
    "addr:full":"Hauptpl 16 Horn Nieder\u00f6sterreich 3580",
    "addr:housenumber":"16",
    "addr:postcode":"3580",
    "addr:street":"Hauptpl",
    "iso:country":"AT",
    "sg:address":"Hauptpl 16",
    "sg:city":"Horn",
    "sg:classifiers":[
        {
            "category":"Travel",
            "subcategory":"Hotels & Motels",
            "type":"Entertainment"
        }
    ],
    "sg:phone":"+43 2982 23980",
    "sg:postcode":"3580",
    "sg:province":"Nieder\u00f6sterreich",
    "wof:name":"Hotel-Restaurant Weisses R\u00f6ssl",
    "wof:placetype":"venue"
},
  "geometry": {"coordinates":[15.6572084427,48.6641921997],"type":"Point"}
}