{
  "type": "Feature",
  "properties": {
    "addr:full":"Troststr 8-16 Wien Wien 1100",
    "addr:housenumber":"8-16",
    "addr:postcode":"1100",
    "iso:country":"AT",
    "sg:address":"Troststr 8-16",
    "sg:city":"Wien",
    "sg:orig_category":"Optiker",
    "sg:phone":"+43 1 6002904",
    "sg:postcode":"1100",
    "sg:province":"Wien",
    "wof:name":"ADLER V OPTIK Johann Ochs KEG",
    "wof:placetype":"venue"
},
  "geometry": {"coordinates":[16.3792438507,48.1690330505],"type":"Point"}
}