{
  "type": "Feature",
  "properties": {
    "addr:full":"Rathausstr 5 Wien Wien 1010",
    "addr:housenumber":"5",
    "addr:postcode":"1010",
    "addr:street":"Rathausstr",
    "iso:country":"AT",
    "sg:address":"Rathausstr 5",
    "sg:city":"Wien",
    "sg:orig_category":"Exporteure U Importeure",
    "sg:phone":"+43 1 4082390",
    "sg:postcode":"1010",
    "sg:province":"Wien",
    "wof:name":"JL Trading GmbH",
    "wof:placetype":"venue"
},
  "geometry": {"coordinates":[16.3558006287,48.2097434998],"type":"Point"}
}