{
  "type": "Feature",
  "properties": {
    "addr:full":"Elmerweg 12 Linz Ober\u00f6sterreich 4040",
    "addr:housenumber":"12",
    "addr:postcode":"4040",
    "addr:street":"Elmerweg",
    "iso:country":"AT",
    "sg:address":"Elmerweg 12",
    "sg:city":"Linz",
    "sg:classifiers":[
        {
            "category":"Professional",
            "subcategory":"Computer Services",
            "type":"Services"
        }
    ],
    "sg:phone":"+43 7239 6312",
    "sg:postcode":"4040",
    "sg:province":"Ober\u00f6sterreich",
    "sg:tags":[
        "software"
    ],
    "wof:name":"Hois EDV",
    "wof:placetype":"venue"
},
  "geometry": {"coordinates":[14.3393220901,48.3345298767],"type":"Point"}
}