{
  "type": "Feature",
  "properties": {
    "addr:full":"Attendorfberg 94 Hitzendorf Steiermark 8151",
    "addr:housenumber":"94",
    "addr:postcode":"8151",
    "addr:street":"Attendorfberg",
    "iso:country":"AT",
    "sg:address":"Attendorfberg 94",
    "sg:city":"Hitzendorf",
    "sg:classifiers":[
        {
            "category":"Building & Trades",
            "subcategory":"Construction",
            "type":"Services"
        }
    ],
    "sg:phone":"+43 3137 2514",
    "sg:postcode":"8151",
    "sg:province":"Steiermark",
    "sg:tags":[
        "interior",
        "work"
    ],
    "wof:name":"Engelbert Ajtnik",
    "wof:placetype":"venue"
},
  "geometry": {"coordinates":[15.3353347778,47.0280914307],"type":"Point"}
}