{
  "type": "Feature",
  "properties": {
    "iso:country":"AT",
    "sg:address":"Stiftstr 1",
    "sg:city":"Aschach an der Donau",
    "sg:orig_category":"Pensionen / Privatzimmer",
    "sg:phone":"+43 7273 6349",
    "sg:postcode":"4082",
    "sg:province":"Ober\u00f6sterreich",
    "wof:name":"Fr\u00fchst\u00fcckspension K\u00f6pplmayr",
    "wof:placetype":"venue"
},
  "geometry": {"coordinates":[14.0231342316,48.3635444641],"type":"Point"}
}