{
  "type": "Feature",
  "properties": {
    "iso:country":"AT",
    "sg:address":"Nr 50",
    "sg:city":"Windhaag",
    "sg:orig_category":"Gemeinden",
    "sg:phone":"+43 4379 43255",
    "sg:postcode":"4263",
    "sg:province":"Ober\u00f6sterreich",
    "wof:name":"Gemeindeamt Markt Windhaag bei Freistadt",
    "wof:placetype":"venue"
},
  "geometry": {"coordinates":[14.5626926422,48.5861968994],"type":"Point"}
}