{
  "type": "Feature",
  "properties": {
    "iso:country":"AT",
    "sg:address":"Planseestr 49",
    "sg:city":"Reutte",
    "sg:orig_category":"Non-Classified Establishments",
    "sg:phone":"+43 5672 62476",
    "sg:postcode":"6600",
    "sg:province":"Tirol",
    "wof:name":"Pfarramt",
    "wof:placetype":"venue"
},
  "geometry": {"coordinates":[10.7276849747,47.4883041382],"type":"Point"}
}