{
  "type": "Feature",
  "properties": {
    "addr:full":"Hoheneckstr 9 Gallspach Ober\u00f6sterreich 4713",
    "addr:housenumber":"9",
    "addr:postcode":"4713",
    "addr:street":"Hoheneckstr",
    "iso:country":"AT",
    "sg:address":"Hoheneckstr 9",
    "sg:city":"Gallspach",
    "sg:orig_category":"Non-Classified Establishments",
    "sg:phone":"+43 7248 623910",
    "sg:postcode":"4713",
    "sg:province":"Ober\u00f6sterreich",
    "wof:name":"Magauer GesmbH",
    "wof:placetype":"venue"
},
  "geometry": {"coordinates":[13.8125486374,48.2086982727],"type":"Point"}
}