{
  "type": "Feature",
  "properties": {
    "addr:full":"Prager Str 92 Wien Wien 1210",
    "addr:postcode":"1210",
    "addr:street":"Str 92",
    "iso:country":"AT",
    "sg:address":"Prager Str 92",
    "sg:city":"Wien",
    "sg:orig_category":"Spielwaren U Spiele",
    "sg:phone":"+43 4312 784186",
    "sg:postcode":"1210",
    "sg:province":"Wien",
    "wof:name":"Hobby Factory Hobbyartikel GmbH",
    "wof:placetype":"venue"
},
  "geometry": {"coordinates":[16.3904800415,48.2724075317],"type":"Point"}
}