{
  "type": "Feature",
  "properties": {
    "addr:full":"Oberdorfstr 20 Fuschl am See Salzburg 5330",
    "addr:housenumber":"20",
    "addr:postcode":"5330",
    "addr:street":"Oberdorfstr",
    "iso:country":"AT",
    "sg:address":"Oberdorfstr 20",
    "sg:city":"Fuschl am See",
    "sg:orig_category":"Pensionen / Privatzimmer",
    "sg:phone":"+43 6226 82630",
    "sg:postcode":"5330",
    "sg:province":"Salzburg",
    "wof:name":"Fr\u00fchst\u00fcckspension Lindenhof",
    "wof:placetype":"venue"
},
  "geometry": {"coordinates":[13.3071060181,47.7968940735],"type":"Point"}
}