{
  "type": "Feature",
  "properties": {
    "iso:country":"AT",
    "sg:address":"Fl\u00f6tzerweg 134",
    "sg:city":"Linz",
    "sg:orig_category":"Werbegrafik- U Grafik-Design",
    "sg:phone":"+43 4373 2371498",
    "sg:postcode":"4030",
    "sg:province":"Ober\u00f6sterreich",
    "wof:name":"Lichtner Albert Mag - Grafik",
    "wof:placetype":"venue"
},
  "geometry": {"coordinates":[14.2877025604,48.249382019],"type":"Point"}
}