{
  "type": "Feature",
  "properties": {
    "iso:country":"AT",
    "sg:address":"Oberer Markt 19",
    "sg:city":"Rauris",
    "sg:classifiers":[
        {
            "category":"Structure",
            "subcategory":"Bridge",
            "type":"Public Place"
        }
    ],
    "sg:phone":"+43 6544 62160",
    "sg:postcode":"5661",
    "sg:province":"Salzburg",
    "sg:tags":[
        "construction"
    ],
    "wof:name":"Kaiserer Bau GmbH",
    "wof:placetype":"venue"
},
  "geometry": {"coordinates":[12.9915399551,47.2204704285],"type":"Point"}
}