{
  "type": "Feature",
  "properties": {
    "iso:country":"AT",
    "sg:address":"Reichenauer Str 62",
    "sg:city":"Innsbruck",
    "sg:orig_category":"Blumeneinzelhandel",
    "sg:phone":"+43 512 393211",
    "sg:postcode":"6020",
    "sg:province":"Tirol",
    "wof:name":"Lugger Alexandra",
    "wof:placetype":"venue"
},
  "geometry": {"coordinates":[11.4156370163,47.2720756531],"type":"Point"}
}