{
  "type": "Feature",
  "properties": {
    "addr:full":"Moosham 14 Gschwandt Ober\u00f6sterreich 4816",
    "addr:housenumber":"14",
    "addr:postcode":"4816",
    "addr:street":"Moosham",
    "iso:country":"AT",
    "sg:address":"Moosham 14",
    "sg:city":"Gschwandt",
    "sg:orig_category":"Non-Classified Establishments",
    "sg:phone":"+43 699 17170786",
    "sg:postcode":"4816",
    "sg:province":"Ober\u00f6sterreich",
    "wof:name":"Altmaninger Reinhard",
    "wof:placetype":"venue"
},
  "geometry": {"coordinates":[13.8248977661,47.9404563904],"type":"Point"}
}