{
  "type": "Feature",
  "properties": {
    "addr:full":"Schulstr 7 Lauterach Vorarlberg 6923",
    "addr:housenumber":"7",
    "addr:postcode":"6923",
    "addr:street":"Schulstr",
    "iso:country":"AT",
    "sg:address":"Schulstr 7",
    "sg:city":"Lauterach",
    "sg:orig_category":"Volksschulen",
    "sg:phone":"+43 5574 714970",
    "sg:postcode":"6923",
    "sg:province":"Vorarlberg",
    "wof:name":"Volksschule",
    "wof:placetype":"venue"
},
  "geometry": {"coordinates":[9.7278299332,47.4764442444],"type":"Point"}
}