{
  "type": "Feature",
  "properties": {
    "addr:full":"Gadaunerer Str 10 Bad Hofgastein Salzburg 5630",
    "addr:housenumber":"10",
    "addr:postcode":"5630",
    "addr:street":"Str;Salzburg",
    "iso:country":"AT",
    "sg:address":"Gadaunerer Str 10",
    "sg:city":"Bad Hofgastein",
    "sg:orig_category":"Psychotherapie",
    "sg:phone":"+43 6432 85116",
    "sg:postcode":"5630",
    "sg:province":"Salzburg",
    "wof:name":"Zaubzer Laure Mag",
    "wof:placetype":"venue"
},
  "geometry": {"coordinates":[13.1114139557,47.1659545898],"type":"Point"}
}