{
  "type": "Feature",
  "properties": {
    "iso:country":"AT",
    "sg:address":"Gewerbepark B17/11 Str. 1/1",
    "sg:city":"Teesdorf",
    "sg:orig_category":"Fahrzeugeinrichtungen U -Umbauten",
    "sg:phone":"+43 4322 538809",
    "sg:postcode":"2524",
    "sg:province":"Nieder\u00f6sterreich",
    "wof:name":"UPsolute Chiptuning",
    "wof:placetype":"venue"
},
  "geometry": {"coordinates":[16.2753448486,47.9648933411],"type":"Point"}
}