{
  "type": "Feature",
  "properties": {
    "iso:country":"AT",
    "sg:address":"Sonnenburgstr 9/2",
    "sg:city":"Innsbruck",
    "sg:orig_category":"Hobbyvereine",
    "sg:phone":"+43 4351 2587077",
    "sg:postcode":"6020",
    "sg:province":"Tirol",
    "wof:name":"Bridge Club Rot Weiss Rot",
    "wof:placetype":"venue"
},
  "geometry": {"coordinates":[11.3933067322,47.2576560974],"type":"Point"}
}