{
  "type": "Feature",
  "properties": {
    "iso:country":"AT",
    "sg:address":"Hebbelpl 5",
    "sg:city":"Wien",
    "sg:orig_category":"Adressen- U Telefonbuchverlage",
    "sg:phone":"+43 4316 05100",
    "sg:postcode":"1100",
    "sg:province":"Wien",
    "sg:website":"schober.co.at",
    "wof:name":"Schober Information Group GmbH",
    "wof:placetype":"venue"
},
  "geometry": {"coordinates":[16.3783054352,48.1662826538],"type":"Point"}
}