{
  "type": "Feature",
  "properties": {
    "iso:country":"AT",
    "sg:address":"Renng. 10",
    "sg:classifiers":[
        {
            "category":"Banks & Credit Unions",
            "subcategory":"Bank",
            "type":"Services"
        }
    ],
    "sg:phone":"+43 4315 31350",
    "sg:postcode":"1013",
    "sg:tags":[
        "banking",
        "institution"
    ],
    "wof:name":"INVESTKREDIT BANK AG",
    "wof:placetype":"venue"
},
  "geometry": {"coordinates":[16.3671607971,48.2125511169],"type":"Point"}
}