{
  "type": "Feature",
  "properties": {
    "addr:full":"Hinterhof 8/9 Oberperfuss Tirol 6173",
    "addr:housenumber":"8 / 9",
    "addr:postcode":"6173",
    "addr:street":"Hinterhof;Tirol",
    "iso:country":"AT",
    "sg:address":"Hinterhof 8/9",
    "sg:city":"Oberperfuss",
    "sg:orig_category":"Appartements / Ferienwohnungen",
    "sg:phone":"+43 4352 3281810",
    "sg:postcode":"6173",
    "sg:province":"Tirol",
    "wof:name":"Ferienwohnung Wastl",
    "wof:placetype":"venue"
},
  "geometry": {"coordinates":[11.2500524521,47.2472686768],"type":"Point"}
}