{
  "type": "Feature",
  "properties": {
    "iso:country":"AT",
    "sg:address":"Eisenst\u00e4dter Str 1",
    "sg:city":"Oberpullendorf",
    "sg:orig_category":"Autoersatzteile",
    "sg:phone":"+43 2612 43191",
    "sg:postcode":"7350",
    "sg:province":"Burgenland",
    "wof:name":"Autobedarf Schmutzer GesmbH & Co KG",
    "wof:placetype":"venue"
},
  "geometry": {"coordinates":[16.5095233917,47.4958076477],"type":"Point"}
}