{
  "type": "Feature",
  "properties": {
    "iso:country":"AT",
    "sg:address":"Schlossviertel 5",
    "sg:city":"Reichenau im M\u00fchlkreis",
    "sg:orig_category":"Architekten",
    "sg:phone":"+43 4372 1120515",
    "sg:postcode":"4204",
    "sg:province":"Ober\u00f6sterreich",
    "wof:name":"Henter Andreas F Arch Mag",
    "wof:placetype":"venue"
},
  "geometry": {"coordinates":[14.3453598022,48.4516601562],"type":"Point"}
}