{
  "type": "Feature",
  "properties": {
    "addr:full":"Enderlenstr 3 Salzburg Salzburg 5020",
    "addr:housenumber":"3",
    "addr:postcode":"5020",
    "addr:street":"Enderlenstr;Salzburg",
    "iso:country":"AT",
    "sg:address":"Enderlenstr 3",
    "sg:city":"Salzburg",
    "sg:orig_category":"Werbegestalter",
    "sg:phone":"+43 662 4398120",
    "sg:postcode":"5020",
    "sg:province":"Salzburg",
    "wof:name":"Deko Maier Werbegestaltung",
    "wof:placetype":"venue"
},
  "geometry": {"coordinates":[13.009765625,47.81873703],"type":"Point"}
}