{
  "type": "Feature",
  "properties": {
    "iso:country":"AT",
    "sg:address":"Hauptstr 3a",
    "sg:city":"Schalchen",
    "sg:orig_category":"Volksschulen",
    "sg:phone":"+43 7742 2806",
    "sg:postcode":"5231",
    "sg:province":"Ober\u00f6sterreich",
    "wof:name":"Volksschule",
    "wof:placetype":"venue"
},
  "geometry": {"coordinates":[13.1562290192,48.1189498901],"type":"Point"}
}