{
  "type": "Feature",
  "properties": {
    "iso:country":"AT",
    "sg:address":"Untersbergstrasse 1 ",
    "sg:city":"Gr\u00f6dig",
    "sg:orig_category":"Assembly Benches For Printed Circuit Boards Pcb",
    "sg:phone":"+43 6246 724400",
    "sg:postcode":"5082",
    "sg:province":"Salzburg",
    "sg:website":"adoptsmt.com",
    "wof:name":"Adopt Advanced Optimisation Software GmbH",
    "wof:placetype":"venue"
},
  "geometry": {"coordinates":[-76.2684555054,37.4373283386],"type":"Point"}
}