{
  "type": "Feature",
  "properties": {
    "addr:full":"Untere Wei\u00dfgerberstr 18-22/3 Wien Wien 1030",
    "addr:housenumber":"18-22 / 3",
    "addr:postcode":"1030",
    "addr:street":"Untere Weissgerberstr",
    "iso:country":"AT",
    "sg:address":"Untere Wei\u00dfgerberstr 18-22/3",
    "sg:city":"Wien",
    "sg:classifiers":[
        {
            "category":"Taxi",
            "type":"Transportation"
        }
    ],
    "sg:phone":"+43 1 9414231",
    "sg:postcode":"1030",
    "sg:province":"Wien",
    "sg:tags":[
        "personentransporte",
        "u"
    ],
    "wof:name":"Knapp Karl",
    "wof:placetype":"venue"
},
  "geometry": {"coordinates":[16.4025096893,48.1936683655],"type":"Point"}
}