{
  "type": "Feature",
  "properties": {
    "addr:full":"Schmidtg 34 Wels Ober\u00f6sterreich 4600",
    "addr:housenumber":"34",
    "addr:postcode":"4600",
    "addr:street":"Schmidtg;Oberoesterreich",
    "iso:country":"AT",
    "sg:address":"Schmidtg 34",
    "sg:city":"Wels",
    "sg:orig_category":"Textilwaren / Einzelhandel",
    "sg:phone":"+43 7242 4505175",
    "sg:postcode":"4600",
    "sg:province":"Ober\u00f6sterreich",
    "wof:name":"Sisley",
    "wof:placetype":"venue"
},
  "geometry": {"coordinates":[14.0247049332,48.1584968567],"type":"Point"}
}