{
  "type": "Feature",
  "properties": {
    "addr:full":"Landstr 114 Hainburg an der Donau Nieder\u00f6sterreich 2410",
    "addr:housenumber":"114",
    "addr:postcode":"2410",
    "addr:street":"Landstr",
    "iso:country":"AT",
    "sg:address":"Landstr 114",
    "sg:city":"Hainburg an der Donau",
    "sg:orig_category":"Tankstellen",
    "sg:phone":"+43 4321 6562562",
    "sg:postcode":"2410",
    "sg:province":"Nieder\u00f6sterreich",
    "wof:name":"Esso Austria GmbH",
    "wof:placetype":"venue"
},
  "geometry": {"coordinates":[16.9238967896,48.1410064697],"type":"Point"}
}