{
  "type": "Feature",
  "properties": {
    "addr:full":"Unterer Kirchenpl 1 Villach K\u00e4rnten 9500",
    "addr:housenumber":"1",
    "addr:postcode":"9500",
    "addr:street":"Unterer Kirchenpl;Kaernten",
    "iso:country":"AT",
    "sg:address":"Unterer Kirchenpl 1",
    "sg:city":"Villach",
    "sg:orig_category":"Bekleidung / Einzelhandel",
    "sg:phone":"+43 4242 241360",
    "sg:postcode":"9500",
    "sg:province":"K\u00e4rnten",
    "wof:name":"M H T - HIS",
    "wof:placetype":"venue"
},
  "geometry": {"coordinates":[13.8458766937,46.6129341125],"type":"Point"}
}