{
  "type": "Feature",
  "properties": {
    "addr:full":"Bahnhofstr 24 Hohenems Vorarlberg 6845",
    "addr:postcode":"6845",
    "addr:street":"Bahnhofstr 24",
    "iso:country":"AT",
    "sg:address":"Bahnhofstr 24",
    "sg:city":"Hohenems",
    "sg:orig_category":"Spenglereien",
    "sg:phone":"+43 4355 7673759",
    "sg:postcode":"6845",
    "sg:province":"Vorarlberg",
    "wof:name":"Amann Anton",
    "wof:placetype":"venue"
},
  "geometry": {"coordinates":[9.6839475632,47.3630409241],"type":"Point"}
}