{
  "type": "Feature",
  "properties": {
    "iso:country":"AT",
    "sg:address":"Unter der Burg 15",
    "sg:city":"Waidhofen an der Ybbs",
    "sg:orig_category":"Reifen U Reifendienste",
    "sg:phone":"+43 4374 42543420",
    "sg:postcode":"3340",
    "sg:province":"Nieder\u00f6sterreich",
    "wof:name":"Renner Herta",
    "wof:placetype":"venue"
},
  "geometry": {"coordinates":[14.772356987,47.9611625671],"type":"Point"}
}