{
  "type": "Feature",
  "properties": {
    "iso:country":"AT",
    "sg:address":"Bahnhofstrasse 13",
    "sg:city":"St. Johann in Tirol",
    "sg:classifiers":[
        {
            "category":"Building & Trades",
            "subcategory":"Plumbing",
            "type":"Services"
        }
    ],
    "sg:phone":"+43 5352 622380",
    "sg:postcode":"6380",
    "sg:province":"Tirol",
    "sg:tags":[
        "supraregional",
        "gas"
    ],
    "wof:name":"Anton Brunnschmid, Installationen f\u00fcr Heizung und Sanit\u00e4re Ges.m.b.H.",
    "wof:placetype":"venue"
},
  "geometry": {"coordinates":[12.4310569763,47.5210494995],"type":"Point"}
}