{
  "type": "Feature",
  "properties": {
    "addr:full":"Hauptpl 2 Tattendorf Nieder\u00f6sterreich 2523",
    "addr:housenumber":"2",
    "addr:postcode":"2523",
    "addr:street":"Hauptpl",
    "iso:country":"AT",
    "sg:address":"Hauptpl 2",
    "sg:city":"Tattendorf",
    "sg:orig_category":"Gemeinden",
    "sg:phone":"+43 2253 815810",
    "sg:postcode":"2523",
    "sg:province":"Nieder\u00f6sterreich",
    "wof:name":"Gemeinde Tattendorf",
    "wof:placetype":"venue"
},
  "geometry": {"coordinates":[16.3025741577,47.9567642212],"type":"Point"}
}