{
  "type": "Feature",
  "properties": {
    "iso:country":"AT",
    "sg:address":"Breitenfurter Str 219",
    "sg:city":"Wien",
    "sg:classifiers":[
        {
            "category":"Professional",
            "subcategory":"Computer Services",
            "type":"Services"
        }
    ],
    "sg:phone":"+43 1 8021942",
    "sg:postcode":"1230",
    "sg:province":"Wien",
    "sg:tags":[
        "software"
    ],
    "wof:name":"COMPRO Computerprodukte GmbH & CO EDV -Dienstleitungen KEG",
    "wof:placetype":"venue"
},
  "geometry": {"coordinates":[16.3043041229,48.1561965942],"type":"Point"}
}