{
  "type": "Feature",
  "properties": {
    "iso:country":"AT",
    "sg:address":"Anton-Faistauer-Pl 7",
    "sg:city":"Maishofen",
    "sg:orig_category":"Gemeinden",
    "sg:phone":"+43 6542 682130",
    "sg:postcode":"5751",
    "sg:province":"Salzburg",
    "wof:name":"Gemeindeamt Maishofen",
    "wof:placetype":"venue"
},
  "geometry": {"coordinates":[12.8060569763,47.3612785339],"type":"Point"}
}