{
  "type": "Feature",
  "properties": {
    "addr:full":"Hinterhof 5 Oberperfuss Tirol 6173",
    "addr:housenumber":"5",
    "addr:postcode":"6173",
    "addr:street":"Hinterhof;Tirol",
    "iso:country":"AT",
    "sg:address":"Hinterhof 5",
    "sg:city":"Oberperfuss",
    "sg:orig_category":"Schilder- U Schriftenmaler",
    "sg:phone":"+43 5232 81720",
    "sg:postcode":"6173",
    "sg:province":"Tirol",
    "wof:name":"Kirchmair Johann",
    "wof:placetype":"venue"
},
  "geometry": {"coordinates":[11.2500524521,47.2472686768],"type":"Point"}
}