{
  "type": "Feature",
  "properties": {
    "addr:full":"Krafft-Ebing-G 23 Wien Wien 1140",
    "addr:housenumber":"23",
    "addr:postcode":"1140",
    "addr:street":"Krafft-Ebing-G",
    "iso:country":"AT",
    "sg:address":"Krafft-Ebing-G 23",
    "sg:city":"Wien",
    "sg:orig_category":"Baumeister",
    "sg:phone":"+43 1 9145256",
    "sg:postcode":"1140",
    "sg:province":"Wien",
    "wof:name":"Eberhart Walter",
    "wof:placetype":"venue"
},
  "geometry": {"coordinates":[16.2682323456,48.2033424377],"type":"Point"}
}