{
  "type": "Feature",
  "properties": {
    "addr:full":"Nr 39 Mauer-\u00d6hling Nieder\u00f6sterreich 3362",
    "addr:postcode":"3362",
    "addr:street":"Nr 39 Mauer-Oehling",
    "iso:country":"AT",
    "sg:address":"Nr 39",
    "sg:city":"Mauer-\u00d6hling",
    "sg:orig_category":"Volksschulen",
    "sg:phone":"+43 4374 7553103",
    "sg:postcode":"3362",
    "sg:province":"Nieder\u00f6sterreich",
    "wof:name":"Volksschule",
    "wof:placetype":"venue"
},
  "geometry": {"coordinates":[-103.11498260499999,33.7812652588],"type":"Point"}
}