{
  "type": "Feature",
  "properties": {
    "iso:country":"AT",
    "sg:address":"Hauptstr 18",
    "sg:city":"Sch\u00f6rfling am Attersee",
    "sg:orig_category":"Telekommunikation",
    "sg:phone":"+43 4376 62612616",
    "sg:postcode":"4861",
    "sg:province":"Ober\u00f6sterreich",
    "wof:name":"PN Connections DienstleistungsgmbH",
    "wof:placetype":"venue"
},
  "geometry": {"coordinates":[13.5949764252,47.9470672607],"type":"Point"}
}