{
  "type": "Feature",
  "properties": {
    "iso:country":"AT",
    "sg:address":"Hofhaimerg 13",
    "sg:city":"Radstadt",
    "sg:orig_category":"Fahrschulen",
    "sg:phone":"+43 6452 4100",
    "sg:postcode":"5550",
    "sg:province":"Salzburg",
    "sg:website":"www.fahrschule-radstadt.at",
    "wof:name":"Fahrschule Pewny",
    "wof:placetype":"venue"
},
  "geometry": {"coordinates":[13.4613866806,47.3841285706],"type":"Point"}
}