{
  "type": "Feature",
  "properties": {
    "addr:full":"Meinhardstr 1-3 Innsbruck Tirol 6020",
    "addr:housenumber":"1-3",
    "addr:postcode":"6020",
    "addr:street":"Meinhardstr;Tirol",
    "iso:country":"AT",
    "sg:address":"Meinhardstr 1-3",
    "sg:city":"Innsbruck",
    "sg:orig_category":"Banken U Sparkassen",
    "sg:phone":"+43 512 53030",
    "sg:postcode":"6020",
    "sg:province":"Tirol",
    "wof:name":"Volksbank Tirol Innsbruck-Schwaz AG",
    "wof:placetype":"venue"
},
  "geometry": {"coordinates":[11.3993062973,47.2664451599],"type":"Point"}
}