{
  "type": "Feature",
  "properties": {
    "addr:full":"Schie\u00dfstattallee 34 St. Veit an der Glan K\u00e4rnten 9300",
    "addr:housenumber":"34",
    "addr:postcode":"9300",
    "addr:street":"Schiessstattallee;Kaernten",
    "iso:country":"AT",
    "sg:address":"Schie\u00dfstattallee 34",
    "sg:city":"St. Veit an der Glan",
    "sg:orig_category":"Baumeister",
    "sg:phone":"+43 4212 23720",
    "sg:postcode":"9300",
    "sg:province":"K\u00e4rnten",
    "wof:name":"Moser Bau GesmbH",
    "wof:placetype":"venue"
},
  "geometry": {"coordinates":[14.356803894,46.7585601807],"type":"Point"}
}