{
  "type": "Feature",
  "properties": {
    "addr:full":"Wiener Strasse 24 St. Valentin Nieder\u00f6sterreich 4300",
    "addr:housenumber":"24",
    "addr:postcode":"4300",
    "addr:street":"Wiener Strasse",
    "iso:country":"AT",
    "sg:address":"Wiener Strasse 24",
    "sg:city":"St. Valentin",
    "sg:classifiers":[
        {
            "category":"Manufacturing",
            "subcategory":"Metals",
            "type":"Manufacturing & Wholesale Goods"
        }
    ],
    "sg:phone":"+43 7435 54380",
    "sg:postcode":"4300",
    "sg:province":"Nieder\u00f6sterreich",
    "sg:tags":[
        "working"
    ],
    "sg:website":"entlesberger.com",
    "wof:name":"Entlesberger Ges.m.b.H.",
    "wof:placetype":"venue"
},
  "geometry": {"coordinates":[14.5293474197,48.1965446472],"type":"Point"}
}