{
  "type": "Feature",
  "properties": {
    "addr:full":"G\u00f6sserpl. 1 Leoben Steiermark 8700",
    "addr:housenumber":"1",
    "addr:postcode":"8700",
    "addr:street":"Goesserpl.",
    "iso:country":"AT",
    "sg:address":"G\u00f6sserpl. 1",
    "sg:city":"Leoben",
    "sg:classifiers":[
        {
            "category":"Banks & Credit Unions",
            "subcategory":"Financial Services",
            "type":"Services"
        }
    ],
    "sg:phone":"+43 4338 424065",
    "sg:postcode":"8700",
    "sg:province":"Steiermark",
    "sg:tags":[
        "banking",
        "finance",
        "insurance"
    ],
    "wof:name":"ALLIANZ VERSICHERUNG AG",
    "wof:placetype":"venue"
},
  "geometry": {"coordinates":[15.0972089767,47.36302948],"type":"Point"}
}