{
  "type": "Feature",
  "properties": {
    "addr:full":"Augartenstr 48 Lustenau Vorarlberg 6890",
    "addr:housenumber":"48",
    "addr:postcode":"6890",
    "addr:street":"Augartenstr",
    "iso:country":"AT",
    "sg:address":"Augartenstr 48",
    "sg:city":"Lustenau",
    "sg:orig_category":"Folien",
    "sg:phone":"+43 4355 77824940",
    "sg:postcode":"6890",
    "sg:province":"Vorarlberg",
    "wof:name":"Hagen Elmar GesmbH & Co KG",
    "wof:placetype":"venue"
},
  "geometry": {"coordinates":[9.6550121307,47.4432373047],"type":"Point"}
}