{
  "type": "Feature",
  "properties": {
    "addr:full":"Lavam\u00fcnder Str Lavam\u00fcnd K\u00e4rnten 9473",
    "addr:postcode":"9473",
    "addr:street":"Str Lavamuend Kaernten",
    "iso:country":"AT",
    "sg:address":"Lavam\u00fcnder Str",
    "sg:city":"Lavam\u00fcnd",
    "sg:orig_category":"Lebensmittel / Einzelhandel",
    "sg:phone":"+43 4356 2721",
    "sg:postcode":"9473",
    "sg:province":"K\u00e4rnten",
    "wof:name":"Billa AG",
    "wof:placetype":"venue"
},
  "geometry": {"coordinates":[14.9489145279,46.6454124451],"type":"Point"}
}