{
  "type": "Feature",
  "properties": {
    "addr:full":"Osterwitzg 6 Klagenfurt K\u00e4rnten 9020",
    "addr:housenumber":"6",
    "addr:postcode":"9020",
    "addr:street":"Osterwitzg;Kaernten",
    "iso:country":"AT",
    "sg:address":"Osterwitzg 6",
    "sg:city":"Klagenfurt",
    "sg:orig_category":"Bars-Cafes",
    "sg:phone":"+43 463 913008",
    "sg:postcode":"9020",
    "sg:province":"K\u00e4rnten",
    "wof:name":"Stigl's",
    "wof:placetype":"venue"
},
  "geometry": {"coordinates":[14.3092393875,46.6260681152],"type":"Point"}
}