{
  "type": "Feature",
  "properties": {
    "iso:country":"AT",
    "sg:address":"Rasumofskyg 4",
    "sg:city":"Wien",
    "sg:orig_category":"Damenmoden",
    "sg:phone":"+43 1 71378200",
    "sg:postcode":"1030",
    "sg:province":"Wien",
    "wof:name":"Avantgarde Mode Turek HandelsgmbH",
    "wof:placetype":"venue"
},
  "geometry": {"coordinates":[16.3950042725,48.2058639526],"type":"Point"}
}