{
  "type": "Feature",
  "properties": {
    "addr:full":"Maierhof 3 Neuberg an der M\u00fcrz Steiermark 8692",
    "addr:housenumber":"3;8692",
    "addr:street":"Maierhof",
    "iso:country":"AT",
    "sg:address":"Maierhof 3",
    "sg:city":"Neuberg an der M\u00fcrz",
    "sg:orig_category":"Tischlereien",
    "sg:phone":"+43 3857 20145",
    "sg:postcode":"8692",
    "sg:province":"Steiermark",
    "wof:name":"Ulm Gerhard",
    "wof:placetype":"venue"
},
  "geometry": {"coordinates":[15.5749788284,47.6665992737],"type":"Point"}
}