{
  "type": "Feature",
  "properties": {
    "addr:full":"Am Anger 28 St. Oswald Ober\u00f6sterreich 4271",
    "addr:housenumber":"28",
    "addr:postcode":"4271",
    "addr:street":"Am Anger",
    "iso:country":"AT",
    "sg:address":"Am Anger 28",
    "sg:city":"St. Oswald",
    "sg:classifiers":[
        {
            "category":"Building & Trades",
            "subcategory":"Plumbing",
            "type":"Services"
        }
    ],
    "sg:phone":"+43 7945 7887",
    "sg:postcode":"4271",
    "sg:province":"Ober\u00f6sterreich",
    "sg:tags":[
        "supraregional",
        "gas"
    ],
    "wof:name":"Franz Haider KG",
    "wof:placetype":"venue"
},
  "geometry": {"coordinates":[14.6032323837,48.5029792786],"type":"Point"}
}