{
  "type": "Feature",
  "properties": {
    "addr:full":"Im Tal 22a Ehrwald Tirol 6632",
    "addr:housenumber":"22a",
    "addr:postcode":"6632",
    "addr:street":"Im Tal;Tirol",
    "iso:country":"AT",
    "sg:address":"Im Tal 22a",
    "sg:city":"Ehrwald",
    "sg:orig_category":"Pensionen / Privatzimmer",
    "sg:phone":"+43 4356 733504",
    "sg:postcode":"6632",
    "sg:province":"Tirol",
    "wof:name":"Pension Edith",
    "wof:placetype":"venue"
},
  "geometry": {"coordinates":[10.9172563553,47.3957443237],"type":"Point"}
}