{
  "type": "Feature",
  "properties": {
    "addr:full":"Nr 65 P\u00f6rtschach am W\u00f6rther See K\u00e4rnten 9210",
    "addr:postcode":"9210",
    "addr:street":"Nr 65;Am Woerther;Kaernten",
    "iso:country":"AT",
    "sg:address":"Nr 65",
    "sg:city":"P\u00f6rtschach am W\u00f6rther See",
    "sg:orig_category":"Glasereien",
    "sg:phone":"+43 660 1269426",
    "sg:postcode":"9210",
    "sg:province":"K\u00e4rnten",
    "wof:name":"Kempfer Alexandra",
    "wof:placetype":"venue"
},
  "geometry": {"coordinates":[14.1465053558,46.635345459],"type":"Point"}
}