{
  "type": "Feature",
  "properties": {
    "iso:country":"AT",
    "sg:address":"Halleiner Landesstr 38",
    "sg:city":"Oberalm",
    "sg:orig_category":"Transportunternehmen",
    "sg:phone":"+43 6245 803910",
    "sg:postcode":"5411",
    "sg:province":"Salzburg",
    "wof:name":"Klabacher Anton OEG",
    "wof:placetype":"venue"
},
  "geometry": {"coordinates":[13.1001358032,47.6983261108],"type":"Point"}
}