{
  "type": "Feature",
  "properties": {
    "addr:full":"Josef Ferschner-Str 64 Traiskirchen Nieder\u00f6sterreich 2514",
    "addr:housenumber":"64",
    "addr:postcode":"2514",
    "addr:street":"Niederoesterreich",
    "iso:country":"AT",
    "sg:address":"Josef Ferschner-Str 64",
    "sg:city":"Traiskirchen",
    "sg:orig_category":"Garten- U Landschaftsgestaltung",
    "sg:phone":"+43 2252 53028",
    "sg:postcode":"2514",
    "sg:province":"Nieder\u00f6sterreich",
    "wof:name":"Michael Krenn Ing",
    "wof:placetype":"venue"
},
  "geometry": {"coordinates":[16.2940559387,48.0187644958],"type":"Point"}
}