{
  "type": "Feature",
  "properties": {
    "iso:country":"AT",
    "sg:address":"Ostmarkg 11",
    "sg:city":"Wien",
    "sg:orig_category":"Bauunternehmen",
    "sg:phone":"+43 1 2706923",
    "sg:postcode":"1210",
    "sg:province":"Wien",
    "wof:name":"STROBEL & PARTNER BaugesmbH",
    "wof:placetype":"venue"
},
  "geometry": {"coordinates":[16.4089069366,48.2574424744],"type":"Point"}
}