{
  "type": "Feature",
  "properties": {
    "iso:country":"AT",
    "sg:address":"Kremstalstr 8",
    "sg:city":"Neuhofen an der Krems",
    "sg:orig_category":"Sonnenstudios",
    "sg:phone":"+43 4372 2721050",
    "sg:postcode":"4501",
    "sg:province":"Ober\u00f6sterreich",
    "wof:name":"Tropic Sun",
    "wof:placetype":"venue"
},
  "geometry": {"coordinates":[14.2271871567,48.1370811462],"type":"Point"}
}