{
  "type": "Feature",
  "properties": {
    "addr:full":"Resselstr 10 Buchkirchen Ober\u00f6sterreich 4611",
    "addr:housenumber":"10",
    "addr:postcode":"4611",
    "addr:street":"Resselstr",
    "iso:country":"AT",
    "sg:address":"Resselstr 10",
    "sg:city":"Buchkirchen",
    "sg:orig_category":"Volkshochschulen",
    "sg:phone":"+43 664 4005498",
    "sg:postcode":"4611",
    "sg:province":"Ober\u00f6sterreich",
    "wof:name":"Volkshochschule Ober\u00f6sterreich gemeinn\u00fctzige Bildungs-GmbH d AK f O\u00d6",
    "wof:placetype":"venue"
},
  "geometry": {"coordinates":[14.0392990112,48.2097587585],"type":"Point"}
}