{
  "type": "Feature",
  "properties": {
    "addr:full":"Jahnstr 20 Bregenz Vorarlberg 6900",
    "addr:housenumber":"20",
    "addr:postcode":"6900",
    "addr:street":"Jahnstr",
    "iso:country":"AT",
    "sg:address":"Jahnstr 20",
    "sg:city":"Bregenz",
    "sg:orig_category":"Babyausstattung",
    "sg:phone":"+43 5574 47948",
    "sg:postcode":"6900",
    "sg:province":"Vorarlberg",
    "wof:name":"Winkel Doris - red banana",
    "wof:placetype":"venue"
},
  "geometry": {"coordinates":[9.7453517914,47.5031433105],"type":"Point"}
}