{
  "type": "Feature",
  "properties": {
    "iso:country":"AT",
    "sg:address":"Strohg. 28 ",
    "sg:city":"Wien",
    "sg:classifiers":[
        {
            "category":"Parking",
            "subcategory":"Lot",
            "type":"Transportation"
        }
    ],
    "sg:phone":"+43 4316 01224030",
    "sg:postcode":"1030",
    "sg:province":"Wien",
    "sg:tags":[
        "transport",
        "road"
    ],
    "wof:name":"GESUNDHEITSCENTRUM WIEN MITTE",
    "wof:placetype":"venue"
},
  "geometry": {"coordinates":[16.4025096893,48.1936683655],"type":"Point"}
}