{
  "type": "Feature",
  "properties": {
    "iso:country":"AT",
    "sg:address":"Kalmanstrasse 3",
    "sg:city":"Marchtrenk",
    "sg:classifiers":[
        {
            "category":"Transit Center",
            "subcategory":"Freight",
            "type":"Transportation"
        }
    ],
    "sg:phone":"+43 7243 51683",
    "sg:postcode":"4614",
    "sg:province":"Ober\u00f6sterreich",
    "sg:tags":[
        "fuel",
        "container",
        "storage"
    ],
    "sg:website":"emtec-tankanlagen.at",
    "wof:name":"emtec tankanlagen Ing. Erwin Kirchmeir",
    "wof:placetype":"venue"
},
  "geometry": {"coordinates":[14.1053276062,48.1964950562],"type":"Point"}
}