{
  "type": "Feature",
  "properties": {
    "addr:full":"Grazer Str 79 Kapfenberg Steiermark 8605",
    "addr:postcode":"8605",
    "addr:street":"Str 79",
    "iso:country":"AT",
    "sg:address":"Grazer Str 79",
    "sg:city":"Kapfenberg",
    "sg:orig_category":"Juwelen, Gold- U Silberwaren / Einzelhandel",
    "sg:phone":"+43 3862 26082",
    "sg:postcode":"8605",
    "sg:province":"Steiermark",
    "wof:name":"Zeit & Gold",
    "wof:placetype":"venue"
},
  "geometry": {"coordinates":[15.2824029922,47.4377326965],"type":"Point"}
}