{
  "type": "Feature",
  "properties": {
    "iso:country":"AT",
    "sg:address":"Unken 89",
    "sg:city":"Unken",
    "sg:classifiers":[
        {
            "category":"Manufacturing",
            "subcategory":"Wood Products",
            "type":"Manufacturing & Wholesale Goods"
        }
    ],
    "sg:phone":"+43 6589 7322",
    "sg:postcode":"5091",
    "sg:province":"Salzburg",
    "sg:tags":[
        "gate",
        "made",
        "door"
    ],
    "wof:name":"Philipp Haas u. S\u00f6hne GmbH",
    "wof:placetype":"venue"
},
  "geometry": {"coordinates":[12.727481842,47.6388397217],"type":"Point"}
}