{
  "type": "Feature",
  "properties": {
    "addr:full":"Markt 50 Golling an der Salzach Salzburg 5440",
    "addr:housenumber":"50",
    "addr:postcode":"5440",
    "addr:street":"Markt",
    "iso:country":"AT",
    "sg:address":"Markt 50",
    "sg:city":"Golling an der Salzach",
    "sg:orig_category":"Lederwaren / Einzelhandel",
    "sg:phone":"+43 4362 444883",
    "sg:postcode":"5440",
    "sg:province":"Salzburg",
    "wof:name":"Moser Christine",
    "wof:placetype":"venue"
},
  "geometry": {"coordinates":[13.1681623459,47.5983695984],"type":"Point"}
}