{
  "type": "Feature",
  "properties": {
    "iso:country":"AT",
    "sg:address":"Nr 6",
    "sg:city":"Bad Radkersburg",
    "sg:orig_category":"Appartements / Ferienwohnungen",
    "sg:phone":"+43 4334 763522",
    "sg:postcode":"8490",
    "sg:province":"Steiermark",
    "wof:name":"Kittners Kritisches Kabarett",
    "wof:placetype":"venue"
},
  "geometry": {"coordinates":[15.9779663086,46.6914176941],"type":"Point"}
}