{
  "type": "Feature",
  "properties": {
    "iso:country":"AT",
    "sg:address":"Gladenstr 3",
    "sg:city":"Trofaiach",
    "sg:orig_category":"Freizeitangebote U -Einrichtungen",
    "sg:phone":"+43 3847 6097",
    "sg:postcode":"8793",
    "sg:province":"Steiermark",
    "wof:name":"Jugendzentrum Trofaiach",
    "wof:placetype":"venue"
},
  "geometry": {"coordinates":[15.0013599396,47.4310493469],"type":"Point"}
}