{
  "type": "Feature",
  "properties": {
    "iso:country":"AT",
    "sg:address":"Nr 88",
    "sg:city":"Unterbergen",
    "sg:orig_category":"Volksschulen",
    "sg:phone":"+43 4227 6353",
    "sg:postcode":"9163",
    "sg:province":"K\u00e4rnten",
    "wof:name":"Volksschule",
    "wof:placetype":"venue"
},
  "geometry": {"coordinates":[14.2878847122,46.506855011],"type":"Point"}
}