{
  "type": "Feature",
  "properties": {
    "addr:full":"Kirchstr 1 Zirl Tirol 6170",
    "addr:housenumber":"1",
    "addr:postcode":"6170",
    "addr:street":"Kirchstr;Tirol",
    "iso:country":"AT",
    "sg:address":"Kirchstr 1",
    "sg:city":"Zirl",
    "sg:orig_category":"Blumeneinzelhandel",
    "sg:phone":"+43 5238 53125",
    "sg:postcode":"6170",
    "sg:province":"Tirol",
    "wof:name":"Wild Robert und Sebastian",
    "wof:placetype":"venue"
},
  "geometry": {"coordinates":[11.2423753738,47.2725410461],"type":"Point"}
}