{
  "type": "Feature",
  "properties": {
    "iso:country":"AT",
    "sg:address":"Pitzh\u00f6fe 184",
    "sg:city":"Wenns",
    "sg:orig_category":"Imkereien",
    "sg:phone":"+43 5414 87244",
    "sg:postcode":"6473",
    "sg:province":"Tirol",
    "wof:name":"Imkerei - Naturprodukte Gundolf",
    "wof:placetype":"venue"
},
  "geometry": {"coordinates":[10.7312002182,47.1684265137],"type":"Point"}
}