{
  "type": "Feature",
  "properties": {
    "addr:full":"Nr 106a Dalaas Vorarlberg 6752",
    "addr:postcode":"6752",
    "addr:street":"Nr 106A",
    "iso:country":"AT",
    "sg:address":"Nr 106a",
    "sg:city":"Dalaas",
    "sg:classifiers":[
        {
            "category":"Restaurant",
            "type":"Food & Drink"
        }
    ],
    "sg:phone":"+43 664 3410962",
    "sg:postcode":"6752",
    "sg:province":"Vorarlberg",
    "sg:tags":[
        "pizzeria"
    ],
    "wof:name":"Pizzast\u00fcble Berthold",
    "wof:placetype":"venue"
},
  "geometry": {"coordinates":[9.9998960495,47.1229896545],"type":"Point"}
}