{
  "type": "Feature",
  "properties": {
    "addr:full":"Salbeistrasse 3 Kronstorf Ober\u00f6sterreich 4484",
    "addr:housenumber":"3",
    "addr:postcode":"4484",
    "addr:street":"Salbeistrasse",
    "iso:country":"AT",
    "sg:address":"Salbeistrasse 3",
    "sg:city":"Kronstorf",
    "sg:classifiers":[
        {
            "category":"Organizations",
            "subcategory":"Labor Organization",
            "type":"Services"
        }
    ],
    "sg:phone":"+43 7225 90900",
    "sg:postcode":"4484",
    "sg:province":"Ober\u00f6sterreich",
    "sg:tags":[
        "personnel",
        "providing"
    ],
    "sg:website":"www.zisser.at",
    "wof:name":"PR ZISSER",
    "wof:placetype":"venue"
},
  "geometry": {"coordinates":[14.4639043808,48.1348114014],"type":"Point"}
}