{
  "type": "Feature",
  "properties": {
    "iso:country":"AT",
    "sg:address":"Herzog-Odilo-Str 101",
    "sg:city":"Mondsee",
    "sg:orig_category":"Immobilienmakler",
    "sg:phone":"+43 4362 327668",
    "sg:postcode":"5310",
    "sg:province":"Ober\u00f6sterreich",
    "sg:website":"ocs.at",
    "wof:name":"OCS Bauprojektierungs- u VertriebsgmbH",
    "wof:placetype":"venue"
},
  "geometry": {"coordinates":[13.3327865601,47.864654541],"type":"Point"}
}