{
  "type": "Feature",
  "properties": {
    "addr:full":"Auhofstr 184 Wien Wien 1130",
    "addr:housenumber":"184",
    "addr:postcode":"1130",
    "iso:country":"AT",
    "sg:address":"Auhofstr 184",
    "sg:city":"Wien",
    "sg:orig_category":"Matten U Mattenvermietung",
    "sg:phone":"+43 4318 794603",
    "sg:postcode":"1130",
    "sg:province":"Wien",
    "wof:name":"Hammerschmiedt Christof",
    "wof:placetype":"venue"
},
  "geometry": {"coordinates":[16.2629337311,48.194683075],"type":"Point"}
}