{
  "type": "Feature",
  "properties": {
    "iso:country":"AT",
    "sg:address":"S\u00f6llheimer Str 16",
    "sg:city":"Bergheim",
    "sg:orig_category":"Gie\u00c3\u0178ereien",
    "sg:phone":"+43 662 4512300",
    "sg:postcode":"5101",
    "sg:province":"Salzburg",
    "wof:name":"Oberascher Franz GmbH",
    "wof:placetype":"venue"
},
  "geometry": {"coordinates":[13.0230998993,47.8411369324],"type":"Point"}
}