{
  "type": "Feature",
  "properties": {
    "addr:full":"Koling 1 Wien Wien 1090",
    "addr:housenumber":"1",
    "addr:postcode":"1090",
    "addr:street":"Koling",
    "iso:country":"AT",
    "sg:address":"Koling 1",
    "sg:city":"Wien",
    "sg:orig_category":"Werbeagenturen",
    "sg:phone":"+43 1 9949888",
    "sg:postcode":"1090",
    "sg:province":"Wien",
    "wof:name":"Aichner Clodi GGK Werbeagentur GmbH",
    "wof:placetype":"venue"
},
  "geometry": {"coordinates":[16.3614025116,48.2154579163],"type":"Point"}
}