{
  "type": "Feature",
  "properties": {
    "addr:full":"Wildbichler Str 32 Ebbs Tirol 6341",
    "addr:housenumber":"32",
    "addr:postcode":"6341",
    "addr:street":"Str;Tirol",
    "iso:country":"AT",
    "sg:address":"Wildbichler Str 32",
    "sg:city":"Ebbs",
    "sg:orig_category":"Volksschulen",
    "sg:phone":"+43 5373 42391",
    "sg:postcode":"6341",
    "sg:province":"Tirol",
    "wof:name":"Volksschule",
    "wof:placetype":"venue"
},
  "geometry": {"coordinates":[12.2149419785,47.6286087036],"type":"Point"}
}