{
  "type": "Feature",
  "properties": {
    "addr:full":"Kirchenpl 4 Gumpoldskirchen Nieder\u00f6sterreich 2352",
    "addr:housenumber":"4",
    "addr:postcode":"2352",
    "addr:street":"Kirchenpl",
    "iso:country":"AT",
    "sg:address":"Kirchenpl 4",
    "sg:city":"Gumpoldskirchen",
    "sg:classifiers":[
        {
            "category":"Travel",
            "subcategory":"Hotels & Motels",
            "type":"Entertainment"
        }
    ],
    "sg:phone":"+43 4322 52607048",
    "sg:postcode":"2352",
    "sg:province":"Nieder\u00f6sterreich",
    "wof:name":"Deutscher Orden - Br\u00fcder des Deutschen Ordens St.Mariens z Jerusalem",
    "wof:placetype":"venue"
},
  "geometry": {"coordinates":[16.2743148804,48.0457191467],"type":"Point"}
}