{
  "type": "Feature",
  "properties": {
    "iso:country":"AT",
    "sg:address":"Schallemmersdorf 12",
    "sg:city":"Emmersdorf an der Donau",
    "sg:classifiers":[
        {
            "category":"Home & Garden",
            "subcategory":"Building Materials",
            "type":"Retail Goods"
        }
    ],
    "sg:phone":"+43 4366 42033819",
    "sg:postcode":"3644",
    "sg:province":"Nieder\u00f6sterreich",
    "sg:tags":[
        "baustoffe",
        "-material",
        "u"
    ],
    "wof:name":"Ertl Georg - Brenn- u Baustoffhandel",
    "wof:placetype":"venue"
},
  "geometry": {"coordinates":[15.353679657,48.2547988892],"type":"Point"}
}