{
  "type": "Feature",
  "properties": {
    "iso:country":"AT",
    "sg:address":"Nr 4",
    "sg:city":"S\u00e4usenstein",
    "sg:orig_category":"Non-Classified Establishments",
    "sg:phone":"+43 7412 52527",
    "sg:postcode":"3374",
    "sg:province":"Nieder\u00f6sterreich",
    "wof:name":"Steiner GmbH & Co KG",
    "wof:placetype":"venue"
},
  "geometry": {"coordinates":[15.1166582108,48.1923294067],"type":"Point"}
}