{
  "type": "Feature",
  "properties": {
    "addr:full":"Unteres Pfarrtal 197 Mariapfarr Salzburg 5571",
    "addr:housenumber":"197",
    "addr:postcode":"5571",
    "addr:street":"Unteres Pfarrtal;Salzburg",
    "iso:country":"AT",
    "sg:address":"Unteres Pfarrtal 197",
    "sg:city":"Mariapfarr",
    "sg:orig_category":"Appartements / Ferienwohnungen",
    "sg:phone":"+43 6473 8319",
    "sg:postcode":"5571",
    "sg:province":"Salzburg",
    "wof:name":"G\u00e4stehaus Fam Zaller",
    "wof:placetype":"venue"
},
  "geometry": {"coordinates":[13.7425422668,47.1506843567],"type":"Point"}
}