{
  "type": "Feature",
  "properties": {
    "addr:full":"Am Vogelherd 6 Hohenems Vorarlberg 6845",
    "addr:housenumber":"6",
    "addr:postcode":"6845",
    "addr:street":"Am Vogelherd",
    "iso:country":"AT",
    "sg:address":"Am Vogelherd 6",
    "sg:city":"Hohenems",
    "sg:orig_category":"Baumeister",
    "sg:phone":"+43 5576 760360",
    "sg:postcode":"6845",
    "sg:province":"Vorarlberg",
    "wof:name":"Burtscher Reinhard Ing - B\u00fcro f ganzheitliches Bauen",
    "wof:placetype":"venue"
},
  "geometry": {"coordinates":[9.6880464554,47.3551292419],"type":"Point"}
}