{
  "type": "Feature",
  "properties": {
    "addr:full":"Lilienthalg 26 Graz Steiermark 8020",
    "addr:housenumber":"26",
    "addr:postcode":"8020",
    "addr:street":"Lilienthalg",
    "iso:country":"AT",
    "sg:address":"Lilienthalg 26",
    "sg:city":"Graz",
    "sg:orig_category":"Psychotherapie",
    "sg:phone":"+43 316 573060",
    "sg:postcode":"8020",
    "sg:province":"Steiermark",
    "wof:name":"Haselwander Helmut Dr",
    "wof:placetype":"venue"
},
  "geometry": {"coordinates":[15.4040727615,47.074420929],"type":"Point"}
}