{
  "type": "Feature",
  "properties": {
    "iso:country":"AT",
    "sg:address":"Torplatz 2a ",
    "sg:city":"Feldbach",
    "sg:classifiers":[
        {
            "category":"Professional",
            "subcategory":"Printing & Photocopies",
            "type":"Services"
        }
    ],
    "sg:phone":"+43 4331 522318",
    "sg:postcode":"8330",
    "sg:province":"Steiermark",
    "wof:name":"DRUCKEREI SCHARMER GES.MBH & CO KG",
    "wof:placetype":"venue"
},
  "geometry": {"coordinates":[15.8873939514,46.9525184631],"type":"Point"}
}