{
  "type": "Feature",
  "properties": {
    "addr:full":"Tagwacht 4 Mannersdorf an der Rabnitz Burgenland 7444",
    "addr:housenumber":"4",
    "addr:postcode":"7444",
    "addr:street":"Tagwacht",
    "iso:country":"AT",
    "sg:address":"Tagwacht 4",
    "sg:city":"Mannersdorf an der Rabnitz",
    "sg:orig_category":"Musikgruppen",
    "sg:phone":"+43 664 1621916",
    "sg:postcode":"7444",
    "sg:province":"Burgenland",
    "wof:name":"Jagdhornbl\u00e4sergruppe St. Eustachius",
    "wof:placetype":"venue"
},
  "geometry": {"coordinates":[16.5196781158,47.4234924316],"type":"Point"}
}