{
  "type": "Feature",
  "properties": {
    "addr:full":"Sportg. 8 Krumbach Nieder\u00f6sterreich 2851",
    "addr:housenumber":"8",
    "addr:postcode":"2851",
    "addr:street":"Sportg.",
    "iso:country":"AT",
    "sg:address":"Sportg. 8",
    "sg:city":"Krumbach",
    "sg:classifiers":[
        {
            "category":"Parking",
            "subcategory":"Lot",
            "type":"Transportation"
        }
    ],
    "sg:phone":"+43 4326 4742266",
    "sg:postcode":"2851",
    "sg:province":"Nieder\u00f6sterreich",
    "sg:tags":[
        "transport",
        "road"
    ],
    "wof:name":"BUCHEGGER TRANSPORTE GES.MBH",
    "wof:placetype":"venue"
},
  "geometry": {"coordinates":[16.192943573,47.5234718323],"type":"Point"}
}