{
  "type": "Feature",
  "properties": {
    "iso:country":"AT",
    "sg:address":"Kaserng 21",
    "sg:city":"Judenburg",
    "sg:orig_category":"Damenmoden",
    "sg:phone":"+43 3572 826620",
    "sg:postcode":"8750",
    "sg:province":"Steiermark",
    "wof:name":"Modenhaus Friedrich Krenn GmbH",
    "wof:placetype":"venue"
},
  "geometry": {"coordinates":[14.663028717,47.1692733765],"type":"Point"}
}