{
  "type": "Feature",
  "properties": {
    "iso:country":"AT",
    "sg:address":"Nr 42",
    "sg:city":"Albrechtsberg an der Gro\u00dfen Krems",
    "sg:orig_category":"Lebensmittel / Einzelhandel",
    "sg:phone":"+43 4328 76386",
    "sg:postcode":"3613",
    "sg:province":"Nieder\u00f6sterreich",
    "wof:name":"Kastner EinzelhandelsgesmbH",
    "wof:placetype":"venue"
},
  "geometry": {"coordinates":[15.3689508438,48.4618797302],"type":"Point"}
}