{
  "type": "Feature",
  "properties": {
    "iso:country":"AT",
    "sg:address":"Tragweiner Str 56",
    "sg:city":"Pregarten",
    "sg:orig_category":"Non-Classified Establishments",
    "sg:phone":"+43 7236 31110",
    "sg:postcode":"4230",
    "sg:province":"Ober\u00f6sterreich",
    "wof:name":"G\u00fcterwegmeisterei Pregarten",
    "wof:placetype":"venue"
},
  "geometry": {"coordinates":[14.5415964127,48.3480110168],"type":"Point"}
}