{
  "type": "Feature",
  "properties": {
    "iso:country":"AT",
    "sg:address":"Wiener Str 79",
    "sg:city":"Wiener Neustadt",
    "sg:orig_category":"Steinmetzbetriebe",
    "sg:phone":"+43 2622 22255",
    "sg:postcode":"2700",
    "sg:province":"Nieder\u00f6sterreich",
    "wof:name":"Glaser GmbH",
    "wof:placetype":"venue"
},
  "geometry": {"coordinates":[16.2442913055,47.8252601624],"type":"Point"}
}