{
  "type": "Feature",
  "properties": {
    "addr:full":"Rathausstr 3 Langenlois Nieder\u00f6sterreich 3550",
    "addr:housenumber":"3",
    "addr:postcode":"3550",
    "addr:street":"Rathausstr",
    "iso:country":"AT",
    "sg:address":"Rathausstr 3",
    "sg:city":"Langenlois",
    "sg:classifiers":[
        {
            "category":"Restaurant",
            "type":"Food & Drink"
        }
    ],
    "sg:phone":"+43 2734 3742",
    "sg:postcode":"3550",
    "sg:province":"Nieder\u00f6sterreich",
    "sg:tags":[
        "pizzeria"
    ],
    "wof:name":"Pizzeria El Dorado",
    "wof:placetype":"venue"
},
  "geometry": {"coordinates":[15.6765213013,48.4726257324],"type":"Point"}
}