{
  "type": "Feature",
  "properties": {
    "addr:full":"Geist 12 Tannheim Tirol 6675",
    "addr:housenumber":"12",
    "addr:postcode":"6675",
    "addr:street":"Geist;Tirol",
    "iso:country":"AT",
    "sg:address":"Geist 12",
    "sg:city":"Tannheim",
    "sg:orig_category":"Appartements / Ferienwohnungen",
    "sg:phone":"+43 5675 20253",
    "sg:postcode":"6675",
    "sg:province":"Tirol",
    "wof:name":"Landhaus Christina",
    "wof:placetype":"venue"
},
  "geometry": {"coordinates":[10.5162248611,47.4965858459],"type":"Point"}
}