{
  "type": "Feature",
  "properties": {
    "iso:country":"AT",
    "sg:address":"Messendorfgrund 17",
    "sg:city":"St. Peter",
    "sg:classifiers":[
        {
            "category":"Arts & Performance",
            "subcategory":"Dance",
            "type":"Entertainment"
        }
    ],
    "sg:phone":"+43 316 4053030",
    "sg:postcode":"8042",
    "sg:province":"Steiermark",
    "sg:tags":[
        "transport"
    ],
    "wof:name":"Stoff Transporte Ges.m.b.H.",
    "wof:placetype":"venue"
},
  "geometry": {"coordinates":[15.4799203873,47.0419769287],"type":"Point"}
}