{
  "type": "Feature",
  "properties": {
    "addr:full":"C v H\u00f6tzendorf-Str 9 Voitsberg Steiermark 8570",
    "addr:housenumber":"9",
    "addr:postcode":"8570",
    "addr:street":"V Hoetzendorf-Str",
    "iso:country":"AT",
    "sg:address":"C v H\u00f6tzendorf-Str 9",
    "sg:city":"Voitsberg",
    "sg:orig_category":"Waren Aller Art",
    "sg:phone":"+43 3142 26182",
    "sg:postcode":"8570",
    "sg:province":"Steiermark",
    "wof:name":"Weltladen",
    "wof:placetype":"venue"
},
  "geometry": {"coordinates":[15.1501398087,47.0494194031],"type":"Point"}
}