{
  "type": "Feature",
  "properties": {
    "addr:full":"Wiener Str 99 Traiskirchen Nieder\u00f6sterreich 2514",
    "addr:postcode":"2514",
    "addr:street":"99",
    "iso:country":"AT",
    "sg:address":"Wiener Str 99",
    "sg:city":"Traiskirchen",
    "sg:orig_category":"Antriebstechnik",
    "sg:phone":"+43 2252 547330",
    "sg:postcode":"2514",
    "sg:province":"Nieder\u00f6sterreich",
    "wof:name":"J\u00e4gersberger Franz Ing",
    "wof:placetype":"venue"
},
  "geometry": {"coordinates":[16.2994480133,48.0268974304],"type":"Point"}
}