{
  "type": "Feature",
  "properties": {
    "addr:full":"Ludwig-Koe\u00dfler-Pl 3 Wien Wien 1030",
    "addr:housenumber":"3",
    "addr:postcode":"1030",
    "addr:street":"Ludwig-Koessler-Pl",
    "iso:country":"AT",
    "sg:address":"Ludwig-Koe\u00dfler-Pl 3",
    "sg:city":"Wien",
    "sg:orig_category":"Non-Classified Establishments",
    "sg:phone":"+43 1 7109517",
    "sg:postcode":"1030",
    "sg:province":"Wien",
    "wof:name":"TAXI-TEL Standplatztelefon Betriebs GmbH",
    "wof:placetype":"venue"
},
  "geometry": {"coordinates":[16.4092903137,48.1962242126],"type":"Point"}
}