{
  "type": "Feature",
  "properties": {
    "addr:full":"Raiffeisenstr 60 Graz Steiermark 8010",
    "addr:housenumber":"60",
    "addr:postcode":"8010",
    "addr:street":"Raiffeisenstr",
    "iso:country":"AT",
    "sg:address":"Raiffeisenstr 60",
    "sg:city":"Graz",
    "sg:orig_category":"Massagen",
    "sg:phone":"+43 699 10068666",
    "sg:postcode":"8010",
    "sg:province":"Steiermark",
    "wof:name":"Lerchbaumer August - Massagefachinstitut",
    "wof:placetype":"venue"
},
  "geometry": {"coordinates":[15.4478759766,47.0515480042],"type":"Point"}
}