{
  "type": "Feature",
  "properties": {
    "addr:full":"Adi-Dassler-Gasse 2 Klagenfurt-Viktring K\u00e4rnten 9073",
    "addr:housenumber":"2",
    "addr:postcode":"9073",
    "addr:street":"Adi-Dassler-Gasse;Kaernten",
    "iso:country":"AT",
    "sg:address":"Adi-Dassler-Gasse 2",
    "sg:city":"Klagenfurt-Viktring",
    "sg:classifiers":[
        {
            "category":"Home & Garden",
            "subcategory":"Household Appliances",
            "type":"Retail Goods"
        }
    ],
    "sg:phone":"+43 664 1550673",
    "sg:postcode":"9073",
    "sg:province":"K\u00e4rnten",
    "sg:tags":[
        "electric"
    ],
    "wof:name":"Elektro Helmut Dohr KEG",
    "wof:placetype":"venue"
},
  "geometry": {"coordinates":[14.2813844681,46.5803871155],"type":"Point"}
}