{
  "type": "Feature",
  "properties": {
    "iso:country":"AT",
    "sg:address":"Walzeng 40",
    "sg:city":"Perchtoldsdorf",
    "sg:orig_category":"Heurigen / Buschenschank",
    "sg:phone":"+43 1 8654457",
    "sg:postcode":"2380",
    "sg:province":"Nieder\u00f6sterreich",
    "wof:name":"Wurth Franz und Monika",
    "wof:placetype":"venue"
},
  "geometry": {"coordinates":[16.2561225891,48.1215248108],"type":"Point"}
}