{
  "type": "Feature",
  "properties": {
    "addr:full":"Venedigersdlg 4a St. Johann im Pongau Salzburg 5600",
    "addr:housenumber":"4a",
    "addr:postcode":"5600",
    "addr:street":"Venedigersdlg;Salzburg",
    "iso:country":"AT",
    "sg:address":"Venedigersdlg 4a",
    "sg:city":"St. Johann im Pongau",
    "sg:orig_category":"Fleischhauereien",
    "sg:phone":"+43 4364 126150",
    "sg:postcode":"5600",
    "sg:province":"Salzburg",
    "wof:name":"Urban KG",
    "wof:placetype":"venue"
},
  "geometry": {"coordinates":[13.2055616379,47.3558959961],"type":"Point"}
}