{
  "type": "Feature",
  "properties": {
    "iso:country":"AT",
    "sg:address":"Glockeng 4c",
    "sg:city":"Salzburg",
    "sg:orig_category":"Beratungsstellen",
    "sg:phone":"+43 662 84929111",
    "sg:postcode":"5020",
    "sg:province":"Salzburg",
    "wof:name":"Make it - B\u00fcro f M\u00e4dchenf\u00f6rderung",
    "wof:placetype":"venue"
},
  "geometry": {"coordinates":[13.0511274338,47.8046379089],"type":"Point"}
}