{
  "type": "Feature",
  "properties": {
    "addr:full":"Ruster Str 17-19 Eisenstadt Burgenland 7000",
    "addr:postcode":"17-19;7000",
    "addr:street":"Str",
    "iso:country":"AT",
    "sg:address":"Ruster Str 17-19",
    "sg:city":"Eisenstadt",
    "sg:orig_category":"Elektroinstallationsunternehmen",
    "sg:phone":"+43 2682 63556",
    "sg:postcode":"7000",
    "sg:province":"Burgenland",
    "wof:name":"Elektro Dipl-Ing Radics GesmbH",
    "wof:placetype":"venue"
},
  "geometry": {"coordinates":[16.5219955444,47.8435058594],"type":"Point"}
}