{
  "type": "Feature",
  "properties": {
    "addr:full":"Inng 6 Kufstein Tirol 6330",
    "addr:housenumber":"6",
    "addr:postcode":"6330",
    "addr:street":"Inng;Tirol",
    "iso:country":"AT",
    "sg:address":"Inng 6",
    "sg:city":"Kufstein",
    "sg:classifiers":[
        {
            "category":"Restaurant",
            "type":"Food & Drink"
        }
    ],
    "sg:phone":"+43 5372 71874",
    "sg:postcode":"6330",
    "sg:province":"Tirol",
    "sg:tags":[
        "pizzeria"
    ],
    "wof:name":"Pizzeria Va bene",
    "wof:placetype":"venue"
},
  "geometry": {"coordinates":[12.1701383591,47.5843887329],"type":"Point"}
}