{
  "type": "Feature",
  "properties": {
    "addr:full":"Waginger Str 12 Kufstein Tirol 6330",
    "addr:housenumber":"12",
    "addr:postcode":"6330",
    "addr:street":"Str;Tirol",
    "iso:country":"AT",
    "sg:address":"Waginger Str 12",
    "sg:city":"Kufstein",
    "sg:orig_category":"Banken U Sparkassen",
    "sg:phone":"+43 5372 636760",
    "sg:postcode":"6330",
    "sg:province":"Tirol",
    "wof:name":"Volksbank Kufstein regGenmbH",
    "wof:placetype":"venue"
},
  "geometry": {"coordinates":[12.1518001556,47.572429657],"type":"Point"}
}