{
  "type": "Feature",
  "properties": {
    "iso:country":"AT",
    "sg:address":"Liebenauer Hauptstr 187/P",
    "sg:city":"Liebenau",
    "sg:orig_category":"Politische Parteien",
    "sg:phone":"+43 316 409916",
    "sg:postcode":"8041",
    "sg:province":"Steiermark",
    "wof:name":"\u00f6sterreichische Volkspartei (\u00f6VP)",
    "wof:placetype":"venue"
},
  "geometry": {"coordinates":[15.4769926071,47.0117263794],"type":"Point"}
}