{
  "type": "Feature",
  "properties": {
    "addr:full":"Prager Str 19 Horn Nieder\u00f6sterreich 3580",
    "addr:housenumber":"19",
    "addr:postcode":"3580",
    "addr:street":"Str",
    "iso:country":"AT",
    "sg:address":"Prager Str 19",
    "sg:city":"Horn",
    "sg:orig_category":"Fleischhauereien",
    "sg:phone":"+43 2982 26370",
    "sg:postcode":"3580",
    "sg:province":"Nieder\u00f6sterreich",
    "wof:name":"Matzek Adolf",
    "wof:placetype":"venue"
},
  "geometry": {"coordinates":[15.6539478302,48.6615715027],"type":"Point"}
}