{
  "type": "Feature",
  "properties": {
    "addr:full":"Adalbert Stifter-Str 9 Amstetten Nieder\u00f6sterreich 3300",
    "addr:housenumber":"9",
    "addr:postcode":"3300",
    "addr:street":"Adalbert Stifter-Str;Niederoesterreich",
    "iso:country":"AT",
    "sg:address":"Adalbert Stifter-Str 9",
    "sg:city":"Amstetten",
    "sg:orig_category":"Autohandel",
    "sg:phone":"+43 7472 65525",
    "sg:postcode":"3300",
    "sg:province":"Nieder\u00f6sterreich",
    "wof:name":"HOST - Hochreiter Gerhard Industrie- und KFZ-Werkst\u00e4ttenbedarf",
    "wof:placetype":"venue"
},
  "geometry": {"coordinates":[14.8695955276,48.1188392639],"type":"Point"}
}