{
  "type": "Feature",
  "properties": {
    "iso:country":"AT",
    "sg:address":"Birkeng 1",
    "sg:city":"Birkfeld",
    "sg:orig_category":"Polytechnische Schulen",
    "sg:phone":"+43 3174 3040",
    "sg:postcode":"8190",
    "sg:province":"Steiermark",
    "wof:name":"Polytechnische Schule",
    "wof:placetype":"venue"
},
  "geometry": {"coordinates":[15.6905584335,47.3535346985],"type":"Point"}
}