{
  "type": "Feature",
  "properties": {
    "addr:full":"Friesacher Str 32 St. Veit an der Glan K\u00e4rnten 9300",
    "addr:housenumber":"32",
    "addr:postcode":"9300",
    "addr:street":"Str;Kaernten",
    "iso:country":"AT",
    "sg:address":"Friesacher Str 32",
    "sg:city":"St. Veit an der Glan",
    "sg:orig_category":"Transportunternehmen",
    "sg:phone":"+43 4212 2177",
    "sg:postcode":"9300",
    "sg:province":"K\u00e4rnten",
    "wof:name":"St Veiter G\u00fctertrans Dietmar Kriegl GesmbH",
    "wof:placetype":"venue"
},
  "geometry": {"coordinates":[14.3690299988,46.7739105225],"type":"Point"}
}