{
  "type": "Feature",
  "properties": {
    "addr:full":"Derfflingerstr 31 Linz Ober\u00f6sterreich 4020",
    "addr:housenumber":"31",
    "addr:postcode":"4020",
    "addr:street":"Derfflingerstr",
    "iso:country":"AT",
    "sg:address":"Derfflingerstr 31",
    "sg:city":"Linz",
    "sg:orig_category":"Bewachungsunternehmen",
    "sg:phone":"+43 732 6718920",
    "sg:postcode":"4020",
    "sg:province":"Ober\u00f6sterreich",
    "wof:name":"HEL-WACHT Sicherheits- & Kommunikationstechnik GmbH",
    "wof:placetype":"venue"
},
  "geometry": {"coordinates":[14.3129348755,48.309337616],"type":"Point"}
}