{
  "type": "Feature",
  "properties": {
    "addr:full":"Draschestr 31 Wien Wien 1230",
    "addr:housenumber":"31",
    "addr:postcode":"1230",
    "addr:street":"Draschestr",
    "iso:country":"AT",
    "sg:address":"Draschestr 31",
    "sg:city":"Wien",
    "sg:orig_category":"Automaten",
    "sg:phone":"+43 4316 1624339",
    "sg:postcode":"1230",
    "sg:province":"Wien",
    "sg:website":"verpflegungssysteme.at",
    "wof:name":"Kabran Verpflegungssysteme",
    "wof:placetype":"venue"
},
  "geometry": {"coordinates":[16.3574733734,48.1468086243],"type":"Point"}
}