{
  "type": "Feature",
  "properties": {
    "addr:full":"Knieberg 62 Ybbsitz Nieder\u00f6sterreich 3341",
    "addr:housenumber":"62",
    "addr:postcode":"3341",
    "addr:street":"Knieberg",
    "iso:country":"AT",
    "sg:address":"Knieberg 62",
    "sg:city":"Ybbsitz",
    "sg:classifiers":[
        {
            "category":"Structure",
            "subcategory":"Office Building",
            "type":"Public Place"
        }
    ],
    "sg:phone":"+43 7443 86516",
    "sg:postcode":"3341",
    "sg:province":"Nieder\u00f6sterreich",
    "sg:tags":[
        "assemblies",
        "erecting",
        "skeleton"
    ],
    "wof:name":"WFMS - Wieser Fertigung Montage & Service GmbH",
    "wof:placetype":"venue"
},
  "geometry": {"coordinates":[14.8725996017,47.9498176575],"type":"Point"}
}