{
  "type": "Feature",
  "properties": {
    "addr:full":"Mickstetten 27 St. Florian Ober\u00f6sterreich 4490",
    "addr:housenumber":"27",
    "addr:postcode":"4490",
    "addr:street":"Mickstetten",
    "iso:country":"AT",
    "sg:address":"Mickstetten 27",
    "sg:city":"St. Florian",
    "sg:orig_category":"Tischlereien",
    "sg:phone":"+43 7224 8611",
    "sg:postcode":"4490",
    "sg:province":"Ober\u00f6sterreich",
    "wof:name":"Antensteiner Leopold - Tischlerwerkst\u00e4tte",
    "wof:placetype":"venue"
},
  "geometry": {"coordinates":[14.3307256699,48.1862602234],"type":"Point"}
}