{
  "type": "Feature",
  "properties": {
    "addr:full":"Kircheng 23 Langenlebarn Nieder\u00f6sterreich 3425",
    "addr:housenumber":"23",
    "addr:postcode":"3425",
    "addr:street":"Kircheng",
    "iso:country":"AT",
    "sg:address":"Kircheng 23",
    "sg:city":"Langenlebarn",
    "sg:orig_category":"Fotografen",
    "sg:phone":"+43 2272 61940",
    "sg:postcode":"3425",
    "sg:province":"Nieder\u00f6sterreich",
    "wof:name":"Wallner Arthur",
    "wof:placetype":"venue"
},
  "geometry": {"coordinates":[16.1162967682,48.3305931091],"type":"Point"}
}