{
  "type": "Feature",
  "properties": {
    "addr:full":"Stadtgraben 18 Hall in Tirol Tirol 6060",
    "addr:housenumber":"18",
    "addr:postcode":"6060",
    "addr:street":"Stadtgraben;Tirol",
    "iso:country":"AT",
    "sg:address":"Stadtgraben 18",
    "sg:city":"Hall in Tirol",
    "sg:classifiers":[
        {
            "category":"Restaurant",
            "type":"Food & Drink"
        }
    ],
    "sg:phone":"+43 5223 41910",
    "sg:postcode":"6060",
    "sg:province":"Tirol",
    "sg:tags":[
        "pizzeria"
    ],
    "wof:name":"Restaurant-Pizza Geisterburg",
    "wof:placetype":"venue"
},
  "geometry": {"coordinates":[11.5092439651,47.2826576233],"type":"Point"}
}