{
  "type": "Feature",
  "properties": {
    "iso:country":"AT",
    "sg:address":"Salzburger Str 1",
    "sg:city":"Bischofshofen",
    "sg:orig_category":"Volkshochschulen",
    "sg:phone":"+43 6462 4988",
    "sg:postcode":"5500",
    "sg:province":"Salzburg",
    "wof:name":"Salzburger Volkshochschule - Bezirksstelle Pongau",
    "wof:placetype":"venue"
},
  "geometry": {"coordinates":[13.2186841965,47.4179267883],"type":"Point"}
}