{
  "type": "Feature",
  "properties": {
    "addr:full":"Wagramer Strasse 81/II/3 Wien Wien 1220",
    "addr:housenumber":"81 / ii / 3",
    "addr:postcode":"1220",
    "addr:street":"Wagramer Strasse",
    "iso:country":"AT",
    "sg:address":"Wagramer Strasse 81/II/3",
    "sg:city":"Wien",
    "sg:classifiers":[
        {
            "category":"Structure",
            "subcategory":"Warehouse",
            "type":"Public Place"
        }
    ],
    "sg:phone":"+43 1 2032566",
    "sg:postcode":"1220",
    "sg:province":"Wien",
    "sg:tags":[
        "catheter",
        "guide-wires"
    ],
    "wof:name":"Zymed Gmbh (vormals Zmatlik)",
    "wof:placetype":"venue"
},
  "geometry": {"coordinates":[16.444606781,48.2497138977],"type":"Point"}
}