{
  "type": "Feature",
  "properties": {
    "addr:full":"Durisolstr 7/10 Wels Ober\u00f6sterreich 4600",
    "addr:housenumber":"7 / 10",
    "addr:postcode":"4600",
    "addr:street":"Durisolstr;Oberoesterreich",
    "iso:country":"AT",
    "sg:address":"Durisolstr 7/10",
    "sg:city":"Wels",
    "sg:orig_category":"Installationsunternehmen",
    "sg:phone":"+43 1 798300010",
    "sg:postcode":"4600",
    "sg:province":"Ober\u00f6sterreich",
    "wof:name":"Vatro Trocknungs- und Sanierungstechnik GmbH & Co KG",
    "wof:placetype":"venue"
},
  "geometry": {"coordinates":[14.0079917908,48.1509475708],"type":"Point"}
}