{
  "type": "Feature",
  "properties": {
    "addr:full":"Radlpa\u00dfstr 30 Wies Steiermark 8551",
    "addr:housenumber":"30",
    "addr:postcode":"8551",
    "addr:street":"Radlpassstr",
    "iso:country":"AT",
    "sg:address":"Radlpa\u00dfstr 30",
    "sg:city":"Wies",
    "sg:orig_category":"Lebensmittel / Einzelhandel",
    "sg:phone":"+43 3465 20057",
    "sg:postcode":"8551",
    "sg:province":"Steiermark",
    "wof:name":"Hofer KG",
    "wof:placetype":"venue"
},
  "geometry": {"coordinates":[15.2543048859,46.7182693481],"type":"Point"}
}