{
  "type": "Feature",
  "properties": {
    "iso:country":"AT",
    "sg:address":"Lungendorf 30",
    "sg:city":"Pettenbach",
    "sg:classifiers":[
        {
            "category":"Home & Garden",
            "subcategory":"Building Materials",
            "type":"Retail Goods"
        }
    ],
    "sg:phone":"+43 7586 6023",
    "sg:postcode":"4643",
    "sg:province":"Ober\u00f6sterreich",
    "sg:tags":[
        "kind",
        "roll",
        "blank"
    ],
    "wof:name":"Uni-Cut Wasserstrahl-Schneidetechnik",
    "wof:placetype":"venue"
},
  "geometry": {"coordinates":[13.9603796005,47.9773101807],"type":"Point"}
}