{
  "type": "Feature",
  "properties": {
    "addr:full":"Petergstammstr 1 Eisenerz Steiermark 8790",
    "addr:housenumber":"1",
    "addr:postcode":"8790",
    "addr:street":"Petergstammstr",
    "iso:country":"AT",
    "sg:address":"Petergstammstr 1",
    "sg:city":"Eisenerz",
    "sg:orig_category":"Installationsunternehmen",
    "sg:phone":"+43 3848 56420",
    "sg:postcode":"8790",
    "sg:province":"Steiermark",
    "wof:name":"Traussnigg H GesmbH",
    "wof:placetype":"venue"
},
  "geometry": {"coordinates":[14.8612031937,47.5600013733],"type":"Point"}
}