{
  "type": "Feature",
  "properties": {
    "addr:full":"Johannes Filzer-Str 1 Salzburg Salzburg 5020",
    "addr:housenumber":"1",
    "addr:postcode":"5020",
    "addr:street":"Salzburg",
    "iso:country":"AT",
    "sg:address":"Johannes Filzer-Str 1",
    "sg:city":"Salzburg",
    "sg:orig_category":"Genossenschaften",
    "sg:phone":"+43 662 622807",
    "sg:postcode":"5020",
    "sg:province":"Salzburg",
    "wof:name":"KS Wohnungsbau GmbH",
    "wof:placetype":"venue"
},
  "geometry": {"coordinates":[13.0635175705,47.7944145203],"type":"Point"}
}