{
  "type": "Feature",
  "properties": {
    "addr:full":"Kirchdorf 6 Gaspoltshofen Ober\u00f6sterreich 4673",
    "addr:housenumber":"6",
    "addr:postcode":"4673",
    "addr:street":"Kirchdorf",
    "iso:country":"AT",
    "sg:address":"Kirchdorf 6",
    "sg:city":"Gaspoltshofen",
    "sg:classifiers":[
        {
            "category":"Wholesale",
            "subcategory":"Machinery & Supplies",
            "type":"Manufacturing & Wholesale Goods"
        }
    ],
    "sg:phone":"+43 4377 3560510",
    "sg:postcode":"4673",
    "sg:province":"Ober\u00f6sterreich",
    "sg:tags":[
        "-",
        "agriculture",
        "equipment"
    ],
    "wof:name":"GRUBER MASCHINEN GMBH",
    "wof:placetype":"venue"
},
  "geometry": {"coordinates":[13.7417516708,48.1419410706],"type":"Point"}
}