{
  "type": "Feature",
  "properties": {
    "iso:country":"AT",
    "sg:address":"Kauerg 3-5",
    "sg:city":"Wien",
    "sg:orig_category":"Hauptschulen",
    "sg:phone":"+43 1 8923541",
    "sg:postcode":"1150",
    "sg:province":"Wien",
    "wof:name":"Schulen d Stadt Wien",
    "wof:placetype":"venue"
},
  "geometry": {"coordinates":[16.3235855103,48.1908607483],"type":"Point"}
}