{
  "type": "Feature",
  "properties": {
    "iso:country":"AT",
    "sg:address":"Br\u00e4uhausg 11",
    "sg:city":"St. Veit an der Glan",
    "sg:orig_category":"Installationsunternehmen",
    "sg:phone":"+43 4212 3178",
    "sg:postcode":"9300",
    "sg:province":"K\u00e4rnten",
    "wof:name":"Schumach Karl",
    "wof:placetype":"venue"
},
  "geometry": {"coordinates":[14.3559570312,46.7671928406],"type":"Point"}
}