{
  "type": "Feature",
  "properties": {
    "addr:full":"HNr 145 Ried im Oberinntal Tirol 6531",
    "addr:housenumber":"145",
    "addr:postcode":"6531",
    "addr:street":"Hnr;Tirol",
    "iso:country":"AT",
    "sg:address":"HNr 145",
    "sg:city":"Ried im Oberinntal",
    "sg:orig_category":"Immobilien U Baugewerbe, Baugewerbe",
    "sg:phone":"+43 4354 726407",
    "sg:postcode":"6531",
    "sg:province":"Tirol",
    "sg:website":"http://www.tischlerei-tschallener.at",
    "wof:name":"Tischlerei Tschallener",
    "wof:placetype":"venue"
},
  "geometry": {"coordinates":[10.654545784,47.0553817749],"type":"Point"}
}