{
  "type": "Feature",
  "properties": {
    "addr:full":"Karmeliterpl 2 Wien Wien 1020",
    "addr:housenumber":"2",
    "addr:postcode":"1020",
    "addr:street":"Karmeliterpl",
    "iso:country":"AT",
    "sg:address":"Karmeliterpl 2",
    "sg:city":"Wien",
    "sg:orig_category":"Geschenkartikel",
    "sg:phone":"+43 1 2146698",
    "sg:postcode":"1020",
    "sg:province":"Wien",
    "wof:name":"Peyerl Sabine",
    "wof:placetype":"venue"
},
  "geometry": {"coordinates":[16.3794555664,48.215877533],"type":"Point"}
}