{
  "type": "Feature",
  "properties": {
    "addr:full":"Johann Strau\u00df-G 5 Oberwart Burgenland 7400",
    "addr:housenumber":"5",
    "addr:postcode":"7400",
    "iso:country":"AT",
    "sg:address":"Johann Strau\u00df-G 5",
    "sg:city":"Oberwart",
    "sg:orig_category":"Feuerwehren",
    "sg:phone":"+43 3352 325230",
    "sg:postcode":"7400",
    "sg:province":"Burgenland",
    "wof:name":"Feuerwehrkommando Oberwart",
    "wof:placetype":"venue"
},
  "geometry": {"coordinates":[16.2070426941,47.290977478],"type":"Point"}
}