{
  "type": "Feature",
  "properties": {
    "addr:full":"Dillacher Str 14 Fernitz Steiermark 8072",
    "addr:housenumber":"14",
    "addr:postcode":"8072",
    "addr:street":"Str",
    "iso:country":"AT",
    "sg:address":"Dillacher Str 14",
    "sg:city":"Fernitz",
    "sg:orig_category":"Autobusunternehmen",
    "sg:phone":"+43 4331 3582443",
    "sg:postcode":"8072",
    "sg:province":"Steiermark",
    "wof:name":"Matzer Kurt",
    "wof:placetype":"venue"
},
  "geometry": {"coordinates":[15.4987697601,46.9728660583],"type":"Point"}
}