{
  "type": "Feature",
  "properties": {
    "addr:full":"E\u00dflinger Hauptstr 68 Wien Wien 1220",
    "addr:housenumber":"68",
    "addr:postcode":"1220",
    "addr:street":"Esslinger Hauptstr",
    "iso:country":"AT",
    "sg:address":"E\u00dflinger Hauptstr 68",
    "sg:city":"Wien",
    "sg:orig_category":"Spielwaren U Spiele",
    "sg:phone":"+43 1 7748896",
    "sg:postcode":"1220",
    "sg:province":"Wien",
    "wof:name":"Puckyb\u00e4rs-Laden Alfred Hussl",
    "wof:placetype":"venue"
},
  "geometry": {"coordinates":[16.5214653015,48.2144546509],"type":"Point"}
}