{
  "type": "Feature",
  "properties": {
    "iso:country":"AT",
    "sg:address":"Sparkassenweg 11",
    "sg:city":"Ach",
    "sg:classifiers":[
        {
            "category":"Professional",
            "subcategory":"Employment Agencies",
            "type":"Services"
        }
    ],
    "sg:phone":"+43 7727 4071",
    "sg:postcode":"5122",
    "sg:province":"Ober\u00f6sterreich",
    "sg:tags":[
        "pr",
        "relation",
        "public"
    ],
    "sg:website":"wilkom.at",
    "wof:name":"WILKOM - Dr. Wilde Kommunikationsberatung",
    "wof:placetype":"venue"
},
  "geometry": {"coordinates":[12.8391447067,48.1589889526],"type":"Point"}
}