{
  "type": "Feature",
  "properties": {
    "addr:full":"Ifilar 12 Satteins Vorarlberg 6822",
    "addr:housenumber":"12",
    "addr:postcode":"6822",
    "addr:street":"Ifilar",
    "iso:country":"AT",
    "sg:address":"Ifilar 12",
    "sg:city":"Satteins",
    "sg:orig_category":"Energiespartechnik",
    "sg:phone":"+43 5524 2348",
    "sg:postcode":"6822",
    "sg:province":"Vorarlberg",
    "wof:name":"Bischof Hanspeter",
    "wof:placetype":"venue"
},
  "geometry": {"coordinates":[9.6779460907,47.2192230225],"type":"Point"}
}