{
  "type": "Feature",
  "properties": {
    "addr:full":"Wiener Str 16 Petzenkirchen Nieder\u00f6sterreich 3252",
    "addr:postcode":"3252",
    "addr:street":"Niederoesterreich",
    "iso:country":"AT",
    "sg:address":"Wiener Str 16",
    "sg:city":"Petzenkirchen",
    "sg:orig_category":"Restaurants: Italienisch",
    "sg:phone":"+43 7416 53942",
    "sg:postcode":"3252",
    "sg:province":"Nieder\u00f6sterreich",
    "wof:name":"Uno La Strada Restaurant GmbH",
    "wof:placetype":"venue"
},
  "geometry": {"coordinates":[15.1513910294,48.1421661377],"type":"Point"}
}