{
  "type": "Feature",
  "properties": {
    "addr:full":"Wieselburger Str 5 Gresten Nieder\u00f6sterreich 3264",
    "addr:housenumber":"5",
    "addr:postcode":"3264",
    "addr:street":"Str",
    "iso:country":"AT",
    "sg:address":"Wieselburger Str 5",
    "sg:city":"Gresten",
    "sg:orig_category":"Tischlereien",
    "sg:phone":"+43 7487 2389",
    "sg:postcode":"3264",
    "sg:province":"Nieder\u00f6sterreich",
    "wof:name":"Tanzer Johann",
    "wof:placetype":"venue"
},
  "geometry": {"coordinates":[15.0227489471,47.9882316589],"type":"Point"}
}