{
  "type": "Feature",
  "properties": {
    "addr:full":"null Pitztaler/Gletscherb. St. Leonhard im Pitztal Tirol 6481",
    "addr:postcode":"6481",
    "addr:street":"Tirol",
    "iso:country":"AT",
    "sg:address":"null Pitztaler/Gletscherb.",
    "sg:city":"St. Leonhard im Pitztal",
    "sg:orig_category":"Bankomat-Standorte",
    "sg:phone":"+43 800 2048800",
    "sg:postcode":"6481",
    "sg:province":"Tirol",
    "wof:name":"Bankomat d Raiffeisenkasse Pitztal Wenns-Jerzens-St. Leonhard regGenmbH",
    "wof:placetype":"venue"
},
  "geometry": {"coordinates":[10.8461503983,47.0666313171],"type":"Point"}
}