{
  "type": "Feature",
  "properties": {
    "addr:full":"Pl\u00fcddemanngasse 53 Graz Steiermark 8010",
    "addr:housenumber":"53",
    "addr:postcode":"8010",
    "addr:street":"Plueddemanngasse",
    "iso:country":"AT",
    "sg:address":"Pl\u00fcddemanngasse 53",
    "sg:city":"Graz",
    "sg:classifiers":[
        {
            "category":"Autos & Motor Vehicles",
            "subcategory":"Auto Supplies",
            "type":"Retail Goods"
        }
    ],
    "sg:phone":"+43 316 461566",
    "sg:postcode":"8010",
    "sg:province":"Steiermark",
    "sg:tags":[
        "fire",
        "car",
        "extinguisher"
    ],
    "sg:website":"pyrus-pmp.at",
    "wof:name":"P.M.P. Feuerl\u00f6schger\u00e4te Produktions- und Vertriebsges.m.b.H .",
    "wof:placetype":"venue"
},
  "geometry": {"coordinates":[15.4431800842,47.0685653687],"type":"Point"}
}