{
  "type": "Feature",
  "properties": {
    "iso:country":"AT",
    "sg:address":"Hammerlweg 3",
    "sg:city":"Hof",
    "sg:orig_category":"Bauunternehmen",
    "sg:phone":"+43 4362 2922380",
    "sg:postcode":"5322",
    "sg:province":"Salzburg",
    "sg:website":"kibau.at",
    "wof:name":"Kibau Bauunternehmen GesmbH",
    "wof:placetype":"venue"
},
  "geometry": {"coordinates":[13.2269153595,47.8176841736],"type":"Point"}
}