{
  "type": "Feature",
  "properties": {
    "addr:full":"Ragnitzstrasse 303 Ragnitz Steiermark 8047",
    "addr:housenumber":"303",
    "addr:postcode":"8047",
    "addr:street":"Ragnitzstrasse",
    "iso:country":"AT",
    "sg:address":"Ragnitzstrasse 303",
    "sg:city":"Ragnitz",
    "sg:classifiers":[
        {
            "category":"Building & Trades",
            "subcategory":"Plumbing",
            "type":"Services"
        }
    ],
    "sg:phone":"+43 316 302152",
    "sg:postcode":"8047",
    "sg:province":"Steiermark",
    "sg:tags":[
        "supraregional",
        "gas"
    ],
    "wof:name":"Weinhandl Installationen",
    "wof:placetype":"venue"
},
  "geometry": {"coordinates":[15.5069093704,47.0750694275],"type":"Point"}
}