{
  "type": "Feature",
  "properties": {
    "addr:full":"Baumkirchnerring 4 Wiener Neustadt Nieder\u00f6sterreich 2700",
    "addr:housenumber":"4",
    "addr:postcode":"2700",
    "addr:street":"Baumkirchnerring",
    "iso:country":"AT",
    "sg:address":"Baumkirchnerring 4",
    "sg:city":"Wiener Neustadt",
    "sg:orig_category":"Suchtberatung / Alkohol, Drogen, Zigaretten",
    "sg:phone":"+43 4326 22373741",
    "sg:postcode":"2700",
    "sg:province":"Nieder\u00f6sterreich",
    "wof:name":"Drogenberatungsstelle des Anton Proksch-Institutes",
    "wof:placetype":"venue"
},
  "geometry": {"coordinates":[16.2424106598,47.8166313171],"type":"Point"}
}