{
  "type": "Feature",
  "properties": {
    "addr:full":"Moosstr 1 Mattighofen Ober\u00f6sterreich 5230",
    "addr:housenumber":"1",
    "addr:postcode":"5230",
    "addr:street":"Moosstr",
    "iso:country":"AT",
    "sg:address":"Moosstr 1",
    "sg:city":"Mattighofen",
    "sg:orig_category":"Dekorationsartikel",
    "sg:phone":"+43 7742 2143",
    "sg:postcode":"5230",
    "sg:province":"Ober\u00f6sterreich",
    "wof:name":"Doringer Rudolf",
    "wof:placetype":"venue"
},
  "geometry": {"coordinates":[13.1491680145,48.1036491394],"type":"Point"}
}