{
  "type": "Feature",
  "properties": {
    "iso:country":"AT",
    "sg:address":"Schulthe\u00dfg 1",
    "sg:city":"Wien",
    "sg:orig_category":"Teppichreinigung U -Reparatur",
    "sg:phone":"+43 800 3977377",
    "sg:postcode":"1170",
    "sg:province":"Wien",
    "wof:name":"Teppichreinigung 0800EXPRESS",
    "wof:placetype":"venue"
},
  "geometry": {"coordinates":[16.3169384003,48.2234115601],"type":"Point"}
}