{
  "type": "Feature",
  "properties": {
    "iso:country":"AT",
    "sg:address":"Triester Str 23",
    "sg:city":"Neunkirchen",
    "sg:orig_category":"Fu\u00c3\u0178pflege U Fu\u00c3\u0178pflegesalons",
    "sg:phone":"+43 4326 3563241",
    "sg:postcode":"2620",
    "sg:province":"Nieder\u00f6sterreich",
    "wof:name":"Sonnenland Schreib\u00f6ck-Wagner OEG",
    "wof:placetype":"venue"
},
  "geometry": {"coordinates":[16.0792942047,47.718837738],"type":"Point"}
}