{
  "type": "Feature",
  "properties": {
    "addr:full":"Dr.-Rudolf-Klafsky-Str 40 Baden Nieder\u00f6sterreich 2500",
    "addr:housenumber":"40",
    "addr:postcode":"2500",
    "addr:street":"Dr.-Rudolf-Klafsky-Str;Niederoesterreich",
    "iso:country":"AT",
    "sg:address":"Dr.-Rudolf-Klafsky-Str 40",
    "sg:city":"Baden",
    "sg:orig_category":"Handelsagenturen",
    "sg:phone":"+43 4322 5243977",
    "sg:postcode":"2500",
    "sg:province":"Nieder\u00f6sterreich",
    "wof:name":"Claus Gerhard",
    "wof:placetype":"venue"
},
  "geometry": {"coordinates":[16.217666626,48.0136680603],"type":"Point"}
}