{
  "type": "Feature",
  "properties": {
    "addr:full":"Nr 126 St. Georgen ob Murau Steiermark 8861",
    "addr:postcode":"8861",
    "addr:street":"Nr 126",
    "iso:country":"AT",
    "sg:address":"Nr 126",
    "sg:city":"St. Georgen ob Murau",
    "sg:orig_category":"Feuerwehren",
    "sg:phone":"+43 3537 272",
    "sg:postcode":"8861",
    "sg:province":"Steiermark",
    "wof:name":"Freiwillige Feuerwehr St Georgen ob Murau - St Lorenzen",
    "wof:placetype":"venue"
},
  "geometry": {"coordinates":[14.0995817184,47.1049461365],"type":"Point"}
}