{
  "type": "Feature",
  "properties": {
    "iso:country":"AT",
    "sg:address":"Stadtpl 40",
    "sg:city":"Wels",
    "sg:orig_category":"Sonnenstudios",
    "sg:phone":"+43 7242 70762",
    "sg:postcode":"4600",
    "sg:province":"Ober\u00f6sterreich",
    "wof:name":"Sunshine Dein Solarium",
    "wof:placetype":"venue"
},
  "geometry": {"coordinates":[14.0264797211,48.1574401855],"type":"Point"}
}