{
  "type": "Feature",
  "properties": {
    "addr:full":"Industriepark Str 3 Ennsdorf Nieder\u00f6sterreich 4482",
    "addr:housenumber":"3",
    "addr:postcode":"4482",
    "addr:street":"Industriepark Str",
    "iso:country":"AT",
    "sg:address":"Industriepark Str 3",
    "sg:city":"Ennsdorf",
    "sg:classifiers":[
        {
            "category":"Utilities",
            "subcategory":"Recycling",
            "type":"Services"
        }
    ],
    "sg:phone":"+43 7223 81860",
    "sg:postcode":"4482",
    "sg:province":"Nieder\u00f6sterreich",
    "wof:name":"BW Recycling GmbH",
    "wof:placetype":"venue"
},
  "geometry": {"coordinates":[14.5264797211,48.2271881104],"type":"Point"}
}