{
  "type": "Feature",
  "properties": {
    "iso:country":"AT",
    "sg:address":"Nr 55",
    "sg:city":"Katsch an der Mur",
    "sg:orig_category":"Bauunternehmen",
    "sg:phone":"+43 3588 6550",
    "sg:postcode":"8842",
    "sg:province":"Steiermark",
    "wof:name":"STRABAG AG",
    "wof:placetype":"venue"
},
  "geometry": {"coordinates":[14.282959938,47.1429824829],"type":"Point"}
}