{
  "type": "Feature",
  "properties": {
    "iso:country":"AT",
    "sg:address":"Rohrbacher Str 10",
    "sg:city":"Korneuburg",
    "sg:orig_category":"Cd, Dvd,Musikkassetten U Schallplatten",
    "sg:phone":"+43 2262 66510",
    "sg:postcode":"2100",
    "sg:province":"Nieder\u00f6sterreich",
    "wof:name":"TMI Top Music International Vetriebs-GmbH",
    "wof:placetype":"venue"
},
  "geometry": {"coordinates":[16.3210144043,48.3787841797],"type":"Point"}
}