{
  "type": "Feature",
  "properties": {
    "iso:country":"AT",
    "sg:address":"Pfarrgrund 3",
    "sg:city":"Taiskirchen im Innkreis",
    "sg:orig_category":"Elektroinstallationsunternehmen",
    "sg:phone":"+43 4377 647893",
    "sg:postcode":"4753",
    "sg:province":"Ober\u00f6sterreich",
    "wof:name":"Elektrotechnik ZINNER - Inh Zinner Herbert - Installationen u Handel",
    "wof:placetype":"venue"
},
  "geometry": {"coordinates":[13.5705947876,48.2640647888],"type":"Point"}
}