{
  "type": "Feature",
  "properties": {
    "iso:country":"AT",
    "sg:address":"Anton Bruckner-G 6",
    "sg:city":"Klosterneuburg",
    "sg:orig_category":"Volksschulen",
    "sg:phone":"+43 2243 444317",
    "sg:postcode":"3400",
    "sg:province":"Nieder\u00f6sterreich",
    "wof:name":"Volksschule",
    "wof:placetype":"venue"
},
  "geometry": {"coordinates":[16.3285198212,48.2940254211],"type":"Point"}
}