{
  "type": "Feature",
  "properties": {
    "iso:country":"AT",
    "sg:address":"Neue Landstr 105",
    "sg:city":"M\u00e4der",
    "sg:orig_category":"Psychotherapie",
    "sg:phone":"+43 5523 51250",
    "sg:postcode":"6841",
    "sg:province":"Vorarlberg",
    "wof:name":"Tiesler Johannes Dipl-PT",
    "wof:placetype":"venue"
},
  "geometry": {"coordinates":[-72.1344909668,44.9447059631],"type":"Point"}
}