{
  "type": "Feature",
  "properties": {
    "addr:full":"Wiesingerstr 2 Bad Ischl Ober\u00f6sterreich 4820",
    "addr:housenumber":"2",
    "addr:postcode":"4820",
    "addr:street":"Wiesingerstr",
    "iso:country":"AT",
    "sg:address":"Wiesingerstr 2",
    "sg:city":"Bad Ischl",
    "sg:orig_category":"Versicherungsunternehmen",
    "sg:phone":"+43 6132 231800",
    "sg:postcode":"4820",
    "sg:province":"Ober\u00f6sterreich",
    "wof:name":"Wiener St\u00e4dtische Allgemeine Versicherung AG",
    "wof:placetype":"venue"
},
  "geometry": {"coordinates":[13.6200342178,47.7126121521],"type":"Point"}
}