{
  "type": "Feature",
  "properties": {
    "addr:full":"Neunkirchner Str 71 Puchberg am Schneeberg Nieder\u00f6sterreich 2734",
    "addr:housenumber":"71",
    "addr:postcode":"2734",
    "addr:street":"Str",
    "iso:country":"AT",
    "sg:address":"Neunkirchner Str 71",
    "sg:city":"Puchberg am Schneeberg",
    "sg:orig_category":"Zimmereien",
    "sg:phone":"+43 4326 363344",
    "sg:postcode":"2734",
    "sg:province":"Nieder\u00f6sterreich",
    "wof:name":"Pichler-Zimmerei",
    "wof:placetype":"venue"
},
  "geometry": {"coordinates":[15.9196519852,47.7786102295],"type":"Point"}
}