{
  "type": "Feature",
  "properties": {
    "iso:country":"AT",
    "sg:address":"Garteng 29",
    "sg:city":"Graz",
    "sg:orig_category":"Architekten",
    "sg:phone":"+43 316 383785",
    "sg:postcode":"8010",
    "sg:province":"Steiermark",
    "wof:name":"K\u00fcng Martin Arch Dipl-Ing",
    "wof:placetype":"venue"
},
  "geometry": {"coordinates":[15.4513149261,47.069519043],"type":"Point"}
}