{
  "type": "Feature",
  "properties": {
    "iso:country":"AT",
    "sg:address":"Wienerbergstr. 3",
    "sg:city":"Wien",
    "sg:classifiers":[
        {
            "category":"Food & Beverages",
            "subcategory":"Groceries & Convenience Stores",
            "type":"Retail Goods"
        }
    ],
    "sg:phone":"+43 4316 05150",
    "sg:postcode":"1100",
    "sg:province":"Wien",
    "sg:tags":[
        "product",
        "related"
    ],
    "wof:name":"RWA RAIFFEISEN WARE AUSTRIA AG",
    "wof:placetype":"venue"
},
  "geometry": {"coordinates":[16.3476791382,48.1690788269],"type":"Point"}
}