{
  "type": "Feature",
  "properties": {
    "iso:country":"AT",
    "sg:address":"Leutschacher Str 21",
    "sg:city":"Klagenfurt",
    "sg:orig_category":"Transportunternehmen",
    "sg:phone":"+43 463 516342",
    "sg:postcode":"9020",
    "sg:province":"K\u00e4rnten",
    "wof:name":"Bautrans GesmbH",
    "wof:placetype":"venue"
},
  "geometry": {"coordinates":[14.3341007233,46.6226158142],"type":"Point"}
}