{
  "type": "Feature",
  "properties": {
    "addr:full":"Siemensstr 3 Wien Wien 1210",
    "addr:housenumber":"3",
    "addr:postcode":"1210",
    "addr:street":"Siemensstr",
    "iso:country":"AT",
    "sg:address":"Siemensstr 3",
    "sg:city":"Wien",
    "sg:orig_category":"Friseure U Frisiersalons",
    "sg:phone":"+43 4312 925943",
    "sg:postcode":"1210",
    "sg:province":"Wien",
    "wof:name":"Schramm Franz",
    "wof:placetype":"venue"
},
  "geometry": {"coordinates":[16.4092636108,48.2763671875],"type":"Point"}
}