{
  "type": "Feature",
  "properties": {
    "addr:full":"Mertensstr 9 Salzburg Salzburg 5020",
    "addr:housenumber":"9",
    "addr:postcode":"5020",
    "addr:street":"Mertensstr;Salzburg",
    "iso:country":"AT",
    "sg:address":"Mertensstr 9",
    "sg:city":"Salzburg",
    "sg:orig_category":"Marketingberatung",
    "sg:phone":"+43 662 876435",
    "sg:postcode":"5020",
    "sg:province":"Salzburg",
    "wof:name":"SICON -Siller Consulting GmbH",
    "wof:placetype":"venue"
},
  "geometry": {"coordinates":[13.0399103165,47.8120040894],"type":"Point"}
}