{
  "type": "Feature",
  "properties": {
    "addr:full":"Mitterfeldstr. 7 Traun Ober\u00f6sterreich 4050",
    "addr:housenumber":"7",
    "addr:postcode":"4050",
    "addr:street":"Mitterfeldstr.",
    "iso:country":"AT",
    "sg:address":"Mitterfeldstr. 7",
    "sg:city":"Traun",
    "sg:classifiers":[
        {
            "category":"Banks & Credit Unions",
            "subcategory":"Financial Services",
            "type":"Services"
        }
    ],
    "sg:phone":"+43 4372 2961224",
    "sg:postcode":"4050",
    "sg:province":"Ober\u00f6sterreich",
    "sg:tags":[
        "banking",
        "finance",
        "insurance"
    ],
    "wof:name":"UNIQA VERSICHERUNGEN AG",
    "wof:placetype":"venue"
},
  "geometry": {"coordinates":[14.2340803146,48.2261428833],"type":"Point"}
}