{
  "type": "Feature",
  "properties": {
    "addr:full":"Karl Frisch-G 10 Graz Steiermark 8020",
    "addr:housenumber":"10",
    "addr:postcode":"8020",
    "iso:country":"AT",
    "sg:address":"Karl Frisch-G 10",
    "sg:city":"Graz",
    "sg:classifiers":[
        {
            "category":"Taxi",
            "type":"Transportation"
        }
    ],
    "sg:phone":"+43 699 19480200",
    "sg:postcode":"8020",
    "sg:province":"Steiermark",
    "sg:tags":[
        "personentransporte",
        "u"
    ],
    "wof:name":"Gaber Mohamed Taxi OEG",
    "wof:placetype":"venue"
},
  "geometry": {"coordinates":[15.3981952667,47.0646705627],"type":"Point"}
}