{
  "type": "Feature",
  "properties": {
    "iso:country":"AT",
    "sg:address":"Taubenbrunn 29",
    "sg:city":"Eferding",
    "sg:classifiers":[
        {
            "category":"Shopping",
            "subcategory":"Party Supplies",
            "type":"Retail Goods"
        }
    ],
    "sg:phone":"+43 664 4500045",
    "sg:postcode":"4070",
    "sg:province":"Ober\u00f6sterreich",
    "sg:tags":[
        "u",
        "lichtanlagen",
        "ton-"
    ],
    "wof:name":"MVO Licht & Tontechnik",
    "wof:placetype":"venue"
},
  "geometry": {"coordinates":[14.0234451294,48.3086395264],"type":"Point"}
}