{
  "type": "Feature",
  "properties": {
    "addr:full":"Gaisbergstr 37a/Top 1 B Salzburg Salzburg 5020",
    "addr:housenumber":"37a / top 1 b",
    "addr:postcode":"5020",
    "addr:street":"Gaisbergstr;Salzburg",
    "iso:country":"AT",
    "sg:address":"Gaisbergstr 37a/Top 1 B",
    "sg:city":"Salzburg",
    "sg:orig_category":"Garten- U Landschaftsgestaltung",
    "sg:phone":"+43 4367 65198515",
    "sg:postcode":"5020",
    "sg:province":"Salzburg",
    "wof:name":"Germann Thomas - Gartengestaltung u spez Schwimmteichbau",
    "wof:placetype":"venue"
},
  "geometry": {"coordinates":[13.0433769226,47.8006744385],"type":"Point"}
}