{
  "type": "Feature",
  "properties": {
    "iso:country":"AT",
    "sg:address":"Johann Landauer-Str 2",
    "sg:city":"Tattendorf",
    "sg:classifiers":[
        {
            "category":"Landmark",
            "subcategory":"Square",
            "type":"Public Place"
        }
    ],
    "sg:phone":"+43 2253 81284",
    "sg:postcode":"2523",
    "sg:province":"Nieder\u00f6sterreich",
    "sg:tags":[
        "geometer"
    ],
    "wof:name":"Geometerb\u00fcro Hochmayer",
    "wof:placetype":"venue"
},
  "geometry": {"coordinates":[16.2984638214,47.9544868469],"type":"Point"}
}