{
  "type": "Feature",
  "properties": {
    "iso:country":"AT",
    "sg:address":"Stahlm\u00fchle 3-4",
    "sg:city":"Haslach an der M\u00fchl",
    "sg:classifiers":[
        {
            "category":"Shopping",
            "subcategory":"Crafts & Fabrics",
            "type":"Retail Goods"
        }
    ],
    "sg:phone":"+43 4372 8972180",
    "sg:postcode":"4170",
    "sg:province":"Ober\u00f6sterreich",
    "wof:name":"ALOM TEXTILWERKSTATT HASLACH",
    "wof:placetype":"venue"
},
  "geometry": {"coordinates":[14.0414199829,48.5752792358],"type":"Point"}
}