{
  "type": "Feature",
  "properties": {
    "iso:country":"AT",
    "sg:address":"Wallnerstr 2",
    "sg:city":"Wien",
    "sg:classifiers":[
        {
            "category":"Professional",
            "subcategory":"Management & Consulting",
            "type":"Services"
        }
    ],
    "sg:phone":"+43 1 91933",
    "sg:postcode":"1010",
    "sg:province":"Wien",
    "wof:name":"DMS Decision Management Systems Entwicklung v Informationssystemen GesmbH",
    "wof:placetype":"venue"
},
  "geometry": {"coordinates":[16.3676891327,48.2092437744],"type":"Point"}
}