{
  "type": "Feature",
  "properties": {
    "iso:country":"AT",
    "sg:address":"Nr 4",
    "sg:city":"Rennweg",
    "sg:orig_category":"Stra\u00c3\u0178enbau",
    "sg:phone":"+43 4347 343750",
    "sg:postcode":"9863",
    "sg:province":"K\u00e4rnten",
    "wof:name":"\u00d6sterreichische Autobahnen- u Schnellstra\u00dfen AG",
    "wof:placetype":"venue"
},
  "geometry": {"coordinates":[13.6127004623,47.0169067383],"type":"Point"}
}