{
  "type": "Feature",
  "properties": {
    "addr:full":"Nr 8 Berwang Tirol 6622",
    "addr:postcode":"6622",
    "addr:street":"Nr;Berwang Tirol",
    "iso:country":"AT",
    "sg:address":"Nr 8",
    "sg:city":"Berwang",
    "sg:orig_category":"Non-Classified Establishments",
    "sg:phone":"+43 5674 8127",
    "sg:postcode":"6622",
    "sg:province":"Tirol",
    "wof:name":"Pfarramt",
    "wof:placetype":"venue"
},
  "geometry": {"coordinates":[10.7468204498,47.4090003967],"type":"Point"}
}