{
  "type": "Feature",
  "properties": {
    "addr:full":"Stadtpl 35 Laa an der Thaya Nieder\u00f6sterreich 2136",
    "addr:housenumber":"35",
    "addr:postcode":"2136",
    "addr:street":"Stadtpl",
    "iso:country":"AT",
    "sg:address":"Stadtpl 35",
    "sg:city":"Laa an der Thaya",
    "sg:orig_category":"Fotografen",
    "sg:phone":"+43 2522 8988",
    "sg:postcode":"2136",
    "sg:province":"Nieder\u00f6sterreich",
    "wof:name":"Fotostudio Karin Bergermayer",
    "wof:placetype":"venue"
},
  "geometry": {"coordinates":[16.3854408264,48.7216758728],"type":"Point"}
}