{
  "type": "Feature",
  "properties": {
    "iso:country":"AT",
    "sg:address":"Amthorstrasse 10",
    "sg:city":"Innsbruck",
    "sg:orig_category":"Non-Classified Establishments",
    "sg:phone":"+43 512 341370",
    "sg:postcode":"6020",
    "sg:province":"Tirol",
    "sg:website":"alpha2000.at/metzgerei-erhart/index.htm",
    "wof:name":"Erhart Fleisch- und Wurst GmbH",
    "wof:placetype":"venue"
},
  "geometry": {"coordinates":[11.4102249146,47.2663116455],"type":"Point"}
}