{
  "type": "Feature",
  "properties": {
    "addr:full":"Otto-Weber-G 1/18 Wien Wien 1220",
    "addr:housenumber":"1 / 18",
    "addr:postcode":"1220",
    "addr:street":"Otto-Weber-G",
    "iso:country":"AT",
    "sg:address":"Otto-Weber-G 1/18",
    "sg:city":"Wien",
    "sg:orig_category":"Dachdeckereien",
    "sg:phone":"+43 4312 835465",
    "sg:postcode":"1220",
    "sg:province":"Wien",
    "wof:name":"B.D.S. Inh Karl Gulyas",
    "wof:placetype":"venue"
},
  "geometry": {"coordinates":[16.4571666718,48.2063369751],"type":"Point"}
}