{
  "type": "Feature",
  "properties": {
    "addr:full":"Schie\u00dfstattstr 69 Salzburg Salzburg 5020",
    "addr:housenumber":"69",
    "addr:postcode":"5020",
    "addr:street":"Schiessstattstr;Salzburg",
    "iso:country":"AT",
    "sg:address":"Schie\u00dfstattstr 69",
    "sg:city":"Salzburg",
    "sg:orig_category":"Elektroinstallationsunternehmen",
    "sg:phone":"+43 662 4330680",
    "sg:postcode":"5020",
    "sg:province":"Salzburg",
    "wof:name":"R\u00f6mer Stefan Elektrounternehmen GesmbH",
    "wof:placetype":"venue"
},
  "geometry": {"coordinates":[13.0306100845,47.8194580078],"type":"Point"}
}