{
  "type": "Feature",
  "properties": {
    "addr:full":"Hauptpl 43 Schladming Steiermark 8970",
    "addr:housenumber":"43",
    "addr:postcode":"8970",
    "addr:street":"Hauptpl",
    "iso:country":"AT",
    "sg:address":"Hauptpl 43",
    "sg:city":"Schladming",
    "sg:orig_category":"Juweliere, Gold- U Silberschmiede",
    "sg:phone":"+43 4336 87226370",
    "sg:postcode":"8970",
    "sg:province":"Steiermark",
    "wof:name":"Angerer Anneliese",
    "wof:placetype":"venue"
},
  "geometry": {"coordinates":[13.6884126663,47.3915138245],"type":"Point"}
}