{
  "type": "Feature",
  "properties": {
    "addr:full":"Ernst-Gruber-Str 1 Wimpassing im Schwarzatale Nieder\u00f6sterreich 2632",
    "addr:housenumber":"1",
    "addr:postcode":"2632",
    "addr:street":"Ernst-Gruber-Str",
    "iso:country":"AT",
    "sg:address":"Ernst-Gruber-Str 1",
    "sg:city":"Wimpassing im Schwarzatale",
    "sg:orig_category":"Gemeinden",
    "sg:phone":"+43 4326 30372160",
    "sg:postcode":"2632",
    "sg:province":"Nieder\u00f6sterreich",
    "wof:name":"Gemeinde Grafenbach-St Valentin",
    "wof:placetype":"venue"
},
  "geometry": {"coordinates":[16.0059928894,47.6837997437],"type":"Point"}
}