{
  "type": "Feature",
  "properties": {
    "addr:full":"Burgg 15 Klagenfurt K\u00e4rnten 9020",
    "addr:housenumber":"15",
    "addr:postcode":"9020",
    "addr:street":"Burgg;Kaernten",
    "iso:country":"AT",
    "sg:address":"Burgg 15",
    "sg:city":"Klagenfurt",
    "sg:orig_category":"Telefonmarketing",
    "sg:phone":"+43 4346 3502244",
    "sg:postcode":"9020",
    "sg:province":"K\u00e4rnten",
    "wof:name":"Jann Tele-Connect Telefon Marketing KEG",
    "wof:placetype":"venue"
},
  "geometry": {"coordinates":[14.3101921082,46.624458313],"type":"Point"}
}