{
  "type": "Feature",
  "properties": {
    "addr:full":"Hernalser Hauptstr 164 Wien Wien 1170",
    "addr:housenumber":"164",
    "addr:postcode":"1170",
    "addr:street":"Hernalser Hauptstr",
    "iso:country":"AT",
    "sg:address":"Hernalser Hauptstr 164",
    "sg:city":"Wien",
    "sg:orig_category":"Juweliere, Gold- U Silberschmiede",
    "sg:phone":"+43 1 4853327",
    "sg:postcode":"1170",
    "sg:province":"Wien",
    "wof:name":"Eckel Peter KG",
    "wof:placetype":"venue"
},
  "geometry": {"coordinates":[16.3178672791,48.2230491638],"type":"Point"}
}