{
  "type": "Feature",
  "properties": {
    "addr:full":"J\u00e4gerteichstr 3 Waidhofen an der Thaya Nieder\u00f6sterreich 3830",
    "addr:housenumber":"3",
    "addr:postcode":"3830",
    "addr:street":"Jaegerteichstr",
    "iso:country":"AT",
    "sg:address":"J\u00e4gerteichstr 3",
    "sg:city":"Waidhofen an der Thaya",
    "sg:orig_category":"Autohandel",
    "sg:phone":"+43 4328 42533450",
    "sg:postcode":"3830",
    "sg:province":"Nieder\u00f6sterreich",
    "wof:name":"Altschach Klaus",
    "wof:placetype":"venue"
},
  "geometry": {"coordinates":[15.2680130005,48.81275177],"type":"Point"}
}