{
  "type": "Feature",
  "properties": {
    "addr:full":"Ambergpark Reichsstr 126 Feldkirch Vorarlberg 6800",
    "addr:housenumber":"126",
    "addr:postcode":"6800",
    "iso:country":"AT",
    "sg:address":"Ambergpark Reichsstr 126",
    "sg:city":"Feldkirch",
    "sg:orig_category":"Bauleitung U -Betreuung",
    "sg:phone":"+43 4355 2281882",
    "sg:postcode":"6800",
    "sg:province":"Vorarlberg",
    "sg:website":"bauleitung-martin.at",
    "wof:name":"Bauleitung Martin & Partner",
    "wof:placetype":"venue"
},
  "geometry": {"coordinates":[9.5967845917,47.2381515503],"type":"Point"}
}