{
  "type": "Feature",
  "properties": {
    "addr:full":"Nr 7 Wolfsberg K\u00e4rnten 9400",
    "addr:housenumber":"kaernten",
    "addr:postcode":"9400",
    "addr:street":"Nr;Wolfsberg",
    "iso:country":"AT",
    "sg:address":"Nr 7",
    "sg:city":"Wolfsberg",
    "sg:orig_category":"Holzgro\u00c3\u0178handel",
    "sg:phone":"+43 4352 27310",
    "sg:postcode":"9400",
    "sg:province":"K\u00e4rnten",
    "wof:name":"Offner Johann Holzindustrie GesmbH",
    "wof:placetype":"venue"
},
  "geometry": {"coordinates":[14.8418502808,46.8402099609],"type":"Point"}
}