{
  "type": "Feature",
  "properties": {
    "addr:full":"Favoritenstr 115 Wien Wien 1100",
    "addr:housenumber":"115",
    "addr:postcode":"1100",
    "iso:country":"AT",
    "sg:address":"Favoritenstr 115",
    "sg:city":"Wien",
    "sg:orig_category":"Juweliere, Gold- U Silberschmiede",
    "sg:phone":"+43 4316 022357",
    "sg:postcode":"1100",
    "sg:province":"Wien",
    "wof:name":"Thurzo E GesmbH",
    "wof:placetype":"venue"
},
  "geometry": {"coordinates":[16.3780708313,48.1750335693],"type":"Point"}
}