{
  "type": "Feature",
  "properties": {
    "addr:full":"Hetzendorfer Str 130 Wien Wien 1120",
    "addr:housenumber":"130",
    "addr:postcode":"1120",
    "addr:street":"Str",
    "iso:country":"AT",
    "sg:address":"Hetzendorfer Str 130",
    "sg:city":"Wien",
    "sg:orig_category":"Farben U Lacke / Einzelhandel",
    "sg:phone":"+43 1 8042657",
    "sg:postcode":"1120",
    "sg:province":"Wien",
    "sg:website":"www.ruhser.at",
    "wof:name":"Ruhser Josef - Inh Stitzle - ADLER Farbenmeister",
    "wof:placetype":"venue"
},
  "geometry": {"coordinates":[16.3027896881,48.1688766479],"type":"Point"}
}