{
  "type": "Feature",
  "properties": {
    "addr:full":"Kircheng 25 Maria Enzersdorf Nieder\u00f6sterreich 2344",
    "addr:housenumber":"25",
    "addr:postcode":"2344",
    "addr:street":"Kircheng",
    "iso:country":"AT",
    "sg:address":"Kircheng 25",
    "sg:city":"Maria Enzersdorf",
    "sg:orig_category":"Massagen",
    "sg:phone":"+43 2236 864200",
    "sg:postcode":"2344",
    "sg:province":"Nieder\u00f6sterreich",
    "wof:name":"ENERGIEQUELLE ROSWITHA REINER",
    "wof:placetype":"venue"
},
  "geometry": {"coordinates":[16.2813606262,48.1011924744],"type":"Point"}
}