{
  "type": "Feature",
  "properties": {
    "iso:country":"AT",
    "sg:address":"Am Weiher 5/6",
    "sg:city":"Wolfsberg",
    "sg:orig_category":"Bezirkshauptmannschaften",
    "sg:phone":"+43 5 053666000",
    "sg:postcode":"9400",
    "sg:province":"K\u00e4rnten",
    "wof:name":"Bezirkshauptmannschaft Wolfsberg",
    "wof:placetype":"venue"
},
  "geometry": {"coordinates":[14.8406677246,46.8407745361],"type":"Point"}
}