{
  "type": "Feature",
  "properties": {
    "iso:country":"AT",
    "sg:address":"Oberau 81",
    "sg:city":"Wildsch\u00f6nau-Oberau",
    "sg:orig_category":"Pensionen / Privatzimmer",
    "sg:phone":"+43 5339 8406",
    "sg:postcode":"6311",
    "sg:province":"Tirol",
    "wof:name":"Pension Hochland",
    "wof:placetype":"venue"
},
  "geometry": {"coordinates":[12.049654007,47.4430465698],"type":"Point"}
}