{
  "type": "Feature",
  "properties": {
    "addr:full":"Gezing 11 Seekirchen am Wallersee Salzburg 5201",
    "addr:housenumber":"11",
    "addr:postcode":"5201",
    "addr:street":"Gezing;Salzburg",
    "iso:country":"AT",
    "sg:address":"Gezing 11",
    "sg:city":"Seekirchen am Wallersee",
    "sg:orig_category":"Feng-Shui",
    "sg:phone":"+43 4362 126258",
    "sg:postcode":"5201",
    "sg:province":"Salzburg",
    "wof:name":"Feng Shui Olzinger Helmut u Gertraud",
    "wof:placetype":"venue"
},
  "geometry": {"coordinates":[13.1300058365,47.9174156189],"type":"Point"}
}