{
  "type": "Feature",
  "properties": {
    "addr:full":"Nr 4 Stallhofen Steiermark 8152",
    "addr:postcode":"8152",
    "addr:street":"Nr",
    "iso:country":"AT",
    "sg:address":"Nr 4",
    "sg:city":"Stallhofen",
    "sg:orig_category":"Staubsauger",
    "sg:phone":"+43 4331 42209190",
    "sg:postcode":"8152",
    "sg:province":"Steiermark",
    "wof:name":"R\u00f6ssler & Puff OEG",
    "wof:placetype":"venue"
},
  "geometry": {"coordinates":[15.2755184174,47.0200767517],"type":"Point"}
}