{
  "type": "Feature",
  "properties": {
    "addr:full":"Hauptstr 32 Payerbach Nieder\u00f6sterreich 2650",
    "addr:housenumber":"32",
    "addr:postcode":"2650",
    "addr:street":"Hauptstr",
    "iso:country":"AT",
    "sg:address":"Hauptstr 32",
    "sg:city":"Payerbach",
    "sg:orig_category":"Friseure U Frisiersalons",
    "sg:phone":"+43 4326 6653906",
    "sg:postcode":"2650",
    "sg:province":"Nieder\u00f6sterreich",
    "wof:name":"Hofmann Erik",
    "wof:placetype":"venue"
},
  "geometry": {"coordinates":[15.8577070236,47.6925354004],"type":"Point"}
}