{
  "type": "Feature",
  "properties": {
    "addr:full":"Wiesenweg 9 Zirl Tirol 6170",
    "addr:housenumber":"9",
    "addr:postcode":"6170",
    "addr:street":"Wiesenweg;Tirol",
    "iso:country":"AT",
    "sg:address":"Wiesenweg 9",
    "sg:city":"Zirl",
    "sg:classifiers":[
        {
            "category":"Professional",
            "subcategory":"Computer Services",
            "type":"Services"
        }
    ],
    "sg:phone":"+43 4367 64237432",
    "sg:postcode":"6170",
    "sg:province":"Tirol",
    "sg:tags":[
        "software"
    ],
    "wof:name":"Setup EDV-Dienstleistungen",
    "wof:placetype":"venue"
},
  "geometry": {"coordinates":[11.2411756516,47.2684173584],"type":"Point"}
}