{
  "type": "Feature",
  "properties": {
    "addr:full":"Fischerndorf 117 Altaussee Steiermark 8992",
    "addr:housenumber":"117",
    "addr:postcode":"8992",
    "addr:street":"Fischerndorf",
    "iso:country":"AT",
    "sg:address":"Fischerndorf 117",
    "sg:city":"Altaussee",
    "sg:orig_category":"Banken U Sparkassen",
    "sg:phone":"+43 4350 10036217",
    "sg:postcode":"8992",
    "sg:province":"Steiermark",
    "wof:name":"Steierm\u00e4rkische Bank u Sparkassen AG",
    "wof:placetype":"venue"
},
  "geometry": {"coordinates":[13.7710046768,47.6415290833],"type":"Point"}
}