{
  "type": "Feature",
  "properties": {
    "addr:full":"Nr 109 Mieming Tirol 6414",
    "addr:postcode":"6414",
    "addr:street":"Nr 109;Tirol",
    "iso:country":"AT",
    "sg:address":"Nr 109",
    "sg:city":"Mieming",
    "sg:orig_category":"Innenarchitekten",
    "sg:phone":"+43 5264 5820",
    "sg:postcode":"6414",
    "sg:province":"Tirol",
    "wof:name":"Kastl Markus",
    "wof:placetype":"venue"
},
  "geometry": {"coordinates":[11.0065221786,47.3184700012],"type":"Point"}
}