{
  "type": "Feature",
  "properties": {
    "iso:country":"AT",
    "sg:address":"Nr 44",
    "sg:city":"Au",
    "sg:orig_category":"Lebensmittel / Einzelhandel",
    "sg:phone":"+43 3863 2275",
    "sg:postcode":"8624",
    "sg:province":"Steiermark",
    "wof:name":"Leodolter Ingrid",
    "wof:placetype":"venue"
},
  "geometry": {"coordinates":[166.9221496582,-0.5282999873],"type":"Point"}
}