{
  "type": "Feature",
  "properties": {
    "addr:full":"Goldschlagstr 51 Wien Wien 1150",
    "addr:housenumber":"51",
    "addr:postcode":"1150",
    "addr:street":"Goldschlagstr",
    "iso:country":"AT",
    "sg:address":"Goldschlagstr 51",
    "sg:city":"Wien",
    "sg:classifiers":[
        {
            "category":"Internet Cafe",
            "subcategory":"None",
            "type":"Food & Drink"
        }
    ],
    "sg:phone":"+43 4319 905851",
    "sg:postcode":"1150",
    "sg:province":"Wien",
    "wof:name":"plus Internetservice GmbH",
    "wof:placetype":"venue"
},
  "geometry": {"coordinates":[16.327381134,48.1965026855],"type":"Point"}
}