{
  "type": "Feature",
  "properties": {
    "addr:full":"Landgutg 39 Wien Wien 1100",
    "addr:housenumber":"39",
    "addr:postcode":"1100",
    "addr:street":"Landgutg",
    "iso:country":"AT",
    "sg:address":"Landgutg 39",
    "sg:city":"Wien",
    "sg:orig_category":"Tauchsportschulen U -Vereine",
    "sg:phone":"+43 1 6036197",
    "sg:postcode":"1100",
    "sg:province":"Wien",
    "wof:name":"Tauchschule Underwater College",
    "wof:placetype":"venue"
},
  "geometry": {"coordinates":[16.3716602325,48.1812362671],"type":"Point"}
}