{
  "type": "Feature",
  "properties": {
    "addr:full":"Falkenweg Hard Vorarlberg 6971",
    "addr:postcode":"6971",
    "addr:street":"Falkenweg",
    "iso:country":"AT",
    "sg:address":"Falkenweg",
    "sg:city":"Hard",
    "sg:orig_category":"Rettungsdienste",
    "sg:phone":"+43 5574 76330",
    "sg:postcode":"6971",
    "sg:province":"Vorarlberg",
    "wof:name":"Rotes Kreuz Hard",
    "wof:placetype":"venue"
},
  "geometry": {"coordinates":[9.6855726242,47.4788284302],"type":"Point"}
}