{
  "type": "Feature",
  "properties": {
    "iso:country":"AT",
    "sg:address":"Theresieng. 3",
    "sg:city":"Wien",
    "sg:classifiers":[
        {
            "category":"Utilities",
            "subcategory":"Telephone",
            "type":"Services"
        }
    ],
    "sg:phone":"+43 4314 0386210",
    "sg:postcode":"1180",
    "sg:province":"Wien",
    "sg:tags":[
        "telecommunication"
    ],
    "wof:name":"TRANSELEKTRONIK ME\u00dfGER\u00c4TE W. FRIEDRICH OHG",
    "wof:placetype":"venue"
},
  "geometry": {"coordinates":[16.3403816223,48.2178649902],"type":"Point"}
}