{
  "type": "Feature",
  "properties": {
    "addr:full":"Bahnhofstr 12 Feldkirch Vorarlberg 6800",
    "addr:postcode":"6800",
    "addr:street":"Bahnhofstr 12",
    "iso:country":"AT",
    "sg:address":"Bahnhofstr 12",
    "sg:city":"Feldkirch",
    "sg:orig_category":"Unternehmensberatung",
    "sg:phone":"+43 5522 79229",
    "sg:postcode":"6800",
    "sg:province":"Vorarlberg",
    "wof:name":"Coordinator HandelsgesmbH",
    "wof:placetype":"venue"
},
  "geometry": {"coordinates":[9.6016159058,47.2409820557],"type":"Point"}
}