{
  "type": "Feature",
  "properties": {
    "iso:country":"AT",
    "sg:address":"Nr 32",
    "sg:city":"K\u00f6tschach-Mauthen",
    "sg:orig_category":"Fleischhauereien",
    "sg:phone":"+43 4715 20909",
    "sg:postcode":"9640",
    "sg:province":"K\u00e4rnten",
    "wof:name":"Salcher Markus",
    "wof:placetype":"venue"
},
  "geometry": {"coordinates":[12.9984302521,46.6670227051],"type":"Point"}
}