{
  "type": "Feature",
  "properties": {
    "addr:full":"Lainzer Str 14 Wien Wien 1130",
    "addr:postcode":"1130",
    "addr:street":"Str 14",
    "iso:country":"AT",
    "sg:address":"Lainzer Str 14",
    "sg:city":"Wien",
    "sg:orig_category":"Tankstellen",
    "sg:phone":"+43 1 8772572",
    "sg:postcode":"1130",
    "sg:province":"Wien",
    "wof:name":"Shell Austria GmbH",
    "wof:placetype":"venue"
},
  "geometry": {"coordinates":[16.296289444,48.1855278015],"type":"Point"}
}