{
  "type": "Feature",
  "properties": {
    "addr:full":"Raimundstrasse 46 Linz Ober\u00f6sterreich 4020",
    "addr:housenumber":"46",
    "addr:postcode":"4020",
    "addr:street":"Raimundstrasse",
    "iso:country":"AT",
    "sg:address":"Raimundstrasse 46",
    "sg:city":"Linz",
    "sg:classifiers":[
        {
            "category":"Autos & Motor Vehicles",
            "subcategory":"Fuel & Gas Station",
            "type":"Retail Goods"
        }
    ],
    "sg:phone":"+43 732 6511230",
    "sg:postcode":"4020",
    "sg:province":"Ober\u00f6sterreich",
    "sg:tags":[
        "cutting",
        "autogenic",
        "devices",
        "welding"
    ],
    "sg:website":"krakowitzer.at",
    "wof:name":"KRAKOWITZER techn. Gase u. Schwei\u00dfger\u00e4te Ges.m.b.H.",
    "wof:placetype":"venue"
},
  "geometry": {"coordinates":[14.3095149994,48.2907867432],"type":"Point"}
}