{
  "type": "Feature",
  "properties": {
    "addr:full":"Nr 140 Bad Waltersdorf Steiermark 8271",
    "addr:postcode":"8271",
    "addr:street":"Nr",
    "iso:country":"AT",
    "sg:address":"Nr 140",
    "sg:city":"Bad Waltersdorf",
    "sg:orig_category":"Appartements / Ferienwohnungen",
    "sg:phone":"+43 3333 22680",
    "sg:postcode":"8271",
    "sg:province":"Steiermark",
    "wof:name":"G\u00e4stehaus Erika - Ing Gamperl Erika",
    "wof:placetype":"venue"
},
  "geometry": {"coordinates":[16.0086784363,47.1696166992],"type":"Point"}
}