{
  "type": "Feature",
  "properties": {
    "addr:full":"Rosentaler Str 5 Velden am W\u00f6rther See K\u00e4rnten 9220",
    "addr:housenumber":"5",
    "addr:postcode":"9220",
    "addr:street":"Str;Kaernten",
    "iso:country":"AT",
    "sg:address":"Rosentaler Str 5",
    "sg:city":"Velden am W\u00f6rther See",
    "sg:orig_category":"Friseure U Frisiersalons",
    "sg:phone":"+43 4342 7450201",
    "sg:postcode":"9220",
    "sg:province":"K\u00e4rnten",
    "wof:name":"DANIELA natural hair",
    "wof:placetype":"venue"
},
  "geometry": {"coordinates":[14.041475296,46.6127090454],"type":"Point"}
}