{
  "type": "Feature",
  "properties": {
    "addr:full":"Hauptpl 21 Wiener Neustadt Nieder\u00f6sterreich 2700",
    "addr:housenumber":"21",
    "addr:postcode":"2700",
    "addr:street":"Hauptpl",
    "iso:country":"AT",
    "sg:address":"Hauptpl 21",
    "sg:city":"Wiener Neustadt",
    "sg:orig_category":"Apotheken",
    "sg:phone":"+43 2622 23153",
    "sg:postcode":"2700",
    "sg:province":"Nieder\u00f6sterreich",
    "wof:name":"Apotheke Zur Mariahilf",
    "wof:placetype":"venue"
},
  "geometry": {"coordinates":[16.2450675964,47.8131561279],"type":"Point"}
}