{
  "type": "Feature",
  "properties": {
    "addr:full":"Kreitnerg 10/18 Wien Wien 1160",
    "addr:housenumber":"10 / 18",
    "addr:postcode":"1160",
    "addr:street":"Kreitnerg",
    "iso:country":"AT",
    "sg:address":"Kreitnerg 10/18",
    "sg:city":"Wien",
    "sg:classifiers":[
        {
            "category":"Home & Garden",
            "subcategory":"Building Materials",
            "type":"Retail Goods"
        }
    ],
    "sg:phone":"+43 4317 868944",
    "sg:postcode":"1160",
    "sg:province":"Wien",
    "sg:tags":[
        "baustoffe",
        "-material",
        "u"
    ],
    "wof:name":"Reckli-Chemiestoff GmbH",
    "wof:placetype":"venue"
},
  "geometry": {"coordinates":[16.3229236603,48.2066040039],"type":"Point"}
}