{
  "type": "Feature",
  "properties": {
    "addr:full":"Neilreichg 78 Wien Wien 1100",
    "addr:housenumber":"78",
    "addr:postcode":"1100",
    "addr:street":"Neilreichg",
    "iso:country":"AT",
    "sg:address":"Neilreichg 78",
    "sg:city":"Wien",
    "sg:orig_category":"Altwaren",
    "sg:phone":"+43 1 6071818",
    "sg:postcode":"1100",
    "sg:province":"Wien",
    "wof:name":"Altwaren Heindl",
    "wof:placetype":"venue"
},
  "geometry": {"coordinates":[16.3640079498,48.1688156128],"type":"Point"}
}