{
  "type": "Feature",
  "properties": {
    "addr:full":"Obere Landstr 7 Krems an der Donau Nieder\u00f6sterreich 3500",
    "addr:housenumber":"7",
    "addr:postcode":"3500",
    "addr:street":"Obere Landstr",
    "iso:country":"AT",
    "sg:address":"Obere Landstr 7",
    "sg:city":"Krems an der Donau",
    "sg:orig_category":"Damenmoden",
    "sg:phone":"+43 4327 32735460",
    "sg:postcode":"3500",
    "sg:province":"Nieder\u00f6sterreich",
    "wof:name":"Kaufstrasse Helmut Pemsel GesmbH",
    "wof:placetype":"venue"
},
  "geometry": {"coordinates":[15.5993471146,48.4108047485],"type":"Point"}
}