{
  "type": "Feature",
  "properties": {
    "addr:full":"Nr 98 Lavam\u00fcnd K\u00e4rnten 9473",
    "addr:postcode":"9473",
    "addr:street":"Nr 98 Lavamuend Kaernten",
    "iso:country":"AT",
    "sg:address":"Nr 98",
    "sg:city":"Lavam\u00fcnd",
    "sg:orig_category":"Feuerwehren",
    "sg:phone":"+43 4356 2370",
    "sg:postcode":"9473",
    "sg:province":"K\u00e4rnten",
    "wof:name":"Feuerwehr Lavam\u00fcnd",
    "wof:placetype":"venue"
},
  "geometry": {"coordinates":[166.9221496582,-0.5282999873],"type":"Point"}
}