{
  "type": "Feature",
  "properties": {
    "addr:full":"Wagingerstr 2 Salzburg Salzburg 5020",
    "addr:housenumber":"2",
    "addr:postcode":"5020",
    "addr:street":"Wagingerstr;Salzburg",
    "iso:country":"AT",
    "sg:address":"Wagingerstr 2",
    "sg:city":"Salzburg",
    "sg:orig_category":"Strick- U Wirkwaren / Einzelhandel",
    "sg:phone":"+43 4366 2430473",
    "sg:postcode":"5020",
    "sg:province":"Salzburg",
    "wof:name":"Lana Strickmoden KEG - Dworschak Helmut",
    "wof:placetype":"venue"
},
  "geometry": {"coordinates":[13.0216579437,47.8214912415],"type":"Point"}
}