{
  "type": "Feature",
  "properties": {
    "addr:full":"Nr 5 Hohenwarth Nieder\u00f6sterreich 3472",
    "addr:postcode":"3472",
    "addr:street":"Nr;Hohenwarth Niederoesterreich",
    "iso:country":"AT",
    "sg:address":"Nr 5",
    "sg:city":"Hohenwarth",
    "sg:orig_category":"Non-Classified Establishments",
    "sg:phone":"+43 2957 302",
    "sg:postcode":"3472",
    "sg:province":"Nieder\u00f6sterreich",
    "wof:name":"Pfarramt",
    "wof:placetype":"venue"
},
  "geometry": {"coordinates":[15.827583313,48.5075111389],"type":"Point"}
}