{
  "type": "Feature",
  "properties": {
    "iso:country":"AT",
    "sg:address":"Rohrm\u00fchlg 5",
    "sg:city":"Mistelbach",
    "sg:orig_category":"Nachhilfe U Lernbetreuung",
    "sg:phone":"+43 4325 724375",
    "sg:postcode":"2130",
    "sg:province":"Nieder\u00f6sterreich",
    "wof:name":"Reschl Brigitte - Legasthenikerbetreuerin",
    "wof:placetype":"venue"
},
  "geometry": {"coordinates":[16.5724334717,48.5700798035],"type":"Point"}
}