{
  "type": "Feature",
  "properties": {
    "addr:full":"Kirchengasse 10  Ried im Innkreis Ober\u00f6sterreich 4910",
    "addr:housenumber":"10",
    "addr:postcode":"4910",
    "addr:street":"Kirchengasse",
    "iso:country":"AT",
    "sg:address":"Kirchengasse 10 ",
    "sg:city":"Ried im Innkreis",
    "sg:classifiers":[
        {
            "category":"Building & Trades",
            "subcategory":"Equipment Rental",
            "type":"Services"
        }
    ],
    "sg:phone":"+43 7752 828710",
    "sg:postcode":"4910",
    "sg:province":"Ober\u00f6sterreich",
    "sg:tags":[
        "registers",
        "register",
        "system",
        "cash"
    ],
    "sg:website":"www.zeilinger-ried.at",
    "wof:name":"Zeilinger B\u00fcrobedarf Ges.m.b.H.",
    "wof:placetype":"venue"
},
  "geometry": {"coordinates":[13.4882240295,48.2091026306],"type":"Point"}
}