{
  "type": "Feature",
  "properties": {
    "iso:country":"AT",
    "sg:address":"Laudong 18",
    "sg:city":"Wien",
    "sg:orig_category":"Architekten",
    "sg:phone":"+43 4319 294058",
    "sg:postcode":"1080",
    "sg:province":"Wien",
    "wof:name":"noncon:form - Gruber Gulle Nageler Ohrhallinger OEG",
    "wof:placetype":"venue"
},
  "geometry": {"coordinates":[16.3504333496,48.2134513855],"type":"Point"}
}