{
  "type": "Feature",
  "properties": {
    "addr:full":"Kinostr 4 Bischofshofen Salzburg 5500",
    "addr:housenumber":"4",
    "addr:postcode":"5500",
    "addr:street":"Kinostr;Salzburg",
    "iso:country":"AT",
    "sg:address":"Kinostr 4",
    "sg:city":"Bischofshofen",
    "sg:orig_category":"Rettungsdienste",
    "sg:phone":"+43 4366 49251702",
    "sg:postcode":"5500",
    "sg:province":"Salzburg",
    "wof:name":"Wasser-Rettung Herbert Gewolf",
    "wof:placetype":"venue"
},
  "geometry": {"coordinates":[13.216301918,47.4191017151],"type":"Point"}
}