{
  "type": "Feature",
  "properties": {
    "addr:full":"M\u00e4rzstr 140 Wien Wien 1140",
    "addr:housenumber":"140",
    "addr:postcode":"1140",
    "iso:country":"AT",
    "sg:address":"M\u00e4rzstr 140",
    "sg:city":"Wien",
    "sg:orig_category":"Abbruchunternehmen",
    "sg:phone":"+43 4369 910665880",
    "sg:postcode":"1140",
    "sg:province":"Wien",
    "wof:name":"Duran & Tuncel GmbH",
    "wof:placetype":"venue"
},
  "geometry": {"coordinates":[16.2696990967,48.1994247437],"type":"Point"}
}