{
  "type": "Feature",
  "properties": {
    "iso:country":"AT",
    "sg:address":"Anton-Regner-Strasse 11",
    "sg:city":"Knittelfeld",
    "sg:classifiers":[
        {
            "category":"Food & Beverages",
            "subcategory":"Cheese",
            "type":"Retail Goods"
        }
    ],
    "sg:phone":"+43 3512 861000",
    "sg:postcode":"8720",
    "sg:province":"Steiermark",
    "sg:website":"oml.at",
    "wof:name":"Obersteirische Molkerei reg.Gen.m.b.H.",
    "wof:placetype":"venue"
},
  "geometry": {"coordinates":[14.8230342865,47.2164115906],"type":"Point"}
}