{
  "type": "Feature",
  "properties": {
    "addr:full":"Eichenstr. 6  Marchtrenk Ober\u00f6sterreich 4614",
    "addr:housenumber":"6",
    "addr:postcode":"4614",
    "addr:street":"Eichenstr.",
    "iso:country":"AT",
    "sg:address":"Eichenstr. 6 ",
    "sg:city":"Marchtrenk",
    "sg:classifiers":[
        {
            "category":"Communications",
            "subcategory":"Television Station",
            "type":"Services"
        }
    ],
    "sg:phone":"+43 4372 43553",
    "sg:postcode":"4614",
    "sg:province":"Ober\u00f6sterreich",
    "sg:tags":[
        "equipment",
        "optical",
        "instrument"
    ],
    "wof:name":"WIPF - AUSTRIA GES.MBH & CO",
    "wof:placetype":"venue"
},
  "geometry": {"coordinates":[14.1176290512,48.1930503845],"type":"Point"}
}