{
  "type": "Feature",
  "properties": {
    "iso:country":"AT",
    "sg:address":"Nr 141",
    "sg:city":"Fuschl am See",
    "sg:orig_category":"Tankstellen",
    "sg:phone":"+43 6226 8269",
    "sg:postcode":"5330",
    "sg:province":"Salzburg",
    "wof:name":"BP Austria Marketing GmbH",
    "wof:placetype":"venue"
},
  "geometry": {"coordinates":[13.3025903702,47.7964363098],"type":"Point"}
}