{
  "type": "Feature",
  "properties": {
    "iso:country":"AT",
    "sg:address":"Steinbruch 124",
    "sg:city":"Bad Ischl",
    "sg:orig_category":"Autoersatzteile",
    "sg:phone":"+43 6132 254510",
    "sg:postcode":"4820",
    "sg:province":"Ober\u00f6sterreich",
    "wof:name":"Exmanco Inh Ahammer Peter",
    "wof:placetype":"venue"
},
  "geometry": {"coordinates":[13.6257123947,47.711971283],"type":"Point"}
}