{
  "type": "Feature",
  "properties": {
    "addr:full":"Wolfgangsee Bundesstr 1 St. Gilgen Salzburg 5340",
    "addr:housenumber":"1",
    "addr:postcode":"5340",
    "addr:street":"Bundesstr",
    "iso:country":"AT",
    "sg:address":"Wolfgangsee Bundesstr 1",
    "sg:city":"St. Gilgen",
    "sg:orig_category":"Lebensmittel / Einzelhandel",
    "sg:phone":"+43 4362 2720415",
    "sg:postcode":"5340",
    "sg:province":"Salzburg",
    "wof:name":"Billa AG",
    "wof:placetype":"venue"
},
  "geometry": {"coordinates":[13.3596963882,47.7693328857],"type":"Point"}
}