{
  "type": "Feature",
  "properties": {
    "addr:full":"Unterdorf 2 Zell am Ziller Tirol 6280",
    "addr:housenumber":"2",
    "addr:postcode":"6280",
    "addr:street":"Unterdorf;Tirol",
    "iso:country":"AT",
    "sg:address":"Unterdorf 2",
    "sg:city":"Zell am Ziller",
    "sg:orig_category":"Gemeinden",
    "sg:phone":"+43 5282 22220",
    "sg:postcode":"6280",
    "sg:province":"Tirol",
    "wof:name":"Marktgemeindeamt Zell a Ziller",
    "wof:placetype":"venue"
},
  "geometry": {"coordinates":[11.880563736,47.2336845398],"type":"Point"}
}