{
  "type": "Feature",
  "properties": {
    "addr:full":"Hans v d Sann-Str 23 Eisenerz Steiermark 8790",
    "addr:housenumber":"23",
    "addr:postcode":"8790",
    "addr:street":"Hans V;Sann-Str",
    "iso:country":"AT",
    "sg:address":"Hans v d Sann-Str 23",
    "sg:city":"Eisenerz",
    "sg:orig_category":"\u00c3\u201erzte / F Allgemeinmedizin",
    "sg:phone":"+43 3848 22830",
    "sg:postcode":"8790",
    "sg:province":"Steiermark",
    "wof:name":"Bauer Hannes Dr",
    "wof:placetype":"venue"
},
  "geometry": {"coordinates":[14.8870744705,47.5428543091],"type":"Point"}
}