{
  "type": "Feature",
  "properties": {
    "iso:country":"AT",
    "sg:address":"Maria T Zechner-Str 3",
    "sg:city":"Hallein",
    "sg:orig_category":"Non-Classified Establishments",
    "sg:phone":"+43 6245 802870",
    "sg:postcode":"5400",
    "sg:province":"Salzburg",
    "wof:name":"Pfarramt",
    "wof:placetype":"venue"
},
  "geometry": {"coordinates":[13.0920543671,47.6804542542],"type":"Point"}
}