{
  "type": "Feature",
  "properties": {
    "addr:full":"Salurner Str 12 Innsbruck Tirol 6020",
    "addr:postcode":"6020",
    "addr:street":"Str 12;Tirol",
    "iso:country":"AT",
    "sg:address":"Salurner Str 12",
    "sg:city":"Innsbruck",
    "sg:classifiers":[
        {
            "category":"Restaurant",
            "type":"Food & Drink"
        }
    ],
    "sg:phone":"+43 512 938098",
    "sg:postcode":"6020",
    "sg:province":"Tirol",
    "wof:name":"Ita Egidio Dipl-Restaurator f Fresken und Bilder",
    "wof:placetype":"venue"
},
  "geometry": {"coordinates":[11.3974189758,47.2630577087],"type":"Point"}
}