{
  "type": "Feature",
  "properties": {
    "addr:full":"Prater 11 Wien Wien 1020",
    "addr:housenumber":"11",
    "addr:postcode":"1020",
    "addr:street":"Prater",
    "iso:country":"AT",
    "sg:address":"Prater 11",
    "sg:city":"Wien",
    "sg:classifiers":[
        {
            "category":"Restaurant",
            "type":"Food & Drink"
        }
    ],
    "sg:phone":"+43 1 7294785",
    "sg:postcode":"1020",
    "sg:province":"Wien",
    "wof:name":"Restaurant Wieselburger Bierinsel",
    "wof:placetype":"venue"
},
  "geometry": {"coordinates":[16.3811988831,48.2132301331],"type":"Point"}
}