{
  "type": "Feature",
  "properties": {
    "addr:full":"Kremser Str 41 Kirchberg am Wagram Nieder\u00f6sterreich 3470",
    "addr:housenumber":"41",
    "addr:postcode":"3470",
    "addr:street":"Str",
    "iso:country":"AT",
    "sg:address":"Kremser Str 41",
    "sg:city":"Kirchberg am Wagram",
    "sg:orig_category":"Friseure U Frisiersalons",
    "sg:phone":"+43 4322 792356",
    "sg:postcode":"3470",
    "sg:province":"Nieder\u00f6sterreich",
    "wof:name":"Le Figaro Inh Renate Seitner",
    "wof:placetype":"venue"
},
  "geometry": {"coordinates":[15.8948497772,48.4330368042],"type":"Point"}
}