{
  "type": "Feature",
  "properties": {
    "addr:full":"Wiener Str 85 Langenwang Steiermark 8665",
    "addr:postcode":"8665",
    "iso:country":"AT",
    "sg:address":"Wiener Str 85",
    "sg:city":"Langenwang",
    "sg:orig_category":"Decken- U Wandverkleidungen",
    "sg:phone":"+43 3854 2808",
    "sg:postcode":"8665",
    "sg:province":"Steiermark",
    "wof:name":"ERO Holzelemente GmbH",
    "wof:placetype":"venue"
},
  "geometry": {"coordinates":[15.6359891891,47.574508667],"type":"Point"}
}