{
  "type": "Feature",
  "properties": {
    "iso:country":"AT",
    "sg:address":"Lederergasse 67",
    "sg:city":"Linz",
    "sg:classifiers":[
        {
            "category":"Manufacturing",
            "subcategory":"Wood Products",
            "type":"Manufacturing & Wholesale Goods"
        }
    ],
    "sg:phone":"+43 732 7848110",
    "sg:postcode":"4020",
    "sg:province":"Ober\u00f6sterreich",
    "sg:tags":[
        "case"
    ],
    "sg:website":"spedpack.at",
    "wof:name":"SPEDPACK Speditions- und Verpackungsges.m.b.H.",
    "wof:placetype":"venue"
},
  "geometry": {"coordinates":[14.3055238724,48.312538147],"type":"Point"}
}