{
  "type": "Feature",
  "properties": {
    "iso:country":"AT",
    "sg:address":"Am Katzelbach 138",
    "sg:city":"Stra\u00dfgang",
    "sg:orig_category":"Psychologen",
    "sg:phone":"+43 316 285790",
    "sg:postcode":"8054",
    "sg:province":"Steiermark",
    "wof:name":"Novak-Rymarz Michaela Dr",
    "wof:placetype":"venue"
},
  "geometry": {"coordinates":[15.3827381134,47.0270881653],"type":"Point"}
}