{
  "type": "Feature",
  "properties": {
    "addr:full":"Marieng 6 Pinkafeld Burgenland 7423",
    "addr:housenumber":"6",
    "addr:postcode":"7423",
    "addr:street":"Marieng",
    "iso:country":"AT",
    "sg:address":"Marieng 6",
    "sg:city":"Pinkafeld",
    "sg:orig_category":"Fenster",
    "sg:phone":"+43 3357 42997",
    "sg:postcode":"7423",
    "sg:province":"Burgenland",
    "wof:name":"Putz Karl",
    "wof:placetype":"venue"
},
  "geometry": {"coordinates":[16.1243686676,47.3699989319],"type":"Point"}
}