{
  "type": "Feature",
  "properties": {
    "addr:full":"Eibergstr 2-8 Kufstein Tirol 6330",
    "addr:housenumber":"2-8",
    "addr:postcode":"6330",
    "addr:street":"Eibergstr;Tirol",
    "iso:country":"AT",
    "sg:address":"Eibergstr 2-8",
    "sg:city":"Kufstein",
    "sg:orig_category":"Maschinenbau",
    "sg:phone":"+43 5372 64893",
    "sg:postcode":"6330",
    "sg:province":"Tirol",
    "wof:name":"Zimmer J Maschinenbau GesmbH",
    "wof:placetype":"venue"
},
  "geometry": {"coordinates":[12.1573476791,47.5707969666],"type":"Point"}
}