{
  "type": "Feature",
  "properties": {
    "iso:country":"AT",
    "sg:address":"Wolf Huber-Str 12",
    "sg:city":"Feldkirch",
    "sg:orig_category":"Drogerien",
    "sg:phone":"+43 5522 83565",
    "sg:postcode":"6800",
    "sg:province":"Vorarlberg",
    "wof:name":"Drogerie Breu\u00df",
    "wof:placetype":"venue"
},
  "geometry": {"coordinates":[9.5849704742,47.2308502197],"type":"Point"}
}