{
  "type": "Feature",
  "properties": {
    "addr:full":"Pframastr 12 Haringsee Nieder\u00f6sterreich 2286",
    "addr:housenumber":"12",
    "addr:postcode":"2286",
    "addr:street":"Pframastr",
    "iso:country":"AT",
    "sg:address":"Pframastr 12",
    "sg:city":"Haringsee",
    "sg:orig_category":"Unternehmensberatung",
    "sg:phone":"+43 2214 48051",
    "sg:postcode":"2286",
    "sg:province":"Nieder\u00f6sterreich",
    "wof:name":"AS - Consult GmbH",
    "wof:placetype":"venue"
},
  "geometry": {"coordinates":[16.7865657806,48.1908607483],"type":"Point"}
}