{
  "type": "Feature",
  "properties": {
    "iso:country":"AT",
    "sg:address":"B\u00f6hmerwaldstrasse 15 ",
    "sg:city":"Altenfelden",
    "sg:classifiers":[
        {
            "category":"Building & Trades",
            "subcategory":"Plumbing",
            "type":"Services"
        }
    ],
    "sg:phone":"+43 7282 5556",
    "sg:postcode":"4121",
    "sg:province":"Ober\u00f6sterreich",
    "sg:tags":[
        "supraregional",
        "gas"
    ],
    "sg:website":"www.leibetseder.com",
    "wof:name":"Leibetseder Gas-Wasser-Heizung GmbH & Co KG",
    "wof:placetype":"venue"
},
  "geometry": {"coordinates":[13.9678344727,48.4877662659],"type":"Point"}
}