{
  "type": "Feature",
  "properties": {
    "iso:country":"AT",
    "sg:address":"Nr 46",
    "sg:city":"Antiesenhofen",
    "sg:orig_category":"Bohrunternehmen",
    "sg:phone":"+43 4377 5955630",
    "sg:postcode":"4980",
    "sg:province":"Ober\u00f6sterreich",
    "wof:name":"Braumann Bohr- u Brunnenbau GmbH",
    "wof:placetype":"venue"
},
  "geometry": {"coordinates":[5.9138097763,50.3553504944],"type":"Point"}
}