{
  "type": "Feature",
  "properties": {
    "addr:full":"Sch\u00f6nbrunner Allee 66 Wien Wien 1120",
    "addr:housenumber":"66",
    "addr:postcode":"1120",
    "addr:street":"Schoenbrunner Allee",
    "iso:country":"AT",
    "sg:address":"Sch\u00f6nbrunner Allee 66",
    "sg:city":"Wien",
    "sg:orig_category":"Architekten",
    "sg:phone":"+43 1 80269380",
    "sg:postcode":"1120",
    "sg:province":"Wien",
    "wof:name":"Smutny Georg Dipl-Ing",
    "wof:placetype":"venue"
},
  "geometry": {"coordinates":[16.3091087341,48.1677513123],"type":"Point"}
}