{
  "type": "Feature",
  "properties": {
    "addr:full":"Mistelbacher Str 17 Ernstbrunn Nieder\u00f6sterreich 2115",
    "addr:postcode":"2115",
    "addr:street":"Str 17",
    "iso:country":"AT",
    "sg:address":"Mistelbacher Str 17",
    "sg:city":"Ernstbrunn",
    "sg:orig_category":"Rettungsdienste",
    "sg:phone":"+43 2576 22440",
    "sg:postcode":"2115",
    "sg:province":"Nieder\u00f6sterreich",
    "wof:name":"Rotes Kreuz \u00f6sterr Ortsstelle Ernstbrunn",
    "wof:placetype":"venue"
},
  "geometry": {"coordinates":[16.3669319153,48.5276603699],"type":"Point"}
}