{
  "type": "Feature",
  "properties": {
    "addr:full":"Schenkelbachweg 19 Wels Ober\u00f6sterreich 4600",
    "addr:housenumber":"19",
    "addr:postcode":"4600",
    "addr:street":"Schenkelbachweg;Oberoesterreich",
    "iso:country":"AT",
    "sg:address":"Schenkelbachweg 19",
    "sg:city":"Wels",
    "sg:orig_category":"Geologie",
    "sg:phone":"+43 4372 4277164",
    "sg:postcode":"4600",
    "sg:province":"Ober\u00f6sterreich",
    "wof:name":"Sordian Hans Ing Dr - Technisches B\u00fcro f angewandte u theoretische Geologie",
    "wof:placetype":"venue"
},
  "geometry": {"coordinates":[14.0415267944,48.1589012146],"type":"Point"}
}