{
  "type": "Feature",
  "properties": {
    "addr:full":"Wiener Str 48 Brunn am Gebirge Nieder\u00f6sterreich 2345",
    "addr:postcode":"2345",
    "addr:street":"48",
    "iso:country":"AT",
    "sg:address":"Wiener Str 48",
    "sg:city":"Brunn am Gebirge",
    "sg:orig_category":"Autohandel",
    "sg:phone":"+43 4322 3632389",
    "sg:postcode":"2345",
    "sg:province":"Nieder\u00f6sterreich",
    "wof:name":"Reindl Franz - Daihatsu",
    "wof:placetype":"venue"
},
  "geometry": {"coordinates":[16.2893218994,48.1090278625],"type":"Point"}
}