{
  "type": "Feature",
  "properties": {
    "addr:full":"8080",
    "addr:housenumber":"8080",
    "iso:country":"AT",
    "sg:orig_category":"Industrie, Fahrzeugbau",
    "sg:postcode":"8080",
    "sg:website":"http://www.8ung.at/eisenbahn",
    "wof:name":"PG",
    "wof:placetype":"venue"
},
  "geometry": {"coordinates":[16.3687992096,48.2025413513],"type":"Point"}
}