{
  "type": "Feature",
  "properties": {
    "addr:full":"Fasangarteng 36 Wien Wien 1130",
    "addr:housenumber":"36",
    "addr:postcode":"1130",
    "addr:street":"Fasangarteng",
    "iso:country":"AT",
    "sg:address":"Fasangarteng 36",
    "sg:city":"Wien",
    "sg:classifiers":[
        {
            "category":"Home & Garden",
            "subcategory":"Building Materials",
            "type":"Retail Goods"
        }
    ],
    "sg:phone":"+43 1 8048378",
    "sg:postcode":"1130",
    "sg:province":"Wien",
    "sg:tags":[
        "baustoffe",
        "-material",
        "u"
    ],
    "wof:name":"Zehetner Viktor und S\u00f6hne Baustoffgro\u00dfhandlung und Transportunternehmung GesmbH",
    "wof:placetype":"venue"
},
  "geometry": {"coordinates":[16.2885951996,48.173625946],"type":"Point"}
}