{
  "type": "Feature",
  "properties": {
    "addr:full":"Neufelden Ober\u00f6sterreich 4120",
    "addr:postcode":"4120",
    "iso:country":"AT",
    "sg:city":"Neufelden",
    "sg:orig_category":"Feuerwehren",
    "sg:phone":"+43 7282 5782",
    "sg:postcode":"4120",
    "sg:province":"Ober\u00f6sterreich",
    "wof:name":"Freiwillige Feuerwehr Neufelden",
    "wof:placetype":"venue"
},
  "geometry": {"coordinates":[13.9999198914,48.4844017029],"type":"Point"}
}