{
  "type": "Feature",
  "properties": {
    "addr:full":"Frojach 4 Frojach Steiermark 8841",
    "addr:housenumber":"4",
    "addr:postcode":"8841",
    "addr:street":"Frojach",
    "iso:country":"AT",
    "sg:address":"Frojach 4",
    "sg:city":"Frojach",
    "sg:orig_category":"Tankstellen",
    "sg:phone":"+43 3588 274",
    "sg:postcode":"8841",
    "sg:province":"Steiermark",
    "wof:name":"Shell Austria GmbH",
    "wof:placetype":"venue"
},
  "geometry": {"coordinates":[14.3013896942,47.1253128052],"type":"Point"}
}