{
  "type": "Feature",
  "properties": {
    "addr:full":"Gasteiger Str. 23 St. Johann in Tirol Tirol 6380",
    "addr:housenumber":"23",
    "addr:postcode":"6380",
    "addr:street":"Str.;Tirol",
    "iso:country":"AT",
    "sg:address":"Gasteiger Str. 23",
    "sg:city":"St. Johann in Tirol",
    "sg:classifiers":[
        {
            "category":"Utilities",
            "subcategory":"Electric",
            "type":"Services"
        }
    ],
    "sg:phone":"+43 4353 52623410",
    "sg:postcode":"6380",
    "sg:province":"Tirol",
    "sg:tags":[
        "electricity"
    ],
    "wof:name":"TIROLER WASSERKRAFTWERKE AG",
    "wof:placetype":"venue"
},
  "geometry": {"coordinates":[12.4269447327,47.5266227722],"type":"Point"}
}