{
  "type": "Feature",
  "properties": {
    "addr:full":"Badstr 24 Leonstein Ober\u00f6sterreich 4592",
    "addr:housenumber":"24",
    "addr:postcode":"4592",
    "addr:street":"Badstr",
    "iso:country":"AT",
    "sg:address":"Badstr 24",
    "sg:city":"Leonstein",
    "sg:orig_category":"Musikunterricht",
    "sg:phone":"+43 7584 27720",
    "sg:postcode":"4592",
    "sg:province":"Ober\u00f6sterreich",
    "wof:name":"Landesmusikschule",
    "wof:placetype":"venue"
},
  "geometry": {"coordinates":[14.2268810272,47.8959999084],"type":"Point"}
}