{
  "type": "Feature",
  "properties": {
    "addr:full":"Hauptstr 45A Trautmannsdorf an der Leitha Nieder\u00f6sterreich 2454",
    "addr:housenumber":"45a",
    "addr:postcode":"2454",
    "addr:street":"Hauptstr",
    "iso:country":"AT",
    "sg:address":"Hauptstr 45A",
    "sg:city":"Trautmannsdorf an der Leitha",
    "sg:orig_category":"Lebens- U Sozialberatung",
    "sg:phone":"+43 4321 698686",
    "sg:postcode":"2454",
    "sg:province":"Nieder\u00f6sterreich",
    "wof:name":"Nieder\u00f6sterreichische Lebens- u Suchtberatungsstelle",
    "wof:placetype":"venue"
},
  "geometry": {"coordinates":[16.6418590546,48.023235321],"type":"Point"}
}