{
  "type": "Feature",
  "properties": {
    "addr:full":"Alte Poststr 376 Puntigam Steiermark 8055",
    "addr:housenumber":"376",
    "addr:postcode":"8055",
    "iso:country":"AT",
    "sg:address":"Alte Poststr 376",
    "sg:city":"Puntigam",
    "sg:orig_category":"Speditionen",
    "sg:phone":"+43 316 2904260",
    "sg:postcode":"8055",
    "sg:province":"Steiermark",
    "wof:name":"EuroExpress Schnellieferdienst Gebr Weiss GmbH",
    "wof:placetype":"venue"
},
  "geometry": {"coordinates":[15.4243583679,47.042098999],"type":"Point"}
}