{
  "type": "Feature",
  "properties": {
    "iso:country":"AT",
    "sg:address":"Marktpl 19",
    "sg:city":"Neuhofen an der Krems",
    "sg:orig_category":"Tapezierer U Dekorateure",
    "sg:phone":"+43 4372 274325",
    "sg:postcode":"4501",
    "sg:province":"Ober\u00f6sterreich",
    "wof:name":"Packy Andreas",
    "wof:placetype":"venue"
},
  "geometry": {"coordinates":[14.2281103134,48.1378517151],"type":"Point"}
}