{
  "type": "Feature",
  "properties": {
    "iso:country":"AT",
    "sg:address":"Eduard-Klinger-Str. 21",
    "sg:city":"St. Andr\u00e4-W\u00f6rdern",
    "sg:classifiers":[
        {
            "category":"Professional",
            "subcategory":"Engineering",
            "type":"Services"
        }
    ],
    "sg:phone":"+43 4322 4231210",
    "sg:postcode":"3423",
    "sg:province":"Nieder\u00f6sterreich",
    "sg:tags":[
        "machine",
        "-",
        "mechanical"
    ],
    "wof:name":"EEP-MASCHINENBAU GMBH",
    "wof:placetype":"venue"
},
  "geometry": {"coordinates":[16.2101764679,48.3275222778],"type":"Point"}
}