{
  "type": "Feature",
  "properties": {
    "iso:country":"AT",
    "sg:address":"Oberfladnitz 74",
    "sg:city":"Weiz",
    "sg:classifiers":[
        {
            "category":"Structure",
            "subcategory":"Office Building",
            "type":"Public Place"
        }
    ],
    "sg:phone":"+43 3172 23960",
    "sg:postcode":"8160",
    "sg:province":"Steiermark",
    "sg:tags":[
        "engineering",
        "electrical"
    ],
    "sg:website":"sonnek.at",
    "wof:name":"Ing. Rudolf Sonnek Ges.m.b.H.",
    "wof:placetype":"venue"
},
  "geometry": {"coordinates":[15.6215696335,47.2169532776],"type":"Point"}
}