{
  "type": "Feature",
  "properties": {
    "addr:full":"Siegmairstr 3 Innsbruck Tirol 6020",
    "addr:housenumber":"3",
    "addr:postcode":"6020",
    "addr:street":"Siegmairstr;Tirol",
    "iso:country":"AT",
    "sg:address":"Siegmairstr 3",
    "sg:city":"Innsbruck",
    "sg:orig_category":"Polytechnische Schulen",
    "sg:phone":"+43 512 345235",
    "sg:postcode":"6020",
    "sg:province":"Tirol",
    "wof:name":"Polytechnische Schule Innsbruck",
    "wof:placetype":"venue"
},
  "geometry": {"coordinates":[11.4219903946,47.2636566162],"type":"Point"}
}