{
  "type": "Feature",
  "properties": {
    "addr:full":"Hanriederstr 20 Lembach im M\u00fchlkreis Ober\u00f6sterreich 4132",
    "addr:housenumber":"20",
    "addr:postcode":"4132",
    "addr:street":"Hanriederstr;Im Muehlkreis Oberoesterreich",
    "iso:country":"AT",
    "sg:address":"Hanriederstr 20",
    "sg:city":"Lembach im M\u00fchlkreis",
    "sg:orig_category":"Rauchfangkehrer",
    "sg:phone":"+43 7286 8114",
    "sg:postcode":"4132",
    "sg:province":"Ober\u00f6sterreich",
    "wof:name":"Hauer Veronika",
    "wof:placetype":"venue"
},
  "geometry": {"coordinates":[13.8922433853,48.4972610474],"type":"Point"}
}