{
  "type": "Feature",
  "properties": {
    "addr:full":"Edenlehen 676 Mayrhofen Tirol 6290",
    "addr:housenumber":"676",
    "addr:postcode":"6290",
    "addr:street":"Edenlehen;Tirol",
    "iso:country":"AT",
    "sg:address":"Edenlehen 676",
    "sg:city":"Mayrhofen",
    "sg:orig_category":"Pensionen / Privatzimmer",
    "sg:phone":"+43 5285 62300",
    "sg:postcode":"6290",
    "sg:province":"Tirol",
    "wof:name":"Hotel-Pension Edenlehen",
    "wof:placetype":"venue"
},
  "geometry": {"coordinates":[11.8537044525,47.1622810364],"type":"Point"}
}