{
  "type": "Feature",
  "properties": {
    "addr:full":"Lebachstr 1 Hof Salzburg 5322",
    "addr:housenumber":"1",
    "addr:postcode":"5322",
    "addr:street":"Lebachstr;Salzburg",
    "iso:country":"AT",
    "sg:address":"Lebachstr 1",
    "sg:city":"Hof",
    "sg:orig_category":"Abschleppdienste",
    "sg:phone":"+43 6229 27190",
    "sg:postcode":"5322",
    "sg:province":"Salzburg",
    "wof:name":"Lindner Wolfgang GesmbH",
    "wof:placetype":"venue"
},
  "geometry": {"coordinates":[13.2142972946,47.8186302185],"type":"Point"}
}