{
  "type": "Feature",
  "properties": {
    "addr:full":"Heinrich-von-Buol-Gasse 5  Wien Wien 1210",
    "addr:housenumber":"5",
    "addr:postcode":"1210",
    "addr:street":"Heinrich-Von-Buol-Gasse",
    "iso:country":"AT",
    "sg:address":"Heinrich-von-Buol-Gasse 5 ",
    "sg:city":"Wien",
    "sg:classifiers":[
        {
            "category":"Government",
            "subcategory":"Fire Station",
            "type":"Public Place"
        }
    ],
    "sg:phone":"+43 517 070",
    "sg:postcode":"1210",
    "sg:province":"Wien",
    "sg:tags":[
        "protection",
        "safety",
        "cable"
    ],
    "wof:name":"Austria-Kabel-Export-Ges.m.b.H.",
    "wof:placetype":"venue"
},
  "geometry": {"coordinates":[16.4259109497,48.2653083801],"type":"Point"}
}