{
  "type": "Feature",
  "properties": {
    "addr:full":"Aspettenstr 30/11 Perchtoldsdorf Nieder\u00f6sterreich 2380",
    "addr:housenumber":"30 / 11",
    "addr:postcode":"2380",
    "addr:street":"Aspettenstr",
    "iso:country":"AT",
    "sg:address":"Aspettenstr 30/11",
    "sg:city":"Perchtoldsdorf",
    "sg:orig_category":"Gerichtsdolmetscher",
    "sg:phone":"+43 1 8654407",
    "sg:postcode":"2380",
    "sg:province":"Nieder\u00f6sterreich",
    "wof:name":"Soukup-Unterweger Irmgard Mag",
    "wof:placetype":"venue"
},
  "geometry": {"coordinates":[16.2837982178,48.1281852722],"type":"Point"}
}