{
  "type": "Feature",
  "properties": {
    "addr:full":"Nr 112 Taufkirchen an der Trattnach Ober\u00f6sterreich 4715",
    "addr:postcode":"4715",
    "addr:street":"Nr 112",
    "iso:country":"AT",
    "sg:address":"Nr 112",
    "sg:city":"Taufkirchen an der Trattnach",
    "sg:orig_category":"Besonderes",
    "sg:phone":"+43 4366 44732787",
    "sg:postcode":"4715",
    "sg:province":"Ober\u00f6sterreich",
    "sg:website":"zwaier.com",
    "wof:name":"Die Eventbeleber - TEATRO BANAL",
    "wof:placetype":"venue"
},
  "geometry": {"coordinates":[13.7491598129,48.2472038269],"type":"Point"}
}