{
  "type": "Feature",
  "properties": {
    "addr:full":"Nr 117 Rangersdorf K\u00e4rnten 9833",
    "addr:housenumber":"9833",
    "addr:street":"Nr",
    "iso:country":"AT",
    "sg:address":"Nr 117",
    "sg:city":"Rangersdorf",
    "sg:orig_category":"Tischlereien",
    "sg:phone":"+43 4822 72110",
    "sg:postcode":"9833",
    "sg:province":"K\u00e4rnten",
    "wof:name":"Suntinger und Wallner GmbH",
    "wof:placetype":"venue"
},
  "geometry": {"coordinates":[12.9637470245,46.8620872498],"type":"Point"}
}