{
  "type": "Feature",
  "properties": {
    "addr:full":"Paradeisgasse 11 Judenburg Steiermark 8750",
    "addr:housenumber":"11",
    "addr:postcode":"8750",
    "addr:street":"Paradeisgasse",
    "iso:country":"AT",
    "sg:address":"Paradeisgasse 11",
    "sg:city":"Judenburg",
    "sg:classifiers":[
        {
            "category":"Communications",
            "subcategory":"Film & Video Production",
            "type":"Services"
        }
    ],
    "sg:phone":"+43 3572 82489",
    "sg:postcode":"8750",
    "sg:province":"Steiermark",
    "sg:tags":[
        "stove",
        "tiled",
        "accessory"
    ],
    "wof:name":"Erich Kociper",
    "wof:placetype":"venue"
},
  "geometry": {"coordinates":[14.665266037,47.1701087952],"type":"Point"}
}