{
  "type": "Feature",
  "properties": {
    "iso:country":"AT",
    "sg:address":"Laxenburger Strasse 218",
    "sg:city":"Wien",
    "sg:classifiers":[
        {
            "category":"Health Services",
            "subcategory":"Optometrist",
            "type":"Services"
        }
    ],
    "sg:phone":"+43 1 88831120",
    "sg:postcode":"1230",
    "sg:province":"Wien",
    "sg:tags":[
        "prosthesis",
        "breast"
    ],
    "sg:website":"aduschek.at",
    "wof:name":"A. Duschek GmbH",
    "wof:placetype":"venue"
},
  "geometry": {"coordinates":[16.3600845337,48.1428527832],"type":"Point"}
}