{
  "type": "Feature",
  "properties": {
    "addr:full":"Rabensteig 8/3a Wien Wien 1010",
    "addr:housenumber":"8 / 3a",
    "addr:postcode":"1010",
    "addr:street":"Rabensteig",
    "iso:country":"AT",
    "sg:address":"Rabensteig 8/3a",
    "sg:city":"Wien",
    "sg:orig_category":"Forschungsinstitute",
    "sg:phone":"+43 1 404006537",
    "sg:postcode":"1010",
    "sg:province":"Wien",
    "wof:name":"FIBREX Medical Research & Development GmbH",
    "wof:placetype":"venue"
},
  "geometry": {"coordinates":[16.3754653931,48.2119216919],"type":"Point"}
}