{
  "type": "Feature",
  "properties": {
    "addr:full":"Schaunbergerstr 64 Linz Ober\u00f6sterreich 4020",
    "addr:housenumber":"64",
    "addr:postcode":"4020",
    "addr:street":"Schaunbergerstr",
    "iso:country":"AT",
    "sg:address":"Schaunbergerstr 64",
    "sg:city":"Linz",
    "sg:orig_category":"Psychotherapie",
    "sg:phone":"+43 732 670056",
    "sg:postcode":"4020",
    "sg:province":"Ober\u00f6sterreich",
    "wof:name":"Ecker Helmuth Dr",
    "wof:placetype":"venue"
},
  "geometry": {"coordinates":[14.2789611816,48.2708969116],"type":"Point"}
}