{
  "type": "Feature",
  "properties": {
    "addr:full":"Seeh\u00e4userweg 49 Ossiach K\u00e4rnten 9570",
    "addr:housenumber":"49",
    "addr:postcode":"9570",
    "addr:street":"Seehaeuserweg;Kaernten",
    "iso:country":"AT",
    "sg:address":"Seeh\u00e4userweg 49",
    "sg:city":"Ossiach",
    "sg:orig_category":"Appartements / Ferienwohnungen",
    "sg:phone":"+43 4342 42289022",
    "sg:postcode":"9570",
    "sg:province":"K\u00e4rnten",
    "wof:name":"Seehaus Schmidt",
    "wof:placetype":"venue"
},
  "geometry": {"coordinates":[13.9840993881,46.6746025085],"type":"Point"}
}