{
  "type": "Feature",
  "properties": {
    "addr:full":"Reichsstr 11 Stra\u00df in Steiermark Steiermark 8472",
    "addr:housenumber":"11",
    "addr:postcode":"8472",
    "addr:street":"Reichsstr",
    "iso:country":"AT",
    "sg:address":"Reichsstr 11",
    "sg:city":"Stra\u00df in Steiermark",
    "sg:orig_category":"Freizeit- U Sportbekleidung",
    "sg:phone":"+43 4334 534242",
    "sg:postcode":"8472",
    "sg:province":"Steiermark",
    "wof:name":"Carre Sportmode",
    "wof:placetype":"venue"
},
  "geometry": {"coordinates":[15.6132335663,46.7316474915],"type":"Point"}
}