{
  "type": "Feature",
  "properties": {
    "addr:full":"Nr 100 W\u00f6rth an der Lafnitz Steiermark 8293",
    "addr:postcode":"8293",
    "addr:street":"Nr 100 Woerth An Der Lafnitz Steiermark",
    "iso:country":"AT",
    "sg:address":"Nr 100",
    "sg:city":"W\u00f6rth an der Lafnitz",
    "sg:orig_category":"Gemeinden",
    "sg:phone":"+43 3358 29400",
    "sg:postcode":"8293",
    "sg:province":"Steiermark",
    "wof:name":"Gemeinde W\u00f6rterberg",
    "wof:placetype":"venue"
},
  "geometry": {"coordinates":[166.9221496582,-0.5282999873],"type":"Point"}
}