{
  "type": "Feature",
  "properties": {
    "iso:country":"AT",
    "sg:address":"Rudolfstr 48",
    "sg:city":"Linz",
    "sg:orig_category":"Tapezierer U Dekorateure",
    "sg:phone":"+43 732 731236",
    "sg:postcode":"4040",
    "sg:province":"Ober\u00f6sterreich",
    "wof:name":"Wolkerstorfer Heinrich",
    "wof:placetype":"venue"
},
  "geometry": {"coordinates":[14.2778339386,48.3095664978],"type":"Point"}
}