{
  "type": "Feature",
  "properties": {
    "iso:country":"AT",
    "sg:address":"Naarntalstrasse 14",
    "sg:city":"Perg",
    "sg:classifiers":[
        {
            "category":"Home & Garden",
            "subcategory":"Carpets & Floor Coverings",
            "type":"Retail Goods"
        }
    ],
    "sg:phone":"+43 7262 52511",
    "sg:postcode":"4320",
    "sg:province":"Ober\u00f6sterreich",
    "sg:website":"www.zeitlhofer.at",
    "wof:name":"Heinrich Zeitlhofer",
    "wof:placetype":"venue"
},
  "geometry": {"coordinates":[14.6393699646,48.2500610352],"type":"Point"}
}