{
  "type": "Feature",
  "properties": {
    "addr:full":"Burggasse 123 Wien Wien 1070",
    "addr:housenumber":"123",
    "addr:postcode":"1070",
    "addr:street":"Burggasse",
    "iso:country":"AT",
    "sg:address":"Burggasse 123",
    "sg:city":"Wien",
    "sg:classifiers":[
        {
            "category":"Utilities",
            "subcategory":"Natural Gas",
            "type":"Services"
        }
    ],
    "sg:phone":"+43 1 5263960",
    "sg:postcode":"1070",
    "sg:province":"Wien",
    "sg:tags":[
        "heater",
        "electric"
    ],
    "wof:name":"Gerhard Novak Ges.m.b.H.",
    "wof:placetype":"venue"
},
  "geometry": {"coordinates":[16.3378257751,48.2040710449],"type":"Point"}
}