{
  "type": "Feature",
  "properties": {
    "addr:full":"Zemannstr 28 Freistadt Ober\u00f6sterreich 4240",
    "addr:housenumber":"28",
    "addr:postcode":"4240",
    "addr:street":"Zemannstr",
    "iso:country":"AT",
    "sg:address":"Zemannstr 28",
    "sg:city":"Freistadt",
    "sg:orig_category":"Installationsunternehmen",
    "sg:phone":"+43 7942 744100",
    "sg:postcode":"4240",
    "sg:province":"Ober\u00f6sterreich",
    "wof:name":"Schaumberger Franz KG",
    "wof:placetype":"venue"
},
  "geometry": {"coordinates":[14.5034132004,48.506729126],"type":"Point"}
}