{
  "type": "Feature",
  "properties": {
    "iso:country":"AT",
    "sg:address":"Alte Reichsstr 17",
    "sg:city":"Wildon",
    "sg:orig_category":"Feuerwehren",
    "sg:phone":"+43 3182 2104",
    "sg:postcode":"8410",
    "sg:province":"Steiermark",
    "wof:name":"Freiwillige Feuerwehr Wildon",
    "wof:placetype":"venue"
},
  "geometry": {"coordinates":[15.5183792114,46.8812103271],"type":"Point"}
}