{
  "type": "Feature",
  "properties": {
    "addr:full":"Hauptstr 16 Wiesmath Nieder\u00f6sterreich 2811",
    "addr:housenumber":"16",
    "addr:postcode":"2811",
    "addr:street":"Hauptstr",
    "iso:country":"AT",
    "sg:address":"Hauptstr 16",
    "sg:city":"Wiesmath",
    "sg:orig_category":"Fleischhauereien",
    "sg:phone":"+43 2645 20068",
    "sg:postcode":"2811",
    "sg:province":"Nieder\u00f6sterreich",
    "wof:name":"Leitgeb Michaela",
    "wof:placetype":"venue"
},
  "geometry": {"coordinates":[16.2878227234,47.6167297363],"type":"Point"}
}