{
  "type": "Feature",
  "properties": {
    "addr:full":"Innsbrucker Str 90 St. Johann in Tirol Tirol 6380",
    "addr:housenumber":"90",
    "addr:postcode":"johann;6380",
    "addr:street":"Str;Tirol",
    "iso:country":"AT",
    "sg:address":"Innsbrucker Str 90",
    "sg:city":"St. Johann in Tirol",
    "sg:orig_category":"Tapezierer U Dekorateure",
    "sg:phone":"+43 4353 5261032",
    "sg:postcode":"6380",
    "sg:province":"Tirol",
    "wof:name":"Polsterm\u00f6belwerkstatt - Vorhangatelier Peter Siegl",
    "wof:placetype":"venue"
},
  "geometry": {"coordinates":[12.3956155777,47.5225524902],"type":"Point"}
}