{
  "type": "Feature",
  "properties": {
    "iso:country":"AT",
    "sg:address":"Roseggerstrasse 30",
    "sg:city":"Wels",
    "sg:classifiers":[
        {
            "category":"Bars & Pubs",
            "subcategory":"Nightclub",
            "type":"Food & Drink"
        }
    ],
    "sg:phone":"+43 7242 46675",
    "sg:postcode":"4600",
    "sg:province":"Ober\u00f6sterreich",
    "sg:tags":[
        "upright",
        "piano",
        "hammer",
        "grand"
    ],
    "wof:name":"Klavierhaus Kurt Wegner",
    "wof:placetype":"venue"
},
  "geometry": {"coordinates":[14.0268602371,48.1610717773],"type":"Point"}
}