{
  "type": "Feature",
  "properties": {
    "iso:country":"AT",
    "sg:address":"K\u00e4rntner Str 6",
    "sg:city":"St. Michael in Obersteiermark",
    "sg:orig_category":"Speditionen",
    "sg:phone":"+43 3843 40170",
    "sg:postcode":"8770",
    "sg:province":"Steiermark",
    "wof:name":"VIT-Verzollungs- Intrastat- Transportvermittlungs-GesmbH",
    "wof:placetype":"venue"
},
  "geometry": {"coordinates":[15.003112793,47.3671302795],"type":"Point"}
}