{
  "type": "Feature",
  "properties": {
    "addr:full":"Hauptstr 9 Gloggnitz Nieder\u00f6sterreich 2640",
    "addr:housenumber":"9",
    "addr:postcode":"2640",
    "addr:street":"Hauptstr",
    "iso:country":"AT",
    "sg:address":"Hauptstr 9",
    "sg:city":"Gloggnitz",
    "sg:orig_category":"Textilreinigung",
    "sg:phone":"+43 4369 910210967",
    "sg:postcode":"2640",
    "sg:province":"Nieder\u00f6sterreich",
    "wof:name":"G\u00e4rtner Elfriede",
    "wof:placetype":"venue"
},
  "geometry": {"coordinates":[15.9379253387,47.6758880615],"type":"Point"}
}