{
  "type": "Feature",
  "properties": {
    "addr:full":"Vorderer Sonnberg 66 Kirchberg in Tirol Tirol 6365",
    "addr:housenumber":"66",
    "addr:postcode":"6365",
    "addr:street":"Vorderer Sonnberg;Tirol",
    "iso:country":"AT",
    "sg:address":"Vorderer Sonnberg 66",
    "sg:city":"Kirchberg in Tirol",
    "sg:orig_category":"Pensionen / Privatzimmer",
    "sg:phone":"+43 5357 3429",
    "sg:postcode":"6365",
    "sg:province":"Tirol",
    "wof:name":"Ferienhof Stallh\u00e4usl",
    "wof:placetype":"venue"
},
  "geometry": {"coordinates":[12.3247375488,47.456615448],"type":"Point"}
}