{
  "type": "Feature",
  "properties": {
    "addr:full":"Schmiedstr 3 Molln Ober\u00f6sterreich 4591",
    "addr:housenumber":"3",
    "addr:postcode":"4591",
    "addr:street":"Schmiedstr",
    "iso:country":"AT",
    "sg:address":"Schmiedstr 3",
    "sg:city":"Molln",
    "sg:orig_category":"Bauunternehmen",
    "sg:phone":"+43 7584 2290",
    "sg:postcode":"4591",
    "sg:province":"Ober\u00f6sterreich",
    "wof:name":"Glinsner BaugesmbH & Co KG",
    "wof:placetype":"venue"
},
  "geometry": {"coordinates":[14.2628583908,47.8825721741],"type":"Point"}
}