{
  "type": "Feature",
  "properties": {
    "iso:country":"AT",
    "sg:address":"Sternwartestr 25",
    "sg:city":"Wien",
    "sg:orig_category":"Holzgro\u00c3\u0178handel",
    "sg:phone":"+43 1 47954680",
    "sg:postcode":"1180",
    "sg:province":"Wien",
    "wof:name":"Banyai Karl Holzgro\u00dfhandlung GesmbH",
    "wof:placetype":"venue"
},
  "geometry": {"coordinates":[16.3459281921,48.2296104431],"type":"Point"}
}