{
  "type": "Feature",
  "properties": {
    "iso:country":"AT",
    "sg:address":"Glan-Treppelweg 17",
    "sg:city":"Salzburg",
    "sg:classifiers":[
        {
            "category":"Professional",
            "subcategory":"Art Services",
            "type":"Services"
        }
    ],
    "sg:phone":"+43 662 823525",
    "sg:postcode":"5020",
    "sg:province":"Salzburg",
    "sg:tags":[
        "designer"
    ],
    "wof:name":"MD Design Rudolf K Meinhart",
    "wof:placetype":"venue"
},
  "geometry": {"coordinates":[13.0168504715,47.7836990356],"type":"Point"}
}