{
  "type": "Feature",
  "properties": {
    "addr:full":"Jasomirgottstr 5 Wien Wien 1010",
    "addr:housenumber":"5",
    "addr:postcode":"1010",
    "addr:street":"Jasomirgottstr",
    "iso:country":"AT",
    "sg:address":"Jasomirgottstr 5",
    "sg:city":"Wien",
    "sg:orig_category":"Immobilienverwaltungen",
    "sg:phone":"+43 1 53367220",
    "sg:postcode":"1010",
    "sg:province":"Wien",
    "wof:name":"Zeilner Rudolf Ing",
    "wof:placetype":"venue"
},
  "geometry": {"coordinates":[16.3715591431,48.2090644836],"type":"Point"}
}