{
  "type": "Feature",
  "properties": {
    "addr:full":"Erlachstrasse 23 Hard Vorarlberg 6971",
    "addr:housenumber":"23",
    "addr:postcode":"6971",
    "addr:street":"Erlachstrasse",
    "iso:country":"AT",
    "sg:address":"Erlachstrasse 23",
    "sg:city":"Hard",
    "sg:classifiers":[
        {
            "category":"Manufacturing",
            "subcategory":"Wood Products",
            "type":"Manufacturing & Wholesale Goods"
        }
    ],
    "sg:phone":"+43 5574 732060",
    "sg:postcode":"6971",
    "sg:province":"Vorarlberg",
    "sg:tags":[
        "gate",
        "made",
        "door"
    ],
    "sg:website":"tischlerei-schertler.at",
    "wof:name":"SM Schertler M\u00f6bel GmbH",
    "wof:placetype":"venue"
},
  "geometry": {"coordinates":[9.6864099503,47.4771690369],"type":"Point"}
}