{
  "type": "Feature",
  "properties": {
    "addr:full":"Christkindlweg 51 Steyr Ober\u00f6sterreich 4400",
    "addr:housenumber":"51",
    "addr:postcode":"4400",
    "addr:street":"Christkindlweg;Oberoesterreich",
    "iso:country":"AT",
    "sg:address":"Christkindlweg 51",
    "sg:city":"Steyr",
    "sg:orig_category":"Apparatus, Containers, Tanks, Boilers Of Plastic",
    "sg:phone":"+43 664 4454300",
    "sg:postcode":"4400",
    "sg:province":"Ober\u00f6sterreich",
    "sg:website":"thf.co.at",
    "wof:name":"Ing. Klaus Fenzl THF Technische Handels- und Planungsagentur",
    "wof:placetype":"venue"
},
  "geometry": {"coordinates":[14.3998756409,48.0391998291],"type":"Point"}
}