{
  "type": "Feature",
  "properties": {
    "iso:country":"AT",
    "sg:address":"Weilhartstr 30",
    "sg:city":"Ostermiething",
    "sg:orig_category":"Steinmetzbetriebe",
    "sg:phone":"+43 6278 6293",
    "sg:postcode":"5121",
    "sg:province":"Ober\u00f6sterreich",
    "wof:name":"W\u00f6rndl Peter",
    "wof:placetype":"venue"
},
  "geometry": {"coordinates":[12.8285856247,48.0477600098],"type":"Point"}
}