{
  "type": "Feature",
  "properties": {
    "addr:full":"R\u00f6merstr 14 Traiskirchen Nieder\u00f6sterreich 2514",
    "addr:housenumber":"14",
    "addr:postcode":"2514",
    "addr:street":"Roemerstr;Niederoesterreich",
    "iso:country":"AT",
    "sg:address":"R\u00f6merstr 14",
    "sg:city":"Traiskirchen",
    "sg:orig_category":"Biologische Produkte",
    "sg:phone":"+43 2252 559010",
    "sg:postcode":"2514",
    "sg:province":"Nieder\u00f6sterreich",
    "wof:name":"Sojarei Vollwertkost GesmbH",
    "wof:placetype":"venue"
},
  "geometry": {"coordinates":[16.2902793884,48.0275840759],"type":"Point"}
}