{
  "type": "Feature",
  "properties": {
    "addr:full":"Nr 310 Saalbach Salzburg 5753",
    "addr:postcode":"5753",
    "addr:street":"Nr;Saalbach",
    "iso:country":"AT",
    "sg:address":"Nr 310",
    "sg:city":"Saalbach",
    "sg:orig_category":"Polizei U Gendarmerie",
    "sg:phone":"+43 4359 1335182",
    "sg:postcode":"5753",
    "sg:province":"Salzburg",
    "wof:name":"Gendarmerieposten Saalbach Hinterglemm",
    "wof:placetype":"venue"
},
  "geometry": {"coordinates":[12.6367301941,47.3899307251],"type":"Point"}
}