{
  "type": "Feature",
  "properties": {
    "iso:country":"AT",
    "sg:address":"Goldschlagstr 182",
    "sg:city":"Wien",
    "sg:orig_category":"Badezimmer U Badezimmereinrichtungen",
    "sg:phone":"+43 1 41996440",
    "sg:postcode":"1140",
    "sg:province":"Wien",
    "sg:website":"www.ezor.at",
    "wof:name":"Ezor B\u00e4derstudio",
    "wof:placetype":"venue"
},
  "geometry": {"coordinates":[16.2986030579,48.1946182251],"type":"Point"}
}