{
  "type": "Feature",
  "properties": {
    "addr:full":"Sparkassegasse 31 Hollabrunn Nieder\u00f6sterreich 2020",
    "addr:housenumber":"31",
    "addr:postcode":"2020",
    "addr:street":"Sparkassegasse",
    "iso:country":"AT",
    "sg:address":"Sparkassegasse 31",
    "sg:city":"Hollabrunn",
    "sg:classifiers":[
        {
            "category":"Building & Trades",
            "subcategory":"Construction",
            "type":"Services"
        }
    ],
    "sg:phone":"+43 2952 4411",
    "sg:postcode":"2020",
    "sg:province":"Nieder\u00f6sterreich",
    "sg:tags":[
        "fireplace"
    ],
    "sg:website":"fliesen-kachel.at",
    "wof:name":"Johann Bauer jun.",
    "wof:placetype":"venue"
},
  "geometry": {"coordinates":[16.0796451569,48.5658340454],"type":"Point"}
}