{
  "type": "Feature",
  "properties": {
    "addr:full":"Braunhirscheng 24/13 Wien Wien 1150",
    "addr:housenumber":"24 / 13",
    "addr:postcode":"1150",
    "addr:street":"Braunhirscheng",
    "iso:country":"AT",
    "sg:address":"Braunhirscheng 24/13",
    "sg:city":"Wien",
    "sg:orig_category":"Baumeister",
    "sg:phone":"+43 1 5962724",
    "sg:postcode":"1150",
    "sg:province":"Wien",
    "wof:name":"Todorov Todor Bmstr Dipl-Ing",
    "wof:placetype":"venue"
},
  "geometry": {"coordinates":[16.3268985748,48.1881065369],"type":"Point"}
}