{
  "type": "Feature",
  "properties": {
    "addr:full":"Stubenring 6 Wien Wien 1010",
    "addr:housenumber":"6",
    "addr:postcode":"1010",
    "addr:street":"Stubenring",
    "iso:country":"AT",
    "sg:address":"Stubenring 6",
    "sg:city":"Wien",
    "sg:orig_category":"Institute",
    "sg:phone":"+43 1 515610",
    "sg:postcode":"1010",
    "sg:province":"Wien",
    "sg:website":"oebig.at",
    "wof:name":"\u00f6BIG - \u00f6sterreichisches Bundesinstitut f Gesundheitswesen",
    "wof:placetype":"venue"
},
  "geometry": {"coordinates":[16.3822021484,48.2102394104],"type":"Point"}
}