{
  "type": "Feature",
  "properties": {
    "addr:full":"Max-Kleinoscheg-G 2 M\u00fcrzzuschlag Steiermark 8680",
    "addr:housenumber":"2",
    "addr:postcode":"8680",
    "addr:street":"Max-Kleinoscheg-G",
    "iso:country":"AT",
    "sg:address":"Max-Kleinoscheg-G 2",
    "sg:city":"M\u00fcrzzuschlag",
    "sg:orig_category":"Versicherungsunternehmen",
    "sg:phone":"+43 3852 3133",
    "sg:postcode":"8680",
    "sg:province":"Steiermark",
    "wof:name":"Allianz Elementar Versicherungs-AG",
    "wof:placetype":"venue"
},
  "geometry": {"coordinates":[15.6745281219,47.6065711975],"type":"Point"}
}