{
  "type": "Feature",
  "properties": {
    "iso:country":"AT",
    "sg:address":"Alpendorf 12",
    "sg:city":"St. Johann im Pongau",
    "sg:classifiers":[
        {
            "category":"Restaurant",
            "type":"Food & Drink"
        }
    ],
    "sg:phone":"+43 4364 1263960",
    "sg:postcode":"5600",
    "sg:province":"Salzburg",
    "wof:name":"Oberforsthofalm GesmbH",
    "wof:placetype":"venue"
},
  "geometry": {"coordinates":[13.204990387,47.3366546631],"type":"Point"}
}