{
  "type": "Feature",
  "properties": {
    "addr:full":"Larch 1 Aldrans Tirol 6071",
    "addr:housenumber":"1",
    "addr:postcode":"6071",
    "addr:street":"Larch;Tirol",
    "iso:country":"AT",
    "sg:address":"Larch 1",
    "sg:city":"Aldrans",
    "sg:orig_category":"Installationsunternehmen",
    "sg:phone":"+43 512 261754",
    "sg:postcode":"6071",
    "sg:province":"Tirol",
    "wof:name":"Terrakalor Haidsengst Michael",
    "wof:placetype":"venue"
},
  "geometry": {"coordinates":[11.4482002258,47.2512512207],"type":"Point"}
}