{
  "type": "Feature",
  "properties": {
    "addr:full":"Wiener G 46 Auersthal Nieder\u00f6sterreich 2214",
    "addr:housenumber":"46",
    "addr:postcode":"2214",
    "addr:street":"Wiener G",
    "iso:country":"AT",
    "sg:address":"Wiener G 46",
    "sg:city":"Auersthal",
    "sg:orig_category":"Glasereien",
    "sg:phone":"+43 2288 2766",
    "sg:postcode":"2214",
    "sg:province":"Nieder\u00f6sterreich",
    "wof:name":"Erben Glasbau",
    "wof:placetype":"venue"
},
  "geometry": {"coordinates":[16.6318054199,48.3722343445],"type":"Point"}
}