{
  "type": "Feature",
  "properties": {
    "addr:full":"Georgestr 10 St. Georgen an der Gusen Ober\u00f6sterreich 4222",
    "addr:housenumber":"10",
    "addr:postcode":"4222",
    "addr:street":"Georgestr",
    "iso:country":"AT",
    "sg:address":"Georgestr 10",
    "sg:city":"St. Georgen an der Gusen",
    "sg:orig_category":"Finanz- U Wirtschaftsberatung",
    "sg:phone":"+43 4372 373379",
    "sg:postcode":"4222",
    "sg:province":"Ober\u00f6sterreich",
    "wof:name":"Schachl Maximilian",
    "wof:placetype":"venue"
},
  "geometry": {"coordinates":[14.4651670456,48.2554550171],"type":"Point"}
}