{
  "type": "Feature",
  "properties": {
    "addr:full":"Wiener Str 3 Halbturn Burgenland 7131",
    "addr:housenumber":"3",
    "addr:postcode":"7131",
    "iso:country":"AT",
    "sg:address":"Wiener Str 3",
    "sg:city":"Halbturn",
    "sg:orig_category":"Gemeinden",
    "sg:phone":"+43 2172 86450",
    "sg:postcode":"7131",
    "sg:province":"Burgenland",
    "wof:name":"Gemeindeamt Halbturn",
    "wof:placetype":"venue"
},
  "geometry": {"coordinates":[16.971988678,47.8718261719],"type":"Point"}
}