{
  "type": "Feature",
  "properties": {
    "addr:full":"Salzburger Strasse 262 Linz Ober\u00f6sterreich 4020",
    "addr:housenumber":"262",
    "addr:postcode":"4020",
    "addr:street":"Salzburger Strasse",
    "iso:country":"AT",
    "sg:address":"Salzburger Strasse 262",
    "sg:city":"Linz",
    "sg:classifiers":[
        {
            "category":"Bars & Pubs",
            "subcategory":"Wine Bar",
            "type":"Food & Drink"
        }
    ],
    "sg:phone":"+43 732 3828480",
    "sg:postcode":"4020",
    "sg:province":"Ober\u00f6sterreich",
    "sg:tags":[
        "chimney",
        "cowl"
    ],
    "sg:website":"kuny.at",
    "wof:name":"KUNY Kaminbau Ing. Fritz Baum & S\u00f6hne Ges.m.b.H.",
    "wof:placetype":"venue"
},
  "geometry": {"coordinates":[14.2831678391,48.2542762756],"type":"Point"}
}