{
  "type": "Feature",
  "properties": {
    "addr:full":"Bremschlstr 16a B\u00fcrs Vorarlberg 6706",
    "addr:housenumber":"16a",
    "addr:postcode":"6706",
    "addr:street":"Bremschlstr",
    "iso:country":"AT",
    "sg:address":"Bremschlstr 16a",
    "sg:city":"B\u00fcrs",
    "sg:orig_category":"Autohandel",
    "sg:phone":"+43 4355 52627300",
    "sg:postcode":"6706",
    "sg:province":"Vorarlberg",
    "wof:name":"Schmidmayr Walter GesmbH & Co KG",
    "wof:placetype":"venue"
},
  "geometry": {"coordinates":[9.8174800873,47.1492080688],"type":"Point"}
}