{
  "type": "Feature",
  "properties": {
    "addr:full":"Brillergraben 11 St. Veit an der G\u00f6lsen Nieder\u00f6sterreich 3161",
    "addr:housenumber":"11",
    "addr:postcode":"3161",
    "addr:street":"Brillergraben;Niederoesterreich",
    "iso:country":"AT",
    "sg:address":"Brillergraben 11",
    "sg:city":"St. Veit an der G\u00f6lsen",
    "sg:orig_category":"Physiotherapie",
    "sg:phone":"+43 4366 42715734",
    "sg:postcode":"3161",
    "sg:province":"Nieder\u00f6sterreich",
    "wof:name":"Tierphysiotherapie Eva Singer",
    "wof:placetype":"venue"
},
  "geometry": {"coordinates":[15.6741037369,48.0409240723],"type":"Point"}
}