{
  "type": "Feature",
  "properties": {
    "iso:country":"AT",
    "sg:address":"Tuschenkogelstr 463",
    "sg:city":"Bad St. Leonhard im Lavanttal",
    "sg:orig_category":"Glas",
    "sg:phone":"+43 4350 3408",
    "sg:postcode":"9462",
    "sg:province":"K\u00e4rnten",
    "wof:name":"Euro-Tech Bauer Glasindustrieservice & Handels GesmbH",
    "wof:placetype":"venue"
},
  "geometry": {"coordinates":[12.3305559158,48.0921058655],"type":"Point"}
}