{
  "type": "Feature",
  "properties": {
    "iso:country":"AT",
    "sg:address":"Fischachstr 36",
    "sg:city":"Bergheim",
    "sg:orig_category":"Autolackierereien",
    "sg:phone":"+43 662 457255",
    "sg:postcode":"5101",
    "sg:province":"Salzburg",
    "wof:name":"Staudinger Josef",
    "wof:placetype":"venue"
},
  "geometry": {"coordinates":[13.0294494629,47.8473777771],"type":"Point"}
}