{
  "type": "Feature",
  "properties": {
    "iso:country":"AT",
    "sg:address":"Tiroler Str 80",
    "sg:city":"Villach",
    "sg:orig_category":"Pumpen / Reparatur",
    "sg:phone":"+43 4342 4251751",
    "sg:postcode":"9500",
    "sg:province":"K\u00e4rnten",
    "sg:website":"vacutech.at",
    "wof:name":"vacutech Vakuum- u F\u00f6rdertechnik GmbH",
    "wof:placetype":"venue"
},
  "geometry": {"coordinates":[13.8260374069,46.6157226562],"type":"Point"}
}