{
  "type": "Feature",
  "properties": {
    "addr:full":"Schulstr 223 Feistritz an der Drau K\u00e4rnten 9710",
    "addr:housenumber":"223",
    "addr:postcode":"9710",
    "iso:country":"AT",
    "sg:address":"Schulstr 223",
    "sg:city":"Feistritz an der Drau",
    "sg:orig_category":"Volksschulen",
    "sg:phone":"+43 4342 4525104",
    "sg:postcode":"9710",
    "sg:province":"K\u00e4rnten",
    "wof:name":"Volksschule 1",
    "wof:placetype":"venue"
},
  "geometry": {"coordinates":[13.6658649445,46.6946182251],"type":"Point"}
}