{
  "type": "Feature",
  "properties": {
    "addr:full":"Gewerbestrasse 6 Seekirchen am Wallersee Salzburg 5201",
    "addr:housenumber":"6",
    "addr:postcode":"5201",
    "addr:street":"Gewerbestrasse;Salzburg",
    "iso:country":"AT",
    "sg:address":"Gewerbestrasse 6",
    "sg:city":"Seekirchen am Wallersee",
    "sg:orig_category":"Apparatus, Containers, Tanks, Vessels, And Boilers Of Stainless Steel",
    "sg:phone":"+43 6212 22810",
    "sg:postcode":"5201",
    "sg:province":"Salzburg",
    "sg:website":"schmidt-edelstahl.at",
    "wof:name":"W. Schmidt Ges.m.b.H.",
    "wof:placetype":"venue"
},
  "geometry": {"coordinates":[13.1206388474,47.8871192932],"type":"Point"}
}