{
  "type": "Feature",
  "properties": {
    "addr:full":"Wiener Str 2c Stegersbach Burgenland 7551",
    "addr:housenumber":"2c",
    "addr:postcode":"7551",
    "addr:street":"Str",
    "iso:country":"AT",
    "sg:address":"Wiener Str 2c",
    "sg:city":"Stegersbach",
    "sg:orig_category":"Blumeneinzelhandel",
    "sg:phone":"+43 3326 53706",
    "sg:postcode":"7551",
    "sg:province":"Burgenland",
    "wof:name":"Langer's Blumenecke",
    "wof:placetype":"venue"
},
  "geometry": {"coordinates":[16.1659355164,47.1603355408],"type":"Point"}
}