{
  "type": "Feature",
  "properties": {
    "addr:full":"Untere Hauptstr 39 Riedlingsdorf Burgenland 7422",
    "addr:housenumber":"39",
    "addr:postcode":"7422",
    "addr:street":"Untere Hauptstr",
    "iso:country":"AT",
    "sg:address":"Untere Hauptstr 39",
    "sg:city":"Riedlingsdorf",
    "sg:orig_category":"Bestattungsunternehmen",
    "sg:phone":"+43 3357 42377",
    "sg:postcode":"7422",
    "sg:province":"Burgenland",
    "wof:name":"Strobl Isolde",
    "wof:placetype":"venue"
},
  "geometry": {"coordinates":[16.1388092041,47.3436203003],"type":"Point"}
}