{
  "type": "Feature",
  "properties": {
    "addr:full":"Vorderstadt 25 Kitzb\u00fchel Tirol 6370",
    "addr:housenumber":"25",
    "addr:postcode":"6370",
    "addr:street":"Vorderstadt;Tirol",
    "iso:country":"AT",
    "sg:address":"Vorderstadt 25",
    "sg:city":"Kitzb\u00fchel",
    "sg:orig_category":"Lebensmittel / Einzelhandel",
    "sg:phone":"+43 5356 66002",
    "sg:postcode":"6370",
    "sg:province":"Tirol",
    "wof:name":"Corso Gourmet",
    "wof:placetype":"venue"
},
  "geometry": {"coordinates":[12.3914337158,47.4463386536],"type":"Point"}
}