{
  "type": "Feature",
  "properties": {
    "addr:full":"Hauptstr 65 Reichenau an der Rax Nieder\u00f6sterreich 2651",
    "addr:housenumber":"65",
    "addr:postcode":"2651",
    "addr:street":"Hauptstr",
    "iso:country":"AT",
    "sg:address":"Hauptstr 65",
    "sg:city":"Reichenau an der Rax",
    "sg:orig_category":"Fotografen",
    "sg:phone":"+43 2666 52298",
    "sg:postcode":"2651",
    "sg:province":"Nieder\u00f6sterreich",
    "wof:name":"Foto & Studio - Erika Cifrain",
    "wof:placetype":"venue"
},
  "geometry": {"coordinates":[15.8423929214,47.6959915161],"type":"Point"}
}