{
  "type": "Feature",
  "properties": {
    "addr:full":"D\u00fcrnbichlstr 48 Eugendorf Salzburg 5301",
    "addr:housenumber":"48",
    "addr:postcode":"5301",
    "addr:street":"Duernbichlstr;Salzburg",
    "iso:country":"AT",
    "sg:address":"D\u00fcrnbichlstr 48",
    "sg:city":"Eugendorf",
    "sg:classifiers":[
        {
            "category":"Restaurant",
            "type":"Food & Drink"
        }
    ],
    "sg:phone":"+43 6225 3044",
    "sg:postcode":"5301",
    "sg:province":"Salzburg",
    "wof:name":"Bar B Q",
    "wof:placetype":"venue"
},
  "geometry": {"coordinates":[13.122505188,47.8666496277],"type":"Point"}
}