{
  "type": "Feature",
  "properties": {
    "addr:full":"Haiden 513 Bad Ischl Ober\u00f6sterreich 4820",
    "addr:housenumber":"513",
    "addr:postcode":"4820",
    "addr:street":"Haiden",
    "iso:country":"AT",
    "sg:address":"Haiden 513",
    "sg:city":"Bad Ischl",
    "sg:orig_category":"Bekleidung / Einzelhandel",
    "sg:phone":"+43 6132 22697",
    "sg:postcode":"4820",
    "sg:province":"Ober\u00f6sterreich",
    "wof:name":"Takko ModeMarkt GmbH",
    "wof:placetype":"venue"
},
  "geometry": {"coordinates":[13.5800170898,47.7264595032],"type":"Point"}
}