{
  "type": "Feature",
  "properties": {
    "addr:full":"Nr 19 K\u00f6tschach-Mauthen K\u00e4rnten 9640",
    "addr:postcode":"9640",
    "addr:street":"Nr 19 Koetschach-Mauthen Kaernten",
    "iso:country":"AT",
    "sg:address":"Nr 19",
    "sg:city":"K\u00f6tschach-Mauthen",
    "sg:orig_category":"Banken U Sparkassen",
    "sg:phone":"+43 4715 818333",
    "sg:postcode":"9640",
    "sg:province":"K\u00e4rnten",
    "wof:name":"Raiffeisenbank K\u00f6tschach-Mauthen regGenmbH",
    "wof:placetype":"venue"
},
  "geometry": {"coordinates":[12.9984302521,46.6670227051],"type":"Point"}
}