{
  "type": "Feature",
  "properties": {
    "addr:full":"Zippersfeld 24 Altach Vorarlberg 6844",
    "addr:housenumber":"24",
    "addr:postcode":"6844",
    "addr:street":"Zippersfeld",
    "iso:country":"AT",
    "sg:address":"Zippersfeld 24",
    "sg:city":"Altach",
    "sg:classifiers":[
        {
            "category":"Communications",
            "subcategory":"Television Station",
            "type":"Services"
        }
    ],
    "sg:phone":"+43 5576 78830",
    "sg:postcode":"6844",
    "sg:province":"Vorarlberg",
    "sg:tags":[
        "tv",
        "component",
        "cable"
    ],
    "wof:name":"Netcom",
    "wof:placetype":"venue"
},
  "geometry": {"coordinates":[9.6565170288,47.3599967957],"type":"Point"}
}