{
  "type": "Feature",
  "properties": {
    "addr:full":"Nr 102 Ainet Tirol 9951",
    "addr:postcode":"9951",
    "addr:street":"Nr 102 Ainet Tirol",
    "iso:country":"AT",
    "sg:address":"Nr 102",
    "sg:city":"Ainet",
    "sg:classifiers":[
        {
            "category":"Home & Garden",
            "subcategory":"Garden Supply",
            "type":"Retail Goods"
        }
    ],
    "sg:phone":"+43 4348 535296",
    "sg:postcode":"9951",
    "sg:province":"Tirol",
    "sg:tags":[
        "schotter",
        "sand",
        "u"
    ],
    "wof:name":"Staller Josef",
    "wof:placetype":"venue"
},
  "geometry": {"coordinates":[12.6879796982,46.8666038513],"type":"Point"}
}