{
  "type": "Feature",
  "properties": {
    "iso:country":"AT",
    "sg:address":"Bahnhofstr 42",
    "sg:city":"Zirl",
    "sg:orig_category":"Autoverwertung",
    "sg:phone":"+43 5238 53151",
    "sg:postcode":"6170",
    "sg:province":"Tirol",
    "wof:name":"Autorecycling Schaber GesmbH",
    "wof:placetype":"venue"
},
  "geometry": {"coordinates":[11.2316999435,47.2672996521],"type":"Point"}
}