{
  "type": "Feature",
  "properties": {
    "addr:full":"Herrengasse 2 Rechnitz Burgenland 7471",
    "addr:housenumber":"2",
    "addr:postcode":"7471",
    "addr:street":"Herrengasse",
    "iso:country":"AT",
    "sg:address":"Herrengasse 2",
    "sg:city":"Rechnitz",
    "sg:classifiers":[
        {
            "category":"Home & Garden",
            "subcategory":"Carpets & Floor Coverings",
            "type":"Retail Goods"
        }
    ],
    "sg:phone":"+43 3363 79297",
    "sg:postcode":"7471",
    "sg:province":"Burgenland",
    "sg:tags":[
        "cotton"
    ],
    "wof:name":"Erhard Radl",
    "wof:placetype":"venue"
},
  "geometry": {"coordinates":[16.4402866364,47.3047866821],"type":"Point"}
}