{
  "type": "Feature",
  "properties": {
    "addr:full":"Bad-S\u00e4ckingen-Str 4 Purkersdorf Nieder\u00f6sterreich 3002",
    "addr:housenumber":"4",
    "addr:postcode":"3002",
    "addr:street":"Bad-Saeckingen-Str",
    "iso:country":"AT",
    "sg:address":"Bad-S\u00e4ckingen-Str 4",
    "sg:city":"Purkersdorf",
    "sg:orig_category":"Handelsagenturen",
    "sg:phone":"+43 2231 64059",
    "sg:postcode":"3002",
    "sg:province":"Nieder\u00f6sterreich",
    "wof:name":"Schreiweis Karin",
    "wof:placetype":"venue"
},
  "geometry": {"coordinates":[16.1764831543,48.2095603943],"type":"Point"}
}