{
  "type": "Feature",
  "properties": {
    "iso:country":"AT",
    "sg:address":"Auhofstrasse 186e",
    "sg:city":"Wien",
    "sg:classifiers":[
        {
            "category":"Utilities",
            "subcategory":"Natural Gas",
            "type":"Services"
        }
    ],
    "sg:phone":"+43 1 8776803",
    "sg:postcode":"1130",
    "sg:province":"Wien",
    "sg:tags":[
        "heater",
        "direct",
        "electric"
    ],
    "wof:name":"Eugen Zeillinger",
    "wof:placetype":"venue"
},
  "geometry": {"coordinates":[16.2624874115,48.1948051453],"type":"Point"}
}