{
  "type": "Feature",
  "properties": {
    "addr:full":"Ledererg 25 Wien Wien 1080",
    "addr:housenumber":"25",
    "addr:postcode":"1080",
    "addr:street":"Ledererg",
    "iso:country":"AT",
    "sg:address":"Ledererg 25",
    "sg:city":"Wien",
    "sg:orig_category":"Institute",
    "sg:phone":"+43 1 400087360",
    "sg:postcode":"1080",
    "sg:province":"Wien",
    "wof:name":"Institut f Suchtdiagnostik",
    "wof:placetype":"venue"
},
  "geometry": {"coordinates":[16.3483581543,48.21276474],"type":"Point"}
}