{
  "type": "Feature",
  "properties": {
    "addr:full":"Wr Neust\u00e4dter Str 40 Kottingbrunn Nieder\u00f6sterreich 2542",
    "addr:housenumber":"40",
    "addr:postcode":"2542",
    "addr:street":"Str",
    "iso:country":"AT",
    "sg:address":"Wr Neust\u00e4dter Str 40",
    "sg:city":"Kottingbrunn",
    "sg:orig_category":"Steinmetzbetriebe",
    "sg:phone":"+43 2252 790801",
    "sg:postcode":"2542",
    "sg:province":"Nieder\u00f6sterreich",
    "wof:name":"Erber Peter",
    "wof:placetype":"venue"
},
  "geometry": {"coordinates":[16.2285327911,47.9514656067],"type":"Point"}
}