{
  "type": "Feature",
  "properties": {
    "iso:country":"AT",
    "sg:address":"Am Anger 2",
    "sg:city":"Lilienfeld",
    "sg:orig_category":"Bezirkshauptmannschaften",
    "sg:phone":"+43 2762 90250",
    "sg:postcode":"3180",
    "sg:province":"Nieder\u00f6sterreich",
    "wof:name":"Bezirkshauptmannschaft Lilienfeld",
    "wof:placetype":"venue"
},
  "geometry": {"coordinates":[15.5959501266,48.0164756775],"type":"Point"}
}