{
  "type": "Feature",
  "properties": {
    "addr:full":"Oberm\u00fchl 16 Unterwei\u00dfenbach Ober\u00f6sterreich 4273",
    "addr:housenumber":"16",
    "addr:postcode":"4273",
    "addr:street":"Obermuehl",
    "iso:country":"AT",
    "sg:address":"Oberm\u00fchl 16",
    "sg:city":"Unterwei\u00dfenbach",
    "sg:classifiers":[
        {
            "category":"Home & Garden",
            "subcategory":"Building Materials",
            "type":"Retail Goods"
        }
    ],
    "sg:phone":"+43 7956 72680",
    "sg:postcode":"4273",
    "sg:province":"Ober\u00f6sterreich",
    "sg:tags":[
        "railing",
        "balcony"
    ],
    "wof:name":"Felix Franz Haider",
    "wof:placetype":"venue"
},
  "geometry": {"coordinates":[14.7811594009,48.4358215332],"type":"Point"}
}