{
  "type": "Feature",
  "properties": {
    "addr:full":"Cumberlandstr 27 Wien Wien 1140",
    "addr:housenumber":"27",
    "addr:postcode":"1140",
    "addr:street":"Cumberlandstr",
    "iso:country":"AT",
    "sg:address":"Cumberlandstr 27",
    "sg:city":"Wien",
    "sg:orig_category":"Maler, Anstreicher U Lackierer",
    "sg:phone":"+43 1 89427410",
    "sg:postcode":"1140",
    "sg:province":"Wien",
    "wof:name":"Lehner Malerbetrieb GmbH",
    "wof:placetype":"venue"
},
  "geometry": {"coordinates":[16.3079624176,48.191696167],"type":"Point"}
}