{
  "type": "Feature",
  "properties": {
    "addr:full":"Loferer Str 123 Kirchbichl Tirol 6322",
    "addr:housenumber":"123",
    "addr:postcode":"6322",
    "addr:street":"Kirchbichl Tirol",
    "iso:country":"AT",
    "sg:address":"Loferer Str 123",
    "sg:city":"Kirchbichl",
    "sg:orig_category":"Transportunternehmen",
    "sg:phone":"+43 5332 72072",
    "sg:postcode":"6322",
    "sg:province":"Tirol",
    "wof:name":"Kogler Manfred",
    "wof:placetype":"venue"
},
  "geometry": {"coordinates":[12.1170549393,47.4862976074],"type":"Point"}
}