{
  "type": "Feature",
  "properties": {
    "addr:full":"Nr 18 St. Wolfgang im Salzkammergut Ober\u00f6sterreich 5360",
    "addr:postcode":"5360",
    "addr:street":"Nr 18 St.",
    "iso:country":"AT",
    "sg:address":"Nr 18",
    "sg:city":"St. Wolfgang im Salzkammergut",
    "sg:classifiers":[
        {
            "category":"Travel",
            "subcategory":"Hotels & Motels",
            "type":"Entertainment"
        }
    ],
    "sg:phone":"+43 6138 22090",
    "sg:postcode":"5360",
    "sg:province":"Ober\u00f6sterreich",
    "wof:name":"Landhaus zu Appesbach - Hotel am See",
    "wof:placetype":"venue"
},
  "geometry": {"coordinates":[13.4459896088,47.73985672],"type":"Point"}
}