{
  "type": "Feature",
  "properties": {
    "addr:full":"Burgg 15 Judenburg Steiermark 8750",
    "addr:housenumber":"15",
    "addr:postcode":"8750",
    "addr:street":"Burgg",
    "iso:country":"AT",
    "sg:address":"Burgg 15",
    "sg:city":"Judenburg",
    "sg:orig_category":"Fernseh- U Radiogesellschaften",
    "sg:phone":"+43 3572 83146188",
    "sg:postcode":"8750",
    "sg:province":"Steiermark",
    "wof:name":"Kanal3 - das regionale Fernsehen",
    "wof:placetype":"venue"
},
  "geometry": {"coordinates":[14.6587848663,47.1678848267],"type":"Point"}
}