{
  "type": "Feature",
  "properties": {
    "addr:full":"Buchenweg 3 Lannach Steiermark 8502",
    "addr:housenumber":"3",
    "addr:postcode":"8502",
    "addr:street":"Buchenweg",
    "iso:country":"AT",
    "sg:address":"Buchenweg 3",
    "sg:city":"Lannach",
    "sg:orig_category":"Alternativtherapie",
    "sg:phone":"+43 3136 81870",
    "sg:postcode":"8502",
    "sg:province":"Steiermark",
    "wof:name":"MK-ENERGIES - Bioenergetische Produkte",
    "wof:placetype":"venue"
},
  "geometry": {"coordinates":[15.3107061386,46.9618263245],"type":"Point"}
}