{
  "type": "Feature",
  "properties": {
    "addr:full":"Wiener Str 22 Gloggnitz Nieder\u00f6sterreich 2640",
    "addr:postcode":"2640",
    "addr:street":"Niederoesterreich",
    "iso:country":"AT",
    "sg:address":"Wiener Str 22",
    "sg:city":"Gloggnitz",
    "sg:orig_category":"Banken U Sparkassen",
    "sg:phone":"+43 2662 433570",
    "sg:postcode":"2640",
    "sg:province":"Nieder\u00f6sterreich",
    "wof:name":"Sparkasse Neunkirchen-Gloggnitz-Ternitz",
    "wof:placetype":"venue"
},
  "geometry": {"coordinates":[15.9432020187,47.6739425659],"type":"Point"}
}