{
  "type": "Feature",
  "properties": {
    "iso:country":"AT",
    "sg:address":"Grazer Str 54",
    "sg:city":"Heiligenkreuz am Waasen",
    "sg:orig_category":"Lebensmittel / Einzelhandel",
    "sg:phone":"+43 3134 30082",
    "sg:postcode":"8081",
    "sg:province":"Steiermark",
    "wof:name":"Spar-Markt Platzer GesmbH",
    "wof:placetype":"venue"
},
  "geometry": {"coordinates":[15.5846948624,46.9635314941],"type":"Point"}
}