{
  "type": "Feature",
  "properties": {
    "iso:country":"AT",
    "sg:address":"Karl-Huber-G 15",
    "sg:city":"Liebenau",
    "sg:orig_category":"Tischlereien",
    "sg:phone":"+43 316 4650100",
    "sg:postcode":"8041",
    "sg:province":"Steiermark",
    "sg:website":"pleschek.at",
    "wof:name":"Pleschek Felix GesmbH",
    "wof:placetype":"venue"
},
  "geometry": {"coordinates":[15.461315155,47.0434150696],"type":"Point"}
}