{
  "type": "Feature",
  "properties": {
    "addr:full":"Oberer Stadtpl 22 Waidhofen an der Ybbs Nieder\u00f6sterreich 3340",
    "addr:housenumber":"22",
    "addr:postcode":"3340",
    "addr:street":"Oberer Stadtpl",
    "iso:country":"AT",
    "sg:address":"Oberer Stadtpl 22",
    "sg:city":"Waidhofen an der Ybbs",
    "sg:orig_category":"Banken U Sparkassen",
    "sg:phone":"+43 4374 42556000",
    "sg:postcode":"3340",
    "sg:province":"Nieder\u00f6sterreich",
    "wof:name":"Bankomat d Raiffeisenbank Waidhofen/Ybbs regGenmbH",
    "wof:placetype":"venue"
},
  "geometry": {"coordinates":[14.7751951218,47.9604873657],"type":"Point"}
}