{
  "type": "Feature",
  "properties": {
    "addr:full":"Schillg 13/9 Wien Wien 1210",
    "addr:housenumber":"13 / 9",
    "addr:postcode":"1210",
    "addr:street":"Schillg",
    "iso:country":"AT",
    "sg:address":"Schillg 13/9",
    "sg:city":"Wien",
    "sg:orig_category":"Ergotherapie",
    "sg:phone":"+43 1 2787772",
    "sg:postcode":"1210",
    "sg:province":"Wien",
    "wof:name":"Muth Irene Dipl-Erg",
    "wof:placetype":"venue"
},
  "geometry": {"coordinates":[16.3867034912,48.2661552429],"type":"Point"}
}