{
  "type": "Feature",
  "properties": {
    "addr:full":"Linzer Str 10 Wien Wien 1140",
    "addr:housenumber":"10",
    "addr:postcode":"1140",
    "addr:street":"Linzer Str",
    "iso:country":"AT",
    "sg:address":"Linzer Str 10",
    "sg:city":"Wien",
    "sg:orig_category":"Lebensmittel / Einzelhandel",
    "sg:phone":"+43 1 9851340",
    "sg:postcode":"1140",
    "sg:province":"Wien",
    "wof:name":"MONDO Lebensmitteldiskonter",
    "wof:placetype":"venue"
},
  "geometry": {"coordinates":[16.3154945374,48.1927909851],"type":"Point"}
}