{
  "type": "Feature",
  "properties": {
    "iso:country":"AT",
    "sg:address":"Karl-Holub-Str 3",
    "sg:city":"Steyr",
    "sg:orig_category":"Immobilienverwaltungen",
    "sg:phone":"+43 4372 527622719",
    "sg:postcode":"4400",
    "sg:province":"Ober\u00f6sterreich",
    "wof:name":"Alpenland Immobilienverwaltungs- u BeteiligungsgesmbH",
    "wof:placetype":"venue"
},
  "geometry": {"coordinates":[14.4186620712,48.0509376526],"type":"Point"}
}