{
  "type": "Feature",
  "properties": {
    "iso:country":"AT",
    "sg:address":"Nr 98",
    "sg:city":"Strengberg",
    "sg:orig_category":"Tapezierer U Dekorateure",
    "sg:phone":"+43 7432 2693",
    "sg:postcode":"3314",
    "sg:province":"Nieder\u00f6sterreich",
    "wof:name":"Bachler Leopold",
    "wof:placetype":"venue"
},
  "geometry": {"coordinates":[14.6513147354,48.1428489685],"type":"Point"}
}