{
  "type": "Feature",
  "properties": {
    "addr:full":"Hauptstr 2 Ternitz Nieder\u00f6sterreich 2630",
    "addr:housenumber":"2",
    "addr:postcode":"2630",
    "addr:street":"Hauptstr",
    "iso:country":"AT",
    "sg:address":"Hauptstr 2",
    "sg:city":"Ternitz",
    "sg:classifiers":[
        {
            "category":"Internet Cafe",
            "subcategory":"None",
            "type":"Food & Drink"
        }
    ],
    "sg:phone":"+43 2630 2012040",
    "sg:postcode":"2630",
    "sg:province":"Nieder\u00f6sterreich",
    "sg:tags":[
        "internet-provider"
    ],
    "wof:name":"Compufit Datenverarbeitungs-GmbH",
    "wof:placetype":"venue"
},
  "geometry": {"coordinates":[16.0361824036,47.7149124146],"type":"Point"}
}