{
  "type": "Feature",
  "properties": {
    "addr:full":"Stadtpl 40 Wels Ober\u00f6sterreich 4600",
    "addr:housenumber":"40",
    "addr:postcode":"4600",
    "addr:street":"Stadtpl;Oberoesterreich",
    "iso:country":"AT",
    "sg:address":"Stadtpl 40",
    "sg:city":"Wels",
    "sg:orig_category":"Tabaktrafiken",
    "sg:phone":"+43 7242 46193",
    "sg:postcode":"4600",
    "sg:province":"Ober\u00f6sterreich",
    "wof:name":"Hofmair Josef",
    "wof:placetype":"venue"
},
  "geometry": {"coordinates":[14.0264797211,48.1574401855],"type":"Point"}
}