{
  "type": "Feature",
  "properties": {
    "addr:full":"Industriestr 18 Himberg Nieder\u00f6sterreich 2325",
    "addr:housenumber":"18",
    "addr:postcode":"2325",
    "addr:street":"Industriestr",
    "iso:country":"AT",
    "sg:address":"Industriestr 18",
    "sg:city":"Himberg",
    "sg:orig_category":"Bauunternehmen",
    "sg:phone":"+43 4322 3587124",
    "sg:postcode":"2325",
    "sg:province":"Nieder\u00f6sterreich",
    "wof:name":"Bilfinger + Berger BaugesmbH",
    "wof:placetype":"venue"
},
  "geometry": {"coordinates":[16.4504241943,48.077255249],"type":"Point"}
}