{
  "type": "Feature",
  "properties": {
    "addr:full":"Landstr 24 Linz Ober\u00f6sterreich 4020",
    "addr:housenumber":"24",
    "addr:postcode":"4020",
    "addr:street":"Landstr",
    "iso:country":"AT",
    "sg:address":"Landstr 24",
    "sg:city":"Linz",
    "sg:orig_category":"Lederwaren / Erzeugung U Gro\u00c3\u0178handel",
    "sg:phone":"+43 732 772831",
    "sg:postcode":"4020",
    "sg:province":"Ober\u00f6sterreich",
    "wof:name":"Hackl Karl GesmbH & Co KG",
    "wof:placetype":"venue"
},
  "geometry": {"coordinates":[14.2890453339,48.302772522],"type":"Point"}
}