{
  "type": "Feature",
  "properties": {
    "addr:full":"Faludig 22b Rechnitz Burgenland 7471",
    "addr:housenumber":"22b",
    "addr:postcode":"7471",
    "addr:street":"Faludig",
    "iso:country":"AT",
    "sg:address":"Faludig 22b",
    "sg:city":"Rechnitz",
    "sg:orig_category":"Gastronomie- U Hoteleinrichtungen",
    "sg:phone":"+43 4333 6377777",
    "sg:postcode":"7471",
    "sg:province":"Burgenland",
    "wof:name":"Binder Johann",
    "wof:placetype":"venue"
},
  "geometry": {"coordinates":[16.4403247833,47.3056755066],"type":"Point"}
}