{
  "type": "Feature",
  "properties": {
    "addr:full":"Bundesstr 7 Fohnsdorf Steiermark 8753",
    "addr:housenumber":"7",
    "addr:postcode":"8753",
    "addr:street":"Bundesstr",
    "iso:country":"AT",
    "sg:address":"Bundesstr 7",
    "sg:city":"Fohnsdorf",
    "sg:orig_category":"Autoreparatur",
    "sg:phone":"+43 4335 7282783",
    "sg:postcode":"8753",
    "sg:province":"Steiermark",
    "wof:name":"Huber Theodor",
    "wof:placetype":"venue"
},
  "geometry": {"coordinates":[14.6845693588,47.1904983521],"type":"Point"}
}