{
  "type": "Feature",
  "properties": {
    "addr:full":"Bahnhofstr 27A Mauerkirchen Ober\u00f6sterreich 5270",
    "addr:housenumber":"27a",
    "addr:postcode":"5270",
    "addr:street":"Bahnhofstr",
    "iso:country":"AT",
    "sg:address":"Bahnhofstr 27A",
    "sg:city":"Mauerkirchen",
    "sg:orig_category":"Transportunternehmen",
    "sg:phone":"+43 7724 3112",
    "sg:postcode":"5270",
    "sg:province":"Ober\u00f6sterreich",
    "wof:name":"RAINER Handels-, Speditions und Transport GesmbH",
    "wof:placetype":"venue"
},
  "geometry": {"coordinates":[13.1294202805,48.1928100586],"type":"Point"}
}