{
  "type": "Feature",
  "properties": {
    "addr:full":"Nr 33 Lienz Tirol 9900",
    "addr:postcode":"9900",
    "addr:street":"Nr 33;Tirol",
    "iso:country":"AT",
    "sg:address":"Nr 33",
    "sg:city":"Lienz",
    "sg:orig_category":"Erdarbeiten",
    "sg:phone":"+43 4852 68102",
    "sg:postcode":"9900",
    "sg:province":"Tirol",
    "wof:name":"Dietrich Gebr GesmbH",
    "wof:placetype":"venue"
},
  "geometry": {"coordinates":[12.7684783936,46.8281173706],"type":"Point"}
}