{
  "type": "Feature",
  "properties": {
    "iso:country":"AT",
    "sg:address":"Nr 1",
    "sg:city":"Schiefling am See",
    "sg:orig_category":"Pensionen / Privatzimmer",
    "sg:phone":"+43 4274 51963",
    "sg:postcode":"9535",
    "sg:province":"K\u00e4rnten",
    "wof:name":"Putzi Emil und Christine",
    "wof:placetype":"venue"
},
  "geometry": {"coordinates":[14.0961742401,46.602809906],"type":"Point"}
}