{
  "type": "Feature",
  "properties": {
    "iso:country":"AT",
    "sg:address":"Max-Planck-Str. 1 ",
    "sg:city":"V\u00f6lkermarkt",
    "sg:classifiers":[
        {
            "category":"Autos & Motor Vehicles",
            "subcategory":"Automobile Sales",
            "type":"Retail Goods"
        }
    ],
    "sg:phone":"+43 4342 3251480",
    "sg:postcode":"9100",
    "sg:province":"K\u00e4rnten",
    "sg:tags":[
        "industrial"
    ],
    "wof:name":"DANA AUSTRIA GMBH",
    "wof:placetype":"venue"
},
  "geometry": {"coordinates":[4.1414952278,51.1644668579],"type":"Point"}
}