{
  "type": "Feature",
  "properties": {
    "addr:full":"Hauptstr 27 Hohenau an der March Nieder\u00f6sterreich 2273",
    "addr:housenumber":"27",
    "addr:postcode":"2273",
    "addr:street":"Hauptstr",
    "iso:country":"AT",
    "sg:address":"Hauptstr 27",
    "sg:city":"Hohenau an der March",
    "sg:orig_category":"Hauptschulen",
    "sg:phone":"+43 2535 2334",
    "sg:postcode":"2273",
    "sg:province":"Nieder\u00f6sterreich",
    "wof:name":"Hauptschule 1 Emil Kuntner",
    "wof:placetype":"venue"
},
  "geometry": {"coordinates":[16.9093971252,48.6092987061],"type":"Point"}
}