{
  "type": "Feature",
  "properties": {
    "addr:full":"Dominikanerg 4 Leoben Steiermark 8700",
    "addr:housenumber":"4",
    "addr:postcode":"8700",
    "addr:street":"Dominikanerg",
    "iso:country":"AT",
    "sg:address":"Dominikanerg 4",
    "sg:city":"Leoben",
    "sg:orig_category":"Friseure U Frisiersalons",
    "sg:phone":"+43 4338 4246763",
    "sg:postcode":"8700",
    "sg:province":"Steiermark",
    "wof:name":"Pr\u00e4sent & Kohlbacher OEG",
    "wof:placetype":"venue"
},
  "geometry": {"coordinates":[15.0954818726,47.3815002441],"type":"Point"}
}