{
  "type": "Feature",
  "properties": {
    "addr:full":"Negrellistr 38 Wels Ober\u00f6sterreich 4600",
    "addr:housenumber":"38",
    "addr:postcode":"4600",
    "addr:street":"Negrellistr;Oberoesterreich",
    "iso:country":"AT",
    "sg:address":"Negrellistr 38",
    "sg:city":"Wels",
    "sg:orig_category":"Anlagenbau U -Technik",
    "sg:phone":"+43 4372 42351339",
    "sg:postcode":"4600",
    "sg:province":"Ober\u00f6sterreich",
    "wof:name":"Coneco Extrusionstechnik GmbH",
    "wof:placetype":"venue"
},
  "geometry": {"coordinates":[14.0596055984,48.1635169983],"type":"Point"}
}