{
  "type": "Feature",
  "properties": {
    "addr:full":"Hamerlingstr 13 Zwettl Nieder\u00f6sterreich 3910",
    "addr:housenumber":"13",
    "addr:postcode":"3910",
    "addr:street":"Hamerlingstr;Niederoesterreich",
    "iso:country":"AT",
    "sg:address":"Hamerlingstr 13",
    "sg:city":"Zwettl",
    "sg:orig_category":"Friseurbedarf",
    "sg:phone":"+43 2822 34075",
    "sg:postcode":"3910",
    "sg:province":"Nieder\u00f6sterreich",
    "wof:name":"Maurer Robert GmbH",
    "wof:placetype":"venue"
},
  "geometry": {"coordinates":[15.1681003571,48.6041564941],"type":"Point"}
}