{
  "type": "Feature",
  "properties": {
    "iso:country":"AT",
    "sg:address":"Kartause 1",
    "sg:city":"Gaming",
    "sg:orig_category":"Institute",
    "sg:phone":"+43 7485 986780",
    "sg:postcode":"3292",
    "sg:province":"Nieder\u00f6sterreich",
    "wof:name":"Franciscan University Austrian Program",
    "wof:placetype":"venue"
},
  "geometry": {"coordinates":[15.0819988251,47.9233779907],"type":"Point"}
}