{
  "type": "Feature",
  "properties": {
    "addr:full":"Gst\u00e4tteng 11 Salzburg Salzburg 5020",
    "addr:housenumber":"11",
    "addr:postcode":"5020",
    "addr:street":"Gstaetteng;Salzburg",
    "iso:country":"AT",
    "sg:address":"Gst\u00e4tteng 11",
    "sg:city":"Salzburg",
    "sg:orig_category":"Boutiquen",
    "sg:phone":"+43 662 840940",
    "sg:postcode":"5020",
    "sg:province":"Salzburg",
    "wof:name":"Boutique Trauttenfels",
    "wof:placetype":"venue"
},
  "geometry": {"coordinates":[13.038936615,47.8006591797],"type":"Point"}
}