{
  "type": "Feature",
  "properties": {
    "addr:full":"Schillerpl 3 Wien Wien 1010",
    "addr:housenumber":"3",
    "addr:postcode":"1010",
    "addr:street":"Schillerpl",
    "iso:country":"AT",
    "sg:address":"Schillerpl 3",
    "sg:city":"Wien",
    "sg:orig_category":"Betriebs- U Fernverpflegung",
    "sg:phone":"+43 1 58816138",
    "sg:postcode":"1010",
    "sg:province":"Wien",
    "wof:name":"\u00d6sterreichische Mensen BetriebsgesmbH",
    "wof:placetype":"venue"
},
  "geometry": {"coordinates":[16.36561203,48.2015533447],"type":"Point"}
}