{
  "type": "Feature",
  "properties": {
    "iso:country":"AT",
    "sg:address":"Oberrainer Str 53",
    "sg:city":"F\u00fcrnitz",
    "sg:orig_category":"Friseure U Frisiersalons",
    "sg:phone":"+43 676 3366207",
    "sg:postcode":"9586",
    "sg:province":"K\u00e4rnten",
    "wof:name":"Mobilfriseur Bettina",
    "wof:placetype":"venue"
},
  "geometry": {"coordinates":[13.8056221008,46.5602455139],"type":"Point"}
}