{
  "type": "Feature",
  "properties": {
    "addr:full":"Kurzbauerg 3 Wien Wien 1020",
    "addr:housenumber":"3",
    "addr:postcode":"1020",
    "addr:street":"Kurzbauerg",
    "iso:country":"AT",
    "sg:address":"Kurzbauerg 3",
    "sg:city":"Wien",
    "sg:orig_category":"Non-Classified Establishments",
    "sg:phone":"+43 1 7280025",
    "sg:postcode":"1020",
    "sg:province":"Wien",
    "wof:name":"Kirche Jesu Christi der Heiligen der letzten Tage",
    "wof:placetype":"venue"
},
  "geometry": {"coordinates":[16.3958187103,48.211933136],"type":"Point"}
}