{
  "type": "Feature",
  "properties": {
    "iso:country":"AT",
    "sg:address":"Zw\u00f6lfquanten 21",
    "sg:city":"Schrattenberg",
    "sg:orig_category":"Maler, Anstreicher U Lackierer",
    "sg:phone":"+43 2555 2283",
    "sg:postcode":"2172",
    "sg:province":"Nieder\u00f6sterreich",
    "wof:name":"Leutl Manfred Ing",
    "wof:placetype":"venue"
},
  "geometry": {"coordinates":[16.7198028564,48.7233963013],"type":"Point"}
}