{
  "type": "Feature",
  "properties": {
    "addr:full":"Mitteraustr 3 Krems an der Donau Nieder\u00f6sterreich 3500",
    "addr:housenumber":"3",
    "addr:postcode":"3500",
    "addr:street":"Mitteraustr",
    "iso:country":"AT",
    "sg:address":"Mitteraustr 3",
    "sg:city":"Krems an der Donau",
    "sg:orig_category":"Handelsagenturen",
    "sg:phone":"+43 2732 85748",
    "sg:postcode":"3500",
    "sg:province":"Nieder\u00f6sterreich",
    "wof:name":"Steininger Herbert",
    "wof:placetype":"venue"
},
  "geometry": {"coordinates":[15.6150550842,48.4074287415],"type":"Point"}
}