{
  "type": "Feature",
  "properties": {
    "addr:full":"Industriezeile 36 Linz Ober\u00f6sterreich 4020",
    "addr:housenumber":"36",
    "addr:postcode":"4020",
    "addr:street":"Industriezeile",
    "iso:country":"AT",
    "sg:address":"Industriezeile 36",
    "sg:city":"Linz",
    "sg:orig_category":"Werbeagenturen",
    "sg:phone":"+43 4373 2786364",
    "sg:postcode":"4020",
    "sg:province":"Ober\u00f6sterreich",
    "wof:name":"Solidar Media Service GmbH",
    "wof:placetype":"venue"
},
  "geometry": {"coordinates":[14.3126420975,48.3130264282],"type":"Point"}
}