{
  "type": "Feature",
  "properties": {
    "addr:full":"Herrengasse 7 Graz Steiermark 8010",
    "addr:housenumber":"7",
    "addr:postcode":"8010",
    "addr:street":"Herrengasse",
    "iso:country":"AT",
    "sg:address":"Herrengasse 7",
    "sg:city":"Graz",
    "sg:classifiers":[
        {
            "category":"Professional",
            "subcategory":"Advertising",
            "type":"Services"
        }
    ],
    "sg:phone":"+43 316 8275570",
    "sg:postcode":"8010",
    "sg:province":"Steiermark",
    "sg:tags":[
        "agency"
    ],
    "wof:name":"DI Klautzer Werbe GmbH",
    "wof:placetype":"venue"
},
  "geometry": {"coordinates":[15.4394407272,47.0704536438],"type":"Point"}
}