{
  "type": "Feature",
  "properties": {
    "addr:full":"Lindenstr 18 Blindenmarkt Nieder\u00f6sterreich 3372",
    "addr:housenumber":"18",
    "addr:postcode":"3372",
    "addr:street":"Lindenstr",
    "iso:country":"AT",
    "sg:address":"Lindenstr 18",
    "sg:city":"Blindenmarkt",
    "sg:orig_category":"Volksschulen",
    "sg:phone":"+43 7473 2373",
    "sg:postcode":"3372",
    "sg:province":"Nieder\u00f6sterreich",
    "wof:name":"Volksschule",
    "wof:placetype":"venue"
},
  "geometry": {"coordinates":[14.9900808334,48.1268577576],"type":"Point"}
}