{
  "type": "Feature",
  "properties": {
    "addr:full":"Steinbachstr 63 Gamlitz Steiermark 8462",
    "addr:housenumber":"63",
    "addr:postcode":"8462",
    "addr:street":"Steinbachstr",
    "iso:country":"AT",
    "sg:address":"Steinbachstr 63",
    "sg:city":"Gamlitz",
    "sg:orig_category":"Pensionen / Privatzimmer",
    "sg:phone":"+43 4334 535922",
    "sg:postcode":"8462",
    "sg:province":"Steiermark",
    "wof:name":"Reiner Peter u Johanna",
    "wof:placetype":"venue"
},
  "geometry": {"coordinates":[15.5304460526,46.6918067932],"type":"Point"}
}