{
  "type": "Feature",
  "properties": {
    "addr:full":"Templstr 5 Innsbruck Tirol 6020",
    "addr:housenumber":"5",
    "addr:postcode":"6020",
    "addr:street":"Templstr;Tirol",
    "iso:country":"AT",
    "sg:address":"Templstr 5",
    "sg:city":"Innsbruck",
    "sg:orig_category":"Bilder",
    "sg:phone":"+43 512 5771820",
    "sg:postcode":"6020",
    "sg:province":"Tirol",
    "wof:name":"Atelier Hofinger",
    "wof:placetype":"venue"
},
  "geometry": {"coordinates":[11.3939342499,47.2603034973],"type":"Point"}
}