{
  "type": "Feature",
  "properties": {
    "addr:full":"Dorfstr 116 Niklasdorf Steiermark 8712",
    "addr:housenumber":"116",
    "addr:postcode":"8712",
    "addr:street":"Dorfstr",
    "iso:country":"AT",
    "sg:address":"Dorfstr 116",
    "sg:city":"Niklasdorf",
    "sg:orig_category":"Volksschulen",
    "sg:phone":"+43 3842 81146",
    "sg:postcode":"8712",
    "sg:province":"Steiermark",
    "wof:name":"Volksschule",
    "wof:placetype":"venue"
},
  "geometry": {"coordinates":[15.1296195984,47.4006385803],"type":"Point"}
}