{
  "type": "Feature",
  "properties": {
    "addr:full":"Atterseestr 95 Lenzing Ober\u00f6sterreich 4860",
    "addr:housenumber":"95",
    "addr:postcode":"4860",
    "addr:street":"Atterseestr",
    "iso:country":"AT",
    "sg:address":"Atterseestr 95",
    "sg:city":"Lenzing",
    "sg:orig_category":"Dachdeckereien",
    "sg:phone":"+43 7672953950",
    "sg:postcode":"4860",
    "sg:province":"Ober\u00f6sterreich",
    "wof:name":"Aigner & Anschober GesmbH",
    "wof:placetype":"venue"
},
  "geometry": {"coordinates":[13.6059017181,47.9690666199],"type":"Point"}
}