{
  "type": "Feature",
  "properties": {
    "addr:full":"Achstr. 38  Wolfurt-Bahnhof Vorarlberg 6960",
    "addr:housenumber":"38",
    "addr:postcode":"6960",
    "addr:street":"Achstr.",
    "iso:country":"AT",
    "sg:address":"Achstr. 38 ",
    "sg:city":"Wolfurt-Bahnhof",
    "sg:classifiers":[
        {
            "category":"Communications",
            "subcategory":"Newspaper",
            "type":"Services"
        }
    ],
    "sg:phone":"+43 4355 7467560",
    "sg:postcode":"6960",
    "sg:province":"Vorarlberg",
    "sg:tags":[
        "advertising"
    ],
    "wof:name":"PAWAG VERPACKUNGEN GES.MBH",
    "wof:placetype":"venue"
},
  "geometry": {"coordinates":[9.8225746155,47.4822731018],"type":"Point"}
}