{
  "type": "Feature",
  "properties": {
    "addr:full":"Lavantkai 1 Wolfsberg K\u00e4rnten 9400",
    "addr:housenumber":"1;kaernten",
    "addr:postcode":"9400",
    "addr:street":"Lavantkai",
    "iso:country":"AT",
    "sg:address":"Lavantkai 1",
    "sg:city":"Wolfsberg",
    "sg:orig_category":"Gerichte",
    "sg:phone":"+43 4352 41010",
    "sg:postcode":"9400",
    "sg:province":"K\u00e4rnten",
    "wof:name":"Bezirksgericht Wolfsberg",
    "wof:placetype":"venue"
},
  "geometry": {"coordinates":[14.8436565399,46.8383407593],"type":"Point"}
}