{
  "type": "Feature",
  "properties": {
    "addr:full":"Dorfstr 19 Wartberg im M\u00fcrztal Steiermark 8661",
    "addr:housenumber":"19",
    "addr:postcode":"8661",
    "addr:street":"Dorfstr",
    "iso:country":"AT",
    "sg:address":"Dorfstr 19",
    "sg:city":"Wartberg im M\u00fcrztal",
    "sg:orig_category":"Transportunternehmen",
    "sg:phone":"+43 3858 3562",
    "sg:postcode":"8661",
    "sg:province":"Steiermark",
    "wof:name":"Leitner Ernst",
    "wof:placetype":"venue"
},
  "geometry": {"coordinates":[15.4923820496,47.5256118774],"type":"Point"}
}