{
  "type": "Feature",
  "properties": {
    "addr:full":"D\u00f6rferstr 33 Absam Tirol 6067",
    "addr:housenumber":"33",
    "addr:postcode":"6067",
    "addr:street":"Doerferstr;Tirol",
    "iso:country":"AT",
    "sg:address":"D\u00f6rferstr 33",
    "sg:city":"Absam",
    "sg:orig_category":"Gemeinden",
    "sg:phone":"+43 5223 564890",
    "sg:postcode":"6067",
    "sg:province":"Tirol",
    "wof:name":"Gemeindeamt Absam",
    "wof:placetype":"venue"
},
  "geometry": {"coordinates":[11.5059337616,47.2951393127],"type":"Point"}
}