{
  "type": "Feature",
  "properties": {
    "addr:full":"Leonfeldner Str 87 Linz Ober\u00f6sterreich 4040",
    "addr:postcode":"4040",
    "addr:street":"Oberoesterreich",
    "iso:country":"AT",
    "sg:address":"Leonfeldner Str 87",
    "sg:city":"Linz",
    "sg:orig_category":"Installationsunternehmen",
    "sg:phone":"+43 732 7343870",
    "sg:postcode":"4040",
    "sg:province":"Ober\u00f6sterreich",
    "wof:name":"Bibl Erwin Installationen GmbH",
    "wof:placetype":"venue"
},
  "geometry": {"coordinates":[14.2860708237,48.3285980225],"type":"Point"}
}