{
  "type": "Feature",
  "properties": {
    "addr:full":"Hauptstr 37 Linz Ober\u00f6sterreich 4040",
    "addr:housenumber":"37",
    "addr:postcode":"4040",
    "addr:street":"Hauptstr",
    "iso:country":"AT",
    "sg:address":"Hauptstr 37",
    "sg:city":"Linz",
    "sg:orig_category":"Papier- U Schreibwaren / Einzelhandel",
    "sg:phone":"+43 732 731288",
    "sg:postcode":"4040",
    "sg:province":"Ober\u00f6sterreich",
    "wof:name":"Fr\u00f6ller Inh. Gerlinde Kukral",
    "wof:placetype":"venue"
},
  "geometry": {"coordinates":[14.2823019028,48.311794281],"type":"Point"}
}