{
  "type": "Feature",
  "properties": {
    "addr:full":"Manker Str 1 St. Leonhard am Forst Nieder\u00f6sterreich 3243",
    "addr:housenumber":"1",
    "addr:postcode":"3243",
    "addr:street":"Str",
    "iso:country":"AT",
    "sg:address":"Manker Str 1",
    "sg:city":"St. Leonhard am Forst",
    "sg:orig_category":"Hauptschulen",
    "sg:phone":"+43 4327 562261",
    "sg:postcode":"3243",
    "sg:province":"Nieder\u00f6sterreich",
    "wof:name":"Hauptschule St Leonhard am Forst",
    "wof:placetype":"venue"
},
  "geometry": {"coordinates":[15.2880821228,48.1398429871],"type":"Point"}
}