{
  "type": "Feature",
  "properties": {
    "iso:country":"AT",
    "sg:address":"Lerchenfelder Str 55",
    "sg:city":"Wien",
    "sg:orig_category":"Juweliere, Gold- U Silberschmiede",
    "sg:phone":"+43 1 5234283",
    "sg:postcode":"1070",
    "sg:province":"Wien",
    "wof:name":"Urban Gisela",
    "wof:placetype":"venue"
},
  "geometry": {"coordinates":[16.3482284546,48.2064437866],"type":"Point"}
}