{
  "type": "Feature",
  "properties": {
    "iso:country":"AT",
    "sg:address":"Schmalzhofg 11",
    "sg:city":"Wien",
    "sg:orig_category":"Pensionen / Privatzimmer",
    "sg:phone":"+43 1 5972935",
    "sg:postcode":"1060",
    "sg:province":"Wien",
    "wof:name":"Koller Barbara",
    "wof:placetype":"venue"
},
  "geometry": {"coordinates":[16.3462333679,48.1950721741],"type":"Point"}
}