{
  "type": "Feature",
  "properties": {
    "iso:country":"AT",
    "sg:address":"M\u00fchlau 1",
    "sg:city":"Erpfendorf",
    "sg:classifiers":[
        {
            "category":"Manufacturing",
            "subcategory":"Furniture",
            "type":"Manufacturing & Wholesale Goods"
        }
    ],
    "sg:phone":"+43 5352 8121",
    "sg:postcode":"6383",
    "sg:province":"Tirol",
    "sg:tags":[
        "bedroom"
    ],
    "sg:website":"christian-friedl.com",
    "wof:name":"Kunsttischlerei und L\u00fcftungsanlagenbau Christian Friedl GmbH",
    "wof:placetype":"venue"
},
  "geometry": {"coordinates":[12.4780540466,47.5758552551],"type":"Point"}
}