{
  "type": "Feature",
  "properties": {
    "addr:full":"Brunner Str 70 Wien Wien 1230",
    "addr:postcode":"1230",
    "addr:street":"Str 70",
    "iso:country":"AT",
    "sg:address":"Brunner Str 70",
    "sg:city":"Wien",
    "sg:orig_category":"Abbruchunternehmen",
    "sg:phone":"+43 4319 146141",
    "sg:postcode":"1230",
    "sg:province":"Wien",
    "wof:name":"Jordanits Helmut Bau- u Abbruchunternehmnung GesmbH",
    "wof:placetype":"venue"
},
  "geometry": {"coordinates":[16.2977771759,48.1321754456],"type":"Point"}
}