{
  "type": "Feature",
  "properties": {
    "iso:country":"AT",
    "sg:address":"Praterstr 61",
    "sg:city":"Wien",
    "sg:orig_category":"Telekommunikation",
    "sg:phone":"+43 1 24540232",
    "sg:postcode":"1020",
    "sg:province":"Wien",
    "wof:name":"Telephon Discount",
    "wof:placetype":"venue"
},
  "geometry": {"coordinates":[16.3891773224,48.2174415588],"type":"Point"}
}