{
  "type": "Feature",
  "properties": {
    "addr:full":"An der oberen Alten Donau 191-193 Wien Wien 1220",
    "addr:housenumber":"191-193",
    "addr:postcode":"1220",
    "addr:street":"An Der Oberen Alten Donau",
    "iso:country":"AT",
    "sg:address":"An der oberen Alten Donau 191-193",
    "sg:city":"Wien",
    "sg:orig_category":"Gastronomie- U Hotelbetriebsgesellschaften",
    "sg:phone":"+43 4312 037477",
    "sg:postcode":"1220",
    "sg:province":"Wien",
    "wof:name":"Ho-Meer Wassersport GmbH",
    "wof:placetype":"venue"
},
  "geometry": {"coordinates":[16.42694664,48.2406654358],"type":"Point"}
}