{
  "type": "Feature",
  "properties": {
    "addr:full":"Nr 2 Prinzendorf an der Zaya Nieder\u00f6sterreich 2185",
    "addr:housenumber":"2185",
    "addr:street":"Nr;An Der Zaya Niederoesterreich",
    "iso:country":"AT",
    "sg:address":"Nr 2",
    "sg:city":"Prinzendorf an der Zaya",
    "sg:orig_category":"Gutsverwaltungen",
    "sg:phone":"+43 4325 3389466",
    "sg:postcode":"2185",
    "sg:province":"Nieder\u00f6sterreich",
    "wof:name":"Gutsverwaltung Prinzendorf d Chorherrenstiftes Klosterneuburg",
    "wof:placetype":"venue"
},
  "geometry": {"coordinates":[16.7169094086,48.5999908447],"type":"Point"}
}