{
  "type": "Feature",
  "properties": {
    "addr:full":"Goethestr 1a Linz Ober\u00f6sterreich 4020",
    "addr:housenumber":"1a",
    "addr:postcode":"4020",
    "addr:street":"Goethestr",
    "iso:country":"AT",
    "sg:address":"Goethestr 1a",
    "sg:city":"Linz",
    "sg:orig_category":"Tabaktrafiken",
    "sg:phone":"+43 732 664053",
    "sg:postcode":"4020",
    "sg:province":"Ober\u00f6sterreich",
    "wof:name":"Ebner Christian",
    "wof:placetype":"venue"
},
  "geometry": {"coordinates":[14.2921199799,48.2963905334],"type":"Point"}
}