{
  "type": "Feature",
  "properties": {
    "iso:country":"AT",
    "sg:address":"Linzer Str 3",
    "sg:city":"Rohrbach in Ober\u00f6sterreich",
    "sg:orig_category":"Freizeitangebote U -Einrichtungen",
    "sg:phone":"+43 4372 896160",
    "sg:postcode":"4150",
    "sg:province":"Ober\u00f6sterreich",
    "wof:name":"Jugendzentrum Alcatraz",
    "wof:placetype":"venue"
},
  "geometry": {"coordinates":[13.9951534271,48.5746955872],"type":"Point"}
}