{
  "type": "Feature",
  "properties": {
    "addr:full":"Gatterburgg 2a Wien Wien 1190",
    "addr:housenumber":"2a",
    "addr:postcode":"1190",
    "addr:street":"Gatterburgg",
    "iso:country":"AT",
    "sg:address":"Gatterburgg 2a",
    "sg:city":"Wien",
    "sg:orig_category":"Gewerkschaften",
    "sg:phone":"+43 1 3684665",
    "sg:postcode":"1190",
    "sg:province":"Wien",
    "wof:name":"\u00d6sterreichischer Gewerkschaftsbund",
    "wof:placetype":"venue"
},
  "geometry": {"coordinates":[16.3505821228,48.2391014099],"type":"Point"}
}