{
  "type": "Feature",
  "properties": {
    "addr:full":"Valiergasse 58 Innsbruck Tirol 6020",
    "addr:housenumber":"58",
    "addr:postcode":"6020",
    "addr:street":"Valiergasse;Tirol",
    "iso:country":"AT",
    "sg:address":"Valiergasse 58",
    "sg:city":"Innsbruck",
    "sg:classifiers":[
        {
            "category":"Train Station",
            "subcategory":"Light Rail",
            "type":"Transportation"
        }
    ],
    "sg:phone":"+43 512 3415550",
    "sg:postcode":"6020",
    "sg:province":"Tirol",
    "sg:tags":[
        "insert",
        "carbide",
        "indexable"
    ],
    "sg:website":"tirotool.com",
    "wof:name":"TiroTool Werkzeugsysteme GmbH",
    "wof:placetype":"venue"
},
  "geometry": {"coordinates":[11.4399023056,47.2656707764],"type":"Point"}
}