{
  "type": "Feature",
  "properties": {
    "iso:country":"AT",
    "sg:address":"Matth\u00e4us Much-Str 1/6",
    "sg:city":"Mondsee",
    "sg:classifiers":[
        {
            "category":"Professional",
            "subcategory":"Computer Services",
            "type":"Services"
        }
    ],
    "sg:phone":"+43 6232 2784",
    "sg:postcode":"5310",
    "sg:province":"Ober\u00f6sterreich",
    "sg:tags":[
        "software"
    ],
    "wof:name":"Infony Entwicklungs- Vertriebs- und Service GmbH",
    "wof:placetype":"venue"
},
  "geometry": {"coordinates":[13.3456439972,47.8521690369],"type":"Point"}
}