{
  "type": "Feature",
  "properties": {
    "addr:full":"Wallnerstr 1 Wien Wien 1010",
    "addr:housenumber":"1",
    "addr:postcode":"1010",
    "addr:street":"Wallnerstr",
    "iso:country":"AT",
    "sg:address":"Wallnerstr 1",
    "sg:city":"Wien",
    "sg:orig_category":"Juweliere, Gold- U Silberschmiede",
    "sg:phone":"+43 1 5337878",
    "sg:postcode":"1010",
    "sg:province":"Wien",
    "wof:name":"Floschmuck",
    "wof:placetype":"venue"
},
  "geometry": {"coordinates":[16.3674106598,48.2090454102],"type":"Point"}
}