{
  "type": "Feature",
  "properties": {
    "addr:full":"Nr 25 Lofer Salzburg 5090",
    "addr:postcode":"5090",
    "addr:street":"Nr;Lofer",
    "iso:country":"AT",
    "sg:address":"Nr 25",
    "sg:city":"Lofer",
    "sg:orig_category":"Gemeinden",
    "sg:phone":"+43 4365 8882080",
    "sg:postcode":"5090",
    "sg:province":"Salzburg",
    "wof:name":"Gemeindeamt Lofer",
    "wof:placetype":"venue"
},
  "geometry": {"coordinates":[12.6930541992,47.5873069763],"type":"Point"}
}