{
  "type": "Feature",
  "properties": {
    "addr:full":"Zirkusgasse 35 Wien Wien 1020",
    "addr:housenumber":"35",
    "addr:postcode":"1020",
    "addr:street":"Zirkusgasse",
    "iso:country":"AT",
    "sg:address":"Zirkusgasse 35",
    "sg:city":"Wien",
    "sg:orig_category":"Baby Carriers",
    "sg:phone":"+43 1 2147234",
    "sg:postcode":"1020",
    "sg:province":"Wien",
    "sg:website":"easycare.at",
    "wof:name":"easycare",
    "wof:placetype":"venue"
},
  "geometry": {"coordinates":[16.3852005005,48.2173080444],"type":"Point"}
}