{
  "type": "Feature",
  "properties": {
    "addr:full":"Ameishaufen 541 Wenns Tirol 6473",
    "addr:housenumber":"541",
    "addr:postcode":"6473",
    "addr:street":"Tirol",
    "iso:country":"AT",
    "sg:address":"Ameishaufen 541",
    "sg:city":"Wenns",
    "sg:orig_category":"Pensionen / Privatzimmer",
    "sg:phone":"+43 4354 1487746",
    "sg:postcode":"6473",
    "sg:province":"Tirol",
    "wof:name":"Bauernhof Waschler",
    "wof:placetype":"venue"
},
  "geometry": {"coordinates":[10.7233657837,47.1780471802],"type":"Point"}
}