{
  "type": "Feature",
  "properties": {
    "iso:country":"AT",
    "sg:address":"Felbigerg 64",
    "sg:city":"Wien",
    "sg:orig_category":"Telekommunikation",
    "sg:phone":"+43 4319 0762820",
    "sg:postcode":"1140",
    "sg:province":"Wien",
    "wof:name":"Upcom Telekom Vertriebs GmbH",
    "wof:placetype":"venue"
},
  "geometry": {"coordinates":[16.2888374329,48.1960144043],"type":"Point"}
}