{
  "type": "Feature",
  "properties": {
    "iso:country":"AT",
    "sg:address":"Hernalser Hauptstr 213",
    "sg:city":"Wien",
    "sg:orig_category":"Werbeagenturen",
    "sg:phone":"+43 4314 8686010",
    "sg:postcode":"1170",
    "sg:province":"Wien",
    "wof:name":"Media-Consult Werbe- u AusstellungsgesmbH",
    "wof:placetype":"venue"
},
  "geometry": {"coordinates":[16.3102321625,48.2251472473],"type":"Point"}
}