{
  "type": "Feature",
  "properties": {
    "addr:full":"Dr Hans Lechner-Sdlg 4/9 Eugendorf Salzburg 5301",
    "addr:housenumber":"4 / 9",
    "addr:postcode":"5301",
    "addr:street":"Dr;Lechner-Sdlg;Salzburg",
    "iso:country":"AT",
    "sg:address":"Dr Hans Lechner-Sdlg 4/9",
    "sg:city":"Eugendorf",
    "sg:orig_category":"Handelsagenturen",
    "sg:phone":"+43 6225 2602",
    "sg:postcode":"5301",
    "sg:province":"Salzburg",
    "wof:name":"Nedelka Erika",
    "wof:placetype":"venue"
},
  "geometry": {"coordinates":[13.1293678284,47.8667984009],"type":"Point"}
}