{
  "type": "Feature",
  "properties": {
    "addr:full":"Br\u00e4uweg 60 F\u00fcgen Tirol 6263",
    "addr:housenumber":"60",
    "addr:postcode":"6263",
    "addr:street":"Braeuweg;Tirol",
    "iso:country":"AT",
    "sg:address":"Br\u00e4uweg 60",
    "sg:city":"F\u00fcgen",
    "sg:orig_category":"Fliesen U Platten",
    "sg:phone":"+43 4352 8860038",
    "sg:postcode":"6263",
    "sg:province":"Tirol",
    "wof:name":"Buttenhauser Ofen- u Fliesenstudio",
    "wof:placetype":"venue"
},
  "geometry": {"coordinates":[101.76634216310001,30.9142303467],"type":"Point"}
}