{
  "type": "Feature",
  "properties": {
    "addr:full":"Klosterwies 12 Graz Steiermark 8010",
    "addr:housenumber":"12",
    "addr:postcode":"8010",
    "addr:street":"Klosterwies",
    "iso:country":"AT",
    "sg:address":"Klosterwies 12",
    "sg:city":"Graz",
    "sg:orig_category":"Biologische Produkte",
    "sg:phone":"+43 4331 6816945",
    "sg:postcode":"8010",
    "sg:province":"Steiermark",
    "wof:name":"Harich Roswitha - Naturkosmetik",
    "wof:placetype":"venue"
},
  "geometry": {"coordinates":[15.4434270859,47.0663032532],"type":"Point"}
}