{
  "type": "Feature",
  "properties": {
    "iso:country":"AT",
    "sg:address":"Nr 73",
    "sg:city":"Heidenreichstein",
    "sg:classifiers":[
        {
            "category":"Government",
            "subcategory":"Post Office",
            "type":"Public Place"
        }
    ],
    "sg:phone":"+43 4328 6253100",
    "sg:postcode":"3860",
    "sg:province":"Nieder\u00f6sterreich",
    "sg:tags":[
        "-handel",
        "tierzucht",
        "u"
    ],
    "wof:name":"Pfeiffer Anni Dr",
    "wof:placetype":"venue"
},
  "geometry": {"coordinates":[15.111869812,48.861869812],"type":"Point"}
}