{
  "type": "Feature",
  "properties": {
    "iso:country":"AT",
    "sg:address":"Stefan-Ludwig-Roth-Str 31",
    "sg:city":"Salzburg",
    "sg:classifiers":[
        {
            "category":"Professional",
            "subcategory":"Computer Services",
            "type":"Services"
        }
    ],
    "sg:phone":"+43 4366 2833185",
    "sg:postcode":"5020",
    "sg:province":"Salzburg",
    "sg:tags":[
        "software"
    ],
    "wof:name":"Strapetz Marc",
    "wof:placetype":"venue"
},
  "geometry": {"coordinates":[13.0370874405,47.7643432617],"type":"Point"}
}