{
  "type": "Feature",
  "properties": {
    "addr:full":"Joseph-Haydn-Gasse 29 Breitenbrunn Burgenland 7091",
    "addr:housenumber":"29",
    "addr:postcode":"7091",
    "addr:street":"Joseph-Haydn-Gasse",
    "iso:country":"AT",
    "sg:address":"Joseph-Haydn-Gasse 29",
    "sg:city":"Breitenbrunn",
    "sg:classifiers":[
        {
            "category":"Home & Garden",
            "subcategory":"Mobile Homes",
            "type":"Retail Goods"
        }
    ],
    "sg:phone":"+43 2682 67281",
    "sg:postcode":"7091",
    "sg:province":"Burgenland",
    "sg:tags":[
        "awning",
        "outdoor",
        "marquee"
    ],
    "sg:website":"hubacek.at",
    "wof:name":"Hubacek Markisen, Roladen, Sonnenschutz",
    "wof:placetype":"venue"
},
  "geometry": {"coordinates":[16.7357215881,47.9446907043],"type":"Point"}
}