{
  "type": "Feature",
  "properties": {
    "addr:full":"Albert Hejpeterg. 21 Gro\u00df-Enzersdorf Nieder\u00f6sterreich 2301",
    "addr:housenumber":"21;2301",
    "addr:street":"Gross-Enzersdorf Niederoesterreich",
    "iso:country":"AT",
    "sg:address":"Albert Hejpeterg. 21",
    "sg:city":"Gro\u00df-Enzersdorf",
    "sg:orig_category":"Dienstleistungen, Fotografie, Grafik U Design",
    "sg:phone":"+43 2249",
    "sg:postcode":"2301",
    "sg:province":"Nieder\u00f6sterreich",
    "sg:website":"http://www.kurt-kracher.at",
    "wof:name":"Kurt Kracher - Tier, und Naturfotografie",
    "wof:placetype":"venue"
},
  "geometry": {"coordinates":[16.542766571,48.1962471008],"type":"Point"}
}