{
  "type": "Feature",
  "properties": {
    "addr:full":"Untere Dorfstr 35 Serfaus Tirol 6534",
    "addr:housenumber":"35",
    "addr:postcode":"6534",
    "addr:street":"Untere Dorfstr;Tirol",
    "iso:country":"AT",
    "sg:address":"Untere Dorfstr 35",
    "sg:city":"Serfaus",
    "sg:classifiers":[
        {
            "category":"Travel",
            "subcategory":"Hotels & Motels",
            "type":"Entertainment"
        }
    ],
    "sg:phone":"+43 5476 62010",
    "sg:postcode":"6534",
    "sg:province":"Tirol",
    "wof:name":"Familienhotel Furgler",
    "wof:placetype":"venue"
},
  "geometry": {"coordinates":[10.604850769,47.0384483337],"type":"Point"}
}