{
  "type": "Feature",
  "properties": {
    "addr:full":"Grazer Str 24 Fehring Steiermark 8350",
    "addr:housenumber":"24",
    "addr:postcode":"8350",
    "addr:street":"Str",
    "iso:country":"AT",
    "sg:address":"Grazer Str 24",
    "sg:city":"Fehring",
    "sg:orig_category":"Autohandel",
    "sg:phone":"+43 4331 5524240",
    "sg:postcode":"8350",
    "sg:province":"Steiermark",
    "sg:website":"peugeot-kalcher.at",
    "wof:name":"Kalcher Autohaus GesmbH",
    "wof:placetype":"venue"
},
  "geometry": {"coordinates":[16.0047950745,46.9374351501],"type":"Point"}
}