{
  "type": "Feature",
  "properties": {
    "iso:country":"AT",
    "sg:address":"Schie\u00dfstandweg 1",
    "sg:city":"Kundl",
    "sg:orig_category":"Installationsunternehmen",
    "sg:phone":"+43 5338 7345",
    "sg:postcode":"6250",
    "sg:province":"Tirol",
    "wof:name":"Hauswitzka Installationen GesmbH & Co KG",
    "wof:placetype":"venue"
},
  "geometry": {"coordinates":[11.9895610809,47.4665756226],"type":"Point"}
}