{
  "type": "Feature",
  "properties": {
    "addr:full":"Leobersdorfer Strasse 18 G\u00fcnselsdorf Nieder\u00f6sterreich 2525",
    "addr:housenumber":"18",
    "addr:postcode":"2525",
    "addr:street":"Leobersdorfer Strasse;Niederoesterreich",
    "iso:country":"AT",
    "sg:address":"Leobersdorfer Strasse 18",
    "sg:city":"G\u00fcnselsdorf",
    "sg:classifiers":[
        {
            "category":"Banks & Credit Unions",
            "subcategory":"Investment Brokerage",
            "type":"Services"
        }
    ],
    "sg:phone":"+43 2253 80284",
    "sg:postcode":"2525",
    "sg:province":"Nieder\u00f6sterreich",
    "sg:tags":[
        "fork",
        "lift",
        "truck",
        "electric"
    ],
    "sg:website":"gabelstapler.at",
    "wof:name":"Schwarzer Gabelstapler",
    "wof:placetype":"venue"
},
  "geometry": {"coordinates":[7.4943199158,50.8699913025],"type":"Point"}
}