{
  "type": "Feature",
  "properties": {
    "addr:full":"Siccardsburgg 44 Wien Wien 1100",
    "addr:housenumber":"44",
    "addr:postcode":"1100",
    "addr:street":"Siccardsburgg",
    "iso:country":"AT",
    "sg:address":"Siccardsburgg 44",
    "sg:city":"Wien",
    "sg:orig_category":"Transportunternehmen",
    "sg:phone":"+43 664 1245678",
    "sg:postcode":"1100",
    "sg:province":"Wien",
    "wof:name":"Jager Lin",
    "wof:placetype":"venue"
},
  "geometry": {"coordinates":[16.3702430725,48.1739654541],"type":"Point"}
}