{
  "type": "Feature",
  "properties": {
    "iso:country":"AT",
    "sg:address":"Am Riedelwald 25",
    "sg:city":"Seekirchen am Wallersee",
    "sg:orig_category":"Fenster",
    "sg:phone":"+43 664 3200959",
    "sg:postcode":"5201",
    "sg:province":"Salzburg",
    "wof:name":"MEA Meisinger GesmbH",
    "wof:placetype":"venue"
},
  "geometry": {"coordinates":[13.120259285,47.9085006714],"type":"Point"}
}