{
  "type": "Feature",
  "properties": {
    "addr:full":"Stilles Tal St. P\u00f6lten Nieder\u00f6sterreich 3100",
    "addr:postcode":"3100",
    "addr:street":"Tal St.",
    "iso:country":"AT",
    "sg:address":"Stilles Tal",
    "sg:city":"St. P\u00f6lten",
    "sg:orig_category":"Hobbyvereine",
    "sg:phone":"+43 2742 70721",
    "sg:postcode":"3100",
    "sg:province":"Nieder\u00f6sterreich",
    "wof:name":"Erster Billard Club St P\u00f6lten",
    "wof:placetype":"venue"
},
  "geometry": {"coordinates":[15.6240940094,48.2076377869],"type":"Point"}
}