{
  "type": "Feature",
  "properties": {
    "addr:full":"Hauptstr 5 Wartberg ob der Aist Ober\u00f6sterreich 4224",
    "addr:housenumber":"5",
    "addr:postcode":"4224",
    "addr:street":"Hauptstr",
    "iso:country":"AT",
    "sg:address":"Hauptstr 5",
    "sg:city":"Wartberg ob der Aist",
    "sg:orig_category":"Gemeinden",
    "sg:phone":"+43 4372 3637000",
    "sg:postcode":"4224",
    "sg:province":"Ober\u00f6sterreich",
    "wof:name":"Marktgemeinde Wartberg ob der Aist",
    "wof:placetype":"venue"
},
  "geometry": {"coordinates":[14.5085382462,48.3481750488],"type":"Point"}
}