{
  "type": "Feature",
  "properties": {
    "iso:country":"AT",
    "sg:address":"Raphael-Donner-Str 4a",
    "sg:city":"Leonding",
    "sg:orig_category":"Juwelen, Gold- U Silberwaren / Einzelhandel",
    "sg:phone":"+43 4373 2678700",
    "sg:postcode":"4060",
    "sg:province":"Ober\u00f6sterreich",
    "wof:name":"Schmuck-St\u00fccke Herbert Gnadlinger",
    "wof:placetype":"venue"
},
  "geometry": {"coordinates":[14.2510786057,48.2800216675],"type":"Point"}
}