{
  "type": "Feature",
  "properties": {
    "iso:country":"AT",
    "sg:address":"Falkensteinstrasse 40b",
    "sg:city":"Schwaz",
    "sg:classifiers":[
        {
            "category":"Wholesale",
            "subcategory":"Beer",
            "type":"Manufacturing & Wholesale Goods"
        }
    ],
    "sg:phone":"+43 5242 72451",
    "sg:postcode":"6130",
    "sg:province":"Tirol",
    "sg:website":"spirit-of-hanf.com",
    "wof:name":"Andreas Kreutner HandelsgmbH",
    "wof:placetype":"venue"
},
  "geometry": {"coordinates":[11.7161474228,47.3496742249],"type":"Point"}
}