{
  "type": "Feature",
  "properties": {
    "addr:full":"Bacherstr 218 Hirm Burgenland 7024",
    "addr:housenumber":"218",
    "addr:postcode":"7024",
    "iso:country":"AT",
    "sg:address":"Bacherstr 218",
    "sg:city":"Hirm",
    "sg:orig_category":"Fliesen U Platten",
    "sg:phone":"+43 4326 8747254",
    "sg:postcode":"7024",
    "sg:province":"Burgenland",
    "wof:name":"Pfeiler Georg Ing & Co GmbH",
    "wof:placetype":"venue"
},
  "geometry": {"coordinates":[16.4570045471,47.785785675],"type":"Point"}
}