{
  "type": "Feature",
  "properties": {
    "addr:full":"Bachg 7 Leopoldsdorf im Marchfelde Nieder\u00f6sterreich 2285",
    "addr:housenumber":"7",
    "addr:postcode":"2285",
    "addr:street":"Bachg",
    "iso:country":"AT",
    "sg:address":"Bachg 7",
    "sg:city":"Leopoldsdorf im Marchfelde",
    "sg:orig_category":"Bauunternehmen",
    "sg:phone":"+43 2216 2449",
    "sg:postcode":"2285",
    "sg:province":"Nieder\u00f6sterreich",
    "wof:name":"Ivanics Bauunternehmung GesmbH",
    "wof:placetype":"venue"
},
  "geometry": {"coordinates":[16.7001113892,48.2356452942],"type":"Point"}
}