{
  "type": "Feature",
  "properties": {
    "addr:full":"Paris Lodron-Str 3A Salzburg Salzburg 5020",
    "addr:housenumber":"3a",
    "addr:postcode":"5020",
    "addr:street":"Salzburg",
    "iso:country":"AT",
    "sg:address":"Paris Lodron-Str 3A",
    "sg:city":"Salzburg",
    "sg:orig_category":"Telekommunikation",
    "sg:phone":"+43 662 878888",
    "sg:postcode":"5020",
    "sg:province":"Salzburg",
    "wof:name":"Elcotronic elektrotechnische Daten- und Telekommunikations GesmbH",
    "wof:placetype":"venue"
},
  "geometry": {"coordinates":[13.0446949005,47.8048019409],"type":"Point"}
}