{
  "type": "Feature",
  "properties": {
    "addr:full":"Nr 58 Bad Waltersdorf Steiermark 8271",
    "addr:housenumber":"58",
    "addr:postcode":"8271",
    "addr:street":"Nr",
    "iso:country":"AT",
    "sg:address":"Nr 58",
    "sg:city":"Bad Waltersdorf",
    "sg:classifiers":[
        {
            "category":"Travel",
            "subcategory":"Hotels & Motels",
            "type":"Entertainment"
        }
    ],
    "sg:phone":"+43 4333 3322730",
    "sg:postcode":"8271",
    "sg:province":"Steiermark",
    "wof:name":"Hotel-Restaurant Fischer",
    "wof:placetype":"venue"
},
  "geometry": {"coordinates":[16.0086784363,47.1696166992],"type":"Point"}
}