{
  "type": "Feature",
  "properties": {
    "addr:full":"Nr 2 Kukmirn Burgenland 7543",
    "addr:postcode":"7543",
    "addr:street":"Nr",
    "iso:country":"AT",
    "sg:address":"Nr 2",
    "sg:city":"Kukmirn",
    "sg:orig_category":"Non-Classified Establishments",
    "sg:phone":"+43 3328 32767",
    "sg:postcode":"7543",
    "sg:province":"Burgenland",
    "wof:name":"Evangelische Pfarrgemeinde AB",
    "wof:placetype":"venue"
},
  "geometry": {"coordinates":[16.2055358887,47.072227478],"type":"Point"}
}