{
  "type": "Feature",
  "properties": {
    "addr:full":"Wasserg 11 Wien Wien 1030",
    "addr:housenumber":"11",
    "addr:postcode":"1030",
    "addr:street":"Wasserg",
    "iso:country":"AT",
    "sg:address":"Wasserg 11",
    "sg:city":"Wien",
    "sg:orig_category":"Schilder",
    "sg:phone":"+43 4317 108900",
    "sg:postcode":"1030",
    "sg:province":"Wien",
    "sg:website":"schilderundbilder.com",
    "wof:name":"Bauer Kurt",
    "wof:placetype":"venue"
},
  "geometry": {"coordinates":[16.3961448669,48.2015228271],"type":"Point"}
}