{
  "type": "Feature",
  "properties": {
    "iso:country":"AT",
    "sg:address":"Pillersdorfg 8/1",
    "sg:city":"Wien",
    "sg:orig_category":"Dachdeckereien",
    "sg:phone":"+43 1 3339898",
    "sg:postcode":"1020",
    "sg:province":"Wien",
    "wof:name":"The Roof Dachdeckerei Rohacek Richard",
    "wof:placetype":"venue"
},
  "geometry": {"coordinates":[16.3852043152,48.2199516296],"type":"Point"}
}