{
  "type": "Feature",
  "properties": {
    "addr:full":"Terlacher Str 19 Wernberg K\u00e4rnten 9241",
    "addr:housenumber":"9241",
    "addr:street":"Str",
    "iso:country":"AT",
    "sg:address":"Terlacher Str 19",
    "sg:city":"Wernberg",
    "sg:orig_category":"Lebensmittel / Einzelhandel",
    "sg:phone":"+43 4252 2110",
    "sg:postcode":"9241",
    "sg:province":"K\u00e4rnten",
    "wof:name":"Happe Kaufhaus - Ambrosch Sabine",
    "wof:placetype":"venue"
},
  "geometry": {"coordinates":[13.9766139984,46.6173095703],"type":"Point"}
}