{
  "type": "Feature",
  "properties": {
    "addr:full":"Goldbergg 20 Neusiedl am See Burgenland 7100",
    "addr:housenumber":"20",
    "addr:postcode":"7100",
    "addr:street":"Goldbergg",
    "iso:country":"AT",
    "sg:address":"Goldbergg 20",
    "sg:city":"Neusiedl am See",
    "sg:orig_category":"Appartements / Ferienwohnungen",
    "sg:phone":"+43 4321 675069",
    "sg:postcode":"7100",
    "sg:province":"Burgenland",
    "wof:name":"LA GALLERIA Appartement",
    "wof:placetype":"venue"
},
  "geometry": {"coordinates":[16.8358917236,47.9545288086],"type":"Point"}
}