{
  "type": "Feature",
  "properties": {
    "addr:full":"Mauritzener Hauptstr 8 Frohnleiten Steiermark 8130",
    "addr:housenumber":"8",
    "addr:postcode":"8130",
    "addr:street":"Mauritzener Hauptstr",
    "iso:country":"AT",
    "sg:address":"Mauritzener Hauptstr 8",
    "sg:city":"Frohnleiten",
    "sg:orig_category":"Tabaktrafiken",
    "sg:phone":"+43 3126 2826",
    "sg:postcode":"8130",
    "sg:province":"Steiermark",
    "wof:name":"Novati Anna",
    "wof:placetype":"venue"
},
  "geometry": {"coordinates":[15.3262214661,47.2668647766],"type":"Point"}
}