{
  "type": "Feature",
  "properties": {
    "addr:full":"Sillufer 11 Innsbruck Tirol 6020",
    "addr:housenumber":"11",
    "addr:postcode":"6020",
    "addr:street":"Sillufer;Tirol",
    "iso:country":"AT",
    "sg:address":"Sillufer 11",
    "sg:city":"Innsbruck",
    "sg:orig_category":"Automaten",
    "sg:phone":"+43 512 360161",
    "sg:postcode":"6020",
    "sg:province":"Tirol",
    "wof:name":"Wurzer Siegfried",
    "wof:placetype":"venue"
},
  "geometry": {"coordinates":[11.4043226242,47.256778717],"type":"Point"}
}