{
  "type": "Feature",
  "properties": {
    "addr:full":"Hauptstr 42 Waldegg an der Piesting Nieder\u00f6sterreich 2754",
    "addr:housenumber":"42",
    "addr:postcode":"2754",
    "addr:street":"Hauptstr",
    "iso:country":"AT",
    "sg:address":"Hauptstr 42",
    "sg:city":"Waldegg an der Piesting",
    "sg:orig_category":"Bankomat-Standorte",
    "sg:phone":"+43 2633 42497",
    "sg:postcode":"2754",
    "sg:province":"Nieder\u00f6sterreich",
    "wof:name":"Bankomat d 2754 Waldegg an der Piesting",
    "wof:placetype":"venue"
},
  "geometry": {"coordinates":[16.0579948425,47.8691902161],"type":"Point"}
}