{
  "type": "Feature",
  "properties": {
    "addr:full":"Kircheng 25 Wien Wien 1070",
    "addr:housenumber":"25",
    "addr:postcode":"1070",
    "addr:street":"Kircheng",
    "iso:country":"AT",
    "sg:address":"Kircheng 25",
    "sg:city":"Wien",
    "sg:orig_category":"Boutiquen",
    "sg:phone":"+43 1 5240809",
    "sg:postcode":"1070",
    "sg:province":"Wien",
    "wof:name":"Chactun-Cyber Store",
    "wof:placetype":"venue"
},
  "geometry": {"coordinates":[16.3514595032,48.2025146484],"type":"Point"}
}