{
  "type": "Feature",
  "properties": {
    "addr:full":"Aschauer Str 28 Kirchberg in Tirol Tirol 6365",
    "addr:housenumber":"28",
    "addr:postcode":"6365",
    "addr:street":"Str;Tirol",
    "iso:country":"AT",
    "sg:address":"Aschauer Str 28",
    "sg:city":"Kirchberg in Tirol",
    "sg:classifiers":[
        {
            "category":"Travel",
            "subcategory":"Hotels & Motels",
            "type":"Entertainment"
        }
    ],
    "sg:phone":"+43 4353 572973",
    "sg:postcode":"6365",
    "sg:province":"Tirol",
    "wof:name":"Appartement-Hotel Almhof - Marcel Sore",
    "wof:placetype":"venue"
},
  "geometry": {"coordinates":[12.3196754456,47.4376296997],"type":"Point"}
}