{
  "type": "Feature",
  "properties": {
    "addr:full":"Gatterederstr. 4  Wien Wien 1230",
    "addr:housenumber":"4",
    "addr:postcode":"1230",
    "addr:street":"Gatterederstr.",
    "iso:country":"AT",
    "sg:address":"Gatterederstr. 4 ",
    "sg:city":"Wien",
    "sg:classifiers":[
        {
            "category":"Sports & Exercise",
            "subcategory":"Playing Field",
            "type":"Entertainment"
        }
    ],
    "sg:phone":"+43 4318 882287",
    "sg:postcode":"1230",
    "sg:province":"Wien",
    "sg:tags":[
        "game"
    ],
    "wof:name":"KLEINBAHN ING. ERICH KLEIN",
    "wof:placetype":"venue"
},
  "geometry": {"coordinates":[16.2901344299,48.1526031494],"type":"Point"}
}