{
  "type": "Feature",
  "properties": {
    "iso:country":"AT",
    "sg:address":"Rauth 26",
    "sg:city":"Keutschach",
    "sg:orig_category":"Autohandel",
    "sg:phone":"+43 4273 3230",
    "sg:postcode":"9074",
    "sg:province":"K\u00e4rnten",
    "wof:name":"Murko Klaus",
    "wof:placetype":"venue"
},
  "geometry": {"coordinates":[14.1858158112,46.5947608948],"type":"Point"}
}