{
  "type": "Feature",
  "properties": {
    "iso:country":"AT",
    "sg:address":"Parkstr 13",
    "sg:city":"F\u00fcrstenfeld",
    "sg:orig_category":"Massagen",
    "sg:phone":"+43 4366 03403633",
    "sg:postcode":"8280",
    "sg:province":"Steiermark",
    "wof:name":"Erregger Margret - Heilmassage-Praxis",
    "wof:placetype":"venue"
},
  "geometry": {"coordinates":[9.1764993668,47.6480064392],"type":"Point"}
}