{
  "type": "Feature",
  "properties": {
    "addr:full":"Wiener G 108 Perchtoldsdorf Nieder\u00f6sterreich 2380",
    "addr:housenumber":"108",
    "addr:postcode":"2380",
    "addr:street":"Wiener G",
    "iso:country":"AT",
    "sg:address":"Wiener G 108",
    "sg:city":"Perchtoldsdorf",
    "sg:orig_category":"Autohandel",
    "sg:phone":"+43 1 86593590",
    "sg:postcode":"2380",
    "sg:province":"Nieder\u00f6sterreich",
    "wof:name":"Bauer & Mohrenberger GesmbH",
    "wof:placetype":"venue"
},
  "geometry": {"coordinates":[16.2745246887,48.1265296936],"type":"Point"}
}