{
  "type": "Feature",
  "properties": {
    "addr:full":"Braunauer Str 3a Ried im Innkreis Ober\u00f6sterreich 4910",
    "addr:postcode":"4910",
    "addr:street":"Str 3A",
    "iso:country":"AT",
    "sg:address":"Braunauer Str 3a",
    "sg:city":"Ried im Innkreis",
    "sg:orig_category":"Beschriftungen",
    "sg:phone":"+43 7752 71462",
    "sg:postcode":"4910",
    "sg:province":"Ober\u00f6sterreich",
    "wof:name":"Pfeil-Design",
    "wof:placetype":"venue"
},
  "geometry": {"coordinates":[13.4828023911,48.2058258057],"type":"Point"}
}