{
  "type": "Feature",
  "properties": {
    "addr:full":"Nr 78 Thiersee Tirol 6335",
    "addr:postcode":"6335",
    "addr:street":"Nr 78;Tirol",
    "iso:country":"AT",
    "sg:address":"Nr 78",
    "sg:city":"Thiersee",
    "sg:orig_category":"Volksschulen",
    "sg:phone":"+43 5376 55274",
    "sg:postcode":"6335",
    "sg:province":"Tirol",
    "wof:name":"Volksschule",
    "wof:placetype":"venue"
},
  "geometry": {"coordinates":[12.0649995804,47.584148407],"type":"Point"}
}