{
  "type": "Feature",
  "properties": {
    "iso:country":"AT",
    "sg:address":"Rudolf-Hans-Bartsch-Str 22",
    "sg:city":"St. Peter",
    "sg:orig_category":"Ingenieurkonsulenten / Zivilingenieure",
    "sg:phone":"+43 4331 64655270",
    "sg:postcode":"8042",
    "sg:province":"Steiermark",
    "wof:name":"Baumkirchner Gerhard Dipl-Ing",
    "wof:placetype":"venue"
},
  "geometry": {"coordinates":[15.468670845,47.0561943054],"type":"Point"}
}