{
  "type": "Feature",
  "properties": {
    "addr:full":"Kirchg 18 St. Veit an der Glan K\u00e4rnten 9300",
    "addr:housenumber":"18",
    "addr:postcode":"9300",
    "addr:street":"Kirchg;Kaernten",
    "iso:country":"AT",
    "sg:address":"Kirchg 18",
    "sg:city":"St. Veit an der Glan",
    "sg:orig_category":"Psychologen",
    "sg:phone":"+43 4212 45050",
    "sg:postcode":"9300",
    "sg:province":"K\u00e4rnten",
    "wof:name":"Germadnik Manfred Mag",
    "wof:placetype":"venue"
},
  "geometry": {"coordinates":[14.3586864471,46.7663993835],"type":"Point"}
}