{
  "type": "Feature",
  "properties": {
    "addr:full":"10.-Oktober-Strasse 20a Spittal an der Drau K\u00e4rnten 9800",
    "addr:housenumber":"20a",
    "addr:postcode":"9800",
    "addr:street":"10.-Oktober-Strasse;Kaernten",
    "iso:country":"AT",
    "sg:address":"10.-Oktober-Strasse 20a",
    "sg:city":"Spittal an der Drau",
    "sg:classifiers":[
        {
            "category":"Communications",
            "subcategory":"Television Station",
            "type":"Services"
        }
    ],
    "sg:phone":"+43 4762 2314",
    "sg:postcode":"9800",
    "sg:province":"K\u00e4rnten",
    "sg:tags":[
        "set",
        "radio",
        "cable",
        "antenna"
    ],
    "wof:name":"Ernst Neunegger",
    "wof:placetype":"venue"
},
  "geometry": {"coordinates":[13.486869812,46.8216552734],"type":"Point"}
}