{
  "type": "Feature",
  "properties": {
    "iso:country":"AT",
    "sg:address":"Waldweg 116",
    "sg:city":"G\u00f6sting",
    "sg:orig_category":"Maler, Anstreicher U Lackierer",
    "sg:phone":"+43 4331 6672833",
    "sg:postcode":"8051",
    "sg:province":"Steiermark",
    "wof:name":"Schimpel GesmbH Malerbetrieb",
    "wof:placetype":"venue"
},
  "geometry": {"coordinates":[15.3692340851,47.1161766052],"type":"Point"}
}