{
  "type": "Feature",
  "properties": {
    "addr:full":"Ro\u00dflach 376 Umhausen Tirol 6441",
    "addr:housenumber":"376",
    "addr:postcode":"6441",
    "addr:street":"Rosslach;Tirol",
    "iso:country":"AT",
    "sg:address":"Ro\u00dflach 376",
    "sg:city":"Umhausen",
    "sg:orig_category":"Appartements / Ferienwohnungen",
    "sg:phone":"+43 4352 555605",
    "sg:postcode":"6441",
    "sg:province":"Tirol",
    "wof:name":"Domenig Hanni",
    "wof:placetype":"venue"
},
  "geometry": {"coordinates":[10.9276542664,47.1393241882],"type":"Point"}
}