{
  "type": "Feature",
  "properties": {
    "iso:country":"AT",
    "sg:address":"Zwettler Strasse 1a",
    "sg:city":"Horn",
    "sg:classifiers":[
        {
            "category":"Real Estate",
            "subcategory":"Developer",
            "type":"Services"
        }
    ],
    "sg:phone":"+43 2982 31110",
    "sg:postcode":"3580",
    "sg:province":"Nieder\u00f6sterreich",
    "sg:tags":[
        "development",
        "project",
        "industry",
        "construction"
    ],
    "sg:website":"members.aon.at/kamptal",
    "wof:name":"Gemeinn\u00fctzige Wohnbauges. KAMPTAL GmbH",
    "wof:placetype":"venue"
},
  "geometry": {"coordinates":[15.6523427963,48.6609420776],"type":"Point"}
}