{
  "type": "Feature",
  "properties": {
    "addr:full":"Gerberg 2 Stockerau Nieder\u00f6sterreich 2000",
    "addr:housenumber":"2",
    "addr:postcode":"2000",
    "addr:street":"Gerberg",
    "iso:country":"AT",
    "sg:address":"Gerberg 2",
    "sg:city":"Stockerau",
    "sg:orig_category":"Innenausbau",
    "sg:phone":"+43 2266 6050",
    "sg:postcode":"2000",
    "sg:province":"Nieder\u00f6sterreich",
    "sg:website":"frischeis.at",
    "wof:name":"Frischeis J & A GesmbH",
    "wof:placetype":"venue"
},
  "geometry": {"coordinates":[16.2181282043,48.3832817078],"type":"Point"}
}