{
  "type": "Feature",
  "properties": {
    "iso:country":"AT",
    "sg:address":"Herzmanovsky-Orlando-G 1",
    "sg:city":"Wien",
    "sg:orig_category":"\u00c3\u201erzte / F Allgemeinmedizin",
    "sg:phone":"+43 4312 598355",
    "sg:postcode":"1210",
    "sg:province":"Wien",
    "wof:name":"Bauer Christian Dr",
    "wof:placetype":"venue"
},
  "geometry": {"coordinates":[16.4510574341,48.2690048218],"type":"Point"}
}