{
  "type": "Feature",
  "properties": {
    "iso:country":"AT",
    "sg:address":"Dorfpl 533",
    "sg:city":"Saalbach",
    "sg:classifiers":[
        {
            "category":"Park",
            "subcategory":"Provincial",
            "type":"Public Place"
        }
    ],
    "sg:phone":"+43 4365 41668256",
    "sg:postcode":"5753",
    "sg:province":"Salzburg",
    "sg:tags":[
        "u",
        "ski-",
        "snowboardschulen"
    ],
    "wof:name":"Snowacademy Aamadall",
    "wof:placetype":"venue"
},
  "geometry": {"coordinates":[12.6368951797,47.3900032043],"type":"Point"}
}