{
  "type": "Feature",
  "properties": {
    "addr:full":"Spinng 19 Apetlon Burgenland 7143",
    "addr:housenumber":"19",
    "addr:postcode":"7143",
    "addr:street":"Spinng",
    "iso:country":"AT",
    "sg:address":"Spinng 19",
    "sg:city":"Apetlon",
    "sg:orig_category":"Appartements / Ferienwohnungen",
    "sg:phone":"+43 2175 2834",
    "sg:postcode":"7143",
    "sg:province":"Burgenland",
    "wof:name":"Wegleitner Gertrude",
    "wof:placetype":"venue"
},
  "geometry": {"coordinates":[16.8273429871,47.7472496033],"type":"Point"}
}