{
  "type": "Feature",
  "properties": {
    "addr:full":"Ruster Str 86-104 Eisenstadt Burgenland 7000",
    "addr:postcode":"86-104;7000",
    "addr:street":"Str",
    "iso:country":"AT",
    "sg:address":"Ruster Str 86-104",
    "sg:city":"Eisenstadt",
    "sg:orig_category":"Friseurbedarf",
    "sg:phone":"+43 2682 62641",
    "sg:postcode":"7000",
    "sg:province":"Burgenland",
    "wof:name":"Maurer Robert GmbH",
    "wof:placetype":"venue"
},
  "geometry": {"coordinates":[16.5287532806,47.8358955383],"type":"Point"}
}