{
  "type": "Feature",
  "properties": {
    "iso:country":"AT",
    "sg:address":"Wolfa 3",
    "sg:city":"Glanegg",
    "sg:orig_category":"Pensionen / Privatzimmer",
    "sg:phone":"+43 4277 2240",
    "sg:postcode":"9555",
    "sg:province":"K\u00e4rnten",
    "wof:name":"Matlhof",
    "wof:placetype":"venue"
},
  "geometry": {"coordinates":[14.2108659744,46.7163887024],"type":"Point"}
}