{
  "type": "Feature",
  "properties": {
    "addr:full":"Nr 33 Schwanberg Steiermark 8541",
    "addr:postcode":"8541",
    "addr:street":"Nr",
    "iso:country":"AT",
    "sg:address":"Nr 33",
    "sg:city":"Schwanberg",
    "sg:orig_category":"Volksschulen",
    "sg:phone":"+43 3467 7530",
    "sg:postcode":"8541",
    "sg:province":"Steiermark",
    "wof:name":"Volksschule",
    "wof:placetype":"venue"
},
  "geometry": {"coordinates":[15.2004699707,46.7570381165],"type":"Point"}
}