{
  "type": "Feature",
  "properties": {
    "addr:full":"Burgg 31 Wien Wien 1070",
    "addr:housenumber":"31",
    "addr:postcode":"1070",
    "addr:street":"Burgg",
    "iso:country":"AT",
    "sg:address":"Burgg 31",
    "sg:city":"Wien",
    "sg:orig_category":"Schilder",
    "sg:phone":"+43 1 5237140",
    "sg:postcode":"1070",
    "sg:province":"Wien",
    "sg:website":"www.siegwart.at",
    "wof:name":"Siegwart G\u00fcnter Schilder-Kennzeichnungen",
    "wof:placetype":"venue"
},
  "geometry": {"coordinates":[16.3528518677,48.2041893005],"type":"Point"}
}