{
  "type": "Feature",
  "properties": {
    "addr:full":"Niederndorfer Str 2 Erlauf Nieder\u00f6sterreich 3253",
    "addr:housenumber":"2",
    "addr:postcode":"3253",
    "addr:street":"Niederndorfer Str;Niederoesterreich",
    "iso:country":"AT",
    "sg:address":"Niederndorfer Str 2",
    "sg:city":"Erlauf",
    "sg:orig_category":"Banken U Sparkassen",
    "sg:phone":"+43 4327 576281",
    "sg:postcode":"3253",
    "sg:province":"Nieder\u00f6sterreich",
    "wof:name":"Raiffeisenbank Region Melk regGenmbH",
    "wof:placetype":"venue"
},
  "geometry": {"coordinates":[15.1842756271,48.1824455261],"type":"Point"}
}