{
  "type": "Feature",
  "properties": {
    "addr:full":"Exlg 37/1 Innsbruck Tirol 6020",
    "addr:housenumber":"37 / 1",
    "addr:postcode":"6020",
    "addr:street":"Exlg;Tirol",
    "iso:country":"AT",
    "sg:address":"Exlg 37/1",
    "sg:city":"Innsbruck",
    "sg:orig_category":"Werbeagenturen",
    "sg:phone":"+43 4351 22763140",
    "sg:postcode":"6020",
    "sg:province":"Tirol",
    "wof:name":"ABW J. Bernhart GmbH",
    "wof:placetype":"venue"
},
  "geometry": {"coordinates":[11.3717002869,47.2597770691],"type":"Point"}
}