{
  "type": "Feature",
  "properties": {
    "addr:full":"Hammerschmiedg 13 Kitzb\u00fchel Tirol 6370",
    "addr:housenumber":"13",
    "addr:postcode":"6370",
    "addr:street":"Hammerschmiedg;Tirol",
    "iso:country":"AT",
    "sg:address":"Hammerschmiedg 13",
    "sg:city":"Kitzb\u00fchel",
    "sg:orig_category":"Autoelektrik U -Ersatzteile",
    "sg:phone":"+43 4353 5664797",
    "sg:postcode":"6370",
    "sg:province":"Tirol",
    "wof:name":"Autotechnik Schroll",
    "wof:placetype":"venue"
},
  "geometry": {"coordinates":[12.3953409195,47.4449882507],"type":"Point"}
}