{
  "type": "Feature",
  "properties": {
    "addr:full":"Gei\u00dfmayerstr 4 Salzburg Salzburg 5020",
    "addr:housenumber":"4",
    "addr:postcode":"5020",
    "addr:street":"Geissmayerstr;Salzburg",
    "iso:country":"AT",
    "sg:address":"Gei\u00dfmayerstr 4",
    "sg:city":"Salzburg",
    "sg:orig_category":"Kinderbetreuung",
    "sg:phone":"+43 662 641034",
    "sg:postcode":"5020",
    "sg:province":"Salzburg",
    "wof:name":"Hort Parsch",
    "wof:placetype":"venue"
},
  "geometry": {"coordinates":[13.0677871704,47.7994766235],"type":"Point"}
}