{
  "type": "Feature",
  "properties": {
    "addr:full":"Loferer Bundesstr. 19 Saalfelden am Steinernen Meer Salzburg 5760",
    "addr:housenumber":"19",
    "addr:postcode":"5760",
    "addr:street":"Salzburg",
    "iso:country":"AT",
    "sg:address":"Loferer Bundesstr. 19",
    "sg:city":"Saalfelden am Steinernen Meer",
    "sg:classifiers":[
        {
            "category":"Parking",
            "subcategory":"Lot",
            "type":"Transportation"
        }
    ],
    "sg:phone":"+43 4365 8272268",
    "sg:postcode":"5760",
    "sg:province":"Salzburg",
    "sg:tags":[
        "transport",
        "road"
    ],
    "wof:name":"GEIGER KG",
    "wof:placetype":"venue"
},
  "geometry": {"coordinates":[12.8424463272,47.4356536865],"type":"Point"}
}