{
  "type": "Feature",
  "properties": {
    "addr:full":"Nr 124 Strass im Zillertal Tirol 6261",
    "addr:postcode":"6261",
    "addr:street":"Nr 124;Zillertal Tirol",
    "iso:country":"AT",
    "sg:address":"Nr 124",
    "sg:city":"Strass im Zillertal",
    "sg:classifiers":[
        {
            "category":"Farming",
            "subcategory":"Livestock Farm",
            "type":"Manufacturing & Wholesale Goods"
        }
    ],
    "sg:phone":"+43 4352 44633880",
    "sg:postcode":"6261",
    "sg:province":"Tirol",
    "sg:tags":[
        "-handel",
        "viehzucht",
        "u"
    ],
    "wof:name":"Wetscher Franz KmzlR Viehhandel-Viehexport",
    "wof:placetype":"venue"
},
  "geometry": {"coordinates":[11.8219985962,47.3957252502],"type":"Point"}
}