{
  "type": "Feature",
  "properties": {
    "addr:full":"Appenzeller Str 17 Rankweil Vorarlberg 6830",
    "addr:postcode":"6830",
    "addr:street":"Str 17",
    "iso:country":"AT",
    "sg:address":"Appenzeller Str 17",
    "sg:city":"Rankweil",
    "sg:orig_category":"Fotografen",
    "sg:phone":"+43 5522 420260",
    "sg:postcode":"6830",
    "sg:province":"Vorarlberg",
    "wof:name":"Roth Erich",
    "wof:placetype":"venue"
},
  "geometry": {"coordinates":[9.6321821213,47.2777824402],"type":"Point"}
}