{
  "type": "Feature",
  "properties": {
    "addr:full":"Nr 1 Nauders Tirol 6543",
    "addr:postcode":"6543",
    "addr:street":"Nr;Nauders Tirol",
    "iso:country":"AT",
    "sg:address":"Nr 1",
    "sg:city":"Nauders",
    "sg:classifiers":[
        {
            "category":"Restaurant",
            "type":"Food & Drink"
        }
    ],
    "sg:phone":"+43 5473 87596",
    "sg:postcode":"6543",
    "sg:province":"Tirol",
    "wof:name":"Schlo\u00df Naudersberg",
    "wof:placetype":"venue"
},
  "geometry": {"coordinates":[10.4996595383,46.8896980286],"type":"Point"}
}