{
  "type": "Feature",
  "properties": {
    "addr:full":"Nr 184 Feldbach Steiermark 8330",
    "addr:postcode":"8330",
    "addr:street":"Nr 184",
    "iso:country":"AT",
    "sg:address":"Nr 184",
    "sg:city":"Feldbach",
    "sg:orig_category":"Personalbereitstellung",
    "sg:phone":"+43 3159 2314",
    "sg:postcode":"8330",
    "sg:province":"Steiermark",
    "wof:name":"Friesinger Karl & Sieglinde",
    "wof:placetype":"venue"
},
  "geometry": {"coordinates":[15.9065151215,46.9382896423],"type":"Point"}
}