{
  "type": "Feature",
  "properties": {
    "addr:full":"Raiffeisenstr. 7 Kufstein Tirol 6330",
    "addr:housenumber":"7",
    "addr:postcode":"6330",
    "addr:street":"Raiffeisenstr.;Tirol",
    "iso:country":"AT",
    "sg:address":"Raiffeisenstr. 7",
    "sg:city":"Kufstein",
    "sg:classifiers":[
        {
            "category":"Home & Garden",
            "subcategory":"Home Furnishings",
            "type":"Retail Goods"
        }
    ],
    "sg:phone":"+43 4353 7262407",
    "sg:postcode":"6330",
    "sg:province":"Tirol",
    "sg:tags":[
        "household"
    ],
    "wof:name":"RAIFFEISENLAGERHAUS KUFSTEIN REG. GEN.MBH",
    "wof:placetype":"venue"
},
  "geometry": {"coordinates":[12.1638631821,47.5806732178],"type":"Point"}
}