{
  "type": "Feature",
  "properties": {
    "addr:full":"H\u00e4ndelstr 2 Linz Ober\u00f6sterreich 4020",
    "addr:housenumber":"2",
    "addr:postcode":"4020",
    "addr:street":"Haendelstr",
    "iso:country":"AT",
    "sg:address":"H\u00e4ndelstr 2",
    "sg:city":"Linz",
    "sg:orig_category":"\u00c3\u201erzte / F Allgemeinmedizin",
    "sg:phone":"+43 732 6612450",
    "sg:postcode":"4020",
    "sg:province":"Ober\u00f6sterreich",
    "wof:name":"Kappo Martina Dr",
    "wof:placetype":"venue"
},
  "geometry": {"coordinates":[14.26998806,48.2902603149],"type":"Point"}
}