{
  "type": "Feature",
  "properties": {
    "addr:full":"Eben 115 Eben im Pongau Salzburg 5531",
    "addr:housenumber":"115",
    "addr:postcode":"5531",
    "addr:street":"Eben",
    "iso:country":"AT",
    "sg:address":"Eben 115",
    "sg:city":"Eben im Pongau",
    "sg:classifiers":[
        {
            "category":"Manufacturing",
            "subcategory":"Glass & Minerals",
            "type":"Manufacturing & Wholesale Goods"
        }
    ],
    "sg:phone":"+43 6458 8481",
    "sg:postcode":"5531",
    "sg:province":"Salzburg",
    "sg:tags":[
        "processing",
        "mirror"
    ],
    "wof:name":"Ebener Glaserei Helmut Zand",
    "wof:placetype":"venue"
},
  "geometry": {"coordinates":[13.3965826035,47.4049949646],"type":"Point"}
}