{
  "type": "Feature",
  "properties": {
    "iso:country":"AT",
    "sg:address":"St Veiter Anger 30",
    "sg:city":"St. Veit",
    "sg:orig_category":"Architekten",
    "sg:phone":"+43 4331 6692307",
    "sg:postcode":"8046",
    "sg:province":"Steiermark",
    "wof:name":"Molnar Jen\u00f6 Univ Doz Dipl-Ing Dr",
    "wof:placetype":"venue"
},
  "geometry": {"coordinates":[15.4158248901,47.1117668152],"type":"Point"}
}