{
  "type": "Feature",
  "properties": {
    "iso:country":"AT",
    "sg:address":"Amselweg 11",
    "sg:city":"Linz",
    "sg:orig_category":"Raumausstattung",
    "sg:phone":"+43 732 320964",
    "sg:postcode":"4030",
    "sg:province":"Ober\u00f6sterreich",
    "wof:name":"M\u00fcller Helmut",
    "wof:placetype":"venue"
},
  "geometry": {"coordinates":[14.3700971603,48.2431106567],"type":"Point"}
}