{
  "type": "Feature",
  "properties": {
    "addr:full":"Hartlg 21 Wien Wien 1200",
    "addr:housenumber":"21",
    "addr:postcode":"1200",
    "addr:street":"Hartlg",
    "iso:country":"AT",
    "sg:address":"Hartlg 21",
    "sg:city":"Wien",
    "sg:classifiers":[
        {
            "category":"Travel",
            "subcategory":"Hotels & Motels",
            "type":"Entertainment"
        }
    ],
    "sg:phone":"+43 4313 305059",
    "sg:postcode":"1200",
    "sg:province":"Wien",
    "wof:name":"Marien-hof Appartement-Hotel",
    "wof:placetype":"venue"
},
  "geometry": {"coordinates":[16.3734645844,48.2306060791],"type":"Point"}
}