{
  "type": "Feature",
  "properties": {
    "addr:full":"Josef-Reither-Str 16 Tulln an der Donau Nieder\u00f6sterreich 3430",
    "addr:housenumber":"16",
    "addr:postcode":"3430",
    "addr:street":"Josef-Reither-Str",
    "iso:country":"AT",
    "sg:address":"Josef-Reither-Str 16",
    "sg:city":"Tulln an der Donau",
    "sg:orig_category":"Transportunternehmen",
    "sg:phone":"+43 2272 626860",
    "sg:postcode":"3430",
    "sg:province":"Nieder\u00f6sterreich",
    "wof:name":"Schildecker Transport GmbH",
    "wof:placetype":"venue"
},
  "geometry": {"coordinates":[16.0360393524,48.3263206482],"type":"Point"}
}