{
  "type": "Feature",
  "properties": {
    "iso:country":"AT",
    "sg:address":"Achstrasse 42",
    "sg:city":"Wolfurt-Bahnhof",
    "sg:classifiers":[
        {
            "category":"Education",
            "subcategory":"Special Training",
            "type":"Public Place"
        }
    ],
    "sg:phone":"+43 5574 668500",
    "sg:postcode":"6960",
    "sg:province":"Vorarlberg",
    "sg:tags":[
        "bread"
    ],
    "wof:name":"B\u00e4ckerei Mangold GmbH",
    "wof:placetype":"venue"
},
  "geometry": {"coordinates":[9.7423458099,47.4827270508],"type":"Point"}
}