{
  "type": "Feature",
  "properties": {
    "iso:country":"AT",
    "sg:address":"Schulstr 98",
    "sg:city":"Uttendorf",
    "sg:orig_category":"Lebensmittel / Einzelhandel",
    "sg:phone":"+43 6563 8212",
    "sg:postcode":"5723",
    "sg:province":"Salzburg",
    "wof:name":"Vorreiter Johann",
    "wof:placetype":"venue"
},
  "geometry": {"coordinates":[12.5717048645,47.2853317261],"type":"Point"}
}