{
  "type": "Feature",
  "properties": {
    "addr:full":"Nr 275 Strobl Salzburg 5350",
    "addr:postcode":"5350",
    "addr:street":"Nr;Strobl",
    "iso:country":"AT",
    "sg:address":"Nr 275",
    "sg:city":"Strobl",
    "sg:orig_category":"Bankomat-Standorte",
    "sg:phone":"+43 6137 72520",
    "sg:postcode":"5350",
    "sg:province":"Salzburg",
    "wof:name":"Bankomat d Raiffeisenkasse St.Gilgen-Fuschl-Strobl regGenmbH",
    "wof:placetype":"venue"
},
  "geometry": {"coordinates":[13.4822740555,47.719165802],"type":"Point"}
}