{
  "type": "Feature",
  "properties": {
    "iso:country":"AT",
    "sg:address":"Traunsteinstr 101",
    "sg:city":"Gmunden",
    "sg:orig_category":"Mineralien",
    "sg:phone":"+43 664 5131229",
    "sg:postcode":"4810",
    "sg:province":"Ober\u00f6sterreich",
    "wof:name":"Urban Vertriebs GesmbH - Korallen",
    "wof:placetype":"venue"
},
  "geometry": {"coordinates":[13.8073101044,47.9052238464],"type":"Point"}
}