{
  "type": "Feature",
  "properties": {
    "addr:full":"Pitze 182 S\u00f6lden Tirol 6450",
    "addr:housenumber":"182",
    "addr:postcode":"6450",
    "addr:street":"Pitze;Tirol",
    "iso:country":"AT",
    "sg:address":"Pitze 182",
    "sg:city":"S\u00f6lden",
    "sg:classifiers":[
        {
            "category":"Travel",
            "subcategory":"Hotels & Motels",
            "type":"Entertainment"
        }
    ],
    "sg:phone":"+43 5254 2559",
    "sg:postcode":"6450",
    "sg:province":"Tirol",
    "wof:name":"Alphof S\u00f6lden",
    "wof:placetype":"venue"
},
  "geometry": {"coordinates":[11.0113515854,46.9527320862],"type":"Point"}
}