{
  "type": "Feature",
  "properties": {
    "addr:full":"Neustiftg 21 Gols Burgenland 7122",
    "addr:housenumber":"21",
    "addr:postcode":"7122",
    "addr:street":"Neustiftg",
    "iso:country":"AT",
    "sg:address":"Neustiftg 21",
    "sg:city":"Gols",
    "sg:orig_category":"Pensionen / Privatzimmer",
    "sg:phone":"+43 2173 2348",
    "sg:postcode":"7122",
    "sg:province":"Burgenland",
    "wof:name":"Beck J\u00fcrgen und Rosemarie - Weinbau",
    "wof:placetype":"venue"
},
  "geometry": {"coordinates":[16.9091434479,47.8990325928],"type":"Point"}
}