{
  "type": "Feature",
  "properties": {
    "addr:full":"Landstr 2 Holzhausen Ober\u00f6sterreich 4615",
    "addr:housenumber":"2",
    "addr:postcode":"4615",
    "addr:street":"Landstr",
    "iso:country":"AT",
    "sg:address":"Landstr 2",
    "sg:city":"Holzhausen",
    "sg:orig_category":"Volksschulen",
    "sg:phone":"+43 4372 4357193",
    "sg:postcode":"4615",
    "sg:province":"Ober\u00f6sterreich",
    "wof:name":"Volksschule",
    "wof:placetype":"venue"
},
  "geometry": {"coordinates":[14.0966567993,48.222858429],"type":"Point"}
}