{
  "type": "Feature",
  "properties": {
    "addr:full":"Posthofstr 16 Linz Ober\u00f6sterreich 4020",
    "addr:housenumber":"16",
    "addr:postcode":"4020",
    "addr:street":"Posthofstr",
    "iso:country":"AT",
    "sg:address":"Posthofstr 16",
    "sg:city":"Linz",
    "sg:orig_category":"Transportunternehmen",
    "sg:phone":"+43 732 7704660",
    "sg:postcode":"4020",
    "sg:province":"Ober\u00f6sterreich",
    "wof:name":"Pejak-Transporte KFZ Handel",
    "wof:placetype":"venue"
},
  "geometry": {"coordinates":[14.3077802658,48.3141937256],"type":"Point"}
}