{
  "type": "Feature",
  "properties": {
    "iso:country":"AT",
    "sg:address":"Kaiserebersdorferstr 248-250",
    "sg:city":"Wien",
    "sg:orig_category":"Tankstellen",
    "sg:phone":"+43 1 76710630",
    "sg:postcode":"1110",
    "sg:province":"Wien",
    "wof:name":"BP Austria Marketing GmbH",
    "wof:placetype":"venue"
},
  "geometry": {"coordinates":[16.4578227997,48.1601028442],"type":"Point"}
}