{
  "type": "Feature",
  "properties": {
    "addr:full":"Klagenfurter Str 4 Wolfsberg K\u00e4rnten 9400",
    "addr:housenumber":"4;kaernten",
    "addr:postcode":"9400",
    "addr:street":"Str",
    "iso:country":"AT",
    "sg:address":"Klagenfurter Str 4",
    "sg:city":"Wolfsberg",
    "sg:orig_category":"Non-Classified Establishments",
    "sg:phone":"+43 4352 25450",
    "sg:postcode":"9400",
    "sg:province":"K\u00e4rnten",
    "wof:name":"Stra\u00dfenmeisterei Wolfsberg",
    "wof:placetype":"venue"
},
  "geometry": {"coordinates":[14.8417711258,46.832118988],"type":"Point"}
}