{
  "type": "Feature",
  "properties": {
    "addr:full":"Haiderstrasse 16 Ansfelden Ober\u00f6sterreich 4052",
    "addr:housenumber":"16",
    "addr:postcode":"4052",
    "addr:street":"Haiderstrasse",
    "iso:country":"AT",
    "sg:address":"Haiderstrasse 16",
    "sg:city":"Ansfelden",
    "sg:classifiers":[
        {
            "category":"Professional",
            "subcategory":"Art Services",
            "type":"Services"
        }
    ],
    "sg:phone":"+43 7229 87108",
    "sg:postcode":"4052",
    "sg:province":"Ober\u00f6sterreich",
    "sg:tags":[
        "metalwork"
    ],
    "sg:website":"members.aon.at/s-kn/",
    "wof:name":"Klinger & Niedermayr OEG Schlosserei u. Leichtmetallbau Reparatur - Eildienst",
    "wof:placetype":"venue"
},
  "geometry": {"coordinates":[14.2869052887,48.210357666],"type":"Point"}
}