{
  "type": "Feature",
  "properties": {
    "iso:country":"AT",
    "sg:address":"Nr 36",
    "sg:city":"Weitra",
    "sg:orig_category":"Lebensmittel / Einzelhandel",
    "sg:phone":"+43 2858 5364",
    "sg:postcode":"3970",
    "sg:province":"Nieder\u00f6sterreich",
    "wof:name":"Lebensmittelgesch\u00e4ft Krenn Herbert",
    "wof:placetype":"venue"
},
  "geometry": {"coordinates":[14.8928060532,48.7005844116],"type":"Point"}
}