{
  "type": "Feature",
  "properties": {
    "iso:country":"AT",
    "sg:address":"Niedere Munde-Str 15",
    "sg:city":"Telfs",
    "sg:orig_category":"Architekten",
    "sg:phone":"+43 5262 61470",
    "sg:postcode":"6410",
    "sg:province":"Tirol",
    "wof:name":"Wulz Raimund Arch Mag",
    "wof:placetype":"venue"
},
  "geometry": {"coordinates":[11.0641241074,47.3117485046],"type":"Point"}
}