{
  "type": "Feature",
  "properties": {
    "iso:country":"AT",
    "sg:address":"Hauptstr 2",
    "sg:city":"Aigen im M\u00fchlkreis",
    "sg:orig_category":"Bergbahnen",
    "sg:phone":"+43 7281 6361",
    "sg:postcode":"4160",
    "sg:province":"Ober\u00f6sterreich",
    "wof:name":"Hochficht Schilift GesmbH",
    "wof:placetype":"venue"
},
  "geometry": {"coordinates":[13.9701719284,48.6460494995],"type":"Point"}
}