{
  "type": "Feature",
  "properties": {
    "iso:country":"AT",
    "sg:address":"Obereggerstr 5",
    "sg:city":"Traun",
    "sg:orig_category":"Speditionen",
    "sg:phone":"+43 7229 510640",
    "sg:postcode":"4050",
    "sg:province":"Ober\u00f6sterreich",
    "wof:name":"Mammoet Ferry Transport GmbH",
    "wof:placetype":"venue"
},
  "geometry": {"coordinates":[14.2546300888,48.2249603271],"type":"Point"}
}