{
  "type": "Feature",
  "properties": {
    "addr:full":"Nr 41 Bad Gams Steiermark 8524",
    "addr:housenumber":"41",
    "addr:postcode":"8524",
    "addr:street":"Nr",
    "iso:country":"AT",
    "sg:address":"Nr 41",
    "sg:city":"Bad Gams",
    "sg:orig_category":"Massagen",
    "sg:phone":"+43 664 3448596",
    "sg:postcode":"8524",
    "sg:province":"Steiermark",
    "wof:name":"Massagestudio Schwarzl Karin",
    "wof:placetype":"venue"
},
  "geometry": {"coordinates":[166.9221496582,-0.5282999873],"type":"Point"}
}