{
  "type": "Feature",
  "properties": {
    "iso:country":"AT",
    "sg:address":"Stadt 67",
    "sg:city":"Oberw\u00f6lz",
    "sg:classifiers":[
        {
            "category":"Home & Garden",
            "subcategory":"Household Appliances",
            "type":"Retail Goods"
        }
    ],
    "sg:phone":"+43 3581 71000",
    "sg:postcode":"8832",
    "sg:province":"Steiermark",
    "sg:tags":[
        "electric"
    ],
    "sg:website":"elektro-heiss.at",
    "wof:name":"Norbert Heiss",
    "wof:placetype":"venue"
},
  "geometry": {"coordinates":[11.5144367218,46.4019699097],"type":"Point"}
}