{
  "type": "Feature",
  "properties": {
    "addr:full":"Am W\u00f6hr 22 Ybbsitz Nieder\u00f6sterreich 3341",
    "addr:housenumber":"22",
    "addr:postcode":"3341",
    "addr:street":"Am Woehr",
    "iso:country":"AT",
    "sg:address":"Am W\u00f6hr 22",
    "sg:city":"Ybbsitz",
    "sg:orig_category":"Bauunternehmen",
    "sg:phone":"+43 7443 864150",
    "sg:postcode":"3341",
    "sg:province":"Nieder\u00f6sterreich",
    "wof:name":"SCE Schaufler Bau GmbH",
    "wof:placetype":"venue"
},
  "geometry": {"coordinates":[14.8938436508,47.9479408264],"type":"Point"}
}