{
  "type": "Feature",
  "properties": {
    "addr:full":"Ulrichstr 18 Steyr Ober\u00f6sterreich 4400",
    "addr:housenumber":"18",
    "addr:postcode":"4400",
    "addr:street":"Ulrichstr;Oberoesterreich",
    "iso:country":"AT",
    "sg:address":"Ulrichstr 18",
    "sg:city":"Steyr",
    "sg:orig_category":"Installationsunternehmen",
    "sg:phone":"+43 7252 51915",
    "sg:postcode":"4400",
    "sg:province":"Ober\u00f6sterreich",
    "wof:name":"Gschliffner Josef",
    "wof:placetype":"venue"
},
  "geometry": {"coordinates":[14.421049118,48.0248641968],"type":"Point"}
}