{
  "type": "Feature",
  "properties": {
    "addr:full":"Europastr 12 Linz Ober\u00f6sterreich 4020",
    "addr:housenumber":"12",
    "addr:postcode":"4020",
    "addr:street":"Europastr",
    "iso:country":"AT",
    "sg:address":"Europastr 12",
    "sg:city":"Linz",
    "sg:classifiers":[
        {
            "category":"Internet Cafe",
            "subcategory":"None",
            "type":"Food & Drink"
        }
    ],
    "sg:phone":"+43 732 791918",
    "sg:postcode":"4020",
    "sg:province":"Ober\u00f6sterreich",
    "wof:name":"I - TC - E Galirow Dienstleistungs KG",
    "wof:placetype":"venue"
},
  "geometry": {"coordinates":[14.282781601,48.2650985718],"type":"Point"}
}