{
  "type": "Feature",
  "properties": {
    "addr:full":"Kirchbichlweg 1 Obertrum am See Salzburg 5162",
    "addr:housenumber":"1",
    "addr:postcode":"5162",
    "addr:street":"Kirchbichlweg;Salzburg",
    "iso:country":"AT",
    "sg:address":"Kirchbichlweg 1",
    "sg:city":"Obertrum am See",
    "sg:orig_category":"Erdarbeiten",
    "sg:phone":"+43 6219 20381",
    "sg:postcode":"5162",
    "sg:province":"Salzburg",
    "wof:name":"Langwieder Rupert jun",
    "wof:placetype":"venue"
},
  "geometry": {"coordinates":[13.0640277863,47.9373321533],"type":"Point"}
}