{
  "type": "Feature",
  "properties": {
    "iso:country":"AT",
    "sg:address":"Pummererstrasse 14",
    "sg:city":"Linz",
    "sg:classifiers":[
        {
            "category":"Home & Garden",
            "subcategory":"Carpets & Floor Coverings",
            "type":"Retail Goods"
        }
    ],
    "sg:phone":"+43 732 778053",
    "sg:postcode":"4020",
    "sg:province":"Ober\u00f6sterreich",
    "sg:tags":[
        "carpeting"
    ],
    "wof:name":"Johann Gangl",
    "wof:placetype":"venue"
},
  "geometry": {"coordinates":[14.3227958679,48.3068351746],"type":"Point"}
}