{
  "type": "Feature",
  "properties": {
    "addr:full":"Neustift 30 Sitzendorf an der Schmida Nieder\u00f6sterreich 3714",
    "addr:housenumber":"30",
    "addr:postcode":"3714",
    "addr:street":"Neustift",
    "iso:country":"AT",
    "sg:address":"Neustift 30",
    "sg:city":"Sitzendorf an der Schmida",
    "sg:orig_category":"Pensionen / Privatzimmer",
    "sg:phone":"+43 4329 592255",
    "sg:postcode":"3714",
    "sg:province":"Nieder\u00f6sterreich",
    "wof:name":"W\u00f6ber Weinbauernhof",
    "wof:placetype":"venue"
},
  "geometry": {"coordinates":[15.9363470078,48.5999031067],"type":"Point"}
}