{
  "type": "Feature",
  "properties": {
    "addr:full":"Hackledt 49 Eggerding Ober\u00f6sterreich 4773",
    "addr:housenumber":"49",
    "addr:postcode":"4773",
    "addr:street":"Hackledt",
    "iso:country":"AT",
    "sg:address":"Hackledt 49",
    "sg:city":"Eggerding",
    "sg:orig_category":"Hafnereien",
    "sg:phone":"+43 7767 7006",
    "sg:postcode":"4773",
    "sg:province":"Ober\u00f6sterreich",
    "wof:name":"Zauner Alois",
    "wof:placetype":"venue"
},
  "geometry": {"coordinates":[13.4437999725,48.3490943909],"type":"Point"}
}