{
  "type": "Feature",
  "properties": {
    "iso:country":"AT",
    "sg:address":"Nr 5",
    "sg:city":"H\u00fcrm",
    "sg:orig_category":"Futtermittel",
    "sg:phone":"+43 4327 548707",
    "sg:postcode":"3383",
    "sg:province":"Nieder\u00f6sterreich",
    "wof:name":"Pirabe Franz - Stroh- u Heuhandel",
    "wof:placetype":"venue"
},
  "geometry": {"coordinates":[-90.4956283569,41.5259017944],"type":"Point"}
}