{
  "type": "Feature",
  "properties": {
    "addr:full":"Nr 51 Reichraming Ober\u00f6sterreich 4462",
    "addr:postcode":"4462",
    "addr:street":"Nr;Oberoesterreich",
    "iso:country":"AT",
    "sg:address":"Nr 51",
    "sg:city":"Reichraming",
    "sg:orig_category":"Installationsunternehmen",
    "sg:phone":"+43 7255 8304",
    "sg:postcode":"4462",
    "sg:province":"Ober\u00f6sterreich",
    "wof:name":"SULZNER GesmbH",
    "wof:placetype":"venue"
},
  "geometry": {"coordinates":[14.4618120193,47.8909645081],"type":"Point"}
}