{
  "type": "Feature",
  "properties": {
    "addr:full":"Laaer-Berg-Str 207 Wien Wien 1100",
    "addr:housenumber":"207",
    "addr:postcode":"1100",
    "iso:country":"AT",
    "sg:address":"Laaer-Berg-Str 207",
    "sg:city":"Wien",
    "sg:orig_category":"Tankstellen",
    "sg:phone":"+43 1 6881160",
    "sg:postcode":"1100",
    "sg:province":"Wien",
    "wof:name":"BP Tankstelle - Mazzulini Walter",
    "wof:placetype":"venue"
},
  "geometry": {"coordinates":[16.396900177,48.1519851685],"type":"Point"}
}