{
  "type": "Feature",
  "properties": {
    "addr:full":"Aum\u00fchlg 12-14 Hollabrunn Nieder\u00f6sterreich 2020",
    "addr:postcode":"12-14;2020",
    "addr:street":"Niederoesterreich",
    "iso:country":"AT",
    "sg:address":"Aum\u00fchlg 12-14",
    "sg:city":"Hollabrunn",
    "sg:orig_category":"Pumpen",
    "sg:phone":"+43 2952 31440",
    "sg:postcode":"2020",
    "sg:province":"Nieder\u00f6sterreich",
    "wof:name":"Sivag Pumpen GesmbH",
    "wof:placetype":"venue"
},
  "geometry": {"coordinates":[16.0783004761,48.5624580383],"type":"Point"}
}