{
  "type": "Feature",
  "properties": {
    "addr:full":"Brucknerstr 23 Bad Schallerbach Ober\u00f6sterreich 4701",
    "addr:housenumber":"23",
    "addr:postcode":"4701",
    "addr:street":"Brucknerstr",
    "iso:country":"AT",
    "sg:address":"Brucknerstr 23",
    "sg:city":"Bad Schallerbach",
    "sg:orig_category":"Biologische Produkte",
    "sg:phone":"+43 7249 428493",
    "sg:postcode":"4701",
    "sg:province":"Ober\u00f6sterreich",
    "wof:name":"Treben Maria Naturprodukte GmbH",
    "wof:placetype":"venue"
},
  "geometry": {"coordinates":[13.924574852,48.235294342],"type":"Point"}
}