{
  "type": "Feature",
  "properties": {
    "addr:full":"Namlach 11 Winklern K\u00e4rnten 9841",
    "addr:housenumber":"11",
    "addr:postcode":"9841",
    "addr:street":"Namlach;Kaernten",
    "iso:country":"AT",
    "sg:address":"Namlach 11",
    "sg:city":"Winklern",
    "sg:classifiers":[
        {
            "category":"Taxi",
            "type":"Transportation"
        }
    ],
    "sg:phone":"+43 4348 22361",
    "sg:postcode":"9841",
    "sg:province":"K\u00e4rnten",
    "sg:tags":[
        "personentransporte",
        "u"
    ],
    "wof:name":"Taxi Grubenbauer",
    "wof:placetype":"venue"
},
  "geometry": {"coordinates":[12.9168014526,46.8631591797],"type":"Point"}
}