{
  "type": "Feature",
  "properties": {
    "addr:full":"Wolkensteingasse 21 Graz Steiermark 8020",
    "addr:housenumber":"21",
    "addr:postcode":"8020",
    "addr:street":"Wolkensteingasse",
    "iso:country":"AT",
    "sg:address":"Wolkensteingasse 21",
    "sg:city":"Graz",
    "sg:classifiers":[
        {
            "category":"Retail",
            "subcategory":"Repair Shop",
            "type":"Services"
        }
    ],
    "sg:phone":"+43 316 574655",
    "sg:postcode":"8020",
    "sg:province":"Steiermark",
    "sg:tags":[
        "item",
        "decorating",
        "window"
    ],
    "sg:website":"f-heger.at",
    "wof:name":"F. Heger",
    "wof:placetype":"venue"
},
  "geometry": {"coordinates":[15.4081439972,47.0803565979],"type":"Point"}
}