{
  "type": "Feature",
  "properties": {
    "addr:full":"K\u00e4rntner Str 90 Lienz Tirol 9900",
    "addr:postcode":"9900",
    "addr:street":"Str 90;Tirol",
    "iso:country":"AT",
    "sg:address":"K\u00e4rntner Str 90",
    "sg:city":"Lienz",
    "sg:orig_category":"Bauunternehmen",
    "sg:phone":"+43 4348 52634560",
    "sg:postcode":"9900",
    "sg:province":"Tirol",
    "wof:name":"Wildbach- u Lawinenverbauung",
    "wof:placetype":"venue"
},
  "geometry": {"coordinates":[12.7684783936,46.8281173706],"type":"Point"}
}