{
  "type": "Feature",
  "properties": {
    "addr:full":"Eggenberger Allee 42 Graz Steiermark 8020",
    "addr:housenumber":"42",
    "addr:postcode":"8020",
    "addr:street":"Eggenberger Allee",
    "iso:country":"AT",
    "sg:address":"Eggenberger Allee 42",
    "sg:city":"Graz",
    "sg:orig_category":"Banken U Sparkassen",
    "sg:phone":"+43 4331 680332220",
    "sg:postcode":"8020",
    "sg:province":"Steiermark",
    "wof:name":"Steierm\u00e4rkische Bank u Sparkassen AG",
    "wof:placetype":"venue"
},
  "geometry": {"coordinates":[15.4113883972,47.0704460144],"type":"Point"}
}