{
  "type": "Feature",
  "properties": {
    "iso:country":"AT",
    "sg:address":"Wurmserg 35/17",
    "sg:city":"Wien",
    "sg:orig_category":"Werbeagenturen",
    "sg:phone":"+43 1 9820622",
    "sg:postcode":"1150",
    "sg:province":"Wien",
    "wof:name":"Pink Advertising Gerd Eichler KEG",
    "wof:placetype":"venue"
},
  "geometry": {"coordinates":[16.320684433,48.1986656189],"type":"Point"}
}