{
  "type": "Feature",
  "properties": {
    "addr:full":"Amselweg 29 Wernberg K\u00e4rnten 9241",
    "addr:housenumber":"29",
    "addr:postcode":"9241",
    "addr:street":"Amselweg;Kaernten",
    "iso:country":"AT",
    "sg:address":"Amselweg 29",
    "sg:city":"Wernberg",
    "sg:orig_category":"Esoterik",
    "sg:phone":"+43 4342 5224408",
    "sg:postcode":"9241",
    "sg:province":"K\u00e4rnten",
    "wof:name":"Lesjak Martina - Esoterik f Mensch & Tier, Edelsteine u Geschenkartikel",
    "wof:placetype":"venue"
},
  "geometry": {"coordinates":[13.939406395,46.6282157898],"type":"Point"}
}