{
  "type": "Feature",
  "properties": {
    "iso:country":"AT",
    "sg:address":"Nr 50",
    "sg:city":"Thalgau",
    "sg:orig_category":"Volksschulen",
    "sg:phone":"+43 6235 6394",
    "sg:postcode":"5303",
    "sg:province":"Salzburg",
    "wof:name":"Volksschule Egg",
    "wof:placetype":"venue"
},
  "geometry": {"coordinates":[13.2537698746,47.841709137],"type":"Point"}
}