{
  "type": "Feature",
  "properties": {
    "addr:full":"Flughafen Wien Schwechat Pier West Wien Wien 1300",
    "addr:postcode":"1300",
    "addr:street":"Pier West",
    "iso:country":"AT",
    "sg:address":"Flughafen Wien Schwechat Pier West",
    "sg:city":"Wien",
    "sg:classifiers":[
        {
            "category":"Personal",
            "subcategory":"Adult",
            "type":"Services"
        }
    ],
    "sg:phone":"+43 4317 00733466",
    "sg:postcode":"1300",
    "sg:province":"Wien",
    "sg:tags":[
        "sex-shops"
    ],
    "wof:name":"Uhse Beate VertriebsgesmbH",
    "wof:placetype":"venue"
},
  "geometry": {"coordinates":[16.5561008453,48.1137504578],"type":"Point"}
}