{
  "type": "Feature",
  "properties": {
    "addr:full":"Wiener Str 66-72/8/6 Brunn am Gebirge Nieder\u00f6sterreich 2345",
    "addr:housenumber":"66-72 / 8 / 6",
    "addr:postcode":"2345",
    "iso:country":"AT",
    "sg:address":"Wiener Str 66-72/8/6",
    "sg:city":"Brunn am Gebirge",
    "sg:orig_category":"Transportunternehmen",
    "sg:phone":"+43 699 11311313",
    "sg:postcode":"2345",
    "sg:province":"Nieder\u00f6sterreich",
    "wof:name":"Nagy Transport KEG",
    "wof:placetype":"venue"
},
  "geometry": {"coordinates":[16.2839355469,48.107170105],"type":"Point"}
}