{
  "type": "Feature",
  "properties": {
    "addr:full":"St. Veiter Str 115 Klagenfurt K\u00e4rnten 9020",
    "addr:housenumber":"115",
    "addr:postcode":"9020",
    "addr:street":"St. Veiter Str;Kaernten",
    "iso:country":"AT",
    "sg:address":"St. Veiter Str 115",
    "sg:city":"Klagenfurt",
    "sg:orig_category":"Hydrokulturen",
    "sg:phone":"+43 463 411110",
    "sg:postcode":"9020",
    "sg:province":"K\u00e4rnten",
    "wof:name":"Blumen Kainz KEG",
    "wof:placetype":"venue"
},
  "geometry": {"coordinates":[14.3147497177,46.6422767639],"type":"Point"}
}