{
  "type": "Feature",
  "properties": {
    "addr:full":"Edelhof 3 Zwettl Nieder\u00f6sterreich 3910",
    "addr:housenumber":"3",
    "addr:postcode":"3910",
    "addr:street":"Edelhof;Niederoesterreich",
    "iso:country":"AT",
    "sg:address":"Edelhof 3",
    "sg:city":"Zwettl",
    "sg:classifiers":[
        {
            "category":"Professional",
            "subcategory":"Management & Consulting",
            "type":"Services"
        }
    ],
    "sg:phone":"+43 2822 5363325",
    "sg:postcode":"3910",
    "sg:province":"Nieder\u00f6sterreich",
    "wof:name":"Telehaus Waldviertel",
    "wof:placetype":"venue"
},
  "geometry": {"coordinates":[15.220864296,48.6061897278],"type":"Point"}
}