{
  "type": "Feature",
  "properties": {
    "iso:country":"AT",
    "sg:address":"Hauptpl 15",
    "sg:city":"Hainburg an der Donau",
    "sg:orig_category":"Hauskrankenpflege / Heimhilfe",
    "sg:phone":"+43 4321 6565410",
    "sg:postcode":"2410",
    "sg:province":"Nieder\u00f6sterreich",
    "wof:name":"Caritas Betreuen und Pflegen Zuhause Hainburg",
    "wof:placetype":"venue"
},
  "geometry": {"coordinates":[16.9404735565,48.147769928],"type":"Point"}
}