{
  "type": "Feature",
  "properties": {
    "addr:full":"Pillweinstr 5 Linz Ober\u00f6sterreich 4020",
    "addr:housenumber":"5",
    "addr:postcode":"4020",
    "addr:street":"Pillweinstr",
    "iso:country":"AT",
    "sg:address":"Pillweinstr 5",
    "sg:city":"Linz",
    "sg:orig_category":"Waagen / Einzelhandel",
    "sg:phone":"+43 732 6550220",
    "sg:postcode":"4020",
    "sg:province":"Ober\u00f6sterreich",
    "wof:name":"Bizerba Waagen GesmbH & Co KG",
    "wof:placetype":"venue"
},
  "geometry": {"coordinates":[14.2973098755,48.2888031006],"type":"Point"}
}