{
  "type": "Feature",
  "properties": {
    "iso:country":"AT",
    "sg:address":"Reiterweg 1",
    "sg:city":"Gro\u00df-Enzersdorf",
    "sg:orig_category":"Autohandel",
    "sg:phone":"+43 2215 2365",
    "sg:postcode":"2301",
    "sg:province":"Nieder\u00f6sterreich",
    "wof:name":"Hofer GmbH",
    "wof:placetype":"venue"
},
  "geometry": {"coordinates":[16.6158695221,48.1686019897],"type":"Point"}
}