{
  "type": "Feature",
  "properties": {
    "addr:full":"Kirchg 2 Obdach Steiermark 8742",
    "addr:housenumber":"2",
    "addr:postcode":"8742",
    "addr:street":"Kirchg",
    "iso:country":"AT",
    "sg:address":"Kirchg 2",
    "sg:city":"Obdach",
    "sg:orig_category":"Tapezierer U Dekorateure",
    "sg:phone":"+43 4335 782680",
    "sg:postcode":"8742",
    "sg:province":"Steiermark",
    "wof:name":"Rieser Konrad",
    "wof:placetype":"venue"
},
  "geometry": {"coordinates":[14.6939144135,47.0673866272],"type":"Point"}
}