{
  "type": "Feature",
  "properties": {
    "addr:full":"Kairegg 89 St. Josef Steiermark 8503",
    "addr:housenumber":"89",
    "addr:postcode":"8503",
    "addr:street":"Kairegg",
    "iso:country":"AT",
    "sg:address":"Kairegg 89",
    "sg:city":"St. Josef",
    "sg:orig_category":"Mietautos",
    "sg:phone":"+43 4331 3681280",
    "sg:postcode":"8503",
    "sg:province":"Steiermark",
    "wof:name":"Lindschinger Franz",
    "wof:placetype":"venue"
},
  "geometry": {"coordinates":[15.3384799957,46.9120903015],"type":"Point"}
}