{
  "type": "Feature",
  "properties": {
    "iso:country":"AT",
    "sg:address":"Oberthal 9",
    "sg:city":"Assling",
    "sg:orig_category":"Tourismusinformation U -Organisationen",
    "sg:phone":"+43 4855 8444",
    "sg:postcode":"9911",
    "sg:province":"Tirol",
    "wof:name":"Tourismusverband Tahl-Assling",
    "wof:placetype":"venue"
},
  "geometry": {"coordinates":[12.6467514038,46.7905960083],"type":"Point"}
}