{
  "type": "Feature",
  "properties": {
    "addr:full":"Winklen 82 L\u00e4ngenfeld Tirol 6444",
    "addr:housenumber":"82",
    "addr:postcode":"6444",
    "addr:street":"Winklen;Tirol",
    "iso:country":"AT",
    "sg:address":"Winklen 82",
    "sg:city":"L\u00e4ngenfeld",
    "sg:orig_category":"Pensionen / Privatzimmer",
    "sg:phone":"+43 4352 535822",
    "sg:postcode":"6444",
    "sg:province":"Tirol",
    "wof:name":"Reindl Anneliese",
    "wof:placetype":"venue"
},
  "geometry": {"coordinates":[10.9441728592,47.1027908325],"type":"Point"}
}