{
  "type": "Feature",
  "properties": {
    "iso:country":"AT",
    "sg:address":"Hauptstr 157",
    "sg:city":"Breitenfurt",
    "sg:orig_category":"Drogerien",
    "sg:phone":"+43 2239 2398",
    "sg:postcode":"2384",
    "sg:province":"Nieder\u00f6sterreich",
    "wof:name":"Fahrecker Gerhard",
    "wof:placetype":"venue"
},
  "geometry": {"coordinates":[16.2033882141,48.1379966736],"type":"Point"}
}