{
  "type": "Feature",
  "properties": {
    "addr:full":"Markt 67 Waldhausen im Strudengau Ober\u00f6sterreich 4391",
    "addr:housenumber":"67",
    "addr:postcode":"4391",
    "addr:street":"Markt",
    "iso:country":"AT",
    "sg:address":"Markt 67",
    "sg:city":"Waldhausen im Strudengau",
    "sg:orig_category":"Hauptschulen",
    "sg:phone":"+43 7260 42390",
    "sg:postcode":"4391",
    "sg:province":"Ober\u00f6sterreich",
    "wof:name":"Hauptschule",
    "wof:placetype":"venue"
},
  "geometry": {"coordinates":[14.9481801987,48.2729988098],"type":"Point"}
}