{
  "type": "Feature",
  "properties": {
    "addr:full":"Maria Theresien-G 6 Theresienfeld Nieder\u00f6sterreich 2604",
    "addr:housenumber":"6;2604",
    "addr:street":"Theresienfeld Niederoesterreich",
    "iso:country":"AT",
    "sg:address":"Maria Theresien-G 6",
    "sg:city":"Theresienfeld",
    "sg:orig_category":"Bauunternehmen",
    "sg:phone":"+43 664 2838366",
    "sg:postcode":"2604",
    "sg:province":"Nieder\u00f6sterreich",
    "wof:name":"TEAM-BAU Exakta Dietmar MACHO OEG",
    "wof:placetype":"venue"
},
  "geometry": {"coordinates":[16.2440242767,47.8574981689],"type":"Point"}
}