{
  "type": "Feature",
  "properties": {
    "addr:full":"Albrechtsbergerg 30 Wien Wien 1120",
    "addr:housenumber":"30",
    "addr:postcode":"1120",
    "addr:street":"Albrechtsbergerg",
    "iso:country":"AT",
    "sg:address":"Albrechtsbergerg 30",
    "sg:city":"Wien",
    "sg:orig_category":"Mauertrockenlegungen",
    "sg:phone":"+43 1 8178990",
    "sg:postcode":"1120",
    "sg:province":"Wien",
    "wof:name":"GESAN Pfeiffermann",
    "wof:placetype":"venue"
},
  "geometry": {"coordinates":[16.3364677429,48.1789093018],"type":"Point"}
}