{
  "type": "Feature",
  "properties": {
    "iso:country":"AT",
    "sg:address":"Ederstr 7/6",
    "sg:city":"Linz",
    "sg:orig_category":"Personalbereitstellung",
    "sg:phone":"+43 732 601259",
    "sg:postcode":"4020",
    "sg:province":"Ober\u00f6sterreich",
    "sg:website":"rantasa.at",
    "wof:name":"Rantasa Dr Interimspersonal GmbH",
    "wof:placetype":"venue"
},
  "geometry": {"coordinates":[14.2912158966,48.2965965271],"type":"Point"}
}