{
  "type": "Feature",
  "properties": {
    "iso:country":"AT",
    "sg:address":"Ennser Strasse 29a",
    "sg:city":"Steyr",
    "sg:classifiers":[
        {
            "category":"Farming",
            "subcategory":"Berry Farm",
            "type":"Manufacturing & Wholesale Goods"
        }
    ],
    "sg:phone":"+43 7252 738130",
    "sg:postcode":"4400",
    "sg:province":"Ober\u00f6sterreich",
    "sg:tags":[
        "austrian",
        "wine"
    ],
    "wof:name":"Brauerei Enns Steyr Getr\u00e4nke GmbH",
    "wof:placetype":"venue"
},
  "geometry": {"coordinates":[14.4204397202,48.0544433594],"type":"Point"}
}