{
  "type": "Feature",
  "properties": {
    "iso:country":"AT",
    "sg:address":"Opernring 13",
    "sg:city":"Wien",
    "sg:orig_category":"Blumeneinzelhandel",
    "sg:phone":"+43 1 58742190",
    "sg:postcode":"1010",
    "sg:province":"Wien",
    "wof:name":"S\u00e4dtler GesmbH & Co KG",
    "wof:placetype":"venue"
},
  "geometry": {"coordinates":[16.366651535,48.2027702332],"type":"Point"}
}