{
  "type": "Feature",
  "properties": {
    "addr:full":"Kremser Str 57 Zwettl Nieder\u00f6sterreich 3910",
    "addr:postcode":"3910",
    "addr:street":"Str 57",
    "iso:country":"AT",
    "sg:address":"Kremser Str 57",
    "sg:city":"Zwettl",
    "sg:orig_category":"Schlossereien",
    "sg:phone":"+43 2822 526030",
    "sg:postcode":"3910",
    "sg:province":"Nieder\u00f6sterreich",
    "wof:name":"Lehenbauer Engelbert GesmbH",
    "wof:placetype":"venue"
},
  "geometry": {"coordinates":[15.1681003571,48.6041564941],"type":"Point"}
}