{
  "type": "Feature",
  "properties": {
    "addr:full":"Vivenotg 30/1 Wien Wien 1120",
    "addr:housenumber":"30 / 1",
    "addr:postcode":"1120",
    "addr:street":"Vivenotg",
    "iso:country":"AT",
    "sg:address":"Vivenotg 30/1",
    "sg:city":"Wien",
    "sg:orig_category":"Waren Aller Art",
    "sg:phone":"+43 1 8171524",
    "sg:postcode":"1120",
    "sg:province":"Wien",
    "wof:name":"Duke's Handels GmbH",
    "wof:placetype":"venue"
},
  "geometry": {"coordinates":[16.3310871124,48.1785354614],"type":"Point"}
}