{
  "type": "Feature",
  "properties": {
    "addr:full":"Kristein 2 Enns Ober\u00f6sterreich 4470",
    "addr:housenumber":"2",
    "addr:postcode":"4470",
    "addr:street":"Kristein",
    "iso:country":"AT",
    "sg:address":"Kristein 2",
    "sg:city":"Enns",
    "sg:orig_category":"Metallbe- U -Verarbeitung",
    "sg:phone":"+43 4372 2381787",
    "sg:postcode":"4470",
    "sg:province":"Ober\u00f6sterreich",
    "wof:name":"Buchegger OEG",
    "wof:placetype":"venue"
},
  "geometry": {"coordinates":[14.4506473541,48.2168083191],"type":"Point"}
}