{
  "type": "Feature",
  "properties": {
    "addr:full":"Nr 130 Sch\u00f6nb\u00fchel an der Donau Nieder\u00f6sterreich 3392",
    "addr:postcode":"3392",
    "addr:street":"Nr 130 Schoenbuehel An Der Donau",
    "iso:country":"AT",
    "sg:address":"Nr 130",
    "sg:city":"Sch\u00f6nb\u00fchel an der Donau",
    "sg:orig_category":"Schwei\u00c3\u0178arbeiten",
    "sg:phone":"+43 2752 8516",
    "sg:postcode":"3392",
    "sg:province":"Nieder\u00f6sterreich",
    "wof:name":"Zemann Siegfried Lohnschwei\u00dfungen-Schwei\u00dferschulung-Rohrleitungsbau",
    "wof:placetype":"venue"
},
  "geometry": {"coordinates":[-82.9872589111,36.5964202881],"type":"Point"}
}