{
  "type": "Feature",
  "properties": {
    "addr:full":"Gewerbeg 5 Guntramsdorf Nieder\u00f6sterreich 2353",
    "addr:housenumber":"5",
    "addr:postcode":"2353",
    "addr:street":"Gewerbeg",
    "iso:country":"AT",
    "sg:address":"Gewerbeg 5",
    "sg:city":"Guntramsdorf",
    "sg:orig_category":"Autohandel",
    "sg:phone":"+43 2236 53506",
    "sg:postcode":"2353",
    "sg:province":"Nieder\u00f6sterreich",
    "wof:name":"Fahsalter Stefan",
    "wof:placetype":"venue"
},
  "geometry": {"coordinates":[16.3131484985,48.0491676331],"type":"Point"}
}