{
  "type": "Feature",
  "properties": {
    "addr:full":"Markt 98 St. Wolfgang im Salzkammergut Ober\u00f6sterreich 5360",
    "addr:housenumber":"98",
    "addr:postcode":"5360",
    "addr:street":"Markt",
    "iso:country":"AT",
    "sg:address":"Markt 98",
    "sg:city":"St. Wolfgang im Salzkammergut",
    "sg:orig_category":"Pensionen / Privatzimmer",
    "sg:phone":"+43 4361 382224",
    "sg:postcode":"5360",
    "sg:province":"Ober\u00f6sterreich",
    "wof:name":"Haus am See",
    "wof:placetype":"venue"
},
  "geometry": {"coordinates":[13.4466266632,47.7386398315],"type":"Point"}
}