{
  "type": "Feature",
  "properties": {
    "addr:full":"Erzherzog-Karl-Str 33 Wien Wien 1220",
    "addr:housenumber":"33",
    "addr:postcode":"1220",
    "addr:street":"Erzherzog-Karl-Str",
    "iso:country":"AT",
    "sg:address":"Erzherzog-Karl-Str 33",
    "sg:city":"Wien",
    "sg:orig_category":"Tabaktrafiken",
    "sg:phone":"+43 1 2041961",
    "sg:postcode":"1220",
    "sg:province":"Wien",
    "wof:name":"Brenner Harald",
    "wof:placetype":"venue"
},
  "geometry": {"coordinates":[16.4382514954,48.2362327576],"type":"Point"}
}