{
  "type": "Feature",
  "properties": {
    "iso:country":"AT",
    "sg:address":"Nr 1",
    "sg:city":"Sillian",
    "sg:orig_category":"Volksschulen",
    "sg:phone":"+43 4348 426695",
    "sg:postcode":"9920",
    "sg:province":"Tirol",
    "wof:name":"Volksschule",
    "wof:placetype":"venue"
},
  "geometry": {"coordinates":[12.4398870468,46.7495117188],"type":"Point"}
}