{
  "type": "Feature",
  "properties": {
    "addr:full":"null Parz 94 Podersdorf am See Burgenland 7141",
    "addr:housenumber":"94",
    "addr:postcode":"7141",
    "iso:country":"AT",
    "sg:address":"null Parz 94",
    "sg:city":"Podersdorf am See",
    "sg:orig_category":"Weine / Einzelhandel",
    "sg:phone":"+43 4321 772236",
    "sg:postcode":"7141",
    "sg:province":"Burgenland",
    "wof:name":"Gisch-Steiner Weingut",
    "wof:placetype":"venue"
},
  "geometry": {"coordinates":[16.8368549347,47.8544998169],"type":"Point"}
}