{
  "type": "Feature",
  "properties": {
    "addr:full":"Griesm\u00fchlstr 2 Marchtrenk Ober\u00f6sterreich 4614",
    "addr:housenumber":"2",
    "addr:postcode":"4614",
    "addr:street":"Griesmuehlstr",
    "iso:country":"AT",
    "sg:address":"Griesm\u00fchlstr 2",
    "sg:city":"Marchtrenk",
    "sg:orig_category":"Betonerzeugnisse",
    "sg:phone":"+43 7242 62316",
    "sg:postcode":"4614",
    "sg:province":"Ober\u00f6sterreich",
    "wof:name":"Gerstl Rudolf - Abt Beton- und Fertigteilbau - Werk",
    "wof:placetype":"venue"
},
  "geometry": {"coordinates":[14.1149396896,48.190826416],"type":"Point"}
}