{
  "type": "Feature",
  "properties": {
    "iso:country":"AT",
    "sg:address":"Plabutscher Str 42",
    "sg:city":"G\u00f6sting",
    "sg:orig_category":"Badezimmer U Badezimmereinrichtungen",
    "sg:phone":"+43 316 27720",
    "sg:postcode":"8051",
    "sg:province":"Steiermark",
    "wof:name":"Od\u00f6rfer Haustechnik GmbH",
    "wof:placetype":"venue"
},
  "geometry": {"coordinates":[15.4041996002,47.0874404907],"type":"Point"}
}