{
  "type": "Feature",
  "properties": {
    "iso:country":"AT",
    "sg:address":"Mitterstr 100",
    "sg:city":"Puntigam",
    "sg:orig_category":"Stahlbau",
    "sg:phone":"+43 316 2932590",
    "sg:postcode":"8055",
    "sg:province":"Steiermark",
    "wof:name":"B.S.S. Stahlbau GmbH",
    "wof:placetype":"venue"
},
  "geometry": {"coordinates":[15.4305763245,47.0192604065],"type":"Point"}
}