{
  "type": "Feature",
  "properties": {
    "addr:full":"Schwerbachgegend 39 Kirchberg an der Pielach Nieder\u00f6sterreich 3204",
    "addr:housenumber":"39",
    "addr:postcode":"3204",
    "addr:street":"Schwerbachgegend",
    "iso:country":"AT",
    "sg:address":"Schwerbachgegend 39",
    "sg:city":"Kirchberg an der Pielach",
    "sg:classifiers":[
        {
            "category":"Home & Garden",
            "subcategory":"Furniture",
            "type":"Retail Goods"
        }
    ],
    "sg:phone":"+43 2722 2224",
    "sg:postcode":"3204",
    "sg:province":"Nieder\u00f6sterreich",
    "sg:tags":[
        "bathroom"
    ],
    "wof:name":"Wohnstudio Singer",
    "wof:placetype":"venue"
},
  "geometry": {"coordinates":[15.4310598373,48.0258712769],"type":"Point"}
}