{
  "type": "Feature",
  "properties": {
    "addr:full":"Hauptstr 73 Linz Ober\u00f6sterreich 4040",
    "addr:housenumber":"73",
    "addr:postcode":"4040",
    "addr:street":"Hauptstr",
    "iso:country":"AT",
    "sg:address":"Hauptstr 73",
    "sg:city":"Linz",
    "sg:orig_category":"Esoterik",
    "sg:phone":"+43 70715190",
    "sg:postcode":"4040",
    "sg:province":"Ober\u00f6sterreich",
    "wof:name":"Balance Esoterik Inh Frido Berger",
    "wof:placetype":"venue"
},
  "geometry": {"coordinates":[14.2807092667,48.314704895],"type":"Point"}
}