{
  "type": "Feature",
  "properties": {
    "addr:full":"Maria-Theresien-Str 51-53 Innsbruck Tirol 6020",
    "addr:housenumber":"51-53",
    "addr:postcode":"6020",
    "addr:street":"Tirol",
    "iso:country":"AT",
    "sg:address":"Maria-Theresien-Str 51-53",
    "sg:city":"Innsbruck",
    "sg:orig_category":"Versicherungsunternehmen",
    "sg:phone":"+43 512 59260",
    "sg:postcode":"6020",
    "sg:province":"Tirol",
    "sg:website":"generali.at",
    "wof:name":"Generali Versicherung AG",
    "wof:placetype":"venue"
},
  "geometry": {"coordinates":[11.3949642181,47.2632904053],"type":"Point"}
}