{
  "type": "Feature",
  "properties": {
    "addr:full":"Kirchenpl 2 Nu\u00dfbach Ober\u00f6sterreich 4542",
    "addr:housenumber":"2",
    "addr:postcode":"4542",
    "addr:street":"Kirchenpl",
    "iso:country":"AT",
    "sg:address":"Kirchenpl 2",
    "sg:city":"Nu\u00dfbach",
    "sg:orig_category":"Gemeinden",
    "sg:phone":"+43 4375 8782550",
    "sg:postcode":"4542",
    "sg:province":"Ober\u00f6sterreich",
    "wof:name":"Gemeindeamt Nu\u00dfbach",
    "wof:placetype":"venue"
},
  "geometry": {"coordinates":[-95.76676177980001,34.9332809448],"type":"Point"}
}