{
  "type": "Feature",
  "properties": {
    "iso:country":"AT",
    "sg:address":"Sch\u00f6nau bei Litschau 32",
    "sg:city":"Litschau",
    "sg:classifiers":[
        {
            "category":"Home & Garden",
            "subcategory":"Carpets & Floor Coverings",
            "type":"Retail Goods"
        }
    ],
    "sg:phone":"+43 2865 5392",
    "sg:postcode":"3874",
    "sg:province":"Nieder\u00f6sterreich",
    "sg:tags":[
        "carpeting"
    ],
    "wof:name":"Gerhard Irrschik",
    "wof:placetype":"venue"
},
  "geometry": {"coordinates":[15.0453643799,48.9441757202],"type":"Point"}
}