{
  "type": "Feature",
  "properties": {
    "addr:full":"Endresstr 92 Wien Wien 1230",
    "addr:housenumber":"92",
    "addr:postcode":"1230",
    "addr:street":"Endresstr",
    "iso:country":"AT",
    "sg:address":"Endresstr 92",
    "sg:city":"Wien",
    "sg:orig_category":"Esoterik",
    "sg:phone":"+43 1 8766768",
    "sg:postcode":"1230",
    "sg:province":"Wien",
    "wof:name":"Kortenburg Ella",
    "wof:placetype":"venue"
},
  "geometry": {"coordinates":[16.2722835541,48.1505355835],"type":"Point"}
}