{
  "type": "Feature",
  "properties": {
    "addr:full":"Johann-Staud-Str 53 Wien Wien 1160",
    "addr:housenumber":"53",
    "addr:postcode":"1160",
    "addr:street":"Johann-Staud-Str",
    "iso:country":"AT",
    "sg:address":"Johann-Staud-Str 53",
    "sg:city":"Wien",
    "sg:orig_category":"Weinstuben",
    "sg:phone":"+43 1 9114760",
    "sg:postcode":"1160",
    "sg:province":"Wien",
    "wof:name":"Binder Margarete",
    "wof:placetype":"venue"
},
  "geometry": {"coordinates":[16.285949707,48.2140579224],"type":"Point"}
}