{
  "type": "Feature",
  "properties": {
    "addr:full":"Altmannsdorfer Str 25 Wien Wien 1120",
    "addr:postcode":"1120",
    "addr:street":"Str 25",
    "iso:country":"AT",
    "sg:address":"Altmannsdorfer Str 25",
    "sg:city":"Wien",
    "sg:orig_category":"Garagen Parkgaragen",
    "sg:phone":"+43 1 8102998",
    "sg:postcode":"1120",
    "sg:province":"Wien",
    "wof:name":"Zimmermann Norbert",
    "wof:placetype":"venue"
},
  "geometry": {"coordinates":[16.3149452209,48.1725845337],"type":"Point"}
}