{
  "type": "Feature",
  "properties": {
    "addr:full":"Nr 49 M\u00fchldorf Nieder\u00f6sterreich 3622",
    "addr:postcode":"3622",
    "addr:street":"Nr 49 Muehldorf",
    "iso:country":"AT",
    "sg:address":"Nr 49",
    "sg:city":"M\u00fchldorf",
    "sg:orig_category":"Feuerwehren",
    "sg:phone":"+43 2713 78322",
    "sg:postcode":"3622",
    "sg:province":"Nieder\u00f6sterreich",
    "wof:name":"Freiwillige Feuerwehr M\u00fchldorf",
    "wof:placetype":"venue"
},
  "geometry": {"coordinates":[166.9221496582,-0.5282999873],"type":"Point"}
}