{
  "type": "Feature",
  "properties": {
    "addr:full":"Hauptstrasse 1 Gr\u00fcnburg Ober\u00f6sterreich 4594",
    "addr:housenumber":"1",
    "addr:postcode":"4594",
    "addr:street":"Hauptstrasse;Oberoesterreich",
    "iso:country":"AT",
    "sg:address":"Hauptstrasse 1",
    "sg:city":"Gr\u00fcnburg",
    "sg:classifiers":[
        {
            "category":"Building & Trades",
            "subcategory":"Construction",
            "type":"Services"
        }
    ],
    "sg:phone":"+43 7257 8158",
    "sg:postcode":"4594",
    "sg:province":"Ober\u00f6sterreich",
    "sg:tags":[
        "flat",
        "steep",
        "roof",
        "waterproofing"
    ],
    "sg:website":"tuscher.at",
    "wof:name":"Erwin Tuscher",
    "wof:placetype":"venue"
},
  "geometry": {"coordinates":[14.264875412,47.9736785889],"type":"Point"}
}