{
  "type": "Feature",
  "properties": {
    "addr:full":"Dorf 35 Anras Tirol 9912",
    "addr:housenumber":"35",
    "addr:postcode":"9912",
    "addr:street":"Dorf;Tirol",
    "iso:country":"AT",
    "sg:address":"Dorf 35",
    "sg:city":"Anras",
    "sg:orig_category":"Non-Classified Establishments",
    "sg:phone":"+43 4846 6152",
    "sg:postcode":"9912",
    "sg:province":"Tirol",
    "wof:name":"Pfarramt",
    "wof:placetype":"venue"
},
  "geometry": {"coordinates":[12.5568389893,46.7720298767],"type":"Point"}
}