{
  "type": "Feature",
  "properties": {
    "iso:country":"AT",
    "sg:address":"Rilkestr 20",
    "sg:city":"Linz",
    "sg:orig_category":"Finanz- U Wirtschaftsberatung",
    "sg:phone":"+43 732 6515030",
    "sg:postcode":"4020",
    "sg:province":"Ober\u00f6sterreich",
    "wof:name":"TVG - Institut f Betriebs- und Verm\u00f6gensberatung LdsDion O\u00d6",
    "wof:placetype":"venue"
},
  "geometry": {"coordinates":[14.3016691208,48.2914619446],"type":"Point"}
}