{
  "type": "Feature",
  "properties": {
    "addr:full":"Wiener Str 14 Lockenhaus Burgenland 7442",
    "addr:postcode":"7442",
    "iso:country":"AT",
    "sg:address":"Wiener Str 14",
    "sg:city":"Lockenhaus",
    "sg:classifiers":[
        {
            "category":"Restaurant",
            "type":"Food & Drink"
        }
    ],
    "sg:phone":"+43 2616 2075",
    "sg:postcode":"7442",
    "sg:province":"Burgenland",
    "sg:tags":[
        "pizzeria"
    ],
    "wof:name":"Pizzeria Amore",
    "wof:placetype":"venue"
},
  "geometry": {"coordinates":[16.4171905518,47.4097290039],"type":"Point"}
}