{
  "type": "Feature",
  "properties": {
    "addr:full":"Hauptpl 39 Frohnleiten Steiermark 8130",
    "addr:housenumber":"39",
    "addr:postcode":"8130",
    "addr:street":"Hauptpl",
    "iso:country":"AT",
    "sg:address":"Hauptpl 39",
    "sg:city":"Frohnleiten",
    "sg:orig_category":"Drogerien",
    "sg:phone":"+43 3126 4100",
    "sg:postcode":"8130",
    "sg:province":"Steiermark",
    "wof:name":"dm drogerie markt GmbH",
    "wof:placetype":"venue"
},
  "geometry": {"coordinates":[15.3272237778,47.2712860107],"type":"Point"}
}