{
  "type": "Feature",
  "properties": {
    "addr:full":"Dorfstr 119 Westendorf Tirol 6363",
    "addr:housenumber":"119",
    "addr:postcode":"6363",
    "addr:street":"Dorfstr;Tirol",
    "iso:country":"AT",
    "sg:address":"Dorfstr 119",
    "sg:city":"Westendorf",
    "sg:orig_category":"Pensionen / Privatzimmer",
    "sg:phone":"+43 5334 62580",
    "sg:postcode":"6363",
    "sg:province":"Tirol",
    "wof:name":"Haus Katharina",
    "wof:placetype":"venue"
},
  "geometry": {"coordinates":[12.2102460861,47.429901123],"type":"Point"}
}