{
  "type": "Feature",
  "properties": {
    "addr:full":"Marienstr 5 Steyr Ober\u00f6sterreich 4400",
    "addr:housenumber":"5",
    "addr:postcode":"4400",
    "addr:street":"Marienstr;Oberoesterreich",
    "iso:country":"AT",
    "sg:address":"Marienstr 5",
    "sg:city":"Steyr",
    "sg:orig_category":"Psychotherapie",
    "sg:phone":"+43 676 6406108",
    "sg:postcode":"4400",
    "sg:province":"Ober\u00f6sterreich",
    "wof:name":"Mayr Susanne",
    "wof:placetype":"venue"
},
  "geometry": {"coordinates":[14.4181661606,48.0310096741],"type":"Point"}
}