{
  "type": "Feature",
  "properties": {
    "addr:full":"Rochusg 17 Wien Wien 1030",
    "addr:housenumber":"17",
    "addr:postcode":"1030",
    "addr:street":"Rochusg",
    "iso:country":"AT",
    "sg:address":"Rochusg 17",
    "sg:city":"Wien",
    "sg:orig_category":"Fu\u00c3\u0178pflege U Fu\u00c3\u0178pflegesalons",
    "sg:phone":"+43 4317 148078",
    "sg:postcode":"1030",
    "sg:province":"Wien",
    "wof:name":"K\u00f6stler Elisabeth",
    "wof:placetype":"venue"
},
  "geometry": {"coordinates":[16.3886299133,48.2010002136],"type":"Point"}
}