{
  "type": "Feature",
  "properties": {
    "addr:full":"Hainbuchenweg 6 Linz Ober\u00f6sterreich 4030",
    "addr:housenumber":"6",
    "addr:postcode":"4030",
    "addr:street":"Hainbuchenweg",
    "iso:country":"AT",
    "sg:address":"Hainbuchenweg 6",
    "sg:city":"Linz",
    "sg:orig_category":"Dekorationen",
    "sg:phone":"+43 70916661",
    "sg:postcode":"4030",
    "sg:province":"Ober\u00f6sterreich",
    "sg:website":"www.dekorateurin.at",
    "wof:name":"Dekorateurin Schernhammer Regina",
    "wof:placetype":"venue"
},
  "geometry": {"coordinates":[14.2844352722,48.247543335],"type":"Point"}
}