{
  "type": "Feature",
  "properties": {
    "addr:full":"Weidlinger Str 45 Klosterneuburg Nieder\u00f6sterreich 3400",
    "addr:housenumber":"45",
    "addr:postcode":"3400",
    "addr:street":"Str;Niederoesterreich",
    "iso:country":"AT",
    "sg:address":"Weidlinger Str 45",
    "sg:city":"Klosterneuburg",
    "sg:orig_category":"Autohandel",
    "sg:phone":"+43 4322 43377300",
    "sg:postcode":"3400",
    "sg:province":"Nieder\u00f6sterreich",
    "wof:name":"Porsche Inter Auto GmbH & Co KG Zweigniederlassung Weilguni",
    "wof:placetype":"venue"
},
  "geometry": {"coordinates":[16.3268451691,48.2949562073],"type":"Point"}
}