{
  "type": "Feature",
  "properties": {
    "iso:country":"AT",
    "sg:address":"Weidmanng 19",
    "sg:city":"Wien",
    "sg:orig_category":"Direktmarketing",
    "sg:phone":"+43 1 40705470",
    "sg:postcode":"1170",
    "sg:province":"Wien",
    "wof:name":"Poltner Mag GmbH",
    "wof:placetype":"venue"
},
  "geometry": {"coordinates":[16.3328075409,48.2217216492],"type":"Point"}
}