{
  "type": "Feature",
  "properties": {
    "addr:full":"Obere Rauschhofstrasse Innermanzing Nieder\u00f6sterreich 3052",
    "addr:postcode":"3052",
    "addr:street":"Obere Rauschhofstrasse",
    "iso:country":"AT",
    "sg:address":"Obere Rauschhofstrasse",
    "sg:city":"Innermanzing",
    "sg:classifiers":[
        {
            "category":"Communications",
            "subcategory":"Film & Video Production",
            "type":"Services"
        }
    ],
    "sg:phone":"+43 2774 29081",
    "sg:postcode":"3052",
    "sg:province":"Nieder\u00f6sterreich",
    "sg:tags":[
        "attendance",
        "working",
        "recording",
        "time",
        "flexitime",
        "software"
    ],
    "sg:website":"www.zeitwirtschaft.at",
    "wof:name":"hpm Heinz-Peter Morawetz",
    "wof:placetype":"venue"
},
  "geometry": {"coordinates":[15.9083547592,48.1292381287],"type":"Point"}
}