{
  "type": "Feature",
  "properties": {
    "addr:full":"Scheunenstr 9 Korneuburg Nieder\u00f6sterreich 2100",
    "addr:housenumber":"9",
    "addr:postcode":"2100",
    "addr:street":"Scheunenstr;Niederoesterreich",
    "iso:country":"AT",
    "sg:address":"Scheunenstr 9",
    "sg:city":"Korneuburg",
    "sg:orig_category":"Montagen U Montagetechnik",
    "sg:phone":"+43 4322 6262168",
    "sg:postcode":"2100",
    "sg:province":"Nieder\u00f6sterreich",
    "wof:name":"Straub Ronald - Anlagen- u Regalmontagen",
    "wof:placetype":"venue"
},
  "geometry": {"coordinates":[16.3332500458,48.3524703979],"type":"Point"}
}