{
  "type": "Feature",
  "properties": {
    "addr:full":"Lehen 7 Ruprechtshofen Nieder\u00f6sterreich 3244",
    "addr:housenumber":"7",
    "addr:postcode":"3244",
    "addr:street":"Lehen",
    "iso:country":"AT",
    "sg:address":"Lehen 7",
    "sg:city":"Ruprechtshofen",
    "sg:orig_category":"Tischlereien",
    "sg:phone":"+43 2756 21240",
    "sg:postcode":"3244",
    "sg:province":"Nieder\u00f6sterreich",
    "sg:website":"www.ab-holz.at",
    "wof:name":"Baumgartner Alfred Bau- und M\u00f6beltischlerei GmbH",
    "wof:placetype":"venue"
},
  "geometry": {"coordinates":[15.2420902252,48.0953369141],"type":"Point"}
}