{
  "type": "Feature",
  "properties": {
    "iso:country":"AT",
    "sg:address":"Paulanerg 10",
    "sg:city":"Wien",
    "sg:orig_category":"Gie\u00c3\u0178ereieinrichtungen U -Bedarf",
    "sg:phone":"+43 1 58755110",
    "sg:postcode":"1040",
    "sg:province":"Wien",
    "wof:name":"Frank & Schulte in Austria GesmbH",
    "wof:placetype":"venue"
},
  "geometry": {"coordinates":[16.366443634,48.1960716248],"type":"Point"}
}