{
  "type": "Feature",
  "properties": {
    "addr:full":"Kramerg 1/3 Wien Wien 1010",
    "addr:housenumber":"1 / 3",
    "addr:postcode":"1010",
    "addr:street":"Kramerg",
    "iso:country":"AT",
    "sg:address":"Kramerg 1/3",
    "sg:city":"Wien",
    "sg:orig_category":"Unternehmensberatung",
    "sg:phone":"+43 1 5321895",
    "sg:postcode":"1010",
    "sg:province":"Wien",
    "wof:name":"FH Consult Ing. Hrachowitz",
    "wof:placetype":"venue"
},
  "geometry": {"coordinates":[16.3724555969,48.2095794678],"type":"Point"}
}