{
  "type": "Feature",
  "properties": {
    "addr:full":"Steinamangerer Str 157 Oberwart Burgenland 7400",
    "addr:housenumber":"157",
    "addr:postcode":"7400",
    "addr:street":"Str",
    "iso:country":"AT",
    "sg:address":"Steinamangerer Str 157",
    "sg:city":"Oberwart",
    "sg:classifiers":[
        {
            "category":"Shopping",
            "subcategory":"Thrift Store",
            "type":"Retail Goods"
        }
    ],
    "sg:phone":"+43 3352 33477",
    "sg:postcode":"7400",
    "sg:province":"Burgenland",
    "sg:tags":[
        "second-hand-shops"
    ],
    "wof:name":"Kinderwelt",
    "wof:placetype":"venue"
},
  "geometry": {"coordinates":[16.2302112579,47.2759819031],"type":"Point"}
}