{
  "type": "Feature",
  "properties": {
    "addr:full":"Sturzgasse 6b Wien Wien 1150",
    "addr:housenumber":"6b",
    "addr:postcode":"1150",
    "addr:street":"Sturzgasse",
    "iso:country":"AT",
    "sg:address":"Sturzgasse 6b",
    "sg:city":"Wien",
    "sg:classifiers":[
        {
            "category":"Home & Garden",
            "subcategory":"Building Materials",
            "type":"Retail Goods"
        }
    ],
    "sg:phone":"+43 1 9821338",
    "sg:postcode":"1150",
    "sg:province":"Wien",
    "sg:tags":[
        "steel",
        "balcony"
    ],
    "wof:name":"Richard Morais Inh. Wolfgang Schmid",
    "wof:placetype":"venue"
},
  "geometry": {"coordinates":[16.3162136078,48.1941146851],"type":"Point"}
}