{
  "type": "Feature",
  "properties": {
    "iso:country":"AT",
    "sg:address":"Hertha Kr\u00e4ftner-G 4",
    "sg:city":"Wien",
    "sg:orig_category":"Dichtungen",
    "sg:phone":"+43 1 4064733",
    "sg:postcode":"1210",
    "sg:province":"Wien",
    "sg:website":"busakshamban.at",
    "wof:name":"Busak + Shamban \u00d6sterreich GmbH",
    "wof:placetype":"venue"
},
  "geometry": {"coordinates":[16.4324913025,48.2691841125],"type":"Point"}
}