{
  "type": "Feature",
  "properties": {
    "addr:full":"Liesing 38 Liesing K\u00e4rnten 9653",
    "addr:housenumber":"38",
    "addr:postcode":"9653",
    "addr:street":"Liesing;Kaernten",
    "iso:country":"AT",
    "sg:address":"Liesing 38",
    "sg:city":"Liesing",
    "sg:classifiers":[
        {
            "category":"Home & Garden",
            "subcategory":"Building Materials",
            "type":"Retail Goods"
        }
    ],
    "sg:phone":"+43 4716 218",
    "sg:postcode":"9653",
    "sg:province":"K\u00e4rnten",
    "sg:tags":[
        "railing",
        "balcony"
    ],
    "wof:name":"Herwig Unter\u00fcberbacher",
    "wof:placetype":"venue"
},
  "geometry": {"coordinates":[12.8082408905,46.694065094],"type":"Point"}
}