{
  "type": "Feature",
  "properties": {
    "addr:full":"Hauptpl 84 Eibiswald Steiermark 8552",
    "addr:housenumber":"84",
    "addr:postcode":"8552",
    "addr:street":"Hauptpl",
    "iso:country":"AT",
    "sg:address":"Hauptpl 84",
    "sg:city":"Eibiswald",
    "sg:orig_category":"Maler, Anstreicher U Lackierer",
    "sg:phone":"+43 4334 6642332",
    "sg:postcode":"8552",
    "sg:province":"Steiermark",
    "wof:name":"Jauk Alfred & Co",
    "wof:placetype":"venue"
},
  "geometry": {"coordinates":[15.2274599075,46.6824150085],"type":"Point"}
}