{
  "type": "Feature",
  "properties": {
    "addr:full":"Nr 138 Pruggern Steiermark 8965",
    "addr:postcode":"8965",
    "addr:street":"Nr 138",
    "iso:country":"AT",
    "sg:address":"Nr 138",
    "sg:city":"Pruggern",
    "sg:classifiers":[
        {
            "category":"Taxi",
            "type":"Transportation"
        }
    ],
    "sg:phone":"+43 4336 8523999",
    "sg:postcode":"8965",
    "sg:province":"Steiermark",
    "sg:tags":[
        "personentransporte",
        "u"
    ],
    "wof:name":"TAXI+BUS - Seebacher Claudia",
    "wof:placetype":"venue"
},
  "geometry": {"coordinates":[13.8756341934,47.4231910706],"type":"Point"}
}