{
  "type": "Feature",
  "properties": {
    "addr:full":"Gemeindeg 30 Hirm Burgenland 7024",
    "addr:housenumber":"30",
    "addr:postcode":"7024",
    "addr:street":"Gemeindeg",
    "iso:country":"AT",
    "sg:address":"Gemeindeg 30",
    "sg:city":"Hirm",
    "sg:orig_category":"Damenmoden",
    "sg:phone":"+43 2687 47290",
    "sg:postcode":"7024",
    "sg:province":"Burgenland",
    "wof:name":"Jammernegg GmbH",
    "wof:placetype":"venue"
},
  "geometry": {"coordinates":[16.4545059204,47.7873191833],"type":"Point"}
}