{
  "type": "Feature",
  "properties": {
    "addr:full":"Nr 17 P\u00f6lfing-Brunn Steiermark 8544",
    "addr:postcode":"8544",
    "addr:street":"Nr 17 Poelfing-Brunn Steiermark",
    "iso:country":"AT",
    "sg:address":"Nr 17",
    "sg:city":"P\u00f6lfing-Brunn",
    "sg:orig_category":"Autobusunternehmen",
    "sg:phone":"+43 4334 652160",
    "sg:postcode":"8544",
    "sg:province":"Steiermark",
    "wof:name":"Muchitsch Franz",
    "wof:placetype":"venue"
},
  "geometry": {"coordinates":[15.2971801758,46.730178833],"type":"Point"}
}