{
  "type": "Feature",
  "properties": {
    "addr:full":"Wohllebenggasse 18 Wien Wien 1040",
    "addr:housenumber":"18",
    "addr:postcode":"1040",
    "addr:street":"Wohllebenggasse",
    "iso:country":"AT",
    "sg:address":"Wohllebenggasse 18",
    "sg:city":"Wien",
    "sg:classifiers":[
        {
            "category":"Parking",
            "subcategory":"Lot",
            "type":"Transportation"
        }
    ],
    "sg:phone":"+43 4315 01560",
    "sg:postcode":"1040",
    "sg:province":"Wien",
    "sg:tags":[
        "transport",
        "road"
    ],
    "wof:name":"EXPRESS-INTERFRACHT INTERNATIONALE SPEDITIONS GES.MBH",
    "wof:placetype":"venue"
},
  "geometry": {"coordinates":[16.3729133606,48.1962890625],"type":"Point"}
}