{
  "type": "Feature",
  "properties": {
    "iso:country":"AT",
    "sg:address":"Bahnstr 10",
    "sg:city":"Neumarkt an der Ybbs",
    "sg:orig_category":"Gie\u00c3\u0178ereien",
    "sg:phone":"+43 7412 524170",
    "sg:postcode":"3371",
    "sg:province":"Nieder\u00f6sterreich",
    "wof:name":"Steininger Franz GesmbH",
    "wof:placetype":"venue"
},
  "geometry": {"coordinates":[15.0543022156,48.1419181824],"type":"Point"}
}