{
  "type": "Feature",
  "properties": {
    "iso:country":"AT",
    "sg:address":"Nr 99",
    "sg:city":"Neumarkt in Steiermark",
    "sg:orig_category":"Elektroinstallationsunternehmen",
    "sg:phone":"+43 4335 843727",
    "sg:postcode":"8820",
    "sg:province":"Steiermark",
    "wof:name":"Elektro Markolin",
    "wof:placetype":"venue"
},
  "geometry": {"coordinates":[14.4293413162,47.0666313171],"type":"Point"}
}