{
  "type": "Feature",
  "properties": {
    "addr:full":"Hauptstr 21 Felixdorf Nieder\u00f6sterreich 2603",
    "addr:housenumber":"21",
    "addr:postcode":"2603",
    "addr:street":"Hauptstr",
    "iso:country":"AT",
    "sg:address":"Hauptstr 21",
    "sg:city":"Felixdorf",
    "sg:orig_category":"Bestattungsunternehmen",
    "sg:phone":"+43 2628 62200",
    "sg:postcode":"2603",
    "sg:province":"Nieder\u00f6sterreich",
    "wof:name":"Ramoser Hannes OHG",
    "wof:placetype":"venue"
},
  "geometry": {"coordinates":[16.2438716888,47.8828392029],"type":"Point"}
}