{
  "type": "Feature",
  "properties": {
    "iso:country":"AT",
    "sg:address":"Hauptstr 18",
    "sg:city":"Ravelsbach",
    "sg:orig_category":"Friseure U Frisiersalons",
    "sg:phone":"+43 4329 588530",
    "sg:postcode":"3720",
    "sg:province":"Nieder\u00f6sterreich",
    "wof:name":"S\u00fc\u00df Christa",
    "wof:placetype":"venue"
},
  "geometry": {"coordinates":[15.8481168747,48.550994873],"type":"Point"}
}