{
  "type": "Feature",
  "properties": {
    "iso:country":"AT",
    "sg:address":"Keplerg 12",
    "sg:city":"Weiz",
    "sg:orig_category":"Rauchfangkehrer",
    "sg:phone":"+43 3172 27470",
    "sg:postcode":"8160",
    "sg:province":"Steiermark",
    "wof:name":"Schl\u00f6gl Eva",
    "wof:placetype":"venue"
},
  "geometry": {"coordinates":[15.6360254288,47.2205352783],"type":"Point"}
}