{
  "type": "Feature",
  "properties": {
    "iso:country":"AT",
    "sg:address":"Altstadt 29",
    "sg:city":"Bruck an der Leitha",
    "sg:orig_category":"Reifen U Reifendienste",
    "sg:phone":"+43 4321 6262287",
    "sg:postcode":"2460",
    "sg:province":"Nieder\u00f6sterreich",
    "wof:name":"Reifen-Ritz GesmbH",
    "wof:placetype":"venue"
},
  "geometry": {"coordinates":[16.7742958069,48.0218162537],"type":"Point"}
}