{
  "type": "Feature",
  "properties": {
    "addr:full":"Bischofstr 5 Linz Ober\u00f6sterreich 4020",
    "addr:housenumber":"5",
    "addr:postcode":"4020",
    "addr:street":"Bischofstr",
    "iso:country":"AT",
    "sg:address":"Bischofstr 5",
    "sg:city":"Linz",
    "sg:orig_category":"Werbeagenturen",
    "sg:phone":"+43 732 778877",
    "sg:postcode":"4020",
    "sg:province":"Ober\u00f6sterreich",
    "wof:name":"Bogner & Bogner OEG",
    "wof:placetype":"venue"
},
  "geometry": {"coordinates":[14.288898468,48.3017654419],"type":"Point"}
}