{
  "type": "Feature",
  "properties": {
    "iso:country":"AT",
    "sg:address":"Laaer Str 48",
    "sg:city":"Niederleis",
    "sg:orig_category":"Fassaden",
    "sg:phone":"+43 2576 2622",
    "sg:postcode":"2116",
    "sg:province":"Nieder\u00f6sterreich",
    "wof:name":"BVS Bau GmbH",
    "wof:placetype":"venue"
},
  "geometry": {"coordinates":[16.3866825104,48.5457305908],"type":"Point"}
}