{
  "type": "Feature",
  "properties": {
    "iso:country":"AT",
    "sg:address":"Schulstr 5",
    "sg:city":"Bad Sauerbrunn",
    "sg:orig_category":"Apotheken",
    "sg:phone":"+43 2625 32201",
    "sg:postcode":"7202",
    "sg:province":"Burgenland",
    "wof:name":"Kurbad-Apotheke Mag pharm Safai Jajou Roumaia KG",
    "wof:placetype":"venue"
},
  "geometry": {"coordinates":[16.3255710602,47.7754936218],"type":"Point"}
}