{
  "type": "Feature",
  "properties": {
    "addr:full":"Unterer Markt 35 Gresten Nieder\u00f6sterreich 3264",
    "addr:housenumber":"35",
    "addr:postcode":"3264",
    "addr:street":"Unterer Markt",
    "iso:country":"AT",
    "sg:address":"Unterer Markt 35",
    "sg:city":"Gresten",
    "sg:orig_category":"Banken U Sparkassen",
    "sg:phone":"+43 4374 8723280",
    "sg:postcode":"3264",
    "sg:province":"Nieder\u00f6sterreich",
    "wof:name":"Raiffeisenbank im Erlauftal regGenmbH",
    "wof:placetype":"venue"
},
  "geometry": {"coordinates":[15.0251569748,47.9853591919],"type":"Point"}
}