{
  "type": "Feature",
  "properties": {
    "addr:full":"Neuwaldegger Str 27 Wien Wien 1170",
    "addr:postcode":"1170",
    "addr:street":"Str 27",
    "iso:country":"AT",
    "sg:address":"Neuwaldegger Str 27",
    "sg:city":"Wien",
    "sg:orig_category":"Alternativtherapie",
    "sg:phone":"+43 1 4899406",
    "sg:postcode":"1170",
    "sg:province":"Wien",
    "wof:name":"Veeck Christopher Mag",
    "wof:placetype":"venue"
},
  "geometry": {"coordinates":[16.2868061066,48.2372055054],"type":"Point"}
}