{
  "type": "Feature",
  "properties": {
    "addr:full":"Ing Baller-Str 4 Imst Tirol 6460",
    "addr:housenumber":"4",
    "addr:postcode":"6460",
    "addr:street":"Imst Tirol",
    "iso:country":"AT",
    "sg:address":"Ing Baller-Str 4",
    "sg:city":"Imst",
    "sg:orig_category":"Fernseh- U Radiogesellschaften",
    "sg:phone":"+43 5412 66900",
    "sg:postcode":"6460",
    "sg:province":"Tirol",
    "wof:name":"Radio Arabella Oberland",
    "wof:placetype":"venue"
},
  "geometry": {"coordinates":[10.7392530441,47.2363395691],"type":"Point"}
}