{
  "type": "Feature",
  "properties": {
    "iso:country":"AT",
    "sg:address":"Alszeile 118",
    "sg:city":"Wien",
    "sg:orig_category":"Lebensmittel / Einzelhandel",
    "sg:phone":"+43 1 4864117",
    "sg:postcode":"1170",
    "sg:province":"Wien",
    "wof:name":"BOZALIJA KEG",
    "wof:placetype":"venue"
},
  "geometry": {"coordinates":[16.2971553802,48.2305297852],"type":"Point"}
}