{
  "type": "Feature",
  "properties": {
    "iso:country":"AT",
    "sg:address":"Am Bach 1",
    "sg:city":"Anif",
    "sg:orig_category":"Pensionen / Privatzimmer",
    "sg:phone":"+43 6246 72512",
    "sg:postcode":"5081",
    "sg:province":"Salzburg",
    "wof:name":"Luisenhof",
    "wof:placetype":"venue"
},
  "geometry": {"coordinates":[13.0717172623,47.7506980896],"type":"Point"}
}