{
  "type": "Feature",
  "properties": {
    "addr:full":"Habsburgerg 2 Wien Wien 1010",
    "addr:housenumber":"2",
    "addr:postcode":"1010",
    "addr:street":"Habsburgerg",
    "iso:country":"AT",
    "sg:address":"Habsburgerg 2",
    "sg:city":"Wien",
    "sg:orig_category":"Boutiquen",
    "sg:phone":"+43 1 5326334",
    "sg:postcode":"1010",
    "sg:province":"Wien",
    "wof:name":"Boutique Kasha",
    "wof:placetype":"venue"
},
  "geometry": {"coordinates":[16.3687534332,48.2088699341],"type":"Point"}
}