{
  "type": "Feature",
  "properties": {
    "addr:full":"Julius-Ficker-Str 77 Wien Wien 1210",
    "addr:housenumber":"77",
    "addr:postcode":"1210",
    "addr:street":"Julius-Ficker-Str",
    "iso:country":"AT",
    "sg:address":"Julius-Ficker-Str 77",
    "sg:city":"Wien",
    "sg:orig_category":"Tankstellen",
    "sg:phone":"+43 1 2596075",
    "sg:postcode":"1210",
    "sg:province":"Wien",
    "wof:name":"OMV AG",
    "wof:placetype":"venue"
},
  "geometry": {"coordinates":[16.4489459991,48.266494751],"type":"Point"}
}