{
  "type": "Feature",
  "properties": {
    "iso:country":"AT",
    "sg:address":"Neunkirchner Str 56",
    "sg:city":"Wiener Neustadt",
    "sg:orig_category":"Fenster",
    "sg:phone":"+43 2622 28235",
    "sg:postcode":"2700",
    "sg:province":"Nieder\u00f6sterreich",
    "wof:name":"Leitner Fenster- T\u00fcren",
    "wof:placetype":"venue"
},
  "geometry": {"coordinates":[16.2381858826,47.8055801392],"type":"Point"}
}