{
  "type": "Feature",
  "properties": {
    "iso:country":"AT",
    "sg:address":"Siemensstr. 5",
    "sg:city":"Klagenfurt",
    "sg:classifiers":[
        {
            "category":"Home & Garden",
            "subcategory":"Home Furnishings",
            "type":"Retail Goods"
        }
    ],
    "sg:phone":"+43 4346 35563861",
    "sg:postcode":"9020",
    "sg:province":"K\u00e4rnten",
    "sg:tags":[
        "household"
    ],
    "wof:name":"SLAMA VERGOLDER GMBH",
    "wof:placetype":"venue"
},
  "geometry": {"coordinates":[14.3059329987,46.6302108765],"type":"Point"}
}