{
  "type": "Feature",
  "properties": {
    "addr:full":"Stift Metten-Str 2 Amstetten Nieder\u00f6sterreich 3300",
    "addr:housenumber":"2",
    "addr:postcode":"3300",
    "addr:street":"Metten-Str;Niederoesterreich",
    "iso:country":"AT",
    "sg:address":"Stift Metten-Str 2",
    "sg:city":"Amstetten",
    "sg:orig_category":"Feuerwehren",
    "sg:phone":"+43 7472 65784",
    "sg:postcode":"3300",
    "sg:province":"Nieder\u00f6sterreich",
    "wof:name":"Freiwillige Feuerwehr Preinsbach",
    "wof:placetype":"venue"
},
  "geometry": {"coordinates":[14.8888025284,48.1333847046],"type":"Point"}
}