{
  "type": "Feature",
  "properties": {
    "addr:full":"Triester Str 306 Feldkirchen Steiermark 8073",
    "addr:housenumber":"306",
    "addr:postcode":"8073",
    "iso:country":"AT",
    "sg:address":"Triester Str 306",
    "sg:city":"Feldkirchen",
    "sg:orig_category":"Armaturen / Erzeugung U Gro\u00c3\u0178handel",
    "sg:phone":"+43 4331 35532440",
    "sg:postcode":"8073",
    "sg:province":"Steiermark",
    "sg:website":"moerth-armaturen.com",
    "wof:name":"M\u00f6rth Rudolf GesmbH",
    "wof:placetype":"venue"
},
  "geometry": {"coordinates":[15.4594125748,46.9843673706],"type":"Point"}
}