{
  "type": "Feature",
  "properties": {
    "addr:full":"Mitterbauerstrasse 6 Ansfelden Ober\u00f6sterreich 4052",
    "addr:housenumber":"6",
    "addr:postcode":"4052",
    "addr:street":"Mitterbauerstrasse",
    "iso:country":"AT",
    "sg:address":"Mitterbauerstrasse 6",
    "sg:city":"Ansfelden",
    "sg:classifiers":[
        {
            "category":"Wholesale",
            "subcategory":"Plants",
            "type":"Manufacturing & Wholesale Goods"
        }
    ],
    "sg:phone":"+43 732 3153170",
    "sg:postcode":"4052",
    "sg:province":"Ober\u00f6sterreich",
    "sg:tags":[
        "machine",
        "industrial",
        "automation"
    ],
    "sg:website":"imk-automation.com",
    "wof:name":"Ing. Manfred Krista",
    "wof:placetype":"venue"
},
  "geometry": {"coordinates":[14.302646637,48.2268829346],"type":"Point"}
}