{
  "type": "Feature",
  "properties": {
    "iso:country":"AT",
    "sg:address":"Schulallee 9",
    "sg:city":"Seeboden",
    "sg:orig_category":"Kinderbetreuung",
    "sg:phone":"+43 4367 688987103",
    "sg:postcode":"9871",
    "sg:province":"K\u00e4rnten",
    "wof:name":"Hort Seeboden Kindernest gemGmbH",
    "wof:placetype":"venue"
},
  "geometry": {"coordinates":[13.5172948837,46.8196754456],"type":"Point"}
}