{
  "type": "Feature",
  "properties": {
    "addr:full":"Dr.-Karl-Renner-Weg 14 Velden am W\u00f6rther See K\u00e4rnten 9220",
    "addr:housenumber":"14",
    "addr:postcode":"9220",
    "addr:street":"Dr.-Karl-Renner-Weg;Kaernten",
    "iso:country":"AT",
    "sg:address":"Dr.-Karl-Renner-Weg 14",
    "sg:city":"Velden am W\u00f6rther See",
    "sg:orig_category":"Architekten",
    "sg:phone":"+43 4342 743918",
    "sg:postcode":"9220",
    "sg:province":"K\u00e4rnten",
    "wof:name":"Kopeinig Gerhard Arch Dipl-Ing Staatlich befugter und beeidigter Ziviltechniker ARCH+MORE",
    "wof:placetype":"venue"
},
  "geometry": {"coordinates":[13.997341156,46.6015357971],"type":"Point"}
}