{
  "type": "Feature",
  "properties": {
    "addr:full":"Sportplatzgasse 24 Kottingbrunn Nieder\u00f6sterreich 2542",
    "addr:housenumber":"24",
    "addr:postcode":"2542",
    "addr:street":"Sportplatzgasse",
    "iso:country":"AT",
    "sg:address":"Sportplatzgasse 24",
    "sg:city":"Kottingbrunn",
    "sg:classifiers":[
        {
            "category":"Retail",
            "subcategory":"Car Wash",
            "type":"Services"
        }
    ],
    "sg:phone":"+43 2252 251047",
    "sg:postcode":"2542",
    "sg:province":"Nieder\u00f6sterreich",
    "sg:tags":[
        "machine",
        "banding"
    ],
    "wof:name":"Woda & Tanner GmbH",
    "wof:placetype":"venue"
},
  "geometry": {"coordinates":[16.2287769318,47.9472618103],"type":"Point"}
}