{
  "type": "Feature",
  "properties": {
    "iso:country":"AT",
    "sg:address":"Engerthstr 267-269",
    "sg:city":"Wien",
    "sg:orig_category":"Sporthallen",
    "sg:phone":"+43 1 72951340",
    "sg:postcode":"1020",
    "sg:province":"Wien",
    "wof:name":"Dusika Hallenstadion",
    "wof:placetype":"venue"
},
  "geometry": {"coordinates":[16.4227561951,48.2106933594],"type":"Point"}
}