{
  "type": "Feature",
  "properties": {
    "addr:full":"Krotenthallerg 3 Wien Wien 1080",
    "addr:housenumber":"3",
    "addr:postcode":"1080",
    "addr:street":"Krotenthallerg",
    "iso:country":"AT",
    "sg:address":"Krotenthallerg 3",
    "sg:city":"Wien",
    "sg:orig_category":"Non-Classified Establishments",
    "sg:phone":"+43 1 401460",
    "sg:postcode":"1080",
    "sg:province":"Wien",
    "wof:name":"Bundesamt f Eich- und Vermessungswesen (BEV)",
    "wof:placetype":"venue"
},
  "geometry": {"coordinates":[16.3457717896,48.2117424011],"type":"Point"}
}