{
  "type": "Feature",
  "properties": {
    "addr:full":"Pelikanstr 5 Salzburg Salzburg 5020",
    "addr:housenumber":"5",
    "addr:postcode":"5020",
    "addr:street":"Pelikanstr;Salzburg",
    "iso:country":"AT",
    "sg:address":"Pelikanstr 5",
    "sg:city":"Salzburg",
    "sg:orig_category":"Waagen / Einzelhandel",
    "sg:phone":"+43 662 876630",
    "sg:postcode":"5020",
    "sg:province":"Salzburg",
    "wof:name":"MGT Technics Meierhofer Gr\u00fcnwald GmbH",
    "wof:placetype":"venue"
},
  "geometry": {"coordinates":[13.0527696609,47.8126373291],"type":"Point"}
}