{
  "type": "Feature",
  "properties": {
    "iso:country":"AT",
    "sg:address":"Haidfeldstrasse 25",
    "sg:city":"Leonding",
    "sg:classifiers":[
        {
            "category":"Manufacturing",
            "subcategory":"Signs",
            "type":"Manufacturing & Wholesale Goods"
        }
    ],
    "sg:phone":"+43 732 682196",
    "sg:postcode":"4060",
    "sg:province":"Ober\u00f6sterreich",
    "sg:tags":[
        "aluminium"
    ],
    "sg:website":"schwark.at",
    "wof:name":"Dieter Erich Schwark",
    "wof:placetype":"venue"
},
  "geometry": {"coordinates":[14.2599143982,48.2564353943],"type":"Point"}
}