{
  "type": "Feature",
  "properties": {
    "addr:full":"Grazerstrasse 467 Deutschfeistritz Steiermark 8121",
    "addr:housenumber":"467",
    "addr:postcode":"8121",
    "addr:street":"Grazerstrasse",
    "iso:country":"AT",
    "sg:address":"Grazerstrasse 467",
    "sg:city":"Deutschfeistritz",
    "sg:classifiers":[
        {
            "category":"Professional",
            "subcategory":"Engineering",
            "type":"Services"
        }
    ],
    "sg:phone":"+43 3127 409300",
    "sg:postcode":"8121",
    "sg:province":"Steiermark",
    "sg:tags":[
        "manufacturing",
        "cnc"
    ],
    "sg:website":"stadlercnc.at",
    "wof:name":"STADLER Sensorik CNC Technik GmbH Feinstdrehen - Prototypenbau - Medizintechnik",
    "wof:placetype":"venue"
},
  "geometry": {"coordinates":[15.3356399536,47.1943855286],"type":"Point"}
}