{
  "type": "Feature",
  "properties": {
    "iso:country":"AT",
    "sg:address":"Emmenstr 7",
    "sg:city":"Bad Radkersburg",
    "sg:orig_category":"Politische Parteien",
    "sg:phone":"+43 3476 3636",
    "sg:postcode":"8490",
    "sg:province":"Steiermark",
    "wof:name":"Freiheitliche Partei \u00f6sterreichs (FP\u00f6)",
    "wof:placetype":"venue"
},
  "geometry": {"coordinates":[15.9874315262,46.6889076233],"type":"Point"}
}