{
  "type": "Feature",
  "properties": {
    "iso:country":"AT",
    "sg:address":"Rennfeld 18a",
    "sg:city":"Kitzb\u00fchel",
    "sg:classifiers":[
        {
            "category":"Manufacturing",
            "subcategory":"Furniture",
            "type":"Manufacturing & Wholesale Goods"
        }
    ],
    "sg:phone":"+43 5356 65639",
    "sg:postcode":"6370",
    "sg:province":"Tirol",
    "sg:tags":[
        "bedroom"
    ],
    "wof:name":"Tischlerei D\u00fcnser Ges.m.b.H.",
    "wof:placetype":"venue"
},
  "geometry": {"coordinates":[12.3884315491,47.4555511475],"type":"Point"}
}