{
  "type": "Feature",
  "properties": {
    "addr:full":"Ringstr 247 Bad Gleichenberg Steiermark 8344",
    "addr:housenumber":"247",
    "addr:postcode":"8344",
    "iso:country":"AT",
    "sg:address":"Ringstr 247",
    "sg:city":"Bad Gleichenberg",
    "sg:orig_category":"Rauchfangkehrer",
    "sg:phone":"+43 4331 592218",
    "sg:postcode":"8344",
    "sg:province":"Steiermark",
    "wof:name":"Hartinger Franz",
    "wof:placetype":"venue"
},
  "geometry": {"coordinates":[15.9055433273,46.8777656555],"type":"Point"}
}