{
  "type": "Feature",
  "properties": {
    "iso:country":"AT",
    "sg:address":"Tiefenbach 27",
    "sg:city":"Weitra",
    "sg:classifiers":[
        {
            "category":"Building & Trades",
            "subcategory":"Construction",
            "type":"Services"
        }
    ],
    "sg:phone":"+43 2856 2428",
    "sg:postcode":"3970",
    "sg:province":"Nieder\u00f6sterreich",
    "sg:tags":[
        "central",
        "heating",
        "system"
    ],
    "sg:website":"smutka.com",
    "wof:name":"Peter Smutka",
    "wof:placetype":"venue"
},
  "geometry": {"coordinates":[14.8905534744,48.7053260803],"type":"Point"}
}