{
  "type": "Feature",
  "properties": {
    "addr:full":"Nr 38 Kemmelbach Nieder\u00f6sterreich 3373",
    "addr:postcode":"3373",
    "addr:street":"Nr;Niederoesterreich",
    "iso:country":"AT",
    "sg:address":"Nr 38",
    "sg:city":"Kemmelbach",
    "sg:orig_category":"Lebensmittel / Erzeugung U Gro\u00c3\u0178handel",
    "sg:phone":"+43 7412 53005",
    "sg:postcode":"3373",
    "sg:province":"Nieder\u00f6sterreich",
    "wof:name":"Pizza & Baguette GmbH",
    "wof:placetype":"venue"
},
  "geometry": {"coordinates":[15.0943393707,48.1549682617],"type":"Point"}
}