{
  "type": "Feature",
  "properties": {
    "addr:full":"Dorf 32b Eugendorf Salzburg 5301",
    "addr:housenumber":"32b",
    "addr:postcode":"5301",
    "addr:street":"Dorf;Salzburg",
    "iso:country":"AT",
    "sg:address":"Dorf 32b",
    "sg:city":"Eugendorf",
    "sg:orig_category":"Fassaden",
    "sg:phone":"+43 6225 7822",
    "sg:postcode":"5301",
    "sg:province":"Salzburg",
    "wof:name":"BONE Fassadenbau GmbH",
    "wof:placetype":"venue"
},
  "geometry": {"coordinates":[13.1218156815,47.8679084778],"type":"Point"}
}