{
  "type": "Feature",
  "properties": {
    "addr:full":"Herbststr 49 Wien Wien 1160",
    "addr:housenumber":"49",
    "addr:postcode":"1160",
    "addr:street":"Herbststr",
    "iso:country":"AT",
    "sg:address":"Herbststr 49",
    "sg:city":"Wien",
    "sg:orig_category":"Anlagenbau U -Technik",
    "sg:phone":"+43 1 4947188",
    "sg:postcode":"1160",
    "sg:province":"Wien",
    "wof:name":"CEMCON Mineraltechnische Anlagen GmbH",
    "wof:placetype":"venue"
},
  "geometry": {"coordinates":[16.3269615173,48.2062454224],"type":"Point"}
}