{
  "type": "Feature",
  "properties": {
    "addr:full":"Schottenfeldg 42-44 Wien Wien 1070",
    "addr:postcode":"42-44;1070",
    "iso:country":"AT",
    "sg:address":"Schottenfeldg 42-44",
    "sg:city":"Wien",
    "sg:orig_category":"Hydrokulturen",
    "sg:phone":"+43 664 4145215",
    "sg:postcode":"1070",
    "sg:province":"Wien",
    "sg:website":"www.ammon.at",
    "wof:name":"Ammon KG",
    "wof:placetype":"venue"
},
  "geometry": {"coordinates":[16.3434257507,48.2012634277],"type":"Point"}
}