{
  "type": "Feature",
  "properties": {
    "iso:country":"AT",
    "sg:address":"Dr.-Skala-Strasse 3-5",
    "sg:city":"Wien",
    "sg:classifiers":[
        {
            "category":"Building & Trades",
            "subcategory":"Construction",
            "type":"Services"
        }
    ],
    "sg:phone":"+43 1 2902972",
    "sg:postcode":"1210",
    "sg:province":"Wien",
    "sg:tags":[
        "dry"
    ],
    "wof:name":"Stuck + Innenausbau Wilhelm H\u00f6ger",
    "wof:placetype":"venue"
},
  "geometry": {"coordinates":[16.4191150665,48.2992897034],"type":"Point"}
}