{
  "type": "Feature",
  "properties": {
    "addr:full":"Kremsegger Str. 15 Kremsm\u00fcnster Ober\u00f6sterreich 4550",
    "addr:postcode":"4550",
    "addr:street":"Str. 15 Kremsmuenster Oberoesterreich",
    "iso:country":"AT",
    "sg:address":"Kremsegger Str. 15",
    "sg:city":"Kremsm\u00fcnster",
    "sg:classifiers":[
        {
            "category":"Manufacturing",
            "subcategory":"Metals",
            "type":"Manufacturing & Wholesale Goods"
        }
    ],
    "sg:phone":"+43 4375 835140",
    "sg:postcode":"4550",
    "sg:province":"Ober\u00f6sterreich",
    "sg:tags":[
        "metallurgy",
        "metalworking"
    ],
    "wof:name":"SPG - WERKZEUGBAU GES.MBH",
    "wof:placetype":"venue"
},
  "geometry": {"coordinates":[14.1393127441,48.0569000244],"type":"Point"}
}