{
  "type": "Feature",
  "properties": {
    "addr:full":"Apostelg 13 Wien Wien 1030",
    "addr:housenumber":"13",
    "addr:postcode":"1030",
    "addr:street":"Apostelg",
    "iso:country":"AT",
    "sg:address":"Apostelg 13",
    "sg:city":"Wien",
    "sg:orig_category":"Restaurants: Chinesisch",
    "sg:phone":"+43 1 7136068",
    "sg:postcode":"1030",
    "sg:province":"Wien",
    "wof:name":"China-Restaurant Prinz",
    "wof:placetype":"venue"
},
  "geometry": {"coordinates":[16.3972396851,48.1988372803],"type":"Point"}
}