{
  "type": "Feature",
  "properties": {
    "iso:country":"AT",
    "sg:address":"Wollzeile 2",
    "sg:city":"Wien",
    "sg:orig_category":"Non-Classified Establishments",
    "sg:phone":"+43 1 51348310",
    "sg:postcode":"1010",
    "sg:province":"Wien",
    "wof:name":"Erzbisch\u00f6fliches Rentamt",
    "wof:placetype":"venue"
},
  "geometry": {"coordinates":[16.3736248016,48.2093925476],"type":"Point"}
}