{
  "type": "Feature",
  "properties": {
    "addr:full":"Albrechtstr 55-57 Klosterneuburg Nieder\u00f6sterreich 3400",
    "addr:housenumber":"55-57",
    "addr:postcode":"3400",
    "addr:street":"Niederoesterreich",
    "iso:country":"AT",
    "sg:address":"Albrechtstr 55-57",
    "sg:city":"Klosterneuburg",
    "sg:orig_category":"Tapezierer U Dekorateure",
    "sg:phone":"+43 4322 4337994",
    "sg:postcode":"3400",
    "sg:province":"Nieder\u00f6sterreich",
    "wof:name":"Seltenlach Heinz",
    "wof:placetype":"venue"
},
  "geometry": {"coordinates":[16.3195457458,48.3103790283],"type":"Point"}
}