{
  "type": "Feature",
  "properties": {
    "iso:country":"AT",
    "sg:city":"Altaussee",
    "sg:orig_category":"Reisen, Tourismusinfo",
    "sg:phone":"+43 4336 2286666",
    "sg:postcode":"8992",
    "sg:province":"Steiermark",
    "sg:website":"http://www.grundlsee.at",
    "wof:name":"Grundlsee",
    "wof:placetype":"venue"
},
  "geometry": {"coordinates":[13.764960289,47.6403694153],"type":"Point"}
}