{
  "type": "Feature",
  "properties": {
    "iso:country":"AT",
    "sg:address":"Ritterg 4",
    "sg:city":"Wien",
    "sg:orig_category":"Geschenkartikel",
    "sg:phone":"+43 1 58726100",
    "sg:postcode":"1040",
    "sg:province":"Wien",
    "wof:name":"Kolbenheyer E",
    "wof:placetype":"venue"
},
  "geometry": {"coordinates":[16.3634567261,48.1932449341],"type":"Point"}
}