{
  "type": "Feature",
  "properties": {
    "addr:full":"Michaelsbergstr 1 Leonding Ober\u00f6sterreich 4060",
    "addr:housenumber":"1",
    "addr:postcode":"4060",
    "addr:street":"Michaelsbergstr",
    "iso:country":"AT",
    "sg:address":"Michaelsbergstr 1",
    "sg:city":"Leonding",
    "sg:orig_category":"Fotografen",
    "sg:phone":"+43 732 682737",
    "sg:postcode":"4060",
    "sg:province":"Ober\u00f6sterreich",
    "sg:website":"foto-berger.at",
    "wof:name":"Berger Margit",
    "wof:placetype":"venue"
},
  "geometry": {"coordinates":[14.2491903305,48.2772598267],"type":"Point"}
}