{
  "type": "Feature",
  "properties": {
    "iso:country":"AT",
    "sg:address":"Missindorfstr 15",
    "sg:city":"Wien",
    "sg:orig_category":"Autospenglereien",
    "sg:phone":"+43 1 9820418",
    "sg:postcode":"1140",
    "sg:province":"Wien",
    "wof:name":"KFZ Singer OEG",
    "wof:placetype":"venue"
},
  "geometry": {"coordinates":[16.3058891296,48.195438385],"type":"Point"}
}