{
  "type": "Feature",
  "properties": {
    "addr:full":"Brunner Strasse 25 Wiener Neustadt Nieder\u00f6sterreich 2700",
    "addr:housenumber":"25",
    "addr:postcode":"2700",
    "addr:street":"Brunner Strasse",
    "iso:country":"AT",
    "sg:address":"Brunner Strasse 25",
    "sg:city":"Wiener Neustadt",
    "sg:classifiers":[
        {
            "category":"Home & Garden",
            "subcategory":"Building Materials",
            "type":"Retail Goods"
        }
    ],
    "sg:phone":"+43 2622 221940",
    "sg:postcode":"2700",
    "sg:province":"Nieder\u00f6sterreich",
    "sg:tags":[
        "installation",
        "electric"
    ],
    "sg:website":"witzmann.at",
    "wof:name":"Josef Witzmann Ges.m.b.H.",
    "wof:placetype":"venue"
},
  "geometry": {"coordinates":[16.2306423187,47.8012542725],"type":"Point"}
}