{
  "type": "Feature",
  "properties": {
    "addr:full":"Tiefental 2 Oberperfuss Tirol 6173",
    "addr:housenumber":"2",
    "addr:postcode":"6173",
    "addr:street":"Tiefental;Tirol",
    "iso:country":"AT",
    "sg:address":"Tiefental 2",
    "sg:city":"Oberperfuss",
    "sg:orig_category":"Schleifereien",
    "sg:phone":"+43 699 11702039",
    "sg:postcode":"6173",
    "sg:province":"Tirol",
    "wof:name":"Scharfer Stoffel - Christoph Peer",
    "wof:placetype":"venue"
},
  "geometry": {"coordinates":[11.2143268585,47.2310180664],"type":"Point"}
}