{
  "type": "Feature",
  "properties": {
    "addr:full":"Maiffredyg 14 Graz Steiermark 8010",
    "addr:housenumber":"14",
    "addr:postcode":"8010",
    "addr:street":"Maiffredyg",
    "iso:country":"AT",
    "sg:address":"Maiffredyg 14",
    "sg:city":"Graz",
    "sg:orig_category":"Reinigungsservice",
    "sg:phone":"+43 676 4775281",
    "sg:postcode":"8010",
    "sg:province":"Steiermark",
    "wof:name":"Fensterreinigung Toth",
    "wof:placetype":"venue"
},
  "geometry": {"coordinates":[15.4487886429,47.0716171265],"type":"Point"}
}