{
  "type": "Feature",
  "properties": {
    "addr:full":"Besenberg 25 Peuerbach Ober\u00f6sterreich 4722",
    "addr:housenumber":"25",
    "addr:postcode":"4722",
    "addr:street":"Besenberg",
    "iso:country":"AT",
    "sg:address":"Besenberg 25",
    "sg:city":"Peuerbach",
    "sg:orig_category":"Montagen U Montagetechnik",
    "sg:phone":"+43 7276 3952",
    "sg:postcode":"4722",
    "sg:province":"Ober\u00f6sterreich",
    "wof:name":"HARTL Service und Montagetechnik GmbH",
    "wof:placetype":"venue"
},
  "geometry": {"coordinates":[13.7683334351,48.3549575806],"type":"Point"}
}