{
  "type": "Feature",
  "properties": {
    "addr:full":"Johann-Steinb\u00f6ck-Str. 4 Brunn am Gebirge Nieder\u00f6sterreich 2345",
    "addr:housenumber":"4",
    "addr:postcode":"2345",
    "addr:street":"Johann-Steinboeck-Str.",
    "iso:country":"AT",
    "sg:address":"Johann-Steinb\u00f6ck-Str. 4",
    "sg:city":"Brunn am Gebirge",
    "sg:classifiers":[
        {
            "category":"Autos & Motor Vehicles",
            "subcategory":"Automobile Sales",
            "type":"Retail Goods"
        }
    ],
    "sg:phone":"+43 4322 3639020",
    "sg:postcode":"2345",
    "sg:province":"Nieder\u00f6sterreich",
    "sg:tags":[
        "industrial"
    ],
    "wof:name":"SCANIA \u00d6STERREICH GES.MBH",
    "wof:placetype":"venue"
},
  "geometry": {"coordinates":[16.3082447052,48.1107177734],"type":"Point"}
}