{
  "type": "Feature",
  "properties": {
    "addr:full":"Nr 1 Haus Steiermark 8967",
    "addr:postcode":"8967",
    "addr:street":"Nr;Haus",
    "iso:country":"AT",
    "sg:address":"Nr 1",
    "sg:city":"Haus",
    "sg:orig_category":"Museen / Ausstellungen",
    "sg:phone":"+43 3686 2316",
    "sg:postcode":"8967",
    "sg:province":"Steiermark",
    "wof:name":"Dekanatsmuseum Haus im Ennstal",
    "wof:placetype":"venue"
},
  "geometry": {"coordinates":[13.7679595947,47.4105949402],"type":"Point"}
}