{
  "type": "Feature",
  "properties": {
    "addr:full":"Grazer Vorstadt 11 Voitsberg Steiermark 8570",
    "addr:housenumber":"11",
    "addr:postcode":"8570",
    "addr:street":"Grazer Vorstadt",
    "iso:country":"AT",
    "sg:address":"Grazer Vorstadt 11",
    "sg:city":"Voitsberg",
    "sg:orig_category":"Tankstellen",
    "sg:phone":"+43 4331 42222870",
    "sg:postcode":"8570",
    "sg:province":"Steiermark",
    "wof:name":"Esso Austria GmbH",
    "wof:placetype":"venue"
},
  "geometry": {"coordinates":[15.1541223526,47.0477485657],"type":"Point"}
}