{
  "type": "Feature",
  "properties": {
    "addr:full":"S Charoux-Str 9 Langenzersdorf Nieder\u00f6sterreich 2103",
    "addr:housenumber":"9",
    "addr:postcode":"2103",
    "iso:country":"AT",
    "sg:address":"S Charoux-Str 9",
    "sg:city":"Langenzersdorf",
    "sg:orig_category":"Elektroinstallationsunternehmen",
    "sg:phone":"+43 2244 30714",
    "sg:postcode":"2103",
    "sg:province":"Nieder\u00f6sterreich",
    "wof:name":"Elektro Weber",
    "wof:placetype":"venue"
},
  "geometry": {"coordinates":[16.356470108,48.2972679138],"type":"Point"}
}