{
  "type": "Feature",
  "properties": {
    "addr:full":"Eisent\u00fcrg 10 Krems an der Donau Nieder\u00f6sterreich 3500",
    "addr:housenumber":"10",
    "addr:postcode":"3500",
    "addr:street":"Eisentuerg",
    "iso:country":"AT",
    "sg:address":"Eisent\u00fcrg 10",
    "sg:city":"Krems an der Donau",
    "sg:orig_category":"Maler, Anstreicher U Lackierer",
    "sg:phone":"+43 4327 32843850",
    "sg:postcode":"3500",
    "sg:province":"Nieder\u00f6sterreich",
    "wof:name":"Kreativ",
    "wof:placetype":"venue"
},
  "geometry": {"coordinates":[15.5965108871,48.4088058472],"type":"Point"}
}