{
  "type": "Feature",
  "properties": {
    "addr:full":"Wollzeile 14 Wien Wien 1010",
    "addr:housenumber":"14",
    "addr:postcode":"1010",
    "addr:street":"Wollzeile",
    "iso:country":"AT",
    "sg:address":"Wollzeile 14",
    "sg:city":"Wien",
    "sg:classifiers":[
        {
            "category":"Shopping",
            "subcategory":"Clothing, Apparel, & Fashions",
            "type":"Retail Goods"
        }
    ],
    "sg:phone":"+43 1 5125170",
    "sg:postcode":"1010",
    "sg:province":"Wien",
    "sg:tags":[
        "garment",
        "fur"
    ],
    "wof:name":"Johann Philipp",
    "wof:placetype":"venue"
},
  "geometry": {"coordinates":[16.3759021759,48.2083587646],"type":"Point"}
}