{
  "type": "Feature",
  "properties": {
    "addr:full":"Am Hauersteig 7 Sollenau Nieder\u00f6sterreich 2601",
    "addr:housenumber":"7",
    "addr:postcode":"2601",
    "addr:street":"Am Hauersteig",
    "iso:country":"AT",
    "sg:address":"Am Hauersteig 7",
    "sg:city":"Sollenau",
    "sg:orig_category":"Automaten",
    "sg:phone":"+43 2628 420000",
    "sg:postcode":"2601",
    "sg:province":"Nieder\u00f6sterreich",
    "sg:website":"berghofer.at",
    "wof:name":"Berghofer Friedrich",
    "wof:placetype":"venue"
},
  "geometry": {"coordinates":[16.2555332184,47.904586792],"type":"Point"}
}