{
  "type": "Feature",
  "properties": {
    "addr:full":"Hauptstr 97 Forchtenstein Burgenland 7212",
    "addr:housenumber":"97",
    "addr:postcode":"7212",
    "addr:street":"Hauptstr",
    "iso:country":"AT",
    "sg:address":"Hauptstr 97",
    "sg:city":"Forchtenstein",
    "sg:orig_category":"Tankstellen",
    "sg:phone":"+43 2626 63187",
    "sg:postcode":"7212",
    "sg:province":"Burgenland",
    "wof:name":"Huber G\u00fcnter",
    "wof:placetype":"venue"
},
  "geometry": {"coordinates":[16.3514461517,47.7141952515],"type":"Point"}
}