{
  "type": "Feature",
  "properties": {
    "addr:full":"Pater G Leser-Str 9 G\u00fcssing Burgenland 7540",
    "addr:housenumber":"9",
    "addr:postcode":"7540",
    "addr:street":"Pater G Leser-Str",
    "iso:country":"AT",
    "sg:address":"Pater G Leser-Str 9",
    "sg:city":"G\u00fcssing",
    "sg:orig_category":"Versicherungsunternehmen",
    "sg:phone":"+43 3322 424610",
    "sg:postcode":"7540",
    "sg:province":"Burgenland",
    "wof:name":"Allianz Elementar Versicherungs-AG",
    "wof:placetype":"venue"
},
  "geometry": {"coordinates":[172.01626586910001,-43.3872413635],"type":"Point"}
}