{
  "type": "Feature",
  "properties": {
    "addr:full":"Prosdorf 58 Heiligenkreuz am Waasen Steiermark 8081",
    "addr:housenumber":"58",
    "addr:postcode":"8081",
    "addr:street":"Prosdorf",
    "iso:country":"AT",
    "sg:address":"Prosdorf 58",
    "sg:city":"Heiligenkreuz am Waasen",
    "sg:orig_category":"Autoreparatur",
    "sg:phone":"+43 4331 3422350",
    "sg:postcode":"8081",
    "sg:province":"Steiermark",
    "wof:name":"Freisacher Rupert",
    "wof:placetype":"venue"
},
  "geometry": {"coordinates":[15.5834436417,46.9732246399],"type":"Point"}
}