{
  "type": "Feature",
  "properties": {
    "addr:full":"Neustift 39 Sebersdorf Steiermark 8272",
    "addr:housenumber":"39",
    "addr:postcode":"8272",
    "addr:street":"Neustift",
    "iso:country":"AT",
    "sg:address":"Neustift 39",
    "sg:city":"Sebersdorf",
    "sg:orig_category":"Tabaktrafiken",
    "sg:phone":"+43 3333 2438",
    "sg:postcode":"8272",
    "sg:province":"Steiermark",
    "wof:name":"Stranzl Hermine",
    "wof:placetype":"venue"
},
  "geometry": {"coordinates":[15.9803342819,47.1829566956],"type":"Point"}
}