{
  "type": "Feature",
  "properties": {
    "addr:full":"Am Ring 6 Graz Steiermark 8010",
    "addr:housenumber":"6",
    "addr:postcode":"8010",
    "addr:street":"Am Ring",
    "iso:country":"AT",
    "sg:address":"Am Ring 6",
    "sg:city":"Graz",
    "sg:orig_category":"Maler, Anstreicher U Lackierer",
    "sg:phone":"+43 4331 6835973",
    "sg:postcode":"8010",
    "sg:province":"Steiermark",
    "wof:name":"Kovatschitz Eduard",
    "wof:placetype":"venue"
},
  "geometry": {"coordinates":[15.4619340897,47.0658226013],"type":"Point"}
}