{
  "type": "Feature",
  "properties": {
    "addr:full":"8.Mai-Pl 4 Villach K\u00e4rnten 9500",
    "addr:housenumber":"4",
    "addr:postcode":"9500",
    "addr:street":"8.Mai-Pl;Kaernten",
    "iso:country":"AT",
    "sg:address":"8.Mai-Pl 4",
    "sg:city":"Villach",
    "sg:orig_category":"Blumeneinzelhandel",
    "sg:phone":"+43 4342 4224253",
    "sg:postcode":"9500",
    "sg:province":"K\u00e4rnten",
    "wof:name":"Moser Blumen",
    "wof:placetype":"venue"
},
  "geometry": {"coordinates":[13.8456468582,46.6122550964],"type":"Point"}
}