{
  "type": "Feature",
  "properties": {
    "addr:full":"Ledererg 27 Linz Ober\u00f6sterreich 4020",
    "addr:housenumber":"27",
    "addr:postcode":"4020",
    "addr:street":"Ledererg",
    "iso:country":"AT",
    "sg:address":"Ledererg 27",
    "sg:city":"Linz",
    "sg:orig_category":"Blumeneinzelhandel",
    "sg:phone":"+43 732 770127",
    "sg:postcode":"4020",
    "sg:province":"Ober\u00f6sterreich",
    "wof:name":"Blumen Stark",
    "wof:placetype":"venue"
},
  "geometry": {"coordinates":[14.295419693,48.3074035645],"type":"Point"}
}