{
  "type": "Feature",
  "properties": {
    "addr:full":"Nr 2b Hippach Tirol 6283",
    "addr:postcode":"6283",
    "addr:street":"Nr 2B;Tirol",
    "iso:country":"AT",
    "sg:address":"Nr 2b",
    "sg:city":"Hippach",
    "sg:orig_category":"Gastronomie- U Hoteleinrichtungen",
    "sg:phone":"+43 4352 8251025",
    "sg:postcode":"6283",
    "sg:province":"Tirol",
    "wof:name":"Schankservice Peer",
    "wof:placetype":"venue"
},
  "geometry": {"coordinates":[11.8661670685,47.2039108276],"type":"Point"}
}