{
  "type": "Feature",
  "properties": {
    "addr:full":"Reichsstrasse 24 Amstetten Nieder\u00f6sterreich 3300",
    "addr:housenumber":"24",
    "addr:postcode":"3300",
    "addr:street":"Reichsstrasse;Niederoesterreich",
    "iso:country":"AT",
    "sg:address":"Reichsstrasse 24",
    "sg:city":"Amstetten",
    "sg:orig_category":"Cnc-Edging Work",
    "sg:phone":"+43 7472 626460",
    "sg:postcode":"3300",
    "sg:province":"Nieder\u00f6sterreich",
    "wof:name":"Hans Pitlicek Ges.m.b.H. Schulm\u00f6belerzeugung",
    "wof:placetype":"venue"
},
  "geometry": {"coordinates":[14.8977603912,48.119178772],"type":"Point"}
}