{
  "type": "Feature",
  "properties": {
    "addr:full":"Pramet Ober\u00f6sterreich 4925",
    "addr:postcode":"4925",
    "addr:street":"Oberoesterreich",
    "iso:country":"AT",
    "sg:city":"Pramet",
    "sg:orig_category":"Feuerwehren",
    "sg:phone":"+43 7754 8622",
    "sg:postcode":"4925",
    "sg:province":"Ober\u00f6sterreich",
    "wof:name":"Freiwillige Feuerwehr - Zeughaus",
    "wof:placetype":"venue"
},
  "geometry": {"coordinates":[13.4865837097,48.1419219971],"type":"Point"}
}