{
  "type": "Feature",
  "properties": {
    "addr:full":"Feldkirchner Str 140 Klagenfurt K\u00e4rnten 9020",
    "addr:housenumber":"140",
    "addr:postcode":"9020",
    "addr:street":"Str;Kaernten",
    "iso:country":"AT",
    "sg:address":"Feldkirchner Str 140",
    "sg:city":"Klagenfurt",
    "sg:orig_category":"Finanz- U Wirtschaftsberatung",
    "sg:phone":"+43 463 50840535",
    "sg:postcode":"9020",
    "sg:province":"K\u00e4rnten",
    "wof:name":"Managementkompetenz Mag Grabner G\u00fcnter Mag",
    "wof:placetype":"venue"
},
  "geometry": {"coordinates":[14.2889699936,46.641708374],"type":"Point"}
}