{
  "type": "Feature",
  "properties": {
    "addr:full":"Innsbrucker Str 3 Ehrwald Tirol 6632",
    "addr:housenumber":"3",
    "addr:postcode":"6632",
    "addr:street":"Str;Tirol",
    "iso:country":"AT",
    "sg:address":"Innsbrucker Str 3",
    "sg:city":"Ehrwald",
    "sg:orig_category":"Psychotherapie",
    "sg:phone":"+43 4366 07603648",
    "sg:postcode":"6632",
    "sg:province":"Tirol",
    "wof:name":"Witschela Christian - Psychotherapie-Beratung-K\u00f6rperarbeit",
    "wof:placetype":"venue"
},
  "geometry": {"coordinates":[10.917965889,47.3980178833],"type":"Point"}
}