{
  "type": "Feature",
  "properties": {
    "addr:full":"Berg 6 Hirschbach im M\u00fchlkreis Ober\u00f6sterreich 4242",
    "addr:housenumber":"6",
    "addr:postcode":"4242",
    "addr:street":"Berg",
    "iso:country":"AT",
    "sg:address":"Berg 6",
    "sg:city":"Hirschbach im M\u00fchlkreis",
    "sg:orig_category":"Futtermittel",
    "sg:phone":"+43 7948 364",
    "sg:postcode":"4242",
    "sg:province":"Ober\u00f6sterreich",
    "wof:name":"Binder Erich",
    "wof:placetype":"venue"
},
  "geometry": {"coordinates":[14.4492607117,48.4767417908],"type":"Point"}
}