{
  "type": "Feature",
  "properties": {
    "addr:full":"Schegarg 1/10 Wien Wien 1190",
    "addr:housenumber":"1 / 10",
    "addr:postcode":"1190",
    "addr:street":"Schegarg",
    "iso:country":"AT",
    "sg:address":"Schegarg 1/10",
    "sg:city":"Wien",
    "sg:classifiers":[
        {
            "category":"Communications",
            "subcategory":"Film & Video Production",
            "type":"Services"
        }
    ],
    "sg:phone":"+43 676 5247123",
    "sg:postcode":"1190",
    "sg:province":"Wien",
    "sg:tags":[
        "multimedia"
    ],
    "wof:name":"SEELAND-AT",
    "wof:placetype":"venue"
},
  "geometry": {"coordinates":[16.3487300873,48.235042572],"type":"Point"}
}