{
  "type": "Feature",
  "properties": {
    "addr:full":"B\u00e4ckerstr 4 Wien Wien 1010",
    "addr:housenumber":"4",
    "addr:postcode":"1010",
    "addr:street":"Baeckerstr",
    "iso:country":"AT",
    "sg:address":"B\u00e4ckerstr 4",
    "sg:city":"Wien",
    "sg:orig_category":"Leder",
    "sg:phone":"+43 1 5123279",
    "sg:postcode":"1010",
    "sg:province":"Wien",
    "wof:name":"Friedrich Gustav",
    "wof:placetype":"venue"
},
  "geometry": {"coordinates":[16.3753299713,48.2093048096],"type":"Point"}
}