{
  "type": "Feature",
  "properties": {
    "addr:full":"Zeiller Pl 3 Reutte Tirol 6600",
    "addr:housenumber":"3",
    "addr:postcode":"6600",
    "addr:street":"Zeiller Pl;Tirol",
    "iso:country":"AT",
    "sg:address":"Zeiller Pl 3",
    "sg:city":"Reutte",
    "sg:orig_category":"Druckereien",
    "sg:phone":"+43 5672 624360",
    "sg:postcode":"6600",
    "sg:province":"Tirol",
    "wof:name":"Au\u00dferferner Druckhaus Gutmann Wohlgenannt GmbH & Co KG",
    "wof:placetype":"venue"
},
  "geometry": {"coordinates":[10.7205524445,47.488609314],"type":"Point"}
}