{
  "type": "Feature",
  "properties": {
    "addr:full":"Mitterg 24 Bruck an der Mur Steiermark 8600",
    "addr:housenumber":"24",
    "addr:postcode":"8600",
    "addr:street":"Mitterg",
    "iso:country":"AT",
    "sg:address":"Mitterg 24",
    "sg:city":"Bruck an der Mur",
    "sg:orig_category":"Boutiquen",
    "sg:phone":"+43 3862 51822",
    "sg:postcode":"8600",
    "sg:province":"Steiermark",
    "wof:name":"Trendsetter",
    "wof:placetype":"venue"
},
  "geometry": {"coordinates":[15.2723140717,47.4105186462],"type":"Point"}
}