{
  "type": "Feature",
  "properties": {
    "addr:full":"Altenrieder Str 7 Ried im Innkreis Ober\u00f6sterreich 4910",
    "addr:housenumber":"7",
    "addr:postcode":"4910",
    "addr:street":"Str",
    "iso:country":"AT",
    "sg:address":"Altenrieder Str 7",
    "sg:city":"Ried im Innkreis",
    "sg:orig_category":"Tonstudios",
    "sg:phone":"+43 7752 86777",
    "sg:postcode":"4910",
    "sg:province":"Ober\u00f6sterreich",
    "wof:name":"LRP Studios",
    "wof:placetype":"venue"
},
  "geometry": {"coordinates":[13.4808483124,48.2179603577],"type":"Point"}
}