{
  "type": "Feature",
  "properties": {
    "addr:full":"Moosstrasse 60 Salzburg Salzburg 5020",
    "addr:housenumber":"60",
    "addr:postcode":"5020",
    "addr:street":"Moosstrasse;Salzburg",
    "iso:country":"AT",
    "sg:address":"Moosstrasse 60",
    "sg:city":"Salzburg",
    "sg:classifiers":[
        {
            "category":"Building & Trades",
            "subcategory":"Pest Control",
            "type":"Services"
        }
    ],
    "sg:phone":"+43 662 83067654",
    "sg:postcode":"5020",
    "sg:province":"Salzburg",
    "sg:tags":[
        "bleacher",
        "construction"
    ],
    "sg:website":"nuessli.at",
    "wof:name":"N\u00fcssli (Austria) GmbH",
    "wof:placetype":"venue"
},
  "geometry": {"coordinates":[13.0251674652,47.7827682495],"type":"Point"}
}