{
  "type": "Feature",
  "properties": {
    "addr:full":"Schweizer G 15 Lienz Tirol 9900",
    "addr:housenumber":"15",
    "addr:postcode":"9900",
    "addr:street":"Schweizer G;Tirol",
    "iso:country":"AT",
    "sg:address":"Schweizer G 15",
    "sg:city":"Lienz",
    "sg:orig_category":"Elektroinstallationsunternehmen",
    "sg:phone":"+43 4348 5265533",
    "sg:postcode":"9900",
    "sg:province":"Tirol",
    "wof:name":"Elektro - K\u00fchlung Duregger Heinrich GmbH",
    "wof:placetype":"venue"
},
  "geometry": {"coordinates":[12.7624549866,46.8309707642],"type":"Point"}
}