{
  "type": "Feature",
  "properties": {
    "addr:full":"Riedstrasse 17 Hohenems Vorarlberg 6845",
    "addr:housenumber":"17",
    "addr:postcode":"6845",
    "addr:street":"Riedstrasse",
    "iso:country":"AT",
    "sg:address":"Riedstrasse 17",
    "sg:city":"Hohenems",
    "sg:classifiers":[
        {
            "category":"Building & Trades",
            "subcategory":"Landscaping Services",
            "type":"Services"
        }
    ],
    "sg:phone":"+43 5576 42145",
    "sg:postcode":"6845",
    "sg:province":"Vorarlberg",
    "sg:tags":[
        "dredging"
    ],
    "sg:website":"fenkart.cc",
    "wof:name":"Hansj\u00f6rg Fenkart",
    "wof:placetype":"venue"
},
  "geometry": {"coordinates":[9.6692905426,47.3557853699],"type":"Point"}
}