{
  "type": "Feature",
  "properties": {
    "iso:country":"AT",
    "sg:address":"St Michaeler Str 13",
    "sg:city":"Pischeldorf",
    "sg:orig_category":"Garten- U Landschaftsgestaltung",
    "sg:phone":"+43 664 1042309",
    "sg:postcode":"9064",
    "sg:province":"K\u00e4rnten",
    "wof:name":"Baum Strauch & Co",
    "wof:placetype":"venue"
},
  "geometry": {"coordinates":[14.4197463989,46.6829566956],"type":"Point"}
}