{
  "type": "Feature",
  "properties": {
    "iso:country":"AT",
    "sg:address":"Mozartweg 6",
    "sg:city":"Bad Kleinkirchheim",
    "sg:classifiers":[
        {
            "category":"Travel",
            "subcategory":"Hotels & Motels",
            "type":"Entertainment"
        }
    ],
    "sg:phone":"+43 4240 6810",
    "sg:postcode":"9546",
    "sg:province":"K\u00e4rnten",
    "sg:website":"www.hotelfelsenhof.at",
    "wof:name":"Hotel Felsenhof",
    "wof:placetype":"venue"
},
  "geometry": {"coordinates":[13.8160667419,46.816078186],"type":"Point"}
}