{
  "type": "Feature",
  "properties": {
    "iso:country":"AT",
    "sg:address":"Wolfsegger Str 12",
    "sg:city":"Attnang-Puchheim",
    "sg:orig_category":"Maler, Anstreicher U Lackierer",
    "sg:phone":"+43 4376 7462062",
    "sg:postcode":"4800",
    "sg:province":"Ober\u00f6sterreich",
    "wof:name":"Garstenauer Kurt",
    "wof:placetype":"venue"
},
  "geometry": {"coordinates":[13.7181358337,48.01978302],"type":"Point"}
}