{
  "type": "Feature",
  "properties": {
    "addr:full":"Europapl 583 Schladming Steiermark 8970",
    "addr:housenumber":"583",
    "addr:postcode":"8970",
    "iso:country":"AT",
    "sg:address":"Europapl 583",
    "sg:city":"Schladming",
    "sg:orig_category":"Friseure U Frisiersalons",
    "sg:phone":"+43 3687 200423",
    "sg:postcode":"8970",
    "sg:province":"Steiermark",
    "wof:name":"Gaby's Hairstyle",
    "wof:placetype":"venue"
},
  "geometry": {"coordinates":[13.6948928833,47.3958892822],"type":"Point"}
}