{
  "type": "Feature",
  "properties": {
    "addr:full":"Schumanng 3 Graz Steiermark 8010",
    "addr:housenumber":"3",
    "addr:postcode":"8010",
    "addr:street":"Schumanng",
    "iso:country":"AT",
    "sg:address":"Schumanng 3",
    "sg:city":"Graz",
    "sg:orig_category":"Bildungsservice / Allgemeine Informationsstellen",
    "sg:phone":"+43 4331 6821137",
    "sg:postcode":"8010",
    "sg:province":"Steiermark",
    "wof:name":"S\u00fcdwind Entwicklungspolitik Steiermark",
    "wof:placetype":"venue"
},
  "geometry": {"coordinates":[15.4530591965,47.0722236633],"type":"Point"}
}