{
  "type": "Feature",
  "properties": {
    "iso:country":"AT",
    "sg:address":"Querg 9",
    "sg:city":"Leibnitz",
    "sg:orig_category":"Sonnenstudios",
    "sg:phone":"+43 3452 86979",
    "sg:postcode":"8430",
    "sg:province":"Steiermark",
    "wof:name":"Cafe-Sonnenstudio Haselbacher",
    "wof:placetype":"venue"
},
  "geometry": {"coordinates":[15.5386753082,46.7836265564],"type":"Point"}
}