{
  "type": "Feature",
  "properties": {
    "addr:full":"Erdbergstr 81 Wien Wien 1030",
    "addr:housenumber":"81",
    "addr:postcode":"1030",
    "addr:street":"Erdbergstr",
    "iso:country":"AT",
    "sg:address":"Erdbergstr 81",
    "sg:city":"Wien",
    "sg:orig_category":"Juweliere, Gold- U Silberschmiede",
    "sg:phone":"+43 1 7144777",
    "sg:postcode":"1030",
    "sg:province":"Wien",
    "wof:name":"Schmidl Gertrude",
    "wof:placetype":"venue"
},
  "geometry": {"coordinates":[16.4027996063,48.1974411011],"type":"Point"}
}