{
  "type": "Feature",
  "properties": {
    "addr:full":"Keplerstrasse 114c Graz Steiermark 8020",
    "addr:housenumber":"114c",
    "addr:postcode":"8020",
    "addr:street":"Keplerstrasse",
    "iso:country":"AT",
    "sg:address":"Keplerstrasse 114c",
    "sg:city":"Graz",
    "sg:classifiers":[
        {
            "category":"Winery",
            "type":"Food & Drink"
        }
    ],
    "sg:phone":"+43 316 715660",
    "sg:postcode":"8020",
    "sg:province":"Steiermark",
    "sg:tags":[
        "argentinian",
        "wine"
    ],
    "wof:name":"Sch\u00e4ffer Ges.m.b.H.",
    "wof:placetype":"venue"
},
  "geometry": {"coordinates":[15.4191427231,47.0734176636],"type":"Point"}
}