{
  "type": "Feature",
  "properties": {
    "addr:full":"Waldstr 98 Mistelbach Nieder\u00f6sterreich 2130",
    "addr:housenumber":"98",
    "addr:postcode":"2130",
    "addr:street":"Waldstr;Niederoesterreich",
    "iso:country":"AT",
    "sg:address":"Waldstr 98",
    "sg:city":"Mistelbach",
    "sg:orig_category":"Elektronische Bauelemente U Bauteile",
    "sg:phone":"+43 4325 7220275",
    "sg:postcode":"2130",
    "sg:province":"Nieder\u00f6sterreich",
    "wof:name":"EKLAMA ELECTRONIC HandelsgesmbH",
    "wof:placetype":"venue"
},
  "geometry": {"coordinates":[16.5679225922,48.5789833069],"type":"Point"}
}