{
  "type": "Feature",
  "properties": {
    "addr:full":"Hockeg 19 Wien Wien 1180",
    "addr:housenumber":"19",
    "addr:postcode":"1180",
    "addr:street":"Hockeg",
    "iso:country":"AT",
    "sg:address":"Hockeg 19",
    "sg:city":"Wien",
    "sg:orig_category":"Werbegrafik- U Grafik-Design",
    "sg:phone":"+43 4314 788574",
    "sg:postcode":"1180",
    "sg:province":"Wien",
    "wof:name":"Grollnigg KEG",
    "wof:placetype":"venue"
},
  "geometry": {"coordinates":[16.3243255615,48.2355766296],"type":"Point"}
}