{
  "type": "Feature",
  "properties": {
    "addr:full":"Industriezentrum N\u00f6 S\u00fcd Stra\u00dfe 1 Obj 50 Wiener Neudorf Nieder\u00f6sterreich 2351",
    "addr:housenumber":"1 obj 50",
    "addr:postcode":"2351",
    "addr:street":"Industriezentrum Noe Sued Strasse",
    "iso:country":"AT",
    "sg:address":"Industriezentrum N\u00f6 S\u00fcd Stra\u00dfe 1 Obj 50",
    "sg:city":"Wiener Neudorf",
    "sg:orig_category":"Autoelektrik U -Ersatzteile",
    "sg:phone":"+43 4322 3664939",
    "sg:postcode":"2351",
    "sg:province":"Nieder\u00f6sterreich",
    "wof:name":"Pokorny Hubert Dkfm WarenhandelsgesmbH",
    "wof:placetype":"venue"
},
  "geometry": {"coordinates":[16.3183326721,48.0863113403],"type":"Point"}
}