{
  "type": "Feature",
  "properties": {
    "iso:country":"AT",
    "sg:address":"Schneebergstrasse 11 ",
    "sg:city":"Puchberg am Schneeberg",
    "sg:orig_category":"Paintwork Supraregional",
    "sg:phone":"+43 2636 3467",
    "sg:postcode":"2734",
    "sg:province":"Nieder\u00f6sterreich",
    "sg:website":"www.malerei-kerbl.com",
    "wof:name":"Erwin Kerbl",
    "wof:placetype":"venue"
},
  "geometry": {"coordinates":[15.9109420776,47.787940979],"type":"Point"}
}