{
  "type": "Feature",
  "properties": {
    "addr:full":"Mitterg 3A Spitz Nieder\u00f6sterreich 3620",
    "addr:housenumber":"3a",
    "addr:postcode":"3620",
    "addr:street":"Mitterg",
    "iso:country":"AT",
    "sg:address":"Mitterg 3A",
    "sg:city":"Spitz",
    "sg:orig_category":"Tourismusinformation U -Organisationen",
    "sg:phone":"+43 2713 2363",
    "sg:postcode":"3620",
    "sg:province":"Nieder\u00f6sterreich",
    "wof:name":"Fremdenverkehrsverein Spitz",
    "wof:placetype":"venue"
},
  "geometry": {"coordinates":[15.4154567719,48.3620567322],"type":"Point"}
}