{
  "type": "Feature",
  "properties": {
    "iso:country":"AT",
    "sg:address":"Linke Br\u00fcckenstr 24-26",
    "sg:city":"Linz",
    "sg:orig_category":"Banken U Sparkassen",
    "sg:phone":"+43 4373 27128000",
    "sg:postcode":"4040",
    "sg:province":"Ober\u00f6sterreich",
    "wof:name":"VKB-Bank Volkskreditbank AG",
    "wof:placetype":"venue"
},
  "geometry": {"coordinates":[14.2578554153,48.3602561951],"type":"Point"}
}