{
  "type": "Feature",
  "properties": {
    "addr:full":"Pyrkerstr 25 Bad Hofgastein Salzburg 5630",
    "addr:housenumber":"25",
    "addr:postcode":"5630",
    "addr:street":"Pyrkerstr;Salzburg",
    "iso:country":"AT",
    "sg:address":"Pyrkerstr 25",
    "sg:city":"Bad Hofgastein",
    "sg:orig_category":"Physiotherapie",
    "sg:phone":"+43 6432 8406",
    "sg:postcode":"5630",
    "sg:province":"Salzburg",
    "wof:name":"Fit und Fun",
    "wof:placetype":"venue"
},
  "geometry": {"coordinates":[13.1107244492,47.1682891846],"type":"Point"}
}