{
  "type": "Feature",
  "properties": {
    "addr:full":"Favoritenstr 25 Wien Wien 1040",
    "addr:housenumber":"25",
    "addr:postcode":"1040",
    "addr:street":"Favoritenstr",
    "iso:country":"AT",
    "sg:address":"Favoritenstr 25",
    "sg:city":"Wien",
    "sg:orig_category":"\u00c3\u201erzte / F Allgemeinmedizin",
    "sg:phone":"+43 1 5046578",
    "sg:postcode":"1040",
    "sg:province":"Wien",
    "wof:name":"Hruschka Leopold Dr",
    "wof:placetype":"venue"
},
  "geometry": {"coordinates":[16.3722267151,48.1899414062],"type":"Point"}
}