{
  "type": "Feature",
  "properties": {
    "addr:full":"Koppstr 61 Wien Wien 1160",
    "addr:housenumber":"61",
    "addr:postcode":"1160",
    "addr:street":"Koppstr",
    "iso:country":"AT",
    "sg:address":"Koppstr 61",
    "sg:city":"Wien",
    "sg:orig_category":"Waren Aller Art",
    "sg:phone":"+43 1 4945886",
    "sg:postcode":"1160",
    "sg:province":"Wien",
    "wof:name":"Preisknacker - J\u00f6rg Daniel Schmickl",
    "wof:placetype":"venue"
},
  "geometry": {"coordinates":[16.3247737885,48.207862854],"type":"Point"}
}