{
  "type": "Feature",
  "properties": {
    "addr:full":"Loiger Str 220 Wals Salzburg 5071",
    "addr:housenumber":"220",
    "addr:postcode":"5071",
    "addr:street":"Wals Salzburg",
    "iso:country":"AT",
    "sg:address":"Loiger Str 220",
    "sg:city":"Wals",
    "sg:orig_category":"Biologische Produkte",
    "sg:phone":"+43 662 853675",
    "sg:postcode":"5071",
    "sg:province":"Salzburg",
    "wof:name":"Keimling Naturkostladen",
    "wof:placetype":"venue"
},
  "geometry": {"coordinates":[12.9940509796,47.7899131775],"type":"Point"}
}