{
  "type": "Feature",
  "properties": {
    "addr:full":"Kapellerfelderstr. 490 Gerasdorf Nieder\u00f6sterreich 2201",
    "addr:housenumber":"2201",
    "addr:postcode":"490",
    "addr:street":"Niederoesterreich",
    "iso:country":"AT",
    "sg:address":"Kapellerfelderstr. 490",
    "sg:city":"Gerasdorf",
    "sg:classifiers":[
        {
            "category":"Manufacturing",
            "subcategory":"Rubber & Plastics",
            "type":"Manufacturing & Wholesale Goods"
        }
    ],
    "sg:phone":"+43 4322 463692",
    "sg:postcode":"2201",
    "sg:province":"Nieder\u00f6sterreich",
    "wof:name":"POLYGLAS ING. DECKER & CO. GESMBH",
    "wof:placetype":"venue"
},
  "geometry": {"coordinates":[16.4731903076,48.3004493713],"type":"Point"}
}