{
  "type": "Feature",
  "properties": {
    "addr:full":"Schubertg 13 Wien Wien 1090",
    "addr:housenumber":"13",
    "addr:postcode":"1090",
    "addr:street":"Schubertg",
    "iso:country":"AT",
    "sg:address":"Schubertg 13",
    "sg:city":"Wien",
    "sg:orig_category":"Restaurants: Lateinamerikanisch",
    "sg:phone":"+43 4313 106573",
    "sg:postcode":"1090",
    "sg:province":"Wien",
    "wof:name":"Cantinas",
    "wof:placetype":"venue"
},
  "geometry": {"coordinates":[16.3530483246,48.2272872925],"type":"Point"}
}