{
  "type": "Feature",
  "properties": {
    "addr:full":"Alpinestr 1 Zeltweg Steiermark 8740",
    "addr:housenumber":"1",
    "addr:postcode":"8740",
    "addr:street":"Alpinestr",
    "iso:country":"AT",
    "sg:address":"Alpinestr 1",
    "sg:city":"Zeltweg",
    "sg:classifiers":[
        {
            "category":"Home & Garden",
            "subcategory":"Building Materials",
            "type":"Retail Goods"
        }
    ],
    "sg:phone":"+43 4335 777500",
    "sg:postcode":"8740",
    "sg:province":"Steiermark",
    "sg:tags":[
        "baustoffe",
        "-material",
        "u"
    ],
    "wof:name":"VAE Eisenbahnsysteme GmbH",
    "wof:placetype":"venue"
},
  "geometry": {"coordinates":[14.7516326904,47.1865272522],"type":"Point"}
}