{
  "type": "Feature",
  "properties": {
    "addr:full":"Klosterg 1 Ried in der Riedmark Ober\u00f6sterreich 4312",
    "addr:housenumber":"1",
    "addr:postcode":"4312",
    "addr:street":"Klosterg",
    "iso:country":"AT",
    "sg:address":"Klosterg 1",
    "sg:city":"Ried in der Riedmark",
    "sg:orig_category":"Kinderbetreuung",
    "sg:phone":"+43 7238 2810",
    "sg:postcode":"4312",
    "sg:province":"Ober\u00f6sterreich",
    "wof:name":"Kindergarten d Pfarrcaritas",
    "wof:placetype":"venue"
},
  "geometry": {"coordinates":[14.527879715,48.2715644836],"type":"Point"}
}