{
  "type": "Feature",
  "properties": {
    "addr:full":"Johannesstr 6 Walchsee Tirol 6344",
    "addr:housenumber":"6",
    "addr:postcode":"6344",
    "addr:street":"Johannesstr;Tirol",
    "iso:country":"AT",
    "sg:address":"Johannesstr 6",
    "sg:city":"Walchsee",
    "sg:orig_category":"Pensionen / Privatzimmer",
    "sg:phone":"+43 5374 5666",
    "sg:postcode":"6344",
    "sg:province":"Tirol",
    "wof:name":"Hupf Michael",
    "wof:placetype":"venue"
},
  "geometry": {"coordinates":[12.3269033432,47.6512413025],"type":"Point"}
}