{
  "type": "Feature",
  "properties": {
    "addr:full":"Traunsteinstr 329 Gmunden Ober\u00f6sterreich 4810",
    "addr:housenumber":"329",
    "addr:postcode":"4810",
    "addr:street":"Oberoesterreich",
    "iso:country":"AT",
    "sg:address":"Traunsteinstr 329",
    "sg:city":"Gmunden",
    "sg:orig_category":"Forstbedarf",
    "sg:phone":"+43 761265608",
    "sg:postcode":"4810",
    "sg:province":"Ober\u00f6sterreich",
    "wof:name":"Forsttechnikb\u00fcro Zopf Walter",
    "wof:placetype":"venue"
},
  "geometry": {"coordinates":[13.8153438568,47.8722457886],"type":"Point"}
}