{
  "type": "Feature",
  "properties": {
    "addr:full":"Klarenbrunnstrasse 8 Bludenz Vorarlberg 6700",
    "addr:housenumber":"8",
    "addr:postcode":"6700",
    "addr:street":"Klarenbrunnstrasse",
    "iso:country":"AT",
    "sg:address":"Klarenbrunnstrasse 8",
    "sg:city":"Bludenz",
    "sg:classifiers":[
        {
            "category":"Building & Trades",
            "subcategory":"Cleaning & Sanitation",
            "type":"Services"
        }
    ],
    "sg:phone":"+43 5552 620750",
    "sg:postcode":"6700",
    "sg:province":"Vorarlberg",
    "sg:tags":[
        "carpet"
    ],
    "sg:website":"sander-reinigung.com",
    "wof:name":"Heinrich Sander Ges.m.b.H. & Co KG",
    "wof:placetype":"venue"
},
  "geometry": {"coordinates":[9.8173847198,47.1519012451],"type":"Point"}
}