{
  "type": "Feature",
  "properties": {
    "addr:full":"Dorfstrasse 3 Niedernsill Salzburg 5722",
    "addr:housenumber":"3",
    "addr:postcode":"5722",
    "addr:street":"Dorfstrasse;Salzburg",
    "iso:country":"AT",
    "sg:address":"Dorfstrasse 3",
    "sg:city":"Niedernsill",
    "sg:classifiers":[
        {
            "category":"Organizations",
            "subcategory":"Non-profit Organization",
            "type":"Services"
        }
    ],
    "sg:phone":"+43 6548 82410",
    "sg:postcode":"5722",
    "sg:province":"Salzburg",
    "sg:tags":[
        "alarm",
        "system"
    ],
    "wof:name":"ETB Elektrotechnik Brennsteiner GmbH",
    "wof:placetype":"venue"
},
  "geometry": {"coordinates":[12.6482648849,47.282043457],"type":"Point"}
}