{
  "type": "Feature",
  "properties": {
    "addr:full":"Eibesbrunnerg. 24  Wien Wien 1120",
    "addr:housenumber":"24",
    "addr:postcode":"1120",
    "addr:street":"Eibesbrunnerg.",
    "iso:country":"AT",
    "sg:address":"Eibesbrunnerg. 24 ",
    "sg:city":"Wien",
    "sg:classifiers":[
        {
            "category":"Parking",
            "subcategory":"Lot",
            "type":"Transportation"
        }
    ],
    "sg:phone":"+43 4318 155295",
    "sg:postcode":"1120",
    "sg:province":"Wien",
    "sg:tags":[
        "transport",
        "road"
    ],
    "wof:name":"KARL DOLEZAL",
    "wof:placetype":"venue"
},
  "geometry": {"coordinates":[16.3360023499,48.1691513062],"type":"Point"}
}