{
  "type": "Feature",
  "properties": {
    "addr:full":"Marktpassage 1/b1 Knittelfeld Steiermark 8720",
    "addr:housenumber":"1 / b1",
    "addr:postcode":"8720",
    "addr:street":"Marktpassage",
    "iso:country":"AT",
    "sg:address":"Marktpassage 1/b1",
    "sg:city":"Knittelfeld",
    "sg:orig_category":"Gemeinden",
    "sg:phone":"+43 4335 12752300",
    "sg:postcode":"8720",
    "sg:province":"Steiermark",
    "wof:name":"Marktgemeindeamt Spielberg bei Knittelfeld",
    "wof:placetype":"venue"
},
  "geometry": {"coordinates":[14.7973117828,47.2074241638],"type":"Point"}
}