{
  "type": "Feature",
  "properties": {
    "iso:country":"AT",
    "sg:address":"Wei\u00dfenbachg 1",
    "sg:city":"Telfs",
    "sg:orig_category":"Papier- U Schreibwaren / Einzelhandel",
    "sg:phone":"+43 5262 628420",
    "sg:postcode":"6410",
    "sg:province":"Tirol",
    "wof:name":"Holzknecht Gerhard",
    "wof:placetype":"venue"
},
  "geometry": {"coordinates":[11.072218895,47.3066978455],"type":"Point"}
}