{
  "type": "Feature",
  "properties": {
    "addr:full":"Dornbacher Str 14 Sulz im Wienerwald Nieder\u00f6sterreich 2392",
    "addr:housenumber":"14",
    "addr:postcode":"2392",
    "addr:street":"Str",
    "iso:country":"AT",
    "sg:address":"Dornbacher Str 14",
    "sg:city":"Sulz im Wienerwald",
    "sg:orig_category":"Transportunternehmen",
    "sg:phone":"+43 2258 8213",
    "sg:postcode":"2392",
    "sg:province":"Nieder\u00f6sterreich",
    "wof:name":"Grimm Walter Transporte GesmbH",
    "wof:placetype":"venue"
},
  "geometry": {"coordinates":[16.1391887665,48.1020393372],"type":"Point"}
}