{
  "type": "Feature",
  "properties": {
    "iso:country":"AT",
    "sg:address":"Beatrixg 28",
    "sg:city":"Wien",
    "sg:classifiers":[
        {
            "category":"Government",
            "subcategory":"Post Office",
            "type":"Public Place"
        }
    ],
    "sg:phone":"+43 1 7107000",
    "sg:postcode":"1030",
    "sg:province":"Wien",
    "sg:tags":[
        "yoga"
    ],
    "wof:name":"Bikram Yoga Studio KEG",
    "wof:placetype":"venue"
},
  "geometry": {"coordinates":[16.3814296722,48.201499939],"type":"Point"}
}