{
  "type": "Feature",
  "properties": {
    "addr:full":"St Julien-Str 2 Salzburg Salzburg 5020",
    "addr:housenumber":"2",
    "addr:postcode":"5020",
    "addr:street":"Salzburg",
    "iso:country":"AT",
    "sg:address":"St Julien-Str 2",
    "sg:city":"Salzburg",
    "sg:orig_category":"Friseure U Frisiersalons",
    "sg:phone":"+43 662 876794",
    "sg:postcode":"5020",
    "sg:province":"Salzburg",
    "wof:name":"Coiffeur Irfan",
    "wof:placetype":"venue"
},
  "geometry": {"coordinates":[13.038356781,47.8107566833],"type":"Point"}
}