{
  "type": "Feature",
  "properties": {
    "addr:full":"Reuttener Str 12 Lermoos Tirol 6631",
    "addr:postcode":"6631",
    "addr:street":"Str 12;Tirol",
    "iso:country":"AT",
    "sg:address":"Reuttener Str 12",
    "sg:city":"Lermoos",
    "sg:orig_category":"Appartements / Ferienwohnungen",
    "sg:phone":"+43 5673 42410",
    "sg:postcode":"6631",
    "sg:province":"Tirol",
    "wof:name":"Haus Goldeck",
    "wof:placetype":"venue"
},
  "geometry": {"coordinates":[10.877790451,47.4050292969],"type":"Point"}
}