{
  "type": "Feature",
  "properties": {
    "iso:country":"AT",
    "sg:address":"Fraueng 31",
    "sg:city":"Leibnitz",
    "sg:orig_category":"Feinkost",
    "sg:phone":"+43 3452 75750",
    "sg:postcode":"8430",
    "sg:province":"Steiermark",
    "wof:name":"Legat Christa",
    "wof:placetype":"venue"
},
  "geometry": {"coordinates":[15.5338563919,46.7930717468],"type":"Point"}
}