{
  "type": "Feature",
  "properties": {
    "addr:full":"Burgg 123 Judenburg Steiermark 8750",
    "addr:housenumber":"123",
    "addr:postcode":"8750",
    "iso:country":"AT",
    "sg:address":"Burgg 123",
    "sg:city":"Judenburg",
    "sg:orig_category":"Immobilienverwaltungen",
    "sg:phone":"+43 3572 826240",
    "sg:postcode":"8750",
    "sg:province":"Steiermark",
    "wof:name":"Raiffeisen Immobilien Steiermark GesmbH",
    "wof:placetype":"venue"
},
  "geometry": {"coordinates":[14.6391019821,47.1707191467],"type":"Point"}
}