{
  "type": "Feature",
  "properties": {
    "addr:full":"Almegg 5 Scharnstein Ober\u00f6sterreich 4644",
    "addr:housenumber":"5",
    "addr:postcode":"4644",
    "addr:street":"Almegg",
    "iso:country":"AT",
    "sg:address":"Almegg 5",
    "sg:city":"Scharnstein",
    "sg:orig_category":"Appartements / Ferienwohnungen",
    "sg:phone":"+43 76168586",
    "sg:postcode":"4644",
    "sg:province":"Ober\u00f6sterreich",
    "wof:name":"Ferienhof Andrebauer Fam Binder",
    "wof:placetype":"venue"
},
  "geometry": {"coordinates":[13.939704895,47.8709602356],"type":"Point"}
}