{
  "type": "Feature",
  "properties": {
    "addr:full":"Arsenalstr 2a Wien Wien 1100",
    "addr:housenumber":"2a",
    "addr:postcode":"1100",
    "addr:street":"Arsenalstr",
    "iso:country":"AT",
    "sg:address":"Arsenalstr 2a",
    "sg:city":"Wien",
    "sg:orig_category":"Tankstellen",
    "sg:phone":"+43 1 7984342",
    "sg:postcode":"1100",
    "sg:province":"Wien",
    "wof:name":"Shell Austria GmbH",
    "wof:placetype":"venue"
},
  "geometry": {"coordinates":[16.4009647369,48.1706161499],"type":"Point"}
}