{
  "type": "Feature",
  "properties": {
    "iso:country":"AT",
    "sg:address":"Moosg 6",
    "sg:city":"Voitsberg",
    "sg:orig_category":"Baumeister",
    "sg:phone":"+43 3142 240800",
    "sg:postcode":"8570",
    "sg:province":"Steiermark",
    "wof:name":"Preschan Wolfgang Bmstr",
    "wof:placetype":"venue"
},
  "geometry": {"coordinates":[15.1501398087,47.0494194031],"type":"Point"}
}