{
  "type": "Feature",
  "properties": {
    "addr:full":"Steinamangerer Str 364 Rotenturm an der Pinka Burgenland 7501",
    "addr:housenumber":"364",
    "addr:postcode":"7501",
    "addr:street":"Str",
    "iso:country":"AT",
    "sg:address":"Steinamangerer Str 364",
    "sg:city":"Rotenturm an der Pinka",
    "sg:orig_category":"Autohandel",
    "sg:phone":"+43 3352 34763",
    "sg:postcode":"7501",
    "sg:province":"Burgenland",
    "wof:name":"Toyota - F\u00fcrst",
    "wof:placetype":"venue"
},
  "geometry": {"coordinates":[16.2398853302,47.2711791992],"type":"Point"}
}