{
  "type": "Feature",
  "properties": {
    "addr:full":"Yppenpl Kiosk 1 Wien Wien 1160",
    "addr:housenumber":"1",
    "addr:postcode":"1160",
    "iso:country":"AT",
    "sg:address":"Yppenpl Kiosk 1",
    "sg:city":"Wien",
    "sg:orig_category":"Tabaktrafiken",
    "sg:phone":"+43 1 4099905",
    "sg:postcode":"1160",
    "sg:province":"Wien",
    "wof:name":"Perzel Michael",
    "wof:placetype":"venue"
},
  "geometry": {"coordinates":[16.2961292267,48.214931488],"type":"Point"}
}