{
  "type": "Feature",
  "properties": {
    "addr:full":"Nr 94 Gro\u00dfpetersdorf Burgenland 7503",
    "addr:postcode":"7503",
    "addr:street":"Nr 94",
    "iso:country":"AT",
    "sg:address":"Nr 94",
    "sg:city":"Gro\u00dfpetersdorf",
    "sg:orig_category":"Tischlereien",
    "sg:phone":"+43 3362 2412",
    "sg:postcode":"7503",
    "sg:province":"Burgenland",
    "wof:name":"Halper Gerhard",
    "wof:placetype":"venue"
},
  "geometry": {"coordinates":[16.3193855286,47.2381019592],"type":"Point"}
}