{
  "type": "Feature",
  "properties": {
    "addr:full":"Kirchpl 1 Fernitz Steiermark 8072",
    "addr:housenumber":"1",
    "addr:postcode":"8072",
    "addr:street":"Kirchpl",
    "iso:country":"AT",
    "sg:address":"Kirchpl 1",
    "sg:city":"Fernitz",
    "sg:orig_category":"Restaurants: Chinesisch",
    "sg:phone":"+43 3135 55511",
    "sg:postcode":"8072",
    "sg:province":"Steiermark",
    "wof:name":"China-Restaurant China Haus",
    "wof:placetype":"venue"
},
  "geometry": {"coordinates":[15.4998197556,46.9730224609],"type":"Point"}
}