{
  "type": "Feature",
  "properties": {
    "iso:country":"AT",
    "sg:address":"St. Veiterstra\u00dfe 61",
    "sg:city":"Graz",
    "sg:orig_category":"Bildung And Forschung, Schulen",
    "sg:phone":"+43 316 694229",
    "sg:postcode":"8020",
    "sg:province":"Steiermark",
    "sg:website":"http://www.via.at/koller-development",
    "wof:name":"Koller Development KEG",
    "wof:placetype":"venue"
},
  "geometry": {"coordinates":[15.4146194458,47.1136665344],"type":"Point"}
}