{
  "type": "Feature",
  "properties": {
    "addr:full":"Baiernstr 54 Graz Steiermark 8020",
    "addr:housenumber":"54",
    "addr:postcode":"8020",
    "addr:street":"Baiernstr",
    "iso:country":"AT",
    "sg:address":"Baiernstr 54",
    "sg:city":"Graz",
    "sg:classifiers":[
        {
            "category":"Professional",
            "subcategory":"Computer Services",
            "type":"Services"
        }
    ],
    "sg:phone":"+43 316 583163",
    "sg:postcode":"8020",
    "sg:province":"Steiermark",
    "sg:tags":[
        "software"
    ],
    "wof:name":"Dolphicom - Kalcher",
    "wof:placetype":"venue"
},
  "geometry": {"coordinates":[15.3903865814,47.0707397461],"type":"Point"}
}