{
  "type": "Feature",
  "properties": {
    "addr:full":"Hauptpl 12 Villach K\u00e4rnten 9500",
    "addr:housenumber":"12",
    "addr:postcode":"9500",
    "addr:street":"Hauptpl;Kaernten",
    "iso:country":"AT",
    "sg:address":"Hauptpl 12",
    "sg:city":"Villach",
    "sg:classifiers":[
        {
            "category":"Restaurant",
            "type":"Food & Drink"
        }
    ],
    "sg:phone":"+43 4242 23783",
    "sg:postcode":"9500",
    "sg:province":"K\u00e4rnten",
    "wof:name":"Nordsee GesmbH",
    "wof:placetype":"venue"
},
  "geometry": {"coordinates":[13.846985817,46.6145477295],"type":"Point"}
}