{
  "type": "Feature",
  "properties": {
    "addr:full":"Josef-Haas-G 3 Wien Wien 1110",
    "addr:housenumber":"3",
    "addr:postcode":"1110",
    "addr:street":"Josef-Haas-G",
    "iso:country":"AT",
    "sg:address":"Josef-Haas-G 3",
    "sg:city":"Wien",
    "sg:classifiers":[
        {
            "category":"Government",
            "subcategory":"Post Office",
            "type":"Public Place"
        }
    ],
    "sg:phone":"+43 4366 41352215",
    "sg:postcode":"1110",
    "sg:province":"Wien",
    "sg:tags":[
        "u",
        "-material",
        "dachdeckereibedarf"
    ],
    "wof:name":"Erlus Baustoffwerke AG",
    "wof:placetype":"venue"
},
  "geometry": {"coordinates":[16.4580421448,48.1511611938],"type":"Point"}
}