{
  "type": "Feature",
  "properties": {
    "iso:country":"AT",
    "sg:address":"Arnbach 74",
    "sg:city":"Sillian",
    "sg:orig_category":"Tabaktrafiken",
    "sg:phone":"+43 4842 6311",
    "sg:postcode":"9920",
    "sg:province":"Tirol",
    "wof:name":"Kopecky Doris",
    "wof:placetype":"venue"
},
  "geometry": {"coordinates":[12.3908557892,46.7448654175],"type":"Point"}
}