{
  "type": "Feature",
  "properties": {
    "iso:country":"AT",
    "sg:address":"Nr 22",
    "sg:city":"Bad Gleichenberg",
    "sg:classifiers":[
        {
            "category":"Travel",
            "subcategory":"Hotels & Motels",
            "type":"Entertainment"
        }
    ],
    "sg:phone":"+43 4331 5923120",
    "sg:postcode":"8344",
    "sg:province":"Steiermark",
    "wof:name":"Hotel Grazerhof",
    "wof:placetype":"venue"
},
  "geometry": {"coordinates":[15.9038906097,46.8549499512],"type":"Point"}
}