{
  "type": "Feature",
  "properties": {
    "addr:full":"Perkonigweg 1 St. Magdalen K\u00e4rnten 9524",
    "addr:housenumber":"1",
    "addr:postcode":"9524",
    "addr:street":"Perkonigweg;Kaernten",
    "iso:country":"AT",
    "sg:address":"Perkonigweg 1",
    "sg:city":"St. Magdalen",
    "sg:orig_category":"Finanz- U Wirtschaftsberatung",
    "sg:phone":"+43 676 5218277",
    "sg:postcode":"9524",
    "sg:province":"K\u00e4rnten",
    "wof:name":"Albl Hartmut",
    "wof:placetype":"venue"
},
  "geometry": {"coordinates":[-107.6441268921,34.3684654236],"type":"Point"}
}