{
  "type": "Feature",
  "properties": {
    "addr:full":"Gnigler Str 52 Salzburg Salzburg 5020",
    "addr:housenumber":"52",
    "addr:postcode":"5020",
    "addr:street":"Str;Salzburg",
    "iso:country":"AT",
    "sg:address":"Gnigler Str 52",
    "sg:city":"Salzburg",
    "sg:orig_category":"Bijouteriewaren",
    "sg:phone":"+43 662 882690",
    "sg:postcode":"5020",
    "sg:province":"Salzburg",
    "wof:name":"Trend Stilschmuck Uhren und Schmuck Vertrieb GesmbH",
    "wof:placetype":"venue"
},
  "geometry": {"coordinates":[13.0598325729,47.8165626526],"type":"Point"}
}