{
  "type": "Feature",
  "properties": {
    "iso:country":"AT",
    "sg:address":"Bahnhofstr 6",
    "sg:city":"Wels",
    "sg:orig_category":"Friseure U Frisiersalons",
    "sg:phone":"+43 4372 4247480",
    "sg:postcode":"4600",
    "sg:province":"Ober\u00f6sterreich",
    "wof:name":"K\u00f6nigsberger Bernhard",
    "wof:placetype":"venue"
},
  "geometry": {"coordinates":[14.0256433487,48.1607894897],"type":"Point"}
}