{
  "type": "Feature",
  "properties": {
    "addr:full":"Hauptpl 15-16 Linz Ober\u00f6sterreich 4020",
    "addr:postcode":"4020",
    "addr:street":"Oberoesterreich",
    "iso:country":"AT",
    "sg:address":"Hauptpl 15-16",
    "sg:city":"Linz",
    "sg:orig_category":"Restaurants: Griechisch",
    "sg:phone":"+43 732 791598",
    "sg:postcode":"4020",
    "sg:province":"Ober\u00f6sterreich",
    "wof:name":"Restaurant El Greco",
    "wof:placetype":"venue"
},
  "geometry": {"coordinates":[14.2860746384,48.305557251],"type":"Point"}
}