{
  "type": "Feature",
  "properties": {
    "addr:full":"Gersdorf 54 Spielfeld Steiermark 8471",
    "addr:housenumber":"54",
    "addr:postcode":"8471",
    "addr:street":"Gersdorf",
    "iso:country":"AT",
    "sg:address":"Gersdorf 54",
    "sg:city":"Spielfeld",
    "sg:orig_category":"Tischlereien",
    "sg:phone":"+43 3453 2323",
    "sg:postcode":"8471",
    "sg:province":"Steiermark",
    "wof:name":"Ulz Karl",
    "wof:placetype":"venue"
},
  "geometry": {"coordinates":[15.6369409561,46.710975647],"type":"Point"}
}