{
  "type": "Feature",
  "properties": {
    "addr:full":"Marokkanerg 23 Wien Wien 1030",
    "addr:housenumber":"23",
    "addr:postcode":"1030",
    "addr:street":"Marokkanerg",
    "iso:country":"AT",
    "sg:address":"Marokkanerg 23",
    "sg:city":"Wien",
    "sg:orig_category":"Abfallentsorgung U -Verwertung",
    "sg:phone":"+43 1 8956787",
    "sg:postcode":"1030",
    "sg:province":"Wien",
    "wof:name":"Interservice Abfallentsorgung regGenmbH",
    "wof:placetype":"venue"
},
  "geometry": {"coordinates":[16.3804683685,48.1974334717],"type":"Point"}
}