{
  "type": "Feature",
  "properties": {
    "addr:full":"Missong 39 Krems an der Donau Nieder\u00f6sterreich 3500",
    "addr:housenumber":"39",
    "addr:postcode":"3500",
    "addr:street":"Missong",
    "iso:country":"AT",
    "sg:address":"Missong 39",
    "sg:city":"Krems an der Donau",
    "sg:orig_category":"Imkereien",
    "sg:phone":"+43 4327 3284486",
    "sg:postcode":"3500",
    "sg:province":"Nieder\u00f6sterreich",
    "wof:name":"Imkerei Brandl Marianne u Gruber Erwin",
    "wof:placetype":"venue"
},
  "geometry": {"coordinates":[15.6134262085,48.4093322754],"type":"Point"}
}