{
  "type": "Feature",
  "properties": {
    "addr:full":"Rudolf-Virchow-Str 2-6 Wien Wien 1210",
    "addr:housenumber":"2-6",
    "addr:postcode":"1210",
    "addr:street":"Rudolf-Virchow-Str",
    "iso:country":"AT",
    "sg:address":"Rudolf-Virchow-Str 2-6",
    "sg:city":"Wien",
    "sg:orig_category":"Glasereien",
    "sg:phone":"+43 4312 7033510",
    "sg:postcode":"1210",
    "sg:province":"Wien",
    "wof:name":"Weissmann Ferdinand Glaserei GesmbH",
    "wof:placetype":"venue"
},
  "geometry": {"coordinates":[16.3859977722,48.272403717],"type":"Point"}
}