{
  "type": "Feature",
  "properties": {
    "iso:country":"AT",
    "sg:address":"Bergl 38",
    "sg:city":"Patergassen",
    "sg:orig_category":"Tischlereien",
    "sg:phone":"+43 4275 648",
    "sg:postcode":"9564",
    "sg:province":"K\u00e4rnten",
    "wof:name":"Dorfer Johann",
    "wof:placetype":"venue"
},
  "geometry": {"coordinates":[13.8319253922,46.8631591797],"type":"Point"}
}