{
  "type": "Feature",
  "properties": {
    "addr:full":"Alemannenstr 20c Rankweil Vorarlberg 6830",
    "addr:housenumber":"20c",
    "addr:postcode":"6830",
    "addr:street":"Alemannenstr",
    "iso:country":"AT",
    "sg:address":"Alemannenstr 20c",
    "sg:city":"Rankweil",
    "sg:orig_category":"Tabaktrafiken",
    "sg:phone":"+43 5522 47947",
    "sg:postcode":"6830",
    "sg:province":"Vorarlberg",
    "wof:name":"Friedrich Kurt",
    "wof:placetype":"venue"
},
  "geometry": {"coordinates":[9.650850296,47.2748718262],"type":"Point"}
}