{
  "type": "Feature",
  "properties": {
    "addr:full":"G\u00e4nsackerweg 2 Serfaus Tirol 6534",
    "addr:housenumber":"2",
    "addr:postcode":"6534",
    "addr:street":"Gaensackerweg;Tirol",
    "iso:country":"AT",
    "sg:address":"G\u00e4nsackerweg 2",
    "sg:city":"Serfaus",
    "sg:classifiers":[
        {
            "category":"Park",
            "subcategory":"Provincial",
            "type":"Public Place"
        }
    ],
    "sg:phone":"+43 5476 62680",
    "sg:postcode":"6534",
    "sg:province":"Tirol",
    "sg:tags":[
        "u",
        "ski-",
        "snowboardschulen"
    ],
    "wof:name":"Schischule Serfaus-Komperdell",
    "wof:placetype":"venue"
},
  "geometry": {"coordinates":[10.6073760986,47.0389518738],"type":"Point"}
}