{
  "type": "Feature",
  "properties": {
    "iso:country":"AT",
    "sg:address":"Europastr 8",
    "sg:city":"St. Magdalen",
    "sg:orig_category":"Digitaldruck",
    "sg:phone":"+43 4369 912926250",
    "sg:postcode":"9524",
    "sg:province":"K\u00e4rnten",
    "wof:name":"MWT productions",
    "wof:placetype":"venue"
},
  "geometry": {"coordinates":[13.8850021362,46.6103935242],"type":"Point"}
}