{
  "type": "Feature",
  "properties": {
    "addr:full":"V\u00f6lkermarkter Str 15 Bleiburg K\u00e4rnten 9150",
    "addr:housenumber":"15",
    "addr:postcode":"9150",
    "addr:street":"Str;Kaernten",
    "iso:country":"AT",
    "sg:address":"V\u00f6lkermarkter Str 15",
    "sg:city":"Bleiburg",
    "sg:orig_category":"Autohandel",
    "sg:phone":"+43 4235 2027",
    "sg:postcode":"9150",
    "sg:province":"K\u00e4rnten",
    "wof:name":"Pustnik Werner",
    "wof:placetype":"venue"
},
  "geometry": {"coordinates":[14.7956285477,46.5940475464],"type":"Point"}
}