{
  "type": "Feature",
  "properties": {
    "addr:full":"Handelsstr 4 Obertrum am See Salzburg 5162",
    "addr:housenumber":"4",
    "addr:postcode":"5162",
    "addr:street":"Handelsstr;Salzburg",
    "iso:country":"AT",
    "sg:address":"Handelsstr 4",
    "sg:city":"Obertrum am See",
    "sg:orig_category":"Lebensmittel / Einzelhandel",
    "sg:phone":"+43 6219 62770",
    "sg:postcode":"5162",
    "sg:province":"Salzburg",
    "wof:name":"ADEG Contra Markt",
    "wof:placetype":"venue"
},
  "geometry": {"coordinates":[13.0815429688,47.9368896484],"type":"Point"}
}