{
  "type": "Feature",
  "properties": {
    "addr:full":"Hauptpl 64 Obervellach K\u00e4rnten 9821",
    "addr:housenumber":"64",
    "addr:postcode":"9821",
    "addr:street":"Hauptpl;Kaernten",
    "iso:country":"AT",
    "sg:address":"Hauptpl 64",
    "sg:city":"Obervellach",
    "sg:classifiers":[
        {
            "category":"Travel",
            "subcategory":"Hotels & Motels",
            "type":"Entertainment"
        }
    ],
    "sg:phone":"+43 4782 22590",
    "sg:postcode":"9821",
    "sg:province":"K\u00e4rnten",
    "wof:name":"Hotel Pacher",
    "wof:placetype":"venue"
},
  "geometry": {"coordinates":[13.202000618,46.9322319031],"type":"Point"}
}