{
  "type": "Feature",
  "properties": {
    "iso:country":"AT",
    "sg:address":"Karolineng 16a",
    "sg:city":"Wien",
    "sg:orig_category":"Architekten",
    "sg:phone":"+43 1 5055312",
    "sg:postcode":"1040",
    "sg:province":"Wien",
    "wof:name":"Wilda Bernd Dipl-Ing",
    "wof:placetype":"venue"
},
  "geometry": {"coordinates":[16.3767280579,48.1907348633],"type":"Point"}
}