{
  "type": "Feature",
  "properties": {
    "iso:country":"AT",
    "sg:address":"Weingartenweg 1",
    "sg:city":"Moosburg",
    "sg:orig_category":"Forstverwaltungen",
    "sg:phone":"+43 4272 83443",
    "sg:postcode":"9062",
    "sg:province":"K\u00e4rnten",
    "wof:name":"Goess Peter Dipl-Ing",
    "wof:placetype":"venue"
},
  "geometry": {"coordinates":[14.1693716049,46.6563644409],"type":"Point"}
}