{
  "type": "Feature",
  "properties": {
    "addr:full":"Michael-Koch-Str 25 Mattersburg Burgenland 7210",
    "addr:housenumber":"25",
    "addr:postcode":"7210",
    "addr:street":"Michael-Koch-Str",
    "iso:country":"AT",
    "sg:address":"Michael-Koch-Str 25",
    "sg:city":"Mattersburg",
    "sg:orig_category":"Alarmanlagen U Sicherheitssysteme",
    "sg:phone":"+43 4326 2663422",
    "sg:postcode":"7210",
    "sg:province":"Burgenland",
    "wof:name":"ASB Sicherheitstechnik GmbH",
    "wof:placetype":"venue"
},
  "geometry": {"coordinates":[16.398349762,47.7387771606],"type":"Point"}
}