{
  "type": "Feature",
  "properties": {
    "addr:full":"Hauptpl 16 Gols Burgenland 7122",
    "addr:housenumber":"16",
    "addr:postcode":"7122",
    "addr:street":"Hauptpl",
    "iso:country":"AT",
    "sg:address":"Hauptpl 16",
    "sg:city":"Gols",
    "sg:orig_category":"Fenster",
    "sg:phone":"+43 4321 7323903",
    "sg:postcode":"7122",
    "sg:province":"Burgenland",
    "wof:name":"T\u00fcchler Albin",
    "wof:placetype":"venue"
},
  "geometry": {"coordinates":[16.9074497223,47.8977928162],"type":"Point"}
}