{
  "type": "Feature",
  "properties": {
    "addr:full":"Tirolerhofstr 8 Leonding Ober\u00f6sterreich 4060",
    "addr:housenumber":"8",
    "addr:postcode":"4060",
    "addr:street":"Tirolerhofstr",
    "iso:country":"AT",
    "sg:address":"Tirolerhofstr 8",
    "sg:city":"Leonding",
    "sg:orig_category":"Ingenieurkonsulenten / Zivilingenieure",
    "sg:phone":"+43 732 671652",
    "sg:postcode":"4060",
    "sg:province":"Ober\u00f6sterreich",
    "wof:name":"Mayr Johann Prof Dipl-Ing",
    "wof:placetype":"venue"
},
  "geometry": {"coordinates":[14.2538051605,48.2841835022],"type":"Point"}
}