{
  "type": "Feature",
  "properties": {
    "iso:country":"AT",
    "sg:address":"Horner Strasse 24",
    "sg:city":"Horn",
    "sg:orig_category":"First-Aid Kits",
    "sg:phone":"+43 2982 2928",
    "sg:postcode":"3580",
    "sg:province":"Nieder\u00f6sterreich",
    "sg:website":"members.aon.at/porod.robert",
    "wof:name":"Medizintechnik Robert Porod",
    "wof:placetype":"venue"
},
  "geometry": {"coordinates":[15.6326532364,48.6719856262],"type":"Point"}
}