{
  "type": "Feature",
  "properties": {
    "addr:full":"Mayrwiesstr 5 Hallwang Salzburg 5300",
    "addr:housenumber":"5",
    "addr:postcode":"5300",
    "addr:street":"Mayrwiesstr;Salzburg",
    "iso:country":"AT",
    "sg:address":"Mayrwiesstr 5",
    "sg:city":"Hallwang",
    "sg:orig_category":"Transportbeton",
    "sg:phone":"+43 662 661255",
    "sg:postcode":"5300",
    "sg:province":"Salzburg",
    "wof:name":"Readymix Salzburg Transporbeton GmbH",
    "wof:placetype":"venue"
},
  "geometry": {"coordinates":[13.0830469131,47.831287384],"type":"Point"}
}