{
  "type": "Feature",
  "properties": {
    "addr:full":"St Veiter Str 43 Klagenfurt K\u00e4rnten 9020",
    "addr:housenumber":"43",
    "addr:postcode":"9020",
    "addr:street":"St Veiter Str;Kaernten",
    "iso:country":"AT",
    "sg:address":"St Veiter Str 43",
    "sg:city":"Klagenfurt",
    "sg:orig_category":"Garagen Parkgaragen",
    "sg:phone":"+43 463 501920",
    "sg:postcode":"9020",
    "sg:province":"K\u00e4rnten",
    "wof:name":"APCOA Parking Austria AG",
    "wof:placetype":"venue"
},
  "geometry": {"coordinates":[14.309548378,46.6280937195],"type":"Point"}
}