{
  "type": "Feature",
  "properties": {
    "addr:full":"Simon-Redtenbacher-Pl 4 Kirchdorf an der Krems Ober\u00f6sterreich 4560",
    "addr:housenumber":"4",
    "addr:postcode":"4560",
    "addr:street":"Simon-Redtenbacher-Pl",
    "iso:country":"AT",
    "sg:address":"Simon-Redtenbacher-Pl 4",
    "sg:city":"Kirchdorf an der Krems",
    "sg:classifiers":[
        {
            "category":"Restaurant",
            "type":"Food & Drink"
        }
    ],
    "sg:phone":"+43 4367 66077144",
    "sg:postcode":"4560",
    "sg:province":"Ober\u00f6sterreich",
    "wof:name":"Horny Ferdinand - Stil- u Bauernm\u00f6belrestaurierung",
    "wof:placetype":"venue"
},
  "geometry": {"coordinates":[14.1221961975,47.9061393738],"type":"Point"}
}