{
  "type": "Feature",
  "properties": {
    "addr:full":"Landstrasse 61 Zwettl Nieder\u00f6sterreich 3910",
    "addr:housenumber":"61",
    "addr:postcode":"3910",
    "addr:street":"Landstrasse;Niederoesterreich",
    "iso:country":"AT",
    "sg:address":"Landstrasse 61",
    "sg:city":"Zwettl",
    "sg:orig_category":"Bags, Customized",
    "sg:phone":"+43 2822 52453",
    "sg:postcode":"3910",
    "sg:province":"Nieder\u00f6sterreich",
    "sg:website":"holztaschen.at",
    "wof:name":"Christian Franzus",
    "wof:placetype":"venue"
},
  "geometry": {"coordinates":[15.165389061,48.6063995361],"type":"Point"}
}