{
  "type": "Feature",
  "properties": {
    "addr:full":"Gro\u00dfendorf 66 Ried im Traunkreis Ober\u00f6sterreich 4551",
    "addr:housenumber":"66",
    "addr:postcode":"4551",
    "addr:street":"Grossendorf",
    "iso:country":"AT",
    "sg:address":"Gro\u00dfendorf 66",
    "sg:city":"Ried im Traunkreis",
    "sg:classifiers":[
        {
            "category":"Building & Trades",
            "subcategory":"Construction",
            "type":"Services"
        }
    ],
    "sg:phone":"+43 7588 7400",
    "sg:postcode":"4551",
    "sg:province":"Ober\u00f6sterreich",
    "sg:tags":[
        "rooms",
        "sauna"
    ],
    "sg:website":"happy-pool.com",
    "wof:name":"Happy-pool Schwimmbad- und Saunatechnik GmbH",
    "wof:placetype":"venue"
},
  "geometry": {"coordinates":[14.0738592148,48.0253601074],"type":"Point"}
}