{
  "type": "Feature",
  "properties": {
    "addr:full":"Edmund Aigner-Str 3 Linz Ober\u00f6sterreich 4030",
    "addr:housenumber":"3",
    "addr:postcode":"4030",
    "iso:country":"AT",
    "sg:address":"Edmund Aigner-Str 3",
    "sg:city":"Linz",
    "sg:orig_category":"Psychotherapie",
    "sg:phone":"+43 732 301495",
    "sg:postcode":"4030",
    "sg:province":"Ober\u00f6sterreich",
    "wof:name":"Weibold Margot",
    "wof:placetype":"venue"
},
  "geometry": {"coordinates":[14.3324270248,48.2401123047],"type":"Point"}
}