{
  "type": "Feature",
  "properties": {
    "addr:full":"Sterzinger Str 12B Kufstein Tirol 6330",
    "addr:postcode":"6330",
    "addr:street":"Str 12B;Tirol",
    "iso:country":"AT",
    "sg:address":"Sterzinger Str 12B",
    "sg:city":"Kufstein",
    "sg:classifiers":[
        {
            "category":"Taxi",
            "type":"Transportation"
        }
    ],
    "sg:phone":"+43 4353 7267474",
    "sg:postcode":"6330",
    "sg:province":"Tirol",
    "sg:tags":[
        "personentransporte",
        "u"
    ],
    "wof:name":"Taxi Bundschuh KEG",
    "wof:placetype":"venue"
},
  "geometry": {"coordinates":[12.1782360077,47.5904846191],"type":"Point"}
}