{
  "type": "Feature",
  "properties": {
    "addr:full":"Lazarettg 19 Wien Wien 1090",
    "addr:housenumber":"19",
    "addr:postcode":"1090",
    "addr:street":"Lazarettg",
    "iso:country":"AT",
    "sg:address":"Lazarettg 19",
    "sg:city":"Wien",
    "sg:orig_category":"Forschungsinstitute",
    "sg:phone":"+43 4314 081091",
    "sg:postcode":"1090",
    "sg:province":"Wien",
    "wof:name":"Biomedizinische ForschungsgesmbH",
    "wof:placetype":"venue"
},
  "geometry": {"coordinates":[16.3485088348,48.2172927856],"type":"Point"}
}