{
  "type": "Feature",
  "properties": {
    "addr:full":"Weinberggasse 51 Wien Wien 1190",
    "addr:housenumber":"51",
    "addr:postcode":"1190",
    "addr:street":"Weinberggasse",
    "iso:country":"AT",
    "sg:address":"Weinberggasse 51",
    "sg:city":"Wien",
    "sg:classifiers":[
        {
            "category":"Park",
            "subcategory":"Town Common",
            "type":"Public Place"
        }
    ],
    "sg:phone":"+43 1 3683574",
    "sg:postcode":"1190",
    "sg:province":"Wien",
    "sg:tags":[
        "car",
        "lift"
    ],
    "sg:website":"ems-industries.at",
    "wof:name":"El. Maschinen Montage & Service F. R. Plattner Ges.m.b.H.",
    "wof:placetype":"venue"
},
  "geometry": {"coordinates":[16.3337306976,48.2433929443],"type":"Point"}
}