{
  "type": "Feature",
  "properties": {
    "addr:full":"Im Markt 2 Gaming Nieder\u00f6sterreich 3292",
    "addr:housenumber":"2",
    "addr:postcode":"3292",
    "addr:street":"Im Markt",
    "iso:country":"AT",
    "sg:address":"Im Markt 2",
    "sg:city":"Gaming",
    "sg:orig_category":"Papier- U Schreibwaren / Einzelhandel",
    "sg:phone":"+43 4374 8567150",
    "sg:postcode":"3292",
    "sg:province":"Nieder\u00f6sterreich",
    "wof:name":"Dienstbier Christa",
    "wof:placetype":"venue"
},
  "geometry": {"coordinates":[15.0880804062,47.9290084839],"type":"Point"}
}