{
  "type": "Feature",
  "properties": {
    "addr:full":"Leithag 1a Zurndorf Burgenland 2424",
    "addr:housenumber":"1a",
    "addr:postcode":"2424",
    "addr:street":"Leithag",
    "iso:country":"AT",
    "sg:address":"Leithag 1a",
    "sg:city":"Zurndorf",
    "sg:orig_category":"Friseure U Frisiersalons",
    "sg:phone":"+43 4321 472587",
    "sg:postcode":"2424",
    "sg:province":"Burgenland",
    "wof:name":"Schmidt Hedwig",
    "wof:placetype":"venue"
},
  "geometry": {"coordinates":[17.0035190582,47.9828453064],"type":"Point"}
}