{
  "type": "Feature",
  "properties": {
    "addr:full":"Ischler Str 65 Bad Aussee Steiermark 8990",
    "addr:housenumber":"65",
    "addr:postcode":"8990",
    "addr:street":"Str",
    "iso:country":"AT",
    "sg:address":"Ischler Str 65",
    "sg:city":"Bad Aussee",
    "sg:orig_category":"Banken U Sparkassen",
    "sg:phone":"+43 4336 22523450",
    "sg:postcode":"8990",
    "sg:province":"Steiermark",
    "wof:name":"Bankomat d Raiffeisenbank Steirisches Salzkammergut",
    "wof:placetype":"venue"
},
  "geometry": {"coordinates":[13.7821416855,47.609336853],"type":"Point"}
}