{
  "type": "Feature",
  "properties": {
    "addr:full":"\u00c4u\u00dferer Markt 5 Kirchschlag in der Buckligen Welt Nieder\u00f6sterreich 2860",
    "addr:housenumber":"5",
    "addr:postcode":"2860",
    "addr:street":"Markt",
    "iso:country":"AT",
    "sg:address":"\u00c4u\u00dferer Markt 5",
    "sg:city":"Kirchschlag in der Buckligen Welt",
    "sg:orig_category":"Rauchfangkehrer",
    "sg:phone":"+43 2646 2330",
    "sg:postcode":"2860",
    "sg:province":"Nieder\u00f6sterreich",
    "wof:name":"Pichler Franz",
    "wof:placetype":"venue"
},
  "geometry": {"coordinates":[16.2951545715,47.501991272],"type":"Point"}
}