{
  "type": "Feature",
  "properties": {
    "addr:full":"Mautner-Markhof-G 45 Wien Wien 1110",
    "addr:housenumber":"45",
    "addr:postcode":"1110",
    "addr:street":"Mautner-Markhof-G",
    "iso:country":"AT",
    "sg:address":"Mautner-Markhof-G 45",
    "sg:city":"Wien",
    "sg:orig_category":"Musikunterricht",
    "sg:phone":"+43 4317 434000",
    "sg:postcode":"1110",
    "sg:province":"Wien",
    "wof:name":"Mahler Gustav Konservatorium f Musik u darstellende Kunst",
    "wof:placetype":"venue"
},
  "geometry": {"coordinates":[16.4207038879,48.1756477356],"type":"Point"}
}