{
  "type": "Feature",
  "properties": {
    "iso:country":"AT",
    "sg:address":"Herrgottwiesgasse 117-119",
    "sg:city":"Graz",
    "sg:classifiers":[
        {
            "category":"Education",
            "subcategory":"Library",
            "type":"Public Place"
        }
    ],
    "sg:phone":"+43 316 817171",
    "sg:postcode":"8020",
    "sg:province":"Steiermark",
    "sg:tags":[
        "software"
    ],
    "sg:website":"bytework.at",
    "wof:name":"ByteWork Datenverarbeitungs GmbH",
    "wof:placetype":"venue"
},
  "geometry": {"coordinates":[15.4331445694,47.0480804443],"type":"Point"}
}