{
  "type": "Feature",
  "properties": {
    "addr:full":"D\u00f6llach 50 Au Steiermark 8624",
    "addr:housenumber":"50",
    "addr:postcode":"8624",
    "addr:street":"Doellach",
    "iso:country":"AT",
    "sg:address":"D\u00f6llach 50",
    "sg:city":"Au",
    "sg:classifiers":[
        {
            "category":"Manufacturing",
            "subcategory":"Metals",
            "type":"Manufacturing & Wholesale Goods"
        }
    ],
    "sg:phone":"+43 4338 632788",
    "sg:postcode":"8624",
    "sg:province":"Steiermark",
    "sg:tags":[
        "processing"
    ],
    "wof:name":"HELDECO CAD CAM FERTIGUNGSTECHNIK GESMBH",
    "wof:placetype":"venue"
},
  "geometry": {"coordinates":[15.296705246,47.5503921509],"type":"Point"}
}