{
  "type": "Feature",
  "properties": {
    "iso:country":"AT",
    "sg:address":"Hauptstr 69",
    "sg:city":"Linz",
    "sg:orig_category":"Fotografen",
    "sg:phone":"+43 732 718866",
    "sg:postcode":"4040",
    "sg:province":"Ober\u00f6sterreich",
    "wof:name":"Fotostudio 7 Margit Harruk",
    "wof:placetype":"venue"
},
  "geometry": {"coordinates":[14.2809181213,48.3142814636],"type":"Point"}
}