{
  "type": "Feature",
  "properties": {
    "iso:country":"AT",
    "sg:address":"Seideng 26",
    "sg:city":"Wien",
    "sg:classifiers":[
        {
            "category":"Internet Cafe",
            "subcategory":"None",
            "type":"Food & Drink"
        }
    ],
    "sg:phone":"+43 1 52353430",
    "sg:postcode":"1070",
    "sg:province":"Wien",
    "wof:name":"U.R.L. Agentur f Informationsdesign GmbH",
    "wof:placetype":"venue"
},
  "geometry": {"coordinates":[16.3421497345,48.200553894],"type":"Point"}
}