{
  "type": "Feature",
  "properties": {
    "iso:country":"AT",
    "sg:address":"Nr 3",
    "sg:city":"Kainisch",
    "sg:orig_category":"Zimmereien",
    "sg:phone":"+43 3624 2790",
    "sg:postcode":"8984",
    "sg:province":"Steiermark",
    "wof:name":"Tepidarium & Zimmerei Inh Peter Hei\u00df",
    "wof:placetype":"venue"
},
  "geometry": {"coordinates":[13.8338899612,47.5548400879],"type":"Point"}
}