{
  "type": "Feature",
  "properties": {
    "addr:full":"Bahnhofstr 1 Sierning Ober\u00f6sterreich 4522",
    "addr:housenumber":"1",
    "addr:postcode":"4522",
    "addr:street":"Bahnhofstr",
    "iso:country":"AT",
    "sg:address":"Bahnhofstr 1",
    "sg:city":"Sierning",
    "sg:orig_category":"Papier- U Schreibwaren / Einzelhandel",
    "sg:phone":"+43 7259 3156",
    "sg:postcode":"4522",
    "sg:province":"Ober\u00f6sterreich",
    "wof:name":"Scheinecker Heidi",
    "wof:placetype":"venue"
},
  "geometry": {"coordinates":[14.310172081,48.0436935425],"type":"Point"}
}