{
  "type": "Feature",
  "properties": {
    "addr:full":"Hauptpl 30 Retz Nieder\u00f6sterreich 2070",
    "addr:housenumber":"30",
    "addr:postcode":"2070",
    "addr:street":"Hauptpl",
    "iso:country":"AT",
    "sg:address":"Hauptpl 30",
    "sg:city":"Retz",
    "sg:orig_category":"Gemeinden",
    "sg:phone":"+43 2942 22230",
    "sg:postcode":"2070",
    "sg:province":"Nieder\u00f6sterreich",
    "wof:name":"Stadtgemeinde Retz",
    "wof:placetype":"venue"
},
  "geometry": {"coordinates":[15.9507322311,48.7574462891],"type":"Point"}
}