{
  "type": "Feature",
  "properties": {
    "addr:full":"Hainfelder Str 24 Pottenstein Nieder\u00f6sterreich 2563",
    "addr:postcode":"2563",
    "addr:street":"Str 24",
    "iso:country":"AT",
    "sg:address":"Hainfelder Str 24",
    "sg:city":"Pottenstein",
    "sg:orig_category":"Volksschulen",
    "sg:phone":"+43 4326 72851700",
    "sg:postcode":"2563",
    "sg:province":"Nieder\u00f6sterreich",
    "wof:name":"Volksschule",
    "wof:placetype":"venue"
},
  "geometry": {"coordinates":[16.0939159393,47.9607772827],"type":"Point"}
}