{
  "type": "Feature",
  "properties": {
    "addr:full":"Nr 71 Lieserbr\u00fccke K\u00e4rnten 9851",
    "addr:postcode":"9851",
    "addr:street":"Nr 71 Lieserbruecke Kaernten",
    "iso:country":"AT",
    "sg:address":"Nr 71",
    "sg:city":"Lieserbr\u00fccke",
    "sg:orig_category":"Restaurants: Italienisch",
    "sg:phone":"+43 4762 36555",
    "sg:postcode":"9851",
    "sg:province":"K\u00e4rnten",
    "wof:name":"Ristorante Da Piero",
    "wof:placetype":"venue"
},
  "geometry": {"coordinates":[13.4910869598,46.82862854],"type":"Point"}
}