{
  "type": "Feature",
  "properties": {
    "addr:full":"Trillerg 6 Wien Wien 1210",
    "addr:housenumber":"6",
    "addr:postcode":"1210",
    "addr:street":"Trillerg",
    "iso:country":"AT",
    "sg:address":"Trillerg 6",
    "sg:city":"Wien",
    "sg:orig_category":"Lebensmittel / Einzelhandel",
    "sg:phone":"+43 1 2922511",
    "sg:postcode":"1210",
    "sg:province":"Wien",
    "wof:name":"INTERSPAR Markt",
    "wof:placetype":"venue"
},
  "geometry": {"coordinates":[16.4048194885,48.2732009888],"type":"Point"}
}