{
  "type": "Feature",
  "properties": {
    "iso:country":"AT",
    "sg:address":"Hauptstr 103",
    "sg:city":"Marz",
    "sg:classifiers":[
        {
            "category":"Travel",
            "subcategory":"Hotels & Motels",
            "type":"Entertainment"
        }
    ],
    "sg:phone":"+43 4326 2663967",
    "sg:postcode":"7221",
    "sg:province":"Burgenland",
    "wof:name":"Cafe Royal",
    "wof:placetype":"venue"
},
  "geometry": {"coordinates":[16.4091644287,47.7146148682],"type":"Point"}
}