{
  "type": "Feature",
  "properties": {
    "addr:full":"Gottfried-Keller-Gasse 13 Wien Wien 1030",
    "addr:housenumber":"13",
    "addr:postcode":"1030",
    "addr:street":"Gottfried-Keller-Gasse",
    "iso:country":"AT",
    "sg:address":"Gottfried-Keller-Gasse 13",
    "sg:city":"Wien",
    "sg:classifiers":[
        {
            "category":"Food & Beverages",
            "subcategory":"Fruits & Vegetables",
            "type":"Retail Goods"
        }
    ],
    "sg:phone":"+43 1 7124564",
    "sg:postcode":"1030",
    "sg:province":"Wien",
    "sg:tags":[
        "frozen"
    ],
    "wof:name":"Donaufrucht Handelsges.m.b.H.",
    "wof:placetype":"venue"
},
  "geometry": {"coordinates":[16.3832015991,48.1986923218],"type":"Point"}
}