{
  "type": "Feature",
  "properties": {
    "addr:full":"Denglerg 13 Wien Wien 1150",
    "addr:housenumber":"13",
    "addr:postcode":"1150",
    "addr:street":"Denglerg",
    "iso:country":"AT",
    "sg:address":"Denglerg 13",
    "sg:city":"Wien",
    "sg:orig_category":"Elektromotoren / Reparatur U Wickelei",
    "sg:phone":"+43 1 8932660",
    "sg:postcode":"1150",
    "sg:province":"Wien",
    "wof:name":"Smitka Wilhelm GesmbH",
    "wof:placetype":"venue"
},
  "geometry": {"coordinates":[16.3283500671,48.1932106018],"type":"Point"}
}