{
  "type": "Feature",
  "properties": {
    "addr:full":"Egerseeweg 5 Henndorf am Wallersee Salzburg 5302",
    "addr:housenumber":"5",
    "addr:postcode":"5302",
    "addr:street":"Egerseeweg",
    "iso:country":"AT",
    "sg:address":"Egerseeweg 5",
    "sg:city":"Henndorf am Wallersee",
    "sg:orig_category":"Steuerberatung",
    "sg:phone":"+43 4362 146310",
    "sg:postcode":"5302",
    "sg:province":"Salzburg",
    "wof:name":"Hofer Manfred Mag Dr",
    "wof:placetype":"venue"
},
  "geometry": {"coordinates":[13.1813011169,47.9008140564],"type":"Point"}
}