{
  "type": "Feature",
  "properties": {
    "iso:country":"AT",
    "sg:address":"Hauptpl 7",
    "sg:city":"Kirchdorf an der Krems",
    "sg:classifiers":[
        {
            "category":"Restaurant",
            "type":"Food & Drink"
        }
    ],
    "sg:phone":"+43 4375 8261571",
    "sg:postcode":"4560",
    "sg:province":"Ober\u00f6sterreich",
    "sg:tags":[
        "pizzeria"
    ],
    "wof:name":"Schabanack Pizza-Kebap",
    "wof:placetype":"venue"
},
  "geometry": {"coordinates":[14.1228322983,47.9052124023],"type":"Point"}
}