{
  "type": "Feature",
  "properties": {
    "addr:full":"Daponteg 13 Wien Wien 1030",
    "addr:housenumber":"13",
    "addr:postcode":"1030",
    "addr:street":"Daponteg",
    "iso:country":"AT",
    "sg:address":"Daponteg 13",
    "sg:city":"Wien",
    "sg:orig_category":"Werbeagenturen",
    "sg:phone":"+43 1 7132976",
    "sg:postcode":"1030",
    "sg:province":"Wien",
    "wof:name":"Beck & Co Agentur f Marketing und Kommunikation GmbH KEG",
    "wof:placetype":"venue"
},
  "geometry": {"coordinates":[16.3874645233,48.1979446411],"type":"Point"}
}