{
  "type": "Feature",
  "properties": {
    "addr:full":"Industriezentrum N\u00f6 S\u00fcd Stra\u00dfe 2a Obj M8 Wiener Neudorf Nieder\u00f6sterreich 2351",
    "addr:housenumber":"2a obj",
    "addr:postcode":"2351",
    "addr:street":"Industriezentrum Noe Sued Strasse",
    "iso:country":"AT",
    "sg:address":"Industriezentrum N\u00f6 S\u00fcd Stra\u00dfe 2a Obj M8",
    "sg:city":"Wiener Neudorf",
    "sg:orig_category":"Automatisierungstechnik",
    "sg:phone":"+43 4322 36637190",
    "sg:postcode":"2351",
    "sg:province":"Nieder\u00f6sterreich",
    "wof:name":"AMH Automation Montage Handhabung Inh Dipl-Ing Lederbauer",
    "wof:placetype":"venue"
},
  "geometry": {"coordinates":[16.3183326721,48.0863113403],"type":"Point"}
}