{
  "type": "Feature",
  "properties": {
    "addr:full":"Nr 122 Bad Bleiberg K\u00e4rnten 9530",
    "addr:postcode":"9530",
    "addr:street":"Nr",
    "iso:country":"AT",
    "sg:address":"Nr 122",
    "sg:city":"Bad Bleiberg",
    "sg:orig_category":"\u00c3\u201erzte / F Allgemeinmedizin",
    "sg:phone":"+43 4342 442240",
    "sg:postcode":"9530",
    "sg:province":"K\u00e4rnten",
    "wof:name":"Fehringer Walther Dr",
    "wof:placetype":"venue"
},
  "geometry": {"coordinates":[13.6877374649,46.6243476868],"type":"Point"}
}