{
  "type": "Feature",
  "properties": {
    "addr:full":"Prentenweg 6 Thaur Tirol 6065",
    "addr:housenumber":"6",
    "addr:postcode":"6065",
    "addr:street":"Prentenweg;Tirol",
    "iso:country":"AT",
    "sg:address":"Prentenweg 6",
    "sg:city":"Thaur",
    "sg:orig_category":"Maler, Anstreicher U Lackierer",
    "sg:phone":"+43 4352 23492350",
    "sg:postcode":"6065",
    "sg:province":"Tirol",
    "wof:name":"Mairhofer Peter",
    "wof:placetype":"venue"
},
  "geometry": {"coordinates":[11.4709367752,47.2976455688],"type":"Point"}
}