{
  "type": "Feature",
  "properties": {
    "iso:country":"AT",
    "sg:address":"Hussarg 20",
    "sg:city":"Wiener Neustadt",
    "sg:orig_category":"\u00c3\u201erzte / F Allgemeinmedizin",
    "sg:phone":"+43 2622 24929",
    "sg:postcode":"2700",
    "sg:province":"Nieder\u00f6sterreich",
    "wof:name":"Kuttner Karl Dr",
    "wof:placetype":"venue"
},
  "geometry": {"coordinates":[16.2539482117,47.8146476746],"type":"Point"}
}