{
  "type": "Feature",
  "properties": {
    "iso:country":"AT",
    "sg:address":"Autokaderstr 3-7/Ekazent/Top 9",
    "sg:city":"Wien",
    "sg:classifiers":[
        {
            "category":"Retail",
            "subcategory":"Event Space",
            "type":"Services"
        }
    ],
    "sg:phone":"+43 1 2716378",
    "sg:postcode":"1210",
    "sg:province":"Wien",
    "sg:tags":[
        "hand-",
        "u",
        "fu\u00c3\u0178pflege"
    ],
    "wof:name":"Wenger Ulrike Kosmetik und Fu\u00dfpflege",
    "wof:placetype":"venue"
},
  "geometry": {"coordinates":[16.3978404999,48.2579994202],"type":"Point"}
}