{
  "type": "Feature",
  "properties": {
    "iso:country":"AT",
    "sg:address":"Am Stadtpark 1",
    "sg:city":"Wien",
    "sg:orig_category":"Lastkraftwagen",
    "sg:phone":"+43 4317 993550",
    "sg:postcode":"1030",
    "sg:province":"Wien",
    "wof:name":"Transconstruct Handels- und BeteiligungsgesmbH",
    "wof:placetype":"venue"
},
  "geometry": {"coordinates":[16.3828201294,48.2062339783],"type":"Point"}
}