{
  "type": "Feature",
  "properties": {
    "addr:full":"Willersdorfer Str 26 Obersch\u00fctzen Burgenland 7432",
    "addr:postcode":"7432",
    "addr:street":"Str 26 Oberschuetzen",
    "iso:country":"AT",
    "sg:address":"Willersdorfer Str 26",
    "sg:city":"Obersch\u00fctzen",
    "sg:orig_category":"Lebens- U Sozialberatung",
    "sg:phone":"+43 3353 7652",
    "sg:postcode":"7432",
    "sg:province":"Burgenland",
    "sg:website":"www.zum.at",
    "wof:name":"Zumpf Manuela",
    "wof:placetype":"venue"
},
  "geometry": {"coordinates":[16.2026996613,47.3548049927],"type":"Point"}
}