{
  "type": "Feature",
  "properties": {
    "iso:country":"AT",
    "sg:address":"Schlo\u00dfg 2-4",
    "sg:city":"Marchegg",
    "sg:orig_category":"Erdarbeiten",
    "sg:phone":"+43 2285 64415",
    "sg:postcode":"2293",
    "sg:province":"Nieder\u00f6sterreich",
    "wof:name":"Buhl Josef",
    "wof:placetype":"venue"
},
  "geometry": {"coordinates":[16.9099159241,48.2816200256],"type":"Point"}
}