{
  "type": "Feature",
  "properties": {
    "iso:country":"AT",
    "sg:address":"Hochmuthg 5/33",
    "sg:city":"Wien",
    "sg:classifiers":[
        {
            "category":"Professional",
            "subcategory":"Computer Services",
            "type":"Services"
        }
    ],
    "sg:phone":"+43 1 2586132",
    "sg:postcode":"1220",
    "sg:province":"Wien",
    "sg:tags":[
        "software"
    ],
    "wof:name":"Knoll Alfred C",
    "wof:placetype":"venue"
},
  "geometry": {"coordinates":[16.4570293427,48.2534637451],"type":"Point"}
}