{
  "type": "Feature",
  "properties": {
    "addr:full":"Reisenbauerring 5/4 Wiener Neudorf Nieder\u00f6sterreich 2351",
    "addr:housenumber":"5 / 4",
    "addr:postcode":"2351",
    "addr:street":"Reisenbauerring",
    "iso:country":"AT",
    "sg:address":"Reisenbauerring 5/4",
    "sg:city":"Wiener Neudorf",
    "sg:orig_category":"Botendienste",
    "sg:phone":"+43 4322 3646119",
    "sg:postcode":"2351",
    "sg:province":"Nieder\u00f6sterreich",
    "wof:name":"Prompt-Service Handels- Logistik- u Transport GmbH",
    "wof:placetype":"venue"
},
  "geometry": {"coordinates":[16.3092422485,48.0886268616],"type":"Point"}
}