{
  "type": "Feature",
  "properties": {
    "addr:full":"Salzburger Str 40-42 Oberndorf Salzburg 5110",
    "addr:postcode":"40-42;5110",
    "addr:street":"Salzburger Str",
    "iso:country":"AT",
    "sg:address":"Salzburger Str 40-42",
    "sg:city":"Oberndorf",
    "sg:orig_category":"Fliesen U Platten",
    "sg:phone":"+43 4362 727550",
    "sg:postcode":"5110",
    "sg:province":"Salzburg",
    "wof:name":"BAUKERAMIK HandelsgesmbH Verlegung Gro\u00df- u. Einzelhandel",
    "wof:placetype":"venue"
},
  "geometry": {"coordinates":[12.94282341,47.9431648254],"type":"Point"}
}