{
  "type": "Feature",
  "properties": {
    "iso:country":"AT",
    "sg:address":"Tr\u00f6lsberg 54",
    "sg:city":"Freistadt",
    "sg:orig_category":"Tischlereien",
    "sg:phone":"+43 7942 74000",
    "sg:postcode":"4240",
    "sg:province":"Ober\u00f6sterreich",
    "wof:name":"Kratochvil Johann",
    "wof:placetype":"venue"
},
  "geometry": {"coordinates":[14.5049953461,48.5119857788],"type":"Point"}
}