{
  "type": "Feature",
  "properties": {
    "addr:full":"Am Stollingbach 35 St. Lorenzen im M\u00fcrztal Steiermark 8642",
    "addr:housenumber":"35",
    "addr:postcode":"8642",
    "addr:street":"Am Stollingbach",
    "iso:country":"AT",
    "sg:address":"Am Stollingbach 35",
    "sg:city":"St. Lorenzen im M\u00fcrztal",
    "sg:orig_category":"Handelsagenturen",
    "sg:phone":"+43 4338 6430441",
    "sg:postcode":"8642",
    "sg:province":"Steiermark",
    "wof:name":"INTEC-Austria Ing Predl GmbH",
    "wof:placetype":"venue"
},
  "geometry": {"coordinates":[15.3747901917,47.4793739319],"type":"Point"}
}