{
  "type": "Feature",
  "properties": {
    "iso:country":"AT",
    "sg:address":"Nordbergg 6-8",
    "sg:city":"Andritz",
    "sg:orig_category":"Immobilienverwaltungen",
    "sg:phone":"+43 4331 6671327",
    "sg:postcode":"8045",
    "sg:province":"Steiermark",
    "wof:name":"Reiterer Realit\u00e4ten GmbH",
    "wof:placetype":"venue"
},
  "geometry": {"coordinates":[15.4285545349,47.103225708],"type":"Point"}
}