{
  "type": "Feature",
  "properties": {
    "addr:full":"Perger Str 12 Naarn im Machlande Ober\u00f6sterreich 4331",
    "addr:housenumber":"12",
    "addr:postcode":"4331",
    "addr:street":"Str",
    "iso:country":"AT",
    "sg:address":"Perger Str 12",
    "sg:city":"Naarn im Machlande",
    "sg:orig_category":"Hauptschulen",
    "sg:phone":"+43 7262 587970",
    "sg:postcode":"4331",
    "sg:province":"Ober\u00f6sterreich",
    "wof:name":"Hauptschule",
    "wof:placetype":"venue"
},
  "geometry": {"coordinates":[14.6115608215,48.2259674072],"type":"Point"}
}