{
  "type": "Feature",
  "properties": {
    "addr:full":"Schwarzenbergplatz 6 Wien Wien 1030",
    "addr:housenumber":"6",
    "addr:postcode":"1030",
    "addr:street":"Schwarzenbergplatz",
    "iso:country":"AT",
    "sg:address":"Schwarzenbergplatz 6",
    "sg:city":"Wien",
    "sg:classifiers":[
        {
            "category":"Communications",
            "subcategory":"Radio Station",
            "type":"Services"
        }
    ],
    "sg:phone":"+43 1 71630",
    "sg:postcode":"1030",
    "sg:province":"Wien",
    "sg:tags":[
        "medium",
        "analysis"
    ],
    "sg:website":"mediahausaustria.at",
    "wof:name":"Medihaus Austria Sp\u00e4th Ges.m.b.H.",
    "wof:placetype":"venue"
},
  "geometry": {"coordinates":[16.3769416809,48.1987724304],"type":"Point"}
}