{
  "type": "Feature",
  "properties": {
    "iso:country":"AT",
    "sg:address":"Siebenhirtenstr 32",
    "sg:city":"Mistelbach",
    "sg:orig_category":"Heurigen / Buschenschank",
    "sg:phone":"+43 2572 3985",
    "sg:postcode":"2130",
    "sg:province":"Nieder\u00f6sterreich",
    "wof:name":"Stubenvoll Ludwig",
    "wof:placetype":"venue"
},
  "geometry": {"coordinates":[16.5724334717,48.5700798035],"type":"Point"}
}