{
  "type": "Feature",
  "properties": {
    "addr:full":"Salurner Str 23 Kufstein Tirol 6330",
    "addr:housenumber":"23",
    "addr:postcode":"6330",
    "addr:street":"Str;Tirol",
    "iso:country":"AT",
    "sg:address":"Salurner Str 23",
    "sg:city":"Kufstein",
    "sg:orig_category":"Tischlereien",
    "sg:phone":"+43 4353 7265452",
    "sg:postcode":"6330",
    "sg:province":"Tirol",
    "sg:website":"tischler-muehlegger.at",
    "wof:name":"M\u00fchlegger Walter",
    "wof:placetype":"venue"
},
  "geometry": {"coordinates":[12.1638622284,47.5777397156],"type":"Point"}
}