{
  "type": "Feature",
  "properties": {
    "addr:full":"Rossakg 8 Wien Wien 1230",
    "addr:housenumber":"8",
    "addr:postcode":"1230",
    "addr:street":"Rossakg",
    "iso:country":"AT",
    "sg:address":"Rossakg 8",
    "sg:city":"Wien",
    "sg:orig_category":"Brandschutz, Aluminiumprofile, Aluminium, Aluminiumhalbfabrikate",
    "sg:phone":"+43 1 66715290",
    "sg:postcode":"1230",
    "sg:province":"Wien",
    "sg:website":"www.hueckrichter.at",
    "wof:name":"Hueck + Richter Aluminium GmbH",
    "wof:placetype":"venue"
},
  "geometry": {"coordinates":[16.3305873871,48.146686554],"type":"Point"}
}