{
  "type": "Feature",
  "properties": {
    "iso:country":"AT",
    "sg:address":"Fr\u00fchlingstr 11",
    "sg:city":"Dornbirn",
    "sg:orig_category":"Beratungsstellen",
    "sg:phone":"+43 5572 213310",
    "sg:postcode":"6850",
    "sg:province":"Vorarlberg",
    "wof:name":"IfS-Reha, Beratung f Menschen mit Behinderung",
    "wof:placetype":"venue"
},
  "geometry": {"coordinates":[9.7437801361,47.4131889343],"type":"Point"}
}