{
  "type": "Feature",
  "properties": {
    "addr:full":"Donau-City-Str 2 Wien Wien 1220",
    "addr:housenumber":"2",
    "addr:postcode":"1220",
    "addr:street":"Donau-City-Str",
    "iso:country":"AT",
    "sg:address":"Donau-City-Str 2",
    "sg:city":"Wien",
    "sg:orig_category":"Non-Classified Establishments",
    "sg:phone":"+43 1 2630952",
    "sg:postcode":"1220",
    "sg:province":"Wien",
    "wof:name":"Pfarramt Kaiserm\u00fchlen",
    "wof:placetype":"venue"
},
  "geometry": {"coordinates":[16.4155807495,48.2328796387],"type":"Point"}
}