{
  "type": "Feature",
  "properties": {
    "addr:full":"Reith 9 Neukirchen am Walde Ober\u00f6sterreich 4724",
    "addr:housenumber":"9",
    "addr:postcode":"4724",
    "addr:street":"Reith",
    "iso:country":"AT",
    "sg:address":"Reith 9",
    "sg:city":"Neukirchen am Walde",
    "sg:orig_category":"Weine / Einzelhandel",
    "sg:phone":"+43 4372 783611",
    "sg:postcode":"4724",
    "sg:province":"Ober\u00f6sterreich",
    "wof:name":"Dobetsberger Alois",
    "wof:placetype":"venue"
},
  "geometry": {"coordinates":[13.8150224686,48.3966751099],"type":"Point"}
}