{
  "type": "Feature",
  "properties": {
    "iso:country":"AT",
    "sg:address":"Stiftg. 31 ",
    "sg:city":"Wien",
    "sg:classifiers":[
        {
            "category":"Manufacturing",
            "subcategory":"Printing",
            "type":"Manufacturing & Wholesale Goods"
        }
    ],
    "sg:phone":"+43 4315 21240",
    "sg:postcode":"1070",
    "sg:province":"Wien",
    "sg:tags":[
        "publishing"
    ],
    "wof:name":"WAILAND & WALDSTEIN GMBH",
    "wof:placetype":"venue"
},
  "geometry": {"coordinates":[16.3540248871,48.2034378052],"type":"Point"}
}