{
  "type": "Feature",
  "properties": {
    "addr:full":"Wilhelm-Fazokas-Str 718 Kaprun Salzburg 5710",
    "addr:housenumber":"718",
    "addr:postcode":"5710",
    "addr:street":"Kaprun Salzburg",
    "iso:country":"AT",
    "sg:address":"Wilhelm-Fazokas-Str 718",
    "sg:city":"Kaprun",
    "sg:orig_category":"Freizeit- U Sportbekleidung",
    "sg:phone":"+43 4365 4787150",
    "sg:postcode":"5710",
    "sg:province":"Salzburg",
    "wof:name":"Mode u Sport Moreau GesmbH & Co KG",
    "wof:placetype":"venue"
},
  "geometry": {"coordinates":[12.758146286,47.2713813782],"type":"Point"}
}