{
  "type": "Feature",
  "properties": {
    "addr:full":"Ennstaler Bundesstr 68 Trautenfels Steiermark 8951",
    "addr:housenumber":"68",
    "addr:postcode":"8951",
    "addr:street":"Trautenfels Steiermark",
    "iso:country":"AT",
    "sg:address":"Ennstaler Bundesstr 68",
    "sg:city":"Trautenfels",
    "sg:orig_category":"Autoverwertung",
    "sg:phone":"+43 3682 243010",
    "sg:postcode":"8951",
    "sg:province":"Steiermark",
    "wof:name":"Moser Erich & Erich Moser GesnbR",
    "wof:placetype":"venue"
},
  "geometry": {"coordinates":[14.0831203461,47.5187416077],"type":"Point"}
}