{
  "type": "Feature",
  "properties": {
    "iso:country":"AT",
    "sg:address":"Alte Landstrasse 1",
    "sg:city":"Wilhering",
    "sg:classifiers":[
        {
            "category":"Home & Garden",
            "subcategory":"Home Furnishings",
            "type":"Retail Goods"
        }
    ],
    "sg:phone":"+43 7226 2262",
    "sg:postcode":"4073",
    "sg:province":"Ober\u00f6sterreich",
    "sg:tags":[
        "air-conditioners"
    ],
    "wof:name":"Albin Gaggl K\u00fchlanlagen",
    "wof:placetype":"venue"
},
  "geometry": {"coordinates":[14.173330307,48.3161087036],"type":"Point"}
}