{
  "type": "Feature",
  "properties": {
    "addr:full":"Lorenz-Mandl-G. 25 Wien Wien 1160",
    "addr:housenumber":"25",
    "addr:postcode":"1160",
    "addr:street":"Lorenz-Mandl-G.",
    "iso:country":"AT",
    "sg:address":"Lorenz-Mandl-G. 25",
    "sg:city":"Wien",
    "sg:classifiers":[
        {
            "category":"Professional",
            "subcategory":"Engineering",
            "type":"Services"
        }
    ],
    "sg:phone":"+43 4314 9574550",
    "sg:postcode":"1160",
    "sg:province":"Wien",
    "sg:tags":[
        "machine",
        "-",
        "mechanical"
    ],
    "wof:name":"ZARZI GMBH",
    "wof:placetype":"venue"
},
  "geometry": {"coordinates":[16.3060684204,48.2090339661],"type":"Point"}
}