{
  "type": "Feature",
  "properties": {
    "addr:full":"Patscher Str 10 Innsbruck-Igls Tirol 6080",
    "addr:housenumber":"10",
    "addr:postcode":"6080",
    "addr:street":"Str",
    "iso:country":"AT",
    "sg:address":"Patscher Str 10",
    "sg:city":"Innsbruck-Igls",
    "sg:classifiers":[
        {
            "category":"Internet Cafe",
            "subcategory":"None",
            "type":"Food & Drink"
        }
    ],
    "sg:phone":"+43 512 378942",
    "sg:postcode":"6080",
    "sg:province":"Tirol",
    "wof:name":"Heine NetSolutions",
    "wof:placetype":"venue"
},
  "geometry": {"coordinates":[11.4084882736,47.2294425964],"type":"Point"}
}