{
  "type": "Feature",
  "properties": {
    "addr:full":"Stuwerstr 46 Wien Wien 1020",
    "addr:housenumber":"46",
    "addr:postcode":"1020",
    "addr:street":"Stuwerstr",
    "iso:country":"AT",
    "sg:address":"Stuwerstr 46",
    "sg:city":"Wien",
    "sg:classifiers":[
        {
            "category":"Taxi",
            "type":"Transportation"
        }
    ],
    "sg:phone":"+43 4365 04540450",
    "sg:postcode":"1020",
    "sg:province":"Wien",
    "sg:tags":[
        "personentransporte",
        "u"
    ],
    "wof:name":"Kostadin Stefanov OEG",
    "wof:placetype":"venue"
},
  "geometry": {"coordinates":[16.4044151306,48.218662262],"type":"Point"}
}