{
  "type": "Feature",
  "properties": {
    "addr:full":"Bahnhofstr 8 Villach K\u00e4rnten 9500",
    "addr:housenumber":"8",
    "addr:postcode":"9500",
    "addr:street":"Bahnhofstr;Kaernten",
    "iso:country":"AT",
    "sg:address":"Bahnhofstr 8",
    "sg:city":"Villach",
    "sg:classifiers":[
        {
            "category":"Restaurant",
            "type":"Food & Drink"
        }
    ],
    "sg:phone":"+43 4242 242220",
    "sg:postcode":"9500",
    "sg:province":"K\u00e4rnten",
    "wof:name":"Brauhof Villach",
    "wof:placetype":"venue"
},
  "geometry": {"coordinates":[13.8491191864,46.6160774231],"type":"Point"}
}