{
  "type": "Feature",
  "properties": {
    "iso:country":"AT",
    "sg:address":"St. Veiter Str 158 c",
    "sg:city":"St. Veit",
    "sg:orig_category":"Architekten",
    "sg:phone":"+43 316 694505",
    "sg:postcode":"8046",
    "sg:province":"Steiermark",
    "wof:name":"Dreier Klaus Dipl-Ing & Dipl-Ing Bettina Dreier",
    "wof:placetype":"venue"
},
  "geometry": {"coordinates":[15.41065979,47.1242713928],"type":"Point"}
}