{
  "type": "Feature",
  "properties": {
    "addr:full":"Abteistr 23 Altm\u00fcnster Ober\u00f6sterreich 4813",
    "addr:housenumber":"23",
    "addr:postcode":"4813",
    "addr:street":"Abteistr;Oberoesterreich",
    "iso:country":"AT",
    "sg:address":"Abteistr 23",
    "sg:city":"Altm\u00fcnster",
    "sg:orig_category":"Industrievertretungen",
    "sg:phone":"+43 761288360",
    "sg:postcode":"4813",
    "sg:province":"Ober\u00f6sterreich",
    "wof:name":"Hufnagl Albert Industrie-Produkte",
    "wof:placetype":"venue"
},
  "geometry": {"coordinates":[13.7598171234,47.9023933411],"type":"Point"}
}