{
  "type": "Feature",
  "properties": {
    "addr:full":"Au\u00dferg 192 Jerzens Tirol 6474",
    "addr:housenumber":"192",
    "addr:postcode":"6474",
    "addr:street":"Jerzens Tirol",
    "iso:country":"AT",
    "sg:address":"Au\u00dferg 192",
    "sg:city":"Jerzens",
    "sg:orig_category":"Pensionen / Privatzimmer",
    "sg:phone":"+43 5414 873150",
    "sg:postcode":"6474",
    "sg:province":"Tirol",
    "sg:website":"haus-hubertus.com",
    "wof:name":"Haus Hubertus Fr\u00fchst\u00fcckspension - Schultes Rita",
    "wof:placetype":"venue"
},
  "geometry": {"coordinates":[10.7465543747,47.1491737366],"type":"Point"}
}