{
  "type": "Feature",
  "properties": {
    "addr:full":"Dullh\u00f6he 64 Seeboden K\u00e4rnten 9871",
    "addr:housenumber":"64",
    "addr:postcode":"9871",
    "addr:street":"Dullhoehe;Kaernten",
    "iso:country":"AT",
    "sg:address":"Dullh\u00f6he 64",
    "sg:city":"Seeboden",
    "sg:orig_category":"Pensionen / Privatzimmer",
    "sg:phone":"+43 4347 6281991",
    "sg:postcode":"9871",
    "sg:province":"K\u00e4rnten",
    "wof:name":"Fr\u00fchst\u00fcckspension Passler",
    "wof:placetype":"venue"
},
  "geometry": {"coordinates":[13.5192050934,46.8188858032],"type":"Point"}
}