{
  "type": "Feature",
  "properties": {
    "iso:country":"AT",
    "sg:address":"Nr 49",
    "sg:city":"Gro\u00df Siegharts",
    "sg:orig_category":"Tischlereien",
    "sg:phone":"+43 2847 2675",
    "sg:postcode":"3812",
    "sg:province":"Nieder\u00f6sterreich",
    "wof:name":"Bigl Adolf",
    "wof:placetype":"venue"
},
  "geometry": {"coordinates":[15.404999733,48.7899398804],"type":"Point"}
}