{
  "type": "Feature",
  "properties": {
    "addr:full":"Leonfeldner Str 2 Linz Ober\u00f6sterreich 4040",
    "addr:housenumber":"2",
    "addr:postcode":"4040",
    "iso:country":"AT",
    "sg:address":"Leonfeldner Str 2",
    "sg:city":"Linz",
    "sg:orig_category":"Textilreinigung",
    "sg:phone":"+43 732 731272",
    "sg:postcode":"4040",
    "sg:province":"Ober\u00f6sterreich",
    "wof:name":"Schwab Karl & Co PutzereibetriebsgesmbH",
    "wof:placetype":"venue"
},
  "geometry": {"coordinates":[14.283405304,48.3177185059],"type":"Point"}
}