{
  "type": "Feature",
  "properties": {
    "addr:full":"Oberdorf 6 Neustift im Stubaital Tirol 6167",
    "addr:housenumber":"6",
    "addr:postcode":"6167",
    "addr:street":"Oberdorf;Tirol",
    "iso:country":"AT",
    "sg:address":"Oberdorf 6",
    "sg:city":"Neustift im Stubaital",
    "sg:classifiers":[
        {
            "category":"Restaurant",
            "type":"Food & Drink"
        }
    ],
    "sg:phone":"+43 4352 263147",
    "sg:postcode":"6167",
    "sg:province":"Tirol",
    "wof:name":"Grillstube Pedevilla",
    "wof:placetype":"venue"
},
  "geometry": {"coordinates":[11.3041906357,47.1108207703],"type":"Point"}
}