{
  "type": "Feature",
  "properties": {
    "addr:full":"Osterndorf 105 Bad H\u00e4ring Tirol 6323",
    "addr:housenumber":"105",
    "addr:postcode":"6323",
    "addr:street":"Osterndorf;Tirol",
    "iso:country":"AT",
    "sg:address":"Osterndorf 105",
    "sg:city":"Bad H\u00e4ring",
    "sg:orig_category":"Pensionen / Privatzimmer",
    "sg:phone":"+43 5332 85064",
    "sg:postcode":"6323",
    "sg:province":"Tirol",
    "wof:name":"Pension Hechenleitner",
    "wof:placetype":"venue"
},
  "geometry": {"coordinates":[-88.67497253419999,43.9075889587],"type":"Point"}
}