{
  "type": "Feature",
  "properties": {
    "addr:full":"Oberdorf 4 Satteins Vorarlberg 6822",
    "addr:housenumber":"4",
    "addr:postcode":"6822",
    "addr:street":"Oberdorf",
    "iso:country":"AT",
    "sg:address":"Oberdorf 4",
    "sg:city":"Satteins",
    "sg:orig_category":"Non-Classified Establishments",
    "sg:phone":"+43 5524 8215",
    "sg:postcode":"6822",
    "sg:province":"Vorarlberg",
    "wof:name":"Pfarramt",
    "wof:placetype":"venue"
},
  "geometry": {"coordinates":[9.6721582413,47.2254943848],"type":"Point"}
}