{
  "type": "Feature",
  "properties": {
    "addr:full":"Reisperbachtalstr 8 Krems an der Donau Nieder\u00f6sterreich 3500",
    "addr:housenumber":"8",
    "addr:postcode":"3500",
    "addr:street":"Reisperbachtalstr",
    "iso:country":"AT",
    "sg:address":"Reisperbachtalstr 8",
    "sg:city":"Krems an der Donau",
    "sg:orig_category":"Rauchfangkehrer",
    "sg:phone":"+43 2732 832460",
    "sg:postcode":"3500",
    "sg:province":"Nieder\u00f6sterreich",
    "wof:name":"Landa Gerhard",
    "wof:placetype":"venue"
},
  "geometry": {"coordinates":[15.5780363083,48.4015731812],"type":"Point"}
}