{
  "type": "Feature",
  "properties": {
    "addr:full":"Ernst-Swatek-Str 10 Wolfsberg K\u00e4rnten 9400",
    "addr:housenumber":"10;kaernten",
    "addr:postcode":"9400",
    "addr:street":"Ernst-Swatek-Str",
    "iso:country":"AT",
    "sg:address":"Ernst-Swatek-Str 10",
    "sg:city":"Wolfsberg",
    "sg:orig_category":"Fahrschulen",
    "sg:phone":"+43 4352 28680",
    "sg:postcode":"9400",
    "sg:province":"K\u00e4rnten",
    "wof:name":"Schellander Martin Ing",
    "wof:placetype":"venue"
},
  "geometry": {"coordinates":[14.8400087357,46.8386116028],"type":"Point"}
}