{
  "type": "Feature",
  "properties": {
    "addr:full":"Bahnhofstr 6 Langenwang Steiermark 8665",
    "addr:housenumber":"6",
    "addr:postcode":"8665",
    "addr:street":"Bahnhofstr",
    "iso:country":"AT",
    "sg:address":"Bahnhofstr 6",
    "sg:city":"Langenwang",
    "sg:orig_category":"Eis / Erzeugung",
    "sg:phone":"+43 3854 6116",
    "sg:postcode":"8665",
    "sg:province":"Steiermark",
    "wof:name":"Pregel Austria GmbH",
    "wof:placetype":"venue"
},
  "geometry": {"coordinates":[15.6182594299,47.5680122375],"type":"Point"}
}