{
  "type": "Feature",
  "properties": {
    "addr:full":"M\u00fchlfeldg 35/1/2 Wiener Neudorf Nieder\u00f6sterreich 2351",
    "addr:housenumber":"35 / 1 / 2",
    "addr:postcode":"2351",
    "addr:street":"Muehlfeldg",
    "iso:country":"AT",
    "sg:address":"M\u00fchlfeldg 35/1/2",
    "sg:city":"Wiener Neudorf",
    "sg:orig_category":"Chemisch-Technische Produkte",
    "sg:phone":"+43 2236 65395",
    "sg:postcode":"2351",
    "sg:province":"Nieder\u00f6sterreich",
    "wof:name":"AUWA Chemie GmbH",
    "wof:placetype":"venue"
},
  "geometry": {"coordinates":[16.3183326721,48.0863113403],"type":"Point"}
}