{
  "type": "Feature",
  "properties": {
    "iso:country":"AT",
    "sg:address":"Hauptpl 1",
    "sg:city":"Horn",
    "sg:orig_category":"Waren Aller Art",
    "sg:phone":"+43 2982 30431",
    "sg:postcode":"3580",
    "sg:province":"Nieder\u00f6sterreich",
    "wof:name":"Ein Euro Shop",
    "wof:placetype":"venue"
},
  "geometry": {"coordinates":[15.6570301056,48.6636695862],"type":"Point"}
}