{
  "type": "Feature",
  "properties": {
    "addr:full":"Linzer Str 14 Enns Ober\u00f6sterreich 4470",
    "addr:housenumber":"14",
    "addr:postcode":"4470",
    "addr:street":"Linzer Str",
    "iso:country":"AT",
    "sg:address":"Linzer Str 14",
    "sg:city":"Enns",
    "sg:orig_category":"Drogerien",
    "sg:phone":"+43 7223 82659",
    "sg:postcode":"4470",
    "sg:province":"Ober\u00f6sterreich",
    "wof:name":"Pfeiffer Drogerie GmbH",
    "wof:placetype":"venue"
},
  "geometry": {"coordinates":[14.4779167175,48.2144813538],"type":"Point"}
}