{
  "type": "Feature",
  "properties": {
    "addr:full":"Sportweg 5 Moosburg K\u00e4rnten 9062",
    "addr:housenumber":"5",
    "addr:postcode":"9062",
    "addr:street":"Sportweg;Kaernten",
    "iso:country":"AT",
    "sg:address":"Sportweg 5",
    "sg:city":"Moosburg",
    "sg:orig_category":"Lebens- U Sozialberatung",
    "sg:phone":"+43 4342 7283600",
    "sg:postcode":"9062",
    "sg:province":"K\u00e4rnten",
    "wof:name":"Scheriau Karl Heinz Mag Dr",
    "wof:placetype":"venue"
},
  "geometry": {"coordinates":[14.17852211,46.6589202881],"type":"Point"}
}