{
  "type": "Feature",
  "properties": {
    "iso:country":"AT",
    "sg:address":"Donauturmstr 4",
    "sg:city":"Wien",
    "sg:classifiers":[
        {
            "category":"Restaurant",
            "type":"Food & Drink"
        }
    ],
    "sg:phone":"+43 4312 633574",
    "sg:postcode":"1220",
    "sg:province":"Wien",
    "wof:name":"Isola im Donaupark",
    "wof:placetype":"venue"
},
  "geometry": {"coordinates":[16.4097194672,48.2422218323],"type":"Point"}
}