{
  "type": "Feature",
  "properties": {
    "addr:full":"Hauptstr 38 Berg Nieder\u00f6sterreich 2413",
    "addr:housenumber":"38",
    "addr:postcode":"2413",
    "addr:street":"Hauptstr",
    "iso:country":"AT",
    "sg:address":"Hauptstr 38",
    "sg:city":"Berg",
    "sg:orig_category":"Banken U Sparkassen",
    "sg:phone":"+43 2145 2340",
    "sg:postcode":"2413",
    "sg:province":"Nieder\u00f6sterreich",
    "wof:name":"Raiffeisenbank Kittsee-Edelstal-Pama regGenmbH",
    "wof:placetype":"venue"
},
  "geometry": {"coordinates":[16.9871482849,48.0986595154],"type":"Point"}
}