{
  "type": "Feature",
  "properties": {
    "addr:full":"Industriestr 19 Zwettl Nieder\u00f6sterreich 3910",
    "addr:housenumber":"19",
    "addr:postcode":"3910",
    "addr:street":"Industriestr;Niederoesterreich",
    "iso:country":"AT",
    "sg:address":"Industriestr 19",
    "sg:city":"Zwettl",
    "sg:orig_category":"Lebensmittel / Einzelhandel",
    "sg:phone":"+43 2822 52303",
    "sg:postcode":"3910",
    "sg:province":"Nieder\u00f6sterreich",
    "wof:name":"Hofer KG",
    "wof:placetype":"venue"
},
  "geometry": {"coordinates":[15.190779686,48.6002082825],"type":"Point"}
}