{
  "type": "Feature",
  "properties": {
    "addr:full":"Treietsstr. 19  Klaus-Weiler Vorarlberg 6833",
    "addr:housenumber":"19",
    "addr:postcode":"6833",
    "addr:street":"Treietsstr.",
    "iso:country":"AT",
    "sg:address":"Treietsstr. 19 ",
    "sg:city":"Klaus-Weiler",
    "sg:classifiers":[
        {
            "category":"Manufacturing",
            "subcategory":"Metals",
            "type":"Manufacturing & Wholesale Goods"
        }
    ],
    "sg:phone":"+43 4355 2362420",
    "sg:postcode":"6833",
    "sg:province":"Vorarlberg",
    "sg:tags":[
        "metallurgy",
        "metalworking"
    ],
    "wof:name":"JOSEF FRICK OHG",
    "wof:placetype":"venue"
},
  "geometry": {"coordinates":[9.6449737549,47.30493927],"type":"Point"}
}