{
  "type": "Feature",
  "properties": {
    "addr:full":"Benediktinerpl 1 Klagenfurt K\u00e4rnten 9020",
    "addr:housenumber":"1",
    "addr:postcode":"9020",
    "addr:street":"Benediktinerpl;Kaernten",
    "iso:country":"AT",
    "sg:address":"Benediktinerpl 1",
    "sg:city":"Klagenfurt",
    "sg:orig_category":"Hauptschulen",
    "sg:phone":"+43 463 5375464",
    "sg:postcode":"9020",
    "sg:province":"K\u00e4rnten",
    "wof:name":"Hauptschule 7 - Benediktinerschule",
    "wof:placetype":"venue"
},
  "geometry": {"coordinates":[14.3054599762,46.6228256226],"type":"Point"}
}