{
  "type": "Feature",
  "properties": {
    "addr:full":"Gro\u00dfe Neug 44 Wien Wien 1040",
    "addr:housenumber":"44",
    "addr:postcode":"1040",
    "iso:country":"AT",
    "sg:address":"Gro\u00dfe Neug 44",
    "sg:city":"Wien",
    "sg:orig_category":"Filmproduktionen",
    "sg:phone":"+43 1 5817896",
    "sg:postcode":"1040",
    "sg:province":"Wien",
    "wof:name":"Extrafilm Arbeitsgemeinschaft Film & Video GesmbH",
    "wof:placetype":"venue"
},
  "geometry": {"coordinates":[16.3671455383,48.1940345764],"type":"Point"}
}