{
  "type": "Feature",
  "properties": {
    "addr:full":"Linzer Str 94 Gablitz Nieder\u00f6sterreich 3003",
    "addr:housenumber":"94",
    "addr:postcode":"3003",
    "addr:street":"Linzer Str",
    "iso:country":"AT",
    "sg:address":"Linzer Str 94",
    "sg:city":"Gablitz",
    "sg:orig_category":"Architekten",
    "sg:phone":"+43 2231 628640",
    "sg:postcode":"3003",
    "sg:province":"Nieder\u00f6sterreich",
    "wof:name":"Flei\u00df Peter Dipl-Ing",
    "wof:placetype":"venue"
},
  "geometry": {"coordinates":[16.151714325,48.2300109863],"type":"Point"}
}