{
  "type": "Feature",
  "properties": {
    "addr:full":"Nr 175 St. Stefan ob Stainz Steiermark 8511",
    "addr:postcode":"8511",
    "addr:street":"Nr 175",
    "iso:country":"AT",
    "sg:address":"Nr 175",
    "sg:city":"St. Stefan ob Stainz",
    "sg:orig_category":"Autohandel",
    "sg:phone":"+43 4334 63816110",
    "sg:postcode":"8511",
    "sg:province":"Steiermark",
    "wof:name":"Jeschelnig GesmbH - Fiat-Lancia-Alfa Romeo Vertragsh\u00e4ndler",
    "wof:placetype":"venue"
},
  "geometry": {"coordinates":[15.2549381256,46.9294662476],"type":"Point"}
}