{
  "type": "Feature",
  "properties": {
    "iso:country":"AT",
    "sg:address":"Hauptstr 9",
    "sg:city":"Wundschuh",
    "sg:orig_category":"Feuerwehren",
    "sg:phone":"+43 3135 56242",
    "sg:postcode":"8142",
    "sg:province":"Steiermark",
    "wof:name":"Freiwillige Feuerwehr Wundschuh",
    "wof:placetype":"venue"
},
  "geometry": {"coordinates":[15.4512519836,46.9280395508],"type":"Point"}
}