{
  "type": "Feature",
  "properties": {
    "addr:full":"Kirchstr 9a Bregenz Vorarlberg 6900",
    "addr:housenumber":"9a",
    "addr:postcode":"6900",
    "addr:street":"Kirchstr",
    "iso:country":"AT",
    "sg:address":"Kirchstr 9a",
    "sg:city":"Bregenz",
    "sg:orig_category":"Steuerberatung",
    "sg:phone":"+43 5574 462520",
    "sg:postcode":"6900",
    "sg:province":"Vorarlberg",
    "sg:website":"kanzlei-lang.at",
    "wof:name":"Lang Christoph Mag",
    "wof:placetype":"venue"
},
  "geometry": {"coordinates":[9.7471618652,47.5017471313],"type":"Point"}
}