{
  "type": "Feature",
  "properties": {
    "addr:full":"Billrothstr 2 Wien Wien 1190",
    "addr:housenumber":"2",
    "addr:postcode":"1190",
    "addr:street":"Billrothstr",
    "iso:country":"AT",
    "sg:address":"Billrothstr 2",
    "sg:city":"Wien",
    "sg:orig_category":"Liegenschaften / Vermietung",
    "sg:phone":"+43 4313 6080",
    "sg:postcode":"1190",
    "sg:province":"Wien",
    "wof:name":"Mischek Liegenschaftsbeteiligungs GmbH",
    "wof:placetype":"venue"
},
  "geometry": {"coordinates":[16.351940155,48.23412323],"type":"Point"}
}