{
  "type": "Feature",
  "properties": {
    "iso:country":"AT",
    "sg:address":"Primoschg 3",
    "sg:city":"Klagenfurt",
    "sg:orig_category":"Dolmetscher",
    "sg:phone":"+43 4346 33875444",
    "sg:postcode":"9020",
    "sg:province":"K\u00e4rnten",
    "wof:name":"Schatz Margot Mag",
    "wof:placetype":"venue"
},
  "geometry": {"coordinates":[14.3291044235,46.6105499268],"type":"Point"}
}