{
  "type": "Feature",
  "properties": {
    "iso:country":"AT",
    "sg:address":"Gottlieb-August-Wimmer-Pl 1",
    "sg:city":"Obersch\u00fctzen",
    "sg:orig_category":"Friseure U Frisiersalons",
    "sg:phone":"+43 4333 5361355",
    "sg:postcode":"7432",
    "sg:province":"Burgenland",
    "wof:name":"Friseur Salon Andrea",
    "wof:placetype":"venue"
},
  "geometry": {"coordinates":[19.1364707947,51.9225082397],"type":"Point"}
}