{
  "type": "Feature",
  "properties": {
    "addr:full":"Brunnbergstr 34 Seewalchen am Attersee Ober\u00f6sterreich 4863",
    "addr:housenumber":"34",
    "addr:postcode":"4863",
    "addr:street":"Brunnbergstr",
    "iso:country":"AT",
    "sg:address":"Brunnbergstr 34",
    "sg:city":"Seewalchen am Attersee",
    "sg:orig_category":"Druckereien",
    "sg:phone":"+43 4376 628454",
    "sg:postcode":"4863",
    "sg:province":"Ober\u00f6sterreich",
    "wof:name":"Katterbauer Helmut",
    "wof:placetype":"venue"
},
  "geometry": {"coordinates":[13.5878629684,47.969707489],"type":"Point"}
}