{
  "type": "Feature",
  "properties": {
    "addr:full":"Dr.-Karl-Widdmann-Str 4 Weiz Steiermark 8160",
    "addr:housenumber":"4",
    "addr:postcode":"8160",
    "addr:street":"Dr.-Karl-Widdmann-Str",
    "iso:country":"AT",
    "sg:address":"Dr.-Karl-Widdmann-Str 4",
    "sg:city":"Weiz",
    "sg:orig_category":"Bierlokale-Pubs",
    "sg:phone":"+43 4331 723360",
    "sg:postcode":"8160",
    "sg:province":"Steiermark",
    "wof:name":"Billard The Pub",
    "wof:placetype":"venue"
},
  "geometry": {"coordinates":[15.6244716644,47.2196731567],"type":"Point"}
}