{
  "type": "Feature",
  "properties": {
    "addr:full":"Prager Str 3 Freistadt Ober\u00f6sterreich 4240",
    "addr:housenumber":"3",
    "addr:postcode":"4240",
    "addr:street":"Str",
    "iso:country":"AT",
    "sg:address":"Prager Str 3",
    "sg:city":"Freistadt",
    "sg:orig_category":"Tankstellen",
    "sg:phone":"+43 7942 754490",
    "sg:postcode":"4240",
    "sg:province":"Ober\u00f6sterreich",
    "wof:name":"BP Austria Marketing GmbH",
    "wof:placetype":"venue"
},
  "geometry": {"coordinates":[14.5028505325,48.5147094727],"type":"Point"}
}