{
  "type": "Feature",
  "properties": {
    "iso:country":"AT",
    "sg:address":"Alpenstr 8",
    "sg:city":"Anif",
    "sg:orig_category":"Fliesen U Platten",
    "sg:phone":"+43 4362 4674974",
    "sg:postcode":"5081",
    "sg:province":"Salzburg",
    "wof:name":"HOLZKNECHT Disayn GesmbH",
    "wof:placetype":"venue"
},
  "geometry": {"coordinates":[13.0677919388,47.7485656738],"type":"Point"}
}