{
  "type": "Feature",
  "properties": {
    "addr:full":"Wagramer Str 21 Wien Wien 1220",
    "addr:postcode":"1220",
    "addr:street":"Str 21",
    "iso:country":"AT",
    "sg:address":"Wagramer Str 21",
    "sg:city":"Wien",
    "sg:classifiers":[
        {
            "category":"Travel",
            "subcategory":"Hotels & Motels",
            "type":"Entertainment"
        }
    ],
    "sg:phone":"+43 1 260200",
    "sg:postcode":"1220",
    "sg:province":"Wien",
    "sg:website":"vienna.crowneplaza.com",
    "wof:name":"Crowne Plaza Vienna IZD Hotel Betriebs GmbH",
    "wof:placetype":"venue"
},
  "geometry": {"coordinates":[16.4216938019,48.235206604],"type":"Point"}
}