{
  "type": "Feature",
  "properties": {
    "addr:full":"Gartenstr 30 Eggendorf Nieder\u00f6sterreich 2492",
    "addr:housenumber":"30",
    "addr:postcode":"2492",
    "addr:street":"Gartenstr",
    "iso:country":"AT",
    "sg:address":"Gartenstr 30",
    "sg:city":"Eggendorf",
    "sg:orig_category":"Zimmereien",
    "sg:phone":"+43 2622 74680",
    "sg:postcode":"2492",
    "sg:province":"Nieder\u00f6sterreich",
    "wof:name":"Jaitz Thomas",
    "wof:placetype":"venue"
},
  "geometry": {"coordinates":[16.3359661102,47.8572120667],"type":"Point"}
}