{
  "type": "Feature",
  "properties": {
    "addr:full":"Bahnhofstr 34-38 Telfs Tirol 6410",
    "addr:postcode":"34-38;6410",
    "addr:street":"Bahnhofstr;Tirol",
    "iso:country":"AT",
    "sg:address":"Bahnhofstr 34-38",
    "sg:city":"Telfs",
    "sg:orig_category":"Reiseveranstalter",
    "sg:phone":"+43 4352 62622260",
    "sg:postcode":"6410",
    "sg:province":"Tirol",
    "sg:website":"dietrich-touristik.at",
    "wof:name":"Dietrich Touristik GesmbH - Omnibusbetrieb u Reiseveranstalter",
    "wof:placetype":"venue"
},
  "geometry": {"coordinates":[11.0731925964,47.3031425476],"type":"Point"}
}