{
  "type": "Feature",
  "properties": {
    "addr:full":"Lindenstrasse 4 Steindorf K\u00e4rnten 9552",
    "addr:housenumber":"4",
    "addr:postcode":"9552",
    "addr:street":"Lindenstrasse;Kaernten",
    "iso:country":"AT",
    "sg:address":"Lindenstrasse 4",
    "sg:city":"Steindorf",
    "sg:classifiers":[
        {
            "category":"Professional",
            "subcategory":"Detective & Security Services",
            "type":"Services"
        }
    ],
    "sg:phone":"+43 4243 2480",
    "sg:postcode":"9552",
    "sg:province":"K\u00e4rnten",
    "sg:tags":[
        "access",
        "control",
        "ac",
        "system"
    ],
    "sg:website":"alpina.at",
    "wof:name":"Alpina Sicherheitssysteme GmbH",
    "wof:placetype":"venue"
},
  "geometry": {"coordinates":[14.0101804733,46.6985244751],"type":"Point"}
}