{
  "type": "Feature",
  "properties": {
    "iso:country":"AT",
    "sg:address":"Grafenbergweg 2",
    "sg:city":"Wagrain",
    "sg:orig_category":"Pensionen / Privatzimmer",
    "sg:phone":"+43 4364 138615",
    "sg:postcode":"5602",
    "sg:province":"Salzburg",
    "wof:name":"Haus Schartner",
    "wof:placetype":"venue"
},
  "geometry": {"coordinates":[13.2942333221,47.3334274292],"type":"Point"}
}