{
  "type": "Feature",
  "properties": {
    "addr:full":"Grazer Str 12 Kapfenberg Steiermark 8605",
    "addr:postcode":"8605",
    "addr:street":"Str 12",
    "iso:country":"AT",
    "sg:address":"Grazer Str 12",
    "sg:city":"Kapfenberg",
    "sg:classifiers":[
        {
            "category":"Shopping",
            "subcategory":"Thrift Store",
            "type":"Retail Goods"
        }
    ],
    "sg:phone":"+43 4338 6227079",
    "sg:postcode":"8605",
    "sg:province":"Steiermark",
    "sg:tags":[
        "second-hand-shops"
    ],
    "wof:name":"Caritas Di\u00f6zese Graz Seckau",
    "wof:placetype":"venue"
},
  "geometry": {"coordinates":[15.2879219055,47.4384346008],"type":"Point"}
}