{
  "type": "Feature",
  "properties": {
    "addr:full":"Rosensteingasse 14 Wien Wien 1170",
    "addr:housenumber":"14",
    "addr:postcode":"1170",
    "addr:street":"Rosensteingasse",
    "iso:country":"AT",
    "sg:address":"Rosensteingasse 14",
    "sg:city":"Wien",
    "sg:classifiers":[
        {
            "category":"Building & Trades",
            "subcategory":"Electrical",
            "type":"Services"
        }
    ],
    "sg:phone":"+43 1 4862448",
    "sg:postcode":"1170",
    "sg:province":"Wien",
    "sg:tags":[
        "work",
        "installation"
    ],
    "wof:name":"Gerhard Sokolt KEG",
    "wof:placetype":"venue"
},
  "geometry": {"coordinates":[16.3257465363,48.2161064148],"type":"Point"}
}