{
  "type": "Feature",
  "properties": {
    "addr:full":"Hochwasserg 2 Wien Wien 1230",
    "addr:housenumber":"2",
    "addr:postcode":"1230",
    "addr:street":"Hochwasserg",
    "iso:country":"AT",
    "sg:address":"Hochwasserg 2",
    "sg:city":"Wien",
    "sg:orig_category":"Elektroinstallationsunternehmen",
    "sg:phone":"+43 1 61633500",
    "sg:postcode":"1230",
    "sg:province":"Wien",
    "wof:name":"Eltech Elektroinstallationen GesmbH",
    "wof:placetype":"venue"
},
  "geometry": {"coordinates":[16.36028862,48.1474952698],"type":"Point"}
}