{
  "type": "Feature",
  "properties": {
    "iso:country":"AT",
    "sg:address":"Molkereistr. 5",
    "sg:city":"Aschbach Markt",
    "sg:classifiers":[
        {
            "category":"Food & Beverages",
            "subcategory":"Dairy",
            "type":"Retail Goods"
        }
    ],
    "sg:phone":"+43 4374 76773110",
    "sg:postcode":"3361",
    "sg:province":"Nieder\u00f6sterreich",
    "sg:tags":[
        "product"
    ],
    "wof:name":"BERGLAND MILCH REG.GEN.MBH",
    "wof:placetype":"venue"
},
  "geometry": {"coordinates":[14.7597398758,48.071144104],"type":"Point"}
}