{
  "type": "Feature",
  "properties": {
    "iso:country":"AT",
    "sg:address":"Fluchtg 9",
    "sg:city":"Wien",
    "sg:orig_category":"Psychotherapie",
    "sg:phone":"+43 1 3176585",
    "sg:postcode":"1090",
    "sg:province":"Wien",
    "wof:name":"Strausz Leonora",
    "wof:placetype":"venue"
},
  "geometry": {"coordinates":[16.3529949188,48.2243919373],"type":"Point"}
}