{
  "type": "Feature",
  "properties": {
    "addr:full":"Grinzinger Str 5 Wien Wien 1190",
    "addr:housenumber":"5",
    "addr:postcode":"1190",
    "addr:street":"Str",
    "iso:country":"AT",
    "sg:address":"Grinzinger Str 5",
    "sg:city":"Wien",
    "sg:orig_category":"Architekten",
    "sg:phone":"+43 4313 2877660",
    "sg:postcode":"1190",
    "sg:province":"Wien",
    "wof:name":"Schenk Sebastian Arch Dipl-Ing",
    "wof:placetype":"venue"
},
  "geometry": {"coordinates":[16.3427906036,48.2564201355],"type":"Point"}
}