{
  "type": "Feature",
  "properties": {
    "addr:full":"Proboj 24 Miklauzhof K\u00e4rnten 9133",
    "addr:housenumber":"24;9133",
    "addr:street":"Proboj;Kaernten",
    "iso:country":"AT",
    "sg:address":"Proboj 24",
    "sg:city":"Miklauzhof",
    "sg:orig_category":"Tischlereien",
    "sg:phone":"+43 4237 21800",
    "sg:postcode":"9133",
    "sg:province":"K\u00e4rnten",
    "wof:name":"Lobnig Valentin",
    "wof:placetype":"venue"
},
  "geometry": {"coordinates":[14.6061134338,46.5438575745],"type":"Point"}
}