{
  "type": "Feature",
  "properties": {
    "addr:full":"Klagenfurter Str 3 Feldkirchen in K\u00e4rnten K\u00e4rnten 9560",
    "addr:housenumber":"3",
    "addr:postcode":"9560",
    "addr:street":"Str;Kaernten",
    "iso:country":"AT",
    "sg:address":"Klagenfurter Str 3",
    "sg:city":"Feldkirchen in K\u00e4rnten",
    "sg:orig_category":"\u00c3\u201erzte / F Allgemeinmedizin",
    "sg:phone":"+43 4342 7620910",
    "sg:postcode":"9560",
    "sg:province":"K\u00e4rnten",
    "wof:name":"Eysselt Dieter Dr",
    "wof:placetype":"venue"
},
  "geometry": {"coordinates":[14.0959806442,46.7216300964],"type":"Point"}
}