{
  "type": "Feature",
  "properties": {
    "addr:full":"Hauptstrasse 47 Strasshof an der Nordbahn Nieder\u00f6sterreich 2231",
    "addr:housenumber":"47",
    "addr:postcode":"2231",
    "addr:street":"Hauptstrasse",
    "iso:country":"AT",
    "sg:address":"Hauptstrasse 47",
    "sg:city":"Strasshof an der Nordbahn",
    "sg:classifiers":[
        {
            "category":"Home & Garden",
            "subcategory":"Building Materials",
            "type":"Retail Goods"
        }
    ],
    "sg:phone":"+43 2287 4859",
    "sg:postcode":"2231",
    "sg:province":"Nieder\u00f6sterreich",
    "sg:tags":[
        "tile",
        "ceramic"
    ],
    "wof:name":"Johann Voglhuber",
    "wof:placetype":"venue"
},
  "geometry": {"coordinates":[16.6106395721,48.3223457336],"type":"Point"}
}