{
  "type": "Feature",
  "properties": {
    "addr:full":"Hauptstr 69 Fohnsdorf Steiermark 8753",
    "addr:housenumber":"69",
    "addr:postcode":"8753",
    "addr:street":"Hauptstr",
    "iso:country":"AT",
    "sg:address":"Hauptstr 69",
    "sg:city":"Fohnsdorf",
    "sg:orig_category":"Weiterbildungsinstitute M Allg U Berufl Bildungsangebot",
    "sg:phone":"+43 3573 60600",
    "sg:postcode":"8753",
    "sg:province":"Steiermark",
    "wof:name":"BMS Bildungs- und Managementservice GmbH",
    "wof:placetype":"venue"
},
  "geometry": {"coordinates":[14.6657485962,47.2054748535],"type":"Point"}
}