{
  "type": "Feature",
  "properties": {
    "addr:full":"Shuttleworthstr 77 Wien Wien 1210",
    "addr:housenumber":"77",
    "addr:postcode":"1210",
    "addr:street":"Shuttleworthstr",
    "iso:country":"AT",
    "sg:address":"Shuttleworthstr 77",
    "sg:city":"Wien",
    "sg:orig_category":"Autoelektrik U -Ersatzteile",
    "sg:phone":"+43 4312 9212600",
    "sg:postcode":"1210",
    "sg:province":"Wien",
    "wof:name":"Svoboda Franz",
    "wof:placetype":"venue"
},
  "geometry": {"coordinates":[16.4157772064,48.2704772949],"type":"Point"}
}