{
  "type": "Feature",
  "properties": {
    "addr:full":"Nr 9 Z\u00f6bern Nieder\u00f6sterreich 2871",
    "addr:housenumber":"2871",
    "addr:street":"Nr;Zoebern Niederoesterreich",
    "iso:country":"AT",
    "sg:address":"Nr 9",
    "sg:city":"Z\u00f6bern",
    "sg:orig_category":"Ingenieurkonsulenten / Zivilingenieure",
    "sg:phone":"+43 2642 8495",
    "sg:postcode":"2871",
    "sg:province":"Nieder\u00f6sterreich",
    "wof:name":"Reithofer Anton P Dipl-Ing",
    "wof:placetype":"venue"
},
  "geometry": {"coordinates":[16.1311836243,47.5121498108],"type":"Point"}
}