{
  "type": "Feature",
  "properties": {
    "addr:full":"Lobminger Str 20 Knittelfeld Steiermark 8720",
    "addr:housenumber":"20",
    "addr:postcode":"8720",
    "addr:street":"Str",
    "iso:country":"AT",
    "sg:address":"Lobminger Str 20",
    "sg:city":"Knittelfeld",
    "sg:orig_category":"Friseure U Frisiersalons",
    "sg:phone":"+43 4335 1283145",
    "sg:postcode":"8720",
    "sg:province":"Steiermark",
    "wof:name":"Grasslober Annemarie",
    "wof:placetype":"venue"
},
  "geometry": {"coordinates":[14.8310775757,47.2100524902],"type":"Point"}
}