{
  "type": "Feature",
  "properties": {
    "addr:full":"Steing 9 Salzburg Salzburg 5020",
    "addr:housenumber":"9",
    "addr:postcode":"5020",
    "addr:street":"Steing;Salzburg",
    "iso:country":"AT",
    "sg:address":"Steing 9",
    "sg:city":"Salzburg",
    "sg:orig_category":"Psychotherapie",
    "sg:phone":"+43 662 8831725",
    "sg:postcode":"5020",
    "sg:province":"Salzburg",
    "wof:name":"Schacht Christian Dr phil",
    "wof:placetype":"venue"
},
  "geometry": {"coordinates":[13.0456695557,47.801448822],"type":"Point"}
}