{
  "type": "Feature",
  "properties": {
    "addr:full":"Stubenring 16 Wien Wien 1010",
    "addr:housenumber":"16",
    "addr:postcode":"1010",
    "addr:street":"Stubenring",
    "iso:country":"AT",
    "sg:address":"Stubenring 16",
    "sg:city":"Wien",
    "sg:orig_category":"Puppen",
    "sg:phone":"+43 4366 43565694",
    "sg:postcode":"1010",
    "sg:province":"Wien",
    "sg:website":"puppendoktor.at",
    "wof:name":"Der Puppendoktor Karin Haider",
    "wof:placetype":"venue"
},
  "geometry": {"coordinates":[16.381565094,48.208656311],"type":"Point"}
}