{
  "type": "Feature",
  "properties": {
    "addr:full":"Goldgeben 14 Hausleiten Nieder\u00f6sterreich 3464",
    "addr:housenumber":"14",
    "addr:postcode":"3464",
    "addr:street":"Goldgeben",
    "iso:country":"AT",
    "sg:address":"Goldgeben 14",
    "sg:city":"Hausleiten",
    "sg:classifiers":[
        {
            "category":"Home & Garden",
            "subcategory":"Hardware",
            "type":"Retail Goods"
        }
    ],
    "sg:phone":"+43 2265 7223",
    "sg:postcode":"3464",
    "sg:province":"Nieder\u00f6sterreich",
    "sg:tags":[
        "agricultural",
        "implement"
    ],
    "wof:name":"Franz Vogl",
    "wof:placetype":"venue"
},
  "geometry": {"coordinates":[16.1025238037,48.393989563],"type":"Point"}
}