{
  "type": "Feature",
  "properties": {
    "addr:full":"Nelkeng 1/2 Wien Wien 1060",
    "addr:housenumber":"1 / 2",
    "addr:postcode":"1060",
    "addr:street":"Nelkeng",
    "iso:country":"AT",
    "sg:address":"Nelkeng 1/2",
    "sg:city":"Wien",
    "sg:classifiers":[
        {
            "category":"Utilities",
            "subcategory":"Refuse",
            "type":"Services"
        }
    ],
    "sg:phone":"+43 1 5856452",
    "sg:postcode":"1060",
    "sg:province":"Wien",
    "sg:tags":[
        "catering"
    ],
    "wof:name":"Esswarenfaktorei Inh Walther Gelmini",
    "wof:placetype":"venue"
},
  "geometry": {"coordinates":[16.3521728516,48.1981735229],"type":"Point"}
}