{
  "type": "Feature",
  "properties": {
    "iso:country":"AT",
    "sg:address":"Hohenegg 22",
    "sg:city":"St. Marein",
    "sg:classifiers":[
        {
            "category":"Ice Cream",
            "type":"Food & Drink"
        }
    ],
    "sg:phone":"+43 3133 38075",
    "sg:postcode":"8323",
    "sg:province":"Steiermark",
    "sg:tags":[
        "seed",
        "oil",
        "pumpkin"
    ],
    "sg:website":"greengold.net",
    "wof:name":"GREENGOLD Kern\u00f6l Handels GmbH",
    "wof:placetype":"venue"
},
  "geometry": {"coordinates":[15.6933031082,46.994140625],"type":"Point"}
}