{
  "type": "Feature",
  "properties": {
    "addr:full":"Sandberg 5 Altenfelden Ober\u00f6sterreich 4121",
    "addr:housenumber":"5",
    "addr:postcode":"4121",
    "addr:street":"Sandberg",
    "iso:country":"AT",
    "sg:address":"Sandberg 5",
    "sg:city":"Altenfelden",
    "sg:orig_category":"Autohandel",
    "sg:phone":"+43 7282 66060",
    "sg:postcode":"4121",
    "sg:province":"Ober\u00f6sterreich",
    "wof:name":"J\u00e4ger Josef Ing",
    "wof:placetype":"venue"
},
  "geometry": {"coordinates":[13.9712572098,48.4896202087],"type":"Point"}
}