{
  "type": "Feature",
  "properties": {
    "addr:full":"Marktpl 2 St. Peter in der Au Nieder\u00f6sterreich 3352",
    "addr:housenumber":"2",
    "addr:postcode":"3352",
    "addr:street":"Marktpl",
    "iso:country":"AT",
    "sg:address":"Marktpl 2",
    "sg:city":"St. Peter in der Au",
    "sg:orig_category":"Lebensmittel / Einzelhandel",
    "sg:phone":"+43 7477 44788",
    "sg:postcode":"3352",
    "sg:province":"Nieder\u00f6sterreich",
    "wof:name":"Spar-Markt Ralph Krondorfer",
    "wof:placetype":"venue"
},
  "geometry": {"coordinates":[14.623459816,48.0446891785],"type":"Point"}
}