{
  "type": "Feature",
  "properties": {
    "addr:full":"Heigerleinstr 36-40 Wien Wien 1160",
    "addr:postcode":"36-40;1160",
    "iso:country":"AT",
    "sg:address":"Heigerleinstr 36-40",
    "sg:city":"Wien",
    "sg:orig_category":"Reproanstalten",
    "sg:phone":"+43 1 488870",
    "sg:postcode":"1160",
    "sg:province":"Wien",
    "wof:name":"GRAFO ZeitschriftendruckgesmbH",
    "wof:placetype":"venue"
},
  "geometry": {"coordinates":[16.3118343353,48.2176017761],"type":"Point"}
}