{
  "type": "Feature",
  "properties": {
    "addr:full":"Wiener Str 1 Friesach K\u00e4rnten 9360",
    "addr:postcode":"9360",
    "iso:country":"AT",
    "sg:address":"Wiener Str 1",
    "sg:city":"Friesach",
    "sg:orig_category":"Lebensmittel / Einzelhandel",
    "sg:phone":"+43 4268 2390",
    "sg:postcode":"9360",
    "sg:province":"K\u00e4rnten",
    "wof:name":"Spar-Markt Inh Kurt Berger",
    "wof:placetype":"venue"
},
  "geometry": {"coordinates":[14.4059276581,46.9508171082],"type":"Point"}
}