{
  "type": "Feature",
  "properties": {
    "addr:full":"Bernsteinstr 12 Hohenau an der March Nieder\u00f6sterreich 2273",
    "addr:housenumber":"12",
    "addr:postcode":"2273",
    "addr:street":"Bernsteinstr",
    "iso:country":"AT",
    "sg:address":"Bernsteinstr 12",
    "sg:city":"Hohenau an der March",
    "sg:orig_category":"Autoreparatur",
    "sg:phone":"+43 2535 34820",
    "sg:postcode":"2273",
    "sg:province":"Nieder\u00f6sterreich",
    "wof:name":"Nossian Gerhard",
    "wof:placetype":"venue"
},
  "geometry": {"coordinates":[16.8980903625,48.6007881165],"type":"Point"}
}