{
  "type": "Feature",
  "properties": {
    "addr:full":"Josef-Hei\u00dfl-Str 26 Leoben Steiermark 8700",
    "addr:housenumber":"26",
    "addr:postcode":"8700",
    "addr:street":"Josef-Heissl-Str",
    "iso:country":"AT",
    "sg:address":"Josef-Hei\u00dfl-Str 26",
    "sg:city":"Leoben",
    "sg:classifiers":[
        {
            "category":"Restaurant",
            "type":"Food & Drink"
        }
    ],
    "sg:phone":"+43 3842 27890",
    "sg:postcode":"8700",
    "sg:province":"Steiermark",
    "wof:name":"Hallenbadrestaurant Pracher",
    "wof:placetype":"venue"
},
  "geometry": {"coordinates":[15.0921401978,47.3697433472],"type":"Point"}
}