{
  "type": "Feature",
  "properties": {
    "iso:country":"AT",
    "sg:address":"Lumplgraben 25",
    "sg:city":"Gro\u00dframing",
    "sg:classifiers":[
        {
            "category":"Professional",
            "type":"Services"
        }
    ],
    "sg:phone":"+43 7254 8219",
    "sg:postcode":"4463",
    "sg:province":"Ober\u00f6sterreich",
    "sg:tags":[
        "transport"
    ],
    "wof:name":"Gerhard Aschauer",
    "wof:placetype":"venue"
},
  "geometry": {"coordinates":[14.5318183899,47.8597755432],"type":"Point"}
}