{
  "type": "Feature",
  "properties": {
    "iso:country":"AT",
    "sg:address":"Hegelg 13",
    "sg:city":"Wien",
    "sg:orig_category":"Immobilienverwaltungen",
    "sg:phone":"+43 1 51280010",
    "sg:postcode":"1010",
    "sg:province":"Wien",
    "wof:name":"Petri Gustav & Co GesmbH",
    "wof:placetype":"venue"
},
  "geometry": {"coordinates":[16.3750076294,48.2029800415],"type":"Point"}
}