{
  "type": "Feature",
  "properties": {
    "addr:full":"Nr 5 Oftering Ober\u00f6sterreich 4064",
    "addr:postcode":"4064",
    "addr:street":"Nr;Oberoesterreich",
    "iso:country":"AT",
    "sg:address":"Nr 5",
    "sg:city":"Oftering",
    "sg:orig_category":"Fleischhauereien",
    "sg:phone":"+43 7221 63407",
    "sg:postcode":"4064",
    "sg:province":"Ober\u00f6sterreich",
    "wof:name":"Netherer OHG",
    "wof:placetype":"venue"
},
  "geometry": {"coordinates":[14.1337490082,48.2345199585],"type":"Point"}
}