{
  "type": "Feature",
  "properties": {
    "addr:full":"Lindgrabeng 8 Wien Wien 1230",
    "addr:housenumber":"8",
    "addr:postcode":"1230",
    "addr:street":"Lindgrabeng",
    "iso:country":"AT",
    "sg:address":"Lindgrabeng 8",
    "sg:city":"Wien",
    "sg:classifiers":[
        {
            "category":"Personal",
            "subcategory":"Sauna",
            "type":"Services"
        }
    ],
    "sg:phone":"+43 1 8883291",
    "sg:postcode":"1230",
    "sg:province":"Wien",
    "sg:tags":[
        "u",
        "dampfbad"
    ],
    "wof:name":"Sauna Herricht",
    "wof:placetype":"venue"
},
  "geometry": {"coordinates":[16.2595081329,48.1534194946],"type":"Point"}
}