{
  "type": "Feature",
  "properties": {
    "addr:full":"Testarellog 24 Wien Wien 1130",
    "addr:housenumber":"24",
    "addr:postcode":"1130",
    "addr:street":"Testarellog",
    "iso:country":"AT",
    "sg:address":"Testarellog 24",
    "sg:city":"Wien",
    "sg:orig_category":"Transportunternehmen",
    "sg:phone":"+43 1 87769710",
    "sg:postcode":"1130",
    "sg:province":"Wien",
    "wof:name":"Mitsui OSK Lines GesmbH",
    "wof:placetype":"venue"
},
  "geometry": {"coordinates":[16.2738895416,48.1909217834],"type":"Point"}
}