{
  "type": "Feature",
  "properties": {
    "iso:country":"AT",
    "sg:address":"Nr 162",
    "sg:city":"Sigharting",
    "sg:orig_category":"Tischlereien",
    "sg:phone":"+43 7766 31870",
    "sg:postcode":"4771",
    "sg:province":"Ober\u00f6sterreich",
    "wof:name":"Kieslinger Hermann GmbH & Co KG",
    "wof:placetype":"venue"
},
  "geometry": {"coordinates":[13.5986776352,48.3950500488],"type":"Point"}
}