{
  "type": "Feature",
  "properties": {
    "iso:country":"AT",
    "sg:address":"Platz 66",
    "sg:city":"Mellau",
    "sg:classifiers":[
        {
            "category":"Travel",
            "subcategory":"Hotels & Motels",
            "type":"Entertainment"
        }
    ],
    "sg:phone":"+43 4355 182207",
    "sg:postcode":"6881",
    "sg:province":"Vorarlberg",
    "wof:name":"Appartementhotel B\u00e4ren",
    "wof:placetype":"venue"
},
  "geometry": {"coordinates":[9.881570816,47.3503112793],"type":"Point"}
}