{
  "type": "Feature",
  "properties": {
    "addr:full":"Zirkusgasse 40 Wien Wien 1020",
    "addr:housenumber":"40",
    "addr:postcode":"1020",
    "addr:street":"Zirkusgasse",
    "iso:country":"AT",
    "sg:address":"Zirkusgasse 40",
    "sg:city":"Wien",
    "sg:orig_category":"Dtp Applications",
    "sg:phone":"+43 1 2165585",
    "sg:postcode":"1020",
    "sg:province":"Wien",
    "sg:website":"toolsatwork.com",
    "wof:name":"Tools at Work Hard + Soft Vertriebsges.m.b.H.",
    "wof:placetype":"venue"
},
  "geometry": {"coordinates":[16.3855381012,48.2171592712],"type":"Point"}
}