{
  "type": "Feature",
  "properties": {
    "iso:country":"AT",
    "sg:address":"Jeneweing 20",
    "sg:city":"Wien",
    "sg:orig_category":"Elektroinstallationsunternehmen",
    "sg:phone":"+43 1 2717125",
    "sg:postcode":"1210",
    "sg:province":"Wien",
    "wof:name":"Franner Klemens",
    "wof:placetype":"venue"
},
  "geometry": {"coordinates":[16.3866691589,48.2678146362],"type":"Point"}
}