{
  "type": "Feature",
  "properties": {
    "addr:full":"Franzosenhausweg 51B Linz Ober\u00f6sterreich 4030",
    "addr:housenumber":"51b",
    "addr:postcode":"4030",
    "addr:street":"Franzosenhausweg",
    "iso:country":"AT",
    "sg:address":"Franzosenhausweg 51B",
    "sg:city":"Linz",
    "sg:orig_category":"Schaltanlagen U -Systeme",
    "sg:phone":"+43 732 3766990",
    "sg:postcode":"4030",
    "sg:province":"Ober\u00f6sterreich",
    "wof:name":"Schrack Energietechnik GmbH",
    "wof:placetype":"venue"
},
  "geometry": {"coordinates":[14.2956857681,48.2439002991],"type":"Point"}
}