{
  "type": "Feature",
  "properties": {
    "iso:country":"AT",
    "sg:address":"Stattersdorfer Hauptstr 127",
    "sg:city":"St. P\u00f6lten",
    "sg:orig_category":"Blumeneinzelhandel",
    "sg:phone":"+43 4327 42253115",
    "sg:postcode":"3100",
    "sg:province":"Nieder\u00f6sterreich",
    "wof:name":"Konrad Blumen",
    "wof:placetype":"venue"
},
  "geometry": {"coordinates":[15.6435899734,48.1820907593],"type":"Point"}
}