{
  "type": "Feature",
  "properties": {
    "addr:full":"Ludwig-Hinnerth-Str 34 Pressbaum Nieder\u00f6sterreich 3021",
    "addr:housenumber":"34",
    "addr:postcode":"3021",
    "addr:street":"Ludwig-Hinnerth-Str;Niederoesterreich",
    "iso:country":"AT",
    "sg:address":"Ludwig-Hinnerth-Str 34",
    "sg:city":"Pressbaum",
    "sg:orig_category":"Installationsunternehmen",
    "sg:phone":"+43 2233 54439",
    "sg:postcode":"3021",
    "sg:province":"Nieder\u00f6sterreich",
    "wof:name":"Rohr & Knie Roland Kupsovsky",
    "wof:placetype":"venue"
},
  "geometry": {"coordinates":[16.0646343231,48.1811828613],"type":"Point"}
}