{
  "type": "Feature",
  "properties": {
    "addr:full":"Dieselg 2 Leopoldsdorf Nieder\u00f6sterreich 2333",
    "addr:housenumber":"2",
    "addr:postcode":"2333",
    "addr:street":"Dieselg",
    "iso:country":"AT",
    "sg:address":"Dieselg 2",
    "sg:city":"Leopoldsdorf",
    "sg:orig_category":"Chemisch-Technische Produkte",
    "sg:phone":"+43 2235 42041",
    "sg:postcode":"2333",
    "sg:province":"Nieder\u00f6sterreich",
    "wof:name":"WB - Chemie Ing Blacky",
    "wof:placetype":"venue"
},
  "geometry": {"coordinates":[16.4088058472,48.1078033447],"type":"Point"}
}