{
  "type": "Feature",
  "properties": {
    "addr:full":"Wahastrasse 3 B\u00fcrmoos Salzburg 5111",
    "addr:housenumber":"3",
    "addr:postcode":"5111",
    "addr:street":"Wahastrasse;Salzburg",
    "iso:country":"AT",
    "sg:address":"Wahastrasse 3",
    "sg:city":"B\u00fcrmoos",
    "sg:classifiers":[
        {
            "category":"Utilities",
            "subcategory":"Recycling",
            "type":"Services"
        }
    ],
    "sg:phone":"+43 6274 75980",
    "sg:postcode":"5111",
    "sg:province":"Salzburg",
    "sg:tags":[
        "metal"
    ],
    "sg:website":"s-m-k.at",
    "wof:name":"Salzburger Metall- und Kabelverwertungs-Ges.m.b.H.",
    "wof:placetype":"venue"
},
  "geometry": {"coordinates":[12.9285469055,47.9848098755],"type":"Point"}
}