{
  "type": "Feature",
  "properties": {
    "addr:full":"Hauptstr 44 Laab im Walde Nieder\u00f6sterreich 2381",
    "addr:housenumber":"44",
    "addr:postcode":"2381",
    "addr:street":"Hauptstr",
    "iso:country":"AT",
    "sg:address":"Hauptstr 44",
    "sg:city":"Laab im Walde",
    "sg:orig_category":"Banken U Sparkassen",
    "sg:phone":"+43 4322 3927920",
    "sg:postcode":"2381",
    "sg:province":"Nieder\u00f6sterreich",
    "wof:name":"Raiffeisenbank Pressbaum-Breitenfurt regGenmbH - Bankstelle Laab i Walde",
    "wof:placetype":"venue"
},
  "geometry": {"coordinates":[16.1736354828,48.1559257507],"type":"Point"}
}