{
  "type": "Feature",
  "properties": {
    "iso:country":"AT",
    "sg:address":"Galtbergstr 1",
    "sg:city":"Mauer-\u00d6hling",
    "sg:orig_category":"Autohandel",
    "sg:phone":"+43 4374 75539410",
    "sg:postcode":"3362",
    "sg:province":"Nieder\u00f6sterreich",
    "sg:website":"senker.at",
    "wof:name":"Autohaus Senker GmbH",
    "wof:placetype":"venue"
},
  "geometry": {"coordinates":[14.7985095978,48.1009559631],"type":"Point"}
}