{
  "type": "Feature",
  "properties": {
    "addr:full":"Frauenfelderstr 11/26 Wien Wien 1170",
    "addr:housenumber":"11 / 26",
    "addr:postcode":"1170",
    "addr:street":"Frauenfelderstr",
    "iso:country":"AT",
    "sg:address":"Frauenfelderstr 11/26",
    "sg:city":"Wien",
    "sg:orig_category":"Weiterbildungsinstitute M Allg U Berufl Bildungsangebot",
    "sg:phone":"+43 664 3222331",
    "sg:postcode":"1170",
    "sg:province":"Wien",
    "wof:name":"Salhofer Marcus Mag",
    "wof:placetype":"venue"
},
  "geometry": {"coordinates":[16.3125267029,48.225479126],"type":"Point"}
}