{
  "type": "Feature",
  "properties": {
    "addr:full":"Marschallg 17 Graz Steiermark 8020",
    "addr:housenumber":"17",
    "addr:postcode":"8020",
    "addr:street":"Marschallg",
    "iso:country":"AT",
    "sg:address":"Marschallg 17",
    "sg:city":"Graz",
    "sg:orig_category":"Ingenieurkonsulenten / Zivilingenieure",
    "sg:phone":"+43 316 712307",
    "sg:postcode":"8020",
    "sg:province":"Steiermark",
    "wof:name":"Setz Johann Dipl-Ing",
    "wof:placetype":"venue"
},
  "geometry": {"coordinates":[15.4305810928,47.0728034973],"type":"Point"}
}