{
  "type": "Feature",
  "properties": {
    "iso:country":"AT",
    "sg:address":"Aichholzg 52",
    "sg:city":"Wien",
    "sg:orig_category":"Lebensmittel / Einzelhandel",
    "sg:phone":"+43 1 8103738",
    "sg:postcode":"1120",
    "sg:province":"Wien",
    "wof:name":"Zielpunkt Warenhandel GmbH & Co KG",
    "wof:placetype":"venue"
},
  "geometry": {"coordinates":[16.3234615326,48.1769714355],"type":"Point"}
}