{
  "type": "Feature",
  "properties": {
    "addr:full":"Nr 41 Ilz Steiermark 8262",
    "addr:postcode":"8262",
    "addr:street":"Nr",
    "iso:country":"AT",
    "sg:address":"Nr 41",
    "sg:city":"Ilz",
    "sg:orig_category":"Bierlokale-Pubs",
    "sg:phone":"+43 3385 8264",
    "sg:postcode":"8262",
    "sg:province":"Steiermark",
    "wof:name":"Bierstube Ilz",
    "wof:placetype":"venue"
},
  "geometry": {"coordinates":[15.9260549545,47.086479187],"type":"Point"}
}