{
  "type": "Feature",
  "properties": {
    "iso:country":"AT",
    "sg:address":"Landwehrstr 6",
    "sg:city":"Wien",
    "sg:orig_category":"Unterhaltungselektronik / Einzelhandel",
    "sg:phone":"+43 1 76716200",
    "sg:postcode":"1110",
    "sg:province":"Wien",
    "wof:name":"Media Markt TV-Hifi Elektro Wien XI GesmbH",
    "wof:placetype":"venue"
},
  "geometry": {"coordinates":[16.4725265503,48.1718521118],"type":"Point"}
}