{
  "type": "Feature",
  "properties": {
    "addr:full":"St. Peter Hauptstr 53 St. Peter Steiermark 8042",
    "addr:housenumber":"53",
    "addr:postcode":"8042",
    "addr:street":"Hauptstr",
    "iso:country":"AT",
    "sg:address":"St. Peter Hauptstr 53",
    "sg:city":"St. Peter",
    "sg:orig_category":"Optiker",
    "sg:phone":"+43 4331 6428871",
    "sg:postcode":"8042",
    "sg:province":"Steiermark",
    "wof:name":"Brillenstube E u H Rohsmann",
    "wof:placetype":"venue"
},
  "geometry": {"coordinates":[15.471452713,47.0574760437],"type":"Point"}
}