{
  "type": "Feature",
  "properties": {
    "addr:full":"Neualmer Str 25 Hallein Salzburg 5400",
    "addr:housenumber":"25",
    "addr:postcode":"5400",
    "addr:street":"Str;Salzburg",
    "iso:country":"AT",
    "sg:address":"Neualmer Str 25",
    "sg:city":"Hallein",
    "sg:orig_category":"Autolackierereien",
    "sg:phone":"+43 4362 4586906",
    "sg:postcode":"5400",
    "sg:province":"Salzburg",
    "sg:website":"gerl-hallein.at.tf",
    "wof:name":"GERL KAROSSERIE-ZENTRUM",
    "wof:placetype":"venue"
},
  "geometry": {"coordinates":[13.0888004303,47.688293457],"type":"Point"}
}