{
  "type": "Feature",
  "properties": {
    "addr:full":"Offner Platzl 2 Wolfsberg K\u00e4rnten 9400",
    "addr:housenumber":"2;kaernten",
    "addr:postcode":"9400",
    "addr:street":"Platzl",
    "iso:country":"AT",
    "sg:address":"Offner Platzl 2",
    "sg:city":"Wolfsberg",
    "sg:orig_category":"Physikalische Institute",
    "sg:phone":"+43 4352 46007",
    "sg:postcode":"9400",
    "sg:province":"K\u00e4rnten",
    "wof:name":"Panvital Physiotherapie-Praxis",
    "wof:placetype":"venue"
},
  "geometry": {"coordinates":[14.8421592712,46.8404693604],"type":"Point"}
}