{
  "type": "Feature",
  "properties": {
    "addr:full":"Wiener Str 86 Kirchschlag in der Buckligen Welt Nieder\u00f6sterreich 2860",
    "addr:postcode":"2860",
    "iso:country":"AT",
    "sg:address":"Wiener Str 86",
    "sg:city":"Kirchschlag in der Buckligen Welt",
    "sg:orig_category":"Tankstellen",
    "sg:phone":"+43 4326 462342",
    "sg:postcode":"2860",
    "sg:province":"Nieder\u00f6sterreich",
    "wof:name":"Rembart GesmbH",
    "wof:placetype":"venue"
},
  "geometry": {"coordinates":[16.2825927734,47.4941940308],"type":"Point"}
}