{
  "type": "Feature",
  "properties": {
    "addr:full":"Bethlehemstr 24 Linz Ober\u00f6sterreich 4020",
    "addr:housenumber":"24",
    "addr:postcode":"4020",
    "addr:street":"Bethlehemstr",
    "iso:country":"AT",
    "sg:address":"Bethlehemstr 24",
    "sg:city":"Linz",
    "sg:orig_category":"Steuerberatung",
    "sg:phone":"+43 732 794533",
    "sg:postcode":"4020",
    "sg:province":"Ober\u00f6sterreich",
    "wof:name":"Danubia-Treuhand SteuerberatungsgesmbH",
    "wof:placetype":"venue"
},
  "geometry": {"coordinates":[14.2922391891,48.3040046692],"type":"Point"}
}