{
  "type": "Feature",
  "properties": {
    "addr:full":"Klosterwiesg. 9  Graz Steiermark 8010",
    "addr:housenumber":"9",
    "addr:postcode":"8010",
    "addr:street":"Klosterwiesg.",
    "iso:country":"AT",
    "sg:address":"Klosterwiesg. 9 ",
    "sg:city":"Graz",
    "sg:classifiers":[
        {
            "category":"Shopping",
            "subcategory":"Clothing, Apparel, & Fashions",
            "type":"Retail Goods"
        }
    ],
    "sg:phone":"+43 4331 6827796",
    "sg:postcode":"8010",
    "sg:province":"Steiermark",
    "sg:tags":[
        "clothes"
    ],
    "wof:name":"TRACHTENSTUBE DOPPAN",
    "wof:placetype":"venue"
},
  "geometry": {"coordinates":[15.443816185,47.0663948059],"type":"Point"}
}