{
  "type": "Feature",
  "properties": {
    "iso:country":"AT",
    "sg:address":"Schulg 27",
    "sg:city":"Deutschlandsberg",
    "sg:orig_category":"Notare",
    "sg:phone":"+43 3462 24920",
    "sg:postcode":"8530",
    "sg:province":"Steiermark",
    "sg:website":"notariat.info",
    "wof:name":"Czapka Peter Dr",
    "wof:placetype":"venue"
},
  "geometry": {"coordinates":[15.2111930847,46.8151016235],"type":"Point"}
}