{
  "type": "Feature",
  "properties": {
    "addr:full":"Am Modenapark 3 Wien Wien 1030",
    "addr:housenumber":"3",
    "addr:postcode":"1030",
    "addr:street":"Am Modenapark",
    "iso:country":"AT",
    "sg:address":"Am Modenapark 3",
    "sg:city":"Wien",
    "sg:orig_category":"Geschenkartikel",
    "sg:phone":"+43 1 7136767",
    "sg:postcode":"1030",
    "sg:province":"Wien",
    "wof:name":"Venuleth Christian Dkfm Dr",
    "wof:placetype":"venue"
},
  "geometry": {"coordinates":[16.3830356598,48.2001876831],"type":"Point"}
}