{
  "type": "Feature",
  "properties": {
    "iso:country":"AT",
    "sg:address":"Kurhausstr 8",
    "sg:city":"Bad Ischl",
    "sg:classifiers":[
        {
            "category":"Restaurant",
            "type":"Food & Drink"
        }
    ],
    "sg:phone":"+43 6132 233220",
    "sg:postcode":"4820",
    "sg:province":"Ober\u00f6sterreich",
    "wof:name":"Das Cafe-Restaurant",
    "wof:placetype":"venue"
},
  "geometry": {"coordinates":[13.6183080673,47.7112236023],"type":"Point"}
}