{
  "type": "Feature",
  "properties": {
    "addr:full":"Hauptstr 41 Radenthein K\u00e4rnten 9545",
    "addr:housenumber":"41",
    "addr:postcode":"9545",
    "addr:street":"Hauptstr;Kaernten",
    "iso:country":"AT",
    "sg:address":"Hauptstr 41",
    "sg:city":"Radenthein",
    "sg:orig_category":"Bankomat-Standorte",
    "sg:phone":"+43 4246 20820",
    "sg:postcode":"9545",
    "sg:province":"K\u00e4rnten",
    "wof:name":"Bankomat d Raiffeisenbank Radenthein-Bad Kleinkirchheim regGenmbH",
    "wof:placetype":"venue"
},
  "geometry": {"coordinates":[13.7039575577,46.8006591797],"type":"Point"}
}