{
  "type": "Feature",
  "properties": {
    "iso:country":"AT",
    "sg:address":"Kircheng 1a/5",
    "sg:city":"Wien",
    "sg:orig_category":"Werbeagenturen",
    "sg:phone":"+43 1 5248900",
    "sg:postcode":"1070",
    "sg:province":"Wien",
    "wof:name":"Egger & Lerch GmbH",
    "wof:placetype":"venue"
},
  "geometry": {"coordinates":[16.3525848389,48.1996421814],"type":"Point"}
}