{
  "type": "Feature",
  "properties": {
    "addr:full":"Obere Hauptstr 7 Wilhelmsburg an der Traisen Nieder\u00f6sterreich 3150",
    "addr:housenumber":"7",
    "addr:postcode":"3150",
    "addr:street":"Obere Hauptstr",
    "iso:country":"AT",
    "sg:address":"Obere Hauptstr 7",
    "sg:city":"Wilhelmsburg an der Traisen",
    "sg:orig_category":"Apotheken",
    "sg:phone":"+43 4327 462223",
    "sg:postcode":"3150",
    "sg:province":"Nieder\u00f6sterreich",
    "wof:name":"Apotheke Zur Mariahilf",
    "wof:placetype":"venue"
},
  "geometry": {"coordinates":[15.6054210663,48.1034393311],"type":"Point"}
}