{
  "type": "Feature",
  "properties": {
    "iso:country":"AT",
    "sg:address":"Wachaustr 7",
    "sg:city":"Krems an der Donau",
    "sg:orig_category":"Textildruckereien",
    "sg:phone":"+43 4327 32700080",
    "sg:postcode":"3500",
    "sg:province":"Nieder\u00f6sterreich",
    "wof:name":"Grafik & Druck GesmbH",
    "wof:placetype":"venue"
},
  "geometry": {"coordinates":[15.6012363434,48.4134521484],"type":"Point"}
}