{
  "type": "Feature",
  "properties": {
    "addr:full":"Reichsstr 35a Feldkirch Vorarlberg 6800",
    "addr:housenumber":"35a",
    "addr:postcode":"6800",
    "addr:street":"Reichsstr",
    "iso:country":"AT",
    "sg:address":"Reichsstr 35a",
    "sg:city":"Feldkirch",
    "sg:orig_category":"Schneidereien",
    "sg:phone":"+43 5522 73376",
    "sg:postcode":"6800",
    "sg:province":"Vorarlberg",
    "wof:name":"Nikolic Draga",
    "wof:placetype":"venue"
},
  "geometry": {"coordinates":[9.6162443161,47.2575798035],"type":"Point"}
}