{
  "type": "Feature",
  "properties": {
    "addr:full":"Bahnhofstr 25 Rankweil Vorarlberg 6830",
    "addr:postcode":"6830",
    "addr:street":"Bahnhofstr 25",
    "iso:country":"AT",
    "sg:address":"Bahnhofstr 25",
    "sg:city":"Rankweil",
    "sg:orig_category":"Physiotherapie",
    "sg:phone":"+43 5522 42478",
    "sg:postcode":"6830",
    "sg:province":"Vorarlberg",
    "wof:name":"Antina van der Veen",
    "wof:placetype":"venue"
},
  "geometry": {"coordinates":[9.6390638351,47.2714271545],"type":"Point"}
}