{
  "type": "Feature",
  "properties": {
    "addr:full":"Bahnhofstr 22 Andorf Ober\u00f6sterreich 4770",
    "addr:housenumber":"22",
    "addr:postcode":"4770",
    "addr:street":"Bahnhofstr",
    "iso:country":"AT",
    "sg:address":"Bahnhofstr 22",
    "sg:city":"Andorf",
    "sg:orig_category":"Rettungsdienste",
    "sg:phone":"+43 7766 2144",
    "sg:postcode":"4770",
    "sg:province":"Ober\u00f6sterreich",
    "wof:name":"Rotes Kreuz \u00d6sterreichisches",
    "wof:placetype":"venue"
},
  "geometry": {"coordinates":[13.5664701462,48.3708953857],"type":"Point"}
}