{
  "type": "Feature",
  "properties": {
    "iso:country":"AT",
    "sg:address":"Alte Poststr 136a",
    "sg:city":"Graz",
    "sg:orig_category":"Unternehmensberatung",
    "sg:phone":"+43 316 578602",
    "sg:postcode":"8020",
    "sg:province":"Steiermark",
    "wof:name":"Gogg Hans Unternehmensberater",
    "wof:placetype":"venue"
},
  "geometry": {"coordinates":[15.4085760117,47.071395874],"type":"Point"}
}