{
  "type": "Feature",
  "properties": {
    "addr:full":"Johann Herbst-Str Elsbethen-Glasenbach Salzburg 5061",
    "addr:postcode":"5061",
    "iso:country":"AT",
    "sg:address":"Johann Herbst-Str",
    "sg:city":"Elsbethen-Glasenbach",
    "sg:orig_category":"Tourismusinformation U -Organisationen",
    "sg:phone":"+43 662 628891",
    "sg:postcode":"5061",
    "sg:province":"Salzburg",
    "wof:name":"Fremdenverkehrsverband Elsbethen",
    "wof:placetype":"venue"
},
  "geometry": {"coordinates":[13.0837421417,47.7701072693],"type":"Point"}
}