{
  "type": "Feature",
  "properties": {
    "iso:country":"AT",
    "sg:address":"Seestr",
    "sg:city":"Bregenz",
    "sg:orig_category":"Molkereien U Molkereiprodukte",
    "sg:phone":"+43 4355 7443508",
    "sg:postcode":"6900",
    "sg:province":"Vorarlberg",
    "wof:name":"Vorarlberg Milch reg GenmbH",
    "wof:placetype":"venue"
},
  "geometry": {"coordinates":[9.748052597,47.5055465698],"type":"Point"}
}