{
  "type": "Feature",
  "properties": {
    "iso:country":"AT",
    "sg:address":"Jakob-Haringer-Str 5",
    "sg:city":"Salzburg",
    "sg:classifiers":[
        {
            "category":"Internet Cafe",
            "subcategory":"None",
            "type":"Food & Drink"
        }
    ],
    "sg:phone":"+43 4366 2890000",
    "sg:postcode":"5020",
    "sg:province":"Salzburg",
    "sg:tags":[
        "internet-provider"
    ],
    "wof:name":"mki Technologie und Dienstleistungs GmbH",
    "wof:placetype":"venue"
},
  "geometry": {"coordinates":[13.0414838791,47.8227577209],"type":"Point"}
}