{
  "type": "Feature",
  "properties": {
    "iso:country":"AT",
    "sg:address":"Neugasse 69",
    "sg:city":"Oberw\u00f6lz",
    "sg:classifiers":[
        {
            "category":"Manufacturing",
            "subcategory":"Furniture",
            "type":"Manufacturing & Wholesale Goods"
        }
    ],
    "sg:phone":"+43 3581 8258",
    "sg:postcode":"8832",
    "sg:province":"Steiermark",
    "sg:tags":[
        "beech"
    ],
    "wof:name":"Peter Rauch",
    "wof:placetype":"venue"
},
  "geometry": {"coordinates":[12.7382097244,42.0217399597],"type":"Point"}
}