{
  "type": "Feature",
  "properties": {
    "iso:country":"AT",
    "sg:address":"Eisenst\u00e4dt Bundesstr 15",
    "sg:city":"Oberwart",
    "sg:orig_category":"Autohandel",
    "sg:phone":"+43 3352 32519",
    "sg:postcode":"7400",
    "sg:province":"Burgenland",
    "wof:name":"Autohandels GmbH",
    "wof:placetype":"venue"
},
  "geometry": {"coordinates":[16.2131557465,47.2876167297],"type":"Point"}
}