{
  "type": "Feature",
  "properties": {
    "addr:full":"Unterer Pl 15 St. Veit an der Glan K\u00e4rnten 9300",
    "addr:housenumber":"15",
    "addr:postcode":"9300",
    "addr:street":"Unterer Pl;Kaernten",
    "iso:country":"AT",
    "sg:address":"Unterer Pl 15",
    "sg:city":"St. Veit an der Glan",
    "sg:orig_category":"Alternativtherapie",
    "sg:phone":"+43 4369 910204273",
    "sg:postcode":"9300",
    "sg:province":"K\u00e4rnten",
    "wof:name":"Hafner Kristina - Shiatsu Praxis",
    "wof:placetype":"venue"
},
  "geometry": {"coordinates":[14.359746933,46.7681846619],"type":"Point"}
}