{
  "type": "Feature",
  "properties": {
    "addr:full":"K\u00e4rntner Str. 57  Lienz Tirol 9900",
    "addr:postcode":"9900",
    "addr:street":"Str. 57;Tirol",
    "iso:country":"AT",
    "sg:address":"K\u00e4rntner Str. 57 ",
    "sg:city":"Lienz",
    "sg:classifiers":[
        {
            "category":"Manufacturing",
            "subcategory":"Textiles",
            "type":"Manufacturing & Wholesale Goods"
        }
    ],
    "sg:phone":"+43 4348 52636550",
    "sg:postcode":"9900",
    "sg:province":"Tirol",
    "sg:tags":[
        "leather",
        "raw",
        "material",
        "-"
    ],
    "wof:name":"STAFFLER GES.MBH",
    "wof:placetype":"venue"
},
  "geometry": {"coordinates":[12.7684783936,46.8281173706],"type":"Point"}
}