{
  "type": "Feature",
  "properties": {
    "addr:full":"Leonfeldner Str 289 Linz Ober\u00f6sterreich 4040",
    "addr:housenumber":"289",
    "addr:postcode":"4040",
    "iso:country":"AT",
    "sg:address":"Leonfeldner Str 289",
    "sg:city":"Linz",
    "sg:orig_category":"Spenglereien",
    "sg:phone":"+43 4366 43525701",
    "sg:postcode":"4040",
    "sg:province":"Ober\u00f6sterreich",
    "wof:name":"Seyr-Dachdeckerei u Spenglerei GesmbH",
    "wof:placetype":"venue"
},
  "geometry": {"coordinates":[14.2920560837,48.3491859436],"type":"Point"}
}