{
  "type": "Feature",
  "properties": {
    "addr:full":"Paul-Hahn-Str 1 Linz Ober\u00f6sterreich 4020",
    "addr:housenumber":"1",
    "addr:postcode":"4020",
    "addr:street":"Paul-Hahn-Str",
    "iso:country":"AT",
    "sg:address":"Paul-Hahn-Str 1",
    "sg:city":"Linz",
    "sg:classifiers":[
        {
            "category":"Internet Cafe",
            "subcategory":"None",
            "type":"Food & Drink"
        }
    ],
    "sg:phone":"+43 732 779463",
    "sg:postcode":"4020",
    "sg:province":"Ober\u00f6sterreich",
    "wof:name":"Networx.at Internet-Design Busta & Neumayr OEG",
    "wof:placetype":"venue"
},
  "geometry": {"coordinates":[14.3103580475,48.3071784973],"type":"Point"}
}