{
  "type": "Feature",
  "properties": {
    "addr:full":"Grinzinger Str 71-73 Wien Wien 1190",
    "addr:postcode":"71-73;1190",
    "addr:street":"Str",
    "iso:country":"AT",
    "sg:address":"Grinzinger Str 71-73",
    "sg:city":"Wien",
    "sg:orig_category":"Restaurants: Chinesisch",
    "sg:phone":"+43 1 3206896",
    "sg:postcode":"1190",
    "sg:province":"Wien",
    "wof:name":"Jade China Restaurant",
    "wof:placetype":"venue"
},
  "geometry": {"coordinates":[16.3530521393,48.2537956238],"type":"Point"}
}