{
  "type": "Feature",
  "properties": {
    "addr:full":"Erzherzog-Johann-Gasse 10 Bruck an der Mur Steiermark 8600",
    "addr:housenumber":"10",
    "addr:postcode":"8600",
    "addr:street":"Erzherzog-Johann-Gasse",
    "iso:country":"AT",
    "sg:address":"Erzherzog-Johann-Gasse 10",
    "sg:city":"Bruck an der Mur",
    "sg:classifiers":[
        {
            "category":"Shopping",
            "subcategory":"Books",
            "type":"Retail Goods"
        }
    ],
    "sg:phone":"+43 3862 570180",
    "sg:postcode":"8600",
    "sg:province":"Steiermark",
    "sg:website":"compact-druck.at",
    "wof:name":"CD COMPACT-DRUCK GmbH",
    "wof:placetype":"venue"
},
  "geometry": {"coordinates":[15.2729387283,47.4080963135],"type":"Point"}
}