{
  "type": "Feature",
  "properties": {
    "iso:country":"AT",
    "sg:address":"Bahnhofstr 5",
    "sg:city":"Tulln an der Donau",
    "sg:orig_category":"Bekleidung / Einzelhandel",
    "sg:phone":"+43 2272 66438",
    "sg:postcode":"3430",
    "sg:province":"Nieder\u00f6sterreich",
    "wof:name":"Marc O' Polo",
    "wof:placetype":"venue"
},
  "geometry": {"coordinates":[16.0536518097,48.3302459717],"type":"Point"}
}