{
  "type": "Feature",
  "properties": {
    "addr:full":"Dandlerau 13 Fieberbrunn Tirol 6391",
    "addr:housenumber":"13",
    "addr:postcode":"6391",
    "addr:street":"Dandlerau;Tirol",
    "iso:country":"AT",
    "sg:address":"Dandlerau 13",
    "sg:city":"Fieberbrunn",
    "sg:orig_category":"Bauunternehmen",
    "sg:phone":"+43 5354 56544",
    "sg:postcode":"6391",
    "sg:province":"Tirol",
    "wof:name":"Bendler Herbert Bauunternehmen GesmbH",
    "wof:placetype":"venue"
},
  "geometry": {"coordinates":[12.5693826675,47.4668312073],"type":"Point"}
}