{
  "type": "Feature",
  "properties": {
    "addr:full":"Nibelungengasse 13 -  Wien Wien 1010",
    "addr:housenumber":"13",
    "addr:postcode":"1010",
    "addr:street":"Nibelungengasse",
    "iso:country":"AT",
    "sg:address":"Nibelungengasse 13 - ",
    "sg:city":"Wien",
    "sg:classifiers":[
        {
            "category":"Professional",
            "subcategory":"Art Services",
            "type":"Services"
        }
    ],
    "sg:phone":"+43 4315 861309",
    "sg:postcode":"1010",
    "sg:province":"Wien",
    "sg:tags":[
        "export-import"
    ],
    "wof:name":"Slovenia Embassy",
    "wof:placetype":"venue"
},
  "geometry": {"coordinates":[16.3625564575,48.2025527954],"type":"Point"}
}