{
  "type": "Feature",
  "properties": {
    "addr:full":"Klausner H\u00f6he 14 Kirchberg in Tirol Tirol 6365",
    "addr:housenumber":"14",
    "addr:postcode":"6365",
    "addr:street":"Hoehe;Tirol",
    "iso:country":"AT",
    "sg:address":"Klausner H\u00f6he 14",
    "sg:city":"Kirchberg in Tirol",
    "sg:orig_category":"Elektroinstallationsunternehmen",
    "sg:phone":"+43 5357 33550",
    "sg:postcode":"6365",
    "sg:province":"Tirol",
    "wof:name":"Elektro Moser GmbH",
    "wof:placetype":"venue"
},
  "geometry": {"coordinates":[12.3149347305,47.4481468201],"type":"Point"}
}