{
  "type": "Feature",
  "properties": {
    "iso:country":"AT",
    "sg:address":"Maximilianstr 2",
    "sg:city":"Innsbruck",
    "sg:orig_category":"Fotoapparate U -Artikel / Einzelhandel",
    "sg:phone":"+43 512 584304",
    "sg:postcode":"6020",
    "sg:province":"Tirol",
    "wof:name":"Foto Busarello GesmbH",
    "wof:placetype":"venue"
},
  "geometry": {"coordinates":[11.3937578201,47.262714386],"type":"Point"}
}