{
  "type": "Feature",
  "properties": {
    "addr:full":"St\u00f6cklerh\u00f6he 5 St. Valentin Nieder\u00f6sterreich 4300",
    "addr:housenumber":"5",
    "addr:postcode":"4300",
    "addr:street":"Stoecklerhoehe",
    "iso:country":"AT",
    "sg:address":"St\u00f6cklerh\u00f6he 5",
    "sg:city":"St. Valentin",
    "sg:orig_category":"Unternehmensberatung",
    "sg:phone":"+43 4374 3559177",
    "sg:postcode":"4300",
    "sg:province":"Nieder\u00f6sterreich",
    "wof:name":"B & B Hornaus GmbH",
    "wof:placetype":"venue"
},
  "geometry": {"coordinates":[14.5330696106,48.174621582],"type":"Point"}
}