{
  "type": "Feature",
  "properties": {
    "addr:full":"Kreuzg 28 Wien Wien 1180",
    "addr:housenumber":"28",
    "addr:postcode":"1180",
    "addr:street":"Kreuzg",
    "iso:country":"AT",
    "sg:address":"Kreuzg 28",
    "sg:city":"Wien",
    "sg:orig_category":"Handelsagenturen",
    "sg:phone":"+43 4314 029380",
    "sg:postcode":"1180",
    "sg:province":"Wien",
    "wof:name":"Schubert Franz HandelsgesmbH Wien Nfg KEG",
    "wof:placetype":"venue"
},
  "geometry": {"coordinates":[16.3395881653,48.2229766846],"type":"Point"}
}