{
  "type": "Feature",
  "properties": {
    "addr:full":"Schulg 2 Pamhagen Burgenland 7152",
    "addr:housenumber":"2",
    "addr:postcode":"7152",
    "addr:street":"Schulg",
    "iso:country":"AT",
    "sg:address":"Schulg 2",
    "sg:city":"Pamhagen",
    "sg:orig_category":"Hauptschulen",
    "sg:phone":"+43 2174 21490",
    "sg:postcode":"7152",
    "sg:province":"Burgenland",
    "wof:name":"Hauptschule",
    "wof:placetype":"venue"
},
  "geometry": {"coordinates":[16.9034194946,47.6996498108],"type":"Point"}
}