{
  "type": "Feature",
  "properties": {
    "addr:full":"Mozartg 28 Perchtoldsdorf Nieder\u00f6sterreich 2380",
    "addr:housenumber":"28",
    "addr:postcode":"2380",
    "addr:street":"Mozartg",
    "iso:country":"AT",
    "sg:address":"Mozartg 28",
    "sg:city":"Perchtoldsdorf",
    "sg:orig_category":"Kosmetikanwendungsberatung",
    "sg:phone":"+43 1 86598150",
    "sg:postcode":"2380",
    "sg:province":"Nieder\u00f6sterreich",
    "wof:name":"Channoine Systempflegeberatung und Nobusan Ern\u00e4hrungsberatung Anton Eigner",
    "wof:placetype":"venue"
},
  "geometry": {"coordinates":[16.2652320862,48.1192970276],"type":"Point"}
}