{
  "type": "Feature",
  "properties": {
    "addr:full":"Hauptstr 15 Hieflau Steiermark 8920",
    "addr:housenumber":"15",
    "addr:postcode":"8920",
    "addr:street":"Hauptstr",
    "iso:country":"AT",
    "sg:address":"Hauptstr 15",
    "sg:city":"Hieflau",
    "sg:orig_category":"Polizei U Gendarmerie",
    "sg:phone":"+43 4359 1336322",
    "sg:postcode":"8920",
    "sg:province":"Steiermark",
    "wof:name":"Gendarmerie Hieflau",
    "wof:placetype":"venue"
},
  "geometry": {"coordinates":[14.7447004318,47.6060791016],"type":"Point"}
}