{
  "type": "Feature",
  "properties": {
    "iso:country":"AT",
    "sg:address":"M\u00f6selg 17",
    "sg:city":"Kirchberg in Tirol",
    "sg:orig_category":"Pensionen / Privatzimmer",
    "sg:phone":"+43 5357 2789",
    "sg:postcode":"6365",
    "sg:province":"Tirol",
    "wof:name":"Pension Traudl",
    "wof:placetype":"venue"
},
  "geometry": {"coordinates":[12.3149347305,47.4481468201],"type":"Point"}
}