{
  "type": "Feature",
  "properties": {
    "addr:full":"Gemeindepl 14 Wels Ober\u00f6sterreich 4600",
    "addr:housenumber":"14",
    "addr:postcode":"4600",
    "addr:street":"Gemeindepl;Oberoesterreich",
    "iso:country":"AT",
    "sg:address":"Gemeindepl 14",
    "sg:city":"Wels",
    "sg:orig_category":"Volkshochschulen",
    "sg:phone":"+43 4372 4272898",
    "sg:postcode":"4600",
    "sg:province":"Ober\u00f6sterreich",
    "wof:name":"Volkshochschule Thalheim",
    "wof:placetype":"venue"
},
  "geometry": {"coordinates":[14.0308856964,48.1529006958],"type":"Point"}
}