{
  "type": "Feature",
  "properties": {
    "addr:full":"Obere Hauptstr 27 Rohrendorf Nieder\u00f6sterreich 3495",
    "addr:housenumber":"27",
    "addr:postcode":"3495",
    "addr:street":"Obere Hauptstr",
    "iso:country":"AT",
    "sg:address":"Obere Hauptstr 27",
    "sg:city":"Rohrendorf",
    "sg:orig_category":"Architekten",
    "sg:phone":"+43 2732 87320",
    "sg:postcode":"3495",
    "sg:province":"Nieder\u00f6sterreich",
    "wof:name":"Z.B. B\u00fcro f Architektur",
    "wof:placetype":"venue"
},
  "geometry": {"coordinates":[15.653881073,48.419052124],"type":"Point"}
}