{
  "type": "Feature",
  "properties": {
    "addr:full":"Europaallee 5 Weiz Steiermark 8160",
    "addr:housenumber":"5",
    "addr:postcode":"8160",
    "addr:street":"Europaallee",
    "iso:country":"AT",
    "sg:address":"Europaallee 5",
    "sg:city":"Weiz",
    "sg:orig_category":"Volksschulen",
    "sg:phone":"+43 3172 2634",
    "sg:postcode":"8160",
    "sg:province":"Steiermark",
    "wof:name":"Volksschule 1",
    "wof:placetype":"venue"
},
  "geometry": {"coordinates":[15.6262626648,47.218536377],"type":"Point"}
}