{
  "type": "Feature",
  "properties": {
    "iso:country":"AT",
    "sg:address":"Stempferg 2",
    "sg:city":"Graz",
    "sg:orig_category":"Feinkost",
    "sg:phone":"+43 4331 68222120",
    "sg:postcode":"8010",
    "sg:province":"Steiermark",
    "sg:website":"frankowitsch.at",
    "wof:name":"Frankowitsch-Delikatessen",
    "wof:placetype":"venue"
},
  "geometry": {"coordinates":[15.4411096573,47.0707511902],"type":"Point"}
}