{
  "type": "Feature",
  "properties": {
    "addr:full":"Obere Hauptstr 7 Illmitz Burgenland 7142",
    "addr:housenumber":"7",
    "addr:postcode":"7142",
    "addr:street":"Obere Hauptstr",
    "iso:country":"AT",
    "sg:address":"Obere Hauptstr 7",
    "sg:city":"Illmitz",
    "sg:orig_category":"Pensionen / Privatzimmer",
    "sg:phone":"+43 2175 2355",
    "sg:postcode":"7142",
    "sg:province":"Burgenland",
    "wof:name":"Pension-Weingut Storchenblick",
    "wof:placetype":"venue"
},
  "geometry": {"coordinates":[16.7999610901,47.7626075745],"type":"Point"}
}