{
  "type": "Feature",
  "properties": {
    "addr:full":"Mitterg 1 Stams Tirol 6422",
    "addr:housenumber":"1",
    "addr:postcode":"6422",
    "addr:street":"Mitterg;Tirol",
    "iso:country":"AT",
    "sg:address":"Mitterg 1",
    "sg:city":"Stams",
    "sg:orig_category":"Weiterbildungsinstitute M Allg U Berufl Bildungsangebot",
    "sg:phone":"+43 4352 636096",
    "sg:postcode":"6422",
    "sg:province":"Tirol",
    "wof:name":"Erwachsenenschule Stams",
    "wof:placetype":"venue"
},
  "geometry": {"coordinates":[10.9793548584,47.2763786316],"type":"Point"}
}