{
  "type": "Feature",
  "properties": {
    "addr:full":"Dorf 29 Maria Alm am Steinernen Meer Salzburg 5761",
    "addr:housenumber":"29",
    "addr:postcode":"5761",
    "addr:street":"Dorf",
    "iso:country":"AT",
    "sg:address":"Dorf 29",
    "sg:city":"Maria Alm am Steinernen Meer",
    "sg:orig_category":"Pensionen / Privatzimmer",
    "sg:phone":"+43 4365 847767",
    "sg:postcode":"5761",
    "sg:province":"Salzburg",
    "wof:name":"Schernthaner Stefan",
    "wof:placetype":"venue"
},
  "geometry": {"coordinates":[12.9026556015,47.4013557434],"type":"Point"}
}