{
  "type": "Feature",
  "properties": {
    "addr:full":"Mittersteig 2a Wien Wien 1040",
    "addr:housenumber":"2a",
    "addr:postcode":"1040",
    "addr:street":"Mittersteig",
    "iso:country":"AT",
    "sg:address":"Mittersteig 2a",
    "sg:city":"Wien",
    "sg:orig_category":"Friseure U Frisiersalons",
    "sg:phone":"+43 1 5815810",
    "sg:postcode":"1040",
    "sg:province":"Wien",
    "wof:name":"Sophie's Salon",
    "wof:placetype":"venue"
},
  "geometry": {"coordinates":[16.3643722534,48.1925468445],"type":"Point"}
}