{
  "type": "Feature",
  "properties": {
    "iso:country":"AT",
    "sg:address":"Rathauspl 1",
    "sg:city":"Hornstein",
    "sg:orig_category":"Gemeinden",
    "sg:phone":"+43 2689 22250",
    "sg:postcode":"7053",
    "sg:province":"Burgenland",
    "wof:name":"Gemeinde Hornstein",
    "wof:placetype":"venue"
},
  "geometry": {"coordinates":[16.4426708221,47.8794975281],"type":"Point"}
}