{
  "type": "Feature",
  "properties": {
    "addr:full":"See 504 S\u00f6lden Tirol 6450",
    "addr:housenumber":"504",
    "addr:postcode":"6450",
    "addr:street":"See;Tirol",
    "iso:country":"AT",
    "sg:address":"See 504",
    "sg:city":"S\u00f6lden",
    "sg:orig_category":"Appartements / Ferienwohnungen",
    "sg:phone":"+43 5254 2624",
    "sg:postcode":"6450",
    "sg:province":"Tirol",
    "wof:name":"G\u00e4stehaus See",
    "wof:placetype":"venue"
},
  "geometry": {"coordinates":[11.0032901764,46.9705314636],"type":"Point"}
}