{
  "type": "Feature",
  "properties": {
    "addr:full":"Sankt-Josef-Strasse 33 Villach K\u00e4rnten 9500",
    "addr:housenumber":"33",
    "addr:postcode":"9500",
    "addr:street":"Sankt-Josef-Strasse;Kaernten",
    "iso:country":"AT",
    "sg:address":"Sankt-Josef-Strasse 33",
    "sg:city":"Villach",
    "sg:classifiers":[
        {
            "category":"Professional",
            "subcategory":"Engineering",
            "type":"Services"
        }
    ],
    "sg:phone":"+43 4242 34506",
    "sg:postcode":"9500",
    "sg:province":"K\u00e4rnten",
    "sg:tags":[
        "technology",
        "dredging"
    ],
    "wof:name":"Baumaschinentechnik Ges.m.b.H.",
    "wof:placetype":"venue"
},
  "geometry": {"coordinates":[13.8403396606,46.5945701599],"type":"Point"}
}