{
  "type": "Feature",
  "properties": {
    "iso:country":"AT",
    "sg:address":"Schlo\u00dfpl 1",
    "sg:city":"Oberpullendorf",
    "sg:orig_category":"Apotheken",
    "sg:phone":"+43 2612 423390",
    "sg:postcode":"7350",
    "sg:province":"Burgenland",
    "wof:name":"Apotheke z Mohren Mr Szczepanski",
    "wof:placetype":"venue"
},
  "geometry": {"coordinates":[16.5028171539,47.5027618408],"type":"Point"}
}