{
  "type": "Feature",
  "properties": {
    "iso:country":"AT",
    "sg:address":"Hauptstr 135",
    "sg:city":"Jagenbach",
    "sg:orig_category":"Transportunternehmen",
    "sg:phone":"+43 2829 200100",
    "sg:postcode":"3923",
    "sg:province":"Nieder\u00f6sterreich",
    "wof:name":"Anderst Transport GmbH",
    "wof:placetype":"venue"
},
  "geometry": {"coordinates":[15.0300912857,48.6392173767],"type":"Point"}
}