{
  "type": "Feature",
  "properties": {
    "addr:full":"Zschokkeg 91 Wien Wien 1220",
    "addr:housenumber":"91",
    "addr:postcode":"1220",
    "addr:street":"Zschokkeg",
    "iso:country":"AT",
    "sg:address":"Zschokkeg 91",
    "sg:city":"Wien",
    "sg:orig_category":"Tabaktrafiken",
    "sg:phone":"+43 1 2837126",
    "sg:postcode":"1220",
    "sg:province":"Wien",
    "wof:name":"Lehner Eveline",
    "wof:placetype":"venue"
},
  "geometry": {"coordinates":[16.4649505615,48.220615387],"type":"Point"}
}