{
  "type": "Feature",
  "properties": {
    "addr:full":"Schwarzenbergpl Wien Wien 1040",
    "addr:postcode":"1040",
    "iso:country":"AT",
    "sg:address":"Schwarzenbergpl",
    "sg:city":"Wien",
    "sg:orig_category":"Non-Classified Establishments",
    "sg:phone":"+43 4315 053440",
    "sg:postcode":"1040",
    "sg:province":"Wien",
    "wof:name":"TAXI-TEL Standplatztelefon Betriebs GmbH",
    "wof:placetype":"venue"
},
  "geometry": {"coordinates":[16.375120163,48.1977043152],"type":"Point"}
}