{
  "type": "Feature",
  "properties": {
    "addr:full":"Hauptstr 13 Altenmarkt-Thenneberg Nieder\u00f6sterreich 2571",
    "addr:housenumber":"13",
    "addr:postcode":"2571",
    "addr:street":"Hauptstr;Niederoesterreich",
    "iso:country":"AT",
    "sg:address":"Hauptstr 13",
    "sg:city":"Altenmarkt-Thenneberg",
    "sg:orig_category":"Banken U Sparkassen",
    "sg:phone":"+43 2673 2267",
    "sg:postcode":"2571",
    "sg:province":"Nieder\u00f6sterreich",
    "wof:name":"Raiffeisenkasse Oberes Triestingtal regGenmbH",
    "wof:placetype":"venue"
},
  "geometry": {"coordinates":[15.9934597015,48.0158500671],"type":"Point"}
}