{
  "type": "Feature",
  "properties": {
    "addr:full":"Wiener Str 46 Kapfenberg Steiermark 8605",
    "addr:postcode":"8605",
    "addr:street":"46",
    "iso:country":"AT",
    "sg:address":"Wiener Str 46",
    "sg:city":"Kapfenberg",
    "sg:orig_category":"Beratungsstellen",
    "sg:phone":"+43 3862 24957",
    "sg:postcode":"8605",
    "sg:province":"Steiermark",
    "wof:name":"Institut f Familienberatung und Psychotherapie d Di\u00f6zese Graz-Seckau",
    "wof:placetype":"venue"
},
  "geometry": {"coordinates":[15.2918567657,47.4439163208],"type":"Point"}
}