{
  "type": "Feature",
  "properties": {
    "iso:country":"AT",
    "sg:address":"Schulstr 2",
    "sg:city":"Wolfurt",
    "sg:orig_category":"Bibliotheken",
    "sg:phone":"+43 5574 6840406",
    "sg:postcode":"6922",
    "sg:province":"Vorarlberg",
    "wof:name":"B\u00fccherei d Marktgemeinde Wolfurt",
    "wof:placetype":"venue"
},
  "geometry": {"coordinates":[9.7491483688,47.4666252136],"type":"Point"}
}