{
  "type": "Feature",
  "properties": {
    "addr:full":"Laxenburger Str 39 Wien Wien 1100",
    "addr:housenumber":"39",
    "addr:postcode":"1100",
    "addr:street":"Laxenburger Str",
    "iso:country":"AT",
    "sg:address":"Laxenburger Str 39",
    "sg:city":"Wien",
    "sg:orig_category":"Eissalons",
    "sg:phone":"+43 1 6043193",
    "sg:postcode":"1100",
    "sg:province":"Wien",
    "wof:name":"Gavaz Dario",
    "wof:placetype":"venue"
},
  "geometry": {"coordinates":[16.3740367889,48.179599762],"type":"Point"}
}