{
  "type": "Feature",
  "properties": {
    "addr:full":"Tschurtschenthalerstr 6 Innsbruck Tirol 6020",
    "addr:housenumber":"6",
    "addr:postcode":"6020",
    "addr:street":"Tschurtschenthalerstr;Tirol",
    "iso:country":"AT",
    "sg:address":"Tschurtschenthalerstr 6",
    "sg:city":"Innsbruck",
    "sg:orig_category":"Werbeagenturen",
    "sg:phone":"+43 4351 2564477",
    "sg:postcode":"6020",
    "sg:province":"Tirol",
    "sg:website":"imagehaus.at",
    "wof:name":"Imagehaus Konzept & Design",
    "wof:placetype":"venue"
},
  "geometry": {"coordinates":[11.4001541138,47.2739868164],"type":"Point"}
}