{
  "type": "Feature",
  "properties": {
    "iso:country":"AT",
    "sg:address":"Nr 30",
    "sg:city":"Mauerbach",
    "sg:orig_category":"Badezimmer U Badezimmereinrichtungen",
    "sg:phone":"+43 4322 732291",
    "sg:postcode":"3001",
    "sg:province":"Nieder\u00f6sterreich",
    "wof:name":"Wiba Innenraum-Einrichtungen HandelsgesmbH",
    "wof:placetype":"venue"
},
  "geometry": {"coordinates":[16.1678390503,48.2454948425],"type":"Point"}
}