{
  "type": "Feature",
  "properties": {
    "addr:full":"Steinpichl 6 Wartberg ob der Aist Ober\u00f6sterreich 4224",
    "addr:housenumber":"6",
    "addr:postcode":"4224",
    "addr:street":"Steinpichl",
    "iso:country":"AT",
    "sg:address":"Steinpichl 6",
    "sg:city":"Wartberg ob der Aist",
    "sg:orig_category":"Elektroinstallationsunternehmen",
    "sg:phone":"+43 7236 3193",
    "sg:postcode":"4224",
    "sg:province":"Ober\u00f6sterreich",
    "wof:name":"Hochedlinger Karl",
    "wof:placetype":"venue"
},
  "geometry": {"coordinates":[14.5113220215,48.3448448181],"type":"Point"}
}