{
  "type": "Feature",
  "properties": {
    "addr:full":"Hirschenwirtstr 17 Klagenfurt K\u00e4rnten 9020",
    "addr:housenumber":"17",
    "addr:postcode":"9020",
    "addr:street":"Hirschenwirtstr;Kaernten",
    "iso:country":"AT",
    "sg:address":"Hirschenwirtstr 17",
    "sg:city":"Klagenfurt",
    "sg:orig_category":"Non-Classified Establishments",
    "sg:phone":"+43 463 21130",
    "sg:postcode":"9020",
    "sg:province":"K\u00e4rnten",
    "wof:name":"Kirche Jesu Christi der Heiligen der letzten Tage",
    "wof:placetype":"venue"
},
  "geometry": {"coordinates":[14.2977209091,46.6104812622],"type":"Point"}
}