{
  "type": "Feature",
  "properties": {
    "iso:country":"AT",
    "sg:address":"Engerthstrasse 232-238",
    "sg:city":"Wien",
    "sg:orig_category":"Sewage Pumping Stations, Turnkey",
    "sg:phone":"+43 1 72802620",
    "sg:postcode":"1020",
    "sg:province":"Wien",
    "sg:website":"jung-pumpen.at",
    "wof:name":"Jung Pumpen Handelsges.m.b.H.",
    "wof:placetype":"venue"
},
  "geometry": {"coordinates":[16.4201583862,48.2120285034],"type":"Point"}
}