{
  "type": "Feature",
  "properties": {
    "iso:country":"AT",
    "sg:address":"Hauptstr 3",
    "sg:city":"Sch\u00f6rfling am Attersee",
    "sg:classifiers":[
        {
            "category":"Restaurant",
            "type":"Food & Drink"
        }
    ],
    "sg:phone":"+43 4376 6229292",
    "sg:postcode":"4861",
    "sg:province":"Ober\u00f6sterreich",
    "sg:tags":[
        "pizzeria"
    ],
    "wof:name":"Pizzeria Castiglione",
    "wof:placetype":"venue"
},
  "geometry": {"coordinates":[13.5953035355,47.9469032288],"type":"Point"}
}