{
  "type": "Feature",
  "properties": {
    "addr:full":"Unterm\u00f6schach 12 Hermagor K\u00e4rnten 9620",
    "addr:housenumber":"12",
    "addr:postcode":"9620",
    "addr:street":"Untermoeschach;Kaernten",
    "iso:country":"AT",
    "sg:address":"Unterm\u00f6schach 12",
    "sg:city":"Hermagor",
    "sg:classifiers":[
        {
            "category":"Manufacturing",
            "subcategory":"Wood Products",
            "type":"Manufacturing & Wholesale Goods"
        }
    ],
    "sg:phone":"+43 4282 2133",
    "sg:postcode":"9620",
    "sg:province":"K\u00e4rnten",
    "sg:tags":[
        "gate",
        "made",
        "door"
    ],
    "wof:name":"Tischlerei Jost KEG",
    "wof:placetype":"venue"
},
  "geometry": {"coordinates":[13.3710899353,46.6263885498],"type":"Point"}
}