{
  "type": "Feature",
  "properties": {
    "iso:country":"AT",
    "sg:address":"Oswaldg 84",
    "sg:city":"Weitra",
    "sg:orig_category":"Papier- U Schreibwaren / Einzelhandel",
    "sg:phone":"+43 4328 562277",
    "sg:postcode":"3970",
    "sg:province":"Nieder\u00f6sterreich",
    "wof:name":"Janetschek Christian Ing",
    "wof:placetype":"venue"
},
  "geometry": {"coordinates":[14.8928060532,48.7005844116],"type":"Point"}
}