{
  "type": "Feature",
  "properties": {
    "addr:full":"Harrachg 22 Graz Steiermark 8010",
    "addr:housenumber":"22",
    "addr:postcode":"8010",
    "addr:street":"Harrachg",
    "iso:country":"AT",
    "sg:address":"Harrachg 22",
    "sg:city":"Graz",
    "sg:orig_category":"Versicherungsunternehmen",
    "sg:phone":"+43 316 3825880",
    "sg:postcode":"8010",
    "sg:province":"Steiermark",
    "wof:name":"Gerling-Gruppe Versicherungs-Service GmbH",
    "wof:placetype":"venue"
},
  "geometry": {"coordinates":[15.4472360611,47.0766448975],"type":"Point"}
}