{
  "type": "Feature",
  "properties": {
    "addr:full":"Vilzbach 2  Neukirchen am Walde Ober\u00f6sterreich 4724",
    "addr:housenumber":"2",
    "addr:postcode":"4724",
    "addr:street":"Vilzbach",
    "iso:country":"AT",
    "sg:address":"Vilzbach 2 ",
    "sg:city":"Neukirchen am Walde",
    "sg:classifiers":[
        {
            "category":"Building & Trades",
            "subcategory":"Cleaning & Sanitation",
            "type":"Services"
        }
    ],
    "sg:phone":"+43 7278 3340",
    "sg:postcode":"4724",
    "sg:province":"Ober\u00f6sterreich",
    "sg:tags":[
        "carpet"
    ],
    "sg:website":"www.krempl.at",
    "wof:name":"Krempl Geb\u00e4udereinigung",
    "wof:placetype":"venue"
},
  "geometry": {"coordinates":[13.7808732986,48.4049911499],"type":"Point"}
}