{
  "type": "Feature",
  "properties": {
    "iso:country":"AT",
    "sg:address":"Altmannsdorfer Str 154-156",
    "sg:city":"Wien",
    "sg:orig_category":"Digitaldruck",
    "sg:phone":"+43 4316 61226414",
    "sg:postcode":"1230",
    "sg:province":"Wien",
    "wof:name":"digidee Inovamedia Print u Medien GmbH",
    "wof:placetype":"venue"
},
  "geometry": {"coordinates":[16.3198356628,48.153553009],"type":"Point"}
}