{
  "type": "Feature",
  "properties": {
    "addr:full":"Wieselburger Str 8 Gresten Nieder\u00f6sterreich 3264",
    "addr:housenumber":"8",
    "addr:postcode":"3264",
    "addr:street":"Str",
    "iso:country":"AT",
    "sg:address":"Wieselburger Str 8",
    "sg:city":"Gresten",
    "sg:orig_category":"Hafnereien",
    "sg:phone":"+43 7487 2065",
    "sg:postcode":"3264",
    "sg:province":"Nieder\u00f6sterreich",
    "wof:name":"Stockinger Stefan",
    "wof:placetype":"venue"
},
  "geometry": {"coordinates":[15.0241718292,47.987953186],"type":"Point"}
}