{
  "type": "Feature",
  "properties": {
    "addr:full":"Moosstr 35 Salzburg Salzburg 5020",
    "addr:housenumber":"35",
    "addr:postcode":"5020",
    "addr:street":"Moosstr;Salzburg",
    "iso:country":"AT",
    "sg:address":"Moosstr 35",
    "sg:city":"Salzburg",
    "sg:orig_category":"Fotografen",
    "sg:phone":"+43 662 830071",
    "sg:postcode":"5020",
    "sg:province":"Salzburg",
    "wof:name":"Lindner Elfriede",
    "wof:placetype":"venue"
},
  "geometry": {"coordinates":[13.0275268555,47.7887306213],"type":"Point"}
}