{
  "type": "Feature",
  "properties": {
    "addr:full":"Wiener Str 24 Loosdorf Nieder\u00f6sterreich 3382",
    "addr:postcode":"3382",
    "addr:street":"Loosdorf",
    "iso:country":"AT",
    "sg:address":"Wiener Str 24",
    "sg:city":"Loosdorf",
    "sg:orig_category":"Bauunternehmen",
    "sg:phone":"+43 2754 64730",
    "sg:postcode":"3382",
    "sg:province":"Nieder\u00f6sterreich",
    "wof:name":"Lang und Menhofer BaugmbH & Co KG",
    "wof:placetype":"venue"
},
  "geometry": {"coordinates":[15.3811845779,48.1837120056],"type":"Point"}
}