{
  "type": "Feature",
  "properties": {
    "addr:full":"M\u00fchlg 2 Tattendorf Nieder\u00f6sterreich 2523",
    "addr:housenumber":"2",
    "addr:postcode":"2523",
    "addr:street":"Muehlg",
    "iso:country":"AT",
    "sg:address":"M\u00fchlg 2",
    "sg:city":"Tattendorf",
    "sg:orig_category":"Weine / Einzelhandel",
    "sg:phone":"+43 2253 81290",
    "sg:postcode":"2523",
    "sg:province":"Nieder\u00f6sterreich",
    "wof:name":"Kollenhofer Johann",
    "wof:placetype":"venue"
},
  "geometry": {"coordinates":[16.3026027679,47.9566307068],"type":"Point"}
}