{
  "type": "Feature",
  "properties": {
    "addr:full":"Oberstrahlbach 72 Zwettl Nieder\u00f6sterreich 3910",
    "addr:housenumber":"72",
    "addr:postcode":"3910",
    "addr:street":"Oberstrahlbach;Niederoesterreich",
    "iso:country":"AT",
    "sg:address":"Oberstrahlbach 72",
    "sg:city":"Zwettl",
    "sg:orig_category":"Biotopes",
    "sg:phone":"+43 664 1915519",
    "sg:postcode":"3910",
    "sg:province":"Nieder\u00f6sterreich",
    "sg:website":"gartentraum.at",
    "wof:name":"Galerteich Haneder",
    "wof:placetype":"venue"
},
  "geometry": {"coordinates":[15.1114807129,48.6435203552],"type":"Point"}
}