{
  "type": "Feature",
  "properties": {
    "addr:full":"Grafendorfer Str 1 Friesach K\u00e4rnten 9360",
    "addr:housenumber":"1",
    "addr:postcode":"9360",
    "addr:street":"Str;Kaernten",
    "iso:country":"AT",
    "sg:address":"Grafendorfer Str 1",
    "sg:city":"Friesach",
    "sg:orig_category":"Gewerkschaften",
    "sg:phone":"+43 4268 2552",
    "sg:postcode":"9360",
    "sg:province":"K\u00e4rnten",
    "wof:name":"\u00f6sterreichischer Gewerkschaftsbund",
    "wof:placetype":"venue"
},
  "geometry": {"coordinates":[14.4121608734,46.9512023926],"type":"Point"}
}