{
  "type": "Feature",
  "properties": {
    "addr:full":"Konrad-Seyde-Str 2 Eugendorf Salzburg 5301",
    "addr:housenumber":"2",
    "addr:postcode":"5301",
    "addr:street":"Konrad-Seyde-Str;Salzburg",
    "iso:country":"AT",
    "sg:address":"Konrad-Seyde-Str 2",
    "sg:city":"Eugendorf",
    "sg:orig_category":"Blumeneinzelhandel",
    "sg:phone":"+43 6225 7211",
    "sg:postcode":"5301",
    "sg:province":"Salzburg",
    "wof:name":"Blumen Reisner",
    "wof:placetype":"venue"
},
  "geometry": {"coordinates":[13.1224050522,47.8660163879],"type":"Point"}
}