{
  "type": "Feature",
  "properties": {
    "addr:full":"Sportplatzstr 8 Ebreichsdorf Nieder\u00f6sterreich 2483",
    "addr:housenumber":"8",
    "addr:postcode":"2483",
    "addr:street":"Sportplatzstr",
    "iso:country":"AT",
    "sg:address":"Sportplatzstr 8",
    "sg:city":"Ebreichsdorf",
    "sg:orig_category":"Garten- U Landschaftsgestaltung",
    "sg:phone":"+43 4322 5474544",
    "sg:postcode":"2483",
    "sg:province":"Nieder\u00f6sterreich",
    "wof:name":"B & S Gartenbau u Hydrokultur GesmbH",
    "wof:placetype":"venue"
},
  "geometry": {"coordinates":[16.4009456635,47.9600486755],"type":"Point"}
}