{
  "type": "Feature",
  "properties": {
    "addr:full":"Hauptpl 2 Neulengbach Nieder\u00f6sterreich 3040",
    "addr:housenumber":"2",
    "addr:postcode":"3040",
    "addr:street":"Hauptpl",
    "iso:country":"AT",
    "sg:address":"Hauptpl 2",
    "sg:city":"Neulengbach",
    "sg:orig_category":"Gerichte",
    "sg:phone":"+43 2772 525810",
    "sg:postcode":"3040",
    "sg:province":"Nieder\u00f6sterreich",
    "wof:name":"Bezirksgericht Neulengbach",
    "wof:placetype":"venue"
},
  "geometry": {"coordinates":[15.908039093,48.198425293],"type":"Point"}
}