{
  "type": "Feature",
  "properties": {
    "addr:full":"Untere Viaduktg 45 Wien Wien 1030",
    "addr:housenumber":"45",
    "addr:postcode":"1030",
    "addr:street":"Untere Viaduktg",
    "iso:country":"AT",
    "sg:address":"Untere Viaduktg 45",
    "sg:city":"Wien",
    "sg:classifiers":[
        {
            "category":"Restaurant",
            "type":"Food & Drink"
        }
    ],
    "sg:phone":"+43 4317 133828",
    "sg:postcode":"1030",
    "sg:province":"Wien",
    "sg:website":"stadtwirt.at",
    "wof:name":"Gasthaus Stadtwirt",
    "wof:placetype":"venue"
},
  "geometry": {"coordinates":[16.3877105713,48.207244873],"type":"Point"}
}