{
  "type": "Feature",
  "properties": {
    "iso:country":"AT",
    "sg:address":"Waltersdorfer Str 67",
    "sg:city":"Judenburg",
    "sg:orig_category":"Tanzcafes",
    "sg:phone":"+43 3572 82910",
    "sg:postcode":"8750",
    "sg:province":"Steiermark",
    "wof:name":"Tanzcafe Memory",
    "wof:placetype":"venue"
},
  "geometry": {"coordinates":[14.6552762985,47.1776733398],"type":"Point"}
}