{
  "type": "Feature",
  "properties": {
    "addr:full":"Bundesstr 18 Schwarzenau Nieder\u00f6sterreich 3900",
    "addr:housenumber":"18",
    "addr:postcode":"3900",
    "addr:street":"Bundesstr",
    "iso:country":"AT",
    "sg:address":"Bundesstr 18",
    "sg:city":"Schwarzenau",
    "sg:orig_category":"Lebensmittel / Einzelhandel",
    "sg:phone":"+43 2849 2042",
    "sg:postcode":"3900",
    "sg:province":"Nieder\u00f6sterreich",
    "wof:name":"Bauernladen f\u00fcrs Wochenende",
    "wof:placetype":"venue"
},
  "geometry": {"coordinates":[15.2599096298,48.743057251],"type":"Point"}
}