{
  "type": "Feature",
  "properties": {
    "addr:full":"Gabelsberger Str 7 Wels Ober\u00f6sterreich 4600",
    "addr:housenumber":"7",
    "addr:postcode":"4600",
    "addr:street":"Str;Oberoesterreich",
    "iso:country":"AT",
    "sg:address":"Gabelsberger Str 7",
    "sg:city":"Wels",
    "sg:orig_category":"Werbeagenturen",
    "sg:phone":"+43 7242 52802",
    "sg:postcode":"4600",
    "sg:province":"Ober\u00f6sterreich",
    "wof:name":"imageprofiler media & communications gmbH",
    "wof:placetype":"venue"
},
  "geometry": {"coordinates":[13.9685125351,48.1398696899],"type":"Point"}
}