{
  "type": "Feature",
  "properties": {
    "iso:country":"AT",
    "sg:address":"Nr 61",
    "sg:city":"Lienz",
    "sg:orig_category":"Bauunternehmen",
    "sg:phone":"+43 4852 64500",
    "sg:postcode":"9900",
    "sg:province":"Tirol",
    "wof:name":"STRABAG AG",
    "wof:placetype":"venue"
},
  "geometry": {"coordinates":[12.7304296494,46.8440513611],"type":"Point"}
}