{
  "type": "Feature",
  "properties": {
    "addr:full":"Annaburg 7 Mariazell Steiermark 8630",
    "addr:housenumber":"7",
    "addr:postcode":"8630",
    "addr:street":"Annaburg",
    "iso:country":"AT",
    "sg:address":"Annaburg 7",
    "sg:city":"Mariazell",
    "sg:classifiers":[
        {
            "category":"Sports & Exercise",
            "subcategory":"Playing Field",
            "type":"Entertainment"
        }
    ],
    "sg:phone":"+43 4338 8220820",
    "sg:postcode":"8630",
    "sg:province":"Steiermark",
    "sg:tags":[
        "game"
    ],
    "wof:name":"LEDACOLOR GMBH",
    "wof:placetype":"venue"
},
  "geometry": {"coordinates":[15.3150863647,47.765499115],"type":"Point"}
}