{
  "type": "Feature",
  "properties": {
    "addr:full":"Hauptpl 6 Neulengbach Nieder\u00f6sterreich 3040",
    "addr:housenumber":"6",
    "addr:postcode":"3040",
    "addr:street":"Hauptpl",
    "iso:country":"AT",
    "sg:address":"Hauptpl 6",
    "sg:city":"Neulengbach",
    "sg:orig_category":"Biologische Produkte",
    "sg:phone":"+43 2772 51752",
    "sg:postcode":"3040",
    "sg:province":"Nieder\u00f6sterreich",
    "wof:name":"Eva's Naturkost-Kr\u00e4uterladen",
    "wof:placetype":"venue"
},
  "geometry": {"coordinates":[15.908039093,48.198425293],"type":"Point"}
}