{
  "type": "Feature",
  "properties": {
    "addr:full":"Hauptpl 2 Pulkau Nieder\u00f6sterreich 3741",
    "addr:housenumber":"2",
    "addr:postcode":"3741",
    "addr:street":"Hauptpl",
    "iso:country":"AT",
    "sg:address":"Hauptpl 2",
    "sg:city":"Pulkau",
    "sg:orig_category":"Rohrreinigung",
    "sg:phone":"+43 2946 2680",
    "sg:postcode":"3741",
    "sg:province":"Nieder\u00f6sterreich",
    "wof:name":"SHS - Ing Geist GesmbH",
    "wof:placetype":"venue"
},
  "geometry": {"coordinates":[15.8613500595,48.704624176],"type":"Point"}
}