{
  "type": "Feature",
  "properties": {
    "addr:full":"Speckbacherg 2 Wien Wien 1160",
    "addr:housenumber":"2",
    "addr:postcode":"1160",
    "addr:street":"Speckbacherg",
    "iso:country":"AT",
    "sg:address":"Speckbacherg 2",
    "sg:city":"Wien",
    "sg:orig_category":"Filmproduktionen",
    "sg:phone":"+43 1 4893349",
    "sg:postcode":"1160",
    "sg:province":"Wien",
    "wof:name":"J\u00e4ger Gert G\u00fcnter",
    "wof:placetype":"venue"
},
  "geometry": {"coordinates":[16.3160438538,48.2134552002],"type":"Point"}
}