{
  "type": "Feature",
  "properties": {
    "addr:full":"Nr 257 Bad Goisern Ober\u00f6sterreich 4822",
    "addr:postcode":"4822",
    "addr:street":"Nr",
    "iso:country":"AT",
    "sg:address":"Nr 257",
    "sg:city":"Bad Goisern",
    "sg:orig_category":"Rettungsdienste",
    "sg:phone":"+43 6135 8961",
    "sg:postcode":"4822",
    "sg:province":"Ober\u00f6sterreich",
    "wof:name":"\u00d6sterreichische Wasser-Rettung Einsatzleitung Bad Goisern",
    "wof:placetype":"venue"
},
  "geometry": {"coordinates":[13.6164741516,47.6411628723],"type":"Point"}
}