{
  "type": "Feature",
  "properties": {
    "iso:country":"AT",
    "sg:address":"Holzerhofstr 81",
    "sg:city":"Hart",
    "sg:orig_category":"Telekommunikation",
    "sg:phone":"+43 699 10118888",
    "sg:postcode":"8075",
    "sg:province":"Steiermark",
    "wof:name":"Unterhuber & Partner KEG",
    "wof:placetype":"venue"
},
  "geometry": {"coordinates":[15.5200986862,47.0566978455],"type":"Point"}
}