{
  "type": "Feature",
  "properties": {
    "addr:full":"Aug 77 G\u00f6sting Steiermark 8051",
    "addr:housenumber":"77",
    "addr:postcode":"8051",
    "addr:street":"Aug",
    "iso:country":"AT",
    "sg:address":"Aug 77",
    "sg:city":"G\u00f6sting",
    "sg:orig_category":"Apotheken",
    "sg:phone":"+43 316 6842660",
    "sg:postcode":"8051",
    "sg:province":"Steiermark",
    "wof:name":"Kalvarien-Apotheke",
    "wof:placetype":"venue"
},
  "geometry": {"coordinates":[15.3543653488,47.0787315369],"type":"Point"}
}