{
  "type": "Feature",
  "properties": {
    "addr:full":"Dr.-Robert-Koch-G 10 Klagenfurt K\u00e4rnten 9020",
    "addr:housenumber":"10",
    "addr:postcode":"9020",
    "addr:street":"Dr.-Robert-Koch-G;Kaernten",
    "iso:country":"AT",
    "sg:address":"Dr.-Robert-Koch-G 10",
    "sg:city":"Klagenfurt",
    "sg:orig_category":"Lebensmittel / Einzelhandel",
    "sg:phone":"+43 463 418089",
    "sg:postcode":"9020",
    "sg:province":"K\u00e4rnten",
    "wof:name":"Spar Markt - Burkot & Kossarnig OHG",
    "wof:placetype":"venue"
},
  "geometry": {"coordinates":[14.3268613815,46.6323204041],"type":"Point"}
}