{
  "type": "Feature",
  "properties": {
    "iso:country":"AT",
    "sg:address":"Wiener Str 12",
    "sg:city":"Krems an der Donau",
    "sg:classifiers":[
        {
            "category":"Travel",
            "subcategory":"Hotels & Motels",
            "type":"Entertainment"
        }
    ],
    "sg:phone":"+43 2732 869600",
    "sg:postcode":"3500",
    "sg:province":"Nieder\u00f6sterreich",
    "wof:name":"Klinglhuber Seminarhotel",
    "wof:placetype":"venue"
},
  "geometry": {"coordinates":[15.6072158813,48.4126968384],"type":"Point"}
}