{
  "type": "Feature",
  "properties": {
    "addr:full":"Neunkirchner Str 35 Puchberg am Schneeberg Nieder\u00f6sterreich 2734",
    "addr:housenumber":"35",
    "addr:postcode":"2734",
    "addr:street":"Str",
    "iso:country":"AT",
    "sg:address":"Neunkirchner Str 35",
    "sg:city":"Puchberg am Schneeberg",
    "sg:orig_category":"Behinderungen / Leben Mit Behinderungen",
    "sg:phone":"+43 4326 3623470",
    "sg:postcode":"2734",
    "sg:province":"Nieder\u00f6sterreich",
    "wof:name":"Lebenshilfe N\u00f6 Gemeinn\u00fctzige GmbH",
    "wof:placetype":"venue"
},
  "geometry": {"coordinates":[15.9168634415,47.783706665],"type":"Point"}
}