{
  "type": "Feature",
  "properties": {
    "addr:full":"Grie\u00dfen 46 Leogang Salzburg 5771",
    "addr:housenumber":"46",
    "addr:postcode":"5771",
    "addr:street":"Griessen;Salzburg",
    "iso:country":"AT",
    "sg:address":"Grie\u00dfen 46",
    "sg:city":"Leogang",
    "sg:classifiers":[
        {
            "category":"Home & Garden",
            "subcategory":"Building Materials",
            "type":"Retail Goods"
        }
    ],
    "sg:phone":"+43 6583 72890",
    "sg:postcode":"5771",
    "sg:province":"Salzburg",
    "sg:tags":[
        "gravel",
        "crushed"
    ],
    "wof:name":"Ruperti Beton GmbH",
    "wof:placetype":"venue"
},
  "geometry": {"coordinates":[12.7606391907,47.4386634827],"type":"Point"}
}