{
  "type": "Feature",
  "properties": {
    "addr:full":"Nr 193a F\u00fcrstenfeld Steiermark 8280",
    "addr:housenumber":"193a",
    "addr:postcode":"8280",
    "addr:street":"Nr",
    "iso:country":"AT",
    "sg:address":"Nr 193a",
    "sg:city":"F\u00fcrstenfeld",
    "sg:orig_category":"Lebensmittel / Einzelhandel",
    "sg:phone":"+43 3382 512480",
    "sg:postcode":"8280",
    "sg:province":"Steiermark",
    "wof:name":"Unimarkt HandelsgesmbH & Co KG",
    "wof:placetype":"venue"
},
  "geometry": {"coordinates":[16.0748786926,47.0515441895],"type":"Point"}
}