{
  "type": "Feature",
  "properties": {
    "addr:full":"Schwarzenbergpl 9 Wien Wien 1030",
    "addr:housenumber":"9",
    "addr:postcode":"1030",
    "addr:street":"Schwarzenbergpl",
    "iso:country":"AT",
    "sg:address":"Schwarzenbergpl 9",
    "sg:city":"Wien",
    "sg:classifiers":[
        {
            "category":"Travel",
            "subcategory":"Hotels & Motels",
            "type":"Entertainment"
        }
    ],
    "sg:phone":"+43 1 79845150",
    "sg:postcode":"1030",
    "sg:province":"Wien",
    "wof:name":"Palais Schwarzenberg",
    "wof:placetype":"venue"
},
  "geometry": {"coordinates":[16.3754291534,48.1977500916],"type":"Point"}
}