{
  "type": "Feature",
  "properties": {
    "addr:full":"Josef Rauter-Str 49 Villach K\u00e4rnten 9500",
    "addr:housenumber":"49",
    "addr:postcode":"9500",
    "addr:street":"Kaernten",
    "iso:country":"AT",
    "sg:address":"Josef Rauter-Str 49",
    "sg:city":"Villach",
    "sg:orig_category":"Musikunterricht",
    "sg:phone":"+43 4242 53113",
    "sg:postcode":"9500",
    "sg:province":"K\u00e4rnten",
    "wof:name":"Musicus Keyboard- und Musikschule",
    "wof:placetype":"venue"
},
  "geometry": {"coordinates":[13.8142547607,46.6193618774],"type":"Point"}
}