{
  "type": "Feature",
  "properties": {
    "iso:country":"AT",
    "sg:address":"Salzburger Str 621",
    "sg:city":"Schladming",
    "sg:orig_category":"Friseure U Frisiersalons",
    "sg:phone":"+43 3687 23826",
    "sg:postcode":"8970",
    "sg:province":"Steiermark",
    "wof:name":"Friseur Renate",
    "wof:placetype":"venue"
},
  "geometry": {"coordinates":[13.6604976654,47.3911476135],"type":"Point"}
}