{
  "type": "Feature",
  "properties": {
    "iso:country":"AT",
    "sg:address":"Hietzinger Kai 89",
    "sg:city":"Wien",
    "sg:orig_category":"Installationsunternehmen",
    "sg:phone":"+43 1 8862759",
    "sg:postcode":"1130",
    "sg:province":"Wien",
    "wof:name":"B\u00e4dermeister Lugar - Installationen",
    "wof:placetype":"venue"
},
  "geometry": {"coordinates":[16.2911891937,48.1900978088],"type":"Point"}
}