{
  "type": "Feature",
  "properties": {
    "iso:country":"AT",
    "sg:address":"Nr 88",
    "sg:city":"Randegg",
    "sg:orig_category":"Zimmereien",
    "sg:phone":"+43 7487 50200",
    "sg:postcode":"3263",
    "sg:province":"Nieder\u00f6sterreich",
    "wof:name":"Mosser Leimholz GesmbH",
    "wof:placetype":"venue"
},
  "geometry": {"coordinates":[14.9729251862,48.0112915039],"type":"Point"}
}