{
  "type": "Feature",
  "properties": {
    "addr:full":"Johanniterg 6 Feldkirch Vorarlberg 6800",
    "addr:housenumber":"6",
    "addr:postcode":"6800",
    "addr:street":"Johanniterg",
    "iso:country":"AT",
    "sg:address":"Johanniterg 6",
    "sg:city":"Feldkirch",
    "sg:orig_category":"Mikrofilme",
    "sg:phone":"+43 5522 39654",
    "sg:postcode":"6800",
    "sg:province":"Vorarlberg",
    "wof:name":"ABF - Arbeitsinitiative f d Bezirk Feldkirch - Mikroverfilmung",
    "wof:placetype":"venue"
},
  "geometry": {"coordinates":[9.5965042114,47.2359199524],"type":"Point"}
}