{
  "type": "Feature",
  "properties": {
    "addr:full":"Hainfelder Str 14 Altenmarkt-Thenneberg Nieder\u00f6sterreich 2571",
    "addr:postcode":"2571",
    "addr:street":"Str 14 Altenmarkt-Thenneberg",
    "iso:country":"AT",
    "sg:address":"Hainfelder Str 14",
    "sg:city":"Altenmarkt-Thenneberg",
    "sg:orig_category":"Friseure U Frisiersalons",
    "sg:phone":"+43 4326 732157",
    "sg:postcode":"2571",
    "sg:province":"Nieder\u00f6sterreich",
    "wof:name":"Salon Maria Gadinger",
    "wof:placetype":"venue"
},
  "geometry": {"coordinates":[15.9934597015,48.0158500671],"type":"Point"}
}