{
  "type": "Feature",
  "properties": {
    "iso:country":"AT",
    "sg:address":"Hofferpl 9-11",
    "sg:city":"Wien",
    "sg:orig_category":"Bekleidung / Einzelhandel",
    "sg:phone":"+43 1 40986100",
    "sg:postcode":"1160",
    "sg:province":"Wien",
    "wof:name":"KBS Kleider Bauer Betriebs-GmbH",
    "wof:placetype":"venue"
},
  "geometry": {"coordinates":[16.3334064484,48.2095184326],"type":"Point"}
}