{
  "type": "Feature",
  "properties": {
    "addr:full":"Klagenfurter Str 16 St. Veit an der Glan K\u00e4rnten 9300",
    "addr:housenumber":"16",
    "addr:postcode":"9300",
    "addr:street":"Str;Kaernten",
    "iso:country":"AT",
    "sg:address":"Klagenfurter Str 16",
    "sg:city":"St. Veit an der Glan",
    "sg:classifiers":[
        {
            "category":"Restaurant",
            "type":"Food & Drink"
        }
    ],
    "sg:phone":"+43 4212 36246",
    "sg:postcode":"9300",
    "sg:province":"K\u00e4rnten",
    "sg:tags":[
        "pizzeria"
    ],
    "wof:name":"Donatello Gastst\u00e4ttenbetriebs GmbH & Co KEG",
    "wof:placetype":"venue"
},
  "geometry": {"coordinates":[14.3818511963,46.7486839294],"type":"Point"}
}