{
  "type": "Feature",
  "properties": {
    "iso:country":"AT",
    "sg:address":"Pluskaufstr 7",
    "sg:city":"Pasching",
    "sg:orig_category":"Damenmoden",
    "sg:phone":"+43 4372 2951385",
    "sg:postcode":"4061",
    "sg:province":"Ober\u00f6sterreich",
    "wof:name":"C & A Mode GesmbH & Co KG - C & A Mode",
    "wof:placetype":"venue"
},
  "geometry": {"coordinates":[14.2359104156,48.2444572449],"type":"Point"}
}