{
  "type": "Feature",
  "properties": {
    "iso:country":"AT",
    "sg:address":"Winkl 2",
    "sg:city":"St. Gilgen",
    "sg:orig_category":"Non-Classified Establishments",
    "sg:phone":"+43 6227 23180",
    "sg:postcode":"5340",
    "sg:province":"Salzburg",
    "wof:name":"Kloster Gut Aich",
    "wof:placetype":"venue"
},
  "geometry": {"coordinates":[13.3864688873,47.779964447],"type":"Point"}
}