{
  "type": "Feature",
  "properties": {
    "iso:country":"AT",
    "sg:address":"Leo-Slezak-G 9",
    "sg:city":"Wien",
    "sg:orig_category":"Bauunternehmen",
    "sg:phone":"+43 4319 254475",
    "sg:postcode":"1180",
    "sg:province":"Wien",
    "wof:name":"GRGIC Bau KEG",
    "wof:placetype":"venue"
},
  "geometry": {"coordinates":[16.3411140442,48.2185554504],"type":"Point"}
}