{
  "type": "Feature",
  "properties": {
    "iso:country":"AT",
    "sg:address":"S\u00fcdbahnstrasse 41",
    "sg:city":"Leobersdorf",
    "sg:classifiers":[
        {
            "category":"Manufacturing",
            "subcategory":"Chemicals & Compounds",
            "type":"Manufacturing & Wholesale Goods"
        }
    ],
    "sg:phone":"+43 2256 65516",
    "sg:postcode":"2544",
    "sg:province":"Nieder\u00f6sterreich",
    "sg:tags":[
        "analysis"
    ],
    "sg:website":"smk.co.at",
    "wof:name":"smk Me\u00df- und Umwelttechnik Handelsges.m.b.H.",
    "wof:placetype":"venue"
},
  "geometry": {"coordinates":[16.2165107727,47.9286613464],"type":"Point"}
}