{
  "type": "Feature",
  "properties": {
    "addr:full":"Frauentaler Str 5 Deutschlandsberg Steiermark 8530",
    "addr:housenumber":"5",
    "addr:postcode":"8530",
    "addr:street":"Str",
    "iso:country":"AT",
    "sg:address":"Frauentaler Str 5",
    "sg:city":"Deutschlandsberg",
    "sg:orig_category":"Boutiquen",
    "sg:phone":"+43 3462 30442",
    "sg:postcode":"8530",
    "sg:province":"Steiermark",
    "wof:name":"Boutique Raffinesse",
    "wof:placetype":"venue"
},
  "geometry": {"coordinates":[15.2165746689,46.8167877197],"type":"Point"}
}