{
  "type": "Feature",
  "properties": {
    "addr:full":"Benediktinerpl 7/1 Klagenfurt K\u00e4rnten 9020",
    "addr:housenumber":"7 / 1",
    "addr:postcode":"9020",
    "addr:street":"Benediktinerpl;Kaernten",
    "iso:country":"AT",
    "sg:address":"Benediktinerpl 7/1",
    "sg:city":"Klagenfurt",
    "sg:orig_category":"\u00c3\u201erzte / F Allgemeinmedizin",
    "sg:phone":"+43 4366 44061188",
    "sg:postcode":"9020",
    "sg:province":"K\u00e4rnten",
    "wof:name":"Fasching Ute Dr",
    "wof:placetype":"venue"
},
  "geometry": {"coordinates":[14.3069400787,46.622844696],"type":"Point"}
}