{
  "type": "Feature",
  "properties": {
    "iso:country":"AT",
    "sg:address":"Schubertpl 13",
    "sg:city":"Gm\u00fcnd",
    "sg:orig_category":"Blumeneinzelhandel",
    "sg:phone":"+43 2852 51462",
    "sg:postcode":"3950",
    "sg:province":"Nieder\u00f6sterreich",
    "wof:name":"Kaltenb\u00f6ck Thomas Peter",
    "wof:placetype":"venue"
},
  "geometry": {"coordinates":[14.972281456,48.7615432739],"type":"Point"}
}