{
  "type": "Feature",
  "properties": {
    "addr:full":"Zur Spinnerin 45 Wien Wien 1100",
    "addr:housenumber":"45",
    "addr:postcode":"1100",
    "addr:street":"Zur Spinnerin",
    "iso:country":"AT",
    "sg:address":"Zur Spinnerin 45",
    "sg:city":"Wien",
    "sg:orig_category":"Fu\u00c3\u0178pflege U Fu\u00c3\u0178pflegesalons",
    "sg:phone":"+43 1 6060137",
    "sg:postcode":"1100",
    "sg:province":"Wien",
    "wof:name":"Radl Christine",
    "wof:placetype":"venue"
},
  "geometry": {"coordinates":[16.3543243408,48.1719017029],"type":"Point"}
}