{
  "type": "Feature",
  "properties": {
    "iso:country":"AT",
    "sg:address":"Nr 21",
    "sg:city":"St. P\u00f6lten",
    "sg:orig_category":"Feuerwehren",
    "sg:phone":"+43 2742 77357",
    "sg:postcode":"3100",
    "sg:province":"Nieder\u00f6sterreich",
    "wof:name":"Freiwillige Feuerwehr St P\u00f6lten - Pummersdorf",
    "wof:placetype":"venue"
},
  "geometry": {"coordinates":[15.6240940094,48.2076377869],"type":"Point"}
}