{
  "type": "Feature",
  "properties": {
    "addr:full":"Schwimmbadg 361 Altenmarkt im Pongau Salzburg 5541",
    "addr:housenumber":"361",
    "addr:postcode":"5541",
    "addr:street":"Salzburg",
    "iso:country":"AT",
    "sg:address":"Schwimmbadg 361",
    "sg:city":"Altenmarkt im Pongau",
    "sg:classifiers":[
        {
            "category":"Restaurant",
            "type":"Food & Drink"
        }
    ],
    "sg:phone":"+43 6452 7452",
    "sg:postcode":"5541",
    "sg:province":"Salzburg",
    "wof:name":"R\u00f6merkeller",
    "wof:placetype":"venue"
},
  "geometry": {"coordinates":[13.4227304459,47.3759117126],"type":"Point"}
}