{
  "type": "Feature",
  "properties": {
    "addr:full":"Lecher Stra\u00dfe Lech Vorarlberg 6764",
    "addr:postcode":"6764",
    "addr:street":"Lecher Strasse",
    "iso:country":"AT",
    "sg:address":"Lecher Stra\u00dfe",
    "sg:city":"Lech",
    "sg:orig_category":"Reisen, Tourismusinfo",
    "sg:postcode":"6764",
    "sg:province":"Vorarlberg",
    "sg:website":"http://www.hotelelisabeth.com",
    "wof:name":"Elisabeth Hotel",
    "wof:placetype":"venue"
},
  "geometry": {"coordinates":[10.1417798996,47.2082939148],"type":"Point"}
}