{
  "type": "Feature",
  "properties": {
    "addr:full":"XXXXXXXXXXXXXXXXXXXXXXXXX Wien Wien 1210",
    "addr:postcode":"1210",
    "iso:country":"AT",
    "sg:address":"XXXXXXXXXXXXXXXXXXXXXXXXX",
    "sg:city":"Wien",
    "sg:orig_category":"Freizeit, Hobbies U Vereine",
    "sg:postcode":"1210",
    "sg:province":"Wien",
    "sg:website":"energydrink.cjb.net/",
    "wof:name":"Energy-Drink Club 2000",
    "wof:placetype":"venue"
},
  "geometry": {"coordinates":[16.3978404999,48.2579994202],"type":"Point"}
}