{
  "type": "Feature",
  "properties": {
    "iso:country":"AT",
    "sg:address":"Nr 15",
    "sg:city":"Mariazell",
    "sg:orig_category":"Biologische Produkte",
    "sg:phone":"+43 3882 4533",
    "sg:postcode":"8630",
    "sg:province":"Steiermark",
    "wof:name":"Hofladen Naglhofer",
    "wof:placetype":"venue"
},
  "geometry": {"coordinates":[15.3180360794,47.7734832764],"type":"Point"}
}