{
  "type": "Feature",
  "properties": {
    "addr:full":"Peter-Pfenninger-Str 8 Salzburg Salzburg 5020",
    "addr:housenumber":"8",
    "addr:postcode":"5020",
    "addr:street":"Peter-Pfenninger-Str;Salzburg",
    "iso:country":"AT",
    "sg:address":"Peter-Pfenninger-Str 8",
    "sg:city":"Salzburg",
    "sg:orig_category":"Restaurants: Italienisch",
    "sg:phone":"+43 662 832413",
    "sg:postcode":"5020",
    "sg:province":"Salzburg",
    "wof:name":"Ristorante Ciccio",
    "wof:placetype":"venue"
},
  "geometry": {"coordinates":[13.0130548477,47.8194084167],"type":"Point"}
}