{
  "type": "Feature",
  "properties": {
    "addr:full":"Leonhardstr 99 Graz Steiermark 8010",
    "addr:housenumber":"99",
    "addr:postcode":"8010",
    "addr:street":"Leonhardstr",
    "iso:country":"AT",
    "sg:address":"Leonhardstr 99",
    "sg:city":"Graz",
    "sg:orig_category":"Friseure U Frisiersalons",
    "sg:phone":"+43 316 366143",
    "sg:postcode":"8010",
    "sg:province":"Steiermark",
    "wof:name":"Stiegler Josef",
    "wof:placetype":"venue"
},
  "geometry": {"coordinates":[15.4589948654,47.0756340027],"type":"Point"}
}