{
  "type": "Feature",
  "properties": {
    "addr:full":"Hackherg 7 Graz Steiermark 8020",
    "addr:housenumber":"7",
    "addr:postcode":"8020",
    "addr:street":"Hackherg",
    "iso:country":"AT",
    "sg:address":"Hackherg 7",
    "sg:city":"Graz",
    "sg:orig_category":"Webdesign",
    "sg:phone":"+43 4365 03444456",
    "sg:postcode":"8020",
    "sg:province":"Steiermark",
    "wof:name":"cyber - ideas GesbR Konrad Fr\u00f6tscher & Thomas Werth",
    "wof:placetype":"venue"
},
  "geometry": {"coordinates":[15.4206037521,47.082321167],"type":"Point"}
}