{
  "type": "Feature",
  "properties": {
    "iso:country":"AT",
    "sg:address":"Guntramser Str. 128 ",
    "sg:city":"Neunkirchen",
    "sg:classifiers":[
        {
            "category":"Building & Trades",
            "subcategory":"Construction",
            "type":"Services"
        }
    ],
    "sg:phone":"+43 4326 3563206",
    "sg:postcode":"2620",
    "sg:province":"Nieder\u00f6sterreich",
    "sg:tags":[
        "work",
        "public"
    ],
    "wof:name":"SWIETELSKY BAU GESMBH",
    "wof:placetype":"venue"
},
  "geometry": {"coordinates":[12.5209140778,50.6101646423],"type":"Point"}
}