{
  "type": "Feature",
  "properties": {
    "addr:full":"Haller Str 190 Innsbruck Tirol 6020",
    "addr:housenumber":"190",
    "addr:postcode":"6020",
    "addr:street":"Str;Tirol",
    "iso:country":"AT",
    "sg:address":"Haller Str 190",
    "sg:city":"Innsbruck",
    "sg:orig_category":"Freizeit- U Sportbekleidung",
    "sg:phone":"+43 4351 2261463",
    "sg:postcode":"6020",
    "sg:province":"Tirol",
    "wof:name":"Multessa Sportswear Brigitte Vajk",
    "wof:placetype":"venue"
},
  "geometry": {"coordinates":[11.4390583038,47.2763786316],"type":"Point"}
}