{
  "type": "Feature",
  "properties": {
    "addr:full":"Marktpl 14 Lembach im M\u00fchlkreis Ober\u00f6sterreich 4132",
    "addr:housenumber":"14",
    "addr:postcode":"4132",
    "addr:street":"Marktpl;Im Muehlkreis Oberoesterreich",
    "iso:country":"AT",
    "sg:address":"Marktpl 14",
    "sg:city":"Lembach im M\u00fchlkreis",
    "sg:orig_category":"Autolackierereien",
    "sg:phone":"+43 7286 82360",
    "sg:postcode":"4132",
    "sg:province":"Ober\u00f6sterreich",
    "wof:name":"Bauer Anton",
    "wof:placetype":"venue"
},
  "geometry": {"coordinates":[13.8948545456,48.4948387146],"type":"Point"}
}