{
  "type": "Feature",
  "properties": {
    "iso:country":"AT",
    "sg:address":"Sonnhalde 16",
    "sg:city":"Dornbirn",
    "sg:orig_category":"Rauchfangkehrer",
    "sg:phone":"+43 5572 25002",
    "sg:postcode":"6850",
    "sg:province":"Vorarlberg",
    "wof:name":"Baurenhas Wolfgang",
    "wof:placetype":"venue"
},
  "geometry": {"coordinates":[9.7446060181,47.3984489441],"type":"Point"}
}