{
  "type": "Feature",
  "properties": {
    "iso:country":"AT",
    "sg:address":"Schillerstr 8a",
    "sg:city":"Zell am See",
    "sg:orig_category":"Psychotherapie",
    "sg:phone":"+43 664 5217757",
    "sg:postcode":"5700",
    "sg:province":"Salzburg",
    "wof:name":"Gallner Renate Mag phil",
    "wof:placetype":"venue"
},
  "geometry": {"coordinates":[12.7950725555,47.3245353699],"type":"Point"}
}