{
  "type": "Feature",
  "properties": {
    "addr:full":"Brunnenfeldstr 15 Linz Ober\u00f6sterreich 4030",
    "addr:housenumber":"15",
    "addr:postcode":"4030",
    "addr:street":"Brunnenfeldstr",
    "iso:country":"AT",
    "sg:address":"Brunnenfeldstr 15",
    "sg:city":"Linz",
    "sg:orig_category":"Reinigungsbedarf U Reinigungsmittel",
    "sg:phone":"+43 732 301102",
    "sg:postcode":"4030",
    "sg:province":"Ober\u00f6sterreich",
    "wof:name":"Clean Tec GmbH",
    "wof:placetype":"venue"
},
  "geometry": {"coordinates":[14.3152618408,48.2643013],"type":"Point"}
}