{
  "type": "Feature",
  "properties": {
    "addr:full":"Walchsee Bundesstr 52a Niederndorf Tirol 6342",
    "addr:housenumber":"52a",
    "addr:postcode":"6342",
    "iso:country":"AT",
    "sg:address":"Walchsee Bundesstr 52a",
    "sg:city":"Niederndorf",
    "sg:orig_category":"Installationsunternehmen",
    "sg:phone":"+43 5373 611610",
    "sg:postcode":"6342",
    "sg:province":"Tirol",
    "wof:name":"Keiler Paul KG",
    "wof:placetype":"venue"
},
  "geometry": {"coordinates":[12.2459192276,47.6464080811],"type":"Point"}
}