{
  "type": "Feature",
  "properties": {
    "addr:full":"Diepersdorf 71 Wartberg an der Krems Ober\u00f6sterreich 4552",
    "addr:housenumber":"71",
    "addr:postcode":"4552",
    "addr:street":"Diepersdorf",
    "iso:country":"AT",
    "sg:address":"Diepersdorf 71",
    "sg:city":"Wartberg an der Krems",
    "sg:orig_category":"Erdarbeiten",
    "sg:phone":"+43 7587 7482",
    "sg:postcode":"4552",
    "sg:province":"Ober\u00f6sterreich",
    "wof:name":"Weinzinger Wolfgang",
    "wof:placetype":"venue"
},
  "geometry": {"coordinates":[14.1169452667,47.9891738892],"type":"Point"}
}