{
  "type": "Feature",
  "properties": {
    "addr:full":"Troststr 92 Wien Wien 1100",
    "addr:housenumber":"92",
    "addr:postcode":"1100",
    "addr:street":"Troststr",
    "iso:country":"AT",
    "sg:address":"Troststr 92",
    "sg:city":"Wien",
    "sg:orig_category":"Banken U Sparkassen",
    "sg:phone":"+43 4350 50533100",
    "sg:postcode":"1100",
    "sg:province":"Wien",
    "wof:name":"Bank Austria Creditanstalt AG",
    "wof:placetype":"venue"
},
  "geometry": {"coordinates":[16.3575191498,48.1713905334],"type":"Point"}
}