{
  "type": "Feature",
  "properties": {
    "iso:country":"AT",
    "sg:address":"Kuffern 43",
    "sg:city":"Statzendorf",
    "sg:orig_category":"Lebensmittel / Einzelhandel",
    "sg:phone":"+43 2786 2338",
    "sg:postcode":"3125",
    "sg:province":"Nieder\u00f6sterreich",
    "wof:name":"Harold Angela",
    "wof:placetype":"venue"
},
  "geometry": {"coordinates":[15.6513996124,48.3281211853],"type":"Point"}
}