{
  "type": "Feature",
  "properties": {
    "addr:full":"Wehrbachweg 17 Kirchberg in Tirol Tirol 6365",
    "addr:housenumber":"17",
    "addr:postcode":"6365",
    "addr:street":"Wehrbachweg;Tirol",
    "iso:country":"AT",
    "sg:address":"Wehrbachweg 17",
    "sg:city":"Kirchberg in Tirol",
    "sg:orig_category":"Physiotherapie",
    "sg:phone":"+43 5357 3762",
    "sg:postcode":"6365",
    "sg:province":"Tirol",
    "wof:name":"Schuler Christina Dipl-PT",
    "wof:placetype":"venue"
},
  "geometry": {"coordinates":[12.310874939,47.4531517029],"type":"Point"}
}