{
  "type": "Feature",
  "properties": {
    "addr:full":"Hauptstr 21 Pernitz Nieder\u00f6sterreich 2763",
    "addr:housenumber":"21",
    "addr:postcode":"2763",
    "addr:street":"Hauptstr",
    "iso:country":"AT",
    "sg:address":"Hauptstr 21",
    "sg:city":"Pernitz",
    "sg:orig_category":"Werbegrafik- U Grafik-Design",
    "sg:phone":"+43 4326 3273680",
    "sg:postcode":"2763",
    "sg:province":"Nieder\u00f6sterreich",
    "wof:name":"ENZO GRAFIK DESIGN",
    "wof:placetype":"venue"
},
  "geometry": {"coordinates":[15.966547966,47.8965187073],"type":"Point"}
}