{
  "type": "Feature",
  "properties": {
    "addr:full":"Angerstr 224 Wals Salzburg 5071",
    "addr:housenumber":"224",
    "addr:postcode":"5071",
    "addr:street":"Wals Salzburg",
    "iso:country":"AT",
    "sg:address":"Angerstr 224",
    "sg:city":"Wals",
    "sg:orig_category":"Betriebs- U Fernverpflegung",
    "sg:phone":"+43 662 8551800",
    "sg:postcode":"5071",
    "sg:province":"Salzburg",
    "wof:name":"Kantinenbetreuung GesmbH",
    "wof:placetype":"venue"
},
  "geometry": {"coordinates":[12.9826831818,47.8128356934],"type":"Point"}
}