{
  "type": "Feature",
  "properties": {
    "addr:full":"Unterrotte 83 St. Jakob in Defereggen Tirol 9963",
    "addr:housenumber":"83",
    "addr:postcode":"jakob;defereggen;9963",
    "addr:street":"Unterrotte",
    "iso:country":"AT",
    "sg:address":"Unterrotte 83",
    "sg:city":"St. Jakob in Defereggen",
    "sg:orig_category":"Speditionen",
    "sg:phone":"+43 4348 735221",
    "sg:postcode":"9963",
    "sg:province":"Tirol",
    "wof:name":"Gasser Bruno Fr\u00e4chterei u Erdbewegungs GesmbH",
    "wof:placetype":"venue"
},
  "geometry": {"coordinates":[12.3313846588,46.9159965515],"type":"Point"}
}