{
  "type": "Feature",
  "properties": {
    "iso:country":"AT",
    "sg:address":"Esterhazypl 6",
    "sg:city":"Eisenstadt",
    "sg:orig_category":"Bandagen U Bandagisten",
    "sg:phone":"+43 4326 82612820",
    "sg:postcode":"7000",
    "sg:province":"Burgenland",
    "wof:name":"Steinprecher Theodor GmbH",
    "wof:placetype":"venue"
},
  "geometry": {"coordinates":[16.5205917358,47.8461685181],"type":"Point"}
}