{
  "type": "Feature",
  "properties": {
    "addr:full":"Reithofferpl 11/f Wien Wien 1150",
    "addr:housenumber":"11 / f",
    "addr:postcode":"1150",
    "addr:street":"Reithofferpl",
    "iso:country":"AT",
    "sg:address":"Reithofferpl 11/f",
    "sg:city":"Wien",
    "sg:orig_category":"Elektroinstallationsunternehmen",
    "sg:phone":"+43 1 9821435",
    "sg:postcode":"1150",
    "sg:province":"Wien",
    "wof:name":"Kramar Karl",
    "wof:placetype":"venue"
},
  "geometry": {"coordinates":[16.3320903778,48.2006416321],"type":"Point"}
}