{
  "type": "Feature",
  "properties": {
    "addr:full":"Adalbert-Stifter-G 8-10 Klosterneuburg Nieder\u00f6sterreich 3400",
    "addr:housenumber":"8-10",
    "addr:postcode":"3400",
    "addr:street":"Niederoesterreich",
    "iso:country":"AT",
    "sg:address":"Adalbert-Stifter-G 8-10",
    "sg:city":"Klosterneuburg",
    "sg:orig_category":"Immobilienverwaltungen",
    "sg:phone":"+43 664 1606076",
    "sg:postcode":"3400",
    "sg:province":"Nieder\u00f6sterreich",
    "wof:name":"CWS Immobilien GesmbH",
    "wof:placetype":"venue"
},
  "geometry": {"coordinates":[16.3025856018,48.3077011108],"type":"Point"}
}