{
  "type": "Feature",
  "properties": {
    "addr:full":"Sistranser Str 205 Lans Tirol 6072",
    "addr:housenumber":"205",
    "addr:postcode":"6072",
    "addr:street":"Sistranser Str;Tirol",
    "iso:country":"AT",
    "sg:address":"Sistranser Str 205",
    "sg:city":"Lans",
    "sg:orig_category":"Immobilienmakler",
    "sg:phone":"+43 512 379538",
    "sg:postcode":"6072",
    "sg:province":"Tirol",
    "wof:name":"Cammerlander Immobilien KEG",
    "wof:placetype":"venue"
},
  "geometry": {"coordinates":[11.4369297028,47.2381057739],"type":"Point"}
}