{
  "type": "Feature",
  "properties": {
    "addr:full":"Schmalzhofg 14 Wien Wien 1060",
    "addr:housenumber":"14",
    "addr:postcode":"1060",
    "addr:street":"Schmalzhofg",
    "iso:country":"AT",
    "sg:address":"Schmalzhofg 14",
    "sg:city":"Wien",
    "sg:orig_category":"Bauunternehmen",
    "sg:phone":"+43 4366 42131114",
    "sg:postcode":"1060",
    "sg:province":"Wien",
    "wof:name":"BEQIRAJ BAU-KEG",
    "wof:placetype":"venue"
},
  "geometry": {"coordinates":[16.3463745117,48.1954193115],"type":"Point"}
}