{
  "type": "Feature",
  "properties": {
    "addr:full":"Koppstr 60 Wien Wien 1160",
    "addr:housenumber":"60",
    "addr:postcode":"1160",
    "addr:street":"Koppstr",
    "iso:country":"AT",
    "sg:address":"Koppstr 60",
    "sg:city":"Wien",
    "sg:orig_category":"Textilreinigung",
    "sg:phone":"+43 1 4924317",
    "sg:postcode":"1160",
    "sg:province":"Wien",
    "wof:name":"Zwanziger Brigitte",
    "wof:placetype":"venue"
},
  "geometry": {"coordinates":[16.3255176544,48.2080307007],"type":"Point"}
}