{
  "type": "Feature",
  "properties": {
    "iso:country":"AT",
    "sg:address":"Franz-Erler-Str 11",
    "sg:city":"Kitzb\u00fchel",
    "sg:orig_category":"Notare",
    "sg:phone":"+43 5356 66610",
    "sg:postcode":"6370",
    "sg:province":"Tirol",
    "wof:name":"Grander Wilhelm Dr",
    "wof:placetype":"venue"
},
  "geometry": {"coordinates":[12.3926887512,47.4479026794],"type":"Point"}
}