{
  "type": "Feature",
  "properties": {
    "addr:full":"Hasnerstr 123 Wien Wien 1160",
    "addr:housenumber":"123",
    "addr:postcode":"1160",
    "iso:country":"AT",
    "sg:address":"Hasnerstr 123",
    "sg:city":"Wien",
    "sg:classifiers":[
        {
            "category":"Professional",
            "subcategory":"Computer Services",
            "type":"Services"
        }
    ],
    "sg:phone":"+43 1 95555100",
    "sg:postcode":"1160",
    "sg:province":"Wien",
    "sg:tags":[
        "software"
    ],
    "wof:name":"SYSIS Interactive Simulations AG",
    "wof:placetype":"venue"
},
  "geometry": {"coordinates":[16.3146095276,48.2107391357],"type":"Point"}
}