{
  "type": "Feature",
  "properties": {
    "iso:country":"AT",
    "sg:address":"Maria-Theresia-Strasse 41",
    "sg:city":"Wels",
    "sg:classifiers":[
        {
            "category":"Communications",
            "subcategory":"Film & Video Production",
            "type":"Services"
        }
    ],
    "sg:phone":"+43 7242 648850",
    "sg:postcode":"4600",
    "sg:province":"Ober\u00f6sterreich",
    "sg:tags":[
        "image",
        "processing",
        "electronic"
    ],
    "sg:website":"muk.at",
    "wof:name":"M & K Elektronische Bildverarbeitung und Reproduktion GmbH",
    "wof:placetype":"venue"
},
  "geometry": {"coordinates":[14.0128498077,48.1539382935],"type":"Point"}
}