{
  "type": "Feature",
  "properties": {
    "iso:country":"AT",
    "sg:address":"Operng 18",
    "sg:city":"Wien",
    "sg:orig_category":"Steuerberatung",
    "sg:phone":"+43 4315 8610450",
    "sg:postcode":"1040",
    "sg:province":"Wien",
    "wof:name":"Balas Heinrich Dr",
    "wof:placetype":"venue"
},
  "geometry": {"coordinates":[16.366651535,48.1997642517],"type":"Point"}
}