{
  "type": "Feature",
  "properties": {
    "addr:full":"Ziegelofenstr 4 Vitis Nieder\u00f6sterreich 3902",
    "addr:housenumber":"4",
    "addr:postcode":"3902",
    "addr:street":"Ziegelofenstr",
    "iso:country":"AT",
    "sg:address":"Ziegelofenstr 4",
    "sg:city":"Vitis",
    "sg:orig_category":"Transportunternehmen",
    "sg:phone":"+43 2841 87720",
    "sg:postcode":"3902",
    "sg:province":"Nieder\u00f6sterreich",
    "wof:name":"Meyer Transport GmbH",
    "wof:placetype":"venue"
},
  "geometry": {"coordinates":[15.1723146439,48.758644104],"type":"Point"}
}