{
  "type": "Feature",
  "properties": {
    "iso:country":"AT",
    "sg:address":"Nr 134",
    "sg:city":"Turnau",
    "sg:orig_category":"Lederwaren / Erzeugung U Gro\u00c3\u0178handel",
    "sg:phone":"+43 3863 51000",
    "sg:postcode":"8625",
    "sg:province":"Steiermark",
    "wof:name":"Deiml Wolfgang",
    "wof:placetype":"venue"
},
  "geometry": {"coordinates":[-0.1163489968,45.6774291992],"type":"Point"}
}