{
  "type": "Feature",
  "properties": {
    "iso:country":"AT",
    "sg:address":"Nr 4",
    "sg:city":"Gurk",
    "sg:orig_category":"Pensionen / Privatzimmer",
    "sg:phone":"+43 4266 8132",
    "sg:postcode":"9342",
    "sg:province":"K\u00e4rnten",
    "wof:name":"Gasthof Leitgeb",
    "wof:placetype":"venue"
},
  "geometry": {"coordinates":[14.2920770645,46.8744773865],"type":"Point"}
}