{
  "type": "Feature",
  "properties": {
    "iso:country":"AT",
    "sg:address":"Vorgartenstr 54",
    "sg:city":"Wien",
    "sg:orig_category":"Sprachschulen U -Unterricht",
    "sg:phone":"+43 4313 342335",
    "sg:postcode":"1200",
    "sg:province":"Wien",
    "wof:name":"Huttar OEG",
    "wof:placetype":"venue"
},
  "geometry": {"coordinates":[16.3861198425,48.2371253967],"type":"Point"}
}