{
  "type": "Feature",
  "properties": {
    "addr:full":"Hannoverg 25 Wien Wien 1200",
    "addr:housenumber":"25",
    "addr:postcode":"1200",
    "addr:street":"Hannoverg",
    "iso:country":"AT",
    "sg:address":"Hannoverg 25",
    "sg:city":"Wien",
    "sg:orig_category":"Filmproduktionen",
    "sg:phone":"+43 1 35072900",
    "sg:postcode":"1200",
    "sg:province":"Wien",
    "wof:name":"DWW HandelsgesmbH",
    "wof:placetype":"venue"
},
  "geometry": {"coordinates":[16.3683376312,48.2316436768],"type":"Point"}
}