{
  "type": "Feature",
  "properties": {
    "iso:country":"AT",
    "sg:address":"Gewerb Litzelsdorf 249",
    "sg:city":"Tamsweg",
    "sg:orig_category":"Autoreparatur",
    "sg:phone":"+43 6474 22450",
    "sg:postcode":"5580",
    "sg:province":"Salzburg",
    "wof:name":"Autohaus Rott GesmbH",
    "wof:placetype":"venue"
},
  "geometry": {"coordinates":[13.7957859039,47.1323242188],"type":"Point"}
}