{
  "type": "Feature",
  "properties": {
    "addr:full":"Burgg 11 Schwaz Tirol 6130",
    "addr:housenumber":"11",
    "addr:postcode":"6130",
    "addr:street":"Burgg;Tirol",
    "iso:country":"AT",
    "sg:address":"Burgg 11",
    "sg:city":"Schwaz",
    "sg:orig_category":"Behinderungen / Leben Mit Behinderungen",
    "sg:phone":"+43 5242 61172",
    "sg:postcode":"6130",
    "sg:province":"Tirol",
    "wof:name":"Lebenshilfe Tirol Fr\u00fchf\u00f6rderstelle",
    "wof:placetype":"venue"
},
  "geometry": {"coordinates":[11.7104120255,47.3445625305],"type":"Point"}
}