{
  "type": "Feature",
  "properties": {
    "addr:full":"Grinzinger Str 99 Wien Wien 1190",
    "addr:postcode":"1190",
    "addr:street":"Str 99",
    "iso:country":"AT",
    "sg:address":"Grinzinger Str 99",
    "sg:city":"Wien",
    "sg:orig_category":"Massagen",
    "sg:phone":"+43 4365 04100305",
    "sg:postcode":"1190",
    "sg:province":"Wien",
    "wof:name":"Fachinstitut f\u00fcr Asiatische Massagen Fasching Clemens",
    "wof:placetype":"venue"
},
  "geometry": {"coordinates":[16.358247757,48.2541465759],"type":"Point"}
}