{
  "type": "Feature",
  "properties": {
    "addr:full":"Amselg 2 Freistadt Ober\u00f6sterreich 4240",
    "addr:housenumber":"2",
    "addr:postcode":"4240",
    "addr:street":"Amselg",
    "iso:country":"AT",
    "sg:address":"Amselg 2",
    "sg:city":"Freistadt",
    "sg:orig_category":"Estriche",
    "sg:phone":"+43 4366 43225888",
    "sg:postcode":"4240",
    "sg:province":"Ober\u00f6sterreich",
    "wof:name":"G-tec Mario Winter GmbH",
    "wof:placetype":"venue"
},
  "geometry": {"coordinates":[14.4955196381,48.5191993713],"type":"Point"}
}