{
  "type": "Feature",
  "properties": {
    "addr:full":"Grabenfeldstr 12a Bruck an der Mur Steiermark 8600",
    "addr:housenumber":"12a",
    "addr:postcode":"8600",
    "addr:street":"Grabenfeldstr",
    "iso:country":"AT",
    "sg:address":"Grabenfeldstr 12a",
    "sg:city":"Bruck an der Mur",
    "sg:orig_category":"Feuerwehren",
    "sg:phone":"+43 3862 54932",
    "sg:postcode":"8600",
    "sg:province":"Steiermark",
    "wof:name":"Bezirksfeuerwehrkommando Bruck a d Mur",
    "wof:placetype":"venue"
},
  "geometry": {"coordinates":[15.2635374069,47.4135894775],"type":"Point"}
}