{
  "type": "Feature",
  "properties": {
    "addr:full":"Paris-Lodron-Str 19 Salzburg Salzburg 5020",
    "addr:housenumber":"19",
    "addr:postcode":"5020",
    "addr:street":"Paris-Lodron-Str;Salzburg",
    "iso:country":"AT",
    "sg:address":"Paris-Lodron-Str 19",
    "sg:city":"Salzburg",
    "sg:orig_category":"Personalbereitstellung",
    "sg:phone":"+43 662 881034",
    "sg:postcode":"5020",
    "sg:province":"Salzburg",
    "sg:website":"osc.cc",
    "wof:name":"OSC Personaldienstleistungen Brigitte Trattner GesmbH",
    "wof:placetype":"venue"
},
  "geometry": {"coordinates":[13.0492429733,47.8063735962],"type":"Point"}
}