{
  "type": "Feature",
  "properties": {
    "iso:country":"AT",
    "sg:address":"Hormayrg 3",
    "sg:city":"Wien",
    "sg:orig_category":"Blumeneinzelhandel",
    "sg:phone":"+43 1 4895324",
    "sg:postcode":"1170",
    "sg:province":"Wien",
    "wof:name":"Novotny Rosa",
    "wof:placetype":"venue"
},
  "geometry": {"coordinates":[16.3305912018,48.2187690735],"type":"Point"}
}