{
  "type": "Feature",
  "properties": {
    "iso:country":"AT",
    "sg:address":"Bischof Faber-Pl 14/1a",
    "sg:city":"Wien",
    "sg:orig_category":"Satzherstellung",
    "sg:phone":"+43 1 4799461",
    "sg:postcode":"1180",
    "sg:province":"Wien",
    "wof:name":"M\u00fcller OK Repro- und Druck GesmbH",
    "wof:placetype":"venue"
},
  "geometry": {"coordinates":[16.3256225586,48.234249115],"type":"Point"}
}