{
  "type": "Feature",
  "properties": {
    "iso:country":"AT",
    "sg:address":"Florianipl 2",
    "sg:city":"Weikendorf",
    "sg:orig_category":"Feuerwehren",
    "sg:phone":"+43 2282 4141",
    "sg:postcode":"2253",
    "sg:province":"Nieder\u00f6sterreich",
    "wof:name":"Freiwillige Feuerwehr Weikendorf",
    "wof:placetype":"venue"
},
  "geometry": {"coordinates":[16.7665138245,48.3462142944],"type":"Point"}
}