{
  "type": "Feature",
  "properties": {
    "addr:full":"Grazer Str 4 Wolfsberg K\u00e4rnten 9400",
    "addr:housenumber":"4;kaernten",
    "addr:postcode":"9400",
    "addr:street":"Str",
    "iso:country":"AT",
    "sg:address":"Grazer Str 4",
    "sg:city":"Wolfsberg",
    "sg:orig_category":"Autohandel",
    "sg:phone":"+43 4352 25400",
    "sg:postcode":"9400",
    "sg:province":"K\u00e4rnten",
    "wof:name":"G\u00f6nitzer GesmbH & Co KG",
    "wof:placetype":"venue"
},
  "geometry": {"coordinates":[14.8422451019,46.8430519104],"type":"Point"}
}