{
  "type": "Feature",
  "properties": {
    "addr:full":"Winkl 3 St. Gilgen Salzburg 5340",
    "addr:housenumber":"3",
    "addr:postcode":"5340",
    "addr:street":"Winkl",
    "iso:country":"AT",
    "sg:address":"Winkl 3",
    "sg:city":"St. Gilgen",
    "sg:orig_category":"Pensionen / Privatzimmer",
    "sg:phone":"+43 6227 2394",
    "sg:postcode":"5340",
    "sg:province":"Salzburg",
    "wof:name":"Ziffer Karl Heinz",
    "wof:placetype":"venue"
},
  "geometry": {"coordinates":[13.3856296539,47.7812156677],"type":"Point"}
}