{
  "type": "Feature",
  "properties": {
    "addr:full":"Ruthnerg 19 Sierning Ober\u00f6sterreich 4522",
    "addr:housenumber":"19",
    "addr:postcode":"4522",
    "addr:street":"Ruthnerg",
    "iso:country":"AT",
    "sg:address":"Ruthnerg 19",
    "sg:city":"Sierning",
    "sg:orig_category":"Lebensmittel / Einzelhandel",
    "sg:phone":"+43 7259 22230",
    "sg:postcode":"4522",
    "sg:province":"Ober\u00f6sterreich",
    "wof:name":"Luftensteiner GmbH und Co KG",
    "wof:placetype":"venue"
},
  "geometry": {"coordinates":[14.3090353012,48.0417137146],"type":"Point"}
}