{
  "type": "Feature",
  "properties": {
    "addr:full":"Bundesstr 24 Rankweil Vorarlberg 6830",
    "addr:housenumber":"24",
    "addr:postcode":"6830",
    "addr:street":"Bundesstr",
    "iso:country":"AT",
    "sg:address":"Bundesstr 24",
    "sg:city":"Rankweil",
    "sg:orig_category":"Restaurants: Amerikanisch",
    "sg:phone":"+43 5522 826220",
    "sg:postcode":"6830",
    "sg:province":"Vorarlberg",
    "wof:name":"McDonald's Restaurant - McDrive",
    "wof:placetype":"venue"
},
  "geometry": {"coordinates":[9.6162004471,47.2730560303],"type":"Point"}
}