{
  "type": "Feature",
  "properties": {
    "addr:full":"Hans-Sachs-G 14 Graz Steiermark 8010",
    "addr:housenumber":"14",
    "addr:postcode":"8010",
    "addr:street":"Hans-Sachs-G",
    "iso:country":"AT",
    "sg:address":"Hans-Sachs-G 14",
    "sg:city":"Graz",
    "sg:orig_category":"Antiquariate",
    "sg:phone":"+43 316 83011023",
    "sg:postcode":"8010",
    "sg:province":"Steiermark",
    "wof:name":"Antiquariat der Buchhandlung Moser",
    "wof:placetype":"venue"
},
  "geometry": {"coordinates":[15.4418067932,47.0692634583],"type":"Point"}
}