{
  "type": "Feature",
  "properties": {
    "iso:country":"AT",
    "sg:address":"Nr 154",
    "sg:city":"Stegersbach",
    "sg:orig_category":"Tabaktrafiken",
    "sg:phone":"+43 3326 52664",
    "sg:postcode":"7551",
    "sg:province":"Burgenland",
    "wof:name":"Potzmann Annemarie und Otmar",
    "wof:placetype":"venue"
},
  "geometry": {"coordinates":[16.1662063599,47.1597747803],"type":"Point"}
}