{
  "type": "Feature",
  "properties": {
    "addr:full":"Bahnhofstr 14 Feldkirch Vorarlberg 6800",
    "addr:postcode":"6800",
    "addr:street":"Bahnhofstr 14",
    "iso:country":"AT",
    "sg:address":"Bahnhofstr 14",
    "sg:city":"Feldkirch",
    "sg:orig_category":"Schneidereien",
    "sg:phone":"+43 5522 74971",
    "sg:postcode":"6800",
    "sg:province":"Vorarlberg",
    "wof:name":"Pfleger Gregor",
    "wof:placetype":"venue"
},
  "geometry": {"coordinates":[9.6019382477,47.2412185669],"type":"Point"}
}