{
  "type": "Feature",
  "properties": {
    "addr:full":"Obere Hauptstr 4 B\u00f6heimkirchen Nieder\u00f6sterreich 3071",
    "addr:housenumber":"4",
    "addr:postcode":"3071",
    "addr:street":"Obere Hauptstr;Niederoesterreich",
    "iso:country":"AT",
    "sg:address":"Obere Hauptstr 4",
    "sg:city":"B\u00f6heimkirchen",
    "sg:orig_category":"Glasereien",
    "sg:phone":"+43 2743 2246",
    "sg:postcode":"3071",
    "sg:province":"Nieder\u00f6sterreich",
    "wof:name":"Anzenberger Peter",
    "wof:placetype":"venue"
},
  "geometry": {"coordinates":[7.7127490044,49.574382782],"type":"Point"}
}