{
  "type": "Feature",
  "properties": {
    "addr:full":"Dr.-Franz-Thomas-Str 12 Gmunden Ober\u00f6sterreich 4810",
    "addr:housenumber":"12",
    "addr:postcode":"4810",
    "addr:street":"Dr.-Franz-Thomas-Str;Oberoesterreich",
    "iso:country":"AT",
    "sg:address":"Dr.-Franz-Thomas-Str 12",
    "sg:city":"Gmunden",
    "sg:orig_category":"Lastkraftwagen",
    "sg:phone":"+43 761266346",
    "sg:postcode":"4810",
    "sg:province":"Ober\u00f6sterreich",
    "wof:name":"Schmid Christian",
    "wof:placetype":"venue"
},
  "geometry": {"coordinates":[13.7867994308,47.9125366211],"type":"Point"}
}