{
  "type": "Feature",
  "properties": {
    "addr:full":"Stattersdorf Hptstr 42 St. P\u00f6lten Nieder\u00f6sterreich 3100",
    "addr:housenumber":"42",
    "addr:postcode":"3100",
    "addr:street":"St. Poelten",
    "iso:country":"AT",
    "sg:address":"Stattersdorf Hptstr 42",
    "sg:city":"St. P\u00f6lten",
    "sg:orig_category":"Lebensmittel / Einzelhandel",
    "sg:phone":"+43 2742 24648",
    "sg:postcode":"3100",
    "sg:province":"Nieder\u00f6sterreich",
    "wof:name":"Hofer KG",
    "wof:placetype":"venue"
},
  "geometry": {"coordinates":[15.6410903931,48.1977272034],"type":"Point"}
}