{
  "type": "Feature",
  "properties": {
    "addr:full":"Hauptpl 2 Deutschlandsberg Steiermark 8530",
    "addr:housenumber":"2",
    "addr:postcode":"8530",
    "addr:street":"Hauptpl",
    "iso:country":"AT",
    "sg:address":"Hauptpl 2",
    "sg:city":"Deutschlandsberg",
    "sg:orig_category":"Haushaltsartikel",
    "sg:phone":"+43 3462 3773",
    "sg:postcode":"8530",
    "sg:province":"Steiermark",
    "wof:name":"Prassl Viktor",
    "wof:placetype":"venue"
},
  "geometry": {"coordinates":[15.21596241,46.8155021667],"type":"Point"}
}