{
  "type": "Feature",
  "properties": {
    "iso:country":"AT",
    "sg:address":"Hietzinger Hauptstr 88a",
    "sg:city":"Wien",
    "sg:orig_category":"Blumeneinzelhandel",
    "sg:phone":"+43 1 8775998",
    "sg:postcode":"1130",
    "sg:province":"Wien",
    "wof:name":"Blumenstube Grete Inh Gabriela Seyer",
    "wof:placetype":"venue"
},
  "geometry": {"coordinates":[16.2821598053,48.1876220703],"type":"Point"}
}