{
  "type": "Feature",
  "properties": {
    "iso:country":"AT",
    "sg:address":"Leitenweg 1",
    "sg:city":"Gratkorn",
    "sg:orig_category":"Friseure U Frisiersalons",
    "sg:phone":"+43 664 5017535",
    "sg:postcode":"8101",
    "sg:province":"Steiermark",
    "wof:name":"Wlasics Doris - Mobilfriseur",
    "wof:placetype":"venue"
},
  "geometry": {"coordinates":[15.357919693,47.1281089783],"type":"Point"}
}