{
  "type": "Feature",
  "properties": {
    "iso:country":"AT",
    "sg:address":"Lindhofstr 20/1",
    "sg:city":"Salzburg",
    "sg:orig_category":"Massagen",
    "sg:phone":"+43 4369 912883317",
    "sg:postcode":"5020",
    "sg:province":"Salzburg",
    "wof:name":"Malzl Hans A K u Partner",
    "wof:placetype":"venue"
},
  "geometry": {"coordinates":[13.0331792831,47.806438446],"type":"Point"}
}