{
  "type": "Feature",
  "properties": {
    "addr:full":"Pazmaniteng 16 Wien Wien 1020",
    "addr:housenumber":"16",
    "addr:postcode":"1020",
    "addr:street":"Pazmaniteng",
    "iso:country":"AT",
    "sg:address":"Pazmaniteng 16",
    "sg:city":"Wien",
    "sg:orig_category":"Werbegestalter",
    "sg:phone":"+43 1 6880958",
    "sg:postcode":"1020",
    "sg:province":"Wien",
    "wof:name":"DECO-HAND Fritz Dobnig",
    "wof:placetype":"venue"
},
  "geometry": {"coordinates":[16.3853435516,48.2219772339],"type":"Point"}
}