{
  "type": "Feature",
  "properties": {
    "addr:full":"Kleinfelder Strasse 3 Berndorf Nieder\u00f6sterreich 2560",
    "addr:housenumber":"3",
    "addr:postcode":"2560",
    "addr:street":"Kleinfelder Strasse",
    "iso:country":"AT",
    "sg:address":"Kleinfelder Strasse 3",
    "sg:city":"Berndorf",
    "sg:classifiers":[
        {
            "category":"Manufacturing",
            "subcategory":"Rubber & Plastics",
            "type":"Manufacturing & Wholesale Goods"
        }
    ],
    "sg:phone":"+43 2672 825300",
    "sg:postcode":"2560",
    "sg:province":"Nieder\u00f6sterreich",
    "sg:tags":[
        "injection",
        "part",
        "moulded"
    ],
    "wof:name":"A. u. K. Zihlarsch Kunstharzspritzerei Ges.m.b.H. & Co KG",
    "wof:placetype":"venue"
},
  "geometry": {"coordinates":[16.1119327545,47.9387588501],"type":"Point"}
}