{
  "type": "Feature",
  "properties": {
    "addr:full":"Niederau 39 Wildsch\u00f6nau-Niederau Tirol 6314",
    "addr:housenumber":"39",
    "addr:postcode":"6314",
    "addr:street":"Niederau;Tirol",
    "iso:country":"AT",
    "sg:address":"Niederau 39",
    "sg:city":"Wildsch\u00f6nau-Niederau",
    "sg:orig_category":"Banken U Sparkassen",
    "sg:phone":"+43 4353 3981650",
    "sg:postcode":"6314",
    "sg:province":"Tirol",
    "wof:name":"Raiffeisenkasse Wildsch\u00f6nau regGenmbH",
    "wof:placetype":"venue"
},
  "geometry": {"coordinates":[12.105055809,47.4490509033],"type":"Point"}
}