{
  "type": "Feature",
  "properties": {
    "iso:country":"AT",
    "sg:address":"Untere Marktstr 90",
    "sg:city":"Etsdorf am Kamp",
    "sg:orig_category":"Installationsunternehmen",
    "sg:phone":"+43 2735 24650",
    "sg:postcode":"3492",
    "sg:province":"Nieder\u00f6sterreich",
    "sg:website":"tiefenbacher.co.at",
    "wof:name":"Tiefenbacher Klaus Ing",
    "wof:placetype":"venue"
},
  "geometry": {"coordinates":[15.7414398193,48.44373703],"type":"Point"}
}