{
  "type": "Feature",
  "properties": {
    "addr:full":"Holzleitnerstr 41 Mattighofen Ober\u00f6sterreich 5230",
    "addr:housenumber":"41",
    "addr:postcode":"5230",
    "addr:street":"Holzleitnerstr",
    "iso:country":"AT",
    "sg:address":"Holzleitnerstr 41",
    "sg:city":"Mattighofen",
    "sg:classifiers":[
        {
            "category":"Professional",
            "subcategory":"Computer Services",
            "type":"Services"
        }
    ],
    "sg:phone":"+43 664 2643447",
    "sg:postcode":"5230",
    "sg:province":"Ober\u00f6sterreich",
    "sg:tags":[
        "software"
    ],
    "wof:name":"Daberto Ewald",
    "wof:placetype":"venue"
},
  "geometry": {"coordinates":[13.1500482559,48.1035919189],"type":"Point"}
}