{
  "type": "Feature",
  "properties": {
    "iso:country":"AT",
    "sg:address":"Linke Wulkazeile 53",
    "sg:city":"Trausdorf an der Wulka",
    "sg:orig_category":"Garten- U Landschaftsgestaltung",
    "sg:phone":"+43 4366 44945013",
    "sg:postcode":"7061",
    "sg:province":"Burgenland",
    "wof:name":"ERFO Gartenbau",
    "wof:placetype":"venue"
},
  "geometry": {"coordinates":[16.5547866821,47.8150482178],"type":"Point"}
}