{
  "type": "Feature",
  "properties": {
    "addr:full":"Baumgasse 72 Wien Wien 1030",
    "addr:housenumber":"72",
    "addr:postcode":"1030",
    "addr:street":"Baumgasse",
    "iso:country":"AT",
    "sg:address":"Baumgasse 72",
    "sg:city":"Wien",
    "sg:classifiers":[
        {
            "category":"Retail",
            "subcategory":"Repair Shop",
            "type":"Services"
        }
    ],
    "sg:phone":"+43 1 7988653",
    "sg:postcode":"1030",
    "sg:province":"Wien",
    "sg:tags":[
        "balance",
        "scale"
    ],
    "sg:website":"atzl.at",
    "wof:name":"Lenz & Atzl Systeme GmbH W\u00e4ge- und Anlagentechnik",
    "wof:placetype":"venue"
},
  "geometry": {"coordinates":[16.411315918,48.188911438],"type":"Point"}
}