{
  "type": "Feature",
  "properties": {
    "addr:full":"Nr 272 Ried in der Riedmark Ober\u00f6sterreich 4312",
    "addr:postcode":"4312",
    "addr:street":"Nr 272",
    "iso:country":"AT",
    "sg:address":"Nr 272",
    "sg:city":"Ried in der Riedmark",
    "sg:orig_category":"Lebensmittel / Einzelhandel",
    "sg:phone":"+43 7238 29273",
    "sg:postcode":"4312",
    "sg:province":"Ober\u00f6sterreich",
    "wof:name":"SPAR \u00f6sterreichische Warenhandels-AG",
    "wof:placetype":"venue"
},
  "geometry": {"coordinates":[14.5276536942,48.2708244324],"type":"Point"}
}