{
  "type": "Feature",
  "properties": {
    "addr:full":"Salzburger Str 32 M4 W\u00f6rgl Top 24 W\u00f6rgl Tirol 6300",
    "addr:housenumber":"32 m4 woergl;24",
    "addr:postcode":"6300",
    "addr:street":"Salzburger Str;Top;Tirol",
    "iso:country":"AT",
    "sg:address":"Salzburger Str 32 M4 W\u00f6rgl Top 24",
    "sg:city":"W\u00f6rgl",
    "sg:orig_category":"Friseure U Frisiersalons",
    "sg:phone":"+43 4353 3272697",
    "sg:postcode":"6300",
    "sg:province":"Tirol",
    "wof:name":"FRIS\u00f6R KLIER GesmbH",
    "wof:placetype":"venue"
},
  "geometry": {"coordinates":[-69.3131027222,-51.6091995239],"type":"Point"}
}