{
  "type": "Feature",
  "properties": {
    "addr:full":"Walgaustr 546 Th\u00fcringen Vorarlberg 6712",
    "addr:housenumber":"546",
    "addr:postcode":"6712",
    "addr:street":"Thueringen Vorarlberg",
    "iso:country":"AT",
    "sg:address":"Walgaustr 546",
    "sg:city":"Th\u00fcringen",
    "sg:orig_category":"Lebensmittel / Einzelhandel",
    "sg:phone":"+43 5550 5041",
    "sg:postcode":"6712",
    "sg:province":"Vorarlberg",
    "wof:name":"Billa AG",
    "wof:placetype":"venue"
},
  "geometry": {"coordinates":[9.7563447952,47.1989860535],"type":"Point"}
}