{
  "type": "Feature",
  "properties": {
    "iso:country":"AT",
    "sg:address":"Maurergasse 12",
    "sg:city":"Neunkirchen",
    "sg:classifiers":[
        {
            "category":"Home & Garden",
            "subcategory":"Household Appliances",
            "type":"Retail Goods"
        }
    ],
    "sg:phone":"+43 2635 62034",
    "sg:postcode":"2620",
    "sg:province":"Nieder\u00f6sterreich",
    "sg:tags":[
        "electric"
    ],
    "wof:name":"Wilhelm Haberbichler",
    "wof:placetype":"venue"
},
  "geometry": {"coordinates":[16.0865936279,47.717918396],"type":"Point"}
}