{
  "type": "Feature",
  "properties": {
    "addr:full":"Schulstr 4 Feldkirchen an der Donau Ober\u00f6sterreich 4101",
    "addr:housenumber":"4",
    "addr:postcode":"4101",
    "addr:street":"Schulstr",
    "iso:country":"AT",
    "sg:address":"Schulstr 4",
    "sg:city":"Feldkirchen an der Donau",
    "sg:orig_category":"Versicherungsunternehmen",
    "sg:phone":"+43 4372 337298",
    "sg:postcode":"4101",
    "sg:province":"Ober\u00f6sterreich",
    "wof:name":"Feldkirchner Versicherung Versicherungsverein auf Gegenseitigkeit",
    "wof:placetype":"venue"
},
  "geometry": {"coordinates":[14.0536108017,48.3445777893],"type":"Point"}
}