{
  "type": "Feature",
  "properties": {
    "iso:country":"AT",
    "sg:address":"Seeg 10",
    "sg:city":"Illmitz",
    "sg:orig_category":"Tischlereien",
    "sg:phone":"+43 2175 2130",
    "sg:postcode":"7142",
    "sg:province":"Burgenland",
    "wof:name":"Schneider Otto",
    "wof:placetype":"venue"
},
  "geometry": {"coordinates":[16.7998695374,47.7619514465],"type":"Point"}
}