{
  "type": "Feature",
  "properties": {
    "addr:full":"Hanriederstr 14 Lembach im M\u00fchlkreis Ober\u00f6sterreich 4132",
    "addr:housenumber":"14",
    "addr:postcode":"4132",
    "addr:street":"Hanriederstr;Im Muehlkreis Oberoesterreich",
    "iso:country":"AT",
    "sg:address":"Hanriederstr 14",
    "sg:city":"Lembach im M\u00fchlkreis",
    "sg:orig_category":"Autohandel",
    "sg:phone":"+43 7286 26842",
    "sg:postcode":"4132",
    "sg:province":"Ober\u00f6sterreich",
    "wof:name":"Seat J\u00e4ger",
    "wof:placetype":"venue"
},
  "geometry": {"coordinates":[13.8930063248,48.496711731],"type":"Point"}
}