{
  "type": "Feature",
  "properties": {
    "addr:full":"Rindbachstrasse 32 Ebensee Ober\u00f6sterreich 4802",
    "addr:housenumber":"32",
    "addr:postcode":"4802",
    "addr:street":"Rindbachstrasse",
    "iso:country":"AT",
    "sg:address":"Rindbachstrasse 32",
    "sg:city":"Ebensee",
    "sg:classifiers":[
        {
            "category":"Banks & Credit Unions",
            "subcategory":"Investment Brokerage",
            "type":"Services"
        }
    ],
    "sg:phone":"+43 6133 50160",
    "sg:postcode":"4802",
    "sg:province":"Ober\u00f6sterreich",
    "sg:tags":[
        "bearing",
        "ball"
    ],
    "sg:website":"thb.at",
    "wof:name":"Brummer Technischer Handel, THB gmbh",
    "wof:placetype":"venue"
},
  "geometry": {"coordinates":[13.7761297226,47.8093299866],"type":"Point"}
}