{
  "type": "Feature",
  "properties": {
    "addr:full":"Deutenhofenstr 2 Klagenfurt K\u00e4rnten 9020",
    "addr:housenumber":"2",
    "addr:postcode":"9020",
    "addr:street":"Deutenhofenstr;Kaernten",
    "iso:country":"AT",
    "sg:address":"Deutenhofenstr 2",
    "sg:city":"Klagenfurt",
    "sg:orig_category":"Friseure U Frisiersalons",
    "sg:phone":"+43 4346 356176",
    "sg:postcode":"9020",
    "sg:province":"K\u00e4rnten",
    "wof:name":"Frisiersalon Helga",
    "wof:placetype":"venue"
},
  "geometry": {"coordinates":[14.2996091843,46.6289291382],"type":"Point"}
}