{
  "type": "Feature",
  "properties": {
    "iso:country":"AT",
    "sg:address":"Hauptstr 15",
    "sg:city":"Oberpullendorf",
    "sg:orig_category":"Friseure U Frisiersalons",
    "sg:phone":"+43 4326 1243791",
    "sg:postcode":"7350",
    "sg:province":"Burgenland",
    "wof:name":"Haarstudio B - Brigitte Bubits",
    "wof:placetype":"venue"
},
  "geometry": {"coordinates":[16.505689621,47.5008544922],"type":"Point"}
}