{
  "type": "Feature",
  "properties": {
    "addr:full":"Radetzkystr 1-4 Klagenfurt K\u00e4rnten 9020",
    "addr:housenumber":"1-4",
    "addr:postcode":"9020",
    "addr:street":"Radetzkystr;Kaernten",
    "iso:country":"AT",
    "sg:address":"Radetzkystr 1-4",
    "sg:city":"Klagenfurt",
    "sg:orig_category":"Immobilienmakler",
    "sg:phone":"+43 463 500530",
    "sg:postcode":"9020",
    "sg:province":"K\u00e4rnten",
    "wof:name":"Immobilien-Office Hart & Brandl GmbH",
    "wof:placetype":"venue"
},
  "geometry": {"coordinates":[14.3019533157,46.6268501282],"type":"Point"}
}