{
  "type": "Feature",
  "properties": {
    "addr:full":"Nr 95 D\u00fcrnstein Nieder\u00f6sterreich 3601",
    "addr:postcode":"3601",
    "addr:street":"Nr 95 Duernstein",
    "iso:country":"AT",
    "sg:address":"Nr 95",
    "sg:city":"D\u00fcrnstein",
    "sg:orig_category":"Freizeitangebote U -Einrichtungen",
    "sg:phone":"+43 4369 911669522",
    "sg:postcode":"3601",
    "sg:province":"Nieder\u00f6sterreich",
    "wof:name":"Riesenhuber Ernst - Bummelzug",
    "wof:placetype":"venue"
},
  "geometry": {"coordinates":[15.5194883347,48.3960990906],"type":"Point"}
}