{
  "type": "Feature",
  "properties": {
    "addr:full":"Maderspergerstr 8 Kufstein Tirol 6330",
    "addr:housenumber":"8",
    "addr:postcode":"6330",
    "addr:street":"Maderspergerstr;Tirol",
    "iso:country":"AT",
    "sg:address":"Maderspergerstr 8",
    "sg:city":"Kufstein",
    "sg:orig_category":"Psychologen",
    "sg:phone":"+43 699 10018425",
    "sg:postcode":"6330",
    "sg:province":"Tirol",
    "wof:name":"Mayr-Grafl Annemarie Mag",
    "wof:placetype":"venue"
},
  "geometry": {"coordinates":[12.1720523834,47.5801696777],"type":"Point"}
}