{
  "type": "Feature",
  "properties": {
    "addr:full":"Grazer Bundesstr 19 d Gnigl Salzburg 5023",
    "addr:housenumber":"19 d",
    "addr:postcode":"5023",
    "iso:country":"AT",
    "sg:address":"Grazer Bundesstr 19 d",
    "sg:city":"Gnigl",
    "sg:classifiers":[
        {
            "category":"Home & Garden",
            "subcategory":"Kitchen Supply",
            "type":"Retail Goods"
        }
    ],
    "sg:phone":"+43 662 640919",
    "sg:postcode":"5023",
    "sg:province":"Salzburg",
    "sg:tags":[
        "espresso-",
        "u",
        "kaffeemaschinen"
    ],
    "wof:name":"LaCimbali Ebner Rudolf jun",
    "wof:placetype":"venue"
},
  "geometry": {"coordinates":[13.0742712021,47.8144226074],"type":"Point"}
}