{
  "type": "Feature",
  "properties": {
    "iso:country":"AT",
    "sg:address":"Wiener Str 98",
    "sg:city":"Neulengbach",
    "sg:orig_category":"Elektroinstallationsunternehmen",
    "sg:phone":"+43 2772 55636",
    "sg:postcode":"3040",
    "sg:province":"Nieder\u00f6sterreich",
    "wof:name":"Elektro Eduard Steiner",
    "wof:placetype":"venue"
},
  "geometry": {"coordinates":[15.9092121124,48.1964454651],"type":"Point"}
}