{
  "type": "Feature",
  "properties": {
    "addr:full":"Trauttmansdorffg 17 Wien Wien 1130",
    "addr:housenumber":"17",
    "addr:postcode":"1130",
    "addr:street":"Trauttmansdorffg",
    "iso:country":"AT",
    "sg:address":"Trauttmansdorffg 17",
    "sg:city":"Wien",
    "sg:orig_category":"Forschungsinstitute",
    "sg:phone":"+43 4318 7723920",
    "sg:postcode":"1130",
    "sg:province":"Wien",
    "wof:name":"Institut f Pers\u00f6nlichkeitsentfaltung",
    "wof:placetype":"venue"
},
  "geometry": {"coordinates":[16.2962036133,48.1841087341],"type":"Point"}
}