{
  "type": "Feature",
  "properties": {
    "addr:full":"Baldiag 14 Wien Wien 1160",
    "addr:housenumber":"14",
    "addr:postcode":"1160",
    "addr:street":"Baldiag",
    "iso:country":"AT",
    "sg:address":"Baldiag 14",
    "sg:city":"Wien",
    "sg:orig_category":"Tankstellen",
    "sg:phone":"+43 1 4868916",
    "sg:postcode":"1160",
    "sg:province":"Wien",
    "wof:name":"BP Austria Marketing GmbH",
    "wof:placetype":"venue"
},
  "geometry": {"coordinates":[16.2961292267,48.214931488],"type":"Point"}
}