{
  "type": "Feature",
  "properties": {
    "addr:full":"Wastlerg 10 Graz Steiermark 8010",
    "addr:housenumber":"10",
    "addr:postcode":"8010",
    "addr:street":"Wastlerg",
    "iso:country":"AT",
    "sg:address":"Wastlerg 10",
    "sg:city":"Graz",
    "sg:orig_category":"Immobilienmakler",
    "sg:phone":"+43 316 3222300",
    "sg:postcode":"8010",
    "sg:province":"Steiermark",
    "wof:name":"M\u00f6lzer Gerold & Co GesmbH",
    "wof:placetype":"venue"
},
  "geometry": {"coordinates":[15.4428977966,47.0804862976],"type":"Point"}
}