{
  "type": "Feature",
  "properties": {
    "addr:full":"Goldschmiedg 9 Wien Wien 1010",
    "addr:housenumber":"9",
    "addr:postcode":"1010",
    "addr:street":"Goldschmiedg",
    "iso:country":"AT",
    "sg:address":"Goldschmiedg 9",
    "sg:city":"Wien",
    "sg:orig_category":"Freizeit- U Sportbekleidung",
    "sg:phone":"+43 4315 331028",
    "sg:postcode":"1010",
    "sg:province":"Wien",
    "wof:name":"BLAUMAX HandelsgmbH",
    "wof:placetype":"venue"
},
  "geometry": {"coordinates":[16.3703765869,48.208984375],"type":"Point"}
}