{
  "type": "Feature",
  "properties": {
    "addr:full":"Neulerchenfelder Str 32 Wien Wien 1160",
    "addr:postcode":"1160",
    "addr:street":"Str 32",
    "iso:country":"AT",
    "sg:address":"Neulerchenfelder Str 32",
    "sg:city":"Wien",
    "sg:classifiers":[
        {
            "category":"Professional",
            "subcategory":"Computer Services",
            "type":"Services"
        }
    ],
    "sg:phone":"+43 4319 578917",
    "sg:postcode":"1160",
    "sg:province":"Wien",
    "sg:tags":[
        "software"
    ],
    "wof:name":"COMTARSIA IT SERVICES GMBH",
    "wof:placetype":"venue"
},
  "geometry": {"coordinates":[16.3349609375,48.2113456726],"type":"Point"}
}