{
  "type": "Feature",
  "properties": {
    "iso:country":"AT",
    "sg:address":"Johann-Strau\u00df-G 7",
    "sg:city":"Stra\u00dfgang",
    "sg:orig_category":"Transportunternehmen",
    "sg:phone":"+43 316 284104",
    "sg:postcode":"8054",
    "sg:province":"Steiermark",
    "wof:name":"Hillebrand Werner KG",
    "wof:placetype":"venue"
},
  "geometry": {"coordinates":[15.3884181976,46.9972763062],"type":"Point"}
}