{
  "type": "Feature",
  "properties": {
    "addr:full":"Mariahilfstr 29 Bregenz Vorarlberg 6900",
    "addr:housenumber":"29",
    "addr:postcode":"6900",
    "addr:street":"Mariahilfstr",
    "iso:country":"AT",
    "sg:address":"Mariahilfstr 29",
    "sg:city":"Bregenz",
    "sg:orig_category":"Webereien U Spinnereien",
    "sg:phone":"+43 5574 6090",
    "sg:postcode":"6900",
    "sg:province":"Vorarlberg",
    "wof:name":"Schoeller Bregenz GmbH & Co KG",
    "wof:placetype":"venue"
},
  "geometry": {"coordinates":[9.7302532196,47.4960670471],"type":"Point"}
}