{
  "type": "Feature",
  "properties": {
    "addr:full":"Nr 100 Zlan K\u00e4rnten 9713",
    "addr:postcode":"9713",
    "addr:street":"Nr;Kaernten",
    "iso:country":"AT",
    "sg:address":"Nr 100",
    "sg:city":"Zlan",
    "sg:orig_category":"Feuerwehren",
    "sg:phone":"+43 4761 550",
    "sg:postcode":"9713",
    "sg:province":"K\u00e4rnten",
    "wof:name":"Feuerwehr Stockenboi",
    "wof:placetype":"venue"
},
  "geometry": {"coordinates":[13.5806102753,46.7291069031],"type":"Point"}
}