{
  "type": "Feature",
  "properties": {
    "addr:full":"Franziskanerstrasse 9  Frauenkirchen Burgenland 7132",
    "addr:housenumber":"9",
    "addr:postcode":"7132",
    "addr:street":"Franziskanerstrasse",
    "iso:country":"AT",
    "sg:address":"Franziskanerstrasse 9 ",
    "sg:city":"Frauenkirchen",
    "sg:classifiers":[
        {
            "category":"Manufacturing",
            "subcategory":"Glass & Minerals",
            "type":"Manufacturing & Wholesale Goods"
        }
    ],
    "sg:phone":"+43 2172 2553",
    "sg:postcode":"7132",
    "sg:province":"Burgenland",
    "sg:tags":[
        "cleaning",
        "agent"
    ],
    "sg:website":"www.kettner-optik.at",
    "wof:name":"Anton Kettner & Co KG",
    "wof:placetype":"venue"
},
  "geometry": {"coordinates":[16.925453186,47.8357772827],"type":"Point"}
}