{
  "type": "Feature",
  "properties": {
    "iso:country":"AT",
    "sg:address":"Dietersdorf 72",
    "sg:city":"Wundschuh",
    "sg:orig_category":"Brunnen U Brunnenbau",
    "sg:phone":"+43 3136 52993",
    "sg:postcode":"8142",
    "sg:province":"Steiermark",
    "wof:name":"Mlasko Richard",
    "wof:placetype":"venue"
},
  "geometry": {"coordinates":[15.4498796463,46.9254493713],"type":"Point"}
}