{
  "type": "Feature",
  "properties": {
    "addr:full":"Unterdorf 5 Westendorf Tirol 6363",
    "addr:housenumber":"5",
    "addr:postcode":"6363",
    "addr:street":"Unterdorf",
    "iso:country":"AT",
    "sg:address":"Unterdorf 5",
    "sg:city":"Westendorf",
    "sg:orig_category":"Pensionen / Privatzimmer",
    "sg:phone":"+43 5334 6295",
    "sg:postcode":"6363",
    "sg:province":"Tirol",
    "wof:name":"Aschaber Sylvia KEG",
    "wof:placetype":"venue"
},
  "geometry": {"coordinates":[12.213476181,47.432144165],"type":"Point"}
}