{
  "type": "Feature",
  "properties": {
    "addr:full":"Sonnegg 14 Fulpmes Tirol 6166",
    "addr:housenumber":"14",
    "addr:postcode":"6166",
    "addr:street":"Sonnegg;Tirol",
    "iso:country":"AT",
    "sg:address":"Sonnegg 14",
    "sg:city":"Fulpmes",
    "sg:orig_category":"Rauchfangkehrer",
    "sg:phone":"+43 5225 63192",
    "sg:postcode":"6166",
    "sg:province":"Tirol",
    "wof:name":"Pfurtscheller Ernst",
    "wof:placetype":"venue"
},
  "geometry": {"coordinates":[11.3420238495,47.1441307068],"type":"Point"}
}