{
  "type": "Feature",
  "properties": {
    "addr:full":"Puchberger Str 98 Willendorf am Steinfelde Nieder\u00f6sterreich 2732",
    "addr:postcode":"2732",
    "addr:street":"Str;Niederoesterreich",
    "iso:country":"AT",
    "sg:address":"Puchberger Str 98",
    "sg:city":"Willendorf am Steinfelde",
    "sg:orig_category":"Erdarbeiten",
    "sg:phone":"+43 4326 202864",
    "sg:postcode":"2732",
    "sg:province":"Nieder\u00f6sterreich",
    "wof:name":"Merian Hannelore - Deichgr\u00e4berei - Erdbewegung",
    "wof:placetype":"venue"
},
  "geometry": {"coordinates":[16.0432529449,47.7918243408],"type":"Point"}
}