{
  "type": "Feature",
  "properties": {
    "addr:full":"Talkbrunnenweg 2 Bad Kleinkirchheim K\u00e4rnten 9546",
    "addr:housenumber":"2",
    "addr:postcode":"9546",
    "addr:street":"Talkbrunnenweg",
    "iso:country":"AT",
    "sg:address":"Talkbrunnenweg 2",
    "sg:city":"Bad Kleinkirchheim",
    "sg:orig_category":"Appartements / Ferienwohnungen",
    "sg:phone":"+43 664 3376855",
    "sg:postcode":"9546",
    "sg:province":"K\u00e4rnten",
    "wof:name":"Appartementvermietung Bach-Bad Kleinkirchheim GesmbH",
    "wof:placetype":"venue"
},
  "geometry": {"coordinates":[13.7834672928,46.809551239],"type":"Point"}
}