{
  "type": "Feature",
  "properties": {
    "iso:country":"AT",
    "sg:address":"Markt 69",
    "sg:city":"Schwarzau im Gebirge",
    "sg:orig_category":"Feuerwehren",
    "sg:phone":"+43 2667 200",
    "sg:postcode":"2662",
    "sg:province":"Nieder\u00f6sterreich",
    "wof:name":"Freiwillige Feuerwehr Schwarzau i Gebirge",
    "wof:placetype":"venue"
},
  "geometry": {"coordinates":[15.7046060562,47.8125152588],"type":"Point"}
}