{
  "type": "Feature",
  "properties": {
    "addr:full":"Tegetthoffstr 34 Linz Ober\u00f6sterreich 4020",
    "addr:housenumber":"34",
    "addr:postcode":"4020",
    "addr:street":"Tegetthoffstr",
    "iso:country":"AT",
    "sg:address":"Tegetthoffstr 34",
    "sg:city":"Linz",
    "sg:orig_category":"Gastronomie- U Hoteleinrichtungen",
    "sg:phone":"+43 4366 43830381",
    "sg:postcode":"4020",
    "sg:province":"Ober\u00f6sterreich",
    "wof:name":"Sani Air Austria - Langaditis Nikos",
    "wof:placetype":"venue"
},
  "geometry": {"coordinates":[14.2883386612,48.2934265137],"type":"Point"}
}