{
  "type": "Feature",
  "properties": {
    "addr:full":"Langackerg 36 Wien Wien 1190",
    "addr:housenumber":"36",
    "addr:postcode":"1190",
    "addr:street":"Langackerg",
    "iso:country":"AT",
    "sg:address":"Langackerg 36",
    "sg:city":"Wien",
    "sg:orig_category":"Schauspielschulen",
    "sg:phone":"+43 1 3205652",
    "sg:postcode":"1190",
    "sg:province":"Wien",
    "wof:name":"Janisch Mara Dr",
    "wof:placetype":"venue"
},
  "geometry": {"coordinates":[16.3524188995,48.2575569153],"type":"Point"}
}