{
  "type": "Feature",
  "properties": {
    "addr:full":"B\u00f6cksteiner Bundesstr. 15-17 Bad Gastein Salzburg 5640",
    "addr:housenumber":"15-17",
    "addr:postcode":"5640",
    "addr:street":"Salzburg",
    "iso:country":"AT",
    "sg:address":"B\u00f6cksteiner Bundesstr. 15-17",
    "sg:city":"Bad Gastein",
    "sg:classifiers":[
        {
            "category":"Utilities",
            "subcategory":"Electric",
            "type":"Services"
        }
    ],
    "sg:phone":"+43 4364 3424450",
    "sg:postcode":"5640",
    "sg:province":"Salzburg",
    "sg:tags":[
        "energy"
    ],
    "wof:name":"THOMAS GR\u00dcBLER OHG",
    "wof:placetype":"venue"
},
  "geometry": {"coordinates":[13.1341981888,47.1053504944],"type":"Point"}
}