{
  "type": "Feature",
  "properties": {
    "iso:country":"AT",
    "sg:address":"Rasumofskyg 7/6",
    "sg:city":"Wien",
    "sg:orig_category":"Bekleidung / Einzelhandel",
    "sg:phone":"+43 699 10635781",
    "sg:postcode":"1030",
    "sg:province":"Wien",
    "wof:name":"Prandst\u00e4tter Verena - VON HAND",
    "wof:placetype":"venue"
},
  "geometry": {"coordinates":[16.394947052,48.2055854797],"type":"Point"}
}