{
  "type": "Feature",
  "properties": {
    "iso:country":"AT",
    "sg:address":"Krottenbachstr 106a",
    "sg:city":"Wien",
    "sg:orig_category":"Friseure U Frisiersalons",
    "sg:phone":"+43 1 3697177",
    "sg:postcode":"1190",
    "sg:province":"Wien",
    "wof:name":"Krones Karl",
    "wof:placetype":"venue"
},
  "geometry": {"coordinates":[16.3270511627,48.242023468],"type":"Point"}
}