{
  "type": "Feature",
  "properties": {
    "addr:full":"Friedlach 42 Glanegg K\u00e4rnten 9555",
    "addr:housenumber":"42",
    "addr:postcode":"9555",
    "addr:street":"Friedlach;Kaernten",
    "iso:country":"AT",
    "sg:address":"Friedlach 42",
    "sg:city":"Glanegg",
    "sg:orig_category":"Maler, Anstreicher U Lackierer",
    "sg:phone":"+43 4342 772374",
    "sg:postcode":"9555",
    "sg:province":"K\u00e4rnten",
    "wof:name":"Novak Josef",
    "wof:placetype":"venue"
},
  "geometry": {"coordinates":[14.193860054,46.7225036621],"type":"Point"}
}