{
  "type": "Feature",
  "properties": {
    "addr:full":"Hauptpl 29 Pitten Nieder\u00f6sterreich 2823",
    "addr:housenumber":"29",
    "addr:postcode":"2823",
    "addr:street":"Hauptpl",
    "iso:country":"AT",
    "sg:address":"Hauptpl 29",
    "sg:city":"Pitten",
    "sg:orig_category":"Banken U Sparkassen",
    "sg:phone":"+43 2627 825800",
    "sg:postcode":"2823",
    "sg:province":"Nieder\u00f6sterreich",
    "wof:name":"Sparkasse Neunkirchen-Gloggnitz-Ternitz",
    "wof:placetype":"venue"
},
  "geometry": {"coordinates":[16.1865634918,47.7161407471],"type":"Point"}
}