{
  "type": "Feature",
  "properties": {
    "iso:country":"AT",
    "sg:address":"Florianig 29",
    "sg:city":"Wien",
    "sg:orig_category":"Glasereien",
    "sg:phone":"+43 1 4063329",
    "sg:postcode":"1080",
    "sg:province":"Wien",
    "wof:name":"Glas Frank GesmbH & Co KG",
    "wof:placetype":"venue"
},
  "geometry": {"coordinates":[16.349729538,48.2117614746],"type":"Point"}
}