{
  "type": "Feature",
  "properties": {
    "addr:full":"Lindhofstr 2 Wolfsberg K\u00e4rnten 9400",
    "addr:housenumber":"2;kaernten",
    "addr:postcode":"9400",
    "addr:street":"Lindhofstr",
    "iso:country":"AT",
    "sg:address":"Lindhofstr 2",
    "sg:city":"Wolfsberg",
    "sg:orig_category":"Bestattungsunternehmen",
    "sg:phone":"+43 4343 522792",
    "sg:postcode":"9400",
    "sg:province":"K\u00e4rnten",
    "wof:name":"Bestattung der Stadt Wolfsberg",
    "wof:placetype":"venue"
},
  "geometry": {"coordinates":[14.8440198898,46.8334922791],"type":"Point"}
}