{
  "type": "Feature",
  "properties": {
    "addr:full":"Bahnhofstrasse 429 Schladming Steiermark 8970",
    "addr:housenumber":"429",
    "addr:postcode":"8970",
    "addr:street":"Bahnhofstrasse",
    "iso:country":"AT",
    "sg:address":"Bahnhofstrasse 429",
    "sg:city":"Schladming",
    "sg:classifiers":[
        {
            "category":"Manufacturing",
            "subcategory":"Wood Products",
            "type":"Manufacturing & Wholesale Goods"
        }
    ],
    "sg:phone":"+43 3687 22371",
    "sg:postcode":"8970",
    "sg:province":"Steiermark",
    "sg:tags":[
        "made",
        "balcony"
    ],
    "wof:name":"Ing. Herbert Tritscher",
    "wof:placetype":"venue"
},
  "geometry": {"coordinates":[13.6805505753,47.393573761],"type":"Point"}
}