{
  "type": "Feature",
  "properties": {
    "addr:full":"Braunhirschengasse 12-20/3/9  Wien Wien 1150",
    "addr:housenumber":"12-20 / 3 / 9",
    "addr:postcode":"1150",
    "addr:street":"Braunhirschengasse",
    "iso:country":"AT",
    "sg:address":"Braunhirschengasse 12-20/3/9 ",
    "sg:city":"Wien",
    "sg:classifiers":[
        {
            "category":"Building & Trades",
            "subcategory":"Plumbing",
            "type":"Services"
        }
    ],
    "sg:phone":"+43 1 8936417",
    "sg:postcode":"1150",
    "sg:province":"Wien",
    "sg:tags":[
        "supraregional",
        "gas"
    ],
    "sg:website":"www.vetter.co.at",
    "wof:name":"Erich Vetter Ges.m.b.H.",
    "wof:placetype":"venue"
},
  "geometry": {"coordinates":[16.3320903778,48.2006416321],"type":"Point"}
}