{
  "type": "Feature",
  "properties": {
    "addr:full":"Neustiftstr 50 Frauenkirchen Burgenland 7132",
    "addr:housenumber":"50",
    "addr:postcode":"7132",
    "addr:street":"Neustiftstr",
    "iso:country":"AT",
    "sg:address":"Neustiftstr 50",
    "sg:city":"Frauenkirchen",
    "sg:orig_category":"Rauchfangkehrer",
    "sg:phone":"+43 4321 723378",
    "sg:postcode":"7132",
    "sg:province":"Burgenland",
    "wof:name":"Mateju Franz",
    "wof:placetype":"venue"
},
  "geometry": {"coordinates":[16.9190368652,47.8410186768],"type":"Point"}
}