{
  "type": "Feature",
  "properties": {
    "addr:full":"Nr 70 Aigen-Voglhub Salzburg 5351",
    "addr:postcode":"5351",
    "addr:street":"Nr 70 Aigen-Voglhub Salzburg",
    "iso:country":"AT",
    "sg:address":"Nr 70",
    "sg:city":"Aigen-Voglhub",
    "sg:orig_category":"Gastronomie- U Hotelbedarf",
    "sg:phone":"+43 6137 5416",
    "sg:postcode":"5351",
    "sg:province":"Salzburg",
    "wof:name":"Werndl C+C Inh Windhofer-Werndl Margit",
    "wof:placetype":"venue"
},
  "geometry": {"coordinates":[13.5863456726,47.7190666199],"type":"Point"}
}