{
  "type": "Feature",
  "properties": {
    "iso:country":"AT",
    "sg:address":"Machlandstrasse 2",
    "sg:city":"Mauthausen",
    "sg:classifiers":[
        {
            "category":"Home & Garden",
            "subcategory":"Building Materials",
            "type":"Retail Goods"
        }
    ],
    "sg:phone":"+43 7238 24470",
    "sg:postcode":"4310",
    "sg:province":"Ober\u00f6sterreich",
    "sg:tags":[
        "installation",
        "electric"
    ],
    "wof:name":"Ernst Haslinger",
    "wof:placetype":"venue"
},
  "geometry": {"coordinates":[14.5336322784,48.2428474426],"type":"Point"}
}