{
  "type": "Feature",
  "properties": {
    "addr:full":"Gallmeyerg 15 Graz Steiermark 8020",
    "addr:housenumber":"15",
    "addr:postcode":"8020",
    "addr:street":"Gallmeyerg",
    "iso:country":"AT",
    "sg:address":"Gallmeyerg 15",
    "sg:city":"Graz",
    "sg:orig_category":"Suchtberatung / Alkohol, Drogen, Zigaretten",
    "sg:phone":"+43 316 578783",
    "sg:postcode":"8020",
    "sg:province":"Steiermark",
    "wof:name":"Dopplinger Reinhard Mag - Blaues Kreuz",
    "wof:placetype":"venue"
},
  "geometry": {"coordinates":[15.3992071152,47.0620002747],"type":"Point"}
}