{
  "type": "Feature",
  "properties": {
    "addr:full":"Scheydgasse 44 Wien Wien 1210",
    "addr:housenumber":"44",
    "addr:postcode":"1210",
    "addr:street":"Scheydgasse",
    "iso:country":"AT",
    "sg:address":"Scheydgasse 44",
    "sg:city":"Wien",
    "sg:classifiers":[
        {
            "category":"Manufacturing",
            "subcategory":"Metals",
            "type":"Manufacturing & Wholesale Goods"
        }
    ],
    "sg:phone":"+43 4312 7737",
    "sg:postcode":"1210",
    "sg:province":"Wien",
    "sg:tags":[
        "metallurgy",
        "metalworking"
    ],
    "wof:name":"SANDVIK IN AUSTRIA GMBH",
    "wof:placetype":"venue"
},
  "geometry": {"coordinates":[16.3729667664,48.283454895],"type":"Point"}
}