{
  "type": "Feature",
  "properties": {
    "addr:full":"Steierm\u00e4rker Str 12 Kirchdorf an der Krems Ober\u00f6sterreich 4560",
    "addr:housenumber":"12",
    "addr:postcode":"4560",
    "addr:street":"Str",
    "iso:country":"AT",
    "sg:address":"Steierm\u00e4rker Str 12",
    "sg:city":"Kirchdorf an der Krems",
    "sg:orig_category":"Glasereien",
    "sg:phone":"+43 4375 8263456",
    "sg:postcode":"4560",
    "sg:province":"Ober\u00f6sterreich",
    "wof:name":"Brocks A & M OEG",
    "wof:placetype":"venue"
},
  "geometry": {"coordinates":[14.123623848,47.9027900696],"type":"Point"}
}