{
  "type": "Feature",
  "properties": {
    "addr:full":"Wildenhag 2 St. Georgen im Attergau Ober\u00f6sterreich 4880",
    "addr:housenumber":"2",
    "addr:postcode":"4880",
    "addr:street":"Wildenhag",
    "iso:country":"AT",
    "sg:address":"Wildenhag 2",
    "sg:city":"St. Georgen im Attergau",
    "sg:orig_category":"Spielwaren U Spiele",
    "sg:phone":"+43 4376 676483",
    "sg:postcode":"4880",
    "sg:province":"Ober\u00f6sterreich",
    "wof:name":"Schneeweiss Roman",
    "wof:placetype":"venue"
},
  "geometry": {"coordinates":[13.4907569885,47.9334526062],"type":"Point"}
}