{
  "type": "Feature",
  "properties": {
    "addr:full":"Badstr 1 G\u00fcssing Burgenland 7540",
    "addr:housenumber":"1",
    "addr:postcode":"7540",
    "addr:street":"Badstr",
    "iso:country":"AT",
    "sg:address":"Badstr 1",
    "sg:city":"G\u00fcssing",
    "sg:orig_category":"Wasserwerke",
    "sg:phone":"+43 3322 423180",
    "sg:postcode":"7540",
    "sg:province":"Burgenland",
    "wof:name":"Wasserbauleitung G\u00fcssing",
    "wof:placetype":"venue"
},
  "geometry": {"coordinates":[16.3196792603,47.0572547913],"type":"Point"}
}