{
  "type": "Feature",
  "properties": {
    "iso:country":"AT",
    "sg:address":"Seebach 18",
    "sg:city":"K\u00fchnsdorf",
    "sg:orig_category":"Tischlereien",
    "sg:phone":"+43 4232 89241",
    "sg:postcode":"9125",
    "sg:province":"K\u00e4rnten",
    "wof:name":"Klemen Johann",
    "wof:placetype":"venue"
},
  "geometry": {"coordinates":[14.6336803436,46.6305084229],"type":"Point"}
}