{
  "type": "Feature",
  "properties": {
    "iso:country":"AT",
    "sg:address":"Nr 9",
    "sg:city":"St. Margareten im Rosental",
    "sg:orig_category":"Gemeinden",
    "sg:phone":"+43 4342 262180",
    "sg:postcode":"9173",
    "sg:province":"K\u00e4rnten",
    "wof:name":"Gemeindeamt St Margarethen im Rosental",
    "wof:placetype":"venue"
},
  "geometry": {"coordinates":[14.4213676453,46.5419616699],"type":"Point"}
}