{
  "type": "Feature",
  "properties": {
    "iso:country":"AT",
    "sg:address":"Seeblickstr 177",
    "sg:city":"Drobollach am Faaker See",
    "sg:orig_category":"Pensionen / Privatzimmer",
    "sg:phone":"+43 4342 542092",
    "sg:postcode":"9580",
    "sg:province":"K\u00e4rnten",
    "wof:name":"Kugi Josef",
    "wof:placetype":"venue"
},
  "geometry": {"coordinates":[13.9272851944,46.5897521973],"type":"Point"}
}