{
  "type": "Feature",
  "properties": {
    "iso:country":"AT",
    "sg:address":"Bahnhofstr 2",
    "sg:city":"F\u00fcrstenfeld",
    "sg:orig_category":"Autoersatzteile",
    "sg:phone":"+43 4333 8254655",
    "sg:postcode":"8280",
    "sg:province":"Steiermark",
    "wof:name":"Monschein G\u00fcnther - Ersatzteile, Reifen u Service",
    "wof:placetype":"venue"
},
  "geometry": {"coordinates":[9.1733436584,47.6517524719],"type":"Point"}
}