{
  "type": "Feature",
  "properties": {
    "addr:full":"Nr 153 Reichenau an der Rax Nieder\u00f6sterreich 2651",
    "addr:postcode":"2651",
    "addr:street":"Nr 153",
    "iso:country":"AT",
    "sg:address":"Nr 153",
    "sg:city":"Reichenau an der Rax",
    "sg:orig_category":"Reifen U Reifendienste",
    "sg:phone":"+43 4326 6655157",
    "sg:postcode":"2651",
    "sg:province":"Nieder\u00f6sterreich",
    "wof:name":"Reifencenter Hirschwang",
    "wof:placetype":"venue"
},
  "geometry": {"coordinates":[15.8102397919,47.7058601379],"type":"Point"}
}