{
  "type": "Feature",
  "properties": {
    "iso:country":"AT",
    "sg:address":"Auwald 15",
    "sg:city":"Ellmau",
    "sg:orig_category":"Biologische Produkte",
    "sg:phone":"+43 4353 5844252",
    "sg:postcode":"6352",
    "sg:province":"Tirol",
    "wof:name":"Primaloe Handels- u Vertriebs GmbH",
    "wof:placetype":"venue"
},
  "geometry": {"coordinates":[12.2762994766,47.5229377747],"type":"Point"}
}