{
  "type": "Feature",
  "properties": {
    "addr:full":"Rottweg 17 Salzburg Salzburg 5020",
    "addr:housenumber":"17",
    "addr:postcode":"5020",
    "addr:street":"Rottweg;Salzburg",
    "iso:country":"AT",
    "sg:address":"Rottweg 17",
    "sg:city":"Salzburg",
    "sg:orig_category":"Lebensmittel / Erzeugung U Gro\u00c3\u0178handel",
    "sg:phone":"+43 4366 24323950",
    "sg:postcode":"5020",
    "sg:province":"Salzburg",
    "wof:name":"Eurogast \u00f6sterreich GesmbH",
    "wof:placetype":"venue"
},
  "geometry": {"coordinates":[13.0059299469,47.8269386292],"type":"Point"}
}