{
  "type": "Feature",
  "properties": {
    "iso:country":"AT",
    "sg:address":"Weiserhofstrasse 18",
    "sg:city":"Salzburg",
    "sg:classifiers":[
        {
            "category":"Banks & Credit Unions",
            "subcategory":"Bank",
            "type":"Services"
        }
    ],
    "sg:phone":"+43 662 8710330",
    "sg:postcode":"5020",
    "sg:province":"Salzburg",
    "sg:tags":[
        "saving",
        "software"
    ],
    "sg:website":"sbs.co.at",
    "wof:name":"SBS Software Ges.m.b.H.",
    "wof:placetype":"venue"
},
  "geometry": {"coordinates":[13.0485515594,47.8140296936],"type":"Point"}
}