{
  "type": "Feature",
  "properties": {
    "iso:country":"AT",
    "sg:address":"Spittelbreiteng 23/27",
    "sg:city":"Wien",
    "sg:orig_category":"Bauunternehmen",
    "sg:phone":"+43 1 8171628",
    "sg:postcode":"1120",
    "sg:province":"Wien",
    "wof:name":"Zaussinger & Co GesmbH",
    "wof:placetype":"venue"
},
  "geometry": {"coordinates":[16.3254833221,48.1763343811],"type":"Point"}
}