{
  "type": "Feature",
  "properties": {
    "addr:full":"Karfreitstr 26 Klagenfurt K\u00e4rnten 9020",
    "addr:housenumber":"26",
    "addr:postcode":"9020",
    "addr:street":"Karfreitstr;Kaernten",
    "iso:country":"AT",
    "sg:address":"Karfreitstr 26",
    "sg:city":"Klagenfurt",
    "sg:classifiers":[
        {
            "category":"Home & Garden",
            "subcategory":"Building Materials",
            "type":"Retail Goods"
        }
    ],
    "sg:phone":"+43 4346 3591048",
    "sg:postcode":"9020",
    "sg:province":"K\u00e4rnten",
    "sg:tags":[
        "baustoffe",
        "-material",
        "u"
    ],
    "wof:name":"Aules HandelsgesmbH",
    "wof:placetype":"venue"
},
  "geometry": {"coordinates":[14.3084020615,46.6212463379],"type":"Point"}
}