{
  "type": "Feature",
  "properties": {
    "addr:full":"Bergg 3 Hochwolkersdorf Nieder\u00f6sterreich 2802",
    "addr:housenumber":"3",
    "addr:postcode":"2802",
    "addr:street":"Bergg",
    "iso:country":"AT",
    "sg:address":"Bergg 3",
    "sg:city":"Hochwolkersdorf",
    "sg:orig_category":"Bauleitung U -Betreuung",
    "sg:phone":"+43 4326 458497",
    "sg:postcode":"2802",
    "sg:province":"Nieder\u00f6sterreich",
    "wof:name":"Waldherr Ing GesmbH",
    "wof:placetype":"venue"
},
  "geometry": {"coordinates":[16.2837657928,47.6621856689],"type":"Point"}
}