{
  "type": "Feature",
  "properties": {
    "addr:full":"Elisabethgasse 51-53 Klosterneuburg Nieder\u00f6sterreich 3400",
    "addr:postcode":"51-53;3400",
    "addr:street":"Elisabethgasse;Niederoesterreich",
    "iso:country":"AT",
    "sg:address":"Elisabethgasse 51-53",
    "sg:city":"Klosterneuburg",
    "sg:classifiers":[
        {
            "category":"Professional",
            "subcategory":"Advertising",
            "type":"Services"
        }
    ],
    "sg:phone":"+43 2243 371910",
    "sg:postcode":"3400",
    "sg:province":"Nieder\u00f6sterreich",
    "sg:tags":[
        "marketing",
        "direct"
    ],
    "sg:website":"hc-promotion.at",
    "wof:name":"H. C. System Promotion Corsmann & Co KG",
    "wof:placetype":"venue"
},
  "geometry": {"coordinates":[16.3104476929,48.3061103821],"type":"Point"}
}