{
  "type": "Feature",
  "properties": {
    "addr:full":"Wiener Str 5 Waidhofen an der Thaya Nieder\u00f6sterreich 3830",
    "addr:postcode":"3830",
    "addr:street":"An Der Thaya",
    "iso:country":"AT",
    "sg:address":"Wiener Str 5",
    "sg:city":"Waidhofen an der Thaya",
    "sg:classifiers":[
        {
            "category":"Restaurant",
            "type":"Food & Drink"
        }
    ],
    "sg:phone":"+43 4328 4252911",
    "sg:postcode":"3830",
    "sg:province":"Nieder\u00f6sterreich",
    "wof:name":"Cafe-Restaurant Lorbaer",
    "wof:placetype":"venue"
},
  "geometry": {"coordinates":[15.2883462906,48.8154716492],"type":"Point"}
}