{
  "type": "Feature",
  "properties": {
    "iso:country":"AT",
    "sg:address":"Schallerg 36",
    "sg:city":"Wien",
    "sg:orig_category":"Dolmetscher",
    "sg:phone":"+43 1 8109671",
    "sg:postcode":"1120",
    "sg:province":"Wien",
    "wof:name":"Fuente Medina",
    "wof:placetype":"venue"
},
  "geometry": {"coordinates":[16.3441371918,48.181842804],"type":"Point"}
}