{
  "type": "Feature",
  "properties": {
    "addr:full":"Bahnhofstr 43a Marchtrenk Ober\u00f6sterreich 4614",
    "addr:housenumber":"43a",
    "addr:postcode":"4614",
    "addr:street":"Bahnhofstr",
    "iso:country":"AT",
    "sg:address":"Bahnhofstr 43a",
    "sg:city":"Marchtrenk",
    "sg:orig_category":"Nachhilfe U Lernbetreuung",
    "sg:phone":"+43 7243 52604",
    "sg:postcode":"4614",
    "sg:province":"Ober\u00f6sterreich",
    "wof:name":"Nachhilfeinstitut Marchtrenk",
    "wof:placetype":"venue"
},
  "geometry": {"coordinates":[14.1069002151,48.1961784363],"type":"Point"}
}