{
  "type": "Feature",
  "properties": {
    "addr:full":"Nr 16 Michaelbeuern Salzburg 5152",
    "addr:postcode":"5152",
    "addr:street":"Nr;Michaelbeuern",
    "iso:country":"AT",
    "sg:address":"Nr 16",
    "sg:city":"Michaelbeuern",
    "sg:orig_category":"Autohandel",
    "sg:phone":"+43 6274 8172",
    "sg:postcode":"5152",
    "sg:province":"Salzburg",
    "wof:name":"Auto Wagner",
    "wof:placetype":"venue"
},
  "geometry": {"coordinates":[13.0150594711,48.0233306885],"type":"Point"}
}