{
  "type": "Feature",
  "properties": {
    "iso:country":"AT",
    "sg:address":"Wagramer Str 105",
    "sg:city":"Wien",
    "sg:orig_category":"Restaurants: Chinesisch",
    "sg:phone":"+43 1 2030657",
    "sg:postcode":"1220",
    "sg:province":"Wien",
    "wof:name":"China-Restaurant Tien Tan",
    "wof:placetype":"venue"
},
  "geometry": {"coordinates":[16.4391994476,48.2459220886],"type":"Point"}
}