{
  "type": "Feature",
  "properties": {
    "iso:country":"AT",
    "sg:address":"K\u00e4rntner Str 51",
    "sg:city":"Wien",
    "sg:orig_category":"Damenmoden",
    "sg:phone":"+43 4315 1278010",
    "sg:postcode":"1010",
    "sg:province":"Wien",
    "sg:website":"popp-kretschmer.at",
    "wof:name":"Popp & Kretschmer",
    "wof:placetype":"venue"
},
  "geometry": {"coordinates":[16.3688049316,48.2025489807],"type":"Point"}
}