{
  "type": "Feature",
  "properties": {
    "addr:full":"Gewerbepark 4 Hart Steiermark 8075",
    "addr:housenumber":"4",
    "addr:postcode":"8075",
    "addr:street":"Gewerbepark",
    "iso:country":"AT",
    "sg:address":"Gewerbepark 4",
    "sg:city":"Hart",
    "sg:orig_category":"Arbeitsschutz U Arbeitsschutzartikel",
    "sg:phone":"+43 4331 64916920",
    "sg:postcode":"8075",
    "sg:province":"Steiermark",
    "wof:name":"Schloffer Arbeitsschutz GmbH",
    "wof:placetype":"venue"
},
  "geometry": {"coordinates":[15.5162229538,47.0439682007],"type":"Point"}
}