{
  "type": "Feature",
  "properties": {
    "addr:full":"St. Marxen 6 K\u00fchnsdorf K\u00e4rnten 9125",
    "addr:housenumber":"6",
    "addr:postcode":"9125",
    "addr:street":"Kuehnsdorf Kaernten",
    "iso:country":"AT",
    "sg:address":"St. Marxen 6",
    "sg:city":"K\u00fchnsdorf",
    "sg:orig_category":"Maler, Anstreicher U Lackierer",
    "sg:phone":"+43 4366 45446941",
    "sg:postcode":"9125",
    "sg:province":"K\u00e4rnten",
    "wof:name":"Desigenparkett-GMBH",
    "wof:placetype":"venue"
},
  "geometry": {"coordinates":[14.6234197617,46.6314315796],"type":"Point"}
}