{
  "type": "Feature",
  "properties": {
    "addr:full":"Puitweg 10 Tarrenz Tirol 6464",
    "addr:housenumber":"10",
    "addr:postcode":"6464",
    "addr:street":"Puitweg;Tirol",
    "iso:country":"AT",
    "sg:address":"Puitweg 10",
    "sg:city":"Tarrenz",
    "sg:classifiers":[
        {
            "category":"Professional",
            "subcategory":"Art Services",
            "type":"Services"
        }
    ],
    "sg:phone":"+43 5412 61240",
    "sg:postcode":"6464",
    "sg:province":"Tirol",
    "sg:tags":[
        "designer"
    ],
    "wof:name":"Poschusta Wernfried",
    "wof:placetype":"venue"
},
  "geometry": {"coordinates":[10.7579116821,47.2585830688],"type":"Point"}
}