{
  "type": "Feature",
  "properties": {
    "iso:country":"AT",
    "sg:address":"Zamenhofstr 2",
    "sg:city":"Linz",
    "sg:orig_category":"Blumeneinzelhandel",
    "sg:phone":"+43 732 661220",
    "sg:postcode":"4020",
    "sg:province":"Ober\u00f6sterreich",
    "wof:name":"Blumen Edlinger",
    "wof:placetype":"venue"
},
  "geometry": {"coordinates":[14.3139762878,48.2895965576],"type":"Point"}
}