{
  "type": "Feature",
  "properties": {
    "addr:full":"Neue Heimat 4 Bischofshofen Salzburg 5500",
    "addr:housenumber":"4",
    "addr:postcode":"5500",
    "addr:street":"Neue Heimat;Salzburg",
    "iso:country":"AT",
    "sg:address":"Neue Heimat 4",
    "sg:city":"Bischofshofen",
    "sg:orig_category":"Fahrschulen",
    "sg:phone":"+43 6462 8288",
    "sg:postcode":"5500",
    "sg:province":"Salzburg",
    "wof:name":"Fahrschule Stipek (B\u00fcro + Kurse)",
    "wof:placetype":"venue"
},
  "geometry": {"coordinates":[13.2160148621,47.4235534668],"type":"Point"}
}