{
  "type": "Feature",
  "properties": {
    "addr:full":"Innsbrucker Str 3 Seefeld in Tirol Tirol 6100",
    "addr:housenumber":"3",
    "addr:postcode":"6100",
    "addr:street":"Str;Tirol",
    "iso:country":"AT",
    "sg:address":"Innsbrucker Str 3",
    "sg:city":"Seefeld in Tirol",
    "sg:classifiers":[
        {
            "category":"Travel",
            "subcategory":"Hotels & Motels",
            "type":"Entertainment"
        }
    ],
    "sg:phone":"+43 5212 22930",
    "sg:postcode":"6100",
    "sg:province":"Tirol",
    "wof:name":"Hotel Bergland",
    "wof:placetype":"venue"
},
  "geometry": {"coordinates":[11.1883249283,47.3268280029],"type":"Point"}
}