{
  "type": "Feature",
  "properties": {
    "addr:full":"Raiffeisenstr 2 Oberalm Salzburg 5411",
    "addr:housenumber":"2",
    "addr:postcode":"5411",
    "addr:street":"Raiffeisenstr;Salzburg",
    "iso:country":"AT",
    "sg:address":"Raiffeisenstr 2",
    "sg:city":"Oberalm",
    "sg:orig_category":"Natursteine U -Platten",
    "sg:phone":"+43 4362 4570133",
    "sg:postcode":"5411",
    "sg:province":"Salzburg",
    "wof:name":"Gscho\u00dfmann Felix - Ihr Natursteinpartner",
    "wof:placetype":"venue"
},
  "geometry": {"coordinates":[13.0984249115,47.7006378174],"type":"Point"}
}