{
  "type": "Feature",
  "properties": {
    "addr:full":"Friedhofstr 364 Hoheneich Nieder\u00f6sterreich 3945",
    "addr:housenumber":"364",
    "addr:postcode":"3945",
    "addr:street":"Hoheneich Niederoesterreich",
    "iso:country":"AT",
    "sg:address":"Friedhofstr 364",
    "sg:city":"Hoheneich",
    "sg:orig_category":"Pensionen / Privatzimmer",
    "sg:phone":"+43 2852 52932",
    "sg:postcode":"3945",
    "sg:province":"Nieder\u00f6sterreich",
    "wof:name":"G\u00e4stehaus Sport und Freizeit",
    "wof:placetype":"venue"
},
  "geometry": {"coordinates":[15.0211896896,48.7715263367],"type":"Point"}
}