{
  "type": "Feature",
  "properties": {
    "iso:country":"AT",
    "sg:address":"Salzburger Str 15",
    "sg:city":"St. Johann in Tirol",
    "sg:orig_category":"Lebensmittel / Einzelhandel",
    "sg:phone":"+43 5352 63745",
    "sg:postcode":"6380",
    "sg:province":"Tirol",
    "wof:name":"Billa AG",
    "wof:placetype":"venue"
},
  "geometry": {"coordinates":[12.4230165482,47.52526474],"type":"Point"}
}