{
  "type": "Feature",
  "properties": {
    "addr:full":"Adalbert-Stifter-Str 16 Ried im Innkreis Ober\u00f6sterreich 4910",
    "addr:housenumber":"16",
    "addr:postcode":"4910",
    "addr:street":"Adalbert-Stifter-Str",
    "iso:country":"AT",
    "sg:address":"Adalbert-Stifter-Str 16",
    "sg:city":"Ried im Innkreis",
    "sg:orig_category":"Politische Parteien",
    "sg:phone":"+43 7752 87483",
    "sg:postcode":"4910",
    "sg:province":"Ober\u00f6sterreich",
    "wof:name":"Die Gr\u00fcnen Ried",
    "wof:placetype":"venue"
},
  "geometry": {"coordinates":[13.484749794,48.203540802],"type":"Point"}
}