{
  "type": "Feature",
  "properties": {
    "addr:full":"Spanheimerstr 36 Wolfsberg K\u00e4rnten 9400",
    "addr:housenumber":"36;kaernten",
    "addr:postcode":"9400",
    "addr:street":"Spanheimerstr",
    "iso:country":"AT",
    "sg:address":"Spanheimerstr 36",
    "sg:city":"Wolfsberg",
    "sg:orig_category":"Autohandel",
    "sg:phone":"+43 4352 28020",
    "sg:postcode":"9400",
    "sg:province":"K\u00e4rnten",
    "wof:name":"Porsche Inter Auto KG - Zweigniederlassung Porsche Wolfsberg",
    "wof:placetype":"venue"
},
  "geometry": {"coordinates":[14.8410739899,46.8368911743],"type":"Point"}
}