{
  "type": "Feature",
  "properties": {
    "addr:full":"Berglandweg 6 St. Johann in Tirol Tirol 6380",
    "addr:housenumber":"6",
    "addr:postcode":"6380",
    "addr:street":"Berglandweg;Tirol",
    "iso:country":"AT",
    "sg:address":"Berglandweg 6",
    "sg:city":"St. Johann in Tirol",
    "sg:orig_category":"Pensionen / Privatzimmer",
    "sg:phone":"+43 5352 62956",
    "sg:postcode":"6380",
    "sg:province":"Tirol",
    "wof:name":"Haus Astl",
    "wof:placetype":"venue"
},
  "geometry": {"coordinates":[12.4347982407,47.5258522034],"type":"Point"}
}