{
  "type": "Feature",
  "properties": {
    "iso:country":"AT",
    "sg:address":"Hernalser Hauptstr 165",
    "sg:city":"Wien",
    "sg:orig_category":"Restaurants: Chinesisch",
    "sg:phone":"+43 1 4893246",
    "sg:postcode":"1170",
    "sg:province":"Wien",
    "wof:name":"China-Restaurant Hernals",
    "wof:placetype":"venue"
},
  "geometry": {"coordinates":[16.3170623779,48.2227401733],"type":"Point"}
}