{
  "type": "Feature",
  "properties": {
    "addr:full":"Arkenstr. 38-39  Sulz-R\u00f6this Vorarlberg 6832",
    "addr:housenumber":"38-39",
    "addr:postcode":"6832",
    "addr:street":"Sulz-Roethis Vorarlberg",
    "iso:country":"AT",
    "sg:address":"Arkenstr. 38-39 ",
    "sg:city":"Sulz-R\u00f6this",
    "sg:classifiers":[
        {
            "category":"Communications",
            "subcategory":"Newspaper",
            "type":"Services"
        }
    ],
    "sg:phone":"+43 4355 2244675",
    "sg:postcode":"6832",
    "sg:province":"Vorarlberg",
    "sg:tags":[
        "advertising"
    ],
    "wof:name":"HELMUT HUBER GESMBH & CO KG",
    "wof:placetype":"venue"
},
  "geometry": {"coordinates":[9.6588611603,47.2792854309],"type":"Point"}
}