{
  "type": "Feature",
  "properties": {
    "iso:country":"AT",
    "sg:address":"Staudingerg 13",
    "sg:city":"Wien",
    "sg:orig_category":"Physiotherapie",
    "sg:phone":"+43 1 3343722",
    "sg:postcode":"1200",
    "sg:province":"Wien",
    "wof:name":"PHYSIOFIT 50 PLUS - Elisabeth Rosenberger",
    "wof:placetype":"venue"
},
  "geometry": {"coordinates":[16.3704338074,48.22838974],"type":"Point"}
}