{
  "type": "Feature",
  "properties": {
    "addr:full":"Pottendorfer Strasse 5 Wien Wien 1120",
    "addr:housenumber":"5",
    "addr:postcode":"1120",
    "addr:street":"Pottendorfer Strasse",
    "iso:country":"AT",
    "sg:address":"Pottendorfer Strasse 5",
    "sg:city":"Wien",
    "sg:classifiers":[
        {
            "category":"Freight",
            "type":"Transportation"
        }
    ],
    "sg:phone":"+43 1 81585530",
    "sg:postcode":"1120",
    "sg:province":"Wien",
    "sg:tags":[
        "lift",
        "appliances",
        "lifting"
    ],
    "sg:website":"gemba.at",
    "wof:name":"Gemba Maschinenhandelsges.m.b.H.",
    "wof:placetype":"venue"
},
  "geometry": {"coordinates":[16.3315563202,48.1721611023],"type":"Point"}
}