{
  "type": "Feature",
  "properties": {
    "addr:full":"Herreng 10 Wolfsberg K\u00e4rnten 9400",
    "addr:housenumber":"10;kaernten",
    "addr:postcode":"9400",
    "addr:street":"Herreng",
    "iso:country":"AT",
    "sg:address":"Herreng 10",
    "sg:city":"Wolfsberg",
    "sg:orig_category":"Trachtenbekleidung",
    "sg:phone":"+43 4352 52522",
    "sg:postcode":"9400",
    "sg:province":"K\u00e4rnten",
    "wof:name":"Harrys-Fedyniak Ursula",
    "wof:placetype":"venue"
},
  "geometry": {"coordinates":[14.8424396515,46.8393707275],"type":"Point"}
}