{
  "type": "Feature",
  "properties": {
    "addr:full":"Landstr 70 Linz Ober\u00f6sterreich 4020",
    "addr:housenumber":"70",
    "addr:postcode":"4020",
    "addr:street":"Landstr",
    "iso:country":"AT",
    "sg:address":"Landstr 70",
    "sg:city":"Linz",
    "sg:classifiers":[
        {
            "category":"Restaurant",
            "type":"Food & Drink"
        }
    ],
    "sg:phone":"+43 4373 2785703",
    "sg:postcode":"4020",
    "sg:province":"Ober\u00f6sterreich",
    "sg:tags":[
        "pizzeria"
    ],
    "wof:name":"Pizza Leonardo - BALTA GASTRO KEG",
    "wof:placetype":"venue"
},
  "geometry": {"coordinates":[14.291226387,48.2986907959],"type":"Point"}
}