{
  "type": "Feature",
  "properties": {
    "addr:full":"Karl-Sch\u00f6nherr-Str 7 Friesach K\u00e4rnten 9360",
    "addr:housenumber":"7",
    "addr:postcode":"9360",
    "addr:street":"Karl-Schoenherr-Str;Kaernten",
    "iso:country":"AT",
    "sg:address":"Karl-Sch\u00f6nherr-Str 7",
    "sg:city":"Friesach",
    "sg:orig_category":"Hauptschulen",
    "sg:phone":"+43 4342 682469",
    "sg:postcode":"9360",
    "sg:province":"K\u00e4rnten",
    "wof:name":"Hauptschule",
    "wof:placetype":"venue"
},
  "geometry": {"coordinates":[14.4136791229,46.9477539062],"type":"Point"}
}