{
  "type": "Feature",
  "properties": {
    "iso:country":"AT",
    "sg:address":"Hofrat-Hugo-Steiner-G 3",
    "sg:city":"Bisamberg",
    "sg:orig_category":"Elektroinstallationsunternehmen",
    "sg:phone":"+43 4322 6274808",
    "sg:postcode":"2102",
    "sg:province":"Nieder\u00f6sterreich",
    "wof:name":"K\u00f6gler H-Jung Licht u Kraftstrominstallationen GesmbH",
    "wof:placetype":"venue"
},
  "geometry": {"coordinates":[16.3445110321,48.3336601257],"type":"Point"}
}