{
  "type": "Feature",
  "properties": {
    "addr:full":"Donaufelder Str 211 Wien Wien 1220",
    "addr:housenumber":"211",
    "addr:postcode":"1220",
    "iso:country":"AT",
    "sg:address":"Donaufelder Str 211",
    "sg:city":"Wien",
    "sg:classifiers":[
        {
            "category":"Taxi",
            "type":"Transportation"
        }
    ],
    "sg:phone":"+43 4312 586235",
    "sg:postcode":"1220",
    "sg:province":"Wien",
    "sg:tags":[
        "personentransporte",
        "u"
    ],
    "wof:name":"Lindtner Heinrich u Rosemarie",
    "wof:placetype":"venue"
},
  "geometry": {"coordinates":[16.4358787537,48.2508087158],"type":"Point"}
}