{
  "type": "Feature",
  "properties": {
    "iso:country":"AT",
    "sg:address":"Dorfstr 4",
    "sg:city":"Oetz",
    "sg:orig_category":"Pensionen / Privatzimmer",
    "sg:phone":"+43 5252 6367",
    "sg:postcode":"6433",
    "sg:province":"Tirol",
    "wof:name":"Haus Kuen",
    "wof:placetype":"venue"
},
  "geometry": {"coordinates":[10.896645546,47.2032546997],"type":"Point"}
}