{
  "type": "Feature",
  "properties": {
    "addr:full":"Kaiser-Franz-Josef-Ring 37 Baden Nieder\u00f6sterreich 2500",
    "addr:housenumber":"37",
    "addr:postcode":"2500",
    "addr:street":"Kaiser-Franz-Josef-Ring;Niederoesterreich",
    "iso:country":"AT",
    "sg:address":"Kaiser-Franz-Josef-Ring 37",
    "sg:city":"Baden",
    "sg:orig_category":"Steuerberatung",
    "sg:phone":"+43 4322 522070",
    "sg:postcode":"2500",
    "sg:province":"Nieder\u00f6sterreich",
    "wof:name":"Jaitler Heinz A",
    "wof:placetype":"venue"
},
  "geometry": {"coordinates":[16.2343502045,48.0049934387],"type":"Point"}
}