{
  "type": "Feature",
  "properties": {
    "iso:country":"AT",
    "sg:address":"Landstr 52/2",
    "sg:city":"Zwettl",
    "sg:orig_category":"Ingenieurkonsulenten / Zivilingenieure",
    "sg:phone":"+43 2822 52096",
    "sg:postcode":"3910",
    "sg:province":"Nieder\u00f6sterreich",
    "wof:name":"Zehetgruber Johann Dipl-Ing",
    "wof:placetype":"venue"
},
  "geometry": {"coordinates":[15.1657934189,48.6062698364],"type":"Point"}
}