{
  "type": "Feature",
  "properties": {
    "iso:country":"AT",
    "sg:address":"Nr 53",
    "sg:city":"Texing",
    "sg:orig_category":"Fenster",
    "sg:phone":"+43 4327 557281",
    "sg:postcode":"3242",
    "sg:province":"Nieder\u00f6sterreich",
    "wof:name":"Wippel Leopold - JOSKO",
    "wof:placetype":"venue"
},
  "geometry": {"coordinates":[15.3228321075,48.0478782654],"type":"Point"}
}