{
  "type": "Feature",
  "properties": {
    "addr:full":"Hauptstr 105 Henndorf am Wallersee Salzburg 5302",
    "addr:housenumber":"105",
    "addr:postcode":"5302",
    "addr:street":"Hauptstr;Salzburg",
    "iso:country":"AT",
    "sg:address":"Hauptstr 105",
    "sg:city":"Henndorf am Wallersee",
    "sg:orig_category":"Autoreparatur",
    "sg:phone":"+43 4362 1482910",
    "sg:postcode":"5302",
    "sg:province":"Salzburg",
    "wof:name":"K\u00fccher GmbH & Co KG",
    "wof:placetype":"venue"
},
  "geometry": {"coordinates":[13.193561554,47.9058036804],"type":"Point"}
}