{
  "type": "Feature",
  "properties": {
    "addr:full":"Klaudiastrasse 6 Dornbirn Vorarlberg 6850",
    "addr:housenumber":"6",
    "addr:postcode":"6850",
    "addr:street":"Klaudiastrasse",
    "iso:country":"AT",
    "sg:address":"Klaudiastrasse 6",
    "sg:city":"Dornbirn",
    "sg:classifiers":[
        {
            "category":"Professional",
            "type":"Services"
        }
    ],
    "sg:phone":"+43 5572 241260",
    "sg:postcode":"6850",
    "sg:province":"Vorarlberg",
    "sg:tags":[
        "leasing"
    ],
    "sg:website":"hyposuedleasing.at",
    "wof:name":"Hypo S\u00fcdleasing GmbH",
    "wof:placetype":"venue"
},
  "geometry": {"coordinates":[9.7467899323,47.414516449],"type":"Point"}
}