{
  "type": "Feature",
  "properties": {
    "iso:country":"AT",
    "sg:address":"Wimmerg 33",
    "sg:city":"Wien",
    "sg:classifiers":[
        {
            "category":"Professional",
            "subcategory":"Computer Services",
            "type":"Services"
        }
    ],
    "sg:phone":"+43 1 5455260",
    "sg:postcode":"1050",
    "sg:province":"Wien",
    "sg:tags":[
        "software"
    ],
    "wof:name":"SCHWEIGHOFER Manager-Software GesmbH & Co KG",
    "wof:placetype":"venue"
},
  "geometry": {"coordinates":[16.3570175171,48.1862335205],"type":"Point"}
}