{
  "type": "Feature",
  "properties": {
    "addr:full":"Ruster Str 114a Eisenstadt Burgenland 7000",
    "addr:postcode":"7000",
    "addr:street":"Str 114A",
    "iso:country":"AT",
    "sg:address":"Ruster Str 114a",
    "sg:city":"Eisenstadt",
    "sg:orig_category":"Fitnesscenter",
    "sg:phone":"+43 2682 75885",
    "sg:postcode":"7000",
    "sg:province":"Burgenland",
    "wof:name":"Slender You & Sun - Melitta Pauer",
    "wof:placetype":"venue"
},
  "geometry": {"coordinates":[16.530002594,47.8331985474],"type":"Point"}
}