{
  "type": "Feature",
  "properties": {
    "iso:country":"AT",
    "sg:address":"Rasumofskyg 7",
    "sg:city":"Wien",
    "sg:orig_category":"Besonderes",
    "sg:phone":"+43 4317 1508320",
    "sg:postcode":"1030",
    "sg:province":"Wien",
    "sg:website":"osgar.at",
    "wof:name":"1A Betriebseinrichtungen OSGAR GmbH",
    "wof:placetype":"venue"
},
  "geometry": {"coordinates":[16.394947052,48.2055854797],"type":"Point"}
}