{
  "type": "Feature",
  "properties": {
    "addr:full":"Wiegelestr 26 Wien Wien 1230",
    "addr:housenumber":"26",
    "addr:postcode":"1230",
    "addr:street":"Wiegelestr",
    "iso:country":"AT",
    "sg:address":"Wiegelestr 26",
    "sg:city":"Wien",
    "sg:orig_category":"Etiketten",
    "sg:phone":"+43 1 61636380",
    "sg:postcode":"1230",
    "sg:province":"Wien",
    "sg:website":"www.ulikett.at",
    "wof:name":"ULIKETT GmbH Etiketten und Rollendruck",
    "wof:placetype":"venue"
},
  "geometry": {"coordinates":[16.2956066132,48.1524047852],"type":"Point"}
}