{
  "type": "Feature",
  "properties": {
    "addr:full":"Karl-Egon-Str 189 Weitra Nieder\u00f6sterreich 3970",
    "addr:housenumber":"189",
    "addr:postcode":"3970",
    "addr:street":"Niederoesterreich",
    "iso:country":"AT",
    "sg:address":"Karl-Egon-Str 189",
    "sg:city":"Weitra",
    "sg:orig_category":"Lebensmittel / Einzelhandel",
    "sg:phone":"+43 4328 562029",
    "sg:postcode":"3970",
    "sg:province":"Nieder\u00f6sterreich",
    "wof:name":"Billa AG",
    "wof:placetype":"venue"
},
  "geometry": {"coordinates":[14.8928060532,48.7005844116],"type":"Point"}
}