{
  "type": "Feature",
  "properties": {
    "addr:full":"Golfstr 17 Zell am See Salzburg 5700",
    "addr:housenumber":"17",
    "addr:postcode":"5700",
    "addr:street":"Golfstr;Salzburg",
    "iso:country":"AT",
    "sg:address":"Golfstr 17",
    "sg:city":"Zell am See",
    "sg:orig_category":"Rauchfangkehrer",
    "sg:phone":"+43 6542 563720",
    "sg:postcode":"5700",
    "sg:province":"Salzburg",
    "wof:name":"Buzanich Franz",
    "wof:placetype":"venue"
},
  "geometry": {"coordinates":[12.7738351822,47.2945289612],"type":"Point"}
}