{
  "type": "Feature",
  "properties": {
    "iso:country":"AT",
    "sg:address":"Rooseveltpl 10",
    "sg:city":"Wien",
    "sg:orig_category":"Institute",
    "sg:phone":"+43 4314 27732801",
    "sg:postcode":"1090",
    "sg:province":"Wien",
    "wof:name":"Institut f Praktische Theologie u Religionspsychologie d Uni Wien",
    "wof:placetype":"venue"
},
  "geometry": {"coordinates":[16.3580417633,48.2160797119],"type":"Point"}
}