{
  "type": "Feature",
  "properties": {
    "addr:full":"Schlo\u00dfstr 2 Kirchberg an der Pielach Nieder\u00f6sterreich 3204",
    "addr:housenumber":"2",
    "addr:postcode":"3204",
    "addr:street":"Schlossstr",
    "iso:country":"AT",
    "sg:address":"Schlo\u00dfstr 2",
    "sg:city":"Kirchberg an der Pielach",
    "sg:orig_category":"Banken U Sparkassen",
    "sg:phone":"+43 4327 2226060",
    "sg:postcode":"3204",
    "sg:province":"Nieder\u00f6sterreich",
    "wof:name":"Bankomat der Volksbank N\u00f6 Mitte regGenmbH",
    "wof:placetype":"venue"
},
  "geometry": {"coordinates":[15.4298191071,48.0257797241],"type":"Point"}
}