{
  "type": "Feature",
  "properties": {
    "addr:full":"Dorfstr 24 St. Anton am Arlberg Tirol 6580",
    "addr:housenumber":"24",
    "addr:postcode":"6580",
    "addr:street":"Dorfstr;Tirol",
    "iso:country":"AT",
    "sg:address":"Dorfstr 24",
    "sg:city":"St. Anton am Arlberg",
    "sg:orig_category":"Appartements / Ferienwohnungen",
    "sg:phone":"+43 4354 462020",
    "sg:postcode":"6580",
    "sg:province":"Tirol",
    "wof:name":"Haus Mazora",
    "wof:placetype":"venue"
},
  "geometry": {"coordinates":[10.2649717331,47.1279182434],"type":"Point"}
}