{
  "type": "Feature",
  "properties": {
    "addr:full":"Untere Donaustr 13-15 Wien Wien 1020",
    "addr:postcode":"13-15;1020",
    "addr:street":"Untere Donaustr",
    "iso:country":"AT",
    "sg:address":"Untere Donaustr 13-15",
    "sg:city":"Wien",
    "sg:classifiers":[
        {
            "category":"Professional",
            "subcategory":"Computer Services",
            "type":"Services"
        }
    ],
    "sg:phone":"+43 1 51400",
    "sg:postcode":"1020",
    "sg:province":"Wien",
    "sg:tags":[
        "software"
    ],
    "wof:name":"BAWAG P.S.K. Datendienst GesmbH",
    "wof:placetype":"venue"
},
  "geometry": {"coordinates":[16.3816261292,48.2124938965],"type":"Point"}
}