{
  "type": "Feature",
  "properties": {
    "iso:country":"AT",
    "sg:address":"Kirchstetterng 7-9",
    "sg:city":"Wien",
    "sg:orig_category":"Gastronomie- U Hoteleinrichtungen",
    "sg:phone":"+43 4314 952377",
    "sg:postcode":"1160",
    "sg:province":"Wien",
    "sg:website":"rostfrei.co.at",
    "wof:name":"Rostfrei-Metallbau Eckhardt GesmbH",
    "wof:placetype":"venue"
},
  "geometry": {"coordinates":[16.3313465118,48.2051734924],"type":"Point"}
}