{
  "type": "Feature",
  "properties": {
    "addr:full":"Hauptstr 6 Blindenmarkt Nieder\u00f6sterreich 3372",
    "addr:housenumber":"6",
    "addr:postcode":"3372",
    "addr:street":"Hauptstr",
    "iso:country":"AT",
    "sg:address":"Hauptstr 6",
    "sg:city":"Blindenmarkt",
    "sg:orig_category":"Textilreinigung",
    "sg:phone":"+43 7473 6104",
    "sg:postcode":"3372",
    "sg:province":"Nieder\u00f6sterreich",
    "wof:name":"H\u00f6sl Maria",
    "wof:placetype":"venue"
},
  "geometry": {"coordinates":[14.9916553497,48.1288375854],"type":"Point"}
}