{
  "type": "Feature",
  "properties": {
    "addr:full":"D\u00f6rferstr 29 Thaur Tirol 6065",
    "addr:housenumber":"29",
    "addr:postcode":"6065",
    "addr:street":"Doerferstr;Tirol",
    "iso:country":"AT",
    "sg:address":"D\u00f6rferstr 29",
    "sg:city":"Thaur",
    "sg:orig_category":"Werbeagenturen",
    "sg:phone":"+43 699 11203302",
    "sg:postcode":"6065",
    "sg:province":"Tirol",
    "wof:name":"fraufischer - b\u00fcro f\u00fcr visuelle kommunikation",
    "wof:placetype":"venue"
},
  "geometry": {"coordinates":[11.4780483246,47.2929458618],"type":"Point"}
}