{
  "type": "Feature",
  "properties": {
    "addr:full":"Nr 399 Kappl Tirol 6555",
    "addr:postcode":"6555",
    "addr:street":"Nr 399;Tirol",
    "iso:country":"AT",
    "sg:address":"Nr 399",
    "sg:city":"Kappl",
    "sg:classifiers":[
        {
            "category":"Travel",
            "subcategory":"Hotels & Motels",
            "type":"Entertainment"
        }
    ],
    "sg:phone":"+43 5445 64520",
    "sg:postcode":"6555",
    "sg:province":"Tirol",
    "wof:name":"Hotel-Restaurant Christophorus",
    "wof:placetype":"venue"
},
  "geometry": {"coordinates":[10.3749132156,47.0630874634],"type":"Point"}
}