{
  "type": "Feature",
  "properties": {
    "addr:full":"Salzburger Str 24 Braunau am Inn Ober\u00f6sterreich 5280",
    "addr:housenumber":"24",
    "addr:postcode":"5280",
    "addr:street":"Salzburger Str",
    "iso:country":"AT",
    "sg:address":"Salzburger Str 24",
    "sg:city":"Braunau am Inn",
    "sg:orig_category":"Friseure U Frisiersalons",
    "sg:phone":"+43 4377 2262756",
    "sg:postcode":"5280",
    "sg:province":"Ober\u00f6sterreich",
    "wof:name":"Bauder Erich",
    "wof:placetype":"venue"
},
  "geometry": {"coordinates":[13.0347232819,48.2531471252],"type":"Point"}
}