{
  "type": "Feature",
  "properties": {
    "iso:country":"AT",
    "sg:address":"Sch\u00fctzab\u00fchl 6",
    "sg:city":"Mittelberg",
    "sg:orig_category":"Pensionen / Privatzimmer",
    "sg:phone":"+43 5517 32860",
    "sg:postcode":"6993",
    "sg:province":"Vorarlberg",
    "wof:name":"Haus Markus",
    "wof:placetype":"venue"
},
  "geometry": {"coordinates":[10.1548366547,47.3239440918],"type":"Point"}
}