{
  "type": "Feature",
  "properties": {
    "addr:full":"Gebhard-Wei\u00df-G 4 Bregenz Vorarlberg 6900",
    "addr:housenumber":"4",
    "addr:postcode":"6900",
    "addr:street":"Gebhard-Weiss-G",
    "iso:country":"AT",
    "sg:address":"Gebhard-Wei\u00df-G 4",
    "sg:city":"Bregenz",
    "sg:orig_category":"Hausbetreuung",
    "sg:phone":"+43 5574 44921",
    "sg:postcode":"6900",
    "sg:province":"Vorarlberg",
    "wof:name":"Udovicic Zoran",
    "wof:placetype":"venue"
},
  "geometry": {"coordinates":[9.7477378845,47.5041885376],"type":"Point"}
}