{
  "type": "Feature",
  "properties": {
    "iso:country":"AT",
    "sg:address":"Plonerweg 2",
    "sg:city":"Silz",
    "sg:orig_category":"Tischlereien",
    "sg:phone":"+43 5263 5722",
    "sg:postcode":"6424",
    "sg:province":"Tirol",
    "wof:name":"Zoller Roland OEG",
    "wof:placetype":"venue"
},
  "geometry": {"coordinates":[10.9276199341,47.2656555176],"type":"Point"}
}