{
  "type": "Feature",
  "properties": {
    "iso:country":"AT",
    "sg:address":"Wollzeile 5",
    "sg:city":"Wien",
    "sg:orig_category":"Textilwaren / Einzelhandel",
    "sg:phone":"+43 1 5128138",
    "sg:postcode":"1010",
    "sg:province":"Wien",
    "wof:name":"Komaretho GmbH & Co KG",
    "wof:placetype":"venue"
},
  "geometry": {"coordinates":[16.3743095398,48.2093887329],"type":"Point"}
}