{
  "type": "Feature",
  "properties": {
    "iso:country":"AT",
    "sg:address":"Viktringer Ring 26",
    "sg:city":"Klagenfurt",
    "sg:orig_category":"Non-Classified Establishments",
    "sg:phone":"+43 463 54587",
    "sg:postcode":"9020",
    "sg:province":"K\u00e4rnten",
    "wof:name":"Dussnopastirski urad - Slow Seelsorgeamt",
    "wof:placetype":"venue"
},
  "geometry": {"coordinates":[14.3076400757,46.6207618713],"type":"Point"}
}