{
  "type": "Feature",
  "properties": {
    "addr:full":"Schiffmannstr 4 Linz Ober\u00f6sterreich 4020",
    "addr:housenumber":"4",
    "addr:postcode":"4020",
    "addr:street":"Schiffmannstr",
    "iso:country":"AT",
    "sg:address":"Schiffmannstr 4",
    "sg:city":"Linz",
    "sg:orig_category":"Finanz- U Wirtschaftsberatung",
    "sg:phone":"+43 4373 2376080",
    "sg:postcode":"4020",
    "sg:province":"Ober\u00f6sterreich",
    "wof:name":"Tricon Wirtschaftsberatung",
    "wof:placetype":"venue"
},
  "geometry": {"coordinates":[14.2798118591,48.2670478821],"type":"Point"}
}