{
  "type": "Feature",
  "properties": {
    "addr:full":"Oberberg 431 Bizau Vorarlberg 6874",
    "addr:housenumber":"431",
    "addr:postcode":"6874",
    "addr:street":"Oberberg",
    "iso:country":"AT",
    "sg:address":"Oberberg 431",
    "sg:city":"Bizau",
    "sg:orig_category":"Werbegestalter",
    "sg:phone":"+43 5514 3211",
    "sg:postcode":"6874",
    "sg:province":"Vorarlberg",
    "wof:name":"Erath Anton",
    "wof:placetype":"venue"
},
  "geometry": {"coordinates":[9.9270410538,47.3717269897],"type":"Point"}
}