{
  "type": "Feature",
  "properties": {
    "iso:country":"AT",
    "sg:address":"Linzer Str 240",
    "sg:city":"Wien",
    "sg:orig_category":"Industrievertretungen",
    "sg:phone":"+43 1 4860337",
    "sg:postcode":"1140",
    "sg:province":"Wien",
    "wof:name":"Mada Austria Alfred Dadisch - Maschinen f\u00fcr die Lebensmittelindustrie",
    "wof:placetype":"venue"
},
  "geometry": {"coordinates":[16.2823619843,48.1955604553],"type":"Point"}
}