{
  "type": "Feature",
  "properties": {
    "iso:country":"AT",
    "sg:address":"Fichteng 14",
    "sg:city":"Trofaiach",
    "sg:orig_category":"Energietechnik",
    "sg:phone":"+43 3847 2148",
    "sg:postcode":"8793",
    "sg:province":"Steiermark",
    "wof:name":"Katzelberger Josef",
    "wof:placetype":"venue"
},
  "geometry": {"coordinates":[14.9861412048,47.4238586426],"type":"Point"}
}