{
  "type": "Feature",
  "properties": {
    "addr:full":"Puchsbaumg 25-27 Wien Wien 1100",
    "addr:postcode":"25-27;1100",
    "iso:country":"AT",
    "sg:address":"Puchsbaumg 25-27",
    "sg:city":"Wien",
    "sg:orig_category":"Technische Bedarfsartikel",
    "sg:phone":"+43 1 6076353",
    "sg:postcode":"1100",
    "sg:province":"Wien",
    "wof:name":"IGS.Innovative Gateway Systems Handels AG",
    "wof:placetype":"venue"
},
  "geometry": {"coordinates":[16.3845901489,48.1729927063],"type":"Point"}
}