{
  "type": "Feature",
  "properties": {
    "iso:country":"AT",
    "sg:address":"Leusb\u00fcndtweg 12",
    "sg:city":"Feldkirch",
    "sg:classifiers":[
        {
            "category":"Manufacturing",
            "subcategory":"Metals",
            "type":"Manufacturing & Wholesale Goods"
        }
    ],
    "sg:phone":"+43 4355 22779630",
    "sg:postcode":"6800",
    "sg:province":"Vorarlberg",
    "sg:tags":[
        "metallurgy",
        "metalworking"
    ],
    "wof:name":"METZLER GESMBH & CO KG",
    "wof:placetype":"venue"
},
  "geometry": {"coordinates":[9.5967845917,47.2381515503],"type":"Point"}
}