{
  "type": "Feature",
  "properties": {
    "addr:full":"Bahnhofstr 1 Asten Ober\u00f6sterreich 4481",
    "addr:housenumber":"1",
    "addr:postcode":"4481",
    "addr:street":"Bahnhofstr",
    "iso:country":"AT",
    "sg:address":"Bahnhofstr 1",
    "sg:city":"Asten",
    "sg:classifiers":[
        {
            "category":"Manufacturing",
            "subcategory":"Metals",
            "type":"Manufacturing & Wholesale Goods"
        }
    ],
    "sg:phone":"+43 4372 2467090",
    "sg:postcode":"4481",
    "sg:province":"Ober\u00f6sterreich",
    "sg:tags":[
        "metallurgy",
        "metalworking"
    ],
    "wof:name":"K\u00d6NIG AUSTRIA GESMBH",
    "wof:placetype":"venue"
},
  "geometry": {"coordinates":[14.4001426697,48.2255210876],"type":"Point"}
}