{
  "type": "Feature",
  "properties": {
    "iso:country":"AT",
    "sg:address":"Bachstr 41C",
    "sg:city":"Steinerkirchen an der Traun",
    "sg:orig_category":"Automatisierungstechnik",
    "sg:phone":"+43 7241 28180",
    "sg:postcode":"4652",
    "sg:province":"Ober\u00f6sterreich",
    "wof:name":"Michlmayr Franz",
    "wof:placetype":"venue"
},
  "geometry": {"coordinates":[13.9564161301,48.0752906799],"type":"Point"}
}