{
  "type": "Feature",
  "properties": {
    "iso:country":"AT",
    "sg:address":"Oberaigenweg 20",
    "sg:city":"Kitzb\u00fchel",
    "sg:orig_category":"Schmieden U Schmiedeeisenelemente",
    "sg:phone":"+43 664 3034204",
    "sg:postcode":"6370",
    "sg:province":"Tirol",
    "wof:name":"Monitzer Siegfried KEG",
    "wof:placetype":"venue"
},
  "geometry": {"coordinates":[12.4372882843,47.4317893982],"type":"Point"}
}