{
  "type": "Feature",
  "properties": {
    "iso:country":"AT",
    "sg:address":"Breite Lache 1",
    "sg:city":"Feldkirch",
    "sg:classifiers":[
        {
            "category":"Parking",
            "subcategory":"Lot",
            "type":"Transportation"
        }
    ],
    "sg:phone":"+43 4355 2276777",
    "sg:postcode":"6800",
    "sg:province":"Vorarlberg",
    "sg:tags":[
        "transport",
        "road"
    ],
    "wof:name":"OTTO BISCHOF TRANSPORT GMBH",
    "wof:placetype":"venue"
},
  "geometry": {"coordinates":[9.5914039612,47.2698440552],"type":"Point"}
}