{
  "type": "Feature",
  "properties": {
    "iso:country":"AT",
    "sg:address":"Sportplatzweg 15",
    "sg:city":"Mieming",
    "sg:orig_category":"Glasereien",
    "sg:phone":"+43 4366 44201379",
    "sg:postcode":"6414",
    "sg:province":"Tirol",
    "wof:name":"bernold verglasung - Inh Bernold D\u00f6rrer",
    "wof:placetype":"venue"
},
  "geometry": {"coordinates":[10.9813079834,47.2984771729],"type":"Point"}
}