{
  "type": "Feature",
  "properties": {
    "iso:country":"AT",
    "sg:address":"Nr 107",
    "sg:city":"Kirchberg am Wechsel",
    "sg:orig_category":"Appartements / Ferienwohnungen",
    "sg:phone":"+43 4326 416240",
    "sg:postcode":"2880",
    "sg:province":"Nieder\u00f6sterreich",
    "wof:name":"Apschner Christine",
    "wof:placetype":"venue"
},
  "geometry": {"coordinates":[16.0085334778,47.5865592957],"type":"Point"}
}