{
  "type": "Feature",
  "properties": {
    "addr:full":"Blunerweg Silz Tirol 6424",
    "addr:postcode":"6424",
    "addr:street":"Blunerweg;Tirol",
    "iso:country":"AT",
    "sg:address":"Blunerweg",
    "sg:city":"Silz",
    "sg:classifiers":[
        {
            "category":"Manufacturing",
            "subcategory":"Wood Products",
            "type":"Manufacturing & Wholesale Goods"
        }
    ],
    "sg:phone":"+43 5263 6432",
    "sg:postcode":"6424",
    "sg:province":"Tirol",
    "sg:tags":[
        "lumber"
    ],
    "wof:name":"Anton Steuxner",
    "wof:placetype":"venue"
},
  "geometry": {"coordinates":[10.9276199341,47.2656555176],"type":"Point"}
}