{
  "type": "Feature",
  "properties": {
    "addr:full":"Marktpl 6 Wagna Steiermark 8435",
    "addr:housenumber":"6",
    "addr:postcode":"8435",
    "addr:street":"Marktpl",
    "iso:country":"AT",
    "sg:address":"Marktpl 6",
    "sg:city":"Wagna",
    "sg:orig_category":"Banken U Sparkassen",
    "sg:phone":"+43 3452 83496",
    "sg:postcode":"8435",
    "sg:province":"Steiermark",
    "wof:name":"Steierm\u00e4rkische Bank und Sparkassen AG",
    "wof:placetype":"venue"
},
  "geometry": {"coordinates":[15.5572576523,46.7656211853],"type":"Point"}
}