{
  "type": "Feature",
  "properties": {
    "addr:full":"Untere Hauptstr 1 Lengenfeld Nieder\u00f6sterreich 3552",
    "addr:housenumber":"1",
    "addr:postcode":"3552",
    "addr:street":"Untere Hauptstr",
    "iso:country":"AT",
    "sg:address":"Untere Hauptstr 1",
    "sg:city":"Lengenfeld",
    "sg:orig_category":"Gemeinden",
    "sg:phone":"+43 2719 8287",
    "sg:postcode":"3552",
    "sg:province":"Nieder\u00f6sterreich",
    "wof:name":"Marktgemeinde Stratzing",
    "wof:placetype":"venue"
},
  "geometry": {"coordinates":[15.6047115326,48.4501190186],"type":"Point"}
}