{
  "type": "Feature",
  "properties": {
    "addr:full":"Nr 18 St. Anton am Arlberg Tirol 6580",
    "addr:postcode":"6580",
    "addr:street":"Nr 18;Tirol",
    "iso:country":"AT",
    "sg:address":"Nr 18",
    "sg:city":"St. Anton am Arlberg",
    "sg:classifiers":[
        {
            "category":"Restaurant",
            "type":"Food & Drink"
        }
    ],
    "sg:phone":"+43 5446 36250",
    "sg:postcode":"6580",
    "sg:province":"Tirol",
    "wof:name":"Hospiz Alm-Restaurant",
    "wof:placetype":"venue"
},
  "geometry": {"coordinates":[10.2129440308,47.128200531],"type":"Point"}
}