{
  "type": "Feature",
  "properties": {
    "iso:country":"AT",
    "sg:address":"Brauhausstr 23",
    "sg:city":"Schwechat",
    "sg:orig_category":"Non-Classified Establishments",
    "sg:phone":"+43 1 7071745",
    "sg:postcode":"2320",
    "sg:province":"Nieder\u00f6sterreich",
    "wof:name":"Pfarramt Schwechat Maria Herz",
    "wof:placetype":"venue"
},
  "geometry": {"coordinates":[16.4667491913,48.1308555603],"type":"Point"}
}