{
  "type": "Feature",
  "properties": {
    "iso:country":"AT",
    "sg:address":"Neu Burgstall 303",
    "sg:city":"Mayrhofen",
    "sg:orig_category":"Pensionen / Privatzimmer",
    "sg:phone":"+43 5285 64437",
    "sg:postcode":"6290",
    "sg:province":"Tirol",
    "wof:name":"G\u00e4stehaus Emberger",
    "wof:placetype":"venue"
},
  "geometry": {"coordinates":[11.8624277115,47.1670684814],"type":"Point"}
}