{
  "type": "Feature",
  "properties": {
    "addr:full":"Andritzer Reichsstr 27 Andritz Steiermark 8045",
    "addr:housenumber":"27",
    "addr:postcode":"8045",
    "iso:country":"AT",
    "sg:address":"Andritzer Reichsstr 27",
    "sg:city":"Andritz",
    "sg:orig_category":"Lebensmittel / Einzelhandel",
    "sg:phone":"+43 316 671109",
    "sg:postcode":"8045",
    "sg:province":"Steiermark",
    "wof:name":"MONDO Lebensmitteldiskonter",
    "wof:placetype":"venue"
},
  "geometry": {"coordinates":[15.4242668152,47.1025390625],"type":"Point"}
}