{
  "type": "Feature",
  "properties": {
    "iso:country":"AT",
    "sg:address":"St. Margarethen 151c",
    "sg:city":"Jenbach",
    "sg:orig_category":"Autohandel",
    "sg:phone":"+43 5244 61681",
    "sg:postcode":"6200",
    "sg:province":"Tirol",
    "wof:name":"Auto Rofan GesmbH",
    "wof:placetype":"venue"
},
  "geometry": {"coordinates":[11.768409729,47.3775215149],"type":"Point"}
}