{
  "type": "Feature",
  "properties": {
    "addr:full":"Kremstalstr 1 Ansfelden Ober\u00f6sterreich 4052",
    "addr:housenumber":"1",
    "addr:postcode":"4052",
    "addr:street":"Kremstalstr",
    "iso:country":"AT",
    "sg:address":"Kremstalstr 1",
    "sg:city":"Ansfelden",
    "sg:orig_category":"Autoersatzteile",
    "sg:phone":"+43 7229 780960",
    "sg:postcode":"4052",
    "sg:province":"Ober\u00f6sterreich",
    "wof:name":"ATP Auto-Teile-Partner regGenmbH",
    "wof:placetype":"venue"
},
  "geometry": {"coordinates":[14.245839119,48.2082328796],"type":"Point"}
}