{
  "type": "Feature",
  "properties": {
    "addr:full":"Lindeng 18 Linz Ober\u00f6sterreich 4040",
    "addr:housenumber":"18",
    "addr:postcode":"4040",
    "addr:street":"Lindeng",
    "iso:country":"AT",
    "sg:address":"Lindeng 18",
    "sg:city":"Linz",
    "sg:classifiers":[
        {
            "category":"Communications",
            "subcategory":"Film & Video Production",
            "type":"Services"
        }
    ],
    "sg:phone":"+43 732 944944",
    "sg:postcode":"4040",
    "sg:province":"Ober\u00f6sterreich",
    "sg:tags":[
        "multimedia"
    ],
    "wof:name":"Multimedia Austria",
    "wof:placetype":"venue"
},
  "geometry": {"coordinates":[14.2905225754,48.3228530884],"type":"Point"}
}