{
  "type": "Feature",
  "properties": {
    "addr:full":"Nr 184 Ried im Oberinntal Tirol 6531",
    "addr:postcode":"6531",
    "addr:street":"Nr 184;Tirol",
    "iso:country":"AT",
    "sg:address":"Nr 184",
    "sg:city":"Ried im Oberinntal",
    "sg:orig_category":"Architekten",
    "sg:phone":"+43 5472 64830",
    "sg:postcode":"6531",
    "sg:province":"Tirol",
    "wof:name":"Mathoy Klaus Dipl-Ing",
    "wof:placetype":"venue"
},
  "geometry": {"coordinates":[10.654545784,47.0553817749],"type":"Point"}
}