{
  "type": "Feature",
  "properties": {
    "iso:country":"AT",
    "sg:address":"Bahnhofstr 237",
    "sg:city":"Bad Aussee",
    "sg:orig_category":"Arbeitsvermittlung",
    "sg:phone":"+43 3622 523150",
    "sg:postcode":"8990",
    "sg:province":"Steiermark",
    "wof:name":"Arbeitsmarktservice Zweigstelle Bad Aussee",
    "wof:placetype":"venue"
},
  "geometry": {"coordinates":[13.7768774033,47.599029541],"type":"Point"}
}