{
  "type": "Feature",
  "properties": {
    "iso:country":"AT",
    "sg:address":"Sierninger Str 168a",
    "sg:city":"Steyr",
    "sg:orig_category":"Friseure U Frisiersalons",
    "sg:phone":"+43 7252 74044",
    "sg:postcode":"4400",
    "sg:province":"Ober\u00f6sterreich",
    "wof:name":"Michi's Frisuren",
    "wof:placetype":"venue"
},
  "geometry": {"coordinates":[14.3950195312,48.043182373],"type":"Point"}
}