{
  "type": "Feature",
  "properties": {
    "iso:country":"AT",
    "sg:address":"Nr 130/Badesee",
    "sg:city":"Stubenberg am See",
    "sg:orig_category":"Waren Aller Art",
    "sg:phone":"+43 3176 8817",
    "sg:postcode":"8223",
    "sg:province":"Steiermark",
    "wof:name":"Bunter Laden -Kiosk am See",
    "wof:placetype":"venue"
},
  "geometry": {"coordinates":[15.8004598618,47.243724823],"type":"Point"}
}