{
  "type": "Feature",
  "properties": {
    "addr:full":"Heiligenst\u00e4dter Str 44 Wien Wien 1190",
    "addr:postcode":"1190",
    "addr:street":"Str 44",
    "iso:country":"AT",
    "sg:address":"Heiligenst\u00e4dter Str 44",
    "sg:city":"Wien",
    "sg:orig_category":"Autoreparatur",
    "sg:phone":"+43 1 36844120",
    "sg:postcode":"1190",
    "sg:province":"Wien",
    "wof:name":"Reinprecht Franz Ing GesmbH",
    "wof:placetype":"venue"
},
  "geometry": {"coordinates":[16.3593769073,48.239112854],"type":"Point"}
}