{
  "type": "Feature",
  "properties": {
    "addr:full":"Hauptpl 12 Enns Ober\u00f6sterreich 4470",
    "addr:housenumber":"12",
    "addr:postcode":"4470",
    "addr:street":"Hauptpl",
    "iso:country":"AT",
    "sg:address":"Hauptpl 12",
    "sg:city":"Enns",
    "sg:orig_category":"Tabaktrafiken",
    "sg:phone":"+43 7223 82380",
    "sg:postcode":"4470",
    "sg:province":"Ober\u00f6sterreich",
    "wof:name":"Rogl",
    "wof:placetype":"venue"
},
  "geometry": {"coordinates":[14.4790773392,48.2135238647],"type":"Point"}
}