{
  "type": "Feature",
  "properties": {
    "addr:full":"Nr 206 Gosau Ober\u00f6sterreich 4824",
    "addr:postcode":"4824",
    "addr:street":"Nr 206",
    "iso:country":"AT",
    "sg:address":"Nr 206",
    "sg:city":"Gosau",
    "sg:orig_category":"Freizeit- U Sportbekleidung",
    "sg:phone":"+43 6136 8336",
    "sg:postcode":"4824",
    "sg:province":"Ober\u00f6sterreich",
    "wof:name":"Sportstadl OEG Reitmaier-Zwilling",
    "wof:placetype":"venue"
},
  "geometry": {"coordinates":[13.5339212418,47.5838432312],"type":"Point"}
}