{
  "type": "Feature",
  "properties": {
    "iso:country":"AT",
    "sg:address":"Dr.-C.-Pfeiffenberger-Str 8a",
    "sg:city":"Imst",
    "sg:orig_category":"Banken U Sparkassen",
    "sg:phone":"+43 4350 53335120",
    "sg:postcode":"6460",
    "sg:province":"Tirol",
    "wof:name":"BTV - Bank f\u00fcr Tirol und Vorarlberg AG",
    "wof:placetype":"venue"
},
  "geometry": {"coordinates":[10.7392082214,47.2397956848],"type":"Point"}
}