{
  "type": "Feature",
  "properties": {
    "addr:full":"Nr 104 Trautmannsdorf in Oststeiermark Steiermark 8343",
    "addr:postcode":"8343",
    "addr:street":"Nr 104",
    "iso:country":"AT",
    "sg:address":"Nr 104",
    "sg:city":"Trautmannsdorf in Oststeiermark",
    "sg:orig_category":"Pensionen / Privatzimmer",
    "sg:phone":"+43 3159 2885",
    "sg:postcode":"8343",
    "sg:province":"Steiermark",
    "wof:name":"Leitgeb Engelbert",
    "wof:placetype":"venue"
},
  "geometry": {"coordinates":[15.8558778763,46.864730835],"type":"Point"}
}