{
  "type": "Feature",
  "properties": {
    "addr:full":"Kinkstr 24 Kufstein Tirol 6330",
    "addr:housenumber":"24",
    "addr:postcode":"6330",
    "addr:street":"Kinkstr;Tirol",
    "iso:country":"AT",
    "sg:address":"Kinkstr 24",
    "sg:city":"Kufstein",
    "sg:orig_category":"Hobbyvereine",
    "sg:phone":"+43 5372 62767",
    "sg:postcode":"6330",
    "sg:province":"Tirol",
    "wof:name":"\u00f6sterreichischer Alpenverein - Sektion Kufstein",
    "wof:placetype":"venue"
},
  "geometry": {"coordinates":[12.169342041,47.579498291],"type":"Point"}
}