{
  "type": "Feature",
  "properties": {
    "addr:full":"Schillerstr 27a Graz Steiermark 8010",
    "addr:housenumber":"27a",
    "addr:postcode":"8010",
    "addr:street":"Schillerstr",
    "iso:country":"AT",
    "sg:address":"Schillerstr 27a",
    "sg:city":"Graz",
    "sg:orig_category":"Unternehmensberatung",
    "sg:phone":"+43 316 338338",
    "sg:postcode":"8010",
    "sg:province":"Steiermark",
    "wof:name":"Consulting Team UnternehmensberatungsgesmbH",
    "wof:placetype":"venue"
},
  "geometry": {"coordinates":[15.4548330307,47.0707511902],"type":"Point"}
}