{
  "type": "Feature",
  "properties": {
    "addr:full":"Gilmstr 57 Schwaz Tirol 6130",
    "addr:housenumber":"57",
    "addr:postcode":"6130",
    "addr:street":"Gilmstr;Tirol",
    "iso:country":"AT",
    "sg:address":"Gilmstr 57",
    "sg:city":"Schwaz",
    "sg:orig_category":"Dolmetscher",
    "sg:phone":"+43 5242 65886",
    "sg:postcode":"6130",
    "sg:province":"Tirol",
    "wof:name":"Schwaiger Edith Mag",
    "wof:placetype":"venue"
},
  "geometry": {"coordinates":[11.7071990967,47.3454208374],"type":"Point"}
}