{
  "type": "Feature",
  "properties": {
    "iso:country":"AT",
    "sg:address":"Nr 1",
    "sg:city":"Drosendorf an der Thaya",
    "sg:classifiers":[
        {
            "category":"Restaurant",
            "type":"Food & Drink"
        }
    ],
    "sg:phone":"+43 2915 2555",
    "sg:postcode":"2095",
    "sg:province":"Nieder\u00f6sterreich",
    "wof:name":"Hennig-Pultar Miriam",
    "wof:placetype":"venue"
},
  "geometry": {"coordinates":[15.620100975,48.8681373596],"type":"Point"}
}