{
  "type": "Feature",
  "properties": {
    "addr:full":"Industriestrasse 19 Feldkirchen in K\u00e4rnten K\u00e4rnten 9560",
    "addr:housenumber":"19",
    "addr:postcode":"9560",
    "addr:street":"Industriestrasse;Kaernten",
    "iso:country":"AT",
    "sg:address":"Industriestrasse 19",
    "sg:city":"Feldkirchen in K\u00e4rnten",
    "sg:orig_category":"ChildrenS Furniture",
    "sg:phone":"+43 4276 3515",
    "sg:postcode":"9560",
    "sg:province":"K\u00e4rnten",
    "sg:website":"biedermann.cc",
    "wof:name":"Manfred Biedermann",
    "wof:placetype":"venue"
},
  "geometry": {"coordinates":[14.1029529572,46.7211685181],"type":"Point"}
}