{
  "type": "Feature",
  "properties": {
    "iso:country":"AT",
    "sg:address":"St. Urban-Weg 6",
    "sg:city":"Bodensdorf",
    "sg:orig_category":"Appartements / Ferienwohnungen",
    "sg:phone":"+43 4342 438268",
    "sg:postcode":"9551",
    "sg:province":"K\u00e4rnten",
    "wof:name":"Appartement Erzherzog Johann Inh Brandner Rosina",
    "wof:placetype":"venue"
},
  "geometry": {"coordinates":[13.9706993103,46.6813430786],"type":"Point"}
}