{
  "type": "Feature",
  "properties": {
    "addr:full":"Ermenstr 9 Hohenems Vorarlberg 6845",
    "addr:housenumber":"9",
    "addr:postcode":"6845",
    "addr:street":"Ermenstr",
    "iso:country":"AT",
    "sg:address":"Ermenstr 9",
    "sg:city":"Hohenems",
    "sg:orig_category":"Spenglereien",
    "sg:phone":"+43 5576 79206",
    "sg:postcode":"6845",
    "sg:province":"Vorarlberg",
    "wof:name":"Br\u00e4ndle Gerhard",
    "wof:placetype":"venue"
},
  "geometry": {"coordinates":[9.7092370987,47.3813514709],"type":"Point"}
}