{
  "type": "Feature",
  "properties": {
    "iso:country":"AT",
    "sg:address":"Brandweg 26",
    "sg:city":"Rohrmoos-Untertal",
    "sg:orig_category":"Pensionen / Privatzimmer",
    "sg:phone":"+43 4336 87224950",
    "sg:postcode":"8971",
    "sg:province":"Steiermark",
    "wof:name":"Asingerhof",
    "wof:placetype":"venue"
},
  "geometry": {"coordinates":[13.7149744034,47.3899650574],"type":"Point"}
}