{
  "type": "Feature",
  "properties": {
    "addr:full":"Burgg 121 Judenburg Steiermark 8750",
    "addr:housenumber":"121",
    "addr:postcode":"8750",
    "iso:country":"AT",
    "sg:address":"Burgg 121",
    "sg:city":"Judenburg",
    "sg:orig_category":"Fleischhauereien",
    "sg:phone":"+43 3572 44190",
    "sg:postcode":"8750",
    "sg:province":"Steiermark",
    "wof:name":"Schirnhofer-Breisler GesmbH - Shop in Shop",
    "wof:placetype":"venue"
},
  "geometry": {"coordinates":[14.6394100189,47.1706771851],"type":"Point"}
}