{
  "type": "Feature",
  "properties": {
    "addr:full":"Grillgasse 46 Wien Wien 1110",
    "addr:housenumber":"46",
    "addr:postcode":"1110",
    "addr:street":"Grillgasse",
    "iso:country":"AT",
    "sg:address":"Grillgasse 46",
    "sg:city":"Wien",
    "sg:classifiers":[
        {
            "category":"Military Area",
            "subcategory":"Air Force Base",
            "type":"Public Place"
        }
    ],
    "sg:phone":"+43 1 6886357",
    "sg:postcode":"1110",
    "sg:province":"Wien",
    "sg:tags":[
        "prime",
        "contractor",
        "contractors"
    ],
    "sg:website":"egbau.at",
    "wof:name":"Ing. Edelm\u00fcller Ges.m.b.H.",
    "wof:placetype":"venue"
},
  "geometry": {"coordinates":[16.409362793,48.1694641113],"type":"Point"}
}