{
  "type": "Feature",
  "properties": {
    "addr:full":"Salzburger Str 30/EKZ Wattens Tirol 6112",
    "addr:housenumber":"30 /",
    "addr:postcode":"6112",
    "addr:street":"Salzburger Str",
    "iso:country":"AT",
    "sg:address":"Salzburger Str 30/EKZ",
    "sg:city":"Wattens",
    "sg:orig_category":"Bankomat-Standorte",
    "sg:phone":"+43 800 2048800",
    "sg:postcode":"6112",
    "sg:province":"Tirol",
    "wof:name":"Bankomat der Raiffeisenbank Wattens und Umgebung regGenmbH",
    "wof:placetype":"venue"
},
  "geometry": {"coordinates":[11.5924959183,47.2911643982],"type":"Point"}
}