{
  "type": "Feature",
  "properties": {
    "addr:full":"Innerhalbach 49 Rohr im Gebirge Nieder\u00f6sterreich 2663",
    "addr:housenumber":"49",
    "addr:postcode":"2663",
    "addr:street":"Innerhalbach",
    "iso:country":"AT",
    "sg:address":"Innerhalbach 49",
    "sg:city":"Rohr im Gebirge",
    "sg:classifiers":[
        {
            "category":"Building & Trades",
            "subcategory":"Electrical",
            "type":"Services"
        }
    ],
    "sg:phone":"+43 2766 8523",
    "sg:postcode":"2663",
    "sg:province":"Nieder\u00f6sterreich",
    "sg:tags":[
        "work",
        "installation"
    ],
    "wof:name":"Johann Tisch",
    "wof:placetype":"venue"
},
  "geometry": {"coordinates":[15.7363061905,47.8951377869],"type":"Point"}
}