{
  "type": "Feature",
  "properties": {
    "addr:full":"An der Sonnleithen 13 Linz Ober\u00f6sterreich 4020",
    "addr:housenumber":"13",
    "addr:postcode":"4020",
    "addr:street":"An Der Sonnleithen",
    "iso:country":"AT",
    "sg:address":"An der Sonnleithen 13",
    "sg:city":"Linz",
    "sg:classifiers":[
        {
            "category":"Utilities",
            "subcategory":"Natural Gas",
            "type":"Services"
        }
    ],
    "sg:phone":"+43 699 10301667",
    "sg:postcode":"4020",
    "sg:province":"Ober\u00f6sterreich",
    "sg:tags":[
        "blasting",
        "explosive",
        "drilling",
        "quarry"
    ],
    "sg:website":"tbbenisch.com",
    "wof:name":"Technisches Ingenieurb\u00fcro Ing. Benisch",
    "wof:placetype":"venue"
},
  "geometry": {"coordinates":[14.2942733765,48.2670898438],"type":"Point"}
}