{
  "type": "Feature",
  "properties": {
    "addr:full":"Breitenfurter Str 262 Wien Wien 1230",
    "addr:housenumber":"262",
    "addr:postcode":"1230",
    "addr:street":"Str",
    "iso:country":"AT",
    "sg:address":"Breitenfurter Str 262",
    "sg:city":"Wien",
    "sg:orig_category":"Lehrmittel",
    "sg:phone":"+43 1 8693014",
    "sg:postcode":"1230",
    "sg:province":"Wien",
    "wof:name":"Opitec Produktions- und VertriebsgesmbH",
    "wof:placetype":"venue"
},
  "geometry": {"coordinates":[16.2936382294,48.1450614929],"type":"Point"}
}