{
  "type": "Feature",
  "properties": {
    "addr:full":"Nr 114 Straning Nieder\u00f6sterreich 3722",
    "addr:postcode":"3722",
    "addr:street":"Nr 114 Straning",
    "iso:country":"AT",
    "sg:address":"Nr 114",
    "sg:city":"Straning",
    "sg:orig_category":"Gemeinden",
    "sg:phone":"+43 2984 7273",
    "sg:postcode":"3722",
    "sg:province":"Nieder\u00f6sterreich",
    "wof:name":"Gemeindeamt Straning",
    "wof:placetype":"venue"
},
  "geometry": {"coordinates":[15.863940239,48.6107978821],"type":"Point"}
}