{
  "type": "Feature",
  "properties": {
    "iso:country":"AT",
    "sg:address":"Nachtigallg 5",
    "sg:city":"St. P\u00f6lten-Harland",
    "sg:orig_category":"Werbegrafik- U Grafik-Design",
    "sg:phone":"+43 4327 42882188",
    "sg:postcode":"3104",
    "sg:province":"Nieder\u00f6sterreich",
    "wof:name":"Kitzinger Michael",
    "wof:placetype":"venue"
},
  "geometry": {"coordinates":[15.6372499466,48.1600189209],"type":"Point"}
}