{
  "type": "Feature",
  "properties": {
    "iso:country":"AT",
    "sg:address":"Hauptstr 1",
    "sg:city":"Stockerau",
    "sg:orig_category":"Altwaren",
    "sg:phone":"+43 2266 64695",
    "sg:postcode":"2000",
    "sg:province":"Nieder\u00f6sterreich",
    "wof:name":"Daniel & Br\u00fcder Schmidt OEG",
    "wof:placetype":"venue"
},
  "geometry": {"coordinates":[16.2085838318,48.3853111267],"type":"Point"}
}