{
  "type": "Feature",
  "properties": {
    "addr:full":"Stadtpl 1 Zell am See Salzburg 5700",
    "addr:housenumber":"1",
    "addr:postcode":"5700",
    "addr:street":"Stadtpl;Salzburg",
    "iso:country":"AT",
    "sg:address":"Stadtpl 1",
    "sg:city":"Zell am See",
    "sg:classifiers":[
        {
            "category":"Professional",
            "subcategory":"Management & Consulting",
            "type":"Services"
        }
    ],
    "sg:phone":"+43 6542 7606817",
    "sg:postcode":"5700",
    "sg:province":"Salzburg",
    "wof:name":"Regionalmanagement Pinzgau",
    "wof:placetype":"venue"
},
  "geometry": {"coordinates":[12.7979011536,47.3233566284],"type":"Point"}
}