{
  "type": "Feature",
  "properties": {
    "addr:full":"Lustenauer Strasse 114 Hohenems Vorarlberg 6845",
    "addr:housenumber":"114",
    "addr:postcode":"6845",
    "addr:street":"Lustenauer Strasse",
    "iso:country":"AT",
    "sg:address":"Lustenauer Strasse 114",
    "sg:city":"Hohenems",
    "sg:classifiers":[
        {
            "category":"Retail",
            "subcategory":"Event Space",
            "type":"Services"
        }
    ],
    "sg:phone":"+43 5578 72639",
    "sg:postcode":"6845",
    "sg:province":"Vorarlberg",
    "sg:tags":[
        "firework",
        "display"
    ],
    "sg:website":"fire-event.com",
    "wof:name":"Michael Rzehak GmbH FIREevent - Die Feuerwerker",
    "wof:placetype":"venue"
},
  "geometry": {"coordinates":[9.6631374359,47.3564758301],"type":"Point"}
}