{
  "type": "Feature",
  "properties": {
    "iso:country":"AT",
    "sg:address":"Langenlebarner Str 111a",
    "sg:city":"Tulln an der Donau",
    "sg:orig_category":"Reitsportartikel",
    "sg:phone":"+43 4322 7266368",
    "sg:postcode":"3430",
    "sg:province":"Nieder\u00f6sterreich",
    "wof:name":"The Red Horse - Fachhandel f\u00fcr English,Western u Islandpferdebedarf",
    "wof:placetype":"venue"
},
  "geometry": {"coordinates":[16.0746212006,48.3293418884],"type":"Point"}
}