{
  "type": "Feature",
  "properties": {
    "addr:full":"Hauptstr 1 Gurk K\u00e4rnten 9342",
    "addr:housenumber":"1",
    "addr:postcode":"9342",
    "addr:street":"Hauptstr;Kaernten",
    "iso:country":"AT",
    "sg:address":"Hauptstr 1",
    "sg:city":"Gurk",
    "sg:orig_category":"Appartements / Ferienwohnungen",
    "sg:phone":"+43 4266 8365",
    "sg:postcode":"9342",
    "sg:province":"K\u00e4rnten",
    "wof:name":"Isopp-Erian Ines",
    "wof:placetype":"venue"
},
  "geometry": {"coordinates":[14.292093277,46.8739433289],"type":"Point"}
}