{
  "type": "Feature",
  "properties": {
    "addr:full":"Leopold-Bruckner-Str 10 Schwarzach im Pongau Salzburg 5620",
    "addr:housenumber":"10",
    "addr:postcode":"5620",
    "addr:street":"Leopold-Bruckner-Str;Salzburg",
    "iso:country":"AT",
    "sg:address":"Leopold-Bruckner-Str 10",
    "sg:city":"Schwarzach im Pongau",
    "sg:orig_category":"Maler, Anstreicher U Lackierer",
    "sg:phone":"+43 4364 157836",
    "sg:postcode":"5620",
    "sg:province":"Salzburg",
    "wof:name":"Malerei Farbdesign Marko",
    "wof:placetype":"venue"
},
  "geometry": {"coordinates":[13.1494903564,47.3205184937],"type":"Point"}
}