{
  "type": "Feature",
  "properties": {
    "addr:full":"Thermenpl 7 Lutzmannsburg Burgenland 7361",
    "addr:housenumber":"7",
    "addr:postcode":"7361",
    "addr:street":"Thermenpl",
    "iso:country":"AT",
    "sg:address":"Thermenpl 7",
    "sg:city":"Lutzmannsburg",
    "sg:classifiers":[
        {
            "category":"Travel",
            "subcategory":"Hotels & Motels",
            "type":"Entertainment"
        }
    ],
    "sg:phone":"+43 4326 1581313",
    "sg:postcode":"7361",
    "sg:province":"Burgenland",
    "sg:website":"allinred.at",
    "wof:name":"ALL IN RED Thermenhotel",
    "wof:placetype":"venue"
},
  "geometry": {"coordinates":[16.6568450928,47.4663505554],"type":"Point"}
}