{
  "type": "Feature",
  "properties": {
    "iso:country":"AT",
    "sg:address":"Hauptstr 80",
    "sg:city":"Katzelsdorf",
    "sg:orig_category":"Partyservice",
    "sg:phone":"+43 2622 78283",
    "sg:postcode":"2801",
    "sg:province":"Nieder\u00f6sterreich",
    "wof:name":"Sch\u00f6berl Dominikus",
    "wof:placetype":"venue"
},
  "geometry": {"coordinates":[16.2690887451,47.7788009644],"type":"Point"}
}