{
  "type": "Feature",
  "properties": {
    "addr:full":"Anton-Wallner-Str 1 Zell am See Salzburg 5700",
    "addr:housenumber":"1",
    "addr:postcode":"5700",
    "addr:street":"Anton-Wallner-Str;Salzburg",
    "iso:country":"AT",
    "sg:address":"Anton-Wallner-Str 1",
    "sg:city":"Zell am See",
    "sg:orig_category":"Pensionen / Privatzimmer",
    "sg:phone":"+43 4365 4273150",
    "sg:postcode":"5700",
    "sg:province":"Salzburg",
    "wof:name":"Karlshofhotels - Pension Susanna",
    "wof:placetype":"venue"
},
  "geometry": {"coordinates":[12.796869278,47.3244132996],"type":"Point"}
}