{
  "type": "Feature",
  "properties": {
    "addr:full":"Traunufer Arkade 1 Wels Ober\u00f6sterreich 4600",
    "addr:housenumber":"1",
    "addr:postcode":"4600",
    "addr:street":"Traunufer Arkade;Oberoesterreich",
    "iso:country":"AT",
    "sg:address":"Traunufer Arkade 1",
    "sg:city":"Wels",
    "sg:classifiers":[
        {
            "category":"Professional",
            "subcategory":"Computer Services",
            "type":"Services"
        }
    ],
    "sg:phone":"+43 7242 93963500",
    "sg:postcode":"4600",
    "sg:province":"Ober\u00f6sterreich",
    "sg:tags":[
        "software"
    ],
    "wof:name":"CADENAS Technologies Austria GmbH",
    "wof:placetype":"venue"
},
  "geometry": {"coordinates":[14.0349807739,48.1539916992],"type":"Point"}
}