{
  "type": "Feature",
  "properties": {
    "addr:full":"Triglavstrasse 19 Villach K\u00e4rnten 9500",
    "addr:housenumber":"19",
    "addr:postcode":"9500",
    "addr:street":"Triglavstrasse;Kaernten",
    "iso:country":"AT",
    "sg:address":"Triglavstrasse 19",
    "sg:city":"Villach",
    "sg:classifiers":[
        {
            "category":"Manufacturing",
            "subcategory":"Furniture",
            "type":"Manufacturing & Wholesale Goods"
        }
    ],
    "sg:phone":"+43 4242 37718",
    "sg:postcode":"9500",
    "sg:province":"K\u00e4rnten",
    "sg:tags":[
        "bedroom"
    ],
    "wof:name":"Tischlerei Wiederschwinger GmbH",
    "wof:placetype":"venue"
},
  "geometry": {"coordinates":[13.8402633667,46.5917892456],"type":"Point"}
}