{
  "type": "Feature",
  "properties": {
    "addr:full":"M\u00fchl 29 St. Veit Steiermark 8046",
    "addr:housenumber":"29",
    "addr:postcode":"8046",
    "addr:street":"Muehl",
    "iso:country":"AT",
    "sg:address":"M\u00fchl 29",
    "sg:city":"St. Veit",
    "sg:classifiers":[
        {
            "category":"Building & Trades",
            "subcategory":"Plumbing",
            "type":"Services"
        }
    ],
    "sg:phone":"+43 316 693390",
    "sg:postcode":"8046",
    "sg:province":"Steiermark",
    "sg:tags":[
        "supraregional",
        "gas"
    ],
    "wof:name":"Schl\u00fcsselberger G\u00fcnter",
    "wof:placetype":"venue"
},
  "geometry": {"coordinates":[15.4190244675,47.1442832947],"type":"Point"}
}