{
  "type": "Feature",
  "properties": {
    "addr:full":"Boschstr 45 Wels Ober\u00f6sterreich 4600",
    "addr:housenumber":"45",
    "addr:postcode":"4600",
    "addr:street":"Boschstr;Oberoesterreich",
    "iso:country":"AT",
    "sg:address":"Boschstr 45",
    "sg:city":"Wels",
    "sg:orig_category":"Lebensmittel / Einzelhandel",
    "sg:phone":"+43 7242 47773",
    "sg:postcode":"4600",
    "sg:province":"Ober\u00f6sterreich",
    "wof:name":"MAM EinzelhandelsgesmbH",
    "wof:placetype":"venue"
},
  "geometry": {"coordinates":[14.058596611,48.162147522],"type":"Point"}
}