{
  "type": "Feature",
  "properties": {
    "addr:full":"Gartenstr 8 Bad Hofgastein Salzburg 5630",
    "addr:housenumber":"8",
    "addr:postcode":"5630",
    "addr:street":"Gartenstr;Salzburg",
    "iso:country":"AT",
    "sg:address":"Gartenstr 8",
    "sg:city":"Bad Hofgastein",
    "sg:orig_category":"Pensionen / Privatzimmer",
    "sg:phone":"+43 6432 6137",
    "sg:postcode":"5630",
    "sg:province":"Salzburg",
    "wof:name":"Haus Himmelreich - Fr\u00fchst\u00fcckspension",
    "wof:placetype":"venue"
},
  "geometry": {"coordinates":[13.1067476273,47.1754074097],"type":"Point"}
}