{
  "type": "Feature",
  "properties": {
    "addr:full":"Blumentalstr 48 K\u00f6nigsbrunn am Wagram Nieder\u00f6sterreich 3465",
    "addr:housenumber":"48",
    "addr:postcode":"3465",
    "addr:street":"Blumentalstr;Am Wagram",
    "iso:country":"AT",
    "sg:address":"Blumentalstr 48",
    "sg:city":"K\u00f6nigsbrunn am Wagram",
    "sg:orig_category":"Installationsunternehmen",
    "sg:phone":"+43 4322 782278",
    "sg:postcode":"3465",
    "sg:province":"Nieder\u00f6sterreich",
    "wof:name":"Ecker Franz",
    "wof:placetype":"venue"
},
  "geometry": {"coordinates":[-79.3644332886,34.8895263672],"type":"Point"}
}