{
  "type": "Feature",
  "properties": {
    "iso:country":"AT",
    "sg:address":"Nr 90",
    "sg:city":"Traunstein",
    "sg:orig_category":"Banken U Sparkassen",
    "sg:phone":"+43 2878 6248",
    "sg:postcode":"3632",
    "sg:province":"Nieder\u00f6sterreich",
    "wof:name":"Raiffeisenbank Zwettl regGenmbH",
    "wof:placetype":"venue"
},
  "geometry": {"coordinates":[15.1159744263,48.4355010986],"type":"Point"}
}