{
  "type": "Feature",
  "properties": {
    "addr:full":"Nr 307 B\u00f6heimkirchen Nieder\u00f6sterreich 3071",
    "addr:postcode":"3071",
    "addr:street":"Nr 307 Boeheimkirchen",
    "iso:country":"AT",
    "sg:address":"Nr 307",
    "sg:city":"B\u00f6heimkirchen",
    "sg:orig_category":"Feuerwehren",
    "sg:phone":"+43 2744 7787",
    "sg:postcode":"3071",
    "sg:province":"Nieder\u00f6sterreich",
    "wof:name":"Freiwillige Feuerwehr",
    "wof:placetype":"venue"
},
  "geometry": {"coordinates":[15.7625226974,48.1979560852],"type":"Point"}
}