{
  "type": "Feature",
  "properties": {
    "iso:country":"AT",
    "sg:address":"Kutschkerg 39",
    "sg:city":"Wien",
    "sg:classifiers":[
        {
            "category":"Restaurant",
            "type":"Food & Drink"
        }
    ],
    "sg:phone":"+43 1 4796630",
    "sg:postcode":"1180",
    "sg:province":"Wien",
    "sg:tags":[
        "pizzeria"
    ],
    "wof:name":"Ristorante Roma",
    "wof:placetype":"venue"
},
  "geometry": {"coordinates":[16.3445796967,48.2264823914],"type":"Point"}
}