{
  "type": "Feature",
  "properties": {
    "addr:full":"Haberlg 46 Wien Wien 1160",
    "addr:housenumber":"46",
    "addr:postcode":"1160",
    "addr:street":"Haberlg",
    "iso:country":"AT",
    "sg:address":"Haberlg 46",
    "sg:city":"Wien",
    "sg:orig_category":"Biologische Produkte",
    "sg:phone":"+43 4314 945689",
    "sg:postcode":"1160",
    "sg:province":"Wien",
    "wof:name":"CIA - Cannabis in Austria",
    "wof:placetype":"venue"
},
  "geometry": {"coordinates":[16.3290691376,48.2095184326],"type":"Point"}
}