{
  "type": "Feature",
  "properties": {
    "addr:full":"Rathauspl 14 Klosterneuburg Nieder\u00f6sterreich 3400",
    "addr:housenumber":"14",
    "addr:postcode":"3400",
    "addr:street":"Rathauspl;Niederoesterreich",
    "iso:country":"AT",
    "sg:address":"Rathauspl 14",
    "sg:city":"Klosterneuburg",
    "sg:orig_category":"Tabaktrafiken",
    "sg:phone":"+43 2243 26001",
    "sg:postcode":"3400",
    "sg:province":"Nieder\u00f6sterreich",
    "wof:name":"Konar Leopold",
    "wof:placetype":"venue"
},
  "geometry": {"coordinates":[16.3250637054,48.3055839539],"type":"Point"}
}