{
  "type": "Feature",
  "properties": {
    "addr:full":"Latschenweg 3 Bad Kleinkirchheim K\u00e4rnten 9546",
    "addr:housenumber":"3",
    "addr:postcode":"9546",
    "addr:street":"Latschenweg",
    "iso:country":"AT",
    "sg:address":"Latschenweg 3",
    "sg:city":"Bad Kleinkirchheim",
    "sg:orig_category":"Appartements / Ferienwohnungen",
    "sg:phone":"+43 4240 5400",
    "sg:postcode":"9546",
    "sg:province":"K\u00e4rnten",
    "wof:name":"Appartement Latschen",
    "wof:placetype":"venue"
},
  "geometry": {"coordinates":[13.7655286789,46.8291244507],"type":"Point"}
}