{
  "type": "Feature",
  "properties": {
    "addr:full":"Dorf 10 Schwaz Tirol 6130",
    "addr:housenumber":"10",
    "addr:postcode":"6130",
    "addr:street":"Dorf;Tirol",
    "iso:country":"AT",
    "sg:address":"Dorf 10",
    "sg:city":"Schwaz",
    "sg:orig_category":"Feuerwehren",
    "sg:phone":"+43 5242 67694",
    "sg:postcode":"6130",
    "sg:province":"Tirol",
    "wof:name":"Feuerwehr Pill",
    "wof:placetype":"venue"
},
  "geometry": {"coordinates":[11.6807641983,47.3193206787],"type":"Point"}
}