{
  "type": "Feature",
  "properties": {
    "iso:country":"AT",
    "sg:address":"Grieskirchner Str 7",
    "sg:city":"Bad Schallerbach",
    "sg:orig_category":"Friseure U Frisiersalons",
    "sg:phone":"+43 4372 4943443",
    "sg:postcode":"4701",
    "sg:province":"Ober\u00f6sterreich",
    "wof:name":"Moser Ursula",
    "wof:placetype":"venue"
},
  "geometry": {"coordinates":[13.9183549881,48.2309684753],"type":"Point"}
}