{
  "type": "Feature",
  "properties": {
    "addr:full":"Neubaugasse, 12 - 14 -  Wien Wien 1070",
    "addr:housenumber":"12 14",
    "addr:postcode":"1070",
    "addr:street":"Neubaugasse",
    "iso:country":"AT",
    "sg:address":"Neubaugasse, 12 - 14 - ",
    "sg:city":"Wien",
    "sg:classifiers":[
        {
            "category":"Professional",
            "subcategory":"Art Services",
            "type":"Services"
        }
    ],
    "sg:phone":"+43 4315 227479",
    "sg:postcode":"1070",
    "sg:province":"Wien",
    "sg:tags":[
        "export-import"
    ],
    "wof:name":"Armenia Embassy",
    "wof:placetype":"venue"
},
  "geometry": {"coordinates":[16.3497924805,48.1991539001],"type":"Point"}
}