{
  "type": "Feature",
  "properties": {
    "iso:country":"AT",
    "sg:address":"Dechantweg 9",
    "sg:city":"Tobelbad",
    "sg:orig_category":"Haushaltsartikel",
    "sg:phone":"+43 3136 52780",
    "sg:postcode":"8144",
    "sg:province":"Steiermark",
    "wof:name":"Vemmina - backen ohne Boden Roswita Kousek",
    "wof:placetype":"venue"
},
  "geometry": {"coordinates":[15.3614063263,46.9892425537],"type":"Point"}
}