{
  "type": "Feature",
  "properties": {
    "addr:full":"Nr 75 Holzgau Tirol 6654",
    "addr:postcode":"6654",
    "addr:street":"Nr;Holzgau Tirol",
    "iso:country":"AT",
    "sg:address":"Nr 75",
    "sg:city":"Holzgau",
    "sg:orig_category":"Pensionen / Privatzimmer",
    "sg:phone":"+43 5633 5305",
    "sg:postcode":"6654",
    "sg:province":"Tirol",
    "wof:name":"Bader Rudolf",
    "wof:placetype":"venue"
},
  "geometry": {"coordinates":[10.3436069489,47.2595977783],"type":"Point"}
}