{
  "type": "Feature",
  "properties": {
    "iso:country":"AT",
    "sg:address":"Wagramer Str 25/3",
    "sg:city":"Wien",
    "sg:orig_category":"Werbegrafik- U Grafik-Design",
    "sg:phone":"+43 1 2637430",
    "sg:postcode":"1220",
    "sg:province":"Wien",
    "wof:name":"Blazejovsky Herbert",
    "wof:placetype":"venue"
},
  "geometry": {"coordinates":[16.4227771759,48.2357978821],"type":"Point"}
}