{
  "type": "Feature",
  "properties": {
    "addr:full":"K\u00e4rntner Str 28 Lienz Tirol 9900",
    "addr:postcode":"9900",
    "addr:street":"Str 28;Tirol",
    "iso:country":"AT",
    "sg:address":"K\u00e4rntner Str 28",
    "sg:city":"Lienz",
    "sg:orig_category":"Elektroinstallationsunternehmen",
    "sg:phone":"+43 4852 63181",
    "sg:postcode":"9900",
    "sg:province":"Tirol",
    "wof:name":"Elektro Mu\u00dfhauser",
    "wof:placetype":"venue"
},
  "geometry": {"coordinates":[12.7684783936,46.8281173706],"type":"Point"}
}