{
  "type": "Feature",
  "properties": {
    "addr:full":"Tischlerberg 8 Helfenberg Ober\u00f6sterreich 4184",
    "addr:housenumber":"8",
    "addr:postcode":"4184",
    "addr:street":"Tischlerberg",
    "iso:country":"AT",
    "sg:address":"Tischlerberg 8",
    "sg:city":"Helfenberg",
    "sg:orig_category":"Stiegen U Treppen",
    "sg:phone":"+43 4372 166237",
    "sg:postcode":"4184",
    "sg:province":"Ober\u00f6sterreich",
    "sg:website":"traxler-treppen.at",
    "wof:name":"Traxler Wolfgang",
    "wof:placetype":"venue"
},
  "geometry": {"coordinates":[14.146780014,48.543510437],"type":"Point"}
}