{
  "type": "Feature",
  "properties": {
    "iso:country":"AT",
    "sg:address":"Linzer Str 47",
    "sg:city":"Steyregg",
    "sg:orig_category":"Futtermittel",
    "sg:phone":"+43 732 6411000",
    "sg:postcode":"4221",
    "sg:province":"Ober\u00f6sterreich",
    "wof:name":"Koch GesmbH & Co KG - Iams & Eukanuba Generalimporteur",
    "wof:placetype":"venue"
},
  "geometry": {"coordinates":[14.3613100052,48.2835426331],"type":"Point"}
}