{
  "type": "Feature",
  "properties": {
    "addr:full":"Donawitz Pestalozzistr 67 Leoben Steiermark 8700",
    "addr:housenumber":"67",
    "addr:postcode":"8700",
    "iso:country":"AT",
    "sg:address":"Donawitz Pestalozzistr 67",
    "sg:city":"Leoben",
    "sg:orig_category":"Apotheken",
    "sg:phone":"+43 4338 42213860",
    "sg:postcode":"8700",
    "sg:province":"Steiermark",
    "wof:name":"Apotheke Zur H\u00fctte",
    "wof:placetype":"venue"
},
  "geometry": {"coordinates":[15.0741767883,47.3760986328],"type":"Point"}
}