{
  "type": "Feature",
  "properties": {
    "addr:full":"Nibelungenstr 19 Hohenems Vorarlberg 6845",
    "addr:housenumber":"19",
    "addr:postcode":"6845",
    "addr:street":"Nibelungenstr",
    "iso:country":"AT",
    "sg:address":"Nibelungenstr 19",
    "sg:city":"Hohenems",
    "sg:orig_category":"Banken U Sparkassen",
    "sg:phone":"+43 4355 76735020",
    "sg:postcode":"6845",
    "sg:province":"Vorarlberg",
    "wof:name":"Vorarlberger Volksbank reg GenmbH",
    "wof:placetype":"venue"
},
  "geometry": {"coordinates":[9.6761445999,47.3658447266],"type":"Point"}
}