{
  "type": "Feature",
  "properties": {
    "iso:country":"AT",
    "sg:address":"R\u00fcstenen 154",
    "sg:city":"Riefensberg",
    "sg:orig_category":"Furniture, General",
    "sg:phone":"+43 5513 8108",
    "sg:postcode":"6943",
    "sg:province":"Vorarlberg",
    "wof:name":"Andreas Giselbrecht",
    "wof:placetype":"venue"
},
  "geometry": {"coordinates":[9.9638547897,47.5045547485],"type":"Point"}
}