{
  "type": "Feature",
  "properties": {
    "addr:full":"Vorderstadt 9 Kitzb\u00fchel Tirol 6370",
    "addr:housenumber":"9",
    "addr:postcode":"6370",
    "addr:street":"Vorderstadt;Tirol",
    "iso:country":"AT",
    "sg:address":"Vorderstadt 9",
    "sg:city":"Kitzb\u00fchel",
    "sg:orig_category":"Optiker",
    "sg:phone":"+43 5356 65653",
    "sg:postcode":"6370",
    "sg:province":"Tirol",
    "wof:name":"Meikl Optik - Brandst\u00e4tter Fred",
    "wof:placetype":"venue"
},
  "geometry": {"coordinates":[12.3908863068,47.4470252991],"type":"Point"}
}