{
  "type": "Feature",
  "properties": {
    "addr:full":"Tiroler Str 25 Silz Tirol 6424",
    "addr:postcode":"6424",
    "addr:street":"Str 25;Tirol",
    "iso:country":"AT",
    "sg:address":"Tiroler Str 25",
    "sg:city":"Silz",
    "sg:orig_category":"Speditionen",
    "sg:phone":"+43 4352 63510510",
    "sg:postcode":"6424",
    "sg:province":"Tirol",
    "wof:name":"Interlogsped Int Spedition GmbH & Co KG",
    "wof:placetype":"venue"
},
  "geometry": {"coordinates":[10.9358215332,47.2680473328],"type":"Point"}
}