{
  "type": "Feature",
  "properties": {
    "addr:full":"Einfang 37 Schwaz Tirol 6130",
    "addr:housenumber":"37",
    "addr:postcode":"6130",
    "addr:street":"Einfang;Tirol",
    "iso:country":"AT",
    "sg:address":"Einfang 37",
    "sg:city":"Schwaz",
    "sg:classifiers":[
        {
            "category":"Wholesale",
            "subcategory":"Vending Machines",
            "type":"Manufacturing & Wholesale Goods"
        }
    ],
    "sg:phone":"+43 5242 62255",
    "sg:postcode":"6130",
    "sg:province":"Tirol",
    "sg:tags":[
        "filter"
    ],
    "wof:name":"Inpratech Luftfilter HandelsgmbH",
    "wof:placetype":"venue"
},
  "geometry": {"coordinates":[11.7222967148,47.3592681885],"type":"Point"}
}