{
  "type": "Feature",
  "properties": {
    "addr:full":"Michlbauernweg 18 Linz Ober\u00f6sterreich 4040",
    "addr:housenumber":"18",
    "addr:postcode":"4040",
    "addr:street":"Michlbauernweg",
    "iso:country":"AT",
    "sg:address":"Michlbauernweg 18",
    "sg:city":"Linz",
    "sg:orig_category":"Medizintechnik",
    "sg:phone":"+43 732 253600",
    "sg:postcode":"4040",
    "sg:province":"Ober\u00f6sterreich",
    "wof:name":"M T C Medicine Technical Cooperation Medizintechnischer Vertrieb GesmbH",
    "wof:placetype":"venue"
},
  "geometry": {"coordinates":[14.2879085541,48.3369941711],"type":"Point"}
}