{
  "type": "Feature",
  "properties": {
    "addr:full":"An der oberen Alten 186 Wien Wien 1220",
    "addr:housenumber":"186",
    "addr:postcode":"1220",
    "addr:street":"An Der Oberen Alten",
    "iso:country":"AT",
    "sg:address":"An der oberen Alten 186",
    "sg:city":"Wien",
    "sg:classifiers":[
        {
            "category":"Restaurant",
            "type":"Food & Drink"
        }
    ],
    "sg:phone":"+43 1 2043953",
    "sg:postcode":"1220",
    "sg:province":"Wien",
    "wof:name":"Ufertaverne",
    "wof:placetype":"venue"
},
  "geometry": {"coordinates":[16.4259033203,48.2411003113],"type":"Point"}
}