{
  "type": "Feature",
  "properties": {
    "addr:full":"Porschestrasse 15 3106",
    "addr:housenumber":"15",
    "addr:postcode":"3106",
    "addr:street":"Porschestrasse",
    "iso:country":"AT",
    "sg:address":"Porschestrasse 15",
    "sg:classifiers":[
        {
            "category":"Manufacturing",
            "subcategory":"Paper Products",
            "type":"Manufacturing & Wholesale Goods"
        }
    ],
    "sg:phone":"+43 2742 728770",
    "sg:postcode":"3106",
    "sg:tags":[
        "device",
        "binding",
        "systems"
    ],
    "sg:website":"idus-dorsch.at",
    "wof:name":"Idus-Dorsch GmbH & Co KG",
    "wof:placetype":"venue"
},
  "geometry": {"coordinates":[15.6206197739,48.1706390381],"type":"Point"}
}