{
  "type": "Feature",
  "properties": {
    "iso:country":"AT",
    "sg:address":"Bambergerstr 2",
    "sg:city":"Reichenfels",
    "sg:orig_category":"Banken U Sparkassen",
    "sg:phone":"+43 5 010030881",
    "sg:postcode":"9463",
    "sg:province":"K\u00e4rnten",
    "wof:name":"K\u00e4rntner Sparkasse AG",
    "wof:placetype":"venue"
},
  "geometry": {"coordinates":[14.7410926819,47.0073852539],"type":"Point"}
}