{
  "type": "Feature",
  "properties": {
    "addr:full":"Drauweg 3 Rosegg K\u00e4rnten 9232",
    "addr:housenumber":"3",
    "addr:postcode":"9232",
    "addr:street":"Drauweg;Kaernten",
    "iso:country":"AT",
    "sg:address":"Drauweg 3",
    "sg:city":"Rosegg",
    "sg:orig_category":"Tischlereien",
    "sg:phone":"+43 4342 7445060",
    "sg:postcode":"9232",
    "sg:province":"K\u00e4rnten",
    "wof:name":"Heregger Manfred",
    "wof:placetype":"venue"
},
  "geometry": {"coordinates":[14.0000419617,46.5895881653],"type":"Point"}
}