{
  "type": "Feature",
  "properties": {
    "addr:full":"Hauptstr 70 D\u00f6briach K\u00e4rnten 9873",
    "addr:housenumber":"70",
    "addr:postcode":"9873",
    "addr:street":"Hauptstr;Kaernten",
    "iso:country":"AT",
    "sg:address":"Hauptstr 70",
    "sg:city":"D\u00f6briach",
    "sg:orig_category":"Appartements / Ferienwohnungen",
    "sg:phone":"+43 4246 7243",
    "sg:postcode":"9873",
    "sg:province":"K\u00e4rnten",
    "wof:name":"Brunner Komfort Appartements",
    "wof:placetype":"venue"
},
  "geometry": {"coordinates":[9.6596899033,47.818321228],"type":"Point"}
}