{
  "type": "Feature",
  "properties": {
    "iso:country":"AT",
    "sg:address":"Unterer Waldweg 105",
    "sg:city":"Furth",
    "sg:classifiers":[
        {
            "category":"Home & Garden",
            "subcategory":"Building Materials",
            "type":"Retail Goods"
        }
    ],
    "sg:phone":"+43 2739 2537",
    "sg:postcode":"3511",
    "sg:province":"Nieder\u00f6sterreich",
    "sg:tags":[
        "installation",
        "electric"
    ],
    "wof:name":"Manfred Schinko",
    "wof:placetype":"venue"
},
  "geometry": {"coordinates":[15.6125049591,48.374168396],"type":"Point"}
}