{
  "type": "Feature",
  "properties": {
    "iso:country":"AT",
    "sg:address":"Hillerstr 8/4A",
    "sg:city":"Wien",
    "sg:orig_category":"\u00c3\u201erzte / F Allgemeinmedizin",
    "sg:phone":"+43 1 7280430",
    "sg:postcode":"1020",
    "sg:province":"Wien",
    "wof:name":"Gr\u00f6ger G\u00fcnter Dr",
    "wof:placetype":"venue"
},
  "geometry": {"coordinates":[16.4064750671,48.2201805115],"type":"Point"}
}