{
  "type": "Feature",
  "properties": {
    "addr:full":"Haseng 25 Wien Wien 1100",
    "addr:housenumber":"25",
    "addr:postcode":"1100",
    "addr:street":"Haseng",
    "iso:country":"AT",
    "sg:address":"Haseng 25",
    "sg:city":"Wien",
    "sg:orig_category":"Elektroinstallationsunternehmen",
    "sg:phone":"+43 1 8126711",
    "sg:postcode":"1100",
    "sg:province":"Wien",
    "wof:name":"Gruner Elektrotechnik",
    "wof:placetype":"venue"
},
  "geometry": {"coordinates":[16.3689842224,48.1792488098],"type":"Point"}
}