{
  "type": "Feature",
  "properties": {
    "addr:full":"Mitterg 15 Mitterdorf im M\u00fcrztal Steiermark 8662",
    "addr:housenumber":"15;im",
    "addr:postcode":"8662",
    "addr:street":"Mitterg;Muerztal Steiermark",
    "iso:country":"AT",
    "sg:address":"Mitterg 15",
    "sg:city":"Mitterdorf im M\u00fcrztal",
    "sg:orig_category":"Raumausstattung",
    "sg:phone":"+43 4338 5832960",
    "sg:postcode":"8662",
    "sg:province":"Steiermark",
    "wof:name":"Sedlmayer Andreas",
    "wof:placetype":"venue"
},
  "geometry": {"coordinates":[15.5138864517,47.5354309082],"type":"Point"}
}