{
  "type": "Feature",
  "properties": {
    "addr:full":"Mozartstr 4 Timelkam Ober\u00f6sterreich 4850",
    "addr:housenumber":"4",
    "addr:postcode":"4850",
    "addr:street":"Mozartstr",
    "iso:country":"AT",
    "sg:address":"Mozartstr 4",
    "sg:city":"Timelkam",
    "sg:orig_category":"Fernsehservice",
    "sg:phone":"+43 767292680",
    "sg:postcode":"4850",
    "sg:province":"Ober\u00f6sterreich",
    "wof:name":"K\u00f6nigseder Wolfgang",
    "wof:placetype":"venue"
},
  "geometry": {"coordinates":[13.6125326157,48.000831604],"type":"Point"}
}