{
  "type": "Feature",
  "properties": {
    "addr:full":"Bl\u00fctenstr 3 Linz Ober\u00f6sterreich 4040",
    "addr:housenumber":"3",
    "addr:postcode":"4040",
    "addr:street":"Bluetenstr",
    "iso:country":"AT",
    "sg:address":"Bl\u00fctenstr 3",
    "sg:city":"Linz",
    "sg:orig_category":"Friseure U Frisiersalons",
    "sg:phone":"+43 732 738984",
    "sg:postcode":"4040",
    "sg:province":"Ober\u00f6sterreich",
    "wof:name":"Kamm & Schere",
    "wof:placetype":"venue"
},
  "geometry": {"coordinates":[14.2578554153,48.3602561951],"type":"Point"}
}