{
  "type": "Feature",
  "properties": {
    "iso:country":"AT",
    "sg:address":"K\u00e4rntner Ring 10",
    "sg:city":"Wien",
    "sg:orig_category":"Bars-Cafes",
    "sg:phone":"+43 1 5059986",
    "sg:postcode":"1010",
    "sg:province":"Wien",
    "wof:name":"Cocktail-Bar Restaurant Wolke",
    "wof:placetype":"venue"
},
  "geometry": {"coordinates":[16.3716869354,48.2016487122],"type":"Point"}
}