{
  "type": "Feature",
  "properties": {
    "iso:country":"AT",
    "sg:address":"Leopold-Weber-Str 24",
    "sg:city":"B\u00f6hlerwerk",
    "sg:orig_category":"Elektroinstallationsunternehmen",
    "sg:phone":"+43 7442 65780",
    "sg:postcode":"3333",
    "sg:province":"Nieder\u00f6sterreich",
    "wof:name":"Stockinger Ernst",
    "wof:placetype":"venue"
},
  "geometry": {"coordinates":[-89.92952728269999,37.2506599426],"type":"Point"}
}