{
  "type": "Feature",
  "properties": {
    "addr:full":"Hertha Firnberg-Str 11 Wien Wien 1100",
    "addr:housenumber":"11",
    "addr:postcode":"1100",
    "iso:country":"AT",
    "sg:address":"Hertha Firnberg-Str 11",
    "sg:city":"Wien",
    "sg:orig_category":"Datenverarbeitung",
    "sg:phone":"+43 1 8136865",
    "sg:postcode":"1100",
    "sg:province":"Wien",
    "wof:name":"Scharf Franz",
    "wof:placetype":"venue"
},
  "geometry": {"coordinates":[16.3421878815,48.1685066223],"type":"Point"}
}