{
  "type": "Feature",
  "properties": {
    "addr:full":"Widum 1a Lustenau Vorarlberg 6890",
    "addr:housenumber":"1a",
    "addr:postcode":"6890",
    "addr:street":"Widum",
    "iso:country":"AT",
    "sg:address":"Widum 1a",
    "sg:city":"Lustenau",
    "sg:classifiers":[
        {
            "category":"Banks & Credit Unions",
            "subcategory":"Investment Brokerage",
            "type":"Services"
        }
    ],
    "sg:phone":"+43 5577 830550",
    "sg:postcode":"6890",
    "sg:province":"Vorarlberg",
    "sg:tags":[
        "work",
        "bituminous",
        "surfacing"
    ],
    "sg:website":"haemmerle-dach.at",
    "wof:name":"Markus H\u00e4mmerle GmbH & Co KG",
    "wof:placetype":"venue"
},
  "geometry": {"coordinates":[9.6577997208,47.4282264709],"type":"Point"}
}