{
  "type": "Feature",
  "properties": {
    "addr:full":"Linke Wienzeile 18 Wien Wien 1060",
    "addr:housenumber":"18",
    "addr:postcode":"1060",
    "addr:street":"Linke Wienzeile",
    "iso:country":"AT",
    "sg:address":"Linke Wienzeile 18",
    "sg:city":"Wien",
    "sg:orig_category":"Lebensmittel / Einzelhandel",
    "sg:phone":"+43 1 9610604",
    "sg:postcode":"1060",
    "sg:province":"Wien",
    "wof:name":"Billa AG",
    "wof:placetype":"venue"
},
  "geometry": {"coordinates":[16.3631877899,48.1987380981],"type":"Point"}
}