{
  "type": "Feature",
  "properties": {
    "iso:country":"AT",
    "sg:address":"Nr 62",
    "sg:city":"Feldkirchen an der Donau",
    "sg:orig_category":"Lebensmittel / Einzelhandel",
    "sg:phone":"+43 7233 6373",
    "sg:postcode":"4101",
    "sg:province":"Ober\u00f6sterreich",
    "wof:name":"ADEG Aktiv Markt",
    "wof:placetype":"venue"
},
  "geometry": {"coordinates":[14.0524549484,48.3450508118],"type":"Point"}
}