{
  "type": "Feature",
  "properties": {
    "iso:country":"AT",
    "sg:address":"Korbin 36",
    "sg:city":"St. Peter im Sulmtal",
    "sg:orig_category":"Schlossereien",
    "sg:phone":"+43 3465 23350",
    "sg:postcode":"8542",
    "sg:province":"Steiermark",
    "wof:name":"Sinnitsch Johann GesmbH & Co KG",
    "wof:placetype":"venue"
},
  "geometry": {"coordinates":[15.2772893906,46.7726974487],"type":"Point"}
}