{
  "type": "Feature",
  "properties": {
    "addr:full":"Oberndorfer Str 28 St. Leonhard am Forst Nieder\u00f6sterreich 3243",
    "addr:housenumber":"28",
    "addr:postcode":"3243",
    "addr:street":"Oberndorfer Str",
    "iso:country":"AT",
    "sg:address":"Oberndorfer Str 28",
    "sg:city":"St. Leonhard am Forst",
    "sg:orig_category":"Tischlereien",
    "sg:phone":"+43 4327 568734",
    "sg:postcode":"3243",
    "sg:province":"Nieder\u00f6sterreich",
    "wof:name":"Baumgartner Herbert GesmbH",
    "wof:placetype":"venue"
},
  "geometry": {"coordinates":[15.2853403091,48.1348114014],"type":"Point"}
}