{
  "type": "Feature",
  "properties": {
    "iso:country":"AT",
    "sg:address":"Hauptschulstr 5a",
    "sg:city":"Wolfsegg am Hausruck",
    "sg:orig_category":"Volksschulen",
    "sg:phone":"+43 4376 767328",
    "sg:postcode":"4902",
    "sg:province":"Ober\u00f6sterreich",
    "wof:name":"Volksschule",
    "wof:placetype":"venue"
},
  "geometry": {"coordinates":[13.676905632,48.108631134],"type":"Point"}
}