{
  "type": "Feature",
  "properties": {
    "iso:country":"AT",
    "sg:address":"Rottmayrg 33",
    "sg:city":"Salzburg",
    "sg:orig_category":"Behinderungen / Leben Mit Behinderungen",
    "sg:phone":"+43 4366 2630428",
    "sg:postcode":"5020",
    "sg:province":"Salzburg",
    "wof:name":"Lebenshilfe Salzburg gemeinn\u00fctzige GmbH",
    "wof:placetype":"venue"
},
  "geometry": {"coordinates":[13.0694608688,47.7862434387],"type":"Point"}
}