{
  "type": "Feature",
  "properties": {
    "addr:full":"Kaindorf 141 Gr\u00f6bming Steiermark 8962",
    "addr:housenumber":"141",
    "addr:postcode":"8962",
    "addr:street":"Kaindorf",
    "iso:country":"AT",
    "sg:address":"Kaindorf 141",
    "sg:city":"Gr\u00f6bming",
    "sg:orig_category":"Filmproduktionen",
    "sg:phone":"+43 676 3391205",
    "sg:postcode":"8962",
    "sg:province":"Steiermark",
    "wof:name":"DIGITAL MEDIA creativ video solutions Inh Christoph Schl\u00fc\u00dflmayr",
    "wof:placetype":"venue"
},
  "geometry": {"coordinates":[13.9257564545,47.443939209],"type":"Point"}
}