{
  "type": "Feature",
  "properties": {
    "iso:country":"AT",
    "sg:address":"Heiligenst\u00e4dter Str 32",
    "sg:city":"Wien",
    "sg:classifiers":[
        {
            "category":"Internet Cafe",
            "subcategory":"None",
            "type":"Food & Drink"
        }
    ],
    "sg:phone":"+43 1 3678082",
    "sg:postcode":"1190",
    "sg:province":"Wien",
    "sg:tags":[
        "internet-provider"
    ],
    "wof:name":"Two Wings Network Inh Benedikt Carda",
    "wof:placetype":"venue"
},
  "geometry": {"coordinates":[16.3584346771,48.2379760742],"type":"Point"}
}