{
  "type": "Feature",
  "properties": {
    "addr:full":"Hauptstr 36 Allentsteig Nieder\u00f6sterreich 3804",
    "addr:housenumber":"36",
    "addr:postcode":"3804",
    "addr:street":"Hauptstr",
    "iso:country":"AT",
    "sg:address":"Hauptstr 36",
    "sg:city":"Allentsteig",
    "sg:orig_category":"Apotheken",
    "sg:phone":"+43 2824 23270",
    "sg:postcode":"3804",
    "sg:province":"Nieder\u00f6sterreich",
    "wof:name":"Apotheke Zur Mariahilf",
    "wof:placetype":"venue"
},
  "geometry": {"coordinates":[15.3299160004,48.6953544617],"type":"Point"}
}