{
  "type": "Feature",
  "properties": {
    "addr:full":"Wallerner Strasse 38 Apetlon Burgenland 7143",
    "addr:housenumber":"38",
    "addr:postcode":"7143",
    "addr:street":"Wallerner Strasse",
    "iso:country":"AT",
    "sg:address":"Wallerner Strasse 38",
    "sg:city":"Apetlon",
    "sg:classifiers":[
        {
            "category":"Building & Trades",
            "subcategory":"Plumbing",
            "type":"Services"
        }
    ],
    "sg:phone":"+43 2175 2294",
    "sg:postcode":"7143",
    "sg:province":"Burgenland",
    "sg:tags":[
        "supraregional",
        "gas"
    ],
    "sg:website":"koppi.at",
    "wof:name":"Hermann Koppi",
    "wof:placetype":"venue"
},
  "geometry": {"coordinates":[16.8387203217,47.747341156],"type":"Point"}
}