{
  "type": "Feature",
  "properties": {
    "addr:full":"Auhofstrasse 188 Wien Wien 1130",
    "addr:housenumber":"188",
    "addr:postcode":"1130",
    "addr:street":"Auhofstrasse",
    "iso:country":"AT",
    "sg:address":"Auhofstrasse 188",
    "sg:city":"Wien",
    "sg:classifiers":[
        {
            "category":"Building & Trades",
            "subcategory":"Plumbing",
            "type":"Services"
        }
    ],
    "sg:phone":"+43 1 8778297",
    "sg:postcode":"1130",
    "sg:province":"Wien",
    "sg:tags":[
        "supraregional",
        "gas"
    ],
    "wof:name":"Rudolf Frenslich",
    "wof:placetype":"venue"
},
  "geometry": {"coordinates":[16.2615299225,48.195022583],"type":"Point"}
}