{
  "type": "Feature",
  "properties": {
    "addr:full":"Kalvarienbergweg 40 Altm\u00fcnster Ober\u00f6sterreich 4813",
    "addr:housenumber":"40",
    "addr:postcode":"4813",
    "addr:street":"Kalvarienbergweg;Oberoesterreich",
    "iso:country":"AT",
    "sg:address":"Kalvarienbergweg 40",
    "sg:city":"Altm\u00fcnster",
    "sg:orig_category":"Lebens- U Sozialberatung",
    "sg:phone":"+43 664 3402371",
    "sg:postcode":"4813",
    "sg:province":"Ober\u00f6sterreich",
    "wof:name":"Institut f Naturheilverfahren - systemische Lebens und Sozialberatung",
    "wof:placetype":"venue"
},
  "geometry": {"coordinates":[13.7551708221,47.9016075134],"type":"Point"}
}