{
  "type": "Feature",
  "properties": {
    "addr:full":"Feldg 7 Hornstein Burgenland 7053",
    "addr:housenumber":"7",
    "addr:postcode":"7053",
    "addr:street":"Feldg",
    "iso:country":"AT",
    "sg:address":"Feldg 7",
    "sg:city":"Hornstein",
    "sg:orig_category":"Reinigungsbedarf U Reinigungsmittel",
    "sg:phone":"+43 4366 42525742",
    "sg:postcode":"7053",
    "sg:province":"Burgenland",
    "wof:name":"Seifen Baron - Karl Glotzmann",
    "wof:placetype":"venue"
},
  "geometry": {"coordinates":[16.442199707,47.8792800903],"type":"Point"}
}