{
  "type": "Feature",
  "properties": {
    "addr:full":"Saalhofstr. 16 Maishofen Salzburg 5751",
    "addr:housenumber":"16",
    "addr:postcode":"5751",
    "addr:street":"Saalhofstr.;Salzburg",
    "iso:country":"AT",
    "sg:address":"Saalhofstr. 16",
    "sg:city":"Maishofen",
    "sg:orig_category":"Immobilien U Baugewerbe, Baugewerbe",
    "sg:postcode":"5751",
    "sg:province":"Salzburg",
    "sg:website":"http://www.oberrater-bau.at",
    "wof:name":"Oberrater Bau GesmbH - Maishofen",
    "wof:placetype":"venue"
},
  "geometry": {"coordinates":[12.8030033112,47.3610572815],"type":"Point"}
}