{
  "type": "Feature",
  "properties": {
    "addr:full":"Steiner Landstr 66 Krems an der Donau Nieder\u00f6sterreich 3500",
    "addr:housenumber":"66",
    "addr:postcode":"3500",
    "addr:street":"Steiner Landstr",
    "iso:country":"AT",
    "sg:address":"Steiner Landstr 66",
    "sg:city":"Krems an der Donau",
    "sg:orig_category":"Mauertrockenlegungen",
    "sg:phone":"+43 2732 85720",
    "sg:postcode":"3500",
    "sg:province":"Nieder\u00f6sterreich",
    "wof:name":"Mauertrockenlegung Klein",
    "wof:placetype":"venue"
},
  "geometry": {"coordinates":[15.5822820663,48.4022064209],"type":"Point"}
}