{
  "type": "Feature",
  "properties": {
    "addr:full":"Knappenstr 13 Seebenstein Nieder\u00f6sterreich 2824",
    "addr:housenumber":"13",
    "addr:postcode":"2824",
    "addr:street":"Knappenstr",
    "iso:country":"AT",
    "sg:address":"Knappenstr 13",
    "sg:city":"Seebenstein",
    "sg:orig_category":"Installationsunternehmen",
    "sg:phone":"+43 2627 47788",
    "sg:postcode":"2824",
    "sg:province":"Nieder\u00f6sterreich",
    "wof:name":"Mr. Solar Johann Speta",
    "wof:placetype":"venue"
},
  "geometry": {"coordinates":[16.1547203064,47.6996574402],"type":"Point"}
}