{
  "type": "Feature",
  "properties": {
    "addr:full":"Triester Str 47 Feldkirchen Steiermark 8073",
    "addr:postcode":"8073",
    "addr:street":"Str 47",
    "iso:country":"AT",
    "sg:address":"Triester Str 47",
    "sg:city":"Feldkirchen",
    "sg:orig_category":"Tankstellen",
    "sg:phone":"+43 316 291305",
    "sg:postcode":"8073",
    "sg:province":"Steiermark",
    "wof:name":"Hammerl Peter",
    "wof:placetype":"venue"
},
  "geometry": {"coordinates":[15.4434957504,47.012096405],"type":"Point"}
}