{
  "type": "Feature",
  "properties": {
    "addr:full":"Esterhazypl 6a Eisenstadt Burgenland 7000",
    "addr:housenumber":"6a",
    "addr:postcode":"7000",
    "addr:street":"Esterhazypl",
    "iso:country":"AT",
    "sg:address":"Esterhazypl 6a",
    "sg:city":"Eisenstadt",
    "sg:orig_category":"Banken U Sparkassen",
    "sg:phone":"+43 2682 75562",
    "sg:postcode":"7000",
    "sg:province":"Burgenland",
    "wof:name":"Oberbank AG",
    "wof:placetype":"venue"
},
  "geometry": {"coordinates":[16.5205917358,47.8461685181],"type":"Point"}
}