{
  "type": "Feature",
  "properties": {
    "addr:full":"Venusberger Str. 40 Traismauer Nieder\u00f6sterreich 3133",
    "addr:postcode":"3133",
    "addr:street":"Str. 40",
    "iso:country":"AT",
    "sg:address":"Venusberger Str. 40",
    "sg:city":"Traismauer",
    "sg:classifiers":[
        {
            "category":"Professional",
            "subcategory":"Engineering",
            "type":"Services"
        }
    ],
    "sg:phone":"+43 4327 834111",
    "sg:postcode":"3133",
    "sg:province":"Nieder\u00f6sterreich",
    "sg:tags":[
        "machine",
        "-",
        "mechanical"
    ],
    "wof:name":"BEKUM MASCHINENFABRIK GESMBH",
    "wof:placetype":"venue"
},
  "geometry": {"coordinates":[15.7426900864,48.3481292725],"type":"Point"}
}