{
  "type": "Feature",
  "properties": {
    "addr:full":"Herreng 21 Fulpmes Tirol 6166",
    "addr:housenumber":"21",
    "addr:postcode":"6166",
    "addr:street":"Herreng;Tirol",
    "iso:country":"AT",
    "sg:address":"Herreng 21",
    "sg:city":"Fulpmes",
    "sg:orig_category":"Feuerwehren",
    "sg:phone":"+43 5225 62047",
    "sg:postcode":"6166",
    "sg:province":"Tirol",
    "wof:name":"Freiwillige Feuerwehr Fulpmes",
    "wof:placetype":"venue"
},
  "geometry": {"coordinates":[11.3464460373,47.1537284851],"type":"Point"}
}