{
  "type": "Feature",
  "properties": {
    "addr:full":"Florianig 3 Weiz Steiermark 8160",
    "addr:housenumber":"3",
    "addr:postcode":"8160",
    "addr:street":"Florianig",
    "iso:country":"AT",
    "sg:address":"Florianig 3",
    "sg:city":"Weiz",
    "sg:orig_category":"Alternativtherapie",
    "sg:phone":"+43 664 5829294",
    "sg:postcode":"8160",
    "sg:province":"Steiermark",
    "wof:name":"Teni-Rath Anita",
    "wof:placetype":"venue"
},
  "geometry": {"coordinates":[15.62596035,47.2131958008],"type":"Point"}
}