{
  "type": "Feature",
  "properties": {
    "iso:country":"AT",
    "sg:address":"Lastenstr 38/9",
    "sg:city":"Linz",
    "sg:classifiers":[
        {
            "category":"Internet Cafe",
            "subcategory":"None",
            "type":"Food & Drink"
        }
    ],
    "sg:phone":"+43 732 3313000",
    "sg:postcode":"4020",
    "sg:province":"Ober\u00f6sterreich",
    "sg:tags":[
        "internet-provider"
    ],
    "wof:name":"ACSIS IT-Solutions GmbH & Co KG",
    "wof:placetype":"venue"
},
  "geometry": {"coordinates":[14.3051519394,48.291469574],"type":"Point"}
}