{
  "type": "Feature",
  "properties": {
    "addr:full":"Hauptstr 164 Krumpendorf K\u00e4rnten 9201",
    "addr:housenumber":"164",
    "addr:postcode":"9201",
    "addr:street":"Hauptstr;Kaernten",
    "iso:country":"AT",
    "sg:address":"Hauptstr 164",
    "sg:city":"Krumpendorf",
    "sg:classifiers":[
        {
            "category":"Travel",
            "subcategory":"Hotels & Motels",
            "type":"Entertainment"
        }
    ],
    "sg:phone":"+43 4229 23010",
    "sg:postcode":"9201",
    "sg:province":"K\u00e4rnten",
    "wof:name":"Hotel Krumpendorferhof",
    "wof:placetype":"venue"
},
  "geometry": {"coordinates":[14.2111902237,46.6271438599],"type":"Point"}
}