{
  "type": "Feature",
  "properties": {
    "addr:full":"Enhartinger Str 3 K\u00f6stendorf Salzburg 5203",
    "addr:housenumber":"3",
    "addr:postcode":"5203",
    "addr:street":"Str;Salzburg",
    "iso:country":"AT",
    "sg:address":"Enhartinger Str 3",
    "sg:city":"K\u00f6stendorf",
    "sg:classifiers":[
        {
            "category":"Home & Garden",
            "subcategory":"Building Materials",
            "type":"Retail Goods"
        }
    ],
    "sg:phone":"+43 4362 1653190",
    "sg:postcode":"5203",
    "sg:province":"Salzburg",
    "sg:tags":[
        "baustoffe",
        "-material",
        "u"
    ],
    "wof:name":"Struber Josef",
    "wof:placetype":"venue"
},
  "geometry": {"coordinates":[13.1981563568,47.9566192627],"type":"Point"}
}