{
  "type": "Feature",
  "properties": {
    "addr:full":"Wieseng 13 Wiener Neudorf Nieder\u00f6sterreich 2351",
    "addr:housenumber":"13",
    "addr:postcode":"2351",
    "addr:street":"Wieseng",
    "iso:country":"AT",
    "sg:address":"Wieseng 13",
    "sg:city":"Wiener Neudorf",
    "sg:orig_category":"Kosmetikanwendungsberatung",
    "sg:phone":"+43 2236 65133",
    "sg:postcode":"2351",
    "sg:province":"Nieder\u00f6sterreich",
    "wof:name":"CHANNOINE-KOSMETIK - Schalko Waltraud",
    "wof:placetype":"venue"
},
  "geometry": {"coordinates":[16.3258571625,48.088306427],"type":"Point"}
}