{
  "type": "Feature",
  "properties": {
    "addr:full":"Wiener Str 39 Wiener Neustadt Nieder\u00f6sterreich 2700",
    "addr:postcode":"2700",
    "addr:street":"39",
    "iso:country":"AT",
    "sg:address":"Wiener Str 39",
    "sg:city":"Wiener Neustadt",
    "sg:orig_category":"Massagen",
    "sg:phone":"+43 2622 66561",
    "sg:postcode":"2700",
    "sg:province":"Nieder\u00f6sterreich",
    "wof:name":"Schwarz Helga HARA-SHIATSU-PRAXIS",
    "wof:placetype":"venue"
},
  "geometry": {"coordinates":[16.2448234558,47.8172683716],"type":"Point"}
}