{
  "type": "Feature",
  "properties": {
    "iso:country":"AT",
    "sg:address":"Nr 315",
    "sg:city":"Ischgl",
    "sg:orig_category":"Tankstellen",
    "sg:phone":"+43 5444 5787",
    "sg:postcode":"6561",
    "sg:province":"Tirol",
    "wof:name":"BP Austria Marketing GmbH",
    "wof:placetype":"venue"
},
  "geometry": {"coordinates":[10.2881736755,47.0111351013],"type":"Point"}
}