{
  "type": "Feature",
  "properties": {
    "addr:full":"Kirchstetterng 13 Wien Wien 1160",
    "addr:housenumber":"13",
    "addr:postcode":"1160",
    "addr:street":"Kirchstetterng",
    "iso:country":"AT",
    "sg:address":"Kirchstetterng 13",
    "sg:city":"Wien",
    "sg:orig_category":"Pensionen / Privatzimmer",
    "sg:phone":"+43 1 2181041",
    "sg:postcode":"1160",
    "sg:province":"Wien",
    "sg:website":"members.tripop.com/pension_luf",
    "wof:name":"Luf & Co GesmbH",
    "wof:placetype":"venue"
},
  "geometry": {"coordinates":[16.3316001892,48.2058143616],"type":"Point"}
}