{
  "type": "Feature",
  "properties": {
    "addr:full":"Koednitz 30 Kals am Gro\u00dfglockner Tirol 9981",
    "addr:housenumber":"30",
    "addr:postcode":"9981",
    "addr:street":"Koednitz;Grossglockner",
    "iso:country":"AT",
    "sg:address":"Koednitz 30",
    "sg:city":"Kals am Gro\u00dfglockner",
    "sg:orig_category":"Reisen, Tourismusinfo",
    "sg:phone":"+43 4876 8328",
    "sg:postcode":"9981",
    "sg:province":"Tirol",
    "sg:website":"http://provider.freepage.de/austria",
    "wof:name":"Abenteuer am Grossglockner",
    "wof:placetype":"venue"
},
  "geometry": {"coordinates":[12.6448354721,47.0012321472],"type":"Point"}
}