{
  "type": "Feature",
  "properties": {
    "iso:country":"AT",
    "sg:address":"Salurner Str 2-4",
    "sg:city":"Kufstein",
    "sg:orig_category":"Fliesen U Platten",
    "sg:phone":"+43 5372 68463",
    "sg:postcode":"6330",
    "sg:province":"Tirol",
    "wof:name":"Lercher",
    "wof:placetype":"venue"
},
  "geometry": {"coordinates":[12.1675977707,47.5791740417],"type":"Point"}
}