{
  "type": "Feature",
  "properties": {
    "addr:full":"Industriestr 19a Haid Ober\u00f6sterreich 4053",
    "addr:housenumber":"19a",
    "addr:postcode":"4053",
    "addr:street":"Industriestr",
    "iso:country":"AT",
    "sg:address":"Industriestr 19a",
    "sg:city":"Haid",
    "sg:orig_category":"Fotografen",
    "sg:phone":"+43 7229 78661",
    "sg:postcode":"4053",
    "sg:province":"Ober\u00f6sterreich",
    "sg:website":"www.bildwerk.at",
    "wof:name":"BILDWERK Breitenfellner-Neum\u00fcller OEG",
    "wof:placetype":"venue"
},
  "geometry": {"coordinates":[14.2602996826,48.2097244263],"type":"Point"}
}