{
  "type": "Feature",
  "properties": {
    "iso:country":"AT",
    "sg:address":"Paradeiserg 10",
    "sg:city":"Klagenfurt",
    "sg:orig_category":"Steuerberatung",
    "sg:phone":"+43 463 56879",
    "sg:postcode":"9020",
    "sg:province":"K\u00e4rnten",
    "wof:name":"Hafner Franz Dkfm WirtschaftstreuhandgesmbH nunm KG",
    "wof:placetype":"venue"
},
  "geometry": {"coordinates":[14.3103132248,46.6235198975],"type":"Point"}
}