{
  "type": "Feature",
  "properties": {
    "iso:country":"AT",
    "sg:address":"Rathausstr 74",
    "sg:city":"Etsdorf am Kamp",
    "sg:orig_category":"Gemeinden",
    "sg:phone":"+43 2735 24450",
    "sg:postcode":"3492",
    "sg:province":"Nieder\u00f6sterreich",
    "wof:name":"Marktgemeinde Grafenegg",
    "wof:placetype":"venue"
},
  "geometry": {"coordinates":[15.7430467606,48.4443740845],"type":"Point"}
}