{
  "type": "Feature",
  "properties": {
    "addr:full":"Bismarckstr 1 Feldbach Steiermark 8330",
    "addr:housenumber":"1",
    "addr:postcode":"8330",
    "addr:street":"Bismarckstr",
    "iso:country":"AT",
    "sg:address":"Bismarckstr 1",
    "sg:city":"Feldbach",
    "sg:orig_category":"Fotografen",
    "sg:phone":"+43 3152 2991",
    "sg:postcode":"8330",
    "sg:province":"Steiermark",
    "wof:name":"Foto Trummer Inh Derler Christine",
    "wof:placetype":"venue"
},
  "geometry": {"coordinates":[15.8879909515,46.9524993896],"type":"Point"}
}