{
  "type": "Feature",
  "properties": {
    "iso:country":"AT",
    "sg:address":"Gewerbepark-Rosenau/Sonntagberg",
    "sg:city":"Rosenau",
    "sg:classifiers":[
        {
            "category":"Bars & Pubs",
            "subcategory":"Biergarten",
            "type":"Food & Drink"
        }
    ],
    "sg:phone":"+43 7448 30400",
    "sg:postcode":"3332",
    "sg:province":"Nieder\u00f6sterreich",
    "sg:tags":[
        "dosing",
        "pump"
    ],
    "sg:website":"prominent.at",
    "wof:name":"ProMinent Dosiertechnik Ges.m.b.H.",
    "wof:placetype":"venue"
},
  "geometry": {"coordinates":[14.761885643,47.9961738586],"type":"Point"}
}