{
  "type": "Feature",
  "properties": {
    "addr:full":"Gewerbepark, Fabriksplatz 1/11 Steyrerm\u00fchl Ober\u00f6sterreich 4662",
    "addr:housenumber":"1 / 11",
    "addr:postcode":"4662",
    "addr:street":"Gewerbepark Fabriksplatz;Oberoesterreich",
    "iso:country":"AT",
    "sg:address":"Gewerbepark, Fabriksplatz 1/11",
    "sg:city":"Steyrerm\u00fchl",
    "sg:classifiers":[
        {
            "category":"Professional",
            "subcategory":"Advertising",
            "type":"Services"
        }
    ],
    "sg:phone":"+43 761344956",
    "sg:postcode":"4662",
    "sg:province":"Ober\u00f6sterreich",
    "sg:tags":[
        "articles"
    ],
    "sg:website":"team4you.co.at",
    "wof:name":"Bauer Karin, team4you",
    "wof:placetype":"venue"
},
  "geometry": {"coordinates":[13.8019104004,47.9919204712],"type":"Point"}
}