{
  "type": "Feature",
  "properties": {
    "addr:full":"Argentinierstr 12/14 Wien Wien 1040",
    "addr:housenumber":"12 / 14",
    "addr:postcode":"1040",
    "addr:street":"Argentinierstr",
    "iso:country":"AT",
    "sg:address":"Argentinierstr 12/14",
    "sg:city":"Wien",
    "sg:classifiers":[
        {
            "category":"Taxi",
            "type":"Transportation"
        }
    ],
    "sg:phone":"+43 4366 41028500",
    "sg:postcode":"1040",
    "sg:province":"Wien",
    "sg:tags":[
        "personentransporte",
        "u"
    ],
    "wof:name":"Heinrich Josef",
    "wof:placetype":"venue"
},
  "geometry": {"coordinates":[16.3716983795,48.1971473694],"type":"Point"}
}