{
  "type": "Feature",
  "properties": {
    "addr:full":"Glocknerstr 24 Bruck an der Gro\u00dfglocknerstra\u00dfe Salzburg 5671",
    "addr:housenumber":"24",
    "addr:postcode":"5671",
    "addr:street":"Glocknerstr;Grossglocknerstrasse Salzburg",
    "iso:country":"AT",
    "sg:address":"Glocknerstr 24",
    "sg:city":"Bruck an der Gro\u00dfglocknerstra\u00dfe",
    "sg:orig_category":"Friseure U Frisiersalons",
    "sg:phone":"+43 4365 456591",
    "sg:postcode":"5671",
    "sg:province":"Salzburg",
    "wof:name":"Friseursalon Schnipp-Schnapp",
    "wof:placetype":"venue"
},
  "geometry": {"coordinates":[12.8232307434,47.28565979],"type":"Point"}
}