{
  "type": "Feature",
  "properties": {
    "addr:full":"Gemstelweg 2 Mittelberg Vorarlberg 6993",
    "addr:housenumber":"2",
    "addr:postcode":"6993",
    "addr:street":"Gemstelweg",
    "iso:country":"AT",
    "sg:address":"Gemstelweg 2",
    "sg:city":"Mittelberg",
    "sg:orig_category":"Pensionen / Privatzimmer",
    "sg:phone":"+43 4355 1765681",
    "sg:postcode":"6993",
    "sg:province":"Vorarlberg",
    "wof:name":"G\u00e4stehaus Walliserstube",
    "wof:placetype":"venue"
},
  "geometry": {"coordinates":[10.1440668106,47.3144683838],"type":"Point"}
}