{
  "type": "Feature",
  "properties": {
    "addr:full":"Ferdinand-Weyrer-Str 15 Innsbruck Tirol 6020",
    "addr:housenumber":"15",
    "addr:postcode":"6020",
    "addr:street":"Ferdinand-Weyrer-Str;Tirol",
    "iso:country":"AT",
    "sg:address":"Ferdinand-Weyrer-Str 15",
    "sg:city":"Innsbruck",
    "sg:orig_category":"Maler, Anstreicher U Lackierer",
    "sg:phone":"+43 4367 63306827",
    "sg:postcode":"6020",
    "sg:province":"Tirol",
    "wof:name":"Armagan KEG",
    "wof:placetype":"venue"
},
  "geometry": {"coordinates":[11.4121904373,47.2811088562],"type":"Point"}
}