{
  "type": "Feature",
  "properties": {
    "addr:full":"Florianisdlg 10 Niklasdorf Steiermark 8712",
    "addr:housenumber":"10",
    "addr:postcode":"8712",
    "addr:street":"Florianisdlg",
    "iso:country":"AT",
    "sg:address":"Florianisdlg 10",
    "sg:city":"Niklasdorf",
    "sg:orig_category":"Feuerwehren",
    "sg:phone":"+43 3842 810600",
    "sg:postcode":"8712",
    "sg:province":"Steiermark",
    "wof:name":"Freiwillige Feuerwehr Proleb",
    "wof:placetype":"venue"
},
  "geometry": {"coordinates":[15.1387062073,47.39818573],"type":"Point"}
}