{
  "type": "Feature",
  "properties": {
    "addr:full":"Modecenterstr 14 Wien Wien 1030",
    "addr:housenumber":"14",
    "addr:postcode":"1030",
    "addr:street":"Modecenterstr",
    "iso:country":"AT",
    "sg:address":"Modecenterstr 14",
    "sg:city":"Wien",
    "sg:orig_category":"Datenverarbeitung",
    "sg:phone":"+43 4317 985012",
    "sg:postcode":"1030",
    "sg:province":"Wien",
    "wof:name":"ITSDONE EDV Dienstleistungs GmbH",
    "wof:placetype":"venue"
},
  "geometry": {"coordinates":[16.4151210785,48.1857070923],"type":"Point"}
}