{
  "type": "Feature",
  "properties": {
    "addr:full":"Favoritenstr 168 Wien Wien 1100",
    "addr:housenumber":"168",
    "addr:postcode":"1100",
    "iso:country":"AT",
    "sg:address":"Favoritenstr 168",
    "sg:city":"Wien",
    "sg:orig_category":"Blumeneinzelhandel",
    "sg:phone":"+43 1 7602550",
    "sg:postcode":"1100",
    "sg:province":"Wien",
    "wof:name":"F\u00f6tschl Martin - F\u00f6tschl bl\u00fcht",
    "wof:placetype":"venue"
},
  "geometry": {"coordinates":[16.3801498413,48.1688728333],"type":"Point"}
}