{
  "type": "Feature",
  "properties": {
    "addr:full":"Freytaggasse 4/16 Wien Wien 1210",
    "addr:housenumber":"4 / 16",
    "addr:postcode":"1210",
    "addr:street":"Freytaggasse",
    "iso:country":"AT",
    "sg:address":"Freytaggasse 4/16",
    "sg:city":"Wien",
    "sg:classifiers":[
        {
            "category":"Organizations",
            "subcategory":"Non-profit Organization",
            "type":"Services"
        }
    ],
    "sg:phone":"+43 1 2713412",
    "sg:postcode":"1210",
    "sg:province":"Wien",
    "sg:tags":[
        "alarm",
        "system"
    ],
    "wof:name":"Mag Hermann Weilinger",
    "wof:placetype":"venue"
},
  "geometry": {"coordinates":[16.4000110626,48.2525596619],"type":"Point"}
}