{
  "type": "Feature",
  "properties": {
    "iso:country":"AT",
    "sg:address":"Burgg 28",
    "sg:city":"Wien",
    "sg:orig_category":"Werbegrafik- U Grafik-Design",
    "sg:phone":"+43 4315 260800",
    "sg:postcode":"1070",
    "sg:province":"Wien",
    "wof:name":"Film & Grafik Studios Manfred Studnitzka",
    "wof:placetype":"venue"
},
  "geometry": {"coordinates":[16.3513908386,48.2044715881],"type":"Point"}
}