{
  "type": "Feature",
  "properties": {
    "addr:full":"Marktpl 1 Grafenw\u00f6rth Nieder\u00f6sterreich 3484",
    "addr:housenumber":"1",
    "addr:postcode":"3484",
    "addr:street":"Marktpl;Niederoesterreich",
    "iso:country":"AT",
    "sg:address":"Marktpl 1",
    "sg:city":"Grafenw\u00f6rth",
    "sg:orig_category":"Polizei U Gendarmerie",
    "sg:phone":"+43 4359 1333283",
    "sg:postcode":"3484",
    "sg:province":"Nieder\u00f6sterreich",
    "wof:name":"Gendarmerie",
    "wof:placetype":"venue"
},
  "geometry": {"coordinates":[-9.1345300674,52.9185905457],"type":"Point"}
}