{
  "type": "Feature",
  "properties": {
    "addr:full":"Hauptstr 73 Stegersbach Burgenland 7551",
    "addr:housenumber":"73",
    "addr:postcode":"7551",
    "addr:street":"Hauptstr",
    "iso:country":"AT",
    "sg:address":"Hauptstr 73",
    "sg:city":"Stegersbach",
    "sg:orig_category":"Autobusunternehmen",
    "sg:phone":"+43 3326 52476",
    "sg:postcode":"7551",
    "sg:province":"Burgenland",
    "wof:name":"Holitz Personentransporte Inh Margit Pelzmann - Autobus-Taxi-Krankenbef\u00f6rderung",
    "wof:placetype":"venue"
},
  "geometry": {"coordinates":[16.1729221344,47.153011322],"type":"Point"}
}