{
  "type": "Feature",
  "properties": {
    "addr:full":"Dirmhirngasse 110 1235",
    "addr:housenumber":"110",
    "addr:postcode":"1235",
    "addr:street":"Dirmhirngasse",
    "iso:country":"AT",
    "sg:address":"Dirmhirngasse 110",
    "sg:classifiers":[
        {
            "category":"Retail",
            "subcategory":"Auto Repair",
            "type":"Services"
        }
    ],
    "sg:phone":"+43 1 8882511",
    "sg:postcode":"1235",
    "sg:tags":[
        "machine",
        "automatic",
        "welding"
    ],
    "sg:website":"esab.at",
    "wof:name":"Esab Ges.m.b.H.",
    "wof:placetype":"venue"
},
  "geometry": {"coordinates":[16.2844524384,48.1391296387],"type":"Point"}
}