{
  "type": "Feature",
  "properties": {
    "iso:country":"AT",
    "sg:address":"Himmelpfortg 5",
    "sg:city":"Wien",
    "sg:orig_category":"Werbegrafik- U Grafik-Design",
    "sg:phone":"+43 4315 126169",
    "sg:postcode":"1010",
    "sg:province":"Wien",
    "sg:website":"freygrafik.at",
    "wof:name":"FREY GRAFIK",
    "wof:placetype":"venue"
},
  "geometry": {"coordinates":[16.3721618652,48.2059516907],"type":"Point"}
}