{
  "type": "Feature",
  "properties": {
    "addr:full":"Oserstr 6 Mistelbach Nieder\u00f6sterreich 2130",
    "addr:housenumber":"6",
    "addr:postcode":"2130",
    "addr:street":"Oserstr;Niederoesterreich",
    "iso:country":"AT",
    "sg:address":"Oserstr 6",
    "sg:city":"Mistelbach",
    "sg:orig_category":"Apotheken",
    "sg:phone":"+43 2572 22710",
    "sg:postcode":"2130",
    "sg:province":"Nieder\u00f6sterreich",
    "wof:name":"St Martin Apotheke",
    "wof:placetype":"venue"
},
  "geometry": {"coordinates":[16.5738372803,48.5672073364],"type":"Point"}
}