{
  "type": "Feature",
  "properties": {
    "addr:full":"Maria-Theresien-Str 36 Lustenau Vorarlberg 6890",
    "addr:housenumber":"36",
    "addr:postcode":"6890",
    "addr:street":"Maria-Theresien-Str",
    "iso:country":"AT",
    "sg:address":"Maria-Theresien-Str 36",
    "sg:city":"Lustenau",
    "sg:orig_category":"Botendienste",
    "sg:phone":"+43 5577 86930",
    "sg:postcode":"6890",
    "sg:province":"Vorarlberg",
    "wof:name":"FunkTrans Schneider",
    "wof:placetype":"venue"
},
  "geometry": {"coordinates":[9.659907341,47.4294662476],"type":"Point"}
}