{
  "type": "Feature",
  "properties": {
    "iso:country":"AT",
    "sg:address":"Gilmstr 1",
    "sg:city":"Innsbruck",
    "sg:orig_category":"Damenmoden",
    "sg:phone":"+43 512 57237746",
    "sg:postcode":"6020",
    "sg:province":"Tirol",
    "wof:name":"Laurel-Shop",
    "wof:placetype":"venue"
},
  "geometry": {"coordinates":[11.3972997665,47.2659187317],"type":"Point"}
}