{
  "type": "Feature",
  "properties": {
    "addr:full":"Franckstrasse 34 Linz Ober\u00f6sterreich 4020",
    "addr:housenumber":"34",
    "addr:postcode":"4020",
    "addr:street":"Franckstrasse",
    "iso:country":"AT",
    "sg:address":"Franckstrasse 34",
    "sg:city":"Linz",
    "sg:classifiers":[
        {
            "category":"Home & Garden",
            "subcategory":"Building Materials",
            "type":"Retail Goods"
        }
    ],
    "sg:phone":"+43 732 6000300",
    "sg:postcode":"4020",
    "sg:province":"Ober\u00f6sterreich",
    "sg:tags":[
        "window",
        "plastic"
    ],
    "sg:website":"komplett-fenster.at",
    "wof:name":"Komplett Fenster Service GmbH & Co KG",
    "wof:placetype":"venue"
},
  "geometry": {"coordinates":[14.3108358383,48.2944755554],"type":"Point"}
}