{
  "type": "Feature",
  "properties": {
    "iso:country":"AT",
    "sg:address":"Sunnbichl 17",
    "sg:city":"Weerberg",
    "sg:orig_category":"Appartements / Ferienwohnungen",
    "sg:phone":"+43 5224 67480",
    "sg:postcode":"6133",
    "sg:province":"Tirol",
    "wof:name":"Anfang Robert",
    "wof:placetype":"venue"
},
  "geometry": {"coordinates":[11.6807117462,47.3138580322],"type":"Point"}
}