{
  "type": "Feature",
  "properties": {
    "addr:full":"Karl Vogt-Str 65 Zell am See Salzburg 5700",
    "addr:housenumber":"65",
    "addr:postcode":"5700",
    "addr:street":"Salzburg",
    "iso:country":"AT",
    "sg:address":"Karl Vogt-Str 65",
    "sg:city":"Zell am See",
    "sg:orig_category":"Werbeagenturen",
    "sg:phone":"+43 6542 741000",
    "sg:postcode":"5700",
    "sg:province":"Salzburg",
    "wof:name":"GFB & Partner Marketing Services GesmbH",
    "wof:placetype":"venue"
},
  "geometry": {"coordinates":[12.801407814,47.3041191101],"type":"Point"}
}