{
  "type": "Feature",
  "properties": {
    "iso:country":"AT",
    "sg:address":"Untertellenmoos 3",
    "sg:city":"Schwarzach",
    "sg:orig_category":"Restaurants: Chinesisch",
    "sg:phone":"+43 5572 57055",
    "sg:postcode":"6858",
    "sg:province":"Vorarlberg",
    "wof:name":"China Restaurant H D",
    "wof:placetype":"venue"
},
  "geometry": {"coordinates":[9.7581701279,47.4516067505],"type":"Point"}
}