{
  "type": "Feature",
  "properties": {
    "iso:country":"AT",
    "sg:address":"Friedhofplatz 4",
    "sg:city":"Tadten",
    "sg:classifiers":[
        {
            "category":"Banks & Credit Unions",
            "subcategory":"Bureau De Change",
            "type":"Services"
        }
    ],
    "sg:phone":"+43 2176 2268",
    "sg:postcode":"7162",
    "sg:province":"Burgenland",
    "sg:tags":[
        "container",
        "storage",
        "tank"
    ],
    "sg:website":"freudenberger.at",
    "wof:name":"Johann Freudenberger",
    "wof:placetype":"venue"
},
  "geometry": {"coordinates":[16.9918670654,47.7604789734],"type":"Point"}
}