{
  "type": "Feature",
  "properties": {
    "iso:country":"AT",
    "sg:address":"Aigen 90",
    "sg:city":"Aigen im Ennstal",
    "sg:classifiers":[
        {
            "category":"Building & Trades",
            "subcategory":"Plumbing",
            "type":"Services"
        }
    ],
    "sg:phone":"+43 3682 23900",
    "sg:postcode":"8943",
    "sg:province":"Steiermark",
    "sg:tags":[
        "supraregional",
        "gas"
    ],
    "sg:website":"haeusler.at",
    "wof:name":"Peter H\u00e4usler - Haustechnik",
    "wof:placetype":"venue"
},
  "geometry": {"coordinates":[14.147192955,47.5240402222],"type":"Point"}
}