{
  "type": "Feature",
  "properties": {
    "iso:country":"AT",
    "sg:address":"Litschauer Str 17",
    "sg:city":"Gm\u00fcnd",
    "sg:orig_category":"Fleischhauereien",
    "sg:phone":"+43 2852 54206",
    "sg:postcode":"3950",
    "sg:province":"Nieder\u00f6sterreich",
    "wof:name":"Feiler Gerhard",
    "wof:placetype":"venue"
},
  "geometry": {"coordinates":[14.9824142456,48.7751235962],"type":"Point"}
}