{
  "type": "Feature",
  "properties": {
    "addr:full":"Rechter Graben 43 Breitenfurt Nieder\u00f6sterreich 2384",
    "addr:housenumber":"43",
    "addr:postcode":"2384",
    "addr:street":"Rechter Graben",
    "iso:country":"AT",
    "sg:address":"Rechter Graben 43",
    "sg:city":"Breitenfurt",
    "sg:orig_category":"Bauunternehmen",
    "sg:phone":"+43 2239 2116",
    "sg:postcode":"2384",
    "sg:province":"Nieder\u00f6sterreich",
    "wof:name":"Frank Peter GesmbH",
    "wof:placetype":"venue"
},
  "geometry": {"coordinates":[16.1386394501,48.1330184937],"type":"Point"}
}