{
  "type": "Feature",
  "properties": {
    "iso:country":"AT",
    "sg:address":"Pettenbacher Str 1",
    "sg:city":"Vorchdorf",
    "sg:orig_category":"Geschenkartikel",
    "sg:phone":"+43 4365 02310711",
    "sg:postcode":"4655",
    "sg:province":"Ober\u00f6sterreich",
    "wof:name":"PRESENTI - edle Aufmerksamkeiten",
    "wof:placetype":"venue"
},
  "geometry": {"coordinates":[13.9236984253,48.0031471252],"type":"Point"}
}