{
  "type": "Feature",
  "properties": {
    "addr:full":"Streitzing 2 Waldzell Ober\u00f6sterreich 4924",
    "addr:housenumber":"2",
    "addr:postcode":"4924",
    "addr:street":"Streitzing",
    "iso:country":"AT",
    "sg:address":"Streitzing 2",
    "sg:city":"Waldzell",
    "sg:orig_category":"Raumausstattung",
    "sg:phone":"+43 7754 33230",
    "sg:postcode":"4924",
    "sg:province":"Ober\u00f6sterreich",
    "wof:name":"Eberhardter-Raumdesign-Dekorstoffe-B\u00f6den",
    "wof:placetype":"venue"
},
  "geometry": {"coordinates":[13.4262657166,48.1358413696],"type":"Point"}
}