{
  "type": "Feature",
  "properties": {
    "iso:country":"AT",
    "sg:address":"Leonfeldner Str 5",
    "sg:city":"Helfenberg",
    "sg:orig_category":"Rettungsdienste",
    "sg:phone":"+43 7216 7003",
    "sg:postcode":"4184",
    "sg:province":"Ober\u00f6sterreich",
    "wof:name":"Rotes Kreuz \u00d6sterreichisches",
    "wof:placetype":"venue"
},
  "geometry": {"coordinates":[14.1428155899,48.5432739258],"type":"Point"}
}