{
  "type": "Feature",
  "properties": {
    "iso:country":"AT",
    "sg:address":"Maria-Theresien-Str 22",
    "sg:city":"Wien",
    "sg:orig_category":"Webdesign",
    "sg:phone":"+43 1 3193887",
    "sg:postcode":"1010",
    "sg:province":"Wien",
    "wof:name":"Datenkraft IT-consulting GmbH",
    "wof:placetype":"venue"
},
  "geometry": {"coordinates":[16.3668613434,48.2167167664],"type":"Point"}
}