{
  "type": "Feature",
  "properties": {
    "addr:full":"Industrieg I/3 Hornstein Burgenland 7053",
    "addr:housenumber":"/ 3",
    "addr:postcode":"7053",
    "addr:street":"I",
    "iso:country":"AT",
    "sg:address":"Industrieg I/3",
    "sg:city":"Hornstein",
    "sg:orig_category":"Elektroinstallationsunternehmen",
    "sg:phone":"+43 2689 22780",
    "sg:postcode":"7053",
    "sg:province":"Burgenland",
    "wof:name":"Mesgolits Ing Elektroinstallationen und HandelsgesmbH",
    "wof:placetype":"venue"
},
  "geometry": {"coordinates":[16.4311943054,47.8761901855],"type":"Point"}
}