{
  "type": "Feature",
  "properties": {
    "addr:full":"Nr 176 Lofer Salzburg 5090",
    "addr:postcode":"5090",
    "addr:street":"Nr;Lofer",
    "iso:country":"AT",
    "sg:address":"Nr 176",
    "sg:city":"Lofer",
    "sg:classifiers":[
        {
            "category":"Park",
            "subcategory":"Provincial",
            "type":"Public Place"
        }
    ],
    "sg:phone":"+43 6588 7326",
    "sg:postcode":"5090",
    "sg:province":"Salzburg",
    "sg:tags":[
        "u",
        "ski-",
        "snowboardschulen"
    ],
    "wof:name":"Skischule & Skiverleih Sturm - Bobo-Kinderclub",
    "wof:placetype":"venue"
},
  "geometry": {"coordinates":[12.6930541992,47.5873069763],"type":"Point"}
}