{
  "type": "Feature",
  "properties": {
    "addr:full":"Renng 18 Kottingbrunn Nieder\u00f6sterreich 2542",
    "addr:housenumber":"18",
    "addr:postcode":"2542",
    "addr:street":"Renng",
    "iso:country":"AT",
    "sg:address":"Renng 18",
    "sg:city":"Kottingbrunn",
    "sg:orig_category":"Polytechnische Schulen",
    "sg:phone":"+43 2252 763340",
    "sg:postcode":"2542",
    "sg:province":"Nieder\u00f6sterreich",
    "wof:name":"Polytechnische Schule",
    "wof:placetype":"venue"
},
  "geometry": {"coordinates":[16.2293796539,47.9499397278],"type":"Point"}
}