{
  "type": "Feature",
  "properties": {
    "addr:full":"Konstanziag 24 Wien Wien 1220",
    "addr:housenumber":"24",
    "addr:postcode":"1220",
    "addr:street":"Konstanziag",
    "iso:country":"AT",
    "sg:address":"Konstanziag 24",
    "sg:city":"Wien",
    "sg:orig_category":"Volksschulen",
    "sg:phone":"+43 1 28098610",
    "sg:postcode":"1220",
    "sg:province":"Wien",
    "wof:name":"Schulen d Stadt Wien",
    "wof:placetype":"venue"
},
  "geometry": {"coordinates":[16.4537582397,48.2231864929],"type":"Point"}
}