{
  "type": "Feature",
  "properties": {
    "iso:country":"AT",
    "sg:address":"Innrain 11/Ursulinenh.",
    "sg:city":"Innsbruck",
    "sg:orig_category":"Psychologen",
    "sg:phone":"+43 664 2225890",
    "sg:postcode":"6020",
    "sg:province":"Tirol",
    "wof:name":"Reichel Elisabeth Dr",
    "wof:placetype":"venue"
},
  "geometry": {"coordinates":[11.3913040161,47.2679977417],"type":"Point"}
}