{
  "type": "Feature",
  "properties": {
    "addr:full":"Hugog 8 Wien Wien 1110",
    "addr:housenumber":"8",
    "addr:postcode":"1110",
    "addr:street":"Hugog",
    "iso:country":"AT",
    "sg:address":"Hugog 8",
    "sg:city":"Wien",
    "sg:orig_category":"Politische Parteien",
    "sg:phone":"+43 1 7492229",
    "sg:postcode":"1110",
    "sg:province":"Wien",
    "wof:name":"Kommunistische Partei \u00f6sterr",
    "wof:placetype":"venue"
},
  "geometry": {"coordinates":[16.4167613983,48.1712722778],"type":"Point"}
}