{
  "type": "Feature",
  "properties": {
    "iso:country":"AT",
    "sg:address":"Neubaugasse 5",
    "sg:city":"Wieselburg an der Erlauf",
    "sg:classifiers":[
        {
            "category":"Military Area",
            "subcategory":"Restricted Area",
            "type":"Public Place"
        }
    ],
    "sg:phone":"+43 7416 58986",
    "sg:postcode":"3250",
    "sg:province":"Nieder\u00f6sterreich",
    "sg:tags":[
        "lan",
        "local",
        "network"
    ],
    "sg:website":"hoermanntechnik.at",
    "wof:name":"Walter H\u00f6rmann GesmbH",
    "wof:placetype":"venue"
},
  "geometry": {"coordinates":[15.1405534744,48.1377639771],"type":"Point"}
}