{
  "type": "Feature",
  "properties": {
    "addr:full":"Sechshauser Str. 48 Wien Wien 1150",
    "addr:postcode":"1150",
    "addr:street":"Str. 48",
    "iso:country":"AT",
    "sg:address":"Sechshauser Str. 48",
    "sg:city":"Wien",
    "sg:classifiers":[
        {
            "category":"Wholesale",
            "subcategory":"Drugs",
            "type":"Manufacturing & Wholesale Goods"
        }
    ],
    "sg:phone":"+43 4318 939333",
    "sg:postcode":"1150",
    "sg:province":"Wien",
    "sg:tags":[
        "chemical",
        "pharmaceutical"
    ],
    "wof:name":"DOW AUSTRIA GESMBH",
    "wof:placetype":"venue"
},
  "geometry": {"coordinates":[16.3315086365,48.1878204346],"type":"Point"}
}