{
  "type": "Feature",
  "properties": {
    "iso:country":"AT",
    "sg:address":"Br\u00e4uhof 118",
    "sg:city":"Grundlsee",
    "sg:orig_category":"Kinderbetreuung",
    "sg:phone":"+43 3622 8511",
    "sg:postcode":"8993",
    "sg:province":"Steiermark",
    "wof:name":"Kindergarten d Pfarre Grundlsee",
    "wof:placetype":"venue"
},
  "geometry": {"coordinates":[13.8424301147,47.62865448],"type":"Point"}
}