{
  "type": "Feature",
  "properties": {
    "addr:full":"Nansenstrasse 2 Wels Ober\u00f6sterreich 4600",
    "addr:housenumber":"2",
    "addr:postcode":"4600",
    "addr:street":"Nansenstrasse;Oberoesterreich",
    "iso:country":"AT",
    "sg:address":"Nansenstrasse 2",
    "sg:city":"Wels",
    "sg:classifiers":[
        {
            "category":"Shopping",
            "subcategory":"Hobbies, Toys, & Games",
            "type":"Retail Goods"
        }
    ],
    "sg:phone":"+43 7242 67305",
    "sg:postcode":"4600",
    "sg:province":"Ober\u00f6sterreich",
    "sg:tags":[
        "baby",
        "infant",
        "toy",
        "toys"
    ],
    "sg:website":"pietro.at",
    "wof:name":"PIETRO Spielwaren Heinzl",
    "wof:placetype":"venue"
},
  "geometry": {"coordinates":[14.0136756897,48.1746635437],"type":"Point"}
}