{
  "type": "Feature",
  "properties": {
    "addr:full":"Pfarrg 11 Bad Ischl Ober\u00f6sterreich 4820",
    "addr:housenumber":"11",
    "addr:postcode":"4820",
    "addr:street":"Pfarrg",
    "iso:country":"AT",
    "sg:address":"Pfarrg 11",
    "sg:city":"Bad Ischl",
    "sg:orig_category":"Gemeinden",
    "sg:phone":"+43 6132 3010",
    "sg:postcode":"4820",
    "sg:province":"Ober\u00f6sterreich",
    "wof:name":"Stadtamt Bad Ischl",
    "wof:placetype":"venue"
},
  "geometry": {"coordinates":[13.6219987869,47.7110214233],"type":"Point"}
}