{
  "type": "Feature",
  "properties": {
    "addr:full":"Hofsteigstr 18 Hard Vorarlberg 6971",
    "addr:housenumber":"18",
    "addr:postcode":"6971",
    "addr:street":"Hofsteigstr",
    "iso:country":"AT",
    "sg:address":"Hofsteigstr 18",
    "sg:city":"Hard",
    "sg:orig_category":"Werbeartikel U -Geschenke, Geschenkartikel",
    "sg:phone":"+43 5574 75377",
    "sg:postcode":"6971",
    "sg:province":"Vorarlberg",
    "wof:name":"Bachmann Gro\u00dfhandel",
    "wof:placetype":"venue"
},
  "geometry": {"coordinates":[9.6928796768,47.4899520874],"type":"Point"}
}