{
  "type": "Feature",
  "properties": {
    "addr:full":"Valdunastr 16 Rankweil Vorarlberg 6830",
    "addr:housenumber":"16",
    "addr:postcode":"6830",
    "addr:street":"Valdunastr",
    "iso:country":"AT",
    "sg:address":"Valdunastr 16",
    "sg:city":"Rankweil",
    "sg:orig_category":"Banken U Sparkassen",
    "sg:phone":"+43 4355 224034510",
    "sg:postcode":"6830",
    "sg:province":"Vorarlberg",
    "wof:name":"Vorarlberger Landes- u Hypothekenbank AG",
    "wof:placetype":"venue"
},
  "geometry": {"coordinates":[9.6473484039,47.2608795166],"type":"Point"}
}