{
  "type": "Feature",
  "properties": {
    "addr:full":"Nr 44 Bischofshofen Salzburg 5500",
    "addr:postcode":"5500",
    "addr:street":"Nr",
    "iso:country":"AT",
    "sg:address":"Nr 44",
    "sg:city":"Bischofshofen",
    "sg:orig_category":"Musikgruppen",
    "sg:phone":"+43 6462 3493",
    "sg:postcode":"5500",
    "sg:province":"Salzburg",
    "wof:name":"ALPENECHO",
    "wof:placetype":"venue"
},
  "geometry": {"coordinates":[166.9221496582,-0.5282999873],"type":"Point"}
}