{
  "type": "Feature",
  "properties": {
    "addr:full":"Siebensterng 42-44 Wien Wien 1070",
    "addr:postcode":"42-44;1070",
    "iso:country":"AT",
    "sg:address":"Siebensterng 42-44",
    "sg:city":"Wien",
    "sg:orig_category":"Physiotherapie",
    "sg:phone":"+43 4369 919247221",
    "sg:postcode":"1070",
    "sg:province":"Wien",
    "wof:name":"Prinz Martina Dipl-PT",
    "wof:placetype":"venue"
},
  "geometry": {"coordinates":[16.3515758514,48.2023086548],"type":"Point"}
}