{
  "type": "Feature",
  "properties": {
    "addr:full":"Mozartstr 10 Eggenburg Nieder\u00f6sterreich 3730",
    "addr:housenumber":"10",
    "addr:postcode":"3730",
    "addr:street":"Mozartstr",
    "iso:country":"AT",
    "sg:address":"Mozartstr 10",
    "sg:city":"Eggenburg",
    "sg:orig_category":"Hauptschulen",
    "sg:phone":"+43 2984 26440",
    "sg:postcode":"3730",
    "sg:province":"Nieder\u00f6sterreich",
    "wof:name":"Interessens- und Begabungsorientierte Hauptschule Eggenburg",
    "wof:placetype":"venue"
},
  "geometry": {"coordinates":[15.8162641525,48.6473388672],"type":"Point"}
}