{
  "type": "Feature",
  "properties": {
    "addr:full":"Albert-Schweitzer-Str 50a Wels Ober\u00f6sterreich 4600",
    "addr:housenumber":"50a",
    "addr:postcode":"4600",
    "addr:street":"Albert-Schweitzer-Str;Oberoesterreich",
    "iso:country":"AT",
    "sg:address":"Albert-Schweitzer-Str 50a",
    "sg:city":"Wels",
    "sg:orig_category":"Behinderungen / Leben Mit Behinderungen",
    "sg:phone":"+43 4372 4273996",
    "sg:postcode":"4600",
    "sg:province":"Ober\u00f6sterreich",
    "wof:name":"Arbeiter Samariter Bund \u00f6sterreich - Behindertenservice",
    "wof:placetype":"venue"
},
  "geometry": {"coordinates":[13.9927244186,48.1597442627],"type":"Point"}
}