{
  "type": "Feature",
  "properties": {
    "iso:country":"AT",
    "sg:address":"Franz-Dittelbach-Strasse 16-18",
    "sg:city":"Gloggnitz",
    "sg:orig_category":"ChildrenS Beds, Cots",
    "sg:phone":"+43 2662 42285",
    "sg:postcode":"2640",
    "sg:province":"Nieder\u00f6sterreich",
    "sg:website":"moebeledlinger.com",
    "wof:name":"Ing. Karl Edlinger GesmbH",
    "wof:placetype":"venue"
},
  "geometry": {"coordinates":[15.945775032,47.6759529114],"type":"Point"}
}