{
  "type": "Feature",
  "properties": {
    "addr:full":"Industriestrasse 1 Kittsee Burgenland 2421",
    "addr:housenumber":"1",
    "addr:postcode":"2421",
    "addr:street":"Industriestrasse",
    "iso:country":"AT",
    "sg:address":"Industriestrasse 1",
    "sg:city":"Kittsee",
    "sg:classifiers":[
        {
            "category":"Food & Beverages",
            "subcategory":"Chocolate",
            "type":"Retail Goods"
        }
    ],
    "sg:phone":"+43 2143 23510",
    "sg:postcode":"2421",
    "sg:province":"Burgenland",
    "sg:website":"chocolate-austria.com",
    "wof:name":"Franz Hauswirth Ges.m.b.H.",
    "wof:placetype":"venue"
},
  "geometry": {"coordinates":[17.0641498566,48.0944442749],"type":"Point"}
}