{
  "type": "Feature",
  "properties": {
    "iso:country":"AT",
    "sg:address":"Panikeng 3-5",
    "sg:city":"Wien",
    "sg:orig_category":"Siebdruckmaschinen U -Bedarf",
    "sg:phone":"+43 1 49552180",
    "sg:postcode":"1160",
    "sg:province":"Wien",
    "wof:name":"Szerencsics Alexander Ing",
    "wof:placetype":"venue"
},
  "geometry": {"coordinates":[16.3233890533,48.2060165405],"type":"Point"}
}