{
  "type": "Feature",
  "properties": {
    "iso:country":"AT",
    "sg:address":"Hauptpl 13",
    "sg:city":"G\u00fcssing",
    "sg:orig_category":"Non-Classified Establishments",
    "sg:phone":"+43 3322 42428",
    "sg:postcode":"7540",
    "sg:province":"Burgenland",
    "wof:name":"Kirchenbeitragsstelle",
    "wof:placetype":"venue"
},
  "geometry": {"coordinates":[16.3229007721,47.059627533],"type":"Point"}
}