{
  "type": "Feature",
  "properties": {
    "addr:full":"Mantlerg 30-32 Wien Wien 1130",
    "addr:postcode":"30-32;1130",
    "iso:country":"AT",
    "sg:address":"Mantlerg 30-32",
    "sg:city":"Wien",
    "sg:orig_category":"Werbeagenturen",
    "sg:phone":"+43 1 878870",
    "sg:postcode":"1130",
    "sg:province":"Wien",
    "wof:name":"Saatchi & Saatchi WerbegesmbH",
    "wof:placetype":"venue"
},
  "geometry": {"coordinates":[16.2807064056,48.1909408569],"type":"Point"}
}