{
  "type": "Feature",
  "properties": {
    "iso:country":"AT",
    "sg:address":"Hollabrunner Str 31",
    "sg:city":"Hollabrunn",
    "sg:orig_category":"Weine / Einzelhandel",
    "sg:phone":"+43 2952 2989",
    "sg:postcode":"2020",
    "sg:province":"Nieder\u00f6sterreich",
    "wof:name":"Strobl Friedrich",
    "wof:placetype":"venue"
},
  "geometry": {"coordinates":[16.0669784546,48.6014022827],"type":"Point"}
}