{
  "type": "Feature",
  "properties": {
    "iso:country":"AT",
    "sg:address":"Hauptpl 9",
    "sg:city":"Spittal an der Drau",
    "sg:orig_category":"Glaswaren",
    "sg:phone":"+43 4762 207516",
    "sg:postcode":"9800",
    "sg:province":"K\u00e4rnten",
    "wof:name":"Casa Leonardo Inh Franz Pech",
    "wof:placetype":"venue"
},
  "geometry": {"coordinates":[13.4980821609,46.7975883484],"type":"Point"}
}