{
  "type": "Feature",
  "properties": {
    "addr:full":"Tratteng 1 Villach K\u00e4rnten 9500",
    "addr:housenumber":"1",
    "addr:postcode":"9500",
    "addr:street":"Tratteng;Kaernten",
    "iso:country":"AT",
    "sg:address":"Tratteng 1",
    "sg:city":"Villach",
    "sg:orig_category":"Telekommunikation",
    "sg:phone":"+43 4242 22400",
    "sg:postcode":"9500",
    "sg:province":"K\u00e4rnten",
    "wof:name":"PS-TEC Technologie HandelsgesmbH",
    "wof:placetype":"venue"
},
  "geometry": {"coordinates":[13.8523759842,46.6145477295],"type":"Point"}
}