{
  "type": "Feature",
  "properties": {
    "addr:full":"Rasdorf 10 Kopfing im Innkreis Ober\u00f6sterreich 4794",
    "addr:housenumber":"10",
    "addr:postcode":"4794",
    "addr:street":"Im Innkreis",
    "iso:country":"AT",
    "sg:address":"Rasdorf 10",
    "sg:city":"Kopfing im Innkreis",
    "sg:orig_category":"Installationsunternehmen",
    "sg:phone":"+43 7763 2513",
    "sg:postcode":"4794",
    "sg:province":"Ober\u00f6sterreich",
    "wof:name":"Gahleitner Installationen GesmbH & Co KG",
    "wof:placetype":"venue"
},
  "geometry": {"coordinates":[13.6788072586,48.4335250854],"type":"Point"}
}