{
  "type": "Feature",
  "properties": {
    "addr:full":"Steyrtalstr 133 Neuzeug Ober\u00f6sterreich 4523",
    "addr:housenumber":"133",
    "addr:postcode":"4523",
    "iso:country":"AT",
    "sg:address":"Steyrtalstr 133",
    "sg:city":"Neuzeug",
    "sg:orig_category":"Autohandel",
    "sg:phone":"+43 7259 2059",
    "sg:postcode":"4523",
    "sg:province":"Ober\u00f6sterreich",
    "wof:name":"Mohringer Karl",
    "wof:placetype":"venue"
},
  "geometry": {"coordinates":[14.330329895,48.0440711975],"type":"Point"}
}