{
  "type": "Feature",
  "properties": {
    "addr:full":"Reinhartsdorfg 36 Schwechat Nieder\u00f6sterreich 2320",
    "addr:housenumber":"36",
    "addr:postcode":"2320",
    "addr:street":"Reinhartsdorfg;Niederoesterreich",
    "iso:country":"AT",
    "sg:address":"Reinhartsdorfg 36",
    "sg:city":"Schwechat",
    "sg:orig_category":"Innenausbau",
    "sg:phone":"+43 1 70797790",
    "sg:postcode":"2320",
    "sg:province":"Nieder\u00f6sterreich",
    "wof:name":"Knapp Johann GesmbH",
    "wof:placetype":"venue"
},
  "geometry": {"coordinates":[16.4606800079,48.1166000366],"type":"Point"}
}