{
  "type": "Feature",
  "properties": {
    "addr:full":"Untereitzing 32 Aurolzm\u00fcnster Ober\u00f6sterreich 4971",
    "addr:housenumber":"32",
    "addr:postcode":"4971",
    "addr:street":"Untereitzing;Oberoesterreich",
    "iso:country":"AT",
    "sg:address":"Untereitzing 32",
    "sg:city":"Aurolzm\u00fcnster",
    "sg:orig_category":"Banken U Sparkassen",
    "sg:phone":"+43 4377 52834110",
    "sg:postcode":"4971",
    "sg:province":"Ober\u00f6sterreich",
    "wof:name":"Raiffeisenbank Region Ried regGenmbH",
    "wof:placetype":"venue"
},
  "geometry": {"coordinates":[13.4548149109,48.248500824],"type":"Point"}
}