{
  "type": "Feature",
  "properties": {
    "addr:full":"Sachsenpl. 4-6  Wien Wien 1200",
    "addr:housenumber":"4-6",
    "addr:postcode":"1200",
    "addr:street":"Sachsenpl.",
    "iso:country":"AT",
    "sg:address":"Sachsenpl. 4-6 ",
    "sg:city":"Wien",
    "sg:classifiers":[
        {
            "category":"Manufacturing",
            "subcategory":"Printing",
            "type":"Manufacturing & Wholesale Goods"
        }
    ],
    "sg:phone":"+43 4313 3024330",
    "sg:postcode":"1200",
    "sg:province":"Wien",
    "sg:tags":[
        "publishing"
    ],
    "wof:name":"MINERVA WISSENSCHAFTLICHE BUCHHANDLUNG GESMBH",
    "wof:placetype":"venue"
},
  "geometry": {"coordinates":[16.3758735657,48.2318344116],"type":"Point"}
}