{
  "type": "Feature",
  "properties": {
    "addr:full":"Maria-Theresia-Strasse 17 Wels Ober\u00f6sterreich 4600",
    "addr:housenumber":"17",
    "addr:postcode":"4600",
    "addr:street":"Maria-Theresia-Strasse;Oberoesterreich",
    "iso:country":"AT",
    "sg:address":"Maria-Theresia-Strasse 17",
    "sg:city":"Wels",
    "sg:classifiers":[
        {
            "category":"Manufacturing",
            "subcategory":"Petroleum Products",
            "type":"Manufacturing & Wholesale Goods"
        }
    ],
    "sg:phone":"+43 7242 470270",
    "sg:postcode":"4600",
    "sg:province":"Ober\u00f6sterreich",
    "sg:tags":[
        "oil",
        "diesel"
    ],
    "wof:name":"Kurt Austaller - Heiz\u00f6le",
    "wof:placetype":"venue"
},
  "geometry": {"coordinates":[14.0192518234,48.1560134888],"type":"Point"}
}