{
  "type": "Feature",
  "properties": {
    "addr:full":"Ederg 1-3 Wien Wien 1210",
    "addr:housenumber":"1-3",
    "addr:postcode":"1210",
    "addr:street":"Ederg",
    "iso:country":"AT",
    "sg:address":"Ederg 1-3",
    "sg:city":"Wien",
    "sg:orig_category":"Sonnenstudios",
    "sg:phone":"+43 4312 926468",
    "sg:postcode":"1210",
    "sg:province":"Wien",
    "wof:name":"Sonnenstudio Sunlight",
    "wof:placetype":"venue"
},
  "geometry": {"coordinates":[16.4098339081,48.2774810791],"type":"Point"}
}