{
  "type": "Feature",
  "properties": {
    "addr:full":"Hoher Markt 2 Wien Wien 1010",
    "addr:housenumber":"2",
    "addr:postcode":"1010",
    "addr:street":"Hoher Markt",
    "iso:country":"AT",
    "sg:address":"Hoher Markt 2",
    "sg:city":"Wien",
    "sg:orig_category":"Textilreinigung",
    "sg:phone":"+43 1 5339552",
    "sg:postcode":"1010",
    "sg:province":"Wien",
    "wof:name":"stross qualit\u00e4ts-sofortreinigung - Stross Chem Kleiderreinigung OHG",
    "wof:placetype":"venue"
},
  "geometry": {"coordinates":[16.3727645874,48.2107429504],"type":"Point"}
}