{
  "type": "Feature",
  "properties": {
    "addr:full":"Waldrasterstr 45 Fulpmes Tirol 6166",
    "addr:housenumber":"45",
    "addr:postcode":"6166",
    "addr:street":"Waldrasterstr;Tirol",
    "iso:country":"AT",
    "sg:address":"Waldrasterstr 45",
    "sg:city":"Fulpmes",
    "sg:orig_category":"Tankstellen",
    "sg:phone":"+43 5225 62338",
    "sg:postcode":"6166",
    "sg:province":"Tirol",
    "wof:name":"Shell Austria GmbH",
    "wof:placetype":"venue"
},
  "geometry": {"coordinates":[11.3526792526,47.150302887],"type":"Point"}
}