{
  "type": "Feature",
  "properties": {
    "iso:country":"AT",
    "sg:address":"Ignaz Hirsch-G 22",
    "sg:city":"Willendorf am Steinfelde",
    "sg:orig_category":"Autohandel",
    "sg:phone":"+43 664 2053770",
    "sg:postcode":"2732",
    "sg:province":"Nieder\u00f6sterreich",
    "wof:name":"atv-fun",
    "wof:placetype":"venue"
},
  "geometry": {"coordinates":[16.0493450165,47.7829627991],"type":"Point"}
}