{
  "type": "Feature",
  "properties": {
    "iso:country":"AT",
    "sg:address":"Hauptpl 10",
    "sg:city":"G\u00fcssing",
    "sg:orig_category":"Tabaktrafiken",
    "sg:phone":"+43 3322 42667",
    "sg:postcode":"7540",
    "sg:province":"Burgenland",
    "wof:name":"Menzel Erna",
    "wof:placetype":"venue"
},
  "geometry": {"coordinates":[16.3232746124,47.0594177246],"type":"Point"}
}