{
  "type": "Feature",
  "properties": {
    "addr:full":"Hauptstrasse 36 Kritzendorf Nieder\u00f6sterreich 3420",
    "addr:housenumber":"36",
    "addr:postcode":"3420",
    "addr:street":"Hauptstrasse",
    "iso:country":"AT",
    "sg:address":"Hauptstrasse 36",
    "sg:city":"Kritzendorf",
    "sg:orig_category":"ChildrenS Furniture",
    "sg:phone":"+43 2243 32726",
    "sg:postcode":"3420",
    "sg:province":"Nieder\u00f6sterreich",
    "sg:website":"klosterneuburg.com/chytil",
    "wof:name":"Franz Chytil",
    "wof:placetype":"venue"
},
  "geometry": {"coordinates":[16.3012657166,48.3282661438],"type":"Point"}
}