{
  "type": "Feature",
  "properties": {
    "iso:country":"AT",
    "sg:address":"Tungassingerstr 23",
    "sg:city":"Linz",
    "sg:orig_category":"Polytechnische Schulen",
    "sg:phone":"+43 732 3463060",
    "sg:postcode":"4020",
    "sg:province":"Ober\u00f6sterreich",
    "wof:name":"Polytechnische Schule Spallerhofschule",
    "wof:placetype":"venue"
},
  "geometry": {"coordinates":[14.2995424271,48.2745895386],"type":"Point"}
}