{
  "type": "Feature",
  "properties": {
    "addr:full":"Europastr 22 Linz Ober\u00f6sterreich 4020",
    "addr:housenumber":"22",
    "addr:postcode":"4020",
    "addr:street":"Europastr",
    "iso:country":"AT",
    "sg:address":"Europastr 22",
    "sg:city":"Linz",
    "sg:orig_category":"Werbeagenturen",
    "sg:phone":"+43 732 385794",
    "sg:postcode":"4020",
    "sg:province":"Ober\u00f6sterreich",
    "wof:name":"Bamberger Gerald",
    "wof:placetype":"venue"
},
  "geometry": {"coordinates":[14.2808532715,48.2635765076],"type":"Point"}
}