{
  "type": "Feature",
  "properties": {
    "iso:country":"AT",
    "sg:address":"Maria-Theresien-Str 49",
    "sg:city":"Lustenau",
    "sg:orig_category":"Raumausstattung",
    "sg:phone":"+43 4355 7784344",
    "sg:postcode":"6890",
    "sg:province":"Vorarlberg",
    "wof:name":"Fink Josef",
    "wof:placetype":"venue"
},
  "geometry": {"coordinates":[9.6584024429,47.4321289062],"type":"Point"}
}