{
  "type": "Feature",
  "properties": {
    "iso:country":"AT",
    "sg:address":"Rieder Str 3",
    "sg:city":"Waldzell",
    "sg:orig_category":"Maler, Anstreicher U Lackierer",
    "sg:phone":"+43 7754 25500",
    "sg:postcode":"4924",
    "sg:province":"Ober\u00f6sterreich",
    "wof:name":"Malerei Schachl GmbH",
    "wof:placetype":"venue"
},
  "geometry": {"coordinates":[13.4254798889,48.1371994019],"type":"Point"}
}