{
  "type": "Feature",
  "properties": {
    "addr:full":"Auhofstr 208 Wien Wien 1130",
    "addr:housenumber":"208",
    "addr:postcode":"1130",
    "iso:country":"AT",
    "sg:address":"Auhofstr 208",
    "sg:city":"Wien",
    "sg:orig_category":"Bauunternehmen",
    "sg:phone":"+43 1 87608780",
    "sg:postcode":"1130",
    "sg:province":"Wien",
    "wof:name":"FBG FassadenbaugesmbH",
    "wof:placetype":"venue"
},
  "geometry": {"coordinates":[16.2587451935,48.1960105896],"type":"Point"}
}