{
  "type": "Feature",
  "properties": {
    "addr:full":"Salzg 7 Freistadt Ober\u00f6sterreich 4240",
    "addr:housenumber":"7",
    "addr:postcode":"4240",
    "addr:street":"Salzg",
    "iso:country":"AT",
    "sg:address":"Salzg 7",
    "sg:city":"Freistadt",
    "sg:orig_category":"Tapezierer U Dekorateure",
    "sg:phone":"+43 4379 4273236",
    "sg:postcode":"4240",
    "sg:province":"Ober\u00f6sterreich",
    "wof:name":"H\u00f6rbst Walter",
    "wof:placetype":"venue"
},
  "geometry": {"coordinates":[14.5029687881,48.5115013123],"type":"Point"}
}