{
  "type": "Feature",
  "properties": {
    "iso:country":"AT",
    "sg:address":"Hahng 8/2/17",
    "sg:city":"Wien",
    "sg:orig_category":"Behinderungen / Leben Mit Behinderungen",
    "sg:phone":"+43 1 3178122",
    "sg:postcode":"1090",
    "sg:province":"Wien",
    "wof:name":"Lebenshilfe N\u00d6 Wohngruppe f H\u00f6rgesch\u00e4digte",
    "wof:placetype":"venue"
},
  "geometry": {"coordinates":[16.351474762,48.2234115601],"type":"Point"}
}