{
  "type": "Feature",
  "properties": {
    "addr:full":"Engelbert-Laimer-Str 1 St. P\u00f6lten Nieder\u00f6sterreich 3100",
    "addr:housenumber":"1",
    "addr:postcode":"3100",
    "addr:street":"Engelbert-Laimer-Str",
    "iso:country":"AT",
    "sg:address":"Engelbert-Laimer-Str 1",
    "sg:city":"St. P\u00f6lten",
    "sg:orig_category":"Spielkasinos",
    "sg:phone":"+43 4327 42258675",
    "sg:postcode":"3100",
    "sg:province":"Nieder\u00f6sterreich",
    "wof:name":"Playzon - BT Merten OEG",
    "wof:placetype":"venue"
},
  "geometry": {"coordinates":[-76.07303619379999,41.7845001221],"type":"Point"}
}