{
  "type": "Feature",
  "properties": {
    "iso:country":"AT",
    "sg:address":"Brandstatt 25",
    "sg:city":"Piberbach",
    "sg:orig_category":"Fu\u00c3\u0178pflege U Fu\u00c3\u0178pflegesalons",
    "sg:phone":"+43 4372 288129",
    "sg:postcode":"4533",
    "sg:province":"Ober\u00f6sterreich",
    "wof:name":"Fu\u00dfpflege Geistberger Christine",
    "wof:placetype":"venue"
},
  "geometry": {"coordinates":[14.2183256149,48.0987854004],"type":"Point"}
}