{
  "type": "Feature",
  "properties": {
    "addr:full":"Ernstbrunn Nieder\u00f6sterreich 2115",
    "addr:postcode":"2115",
    "addr:street":"Niederoesterreich",
    "iso:country":"AT",
    "sg:city":"Ernstbrunn",
    "sg:orig_category":"Feuerwehren",
    "sg:phone":"+43 2576 3883",
    "sg:postcode":"2115",
    "sg:province":"Nieder\u00f6sterreich",
    "wof:name":"Freiwillige Feuerwehr Merkersdorf",
    "wof:placetype":"venue"
},
  "geometry": {"coordinates":[16.2997188568,48.53540802],"type":"Point"}
}