{
  "type": "Feature",
  "properties": {
    "iso:country":"AT",
    "sg:address":"Landstra\u00dfer Hauptstr 98/3",
    "sg:city":"Wien",
    "sg:orig_category":"Immobilienmakler",
    "sg:phone":"+43 1 9619861",
    "sg:postcode":"1030",
    "sg:province":"Wien",
    "wof:name":"Grand Markovic KEG",
    "wof:placetype":"venue"
},
  "geometry": {"coordinates":[16.3942527771,48.1988372803],"type":"Point"}
}