{
  "type": "Feature",
  "properties": {
    "addr:full":"Nr 48 Katsch an der Mur Steiermark 8842",
    "addr:postcode":"8842",
    "addr:street":"Nr",
    "iso:country":"AT",
    "sg:address":"Nr 48",
    "sg:city":"Katsch an der Mur",
    "sg:orig_category":"Transportunternehmen",
    "sg:phone":"+43 4335 3683120",
    "sg:postcode":"8842",
    "sg:province":"Steiermark",
    "wof:name":"Hofstadler GmbH",
    "wof:placetype":"venue"
},
  "geometry": {"coordinates":[14.282959938,47.1429824829],"type":"Point"}
}