{
  "type": "Feature",
  "properties": {
    "addr:full":"Gustav-Dittrich-Str 12 Neunkirchen Nieder\u00f6sterreich 2620",
    "addr:housenumber":"12",
    "addr:postcode":"2620",
    "addr:street":"Gustav-Dittrich-Str",
    "iso:country":"AT",
    "sg:address":"Gustav-Dittrich-Str 12",
    "sg:city":"Neunkirchen",
    "sg:orig_category":"Volksschulen",
    "sg:phone":"+43 2635 62768",
    "sg:postcode":"2620",
    "sg:province":"Nieder\u00f6sterreich",
    "wof:name":"Volksschule Neunkirchen-Steinfeld",
    "wof:placetype":"venue"
},
  "geometry": {"coordinates":[16.0779895782,47.7261352539],"type":"Point"}
}