{
  "type": "Feature",
  "properties": {
    "addr:full":"Winterg 61 Purkersdorf Nieder\u00f6sterreich 3002",
    "addr:housenumber":"61",
    "addr:postcode":"3002",
    "addr:street":"Winterg",
    "iso:country":"AT",
    "sg:address":"Winterg 61",
    "sg:city":"Purkersdorf",
    "sg:orig_category":"Physiotherapie",
    "sg:phone":"+43 2231 65437",
    "sg:postcode":"3002",
    "sg:province":"Nieder\u00f6sterreich",
    "wof:name":"Meriaux Silvia Dipl-PT",
    "wof:placetype":"venue"
},
  "geometry": {"coordinates":[16.1875991821,48.2089385986],"type":"Point"}
}