{
  "type": "Feature",
  "properties": {
    "addr:full":"198 A St. Gallenkirch Vorarlberg 6791",
    "addr:housenumber":"198",
    "addr:postcode":"6791",
    "addr:street":"A St.",
    "iso:country":"AT",
    "sg:address":"198 A",
    "sg:city":"St. Gallenkirch",
    "sg:classifiers":[
        {
            "category":"Sports & Exercise",
            "subcategory":"Playing Field",
            "type":"Entertainment"
        }
    ],
    "sg:phone":"+43 4355 5763000",
    "sg:postcode":"6791",
    "sg:province":"Vorarlberg",
    "sg:tags":[
        "game"
    ],
    "wof:name":"SILVRETTA NOVA BERGBAHNEN GMBH",
    "wof:placetype":"venue"
},
  "geometry": {"coordinates":[9.9691953659,47.0225639343],"type":"Point"}
}