{
  "type": "Feature",
  "properties": {
    "addr:full":"Edling 25 Ludmannsdorf K\u00e4rnten 9072",
    "addr:housenumber":"25",
    "addr:postcode":"9072",
    "addr:street":"Edling;Kaernten",
    "iso:country":"AT",
    "sg:address":"Edling 25",
    "sg:city":"Ludmannsdorf",
    "sg:orig_category":"CarpenterS Work Supraregional",
    "sg:phone":"+43 4228 2219",
    "sg:postcode":"9072",
    "sg:province":"K\u00e4rnten",
    "sg:website":"holzbau-gasser.at",
    "wof:name":"Holzbau Gasser GmbH",
    "wof:placetype":"venue"
},
  "geometry": {"coordinates":[14.1477766037,46.542339325],"type":"Point"}
}