{
  "type": "Feature",
  "properties": {
    "addr:full":"Nr 92 Neunkirchen Nieder\u00f6sterreich 2620",
    "addr:postcode":"2620",
    "addr:street":"Nr 92",
    "iso:country":"AT",
    "sg:address":"Nr 92",
    "sg:city":"Neunkirchen",
    "sg:orig_category":"Elektroinstallationsunternehmen",
    "sg:phone":"+43 2635 65135",
    "sg:postcode":"2620",
    "sg:province":"Nieder\u00f6sterreich",
    "wof:name":"Pichler Christian Ing",
    "wof:placetype":"venue"
},
  "geometry": {"coordinates":[16.0825557709,47.7204246521],"type":"Point"}
}