{
  "type": "Feature",
  "properties": {
    "addr:full":"Georg-Sigl-Str 42 Breitenfurt Nieder\u00f6sterreich 2384",
    "addr:housenumber":"42",
    "addr:postcode":"2384",
    "addr:street":"Georg-Sigl-Str",
    "iso:country":"AT",
    "sg:address":"Georg-Sigl-Str 42",
    "sg:city":"Breitenfurt",
    "sg:orig_category":"Stuckateure U Trockenausbauer",
    "sg:phone":"+43 4322 3941300",
    "sg:postcode":"2384",
    "sg:province":"Nieder\u00f6sterreich",
    "wof:name":"Eggenberger HandelsgesmbH",
    "wof:placetype":"venue"
},
  "geometry": {"coordinates":[16.1864395142,48.1355895996],"type":"Point"}
}