{
  "type": "Feature",
  "properties": {
    "iso:country":"AT",
    "sg:address":"Malser Str 17",
    "sg:city":"Landeck",
    "sg:orig_category":"Fleischhauereien",
    "sg:phone":"+43 5442 62522",
    "sg:postcode":"6500",
    "sg:province":"Tirol",
    "wof:name":"Zangerl Franz",
    "wof:placetype":"venue"
},
  "geometry": {"coordinates":[10.6277132034,47.1200027466],"type":"Point"}
}