{
  "type": "Feature",
  "properties": {
    "iso:country":"AT",
    "sg:address":"Neuwaldegger Str 16",
    "sg:city":"Wien",
    "sg:orig_category":"Gerichtsdolmetscher",
    "sg:phone":"+43 1 4891814",
    "sg:postcode":"1170",
    "sg:province":"Wien",
    "wof:name":"Messner Daniela Mag",
    "wof:placetype":"venue"
},
  "geometry": {"coordinates":[16.2883968353,48.2368392944],"type":"Point"}
}