{
  "type": "Feature",
  "properties": {
    "addr:full":"Porzellang 37 Wien Wien 1090",
    "addr:housenumber":"37",
    "addr:postcode":"1090",
    "addr:street":"Porzellang",
    "iso:country":"AT",
    "sg:address":"Porzellang 37",
    "sg:city":"Wien",
    "sg:orig_category":"Friseure U Frisiersalons",
    "sg:phone":"+43 1 3104924",
    "sg:postcode":"1090",
    "sg:province":"Wien",
    "wof:name":"Frisiersalon Lisbeth",
    "wof:placetype":"venue"
},
  "geometry": {"coordinates":[16.3609580994,48.2225151062],"type":"Point"}
}