{
  "type": "Feature",
  "properties": {
    "iso:country":"AT",
    "sg:address":"Hans-Brandstetter-G 12",
    "sg:city":"Graz",
    "sg:orig_category":"Beratungsstellen",
    "sg:phone":"+43 316 481813",
    "sg:postcode":"8010",
    "sg:province":"Steiermark",
    "wof:name":"Psychologische Lehrlingsberatung",
    "wof:placetype":"venue"
},
  "geometry": {"coordinates":[15.4666261673,47.0617332458],"type":"Point"}
}