{
  "type": "Feature",
  "properties": {
    "iso:country":"AT",
    "sg:address":"Gartenstr 10",
    "sg:city":"Wartberg an der Krems",
    "sg:orig_category":"Maler, Anstreicher U Lackierer",
    "sg:phone":"+43 4375 877362",
    "sg:postcode":"4552",
    "sg:province":"Ober\u00f6sterreich",
    "wof:name":"Grall Gernot",
    "wof:placetype":"venue"
},
  "geometry": {"coordinates":[14.1145029068,47.9866294861],"type":"Point"}
}