{
  "type": "Feature",
  "properties": {
    "iso:country":"AT",
    "sg:address":"M\u00fcnchendorfer Str 2",
    "sg:city":"Himberg",
    "sg:orig_category":"Installationsunternehmen",
    "sg:phone":"+43 2235 86789",
    "sg:postcode":"2325",
    "sg:province":"Nieder\u00f6sterreich",
    "wof:name":"Drochter Heinrich GmbH",
    "wof:placetype":"venue"
},
  "geometry": {"coordinates":[16.4394855499,48.0822868347],"type":"Point"}
}