{
  "type": "Feature",
  "properties": {
    "addr:full":"Mariahilfer Str 18 Graz Steiermark 8020",
    "addr:housenumber":"18",
    "addr:postcode":"8020",
    "addr:street":"Str",
    "iso:country":"AT",
    "sg:address":"Mariahilfer Str 18",
    "sg:city":"Graz",
    "sg:orig_category":"Blumeneinzelhandel",
    "sg:phone":"+43 316 711766",
    "sg:postcode":"8020",
    "sg:province":"Steiermark",
    "wof:name":"Blumen Leitner",
    "wof:placetype":"venue"
},
  "geometry": {"coordinates":[15.4336500168,47.07239151],"type":"Point"}
}