{
  "type": "Feature",
  "properties": {
    "addr:full":"H\u00e4ndelstr 27 Linz Ober\u00f6sterreich 4020",
    "addr:housenumber":"27",
    "addr:postcode":"4020",
    "addr:street":"Haendelstr",
    "iso:country":"AT",
    "sg:address":"H\u00e4ndelstr 27",
    "sg:city":"Linz",
    "sg:orig_category":"Banken U Sparkassen",
    "sg:phone":"+43 732 665283",
    "sg:postcode":"4020",
    "sg:province":"Ober\u00f6sterreich",
    "wof:name":"Sparda-Bank Linz regGenmbH",
    "wof:placetype":"venue"
},
  "geometry": {"coordinates":[14.2749090195,48.2897186279],"type":"Point"}
}