{
  "type": "Feature",
  "properties": {
    "addr:full":"Mantlergasse 30-32 Wien Wien 1130",
    "addr:postcode":"30-32;1130",
    "addr:street":"Mantlergasse",
    "iso:country":"AT",
    "sg:address":"Mantlergasse 30-32",
    "sg:city":"Wien",
    "sg:classifiers":[
        {
            "category":"Professional",
            "subcategory":"Advertising",
            "type":"Services"
        }
    ],
    "sg:phone":"+43 1 878870",
    "sg:postcode":"1130",
    "sg:province":"Wien",
    "sg:tags":[
        "agency"
    ],
    "sg:website":"saatchi.at",
    "wof:name":"Saatchi & Saatchi Werbegesellschaft m.b.H.",
    "wof:placetype":"venue"
},
  "geometry": {"coordinates":[16.2807064056,48.1909408569],"type":"Point"}
}