{
  "type": "Feature",
  "properties": {
    "iso:country":"AT",
    "sg:address":"Getreideg 31",
    "sg:city":"Salzburg",
    "sg:orig_category":"Immobilienmakler",
    "sg:phone":"+43 4366 2841878",
    "sg:postcode":"5020",
    "sg:province":"Salzburg",
    "wof:name":"CEDES Immobilien & Projektentwicklung GmbH",
    "wof:placetype":"venue"
},
  "geometry": {"coordinates":[13.0417327881,47.7998657227],"type":"Point"}
}