{
  "type": "Feature",
  "properties": {
    "addr:full":"Neudeggerg 13 Wien Wien 1080",
    "addr:housenumber":"13",
    "addr:postcode":"1080",
    "addr:street":"Neudeggerg",
    "iso:country":"AT",
    "sg:address":"Neudeggerg 13",
    "sg:city":"Wien",
    "sg:orig_category":"Architekten",
    "sg:phone":"+43 1 5229682",
    "sg:postcode":"1080",
    "sg:province":"Wien",
    "wof:name":"Petrac Heribert Arch Dipl-Ing",
    "wof:placetype":"venue"
},
  "geometry": {"coordinates":[16.3515548706,48.2073020935],"type":"Point"}
}