{
  "type": "Feature",
  "properties": {
    "addr:full":"Nr 217 M\u00f6nichkirchen Nieder\u00f6sterreich 2872",
    "addr:postcode":"2872",
    "addr:street":"Nr 217 Moenichkirchen",
    "iso:country":"AT",
    "sg:address":"Nr 217",
    "sg:city":"M\u00f6nichkirchen",
    "sg:orig_category":"Tankstellen",
    "sg:phone":"+43 2649 247",
    "sg:postcode":"2872",
    "sg:province":"Nieder\u00f6sterreich",
    "wof:name":"Pichlh\u00f6fer Johann",
    "wof:placetype":"venue"
},
  "geometry": {"coordinates":[166.9221496582,-0.5282999873],"type":"Point"}
}