{
  "type": "Feature",
  "properties": {
    "addr:full":"Am Regengei\u00dfl 1 Obernberg am Inn Ober\u00f6sterreich 4982",
    "addr:housenumber":"1",
    "addr:postcode":"4982",
    "addr:street":"Am Regengeissl",
    "iso:country":"AT",
    "sg:address":"Am Regengei\u00dfl 1",
    "sg:city":"Obernberg am Inn",
    "sg:classifiers":[
        {
            "category":"Transit Center",
            "subcategory":"Freight",
            "type":"Transportation"
        }
    ],
    "sg:phone":"+43 4377 5824240",
    "sg:postcode":"4982",
    "sg:province":"Ober\u00f6sterreich",
    "sg:tags":[
        "import",
        "gro\u00c3\u0178handel",
        "u",
        "tee",
        "/"
    ],
    "wof:name":"Scherbaum KG",
    "wof:placetype":"venue"
},
  "geometry": {"coordinates":[13.3354701996,48.3221435547],"type":"Point"}
}