{
  "type": "Feature",
  "properties": {
    "iso:country":"AT",
    "sg:address":"Annaberg 19a",
    "sg:city":"Grieskirchen",
    "sg:orig_category":"Personalbereitstellung",
    "sg:phone":"+43 4372 48684990",
    "sg:postcode":"4710",
    "sg:province":"Ober\u00f6sterreich",
    "wof:name":"Industriemontagen u konzessionierte Personal-Leasing GesmbH",
    "wof:placetype":"venue"
},
  "geometry": {"coordinates":[13.8439702988,48.2311248779],"type":"Point"}
}