{
  "type": "Feature",
  "properties": {
    "iso:country":"AT",
    "sg:address":"Flugh Wien Schwechat Obj 107",
    "sg:city":"Wien",
    "sg:orig_category":"Restaurants: Amerikanisch",
    "sg:phone":"+43 1 700733522",
    "sg:postcode":"1300",
    "sg:province":"Wien",
    "wof:name":"McDonald's Restaurant",
    "wof:placetype":"venue"
},
  "geometry": {"coordinates":[16.5561008453,48.1137504578],"type":"Point"}
}