{
  "type": "Feature",
  "properties": {
    "addr:full":"Schlo\u00dfberg 40 Maria Alm am Steinernen Meer Salzburg 5761",
    "addr:housenumber":"40",
    "addr:postcode":"5761",
    "addr:street":"Schlossberg",
    "iso:country":"AT",
    "sg:address":"Schlo\u00dfberg 40",
    "sg:city":"Maria Alm am Steinernen Meer",
    "sg:orig_category":"Maler, Anstreicher U Lackierer",
    "sg:phone":"+43 4365 847635",
    "sg:postcode":"5761",
    "sg:province":"Salzburg",
    "wof:name":"Malerei F\u00f6rl GesmbH",
    "wof:placetype":"venue"
},
  "geometry": {"coordinates":[12.8989639282,47.4027824402],"type":"Point"}
}