{
  "type": "Feature",
  "properties": {
    "addr:full":"Schulg 2 Rattersdorf-Liebing Burgenland 7443",
    "addr:housenumber":"2",
    "addr:postcode":"7443",
    "addr:street":"Schulg",
    "iso:country":"AT",
    "sg:address":"Schulg 2",
    "sg:city":"Rattersdorf-Liebing",
    "sg:orig_category":"Volksschulen",
    "sg:phone":"+43 2611 2692",
    "sg:postcode":"7443",
    "sg:province":"Burgenland",
    "wof:name":"Volksschule",
    "wof:placetype":"venue"
},
  "geometry": {"coordinates":[16.4990158081,47.409034729],"type":"Point"}
}