{
  "type": "Feature",
  "properties": {
    "iso:country":"AT",
    "sg:address":"Ernstbrunner Str 379",
    "sg:city":"Mistelbach",
    "sg:orig_category":"Betten",
    "sg:phone":"+43 4325 72201460",
    "sg:postcode":"2130",
    "sg:province":"Nieder\u00f6sterreich",
    "wof:name":"D\u00e4nisches Bettenlager HandelsgesmbH",
    "wof:placetype":"venue"
},
  "geometry": {"coordinates":[16.5624198914,48.5587806702],"type":"Point"}
}