{
  "type": "Feature",
  "properties": {
    "addr:full":"Lob\u00e4ckerstr 2/Parz 3806 Eisenstadt Burgenland 7000",
    "addr:housenumber":"2 / parz",
    "addr:postcode":"3806;7000",
    "addr:street":"Lobaeckerstr",
    "iso:country":"AT",
    "sg:address":"Lob\u00e4ckerstr 2/Parz 3806",
    "sg:city":"Eisenstadt",
    "sg:orig_category":"Beton- U Betonsteinwerke",
    "sg:phone":"+43 4326 82682250",
    "sg:postcode":"7000",
    "sg:province":"Burgenland",
    "wof:name":"Stainer Julius Dr Betonwerke GmbH",
    "wof:placetype":"venue"
},
  "geometry": {"coordinates":[16.5189552307,47.8455657959],"type":"Point"}
}