{
  "type": "Feature",
  "properties": {
    "iso:country":"AT",
    "sg:address":"Lindenbauerweg 16",
    "sg:city":"Linz",
    "sg:orig_category":"Physiotherapie",
    "sg:phone":"+43 4366 49455659",
    "sg:postcode":"4020",
    "sg:province":"Ober\u00f6sterreich",
    "wof:name":"Ringer Neumann Elisabeth",
    "wof:placetype":"venue"
},
  "geometry": {"coordinates":[14.2467002869,48.3022499084],"type":"Point"}
}