{
  "type": "Feature",
  "properties": {
    "addr:full":"Wolkersdorfer Str 24 Ulrichskirchen Nieder\u00f6sterreich 2122",
    "addr:housenumber":"24",
    "addr:postcode":"2122",
    "addr:street":"Wolkersdorfer Str",
    "iso:country":"AT",
    "sg:address":"Wolkersdorfer Str 24",
    "sg:city":"Ulrichskirchen",
    "sg:orig_category":"Psychologen",
    "sg:phone":"+43 2245 83058",
    "sg:postcode":"2122",
    "sg:province":"Nieder\u00f6sterreich",
    "wof:name":"Strobl Roland Mag",
    "wof:placetype":"venue"
},
  "geometry": {"coordinates":[16.4960002899,48.4004745483],"type":"Point"}
}