{
  "type": "Feature",
  "properties": {
    "iso:country":"AT",
    "sg:address":"Waldm\u00fcllerg 2-4",
    "sg:city":"Oberwart",
    "sg:orig_category":"Banken U Sparkassen",
    "sg:phone":"+43 4333 52328710",
    "sg:postcode":"7400",
    "sg:province":"Burgenland",
    "wof:name":"GE Capital Bank GmbH",
    "wof:placetype":"venue"
},
  "geometry": {"coordinates":[16.2131557465,47.2876167297],"type":"Point"}
}