{
  "type": "Feature",
  "properties": {
    "iso:country":"AT",
    "sg:address":"Lendpl 29",
    "sg:city":"Graz",
    "sg:orig_category":"Fotografen",
    "sg:phone":"+43 316 715833",
    "sg:postcode":"8020",
    "sg:province":"Steiermark",
    "wof:name":"Sabine's Fotostudio Lend",
    "wof:placetype":"venue"
},
  "geometry": {"coordinates":[15.4292707443,47.076675415],"type":"Point"}
}