{
  "type": "Feature",
  "properties": {
    "addr:full":"Marktpl 20 Mittersill Salzburg 5730",
    "addr:housenumber":"20",
    "addr:postcode":"5730",
    "addr:street":"Marktpl;Salzburg",
    "iso:country":"AT",
    "sg:address":"Marktpl 20",
    "sg:city":"Mittersill",
    "sg:orig_category":"Textilwaren / Einzelhandel",
    "sg:phone":"+43 6562 62560",
    "sg:postcode":"5730",
    "sg:province":"Salzburg",
    "wof:name":"H\u00f6lzl Moden KG",
    "wof:placetype":"venue"
},
  "geometry": {"coordinates":[12.482336998,47.2816467285],"type":"Point"}
}