{
  "type": "Feature",
  "properties": {
    "addr:full":"Neubaug 14 Mattersburg Burgenland 7210",
    "addr:housenumber":"14",
    "addr:postcode":"7210",
    "addr:street":"Neubaug",
    "iso:country":"AT",
    "sg:address":"Neubaug 14",
    "sg:city":"Mattersburg",
    "sg:orig_category":"Druckereien",
    "sg:phone":"+43 2626 62216",
    "sg:postcode":"7210",
    "sg:province":"Burgenland",
    "wof:name":"Wograndl Druck",
    "wof:placetype":"venue"
},
  "geometry": {"coordinates":[16.4006614685,47.7379341125],"type":"Point"}
}