{
  "type": "Feature",
  "properties": {
    "iso:country":"AT",
    "sg:address":"Bergernstr 1",
    "sg:city":"Wallern an der Trattnach",
    "sg:orig_category":"Tanzcafes",
    "sg:phone":"+43 4372 4943321",
    "sg:postcode":"4702",
    "sg:province":"Ober\u00f6sterreich",
    "wof:name":"Diana Tanzbar",
    "wof:placetype":"venue"
},
  "geometry": {"coordinates":[13.9452400208,48.2344284058],"type":"Point"}
}