{
  "type": "Feature",
  "properties": {
    "addr:full":"Bahnhofstr 2 Ferlach K\u00e4rnten 9170",
    "addr:housenumber":"2",
    "addr:postcode":"9170",
    "addr:street":"Bahnhofstr;Kaernten",
    "iso:country":"AT",
    "sg:address":"Bahnhofstr 2",
    "sg:city":"Ferlach",
    "sg:orig_category":"Lebensmittel / Einzelhandel",
    "sg:phone":"+43 4342 2732620",
    "sg:postcode":"9170",
    "sg:province":"K\u00e4rnten",
    "wof:name":"SPAR \u00d6sterreichische Warenhandels-AG",
    "wof:placetype":"venue"
},
  "geometry": {"coordinates":[14.3011245728,46.5234069824],"type":"Point"}
}