{
  "type": "Feature",
  "properties": {
    "addr:full":"Markt 8 St. Veit im Pongau Salzburg 5621",
    "addr:housenumber":"8",
    "addr:postcode":"5621",
    "addr:street":"Markt;Salzburg",
    "iso:country":"AT",
    "sg:address":"Markt 8",
    "sg:city":"St. Veit im Pongau",
    "sg:orig_category":"Banken U Sparkassen",
    "sg:phone":"+43 4364 1561140",
    "sg:postcode":"5621",
    "sg:province":"Salzburg",
    "wof:name":"Bankomat d Raiffeisenbank St. Veit-Schwarzach-Goldegg regGenmbH",
    "wof:placetype":"venue"
},
  "geometry": {"coordinates":[13.1538887024,47.3288497925],"type":"Point"}
}