{
  "type": "Feature",
  "properties": {
    "addr:full":"Torpl 2a Feldbach Steiermark 8330",
    "addr:housenumber":"2a",
    "addr:postcode":"8330",
    "addr:street":"Torpl",
    "iso:country":"AT",
    "sg:address":"Torpl 2a",
    "sg:city":"Feldbach",
    "sg:orig_category":"Offsetdruckereien",
    "sg:phone":"+43 3152 23180",
    "sg:postcode":"8330",
    "sg:province":"Steiermark",
    "wof:name":"Scharmer Druckerei GesmbH & Co KG",
    "wof:placetype":"venue"
},
  "geometry": {"coordinates":[15.8873939514,46.9525184631],"type":"Point"}
}