{
  "type": "Feature",
  "properties": {
    "addr:full":"Amerlingstr 1/10 Wien Wien 1060",
    "addr:housenumber":"1 / 10",
    "addr:postcode":"1060",
    "addr:street":"Amerlingstr",
    "iso:country":"AT",
    "sg:address":"Amerlingstr 1/10",
    "sg:city":"Wien",
    "sg:classifiers":[
        {
            "category":"Internet Cafe",
            "subcategory":"None",
            "type":"Food & Drink"
        }
    ],
    "sg:phone":"+43 1 5854466",
    "sg:postcode":"1060",
    "sg:province":"Wien",
    "wof:name":"Diller & Partner Agentur f\u00fcr Neue Medien WerbegesmbH",
    "wof:placetype":"venue"
},
  "geometry": {"coordinates":[16.3514022827,48.1964035034],"type":"Point"}
}