{
  "type": "Feature",
  "properties": {
    "addr:full":"Ungarg 46 Wien Wien 1030",
    "addr:housenumber":"46",
    "addr:postcode":"1030",
    "addr:street":"Ungarg",
    "iso:country":"AT",
    "sg:address":"Ungarg 46",
    "sg:city":"Wien",
    "sg:orig_category":"Botendienste",
    "sg:phone":"+43 1 521170",
    "sg:postcode":"1030",
    "sg:province":"Wien",
    "sg:website":"www.veloce.at",
    "wof:name":"Botendienst Veloce",
    "wof:placetype":"venue"
},
  "geometry": {"coordinates":[16.3872261047,48.1995620728],"type":"Point"}
}