{
  "type": "Feature",
  "properties": {
    "addr:full":"Industriestr 3 Maria Lanzendorf Nieder\u00f6sterreich 2326",
    "addr:housenumber":"3",
    "addr:postcode":"2326",
    "addr:street":"Industriestr",
    "iso:country":"AT",
    "sg:address":"Industriestr 3",
    "sg:city":"Maria Lanzendorf",
    "sg:orig_category":"Speditionen",
    "sg:phone":"+43 2235 433130",
    "sg:postcode":"2326",
    "sg:province":"Nieder\u00f6sterreich",
    "wof:name":"ONTIME Logistics Speditions GmbH",
    "wof:placetype":"venue"
},
  "geometry": {"coordinates":[16.4172954559,48.1067962646],"type":"Point"}
}