{
  "type": "Feature",
  "properties": {
    "addr:full":"Rauscherstr 6/54 Wien Wien 1200",
    "addr:housenumber":"6 / 54",
    "addr:postcode":"1200",
    "addr:street":"Rauscherstr",
    "iso:country":"AT",
    "sg:address":"Rauscherstr 6/54",
    "sg:city":"Wien",
    "sg:orig_category":"Architekten",
    "sg:phone":"+43 1 35088060",
    "sg:postcode":"1200",
    "sg:province":"Wien",
    "wof:name":"Huber Christoph Dipl-Ing",
    "wof:placetype":"venue"
},
  "geometry": {"coordinates":[16.3758296967,48.2303085327],"type":"Point"}
}