{
  "type": "Feature",
  "properties": {
    "addr:full":"Itzlinger Hauptstrasse 55 Salzburg Salzburg 5020",
    "addr:housenumber":"55",
    "addr:postcode":"5020",
    "addr:street":"Itzlinger Hauptstrasse;Salzburg",
    "iso:country":"AT",
    "sg:address":"Itzlinger Hauptstrasse 55",
    "sg:city":"Salzburg",
    "sg:orig_category":"LocksmithS Shops",
    "sg:phone":"+43 662 450282",
    "sg:postcode":"5020",
    "sg:province":"Salzburg",
    "wof:name":"Christian St\u00f6gbuchner",
    "wof:placetype":"venue"
},
  "geometry": {"coordinates":[13.0416002274,47.8239898682],"type":"Point"}
}