{
  "type": "Feature",
  "properties": {
    "addr:full":"L\u00fc\u00dfstr 2 Trumau Nieder\u00f6sterreich 2521",
    "addr:housenumber":"2",
    "addr:postcode":"2521",
    "addr:street":"Luessstr",
    "iso:country":"AT",
    "sg:address":"L\u00fc\u00dfstr 2",
    "sg:city":"Trumau",
    "sg:orig_category":"Autoreparatur",
    "sg:phone":"+43 2253 6666",
    "sg:postcode":"2521",
    "sg:province":"Nieder\u00f6sterreich",
    "wof:name":"Hammerschmid GesmbH",
    "wof:placetype":"venue"
},
  "geometry": {"coordinates":[16.3423233032,47.9932975769],"type":"Point"}
}