{
  "type": "Feature",
  "properties": {
    "iso:country":"AT",
    "sg:address":"Hoheneggstr 2",
    "sg:city":"Radstadt",
    "sg:orig_category":"Getriebe",
    "sg:phone":"+43 4364 5220230",
    "sg:postcode":"5550",
    "sg:province":"Salzburg",
    "wof:name":"Benzler Antriebstechnik GesmbH",
    "wof:placetype":"venue"
},
  "geometry": {"coordinates":[13.4624481201,47.3848419189],"type":"Point"}
}