{
  "type": "Feature",
  "properties": {
    "addr:full":"Kirchberg 48 St. Pantaleon Ober\u00f6sterreich 5120",
    "addr:housenumber":"48",
    "addr:postcode":"5120",
    "addr:street":"Kirchberg",
    "iso:country":"AT",
    "sg:address":"Kirchberg 48",
    "sg:city":"St. Pantaleon",
    "sg:classifiers":[
        {
            "category":"Shopping",
            "subcategory":"Clothing, Apparel, & Fashions",
            "type":"Retail Goods"
        }
    ],
    "sg:phone":"+43 4362 7772880",
    "sg:postcode":"5120",
    "sg:province":"Ober\u00f6sterreich",
    "sg:tags":[
        "t-shirt"
    ],
    "wof:name":"Kona HandelsgesmbH",
    "wof:placetype":"venue"
},
  "geometry": {"coordinates":[12.8832397461,48.045375824],"type":"Point"}
}