{
  "type": "Feature",
  "properties": {
    "addr:full":"Leonhardstr 100b Graz Steiermark 8010",
    "addr:housenumber":"100b",
    "addr:postcode":"8010",
    "iso:country":"AT",
    "sg:address":"Leonhardstr 100b",
    "sg:city":"Graz",
    "sg:orig_category":"Fotografen",
    "sg:phone":"+43 676 3711810",
    "sg:postcode":"8010",
    "sg:province":"Steiermark",
    "wof:name":"Angerbauer Christian",
    "wof:placetype":"venue"
},
  "geometry": {"coordinates":[15.4609613419,47.076084137],"type":"Point"}
}