{
  "type": "Feature",
  "properties": {
    "addr:full":"Diesseits 1 St. Martin im Innkreis Ober\u00f6sterreich 4973",
    "addr:housenumber":"1",
    "addr:postcode":"4973",
    "addr:street":"Diesseits",
    "iso:country":"AT",
    "sg:address":"Diesseits 1",
    "sg:city":"St. Martin im Innkreis",
    "sg:orig_category":"Brauereien",
    "sg:phone":"+43 4377 518202",
    "sg:postcode":"4973",
    "sg:province":"Ober\u00f6sterreich",
    "wof:name":"Arco-Zinneberg'sche Gr\u00e4fliche Dom\u00e4nenverwaltung",
    "wof:placetype":"venue"
},
  "geometry": {"coordinates":[13.4381246567,48.2940559387],"type":"Point"}
}