{
  "type": "Feature",
  "properties": {
    "addr:full":"Waagg 10 Wien Wien 1040",
    "addr:housenumber":"10",
    "addr:postcode":"1040",
    "addr:street":"Waagg",
    "iso:country":"AT",
    "sg:address":"Waagg 10",
    "sg:city":"Wien",
    "sg:orig_category":"Botschaften",
    "sg:phone":"+43 1 5874675",
    "sg:postcode":"1040",
    "sg:province":"Wien",
    "wof:name":"Botschaft der Republik Bolivien",
    "wof:placetype":"venue"
},
  "geometry": {"coordinates":[16.36469841,48.1953544617],"type":"Point"}
}