{
  "type": "Feature",
  "properties": {
    "iso:country":"AT",
    "sg:address":"Heiligenst\u00e4dter Str 34",
    "sg:city":"Wien",
    "sg:orig_category":"Waren Aller Art",
    "sg:phone":"+43 699 13093638",
    "sg:postcode":"1190",
    "sg:province":"Wien",
    "wof:name":"Pyramiden Import/Export Hamid & Refai OEG",
    "wof:placetype":"venue"
},
  "geometry": {"coordinates":[16.3585796356,48.2381706238],"type":"Point"}
}