{
  "type": "Feature",
  "properties": {
    "addr:full":"Unterer Stadtplatz 21 Kufstein Tirol 6330",
    "addr:housenumber":"21",
    "addr:postcode":"6330",
    "addr:street":"Unterer Stadtplatz;Tirol",
    "iso:country":"AT",
    "sg:address":"Unterer Stadtplatz 21",
    "sg:city":"Kufstein",
    "sg:classifiers":[
        {
            "category":"Banks & Credit Unions",
            "subcategory":"Bank",
            "type":"Services"
        }
    ],
    "sg:phone":"+43 4353 7269220",
    "sg:postcode":"6330",
    "sg:province":"Tirol",
    "sg:tags":[
        "banking",
        "institution"
    ],
    "wof:name":"VOLKSBANK KUFSTEIN REG.GEN.MBH",
    "wof:placetype":"venue"
},
  "geometry": {"coordinates":[12.169588089,47.5831222534],"type":"Point"}
}