{
  "type": "Feature",
  "properties": {
    "addr:full":"Danhauserg 6/4 Wien Wien 1040",
    "addr:housenumber":"6 / 4",
    "addr:postcode":"1040",
    "addr:street":"Danhauserg",
    "iso:country":"AT",
    "sg:address":"Danhauserg 6/4",
    "sg:city":"Wien",
    "sg:orig_category":"Psychologen",
    "sg:phone":"+43 4315 041546",
    "sg:postcode":"1040",
    "sg:province":"Wien",
    "wof:name":"Chaloupka Christine Dr",
    "wof:placetype":"venue"
},
  "geometry": {"coordinates":[16.3692550659,48.1920547485],"type":"Point"}
}