{
  "type": "Feature",
  "properties": {
    "addr:full":"Markt 26 Hohenberg Nieder\u00f6sterreich 3192",
    "addr:housenumber":"26",
    "addr:postcode":"3192",
    "addr:street":"Markt",
    "iso:country":"AT",
    "sg:address":"Markt 26",
    "sg:city":"Hohenberg",
    "sg:orig_category":"Banken U Sparkassen",
    "sg:phone":"+43 4350 10073046",
    "sg:postcode":"3192",
    "sg:province":"Nieder\u00f6sterreich",
    "wof:name":"Sparkasse Nieder\u00f6sterreich Mitte West AG",
    "wof:placetype":"venue"
},
  "geometry": {"coordinates":[15.6195106506,47.9100456238],"type":"Point"}
}