{
  "type": "Feature",
  "properties": {
    "iso:country":"AT",
    "sg:address":"Nr 43",
    "sg:city":"Raabs an der Thaya",
    "sg:orig_category":"Feuerwehren",
    "sg:phone":"+43 2846 20723",
    "sg:postcode":"3820",
    "sg:province":"Nieder\u00f6sterreich",
    "wof:name":"Freiwillige Feuerwehr Speisendorf",
    "wof:placetype":"venue"
},
  "geometry": {"coordinates":[15.4923467636,48.8486366272],"type":"Point"}
}