{
  "type": "Feature",
  "properties": {
    "addr:full":"Massingstr 25 Krieglach Steiermark 8670",
    "addr:housenumber":"25",
    "addr:postcode":"8670",
    "addr:street":"Massingstr",
    "iso:country":"AT",
    "sg:address":"Massingstr 25",
    "sg:city":"Krieglach",
    "sg:orig_category":"Erdarbeiten",
    "sg:phone":"+43 3855 45507",
    "sg:postcode":"8670",
    "sg:province":"Steiermark",
    "wof:name":"Enickl Bernhard KEG",
    "wof:placetype":"venue"
},
  "geometry": {"coordinates":[15.5495109558,47.564743042],"type":"Point"}
}