{
  "type": "Feature",
  "properties": {
    "iso:country":"AT",
    "sg:address":"Pertholzer Str 7",
    "sg:city":"Heidenreichstein",
    "sg:orig_category":"Lebensmittel / Erzeugung U Gro\u00c3\u0178handel",
    "sg:phone":"+43 2862 52325",
    "sg:postcode":"3860",
    "sg:province":"Nieder\u00f6sterreich",
    "wof:name":"NOWAKORN Heidenreichstein Alternative Kornverarbeitung regGenmbH",
    "wof:placetype":"venue"
},
  "geometry": {"coordinates":[15.1191997528,48.8620071411],"type":"Point"}
}