{
  "type": "Feature",
  "properties": {
    "addr:full":"Mariahilfer Str 117 Wien Wien 1060",
    "addr:housenumber":"117",
    "addr:postcode":"1060",
    "iso:country":"AT",
    "sg:address":"Mariahilfer Str 117",
    "sg:city":"Wien",
    "sg:classifiers":[
        {
            "category":"Professional",
            "subcategory":"Management & Consulting",
            "type":"Services"
        }
    ],
    "sg:phone":"+43 1 59775100",
    "sg:postcode":"1060",
    "sg:province":"Wien",
    "wof:name":"G und I Generalunternehmen f Projektierung Ausf\u00fchrung und Innenausbau GesmbH",
    "wof:placetype":"venue"
},
  "geometry": {"coordinates":[16.3426094055,48.1963043213],"type":"Point"}
}