{
  "type": "Feature",
  "properties": {
    "addr:full":"Ausstellungsstr 6 Hollabrunn Nieder\u00f6sterreich 2020",
    "addr:housenumber":"6",
    "addr:postcode":"2020",
    "addr:street":"Ausstellungsstr",
    "iso:country":"AT",
    "sg:address":"Ausstellungsstr 6",
    "sg:city":"Hollabrunn",
    "sg:orig_category":"Drehereien",
    "sg:phone":"+43 2952 302605140",
    "sg:postcode":"2020",
    "sg:province":"Nieder\u00f6sterreich",
    "wof:name":"Benesch Peter",
    "wof:placetype":"venue"
},
  "geometry": {"coordinates":[16.0726299286,48.5582275391],"type":"Point"}
}