{
  "type": "Feature",
  "properties": {
    "addr:full":"Hirschgraben 4 Feldkirch Vorarlberg 6800",
    "addr:housenumber":"4",
    "addr:postcode":"6800",
    "addr:street":"Hirschgraben",
    "iso:country":"AT",
    "sg:address":"Hirschgraben 4",
    "sg:city":"Feldkirch",
    "sg:orig_category":"Friseure U Frisiersalons",
    "sg:phone":"+43 4355 2237200",
    "sg:postcode":"6800",
    "sg:province":"Vorarlberg",
    "wof:name":"x-tream for young hair - Sandra Schwarz",
    "wof:placetype":"venue"
},
  "geometry": {"coordinates":[9.5965690613,47.2386703491],"type":"Point"}
}