{
  "type": "Feature",
  "properties": {
    "addr:full":"Brunnleiten 17  Klosterneuburg Nieder\u00f6sterreich 3400",
    "addr:housenumber":"17",
    "addr:postcode":"3400",
    "addr:street":"Brunnleiten;Niederoesterreich",
    "iso:country":"AT",
    "sg:address":"Brunnleiten 17 ",
    "sg:city":"Klosterneuburg",
    "sg:classifiers":[
        {
            "category":"Farming",
            "subcategory":"Livestock Farm",
            "type":"Manufacturing & Wholesale Goods"
        }
    ],
    "sg:phone":"+43 4322 4332698",
    "sg:postcode":"3400",
    "sg:province":"Nieder\u00f6sterreich",
    "sg:tags":[
        "agriculture"
    ],
    "wof:name":"VITRO PLANT PFLANZENBIOTECHNOLOGIE GMBH",
    "wof:placetype":"venue"
},
  "geometry": {"coordinates":[16.3087596893,48.3232307434],"type":"Point"}
}