{
  "type": "Feature",
  "properties": {
    "iso:country":"AT",
    "sg:address":"Thaliastr 24",
    "sg:city":"Wien",
    "sg:orig_category":"Fotoapparate U -Artikel / Einzelhandel",
    "sg:phone":"+43 4314 057169",
    "sg:postcode":"1160",
    "sg:province":"Wien",
    "wof:name":"Niedermeyer GmbH",
    "wof:placetype":"venue"
},
  "geometry": {"coordinates":[16.3351955414,48.2092323303],"type":"Point"}
}