{
  "type": "Feature",
  "properties": {
    "addr:full":"Bozner Str 4 Wattens Tirol 6112",
    "addr:housenumber":"4",
    "addr:postcode":"6112",
    "addr:street":"Bozner Str;Tirol",
    "iso:country":"AT",
    "sg:address":"Bozner Str 4",
    "sg:city":"Wattens",
    "sg:orig_category":"\u00c3\u201erzte / F Allgemeinmedizin",
    "sg:phone":"+43 5224 52767",
    "sg:postcode":"6112",
    "sg:province":"Tirol",
    "wof:name":"Hammer Siegfried Dr",
    "wof:placetype":"venue"
},
  "geometry": {"coordinates":[11.5835151672,47.2936820984],"type":"Point"}
}