{
  "type": "Feature",
  "properties": {
    "addr:full":"Eduard-Heinrich-Str 4 Salzburg Salzburg 5020",
    "addr:housenumber":"4",
    "addr:postcode":"5020",
    "addr:street":"Eduard-Heinrich-Str;Salzburg",
    "iso:country":"AT",
    "sg:address":"Eduard-Heinrich-Str 4",
    "sg:city":"Salzburg",
    "sg:orig_category":"Psychotherapie",
    "sg:phone":"+43 662 626204",
    "sg:postcode":"5020",
    "sg:province":"Salzburg",
    "wof:name":"St\u00f6ller Erich Dr",
    "wof:placetype":"venue"
},
  "geometry": {"coordinates":[13.0694246292,47.7805137634],"type":"Point"}
}