{
  "type": "Feature",
  "properties": {
    "addr:full":"Feldbauerstr 3 Pinsdorf Ober\u00f6sterreich 4812",
    "addr:housenumber":"3",
    "addr:postcode":"4812",
    "addr:street":"Feldbauerstr",
    "iso:country":"AT",
    "sg:address":"Feldbauerstr 3",
    "sg:city":"Pinsdorf",
    "sg:orig_category":"Arbeitsschutz U Arbeitsschutzartikel",
    "sg:phone":"+43 4376 1247600",
    "sg:postcode":"4812",
    "sg:province":"Ober\u00f6sterreich",
    "wof:name":"INNOTECH Arbeitsschutz GmbH",
    "wof:placetype":"venue"
},
  "geometry": {"coordinates":[13.7712898254,47.9298934937],"type":"Point"}
}