{
  "type": "Feature",
  "properties": {
    "addr:full":"Garteng 3 Neumarkt in Steiermark Steiermark 8820",
    "addr:housenumber":"3",
    "addr:postcode":"8820",
    "addr:street":"Garteng",
    "iso:country":"AT",
    "sg:address":"Garteng 3",
    "sg:city":"Neumarkt in Steiermark",
    "sg:orig_category":"\u00c3\u201erzte / F Allgemeinmedizin",
    "sg:phone":"+43 4335 8438500",
    "sg:postcode":"8820",
    "sg:province":"Steiermark",
    "wof:name":"Bertha Martin Dr",
    "wof:placetype":"venue"
},
  "geometry": {"coordinates":[14.4266662598,47.0741081238],"type":"Point"}
}