{
  "type": "Feature",
  "properties": {
    "addr:full":"Linzer Str 32/Stg 1 Wien Wien 1140",
    "addr:housenumber":"32 / stg 1",
    "addr:postcode":"1140",
    "addr:street":"Linzer Str",
    "iso:country":"AT",
    "sg:address":"Linzer Str 32/Stg 1",
    "sg:city":"Wien",
    "sg:orig_category":"Satellitenempfangsanlagen",
    "sg:phone":"+43 4318 659980",
    "sg:postcode":"1140",
    "sg:province":"Wien",
    "wof:name":"Tele-Electronic Handels- u VertriebsgmbH",
    "wof:placetype":"venue"
},
  "geometry": {"coordinates":[16.2696990967,48.1994247437],"type":"Point"}
}