{
  "type": "Feature",
  "properties": {
    "iso:country":"AT",
    "sg:address":"Sch\u00f6rgelhofsdlg 33",
    "sg:city":"St. Peter-Freienstein",
    "sg:orig_category":"Glasereien",
    "sg:phone":"+43 4338 4226342",
    "sg:postcode":"8792",
    "sg:province":"Steiermark",
    "wof:name":"Glaserei Gruber",
    "wof:placetype":"venue"
},
  "geometry": {"coordinates":[15.0431137085,47.3890762329],"type":"Point"}
}