{
  "type": "Feature",
  "properties": {
    "iso:country":"AT",
    "sg:address":"Laahener Str 75",
    "sg:city":"Wels",
    "sg:orig_category":"Transportunternehmen",
    "sg:phone":"+43 7242 63633",
    "sg:postcode":"4600",
    "sg:province":"Ober\u00f6sterreich",
    "wof:name":"Egger Franz",
    "wof:placetype":"venue"
},
  "geometry": {"coordinates":[14.0081748962,48.1706924438],"type":"Point"}
}