{
  "type": "Feature",
  "properties": {
    "addr:full":"Nr 77 Seibersdorf Nieder\u00f6sterreich 2444",
    "addr:postcode":"2444",
    "addr:street":"Nr;Seibersdorf",
    "iso:country":"AT",
    "sg:address":"Nr 77",
    "sg:city":"Seibersdorf",
    "sg:orig_category":"Polizei U Gendarmerie",
    "sg:phone":"+43 4359 1333312",
    "sg:postcode":"2444",
    "sg:province":"Nieder\u00f6sterreich",
    "wof:name":"Gendarmerie",
    "wof:placetype":"venue"
},
  "geometry": {"coordinates":[16.422700882,47.9040603638],"type":"Point"}
}