{
  "type": "Feature",
  "properties": {
    "addr:full":"Wiesenweg 135 Golling an der Salzach Salzburg 5440",
    "addr:housenumber":"135",
    "addr:postcode":"5440",
    "addr:street":"Wiesenweg",
    "iso:country":"AT",
    "sg:address":"Wiesenweg 135",
    "sg:city":"Golling an der Salzach",
    "sg:orig_category":"Forstverwaltungen",
    "sg:phone":"+43 4366 49064050",
    "sg:postcode":"5440",
    "sg:province":"Salzburg",
    "wof:name":"\u00f6sterreichische Bundesforste AG - Forstrevier Hallein",
    "wof:placetype":"venue"
},
  "geometry": {"coordinates":[13.1565389633,47.6025009155],"type":"Point"}
}