{
  "type": "Feature",
  "properties": {
    "iso:country":"AT",
    "sg:address":"Nr 51",
    "sg:city":"Schweiggers",
    "sg:orig_category":"Volksschulen",
    "sg:phone":"+43 4328 297443",
    "sg:postcode":"3931",
    "sg:province":"Nieder\u00f6sterreich",
    "wof:name":"Volksschule",
    "wof:placetype":"venue"
},
  "geometry": {"coordinates":[15.0794849396,48.6186676025],"type":"Point"}
}