{
  "type": "Feature",
  "properties": {
    "addr:full":"Nr 51 Schweiggers Nieder\u00f6sterreich 3931",
    "addr:postcode":"3931",
    "addr:street":"Nr;Niederoesterreich",
    "iso:country":"AT",
    "sg:address":"Nr 51",
    "sg:city":"Schweiggers",
    "sg:orig_category":"Volksschulen",
    "sg:phone":"+43 4328 297443",
    "sg:postcode":"3931",
    "sg:province":"Nieder\u00f6sterreich",
    "wof:name":"Volksschule",
    "wof:placetype":"venue"
},
  "geometry": {"coordinates":[15.0794849396,48.6186676025],"type":"Point"}
}