{
  "type": "Feature",
  "properties": {
    "addr:full":"\u00f6lrainstr 24 Bregenz Vorarlberg 6900",
    "addr:housenumber":"24",
    "addr:postcode":"6900",
    "addr:street":"Oelrainstr",
    "iso:country":"AT",
    "sg:address":"\u00f6lrainstr 24",
    "sg:city":"Bregenz",
    "sg:orig_category":"Medizintechnik",
    "sg:phone":"+43 5574 53653",
    "sg:postcode":"6900",
    "sg:province":"Vorarlberg",
    "wof:name":"Optimist HandelsgmbH",
    "wof:placetype":"venue"
},
  "geometry": {"coordinates":[9.7366876602,47.497959137],"type":"Point"}
}