{
  "type": "Feature",
  "properties": {
    "iso:country":"AT",
    "sg:address":"Hauptstrasse 74",
    "sg:city":"Kronstorf",
    "sg:classifiers":[
        {
            "category":"Wholesale",
            "subcategory":"Construction Materials",
            "type":"Manufacturing & Wholesale Goods"
        }
    ],
    "sg:phone":"+43 7225 8248",
    "sg:postcode":"4484",
    "sg:province":"Ober\u00f6sterreich",
    "sg:tags":[
        "bulk",
        "unit",
        "agglomeration"
    ],
    "sg:website":"theiss-engineering.at",
    "wof:name":"Theiss Engineering TE",
    "wof:placetype":"venue"
},
  "geometry": {"coordinates":[14.4640474319,48.138999939],"type":"Point"}
}