{
  "type": "Feature",
  "properties": {
    "iso:country":"AT",
    "sg:address":"Nr 209",
    "sg:city":"Yspertal",
    "sg:orig_category":"Elektroinstallationsunternehmen",
    "sg:phone":"+43 7415 6296",
    "sg:postcode":"3683",
    "sg:province":"Nieder\u00f6sterreich",
    "wof:name":"Elektro Rameder",
    "wof:placetype":"venue"
},
  "geometry": {"coordinates":[15.065489769,48.282119751],"type":"Point"}
}