{
  "type": "Feature",
  "properties": {
    "addr:full":"Brausewetterg. 8 Wien Wien 1220",
    "addr:housenumber":"8",
    "addr:postcode":"1220",
    "addr:street":"Brausewetterg.",
    "iso:country":"AT",
    "sg:address":"Brausewetterg. 8",
    "sg:city":"Wien",
    "sg:classifiers":[
        {
            "category":"Sports & Exercise",
            "subcategory":"Playing Field",
            "type":"Entertainment"
        }
    ],
    "sg:phone":"+43 4312 8343740",
    "sg:postcode":"1220",
    "sg:province":"Wien",
    "sg:tags":[
        "game"
    ],
    "wof:name":"LAGERHOLM SOLARIUM GES.MBH",
    "wof:placetype":"venue"
},
  "geometry": {"coordinates":[16.4513607025,48.2220497131],"type":"Point"}
}