{
  "type": "Feature",
  "properties": {
    "addr:full":"Wolfsh\u00fctte 29 Ottnang am Hausruck Ober\u00f6sterreich 4901",
    "addr:housenumber":"29",
    "addr:postcode":"4901",
    "addr:street":"Wolfshuette",
    "iso:country":"AT",
    "sg:address":"Wolfsh\u00fctte 29",
    "sg:city":"Ottnang am Hausruck",
    "sg:orig_category":"Werbegestalter",
    "sg:phone":"+43 76766599",
    "sg:postcode":"4901",
    "sg:province":"Ober\u00f6sterreich",
    "wof:name":"Krautgasser Erwin",
    "wof:placetype":"venue"
},
  "geometry": {"coordinates":[13.6660804749,48.0968818665],"type":"Point"}
}