{
  "type": "Feature",
  "properties": {
    "addr:full":"Stampfle 135a Landeck Tirol 6500",
    "addr:housenumber":"135a",
    "addr:postcode":"6500",
    "addr:street":"Landeck Tirol",
    "iso:country":"AT",
    "sg:address":"Stampfle 135a",
    "sg:city":"Landeck",
    "sg:orig_category":"Steuerberatung",
    "sg:phone":"+43 5442 68306",
    "sg:postcode":"6500",
    "sg:province":"Tirol",
    "wof:name":"OL Steuerberatungsgesellschaft mbH",
    "wof:placetype":"venue"
},
  "geometry": {"coordinates":[10.5455236435,47.1422042847],"type":"Point"}
}