{
  "type": "Feature",
  "properties": {
    "iso:country":"AT",
    "sg:address":"Nr 4",
    "sg:city":"Pichl",
    "sg:orig_category":"Juweliere, Gold- U Silberschmiede",
    "sg:phone":"+43 7247 6633",
    "sg:postcode":"4632",
    "sg:province":"Ober\u00f6sterreich",
    "wof:name":"Keuschnigg Andreas",
    "wof:placetype":"venue"
},
  "geometry": {"coordinates":[13.8999576569,48.1844367981],"type":"Point"}
}