{
  "type": "Feature",
  "properties": {
    "addr:full":"Hieflauer Str 82 Eisenerz Steiermark 8790",
    "addr:postcode":"8790",
    "addr:street":"Str 82",
    "iso:country":"AT",
    "sg:address":"Hieflauer Str 82",
    "sg:city":"Eisenerz",
    "sg:orig_category":"Autohandel",
    "sg:phone":"+43 4338 484548",
    "sg:postcode":"8790",
    "sg:province":"Steiermark",
    "wof:name":"Fixl Autohaus GmbH",
    "wof:placetype":"venue"
},
  "geometry": {"coordinates":[14.8693971634,47.5574836731],"type":"Point"}
}