{
  "type": "Feature",
  "properties": {
    "addr:full":"M\u00fchlgraben 43A Erl Tirol 6343",
    "addr:housenumber":"43a",
    "addr:postcode":"6343",
    "addr:street":"Muehlgraben;Tirol",
    "iso:country":"AT",
    "sg:address":"M\u00fchlgraben 43A",
    "sg:city":"Erl",
    "sg:orig_category":"Druckereimaschinen U -Bedarf",
    "sg:phone":"+43 4353 73760800",
    "sg:postcode":"6343",
    "sg:province":"Tirol",
    "wof:name":"Dryer Systems Trocknerbau GmbH",
    "wof:placetype":"venue"
},
  "geometry": {"coordinates":[12.1806850433,47.6813354492],"type":"Point"}
}