{
  "type": "Feature",
  "properties": {
    "addr:full":"Lederwinkel 16 Salla Steiermark 8592",
    "addr:housenumber":"16",
    "addr:postcode":"8592",
    "addr:street":"Lederwinkel",
    "iso:country":"AT",
    "sg:address":"Lederwinkel 16",
    "sg:city":"Salla",
    "sg:orig_category":"Fischzucht",
    "sg:phone":"+43 4366 45640066",
    "sg:postcode":"8592",
    "sg:province":"Steiermark",
    "wof:name":"Almbuffet Forellenferdl",
    "wof:placetype":"venue"
},
  "geometry": {"coordinates":[14.9636573792,47.1064071655],"type":"Point"}
}