{
  "type": "Feature",
  "properties": {
    "iso:country":"AT",
    "sg:address":"W Hohenheim-Str 19",
    "sg:city":"Villach",
    "sg:classifiers":[
        {
            "category":"Military Area",
            "subcategory":"Army Base",
            "type":"Public Place"
        }
    ],
    "sg:phone":"+43 4242 21217",
    "sg:postcode":"9500",
    "sg:province":"K\u00e4rnten",
    "sg:tags":[
        "shop"
    ],
    "wof:name":"US Military Shop",
    "wof:placetype":"venue"
},
  "geometry": {"coordinates":[13.8451948166,46.6059684753],"type":"Point"}
}