{
  "type": "Feature",
  "properties": {
    "iso:country":"AT",
    "sg:address":"Industriegebiet Leobendorf",
    "sg:city":"Korneuburg",
    "sg:classifiers":[
        {
            "category":"Home & Garden",
            "subcategory":"Hardware",
            "type":"Retail Goods"
        }
    ],
    "sg:phone":"+43 2262 663810",
    "sg:postcode":"2100",
    "sg:province":"Nieder\u00f6sterreich",
    "sg:tags":[
        "agricultural",
        "implement"
    ],
    "sg:website":"hammerschmied.at",
    "wof:name":"Hammerschmied und S\u00f6hne Ges.m.b.H.",
    "wof:placetype":"venue"
},
  "geometry": {"coordinates":[16.3329143524,48.3437843323],"type":"Point"}
}