{
  "type": "Feature",
  "properties": {
    "addr:full":"Robinigstr 19 Salzburg Salzburg 5020",
    "addr:housenumber":"19",
    "addr:postcode":"5020",
    "addr:street":"Robinigstr;Salzburg",
    "iso:country":"AT",
    "sg:address":"Robinigstr 19",
    "sg:city":"Salzburg",
    "sg:orig_category":"Holdinggesellschaften",
    "sg:phone":"+43 4366 28741230",
    "sg:postcode":"5020",
    "sg:province":"Salzburg",
    "sg:website":"salzburger-verpackung.at",
    "wof:name":"Gr\u00fcssing Josef & Co KG",
    "wof:placetype":"venue"
},
  "geometry": {"coordinates":[13.0599431992,47.812046051],"type":"Point"}
}