{
  "type": "Feature",
  "properties": {
    "addr:full":"Bundesstr 185 Warth Nieder\u00f6sterreich 2831",
    "addr:housenumber":"185",
    "addr:postcode":"2831",
    "addr:street":"Warth",
    "iso:country":"AT",
    "sg:address":"Bundesstr 185",
    "sg:city":"Warth",
    "sg:orig_category":"Spenglereien",
    "sg:phone":"+43 2629 25030",
    "sg:postcode":"2831",
    "sg:province":"Nieder\u00f6sterreich",
    "wof:name":"Kager Anton",
    "wof:placetype":"venue"
},
  "geometry": {"coordinates":[16.1287155151,47.6600112915],"type":"Point"}
}