{
  "type": "Feature",
  "properties": {
    "iso:country":"AT",
    "sg:address":"Hauptstr 24a",
    "sg:city":"Sch\u00f6rfling am Attersee",
    "sg:orig_category":"Fenster",
    "sg:phone":"+43 4376 6229377",
    "sg:postcode":"4861",
    "sg:province":"Ober\u00f6sterreich",
    "wof:name":"Fensterstudio Salzkammergut",
    "wof:placetype":"venue"
},
  "geometry": {"coordinates":[13.59471035,47.9467163086],"type":"Point"}
}