{
  "type": "Feature",
  "properties": {
    "addr:full":"Fischachstr 7a Bergheim Salzburg 5101",
    "addr:housenumber":"7a",
    "addr:postcode":"5101",
    "addr:street":"Fischachstr;Salzburg",
    "iso:country":"AT",
    "sg:address":"Fischachstr 7a",
    "sg:city":"Bergheim",
    "sg:orig_category":"Textilwaren / Einzelhandel",
    "sg:phone":"+43 676 5383163",
    "sg:postcode":"5101",
    "sg:province":"Salzburg",
    "wof:name":"Object Fashion Huttary KEG",
    "wof:placetype":"venue"
},
  "geometry": {"coordinates":[13.0272035599,47.8436317444],"type":"Point"}
}