{
  "type": "Feature",
  "properties": {
    "iso:country":"AT",
    "sg:address":"Castellezg 24/13",
    "sg:city":"Wien",
    "sg:orig_category":"Musikverlage",
    "sg:phone":"+43 1 2180743",
    "sg:postcode":"1020",
    "sg:province":"Wien",
    "wof:name":"Sonotonvertretung Narholz G Musikverlag",
    "wof:placetype":"venue"
},
  "geometry": {"coordinates":[16.3811798096,48.2216682434],"type":"Point"}
}