{
  "type": "Feature",
  "properties": {
    "addr:full":"Nr 202 Nestelbach Steiermark 8302",
    "addr:postcode":"8302",
    "addr:street":"Nr;Nestelbach",
    "iso:country":"AT",
    "sg:address":"Nr 202",
    "sg:city":"Nestelbach",
    "sg:orig_category":"Gemeinden",
    "sg:phone":"+43 3133 2110",
    "sg:postcode":"8302",
    "sg:province":"Steiermark",
    "wof:name":"Gemeinde Edelsgrub",
    "wof:placetype":"venue"
},
  "geometry": {"coordinates":[15.6095781326,47.0327033997],"type":"Point"}
}