{
  "type": "Feature",
  "properties": {
    "addr:full":"G\u00f6tzens Tirol 6091",
    "addr:postcode":"6091",
    "addr:street":"Tirol",
    "iso:country":"AT",
    "sg:city":"G\u00f6tzens",
    "sg:orig_category":"Feuerwehren",
    "sg:phone":"+43 5234 3323315",
    "sg:postcode":"6091",
    "sg:province":"Tirol",
    "wof:name":"Freiwillige Feuerwehr Birgitz",
    "wof:placetype":"venue"
},
  "geometry": {"coordinates":[11.2991819382,47.2356338501],"type":"Point"}
}