{
  "type": "Feature",
  "properties": {
    "addr:full":"B\u00e4ckerg 18 Wels Ober\u00f6sterreich 4600",
    "addr:housenumber":"18",
    "addr:postcode":"4600",
    "addr:street":"Baeckerg;Oberoesterreich",
    "iso:country":"AT",
    "sg:address":"B\u00e4ckerg 18",
    "sg:city":"Wels",
    "sg:orig_category":"Optiker",
    "sg:phone":"+43 7242 211390",
    "sg:postcode":"4600",
    "sg:province":"Ober\u00f6sterreich",
    "wof:name":"Fielmann GmbH",
    "wof:placetype":"venue"
},
  "geometry": {"coordinates":[14.024559021,48.1596984863],"type":"Point"}
}