{
  "type": "Feature",
  "properties": {
    "addr:full":"Fischerstr 9 Ried im Innkreis Ober\u00f6sterreich 4910",
    "addr:housenumber":"9",
    "addr:postcode":"4910",
    "addr:street":"Fischerstr",
    "iso:country":"AT",
    "sg:address":"Fischerstr 9",
    "sg:city":"Ried im Innkreis",
    "sg:orig_category":"Flugzeuge",
    "sg:phone":"+43 7752 6160",
    "sg:postcode":"4910",
    "sg:province":"Ober\u00f6sterreich",
    "wof:name":"Fischer Advanced Composite Components AG",
    "wof:placetype":"venue"
},
  "geometry": {"coordinates":[13.4751157761,48.1996650696],"type":"Point"}
}