{
  "type": "Feature",
  "properties": {
    "addr:full":"Leopold Werndl-Str 2 Steyr Ober\u00f6sterreich 4400",
    "addr:housenumber":"2",
    "addr:postcode":"4400",
    "addr:street":"Oberoesterreich",
    "iso:country":"AT",
    "sg:address":"Leopold Werndl-Str 2",
    "sg:city":"Steyr",
    "sg:orig_category":"Lebensmittel / Einzelhandel",
    "sg:phone":"+43 7252 44840",
    "sg:postcode":"4400",
    "sg:province":"Ober\u00f6sterreich",
    "wof:name":"SPAR \u00d6sterreichische Warenhandels-AG",
    "wof:placetype":"venue"
},
  "geometry": {"coordinates":[14.4151735306,48.0370979309],"type":"Point"}
}