{
  "type": "Feature",
  "properties": {
    "addr:full":"Bundesstr 55 Nenzing Vorarlberg 6710",
    "addr:housenumber":"55",
    "addr:postcode":"6710",
    "addr:street":"Bundesstr",
    "iso:country":"AT",
    "sg:address":"Bundesstr 55",
    "sg:city":"Nenzing",
    "sg:classifiers":[
        {
            "category":"Health Services",
            "subcategory":"Doctor",
            "type":"Services"
        }
    ],
    "sg:phone":"+43 5525 62531",
    "sg:postcode":"6710",
    "sg:province":"Vorarlberg",
    "sg:tags":[
        "wellness"
    ],
    "wof:name":"Bio line HandelsgesmbH",
    "wof:placetype":"venue"
},
  "geometry": {"coordinates":[9.7075891495,47.1875686646],"type":"Point"}
}