{
  "type": "Feature",
  "properties": {
    "addr:full":"Hauptstr 31 Radenthein K\u00e4rnten 9545",
    "addr:housenumber":"31",
    "addr:postcode":"9545",
    "addr:street":"Hauptstr;Kaernten",
    "iso:country":"AT",
    "sg:address":"Hauptstr 31",
    "sg:city":"Radenthein",
    "sg:orig_category":"Lebensmittel / Einzelhandel",
    "sg:phone":"+43 4246 2097",
    "sg:postcode":"9545",
    "sg:province":"K\u00e4rnten",
    "wof:name":"Schretter Ernst",
    "wof:placetype":"venue"
},
  "geometry": {"coordinates":[13.7048597336,46.8012008667],"type":"Point"}
}