{
  "type": "Feature",
  "properties": {
    "addr:full":"Marchfeldstr 12 Wien Wien 1200",
    "addr:housenumber":"12",
    "addr:postcode":"1200",
    "addr:street":"Marchfeldstr",
    "iso:country":"AT",
    "sg:address":"Marchfeldstr 12",
    "sg:city":"Wien",
    "sg:orig_category":"Restaurants: Chinesisch",
    "sg:phone":"+43 1 3308368",
    "sg:postcode":"1200",
    "sg:province":"Wien",
    "wof:name":"China-Restaurant Siegreich",
    "wof:placetype":"venue"
},
  "geometry": {"coordinates":[16.3786354065,48.2420539856],"type":"Point"}
}