{
  "type": "Feature",
  "properties": {
    "addr:full":"Interspar EKZ Ennser Str 23 Steyr Ober\u00f6sterreich 4400",
    "addr:postcode":"4400",
    "addr:street":"Str 23",
    "iso:country":"AT",
    "sg:address":"Interspar EKZ Ennser Str 23",
    "sg:city":"Steyr",
    "sg:orig_category":"Freizeit- U Sportbekleidung",
    "sg:phone":"+43 4372 5272379",
    "sg:postcode":"4400",
    "sg:province":"Ober\u00f6sterreich",
    "wof:name":"HERVIS Sport- u ModegesmbH",
    "wof:placetype":"venue"
},
  "geometry": {"coordinates":[14.4193296432,48.0391807556],"type":"Point"}
}