{
  "type": "Feature",
  "properties": {
    "iso:country":"AT",
    "sg:address":"Neue Landstr 29",
    "sg:city":"M\u00e4der",
    "sg:orig_category":"Hauptschulen",
    "sg:phone":"+43 5523 6400711",
    "sg:postcode":"6841",
    "sg:province":"Vorarlberg",
    "wof:name":"\u00f6ko-Hauptsschule M\u00e4der",
    "wof:placetype":"venue"
},
  "geometry": {"coordinates":[-72.157043457,44.9643554688],"type":"Point"}
}