{
  "type": "Feature",
  "properties": {
    "iso:country":"AT",
    "sg:address":"Marschallgasse 36",
    "sg:city":"Graz",
    "sg:classifiers":[
        {
            "category":"Building & Trades",
            "subcategory":"Construction",
            "type":"Services"
        }
    ],
    "sg:phone":"+43 316 711578",
    "sg:postcode":"8020",
    "sg:province":"Steiermark",
    "sg:tags":[
        "historic",
        "restoration"
    ],
    "sg:website":"jahrhundertmaler.at",
    "wof:name":"Viktor Steiner",
    "wof:placetype":"venue"
},
  "geometry": {"coordinates":[15.4308767319,47.0733985901],"type":"Point"}
}