{
  "type": "Feature",
  "properties": {
    "addr:full":"Bergmanng 38 Graz Steiermark 8010",
    "addr:housenumber":"38",
    "addr:postcode":"8010",
    "addr:street":"Bergmanng",
    "iso:country":"AT",
    "sg:address":"Bergmanng 38",
    "sg:city":"Graz",
    "sg:orig_category":"Handelsagenturen",
    "sg:phone":"+43 4331 6384235",
    "sg:postcode":"8010",
    "sg:province":"Steiermark",
    "wof:name":"Hobisch Bernd",
    "wof:placetype":"venue"
},
  "geometry": {"coordinates":[15.4396810532,47.0827102661],"type":"Point"}
}