{
  "type": "Feature",
  "properties": {
    "iso:country":"AT",
    "sg:address":"Lisztstr 52",
    "sg:city":"Lackendorf",
    "sg:orig_category":"Banken U Sparkassen",
    "sg:phone":"+43 2619 7451",
    "sg:postcode":"7321",
    "sg:province":"Burgenland",
    "wof:name":"Raiffeisenbank Ritzing-Raiding regGenmbH",
    "wof:placetype":"venue"
},
  "geometry": {"coordinates":[16.5298595428,47.5673599243],"type":"Point"}
}