{
  "type": "Feature",
  "properties": {
    "addr:full":"Lisztstr 52 Lackendorf Burgenland 7321",
    "addr:housenumber":"52",
    "addr:postcode":"7321",
    "addr:street":"Lisztstr",
    "iso:country":"AT",
    "sg:address":"Lisztstr 52",
    "sg:city":"Lackendorf",
    "sg:orig_category":"Banken U Sparkassen",
    "sg:phone":"+43 2619 7451",
    "sg:postcode":"7321",
    "sg:province":"Burgenland",
    "wof:name":"Raiffeisenbank Ritzing-Raiding regGenmbH",
    "wof:placetype":"venue"
},
  "geometry": {"coordinates":[16.5298595428,47.5673599243],"type":"Point"}
}