{
  "type": "Feature",
  "properties": {
    "iso:country":"AT",
    "sg:address":"Jesuitensteig 34a",
    "sg:city":"Wien",
    "sg:orig_category":"Elektroinstallationsunternehmen",
    "sg:phone":"+43 4318 895710",
    "sg:postcode":"1230",
    "sg:province":"Wien",
    "wof:name":"K.E.M. Kabel-Elektro-Montage GmbH",
    "wof:placetype":"venue"
},
  "geometry": {"coordinates":[16.2735290527,48.1490745544],"type":"Point"}
}