{
  "type": "Feature",
  "properties": {
    "addr:full":"Nr 560 Saalbach Salzburg 5753",
    "addr:postcode":"5753",
    "addr:street":"Nr 560;Salzburg",
    "iso:country":"AT",
    "sg:address":"Nr 560",
    "sg:city":"Saalbach",
    "sg:classifiers":[
        {
            "category":"Park",
            "subcategory":"Provincial",
            "type":"Public Place"
        }
    ],
    "sg:phone":"+43 4365 418444",
    "sg:postcode":"5753",
    "sg:province":"Salzburg",
    "sg:tags":[
        "u",
        "ski-",
        "snowboardschulen"
    ],
    "wof:name":"Schischule Hannes F\u00fcrstauer Ucki & Hannes F\u00fcrstauer",
    "wof:placetype":"venue"
},
  "geometry": {"coordinates":[12.6367301941,47.3899307251],"type":"Point"}
}