{
  "type": "Feature",
  "properties": {
    "iso:country":"AT",
    "sg:address":"Aubach 13",
    "sg:city":"Haag am Hausruck",
    "sg:orig_category":"Autoreparatur",
    "sg:phone":"+43 4366 43767937",
    "sg:postcode":"4680",
    "sg:province":"Ober\u00f6sterreich",
    "wof:name":"Grausgruber Anton",
    "wof:placetype":"venue"
},
  "geometry": {"coordinates":[13.6445636749,48.1712913513],"type":"Point"}
}