{
  "type": "Feature",
  "properties": {
    "addr:full":"Kaiserebersdorferstr 271 Wien Wien 1110",
    "addr:housenumber":"271",
    "addr:postcode":"1110",
    "iso:country":"AT",
    "sg:address":"Kaiserebersdorferstr 271",
    "sg:city":"Wien",
    "sg:orig_category":"Friseure U Frisiersalons",
    "sg:phone":"+43 1 7671038",
    "sg:postcode":"1110",
    "sg:province":"Wien",
    "wof:name":"Helene Winkler",
    "wof:placetype":"venue"
},
  "geometry": {"coordinates":[16.4665489197,48.1601295471],"type":"Point"}
}