{
  "type": "Feature",
  "properties": {
    "addr:full":"Querg 4 Stra\u00dfgang Steiermark 8054",
    "addr:housenumber":"4",
    "addr:postcode":"8054",
    "addr:street":"Querg",
    "iso:country":"AT",
    "sg:address":"Querg 4",
    "sg:city":"Stra\u00dfgang",
    "sg:orig_category":"Friseure U Frisiersalons",
    "sg:phone":"+43 4331 6281517",
    "sg:postcode":"8054",
    "sg:province":"Steiermark",
    "wof:name":"Salon Bettina",
    "wof:placetype":"venue"
},
  "geometry": {"coordinates":[15.3973760605,47.0076370239],"type":"Point"}
}