{
  "type": "Feature",
  "properties": {
    "addr:full":"Hainburger Str 20 Wien Wien 1030",
    "addr:postcode":"1030",
    "addr:street":"Str 20",
    "iso:country":"AT",
    "sg:address":"Hainburger Str 20",
    "sg:city":"Wien",
    "sg:orig_category":"Steuerberatung",
    "sg:phone":"+43 4317 135600",
    "sg:postcode":"1030",
    "sg:province":"Wien",
    "wof:name":"Streitenberger E Dr Wirtschaftstreuhand KG",
    "wof:placetype":"venue"
},
  "geometry": {"coordinates":[16.3941135406,48.2008628845],"type":"Point"}
}