{
  "type": "Feature",
  "properties": {
    "addr:full":"Steinbruch 135 Bad Ischl Ober\u00f6sterreich 4820",
    "addr:housenumber":"135",
    "addr:postcode":"4820",
    "addr:street":"Steinbruch",
    "iso:country":"AT",
    "sg:address":"Steinbruch 135",
    "sg:city":"Bad Ischl",
    "sg:orig_category":"Appartements / Ferienwohnungen",
    "sg:phone":"+43 6132 27493",
    "sg:postcode":"4820",
    "sg:province":"Ober\u00f6sterreich",
    "wof:name":"Ferienhof Faber Fam Bramberger",
    "wof:placetype":"venue"
},
  "geometry": {"coordinates":[13.5973749161,47.7178726196],"type":"Point"}
}