{
  "type": "Feature",
  "properties": {
    "addr:full":"Industriestrasse 46 St. Johann im Pongau Salzburg 5600",
    "addr:housenumber":"46",
    "addr:postcode":"5600",
    "addr:street":"Industriestrasse;Salzburg",
    "iso:country":"AT",
    "sg:address":"Industriestrasse 46",
    "sg:city":"St. Johann im Pongau",
    "sg:classifiers":[
        {
            "category":"Organizations",
            "subcategory":"Non-profit Organization",
            "type":"Services"
        }
    ],
    "sg:phone":"+43 6412 8180",
    "sg:postcode":"5600",
    "sg:province":"Salzburg",
    "sg:tags":[
        "alarm",
        "system"
    ],
    "sg:website":"etk-kappacher.at",
    "wof:name":"ETK Elektrotechnik Kappacher GmbH & Co KG",
    "wof:placetype":"venue"
},
  "geometry": {"coordinates":[13.2056760788,47.3641738892],"type":"Point"}
}