{
  "type": "Feature",
  "properties": {
    "addr:full":"Haidmannsg 9 Wien Wien 1150",
    "addr:housenumber":"9",
    "addr:postcode":"1150",
    "addr:street":"Haidmannsg",
    "iso:country":"AT",
    "sg:address":"Haidmannsg 9",
    "sg:city":"Wien",
    "sg:orig_category":"Fotoapparate U -Artikel / Einzelhandel",
    "sg:phone":"+43 1 8934387",
    "sg:postcode":"1150",
    "sg:province":"Wien",
    "wof:name":"Foto Sobotka - Second Hand Shop",
    "wof:placetype":"venue"
},
  "geometry": {"coordinates":[16.3353443146,48.1939201355],"type":"Point"}
}