{
  "type": "Feature",
  "properties": {
    "addr:full":"Gottsreithweg 9 Eugendorf Salzburg 5301",
    "addr:housenumber":"9",
    "addr:postcode":"5301",
    "addr:street":"Gottsreithweg;Salzburg",
    "iso:country":"AT",
    "sg:address":"Gottsreithweg 9",
    "sg:city":"Eugendorf",
    "sg:orig_category":"Cd, Dvd,Musikkassetten U Schallplatten",
    "sg:phone":"+43 4362 2528312",
    "sg:postcode":"5301",
    "sg:province":"Salzburg",
    "wof:name":"Mentalis Handels- u VeranstaltungsgesmbH",
    "wof:placetype":"venue"
},
  "geometry": {"coordinates":[13.136177063,47.8408432007],"type":"Point"}
}