{
  "type": "Feature",
  "properties": {
    "addr:full":"Ludwig-Kofler-Str 1 Dornbirn Vorarlberg 6850",
    "addr:housenumber":"1",
    "addr:postcode":"6850",
    "addr:street":"Ludwig-Kofler-Str",
    "iso:country":"AT",
    "sg:address":"Ludwig-Kofler-Str 1",
    "sg:city":"Dornbirn",
    "sg:orig_category":"Autohandel",
    "sg:phone":"+43 5572 221600",
    "sg:postcode":"6850",
    "sg:province":"Vorarlberg",
    "sg:website":"mercedes-benz.at/schneider",
    "wof:name":"Schneider Herbert Dipl-Ing GmbH & Co",
    "wof:placetype":"venue"
},
  "geometry": {"coordinates":[9.7427949905,47.4217910767],"type":"Point"}
}