{
  "type": "Feature",
  "properties": {
    "iso:country":"AT",
    "sg:address":"Weyrgasse 8/7",
    "sg:city":"Wien",
    "sg:classifiers":[
        {
            "category":"Government",
            "subcategory":"Fire Station",
            "type":"Public Place"
        }
    ],
    "sg:phone":"+43 1 7125911",
    "sg:postcode":"1030",
    "sg:province":"Wien",
    "sg:tags":[
        "filter",
        "air"
    ],
    "sg:website":"aaf.at",
    "wof:name":"AAF Luftreinigungssysteme GmbH",
    "wof:placetype":"venue"
},
  "geometry": {"coordinates":[16.3887481689,48.2045211792],"type":"Point"}
}