{
  "type": "Feature",
  "properties": {
    "addr:full":"Markt 27 Waldhausen im Strudengau Ober\u00f6sterreich 4391",
    "addr:housenumber":"27",
    "addr:postcode":"4391",
    "addr:street":"Markt",
    "iso:country":"AT",
    "sg:address":"Markt 27",
    "sg:city":"Waldhausen im Strudengau",
    "sg:classifiers":[
        {
            "category":"Manufacturing",
            "subcategory":"Textiles",
            "type":"Manufacturing & Wholesale Goods"
        }
    ],
    "sg:phone":"+43 7260 4231",
    "sg:postcode":"4391",
    "sg:province":"Ober\u00f6sterreich",
    "sg:tags":[
        "curtain",
        "fabric"
    ],
    "wof:name":"Erwin Uhrmann",
    "wof:placetype":"venue"
},
  "geometry": {"coordinates":[14.9481801987,48.2729988098],"type":"Point"}
}