{
  "type": "Feature",
  "properties": {
    "addr:full":"Linzer Str 38 Gmunden Ober\u00f6sterreich 4810",
    "addr:housenumber":"38",
    "addr:postcode":"4810",
    "addr:street":"Linzer Str;Oberoesterreich",
    "iso:country":"AT",
    "sg:address":"Linzer Str 38",
    "sg:city":"Gmunden",
    "sg:orig_category":"Musikunterricht",
    "sg:phone":"+43 761263293",
    "sg:postcode":"4810",
    "sg:province":"Ober\u00f6sterreich",
    "wof:name":"Landesmusikschule",
    "wof:placetype":"venue"
},
  "geometry": {"coordinates":[13.8010501862,47.9282493591],"type":"Point"}
}