{
  "type": "Feature",
  "properties": {
    "addr:full":"Lohnau 67 Uttendorf Ober\u00f6sterreich 5261",
    "addr:housenumber":"67",
    "addr:postcode":"5261",
    "addr:street":"Lohnau",
    "iso:country":"AT",
    "sg:address":"Lohnau 67",
    "sg:city":"Uttendorf",
    "sg:classifiers":[
        {
            "category":"Restaurant",
            "type":"Food & Drink"
        }
    ],
    "sg:phone":"+43 7724 2139",
    "sg:postcode":"5261",
    "sg:province":"Ober\u00f6sterreich",
    "wof:name":"Malenda Melissa",
    "wof:placetype":"venue"
},
  "geometry": {"coordinates":[13.1169176102,48.1526031494],"type":"Point"}
}