{
  "type": "Feature",
  "properties": {
    "iso:country":"AT",
    "sg:address":"Schottenring 24",
    "sg:city":"Wien",
    "sg:orig_category":"Lebensmittel / Einzelhandel",
    "sg:phone":"+43 4315 326402",
    "sg:postcode":"1010",
    "sg:province":"Wien",
    "wof:name":"Naturkost am Ring",
    "wof:placetype":"venue"
},
  "geometry": {"coordinates":[16.3684673309,48.21641922],"type":"Point"}
}