{
  "type": "Feature",
  "properties": {
    "addr:full":"K\u00f6nigfeldweg 2 Schwaz Tirol 6130",
    "addr:housenumber":"2",
    "addr:postcode":"6130",
    "addr:street":"Koenigfeldweg;Tirol",
    "iso:country":"AT",
    "sg:address":"K\u00f6nigfeldweg 2",
    "sg:city":"Schwaz",
    "sg:orig_category":"Spielwaren U Spiele",
    "sg:phone":"+43 4352 4264935",
    "sg:postcode":"6130",
    "sg:province":"Tirol",
    "wof:name":"Hesi Spielwarenfachmarkt",
    "wof:placetype":"venue"
},
  "geometry": {"coordinates":[11.7071990967,47.3454208374],"type":"Point"}
}