{
  "type": "Feature",
  "properties": {
    "iso:country":"AT",
    "sg:address":"Ottakringer Str 217",
    "sg:city":"Wien",
    "sg:orig_category":"Politische Parteien",
    "sg:phone":"+43 1 4863641",
    "sg:postcode":"1160",
    "sg:province":"Wien",
    "wof:name":"\u00f6sterreichische Volkspartei",
    "wof:placetype":"venue"
},
  "geometry": {"coordinates":[16.3082542419,48.2137069702],"type":"Point"}
}