{
  "type": "Feature",
  "properties": {
    "addr:full":"Loferer Bundesstr 38 Zell am See Salzburg 5700",
    "addr:housenumber":"38",
    "addr:postcode":"5700",
    "addr:street":"Salzburg",
    "iso:country":"AT",
    "sg:address":"Loferer Bundesstr 38",
    "sg:city":"Zell am See",
    "sg:orig_category":"Werbegrafik- U Grafik-Design",
    "sg:phone":"+43 4365 42680800",
    "sg:postcode":"5700",
    "sg:province":"Salzburg",
    "wof:name":"Grafik Werbung Nill GmbH",
    "wof:placetype":"venue"
},
  "geometry": {"coordinates":[12.7939519882,47.3163452148],"type":"Point"}
}