{
  "type": "Feature",
  "properties": {
    "addr:full":"Losau 30 Leiben Nieder\u00f6sterreich 3652",
    "addr:housenumber":"30",
    "addr:postcode":"3652",
    "addr:street":"Losau",
    "iso:country":"AT",
    "sg:address":"Losau 30",
    "sg:city":"Leiben",
    "sg:orig_category":"Autoreparatur",
    "sg:phone":"+43 2752 718030",
    "sg:postcode":"3652",
    "sg:province":"Nieder\u00f6sterreich",
    "wof:name":"Lorenz Johann",
    "wof:placetype":"venue"
},
  "geometry": {"coordinates":[15.2510948181,48.2388954163],"type":"Point"}
}