{
  "type": "Feature",
  "properties": {
    "addr:full":"Krastelg 7/7 Wien Wien 1120",
    "addr:housenumber":"7 / 7",
    "addr:postcode":"1120",
    "addr:street":"Krastelg",
    "iso:country":"AT",
    "sg:address":"Krastelg 7/7",
    "sg:city":"Wien",
    "sg:orig_category":"Handelsagenturen",
    "sg:phone":"+43 699 15155898",
    "sg:postcode":"1120",
    "sg:province":"Wien",
    "wof:name":"Janaszek Bronislaw Ing",
    "wof:placetype":"venue"
},
  "geometry": {"coordinates":[16.3160915375,48.1750602722],"type":"Point"}
}