{
  "type": "Feature",
  "properties": {
    "addr:full":"Gerichtsstr 9 St. Veit an der Glan K\u00e4rnten 9300",
    "addr:housenumber":"9",
    "addr:postcode":"9300",
    "addr:street":"Gerichtsstr;Kaernten",
    "iso:country":"AT",
    "sg:address":"Gerichtsstr 9",
    "sg:city":"St. Veit an der Glan",
    "sg:orig_category":"Gerichte",
    "sg:phone":"+43 4212 42420",
    "sg:postcode":"9300",
    "sg:province":"K\u00e4rnten",
    "wof:name":"Bezirksgericht St Veit an der Glan",
    "wof:placetype":"venue"
},
  "geometry": {"coordinates":[-90.4969863892,31.8169898987],"type":"Point"}
}