{
  "type": "Feature",
  "properties": {
    "iso:country":"AT",
    "sg:address":"Franz-Wallack-Str 17",
    "sg:city":"Bruck an der Gro\u00dfglocknerstra\u00dfe",
    "sg:orig_category":"Auskunfteien",
    "sg:phone":"+43 4365 456048",
    "sg:postcode":"5671",
    "sg:province":"Salzburg",
    "wof:name":"Eder Christian Auskunftei GmbH",
    "wof:placetype":"venue"
},
  "geometry": {"coordinates":[12.8262853622,47.2858848572],"type":"Point"}
}