{
  "type": "Feature",
  "properties": {
    "addr:full":"Brown-Boveri-Strasse 6, Top 18 Wiener Neudorf Nieder\u00f6sterreich 2351",
    "addr:housenumber":"6 top 18",
    "addr:postcode":"2351",
    "addr:street":"Brown-Boveri-Strasse",
    "iso:country":"AT",
    "sg:address":"Brown-Boveri-Strasse 6, Top 18",
    "sg:city":"Wiener Neudorf",
    "sg:orig_category":"Datacom",
    "sg:phone":"+43 2236 223670",
    "sg:postcode":"2351",
    "sg:province":"Nieder\u00f6sterreich",
    "sg:website":"irv.at",
    "wof:name":"IRV Datenverarbeitung GmbH",
    "wof:placetype":"venue"
},
  "geometry": {"coordinates":[16.3183326721,48.0863113403],"type":"Point"}
}