{
  "type": "Feature",
  "properties": {
    "addr:full":"Aum\u00fchle 33 Breitenaich Ober\u00f6sterreich 4075",
    "addr:housenumber":"33",
    "addr:postcode":"4075",
    "addr:street":"Aumuehle",
    "iso:country":"AT",
    "sg:address":"Aum\u00fchle 33",
    "sg:city":"Breitenaich",
    "sg:orig_category":"Abfallentsorgung U -Verwertung",
    "sg:phone":"+43 4372 7276800",
    "sg:postcode":"4075",
    "sg:province":"Ober\u00f6sterreich",
    "wof:name":"EKT-Eferdinger Kl\u00e4rschlammtrocknung-GmbH",
    "wof:placetype":"venue"
},
  "geometry": {"coordinates":[13.9787015915,48.2480621338],"type":"Point"}
}