{
  "type": "Feature",
  "properties": {
    "addr:full":"Kalsdorfer Str 4 Fernitz Steiermark 8072",
    "addr:housenumber":"4",
    "addr:postcode":"8072",
    "addr:street":"Str",
    "iso:country":"AT",
    "sg:address":"Kalsdorfer Str 4",
    "sg:city":"Fernitz",
    "sg:orig_category":"Blumeneinzelhandel",
    "sg:phone":"+43 4331 3553324",
    "sg:postcode":"8072",
    "sg:province":"Steiermark",
    "wof:name":"K\u00f6l Blumen Fernitz",
    "wof:placetype":"venue"
},
  "geometry": {"coordinates":[15.4950304031,46.9714012146],"type":"Point"}
}