{
  "type": "Feature",
  "properties": {
    "addr:full":"Ratschkyg 20 Wien Wien 1120",
    "addr:housenumber":"20",
    "addr:postcode":"1120",
    "addr:street":"Ratschkyg",
    "iso:country":"AT",
    "sg:address":"Ratschkyg 20",
    "sg:city":"Wien",
    "sg:orig_category":"Tabaktrafiken",
    "sg:phone":"+43 1 8131595",
    "sg:postcode":"1120",
    "sg:province":"Wien",
    "wof:name":"Latzke Renate",
    "wof:placetype":"venue"
},
  "geometry": {"coordinates":[16.3269824982,48.1773719788],"type":"Point"}
}