{
  "type": "Feature",
  "properties": {
    "addr:full":"Kranzlweg 18 Zell an der Pram Ober\u00f6sterreich 4755",
    "addr:housenumber":"18",
    "addr:postcode":"4755",
    "addr:street":"Kranzlweg",
    "iso:country":"AT",
    "sg:address":"Kranzlweg 18",
    "sg:city":"Zell an der Pram",
    "sg:orig_category":"Gartenarchitekten",
    "sg:phone":"+43 7764 7434",
    "sg:postcode":"4755",
    "sg:province":"Ober\u00f6sterreich",
    "wof:name":"St\u00f6ckl Otmar Dipl-Ing Mag",
    "wof:placetype":"venue"
},
  "geometry": {"coordinates":[13.6272468567,48.313709259],"type":"Point"}
}