{
  "type": "Feature",
  "properties": {
    "iso:country":"AT",
    "sg:address":"Nr 100",
    "sg:city":"Rohrbach an der Lafnitz",
    "sg:classifiers":[
        {
            "category":"Real Estate",
            "subcategory":"Surveying",
            "type":"Services"
        }
    ],
    "sg:phone":"+43 4333 3823260",
    "sg:postcode":"8234",
    "sg:province":"Steiermark",
    "sg:tags":[
        "equipment",
        "material",
        "good",
        "-",
        "handling"
    ],
    "wof:name":"RUBNER HOLZINDUSTRIE GES.MBH",
    "wof:placetype":"venue"
},
  "geometry": {"coordinates":[15.9732465744,47.3812446594],"type":"Point"}
}