{
  "type": "Feature",
  "properties": {
    "addr:full":"Klagenfurter Strasse 43 St. Veit an der Glan K\u00e4rnten 9300",
    "addr:housenumber":"43",
    "addr:postcode":"9300",
    "addr:street":"Klagenfurter Strasse;Kaernten",
    "iso:country":"AT",
    "sg:address":"Klagenfurter Strasse 43",
    "sg:city":"St. Veit an der Glan",
    "sg:classifiers":[
        {
            "category":"Organizations",
            "subcategory":"Non-profit Organization",
            "type":"Services"
        }
    ],
    "sg:phone":"+43 4212 2490",
    "sg:postcode":"9300",
    "sg:province":"K\u00e4rnten",
    "sg:tags":[
        "alarm",
        "system"
    ],
    "wof:name":"Ernst Blasnig Elektro",
    "wof:placetype":"venue"
},
  "geometry": {"coordinates":[14.3577518463,46.7791061401],"type":"Point"}
}