{
  "type": "Feature",
  "properties": {
    "addr:full":"Birkenweg 15 Axams Tirol 6094",
    "addr:housenumber":"15",
    "addr:postcode":"6094",
    "addr:street":"Birkenweg;Tirol",
    "iso:country":"AT",
    "sg:address":"Birkenweg 15",
    "sg:city":"Axams",
    "sg:orig_category":"Installationsunternehmen",
    "sg:phone":"+43 5234 68963",
    "sg:postcode":"6094",
    "sg:province":"Tirol",
    "wof:name":"Brecher Andreas",
    "wof:placetype":"venue"
},
  "geometry": {"coordinates":[11.2596502304,47.2326583862],"type":"Point"}
}