{
  "type": "Feature",
  "properties": {
    "iso:country":"AT",
    "sg:address":"Bendlgasse 16/3",
    "sg:city":"Wien",
    "sg:orig_category":"Castings, Finished",
    "sg:phone":"+43 1 8121507",
    "sg:postcode":"1120",
    "sg:province":"Wien",
    "wof:name":"Ing. Ernst Einsiedl Armaturen- und Schienenfahrzeugersatzteile HandelsgmbH",
    "wof:placetype":"venue"
},
  "geometry": {"coordinates":[16.3349609375,48.1802482605],"type":"Point"}
}