{
  "type": "Feature",
  "properties": {
    "addr:full":"Naschmarkt 439-452 Wien Wien 1040",
    "addr:housenumber":"439-452",
    "addr:postcode":"1040",
    "addr:street":"Naschmarkt",
    "iso:country":"AT",
    "sg:address":"Naschmarkt 439-452",
    "sg:city":"Wien",
    "sg:orig_category":"Feinkost",
    "sg:phone":"+43 1 5852889",
    "sg:postcode":"1040",
    "sg:province":"Wien",
    "wof:name":"Araxi WarenhandelsgesmbH",
    "wof:placetype":"venue"
},
  "geometry": {"coordinates":[16.363779068,48.1984405518],"type":"Point"}
}