{
  "type": "Feature",
  "properties": {
    "addr:full":"Wiener Str 22 St. Andr\u00e4-W\u00f6rdern Nieder\u00f6sterreich 3423",
    "addr:housenumber":"22",
    "addr:postcode":"3423",
    "addr:street":"St. Andrae-Woerdern",
    "iso:country":"AT",
    "sg:address":"Wiener Str 22",
    "sg:city":"St. Andr\u00e4-W\u00f6rdern",
    "sg:orig_category":"Fische U Fischwaren / Einzelhandel",
    "sg:phone":"+43 4322 4232293",
    "sg:postcode":"3423",
    "sg:province":"Nieder\u00f6sterreich",
    "wof:name":"Heindl Martin",
    "wof:placetype":"venue"
},
  "geometry": {"coordinates":[16.2099628448,48.3189926147],"type":"Point"}
}