{
  "type": "Feature",
  "properties": {
    "addr:full":"Gunskirchen Ober\u00f6sterreich 4623",
    "addr:postcode":"4623",
    "iso:country":"AT",
    "sg:city":"Gunskirchen",
    "sg:orig_category":"Feuerwehren",
    "sg:phone":"+43 7246 56149",
    "sg:postcode":"4623",
    "sg:province":"Ober\u00f6sterreich",
    "wof:name":"Freiwillige Feuerwehr Fernreith",
    "wof:placetype":"venue"
},
  "geometry": {"coordinates":[13.9464359283,48.1752510071],"type":"Point"}
}