{
  "type": "Feature",
  "properties": {
    "iso:country":"AT",
    "sg:address":"Feldham 49",
    "sg:city":"Vorchdorf",
    "sg:orig_category":"Metallbe- U -Verarbeitung",
    "sg:phone":"+43 76147785",
    "sg:postcode":"4655",
    "sg:province":"Ober\u00f6sterreich",
    "wof:name":"KMB Kempinger GmbH",
    "wof:placetype":"venue"
},
  "geometry": {"coordinates":[13.9111175537,48.0197792053],"type":"Point"}
}