{
  "type": "Feature",
  "properties": {
    "addr:full":"Mitterfeldg 38 Wiener Neudorf Nieder\u00f6sterreich 2351",
    "addr:housenumber":"38",
    "addr:postcode":"2351",
    "addr:street":"Mitterfeldg",
    "iso:country":"AT",
    "sg:address":"Mitterfeldg 38",
    "sg:city":"Wiener Neudorf",
    "sg:orig_category":"Transportunternehmen",
    "sg:phone":"+43 2236 62166",
    "sg:postcode":"2351",
    "sg:province":"Nieder\u00f6sterreich",
    "wof:name":"Sanda Wolfgang",
    "wof:placetype":"venue"
},
  "geometry": {"coordinates":[16.323102951,48.0887985229],"type":"Point"}
}