{
  "type": "Feature",
  "properties": {
    "iso:country":"AT",
    "sg:address":"Lebenaustr 8",
    "sg:city":"Salzburg",
    "sg:orig_category":"Bierlokale-Pubs",
    "sg:phone":"+43 662 429829",
    "sg:postcode":"5020",
    "sg:province":"Salzburg",
    "wof:name":"Gl\u00fccks Pub",
    "wof:placetype":"venue"
},
  "geometry": {"coordinates":[13.0256786346,47.8207359314],"type":"Point"}
}