{
  "type": "Feature",
  "properties": {
    "iso:country":"AT",
    "sg:address":"Hauptstrasse 238",
    "sg:city":"Raab",
    "sg:classifiers":[
        {
            "category":"Autos & Motor Vehicles",
            "subcategory":"Auto Supplies",
            "type":"Retail Goods"
        }
    ],
    "sg:phone":"+43 7762 2336",
    "sg:postcode":"4760",
    "sg:province":"Ober\u00f6sterreich",
    "sg:tags":[
        "automobile",
        "accessory"
    ],
    "sg:website":"allrad-christ.com",
    "wof:name":"Allrad Christ",
    "wof:placetype":"venue"
},
  "geometry": {"coordinates":[13.6461172104,48.3543930054],"type":"Point"}
}