{
  "type": "Feature",
  "properties": {
    "addr:full":"Haselb\u00f6ckau 9 Schlierbach Ober\u00f6sterreich 4553",
    "addr:housenumber":"9",
    "addr:postcode":"4553",
    "addr:street":"Haselboeckau",
    "iso:country":"AT",
    "sg:address":"Haselb\u00f6ckau 9",
    "sg:city":"Schlierbach",
    "sg:orig_category":"Fahrzeugbau",
    "sg:phone":"+43 7582 37508",
    "sg:postcode":"4553",
    "sg:province":"Ober\u00f6sterreich",
    "wof:name":"Baumschlager Ralley & Racing GmbH",
    "wof:placetype":"venue"
},
  "geometry": {"coordinates":[14.0942153931,47.9508666992],"type":"Point"}
}