{
  "type": "Feature",
  "properties": {
    "iso:country":"AT",
    "sg:address":"Allmeinteilweg 1",
    "sg:city":"Ludesch",
    "sg:orig_category":"Baumschulen",
    "sg:phone":"+43 5550 2424",
    "sg:postcode":"6713",
    "sg:province":"Vorarlberg",
    "wof:name":"D\u00fcnser Gartenbaumschule",
    "wof:placetype":"venue"
},
  "geometry": {"coordinates":[9.7772989273,47.1932067871],"type":"Point"}
}