{
  "type": "Feature",
  "properties": {
    "iso:country":"AT",
    "sg:address":"Bubing 129",
    "sg:city":"Sch\u00e4rding",
    "sg:orig_category":"Gastronomie- U Hoteleinrichtungen",
    "sg:phone":"+43 7712 29099",
    "sg:postcode":"4780",
    "sg:province":"Ober\u00f6sterreich",
    "wof:name":"Lechner K\u00fcchentechnik GmbH",
    "wof:placetype":"venue"
},
  "geometry": {"coordinates":[13.4304552078,48.4575538635],"type":"Point"}
}