{
  "type": "Feature",
  "properties": {
    "addr:full":"Hauptpl 11 Liezen Steiermark 8940",
    "addr:housenumber":"11",
    "addr:postcode":"8940",
    "addr:street":"Hauptpl",
    "iso:country":"AT",
    "sg:address":"Hauptpl 11",
    "sg:city":"Liezen",
    "sg:orig_category":"Immobilienmakler",
    "sg:phone":"+43 3612 249040",
    "sg:postcode":"8940",
    "sg:province":"Steiermark",
    "wof:name":"Raiffeisen-Immobilien Steiermark GesmbH",
    "wof:placetype":"venue"
},
  "geometry": {"coordinates":[14.2411966324,47.5668792725],"type":"Point"}
}