{
  "type": "Feature",
  "properties": {
    "iso:country":"AT",
    "sg:address":"Leberstr 118A",
    "sg:city":"Wien",
    "sg:orig_category":"Anlagenbau U -Technik",
    "sg:phone":"+43 1 74323240",
    "sg:postcode":"1110",
    "sg:province":"Wien",
    "wof:name":"AGB Anlagen-Ger\u00e4te-Betriebstechnik GmbH",
    "wof:placetype":"venue"
},
  "geometry": {"coordinates":[16.410774231,48.1689567566],"type":"Point"}
}