{
  "type": "Feature",
  "properties": {
    "addr:full":"Halbarting 36 Kematen an der Krems Ober\u00f6sterreich 4531",
    "addr:housenumber":"36",
    "addr:postcode":"4531",
    "addr:street":"Halbarting",
    "iso:country":"AT",
    "sg:address":"Halbarting 36",
    "sg:city":"Kematen an der Krems",
    "sg:orig_category":"Transportunternehmen",
    "sg:phone":"+43 664 4519202",
    "sg:postcode":"4531",
    "sg:province":"Ober\u00f6sterreich",
    "wof:name":"Wagner Christian",
    "wof:placetype":"venue"
},
  "geometry": {"coordinates":[14.1900997162,48.093711853],"type":"Point"}
}