{
  "type": "Feature",
  "properties": {
    "addr:full":"Pluskaufstr 7/1. OG/neben Vobis 4066",
    "addr:housenumber":"7 / 1 og",
    "addr:postcode":"4066",
    "addr:street":"Pluskaufstr;Vobis",
    "iso:country":"AT",
    "sg:address":"Pluskaufstr 7/1. OG/neben Vobis",
    "sg:orig_category":"Telekommunikation",
    "sg:phone":"+43 800 664300",
    "sg:postcode":"4066",
    "wof:name":"A1-Shop Linz Plus City",
    "wof:placetype":"venue"
},
  "geometry": {"coordinates":[14.2019853592,48.2585906982],"type":"Point"}
}