{
  "type": "Feature",
  "properties": {
    "addr:full":"Lechtaler Str 30A Reutte Tirol 6600",
    "addr:postcode":"6600",
    "addr:street":"Str 30A;Tirol",
    "iso:country":"AT",
    "sg:address":"Lechtaler Str 30A",
    "sg:city":"Reutte",
    "sg:orig_category":"Lebensmittel / Einzelhandel",
    "sg:phone":"+43 5672 718650",
    "sg:postcode":"6600",
    "sg:province":"Tirol",
    "wof:name":"MPREIS WarenvertriebsgesmbH",
    "wof:placetype":"venue"
},
  "geometry": {"coordinates":[10.6992883682,47.4807891846],"type":"Point"}
}