{
  "type": "Feature",
  "properties": {
    "addr:full":"Hauptpl 14 Korneuburg Nieder\u00f6sterreich 2100",
    "addr:housenumber":"14",
    "addr:postcode":"2100",
    "addr:street":"Hauptpl;Niederoesterreich",
    "iso:country":"AT",
    "sg:address":"Hauptpl 14",
    "sg:city":"Korneuburg",
    "sg:orig_category":"Medizintechnik",
    "sg:phone":"+43 2262 71110",
    "sg:postcode":"2100",
    "sg:province":"Nieder\u00f6sterreich",
    "wof:name":"ENERMED VertriebsgesmbH",
    "wof:placetype":"venue"
},
  "geometry": {"coordinates":[16.3344135284,48.3441314697],"type":"Point"}
}