{
  "type": "Feature",
  "properties": {
    "addr:full":"Atterseestr 57 Lenzing Ober\u00f6sterreich 4860",
    "addr:housenumber":"57",
    "addr:postcode":"4860",
    "addr:street":"Atterseestr",
    "iso:country":"AT",
    "sg:address":"Atterseestr 57",
    "sg:city":"Lenzing",
    "sg:orig_category":"Apotheken",
    "sg:phone":"+43 767293200",
    "sg:postcode":"4860",
    "sg:province":"Ober\u00f6sterreich",
    "wof:name":"Apotheke Lenzing Mag pharm Dr E Berndt KG",
    "wof:placetype":"venue"
},
  "geometry": {"coordinates":[13.610159874,47.975402832],"type":"Point"}
}