{
  "type": "Feature",
  "properties": {
    "addr:full":"Lindenweg 33 Gerasdorf Nieder\u00f6sterreich 2201",
    "addr:housenumber":"33",
    "addr:postcode":"2201",
    "addr:street":"Lindenweg",
    "iso:country":"AT",
    "sg:address":"Lindenweg 33",
    "sg:city":"Gerasdorf",
    "sg:orig_category":"Mess-, Steuer- U Regeltechnik",
    "sg:phone":"+43 4322 4628438",
    "sg:postcode":"2201",
    "sg:province":"Nieder\u00f6sterreich",
    "wof:name":"Seuhs Friedrich Ing",
    "wof:placetype":"venue"
},
  "geometry": {"coordinates":[16.4516925812,48.2928962708],"type":"Point"}
}