{
  "type": "Feature",
  "properties": {
    "addr:full":"Kircheng 3 Gmunden Ober\u00f6sterreich 4810",
    "addr:housenumber":"3",
    "addr:postcode":"4810",
    "addr:street":"Kircheng;Oberoesterreich",
    "iso:country":"AT",
    "sg:address":"Kircheng 3",
    "sg:city":"Gmunden",
    "sg:classifiers":[
        {
            "category":"Taxi",
            "type":"Transportation"
        }
    ],
    "sg:phone":"+43 4376 121711",
    "sg:postcode":"4810",
    "sg:province":"Ober\u00f6sterreich",
    "sg:tags":[
        "personentransporte",
        "u"
    ],
    "wof:name":"Attwenger Norbert",
    "wof:placetype":"venue"
},
  "geometry": {"coordinates":[13.7995681763,47.9184799194],"type":"Point"}
}