{
  "type": "Feature",
  "properties": {
    "addr:full":"Wiener Str 22 Neumarkt in Steiermark Steiermark 8820",
    "addr:postcode":"8820",
    "iso:country":"AT",
    "sg:address":"Wiener Str 22",
    "sg:city":"Neumarkt in Steiermark",
    "sg:orig_category":"Maler, Anstreicher U Lackierer",
    "sg:phone":"+43 4335 843939",
    "sg:postcode":"8820",
    "sg:province":"Steiermark",
    "wof:name":"Ehgartner GesmbH",
    "wof:placetype":"venue"
},
  "geometry": {"coordinates":[14.4250593185,47.0796432495],"type":"Point"}
}