{
  "type": "Feature",
  "properties": {
    "addr:full":"Kulturhausstrasse 7 Latschach ober dem Faaker See K\u00e4rnten 9582",
    "addr:housenumber":"7",
    "addr:postcode":"9582",
    "addr:street":"Kulturhausstrasse",
    "iso:country":"AT",
    "sg:address":"Kulturhausstrasse 7",
    "sg:city":"Latschach ober dem Faaker See",
    "sg:classifiers":[
        {
            "category":"Home & Garden",
            "subcategory":"Household Appliances",
            "type":"Retail Goods"
        }
    ],
    "sg:phone":"+43 4254 2651",
    "sg:postcode":"9582",
    "sg:province":"K\u00e4rnten",
    "sg:tags":[
        "electric"
    ],
    "wof:name":"Walter Hassler",
    "wof:placetype":"venue"
},
  "geometry": {"coordinates":[13.9216537476,46.5588226318],"type":"Point"}
}