{
  "type": "Feature",
  "properties": {
    "addr:full":"Am Concordepl 1 Schwechat Nieder\u00f6sterreich 2320",
    "addr:housenumber":"1",
    "addr:postcode":"2320",
    "addr:street":"Am Concordepl;Niederoesterreich",
    "iso:country":"AT",
    "sg:address":"Am Concordepl 1",
    "sg:city":"Schwechat",
    "sg:orig_category":"Unterhaltungselektronik / Erzeugung U Gro\u00c3\u0178handel",
    "sg:phone":"+43 1 5266660",
    "sg:postcode":"2320",
    "sg:province":"Nieder\u00f6sterreich",
    "wof:name":"NOVIS Electronics GmbH",
    "wof:placetype":"venue"
},
  "geometry": {"coordinates":[16.4918956757,48.1379928589],"type":"Point"}
}