{
  "type": "Feature",
  "properties": {
    "addr:full":"Klausweg 13 Puch Salzburg 5412",
    "addr:housenumber":"13",
    "addr:postcode":"5412",
    "addr:street":"Klausweg;Salzburg",
    "iso:country":"AT",
    "sg:address":"Klausweg 13",
    "sg:city":"Puch",
    "sg:orig_category":"Feng-Shui",
    "sg:phone":"+43 4362 4577415",
    "sg:postcode":"5412",
    "sg:province":"Salzburg",
    "wof:name":"Feng Shui & Geomantie - Karin Wimmeder",
    "wof:placetype":"venue"
},
  "geometry": {"coordinates":[13.0908412933,47.7144966125],"type":"Point"}
}