{
  "type": "Feature",
  "properties": {
    "addr:full":"Nr 148 G\u00fcssing Burgenland 7540",
    "addr:postcode":"7540",
    "addr:street":"Nr 148 Guessing",
    "iso:country":"AT",
    "sg:address":"Nr 148",
    "sg:city":"G\u00fcssing",
    "sg:orig_category":"Musikgruppen",
    "sg:phone":"+43 3328 32922",
    "sg:postcode":"7540",
    "sg:province":"Burgenland",
    "wof:name":"Musikverein Neusiedl bei G\u00fcssing",
    "wof:placetype":"venue"
},
  "geometry": {"coordinates":[16.8418807983,47.9491081238],"type":"Point"}
}