{
  "type": "Feature",
  "properties": {
    "addr:full":"Bundesstr 32 Wimpassing im Schwarzatale Nieder\u00f6sterreich 2632",
    "addr:housenumber":"32",
    "addr:postcode":"2632",
    "addr:street":"Bundesstr",
    "iso:country":"AT",
    "sg:address":"Bundesstr 32",
    "sg:city":"Wimpassing im Schwarzatale",
    "sg:orig_category":"Kinderbetreuung",
    "sg:phone":"+43 2630 35430",
    "sg:postcode":"2632",
    "sg:province":"Nieder\u00f6sterreich",
    "wof:name":"Hort d Marktgemeinde Wimpassing",
    "wof:placetype":"venue"
},
  "geometry": {"coordinates":[16.0058555603,47.6837768555],"type":"Point"}
}