{
  "type": "Feature",
  "properties": {
    "addr:full":"Walser Str 49 Riezlern Vorarlberg 6991",
    "addr:postcode":"6991",
    "addr:street":"Str 49",
    "iso:country":"AT",
    "sg:address":"Walser Str 49",
    "sg:city":"Riezlern",
    "sg:orig_category":"Fotoapparate U -Artikel / Einzelhandel",
    "sg:phone":"+43 4355 175244",
    "sg:postcode":"6991",
    "sg:province":"Vorarlberg",
    "wof:name":"Herr Matthias",
    "wof:placetype":"venue"
},
  "geometry": {"coordinates":[10.1881504059,47.3579444885],"type":"Point"}
}