{
  "type": "Feature",
  "properties": {
    "addr:full":"Eisenkappler Str 1 Eberndorf K\u00e4rnten 9141",
    "addr:housenumber":"1",
    "addr:postcode":"9141",
    "addr:street":"Str;Kaernten",
    "iso:country":"AT",
    "sg:address":"Eisenkappler Str 1",
    "sg:city":"Eberndorf",
    "sg:orig_category":"Lebensmittel / Einzelhandel",
    "sg:phone":"+43 4236 3301",
    "sg:postcode":"9141",
    "sg:province":"K\u00e4rnten",
    "wof:name":"Billa AG",
    "wof:placetype":"venue"
},
  "geometry": {"coordinates":[14.6391401291,46.589881897],"type":"Point"}
}