{
  "type": "Feature",
  "properties": {
    "addr:full":"Rabensteig 5 Wien Wien 1010",
    "addr:housenumber":"5",
    "addr:postcode":"1010",
    "addr:street":"Rabensteig",
    "iso:country":"AT",
    "sg:address":"Rabensteig 5",
    "sg:city":"Wien",
    "sg:orig_category":"Bars-Cafes",
    "sg:phone":"+43 1 5354105",
    "sg:postcode":"1010",
    "sg:province":"Wien",
    "wof:name":"Cafe-Bar Roter Engel",
    "wof:placetype":"venue"
},
  "geometry": {"coordinates":[16.3750648499,48.2118988037],"type":"Point"}
}