{
  "type": "Feature",
  "properties": {
    "addr:full":"Nesselthaler G 5 Salzburg Salzburg 5020",
    "addr:housenumber":"5",
    "addr:postcode":"5020",
    "addr:street":"Nesselthaler G;Salzburg",
    "iso:country":"AT",
    "sg:address":"Nesselthaler G 5",
    "sg:city":"Salzburg",
    "sg:classifiers":[
        {
            "category":"Travel",
            "subcategory":"Hotels & Motels",
            "type":"Entertainment"
        }
    ],
    "sg:phone":"+43 662 623142",
    "sg:postcode":"5020",
    "sg:province":"Salzburg",
    "wof:name":"Hotel Villa Della Scala",
    "wof:placetype":"venue"
},
  "geometry": {"coordinates":[13.0668153763,47.7949714661],"type":"Point"}
}