{
  "type": "Feature",
  "properties": {
    "addr:full":"Ketzerg 57 Wien Wien 1230",
    "addr:housenumber":"57",
    "addr:postcode":"1230",
    "addr:street":"Ketzerg",
    "iso:country":"AT",
    "sg:address":"Ketzerg 57",
    "sg:city":"Wien",
    "sg:orig_category":"Baumeister",
    "sg:phone":"+43 1 6994981",
    "sg:postcode":"1230",
    "sg:province":"Wien",
    "wof:name":"Satler E GesmbH",
    "wof:placetype":"venue"
},
  "geometry": {"coordinates":[16.3127841949,48.1268959045],"type":"Point"}
}