{
  "type": "Feature",
  "properties": {
    "iso:country":"AT",
    "sg:address":"Hauptstr 31/1/5",
    "sg:city":"Bisamberg",
    "sg:orig_category":"Massagen",
    "sg:phone":"+43 4322 6262680",
    "sg:postcode":"2102",
    "sg:province":"Nieder\u00f6sterreich",
    "wof:name":"B\u00f6hnel Eva Massage-Fachinstitut",
    "wof:placetype":"venue"
},
  "geometry": {"coordinates":[16.3610553741,48.3311195374],"type":"Point"}
}