{
  "type": "Feature",
  "properties": {
    "addr:full":"Wiesel 1 Mieders Tirol 6142",
    "addr:housenumber":"1",
    "addr:postcode":"6142",
    "addr:street":"Wiesel;Tirol",
    "iso:country":"AT",
    "sg:address":"Wiesel 1",
    "sg:city":"Mieders",
    "sg:classifiers":[
        {
            "category":"Travel",
            "subcategory":"Hotels & Motels",
            "type":"Entertainment"
        }
    ],
    "sg:phone":"+43 5225 64504",
    "sg:postcode":"6142",
    "sg:province":"Tirol",
    "wof:name":"Hotel Wiesenhof",
    "wof:placetype":"venue"
},
  "geometry": {"coordinates":[11.3837833405,47.1667938232],"type":"Point"}
}