{
  "type": "Feature",
  "properties": {
    "addr:full":"Linzer Strasse 110 Marchtrenk Ober\u00f6sterreich 4614",
    "addr:housenumber":"110",
    "addr:postcode":"4614",
    "addr:street":"Linzer Strasse",
    "iso:country":"AT",
    "sg:address":"Linzer Strasse 110",
    "sg:city":"Marchtrenk",
    "sg:classifiers":[
        {
            "category":"Autos & Motor Vehicles",
            "subcategory":"Fuel & Gas Station",
            "type":"Retail Goods"
        }
    ],
    "sg:phone":"+43 7243 54444",
    "sg:postcode":"4614",
    "sg:province":"Ober\u00f6sterreich",
    "sg:tags":[
        "machine",
        "cold",
        "milling",
        "asphalt",
        "machines"
    ],
    "sg:website":"p-h.at",
    "wof:name":"Ploier + H\u00f6rmann Bau Gesellschaft mbH",
    "wof:placetype":"venue"
},
  "geometry": {"coordinates":[14.1315174103,48.194568634],"type":"Point"}
}