{
  "type": "Feature",
  "properties": {
    "addr:full":"Beethoveng 6 Haid Ober\u00f6sterreich 4053",
    "addr:housenumber":"6",
    "addr:postcode":"4053",
    "addr:street":"Beethoveng",
    "iso:country":"AT",
    "sg:address":"Beethoveng 6",
    "sg:city":"Haid",
    "sg:orig_category":"Reinigungsbedarf U Reinigungsmittel",
    "sg:phone":"+43 4372 2989371",
    "sg:postcode":"4053",
    "sg:province":"Ober\u00f6sterreich",
    "wof:name":"Dorfner Willi",
    "wof:placetype":"venue"
},
  "geometry": {"coordinates":[14.2578325272,48.2075424194],"type":"Point"}
}