{
  "type": "Feature",
  "properties": {
    "addr:full":"Bahnhofpl 9 Stockerau Nieder\u00f6sterreich 2000",
    "addr:housenumber":"9",
    "addr:postcode":"2000",
    "addr:street":"Bahnhofpl",
    "iso:country":"AT",
    "sg:address":"Bahnhofpl 9",
    "sg:city":"Stockerau",
    "sg:classifiers":[
        {
            "category":"Restaurant",
            "type":"Food & Drink"
        }
    ],
    "sg:phone":"+43 2266 62247",
    "sg:postcode":"2000",
    "sg:province":"Nieder\u00f6sterreich",
    "wof:name":"Restaurant Zur Post",
    "wof:placetype":"venue"
},
  "geometry": {"coordinates":[16.2116508484,48.3831443787],"type":"Point"}
}