{
  "type": "Feature",
  "properties": {
    "addr:full":"Judeng 9 Salzburg Salzburg 5020",
    "addr:housenumber":"9",
    "addr:postcode":"5020",
    "addr:street":"Judeng;Salzburg",
    "iso:country":"AT",
    "sg:address":"Judeng 9",
    "sg:city":"Salzburg",
    "sg:orig_category":"Tourismusunternehmen",
    "sg:phone":"+43 4366 28461810",
    "sg:postcode":"5020",
    "sg:province":"Salzburg",
    "wof:name":"Salzburger Burgen- u Schl\u00f6sserbetriebsf\u00fchrung",
    "wof:placetype":"venue"
},
  "geometry": {"coordinates":[13.0463275909,47.7998847961],"type":"Point"}
}