{
  "type": "Feature",
  "properties": {
    "addr:full":"Neue Str 6 Neuhaus Nieder\u00f6sterreich 2565",
    "addr:housenumber":"6",
    "addr:postcode":"2565",
    "addr:street":"Neue Str",
    "iso:country":"AT",
    "sg:address":"Neue Str 6",
    "sg:city":"Neuhaus",
    "sg:orig_category":"Hauskrankenpflege / Heimhilfe",
    "sg:phone":"+43 2674 87466",
    "sg:postcode":"2565",
    "sg:province":"Nieder\u00f6sterreich",
    "wof:name":"Hilfswerk Triestingtal - Hilfe und Pflege daheim",
    "wof:placetype":"venue"
},
  "geometry": {"coordinates":[16.0613861084,48.0097465515],"type":"Point"}
}