{
  "type": "Feature",
  "properties": {
    "addr:full":"Bahnhofstr 10 St. Johann im Pongau Salzburg 5600",
    "addr:housenumber":"10",
    "addr:postcode":"5600",
    "addr:street":"Bahnhofstr;Salzburg",
    "iso:country":"AT",
    "sg:address":"Bahnhofstr 10",
    "sg:city":"St. Johann im Pongau",
    "sg:orig_category":"Tabaktrafiken",
    "sg:phone":"+43 6412 8485",
    "sg:postcode":"5600",
    "sg:province":"Salzburg",
    "wof:name":"Gerer Rupert",
    "wof:placetype":"venue"
},
  "geometry": {"coordinates":[13.1952476501,47.3472061157],"type":"Point"}
}