{
  "type": "Feature",
  "properties": {
    "addr:full":"Zellenpl 3 Seckau Steiermark 8732",
    "addr:housenumber":"3",
    "addr:postcode":"8732",
    "addr:street":"Zellenpl",
    "iso:country":"AT",
    "sg:address":"Zellenpl 3",
    "sg:city":"Seckau",
    "sg:classifiers":[
        {
            "category":"Travel",
            "subcategory":"Hotels & Motels",
            "type":"Entertainment"
        }
    ],
    "sg:phone":"+43 3514 56450",
    "sg:postcode":"8732",
    "sg:province":"Steiermark",
    "sg:website":"hofwirt.at",
    "wof:name":"Hotel-Restaurant Hofwirt",
    "wof:placetype":"venue"
},
  "geometry": {"coordinates":[14.7858562469,47.2741394043],"type":"Point"}
}