{
  "type": "Feature",
  "properties": {
    "iso:country":"AT",
    "sg:address":"Reitzersdorfer Str 1",
    "sg:city":"St. Georgen am Steinfelde",
    "sg:orig_category":"Banken U Sparkassen",
    "sg:phone":"+43 4327 42884254",
    "sg:postcode":"3151",
    "sg:province":"Nieder\u00f6sterreich",
    "wof:name":"Raiffeisenbank Wilhelmsburg-St Georgen regGenmbH",
    "wof:placetype":"venue"
},
  "geometry": {"coordinates":[15.612279892,48.1410713196],"type":"Point"}
}