{
  "type": "Feature",
  "properties": {
    "iso:country":"AT",
    "sg:address":"Seebach 6",
    "sg:city":"Eferding",
    "sg:orig_category":"Garten- U Landschaftsgestaltung",
    "sg:phone":"+43 4372 724396",
    "sg:postcode":"4070",
    "sg:province":"Ober\u00f6sterreich",
    "wof:name":"Hehenberger Augustine",
    "wof:placetype":"venue"
},
  "geometry": {"coordinates":[13.9963912964,48.3227043152],"type":"Point"}
}