{
  "type": "Feature",
  "properties": {
    "addr:full":"Hauptpl 8 St. Leonhard am Forst Nieder\u00f6sterreich 3243",
    "addr:housenumber":"8",
    "addr:postcode":"3243",
    "addr:street":"Hauptpl",
    "iso:country":"AT",
    "sg:address":"Hauptpl 8",
    "sg:city":"St. Leonhard am Forst",
    "sg:orig_category":"Fleischhauereien",
    "sg:phone":"+43 4327 562100",
    "sg:postcode":"3243",
    "sg:province":"Nieder\u00f6sterreich",
    "wof:name":"Gruber M u H GesmbH",
    "wof:placetype":"venue"
},
  "geometry": {"coordinates":[15.2835197449,48.1421813965],"type":"Point"}
}