{
  "type": "Feature",
  "properties": {
    "addr:full":"Industriestrasse 1 Stadl-Paura Ober\u00f6sterreich 4651",
    "addr:housenumber":"1",
    "addr:postcode":"4651",
    "addr:street":"Industriestrasse",
    "iso:country":"AT",
    "sg:address":"Industriestrasse 1",
    "sg:city":"Stadl-Paura",
    "sg:classifiers":[
        {
            "category":"Manufacturing",
            "subcategory":"Rubber & Plastics",
            "type":"Manufacturing & Wholesale Goods"
        }
    ],
    "sg:phone":"+43 7245 226990",
    "sg:postcode":"4651",
    "sg:province":"Ober\u00f6sterreich",
    "sg:tags":[
        "film"
    ],
    "wof:name":"AWA Andernach Isolier- und D\u00e4mmstoffe Ges.m.b.H. & Co KG",
    "wof:placetype":"venue"
},
  "geometry": {"coordinates":[13.8865394592,48.0848693848],"type":"Point"}
}