{
  "type": "Feature",
  "properties": {
    "iso:country":"AT",
    "sg:address":"Ettenreichg 10",
    "sg:city":"Wien",
    "sg:orig_category":"Lottokollekturen",
    "sg:phone":"+43 1 6062360",
    "sg:postcode":"1100",
    "sg:province":"Wien",
    "wof:name":"Lotto-Toto",
    "wof:placetype":"venue"
},
  "geometry": {"coordinates":[16.3764972687,48.1723937988],"type":"Point"}
}