{
  "type": "Feature",
  "properties": {
    "iso:country":"AT",
    "sg:address":"Nr 6",
    "sg:city":"Munderfing",
    "sg:orig_category":"Non-Classified Establishments",
    "sg:phone":"+43 7744 6378",
    "sg:postcode":"5222",
    "sg:province":"Ober\u00f6sterreich",
    "wof:name":"Pfarramt",
    "wof:placetype":"venue"
},
  "geometry": {"coordinates":[13.1816291809,48.0702476501],"type":"Point"}
}