{
  "type": "Feature",
  "properties": {
    "iso:country":"AT",
    "sg:address":"Erzherzog-Johann-Str 675",
    "sg:city":"Schladming",
    "sg:classifiers":[
        {
            "category":"Professional",
            "subcategory":"Computer Services",
            "type":"Services"
        }
    ],
    "sg:phone":"+43 4336 8724577",
    "sg:postcode":"8970",
    "sg:province":"Steiermark",
    "sg:tags":[
        "software"
    ],
    "sg:website":"comaktiv.at",
    "wof:name":"ComAktiv",
    "wof:placetype":"venue"
},
  "geometry": {"coordinates":[13.6907081604,47.3944816589],"type":"Point"}
}