{
  "type": "Feature",
  "properties": {
    "addr:full":"Triester Str 45 Tribuswinkel Nieder\u00f6sterreich 2512",
    "addr:postcode":"2512",
    "addr:street":"Str;Niederoesterreich",
    "iso:country":"AT",
    "sg:address":"Triester Str 45",
    "sg:city":"Tribuswinkel",
    "sg:orig_category":"Feuerwehren",
    "sg:phone":"+43 2252 419220",
    "sg:postcode":"2512",
    "sg:province":"Nieder\u00f6sterreich",
    "wof:name":"Freiwillige Feuerwehr Oeynhausen",
    "wof:placetype":"venue"
},
  "geometry": {"coordinates":[16.2932167053,47.9866409302],"type":"Point"}
}