{
  "type": "Feature",
  "properties": {
    "addr:full":"Dorf 7 Ellmau Tirol 6352",
    "addr:housenumber":"7",
    "addr:postcode":"6352",
    "addr:street":"Dorf;Tirol",
    "iso:country":"AT",
    "sg:address":"Dorf 7",
    "sg:city":"Ellmau",
    "sg:orig_category":"Handelsagenturen",
    "sg:phone":"+43 4353 582333",
    "sg:postcode":"6352",
    "sg:province":"Tirol",
    "wof:name":"Apparthotel Tom Sojer",
    "wof:placetype":"venue"
},
  "geometry": {"coordinates":[12.304233551,47.5135993958],"type":"Point"}
}