{
  "type": "Feature",
  "properties": {
    "iso:country":"AT",
    "sg:address":"Weidenthal 7",
    "sg:city":"Altheim",
    "sg:classifiers":[
        {
            "category":"Home & Garden",
            "subcategory":"Building Materials",
            "type":"Retail Goods"
        }
    ],
    "sg:phone":"+43 7723 44198",
    "sg:postcode":"4950",
    "sg:province":"Ober\u00f6sterreich",
    "sg:tags":[
        "baustoffe",
        "-material",
        "u"
    ],
    "wof:name":"Gruber Ferdinand",
    "wof:placetype":"venue"
},
  "geometry": {"coordinates":[13.2506742477,48.2663726807],"type":"Point"}
}