{
  "type": "Feature",
  "properties": {
    "addr:full":"Dreisesselbergstr. 17 Ulrichsberg Ober\u00f6sterreich 4161",
    "addr:housenumber":"17",
    "addr:postcode":"4161",
    "addr:street":"Dreisesselbergstr.",
    "iso:country":"AT",
    "sg:address":"Dreisesselbergstr. 17",
    "sg:city":"Ulrichsberg",
    "sg:classifiers":[
        {
            "category":"Shopping",
            "type":"Retail Goods"
        }
    ],
    "sg:phone":"+43 4372 882424",
    "sg:postcode":"4161",
    "sg:province":"Ober\u00f6sterreich",
    "sg:tags":[
        "finished",
        "-",
        "metallic"
    ],
    "wof:name":"RICHARD LEITNER GES.MBH",
    "wof:placetype":"venue"
},
  "geometry": {"coordinates":[13.9087667465,48.6784515381],"type":"Point"}
}