{
  "type": "Feature",
  "properties": {
    "iso:country":"AT",
    "sg:address":"Belvedereg 12/29",
    "sg:city":"Wien",
    "sg:orig_category":"Stickereien",
    "sg:phone":"+43 1 5055238",
    "sg:postcode":"1040",
    "sg:province":"Wien",
    "wof:name":"Fiala Claudia",
    "wof:placetype":"venue"
},
  "geometry": {"coordinates":[16.3773708344,48.191619873],"type":"Point"}
}