{
  "type": "Feature",
  "properties": {
    "addr:full":"Belvedereg 12/29 Wien Wien 1040",
    "addr:housenumber":"12 / 29",
    "addr:postcode":"1040",
    "addr:street":"Belvedereg",
    "iso:country":"AT",
    "sg:address":"Belvedereg 12/29",
    "sg:city":"Wien",
    "sg:orig_category":"Stickereien",
    "sg:phone":"+43 1 5055238",
    "sg:postcode":"1040",
    "sg:province":"Wien",
    "wof:name":"Fiala Claudia",
    "wof:placetype":"venue"
},
  "geometry": {"coordinates":[16.3773708344,48.191619873],"type":"Point"}
}