{
  "type": "Feature",
  "properties": {
    "addr:full":"Triester Str 219 Feldkirchen Steiermark 8073",
    "addr:housenumber":"219",
    "addr:postcode":"8073",
    "iso:country":"AT",
    "sg:address":"Triester Str 219",
    "sg:city":"Feldkirchen",
    "sg:orig_category":"Tankstellen",
    "sg:phone":"+43 316 2962920",
    "sg:postcode":"8073",
    "sg:province":"Steiermark",
    "wof:name":"OMV AG",
    "wof:placetype":"venue"
},
  "geometry": {"coordinates":[15.4546527863,46.9938087463],"type":"Point"}
}