{
  "type": "Feature",
  "properties": {
    "addr:full":"Herreng 14/1 Klagenfurt K\u00e4rnten 9020",
    "addr:housenumber":"14 / 1",
    "addr:postcode":"9020",
    "addr:street":"Herreng;Kaernten",
    "iso:country":"AT",
    "sg:address":"Herreng 14/1",
    "sg:city":"Klagenfurt",
    "sg:orig_category":"Notare",
    "sg:phone":"+43 463 505330",
    "sg:postcode":"9020",
    "sg:province":"K\u00e4rnten",
    "wof:name":"Ro\u00dfbacher Artur Dr & Partner",
    "wof:placetype":"venue"
},
  "geometry": {"coordinates":[14.3053741455,46.625541687],"type":"Point"}
}