{
  "type": "Feature",
  "properties": {
    "addr:full":"Br\u00e4uerstr 9 Hallein Salzburg 5400",
    "addr:housenumber":"9",
    "addr:postcode":"5400",
    "addr:street":"Braeuerstr;Salzburg",
    "iso:country":"AT",
    "sg:address":"Br\u00e4uerstr 9",
    "sg:city":"Hallein",
    "sg:orig_category":"Papier- U Schreibwaren / Einzelhandel",
    "sg:phone":"+43 4362 4577325",
    "sg:postcode":"5400",
    "sg:province":"Salzburg",
    "wof:name":"Paperworld - RePo HandelsgesmbH",
    "wof:placetype":"venue"
},
  "geometry": {"coordinates":[13.0895252228,47.6841812134],"type":"Point"}
}