{
  "type": "Feature",
  "properties": {
    "addr:full":"Taxlberg 2 Steinhaus Ober\u00f6sterreich 4641",
    "addr:housenumber":"2",
    "addr:postcode":"4641",
    "addr:street":"Taxlberg;Oberoesterreich",
    "iso:country":"AT",
    "sg:address":"Taxlberg 2",
    "sg:city":"Steinhaus",
    "sg:orig_category":"Fischzucht",
    "sg:phone":"+43 7242 27318",
    "sg:postcode":"4641",
    "sg:province":"Ober\u00f6sterreich",
    "wof:name":"Dietl Christa",
    "wof:placetype":"venue"
},
  "geometry": {"coordinates":[14.0210599899,48.09400177],"type":"Point"}
}