{
  "type": "Feature",
  "properties": {
    "addr:full":"Marktpl 22 Ottensheim Ober\u00f6sterreich 4100",
    "addr:housenumber":"22",
    "addr:postcode":"4100",
    "addr:street":"Marktpl",
    "iso:country":"AT",
    "sg:address":"Marktpl 22",
    "sg:city":"Ottensheim",
    "sg:orig_category":"Tabaktrafiken",
    "sg:phone":"+43 7234 82429",
    "sg:postcode":"4100",
    "sg:province":"Ober\u00f6sterreich",
    "wof:name":"Mayer Gabriele",
    "wof:placetype":"venue"
},
  "geometry": {"coordinates":[14.1757955551,48.3316192627],"type":"Point"}
}