{
  "type": "Feature",
  "properties": {
    "addr:full":"Neukirchen an der Enknach 120 Neukirchen an der Enknach Ober\u00f6sterreich 5145",
    "addr:housenumber":"120",
    "addr:postcode":"5145",
    "addr:street":"Neukirchen An Der Enknach",
    "iso:country":"AT",
    "sg:address":"Neukirchen an der Enknach 120",
    "sg:city":"Neukirchen an der Enknach",
    "sg:classifiers":[
        {
            "category":"Structure",
            "subcategory":"Building",
            "type":"Public Place"
        }
    ],
    "sg:phone":"+43 7729 2235",
    "sg:postcode":"5145",
    "sg:province":"Ober\u00f6sterreich",
    "sg:tags":[
        "canopy"
    ],
    "wof:name":"Richard Kreuzwirth GesmbH",
    "wof:placetype":"venue"
},
  "geometry": {"coordinates":[13.04708004,48.1787986755],"type":"Point"}
}