{
  "type": "Feature",
  "properties": {
    "addr:full":"Pater Engelbert-Str 1 Sattledt Ober\u00f6sterreich 4642",
    "addr:housenumber":"1",
    "addr:postcode":"4642",
    "addr:street":"Pater Engelbert-Str",
    "iso:country":"AT",
    "sg:address":"Pater Engelbert-Str 1",
    "sg:city":"Sattledt",
    "sg:orig_category":"Non-Classified Establishments",
    "sg:phone":"+43 7244 8817",
    "sg:postcode":"4642",
    "sg:province":"Ober\u00f6sterreich",
    "wof:name":"Pfarramt",
    "wof:placetype":"venue"
},
  "geometry": {"coordinates":[14.0563154221,48.07371521],"type":"Point"}
}