{
  "type": "Feature",
  "properties": {
    "iso:country":"AT",
    "sg:address":"Auenweg 102",
    "sg:city":"Klagenfurt",
    "sg:orig_category":"Tierschutz",
    "sg:phone":"+43 4346 3320041",
    "sg:postcode":"9020",
    "sg:province":"K\u00e4rnten",
    "wof:name":"Tierheim Garten Eden",
    "wof:placetype":"venue"
},
  "geometry": {"coordinates":[14.3250198364,46.5982589722],"type":"Point"}
}