{
  "type": "Feature",
  "properties": {
    "iso:country":"AT",
    "sg:address":"Lobminger Strasse 20",
    "sg:city":"Knittelfeld",
    "sg:classifiers":[
        {
            "category":"Retail",
            "subcategory":"Emissions Testing",
            "type":"Services"
        }
    ],
    "sg:phone":"+43 3512 759260",
    "sg:postcode":"8720",
    "sg:province":"Steiermark",
    "sg:tags":[
        "instrument",
        "immission",
        "measurement"
    ],
    "sg:website":"murtac.at",
    "wof:name":"Murtac Me\u00df- und Regeltechnik Analytische Chemie GmbH",
    "wof:placetype":"venue"
},
  "geometry": {"coordinates":[14.8310775757,47.2100524902],"type":"Point"}
}