{
  "type": "Feature",
  "properties": {
    "iso:country":"AT",
    "sg:address":"Bromberger Str 589",
    "sg:city":"Bad Erlach",
    "sg:orig_category":"Ziegeleien",
    "sg:phone":"+43 2627 482210",
    "sg:postcode":"2822",
    "sg:province":"Nieder\u00f6sterreich",
    "wof:name":"Lizzi Ziegelwerk GmbH",
    "wof:placetype":"venue"
},
  "geometry": {"coordinates":[16.2160301208,47.7281303406],"type":"Point"}
}