{
  "type": "Feature",
  "properties": {
    "addr:full":"Etruskerweg 90 Klagenfurt-Viktring K\u00e4rnten 9073",
    "addr:housenumber":"90",
    "addr:postcode":"9073",
    "addr:street":"Etruskerweg;Kaernten",
    "iso:country":"AT",
    "sg:address":"Etruskerweg 90",
    "sg:city":"Klagenfurt-Viktring",
    "sg:orig_category":"Immobilienmakler",
    "sg:phone":"+43 463 282829",
    "sg:postcode":"9073",
    "sg:province":"K\u00e4rnten",
    "wof:name":"Safron Helma Dr",
    "wof:placetype":"venue"
},
  "geometry": {"coordinates":[14.2749090195,46.5975456238],"type":"Point"}
}