{
  "type": "Feature",
  "properties": {
    "addr:full":"Pfaffst\u00e4ttner Str 4 Gumpoldskirchen Nieder\u00f6sterreich 2352",
    "addr:housenumber":"4",
    "addr:postcode":"2352",
    "addr:street":"Str",
    "iso:country":"AT",
    "sg:address":"Pfaffst\u00e4ttner Str 4",
    "sg:city":"Gumpoldskirchen",
    "sg:orig_category":"Installationsunternehmen",
    "sg:phone":"+43 2252 63488",
    "sg:postcode":"2352",
    "sg:province":"Nieder\u00f6sterreich",
    "wof:name":"Seidel Werner KEG",
    "wof:placetype":"venue"
},
  "geometry": {"coordinates":[16.2873897552,48.0398178101],"type":"Point"}
}