{
  "type": "Feature",
  "properties": {
    "addr:full":"Simmeringer Hauptstrasse 197 Wien Wien 1110",
    "addr:housenumber":"197",
    "addr:postcode":"1110",
    "addr:street":"Simmeringer Hauptstrasse",
    "iso:country":"AT",
    "sg:address":"Simmeringer Hauptstrasse 197",
    "sg:city":"Wien",
    "sg:classifiers":[
        {
            "category":"Home & Garden",
            "subcategory":"Building Materials",
            "type":"Retail Goods"
        }
    ],
    "sg:phone":"+43 1 7671032",
    "sg:postcode":"1110",
    "sg:province":"Wien",
    "sg:tags":[
        "installation",
        "electric"
    ],
    "wof:name":"M\u00fcller & Miksch Ges.m.b.H.",
    "wof:placetype":"venue"
},
  "geometry": {"coordinates":[16.4243450165,48.1667556763],"type":"Point"}
}