{
  "type": "Feature",
  "properties": {
    "addr:full":"Liechtensteinstrasse 39 Wien Wien 1090",
    "addr:housenumber":"39",
    "addr:postcode":"1090",
    "addr:street":"Liechtensteinstrasse",
    "iso:country":"AT",
    "sg:address":"Liechtensteinstrasse 39",
    "sg:city":"Wien",
    "sg:classifiers":[
        {
            "category":"Home & Garden",
            "subcategory":"Building Materials",
            "type":"Retail Goods"
        }
    ],
    "sg:phone":"+43 1 3172244",
    "sg:postcode":"1090",
    "sg:province":"Wien",
    "sg:tags":[
        "tile",
        "granite"
    ],
    "wof:name":"Viktor Kuhn Fliesen",
    "wof:placetype":"venue"
},
  "geometry": {"coordinates":[16.3596439362,48.2210693359],"type":"Point"}
}