{
  "type": "Feature",
  "properties": {
    "addr:full":"Effingergasse 27-29 Wien Wien 1160",
    "addr:postcode":"27-29;1160",
    "addr:street":"Effingergasse",
    "iso:country":"AT",
    "sg:address":"Effingergasse 27-29",
    "sg:city":"Wien",
    "sg:classifiers":[
        {
            "category":"Shopping",
            "type":"Retail Goods"
        }
    ],
    "sg:phone":"+43 4314 861286",
    "sg:postcode":"1160",
    "sg:province":"Wien",
    "sg:tags":[
        "finished",
        "-",
        "metallic"
    ],
    "wof:name":"A. PUTZ G\u00d6RG GMBH",
    "wof:placetype":"venue"
},
  "geometry": {"coordinates":[16.3151416779,48.2192611694],"type":"Point"}
}