{
  "type": "Feature",
  "properties": {
    "addr:full":"Gst\u00e4tteng 4 Salzburg Salzburg 5020",
    "addr:housenumber":"4",
    "addr:postcode":"5020",
    "addr:street":"Gstaetteng;Salzburg",
    "iso:country":"AT",
    "sg:address":"Gst\u00e4tteng 4",
    "sg:city":"Salzburg",
    "sg:orig_category":"Spielwaren U Spiele",
    "sg:phone":"+43 662 840212",
    "sg:postcode":"5020",
    "sg:province":"Salzburg",
    "wof:name":"Rocky's B\u00e4renh\u00f6hle",
    "wof:placetype":"venue"
},
  "geometry": {"coordinates":[13.0393724442,47.8006668091],"type":"Point"}
}