{
  "type": "Feature",
  "properties": {
    "iso:country":"AT",
    "sg:address":"Bachstr. 75 ",
    "sg:city":"Gnigl",
    "sg:classifiers":[
        {
            "category":"Parking",
            "subcategory":"Lot",
            "type":"Transportation"
        }
    ],
    "sg:phone":"+43 4366 285850",
    "sg:postcode":"5023",
    "sg:province":"Salzburg",
    "sg:tags":[
        "transport",
        "road"
    ],
    "wof:name":"WELZ INTERNATIONALE SPEDITIONS GMBH",
    "wof:placetype":"venue"
},
  "geometry": {"coordinates":[13.0641803741,47.8239402771],"type":"Point"}
}