{
  "type": "Feature",
  "properties": {
    "addr:full":"Genochpl 15 Wien Wien 1220",
    "addr:housenumber":"15",
    "addr:postcode":"1220",
    "addr:street":"Genochpl",
    "iso:country":"AT",
    "sg:address":"Genochpl 15",
    "sg:city":"Wien",
    "sg:orig_category":"Blumeneinzelhandel",
    "sg:phone":"+43 1 2836757",
    "sg:postcode":"1220",
    "sg:province":"Wien",
    "wof:name":"Tilly Blumen - Hinterecker",
    "wof:placetype":"venue"
},
  "geometry": {"coordinates":[16.4552955627,48.2281455994],"type":"Point"}
}