{
  "type": "Feature",
  "properties": {
    "iso:country":"AT",
    "sg:address":"Pitze 602",
    "sg:city":"S\u00f6lden",
    "sg:orig_category":"Reisen, Tourismusinfo",
    "sg:phone":"+43 5254 2089",
    "sg:postcode":"6450",
    "sg:province":"Tirol",
    "sg:website":"http://www.raphaela.at",
    "wof:name":"Garni Raphaela",
    "wof:placetype":"venue"
},
  "geometry": {"coordinates":[11.0105848312,46.9527282715],"type":"Point"}
}