{
  "type": "Feature",
  "properties": {
    "iso:country":"AT",
    "sg:address":"Maria-Pfeiffer-Str 8",
    "sg:city":"Stra\u00dfgang",
    "sg:orig_category":"Lebensmittel / Einzelhandel",
    "sg:phone":"+43 4331 6244365",
    "sg:postcode":"8054",
    "sg:province":"Steiermark",
    "wof:name":"Hofer KG",
    "wof:placetype":"venue"
},
  "geometry": {"coordinates":[15.4088106155,47.0141906738],"type":"Point"}
}