{
  "type": "Feature",
  "properties": {
    "addr:full":"Leonfeldner Str 101a Linz Ober\u00f6sterreich 4040",
    "addr:postcode":"4040",
    "addr:street":"Str 101A",
    "iso:country":"AT",
    "sg:address":"Leonfeldner Str 101a",
    "sg:city":"Linz",
    "sg:classifiers":[
        {
            "category":"Shopping",
            "subcategory":"Party Supplies",
            "type":"Retail Goods"
        }
    ],
    "sg:phone":"+43 4366 45033937",
    "sg:postcode":"4040",
    "sg:province":"Ober\u00f6sterreich",
    "sg:tags":[
        "u",
        "lichtanlagen",
        "ton-"
    ],
    "wof:name":"Vicom Veranstaltungstechnik",
    "wof:placetype":"venue"
},
  "geometry": {"coordinates":[14.2873573303,48.3304672241],"type":"Point"}
}