{
  "type": "Feature",
  "properties": {
    "addr:full":"Weidmanng 21 Wien Wien 1170",
    "addr:housenumber":"21",
    "addr:postcode":"1170",
    "addr:street":"Weidmanng",
    "iso:country":"AT",
    "sg:address":"Weidmanng 21",
    "sg:city":"Wien",
    "sg:orig_category":"Transportunternehmen",
    "sg:phone":"+43 1 40542760",
    "sg:postcode":"1170",
    "sg:province":"Wien",
    "wof:name":"Lasch Michael & Co GesmbH",
    "wof:placetype":"venue"
},
  "geometry": {"coordinates":[16.332906723,48.2218780518],"type":"Point"}
}