{
  "type": "Feature",
  "properties": {
    "addr:full":"Zei\u00dfstr 20 Ebenthal in K\u00e4rnten K\u00e4rnten 9065",
    "addr:housenumber":"20",
    "addr:postcode":"9065",
    "addr:street":"Zeissstr;Kaernten",
    "iso:country":"AT",
    "sg:address":"Zei\u00dfstr 20",
    "sg:city":"Ebenthal in K\u00e4rnten",
    "sg:orig_category":"Anlagenbau U -Technik",
    "sg:phone":"+43 4346 3740088",
    "sg:postcode":"9065",
    "sg:province":"K\u00e4rnten",
    "wof:name":"AB & Z Anlagenbau- u Zerkleinerungstechnik GmbH",
    "wof:placetype":"venue"
},
  "geometry": {"coordinates":[14.3621454239,46.6070404053],"type":"Point"}
}