{
  "type": "Feature",
  "properties": {
    "addr:full":"Schmiedingerstr 69a Salzburg Salzburg 5020",
    "addr:housenumber":"69a",
    "addr:postcode":"5020",
    "addr:street":"Schmiedingerstr;Salzburg",
    "iso:country":"AT",
    "sg:address":"Schmiedingerstr 69a",
    "sg:city":"Salzburg",
    "sg:orig_category":"Spenglereien",
    "sg:phone":"+43 664 2026917",
    "sg:postcode":"5020",
    "sg:province":"Salzburg",
    "wof:name":"Notsch Alfons",
    "wof:placetype":"venue"
},
  "geometry": {"coordinates":[13.022403717,47.8283042908],"type":"Point"}
}