{
  "type": "Feature",
  "properties": {
    "iso:country":"AT",
    "sg:address":"Pappenheimgasse 37/15",
    "sg:city":"Wien",
    "sg:classifiers":[
        {
            "category":"Home & Garden",
            "subcategory":"Building Materials",
            "type":"Retail Goods"
        }
    ],
    "sg:phone":"+43 1 3749152",
    "sg:postcode":"1200",
    "sg:province":"Wien",
    "sg:tags":[
        "insect",
        "screen"
    ],
    "wof:name":"Soljal- Inh. Solodovskij Michael",
    "wof:placetype":"venue"
},
  "geometry": {"coordinates":[16.3705234528,48.2340736389],"type":"Point"}
}