{
  "type": "Feature",
  "properties": {
    "iso:country":"AT",
    "sg:address":"Franz M Felder-Str 6/1",
    "sg:city":"Dornbirn",
    "sg:orig_category":"Immobilienverwaltungen",
    "sg:phone":"+43 5572 23975",
    "sg:postcode":"6850",
    "sg:province":"Vorarlberg",
    "wof:name":"ILF Immobilien-Leasing-FinanzierungsgesmbH & Co KG",
    "wof:placetype":"venue"
},
  "geometry": {"coordinates":[9.7412796021,47.4169883728],"type":"Point"}
}