{
  "type": "Feature",
  "properties": {
    "addr:full":"Salzburger Str 15 Bad Hofgastein Salzburg 5630",
    "addr:housenumber":"15",
    "addr:postcode":"5630",
    "addr:street":"Salzburger Str;Salzburg",
    "iso:country":"AT",
    "sg:address":"Salzburger Str 15",
    "sg:city":"Bad Hofgastein",
    "sg:orig_category":"Appartements / Ferienwohnungen",
    "sg:phone":"+43 6432 71030",
    "sg:postcode":"5630",
    "sg:province":"Salzburg",
    "wof:name":"Ferienhaus Birgit",
    "wof:placetype":"venue"
},
  "geometry": {"coordinates":[13.1044397354,47.1726875305],"type":"Point"}
}