{
  "type": "Feature",
  "properties": {
    "addr:full":"Moschingerg 6 Wien Wien 1140",
    "addr:housenumber":"6",
    "addr:postcode":"1140",
    "addr:street":"Moschingerg",
    "iso:country":"AT",
    "sg:address":"Moschingerg 6",
    "sg:city":"Wien",
    "sg:orig_category":"Alarmanlagen U Sicherheitssysteme",
    "sg:phone":"+43 4313 679453",
    "sg:postcode":"1140",
    "sg:province":"Wien",
    "wof:name":"SALUS Sicherheits-Systeme GmbH",
    "wof:placetype":"venue"
},
  "geometry": {"coordinates":[16.2411384583,48.219997406],"type":"Point"}
}