{
  "type": "Feature",
  "properties": {
    "iso:country":"AT",
    "sg:address":"Huben 40",
    "sg:city":"L\u00e4ngenfeld",
    "sg:orig_category":"Pensionen / Privatzimmer",
    "sg:phone":"+43 5253 5806",
    "sg:postcode":"6444",
    "sg:province":"Tirol",
    "wof:name":"Haus Stefan",
    "wof:placetype":"venue"
},
  "geometry": {"coordinates":[10.9703655243,47.0431976318],"type":"Point"}
}