{
  "type": "Feature",
  "properties": {
    "addr:full":"Am Terminal 1b Werndorf Steiermark 8402",
    "addr:housenumber":"1b",
    "addr:postcode":"8402",
    "addr:street":"Am Terminal",
    "iso:country":"AT",
    "sg:address":"Am Terminal 1b",
    "sg:city":"Werndorf",
    "sg:orig_category":"Speditionen",
    "sg:phone":"+43 4331 658340124",
    "sg:postcode":"8402",
    "sg:province":"Steiermark",
    "wof:name":"J\u00f6bstl KG, J\u00f6bstl Group, Logistics, Warehousing, Seefracht",
    "wof:placetype":"venue"
},
  "geometry": {"coordinates":[15.4903116226,46.9242973328],"type":"Point"}
}