{
  "type": "Feature",
  "properties": {
    "addr:full":"Morsbacher Str 2 Kufstein Tirol 6330",
    "addr:housenumber":"2",
    "addr:postcode":"6330",
    "addr:street":"Str;Tirol",
    "iso:country":"AT",
    "sg:address":"Morsbacher Str 2",
    "sg:city":"Kufstein",
    "sg:orig_category":"Fu\u00c3\u0178pflege U Fu\u00c3\u0178pflegesalons",
    "sg:phone":"+43 4353 7263986",
    "sg:postcode":"6330",
    "sg:province":"Tirol",
    "wof:name":"Kopsch Peter",
    "wof:placetype":"venue"
},
  "geometry": {"coordinates":[12.1536331177,47.5880432129],"type":"Point"}
}