{
  "type": "Feature",
  "properties": {
    "addr:full":"Nr 6 Moosbach Ober\u00f6sterreich 5271",
    "addr:postcode":"5271",
    "addr:street":"Nr;Moosbach",
    "iso:country":"AT",
    "sg:address":"Nr 6",
    "sg:city":"Moosbach",
    "sg:orig_category":"Installationsunternehmen",
    "sg:phone":"+43 7724 6494",
    "sg:postcode":"5271",
    "sg:province":"Ober\u00f6sterreich",
    "wof:name":"Priller Hermann",
    "wof:placetype":"venue"
},
  "geometry": {"coordinates":[13.165017128,48.2062492371],"type":"Point"}
}