{
  "type": "Feature",
  "properties": {
    "addr:full":"S\u00e4gerweg 5 Rankweil Vorarlberg 6830",
    "addr:housenumber":"5",
    "addr:postcode":"6830",
    "addr:street":"Saegerweg",
    "iso:country":"AT",
    "sg:address":"S\u00e4gerweg 5",
    "sg:city":"Rankweil",
    "sg:orig_category":"Transportunternehmen",
    "sg:phone":"+43 5522 42098",
    "sg:postcode":"6830",
    "sg:province":"Vorarlberg",
    "wof:name":"Reith G\u00fcnther",
    "wof:placetype":"venue"
},
  "geometry": {"coordinates":[9.6544542313,47.2766838074],"type":"Point"}
}