{
  "type": "Feature",
  "properties": {
    "iso:country":"AT",
    "sg:address":"Haidweg 1",
    "sg:city":"Riezlern",
    "sg:classifiers":[
        {
            "category":"Home & Garden",
            "subcategory":"Building Materials",
            "type":"Retail Goods"
        }
    ],
    "sg:phone":"+43 4355 1754370",
    "sg:postcode":"6991",
    "sg:province":"Vorarlberg",
    "sg:tags":[
        "baustoffe",
        "-material",
        "u"
    ],
    "wof:name":"Matt Kleinwalsertaler Brennstoffhandel GmbH & Co KG",
    "wof:placetype":"venue"
},
  "geometry": {"coordinates":[10.1952047348,47.3619651794],"type":"Point"}
}