{
  "type": "Feature",
  "properties": {
    "addr:full":"Schulstr 7 Oberndorf an der Melk Nieder\u00f6sterreich 3281",
    "addr:housenumber":"7",
    "addr:postcode":"3281",
    "addr:street":"Schulstr;Niederoesterreich",
    "iso:country":"AT",
    "sg:address":"Schulstr 7",
    "sg:city":"Oberndorf an der Melk",
    "sg:orig_category":"Volksschulen",
    "sg:phone":"+43 4374 837029",
    "sg:postcode":"3281",
    "sg:province":"Nieder\u00f6sterreich",
    "wof:name":"Volksschule u allgemeine Sonderschule",
    "wof:placetype":"venue"
},
  "geometry": {"coordinates":[15.2212657928,48.0633430481],"type":"Point"}
}