{
  "type": "Feature",
  "properties": {
    "addr:full":"Ossiacher Zeile 68 Villach K\u00e4rnten 9500",
    "addr:housenumber":"68",
    "addr:postcode":"9500",
    "addr:street":"Ossiacher Zeile;Kaernten",
    "iso:country":"AT",
    "sg:address":"Ossiacher Zeile 68",
    "sg:city":"Villach",
    "sg:orig_category":"Fahrradreparatur",
    "sg:phone":"+43 4242 430743",
    "sg:postcode":"9500",
    "sg:province":"K\u00e4rnten",
    "wof:name":"Rad-Sport A K\u00e4fer",
    "wof:placetype":"venue"
},
  "geometry": {"coordinates":[13.8601894379,46.6169242859],"type":"Point"}
}