{
  "type": "Feature",
  "properties": {
    "addr:full":"Sportplatzstr 339 Mayrhofen Tirol 6290",
    "addr:housenumber":"339",
    "addr:postcode":"6290",
    "addr:street":"Mayrhofen Tirol",
    "iso:country":"AT",
    "sg:address":"Sportplatzstr 339",
    "sg:city":"Mayrhofen",
    "sg:orig_category":"Handarbeiten",
    "sg:phone":"+43 5285 62148",
    "sg:postcode":"6290",
    "sg:province":"Tirol",
    "wof:name":"Maria's Handarbeitsst\u00fcberl",
    "wof:placetype":"venue"
},
  "geometry": {"coordinates":[11.8657283783,47.1663017273],"type":"Point"}
}