{
  "type": "Feature",
  "properties": {
    "iso:country":"AT",
    "sg:address":"Burgg 16",
    "sg:city":"Graz",
    "sg:orig_category":"Werbeagenturen",
    "sg:phone":"+43 316 8159760",
    "sg:postcode":"8010",
    "sg:province":"Steiermark",
    "wof:name":"conneXion - Inh Clemens Rant",
    "wof:placetype":"venue"
},
  "geometry": {"coordinates":[15.4448432922,47.0696144104],"type":"Point"}
}