{
  "type": "Feature",
  "properties": {
    "addr:full":"Gamper-Strasse-S\u00fcd 3 Hallein Salzburg 5400",
    "addr:housenumber":"3",
    "addr:postcode":"5400",
    "addr:street":"Gamper-Strasse-Sued;Salzburg",
    "iso:country":"AT",
    "sg:address":"Gamper-Strasse-S\u00fcd 3",
    "sg:city":"Hallein",
    "sg:classifiers":[
        {
            "category":"Real Estate",
            "subcategory":"Architect",
            "type":"Services"
        }
    ],
    "sg:phone":"+43 6245 800570",
    "sg:postcode":"5400",
    "sg:province":"Salzburg",
    "sg:tags":[
        "paving"
    ],
    "wof:name":"Dipl.-Ing. M\u00f6rtinger-Grohmann Tief-, Hoch- und Stra\u00dfenbau Ges.m.b.H. & Co KG",
    "wof:placetype":"venue"
},
  "geometry": {"coordinates":[13.0926103592,47.6814613342],"type":"Point"}
}