{
  "type": "Feature",
  "properties": {
    "addr:full":"Industriestrasse 2 Marz Burgenland 7221",
    "addr:housenumber":"2",
    "addr:postcode":"7221",
    "addr:street":"Industriestrasse",
    "iso:country":"AT",
    "sg:address":"Industriestrasse 2",
    "sg:city":"Marz",
    "sg:orig_category":"Plastic Buckles",
    "sg:phone":"+43 2626 624550",
    "sg:postcode":"7221",
    "sg:province":"Burgenland",
    "sg:website":"www.ykk.at",
    "wof:name":"YKK Austria GmbH",
    "wof:placetype":"venue"
},
  "geometry": {"coordinates":[16.4114952087,47.7252235413],"type":"Point"}
}