{
  "type": "Feature",
  "properties": {
    "addr:full":"Kerng 10 Loosdorf Nieder\u00f6sterreich 3382",
    "addr:housenumber":"10",
    "addr:postcode":"3382",
    "addr:street":"Kerng",
    "iso:country":"AT",
    "sg:address":"Kerng 10",
    "sg:city":"Loosdorf",
    "sg:orig_category":"Friseure U Frisiersalons",
    "sg:phone":"+43 4327 542112",
    "sg:postcode":"3382",
    "sg:province":"Nieder\u00f6sterreich",
    "wof:name":"Friesierstube Margit Dobler",
    "wof:placetype":"venue"
},
  "geometry": {"coordinates":[15.4109554291,48.223651886],"type":"Point"}
}