{
  "type": "Feature",
  "properties": {
    "addr:full":"Meiselstr 7 Wien Wien 1150",
    "addr:housenumber":"7",
    "addr:postcode":"1150",
    "addr:street":"Meiselstr",
    "iso:country":"AT",
    "sg:address":"Meiselstr 7",
    "sg:city":"Wien",
    "sg:orig_category":"Textilwaren / Einzelhandel",
    "sg:phone":"+43 1 9820326",
    "sg:postcode":"1150",
    "sg:province":"Wien",
    "wof:name":"Eybner Wolfgang",
    "wof:placetype":"venue"
},
  "geometry": {"coordinates":[16.3214244843,48.1973724365],"type":"Point"}
}