{
  "type": "Feature",
  "properties": {
    "iso:country":"AT",
    "sg:address":"Gumpendorfer Str 37",
    "sg:city":"Wien",
    "sg:orig_category":"Friseure U Frisiersalons",
    "sg:phone":"+43 1 5875759",
    "sg:postcode":"1060",
    "sg:province":"Wien",
    "wof:name":"HAIR COMPANY Inh Denise Jasmin Janda",
    "wof:placetype":"venue"
},
  "geometry": {"coordinates":[16.357837677,48.1985855103],"type":"Point"}
}