{
  "type": "Feature",
  "properties": {
    "addr:full":"Wollzeile 4 Wien Wien 1010",
    "addr:housenumber":"4",
    "addr:postcode":"1010",
    "addr:street":"Wollzeile",
    "iso:country":"AT",
    "sg:address":"Wollzeile 4",
    "sg:city":"Wien",
    "sg:orig_category":"Tabaktrafiken",
    "sg:phone":"+43 1 5127337",
    "sg:postcode":"1010",
    "sg:province":"Wien",
    "wof:name":"Eipeldauer Franz",
    "wof:placetype":"venue"
},
  "geometry": {"coordinates":[16.374004364,48.2092018127],"type":"Point"}
}