{
  "type": "Feature",
  "properties": {
    "addr:full":"Anton-Baumgartner-Str Wien Wien 1230",
    "addr:postcode":"1230",
    "iso:country":"AT",
    "sg:address":"Anton-Baumgartner-Str",
    "sg:city":"Wien",
    "sg:orig_category":"Non-Classified Establishments",
    "sg:phone":"+43 4316 670250",
    "sg:postcode":"1230",
    "sg:province":"Wien",
    "wof:name":"TAXI-TEL Standplatztelefon Betriebs GmbH",
    "wof:placetype":"venue"
},
  "geometry": {"coordinates":[16.3275794983,48.1523704529],"type":"Point"}
}