{
  "type": "Feature",
  "properties": {
    "iso:country":"AT",
    "sg:address":"Kufsteiner Wald 4",
    "sg:city":"Kufstein",
    "sg:orig_category":"Cad For The Textile Industry",
    "sg:phone":"+43 5372 69930",
    "sg:postcode":"6330",
    "sg:province":"Tirol",
    "sg:website":"stork-stk.com",
    "wof:name":"Schablonentechnik Kufstein AG",
    "wof:placetype":"venue"
},
  "geometry": {"coordinates":[12.1459503174,47.5660018921],"type":"Point"}
}