{
  "type": "Feature",
  "properties": {
    "addr:full":"Schulstr 54 Marz Burgenland 7221",
    "addr:housenumber":"54",
    "addr:postcode":"7221",
    "addr:street":"Schulstr",
    "iso:country":"AT",
    "sg:address":"Schulstr 54",
    "sg:city":"Marz",
    "sg:orig_category":"Tabaktrafiken",
    "sg:phone":"+43 2626 63672",
    "sg:postcode":"7221",
    "sg:province":"Burgenland",
    "wof:name":"Sailer Hannelore",
    "wof:placetype":"venue"
},
  "geometry": {"coordinates":[16.4134140015,47.7140541077],"type":"Point"}
}