{
  "type": "Feature",
  "properties": {
    "iso:country":"AT",
    "sg:address":"Nr 21",
    "sg:city":"Fladnitz an der Teichalm",
    "sg:orig_category":"Pensionen / Privatzimmer",
    "sg:phone":"+43 3179 6147",
    "sg:postcode":"8163",
    "sg:province":"Steiermark",
    "wof:name":"Bauernhof Weber",
    "wof:placetype":"venue"
},
  "geometry": {"coordinates":[15.4762983322,47.2858695984],"type":"Point"}
}