{
  "type": "Feature",
  "properties": {
    "addr:full":"Mayr Melnhof-Str 32 Frohnleiten Steiermark 8130",
    "addr:housenumber":"32",
    "addr:postcode":"8130",
    "iso:country":"AT",
    "sg:address":"Mayr Melnhof-Str 32",
    "sg:city":"Frohnleiten",
    "sg:orig_category":"Forstverwaltungen",
    "sg:phone":"+43 3126 25010",
    "sg:postcode":"8130",
    "sg:province":"Steiermark",
    "wof:name":"Goess-Saurau Schlo\u00df Pfannberg",
    "wof:placetype":"venue"
},
  "geometry": {"coordinates":[15.3217287064,47.2615776062],"type":"Point"}
}