{
  "type": "Feature",
  "properties": {
    "iso:country":"AT",
    "sg:address":"Juns 598",
    "sg:city":"Tux",
    "sg:orig_category":"Maler, Anstreicher U Lackierer",
    "sg:phone":"+43 4352 8787747",
    "sg:postcode":"6293",
    "sg:province":"Tirol",
    "wof:name":"Schneeberger Konrad",
    "wof:placetype":"venue"
},
  "geometry": {"coordinates":[11.7115001678,47.1395645142],"type":"Point"}
}