{
  "type": "Feature",
  "properties": {
    "addr:full":"Hofmark 9 Wagrain Salzburg 5602",
    "addr:housenumber":"9",
    "addr:postcode":"5602",
    "addr:street":"Hofmark;Salzburg",
    "iso:country":"AT",
    "sg:address":"Hofmark 9",
    "sg:city":"Wagrain",
    "sg:classifiers":[
        {
            "category":"Travel",
            "subcategory":"Hotels & Motels",
            "type":"Entertainment"
        }
    ],
    "sg:phone":"+43 6413 73330",
    "sg:postcode":"5602",
    "sg:province":"Salzburg",
    "sg:website":"sporthotel.at",
    "wof:name":"Sporthotel Wagrain",
    "wof:placetype":"venue"
},
  "geometry": {"coordinates":[13.3020029068,47.3274917603],"type":"Point"}
}