{
  "type": "Feature",
  "properties": {
    "addr:full":"Beimrohrweg 3 Gramastetten Ober\u00f6sterreich 4201",
    "addr:housenumber":"3",
    "addr:postcode":"4201",
    "addr:street":"Beimrohrweg",
    "iso:country":"AT",
    "sg:address":"Beimrohrweg 3",
    "sg:city":"Gramastetten",
    "sg:orig_category":"Anlagenbau U -Technik",
    "sg:phone":"+43 4372 3920070",
    "sg:postcode":"4201",
    "sg:province":"Ober\u00f6sterreich",
    "wof:name":"JBV Indurest Engineering GmbH",
    "wof:placetype":"venue"
},
  "geometry": {"coordinates":[14.1990671158,48.3792572021],"type":"Point"}
}