{
  "type": "Feature",
  "properties": {
    "addr:full":"Alois-Auer-Str 14 Wels Ober\u00f6sterreich 4600",
    "addr:housenumber":"14",
    "addr:postcode":"4600",
    "addr:street":"Alois-Auer-Str;Oberoesterreich",
    "iso:country":"AT",
    "sg:address":"Alois-Auer-Str 14",
    "sg:city":"Wels",
    "sg:orig_category":"Architekten",
    "sg:phone":"+43 4372 4247641",
    "sg:postcode":"4600",
    "sg:province":"Ober\u00f6sterreich",
    "wof:name":"Architekturb\u00fcro Gellner",
    "wof:placetype":"venue"
},
  "geometry": {"coordinates":[14.0276002884,48.1630783081],"type":"Point"}
}