{
  "type": "Feature",
  "properties": {
    "addr:full":"Au 50 Bad Wimsbach-Neydharting Ober\u00f6sterreich 4654",
    "addr:housenumber":"50",
    "addr:postcode":"4654",
    "addr:street":"Au",
    "iso:country":"AT",
    "sg:address":"Au 50",
    "sg:city":"Bad Wimsbach-Neydharting",
    "sg:orig_category":"Orgel- U Harmoniumbau",
    "sg:phone":"+43 4372 452562511",
    "sg:postcode":"4654",
    "sg:province":"Ober\u00f6sterreich",
    "wof:name":"Kaltenbrunner - ORGELBAU",
    "wof:placetype":"venue"
},
  "geometry": {"coordinates":[13.9122600555,48.0315513611],"type":"Point"}
}