{
  "type": "Feature",
  "properties": {
    "addr:full":"Eisenst\u00e4dter Str 16 Donnerskirchen Burgenland 7082",
    "addr:housenumber":"16",
    "addr:postcode":"7082",
    "addr:street":"Str",
    "iso:country":"AT",
    "sg:address":"Eisenst\u00e4dter Str 16",
    "sg:city":"Donnerskirchen",
    "sg:orig_category":"Rebschulen",
    "sg:phone":"+43 2683 8531",
    "sg:postcode":"7082",
    "sg:province":"Burgenland",
    "wof:name":"Mayer Josef",
    "wof:placetype":"venue"
},
  "geometry": {"coordinates":[16.6475734711,47.8928031921],"type":"Point"}
}