{
  "type": "Feature",
  "properties": {
    "iso:country":"AT",
    "sg:address":"Gailtalstr 4",
    "sg:city":"Hermagor",
    "sg:orig_category":"Molkereien U Molkereiprodukte",
    "sg:phone":"+43 4342 822852",
    "sg:postcode":"9620",
    "sg:province":"K\u00e4rnten",
    "wof:name":"K\u00e4rntnermilch - Verkaufsmarkt",
    "wof:placetype":"venue"
},
  "geometry": {"coordinates":[13.3784599304,46.6293182373],"type":"Point"}
}