{
  "type": "Feature",
  "properties": {
    "addr:full":"Anton-Bruckner-Str 4 Ansfelden Ober\u00f6sterreich 4052",
    "addr:housenumber":"4",
    "addr:postcode":"4052",
    "addr:street":"Anton-Bruckner-Str",
    "iso:country":"AT",
    "sg:address":"Anton-Bruckner-Str 4",
    "sg:city":"Ansfelden",
    "sg:orig_category":"Landwirtschaftliche Produkte",
    "sg:phone":"+43 7229 87064",
    "sg:postcode":"4052",
    "sg:province":"Ober\u00f6sterreich",
    "wof:name":"Schreiberhuber Alfred Dipl-Ing Dr",
    "wof:placetype":"venue"
},
  "geometry": {"coordinates":[14.2917165756,48.2122535706],"type":"Point"}
}