{
  "type": "Feature",
  "properties": {
    "addr:full":"Bahnhofpl 1 Krems an der Donau Nieder\u00f6sterreich 3500",
    "addr:housenumber":"1",
    "addr:postcode":"3500",
    "addr:street":"Bahnhofpl",
    "iso:country":"AT",
    "sg:address":"Bahnhofpl 1",
    "sg:city":"Krems an der Donau",
    "sg:orig_category":"Tabaktrafiken",
    "sg:phone":"+43 2732 76176",
    "sg:postcode":"3500",
    "sg:province":"Nieder\u00f6sterreich",
    "wof:name":"Jurcsa Birgitte",
    "wof:placetype":"venue"
},
  "geometry": {"coordinates":[15.6053743362,48.4094352722],"type":"Point"}
}