{
  "type": "Feature",
  "properties": {
    "addr:full":"Mariafeldstr 18 Krenglbach Ober\u00f6sterreich 4631",
    "addr:housenumber":"18",
    "addr:postcode":"4631",
    "addr:street":"Mariafeldstr",
    "iso:country":"AT",
    "sg:address":"Mariafeldstr 18",
    "sg:city":"Krenglbach",
    "sg:classifiers":[
        {
            "category":"Professional",
            "subcategory":"Computer Services",
            "type":"Services"
        }
    ],
    "sg:phone":"+43 4369 910120218",
    "sg:postcode":"4631",
    "sg:province":"Ober\u00f6sterreich",
    "sg:tags":[
        "software"
    ],
    "wof:name":"cmaxmedia",
    "wof:placetype":"venue"
},
  "geometry": {"coordinates":[13.954867363,48.2035179138],"type":"Point"}
}