{
  "type": "Feature",
  "properties": {
    "addr:full":"Huglg 9 Wien Wien 1150",
    "addr:housenumber":"9",
    "addr:postcode":"1150",
    "addr:street":"Huglg",
    "iso:country":"AT",
    "sg:address":"Huglg 9",
    "sg:city":"Wien",
    "sg:orig_category":"Autolackierereien",
    "sg:phone":"+43 4319 8221560",
    "sg:postcode":"1150",
    "sg:province":"Wien",
    "sg:website":"swoboda-karosserie.at",
    "wof:name":"Swoboda Karosseriebau u Reparaturen GesmbH",
    "wof:placetype":"venue"
},
  "geometry": {"coordinates":[16.324886322,48.1980400085],"type":"Point"}
}