{
  "type": "Feature",
  "properties": {
    "addr:full":"Dominikanerg 7 Graz Steiermark 8020",
    "addr:housenumber":"7",
    "addr:postcode":"8020",
    "addr:street":"Dominikanerg",
    "iso:country":"AT",
    "sg:address":"Dominikanerg 7",
    "sg:city":"Graz",
    "sg:orig_category":"Maler, Anstreicher U Lackierer",
    "sg:phone":"+43 316 713793",
    "sg:postcode":"8020",
    "sg:province":"Steiermark",
    "wof:name":"Robnik Franz",
    "wof:placetype":"venue"
},
  "geometry": {"coordinates":[15.4299192429,47.0703163147],"type":"Point"}
}