{
  "type": "Feature",
  "properties": {
    "addr:full":"Am Limberg 24b Zell am See Salzburg 5700",
    "addr:housenumber":"24b",
    "addr:postcode":"5700",
    "addr:street":"Am Limberg;Salzburg",
    "iso:country":"AT",
    "sg:address":"Am Limberg 24b",
    "sg:city":"Zell am See",
    "sg:orig_category":"Webdesign",
    "sg:phone":"+43 4365 4255725",
    "sg:postcode":"5700",
    "sg:province":"Salzburg",
    "wof:name":"way2web - Ing Christoph Mayr",
    "wof:placetype":"venue"
},
  "geometry": {"coordinates":[12.770318985,47.2955627441],"type":"Point"}
}