{
  "type": "Feature",
  "properties": {
    "addr:full":"Nobisweg 20 Hellmons\u00f6dt Ober\u00f6sterreich 4202",
    "addr:housenumber":"20",
    "addr:postcode":"4202",
    "addr:street":"Nobisweg;Oberoesterreich",
    "iso:country":"AT",
    "sg:address":"Nobisweg 20",
    "sg:city":"Hellmons\u00f6dt",
    "sg:orig_category":"Glasereien",
    "sg:phone":"+43 7215 2828",
    "sg:postcode":"4202",
    "sg:province":"Ober\u00f6sterreich",
    "wof:name":"Glasstudio f\u00fcr Kunstverglasungen Ing Oskar Sitz",
    "wof:placetype":"venue"
},
  "geometry": {"coordinates":[14.2739610672,48.409526825],"type":"Point"}
}