{
  "type": "Feature",
  "properties": {
    "addr:full":"Wagnastr 16a Leibnitz Steiermark 8430",
    "addr:housenumber":"16a",
    "addr:postcode":"8430",
    "addr:street":"Wagnastr;Steiermark",
    "iso:country":"AT",
    "sg:address":"Wagnastr 16a",
    "sg:city":"Leibnitz",
    "sg:orig_category":"Schilder",
    "sg:phone":"+43 3452 853880",
    "sg:postcode":"8430",
    "sg:province":"Steiermark",
    "wof:name":"Kratzer Karl",
    "wof:placetype":"venue"
},
  "geometry": {"coordinates":[15.5432987213,46.7760124207],"type":"Point"}
}