{
  "type": "Feature",
  "properties": {
    "addr:full":"Heidegasse 2 St. Margarethen im Burgenland Burgenland 7062",
    "addr:housenumber":"2",
    "addr:postcode":"7062",
    "addr:street":"Heidegasse",
    "iso:country":"AT",
    "sg:address":"Heidegasse 2",
    "sg:city":"St. Margarethen im Burgenland",
    "sg:classifiers":[
        {
            "category":"Home & Garden",
            "subcategory":"Hardware",
            "type":"Retail Goods"
        }
    ],
    "sg:phone":"+43 2680 2217",
    "sg:postcode":"7062",
    "sg:province":"Burgenland",
    "sg:tags":[
        "steel",
        "stainless",
        "banister"
    ],
    "sg:website":"granabetter.at",
    "wof:name":"Ing. Thomas Granabetter",
    "wof:placetype":"venue"
},
  "geometry": {"coordinates":[16.6067237854,47.8019790649],"type":"Point"}
}