{
  "type": "Feature",
  "properties": {
    "iso:country":"AT",
    "sg:address":"Linzer Str 18",
    "sg:city":"Haag",
    "sg:orig_category":"Autobusse / Service U Vertrieb",
    "sg:phone":"+43 4374 34423020",
    "sg:postcode":"3350",
    "sg:province":"Nieder\u00f6sterreich",
    "wof:name":"Neoplan Omnibus HandelsgesmbH",
    "wof:placetype":"venue"
},
  "geometry": {"coordinates":[14.562371254,48.1130485535],"type":"Point"}
}