{
  "type": "Feature",
  "properties": {
    "addr:full":"Kreuzg 6 Lauterach Vorarlberg 6923",
    "addr:housenumber":"6",
    "addr:postcode":"6923",
    "addr:street":"Kreuzg",
    "iso:country":"AT",
    "sg:address":"Kreuzg 6",
    "sg:city":"Lauterach",
    "sg:orig_category":"Grafische Bedarfsartikel",
    "sg:phone":"+43 4355 7486950",
    "sg:postcode":"6923",
    "sg:province":"Vorarlberg",
    "wof:name":"reico austria GmbH",
    "wof:placetype":"venue"
},
  "geometry": {"coordinates":[9.7204828262,47.4790840149],"type":"Point"}
}