{
  "type": "Feature",
  "properties": {
    "addr:full":"Kaiserstr 18 St. Johann in Tirol Tirol 6380",
    "addr:housenumber":"18",
    "addr:postcode":"6380",
    "addr:street":"Kaiserstr;Tirol",
    "iso:country":"AT",
    "sg:address":"Kaiserstr 18",
    "sg:city":"St. Johann in Tirol",
    "sg:classifiers":[
        {
            "category":"Travel",
            "subcategory":"Hotels & Motels",
            "type":"Entertainment"
        }
    ],
    "sg:phone":"+43 5352 625850",
    "sg:postcode":"6380",
    "sg:province":"Tirol",
    "wof:name":"Hotel-Restaurant Ambiente Br\u00fcckenwirt",
    "wof:placetype":"venue"
},
  "geometry": {"coordinates":[12.424492836,47.5229263306],"type":"Point"}
}