{
  "type": "Feature",
  "properties": {
    "addr:full":"Kegelgasse 21 Wien Wien 1030",
    "addr:housenumber":"21",
    "addr:postcode":"1030",
    "addr:street":"Kegelgasse",
    "iso:country":"AT",
    "sg:address":"Kegelgasse 21",
    "sg:city":"Wien",
    "sg:classifiers":[
        {
            "category":"Manufacturing",
            "subcategory":"Signs",
            "type":"Manufacturing & Wholesale Goods"
        }
    ],
    "sg:phone":"+43 1 7141207",
    "sg:postcode":"1030",
    "sg:province":"Wien",
    "sg:tags":[
        "car",
        "lettering"
    ],
    "wof:name":"H. Ortmayr",
    "wof:placetype":"venue"
},
  "geometry": {"coordinates":[16.3913803101,48.2075881958],"type":"Point"}
}