{
  "type": "Feature",
  "properties": {
    "addr:full":"Brockmanng 106 Graz Steiermark 8010",
    "addr:housenumber":"106",
    "addr:postcode":"8010",
    "iso:country":"AT",
    "sg:address":"Brockmanng 106",
    "sg:city":"Graz",
    "sg:orig_category":"Steuerberatung",
    "sg:phone":"+43 4331 68100900",
    "sg:postcode":"8010",
    "sg:province":"Steiermark",
    "sg:website":"steuerberatung.at",
    "wof:name":"ECON Steuer- u Wirtschaftsberatungsgesellschaft mbH",
    "wof:placetype":"venue"
},
  "geometry": {"coordinates":[15.4394130707,47.0613174438],"type":"Point"}
}