{
  "type": "Feature",
  "properties": {
    "addr:full":"Kaspar-Schoch-Str 1a Bregenz Vorarlberg 6900",
    "addr:housenumber":"1a",
    "addr:postcode":"6900",
    "addr:street":"Kaspar-Schoch-Str",
    "iso:country":"AT",
    "sg:address":"Kaspar-Schoch-Str 1a",
    "sg:city":"Bregenz",
    "sg:orig_category":"Architekten",
    "sg:phone":"+43 5574 42126",
    "sg:postcode":"6900",
    "sg:province":"Vorarlberg",
    "wof:name":"Reininger Nikolaus Arch Dipl-Ing",
    "wof:placetype":"venue"
},
  "geometry": {"coordinates":[9.7403411865,47.4969367981],"type":"Point"}
}