{
  "type": "Feature",
  "properties": {
    "iso:country":"AT",
    "sg:address":"Niederfeld 1",
    "sg:city":"Thening",
    "sg:orig_category":"Chemisch-Technische Produkte",
    "sg:phone":"+43 7221 64951",
    "sg:postcode":"4062",
    "sg:province":"Ober\u00f6sterreich",
    "wof:name":"Link Chemie GmbH",
    "wof:placetype":"venue"
},
  "geometry": {"coordinates":[14.1746082306,48.2458305359],"type":"Point"}
}