{
  "type": "Feature",
  "properties": {
    "addr:full":"Wiesg 1e Oberperfuss Tirol 6173",
    "addr:housenumber":"1e",
    "addr:postcode":"6173",
    "addr:street":"Wiesg;Tirol",
    "iso:country":"AT",
    "sg:address":"Wiesg 1e",
    "sg:city":"Oberperfuss",
    "sg:orig_category":"Markt- U Meinungsforschung",
    "sg:phone":"+43 5232 771051",
    "sg:postcode":"6173",
    "sg:province":"Tirol",
    "wof:name":"IMAD Marktforschung",
    "wof:placetype":"venue"
},
  "geometry": {"coordinates":[11.2443246841,47.2451858521],"type":"Point"}
}