{
  "type": "Feature",
  "properties": {
    "iso:country":"AT",
    "sg:address":"Hauptpl 4",
    "sg:city":"Dobersberg",
    "sg:orig_category":"Installationsunternehmen",
    "sg:phone":"+43 2843 2236",
    "sg:postcode":"3843",
    "sg:province":"Nieder\u00f6sterreich",
    "wof:name":"Kollenz Norbert Ing",
    "wof:placetype":"venue"
},
  "geometry": {"coordinates":[15.3229846954,48.9147644043],"type":"Point"}
}