{
  "type": "Feature",
  "properties": {
    "addr:full":"Untere Hauptstr 78 Weiden am See Burgenland 7121",
    "addr:housenumber":"78",
    "addr:postcode":"7121",
    "addr:street":"Untere Hauptstr",
    "iso:country":"AT",
    "sg:address":"Untere Hauptstr 78",
    "sg:city":"Weiden am See",
    "sg:orig_category":"Elektroinstallationsunternehmen",
    "sg:phone":"+43 664 8982109",
    "sg:postcode":"7121",
    "sg:province":"Burgenland",
    "wof:name":"KARNER Elektro",
    "wof:placetype":"venue"
},
  "geometry": {"coordinates":[16.8748035431,47.9224395752],"type":"Point"}
}