{
  "type": "Feature",
  "properties": {
    "iso:country":"AT",
    "sg:address":"Dr.-Karl-Renner-Str 4",
    "sg:city":"Ternitz",
    "sg:orig_category":"Spielautomaten",
    "sg:phone":"+43 2630 35215",
    "sg:postcode":"2630",
    "sg:province":"Nieder\u00f6sterreich",
    "wof:name":"Marsmatic Spielautomatenverleih - Inh Grundner Alfred",
    "wof:placetype":"venue"
},
  "geometry": {"coordinates":[16.0016117096,47.7025108337],"type":"Point"}
}