{
  "type": "Feature",
  "properties": {
    "addr:full":"Hochstr 283 Semmering Nieder\u00f6sterreich 2680",
    "addr:housenumber":"283",
    "addr:postcode":"2680",
    "iso:country":"AT",
    "sg:address":"Hochstr 283",
    "sg:city":"Semmering",
    "sg:orig_category":"Non-Classified Establishments",
    "sg:phone":"+43 5 91333359",
    "sg:postcode":"2680",
    "sg:province":"Nieder\u00f6sterreich",
    "wof:name":"Gendarmerie",
    "wof:placetype":"venue"
},
  "geometry": {"coordinates":[15.8293857574,47.6348991394],"type":"Point"}
}