{
  "type": "Feature",
  "properties": {
    "addr:full":"Bruck 3 Zell am Pettenfirst Ober\u00f6sterreich 4842",
    "addr:housenumber":"3",
    "addr:postcode":"4842",
    "addr:street":"Bruck",
    "iso:country":"AT",
    "sg:address":"Bruck 3",
    "sg:city":"Zell am Pettenfirst",
    "sg:classifiers":[
        {
            "category":"Restaurant",
            "type":"Food & Drink"
        }
    ],
    "sg:phone":"+43 76752866",
    "sg:postcode":"4842",
    "sg:province":"Ober\u00f6sterreich",
    "wof:name":"Restaurant Ochsensepp -F\u00fcrtbauer Josef",
    "wof:placetype":"venue"
},
  "geometry": {"coordinates":[13.5806903839,48.0754356384],"type":"Point"}
}