{
  "type": "Feature",
  "properties": {
    "addr:full":"Almegger Str 2 Bad Wimsbach-Neydharting Ober\u00f6sterreich 4654",
    "addr:housenumber":"2",
    "addr:postcode":"4654",
    "addr:street":"Str",
    "iso:country":"AT",
    "sg:address":"Almegger Str 2",
    "sg:city":"Bad Wimsbach-Neydharting",
    "sg:orig_category":"Psychotherapie",
    "sg:phone":"+43 4372 4525791",
    "sg:postcode":"4654",
    "sg:province":"Ober\u00f6sterreich",
    "wof:name":"Franzelin Christa Dr",
    "wof:placetype":"venue"
},
  "geometry": {"coordinates":[13.9025154114,48.0634498596],"type":"Point"}
}