{
  "type": "Feature",
  "properties": {
    "addr:full":"Praschweg 9 Hallein Salzburg 5400",
    "addr:housenumber":"9",
    "addr:postcode":"5400",
    "addr:street":"Praschweg;Salzburg",
    "iso:country":"AT",
    "sg:address":"Praschweg 9",
    "sg:city":"Hallein",
    "sg:orig_category":"Holzhandel",
    "sg:phone":"+43 6245 802300",
    "sg:postcode":"5400",
    "sg:province":"Salzburg",
    "wof:name":"Pliem Manfred",
    "wof:placetype":"venue"
},
  "geometry": {"coordinates":[13.100279808,47.6867218018],"type":"Point"}
}