{
  "type": "Feature",
  "properties": {
    "addr:full":"Rathauspl 4 Wien Wien 1010",
    "addr:housenumber":"4",
    "addr:postcode":"1010",
    "addr:street":"Rathauspl",
    "iso:country":"AT",
    "sg:address":"Rathauspl 4",
    "sg:city":"Wien",
    "sg:orig_category":"Immobilienverwaltungen",
    "sg:phone":"+43 4314 023169",
    "sg:postcode":"1010",
    "sg:province":"Wien",
    "sg:website":"schneeweiss.at",
    "wof:name":"Schneeweiss Wolf-Dietrich Mag MAS Real Estate & Facility Management",
    "wof:placetype":"venue"
},
  "geometry": {"coordinates":[16.3584461212,48.2120628357],"type":"Point"}
}