{
  "type": "Feature",
  "properties": {
    "iso:country":"AT",
    "sg:address":"Waltersdorfer Str 14",
    "sg:city":"Baden",
    "sg:orig_category":"Autohandel",
    "sg:phone":"+43 4322 5224789",
    "sg:postcode":"2500",
    "sg:province":"Nieder\u00f6sterreich",
    "wof:name":"CARAT EXCLUSIV AUTOREINIGUNG",
    "wof:placetype":"venue"
},
  "geometry": {"coordinates":[16.2459850311,48.001739502],"type":"Point"}
}