{
  "type": "Feature",
  "properties": {
    "iso:country":"AT",
    "sg:address":"Reichsratsstrasse 15/3 ",
    "sg:city":"Wien",
    "sg:classifiers":[
        {
            "category":"Building & Trades",
            "subcategory":"Electrical",
            "type":"Services"
        }
    ],
    "sg:phone":"+43 1 53246840",
    "sg:postcode":"1010",
    "sg:province":"Wien",
    "sg:tags":[
        "communication",
        "computers",
        "equipment",
        "terminals",
        "computer",
        "data"
    ],
    "sg:website":"www.logix.at",
    "wof:name":"logix Technologie und Beteiligungs GmbH",
    "wof:placetype":"venue"
},
  "geometry": {"coordinates":[16.3588867188,48.2135543823],"type":"Point"}
}