{
  "type": "Feature",
  "properties": {
    "addr:full":"Feldg 369 Ollersdorf Nieder\u00f6sterreich 2252",
    "addr:housenumber":"369;2252",
    "addr:street":"Ollersdorf Niederoesterreich",
    "iso:country":"AT",
    "sg:address":"Feldg 369",
    "sg:city":"Ollersdorf",
    "sg:orig_category":"Elektroinstallationsunternehmen",
    "sg:phone":"+43 2283 2729",
    "sg:postcode":"2252",
    "sg:province":"Nieder\u00f6sterreich",
    "wof:name":"Elektro Langer",
    "wof:placetype":"venue"
},
  "geometry": {"coordinates":[16.7951660156,48.3962173462],"type":"Point"}
}