{
  "type": "Feature",
  "properties": {
    "iso:country":"AT",
    "sg:address":"Orgeniweg 5",
    "sg:city":"Graz",
    "sg:orig_category":"Physiotherapie",
    "sg:phone":"+43 316 359838",
    "sg:postcode":"8010",
    "sg:province":"Steiermark",
    "wof:name":"Lehofer-Gersdorf Christa Dipl-PT",
    "wof:placetype":"venue"
},
  "geometry": {"coordinates":[15.4695367813,47.0762481689],"type":"Point"}
}