{
  "type": "Feature",
  "properties": {
    "iso:country":"AT",
    "sg:address":"Hauptstr 10",
    "sg:city":"Kobersdorf",
    "sg:orig_category":"Non-Classified Establishments",
    "sg:phone":"+43 2618 8208",
    "sg:postcode":"7332",
    "sg:province":"Burgenland",
    "wof:name":"Pfarramt",
    "wof:placetype":"venue"
},
  "geometry": {"coordinates":[16.3916664124,47.5954818726],"type":"Point"}
}