{
  "type": "Feature",
  "properties": {
    "addr:full":"Taborstr 27/3 Wien Wien 1020",
    "addr:housenumber":"3",
    "addr:postcode":"1020",
    "iso:country":"AT",
    "sg:address":"Taborstr 27/3",
    "sg:city":"Wien",
    "sg:orig_category":"Psychotherapie",
    "sg:phone":"+43 1 9426644",
    "sg:postcode":"1020",
    "sg:province":"Wien",
    "wof:name":"Zykan Hanns Dr",
    "wof:placetype":"venue"
},
  "geometry": {"coordinates":[16.380651474,48.2176933289],"type":"Point"}
}