{
  "type": "Feature",
  "properties": {
    "iso:country":"AT",
    "sg:address":"Edisonstrasse 2",
    "sg:city":"Wels",
    "sg:orig_category":"Edifact For Electronic Data Exchange",
    "sg:phone":"+43 7242 43609",
    "sg:postcode":"4600",
    "sg:province":"Ober\u00f6sterreich",
    "sg:website":"seeburger.at",
    "wof:name":"SEEBURGER Informatik GmbH",
    "wof:placetype":"venue"
},
  "geometry": {"coordinates":[14.0090208054,48.1523284912],"type":"Point"}
}