{
  "type": "Feature",
  "properties": {
    "addr:full":"Weerer Eben 10a Kolsass Tirol 6114",
    "addr:housenumber":"10a",
    "addr:postcode":"6114",
    "addr:street":"Eben;Tirol",
    "iso:country":"AT",
    "sg:address":"Weerer Eben 10a",
    "sg:city":"Kolsass",
    "sg:orig_category":"Installationsunternehmen",
    "sg:phone":"+43 5224 68988",
    "sg:postcode":"6114",
    "sg:province":"Tirol",
    "wof:name":"Peyer Mario",
    "wof:placetype":"venue"
},
  "geometry": {"coordinates":[11.6497659683,47.3017272949],"type":"Point"}
}