{
  "type": "Feature",
  "properties": {
    "iso:country":"AT",
    "sg:address":"Untere Hauptstr 62",
    "sg:city":"Deutsch Brodersdorf",
    "sg:orig_category":"Dachdeckereien",
    "sg:phone":"+43 4322 557211",
    "sg:postcode":"2443",
    "sg:province":"Nieder\u00f6sterreich",
    "wof:name":"Holzbau Roller",
    "wof:placetype":"venue"
},
  "geometry": {"coordinates":[16.4713840485,47.9397583008],"type":"Point"}
}