{
  "type": "Feature",
  "properties": {
    "addr:full":"Prandtauersdlg 16 Landeck Tirol 6500",
    "addr:housenumber":"16",
    "addr:postcode":"6500",
    "addr:street":"Prandtauersdlg;Tirol",
    "iso:country":"AT",
    "sg:address":"Prandtauersdlg 16",
    "sg:city":"Landeck",
    "sg:orig_category":"Fotografen",
    "sg:phone":"+43 5442 680010",
    "sg:postcode":"6500",
    "sg:province":"Tirol",
    "wof:name":"Studio 45",
    "wof:placetype":"venue"
},
  "geometry": {"coordinates":[10.6277132034,47.1200027466],"type":"Point"}
}