{
  "type": "Feature",
  "properties": {
    "iso:country":"AT",
    "sg:address":"Neunkirchner Str 36",
    "sg:city":"Breitenau am Steinfelde",
    "sg:orig_category":"Tabaktrafiken",
    "sg:phone":"+43 2635 68027",
    "sg:postcode":"2624",
    "sg:province":"Nieder\u00f6sterreich",
    "wof:name":"Schr\u00f6ckenstein Olga",
    "wof:placetype":"venue"
},
  "geometry": {"coordinates":[16.1411552429,47.7333755493],"type":"Point"}
}