{
  "type": "Feature",
  "properties": {
    "addr:full":"Ottensheimer Str 112/5 Linz Ober\u00f6sterreich 4040",
    "addr:housenumber":"112 / 5",
    "addr:postcode":"4040",
    "iso:country":"AT",
    "sg:address":"Ottensheimer Str 112/5",
    "sg:city":"Linz",
    "sg:orig_category":"Gartenarchitekten",
    "sg:phone":"+43 732 714371",
    "sg:postcode":"4040",
    "sg:province":"Ober\u00f6sterreich",
    "wof:name":"Frischenschlager Gert Dipl-Ing",
    "wof:placetype":"venue"
},
  "geometry": {"coordinates":[14.2736148834,48.3064994812],"type":"Point"}
}