{
  "type": "Feature",
  "properties": {
    "iso:country":"AT",
    "sg:address":"Serlesstr 24",
    "sg:city":"Neustift im Stubaital",
    "sg:orig_category":"Friseure U Frisiersalons",
    "sg:phone":"+43 4352 263398",
    "sg:postcode":"6167",
    "sg:province":"Tirol",
    "wof:name":"Haargenau",
    "wof:placetype":"venue"
},
  "geometry": {"coordinates":[11.3369989395,47.1260871887],"type":"Point"}
}