{
  "type": "Feature",
  "properties": {
    "addr:full":"Lammg 12/3a Wien Wien 1080",
    "addr:housenumber":"12 / 3a",
    "addr:postcode":"1080",
    "addr:street":"Lammg",
    "iso:country":"AT",
    "sg:address":"Lammg 12/3a",
    "sg:city":"Wien",
    "sg:orig_category":"Exporteure U Importeure",
    "sg:phone":"+43 4314 060241",
    "sg:postcode":"1080",
    "sg:province":"Wien",
    "wof:name":"Shodiya Sonja & Partner - Spanische Spezialit\u00e4ten- und Wein-Direktimport",
    "wof:placetype":"venue"
},
  "geometry": {"coordinates":[16.3520755768,48.2131652832],"type":"Point"}
}