{
  "type": "Feature",
  "properties": {
    "addr:full":"Lastenstr 38 Linz Ober\u00f6sterreich 4020",
    "addr:housenumber":"38",
    "addr:postcode":"4020",
    "addr:street":"Lastenstr",
    "iso:country":"AT",
    "sg:address":"Lastenstr 38",
    "sg:city":"Linz",
    "sg:orig_category":"Banken U Sparkassen",
    "sg:phone":"+43 4373 2660427",
    "sg:postcode":"4020",
    "sg:province":"Ober\u00f6sterreich",
    "wof:name":"Sparda-Bank Linz regGenmbH",
    "wof:placetype":"venue"
},
  "geometry": {"coordinates":[14.3051519394,48.291469574],"type":"Point"}
}