{
  "type": "Feature",
  "properties": {
    "addr:full":"Wiener Str 1 Asten Ober\u00f6sterreich 4481",
    "addr:housenumber":"1",
    "addr:postcode":"4481",
    "iso:country":"AT",
    "sg:address":"Wiener Str 1",
    "sg:city":"Asten",
    "sg:orig_category":"Textilwaren / Einzelhandel",
    "sg:phone":"+43 4372 2467866",
    "sg:postcode":"4481",
    "sg:province":"Ober\u00f6sterreich",
    "wof:name":"NKD",
    "wof:placetype":"venue"
},
  "geometry": {"coordinates":[14.408164978,48.2224273682],"type":"Point"}
}