{
  "type": "Feature",
  "properties": {
    "addr:full":"Schottenring 24 Wien Wien 1010",
    "addr:housenumber":"24",
    "addr:postcode":"1010",
    "addr:street":"Schottenring",
    "iso:country":"AT",
    "sg:address":"Schottenring 24",
    "sg:city":"Wien",
    "sg:orig_category":"Lebens- U Sozialberatung",
    "sg:phone":"+43 4315 311485255",
    "sg:postcode":"1010",
    "sg:province":"Wien",
    "wof:name":"Beratungsstelle in sozialen Fragen",
    "wof:placetype":"venue"
},
  "geometry": {"coordinates":[16.3684673309,48.21641922],"type":"Point"}
}