{
  "type": "Feature",
  "properties": {
    "addr:full":"Nr 31 Statzendorf Nieder\u00f6sterreich 3125",
    "addr:postcode":"3125",
    "addr:street":"Nr;Niederoesterreich",
    "iso:country":"AT",
    "sg:address":"Nr 31",
    "sg:city":"Statzendorf",
    "sg:orig_category":"Gastronomie- U Hoteleinrichtungen",
    "sg:phone":"+43 4367 64144069",
    "sg:postcode":"3125",
    "sg:province":"Nieder\u00f6sterreich",
    "wof:name":"A + R Gradl KEG",
    "wof:placetype":"venue"
},
  "geometry": {"coordinates":[15.6341323853,48.2908477783],"type":"Point"}
}