{
  "type": "Feature",
  "properties": {
    "addr:full":"Wildg 9 Sollenau Nieder\u00f6sterreich 2601",
    "addr:housenumber":"9",
    "addr:postcode":"2601",
    "addr:street":"Wildg",
    "iso:country":"AT",
    "sg:address":"Wildg 9",
    "sg:city":"Sollenau",
    "sg:orig_category":"Mineralien",
    "sg:phone":"+43 4366 41508544",
    "sg:postcode":"2601",
    "sg:province":"Nieder\u00f6sterreich",
    "wof:name":"Wukonig Minerals OEG",
    "wof:placetype":"venue"
},
  "geometry": {"coordinates":[16.2412605286,47.9025688171],"type":"Point"}
}