{
  "type": "Feature",
  "properties": {
    "addr:full":"Kellau 151 Kuchl Salzburg 5431",
    "addr:housenumber":"151",
    "addr:postcode":"5431",
    "addr:street":"Kellau;Salzburg",
    "iso:country":"AT",
    "sg:address":"Kellau 151",
    "sg:city":"Kuchl",
    "sg:classifiers":[
        {
            "category":"Banks & Credit Unions",
            "subcategory":"Investment Brokerage",
            "type":"Services"
        }
    ],
    "sg:phone":"+43 6244 4433",
    "sg:postcode":"5431",
    "sg:province":"Salzburg",
    "sg:tags":[
        "development",
        "electronics"
    ],
    "sg:website":"gfi-elektronik.at",
    "wof:name":"gfi - Gesellschaft f\u00fcr Industrieelektronik GmbH",
    "wof:placetype":"venue"
},
  "geometry": {"coordinates":[13.1438808441,47.625667572],"type":"Point"}
}