{
  "type": "Feature",
  "properties": {
    "addr:full":"Sandteneck 8 Bad Ischl Ober\u00f6sterreich 4820",
    "addr:housenumber":"8",
    "addr:postcode":"4820",
    "addr:street":"Sandteneck;Oberoesterreich",
    "iso:country":"AT",
    "sg:address":"Sandteneck 8",
    "sg:city":"Bad Ischl",
    "sg:orig_category":"Personalberatung",
    "sg:phone":"+43 6132 2705011",
    "sg:postcode":"4820",
    "sg:province":"Ober\u00f6sterreich",
    "wof:name":"Diesenreiter Bruno branchenorientierte Personalberatung Personaltraining Swissconsult",
    "wof:placetype":"venue"
},
  "geometry": {"coordinates":[13.5902166367,47.716468811],"type":"Point"}
}