{
  "type": "Feature",
  "properties": {
    "addr:full":"Kroateng 3 Linz Ober\u00f6sterreich 4020",
    "addr:housenumber":"3",
    "addr:postcode":"4020",
    "addr:street":"Kroateng",
    "iso:country":"AT",
    "sg:address":"Kroateng 3",
    "sg:city":"Linz",
    "sg:orig_category":"Ingenieurkonsulenten / Zivilingenieure",
    "sg:phone":"+43 732 609835",
    "sg:postcode":"4020",
    "sg:province":"Ober\u00f6sterreich",
    "wof:name":"Hubauer Rudolf Dipl-Ing",
    "wof:placetype":"venue"
},
  "geometry": {"coordinates":[14.2846212387,48.2973022461],"type":"Point"}
}