{
  "type": "Feature",
  "properties": {
    "addr:full":"H\u00f6rlg 6 Wien Wien 1090",
    "addr:housenumber":"6",
    "addr:postcode":"1090",
    "addr:street":"Hoerlg",
    "iso:country":"AT",
    "sg:address":"H\u00f6rlg 6",
    "sg:city":"Wien",
    "sg:orig_category":"Friseure U Frisiersalons",
    "sg:phone":"+43 1 3175675",
    "sg:postcode":"1090",
    "sg:province":"Wien",
    "wof:name":"Salon Susanne",
    "wof:placetype":"venue"
},
  "geometry": {"coordinates":[16.351474762,48.2234115601],"type":"Point"}
}