{
  "type": "Feature",
  "properties": {
    "addr:full":"Rohrbachh\u00f6he 23 Graz Steiermark 8010",
    "addr:housenumber":"23",
    "addr:postcode":"8010",
    "addr:street":"Rohrbachhoehe",
    "iso:country":"AT",
    "sg:address":"Rohrbachh\u00f6he 23",
    "sg:city":"Graz",
    "sg:classifiers":[
        {
            "category":"Farming",
            "subcategory":"Livestock Farm",
            "type":"Manufacturing & Wholesale Goods"
        }
    ],
    "sg:phone":"+43 316 3910100",
    "sg:postcode":"8010",
    "sg:province":"Steiermark",
    "sg:tags":[
        "-handel",
        "viehzucht",
        "u"
    ],
    "wof:name":"Gassner GesmbH",
    "wof:placetype":"venue"
},
  "geometry": {"coordinates":[15.5035104752,47.1017303467],"type":"Point"}
}