{
  "type": "Feature",
  "properties": {
    "addr:full":"Alfons-Petzold-G 17/9 Brunn am Gebirge Nieder\u00f6sterreich 2345",
    "addr:housenumber":"17 / 9",
    "addr:postcode":"2345",
    "addr:street":"Alfons-Petzold-G",
    "iso:country":"AT",
    "sg:address":"Alfons-Petzold-G 17/9",
    "sg:city":"Brunn am Gebirge",
    "sg:orig_category":"Tapezierer U Dekorateure",
    "sg:phone":"+43 4365 03406802",
    "sg:postcode":"2345",
    "sg:province":"Nieder\u00f6sterreich",
    "wof:name":"Mackinger Antonio",
    "wof:placetype":"venue"
},
  "geometry": {"coordinates":[16.2922039032,48.1055717468],"type":"Point"}
}