{
  "type": "Feature",
  "properties": {
    "addr:full":"Spitalg 17 St. Veit an der Glan K\u00e4rnten 9300",
    "addr:housenumber":"17",
    "addr:postcode":"9300",
    "addr:street":"Spitalg;Kaernten",
    "iso:country":"AT",
    "sg:address":"Spitalg 17",
    "sg:city":"St. Veit an der Glan",
    "sg:orig_category":"Fluggesellschaften",
    "sg:phone":"+43 664 4066187",
    "sg:postcode":"9300",
    "sg:province":"K\u00e4rnten",
    "wof:name":"AIRDIRECT Bedarfsflug GmbH",
    "wof:placetype":"venue"
},
  "geometry": {"coordinates":[14.3591928482,46.7664413452],"type":"Point"}
}