{
  "type": "Feature",
  "properties": {
    "addr:full":"Ringstrasse 26 Wels Ober\u00f6sterreich 4600",
    "addr:housenumber":"26",
    "addr:postcode":"4600",
    "addr:street":"Ringstrasse;Oberoesterreich",
    "iso:country":"AT",
    "sg:address":"Ringstrasse 26",
    "sg:city":"Wels",
    "sg:orig_category":"Anti-Mould Coatings",
    "sg:phone":"+43 7242 44338",
    "sg:postcode":"4600",
    "sg:province":"Ober\u00f6sterreich",
    "wof:name":"Gerhard Klaus P\u00f6ssl",
    "wof:placetype":"venue"
},
  "geometry": {"coordinates":[14.0255556107,48.158706665],"type":"Point"}
}