{
  "type": "Feature",
  "properties": {
    "addr:full":"Kirchenpl 1 Deutsch Brodersdorf Nieder\u00f6sterreich 2443",
    "addr:housenumber":"1",
    "addr:postcode":"2443",
    "addr:street":"Kirchenpl",
    "iso:country":"AT",
    "sg:address":"Kirchenpl 1",
    "sg:city":"Deutsch Brodersdorf",
    "sg:orig_category":"Non-Classified Establishments",
    "sg:phone":"+43 2255 8204",
    "sg:postcode":"2443",
    "sg:province":"Nieder\u00f6sterreich",
    "wof:name":"Pfarramt",
    "wof:placetype":"venue"
},
  "geometry": {"coordinates":[16.5467300415,47.904838562],"type":"Point"}
}