{
  "type": "Feature",
  "properties": {
    "addr:full":"Liechtensteinstr 123 Wien Wien 1090",
    "addr:housenumber":"123",
    "addr:postcode":"1090",
    "iso:country":"AT",
    "sg:address":"Liechtensteinstr 123",
    "sg:city":"Wien",
    "sg:orig_category":"Zeitungen U Zeitschriften",
    "sg:phone":"+43 1 5036828",
    "sg:postcode":"1090",
    "sg:province":"Wien",
    "wof:name":"Verein zur F\u00f6rderung gesellschaftskritischer Zeitschriften",
    "wof:placetype":"venue"
},
  "geometry": {"coordinates":[16.355928421,48.2292785645],"type":"Point"}
}