{
  "type": "Feature",
  "properties": {
    "addr:full":"Am Freihof 23 Wien Wien 1220",
    "addr:housenumber":"23",
    "addr:postcode":"1220",
    "addr:street":"Am Freihof",
    "iso:country":"AT",
    "sg:address":"Am Freihof 23",
    "sg:city":"Wien",
    "sg:orig_category":"Baumeister",
    "sg:phone":"+43 4312 042614",
    "sg:postcode":"1220",
    "sg:province":"Wien",
    "sg:website":"safferthal.at",
    "wof:name":"Safferthal Dipl-Ing Bmstr GesmbH",
    "wof:placetype":"venue"
},
  "geometry": {"coordinates":[16.4466838837,48.2478523254],"type":"Point"}
}