{
  "type": "Feature",
  "properties": {
    "addr:full":"Weng 48 Goldegg Salzburg 5622",
    "addr:housenumber":"48",
    "addr:postcode":"5622",
    "addr:street":"Weng;Salzburg",
    "iso:country":"AT",
    "sg:address":"Weng 48",
    "sg:city":"Goldegg",
    "sg:orig_category":"Flower Box Holders And Attachment Fittings",
    "sg:phone":"+43 6415 8533",
    "sg:postcode":"5622",
    "sg:province":"Salzburg",
    "wof:name":"Franz Lackner",
    "wof:placetype":"venue"
},
  "geometry": {"coordinates":[13.0739183426,47.3287277222],"type":"Point"}
}