{
  "type": "Feature",
  "properties": {
    "addr:full":"Zaunerg. 4 1031",
    "addr:housenumber":"4",
    "addr:postcode":"1031",
    "addr:street":"Zaunerg.",
    "iso:country":"AT",
    "sg:address":"Zaunerg. 4",
    "sg:classifiers":[
        {
            "category":"Professional",
            "subcategory":"Business Services",
            "type":"Services"
        }
    ],
    "sg:phone":"+43 4317 1772",
    "sg:postcode":"1031",
    "sg:tags":[
        "advice"
    ],
    "wof:name":"DRIVE SICHERHEIT-SERVICE GMBH.",
    "wof:placetype":"venue"
},
  "geometry": {"coordinates":[16.3777351379,48.1988334656],"type":"Point"}
}