{
  "type": "Feature",
  "properties": {
    "iso:country":"AT",
    "sg:address":"Hubert-Sch\u00fctzner-G 7",
    "sg:city":"Hafnerbach",
    "sg:classifiers":[
        {
            "category":"Home & Garden",
            "subcategory":"Building Materials",
            "type":"Retail Goods"
        }
    ],
    "sg:phone":"+43 4327 4921760",
    "sg:postcode":"3386",
    "sg:province":"Nieder\u00f6sterreich",
    "sg:tags":[
        "baustoffe",
        "-material",
        "u"
    ],
    "wof:name":"Z\u00f6chbauer J GmbH",
    "wof:placetype":"venue"
},
  "geometry": {"coordinates":[15.4880743027,48.2166900635],"type":"Point"}
}