{
  "type": "Feature",
  "properties": {
    "addr:full":"Hauptstr 54 Aschau Tirol 6274",
    "addr:housenumber":"54",
    "addr:postcode":"6274",
    "addr:street":"Hauptstr;Aschau Tirol",
    "iso:country":"AT",
    "sg:address":"Hauptstr 54",
    "sg:city":"Aschau",
    "sg:orig_category":"Appartements / Ferienwohnungen",
    "sg:phone":"+43 4352 822811",
    "sg:postcode":"6274",
    "sg:province":"Tirol",
    "wof:name":"Binderhof Wildauer Maria",
    "wof:placetype":"venue"
},
  "geometry": {"coordinates":[11.8959445953,47.2627754211],"type":"Point"}
}