{
  "type": "Feature",
  "properties": {
    "addr:full":"Usting 11 Peuerbach Ober\u00f6sterreich 4722",
    "addr:housenumber":"11",
    "addr:postcode":"4722",
    "addr:street":"Usting",
    "iso:country":"AT",
    "sg:address":"Usting 11",
    "sg:city":"Peuerbach",
    "sg:orig_category":"Tischlereien",
    "sg:phone":"+43 7276 2650",
    "sg:postcode":"4722",
    "sg:province":"Ober\u00f6sterreich",
    "wof:name":"M\u00fchringer Josef",
    "wof:placetype":"venue"
},
  "geometry": {"coordinates":[13.7729463577,48.3276634216],"type":"Point"}
}