{
  "type": "Feature",
  "properties": {
    "addr:full":"Franz-Josefs-Kai 41 Wien Wien 1010",
    "addr:housenumber":"41",
    "addr:postcode":"1010",
    "addr:street":"Franz-Josefs-Kai",
    "iso:country":"AT",
    "sg:address":"Franz-Josefs-Kai 41",
    "sg:city":"Wien",
    "sg:orig_category":"Sonnenstudios",
    "sg:phone":"+43 4315 335806",
    "sg:postcode":"1010",
    "sg:province":"Wien",
    "wof:name":"Sun Club Br\u00e4unungsanlagen Vermietung u Betriebs-GesmbH",
    "wof:placetype":"venue"
},
  "geometry": {"coordinates":[16.3728981018,48.2146568298],"type":"Point"}
}