{
  "type": "Feature",
  "properties": {
    "addr:full":"Bahnhofstr 6 Bischofshofen Salzburg 5500",
    "addr:housenumber":"6",
    "addr:postcode":"5500",
    "addr:street":"Bahnhofstr;Salzburg",
    "iso:country":"AT",
    "sg:address":"Bahnhofstr 6",
    "sg:city":"Bischofshofen",
    "sg:orig_category":"Boutiquen",
    "sg:phone":"+43 4364 623005",
    "sg:postcode":"5500",
    "sg:province":"Salzburg",
    "wof:name":"Benetton",
    "wof:placetype":"venue"
},
  "geometry": {"coordinates":[13.2184972763,47.4157943726],"type":"Point"}
}