{
  "type": "Feature",
  "properties": {
    "addr:full":"Markt 36 Edlitz Nieder\u00f6sterreich 2842",
    "addr:housenumber":"36",
    "addr:postcode":"2842",
    "addr:street":"Markt",
    "iso:country":"AT",
    "sg:address":"Markt 36",
    "sg:city":"Edlitz",
    "sg:orig_category":"Bibliotheken",
    "sg:phone":"+43 2644 20173",
    "sg:postcode":"2842",
    "sg:province":"Nieder\u00f6sterreich",
    "wof:name":"Bibliothek Edlitz",
    "wof:placetype":"venue"
},
  "geometry": {"coordinates":[16.1358203888,47.6015663147],"type":"Point"}
}