{
  "type": "Feature",
  "properties": {
    "addr:full":"Erzog Odilo Str. 101 Mondsee Ober\u00f6sterreich 5310",
    "addr:housenumber":"101",
    "addr:postcode":"5310",
    "addr:street":"Str.;Oberoesterreich",
    "iso:country":"AT",
    "sg:address":"Erzog Odilo Str. 101",
    "sg:city":"Mondsee",
    "sg:orig_category":"Miscellaneous Products",
    "sg:phone":"+43 4362 325204",
    "sg:postcode":"5310",
    "sg:province":"Ober\u00f6sterreich",
    "wof:name":"AMBRATEC GMBH",
    "wof:placetype":"venue"
},
  "geometry": {"coordinates":[13.3327865601,47.864654541],"type":"Point"}
}