{
  "type": "Feature",
  "properties": {
    "iso:country":"AT",
    "sg:address":"Tiroler Str 9",
    "sg:city":"St. P\u00f6lten-Radlberg",
    "sg:orig_category":"Elektroinstallationsunternehmen",
    "sg:phone":"+43 4327 423420",
    "sg:postcode":"3105",
    "sg:province":"Nieder\u00f6sterreich",
    "wof:name":"VA TECH ELIN EBG GmbH Landeldirektion Wien/N\u00f6 Au\u00dfenstelle St P\u00f6lten",
    "wof:placetype":"venue"
},
  "geometry": {"coordinates":[15.6872873306,48.2614517212],"type":"Point"}
}