{
  "type": "Feature",
  "properties": {
    "addr:full":"Johann-Teufel-G 47/13 Wien Wien 1230",
    "addr:housenumber":"47 / 13",
    "addr:postcode":"1230",
    "addr:street":"Johann-Teufel-G",
    "iso:country":"AT",
    "sg:address":"Johann-Teufel-G 47/13",
    "sg:city":"Wien",
    "sg:classifiers":[
        {
            "category":"Taxi",
            "type":"Transportation"
        }
    ],
    "sg:phone":"+43 4318 891247",
    "sg:postcode":"1230",
    "sg:province":"Wien",
    "sg:tags":[
        "personentransporte",
        "u"
    ],
    "wof:name":"Nowotny Gerhard",
    "wof:placetype":"venue"
},
  "geometry": {"coordinates":[16.2744522095,48.1443405151],"type":"Point"}
}