{
  "type": "Feature",
  "properties": {
    "addr:full":"Oberfeld 41 Ostermiething Ober\u00f6sterreich 5121",
    "addr:housenumber":"41",
    "addr:postcode":"5121",
    "addr:street":"Oberfeld",
    "iso:country":"AT",
    "sg:address":"Oberfeld 41",
    "sg:city":"Ostermiething",
    "sg:orig_category":"Blumeneinzelhandel",
    "sg:phone":"+43 6278 7328",
    "sg:postcode":"5121",
    "sg:province":"Ober\u00f6sterreich",
    "wof:name":"Flowers & Co Trockenblumen - Hochzeitsfloristik Sandra Schwab",
    "wof:placetype":"venue"
},
  "geometry": {"coordinates":[12.83847332,48.0403327942],"type":"Point"}
}