{
  "type": "Feature",
  "properties": {
    "addr:full":"Herbststr 30 Wien Wien 1160",
    "addr:housenumber":"30",
    "addr:postcode":"1160",
    "addr:street":"Herbststr",
    "iso:country":"AT",
    "sg:address":"Herbststr 30",
    "sg:city":"Wien",
    "sg:orig_category":"Industrievertretungen",
    "sg:phone":"+43 1 49317170",
    "sg:postcode":"1160",
    "sg:province":"Wien",
    "wof:name":"Zastera Wilhelm",
    "wof:placetype":"venue"
},
  "geometry": {"coordinates":[16.3309879303,48.2058906555],"type":"Point"}
}