{
  "type": "Feature",
  "properties": {
    "addr:full":"Hauptstr 189a St. Andr\u00e4 K\u00e4rnten 9433",
    "addr:housenumber":"189a",
    "addr:postcode":"9433",
    "addr:street":"Hauptstr;St. Andrae Kaernten",
    "iso:country":"AT",
    "sg:address":"Hauptstr 189a",
    "sg:city":"St. Andr\u00e4",
    "sg:orig_category":"Autohandel",
    "sg:phone":"+43 4358 3630",
    "sg:postcode":"9433",
    "sg:province":"K\u00e4rnten",
    "wof:name":"DT Autohandel GmbH",
    "wof:placetype":"venue"
},
  "geometry": {"coordinates":[14.821849823,46.7685317993],"type":"Point"}
}