{
  "type": "Feature",
  "properties": {
    "iso:country":"AT",
    "sg:address":"Im Aichetfeld 111",
    "sg:city":"St. Florian",
    "sg:orig_category":"Handarbeiten",
    "sg:phone":"+43 7224 5803",
    "sg:postcode":"4490",
    "sg:province":"Ober\u00f6sterreich",
    "wof:name":"Mei\u00dfl Brigitte",
    "wof:placetype":"venue"
},
  "geometry": {"coordinates":[14.364988327,48.2056922913],"type":"Point"}
}