{
  "type": "Feature",
  "properties": {
    "iso:country":"AT",
    "sg:address":"G\u00fcterweg 1",
    "sg:city":"Apetlon",
    "sg:orig_category":"Umweltschutz",
    "sg:phone":"+43 4321 753149",
    "sg:postcode":"7143",
    "sg:province":"Burgenland",
    "wof:name":"WWF Infohaus - Seewinkelhof",
    "wof:placetype":"venue"
},
  "geometry": {"coordinates":[16.8309898376,47.7431602478],"type":"Point"}
}