{
  "type": "Feature",
  "properties": {
    "iso:country":"AT",
    "sg:address":"Greifensteiner Str 90",
    "sg:city":"St. Andr\u00e4-W\u00f6rdern",
    "sg:classifiers":[
        {
            "category":"Restaurant",
            "type":"Food & Drink"
        }
    ],
    "sg:phone":"+43 2242 33644",
    "sg:postcode":"3423",
    "sg:province":"Nieder\u00f6sterreich",
    "sg:tags":[
        "pizzeria"
    ],
    "sg:website":"pizzahaus.at",
    "wof:name":"Pizza-Haus Mathias Z\u00f6chmann",
    "wof:placetype":"venue"
},
  "geometry": {"coordinates":[16.216878891,48.3269348145],"type":"Point"}
}