{
  "type": "Feature",
  "properties": {
    "addr:full":"Neubaug Wien Wien 1070",
    "addr:postcode":"1070",
    "iso:country":"AT",
    "sg:address":"Neubaug",
    "sg:city":"Wien",
    "sg:orig_category":"Non-Classified Establishments",
    "sg:phone":"+43 1 5231060",
    "sg:postcode":"1070",
    "sg:province":"Wien",
    "wof:name":"TAXI-TEL Standplatztelefon Betriebs GmbH",
    "wof:placetype":"venue"
},
  "geometry": {"coordinates":[16.3383293152,48.2016792297],"type":"Point"}
}