{
  "type": "Feature",
  "properties": {
    "addr:full":"Grundstr 31 Neuhofen an der Krems Ober\u00f6sterreich 4501",
    "addr:housenumber":"31",
    "addr:postcode":"4501",
    "addr:street":"Grundstr",
    "iso:country":"AT",
    "sg:address":"Grundstr 31",
    "sg:city":"Neuhofen an der Krems",
    "sg:orig_category":"Transportunternehmen",
    "sg:phone":"+43 4372 274463",
    "sg:postcode":"4501",
    "sg:province":"Ober\u00f6sterreich",
    "wof:name":"Haslinger Hans Intern Transporte GesmbH",
    "wof:placetype":"venue"
},
  "geometry": {"coordinates":[14.2102918625,48.1286277771],"type":"Point"}
}