{
  "type": "Feature",
  "properties": {
    "addr:full":"Ziegeleistr 8 u 10 Wolfsberg K\u00e4rnten 9400",
    "addr:housenumber":"8 u 10;kaernten",
    "addr:postcode":"9400",
    "addr:street":"Ziegeleistr",
    "iso:country":"AT",
    "sg:address":"Ziegeleistr 8 u 10",
    "sg:city":"Wolfsberg",
    "sg:orig_category":"Stahlbau",
    "sg:phone":"+43 4343 524432",
    "sg:postcode":"9400",
    "sg:province":"K\u00e4rnten",
    "wof:name":"Kirschner Raimund Stahlbau GmbH",
    "wof:placetype":"venue"
},
  "geometry": {"coordinates":[14.8418502808,46.8402099609],"type":"Point"}
}