{
  "type": "Feature",
  "properties": {
    "addr:full":"B\u00fchelstr 1 Zirl Tirol 6170",
    "addr:housenumber":"1",
    "addr:postcode":"6170",
    "addr:street":"Buehelstr;Tirol",
    "iso:country":"AT",
    "sg:address":"B\u00fchelstr 1",
    "sg:city":"Zirl",
    "sg:orig_category":"Bankomat-Standorte",
    "sg:phone":"+43 5238 55010",
    "sg:postcode":"6170",
    "sg:province":"Tirol",
    "wof:name":"Bankomat d Raiffeisen-Landesbank Tirol AG",
    "wof:placetype":"venue"
},
  "geometry": {"coordinates":[11.2416305542,47.2735519409],"type":"Point"}
}