{
  "type": "Feature",
  "properties": {
    "addr:full":"Nr 31 Stainz Steiermark 8510",
    "addr:postcode":"8510",
    "addr:street":"Nr 31",
    "iso:country":"AT",
    "sg:address":"Nr 31",
    "sg:city":"Stainz",
    "sg:orig_category":"Montagen U Montagetechnik",
    "sg:phone":"+43 4366 42416136",
    "sg:postcode":"8510",
    "sg:province":"Steiermark",
    "wof:name":"Jochum & Haas",
    "wof:placetype":"venue"
},
  "geometry": {"coordinates":[15.2647809982,46.8937683105],"type":"Point"}
}