{
  "type": "Feature",
  "properties": {
    "iso:country":"AT",
    "sg:address":"Adolf-Holzer-G 32",
    "sg:city":"Perchtoldsdorf",
    "sg:orig_category":"Essenzen",
    "sg:phone":"+43 1 8659446",
    "sg:postcode":"2380",
    "sg:province":"Nieder\u00f6sterreich",
    "wof:name":"Cerny Erich Dr GesmbH",
    "wof:placetype":"venue"
},
  "geometry": {"coordinates":[16.2770385742,48.1202812195],"type":"Point"}
}