{
  "type": "Feature",
  "properties": {
    "iso:country":"AT",
    "sg:address":"Nr 44",
    "sg:city":"Neulengbach",
    "sg:classifiers":[
        {
            "category":"Restaurant",
            "type":"Food & Drink"
        }
    ],
    "sg:phone":"+43 4327 7254466",
    "sg:postcode":"3040",
    "sg:province":"Nieder\u00f6sterreich",
    "sg:tags":[
        "pizzeria"
    ],
    "wof:name":"Restaurant - Catering - Cafe Castor",
    "wof:placetype":"venue"
},
  "geometry": {"coordinates":[15.9079504013,48.1976547241],"type":"Point"}
}