{
  "type": "Feature",
  "properties": {
    "addr:full":"P\u00f6tschenstr 134 Bad Aussee Steiermark 8990",
    "addr:housenumber":"134",
    "addr:postcode":"8990",
    "iso:country":"AT",
    "sg:address":"P\u00f6tschenstr 134",
    "sg:city":"Bad Aussee",
    "sg:orig_category":"Marmor U Marmorwaren",
    "sg:phone":"+43 4336 2253276",
    "sg:postcode":"8990",
    "sg:province":"Steiermark",
    "wof:name":"Kopp Gu\u00dfmarmorwerk - Werner Rastl",
    "wof:placetype":"venue"
},
  "geometry": {"coordinates":[13.783372879,47.6095199585],"type":"Point"}
}