{
  "type": "Feature",
  "properties": {
    "addr:full":"Bayerng 3/5 Wien Wien 1030",
    "addr:housenumber":"3 / 5",
    "addr:postcode":"1030",
    "addr:street":"Bayerng",
    "iso:country":"AT",
    "sg:address":"Bayerng 3/5",
    "sg:city":"Wien",
    "sg:classifiers":[
        {
            "category":"Organizations",
            "subcategory":"Community Association",
            "type":"Services"
        }
    ],
    "sg:phone":"+43 1 50593220",
    "sg:postcode":"1030",
    "sg:province":"Wien",
    "sg:tags":[
        "relation",
        "public"
    ],
    "wof:name":"Herzer Communications",
    "wof:placetype":"venue"
},
  "geometry": {"coordinates":[16.3819828033,48.2008705139],"type":"Point"}
}