{
  "type": "Feature",
  "properties": {
    "addr:full":"Trillerg 4 EKZ Wien Wien 1210",
    "addr:housenumber":"4",
    "addr:postcode":"1210",
    "addr:street":"Trillerg",
    "iso:country":"AT",
    "sg:address":"Trillerg 4 EKZ",
    "sg:city":"Wien",
    "sg:orig_category":"Bankomat-Standorte",
    "sg:phone":"+43 1 2948270",
    "sg:postcode":"1210",
    "sg:province":"Wien",
    "wof:name":"Bankomat d Die Burgenl\u00e4ndische Anlage & Kredit Bank AG",
    "wof:placetype":"venue"
},
  "geometry": {"coordinates":[16.3978404999,48.2579994202],"type":"Point"}
}