{
  "type": "Feature",
  "properties": {
    "addr:full":"Bahnhof 416 Bezau Vorarlberg 6870",
    "addr:housenumber":"416",
    "addr:postcode":"6870",
    "addr:street":"Bahnhof",
    "iso:country":"AT",
    "sg:address":"Bahnhof 416",
    "sg:city":"Bezau",
    "sg:orig_category":"Friseure U Frisiersalons",
    "sg:phone":"+43 4355 14217213",
    "sg:postcode":"6870",
    "sg:province":"Vorarlberg",
    "wof:name":"Lipburger Hermann",
    "wof:placetype":"venue"
},
  "geometry": {"coordinates":[9.89752388,47.3811302185],"type":"Point"}
}