{
  "type": "Feature",
  "properties": {
    "addr:full":"Durisolstr 1 Wels Ober\u00f6sterreich 4600",
    "addr:housenumber":"1",
    "addr:postcode":"4600",
    "addr:street":"Durisolstr;Oberoesterreich",
    "iso:country":"AT",
    "sg:address":"Durisolstr 1",
    "sg:city":"Wels",
    "sg:orig_category":"Personalberatung",
    "sg:phone":"+43 4372 4277948",
    "sg:postcode":"4600",
    "sg:province":"Ober\u00f6sterreich",
    "wof:name":"ACCO Personalservice u Montage GmbH",
    "wof:placetype":"venue"
},
  "geometry": {"coordinates":[14.0084609985,48.1513252258],"type":"Point"}
}