{
  "type": "Feature",
  "properties": {
    "iso:country":"AT",
    "sg:address":"Marxerg 40",
    "sg:city":"Wien",
    "sg:classifiers":[
        {
            "category":"Restaurant",
            "type":"Food & Drink"
        }
    ],
    "sg:phone":"+43 1 599100",
    "sg:postcode":"1030",
    "sg:province":"Wien",
    "sg:tags":[
        "pizzeria"
    ],
    "wof:name":"Pizza Flitzer",
    "wof:placetype":"venue"
},
  "geometry": {"coordinates":[16.3934650421,48.2056388855],"type":"Point"}
}