{
  "type": "Feature",
  "properties": {
    "addr:full":"Fischachstr 11 Hallwang Salzburg 5300",
    "addr:housenumber":"11",
    "addr:postcode":"5300",
    "addr:street":"Fischachstr;Salzburg",
    "iso:country":"AT",
    "sg:address":"Fischachstr 11",
    "sg:city":"Hallwang",
    "sg:orig_category":"Werbeagenturen",
    "sg:phone":"+43 662 4280200",
    "sg:postcode":"5300",
    "sg:province":"Salzburg",
    "wof:name":"pos-hauer gmbh",
    "wof:placetype":"venue"
},
  "geometry": {"coordinates":[13.0884847641,47.8602180481],"type":"Point"}
}