{
  "type": "Feature",
  "properties": {
    "addr:full":"D\u00f6blerhofstrasse 14 Wien Wien 1110",
    "addr:housenumber":"14",
    "addr:postcode":"1110",
    "addr:street":"Doeblerhofstrasse",
    "iso:country":"AT",
    "sg:address":"D\u00f6blerhofstrasse 14",
    "sg:city":"Wien",
    "sg:classifiers":[
        {
            "category":"Food & Beverages",
            "subcategory":"Meat & Fish",
            "type":"Retail Goods"
        }
    ],
    "sg:phone":"+43 1 740160",
    "sg:postcode":"1110",
    "sg:province":"Wien",
    "sg:tags":[
        "preserves",
        "delicacy"
    ],
    "sg:website":"nordsee.at",
    "wof:name":"Nordsee Ges.m.b.H.",
    "wof:placetype":"venue"
},
  "geometry": {"coordinates":[16.4152030945,48.1851577759],"type":"Point"}
}