{
  "type": "Feature",
  "properties": {
    "addr:full":"Nr 35 Timmersdorf Steiermark 8772",
    "addr:postcode":"8772",
    "addr:street":"Nr",
    "iso:country":"AT",
    "sg:address":"Nr 35",
    "sg:city":"Timmersdorf",
    "sg:orig_category":"Fleischhauereien",
    "sg:phone":"+43 3833 8214",
    "sg:postcode":"8772",
    "sg:province":"Steiermark",
    "wof:name":"Loschat Harald",
    "wof:placetype":"venue"
},
  "geometry": {"coordinates":[14.9870042801,47.3773269653],"type":"Point"}
}