{
  "type": "Feature",
  "properties": {
    "addr:full":"Adolf Lorenz-G Wien Wien 1130",
    "addr:postcode":"1130",
    "iso:country":"AT",
    "sg:address":"Adolf Lorenz-G",
    "sg:city":"Wien",
    "sg:orig_category":"Beratungsstellen",
    "sg:phone":"+43 1 8763061",
    "sg:postcode":"1130",
    "sg:province":"Wien",
    "wof:name":"Rechtskomitee Lambda - Rechtsberatung und Hilfe f homosexuelle Frauen und M\u00e4nner",
    "wof:placetype":"venue"
},
  "geometry": {"coordinates":[16.2947654724,48.1782302856],"type":"Point"}
}