{
  "type": "Feature",
  "properties": {
    "addr:full":"St.-Peter-Str 5/1 Klagenfurt K\u00e4rnten 9020",
    "addr:housenumber":"5 / 1",
    "addr:postcode":"9020",
    "addr:street":"St.-Peter-Str;Kaernten",
    "iso:country":"AT",
    "sg:address":"St.-Peter-Str 5/1",
    "sg:city":"Klagenfurt",
    "sg:orig_category":"Botendienste",
    "sg:phone":"+43 463 3104400",
    "sg:postcode":"9020",
    "sg:province":"K\u00e4rnten",
    "wof:name":"Botendienst Fuchs",
    "wof:placetype":"venue"
},
  "geometry": {"coordinates":[14.3239917755,46.6182861328],"type":"Point"}
}