{
  "type": "Feature",
  "properties": {
    "iso:country":"AT",
    "sg:address":"Sarsteinstr 21",
    "sg:city":"Bad Aussee",
    "sg:orig_category":"Pensionen / Privatzimmer",
    "sg:phone":"+43 3622 546600",
    "sg:postcode":"8990",
    "sg:province":"Steiermark",
    "wof:name":"Haus Stangl",
    "wof:placetype":"venue"
},
  "geometry": {"coordinates":[13.7181758881,47.5768585205],"type":"Point"}
}