{
  "type": "Feature",
  "properties": {
    "addr:full":"Enzersberg 130 Thalgau Salzburg 5303",
    "addr:housenumber":"130",
    "addr:postcode":"5303",
    "addr:street":"Enzersberg;Salzburg",
    "iso:country":"AT",
    "sg:address":"Enzersberg 130",
    "sg:city":"Thalgau",
    "sg:classifiers":[
        {
            "category":"Government",
            "subcategory":"Department Of Motor Vehicles",
            "type":"Public Place"
        }
    ],
    "sg:phone":"+43 6235 67770",
    "sg:postcode":"5303",
    "sg:province":"Salzburg",
    "sg:tags":[
        "part",
        "bought-in"
    ],
    "sg:website":"enzersberger.at",
    "wof:name":"Enzersberger Metallfertigungstechnik GmbH",
    "wof:placetype":"venue"
},
  "geometry": {"coordinates":[13.1954441071,47.8485679626],"type":"Point"}
}