{
  "type": "Feature",
  "properties": {
    "addr:full":"Allhartsberg 133 Kematen an der Ybbs Nieder\u00f6sterreich 3331",
    "addr:housenumber":"133",
    "addr:postcode":"3331",
    "addr:street":"Allhartsberg",
    "iso:country":"AT",
    "sg:address":"Allhartsberg 133",
    "sg:city":"Kematen an der Ybbs",
    "sg:orig_category":"LocksmithS Shops",
    "sg:phone":"+43 7448 2430",
    "sg:postcode":"3331",
    "sg:province":"Nieder\u00f6sterreich",
    "sg:website":"metall-schiefer.at",
    "wof:name":"Helmut Schiefer",
    "wof:placetype":"venue"
},
  "geometry": {"coordinates":[14.8144960403,48.0151939392],"type":"Point"}
}