{
  "type": "Feature",
  "properties": {
    "iso:country":"AT",
    "sg:address":"Waldeben 1",
    "sg:city":"Weerberg",
    "sg:classifiers":[
        {
            "category":"Food & Beverages",
            "subcategory":"Cheese",
            "type":"Retail Goods"
        }
    ],
    "sg:phone":"+43 5224 68244",
    "sg:postcode":"6133",
    "sg:province":"Tirol",
    "sg:website":"graukaese.at",
    "wof:name":"Thomas Lieb Grauk\u00e4seerzeugung",
    "wof:placetype":"venue"
},
  "geometry": {"coordinates":[11.6784667969,47.3143615723],"type":"Point"}
}