{
  "type": "Feature",
  "properties": {
    "iso:country":"AT",
    "sg:address":"Unterer Bonauweg 31",
    "sg:city":"Salzburg",
    "sg:classifiers":[
        {
            "category":"Retail",
            "subcategory":"Repair Shop",
            "type":"Services"
        }
    ],
    "sg:phone":"+43 662 435307",
    "sg:postcode":"5020",
    "sg:province":"Salzburg",
    "sg:tags":[
        "compressor",
        "gas",
        "air"
    ],
    "sg:website":"kompressorenbau.at",
    "wof:name":"Josef Schmidleitner",
    "wof:placetype":"venue"
},
  "geometry": {"coordinates":[13.0112934113,47.825843811],"type":"Point"}
}