{
  "type": "Feature",
  "properties": {
    "iso:country":"AT",
    "sg:address":"Ludwig-Heinrich-Jungnickel-Str 1/1/40",
    "sg:city":"Villach",
    "sg:orig_category":"Gerichtsdolmetscher",
    "sg:phone":"+43 4342 4259414",
    "sg:postcode":"9500",
    "sg:province":"K\u00e4rnten",
    "wof:name":"D'Angelo Andreas",
    "wof:placetype":"venue"
},
  "geometry": {"coordinates":[13.8284702301,46.6152381897],"type":"Point"}
}