{
  "type": "Feature",
  "properties": {
    "addr:full":"Wiener Str 23 St. Florian Ober\u00f6sterreich 4490",
    "addr:housenumber":"23",
    "addr:postcode":"4490",
    "addr:street":"St.;Oberoesterreich",
    "iso:country":"AT",
    "sg:address":"Wiener Str 23",
    "sg:city":"St. Florian",
    "sg:orig_category":"Autohandel",
    "sg:phone":"+43 7224 42170",
    "sg:postcode":"4490",
    "sg:province":"Ober\u00f6sterreich",
    "wof:name":"Autohaus BRUNNER",
    "wof:placetype":"venue"
},
  "geometry": {"coordinates":[14.3847389221,48.2074508667],"type":"Point"}
}