{
  "type": "Feature",
  "properties": {
    "addr:full":"Maria-Platzer-Str 8 Klagenfurt K\u00e4rnten 9020",
    "addr:housenumber":"8",
    "addr:postcode":"9020",
    "addr:street":"Maria-Platzer-Str;Kaernten",
    "iso:country":"AT",
    "sg:address":"Maria-Platzer-Str 8",
    "sg:city":"Klagenfurt",
    "sg:orig_category":"Lebensmittel / Einzelhandel",
    "sg:phone":"+43 463 210204",
    "sg:postcode":"9020",
    "sg:province":"K\u00e4rnten",
    "wof:name":"SPAR \u00f6sterreichische Warenhandels-AG",
    "wof:placetype":"venue"
},
  "geometry": {"coordinates":[14.2837724686,46.612651825],"type":"Point"}
}