{
  "type": "Feature",
  "properties": {
    "iso:country":"AT",
    "sg:address":"Schaumanng 8",
    "sg:city":"Stockerau",
    "sg:orig_category":"Massagen",
    "sg:phone":"+43 4322 6663997",
    "sg:postcode":"2000",
    "sg:province":"Nieder\u00f6sterreich",
    "wof:name":"Massagefachinstitut Breyer - Holovics",
    "wof:placetype":"venue"
},
  "geometry": {"coordinates":[16.2011032104,48.3866691589],"type":"Point"}
}