{
  "type": "Feature",
  "properties": {
    "iso:country":"AT",
    "sg:address":"Theresienthalstr 11-13",
    "sg:city":"Hausmening",
    "sg:orig_category":"Automatisierungstechnik",
    "sg:phone":"+43 7475 541000",
    "sg:postcode":"3363",
    "sg:province":"Nieder\u00f6sterreich",
    "wof:name":"E A S Automatisierungstechnik BeratungsgesmbH",
    "wof:placetype":"venue"
},
  "geometry": {"coordinates":[14.813949585,48.076133728],"type":"Point"}
}