{
  "type": "Feature",
  "properties": {
    "addr:full":"Klosteralm 1 Lilienfeld Nieder\u00f6sterreich 3180",
    "addr:housenumber":"1",
    "addr:postcode":"3180",
    "addr:street":"Klosteralm",
    "iso:country":"AT",
    "sg:address":"Klosteralm 1",
    "sg:city":"Lilienfeld",
    "sg:orig_category":"Bergbahnen",
    "sg:phone":"+43 2762 53570",
    "sg:postcode":"3180",
    "sg:province":"Nieder\u00f6sterreich",
    "wof:name":"Schiland Voralpen GesmbH",
    "wof:placetype":"venue"
},
  "geometry": {"coordinates":[15.596619606,48.0180015564],"type":"Point"}
}