{
  "type": "Feature",
  "properties": {
    "addr:full":"Europastr 15 Feldbach Steiermark 8330",
    "addr:housenumber":"15",
    "addr:postcode":"8330",
    "addr:street":"Europastr",
    "iso:country":"AT",
    "sg:address":"Europastr 15",
    "sg:city":"Feldbach",
    "sg:orig_category":"Lederwaren / Einzelhandel",
    "sg:phone":"+43 3152 6457",
    "sg:postcode":"8330",
    "sg:province":"Steiermark",
    "wof:name":"SMG Lindenau & Lindenau GmbH",
    "wof:placetype":"venue"
},
  "geometry": {"coordinates":[15.9072132111,46.9529685974],"type":"Point"}
}