{
  "type": "Feature",
  "properties": {
    "addr:full":"Mariahilfer Str 84 Wien Wien 1070",
    "addr:postcode":"1070",
    "addr:street":"Str 84",
    "iso:country":"AT",
    "sg:address":"Mariahilfer Str 84",
    "sg:city":"Wien",
    "sg:classifiers":[
        {
            "category":"Professional",
            "subcategory":"Management & Consulting",
            "type":"Services"
        }
    ],
    "sg:phone":"+43 1 5261102",
    "sg:postcode":"1070",
    "sg:province":"Wien",
    "wof:name":"Benischek Erich",
    "wof:placetype":"venue"
},
  "geometry": {"coordinates":[16.3478355408,48.197681427],"type":"Point"}
}