{
  "type": "Feature",
  "properties": {
    "iso:country":"AT",
    "sg:address":"Tragweiner Str 30",
    "sg:city":"Pregarten",
    "sg:orig_category":"Optiker",
    "sg:phone":"+43 7236 3880",
    "sg:postcode":"4230",
    "sg:province":"Ober\u00f6sterreich",
    "wof:name":"Optik Weiss",
    "wof:placetype":"venue"
},
  "geometry": {"coordinates":[14.5337057114,48.3539848328],"type":"Point"}
}