{
  "type": "Feature",
  "properties": {
    "addr:full":"Pottendorfer Str 3 Wiener Neustadt Nieder\u00f6sterreich 2700",
    "addr:postcode":"2700",
    "addr:street":"Str",
    "iso:country":"AT",
    "sg:address":"Pottendorfer Str 3",
    "sg:city":"Wiener Neustadt",
    "sg:orig_category":"Sonnenstudios",
    "sg:phone":"+43 664 5132980",
    "sg:postcode":"2700",
    "sg:province":"Nieder\u00f6sterreich",
    "wof:name":"Sonnenstudio Turbo Sun",
    "wof:placetype":"venue"
},
  "geometry": {"coordinates":[16.2472133636,47.8228492737],"type":"Point"}
}