{
  "type": "Feature",
  "properties": {
    "iso:country":"AT",
    "sg:address":"Sechshauser Str 97",
    "sg:city":"Wien",
    "sg:orig_category":"Friseure U Frisiersalons",
    "sg:phone":"+43 1 8920512",
    "sg:postcode":"1150",
    "sg:province":"Wien",
    "wof:name":"Frisiersalon Katharina Lehner",
    "wof:placetype":"venue"
},
  "geometry": {"coordinates":[16.322435379,48.1860198975],"type":"Point"}
}