{
  "type": "Feature",
  "properties": {
    "addr:full":"Nr 72 Angern Nieder\u00f6sterreich 2261",
    "addr:postcode":"2261",
    "addr:street":"Nr;Angern",
    "iso:country":"AT",
    "sg:address":"Nr 72",
    "sg:city":"Angern",
    "sg:orig_category":"Non-Classified Establishments",
    "sg:phone":"+43 2284 2285",
    "sg:postcode":"2261",
    "sg:province":"Nieder\u00f6sterreich",
    "wof:name":"Pfarramt",
    "wof:placetype":"venue"
},
  "geometry": {"coordinates":[16.8282699585,48.3832092285],"type":"Point"}
}