{
  "type": "Feature",
  "properties": {
    "addr:full":"Brunner Feldstr 53 Perchtoldsdorf Nieder\u00f6sterreich 2380",
    "addr:housenumber":"53",
    "addr:postcode":"2380",
    "addr:street":"Feldstr",
    "iso:country":"AT",
    "sg:address":"Brunner Feldstr 53",
    "sg:city":"Perchtoldsdorf",
    "sg:orig_category":"Badezimmer U Badezimmereinrichtungen",
    "sg:phone":"+43 4318 6302311",
    "sg:postcode":"2380",
    "sg:province":"Nieder\u00f6sterreich",
    "sg:website":"baederparadies.at",
    "wof:name":"B\u00e4derparadies",
    "wof:placetype":"venue"
},
  "geometry": {"coordinates":[16.2928562164,48.1231269836],"type":"Point"}
}