{
  "type": "Feature",
  "properties": {
    "iso:country":"AT",
    "sg:address":"Schlo\u00dfstr 1",
    "sg:city":"Alkoven",
    "sg:orig_category":"Museen / Ausstellungen",
    "sg:phone":"+43 7274 20320",
    "sg:postcode":"4072",
    "sg:province":"Ober\u00f6sterreich",
    "wof:name":"Lern- und Gedenkort Schlo\u00df Hartheim",
    "wof:placetype":"venue"
},
  "geometry": {"coordinates":[14.1054210663,48.2859916687],"type":"Point"}
}