{
  "type": "Feature",
  "properties": {
    "addr:full":"Nr 89 Bad Waltersdorf Steiermark 8271",
    "addr:housenumber":"89",
    "addr:postcode":"8271",
    "addr:street":"Nr",
    "iso:country":"AT",
    "sg:address":"Nr 89",
    "sg:city":"Bad Waltersdorf",
    "sg:orig_category":"Schneidereien",
    "sg:phone":"+43 3333 26033",
    "sg:postcode":"8271",
    "sg:province":"Steiermark",
    "wof:name":"Tina's Salon Mode etc",
    "wof:placetype":"venue"
},
  "geometry": {"coordinates":[16.0086784363,47.1696166992],"type":"Point"}
}