{
  "type": "Feature",
  "properties": {
    "addr:full":"Stadtpl 55 Schwanenstadt Ober\u00f6sterreich 4690",
    "addr:housenumber":"55",
    "addr:postcode":"4690",
    "addr:street":"Stadtpl",
    "iso:country":"AT",
    "sg:address":"Stadtpl 55",
    "sg:city":"Schwanenstadt",
    "sg:orig_category":"Immobilienmakler",
    "sg:phone":"+43 76734306",
    "sg:postcode":"4690",
    "sg:province":"Ober\u00f6sterreich",
    "wof:name":"Schlesinger-Kirchwehr Jost Immobilien KEG",
    "wof:placetype":"venue"
},
  "geometry": {"coordinates":[13.7734670639,48.0544586182],"type":"Point"}
}