{
  "type": "Feature",
  "properties": {
    "iso:country":"AT",
    "sg:address":"Peter-Neuschmid-Str 2",
    "sg:city":"Westendorf",
    "sg:orig_category":"Friseure U Frisiersalons",
    "sg:phone":"+43 4353 346565",
    "sg:postcode":"6363",
    "sg:province":"Tirol",
    "wof:name":"Haarstudio Veronika - Inh Fischler Veronika",
    "wof:placetype":"venue"
},
  "geometry": {"coordinates":[12.2137022018,47.4324188232],"type":"Point"}
}