{
  "type": "Feature",
  "properties": {
    "addr:full":"Schlangglfeld 5 Hall in Tirol Tirol 6060",
    "addr:housenumber":"5",
    "addr:postcode":"6060",
    "addr:street":"Schlangglfeld;Tirol",
    "iso:country":"AT",
    "sg:address":"Schlangglfeld 5",
    "sg:city":"Hall in Tirol",
    "sg:orig_category":"Handelsagenturen",
    "sg:phone":"+43 5223 93204",
    "sg:postcode":"6060",
    "sg:province":"Tirol",
    "wof:name":"Zaderer Wolfgang",
    "wof:placetype":"venue"
},
  "geometry": {"coordinates":[11.5211305618,47.2856941223],"type":"Point"}
}