{
  "type": "Feature",
  "properties": {
    "iso:country":"AT",
    "sg:address":"Hammerschmiedstr 2",
    "sg:city":"Waidhofen an der Ybbs",
    "sg:orig_category":"Lebensmittel / Einzelhandel",
    "sg:phone":"+43 4374 4254800",
    "sg:postcode":"3340",
    "sg:province":"Nieder\u00f6sterreich",
    "wof:name":"SPAR \u00f6sterreichische Warenhandels-AG",
    "wof:placetype":"venue"
},
  "geometry": {"coordinates":[14.7915887833,47.949005127],"type":"Point"}
}