{
  "type": "Feature",
  "properties": {
    "addr:full":"Bahnhofstr 47 Kematen in Tirol Tirol 6175",
    "addr:housenumber":"47",
    "addr:postcode":"6175",
    "addr:street":"Bahnhofstr;Tirol",
    "iso:country":"AT",
    "sg:address":"Bahnhofstr 47",
    "sg:city":"Kematen in Tirol",
    "sg:orig_category":"Wasseraufbereitung U -Reinigung",
    "sg:phone":"+43 4352 322244222",
    "sg:postcode":"6175",
    "sg:province":"Tirol",
    "wof:name":"Biocat Wassertechnik Vertriebs GmbH & Co. KG",
    "wof:placetype":"venue"
},
  "geometry": {"coordinates":[11.2765197754,47.2609481812],"type":"Point"}
}