{
  "type": "Feature",
  "properties": {
    "addr:full":"Steing 10a Pucking Ober\u00f6sterreich 4055",
    "addr:housenumber":"10a",
    "addr:postcode":"4055",
    "addr:street":"Steing",
    "iso:country":"AT",
    "sg:address":"Steing 10a",
    "sg:city":"Pucking",
    "sg:orig_category":"Elektroinstallationsunternehmen",
    "sg:phone":"+43 7229 78639",
    "sg:postcode":"4055",
    "sg:province":"Ober\u00f6sterreich",
    "wof:name":"Wild Elektrotechnik OEG",
    "wof:placetype":"venue"
},
  "geometry": {"coordinates":[14.179060936,48.1819229126],"type":"Point"}
}