{
  "type": "Feature",
  "properties": {
    "addr:full":"Nr 20a Bad Kreuzen Ober\u00f6sterreich 4362",
    "addr:housenumber":"20a",
    "addr:postcode":"4362",
    "addr:street":"Nr",
    "iso:country":"AT",
    "sg:address":"Nr 20a",
    "sg:city":"Bad Kreuzen",
    "sg:orig_category":"Tourismusinformation U -Organisationen",
    "sg:phone":"+43 4372 66625578",
    "sg:postcode":"4362",
    "sg:province":"Ober\u00f6sterreich",
    "wof:name":"Tourismusverband",
    "wof:placetype":"venue"
},
  "geometry": {"coordinates":[14.8063306808,48.267124176],"type":"Point"}
}