{
  "type": "Feature",
  "properties": {
    "iso:country":"AT",
    "sg:address":"Mooswinkl 43",
    "sg:city":"Vomp",
    "sg:orig_category":"Weiterbildungsinstitute M Allg U Berufl Bildungsangebot",
    "sg:phone":"+43 5242 93723",
    "sg:postcode":"6134",
    "sg:province":"Tirol",
    "wof:name":"Erwachsenenschule Vomp-Stans",
    "wof:placetype":"venue"
},
  "geometry": {"coordinates":[11.6888093948,47.3440170288],"type":"Point"}
}