{
  "type": "Feature",
  "properties": {
    "addr:full":"Himmelpfortg 11 Wien Wien 1010",
    "addr:housenumber":"11",
    "addr:postcode":"1010",
    "addr:street":"Himmelpfortg",
    "iso:country":"AT",
    "sg:address":"Himmelpfortg 11",
    "sg:city":"Wien",
    "sg:orig_category":"Psychologen",
    "sg:phone":"+43 1 7151303",
    "sg:postcode":"1010",
    "sg:province":"Wien",
    "wof:name":"Hueber Brigitte Mag - Klinische- und Gesundheitspsychologin",
    "wof:placetype":"venue"
},
  "geometry": {"coordinates":[16.373128891,48.2057304382],"type":"Point"}
}