{
  "type": "Feature",
  "properties": {
    "addr:full":"Dirnbergerstr 13 Perg Ober\u00f6sterreich 4320",
    "addr:housenumber":"13",
    "addr:postcode":"4320",
    "addr:street":"Dirnbergerstr",
    "iso:country":"AT",
    "sg:address":"Dirnbergerstr 13",
    "sg:city":"Perg",
    "sg:orig_category":"Werbegrafik- U Grafik-Design",
    "sg:phone":"+43 7262 52743",
    "sg:postcode":"4320",
    "sg:province":"Ober\u00f6sterreich",
    "wof:name":"Gruber Grafik-Designer",
    "wof:placetype":"venue"
},
  "geometry": {"coordinates":[14.635219574,48.2461700439],"type":"Point"}
}