{
  "type": "Feature",
  "properties": {
    "addr:full":"Dorfbahnstr 51 Serfaus Tirol 6534",
    "addr:housenumber":"51",
    "addr:postcode":"6534",
    "addr:street":"Dorfbahnstr;Tirol",
    "iso:country":"AT",
    "sg:address":"Dorfbahnstr 51",
    "sg:city":"Serfaus",
    "sg:orig_category":"Pensionen / Privatzimmer",
    "sg:phone":"+43 5476 6283",
    "sg:postcode":"6534",
    "sg:province":"Tirol",
    "wof:name":"R\u00f6merhof Pension-garni",
    "wof:placetype":"venue"
},
  "geometry": {"coordinates":[10.6037521362,47.0387306213],"type":"Point"}
}