{
  "type": "Feature",
  "properties": {
    "addr:full":"Forchtensteinweg 30 Marz Burgenland 7221",
    "addr:housenumber":"30",
    "addr:postcode":"7221",
    "addr:street":"Forchtensteinweg",
    "iso:country":"AT",
    "sg:address":"Forchtensteinweg 30",
    "sg:city":"Marz",
    "sg:orig_category":"Maler, Anstreicher U Lackierer",
    "sg:phone":"+43 2626 63984",
    "sg:postcode":"7221",
    "sg:province":"Burgenland",
    "wof:name":"Lehrner Michael",
    "wof:placetype":"venue"
},
  "geometry": {"coordinates":[16.4098434448,47.7163352966],"type":"Point"}
}