{
  "type": "Feature",
  "properties": {
    "iso:country":"AT",
    "sg:address":"Triester Str 50 A",
    "sg:city":"Wien",
    "sg:orig_category":"Autoreparatur, Autohandel",
    "sg:phone":"+43 1 601420",
    "sg:postcode":"1100",
    "sg:province":"Wien",
    "sg:website":"peugeot-wien.at",
    "wof:name":"PEUGEOT WIEN",
    "wof:placetype":"venue"
},
  "geometry": {"coordinates":[16.3510799408,48.1715736389],"type":"Point"}
}