{
  "type": "Feature",
  "properties": {
    "iso:country":"AT",
    "sg:city":"Gr\u00f6bming",
    "sg:orig_category":"Feuerwehren",
    "sg:phone":"+43 3685 23354",
    "sg:postcode":"8962",
    "sg:province":"Steiermark",
    "wof:name":"Freiwillige Feuerwehr Mitterberg",
    "wof:placetype":"venue"
},
  "geometry": {"coordinates":[13.9440145493,47.4527168274],"type":"Point"}
}