{
  "type": "Feature",
  "properties": {
    "addr:full":"Marktpl 43 Haslach an der M\u00fchl Ober\u00f6sterreich 4170",
    "addr:housenumber":"43",
    "addr:postcode":"4170",
    "addr:street":"Marktpl;Oberoesterreich",
    "iso:country":"AT",
    "sg:address":"Marktpl 43",
    "sg:city":"Haslach an der M\u00fchl",
    "sg:orig_category":"Fleischhauereien",
    "sg:phone":"+43 4372 89712360",
    "sg:postcode":"4170",
    "sg:province":"Ober\u00f6sterreich",
    "wof:name":"Klimitsch Ludwig",
    "wof:placetype":"venue"
},
  "geometry": {"coordinates":[14.040766716,48.5755386353],"type":"Point"}
}