{
  "type": "Feature",
  "properties": {
    "addr:full":"Pirath 1 Altheim Ober\u00f6sterreich 4950",
    "addr:housenumber":"1",
    "addr:postcode":"4950",
    "addr:street":"Pirath",
    "iso:country":"AT",
    "sg:address":"Pirath 1",
    "sg:city":"Altheim",
    "sg:classifiers":[
        {
            "category":"Bars & Pubs",
            "subcategory":"Dive Bar",
            "type":"Food & Drink"
        }
    ],
    "sg:phone":"+43 7723 43750",
    "sg:postcode":"4950",
    "sg:province":"Ober\u00f6sterreich",
    "sg:tags":[
        "column",
        "granite"
    ],
    "wof:name":"Josef Faschang Pic-Stein",
    "wof:placetype":"venue"
},
  "geometry": {"coordinates":[13.2192296982,48.2503242493],"type":"Point"}
}