{
  "type": "Feature",
  "properties": {
    "addr:full":"Hollerg 41 Wien Wien 1150",
    "addr:housenumber":"41",
    "addr:postcode":"1150",
    "addr:street":"Hollerg",
    "iso:country":"AT",
    "sg:address":"Hollerg 41",
    "sg:city":"Wien",
    "sg:orig_category":"Fotoapparate U -Artikel / Einzelhandel",
    "sg:phone":"+43 1 89944",
    "sg:postcode":"1150",
    "sg:province":"Wien",
    "wof:name":"Lomographische AG",
    "wof:placetype":"venue"
},
  "geometry": {"coordinates":[16.3239021301,48.1890144348],"type":"Point"}
}