{
  "type": "Feature",
  "properties": {
    "iso:country":"AT",
    "sg:address":"Loferer Bundesstr 50a",
    "sg:city":"Saalfelden am Steinernen Meer",
    "sg:orig_category":"Non-Classified Establishments",
    "sg:phone":"+43 5 91335183",
    "sg:postcode":"5760",
    "sg:province":"Salzburg",
    "wof:name":"Gendarmerie Saalfelden",
    "wof:placetype":"venue"
},
  "geometry": {"coordinates":[12.8407926559,47.4403953552],"type":"Point"}
}