{
  "type": "Feature",
  "properties": {
    "addr:full":"Speckbacherstr 29 Innsbruck Tirol 6020",
    "addr:housenumber":"29",
    "addr:postcode":"6020",
    "addr:street":"Speckbacherstr;Tirol",
    "iso:country":"AT",
    "sg:address":"Speckbacherstr 29",
    "sg:city":"Innsbruck",
    "sg:orig_category":"Studentenheime",
    "sg:phone":"+43 512 562560",
    "sg:postcode":"6020",
    "sg:province":"Tirol",
    "wof:name":"Kath Studentenheim",
    "wof:placetype":"venue"
},
  "geometry": {"coordinates":[11.390083313,47.2595977783],"type":"Point"}
}