{
  "type": "Feature",
  "properties": {
    "iso:country":"AT",
    "sg:address":"Bundesstr 50",
    "sg:city":"Mattersburg",
    "sg:orig_category":"Matratzen",
    "sg:phone":"+43 2626 68074",
    "sg:postcode":"7210",
    "sg:province":"Burgenland",
    "wof:name":"BETTEN MAX GmbH",
    "wof:placetype":"venue"
},
  "geometry": {"coordinates":[16.4151268005,47.7406387329],"type":"Point"}
}