{
  "type": "Feature",
  "properties": {
    "iso:country":"AT",
    "sg:address":"Weigunystr 8",
    "sg:city":"Linz",
    "sg:orig_category":"Nachhilfe U Lernbetreuung",
    "sg:phone":"+43 4373 2737679",
    "sg:postcode":"4040",
    "sg:province":"Ober\u00f6sterreich",
    "wof:name":"Lernen-Sport-Spiel-LSS-Ferienschule Markus Mayr",
    "wof:placetype":"venue"
},
  "geometry": {"coordinates":[14.2825727463,48.3237724304],"type":"Point"}
}