{
  "type": "Feature",
  "properties": {
    "addr:full":"Dr.-Kolisko-Pl 5 Hollabrunn Nieder\u00f6sterreich 2020",
    "addr:housenumber":"5",
    "addr:postcode":"2020",
    "addr:street":"Dr.-Kolisko-Pl",
    "iso:country":"AT",
    "sg:address":"Dr.-Kolisko-Pl 5",
    "sg:city":"Hollabrunn",
    "sg:orig_category":"Politische Parteien",
    "sg:phone":"+43 4329 5230307",
    "sg:postcode":"2020",
    "sg:province":"Nieder\u00f6sterreich",
    "wof:name":"Sozialistische Jugend N\u00f6",
    "wof:placetype":"venue"
},
  "geometry": {"coordinates":[16.0802593231,48.5635032654],"type":"Point"}
}