{
  "type": "Feature",
  "properties": {
    "iso:country":"AT",
    "sg:address":"F Hinterholzer-Kai 4",
    "sg:city":"Salzburg",
    "sg:orig_category":"Polizei U Gendarmerie",
    "sg:phone":"+43 5 913350",
    "sg:postcode":"5020",
    "sg:province":"Salzburg",
    "wof:name":"Landesgendarmeriekommando f Salzburg in Salzburg",
    "wof:placetype":"venue"
},
  "geometry": {"coordinates":[13.0600404739,47.7941703796],"type":"Point"}
}