{
  "type": "Feature",
  "properties": {
    "iso:country":"AT",
    "sg:address":"Erlacherg 20",
    "sg:city":"Wiener Neustadt",
    "sg:orig_category":"Physiotherapie",
    "sg:phone":"+43 2622 27093",
    "sg:postcode":"2700",
    "sg:province":"Nieder\u00f6sterreich",
    "wof:name":"Zolda-Wagner Martina Dipl-PT",
    "wof:placetype":"venue"
},
  "geometry": {"coordinates":[16.236536026,47.797000885],"type":"Point"}
}