{
  "type": "Feature",
  "properties": {
    "addr:full":"Drei L\u00e4rchen 150 Bad Bleiberg K\u00e4rnten 9530",
    "addr:housenumber":"150",
    "addr:postcode":"9530",
    "iso:country":"AT",
    "sg:address":"Drei L\u00e4rchen 150",
    "sg:city":"Bad Bleiberg",
    "sg:classifiers":[
        {
            "category":"Travel",
            "subcategory":"Hotels & Motels",
            "type":"Entertainment"
        }
    ],
    "sg:phone":"+43 4244 2205",
    "sg:postcode":"9530",
    "sg:province":"K\u00e4rnten",
    "wof:name":"Hotel Bleibergerhof",
    "wof:placetype":"venue"
},
  "geometry": {"coordinates":[13.6877374649,46.6243476868],"type":"Point"}
}