{
  "type": "Feature",
  "properties": {
    "iso:country":"AT",
    "sg:address":"Fillgraderg 5",
    "sg:city":"Wien",
    "sg:classifiers":[
        {
            "category":"Retail",
            "subcategory":"Event Space",
            "type":"Services"
        }
    ],
    "sg:phone":"+43 4315 861087",
    "sg:postcode":"1060",
    "sg:province":"Wien",
    "sg:tags":[
        "hand-",
        "u",
        "fu\u00c3\u0178pflege"
    ],
    "wof:name":"Kerschbaumer Fu\u00dfpflege Wilde Ingrid",
    "wof:placetype":"venue"
},
  "geometry": {"coordinates":[16.3591022491,48.1998786926],"type":"Point"}
}