{
  "type": "Feature",
  "properties": {
    "addr:full":"Braung 195 Bad Aussee Steiermark 8990",
    "addr:housenumber":"195",
    "addr:postcode":"8990",
    "iso:country":"AT",
    "sg:address":"Braung 195",
    "sg:city":"Bad Aussee",
    "sg:orig_category":"Maler, Anstreicher U Lackierer",
    "sg:phone":"+43 4336 2252263",
    "sg:postcode":"8990",
    "sg:province":"Steiermark",
    "wof:name":"Schranz Johann",
    "wof:placetype":"venue"
},
  "geometry": {"coordinates":[13.7828645706,47.6105499268],"type":"Point"}
}