{
  "type": "Feature",
  "properties": {
    "addr:full":"Neubaug 44 Wien Wien 1070",
    "addr:housenumber":"44",
    "addr:postcode":"1070",
    "addr:street":"Neubaug",
    "iso:country":"AT",
    "sg:address":"Neubaug 44",
    "sg:city":"Wien",
    "sg:orig_category":"Handschuhe",
    "sg:phone":"+43 1 5226993",
    "sg:postcode":"1070",
    "sg:province":"Wien",
    "wof:name":"Amit Christine",
    "wof:placetype":"venue"
},
  "geometry": {"coordinates":[16.3383293152,48.2016792297],"type":"Point"}
}