{
  "type": "Feature",
  "properties": {
    "addr:full":"Niederdorfer Str 32 Treffen K\u00e4rnten 9521",
    "addr:housenumber":"32",
    "addr:postcode":"9521",
    "addr:street":"Str;Kaernten",
    "iso:country":"AT",
    "sg:address":"Niederdorfer Str 32",
    "sg:city":"Treffen",
    "sg:orig_category":"Volksschulen",
    "sg:phone":"+43 4248 3806",
    "sg:postcode":"9521",
    "sg:province":"K\u00e4rnten",
    "wof:name":"Private Evangelische Volksschule auf Basis der Montessore P\u00e4dagogik",
    "wof:placetype":"venue"
},
  "geometry": {"coordinates":[13.8688793182,46.6600914001],"type":"Point"}
}