{
  "type": "Feature",
  "properties": {
    "addr:full":"Kasberg 1 Hainfeld Nieder\u00f6sterreich 3170",
    "addr:housenumber":"1",
    "addr:postcode":"3170",
    "addr:street":"Kasberg",
    "iso:country":"AT",
    "sg:address":"Kasberg 1",
    "sg:city":"Hainfeld",
    "sg:classifiers":[
        {
            "category":"Government",
            "subcategory":"Post Office",
            "type":"Public Place"
        }
    ],
    "sg:phone":"+43 4327 647041",
    "sg:postcode":"3170",
    "sg:province":"Nieder\u00f6sterreich",
    "sg:tags":[
        "-handel",
        "tierzucht",
        "u"
    ],
    "wof:name":"Gest\u00fct Ederhof - Fam Au",
    "wof:placetype":"venue"
},
  "geometry": {"coordinates":[15.7999401093,48.0749588013],"type":"Point"}
}