{
  "type": "Feature",
  "properties": {
    "iso:country":"AT",
    "sg:address":"Bahng 11",
    "sg:city":"Breitenau am Hochlantsch",
    "sg:orig_category":"Lebensmittel / Einzelhandel",
    "sg:phone":"+43 3866 51040",
    "sg:postcode":"8614",
    "sg:province":"Steiermark",
    "wof:name":"Kopatsch Gerhard",
    "wof:placetype":"venue"
},
  "geometry": {"coordinates":[16.145483017,47.7357215881],"type":"Point"}
}