{
  "type": "Feature",
  "properties": {
    "addr:full":"Brauhausstr 1 Schwechat Nieder\u00f6sterreich 2320",
    "addr:housenumber":"1",
    "addr:postcode":"2320",
    "addr:street":"Brauhausstr;Niederoesterreich",
    "iso:country":"AT",
    "sg:address":"Brauhausstr 1",
    "sg:city":"Schwechat",
    "sg:orig_category":"Weiterbildungsinstitute M Allg U Berufl Bildungsangebot",
    "sg:phone":"+43 4317 0659590",
    "sg:postcode":"2320",
    "sg:province":"Nieder\u00f6sterreich",
    "wof:name":"schmidt training.co gmbh",
    "wof:placetype":"venue"
},
  "geometry": {"coordinates":[16.4738578796,48.1423301697],"type":"Point"}
}