{
  "type": "Feature",
  "properties": {
    "iso:country":"AT",
    "sg:address":"Werner-von-Siemens-Str 13",
    "sg:city":"Steyr",
    "sg:orig_category":"Fleischhauereien",
    "sg:phone":"+43 4372 5271022",
    "sg:postcode":"4400",
    "sg:province":"Ober\u00f6sterreich",
    "wof:name":"Maier Franz",
    "wof:placetype":"venue"
},
  "geometry": {"coordinates":[14.4231786728,48.0600166321],"type":"Point"}
}