{
  "type": "Feature",
  "properties": {
    "addr:full":"Altenmarkter Strasse 4 Leibnitz Steiermark 8430",
    "addr:housenumber":"4",
    "addr:postcode":"8430",
    "addr:street":"Altenmarkter Strasse;Steiermark",
    "iso:country":"AT",
    "sg:address":"Altenmarkter Strasse 4",
    "sg:city":"Leibnitz",
    "sg:classifiers":[
        {
            "category":"Home & Garden",
            "subcategory":"Household Appliances",
            "type":"Retail Goods"
        }
    ],
    "sg:phone":"+43 3452 82633",
    "sg:postcode":"8430",
    "sg:province":"Steiermark",
    "sg:tags":[
        "electric"
    ],
    "wof:name":"Ing. Karl Kortschak & Co",
    "wof:placetype":"venue"
},
  "geometry": {"coordinates":[15.5398073196,46.7791404724],"type":"Point"}
}