{
  "type": "Feature",
  "properties": {
    "addr:full":"Prunnerstr 14 Wels Ober\u00f6sterreich 4600",
    "addr:housenumber":"14",
    "addr:postcode":"4600",
    "addr:street":"Prunnerstr;Oberoesterreich",
    "iso:country":"AT",
    "sg:address":"Prunnerstr 14",
    "sg:city":"Wels",
    "sg:orig_category":"Physiotherapie",
    "sg:phone":"+43 7242 26459",
    "sg:postcode":"4600",
    "sg:province":"Ober\u00f6sterreich",
    "wof:name":"Haslinger Dorothea Dipl-PT",
    "wof:placetype":"venue"
},
  "geometry": {"coordinates":[14.0145025253,48.1917419434],"type":"Point"}
}