{
  "type": "Feature",
  "properties": {
    "iso:country":"AT",
    "sg:address":"Lorenz Vest-Weg 9",
    "sg:city":"Liebenau",
    "sg:orig_category":"Medizintechnik",
    "sg:phone":"+43 316 401331",
    "sg:postcode":"8041",
    "sg:province":"Steiermark",
    "wof:name":"Pilz Medica",
    "wof:placetype":"venue"
},
  "geometry": {"coordinates":[15.4734344482,47.0242652893],"type":"Point"}
}