{
  "type": "Feature",
  "properties": {
    "addr:full":"Unterlochner Str 4A Mattighofen Ober\u00f6sterreich 5230",
    "addr:postcode":"5230",
    "addr:street":"Str 4A",
    "iso:country":"AT",
    "sg:address":"Unterlochner Str 4A",
    "sg:city":"Mattighofen",
    "sg:orig_category":"Nachhilfe U Lernbetreuung",
    "sg:phone":"+43 4377 4258814",
    "sg:postcode":"5230",
    "sg:province":"Ober\u00f6sterreich",
    "wof:name":"Mini-Lernkreis - Streif Sonja",
    "wof:placetype":"venue"
},
  "geometry": {"coordinates":[13.1465167999,48.1094818115],"type":"Point"}
}