{
  "type": "Feature",
  "properties": {
    "addr:full":"Burgenlandstr 13 Bruck an der Leitha Nieder\u00f6sterreich 2460",
    "addr:housenumber":"13",
    "addr:postcode":"2460",
    "addr:street":"Burgenlandstr",
    "iso:country":"AT",
    "sg:address":"Burgenlandstr 13",
    "sg:city":"Bruck an der Leitha",
    "sg:orig_category":"Museen / Ausstellungen",
    "sg:phone":"+43 2162 62715",
    "sg:postcode":"2460",
    "sg:province":"Nieder\u00f6sterreich",
    "wof:name":"Vogelmuseum",
    "wof:placetype":"venue"
},
  "geometry": {"coordinates":[16.7811260223,48.024017334],"type":"Point"}
}