{
  "type": "Feature",
  "properties": {
    "addr:full":"Christlg 3 Traun Ober\u00f6sterreich 4050",
    "addr:housenumber":"3",
    "addr:postcode":"4050",
    "addr:street":"Christlg",
    "iso:country":"AT",
    "sg:address":"Christlg 3",
    "sg:city":"Traun",
    "sg:orig_category":"Arbeitsvermittlung",
    "sg:phone":"+43 7229 64264",
    "sg:postcode":"4050",
    "sg:province":"Ober\u00f6sterreich",
    "sg:website":"www.ams-ooe.or.at",
    "wof:name":"Arbeitsmarktservice Traun",
    "wof:placetype":"venue"
},
  "geometry": {"coordinates":[14.2404317856,48.221370697],"type":"Point"}
}