{
  "type": "Feature",
  "properties": {
    "addr:full":"Opernring 24 Graz Steiermark 8010",
    "addr:housenumber":"24",
    "addr:postcode":"8010",
    "addr:street":"Opernring",
    "iso:country":"AT",
    "sg:address":"Opernring 24",
    "sg:city":"Graz",
    "sg:orig_category":"Apotheken",
    "sg:phone":"+43 316 829647",
    "sg:postcode":"8010",
    "sg:province":"Steiermark",
    "sg:website":"opernapotheke.com",
    "wof:name":"Opernapotheke",
    "wof:placetype":"venue"
},
  "geometry": {"coordinates":[15.4422588348,47.0682563782],"type":"Point"}
}