{
  "type": "Feature",
  "properties": {
    "addr:full":"Dreifaltigkeitsg 3/2/66 Salzburg Salzburg 5020",
    "addr:housenumber":"3 / 2 / 66",
    "addr:postcode":"5020",
    "addr:street":"Dreifaltigkeitsg;Salzburg",
    "iso:country":"AT",
    "sg:address":"Dreifaltigkeitsg 3/2/66",
    "sg:city":"Salzburg",
    "sg:orig_category":"Detekteien",
    "sg:phone":"+43 662 877782",
    "sg:postcode":"5020",
    "sg:province":"Salzburg",
    "sg:website":"abs-detektive.at",
    "wof:name":"ABS-Detektive Roland Rameseder KEG",
    "wof:placetype":"venue"
},
  "geometry": {"coordinates":[13.0452442169,47.8020896912],"type":"Point"}
}