{
  "type": "Feature",
  "properties": {
    "addr:full":"Witthauerg 40 Wien Wien 1180",
    "addr:housenumber":"40",
    "addr:postcode":"1180",
    "addr:street":"Witthauerg",
    "iso:country":"AT",
    "sg:address":"Witthauerg 40",
    "sg:city":"Wien",
    "sg:orig_category":"Maler, Anstreicher U Lackierer",
    "sg:phone":"+43 4314 786677",
    "sg:postcode":"1180",
    "sg:province":"Wien",
    "wof:name":"RAGGER SIGRIT KEG",
    "wof:placetype":"venue"
},
  "geometry": {"coordinates":[16.3253517151,48.236000061],"type":"Point"}
}