{
  "type": "Feature",
  "properties": {
    "addr:full":"MS Design-Str 1 Roppen Tirol 6426",
    "addr:housenumber":"1",
    "addr:postcode":"6426",
    "addr:street":"Tirol",
    "iso:country":"AT",
    "sg:address":"MS Design-Str 1",
    "sg:city":"Roppen",
    "sg:orig_category":"Autohandel",
    "sg:phone":"+43 5417 63630",
    "sg:postcode":"6426",
    "sg:province":"Tirol",
    "wof:name":"MS Automobile Handel- und Reparaturen-Roppen GmbH & Co KG",
    "wof:placetype":"venue"
},
  "geometry": {"coordinates":[10.8291902542,47.2305526733],"type":"Point"}
}