{
  "type": "Feature",
  "properties": {
    "iso:country":"AT",
    "sg:address":"Linzer G 55/1",
    "sg:city":"Salzburg",
    "sg:orig_category":"Psychotherapie",
    "sg:phone":"+43 662 874488",
    "sg:postcode":"5020",
    "sg:province":"Salzburg",
    "wof:name":"Breitfuss Andrea Dr",
    "wof:placetype":"venue"
},
  "geometry": {"coordinates":[13.0489768982,47.8046264648],"type":"Point"}
}