{
  "type": "Feature",
  "properties": {
    "addr:full":"Drautalstr 10 Gummern K\u00e4rnten 9722",
    "addr:housenumber":"10",
    "addr:postcode":"9722",
    "addr:street":"Drautalstr;Kaernten",
    "iso:country":"AT",
    "sg:address":"Drautalstr 10",
    "sg:city":"Gummern",
    "sg:orig_category":"Volksschulen",
    "sg:phone":"+43 4258 647",
    "sg:postcode":"9722",
    "sg:province":"K\u00e4rnten",
    "wof:name":"Volksschule",
    "wof:placetype":"venue"
},
  "geometry": {"coordinates":[13.7566080093,46.6640281677],"type":"Point"}
}