{
  "type": "Feature",
  "properties": {
    "addr:full":"Kirchdorf 200 Doren Vorarlberg 6933",
    "addr:housenumber":"200",
    "addr:postcode":"6933",
    "addr:street":"Kirchdorf",
    "iso:country":"AT",
    "sg:address":"Kirchdorf 200",
    "sg:city":"Doren",
    "sg:orig_category":"Hauptschulen",
    "sg:phone":"+43 5516 2098",
    "sg:postcode":"6933",
    "sg:province":"Vorarlberg",
    "wof:name":"Hauptschule Doren",
    "wof:placetype":"venue"
},
  "geometry": {"coordinates":[9.8796796799,47.4928436279],"type":"Point"}
}