{
  "type": "Feature",
  "properties": {
    "iso:country":"AT",
    "sg:address":"M\u00fcnchner Str 21",
    "sg:city":"Kufstein",
    "sg:orig_category":"Holzbau",
    "sg:phone":"+43 5372 66066",
    "sg:postcode":"6330",
    "sg:province":"Tirol",
    "wof:name":"Ritzer Wolfgang Ing GmbH",
    "wof:placetype":"venue"
},
  "geometry": {"coordinates":[12.1717987061,47.5847892761],"type":"Point"}
}