{
  "type": "Feature",
  "properties": {
    "iso:country":"AT",
    "sg:address":"Passauer Str 48",
    "sg:city":"St. P\u00f6lten",
    "sg:orig_category":"Genossenschaften",
    "sg:phone":"+43 4327 4275368",
    "sg:postcode":"3100",
    "sg:province":"Nieder\u00f6sterreich",
    "wof:name":"BWS Gemeinn\u00fctzige allgemeine Bau- Wohn- u Siedlungsgenossenschaft",
    "wof:placetype":"venue"
},
  "geometry": {"coordinates":[-76.07303619379999,41.7845001221],"type":"Point"}
}