{
  "type": "Feature",
  "properties": {
    "iso:country":"AT",
    "sg:address":"Viecht 35",
    "sg:city":"Desselbrunn",
    "sg:orig_category":"Autohandel",
    "sg:phone":"+43 767330650",
    "sg:postcode":"4693",
    "sg:province":"Ober\u00f6sterreich",
    "wof:name":"Sterlich Automobil GmbH",
    "wof:placetype":"venue"
},
  "geometry": {"coordinates":[13.781126976,47.9998168945],"type":"Point"}
}