{
  "type": "Feature",
  "properties": {
    "addr:full":"G\u00e4rtnerstr 16 Linz Ober\u00f6sterreich 4020",
    "addr:housenumber":"16",
    "addr:postcode":"4020",
    "addr:street":"Gaertnerstr",
    "iso:country":"AT",
    "sg:address":"G\u00e4rtnerstr 16",
    "sg:city":"Linz",
    "sg:orig_category":"Schlankheitsinstitute",
    "sg:phone":"+43 732 650890",
    "sg:postcode":"4020",
    "sg:province":"Ober\u00f6sterreich",
    "wof:name":"Slender You Figursalon",
    "wof:placetype":"venue"
},
  "geometry": {"coordinates":[14.2879953384,48.2951583862],"type":"Point"}
}