{
  "type": "Feature",
  "properties": {
    "addr:full":"Ardetzenbergstr 5 Feldkirch Vorarlberg 6800",
    "addr:housenumber":"5",
    "addr:postcode":"6800",
    "addr:street":"Ardetzenbergstr",
    "iso:country":"AT",
    "sg:address":"Ardetzenbergstr 5",
    "sg:city":"Feldkirch",
    "sg:orig_category":"Unternehmensberatung",
    "sg:phone":"+43 5522 82197",
    "sg:postcode":"6800",
    "sg:province":"Vorarlberg",
    "wof:name":"Gabriel-Ritter Angelika Dr",
    "wof:placetype":"venue"
},
  "geometry": {"coordinates":[9.591711998,47.2384262085],"type":"Point"}
}