{
  "type": "Feature",
  "properties": {
    "iso:country":"AT",
    "sg:address":"Schubertstr 23",
    "sg:city":"Wels",
    "sg:orig_category":"Reifen U Reifendienste",
    "sg:phone":"+43 4372 42416090",
    "sg:postcode":"4600",
    "sg:province":"Ober\u00f6sterreich",
    "wof:name":"Profi Reifen- u Autoservice GesmbH",
    "wof:placetype":"venue"
},
  "geometry": {"coordinates":[14.0219783783,48.1633491516],"type":"Point"}
}