{
  "type": "Feature",
  "properties": {
    "addr:full":"Landstra\u00dfer Hauptstr 50 Wien Wien 1030",
    "addr:housenumber":"50",
    "addr:postcode":"1030",
    "addr:street":"Landstrasser Hauptstr",
    "iso:country":"AT",
    "sg:address":"Landstra\u00dfer Hauptstr 50",
    "sg:city":"Wien",
    "sg:classifiers":[
        {
            "category":"Restaurant",
            "type":"Food & Drink"
        }
    ],
    "sg:phone":"+43 1 7153470",
    "sg:postcode":"1030",
    "sg:province":"Wien",
    "wof:name":"Restaurant Kiang",
    "wof:placetype":"venue"
},
  "geometry": {"coordinates":[16.3902244568,48.2026481628],"type":"Point"}
}