{
  "type": "Feature",
  "properties": {
    "addr:full":"Greifensteiner Str 32 St. Andr\u00e4-W\u00f6rdern Nieder\u00f6sterreich 3423",
    "addr:housenumber":"32",
    "addr:postcode":"3423",
    "addr:street":"Str",
    "iso:country":"AT",
    "sg:address":"Greifensteiner Str 32",
    "sg:city":"St. Andr\u00e4-W\u00f6rdern",
    "sg:orig_category":"Installationsunternehmen",
    "sg:phone":"+43 4322 42322740",
    "sg:postcode":"3423",
    "sg:province":"Nieder\u00f6sterreich",
    "wof:name":"Frieberger T Ing Installationen Dipl-Ing",
    "wof:placetype":"venue"
},
  "geometry": {"coordinates":[16.2114524841,48.3237571716],"type":"Point"}
}