{
  "type": "Feature",
  "properties": {
    "addr:full":"Illpark Feldkirch Vorarlberg 6800",
    "addr:postcode":"6800",
    "addr:street":"Illpark",
    "iso:country":"AT",
    "sg:address":"Illpark",
    "sg:city":"Feldkirch",
    "sg:orig_category":"Einkaufszentren",
    "sg:phone":"+43 5522 74377",
    "sg:postcode":"6800",
    "sg:province":"Vorarlberg",
    "wof:name":"Illpark - Das Einkaufszentrum im Herzen von Feldkirch",
    "wof:placetype":"venue"
},
  "geometry": {"coordinates":[9.5844116211,47.2480163574],"type":"Point"}
}