{
  "type": "Feature",
  "properties": {
    "addr:full":"Uttenhofweg 1 Hafnerbach Nieder\u00f6sterreich 3386",
    "addr:housenumber":"1",
    "addr:postcode":"3386",
    "addr:street":"Uttenhofweg;Niederoesterreich",
    "iso:country":"AT",
    "sg:address":"Uttenhofweg 1",
    "sg:city":"Hafnerbach",
    "sg:orig_category":"Lebens- U Sozialberatung",
    "sg:phone":"+43 4327 492594",
    "sg:postcode":"3386",
    "sg:province":"Nieder\u00f6sterreich",
    "wof:name":"Feichtner Zafer E Mag",
    "wof:placetype":"venue"
},
  "geometry": {"coordinates":[15.4880743027,48.2166900635],"type":"Point"}
}