{
  "type": "Feature",
  "properties": {
    "addr:full":"Laaer Str 145 Poysdorf Nieder\u00f6sterreich 2170",
    "addr:housenumber":"145",
    "addr:postcode":"2170",
    "addr:street":"Str",
    "iso:country":"AT",
    "sg:address":"Laaer Str 145",
    "sg:city":"Poysdorf",
    "sg:orig_category":"Elektroinstallationsmaterial",
    "sg:phone":"+43 2552 28400",
    "sg:postcode":"2170",
    "sg:province":"Nieder\u00f6sterreich",
    "wof:name":"Gebauer & Griller Kabelkonfektion GmbH",
    "wof:placetype":"venue"
},
  "geometry": {"coordinates":[16.6088695526,48.6641807556],"type":"Point"}
}