{
  "type": "Feature",
  "properties": {
    "addr:full":"Heiderosenweg 10a Linz Ober\u00f6sterreich 4030",
    "addr:housenumber":"10a",
    "addr:postcode":"4030",
    "addr:street":"Heiderosenweg",
    "iso:country":"AT",
    "sg:address":"Heiderosenweg 10a",
    "sg:city":"Linz",
    "sg:orig_category":"Entsorgungen",
    "sg:phone":"+43 699 11506606",
    "sg:postcode":"4030",
    "sg:province":"Ober\u00f6sterreich",
    "wof:name":"FESA Entsorgung-Entr\u00fcmpelung-R\u00e4umung",
    "wof:placetype":"venue"
},
  "geometry": {"coordinates":[14.2843675613,48.2439041138],"type":"Point"}
}