{
  "type": "Feature",
  "properties": {
    "addr:full":"Triester Str 309 Feldkirchen Steiermark 8073",
    "addr:housenumber":"309",
    "addr:postcode":"8073",
    "iso:country":"AT",
    "sg:address":"Triester Str 309",
    "sg:city":"Feldkirchen",
    "sg:orig_category":"Montagen U Montagetechnik",
    "sg:phone":"+43 4331 3554804",
    "sg:postcode":"8073",
    "sg:province":"Steiermark",
    "wof:name":"IMG Industriemontagen GmbH",
    "wof:placetype":"venue"
},
  "geometry": {"coordinates":[15.4606246948,46.9852333069],"type":"Point"}
}