{
  "type": "Feature",
  "properties": {
    "iso:country":"AT",
    "sg:address":"Arndtstr 98",
    "sg:city":"Wien",
    "sg:orig_category":"Nachhilfe U Lernbetreuung",
    "sg:phone":"+43 4318 120679",
    "sg:postcode":"1120",
    "sg:province":"Wien",
    "sg:website":"schuelerhilfe.at",
    "wof:name":"Humer Christiane - Sch\u00fclerhilfe",
    "wof:placetype":"venue"
},
  "geometry": {"coordinates":[16.3302574158,48.181842804],"type":"Point"}
}