{
  "type": "Feature",
  "properties": {
    "addr:full":"Sportplatzg 4 Teesdorf Nieder\u00f6sterreich 2524",
    "addr:housenumber":"4",
    "addr:postcode":"2524",
    "addr:street":"Sportplatzg",
    "iso:country":"AT",
    "sg:address":"Sportplatzg 4",
    "sg:city":"Teesdorf",
    "sg:orig_category":"Handelsagenturen",
    "sg:phone":"+43 699 10851247",
    "sg:postcode":"2524",
    "sg:province":"Nieder\u00f6sterreich",
    "wof:name":"Woltron Beatrix",
    "wof:placetype":"venue"
},
  "geometry": {"coordinates":[16.2757987976,47.9500274658],"type":"Point"}
}