{
  "type": "Feature",
  "properties": {
    "iso:country":"AT",
    "sg:address":"Linzer Str. 258 ",
    "sg:city":"Wels",
    "sg:classifiers":[
        {
            "category":"Autos & Motor Vehicles",
            "subcategory":"Automobile Sales",
            "type":"Retail Goods"
        }
    ],
    "sg:phone":"+43 4372 42473310",
    "sg:postcode":"4600",
    "sg:province":"Ober\u00f6sterreich",
    "sg:tags":[
        "industrial"
    ],
    "wof:name":"WILHELM SCHWARZM\u00dcLLER GMBH",
    "wof:placetype":"venue"
},
  "geometry": {"coordinates":[14.0641431808,48.1795692444],"type":"Point"}
}