{
  "type": "Feature",
  "properties": {
    "iso:country":"AT",
    "sg:address":"Sverigestr 1B",
    "sg:city":"Wien",
    "sg:classifiers":[
        {
            "category":"Restaurant",
            "type":"Food & Drink"
        }
    ],
    "sg:phone":"+43 1 7345430",
    "sg:postcode":"1220",
    "sg:province":"Wien",
    "sg:tags":[
        "pizzeria"
    ],
    "wof:name":"Fantastica ital Spezialit\u00e4ten Restaurant BetriebsgesmbH",
    "wof:placetype":"venue"
},
  "geometry": {"coordinates":[16.4711265564,48.2527275085],"type":"Point"}
}