{
  "type": "Feature",
  "properties": {
    "iso:country":"AT",
    "sg:address":"Gregerstrasse 28",
    "sg:city":"Fischamend",
    "sg:classifiers":[
        {
            "category":"Building & Trades",
            "subcategory":"Construction",
            "type":"Services"
        }
    ],
    "sg:phone":"+43 2232 76428",
    "sg:postcode":"2401",
    "sg:province":"Nieder\u00f6sterreich",
    "sg:tags":[
        "mural"
    ],
    "wof:name":"Herbert Stepan Ges.m.b.H.",
    "wof:placetype":"venue"
},
  "geometry": {"coordinates":[16.6107654572,48.1155548096],"type":"Point"}
}