{
  "type": "Feature",
  "properties": {
    "addr:full":"Oberwegbach 13 Waizenkirchen Ober\u00f6sterreich 4730",
    "addr:housenumber":"13",
    "addr:postcode":"4730",
    "addr:street":"Oberwegbach",
    "iso:country":"AT",
    "sg:address":"Oberwegbach 13",
    "sg:city":"Waizenkirchen",
    "sg:orig_category":"Tischlereien",
    "sg:phone":"+43 7277 6139",
    "sg:postcode":"4730",
    "sg:province":"Ober\u00f6sterreich",
    "wof:name":"Lindinger Franz Tischlerei GesmbH",
    "wof:placetype":"venue"
},
  "geometry": {"coordinates":[13.8544282913,48.3170089722],"type":"Point"}
}