{
  "type": "Feature",
  "properties": {
    "addr:full":"Steinebach 7 Dornbirn Vorarlberg 6850",
    "addr:housenumber":"7",
    "addr:postcode":"6850",
    "addr:street":"Steinebach",
    "iso:country":"AT",
    "sg:address":"Steinebach 7",
    "sg:city":"Dornbirn",
    "sg:orig_category":"Damenmoden",
    "sg:phone":"+43 5572 22167",
    "sg:postcode":"6850",
    "sg:province":"Vorarlberg",
    "wof:name":"H\u00e4mmerle Manfred",
    "wof:placetype":"venue"
},
  "geometry": {"coordinates":[9.7587423325,47.4051856995],"type":"Point"}
}