{
  "type": "Feature",
  "properties": {
    "addr:full":"Diefenbachg 24 Wien Wien 1150",
    "addr:housenumber":"24",
    "addr:postcode":"1150",
    "addr:street":"Diefenbachg",
    "iso:country":"AT",
    "sg:address":"Diefenbachg 24",
    "sg:city":"Wien",
    "sg:orig_category":"Autoersatzteile",
    "sg:phone":"+43 1 89200070",
    "sg:postcode":"1150",
    "sg:province":"Wien",
    "wof:name":"Felber J & B GesmbH",
    "wof:placetype":"venue"
},
  "geometry": {"coordinates":[16.3328952789,48.1858596802],"type":"Point"}
}