{
  "type": "Feature",
  "properties": {
    "iso:country":"AT",
    "sg:address":"Hauptstr 38",
    "sg:city":"Hinterbr\u00fchl",
    "sg:orig_category":"Ingenieurkonsulenten / Zivilingenieure",
    "sg:phone":"+43 2236 29240",
    "sg:postcode":"2371",
    "sg:province":"Nieder\u00f6sterreich",
    "wof:name":"Sittner Johann Dipl-Ing",
    "wof:placetype":"venue"
},
  "geometry": {"coordinates":[16.2518997192,48.0884628296],"type":"Point"}
}