{
  "type": "Feature",
  "properties": {
    "iso:country":"AT",
    "sg:address":"Heiligensteinstr 54",
    "sg:city":"Z\u00f6bing",
    "sg:orig_category":"Weine / Einzelhandel",
    "sg:phone":"+43 2734 2833",
    "sg:postcode":"3561",
    "sg:province":"Nieder\u00f6sterreich",
    "wof:name":"Rockenbauer Erhard",
    "wof:placetype":"venue"
},
  "geometry": {"coordinates":[-114.0767440796,46.4432487488],"type":"Point"}
}