{
  "type": "Feature",
  "properties": {
    "addr:full":"Margaretenstr 87 Wien Wien 1050",
    "addr:housenumber":"87",
    "addr:postcode":"1050",
    "addr:street":"Margaretenstr",
    "iso:country":"AT",
    "sg:address":"Margaretenstr 87",
    "sg:city":"Wien",
    "sg:orig_category":"Steuerberatung",
    "sg:phone":"+43 4367 69195954",
    "sg:postcode":"1050",
    "sg:province":"Wien",
    "wof:name":"Haberl Eduard Mag",
    "wof:placetype":"venue"
},
  "geometry": {"coordinates":[16.3573112488,48.1903381348],"type":"Point"}
}