{
  "type": "Feature",
  "properties": {
    "addr:full":"Halirschgasse 16 Wien Wien 1170",
    "addr:housenumber":"16",
    "addr:postcode":"1170",
    "addr:street":"Halirschgasse",
    "iso:country":"AT",
    "sg:address":"Halirschgasse 16",
    "sg:city":"Wien",
    "sg:classifiers":[
        {
            "category":"Professional",
            "subcategory":"Advertising",
            "type":"Services"
        }
    ],
    "sg:phone":"+43 1 488880",
    "sg:postcode":"1170",
    "sg:province":"Wien",
    "sg:tags":[
        "gift"
    ],
    "sg:website":"feibra.at",
    "wof:name":"feibra AG",
    "wof:placetype":"venue"
},
  "geometry": {"coordinates":[16.3172607422,48.2246398926],"type":"Point"}
}