{
  "type": "Feature",
  "properties": {
    "addr:full":"Ottakringer Str 71 Wien Wien 1160",
    "addr:postcode":"1160",
    "addr:street":"Str 71",
    "iso:country":"AT",
    "sg:address":"Ottakringer Str 71",
    "sg:city":"Wien",
    "sg:classifiers":[
        {
            "category":"Restaurant",
            "type":"Food & Drink"
        }
    ],
    "sg:phone":"+43 1 4857849",
    "sg:postcode":"1160",
    "sg:province":"Wien",
    "wof:name":"Blunzenstricker",
    "wof:placetype":"venue"
},
  "geometry": {"coordinates":[16.3285560608,48.2135467529],"type":"Point"}
}