{
  "type": "Feature",
  "properties": {
    "iso:country":"AT",
    "sg:address":"Nr 47",
    "sg:city":"Wendling",
    "sg:orig_category":"Lebensmittel / Einzelhandel",
    "sg:phone":"+43 7736 6033",
    "sg:postcode":"4741",
    "sg:province":"Ober\u00f6sterreich",
    "wof:name":"Strau\u00df KEG",
    "wof:placetype":"venue"
},
  "geometry": {"coordinates":[13.6804189682,48.2285614014],"type":"Point"}
}