{
  "type": "Feature",
  "properties": {
    "addr:full":"Leithabergstr 14B Eisenstadt Burgenland 7000",
    "addr:housenumber":"14b",
    "addr:postcode":"7000",
    "addr:street":"Leithabergstr",
    "iso:country":"AT",
    "sg:address":"Leithabergstr 14B",
    "sg:city":"Eisenstadt",
    "sg:orig_category":"Physiotherapie",
    "sg:phone":"+43 2682 67857",
    "sg:postcode":"7000",
    "sg:province":"Burgenland",
    "wof:name":"Lentsch Maria Theresia Dipl-PT",
    "wof:placetype":"venue"
},
  "geometry": {"coordinates":[16.5375289917,47.856174469],"type":"Point"}
}