{
  "type": "Feature",
  "properties": {
    "iso:country":"AT",
    "sg:address":"Herrgottwiesgasse 117",
    "sg:city":"Graz",
    "sg:orig_category":"Catering For Schools",
    "sg:phone":"+43 316 271212",
    "sg:postcode":"8020",
    "sg:province":"Steiermark",
    "sg:website":"g-m-s.at",
    "wof:name":"GRAZER MEN\u00dc SERVICE",
    "wof:placetype":"venue"
},
  "geometry": {"coordinates":[15.4331445694,47.0480804443],"type":"Point"}
}