{
  "type": "Feature",
  "properties": {
    "addr:full":"Obere Hauptstr 10 Perschling Nieder\u00f6sterreich 3142",
    "addr:housenumber":"10",
    "addr:postcode":"3142",
    "addr:street":"Obere Hauptstr;Niederoesterreich",
    "iso:country":"AT",
    "sg:address":"Obere Hauptstr 10",
    "sg:city":"Perschling",
    "sg:orig_category":"Friseure U Frisiersalons",
    "sg:phone":"+43 2784 2437",
    "sg:postcode":"3142",
    "sg:province":"Nieder\u00f6sterreich",
    "wof:name":"Kos Anton",
    "wof:placetype":"venue"
},
  "geometry": {"coordinates":[15.8314247131,48.2379646301],"type":"Point"}
}