{
  "type": "Feature",
  "properties": {
    "iso:country":"AT",
    "sg:address":"Johann-Herbst-Str 33",
    "sg:city":"Elsbethen-Glasenbach",
    "sg:orig_category":"Fleischhauereien",
    "sg:phone":"+43 662 627575",
    "sg:postcode":"5061",
    "sg:province":"Salzburg",
    "wof:name":"H\u00f6henwarter Karl",
    "wof:placetype":"venue"
},
  "geometry": {"coordinates":[13.0846509933,47.7697753906],"type":"Point"}
}