{
  "type": "Feature",
  "properties": {
    "addr:full":"Hammer Purgstall-G 1 Wien Wien 1020",
    "addr:housenumber":"1",
    "addr:postcode":"1020",
    "addr:street":"Purgstall-G",
    "iso:country":"AT",
    "sg:address":"Hammer Purgstall-G 1",
    "sg:city":"Wien",
    "sg:orig_category":"Farben U Lacke / Einzelhandel",
    "sg:phone":"+43 1 2142514",
    "sg:postcode":"1020",
    "sg:province":"Wien",
    "wof:name":"SEFRA Farben- und Tapetenvertrieb GesmbH",
    "wof:placetype":"venue"
},
  "geometry": {"coordinates":[16.3766651154,48.2151031494],"type":"Point"}
}