{
  "type": "Feature",
  "properties": {
    "addr:full":"Wiener Str 60 Amstetten Nieder\u00f6sterreich 3300",
    "addr:postcode":"3300",
    "addr:street":"Niederoesterreich",
    "iso:country":"AT",
    "sg:address":"Wiener Str 60",
    "sg:city":"Amstetten",
    "sg:orig_category":"Tankstellen",
    "sg:phone":"+43 4374 7262760",
    "sg:postcode":"3300",
    "sg:province":"Nieder\u00f6sterreich",
    "wof:name":"AVANTI TankstellenbetriebsgesmbH",
    "wof:placetype":"venue"
},
  "geometry": {"coordinates":[14.887796402,48.1224021912],"type":"Point"}
}