{
  "type": "Feature",
  "properties": {
    "iso:country":"AT",
    "sg:address":"Schilti 1",
    "sg:city":"Serfaus",
    "sg:orig_category":"Appartements / Ferienwohnungen",
    "sg:phone":"+43 5476 6042",
    "sg:postcode":"6534",
    "sg:province":"Tirol",
    "wof:name":"Fergl's Hof",
    "wof:placetype":"venue"
},
  "geometry": {"coordinates":[10.6140508652,47.042339325],"type":"Point"}
}