{
  "type": "Feature",
  "properties": {
    "addr:full":"Stadtpl 43 Laa an der Thaya Nieder\u00f6sterreich 2136",
    "addr:housenumber":"43",
    "addr:postcode":"2136",
    "addr:street":"Stadtpl",
    "iso:country":"AT",
    "sg:address":"Stadtpl 43",
    "sg:city":"Laa an der Thaya",
    "sg:orig_category":"Banken U Sparkassen",
    "sg:phone":"+43 4350 10020080",
    "sg:postcode":"2136",
    "sg:province":"Nieder\u00f6sterreich",
    "wof:name":"Erste Bank d oesterreichischen Sparkassen AG",
    "wof:placetype":"venue"
},
  "geometry": {"coordinates":[16.3851261139,48.7208862305],"type":"Point"}
}