{
  "type": "Feature",
  "properties": {
    "addr:full":"Haunspergstrasse 41 Salzburg Salzburg 5020",
    "addr:housenumber":"41",
    "addr:postcode":"5020",
    "addr:street":"Haunspergstrasse;Salzburg",
    "iso:country":"AT",
    "sg:address":"Haunspergstrasse 41",
    "sg:city":"Salzburg",
    "sg:classifiers":[
        {
            "category":"Manufacturing",
            "subcategory":"Furniture",
            "type":"Manufacturing & Wholesale Goods"
        }
    ],
    "sg:phone":"+43 662 4501610",
    "sg:postcode":"5020",
    "sg:province":"Salzburg",
    "sg:tags":[
        "bedroom"
    ],
    "wof:name":"M\u00f6bel Treml Ges.m.b.H. & Co KG",
    "wof:placetype":"venue"
},
  "geometry": {"coordinates":[13.0387935638,47.8155441284],"type":"Point"}
}