{
  "type": "Feature",
  "properties": {
    "iso:country":"AT",
    "sg:address":"Vitusgasse 6",
    "sg:city":"Wien",
    "sg:classifiers":[
        {
            "category":"Banks & Credit Unions",
            "subcategory":"Investment Brokerage",
            "type":"Services"
        }
    ],
    "sg:phone":"+43 1 870070",
    "sg:postcode":"1130",
    "sg:province":"Wien",
    "sg:tags":[
        "delivery",
        "flower"
    ],
    "sg:website":"fleurop.at",
    "wof:name":"Fleurop-Interflora Landesabteilung \u00d6sterreich Ges.m.b.H.",
    "wof:placetype":"venue"
},
  "geometry": {"coordinates":[16.2659397125,48.1876945496],"type":"Point"}
}