{
  "type": "Feature",
  "properties": {
    "iso:country":"AT",
    "sg:address":"B\u00fcrgerg 8",
    "sg:city":"Gleisdorf",
    "sg:orig_category":"Geschenkartikel",
    "sg:phone":"+43 3112 38338",
    "sg:postcode":"8200",
    "sg:province":"Steiermark",
    "wof:name":"Magic Box Geschenkboutique",
    "wof:placetype":"venue"
},
  "geometry": {"coordinates":[15.6912050247,47.103477478],"type":"Point"}
}