{
  "type": "Feature",
  "properties": {
    "addr:full":"Steierm\u00e4rker Strasse 49 Kirchdorf an der Krems Ober\u00f6sterreich 4560",
    "addr:housenumber":"49",
    "addr:postcode":"4560",
    "addr:street":"Steiermaerker Strasse",
    "iso:country":"AT",
    "sg:address":"Steierm\u00e4rker Strasse 49",
    "sg:city":"Kirchdorf an der Krems",
    "sg:classifiers":[
        {
            "category":"Manufacturing",
            "subcategory":"Metals",
            "type":"Manufacturing & Wholesale Goods"
        }
    ],
    "sg:phone":"+43 7582 6900",
    "sg:postcode":"4560",
    "sg:province":"Ober\u00f6sterreich",
    "sg:tags":[
        "die",
        "aluminium",
        "casting"
    ],
    "sg:website":"tridentcomponentsgroup.com",
    "wof:name":"TCG Unitech AG",
    "wof:placetype":"venue"
},
  "geometry": {"coordinates":[14.0811481476,47.927116394],"type":"Point"}
}