{
  "type": "Feature",
  "properties": {
    "iso:country":"AT",
    "sg:address":"Markt 458",
    "sg:city":"Litzelsdorf",
    "sg:orig_category":"\u00c3\u201erzte / F Allgemeinmedizin",
    "sg:phone":"+43 3358 24120",
    "sg:postcode":"7532",
    "sg:province":"Burgenland",
    "wof:name":"Glauninger Albin Dr",
    "wof:placetype":"venue"
},
  "geometry": {"coordinates":[16.1615982056,47.2041702271],"type":"Point"}
}