{
  "type": "Feature",
  "properties": {
    "iso:country":"AT",
    "sg:address":"Bruckfeldstr 5",
    "sg:city":"St. Valentin",
    "sg:orig_category":"Installationsunternehmen",
    "sg:phone":"+43 7435 520000",
    "sg:postcode":"4300",
    "sg:province":"Nieder\u00f6sterreich",
    "wof:name":"Spannbauer Heizung-Sanit\u00e4r-L\u00fcftung GmbH",
    "wof:placetype":"venue"
},
  "geometry": {"coordinates":[14.5259199142,48.1696777344],"type":"Point"}
}