{
  "type": "Feature",
  "properties": {
    "addr:full":"Mariahilfer Str 152 Wien Wien 1150",
    "addr:housenumber":"152",
    "addr:postcode":"1150",
    "iso:country":"AT",
    "sg:address":"Mariahilfer Str 152",
    "sg:city":"Wien",
    "sg:orig_category":"Altwaren",
    "sg:phone":"+43 1 8922894",
    "sg:postcode":"1150",
    "sg:province":"Wien",
    "wof:name":"Greiner G\u00fcnter",
    "wof:placetype":"venue"
},
  "geometry": {"coordinates":[16.3345108032,48.1939239502],"type":"Point"}
}