{
  "type": "Feature",
  "properties": {
    "addr:full":"Bergmanng Kiosk Graz Steiermark 8010",
    "addr:postcode":"8010",
    "iso:country":"AT",
    "sg:address":"Bergmanng Kiosk",
    "sg:city":"Graz",
    "sg:orig_category":"Tabaktrafiken",
    "sg:phone":"+43 316 681308",
    "sg:postcode":"8010",
    "sg:province":"Steiermark",
    "wof:name":"Z\u00f6hrer Karl-Heinz",
    "wof:placetype":"venue"
},
  "geometry": {"coordinates":[15.4373922348,47.0856933594],"type":"Point"}
}