{
  "type": "Feature",
  "properties": {
    "addr:full":"Karl-Sch\u00f6nherr-Str 8 Innsbruck Tirol 6020",
    "addr:housenumber":"8",
    "addr:postcode":"6020",
    "addr:street":"Karl-Schoenherr-Str;Tirol",
    "iso:country":"AT",
    "sg:address":"Karl-Sch\u00f6nherr-Str 8",
    "sg:city":"Innsbruck",
    "sg:orig_category":"Ingenieurkonsulenten / Zivilingenieure",
    "sg:phone":"+43 512 5633320",
    "sg:postcode":"6020",
    "sg:province":"Tirol",
    "wof:name":"Brandner Andreas Dipl-Ing",
    "wof:placetype":"venue"
},
  "geometry": {"coordinates":[11.398809433,47.2753219604],"type":"Point"}
}