{
  "type": "Feature",
  "properties": {
    "iso:country":"AT",
    "sg:address":"Kolonitzg 9/14",
    "sg:city":"Wien",
    "sg:orig_category":"Werbeagenturen",
    "sg:phone":"+43 1 4064814",
    "sg:postcode":"1030",
    "sg:province":"Wien",
    "wof:name":"CID Werbe- und PR-Agentur GmbH",
    "wof:placetype":"venue"
},
  "geometry": {"coordinates":[16.3890342712,48.2104377747],"type":"Point"}
}