{
  "type": "Feature",
  "properties": {
    "addr:full":"Hauptpl 28 Frohnleiten Steiermark 8130",
    "addr:housenumber":"28",
    "addr:postcode":"8130",
    "addr:street":"Hauptpl",
    "iso:country":"AT",
    "sg:address":"Hauptpl 28",
    "sg:city":"Frohnleiten",
    "sg:orig_category":"Optiker",
    "sg:phone":"+43 4331 2620022",
    "sg:postcode":"8130",
    "sg:province":"Steiermark",
    "wof:name":"Optik D\u00f6llerer GmbH",
    "wof:placetype":"venue"
},
  "geometry": {"coordinates":[15.3266992569,47.2709007263],"type":"Point"}
}