{
  "type": "Feature",
  "properties": {
    "addr:full":"Mitterboden 13 Saalfelden am Steinernen Meer Salzburg 5760",
    "addr:housenumber":"13",
    "addr:postcode":"5760",
    "addr:street":"Mitterboden;Salzburg",
    "iso:country":"AT",
    "sg:address":"Mitterboden 13",
    "sg:city":"Saalfelden am Steinernen Meer",
    "sg:orig_category":"Botendienste",
    "sg:phone":"+43 6582 73577",
    "sg:postcode":"5760",
    "sg:province":"Salzburg",
    "wof:name":"Botendienst Brachar Anton",
    "wof:placetype":"venue"
},
  "geometry": {"coordinates":[12.8474750519,47.426410675],"type":"Point"}
}