{
  "type": "Feature",
  "properties": {
    "iso:country":"AT",
    "sg:address":"St. Paternianus-Weg 95",
    "sg:city":"Paternion",
    "sg:orig_category":"Transportunternehmen",
    "sg:phone":"+43 4245 3209",
    "sg:postcode":"9711",
    "sg:province":"K\u00e4rnten",
    "wof:name":"Cwioro Walter",
    "wof:placetype":"venue"
},
  "geometry": {"coordinates":[13.6416082382,46.7144622803],"type":"Point"}
}