{
  "type": "Feature",
  "properties": {
    "iso:country":"AT",
    "sg:address":"Gro\u00dfe Sperlgasse 6",
    "sg:city":"Wien",
    "sg:classifiers":[
        {
            "category":"Organizations",
            "subcategory":"Non-profit Organization",
            "type":"Services"
        }
    ],
    "sg:phone":"+43 1 2161430",
    "sg:postcode":"1020",
    "sg:province":"Wien",
    "sg:tags":[
        "alarm",
        "system"
    ],
    "wof:name":"Elektro Petrtil",
    "wof:placetype":"venue"
},
  "geometry": {"coordinates":[16.3783607483,48.2167854309],"type":"Point"}
}