{
  "type": "Feature",
  "properties": {
    "addr:full":"Schulstr 3 Radstadt Salzburg 5550",
    "addr:housenumber":"3",
    "addr:postcode":"5550",
    "addr:street":"Schulstr;Salzburg",
    "iso:country":"AT",
    "sg:address":"Schulstr 3",
    "sg:city":"Radstadt",
    "sg:orig_category":"Hauptschulen",
    "sg:phone":"+43 4364 524336",
    "sg:postcode":"5550",
    "sg:province":"Salzburg",
    "wof:name":"Hauptschule",
    "wof:placetype":"venue"
},
  "geometry": {"coordinates":[13.4598770142,47.3839225769],"type":"Point"}
}