{
  "type": "Feature",
  "properties": {
    "addr:full":"Inneralpbach 40 Alpbach Tirol 6236",
    "addr:housenumber":"40",
    "addr:postcode":"6236",
    "addr:street":"Inneralpbach;Tirol",
    "iso:country":"AT",
    "sg:address":"Inneralpbach 40",
    "sg:city":"Alpbach",
    "sg:classifiers":[
        {
            "category":"Travel",
            "subcategory":"Hotels & Motels",
            "type":"Entertainment"
        }
    ],
    "sg:phone":"+43 5336 56100",
    "sg:postcode":"6236",
    "sg:province":"Tirol",
    "wof:name":"Hotel Galtenberg",
    "wof:placetype":"venue"
},
  "geometry": {"coordinates":[11.9435110092,47.3986091614],"type":"Point"}
}