{
  "type": "Feature",
  "properties": {
    "iso:country":"AT",
    "sg:address":"Kircheng 29",
    "sg:city":"Wien",
    "sg:orig_category":"Sportpreise",
    "sg:phone":"+43 1 5231775",
    "sg:postcode":"1070",
    "sg:province":"Wien",
    "wof:name":"Braun Inh Ulrike Zornija",
    "wof:placetype":"venue"
},
  "geometry": {"coordinates":[16.3514003754,48.2029838562],"type":"Point"}
}