{
  "type": "Feature",
  "properties": {
    "iso:country":"AT",
    "sg:address":"Landstra\u00dfer Hauptstr 2a",
    "sg:city":"Wien",
    "sg:orig_category":"Juwelen, Gold- U Silberwaren / Einzelhandel",
    "sg:phone":"+43 4317 185787",
    "sg:postcode":"1030",
    "sg:province":"Wien",
    "wof:name":"Theuerer KG",
    "wof:placetype":"venue"
},
  "geometry": {"coordinates":[16.3845767975,48.2059020996],"type":"Point"}
}