{
  "type": "Feature",
  "properties": {
    "addr:full":"Stadtpl 17 Radstadt Salzburg 5550",
    "addr:housenumber":"17",
    "addr:postcode":"5550",
    "addr:street":"Stadtpl;Salzburg",
    "iso:country":"AT",
    "sg:address":"Stadtpl 17",
    "sg:city":"Radstadt",
    "sg:orig_category":"Gemeinden",
    "sg:phone":"+43 6452 42920",
    "sg:postcode":"5550",
    "sg:province":"Salzburg",
    "wof:name":"Stadtgemeinde Radstadt",
    "wof:placetype":"venue"
},
  "geometry": {"coordinates":[13.4625778198,47.3846282959],"type":"Point"}
}