{
  "type": "Feature",
  "properties": {
    "addr:full":"Grubdorf 33 St. Veit im M\u00fchlkreis Ober\u00f6sterreich 4173",
    "addr:housenumber":"33",
    "addr:postcode":"4173",
    "addr:street":"Grubdorf",
    "iso:country":"AT",
    "sg:address":"Grubdorf 33",
    "sg:city":"St. Veit im M\u00fchlkreis",
    "sg:orig_category":"Non-Classified Establishments",
    "sg:phone":"+43 7217 6733",
    "sg:postcode":"4173",
    "sg:province":"Ober\u00f6sterreich",
    "sg:website":"kliemstein.net",
    "wof:name":"Kliemstein Sonnenschutz",
    "wof:placetype":"venue"
},
  "geometry": {"coordinates":[14.1713657379,48.4843101501],"type":"Point"}
}