{
  "type": "Feature",
  "properties": {
    "iso:country":"AT",
    "sg:address":"Franzosengraben 12",
    "sg:city":"Wien",
    "sg:classifiers":[
        {
            "category":"Wholesale",
            "subcategory":"Machinery & Supplies",
            "type":"Manufacturing & Wholesale Goods"
        }
    ],
    "sg:phone":"+43 4317 965760",
    "sg:postcode":"1030",
    "sg:province":"Wien",
    "sg:tags":[
        "equipment",
        "-",
        "instrument",
        "measurement"
    ],
    "wof:name":"SARTORIUS GES.MBH",
    "wof:placetype":"venue"
},
  "geometry": {"coordinates":[16.4138774872,48.1881790161],"type":"Point"}
}