{
  "type": "Feature",
  "properties": {
    "addr:full":"Nr 294 St. Martin am Tennengebirge Salzburg 5522",
    "addr:postcode":"5522",
    "addr:street":"Nr 294",
    "iso:country":"AT",
    "sg:address":"Nr 294",
    "sg:city":"St. Martin am Tennengebirge",
    "sg:orig_category":"Fitnesscenter",
    "sg:phone":"+43 6463 20017",
    "sg:postcode":"5522",
    "sg:province":"Salzburg",
    "wof:name":"SAMA-FIT",
    "wof:placetype":"venue"
},
  "geometry": {"coordinates":[-83.1848602295,34.4854125977],"type":"Point"}
}