{
  "type": "Feature",
  "properties": {
    "addr:full":"Nr 20 Mittelberg Vorarlberg 6993",
    "addr:postcode":"6993",
    "addr:street":"Nr",
    "iso:country":"AT",
    "sg:address":"Nr 20",
    "sg:city":"Mittelberg",
    "sg:orig_category":"Weiterbildungsinstitute M Allg U Berufl Bildungsangebot",
    "sg:phone":"+43 4355 175042",
    "sg:postcode":"6993",
    "sg:province":"Vorarlberg",
    "wof:name":"Outward Bound Baad - Deutsche Gesellschaft f Europ\u00e4ische Erziehung",
    "wof:placetype":"venue"
},
  "geometry": {"coordinates":[10.1548366547,47.3239440918],"type":"Point"}
}