{
  "type": "Feature",
  "properties": {
    "addr:full":"Wiener Landstr 15 Atzenbrugg Nieder\u00f6sterreich 3452",
    "addr:housenumber":"15",
    "addr:postcode":"3452",
    "addr:street":"Wiener Landstr",
    "iso:country":"AT",
    "sg:address":"Wiener Landstr 15",
    "sg:city":"Atzenbrugg",
    "sg:orig_category":"Elektroinstallationsunternehmen",
    "sg:phone":"+43 2275 5291",
    "sg:postcode":"3452",
    "sg:province":"Nieder\u00f6sterreich",
    "wof:name":"Wejda Erich GesmbH",
    "wof:placetype":"venue"
},
  "geometry": {"coordinates":[15.8956775665,48.2984962463],"type":"Point"}
}