{
  "type": "Feature",
  "properties": {
    "addr:full":"Gymnasiumstr 50 Wien Wien 1190",
    "addr:housenumber":"50",
    "addr:postcode":"1190",
    "addr:street":"Gymnasiumstr",
    "iso:country":"AT",
    "sg:address":"Gymnasiumstr 50",
    "sg:city":"Wien",
    "sg:orig_category":"Institute",
    "sg:phone":"+43 4314 27758001",
    "sg:postcode":"1190",
    "sg:province":"Wien",
    "wof:name":"Zentrum f Translations Wissenschaft",
    "wof:placetype":"venue"
},
  "geometry": {"coordinates":[16.3477306366,48.2334823608],"type":"Point"}
}