{
  "type": "Feature",
  "properties": {
    "addr:full":"Raffaltpl 2 Murau Steiermark 8850",
    "addr:housenumber":"2",
    "addr:postcode":"8850",
    "addr:street":"Raffaltpl",
    "iso:country":"AT",
    "sg:address":"Raffaltpl 2",
    "sg:city":"Murau",
    "sg:orig_category":"Physiotherapie",
    "sg:phone":"+43 4335 323731",
    "sg:postcode":"8850",
    "sg:province":"Steiermark",
    "wof:name":"Praxis f Physiotherapie Ana u Gordan Kozomara- Brigitte Siebenhofer u Beatrix Teufel",
    "wof:placetype":"venue"
},
  "geometry": {"coordinates":[14.1665859222,47.1109428406],"type":"Point"}
}