{
  "type": "Feature",
  "properties": {
    "addr:full":"Fischerg 2a Wattens Tirol 6112",
    "addr:housenumber":"2a",
    "addr:postcode":"6112",
    "addr:street":"Fischerg;Tirol",
    "iso:country":"AT",
    "sg:address":"Fischerg 2a",
    "sg:city":"Wattens",
    "sg:orig_category":"Tischlereien",
    "sg:phone":"+43 664 3101090",
    "sg:postcode":"6112",
    "sg:province":"Tirol",
    "wof:name":"Mang Georg",
    "wof:placetype":"venue"
},
  "geometry": {"coordinates":[11.5919094086,47.2921066284],"type":"Point"}
}