{
  "type": "Feature",
  "properties": {
    "iso:country":"AT",
    "sg:address":"Br\u00e4unerstr 11",
    "sg:city":"Wien",
    "sg:classifiers":[
        {
            "category":"Banks & Credit Unions",
            "subcategory":"Investment Brokerage",
            "type":"Services"
        }
    ],
    "sg:phone":"+43 4315 123232",
    "sg:postcode":"1010",
    "sg:province":"Wien",
    "sg:tags":[
        "management",
        "facility"
    ],
    "wof:name":"first facility GmbH",
    "wof:placetype":"venue"
},
  "geometry": {"coordinates":[16.368309021,48.2073287964],"type":"Point"}
}