{
  "type": "Feature",
  "properties": {
    "addr:full":"Naglerg 23 Wien Wien 1010",
    "addr:housenumber":"23",
    "addr:postcode":"1010",
    "addr:street":"Naglerg",
    "iso:country":"AT",
    "sg:address":"Naglerg 23",
    "sg:city":"Wien",
    "sg:orig_category":"Bars-Cafes",
    "sg:phone":"+43 1 5350403",
    "sg:postcode":"1010",
    "sg:province":"Wien",
    "wof:name":"Piano-Bar Clair",
    "wof:placetype":"venue"
},
  "geometry": {"coordinates":[16.3667259216,48.2106056213],"type":"Point"}
}