{
  "type": "Feature",
  "properties": {
    "addr:full":"Hauptstr 22 Lichtenegg Nieder\u00f6sterreich 2813",
    "addr:housenumber":"22",
    "addr:postcode":"2813",
    "addr:street":"Hauptstr",
    "iso:country":"AT",
    "sg:address":"Hauptstr 22",
    "sg:city":"Lichtenegg",
    "sg:orig_category":"Gemeinden",
    "sg:phone":"+43 2643 2209",
    "sg:postcode":"2813",
    "sg:province":"Nieder\u00f6sterreich",
    "wof:name":"Gemeindeamt Lichtenegg",
    "wof:placetype":"venue"
},
  "geometry": {"coordinates":[16.1969890594,47.5998191833],"type":"Point"}
}