{
  "type": "Feature",
  "properties": {
    "addr:full":"Krottenbachstr 110/7 Wien Wien 1190",
    "addr:housenumber":"110 / 7",
    "addr:postcode":"1190",
    "iso:country":"AT",
    "sg:address":"Krottenbachstr 110/7",
    "sg:city":"Wien",
    "sg:orig_category":"Transportunternehmen",
    "sg:phone":"+43 676 4038039",
    "sg:postcode":"1190",
    "sg:province":"Wien",
    "wof:name":"Zemann Thomas",
    "wof:placetype":"venue"
},
  "geometry": {"coordinates":[16.3234348297,48.2427177429],"type":"Point"}
}