{
  "type": "Feature",
  "properties": {
    "addr:full":"Singrienerg 30 Wien Wien 1120",
    "addr:housenumber":"30",
    "addr:postcode":"1120",
    "addr:street":"Singrienerg",
    "iso:country":"AT",
    "sg:address":"Singrienerg 30",
    "sg:city":"Wien",
    "sg:orig_category":"Damenmoden",
    "sg:phone":"+43 1 8139163",
    "sg:postcode":"1120",
    "sg:province":"Wien",
    "wof:name":"Dany Textileinzelhandel M Wolfsbauer KEG",
    "wof:placetype":"venue"
},
  "geometry": {"coordinates":[16.3247566223,48.1776542664],"type":"Point"}
}