{
  "type": "Feature",
  "properties": {
    "addr:full":"Riesstrasse 5 Eggersdorf Steiermark 8063",
    "addr:housenumber":"5",
    "addr:postcode":"8063",
    "addr:street":"Riesstrasse",
    "iso:country":"AT",
    "sg:address":"Riesstrasse 5",
    "sg:city":"Eggersdorf",
    "sg:classifiers":[
        {
            "category":"Shopping",
            "subcategory":"Crafts & Fabrics",
            "type":"Retail Goods"
        }
    ],
    "sg:phone":"+43 3117 3468",
    "sg:postcode":"8063",
    "sg:province":"Steiermark",
    "sg:tags":[
        "insulating",
        "felt"
    ],
    "sg:website":"haberl.biz",
    "wof:name":"Andreas Haberl",
    "wof:placetype":"venue"
},
  "geometry": {"coordinates":[15.6227169037,47.1114082336],"type":"Point"}
}