{
  "type": "Feature",
  "properties": {
    "iso:country":"AT",
    "sg:address":"Wiener Str 16",
    "sg:city":"Korneuburg",
    "sg:orig_category":"Tapezierer U Dekorateure",
    "sg:phone":"+43 4322 6272108",
    "sg:postcode":"2100",
    "sg:province":"Nieder\u00f6sterreich",
    "wof:name":"Widy Erwin",
    "wof:placetype":"venue"
},
  "geometry": {"coordinates":[16.3345794678,48.342338562],"type":"Point"}
}