{
  "type": "Feature",
  "properties": {
    "addr:full":"Gundersdorf 1 Klagenfurt K\u00e4rnten 9020",
    "addr:housenumber":"1",
    "addr:postcode":"9020",
    "addr:street":"Gundersdorf;Kaernten",
    "iso:country":"AT",
    "sg:address":"Gundersdorf 1",
    "sg:city":"Klagenfurt",
    "sg:orig_category":"Pensionen / Privatzimmer",
    "sg:phone":"+43 463 43215",
    "sg:postcode":"9020",
    "sg:province":"K\u00e4rnten",
    "wof:name":"Schlossgut Gundersdorf",
    "wof:placetype":"venue"
},
  "geometry": {"coordinates":[14.3274202347,46.6254196167],"type":"Point"}
}