{
  "type": "Feature",
  "properties": {
    "addr:full":"Nr 57 Berwang Tirol 6622",
    "addr:postcode":"6622",
    "addr:street":"Nr;Berwang Tirol",
    "iso:country":"AT",
    "sg:address":"Nr 57",
    "sg:city":"Berwang",
    "sg:classifiers":[
        {
            "category":"Park",
            "subcategory":"Provincial",
            "type":"Public Place"
        }
    ],
    "sg:phone":"+43 4356 748427",
    "sg:postcode":"6622",
    "sg:province":"Tirol",
    "sg:tags":[
        "u",
        "ski-",
        "snowboardschulen"
    ],
    "wof:name":"Schischule Berwang",
    "wof:placetype":"venue"
},
  "geometry": {"coordinates":[10.7468204498,47.4090003967],"type":"Point"}
}