{
  "type": "Feature",
  "properties": {
    "iso:country":"AT",
    "sg:address":"Atriumweg 14",
    "sg:city":"Leonding",
    "sg:classifiers":[
        {
            "category":"Professional",
            "subcategory":"Computer Services",
            "type":"Services"
        }
    ],
    "sg:phone":"+43 664 3558612",
    "sg:postcode":"4060",
    "sg:province":"Ober\u00f6sterreich",
    "sg:tags":[
        "application",
        "client-server"
    ],
    "sg:website":"astral-on.com",
    "wof:name":"ASTRAL Handelsges.m.b.H.",
    "wof:placetype":"venue"
},
  "geometry": {"coordinates":[14.2067499161,48.2764511108],"type":"Point"}
}