{
  "type": "Feature",
  "properties": {
    "addr:full":"Kurpark 1 Puchberg am Schneeberg Nieder\u00f6sterreich 2734",
    "addr:housenumber":"1",
    "addr:postcode":"2734",
    "addr:street":"Kurpark",
    "iso:country":"AT",
    "sg:address":"Kurpark 1",
    "sg:city":"Puchberg am Schneeberg",
    "sg:orig_category":"Steuerberatung",
    "sg:phone":"+43 4326 362280",
    "sg:postcode":"2734",
    "sg:province":"Nieder\u00f6sterreich",
    "wof:name":"Kotrc Robert Wirtschaftstreuhand Steuerberatung GesmbH",
    "wof:placetype":"venue"
},
  "geometry": {"coordinates":[15.9125995636,47.789024353],"type":"Point"}
}