{
  "type": "Feature",
  "properties": {
    "addr:full":"Am See XIII 5 St. Kanzian am Klopeiner See K\u00e4rnten 9122",
    "addr:housenumber":"5",
    "addr:postcode":"9122",
    "addr:street":"Am See Xiii;Kaernten",
    "iso:country":"AT",
    "sg:address":"Am See XIII 5",
    "sg:city":"St. Kanzian am Klopeiner See",
    "sg:classifiers":[
        {
            "category":"Travel",
            "subcategory":"Hotels & Motels",
            "type":"Entertainment"
        }
    ],
    "sg:phone":"+43 4342 3922940",
    "sg:postcode":"9122",
    "sg:province":"K\u00e4rnten",
    "wof:name":"Hotel Klopeinersee",
    "wof:placetype":"venue"
},
  "geometry": {"coordinates":[14.590470314,46.6099205017],"type":"Point"}
}