{
  "type": "Feature",
  "properties": {
    "addr:full":"Am Kanal 73A Wien Wien 1110",
    "addr:housenumber":"73a",
    "addr:postcode":"1110",
    "addr:street":"Am Kanal",
    "iso:country":"AT",
    "sg:address":"Am Kanal 73A",
    "sg:city":"Wien",
    "sg:orig_category":"Elektroinstallationsunternehmen",
    "sg:phone":"+43 1 5441717",
    "sg:postcode":"1110",
    "sg:province":"Wien",
    "wof:name":"KOSBA HandelsgesmbH",
    "wof:placetype":"venue"
},
  "geometry": {"coordinates":[16.4107894897,48.170173645],"type":"Point"}
}