{
  "type": "Feature",
  "properties": {
    "addr:full":"Am Nordsaum 138e Traun Ober\u00f6sterreich 4050",
    "addr:housenumber":"138e",
    "addr:postcode":"4050",
    "addr:street":"Am Nordsaum",
    "iso:country":"AT",
    "sg:address":"Am Nordsaum 138e",
    "sg:city":"Traun",
    "sg:orig_category":"Webdesign",
    "sg:phone":"+43 7229 64364",
    "sg:postcode":"4050",
    "sg:province":"Ober\u00f6sterreich",
    "wof:name":"Walter Diener - gatetoweb design",
    "wof:placetype":"venue"
},
  "geometry": {"coordinates":[14.2404499054,48.2318611145],"type":"Point"}
}