{
  "type": "Feature",
  "properties": {
    "addr:full":"null Parz/119 Eggendorf im Thale Nieder\u00f6sterreich 2031",
    "addr:postcode":"2031",
    "iso:country":"AT",
    "sg:address":"null Parz/119",
    "sg:city":"Eggendorf im Thale",
    "sg:orig_category":"Autoreparatur",
    "sg:phone":"+43 4329 538330",
    "sg:postcode":"2031",
    "sg:province":"Nieder\u00f6sterreich",
    "wof:name":"Einsiedl Georg",
    "wof:placetype":"venue"
},
  "geometry": {"coordinates":[16.1729030609,48.5815963745],"type":"Point"}
}