{
  "type": "Feature",
  "properties": {
    "addr:full":"Leopoldauer Str 70 Wien Wien 1210",
    "addr:housenumber":"70",
    "addr:postcode":"1210",
    "addr:street":"Leopoldauer Str",
    "iso:country":"AT",
    "sg:address":"Leopoldauer Str 70",
    "sg:city":"Wien",
    "sg:orig_category":"Lebensmittel / Einzelhandel",
    "sg:phone":"+43 1 2572676",
    "sg:postcode":"1210",
    "sg:province":"Wien",
    "wof:name":"Zielpunkt Warenhandel GmbH & Co KG",
    "wof:placetype":"venue"
},
  "geometry": {"coordinates":[16.4176826477,48.2606048584],"type":"Point"}
}