{
  "type": "Feature",
  "properties": {
    "iso:country":"AT",
    "sg:address":"Hans-Hruschka-G 11",
    "sg:city":"Himberg",
    "sg:orig_category":"Gie\u00c3\u0178ereien",
    "sg:phone":"+43 2235 86449",
    "sg:postcode":"2325",
    "sg:province":"Nieder\u00f6sterreich",
    "wof:name":"Ruzicka Josef & Franz Metallgie\u00dferei GmbH",
    "wof:placetype":"venue"
},
  "geometry": {"coordinates":[16.446811676,48.0799827576],"type":"Point"}
}