{
  "type": "Feature",
  "properties": {
    "addr:full":"Am Spitz 14 Wien Wien 1210",
    "addr:housenumber":"14",
    "addr:postcode":"1210",
    "addr:street":"Am Spitz",
    "iso:country":"AT",
    "sg:address":"Am Spitz 14",
    "sg:city":"Wien",
    "sg:orig_category":"Blumeneinzelhandel",
    "sg:phone":"+43 1 2781392",
    "sg:postcode":"1210",
    "sg:province":"Wien",
    "wof:name":"Menth Brigitte",
    "wof:placetype":"venue"
},
  "geometry": {"coordinates":[16.3965415955,48.258190155],"type":"Point"}
}