{
  "type": "Feature",
  "properties": {
    "addr:full":"Hauptstr 36 Sch\u00f6rfling am Attersee Ober\u00f6sterreich 4861",
    "addr:housenumber":"36",
    "addr:postcode":"4861",
    "addr:street":"Hauptstr;Am",
    "iso:country":"AT",
    "sg:address":"Hauptstr 36",
    "sg:city":"Sch\u00f6rfling am Attersee",
    "sg:orig_category":"Baumeister",
    "sg:phone":"+43 76624925",
    "sg:postcode":"4861",
    "sg:province":"Ober\u00f6sterreich",
    "wof:name":"Lagerhaus Bau-Service regGenmbH & Co KG",
    "wof:placetype":"venue"
},
  "geometry": {"coordinates":[13.5943651199,47.9457893372],"type":"Point"}
}