{
  "type": "Feature",
  "properties": {
    "addr:full":"Alois-Mayer-G 4 Purkersdorf Nieder\u00f6sterreich 3002",
    "addr:housenumber":"4",
    "addr:postcode":"3002",
    "addr:street":"Alois-Mayer-G",
    "iso:country":"AT",
    "sg:address":"Alois-Mayer-G 4",
    "sg:city":"Purkersdorf",
    "sg:orig_category":"Hauptschulen",
    "sg:phone":"+43 4322 3163381",
    "sg:postcode":"3002",
    "sg:province":"Nieder\u00f6sterreich",
    "wof:name":"Hauptschule Josef Sch\u00f6ffel u Polytechnische Schule",
    "wof:placetype":"venue"
},
  "geometry": {"coordinates":[16.1744632721,48.2065238953],"type":"Point"}
}