{
  "type": "Feature",
  "properties": {
    "iso:country":"AT",
    "sg:address":"S\u00e4gerstr. 100 ",
    "sg:city":"Lustenau",
    "sg:classifiers":[
        {
            "category":"Shopping",
            "subcategory":"Computers & Home Electronics",
            "type":"Retail Goods"
        }
    ],
    "sg:phone":"+43 4357 7330",
    "sg:postcode":"6890",
    "sg:province":"Vorarlberg",
    "sg:tags":[
        "electronic",
        "electrical",
        "equipment"
    ],
    "wof:name":"NEXTIRAONE AUSTRIA GMBH",
    "wof:placetype":"venue"
},
  "geometry": {"coordinates":[9.6722517014,47.4187393188],"type":"Point"}
}