{
  "type": "Feature",
  "properties": {
    "addr:full":"Tallak 127 Rein Steiermark 8103",
    "addr:housenumber":"127",
    "addr:postcode":"8103",
    "addr:street":"Tallak",
    "iso:country":"AT",
    "sg:address":"Tallak 127",
    "sg:city":"Rein",
    "sg:orig_category":"Diskotheken",
    "sg:phone":"+43 3124 55075",
    "sg:postcode":"8103",
    "sg:province":"Steiermark",
    "wof:name":"Mobile Discothek 4Plex",
    "wof:placetype":"venue"
},
  "geometry": {"coordinates":[15.2888708115,47.1344947815],"type":"Point"}
}