{
  "type": "Feature",
  "properties": {
    "addr:full":"Rudigierstr 1 Linz Ober\u00f6sterreich 4020",
    "addr:housenumber":"1",
    "addr:postcode":"4020",
    "addr:street":"Rudigierstr",
    "iso:country":"AT",
    "sg:address":"Rudigierstr 1",
    "sg:city":"Linz",
    "sg:orig_category":"Institute",
    "sg:phone":"+43 4367 63298636",
    "sg:postcode":"4020",
    "sg:province":"Ober\u00f6sterreich",
    "wof:name":"Birgmayer Renate Dr - THINKP\u00e4d - Institut f erfolgreiches Lernen u neues Denken",
    "wof:placetype":"venue"
},
  "geometry": {"coordinates":[14.2904176712,48.3007507324],"type":"Point"}
}