{
  "type": "Feature",
  "properties": {
    "iso:country":"AT",
    "sg:address":"Vinzenzg 7",
    "sg:city":"Wien",
    "sg:orig_category":"Psychotherapie",
    "sg:phone":"+43 4314 701434",
    "sg:postcode":"1180",
    "sg:province":"Wien",
    "wof:name":"Kausel Andrea Dr",
    "wof:placetype":"venue"
},
  "geometry": {"coordinates":[16.33568573,48.2270584106],"type":"Point"}
}