{
  "type": "Feature",
  "properties": {
    "addr:full":"Kirchg 1 Mautern in Steiermark Steiermark 8774",
    "addr:housenumber":"1",
    "addr:postcode":"8774",
    "addr:street":"Kirchg",
    "iso:country":"AT",
    "sg:address":"Kirchg 1",
    "sg:city":"Mautern in Steiermark",
    "sg:orig_category":"Friseure U Frisiersalons",
    "sg:phone":"+43 4338 452285",
    "sg:postcode":"8774",
    "sg:province":"Steiermark",
    "wof:name":"Modefriseur Plank",
    "wof:placetype":"venue"
},
  "geometry": {"coordinates":[14.8252410889,47.4002990723],"type":"Point"}
}