{
  "type": "Feature",
  "properties": {
    "addr:full":"Sportplatzweg 19 G\u00f6fis Vorarlberg 6811",
    "addr:housenumber":"19",
    "addr:postcode":"6811",
    "addr:street":"Sportplatzweg",
    "iso:country":"AT",
    "sg:address":"Sportplatzweg 19",
    "sg:city":"G\u00f6fis",
    "sg:orig_category":"Fliesen- U Plattenverlegungen",
    "sg:phone":"+43 5522 76969",
    "sg:postcode":"6811",
    "sg:province":"Vorarlberg",
    "wof:name":"Walder Kurt",
    "wof:placetype":"venue"
},
  "geometry": {"coordinates":[-90.20757293699999,36.779548645],"type":"Point"}
}