{
  "type": "Feature",
  "properties": {
    "addr:full":"Nr 46 Hollersbach im Pinzgau Salzburg 5731",
    "addr:postcode":"5731",
    "addr:street":"Nr 46;Salzburg",
    "iso:country":"AT",
    "sg:address":"Nr 46",
    "sg:city":"Hollersbach im Pinzgau",
    "sg:classifiers":[
        {
            "category":"Home & Garden",
            "subcategory":"Garden Supply",
            "type":"Retail Goods"
        }
    ],
    "sg:phone":"+43 4365 6281100",
    "sg:postcode":"5731",
    "sg:province":"Salzburg",
    "sg:tags":[
        "schotter",
        "sand",
        "u"
    ],
    "wof:name":"St\u00f6ckl & Wallner KG",
    "wof:placetype":"venue"
},
  "geometry": {"coordinates":[12.4197301865,47.2750968933],"type":"Point"}
}