{
  "type": "Feature",
  "properties": {
    "addr:full":"Ennser Str 113 Steyr Ober\u00f6sterreich 4400",
    "addr:housenumber":"113",
    "addr:postcode":"4400",
    "addr:street":"Oberoesterreich",
    "iso:country":"AT",
    "sg:address":"Ennser Str 113",
    "sg:city":"Steyr",
    "sg:orig_category":"Fenster",
    "sg:phone":"+43 7252 381800",
    "sg:postcode":"4400",
    "sg:province":"Ober\u00f6sterreich",
    "wof:name":"WINKLER Helmut TAUSCHFENSTER GmbH",
    "wof:placetype":"venue"
},
  "geometry": {"coordinates":[14.4203042984,48.0589752197],"type":"Point"}
}