{
  "type": "Feature",
  "properties": {
    "addr:full":"Landstra\u00dfer Hauptstr 173 Wien Wien 1030",
    "addr:housenumber":"173",
    "addr:postcode":"1030",
    "addr:street":"Landstrasser Hauptstr",
    "iso:country":"AT",
    "sg:address":"Landstra\u00dfer Hauptstr 173",
    "sg:city":"Wien",
    "sg:orig_category":"Messerschmiede",
    "sg:phone":"+43 1 7994150",
    "sg:postcode":"1030",
    "sg:province":"Wien",
    "wof:name":"Riccadonna Guido",
    "wof:placetype":"venue"
},
  "geometry": {"coordinates":[16.4008674622,48.1899337769],"type":"Point"}
}