{
  "type": "Feature",
  "properties": {
    "addr:full":"Griesstrasse 12 Pinggau Steiermark 8243",
    "addr:housenumber":"12",
    "addr:postcode":"8243",
    "addr:street":"Griesstrasse",
    "iso:country":"AT",
    "sg:address":"Griesstrasse 12",
    "sg:city":"Pinggau",
    "sg:classifiers":[
        {
            "category":"Manufacturing",
            "subcategory":"Furniture",
            "type":"Manufacturing & Wholesale Goods"
        }
    ],
    "sg:phone":"+43 3339 22155",
    "sg:postcode":"8243",
    "sg:province":"Steiermark",
    "sg:tags":[
        "bedroom"
    ],
    "wof:name":"Josef Oswald",
    "wof:placetype":"venue"
},
  "geometry": {"coordinates":[16.0664710999,47.4400291443],"type":"Point"}
}