{
  "type": "Feature",
  "properties": {
    "iso:country":"AT",
    "sg:address":"Sch\u00f6nangerweg 538",
    "sg:city":"Seefeld in Tirol",
    "sg:orig_category":"Pensionen / Privatzimmer",
    "sg:phone":"+43 5212 28230",
    "sg:postcode":"6100",
    "sg:province":"Tirol",
    "wof:name":"Haus Birgit",
    "wof:placetype":"venue"
},
  "geometry": {"coordinates":[11.1936197281,47.3310890198],"type":"Point"}
}