{
  "type": "Feature",
  "properties": {
    "addr:full":"Am Corso 4 Velden am W\u00f6rther See K\u00e4rnten 9220",
    "addr:housenumber":"4",
    "addr:postcode":"9220",
    "addr:street":"Am Corso;Kaernten",
    "iso:country":"AT",
    "sg:address":"Am Corso 4",
    "sg:city":"Velden am W\u00f6rther See",
    "sg:orig_category":"Tabaktrafiken",
    "sg:phone":"+43 4342 742469",
    "sg:postcode":"9220",
    "sg:province":"K\u00e4rnten",
    "wof:name":"Frate Dieter",
    "wof:placetype":"venue"
},
  "geometry": {"coordinates":[14.0455007553,46.6165084839],"type":"Point"}
}