{
  "type": "Feature",
  "properties": {
    "addr:full":"Kohldorfer Str 52 Klagenfurt K\u00e4rnten 9020",
    "addr:housenumber":"52",
    "addr:postcode":"9020",
    "addr:street":"Str;Kaernten",
    "iso:country":"AT",
    "sg:address":"Kohldorfer Str 52",
    "sg:city":"Klagenfurt",
    "sg:orig_category":"Hotels: Restaurants",
    "sg:phone":"+43 463 2124710",
    "sg:postcode":"9020",
    "sg:province":"K\u00e4rnten",
    "wof:name":"Restaurant Dermuth",
    "wof:placetype":"venue"
},
  "geometry": {"coordinates":[14.2756328583,46.6246681213],"type":"Point"}
}