{
  "type": "Feature",
  "properties": {
    "iso:country":"AT",
    "sg:address":"Weyerg 3",
    "sg:city":"Judenburg",
    "sg:classifiers":[
        {
            "category":"Organizations",
            "subcategory":"Political Organization",
            "type":"Services"
        }
    ],
    "sg:phone":"+43 4335 7247204",
    "sg:postcode":"8750",
    "sg:province":"Steiermark",
    "sg:tags":[
        "mediation"
    ],
    "sg:website":"prolog-mediationscompany.at",
    "wof:name":"Pichler Heinz Dr",
    "wof:placetype":"venue"
},
  "geometry": {"coordinates":[14.660656929,47.1667976379],"type":"Point"}
}