{
  "type": "Feature",
  "properties": {
    "iso:country":"AT",
    "sg:address":"Nr 6",
    "sg:city":"Greifenburg",
    "sg:orig_category":"Tischlereien",
    "sg:phone":"+43 4712 3220",
    "sg:postcode":"9761",
    "sg:province":"K\u00e4rnten",
    "wof:name":"Mandler Josef",
    "wof:placetype":"venue"
},
  "geometry": {"coordinates":[13.1805706024,46.7507743835],"type":"Point"}
}