{
  "type": "Feature",
  "properties": {
    "addr:full":"Bahnhofstr. 8  Eferding Ober\u00f6sterreich 4070",
    "addr:housenumber":"8",
    "addr:postcode":"4070",
    "addr:street":"Bahnhofstr.",
    "iso:country":"AT",
    "sg:address":"Bahnhofstr. 8 ",
    "sg:city":"Eferding",
    "sg:classifiers":[
        {
            "category":"Manufacturing",
            "subcategory":"Rubber & Plastics",
            "type":"Manufacturing & Wholesale Goods"
        }
    ],
    "sg:phone":"+43 4372 7236310",
    "sg:postcode":"4070",
    "sg:province":"Ober\u00f6sterreich",
    "wof:name":"ERNST STADELMANN GESMBH",
    "wof:placetype":"venue"
},
  "geometry": {"coordinates":[14.0178537369,48.3055763245],"type":"Point"}
}