{
  "type": "Feature",
  "properties": {
    "addr:full":"Am Badfeld 17a Wien Wien 1230",
    "addr:housenumber":"17a",
    "addr:postcode":"1230",
    "addr:street":"Am Badfeld",
    "iso:country":"AT",
    "sg:address":"Am Badfeld 17a",
    "sg:city":"Wien",
    "sg:orig_category":"Werbeagenturen",
    "sg:phone":"+43 1 8884155",
    "sg:postcode":"1230",
    "sg:province":"Wien",
    "wof:name":"Wallner Pharma GesmbH",
    "wof:placetype":"venue"
},
  "geometry": {"coordinates":[16.2516613007,48.135761261],"type":"Point"}
}