{
  "type": "Feature",
  "properties": {
    "addr:full":"Bahnhofstr 24 Frastanz Vorarlberg 6820",
    "addr:postcode":"6820",
    "addr:street":"Bahnhofstr 24",
    "iso:country":"AT",
    "sg:address":"Bahnhofstr 24",
    "sg:city":"Frastanz",
    "sg:orig_category":"Holzbearbeitungsmaschinen U -Werkzeuge",
    "sg:phone":"+43 664 5033459",
    "sg:postcode":"6820",
    "sg:province":"Vorarlberg",
    "wof:name":"Iseli-Sch\u00e4rfmaschinen-Sch\u00e4rfprodukte - Alfons Bauer",
    "wof:placetype":"venue"
},
  "geometry": {"coordinates":[9.6343574524,47.2178192139],"type":"Point"}
}