{
  "type": "Feature",
  "properties": {
    "addr:full":"Promenade 3 Steyr Ober\u00f6sterreich 4400",
    "addr:housenumber":"3",
    "addr:postcode":"4400",
    "addr:street":"Promenade;Oberoesterreich",
    "iso:country":"AT",
    "sg:address":"Promenade 3",
    "sg:city":"Steyr",
    "sg:classifiers":[
        {
            "category":"Arts & Performance",
            "subcategory":"Theater",
            "type":"Entertainment"
        }
    ],
    "sg:phone":"+43 7252 53512",
    "sg:postcode":"4400",
    "sg:province":"Ober\u00f6sterreich",
    "wof:name":"Altes Theater",
    "wof:placetype":"venue"
},
  "geometry": {"coordinates":[14.4188270569,48.0406951904],"type":"Point"}
}