{
  "type": "Feature",
  "properties": {
    "addr:full":"Wien Wien 1190",
    "addr:postcode":"1190",
    "iso:country":"AT",
    "sg:city":"Wien",
    "sg:orig_category":"Dienstleistungen, Sonstige Dienstleistungen",
    "sg:postcode":"1190",
    "sg:province":"Wien",
    "sg:website":"http://www.peruskic.at",
    "wof:name":"Glaserei Peruskic - klar wie Glas\u00b4",
    "wof:placetype":"venue"
},
  "geometry": {"coordinates":[16.3493022919,48.2389793396],"type":"Point"}
}