{
  "type": "Feature",
  "properties": {
    "addr:full":"Nr 75/POB 45 Attnang-Puchheim Ober\u00f6sterreich 4800",
    "addr:housenumber":"45",
    "addr:postcode":"4800",
    "addr:street":"Nr 75 / Pob",
    "iso:country":"AT",
    "sg:address":"Nr 75/POB 45",
    "sg:city":"Attnang-Puchheim",
    "sg:classifiers":[
        {
            "category":"Home & Garden",
            "subcategory":"Building Materials",
            "type":"Retail Goods"
        }
    ],
    "sg:phone":"+43 4376 746040",
    "sg:postcode":"4800",
    "sg:province":"Ober\u00f6sterreich",
    "sg:tags":[
        "baustoffe",
        "-material",
        "u"
    ],
    "wof:name":"Domo-Sanifer Koller & Reisinger Produktion Handel GmbH",
    "wof:placetype":"venue"
},
  "geometry": {"coordinates":[13.7204141617,48.0107002258],"type":"Point"}
}