{
  "type": "Feature",
  "properties": {
    "addr:full":"Alter Pl 31 Klagenfurt K\u00e4rnten 9020",
    "addr:housenumber":"31",
    "addr:postcode":"9020",
    "addr:street":"Alter Pl;Kaernten",
    "iso:country":"AT",
    "sg:address":"Alter Pl 31",
    "sg:city":"Klagenfurt",
    "sg:orig_category":"Fotografen",
    "sg:phone":"+43 4346 3513545",
    "sg:postcode":"9020",
    "sg:province":"K\u00e4rnten",
    "wof:name":"Fotoatelier Tollinger Inh Brigitte Rumpf",
    "wof:placetype":"venue"
},
  "geometry": {"coordinates":[14.3274202347,46.6254196167],"type":"Point"}
}