{
  "type": "Feature",
  "properties": {
    "addr:full":"Wasenboden 6A Villach K\u00e4rnten 9500",
    "addr:housenumber":"6a",
    "addr:postcode":"9500",
    "addr:street":"Wasenboden;Kaernten",
    "iso:country":"AT",
    "sg:address":"Wasenboden 6A",
    "sg:city":"Villach",
    "sg:orig_category":"Zimmereien",
    "sg:phone":"+43 4242 23269",
    "sg:postcode":"9500",
    "sg:province":"K\u00e4rnten",
    "wof:name":"Cichini Karl",
    "wof:placetype":"venue"
},
  "geometry": {"coordinates":[13.8613395691,46.6099205017],"type":"Point"}
}