{
  "type": "Feature",
  "properties": {
    "addr:full":"Sommerweg 12 Wien Wien 1210",
    "addr:housenumber":"12",
    "addr:postcode":"1210",
    "addr:street":"Sommerweg",
    "iso:country":"AT",
    "sg:address":"Sommerweg 12",
    "sg:city":"Wien",
    "sg:classifiers":[
        {
            "category":"Home & Garden",
            "subcategory":"Building Materials",
            "type":"Retail Goods"
        }
    ],
    "sg:phone":"+43 4312 564769",
    "sg:postcode":"1210",
    "sg:province":"Wien",
    "sg:tags":[
        "baustoffe",
        "-material",
        "u"
    ],
    "wof:name":"Innovative Baustoffe Vertrieb u Entwicklung GmbH",
    "wof:placetype":"venue"
},
  "geometry": {"coordinates":[16.4594860077,48.2737998962],"type":"Point"}
}