{
  "type": "Feature",
  "properties": {
    "addr:full":"Fischlhamer Strasse 27 Lambach Ober\u00f6sterreich 4650",
    "addr:housenumber":"27",
    "addr:postcode":"4650",
    "addr:street":"Fischlhamer Strasse",
    "iso:country":"AT",
    "sg:address":"Fischlhamer Strasse 27",
    "sg:city":"Lambach",
    "sg:classifiers":[
        {
            "category":"Utilities",
            "subcategory":"Natural Gas",
            "type":"Services"
        }
    ],
    "sg:phone":"+43 7245 21921",
    "sg:postcode":"4650",
    "sg:province":"Ober\u00f6sterreich",
    "sg:tags":[
        "lock",
        "cylinder"
    ],
    "sg:website":"schluesselzentrale.at",
    "wof:name":"Gerhard Altenhofer",
    "wof:placetype":"venue"
},
  "geometry": {"coordinates":[13.9132623672,48.0917320251],"type":"Point"}
}