{
  "type": "Feature",
  "properties": {
    "iso:country":"AT",
    "sg:address":"Karmarschg 46",
    "sg:city":"Wien",
    "sg:orig_category":"Schleifereien",
    "sg:phone":"+43 1 6044887",
    "sg:postcode":"1100",
    "sg:province":"Wien",
    "wof:name":"H\u00f6lzel & Speiser GesmbH",
    "wof:placetype":"venue"
},
  "geometry": {"coordinates":[16.3643035889,48.1759262085],"type":"Point"}
}