{
  "type": "Feature",
  "properties": {
    "iso:country":"AT",
    "sg:address":"Kirchpl 7",
    "sg:city":"St. Stefan ob Leoben",
    "sg:orig_category":"Tabaktrafiken",
    "sg:phone":"+43 3832 2668",
    "sg:postcode":"8713",
    "sg:province":"Steiermark",
    "wof:name":"Luber Peter",
    "wof:placetype":"venue"
},
  "geometry": {"coordinates":[14.9772195816,47.3177528381],"type":"Point"}
}