{
  "type": "Feature",
  "properties": {
    "addr:full":"Kurandtpl Klagenfurt K\u00e4rnten 9020",
    "addr:postcode":"9020",
    "iso:country":"AT",
    "sg:address":"Kurandtpl",
    "sg:city":"Klagenfurt",
    "sg:classifiers":[
        {
            "category":"Restaurant",
            "type":"Food & Drink"
        }
    ],
    "sg:phone":"+43 463 204999",
    "sg:postcode":"9020",
    "sg:province":"K\u00e4rnten",
    "wof:name":"ARTECIELO",
    "wof:placetype":"venue"
},
  "geometry": {"coordinates":[14.2829322815,46.6224212646],"type":"Point"}
}