{
  "type": "Feature",
  "properties": {
    "addr:full":"Seeuferstr 7 Zell am See Salzburg 5700",
    "addr:housenumber":"7",
    "addr:postcode":"5700",
    "addr:street":"Seeuferstr;Salzburg",
    "iso:country":"AT",
    "sg:address":"Seeuferstr 7",
    "sg:city":"Zell am See",
    "sg:classifiers":[
        {
            "category":"Travel",
            "subcategory":"Hotels & Motels",
            "type":"Entertainment"
        }
    ],
    "sg:phone":"+43 6542 7670",
    "sg:postcode":"5700",
    "sg:province":"Salzburg",
    "wof:name":"Hotel St Hubertushof",
    "wof:placetype":"venue"
},
  "geometry": {"coordinates":[12.8170022964,47.32837677],"type":"Point"}
}