{
  "type": "Feature",
  "properties": {
    "addr:full":"Teslastrasse 8 Raaba Steiermark 8074",
    "addr:housenumber":"8",
    "addr:postcode":"8074",
    "addr:street":"Teslastrasse",
    "iso:country":"AT",
    "sg:address":"Teslastrasse 8",
    "sg:city":"Raaba",
    "sg:classifiers":[
        {
            "category":"Shopping",
            "subcategory":"Computers & Home Electronics",
            "type":"Retail Goods"
        }
    ],
    "sg:phone":"+43 316 40000",
    "sg:postcode":"8074",
    "sg:province":"Steiermark",
    "sg:tags":[
        "system",
        "automation"
    ],
    "sg:website":"mrautomation.at",
    "wof:name":"M & R Automation GmbH",
    "wof:placetype":"venue"
},
  "geometry": {"coordinates":[15.4962043762,47.0285224915],"type":"Point"}
}