{
  "type": "Feature",
  "properties": {
    "addr:full":"Nr 43 Selzthal Steiermark 8900",
    "addr:postcode":"8900",
    "addr:street":"Nr 43",
    "iso:country":"AT",
    "sg:address":"Nr 43",
    "sg:city":"Selzthal",
    "sg:orig_category":"Elektroinstallationsunternehmen",
    "sg:phone":"+43 3616 7187",
    "sg:postcode":"8900",
    "sg:province":"Steiermark",
    "wof:name":"Elektrotechnik Ing Michael F\u00f6lsner",
    "wof:placetype":"venue"
},
  "geometry": {"coordinates":[14.3138341904,47.5491828918],"type":"Point"}
}