{
  "type": "Feature",
  "properties": {
    "addr:full":"Hocheggerstr 1 Leonding Ober\u00f6sterreich 4060",
    "addr:housenumber":"1",
    "addr:postcode":"4060",
    "addr:street":"Hocheggerstr",
    "iso:country":"AT",
    "sg:address":"Hocheggerstr 1",
    "sg:city":"Leonding",
    "sg:orig_category":"Offsetdruckereien",
    "sg:phone":"+43 4373 2602268",
    "sg:postcode":"4060",
    "sg:province":"Ober\u00f6sterreich",
    "wof:name":"Froschauer Johann",
    "wof:placetype":"venue"
},
  "geometry": {"coordinates":[14.2491264343,48.2792434692],"type":"Point"}
}