{
  "type": "Feature",
  "properties": {
    "iso:country":"AT",
    "sg:address":"Ringstr 33",
    "sg:city":"Wels",
    "sg:orig_category":"Notare",
    "sg:phone":"+43 7242 450500",
    "sg:postcode":"4600",
    "sg:province":"Ober\u00f6sterreich",
    "wof:name":"Platzer Hans J\u00f6rg Dr",
    "wof:placetype":"venue"
},
  "geometry": {"coordinates":[14.0243320465,48.1585922241],"type":"Point"}
}