{
  "type": "Feature",
  "properties": {
    "addr:full":"Stanz im M\u00fcrztal 92 Stanz im M\u00fcrztal Steiermark 8653",
    "addr:housenumber":"92;im",
    "addr:postcode":"8653",
    "addr:street":"Muerztal Steiermark",
    "iso:country":"AT",
    "sg:address":"Stanz im M\u00fcrztal 92",
    "sg:city":"Stanz im M\u00fcrztal",
    "sg:classifiers":[
        {
            "category":"Manufacturing",
            "subcategory":"Wood Products",
            "type":"Manufacturing & Wholesale Goods"
        }
    ],
    "sg:phone":"+43 3865 88880",
    "sg:postcode":"8653",
    "sg:province":"Steiermark",
    "sg:tags":[
        "tree",
        "felling",
        "difficult"
    ],
    "wof:name":"Forstgut M\u00e4hring",
    "wof:placetype":"venue"
},
  "geometry": {"coordinates":[-94.2612609863,41.3159103394],"type":"Point"}
}