{
  "type": "Feature",
  "properties": {
    "addr:full":"Gallitzinstr 97 Wien Wien 1160",
    "addr:housenumber":"97",
    "addr:postcode":"1160",
    "addr:street":"Gallitzinstr",
    "iso:country":"AT",
    "sg:address":"Gallitzinstr 97",
    "sg:city":"Wien",
    "sg:orig_category":"Innenausbau",
    "sg:phone":"+43 4314 942228",
    "sg:postcode":"1160",
    "sg:province":"Wien",
    "wof:name":"Penthouse Bau & Trading GmbH",
    "wof:placetype":"venue"
},
  "geometry": {"coordinates":[16.2820262909,48.2166061401],"type":"Point"}
}