{
  "type": "Feature",
  "properties": {
    "addr:full":"Kirchpl 11 Mutters Tirol 6162",
    "addr:housenumber":"11",
    "addr:postcode":"6162",
    "addr:street":"Kirchpl;Tirol",
    "iso:country":"AT",
    "sg:address":"Kirchpl 11",
    "sg:city":"Mutters",
    "sg:orig_category":"Tourismusinformation U -Organisationen",
    "sg:phone":"+43 4351 2548410",
    "sg:postcode":"6162",
    "sg:province":"Tirol",
    "wof:name":"Tourismusb\u00fcro Mutters",
    "wof:placetype":"venue"
},
  "geometry": {"coordinates":[11.3777770996,47.2272148132],"type":"Point"}
}