{
  "type": "Feature",
  "properties": {
    "iso:country":"AT",
    "sg:address":"Innsbruck Bundesstr 26",
    "sg:city":"Salzburg",
    "sg:orig_category":"Ingenieurkonsulenten / Zivilingenieure",
    "sg:phone":"+43 662 439256",
    "sg:postcode":"5020",
    "sg:province":"Salzburg",
    "wof:name":"Heitzinger Walter Dipl-Ing Dr",
    "wof:placetype":"venue"
},
  "geometry": {"coordinates":[13.0227241516,47.8054542542],"type":"Point"}
}