{
  "type": "Feature",
  "properties": {
    "addr:full":"Europapl 4 Graz Steiermark 8020",
    "addr:housenumber":"4",
    "addr:postcode":"8020",
    "addr:street":"Europapl",
    "iso:country":"AT",
    "sg:address":"Europapl 4",
    "sg:city":"Graz",
    "sg:orig_category":"Blumeneinzelhandel",
    "sg:phone":"+43 316 713987",
    "sg:postcode":"8020",
    "sg:province":"Steiermark",
    "sg:website":"blumenstudio.co.at",
    "wof:name":"Blumenstudio",
    "wof:placetype":"venue"
},
  "geometry": {"coordinates":[15.4166593552,47.0729789734],"type":"Point"}
}