{
  "type": "Feature",
  "properties": {
    "addr:full":"Halblehenweg 8 Wien Wien 1220",
    "addr:housenumber":"8",
    "addr:postcode":"1220",
    "addr:street":"Halblehenweg",
    "iso:country":"AT",
    "sg:address":"Halblehenweg 8",
    "sg:city":"Wien",
    "sg:classifiers":[
        {
            "category":"Taxi",
            "type":"Transportation"
        }
    ],
    "sg:phone":"+43 4366 41416215",
    "sg:postcode":"1220",
    "sg:province":"Wien",
    "sg:tags":[
        "personentransporte",
        "u"
    ],
    "wof:name":"Teufner Josef",
    "wof:placetype":"venue"
},
  "geometry": {"coordinates":[16.4814682007,48.2474784851],"type":"Point"}
}