{
  "type": "Feature",
  "properties": {
    "addr:full":"Wolfgang Pauli-Str 2 Linz Ober\u00f6sterreich 4020",
    "addr:housenumber":"2",
    "addr:postcode":"4020",
    "iso:country":"AT",
    "sg:address":"Wolfgang Pauli-Str 2",
    "sg:city":"Linz",
    "sg:orig_category":"Telekommunikation",
    "sg:phone":"+43 732 943812",
    "sg:postcode":"4020",
    "sg:province":"Ober\u00f6sterreich",
    "wof:name":"Itworx",
    "wof:placetype":"venue"
},
  "geometry": {"coordinates":[14.3052854538,48.2802658081],"type":"Point"}
}