{
  "type": "Feature",
  "properties": {
    "addr:full":"Belgierg 12 Graz Steiermark 8020",
    "addr:housenumber":"12",
    "addr:postcode":"8020",
    "addr:street":"Belgierg",
    "iso:country":"AT",
    "sg:address":"Belgierg 12",
    "sg:city":"Graz",
    "sg:orig_category":"Juweliere, Gold- U Silberschmiede",
    "sg:phone":"+43 4331 6713407",
    "sg:postcode":"8020",
    "sg:province":"Steiermark",
    "wof:name":"Schmalz Uhren Juwelen",
    "wof:placetype":"venue"
},
  "geometry": {"coordinates":[15.4324178696,47.0697593689],"type":"Point"}
}