{
  "type": "Feature",
  "properties": {
    "addr:full":"Donaustrasse 110 Klosterneuburg Nieder\u00f6sterreich 3400",
    "addr:housenumber":"110",
    "addr:postcode":"3400",
    "addr:street":"Donaustrasse;Niederoesterreich",
    "iso:country":"AT",
    "sg:address":"Donaustrasse 110",
    "sg:city":"Klosterneuburg",
    "sg:classifiers":[
        {
            "category":"Bars & Pubs",
            "subcategory":"Gay Bar",
            "type":"Food & Drink"
        }
    ],
    "sg:phone":"+43 2243 328300",
    "sg:postcode":"3400",
    "sg:province":"Nieder\u00f6sterreich",
    "sg:tags":[
        "injection",
        "moulding",
        "clean-room"
    ],
    "sg:website":"goller.at",
    "wof:name":"Hubertus Goller Ges.m.b.H.",
    "wof:placetype":"venue"
},
  "geometry": {"coordinates":[16.3441371918,48.2903060913],"type":"Point"}
}