{
  "type": "Feature",
  "properties": {
    "addr:full":"Langobardenstr 103 Wien Wien 1220",
    "addr:housenumber":"103",
    "addr:postcode":"1220",
    "iso:country":"AT",
    "sg:address":"Langobardenstr 103",
    "sg:city":"Wien",
    "sg:orig_category":"Banken U Sparkassen",
    "sg:phone":"+43 4350 50535500",
    "sg:postcode":"1220",
    "sg:province":"Wien",
    "wof:name":"Bank Austria Creditanstalt AG",
    "wof:placetype":"venue"
},
  "geometry": {"coordinates":[16.4649581909,48.2195701599],"type":"Point"}
}