{
  "type": "Feature",
  "properties": {
    "addr:full":"Helfentalweg 2 Innsbruck Tirol 6020",
    "addr:housenumber":"2",
    "addr:postcode":"6020",
    "addr:street":"Helfentalweg;Tirol",
    "iso:country":"AT",
    "sg:address":"Helfentalweg 2",
    "sg:city":"Innsbruck",
    "sg:orig_category":"Physiotherapie",
    "sg:phone":"+43 650 5333221",
    "sg:postcode":"6020",
    "sg:province":"Tirol",
    "wof:name":"Blasy Franziska",
    "wof:placetype":"venue"
},
  "geometry": {"coordinates":[11.4233074188,47.2839202881],"type":"Point"}
}