{
  "type": "Feature",
  "properties": {
    "addr:full":"Grazer Pl 7 F\u00fcrstenfeld Steiermark 8280",
    "addr:housenumber":"7",
    "addr:postcode":"8280",
    "addr:street":"Grazer Pl",
    "iso:country":"AT",
    "sg:address":"Grazer Pl 7",
    "sg:city":"F\u00fcrstenfeld",
    "sg:orig_category":"Psychotherapie",
    "sg:phone":"+43 3382 54040",
    "sg:postcode":"8280",
    "sg:province":"Steiermark",
    "wof:name":"Kropf Herbert Dr",
    "wof:placetype":"venue"
},
  "geometry": {"coordinates":[16.07330513,47.0521278381],"type":"Point"}
}