{
  "type": "Feature",
  "properties": {
    "addr:full":"Nr 41 Krakaudorf Steiermark 8854",
    "addr:postcode":"8854",
    "addr:street":"Nr",
    "iso:country":"AT",
    "sg:address":"Nr 41",
    "sg:city":"Krakaudorf",
    "sg:orig_category":"Pensionen / Privatzimmer",
    "sg:phone":"+43 3535 8454",
    "sg:postcode":"8854",
    "sg:province":"Steiermark",
    "wof:name":"Standlhof",
    "wof:placetype":"venue"
},
  "geometry": {"coordinates":[13.9644861221,47.1889724731],"type":"Point"}
}