{
  "type": "Feature",
  "properties": {
    "addr:full":"Kirchbichl 30 Ellmau Tirol 6352",
    "addr:housenumber":"30",
    "addr:postcode":"6352",
    "addr:street":"Kirchbichl;Tirol",
    "iso:country":"AT",
    "sg:address":"Kirchbichl 30",
    "sg:city":"Ellmau",
    "sg:orig_category":"Pensionen / Privatzimmer",
    "sg:phone":"+43 5358 23230",
    "sg:postcode":"6352",
    "sg:province":"Tirol",
    "wof:name":"Pension Kirchbichlhof",
    "wof:placetype":"venue"
},
  "geometry": {"coordinates":[12.304233551,47.5135993958],"type":"Point"}
}