{
  "type": "Feature",
  "properties": {
    "addr:full":"Hauptplatz 15  Wilhelmsburg an der Traisen Nieder\u00f6sterreich 3150",
    "addr:housenumber":"15",
    "addr:postcode":"3150",
    "addr:street":"Hauptplatz;An",
    "iso:country":"AT",
    "sg:address":"Hauptplatz 15 ",
    "sg:city":"Wilhelmsburg an der Traisen",
    "sg:classifiers":[
        {
            "category":"Food & Beverages",
            "subcategory":"Groceries & Convenience Stores",
            "type":"Retail Goods"
        }
    ],
    "sg:phone":"+43 4327 462351",
    "sg:postcode":"3150",
    "sg:province":"Nieder\u00f6sterreich",
    "sg:tags":[
        "product",
        "related"
    ],
    "wof:name":"FLEISCHEREI FRANZ BERGER",
    "wof:placetype":"venue"
},
  "geometry": {"coordinates":[15.605890274,48.1050491333],"type":"Point"}
}