{
  "type": "Feature",
  "properties": {
    "iso:country":"AT",
    "sg:address":"Ried 113",
    "sg:city":"Gerlos",
    "sg:orig_category":"Pensionen / Privatzimmer",
    "sg:phone":"+43 5284 5510",
    "sg:postcode":"6281",
    "sg:province":"Tirol",
    "wof:name":"Kupfnerhof Fr\u00fchst\u00fcckspension",
    "wof:placetype":"venue"
},
  "geometry": {"coordinates":[12.0296506882,47.2242927551],"type":"Point"}
}