{
  "type": "Feature",
  "properties": {
    "addr:full":"Marianneng 26 Wien Wien 1090",
    "addr:housenumber":"26",
    "addr:postcode":"1090",
    "addr:street":"Marianneng",
    "iso:country":"AT",
    "sg:address":"Marianneng 26",
    "sg:city":"Wien",
    "sg:classifiers":[
        {
            "category":"Professional",
            "type":"Services"
        }
    ],
    "sg:phone":"+43 1 4066647",
    "sg:postcode":"1090",
    "sg:province":"Wien",
    "sg:tags":[
        "leasing"
    ],
    "wof:name":"Hypo S\u00fcdleasing GmbH",
    "wof:placetype":"venue"
},
  "geometry": {"coordinates":[16.3466281891,48.2164039612],"type":"Point"}
}