{
  "type": "Feature",
  "properties": {
    "addr:full":"Hauptstr 24 Gerasdorf Nieder\u00f6sterreich 2201",
    "addr:housenumber":"24",
    "addr:postcode":"2201",
    "addr:street":"Hauptstr",
    "iso:country":"AT",
    "sg:address":"Hauptstr 24",
    "sg:city":"Gerasdorf",
    "sg:orig_category":"Tischlereien",
    "sg:phone":"+43 2246 802470",
    "sg:postcode":"2201",
    "sg:province":"Nieder\u00f6sterreich",
    "wof:name":"K\u00f6rmer Josef",
    "wof:placetype":"venue"
},
  "geometry": {"coordinates":[16.4811038971,48.3328132629],"type":"Point"}
}