{
  "type": "Feature",
  "properties": {
    "addr:full":"Panoramastr 28 Kirchbichl Tirol 6322",
    "addr:housenumber":"28",
    "addr:postcode":"6322",
    "addr:street":"Panoramastr;Tirol",
    "iso:country":"AT",
    "sg:address":"Panoramastr 28",
    "sg:city":"Kirchbichl",
    "sg:orig_category":"Yachtcharter",
    "sg:phone":"+43 5332 87529",
    "sg:postcode":"6322",
    "sg:province":"Tirol",
    "wof:name":"Tirol Yachting",
    "wof:placetype":"venue"
},
  "geometry": {"coordinates":[12.0931711197,47.504234314],"type":"Point"}
}