{
  "type": "Feature",
  "properties": {
    "addr:full":"Almteilweg 1 B\u00fcrs Vorarlberg 6706",
    "addr:housenumber":"1",
    "addr:postcode":"6706",
    "addr:street":"Almteilweg",
    "iso:country":"AT",
    "sg:address":"Almteilweg 1",
    "sg:city":"B\u00fcrs",
    "sg:orig_category":"Friseure U Frisiersalons",
    "sg:phone":"+43 5552 31303",
    "sg:postcode":"6706",
    "sg:province":"Vorarlberg",
    "wof:name":"Sprenger Alexander",
    "wof:placetype":"venue"
},
  "geometry": {"coordinates":[9.8131332397,47.1508293152],"type":"Point"}
}