{
  "type": "Feature",
  "properties": {
    "addr:full":"Fischeraustr. 27 G\u00f6sting Steiermark 8051",
    "addr:housenumber":"27",
    "addr:postcode":"8051",
    "addr:street":"Fischeraustr.",
    "iso:country":"AT",
    "sg:address":"Fischeraustr. 27",
    "sg:city":"G\u00f6sting",
    "sg:classifiers":[
        {
            "category":"Utilities",
            "subcategory":"Electric",
            "type":"Services"
        }
    ],
    "sg:phone":"+43 4331 660960",
    "sg:postcode":"8051",
    "sg:province":"Steiermark",
    "sg:tags":[
        "component",
        "electronic"
    ],
    "wof:name":"SSI SCH\u00c4FER PEEM GMBH",
    "wof:placetype":"venue"
},
  "geometry": {"coordinates":[15.409081459,47.096206665],"type":"Point"}
}