{
  "type": "Feature",
  "properties": {
    "iso:country":"AT",
    "sg:address":"Aist 39",
    "sg:city":"Ernsthofen",
    "sg:classifiers":[
        {
            "category":"Government",
            "subcategory":"Department Of Motor Vehicles",
            "type":"Public Place"
        }
    ],
    "sg:phone":"+43 7262 58641",
    "sg:postcode":"4432",
    "sg:province":"Nieder\u00f6sterreich",
    "sg:tags":[
        "car",
        "rental",
        "brokerage"
    ],
    "wof:name":"Scheuwimmer Fahrzeugbau GesmbH & Co KG",
    "wof:placetype":"venue"
},
  "geometry": {"coordinates":[14.4825601578,48.1268806458],"type":"Point"}
}