{
  "type": "Feature",
  "properties": {
    "addr:full":"Ailecg. 34  Wien Wien 1110",
    "addr:housenumber":"34",
    "addr:postcode":"1110",
    "addr:street":"Ailecg.",
    "iso:country":"AT",
    "sg:address":"Ailecg. 34 ",
    "sg:city":"Wien",
    "sg:classifiers":[
        {
            "category":"Manufacturing",
            "subcategory":"Tools & Machinery",
            "type":"Manufacturing & Wholesale Goods"
        }
    ],
    "sg:phone":"+43 4313 3031600",
    "sg:postcode":"1110",
    "sg:province":"Wien",
    "sg:tags":[
        "environment",
        "equipment",
        "-"
    ],
    "wof:name":"P.M.P. GMBH",
    "wof:placetype":"venue"
},
  "geometry": {"coordinates":[16.4566802979,48.1410713196],"type":"Point"}
}