{
  "type": "Feature",
  "properties": {
    "iso:country":"AT",
    "sg:address":"Sch\u00f6pfstr 23A/3",
    "sg:city":"Innsbruck",
    "sg:classifiers":[
        {
            "category":"Government",
            "subcategory":"Post Office",
            "type":"Public Place"
        }
    ],
    "sg:phone":"+43 512 562314",
    "sg:postcode":"6020",
    "sg:province":"Tirol",
    "sg:tags":[
        "yoga"
    ],
    "wof:name":"Yoga-Zentrum Innsbruck",
    "wof:placetype":"venue"
},
  "geometry": {"coordinates":[11.390162468,47.2601928711],"type":"Point"}
}