{
  "type": "Feature",
  "properties": {
    "addr:full":"Ungargasse 36 Wien Wien 1030",
    "addr:housenumber":"36",
    "addr:postcode":"1030",
    "addr:street":"Ungargasse",
    "iso:country":"AT",
    "sg:address":"Ungargasse 36",
    "sg:city":"Wien",
    "sg:classifiers":[
        {
            "category":"Home & Garden",
            "subcategory":"Building Materials",
            "type":"Retail Goods"
        }
    ],
    "sg:phone":"+43 1 7139534",
    "sg:postcode":"1030",
    "sg:province":"Wien",
    "sg:tags":[
        "tile",
        "marble"
    ],
    "wof:name":"Demuth Ges.m.b.H.",
    "wof:placetype":"venue"
},
  "geometry": {"coordinates":[16.3872241974,48.2005577087],"type":"Point"}
}