{
  "type": "Feature",
  "properties": {
    "iso:country":"AT",
    "sg:address":"Maurer Lange G 24",
    "sg:city":"Wien",
    "sg:classifiers":[
        {
            "category":"Personal",
            "subcategory":"Sauna",
            "type":"Services"
        }
    ],
    "sg:phone":"+43 4318 898280",
    "sg:postcode":"1230",
    "sg:province":"Wien",
    "sg:tags":[
        "u",
        "dampfbad"
    ],
    "wof:name":"Teufel Sauna",
    "wof:placetype":"venue"
},
  "geometry": {"coordinates":[16.2734394073,48.1480140686],"type":"Point"}
}