{
  "type": "Feature",
  "properties": {
    "iso:country":"AT",
    "sg:address":"Alberlochstr 7",
    "sg:city":"Lochau",
    "sg:orig_category":"Textilwaren / Einzelhandel",
    "sg:phone":"+43 5574 478400",
    "sg:postcode":"6911",
    "sg:province":"Vorarlberg",
    "wof:name":"TPS",
    "wof:placetype":"venue"
},
  "geometry": {"coordinates":[9.7503738403,47.5317802429],"type":"Point"}
}