{
  "type": "Feature",
  "properties": {
    "addr:full":"Gotschuchen 62 St. Margareten im Rosental K\u00e4rnten 9173",
    "addr:housenumber":"62",
    "addr:postcode":"9173",
    "addr:street":"Gotschuchen",
    "iso:country":"AT",
    "sg:address":"Gotschuchen 62",
    "sg:city":"St. Margareten im Rosental",
    "sg:orig_category":"Physiotherapie",
    "sg:phone":"+43 4367 64931002",
    "sg:postcode":"9173",
    "sg:province":"K\u00e4rnten",
    "wof:name":"Pogoriutschnig Annette Dipl-PT",
    "wof:placetype":"venue"
},
  "geometry": {"coordinates":[14.4001588821,46.5399246216],"type":"Point"}
}