{
  "type": "Feature",
  "properties": {
    "addr:full":"Gewerbestr 5 Baden Nieder\u00f6sterreich 2500",
    "addr:housenumber":"5",
    "addr:postcode":"2500",
    "addr:street":"Gewerbestr;Niederoesterreich",
    "iso:country":"AT",
    "sg:address":"Gewerbestr 5",
    "sg:city":"Baden",
    "sg:orig_category":"Autohandel",
    "sg:phone":"+43 2252 86996",
    "sg:postcode":"2500",
    "sg:province":"Nieder\u00f6sterreich",
    "wof:name":"KFZ Zeller GmbH",
    "wof:placetype":"venue"
},
  "geometry": {"coordinates":[16.2783756256,47.9728736877],"type":"Point"}
}