{
  "type": "Feature",
  "properties": {
    "addr:full":"Brenner Str 77a Steinach am Brenner Tirol 6150",
    "addr:postcode":"6150",
    "addr:street":"Str 77A;Tirol",
    "iso:country":"AT",
    "sg:address":"Brenner Str 77a",
    "sg:city":"Steinach am Brenner",
    "sg:orig_category":"Lebensmittel / Einzelhandel",
    "sg:phone":"+43 5272 2461",
    "sg:postcode":"6150",
    "sg:province":"Tirol",
    "wof:name":"Billa AG",
    "wof:placetype":"venue"
},
  "geometry": {"coordinates":[11.4681158066,47.0887069702],"type":"Point"}
}