{
  "type": "Feature",
  "properties": {
    "addr:full":"Parkring 7 St. Stefan im Rosental Steiermark 8083",
    "addr:housenumber":"7",
    "addr:postcode":"8083",
    "addr:street":"Parkring",
    "iso:country":"AT",
    "sg:address":"Parkring 7",
    "sg:city":"St. Stefan im Rosental",
    "sg:orig_category":"Zimmereien",
    "sg:phone":"+43 4331 1681076",
    "sg:postcode":"8083",
    "sg:province":"Steiermark",
    "wof:name":"Hecher Johann GesmbH",
    "wof:placetype":"venue"
},
  "geometry": {"coordinates":[15.7104692459,46.9051399231],"type":"Point"}
}