{
  "type": "Feature",
  "properties": {
    "addr:full":"Neudorfstr 8 Wolfurt Vorarlberg 6922",
    "addr:housenumber":"8",
    "addr:postcode":"6922",
    "addr:street":"Neudorfstr",
    "iso:country":"AT",
    "sg:address":"Neudorfstr 8",
    "sg:city":"Wolfurt",
    "sg:orig_category":"Innenarchitekten",
    "sg:phone":"+43 4355 7474974",
    "sg:postcode":"6922",
    "sg:province":"Vorarlberg",
    "wof:name":"Eberle Doris - Einrichtungsberatung",
    "wof:placetype":"venue"
},
  "geometry": {"coordinates":[9.7476730347,47.4689064026],"type":"Point"}
}