{
  "type": "Feature",
  "properties": {
    "addr:full":"Grazer Str 1 Fehring Steiermark 8350",
    "addr:housenumber":"1",
    "addr:postcode":"8350",
    "addr:street":"Str",
    "iso:country":"AT",
    "sg:address":"Grazer Str 1",
    "sg:city":"Fehring",
    "sg:classifiers":[
        {
            "category":"Communications",
            "subcategory":"Film & Video Production",
            "type":"Services"
        }
    ],
    "sg:phone":"+43 4331 552865",
    "sg:postcode":"8350",
    "sg:province":"Steiermark",
    "sg:tags":[
        "multimedia"
    ],
    "wof:name":"M.M.C. multimediales Informations-, Ausbildungs- u Kommunikationszentrum GmbH",
    "wof:placetype":"venue"
},
  "geometry": {"coordinates":[16.009771347,46.9361724854],"type":"Point"}
}