{
  "type": "Feature",
  "properties": {
    "iso:country":"AT",
    "sg:address":"Anna-Grundschober-Gasse 6",
    "sg:city":"Stockerau",
    "sg:classifiers":[
        {
            "category":"Taxi",
            "type":"Transportation"
        }
    ],
    "sg:phone":"+43 2266 71941",
    "sg:postcode":"2000",
    "sg:province":"Nieder\u00f6sterreich",
    "sg:tags":[
        "furniture"
    ],
    "wof:name":"Karl Kickinger",
    "wof:placetype":"venue"
},
  "geometry": {"coordinates":[16.1836261749,48.3840789795],"type":"Point"}
}