{
  "type": "Feature",
  "properties": {
    "iso:country":"AT",
    "sg:address":"Nr 113",
    "sg:city":"Regau",
    "sg:orig_category":"Energieberatung U -Untersuchung",
    "sg:phone":"+43 4376 722542314",
    "sg:postcode":"4844",
    "sg:province":"Ober\u00f6sterreich",
    "wof:name":"Infratherm Me\u00dftechnik GmbH - Baudiagnostik-Schadensanalyse-Industriethermographie",
    "wof:placetype":"venue"
},
  "geometry": {"coordinates":[13.689125061,47.9909744263],"type":"Point"}
}