{
  "type": "Feature",
  "properties": {
    "addr:full":"Tristacher See 1 Lienz Tirol 9900",
    "addr:housenumber":"1",
    "addr:postcode":"9900",
    "addr:street":"See;Tirol",
    "iso:country":"AT",
    "sg:address":"Tristacher See 1",
    "sg:city":"Lienz",
    "sg:classifiers":[
        {
            "category":"Travel",
            "subcategory":"Hotels & Motels",
            "type":"Entertainment"
        }
    ],
    "sg:phone":"+43 4852 676660",
    "sg:postcode":"9900",
    "sg:province":"Tirol",
    "wof:name":"Parkhotel Tristachersee",
    "wof:placetype":"venue"
},
  "geometry": {"coordinates":[12.7684783936,46.8281173706],"type":"Point"}
}