{
  "type": "Feature",
  "properties": {
    "iso:country":"AT",
    "sg:address":"Schulstrasse 8",
    "sg:city":"Mank",
    "sg:classifiers":[
        {
            "category":"Food & Beverages",
            "subcategory":"Meat & Fish",
            "type":"Retail Goods"
        }
    ],
    "sg:phone":"+43 2755 2343",
    "sg:postcode":"3240",
    "sg:province":"Nieder\u00f6sterreich",
    "sg:tags":[
        "pie"
    ],
    "wof:name":"Gasthof Fleischhauerei Veronika Sch\u00f6nbichler",
    "wof:placetype":"venue"
},
  "geometry": {"coordinates":[15.3405590057,48.1106948853],"type":"Point"}
}