{
  "type": "Feature",
  "properties": {
    "addr:full":"Marchfeldg 2 Kitzb\u00fchel Tirol 6370",
    "addr:housenumber":"2",
    "addr:postcode":"6370",
    "addr:street":"Marchfeldg;Tirol",
    "iso:country":"AT",
    "sg:address":"Marchfeldg 2",
    "sg:city":"Kitzb\u00fchel",
    "sg:classifiers":[
        {
            "category":"Travel",
            "subcategory":"Hotels & Motels",
            "type":"Entertainment"
        }
    ],
    "sg:phone":"+43 5356 752520",
    "sg:postcode":"6370",
    "sg:province":"Tirol",
    "wof:name":"Hotel Edelwei\u00df",
    "wof:placetype":"venue"
},
  "geometry": {"coordinates":[12.3930454254,47.4412994385],"type":"Point"}
}