{
  "type": "Feature",
  "properties": {
    "addr:full":"Ernstbrunner Str 13 Leitzersdorf Nieder\u00f6sterreich 2003",
    "addr:postcode":"2003",
    "addr:street":"Str 13 Leitzersdorf",
    "iso:country":"AT",
    "sg:address":"Ernstbrunner Str 13",
    "sg:city":"Leitzersdorf",
    "sg:orig_category":"Alarmanlagen U Sicherheitssysteme",
    "sg:phone":"+43 4322 6664006",
    "sg:postcode":"2003",
    "sg:province":"Nieder\u00f6sterreich",
    "wof:name":"Radosztics Sicherheitstechnik",
    "wof:placetype":"venue"
},
  "geometry": {"coordinates":[16.2450046539,48.4192504883],"type":"Point"}
}