{
  "type": "Feature",
  "properties": {
    "iso:country":"AT",
    "sg:address":"Franz Liszt-Str 15",
    "sg:city":"Winden am See",
    "sg:orig_category":"Pensionen / Privatzimmer",
    "sg:phone":"+43 2160 8243",
    "sg:postcode":"7092",
    "sg:province":"Burgenland",
    "wof:name":"Kugler Gertrude",
    "wof:placetype":"venue"
},
  "geometry": {"coordinates":[16.7556266785,47.9520492554],"type":"Point"}
}