{
  "type": "Feature",
  "properties": {
    "addr:full":"Dr.-Ludwig-Leser-G 26/3c Siegendorf im Burgenland Burgenland 7011",
    "addr:housenumber":"26 / 3c",
    "addr:postcode":"7011",
    "addr:street":"Dr.-Ludwig-Leser-G",
    "iso:country":"AT",
    "sg:address":"Dr.-Ludwig-Leser-G 26/3c",
    "sg:city":"Siegendorf im Burgenland",
    "sg:orig_category":"Balkon-, Loggien- U Terrassenverbauten",
    "sg:phone":"+43 4326 8745023",
    "sg:postcode":"7011",
    "sg:province":"Burgenland",
    "wof:name":"Nowack Stephan J GesmbH",
    "wof:placetype":"venue"
},
  "geometry": {"coordinates":[16.5358543396,47.7808990479],"type":"Point"}
}