{
  "type": "Feature",
  "properties": {
    "iso:country":"AT",
    "sg:address":"Neug 3",
    "sg:city":"Blindenmarkt",
    "sg:orig_category":"Fotografen",
    "sg:phone":"+43 664 3125981",
    "sg:postcode":"3372",
    "sg:province":"Nieder\u00f6sterreich",
    "wof:name":"Foto Bemmer",
    "wof:placetype":"venue"
},
  "geometry": {"coordinates":[14.9881477356,48.1284942627],"type":"Point"}
}