{
  "type": "Feature",
  "properties": {
    "addr:full":"Johann-Staud-Str 32 Wien Wien 1160",
    "addr:housenumber":"32",
    "addr:postcode":"1160",
    "addr:street":"Johann-Staud-Str",
    "iso:country":"AT",
    "sg:address":"Johann-Staud-Str 32",
    "sg:city":"Wien",
    "sg:orig_category":"Appartements / Ferienwohnungen",
    "sg:phone":"+43 4314 198770",
    "sg:postcode":"1160",
    "sg:province":"Wien",
    "sg:website":"umwelthotel.at",
    "wof:name":"Hotel Gallitzinberg",
    "wof:placetype":"venue"
},
  "geometry": {"coordinates":[16.2830162048,48.2148628235],"type":"Point"}
}