{
  "type": "Feature",
  "properties": {
    "addr:full":"Innrain 21 Innsbruck Tirol 6020",
    "addr:housenumber":"21",
    "addr:postcode":"6020",
    "addr:street":"Innrain;Tirol",
    "iso:country":"AT",
    "sg:address":"Innrain 21",
    "sg:city":"Innsbruck",
    "sg:orig_category":"Orientteppiche",
    "sg:phone":"+43 512 581185",
    "sg:postcode":"6020",
    "sg:province":"Tirol",
    "wof:name":"Graus Orientteppich",
    "wof:placetype":"venue"
},
  "geometry": {"coordinates":[11.3900089264,47.2660827637],"type":"Point"}
}