{
  "type": "Feature",
  "properties": {
    "addr:full":"Dammstr 20 Lauterach Vorarlberg 6923",
    "addr:housenumber":"20",
    "addr:postcode":"6923",
    "addr:street":"Dammstr",
    "iso:country":"AT",
    "sg:address":"Dammstr 20",
    "sg:city":"Lauterach",
    "sg:orig_category":"Abschleppdienste",
    "sg:phone":"+43 5574 46666",
    "sg:postcode":"6923",
    "sg:province":"Vorarlberg",
    "wof:name":"Auto Immler Handelsgesellschaft m.b.H.",
    "wof:placetype":"venue"
},
  "geometry": {"coordinates":[9.7217855453,47.4857978821],"type":"Point"}
}