{
  "type": "Feature",
  "properties": {
    "addr:full":"Wagramer Str 128 Wien Wien 1220",
    "addr:housenumber":"128",
    "addr:postcode":"1220",
    "iso:country":"AT",
    "sg:address":"Wagramer Str 128",
    "sg:city":"Wien",
    "sg:orig_category":"Papier- U Schreibwaren / Einzelhandel",
    "sg:phone":"+43 4312 034351",
    "sg:postcode":"1220",
    "sg:province":"Wien",
    "wof:name":"Freudensprung Rudolf GesmbH",
    "wof:placetype":"venue"
},
  "geometry": {"coordinates":[16.4416599274,48.2477111816],"type":"Point"}
}