{
  "type": "Feature",
  "properties": {
    "addr:full":"St. Veiter Str 2 Feldkirchen in K\u00e4rnten K\u00e4rnten 9560",
    "addr:housenumber":"2",
    "addr:postcode":"9560",
    "addr:street":"St. Veiter Str;Kaernten",
    "iso:country":"AT",
    "sg:address":"St. Veiter Str 2",
    "sg:city":"Feldkirchen in K\u00e4rnten",
    "sg:orig_category":"Lebensmittel / Einzelhandel",
    "sg:phone":"+43 4342 763253",
    "sg:postcode":"9560",
    "sg:province":"K\u00e4rnten",
    "wof:name":"Billa AG",
    "wof:placetype":"venue"
},
  "geometry": {"coordinates":[14.1003513336,46.7221488953],"type":"Point"}
}