{
  "type": "Feature",
  "properties": {
    "addr:full":"Rankeng 11 Graz Steiermark 8020",
    "addr:housenumber":"11",
    "addr:postcode":"8020",
    "addr:street":"Rankeng",
    "iso:country":"AT",
    "sg:address":"Rankeng 11",
    "sg:city":"Graz",
    "sg:orig_category":"Teppichreinigung U -Reparatur",
    "sg:phone":"+43 316 715350",
    "sg:postcode":"8020",
    "sg:province":"Steiermark",
    "wof:name":"Herzl Ernst",
    "wof:placetype":"venue"
},
  "geometry": {"coordinates":[15.4319992065,47.0626831055],"type":"Point"}
}