{
  "type": "Feature",
  "properties": {
    "addr:full":"Hetzendorfer Str 100 Wien Wien 1120",
    "addr:housenumber":"100",
    "addr:postcode":"1120",
    "addr:street":"Str",
    "iso:country":"AT",
    "sg:address":"Hetzendorfer Str 100",
    "sg:city":"Wien",
    "sg:orig_category":"Friseure U Frisiersalons",
    "sg:phone":"+43 1 8043473",
    "sg:postcode":"1120",
    "sg:province":"Wien",
    "wof:name":"Trend Hair",
    "wof:placetype":"venue"
},
  "geometry": {"coordinates":[16.3069095612,48.1676483154],"type":"Point"}
}