{
  "type": "Feature",
  "properties": {
    "addr:full":"Kircheng 64 M\u00fcllendorf Burgenland 7052",
    "addr:housenumber":"64",
    "addr:postcode":"7052",
    "addr:street":"Kircheng",
    "iso:country":"AT",
    "sg:address":"Kircheng 64",
    "sg:city":"M\u00fcllendorf",
    "sg:classifiers":[
        {
            "category":"Internet Cafe",
            "subcategory":"None",
            "type":"Food & Drink"
        }
    ],
    "sg:phone":"+43 4326 8268469",
    "sg:postcode":"7052",
    "sg:province":"Burgenland",
    "wof:name":"POWERSystems",
    "wof:placetype":"venue"
},
  "geometry": {"coordinates":[16.4556045532,47.841960907],"type":"Point"}
}