{
  "type": "Feature",
  "properties": {
    "iso:country":"AT",
    "sg:address":"Salzburger Str 26-30",
    "sg:city":"Bad Hofgastein",
    "sg:classifiers":[
        {
            "category":"Health Services",
            "subcategory":"Nursing And Care Facility",
            "type":"Services"
        }
    ],
    "sg:phone":"+43 4364 3266850",
    "sg:postcode":"5630",
    "sg:province":"Salzburg",
    "sg:tags":[
        "rehabilitation"
    ],
    "wof:name":"Pensionsversicherungsanstalt - Sonderkrankenanstalt RZ Bad Hofgastein",
    "wof:placetype":"venue"
},
  "geometry": {"coordinates":[13.1044178009,47.1748046875],"type":"Point"}
}