{
  "type": "Feature",
  "properties": {
    "addr:full":"Gallzein 52a Jenbach Tirol 6200",
    "addr:housenumber":"52a",
    "addr:postcode":"6200",
    "addr:street":"Gallzein;Tirol",
    "iso:country":"AT",
    "sg:address":"Gallzein 52a",
    "sg:city":"Jenbach",
    "sg:classifiers":[
        {
            "category":"Manufacturing",
            "subcategory":"Wood Products",
            "type":"Manufacturing & Wholesale Goods"
        }
    ],
    "sg:phone":"+43 5244 66400",
    "sg:postcode":"6200",
    "sg:province":"Tirol",
    "sg:tags":[
        "solid",
        "ceiling",
        "made",
        "panel"
    ],
    "wof:name":"Josef Brunner",
    "wof:placetype":"venue"
},
  "geometry": {"coordinates":[11.7700395584,47.3680801392],"type":"Point"}
}