{
  "type": "Feature",
  "properties": {
    "addr:full":"Flugfeldstr 100 Strasshof an der Nordbahn Nieder\u00f6sterreich 2231",
    "addr:housenumber":"100",
    "addr:postcode":"2231",
    "addr:street":"Strasshof",
    "iso:country":"AT",
    "sg:address":"Flugfeldstr 100",
    "sg:city":"Strasshof an der Nordbahn",
    "sg:orig_category":"Werbegestalter",
    "sg:phone":"+43 4366 41224062",
    "sg:postcode":"2231",
    "sg:province":"Nieder\u00f6sterreich",
    "wof:name":"ACKI Acker & Kitlitschko OEG - Kreative Schauwerbegestaltung",
    "wof:placetype":"venue"
},
  "geometry": {"coordinates":[16.6664905548,48.3142814636],"type":"Point"}
}