{
  "type": "Feature",
  "properties": {
    "addr:full":"D\u00f6blinger Hauptstr 54 Wien Wien 1190",
    "addr:housenumber":"54",
    "addr:postcode":"1190",
    "addr:street":"Hauptstr",
    "iso:country":"AT",
    "sg:address":"D\u00f6blinger Hauptstr 54",
    "sg:city":"Wien",
    "sg:orig_category":"Lebensmittel / Einzelhandel",
    "sg:phone":"+43 4313 6846820",
    "sg:postcode":"1190",
    "sg:province":"Wien",
    "wof:name":"Konsum \u00f6sterreich regGenmbH",
    "wof:placetype":"venue"
},
  "geometry": {"coordinates":[16.3542613983,48.2375984192],"type":"Point"}
}