{
  "type": "Feature",
  "properties": {
    "addr:full":"Mattseer Landesstr 12 Elixhausen Salzburg 5161",
    "addr:housenumber":"12",
    "addr:postcode":"5161",
    "addr:street":"Salzburg",
    "iso:country":"AT",
    "sg:address":"Mattseer Landesstr 12",
    "sg:city":"Elixhausen",
    "sg:orig_category":"Bibliotheken",
    "sg:phone":"+43 662 480015",
    "sg:postcode":"5161",
    "sg:province":"Salzburg",
    "wof:name":"Bibliothek Elixhausen",
    "wof:placetype":"venue"
},
  "geometry": {"coordinates":[13.0648870468,47.866065979],"type":"Point"}
}