{
  "type": "Feature",
  "properties": {
    "addr:full":"Ortsplatz 5  Traunkirchen Ober\u00f6sterreich 4801",
    "addr:housenumber":"5",
    "addr:postcode":"4801",
    "addr:street":"Ortsplatz",
    "iso:country":"AT",
    "sg:address":"Ortsplatz 5 ",
    "sg:city":"Traunkirchen",
    "sg:classifiers":[
        {
            "category":"Travel",
            "subcategory":"Travel Agent",
            "type":"Entertainment"
        }
    ],
    "sg:phone":"+43 4376 172307",
    "sg:postcode":"4801",
    "sg:province":"Ober\u00f6sterreich",
    "sg:tags":[
        "business"
    ],
    "wof:name":"HEINRICH GR\u00d6LLER KG",
    "wof:placetype":"venue"
},
  "geometry": {"coordinates":[13.7899923325,47.8449478149],"type":"Point"}
}