{
  "type": "Feature",
  "properties": {
    "iso:country":"AT",
    "sg:address":"Wiener Str 23",
    "sg:city":"G\u00fcssing",
    "sg:orig_category":"Tischlereien",
    "sg:phone":"+43 3322 427090",
    "sg:postcode":"7540",
    "sg:province":"Burgenland",
    "wof:name":"Tischlerei Pannonia",
    "wof:placetype":"venue"
},
  "geometry": {"coordinates":[16.3208389282,47.0722427368],"type":"Point"}
}