{
  "type": "Feature",
  "properties": {
    "iso:country":"AT",
    "sg:address":"Dorf 87",
    "sg:city":"Flie\u00df",
    "sg:orig_category":"Gemeinden",
    "sg:phone":"+43 5449 5234",
    "sg:postcode":"6521",
    "sg:province":"Tirol",
    "wof:name":"Gemeindeamt Flie\u00df",
    "wof:placetype":"venue"
},
  "geometry": {"coordinates":[10.6277103424,47.1199989319],"type":"Point"}
}