{
  "type": "Feature",
  "properties": {
    "addr:full":"Wasendorfer Weg 7 Judenburg Steiermark 8750",
    "addr:housenumber":"7",
    "addr:postcode":"8750",
    "addr:street":"Wasendorfer Weg",
    "iso:country":"AT",
    "sg:address":"Wasendorfer Weg 7",
    "sg:city":"Judenburg",
    "sg:orig_category":"Stuckateure U Trockenausbauer",
    "sg:phone":"+43 4335 728271211",
    "sg:postcode":"8750",
    "sg:province":"Steiermark",
    "wof:name":"TSD Wallner GesmbH",
    "wof:placetype":"venue"
},
  "geometry": {"coordinates":[14.6650381088,47.1773643494],"type":"Point"}
}