{
  "type": "Feature",
  "properties": {
    "addr:full":"An der Au 1 Sch\u00f6nwies Tirol 6491",
    "addr:housenumber":"1",
    "addr:postcode":"6491",
    "addr:street":"An Der Au;Tirol",
    "iso:country":"AT",
    "sg:address":"An der Au 1",
    "sg:city":"Sch\u00f6nwies",
    "sg:classifiers":[
        {
            "category":"Restaurant",
            "type":"Food & Drink"
        }
    ],
    "sg:phone":"+43 5418 6010",
    "sg:postcode":"6491",
    "sg:province":"Tirol",
    "wof:name":"Trofana Tyrol",
    "wof:placetype":"venue"
},
  "geometry": {"coordinates":[10.6977949142,47.2136459351],"type":"Point"}
}