{
  "type": "Feature",
  "properties": {
    "iso:country":"AT",
    "sg:address":"Bachofengasse 9",
    "sg:city":"Wien",
    "sg:classifiers":[
        {
            "category":"Home & Garden",
            "subcategory":"Furniture",
            "type":"Retail Goods"
        }
    ],
    "sg:phone":"+43 1 3704960",
    "sg:postcode":"1190",
    "sg:province":"Wien",
    "sg:tags":[
        "bathroom"
    ],
    "wof:name":"Hans Fellner",
    "wof:placetype":"venue"
},
  "geometry": {"coordinates":[16.3684997559,48.2570343018],"type":"Point"}
}