{
  "type": "Feature",
  "properties": {
    "addr:full":"Nr 4 Langenlois Nieder\u00f6sterreich 3550",
    "addr:postcode":"3550",
    "addr:street":"Nr;Niederoesterreich",
    "iso:country":"AT",
    "sg:address":"Nr 4",
    "sg:city":"Langenlois",
    "sg:orig_category":"Wasserschadensanierung",
    "sg:phone":"+43 2734 70090",
    "sg:postcode":"3550",
    "sg:province":"Nieder\u00f6sterreich",
    "wof:name":"entfeuchter.at.gmbh",
    "wof:placetype":"venue"
},
  "geometry": {"coordinates":[15.67689991,48.4733161926],"type":"Point"}
}