{
  "type": "Feature",
  "properties": {
    "addr:full":"Murbang. 4 Wien Wien 1100",
    "addr:housenumber":"4",
    "addr:postcode":"1100",
    "addr:street":"Murbang.",
    "iso:country":"AT",
    "sg:address":"Murbang. 4",
    "sg:city":"Wien",
    "sg:classifiers":[
        {
            "category":"Professional",
            "subcategory":"Engineering",
            "type":"Services"
        }
    ],
    "sg:phone":"+43 4316 80070",
    "sg:postcode":"1100",
    "sg:province":"Wien",
    "sg:tags":[
        "machine",
        "-",
        "mechanical"
    ],
    "wof:name":"HEINISCH GMBH",
    "wof:placetype":"venue"
},
  "geometry": {"coordinates":[16.3788013458,48.1460037231],"type":"Point"}
}