{
  "type": "Feature",
  "properties": {
    "iso:country":"AT",
    "sg:address":"Hinterwinkl 205",
    "sg:city":"Filzmoos",
    "sg:orig_category":"Spenglereien",
    "sg:phone":"+43 4364 538445",
    "sg:postcode":"5532",
    "sg:province":"Salzburg",
    "wof:name":"Hofer Florian",
    "wof:placetype":"venue"
},
  "geometry": {"coordinates":[13.5202980042,47.4332199097],"type":"Point"}
}