{
  "type": "Feature",
  "properties": {
    "addr:full":"Langefelder Str 28 Trofaiach Steiermark 8793",
    "addr:postcode":"8793",
    "addr:street":"Str 28",
    "iso:country":"AT",
    "sg:address":"Langefelder Str 28",
    "sg:city":"Trofaiach",
    "sg:orig_category":"Maler, Anstreicher U Lackierer",
    "sg:phone":"+43 4338 473526",
    "sg:postcode":"8793",
    "sg:province":"Steiermark",
    "wof:name":"Sochor Roland",
    "wof:placetype":"venue"
},
  "geometry": {"coordinates":[14.9932689667,47.4250183105],"type":"Point"}
}