{
  "type": "Feature",
  "properties": {
    "iso:country":"AT",
    "sg:address":"Paschinger Strasse 1",
    "sg:city":"Marchtrenk",
    "sg:classifiers":[
        {
            "category":"Bars & Pubs",
            "subcategory":"Champagne Bar",
            "type":"Food & Drink"
        }
    ],
    "sg:phone":"+43 7243 572830",
    "sg:postcode":"4614",
    "sg:province":"Ober\u00f6sterreich",
    "sg:tags":[
        "stool"
    ],
    "sg:website":"sitz-art.at",
    "wof:name":"SITZ-ART sitzm\u00f6bel mit design",
    "wof:placetype":"venue"
},
  "geometry": {"coordinates":[14.1020803452,48.202671051],"type":"Point"}
}