{
  "type": "Feature",
  "properties": {
    "addr:full":"Trauner Str 100 Traun Ober\u00f6sterreich 4050",
    "addr:housenumber":"100",
    "addr:postcode":"4050",
    "addr:street":"Traun Oberoesterreich",
    "iso:country":"AT",
    "sg:address":"Trauner Str 100",
    "sg:city":"Traun",
    "sg:orig_category":"Massagen",
    "sg:phone":"+43 4366 41606465",
    "sg:postcode":"4050",
    "sg:province":"Ober\u00f6sterreich",
    "wof:name":"Massagefachinstitut Aufreiter",
    "wof:placetype":"venue"
},
  "geometry": {"coordinates":[14.2123880386,48.2160148621],"type":"Point"}
}