{
  "type": "Feature",
  "properties": {
    "iso:country":"AT",
    "sg:address":"Industriegel\u00e4nde 123",
    "sg:city":"Melk",
    "sg:orig_category":"Floodlight Masts",
    "sg:phone":"+43 2752 527230",
    "sg:postcode":"3390",
    "sg:province":"Nieder\u00f6sterreich",
    "sg:website":"fonatsch.at",
    "wof:name":"Fonatsch GmbH",
    "wof:placetype":"venue"
},
  "geometry": {"coordinates":[15.3291749954,48.2272262573],"type":"Point"}
}