{
  "type": "Feature",
  "properties": {
    "iso:country":"AT",
    "sg:address":"Schwamingstrasse 3",
    "sg:city":"Neuzeug",
    "sg:classifiers":[
        {
            "category":"Home & Garden",
            "subcategory":"Building Materials",
            "type":"Retail Goods"
        }
    ],
    "sg:phone":"+43 7259 4242",
    "sg:postcode":"4523",
    "sg:province":"Ober\u00f6sterreich",
    "sg:tags":[
        "steel",
        "balcony"
    ],
    "wof:name":"3s Metallbau u. Lohnfertigung GmbH",
    "wof:placetype":"venue"
},
  "geometry": {"coordinates":[14.3221750259,48.0261383057],"type":"Point"}
}