{
  "type": "Feature",
  "properties": {
    "addr:full":"Anzengruberstr 8 Traun Ober\u00f6sterreich 4050",
    "addr:housenumber":"8",
    "addr:postcode":"4050",
    "addr:street":"Anzengruberstr",
    "iso:country":"AT",
    "sg:address":"Anzengruberstr 8",
    "sg:city":"Traun",
    "sg:orig_category":"Tanzcafes",
    "sg:phone":"+43 7229 71201",
    "sg:postcode":"4050",
    "sg:province":"Ober\u00f6sterreich",
    "wof:name":"Maybelline Oldie",
    "wof:placetype":"venue"
},
  "geometry": {"coordinates":[14.2586660385,48.2436294556],"type":"Point"}
}