{
  "type": "Feature",
  "properties": {
    "addr:full":"Schumanng 13 Wien Wien 1180",
    "addr:housenumber":"13",
    "addr:postcode":"1180",
    "addr:street":"Schumanng",
    "iso:country":"AT",
    "sg:address":"Schumanng 13",
    "sg:city":"Wien",
    "sg:orig_category":"Installationsunternehmen",
    "sg:phone":"+43 1 40523870",
    "sg:postcode":"1180",
    "sg:province":"Wien",
    "wof:name":"Leitner M KG",
    "wof:placetype":"venue"
},
  "geometry": {"coordinates":[16.34075737,48.2202949524],"type":"Point"}
}