{
  "type": "Feature",
  "properties": {
    "addr:full":"Grazerstrasse 168 Bad Gleichenberg Steiermark 8344",
    "addr:housenumber":"168",
    "addr:postcode":"8344",
    "addr:street":"Grazerstrasse",
    "iso:country":"AT",
    "sg:address":"Grazerstrasse 168",
    "sg:city":"Bad Gleichenberg",
    "sg:classifiers":[
        {
            "category":"Home & Garden",
            "subcategory":"Furniture",
            "type":"Retail Goods"
        }
    ],
    "sg:phone":"+43 3159 2530",
    "sg:postcode":"8344",
    "sg:province":"Steiermark",
    "sg:tags":[
        "bathroom"
    ],
    "sg:website":"ulrich-wohnen.at",
    "wof:name":"Anton Ulrich",
    "wof:placetype":"venue"
},
  "geometry": {"coordinates":[15.8957300186,46.8837356567],"type":"Point"}
}