{
  "type": "Feature",
  "properties": {
    "iso:country":"AT",
    "sg:address":"Wiener Str 4/9",
    "sg:city":"Neunkirchen",
    "sg:orig_category":"Lebens- U Sozialberatung",
    "sg:phone":"+43 4326 3561125",
    "sg:postcode":"2620",
    "sg:province":"Nieder\u00f6sterreich",
    "wof:name":"Frauenberatungsstelle Freiraum",
    "wof:placetype":"venue"
},
  "geometry": {"coordinates":[16.0810184479,47.7215805054],"type":"Point"}
}