{
  "type": "Feature",
  "properties": {
    "iso:country":"AT",
    "sg:address":"Nr 242",
    "sg:city":"Eibiswald",
    "sg:orig_category":"Pensionen / Privatzimmer",
    "sg:phone":"+43 676 4293232",
    "sg:postcode":"8552",
    "sg:province":"Steiermark",
    "wof:name":"Orlitsch Gerald",
    "wof:placetype":"venue"
},
  "geometry": {"coordinates":[15.2274599075,46.6824150085],"type":"Point"}
}