{
  "type": "Feature",
  "properties": {
    "addr:full":"Josef-Dunkl-Strasse 19 Mistelbach Nieder\u00f6sterreich 2130",
    "addr:housenumber":"19",
    "addr:postcode":"2130",
    "addr:street":"Josef-Dunkl-Strasse;Niederoesterreich",
    "iso:country":"AT",
    "sg:address":"Josef-Dunkl-Strasse 19",
    "sg:city":"Mistelbach",
    "sg:orig_category":"CarpenterS Work Supraregional",
    "sg:phone":"+43 2572 2786",
    "sg:postcode":"2130",
    "sg:province":"Nieder\u00f6sterreich",
    "sg:website":"holz-tretter.at",
    "wof:name":"Heinrich Tretter S\u00e4gewerk",
    "wof:placetype":"venue"
},
  "geometry": {"coordinates":[16.5704307556,48.5687217712],"type":"Point"}
}