{
  "type": "Feature",
  "properties": {
    "addr:full":"Kolonitzgasse 6 Wien Wien 1030",
    "addr:housenumber":"6",
    "addr:postcode":"1030",
    "addr:street":"Kolonitzgasse",
    "iso:country":"AT",
    "sg:address":"Kolonitzgasse 6",
    "sg:city":"Wien",
    "sg:classifiers":[
        {
            "category":"Home & Garden",
            "subcategory":"Carpets & Floor Coverings",
            "type":"Retail Goods"
        }
    ],
    "sg:phone":"+43 1 7125395",
    "sg:postcode":"1030",
    "sg:province":"Wien",
    "sg:tags":[
        "restoration"
    ],
    "wof:name":"Helmut Renner Ges.m.b.H.",
    "wof:placetype":"venue"
},
  "geometry": {"coordinates":[16.3886814117,48.210193634],"type":"Point"}
}