{
  "type": "Feature",
  "properties": {
    "addr:full":"Bichlstr 7 Kitzb\u00fchel Tirol 6370",
    "addr:housenumber":"7",
    "addr:postcode":"6370",
    "addr:street":"Bichlstr;Tirol",
    "iso:country":"AT",
    "sg:address":"Bichlstr 7",
    "sg:city":"Kitzb\u00fchel",
    "sg:orig_category":"Friseure U Frisiersalons",
    "sg:phone":"+43 4353 5671538",
    "sg:postcode":"6370",
    "sg:province":"Tirol",
    "wof:name":"Salon Haargenau",
    "wof:placetype":"venue"
},
  "geometry": {"coordinates":[12.3926877975,47.4450340271],"type":"Point"}
}