{
  "type": "Feature",
  "properties": {
    "addr:full":"Rathauspl 2 Liezen Steiermark 8940",
    "addr:housenumber":"2",
    "addr:postcode":"8940",
    "addr:street":"Rathauspl",
    "iso:country":"AT",
    "sg:address":"Rathauspl 2",
    "sg:city":"Liezen",
    "sg:orig_category":"Friseure U Frisiersalons",
    "sg:phone":"+43 3612 22666",
    "sg:postcode":"8940",
    "sg:province":"Steiermark",
    "wof:name":"Modefriseur Knotzer",
    "wof:placetype":"venue"
},
  "geometry": {"coordinates":[14.2420969009,47.5679473877],"type":"Point"}
}