{
  "type": "Feature",
  "properties": {
    "iso:country":"AT",
    "sg:address":"Rutesheimer Str 3",
    "sg:city":"Scheibbs",
    "sg:orig_category":"Rettungsdienste",
    "sg:phone":"+43 7482 422440",
    "sg:postcode":"3270",
    "sg:province":"Nieder\u00f6sterreich",
    "wof:name":"Rotes Kreuz \u00f6sterr Bezirksstelle Scheibbs",
    "wof:placetype":"venue"
},
  "geometry": {"coordinates":[15.1610822678,48.0090751648],"type":"Point"}
}