{
  "type": "Feature",
  "properties": {
    "iso:country":"AT",
    "sg:address":"Penzinger Str 63",
    "sg:city":"Wien",
    "sg:orig_category":"Institute",
    "sg:phone":"+43 1 8946530",
    "sg:postcode":"1140",
    "sg:province":"Wien",
    "wof:name":"Institut f duale Biosignalmodulation",
    "wof:placetype":"venue"
},
  "geometry": {"coordinates":[16.3038482666,48.189540863],"type":"Point"}
}