{
  "type": "Feature",
  "properties": {
    "iso:country":"AT",
    "sg:address":"Nr 33",
    "sg:city":"Warth",
    "sg:orig_category":"Bankomat-Standorte",
    "sg:phone":"+43 5583 3501",
    "sg:postcode":"6767",
    "sg:province":"Vorarlberg",
    "wof:name":"Bankomat d Raiffeisenbank Lech/Arlberg",
    "wof:placetype":"venue"
},
  "geometry": {"coordinates":[10.1830291748,47.2582550049],"type":"Point"}
}