{
  "type": "Feature",
  "properties": {
    "addr:full":"Stubenring 6/8 Wien Wien 1010",
    "addr:housenumber":"6 / 8",
    "addr:postcode":"1010",
    "addr:street":"Stubenring",
    "iso:country":"AT",
    "sg:address":"Stubenring 6/8",
    "sg:city":"Wien",
    "sg:orig_category":"Steuerberatung",
    "sg:phone":"+43 1 51286700",
    "sg:postcode":"1010",
    "sg:province":"Wien",
    "wof:name":"Contenda WirtschaftstreuhandgesmbH",
    "wof:placetype":"venue"
},
  "geometry": {"coordinates":[16.3822021484,48.2102394104],"type":"Point"}
}