{
  "type": "Feature",
  "properties": {
    "addr:full":"Bubenland 8 Desselbrunn Ober\u00f6sterreich 4693",
    "addr:housenumber":"8",
    "addr:postcode":"4693",
    "addr:street":"Bubenland",
    "iso:country":"AT",
    "sg:address":"Bubenland 8",
    "sg:city":"Desselbrunn",
    "sg:orig_category":"Handelsagenturen",
    "sg:phone":"+43 4376 733817",
    "sg:postcode":"4693",
    "sg:province":"Ober\u00f6sterreich",
    "wof:name":"Parzer Erwin u Karin",
    "wof:placetype":"venue"
},
  "geometry": {"coordinates":[13.7849645615,48.0151863098],"type":"Point"}
}