{
  "type": "Feature",
  "properties": {
    "addr:full":"Kleingasse 6-18 Wien Wien 1030",
    "addr:housenumber":"6-18",
    "addr:postcode":"1030",
    "addr:street":"Kleingasse",
    "iso:country":"AT",
    "sg:address":"Kleingasse 6-18",
    "sg:city":"Wien",
    "sg:classifiers":[
        {
            "category":"Manufacturing",
            "subcategory":"Signs",
            "type":"Manufacturing & Wholesale Goods"
        }
    ],
    "sg:phone":"+43 1 7139242",
    "sg:postcode":"1030",
    "sg:province":"Wien",
    "sg:tags":[
        "display"
    ],
    "sg:website":"designwerkstatt.at",
    "wof:name":"Designwerkstatt Becker & Oreschnik",
    "wof:placetype":"venue"
},
  "geometry": {"coordinates":[16.4051742554,48.1946258545],"type":"Point"}
}