{
  "type": "Feature",
  "properties": {
    "iso:country":"AT",
    "sg:address":"Marktg 22",
    "sg:city":"Knittelfeld",
    "sg:orig_category":"Gerichte",
    "sg:phone":"+43 3512 866170",
    "sg:postcode":"8720",
    "sg:province":"Steiermark",
    "wof:name":"Bezirksgericht Knittelfeld",
    "wof:placetype":"venue"
},
  "geometry": {"coordinates":[14.8291902542,47.2139434814],"type":"Point"}
}