{
  "type": "Feature",
  "properties": {
    "iso:country":"AT",
    "sg:address":"Pfarrg 22",
    "sg:city":"Freistadt",
    "sg:orig_category":"Bars-Cafes",
    "sg:phone":"+43 7942 77897",
    "sg:postcode":"4240",
    "sg:province":"Ober\u00f6sterreich",
    "wof:name":"Cafe-Bar Gw\u00f6lb",
    "wof:placetype":"venue"
},
  "geometry": {"coordinates":[14.5025558472,48.51121521],"type":"Point"}
}