{
  "type": "Feature",
  "properties": {
    "addr:full":"Hafnerstr 26 Villach K\u00e4rnten 9500",
    "addr:housenumber":"26",
    "addr:postcode":"9500",
    "addr:street":"Hafnerstr;Kaernten",
    "iso:country":"AT",
    "sg:address":"Hafnerstr 26",
    "sg:city":"Villach",
    "sg:orig_category":"Bekleidung / Erzeugung U Gro\u00c3\u0178handel",
    "sg:phone":"+43 664 1075316",
    "sg:postcode":"9500",
    "sg:province":"K\u00e4rnten",
    "wof:name":"Koller Martin",
    "wof:placetype":"venue"
},
  "geometry": {"coordinates":[13.8201007843,46.627696991],"type":"Point"}
}