{
  "type": "Feature",
  "properties": {
    "iso:country":"AT",
    "sg:address":"Haslingerg 9/21",
    "sg:city":"Wien",
    "sg:classifiers":[
        {
            "category":"Organizations",
            "subcategory":"Community Association",
            "type":"Services"
        }
    ],
    "sg:phone":"+43 4367 63003222",
    "sg:postcode":"1170",
    "sg:province":"Wien",
    "sg:tags":[
        "relation",
        "public"
    ],
    "wof:name":"Aicher Alexander",
    "wof:placetype":"venue"
},
  "geometry": {"coordinates":[16.331035614,48.21484375],"type":"Point"}
}