{
  "type": "Feature",
  "properties": {
    "addr:full":"Am Reitweg 55 Wiener Neustadt Nieder\u00f6sterreich 2700",
    "addr:housenumber":"55",
    "addr:postcode":"2700",
    "addr:street":"Am Reitweg",
    "iso:country":"AT",
    "sg:address":"Am Reitweg 55",
    "sg:city":"Wiener Neustadt",
    "sg:orig_category":"Autohandel",
    "sg:phone":"+43 2622 21883",
    "sg:postcode":"2700",
    "sg:province":"Nieder\u00f6sterreich",
    "wof:name":"Autohaus Hahn",
    "wof:placetype":"venue"
},
  "geometry": {"coordinates":[16.2207660675,47.8196182251],"type":"Point"}
}