{
  "type": "Feature",
  "properties": {
    "addr:full":"Marktg 5 Wiener Neustadt Nieder\u00f6sterreich 2700",
    "addr:housenumber":"5",
    "addr:postcode":"2700",
    "addr:street":"Marktg",
    "iso:country":"AT",
    "sg:address":"Marktg 5",
    "sg:city":"Wiener Neustadt",
    "sg:classifiers":[
        {
            "category":"Restaurant",
            "type":"Food & Drink"
        }
    ],
    "sg:phone":"+43 2622 69828",
    "sg:postcode":"2700",
    "sg:province":"Nieder\u00f6sterreich",
    "wof:name":"Steak's Bar & Restaurant GmbH",
    "wof:placetype":"venue"
},
  "geometry": {"coordinates":[16.2455158234,47.8128814697],"type":"Point"}
}