{
  "type": "Feature",
  "properties": {
    "addr:full":"Kircheng 4 Lackendorf Burgenland 7321",
    "addr:housenumber":"4",
    "addr:postcode":"7321",
    "addr:street":"Kircheng",
    "iso:country":"AT",
    "sg:address":"Kircheng 4",
    "sg:city":"Lackendorf",
    "sg:orig_category":"Non-Classified Establishments",
    "sg:phone":"+43 2619 7461",
    "sg:postcode":"7321",
    "sg:province":"Burgenland",
    "wof:name":"Pfarramt",
    "wof:placetype":"venue"
},
  "geometry": {"coordinates":[16.528263092,47.567855835],"type":"Point"}
}