{
  "type": "Feature",
  "properties": {
    "addr:full":"Ernest-Thum-Str 5 Gf\u00f6hl Nieder\u00f6sterreich 3542",
    "addr:housenumber":"5",
    "addr:postcode":"3542",
    "addr:street":"Ernest-Thum-Str;Niederoesterreich",
    "iso:country":"AT",
    "sg:address":"Ernest-Thum-Str 5",
    "sg:city":"Gf\u00f6hl",
    "sg:orig_category":"Textilwaren / Einzelhandel",
    "sg:phone":"+43 2716 6348",
    "sg:postcode":"3542",
    "sg:province":"Nieder\u00f6sterreich",
    "wof:name":"Textil-Ledershop Leutgeb",
    "wof:placetype":"venue"
},
  "geometry": {"coordinates":[-71.7024688721,43.5195732117],"type":"Point"}
}