{
  "type": "Feature",
  "properties": {
    "iso:country":"AT",
    "sg:address":"Seestr 12",
    "sg:city":"St. Andr\u00e4 am Zicksee",
    "sg:orig_category":"Fassbindereien",
    "sg:phone":"+43 4321 7623270",
    "sg:postcode":"7161",
    "sg:province":"Burgenland",
    "wof:name":"Roll Karl Fassbinderei u Edelstahltankerzeugung",
    "wof:placetype":"venue"
},
  "geometry": {"coordinates":[16.9260616302,47.7845115662],"type":"Point"}
}