{
  "type": "Feature",
  "properties": {
    "iso:country":"AT",
    "sg:address":"Liechtensteiner Str 45",
    "sg:city":"Feldkirch",
    "sg:orig_category":"Architekten",
    "sg:phone":"+43 4355 2272101",
    "sg:postcode":"6800",
    "sg:province":"Vorarlberg",
    "wof:name":"atelier rainer + amann Architekturb\u00fcro ZT-GmbH",
    "wof:placetype":"venue"
},
  "geometry": {"coordinates":[9.5868196487,47.230796814],"type":"Point"}
}