{
  "type": "Feature",
  "properties": {
    "iso:country":"AT",
    "sg:address":"Obere Augartenstr 38",
    "sg:city":"Wien",
    "sg:orig_category":"Hauptschulen",
    "sg:phone":"+43 1 2165990",
    "sg:postcode":"1020",
    "sg:province":"Wien",
    "wof:name":"Schulen d Stadt Wien",
    "wof:placetype":"venue"
},
  "geometry": {"coordinates":[16.3761959076,48.2217330933],"type":"Point"}
}