{
  "type": "Feature",
  "properties": {
    "addr:full":"Floriang 19 Imst Tirol 6460",
    "addr:housenumber":"19",
    "addr:postcode":"6460",
    "addr:street":"Floriang;Tirol",
    "iso:country":"AT",
    "sg:address":"Floriang 19",
    "sg:city":"Imst",
    "sg:orig_category":"Filmverleih U -Vertrieb",
    "sg:phone":"+43 5412 63908",
    "sg:postcode":"6460",
    "sg:province":"Tirol",
    "wof:name":"Medienzentrum Bezirk Imst",
    "wof:placetype":"venue"
},
  "geometry": {"coordinates":[10.7422523499,47.2395133972],"type":"Point"}
}