{
  "type": "Feature",
  "properties": {
    "iso:country":"AT",
    "sg:address":"Matzner Str 35",
    "sg:city":"Spannberg",
    "sg:orig_category":"Zimmereien",
    "sg:phone":"+43 2538 85388",
    "sg:postcode":"2244",
    "sg:province":"Nieder\u00f6sterreich",
    "wof:name":"Stur Robert Holzbau",
    "wof:placetype":"venue"
},
  "geometry": {"coordinates":[16.7307472229,48.4610710144],"type":"Point"}
}