{
  "type": "Feature",
  "properties": {
    "addr:full":"B\u00f6dmer Str 88 Mittelberg Vorarlberg 6993",
    "addr:housenumber":"88",
    "addr:postcode":"6993",
    "addr:street":"Str",
    "iso:country":"AT",
    "sg:address":"B\u00f6dmer Str 88",
    "sg:city":"Mittelberg",
    "sg:orig_category":"Pensionen / Privatzimmer",
    "sg:phone":"+43 4355 175871",
    "sg:postcode":"6993",
    "sg:province":"Vorarlberg",
    "wof:name":"Grauer Andreas",
    "wof:placetype":"venue"
},
  "geometry": {"coordinates":[10.1548366547,47.3239440918],"type":"Point"}
}