{
  "type": "Feature",
  "properties": {
    "addr:full":"Paracelsusstr 11a Salzburg Salzburg 5020",
    "addr:housenumber":"11a",
    "addr:postcode":"5020",
    "addr:street":"Paracelsusstr;Salzburg",
    "iso:country":"AT",
    "sg:address":"Paracelsusstr 11a",
    "sg:city":"Salzburg",
    "sg:orig_category":"Finanz- U Wirtschaftsberatung",
    "sg:phone":"+43 662 875272",
    "sg:postcode":"5020",
    "sg:province":"Salzburg",
    "wof:name":"Agenta Service GmbH",
    "wof:placetype":"venue"
},
  "geometry": {"coordinates":[13.047627449,47.8087425232],"type":"Point"}
}