{
  "type": "Feature",
  "properties": {
    "addr:full":"Siebensterng 19/1 Wien Wien 1070",
    "addr:housenumber":"19 / 1",
    "addr:postcode":"1070",
    "addr:street":"Siebensterng",
    "iso:country":"AT",
    "sg:address":"Siebensterng 19/1",
    "sg:city":"Wien",
    "sg:orig_category":"Tonstudios",
    "sg:phone":"+43 1 5973200",
    "sg:postcode":"1070",
    "sg:province":"Wien",
    "wof:name":"Klein Records",
    "wof:placetype":"venue"
},
  "geometry": {"coordinates":[16.3534736633,48.2021446228],"type":"Point"}
}