{
  "type": "Feature",
  "properties": {
    "iso:country":"AT",
    "sg:address":"Graben 26",
    "sg:city":"Wien",
    "sg:orig_category":"Bettwaren",
    "sg:phone":"+43 1 5355356",
    "sg:postcode":"1010",
    "sg:province":"Wien",
    "sg:website":"schwaebische-jungfrau.at",
    "wof:name":"Zur Schw\u00e4bischen Jungfrau",
    "wof:placetype":"venue"
},
  "geometry": {"coordinates":[16.3694458008,48.2089691162],"type":"Point"}
}