{
  "type": "Feature",
  "properties": {
    "addr:full":"Sandg 1 W\u00fcrnitz Nieder\u00f6sterreich 2112",
    "addr:housenumber":"1",
    "addr:postcode":"2112",
    "addr:street":"Sandg;Niederoesterreich",
    "iso:country":"AT",
    "sg:address":"Sandg 1",
    "sg:city":"W\u00fcrnitz",
    "sg:orig_category":"Maschinenhandel",
    "sg:phone":"+43 2263 2595",
    "sg:postcode":"2112",
    "sg:province":"Nieder\u00f6sterreich",
    "wof:name":"Berthold Franz Ing",
    "wof:placetype":"venue"
},
  "geometry": {"coordinates":[16.3974533081,48.4415969849],"type":"Point"}
}