{
  "type": "Feature",
  "properties": {
    "iso:country":"AT",
    "sg:address":"Urberweg 13",
    "sg:city":"Klosterneuburg",
    "sg:orig_category":"\u00c3\u201erzte / F Allgemeinmedizin",
    "sg:phone":"+43 2243 36724",
    "sg:postcode":"3400",
    "sg:province":"Nieder\u00f6sterreich",
    "wof:name":"Auner Christoph Dr",
    "wof:placetype":"venue"
},
  "geometry": {"coordinates":[16.3080921173,48.311882019],"type":"Point"}
}