{
  "type": "Feature",
  "properties": {
    "iso:country":"AT",
    "sg:address":"Bahnhofstr 105",
    "sg:city":"Attnang-Puchheim",
    "sg:orig_category":"Maschinenbau",
    "sg:phone":"+43 4376 74626610",
    "sg:postcode":"4800",
    "sg:province":"Ober\u00f6sterreich",
    "wof:name":"Berger F & C Regent Pflugfabrik",
    "wof:placetype":"venue"
},
  "geometry": {"coordinates":[13.7182197571,48.0091018677],"type":"Point"}
}