{
  "type": "Feature",
  "properties": {
    "addr:full":"Dorf 21 Erl Tirol 6343",
    "addr:housenumber":"21",
    "addr:postcode":"6343",
    "addr:street":"Dorf;Tirol",
    "iso:country":"AT",
    "sg:address":"Dorf 21",
    "sg:city":"Erl",
    "sg:orig_category":"Non-Classified Establishments",
    "sg:phone":"+43 5373 8123",
    "sg:postcode":"6343",
    "sg:province":"Tirol",
    "wof:name":"Pfarramt",
    "wof:placetype":"venue"
},
  "geometry": {"coordinates":[12.1794652939,47.682762146],"type":"Point"}
}