{
  "type": "Feature",
  "properties": {
    "addr:full":"Franz-Liszt-Weg 9 Bad Tatzmannsdorf Burgenland 7431",
    "addr:housenumber":"9",
    "addr:postcode":"7431",
    "addr:street":"Franz-Liszt-Weg",
    "iso:country":"AT",
    "sg:address":"Franz-Liszt-Weg 9",
    "sg:city":"Bad Tatzmannsdorf",
    "sg:orig_category":"Pensionen / Privatzimmer",
    "sg:phone":"+43 3353 8567",
    "sg:postcode":"7431",
    "sg:province":"Burgenland",
    "wof:name":"Pension Sonja",
    "wof:placetype":"venue"
},
  "geometry": {"coordinates":[16.222120285,47.3472328186],"type":"Point"}
}