{
  "type": "Feature",
  "properties": {
    "addr:full":"Johann-Wolf-Str 10a/11 Salzburg Salzburg 5020",
    "addr:housenumber":"10a / 11",
    "addr:postcode":"5020",
    "addr:street":"Johann-Wolf-Str;Salzburg",
    "iso:country":"AT",
    "sg:address":"Johann-Wolf-Str 10a/11",
    "sg:city":"Salzburg",
    "sg:orig_category":"Architekten",
    "sg:phone":"+43 4366 2840698",
    "sg:postcode":"5020",
    "sg:province":"Salzburg",
    "wof:name":"Pabis D.I.Z T Leszek",
    "wof:placetype":"venue"
},
  "geometry": {"coordinates":[13.0356369019,47.796962738],"type":"Point"}
}