{
  "type": "Feature",
  "properties": {
    "addr:full":"Hauptstr 5 Reichenfels K\u00e4rnten 9463",
    "addr:housenumber":"5",
    "addr:postcode":"9463",
    "addr:street":"Hauptstr;Kaernten",
    "iso:country":"AT",
    "sg:address":"Hauptstr 5",
    "sg:city":"Reichenfels",
    "sg:orig_category":"Waren Aller Art",
    "sg:phone":"+43 4359 28070",
    "sg:postcode":"9463",
    "sg:province":"K\u00e4rnten",
    "wof:name":"Quelle-Shop - St\u00fcckler Christine",
    "wof:placetype":"venue"
},
  "geometry": {"coordinates":[14.7413663864,47.0071258545],"type":"Point"}
}