{
  "type": "Feature",
  "properties": {
    "addr:full":"Innrain 23 Innsbruck Tirol 6020",
    "addr:housenumber":"23",
    "addr:postcode":"6020",
    "addr:street":"Innrain;Tirol",
    "iso:country":"AT",
    "sg:address":"Innrain 23",
    "sg:city":"Innsbruck",
    "sg:orig_category":"Fleischhauereien",
    "sg:phone":"+43 512 580046",
    "sg:postcode":"6020",
    "sg:province":"Tirol",
    "wof:name":"Holy Harald",
    "wof:placetype":"venue"
},
  "geometry": {"coordinates":[11.3898620605,47.2659645081],"type":"Point"}
}