{
  "type": "Feature",
  "properties": {
    "addr:full":"Flugplatzstrasse 1 Wels Ober\u00f6sterreich 4600",
    "addr:housenumber":"1",
    "addr:postcode":"4600",
    "addr:street":"Flugplatzstrasse;Oberoesterreich",
    "iso:country":"AT",
    "sg:address":"Flugplatzstrasse 1",
    "sg:city":"Wels",
    "sg:classifiers":[
        {
            "category":"Professional",
            "subcategory":"Advertising",
            "type":"Services"
        }
    ],
    "sg:phone":"+43 7242 43220",
    "sg:postcode":"4600",
    "sg:province":"Ober\u00f6sterreich",
    "sg:tags":[
        "flight",
        "balloon",
        "aerial"
    ],
    "sg:website":"schoenballon.at",
    "wof:name":"Sch\u00f6n Ballon",
    "wof:placetype":"venue"
},
  "geometry": {"coordinates":[14.0402536392,48.17527771],"type":"Point"}
}