{
  "type": "Feature",
  "properties": {
    "iso:country":"AT",
    "sg:address":"Ybbsitzer Str 33",
    "sg:city":"Waidhofen an der Ybbs",
    "sg:orig_category":"\u00c3\u201erzte / F Allgemeinmedizin",
    "sg:phone":"+43 4374 42538910",
    "sg:postcode":"3340",
    "sg:province":"Nieder\u00f6sterreich",
    "wof:name":"Gattringer Gerhard Dr",
    "wof:placetype":"venue"
},
  "geometry": {"coordinates":[14.8059711456,47.94298172],"type":"Point"}
}