{
  "type": "Feature",
  "properties": {
    "iso:country":"AT",
    "sg:address":"Anton Faistauer-Pl 2",
    "sg:city":"Maishofen",
    "sg:orig_category":"Friseure U Frisiersalons",
    "sg:phone":"+43 6542 80511",
    "sg:postcode":"5751",
    "sg:province":"Salzburg",
    "wof:name":"Frisiersalon Karin",
    "wof:placetype":"venue"
},
  "geometry": {"coordinates":[12.8052520752,47.3611106873],"type":"Point"}
}