{
  "type": "Feature",
  "properties": {
    "addr:full":"Schrannenpl 4 Gumpoldskirchen Nieder\u00f6sterreich 2352",
    "addr:housenumber":"4",
    "addr:postcode":"2352",
    "addr:street":"Schrannenpl",
    "iso:country":"AT",
    "sg:address":"Schrannenpl 4",
    "sg:city":"Gumpoldskirchen",
    "sg:orig_category":"Bars-Cafes",
    "sg:phone":"+43 664 3147273",
    "sg:postcode":"2352",
    "sg:province":"Nieder\u00f6sterreich",
    "wof:name":"Vinothek-Spaetrot",
    "wof:placetype":"venue"
},
  "geometry": {"coordinates":[16.2767505646,48.0456504822],"type":"Point"}
}