{
  "type": "Feature",
  "properties": {
    "iso:country":"AT",
    "sg:address":"Phorusg 7/11",
    "sg:city":"Wien",
    "sg:classifiers":[
        {
            "category":"Communications",
            "subcategory":"Film & Video Production",
            "type":"Services"
        }
    ],
    "sg:phone":"+43 676 4086825",
    "sg:postcode":"1040",
    "sg:province":"Wien",
    "sg:tags":[
        "multimedia"
    ],
    "wof:name":"Maehring Renato Stefan",
    "wof:placetype":"venue"
},
  "geometry": {"coordinates":[16.3671455383,48.1940345764],"type":"Point"}
}