{
  "type": "Feature",
  "properties": {
    "iso:country":"AT",
    "sg:address":"Nr 67",
    "sg:city":"Oberweiden",
    "sg:orig_category":"Behinderungen / Leben Mit Behinderungen",
    "sg:phone":"+43 2284 29060",
    "sg:postcode":"2295",
    "sg:province":"Nieder\u00f6sterreich",
    "wof:name":"Lebenshilfe N\u00d6 Werkst\u00e4tte",
    "wof:placetype":"venue"
},
  "geometry": {"coordinates":[16.8719882965,48.3066864014],"type":"Point"}
}