{
  "type": "Feature",
  "properties": {
    "addr:full":"Grenzgasse 23 Ternitz Nieder\u00f6sterreich 2630",
    "addr:housenumber":"23",
    "addr:postcode":"2630",
    "addr:street":"Grenzgasse",
    "iso:country":"AT",
    "sg:address":"Grenzgasse 23",
    "sg:city":"Ternitz",
    "sg:classifiers":[
        {
            "category":"Manufacturing",
            "subcategory":"Glass & Minerals",
            "type":"Manufacturing & Wholesale Goods"
        }
    ],
    "sg:phone":"+43 2630 33000",
    "sg:postcode":"2630",
    "sg:province":"Nieder\u00f6sterreich",
    "sg:tags":[
        "flat"
    ],
    "sg:website":"reiterer-glas.at",
    "wof:name":"Gerhard Reiterer GesmbH",
    "wof:placetype":"venue"
},
  "geometry": {"coordinates":[16.0230846405,47.7107391357],"type":"Point"}
}