{
  "type": "Feature",
  "properties": {
    "addr:full":"Eichenweg 36 Henndorf am Wallersee Salzburg 5302",
    "addr:housenumber":"36",
    "addr:postcode":"5302",
    "addr:street":"Eichenweg",
    "iso:country":"AT",
    "sg:address":"Eichenweg 36",
    "sg:city":"Henndorf am Wallersee",
    "sg:orig_category":"Marketingberatung",
    "sg:phone":"+43 4362 146347",
    "sg:postcode":"5302",
    "sg:province":"Salzburg",
    "wof:name":"Ruzicka Hans Ing Up-Grade Marketing Consulting",
    "wof:placetype":"venue"
},
  "geometry": {"coordinates":[13.183131218,47.8942070007],"type":"Point"}
}