{
  "type": "Feature",
  "properties": {
    "addr:full":"Rambergweg 9 St. Lorenzen Steiermark 8715",
    "addr:housenumber":"9",
    "addr:postcode":"8715",
    "addr:street":"Rambergweg",
    "iso:country":"AT",
    "sg:address":"Rambergweg 9",
    "sg:city":"St. Lorenzen",
    "sg:orig_category":"Molkereien U Molkereiprodukte",
    "sg:phone":"+43 3515 4340",
    "sg:postcode":"8715",
    "sg:province":"Steiermark",
    "wof:name":"Landforst Obersteirische Molkerei Lagerhaus KG",
    "wof:placetype":"venue"
},
  "geometry": {"coordinates":[14.8935403824,47.2492713928],"type":"Point"}
}