{
  "type": "Feature",
  "properties": {
    "addr:full":"Ziggamweg 224a St. Gallenkirch Vorarlberg 6791",
    "addr:housenumber":"224a",
    "addr:postcode":"6791",
    "addr:street":"St. Gallenkirch",
    "iso:country":"AT",
    "sg:address":"Ziggamweg 224a",
    "sg:city":"St. Gallenkirch",
    "sg:orig_category":"Pensionen / Privatzimmer",
    "sg:phone":"+43 5557 6265",
    "sg:postcode":"6791",
    "sg:province":"Vorarlberg",
    "wof:name":"K\u00f6berle Maria",
    "wof:placetype":"venue"
},
  "geometry": {"coordinates":[9.9814996719,47.0224914551],"type":"Point"}
}