{
  "type": "Feature",
  "properties": {
    "iso:country":"AT",
    "sg:city":"Leogang",
    "sg:orig_category":"Feuerwehren",
    "sg:phone":"+43 6583 8391",
    "sg:postcode":"5771",
    "sg:province":"Salzburg",
    "wof:name":"Feuerwehr Leogang",
    "wof:placetype":"venue"
},
  "geometry": {"coordinates":[12.7606391907,47.4386634827],"type":"Point"}
}