{
  "type": "Feature",
  "properties": {
    "iso:country":"AT",
    "sg:address":"Zollamtspl",
    "sg:city":"Kittsee",
    "sg:orig_category":"Speditionen",
    "sg:phone":"+43 2143 30003",
    "sg:postcode":"2421",
    "sg:province":"Burgenland",
    "wof:name":"Gebr\u00fcder Weiss GmbH",
    "wof:placetype":"venue"
},
  "geometry": {"coordinates":[17.0656547546,48.0917396545],"type":"Point"}
}