{
  "type": "Feature",
  "properties": {
    "iso:country":"AT",
    "sg:address":"Erlbachweg 29",
    "sg:city":"Leonding",
    "sg:orig_category":"Finanz- U Wirtschaftsberatung",
    "sg:phone":"+43 676 3115425",
    "sg:postcode":"4060",
    "sg:province":"Ober\u00f6sterreich",
    "wof:name":"Entlicher Winfried Dipl-Ing & Partner OEG",
    "wof:placetype":"venue"
},
  "geometry": {"coordinates":[14.2666282654,48.2840309143],"type":"Point"}
}