{
  "type": "Feature",
  "properties": {
    "addr:full":"Konstanzer Str 48 Altach Vorarlberg 6844",
    "addr:postcode":"6844",
    "addr:street":"Str 48",
    "iso:country":"AT",
    "sg:address":"Konstanzer Str 48",
    "sg:city":"Altach",
    "sg:orig_category":"Autolacke",
    "sg:phone":"+43 5576 78724",
    "sg:postcode":"6844",
    "sg:province":"Vorarlberg",
    "wof:name":"ALS-Autolackservice - Inh Posch Peter Michael",
    "wof:placetype":"venue"
},
  "geometry": {"coordinates":[9.6598396301,47.3605499268],"type":"Point"}
}