{
  "type": "Feature",
  "properties": {
    "addr:full":"Loigerstrasse 47 Wals Salzburg 5071",
    "addr:housenumber":"47",
    "addr:postcode":"5071",
    "addr:street":"Loigerstrasse;Salzburg",
    "iso:country":"AT",
    "sg:address":"Loigerstrasse 47",
    "sg:city":"Wals",
    "sg:classifiers":[
        {
            "category":"Manufacturing",
            "subcategory":"Signs",
            "type":"Manufacturing & Wholesale Goods"
        }
    ],
    "sg:phone":"+43 662 850061",
    "sg:postcode":"5071",
    "sg:province":"Salzburg",
    "sg:tags":[
        "display"
    ],
    "sg:website":"messebau-svaton.at",
    "wof:name":"Messebau Svaton",
    "wof:placetype":"venue"
},
  "geometry": {"coordinates":[12.9932746887,47.7912902832],"type":"Point"}
}