{
  "type": "Feature",
  "properties": {
    "addr:full":"Wiener Str 21 Poysdorf Nieder\u00f6sterreich 2170",
    "addr:postcode":"2170",
    "addr:street":"Niederoesterreich",
    "iso:country":"AT",
    "sg:address":"Wiener Str 21",
    "sg:city":"Poysdorf",
    "sg:orig_category":"Autohandel",
    "sg:phone":"+43 2552 26680",
    "sg:postcode":"2170",
    "sg:province":"Nieder\u00f6sterreich",
    "wof:name":"Parisch Auto GesmbH & Co KG",
    "wof:placetype":"venue"
},
  "geometry": {"coordinates":[16.6286067963,48.6648445129],"type":"Point"}
}