{
  "type": "Feature",
  "properties": {
    "addr:full":"Kornbauerstr 27 Liezen Steiermark 8940",
    "addr:housenumber":"27",
    "addr:postcode":"8940",
    "addr:street":"Kornbauerstr",
    "iso:country":"AT",
    "sg:address":"Kornbauerstr 27",
    "sg:city":"Liezen",
    "sg:orig_category":"Immobilienverwaltungen",
    "sg:phone":"+43 4336 1223746",
    "sg:postcode":"8940",
    "sg:province":"Steiermark",
    "wof:name":"Radlingmayer Verwaltung GmbH",
    "wof:placetype":"venue"
},
  "geometry": {"coordinates":[14.2368097305,47.5712127686],"type":"Point"}
}