{
  "type": "Feature",
  "properties": {
    "iso:country":"AT",
    "sg:address":"Max-Schrems-G 3/2/20",
    "sg:city":"Brunn am Gebirge",
    "sg:orig_category":"Metallbau",
    "sg:phone":"+43 4322 3631584",
    "sg:postcode":"2345",
    "sg:province":"Nieder\u00f6sterreich",
    "wof:name":"Schwaberger & Stefanits GesmbH Alu-Stahl-Glas Fassaden",
    "wof:placetype":"venue"
},
  "geometry": {"coordinates":[16.2839355469,48.107170105],"type":"Point"}
}