{
  "type": "Feature",
  "properties": {
    "addr:full":"Lindenhof 1 Innsbruck Tirol 6020",
    "addr:housenumber":"1",
    "addr:postcode":"6020",
    "addr:street":"Lindenhof;Tirol",
    "iso:country":"AT",
    "sg:address":"Lindenhof 1",
    "sg:city":"Innsbruck",
    "sg:orig_category":"Textilreinigung",
    "sg:phone":"+43 512 343210",
    "sg:postcode":"6020",
    "sg:province":"Tirol",
    "wof:name":"SOFORT DIENST GesmbH & Co KG",
    "wof:placetype":"venue"
},
  "geometry": {"coordinates":[11.4137477875,47.2671775818],"type":"Point"}
}