{
  "type": "Feature",
  "properties": {
    "iso:country":"AT",
    "sg:address":"Cumberlandstr 46-50",
    "sg:city":"Gmunden",
    "sg:orig_category":"Dosieranlagen U -Pumpen",
    "sg:phone":"+43 7612637580",
    "sg:postcode":"4810",
    "sg:province":"Ober\u00f6sterreich",
    "wof:name":"Hauke GesmbH & Co KG",
    "wof:placetype":"venue"
},
  "geometry": {"coordinates":[13.8092308044,47.9286651611],"type":"Point"}
}