{
  "type": "Feature",
  "properties": {
    "addr:full":"Hammerstr 6 Hallein Salzburg 5400",
    "addr:housenumber":"6",
    "addr:postcode":"5400",
    "addr:street":"Hammerstr;Salzburg",
    "iso:country":"AT",
    "sg:address":"Hammerstr 6",
    "sg:city":"Hallein",
    "sg:orig_category":"Tischlereien",
    "sg:phone":"+43 6245 75243",
    "sg:postcode":"5400",
    "sg:province":"Salzburg",
    "wof:name":"Auer Johann",
    "wof:placetype":"venue"
},
  "geometry": {"coordinates":[13.100528717,47.6886558533],"type":"Point"}
}