{
  "type": "Feature",
  "properties": {
    "addr:full":"Hauptpl 3-5 Hofstetten Nieder\u00f6sterreich 3202",
    "addr:housenumber":"3-5",
    "addr:postcode":"3202",
    "addr:street":"Hauptpl",
    "iso:country":"AT",
    "sg:address":"Hauptpl 3-5",
    "sg:city":"Hofstetten",
    "sg:orig_category":"Fu\u00c3\u0178pflege U Fu\u00c3\u0178pflegesalons",
    "sg:phone":"+43 2723 8869",
    "sg:postcode":"3202",
    "sg:province":"Nieder\u00f6sterreich",
    "wof:name":"Luger Barbara",
    "wof:placetype":"venue"
},
  "geometry": {"coordinates":[15.4798202515,48.0778617859],"type":"Point"}
}