{
  "type": "Feature",
  "properties": {
    "iso:country":"AT",
    "sg:address":"M\u00fcllerviertel 9",
    "sg:city":"Micheldorf in Ober\u00f6sterreich",
    "sg:orig_category":"Personalbereitstellung",
    "sg:phone":"+43 676 9218492",
    "sg:postcode":"4563",
    "sg:province":"Ober\u00f6sterreich",
    "wof:name":"EMF-Erfahrene Metallfacharbeiter Handels-u Personalleasing GmbH",
    "wof:placetype":"venue"
},
  "geometry": {"coordinates":[14.1334295273,47.877910614],"type":"Point"}
}