{
  "type": "Feature",
  "properties": {
    "addr:full":"Dornau 364 Finkenberg Tirol 6292",
    "addr:housenumber":"364",
    "addr:postcode":"6292",
    "addr:street":"Dornau",
    "iso:country":"AT",
    "sg:address":"Dornau 364",
    "sg:city":"Finkenberg",
    "sg:orig_category":"Erdarbeiten",
    "sg:phone":"+43 676 9090880",
    "sg:postcode":"6292",
    "sg:province":"Tirol",
    "wof:name":"Geisler Jakob",
    "wof:placetype":"venue"
},
  "geometry": {"coordinates":[11.8227539062,47.1480140686],"type":"Point"}
}