{
  "type": "Feature",
  "properties": {
    "addr:full":"Gmundner Str 10 Laakirchen Ober\u00f6sterreich 4663",
    "addr:postcode":"4663",
    "addr:street":"Str 10",
    "iso:country":"AT",
    "sg:address":"Gmundner Str 10",
    "sg:city":"Laakirchen",
    "sg:orig_category":"Banken U Sparkassen",
    "sg:phone":"+43 761325510",
    "sg:postcode":"4663",
    "sg:province":"Ober\u00f6sterreich",
    "wof:name":"Oberbank AG",
    "wof:placetype":"venue"
},
  "geometry": {"coordinates":[13.8232879639,47.9803314209],"type":"Point"}
}