{
  "type": "Feature",
  "properties": {
    "addr:full":"Nr 151 Kapfenstein Steiermark 8353",
    "addr:postcode":"8353",
    "addr:street":"Nr 151",
    "iso:country":"AT",
    "sg:address":"Nr 151",
    "sg:city":"Kapfenstein",
    "sg:classifiers":[
        {
            "category":"Taxi",
            "type":"Transportation"
        }
    ],
    "sg:phone":"+43 664 2238169",
    "sg:postcode":"8353",
    "sg:province":"Steiermark",
    "sg:tags":[
        "personentransporte",
        "u"
    ],
    "wof:name":"Bscheiden Siegfried",
    "wof:placetype":"venue"
},
  "geometry": {"coordinates":[15.9740009308,46.8857727051],"type":"Point"}
}