{
  "type": "Feature",
  "properties": {
    "iso:country":"AT",
    "sg:address":"Hauptstr 104",
    "sg:city":"Seeboden",
    "sg:classifiers":[
        {
            "category":"Restaurant",
            "type":"Food & Drink"
        }
    ],
    "sg:phone":"+43 4762 81064",
    "sg:postcode":"9871",
    "sg:province":"K\u00e4rnten",
    "wof:name":"Ostwind Restaurant",
    "wof:placetype":"venue"
},
  "geometry": {"coordinates":[13.5208082199,46.8190841675],"type":"Point"}
}