{
  "type": "Feature",
  "properties": {
    "addr:full":"Moos 22 Gschwandt Ober\u00f6sterreich 4816",
    "addr:housenumber":"22",
    "addr:postcode":"4816",
    "addr:street":"Moos",
    "iso:country":"AT",
    "sg:address":"Moos 22",
    "sg:city":"Gschwandt",
    "sg:orig_category":"Werbeagenturen",
    "sg:phone":"+43 4376 1289702",
    "sg:postcode":"4816",
    "sg:province":"Ober\u00f6sterreich",
    "wof:name":"Platoon Werbeagentur GesmbH",
    "wof:placetype":"venue"
},
  "geometry": {"coordinates":[13.8524751663,47.9357299805],"type":"Point"}
}