{
  "type": "Feature",
  "properties": {
    "addr:full":"Bahnstr 19 Wallern im Burgenland Burgenland 7151",
    "addr:housenumber":"19",
    "addr:postcode":"7151",
    "addr:street":"Bahnstr",
    "iso:country":"AT",
    "sg:address":"Bahnstr 19",
    "sg:city":"Wallern im Burgenland",
    "sg:orig_category":"Kinderbetreuung",
    "sg:phone":"+43 4321 742080",
    "sg:postcode":"7151",
    "sg:province":"Burgenland",
    "wof:name":"Kindergarten d r\u00f6misch-katholischen Pfarre Wallern",
    "wof:placetype":"venue"
},
  "geometry": {"coordinates":[16.9344387054,47.7267189026],"type":"Point"}
}