{
  "type": "Feature",
  "properties": {
    "iso:country":"AT",
    "sg:address":"Frimbergerg 6-8",
    "sg:city":"Wien",
    "sg:orig_category":"Osteopathie",
    "sg:phone":"+43 1 8793836",
    "sg:postcode":"1130",
    "sg:province":"Wien",
    "wof:name":"Gabriel Renate",
    "wof:placetype":"venue"
},
  "geometry": {"coordinates":[16.2928562164,48.1887779236],"type":"Point"}
}