{
  "type": "Feature",
  "properties": {
    "iso:country":"AT",
    "sg:address":"Moosstr 94",
    "sg:city":"Salzburg",
    "sg:orig_category":"Fleischhauereien",
    "sg:phone":"+43 662 830011",
    "sg:postcode":"5020",
    "sg:province":"Salzburg",
    "wof:name":"Mache Johann",
    "wof:placetype":"venue"
},
  "geometry": {"coordinates":[13.0229263306,47.7774505615],"type":"Point"}
}