{
  "type": "Feature",
  "properties": {
    "addr:full":"Josef Sch\u00f6pf-Str 16 Telfs Tirol 6410",
    "addr:housenumber":"16",
    "addr:postcode":"6410",
    "addr:street":"Tirol",
    "iso:country":"AT",
    "sg:address":"Josef Sch\u00f6pf-Str 16",
    "sg:city":"Telfs",
    "sg:classifiers":[
        {
            "category":"Home & Garden",
            "subcategory":"Garden Supply",
            "type":"Retail Goods"
        }
    ],
    "sg:phone":"+43 5262 62264",
    "sg:postcode":"6410",
    "sg:province":"Tirol",
    "sg:tags":[
        "schotter",
        "sand",
        "u"
    ],
    "wof:name":"Waldhart Klaus",
    "wof:placetype":"venue"
},
  "geometry": {"coordinates":[11.074098587,47.3045692444],"type":"Point"}
}