{
  "type": "Feature",
  "properties": {
    "iso:country":"AT",
    "sg:address":"Wiener Str 51",
    "sg:city":"Pinkafeld",
    "sg:orig_category":"Friseure U Frisiersalons",
    "sg:phone":"+43 4333 5743764",
    "sg:postcode":"7423",
    "sg:province":"Burgenland",
    "wof:name":"Fris\u00f6r Style-In - Schieder OEG",
    "wof:placetype":"venue"
},
  "geometry": {"coordinates":[16.1197376251,47.381652832],"type":"Point"}
}