{
  "type": "Feature",
  "properties": {
    "addr:full":"Getreidestr 43 Traun Ober\u00f6sterreich 4050",
    "addr:housenumber":"43",
    "addr:postcode":"4050",
    "addr:street":"Getreidestr",
    "iso:country":"AT",
    "sg:address":"Getreidestr 43",
    "sg:city":"Traun",
    "sg:orig_category":"Installationsunternehmen",
    "sg:phone":"+43 7229 74671",
    "sg:postcode":"4050",
    "sg:province":"Ober\u00f6sterreich",
    "wof:name":"Burger Stefan OEG",
    "wof:placetype":"venue"
},
  "geometry": {"coordinates":[14.2179327011,48.2258377075],"type":"Point"}
}