{
  "type": "Feature",
  "properties": {
    "addr:full":"Klammstrasse 24 Weiz Steiermark 8160",
    "addr:housenumber":"24",
    "addr:postcode":"8160",
    "addr:street":"Klammstrasse",
    "iso:country":"AT",
    "sg:address":"Klammstrasse 24",
    "sg:city":"Weiz",
    "sg:classifiers":[
        {
            "category":"Banks & Credit Unions",
            "subcategory":"Atm",
            "type":"Services"
        }
    ],
    "sg:phone":"+43 3172 23720",
    "sg:postcode":"8160",
    "sg:province":"Steiermark",
    "sg:tags":[
        "log",
        "cobble"
    ],
    "sg:website":"weitzer-parkett.com",
    "wof:name":"Weitzer Parkett Ges.m.b.H. & Co KG",
    "wof:placetype":"venue"
},
  "geometry": {"coordinates":[15.6207704544,47.2205886841],"type":"Point"}
}