{
  "type": "Feature",
  "properties": {
    "addr:full":"Panoramastr 83 Eggersdorf Steiermark 8063",
    "addr:housenumber":"83",
    "addr:postcode":"8063",
    "addr:street":"Panoramastr",
    "iso:country":"AT",
    "sg:address":"Panoramastr 83",
    "sg:city":"Eggersdorf",
    "sg:orig_category":"Transportunternehmen",
    "sg:phone":"+43 4331 173277",
    "sg:postcode":"8063",
    "sg:province":"Steiermark",
    "wof:name":"Gottmann Walter GmbH & Co KG",
    "wof:placetype":"venue"
},
  "geometry": {"coordinates":[15.5776195526,47.1552505493],"type":"Point"}
}