{
  "type": "Feature",
  "properties": {
    "iso:country":"AT",
    "sg:address":"Sporg 27",
    "sg:city":"Graz",
    "sg:orig_category":"Matratzen",
    "sg:phone":"+43 316 818866",
    "sg:postcode":"8010",
    "sg:province":"Steiermark",
    "wof:name":"Gr\u00fcne Erde GmbH - Shop & Schaur\u00e4ume",
    "wof:placetype":"venue"
},
  "geometry": {"coordinates":[15.4393548965,47.0731506348],"type":"Point"}
}