{
  "type": "Feature",
  "properties": {
    "addr:full":"Vierthalerstr 13 Salzburg Salzburg 5020",
    "addr:housenumber":"13",
    "addr:postcode":"5020",
    "addr:street":"Vierthalerstr;Salzburg",
    "iso:country":"AT",
    "sg:address":"Vierthalerstr 13",
    "sg:city":"Salzburg",
    "sg:orig_category":"Werbeagenturen",
    "sg:phone":"+43 662 879303",
    "sg:postcode":"5020",
    "sg:province":"Salzburg",
    "wof:name":"ad-net Werbeagentur Gerd Sendlhofer",
    "wof:placetype":"venue"
},
  "geometry": {"coordinates":[13.0501251221,47.8058738708],"type":"Point"}
}