{
  "type": "Feature",
  "properties": {
    "addr:full":"Erledt 1  Neukirchen am Walde Ober\u00f6sterreich 4724",
    "addr:housenumber":"1",
    "addr:postcode":"4724",
    "addr:street":"Erledt",
    "iso:country":"AT",
    "sg:address":"Erledt 1 ",
    "sg:city":"Neukirchen am Walde",
    "sg:classifiers":[
        {
            "category":"Building & Trades",
            "subcategory":"Plumbing",
            "type":"Services"
        }
    ],
    "sg:phone":"+43 7278 3229",
    "sg:postcode":"4724",
    "sg:province":"Ober\u00f6sterreich",
    "sg:tags":[
        "supraregional",
        "gas"
    ],
    "wof:name":"Ing. Markus Hofinger",
    "wof:placetype":"venue"
},
  "geometry": {"coordinates":[13.7808732986,48.4049911499],"type":"Point"}
}