{
  "type": "Feature",
  "properties": {
    "iso:country":"AT",
    "sg:address":"Gletscherblick 32",
    "sg:city":"Innsbruck-Igls",
    "sg:orig_category":"Farb-, Stil- U Typberatung",
    "sg:phone":"+43 512 3773580",
    "sg:postcode":"6080",
    "sg:province":"Tirol",
    "wof:name":"Colorline Consulting",
    "wof:placetype":"venue"
},
  "geometry": {"coordinates":[11.4070386887,47.2240257263],"type":"Point"}
}