{
  "type": "Feature",
  "properties": {
    "addr:full":"Zehenthofg 25 Wien Wien 1190",
    "addr:housenumber":"25",
    "addr:postcode":"1190",
    "addr:street":"Zehenthofg",
    "iso:country":"AT",
    "sg:address":"Zehenthofg 25",
    "sg:city":"Wien",
    "sg:orig_category":"Alternativtherapie",
    "sg:phone":"+43 4313 688787",
    "sg:postcode":"1190",
    "sg:province":"Wien",
    "wof:name":"AURA SOMA Vertriebs GmbH",
    "wof:placetype":"venue"
},
  "geometry": {"coordinates":[16.345615387,48.2475662231],"type":"Point"}
}