{
  "type": "Feature",
  "properties": {
    "iso:country":"AT",
    "sg:address":"Traundorfer Str 272",
    "sg:city":"Linz",
    "sg:orig_category":"Maler, Anstreicher U Lackierer",
    "sg:phone":"+43 732 320158",
    "sg:postcode":"4030",
    "sg:province":"Ober\u00f6sterreich",
    "wof:name":"Wohlfarter Peter",
    "wof:placetype":"venue"
},
  "geometry": {"coordinates":[14.3788490295,48.2492637634],"type":"Point"}
}