{
  "type": "Feature",
  "properties": {
    "iso:country":"AT",
    "sg:address":"Industriestr 30",
    "sg:city":"Himberg",
    "sg:classifiers":[
        {
            "category":"Home & Garden",
            "subcategory":"Building Materials",
            "type":"Retail Goods"
        }
    ],
    "sg:phone":"+43 4322 35872980",
    "sg:postcode":"2325",
    "sg:province":"Nieder\u00f6sterreich",
    "sg:tags":[
        "baustoffe",
        "-material",
        "u"
    ],
    "wof:name":"Toifelhart GesmbH",
    "wof:placetype":"venue"
},
  "geometry": {"coordinates":[16.454416275,48.0759735107],"type":"Point"}
}