{
  "type": "Feature",
  "properties": {
    "iso:country":"AT",
    "sg:address":"Raintal 2",
    "sg:city":"St. Gilgen",
    "sg:orig_category":"Apotheken",
    "sg:phone":"+43 6227 2406",
    "sg:postcode":"5340",
    "sg:province":"Salzburg",
    "wof:name":"Paracelsus-Apotheke KG",
    "wof:placetype":"venue"
},
  "geometry": {"coordinates":[13.3626289368,47.7673416138],"type":"Point"}
}