{
  "type": "Feature",
  "properties": {
    "addr:full":"Schiffmeisterg Steyr Ober\u00f6sterreich 4400",
    "addr:postcode":"4400",
    "addr:street":"Oberoesterreich",
    "iso:country":"AT",
    "sg:address":"Schiffmeisterg",
    "sg:city":"Steyr",
    "sg:orig_category":"Feuerwehren",
    "sg:phone":"+43 7252 52241",
    "sg:postcode":"4400",
    "sg:province":"Ober\u00f6sterreich",
    "wof:name":"Freiwillige Feuerwehr Innere Stadt",
    "wof:placetype":"venue"
},
  "geometry": {"coordinates":[14.4188652039,48.0345039368],"type":"Point"}
}