{
  "type": "Feature",
  "properties": {
    "addr:full":"Tannenfeldstr 22 Meiningen Vorarlberg 6812",
    "addr:housenumber":"22",
    "addr:postcode":"6812",
    "addr:street":"Tannenfeldstr",
    "iso:country":"AT",
    "sg:address":"Tannenfeldstr 22",
    "sg:city":"Meiningen",
    "sg:orig_category":"Autobusunternehmen",
    "sg:phone":"+43 5522 738450",
    "sg:postcode":"6812",
    "sg:province":"Vorarlberg",
    "wof:name":"Tr\u00f6szter Thomas",
    "wof:placetype":"venue"
},
  "geometry": {"coordinates":[9.5804071426,47.2908821106],"type":"Point"}
}