{
  "type": "Feature",
  "properties": {
    "addr:full":"Hugbertstr 16 Salzburg Salzburg 5020",
    "addr:housenumber":"16",
    "addr:postcode":"5020",
    "addr:street":"Hugbertstr;Salzburg",
    "iso:country":"AT",
    "sg:address":"Hugbertstr 16",
    "sg:city":"Salzburg",
    "sg:orig_category":"Immobilienmakler",
    "sg:phone":"+43 662 8513670",
    "sg:postcode":"5020",
    "sg:province":"Salzburg",
    "wof:name":"Fibag Immobilien GesmbH",
    "wof:placetype":"venue"
},
  "geometry": {"coordinates":[13.0191497803,47.8286514282],"type":"Point"}
}