{
  "type": "Feature",
  "properties": {
    "addr:full":"Hauptstr 5 Lichtenw\u00f6rth Nieder\u00f6sterreich 2493",
    "addr:housenumber":"5",
    "addr:postcode":"2493",
    "addr:street":"Hauptstr;Niederoesterreich",
    "iso:country":"AT",
    "sg:address":"Hauptstr 5",
    "sg:city":"Lichtenw\u00f6rth",
    "sg:orig_category":"Banken U Sparkassen",
    "sg:phone":"+43 4326 22752610",
    "sg:postcode":"2493",
    "sg:province":"Nieder\u00f6sterreich",
    "wof:name":"Raiffeisenregionalbank Wr Neustadt regGenmbH",
    "wof:placetype":"venue"
},
  "geometry": {"coordinates":[16.2962799072,47.8375015259],"type":"Point"}
}