{
  "type": "Feature",
  "properties": {
    "addr:full":"Radingerstrasse 9 Salzburg Salzburg 5020",
    "addr:housenumber":"9",
    "addr:postcode":"5020",
    "addr:street":"Radingerstrasse;Salzburg",
    "iso:country":"AT",
    "sg:address":"Radingerstrasse 9",
    "sg:city":"Salzburg",
    "sg:classifiers":[
        {
            "category":"Structure",
            "subcategory":"Office Building",
            "type":"Public Place"
        }
    ],
    "sg:phone":"+43 662 435226",
    "sg:postcode":"5020",
    "sg:province":"Salzburg",
    "sg:tags":[
        "front",
        "canopy",
        "door"
    ],
    "sg:website":"spenglerei-salzburg.at",
    "wof:name":"Walter Reinhardt GmbH",
    "wof:placetype":"venue"
},
  "geometry": {"coordinates":[13.0073852539,47.8038291931],"type":"Point"}
}