{
  "type": "Feature",
  "properties": {
    "addr:full":"Nr 5 Gurten Ober\u00f6sterreich 4942",
    "addr:postcode":"4942",
    "addr:street":"Nr;Gurten Oberoesterreich",
    "iso:country":"AT",
    "sg:address":"Nr 5",
    "sg:city":"Gurten",
    "sg:orig_category":"Tischlereien",
    "sg:phone":"+43 7757 6601",
    "sg:postcode":"4942",
    "sg:province":"Ober\u00f6sterreich",
    "wof:name":"Weibold Johann",
    "wof:placetype":"venue"
},
  "geometry": {"coordinates":[13.3448448181,48.2405700684],"type":"Point"}
}