{
  "type": "Feature",
  "properties": {
    "addr:full":"Nr 41 Weitensfeld K\u00e4rnten 9344",
    "addr:postcode":"9344",
    "addr:street":"Nr;Weitensfeld Kaernten",
    "iso:country":"AT",
    "sg:address":"Nr 41",
    "sg:city":"Weitensfeld",
    "sg:orig_category":"Freizeit- U Sportbekleidung",
    "sg:phone":"+43 4265 7543",
    "sg:postcode":"9344",
    "sg:province":"K\u00e4rnten",
    "wof:name":"Jean's und Mode Hermine Strohmaier",
    "wof:placetype":"venue"
},
  "geometry": {"coordinates":[14.193403244,46.8474197388],"type":"Point"}
}