{
  "type": "Feature",
  "properties": {
    "addr:full":"Pirchat 35 Vomp Tirol 6134",
    "addr:housenumber":"35",
    "addr:postcode":"6134",
    "addr:street":"Pirchat;Tirol",
    "iso:country":"AT",
    "sg:address":"Pirchat 35",
    "sg:city":"Vomp",
    "sg:orig_category":"Garagentore U -Antriebe",
    "sg:phone":"+43 4352 4266313",
    "sg:postcode":"6134",
    "sg:province":"Tirol",
    "wof:name":"Tor & Technik",
    "wof:placetype":"venue"
},
  "geometry": {"coordinates":[11.6738948822,47.3286056519],"type":"Point"}
}