{
  "type": "Feature",
  "properties": {
    "iso:country":"AT",
    "sg:address":"Brenner Str 36",
    "sg:city":"Steinach am Brenner",
    "sg:classifiers":[
        {
            "category":"Travel",
            "subcategory":"Hotels & Motels",
            "type":"Entertainment"
        }
    ],
    "sg:phone":"+43 5272 62210",
    "sg:postcode":"6150",
    "sg:province":"Tirol",
    "wof:name":"Hotel Rose",
    "wof:placetype":"venue"
},
  "geometry": {"coordinates":[11.466711998,47.0918159485],"type":"Point"}
}