{
  "type": "Feature",
  "properties": {
    "addr:full":"Wieselburger Str 11 Gresten Nieder\u00f6sterreich 3264",
    "addr:housenumber":"11",
    "addr:postcode":"3264",
    "addr:street":"Str",
    "iso:country":"AT",
    "sg:address":"Wieselburger Str 11",
    "sg:city":"Gresten",
    "sg:orig_category":"Feuerwehren",
    "sg:phone":"+43 7487 2222",
    "sg:postcode":"3264",
    "sg:province":"Nieder\u00f6sterreich",
    "wof:name":"Freiwillige Feuerwehr Gresten",
    "wof:placetype":"venue"
},
  "geometry": {"coordinates":[15.0228910446,47.9887619019],"type":"Point"}
}