{
  "type": "Feature",
  "properties": {
    "addr:full":"Klagenfurter Str 21 Wolfsberg K\u00e4rnten 9400",
    "addr:housenumber":"21;kaernten",
    "addr:postcode":"9400",
    "addr:street":"Str",
    "iso:country":"AT",
    "sg:address":"Klagenfurter Str 21",
    "sg:city":"Wolfsberg",
    "sg:orig_category":"Lebensmittel / Einzelhandel",
    "sg:phone":"+43 4343 5230979",
    "sg:postcode":"9400",
    "sg:province":"K\u00e4rnten",
    "wof:name":"SPAR \u00f6sterreichische Warenhandels-AG",
    "wof:placetype":"venue"
},
  "geometry": {"coordinates":[14.8396320343,46.8264465332],"type":"Point"}
}