{
  "type": "Feature",
  "properties": {
    "iso:country":"AT",
    "sg:address":"Dr A Schneider-Str 11",
    "sg:city":"Dornbirn",
    "sg:orig_category":"Suchtberatung / Alkohol, Drogen, Zigaretten",
    "sg:phone":"+43 5572 310080",
    "sg:postcode":"6850",
    "sg:province":"Vorarlberg",
    "wof:name":"Drogenberatung Ex & Hopp",
    "wof:placetype":"venue"
},
  "geometry": {"coordinates":[9.7482624054,47.4220466614],"type":"Point"}
}