{
  "type": "Feature",
  "properties": {
    "addr:full":"Sch\u00fctzengasse 1 Wien Wien 1030",
    "addr:housenumber":"1",
    "addr:postcode":"1030",
    "addr:street":"Schuetzengasse",
    "iso:country":"AT",
    "sg:address":"Sch\u00fctzengasse 1",
    "sg:city":"Wien",
    "sg:classifiers":[
        {
            "category":"Wholesale",
            "subcategory":"Medical Equipment & Supplies",
            "type":"Manufacturing & Wholesale Goods"
        }
    ],
    "sg:phone":"+43 1 7134763",
    "sg:postcode":"1030",
    "sg:province":"Wien",
    "sg:tags":[
        "cut-proof",
        "glove"
    ],
    "wof:name":"Herkules KG Dipl.-Kfm. Kurt Vogel Fabrikation von technischen Arbeiterschutz",
    "wof:placetype":"venue"
},
  "geometry": {"coordinates":[16.4025096893,48.1936683655],"type":"Point"}
}