{
  "type": "Feature",
  "properties": {
    "addr:full":"Hauptstr 63 Seekirchen am Wallersee Salzburg 5201",
    "addr:housenumber":"63",
    "addr:postcode":"5201",
    "addr:street":"Hauptstr;Salzburg",
    "iso:country":"AT",
    "sg:address":"Hauptstr 63",
    "sg:city":"Seekirchen am Wallersee",
    "sg:orig_category":"Diamanten U -Werkzeuge / F Industrie U Gewerbe",
    "sg:phone":"+43 6212 23130",
    "sg:postcode":"5201",
    "sg:province":"Salzburg",
    "wof:name":"Urtel Diamantwerkzeuge GmbH",
    "wof:placetype":"venue"
},
  "geometry": {"coordinates":[13.122341156,47.8969841003],"type":"Point"}
}