{
  "type": "Feature",
  "properties": {
    "addr:full":"Dorf 397 Breitenbach am Inn Tirol 6252",
    "addr:housenumber":"397",
    "addr:postcode":"6252",
    "addr:street":"Dorf;Tirol",
    "iso:country":"AT",
    "sg:address":"Dorf 397",
    "sg:city":"Breitenbach am Inn",
    "sg:orig_category":"Antennen",
    "sg:phone":"+43 664 4408969",
    "sg:postcode":"6252",
    "sg:province":"Tirol",
    "wof:name":"Rinnergschwentner Josef",
    "wof:placetype":"venue"
},
  "geometry": {"coordinates":[11.9796380997,47.4805908203],"type":"Point"}
}