{
  "type": "Feature",
  "properties": {
    "addr:full":"Herrenstrasse 48 Linz Ober\u00f6sterreich 4020",
    "addr:housenumber":"48",
    "addr:postcode":"4020",
    "addr:street":"Herrenstrasse",
    "iso:country":"AT",
    "sg:address":"Herrenstrasse 48",
    "sg:city":"Linz",
    "sg:classifiers":[
        {
            "category":"Banks & Credit Unions",
            "subcategory":"Investment Brokerage",
            "type":"Services"
        }
    ],
    "sg:phone":"+43 732 7686",
    "sg:postcode":"4020",
    "sg:province":"Ober\u00f6sterreich",
    "sg:tags":[
        "case",
        "spectacle"
    ],
    "sg:website":"pippig.at",
    "wof:name":"Pippig Augenoptik Brillen und Kontaktlinsen Ges.m.b.H & Co KG",
    "wof:placetype":"venue"
},
  "geometry": {"coordinates":[14.2873830795,48.2990455627],"type":"Point"}
}