{
  "type": "Feature",
  "properties": {
    "addr:full":"Thayapark 5 Laa an der Thaya Nieder\u00f6sterreich 2136",
    "addr:housenumber":"5",
    "addr:postcode":"2136",
    "addr:street":"Thayapark",
    "iso:country":"AT",
    "sg:address":"Thayapark 5",
    "sg:city":"Laa an der Thaya",
    "sg:orig_category":"Lebensmittel / Einzelhandel",
    "sg:phone":"+43 4325 2284482",
    "sg:postcode":"2136",
    "sg:province":"Nieder\u00f6sterreich",
    "wof:name":"Penny Markt",
    "wof:placetype":"venue"
},
  "geometry": {"coordinates":[16.3840770721,48.7280769348],"type":"Point"}
}