{
  "type": "Feature",
  "properties": {
    "addr:full":"Obere Hauptstr 35 Gols Burgenland 7122",
    "addr:housenumber":"35",
    "addr:postcode":"7122",
    "addr:street":"Obere Hauptstr",
    "iso:country":"AT",
    "sg:address":"Obere Hauptstr 35",
    "sg:city":"Gols",
    "sg:orig_category":"Apotheken",
    "sg:phone":"+43 2173 2300",
    "sg:postcode":"7122",
    "sg:province":"Burgenland",
    "wof:name":"St Martin Apotheke",
    "wof:placetype":"venue"
},
  "geometry": {"coordinates":[16.9034347534,47.900642395],"type":"Point"}
}