{
  "type": "Feature",
  "properties": {
    "addr:full":"Gorskistr 15 Wien Wien 1230",
    "addr:housenumber":"15",
    "addr:postcode":"1230",
    "addr:street":"Gorskistr",
    "iso:country":"AT",
    "sg:address":"Gorskistr 15",
    "sg:city":"Wien",
    "sg:orig_category":"Installationsunternehmen",
    "sg:phone":"+43 1 9853730",
    "sg:postcode":"1230",
    "sg:province":"Wien",
    "wof:name":"Eder Anton GesmbH",
    "wof:placetype":"venue"
},
  "geometry": {"coordinates":[16.3553504944,48.1419715881],"type":"Point"}
}