{
  "type": "Feature",
  "properties": {
    "iso:country":"AT",
    "sg:address":"Bundesstr 306",
    "sg:city":"Obersch\u00fctzen",
    "sg:orig_category":"Landwirtschaftliche Produkte",
    "sg:phone":"+43 4333 5238157",
    "sg:postcode":"7432",
    "sg:province":"Burgenland",
    "wof:name":"Milchhof Grabenhofer Hans",
    "wof:placetype":"venue"
},
  "geometry": {"coordinates":[16.2189121246,47.3253974915],"type":"Point"}
}