{
  "type": "Feature",
  "properties": {
    "addr:full":"Nr 8 Sitzenberg-Reidling Nieder\u00f6sterreich 3454",
    "addr:postcode":"3454",
    "addr:street":"Nr;Sitzenberg-Reidling",
    "iso:country":"AT",
    "sg:address":"Nr 8",
    "sg:city":"Sitzenberg-Reidling",
    "sg:orig_category":"Gemeinden",
    "sg:phone":"+43 2782 85500",
    "sg:postcode":"3454",
    "sg:province":"Nieder\u00f6sterreich",
    "wof:name":"Gemeindeamt Herzogenburg - Ortsvorstehung Gutenbrunn",
    "wof:placetype":"venue"
},
  "geometry": {"coordinates":[15.8177452087,48.3197517395],"type":"Point"}
}