{
  "type": "Feature",
  "properties": {
    "iso:country":"AT",
    "sg:address":"Kapellenweg 7",
    "sg:city":"Ellmau",
    "sg:orig_category":"Appartements / Ferienwohnungen",
    "sg:phone":"+43 5358 3426",
    "sg:postcode":"6352",
    "sg:province":"Tirol",
    "wof:name":"Horngacher Klaus",
    "wof:placetype":"venue"
},
  "geometry": {"coordinates":[12.3061294556,47.5124511719],"type":"Point"}
}