{
  "type": "Feature",
  "properties": {
    "addr:full":"Reichsstr 124 Feldkirch Vorarlberg 6800",
    "addr:housenumber":"124",
    "addr:postcode":"6800",
    "iso:country":"AT",
    "sg:address":"Reichsstr 124",
    "sg:city":"Feldkirch",
    "sg:orig_category":"Versicherungsunternehmen",
    "sg:phone":"+43 5522 720790",
    "sg:postcode":"6800",
    "sg:province":"Vorarlberg",
    "wof:name":"Interunfall Versicherung AG",
    "wof:placetype":"venue"
},
  "geometry": {"coordinates":[9.6106119156,47.2481498718],"type":"Point"}
}