{
  "type": "Feature",
  "properties": {
    "addr:full":"Korneuburger Str 12 Korneuburg Nieder\u00f6sterreich 2100",
    "addr:postcode":"2100",
    "addr:street":"Str 12",
    "iso:country":"AT",
    "sg:address":"Korneuburger Str 12",
    "sg:city":"Korneuburg",
    "sg:orig_category":"Tischlereien",
    "sg:phone":"+43 2262 66115",
    "sg:postcode":"2100",
    "sg:province":"Nieder\u00f6sterreich",
    "wof:name":"Moser Andreas",
    "wof:placetype":"venue"
},
  "geometry": {"coordinates":[16.3218841553,48.3753166199],"type":"Point"}
}