{
  "type": "Feature",
  "properties": {
    "addr:full":"Grub I 5 Riegersburg Steiermark 8333",
    "addr:housenumber":"5",
    "addr:postcode":"8333",
    "addr:street":"I",
    "iso:country":"AT",
    "sg:address":"Grub I 5",
    "sg:city":"Riegersburg",
    "sg:classifiers":[
        {
            "category":"Home & Garden",
            "subcategory":"Carpets & Floor Coverings",
            "type":"Retail Goods"
        }
    ],
    "sg:phone":"+43 3153 7366",
    "sg:postcode":"8333",
    "sg:province":"Steiermark",
    "sg:tags":[
        "carpeting"
    ],
    "wof:name":"Franz Ackerl",
    "wof:placetype":"venue"
},
  "geometry": {"coordinates":[15.9359292984,47.0007858276],"type":"Point"}
}