{
  "type": "Feature",
  "properties": {
    "addr:full":"D\u00f6pplingerstr 14 Ternitz Nieder\u00f6sterreich 2630",
    "addr:housenumber":"14",
    "addr:postcode":"2630",
    "addr:street":"Doepplingerstr",
    "iso:country":"AT",
    "sg:address":"D\u00f6pplingerstr 14",
    "sg:city":"Ternitz",
    "sg:orig_category":"Insektenschutzgitter",
    "sg:phone":"+43 2630 38439",
    "sg:postcode":"2630",
    "sg:province":"Nieder\u00f6sterreich",
    "wof:name":"Scherz Josef GesmbH",
    "wof:placetype":"venue"
},
  "geometry": {"coordinates":[16.0378704071,47.7229499817],"type":"Point"}
}