{
  "type": "Feature",
  "properties": {
    "addr:full":"Stadtpl 48 Wels Ober\u00f6sterreich 4600",
    "addr:housenumber":"48",
    "addr:postcode":"4600",
    "addr:street":"Stadtpl;Oberoesterreich",
    "iso:country":"AT",
    "sg:address":"Stadtpl 48",
    "sg:city":"Wels",
    "sg:orig_category":"Damenmoden",
    "sg:phone":"+43 7242 6322455",
    "sg:postcode":"4600",
    "sg:province":"Ober\u00f6sterreich",
    "wof:name":"Gerard women",
    "wof:placetype":"venue"
},
  "geometry": {"coordinates":[14.0242509842,48.1566581726],"type":"Point"}
}