{
  "type": "Feature",
  "properties": {
    "addr:full":"Pollheimerstr 5 Wels Ober\u00f6sterreich 4600",
    "addr:housenumber":"5",
    "addr:postcode":"4600",
    "addr:street":"Pollheimerstr;Oberoesterreich",
    "iso:country":"AT",
    "sg:address":"Pollheimerstr 5",
    "sg:city":"Wels",
    "sg:orig_category":"Restaurants: Chinesisch",
    "sg:phone":"+43 7242 60430",
    "sg:postcode":"4600",
    "sg:province":"Ober\u00f6sterreich",
    "wof:name":"F\u00dcNF STERNE China-Restaurant",
    "wof:placetype":"venue"
},
  "geometry": {"coordinates":[14.0222158432,48.155002594],"type":"Point"}
}