{
  "type": "Feature",
  "properties": {
    "addr:full":"Wiener Str 10 Haid Ober\u00f6sterreich 4053",
    "addr:postcode":"4053",
    "addr:street":"Haid Oberoesterreich",
    "iso:country":"AT",
    "sg:address":"Wiener Str 10",
    "sg:city":"Haid",
    "sg:orig_category":"Gasversorgungsunternehmen",
    "sg:phone":"+43 4372 29886430",
    "sg:postcode":"4053",
    "sg:province":"Ober\u00f6sterreich",
    "wof:name":"Ober\u00f6sterreichische Ferngas AG",
    "wof:placetype":"venue"
},
  "geometry": {"coordinates":[14.2502212524,48.1983757019],"type":"Point"}
}