{
  "type": "Feature",
  "properties": {
    "iso:country":"AT",
    "sg:address":"Aug 144",
    "sg:city":"Arnfels",
    "sg:orig_category":"Tischlereien",
    "sg:phone":"+43 4334 55277",
    "sg:postcode":"8454",
    "sg:province":"Steiermark",
    "wof:name":"W\u00fcrzler Handwerkst\u00e4tte GesmbH",
    "wof:placetype":"venue"
},
  "geometry": {"coordinates":[15.4017324448,46.6779937744],"type":"Point"}
}