{
  "type": "Feature",
  "properties": {
    "iso:country":"AT",
    "sg:address":"Brunnenweg 1-3",
    "sg:city":"Kirchdorf an der Krems",
    "sg:classifiers":[
        {
            "category":"Structure",
            "subcategory":"Tunnel",
            "type":"Public Place"
        }
    ],
    "sg:phone":"+43 7582 60958",
    "sg:postcode":"4560",
    "sg:province":"Ober\u00f6sterreich",
    "sg:tags":[
        "extrusion",
        "system",
        "extruders"
    ],
    "sg:website":"topf.at",
    "wof:name":"Topf Kunststofftechnik Ges.m.b.H.",
    "wof:placetype":"venue"
},
  "geometry": {"coordinates":[14.0811481476,47.927116394],"type":"Point"}
}