{
  "type": "Feature",
  "properties": {
    "addr:full":"Schulstrasse 18 Vorchdorf Ober\u00f6sterreich 4655",
    "addr:housenumber":"18",
    "addr:postcode":"4655",
    "addr:street":"Schulstrasse",
    "iso:country":"AT",
    "sg:address":"Schulstrasse 18",
    "sg:city":"Vorchdorf",
    "sg:classifiers":[
        {
            "category":"Manufacturing",
            "subcategory":"Furniture",
            "type":"Manufacturing & Wholesale Goods"
        }
    ],
    "sg:phone":"+43 76146377",
    "sg:postcode":"4655",
    "sg:province":"Ober\u00f6sterreich",
    "sg:tags":[
        "bedroom"
    ],
    "wof:name":"Bernhard Radner",
    "wof:placetype":"venue"
},
  "geometry": {"coordinates":[13.9249038696,48.0073852539],"type":"Point"}
}