{
  "type": "Feature",
  "properties": {
    "addr:full":"Thayapark 21 Laa an der Thaya Nieder\u00f6sterreich 2136",
    "addr:housenumber":"21",
    "addr:postcode":"2136",
    "addr:street":"Thayapark",
    "iso:country":"AT",
    "sg:address":"Thayapark 21",
    "sg:city":"Laa an der Thaya",
    "sg:orig_category":"Messen U Ausstellungen",
    "sg:phone":"+43 4325 222638",
    "sg:postcode":"2136",
    "sg:province":"Nieder\u00f6sterreich",
    "wof:name":"Veranstaltungs-GmbH Laa a d Thaya",
    "wof:placetype":"venue"
},
  "geometry": {"coordinates":[16.3854312897,48.72838974],"type":"Point"}
}