{
  "type": "Feature",
  "properties": {
    "iso:country":"AT",
    "sg:address":"Wichnerstr 11",
    "sg:city":"Dornbirn",
    "sg:classifiers":[
        {
            "category":"Professional",
            "subcategory":"Computer Services",
            "type":"Services"
        }
    ],
    "sg:phone":"+43 664 9964478",
    "sg:postcode":"6850",
    "sg:province":"Vorarlberg",
    "sg:tags":[
        "software"
    ],
    "wof:name":"novosoft",
    "wof:placetype":"venue"
},
  "geometry": {"coordinates":[9.73346138,47.4237251282],"type":"Point"}
}