{
  "type": "Feature",
  "properties": {
    "addr:full":"Hintergasse 27-29 Waidhofen an der Ybbs Nieder\u00f6sterreich 3340",
    "addr:postcode":"27-29;3340",
    "addr:street":"Hintergasse",
    "iso:country":"AT",
    "sg:address":"Hintergasse 27-29",
    "sg:city":"Waidhofen an der Ybbs",
    "sg:classifiers":[
        {
            "category":"Travel",
            "subcategory":"Hotels & Motels",
            "type":"Entertainment"
        }
    ],
    "sg:phone":"+43 7442 556100",
    "sg:postcode":"3340",
    "sg:province":"Nieder\u00f6sterreich",
    "sg:tags":[
        "linen",
        "leasing",
        "hotels"
    ],
    "sg:website":"pointner.co.at",
    "wof:name":"Textilservice Pointner GmbH",
    "wof:placetype":"venue"
},
  "geometry": {"coordinates":[14.7754898071,47.9613265991],"type":"Point"}
}