{
  "type": "Feature",
  "properties": {
    "addr:full":"Moosstr 76 Salzburg Salzburg 5020",
    "addr:housenumber":"76",
    "addr:postcode":"5020",
    "addr:street":"Moosstr;Salzburg",
    "iso:country":"AT",
    "sg:address":"Moosstr 76",
    "sg:city":"Salzburg",
    "sg:orig_category":"Transportunternehmen",
    "sg:phone":"+43 662 8249408",
    "sg:postcode":"5020",
    "sg:province":"Salzburg",
    "wof:name":"Ziller Johannes",
    "wof:placetype":"venue"
},
  "geometry": {"coordinates":[13.0242929459,47.7807350159],"type":"Point"}
}