{
  "type": "Feature",
  "properties": {
    "addr:full":"Schulstr 2 Klagenfurt-Viktring K\u00e4rnten 9073",
    "addr:housenumber":"2",
    "addr:postcode":"9073",
    "addr:street":"Schulstr;Kaernten",
    "iso:country":"AT",
    "sg:address":"Schulstr 2",
    "sg:city":"Klagenfurt-Viktring",
    "sg:orig_category":"Volksschulen",
    "sg:phone":"+43 463 281102",
    "sg:postcode":"9073",
    "sg:province":"K\u00e4rnten",
    "wof:name":"Volksschule 19",
    "wof:placetype":"venue"
},
  "geometry": {"coordinates":[14.272936821,46.5897102356],"type":"Point"}
}