{
  "type": "Feature",
  "properties": {
    "addr:full":"F\u00fcrstenhofpl 1 Friesach K\u00e4rnten 9360",
    "addr:housenumber":"1",
    "addr:postcode":"9360",
    "addr:street":"Fuerstenhofpl;Kaernten",
    "iso:country":"AT",
    "sg:address":"F\u00fcrstenhofpl 1",
    "sg:city":"Friesach",
    "sg:orig_category":"Raumausstattung",
    "sg:phone":"+43 4268 2396",
    "sg:postcode":"9360",
    "sg:province":"K\u00e4rnten",
    "wof:name":"Omann Gertraud",
    "wof:placetype":"venue"
},
  "geometry": {"coordinates":[14.4060497284,46.9506263733],"type":"Point"}
}