{
  "type": "Feature",
  "properties": {
    "addr:full":"Flurg 31 Klagenfurt K\u00e4rnten 9020",
    "addr:housenumber":"31",
    "addr:postcode":"9020",
    "addr:street":"Flurg;Kaernten",
    "iso:country":"AT",
    "sg:address":"Flurg 31",
    "sg:city":"Klagenfurt",
    "sg:orig_category":"Psychotherapie",
    "sg:phone":"+43 463 328000",
    "sg:postcode":"9020",
    "sg:province":"K\u00e4rnten",
    "wof:name":"Lexel-Gartner Sigrid",
    "wof:placetype":"venue"
},
  "geometry": {"coordinates":[14.3274202347,46.6254196167],"type":"Point"}
}