{
  "type": "Feature",
  "properties": {
    "addr:full":"Winklen 89 L\u00e4ngenfeld Tirol 6444",
    "addr:housenumber":"89",
    "addr:postcode":"6444",
    "addr:street":"Winklen;Tirol",
    "iso:country":"AT",
    "sg:address":"Winklen 89",
    "sg:city":"L\u00e4ngenfeld",
    "sg:orig_category":"Estriche",
    "sg:phone":"+43 5253 6338",
    "sg:postcode":"6444",
    "sg:province":"Tirol",
    "wof:name":"Gebr\u00fcder Mrak Estriche OHG",
    "wof:placetype":"venue"
},
  "geometry": {"coordinates":[10.9441728592,47.1027908325],"type":"Point"}
}