{
  "type": "Feature",
  "properties": {
    "addr:full":"Sonnenstrasse 3 Langenlois Nieder\u00f6sterreich 3550",
    "addr:housenumber":"3",
    "addr:postcode":"3550",
    "addr:street":"Sonnenstrasse",
    "iso:country":"AT",
    "sg:address":"Sonnenstrasse 3",
    "sg:city":"Langenlois",
    "sg:classifiers":[
        {
            "category":"Building & Trades",
            "subcategory":"Electrical",
            "type":"Services"
        }
    ],
    "sg:phone":"+43 2734 32320",
    "sg:postcode":"3550",
    "sg:province":"Nieder\u00f6sterreich",
    "sg:tags":[
        "work",
        "installation"
    ],
    "wof:name":"Harald Unger",
    "wof:placetype":"venue"
},
  "geometry": {"coordinates":[15.6715097427,48.4781913757],"type":"Point"}
}