{
  "type": "Feature",
  "properties": {
    "addr:full":"Marktpl 13 Mondsee Ober\u00f6sterreich 5310",
    "addr:housenumber":"13",
    "addr:postcode":"5310",
    "addr:street":"Marktpl;Oberoesterreich",
    "iso:country":"AT",
    "sg:address":"Marktpl 13",
    "sg:city":"Mondsee",
    "sg:orig_category":"Trachtenbekleidung",
    "sg:phone":"+43 4362 322079",
    "sg:postcode":"5310",
    "sg:province":"Ober\u00f6sterreich",
    "wof:name":"Risch Mode & Tracht",
    "wof:placetype":"venue"
},
  "geometry": {"coordinates":[13.3495254517,47.8559875488],"type":"Point"}
}