{
  "type": "Feature",
  "properties": {
    "addr:full":"Sch\u00f6nbrunner Allee 39 Wien Wien 1120",
    "addr:housenumber":"39",
    "addr:postcode":"1120",
    "addr:street":"Schoenbrunner Allee",
    "iso:country":"AT",
    "sg:address":"Sch\u00f6nbrunner Allee 39",
    "sg:city":"Wien",
    "sg:orig_category":"Handelsagenturen",
    "sg:phone":"+43 1 8033705",
    "sg:postcode":"1120",
    "sg:province":"Wien",
    "wof:name":"M & M InvestitionsberatungsgesmbH",
    "wof:placetype":"venue"
},
  "geometry": {"coordinates":[16.3105545044,48.1694221497],"type":"Point"}
}