{
  "type": "Feature",
  "properties": {
    "addr:full":"Stiftingtalstr 148 Graz Steiermark 8010",
    "addr:housenumber":"148",
    "addr:postcode":"8010",
    "iso:country":"AT",
    "sg:address":"Stiftingtalstr 148",
    "sg:city":"Graz",
    "sg:orig_category":"Steuerberatung",
    "sg:phone":"+43 316 324844",
    "sg:postcode":"8010",
    "sg:province":"Steiermark",
    "wof:name":"Bachheimer Herwig Dkfm Mag SteuerberatungsgesmbH",
    "wof:placetype":"venue"
},
  "geometry": {"coordinates":[15.4851160049,47.0890541077],"type":"Point"}
}