{
  "type": "Feature",
  "properties": {
    "addr:full":"Neustiftg 33 Wien Wien 1070",
    "addr:housenumber":"33",
    "addr:postcode":"1070",
    "addr:street":"Neustiftg",
    "iso:country":"AT",
    "sg:address":"Neustiftg 33",
    "sg:city":"Wien",
    "sg:orig_category":"Psychotherapie",
    "sg:phone":"+43 1 5246198",
    "sg:postcode":"1070",
    "sg:province":"Wien",
    "wof:name":"Aigner Regina Mag",
    "wof:placetype":"venue"
},
  "geometry": {"coordinates":[16.3523159027,48.2052345276],"type":"Point"}
}