{
  "type": "Feature",
  "properties": {
    "addr:full":"Agerstr 43 Sch\u00f6rfling am Attersee Ober\u00f6sterreich 4861",
    "addr:housenumber":"43",
    "addr:postcode":"4861",
    "addr:street":"Agerstr;Am",
    "iso:country":"AT",
    "sg:address":"Agerstr 43",
    "sg:city":"Sch\u00f6rfling am Attersee",
    "sg:orig_category":"Forstverwaltungen",
    "sg:phone":"+43 4376 622220",
    "sg:postcode":"4861",
    "sg:province":"Ober\u00f6sterreich",
    "wof:name":"Stift Schl\u00e4gel'sche Forstverwaltung Kammer am Attersee",
    "wof:placetype":"venue"
},
  "geometry": {"coordinates":[13.5959701538,47.9473991394],"type":"Point"}
}