{
  "type": "Feature",
  "properties": {
    "addr:full":"Mediastr 6 Pinkafeld Burgenland 7423",
    "addr:housenumber":"6",
    "addr:postcode":"7423",
    "addr:street":"Mediastr",
    "iso:country":"AT",
    "sg:address":"Mediastr 6",
    "sg:city":"Pinkafeld",
    "sg:orig_category":"Zimmereien",
    "sg:phone":"+43 3357 42748",
    "sg:postcode":"7423",
    "sg:province":"Burgenland",
    "wof:name":"Wanitsch Johann",
    "wof:placetype":"venue"
},
  "geometry": {"coordinates":[16.1168842316,47.3633117676],"type":"Point"}
}