{
  "type": "Feature",
  "properties": {
    "addr:full":"B\u00e4ckerg 20 Wels Ober\u00f6sterreich 4600",
    "addr:housenumber":"20",
    "addr:postcode":"4600",
    "addr:street":"Baeckerg;Oberoesterreich",
    "iso:country":"AT",
    "sg:address":"B\u00e4ckerg 20",
    "sg:city":"Wels",
    "sg:orig_category":"Boutiquen",
    "sg:phone":"+43 7242 68939",
    "sg:postcode":"4600",
    "sg:province":"Ober\u00f6sterreich",
    "wof:name":"Illenberger Franz GmbH & Co - Trend",
    "wof:placetype":"venue"
},
  "geometry": {"coordinates":[14.0244407654,48.1598014832],"type":"Point"}
}