{
  "type": "Feature",
  "properties": {
    "iso:country":"AT",
    "sg:address":"Achstr 14",
    "sg:city":"Hard",
    "sg:orig_category":"Antriebstechnik",
    "sg:phone":"+43 4355 7464776",
    "sg:postcode":"6971",
    "sg:province":"Vorarlberg",
    "wof:name":"Immler Technologie",
    "wof:placetype":"venue"
},
  "geometry": {"coordinates":[9.6945810318,47.4964523315],"type":"Point"}
}