{
  "type": "Feature",
  "properties": {
    "addr:full":"Nr 101 Straden Steiermark 8345",
    "addr:postcode":"8345",
    "addr:street":"Nr",
    "iso:country":"AT",
    "sg:address":"Nr 101",
    "sg:city":"Straden",
    "sg:classifiers":[
        {
            "category":"Professional",
            "subcategory":"Computer Services",
            "type":"Services"
        }
    ],
    "sg:phone":"+43 4334 738070",
    "sg:postcode":"8345",
    "sg:province":"Steiermark",
    "sg:tags":[
        "software"
    ],
    "wof:name":"Unger Klaus",
    "wof:placetype":"venue"
},
  "geometry": {"coordinates":[15.8692350388,46.8074264526],"type":"Point"}
}