{
  "type": "Feature",
  "properties": {
    "addr:full":"Wiener Str 25 Ebreichsdorf Nieder\u00f6sterreich 2483",
    "addr:postcode":"2483",
    "addr:street":"25",
    "iso:country":"AT",
    "sg:address":"Wiener Str 25",
    "sg:city":"Ebreichsdorf",
    "sg:orig_category":"Lebensmittel / Einzelhandel",
    "sg:phone":"+43 2254 74603",
    "sg:postcode":"2483",
    "sg:province":"Nieder\u00f6sterreich",
    "wof:name":"MONDO Lebensmitteldiskonter",
    "wof:placetype":"venue"
},
  "geometry": {"coordinates":[16.4017162323,47.967048645],"type":"Point"}
}