{
  "type": "Feature",
  "properties": {
    "iso:country":"AT",
    "sg:address":"Amberg 48",
    "sg:city":"Kufstein",
    "sg:classifiers":[
        {
            "category":"Professional",
            "subcategory":"Detective & Security Services",
            "type":"Services"
        }
    ],
    "sg:phone":"+43 5372 5852411",
    "sg:postcode":"6330",
    "sg:province":"Tirol",
    "sg:tags":[
        "access",
        "control",
        "ac",
        "system"
    ],
    "sg:website":"gerof.com",
    "wof:name":"Gerof Rohrpost- und Sicherheitstechnik GmbH",
    "wof:placetype":"venue"
},
  "geometry": {"coordinates":[12.185423851,47.5967750549],"type":"Point"}
}