{
  "type": "Feature",
  "properties": {
    "iso:country":"AT",
    "sg:address":"Herrnhauspl 11",
    "sg:city":"Brixlegg",
    "sg:orig_category":"Futtermittel",
    "sg:phone":"+43 5337 62307",
    "sg:postcode":"6230",
    "sg:province":"Tirol",
    "wof:name":"Kosta Katharina",
    "wof:placetype":"venue"
},
  "geometry": {"coordinates":[11.8779993057,47.4296073914],"type":"Point"}
}