{
  "type": "Feature",
  "properties": {
    "iso:country":"AT",
    "sg:address":"Burgg 5",
    "sg:city":"Judenburg",
    "sg:orig_category":"Steuerberatung",
    "sg:phone":"+43 3572 856160",
    "sg:postcode":"8750",
    "sg:province":"Steiermark",
    "wof:name":"Zehenthofer Hannes Mag",
    "wof:placetype":"venue"
},
  "geometry": {"coordinates":[14.660241127,47.1676826477],"type":"Point"}
}