{
  "type": "Feature",
  "properties": {
    "addr:full":"Umfahrungsstr 1 Hadersdorf am Kamp Nieder\u00f6sterreich 3493",
    "addr:housenumber":"1",
    "addr:postcode":"3493",
    "addr:street":"Umfahrungsstr;Niederoesterreich",
    "iso:country":"AT",
    "sg:address":"Umfahrungsstr 1",
    "sg:city":"Hadersdorf am Kamp",
    "sg:orig_category":"Banken U Sparkassen",
    "sg:phone":"+43 4327 355589",
    "sg:postcode":"3493",
    "sg:province":"Nieder\u00f6sterreich",
    "wof:name":"Volksbank Krems-Zwettl AG",
    "wof:placetype":"venue"
},
  "geometry": {"coordinates":[15.7205963135,48.4622383118],"type":"Point"}
}