{
  "type": "Feature",
  "properties": {
    "addr:full":"Dr Greil-Str 10 St. Georgen im Attergau Ober\u00f6sterreich 4880",
    "addr:housenumber":"10",
    "addr:postcode":"4880",
    "iso:country":"AT",
    "sg:address":"Dr Greil-Str 10",
    "sg:city":"St. Georgen im Attergau",
    "sg:orig_category":"Physiotherapie",
    "sg:phone":"+43 76676248",
    "sg:postcode":"4880",
    "sg:province":"Ober\u00f6sterreich",
    "wof:name":"Greil Sylvia Dipl-PT",
    "wof:placetype":"venue"
},
  "geometry": {"coordinates":[13.486779213,47.9342460632],"type":"Point"}
}