{
  "type": "Feature",
  "properties": {
    "addr:full":"Rebental 22 Rotenturm an der Pinka Burgenland 7501",
    "addr:housenumber":"22",
    "addr:postcode":"7501",
    "addr:street":"Rebental",
    "iso:country":"AT",
    "sg:address":"Rebental 22",
    "sg:city":"Rotenturm an der Pinka",
    "sg:orig_category":"Transportunternehmen",
    "sg:phone":"+43 4333 526565",
    "sg:postcode":"7501",
    "sg:province":"Burgenland",
    "wof:name":"Halper G\u00fcnther",
    "wof:placetype":"venue"
},
  "geometry": {"coordinates":[16.2184925079,47.2228660583],"type":"Point"}
}