{
  "type": "Feature",
  "properties": {
    "iso:country":"AT",
    "sg:address":"Nr 60c",
    "sg:city":"Leibnitz",
    "sg:orig_category":"Tankstellen",
    "sg:phone":"+43 3452 76701",
    "sg:postcode":"8430",
    "sg:province":"Steiermark",
    "wof:name":"OMV AG",
    "wof:placetype":"venue"
},
  "geometry": {"coordinates":[15.5377645493,46.7811355591],"type":"Point"}
}