{
  "type": "Feature",
  "properties": {
    "addr:full":"Karl-Kaubek-Str 23 Langenzersdorf Nieder\u00f6sterreich 2103",
    "addr:housenumber":"23",
    "addr:postcode":"2103",
    "addr:street":"Karl-Kaubek-Str",
    "iso:country":"AT",
    "sg:address":"Karl-Kaubek-Str 23",
    "sg:city":"Langenzersdorf",
    "sg:orig_category":"Weine / Gro\u00c3\u0178handel",
    "sg:phone":"+43 4322 444810",
    "sg:postcode":"2103",
    "sg:province":"Nieder\u00f6sterreich",
    "wof:name":"Rohrbeck P u R Weinhandel KEG",
    "wof:placetype":"venue"
},
  "geometry": {"coordinates":[16.3575534821,48.2963294983],"type":"Point"}
}