{
  "type": "Feature",
  "properties": {
    "addr:full":"Moserhofgasse 19-21 Graz Steiermark 8010",
    "addr:postcode":"19-21;8010",
    "addr:street":"Moserhofgasse",
    "iso:country":"AT",
    "sg:address":"Moserhofgasse 19-21",
    "sg:city":"Graz",
    "sg:classifiers":[
        {
            "category":"Manufacturing",
            "subcategory":"Metals",
            "type":"Manufacturing & Wholesale Goods"
        }
    ],
    "sg:phone":"+43 316 47156212",
    "sg:postcode":"8010",
    "sg:province":"Steiermark",
    "sg:tags":[
        "blanking",
        "dy"
    ],
    "sg:website":"anker.at",
    "wof:name":"Anker-Datentechnik Ges.m.b.H.",
    "wof:placetype":"venue"
},
  "geometry": {"coordinates":[15.4567718506,47.0605278015],"type":"Point"}
}