{
  "type": "Feature",
  "properties": {
    "iso:country":"AT",
    "sg:address":"Obere Tiebelg 7",
    "sg:city":"Feldkirchen in K\u00e4rnten",
    "sg:orig_category":"Raumausstattung",
    "sg:phone":"+43 4342 762777",
    "sg:postcode":"9560",
    "sg:province":"K\u00e4rnten",
    "wof:name":"Farbm\u00fchle Friessnegg GmbH",
    "wof:placetype":"venue"
},
  "geometry": {"coordinates":[14.0920295715,46.7234268188],"type":"Point"}
}