{
  "type": "Feature",
  "properties": {
    "iso:country":"AT",
    "sg:address":"Hauptstrasse 67",
    "sg:city":"Th\u00fcringen",
    "sg:classifiers":[
        {
            "category":"Exhibition Hall",
            "type":"Public Place"
        }
    ],
    "sg:phone":"+43 5550 22650",
    "sg:postcode":"6712",
    "sg:province":"Vorarlberg",
    "sg:tags":[
        "steel"
    ],
    "sg:website":"stahlbau-mark.com",
    "wof:name":"Stahlbau Mark Ges.m.b.H. & Co KG",
    "wof:placetype":"venue"
},
  "geometry": {"coordinates":[9.7659406662,47.1976509094],"type":"Point"}
}