{
  "type": "Feature",
  "properties": {
    "addr:full":"Weideg 1B Gramatneusiedl Nieder\u00f6sterreich 2440",
    "addr:housenumber":"1b",
    "addr:postcode":"2440",
    "addr:street":"Weideg",
    "iso:country":"AT",
    "sg:address":"Weideg 1B",
    "sg:city":"Gramatneusiedl",
    "sg:orig_category":"Transportunternehmen, Entsorgungen",
    "sg:phone":"+43 699 17120183",
    "sg:postcode":"2440",
    "sg:province":"Nieder\u00f6sterreich",
    "wof:name":"Hegyi Matthias - Transportunternehmen",
    "wof:placetype":"venue"
},
  "geometry": {"coordinates":[16.4910297394,48.0298614502],"type":"Point"}
}