{
  "type": "Feature",
  "properties": {
    "addr:full":"Austr 12 Jenbach Tirol 6200",
    "addr:housenumber":"12",
    "addr:postcode":"6200",
    "addr:street":"Austr;Tirol",
    "iso:country":"AT",
    "sg:address":"Austr 12",
    "sg:city":"Jenbach",
    "sg:orig_category":"Baumaschinenverleih",
    "sg:phone":"+43 5244 69660",
    "sg:postcode":"6200",
    "sg:province":"Tirol",
    "wof:name":"Laurer Josef KG",
    "wof:placetype":"venue"
},
  "geometry": {"coordinates":[11.777674675,47.3867225647],"type":"Point"}
}