{
  "type": "Feature",
  "properties": {
    "iso:country":"AT",
    "sg:address":"Fichtenstr 3",
    "sg:city":"Hallwang",
    "sg:orig_category":"Baumeister",
    "sg:phone":"+43 662 661247",
    "sg:postcode":"5300",
    "sg:province":"Salzburg",
    "wof:name":"Emberger Hans-J\u00f6rg Bmstr Ing",
    "wof:placetype":"venue"
},
  "geometry": {"coordinates":[13.0895795822,47.83411026],"type":"Point"}
}