{
  "type": "Feature",
  "properties": {
    "addr:full":"Angerer Str Wien Wien 1210",
    "addr:postcode":"1210",
    "addr:street":"Str Wien",
    "iso:country":"AT",
    "sg:address":"Angerer Str",
    "sg:city":"Wien",
    "sg:orig_category":"Eisen",
    "sg:phone":"+43 1 2585121",
    "sg:postcode":"1210",
    "sg:province":"Wien",
    "wof:name":"VOEST-ALPINE ROHSTOFFHANDEL GmbH",
    "wof:placetype":"venue"
},
  "geometry": {"coordinates":[16.3998508453,48.2597045898],"type":"Point"}
}