{
  "type": "Feature",
  "properties": {
    "addr:full":"Nr 1 Olbendorf Burgenland 7534",
    "addr:postcode":"7534",
    "addr:street":"Nr",
    "iso:country":"AT",
    "sg:address":"Nr 1",
    "sg:city":"Olbendorf",
    "sg:orig_category":"Friseure U Frisiersalons",
    "sg:phone":"+43 4333 2652228",
    "sg:postcode":"7534",
    "sg:province":"Burgenland",
    "wof:name":"Tury Martha",
    "wof:placetype":"venue"
},
  "geometry": {"coordinates":[16.2039165497,47.1885948181],"type":"Point"}
}