{
  "type": "Feature",
  "properties": {
    "addr:full":"Karl-Tornay-G 37-43 Wien Wien 1230",
    "addr:postcode":"37-43;1230",
    "iso:country":"AT",
    "sg:address":"Karl-Tornay-G 37-43",
    "sg:city":"Wien",
    "sg:orig_category":"Polizei U Gendarmerie",
    "sg:phone":"+43 4313 131049320",
    "sg:postcode":"1230",
    "sg:province":"Wien",
    "wof:name":"Polizeikommissariat Wien - Wachzimmer",
    "wof:placetype":"venue"
},
  "geometry": {"coordinates":[16.3159408569,48.1317481995],"type":"Point"}
}