{
  "type": "Feature",
  "properties": {
    "addr:full":"Lochbachstr 6 Hard Vorarlberg 6971",
    "addr:housenumber":"6",
    "addr:postcode":"6971",
    "addr:street":"Lochbachstr",
    "iso:country":"AT",
    "sg:address":"Lochbachstr 6",
    "sg:city":"Hard",
    "sg:orig_category":"Architekten",
    "sg:phone":"+43 5574 77447",
    "sg:postcode":"6971",
    "sg:province":"Vorarlberg",
    "wof:name":"FR\u00dcH - ARCHITEKTURB\u00dcRO",
    "wof:placetype":"venue"
},
  "geometry": {"coordinates":[9.6916723251,47.4948883057],"type":"Point"}
}