{
  "type": "Feature",
  "properties": {
    "addr:full":"Schoarerbergstr 44 Henndorf am Wallersee Salzburg 5302",
    "addr:housenumber":"44",
    "addr:postcode":"5302",
    "addr:street":"Schoarerbergstr",
    "iso:country":"AT",
    "sg:address":"Schoarerbergstr 44",
    "sg:city":"Henndorf am Wallersee",
    "sg:orig_category":"Ingenieurkonsulenten / Zivilingenieure",
    "sg:phone":"+43 4362 146581",
    "sg:postcode":"5302",
    "sg:province":"Salzburg",
    "wof:name":"Mandl Heinz Dipl-Ing",
    "wof:placetype":"venue"
},
  "geometry": {"coordinates":[13.1836538315,47.9005203247],"type":"Point"}
}