{
  "type": "Feature",
  "properties": {
    "addr:full":"Gustav-Tschermak-G 7 Wien Wien 1180",
    "addr:housenumber":"7",
    "addr:postcode":"1180",
    "addr:street":"Gustav-Tschermak-G",
    "iso:country":"AT",
    "sg:address":"Gustav-Tschermak-G 7",
    "sg:city":"Wien",
    "sg:orig_category":"Botschaften",
    "sg:phone":"+43 1 476230",
    "sg:postcode":"1180",
    "sg:province":"Wien",
    "wof:name":"Botschaft der Republik Indonesien",
    "wof:placetype":"venue"
},
  "geometry": {"coordinates":[16.3392009735,48.2325057983],"type":"Point"}
}