{
  "type": "Feature",
  "properties": {
    "addr:full":"Nr 107 Rettenegg Steiermark 8674",
    "addr:postcode":"8674",
    "addr:street":"Nr 107",
    "iso:country":"AT",
    "sg:address":"Nr 107",
    "sg:city":"Rettenegg",
    "sg:orig_category":"Stempel",
    "sg:phone":"+43 3173 8281",
    "sg:postcode":"8674",
    "sg:province":"Steiermark",
    "wof:name":"CKW Kunststoffwerk GmbH",
    "wof:placetype":"venue"
},
  "geometry": {"coordinates":[15.7791147232,47.5252799988],"type":"Point"}
}