{
  "type": "Feature",
  "properties": {
    "addr:full":"Klingendrahtg 5 Puntigam Steiermark 8055",
    "addr:housenumber":"5",
    "addr:postcode":"8055",
    "addr:street":"Klingendrahtg",
    "iso:country":"AT",
    "sg:address":"Klingendrahtg 5",
    "sg:city":"Puntigam",
    "sg:orig_category":"Medizintechnik",
    "sg:phone":"+43 316 292553",
    "sg:postcode":"8055",
    "sg:province":"Steiermark",
    "wof:name":"Sanox Pezzi Elfriede",
    "wof:placetype":"venue"
},
  "geometry": {"coordinates":[15.430557251,47.022064209],"type":"Point"}
}