{
  "type": "Feature",
  "properties": {
    "addr:full":"Brauhausstr 18 Schwechat Nieder\u00f6sterreich 2320",
    "addr:housenumber":"18",
    "addr:postcode":"2320",
    "addr:street":"Brauhausstr;Niederoesterreich",
    "iso:country":"AT",
    "sg:address":"Brauhausstr 18",
    "sg:city":"Schwechat",
    "sg:orig_category":"Feuerwehren",
    "sg:phone":"+43 1 70766110",
    "sg:postcode":"2320",
    "sg:province":"Nieder\u00f6sterreich",
    "wof:name":"Freiwillige Feuerwehr Schwechat-Neukettenhof-Rannersdorf",
    "wof:placetype":"venue"
},
  "geometry": {"coordinates":[16.4726104736,48.1411590576],"type":"Point"}
}