{
  "type": "Feature",
  "properties": {
    "addr:full":"Nonntaler Hauptstr 9a Salzburg Salzburg 5020",
    "addr:housenumber":"9a",
    "addr:postcode":"5020",
    "addr:street":"Nonntaler Hauptstr;Salzburg",
    "iso:country":"AT",
    "sg:address":"Nonntaler Hauptstr 9a",
    "sg:city":"Salzburg",
    "sg:orig_category":"Elektromotoren / Reparatur U Wickelei",
    "sg:phone":"+43 662 841140",
    "sg:postcode":"5020",
    "sg:province":"Salzburg",
    "wof:name":"Pomwenger Paul",
    "wof:placetype":"venue"
},
  "geometry": {"coordinates":[13.052939415,47.7956886292],"type":"Point"}
}