{
  "type": "Feature",
  "properties": {
    "addr:full":"Hauptstr 35 Deutsch Brodersdorf Nieder\u00f6sterreich 2443",
    "addr:housenumber":"35",
    "addr:postcode":"2443",
    "addr:street":"Hauptstr",
    "iso:country":"AT",
    "sg:address":"Hauptstr 35",
    "sg:city":"Deutsch Brodersdorf",
    "sg:orig_category":"Forstverwaltungen",
    "sg:phone":"+43 2255 8246",
    "sg:postcode":"2443",
    "sg:province":"Nieder\u00f6sterreich",
    "wof:name":"Esterhazy Forstverwaltung",
    "wof:placetype":"venue"
},
  "geometry": {"coordinates":[16.5189342499,47.9163131714],"type":"Point"}
}