{
  "type": "Feature",
  "properties": {
    "addr:full":"Bahnhofstr 22 Lustenau Vorarlberg 6890",
    "addr:housenumber":"22",
    "addr:postcode":"6890",
    "addr:street":"Bahnhofstr",
    "iso:country":"AT",
    "sg:address":"Bahnhofstr 22",
    "sg:city":"Lustenau",
    "sg:orig_category":"Stickereien",
    "sg:phone":"+43 5577 83652",
    "sg:postcode":"6890",
    "sg:province":"Vorarlberg",
    "wof:name":"Isele Peter",
    "wof:placetype":"venue"
},
  "geometry": {"coordinates":[9.6577301025,47.4412269592],"type":"Point"}
}