{
  "type": "Feature",
  "properties": {
    "iso:country":"AT",
    "sg:address":"Teichweg 2",
    "sg:city":"Gresten",
    "sg:orig_category":"Transportunternehmen",
    "sg:phone":"+43 7487 2255",
    "sg:postcode":"3264",
    "sg:province":"Nieder\u00f6sterreich",
    "wof:name":"Kraml Leopold",
    "wof:placetype":"venue"
},
  "geometry": {"coordinates":[15.0260295868,47.9850082397],"type":"Point"}
}