{
  "type": "Feature",
  "properties": {
    "iso:country":"AT",
    "sg:address":"Schulstr 57",
    "sg:city":"Felixdorf",
    "sg:orig_category":"Steinmetzbetriebe",
    "sg:phone":"+43 4369 910103118",
    "sg:postcode":"2603",
    "sg:province":"Nieder\u00f6sterreich",
    "wof:name":"Reindl Christian Ing",
    "wof:placetype":"venue"
},
  "geometry": {"coordinates":[16.2483444214,47.874382019],"type":"Point"}
}