{
  "type": "Feature",
  "properties": {
    "addr:full":"Hugo-Wolf-Str 3 Kapfenberg Steiermark 8605",
    "addr:housenumber":"3",
    "addr:postcode":"8605",
    "addr:street":"Hugo-Wolf-Str",
    "iso:country":"AT",
    "sg:address":"Hugo-Wolf-Str 3",
    "sg:city":"Kapfenberg",
    "sg:orig_category":"Lebensmittel / Einzelhandel",
    "sg:phone":"+43 3862 35990",
    "sg:postcode":"8605",
    "sg:province":"Steiermark",
    "wof:name":"Billa AG",
    "wof:placetype":"venue"
},
  "geometry": {"coordinates":[15.2912454605,47.4438438416],"type":"Point"}
}