{
  "type": "Feature",
  "properties": {
    "addr:full":"Freindorf 8 Waizenkirchen Ober\u00f6sterreich 4730",
    "addr:housenumber":"8",
    "addr:postcode":"4730",
    "addr:street":"Freindorf",
    "iso:country":"AT",
    "sg:address":"Freindorf 8",
    "sg:city":"Waizenkirchen",
    "sg:orig_category":"Autoreparatur",
    "sg:phone":"+43 7277 3378",
    "sg:postcode":"4730",
    "sg:province":"Ober\u00f6sterreich",
    "wof:name":"Brunnmayr Gerhard",
    "wof:placetype":"venue"
},
  "geometry": {"coordinates":[13.8224849701,48.3503074646],"type":"Point"}
}