{
  "type": "Feature",
  "properties": {
    "addr:full":"Loretostrasse 4-8 Radstadt Salzburg 5550",
    "addr:housenumber":"4-8",
    "addr:postcode":"5550",
    "addr:street":"Loretostrasse;Salzburg",
    "iso:country":"AT",
    "sg:address":"Loretostrasse 4-8",
    "sg:city":"Radstadt",
    "sg:classifiers":[
        {
            "category":"Recreation",
            "subcategory":"Gardens",
            "type":"Entertainment"
        }
    ],
    "sg:phone":"+43 6452 71930",
    "sg:postcode":"5550",
    "sg:province":"Salzburg",
    "sg:tags":[
        "shredder"
    ],
    "sg:website":"kohlbrat-bunz.com",
    "wof:name":"Kohlbrat & Bunz GmbH",
    "wof:placetype":"venue"
},
  "geometry": {"coordinates":[13.4607162476,47.3859138489],"type":"Point"}
}