{
  "type": "Feature",
  "properties": {
    "addr:full":"Sch\u00e4rdinger Tor 2 Ried im Innkreis Ober\u00f6sterreich 4910",
    "addr:housenumber":"2",
    "addr:postcode":"4910",
    "addr:street":"Schaerdinger Tor",
    "iso:country":"AT",
    "sg:address":"Sch\u00e4rdinger Tor 2",
    "sg:city":"Ried im Innkreis",
    "sg:orig_category":"Freizeitangebote U -Einrichtungen",
    "sg:phone":"+43 4366 43428079",
    "sg:postcode":"4910",
    "sg:province":"Ober\u00f6sterreich",
    "wof:name":"Schauberger Bruno - Vergn\u00fcgungsbetrieb",
    "wof:placetype":"venue"
},
  "geometry": {"coordinates":[13.4879541397,48.210773468],"type":"Point"}
}