{
  "type": "Feature",
  "properties": {
    "addr:full":"Kremsegger Strasse 20 Kremsm\u00fcnster Ober\u00f6sterreich 4550",
    "addr:housenumber":"20",
    "addr:postcode":"4550",
    "addr:street":"Kremsegger Strasse;Oberoesterreich",
    "iso:country":"AT",
    "sg:address":"Kremsegger Strasse 20",
    "sg:city":"Kremsm\u00fcnster",
    "sg:classifiers":[
        {
            "category":"Manufacturing",
            "subcategory":"Jewelry",
            "type":"Manufacturing & Wholesale Goods"
        }
    ],
    "sg:phone":"+43 7583 50100",
    "sg:postcode":"4550",
    "sg:province":"Ober\u00f6sterreich",
    "sg:tags":[
        "bangle",
        "bracelet"
    ],
    "wof:name":"BERLA Modeschmuck Ges.m.b.H.",
    "wof:placetype":"venue"
},
  "geometry": {"coordinates":[7.4943199158,50.8699913025],"type":"Point"}
}