{
  "type": "Feature",
  "properties": {
    "addr:full":"Alois-Schrott-Str 49 Innsbruck Tirol 6020",
    "addr:housenumber":"49",
    "addr:postcode":"6020",
    "addr:street":"Alois-Schrott-Str;Tirol",
    "iso:country":"AT",
    "sg:address":"Alois-Schrott-Str 49",
    "sg:city":"Innsbruck",
    "sg:orig_category":"Bibliotheken",
    "sg:phone":"+43 512 263557",
    "sg:postcode":"6020",
    "sg:province":"Tirol",
    "wof:name":"\u00f6ffentliche B\u00fccherei d Pfarre",
    "wof:placetype":"venue"
},
  "geometry": {"coordinates":[11.4297790527,47.2833518982],"type":"Point"}
}