{
  "type": "Feature",
  "properties": {
    "addr:full":"Amlacher Weg 43/1 Spittal an der Drau K\u00e4rnten 9800",
    "addr:housenumber":"43 / 1",
    "addr:postcode":"9800",
    "addr:street":"Amlacher Weg;Kaernten",
    "iso:country":"AT",
    "sg:address":"Amlacher Weg 43/1",
    "sg:city":"Spittal an der Drau",
    "sg:orig_category":"Holzgro\u00c3\u0178handel",
    "sg:phone":"+43 4762 61979",
    "sg:postcode":"9800",
    "sg:province":"K\u00e4rnten",
    "wof:name":"Wandaller Willibald",
    "wof:placetype":"venue"
},
  "geometry": {"coordinates":[13.5022096634,46.7867088318],"type":"Point"}
}