{
  "type": "Feature",
  "properties": {
    "iso:country":"AT",
    "sg:address":"Hauptstr 101",
    "sg:city":"Eichgraben",
    "sg:orig_category":"Lebensmittel / Einzelhandel",
    "sg:phone":"+43 2773 46239",
    "sg:postcode":"3032",
    "sg:province":"Nieder\u00f6sterreich",
    "wof:name":"Wohlmuth Fritz",
    "wof:placetype":"venue"
},
  "geometry": {"coordinates":[15.9794797897,48.167881012],"type":"Point"}
}