{
  "type": "Feature",
  "properties": {
    "addr:full":"Glaser Str 19 Aigen Salzburg 5026",
    "addr:postcode":"5026",
    "addr:street":"Str 19;Salzburg",
    "iso:country":"AT",
    "sg:address":"Glaser Str 19",
    "sg:city":"Aigen",
    "sg:orig_category":"Holzbe U -Verarbeitung",
    "sg:phone":"+43 4366 48206071",
    "sg:postcode":"5026",
    "sg:province":"Salzburg",
    "sg:website":"lohnschnitt.at",
    "wof:name":"Mobiler Lohnschnitt Resch & Gmachl OEG",
    "wof:placetype":"venue"
},
  "geometry": {"coordinates":[13.0858983994,47.7779769897],"type":"Point"}
}