{
  "type": "Feature",
  "properties": {
    "addr:full":"Tragweiner Str 30 Pregarten Ober\u00f6sterreich 4230",
    "addr:postcode":"4230",
    "addr:street":"Str 30",
    "iso:country":"AT",
    "sg:address":"Tragweiner Str 30",
    "sg:city":"Pregarten",
    "sg:orig_category":"Beteiligungen U Finanzierungen",
    "sg:phone":"+43 4369 911740258",
    "sg:postcode":"4230",
    "sg:province":"Ober\u00f6sterreich",
    "wof:name":"fit for finance FinanzberatungsgmbH",
    "wof:placetype":"venue"
},
  "geometry": {"coordinates":[14.5337057114,48.3539848328],"type":"Point"}
}