{
  "type": "Feature",
  "properties": {
    "addr:full":"Dietrichgasse 51/18  Wien Wien 1030",
    "addr:housenumber":"51 / 18",
    "addr:postcode":"1030",
    "addr:street":"Dietrichgasse",
    "iso:country":"AT",
    "sg:address":"Dietrichgasse 51/18 ",
    "sg:city":"Wien",
    "sg:classifiers":[
        {
            "category":"Manufacturing",
            "subcategory":"Food",
            "type":"Manufacturing & Wholesale Goods"
        }
    ],
    "sg:phone":"+43 4317 1215550",
    "sg:postcode":"1030",
    "sg:province":"Wien",
    "sg:tags":[
        "equipment",
        "processing",
        "-",
        "machinery"
    ],
    "wof:name":"ZANKL GESMBH",
    "wof:placetype":"venue"
},
  "geometry": {"coordinates":[16.4058456421,48.1982688904],"type":"Point"}
}