{
  "type": "Feature",
  "properties": {
    "addr:full":"Nr 1 Lichtenegg Nieder\u00f6sterreich 2813",
    "addr:postcode":"2813",
    "addr:street":"Nr;Lichtenegg",
    "iso:country":"AT",
    "sg:address":"Nr 1",
    "sg:city":"Lichtenegg",
    "sg:orig_category":"Non-Classified Establishments",
    "sg:phone":"+43 2643 2263",
    "sg:postcode":"2813",
    "sg:province":"Nieder\u00f6sterreich",
    "wof:name":"Mandl Johann KG",
    "wof:placetype":"venue"
},
  "geometry": {"coordinates":[12.3425445557,48.0317192078],"type":"Point"}
}