{
  "type": "Feature",
  "properties": {
    "iso:country":"AT",
    "sg:address":"Obere \u00f6dlitzer Str 59",
    "sg:city":"Berndorf",
    "sg:orig_category":"Autolackierereien",
    "sg:phone":"+43 2672 82668",
    "sg:postcode":"2560",
    "sg:province":"Nieder\u00f6sterreich",
    "wof:name":"Klein Wolfgang",
    "wof:placetype":"venue"
},
  "geometry": {"coordinates":[16.1051998138,47.8947486877],"type":"Point"}
}