{
  "type": "Feature",
  "properties": {
    "iso:country":"AT",
    "sg:address":"Gunskirchener Str. 80 ",
    "sg:city":"Wels",
    "sg:classifiers":[
        {
            "category":"Farming",
            "subcategory":"Livestock Farm",
            "type":"Manufacturing & Wholesale Goods"
        }
    ],
    "sg:phone":"+43 4372 42684970",
    "sg:postcode":"4600",
    "sg:province":"Ober\u00f6sterreich",
    "sg:tags":[
        "agriculture"
    ],
    "wof:name":"BELLAFLORA GARTENCENTER GES.MBH",
    "wof:placetype":"venue"
},
  "geometry": {"coordinates":[13.9750747681,48.1482620239],"type":"Point"}
}