{
  "type": "Feature",
  "properties": {
    "addr:full":"Drahtgasse 2/10 Wien Wien 1010",
    "addr:housenumber":"2 / 10",
    "addr:postcode":"1010",
    "addr:street":"Drahtgasse",
    "iso:country":"AT",
    "sg:address":"Drahtgasse 2/10",
    "sg:city":"Wien",
    "sg:orig_category":"Online Documentations",
    "sg:phone":"+43 1 53586450",
    "sg:postcode":"1010",
    "sg:province":"Wien",
    "wof:name":"Dipl.-Kfm. Reinhilde Hohenberg GmbH",
    "wof:placetype":"venue"
},
  "geometry": {"coordinates":[16.3686485291,48.2113990784],"type":"Point"}
}