{
  "type": "Feature",
  "properties": {
    "addr:full":"Bahnhofstr 22 Bruck an der Mur Steiermark 8600",
    "addr:postcode":"8600",
    "addr:street":"Bahnhofstr 22",
    "iso:country":"AT",
    "sg:address":"Bahnhofstr 22",
    "sg:city":"Bruck an der Mur",
    "sg:classifiers":[
        {
            "category":"Restaurant",
            "type":"Food & Drink"
        }
    ],
    "sg:phone":"+43 3862 58020",
    "sg:postcode":"8600",
    "sg:province":"Steiermark",
    "wof:name":"Bahnhofrestaurant Zeismann",
    "wof:placetype":"venue"
},
  "geometry": {"coordinates":[15.2789459229,47.4132881165],"type":"Point"}
}