{
  "type": "Feature",
  "properties": {
    "addr:full":"Hauptstr 62 Deutschkreutz Burgenland 7301",
    "addr:housenumber":"62",
    "addr:postcode":"7301",
    "addr:street":"Hauptstr",
    "iso:country":"AT",
    "sg:address":"Hauptstr 62",
    "sg:city":"Deutschkreutz",
    "sg:orig_category":"Friseure U Frisiersalons",
    "sg:phone":"+43 2613 80226",
    "sg:postcode":"7301",
    "sg:province":"Burgenland",
    "wof:name":"Strehn Gerhard",
    "wof:placetype":"venue"
},
  "geometry": {"coordinates":[16.6261844635,47.5987014771],"type":"Point"}
}