{
  "type": "Feature",
  "properties": {
    "iso:country":"AT",
    "sg:address":"Kurbadstr. 12",
    "sg:city":"Wien",
    "sg:classifiers":[
        {
            "category":"Travel",
            "subcategory":"Travel Agent",
            "type":"Entertainment"
        }
    ],
    "sg:phone":"+43 4316 80099500",
    "sg:postcode":"1100",
    "sg:province":"Wien",
    "sg:tags":[
        "business"
    ],
    "wof:name":"OBERLAA KONDITOREI GMBH & CO. KG",
    "wof:placetype":"venue"
},
  "geometry": {"coordinates":[16.4058761597,48.1418113708],"type":"Point"}
}