{
  "type": "Feature",
  "properties": {
    "addr:full":"Unterfreundorf 41 St. Marienkirchen an der Polsenz Ober\u00f6sterreich 4076",
    "addr:housenumber":"41",
    "addr:postcode":"4076",
    "addr:street":"Unterfreundorf",
    "iso:country":"AT",
    "sg:address":"Unterfreundorf 41",
    "sg:city":"St. Marienkirchen an der Polsenz",
    "sg:orig_category":"Schwimmbecken",
    "sg:phone":"+43 4372 4947673",
    "sg:postcode":"4076",
    "sg:province":"Ober\u00f6sterreich",
    "wof:name":"Schwimmbecken Sauna Gonglach",
    "wof:placetype":"venue"
},
  "geometry": {"coordinates":[13.9563312531,48.2566184998],"type":"Point"}
}