{
  "type": "Feature",
  "properties": {
    "iso:country":"AT",
    "sg:address":"Hebbelpl. 5",
    "sg:city":"Wien",
    "sg:classifiers":[
        {
            "category":"Food & Beverages",
            "subcategory":"Groceries & Convenience Stores",
            "type":"Retail Goods"
        }
    ],
    "sg:phone":"+43 4316 0182",
    "sg:postcode":"1100",
    "sg:province":"Wien",
    "sg:tags":[
        "product",
        "related"
    ],
    "wof:name":"LINDT & SPR\u00dcNGLI AUSTRIA GMBH",
    "wof:placetype":"venue"
},
  "geometry": {"coordinates":[16.3783054352,48.1662826538],"type":"Point"}
}