{
  "type": "Feature",
  "properties": {
    "addr:full":"Kremser Str 13 Ziersdorf Nieder\u00f6sterreich 3710",
    "addr:housenumber":"13",
    "addr:postcode":"3710",
    "addr:street":"Str",
    "iso:country":"AT",
    "sg:address":"Kremser Str 13",
    "sg:city":"Ziersdorf",
    "sg:orig_category":"Schlossereien",
    "sg:phone":"+43 2956 2286",
    "sg:postcode":"3710",
    "sg:province":"Nieder\u00f6sterreich",
    "wof:name":"Firnkranz Josef",
    "wof:placetype":"venue"
},
  "geometry": {"coordinates":[15.9283485413,48.5259284973],"type":"Point"}
}