{
  "type": "Feature",
  "properties": {
    "addr:full":"Handwerksstr 3 Villach K\u00e4rnten 9500",
    "addr:housenumber":"3",
    "addr:postcode":"9500",
    "addr:street":"Handwerksstr;Kaernten",
    "iso:country":"AT",
    "sg:address":"Handwerksstr 3",
    "sg:city":"Villach",
    "sg:orig_category":"Autospenglereien",
    "sg:phone":"+43 4342 4233533",
    "sg:postcode":"9500",
    "sg:province":"K\u00e4rnten",
    "wof:name":"Kenzian Othmar",
    "wof:placetype":"venue"
},
  "geometry": {"coordinates":[13.8455753326,46.5958366394],"type":"Point"}
}