{
  "type": "Feature",
  "properties": {
    "addr:full":"Trefflinger Str 19 Seeboden K\u00e4rnten 9871",
    "addr:housenumber":"19",
    "addr:postcode":"9871",
    "addr:street":"Str;Kaernten",
    "iso:country":"AT",
    "sg:address":"Trefflinger Str 19",
    "sg:city":"Seeboden",
    "sg:orig_category":"Pensionen / Privatzimmer",
    "sg:phone":"+43 4762 82706",
    "sg:postcode":"9871",
    "sg:province":"K\u00e4rnten",
    "wof:name":"G\u00e4stehaus Maria",
    "wof:placetype":"venue"
},
  "geometry": {"coordinates":[13.5148906708,46.8190383911],"type":"Point"}
}