{
  "type": "Feature",
  "properties": {
    "addr:full":"Grazer Pl 9 F\u00fcrstenfeld Steiermark 8280",
    "addr:housenumber":"9",
    "addr:postcode":"8280",
    "addr:street":"Grazer Pl",
    "iso:country":"AT",
    "sg:address":"Grazer Pl 9",
    "sg:city":"F\u00fcrstenfeld",
    "sg:orig_category":"Lebensmittel / Einzelhandel",
    "sg:phone":"+43 4333 8254550",
    "sg:postcode":"8280",
    "sg:province":"Steiermark",
    "wof:name":"Billa AG",
    "wof:placetype":"venue"
},
  "geometry": {"coordinates":[16.0737762451,47.0520133972],"type":"Point"}
}