{
  "type": "Feature",
  "properties": {
    "addr:full":"Badener Str. 9-11  Traiskirchen Nieder\u00f6sterreich 2514",
    "addr:housenumber":"9-11",
    "addr:postcode":"2514",
    "addr:street":"Badener Str.;Niederoesterreich",
    "iso:country":"AT",
    "sg:address":"Badener Str. 9-11 ",
    "sg:city":"Traiskirchen",
    "sg:classifiers":[
        {
            "category":"Manufacturing",
            "subcategory":"Rubber & Plastics",
            "type":"Manufacturing & Wholesale Goods"
        }
    ],
    "sg:phone":"+43 4322 52524220",
    "sg:postcode":"2514",
    "sg:province":"Nieder\u00f6sterreich",
    "wof:name":"\u00d6STERR. LINOLEUM-, WACHSTUCH- UND KUNSTLEDERFABRIK AG",
    "wof:placetype":"venue"
},
  "geometry": {"coordinates":[16.2801113129,48.0218544006],"type":"Point"}
}