{
  "type": "Feature",
  "properties": {
    "addr:full":"Erlauftalstr 34 Purgstall an der Erlauf Nieder\u00f6sterreich 3251",
    "addr:housenumber":"34",
    "addr:postcode":"3251",
    "addr:street":"Erlauftalstr;Niederoesterreich",
    "iso:country":"AT",
    "sg:address":"Erlauftalstr 34",
    "sg:city":"Purgstall an der Erlauf",
    "sg:orig_category":"Tankstellen",
    "sg:phone":"+43 4374 897024",
    "sg:postcode":"3251",
    "sg:province":"Nieder\u00f6sterreich",
    "wof:name":"OMV AG",
    "wof:placetype":"venue"
},
  "geometry": {"coordinates":[15.1392040253,48.0619850159],"type":"Point"}
}