{
  "type": "Feature",
  "properties": {
    "addr:full":"Nr 17 Mailberg Nieder\u00f6sterreich 2024",
    "addr:postcode":"2024",
    "addr:street":"Nr;Mailberg",
    "iso:country":"AT",
    "sg:address":"Nr 17",
    "sg:city":"Mailberg",
    "sg:orig_category":"Volksschulen",
    "sg:phone":"+43 2943 2360",
    "sg:postcode":"2024",
    "sg:province":"Nieder\u00f6sterreich",
    "wof:name":"Volksschule d Souver\u00e4nen Malteser Ritterordens",
    "wof:placetype":"venue"
},
  "geometry": {"coordinates":[16.1827259064,48.6727828979],"type":"Point"}
}