{
  "type": "Feature",
  "properties": {
    "addr:full":"Hauptstr 6 Hainfeld Nieder\u00f6sterreich 3170",
    "addr:housenumber":"6",
    "addr:postcode":"3170",
    "addr:street":"Hauptstr",
    "iso:country":"AT",
    "sg:address":"Hauptstr 6",
    "sg:city":"Hainfeld",
    "sg:orig_category":"Juwelen, Gold- U Silberwaren / Einzelhandel",
    "sg:phone":"+43 4327 642422",
    "sg:postcode":"3170",
    "sg:province":"Nieder\u00f6sterreich",
    "wof:name":"P\u00f6lzgruber Franz",
    "wof:placetype":"venue"
},
  "geometry": {"coordinates":[15.7733402252,48.0351638794],"type":"Point"}
}