{
  "type": "Feature",
  "properties": {
    "addr:full":"Brunneng 2 Raggendorf Nieder\u00f6sterreich 2215",
    "addr:housenumber":"2",
    "addr:postcode":"2215",
    "addr:street":"Brunneng;Niederoesterreich",
    "iso:country":"AT",
    "sg:address":"Brunneng 2",
    "sg:city":"Raggendorf",
    "sg:orig_category":"Massagen",
    "sg:phone":"+43 2289 3657",
    "sg:postcode":"2215",
    "sg:province":"Nieder\u00f6sterreich",
    "wof:name":"Grillitsch Martina - Martinas Mobile Massage",
    "wof:placetype":"venue"
},
  "geometry": {"coordinates":[16.654378891,48.3960189819],"type":"Point"}
}