{
  "type": "Feature",
  "properties": {
    "iso:country":"AT",
    "sg:address":"Maria Theresien-Str 57",
    "sg:city":"Innsbruck",
    "sg:classifiers":[
        {
            "category":"Professional",
            "subcategory":"Computer Services",
            "type":"Services"
        }
    ],
    "sg:phone":"+43 512 53510",
    "sg:postcode":"6020",
    "sg:province":"Tirol",
    "sg:tags":[
        "software"
    ],
    "wof:name":"TIScover AG Travel Information Systems",
    "wof:placetype":"venue"
},
  "geometry": {"coordinates":[11.394859314,47.2627563477],"type":"Point"}
}