{
  "type": "Feature",
  "properties": {
    "addr:full":"Firmiang 5 Wien Wien 1130",
    "addr:housenumber":"5",
    "addr:postcode":"1130",
    "addr:street":"Firmiang",
    "iso:country":"AT",
    "sg:address":"Firmiang 5",
    "sg:city":"Wien",
    "sg:orig_category":"Restaurants: Italienisch",
    "sg:phone":"+43 1 8777309",
    "sg:postcode":"1130",
    "sg:province":"Wien",
    "wof:name":"Pizzeria Punto Rosso",
    "wof:placetype":"venue"
},
  "geometry": {"coordinates":[16.2670707703,48.1887321472],"type":"Point"}
}