{
  "type": "Feature",
  "properties": {
    "addr:full":"Arena am Waldfeld 15 Fohnsdorf Steiermark 8753",
    "addr:housenumber":"15",
    "addr:postcode":"8753",
    "addr:street":"Arena Am Waldfeld",
    "iso:country":"AT",
    "sg:address":"Arena am Waldfeld 15",
    "sg:city":"Fohnsdorf",
    "sg:orig_category":"Spielwaren U Spiele",
    "sg:phone":"+43 3572 468100",
    "sg:postcode":"8753",
    "sg:province":"Steiermark",
    "wof:name":"Spiele Schachner GmbH",
    "wof:placetype":"venue"
},
  "geometry": {"coordinates":[14.6788835526,47.1845626831],"type":"Point"}
}