{
  "type": "Feature",
  "properties": {
    "iso:country":"AT",
    "sg:address":"Hammerbachg 4",
    "sg:city":"Kindberg",
    "sg:orig_category":"Holzgro\u00c3\u0178handel",
    "sg:phone":"+43 4338 6522250",
    "sg:postcode":"8650",
    "sg:province":"Steiermark",
    "wof:name":"Willenshofer Heribert GesmbH",
    "wof:placetype":"venue"
},
  "geometry": {"coordinates":[15.4446601868,47.5009269714],"type":"Point"}
}