{
  "type": "Feature",
  "properties": {
    "iso:country":"AT",
    "sg:address":"Steinweg 23",
    "sg:city":"Traun",
    "sg:orig_category":"\u00c3\u201enderungsschneidereien",
    "sg:phone":"+43 4366 43830963",
    "sg:postcode":"4050",
    "sg:province":"Ober\u00f6sterreich",
    "wof:name":"Scacco Silvia",
    "wof:placetype":"venue"
},
  "geometry": {"coordinates":[14.207526207,48.2100524902],"type":"Point"}
}