{
  "type": "Feature",
  "properties": {
    "addr:full":"Nr 3 Gerersdorf Burgenland 7542",
    "addr:postcode":"7542",
    "addr:street":"Nr",
    "iso:country":"AT",
    "sg:address":"Nr 3",
    "sg:city":"Gerersdorf",
    "sg:orig_category":"Appartements / Ferienwohnungen",
    "sg:phone":"+43 4333 2832680",
    "sg:postcode":"7542",
    "sg:province":"Burgenland",
    "wof:name":"Luipersbeck Franz",
    "wof:placetype":"venue"
},
  "geometry": {"coordinates":[16.252620697,47.0685806274],"type":"Point"}
}