{
  "type": "Feature",
  "properties": {
    "addr:full":"Franz-Reisch-Str 8 Kitzb\u00fchel Tirol 6370",
    "addr:housenumber":"8",
    "addr:postcode":"6370",
    "addr:street":"Franz-Reisch-Str;Tirol",
    "iso:country":"AT",
    "sg:address":"Franz-Reisch-Str 8",
    "sg:city":"Kitzb\u00fchel",
    "sg:classifiers":[
        {
            "category":"Travel",
            "subcategory":"Hotels & Motels",
            "type":"Entertainment"
        }
    ],
    "sg:phone":"+43 4353 56622930",
    "sg:postcode":"6370",
    "sg:province":"Tirol",
    "wof:name":"Hotel Licht",
    "wof:placetype":"venue"
},
  "geometry": {"coordinates":[12.3883018494,47.4462203979],"type":"Point"}
}