{
  "type": "Feature",
  "properties": {
    "addr:full":"Rathauspl 3 Kitzb\u00fchel Tirol 6370",
    "addr:housenumber":"3",
    "addr:postcode":"6370",
    "addr:street":"Rathauspl;Tirol",
    "iso:country":"AT",
    "sg:address":"Rathauspl 3",
    "sg:city":"Kitzb\u00fchel",
    "sg:orig_category":"Trachtenbekleidung",
    "sg:phone":"+43 5356 62486",
    "sg:postcode":"6370",
    "sg:province":"Tirol",
    "wof:name":"Eder Helmut - Trachten-Sport-Couture",
    "wof:placetype":"venue"
},
  "geometry": {"coordinates":[12.390704155,47.446395874],"type":"Point"}
}