{
  "type": "Feature",
  "properties": {
    "addr:full":"\u00f6denburger Str 72 Andau Burgenland 7163",
    "addr:housenumber":"72",
    "addr:postcode":"7163",
    "addr:street":"Str",
    "iso:country":"AT",
    "sg:address":"\u00f6denburger Str 72",
    "sg:city":"Andau",
    "sg:orig_category":"Autohandel",
    "sg:phone":"+43 2176 23460",
    "sg:postcode":"7163",
    "sg:province":"Burgenland",
    "wof:name":"Autohaus Erich Horvath",
    "wof:placetype":"venue"
},
  "geometry": {"coordinates":[17.0324306488,47.7754859924],"type":"Point"}
}