{
  "type": "Feature",
  "properties": {
    "iso:country":"AT",
    "sg:address":"Ignaz-Glaser-Str 48",
    "sg:city":"B\u00fcrmoos",
    "sg:orig_category":"Lebensmittel / Einzelhandel",
    "sg:phone":"+43 6274 77060",
    "sg:postcode":"5111",
    "sg:province":"Salzburg",
    "wof:name":"ADEG Contra Markt",
    "wof:placetype":"venue"
},
  "geometry": {"coordinates":[12.9212112427,47.9832420349],"type":"Point"}
}