{
  "type": "Feature",
  "properties": {
    "addr:full":"Haager Str 46 Steyr Ober\u00f6sterreich 4400",
    "addr:housenumber":"46",
    "addr:postcode":"4400",
    "addr:street":"Haager Str;Oberoesterreich",
    "iso:country":"AT",
    "sg:address":"Haager Str 46",
    "sg:city":"Steyr",
    "sg:orig_category":"Eisenwaren",
    "sg:phone":"+43 7252 7130",
    "sg:postcode":"4400",
    "sg:province":"Ober\u00f6sterreich",
    "wof:name":"Gr\u00fcndler GmbH",
    "wof:placetype":"venue"
},
  "geometry": {"coordinates":[14.4505395889,48.0569496155],"type":"Point"}
}