{
  "type": "Feature",
  "properties": {
    "addr:full":"Dorfpl 79-80 F\u00fcgen Tirol 6263",
    "addr:housenumber":"79-80",
    "addr:postcode":"6263",
    "addr:street":"Fuegen Tirol",
    "iso:country":"AT",
    "sg:address":"Dorfpl 79-80",
    "sg:city":"F\u00fcgen",
    "sg:classifiers":[
        {
            "category":"Travel",
            "subcategory":"Hotels & Motels",
            "type":"Entertainment"
        }
    ],
    "sg:phone":"+43 5288 632120",
    "sg:postcode":"6263",
    "sg:province":"Tirol",
    "wof:name":"Hotel zur Post",
    "wof:placetype":"venue"
},
  "geometry": {"coordinates":[11.8484210968,47.3464775085],"type":"Point"}
}