{
  "type": "Feature",
  "properties": {
    "addr:full":"Klopstockg. 48  Wien Wien 1170",
    "addr:housenumber":"48",
    "addr:postcode":"1170",
    "addr:street":"Klopstockg.",
    "iso:country":"AT",
    "sg:address":"Klopstockg. 48 ",
    "sg:city":"Wien",
    "sg:classifiers":[
        {
            "category":"Manufacturing",
            "subcategory":"Metals",
            "type":"Manufacturing & Wholesale Goods"
        }
    ],
    "sg:phone":"+43 4314 8515250",
    "sg:postcode":"1170",
    "sg:province":"Wien",
    "sg:tags":[
        "metallurgy",
        "metalworking"
    ],
    "wof:name":"ANDREAS GR\u00dcNTHAL GESMBH",
    "wof:placetype":"venue"
},
  "geometry": {"coordinates":[16.3238925934,48.2192993164],"type":"Point"}
}