{
  "type": "Feature",
  "properties": {
    "iso:country":"AT",
    "sg:address":"Wachtberg 14",
    "sg:city":"Behamberg",
    "sg:orig_category":"Handelsagenturen",
    "sg:phone":"+43 7252 76292",
    "sg:postcode":"4441",
    "sg:province":"Nieder\u00f6sterreich",
    "wof:name":"Wakolbinger Karl",
    "wof:placetype":"venue"
},
  "geometry": {"coordinates":[14.4615306854,48.0458908081],"type":"Point"}
}