{
  "type": "Feature",
  "properties": {
    "addr:full":"Bauernmarkt 10 Wien Wien 1010",
    "addr:housenumber":"10",
    "addr:postcode":"1010",
    "addr:street":"Bauernmarkt",
    "iso:country":"AT",
    "sg:address":"Bauernmarkt 10",
    "sg:city":"Wien",
    "sg:orig_category":"Installationsunternehmen",
    "sg:phone":"+43 1 5331430",
    "sg:postcode":"1010",
    "sg:province":"Wien",
    "wof:name":"Stieg Peter GesmbH",
    "wof:placetype":"venue"
},
  "geometry": {"coordinates":[16.3725128174,48.2097816467],"type":"Point"}
}