{
  "type": "Feature",
  "properties": {
    "addr:full":"St Martiner Str 59 Villach K\u00e4rnten 9500",
    "addr:housenumber":"59",
    "addr:postcode":"9500",
    "addr:street":"St;Str;Kaernten",
    "iso:country":"AT",
    "sg:address":"St Martiner Str 59",
    "sg:city":"Villach",
    "sg:orig_category":"Blumeneinzelhandel, Garten- U Landschaftsgestaltung",
    "sg:phone":"+43 4242 56296",
    "sg:postcode":"9500",
    "sg:province":"K\u00e4rnten",
    "wof:name":"M\u00f6lzer Walter Ing",
    "wof:placetype":"venue"
},
  "geometry": {"coordinates":[13.8306703568,46.6193199158],"type":"Point"}
}