{
  "type": "Feature",
  "properties": {
    "addr:full":"Montang 9 Kindberg Steiermark 8650",
    "addr:housenumber":"9",
    "addr:postcode":"8650",
    "addr:street":"Montang",
    "iso:country":"AT",
    "sg:address":"Montang 9",
    "sg:city":"Kindberg",
    "sg:orig_category":"Lastkraftwagen",
    "sg:phone":"+43 4338 6547133",
    "sg:postcode":"8650",
    "sg:province":"Steiermark",
    "wof:name":"Fr\u00fchwirth Oliver Ing GesmbH",
    "wof:placetype":"venue"
},
  "geometry": {"coordinates":[15.4320859909,47.4954605103],"type":"Point"}
}