{
  "type": "Feature",
  "properties": {
    "addr:full":"Koling 1/12 Wien Wien 1090",
    "addr:housenumber":"1 / 12",
    "addr:postcode":"1090",
    "addr:street":"Koling",
    "iso:country":"AT",
    "sg:address":"Koling 1/12",
    "sg:city":"Wien",
    "sg:orig_category":"Forschungsinstitute",
    "sg:phone":"+43 1 31063250",
    "sg:postcode":"1090",
    "sg:province":"Wien",
    "wof:name":"Synthesis Forschung GesmbH",
    "wof:placetype":"venue"
},
  "geometry": {"coordinates":[16.3614025116,48.2154579163],"type":"Point"}
}