{
  "type": "Feature",
  "properties": {
    "addr:full":"Zamenhofstr 3 Linz Ober\u00f6sterreich 4020",
    "addr:housenumber":"3",
    "addr:postcode":"4020",
    "addr:street":"Zamenhofstr",
    "iso:country":"AT",
    "sg:address":"Zamenhofstr 3",
    "sg:city":"Linz",
    "sg:orig_category":"Dachdeckereien",
    "sg:phone":"+43 4373 2661215",
    "sg:postcode":"4020",
    "sg:province":"Ober\u00f6sterreich",
    "wof:name":"Anzinger Egon Dachdeckerei u Spenglerei GmbH",
    "wof:placetype":"venue"
},
  "geometry": {"coordinates":[14.3145608902,48.2893104553],"type":"Point"}
}