{
  "type": "Feature",
  "properties": {
    "addr:full":"Hauptstr 36 Himberg Nieder\u00f6sterreich 2325",
    "addr:housenumber":"36",
    "addr:postcode":"2325",
    "addr:street":"Hauptstr",
    "iso:country":"AT",
    "sg:address":"Hauptstr 36",
    "sg:city":"Himberg",
    "sg:orig_category":"Friseure U Frisiersalons",
    "sg:phone":"+43 4322 3586033",
    "sg:postcode":"2325",
    "sg:province":"Nieder\u00f6sterreich",
    "wof:name":"Salon Inge Inh Zrunek Ingeborg GesmbH",
    "wof:placetype":"venue"
},
  "geometry": {"coordinates":[16.4394645691,48.083770752],"type":"Point"}
}