{
  "type": "Feature",
  "properties": {
    "addr:full":"Dorf 44 Going am Wilden Kaiser Tirol 6353",
    "addr:housenumber":"44",
    "addr:postcode":"6353",
    "addr:street":"Dorf;Tirol",
    "iso:country":"AT",
    "sg:address":"Dorf 44",
    "sg:city":"Going am Wilden Kaiser",
    "sg:orig_category":"Pensionen / Privatzimmer",
    "sg:phone":"+43 4366 41812762",
    "sg:postcode":"6353",
    "sg:province":"Tirol",
    "wof:name":"Pension Kaufmann",
    "wof:placetype":"venue"
},
  "geometry": {"coordinates":[12.3336324692,47.5142402649],"type":"Point"}
}