{
  "type": "Feature",
  "properties": {
    "addr:full":"Parkstr 6 Mooskirchen Steiermark 8562",
    "addr:housenumber":"6",
    "addr:postcode":"8562",
    "addr:street":"Parkstr",
    "iso:country":"AT",
    "sg:address":"Parkstr 6",
    "sg:city":"Mooskirchen",
    "sg:orig_category":"Physikalische Institute",
    "sg:phone":"+43 3137 30960",
    "sg:postcode":"8562",
    "sg:province":"Steiermark",
    "wof:name":"Institut f\u00fcr Physikalische Behandlungen Andreas Herz",
    "wof:placetype":"venue"
},
  "geometry": {"coordinates":[15.2848472595,46.9826393127],"type":"Point"}
}