{
  "type": "Feature",
  "properties": {
    "iso:country":"AT",
    "sg:address":"Oberes Bahnfeld",
    "sg:city":"Raasdorf",
    "sg:orig_category":"Transportunternehmen",
    "sg:phone":"+43 699 11205506",
    "sg:postcode":"2281",
    "sg:province":"Nieder\u00f6sterreich",
    "wof:name":"KESKE GmbH",
    "wof:placetype":"venue"
},
  "geometry": {"coordinates":[16.5902004242,48.2406158447],"type":"Point"}
}