{
  "type": "Feature",
  "properties": {
    "iso:country":"AT",
    "sg:address":"Sportplatzstr 13",
    "sg:city":"Haidershofen",
    "sg:orig_category":"Fotografen",
    "sg:phone":"+43 699 11958065",
    "sg:postcode":"4431",
    "sg:province":"Nieder\u00f6sterreich",
    "wof:name":"Korner Roland",
    "wof:placetype":"venue"
},
  "geometry": {"coordinates":[14.4629716873,48.0709075928],"type":"Point"}
}