{
  "type": "Feature",
  "properties": {
    "addr:full":"Neutorstr 57 Salzburg Salzburg 5020",
    "addr:housenumber":"57",
    "addr:postcode":"5020",
    "addr:street":"Neutorstr;Salzburg",
    "iso:country":"AT",
    "sg:address":"Neutorstr 57",
    "sg:city":"Salzburg",
    "sg:orig_category":"\u00c3\u201erzte / F Allgemeinmedizin",
    "sg:phone":"+43 4366 28339360",
    "sg:postcode":"5020",
    "sg:province":"Salzburg",
    "wof:name":"Schreder Gerhard Dr",
    "wof:placetype":"venue"
},
  "geometry": {"coordinates":[13.027422905,47.7959098816],"type":"Point"}
}