{
  "type": "Feature",
  "properties": {
    "addr:full":"Markt 11 Strengberg Nieder\u00f6sterreich 3314",
    "addr:housenumber":"11",
    "addr:postcode":"3314",
    "addr:street":"Markt",
    "iso:country":"AT",
    "sg:address":"Markt 11",
    "sg:city":"Strengberg",
    "sg:orig_category":"Maler, Anstreicher U Lackierer",
    "sg:phone":"+43 4374 3222260",
    "sg:postcode":"3314",
    "sg:province":"Nieder\u00f6sterreich",
    "wof:name":"Reichart Martin",
    "wof:placetype":"venue"
},
  "geometry": {"coordinates":[14.6512088776,48.1430091858],"type":"Point"}
}