{
  "type": "Feature",
  "properties": {
    "addr:full":"Postleite 10 Lienz Tirol 9900",
    "addr:housenumber":"10",
    "addr:postcode":"9900",
    "addr:street":"Postleite;Tirol",
    "iso:country":"AT",
    "sg:address":"Postleite 10",
    "sg:city":"Lienz",
    "sg:orig_category":"Pensionen / Privatzimmer",
    "sg:phone":"+43 4852 63898",
    "sg:postcode":"9900",
    "sg:province":"Tirol",
    "wof:name":"G\u00e4stehaus Sissi",
    "wof:placetype":"venue"
},
  "geometry": {"coordinates":[12.7813529968,46.8388786316],"type":"Point"}
}