{
  "type": "Feature",
  "properties": {
    "iso:country":"AT",
    "sg:address":"Alpenstr 92-94",
    "sg:city":"Salzburg",
    "sg:orig_category":"Massagen",
    "sg:phone":"+43 662 625800",
    "sg:postcode":"5020",
    "sg:province":"Salzburg",
    "wof:name":"Massage AKU-Chi - Inh Ralph Roschanek",
    "wof:placetype":"venue"
},
  "geometry": {"coordinates":[13.0680341721,47.7779273987],"type":"Point"}
}