{
  "type": "Feature",
  "properties": {
    "iso:country":"AT",
    "sg:address":"Werndlstr 7",
    "sg:city":"Wels",
    "sg:orig_category":"Fenster",
    "sg:phone":"+43 7242 44549",
    "sg:postcode":"4600",
    "sg:province":"Ober\u00f6sterreich",
    "wof:name":"Hrachowina Bauelemente ProduktionsgesmbH",
    "wof:placetype":"venue"
},
  "geometry": {"coordinates":[14.0677995682,48.1805953979],"type":"Point"}
}