{
  "type": "Feature",
  "properties": {
    "addr:full":"Bahnstr 74 Prottes Nieder\u00f6sterreich 2242",
    "addr:housenumber":"74",
    "addr:postcode":"2242",
    "addr:street":"Bahnstr",
    "iso:country":"AT",
    "sg:address":"Bahnstr 74",
    "sg:city":"Prottes",
    "sg:orig_category":"Sektkellereien",
    "sg:phone":"+43 4322 8255660",
    "sg:postcode":"2242",
    "sg:province":"Nieder\u00f6sterreich",
    "wof:name":"Schlo\u00df Raggendorf Sekt- u Weinhandel AG",
    "wof:placetype":"venue"
},
  "geometry": {"coordinates":[16.7288894653,48.3829307556],"type":"Point"}
}