{
  "type": "Feature",
  "properties": {
    "addr:full":"Industriezeile 15 Braunau am Inn Ober\u00f6sterreich 5280",
    "addr:housenumber":"15",
    "addr:postcode":"5280",
    "addr:street":"Industriezeile",
    "iso:country":"AT",
    "sg:address":"Industriezeile 15",
    "sg:city":"Braunau am Inn",
    "sg:orig_category":"Maler, Anstreicher U Lackierer",
    "sg:phone":"+43 4377 2262260",
    "sg:postcode":"5280",
    "sg:province":"Ober\u00f6sterreich",
    "wof:name":"Malermeisterbetrieb Schenett OEG",
    "wof:placetype":"venue"
},
  "geometry": {"coordinates":[13.0642986298,48.2493476868],"type":"Point"}
}