{
  "type": "Feature",
  "properties": {
    "addr:full":"Ziegeleistr 30 Salzburg Salzburg 5020",
    "addr:housenumber":"30",
    "addr:postcode":"5020",
    "addr:street":"Ziegeleistr;Salzburg",
    "iso:country":"AT",
    "sg:address":"Ziegeleistr 30",
    "sg:city":"Salzburg",
    "sg:orig_category":"Alteisen U Altmetalle",
    "sg:phone":"+43 662 875005",
    "sg:postcode":"5020",
    "sg:province":"Salzburg",
    "wof:name":"Schienen- & Stahlhandel GmbH",
    "wof:placetype":"venue"
},
  "geometry": {"coordinates":[13.05727005,47.8263053894],"type":"Point"}
}