{
  "type": "Feature",
  "properties": {
    "addr:full":"Ungarg 24/1 Wien Wien 1030",
    "addr:housenumber":"24 / 1",
    "addr:postcode":"1030",
    "addr:street":"Ungarg",
    "iso:country":"AT",
    "sg:address":"Ungarg 24/1",
    "sg:city":"Wien",
    "sg:classifiers":[
        {
            "category":"Organizations",
            "subcategory":"Political Organization",
            "type":"Services"
        }
    ],
    "sg:phone":"+43 676 7204042",
    "sg:postcode":"1030",
    "sg:province":"Wien",
    "sg:tags":[
        "mediation"
    ],
    "wof:name":"forum wirtschaftsmediation",
    "wof:placetype":"venue"
},
  "geometry": {"coordinates":[16.3871040344,48.2020149231],"type":"Point"}
}