{
  "type": "Feature",
  "properties": {
    "addr:full":"Hirschfeldspitz 3842 Neusiedl am See Burgenland 7100",
    "addr:postcode":"3842;7100",
    "addr:street":"Hirschfeldspitz",
    "iso:country":"AT",
    "sg:address":"Hirschfeldspitz 3842",
    "sg:city":"Neusiedl am See",
    "sg:orig_category":"Lebensmittel / Einzelhandel",
    "sg:phone":"+43 2167 8685",
    "sg:postcode":"7100",
    "sg:province":"Burgenland",
    "wof:name":"Hofer KG",
    "wof:placetype":"venue"
},
  "geometry": {"coordinates":[16.837770462,47.9677696228],"type":"Point"}
}