{
  "type": "Feature",
  "properties": {
    "iso:country":"AT",
    "sg:address":"Freist\u00e4dter Str 224",
    "sg:city":"Linz",
    "sg:orig_category":"Friseure U Frisiersalons",
    "sg:phone":"+43 4373 2252029",
    "sg:postcode":"4040",
    "sg:province":"Ober\u00f6sterreich",
    "wof:name":"Frisiersalon Traudi",
    "wof:placetype":"venue"
},
  "geometry": {"coordinates":[14.3021764755,48.3261146545],"type":"Point"}
}