{
  "type": "Feature",
  "properties": {
    "addr:full":"M\u00fchlbachweg 6 Wei\u00dfenbach am Lech Tirol 6671",
    "addr:housenumber":"6",
    "addr:postcode":"6671",
    "addr:street":"Muehlbachweg;Tirol",
    "iso:country":"AT",
    "sg:address":"M\u00fchlbachweg 6",
    "sg:city":"Wei\u00dfenbach am Lech",
    "sg:classifiers":[
        {
            "category":"Professional",
            "subcategory":"Engineering",
            "type":"Services"
        }
    ],
    "sg:phone":"+43 4356 785279",
    "sg:postcode":"6671",
    "sg:province":"Tirol",
    "sg:tags":[
        "machine",
        "-",
        "mechanical"
    ],
    "wof:name":"BIHLER WEI\u00dfENBACH GESMBH & CO KG",
    "wof:placetype":"venue"
},
  "geometry": {"coordinates":[-90.9634475708,29.8630008698],"type":"Point"}
}