{
  "type": "Feature",
  "properties": {
    "addr:full":"Brenjurweg 10 Tarrenz Tirol 6464",
    "addr:housenumber":"10",
    "addr:postcode":"6464",
    "addr:street":"Brenjurweg;Tirol",
    "iso:country":"AT",
    "sg:address":"Brenjurweg 10",
    "sg:city":"Tarrenz",
    "sg:orig_category":"Hausbetreuung",
    "sg:phone":"+43 4369 910108465",
    "sg:postcode":"6464",
    "sg:province":"Tirol",
    "wof:name":"Kumpusch Bruno Haus- u Gartenservice",
    "wof:placetype":"venue"
},
  "geometry": {"coordinates":[10.7595796585,47.260055542],"type":"Point"}
}