{
  "type": "Feature",
  "properties": {
    "addr:full":"Zollerg 13 Wien Wien 1070",
    "addr:housenumber":"13",
    "addr:postcode":"1070",
    "addr:street":"Zollerg",
    "iso:country":"AT",
    "sg:address":"Zollerg 13",
    "sg:city":"Wien",
    "sg:orig_category":"Tonstudios",
    "sg:phone":"+43 1 5229414",
    "sg:postcode":"1070",
    "sg:province":"Wien",
    "wof:name":"Janeba Wofgang GesmbH",
    "wof:placetype":"venue"
},
  "geometry": {"coordinates":[16.3506851196,48.1995773315],"type":"Point"}
}