{
  "type": "Feature",
  "properties": {
    "iso:country":"AT",
    "sg:address":"Pustertaler Str 5a",
    "sg:city":"Lienz",
    "sg:orig_category":"Farben U Lacke / Einzelhandel",
    "sg:phone":"+43 4348 5263801",
    "sg:postcode":"9900",
    "sg:province":"Tirol",
    "wof:name":"Defregger Farben Tapeten GesmbH",
    "wof:placetype":"venue"
},
  "geometry": {"coordinates":[12.7558670044,46.8239517212],"type":"Point"}
}