{
  "type": "Feature",
  "properties": {
    "addr:full":"Nr 1 Jetzelsdorf Nieder\u00f6sterreich 2053",
    "addr:postcode":"2053",
    "addr:street":"Nr;Jetzelsdorf Niederoesterreich",
    "iso:country":"AT",
    "sg:address":"Nr 1",
    "sg:city":"Jetzelsdorf",
    "sg:orig_category":"Non-Classified Establishments",
    "sg:phone":"+43 2944 2320",
    "sg:postcode":"2053",
    "sg:province":"Nieder\u00f6sterreich",
    "wof:name":"Pfarramt",
    "wof:placetype":"venue"
},
  "geometry": {"coordinates":[16.056646347,48.7062911987],"type":"Point"}
}