{
  "type": "Feature",
  "properties": {
    "addr:full":"Wagnleithnerstr 3a Grieskirchen Ober\u00f6sterreich 4710",
    "addr:housenumber":"3a",
    "addr:postcode":"4710",
    "addr:street":"Wagnleithnerstr",
    "iso:country":"AT",
    "sg:address":"Wagnleithnerstr 3a",
    "sg:city":"Grieskirchen",
    "sg:classifiers":[
        {
            "category":"Taxi",
            "type":"Transportation"
        }
    ],
    "sg:phone":"+43 4372 4864701",
    "sg:postcode":"4710",
    "sg:province":"Ober\u00f6sterreich",
    "sg:tags":[
        "personentransporte",
        "u"
    ],
    "wof:name":"Joschi's Taxi-Mietwagen",
    "wof:placetype":"venue"
},
  "geometry": {"coordinates":[13.8236608505,48.2363166809],"type":"Point"}
}