{
  "type": "Feature",
  "properties": {
    "addr:full":"Nr. 102  Obertauern Salzburg 5562",
    "addr:postcode":"5562",
    "addr:street":"Nr.;Salzburg",
    "iso:country":"AT",
    "sg:address":"Nr. 102 ",
    "sg:city":"Obertauern",
    "sg:classifiers":[
        {
            "category":"Travel",
            "subcategory":"Travel Agent",
            "type":"Entertainment"
        }
    ],
    "sg:phone":"+43 4364 567272",
    "sg:postcode":"5562",
    "sg:province":"Salzburg",
    "sg:tags":[
        "business"
    ],
    "wof:name":"HOTEL KOHLMAYR",
    "wof:placetype":"venue"
},
  "geometry": {"coordinates":[13.5611753464,47.2483558655],"type":"Point"}
}