{
  "type": "Feature",
  "properties": {
    "iso:country":"AT",
    "sg:address":"Ritzenseestr 33",
    "sg:city":"Saalfelden am Steinernen Meer",
    "sg:orig_category":"Pensionen / Privatzimmer",
    "sg:phone":"+43 4365 82738060",
    "sg:postcode":"5760",
    "sg:province":"Salzburg",
    "wof:name":"Pension Ritzenhof",
    "wof:placetype":"venue"
},
  "geometry": {"coordinates":[12.8471412659,47.4210548401],"type":"Point"}
}