{
  "type": "Feature",
  "properties": {
    "addr:full":"Am Grazer Tor 1 Bruck an der Mur Steiermark 8600",
    "addr:housenumber":"1",
    "addr:postcode":"8600",
    "addr:street":"Am Grazer Tor",
    "iso:country":"AT",
    "sg:address":"Am Grazer Tor 1",
    "sg:city":"Bruck an der Mur",
    "sg:orig_category":"Lebensmittel / Einzelhandel",
    "sg:phone":"+43 4338 6257174",
    "sg:postcode":"8600",
    "sg:province":"Steiermark",
    "wof:name":"Billa AG",
    "wof:placetype":"venue"
},
  "geometry": {"coordinates":[15.2735061646,47.4117851257],"type":"Point"}
}