{
  "type": "Feature",
  "properties": {
    "iso:country":"AT",
    "sg:address":"Rudigierstr 3",
    "sg:city":"Linz",
    "sg:orig_category":"Damenmoden",
    "sg:phone":"+43 732 772286",
    "sg:postcode":"4020",
    "sg:province":"Ober\u00f6sterreich",
    "wof:name":"Scala aus Freude an Mode GmbH",
    "wof:placetype":"venue"
},
  "geometry": {"coordinates":[14.2902097702,48.3007049561],"type":"Point"}
}