{
  "type": "Feature",
  "properties": {
    "addr:full":"F\u00f6llinger Str 33 Mariatrost Steiermark 8044",
    "addr:housenumber":"33",
    "addr:postcode":"8044",
    "addr:street":"Str",
    "iso:country":"AT",
    "sg:address":"F\u00f6llinger Str 33",
    "sg:city":"Mariatrost",
    "sg:orig_category":"Damenmoden",
    "sg:phone":"+43 316 393327",
    "sg:postcode":"8044",
    "sg:province":"Steiermark",
    "wof:name":"Strohmeier KEG",
    "wof:placetype":"venue"
},
  "geometry": {"coordinates":[15.4981498718,47.1144142151],"type":"Point"}
}