{
  "type": "Feature",
  "properties": {
    "iso:country":"AT",
    "sg:address":"Doerenkampgasse 7",
    "sg:city":"Wien",
    "sg:orig_category":"Franking Systems",
    "sg:phone":"+43 1 680690",
    "sg:postcode":"1100",
    "sg:province":"Wien",
    "sg:website":"francotyp.at",
    "wof:name":"Francotyp-Postalia GmbH",
    "wof:placetype":"venue"
},
  "geometry": {"coordinates":[16.3795642853,48.142326355],"type":"Point"}
}