{
  "type": "Feature",
  "properties": {
    "addr:full":"Bahnhofpl 4 Villach K\u00e4rnten 9500",
    "addr:housenumber":"4",
    "addr:postcode":"9500",
    "addr:street":"Bahnhofpl;Kaernten",
    "iso:country":"AT",
    "sg:address":"Bahnhofpl 4",
    "sg:city":"Villach",
    "sg:orig_category":"Telekommunikation",
    "sg:phone":"+43 4242 22775",
    "sg:postcode":"9500",
    "sg:province":"K\u00e4rnten",
    "wof:name":"4U Mobiltelefon-Service GmbH",
    "wof:placetype":"venue"
},
  "geometry": {"coordinates":[13.8489265442,46.6179428101],"type":"Point"}
}