{
  "type": "Feature",
  "properties": {
    "addr:full":"Brigittenauer L\u00e4nde 156-158/1/19 Wien Wien 1200",
    "addr:housenumber":"156-158 / 1 / 19",
    "addr:postcode":"1200",
    "iso:country":"AT",
    "sg:address":"Brigittenauer L\u00e4nde 156-158/1/19",
    "sg:city":"Wien",
    "sg:classifiers":[
        {
            "category":"Professional",
            "subcategory":"Testing Lab",
            "type":"Services"
        }
    ],
    "sg:phone":"+43 1 9681593",
    "sg:postcode":"1200",
    "sg:province":"Wien",
    "sg:tags":[
        "chemical",
        "laboratory"
    ],
    "sg:website":"renger.at",
    "wof:name":"Ing. Michael Renger",
    "wof:placetype":"venue"
},
  "geometry": {"coordinates":[16.3734645844,48.2306060791],"type":"Point"}
}