{
  "type": "Feature",
  "properties": {
    "addr:full":"Faberstr 7a Salzburg Salzburg 5020",
    "addr:housenumber":"7a",
    "addr:postcode":"5020",
    "addr:street":"Faberstr;Salzburg",
    "iso:country":"AT",
    "sg:address":"Faberstr 7a",
    "sg:city":"Salzburg",
    "sg:orig_category":"\u00c3\u201erzte / F Allgemeinmedizin",
    "sg:phone":"+43 664 3842704",
    "sg:postcode":"5020",
    "sg:province":"Salzburg",
    "wof:name":"Sch\u00f6ppl Adolf Dr",
    "wof:placetype":"venue"
},
  "geometry": {"coordinates":[13.044046402,47.8066902161],"type":"Point"}
}