{
  "type": "Feature",
  "properties": {
    "iso:country":"AT",
    "sg:address":"Gleichenberger Str 2",
    "sg:city":"Feldbach",
    "sg:orig_category":"Weiterbildungsinstitute M Allg U Berufl Bildungsangebot",
    "sg:phone":"+43 4331 52438850",
    "sg:postcode":"8330",
    "sg:province":"Steiermark",
    "wof:name":"Berufsinfozentrum (BIZ)",
    "wof:placetype":"venue"
},
  "geometry": {"coordinates":[15.8910655975,46.9503822327],"type":"Point"}
}