{
  "type": "Feature",
  "properties": {
    "iso:country":"AT",
    "sg:address":"Haslach 21",
    "sg:city":"Zipf",
    "sg:orig_category":"Transportunternehmen",
    "sg:phone":"+43 76826474",
    "sg:postcode":"4871",
    "sg:province":"Ober\u00f6sterreich",
    "wof:name":"Winter Karl Anton",
    "wof:placetype":"venue"
},
  "geometry": {"coordinates":[13.5000810623,48.0282058716],"type":"Point"}
}