{
  "type": "Feature",
  "properties": {
    "addr:full":"Stubenring 14 Wien Wien 1010",
    "addr:housenumber":"14",
    "addr:postcode":"1010",
    "addr:street":"Stubenring",
    "iso:country":"AT",
    "sg:address":"Stubenring 14",
    "sg:city":"Wien",
    "sg:orig_category":"Restaurants: Vegetarisch",
    "sg:phone":"+43 1 5125553",
    "sg:postcode":"1010",
    "sg:province":"Wien",
    "wof:name":"Art of Life",
    "wof:placetype":"venue"
},
  "geometry": {"coordinates":[16.381729126,48.2088508606],"type":"Point"}
}