{
  "type": "Feature",
  "properties": {
    "iso:country":"AT",
    "sg:address":"Leobner Str 30",
    "sg:city":"Niklasdorf",
    "sg:orig_category":"Lebensmittel / Einzelhandel",
    "sg:phone":"+43 4338 4281096",
    "sg:postcode":"8712",
    "sg:province":"Steiermark",
    "wof:name":"MONDO Lebensmitteldiskonter",
    "wof:placetype":"venue"
},
  "geometry": {"coordinates":[15.161649704,47.3961868286],"type":"Point"}
}