{
  "type": "Feature",
  "properties": {
    "addr:full":"Gellertg 19 Wien Wien 1100",
    "addr:housenumber":"19",
    "addr:postcode":"1100",
    "addr:street":"Gellertg",
    "iso:country":"AT",
    "sg:address":"Gellertg 19",
    "sg:city":"Wien",
    "sg:orig_category":"Tabaktrafiken",
    "sg:phone":"+43 4316 032142",
    "sg:postcode":"1100",
    "sg:province":"Wien",
    "wof:name":"Weber Rudolf",
    "wof:placetype":"venue"
},
  "geometry": {"coordinates":[16.3744049072,48.1782684326],"type":"Point"}
}