{
  "type": "Feature",
  "properties": {
    "addr:full":"Villenstr 10 Zeltweg Steiermark 8740",
    "addr:housenumber":"10",
    "addr:postcode":"8740",
    "addr:street":"Villenstr",
    "iso:country":"AT",
    "sg:address":"Villenstr 10",
    "sg:city":"Zeltweg",
    "sg:orig_category":"Automatisierungstechnik",
    "sg:phone":"+43 4335 77233000",
    "sg:postcode":"8740",
    "sg:province":"Steiermark",
    "wof:name":"Ottronic Regeltechnik GesmbH",
    "wof:placetype":"venue"
},
  "geometry": {"coordinates":[14.7508411407,47.1871032715],"type":"Point"}
}