{
  "type": "Feature",
  "properties": {
    "addr:full":"Landstr 25 Steinerkirchen an der Traun Ober\u00f6sterreich 4652",
    "addr:housenumber":"25",
    "addr:postcode":"4652",
    "addr:street":"Landstr",
    "iso:country":"AT",
    "sg:address":"Landstr 25",
    "sg:city":"Steinerkirchen an der Traun",
    "sg:orig_category":"Lebensmittel / Einzelhandel",
    "sg:phone":"+43 7241 2254",
    "sg:postcode":"4652",
    "sg:province":"Ober\u00f6sterreich",
    "wof:name":"Spar-Markt Inh Johann Leithenmair",
    "wof:placetype":"venue"
},
  "geometry": {"coordinates":[13.9614782333,48.0794487],"type":"Point"}
}