{
  "type": "Feature",
  "properties": {
    "addr:full":"Gewerbepark 10 Marz Burgenland 7221",
    "addr:housenumber":"10",
    "addr:postcode":"7221",
    "addr:street":"Gewerbepark",
    "iso:country":"AT",
    "sg:address":"Gewerbepark 10",
    "sg:city":"Marz",
    "sg:orig_category":"Brandschutz",
    "sg:phone":"+43 2626 654870",
    "sg:postcode":"7221",
    "sg:province":"Burgenland",
    "wof:name":"L\u00f6schsysteme GmbH",
    "wof:placetype":"venue"
},
  "geometry": {"coordinates":[16.416934967,47.7186088562],"type":"Point"}
}