{
  "type": "Feature",
  "properties": {
    "addr:full":"Hafenstr 47-51 Linz Ober\u00f6sterreich 4020",
    "addr:postcode":"4020",
    "addr:street":"Oberoesterreich",
    "iso:country":"AT",
    "sg:address":"Hafenstr 47-51",
    "sg:city":"Linz",
    "sg:orig_category":"Telekommunikation",
    "sg:phone":"+43 732 90157100",
    "sg:postcode":"4020",
    "sg:province":"Ober\u00f6sterreich",
    "wof:name":"It & tel - Informationstechnologie",
    "wof:placetype":"venue"
},
  "geometry": {"coordinates":[14.3066530228,48.317943573],"type":"Point"}
}