{
  "type": "Feature",
  "properties": {
    "addr:full":"Nr 3a Neunkirchen Nieder\u00f6sterreich 2620",
    "addr:housenumber":"3a",
    "addr:postcode":"2620",
    "addr:street":"Nr",
    "iso:country":"AT",
    "sg:address":"Nr 3a",
    "sg:city":"Neunkirchen",
    "sg:orig_category":"Feuerwehren",
    "sg:phone":"+43 2635 65311",
    "sg:postcode":"2620",
    "sg:province":"Nieder\u00f6sterreich",
    "wof:name":"Freiwillige Feuerwehr Wartmannstetten",
    "wof:placetype":"venue"
},
  "geometry": {"coordinates":[16.0825557709,47.7204246521],"type":"Point"}
}