{
  "type": "Feature",
  "properties": {
    "addr:full":"Tendlerg 7 Wien Wien 1090",
    "addr:housenumber":"7",
    "addr:postcode":"1090",
    "addr:street":"Tendlerg",
    "iso:country":"AT",
    "sg:address":"Tendlerg 7",
    "sg:city":"Wien",
    "sg:orig_category":"Psychologen",
    "sg:phone":"+43 664 2208678",
    "sg:postcode":"1090",
    "sg:province":"Wien",
    "wof:name":"Wimmer Aurelia Dr",
    "wof:placetype":"venue"
},
  "geometry": {"coordinates":[16.3512516022,48.2212104797],"type":"Point"}
}