{
  "type": "Feature",
  "properties": {
    "iso:country":"AT",
    "sg:address":"Tendlerg 7",
    "sg:city":"Wien",
    "sg:orig_category":"Psychologen",
    "sg:phone":"+43 664 2208678",
    "sg:postcode":"1090",
    "sg:province":"Wien",
    "wof:name":"Wimmer Aurelia Dr",
    "wof:placetype":"venue"
},
  "geometry": {"coordinates":[16.3512516022,48.2212104797],"type":"Point"}
}