{
  "type": "Feature",
  "properties": {
    "addr:full":"Etrichstr 7 Wels Ober\u00f6sterreich 4600",
    "addr:housenumber":"7",
    "addr:postcode":"4600",
    "addr:street":"Etrichstr;Oberoesterreich",
    "iso:country":"AT",
    "sg:address":"Etrichstr 7",
    "sg:city":"Wels",
    "sg:orig_category":"Abfallentsorgung U -Verwertung",
    "sg:phone":"+43 7242 4910",
    "sg:postcode":"4600",
    "sg:province":"Ober\u00f6sterreich",
    "wof:name":"Sch\u00e4fer GesmbH & Co KG",
    "wof:placetype":"venue"
},
  "geometry": {"coordinates":[14.0670948029,48.1781349182],"type":"Point"}
}