{
  "type": "Feature",
  "properties": {
    "addr:full":"Wiesenthal 147 Bad Gleichenberg Steiermark 8344",
    "addr:housenumber":"147",
    "addr:postcode":"8344",
    "addr:street":"Wiesenthal",
    "iso:country":"AT",
    "sg:address":"Wiesenthal 147",
    "sg:city":"Bad Gleichenberg",
    "sg:orig_category":"Architekten",
    "sg:phone":"+43 3159 2690",
    "sg:postcode":"8344",
    "sg:province":"Steiermark",
    "wof:name":"Architekt di Siegfried Loos",
    "wof:placetype":"venue"
},
  "geometry": {"coordinates":[15.8965864182,46.8749084473],"type":"Point"}
}