{
  "type": "Feature",
  "properties": {
    "addr:full":"Wiener Str 52 Neulengbach Nieder\u00f6sterreich 3040",
    "addr:postcode":"3040",
    "addr:street":"Niederoesterreich",
    "iso:country":"AT",
    "sg:address":"Wiener Str 52",
    "sg:city":"Neulengbach",
    "sg:orig_category":"Installationsunternehmen",
    "sg:phone":"+43 2772 52103",
    "sg:postcode":"3040",
    "sg:province":"Nieder\u00f6sterreich",
    "wof:name":"Schmatz A GesmbH",
    "wof:placetype":"venue"
},
  "geometry": {"coordinates":[15.9092121124,48.1964454651],"type":"Point"}
}