{
  "type": "Feature",
  "properties": {
    "addr:full":"Stettner Weg 282 Korneuburg Nieder\u00f6sterreich 2100",
    "addr:housenumber":"282",
    "addr:postcode":"2100",
    "addr:street":"Stettner Weg;Niederoesterreich",
    "iso:country":"AT",
    "sg:address":"Stettner Weg 282",
    "sg:city":"Korneuburg",
    "sg:orig_category":"Garten- U Landschaftsgestaltung",
    "sg:phone":"+43 4322 6264592",
    "sg:postcode":"2100",
    "sg:province":"Nieder\u00f6sterreich",
    "wof:name":"Tomasek, Vorauer & Walther GesmbH",
    "wof:placetype":"venue"
},
  "geometry": {"coordinates":[16.344789505,48.3503112793],"type":"Point"}
}