{
  "type": "Feature",
  "properties": {
    "addr:full":"Siebererstr 9 Innsbruck Tirol 6020",
    "addr:housenumber":"9",
    "addr:postcode":"6020",
    "addr:street":"Siebererstr;Tirol",
    "iso:country":"AT",
    "sg:address":"Siebererstr 9",
    "sg:city":"Innsbruck",
    "sg:orig_category":"Sonderschulen",
    "sg:phone":"+43 512 589466",
    "sg:postcode":"6020",
    "sg:province":"Tirol",
    "wof:name":"Allgemeine Sonderschule",
    "wof:placetype":"venue"
},
  "geometry": {"coordinates":[11.4042816162,47.2725753784],"type":"Point"}
}