{
  "type": "Feature",
  "properties": {
    "addr:full":"Friedhofstr 40 Linz Ober\u00f6sterreich 4020",
    "addr:housenumber":"40",
    "addr:postcode":"4020",
    "addr:street":"Friedhofstr",
    "iso:country":"AT",
    "sg:address":"Friedhofstr 40",
    "sg:city":"Linz",
    "sg:orig_category":"Lebensmittel / Einzelhandel",
    "sg:phone":"+43 732 604580",
    "sg:postcode":"4020",
    "sg:province":"Ober\u00f6sterreich",
    "wof:name":"SPAR \u00f6sterreichische Warenhandels-AG",
    "wof:placetype":"venue"
},
  "geometry": {"coordinates":[14.3037500381,48.2929382324],"type":"Point"}
}