{
  "type": "Feature",
  "properties": {
    "addr:full":"Georgig 56 Graz Steiermark 8020",
    "addr:housenumber":"56",
    "addr:postcode":"8020",
    "addr:street":"Georgig",
    "iso:country":"AT",
    "sg:address":"Georgig 56",
    "sg:city":"Graz",
    "sg:orig_category":"Restaurants: Chinesisch",
    "sg:phone":"+43 316 573820",
    "sg:postcode":"8020",
    "sg:province":"Steiermark",
    "wof:name":"Chinarestaurant Beile",
    "wof:placetype":"venue"
},
  "geometry": {"coordinates":[15.4013614655,47.0731620789],"type":"Point"}
}