{
  "type": "Feature",
  "properties": {
    "addr:full":"Rosensteing 42/2 Wien Wien 1170",
    "addr:housenumber":"42 / 2",
    "addr:postcode":"1170",
    "addr:street":"Rosensteing",
    "iso:country":"AT",
    "sg:address":"Rosensteing 42/2",
    "sg:city":"Wien",
    "sg:orig_category":"Nachhilfe U Lernbetreuung",
    "sg:phone":"+43 664 3005730",
    "sg:postcode":"1170",
    "sg:province":"Wien",
    "wof:name":"MAS Nachhilfe + Sprachinstitut",
    "wof:placetype":"venue"
},
  "geometry": {"coordinates":[16.3265304565,48.2190322876],"type":"Point"}
}