{
  "type": "Feature",
  "properties": {
    "iso:country":"AT",
    "sg:address":"Nr 149",
    "sg:city":"Stubenberg am See",
    "sg:orig_category":"Musikunterricht",
    "sg:phone":"+43 3176 8911",
    "sg:postcode":"8223",
    "sg:province":"Steiermark",
    "wof:name":"Musikschule Stubenberg",
    "wof:placetype":"venue"
},
  "geometry": {"coordinates":[15.8004598618,47.243724823],"type":"Point"}
}