{
  "type": "Feature",
  "properties": {
    "iso:country":"AT",
    "sg:address":"Richard-Wagner-Pl 19",
    "sg:city":"Wien",
    "sg:orig_category":"Bildungsservice / Allgemeine Informationsstellen",
    "sg:phone":"+43 1 4919616156",
    "sg:postcode":"1160",
    "sg:province":"Wien",
    "wof:name":"Stadtschulrat f Wien f d 16. Bezirk",
    "wof:placetype":"venue"
},
  "geometry": {"coordinates":[16.3272666931,48.2093276978],"type":"Point"}
}