{
  "type": "Feature",
  "properties": {
    "addr:full":"Johann Ure-Weg 15 Klagenfurt K\u00e4rnten 9020",
    "addr:housenumber":"15",
    "addr:postcode":"9020",
    "addr:street":"Kaernten",
    "iso:country":"AT",
    "sg:address":"Johann Ure-Weg 15",
    "sg:city":"Klagenfurt",
    "sg:orig_category":"Reinigungsbedarf U Reinigungsmittel",
    "sg:phone":"+43 463 210025",
    "sg:postcode":"9020",
    "sg:province":"K\u00e4rnten",
    "wof:name":"Regema VertriebsgesmbH & Co KG",
    "wof:placetype":"venue"
},
  "geometry": {"coordinates":[14.2704896927,46.6223373413],"type":"Point"}
}