{
  "type": "Feature",
  "properties": {
    "iso:country":"AT",
    "sg:address":"E\u00dflinger Hauptstr 77",
    "sg:city":"Wien",
    "sg:orig_category":"Politische Parteien",
    "sg:phone":"+43 1 7748846",
    "sg:postcode":"1220",
    "sg:province":"Wien",
    "wof:name":"Sozialdemokratische Partei \u00d6sterreichs -Sektion 5",
    "wof:placetype":"venue"
},
  "geometry": {"coordinates":[16.5219764709,48.214756012],"type":"Point"}
}