{
  "type": "Feature",
  "properties": {
    "addr:full":"Hintausstr Mannersdorf am Leithagebirge Nieder\u00f6sterreich 2452",
    "addr:postcode":"2452",
    "addr:street":"Hintausstr",
    "iso:country":"AT",
    "sg:address":"Hintausstr",
    "sg:city":"Mannersdorf am Leithagebirge",
    "sg:orig_category":"Feuerwehren",
    "sg:phone":"+43 2168 63131",
    "sg:postcode":"2452",
    "sg:province":"Nieder\u00f6sterreich",
    "wof:name":"Freiwillige Feuerwehr Mannersdorf/Leithagebirge",
    "wof:placetype":"venue"
},
  "geometry": {"coordinates":[16.606508255,47.9764442444],"type":"Point"}
}