{
  "type": "Feature",
  "properties": {
    "addr:full":"Unterer Stadtpl 8-9 Waidhofen an der Ybbs Nieder\u00f6sterreich 3340",
    "addr:housenumber":"8-9",
    "addr:postcode":"3340",
    "addr:street":"Unterer Stadtpl",
    "iso:country":"AT",
    "sg:address":"Unterer Stadtpl 8-9",
    "sg:city":"Waidhofen an der Ybbs",
    "sg:orig_category":"Eisenwaren",
    "sg:phone":"+43 4374 42539000",
    "sg:postcode":"3340",
    "sg:province":"Nieder\u00f6sterreich",
    "wof:name":"Funke GmbH",
    "wof:placetype":"venue"
},
  "geometry": {"coordinates":[14.7736673355,47.9608268738],"type":"Point"}
}