{
  "type": "Feature",
  "properties": {
    "addr:full":"Nr 107 M\u00fchlbach Salzburg 5732",
    "addr:postcode":"5732",
    "addr:street":"Nr 107;Salzburg",
    "iso:country":"AT",
    "sg:address":"Nr 107",
    "sg:city":"M\u00fchlbach",
    "sg:orig_category":"Tabaktrafiken",
    "sg:phone":"+43 6566 7278",
    "sg:postcode":"5732",
    "sg:province":"Salzburg",
    "wof:name":"Lerch Katharina",
    "wof:placetype":"venue"
},
  "geometry": {"coordinates":[166.9221496582,-0.5282999873],"type":"Point"}
}