{
  "type": "Feature",
  "properties": {
    "iso:country":"AT",
    "sg:address":"Nr 24",
    "sg:city":"Gamlitz",
    "sg:orig_category":"Montagen U Montagetechnik",
    "sg:phone":"+43 4334 534430",
    "sg:postcode":"8462",
    "sg:province":"Steiermark",
    "wof:name":"Kogler Willibald",
    "wof:placetype":"venue"
},
  "geometry": {"coordinates":[15.5537004471,46.7205543518],"type":"Point"}
}