{
  "type": "Feature",
  "properties": {
    "addr:full":"Bad Haller Str 4 Adlwang Ober\u00f6sterreich 4541",
    "addr:housenumber":"4",
    "addr:postcode":"4541",
    "addr:street":"Bad;Str",
    "iso:country":"AT",
    "sg:address":"Bad Haller Str 4",
    "sg:city":"Adlwang",
    "sg:orig_category":"Transportunternehmen",
    "sg:phone":"+43 4372 583169",
    "sg:postcode":"4541",
    "sg:province":"Ober\u00f6sterreich",
    "wof:name":"Mittermayr Karl",
    "wof:placetype":"venue"
},
  "geometry": {"coordinates":[14.2173910141,47.993106842],"type":"Point"}
}