{
  "type": "Feature",
  "properties": {
    "iso:country":"AT",
    "sg:address":"Wasseracker 2A",
    "sg:city":"Mattighofen",
    "sg:orig_category":"Vinotheken",
    "sg:phone":"+43 7742 52400",
    "sg:postcode":"5230",
    "sg:province":"Ober\u00f6sterreich",
    "wof:name":"Werdecker Max",
    "wof:placetype":"venue"
},
  "geometry": {"coordinates":[13.1516571045,48.104888916],"type":"Point"}
}