{
  "type": "Feature",
  "properties": {
    "addr:full":"Hammersteinpl 1 Braunau am Inn Ober\u00f6sterreich 5280",
    "addr:housenumber":"1",
    "addr:postcode":"5280",
    "addr:street":"Hammersteinpl",
    "iso:country":"AT",
    "sg:address":"Hammersteinpl 1",
    "sg:city":"Braunau am Inn",
    "sg:orig_category":"Bezirkshauptmannschaften",
    "sg:phone":"+43 4377 228030",
    "sg:postcode":"5280",
    "sg:province":"Ober\u00f6sterreich",
    "wof:name":"Bezirkshauptmannschaft Braunau a Inn",
    "wof:placetype":"venue"
},
  "geometry": {"coordinates":[13.0442199707,48.2609558105],"type":"Point"}
}