{
  "type": "Feature",
  "properties": {
    "addr:full":"Pfarrg 7 Imst Tirol 6460",
    "addr:housenumber":"7",
    "addr:postcode":"6460",
    "addr:street":"Pfarrg;Tirol",
    "iso:country":"AT",
    "sg:address":"Pfarrg 7",
    "sg:city":"Imst",
    "sg:orig_category":"Restaurants: Italienisch",
    "sg:phone":"+43 4354 1267944",
    "sg:postcode":"6460",
    "sg:province":"Tirol",
    "wof:name":"La Taverna",
    "wof:placetype":"venue"
},
  "geometry": {"coordinates":[10.7387533188,47.2428588867],"type":"Point"}
}