{
  "type": "Feature",
  "properties": {
    "addr:full":"Werkstr 1 Ferlach K\u00e4rnten 9170",
    "addr:housenumber":"1",
    "addr:postcode":"9170",
    "addr:street":"Werkstr;Kaernten",
    "iso:country":"AT",
    "sg:address":"Werkstr 1",
    "sg:city":"Ferlach",
    "sg:orig_category":"Textilreinigung",
    "sg:phone":"+43 4342 272611",
    "sg:postcode":"9170",
    "sg:province":"K\u00e4rnten",
    "wof:name":"Textilreinigung Kellner",
    "wof:placetype":"venue"
},
  "geometry": {"coordinates":[14.3003759384,46.5256500244],"type":"Point"}
}