{
  "type": "Feature",
  "properties": {
    "addr:full":"Salzstr 2 Bad Leonfelden Ober\u00f6sterreich 4190",
    "addr:housenumber":"2",
    "addr:postcode":"4190",
    "addr:street":"Salzstr",
    "iso:country":"AT",
    "sg:address":"Salzstr 2",
    "sg:city":"Bad Leonfelden",
    "sg:orig_category":"Immobilienmakler",
    "sg:phone":"+43 7213 8184",
    "sg:postcode":"4190",
    "sg:province":"Ober\u00f6sterreich",
    "wof:name":"Kapl Immobilien GmbH",
    "wof:placetype":"venue"
},
  "geometry": {"coordinates":[14.295416832,48.522983551],"type":"Point"}
}