{
  "type": "Feature",
  "properties": {
    "addr:full":"Villacher-Str. 92 Spittal an der Drau K\u00e4rnten 9800",
    "addr:housenumber":"92",
    "addr:postcode":"9800",
    "addr:street":"Villacher-Str.;Kaernten",
    "iso:country":"AT",
    "sg:address":"Villacher-Str. 92",
    "sg:city":"Spittal an der Drau",
    "sg:classifiers":[
        {
            "category":"Food & Beverages",
            "subcategory":"Dairy",
            "type":"Retail Goods"
        }
    ],
    "sg:phone":"+43 4347 62610610",
    "sg:postcode":"9800",
    "sg:province":"K\u00e4rnten",
    "sg:tags":[
        "product"
    ],
    "wof:name":"K\u00c4RNTNERMILCH GENOSSENSCHAFT MBH",
    "wof:placetype":"venue"
},
  "geometry": {"coordinates":[13.5157470703,46.7898216248],"type":"Point"}
}