{
  "type": "Feature",
  "properties": {
    "addr:full":"Fabriksstr 29 Stainz Steiermark 8510",
    "addr:housenumber":"29",
    "addr:postcode":"8510",
    "addr:street":"Fabriksstr",
    "iso:country":"AT",
    "sg:address":"Fabriksstr 29",
    "sg:city":"Stainz",
    "sg:orig_category":"Tischlereien",
    "sg:phone":"+43 3463 2057",
    "sg:postcode":"8510",
    "sg:province":"Steiermark",
    "wof:name":"Aldrian Johann",
    "wof:placetype":"venue"
},
  "geometry": {"coordinates":[15.2728157043,46.8906669617],"type":"Point"}
}