{
  "type": "Feature",
  "properties": {
    "addr:full":"Nr 20 Schwarzenau Nieder\u00f6sterreich 3900",
    "addr:postcode":"3900",
    "addr:street":"Nr;Schwarzenau",
    "iso:country":"AT",
    "sg:address":"Nr 20",
    "sg:city":"Schwarzenau",
    "sg:orig_category":"Appartements / Ferienwohnungen",
    "sg:phone":"+43 4328 492226",
    "sg:postcode":"3900",
    "sg:province":"Nieder\u00f6sterreich",
    "wof:name":"B\u00f6hm Christian",
    "wof:placetype":"venue"
},
  "geometry": {"coordinates":[15.2588233948,48.7432861328],"type":"Point"}
}