{
  "type": "Feature",
  "properties": {
    "iso:country":"AT",
    "sg:address":"Wilhelm-Raabe-G 14",
    "sg:city":"Graz",
    "sg:orig_category":"Steuerberatung",
    "sg:phone":"+43 316 679973",
    "sg:postcode":"8010",
    "sg:province":"Steiermark",
    "wof:name":"Micelli Viktor Mag",
    "wof:placetype":"venue"
},
  "geometry": {"coordinates":[15.4331703186,47.0865249634],"type":"Point"}
}