{
  "type": "Feature",
  "properties": {
    "addr:full":"Erkerg 14 Klagenfurt K\u00e4rnten 9020",
    "addr:housenumber":"14",
    "addr:postcode":"9020",
    "addr:street":"Erkerg;Kaernten",
    "iso:country":"AT",
    "sg:address":"Erkerg 14",
    "sg:city":"Klagenfurt",
    "sg:orig_category":"Sportanlagen",
    "sg:phone":"+43 463 25333",
    "sg:postcode":"9020",
    "sg:province":"K\u00e4rnten",
    "wof:name":"Eislaufverein W\u00f6rthersee",
    "wof:placetype":"venue"
},
  "geometry": {"coordinates":[14.290430069,46.6123161316],"type":"Point"}
}