{
  "type": "Feature",
  "properties": {
    "addr:full":"10.-Oktober-Str 17 Feldkirchen in K\u00e4rnten K\u00e4rnten 9560",
    "addr:housenumber":"17",
    "addr:postcode":"9560",
    "addr:street":"10.-Oktober-Str;Kaernten",
    "iso:country":"AT",
    "sg:address":"10.-Oktober-Str 17",
    "sg:city":"Feldkirchen in K\u00e4rnten",
    "sg:orig_category":"Stahlbau",
    "sg:phone":"+43 4342 7648740",
    "sg:postcode":"9560",
    "sg:province":"K\u00e4rnten",
    "wof:name":"Egger Engineering GmbH",
    "wof:placetype":"venue"
},
  "geometry": {"coordinates":[14.09461689,46.7241668701],"type":"Point"}
}