{
  "type": "Feature",
  "properties": {
    "addr:full":"Ochsenburger Str 44 St. Georgen am Steinfelde Nieder\u00f6sterreich 3151",
    "addr:housenumber":"44",
    "addr:postcode":"3151",
    "addr:street":"Str",
    "iso:country":"AT",
    "sg:address":"Ochsenburger Str 44",
    "sg:city":"St. Georgen am Steinfelde",
    "sg:orig_category":"Bildhauer",
    "sg:phone":"+43 4327 42884292",
    "sg:postcode":"3151",
    "sg:province":"Nieder\u00f6sterreich",
    "wof:name":"Objekte in Stahl Werner K\u00f6hler",
    "wof:placetype":"venue"
},
  "geometry": {"coordinates":[15.630408287,48.1315307617],"type":"Point"}
}