{
  "type": "Feature",
  "properties": {
    "addr:full":"Feldg 5 Mitterdorf im M\u00fcrztal Steiermark 8662",
    "addr:housenumber":"5;im",
    "addr:postcode":"8662",
    "addr:street":"Feldg;Muerztal Steiermark",
    "iso:country":"AT",
    "sg:address":"Feldg 5",
    "sg:city":"Mitterdorf im M\u00fcrztal",
    "sg:orig_category":"\u00c3\u201erzte / F Allgemeinmedizin",
    "sg:phone":"+43 4338 5826250",
    "sg:postcode":"8662",
    "sg:province":"Steiermark",
    "wof:name":"Budiman Sastro Dr",
    "wof:placetype":"venue"
},
  "geometry": {"coordinates":[15.5095262527,47.5347671509],"type":"Point"}
}