{
  "type": "Feature",
  "properties": {
    "addr:full":"Nr 2 Oberzeiring Steiermark 8762",
    "addr:postcode":"8762",
    "addr:street":"Nr;Oberzeiring",
    "iso:country":"AT",
    "sg:address":"Nr 2",
    "sg:city":"Oberzeiring",
    "sg:orig_category":"Autohandel",
    "sg:phone":"+43 3579 7326",
    "sg:postcode":"8762",
    "sg:province":"Steiermark",
    "wof:name":"Kritz Franz KG",
    "wof:placetype":"venue"
},
  "geometry": {"coordinates":[14.5115098953,47.2576713562],"type":"Point"}
}