{
  "type": "Feature",
  "properties": {
    "addr:full":"Erzherzog-Karl-Str 228 Wien Wien 1220",
    "addr:housenumber":"228",
    "addr:postcode":"1220",
    "iso:country":"AT",
    "sg:address":"Erzherzog-Karl-Str 228",
    "sg:city":"Wien",
    "sg:orig_category":"Fleischhauereien",
    "sg:phone":"+43 1 2825117",
    "sg:postcode":"1220",
    "sg:province":"Wien",
    "wof:name":"Wallisch Johann",
    "wof:placetype":"venue"
},
  "geometry": {"coordinates":[16.4778366089,48.2208251953],"type":"Point"}
}