{
  "type": "Feature",
  "properties": {
    "iso:country":"AT",
    "sg:address":"Hans-Resel-Gasse 16",
    "sg:city":"Graz",
    "sg:classifiers":[
        {
            "category":"Home & Garden",
            "subcategory":"Home Furnishings",
            "type":"Retail Goods"
        }
    ],
    "sg:phone":"+43 316 685443",
    "sg:postcode":"8020",
    "sg:province":"Steiermark",
    "sg:tags":[
        "decorative",
        "lighting",
        "system"
    ],
    "sg:website":"lg.licht.at",
    "wof:name":"LG - Licht u. Elektrotechnik GmbH & Co KG",
    "wof:placetype":"venue"
},
  "geometry": {"coordinates":[15.4244947433,47.0727920532],"type":"Point"}
}