{
  "type": "Feature",
  "properties": {
    "iso:country":"AT",
    "sg:address":"Hauptstr 58",
    "sg:city":"Radenthein",
    "sg:orig_category":"Beratungsstellen",
    "sg:phone":"+43 4246 4920",
    "sg:postcode":"9545",
    "sg:province":"K\u00e4rnten",
    "wof:name":"Vitamin R-Zentrum f Gesundheit",
    "wof:placetype":"venue"
},
  "geometry": {"coordinates":[13.7001333237,46.7997055054],"type":"Point"}
}