{
  "type": "Feature",
  "properties": {
    "addr:full":"Abwinden Dorf 3 St. Georgen an der Gusen Ober\u00f6sterreich 4222",
    "addr:housenumber":"3",
    "addr:postcode":"4222",
    "addr:street":"Dorf",
    "iso:country":"AT",
    "sg:address":"Abwinden Dorf 3",
    "sg:city":"St. Georgen an der Gusen",
    "sg:orig_category":"Pensionen / Privatzimmer",
    "sg:phone":"+43 4372 3724550",
    "sg:postcode":"4222",
    "sg:province":"Ober\u00f6sterreich",
    "wof:name":"Fr\u00fchst\u00fcckspension Bauer in Hof - Andrea Reiter",
    "wof:placetype":"venue"
},
  "geometry": {"coordinates":[14.4315261841,48.2602005005],"type":"Point"}
}