{
  "type": "Feature",
  "properties": {
    "addr:full":"Kirchenstr 212 Uttendorf Salzburg 5723",
    "addr:housenumber":"212",
    "addr:postcode":"5723",
    "addr:street":"Uttendorf Salzburg",
    "iso:country":"AT",
    "sg:address":"Kirchenstr 212",
    "sg:city":"Uttendorf",
    "sg:orig_category":"Lebensmittel / Einzelhandel",
    "sg:phone":"+43 6563 84560",
    "sg:postcode":"5723",
    "sg:province":"Salzburg",
    "wof:name":"Spar-Markt Inh Peter G\u00fcnther",
    "wof:placetype":"venue"
},
  "geometry": {"coordinates":[12.5700798035,47.2862014771],"type":"Point"}
}