{
  "type": "Feature",
  "properties": {
    "addr:full":"Hub 18 Obernberg am Inn Ober\u00f6sterreich 4982",
    "addr:housenumber":"18",
    "addr:postcode":"4982",
    "addr:street":"Hub",
    "iso:country":"AT",
    "sg:address":"Hub 18",
    "sg:city":"Obernberg am Inn",
    "sg:orig_category":"Rauchfangkehrer",
    "sg:phone":"+43 7758 2234",
    "sg:postcode":"4982",
    "sg:province":"Ober\u00f6sterreich",
    "wof:name":"Raffelsberger Hans Peter",
    "wof:placetype":"venue"
},
  "geometry": {"coordinates":[13.3337955475,48.3158721924],"type":"Point"}
}