{
  "type": "Feature",
  "properties": {
    "addr:full":"Gerberg 16 Kitzb\u00fchel Tirol 6370",
    "addr:housenumber":"16",
    "addr:postcode":"6370",
    "addr:street":"Gerberg;Tirol",
    "iso:country":"AT",
    "sg:address":"Gerberg 16",
    "sg:city":"Kitzb\u00fchel",
    "sg:orig_category":"Holdinggesellschaften",
    "sg:phone":"+43 5356 64666",
    "sg:postcode":"6370",
    "sg:province":"Tirol",
    "wof:name":"Prodiac Walpurgis Investment GmbH",
    "wof:placetype":"venue"
},
  "geometry": {"coordinates":[12.3929195404,47.4455451965],"type":"Point"}
}