{
  "type": "Feature",
  "properties": {
    "iso:country":"AT",
    "sg:address":"Elisabethstr 9",
    "sg:city":"Wien",
    "sg:orig_category":"Werbeagenturen",
    "sg:phone":"+43 1 9300033380",
    "sg:postcode":"1010",
    "sg:province":"Wien",
    "wof:name":"CI & M Werbeagentur GmbH",
    "wof:placetype":"venue"
},
  "geometry": {"coordinates":[16.3667240143,48.2020454407],"type":"Point"}
}