{
  "type": "Feature",
  "properties": {
    "addr:full":"S\u00f6briach 18 Obervellach K\u00e4rnten 9821",
    "addr:housenumber":"18",
    "addr:postcode":"9821",
    "addr:street":"Soebriach;Kaernten",
    "iso:country":"AT",
    "sg:address":"S\u00f6briach 18",
    "sg:city":"Obervellach",
    "sg:orig_category":"Fenster",
    "sg:phone":"+43 4782 25640",
    "sg:postcode":"9821",
    "sg:province":"K\u00e4rnten",
    "wof:name":"Tischlerei Kapeller",
    "wof:placetype":"venue"
},
  "geometry": {"coordinates":[13.202000618,46.9322319031],"type":"Point"}
}