{
  "type": "Feature",
  "properties": {
    "addr:full":"Kolpingstr 2a Oberndorf Salzburg 5110",
    "addr:housenumber":"2a",
    "addr:postcode":"5110",
    "addr:street":"Kolpingstr",
    "iso:country":"AT",
    "sg:address":"Kolpingstr 2a",
    "sg:city":"Oberndorf",
    "sg:orig_category":"Bibliotheken",
    "sg:phone":"+43 4362 726769",
    "sg:postcode":"5110",
    "sg:province":"Salzburg",
    "wof:name":"Bibliothek Oberndorf",
    "wof:placetype":"venue"
},
  "geometry": {"coordinates":[12.9440927505,47.939540863],"type":"Point"}
}