{
  "type": "Feature",
  "properties": {
    "iso:country":"AT",
    "sg:address":"Nr 291",
    "sg:city":"Wullersdorf",
    "sg:orig_category":"Friseure U Frisiersalons",
    "sg:phone":"+43 4329 518683",
    "sg:postcode":"2041",
    "sg:province":"Nieder\u00f6sterreich",
    "wof:name":"Widerna Christa",
    "wof:placetype":"venue"
},
  "geometry": {"coordinates":[16.1020965576,48.6272735596],"type":"Point"}
}