{
  "type": "Feature",
  "properties": {
    "addr:full":"Florianistr 1 Rum Tirol 6063",
    "addr:housenumber":"1",
    "addr:postcode":"6063",
    "addr:street":"Florianistr;Tirol",
    "iso:country":"AT",
    "sg:address":"Florianistr 1",
    "sg:city":"Rum",
    "sg:orig_category":"Autospenglereien",
    "sg:phone":"+43 512 261113",
    "sg:postcode":"6063",
    "sg:province":"Tirol",
    "wof:name":"Schmarl Karosserie-Spenglerei-Lackierung GesmbH",
    "wof:placetype":"venue"
},
  "geometry": {"coordinates":[11.4511632919,47.2718162537],"type":"Point"}
}