{
  "type": "Feature",
  "properties": {
    "addr:full":"Tigerg 1 Wien Wien 1080",
    "addr:housenumber":"1",
    "addr:postcode":"1080",
    "addr:street":"Tigerg",
    "iso:country":"AT",
    "sg:address":"Tigerg 1",
    "sg:city":"Wien",
    "sg:orig_category":"Architekten",
    "sg:phone":"+43 1 40264300",
    "sg:postcode":"1080",
    "sg:province":"Wien",
    "wof:name":"Sch\u00f6fl Wolfgang Dipl-Ing",
    "wof:placetype":"venue"
},
  "geometry": {"coordinates":[16.344669342,48.2074737549],"type":"Point"}
}