{
  "type": "Feature",
  "properties": {
    "addr:full":"G\u00f6ttweigerhofg 2 Krems an der Donau Nieder\u00f6sterreich 3500",
    "addr:housenumber":"2",
    "addr:postcode":"3500",
    "addr:street":"Goettweigerhofg",
    "iso:country":"AT",
    "sg:address":"G\u00f6ttweigerhofg 2",
    "sg:city":"Krems an der Donau",
    "sg:orig_category":"Friseure U Frisiersalons",
    "sg:phone":"+43 4327 3287979",
    "sg:postcode":"3500",
    "sg:province":"Nieder\u00f6sterreich",
    "wof:name":"Frisiersalon mit Stil",
    "wof:placetype":"venue"
},
  "geometry": {"coordinates":[15.5869827271,48.4036407471],"type":"Point"}
}