{
  "type": "Feature",
  "properties": {
    "addr:full":"K\u00f6nigsbrunng 7 M\u00fcrzzuschlag Steiermark 8680",
    "addr:housenumber":"7",
    "addr:postcode":"8680",
    "addr:street":"Koenigsbrunng",
    "iso:country":"AT",
    "sg:address":"K\u00f6nigsbrunng 7",
    "sg:city":"M\u00fcrzzuschlag",
    "sg:orig_category":"Installationsunternehmen",
    "sg:phone":"+43 4338 5222560",
    "sg:postcode":"8680",
    "sg:province":"Steiermark",
    "wof:name":"Kneihsl Ludwig GesmbH",
    "wof:placetype":"venue"
},
  "geometry": {"coordinates":[15.6702661514,47.6059341431],"type":"Point"}
}