{
  "type": "Feature",
  "properties": {
    "iso:country":"AT",
    "sg:address":"Nr 1",
    "sg:city":"Tainach",
    "sg:orig_category":"Non-Classified Establishments",
    "sg:phone":"+43 4239 26353",
    "sg:postcode":"9121",
    "sg:province":"K\u00e4rnten",
    "wof:name":"Pfarramt",
    "wof:placetype":"venue"
},
  "geometry": {"coordinates":[14.5084590912,46.6561851501],"type":"Point"}
}