{
  "type": "Feature",
  "properties": {
    "addr:full":"Operng 24 Wien Wien 1040",
    "addr:housenumber":"24",
    "addr:postcode":"1040",
    "addr:street":"Operng",
    "iso:country":"AT",
    "sg:address":"Operng 24",
    "sg:city":"Wien",
    "sg:orig_category":"Friseure U Frisiersalons",
    "sg:phone":"+43 1 5853592",
    "sg:postcode":"1040",
    "sg:province":"Wien",
    "wof:name":"mod's Hair",
    "wof:placetype":"venue"
},
  "geometry": {"coordinates":[16.3661823273,48.1987838745],"type":"Point"}
}