{
  "type": "Feature",
  "properties": {
    "addr:full":"Stiftingtalstr 227a Graz Steiermark 8010",
    "addr:housenumber":"227a",
    "addr:postcode":"8010",
    "iso:country":"AT",
    "sg:address":"Stiftingtalstr 227a",
    "sg:city":"Graz",
    "sg:orig_category":"Bauunternehmen",
    "sg:phone":"+43 4331 6392200",
    "sg:postcode":"8010",
    "sg:province":"Steiermark",
    "wof:name":"Hieden & Kall Hoch- u TiefbaugesmbH",
    "wof:placetype":"venue"
},
  "geometry": {"coordinates":[15.4899835587,47.092502594],"type":"Point"}
}