{
  "type": "Feature",
  "properties": {
    "iso:country":"AT",
    "sg:address":"Hauptstr 72",
    "sg:city":"Eggendorf",
    "sg:orig_category":"Volksschulen",
    "sg:phone":"+43 2622 73237",
    "sg:postcode":"2492",
    "sg:province":"Nieder\u00f6sterreich",
    "wof:name":"Volksschule",
    "wof:placetype":"venue"
},
  "geometry": {"coordinates":[16.3174304962,47.856010437],"type":"Point"}
}