{
  "type": "Feature",
  "properties": {
    "iso:country":"AT",
    "sg:address":"Kalchbergg 2",
    "sg:city":"Graz",
    "sg:orig_category":"Bibliotheken",
    "sg:phone":"+43 4331 68774600",
    "sg:postcode":"8010",
    "sg:province":"Steiermark",
    "wof:name":"Landesbibliothek Steiermark",
    "wof:placetype":"venue"
},
  "geometry": {"coordinates":[15.4383478165,47.0682945251],"type":"Point"}
}