{
  "type": "Feature",
  "properties": {
    "addr:full":"Malser Str 44 Landeck Tirol 6500",
    "addr:postcode":"6500",
    "addr:street":"Str 44;Tirol",
    "iso:country":"AT",
    "sg:address":"Malser Str 44",
    "sg:city":"Landeck",
    "sg:orig_category":"Suchtberatung / Alkohol, Drogen, Zigaretten",
    "sg:phone":"+43 5442 64812",
    "sg:postcode":"6500",
    "sg:province":"Tirol",
    "wof:name":"Verein B.I.N. - Alkohol Medikamente Spielsucht",
    "wof:placetype":"venue"
},
  "geometry": {"coordinates":[10.6277132034,47.1200027466],"type":"Point"}
}