{
  "type": "Feature",
  "properties": {
    "addr:full":"Mo\u00dfbacherg. 10  Wien Wien 1140",
    "addr:housenumber":"10",
    "addr:postcode":"1140",
    "addr:street":"Mossbacherg.",
    "iso:country":"AT",
    "sg:address":"Mo\u00dfbacherg. 10 ",
    "sg:city":"Wien",
    "sg:classifiers":[
        {
            "category":"Professional",
            "subcategory":"Advertising",
            "type":"Services"
        }
    ],
    "sg:phone":"+43 4319 1476140",
    "sg:postcode":"1140",
    "sg:province":"Wien",
    "sg:tags":[
        "communication",
        "medium"
    ],
    "wof:name":"ZMG DIREKTWERBUNG GES.MBH",
    "wof:placetype":"venue"
},
  "geometry": {"coordinates":[16.2696990967,48.1994247437],"type":"Point"}
}