{
  "type": "Feature",
  "properties": {
    "addr:full":"Kamerlweg 37 Wels Ober\u00f6sterreich 4600",
    "addr:housenumber":"37",
    "addr:postcode":"4600",
    "addr:street":"Kamerlweg;Oberoesterreich",
    "iso:country":"AT",
    "sg:address":"Kamerlweg 37",
    "sg:city":"Wels",
    "sg:orig_category":"Papierwaren / Erzeugung U Gro\u00c3\u0178handel",
    "sg:phone":"+43 7242 45628",
    "sg:postcode":"4600",
    "sg:province":"Ober\u00f6sterreich",
    "wof:name":"Moosmayr GesmbH",
    "wof:placetype":"venue"
},
  "geometry": {"coordinates":[14.0517082214,48.1753692627],"type":"Point"}
}