{
  "type": "Feature",
  "properties": {
    "iso:country":"AT",
    "sg:address":"Dr.-Glatz-Str 4",
    "sg:city":"Innsbruck",
    "sg:orig_category":"\u00c3\u201enderungsschneidereien",
    "sg:phone":"+43 512 393147",
    "sg:postcode":"6020",
    "sg:province":"Tirol",
    "wof:name":"Silberberger Elisabeth",
    "wof:placetype":"venue"
},
  "geometry": {"coordinates":[11.4130315781,47.2620239258],"type":"Point"}
}