{
  "type": "Feature",
  "properties": {
    "iso:country":"AT",
    "sg:address":"Steinerner Tisch 27",
    "sg:city":"Ellmau",
    "sg:orig_category":"Museen / Ausstellungen",
    "sg:phone":"+43 5358 44205",
    "sg:postcode":"6352",
    "sg:province":"Tirol",
    "wof:name":"Heimatmuseum Ellmau",
    "wof:placetype":"venue"
},
  "geometry": {"coordinates":[12.2850341797,47.5185890198],"type":"Point"}
}