{
  "type": "Feature",
  "properties": {
    "iso:country":"AT",
    "sg:address":"Soisgegend 78",
    "sg:city":"Kirchberg an der Pielach",
    "sg:orig_category":"Forstverwaltungen",
    "sg:phone":"+43 4327 2272030",
    "sg:postcode":"3204",
    "sg:province":"Nieder\u00f6sterreich",
    "wof:name":"Forst- u Landwirtschaftsverwaltung Prinzbachtal",
    "wof:placetype":"venue"
},
  "geometry": {"coordinates":[15.4621324539,48.0056610107],"type":"Point"}
}