{
  "type": "Feature",
  "properties": {
    "addr:full":"Dorf 247 Sulzberg Vorarlberg 6934",
    "addr:housenumber":"247",
    "addr:postcode":"6934",
    "addr:street":"Dorf",
    "iso:country":"AT",
    "sg:address":"Dorf 247",
    "sg:city":"Sulzberg",
    "sg:orig_category":"Pensionen / Privatzimmer",
    "sg:phone":"+43 5516 2123",
    "sg:postcode":"6934",
    "sg:province":"Vorarlberg",
    "wof:name":"Haus Adlerhorst",
    "wof:placetype":"venue"
},
  "geometry": {"coordinates":[9.9141540527,47.5224990845],"type":"Point"}
}