{
  "type": "Feature",
  "properties": {
    "addr:full":"Gadaunerer Str 34 Bad Hofgastein Salzburg 5630",
    "addr:housenumber":"34",
    "addr:postcode":"5630",
    "addr:street":"Str;Salzburg",
    "iso:country":"AT",
    "sg:address":"Gadaunerer Str 34",
    "sg:city":"Bad Hofgastein",
    "sg:orig_category":"Pensionen / Privatzimmer",
    "sg:phone":"+43 6432 8349",
    "sg:postcode":"5630",
    "sg:province":"Salzburg",
    "wof:name":"Landhaus Heuberger",
    "wof:placetype":"venue"
},
  "geometry": {"coordinates":[13.1134414673,47.163028717],"type":"Point"}
}