{
  "type": "Feature",
  "properties": {
    "addr:full":"Lidmanskygasse 8 Klagenfurt K\u00e4rnten 9020",
    "addr:housenumber":"8",
    "addr:postcode":"9020",
    "addr:street":"Lidmanskygasse;Kaernten",
    "iso:country":"AT",
    "sg:address":"Lidmanskygasse 8",
    "sg:city":"Klagenfurt",
    "sg:classifiers":[
        {
            "category":"Professional",
            "subcategory":"Computer Services",
            "type":"Services"
        }
    ],
    "sg:phone":"+43 463 503705",
    "sg:postcode":"9020",
    "sg:province":"K\u00e4rnten",
    "sg:tags":[
        "services",
        "consulting",
        "internet"
    ],
    "sg:website":"ppp-newmedia.at",
    "wof:name":"Knappinger & Frischengruber Multimedia OEG",
    "wof:placetype":"venue"
},
  "geometry": {"coordinates":[14.3082752228,46.622303009],"type":"Point"}
}