{
  "type": "Feature",
  "properties": {
    "iso:country":"AT",
    "sg:address":"Lastenstr 11",
    "sg:city":"Gunskirchen",
    "sg:orig_category":"Transportunternehmen",
    "sg:phone":"+43 7246 84840",
    "sg:postcode":"4623",
    "sg:province":"Ober\u00f6sterreich",
    "wof:name":"Heppner & Oberndorfer TransportgesmbH",
    "wof:placetype":"venue"
},
  "geometry": {"coordinates":[13.944483757,48.1321029663],"type":"Point"}
}