{
  "type": "Feature",
  "properties": {
    "iso:country":"AT",
    "sg:address":"Hainfelder Str 18",
    "sg:city":"Pottenstein",
    "sg:orig_category":"Autoreparatur",
    "sg:phone":"+43 4326 7282403",
    "sg:postcode":"2563",
    "sg:province":"Nieder\u00f6sterreich",
    "wof:name":"Reiter KFZ-Werkstatt GesmbH",
    "wof:placetype":"venue"
},
  "geometry": {"coordinates":[16.0945243835,47.9604530334],"type":"Point"}
}