{
  "type": "Feature",
  "properties": {
    "addr:full":"Nr 160 St. Marienkirchen Ober\u00f6sterreich 4774",
    "addr:postcode":"4774",
    "addr:street":"Nr 160",
    "iso:country":"AT",
    "sg:address":"Nr 160",
    "sg:city":"St. Marienkirchen",
    "sg:orig_category":"Banken U Sparkassen",
    "sg:phone":"+43 4377 1122680",
    "sg:postcode":"4774",
    "sg:province":"Ober\u00f6sterreich",
    "wof:name":"Raiffeisenbank St Marienkirchen bei Sch\u00e4rding regGenmbH",
    "wof:placetype":"venue"
},
  "geometry": {"coordinates":[13.4512290955,48.3879585266],"type":"Point"}
}