{
  "type": "Feature",
  "properties": {
    "addr:full":"Marburger Kai 47 Graz Steiermark 8010",
    "addr:housenumber":"47",
    "addr:postcode":"8010",
    "addr:street":"Marburger Kai",
    "iso:country":"AT",
    "sg:address":"Marburger Kai 47",
    "sg:city":"Graz",
    "sg:classifiers":[
        {
            "category":"Manufacturing",
            "subcategory":"Wood Products",
            "type":"Manufacturing & Wholesale Goods"
        }
    ],
    "sg:phone":"+43 316 8277080",
    "sg:postcode":"8010",
    "sg:province":"Steiermark",
    "sg:tags":[
        "lumber"
    ],
    "sg:website":"siag.at",
    "wof:name":"Siag Holzexport Ges.m.b.H.",
    "wof:placetype":"venue"
},
  "geometry": {"coordinates":[15.4358787537,47.0677719116],"type":"Point"}
}