{
  "type": "Feature",
  "properties": {
    "addr:full":"Dr.-Reinhard-Machold-Str 3 St. Lorenzen im M\u00fcrztal Steiermark 8642",
    "addr:housenumber":"3",
    "addr:postcode":"8642",
    "addr:street":"Dr.-Reinhard-Machold-Str",
    "iso:country":"AT",
    "sg:address":"Dr.-Reinhard-Machold-Str 3",
    "sg:city":"St. Lorenzen im M\u00fcrztal",
    "sg:orig_category":"Zoologiebedarf",
    "sg:phone":"+43 4338 6234008",
    "sg:postcode":"8642",
    "sg:province":"Steiermark",
    "wof:name":"Fressnapf Handels GmbH",
    "wof:placetype":"venue"
},
  "geometry": {"coordinates":[15.3444776535,47.4687461853],"type":"Point"}
}