{
  "type": "Feature",
  "properties": {
    "iso:country":"AT",
    "sg:address":"Paracelsusg 8",
    "sg:city":"Wien",
    "sg:orig_category":"Immobilienverwaltungen",
    "sg:phone":"+43 1 7125354",
    "sg:postcode":"1030",
    "sg:province":"Wien",
    "wof:name":"Polterauer Ingrid",
    "wof:placetype":"venue"
},
  "geometry": {"coordinates":[16.3945846558,48.2071876526],"type":"Point"}
}