{
  "type": "Feature",
  "properties": {
    "addr:full":"Franz-Michael-Felder-Str 10a Hohenems Vorarlberg 6845",
    "addr:housenumber":"10a",
    "addr:postcode":"6845",
    "addr:street":"Franz-Michael-Felder-Str",
    "iso:country":"AT",
    "sg:address":"Franz-Michael-Felder-Str 10a",
    "sg:city":"Hohenems",
    "sg:orig_category":"Stickereien",
    "sg:phone":"+43 4355 76732460",
    "sg:postcode":"6845",
    "sg:province":"Vorarlberg",
    "wof:name":"Nachbaur Manfred",
    "wof:placetype":"venue"
},
  "geometry": {"coordinates":[9.6848773956,47.3610687256],"type":"Point"}
}