{
  "type": "Feature",
  "properties": {
    "iso:country":"AT",
    "sg:address":"Festwiese 14",
    "sg:city":"Gols",
    "sg:classifiers":[
        {
            "category":"Travel",
            "subcategory":"Hotels & Motels",
            "type":"Entertainment"
        }
    ],
    "sg:phone":"+43 2173 2346",
    "sg:postcode":"7122",
    "sg:province":"Burgenland",
    "wof:name":"Birkenhof - Das Landhotel & Das Weingut",
    "wof:placetype":"venue"
},
  "geometry": {"coordinates":[16.9225177765,47.8928260803],"type":"Point"}
}