{
  "type": "Feature",
  "properties": {
    "iso:country":"AT",
    "sg:address":"Nr 52",
    "sg:city":"Kappel am Krappfeld",
    "sg:orig_category":"Banken U Sparkassen",
    "sg:phone":"+43 4342 6223670",
    "sg:postcode":"9321",
    "sg:province":"K\u00e4rnten",
    "wof:name":"Bankomat d Raiffeisen-Bezirksbank St Veit a d Glan-Feldkirchen",
    "wof:placetype":"venue"
},
  "geometry": {"coordinates":[14.4859771729,46.8383102417],"type":"Point"}
}