{
  "type": "Feature",
  "properties": {
    "addr:full":"Kirchberg 23 Fontanella Vorarlberg 6733",
    "addr:housenumber":"23",
    "addr:postcode":"6733",
    "addr:street":"Kirchberg",
    "iso:country":"AT",
    "sg:address":"Kirchberg 23",
    "sg:city":"Fontanella",
    "sg:classifiers":[
        {
            "category":"Travel",
            "subcategory":"Hotels & Motels",
            "type":"Entertainment"
        }
    ],
    "sg:phone":"+43 4355 5452220",
    "sg:postcode":"6733",
    "sg:province":"Vorarlberg",
    "wof:name":"Hotel Post",
    "wof:placetype":"venue"
},
  "geometry": {"coordinates":[9.9078922272,47.2494316101],"type":"Point"}
}