{
  "type": "Feature",
  "properties": {
    "iso:country":"AT",
    "sg:address":"Kapuzinerg 6",
    "sg:city":"Waidhofen an der Ybbs",
    "sg:orig_category":"Behindertenhilfsmittel",
    "sg:phone":"+43 7442 551552177",
    "sg:postcode":"3340",
    "sg:province":"Nieder\u00f6sterreich",
    "wof:name":"mechatron Schnabler & Partner OEG",
    "wof:placetype":"venue"
},
  "geometry": {"coordinates":[14.7766208649,47.9588241577],"type":"Point"}
}