{
  "type": "Feature",
  "properties": {
    "iso:country":"AT",
    "sg:address":"Landstr 30",
    "sg:city":"N\u00fcziders",
    "sg:orig_category":"Geschenkartikel",
    "sg:phone":"+43 5552 30725",
    "sg:postcode":"6714",
    "sg:province":"Vorarlberg",
    "wof:name":"Idee Handels GmbH",
    "wof:placetype":"venue"
},
  "geometry": {"coordinates":[9.7923030853,47.1676712036],"type":"Point"}
}