{
  "type": "Feature",
  "properties": {
    "addr:full":"Helenenstr 40/41 Baden Nieder\u00f6sterreich 2500",
    "addr:housenumber":"40 / 41",
    "addr:postcode":"2500",
    "addr:street":"Helenenstr;Niederoesterreich",
    "iso:country":"AT",
    "sg:address":"Helenenstr 40/41",
    "sg:city":"Baden",
    "sg:orig_category":"Suchtberatung / Alkohol, Drogen, Zigaretten",
    "sg:phone":"+43 2252 259447",
    "sg:postcode":"2500",
    "sg:province":"Nieder\u00f6sterreich",
    "wof:name":"Anton-Proksch-Institut Suchtberatung Baden",
    "wof:placetype":"venue"
},
  "geometry": {"coordinates":[16.2172985077,48.0062675476],"type":"Point"}
}