{
  "type": "Feature",
  "properties": {
    "addr:full":"Buchenstrasse 10 Elixhausen Salzburg 5161",
    "addr:housenumber":"10",
    "addr:postcode":"5161",
    "addr:street":"Buchenstrasse;Salzburg",
    "iso:country":"AT",
    "sg:address":"Buchenstrasse 10",
    "sg:city":"Elixhausen",
    "sg:classifiers":[
        {
            "category":"Shopping",
            "subcategory":"Clothing, Apparel, & Fashions",
            "type":"Retail Goods"
        }
    ],
    "sg:phone":"+43 662 481442",
    "sg:postcode":"5161",
    "sg:province":"Salzburg",
    "sg:tags":[
        "dress",
        "dirndl"
    ],
    "sg:website":"christa-moden.at",
    "wof:name":"Christa Moden GmbH",
    "wof:placetype":"venue"
},
  "geometry": {"coordinates":[13.0649681091,47.8683509827],"type":"Point"}
}