{
  "type": "Feature",
  "properties": {
    "iso:country":"AT",
    "sg:address":"Gadaunerer Str 40c",
    "sg:city":"Bad Hofgastein",
    "sg:orig_category":"Ergotherapie",
    "sg:phone":"+43 4364 328893",
    "sg:postcode":"5630",
    "sg:province":"Salzburg",
    "wof:name":"Krainz Barbara",
    "wof:placetype":"venue"
},
  "geometry": {"coordinates":[13.1138324738,47.1626472473],"type":"Point"}
}