{
  "type": "Feature",
  "properties": {
    "addr:full":"Hauptstrasse 168 Prutz Tirol 6522",
    "addr:housenumber":"168",
    "addr:postcode":"6522",
    "addr:street":"Hauptstrasse;Tirol",
    "iso:country":"AT",
    "sg:address":"Hauptstrasse 168",
    "sg:city":"Prutz",
    "sg:classifiers":[
        {
            "category":"Manufacturing",
            "subcategory":"Wood Products",
            "type":"Manufacturing & Wholesale Goods"
        }
    ],
    "sg:phone":"+43 5472 6330",
    "sg:postcode":"6522",
    "sg:province":"Tirol",
    "sg:tags":[
        "made",
        "balcony"
    ],
    "sg:website":"holzcenter.at",
    "wof:name":"Holz-Center Ortner Ges.m.b.H. & Co KG",
    "wof:placetype":"venue"
},
  "geometry": {"coordinates":[10.6638202667,47.0765533447],"type":"Point"}
}