{
  "type": "Feature",
  "properties": {
    "iso:country":"AT",
    "sg:address":"Nr 108",
    "sg:city":"Kramsach",
    "sg:orig_category":"Minigolfanlagen U -Bedarf",
    "sg:phone":"+43 4353 3764979",
    "sg:postcode":"6233",
    "sg:province":"Tirol",
    "wof:name":"Lettenbichler Alfred Minigolf & PitPat",
    "wof:placetype":"venue"
},
  "geometry": {"coordinates":[11.8835477829,47.4473342896],"type":"Point"}
}