{
  "type": "Feature",
  "properties": {
    "iso:country":"AT",
    "sg:address":"Rechte Wienzeile 71",
    "sg:city":"Wien",
    "sg:orig_category":"Psychotherapie",
    "sg:phone":"+43 699 19413682",
    "sg:postcode":"1050",
    "sg:province":"Wien",
    "wof:name":"PARDUN - Institut f ganzheitl. Gesundheitsf\u00f6rd., Beratung & Therapie, DSA-Solveig Kriegler",
    "wof:placetype":"venue"
},
  "geometry": {"coordinates":[16.3550262451,48.1949157715],"type":"Point"}
}