{
  "type": "Feature",
  "properties": {
    "addr:full":"Hauptpl 12 Wieselburg an der Erlauf Nieder\u00f6sterreich 3250",
    "addr:housenumber":"12",
    "addr:postcode":"3250",
    "addr:street":"Hauptpl",
    "iso:country":"AT",
    "sg:address":"Hauptpl 12",
    "sg:city":"Wieselburg an der Erlauf",
    "sg:orig_category":"Optiker",
    "sg:phone":"+43 4374 1652326",
    "sg:postcode":"3250",
    "sg:province":"Nieder\u00f6sterreich",
    "wof:name":"Forster Optik GesmbH",
    "wof:placetype":"venue"
},
  "geometry": {"coordinates":[15.1388072968,48.1314353943],"type":"Point"}
}