{
  "type": "Feature",
  "properties": {
    "addr:full":"Estepl 6 Wien Wien 1030",
    "addr:housenumber":"6",
    "addr:postcode":"1030",
    "addr:street":"Estepl",
    "iso:country":"AT",
    "sg:address":"Estepl 6",
    "sg:city":"Wien",
    "sg:orig_category":"Restaurants: Italienisch",
    "sg:phone":"+43 1 7155148",
    "sg:postcode":"1030",
    "sg:province":"Wien",
    "wof:name":"MEZZO",
    "wof:placetype":"venue"
},
  "geometry": {"coordinates":[16.3897533417,48.2053375244],"type":"Point"}
}