{
  "type": "Feature",
  "properties": {
    "iso:country":"AT",
    "sg:address":"Bundesstr 395",
    "sg:city":"Nauders",
    "sg:orig_category":"Pensionen / Privatzimmer",
    "sg:phone":"+43 5473 87351",
    "sg:postcode":"6543",
    "sg:province":"Tirol",
    "wof:name":"Bikerpension Landhaus Engadin",
    "wof:placetype":"venue"
},
  "geometry": {"coordinates":[10.4984226227,46.8940391541],"type":"Point"}
}