{
  "type": "Feature",
  "properties": {
    "addr:full":"Landstr 23 Fohnsdorf Steiermark 8753",
    "addr:housenumber":"23",
    "addr:postcode":"8753",
    "addr:street":"Landstr",
    "iso:country":"AT",
    "sg:address":"Landstr 23",
    "sg:city":"Fohnsdorf",
    "sg:orig_category":"Erdbau",
    "sg:phone":"+43 4335 7334014",
    "sg:postcode":"8753",
    "sg:province":"Steiermark",
    "wof:name":"Erdbau und Stein-GmbH",
    "wof:placetype":"venue"
},
  "geometry": {"coordinates":[14.6820259094,47.2090072632],"type":"Point"}
}