{
  "type": "Feature",
  "properties": {
    "iso:country":"AT",
    "sg:address":"Schlo\u00df Jedenspeigen 1",
    "sg:city":"Jedenspeigen",
    "sg:orig_category":"Museen / Ausstellungen",
    "sg:phone":"+43 4325 368468",
    "sg:postcode":"2264",
    "sg:province":"Nieder\u00f6sterreich",
    "wof:name":"Schlo\u00df Jedenspeigen - Ausstellungsleitung",
    "wof:placetype":"venue"
},
  "geometry": {"coordinates":[16.865945816,48.5050163269],"type":"Point"}
}