{
  "type": "Feature",
  "properties": {
    "addr:full":"Untere Donaustr 13-15 Wien Wien 1020",
    "addr:postcode":"13-15;1020",
    "addr:street":"Untere Donaustr",
    "iso:country":"AT",
    "sg:address":"Untere Donaustr 13-15",
    "sg:city":"Wien",
    "sg:orig_category":"Telekommunikation",
    "sg:phone":"+43 1 21193",
    "sg:postcode":"1020",
    "sg:province":"Wien",
    "wof:name":"OMNITEC Informationstechnologie Systemservice GmbH",
    "wof:placetype":"venue"
},
  "geometry": {"coordinates":[16.3816261292,48.2124938965],"type":"Point"}
}