{
  "type": "Feature",
  "properties": {
    "addr:full":"Traberg Ober\u00f6sterreich 4183",
    "addr:postcode":"4183",
    "addr:street":"Oberoesterreich",
    "iso:country":"AT",
    "sg:city":"Traberg",
    "sg:orig_category":"Matratzen",
    "sg:phone":"+43 7218 458",
    "sg:postcode":"4183",
    "sg:province":"Ober\u00f6sterreich",
    "wof:name":"Naturfabrik Ahorn Schneider",
    "wof:placetype":"venue"
},
  "geometry": {"coordinates":[-103.4397277832,42.765663147],"type":"Point"}
}