{
  "type": "Feature",
  "properties": {
    "iso:country":"AT",
    "sg:address":"Schwimmbadg 158",
    "sg:city":"Altenmarkt im Pongau",
    "sg:classifiers":[
        {
            "category":"Travel",
            "subcategory":"Hotels & Motels",
            "type":"Entertainment"
        }
    ],
    "sg:phone":"+43 6452 55210",
    "sg:postcode":"5541",
    "sg:province":"Salzburg",
    "wof:name":"Hotel Barbarahof",
    "wof:placetype":"venue"
},
  "geometry": {"coordinates":[13.4227304459,47.3759117126],"type":"Point"}
}