{
  "type": "Feature",
  "properties": {
    "iso:country":"AT",
    "sg:address":"Schulstr 6",
    "sg:city":"Ober-Grafendorf",
    "sg:orig_category":"Volksschulen",
    "sg:phone":"+43 4327 472351",
    "sg:postcode":"3200",
    "sg:province":"Nieder\u00f6sterreich",
    "wof:name":"Volksschule",
    "wof:placetype":"venue"
},
  "geometry": {"coordinates":[15.5447149277,48.1515655518],"type":"Point"}
}