{
  "type": "Feature",
  "properties": {
    "iso:country":"AT",
    "sg:city":"Mariahof",
    "sg:classifiers":[
        {
            "category":"Home & Garden",
            "subcategory":"Garden Supply",
            "type":"Retail Goods"
        }
    ],
    "sg:phone":"+43 3584 31310",
    "sg:postcode":"8812",
    "sg:province":"Steiermark",
    "sg:tags":[
        "schotter",
        "sand",
        "u"
    ],
    "wof:name":"ZB Sand- und Kieswerke GesmbH",
    "wof:placetype":"venue"
},
  "geometry": {"coordinates":[14.3994102478,47.0992660522],"type":"Point"}
}