{
  "type": "Feature",
  "properties": {
    "iso:country":"AT",
    "sg:address":"Andreas-Hofer-Str 43",
    "sg:city":"Innsbruck",
    "sg:orig_category":"Fleisch-, Wurst- U Selchwaren / Erzeugung U Gro\u00c3\u0178handel",
    "sg:phone":"+43 4352 736666",
    "sg:postcode":"6020",
    "sg:province":"Tirol",
    "wof:name":"Gasser Speck GesmbH",
    "wof:placetype":"venue"
},
  "geometry": {"coordinates":[11.3920326233,47.2578849792],"type":"Point"}
}