{
  "type": "Feature",
  "properties": {
    "iso:country":"AT",
    "sg:address":"Anton Bruckner-Str 9",
    "sg:city":"Wels",
    "sg:orig_category":"Fleischereimaschinen U -Einrichtungen",
    "sg:phone":"+43 7242 64491",
    "sg:postcode":"4600",
    "sg:province":"Ober\u00f6sterreich",
    "wof:name":"Leidenfrost Eberhard GesmbH",
    "wof:placetype":"venue"
},
  "geometry": {"coordinates":[14.0238008499,48.1702194214],"type":"Point"}
}