{
  "type": "Feature",
  "properties": {
    "iso:country":"AT",
    "sg:address":"Ausstellungsstr",
    "sg:city":"Wien",
    "sg:orig_category":"Non-Classified Establishments",
    "sg:phone":"+43 1 7286285",
    "sg:postcode":"1020",
    "sg:province":"Wien",
    "wof:name":"TAXI-TEL Standplatztelefon Betriebs GmbH",
    "wof:placetype":"venue"
},
  "geometry": {"coordinates":[16.3958091736,48.2179031372],"type":"Point"}
}