{
  "type": "Feature",
  "properties": {
    "addr:full":"Billrothstr 85 Wien Wien 1190",
    "addr:housenumber":"85",
    "addr:postcode":"1190",
    "addr:street":"Billrothstr",
    "iso:country":"AT",
    "sg:address":"Billrothstr 85",
    "sg:city":"Wien",
    "sg:orig_category":"Papier- U Schreibwaren / Einzelhandel",
    "sg:phone":"+43 1 3203137",
    "sg:postcode":"1190",
    "sg:province":"Wien",
    "sg:website":"www.stoeger.net",
    "wof:name":"St\u00f6ger M GesmbH",
    "wof:placetype":"venue"
},
  "geometry": {"coordinates":[16.3426437378,48.2455329895],"type":"Point"}
}