{
  "type": "Feature",
  "properties": {
    "addr:full":"Schirmerstr 13 Leonding Ober\u00f6sterreich 4060",
    "addr:housenumber":"13",
    "addr:postcode":"4060",
    "addr:street":"Schirmerstr",
    "iso:country":"AT",
    "sg:address":"Schirmerstr 13",
    "sg:city":"Leonding",
    "sg:orig_category":"Offsetdruckereien",
    "sg:phone":"+43 732 370901",
    "sg:postcode":"4060",
    "sg:province":"Ober\u00f6sterreich",
    "wof:name":"Druckreif Druckerei Frank",
    "wof:placetype":"venue"
},
  "geometry": {"coordinates":[14.2736673355,48.2543067932],"type":"Point"}
}