{
  "type": "Feature",
  "properties": {
    "addr:full":"Dr.-Mehr-Weg 1/2 M\u00fcnzbach Ober\u00f6sterreich 4323",
    "addr:housenumber":"1 / 2",
    "addr:postcode":"4323",
    "addr:street":"Dr.-Mehr-Weg;Oberoesterreich",
    "iso:country":"AT",
    "sg:address":"Dr.-Mehr-Weg 1/2",
    "sg:city":"M\u00fcnzbach",
    "sg:orig_category":"Musikgruppen",
    "sg:phone":"+43 7264 4039",
    "sg:postcode":"4323",
    "sg:province":"Ober\u00f6sterreich",
    "wof:name":"Musikverein M\u00fcnzbach",
    "wof:placetype":"venue"
},
  "geometry": {"coordinates":[14.7124452591,48.2659797668],"type":"Point"}
}