{
  "type": "Feature",
  "properties": {
    "addr:full":"Lange G 5 Wiener Neustadt Nieder\u00f6sterreich 2700",
    "addr:housenumber":"5",
    "addr:postcode":"2700",
    "addr:street":"Lange G",
    "iso:country":"AT",
    "sg:address":"Lange G 5",
    "sg:city":"Wiener Neustadt",
    "sg:orig_category":"Bars-Cafes",
    "sg:phone":"+43 664 3553600",
    "sg:postcode":"2700",
    "sg:province":"Nieder\u00f6sterreich",
    "wof:name":"Tanzbar Erika",
    "wof:placetype":"venue"
},
  "geometry": {"coordinates":[16.241853714,47.8122711182],"type":"Point"}
}