{
  "type": "Feature",
  "properties": {
    "addr:full":"Paschinger Str 26 Marchtrenk Ober\u00f6sterreich 4614",
    "addr:postcode":"4614",
    "addr:street":"Str 26",
    "iso:country":"AT",
    "sg:address":"Paschinger Str 26",
    "sg:city":"Marchtrenk",
    "sg:orig_category":"Blumengro\u00c3\u0178handel",
    "sg:phone":"+43 7243 51550",
    "sg:postcode":"4614",
    "sg:province":"Ober\u00f6sterreich",
    "wof:name":"Ph\u00f6nix-BlumenimportgesmbH",
    "wof:placetype":"venue"
},
  "geometry": {"coordinates":[14.101975441,48.205821991],"type":"Point"}
}