{
  "type": "Feature",
  "properties": {
    "iso:country":"AT",
    "sg:address":"Harterhofweg 91",
    "sg:city":"Innsbruck",
    "sg:orig_category":"Holzhandel",
    "sg:phone":"+43 512 274792",
    "sg:postcode":"6020",
    "sg:province":"Tirol",
    "wof:name":"Antik-Tischlerei Singer",
    "wof:placetype":"venue"
},
  "geometry": {"coordinates":[11.3317327499,47.2631950378],"type":"Point"}
}