{
  "type": "Feature",
  "properties": {
    "addr:full":"Brandhofg 22 Graz Steiermark 8010",
    "addr:housenumber":"22",
    "addr:postcode":"8010",
    "addr:street":"Brandhofg",
    "iso:country":"AT",
    "sg:address":"Brandhofg 22",
    "sg:city":"Graz",
    "sg:orig_category":"Immobilienmakler",
    "sg:phone":"+43 4331 63281810",
    "sg:postcode":"8010",
    "sg:province":"Steiermark",
    "wof:name":"GALA Immobilien GmbH",
    "wof:placetype":"venue"
},
  "geometry": {"coordinates":[15.4483232498,47.0724449158],"type":"Point"}
}