{
  "type": "Feature",
  "properties": {
    "iso:country":"AT",
    "sg:address":"Klagenfurter Str 15",
    "sg:city":"Feldkirchen in K\u00e4rnten",
    "sg:orig_category":"Fahrschulen",
    "sg:phone":"+43 4342 767979",
    "sg:postcode":"9560",
    "sg:province":"K\u00e4rnten",
    "wof:name":"Fahrschule Ing W Werzin",
    "wof:placetype":"venue"
},
  "geometry": {"coordinates":[14.0973434448,46.718963623],"type":"Point"}
}