{
  "type": "Feature",
  "properties": {
    "addr:full":"Bahnhofstr 42 W\u00f6rgl Tirol 6300",
    "addr:housenumber":"42",
    "addr:postcode":"6300",
    "addr:street":"Bahnhofstr;Tirol",
    "iso:country":"AT",
    "sg:address":"Bahnhofstr 42",
    "sg:city":"W\u00f6rgl",
    "sg:orig_category":"Textilreinigung",
    "sg:phone":"+43 5332 75915",
    "sg:postcode":"6300",
    "sg:province":"Tirol",
    "wof:name":"Chwalla Kleiderreinigungs AG",
    "wof:placetype":"venue"
},
  "geometry": {"coordinates":[-69.3131027222,-51.6091995239],"type":"Point"}
}