{
  "type": "Feature",
  "properties": {
    "iso:country":"AT",
    "sg:address":"Stadtpl 5/2",
    "sg:city":"Steyr",
    "sg:orig_category":"Freizeitangebote U -Einrichtungen",
    "sg:phone":"+43 4372 5254061",
    "sg:postcode":"4400",
    "sg:province":"Ober\u00f6sterreich",
    "wof:name":"Sch\u00fcler-Internet-Cafe Clevernet",
    "wof:placetype":"venue"
},
  "geometry": {"coordinates":[14.4200572968,48.0401153564],"type":"Point"}
}