{
  "type": "Feature",
  "properties": {
    "addr:full":"Nr 167 Feldbach Steiermark 8330",
    "addr:postcode":"8330",
    "addr:street":"Nr 167",
    "iso:country":"AT",
    "sg:address":"Nr 167",
    "sg:city":"Feldbach",
    "sg:orig_category":"Feuerwehren",
    "sg:phone":"+43 3152 8233",
    "sg:postcode":"8330",
    "sg:province":"Steiermark",
    "wof:name":"Freiwillige Feuerwehr M\u00fchldorf b Feldbach",
    "wof:placetype":"venue"
},
  "geometry": {"coordinates":[15.8882513046,46.952747345],"type":"Point"}
}