{
  "type": "Feature",
  "properties": {
    "addr:full":"Sparkassenstr 31 St. Johann im Pongau Salzburg 5600",
    "addr:housenumber":"31",
    "addr:postcode":"5600",
    "addr:street":"Sparkassenstr;Salzburg",
    "iso:country":"AT",
    "sg:address":"Sparkassenstr 31",
    "sg:city":"St. Johann im Pongau",
    "sg:orig_category":"Volksschulen",
    "sg:phone":"+43 6412 86840",
    "sg:postcode":"5600",
    "sg:province":"Salzburg",
    "wof:name":"Neue Volksschule",
    "wof:placetype":"venue"
},
  "geometry": {"coordinates":[13.2056665421,47.3583450317],"type":"Point"}
}