{
  "type": "Feature",
  "properties": {
    "iso:country":"AT",
    "sg:address":"Leopoldsgraben 27",
    "sg:city":"Klosterneuburg",
    "sg:orig_category":"Technische Bedarfsartikel",
    "sg:phone":"+43 4322 4326683",
    "sg:postcode":"3400",
    "sg:province":"Nieder\u00f6sterreich",
    "wof:name":"Ditechno Handels GmbH",
    "wof:placetype":"venue"
},
  "geometry": {"coordinates":[16.2957038879,48.3086242676],"type":"Point"}
}