{
  "type": "Feature",
  "properties": {
    "addr:full":"Am Sonnenhang 19 Lenzing Ober\u00f6sterreich 4860",
    "addr:housenumber":"19",
    "addr:postcode":"4860",
    "addr:street":"Am Sonnenhang",
    "iso:country":"AT",
    "sg:address":"Am Sonnenhang 19",
    "sg:city":"Lenzing",
    "sg:orig_category":"Bauunternehmen",
    "sg:phone":"+43 767295944",
    "sg:postcode":"4860",
    "sg:province":"Ober\u00f6sterreich",
    "wof:name":"Schaufler Christian Ing Bau GmbH",
    "wof:placetype":"venue"
},
  "geometry": {"coordinates":[13.5984306335,47.9685249329],"type":"Point"}
}