{
  "type": "Feature",
  "properties": {
    "addr:full":"Hoher Markt 12 Wien Wien 1010",
    "addr:housenumber":"12",
    "addr:postcode":"1010",
    "addr:street":"Hoher Markt",
    "iso:country":"AT",
    "sg:address":"Hoher Markt 12",
    "sg:city":"Wien",
    "sg:orig_category":"Versicherungsunternehmen",
    "sg:phone":"+43 1 534740",
    "sg:postcode":"1010",
    "sg:province":"Wien",
    "wof:name":"Der Anker Allgemeine Versicherung AG-LdsDion f Wien und N\u00d6",
    "wof:placetype":"venue"
},
  "geometry": {"coordinates":[16.3734550476,48.210521698],"type":"Point"}
}