{
  "type": "Feature",
  "properties": {
    "addr:full":"Keferg 10 Wien Wien 1140",
    "addr:housenumber":"10",
    "addr:postcode":"1140",
    "addr:street":"Keferg",
    "iso:country":"AT",
    "sg:address":"Keferg 10",
    "sg:city":"Wien",
    "sg:orig_category":"Dolmetscher",
    "sg:phone":"+43 1 9141204",
    "sg:postcode":"1140",
    "sg:province":"Wien",
    "wof:name":"Hamb\u00f6ck Dominique",
    "wof:placetype":"venue"
},
  "geometry": {"coordinates":[16.2788352966,48.1951255798],"type":"Point"}
}