{
  "type": "Feature",
  "properties": {
    "addr:full":"Allerheiligen 66 Perg Ober\u00f6sterreich 4320",
    "addr:housenumber":"66",
    "addr:postcode":"4320",
    "addr:street":"Allerheiligen",
    "iso:country":"AT",
    "sg:address":"Allerheiligen 66",
    "sg:city":"Perg",
    "sg:orig_category":"Baumeister",
    "sg:phone":"+43 4372 6257241",
    "sg:postcode":"4320",
    "sg:province":"Ober\u00f6sterreich",
    "wof:name":"Aumayer Bau-GesmbH & Co KG",
    "wof:placetype":"venue"
},
  "geometry": {"coordinates":[14.6340551376,48.2500610352],"type":"Point"}
}