{
  "type": "Feature",
  "properties": {
    "addr:full":"Graben 62 Amstetten Nieder\u00f6sterreich 3300",
    "addr:housenumber":"62",
    "addr:postcode":"3300",
    "addr:street":"Graben;Niederoesterreich",
    "iso:country":"AT",
    "sg:address":"Graben 62",
    "sg:city":"Amstetten",
    "sg:classifiers":[
        {
            "category":"Home & Garden",
            "subcategory":"Kitchen Supply",
            "type":"Retail Goods"
        }
    ],
    "sg:phone":"+43 4367 66680207",
    "sg:postcode":"3300",
    "sg:province":"Nieder\u00f6sterreich",
    "sg:tags":[
        "espresso-",
        "u",
        "kaffeemaschinen"
    ],
    "sg:website":"wildberger.cc",
    "wof:name":"AMCO Wildberger Getr\u00e4nkeautomaten - Gastroger\u00e4te FAEMA",
    "wof:placetype":"venue"
},
  "geometry": {"coordinates":[14.8706607819,48.1244812012],"type":"Point"}
}