{
  "type": "Feature",
  "properties": {
    "iso:country":"AT",
    "sg:address":"Egger-Lienz-Str. 8 ",
    "sg:city":"Traun",
    "sg:classifiers":[
        {
            "category":"Manufacturing",
            "subcategory":"Metals",
            "type":"Manufacturing & Wholesale Goods"
        }
    ],
    "sg:phone":"+43 4372 2961501",
    "sg:postcode":"4050",
    "sg:province":"Ober\u00f6sterreich",
    "sg:tags":[
        "metallurgy",
        "metalworking"
    ],
    "wof:name":"BUG ALUTECHNIC GMBH",
    "wof:placetype":"venue"
},
  "geometry": {"coordinates":[14.2741203308,48.2363014221],"type":"Point"}
}