{
  "type": "Feature",
  "properties": {
    "addr:full":"Sportplatzstr 323 Mayrhofen Tirol 6290",
    "addr:housenumber":"323",
    "addr:postcode":"6290",
    "addr:street":"Mayrhofen Tirol",
    "iso:country":"AT",
    "sg:address":"Sportplatzstr 323",
    "sg:city":"Mayrhofen",
    "sg:orig_category":"Pensionen / Privatzimmer",
    "sg:phone":"+43 5285 62438",
    "sg:postcode":"6290",
    "sg:province":"Tirol",
    "wof:name":"Lechner Eva",
    "wof:placetype":"venue"
},
  "geometry": {"coordinates":[11.8675518036,47.1662368774],"type":"Point"}
}