{
  "type": "Feature",
  "properties": {
    "iso:country":"AT",
    "sg:address":"Simmeringer Hauptstr 77",
    "sg:city":"Wien",
    "sg:orig_category":"Schlossereien",
    "sg:phone":"+43 664 3256253",
    "sg:postcode":"1110",
    "sg:province":"Wien",
    "wof:name":"Alscher Rudolf KG",
    "wof:placetype":"venue"
},
  "geometry": {"coordinates":[16.4133701324,48.1774139404],"type":"Point"}
}