{
  "type": "Feature",
  "properties": {
    "addr:full":"Br\u00fcndlg 17 Gro\u00df-Enzersdorf Nieder\u00f6sterreich 2301",
    "addr:housenumber":"17",
    "addr:postcode":"2301",
    "addr:street":"Bruendlg;Niederoesterreich",
    "iso:country":"AT",
    "sg:address":"Br\u00fcndlg 17",
    "sg:city":"Gro\u00df-Enzersdorf",
    "sg:orig_category":"Reinigungsbedarf U Reinigungsmittel",
    "sg:phone":"+43 2215 2420",
    "sg:postcode":"2301",
    "sg:province":"Nieder\u00f6sterreich",
    "sg:website":"www.aeco-clean.com",
    "wof:name":"AECO CLEAN - Microfaser",
    "wof:placetype":"venue"
},
  "geometry": {"coordinates":[16.5502796173,48.2014656067],"type":"Point"}
}