{
  "type": "Feature",
  "properties": {
    "addr:full":"Kirchpl 10 Wattens Tirol 6112",
    "addr:housenumber":"10",
    "addr:postcode":"6112",
    "addr:street":"Kirchpl;Tirol",
    "iso:country":"AT",
    "sg:address":"Kirchpl 10",
    "sg:city":"Wattens",
    "sg:orig_category":"Optiker",
    "sg:phone":"+43 5224 57304",
    "sg:postcode":"6112",
    "sg:province":"Tirol",
    "wof:name":"Endemann Brillenstudio",
    "wof:placetype":"venue"
},
  "geometry": {"coordinates":[11.5927505493,47.2925987244],"type":"Point"}
}