{
  "type": "Feature",
  "properties": {
    "addr:full":"Bahnhofstr 31 Feistritz an der Drau K\u00e4rnten 9710",
    "addr:housenumber":"31",
    "addr:postcode":"9710",
    "addr:street":"Bahnhofstr",
    "iso:country":"AT",
    "sg:address":"Bahnhofstr 31",
    "sg:city":"Feistritz an der Drau",
    "sg:orig_category":"Drogerien",
    "sg:phone":"+43 4342 452234",
    "sg:postcode":"9710",
    "sg:province":"K\u00e4rnten",
    "wof:name":"Laznia Irene",
    "wof:placetype":"venue"
},
  "geometry": {"coordinates":[13.6680831909,46.7062416077],"type":"Point"}
}