{
  "type": "Feature",
  "properties": {
    "iso:country":"AT",
    "sg:address":"Rottstr. 24",
    "sg:city":"Wien",
    "sg:classifiers":[
        {
            "category":"Shopping",
            "type":"Retail Goods"
        }
    ],
    "sg:phone":"+43 4319 1030",
    "sg:postcode":"1140",
    "sg:province":"Wien",
    "sg:tags":[
        "finished",
        "-",
        "metallic"
    ],
    "wof:name":"KSB \u00d6STERREICH GESMBH",
    "wof:placetype":"venue"
},
  "geometry": {"coordinates":[16.2991676331,48.1962966919],"type":"Point"}
}