{
  "type": "Feature",
  "properties": {
    "iso:country":"AT",
    "sg:address":"Wilhelm-Exner-G 30",
    "sg:city":"Wien",
    "sg:classifiers":[
        {
            "category":"Restaurant",
            "type":"Food & Drink"
        }
    ],
    "sg:phone":"+43 4313 195061",
    "sg:postcode":"1090",
    "sg:province":"Wien",
    "wof:name":"Restaurant Danin",
    "wof:placetype":"venue"
},
  "geometry": {"coordinates":[16.352640152,48.2244338989],"type":"Point"}
}