{
  "type": "Feature",
  "properties": {
    "addr:full":"Sonnweg 284 Wals Salzburg 5071",
    "addr:housenumber":"284",
    "addr:postcode":"5071",
    "addr:street":"Sonnweg;Salzburg",
    "iso:country":"AT",
    "sg:address":"Sonnweg 284",
    "sg:city":"Wals",
    "sg:orig_category":"Hobbyvereine",
    "sg:phone":"+43 662 850940",
    "sg:postcode":"5071",
    "sg:province":"Salzburg",
    "wof:name":"\u00f6sterreichischer Verein f Deutsche Sch\u00e4ferhunde",
    "wof:placetype":"venue"
},
  "geometry": {"coordinates":[12.9575099945,47.7912750244],"type":"Point"}
}