{
  "type": "Feature",
  "properties": {
    "addr:full":"Hauptstr 3 Micheldorf in Ober\u00f6sterreich Ober\u00f6sterreich 4563",
    "addr:housenumber":"3",
    "addr:postcode":"4563",
    "addr:street":"Hauptstr",
    "iso:country":"AT",
    "sg:address":"Hauptstr 3",
    "sg:city":"Micheldorf in Ober\u00f6sterreich",
    "sg:orig_category":"Lebensmittel / Einzelhandel",
    "sg:phone":"+43 4375 8263269",
    "sg:postcode":"4563",
    "sg:province":"Ober\u00f6sterreich",
    "wof:name":"Billa AG",
    "wof:placetype":"venue"
},
  "geometry": {"coordinates":[14.1333332062,47.8790893555],"type":"Point"}
}