{
  "type": "Feature",
  "properties": {
    "addr:full":"Kirchenstr 6 Purgstall an der Erlauf Nieder\u00f6sterreich 3251",
    "addr:housenumber":"6",
    "addr:postcode":"3251",
    "addr:street":"Kirchenstr;Niederoesterreich",
    "iso:country":"AT",
    "sg:address":"Kirchenstr 6",
    "sg:city":"Purgstall an der Erlauf",
    "sg:orig_category":"Unterhaltungselektronik / Reparatur",
    "sg:phone":"+43 4374 897051",
    "sg:postcode":"3251",
    "sg:province":"Nieder\u00f6sterreich",
    "wof:name":"Funkberater Ing Kulhanek",
    "wof:placetype":"venue"
},
  "geometry": {"coordinates":[15.1347732544,48.0575866699],"type":"Point"}
}