{
  "type": "Feature",
  "properties": {
    "addr:full":"Schretterstr 2 Innsbruck Tirol 6020",
    "addr:housenumber":"2",
    "addr:postcode":"6020",
    "addr:street":"Schretterstr;Tirol",
    "iso:country":"AT",
    "sg:address":"Schretterstr 2",
    "sg:city":"Innsbruck",
    "sg:orig_category":"Autobusunternehmen",
    "sg:phone":"+43 664 5342310",
    "sg:postcode":"6020",
    "sg:province":"Tirol",
    "wof:name":"Ruef-Reisen",
    "wof:placetype":"venue"
},
  "geometry": {"coordinates":[11.4193029404,47.2647209167],"type":"Point"}
}