{
  "type": "Feature",
  "properties": {
    "addr:full":"Hietzinger Hauptstr 6 Wien Wien 1130",
    "addr:housenumber":"6",
    "addr:postcode":"1130",
    "addr:street":"Hietzinger Hauptstr",
    "iso:country":"AT",
    "sg:address":"Hietzinger Hauptstr 6",
    "sg:city":"Wien",
    "sg:orig_category":"Tanzschulen",
    "sg:phone":"+43 1 8773202",
    "sg:postcode":"1130",
    "sg:province":"Wien",
    "wof:name":"Tanzschule Sch\u00f6nbrunn",
    "wof:placetype":"venue"
},
  "geometry": {"coordinates":[16.3025608063,48.1868934631],"type":"Point"}
}