{
  "type": "Feature",
  "properties": {
    "addr:full":"R\u00e4tikonstr 5 Bludenz Vorarlberg 6700",
    "addr:housenumber":"5",
    "addr:postcode":"6700",
    "addr:street":"Raetikonstr",
    "iso:country":"AT",
    "sg:address":"R\u00e4tikonstr 5",
    "sg:city":"Bludenz",
    "sg:orig_category":"Ingenieurkonsulenten / Zivilingenieure",
    "sg:phone":"+43 5552 30286",
    "sg:postcode":"6700",
    "sg:province":"Vorarlberg",
    "wof:name":"Gantner Christian Dipl-Ing",
    "wof:placetype":"venue"
},
  "geometry": {"coordinates":[9.8209924698,47.1623497009],"type":"Point"}
}