{
  "type": "Feature",
  "properties": {
    "addr:full":"\u00f6tscherlandstr 2 Gaming Nieder\u00f6sterreich 3292",
    "addr:housenumber":"2",
    "addr:postcode":"3292",
    "addr:street":"Oetscherlandstr",
    "iso:country":"AT",
    "sg:address":"\u00f6tscherlandstr 2",
    "sg:city":"Gaming",
    "sg:orig_category":"Damenmoden",
    "sg:phone":"+43 7485 983900",
    "sg:postcode":"3292",
    "sg:province":"Nieder\u00f6sterreich",
    "wof:name":"Steinecker Moden GmbH",
    "wof:placetype":"venue"
},
  "geometry": {"coordinates":[15.0879335403,47.9291610718],"type":"Point"}
}