{
  "type": "Feature",
  "properties": {
    "addr:full":"Am Pregarten 1 Freistadt Ober\u00f6sterreich 4240",
    "addr:housenumber":"1",
    "addr:postcode":"4240",
    "addr:street":"Am Pregarten",
    "iso:country":"AT",
    "sg:address":"Am Pregarten 1",
    "sg:city":"Freistadt",
    "sg:orig_category":"Arbeitsvermittlung",
    "sg:phone":"+43 7942 743310",
    "sg:postcode":"4240",
    "sg:province":"Ober\u00f6sterreich",
    "sg:website":"www.ams-ooe.or.at",
    "wof:name":"Arbeitsmarktservice Freistadt",
    "wof:placetype":"venue"
},
  "geometry": {"coordinates":[14.4994192123,48.5074691772],"type":"Point"}
}