{
  "type": "Feature",
  "properties": {
    "addr:full":"Langwies 48 Zipf Ober\u00f6sterreich 4871",
    "addr:housenumber":"48",
    "addr:postcode":"4871",
    "addr:street":"Langwies",
    "iso:country":"AT",
    "sg:address":"Langwies 48",
    "sg:city":"Zipf",
    "sg:orig_category":"Non-Classified Establishments",
    "sg:phone":"+43 76826418",
    "sg:postcode":"4871",
    "sg:province":"Ober\u00f6sterreich",
    "wof:name":"Pfarramt",
    "wof:placetype":"venue"
},
  "geometry": {"coordinates":[13.5000810623,48.0282058716],"type":"Point"}
}