{
  "type": "Feature",
  "properties": {
    "addr:full":"Schmiedstr 29 Eferding Ober\u00f6sterreich 4070",
    "addr:housenumber":"29",
    "addr:postcode":"4070",
    "addr:street":"Schmiedstr",
    "iso:country":"AT",
    "sg:address":"Schmiedstr 29",
    "sg:city":"Eferding",
    "sg:orig_category":"Tankstellen",
    "sg:phone":"+43 7272 42470",
    "sg:postcode":"4070",
    "sg:province":"Ober\u00f6sterreich",
    "wof:name":"BP Austria Marketing GmbH",
    "wof:placetype":"venue"
},
  "geometry": {"coordinates":[14.0204725266,48.3086242676],"type":"Point"}
}