{
  "type": "Feature",
  "properties": {
    "addr:full":"Fischinger Str 15 Mattsee Salzburg 5163",
    "addr:postcode":"5163",
    "addr:street":"Str 15;Salzburg",
    "iso:country":"AT",
    "sg:address":"Fischinger Str 15",
    "sg:city":"Mattsee",
    "sg:orig_category":"Rettungsdienste",
    "sg:phone":"+43 6217 7194",
    "sg:postcode":"5163",
    "sg:province":"Salzburg",
    "wof:name":"Rotes Kreuz \u00f6sterr Ortsstelle Mattsee",
    "wof:placetype":"venue"
},
  "geometry": {"coordinates":[13.1010799408,47.9727592468],"type":"Point"}
}