{
  "type": "Feature",
  "properties": {
    "addr:full":"Dorf 50 Reith im Alpbachtal Tirol 6235",
    "addr:housenumber":"50",
    "addr:postcode":"6235",
    "addr:street":"Dorf;Alpbachtal Tirol",
    "iso:country":"AT",
    "sg:address":"Dorf 50",
    "sg:city":"Reith im Alpbachtal",
    "sg:orig_category":"Appartements / Ferienwohnungen",
    "sg:phone":"+43 5337 63627",
    "sg:postcode":"6235",
    "sg:province":"Tirol",
    "wof:name":"Landhaus Alpachtal",
    "wof:placetype":"venue"
},
  "geometry": {"coordinates":[11.878993988,47.4160118103],"type":"Point"}
}