{
  "type": "Feature",
  "properties": {
    "iso:country":"AT",
    "sg:address":"Ing Etzel-Str 1",
    "sg:city":"Innsbruck",
    "sg:orig_category":"Suchtberatung / Alkohol, Drogen, Zigaretten",
    "sg:phone":"+43 512 561403",
    "sg:postcode":"6020",
    "sg:province":"Tirol",
    "wof:name":"KOMF\u00dcDRO - Kommunikationszentrum f Drogenabh\u00e4ngige d Caritas d Di\u00f6zese Innsbruck",
    "wof:placetype":"venue"
},
  "geometry": {"coordinates":[11.4015417099,47.2665481567],"type":"Point"}
}