{
  "type": "Feature",
  "properties": {
    "addr:full":"Wagendorf 104 St. Veit am Vogau Steiermark 8423",
    "addr:housenumber":"104",
    "addr:postcode":"8423",
    "addr:street":"Wagendorf",
    "iso:country":"AT",
    "sg:address":"Wagendorf 104",
    "sg:city":"St. Veit am Vogau",
    "sg:orig_category":"Transportunternehmen",
    "sg:phone":"+43 664 4122069",
    "sg:postcode":"8423",
    "sg:province":"Steiermark",
    "wof:name":"Lorber Herbert",
    "wof:placetype":"venue"
},
  "geometry": {"coordinates":[15.6051454544,46.7559776306],"type":"Point"}
}