{
  "type": "Feature",
  "properties": {
    "addr:full":"Hauptpl 19 Judenburg Steiermark 8750",
    "addr:housenumber":"19",
    "addr:postcode":"8750",
    "addr:street":"Hauptpl",
    "iso:country":"AT",
    "sg:address":"Hauptpl 19",
    "sg:city":"Judenburg",
    "sg:orig_category":"Tabaktrafiken",
    "sg:phone":"+43 3572 46890",
    "sg:postcode":"8750",
    "sg:province":"Steiermark",
    "wof:name":"Zand Sylvana",
    "wof:placetype":"venue"
},
  "geometry": {"coordinates":[14.660902977,47.1681632996],"type":"Point"}
}