{
  "type": "Feature",
  "properties": {
    "iso:country":"AT",
    "sg:address":"Tristacher Str 10",
    "sg:city":"Lienz",
    "sg:orig_category":"Psychotherapie",
    "sg:phone":"+43 4852 71561",
    "sg:postcode":"9900",
    "sg:province":"Tirol",
    "wof:name":"Bucher Martina Dr",
    "wof:placetype":"venue"
},
  "geometry": {"coordinates":[12.7693128586,46.8261108398],"type":"Point"}
}