{
  "type": "Feature",
  "properties": {
    "addr:full":"Nr 3 Gleisdorf Steiermark 8200",
    "addr:postcode":"8200",
    "addr:street":"Nr",
    "iso:country":"AT",
    "sg:address":"Nr 3",
    "sg:city":"Gleisdorf",
    "sg:orig_category":"Baumaschinenverleih",
    "sg:phone":"+43 4331 124695",
    "sg:postcode":"8200",
    "sg:province":"Steiermark",
    "wof:name":"Gerstmann GesmbH",
    "wof:placetype":"venue"
},
  "geometry": {"coordinates":[15.6912050247,47.103477478],"type":"Point"}
}