{
  "type": "Feature",
  "properties": {
    "addr:full":"Gr\u00fcnschacherweg 36 Villach K\u00e4rnten 9500",
    "addr:housenumber":"36",
    "addr:postcode":"9500",
    "addr:street":"Gruenschacherweg;Kaernten",
    "iso:country":"AT",
    "sg:address":"Gr\u00fcnschacherweg 36",
    "sg:city":"Villach",
    "sg:classifiers":[
        {
            "category":"Taxi",
            "type":"Transportation"
        }
    ],
    "sg:phone":"+43 4342 4257777",
    "sg:postcode":"9500",
    "sg:province":"K\u00e4rnten",
    "sg:tags":[
        "personentransporte",
        "u"
    ],
    "wof:name":"Maier Franz",
    "wof:placetype":"venue"
},
  "geometry": {"coordinates":[13.8491945267,46.618106842],"type":"Point"}
}