{
  "type": "Feature",
  "properties": {
    "addr:full":"Hauptpl 32 Drosendorf an der Thaya Nieder\u00f6sterreich 2095",
    "addr:housenumber":"32",
    "addr:postcode":"2095",
    "addr:street":"Hauptpl;An Der Thaya",
    "iso:country":"AT",
    "sg:address":"Hauptpl 32",
    "sg:city":"Drosendorf an der Thaya",
    "sg:orig_category":"Banken U Sparkassen",
    "sg:phone":"+43 4329 152229",
    "sg:postcode":"2095",
    "sg:province":"Nieder\u00f6sterreich",
    "wof:name":"Raiffeisenbank Thayatal Mitte regGenmbH",
    "wof:placetype":"venue"
},
  "geometry": {"coordinates":[15.6194162369,48.8687286377],"type":"Point"}
}