{
  "type": "Feature",
  "properties": {
    "iso:country":"AT",
    "sg:address":"Attergaustr 42",
    "sg:city":"St. Georgen im Attergau",
    "sg:orig_category":"Juwelen, Gold- U Silberwaren / Einzelhandel",
    "sg:phone":"+43 4376 676279",
    "sg:postcode":"4880",
    "sg:province":"Ober\u00f6sterreich",
    "wof:name":"Sturm Franz",
    "wof:placetype":"venue"
},
  "geometry": {"coordinates":[13.4877357483,47.935218811],"type":"Point"}
}