{
  "type": "Feature",
  "properties": {
    "addr:full":"Im Erlengrund 5 Wildon Steiermark 8410",
    "addr:housenumber":"5",
    "addr:postcode":"8410",
    "addr:street":"Im Erlengrund;Steiermark",
    "iso:country":"AT",
    "sg:address":"Im Erlengrund 5",
    "sg:city":"Wildon",
    "sg:orig_category":"Eisenwaren",
    "sg:phone":"+43 3182 52064",
    "sg:postcode":"8410",
    "sg:province":"Steiermark",
    "wof:name":"AVVIO Ing Hubmann KEG",
    "wof:placetype":"venue"
},
  "geometry": {"coordinates":[15.5176448822,46.8801651001],"type":"Point"}
}