{
  "type": "Feature",
  "properties": {
    "addr:full":"Villacher Str 99 Spittal an der Drau K\u00e4rnten 9800",
    "addr:housenumber":"99",
    "addr:postcode":"9800",
    "addr:street":"Str;Kaernten",
    "iso:country":"AT",
    "sg:address":"Villacher Str 99",
    "sg:city":"Spittal an der Drau",
    "sg:orig_category":"Autohandel",
    "sg:phone":"+43 4347 62336100",
    "sg:postcode":"9800",
    "sg:province":"K\u00e4rnten",
    "wof:name":"Gruber Automobile GmbH",
    "wof:placetype":"venue"
},
  "geometry": {"coordinates":[13.518576622,46.7887535095],"type":"Point"}
}