{
  "type": "Feature",
  "properties": {
    "addr:full":"Nr 143 Heimschuh Steiermark 8451",
    "addr:postcode":"8451",
    "addr:street":"Nr",
    "iso:country":"AT",
    "sg:address":"Nr 143",
    "sg:city":"Heimschuh",
    "sg:orig_category":"Gemeinden",
    "sg:phone":"+43 3452 827480",
    "sg:postcode":"8451",
    "sg:province":"Steiermark",
    "wof:name":"Gemeindeamt Heimschuh",
    "wof:placetype":"venue"
},
  "geometry": {"coordinates":[15.4879951477,46.7589645386],"type":"Point"}
}