{
  "type": "Feature",
  "properties": {
    "addr:full":"Nr 16 Gaishorn am See Steiermark 8783",
    "addr:postcode":"8783",
    "addr:street":"Nr;Gaishorn Am See Steiermark",
    "iso:country":"AT",
    "sg:address":"Nr 16",
    "sg:city":"Gaishorn am See",
    "sg:classifiers":[
        {
            "category":"Professional",
            "subcategory":"Computer Services",
            "type":"Services"
        }
    ],
    "sg:phone":"+43 3617 2691",
    "sg:postcode":"8783",
    "sg:province":"Steiermark",
    "sg:tags":[
        "software"
    ],
    "wof:name":"Media Soft Scherzer & Kurz KEG",
    "wof:placetype":"venue"
},
  "geometry": {"coordinates":[14.5492944717,47.4914245605],"type":"Point"}
}