{
  "type": "Feature",
  "properties": {
    "addr:full":"Nr 34 Sonntag Vorarlberg 6731",
    "addr:postcode":"6731",
    "addr:street":"Nr;Sonntag",
    "iso:country":"AT",
    "sg:address":"Nr 34",
    "sg:city":"Sonntag",
    "sg:orig_category":"Pensionen / Privatzimmer",
    "sg:phone":"+43 5554 5538",
    "sg:postcode":"6731",
    "sg:province":"Vorarlberg",
    "wof:name":"Fr\u00fchst\u00fcckspension Sicher",
    "wof:placetype":"venue"
},
  "geometry": {"coordinates":[9.9032316208,47.2396812439],"type":"Point"}
}