{
  "type": "Feature",
  "properties": {
    "addr:full":"Herreng 1 Klagenfurt K\u00e4rnten 9020",
    "addr:housenumber":"1",
    "addr:postcode":"9020",
    "addr:street":"Herreng;Kaernten",
    "iso:country":"AT",
    "sg:address":"Herreng 1",
    "sg:city":"Klagenfurt",
    "sg:orig_category":"Boutiquen",
    "sg:phone":"+43 463 57827",
    "sg:postcode":"9020",
    "sg:province":"K\u00e4rnten",
    "wof:name":"Madame Inh Reiter Margit",
    "wof:placetype":"venue"
},
  "geometry": {"coordinates":[14.3066883087,46.6253738403],"type":"Point"}
}