{
  "type": "Feature",
  "properties": {
    "iso:country":"AT",
    "sg:address":"Webereiweg 7",
    "sg:city":"Hallein",
    "sg:orig_category":"Fliesen- U Plattenverlegungen",
    "sg:phone":"+43 6245 76176",
    "sg:postcode":"5400",
    "sg:province":"Salzburg",
    "wof:name":"H\u00f6rbinger Franz",
    "wof:placetype":"venue"
},
  "geometry": {"coordinates":[13.0741844177,47.7282485962],"type":"Point"}
}