{
  "type": "Feature",
  "properties": {
    "iso:country":"AT",
    "sg:address":"Gr\u00f6diger Str 50",
    "sg:city":"Anif",
    "sg:orig_category":"Pensionen / Privatzimmer",
    "sg:phone":"+43 6246 72073",
    "sg:postcode":"5081",
    "sg:province":"Salzburg",
    "wof:name":"Pension Gaberhell",
    "wof:placetype":"venue"
},
  "geometry": {"coordinates":[13.0551118851,47.7477111816],"type":"Point"}
}