{
  "type": "Feature",
  "properties": {
    "addr:full":"Baderb\u00fchelweg 7 Axams Tirol 6094",
    "addr:housenumber":"7",
    "addr:postcode":"6094",
    "addr:street":"Baderbuehelweg;Tirol",
    "iso:country":"AT",
    "sg:address":"Baderb\u00fchelweg 7",
    "sg:city":"Axams",
    "sg:orig_category":"Spenglereien",
    "sg:phone":"+43 5234 68149",
    "sg:postcode":"6094",
    "sg:province":"Tirol",
    "wof:name":"Unterkofler Franz",
    "wof:placetype":"venue"
},
  "geometry": {"coordinates":[11.2798423767,47.2326622009],"type":"Point"}
}