{
  "type": "Feature",
  "properties": {
    "iso:country":"AT",
    "sg:address":"Oberwald 49",
    "sg:city":"Ligist",
    "sg:classifiers":[
        {
            "category":"Travel",
            "subcategory":"Hotels & Motels",
            "type":"Entertainment"
        }
    ],
    "sg:phone":"+43 3143 21060",
    "sg:postcode":"8563",
    "sg:province":"Steiermark",
    "wof:name":"Enzianhof",
    "wof:placetype":"venue"
},
  "geometry": {"coordinates":[15.1765842438,46.9735488892],"type":"Point"}
}