{
  "type": "Feature",
  "properties": {
    "addr:full":"Anton Auer-Str 17 Telfs Tirol 6410",
    "addr:housenumber":"17",
    "addr:postcode":"6410",
    "addr:street":"Tirol",
    "iso:country":"AT",
    "sg:address":"Anton Auer-Str 17",
    "sg:city":"Telfs",
    "sg:orig_category":"Fliesen U Platten",
    "sg:phone":"+43 4352 6261370",
    "sg:postcode":"6410",
    "sg:province":"Tirol",
    "wof:name":"abc Fliesen GesmbH",
    "wof:placetype":"venue"
},
  "geometry": {"coordinates":[11.074754715,47.3054428101],"type":"Point"}
}