{
  "type": "Feature",
  "properties": {
    "addr:full":"Hauslabg 19/5 Wien Wien 1050",
    "addr:housenumber":"19 / 5",
    "addr:postcode":"1050",
    "addr:street":"Hauslabg",
    "iso:country":"AT",
    "sg:address":"Hauslabg 19/5",
    "sg:city":"Wien",
    "sg:orig_category":"Handelsagenturen",
    "sg:phone":"+43 1 5440451",
    "sg:postcode":"1050",
    "sg:province":"Wien",
    "wof:name":"Pfeiffer Helga",
    "wof:placetype":"venue"
},
  "geometry": {"coordinates":[16.3645935059,48.184715271],"type":"Point"}
}