{
  "type": "Feature",
  "properties": {
    "addr:full":"Erndtg 7 Wien Wien 1180",
    "addr:housenumber":"7",
    "addr:postcode":"1180",
    "addr:street":"Erndtg",
    "iso:country":"AT",
    "sg:address":"Erndtg 7",
    "sg:city":"Wien",
    "sg:classifiers":[
        {
            "category":"Restaurant",
            "type":"Food & Drink"
        }
    ],
    "sg:phone":"+43 1 4792954",
    "sg:postcode":"1180",
    "sg:province":"Wien",
    "sg:tags":[
        "pizzeria"
    ],
    "wof:name":"Pizzeria Amico",
    "wof:placetype":"venue"
},
  "geometry": {"coordinates":[16.3445625305,48.2262420654],"type":"Point"}
}