{
  "type": "Feature",
  "properties": {
    "iso:country":"AT",
    "sg:address":"Wagrainer Str 55",
    "sg:city":"St. Johann im Pongau",
    "sg:orig_category":"Holzhandel",
    "sg:phone":"+43 6412 43350",
    "sg:postcode":"5600",
    "sg:province":"Salzburg",
    "wof:name":"Liebenberger Rupert KG - S\u00e4gewerk",
    "wof:placetype":"venue"
},
  "geometry": {"coordinates":[13.243314743,47.3334503174],"type":"Point"}
}