{
  "type": "Feature",
  "properties": {
    "addr:full":"Nr 161 Gleisdorf Steiermark 8200",
    "addr:postcode":"8200",
    "addr:street":"Nr 161",
    "iso:country":"AT",
    "sg:address":"Nr 161",
    "sg:city":"Gleisdorf",
    "sg:orig_category":"Gemeinden",
    "sg:phone":"+43 3112 50600",
    "sg:postcode":"8200",
    "sg:province":"Steiermark",
    "wof:name":"Gemeindeamt Ungerdorf",
    "wof:placetype":"venue"
},
  "geometry": {"coordinates":[15.6912050247,47.103477478],"type":"Point"}
}