{
  "type": "Feature",
  "properties": {
    "addr:full":"Albrechtstr 39 Klosterneuburg Nieder\u00f6sterreich 3400",
    "addr:housenumber":"39",
    "addr:postcode":"3400",
    "addr:street":"Albrechtstr;Niederoesterreich",
    "iso:country":"AT",
    "sg:address":"Albrechtstr 39",
    "sg:city":"Klosterneuburg",
    "sg:orig_category":"Apotheken",
    "sg:phone":"+43 2243 37601",
    "sg:postcode":"3400",
    "sg:province":"Nieder\u00f6sterreich",
    "wof:name":"Stadt-Apotheke-Drogerie Mag pharm Gertrud Hiessmayer KG",
    "wof:placetype":"venue"
},
  "geometry": {"coordinates":[16.3207168579,48.3093261719],"type":"Point"}
}