{
  "type": "Feature",
  "properties": {
    "addr:full":"Schottenfeldg 60/33L Wien Wien 1070",
    "addr:housenumber":"60 / 33l",
    "addr:postcode":"1070",
    "addr:street":"Schottenfeldg",
    "iso:country":"AT",
    "sg:address":"Schottenfeldg 60/33L",
    "sg:city":"Wien",
    "sg:orig_category":"Werbeagenturen",
    "sg:phone":"+43 1 5248424",
    "sg:postcode":"1070",
    "sg:province":"Wien",
    "wof:name":"Fischer Enterprises Werbe GmbH",
    "wof:placetype":"venue"
},
  "geometry": {"coordinates":[16.34333992,48.2035293579],"type":"Point"}
}