{
  "type": "Feature",
  "properties": {
    "iso:country":"AT",
    "sg:address":"Hernalser Hauptstr 193",
    "sg:city":"Wien",
    "sg:classifiers":[
        {
            "category":"Shopping",
            "subcategory":"Thrift Store",
            "type":"Retail Goods"
        }
    ],
    "sg:phone":"+43 1 4811088",
    "sg:postcode":"1170",
    "sg:province":"Wien",
    "sg:tags":[
        "second-hand-shops"
    ],
    "wof:name":"Sapperlot Marken-Second-Hand",
    "wof:placetype":"venue"
},
  "geometry": {"coordinates":[16.3129253387,48.2241592407],"type":"Point"}
}