{
  "type": "Feature",
  "properties": {
    "addr:full":"Innstr. 4  Fritzens Tirol 6122",
    "addr:housenumber":"4",
    "addr:postcode":"6122",
    "addr:street":"Innstr.;Tirol",
    "iso:country":"AT",
    "sg:address":"Innstr. 4 ",
    "sg:city":"Fritzens",
    "sg:classifiers":[
        {
            "category":"Food & Beverages",
            "subcategory":"Groceries & Convenience Stores",
            "type":"Retail Goods"
        }
    ],
    "sg:phone":"+43 4352 2457405",
    "sg:postcode":"6122",
    "sg:province":"Tirol",
    "sg:tags":[
        "product",
        "related"
    ],
    "wof:name":"BONNEVIT FEINB\u00c4CKEREI GESMBH & CO KG",
    "wof:placetype":"venue"
},
  "geometry": {"coordinates":[11.593752861,47.300693512],"type":"Point"}
}