{
  "type": "Feature",
  "properties": {
    "addr:full":"S\u00f6rgerberg 1 Liebenfels K\u00e4rnten 9556",
    "addr:housenumber":"1",
    "addr:postcode":"9556",
    "addr:street":"Soergerberg;Kaernten",
    "iso:country":"AT",
    "sg:address":"S\u00f6rgerberg 1",
    "sg:city":"Liebenfels",
    "sg:orig_category":"Appartements / Ferienwohnungen",
    "sg:phone":"+43 4215 2532",
    "sg:postcode":"9556",
    "sg:province":"K\u00e4rnten",
    "wof:name":"Graglerhof",
    "wof:placetype":"venue"
},
  "geometry": {"coordinates":[14.2895402908,46.7378463745],"type":"Point"}
}