{
  "type": "Feature",
  "properties": {
    "iso:country":"AT",
    "sg:address":"Heideg 45",
    "sg:city":"Parndorf",
    "sg:orig_category":"Isolierglas",
    "sg:phone":"+43 2166 23250",
    "sg:postcode":"7111",
    "sg:province":"Burgenland",
    "wof:name":"Interpane Isolierglas GesmbH & Co KG",
    "wof:placetype":"venue"
},
  "geometry": {"coordinates":[16.8575897217,47.9981613159],"type":"Point"}
}