{
  "type": "Feature",
  "properties": {
    "addr:full":"Marktpl 169 Hallstatt Ober\u00f6sterreich 4830",
    "addr:housenumber":"169",
    "addr:postcode":"4830",
    "addr:street":"Marktpl",
    "iso:country":"AT",
    "sg:address":"Marktpl 169",
    "sg:city":"Hallstatt",
    "sg:orig_category":"Fischzucht",
    "sg:phone":"+43 6134 8204",
    "sg:postcode":"4830",
    "sg:province":"Ober\u00f6sterreich",
    "wof:name":"\u00f6sterreichische Bundesforste AG - Fischerei Hallstatt",
    "wof:placetype":"venue"
},
  "geometry": {"coordinates":[13.6487932205,47.562286377],"type":"Point"}
}