{
  "type": "Feature",
  "properties": {
    "addr:full":"Ausstellungsstr 27/6 Wien Wien 1020",
    "addr:housenumber":"27 / 6",
    "addr:postcode":"1020",
    "addr:street":"Ausstellungsstr",
    "iso:country":"AT",
    "sg:address":"Ausstellungsstr 27/6",
    "sg:city":"Wien",
    "sg:orig_category":"Edelstahl",
    "sg:phone":"+43 1 7203413",
    "sg:postcode":"1020",
    "sg:province":"Wien",
    "sg:website":"gsw-stahl.at",
    "wof:name":"G.S.W. Gu\u00df Schmiedest\u00fccke Werkzeugstahl Handel GmbH",
    "wof:placetype":"venue"
},
  "geometry": {"coordinates":[16.4028377533,48.218170166],"type":"Point"}
}