{
  "type": "Feature",
  "properties": {
    "iso:country":"AT",
    "sg:address":"Wilhelm-Jentsch-Str 4",
    "sg:city":"Peggau",
    "sg:orig_category":"Elektroinstallationsunternehmen",
    "sg:phone":"+43 3127 20908",
    "sg:postcode":"8120",
    "sg:province":"Steiermark",
    "wof:name":"H\u00f6rzer & Brantsch Elektro GmbH",
    "wof:placetype":"venue"
},
  "geometry": {"coordinates":[15.3408031464,47.2039985657],"type":"Point"}
}