{
  "type": "Feature",
  "properties": {
    "addr:full":"Rennweg 3 Gmunden Ober\u00f6sterreich 4810",
    "addr:housenumber":"3",
    "addr:postcode":"4810",
    "addr:street":"Rennweg;Oberoesterreich",
    "iso:country":"AT",
    "sg:address":"Rennweg 3",
    "sg:city":"Gmunden",
    "sg:orig_category":"Installationsunternehmen",
    "sg:phone":"+43 761272233",
    "sg:postcode":"4810",
    "sg:province":"Ober\u00f6sterreich",
    "wof:name":"Moro Haustechnik",
    "wof:placetype":"venue"
},
  "geometry": {"coordinates":[13.791308403,47.9213066101],"type":"Point"}
}