{
  "type": "Feature",
  "properties": {
    "addr:full":"Neuwaldegger Str 30 Wien Wien 1170",
    "addr:postcode":"1170",
    "addr:street":"Str 30",
    "iso:country":"AT",
    "sg:address":"Neuwaldegger Str 30",
    "sg:city":"Wien",
    "sg:orig_category":"Immobilienmakler",
    "sg:phone":"+43 1 48611000",
    "sg:postcode":"1170",
    "sg:province":"Wien",
    "wof:name":"Tomisek Dr Immobilien Consulting International GmbH",
    "wof:placetype":"venue"
},
  "geometry": {"coordinates":[16.2865715027,48.237613678],"type":"Point"}
}