{
  "type": "Feature",
  "properties": {
    "addr:full":"Tullner Str 45 Stockerau Nieder\u00f6sterreich 2000",
    "addr:postcode":"2000",
    "addr:street":"Str 45",
    "iso:country":"AT",
    "sg:address":"Tullner Str 45",
    "sg:city":"Stockerau",
    "sg:orig_category":"Autoersatzteile",
    "sg:phone":"+43 4322 66635390",
    "sg:postcode":"2000",
    "sg:province":"Nieder\u00f6sterreich",
    "wof:name":"Engel Otto",
    "wof:placetype":"venue"
},
  "geometry": {"coordinates":[16.1829547882,48.384677887],"type":"Point"}
}