{
  "type": "Feature",
  "properties": {
    "addr:full":"Kasmanhuberstr 12 Villach K\u00e4rnten 9500",
    "addr:housenumber":"12",
    "addr:postcode":"9500",
    "addr:street":"Kasmanhuberstr;Kaernten",
    "iso:country":"AT",
    "sg:address":"Kasmanhuberstr 12",
    "sg:city":"Villach",
    "sg:orig_category":"Maler, Anstreicher U Lackierer",
    "sg:phone":"+43 4342 4228523",
    "sg:postcode":"9500",
    "sg:province":"K\u00e4rnten",
    "wof:name":"Hribar Josef",
    "wof:placetype":"venue"
},
  "geometry": {"coordinates":[13.8445329666,46.6219367981],"type":"Point"}
}