{
  "type": "Feature",
  "properties": {
    "addr:full":"Kirchpl 3 Eberndorf K\u00e4rnten 9141",
    "addr:housenumber":"3",
    "addr:postcode":"9141",
    "addr:street":"Kirchpl;Kaernten",
    "iso:country":"AT",
    "sg:address":"Kirchpl 3",
    "sg:city":"Eberndorf",
    "sg:orig_category":"Lebensmittel / Einzelhandel",
    "sg:phone":"+43 4236 2272",
    "sg:postcode":"9141",
    "sg:province":"K\u00e4rnten",
    "wof:name":"Morocutti Paul",
    "wof:placetype":"venue"
},
  "geometry": {"coordinates":[14.6408843994,46.5913963318],"type":"Point"}
}