{
  "type": "Feature",
  "properties": {
    "iso:country":"AT",
    "sg:address":"Hauptpl 13",
    "sg:city":"Leoben",
    "sg:orig_category":"Eissalons",
    "sg:phone":"+43 3842 42110",
    "sg:postcode":"8700",
    "sg:province":"Steiermark",
    "wof:name":"Martini",
    "wof:placetype":"venue"
},
  "geometry": {"coordinates":[15.0943002701,47.3806762695],"type":"Point"}
}