{
  "type": "Feature",
  "properties": {
    "addr:full":"Holzstr 5 Linz Ober\u00f6sterreich 4020",
    "addr:housenumber":"5",
    "addr:postcode":"4020",
    "addr:street":"Holzstr",
    "iso:country":"AT",
    "sg:address":"Holzstr 5",
    "sg:city":"Linz",
    "sg:orig_category":"Fleischhauereien",
    "sg:phone":"+43 732 773821",
    "sg:postcode":"4020",
    "sg:province":"Ober\u00f6sterreich",
    "wof:name":"Karnerta GesmbH",
    "wof:placetype":"venue"
},
  "geometry": {"coordinates":[14.3023633957,48.3122787476],"type":"Point"}
}