{
  "type": "Feature",
  "properties": {
    "iso:country":"AT",
    "sg:address":"Landstr 38",
    "sg:city":"Lochau",
    "sg:orig_category":"\u00c3\u201erzte / F Allgemeinmedizin",
    "sg:phone":"+43 5574 47745",
    "sg:postcode":"6911",
    "sg:province":"Vorarlberg",
    "wof:name":"Anwander-B\u00f6sch Bettina Dr",
    "wof:placetype":"venue"
},
  "geometry": {"coordinates":[9.7514247894,47.5276451111],"type":"Point"}
}