{
  "type": "Feature",
  "properties": {
    "iso:country":"AT",
    "sg:address":"St. Michael 88",
    "sg:city":"St. Peter in der Au",
    "sg:orig_category":"Autoreparatur",
    "sg:phone":"+43 7477 7219",
    "sg:postcode":"3352",
    "sg:province":"Nieder\u00f6sterreich",
    "wof:name":"Egger-Richter Johann",
    "wof:placetype":"venue"
},
  "geometry": {"coordinates":[14.6215419769,48.0450401306],"type":"Point"}
}