{
  "type": "Feature",
  "properties": {
    "addr:full":"Hirscheng 23 Wien Wien 1060",
    "addr:housenumber":"23",
    "addr:postcode":"1060",
    "addr:street":"Hirscheng",
    "iso:country":"AT",
    "sg:address":"Hirscheng 23",
    "sg:city":"Wien",
    "sg:orig_category":"Studentenheime",
    "sg:phone":"+43 1 59706620",
    "sg:postcode":"1060",
    "sg:province":"Wien",
    "wof:name":"Wirtschaftshilfe d Arbeiterstudenten \u00f6sterreichs",
    "wof:placetype":"venue"
},
  "geometry": {"coordinates":[16.3470096588,48.1948471069],"type":"Point"}
}