{
  "type": "Feature",
  "properties": {
    "iso:country":"AT",
    "sg:address":"Hauptpl 36",
    "sg:city":"Frohnleiten",
    "sg:orig_category":"Damenmoden",
    "sg:phone":"+43 3126 2313",
    "sg:postcode":"8130",
    "sg:province":"Steiermark",
    "wof:name":"Sie & Er Mode-Shop Johann Zottler",
    "wof:placetype":"venue"
},
  "geometry": {"coordinates":[15.3272590637,47.2710113525],"type":"Point"}
}