{
  "type": "Feature",
  "properties": {
    "addr:full":"Akazienweg 13 Gro\u00df-Enzersdorf Nieder\u00f6sterreich 2301",
    "addr:housenumber":"13",
    "addr:postcode":"2301",
    "addr:street":"Akazienweg;Niederoesterreich",
    "iso:country":"AT",
    "sg:address":"Akazienweg 13",
    "sg:city":"Gro\u00df-Enzersdorf",
    "sg:orig_category":"Fem Calculation",
    "sg:phone":"+43 2249 3505",
    "sg:postcode":"2301",
    "sg:province":"Nieder\u00f6sterreich",
    "sg:website":"stanker.at",
    "wof:name":"Zivilingenieur f\u00fcr Maschinenbau Dipl.-Ing. Gerhard Stanker",
    "wof:placetype":"venue"
},
  "geometry": {"coordinates":[16.541437149,48.2009811401],"type":"Point"}
}