{
  "type": "Feature",
  "properties": {
    "iso:country":"AT",
    "sg:address":"Mitterland 116",
    "sg:city":"Thiersee",
    "sg:orig_category":"Friseure U Frisiersalons",
    "sg:phone":"+43 4353 7620176",
    "sg:postcode":"6335",
    "sg:province":"Tirol",
    "wof:name":"Coiffeur Mitterland",
    "wof:placetype":"venue"
},
  "geometry": {"coordinates":[12.079744339,47.5801620483],"type":"Point"}
}