{
  "type": "Feature",
  "properties": {
    "iso:country":"AT",
    "sg:address":"Gastigweg 21",
    "sg:city":"St. Anton am Arlberg",
    "sg:orig_category":"Appartements / Ferienwohnungen",
    "sg:phone":"+43 5446 3273",
    "sg:postcode":"6580",
    "sg:province":"Tirol",
    "wof:name":"Haus Antonia",
    "wof:placetype":"venue"
},
  "geometry": {"coordinates":[10.257393837,47.1254577637],"type":"Point"}
}