{
  "type": "Feature",
  "properties": {
    "addr:full":"Quaring 16 Wien Wien 1100",
    "addr:housenumber":"16",
    "addr:postcode":"1100",
    "addr:street":"Quaring",
    "iso:country":"AT",
    "sg:address":"Quaring 16",
    "sg:city":"Wien",
    "sg:orig_category":"Elektroinstallationsunternehmen",
    "sg:phone":"+43 1 6006863",
    "sg:postcode":"1100",
    "sg:province":"Wien",
    "wof:name":"Elektro G\u00fcnter Lehejcek GmbH",
    "wof:placetype":"venue"
},
  "geometry": {"coordinates":[16.3542194366,48.1714782715],"type":"Point"}
}