{
  "type": "Feature",
  "properties": {
    "addr:full":"Watzmannstr 34 Oberndorf Salzburg 5110",
    "addr:housenumber":"34",
    "addr:postcode":"5110",
    "addr:street":"Watzmannstr",
    "iso:country":"AT",
    "sg:address":"Watzmannstr 34",
    "sg:city":"Oberndorf",
    "sg:orig_category":"Behinderungen / Leben Mit Behinderungen",
    "sg:phone":"+43 4362 725947",
    "sg:postcode":"5110",
    "sg:province":"Salzburg",
    "wof:name":"Fr\u00fchf\u00f6rderung u Familienbegleitung d Lebenshilfe Salzburg",
    "wof:placetype":"venue"
},
  "geometry": {"coordinates":[12.9406852722,47.9401435852],"type":"Point"}
}