{
  "type": "Feature",
  "properties": {
    "iso:country":"AT",
    "sg:address":"Aigner Str 53",
    "sg:city":"Salzburg",
    "sg:orig_category":"Steuerberatung",
    "sg:phone":"+43 662 628098",
    "sg:postcode":"5020",
    "sg:province":"Salzburg",
    "wof:name":"Tischler Claudia Mag SteuerberatungsgesmbH & Co KEG",
    "wof:placetype":"venue"
},
  "geometry": {"coordinates":[13.0727300644,47.7930908203],"type":"Point"}
}