{
  "type": "Feature",
  "properties": {
    "iso:country":"AT",
    "sg:address":"Industriestrasse 19",
    "sg:city":"Haid",
    "sg:classifiers":[
        {
            "category":"Building & Trades",
            "subcategory":"Electrical",
            "type":"Services"
        }
    ],
    "sg:phone":"+43 7229 83068",
    "sg:postcode":"4053",
    "sg:province":"Ober\u00f6sterreich",
    "sg:tags":[
        "work",
        "installation"
    ],
    "sg:website":"fuse.at",
    "wof:name":"F & S - Elektrotechnik GmbH",
    "wof:placetype":"venue"
},
  "geometry": {"coordinates":[14.2602996826,48.2097244263],"type":"Point"}
}