{
  "type": "Feature",
  "properties": {
    "addr:full":"Judeng 4 Wien Wien 1010",
    "addr:housenumber":"4",
    "addr:postcode":"1010",
    "addr:street":"Judeng",
    "iso:country":"AT",
    "sg:address":"Judeng 4",
    "sg:city":"Wien",
    "sg:orig_category":"Altwaren",
    "sg:phone":"+43 1 5359477",
    "sg:postcode":"1010",
    "sg:province":"Wien",
    "wof:name":"Bastar Alfred",
    "wof:placetype":"venue"
},
  "geometry": {"coordinates":[16.3735160828,48.211101532],"type":"Point"}
}