{
  "type": "Feature",
  "properties": {
    "iso:country":"AT",
    "sg:address":"Judeng 4",
    "sg:city":"Wien",
    "sg:orig_category":"Altwaren",
    "sg:phone":"+43 1 5359477",
    "sg:postcode":"1010",
    "sg:province":"Wien",
    "wof:name":"Bastar Alfred",
    "wof:placetype":"venue"
},
  "geometry": {"coordinates":[16.3735160828,48.211101532],"type":"Point"}
}