{
  "type": "Feature",
  "properties": {
    "addr:full":"Stuhlfelden 28 Stuhlfelden Salzburg 5724",
    "addr:housenumber":"28",
    "addr:postcode":"5724",
    "addr:street":"Stuhlfelden;Salzburg",
    "iso:country":"AT",
    "sg:address":"Stuhlfelden 28",
    "sg:city":"Stuhlfelden",
    "sg:classifiers":[
        {
            "category":"Manufacturing",
            "subcategory":"Furniture",
            "type":"Manufacturing & Wholesale Goods"
        }
    ],
    "sg:phone":"+43 6562 4238",
    "sg:postcode":"5724",
    "sg:province":"Salzburg",
    "sg:tags":[
        "design"
    ],
    "sg:website":"bernd-gruber.at",
    "wof:name":"Bernd Gruber Raum Objekt + Design",
    "wof:placetype":"venue"
},
  "geometry": {"coordinates":[12.5288677216,47.2884979248],"type":"Point"}
}