{
  "type": "Feature",
  "properties": {
    "iso:country":"AT",
    "sg:address":"Skiliftstr 538",
    "sg:city":"Saalbach",
    "sg:orig_category":"Appartements / Ferienwohnungen",
    "sg:phone":"+43 6541 64010",
    "sg:postcode":"5753",
    "sg:province":"Salzburg",
    "wof:name":"Landhaus Ulreich",
    "wof:placetype":"venue"
},
  "geometry": {"coordinates":[12.6374702454,47.3918914795],"type":"Point"}
}