{
  "type": "Feature",
  "properties": {
    "addr:full":"Dorf Haus 773 Mayrhofen Tirol 6290",
    "addr:housenumber":"773",
    "addr:postcode":"6290",
    "addr:street":"Dorf Haus;Tirol",
    "iso:country":"AT",
    "sg:address":"Dorf Haus 773",
    "sg:city":"Mayrhofen",
    "sg:orig_category":"Schlossereien",
    "sg:phone":"+43 5285 625270",
    "sg:postcode":"6290",
    "sg:province":"Tirol",
    "wof:name":"Trinkl Erich",
    "wof:placetype":"venue"
},
  "geometry": {"coordinates":[11.8576602936,47.1589508057],"type":"Point"}
}