{
  "type": "Feature",
  "properties": {
    "addr:full":"Innsbrucker Bundesstr. 79a Salzburg Salzburg 5020",
    "addr:housenumber":"79a",
    "addr:postcode":"5020",
    "addr:street":"Salzburg",
    "iso:country":"AT",
    "sg:address":"Innsbrucker Bundesstr. 79a",
    "sg:city":"Salzburg",
    "sg:classifiers":[
        {
            "category":"Shopping",
            "subcategory":"Clothing, Apparel, & Fashions",
            "type":"Retail Goods"
        }
    ],
    "sg:phone":"+43 4366 28274490",
    "sg:postcode":"5020",
    "sg:province":"Salzburg",
    "sg:tags":[
        "clothes"
    ],
    "wof:name":"LANA STRICKMODEN",
    "wof:placetype":"venue"
},
  "geometry": {"coordinates":[13.0107049942,47.799407959],"type":"Point"}
}