{
  "type": "Feature",
  "properties": {
    "addr:full":"R\u00f6merstr 21 Hall in Tirol Tirol 6060",
    "addr:housenumber":"21",
    "addr:postcode":"6060",
    "addr:street":"Roemerstr;Tirol",
    "iso:country":"AT",
    "sg:address":"R\u00f6merstr 21",
    "sg:city":"Hall in Tirol",
    "sg:orig_category":"Tourismusinformation U -Organisationen",
    "sg:phone":"+43 4351 2345454",
    "sg:postcode":"6060",
    "sg:province":"Tirol",
    "wof:name":"Tourismusb\u00fcro Ampass",
    "wof:placetype":"venue"
},
  "geometry": {"coordinates":[11.4659223557,47.2620429993],"type":"Point"}
}