{
  "type": "Feature",
  "properties": {
    "iso:country":"AT",
    "sg:address":"Seepromenade 121",
    "sg:city":"St. Magdalen",
    "sg:orig_category":"Pensionen / Privatzimmer",
    "sg:phone":"+43 4242 44192",
    "sg:postcode":"9524",
    "sg:province":"K\u00e4rnten",
    "wof:name":"Katholnig Michael",
    "wof:placetype":"venue"
},
  "geometry": {"coordinates":[13.8921890259,46.6196403503],"type":"Point"}
}