{
  "type": "Feature",
  "properties": {
    "iso:country":"AT",
    "sg:address":"Ledererg 4",
    "sg:city":"Tulln an der Donau",
    "sg:orig_category":"Restaurants: Chinesisch",
    "sg:phone":"+43 2272 63508",
    "sg:postcode":"3430",
    "sg:province":"Nieder\u00f6sterreich",
    "wof:name":"China-Restaurant Evergreen",
    "wof:placetype":"venue"
},
  "geometry": {"coordinates":[16.0510196686,48.33177948],"type":"Point"}
}