{
  "type": "Feature",
  "properties": {
    "iso:country":"AT",
    "sg:address":"Otto-Rui\u00df-Str 11",
    "sg:city":"Gresten",
    "sg:orig_category":"Brennstoffe",
    "sg:phone":"+43 4374 872020",
    "sg:postcode":"3264",
    "sg:province":"Nieder\u00f6sterreich",
    "wof:name":"Pfeiffer Uwe - Brennstoffhdl u Tankservice",
    "wof:placetype":"venue"
},
  "geometry": {"coordinates":[15.0241909027,47.9812316895],"type":"Point"}
}