{
  "type": "Feature",
  "properties": {
    "iso:country":"AT",
    "sg:address":"Hauptstr 75a",
    "sg:city":"Pressbaum",
    "sg:orig_category":"Non-Classified Establishments",
    "sg:phone":"+43 2233 52214",
    "sg:postcode":"3021",
    "sg:province":"Nieder\u00f6sterreich",
    "wof:name":"Pfarrgemeinde Pre\u00dfbaum",
    "wof:placetype":"venue"
},
  "geometry": {"coordinates":[16.0771198273,48.1790885925],"type":"Point"}
}