{
  "type": "Feature",
  "properties": {
    "addr:full":"Hauptstr 29A Echsenbach Nieder\u00f6sterreich 3903",
    "addr:housenumber":"29a",
    "addr:postcode":"3903",
    "addr:street":"Hauptstr",
    "iso:country":"AT",
    "sg:address":"Hauptstr 29A",
    "sg:city":"Echsenbach",
    "sg:orig_category":"Friseure U Frisiersalons",
    "sg:phone":"+43 4328 498264",
    "sg:postcode":"3903",
    "sg:province":"Nieder\u00f6sterreich",
    "wof:name":"Dangl Maria",
    "wof:placetype":"venue"
},
  "geometry": {"coordinates":[15.2137241364,48.7183151245],"type":"Point"}
}