{
  "type": "Feature",
  "properties": {
    "addr:full":"Weidenstr 9 Hartberg Steiermark 8230",
    "addr:housenumber":"9",
    "addr:postcode":"8230",
    "addr:street":"Weidenstr",
    "iso:country":"AT",
    "sg:address":"Weidenstr 9",
    "sg:city":"Hartberg",
    "sg:orig_category":"Lebensmittel / Einzelhandel",
    "sg:phone":"+43 4333 3263544",
    "sg:postcode":"8230",
    "sg:province":"Steiermark",
    "wof:name":"Hofer KG",
    "wof:placetype":"venue"
},
  "geometry": {"coordinates":[15.9864444733,47.2834396362],"type":"Point"}
}