{
  "type": "Feature",
  "properties": {
    "addr:full":"Karl-Eybl-Str 8-10 Ebergassing Nieder\u00f6sterreich 2435",
    "addr:housenumber":"8-10",
    "addr:postcode":"2435",
    "iso:country":"AT",
    "sg:address":"Karl-Eybl-Str 8-10",
    "sg:city":"Ebergassing",
    "sg:orig_category":"Autohandel",
    "sg:phone":"+43 2234 72283",
    "sg:postcode":"2435",
    "sg:province":"Nieder\u00f6sterreich",
    "wof:name":"Angy's Brummi Center - Angelika Widhalm",
    "wof:placetype":"venue"
},
  "geometry": {"coordinates":[16.5221710205,48.0468444824],"type":"Point"}
}