{
  "type": "Feature",
  "properties": {
    "addr:full":"Nr 19 Rosegg K\u00e4rnten 9232",
    "addr:postcode":"9232",
    "addr:street":"Nr 19;Kaernten",
    "iso:country":"AT",
    "sg:address":"Nr 19",
    "sg:city":"Rosegg",
    "sg:orig_category":"\u00c3\u201erzte / F Allgemeinmedizin",
    "sg:phone":"+43 4274 4340",
    "sg:postcode":"9232",
    "sg:province":"K\u00e4rnten",
    "wof:name":"Hofer-Moser Otto Dr",
    "wof:placetype":"venue"
},
  "geometry": {"coordinates":[14.0191602707,46.5909347534],"type":"Point"}
}