{
  "type": "Feature",
  "properties": {
    "iso:country":"AT",
    "sg:address":"Nr 47",
    "sg:city":"St. Michael im Burgenland",
    "sg:orig_category":"Partyservice",
    "sg:phone":"+43 4366 44500088",
    "sg:postcode":"7535",
    "sg:province":"Burgenland",
    "wof:name":"Marlov's Catering",
    "wof:placetype":"venue"
},
  "geometry": {"coordinates":[16.2596359253,47.1686592102],"type":"Point"}
}