{
  "type": "Feature",
  "properties": {
    "addr:full":"Stifterstr 12 Rohrbach in Ober\u00f6sterreich Ober\u00f6sterreich 4150",
    "addr:housenumber":"12",
    "addr:postcode":"4150",
    "addr:street":"Stifterstr",
    "iso:country":"AT",
    "sg:address":"Stifterstr 12",
    "sg:city":"Rohrbach in Ober\u00f6sterreich",
    "sg:orig_category":"Notare",
    "sg:phone":"+43 7289 43520",
    "sg:postcode":"4150",
    "sg:province":"Ober\u00f6sterreich",
    "wof:name":"Neundlinger Paul Dr",
    "wof:placetype":"venue"
},
  "geometry": {"coordinates":[13.9978599548,48.5706787109],"type":"Point"}
}