{
  "type": "Feature",
  "properties": {
    "iso:country":"AT",
    "sg:address":"Eduard-Kittenberger-G 69",
    "sg:city":"Wien",
    "sg:orig_category":"Transportunternehmen",
    "sg:phone":"+43 4318 672930",
    "sg:postcode":"1230",
    "sg:province":"Wien",
    "wof:name":"Internationale Transporte Manhartsberger",
    "wof:placetype":"venue"
},
  "geometry": {"coordinates":[16.3042964935,48.1415061951],"type":"Point"}
}