{
  "type": "Feature",
  "properties": {
    "addr:full":"J\u00e4gerstr 89-95/20/R1 Wien Wien 1200",
    "addr:housenumber":"89-95 / 20 / r1",
    "addr:postcode":"1200",
    "iso:country":"AT",
    "sg:address":"J\u00e4gerstr 89-95/20/R1",
    "sg:city":"Wien",
    "sg:orig_category":"Bauunternehmen",
    "sg:phone":"+43 4366 44125417",
    "sg:postcode":"1200",
    "sg:province":"Wien",
    "wof:name":"CENTA Autohandel u Bau GmbH",
    "wof:placetype":"venue"
},
  "geometry": {"coordinates":[16.3734645844,48.2306060791],"type":"Point"}
}