{
  "type": "Feature",
  "properties": {
    "iso:country":"AT",
    "sg:address":"Lindeng 8",
    "sg:city":"Maria Lanzendorf",
    "sg:orig_category":"Musikgruppen",
    "sg:phone":"+43 2235 43122",
    "sg:postcode":"2326",
    "sg:province":"Nieder\u00f6sterreich",
    "wof:name":"Blechbl\u00e4sertrio Colore Wien Mag Andreas Poindl",
    "wof:placetype":"venue"
},
  "geometry": {"coordinates":[16.4457168579,48.1106147766],"type":"Point"}
}