{
  "type": "Feature",
  "properties": {
    "iso:country":"AT",
    "sg:address":"Streinesberg 1",
    "sg:city":"Putzleinsdorf",
    "sg:orig_category":"Bauunternehmen",
    "sg:phone":"+43 7286 81110",
    "sg:postcode":"4134",
    "sg:province":"Ober\u00f6sterreich",
    "wof:name":"P\u00fchringer Bau + Installations GmbH",
    "wof:placetype":"venue"
},
  "geometry": {"coordinates":[13.8892230988,48.5169715881],"type":"Point"}
}