{
  "type": "Feature",
  "properties": {
    "iso:country":"AT",
    "sg:address":"Mitterndorfer Str 20",
    "sg:city":"Traismauer",
    "sg:orig_category":"Tischlereien",
    "sg:phone":"+43 4367 65209335",
    "sg:postcode":"3133",
    "sg:province":"Nieder\u00f6sterreich",
    "wof:name":"H\u00f6rhann Erika",
    "wof:placetype":"venue"
},
  "geometry": {"coordinates":[15.7499103546,48.3505401611],"type":"Point"}
}