{
  "type": "Feature",
  "properties": {
    "addr:full":"Lenaustr 31 Linz Ober\u00f6sterreich 4020",
    "addr:housenumber":"31",
    "addr:postcode":"4020",
    "addr:street":"Lenaustr",
    "iso:country":"AT",
    "sg:address":"Lenaustr 31",
    "sg:city":"Linz",
    "sg:classifiers":[
        {
            "category":"Restaurant",
            "type":"Food & Drink"
        }
    ],
    "sg:phone":"+43 4373 2651478",
    "sg:postcode":"4020",
    "sg:province":"Ober\u00f6sterreich",
    "sg:tags":[
        "pizzeria"
    ],
    "wof:name":"RTO Gastronomie- und Verwaltungs GesmbH Pizzeria Roma",
    "wof:placetype":"venue"
},
  "geometry": {"coordinates":[14.3010826111,48.2915382385],"type":"Point"}
}