{
  "type": "Feature",
  "properties": {
    "addr:full":"Bundesstr 11a Murau Steiermark 8850",
    "addr:housenumber":"11a",
    "addr:postcode":"8850",
    "addr:street":"Bundesstr",
    "iso:country":"AT",
    "sg:address":"Bundesstr 11a",
    "sg:city":"Murau",
    "sg:orig_category":"Polytechnische Schulen",
    "sg:phone":"+43 3532 2040",
    "sg:postcode":"8850",
    "sg:province":"Steiermark",
    "wof:name":"Polytechnische Schule",
    "wof:placetype":"venue"
},
  "geometry": {"coordinates":[14.1776981354,47.1129455566],"type":"Point"}
}