{
  "type": "Feature",
  "properties": {
    "addr:full":"Pfarrg 2 Schleinbach Nieder\u00f6sterreich 2123",
    "addr:housenumber":"2",
    "addr:postcode":"2123",
    "addr:street":"Pfarrg",
    "iso:country":"AT",
    "sg:address":"Pfarrg 2",
    "sg:city":"Schleinbach",
    "sg:orig_category":"Non-Classified Establishments",
    "sg:phone":"+43 2245 89190",
    "sg:postcode":"2123",
    "sg:province":"Nieder\u00f6sterreich",
    "wof:name":"Pfarramt",
    "wof:placetype":"venue"
},
  "geometry": {"coordinates":[16.4917793274,48.446018219],"type":"Point"}
}