{
  "type": "Feature",
  "properties": {
    "addr:full":"Nr 34 Ferlach K\u00e4rnten 9170",
    "addr:postcode":"9170",
    "addr:street":"Nr 34;Kaernten",
    "iso:country":"AT",
    "sg:address":"Nr 34",
    "sg:city":"Ferlach",
    "sg:classifiers":[
        {
            "category":"Home & Garden",
            "subcategory":"Building Materials",
            "type":"Retail Goods"
        }
    ],
    "sg:phone":"+43 4342 2723750",
    "sg:postcode":"9170",
    "sg:province":"K\u00e4rnten",
    "sg:tags":[
        "baustoffe",
        "-material",
        "u"
    ],
    "sg:website":"pagitz-baustoffe.at",
    "wof:name":"Pagitz GesmbH",
    "wof:placetype":"venue"
},
  "geometry": {"coordinates":[14.3864421844,46.4714927673],"type":"Point"}
}