{
  "type": "Feature",
  "properties": {
    "iso:country":"AT",
    "sg:address":"Hauptstr 39",
    "sg:city":"Micheldorf in Ober\u00f6sterreich",
    "sg:orig_category":"Reinigungsservice",
    "sg:phone":"+43 699 10046726",
    "sg:postcode":"4563",
    "sg:province":"Ober\u00f6sterreich",
    "wof:name":"MHD Harald Gutsohn",
    "wof:placetype":"venue"
},
  "geometry": {"coordinates":[14.1339921951,47.8767547607],"type":"Point"}
}