{
  "type": "Feature",
  "properties": {
    "addr:full":"Elisabethstr 62 Baden Nieder\u00f6sterreich 2500",
    "addr:housenumber":"62",
    "addr:postcode":"2500",
    "addr:street":"Elisabethstr;Niederoesterreich",
    "iso:country":"AT",
    "sg:address":"Elisabethstr 62",
    "sg:city":"Baden",
    "sg:orig_category":"Psychotherapie",
    "sg:phone":"+43 699 15818378",
    "sg:postcode":"2500",
    "sg:province":"Nieder\u00f6sterreich",
    "wof:name":"Pirnat-Ecker Marita",
    "wof:placetype":"venue"
},
  "geometry": {"coordinates":[16.22514534,48.00340271],"type":"Point"}
}