{
  "type": "Feature",
  "properties": {
    "iso:country":"AT",
    "sg:address":"Fasanenweg 67",
    "sg:city":"Hartberg",
    "sg:orig_category":"Autobusunternehmen",
    "sg:phone":"+43 3332 63970",
    "sg:postcode":"8230",
    "sg:province":"Steiermark",
    "wof:name":"Verkehrsleitung Hartberg",
    "wof:placetype":"venue"
},
  "geometry": {"coordinates":[15.9904298782,47.2860107422],"type":"Point"}
}