{
  "type": "Feature",
  "properties": {
    "addr:full":"Fasanenweg 67 Hartberg Steiermark 8230",
    "addr:housenumber":"67",
    "addr:postcode":"8230",
    "addr:street":"Fasanenweg",
    "iso:country":"AT",
    "sg:address":"Fasanenweg 67",
    "sg:city":"Hartberg",
    "sg:orig_category":"Autobusunternehmen",
    "sg:phone":"+43 3332 63970",
    "sg:postcode":"8230",
    "sg:province":"Steiermark",
    "wof:name":"Verkehrsleitung Hartberg",
    "wof:placetype":"venue"
},
  "geometry": {"coordinates":[15.9904298782,47.2860107422],"type":"Point"}
}