{
  "type": "Feature",
  "properties": {
    "addr:full":"Kreuzweg 183 Schiefling am See K\u00e4rnten 9535",
    "addr:housenumber":"183",
    "addr:postcode":"9535",
    "addr:street":"Kreuzweg",
    "iso:country":"AT",
    "sg:address":"Kreuzweg 183",
    "sg:city":"Schiefling am See",
    "sg:orig_category":"Pensionen / Privatzimmer",
    "sg:phone":"+43 4342 744306",
    "sg:postcode":"9535",
    "sg:province":"K\u00e4rnten",
    "wof:name":"Pension Windinger",
    "wof:placetype":"venue"
},
  "geometry": {"coordinates":[14.1015167236,46.6034545898],"type":"Point"}
}