{
  "type": "Feature",
  "properties": {
    "iso:country":"AT",
    "sg:address":"Koloman-Wallisch-Pl 22",
    "sg:city":"Bruck an der Mur",
    "sg:orig_category":"Optiker",
    "sg:phone":"+43 3862 544540",
    "sg:postcode":"8600",
    "sg:province":"Steiermark",
    "wof:name":"Wutscher Optik KG",
    "wof:placetype":"venue"
},
  "geometry": {"coordinates":[15.2696256638,47.4105186462],"type":"Point"}
}