{
  "type": "Feature",
  "properties": {
    "addr:full":"Amraser-See-Str 1 Innsbruck Tirol 6020",
    "addr:housenumber":"1",
    "addr:postcode":"6020",
    "addr:street":"Amraser-See-Str;Tirol",
    "iso:country":"AT",
    "sg:address":"Amraser-See-Str 1",
    "sg:city":"Innsbruck",
    "sg:orig_category":"Steinmetzbetriebe",
    "sg:phone":"+43 512 393232",
    "sg:postcode":"6020",
    "sg:province":"Tirol",
    "sg:website":"members.aon.at/pax",
    "wof:name":"Pax Marmor GmbH",
    "wof:placetype":"venue"
},
  "geometry": {"coordinates":[11.4202985764,47.260974884],"type":"Point"}
}