{
  "type": "Feature",
  "properties": {
    "iso:country":"AT",
    "sg:address":"Dingelstedtgasse 11",
    "sg:city":"Wien",
    "sg:classifiers":[
        {
            "category":"Professional",
            "subcategory":"Advertising",
            "type":"Services"
        }
    ],
    "sg:phone":"+43 1 8934253",
    "sg:postcode":"1150",
    "sg:province":"Wien",
    "sg:tags":[
        "poster"
    ],
    "wof:name":"Emil Echsel & Co OHG",
    "wof:placetype":"venue"
},
  "geometry": {"coordinates":[16.3359737396,48.1922111511],"type":"Point"}
}