{
  "type": "Feature",
  "properties": {
    "addr:full":"Stift 6 Leoben Steiermark 8700",
    "addr:housenumber":"6",
    "addr:postcode":"8700",
    "addr:street":"Stift",
    "iso:country":"AT",
    "sg:address":"Stift 6",
    "sg:city":"Leoben",
    "sg:orig_category":"Fernseh- U Radiogesellschaften",
    "sg:phone":"+43 4338 4227072",
    "sg:postcode":"8700",
    "sg:province":"Steiermark",
    "wof:name":"Bezirksfernsehen TV 1 Stift G\u00f6ss",
    "wof:placetype":"venue"
},
  "geometry": {"coordinates":[15.0967998505,47.3630218506],"type":"Point"}
}