{
  "type": "Feature",
  "properties": {
    "addr:full":"Sieveringer Str 175a Wien Wien 1190",
    "addr:housenumber":"175a",
    "addr:postcode":"1190",
    "addr:street":"Sieveringer Str",
    "iso:country":"AT",
    "sg:address":"Sieveringer Str 175a",
    "sg:city":"Wien",
    "sg:orig_category":"Friseure U Frisiersalons",
    "sg:phone":"+43 4314 401778",
    "sg:postcode":"1190",
    "sg:province":"Wien",
    "wof:name":"Steiner Anita",
    "wof:placetype":"venue"
},
  "geometry": {"coordinates":[16.3216705322,48.2516975403],"type":"Point"}
}