{
  "type": "Feature",
  "properties": {
    "addr:full":"KTW-Str 1 Kirchbichl Tirol 6322",
    "addr:housenumber":"1",
    "addr:postcode":"6322",
    "addr:street":"Ktw-Str;Tirol",
    "iso:country":"AT",
    "sg:address":"KTW-Str 1",
    "sg:city":"Kirchbichl",
    "sg:classifiers":[
        {
            "category":"Professional",
            "subcategory":"Computer Services",
            "type":"Services"
        }
    ],
    "sg:phone":"+43 5332 2000",
    "sg:postcode":"6322",
    "sg:province":"Tirol",
    "sg:tags":[
        "software"
    ],
    "sg:website":"ktw.com",
    "wof:name":"KTW Software & Consulting GmbH",
    "wof:placetype":"venue"
},
  "geometry": {"coordinates":[12.0798521042,47.4974746704],"type":"Point"}
}