{
  "type": "Feature",
  "properties": {
    "iso:country":"AT",
    "sg:address":"Reichenauer Str 139",
    "sg:city":"Innsbruck",
    "sg:orig_category":"Garten- U Landschaftsgestaltung",
    "sg:phone":"+43 4351 2390363",
    "sg:postcode":"6020",
    "sg:province":"Tirol",
    "wof:name":"GATTERMAIR",
    "wof:placetype":"venue"
},
  "geometry": {"coordinates":[11.4254598618,47.274520874],"type":"Point"}
}