{
  "type": "Feature",
  "properties": {
    "addr:full":"Engerthstr 249-253 Wien Wien 1020",
    "addr:housenumber":"249-253",
    "addr:postcode":"1020",
    "iso:country":"AT",
    "sg:address":"Engerthstr 249-253",
    "sg:city":"Wien",
    "sg:orig_category":"Familien / Beratung",
    "sg:phone":"+43 1 2110602894",
    "sg:postcode":"1020",
    "sg:province":"Wien",
    "wof:name":"MAG ELF - Eltern Kind Zentrum",
    "wof:placetype":"venue"
},
  "geometry": {"coordinates":[16.4165344238,48.2151145935],"type":"Point"}
}