{
  "type": "Feature",
  "properties": {
    "iso:country":"AT",
    "sg:address":"Eggerweg 526",
    "sg:city":"Kappl",
    "sg:orig_category":"Werbegrafik- U Grafik-Design",
    "sg:phone":"+43 4354 4568399",
    "sg:postcode":"6555",
    "sg:province":"Tirol",
    "wof:name":"m-creativ-design - Marco Sailer",
    "wof:placetype":"venue"
},
  "geometry": {"coordinates":[10.3702163696,47.0637741089],"type":"Point"}
}