{
  "type": "Feature",
  "properties": {
    "addr:full":"Lindeng 19 Lieboch Steiermark 8501",
    "addr:housenumber":"19",
    "addr:postcode":"8501",
    "addr:street":"Lindeng",
    "iso:country":"AT",
    "sg:address":"Lindeng 19",
    "sg:city":"Lieboch",
    "sg:orig_category":"Transportunternehmen",
    "sg:phone":"+43 4366 44635111",
    "sg:postcode":"8501",
    "sg:province":"Steiermark",
    "wof:name":"Sixt Natascha",
    "wof:placetype":"venue"
},
  "geometry": {"coordinates":[15.3428316116,46.9732780457],"type":"Point"}
}