{
  "type": "Feature",
  "properties": {
    "addr:full":"Markt 32 St. Gallen Steiermark 8933",
    "addr:housenumber":"32",
    "addr:postcode":"8933",
    "addr:street":"Markt",
    "iso:country":"AT",
    "sg:address":"Markt 32",
    "sg:city":"St. Gallen",
    "sg:orig_category":"Banken U Sparkassen",
    "sg:phone":"+43 4336 327164",
    "sg:postcode":"8933",
    "sg:province":"Steiermark",
    "wof:name":"Raiffeisenbank Admont regGenmbH",
    "wof:placetype":"venue"
},
  "geometry": {"coordinates":[14.6172552109,47.6922798157],"type":"Point"}
}