{
  "type": "Feature",
  "properties": {
    "addr:full":"Heinestr 36/4 Wien Wien 1020",
    "addr:housenumber":"36 / 4",
    "addr:postcode":"1020",
    "addr:street":"Heinestr",
    "iso:country":"AT",
    "sg:address":"Heinestr 36/4",
    "sg:city":"Wien",
    "sg:orig_category":"Psychotherapie",
    "sg:phone":"+43 664 4427728",
    "sg:postcode":"1020",
    "sg:province":"Wien",
    "wof:name":"Ziegler Heidrun - Ass. \u00c4rztin f Psychiatrie Dr",
    "wof:placetype":"venue"
},
  "geometry": {"coordinates":[16.388589859,48.218837738],"type":"Point"}
}