{
  "type": "Feature",
  "properties": {
    "addr:full":"Bachg 4 Judenburg Steiermark 8750",
    "addr:housenumber":"4",
    "addr:postcode":"8750",
    "addr:street":"Bachg",
    "iso:country":"AT",
    "sg:address":"Bachg 4",
    "sg:city":"Judenburg",
    "sg:orig_category":"Musikgruppen",
    "sg:phone":"+43 3572 86591",
    "sg:postcode":"8750",
    "sg:province":"Steiermark",
    "wof:name":"Alleinunterhalter - Haslebner Fritz",
    "wof:placetype":"venue"
},
  "geometry": {"coordinates":[14.6600446701,47.1651268005],"type":"Point"}
}