{
  "type": "Feature",
  "properties": {
    "addr:full":"Alliogasse 9/6 Wien Wien 1150",
    "addr:housenumber":"9 / 6",
    "addr:postcode":"1150",
    "addr:street":"Alliogasse",
    "iso:country":"AT",
    "sg:address":"Alliogasse 9/6",
    "sg:city":"Wien",
    "sg:classifiers":[
        {
            "category":"Professional",
            "subcategory":"Accounting & Tax Preparation",
            "type":"Services"
        }
    ],
    "sg:phone":"+43 1 9854950",
    "sg:postcode":"1150",
    "sg:province":"Wien",
    "sg:tags":[
        "control",
        "access",
        "contactless",
        "systems",
        "identity"
    ],
    "sg:website":"iwd.at",
    "wof:name":"IWD Ing. Walter D\u00f6rr Zeit- und Zutrittskontrolle Industrie- und B\u00fcrouhren Service und Vertrieb",
    "wof:placetype":"venue"
},
  "geometry": {"coordinates":[16.3280506134,48.201423645],"type":"Point"}
}