{
  "type": "Feature",
  "properties": {
    "iso:country":"AT",
    "sg:address":"Rudolfstr 242",
    "sg:city":"Graz",
    "sg:orig_category":"Bibliotheken",
    "sg:phone":"+43 316 303391",
    "sg:postcode":"8010",
    "sg:province":"Steiermark",
    "wof:name":"Stadtbibliothek d Magistrates",
    "wof:placetype":"venue"
},
  "geometry": {"coordinates":[15.4880533218,47.0728874207],"type":"Point"}
}