{
  "type": "Feature",
  "properties": {
    "addr:full":"Hauptstrasse 233 Wals Salzburg 5071",
    "addr:housenumber":"233",
    "addr:postcode":"5071",
    "addr:street":"Hauptstrasse;Salzburg",
    "iso:country":"AT",
    "sg:address":"Hauptstrasse 233",
    "sg:city":"Wals",
    "sg:classifiers":[
        {
            "category":"Food & Beverages",
            "subcategory":"Fruits & Vegetables",
            "type":"Retail Goods"
        }
    ],
    "sg:phone":"+43 662 8510220",
    "sg:postcode":"5071",
    "sg:province":"Salzburg",
    "sg:tags":[
        "flower",
        "seed"
    ],
    "sg:website":"gartencenter-posch.at",
    "wof:name":"Gartencenter Posch Ges.m.b.H. & Co KG",
    "wof:placetype":"venue"
},
  "geometry": {"coordinates":[12.9694385529,47.7898712158],"type":"Point"}
}