{
  "type": "Feature",
  "properties": {
    "addr:full":"Stubenbach 282 Lech Vorarlberg 6764",
    "addr:housenumber":"282",
    "addr:postcode":"6764",
    "addr:street":"Stubenbach",
    "iso:country":"AT",
    "sg:address":"Stubenbach 282",
    "sg:city":"Lech",
    "sg:orig_category":"Pensionen / Privatzimmer",
    "sg:phone":"+43 5583 2966",
    "sg:postcode":"6764",
    "sg:province":"Vorarlberg",
    "wof:name":"Haus Irmgard",
    "wof:placetype":"venue"
},
  "geometry": {"coordinates":[10.1565876007,47.2214279175],"type":"Point"}
}