{
  "type": "Feature",
  "properties": {
    "addr:full":"Schwenkg 3 Wien Wien 1120",
    "addr:housenumber":"3",
    "addr:postcode":"1120",
    "addr:street":"Schwenkg",
    "iso:country":"AT",
    "sg:address":"Schwenkg 3",
    "sg:city":"Wien",
    "sg:orig_category":"Steuerberatung",
    "sg:phone":"+43 1 8137319",
    "sg:postcode":"1120",
    "sg:province":"Wien",
    "wof:name":"Wimmer Adelheid",
    "wof:placetype":"venue"
},
  "geometry": {"coordinates":[16.3211021423,48.1802368164],"type":"Point"}
}