{
  "type": "Feature",
  "properties": {
    "iso:country":"AT",
    "sg:address":"Simmeringer Hauptstr 41",
    "sg:city":"Wien",
    "sg:orig_category":"Restaurants: Chinesisch",
    "sg:phone":"+43 1 7493422",
    "sg:postcode":"1110",
    "sg:province":"Wien",
    "wof:name":"China-Restaurant Aroma",
    "wof:placetype":"venue"
},
  "geometry": {"coordinates":[16.4097537994,48.1806259155],"type":"Point"}
}