{
  "type": "Feature",
  "properties": {
    "addr:full":"Bahnl\u00e4nde 77 Wien Wien 1100",
    "addr:housenumber":"77",
    "addr:postcode":"1100",
    "addr:street":"Bahnlaende",
    "iso:country":"AT",
    "sg:address":"Bahnl\u00e4nde 77",
    "sg:city":"Wien",
    "sg:orig_category":"Weiterbildungsinstitute M Allg U Berufl Bildungsangebot",
    "sg:phone":"+43 1 6892417",
    "sg:postcode":"1100",
    "sg:province":"Wien",
    "wof:name":"Aquarius Holistic Academy Individual- und Managementttraining",
    "wof:placetype":"venue"
},
  "geometry": {"coordinates":[16.3842430115,48.1456108093],"type":"Point"}
}