{
  "type": "Feature",
  "properties": {
    "addr:full":"Obere Hauptstr 21 Rohrendorf Nieder\u00f6sterreich 3495",
    "addr:housenumber":"21",
    "addr:postcode":"3495",
    "addr:street":"Obere Hauptstr",
    "iso:country":"AT",
    "sg:address":"Obere Hauptstr 21",
    "sg:city":"Rohrendorf",
    "sg:orig_category":"Volksschulen",
    "sg:phone":"+43 2732 8385014",
    "sg:postcode":"3495",
    "sg:province":"Nieder\u00f6sterreich",
    "wof:name":"Volksschule Rohrendorf",
    "wof:placetype":"venue"
},
  "geometry": {"coordinates":[15.6546373367,48.4189720154],"type":"Point"}
}