{
  "type": "Feature",
  "properties": {
    "iso:country":"AT",
    "sg:address":"Lerchenfelder Str 22",
    "sg:city":"Traismauer",
    "sg:orig_category":"Erdarbeiten",
    "sg:phone":"+43 4327 838058",
    "sg:postcode":"3133",
    "sg:province":"Nieder\u00f6sterreich",
    "wof:name":"Reuter Franz",
    "wof:placetype":"venue"
},
  "geometry": {"coordinates":[15.7161808014,48.3583335876],"type":"Point"}
}