{
  "type": "Feature",
  "properties": {
    "addr:full":"Realschulstr 6/5 Dornbirn Vorarlberg 6850",
    "addr:housenumber":"6 / 5",
    "addr:postcode":"6850",
    "addr:street":"Realschulstr",
    "iso:country":"AT",
    "sg:address":"Realschulstr 6/5",
    "sg:city":"Dornbirn",
    "sg:orig_category":"Architekten",
    "sg:phone":"+43 5572 55066",
    "sg:postcode":"6850",
    "sg:province":"Vorarlberg",
    "sg:website":"www.mages.at",
    "wof:name":"Architekt DI Mages Rudolf",
    "wof:placetype":"venue"
},
  "geometry": {"coordinates":[9.7412023544,47.4122886658],"type":"Point"}
}