{
  "type": "Feature",
  "properties": {
    "addr:full":"K\u00e4rntner Str 228 Neuhart Steiermark 8053",
    "addr:housenumber":"228",
    "addr:postcode":"neuhart;8053",
    "addr:street":"Str",
    "iso:country":"AT",
    "sg:address":"K\u00e4rntner Str 228",
    "sg:city":"Neuhart",
    "sg:orig_category":"Betten",
    "sg:phone":"+43 316 2858400",
    "sg:postcode":"8053",
    "sg:province":"Steiermark",
    "wof:name":"D\u00e4nisches Bettenlager HandelsgesmbH",
    "wof:placetype":"venue"
},
  "geometry": {"coordinates":[15.3952732086,47.0450782776],"type":"Point"}
}