{
  "type": "Feature",
  "properties": {
    "addr:full":"Pater Rodlberger-Str 12 Wels Ober\u00f6sterreich 4600",
    "addr:housenumber":"12",
    "addr:postcode":"4600",
    "addr:street":"Pater Rodlberger-Str;Oberoesterreich",
    "iso:country":"AT",
    "sg:address":"Pater Rodlberger-Str 12",
    "sg:city":"Wels",
    "sg:orig_category":"Elektroinstallationsunternehmen",
    "sg:phone":"+43 7242 911068",
    "sg:postcode":"4600",
    "sg:province":"Ober\u00f6sterreich",
    "wof:name":"Glasner Wilhelm Ing",
    "wof:placetype":"venue"
},
  "geometry": {"coordinates":[14.0291795731,48.1528930664],"type":"Point"}
}