{
  "type": "Feature",
  "properties": {
    "addr:full":"Am Pfaffenberg 1 Bad Deutsch Altenburg Nieder\u00f6sterreich 2405",
    "addr:housenumber":"1",
    "addr:postcode":"2405",
    "addr:street":"Am Pfaffenberg",
    "iso:country":"AT",
    "sg:address":"Am Pfaffenberg 1",
    "sg:city":"Bad Deutsch Altenburg",
    "sg:classifiers":[
        {
            "category":"Home & Garden",
            "subcategory":"Garden Supply",
            "type":"Retail Goods"
        }
    ],
    "sg:phone":"+43 4321 65622420",
    "sg:postcode":"2405",
    "sg:province":"Nieder\u00f6sterreich",
    "sg:tags":[
        "schotter",
        "sand",
        "u"
    ],
    "wof:name":"Hollitzer Baustoffwerke Betriebs-GesmbH",
    "wof:placetype":"venue"
},
  "geometry": {"coordinates":[16.9053001404,48.1338043213],"type":"Point"}
}