{
  "type": "Feature",
  "properties": {
    "addr:full":"Dorf 487 Lech Vorarlberg 6764",
    "addr:housenumber":"487",
    "addr:postcode":"6764",
    "addr:street":"Dorf",
    "iso:country":"AT",
    "sg:address":"Dorf 487",
    "sg:city":"Lech",
    "sg:classifiers":[
        {
            "category":"Travel",
            "subcategory":"Hotels & Motels",
            "type":"Entertainment"
        }
    ],
    "sg:phone":"+43 4355 8329700",
    "sg:postcode":"6764",
    "sg:province":"Vorarlberg",
    "wof:name":"Hotel Zursilvia",
    "wof:placetype":"venue"
},
  "geometry": {"coordinates":[10.1413106918,47.207408905],"type":"Point"}
}