{
  "type": "Feature",
  "properties": {
    "addr:full":"Hirscheng 10/2/4 Wien Wien 1060",
    "addr:housenumber":"10 / 2 / 4",
    "addr:postcode":"1060",
    "addr:street":"Hirscheng",
    "iso:country":"AT",
    "sg:address":"Hirscheng 10/2/4",
    "sg:city":"Wien",
    "sg:orig_category":"Architekten",
    "sg:phone":"+43 4319 675422",
    "sg:postcode":"1060",
    "sg:province":"Wien",
    "wof:name":"Schauer Malgorzata Arch Dipl-Ing",
    "wof:placetype":"venue"
},
  "geometry": {"coordinates":[16.3504657745,48.1947135925],"type":"Point"}
}