{
  "type": "Feature",
  "properties": {
    "addr:full":"Kapuzinerstrasse 38 Linz Ober\u00f6sterreich 4020",
    "addr:housenumber":"38",
    "addr:postcode":"4020",
    "addr:street":"Kapuzinerstrasse",
    "iso:country":"AT",
    "sg:address":"Kapuzinerstrasse 38",
    "sg:city":"Linz",
    "sg:classifiers":[
        {
            "category":"Professional",
            "subcategory":"Printing & Photocopies",
            "type":"Services"
        }
    ],
    "sg:phone":"+43 732 7774870",
    "sg:postcode":"4020",
    "sg:province":"Ober\u00f6sterreich",
    "sg:tags":[
        "offset"
    ],
    "sg:website":"fidelis.at",
    "wof:name":"FIDELIS Druck Ges.m.b.H.",
    "wof:placetype":"venue"
},
  "geometry": {"coordinates":[14.2815523148,48.2996559143],"type":"Point"}
}