{
  "type": "Feature",
  "properties": {
    "addr:full":"Nr 78 Pischelsdorf in Steiermark Steiermark 8212",
    "addr:postcode":"8212",
    "addr:street":"Nr;Pischelsdorf",
    "iso:country":"AT",
    "sg:address":"Nr 78",
    "sg:city":"Pischelsdorf in Steiermark",
    "sg:orig_category":"Gemeinden",
    "sg:phone":"+43 4331 1324100",
    "sg:postcode":"8212",
    "sg:province":"Steiermark",
    "wof:name":"Gemeindeamt Gersdorf an der Feistritz",
    "wof:placetype":"venue"
},
  "geometry": {"coordinates":[15.8060102463,47.1733627319],"type":"Point"}
}