{
  "type": "Feature",
  "properties": {
    "iso:country":"AT",
    "sg:address":"B\u00f6cksteiner Bundesstr 30",
    "sg:city":"Bad Gastein",
    "sg:orig_category":"Autoreparatur",
    "sg:phone":"+43 4364 3420840",
    "sg:postcode":"5640",
    "sg:province":"Salzburg",
    "wof:name":"Glawitsch Franz KG",
    "wof:placetype":"venue"
},
  "geometry": {"coordinates":[13.1329622269,47.1046867371],"type":"Point"}
}