{
  "type": "Feature",
  "properties": {
    "addr:full":"Sinabelkirchen 107 Sinabelkirchen Steiermark 8261",
    "addr:housenumber":"107",
    "addr:postcode":"8261",
    "addr:street":"Sinabelkirchen",
    "iso:country":"AT",
    "sg:address":"Sinabelkirchen 107",
    "sg:city":"Sinabelkirchen",
    "sg:classifiers":[
        {
            "category":"Home & Garden",
            "subcategory":"Furniture",
            "type":"Retail Goods"
        }
    ],
    "sg:phone":"+43 3118 2226",
    "sg:postcode":"8261",
    "sg:province":"Steiermark",
    "sg:tags":[
        "bathroom"
    ],
    "wof:name":"Karl Manninger",
    "wof:placetype":"venue"
},
  "geometry": {"coordinates":[15.8233537674,47.1051254272],"type":"Point"}
}