{
  "type": "Feature",
  "properties": {
    "addr:full":"Nr 160 Rettenegg Steiermark 8674",
    "addr:postcode":"8674",
    "addr:street":"Nr",
    "iso:country":"AT",
    "sg:address":"Nr 160",
    "sg:city":"Rettenegg",
    "sg:orig_category":"Pensionen / Privatzimmer",
    "sg:phone":"+43 4331 738252",
    "sg:postcode":"8674",
    "sg:province":"Steiermark",
    "wof:name":"St\u00f6gerer Fr\u00fchst\u00fcckspension",
    "wof:placetype":"venue"
},
  "geometry": {"coordinates":[15.7791147232,47.5252799988],"type":"Point"}
}