{
  "type": "Feature",
  "properties": {
    "addr:full":"P\u00f6llach 117 St. Gilgen Salzburg 5340",
    "addr:housenumber":"117",
    "addr:postcode":"5340",
    "iso:country":"AT",
    "sg:address":"P\u00f6llach 117",
    "sg:city":"St. Gilgen",
    "sg:orig_category":"Garagentore U -Antriebe",
    "sg:phone":"+43 4362 2727037",
    "sg:postcode":"5340",
    "sg:province":"Salzburg",
    "wof:name":"Haslauer METALLBAU GmbH",
    "wof:placetype":"venue"
},
  "geometry": {"coordinates":[13.3484992981,47.7797851562],"type":"Point"}
}