{
  "type": "Feature",
  "properties": {
    "addr:full":"Nr 197 Admont Steiermark 8911",
    "addr:postcode":"8911",
    "addr:street":"Nr",
    "iso:country":"AT",
    "sg:address":"Nr 197",
    "sg:city":"Admont",
    "sg:orig_category":"Volksschulen",
    "sg:phone":"+43 3613 2780",
    "sg:postcode":"8911",
    "sg:province":"Steiermark",
    "wof:name":"Volksschule",
    "wof:placetype":"venue"
},
  "geometry": {"coordinates":[14.4609088898,47.5760040283],"type":"Point"}
}