{
  "type": "Feature",
  "properties": {
    "addr:full":"Friedhofstr 401A Tamsweg Salzburg 5580",
    "addr:housenumber":"401a",
    "addr:postcode":"5580",
    "addr:street":"Salzburg",
    "iso:country":"AT",
    "sg:address":"Friedhofstr 401A",
    "sg:city":"Tamsweg",
    "sg:orig_category":"Weiterbildungsinstitute M Allg U Berufl Bildungsangebot",
    "sg:phone":"+43 6474 27076",
    "sg:postcode":"5580",
    "sg:province":"Salzburg",
    "wof:name":"Lungauer Bildungsverbund",
    "wof:placetype":"venue"
},
  "geometry": {"coordinates":[13.8129768372,47.1286773682],"type":"Point"}
}