{
  "type": "Feature",
  "properties": {
    "addr:full":"Nr 37 Niederndorf Tirol 6342",
    "addr:postcode":"6342",
    "addr:street":"Nr 37;Tirol",
    "iso:country":"AT",
    "sg:address":"Nr 37",
    "sg:city":"Niederndorf",
    "sg:orig_category":"Autohandel",
    "sg:phone":"+43 5373 61296",
    "sg:postcode":"6342",
    "sg:province":"Tirol",
    "wof:name":"Autohaus Kaltschmid GmbH & Co KG",
    "wof:placetype":"venue"
},
  "geometry": {"coordinates":[12.2141237259,47.6500205994],"type":"Point"}
}