{
  "type": "Feature",
  "properties": {
    "iso:country":"AT",
    "sg:address":"Pfarrg 11",
    "sg:city":"Bad Ischl",
    "sg:orig_category":"Polizei U Gendarmerie",
    "sg:phone":"+43 4361 3223288",
    "sg:postcode":"4820",
    "sg:province":"Ober\u00f6sterreich",
    "wof:name":"Polizei",
    "wof:placetype":"venue"
},
  "geometry": {"coordinates":[13.6219987869,47.7110214233],"type":"Point"}
}