{
  "type": "Feature",
  "properties": {
    "addr:full":"Rumer Str 51d Innsbruck Tirol 6020",
    "addr:postcode":"6020",
    "addr:street":"Str 51D;Tirol",
    "iso:country":"AT",
    "sg:address":"Rumer Str 51d",
    "sg:city":"Innsbruck",
    "sg:orig_category":"Institute",
    "sg:phone":"+43 512 263272",
    "sg:postcode":"6020",
    "sg:province":"Tirol",
    "wof:name":"Tiroler Musikforschung",
    "wof:placetype":"venue"
},
  "geometry": {"coordinates":[11.4358901978,47.2846603394],"type":"Point"}
}