{
  "type": "Feature",
  "properties": {
    "iso:country":"AT",
    "sg:address":"Nr 34",
    "sg:city":"Metnitz",
    "sg:orig_category":"Transportunternehmen",
    "sg:phone":"+43 4267 5040",
    "sg:postcode":"9363",
    "sg:province":"K\u00e4rnten",
    "wof:name":"Brachmaier Otmar",
    "wof:placetype":"venue"
},
  "geometry": {"coordinates":[14.2160253525,46.9812393188],"type":"Point"}
}