{
  "type": "Feature",
  "properties": {
    "addr:full":"St. P\u00f6ltner Str 117 Herzogenburg Nieder\u00f6sterreich 3130",
    "addr:housenumber":"117",
    "addr:postcode":"3130",
    "addr:street":"Str",
    "iso:country":"AT",
    "sg:address":"St. P\u00f6ltner Str 117",
    "sg:city":"Herzogenburg",
    "sg:orig_category":"Fertigteilbau",
    "sg:phone":"+43 4327 8282514",
    "sg:postcode":"3130",
    "sg:province":"Nieder\u00f6sterreich",
    "wof:name":"Oberndorfer Franz GmbH & Co",
    "wof:placetype":"venue"
},
  "geometry": {"coordinates":[15.6871261597,48.2675056458],"type":"Point"}
}