{
  "type": "Feature",
  "properties": {
    "addr:full":"Kalkofenweg 7 Oberalm Salzburg 5411",
    "addr:housenumber":"7",
    "addr:postcode":"5411",
    "addr:street":"Kalkofenweg;Salzburg",
    "iso:country":"AT",
    "sg:address":"Kalkofenweg 7",
    "sg:city":"Oberalm",
    "sg:classifiers":[
        {
            "category":"Home & Garden",
            "subcategory":"Building Materials",
            "type":"Retail Goods"
        }
    ],
    "sg:phone":"+43 4362 4580904",
    "sg:postcode":"5411",
    "sg:province":"Salzburg",
    "sg:tags":[
        "baustoffe",
        "-material",
        "u"
    ],
    "wof:name":"Gl\u00fcck Roman KEG - Naturbaustoffe",
    "wof:placetype":"venue"
},
  "geometry": {"coordinates":[13.1094331741,47.7019805908],"type":"Point"}
}