{
  "type": "Feature",
  "properties": {
    "addr:full":"Kochg 9 Wien Wien 1080",
    "addr:housenumber":"9",
    "addr:postcode":"1080",
    "addr:street":"Kochg",
    "iso:country":"AT",
    "sg:address":"Kochg 9",
    "sg:city":"Wien",
    "sg:orig_category":"Restaurants: Griechisch",
    "sg:phone":"+43 1 4057083",
    "sg:postcode":"1080",
    "sg:province":"Wien",
    "wof:name":"Restaurant Dionysos",
    "wof:placetype":"venue"
},
  "geometry": {"coordinates":[16.3493614197,48.2127685547],"type":"Point"}
}