{
  "type": "Feature",
  "properties": {
    "iso:country":"AT",
    "sg:address":"Gradnerstr 145",
    "sg:city":"Stra\u00dfgang",
    "sg:orig_category":"Maschinenbau",
    "sg:phone":"+43 316 2533400",
    "sg:postcode":"8054",
    "sg:province":"Steiermark",
    "wof:name":"Ulmer GmbH",
    "wof:placetype":"venue"
},
  "geometry": {"coordinates":[15.4083099365,47.0212211609],"type":"Point"}
}