{
  "type": "Feature",
  "properties": {
    "iso:country":"AT",
    "sg:address":"Weyprechtg 5/31",
    "sg:city":"Wien",
    "sg:orig_category":"Maler, Anstreicher U Lackierer",
    "sg:phone":"+43 4313 337165",
    "sg:postcode":"1160",
    "sg:province":"Wien",
    "wof:name":"Kaiser",
    "wof:placetype":"venue"
},
  "geometry": {"coordinates":[16.3343811035,48.2139015198],"type":"Point"}
}