{
  "type": "Feature",
  "properties": {
    "iso:country":"AT",
    "sg:address":"Hirschstettner Str 19-21",
    "sg:city":"Wien",
    "sg:classifiers":[
        {
            "category":"Professional",
            "subcategory":"Computer Services",
            "type":"Services"
        }
    ],
    "sg:phone":"+43 1 2569725",
    "sg:postcode":"1220",
    "sg:province":"Wien",
    "sg:tags":[
        "software"
    ],
    "wof:name":"Software Technologies-Development-Service GesmbH",
    "wof:placetype":"venue"
},
  "geometry": {"coordinates":[16.4532337189,48.2456359863],"type":"Point"}
}