{
  "type": "Feature",
  "properties": {
    "addr:full":"Angerstr 1 Hartberg Steiermark 8230",
    "addr:housenumber":"1",
    "addr:postcode":"8230",
    "addr:street":"Angerstr",
    "iso:country":"AT",
    "sg:address":"Angerstr 1",
    "sg:city":"Hartberg",
    "sg:orig_category":"Lebensmittel / Einzelhandel",
    "sg:phone":"+43 4333 3263877",
    "sg:postcode":"8230",
    "sg:province":"Steiermark",
    "wof:name":"Magnet / E center",
    "wof:placetype":"venue"
},
  "geometry": {"coordinates":[15.980091095,47.2871818542],"type":"Point"}
}