{
  "type": "Feature",
  "properties": {
    "iso:country":"AT",
    "sg:address":"Hauptstr 376",
    "sg:city":"Langegg",
    "sg:orig_category":"Banken U Sparkassen",
    "sg:phone":"+43 2862 53488",
    "sg:postcode":"3872",
    "sg:province":"Nieder\u00f6sterreich",
    "wof:name":"Raiffeisenbank Oberes Waldviertel regGenmbH",
    "wof:placetype":"venue"
},
  "geometry": {"coordinates":[15.0874223709,48.8302955627],"type":"Point"}
}