{
  "type": "Feature",
  "properties": {
    "addr:full":"Bahnhofstr 40 Ebensee Ober\u00f6sterreich 4802",
    "addr:housenumber":"40",
    "addr:postcode":"4802",
    "addr:street":"Bahnhofstr",
    "iso:country":"AT",
    "sg:address":"Bahnhofstr 40",
    "sg:city":"Ebensee",
    "sg:orig_category":"Chemisch-Technische Produkte",
    "sg:phone":"+43 6133 54110",
    "sg:postcode":"4802",
    "sg:province":"Ober\u00f6sterreich",
    "wof:name":"Solvay \u00f6sterreich GmbH",
    "wof:placetype":"venue"
},
  "geometry": {"coordinates":[13.7704210281,47.8045959473],"type":"Point"}
}