{
  "type": "Feature",
  "properties": {
    "addr:full":"Gatterederstr 8/3 Wien Wien 1230",
    "addr:housenumber":"8 / 3",
    "addr:postcode":"1230",
    "addr:street":"Gatterederstr",
    "iso:country":"AT",
    "sg:address":"Gatterederstr 8/3",
    "sg:city":"Wien",
    "sg:orig_category":"Telekommunikation",
    "sg:phone":"+43 1 8863217",
    "sg:postcode":"1230",
    "sg:province":"Wien",
    "wof:name":"TELE SELECT MANSER OEG",
    "wof:placetype":"venue"
},
  "geometry": {"coordinates":[16.2898712158,48.1516799927],"type":"Point"}
}