{
  "type": "Feature",
  "properties": {
    "iso:country":"AT",
    "sg:address":"Aschauerweg 151",
    "sg:city":"Going am Wilden Kaiser",
    "sg:orig_category":"Appartements / Ferienwohnungen",
    "sg:phone":"+43 4353 582747",
    "sg:postcode":"6353",
    "sg:province":"Tirol",
    "wof:name":"Hain Anton",
    "wof:placetype":"venue"
},
  "geometry": {"coordinates":[12.3452701569,47.519821167],"type":"Point"}
}