{
  "type": "Feature",
  "properties": {
    "addr:full":"Glemmerstrasse 55 Maishofen Salzburg 5751",
    "addr:housenumber":"55",
    "addr:postcode":"5751",
    "addr:street":"Glemmerstrasse;Salzburg",
    "iso:country":"AT",
    "sg:address":"Glemmerstrasse 55",
    "sg:city":"Maishofen",
    "sg:classifiers":[
        {
            "category":"Manufacturing",
            "subcategory":"Wood Products",
            "type":"Manufacturing & Wholesale Goods"
        }
    ],
    "sg:phone":"+43 6542 68205",
    "sg:postcode":"5751",
    "sg:province":"Salzburg",
    "sg:tags":[
        "lumber"
    ],
    "wof:name":"Albin Neumayr GesmbH & Co KG",
    "wof:placetype":"venue"
},
  "geometry": {"coordinates":[12.783706665,47.3640174866],"type":"Point"}
}