{
  "type": "Feature",
  "properties": {
    "addr:full":"Liebigg 4 Wien Wien 1010",
    "addr:housenumber":"4",
    "addr:postcode":"1010",
    "addr:street":"Liebigg",
    "iso:country":"AT",
    "sg:address":"Liebigg 4",
    "sg:city":"Wien",
    "sg:orig_category":"Altwaren",
    "sg:phone":"+43 1 4060719",
    "sg:postcode":"1010",
    "sg:province":"Wien",
    "wof:name":"Matschnigs Antik Keller",
    "wof:placetype":"venue"
},
  "geometry": {"coordinates":[16.3583908081,48.2134857178],"type":"Point"}
}