{
  "type": "Feature",
  "properties": {
    "addr:full":"Mittriedstr 38 Hard Vorarlberg 6971",
    "addr:housenumber":"38",
    "addr:postcode":"6971",
    "addr:street":"Mittriedstr",
    "iso:country":"AT",
    "sg:address":"Mittriedstr 38",
    "sg:city":"Hard",
    "sg:orig_category":"Autoreparatur",
    "sg:phone":"+43 4366 42027300",
    "sg:postcode":"6971",
    "sg:province":"Vorarlberg",
    "wof:name":"Baumann KFZ",
    "wof:placetype":"venue"
},
  "geometry": {"coordinates":[9.6925239563,47.4839019775],"type":"Point"}
}