{
  "type": "Feature",
  "properties": {
    "addr:full":"Eisenhowerstr 18 Wels Ober\u00f6sterreich 4600",
    "addr:housenumber":"18",
    "addr:postcode":"4600",
    "addr:street":"Eisenhowerstr;Oberoesterreich",
    "iso:country":"AT",
    "sg:address":"Eisenhowerstr 18",
    "sg:city":"Wels",
    "sg:orig_category":"Polytechnische Schulen",
    "sg:phone":"+43 7242 235657",
    "sg:postcode":"4600",
    "sg:province":"Ober\u00f6sterreich",
    "wof:name":"Polytechnische Schule",
    "wof:placetype":"venue"
},
  "geometry": {"coordinates":[14.022644043,48.1621627808],"type":"Point"}
}