{
  "type": "Feature",
  "properties": {
    "iso:country":"AT",
    "sg:address":"Nr 59",
    "sg:city":"Schrems",
    "sg:orig_category":"Autobusunternehmen",
    "sg:phone":"+43 2853 76557",
    "sg:postcode":"3943",
    "sg:province":"Nieder\u00f6sterreich",
    "wof:name":"Zeiler Siegfried",
    "wof:placetype":"venue"
},
  "geometry": {"coordinates":[15.0714254379,48.7929534912],"type":"Point"}
}