{
  "type": "Feature",
  "properties": {
    "addr:full":"Hollabererstr 8-10 Linz Ober\u00f6sterreich 4020",
    "addr:housenumber":"8-10",
    "addr:postcode":"4020",
    "iso:country":"AT",
    "sg:address":"Hollabererstr 8-10",
    "sg:city":"Linz",
    "sg:orig_category":"Messen U Ausstellungen",
    "sg:phone":"+43 732 611100",
    "sg:postcode":"4020",
    "sg:province":"Ober\u00f6sterreich",
    "wof:name":"Messe Management Linz GesmbH",
    "wof:placetype":"venue"
},
  "geometry": {"coordinates":[14.329167366,48.3011054993],"type":"Point"}
}