{
  "type": "Feature",
  "properties": {
    "addr:full":"Daponteg 11 Wien Wien 1030",
    "addr:housenumber":"11",
    "addr:postcode":"1030",
    "addr:street":"Daponteg",
    "iso:country":"AT",
    "sg:address":"Daponteg 11",
    "sg:city":"Wien",
    "sg:orig_category":"Alarmanlagen U Sicherheitssysteme",
    "sg:phone":"+43 4317 1521010",
    "sg:postcode":"1030",
    "sg:province":"Wien",
    "wof:name":"Breitenbach & Heller GmbH",
    "wof:placetype":"venue"
},
  "geometry": {"coordinates":[16.3877048492,48.1979141235],"type":"Point"}
}