{
  "type": "Feature",
  "properties": {
    "addr:full":"Nr 132 Ried im Oberinntal Tirol 6531",
    "addr:postcode":"6531",
    "addr:street":"Nr 132;Tirol",
    "iso:country":"AT",
    "sg:address":"Nr 132",
    "sg:city":"Ried im Oberinntal",
    "sg:orig_category":"Tapezierer U Dekorateure",
    "sg:phone":"+43 4354 726422",
    "sg:postcode":"6531",
    "sg:province":"Tirol",
    "wof:name":"Mair Bruno",
    "wof:placetype":"venue"
},
  "geometry": {"coordinates":[10.654545784,47.0553817749],"type":"Point"}
}