{
  "type": "Feature",
  "properties": {
    "addr:full":"Hauptstr 71 Neumarkt am Wallersee Salzburg 5202",
    "addr:housenumber":"71",
    "addr:postcode":"5202",
    "addr:street":"Hauptstr;Salzburg",
    "iso:country":"AT",
    "sg:address":"Hauptstr 71",
    "sg:city":"Neumarkt am Wallersee",
    "sg:orig_category":"Installationsunternehmen",
    "sg:phone":"+43 4362 1620029",
    "sg:postcode":"5202",
    "sg:province":"Salzburg",
    "wof:name":"IMSER INSTALLATIONEN Gas-Wasser-Heizung-Fliesen",
    "wof:placetype":"venue"
},
  "geometry": {"coordinates":[13.2254390717,47.9481658936],"type":"Point"}
}