{
  "type": "Feature",
  "properties": {
    "addr:full":"Hackhoferg 13 Wien Wien 1190",
    "addr:housenumber":"13",
    "addr:postcode":"1190",
    "addr:street":"Hackhoferg",
    "iso:country":"AT",
    "sg:address":"Hackhoferg 13",
    "sg:city":"Wien",
    "sg:orig_category":"Selbsthilfegruppen",
    "sg:phone":"+43 1 3701285",
    "sg:postcode":"1190",
    "sg:province":"Wien",
    "wof:name":"Hoffnung Selbsthilfegruppe Schmerz",
    "wof:placetype":"venue"
},
  "geometry": {"coordinates":[16.365234375,48.2618370056],"type":"Point"}
}