{
  "type": "Feature",
  "properties": {
    "addr:full":"Halleng 2b Wiener Neustadt Nieder\u00f6sterreich 2700",
    "addr:housenumber":"2b",
    "addr:postcode":"2700",
    "addr:street":"Halleng",
    "iso:country":"AT",
    "sg:address":"Halleng 2b",
    "sg:city":"Wiener Neustadt",
    "sg:orig_category":"Maschinenbau",
    "sg:phone":"+43 2622 232190",
    "sg:postcode":"2700",
    "sg:province":"Nieder\u00f6sterreich",
    "wof:name":"Mican & Stoisser Maschinenfabrik GesmbH",
    "wof:placetype":"venue"
},
  "geometry": {"coordinates":[16.239402771,47.8055496216],"type":"Point"}
}