{
  "type": "Feature",
  "properties": {
    "addr:full":"Nr 138 Neukirchen am Walde Ober\u00f6sterreich 4724",
    "addr:postcode":"4724",
    "addr:street":"Nr 138",
    "iso:country":"AT",
    "sg:address":"Nr 138",
    "sg:city":"Neukirchen am Walde",
    "sg:orig_category":"Damenmoden",
    "sg:phone":"+43 7278 3302",
    "sg:postcode":"4724",
    "sg:province":"Ober\u00f6sterreich",
    "wof:name":"Zachbauer Robert",
    "wof:placetype":"venue"
},
  "geometry": {"coordinates":[13.7808732986,48.4049911499],"type":"Point"}
}