{
  "type": "Feature",
  "properties": {
    "addr:full":"Lustenauerstr. 125  Hohenems Vorarlberg 6845",
    "addr:housenumber":"125",
    "addr:postcode":"6845",
    "iso:country":"AT",
    "sg:address":"Lustenauerstr. 125 ",
    "sg:city":"Hohenems",
    "sg:classifiers":[
        {
            "category":"Home & Garden",
            "subcategory":"Home Furnishings",
            "type":"Retail Goods"
        }
    ],
    "sg:phone":"+43 4355 76731380",
    "sg:postcode":"6845",
    "sg:province":"Vorarlberg",
    "sg:tags":[
        "household"
    ],
    "wof:name":"SUTER GESMBH",
    "wof:placetype":"venue"
},
  "geometry": {"coordinates":[9.6773166656,47.3741188049],"type":"Point"}
}