{
  "type": "Feature",
  "properties": {
    "addr:full":"Wilhelmsdorfer Str 24 Poysdorf Nieder\u00f6sterreich 2170",
    "addr:postcode":"2170",
    "addr:street":"Str;Niederoesterreich",
    "iso:country":"AT",
    "sg:address":"Wilhelmsdorfer Str 24",
    "sg:city":"Poysdorf",
    "sg:orig_category":"Rebschulen",
    "sg:phone":"+43 4325 523500",
    "sg:postcode":"2170",
    "sg:province":"Nieder\u00f6sterreich",
    "wof:name":"Strobl Lorenz u Karin",
    "wof:placetype":"venue"
},
  "geometry": {"coordinates":[16.6295757294,48.668674469],"type":"Point"}
}