{
  "type": "Feature",
  "properties": {
    "addr:full":"Freinberger Str 12 Mondsee Ober\u00f6sterreich 5310",
    "addr:housenumber":"12",
    "addr:postcode":"5310",
    "addr:street":"Str;Oberoesterreich",
    "iso:country":"AT",
    "sg:address":"Freinberger Str 12",
    "sg:city":"Mondsee",
    "sg:orig_category":"\u00c3\u201erzte / F Allgemeinmedizin",
    "sg:phone":"+43 6232 2212",
    "sg:postcode":"5310",
    "sg:province":"Ober\u00f6sterreich",
    "wof:name":"G\u00f6tz Hans-Peter Dr",
    "wof:placetype":"venue"
},
  "geometry": {"coordinates":[13.3468790054,47.8565139771],"type":"Point"}
}