{
  "type": "Feature",
  "properties": {
    "iso:country":"AT",
    "sg:address":"Spenglerg 6",
    "sg:city":"Kirchberg in Tirol",
    "sg:orig_category":"Glasereien",
    "sg:phone":"+43 4353 572361",
    "sg:postcode":"6365",
    "sg:province":"Tirol",
    "wof:name":"Schwaiger Matthias",
    "wof:placetype":"venue"
},
  "geometry": {"coordinates":[12.3123931885,47.4470291138],"type":"Point"}
}