{
  "type": "Feature",
  "properties": {
    "addr:full":"Dorf 36 Reith im Alpbachtal Tirol 6235",
    "addr:housenumber":"36",
    "addr:postcode":"6235",
    "addr:street":"Dorf;Alpbachtal Tirol",
    "iso:country":"AT",
    "sg:address":"Dorf 36",
    "sg:city":"Reith im Alpbachtal",
    "sg:orig_category":"Elektroinstallationsunternehmen",
    "sg:phone":"+43 4353 3764610",
    "sg:postcode":"6235",
    "sg:province":"Tirol",
    "wof:name":"Elektro Bischofer GmbH & Co KG",
    "wof:placetype":"venue"
},
  "geometry": {"coordinates":[11.878993988,47.4160118103],"type":"Point"}
}