{
  "type": "Feature",
  "properties": {
    "addr:full":"Gewerbestr 2 Lochen Ober\u00f6sterreich 5221",
    "addr:housenumber":"2",
    "addr:postcode":"5221",
    "addr:street":"Gewerbestr",
    "iso:country":"AT",
    "sg:address":"Gewerbestr 2",
    "sg:city":"Lochen",
    "sg:orig_category":"Edelstahl",
    "sg:phone":"+43 7745 8504",
    "sg:postcode":"5221",
    "sg:province":"Ober\u00f6sterreich",
    "wof:name":"Meister Josef Laser-Schneid-Technik",
    "wof:placetype":"venue"
},
  "geometry": {"coordinates":[13.1841096878,48.0089111328],"type":"Point"}
}