{
  "type": "Feature",
  "properties": {
    "addr:full":"Bethlehemstr 10 Linz Ober\u00f6sterreich 4020",
    "addr:housenumber":"10",
    "addr:postcode":"4020",
    "addr:street":"Bethlehemstr",
    "iso:country":"AT",
    "sg:address":"Bethlehemstr 10",
    "sg:city":"Linz",
    "sg:orig_category":"Matratzen",
    "sg:phone":"+43 732 771989",
    "sg:postcode":"4020",
    "sg:province":"Ober\u00f6sterreich",
    "wof:name":"Gr\u00fcne Erde Shop & Schaur\u00e4ume",
    "wof:placetype":"venue"
},
  "geometry": {"coordinates":[14.2902822495,48.3033790588],"type":"Point"}
}