{
  "type": "Feature",
  "properties": {
    "addr:full":"Nr 7 Nu\u00dfdorf am Attersee Ober\u00f6sterreich 4865",
    "addr:postcode":"4865",
    "addr:street":"Nr",
    "iso:country":"AT",
    "sg:address":"Nr 7",
    "sg:city":"Nu\u00dfdorf am Attersee",
    "sg:classifiers":[
        {
            "category":"Restaurant",
            "type":"Food & Drink"
        }
    ],
    "sg:phone":"+43 4376 6620972",
    "sg:postcode":"4865",
    "sg:province":"Ober\u00f6sterreich",
    "sg:tags":[
        "pizzeria"
    ],
    "wof:name":"Pizzeria Sandro",
    "wof:placetype":"venue"
},
  "geometry": {"coordinates":[13.5230150223,47.8826751709],"type":"Point"}
}