{
  "type": "Feature",
  "properties": {
    "addr:full":"Linzer Str 131 Wien Wien 1140",
    "addr:housenumber":"131",
    "addr:postcode":"1140",
    "addr:street":"Linzer Str",
    "iso:country":"AT",
    "sg:address":"Linzer Str 131",
    "sg:city":"Wien",
    "sg:orig_category":"Friseure U Frisiersalons",
    "sg:phone":"+43 1 9831263",
    "sg:postcode":"1140",
    "sg:province":"Wien",
    "wof:name":"Dopplinger Karin",
    "wof:placetype":"venue"
},
  "geometry": {"coordinates":[16.3025665283,48.1934890747],"type":"Point"}
}