{
  "type": "Feature",
  "properties": {
    "addr:full":"Toldg 6 Wien Wien 1150",
    "addr:housenumber":"6",
    "addr:postcode":"1150",
    "addr:street":"Toldg",
    "iso:country":"AT",
    "sg:address":"Toldg 6",
    "sg:city":"Wien",
    "sg:orig_category":"Immobilienverwaltungen",
    "sg:phone":"+43 1 98203300",
    "sg:postcode":"1150",
    "sg:province":"Wien",
    "wof:name":"Rannegger Heidi",
    "wof:placetype":"venue"
},
  "geometry": {"coordinates":[16.3320903778,48.2006416321],"type":"Point"}
}