{
  "type": "Feature",
  "properties": {
    "addr:full":"Tiroler Str 19 Lienz Tirol 9900",
    "addr:postcode":"9900",
    "addr:street":"Str 19;Tirol",
    "iso:country":"AT",
    "sg:address":"Tiroler Str 19",
    "sg:city":"Lienz",
    "sg:orig_category":"Farben U Lacke / Einzelhandel",
    "sg:phone":"+43 4348 5263339",
    "sg:postcode":"9900",
    "sg:province":"Tirol",
    "wof:name":"Defregger Farben Tapeten GesmbH",
    "wof:placetype":"venue"
},
  "geometry": {"coordinates":[12.7664346695,46.8275985718],"type":"Point"}
}