{
  "type": "Feature",
  "properties": {
    "addr:full":"Sigmund Haffner-G 6 Salzburg Salzburg 5020",
    "addr:housenumber":"6",
    "addr:postcode":"5020",
    "addr:street":"Salzburg",
    "iso:country":"AT",
    "sg:address":"Sigmund Haffner-G 6",
    "sg:city":"Salzburg",
    "sg:orig_category":"Stoffe / Erzeugung U Gro\u00c3\u0178handel",
    "sg:phone":"+43 662 8417300",
    "sg:postcode":"5020",
    "sg:province":"Salzburg",
    "sg:website":"www.betten-schweitzer.com",
    "wof:name":"Schweitzer Franz GesmbH",
    "wof:placetype":"venue"
},
  "geometry": {"coordinates":[13.044254303,47.7996444702],"type":"Point"}
}