{
  "type": "Feature",
  "properties": {
    "iso:country":"AT",
    "sg:address":"Castellezg 33/6",
    "sg:city":"Wien",
    "sg:orig_category":"Zahntechnische Laboratorien",
    "sg:phone":"+43 1 2164819",
    "sg:postcode":"1020",
    "sg:province":"Wien",
    "wof:name":"Augarten Dental Karl Hruby GmbH",
    "wof:placetype":"venue"
},
  "geometry": {"coordinates":[16.3815345764,48.2237205505],"type":"Point"}
}