{
  "type": "Feature",
  "properties": {
    "iso:country":"AT",
    "sg:address":"Schoellerg. 9 ",
    "sg:city":"Ternitz",
    "sg:classifiers":[
        {
            "category":"Professional",
            "subcategory":"Engineering",
            "type":"Services"
        }
    ],
    "sg:phone":"+43 4326 30357060",
    "sg:postcode":"2630",
    "sg:province":"Nieder\u00f6sterreich",
    "sg:tags":[
        "machine",
        "-",
        "mechanical"
    ],
    "wof:name":"MAPLAN MASCHINENBAU GESMBH",
    "wof:placetype":"venue"
},
  "geometry": {"coordinates":[16.0392436981,47.7149620056],"type":"Point"}
}