{
  "type": "Feature",
  "properties": {
    "iso:country":"AT",
    "sg:address":"St. Georg. Hauptstr. 122",
    "sg:city":"St. Georgen am Steinfelde",
    "sg:classifiers":[
        {
            "category":"Manufacturing",
            "subcategory":"Motor Vehicles & Parts",
            "type":"Manufacturing & Wholesale Goods"
        }
    ],
    "sg:phone":"+43 4327 428852720",
    "sg:postcode":"3151",
    "sg:province":"Nieder\u00f6sterreich",
    "sg:tags":[
        "engine"
    ],
    "wof:name":"K\u00d6SSLER GES.MBH",
    "wof:placetype":"venue"
},
  "geometry": {"coordinates":[15.6131343842,48.140209198],"type":"Point"}
}