{
  "type": "Feature",
  "properties": {
    "addr:full":"Fellentorstr 3 Lauterach Vorarlberg 6923",
    "addr:housenumber":"3",
    "addr:postcode":"6923",
    "addr:street":"Fellentorstr",
    "iso:country":"AT",
    "sg:address":"Fellentorstr 3",
    "sg:city":"Lauterach",
    "sg:orig_category":"Waschmaschinen / Reparatur",
    "sg:phone":"+43 5574 74024",
    "sg:postcode":"6923",
    "sg:province":"Vorarlberg",
    "wof:name":"Elektro-Service Stengg",
    "wof:placetype":"venue"
},
  "geometry": {"coordinates":[9.7221336365,47.4755096436],"type":"Point"}
}