{
  "type": "Feature",
  "properties": {
    "addr:full":"Nr 19 Sch\u00f6rfling am Attersee Ober\u00f6sterreich 4861",
    "addr:postcode":"4861",
    "addr:street":"Nr 19;Am",
    "iso:country":"AT",
    "sg:address":"Nr 19",
    "sg:city":"Sch\u00f6rfling am Attersee",
    "sg:orig_category":"Autobusunternehmen",
    "sg:phone":"+43 766286250",
    "sg:postcode":"4861",
    "sg:province":"Ober\u00f6sterreich",
    "wof:name":"Apfl Alfred",
    "wof:placetype":"venue"
},
  "geometry": {"coordinates":[13.6041002274,47.9463386536],"type":"Point"}
}