{
  "type": "Feature",
  "properties": {
    "addr:full":"Birostrasse 14 Wien Wien 1230",
    "addr:housenumber":"14",
    "addr:postcode":"1230",
    "addr:street":"Birostrasse",
    "iso:country":"AT",
    "sg:address":"Birostrasse 14",
    "sg:city":"Wien",
    "sg:orig_category":"Fruits, Dried",
    "sg:phone":"+43 1 61678810",
    "sg:postcode":"1230",
    "sg:province":"Wien",
    "sg:website":"hweihs.com",
    "wof:name":"H.M. Weihs GmbH",
    "wof:placetype":"venue"
},
  "geometry": {"coordinates":[16.3521709442,48.1366653442],"type":"Point"}
}