{
  "type": "Feature",
  "properties": {
    "iso:country":"AT",
    "sg:address":"Plattenweg 9",
    "sg:city":"Feldkirch",
    "sg:orig_category":"Friseure U Frisiersalons",
    "sg:phone":"+43 4367 67271747",
    "sg:postcode":"6800",
    "sg:province":"Vorarlberg",
    "wof:name":"Mobilfriseur Spliss",
    "wof:placetype":"venue"
},
  "geometry": {"coordinates":[9.5582399368,47.229221344],"type":"Point"}
}