{
  "type": "Feature",
  "properties": {
    "addr:full":"Anton-Sattler-G 116 Wien Wien 1220",
    "addr:housenumber":"116",
    "addr:postcode":"1220",
    "iso:country":"AT",
    "sg:address":"Anton-Sattler-G 116",
    "sg:city":"Wien",
    "sg:orig_category":"Raumgestaltung",
    "sg:phone":"+43 1 25925600",
    "sg:postcode":"1220",
    "sg:province":"Wien",
    "wof:name":"Mader Walter",
    "wof:placetype":"venue"
},
  "geometry": {"coordinates":[16.4439105988,48.2551078796],"type":"Point"}
}