{
  "type": "Feature",
  "properties": {
    "iso:country":"AT",
    "sg:address":"Ebendorferstr 8/24",
    "sg:city":"Wien",
    "sg:orig_category":"Non-Classified Establishments",
    "sg:phone":"+43 1 40633080",
    "sg:postcode":"1010",
    "sg:province":"Wien",
    "wof:name":"Zentrum d Erzdi\u00f6zese Wien f Theologiestudenten",
    "wof:placetype":"venue"
},
  "geometry": {"coordinates":[16.3580856323,48.2127952576],"type":"Point"}
}