{
  "type": "Feature",
  "properties": {
    "addr:full":"Kaiserstr 27 Bregenz Vorarlberg 6900",
    "addr:housenumber":"27",
    "addr:postcode":"6900",
    "addr:street":"Kaiserstr",
    "iso:country":"AT",
    "sg:address":"Kaiserstr 27",
    "sg:city":"Bregenz",
    "sg:orig_category":"Architekten",
    "sg:phone":"+43 5574 469630",
    "sg:postcode":"6900",
    "sg:province":"Vorarlberg",
    "wof:name":"raumhochrosen - architekturerzeugnisse",
    "wof:placetype":"venue"
},
  "geometry": {"coordinates":[9.7457437515,47.503238678],"type":"Point"}
}