{
  "type": "Feature",
  "properties": {
    "addr:full":"Hauptstr 24 D\u00fcrnkrut Nieder\u00f6sterreich 2263",
    "addr:housenumber":"24",
    "addr:postcode":"2263",
    "addr:street":"Hauptstr;Niederoesterreich",
    "iso:country":"AT",
    "sg:address":"Hauptstr 24",
    "sg:city":"D\u00fcrnkrut",
    "sg:orig_category":"Fliesen- U Plattenverlegungen",
    "sg:phone":"+43 4325 3880026",
    "sg:postcode":"2263",
    "sg:province":"Nieder\u00f6sterreich",
    "wof:name":"Sandner OEG",
    "wof:placetype":"venue"
},
  "geometry": {"coordinates":[16.8525505066,48.4718170166],"type":"Point"}
}