{
  "type": "Feature",
  "properties": {
    "iso:country":"AT",
    "sg:address":"Reinprechtsdorfer Strasse 49a",
    "sg:city":"Wien",
    "sg:classifiers":[
        {
            "category":"Shopping",
            "subcategory":"Jewelry",
            "type":"Retail Goods"
        }
    ],
    "sg:phone":"+43 1 5454020",
    "sg:postcode":"1050",
    "sg:province":"Wien",
    "sg:tags":[
        "jewellery",
        "gold"
    ],
    "sg:website":"juwelier-ernst.at",
    "wof:name":"Ernst Kozel Gnbr",
    "wof:placetype":"venue"
},
  "geometry": {"coordinates":[16.3521614075,48.1874160767],"type":"Point"}
}