{
  "type": "Feature",
  "properties": {
    "addr:full":"Ramsau 14a Hippach Tirol 6283",
    "addr:housenumber":"14a",
    "addr:postcode":"6283",
    "addr:street":"Ramsau;Tirol",
    "iso:country":"AT",
    "sg:address":"Ramsau 14a",
    "sg:city":"Hippach",
    "sg:orig_category":"Appartements / Ferienwohnungen",
    "sg:phone":"+43 4352 823532",
    "sg:postcode":"6283",
    "sg:province":"Tirol",
    "wof:name":"Haus Birkenheim",
    "wof:placetype":"venue"
},
  "geometry": {"coordinates":[11.8709201813,47.2054481506],"type":"Point"}
}