{
  "type": "Feature",
  "properties": {
    "iso:country":"AT",
    "sg:address":"Nr 26",
    "sg:city":"F\u00fcrstenfeld",
    "sg:orig_category":"Banken U Sparkassen",
    "sg:phone":"+43 4333 82527120",
    "sg:postcode":"8280",
    "sg:province":"Steiermark",
    "wof:name":"Bankomat d Raiffeisenbank F\u00fcrstenfeld regGenmbH",
    "wof:placetype":"venue"
},
  "geometry": {"coordinates":[16.0478401184,47.0652618408],"type":"Point"}
}