{
  "type": "Feature",
  "properties": {
    "addr:full":"Bahnhofstrasse 20 Telfs Tirol 6410",
    "addr:housenumber":"20",
    "addr:postcode":"6410",
    "addr:street":"Bahnhofstrasse;Tirol",
    "iso:country":"AT",
    "sg:address":"Bahnhofstrasse 20",
    "sg:city":"Telfs",
    "sg:classifiers":[
        {
            "category":"Autos & Motor Vehicles",
            "subcategory":"Automobile Sales",
            "type":"Retail Goods"
        }
    ],
    "sg:phone":"+43 5262 64106",
    "sg:postcode":"6410",
    "sg:province":"Tirol",
    "sg:tags":[
        "varnish",
        "lacquers"
    ],
    "sg:website":"members.aon.at/farbenweiskopf",
    "wof:name":"Weiskopf GmbH",
    "wof:placetype":"venue"
},
  "geometry": {"coordinates":[11.0724773407,47.304397583],"type":"Point"}
}