{
  "type": "Feature",
  "properties": {
    "addr:full":"Wiener Strasse 24 Gloggnitz Nieder\u00f6sterreich 2640",
    "addr:housenumber":"24",
    "addr:postcode":"2640",
    "addr:street":"Wiener Strasse",
    "iso:country":"AT",
    "sg:address":"Wiener Strasse 24",
    "sg:city":"Gloggnitz",
    "sg:classifiers":[
        {
            "category":"Building & Trades",
            "subcategory":"Electrical",
            "type":"Services"
        }
    ],
    "sg:phone":"+43 2662 42282",
    "sg:postcode":"2640",
    "sg:province":"Nieder\u00f6sterreich",
    "sg:tags":[
        "work",
        "installation"
    ],
    "sg:website":"elektro-zottl.xodox.at",
    "wof:name":"Ing. Heinz Zottl",
    "wof:placetype":"venue"
},
  "geometry": {"coordinates":[15.9434070587,47.6738624573],"type":"Point"}
}