{
  "type": "Feature",
  "properties": {
    "addr:full":"Au\u00dferkristen 13 Axams Tirol 6094",
    "addr:housenumber":"13",
    "addr:postcode":"6094",
    "addr:street":"Ausserkristen;Tirol",
    "iso:country":"AT",
    "sg:address":"Au\u00dferkristen 13",
    "sg:city":"Axams",
    "sg:orig_category":"Maler, Anstreicher U Lackierer",
    "sg:phone":"+43 4366 41613934",
    "sg:postcode":"6094",
    "sg:province":"Tirol",
    "wof:name":"Wannack J\u00fcrgen Dekorations- u Kunstmalerei",
    "wof:placetype":"venue"
},
  "geometry": {"coordinates":[11.2958850861,47.2444038391],"type":"Point"}
}