{
  "type": "Feature",
  "properties": {
    "addr:full":"Fronwaldstr 17 Schardenberg Ober\u00f6sterreich 4784",
    "addr:housenumber":"17",
    "addr:postcode":"4784",
    "addr:street":"Fronwaldstr",
    "iso:country":"AT",
    "sg:address":"Fronwaldstr 17",
    "sg:city":"Schardenberg",
    "sg:orig_category":"Autoreparatur",
    "sg:phone":"+43 7713 7132",
    "sg:postcode":"4784",
    "sg:province":"Ober\u00f6sterreich",
    "wof:name":"Knunbauer Herbert",
    "wof:placetype":"venue"
},
  "geometry": {"coordinates":[13.4966459274,48.5206832886],"type":"Point"}
}