{
  "type": "Feature",
  "properties": {
    "iso:country":"AT",
    "sg:address":"Liesinger Flur-G 2c",
    "sg:city":"Wien",
    "sg:orig_category":"Holdinggesellschaften",
    "sg:phone":"+43 1 863900",
    "sg:postcode":"1230",
    "sg:province":"Wien",
    "wof:name":"VIATRIS Holding GmbH",
    "wof:placetype":"venue"
},
  "geometry": {"coordinates":[16.3054618835,48.1358680725],"type":"Point"}
}