{
  "type": "Feature",
  "properties": {
    "addr:full":"Dammweg 10 Judendorf-Stra\u00dfengel Steiermark 8111",
    "addr:housenumber":"10",
    "addr:postcode":"8111",
    "addr:street":"Dammweg",
    "iso:country":"AT",
    "sg:address":"Dammweg 10",
    "sg:city":"Judendorf-Stra\u00dfengel",
    "sg:orig_category":"Werbegrafik- U Grafik-Design",
    "sg:phone":"+43 4331 2454418",
    "sg:postcode":"8111",
    "sg:province":"Steiermark",
    "wof:name":"Graphic Kerstein Werbung & Design",
    "wof:placetype":"venue"
},
  "geometry": {"coordinates":[15.3479166031,47.1179084778],"type":"Point"}
}