{
  "type": "Feature",
  "properties": {
    "addr:full":"Burgstallweg 23a  Kapfenberg Steiermark 8605",
    "addr:housenumber":"23a",
    "addr:postcode":"8605",
    "addr:street":"Burgstallweg",
    "iso:country":"AT",
    "sg:address":"Burgstallweg 23a ",
    "sg:city":"Kapfenberg",
    "sg:classifiers":[
        {
            "category":"Shopping",
            "type":"Retail Goods"
        }
    ],
    "sg:phone":"+43 4338 6234664",
    "sg:postcode":"8605",
    "sg:province":"Steiermark",
    "sg:tags":[
        "finished",
        "-",
        "metallic"
    ],
    "wof:name":"FRANCESCONI TECHNOLOGIE GMBH",
    "wof:placetype":"venue"
},
  "geometry": {"coordinates":[15.3431682587,47.4590873718],"type":"Point"}
}