{
  "type": "Feature",
  "properties": {
    "addr:full":"Sinzingerg 22A Fehring Steiermark 8350",
    "addr:housenumber":"22a",
    "addr:postcode":"8350",
    "addr:street":"Sinzingerg",
    "iso:country":"AT",
    "sg:address":"Sinzingerg 22A",
    "sg:city":"Fehring",
    "sg:orig_category":"Installationsunternehmen",
    "sg:phone":"+43 3155 3684",
    "sg:postcode":"8350",
    "sg:province":"Steiermark",
    "wof:name":"Sch\u00f6gler Alfred",
    "wof:placetype":"venue"
},
  "geometry": {"coordinates":[16.0089435577,46.9304504395],"type":"Point"}
}