{
  "type": "Feature",
  "properties": {
    "addr:full":"Obstg 16A Wiener Neustadt Nieder\u00f6sterreich 2700",
    "addr:housenumber":"16a",
    "addr:postcode":"2700",
    "addr:street":"Obstg",
    "iso:country":"AT",
    "sg:address":"Obstg 16A",
    "sg:city":"Wiener Neustadt",
    "sg:orig_category":"Blitzableiter U Blitzschutzanlagen",
    "sg:phone":"+43 4326 22278590",
    "sg:postcode":"2700",
    "sg:province":"Nieder\u00f6sterreich",
    "wof:name":"Eltro Blitzschutz GesmbH",
    "wof:placetype":"venue"
},
  "geometry": {"coordinates":[16.2321052551,47.8172225952],"type":"Point"}
}