{
  "type": "Feature",
  "properties": {
    "addr:full":"Trondheimg 8 Graz Steiermark 8020",
    "addr:housenumber":"8",
    "addr:postcode":"8020",
    "addr:street":"Trondheimg",
    "iso:country":"AT",
    "sg:address":"Trondheimg 8",
    "sg:city":"Graz",
    "sg:classifiers":[
        {
            "category":"Taxi",
            "type":"Transportation"
        }
    ],
    "sg:phone":"+43 4331 6711554",
    "sg:postcode":"8020",
    "sg:province":"Steiermark",
    "sg:tags":[
        "personentransporte",
        "u"
    ],
    "wof:name":"Schachner Helmut",
    "wof:placetype":"venue"
},
  "geometry": {"coordinates":[15.4235124588,47.0782661438],"type":"Point"}
}