{
  "type": "Feature",
  "properties": {
    "addr:full":"Brockmanng 87 Graz Steiermark 8010",
    "addr:housenumber":"87",
    "addr:postcode":"8010",
    "addr:street":"Brockmanng",
    "iso:country":"AT",
    "sg:address":"Brockmanng 87",
    "sg:city":"Graz",
    "sg:orig_category":"Restaurants: Chinesisch",
    "sg:phone":"+43 316 810373",
    "sg:postcode":"8010",
    "sg:province":"Steiermark",
    "wof:name":"China-Restaurant F\u00fcnf Sterne",
    "wof:placetype":"venue"
},
  "geometry": {"coordinates":[15.4441623688,47.062084198],"type":"Point"}
}