{
  "type": "Feature",
  "properties": {
    "addr:full":"Walser Str 32 Riezlern Vorarlberg 6991",
    "addr:postcode":"6991",
    "addr:street":"Str 32",
    "iso:country":"AT",
    "sg:address":"Walser Str 32",
    "sg:city":"Riezlern",
    "sg:orig_category":"Holzschnitzereien",
    "sg:phone":"+43 4355 175602",
    "sg:postcode":"6991",
    "sg:province":"Vorarlberg",
    "wof:name":"Holzschnitzerei im Tal - M\u00fcller Wolfgang",
    "wof:placetype":"venue"
},
  "geometry": {"coordinates":[10.1895256042,47.3588867188],"type":"Point"}
}