{
  "type": "Feature",
  "properties": {
    "iso:country":"AT",
    "sg:address":"Mellach",
    "sg:city":"Fernitz",
    "sg:classifiers":[
        {
            "category":"Shopping",
            "subcategory":"Computers & Home Electronics",
            "type":"Retail Goods"
        }
    ],
    "sg:phone":"+43 4331 35530410",
    "sg:postcode":"8072",
    "sg:province":"Steiermark",
    "sg:tags":[
        "electronic",
        "electrical",
        "equipment"
    ],
    "wof:name":"STEIRISCHE WASSERKRAFT UND ELEKTRIZIT\u00c4TS AG",
    "wof:placetype":"venue"
},
  "geometry": {"coordinates":[15.5161399841,46.9324607849],"type":"Point"}
}