{
  "type": "Feature",
  "properties": {
    "iso:country":"AT",
    "sg:address":"Reininghausstr 56",
    "sg:city":"Graz",
    "sg:orig_category":"Personalbereitstellung",
    "sg:phone":"+43 4331 6587370",
    "sg:postcode":"8020",
    "sg:province":"Steiermark",
    "wof:name":"EKA Personalbereitstellungs GesmbH",
    "wof:placetype":"venue"
},
  "geometry": {"coordinates":[15.4013576508,47.0636672974],"type":"Point"}
}