{
  "type": "Feature",
  "properties": {
    "iso:country":"AT",
    "sg:address":"Langobardenstrasse 26",
    "sg:city":"Wien",
    "sg:classifiers":[
        {
            "category":"Manufacturing",
            "subcategory":"Soap",
            "type":"Manufacturing & Wholesale Goods"
        }
    ],
    "sg:phone":"+43 1 2821472",
    "sg:postcode":"1220",
    "sg:province":"Wien",
    "sg:tags":[
        "raw",
        "material",
        "detergent"
    ],
    "wof:name":"Friedrich Weiss Stadlauer Seifensiederei",
    "wof:placetype":"venue"
},
  "geometry": {"coordinates":[16.4554405212,48.2237358093],"type":"Point"}
}