{
  "type": "Feature",
  "properties": {
    "addr:full":"Sch\u00f6nbrunner Str 222 Wien Wien 1120",
    "addr:housenumber":"222",
    "addr:postcode":"1120",
    "addr:street":"Str",
    "iso:country":"AT",
    "sg:address":"Sch\u00f6nbrunner Str 222",
    "sg:city":"Wien",
    "sg:orig_category":"Non-Classified Establishments",
    "sg:phone":"+43 1 8135295",
    "sg:postcode":"1120",
    "sg:province":"Wien",
    "wof:name":"TAXI-TEL Standplatztelefon Betriebs GmbH",
    "wof:placetype":"venue"
},
  "geometry": {"coordinates":[16.3290939331,48.1824874878],"type":"Point"}
}