{
  "type": "Feature",
  "properties": {
    "addr:full":"Bockflie\u00dfer Str 12 Auersthal Nieder\u00f6sterreich 2214",
    "addr:postcode":"2214",
    "addr:street":"Str 12",
    "iso:country":"AT",
    "sg:address":"Bockflie\u00dfer Str 12",
    "sg:city":"Auersthal",
    "sg:orig_category":"Schwimmbecken",
    "sg:phone":"+43 2288 2441",
    "sg:postcode":"2214",
    "sg:province":"Nieder\u00f6sterreich",
    "wof:name":"Pool Comfort - J Schr\u00f6nkhammer",
    "wof:placetype":"venue"
},
  "geometry": {"coordinates":[16.6296958923,48.3739700317],"type":"Point"}
}