{
  "type": "Feature",
  "properties": {
    "iso:country":"AT",
    "sg:address":"Leibnizg 37",
    "sg:city":"Wien",
    "sg:orig_category":"Lebensmittel / Einzelhandel",
    "sg:phone":"+43 1 9690856",
    "sg:postcode":"1100",
    "sg:province":"Wien",
    "wof:name":"Cicek Mehmet Hanifi KEG",
    "wof:placetype":"venue"
},
  "geometry": {"coordinates":[16.3757476807,48.1719970703],"type":"Point"}
}