{
  "type": "Feature",
  "properties": {
    "addr:full":"Oberdorf 35 Thalgau Salzburg 5303",
    "addr:housenumber":"35",
    "addr:postcode":"5303",
    "addr:street":"Oberdorf;Salzburg",
    "iso:country":"AT",
    "sg:address":"Oberdorf 35",
    "sg:city":"Thalgau",
    "sg:orig_category":"Erdarbeiten",
    "sg:phone":"+43 6235 5572",
    "sg:postcode":"5303",
    "sg:province":"Salzburg",
    "wof:name":"Schmidhuber Rupert",
    "wof:placetype":"venue"
},
  "geometry": {"coordinates":[13.1979560852,47.8342552185],"type":"Point"}
}