{
  "type": "Feature",
  "properties": {
    "iso:country":"AT",
    "sg:address":"Sierninghofenstr 76",
    "sg:city":"Neuzeug",
    "sg:orig_category":"Schilder",
    "sg:phone":"+43 7259 23790",
    "sg:postcode":"4523",
    "sg:province":"Ober\u00f6sterreich",
    "wof:name":"W. Bayer & Co GesmbH",
    "wof:placetype":"venue"
},
  "geometry": {"coordinates":[14.3221750259,48.0261383057],"type":"Point"}
}