{
  "type": "Feature",
  "properties": {
    "addr:full":"Hofmark 18 Goldegg Salzburg 5622",
    "addr:housenumber":"18",
    "addr:postcode":"5622",
    "addr:street":"Hofmark;Salzburg",
    "iso:country":"AT",
    "sg:address":"Hofmark 18",
    "sg:city":"Goldegg",
    "sg:orig_category":"Tourismusinformation U -Organisationen",
    "sg:phone":"+43 4364 1581310",
    "sg:postcode":"5622",
    "sg:province":"Salzburg",
    "wof:name":"Tourismusverband Goldegg",
    "wof:placetype":"venue"
},
  "geometry": {"coordinates":[13.0994281769,47.3187789917],"type":"Point"}
}