{
  "type": "Feature",
  "properties": {
    "iso:country":"AT",
    "sg:address":"Gramling 9",
    "sg:city":"K\u00f6stendorf",
    "sg:orig_category":"Landwirtschaftliche Produkte",
    "sg:phone":"+43 4362 166541",
    "sg:postcode":"5203",
    "sg:province":"Salzburg",
    "wof:name":"Schober Josef",
    "wof:placetype":"venue"
},
  "geometry": {"coordinates":[13.1981563568,47.9566192627],"type":"Point"}
}