{
  "type": "Feature",
  "properties": {
    "addr:full":"Russhofstr 3 Eichgraben Nieder\u00f6sterreich 3032",
    "addr:housenumber":"3",
    "addr:postcode":"3032",
    "addr:street":"Russhofstr",
    "iso:country":"AT",
    "sg:address":"Russhofstr 3",
    "sg:city":"Eichgraben",
    "sg:orig_category":"Treibriemen",
    "sg:phone":"+43 2773 4670414",
    "sg:postcode":"3032",
    "sg:province":"Nieder\u00f6sterreich",
    "wof:name":"Holub Manfred",
    "wof:placetype":"venue"
},
  "geometry": {"coordinates":[15.9970169067,48.1774673462],"type":"Point"}
}