{
  "type": "Feature",
  "properties": {
    "addr:full":"Rappachg 24 Wien Wien 1110",
    "addr:housenumber":"24",
    "addr:postcode":"1110",
    "addr:street":"Rappachg",
    "iso:country":"AT",
    "sg:address":"Rappachg 24",
    "sg:city":"Wien",
    "sg:orig_category":"Montagen U Montagetechnik",
    "sg:phone":"+43 1 7495180",
    "sg:postcode":"1110",
    "sg:province":"Wien",
    "wof:name":"FM Holzbau + Montage GesmbH",
    "wof:placetype":"venue"
},
  "geometry": {"coordinates":[16.4229507446,48.175327301],"type":"Point"}
}