{
  "type": "Feature",
  "properties": {
    "addr:full":"Linke Wienzeile 108 Wien Wien 1060",
    "addr:housenumber":"108",
    "addr:postcode":"1060",
    "addr:street":"Linke Wienzeile",
    "iso:country":"AT",
    "sg:address":"Linke Wienzeile 108",
    "sg:city":"Wien",
    "sg:orig_category":"Abflussdienste",
    "sg:phone":"+43 4314 892600",
    "sg:postcode":"1060",
    "sg:province":"Wien",
    "sg:website":"rohrrein.com; rohrrein.com; rohrreiniger.at",
    "wof:name":"Rohrrein GmbH",
    "wof:placetype":"venue"
},
  "geometry": {"coordinates":[16.3537406921,48.1926727295],"type":"Point"}
}