{
  "type": "Feature",
  "properties": {
    "addr:full":"Linseng 80 Klagenfurt K\u00e4rnten 9020",
    "addr:housenumber":"80",
    "addr:postcode":"9020",
    "addr:street":"Linseng;Kaernten",
    "iso:country":"AT",
    "sg:address":"Linseng 80",
    "sg:city":"Klagenfurt",
    "sg:orig_category":"Werbeagenturen",
    "sg:phone":"+43 463 503030",
    "sg:postcode":"9020",
    "sg:province":"K\u00e4rnten",
    "wof:name":"Bachinger & Hoffmann Advertising GmbH",
    "wof:placetype":"venue"
},
  "geometry": {"coordinates":[14.2904148102,46.6231155396],"type":"Point"}
}