{
  "type": "Feature",
  "properties": {
    "addr:full":"Neuhausweg 3 Kaltenbach Tirol 6272",
    "addr:housenumber":"3",
    "addr:postcode":"6272",
    "addr:street":"Neuhausweg",
    "iso:country":"AT",
    "sg:address":"Neuhausweg 3",
    "sg:city":"Kaltenbach",
    "sg:orig_category":"Weiterbildungsinstitute M Allg U Berufl Bildungsangebot",
    "sg:phone":"+43 4352 832558",
    "sg:postcode":"6272",
    "sg:province":"Tirol",
    "wof:name":"Erwachsenenschule Mittleres Zillertal",
    "wof:placetype":"venue"
},
  "geometry": {"coordinates":[11.8924617767,47.2848129272],"type":"Point"}
}