{
  "type": "Feature",
  "properties": {
    "addr:full":"Trientlgasse 57  Innsbruck Tirol 6020",
    "addr:housenumber":"57",
    "addr:postcode":"6020",
    "addr:street":"Trientlgasse;Tirol",
    "iso:country":"AT",
    "sg:address":"Trientlgasse 57 ",
    "sg:city":"Innsbruck",
    "sg:classifiers":[
        {
            "category":"Banks & Credit Unions",
            "subcategory":"Investment Brokerage",
            "type":"Services"
        }
    ],
    "sg:phone":"+43 4351 233430",
    "sg:postcode":"6020",
    "sg:province":"Tirol",
    "sg:tags":[
        "-",
        "transport",
        "related"
    ],
    "wof:name":"IMS KUNSTSTOFF GESMBH",
    "wof:placetype":"venue"
},
  "geometry": {"coordinates":[11.4367752075,47.2689247131],"type":"Point"}
}