{
  "type": "Feature",
  "properties": {
    "addr:full":"Raiffeisenstr. 8  Sulz-R\u00f6this Vorarlberg 6832",
    "addr:housenumber":"8",
    "addr:postcode":"6832",
    "addr:street":"Raiffeisenstr.",
    "iso:country":"AT",
    "sg:address":"Raiffeisenstr. 8 ",
    "sg:city":"Sulz-R\u00f6this",
    "sg:classifiers":[
        {
            "category":"Wholesale",
            "subcategory":"Machinery & Supplies",
            "type":"Manufacturing & Wholesale Goods"
        }
    ],
    "sg:phone":"+43 4355 2249410",
    "sg:postcode":"6832",
    "sg:province":"Vorarlberg",
    "sg:tags":[
        "equipment",
        "-",
        "instrument",
        "measurement"
    ],
    "wof:name":"BAUR PR\u00dcF- U. MESSTECHNIK GMBH",
    "wof:placetype":"venue"
},
  "geometry": {"coordinates":[9.6570615768,47.2883338928],"type":"Point"}
}