{
  "type": "Feature",
  "properties": {
    "addr:full":"W\u00e4hringer Str 124 Wien Wien 1180",
    "addr:housenumber":"124",
    "addr:postcode":"1180",
    "addr:street":"Str",
    "iso:country":"AT",
    "sg:address":"W\u00e4hringer Str 124",
    "sg:city":"Wien",
    "sg:orig_category":"Gesundheit / Allgemeine Informationsstellen",
    "sg:phone":"+43 1 4763418280",
    "sg:postcode":"1180",
    "sg:province":"Wien",
    "wof:name":"Bezirksgesundheitsamt f d 18. Bezirk",
    "wof:placetype":"venue"
},
  "geometry": {"coordinates":[16.3425617218,48.2267074585],"type":"Point"}
}