{
  "type": "Feature",
  "properties": {
    "addr:full":"Nr 118 Tauplitz Steiermark 8982",
    "addr:postcode":"8982",
    "addr:street":"Nr",
    "iso:country":"AT",
    "sg:address":"Nr 118",
    "sg:city":"Tauplitz",
    "sg:orig_category":"Appartements / Ferienwohnungen",
    "sg:phone":"+43 4336 882297",
    "sg:postcode":"8982",
    "sg:province":"Steiermark",
    "wof:name":"Hierzegger Helmut",
    "wof:placetype":"venue"
},
  "geometry": {"coordinates":[14.0155315399,47.5634117126],"type":"Point"}
}