{
  "type": "Feature",
  "properties": {
    "addr:full":"Tischlerstr 24 Traun Ober\u00f6sterreich 4050",
    "addr:housenumber":"24",
    "addr:postcode":"4050",
    "addr:street":"Tischlerstr",
    "iso:country":"AT",
    "sg:address":"Tischlerstr 24",
    "sg:city":"Traun",
    "sg:orig_category":"Bestattungsunternehmen",
    "sg:phone":"+43 7229 72423",
    "sg:postcode":"4050",
    "sg:province":"Ober\u00f6sterreich",
    "sg:website":"bestattung-roithner.at",
    "wof:name":"Roithner Rudolf",
    "wof:placetype":"venue"
},
  "geometry": {"coordinates":[14.2407884598,48.2235336304],"type":"Point"}
}