{
  "type": "Feature",
  "properties": {
    "iso:country":"AT",
    "sg:address":"Anger 470",
    "sg:city":"Lech",
    "sg:orig_category":"Pensionen / Privatzimmer",
    "sg:phone":"+43 5583 3760",
    "sg:postcode":"6764",
    "sg:province":"Vorarlberg",
    "wof:name":"Adlerhof",
    "wof:placetype":"venue"
},
  "geometry": {"coordinates":[10.1481189728,47.2123756409],"type":"Point"}
}