{
  "type": "Feature",
  "properties": {
    "iso:country":"AT",
    "sg:address":"Biber 11",
    "sg:city":"Neukirchen an der V\u00f6ckla",
    "sg:orig_category":"Raumausstattung",
    "sg:phone":"+43 4376 827263",
    "sg:postcode":"4872",
    "sg:province":"Ober\u00f6sterreich",
    "wof:name":"Di\u00dflbacher Max",
    "wof:placetype":"venue"
},
  "geometry": {"coordinates":[13.5325937271,48.0328598022],"type":"Point"}
}