{
  "type": "Feature",
  "properties": {
    "addr:full":"Karmeliterg 6 Wien Wien 1020",
    "addr:housenumber":"6",
    "addr:postcode":"1020",
    "addr:street":"Karmeliterg",
    "iso:country":"AT",
    "sg:address":"Karmeliterg 6",
    "sg:city":"Wien",
    "sg:orig_category":"Friseure U Frisiersalons",
    "sg:phone":"+43 4312 148009",
    "sg:postcode":"1020",
    "sg:province":"Wien",
    "sg:website":"afrostudio.at",
    "wof:name":"Afro Studio - The Center of Black Beauty",
    "wof:placetype":"venue"
},
  "geometry": {"coordinates":[16.3789291382,48.2163887024],"type":"Point"}
}