{
  "type": "Feature",
  "properties": {
    "iso:country":"AT",
    "sg:address":"Florianiplatz 1",
    "sg:city":"Gleisdorf",
    "sg:orig_category":"Finanzen, Banken",
    "sg:postcode":"8200",
    "sg:province":"Steiermark",
    "sg:website":"http://www.weiz.volksbank.at",
    "wof:name":"Volksbank f\u00fcr den Bezirk Weiz",
    "wof:placetype":"venue"
},
  "geometry": {"coordinates":[15.7112607956,47.1053771973],"type":"Point"}
}