{
  "type": "Feature",
  "properties": {
    "iso:country":"AT",
    "sg:address":"Wiener Str 26",
    "sg:city":"Schwechat",
    "sg:orig_category":"Tabaktrafiken",
    "sg:phone":"+43 1 7078430",
    "sg:postcode":"2320",
    "sg:province":"Nieder\u00f6sterreich",
    "wof:name":"Gausterer Karl",
    "wof:placetype":"venue"
},
  "geometry": {"coordinates":[16.4723625183,48.143661499],"type":"Point"}
}