{
  "type": "Feature",
  "properties": {
    "addr:full":"Leonfeldner Strasse 4 Zwettl an der Rodl Ober\u00f6sterreich 4180",
    "addr:housenumber":"4",
    "addr:postcode":"4180",
    "addr:street":"Leonfeldner Strasse",
    "iso:country":"AT",
    "sg:address":"Leonfeldner Strasse 4",
    "sg:city":"Zwettl an der Rodl",
    "sg:classifiers":[
        {
            "category":"Home & Garden",
            "subcategory":"Carpets & Floor Coverings",
            "type":"Retail Goods"
        }
    ],
    "sg:phone":"+43 7212 6393",
    "sg:postcode":"4180",
    "sg:province":"Ober\u00f6sterreich",
    "sg:tags":[
        "carpeting"
    ],
    "sg:website":"moebelcom.at",
    "wof:name":"Erwin Kitzm\u00fcller",
    "wof:placetype":"venue"
},
  "geometry": {"coordinates":[14.2729196548,48.4676895142],"type":"Point"}
}