{
  "type": "Feature",
  "properties": {
    "iso:country":"AT",
    "sg:address":"Nr 10",
    "sg:city":"Rottenmann",
    "sg:orig_category":"Appartements / Ferienwohnungen",
    "sg:phone":"+43 3614 2509",
    "sg:postcode":"8786",
    "sg:province":"Steiermark",
    "wof:name":"Thalhamer-Mitterhof",
    "wof:placetype":"venue"
},
  "geometry": {"coordinates":[14.35779953,47.5251693726],"type":"Point"}
}