{
  "type": "Feature",
  "properties": {
    "addr:full":"Antiesenhofen 95 Antiesenhofen Ober\u00f6sterreich 4980",
    "addr:housenumber":"95",
    "addr:postcode":"4980",
    "addr:street":"Antiesenhofen",
    "iso:country":"AT",
    "sg:address":"Antiesenhofen 95",
    "sg:city":"Antiesenhofen",
    "sg:classifiers":[
        {
            "category":"Shopping",
            "subcategory":"Bicycles & Sporting Goods",
            "type":"Retail Goods"
        }
    ],
    "sg:phone":"+43 7759 52610",
    "sg:postcode":"4980",
    "sg:province":"Ober\u00f6sterreich",
    "sg:tags":[
        "snowboard"
    ],
    "wof:name":"GST Global Sports Technologies GmbH",
    "wof:placetype":"venue"
},
  "geometry": {"coordinates":[13.4018602371,48.3493728638],"type":"Point"}
}