{
  "type": "Feature",
  "properties": {
    "addr:full":"Hauptstr. 3c  Wolfsgraben Nieder\u00f6sterreich 3012",
    "addr:housenumber":"3c",
    "addr:postcode":"3012",
    "addr:street":"Hauptstr.",
    "iso:country":"AT",
    "sg:address":"Hauptstr. 3c ",
    "sg:city":"Wolfsgraben",
    "sg:classifiers":[
        {
            "category":"Professional",
            "subcategory":"Business Services",
            "type":"Services"
        }
    ],
    "sg:phone":"+43 4322 3377880",
    "sg:postcode":"3012",
    "sg:province":"Nieder\u00f6sterreich",
    "sg:tags":[
        "advice"
    ],
    "wof:name":"SBB SOFTWARE GESMBH",
    "wof:placetype":"venue"
},
  "geometry": {"coordinates":[16.1240711212,48.1677017212],"type":"Point"}
}