{
  "type": "Feature",
  "properties": {
    "iso:country":"AT",
    "sg:address":"Porzellang 32",
    "sg:city":"Wien",
    "sg:classifiers":[
        {
            "category":"Professional",
            "subcategory":"Computer Services",
            "type":"Services"
        }
    ],
    "sg:phone":"+43 1 3199678",
    "sg:postcode":"1090",
    "sg:province":"Wien",
    "sg:tags":[
        "software"
    ],
    "wof:name":"Atix Software Marketing Friedrich Kofler",
    "wof:placetype":"venue"
},
  "geometry": {"coordinates":[16.3610115051,48.2217483521],"type":"Point"}
}