{
  "type": "Feature",
  "properties": {
    "addr:full":"Oberetrach 27 Krakaudorf Steiermark 8854",
    "addr:housenumber":"27",
    "addr:postcode":"8854",
    "addr:street":"Oberetrach",
    "iso:country":"AT",
    "sg:address":"Oberetrach 27",
    "sg:city":"Krakaudorf",
    "sg:orig_category":"Appartements / Ferienwohnungen",
    "sg:phone":"+43 3535 7354",
    "sg:postcode":"8854",
    "sg:province":"Steiermark",
    "wof:name":"Knapp G\u00fcnter und Brigitte vlg Handl",
    "wof:placetype":"venue"
},
  "geometry": {"coordinates":[13.9921045303,47.1786117554],"type":"Point"}
}