{
  "type": "Feature",
  "properties": {
    "iso:country":"AT",
    "sg:address":"10.-Oktober-Str 2",
    "sg:city":"Hermagor",
    "sg:orig_category":"Drogerien",
    "sg:phone":"+43 4342 822848",
    "sg:postcode":"9620",
    "sg:province":"K\u00e4rnten",
    "wof:name":"dm drogerie markt GmbH",
    "wof:placetype":"venue"
},
  "geometry": {"coordinates":[13.3708734512,46.6270370483],"type":"Point"}
}