{
  "type": "Feature",
  "properties": {
    "addr:full":"Birkenweg 1 Imst Tirol 6460",
    "addr:housenumber":"1",
    "addr:postcode":"6460",
    "addr:street":"Birkenweg;Tirol",
    "iso:country":"AT",
    "sg:address":"Birkenweg 1",
    "sg:city":"Imst",
    "sg:classifiers":[
        {
            "category":"Shopping",
            "type":"Retail Goods"
        }
    ],
    "sg:phone":"+43 4354 1269090",
    "sg:postcode":"6460",
    "sg:province":"Tirol",
    "sg:tags":[
        "finished",
        "-",
        "metallic"
    ],
    "wof:name":"MARKUS STOLZ GES.MBH & CO KG",
    "wof:placetype":"venue"
},
  "geometry": {"coordinates":[10.7352733612,47.2327194214],"type":"Point"}
}