{
  "type": "Feature",
  "properties": {
    "addr:full":"Helmelbodenstr 6 Lunz am See Nieder\u00f6sterreich 3293",
    "addr:housenumber":"6",
    "addr:postcode":"3293",
    "addr:street":"Helmelbodenstr;Niederoesterreich",
    "iso:country":"AT",
    "sg:address":"Helmelbodenstr 6",
    "sg:city":"Lunz am See",
    "sg:orig_category":"Fenster",
    "sg:phone":"+43 7486 8268",
    "sg:postcode":"3293",
    "sg:province":"Nieder\u00f6sterreich",
    "wof:name":"Pechhacker Johann",
    "wof:placetype":"venue"
},
  "geometry": {"coordinates":[15.0208396912,47.857711792],"type":"Point"}
}