{
  "type": "Feature",
  "properties": {
    "iso:country":"AT",
    "sg:address":"St. Veiter Str 70",
    "sg:city":"Klagenfurt",
    "sg:orig_category":"Lebensmittel / Einzelhandel",
    "sg:phone":"+43 4346 3512535",
    "sg:postcode":"9020",
    "sg:province":"K\u00e4rnten",
    "wof:name":"Hofer KG",
    "wof:placetype":"venue"
},
  "geometry": {"coordinates":[14.3111543655,46.634021759],"type":"Point"}
}