{
  "type": "Feature",
  "properties": {
    "addr:full":"Loipersbacher Strasse 7 Neunkirchen Nieder\u00f6sterreich 2620",
    "addr:housenumber":"7",
    "addr:postcode":"2620",
    "addr:street":"Loipersbacher Strasse",
    "iso:country":"AT",
    "sg:address":"Loipersbacher Strasse 7",
    "sg:city":"Neunkirchen",
    "sg:classifiers":[
        {
            "category":"Banks & Credit Unions",
            "subcategory":"Investment Brokerage",
            "type":"Services"
        }
    ],
    "sg:phone":"+43 2635 6000",
    "sg:postcode":"2620",
    "sg:province":"Nieder\u00f6sterreich",
    "sg:tags":[
        "packaging",
        "films",
        "film",
        "laminated"
    ],
    "wof:name":"K. Heyer Ges.m.b.H.",
    "wof:placetype":"venue"
},
  "geometry": {"coordinates":[16.1222019196,47.7224960327],"type":"Point"}
}