{
  "type": "Feature",
  "properties": {
    "addr:full":"Kapfers 1 Telfes im Stubai Tirol 6165",
    "addr:housenumber":"1",
    "addr:postcode":"6165",
    "addr:street":"Kapfers;Tirol",
    "iso:country":"AT",
    "sg:address":"Kapfers 1",
    "sg:city":"Telfes im Stubai",
    "sg:orig_category":"Pensionen / Privatzimmer",
    "sg:phone":"+43 5225 62608",
    "sg:postcode":"6165",
    "sg:province":"Tirol",
    "wof:name":"Thalerhof",
    "wof:placetype":"venue"
},
  "geometry": {"coordinates":[11.3600215912,47.1695594788],"type":"Point"}
}