{
  "type": "Feature",
  "properties": {
    "addr:full":"Dorfstrasse 1 - 3 Leoben Steiermark 8700",
    "addr:housenumber":"1 3",
    "addr:postcode":"8700",
    "addr:street":"Dorfstrasse",
    "iso:country":"AT",
    "sg:address":"Dorfstrasse 1 - 3",
    "sg:city":"Leoben",
    "sg:classifiers":[
        {
            "category":"Government",
            "subcategory":"Fire Station",
            "type":"Public Place"
        }
    ],
    "sg:phone":"+43 3842 212740",
    "sg:postcode":"8700",
    "sg:province":"Steiermark",
    "sg:tags":[
        "blast",
        "furnace"
    ],
    "sg:website":"styrokeram.at",
    "wof:name":"Styrokeram Ges. f\u00fcr Feuerfeste Produkte mbH",
    "wof:placetype":"venue"
},
  "geometry": {"coordinates":[15.0901298523,47.3682899475],"type":"Point"}
}