{
  "type": "Feature",
  "properties": {
    "addr:full":"Kirchstr 3 Fulpmes Tirol 6166",
    "addr:housenumber":"3",
    "addr:postcode":"6166",
    "addr:street":"Kirchstr;Tirol",
    "iso:country":"AT",
    "sg:address":"Kirchstr 3",
    "sg:city":"Fulpmes",
    "sg:orig_category":"Bankomat-Standorte",
    "sg:phone":"+43 5225 62319",
    "sg:postcode":"6166",
    "sg:province":"Tirol",
    "wof:name":"Bankomat d Raiffeisenbank Fulpmes - Telfes regGenmbH",
    "wof:placetype":"venue"
},
  "geometry": {"coordinates":[11.3497543335,47.1530647278],"type":"Point"}
}