{
  "type": "Feature",
  "properties": {
    "addr:full":"Witzelsberger G 23 Wien Wien 1150",
    "addr:housenumber":"23",
    "addr:postcode":"1150",
    "addr:street":"Witzelsberger G",
    "iso:country":"AT",
    "sg:address":"Witzelsberger G 23",
    "sg:city":"Wien",
    "sg:orig_category":"Fleischhauereien",
    "sg:phone":"+43 1 9851151",
    "sg:postcode":"1150",
    "sg:province":"Wien",
    "wof:name":"Sedlak G\u00fcnther",
    "wof:placetype":"venue"
},
  "geometry": {"coordinates":[16.3260917664,48.2016677856],"type":"Point"}
}