{
  "type": "Feature",
  "properties": {
    "addr:full":"Brockmanng 27 Graz Steiermark 8010",
    "addr:housenumber":"27",
    "addr:postcode":"8010",
    "addr:street":"Brockmanng",
    "iso:country":"AT",
    "sg:address":"Brockmanng 27",
    "sg:city":"Graz",
    "sg:orig_category":"Institute",
    "sg:phone":"+43 316 8738227",
    "sg:postcode":"8010",
    "sg:province":"Steiermark",
    "wof:name":"Inst f Quantenchemie",
    "wof:placetype":"venue"
},
  "geometry": {"coordinates":[15.4501256943,47.0644874573],"type":"Point"}
}