{
  "type": "Feature",
  "properties": {
    "addr:full":"Br\u00fcnnlbadg 15 Wien Wien 1090",
    "addr:housenumber":"15",
    "addr:postcode":"1090",
    "addr:street":"Bruennlbadg",
    "iso:country":"AT",
    "sg:address":"Br\u00fcnnlbadg 15",
    "sg:city":"Wien",
    "sg:orig_category":"Restaurants: Indisch",
    "sg:phone":"+43 1 4022123",
    "sg:postcode":"1090",
    "sg:province":"Wien",
    "wof:name":"Restaurant Jaipur Palace",
    "wof:placetype":"venue"
},
  "geometry": {"coordinates":[16.351474762,48.2234115601],"type":"Point"}
}