{
  "type": "Feature",
  "properties": {
    "addr:full":"Nikolaus-Lenau-Str 11 Leoben Steiermark 8700",
    "addr:housenumber":"11",
    "addr:postcode":"8700",
    "addr:street":"Nikolaus-Lenau-Str",
    "iso:country":"AT",
    "sg:address":"Nikolaus-Lenau-Str 11",
    "sg:city":"Leoben",
    "sg:orig_category":"Exporteure U Importeure",
    "sg:phone":"+43 4338 4281174",
    "sg:postcode":"8700",
    "sg:province":"Steiermark",
    "wof:name":"Krainer Alin Tiberiu",
    "wof:placetype":"venue"
},
  "geometry": {"coordinates":[15.1180372238,47.3836288452],"type":"Point"}
}