{
  "type": "Feature",
  "properties": {
    "iso:country":"AT",
    "sg:address":"Metternichg 3",
    "sg:city":"Wien",
    "sg:orig_category":"Botschaften",
    "sg:phone":"+43 1 711540",
    "sg:postcode":"1030",
    "sg:province":"Wien",
    "wof:name":"Botschaft der Bundesrepublik Deutschland",
    "wof:placetype":"venue"
},
  "geometry": {"coordinates":[16.3826961517,48.1975746155],"type":"Point"}
}