{
  "type": "Feature",
  "properties": {
    "addr:full":"Am Sportplatz 12 Unzmarkt Steiermark 8800",
    "addr:housenumber":"12",
    "addr:postcode":"8800",
    "addr:street":"Am Sportplatz",
    "iso:country":"AT",
    "sg:address":"Am Sportplatz 12",
    "sg:city":"Unzmarkt",
    "sg:orig_category":"Holzhandel",
    "sg:phone":"+43 3583 22390",
    "sg:postcode":"8800",
    "sg:province":"Steiermark",
    "wof:name":"Reitinger Alfred",
    "wof:placetype":"venue"
},
  "geometry": {"coordinates":[14.4402713776,47.1971969604],"type":"Point"}
}