{
  "type": "Feature",
  "properties": {
    "addr:full":"Kaplanstr 3 Absam Tirol 6067",
    "addr:housenumber":"3",
    "addr:postcode":"6067",
    "addr:street":"Kaplanstr;Tirol",
    "iso:country":"AT",
    "sg:address":"Kaplanstr 3",
    "sg:city":"Absam",
    "sg:orig_category":"Schneidereien",
    "sg:phone":"+43 664 4714197",
    "sg:postcode":"6067",
    "sg:province":"Tirol",
    "wof:name":"Modestudio Andrea",
    "wof:placetype":"venue"
},
  "geometry": {"coordinates":[11.516283989,47.3015022278],"type":"Point"}
}