{
  "type": "Feature",
  "properties": {
    "iso:country":"AT",
    "sg:address":"Nr 28",
    "sg:city":"Wolfsberg im Schwarzautal",
    "sg:orig_category":"Landwirtschaftliche Produkte",
    "sg:phone":"+43 4331 843217",
    "sg:postcode":"8421",
    "sg:province":"Steiermark",
    "wof:name":"Steirische Naturprodukte Karl Baumann",
    "wof:placetype":"venue"
},
  "geometry": {"coordinates":[15.6651058197,46.8783798218],"type":"Point"}
}