{
  "type": "Feature",
  "properties": {
    "addr:full":"Herbststrasse 53 Wien Wien 1160",
    "addr:housenumber":"53",
    "addr:postcode":"1160",
    "addr:street":"Herbststrasse",
    "iso:country":"AT",
    "sg:address":"Herbststrasse 53",
    "sg:city":"Wien",
    "sg:classifiers":[
        {
            "category":"Government",
            "subcategory":"Court House",
            "type":"Public Place"
        }
    ],
    "sg:phone":"+43 1 4921581",
    "sg:postcode":"1160",
    "sg:province":"Wien",
    "sg:tags":[
        "plant",
        "cellarage",
        "bottle"
    ],
    "wof:name":"Eduard P\u00f6ter",
    "wof:placetype":"venue"
},
  "geometry": {"coordinates":[16.3262577057,48.2063446045],"type":"Point"}
}