{
  "type": "Feature",
  "properties": {
    "iso:country":"AT",
    "sg:address":"Anton-Seidl-Gasse 126",
    "sg:city":"Brunn am Gebirge",
    "sg:classifiers":[
        {
            "category":"Manufacturing",
            "subcategory":"Tools & Machinery",
            "type":"Manufacturing & Wholesale Goods"
        }
    ],
    "sg:phone":"+43 2236 33652",
    "sg:postcode":"2345",
    "sg:province":"Nieder\u00f6sterreich",
    "sg:tags":[
        "construction",
        "container",
        "apparatus"
    ],
    "wof:name":"Ing. Gerhard Bielesz GmbH",
    "wof:placetype":"venue"
},
  "geometry": {"coordinates":[16.2627468109,48.1047897339],"type":"Point"}
}