{
  "type": "Feature",
  "properties": {
    "iso:country":"AT",
    "sg:address":"Alte Arlbergstr 1",
    "sg:city":"St. Anton am Arlberg",
    "sg:orig_category":"Freizeit- U Sportbekleidung",
    "sg:phone":"+43 4354 462524",
    "sg:postcode":"6580",
    "sg:province":"Tirol",
    "wof:name":"Huber Sportmoden & Co",
    "wof:placetype":"venue"
},
  "geometry": {"coordinates":[10.2631597519,47.1272315979],"type":"Point"}
}