{
  "type": "Feature",
  "properties": {
    "iso:country":"AT",
    "sg:address":"H\u00f6henstr 13",
    "sg:city":"Telfs",
    "sg:orig_category":"Transportunternehmen",
    "sg:phone":"+43 664 3075222",
    "sg:postcode":"6410",
    "sg:province":"Tirol",
    "wof:name":"Schmid Stefan",
    "wof:placetype":"venue"
},
  "geometry": {"coordinates":[11.0751829147,47.3205680847],"type":"Point"}
}