{
  "type": "Feature",
  "properties": {
    "addr:full":"H\u00f6henstr 13 Telfs Tirol 6410",
    "addr:housenumber":"13",
    "addr:postcode":"6410",
    "addr:street":"Hoehenstr;Tirol",
    "iso:country":"AT",
    "sg:address":"H\u00f6henstr 13",
    "sg:city":"Telfs",
    "sg:orig_category":"Transportunternehmen",
    "sg:phone":"+43 664 3075222",
    "sg:postcode":"6410",
    "sg:province":"Tirol",
    "wof:name":"Schmid Stefan",
    "wof:placetype":"venue"
},
  "geometry": {"coordinates":[11.0751829147,47.3205680847],"type":"Point"}
}