{
  "type": "Feature",
  "properties": {
    "addr:full":"Neil-Armstrong-Str 5 Tattendorf Nieder\u00f6sterreich 2523",
    "addr:housenumber":"5",
    "addr:postcode":"2523",
    "addr:street":"Neil-Armstrong-Str",
    "iso:country":"AT",
    "sg:address":"Neil-Armstrong-Str 5",
    "sg:city":"Tattendorf",
    "sg:orig_category":"Alternativtherapie",
    "sg:phone":"+43 2253 81864",
    "sg:postcode":"2523",
    "sg:province":"Nieder\u00f6sterreich",
    "wof:name":"Posch Gabriela - Shiatsu - Tai-Chi -QI-Gong",
    "wof:placetype":"venue"
},
  "geometry": {"coordinates":[16.3031272888,47.9496994019],"type":"Point"}
}