{
  "type": "Feature",
  "properties": {
    "iso:country":"AT",
    "sg:address":"Servitengasse 10",
    "sg:city":"Wien",
    "sg:classifiers":[
        {
            "category":"Manufacturing",
            "subcategory":"Glass & Minerals",
            "type":"Manufacturing & Wholesale Goods"
        }
    ],
    "sg:phone":"+43 1 31792320",
    "sg:postcode":"1090",
    "sg:province":"Wien",
    "sg:tags":[
        "flat"
    ],
    "sg:website":"petschenig.com",
    "wof:name":"Petschenig Glastec GmbH & Co. KG",
    "wof:placetype":"venue"
},
  "geometry": {"coordinates":[16.3645038605,48.2202148438],"type":"Point"}
}