{
  "type": "Feature",
  "properties": {
    "addr:full":"Hauptpl 34 Stainach Steiermark 8950",
    "addr:housenumber":"34",
    "addr:postcode":"8950",
    "addr:street":"Hauptpl",
    "iso:country":"AT",
    "sg:address":"Hauptpl 34",
    "sg:city":"Stainach",
    "sg:orig_category":"Ingenieurkonsulenten / Zivilingenieure",
    "sg:phone":"+43 4336 82228080",
    "sg:postcode":"8950",
    "sg:province":"Steiermark",
    "wof:name":"Fritz Martin Dipl-Ing",
    "wof:placetype":"venue"
},
  "geometry": {"coordinates":[14.1075839996,47.5336036682],"type":"Point"}
}