{
  "type": "Feature",
  "properties": {
    "addr:full":"Loco 910 Egg Vorarlberg 6863",
    "addr:housenumber":"910",
    "addr:postcode":"6863",
    "addr:street":"Loco",
    "iso:country":"AT",
    "sg:address":"Loco 910",
    "sg:city":"Egg",
    "sg:orig_category":"Apotheken",
    "sg:phone":"+43 5512 2700",
    "sg:postcode":"6863",
    "sg:province":"Vorarlberg",
    "wof:name":"Apotheke-Columban Mag Trauner KG",
    "wof:placetype":"venue"
},
  "geometry": {"coordinates":[9.8960351944,47.4324951172],"type":"Point"}
}