{
  "type": "Feature",
  "properties": {
    "addr:full":"Wolf-Dietrich-Str 19 Salzburg Salzburg 5020",
    "addr:housenumber":"19",
    "addr:postcode":"5020",
    "addr:street":"Wolf-Dietrich-Str;Salzburg",
    "iso:country":"AT",
    "sg:address":"Wolf-Dietrich-Str 19",
    "sg:city":"Salzburg",
    "sg:orig_category":"Immobilienverwaltungen",
    "sg:phone":"+43 4366 26300930",
    "sg:postcode":"5020",
    "sg:province":"Salzburg",
    "wof:name":"Immobilienverwaltung Schobesberger Martin",
    "wof:placetype":"venue"
},
  "geometry": {"coordinates":[13.0474672318,47.8054580688],"type":"Point"}
}