{
  "type": "Feature",
  "properties": {
    "addr:full":"Dorfstr 4 Koppl Salzburg 5321",
    "addr:housenumber":"4",
    "addr:postcode":"5321",
    "addr:street":"Dorfstr;Salzburg",
    "iso:country":"AT",
    "sg:address":"Dorfstr 4",
    "sg:city":"Koppl",
    "sg:orig_category":"Zimmereien",
    "sg:phone":"+43 6221 7845",
    "sg:postcode":"5321",
    "sg:province":"Salzburg",
    "wof:name":"Zimmerei Pichler Walter",
    "wof:placetype":"venue"
},
  "geometry": {"coordinates":[13.1569814682,47.8078193665],"type":"Point"}
}