{
  "type": "Feature",
  "properties": {
    "addr:full":"Mariatroster Str 26 Kroisbach Steiermark 8043",
    "addr:housenumber":"26",
    "addr:postcode":"8043",
    "addr:street":"Str",
    "iso:country":"AT",
    "sg:address":"Mariatroster Str 26",
    "sg:city":"Kroisbach",
    "sg:orig_category":"Videotheken",
    "sg:phone":"+43 4331 6326118",
    "sg:postcode":"8043",
    "sg:province":"Steiermark",
    "wof:name":"Austria Video Ring",
    "wof:placetype":"venue"
},
  "geometry": {"coordinates":[15.4587240219,47.0890159607],"type":"Point"}
}