{
  "type": "Feature",
  "properties": {
    "iso:country":"AT",
    "sg:address":"Salzburger Str 7-9",
    "sg:city":"Gallspach",
    "sg:classifiers":[
        {
            "category":"Professional",
            "subcategory":"Computer Services",
            "type":"Services"
        }
    ],
    "sg:phone":"+43 7248 61833",
    "sg:postcode":"4713",
    "sg:province":"Ober\u00f6sterreich",
    "sg:tags":[
        "software"
    ],
    "wof:name":"EDV-Systeme Ecker Gerhard",
    "wof:placetype":"venue"
},
  "geometry": {"coordinates":[13.8083200455,48.2056083679],"type":"Point"}
}