{
  "type": "Feature",
  "properties": {
    "addr:full":"Untertal 1 St. Katharein an der Laming Steiermark 8611",
    "addr:housenumber":"1",
    "addr:postcode":"8611",
    "addr:street":"Untertal",
    "iso:country":"AT",
    "sg:address":"Untertal 1",
    "sg:city":"St. Katharein an der Laming",
    "sg:classifiers":[
        {
            "category":"Home & Garden",
            "subcategory":"Building Materials",
            "type":"Retail Goods"
        }
    ],
    "sg:phone":"+43 3869 2291",
    "sg:postcode":"8611",
    "sg:province":"Steiermark",
    "sg:tags":[
        "steel",
        "balcony"
    ],
    "wof:name":"Johann Loidolt",
    "wof:placetype":"venue"
},
  "geometry": {"coordinates":[15.1736001968,47.4659042358],"type":"Point"}
}