{
  "type": "Feature",
  "properties": {
    "addr:full":"Ehrenbrunng 41 Schwechat Nieder\u00f6sterreich 2320",
    "addr:housenumber":"41",
    "addr:postcode":"2320",
    "addr:street":"Ehrenbrunng;Niederoesterreich",
    "iso:country":"AT",
    "sg:address":"Ehrenbrunng 41",
    "sg:city":"Schwechat",
    "sg:orig_category":"Massagen",
    "sg:phone":"+43 1 7079127",
    "sg:postcode":"2320",
    "sg:province":"Nieder\u00f6sterreich",
    "sg:website":"massageschandl.at",
    "wof:name":"Schandl Peter",
    "wof:placetype":"venue"
},
  "geometry": {"coordinates":[16.476234436,48.1368370056],"type":"Point"}
}