{
  "type": "Feature",
  "properties": {
    "iso:country":"AT",
    "sg:address":"Unterer Stadtpl 32",
    "sg:city":"Waidhofen an der Ybbs",
    "sg:orig_category":"Immobilienverwaltungen",
    "sg:phone":"+43 4374 42529480",
    "sg:postcode":"3340",
    "sg:province":"Nieder\u00f6sterreich",
    "wof:name":"F & H Lindner Immobilien GesmbH",
    "wof:placetype":"venue"
},
  "geometry": {"coordinates":[14.773276329,47.9598846436],"type":"Point"}
}