{
  "type": "Feature",
  "properties": {
    "iso:country":"AT",
    "sg:address":"Salzburger Str 7",
    "sg:city":"Haid",
    "sg:orig_category":"Sonnenstudios",
    "sg:phone":"+43 7229 80657",
    "sg:postcode":"4053",
    "sg:province":"Ober\u00f6sterreich",
    "sg:website":"www.power-sun.at",
    "wof:name":"Power Sun Sonnen- & Nagelstudio",
    "wof:placetype":"venue"
},
  "geometry": {"coordinates":[14.2493152618,48.2046203613],"type":"Point"}
}