{
  "type": "Feature",
  "properties": {
    "iso:country":"AT",
    "sg:address":"Reichental 200",
    "sg:city":"Miesenbach",
    "sg:classifiers":[
        {
            "category":"Manufacturing",
            "subcategory":"Wood Products",
            "type":"Manufacturing & Wholesale Goods"
        }
    ],
    "sg:phone":"+43 2632 72574",
    "sg:postcode":"2761",
    "sg:province":"Nieder\u00f6sterreich",
    "sg:tags":[
        "high-quality",
        "board",
        "veneered"
    ],
    "wof:name":"Josef Neumann GesmbH",
    "wof:placetype":"venue"
},
  "geometry": {"coordinates":[16.0047702789,47.8776702881],"type":"Point"}
}