{
  "type": "Feature",
  "properties": {
    "addr:full":"Mollardgasse 85a/2 Wien Wien 1060",
    "addr:housenumber":"85a / 2",
    "addr:postcode":"1060",
    "addr:street":"Mollardgasse",
    "iso:country":"AT",
    "sg:address":"Mollardgasse 85a/2",
    "sg:city":"Wien",
    "sg:classifiers":[
        {
            "category":"Home & Garden",
            "subcategory":"Furniture",
            "type":"Retail Goods"
        }
    ],
    "sg:phone":"+43 1 5971789",
    "sg:postcode":"1060",
    "sg:province":"Wien",
    "sg:tags":[
        "bathroom"
    ],
    "wof:name":"Helmut Klar",
    "wof:placetype":"venue"
},
  "geometry": {"coordinates":[16.3434238434,48.1895751953],"type":"Point"}
}