{
  "type": "Feature",
  "properties": {
    "addr:full":"Malborghetgasse 33/32 Wien Wien 1100",
    "addr:housenumber":"33 / 32",
    "addr:postcode":"1100",
    "addr:street":"Malborghetgasse",
    "iso:country":"AT",
    "sg:address":"Malborghetgasse 33/32",
    "sg:city":"Wien",
    "sg:classifiers":[
        {
            "category":"Retail",
            "subcategory":"Auto Rental",
            "type":"Services"
        }
    ],
    "sg:phone":"+43 664 2014090",
    "sg:postcode":"1100",
    "sg:province":"Wien",
    "sg:tags":[
        "car",
        "transport"
    ],
    "wof:name":"Rudolf Hess Gesellschaft m.b.H.",
    "wof:placetype":"venue"
},
  "geometry": {"coordinates":[16.3592414856,48.1698493958],"type":"Point"}
}