{
  "type": "Feature",
  "properties": {
    "addr:full":"Schweglerstr. 17  Wien Wien 1150",
    "addr:housenumber":"17",
    "addr:postcode":"1150",
    "addr:street":"Schweglerstr.",
    "iso:country":"AT",
    "sg:address":"Schweglerstr. 17 ",
    "sg:city":"Wien",
    "sg:classifiers":[
        {
            "category":"Manufacturing",
            "subcategory":"Glass & Minerals",
            "type":"Manufacturing & Wholesale Goods"
        }
    ],
    "sg:phone":"+43 4319 8210900",
    "sg:postcode":"1150",
    "sg:province":"Wien",
    "wof:name":"LACHMAIR SPIEGEL & GLAS GES.MBH",
    "wof:placetype":"venue"
},
  "geometry": {"coordinates":[16.328458786,48.1976585388],"type":"Point"}
}