{
  "type": "Feature",
  "properties": {
    "addr:full":"Voidersdorf 55 Unternberg Salzburg 5585",
    "addr:housenumber":"55",
    "addr:postcode":"5585",
    "addr:street":"Voidersdorf;Salzburg",
    "iso:country":"AT",
    "sg:address":"Voidersdorf 55",
    "sg:city":"Unternberg",
    "sg:orig_category":"Transportunternehmen",
    "sg:phone":"+43 4364 7462010",
    "sg:postcode":"5585",
    "sg:province":"Salzburg",
    "wof:name":"Gruber Josef Internationale Transporte GesmbH & Co",
    "wof:placetype":"venue"
},
  "geometry": {"coordinates":[13.7212667465,47.1050720215],"type":"Point"}
}