{
  "type": "Feature",
  "properties": {
    "addr:full":"Pradler Saggen 9 Innsbruck Tirol 6020",
    "addr:housenumber":"9",
    "addr:postcode":"6020",
    "addr:street":"Pradler Saggen;Tirol",
    "iso:country":"AT",
    "sg:address":"Pradler Saggen 9",
    "sg:city":"Innsbruck",
    "sg:orig_category":"Maler, Anstreicher U Lackierer",
    "sg:phone":"+43 4366 43375230",
    "sg:postcode":"6020",
    "sg:province":"Tirol",
    "wof:name":"P\u00f6hli Malerei KEG",
    "wof:placetype":"venue"
},
  "geometry": {"coordinates":[11.4141139984,47.2736625671],"type":"Point"}
}