{
  "type": "Feature",
  "properties": {
    "iso:country":"AT",
    "sg:address":"Rudolfstr 6",
    "sg:city":"Linz",
    "sg:orig_category":"Werbeagenturen, Werbegrafik- U Grafik-Design",
    "sg:phone":"+43 676 4381600",
    "sg:postcode":"4040",
    "sg:province":"Ober\u00f6sterreich",
    "wof:name":"creative-inspiration horvath/hemmelmayr oeg",
    "wof:placetype":"venue"
},
  "geometry": {"coordinates":[14.2819290161,48.3111801147],"type":"Point"}
}