{
  "type": "Feature",
  "properties": {
    "iso:country":"AT",
    "sg:address":"Jasminstr 6",
    "sg:city":"Wels",
    "sg:orig_category":"Autoreparatur",
    "sg:phone":"+43 4372 42441290",
    "sg:postcode":"4600",
    "sg:province":"Ober\u00f6sterreich",
    "wof:name":"Autohaus Wurnig GmbH & Co KG",
    "wof:placetype":"venue"
},
  "geometry": {"coordinates":[13.9693183899,48.1418113708],"type":"Point"}
}