{
  "type": "Feature",
  "properties": {
    "addr:full":"Hauptstr 79 Frankenmarkt Ober\u00f6sterreich 4890",
    "addr:housenumber":"79",
    "addr:postcode":"4890",
    "addr:street":"Hauptstr;Oberoesterreich",
    "iso:country":"AT",
    "sg:address":"Hauptstr 79",
    "sg:city":"Frankenmarkt",
    "sg:orig_category":"Spenglereien",
    "sg:phone":"+43 76846293",
    "sg:postcode":"4890",
    "sg:province":"Ober\u00f6sterreich",
    "wof:name":"Bachinger Dach GesmbH & Co KG",
    "wof:placetype":"venue"
},
  "geometry": {"coordinates":[13.4187803268,47.9853401184],"type":"Point"}
}