{
  "type": "Feature",
  "properties": {
    "addr:full":"Bremschlstrasse 8 Bludenz Vorarlberg 6700",
    "addr:housenumber":"8",
    "addr:postcode":"6700",
    "addr:street":"Bremschlstrasse",
    "iso:country":"AT",
    "sg:address":"Bremschlstrasse 8",
    "sg:city":"Bludenz",
    "sg:classifiers":[
        {
            "category":"Home & Garden",
            "subcategory":"Home Furnishings",
            "type":"Retail Goods"
        }
    ],
    "sg:phone":"+43 5552 632050",
    "sg:postcode":"6700",
    "sg:province":"Vorarlberg",
    "sg:tags":[
        "decorative",
        "panel"
    ],
    "sg:website":"tschabrun.at",
    "wof:name":"Hermann Tschabrun Ges.m.b.H.",
    "wof:placetype":"venue"
},
  "geometry": {"coordinates":[9.8163528442,47.1504898071],"type":"Point"}
}