{
  "type": "Feature",
  "properties": {
    "iso:country":"AT",
    "sg:address":"Chvostekg 12",
    "sg:city":"Wien",
    "sg:orig_category":"Botendienste",
    "sg:phone":"+43 4366 48493237",
    "sg:postcode":"1220",
    "sg:province":"Wien",
    "wof:name":"Das Boten-Team",
    "wof:placetype":"venue"
},
  "geometry": {"coordinates":[16.4831180573,48.2816581726],"type":"Point"}
}