{
  "type": "Feature",
  "properties": {
    "addr:full":"Im Langfeld 8a Wildon Steiermark 8410",
    "addr:housenumber":"8a",
    "addr:postcode":"8410",
    "addr:street":"Im Langfeld;Steiermark",
    "iso:country":"AT",
    "sg:address":"Im Langfeld 8a",
    "sg:city":"Wildon",
    "sg:orig_category":"Sonnenschutzanlagen",
    "sg:phone":"+43 4366 42016236",
    "sg:postcode":"8410",
    "sg:province":"Steiermark",
    "wof:name":"Hofer Siegmund",
    "wof:placetype":"venue"
},
  "geometry": {"coordinates":[15.5221500397,46.8898658752],"type":"Point"}
}