{
  "type": "Feature",
  "properties": {
    "iso:country":"AT",
    "sg:address":"Stelzhamerstr 1A",
    "sg:city":"Steyr",
    "sg:orig_category":"Personalbereitstellung",
    "sg:phone":"+43 7252 44420",
    "sg:postcode":"4400",
    "sg:province":"Ober\u00f6sterreich",
    "wof:name":"Connect S & R GmbH - Mensch & Arbeit",
    "wof:placetype":"venue"
},
  "geometry": {"coordinates":[14.4115829468,48.0366363525],"type":"Point"}
}