{
  "type": "Feature",
  "properties": {
    "addr:full":"Br\u00fcnnlbadg 17/2a Wien Wien 1090",
    "addr:housenumber":"17 / 2a",
    "addr:postcode":"1090",
    "addr:street":"Bruennlbadg",
    "iso:country":"AT",
    "sg:address":"Br\u00fcnnlbadg 17/2a",
    "sg:city":"Wien",
    "sg:orig_category":"Datenverarbeitung",
    "sg:phone":"+43 1 4035158",
    "sg:postcode":"1090",
    "sg:province":"Wien",
    "wof:name":"\u00d6sterreichische Bibliothekenverbund und Service Ges.m.b.H.",
    "wof:placetype":"venue"
},
  "geometry": {"coordinates":[16.351474762,48.2234115601],"type":"Point"}
}