{
  "type": "Feature",
  "properties": {
    "iso:country":"AT",
    "sg:address":"Walgaustr 50",
    "sg:city":"Ludesch",
    "sg:orig_category":"Stuckateure U Trockenausbauer",
    "sg:phone":"+43 4355 502391",
    "sg:postcode":"6713",
    "sg:province":"Vorarlberg",
    "wof:name":"Burtscher Trockenbau-Systeme GmbH",
    "wof:placetype":"venue"
},
  "geometry": {"coordinates":[9.7775030136,47.1906471252],"type":"Point"}
}