{
  "type": "Feature",
  "properties": {
    "iso:country":"AT",
    "sg:address":"Grabensee 8",
    "sg:city":"Asperhofen",
    "sg:orig_category":"Feuerwehren",
    "sg:phone":"+43 2772 55357",
    "sg:postcode":"3041",
    "sg:province":"Nieder\u00f6sterreich",
    "wof:name":"Freiwillige Feuerwehr Grabensee",
    "wof:placetype":"venue"
},
  "geometry": {"coordinates":[15.9243936539,48.2437896729],"type":"Point"}
}