{
  "type": "Feature",
  "properties": {
    "iso:country":"AT",
    "sg:address":"Pieslwang 28",
    "sg:city":"Gr\u00fcnburg",
    "sg:classifiers":[
        {
            "category":"Home & Garden",
            "subcategory":"Building Materials",
            "type":"Retail Goods"
        }
    ],
    "sg:phone":"+43 7257 7669",
    "sg:postcode":"4594",
    "sg:province":"Ober\u00f6sterreich",
    "sg:tags":[
        "gravel",
        "crushed"
    ],
    "wof:name":"Karan Ges.m.b.H.",
    "wof:placetype":"venue"
},
  "geometry": {"coordinates":[14.2846603394,47.9814987183],"type":"Point"}
}