{
  "type": "Feature",
  "properties": {
    "addr:full":"Kesselstrasse 11 Wolfurt-Bahnhof Vorarlberg 6960",
    "addr:housenumber":"11",
    "addr:postcode":"6960",
    "addr:street":"Kesselstrasse",
    "iso:country":"AT",
    "sg:address":"Kesselstrasse 11",
    "sg:city":"Wolfurt-Bahnhof",
    "sg:classifiers":[
        {
            "category":"Building & Trades",
            "subcategory":"Plumbing",
            "type":"Services"
        }
    ],
    "sg:phone":"+43 5574 86486",
    "sg:postcode":"6960",
    "sg:province":"Vorarlberg",
    "sg:tags":[
        "supraregional",
        "gas"
    ],
    "sg:website":"lukasgmbh.at",
    "wof:name":"Ing. Lukas GmbH",
    "wof:placetype":"venue"
},
  "geometry": {"coordinates":[9.745349884,47.4537887573],"type":"Point"}
}