{
  "type": "Feature",
  "properties": {
    "addr:full":"Linke Wienzeile 64 Wien Wien 1060",
    "addr:housenumber":"64",
    "addr:postcode":"1060",
    "addr:street":"Linke Wienzeile",
    "iso:country":"AT",
    "sg:address":"Linke Wienzeile 64",
    "sg:city":"Wien",
    "sg:classifiers":[
        {
            "category":"Restaurant",
            "type":"Food & Drink"
        }
    ],
    "sg:phone":"+43 1 5863189",
    "sg:postcode":"1060",
    "sg:province":"Wien",
    "wof:name":"Freyberger Waltraud",
    "wof:placetype":"venue"
},
  "geometry": {"coordinates":[16.3563537598,48.1968231201],"type":"Point"}
}