{
  "type": "Feature",
  "properties": {
    "addr:full":"Anton Faistauer-Pl 3 Maishofen Salzburg 5751",
    "addr:housenumber":"3",
    "addr:postcode":"5751",
    "addr:street":"Salzburg",
    "iso:country":"AT",
    "sg:address":"Anton Faistauer-Pl 3",
    "sg:city":"Maishofen",
    "sg:orig_category":"Bankomat-Standorte",
    "sg:phone":"+43 6542 682360",
    "sg:postcode":"5751",
    "sg:province":"Salzburg",
    "wof:name":"Bankomat d Raiffeisenbank Maishofen-Thumersbach regGenmbH",
    "wof:placetype":"venue"
},
  "geometry": {"coordinates":[12.8052387238,47.361289978],"type":"Point"}
}