{
  "type": "Feature",
  "properties": {
    "addr:full":"Kitzsteinhornstr 40 Zell am See Salzburg 5700",
    "addr:housenumber":"40",
    "addr:postcode":"5700",
    "addr:street":"Kitzsteinhornstr;Salzburg",
    "iso:country":"AT",
    "sg:address":"Kitzsteinhornstr 40",
    "sg:city":"Zell am See",
    "sg:orig_category":"Friseure U Frisiersalons",
    "sg:phone":"+43 4365 4253153",
    "sg:postcode":"5700",
    "sg:province":"Salzburg",
    "wof:name":"Haarlekin Hair-Design",
    "wof:placetype":"venue"
},
  "geometry": {"coordinates":[12.7951087952,47.2980575562],"type":"Point"}
}