{
  "type": "Feature",
  "properties": {
    "addr:full":"Burgenlandstr 7 F\u00fcrstenfeld Steiermark 8280",
    "addr:housenumber":"7",
    "addr:postcode":"8280",
    "addr:street":"Burgenlandstr",
    "iso:country":"AT",
    "sg:address":"Burgenlandstr 7",
    "sg:city":"F\u00fcrstenfeld",
    "sg:orig_category":"Handelsagenturen",
    "sg:phone":"+43 3382 52307",
    "sg:postcode":"8280",
    "sg:province":"Steiermark",
    "wof:name":"EEG Handels GmbH & Co KG",
    "wof:placetype":"venue"
},
  "geometry": {"coordinates":[16.0818004608,47.0485153198],"type":"Point"}
}