{
  "type": "Feature",
  "properties": {
    "addr:full":"Hallerg 8-12 Wien Wien 1110",
    "addr:housenumber":"8-12",
    "addr:postcode":"1110",
    "iso:country":"AT",
    "sg:address":"Hallerg 8-12",
    "sg:city":"Wien",
    "sg:orig_category":"Autoreparatur",
    "sg:phone":"+43 4317 496263",
    "sg:postcode":"1110",
    "sg:province":"Wien",
    "sg:website":"loeschenbrand.at",
    "wof:name":"L\u00f6schenbrand Alfred GesmbH",
    "wof:placetype":"venue"
},
  "geometry": {"coordinates":[16.420042038,48.1806488037],"type":"Point"}
}