{
  "type": "Feature",
  "properties": {
    "addr:full":"Burgwallstr 15 Leonding Ober\u00f6sterreich 4060",
    "addr:housenumber":"15",
    "addr:postcode":"4060",
    "addr:street":"Burgwallstr",
    "iso:country":"AT",
    "sg:address":"Burgwallstr 15",
    "sg:city":"Leonding",
    "sg:orig_category":"Blitzableiter U Blitzschutzanlagen",
    "sg:phone":"+43 732 670131",
    "sg:postcode":"4060",
    "sg:province":"Ober\u00f6sterreich",
    "wof:name":"Aufischer Hans",
    "wof:placetype":"venue"
},
  "geometry": {"coordinates":[14.2201900482,48.2833213806],"type":"Point"}
}