{
  "type": "Feature",
  "properties": {
    "addr:full":"G\u00e4rtnerg 3 Ebenthal Nieder\u00f6sterreich 2251",
    "addr:housenumber":"3",
    "addr:postcode":"2251",
    "addr:street":"Gaertnerg",
    "iso:country":"AT",
    "sg:address":"G\u00e4rtnerg 3",
    "sg:city":"Ebenthal",
    "sg:orig_category":"Gutsverwaltungen",
    "sg:phone":"+43 2538 853540",
    "sg:postcode":"2251",
    "sg:province":"Nieder\u00f6sterreich",
    "wof:name":"Lukits Hans Ing",
    "wof:placetype":"venue"
},
  "geometry": {"coordinates":[16.7934150696,48.437374115],"type":"Point"}
}