{
  "type": "Feature",
  "properties": {
    "addr:full":"Eferdinger Str 79 Wels Ober\u00f6sterreich 4600",
    "addr:housenumber":"79",
    "addr:postcode":"4600",
    "addr:street":"Str;Oberoesterreich",
    "iso:country":"AT",
    "sg:address":"Eferdinger Str 79",
    "sg:city":"Wels",
    "sg:orig_category":"Restaurants: Amerikanisch",
    "sg:phone":"+43 7242 207015",
    "sg:postcode":"4600",
    "sg:province":"Ober\u00f6sterreich",
    "wof:name":"Burger King Restaurant",
    "wof:placetype":"venue"
},
  "geometry": {"coordinates":[14.027929306,48.1807899475],"type":"Point"}
}