{
  "type": "Feature",
  "properties": {
    "iso:country":"AT",
    "sg:address":"Obkircherg 35",
    "sg:city":"Wien",
    "sg:orig_category":"Lebensmittel / Einzelhandel",
    "sg:phone":"+43 1 3201234",
    "sg:postcode":"1190",
    "sg:province":"Wien",
    "wof:name":"Hofer KG",
    "wof:placetype":"venue"
},
  "geometry": {"coordinates":[16.3419895172,48.2446861267],"type":"Point"}
}