{
  "type": "Feature",
  "properties": {
    "addr:full":"Argentinierstr 35 Wien Wien 1040",
    "addr:housenumber":"35",
    "addr:postcode":"1040",
    "addr:street":"Argentinierstr",
    "iso:country":"AT",
    "sg:address":"Argentinierstr 35",
    "sg:city":"Wien",
    "sg:orig_category":"Altbausanierungen",
    "sg:phone":"+43 4315 038330",
    "sg:postcode":"1040",
    "sg:province":"Wien",
    "wof:name":"Gharabaghi Dipl-Ing Bau-u Liegenschaftsverwertungs GesmbH",
    "wof:placetype":"venue"
},
  "geometry": {"coordinates":[16.3738288879,48.1940612793],"type":"Point"}
}