{
  "type": "Feature",
  "properties": {
    "addr:full":"Nr 6 Mehrnbach Ober\u00f6sterreich 4941",
    "addr:postcode":"4941",
    "addr:street":"Nr;Mehrnbach",
    "iso:country":"AT",
    "sg:address":"Nr 6",
    "sg:city":"Mehrnbach",
    "sg:orig_category":"Volksschulen",
    "sg:phone":"+43 4377 5288955",
    "sg:postcode":"4941",
    "sg:province":"Ober\u00f6sterreich",
    "wof:name":"Volksschule",
    "wof:placetype":"venue"
},
  "geometry": {"coordinates":[13.4352054596,48.2079963684],"type":"Point"}
}