{
  "type": "Feature",
  "properties": {
    "addr:full":"Pelzg 1 Wien Wien 1150",
    "addr:housenumber":"1",
    "addr:postcode":"1150",
    "addr:street":"Pelzg",
    "iso:country":"AT",
    "sg:address":"Pelzg 1",
    "sg:city":"Wien",
    "sg:classifiers":[
        {
            "category":"Travel",
            "subcategory":"Hotels & Motels",
            "type":"Entertainment"
        }
    ],
    "sg:phone":"+43 1 98214800",
    "sg:postcode":"1150",
    "sg:province":"Wien",
    "wof:name":"WESTBAHN HOTEL WIEN Am Europaplatz",
    "wof:placetype":"venue"
},
  "geometry": {"coordinates":[16.3363876343,48.1980056763],"type":"Point"}
}