{
  "type": "Feature",
  "properties": {
    "addr:full":"Traunsteiner Weg 2 Kitzb\u00fchel Tirol 6370",
    "addr:housenumber":"2",
    "addr:postcode":"6370",
    "addr:street":"Traunsteiner Weg;Tirol",
    "iso:country":"AT",
    "sg:address":"Traunsteiner Weg 2",
    "sg:city":"Kitzb\u00fchel",
    "sg:orig_category":"Fotoausarbeitungen",
    "sg:phone":"+43 5356 71443",
    "sg:postcode":"6370",
    "sg:province":"Tirol",
    "wof:name":"Flash-Foto Service Rauth KEG",
    "wof:placetype":"venue"
},
  "geometry": {"coordinates":[12.3943729401,47.4455337524],"type":"Point"}
}