{
  "type": "Feature",
  "properties": {
    "iso:country":"AT",
    "sg:address":"Brodschildstr 31",
    "sg:city":"Stockerau",
    "sg:orig_category":"Umweltschutz",
    "sg:phone":"+43 4322 6672656",
    "sg:postcode":"2000",
    "sg:province":"Nieder\u00f6sterreich",
    "wof:name":"Meteo Science Mursch-Radlgruber KEG",
    "wof:placetype":"venue"
},
  "geometry": {"coordinates":[16.2154407501,48.3870124817],"type":"Point"}
}