{
  "type": "Feature",
  "properties": {
    "addr:full":"Schiffsl\u00e4nde 1 Gmunden Ober\u00f6sterreich 4810",
    "addr:housenumber":"1",
    "addr:postcode":"4810",
    "addr:street":"Schiffslaende;Oberoesterreich",
    "iso:country":"AT",
    "sg:address":"Schiffsl\u00e4nde 1",
    "sg:city":"Gmunden",
    "sg:orig_category":"Zahntechnische Laboratorien",
    "sg:phone":"+43 761273150",
    "sg:postcode":"4810",
    "sg:province":"Ober\u00f6sterreich",
    "wof:name":"Riener Peter Zahntechnik GesmbH",
    "wof:placetype":"venue"
},
  "geometry": {"coordinates":[13.8027601242,47.9178466797],"type":"Point"}
}