{
  "type": "Feature",
  "properties": {
    "addr:full":"Dr.-Steger-Gasse 8 Pottenbrunn Nieder\u00f6sterreich 3140",
    "addr:housenumber":"8",
    "addr:postcode":"3140",
    "addr:street":"Dr.-Steger-Gasse;Niederoesterreich",
    "iso:country":"AT",
    "sg:address":"Dr.-Steger-Gasse 8",
    "sg:city":"Pottenbrunn",
    "sg:orig_category":"Garages, Pre-Fabricated Garages",
    "sg:phone":"+43 2742 42198",
    "sg:postcode":"3140",
    "sg:province":"Nieder\u00f6sterreich",
    "wof:name":"Ernst G\u00f6ber",
    "wof:placetype":"venue"
},
  "geometry": {"coordinates":[15.693611145,48.2381401062],"type":"Point"}
}