{
  "type": "Feature",
  "properties": {
    "addr:full":"Tuchlauben 22 Wien Wien 1010",
    "addr:housenumber":"22",
    "addr:postcode":"1010",
    "addr:street":"Tuchlauben",
    "iso:country":"AT",
    "sg:address":"Tuchlauben 22",
    "sg:city":"Wien",
    "sg:classifiers":[
        {
            "category":"Arena",
            "subcategory":"Bull Ring",
            "type":"Entertainment"
        }
    ],
    "sg:phone":"+43 1 5339237",
    "sg:postcode":"1010",
    "sg:province":"Wien",
    "sg:tags":[
        "brooch"
    ],
    "wof:name":"Kurt Deltl",
    "wof:placetype":"venue"
},
  "geometry": {"coordinates":[16.371881485,48.2110519409],"type":"Point"}
}