{
  "type": "Feature",
  "properties": {
    "addr:full":"Hauptpl 4 Ybbs an der Donau Nieder\u00f6sterreich 3370",
    "addr:housenumber":"4",
    "addr:postcode":"3370",
    "addr:street":"Hauptpl",
    "iso:country":"AT",
    "sg:address":"Hauptpl 4",
    "sg:city":"Ybbs an der Donau",
    "sg:orig_category":"Mieder U Miederwaren",
    "sg:phone":"+43 4374 1256770",
    "sg:postcode":"3370",
    "sg:province":"Nieder\u00f6sterreich",
    "wof:name":"Miederfachgesch\u00e4ft Gerti Inh B\u00f6hm KEG",
    "wof:placetype":"venue"
},
  "geometry": {"coordinates":[15.0853567123,48.1773910522],"type":"Point"}
}