{
  "type": "Feature",
  "properties": {
    "addr:full":"Waltenhofeng 8 Wien Wien 1100",
    "addr:housenumber":"8",
    "addr:postcode":"1100",
    "addr:street":"Waltenhofeng",
    "iso:country":"AT",
    "sg:address":"Waltenhofeng 8",
    "sg:city":"Wien",
    "sg:orig_category":"Fluggesellschaften",
    "sg:phone":"+43 1 6025684",
    "sg:postcode":"1100",
    "sg:province":"Wien",
    "wof:name":"Loos & Partner KEG",
    "wof:placetype":"venue"
},
  "geometry": {"coordinates":[16.3892002106,48.1688804626],"type":"Point"}
}