{
  "type": "Feature",
  "properties": {
    "iso:country":"AT",
    "sg:address":"Nr 23",
    "sg:city":"Pinkafeld",
    "sg:orig_category":"Handelsagenturen",
    "sg:phone":"+43 3359 25710",
    "sg:postcode":"7423",
    "sg:province":"Burgenland",
    "wof:name":"Hammerl Siegfried",
    "wof:placetype":"venue"
},
  "geometry": {"coordinates":[16.124250412,47.3718299866],"type":"Point"}
}