{
  "type": "Feature",
  "properties": {
    "addr:full":"Mariahilfer Str 205 Wien Wien 1150",
    "addr:housenumber":"205",
    "addr:postcode":"1150",
    "iso:country":"AT",
    "sg:address":"Mariahilfer Str 205",
    "sg:city":"Wien",
    "sg:orig_category":"Bauphysik",
    "sg:phone":"+43 4319 6171880",
    "sg:postcode":"1150",
    "sg:province":"Wien",
    "sg:website":"bs-ziviltechniker.at",
    "wof:name":"Bauphysik - DI Dr Gernot Scherpke",
    "wof:placetype":"venue"
},
  "geometry": {"coordinates":[16.328578949,48.1912879944],"type":"Point"}
}