{
  "type": "Feature",
  "properties": {
    "addr:full":"S\u00fcdliches Lazarettfeld 36 Graz Steiermark 8020",
    "addr:housenumber":"36",
    "addr:postcode":"8020",
    "addr:street":"Lazarettfeld",
    "iso:country":"AT",
    "sg:address":"S\u00fcdliches Lazarettfeld 36",
    "sg:city":"Graz",
    "sg:classifiers":[
        {
            "category":"Military Area",
            "subcategory":"Air Force Base",
            "type":"Public Place"
        }
    ],
    "sg:phone":"+43 316 273438",
    "sg:postcode":"8020",
    "sg:province":"Steiermark",
    "sg:tags":[
        "supraregional",
        "arrester",
        "installation",
        "system",
        "lightning"
    ],
    "wof:name":"Josef Prenner",
    "wof:placetype":"venue"
},
  "geometry": {"coordinates":[15.4111499786,47.0689201355],"type":"Point"}
}