{
  "type": "Feature",
  "properties": {
    "addr:full":"Josef Leeb-G 18 Maria Enzersdorf Nieder\u00f6sterreich 2344",
    "addr:housenumber":"18",
    "addr:postcode":"2344",
    "iso:country":"AT",
    "sg:address":"Josef Leeb-G 18",
    "sg:city":"Maria Enzersdorf",
    "sg:orig_category":"Handelsagenturen",
    "sg:phone":"+43 2236 24446",
    "sg:postcode":"2344",
    "sg:province":"Nieder\u00f6sterreich",
    "wof:name":"Kutschera R M GesmbH",
    "wof:placetype":"venue"
},
  "geometry": {"coordinates":[16.2803058624,48.0948829651],"type":"Point"}
}