{
  "type": "Feature",
  "properties": {
    "addr:full":"Rieglstr 31 Bad Zell Ober\u00f6sterreich 4283",
    "addr:housenumber":"31",
    "addr:postcode":"4283",
    "addr:street":"Rieglstr",
    "iso:country":"AT",
    "sg:address":"Rieglstr 31",
    "sg:city":"Bad Zell",
    "sg:classifiers":[
        {
            "category":"Professional",
            "subcategory":"Computer Services",
            "type":"Services"
        }
    ],
    "sg:phone":"+43 4366 44953116",
    "sg:postcode":"4283",
    "sg:province":"Ober\u00f6sterreich",
    "sg:tags":[
        "software"
    ],
    "wof:name":"Computer-Shop Grohmann",
    "wof:placetype":"venue"
},
  "geometry": {"coordinates":[14.661904335,48.3509178162],"type":"Point"}
}