{
  "type": "Feature",
  "properties": {
    "addr:full":"Bahnstr 6 Langenlebarn Nieder\u00f6sterreich 3425",
    "addr:housenumber":"6",
    "addr:postcode":"3425",
    "addr:street":"Bahnstr",
    "iso:country":"AT",
    "sg:address":"Bahnstr 6",
    "sg:city":"Langenlebarn",
    "sg:orig_category":"Psychotherapie",
    "sg:phone":"+43 4322 7266977",
    "sg:postcode":"3425",
    "sg:province":"Nieder\u00f6sterreich",
    "wof:name":"Hofreiter Michael Dr med Psychomatik u Psychotherapie",
    "wof:placetype":"venue"
},
  "geometry": {"coordinates":[16.1204071045,48.3318634033],"type":"Point"}
}