{
  "type": "Feature",
  "properties": {
    "addr:full":"Stadtpl 27/2 Schwanenstadt Ober\u00f6sterreich 4690",
    "addr:housenumber":"27 / 2",
    "addr:postcode":"4690",
    "addr:street":"Stadtpl",
    "iso:country":"AT",
    "sg:address":"Stadtpl 27/2",
    "sg:city":"Schwanenstadt",
    "sg:orig_category":"\u00c3\u201erzte / F Allgemeinmedizin",
    "sg:phone":"+43 767362620",
    "sg:postcode":"4690",
    "sg:province":"Ober\u00f6sterreich",
    "wof:name":"Atzelsdorfer Ulrich Dr",
    "wof:placetype":"venue"
},
  "geometry": {"coordinates":[13.7758998871,48.055770874],"type":"Point"}
}