{
  "type": "Feature",
  "properties": {
    "iso:country":"AT",
    "sg:address":"Gumpendorfer Str 68",
    "sg:city":"Wien",
    "sg:orig_category":"Textilreinigung",
    "sg:phone":"+43 1 5870770",
    "sg:postcode":"1060",
    "sg:province":"Wien",
    "wof:name":"Kleiderreinigung Rene",
    "wof:placetype":"venue"
},
  "geometry": {"coordinates":[16.3508281708,48.1952705383],"type":"Point"}
}