{
  "type": "Feature",
  "properties": {
    "addr:full":"Bruggfeldstrasse 52 Landeck Tirol 6500",
    "addr:housenumber":"52",
    "addr:postcode":"6500",
    "addr:street":"Bruggfeldstrasse;Tirol",
    "iso:country":"AT",
    "sg:address":"Bruggfeldstrasse 52",
    "sg:city":"Landeck",
    "sg:classifiers":[
        {
            "category":"Utilities",
            "subcategory":"Natural Gas",
            "type":"Services"
        }
    ],
    "sg:phone":"+43 5442 624310",
    "sg:postcode":"6500",
    "sg:province":"Tirol",
    "sg:tags":[
        "cast",
        "stone",
        "working"
    ],
    "sg:website":"nuenerofen.at",
    "wof:name":"Nikolaus Nuener Ofen- und Heizungsbau, Fliesen- und Plattenverlegung",
    "wof:placetype":"venue"
},
  "geometry": {"coordinates":[10.5555763245,47.1408729553],"type":"Point"}
}