{
  "type": "Feature",
  "properties": {
    "iso:country":"AT",
    "sg:address":"Nr 15",
    "sg:city":"St. Wolfgang im Salzkammergut",
    "sg:orig_category":"Appartements / Ferienwohnungen",
    "sg:phone":"+43 6137 6996",
    "sg:postcode":"5360",
    "sg:province":"Ober\u00f6sterreich",
    "wof:name":"Ferienhof Boabauer Fam Grabner",
    "wof:placetype":"venue"
},
  "geometry": {"coordinates":[13.4459896088,47.73985672],"type":"Point"}
}