{
  "type": "Feature",
  "properties": {
    "addr:full":"Sillufer 7 Innsbruck Tirol 6020",
    "addr:housenumber":"7",
    "addr:postcode":"6020",
    "addr:street":"Sillufer;Tirol",
    "iso:country":"AT",
    "sg:address":"Sillufer 7",
    "sg:city":"Innsbruck",
    "sg:orig_category":"Sportanlagen",
    "sg:phone":"+43 512 342287",
    "sg:postcode":"6020",
    "sg:province":"Tirol",
    "wof:name":"Tivoli Stadion",
    "wof:placetype":"venue"
},
  "geometry": {"coordinates":[11.4044065475,47.2586479187],"type":"Point"}
}