{
  "type": "Feature",
  "properties": {
    "addr:full":"Josef-Wokral-Str 16b Steyr Ober\u00f6sterreich 4400",
    "addr:housenumber":"16b",
    "addr:postcode":"4400",
    "addr:street":"Josef-Wokral-Str;Oberoesterreich",
    "iso:country":"AT",
    "sg:address":"Josef-Wokral-Str 16b",
    "sg:city":"Steyr",
    "sg:orig_category":"Psychotherapie",
    "sg:phone":"+43 650 5250034",
    "sg:postcode":"4400",
    "sg:province":"Ober\u00f6sterreich",
    "wof:name":"Reitner Maria",
    "wof:placetype":"venue"
},
  "geometry": {"coordinates":[14.4210472107,48.0348625183],"type":"Point"}
}