{
  "type": "Feature",
  "properties": {
    "iso:country":"AT",
    "sg:address":"Josef-Wokral-Str 16b",
    "sg:city":"Steyr",
    "sg:orig_category":"Psychotherapie",
    "sg:phone":"+43 650 5250034",
    "sg:postcode":"4400",
    "sg:province":"Ober\u00f6sterreich",
    "wof:name":"Reitner Maria",
    "wof:placetype":"venue"
},
  "geometry": {"coordinates":[14.4210472107,48.0348625183],"type":"Point"}
}