{
  "type": "Feature",
  "properties": {
    "iso:country":"AT",
    "sg:address":"Kulmg 3",
    "sg:city":"Wien",
    "sg:orig_category":"Schilder",
    "sg:phone":"+43 1 40867910",
    "sg:postcode":"1160",
    "sg:province":"Wien",
    "wof:name":"Kelis OHG",
    "wof:placetype":"venue"
},
  "geometry": {"coordinates":[16.3212051392,48.215473175],"type":"Point"}
}