{
  "type": "Feature",
  "properties": {
    "addr:full":"Wagendorf 51 St. Veit am Vogau Steiermark 8423",
    "addr:housenumber":"51",
    "addr:postcode":"8423",
    "addr:street":"Wagendorf",
    "iso:country":"AT",
    "sg:address":"Wagendorf 51",
    "sg:city":"St. Veit am Vogau",
    "sg:orig_category":"Landwirtschaftliche Produkte",
    "sg:phone":"+43 4334 5326970",
    "sg:postcode":"8423",
    "sg:province":"Steiermark",
    "wof:name":"Lober Karl & Annemarie Lober GesnbR",
    "wof:placetype":"venue"
},
  "geometry": {"coordinates":[15.6051454544,46.7559776306],"type":"Point"}
}