{
  "type": "Feature",
  "properties": {
    "addr:full":"Meldemannstr 12-14 Wien Wien 1200",
    "addr:postcode":"12-14;1200",
    "iso:country":"AT",
    "sg:address":"Meldemannstr 12-14",
    "sg:city":"Wien",
    "sg:classifiers":[
        {
            "category":"Professional",
            "subcategory":"Computer Services",
            "type":"Services"
        }
    ],
    "sg:phone":"+43 4322 3352592",
    "sg:postcode":"1200",
    "sg:province":"Wien",
    "sg:tags":[
        "software"
    ],
    "wof:name":"Systemhaus Ing G\u00fcnter Predl",
    "wof:placetype":"venue"
},
  "geometry": {"coordinates":[16.3765392303,48.2408676147],"type":"Point"}
}