{
  "type": "Feature",
  "properties": {
    "addr:full":"Gablenzg 17 Wien Wien 1150",
    "addr:housenumber":"17",
    "addr:postcode":"1150",
    "addr:street":"Gablenzg",
    "iso:country":"AT",
    "sg:address":"Gablenzg 17",
    "sg:city":"Wien",
    "sg:orig_category":"Blumeneinzelhandel",
    "sg:phone":"+43 1 9831910",
    "sg:postcode":"1150",
    "sg:province":"Wien",
    "wof:name":"Dugaschl Silvia",
    "wof:placetype":"venue"
},
  "geometry": {"coordinates":[16.3307723999,48.2044181824],"type":"Point"}
}