{
  "type": "Feature",
  "properties": {
    "addr:full":"Prenterweg 9  Andritz Steiermark 8045",
    "addr:housenumber":"9",
    "addr:postcode":"8045",
    "addr:street":"Prenterweg",
    "iso:country":"AT",
    "sg:address":"Prenterweg 9 ",
    "sg:city":"Andritz",
    "sg:classifiers":[
        {
            "category":"Manufacturing",
            "subcategory":"Printing",
            "type":"Manufacturing & Wholesale Goods"
        }
    ],
    "sg:phone":"+43 4331 3246600",
    "sg:postcode":"8045",
    "sg:province":"Steiermark",
    "sg:tags":[
        "publishing"
    ],
    "wof:name":"FACHMEDIEN VERLAG GMBH",
    "wof:placetype":"venue"
},
  "geometry": {"coordinates":[15.4759988785,47.1443214417],"type":"Point"}
}