{
  "type": "Feature",
  "properties": {
    "addr:full":"Fischmarkt 15 Taiskirchen im Innkreis Ober\u00f6sterreich 4753",
    "addr:housenumber":"15",
    "addr:postcode":"4753",
    "addr:street":"Fischmarkt;Oberoesterreich",
    "iso:country":"AT",
    "sg:address":"Fischmarkt 15",
    "sg:city":"Taiskirchen im Innkreis",
    "sg:orig_category":"Bestattungsunternehmen",
    "sg:phone":"+43 4377 648533",
    "sg:postcode":"4753",
    "sg:province":"Ober\u00f6sterreich",
    "wof:name":"Feichtner Friedrich",
    "wof:placetype":"venue"
},
  "geometry": {"coordinates":[13.5696496964,48.2614860535],"type":"Point"}
}