{
  "type": "Feature",
  "properties": {
    "addr:full":"Nordbahnstr 34 Wien Wien 1020",
    "addr:housenumber":"34",
    "addr:postcode":"1020",
    "addr:street":"Nordbahnstr",
    "iso:country":"AT",
    "sg:address":"Nordbahnstr 34",
    "sg:city":"Wien",
    "sg:orig_category":"Friseure U Frisiersalons",
    "sg:phone":"+43 1 2169725",
    "sg:postcode":"1020",
    "sg:province":"Wien",
    "wof:name":"Salon Christa Inh Christa Kopacs",
    "wof:placetype":"venue"
},
  "geometry": {"coordinates":[16.3891487122,48.2231826782],"type":"Point"}
}