{
  "type": "Feature",
  "properties": {
    "iso:country":"AT",
    "sg:address":"Oberer Markt 17",
    "sg:city":"Kefermarkt",
    "sg:orig_category":"Banken U Sparkassen",
    "sg:phone":"+43 7947 62620",
    "sg:postcode":"4292",
    "sg:province":"Ober\u00f6sterreich",
    "wof:name":"Raiffeisenkasse Kefermarkt regGenmbH",
    "wof:placetype":"venue"
},
  "geometry": {"coordinates":[14.5381698608,48.4426956177],"type":"Point"}
}