{
  "type": "Feature",
  "properties": {
    "addr:full":"Oberer Markt 17 Kefermarkt Ober\u00f6sterreich 4292",
    "addr:housenumber":"17",
    "addr:postcode":"4292",
    "addr:street":"Oberer Markt",
    "iso:country":"AT",
    "sg:address":"Oberer Markt 17",
    "sg:city":"Kefermarkt",
    "sg:orig_category":"Banken U Sparkassen",
    "sg:phone":"+43 7947 62620",
    "sg:postcode":"4292",
    "sg:province":"Ober\u00f6sterreich",
    "wof:name":"Raiffeisenkasse Kefermarkt regGenmbH",
    "wof:placetype":"venue"
},
  "geometry": {"coordinates":[14.5381698608,48.4426956177],"type":"Point"}
}