{
  "type": "Feature",
  "properties": {
    "addr:full":"Obermarkt 5 Reutte Tirol 6600",
    "addr:housenumber":"5",
    "addr:postcode":"6600",
    "addr:street":"Obermarkt;Tirol",
    "iso:country":"AT",
    "sg:address":"Obermarkt 5",
    "sg:city":"Reutte",
    "sg:orig_category":"Gesundheit / Allgemeine Informationsstellen",
    "sg:phone":"+43 5672 69965752",
    "sg:postcode":"6600",
    "sg:province":"Tirol",
    "wof:name":"Gesundheitsamt d Bezirkshauptmannschaft Reutte",
    "wof:placetype":"venue"
},
  "geometry": {"coordinates":[10.7187242508,47.489025116],"type":"Point"}
}