{
  "type": "Feature",
  "properties": {
    "addr:full":"Rennweg 120 Wien Wien 1030",
    "addr:housenumber":"120",
    "addr:postcode":"1030",
    "addr:street":"Rennweg",
    "iso:country":"AT",
    "sg:address":"Rennweg 120",
    "sg:city":"Wien",
    "sg:orig_category":"Autohandel",
    "sg:phone":"+43 1 795430",
    "sg:postcode":"1030",
    "sg:province":"Wien",
    "wof:name":"Opel Kandl Bernhard Autohandel-GesmbH",
    "wof:placetype":"venue"
},
  "geometry": {"coordinates":[16.4032688141,48.1855697632],"type":"Point"}
}