{
  "type": "Feature",
  "properties": {
    "iso:country":"AT",
    "sg:address":"Arthur-Krupp-Str 1",
    "sg:city":"Amstetten",
    "sg:orig_category":"Autohandel",
    "sg:phone":"+43 7472 63060",
    "sg:postcode":"3300",
    "sg:province":"Nieder\u00f6sterreich",
    "wof:name":"Auto B\u00f6rse H Breiteneder",
    "wof:placetype":"venue"
},
  "geometry": {"coordinates":[14.8950948715,48.1190376282],"type":"Point"}
}