{
  "type": "Feature",
  "properties": {
    "addr:full":"Resthofstr 29 Steyr Ober\u00f6sterreich 4400",
    "addr:housenumber":"29",
    "addr:postcode":"4400",
    "addr:street":"Resthofstr;Oberoesterreich",
    "iso:country":"AT",
    "sg:address":"Resthofstr 29",
    "sg:city":"Steyr",
    "sg:classifiers":[
        {
            "category":"Taxi",
            "type":"Transportation"
        }
    ],
    "sg:phone":"+43 7252 80555",
    "sg:postcode":"4400",
    "sg:province":"Ober\u00f6sterreich",
    "sg:tags":[
        "personentransporte",
        "u"
    ],
    "wof:name":"Taxi Auinger",
    "wof:placetype":"venue"
},
  "geometry": {"coordinates":[14.4235906601,48.0585098267],"type":"Point"}
}