{
  "type": "Feature",
  "properties": {
    "iso:country":"AT",
    "sg:address":"Waldrasterstr 3",
    "sg:city":"Fulpmes",
    "sg:orig_category":"Textilwaren / Einzelhandel",
    "sg:phone":"+43 5225 62360",
    "sg:postcode":"6166",
    "sg:province":"Tirol",
    "wof:name":"Troger Karl",
    "wof:placetype":"venue"
},
  "geometry": {"coordinates":[11.3488836288,47.1522827148],"type":"Point"}
}