{
  "type": "Feature",
  "properties": {
    "addr:full":"Viktor Kaplan Strasse 9 Gerasdorf Nieder\u00f6sterreich 2201",
    "addr:housenumber":"9",
    "addr:postcode":"2201",
    "addr:street":"Viktor Kaplan Strasse",
    "iso:country":"AT",
    "sg:address":"Viktor Kaplan Strasse 9",
    "sg:city":"Gerasdorf",
    "sg:classifiers":[
        {
            "category":"Banks & Credit Unions",
            "subcategory":"Bureau De Change",
            "type":"Services"
        }
    ],
    "sg:phone":"+43 1 80435730",
    "sg:postcode":"2201",
    "sg:province":"Nieder\u00f6sterreich",
    "sg:tags":[
        "cash",
        "block"
    ],
    "sg:website":"omega-druck.at",
    "wof:name":"Omega Druck Ges.m.b.H.",
    "wof:placetype":"venue"
},
  "geometry": {"coordinates":[16.4797687531,48.2789077759],"type":"Point"}
}