{
  "type": "Feature",
  "properties": {
    "addr:full":"Leobendorfer Str 48/1 Korneuburg Nieder\u00f6sterreich 2100",
    "addr:housenumber":"48 / 1",
    "addr:postcode":"2100",
    "addr:street":"Str;Niederoesterreich",
    "iso:country":"AT",
    "sg:address":"Leobendorfer Str 48/1",
    "sg:city":"Korneuburg",
    "sg:orig_category":"Futtermittel",
    "sg:phone":"+43 2262 71946",
    "sg:postcode":"2100",
    "sg:province":"Nieder\u00f6sterreich",
    "wof:name":"Femb\u00f6ck Leopold - Tiernahrungsvertrieb",
    "wof:placetype":"venue"
},
  "geometry": {"coordinates":[16.3297843933,48.359462738],"type":"Point"}
}