{
  "type": "Feature",
  "properties": {
    "addr:full":"Hintere Ortsstr 23 Himberg Nieder\u00f6sterreich 2325",
    "addr:housenumber":"23",
    "addr:postcode":"2325",
    "addr:street":"Hintere Ortsstr",
    "iso:country":"AT",
    "sg:address":"Hintere Ortsstr 23",
    "sg:city":"Himberg",
    "sg:orig_category":"Tischlereien",
    "sg:phone":"+43 699 11019362",
    "sg:postcode":"2325",
    "sg:province":"Nieder\u00f6sterreich",
    "wof:name":"Pascher Erich Ing",
    "wof:placetype":"venue"
},
  "geometry": {"coordinates":[16.4410114288,48.0849838257],"type":"Point"}
}