{
  "type": "Feature",
  "properties": {
    "addr:full":"Salzburger Strasse 175 Wels Ober\u00f6sterreich 4600",
    "addr:housenumber":"175",
    "addr:postcode":"4600",
    "addr:street":"Salzburger Strasse;Oberoesterreich",
    "iso:country":"AT",
    "sg:address":"Salzburger Strasse 175",
    "sg:city":"Wels",
    "sg:classifiers":[
        {
            "category":"Home & Garden",
            "subcategory":"Carpets & Floor Coverings",
            "type":"Retail Goods"
        }
    ],
    "sg:phone":"+43 7242 42010",
    "sg:postcode":"4600",
    "sg:province":"Ober\u00f6sterreich",
    "sg:tags":[
        "grout",
        "adhesive",
        "tiles"
    ],
    "wof:name":"Fliesen Stuhl GmbH",
    "wof:placetype":"venue"
},
  "geometry": {"coordinates":[13.9885921478,48.152973175],"type":"Point"}
}