{
  "type": "Feature",
  "properties": {
    "iso:country":"AT",
    "sg:address":"Haiderm\u00fchle 12",
    "sg:city":"Mondsee",
    "sg:orig_category":"Feuerwerksartikel U Feuerwerke",
    "sg:phone":"+43 6232 6201",
    "sg:postcode":"5310",
    "sg:province":"Ober\u00f6sterreich",
    "wof:name":"Pyrotechnik Peter Heigl",
    "wof:placetype":"venue"
},
  "geometry": {"coordinates":[13.349562645,47.855255127],"type":"Point"}
}