{
  "type": "Feature",
  "properties": {
    "addr:full":"Feldkirchner Str 31 Klagenfurt K\u00e4rnten 9020",
    "addr:housenumber":"31",
    "addr:postcode":"9020",
    "addr:street":"Str;Kaernten",
    "iso:country":"AT",
    "sg:address":"Feldkirchner Str 31",
    "sg:city":"Klagenfurt",
    "sg:orig_category":"Galerien",
    "sg:phone":"+43 463 598060",
    "sg:postcode":"9020",
    "sg:province":"K\u00e4rnten",
    "wof:name":"BV - Galerie",
    "wof:placetype":"venue"
},
  "geometry": {"coordinates":[14.3010187149,46.6314582825],"type":"Point"}
}