{
  "type": "Feature",
  "properties": {
    "addr:full":"Badhaus 129 Sulzberg Vorarlberg 6934",
    "addr:housenumber":"129",
    "addr:postcode":"6934",
    "addr:street":"Badhaus",
    "iso:country":"AT",
    "sg:address":"Badhaus 129",
    "sg:city":"Sulzberg",
    "sg:orig_category":"Appartements / Ferienwohnungen",
    "sg:phone":"+43 5516 2127",
    "sg:postcode":"6934",
    "sg:province":"Vorarlberg",
    "wof:name":"Haus Bereuter",
    "wof:placetype":"venue"
},
  "geometry": {"coordinates":[9.9118070602,47.5233802795],"type":"Point"}
}