{
  "type": "Feature",
  "properties": {
    "addr:full":"Arbeiterheimstr 25 Steyrerm\u00fchl Ober\u00f6sterreich 4662",
    "addr:housenumber":"25",
    "addr:postcode":"4662",
    "addr:street":"Arbeiterheimstr;Oberoesterreich",
    "iso:country":"AT",
    "sg:address":"Arbeiterheimstr 25",
    "sg:city":"Steyrerm\u00fchl",
    "sg:orig_category":"Psychologen",
    "sg:phone":"+43 4369 910507786",
    "sg:postcode":"4662",
    "sg:province":"Ober\u00f6sterreich",
    "wof:name":"Hutter Doris Mag",
    "wof:placetype":"venue"
},
  "geometry": {"coordinates":[13.8080739975,47.9916877747],"type":"Point"}
}