{
  "type": "Feature",
  "properties": {
    "iso:country":"AT",
    "sg:address":"Nr 32",
    "sg:city":"K\u00fchnsdorf",
    "sg:orig_category":"Friseure U Frisiersalons",
    "sg:phone":"+43 4232 89280",
    "sg:postcode":"9125",
    "sg:province":"K\u00e4rnten",
    "wof:name":"Fris\u00f6rsalon Creative",
    "wof:placetype":"venue"
},
  "geometry": {"coordinates":[14.615480423,46.6188812256],"type":"Point"}
}