{
  "type": "Feature",
  "properties": {
    "addr:full":"Seestr 10 Faak am See K\u00e4rnten 9583",
    "addr:housenumber":"10",
    "addr:postcode":"9583",
    "addr:street":"Seestr;Kaernten",
    "iso:country":"AT",
    "sg:address":"Seestr 10",
    "sg:city":"Faak am See",
    "sg:orig_category":"Sportschulen",
    "sg:phone":"+43 4254 2265",
    "sg:postcode":"9583",
    "sg:province":"K\u00e4rnten",
    "wof:name":"Gugganig GmbH",
    "wof:placetype":"venue"
},
  "geometry": {"coordinates":[13.9147100449,46.5641593933],"type":"Point"}
}