{
  "type": "Feature",
  "properties": {
    "addr:full":"Mittlere Hauptstrasse 39 Nickelsdorf Burgenland 2425",
    "addr:housenumber":"39",
    "addr:postcode":"2425",
    "addr:street":"Mittlere Hauptstrasse",
    "iso:country":"AT",
    "sg:address":"Mittlere Hauptstrasse 39",
    "sg:city":"Nickelsdorf",
    "sg:classifiers":[
        {
            "category":"Home & Garden",
            "subcategory":"Building Materials",
            "type":"Retail Goods"
        }
    ],
    "sg:phone":"+43 2146 23170",
    "sg:postcode":"2425",
    "sg:province":"Burgenland",
    "sg:tags":[
        "installation",
        "electric"
    ],
    "sg:website":"burgenland.at/elektro-horvath",
    "wof:name":"Elektro Horvath",
    "wof:placetype":"venue"
},
  "geometry": {"coordinates":[17.0721035004,47.9396743774],"type":"Point"}
}