{
  "type": "Feature",
  "properties": {
    "addr:full":"Sporg 21 Graz Steiermark 8010",
    "addr:housenumber":"21",
    "addr:postcode":"8010",
    "addr:street":"Sporg",
    "iso:country":"AT",
    "sg:address":"Sporg 21",
    "sg:city":"Graz",
    "sg:orig_category":"Galerien",
    "sg:phone":"+43 4331 68289820",
    "sg:postcode":"8010",
    "sg:province":"Steiermark",
    "wof:name":"Kunstkabinett Schafschetzy",
    "wof:placetype":"venue"
},
  "geometry": {"coordinates":[15.4389448166,47.0725288391],"type":"Point"}
}