{
  "type": "Feature",
  "properties": {
    "addr:full":"Bundesstr 57 Liebenau Steiermark 8041",
    "addr:housenumber":"57",
    "addr:postcode":"8041",
    "addr:street":"Bundesstr",
    "iso:country":"AT",
    "sg:address":"Bundesstr 57",
    "sg:city":"Liebenau",
    "sg:orig_category":"Betonbohr- U -Schneidedienst",
    "sg:phone":"+43 4331 6403050",
    "sg:postcode":"8041",
    "sg:province":"Steiermark",
    "wof:name":"Betonbohrservice GesmbH",
    "wof:placetype":"venue"
},
  "geometry": {"coordinates":[15.478143692,47.0103797913],"type":"Point"}
}