{
  "type": "Feature",
  "properties": {
    "addr:full":"Michael Haydn-Weg 4 Lamprechtshausen Salzburg 5112",
    "addr:housenumber":"4",
    "addr:postcode":"5112",
    "addr:street":"Haydn-Weg;Salzburg",
    "iso:country":"AT",
    "sg:address":"Michael Haydn-Weg 4",
    "sg:city":"Lamprechtshausen",
    "sg:orig_category":"Lebensmittel / Einzelhandel",
    "sg:phone":"+43 6274 49490",
    "sg:postcode":"5112",
    "sg:province":"Salzburg",
    "wof:name":"ADEG Aktiv Markt Johann Sporer",
    "wof:placetype":"venue"
},
  "geometry": {"coordinates":[12.9536943436,47.9857330322],"type":"Point"}
}