{
  "type": "Feature",
  "properties": {
    "iso:country":"AT",
    "sg:address":"Michael Haydn-Weg 4",
    "sg:city":"Lamprechtshausen",
    "sg:orig_category":"Lebensmittel / Einzelhandel",
    "sg:phone":"+43 6274 49490",
    "sg:postcode":"5112",
    "sg:province":"Salzburg",
    "wof:name":"ADEG Aktiv Markt Johann Sporer",
    "wof:placetype":"venue"
},
  "geometry": {"coordinates":[12.9536943436,47.9857330322],"type":"Point"}
}