{
  "type": "Feature",
  "properties": {
    "iso:country":"AT",
    "sg:address":"Bahng 13",
    "sg:city":"Warth",
    "sg:orig_category":"\u00c3\u201erzte / F Allgemeinmedizin",
    "sg:phone":"+43 2629 2116",
    "sg:postcode":"2831",
    "sg:province":"Nieder\u00f6sterreich",
    "wof:name":"Kn\u00f6bel Harald Dr",
    "wof:placetype":"venue"
},
  "geometry": {"coordinates":[-96.9972000122,37.2408103943],"type":"Point"}
}