{
  "type": "Feature",
  "properties": {
    "iso:country":"AT",
    "sg:address":"Graf-Starhemberg-G 3",
    "sg:city":"Wien",
    "sg:orig_category":"Ingenieurkonsulenten / Zivilingenieure",
    "sg:phone":"+43 4315 036003",
    "sg:postcode":"1040",
    "sg:province":"Wien",
    "wof:name":"Harrer Ewald Dipl-Ing",
    "wof:placetype":"venue"
},
  "geometry": {"coordinates":[16.3686065674,48.192035675],"type":"Point"}
}