{
  "type": "Feature",
  "properties": {
    "addr:full":"Ardetzenbergstr 4 Feldkirch Vorarlberg 6800",
    "addr:housenumber":"4",
    "addr:postcode":"6800",
    "addr:street":"Ardetzenbergstr",
    "iso:country":"AT",
    "sg:address":"Ardetzenbergstr 4",
    "sg:city":"Feldkirch",
    "sg:orig_category":"Non-Classified Establishments",
    "sg:phone":"+43 5522 72081",
    "sg:postcode":"6800",
    "sg:province":"Vorarlberg",
    "wof:name":"Evangelisches Pfarramt A und HB - Pauluskirche",
    "wof:placetype":"venue"
},
  "geometry": {"coordinates":[9.591881752,47.2380332947],"type":"Point"}
}