{
  "type": "Feature",
  "properties": {
    "addr:full":"Weistracher Str 8 Haag Nieder\u00f6sterreich 3350",
    "addr:housenumber":"8",
    "addr:postcode":"3350",
    "addr:street":"Str",
    "iso:country":"AT",
    "sg:address":"Weistracher Str 8",
    "sg:city":"Haag",
    "sg:orig_category":"Rettungsdienste",
    "sg:phone":"+43 7434 44950",
    "sg:postcode":"3350",
    "sg:province":"Nieder\u00f6sterreich",
    "wof:name":"Rotes Kreuz \u00f6sterr Bezirksstelle Haag",
    "wof:placetype":"venue"
},
  "geometry": {"coordinates":[14.5653495789,48.1121902466],"type":"Point"}
}