{
  "type": "Feature",
  "properties": {
    "addr:full":"Hauptpl 2 Frohnleiten Steiermark 8130",
    "addr:housenumber":"2",
    "addr:postcode":"8130",
    "addr:street":"Hauptpl",
    "iso:country":"AT",
    "sg:address":"Hauptpl 2",
    "sg:city":"Frohnleiten",
    "sg:orig_category":"Trachtenbekleidung",
    "sg:phone":"+43 4331 2651085",
    "sg:postcode":"8130",
    "sg:province":"Steiermark",
    "wof:name":"Lanzner Peter u Sabine - G\u00f6ssl Trachten",
    "wof:placetype":"venue"
},
  "geometry": {"coordinates":[15.3248710632,47.2699813843],"type":"Point"}
}