{
  "type": "Feature",
  "properties": {
    "addr:full":"Dreifaltigkeitspl 7 Kleinneusiedl Nieder\u00f6sterreich 2431",
    "addr:housenumber":"7",
    "addr:postcode":"2431",
    "addr:street":"Dreifaltigkeitspl",
    "iso:country":"AT",
    "sg:address":"Dreifaltigkeitspl 7",
    "sg:city":"Kleinneusiedl",
    "sg:orig_category":"Blumeneinzelhandel",
    "sg:phone":"+43 2230 9202",
    "sg:postcode":"2431",
    "sg:province":"Nieder\u00f6sterreich",
    "wof:name":"Blumen Cock",
    "wof:placetype":"venue"
},
  "geometry": {"coordinates":[16.6068992615,48.0845565796],"type":"Point"}
}