{
  "type": "Feature",
  "properties": {
    "iso:country":"AT",
    "sg:address":"Dorfpl 533",
    "sg:city":"Saalbach",
    "sg:orig_category":"Lebensmittel / Einzelhandel",
    "sg:phone":"+43 6541 6569",
    "sg:postcode":"5753",
    "sg:province":"Salzburg",
    "wof:name":"Nah und Frisch Supermarkt",
    "wof:placetype":"venue"
},
  "geometry": {"coordinates":[12.6368951797,47.3900032043],"type":"Point"}
}