{
  "type": "Feature",
  "properties": {
    "addr:full":"Illweg 18 N\u00fcziders Vorarlberg 6714",
    "addr:housenumber":"18",
    "addr:postcode":"6714",
    "addr:street":"Illweg",
    "iso:country":"AT",
    "sg:address":"Illweg 18",
    "sg:city":"N\u00fcziders",
    "sg:classifiers":[
        {
            "category":"Organizations",
            "subcategory":"Labor Organization",
            "type":"Services"
        }
    ],
    "sg:phone":"+43 5552 34184",
    "sg:postcode":"6714",
    "sg:province":"Vorarlberg",
    "sg:tags":[
        "aluminium",
        "door",
        "entrance",
        "system"
    ],
    "sg:website":"bickel-bau.com",
    "wof:name":"Bickel GmbH",
    "wof:placetype":"venue"
},
  "geometry": {"coordinates":[9.7787656784,47.1735038757],"type":"Point"}
}