{
  "type": "Feature",
  "properties": {
    "addr:full":"Frauentaler Str 76 Deutschlandsberg Steiermark 8530",
    "addr:postcode":"8530",
    "addr:street":"Str 76",
    "iso:country":"AT",
    "sg:address":"Frauentaler Str 76",
    "sg:city":"Deutschlandsberg",
    "sg:orig_category":"Tankstellen",
    "sg:phone":"+43 3462 69300",
    "sg:postcode":"8530",
    "sg:province":"Steiermark",
    "wof:name":"BP Austria Marketing GmbH",
    "wof:placetype":"venue"
},
  "geometry": {"coordinates":[15.2277193069,46.8193778992],"type":"Point"}
}