{
  "type": "Feature",
  "properties": {
    "addr:full":"Sch\u00f6ppfeldstr 5 Pasching Ober\u00f6sterreich 4061",
    "addr:housenumber":"5",
    "addr:postcode":"4061",
    "addr:street":"Schoeppfeldstr;Oberoesterreich",
    "iso:country":"AT",
    "sg:address":"Sch\u00f6ppfeldstr 5",
    "sg:city":"Pasching",
    "sg:orig_category":"Reinigungsbedarf U Reinigungsmittel",
    "sg:phone":"+43 7229 72356",
    "sg:postcode":"4061",
    "sg:province":"Ober\u00f6sterreich",
    "wof:name":"Chempro chemische Produkte",
    "wof:placetype":"venue"
},
  "geometry": {"coordinates":[14.2286071777,48.2385482788],"type":"Point"}
}