{
  "type": "Feature",
  "properties": {
    "addr:full":"Villenstr 5 Gallspach Ober\u00f6sterreich 4713",
    "addr:housenumber":"5",
    "addr:postcode":"4713",
    "addr:street":"Villenstr",
    "iso:country":"AT",
    "sg:address":"Villenstr 5",
    "sg:city":"Gallspach",
    "sg:orig_category":"Appartements / Ferienwohnungen",
    "sg:phone":"+43 7248 62612",
    "sg:postcode":"4713",
    "sg:province":"Ober\u00f6sterreich",
    "wof:name":"Ferienwohnungen Ernst",
    "wof:placetype":"venue"
},
  "geometry": {"coordinates":[13.8077325821,48.2077636719],"type":"Point"}
}