{
  "type": "Feature",
  "properties": {
    "addr:full":"Kaiser-Josef-Pl 3 Wels Ober\u00f6sterreich 4600",
    "addr:housenumber":"3",
    "addr:postcode":"4600",
    "addr:street":"Kaiser-Josef-Pl;Oberoesterreich",
    "iso:country":"AT",
    "sg:address":"Kaiser-Josef-Pl 3",
    "sg:city":"Wels",
    "sg:orig_category":"Optiker",
    "sg:phone":"+43 7242 62935",
    "sg:postcode":"4600",
    "sg:province":"Ober\u00f6sterreich",
    "wof:name":"Brillenkistl Michaela Sauer",
    "wof:placetype":"venue"
},
  "geometry": {"coordinates":[14.025396347,48.1600914001],"type":"Point"}
}