{
  "type": "Feature",
  "properties": {
    "addr:full":"Modecenterstr 16 Wien Wien 1030",
    "addr:housenumber":"16",
    "addr:postcode":"1030",
    "addr:street":"Modecenterstr",
    "iso:country":"AT",
    "sg:address":"Modecenterstr 16",
    "sg:city":"Wien",
    "sg:orig_category":"Bauleitung U -Betreuung",
    "sg:phone":"+43 1 79513262",
    "sg:postcode":"1030",
    "sg:province":"Wien",
    "wof:name":"Facility Management Austria GmbH",
    "wof:placetype":"venue"
},
  "geometry": {"coordinates":[16.4150905609,48.18542099],"type":"Point"}
}