{
  "type": "Feature",
  "properties": {
    "addr:full":"Andreas-Dipauli-Str 24a Innsbruck Tirol 6020",
    "addr:housenumber":"24a",
    "addr:postcode":"6020",
    "addr:street":"Andreas-Dipauli-Str;Tirol",
    "iso:country":"AT",
    "sg:address":"Andreas-Dipauli-Str 24a",
    "sg:city":"Innsbruck",
    "sg:orig_category":"Erdarbeiten",
    "sg:phone":"+43 664 1024444",
    "sg:postcode":"6020",
    "sg:province":"Tirol",
    "wof:name":"Tragler GesmbH",
    "wof:placetype":"venue"
},
  "geometry": {"coordinates":[11.3325462341,47.2666740417],"type":"Point"}
}