{
  "type": "Feature",
  "properties": {
    "addr:full":"H\u00fctteldorfer Str 159 Wien Wien 1140",
    "addr:housenumber":"159",
    "addr:postcode":"1140",
    "addr:street":"Str",
    "iso:country":"AT",
    "sg:address":"H\u00fctteldorfer Str 159",
    "sg:city":"Wien",
    "sg:orig_category":"Kontaktlinsenoptiker, Optiker",
    "sg:phone":"+43 1 9821410",
    "sg:postcode":"1140",
    "sg:province":"Wien",
    "sg:website":"www.0800Kontaktlinsen.at, www.kontaktlinsen.co.at",
    "wof:name":"Burger Optik GesmbH",
    "wof:placetype":"venue"
},
  "geometry": {"coordinates":[16.2696990967,48.1994247437],"type":"Point"}
}