{
  "type": "Feature",
  "properties": {
    "iso:country":"AT",
    "sg:address":"Hintere Zollamtsstr 2-4",
    "sg:city":"Wien",
    "sg:orig_category":"Polizei U Gendarmerie",
    "sg:phone":"+43 4313 131058320",
    "sg:postcode":"1030",
    "sg:province":"Wien",
    "wof:name":"Polizeikommissariat Wien - Wachzimmer",
    "wof:placetype":"venue"
},
  "geometry": {"coordinates":[16.3865642548,48.2102890015],"type":"Point"}
}