{
  "type": "Feature",
  "properties": {
    "addr:full":"Unterort 4 Bleiburg K\u00e4rnten 9150",
    "addr:housenumber":"4",
    "addr:postcode":"9150",
    "addr:street":"Unterort;Kaernten",
    "iso:country":"AT",
    "sg:address":"Unterort 4",
    "sg:city":"Bleiburg",
    "sg:classifiers":[
        {
            "category":"Home & Garden",
            "subcategory":"Garden Supply",
            "type":"Retail Goods"
        }
    ],
    "sg:phone":"+43 4342 353805",
    "sg:postcode":"9150",
    "sg:province":"K\u00e4rnten",
    "sg:tags":[
        "schotter",
        "sand",
        "u"
    ],
    "wof:name":"BAUTRANS GesmbH",
    "wof:placetype":"venue"
},
  "geometry": {"coordinates":[14.8096923828,46.5490722656],"type":"Point"}
}