{
  "type": "Feature",
  "properties": {
    "addr:full":"Linzer Str 43 Marchtrenk Ober\u00f6sterreich 4614",
    "addr:housenumber":"43",
    "addr:postcode":"4614",
    "addr:street":"Linzer Str",
    "iso:country":"AT",
    "sg:address":"Linzer Str 43",
    "sg:city":"Marchtrenk",
    "sg:orig_category":"Feuerwehren",
    "sg:phone":"+43 7243 58112",
    "sg:postcode":"4614",
    "sg:province":"Ober\u00f6sterreich",
    "wof:name":"Freiwillige Feuerwehr Marchtrenk",
    "wof:placetype":"venue"
},
  "geometry": {"coordinates":[14.1186714172,48.191783905],"type":"Point"}
}