{
  "type": "Feature",
  "properties": {
    "iso:country":"AT",
    "sg:address":"Ortenburger Str 3",
    "sg:city":"Spittal an der Drau",
    "sg:orig_category":"Waren Aller Art",
    "sg:phone":"+43 4762 37459",
    "sg:postcode":"9800",
    "sg:province":"K\u00e4rnten",
    "sg:website":"bastelmarkt.at",
    "wof:name":"VIF-ZACK",
    "wof:placetype":"venue"
},
  "geometry": {"coordinates":[13.4964008331,46.797416687],"type":"Point"}
}