{
  "type": "Feature",
  "properties": {
    "addr:full":"Brucknerstr 4 Wien Wien 1040",
    "addr:housenumber":"4",
    "addr:postcode":"1040",
    "addr:street":"Brucknerstr",
    "iso:country":"AT",
    "sg:address":"Brucknerstr 4",
    "sg:city":"Wien",
    "sg:orig_category":"Immobilienmakler",
    "sg:phone":"+43 4315 4548550",
    "sg:postcode":"1040",
    "sg:province":"Wien",
    "wof:name":"Ecoreal Economical Real Estate Industrie- u Immobilienvermittlung GesmbH",
    "wof:placetype":"venue"
},
  "geometry": {"coordinates":[16.3746166229,48.199131012],"type":"Point"}
}