{
  "type": "Feature",
  "properties": {
    "iso:country":"AT",
    "sg:address":"Schlo\u00dfstr 1",
    "sg:city":"Helfenberg",
    "sg:orig_category":"Webereien U Spinnereien",
    "sg:phone":"+43 7216 6209",
    "sg:postcode":"4184",
    "sg:province":"Ober\u00f6sterreich",
    "wof:name":"Glaser Hubert",
    "wof:placetype":"venue"
},
  "geometry": {"coordinates":[14.1420660019,48.5427513123],"type":"Point"}
}