{
  "type": "Feature",
  "properties": {
    "addr:full":"Vierzehnerstr 12 Freistadt Ober\u00f6sterreich 4240",
    "addr:housenumber":"12",
    "addr:postcode":"4240",
    "addr:street":"Vierzehnerstr",
    "iso:country":"AT",
    "sg:address":"Vierzehnerstr 12",
    "sg:city":"Freistadt",
    "sg:orig_category":"Fliesen U Platten",
    "sg:phone":"+43 7942 72984",
    "sg:postcode":"4240",
    "sg:province":"Ober\u00f6sterreich",
    "wof:name":"Pfl\u00fcgler Rosemarie",
    "wof:placetype":"venue"
},
  "geometry": {"coordinates":[14.5077772141,48.516582489],"type":"Point"}
}