{
  "type": "Feature",
  "properties": {
    "addr:full":"Michelndorf 13  Atzenbrugg Nieder\u00f6sterreich 3452",
    "addr:housenumber":"13",
    "addr:postcode":"3452",
    "addr:street":"Michelndorf",
    "iso:country":"AT",
    "sg:address":"Michelndorf 13 ",
    "sg:city":"Atzenbrugg",
    "sg:orig_category":"CarpenterS Work Supraregional",
    "sg:phone":"+43 2275 5317",
    "sg:postcode":"3452",
    "sg:province":"Nieder\u00f6sterreich",
    "wof:name":"Johann Kostka Ges.m.b.H.",
    "wof:placetype":"venue"
},
  "geometry": {"coordinates":[15.8978443146,48.2799949646],"type":"Point"}
}