{
  "type": "Feature",
  "properties": {
    "iso:country":"AT",
    "sg:address":"Gaisbacher Str 20",
    "sg:city":"Gallneukirchen",
    "sg:orig_category":"Modistinnen U Modisten",
    "sg:phone":"+43 4372 3562461",
    "sg:postcode":"4210",
    "sg:province":"Ober\u00f6sterreich",
    "wof:name":"H\u00f6ller Brigitta",
    "wof:placetype":"venue"
},
  "geometry": {"coordinates":[14.4164113998,48.350730896],"type":"Point"}
}