{
  "type": "Feature",
  "properties": {
    "addr:full":"Bahnhofstr 37 Klagenfurt K\u00e4rnten 9020",
    "addr:housenumber":"37",
    "addr:postcode":"9020",
    "addr:street":"Bahnhofstr;Kaernten",
    "iso:country":"AT",
    "sg:address":"Bahnhofstr 37",
    "sg:city":"Klagenfurt",
    "sg:orig_category":"Tabaktrafiken",
    "sg:phone":"+43 4346 356440",
    "sg:postcode":"9020",
    "sg:province":"K\u00e4rnten",
    "wof:name":"Podobnig Monika",
    "wof:placetype":"venue"
},
  "geometry": {"coordinates":[14.3109197617,46.6218338013],"type":"Point"}
}