{
  "type": "Feature",
  "properties": {
    "iso:country":"AT",
    "sg:address":"Schulstr 8",
    "sg:city":"Rohrbach in Ober\u00f6sterreich",
    "sg:orig_category":"Politische Parteien",
    "sg:phone":"+43 7289 42950",
    "sg:postcode":"4150",
    "sg:province":"Ober\u00f6sterreich",
    "wof:name":"Sozialdemokratische Partei \u00f6sterreichs (SP\u00f6)",
    "wof:placetype":"venue"
},
  "geometry": {"coordinates":[13.994685173,48.5716781616],"type":"Point"}
}