{
  "type": "Feature",
  "properties": {
    "iso:country":"AT",
    "sg:address":"Steindorf 151-154",
    "sg:city":"Stra\u00dfwalchen",
    "sg:classifiers":[
        {
            "category":"Home & Garden",
            "subcategory":"Building Materials",
            "type":"Retail Goods"
        }
    ],
    "sg:phone":"+43 6215 85310",
    "sg:postcode":"5204",
    "sg:province":"Salzburg",
    "sg:tags":[
        "baustoffe",
        "-material",
        "u"
    ],
    "sg:website":"www.bernit.at",
    "wof:name":"Bernit Baustoffwerk GesmbH & Co KG",
    "wof:placetype":"venue"
},
  "geometry": {"coordinates":[13.2358207703,47.9614639282],"type":"Point"}
}