{
  "type": "Feature",
  "properties": {
    "iso:country":"AT",
    "sg:address":"Nr 33",
    "sg:city":"Kohfidisch",
    "sg:orig_category":"Gemeinden",
    "sg:phone":"+43 3366 76545",
    "sg:postcode":"7512",
    "sg:province":"Burgenland",
    "wof:name":"Gemeinde Badersdorf",
    "wof:placetype":"venue"
},
  "geometry": {"coordinates":[16.3575592041,47.1757698059],"type":"Point"}
}