{
  "type": "Feature",
  "properties": {
    "addr:full":"Dieselstr 3 Mauer-\u00d6hling Nieder\u00f6sterreich 3362",
    "addr:housenumber":"3",
    "addr:postcode":"3362",
    "addr:street":"Dieselstr;Niederoesterreich",
    "iso:country":"AT",
    "sg:address":"Dieselstr 3",
    "sg:city":"Mauer-\u00d6hling",
    "sg:orig_category":"Bauunternehmen",
    "sg:phone":"+43 7472 628530",
    "sg:postcode":"3362",
    "sg:province":"Nieder\u00f6sterreich",
    "wof:name":"AGes-Bau Asphalt-GesmbH",
    "wof:placetype":"venue"
},
  "geometry": {"coordinates":[14.7985095978,48.1009559631],"type":"Point"}
}