{
  "type": "Feature",
  "properties": {
    "addr:full":"Traxleckerweg 2a Bad Ischl Ober\u00f6sterreich 4820",
    "addr:housenumber":"2a",
    "addr:postcode":"4820",
    "addr:street":"Traxleckerweg",
    "iso:country":"AT",
    "sg:address":"Traxleckerweg 2a",
    "sg:city":"Bad Ischl",
    "sg:orig_category":"Architekten",
    "sg:phone":"+43 664 2547142",
    "sg:postcode":"4820",
    "sg:province":"Ober\u00f6sterreich",
    "wof:name":"Erricher Roland Arch Dipl-Ing",
    "wof:placetype":"venue"
},
  "geometry": {"coordinates":[13.6347837448,47.7167396545],"type":"Point"}
}