{
  "type": "Feature",
  "properties": {
    "addr:full":"Hofmark 252 M\u00fcnzkirchen Ober\u00f6sterreich 4792",
    "addr:housenumber":"252",
    "addr:postcode":"4792",
    "addr:street":"Hofmark;Oberoesterreich",
    "iso:country":"AT",
    "sg:address":"Hofmark 252",
    "sg:city":"M\u00fcnzkirchen",
    "sg:orig_category":"Polizei U Gendarmerie",
    "sg:phone":"+43 4359 1334273",
    "sg:postcode":"4792",
    "sg:province":"Ober\u00f6sterreich",
    "wof:name":"Gendarmerie",
    "wof:placetype":"venue"
},
  "geometry": {"coordinates":[13.5722208023,48.484703064],"type":"Point"}
}