{
  "type": "Feature",
  "properties": {
    "addr:full":"Hennersdorfer Str 96 Achau Nieder\u00f6sterreich 2481",
    "addr:housenumber":"96",
    "addr:postcode":"2481",
    "addr:street":"Str",
    "iso:country":"AT",
    "sg:address":"Hennersdorfer Str 96",
    "sg:city":"Achau",
    "sg:classifiers":[
        {
            "category":"Shopping",
            "subcategory":"Party Supplies",
            "type":"Retail Goods"
        }
    ],
    "sg:phone":"+43 4322 3671684",
    "sg:postcode":"2481",
    "sg:province":"Nieder\u00f6sterreich",
    "sg:tags":[
        "u",
        "lichtanlagen",
        "ton-"
    ],
    "wof:name":"For Music Verleih Walter Babich",
    "wof:placetype":"venue"
},
  "geometry": {"coordinates":[16.3801898956,48.0863800049],"type":"Point"}
}