{
  "type": "Feature",
  "properties": {
    "addr:full":"Brandst\u00e4tterstr 18 Eferding Ober\u00f6sterreich 4070",
    "addr:housenumber":"18",
    "addr:postcode":"4070",
    "addr:street":"Brandstaetterstr",
    "iso:country":"AT",
    "sg:address":"Brandst\u00e4tterstr 18",
    "sg:city":"Eferding",
    "sg:orig_category":"Lebensmittel / Einzelhandel",
    "sg:phone":"+43 7272 6074",
    "sg:postcode":"4070",
    "sg:province":"Ober\u00f6sterreich",
    "wof:name":"SPAR \u00d6sterreichische Warenhandels-AG",
    "wof:placetype":"venue"
},
  "geometry": {"coordinates":[14.0230064392,48.3155822754],"type":"Point"}
}