{
  "type": "Feature",
  "properties": {
    "addr:full":"Kochg 30 Wien Wien 1080",
    "addr:housenumber":"30",
    "addr:postcode":"1080",
    "addr:street":"Kochg",
    "iso:country":"AT",
    "sg:address":"Kochg 30",
    "sg:city":"Wien",
    "sg:orig_category":"Friseure U Frisiersalons",
    "sg:phone":"+43 4314 080234",
    "sg:postcode":"1080",
    "sg:province":"Wien",
    "wof:name":"Frisiersalon Fred",
    "wof:placetype":"venue"
},
  "geometry": {"coordinates":[16.349647522,48.214263916],"type":"Point"}
}