{
  "type": "Feature",
  "properties": {
    "iso:country":"AT",
    "sg:address":"Hellmesbergerg 17",
    "sg:city":"Wien",
    "sg:orig_category":"Hunde- U Katzensalons",
    "sg:phone":"+43 4319 147633",
    "sg:postcode":"1140",
    "sg:province":"Wien",
    "wof:name":"Kipfl Andrea",
    "wof:placetype":"venue"
},
  "geometry": {"coordinates":[16.2722892761,48.195602417],"type":"Point"}
}