{
  "type": "Feature",
  "properties": {
    "addr:full":"Bahnstr 15 Hohenau an der March Nieder\u00f6sterreich 2273",
    "addr:housenumber":"15",
    "addr:postcode":"2273",
    "addr:street":"Bahnstr",
    "iso:country":"AT",
    "sg:address":"Bahnstr 15",
    "sg:city":"Hohenau an der March",
    "sg:orig_category":"Hauskrankenpflege / Heimhilfe",
    "sg:phone":"+43 4325 353776",
    "sg:postcode":"2273",
    "sg:province":"Nieder\u00f6sterreich",
    "wof:name":"Caritas Betreuen und Pflegen Zuhause Hohenau",
    "wof:placetype":"venue"
},
  "geometry": {"coordinates":[16.904045105,48.6043663025],"type":"Point"}
}