{
  "type": "Feature",
  "properties": {
    "addr:full":"Nr 32 P\u00f6ndorf Ober\u00f6sterreich 4891",
    "addr:postcode":"4891",
    "addr:street":"Nr 32 Poendorf Oberoesterreich",
    "iso:country":"AT",
    "sg:address":"Nr 32",
    "sg:city":"P\u00f6ndorf",
    "sg:orig_category":"Landwirtschaftliche Produkte",
    "sg:phone":"+43 76847127",
    "sg:postcode":"4891",
    "sg:province":"Ober\u00f6sterreich",
    "wof:name":"Fink Franz",
    "wof:placetype":"venue"
},
  "geometry": {"coordinates":[13.3680820465,47.9972114563],"type":"Point"}
}