{
  "type": "Feature",
  "properties": {
    "addr:full":"Bruckhofstrasse 3 Wels Ober\u00f6sterreich 4600",
    "addr:housenumber":"3",
    "addr:postcode":"4600",
    "addr:street":"Bruckhofstrasse;Oberoesterreich",
    "iso:country":"AT",
    "sg:address":"Bruckhofstrasse 3",
    "sg:city":"Wels",
    "sg:classifiers":[
        {
            "category":"Professional",
            "subcategory":"Advertising",
            "type":"Services"
        }
    ],
    "sg:phone":"+43 7242 72769",
    "sg:postcode":"4600",
    "sg:province":"Ober\u00f6sterreich",
    "sg:tags":[
        "exclusive",
        "articles"
    ],
    "sg:website":"forum-shop.at",
    "wof:name":"Forum Werbegeschenke GmbH",
    "wof:placetype":"venue"
},
  "geometry": {"coordinates":[14.0323829651,48.1510505676],"type":"Point"}
}