{
  "type": "Feature",
  "properties": {
    "addr:full":"Franz-Linser-Weg 3 Reutte Tirol 6600",
    "addr:housenumber":"3",
    "addr:postcode":"6600",
    "addr:street":"Franz-Linser-Weg;Tirol",
    "iso:country":"AT",
    "sg:address":"Franz-Linser-Weg 3",
    "sg:city":"Reutte",
    "sg:orig_category":"Crushed Stone Processing Plants",
    "sg:phone":"+43 5672 63617",
    "sg:postcode":"6600",
    "sg:province":"Tirol",
    "wof:name":"Schotterwerk J\u00e4ger Inh. Brigitte Wasle",
    "wof:placetype":"venue"
},
  "geometry": {"coordinates":[10.7197179794,47.4831695557],"type":"Point"}
}