{
  "type": "Feature",
  "properties": {
    "addr:full":"Biberhaufenweg 78 Wien Wien 1220",
    "addr:housenumber":"78",
    "addr:postcode":"1220",
    "addr:street":"Biberhaufenweg",
    "iso:country":"AT",
    "sg:address":"Biberhaufenweg 78",
    "sg:city":"Wien",
    "sg:orig_category":"Friseure U Frisiersalons",
    "sg:phone":"+43 4312 820115",
    "sg:postcode":"1220",
    "sg:province":"Wien",
    "sg:website":"haarforum.net",
    "wof:name":"Frisurenstudio Melitta Hartner",
    "wof:placetype":"venue"
},
  "geometry": {"coordinates":[16.4786376953,48.2114486694],"type":"Point"}
}