{
  "type": "Feature",
  "properties": {
    "addr:full":"Heiligenkreuzerweg 1 Baden Nieder\u00f6sterreich 2500",
    "addr:housenumber":"1",
    "addr:postcode":"2500",
    "addr:street":"Heiligenkreuzerweg;Niederoesterreich",
    "iso:country":"AT",
    "sg:address":"Heiligenkreuzerweg 1",
    "sg:city":"Baden",
    "sg:orig_category":"Feuerwehren",
    "sg:phone":"+43 2252 25030",
    "sg:postcode":"2500",
    "sg:province":"Nieder\u00f6sterreich",
    "wof:name":"Freiwillige Feuerwehr Siegenfeld",
    "wof:placetype":"venue"
},
  "geometry": {"coordinates":[16.2145595551,47.9845733643],"type":"Point"}
}