{
  "type": "Feature",
  "properties": {
    "iso:country":"AT",
    "sg:address":"Bahnhofweg 1",
    "sg:city":"Gaming",
    "sg:orig_category":"Erdarbeiten",
    "sg:phone":"+43 7485 97221",
    "sg:postcode":"3292",
    "sg:province":"Nieder\u00f6sterreich",
    "wof:name":"Bohlheim Baldur",
    "wof:placetype":"venue"
},
  "geometry": {"coordinates":[15.0880804062,47.9290084839],"type":"Point"}
}