{
  "type": "Feature",
  "properties": {
    "addr:full":"Unterbergg 167 Flachau Salzburg 5542",
    "addr:housenumber":"167",
    "addr:postcode":"5542",
    "addr:street":"Unterbergg;Salzburg",
    "iso:country":"AT",
    "sg:address":"Unterbergg 167",
    "sg:city":"Flachau",
    "sg:classifiers":[
        {
            "category":"Travel",
            "subcategory":"Hotels & Motels",
            "type":"Entertainment"
        }
    ],
    "sg:phone":"+43 6457 24030",
    "sg:postcode":"5542",
    "sg:province":"Salzburg",
    "wof:name":"Hotel Montanara",
    "wof:placetype":"venue"
},
  "geometry": {"coordinates":[13.3921222687,47.3435821533],"type":"Point"}
}