{
  "type": "Feature",
  "properties": {
    "iso:country":"AT",
    "sg:address":"Hauptpl 11",
    "sg:city":"Bruck an der Leitha",
    "sg:classifiers":[
        {
            "category":"Taxi",
            "type":"Transportation"
        }
    ],
    "sg:phone":"+43 4367 66158250",
    "sg:postcode":"2460",
    "sg:province":"Nieder\u00f6sterreich",
    "sg:tags":[
        "personentransporte",
        "u"
    ],
    "wof:name":"Zitzmann Taxi",
    "wof:placetype":"venue"
},
  "geometry": {"coordinates":[16.7791118622,48.0262184143],"type":"Point"}
}