{
  "type": "Feature",
  "properties": {
    "addr:full":"Kollerg 16 Wien Wien 1030",
    "addr:housenumber":"16",
    "addr:postcode":"1030",
    "addr:street":"Kollerg",
    "iso:country":"AT",
    "sg:address":"Kollerg 16",
    "sg:city":"Wien",
    "sg:orig_category":"Haarinstitute",
    "sg:phone":"+43 1 7123149",
    "sg:postcode":"1030",
    "sg:province":"Wien",
    "wof:name":"Capisan Gesellschaft f Haar- und kosmetische Beratung GmbH",
    "wof:placetype":"venue"
},
  "geometry": {"coordinates":[16.3896121979,48.2076263428],"type":"Point"}
}