{
  "type": "Feature",
  "properties": {
    "addr:full":"Pernerstorferg 24 Wien Wien 1100",
    "addr:housenumber":"24",
    "addr:postcode":"1100",
    "addr:street":"Pernerstorferg",
    "iso:country":"AT",
    "sg:address":"Pernerstorferg 24",
    "sg:city":"Wien",
    "sg:orig_category":"Architekten",
    "sg:phone":"+43 1 789866512",
    "sg:postcode":"1100",
    "sg:province":"Wien",
    "wof:name":"Silveri Friedemann Mag arch",
    "wof:placetype":"venue"
},
  "geometry": {"coordinates":[16.378112793,48.1764564514],"type":"Point"}
}