{
  "type": "Feature",
  "properties": {
    "addr:full":"Sommereiner Str 1 Mannersdorf am Leithagebirge Nieder\u00f6sterreich 2452",
    "addr:housenumber":"1",
    "addr:postcode":"2452",
    "addr:street":"Str",
    "iso:country":"AT",
    "sg:address":"Sommereiner Str 1",
    "sg:city":"Mannersdorf am Leithagebirge",
    "sg:orig_category":"Tabaktrafiken",
    "sg:phone":"+43 4321 6862208",
    "sg:postcode":"2452",
    "sg:province":"Nieder\u00f6sterreich",
    "wof:name":"Graf Monika",
    "wof:placetype":"venue"
},
  "geometry": {"coordinates":[16.6098880768,47.9755096436],"type":"Point"}
}