{
  "type": "Feature",
  "properties": {
    "iso:country":"AT",
    "sg:address":"Bahnhofstr 41",
    "sg:city":"Rechnitz",
    "sg:orig_category":"Glasereien",
    "sg:phone":"+43 3363 79495",
    "sg:postcode":"7471",
    "sg:province":"Burgenland",
    "wof:name":"H\u00f6fler Johannes",
    "wof:placetype":"venue"
},
  "geometry": {"coordinates":[16.4444389343,47.2978935242],"type":"Point"}
}