{
  "type": "Feature",
  "properties": {
    "addr:full":"Lainzer Str 141 Wien Wien 1130",
    "addr:housenumber":"141",
    "addr:postcode":"1130",
    "iso:country":"AT",
    "sg:address":"Lainzer Str 141",
    "sg:city":"Wien",
    "sg:orig_category":"Optiker",
    "sg:phone":"+43 1 8048116",
    "sg:postcode":"1130",
    "sg:province":"Wien",
    "wof:name":"Neooptik",
    "wof:placetype":"venue"
},
  "geometry": {"coordinates":[16.2839660645,48.1769561768],"type":"Point"}
}