{
  "type": "Feature",
  "properties": {
    "iso:country":"AT",
    "sg:address":"Kirchpl 14",
    "sg:city":"Ehrwald",
    "sg:classifiers":[
        {
            "category":"Travel",
            "subcategory":"Hotels & Motels",
            "type":"Entertainment"
        }
    ],
    "sg:phone":"+43 5673 22080",
    "sg:postcode":"6632",
    "sg:province":"Tirol",
    "wof:name":"Sonnenspitze Hotel GesmbH & Co KG",
    "wof:placetype":"venue"
},
  "geometry": {"coordinates":[10.9199132919,47.3982391357],"type":"Point"}
}