{
  "type": "Feature",
  "properties": {
    "addr:full":"Ringstr. 11 Krems an der Donau Nieder\u00f6sterreich 3500",
    "addr:housenumber":"11",
    "addr:postcode":"3500",
    "addr:street":"Ringstr.",
    "iso:country":"AT",
    "sg:address":"Ringstr. 11",
    "sg:city":"Krems an der Donau",
    "sg:classifiers":[
        {
            "category":"Banks & Credit Unions",
            "subcategory":"Financial Services",
            "type":"Services"
        }
    ],
    "sg:phone":"+43 4327 32875110",
    "sg:postcode":"3500",
    "sg:province":"Nieder\u00f6sterreich",
    "sg:tags":[
        "banking",
        "finance",
        "insurance"
    ],
    "wof:name":"WIENER ST\u00c4DT. ALLGEMEINE VERSICHERUNGS AG",
    "wof:placetype":"venue"
},
  "geometry": {"coordinates":[15.6037797928,48.4099617004],"type":"Point"}
}