{
  "type": "Feature",
  "properties": {
    "addr:full":"Haltackerried 58 Leibnitz Steiermark 8430",
    "addr:housenumber":"58",
    "addr:postcode":"8430",
    "addr:street":"Haltackerried;Steiermark",
    "iso:country":"AT",
    "sg:address":"Haltackerried 58",
    "sg:city":"Leibnitz",
    "sg:classifiers":[
        {
            "category":"Train Station",
            "subcategory":"Light Rail",
            "type":"Transportation"
        }
    ],
    "sg:phone":"+43 3452 837090",
    "sg:postcode":"8430",
    "sg:province":"Steiermark",
    "sg:tags":[
        "sprocket",
        "drives",
        "chain"
    ],
    "sg:website":"demuth.motoren.at",
    "wof:name":"Elektro Motoren Demuth Inh. Margit Pratter Demuth",
    "wof:placetype":"venue"
},
  "geometry": {"coordinates":[15.5638875961,46.798122406],"type":"Point"}
}