{
  "type": "Feature",
  "properties": {
    "iso:country":"AT",
    "sg:address":"Schl\u00e4gerstr 15",
    "sg:city":"Litschau",
    "sg:orig_category":"Bestattungsunternehmen",
    "sg:phone":"+43 2865 346",
    "sg:postcode":"3874",
    "sg:province":"Nieder\u00f6sterreich",
    "wof:name":"Glaubauf Johann",
    "wof:placetype":"venue"
},
  "geometry": {"coordinates":[15.0453643799,48.9441757202],"type":"Point"}
}