{
  "type": "Feature",
  "properties": {
    "addr:full":"Hauptstr 46 Zeillern Nieder\u00f6sterreich 3311",
    "addr:housenumber":"46",
    "addr:postcode":"3311",
    "addr:street":"Hauptstr",
    "iso:country":"AT",
    "sg:address":"Hauptstr 46",
    "sg:city":"Zeillern",
    "sg:orig_category":"Kosmetikanwendungsberatung",
    "sg:phone":"+43 7472 65123",
    "sg:postcode":"3311",
    "sg:province":"Nieder\u00f6sterreich",
    "wof:name":"Channoine-Cosmetics - Maria Bruckb\u00e4ck",
    "wof:placetype":"venue"
},
  "geometry": {"coordinates":[14.806936264,48.1289596558],"type":"Point"}
}