{
  "type": "Feature",
  "properties": {
    "iso:country":"AT",
    "sg:address":"Nr 68a",
    "sg:city":"Stein an der Enns",
    "sg:orig_category":"Appartements / Ferienwohnungen",
    "sg:phone":"+43 3685 22987",
    "sg:postcode":"8961",
    "sg:province":"Steiermark",
    "wof:name":"Binder Silvia",
    "wof:placetype":"venue"
},
  "geometry": {"coordinates":[13.9389886856,47.3949966431],"type":"Point"}
}