{
  "type": "Feature",
  "properties": {
    "addr:full":"Nr 2 Niederw\u00f6lz Steiermark 8831",
    "addr:postcode":"8831",
    "addr:street":"Nr",
    "iso:country":"AT",
    "sg:address":"Nr 2",
    "sg:city":"Niederw\u00f6lz",
    "sg:orig_category":"Volksschulen",
    "sg:phone":"+43 3587 272",
    "sg:postcode":"8831",
    "sg:province":"Steiermark",
    "wof:name":"Volksschule",
    "wof:placetype":"venue"
},
  "geometry": {"coordinates":[14.346581459,47.1894569397],"type":"Point"}
}