{
  "type": "Feature",
  "properties": {
    "addr:full":"Ottakringer Strasse 147 Wien Wien 1160",
    "addr:housenumber":"147",
    "addr:postcode":"1160",
    "addr:street":"Ottakringer Strasse",
    "iso:country":"AT",
    "sg:address":"Ottakringer Strasse 147",
    "sg:city":"Wien",
    "sg:classifiers":[
        {
            "category":"Home & Garden",
            "subcategory":"Building Materials",
            "type":"Retail Goods"
        }
    ],
    "sg:phone":"+43 1 4857825",
    "sg:postcode":"1160",
    "sg:province":"Wien",
    "sg:tags":[
        "tile",
        "ceramic"
    ],
    "sg:website":"kerabela.at",
    "wof:name":"Kerabela Fliesenverlegung GesmbH",
    "wof:placetype":"venue"
},
  "geometry": {"coordinates":[16.3156070709,48.2131385803],"type":"Point"}
}