{
  "type": "Feature",
  "properties": {
    "addr:full":"H\u00f6fer Str 25 Wilhering Ober\u00f6sterreich 4073",
    "addr:housenumber":"25",
    "addr:postcode":"4073",
    "addr:street":"Str",
    "iso:country":"AT",
    "sg:address":"H\u00f6fer Str 25",
    "sg:city":"Wilhering",
    "sg:orig_category":"Maschinenbau",
    "sg:phone":"+43 7226 22420",
    "sg:postcode":"4073",
    "sg:province":"Ober\u00f6sterreich",
    "wof:name":"Hierzer GesmbH & Co KG",
    "wof:placetype":"venue"
},
  "geometry": {"coordinates":[14.1848506927,48.3224906921],"type":"Point"}
}