{
  "type": "Feature",
  "properties": {
    "addr:full":"Marktpl 28 Eggern Nieder\u00f6sterreich 3861",
    "addr:housenumber":"28",
    "addr:postcode":"3861",
    "addr:street":"Marktpl",
    "iso:country":"AT",
    "sg:address":"Marktpl 28",
    "sg:city":"Eggern",
    "sg:orig_category":"Fleischhauereien",
    "sg:phone":"+43 2863 217",
    "sg:postcode":"3861",
    "sg:province":"Nieder\u00f6sterreich",
    "wof:name":"Gebharter Franz",
    "wof:placetype":"venue"
},
  "geometry": {"coordinates":[15.1480798721,48.9081001282],"type":"Point"}
}