{
  "type": "Feature",
  "properties": {
    "iso:country":"AT",
    "sg:address":"Hauptstr 25",
    "sg:city":"Greifenstein",
    "sg:orig_category":"Postservicestellen",
    "sg:phone":"+43 2242 32280",
    "sg:postcode":"3422",
    "sg:province":"Nieder\u00f6sterreich",
    "wof:name":"Post-Partner Greifenstein",
    "wof:placetype":"venue"
},
  "geometry": {"coordinates":[16.2441825867,48.3470497131],"type":"Point"}
}