{
  "type": "Feature",
  "properties": {
    "iso:country":"AT",
    "sg:address":"Gradnitzer Str. 2 ",
    "sg:city":"Zwettl",
    "sg:classifiers":[
        {
            "category":"Parking",
            "subcategory":"Lot",
            "type":"Transportation"
        }
    ],
    "sg:phone":"+43 4328 2254400",
    "sg:postcode":"3910",
    "sg:province":"Nieder\u00f6sterreich",
    "sg:tags":[
        "transport",
        "road"
    ],
    "wof:name":"LUDWIG RIEDLER KG",
    "wof:placetype":"venue"
},
  "geometry": {"coordinates":[15.1448631287,48.6313781738],"type":"Point"}
}