{
  "type": "Feature",
  "properties": {
    "addr:full":"Fugbachgasse 7/6 Wien Wien 1020",
    "addr:housenumber":"7 / 6",
    "addr:postcode":"1020",
    "addr:street":"Fugbachgasse",
    "iso:country":"AT",
    "sg:address":"Fugbachgasse 7/6",
    "sg:city":"Wien",
    "sg:orig_category":"Internet-Design, Web-Design",
    "sg:phone":"+43 699 19585874",
    "sg:postcode":"1020",
    "sg:province":"Wien",
    "sg:website":"loreth.net",
    "wof:name":"Andrea Loreth",
    "wof:placetype":"venue"
},
  "geometry": {"coordinates":[16.387840271,48.2208900452],"type":"Point"}
}