{
  "type": "Feature",
  "properties": {
    "iso:country":"AT",
    "sg:address":"Millst\u00e4tter Str 86",
    "sg:city":"Feld am See",
    "sg:orig_category":"Holzbau",
    "sg:phone":"+43 4246 29117",
    "sg:postcode":"9544",
    "sg:province":"K\u00e4rnten",
    "sg:website":"holzbau-rauter.at",
    "wof:name":"Holzbau Rauter KEG",
    "wof:placetype":"venue"
},
  "geometry": {"coordinates":[13.7386789322,46.7828865051],"type":"Point"}
}