{
  "type": "Feature",
  "properties": {
    "addr:full":"Zollamtsstr 1 Angern Nieder\u00f6sterreich 2261",
    "addr:housenumber":"1",
    "addr:postcode":"2261",
    "addr:street":"Zollamtsstr",
    "iso:country":"AT",
    "sg:address":"Zollamtsstr 1",
    "sg:city":"Angern",
    "sg:orig_category":"Polizei U Gendarmerie",
    "sg:phone":"+43 4359 1333218",
    "sg:postcode":"2261",
    "sg:province":"Nieder\u00f6sterreich",
    "wof:name":"Gendarmerie Grenzkontrollstelle",
    "wof:placetype":"venue"
},
  "geometry": {"coordinates":[16.8332843781,48.3825263977],"type":"Point"}
}