{
  "type": "Feature",
  "properties": {
    "addr:full":"Bahnstr 48 Schattendorf Burgenland 7022",
    "addr:housenumber":"48",
    "addr:postcode":"7022",
    "addr:street":"Bahnstr",
    "iso:country":"AT",
    "sg:address":"Bahnstr 48",
    "sg:city":"Schattendorf",
    "sg:orig_category":"Brennstoffe",
    "sg:phone":"+43 4326 867480",
    "sg:postcode":"7022",
    "sg:province":"Burgenland",
    "wof:name":"Bauer Kurt Brennstoffdiskont",
    "wof:placetype":"venue"
},
  "geometry": {"coordinates":[16.485918045,47.6991882324],"type":"Point"}
}