{
  "type": "Feature",
  "properties": {
    "addr:full":"Gentzg 2 Wien Wien 1180",
    "addr:housenumber":"2",
    "addr:postcode":"1180",
    "addr:street":"Gentzg",
    "iso:country":"AT",
    "sg:address":"Gentzg 2",
    "sg:city":"Wien",
    "sg:orig_category":"Psychotherapie",
    "sg:phone":"+43 1 4793584",
    "sg:postcode":"1180",
    "sg:province":"Wien",
    "wof:name":"Fak Hanna",
    "wof:placetype":"venue"
},
  "geometry": {"coordinates":[16.3478183746,48.2264099121],"type":"Point"}
}