{
  "type": "Feature",
  "properties": {
    "addr:full":"Triester Str 271 Feldkirchen Steiermark 8073",
    "addr:housenumber":"271",
    "addr:postcode":"8073",
    "iso:country":"AT",
    "sg:address":"Triester Str 271",
    "sg:city":"Feldkirchen",
    "sg:classifiers":[
        {
            "category":"Internet Cafe",
            "subcategory":"None",
            "type":"Food & Drink"
        }
    ],
    "sg:phone":"+43 4331 35570700",
    "sg:postcode":"8073",
    "sg:province":"Steiermark",
    "wof:name":"A-System Datentechnik GmbH",
    "wof:placetype":"venue"
},
  "geometry": {"coordinates":[15.4577455521,46.9883155823],"type":"Point"}
}