{
  "type": "Feature",
  "properties": {
    "iso:country":"AT",
    "sg:address":"Sonnenhofstr 1",
    "sg:city":"Kitzb\u00fchel",
    "sg:classifiers":[
        {
            "category":"Travel",
            "subcategory":"Hotels & Motels",
            "type":"Entertainment"
        }
    ],
    "sg:phone":"+43 5356 627210",
    "sg:postcode":"6370",
    "sg:province":"Tirol",
    "wof:name":"Hotel Sonnenhof",
    "wof:placetype":"venue"
},
  "geometry": {"coordinates":[12.3981180191,47.4469985962],"type":"Point"}
}