{
  "type": "Feature",
  "properties": {
    "iso:country":"AT",
    "sg:address":"Nr 10",
    "sg:city":"Admont",
    "sg:orig_category":"Fahrschulen",
    "sg:phone":"+43 4336 1343956",
    "sg:postcode":"8911",
    "sg:province":"Steiermark",
    "wof:name":"Lubensky GesmbH - Internat u Ferienfahrschule",
    "wof:placetype":"venue"
},
  "geometry": {"coordinates":[14.4609088898,47.5760040283],"type":"Point"}
}