{
  "type": "Feature",
  "properties": {
    "addr:full":"Schulstrasse 29 Gr\u00fcnburg Ober\u00f6sterreich 4594",
    "addr:housenumber":"29",
    "addr:postcode":"4594",
    "addr:street":"Schulstrasse;Oberoesterreich",
    "iso:country":"AT",
    "sg:address":"Schulstrasse 29",
    "sg:city":"Gr\u00fcnburg",
    "sg:classifiers":[
        {
            "category":"Social Services",
            "subcategory":"Job Training",
            "type":"Services"
        }
    ],
    "sg:phone":"+43 664 3334349",
    "sg:postcode":"4594",
    "sg:province":"Ober\u00f6sterreich",
    "sg:tags":[
        "coating",
        "anti-friction"
    ],
    "sg:website":"members.24speed.at/opus/",
    "wof:name":"Handelsagentur Walter F\u00fcrst",
    "wof:placetype":"venue"
},
  "geometry": {"coordinates":[14.2661790848,47.973072052],"type":"Point"}
}