{
  "type": "Feature",
  "properties": {
    "addr:full":"Esterhazyg 32 Wien Wien 1060",
    "addr:housenumber":"32",
    "addr:postcode":"1060",
    "addr:street":"Esterhazyg",
    "iso:country":"AT",
    "sg:address":"Esterhazyg 32",
    "sg:city":"Wien",
    "sg:orig_category":"Friseure U Frisiersalons",
    "sg:phone":"+43 4315 873325",
    "sg:postcode":"1060",
    "sg:province":"Wien",
    "wof:name":"Steiner Gabriele",
    "wof:placetype":"venue"
},
  "geometry": {"coordinates":[16.34907341,48.1974258423],"type":"Point"}
}