{
  "type": "Feature",
  "properties": {
    "iso:country":"AT",
    "sg:address":"Goldschlagstrasse 87-89",
    "sg:city":"Wien",
    "sg:classifiers":[
        {
            "category":"Government",
            "subcategory":"Fire Station",
            "type":"Public Place"
        }
    ],
    "sg:phone":"+43 1 981300",
    "sg:postcode":"1150",
    "sg:province":"Wien",
    "sg:tags":[
        "aluminium",
        "protection",
        "fitting"
    ],
    "sg:website":"alukoenigstahl.com",
    "wof:name":"ALU K\u00d6NIG STAHL GmbH",
    "wof:placetype":"venue"
},
  "geometry": {"coordinates":[16.3202533722,48.1945075989],"type":"Point"}
}