{
  "type": "Feature",
  "properties": {
    "addr:full":"Keutschacher Strasse 71 Velden am W\u00f6rther See K\u00e4rnten 9220",
    "addr:housenumber":"71",
    "addr:postcode":"9220",
    "addr:street":"Keutschacher Strasse;Kaernten",
    "iso:country":"AT",
    "sg:address":"Keutschacher Strasse 71",
    "sg:city":"Velden am W\u00f6rther See",
    "sg:classifiers":[
        {
            "category":"Banks & Credit Unions",
            "subcategory":"Investment Brokerage",
            "type":"Services"
        }
    ],
    "sg:phone":"+43 4274 2582",
    "sg:postcode":"9220",
    "sg:province":"K\u00e4rnten",
    "sg:tags":[
        "fence"
    ],
    "wof:name":"OLIKON Zaunbau Ges.m.b.H.",
    "wof:placetype":"venue"
},
  "geometry": {"coordinates":[14.0525493622,46.6028213501],"type":"Point"}
}