{
  "type": "Feature",
  "properties": {
    "addr:full":"Mutterstr 64 Feldkirch Vorarlberg 6800",
    "addr:housenumber":"64",
    "addr:postcode":"6800",
    "addr:street":"Mutterstr",
    "iso:country":"AT",
    "sg:address":"Mutterstr 64",
    "sg:city":"Feldkirch",
    "sg:orig_category":"Handelsagenturen",
    "sg:phone":"+43 5522 73380",
    "sg:postcode":"6800",
    "sg:province":"Vorarlberg",
    "wof:name":"Dellemann Raimund",
    "wof:placetype":"venue"
},
  "geometry": {"coordinates":[9.6109762192,47.2505760193],"type":"Point"}
}