{
  "type": "Feature",
  "properties": {
    "addr:full":"Planaistr 49 Rohrmoos-Untertal Steiermark 8971",
    "addr:housenumber":"49",
    "addr:postcode":"8971",
    "addr:street":"Planaistr",
    "iso:country":"AT",
    "sg:address":"Planaistr 49",
    "sg:city":"Rohrmoos-Untertal",
    "sg:orig_category":"Tischlereien",
    "sg:phone":"+43 4336 8723364",
    "sg:postcode":"8971",
    "sg:province":"Steiermark",
    "wof:name":"Schrempf Hans",
    "wof:placetype":"venue"
},
  "geometry": {"coordinates":[13.7158756256,47.3959999084],"type":"Point"}
}