{
  "type": "Feature",
  "properties": {
    "iso:country":"AT",
    "sg:address":"Gusenleithnerg 27",
    "sg:city":"Wien",
    "sg:orig_category":"Behinderungen / Leben Mit Behinderungen",
    "sg:phone":"+43 4319 10440",
    "sg:postcode":"1140",
    "sg:province":"Wien",
    "wof:name":"Behindertenbetreuung - Mobile Betreuung u Kommunikationszentrum",
    "wof:placetype":"venue"
},
  "geometry": {"coordinates":[16.2900009155,48.198097229],"type":"Point"}
}