{
  "type": "Feature",
  "properties": {
    "addr:full":"Wallerseestrasse 65 Seekirchen am Wallersee Salzburg 5201",
    "addr:housenumber":"65",
    "addr:postcode":"5201",
    "addr:street":"Wallerseestrasse;Salzburg",
    "iso:country":"AT",
    "sg:address":"Wallerseestrasse 65",
    "sg:city":"Seekirchen am Wallersee",
    "sg:classifiers":[
        {
            "category":"Home & Garden",
            "subcategory":"Building Materials",
            "type":"Retail Goods"
        }
    ],
    "sg:phone":"+43 6212 4013",
    "sg:postcode":"5201",
    "sg:province":"Salzburg",
    "sg:tags":[
        "banister"
    ],
    "wof:name":"Schinwald Ges.m.b.H.",
    "wof:placetype":"venue"
},
  "geometry": {"coordinates":[13.1261043549,47.8981704712],"type":"Point"}
}