{
  "type": "Feature",
  "properties": {
    "iso:country":"AT",
    "sg:address":"Kreuzbichlweg 13",
    "sg:city":"Klagenfurt",
    "sg:orig_category":"Psychologen",
    "sg:phone":"+43 463 46444",
    "sg:postcode":"9020",
    "sg:province":"K\u00e4rnten",
    "wof:name":"Greiner-Kuschej Irene Mag",
    "wof:placetype":"venue"
},
  "geometry": {"coordinates":[14.369972229,46.6520462036],"type":"Point"}
}