{
  "type": "Feature",
  "properties": {
    "iso:country":"AT",
    "sg:address":"Badner Str 8",
    "sg:city":"Tattendorf",
    "sg:orig_category":"Fleischhauereien",
    "sg:phone":"+43 2253 81283",
    "sg:postcode":"2523",
    "sg:province":"Nieder\u00f6sterreich",
    "wof:name":"Heiling Franz",
    "wof:placetype":"venue"
},
  "geometry": {"coordinates":[16.3026027679,47.9566307068],"type":"Point"}
}