{
  "type": "Feature",
  "properties": {
    "iso:country":"AT",
    "sg:address":"Hitzendorfer Str 153",
    "sg:city":"Tobelbad",
    "sg:classifiers":[
        {
            "category":"Government",
            "subcategory":"Post Office",
            "type":"Public Place"
        }
    ],
    "sg:phone":"+43 3136 62210",
    "sg:postcode":"8144",
    "sg:province":"Steiermark",
    "sg:tags":[
        "-handel",
        "tierzucht",
        "u"
    ],
    "wof:name":"Reif Dieter",
    "wof:placetype":"venue"
},
  "geometry": {"coordinates":[15.3394699097,46.9935188293],"type":"Point"}
}