{
  "type": "Feature",
  "properties": {
    "iso:country":"AT",
    "sg:address":"K\u00fchberg 16",
    "sg:city":"Neumarkt am Wallersee",
    "sg:classifiers":[
        {
            "category":"Professional",
            "subcategory":"Management & Consulting",
            "type":"Services"
        }
    ],
    "sg:phone":"+43 6216 4949",
    "sg:postcode":"5202",
    "sg:province":"Salzburg",
    "wof:name":"Graf & Partner Managementberatung KEG",
    "wof:placetype":"venue"
},
  "geometry": {"coordinates":[13.2245721817,47.9449386597],"type":"Point"}
}