{
  "type": "Feature",
  "properties": {
    "iso:country":"AT",
    "sg:address":"Vogelweiderstr 55",
    "sg:city":"Salzburg",
    "sg:orig_category":"Inkassoinstitute",
    "sg:phone":"+43 662 8753460",
    "sg:postcode":"5020",
    "sg:province":"Salzburg",
    "wof:name":"Commerz Inkassob\u00fcro GesmbH",
    "wof:placetype":"venue"
},
  "geometry": {"coordinates":[13.0539007187,47.8130302429],"type":"Point"}
}