{
  "type": "Feature",
  "properties": {
    "addr:full":"Raphael Donner-Allee 79 Wien Wien 1220",
    "addr:housenumber":"79",
    "addr:postcode":"1220",
    "iso:country":"AT",
    "sg:address":"Raphael Donner-Allee 79",
    "sg:city":"Wien",
    "sg:classifiers":[
        {
            "category":"Professional",
            "subcategory":"Computer Services",
            "type":"Services"
        }
    ],
    "sg:phone":"+43 1 7747056",
    "sg:postcode":"1220",
    "sg:province":"Wien",
    "sg:tags":[
        "software"
    ],
    "wof:name":"Tanzer Peter",
    "wof:placetype":"venue"
},
  "geometry": {"coordinates":[16.5233955383,48.2040252686],"type":"Point"}
}