{
  "type": "Feature",
  "properties": {
    "addr:full":"Baumschulstr 6 Tullnerbach Nieder\u00f6sterreich 3013",
    "addr:housenumber":"6",
    "addr:postcode":"3013",
    "addr:street":"Baumschulstr",
    "iso:country":"AT",
    "sg:address":"Baumschulstr 6",
    "sg:city":"Tullnerbach",
    "sg:orig_category":"Betriebsbeteiligungen",
    "sg:phone":"+43 4322 3357995",
    "sg:postcode":"3013",
    "sg:province":"Nieder\u00f6sterreich",
    "wof:name":"EDOK Liegenschaftsverwaltungs- u BeteiligungsgesmbH",
    "wof:placetype":"venue"
},
  "geometry": {"coordinates":[16.0899295807,48.1888122559],"type":"Point"}
}