{
  "type": "Feature",
  "properties": {
    "iso:country":"AT",
    "sg:address":"Hauptstr 61",
    "sg:city":"Schalchen",
    "sg:orig_category":"Banken U Sparkassen",
    "sg:phone":"+43 7742 25060",
    "sg:postcode":"5231",
    "sg:province":"Ober\u00f6sterreich",
    "wof:name":"Raiffeisenbank Mattigtal regGenmbH",
    "wof:placetype":"venue"
},
  "geometry": {"coordinates":[13.1548833847,48.1135940552],"type":"Point"}
}