{
  "type": "Feature",
  "properties": {
    "iso:country":"AT",
    "sg:address":"Schlo\u00dfg 7",
    "sg:city":"Kindberg",
    "sg:orig_category":"Politische Parteien",
    "sg:phone":"+43 664 4514439",
    "sg:postcode":"8650",
    "sg:province":"Steiermark",
    "wof:name":"\u00f6sterreichische Volkspartei (\u00f6VP)",
    "wof:placetype":"venue"
},
  "geometry": {"coordinates":[15.4488525391,47.5068969727],"type":"Point"}
}