{
  "type": "Feature",
  "properties": {
    "iso:country":"AT",
    "sg:address":"L\u00e4ngenfeldg 29",
    "sg:city":"Wien",
    "sg:orig_category":"Teppiche / Einzelhandel",
    "sg:phone":"+43 4318 136473",
    "sg:postcode":"1120",
    "sg:province":"Wien",
    "sg:website":"achtungschaf.at, www.pa-re.at",
    "wof:name":"PA-RE Handwebeteppiche",
    "wof:placetype":"venue"
},
  "geometry": {"coordinates":[16.3406257629,48.1789398193],"type":"Point"}
}