{
  "type": "Feature",
  "properties": {
    "iso:country":"AT",
    "sg:address":"Nr 23a",
    "sg:city":"Hippach",
    "sg:orig_category":"Bekleidung / Einzelhandel",
    "sg:phone":"+43 5282 50901",
    "sg:postcode":"6283",
    "sg:province":"Tirol",
    "wof:name":"H & K Mode Hanser und Kreidl OEG",
    "wof:placetype":"venue"
},
  "geometry": {"coordinates":[11.8661670685,47.2039108276],"type":"Point"}
}