{
  "type": "Feature",
  "properties": {
    "addr:full":"Westbahnstr 3 Wien Wien 1070",
    "addr:housenumber":"3",
    "addr:postcode":"1070",
    "addr:street":"Westbahnstr",
    "iso:country":"AT",
    "sg:address":"Westbahnstr 3",
    "sg:city":"Wien",
    "sg:orig_category":"Bekleidung / Einzelhandel",
    "sg:phone":"+43 1 5220425",
    "sg:postcode":"1070",
    "sg:province":"Wien",
    "wof:name":"ARTPOINT - Elena Zvereva",
    "wof:placetype":"venue"
},
  "geometry": {"coordinates":[16.3479995728,48.2016525269],"type":"Point"}
}