{
  "type": "Feature",
  "properties": {
    "addr:full":"Scheibeng 1/8 Wien Wien 1190",
    "addr:housenumber":"1 / 8",
    "addr:postcode":"1190",
    "addr:street":"Scheibeng",
    "iso:country":"AT",
    "sg:address":"Scheibeng 1/8",
    "sg:city":"Wien",
    "sg:orig_category":"Holzgro\u00c3\u0178handel",
    "sg:phone":"+43 1 36837810",
    "sg:postcode":"1190",
    "sg:province":"Wien",
    "wof:name":"GTH HandelsgesmbH",
    "wof:placetype":"venue"
},
  "geometry": {"coordinates":[16.3534145355,48.2452468872],"type":"Point"}
}