{
  "type": "Feature",
  "properties": {
    "iso:country":"AT",
    "sg:address":"Siedlungsstr 12",
    "sg:city":"Haiming",
    "sg:orig_category":"Fenster",
    "sg:phone":"+43 4352 6688700",
    "sg:postcode":"6425",
    "sg:province":"Tirol",
    "wof:name":"Bau & Wohn Team ideenraich Inh Mario Raich",
    "wof:placetype":"venue"
},
  "geometry": {"coordinates":[10.8800516129,47.2543945312],"type":"Point"}
}