{
  "type": "Feature",
  "properties": {
    "iso:country":"AT",
    "sg:address":"Klagbaumg 8",
    "sg:city":"Wien",
    "sg:orig_category":"Installationsunternehmen",
    "sg:phone":"+43 1 5866886",
    "sg:postcode":"1040",
    "sg:province":"Wien",
    "wof:name":"Kaindl Michael",
    "wof:placetype":"venue"
},
  "geometry": {"coordinates":[16.3655319214,48.1910667419],"type":"Point"}
}