{
  "type": "Feature",
  "properties": {
    "iso:country":"AT",
    "sg:address":"IZ-N\u00d6-S\u00fcd Strasse 3 2d, Objekt M18",
    "sg:classifiers":[
        {
            "category":"Utilities",
            "subcategory":"Natural Gas",
            "type":"Services"
        }
    ],
    "sg:phone":"+43 2236 628300",
    "sg:postcode":"2355",
    "sg:tags":[
        "bathroom",
        "cock",
        "fitting"
    ],
    "sg:website":"hansgrohe.at",
    "wof:name":"Hans Grohe Handelsges.m.b.H.",
    "wof:placetype":"venue"
},
  "geometry": {"coordinates":[16.3183326721,48.0863113403],"type":"Point"}
}