{
  "type": "Feature",
  "properties": {
    "addr:full":"Neubauweg 12 St. Johann in Tirol Tirol 6380",
    "addr:housenumber":"12",
    "addr:postcode":"6380",
    "addr:street":"Neubauweg;Tirol",
    "iso:country":"AT",
    "sg:address":"Neubauweg 12",
    "sg:city":"St. Johann in Tirol",
    "sg:orig_category":"Pensionen / Privatzimmer",
    "sg:phone":"+43 5352 67104",
    "sg:postcode":"6380",
    "sg:province":"Tirol",
    "wof:name":"Pension Edelwei\u00dfhof",
    "wof:placetype":"venue"
},
  "geometry": {"coordinates":[12.4281759262,47.5245857239],"type":"Point"}
}