{
  "type": "Feature",
  "properties": {
    "addr:full":"Florianig 20 Wien Wien 1080",
    "addr:housenumber":"20",
    "addr:postcode":"1080",
    "addr:street":"Florianig",
    "iso:country":"AT",
    "sg:address":"Florianig 20",
    "sg:city":"Wien",
    "sg:orig_category":"Installationsunternehmen",
    "sg:phone":"+43 1 40544530",
    "sg:postcode":"1080",
    "sg:province":"Wien",
    "wof:name":"Stach Wilhelm",
    "wof:placetype":"venue"
},
  "geometry": {"coordinates":[16.3515644073,48.2120246887],"type":"Point"}
}