{
  "type": "Feature",
  "properties": {
    "addr:full":"Ringmauerg 5-7 Villach K\u00e4rnten 9500",
    "addr:housenumber":"5-7",
    "addr:postcode":"9500",
    "addr:street":"Ringmauerg;Kaernten",
    "iso:country":"AT",
    "sg:address":"Ringmauerg 5-7",
    "sg:city":"Villach",
    "sg:orig_category":"Damenmoden",
    "sg:phone":"+43 4242 29432",
    "sg:postcode":"9500",
    "sg:province":"K\u00e4rnten",
    "wof:name":"Charles V\u00f6gele (Austria) AG",
    "wof:placetype":"venue"
},
  "geometry": {"coordinates":[13.8429327011,46.6132888794],"type":"Point"}
}