{
  "type": "Feature",
  "properties": {
    "addr:full":"Altmannsdorfer Str 52 Wien Wien 1120",
    "addr:postcode":"1120",
    "addr:street":"Str 52",
    "iso:country":"AT",
    "sg:address":"Altmannsdorfer Str 52",
    "sg:city":"Wien",
    "sg:classifiers":[
        {
            "category":"Wholesale",
            "subcategory":"Motor Vehicles",
            "type":"Manufacturing & Wholesale Goods"
        }
    ],
    "sg:phone":"+43 1 8047766",
    "sg:postcode":"1120",
    "sg:province":"Wien",
    "sg:tags":[
        "moped"
    ],
    "sg:website":"www.jelinek.co.at",
    "wof:name":"Motorrad-Jelinek",
    "wof:placetype":"venue"
},
  "geometry": {"coordinates":[16.3156776428,48.1678009033],"type":"Point"}
}