{
  "type": "Feature",
  "properties": {
    "addr:full":"Puckinger Str 8 Pucking Ober\u00f6sterreich 4055",
    "addr:housenumber":"8",
    "addr:postcode":"4055",
    "addr:street":"Str",
    "iso:country":"AT",
    "sg:address":"Puckinger Str 8",
    "sg:city":"Pucking",
    "sg:orig_category":"Volksschulen",
    "sg:phone":"+43 7229 88714",
    "sg:postcode":"4055",
    "sg:province":"Ober\u00f6sterreich",
    "wof:name":"Volksschule",
    "wof:placetype":"venue"
},
  "geometry": {"coordinates":[14.1869792938,48.189163208],"type":"Point"}
}