{
  "type": "Feature",
  "properties": {
    "addr:full":"Au St. Wolfgang im Salzkammergut Ober\u00f6sterreich 5360",
    "addr:postcode":"5360",
    "addr:street":"Au;Oberoesterreich",
    "iso:country":"AT",
    "sg:address":"Au",
    "sg:city":"St. Wolfgang im Salzkammergut",
    "sg:orig_category":"Tankstellen",
    "sg:phone":"+43 4361 382436",
    "sg:postcode":"5360",
    "sg:province":"Ober\u00f6sterreich",
    "wof:name":"avanti TANKSTELLE H\u00f6dlmoser Peter",
    "wof:placetype":"venue"
},
  "geometry": {"coordinates":[13.4567718506,47.737903595],"type":"Point"}
}