{
  "type": "Feature",
  "properties": {
    "addr:full":"M\u00fchlstrasse 21 Fernitz Steiermark 8072",
    "addr:housenumber":"21",
    "addr:postcode":"8072",
    "addr:street":"Muehlstrasse",
    "iso:country":"AT",
    "sg:address":"M\u00fchlstrasse 21",
    "sg:city":"Fernitz",
    "sg:classifiers":[
        {
            "category":"Transit Center",
            "subcategory":"Freight",
            "type":"Transportation"
        }
    ],
    "sg:phone":"+43 3135 55412",
    "sg:postcode":"8072",
    "sg:province":"Steiermark",
    "sg:tags":[
        "packing",
        "twine",
        "thread"
    ],
    "sg:website":"ecofil.at",
    "wof:name":"Papierausr\u00fcstung A. Truchse\u00df Ecofil Austria",
    "wof:placetype":"venue"
},
  "geometry": {"coordinates":[15.4987697601,46.9728660583],"type":"Point"}
}