{
  "type": "Feature",
  "properties": {
    "addr:full":"Nr 75 St. Konrad Ober\u00f6sterreich 4817",
    "addr:postcode":"4817",
    "addr:street":"Nr 75 St.;Oberoesterreich",
    "iso:country":"AT",
    "sg:address":"Nr 75",
    "sg:city":"St. Konrad",
    "sg:orig_category":"Beratungsstellen",
    "sg:phone":"+43 76158025",
    "sg:postcode":"4817",
    "sg:province":"Ober\u00f6sterreich",
    "wof:name":"Mutterberatungsstelle",
    "wof:placetype":"venue"
},
  "geometry": {"coordinates":[13.8887310028,47.9127082825],"type":"Point"}
}