{
  "type": "Feature",
  "properties": {
    "addr:full":"Emmersberg 5 Geretsberg Ober\u00f6sterreich 5132",
    "addr:housenumber":"5",
    "addr:postcode":"5132",
    "addr:street":"Emmersberg",
    "iso:country":"AT",
    "sg:address":"Emmersberg 5",
    "sg:city":"Geretsberg",
    "sg:orig_category":"Badezimmer U Badezimmereinrichtungen",
    "sg:phone":"+43 6277 81880",
    "sg:postcode":"5132",
    "sg:province":"Ober\u00f6sterreich",
    "wof:name":"Bauer-Kober Bierbottichbad & Wellness OEG",
    "wof:placetype":"venue"
},
  "geometry": {"coordinates":[12.9568929672,48.0803260803],"type":"Point"}
}