{
  "type": "Feature",
  "properties": {
    "addr:full":"Obere Donaul\u00e4nde 11 Linz Ober\u00f6sterreich 4020",
    "addr:housenumber":"11",
    "addr:postcode":"4020",
    "addr:street":"Obere Donaulaende",
    "iso:country":"AT",
    "sg:address":"Obere Donaul\u00e4nde 11",
    "sg:city":"Linz",
    "sg:orig_category":"Bars-Cafes",
    "sg:phone":"+43 4373 2782777",
    "sg:postcode":"4020",
    "sg:province":"Ober\u00f6sterreich",
    "wof:name":"B52 Cocktailbar",
    "wof:placetype":"venue"
},
  "geometry": {"coordinates":[14.283788681,48.3064842224],"type":"Point"}
}