{
  "type": "Feature",
  "properties": {
    "addr:full":"Linzer Str 18 Bad Hall Ober\u00f6sterreich 4540",
    "addr:housenumber":"18",
    "addr:postcode":"4540",
    "addr:street":"Linzer Str",
    "iso:country":"AT",
    "sg:address":"Linzer Str 18",
    "sg:city":"Bad Hall",
    "sg:orig_category":"Abfallentsorgung U -Verwertung",
    "sg:phone":"+43 4372 585820",
    "sg:postcode":"4540",
    "sg:province":"Ober\u00f6sterreich",
    "wof:name":"Altstoffsammelzentrum",
    "wof:placetype":"venue"
},
  "geometry": {"coordinates":[14.2050046921,48.0383720398],"type":"Point"}
}