{
  "type": "Feature",
  "properties": {
    "addr:full":"Schulg 7 Parndorf Burgenland 7111",
    "addr:housenumber":"7",
    "addr:postcode":"7111",
    "addr:street":"Schulg",
    "iso:country":"AT",
    "sg:address":"Schulg 7",
    "sg:city":"Parndorf",
    "sg:orig_category":"Telekommunikation",
    "sg:phone":"+43 2166 2266",
    "sg:postcode":"7111",
    "sg:province":"Burgenland",
    "wof:name":"TCO Consulting Dora Staudinger",
    "wof:placetype":"venue"
},
  "geometry": {"coordinates":[16.8667469025,47.9991912842],"type":"Point"}
}