{
  "type": "Feature",
  "properties": {
    "addr:full":"Hochstrasse 4 Sierning Ober\u00f6sterreich 4522",
    "addr:housenumber":"4",
    "addr:postcode":"4522",
    "addr:street":"Hochstrasse",
    "iso:country":"AT",
    "sg:address":"Hochstrasse 4",
    "sg:city":"Sierning",
    "sg:classifiers":[
        {
            "category":"Shopping",
            "subcategory":"Computers & Home Electronics",
            "type":"Retail Goods"
        }
    ],
    "sg:phone":"+43 7259 2571",
    "sg:postcode":"4522",
    "sg:province":"Ober\u00f6sterreich",
    "sg:tags":[
        "binoculars",
        "prism"
    ],
    "wof:name":"Thomas Teufel",
    "wof:placetype":"venue"
},
  "geometry": {"coordinates":[14.3084411621,48.0448417664],"type":"Point"}
}