{
  "type": "Feature",
  "properties": {
    "addr:full":"Dorfstr 29 Wundschuh Steiermark 8142",
    "addr:housenumber":"29",
    "addr:postcode":"8142",
    "addr:street":"Dorfstr",
    "iso:country":"AT",
    "sg:address":"Dorfstr 29",
    "sg:city":"Wundschuh",
    "sg:orig_category":"Datenverarbeitung",
    "sg:phone":"+43 4331 3552945",
    "sg:postcode":"8142",
    "sg:province":"Steiermark",
    "wof:name":"Gaggl Walter",
    "wof:placetype":"venue"
},
  "geometry": {"coordinates":[15.4542007446,46.9240722656],"type":"Point"}
}