{
  "type": "Feature",
  "properties": {
    "iso:country":"AT",
    "sg:address":"Sonnenwiese 8",
    "sg:city":"St. Anton am Arlberg",
    "sg:orig_category":"Pensionen / Privatzimmer",
    "sg:phone":"+43 4354 463389",
    "sg:postcode":"6580",
    "sg:province":"Tirol",
    "wof:name":"Alpenheim Pension",
    "wof:placetype":"venue"
},
  "geometry": {"coordinates":[10.2663927078,47.1317863464],"type":"Point"}
}