{
  "type": "Feature",
  "properties": {
    "addr:full":"Schillinghofstr 44 Gnigl Salzburg 5023",
    "addr:housenumber":"44",
    "addr:postcode":"5023",
    "addr:street":"Schillinghofstr",
    "iso:country":"AT",
    "sg:address":"Schillinghofstr 44",
    "sg:city":"Gnigl",
    "sg:classifiers":[
        {
            "category":"Home & Garden",
            "subcategory":"Kitchen Supply",
            "type":"Retail Goods"
        }
    ],
    "sg:phone":"+43 4366 2644032",
    "sg:postcode":"5023",
    "sg:province":"Salzburg",
    "sg:tags":[
        "espresso-",
        "u",
        "kaffeemaschinen"
    ],
    "sg:website":"mks-salzburg.at",
    "wof:name":"mks Maschinen- u Kochger\u00e4te ServicegesmbH",
    "wof:placetype":"venue"
},
  "geometry": {"coordinates":[13.0641813278,47.8208389282],"type":"Point"}
}