{
  "type": "Feature",
  "properties": {
    "addr:full":"Wiener Str 89 Baden Nieder\u00f6sterreich 2500",
    "addr:housenumber":"89",
    "addr:postcode":"2500",
    "addr:street":"Niederoesterreich",
    "iso:country":"AT",
    "sg:address":"Wiener Str 89",
    "sg:city":"Baden",
    "sg:orig_category":"Ingenieurkonsulenten / Zivilingenieure",
    "sg:phone":"+43 2252 425850",
    "sg:postcode":"2500",
    "sg:province":"Nieder\u00f6sterreich",
    "wof:name":"Mitteregger Volker Dipl-Ing",
    "wof:placetype":"venue"
},
  "geometry": {"coordinates":[16.2517261505,48.0127372742],"type":"Point"}
}