{
  "type": "Feature",
  "properties": {
    "addr:full":"Brand 389 Hittisau Vorarlberg 6952",
    "addr:housenumber":"389",
    "addr:postcode":"6952",
    "addr:street":"Brand",
    "iso:country":"AT",
    "sg:address":"Brand 389",
    "sg:city":"Hittisau",
    "sg:orig_category":"Brush Rockers",
    "sg:phone":"+43 5513 41130",
    "sg:postcode":"6952",
    "sg:province":"Vorarlberg",
    "wof:name":"G. Dietrich Gesellschaft m.b.H.",
    "wof:placetype":"venue"
},
  "geometry": {"coordinates":[9.9762210846,47.4584121704],"type":"Point"}
}