{
  "type": "Feature",
  "properties": {
    "addr:full":"Weizensteinerstr 8 Salzburg Salzburg 5020",
    "addr:housenumber":"8",
    "addr:postcode":"5020",
    "addr:street":"Weizensteinerstr;Salzburg",
    "iso:country":"AT",
    "sg:address":"Weizensteinerstr 8",
    "sg:city":"Salzburg",
    "sg:orig_category":"Minigolfanlagen U -Bedarf",
    "sg:phone":"+43 4366 2824133",
    "sg:postcode":"5020",
    "sg:province":"Salzburg",
    "wof:name":"Salzburger Minigolfpl\u00e4tze Karl Hiedler",
    "wof:placetype":"venue"
},
  "geometry": {"coordinates":[13.0267400742,47.7928581238],"type":"Point"}
}