{
  "type": "Feature",
  "properties": {
    "addr:full":"Hambuchen 478 P\u00f6llau Steiermark 8225",
    "addr:housenumber":"478",
    "addr:postcode":"8225",
    "addr:street":"Hambuchen",
    "iso:country":"AT",
    "sg:address":"Hambuchen 478",
    "sg:city":"P\u00f6llau",
    "sg:orig_category":"Tischlereien",
    "sg:phone":"+43 4333 3520940",
    "sg:postcode":"8225",
    "sg:province":"Steiermark",
    "wof:name":"KAPO M\u00f6belwerkst\u00e4tten GmbH - Fensterwerk",
    "wof:placetype":"venue"
},
  "geometry": {"coordinates":[15.8337945938,47.301990509],"type":"Point"}
}