{
  "type": "Feature",
  "properties": {
    "addr:full":"Hauptstr 27 Katzelsdorf Nieder\u00f6sterreich 2801",
    "addr:housenumber":"27",
    "addr:postcode":"2801",
    "addr:street":"Hauptstr",
    "iso:country":"AT",
    "sg:address":"Hauptstr 27",
    "sg:city":"Katzelsdorf",
    "sg:orig_category":"Anlagenbau U -Technik",
    "sg:phone":"+43 4326 2244533",
    "sg:postcode":"2801",
    "sg:province":"Nieder\u00f6sterreich",
    "wof:name":"Weiss Anlagen Technik GmbH",
    "wof:placetype":"venue"
},
  "geometry": {"coordinates":[16.2697982788,47.7827758789],"type":"Point"}
}