{
  "type": "Feature",
  "properties": {
    "iso:country":"AT",
    "sg:address":"C v H\u00f6tzendorf-Str 91",
    "sg:city":"Graz",
    "sg:orig_category":"Restaurants: Amerikanisch",
    "sg:phone":"+43 316 4719090",
    "sg:postcode":"8010",
    "sg:province":"Steiermark",
    "wof:name":"McDonald's Restaurant - McDrive",
    "wof:placetype":"venue"
},
  "geometry": {"coordinates":[15.4431800842,47.0685653687],"type":"Point"}
}