{
  "type": "Feature",
  "properties": {
    "iso:country":"AT",
    "sg:address":"Unterrain 19",
    "sg:city":"St. Andr\u00e4",
    "sg:classifiers":[
        {
            "category":"Home & Garden",
            "subcategory":"Building Materials",
            "type":"Retail Goods"
        }
    ],
    "sg:phone":"+43 4358 28358",
    "sg:postcode":"9433",
    "sg:province":"K\u00e4rnten",
    "sg:tags":[
        "railing",
        "balcony"
    ],
    "wof:name":"Gerold Zabercnik",
    "wof:placetype":"venue"
},
  "geometry": {"coordinates":[14.8384103775,46.7403831482],"type":"Point"}
}