{
  "type": "Feature",
  "properties": {
    "addr:full":"Pfarrg 83 Wien Wien 1230",
    "addr:housenumber":"83",
    "addr:postcode":"1230",
    "addr:street":"Pfarrg",
    "iso:country":"AT",
    "sg:address":"Pfarrg 83",
    "sg:city":"Wien",
    "sg:orig_category":"Reifen U Reifendienste",
    "sg:phone":"+43 1 6174420",
    "sg:postcode":"1230",
    "sg:province":"Wien",
    "wof:name":"Reifen Bruckm\u00fcller GmbH",
    "wof:placetype":"venue"
},
  "geometry": {"coordinates":[16.3418502808,48.1391448975],"type":"Point"}
}