{
  "type": "Feature",
  "properties": {
    "iso:country":"AT",
    "sg:address":"Hauptpl 29",
    "sg:city":"Neusiedl am See",
    "sg:orig_category":"Boutiquen",
    "sg:phone":"+43 2167 8713",
    "sg:postcode":"7100",
    "sg:province":"Burgenland",
    "wof:name":"Salt & Pepper",
    "wof:placetype":"venue"
},
  "geometry": {"coordinates":[16.8419361115,47.9492721558],"type":"Point"}
}