{
  "type": "Feature",
  "properties": {
    "addr:full":"Grundsteingasse 11 Wien Wien 1160",
    "addr:housenumber":"11",
    "addr:postcode":"1160",
    "addr:street":"Grundsteingasse",
    "iso:country":"AT",
    "sg:address":"Grundsteingasse 11",
    "sg:city":"Wien",
    "sg:classifiers":[
        {
            "category":"Building & Trades",
            "subcategory":"Construction",
            "type":"Services"
        }
    ],
    "sg:phone":"+43 1 9140419",
    "sg:postcode":"1160",
    "sg:province":"Wien",
    "sg:tags":[
        "roofing"
    ],
    "wof:name":"DSI Dachdecker- Spengler- u. IsolierungsgesmbH",
    "wof:placetype":"venue"
},
  "geometry": {"coordinates":[16.3373069763,48.2094917297],"type":"Point"}
}