{
  "type": "Feature",
  "properties": {
    "addr:full":"Eggenberger Allee 69 Graz Steiermark 8020",
    "addr:housenumber":"69",
    "addr:postcode":"8020",
    "addr:street":"Eggenberger Allee",
    "iso:country":"AT",
    "sg:address":"Eggenberger Allee 69",
    "sg:city":"Graz",
    "sg:classifiers":[
        {
            "category":"Taxi",
            "type":"Transportation"
        }
    ],
    "sg:phone":"+43 4331 6581290",
    "sg:postcode":"8020",
    "sg:province":"Steiermark",
    "sg:tags":[
        "personentransporte",
        "u"
    ],
    "wof:name":"Sieber-J\u00f6bstl Romana",
    "wof:placetype":"venue"
},
  "geometry": {"coordinates":[15.3985948563,47.0710449219],"type":"Point"}
}