{
  "type": "Feature",
  "properties": {
    "iso:country":"AT",
    "sg:address":"Obermarkt 38",
    "sg:city":"Reutte",
    "sg:orig_category":"Drogerien",
    "sg:phone":"+43 5672 63465",
    "sg:postcode":"6600",
    "sg:province":"Tirol",
    "wof:name":"dm drogerie markt GmbH",
    "wof:placetype":"venue"
},
  "geometry": {"coordinates":[10.7204246521,47.4855270386],"type":"Point"}
}