{
  "type": "Feature",
  "properties": {
    "iso:country":"AT",
    "sg:address":"Unterafiesl 17",
    "sg:city":"Helfenberg",
    "sg:orig_category":"Fenster",
    "sg:phone":"+43 7216 42771",
    "sg:postcode":"4184",
    "sg:province":"Ober\u00f6sterreich",
    "wof:name":"Bauelemente Preining",
    "wof:placetype":"venue"
},
  "geometry": {"coordinates":[14.1439466476,48.5767974854],"type":"Point"}
}