{
  "type": "Feature",
  "properties": {
    "iso:country":"AT",
    "sg:address":"An der Maut 7",
    "sg:city":"Spittal an der Drau",
    "sg:orig_category":"Vinotheken",
    "sg:phone":"+43 4762 42991",
    "sg:postcode":"9800",
    "sg:province":"K\u00e4rnten",
    "wof:name":"Casa del Vino Hans-J\u00f6rg Kronawetter",
    "wof:placetype":"venue"
},
  "geometry": {"coordinates":[13.5039997101,46.7951965332],"type":"Point"}
}