{
  "type": "Feature",
  "properties": {
    "addr:full":"Salzburger Str 261 Linz Ober\u00f6sterreich 4030",
    "addr:housenumber":"261",
    "addr:postcode":"4030",
    "addr:street":"Salzburger Str",
    "iso:country":"AT",
    "sg:address":"Salzburger Str 261",
    "sg:city":"Linz",
    "sg:orig_category":"Restaurants: Balkan",
    "sg:phone":"+43 732 380490",
    "sg:postcode":"4030",
    "sg:province":"Ober\u00f6sterreich",
    "wof:name":"Alte Br\u00fccke Mostar",
    "wof:placetype":"venue"
},
  "geometry": {"coordinates":[14.2814226151,48.253238678],"type":"Point"}
}