{
  "type": "Feature",
  "properties": {
    "addr:full":"F Zuckerst\u00e4tter-Str 9 Thalgau Salzburg 5303",
    "addr:housenumber":"9",
    "addr:postcode":"5303",
    "addr:street":"Zuckerstaetter-Str;Salzburg",
    "iso:country":"AT",
    "sg:address":"F Zuckerst\u00e4tter-Str 9",
    "sg:city":"Thalgau",
    "sg:orig_category":"Ingenieurkonsulenten / Zivilingenieure",
    "sg:phone":"+43 6235 5132",
    "sg:postcode":"5303",
    "sg:province":"Salzburg",
    "wof:name":"Poppinger G\u00fcnther Dipl-Ing",
    "wof:placetype":"venue"
},
  "geometry": {"coordinates":[13.2537765503,47.8417167664],"type":"Point"}
}