{
  "type": "Feature",
  "properties": {
    "iso:country":"AT",
    "sg:address":"Freudenauer Hafenstr. 16",
    "sg:city":"Wien",
    "sg:classifiers":[
        {
            "category":"Parking",
            "subcategory":"Lot",
            "type":"Transportation"
        }
    ],
    "sg:phone":"+43 4317 27170",
    "sg:postcode":"1020",
    "sg:province":"Wien",
    "sg:tags":[
        "transport",
        "road"
    ],
    "wof:name":"BISCHOF GESMBH",
    "wof:placetype":"venue"
},
  "geometry": {"coordinates":[16.4683132172,48.1810913086],"type":"Point"}
}