{
  "type": "Feature",
  "properties": {
    "addr:full":"Grauer-Stein-Weg 47 Innsbruck Tirol 6020",
    "addr:housenumber":"47",
    "addr:postcode":"6020",
    "addr:street":"Grauer-Stein-Weg;Tirol",
    "iso:country":"AT",
    "sg:address":"Grauer-Stein-Weg 47",
    "sg:city":"Innsbruck",
    "sg:classifiers":[
        {
            "category":"Restaurant",
            "type":"Food & Drink"
        }
    ],
    "sg:phone":"+43 512 276252",
    "sg:postcode":"6020",
    "sg:province":"Tirol",
    "wof:name":"Schretthauser Michael",
    "wof:placetype":"venue"
},
  "geometry": {"coordinates":[11.3619785309,47.2663841248],"type":"Point"}
}