{
  "type": "Feature",
  "properties": {
    "addr:full":"Hauptpl 15 Obervellach K\u00e4rnten 9821",
    "addr:housenumber":"15",
    "addr:postcode":"9821",
    "addr:street":"Hauptpl;Kaernten",
    "iso:country":"AT",
    "sg:address":"Hauptpl 15",
    "sg:city":"Obervellach",
    "sg:orig_category":"Polizei U Gendarmerie",
    "sg:phone":"+43 4359 1332232",
    "sg:postcode":"9821",
    "sg:province":"K\u00e4rnten",
    "wof:name":"Gendarmerie",
    "wof:placetype":"venue"
},
  "geometry": {"coordinates":[13.202000618,46.9322319031],"type":"Point"}
}