{
  "type": "Feature",
  "properties": {
    "addr:full":"Anichstr 12 Innsbruck Tirol 6020",
    "addr:housenumber":"12",
    "addr:postcode":"6020",
    "addr:street":"Anichstr;Tirol",
    "iso:country":"AT",
    "sg:address":"Anichstr 12",
    "sg:city":"Innsbruck",
    "sg:orig_category":"Damenmoden",
    "sg:phone":"+43 512 585408",
    "sg:postcode":"6020",
    "sg:province":"Tirol",
    "wof:name":"Fessler Gert",
    "wof:placetype":"venue"
},
  "geometry": {"coordinates":[11.3922252655,47.2649269104],"type":"Point"}
}