{
  "type": "Feature",
  "properties": {
    "addr:full":"Handelszentrum 4 Bergheim Salzburg 5101",
    "addr:housenumber":"4",
    "addr:postcode":"5101",
    "addr:street":"Handelszentrum;Salzburg",
    "iso:country":"AT",
    "sg:address":"Handelszentrum 4",
    "sg:city":"Bergheim",
    "sg:orig_category":"Stahl / Gro\u00c3\u0178handel",
    "sg:phone":"+43 4366 2469820",
    "sg:postcode":"5101",
    "sg:province":"Salzburg",
    "wof:name":"Stahlhandel Bergheim GmbH & Co KG",
    "wof:placetype":"venue"
},
  "geometry": {"coordinates":[13.0358324051,47.8422737122],"type":"Point"}
}