{
  "type": "Feature",
  "properties": {
    "addr:full":"Rotenhofg 77 Wien Wien 1100",
    "addr:housenumber":"77",
    "addr:postcode":"1100",
    "addr:street":"Rotenhofg",
    "iso:country":"AT",
    "sg:address":"Rotenhofg 77",
    "sg:city":"Wien",
    "sg:classifiers":[
        {
            "category":"Wholesale",
            "subcategory":"Vending Machines",
            "type":"Manufacturing & Wholesale Goods"
        }
    ],
    "sg:phone":"+43 4316 043156",
    "sg:postcode":"1100",
    "sg:province":"Wien",
    "sg:tags":[
        "filter"
    ],
    "sg:website":"jaklin.at",
    "wof:name":"Jaklin Friedrich",
    "wof:placetype":"venue"
},
  "geometry": {"coordinates":[16.3626937866,48.174697876],"type":"Point"}
}