{
  "type": "Feature",
  "properties": {
    "addr:full":"Gunzenberg 2 Stra\u00dfburg K\u00e4rnten 9341",
    "addr:housenumber":"2",
    "addr:postcode":"9341",
    "addr:street":"Gunzenberg;Kaernten",
    "iso:country":"AT",
    "sg:address":"Gunzenberg 2",
    "sg:city":"Stra\u00dfburg",
    "sg:classifiers":[
        {
            "category":"Home & Garden",
            "subcategory":"Household Appliances",
            "type":"Retail Goods"
        }
    ],
    "sg:phone":"+43 4266 2291",
    "sg:postcode":"9341",
    "sg:province":"K\u00e4rnten",
    "sg:tags":[
        "electric"
    ],
    "wof:name":"Andreas Sbardelati",
    "wof:placetype":"venue"
},
  "geometry": {"coordinates":[14.3335618973,46.8938331604],"type":"Point"}
}