{
  "type": "Feature",
  "properties": {
    "addr:full":"Mondseestr. 11 Unterach am Attersee Ober\u00f6sterreich 4866",
    "addr:housenumber":"11",
    "addr:postcode":"4866",
    "addr:street":"Mondseestr.",
    "iso:country":"AT",
    "sg:address":"Mondseestr. 11",
    "sg:city":"Unterach am Attersee",
    "sg:classifiers":[
        {
            "category":"Wholesale",
            "subcategory":"Drugs",
            "type":"Manufacturing & Wholesale Goods"
        }
    ],
    "sg:phone":"+43 4376 6581230",
    "sg:postcode":"4866",
    "sg:province":"Ober\u00f6sterreich",
    "sg:tags":[
        "chemical",
        "pharmaceutical"
    ],
    "wof:name":"EBEWE PHARMA GESMBH NFG KG",
    "wof:placetype":"venue"
},
  "geometry": {"coordinates":[13.4797582626,47.8017272949],"type":"Point"}
}