{
  "type": "Feature",
  "properties": {
    "addr:full":"Innsbrucker Str 20 Seefeld in Tirol Tirol 6100",
    "addr:housenumber":"20",
    "addr:postcode":"6100",
    "addr:street":"Str;Tirol",
    "iso:country":"AT",
    "sg:address":"Innsbrucker Str 20",
    "sg:city":"Seefeld in Tirol",
    "sg:orig_category":"Holzschnitzereien",
    "sg:phone":"+43 5212 3471",
    "sg:postcode":"6100",
    "sg:province":"Tirol",
    "wof:name":"Holzschnitzerei Lorenz KEG",
    "wof:placetype":"venue"
},
  "geometry": {"coordinates":[11.1876659393,47.3281593323],"type":"Point"}
}