{
  "type": "Feature",
  "properties": {
    "iso:country":"AT",
    "sg:address":"Marktg. 5 ",
    "sg:city":"Feldkirch",
    "sg:classifiers":[
        {
            "category":"Communications",
            "subcategory":"Television Station",
            "type":"Services"
        }
    ],
    "sg:phone":"+43 4355 22720010",
    "sg:postcode":"6800",
    "sg:province":"Vorarlberg",
    "sg:tags":[
        "audio-visual"
    ],
    "wof:name":"LAMBERT FUNKBERATER GMBH",
    "wof:placetype":"venue"
},
  "geometry": {"coordinates":[9.5967845917,47.2381515503],"type":"Point"}
}