{
  "type": "Feature",
  "properties": {
    "iso:country":"AT",
    "sg:address":"Nr 22",
    "sg:city":"Maria Saal",
    "sg:orig_category":"Friseure U Frisiersalons",
    "sg:phone":"+43 4342 233308",
    "sg:postcode":"9063",
    "sg:province":"K\u00e4rnten",
    "wof:name":"Sauter Silvia",
    "wof:placetype":"venue"
},
  "geometry": {"coordinates":[14.3471212387,46.6808509827],"type":"Point"}
}