{
  "type": "Feature",
  "properties": {
    "iso:country":"AT",
    "sg:address":"Ehlergasse 16",
    "sg:city":"Graz",
    "sg:classifiers":[
        {
            "category":"Manufacturing",
            "subcategory":"Motor Vehicles & Parts",
            "type":"Manufacturing & Wholesale Goods"
        }
    ],
    "sg:phone":"+43 316 323091",
    "sg:postcode":"8010",
    "sg:province":"Steiermark",
    "sg:tags":[
        "bent",
        "strip"
    ],
    "sg:website":"leitnermarketing.at",
    "wof:name":"Leitner Marketing Dipl.-Ing. Franz J\u00f6rg Leitner",
    "wof:placetype":"venue"
},
  "geometry": {"coordinates":[15.4605007172,47.0730285645],"type":"Point"}
}