{
  "type": "Feature",
  "properties": {
    "iso:country":"AT",
    "sg:address":"Wiener Strasse 15a",
    "sg:city":"Wolkersdorf im Weinviertel",
    "sg:classifiers":[
        {
            "category":"Home & Garden",
            "subcategory":"Hardware",
            "type":"Retail Goods"
        }
    ],
    "sg:phone":"+43 2245 24410",
    "sg:postcode":"2120",
    "sg:province":"Nieder\u00f6sterreich",
    "sg:tags":[
        "steel",
        "banister"
    ],
    "sg:website":"strehwitzer.at",
    "wof:name":"Metallbau Strehwitzer Inh. Gerald u. Marius Strehwitzer",
    "wof:placetype":"venue"
},
  "geometry": {"coordinates":[16.5133876801,48.3823661804],"type":"Point"}
}