{
  "type": "Feature",
  "properties": {
    "iso:country":"AT",
    "sg:address":"Kalkofenweg 24",
    "sg:city":"Innsbruck",
    "sg:orig_category":"Filmproduktionen",
    "sg:phone":"+43 512 2638270",
    "sg:postcode":"6020",
    "sg:province":"Tirol",
    "sg:website":"filmatelier.at",
    "wof:name":"Filmatelier Fahrngruber & Slavik OEG",
    "wof:placetype":"venue"
},
  "geometry": {"coordinates":[11.4240665436,47.2833366394],"type":"Point"}
}