{
  "type": "Feature",
  "properties": {
    "addr:full":"Breitwiesergutstr 38 Linz Ober\u00f6sterreich 4020",
    "addr:housenumber":"38",
    "addr:postcode":"4020",
    "addr:street":"Breitwiesergutstr",
    "iso:country":"AT",
    "sg:address":"Breitwiesergutstr 38",
    "sg:city":"Linz",
    "sg:classifiers":[
        {
            "category":"Organizations",
            "subcategory":"Community Association",
            "type":"Services"
        }
    ],
    "sg:phone":"+43 732 717671",
    "sg:postcode":"4020",
    "sg:province":"Ober\u00f6sterreich",
    "sg:tags":[
        "relation",
        "public"
    ],
    "wof:name":"Grazi Manuela - Korrekturlesen",
    "wof:placetype":"venue"
},
  "geometry": {"coordinates":[14.2945995331,48.2843208313],"type":"Point"}
}