{
  "type": "Feature",
  "properties": {
    "iso:country":"AT",
    "sg:address":"Langobardenstrasse 12",
    "sg:city":"Wien",
    "sg:orig_category":"Furniture, General",
    "sg:phone":"+43 1 2804357",
    "sg:postcode":"1220",
    "sg:province":"Wien",
    "wof:name":"Josef Swoboda",
    "wof:placetype":"venue"
},
  "geometry": {"coordinates":[16.4534740448,48.2251358032],"type":"Point"}
}