{
  "type": "Feature",
  "properties": {
    "iso:country":"AT",
    "sg:address":"Engelweingartenstr 52",
    "sg:city":"Stainz",
    "sg:orig_category":"Isolierungen",
    "sg:phone":"+43 3463 2669",
    "sg:postcode":"8510",
    "sg:province":"Steiermark",
    "wof:name":"Schautz Wolfgang",
    "wof:placetype":"venue"
},
  "geometry": {"coordinates":[15.2464580536,46.8942108154],"type":"Point"}
}