{
  "type": "Feature",
  "properties": {
    "addr:full":"Siegelg 6/15 Wien Wien 1030",
    "addr:housenumber":"6 / 15",
    "addr:postcode":"1030",
    "addr:street":"Siegelg",
    "iso:country":"AT",
    "sg:address":"Siegelg 6/15",
    "sg:city":"Wien",
    "sg:orig_category":"Tonstudios",
    "sg:phone":"+43 1 9135614",
    "sg:postcode":"1030",
    "sg:province":"Wien",
    "wof:name":"ToneZone Music Department",
    "wof:placetype":"venue"
},
  "geometry": {"coordinates":[16.3915367126,48.2036857605],"type":"Point"}
}