{
  "type": "Feature",
  "properties": {
    "addr:full":"Claudiaschl\u00f6\u00dfl Kramsach Tirol 6233",
    "addr:postcode":"6233",
    "addr:street":"Claudiaschloessl;Tirol",
    "iso:country":"AT",
    "sg:address":"Claudiaschl\u00f6\u00dfl",
    "sg:city":"Kramsach",
    "sg:orig_category":"Weiterbildungsinstitute M Allg U Berufl Bildungsangebot",
    "sg:phone":"+43 4353 37629620",
    "sg:postcode":"6233",
    "sg:province":"Tirol",
    "wof:name":"Gamper mindSystems",
    "wof:placetype":"venue"
},
  "geometry": {"coordinates":[11.8835477829,47.4473342896],"type":"Point"}
}