{
  "type": "Feature",
  "properties": {
    "addr:full":"Carl-Zuckmayer-Str 37 Salzburg Salzburg 5020",
    "addr:housenumber":"37",
    "addr:postcode":"5020",
    "addr:street":"Carl-Zuckmayer-Str;Salzburg",
    "iso:country":"AT",
    "sg:address":"Carl-Zuckmayer-Str 37",
    "sg:city":"Salzburg",
    "sg:orig_category":"Bekleidung / Erzeugung U Gro\u00c3\u0178handel",
    "sg:phone":"+43 4366 2453406",
    "sg:postcode":"5020",
    "sg:province":"Salzburg",
    "wof:name":"Grebe Gunther",
    "wof:placetype":"venue"
},
  "geometry": {"coordinates":[13.0587177277,47.830039978],"type":"Point"}
}