{
  "type": "Feature",
  "properties": {
    "addr:full":"Siget 1 Hornstein Burgenland 7053",
    "addr:housenumber":"1",
    "addr:postcode":"7053",
    "addr:street":"Siget",
    "iso:country":"AT",
    "sg:address":"Siget 1",
    "sg:city":"Hornstein",
    "sg:orig_category":"Tischlereien",
    "sg:phone":"+43 2689 2274",
    "sg:postcode":"7053",
    "sg:province":"Burgenland",
    "wof:name":"Sindelar GesmbH",
    "wof:placetype":"venue"
},
  "geometry": {"coordinates":[16.442527771,47.8790092468],"type":"Point"}
}