{
  "type": "Feature",
  "properties": {
    "addr:full":"Koglerstr. 8 Sieghartskirchen Nieder\u00f6sterreich 3443",
    "addr:housenumber":"8",
    "addr:postcode":"3443",
    "addr:street":"Koglerstr.;Niederoesterreich",
    "iso:country":"AT",
    "sg:address":"Koglerstr. 8",
    "sg:city":"Sieghartskirchen",
    "sg:classifiers":[
        {
            "category":"Farming",
            "subcategory":"Livestock Farm",
            "type":"Manufacturing & Wholesale Goods"
        }
    ],
    "sg:phone":"+43 4322 746081",
    "sg:postcode":"3443",
    "sg:province":"Nieder\u00f6sterreich",
    "sg:tags":[
        "agriculture"
    ],
    "wof:name":"FLEISCHWAREN BERGER GMBH & CO. KG",
    "wof:placetype":"venue"
},
  "geometry": {"coordinates":[16.0137691498,48.2542724609],"type":"Point"}
}