{
  "type": "Feature",
  "properties": {
    "addr:full":"Eduard-Klein-G 11 Wien Wien 1130",
    "addr:housenumber":"11",
    "addr:postcode":"1130",
    "addr:street":"Eduard-Klein-G",
    "iso:country":"AT",
    "sg:address":"Eduard-Klein-G 11",
    "sg:city":"Wien",
    "sg:orig_category":"Steuerberatung",
    "sg:phone":"+43 4318 7756960",
    "sg:postcode":"1130",
    "sg:province":"Wien",
    "wof:name":"Hopf Reinhardt Dkfm Dr",
    "wof:placetype":"venue"
},
  "geometry": {"coordinates":[16.3017158508,48.1876449585],"type":"Point"}
}