{
  "type": "Feature",
  "properties": {
    "addr:full":"Nr 90 F\u00fcgen Tirol 6263",
    "addr:postcode":"6263",
    "addr:street":"Nr 90 Fuegen Tirol",
    "iso:country":"AT",
    "sg:address":"Nr 90",
    "sg:city":"F\u00fcgen",
    "sg:orig_category":"Bauunternehmen",
    "sg:phone":"+43 5288 632000",
    "sg:postcode":"6263",
    "sg:province":"Tirol",
    "wof:name":"Wohnbau Schultz GesmbH & Co KG",
    "wof:placetype":"venue"
},
  "geometry": {"coordinates":[11.8493213654,47.3472557068],"type":"Point"}
}