{
  "type": "Feature",
  "properties": {
    "iso:country":"AT",
    "sg:address":"Lamezanstr. 13 ",
    "sg:classifiers":[
        {
            "category":"Shopping",
            "subcategory":"Crafts & Fabrics",
            "type":"Retail Goods"
        }
    ],
    "sg:phone":"+43 4316 165548",
    "sg:postcode":"1232",
    "wof:name":"OTTO FLEMMICH KG",
    "wof:placetype":"venue"
},
  "geometry": {"coordinates":[16.3392181396,48.1390686035],"type":"Point"}
}