{
  "type": "Feature",
  "properties": {
    "iso:country":"AT",
    "sg:address":"Bahnhofstr 38",
    "sg:city":"Feldkirchen in K\u00e4rnten",
    "sg:orig_category":"Tabaktrafiken",
    "sg:phone":"+43 4342 762722",
    "sg:postcode":"9560",
    "sg:province":"K\u00e4rnten",
    "wof:name":"Scheiber Stefan",
    "wof:placetype":"venue"
},
  "geometry": {"coordinates":[14.0960092545,46.7224807739],"type":"Point"}
}