{
  "type": "Feature",
  "properties": {
    "iso:country":"AT",
    "sg:address":"Jubil\u00e4umsstrasse 4",
    "sg:city":"Purgstall an der Erlauf",
    "sg:classifiers":[
        {
            "category":"Tea Room",
            "subcategory":"None",
            "type":"Food & Drink"
        }
    ],
    "sg:phone":"+43 7489 2288",
    "sg:postcode":"3251",
    "sg:province":"Nieder\u00f6sterreich",
    "sg:tags":[
        "dining",
        "suite"
    ],
    "wof:name":"Herbert Pils",
    "wof:placetype":"venue"
},
  "geometry": {"coordinates":[15.1385478973,48.0590858459],"type":"Point"}
}