{
  "type": "Feature",
  "properties": {
    "addr:full":"Nr 32 Riegersburg Steiermark 8333",
    "addr:postcode":"8333",
    "addr:street":"Nr",
    "iso:country":"AT",
    "sg:address":"Nr 32",
    "sg:city":"Riegersburg",
    "sg:orig_category":"Non-Classified Establishments",
    "sg:phone":"+43 3153 82220",
    "sg:postcode":"8333",
    "sg:province":"Steiermark",
    "wof:name":"Pfarramt",
    "wof:placetype":"venue"
},
  "geometry": {"coordinates":[15.9359292984,47.0007858276],"type":"Point"}
}