{
  "type": "Feature",
  "properties": {
    "iso:country":"AT",
    "sg:address":"Wehrgraben 2",
    "sg:city":"Lustenau",
    "sg:orig_category":"Handelsagenturen",
    "sg:phone":"+43 4355 7782070",
    "sg:postcode":"6890",
    "sg:province":"Vorarlberg",
    "wof:name":"Grahammer Textilagentur GmbH & Co KEG",
    "wof:placetype":"venue"
},
  "geometry": {"coordinates":[9.6578016281,47.4071311951],"type":"Point"}
}