{
  "type": "Feature",
  "properties": {
    "addr:full":"Annaberg 58 Annaberg Salzburg 5524",
    "addr:housenumber":"58",
    "addr:postcode":"5524",
    "addr:street":"Annaberg;Salzburg",
    "iso:country":"AT",
    "sg:address":"Annaberg 58",
    "sg:city":"Annaberg",
    "sg:classifiers":[
        {
            "category":"Building & Trades",
            "subcategory":"Plumbing",
            "type":"Services"
        }
    ],
    "sg:phone":"+43 6463 8153",
    "sg:postcode":"5524",
    "sg:province":"Salzburg",
    "sg:tags":[
        "supraregional",
        "gas"
    ],
    "sg:website":"schwaighofer-angerer.at",
    "wof:name":"Schwaighofer-Angerer Haustechnik u. BedachungsgesmbH",
    "wof:placetype":"venue"
},
  "geometry": {"coordinates":[13.4313211441,47.5240020752],"type":"Point"}
}