{
  "type": "Feature",
  "properties": {
    "addr:full":"Herrenholzg 2 Wien Wien 1210",
    "addr:housenumber":"2",
    "addr:postcode":"1210",
    "addr:street":"Herrenholzg",
    "iso:country":"AT",
    "sg:address":"Herrenholzg 2",
    "sg:city":"Wien",
    "sg:orig_category":"Maler, Anstreicher U Lackierer",
    "sg:phone":"+43 4312 922033",
    "sg:postcode":"1210",
    "sg:province":"Wien",
    "wof:name":"MAB Maler Anstreicher BetriebsgesmbH",
    "wof:placetype":"venue"
},
  "geometry": {"coordinates":[16.418466568,48.2964324951],"type":"Point"}
}