{
  "type": "Feature",
  "properties": {
    "iso:country":"AT",
    "sg:address":"Sommersgut 13",
    "sg:city":"Wenigzell",
    "sg:classifiers":[
        {
            "category":"Manufacturing",
            "subcategory":"Wood Products",
            "type":"Manufacturing & Wholesale Goods"
        }
    ],
    "sg:phone":"+43 3336 25000",
    "sg:postcode":"8254",
    "sg:province":"Steiermark",
    "sg:tags":[
        "installation",
        "sawmill"
    ],
    "sg:website":"mayrhofer-gmbh.at",
    "wof:name":"Mayrhofer Ges.m.b.H.",
    "wof:placetype":"venue"
},
  "geometry": {"coordinates":[15.7862663269,47.4562797546],"type":"Point"}
}