{
  "type": "Feature",
  "properties": {
    "addr:full":"Seitenstetter Str 7 Mauerbach Nieder\u00f6sterreich 3001",
    "addr:housenumber":"7",
    "addr:postcode":"3001",
    "addr:street":"Str",
    "iso:country":"AT",
    "sg:address":"Seitenstetter Str 7",
    "sg:city":"Mauerbach",
    "sg:orig_category":"Tai Chi, Tai Chi Chuan U Qi Gong",
    "sg:phone":"+43 4322 737784",
    "sg:postcode":"3001",
    "sg:province":"Nieder\u00f6sterreich",
    "wof:name":"Qigong Yangsheng Elfriede Bartel - Sportunion",
    "wof:placetype":"venue"
},
  "geometry": {"coordinates":[16.1548061371,48.274055481],"type":"Point"}
}