{
  "type": "Feature",
  "properties": {
    "iso:country":"AT",
    "sg:address":"Lamezanstr 10",
    "sg:city":"Wien",
    "sg:orig_category":"Reproanstalten, Werbegrafik- U Grafik-Design, Werbegestalter",
    "sg:phone":"+43 1 86545420",
    "sg:postcode":"1230",
    "sg:province":"Wien",
    "sg:website":"www.eurografik.net",
    "wof:name":"EUROGRAFIK - NEW MEDIA",
    "wof:placetype":"venue"
},
  "geometry": {"coordinates":[16.3390102386,48.1395339966],"type":"Point"}
}