{
  "type": "Feature",
  "properties": {
    "iso:country":"AT",
    "sg:address":"Satzg 16",
    "sg:city":"Neusiedl am See",
    "sg:orig_category":"Medizinische Institute",
    "sg:phone":"+43 2167 80815",
    "sg:postcode":"7100",
    "sg:province":"Burgenland",
    "wof:name":"Marathon Institut f Sportmedizin",
    "wof:placetype":"venue"
},
  "geometry": {"coordinates":[16.8481502533,47.9480323792],"type":"Point"}
}