{
  "type": "Feature",
  "properties": {
    "addr:full":"Brunner Str 45 Waidhofen an der Thaya Nieder\u00f6sterreich 3830",
    "addr:postcode":"3830",
    "addr:street":"Str 45",
    "iso:country":"AT",
    "sg:address":"Brunner Str 45",
    "sg:city":"Waidhofen an der Thaya",
    "sg:orig_category":"Autohandel",
    "sg:phone":"+43 4328 42526830",
    "sg:postcode":"3830",
    "sg:province":"Nieder\u00f6sterreich",
    "wof:name":"Zuwach Franz",
    "wof:placetype":"venue"
},
  "geometry": {"coordinates":[15.2659778595,48.8117027283],"type":"Point"}
}