{
  "type": "Feature",
  "properties": {
    "addr:full":"Hauensteiner Str 15 Zwettl Nieder\u00f6sterreich 3910",
    "addr:postcode":"3910",
    "addr:street":"Str 15",
    "iso:country":"AT",
    "sg:address":"Hauensteiner Str 15",
    "sg:city":"Zwettl",
    "sg:orig_category":"Familien / Beratung",
    "sg:phone":"+43 2822 54222101",
    "sg:postcode":"3910",
    "sg:province":"Nieder\u00f6sterreich",
    "wof:name":"Hilfswerk Zentrum f Beratung & Begleitung",
    "wof:placetype":"venue"
},
  "geometry": {"coordinates":[15.1681003571,48.6041564941],"type":"Point"}
}