{
  "type": "Feature",
  "properties": {
    "addr:full":"Hatlerstr 27 Dornbirn Vorarlberg 6850",
    "addr:housenumber":"27",
    "addr:postcode":"6850",
    "addr:street":"Hatlerstr",
    "iso:country":"AT",
    "sg:address":"Hatlerstr 27",
    "sg:city":"Dornbirn",
    "sg:orig_category":"Autohandel",
    "sg:phone":"+43 4355 72220940",
    "sg:postcode":"6850",
    "sg:province":"Vorarlberg",
    "wof:name":"Winder Ludwig - Inh Gerhard Winder",
    "wof:placetype":"venue"
},
  "geometry": {"coordinates":[9.7377328873,47.4017372131],"type":"Point"}
}