{
  "type": "Feature",
  "properties": {
    "addr:full":"J\u00e4gerstrasse 33 Wien Wien 1200",
    "addr:housenumber":"33",
    "addr:postcode":"1200",
    "addr:street":"Jaegerstrasse",
    "iso:country":"AT",
    "sg:address":"J\u00e4gerstrasse 33",
    "sg:city":"Wien",
    "sg:classifiers":[
        {
            "category":"Wholesale",
            "subcategory":"Metals & Minerals",
            "type":"Manufacturing & Wholesale Goods"
        }
    ],
    "sg:phone":"+43 1 3329013",
    "sg:postcode":"1200",
    "sg:province":"Wien",
    "sg:tags":[
        "dental",
        "gold"
    ],
    "sg:website":"aesthetik-dental.at",
    "wof:name":"\u00c4sthetik Dental Zahntechnisches Labor Josef Kozarits GmbH",
    "wof:placetype":"venue"
},
  "geometry": {"coordinates":[16.3706951141,48.2303161621],"type":"Point"}
}