{
  "type": "Feature",
  "properties": {
    "iso:country":"AT",
    "sg:address":"Passauer Str 16",
    "sg:city":"Peuerbach",
    "sg:orig_category":"Steinmetzbetriebe",
    "sg:phone":"+43 7276 23240",
    "sg:postcode":"4722",
    "sg:province":"Ober\u00f6sterreich",
    "wof:name":"Oberschmidleithner GmbH & Co KG",
    "wof:placetype":"venue"
},
  "geometry": {"coordinates":[13.7690944672,48.3465881348],"type":"Point"}
}