{
  "type": "Feature",
  "properties": {
    "addr:full":"Grazer Vorstadt 37 Voitsberg Steiermark 8570",
    "addr:housenumber":"37",
    "addr:postcode":"8570",
    "addr:street":"Grazer Vorstadt",
    "iso:country":"AT",
    "sg:address":"Grazer Vorstadt 37",
    "sg:city":"Voitsberg",
    "sg:orig_category":"Tabaktrafiken",
    "sg:phone":"+43 3142 24034",
    "sg:postcode":"8570",
    "sg:province":"Steiermark",
    "wof:name":"Steinacher Herbert",
    "wof:placetype":"venue"
},
  "geometry": {"coordinates":[15.1590232849,47.044960022],"type":"Point"}
}