{
  "type": "Feature",
  "properties": {
    "iso:country":"AT",
    "sg:address":"Landstra\u00dfer Hauptstr 92-94",
    "sg:city":"Wien",
    "sg:orig_category":"Boutiquen",
    "sg:phone":"+43 1 7121032",
    "sg:postcode":"1030",
    "sg:province":"Wien",
    "wof:name":"da Susanna",
    "wof:placetype":"venue"
},
  "geometry": {"coordinates":[16.3939571381,48.1992721558],"type":"Point"}
}