{
  "type": "Feature",
  "properties": {
    "iso:country":"AT",
    "sg:address":"Gerberg 3",
    "sg:city":"Villach",
    "sg:orig_category":"Farben U Lacke / Einzelhandel",
    "sg:phone":"+43 4242 24514",
    "sg:postcode":"9500",
    "sg:province":"K\u00e4rnten",
    "wof:name":"Somma Andreas",
    "wof:placetype":"venue"
},
  "geometry": {"coordinates":[13.8480520248,46.6148872375],"type":"Point"}
}