{
  "type": "Feature",
  "properties": {
    "addr:full":"Treustrasse 57 Wien Wien 1200",
    "addr:housenumber":"57",
    "addr:postcode":"1200",
    "addr:street":"Treustrasse",
    "iso:country":"AT",
    "sg:address":"Treustrasse 57",
    "sg:city":"Wien",
    "sg:classifiers":[
        {
            "category":"Wholesale",
            "subcategory":"Vending Machines",
            "type":"Manufacturing & Wholesale Goods"
        }
    ],
    "sg:phone":"+43 1 3304890",
    "sg:postcode":"1200",
    "sg:province":"Wien",
    "sg:tags":[
        "packing",
        "automatic",
        "machines"
    ],
    "wof:name":"Graphipack Maschinenhandel Ges.m.b.H.",
    "wof:placetype":"venue"
},
  "geometry": {"coordinates":[16.3638801575,48.2319488525],"type":"Point"}
}