{
  "type": "Feature",
  "properties": {
    "addr:full":"Haunspergstr 1 Oberalm Salzburg 5411",
    "addr:housenumber":"1",
    "addr:postcode":"5411",
    "addr:street":"Haunspergstr;Salzburg",
    "iso:country":"AT",
    "sg:address":"Haunspergstr 1",
    "sg:city":"Oberalm",
    "sg:orig_category":"Transportunternehmen",
    "sg:phone":"+43 6245 72275",
    "sg:postcode":"5411",
    "sg:province":"Salzburg",
    "wof:name":"CARTRANS GmbH & Co KG",
    "wof:placetype":"venue"
},
  "geometry": {"coordinates":[13.1011943817,47.6953926086],"type":"Point"}
}