{
  "type": "Feature",
  "properties": {
    "iso:country":"AT",
    "sg:address":"Bahnhofstr 15",
    "sg:city":"Wels",
    "sg:orig_category":"Farben U Lacke / Erzeugung U Gro\u00c3\u0178handel",
    "sg:phone":"+43 7242 45663",
    "sg:postcode":"4600",
    "sg:province":"Ober\u00f6sterreich",
    "wof:name":"Christ Ludwig & Co GesmbH",
    "wof:placetype":"venue"
},
  "geometry": {"coordinates":[14.0247812271,48.1619949341],"type":"Point"}
}