{
  "type": "Feature",
  "properties": {
    "iso:country":"AT",
    "sg:address":"Julius Tandler-Pl 10",
    "sg:city":"Wien",
    "sg:orig_category":"Apotheken",
    "sg:phone":"+43 1 31752110",
    "sg:postcode":"1090",
    "sg:province":"Wien",
    "wof:name":"Bahnhof-Apotheke Mag pharm K T\u00fcrk und Magpharm Ingrid Zeidler",
    "wof:placetype":"venue"
},
  "geometry": {"coordinates":[16.3609027863,48.2252922058],"type":"Point"}
}