{
  "type": "Feature",
  "properties": {
    "addr:full":"Quadenstr 8/5/4 Wien Wien 1220",
    "addr:housenumber":"8 / 5 / 4",
    "addr:postcode":"1220",
    "addr:street":"Quadenstr",
    "iso:country":"AT",
    "sg:address":"Quadenstr 8/5/4",
    "sg:city":"Wien",
    "sg:orig_category":"Industriereinigung",
    "sg:phone":"+43 4367 63037088",
    "sg:postcode":"1220",
    "sg:province":"Wien",
    "wof:name":"\u00f6lreinigung GmbH - Tankstellenreinigung",
    "wof:placetype":"venue"
},
  "geometry": {"coordinates":[16.444606781,48.2497138977],"type":"Point"}
}