{
  "type": "Feature",
  "properties": {
    "addr:full":"Hauptstr 15 St. Marein im M\u00fcrztal Steiermark 8641",
    "addr:housenumber":"15",
    "addr:postcode":"8641",
    "addr:street":"Hauptstr",
    "iso:country":"AT",
    "sg:address":"Hauptstr 15",
    "sg:city":"St. Marein im M\u00fcrztal",
    "sg:orig_category":"Juweliere, Gold- U Silberschmiede",
    "sg:phone":"+43 4338 6422250",
    "sg:postcode":"8641",
    "sg:province":"Steiermark",
    "wof:name":"Lackner Andrea",
    "wof:placetype":"venue"
},
  "geometry": {"coordinates":[15.3697481155,47.4740409851],"type":"Point"}
}