{
  "type": "Feature",
  "properties": {
    "addr:full":"Sternwartestr 84/2 Wien Wien 1180",
    "addr:housenumber":"84 / 2",
    "addr:postcode":"1180",
    "addr:street":"Sternwartestr",
    "iso:country":"AT",
    "sg:address":"Sternwartestr 84/2",
    "sg:city":"Wien",
    "sg:orig_category":"Psychotherapie",
    "sg:phone":"+43 1 9475144",
    "sg:postcode":"1180",
    "sg:province":"Wien",
    "wof:name":"Herzog Johannes Ferdinand Dr",
    "wof:placetype":"venue"
},
  "geometry": {"coordinates":[16.3305969238,48.2328872681],"type":"Point"}
}