{
  "type": "Feature",
  "properties": {
    "addr:full":"Langenloiser Str 180 Krems an der Donau Nieder\u00f6sterreich 3500",
    "addr:housenumber":"180",
    "addr:postcode":"3500",
    "iso:country":"AT",
    "sg:address":"Langenloiser Str 180",
    "sg:city":"Krems an der Donau",
    "sg:orig_category":"Innenarchitekten",
    "sg:phone":"+43 2732 748330",
    "sg:postcode":"3500",
    "sg:province":"Nieder\u00f6sterreich",
    "wof:name":"Fuchs Leopold Ing",
    "wof:placetype":"venue"
},
  "geometry": {"coordinates":[15.6159801483,48.4314498901],"type":"Point"}
}