{
  "type": "Feature",
  "properties": {
    "addr:full":"Draschestr 88 Wien Wien 1230",
    "addr:housenumber":"88",
    "addr:postcode":"1230",
    "addr:street":"Draschestr",
    "iso:country":"AT",
    "sg:address":"Draschestr 88",
    "sg:city":"Wien",
    "sg:orig_category":"Medizintechnik",
    "sg:phone":"+43 1 6060580",
    "sg:postcode":"1230",
    "sg:province":"Wien",
    "wof:name":"Atomed Handelsgesellschaft mbH",
    "wof:placetype":"venue"
},
  "geometry": {"coordinates":[16.3503475189,48.149105072],"type":"Point"}
}