{
  "type": "Feature",
  "properties": {
    "addr:full":"Pfarrplatz 3 Freistadt Ober\u00f6sterreich 4240",
    "addr:housenumber":"3",
    "addr:postcode":"4240",
    "addr:street":"Pfarrplatz",
    "iso:country":"AT",
    "sg:address":"Pfarrplatz 3",
    "sg:city":"Freistadt",
    "sg:classifiers":[
        {
            "category":"Professional",
            "subcategory":"Art Services",
            "type":"Services"
        }
    ],
    "sg:phone":"+43 7942 776440",
    "sg:postcode":"4240",
    "sg:province":"Ober\u00f6sterreich",
    "sg:tags":[
        "article",
        "design",
        "advertising"
    ],
    "sg:website":"mk-design.at",
    "wof:name":"M.K. Design",
    "wof:placetype":"venue"
},
  "geometry": {"coordinates":[14.5043563843,48.5108833313],"type":"Point"}
}