{
  "type": "Feature",
  "properties": {
    "addr:full":"Stifterstr 2 Traun Ober\u00f6sterreich 4050",
    "addr:housenumber":"2",
    "addr:postcode":"4050",
    "addr:street":"Stifterstr",
    "iso:country":"AT",
    "sg:address":"Stifterstr 2",
    "sg:city":"Traun",
    "sg:orig_category":"Tabaktrafiken",
    "sg:phone":"+43 7229 72458",
    "sg:postcode":"4050",
    "sg:province":"Ober\u00f6sterreich",
    "wof:name":"Lidlbauer Roswitha",
    "wof:placetype":"venue"
},
  "geometry": {"coordinates":[14.2612361908,48.2394561768],"type":"Point"}
}