{
  "type": "Feature",
  "properties": {
    "iso:country":"AT",
    "sg:address":"Villacher Str 8",
    "sg:city":"Klagenfurt",
    "sg:orig_category":"Apotheken",
    "sg:phone":"+43 463 56156",
    "sg:postcode":"9020",
    "sg:province":"K\u00e4rnten",
    "wof:name":"L\u00f6wen Apotheke",
    "wof:placetype":"venue"
},
  "geometry": {"coordinates":[14.3039197922,46.6217422485],"type":"Point"}
}