{
  "type": "Feature",
  "properties": {
    "addr:full":"Goethepl 1 Zwentendorf an der Donau Nieder\u00f6sterreich 3435",
    "addr:housenumber":"1",
    "addr:postcode":"3435",
    "addr:street":"Goethepl",
    "iso:country":"AT",
    "sg:address":"Goethepl 1",
    "sg:city":"Zwentendorf an der Donau",
    "sg:orig_category":"Hauptschulen",
    "sg:phone":"+43 4322 772230",
    "sg:postcode":"3435",
    "sg:province":"Nieder\u00f6sterreich",
    "wof:name":"Hauptschule",
    "wof:placetype":"venue"
},
  "geometry": {"coordinates":[15.9112949371,48.3451766968],"type":"Point"}
}