{
  "type": "Feature",
  "properties": {
    "addr:full":"Bergg 1 Stainz Steiermark 8510",
    "addr:housenumber":"1",
    "addr:postcode":"8510",
    "addr:street":"Bergg",
    "iso:country":"AT",
    "sg:address":"Bergg 1",
    "sg:city":"Stainz",
    "sg:orig_category":"Friseure U Frisiersalons",
    "sg:phone":"+43 3463 2281",
    "sg:postcode":"8510",
    "sg:province":"Steiermark",
    "wof:name":"Haarstudio IWS",
    "wof:placetype":"venue"
},
  "geometry": {"coordinates":[15.2653799057,46.8953361511],"type":"Point"}
}