{
  "type": "Feature",
  "properties": {
    "addr:full":"Unterer Auweg 15 Zams Tirol 6511",
    "addr:housenumber":"15",
    "addr:postcode":"6511",
    "addr:street":"Unterer Auweg;Tirol",
    "iso:country":"AT",
    "sg:address":"Unterer Auweg 15",
    "sg:city":"Zams",
    "sg:orig_category":"Reifen U Reifendienste",
    "sg:phone":"+43 4354 4268383",
    "sg:postcode":"6511",
    "sg:province":"Tirol",
    "wof:name":"Reifenservice GmbH",
    "wof:placetype":"venue"
},
  "geometry": {"coordinates":[10.5884380341,47.1549301147],"type":"Point"}
}