{
  "type": "Feature",
  "properties": {
    "iso:country":"AT",
    "sg:address":"Mirabellpl 10",
    "sg:city":"Salzburg",
    "sg:orig_category":"Medaillen",
    "sg:phone":"+43 662 873800",
    "sg:postcode":"5020",
    "sg:province":"Salzburg",
    "wof:name":"GFM Haus d Kunsteditionen GmbH",
    "wof:placetype":"venue"
},
  "geometry": {"coordinates":[13.0427856445,47.8055038452],"type":"Point"}
}