{
  "type": "Feature",
  "properties": {
    "iso:country":"AT",
    "sg:address":"Lieserhofer Str 17A",
    "sg:city":"Lieserbr\u00fccke",
    "sg:orig_category":"Abschleppdienste",
    "sg:phone":"+43 4762 2006",
    "sg:postcode":"9851",
    "sg:province":"K\u00e4rnten",
    "wof:name":"Lang GmbH",
    "wof:placetype":"venue"
},
  "geometry": {"coordinates":[13.4881229401,46.8275909424],"type":"Point"}
}