{
  "type": "Feature",
  "properties": {
    "addr:full":"Breyerstr 1 Baden Nieder\u00f6sterreich 2500",
    "addr:housenumber":"1",
    "addr:postcode":"2500",
    "addr:street":"Breyerstr;Niederoesterreich",
    "iso:country":"AT",
    "sg:address":"Breyerstr 1",
    "sg:city":"Baden",
    "sg:orig_category":"Optiker",
    "sg:phone":"+43 2252 21900",
    "sg:postcode":"2500",
    "sg:province":"Nieder\u00f6sterreich",
    "wof:name":"City Optiker GesmbH",
    "wof:placetype":"venue"
},
  "geometry": {"coordinates":[16.2355327606,48.0065422058],"type":"Point"}
}