{
  "type": "Feature",
  "properties": {
    "iso:country":"AT",
    "sg:address":"Obermarktstr 46",
    "sg:city":"Telfs",
    "sg:orig_category":"Bars-Cafes",
    "sg:phone":"+43 4366 44552056",
    "sg:postcode":"6410",
    "sg:province":"Tirol",
    "wof:name":"Bar PARADIES",
    "wof:placetype":"venue"
},
  "geometry": {"coordinates":[11.067076683,47.3085403442],"type":"Point"}
}