{
  "type": "Feature",
  "properties": {
    "addr:full":"Am Anger 2 Nu\u00dfdorf am Attersee Ober\u00f6sterreich 4865",
    "addr:housenumber":"2",
    "addr:postcode":"4865",
    "addr:street":"Am Anger",
    "iso:country":"AT",
    "sg:address":"Am Anger 2",
    "sg:city":"Nu\u00dfdorf am Attersee",
    "sg:orig_category":"Papier- U Schreibwaren / Einzelhandel",
    "sg:phone":"+43 4376 668061",
    "sg:postcode":"4865",
    "sg:province":"Ober\u00f6sterreich",
    "wof:name":"Kaufhaus Am Anger Thomas Sch\u00f6nberger",
    "wof:placetype":"venue"
},
  "geometry": {"coordinates":[13.5224399567,47.8828811646],"type":"Point"}
}