{
  "type": "Feature",
  "properties": {
    "iso:country":"AT",
    "sg:address":"Nr 10",
    "sg:city":"Kappel am Krappfeld",
    "sg:orig_category":"Volksschulen",
    "sg:phone":"+43 4342 622006",
    "sg:postcode":"9321",
    "sg:province":"K\u00e4rnten",
    "wof:name":"Volksschule",
    "wof:placetype":"venue"
},
  "geometry": {"coordinates":[14.4859771729,46.8383102417],"type":"Point"}
}