{
  "type": "Feature",
  "properties": {
    "addr:full":"Marktpl 25 Frankenburg am Hausruck Ober\u00f6sterreich 4873",
    "addr:housenumber":"25",
    "addr:postcode":"4873",
    "addr:street":"Marktpl",
    "iso:country":"AT",
    "sg:address":"Marktpl 25",
    "sg:city":"Frankenburg am Hausruck",
    "sg:orig_category":"Friseure U Frisiersalons",
    "sg:phone":"+43 4376 838730",
    "sg:postcode":"4873",
    "sg:province":"Ober\u00f6sterreich",
    "wof:name":"Hair Nova by Sabine",
    "wof:placetype":"venue"
},
  "geometry": {"coordinates":[13.4921274185,48.0678596497],"type":"Point"}
}