{
  "type": "Feature",
  "properties": {
    "addr:full":"Bahnhofstr 12 Vorchdorf Ober\u00f6sterreich 4655",
    "addr:postcode":"4655",
    "addr:street":"Bahnhofstr 12",
    "iso:country":"AT",
    "sg:address":"Bahnhofstr 12",
    "sg:city":"Vorchdorf",
    "sg:orig_category":"Friseure U Frisiersalons",
    "sg:phone":"+43 4376 146304",
    "sg:postcode":"4655",
    "sg:province":"Ober\u00f6sterreich",
    "wof:name":"Haarmode Isolde",
    "wof:placetype":"venue"
},
  "geometry": {"coordinates":[13.9209413528,48.0018081665],"type":"Point"}
}