{
  "type": "Feature",
  "properties": {
    "iso:country":"AT",
    "sg:city":"Mariahof",
    "sg:orig_category":"Paketdienste",
    "sg:phone":"+43 810 221188",
    "sg:postcode":"8812",
    "sg:province":"Steiermark",
    "wof:name":"\u00d6BB-G\u00fcterverkehr - Rail Cargo Austria",
    "wof:placetype":"venue"
},
  "geometry": {"coordinates":[14.3994102478,47.0992660522],"type":"Point"}
}