{
  "type": "Feature",
  "properties": {
    "iso:country":"AT",
    "sg:address":"Salurner Str 31",
    "sg:city":"Kufstein",
    "sg:orig_category":"Autohandel",
    "sg:phone":"+43 5372 62974",
    "sg:postcode":"6330",
    "sg:province":"Tirol",
    "wof:name":"Wendlinger Karl jun",
    "wof:placetype":"venue"
},
  "geometry": {"coordinates":[12.1621770859,47.577003479],"type":"Point"}
}