{
  "type": "Feature",
  "properties": {
    "iso:country":"AT",
    "sg:address":"Reinprechtsdorf Str 51/2",
    "sg:city":"Wien",
    "sg:orig_category":"Partyservice",
    "sg:phone":"+43 1 5452802",
    "sg:postcode":"1050",
    "sg:province":"Wien",
    "wof:name":"Rumino - Schmankerln - Buffet's Imbi\u00df Sandwiches aller Art",
    "wof:placetype":"venue"
},
  "geometry": {"coordinates":[16.3520431519,48.1875801086],"type":"Point"}
}