{
  "type": "Feature",
  "properties": {
    "addr:full":"Gewerbepark 6 Gramastetten Ober\u00f6sterreich 4201",
    "addr:housenumber":"6",
    "addr:postcode":"4201",
    "addr:street":"Gewerbepark",
    "iso:country":"AT",
    "sg:address":"Gewerbepark 6",
    "sg:city":"Gramastetten",
    "sg:orig_category":"Fenster",
    "sg:phone":"+43 7239 7031",
    "sg:postcode":"4201",
    "sg:province":"Ober\u00f6sterreich",
    "sg:website":"fenster-schmidinger.at",
    "wof:name":"Schmidinger Erich",
    "wof:placetype":"venue"
},
  "geometry": {"coordinates":[14.2142763138,48.3714866638],"type":"Point"}
}