{
  "type": "Feature",
  "properties": {
    "iso:country":"AT",
    "sg:address":"Nr 83",
    "sg:city":"St. Johann ob Hohenburg",
    "sg:orig_category":"Gemeinden",
    "sg:phone":"+43 4331 432251",
    "sg:postcode":"8565",
    "sg:province":"Steiermark",
    "wof:name":"Gemeinde St Johann-K\u00f6ppling",
    "wof:placetype":"venue"
},
  "geometry": {"coordinates":[15.2296304703,47.0087890625],"type":"Point"}
}