{
  "type": "Feature",
  "properties": {
    "addr:full":"Hauptstr 4 B\u00fcrs Vorarlberg 6706",
    "addr:housenumber":"4",
    "addr:postcode":"6706",
    "addr:street":"Hauptstr",
    "iso:country":"AT",
    "sg:address":"Hauptstr 4",
    "sg:city":"B\u00fcrs",
    "sg:orig_category":"Psychotherapie",
    "sg:phone":"+43 5552 66433",
    "sg:postcode":"6706",
    "sg:province":"Vorarlberg",
    "wof:name":"Praxis f Psychotherapie Sophia - Kraher Maria Angelika",
    "wof:placetype":"venue"
},
  "geometry": {"coordinates":[9.8089761734,47.1518325806],"type":"Point"}
}