{
  "type": "Feature",
  "properties": {
    "iso:country":"AT",
    "sg:address":"Dr.-Koss-Strasse 13a",
    "sg:city":"Wels",
    "sg:classifiers":[
        {
            "category":"Banks & Credit Unions",
            "subcategory":"Bureau De Change",
            "type":"Services"
        }
    ],
    "sg:phone":"+43 7242 43300",
    "sg:postcode":"4600",
    "sg:province":"Ober\u00f6sterreich",
    "sg:tags":[
        "flat",
        "construction",
        "roof"
    ],
    "wof:name":"G\u00fcnter Pointner",
    "wof:placetype":"venue"
},
  "geometry": {"coordinates":[14.0192146301,48.1597442627],"type":"Point"}
}