{
  "type": "Feature",
  "properties": {
    "iso:country":"AT",
    "sg:address":"Babenbergerstr 5",
    "sg:city":"Wien",
    "sg:classifiers":[
        {
            "category":"Restaurant",
            "type":"Food & Drink"
        }
    ],
    "sg:phone":"+43 1 5872206",
    "sg:postcode":"1010",
    "sg:province":"Wien",
    "sg:tags":[
        "pizzeria"
    ],
    "wof:name":"Pizzeria Der Babenberger",
    "wof:placetype":"venue"
},
  "geometry": {"coordinates":[16.3625068665,48.2030944824],"type":"Point"}
}