{
  "type": "Feature",
  "properties": {
    "addr:full":"Spitzesed 1 Obertrum am See Salzburg 5162",
    "addr:housenumber":"1",
    "addr:postcode":"5162",
    "addr:street":"Spitzesed;Salzburg",
    "iso:country":"AT",
    "sg:address":"Spitzesed 1",
    "sg:city":"Obertrum am See",
    "sg:orig_category":"Appartements / Ferienwohnungen",
    "sg:phone":"+43 4362 197357",
    "sg:postcode":"5162",
    "sg:province":"Salzburg",
    "wof:name":"Breitfuss Johann u Theresia",
    "wof:placetype":"venue"
},
  "geometry": {"coordinates":[13.0547647476,47.9443817139],"type":"Point"}
}