{
  "type": "Feature",
  "properties": {
    "addr:full":"Nr 36a Golling an der Salzach Salzburg 5440",
    "addr:postcode":"5440",
    "addr:street":"Nr 36A",
    "iso:country":"AT",
    "sg:address":"Nr 36a",
    "sg:city":"Golling an der Salzach",
    "sg:orig_category":"Forstverwaltungen",
    "sg:phone":"+43 4362 4420146",
    "sg:postcode":"5440",
    "sg:province":"Salzburg",
    "wof:name":"\u00f6sterreichische Bundesforste AG - Forstrevier Abtenau - Rl Johann Rehrl",
    "wof:placetype":"venue"
},
  "geometry": {"coordinates":[13.1678924561,47.5982322693],"type":"Point"}
}