{
  "type": "Feature",
  "properties": {
    "addr:full":"Schlo\u00dfg 8 Trumau Nieder\u00f6sterreich 2521",
    "addr:housenumber":"8",
    "addr:postcode":"2521",
    "addr:street":"Schlossg",
    "iso:country":"AT",
    "sg:address":"Schlo\u00dfg 8",
    "sg:city":"Trumau",
    "sg:orig_category":"Raumgestaltung",
    "sg:phone":"+43 2253 6234",
    "sg:postcode":"2521",
    "sg:province":"Nieder\u00f6sterreich",
    "wof:name":"Wohnst\u00fcberl Ing Kurt Kern",
    "wof:placetype":"venue"
},
  "geometry": {"coordinates":[16.3423233032,47.9932975769],"type":"Point"}
}