{
  "type": "Feature",
  "properties": {
    "addr:full":"Wilhelminenstr 52 Wien Wien 1160",
    "addr:housenumber":"52",
    "addr:postcode":"1160",
    "addr:street":"Wilhelminenstr",
    "iso:country":"AT",
    "sg:address":"Wilhelminenstr 52",
    "sg:city":"Wien",
    "sg:orig_category":"Autohandel",
    "sg:phone":"+43 1 48561110",
    "sg:postcode":"1160",
    "sg:province":"Wien",
    "sg:website":"www.yourcar.at",
    "wof:name":"AutohandelsgesmbH",
    "wof:placetype":"venue"
},
  "geometry": {"coordinates":[16.3140449524,48.2169761658],"type":"Point"}
}