{
  "type": "Feature",
  "properties": {
    "iso:country":"AT",
    "sg:address":"Kirchenpl 7",
    "sg:city":"Sierning",
    "sg:orig_category":"Fleisch-, Wurst- U Selchwaren / Erzeugung U Gro\u00c3\u0178handel",
    "sg:phone":"+43 4372 592124",
    "sg:postcode":"4522",
    "sg:province":"Ober\u00f6sterreich",
    "wof:name":"Forster Karl",
    "wof:placetype":"venue"
},
  "geometry": {"coordinates":[14.3103122711,48.0441436768],"type":"Point"}
}