{
  "type": "Feature",
  "properties": {
    "iso:country":"AT",
    "sg:address":"Glacisstr 25",
    "sg:city":"Graz",
    "sg:orig_category":"Antiquariate",
    "sg:phone":"+43 316 365305",
    "sg:postcode":"8010",
    "sg:province":"Steiermark",
    "wof:name":"Uni-Antiquariat Gerhard M Buchgraber",
    "wof:placetype":"venue"
},
  "geometry": {"coordinates":[15.4460353851,47.0752182007],"type":"Point"}
}