{
  "type": "Feature",
  "properties": {
    "addr:full":"Senefelderg 13 Wien Wien 1100",
    "addr:housenumber":"13",
    "addr:postcode":"1100",
    "addr:street":"Senefelderg",
    "iso:country":"AT",
    "sg:address":"Senefelderg 13",
    "sg:city":"Wien",
    "sg:orig_category":"Installationsunternehmen",
    "sg:phone":"+43 1 6042733",
    "sg:postcode":"1100",
    "sg:province":"Wien",
    "wof:name":"Kadecka Gottfried Ing",
    "wof:placetype":"venue"
},
  "geometry": {"coordinates":[16.3757705688,48.1761398315],"type":"Point"}
}