{
  "type": "Feature",
  "properties": {
    "iso:country":"AT",
    "sg:address":"Friedhofstr 28",
    "sg:city":"Schwertberg",
    "sg:orig_category":"Elektroinstallationsunternehmen",
    "sg:phone":"+43 7262 612280",
    "sg:postcode":"4311",
    "sg:province":"Ober\u00f6sterreich",
    "wof:name":"Elektro - Industrieanlagenbau GesmbH",
    "wof:placetype":"venue"
},
  "geometry": {"coordinates":[14.5838832855,48.2695732117],"type":"Point"}
}