{
  "type": "Feature",
  "properties": {
    "addr:full":"Nr 56 Gallneukirchen Ober\u00f6sterreich 4210",
    "addr:postcode":"4210",
    "addr:street":"Nr 56",
    "iso:country":"AT",
    "sg:address":"Nr 56",
    "sg:city":"Gallneukirchen",
    "sg:orig_category":"Unternehmensberatung",
    "sg:phone":"+43 7235 64065",
    "sg:postcode":"4210",
    "sg:province":"Ober\u00f6sterreich",
    "sg:website":"www.acquisa.at",
    "wof:name":"ACQUISA Management Design Brunhilde Schram KEG",
    "wof:placetype":"venue"
},
  "geometry": {"coordinates":[14.4160146713,48.3530960083],"type":"Point"}
}