{
  "type": "Feature",
  "properties": {
    "addr:full":"Dorfpl 10 Zell am Ziller Tirol 6280",
    "addr:housenumber":"10",
    "addr:postcode":"6280",
    "addr:street":"Dorfpl;Tirol",
    "iso:country":"AT",
    "sg:address":"Dorfpl 10",
    "sg:city":"Zell am Ziller",
    "sg:orig_category":"Friseure U Frisiersalons",
    "sg:phone":"+43 4352 822217",
    "sg:postcode":"6280",
    "sg:province":"Tirol",
    "wof:name":"Valentina's Haarstudio",
    "wof:placetype":"venue"
},
  "geometry": {"coordinates":[11.8810787201,47.2337417603],"type":"Point"}
}