{
  "type": "Feature",
  "properties": {
    "addr:full":"Neue G 6 Rechnitz Burgenland 7471",
    "addr:housenumber":"6",
    "addr:postcode":"7471",
    "addr:street":"Neue G",
    "iso:country":"AT",
    "sg:address":"Neue G 6",
    "sg:city":"Rechnitz",
    "sg:orig_category":"Sportpreise",
    "sg:phone":"+43 3363 79527",
    "sg:postcode":"7471",
    "sg:province":"Burgenland",
    "wof:name":"Hemetsberger Jakob",
    "wof:placetype":"venue"
},
  "geometry": {"coordinates":[16.4365177155,47.3028411865],"type":"Point"}
}