{
  "type": "Feature",
  "properties": {
    "addr:full":"Pacherg 12 Steyr Ober\u00f6sterreich 4400",
    "addr:housenumber":"12",
    "addr:postcode":"4400",
    "addr:street":"Pacherg;Oberoesterreich",
    "iso:country":"AT",
    "sg:address":"Pacherg 12",
    "sg:city":"Steyr",
    "sg:orig_category":"Fahrschulen",
    "sg:phone":"+43 7252 54366",
    "sg:postcode":"4400",
    "sg:province":"Ober\u00f6sterreich",
    "sg:website":"fahrschule-staudinger.at",
    "wof:name":"Fahrschule Staudinger",
    "wof:placetype":"venue"
},
  "geometry": {"coordinates":[14.4284715652,48.0414619446],"type":"Point"}
}