{
  "type": "Feature",
  "properties": {
    "addr:full":"Pfarrg 23 Imst Tirol 6460",
    "addr:housenumber":"23",
    "addr:postcode":"6460",
    "addr:street":"Pfarrg;Tirol",
    "iso:country":"AT",
    "sg:address":"Pfarrg 23",
    "sg:city":"Imst",
    "sg:classifiers":[
        {
            "category":"Internet Cafe",
            "subcategory":"None",
            "type":"Food & Drink"
        }
    ],
    "sg:phone":"+43 5412 68711",
    "sg:postcode":"6460",
    "sg:province":"Tirol",
    "wof:name":"KONTINENT 7 Jakob Miller",
    "wof:placetype":"venue"
},
  "geometry": {"coordinates":[10.739192009,47.2444992065],"type":"Point"}
}