{
  "type": "Feature",
  "properties": {
    "iso:country":"AT",
    "sg:address":"Nr 53",
    "sg:city":"Lainbach",
    "sg:orig_category":"Holzhandel",
    "sg:phone":"+43 4336 3321790",
    "sg:postcode":"8921",
    "sg:province":"Steiermark",
    "wof:name":"Klausbauer Holzindustrie GesmbH & Co KG",
    "wof:placetype":"venue"
},
  "geometry": {"coordinates":[14.7634248734,47.6528511047],"type":"Point"}
}