{
  "type": "Feature",
  "properties": {
    "iso:country":"AT",
    "sg:address":"Nr 36a",
    "sg:city":"Pertisau",
    "sg:orig_category":"Friseure U Frisiersalons",
    "sg:phone":"+43 4352 435364",
    "sg:postcode":"6213",
    "sg:province":"Tirol",
    "wof:name":"Friseur Helga GesmbH",
    "wof:placetype":"venue"
},
  "geometry": {"coordinates":[11.6961479187,47.4396896362],"type":"Point"}
}