{
  "type": "Feature",
  "properties": {
    "iso:country":"AT",
    "sg:address":"Lerchenstrasse 62",
    "sg:city":"Gnigl",
    "sg:classifiers":[
        {
            "category":"Organizations",
            "subcategory":"Labor Organization",
            "type":"Services"
        }
    ],
    "sg:phone":"+43 662 660559",
    "sg:postcode":"5023",
    "sg:province":"Salzburg",
    "sg:tags":[
        "profile",
        "bending",
        "work"
    ],
    "sg:website":"ellmauer-schlosserei.at",
    "wof:name":"Ellmauer & S\u00f6hne Schlosserei GesmbH",
    "wof:placetype":"venue"
},
  "geometry": {"coordinates":[13.0791215897,47.8252868652],"type":"Point"}
}