{
  "type": "Feature",
  "properties": {
    "iso:country":"AT",
    "sg:address":"H\u00f6raltstr 4",
    "sg:city":"Wattens",
    "sg:orig_category":"Volksschulen",
    "sg:phone":"+43 5224 52436",
    "sg:postcode":"6112",
    "sg:province":"Tirol",
    "wof:name":"Volksschule 2",
    "wof:placetype":"venue"
},
  "geometry": {"coordinates":[11.5881004333,47.2903900146],"type":"Point"}
}