{
  "type": "Feature",
  "properties": {
    "addr:full":"Dr Wilhelm Reich-Str 5 Melk Nieder\u00f6sterreich 3390",
    "addr:housenumber":"5",
    "addr:postcode":"3390",
    "addr:street":"Dr;Reich-Str",
    "iso:country":"AT",
    "sg:address":"Dr Wilhelm Reich-Str 5",
    "sg:city":"Melk",
    "sg:orig_category":"Politische Parteien",
    "sg:phone":"+43 2752 500360",
    "sg:postcode":"3390",
    "sg:province":"Nieder\u00f6sterreich",
    "wof:name":"\u00d6sterreichische Volkspartei (\u00d6VP)",
    "wof:placetype":"venue"
},
  "geometry": {"coordinates":[15.338968277,48.2255401611],"type":"Point"}
}