{
  "type": "Feature",
  "properties": {
    "addr:full":"Messestr 2 Einkaufszentrum Messepark Dornbirn Vorarlberg 6850",
    "addr:housenumber":"2",
    "addr:postcode":"6850",
    "addr:street":"Messestr;Messepark",
    "iso:country":"AT",
    "sg:address":"Messestr 2 Einkaufszentrum Messepark",
    "sg:city":"Dornbirn",
    "sg:orig_category":"Telekommunikation",
    "sg:phone":"+43 4355 7220202",
    "sg:postcode":"6850",
    "sg:province":"Vorarlberg",
    "wof:name":"tele.ring Telekom Service GmbH",
    "wof:placetype":"venue"
},
  "geometry": {"coordinates":[9.7437801361,47.4131889343],"type":"Point"}
}