{
  "type": "Feature",
  "properties": {
    "iso:country":"AT",
    "sg:address":"Holzbauernstr 20",
    "sg:city":"Traun",
    "sg:orig_category":"Automatisierungstechnik",
    "sg:phone":"+43 7229 74330",
    "sg:postcode":"4050",
    "sg:province":"Ober\u00f6sterreich",
    "wof:name":"Kabelschlepp \u00f6sterreich Robert Ganglberger",
    "wof:placetype":"venue"
},
  "geometry": {"coordinates":[14.2562494278,48.2269554138],"type":"Point"}
}