{
  "type": "Feature",
  "properties": {
    "addr:full":"Sigmund-Haffner-G 4 Salzburg Salzburg 5020",
    "addr:housenumber":"4",
    "addr:postcode":"5020",
    "addr:street":"Sigmund-Haffner-G;Salzburg",
    "iso:country":"AT",
    "sg:address":"Sigmund-Haffner-G 4",
    "sg:city":"Salzburg",
    "sg:classifiers":[
        {
            "category":"Travel",
            "subcategory":"Hotels & Motels",
            "type":"Entertainment"
        }
    ],
    "sg:phone":"+43 4366 28433970",
    "sg:postcode":"5020",
    "sg:province":"Salzburg",
    "sg:website":"elefant.at",
    "wof:name":"Hotel Elefant",
    "wof:placetype":"venue"
},
  "geometry": {"coordinates":[13.0443267822,47.7997703552],"type":"Point"}
}