{
  "type": "Feature",
  "properties": {
    "addr:full":"Jauerburgg 18 Graz Steiermark 8010",
    "addr:housenumber":"18",
    "addr:postcode":"8010",
    "addr:street":"Jauerburgg",
    "iso:country":"AT",
    "sg:address":"Jauerburgg 18",
    "sg:city":"Graz",
    "sg:orig_category":"Dachdeckereien",
    "sg:phone":"+43 316 4715710",
    "sg:postcode":"8010",
    "sg:province":"Steiermark",
    "sg:website":"spitzerdach.at",
    "wof:name":"Spitzer GesmbH",
    "wof:placetype":"venue"
},
  "geometry": {"coordinates":[15.4518604279,47.0515327454],"type":"Point"}
}