{
  "type": "Feature",
  "properties": {
    "addr:full":"Ischlerbahnstr 16 Thalgau Salzburg 5303",
    "addr:housenumber":"16",
    "addr:postcode":"5303",
    "addr:street":"Ischlerbahnstr;Salzburg",
    "iso:country":"AT",
    "sg:address":"Ischlerbahnstr 16",
    "sg:city":"Thalgau",
    "sg:orig_category":"Transportunternehmen",
    "sg:phone":"+43 676 7533911",
    "sg:postcode":"5303",
    "sg:province":"Salzburg",
    "wof:name":"Wendlinger Fritz Transport GesmbH",
    "wof:placetype":"venue"
},
  "geometry": {"coordinates":[13.2545089722,47.8433570862],"type":"Point"}
}