{
  "type": "Feature",
  "properties": {
    "addr:full":"Hauptstr. 69 Oberpullendorf Burgenland 7350",
    "addr:housenumber":"69",
    "addr:postcode":"7350",
    "addr:street":"Hauptstr.",
    "iso:country":"AT",
    "sg:address":"Hauptstr. 69",
    "sg:city":"Oberpullendorf",
    "sg:classifiers":[
        {
            "category":"Professional",
            "subcategory":"Business Services",
            "type":"Services"
        }
    ],
    "sg:phone":"+43 4326 1243642",
    "sg:postcode":"7350",
    "sg:province":"Burgenland",
    "sg:tags":[
        "advice"
    ],
    "wof:name":"BIO ERNTE AUSTRIA - BURGENLAND",
    "wof:placetype":"venue"
},
  "geometry": {"coordinates":[16.5072307587,47.4974021912],"type":"Point"}
}