{
  "type": "Feature",
  "properties": {
    "addr:full":"Untere Hauptstr 10 Gols Burgenland 7122",
    "addr:housenumber":"10",
    "addr:postcode":"7122",
    "addr:street":"Untere Hauptstr",
    "iso:country":"AT",
    "sg:address":"Untere Hauptstr 10",
    "sg:city":"Gols",
    "sg:orig_category":"Steuerberatung",
    "sg:phone":"+43 2173 31000",
    "sg:postcode":"7122",
    "sg:province":"Burgenland",
    "wof:name":"Priklopil Werner Dr",
    "wof:placetype":"venue"
},
  "geometry": {"coordinates":[16.910369873,47.8970489502],"type":"Point"}
}