{
  "type": "Feature",
  "properties": {
    "addr:full":"Marktstr 1 Grimmenstein Nieder\u00f6sterreich 2840",
    "addr:housenumber":"1",
    "addr:postcode":"2840",
    "addr:street":"Marktstr",
    "iso:country":"AT",
    "sg:address":"Marktstr 1",
    "sg:city":"Grimmenstein",
    "sg:orig_category":"Banken U Sparkassen",
    "sg:phone":"+43 2644 2230",
    "sg:postcode":"2840",
    "sg:province":"Nieder\u00f6sterreich",
    "wof:name":"Sparkasse Grimmenstein",
    "wof:placetype":"venue"
},
  "geometry": {"coordinates":[16.1247596741,47.6146087646],"type":"Point"}
}