{
  "type": "Feature",
  "properties": {
    "addr:full":"Angerg 18 Innsbruck Tirol 6020",
    "addr:housenumber":"18",
    "addr:postcode":"6020",
    "addr:street":"Angerg;Tirol",
    "iso:country":"AT",
    "sg:address":"Angerg 18",
    "sg:city":"Innsbruck",
    "sg:orig_category":"Volksschulen",
    "sg:phone":"+43 512 281772",
    "sg:postcode":"6020",
    "sg:province":"Tirol",
    "wof:name":"Volksschule",
    "wof:placetype":"venue"
},
  "geometry": {"coordinates":[11.368689537,47.2603492737],"type":"Point"}
}