{
  "type": "Feature",
  "properties": {
    "addr:full":"Untere Hauptstr 59 Illmitz Burgenland 7142",
    "addr:housenumber":"59",
    "addr:postcode":"7142",
    "addr:street":"Untere Hauptstr",
    "iso:country":"AT",
    "sg:address":"Untere Hauptstr 59",
    "sg:city":"Illmitz",
    "sg:orig_category":"Pensionen / Privatzimmer",
    "sg:phone":"+43 2175 2808",
    "sg:postcode":"7142",
    "sg:province":"Burgenland",
    "wof:name":"Weinbauernhof Fam Winkler",
    "wof:placetype":"venue"
},
  "geometry": {"coordinates":[16.7997684479,47.7578392029],"type":"Point"}
}