{
  "type": "Feature",
  "properties": {
    "addr:full":"Schlo\u00dfg 6 G\u00fcssing Burgenland 7540",
    "addr:housenumber":"6",
    "addr:postcode":"7540",
    "addr:street":"Schlossg",
    "iso:country":"AT",
    "sg:address":"Schlo\u00dfg 6",
    "sg:city":"G\u00fcssing",
    "sg:orig_category":"Elektroinstallationsunternehmen",
    "sg:phone":"+43 3322 423210",
    "sg:postcode":"7540",
    "sg:province":"Burgenland",
    "wof:name":"Elektro-G\u00fcssing GesmbH",
    "wof:placetype":"venue"
},
  "geometry": {"coordinates":[16.3274040222,47.0578231812],"type":"Point"}
}