{
  "type": "Feature",
  "properties": {
    "addr:full":"Fischbach Steiermark 8654",
    "addr:postcode":"8654",
    "iso:country":"AT",
    "sg:city":"Fischbach",
    "sg:orig_category":"Non-Classified Establishments",
    "sg:phone":"+43 3170 223",
    "sg:postcode":"8654",
    "sg:province":"Steiermark",
    "wof:name":"Pfarramt",
    "wof:placetype":"venue"
},
  "geometry": {"coordinates":[15.6509952545,47.4420051575],"type":"Point"}
}