{
  "type": "Feature",
  "properties": {
    "addr:full":"Schoberpa\u00df Bundesstr 33 Trieben Steiermark 8784",
    "addr:housenumber":"33",
    "addr:postcode":"8784",
    "iso:country":"AT",
    "sg:address":"Schoberpa\u00df Bundesstr 33",
    "sg:city":"Trieben",
    "sg:orig_category":"Blumeneinzelhandel",
    "sg:phone":"+43 3615 3193",
    "sg:postcode":"8784",
    "sg:province":"Steiermark",
    "wof:name":"Hirczy Johanna",
    "wof:placetype":"venue"
},
  "geometry": {"coordinates":[14.4831371307,47.489025116],"type":"Point"}
}