{
  "type": "Feature",
  "properties": {
    "iso:country":"AT",
    "sg:address":"B\u00e4ckerteichstr 8",
    "sg:city":"Velden am W\u00f6rther See",
    "sg:orig_category":"Hauptschulen",
    "sg:phone":"+43 4342 7422770",
    "sg:postcode":"9220",
    "sg:province":"K\u00e4rnten",
    "wof:name":"Hauptschule Velden",
    "wof:placetype":"venue"
},
  "geometry": {"coordinates":[14.0386590958,46.6112594604],"type":"Point"}
}