{
  "type": "Feature",
  "properties": {
    "addr:full":"Feistritzgrabenstr 129 Bad St. Leonhard im Lavanttal K\u00e4rnten 9462",
    "addr:housenumber":"129",
    "addr:postcode":"9462",
    "iso:country":"AT",
    "sg:address":"Feistritzgrabenstr 129",
    "sg:city":"Bad St. Leonhard im Lavanttal",
    "sg:orig_category":"Musikgruppen",
    "sg:phone":"+43 664 2032283",
    "sg:postcode":"9462",
    "sg:province":"K\u00e4rnten",
    "wof:name":"Die Leonharder",
    "wof:placetype":"venue"
},
  "geometry": {"coordinates":[12.3305559158,48.0921058655],"type":"Point"}
}