{
  "type": "Feature",
  "properties": {
    "addr:full":"Am Marktpl Rankweil Vorarlberg 6830",
    "addr:postcode":"6830",
    "addr:street":"Am Marktpl",
    "iso:country":"AT",
    "sg:address":"Am Marktpl",
    "sg:city":"Rankweil",
    "sg:orig_category":"Tourismusinformation U -Organisationen",
    "sg:phone":"+43 5522 405105",
    "sg:postcode":"6830",
    "sg:province":"Vorarlberg",
    "wof:name":"Verkehrsverein Rankweil",
    "wof:placetype":"venue"
},
  "geometry": {"coordinates":[9.6427202225,47.2705688477],"type":"Point"}
}