{
  "type": "Feature",
  "properties": {
    "iso:country":"AT",
    "sg:address":"Richard-K\u00fcrth-Strasse 7",
    "sg:city":"Salzburg",
    "sg:classifiers":[
        {
            "category":"Manufacturing",
            "subcategory":"Tools & Machinery",
            "type":"Manufacturing & Wholesale Goods"
        }
    ],
    "sg:phone":"+43 662 8766430",
    "sg:postcode":"5020",
    "sg:province":"Salzburg",
    "sg:tags":[
        "bending",
        "press",
        "presses",
        "folding"
    ],
    "sg:website":"schmid-salzburg.at",
    "wof:name":"Schmid Maschinen- und Werkzeugbau Ges.m.b.H. & Co KG",
    "wof:placetype":"venue"
},
  "geometry": {"coordinates":[13.0433769226,47.8006744385],"type":"Point"}
}