{
  "type": "Feature",
  "properties": {
    "addr:full":"Utzstr 1 Krems an der Donau Nieder\u00f6sterreich 3500",
    "addr:housenumber":"1",
    "addr:postcode":"3500",
    "addr:street":"Utzstr",
    "iso:country":"AT",
    "sg:address":"Utzstr 1",
    "sg:city":"Krems an der Donau",
    "sg:classifiers":[
        {
            "category":"Restaurant",
            "type":"Food & Drink"
        }
    ],
    "sg:phone":"+43 4327 32705400",
    "sg:postcode":"3500",
    "sg:province":"Nieder\u00f6sterreich",
    "wof:name":"Restaurant Brauhof",
    "wof:placetype":"venue"
},
  "geometry": {"coordinates":[15.5964136124,48.4091529846],"type":"Point"}
}