{
  "type": "Feature",
  "properties": {
    "iso:country":"AT",
    "sg:address":"InnovationsCenter Taxach",
    "sg:city":"Hallein",
    "sg:orig_category":"Medien, Multimedia",
    "sg:phone":"+43 6245 87725",
    "sg:postcode":"5400",
    "sg:province":"Salzburg",
    "sg:website":"http://www.austria.eu.net/image",
    "wof:name":"IMAGE Kommunikationsdesign GmbH",
    "wof:placetype":"venue"
},
  "geometry": {"coordinates":[13.0926103592,47.6814613342],"type":"Point"}
}