{
  "type": "Feature",
  "properties": {
    "addr:full":"Zinsg 368 Tamsweg Salzburg 5580",
    "addr:housenumber":"368",
    "addr:postcode":"5580",
    "addr:street":"Tamsweg Salzburg",
    "iso:country":"AT",
    "sg:address":"Zinsg 368",
    "sg:city":"Tamsweg",
    "sg:orig_category":"Tischlereien",
    "sg:phone":"+43 4364 747427",
    "sg:postcode":"5580",
    "sg:province":"Salzburg",
    "wof:name":"Wohndesign St. Leonhard Prodinger Peter",
    "wof:placetype":"venue"
},
  "geometry": {"coordinates":[13.8101902008,47.1263389587],"type":"Point"}
}