{
  "type": "Feature",
  "properties": {
    "addr:full":"Mariahilfer Str. 47a  Wien Wien 1060",
    "addr:housenumber":"47a",
    "addr:postcode":"1060",
    "addr:street":"Str.",
    "iso:country":"AT",
    "sg:address":"Mariahilfer Str. 47a ",
    "sg:city":"Wien",
    "sg:classifiers":[
        {
            "category":"Personal",
            "subcategory":"Shoe Repair & Shine",
            "type":"Services"
        }
    ],
    "sg:phone":"+43 4315 8986302",
    "sg:postcode":"1060",
    "sg:province":"Wien",
    "sg:tags":[
        "leather"
    ],
    "wof:name":"STIEFELK\u00d6NIG",
    "wof:placetype":"venue"
},
  "geometry": {"coordinates":[16.3547878265,48.1999435425],"type":"Point"}
}