{
  "type": "Feature",
  "properties": {
    "addr:full":"Mariahilfer Str 32-34 Wien Wien 1070",
    "addr:postcode":"32-34;1070",
    "addr:street":"Str",
    "iso:country":"AT",
    "sg:address":"Mariahilfer Str 32-34",
    "sg:city":"Wien",
    "sg:orig_category":"Boutiquen",
    "sg:phone":"+43 4315 268957",
    "sg:postcode":"1070",
    "sg:province":"Wien",
    "wof:name":"John-Moden",
    "wof:placetype":"venue"
},
  "geometry": {"coordinates":[16.3548851013,48.2001647949],"type":"Point"}
}