{
  "type": "Feature",
  "properties": {
    "addr:full":"Kasernstr 1 Graz Steiermark 8010",
    "addr:housenumber":"1",
    "addr:postcode":"8010",
    "addr:street":"Kasernstr",
    "iso:country":"AT",
    "sg:address":"Kasernstr 1",
    "sg:city":"Graz",
    "sg:orig_category":"Pizzazustellungen",
    "sg:phone":"+43 316 825200",
    "sg:postcode":"8010",
    "sg:province":"Steiermark",
    "wof:name":"Pizzeria Diavoloo",
    "wof:placetype":"venue"
},
  "geometry": {"coordinates":[15.4431142807,47.0535583496],"type":"Point"}
}