{
  "type": "Feature",
  "properties": {
    "addr:full":"Nr 122 Heiligenkreuz am Waasen Steiermark 8081",
    "addr:postcode":"8081",
    "addr:street":"Nr",
    "iso:country":"AT",
    "sg:address":"Nr 122",
    "sg:city":"Heiligenkreuz am Waasen",
    "sg:orig_category":"Feuerwehren",
    "sg:phone":"+43 3134 30063",
    "sg:postcode":"8081",
    "sg:province":"Steiermark",
    "wof:name":"Freiwillige Feuerwehr Edelstauden",
    "wof:placetype":"venue"
},
  "geometry": {"coordinates":[15.5856199265,46.9559020996],"type":"Point"}
}