{
  "type": "Feature",
  "properties": {
    "addr:full":"Kreischberg 2 St. Georgen ob Murau Steiermark 8861",
    "addr:housenumber":"2",
    "addr:postcode":"8861",
    "addr:street":"Kreischberg",
    "iso:country":"AT",
    "sg:address":"Kreischberg 2",
    "sg:city":"St. Georgen ob Murau",
    "sg:classifiers":[
        {
            "category":"Restaurant",
            "type":"Food & Drink"
        }
    ],
    "sg:phone":"+43 3537 203",
    "sg:postcode":"8861",
    "sg:province":"Steiermark",
    "wof:name":"SB-Rest Grillboden",
    "wof:placetype":"venue"
},
  "geometry": {"coordinates":[14.0855197906,47.1000976562],"type":"Point"}
}