{
  "type": "Feature",
  "properties": {
    "addr:full":"Nr 115 Straning Nieder\u00f6sterreich 3722",
    "addr:postcode":"3722",
    "addr:street":"Nr 115 Straning",
    "iso:country":"AT",
    "sg:address":"Nr 115",
    "sg:city":"Straning",
    "sg:orig_category":"Volksschulen",
    "sg:phone":"+43 2984 7239",
    "sg:postcode":"3722",
    "sg:province":"Nieder\u00f6sterreich",
    "wof:name":"Volksschule Straning-Grafenberg",
    "wof:placetype":"venue"
},
  "geometry": {"coordinates":[15.863940239,48.6107978821],"type":"Point"}
}