{
  "type": "Feature",
  "properties": {
    "addr:full":"Hauptstr 38 Himberg Nieder\u00f6sterreich 2325",
    "addr:housenumber":"38",
    "addr:postcode":"2325",
    "addr:street":"Hauptstr",
    "iso:country":"AT",
    "sg:address":"Hauptstr 38",
    "sg:city":"Himberg",
    "sg:orig_category":"Gemeinden",
    "sg:phone":"+43 2235 862130",
    "sg:postcode":"2325",
    "sg:province":"Nieder\u00f6sterreich",
    "wof:name":"Marktgemeinde Himberg",
    "wof:placetype":"venue"
},
  "geometry": {"coordinates":[16.4394302368,48.0835762024],"type":"Point"}
}