{
  "type": "Feature",
  "properties": {
    "addr:full":"Dandlerau 3 Fieberbrunn Tirol 6391",
    "addr:housenumber":"3",
    "addr:postcode":"6391",
    "addr:street":"Dandlerau;Tirol",
    "iso:country":"AT",
    "sg:address":"Dandlerau 3",
    "sg:city":"Fieberbrunn",
    "sg:orig_category":"Elektroinstallationsunternehmen",
    "sg:phone":"+43 5354 56921",
    "sg:postcode":"6391",
    "sg:province":"Tirol",
    "wof:name":"Klymiuk Peter",
    "wof:placetype":"venue"
},
  "geometry": {"coordinates":[12.5654811859,47.4673118591],"type":"Point"}
}