{
  "type": "Feature",
  "properties": {
    "iso:country":"AT",
    "sg:address":"Fachmarktzentrum",
    "sg:city":"Imst",
    "sg:orig_category":"Bankomat-Standorte",
    "sg:phone":"+43 5412 6000",
    "sg:postcode":"6460",
    "sg:province":"Tirol",
    "wof:name":"Bankomat d Sparkasse Imst",
    "wof:placetype":"venue"
},
  "geometry": {"coordinates":[10.737487793,47.2392234802],"type":"Point"}
}