{
  "type": "Feature",
  "properties": {
    "addr:full":"Maria-Theresien-Str 102 Lustenau Vorarlberg 6890",
    "addr:housenumber":"102",
    "addr:postcode":"6890",
    "iso:country":"AT",
    "sg:address":"Maria-Theresien-Str 102",
    "sg:city":"Lustenau",
    "sg:orig_category":"Unterhaltungselektronik / Einzelhandel",
    "sg:phone":"+43 4355 7782359",
    "sg:postcode":"6890",
    "sg:province":"Vorarlberg",
    "wof:name":"K\u00f6nig Radio KG",
    "wof:placetype":"venue"
},
  "geometry": {"coordinates":[9.6561222076,47.4369087219],"type":"Point"}
}