{
  "type": "Feature",
  "properties": {
    "addr:full":"Dammweg 6 Neuzeug Ober\u00f6sterreich 4523",
    "addr:housenumber":"6",
    "addr:postcode":"4523",
    "addr:street":"Dammweg",
    "iso:country":"AT",
    "sg:address":"Dammweg 6",
    "sg:city":"Neuzeug",
    "sg:orig_category":"Erdarbeiten",
    "sg:phone":"+43 4372 5930340",
    "sg:postcode":"4523",
    "sg:province":"Ober\u00f6sterreich",
    "wof:name":"Schendlinger Walter",
    "wof:placetype":"venue"
},
  "geometry": {"coordinates":[14.3221750259,48.0261383057],"type":"Point"}
}