{
  "type": "Feature",
  "properties": {
    "iso:country":"AT",
    "sg:address":"Richard-Neutra-G 11",
    "sg:city":"Wien",
    "sg:orig_category":"Waren Aller Art",
    "sg:phone":"+43 1 9689873",
    "sg:postcode":"1210",
    "sg:province":"Wien",
    "wof:name":"S-T-C Import & Export HandelsgmbH",
    "wof:placetype":"venue"
},
  "geometry": {"coordinates":[16.4316825867,48.271270752],"type":"Point"}
}