{
  "type": "Feature",
  "properties": {
    "iso:country":"AT",
    "sg:address":"Egon-Schiele-G 2a",
    "sg:city":"Tulln an der Donau",
    "sg:orig_category":"Fitnesscenter",
    "sg:phone":"+43 2272 61755",
    "sg:postcode":"3430",
    "sg:province":"Nieder\u00f6sterreich",
    "wof:name":"R\u00fccken & Bewegungszentrum Tulln",
    "wof:placetype":"venue"
},
  "geometry": {"coordinates":[16.0638122559,48.3270683289],"type":"Point"}
}