{
  "type": "Feature",
  "properties": {
    "addr:full":"Grieskirchner Str 72 Wels Ober\u00f6sterreich 4600",
    "addr:housenumber":"72",
    "addr:postcode":"4600",
    "addr:street":"Str;Oberoesterreich",
    "iso:country":"AT",
    "sg:address":"Grieskirchner Str 72",
    "sg:city":"Wels",
    "sg:orig_category":"Banken U Sparkassen",
    "sg:phone":"+43 5 010040113",
    "sg:postcode":"4600",
    "sg:province":"Ober\u00f6sterreich",
    "wof:name":"Allgemeine Sparkasse Ober\u00f6sterreich Bank AG",
    "wof:placetype":"venue"
},
  "geometry": {"coordinates":[14.0216932297,48.1771697998],"type":"Point"}
}