{
  "type": "Feature",
  "properties": {
    "addr:full":"Leopoldg 17 Tulln an der Donau Nieder\u00f6sterreich 3430",
    "addr:housenumber":"17",
    "addr:postcode":"3430",
    "addr:street":"Leopoldg",
    "iso:country":"AT",
    "sg:address":"Leopoldg 17",
    "sg:city":"Tulln an der Donau",
    "sg:orig_category":"Psychotherapie",
    "sg:phone":"+43 2272 67525",
    "sg:postcode":"3430",
    "sg:province":"Nieder\u00f6sterreich",
    "wof:name":"Gutmann Christa",
    "wof:placetype":"venue"
},
  "geometry": {"coordinates":[16.0497398376,48.3306999207],"type":"Point"}
}