{
  "type": "Feature",
  "properties": {
    "iso:country":"AT",
    "sg:address":"PEM-Strasse 1",
    "sg:city":"Mauthausen",
    "sg:classifiers":[
        {
            "category":"Sports & Exercise",
            "subcategory":"Gym",
            "type":"Entertainment"
        }
    ],
    "sg:phone":"+43 7238 27120",
    "sg:postcode":"4310",
    "sg:province":"Ober\u00f6sterreich",
    "sg:tags":[
        "athletic",
        "hall",
        "gymnasium"
    ],
    "sg:website":"pembuildings.com",
    "wof:name":"PEM Gesellschaft m.b.H.",
    "wof:placetype":"venue"
},
  "geometry": {"coordinates":[14.5460538864,48.2409057617],"type":"Point"}
}