{
  "type": "Feature",
  "properties": {
    "iso:country":"AT",
    "sg:address":"Hauptstr 14",
    "sg:city":"Liezen",
    "sg:orig_category":"Banken U Sparkassen",
    "sg:phone":"+43 3612 228280",
    "sg:postcode":"8940",
    "sg:province":"Steiermark",
    "wof:name":"Steierm\u00e4rkische Bank und Sparkassen AG Regionalzentrum Enns & Paltental",
    "wof:placetype":"venue"
},
  "geometry": {"coordinates":[14.2432603836,47.5673522949],"type":"Point"}
}