{
  "type": "Feature",
  "properties": {
    "addr:full":"Unterer Illrain 24 Bludenz Vorarlberg 6700",
    "addr:housenumber":"24",
    "addr:postcode":"6700",
    "addr:street":"Unterer Illrain",
    "iso:country":"AT",
    "sg:address":"Unterer Illrain 24",
    "sg:city":"Bludenz",
    "sg:orig_category":"Detekteien",
    "sg:phone":"+43 664 3525086",
    "sg:postcode":"6700",
    "sg:province":"Vorarlberg",
    "wof:name":"Detektiv- und Sicherheitsb\u00fcro Karl-Heinz Lenk",
    "wof:placetype":"venue"
},
  "geometry": {"coordinates":[9.8091669083,47.15574646],"type":"Point"}
}