{
  "type": "Feature",
  "properties": {
    "addr:full":"Wehrgasse 5a Salzburg Salzburg 5020",
    "addr:housenumber":"5a",
    "addr:postcode":"5020",
    "addr:street":"Wehrgasse;Salzburg",
    "iso:country":"AT",
    "sg:address":"Wehrgasse 5a",
    "sg:city":"Salzburg",
    "sg:classifiers":[
        {
            "category":"Home & Garden",
            "subcategory":"Carpets & Floor Coverings",
            "type":"Retail Goods"
        }
    ],
    "sg:phone":"+43 662 8323770",
    "sg:postcode":"5020",
    "sg:province":"Salzburg",
    "sg:tags":[
        "mosaic"
    ],
    "wof:name":"Hans P\u00f6schl GesmbH",
    "wof:placetype":"venue"
},
  "geometry": {"coordinates":[13.0204906464,47.7983818054],"type":"Point"}
}