{
  "type": "Feature",
  "properties": {
    "iso:country":"AT",
    "sg:address":"Loferer Bundesstr 13",
    "sg:city":"Saalfelden am Steinernen Meer",
    "sg:orig_category":"Autohandel",
    "sg:phone":"+43 4365 82720850",
    "sg:postcode":"5760",
    "sg:province":"Salzburg",
    "wof:name":"Auto Beck GmbH",
    "wof:placetype":"venue"
},
  "geometry": {"coordinates":[12.8437376022,47.4336166382],"type":"Point"}
}