{
  "type": "Feature",
  "properties": {
    "addr:full":"Nr 22 Rappottenstein Nieder\u00f6sterreich 3911",
    "addr:postcode":"3911",
    "addr:street":"Nr 22 Rappottenstein",
    "iso:country":"AT",
    "sg:address":"Nr 22",
    "sg:city":"Rappottenstein",
    "sg:orig_category":"Schneidereien",
    "sg:phone":"+43 2828 83460",
    "sg:postcode":"3911",
    "sg:province":"Nieder\u00f6sterreich",
    "wof:name":"Friedl Franz",
    "wof:placetype":"venue"
},
  "geometry": {"coordinates":[15.0787200928,48.521648407],"type":"Point"}
}