{
  "type": "Feature",
  "properties": {
    "addr:full":"Hutteng 10 Wien Wien 1140",
    "addr:housenumber":"10",
    "addr:postcode":"1140",
    "addr:street":"Hutteng",
    "iso:country":"AT",
    "sg:address":"Hutteng 10",
    "sg:city":"Wien",
    "sg:orig_category":"Edelmetalle U -Verarbeitung",
    "sg:phone":"+43 1 9822430",
    "sg:postcode":"1140",
    "sg:province":"Wien",
    "wof:name":"Metall-Edelmetall-R\u00fcckgewinnungs-HandelsgesmbH",
    "wof:placetype":"venue"
},
  "geometry": {"coordinates":[16.3081035614,48.2034912109],"type":"Point"}
}