{
  "type": "Feature",
  "properties": {
    "addr:full":"Aichholzg 33 Wien Wien 1120",
    "addr:housenumber":"33",
    "addr:postcode":"1120",
    "addr:street":"Aichholzg",
    "iso:country":"AT",
    "sg:address":"Aichholzg 33",
    "sg:city":"Wien",
    "sg:orig_category":"Ambulatorien",
    "sg:phone":"+43 1 8122447",
    "sg:postcode":"1120",
    "sg:province":"Wien",
    "wof:name":"Sozialpsychiatrisches Ambulatorium Meidling f d 12. 13. und 23. Bezirk",
    "wof:placetype":"venue"
},
  "geometry": {"coordinates":[16.3242893219,48.1790428162],"type":"Point"}
}