{
  "type": "Feature",
  "properties": {
    "addr:full":"Abelstrasse 18 Aschach an der Donau Ober\u00f6sterreich 4082",
    "addr:housenumber":"18",
    "addr:postcode":"4082",
    "addr:street":"Abelstrasse",
    "iso:country":"AT",
    "sg:address":"Abelstrasse 18",
    "sg:city":"Aschach an der Donau",
    "sg:classifiers":[
        {
            "category":"Building & Trades",
            "subcategory":"Plumbing",
            "type":"Services"
        }
    ],
    "sg:phone":"+43 7273 6347",
    "sg:postcode":"4082",
    "sg:province":"Ober\u00f6sterreich",
    "sg:tags":[
        "supraregional",
        "gas"
    ],
    "sg:website":"obgrasser.at",
    "wof:name":"Herbert Obgrasser",
    "wof:placetype":"venue"
},
  "geometry": {"coordinates":[14.0237379074,48.3647575378],"type":"Point"}
}