{
  "type": "Feature",
  "properties": {
    "addr:full":"Grubenweg 11 Pasching Ober\u00f6sterreich 4061",
    "addr:housenumber":"11",
    "addr:postcode":"4061",
    "addr:street":"Grubenweg;Oberoesterreich",
    "iso:country":"AT",
    "sg:address":"Grubenweg 11",
    "sg:city":"Pasching",
    "sg:orig_category":"Befestigungstechnik",
    "sg:phone":"+43 4372 2962251",
    "sg:postcode":"4061",
    "sg:province":"Ober\u00f6sterreich",
    "wof:name":"BWE HandelsgesmbH",
    "wof:placetype":"venue"
},
  "geometry": {"coordinates":[14.2504272461,48.2420845032],"type":"Point"}
}