{
  "type": "Feature",
  "properties": {
    "iso:country":"AT",
    "sg:address":"Burgg. 7",
    "sg:city":"Schwaz",
    "sg:classifiers":[
        {
            "category":"Wholesale",
            "subcategory":"Drugs",
            "type":"Manufacturing & Wholesale Goods"
        }
    ],
    "sg:phone":"+43 4352 4262280",
    "sg:postcode":"6130",
    "sg:province":"Tirol",
    "sg:tags":[
        "chemical",
        "pharmaceutical"
    ],
    "wof:name":"MARIENAPOTHEKE",
    "wof:placetype":"venue"
},
  "geometry": {"coordinates":[11.7097787857,47.3444633484],"type":"Point"}
}