{
  "type": "Feature",
  "properties": {
    "iso:country":"AT",
    "sg:address":"Paracelsusweg 8",
    "sg:city":"Dornbirn",
    "sg:classifiers":[
        {
            "category":"Museum",
            "subcategory":"Art Museum",
            "type":"Entertainment"
        }
    ],
    "sg:phone":"+43 5572 23594",
    "sg:postcode":"6850",
    "sg:province":"Vorarlberg",
    "sg:tags":[
        "artwork"
    ],
    "wof:name":"Wolfgang Jochum",
    "wof:placetype":"venue"
},
  "geometry": {"coordinates":[9.7550153732,47.4257774353],"type":"Point"}
}