{
  "type": "Feature",
  "properties": {
    "iso:country":"AT",
    "sg:address":"Neudorfer Str 7/3",
    "sg:city":"Laxenburg",
    "sg:orig_category":"Botendienste",
    "sg:phone":"+43 699 19220092",
    "sg:postcode":"2361",
    "sg:province":"Nieder\u00f6sterreich",
    "sg:website":"www.botendienst-moedling.at",
    "wof:name":"BBT Botendienst M\u00f6dling Bernold Thomas",
    "wof:placetype":"venue"
},
  "geometry": {"coordinates":[16.353843689,48.0691375732],"type":"Point"}
}