{
  "type": "Feature",
  "properties": {
    "addr:full":"Geier 12 Sebersdorf Steiermark 8272",
    "addr:housenumber":"12",
    "addr:postcode":"8272",
    "addr:street":"Geier",
    "iso:country":"AT",
    "sg:address":"Geier 12",
    "sg:city":"Sebersdorf",
    "sg:classifiers":[
        {
            "category":"Manufacturing",
            "subcategory":"Wood Products",
            "type":"Manufacturing & Wholesale Goods"
        }
    ],
    "sg:phone":"+43 3333 2813",
    "sg:postcode":"8272",
    "sg:province":"Steiermark",
    "sg:tags":[
        "gate",
        "made",
        "door"
    ],
    "wof:name":"Franz Posch",
    "wof:placetype":"venue"
},
  "geometry": {"coordinates":[16.0084667206,47.2102355957],"type":"Point"}
}