{
  "type": "Feature",
  "properties": {
    "addr:full":"Ruflinger Str 12 Leonding Ober\u00f6sterreich 4060",
    "addr:postcode":"4060",
    "addr:street":"Str 12",
    "iso:country":"AT",
    "sg:address":"Ruflinger Str 12",
    "sg:city":"Leonding",
    "sg:orig_category":"Friseure U Frisiersalons",
    "sg:phone":"+43 4373 2674343",
    "sg:postcode":"4060",
    "sg:province":"Ober\u00f6sterreich",
    "wof:name":"Helmhart Ursula - Friseur im Altenheim",
    "wof:placetype":"venue"
},
  "geometry": {"coordinates":[14.2488203049,48.2809295654],"type":"Point"}
}