{
  "type": "Feature",
  "properties": {
    "addr:full":"Oberfelben 60 Mittersill Salzburg 5730",
    "addr:housenumber":"60",
    "addr:postcode":"5730",
    "addr:street":"Oberfelben;Salzburg",
    "iso:country":"AT",
    "sg:address":"Oberfelben 60",
    "sg:city":"Mittersill",
    "sg:orig_category":"Autohandel",
    "sg:phone":"+43 6562 5300",
    "sg:postcode":"5730",
    "sg:province":"Salzburg",
    "wof:name":"Gwirl Wolfgang",
    "wof:placetype":"venue"
},
  "geometry": {"coordinates":[12.4771270752,47.1884651184],"type":"Point"}
}