{
  "type": "Feature",
  "properties": {
    "addr:full":"Bundesstr 112 Werndorf Steiermark 8402",
    "addr:housenumber":"112",
    "addr:postcode":"8402",
    "iso:country":"AT",
    "sg:address":"Bundesstr 112",
    "sg:city":"Werndorf",
    "sg:orig_category":"Badezimmer U Badezimmereinrichtungen",
    "sg:phone":"+43 4331 35541770",
    "sg:postcode":"8402",
    "sg:province":"Steiermark",
    "wof:name":"Colazzo Stein-Fliesen-Bad GesmbH & Co KG",
    "wof:placetype":"venue"
},
  "geometry": {"coordinates":[15.4821567535,46.9240150452],"type":"Point"}
}