{
  "type": "Feature",
  "properties": {
    "iso:country":"AT",
    "sg:address":"Nr 85",
    "sg:city":"Antiesenhofen",
    "sg:orig_category":"Non-Classified Establishments",
    "sg:phone":"+43 7759 5209",
    "sg:postcode":"4980",
    "sg:province":"Ober\u00f6sterreich",
    "wof:name":"Grabner Karl",
    "wof:placetype":"venue"
},
  "geometry": {"coordinates":[13.4010677338,48.346862793],"type":"Point"}
}