{
  "type": "Feature",
  "properties": {
    "addr:full":"Hauptstr 81 Klosterneuburg Nieder\u00f6sterreich 3400",
    "addr:housenumber":"81",
    "addr:postcode":"3400",
    "addr:street":"Hauptstr;Niederoesterreich",
    "iso:country":"AT",
    "sg:address":"Hauptstr 81",
    "sg:city":"Klosterneuburg",
    "sg:classifiers":[
        {
            "category":"Taxi",
            "type":"Transportation"
        }
    ],
    "sg:phone":"+43 4322 4383403",
    "sg:postcode":"3400",
    "sg:province":"Nieder\u00f6sterreich",
    "sg:tags":[
        "personentransporte",
        "u"
    ],
    "wof:name":"Weingartner Taxi GesmbH",
    "wof:placetype":"venue"
},
  "geometry": {"coordinates":[16.2832794189,48.3085823059],"type":"Point"}
}