{
  "type": "Feature",
  "properties": {
    "iso:country":"AT",
    "sg:address":"Landesstr 1-3",
    "sg:city":"Grafenstein",
    "sg:orig_category":"Installationsunternehmen",
    "sg:phone":"+43 4224 82178",
    "sg:postcode":"9131",
    "sg:province":"K\u00e4rnten",
    "sg:website":"fufhaustechnik.at",
    "wof:name":"F & F Haustechnik GmbH",
    "wof:placetype":"venue"
},
  "geometry": {"coordinates":[14.4506149292,46.6412239075],"type":"Point"}
}