{
  "type": "Feature",
  "properties": {
    "addr:full":"Nussau 1 Wolfsthal Nieder\u00f6sterreich 2412",
    "addr:housenumber":"1",
    "addr:postcode":"2412",
    "addr:street":"Nussau",
    "iso:country":"AT",
    "sg:address":"Nussau 1",
    "sg:city":"Wolfsthal",
    "sg:orig_category":"Forstverwaltungen",
    "sg:phone":"+43 2165 62664",
    "sg:postcode":"2412",
    "sg:province":"Nieder\u00f6sterreich",
    "wof:name":"Forstverwaltung Wolfsthal Isabella Prosoroff-Wettberg",
    "wof:placetype":"venue"
},
  "geometry": {"coordinates":[17.0106868744,48.1352348328],"type":"Point"}
}