{
  "type": "Feature",
  "properties": {
    "iso:country":"AT",
    "sg:address":"Etrichstr 35",
    "sg:city":"Salzburg",
    "sg:orig_category":"Friseure U Frisiersalons",
    "sg:phone":"+43 4366 2431071",
    "sg:postcode":"5020",
    "sg:province":"Salzburg",
    "wof:name":"Frisiersalon Berger Inh Faistauer Gabriele",
    "wof:placetype":"venue"
},
  "geometry": {"coordinates":[13.0014266968,47.8104324341],"type":"Point"}
}