{
  "type": "Feature",
  "properties": {
    "iso:country":"AT",
    "sg:address":"Wolfurter Str 10",
    "sg:city":"Lauterach",
    "sg:orig_category":"Stickereien",
    "sg:phone":"+43 4355 7462180",
    "sg:postcode":"6923",
    "sg:province":"Vorarlberg",
    "wof:name":"Witzemann Johannes",
    "wof:placetype":"venue"
},
  "geometry": {"coordinates":[9.7322673798,47.4725723267],"type":"Point"}
}