{
  "type": "Feature",
  "properties": {
    "addr:full":"Richard-Neutra-G 14 Wien Wien 1210",
    "addr:housenumber":"14",
    "addr:postcode":"1210",
    "addr:street":"Richard-Neutra-G",
    "iso:country":"AT",
    "sg:address":"Richard-Neutra-G 14",
    "sg:city":"Wien",
    "sg:orig_category":"Lastkraftwagen",
    "sg:phone":"+43 1 25826260",
    "sg:postcode":"1210",
    "sg:province":"Wien",
    "wof:name":"MAN Nutzfahrzeuge Vertrieb OHG",
    "wof:placetype":"venue"
},
  "geometry": {"coordinates":[16.4322986603,48.2722167969],"type":"Point"}
}