{
  "type": "Feature",
  "properties": {
    "iso:country":"AT",
    "sg:address":"Anzental 5",
    "sg:city":"Schwanenstadt",
    "sg:orig_category":"Pensionen / Privatzimmer",
    "sg:phone":"+43 4376 733249",
    "sg:postcode":"4690",
    "sg:province":"Ober\u00f6sterreich",
    "wof:name":"Bauernhof Neidl",
    "wof:placetype":"venue"
},
  "geometry": {"coordinates":[13.7139720917,48.0528564453],"type":"Point"}
}