{
  "type": "Feature",
  "properties": {
    "addr:full":"Brixentaler Str 22 Kirchberg in Tirol Tirol 6365",
    "addr:housenumber":"22",
    "addr:postcode":"6365",
    "addr:street":"Str;Tirol",
    "iso:country":"AT",
    "sg:address":"Brixentaler Str 22",
    "sg:city":"Kirchberg in Tirol",
    "sg:orig_category":"Werbeagenturen",
    "sg:phone":"+43 699 13663661",
    "sg:postcode":"6365",
    "sg:province":"Tirol",
    "wof:name":"SAW - Werbepromotion Agentur",
    "wof:placetype":"venue"
},
  "geometry": {"coordinates":[12.3117742538,47.4494094849],"type":"Point"}
}