{
  "type": "Feature",
  "properties": {
    "addr:full":"Heuparz 70 Angern Nieder\u00f6sterreich 2261",
    "addr:housenumber":"70",
    "addr:postcode":"2261",
    "addr:street":"Heuparz",
    "iso:country":"AT",
    "sg:address":"Heuparz 70",
    "sg:city":"Angern",
    "sg:orig_category":"Maschinenbau",
    "sg:phone":"+43 4322 842703",
    "sg:postcode":"2261",
    "sg:province":"Nieder\u00f6sterreich",
    "wof:name":"Forstner Hans Wolfgang",
    "wof:placetype":"venue"
},
  "geometry": {"coordinates":[16.8282699585,48.3832092285],"type":"Point"}
}