{
  "type": "Feature",
  "properties": {
    "addr:full":"Nr 101 Faistenau Salzburg 5324",
    "addr:postcode":"5324",
    "addr:street":"Nr 101;Salzburg",
    "iso:country":"AT",
    "sg:address":"Nr 101",
    "sg:city":"Faistenau",
    "sg:orig_category":"Handelsagenturen",
    "sg:phone":"+43 6228 2704",
    "sg:postcode":"5324",
    "sg:province":"Salzburg",
    "wof:name":"hoeb Einkaufsservice f\u00fcr Hotellerie & Gastronomie - Ing Schierl Raimund",
    "wof:placetype":"venue"
},
  "geometry": {"coordinates":[13.2332620621,47.7780952454],"type":"Point"}
}