{
  "type": "Feature",
  "properties": {
    "addr:full":"Gewerbepark Mauer 24 Wallern an der Trattnach Ober\u00f6sterreich 4702",
    "addr:housenumber":"24",
    "addr:postcode":"4702",
    "addr:street":"Gewerbepark Mauer",
    "iso:country":"AT",
    "sg:address":"Gewerbepark Mauer 24",
    "sg:city":"Wallern an der Trattnach",
    "sg:orig_category":"Transportunternehmen",
    "sg:phone":"+43 4372 4948601",
    "sg:postcode":"4702",
    "sg:province":"Ober\u00f6sterreich",
    "wof:name":"GROH SpeditionsgesmbH",
    "wof:placetype":"venue"
},
  "geometry": {"coordinates":[13.9445810318,48.2194213867],"type":"Point"}
}