{
  "type": "Feature",
  "properties": {
    "addr:full":"Wenzel-Frey-G 25 Perchtoldsdorf Nieder\u00f6sterreich 2380",
    "addr:housenumber":"25",
    "addr:postcode":"2380",
    "addr:street":"Wenzel-Frey-G",
    "iso:country":"AT",
    "sg:address":"Wenzel-Frey-G 25",
    "sg:city":"Perchtoldsdorf",
    "sg:orig_category":"Handelsagenturen",
    "sg:phone":"+43 4318 693955",
    "sg:postcode":"2380",
    "sg:province":"Nieder\u00f6sterreich",
    "wof:name":"Karl Schmoll KG",
    "wof:placetype":"venue"
},
  "geometry": {"coordinates":[16.2761154175,48.1211395264],"type":"Point"}
}