{
  "type": "Feature",
  "properties": {
    "iso:country":"AT",
    "sg:address":"Mauthausner Str 7",
    "sg:city":"Enns",
    "sg:orig_category":"Friseure U Frisiersalons",
    "sg:phone":"+43 7223 85543",
    "sg:postcode":"4470",
    "sg:province":"Ober\u00f6sterreich",
    "wof:name":"Friseur ROBERT'S FOR HAIR",
    "wof:placetype":"venue"
},
  "geometry": {"coordinates":[14.4796772003,48.215171814],"type":"Point"}
}