{
  "type": "Feature",
  "properties": {
    "addr:full":"Aurachtalstr 9 Reichenfels K\u00e4rnten 9463",
    "addr:housenumber":"9",
    "addr:postcode":"9463",
    "addr:street":"Aurachtalstr;Kaernten",
    "iso:country":"AT",
    "sg:address":"Aurachtalstr 9",
    "sg:city":"Reichenfels",
    "sg:classifiers":[
        {
            "category":"Taxi",
            "type":"Transportation"
        }
    ],
    "sg:phone":"+43 4359 2241",
    "sg:postcode":"9463",
    "sg:province":"K\u00e4rnten",
    "sg:tags":[
        "personentransporte",
        "u"
    ],
    "wof:name":"Steinkellner Wolfgang",
    "wof:placetype":"venue"
},
  "geometry": {"coordinates":[14.7425956726,47.0093078613],"type":"Point"}
}