{
  "type": "Feature",
  "properties": {
    "addr:full":"Hauptstr 141 Stoob Burgenland 7344",
    "addr:housenumber":"141",
    "addr:postcode":"stoob;7344",
    "addr:street":"Hauptstr",
    "iso:country":"AT",
    "sg:address":"Hauptstr 141",
    "sg:city":"Stoob",
    "sg:orig_category":"Hafnereien",
    "sg:phone":"+43 2612 42448",
    "sg:postcode":"7344",
    "sg:province":"Burgenland",
    "wof:name":"Graf Erich",
    "wof:placetype":"venue"
},
  "geometry": {"coordinates":[16.4802265167,47.5257148743],"type":"Point"}
}