{
  "type": "Feature",
  "properties": {
    "addr:full":"Radetzkystr 31 Graz Steiermark 8010",
    "addr:housenumber":"31",
    "addr:postcode":"8010",
    "addr:street":"Radetzkystr",
    "iso:country":"AT",
    "sg:address":"Radetzkystr 31",
    "sg:city":"Graz",
    "sg:orig_category":"Werbeagenturen, Veranstaltungsorganisation",
    "sg:phone":"+43 316 828828",
    "sg:postcode":"8010",
    "sg:province":"Steiermark",
    "sg:website":"www.cb-promotion.com",
    "wof:name":"cb Promotion Werbe- und VeranstaltungsgesmbH",
    "wof:placetype":"venue"
},
  "geometry": {"coordinates":[15.4357757568,47.0662574768],"type":"Point"}
}