{
  "type": "Feature",
  "properties": {
    "iso:country":"AT",
    "sg:address":"Liechtensteinstr 2-4",
    "sg:city":"Murau",
    "sg:orig_category":"Optiker",
    "sg:phone":"+43 3532 23740",
    "sg:postcode":"8850",
    "sg:province":"Steiermark",
    "wof:name":"Optik Fuchs",
    "wof:placetype":"venue"
},
  "geometry": {"coordinates":[14.1711406708,47.1103134155],"type":"Point"}
}