{
  "type": "Feature",
  "properties": {
    "addr:full":"Landstr 11 Zistersdorf Nieder\u00f6sterreich 2225",
    "addr:housenumber":"11",
    "addr:postcode":"2225",
    "addr:street":"Landstr;Niederoesterreich",
    "iso:country":"AT",
    "sg:address":"Landstr 11",
    "sg:city":"Zistersdorf",
    "sg:orig_category":"Fahrschulen",
    "sg:phone":"+43 2532 2485",
    "sg:postcode":"2225",
    "sg:province":"Nieder\u00f6sterreich",
    "wof:name":"Fahrschule Rapid",
    "wof:placetype":"venue"
},
  "geometry": {"coordinates":[16.7657737732,48.544090271],"type":"Point"}
}