{
  "type": "Feature",
  "properties": {
    "iso:country":"AT",
    "sg:address":"Nr 28",
    "sg:city":"Pfarrkirchen im M\u00fchlkreis",
    "sg:orig_category":"Werbeagenturen",
    "sg:phone":"+43 4372 854070",
    "sg:postcode":"4141",
    "sg:province":"Ober\u00f6sterreich",
    "wof:name":"Lindorfer Karl",
    "wof:placetype":"venue"
},
  "geometry": {"coordinates":[13.8255701065,48.5037002563],"type":"Point"}
}