{
  "type": "Feature",
  "properties": {
    "addr:full":"Bienenh\u00e4usl 31 Altlengbach Nieder\u00f6sterreich 3033",
    "addr:housenumber":"31",
    "addr:postcode":"3033",
    "addr:street":"Bienenhaeusl",
    "iso:country":"AT",
    "sg:address":"Bienenh\u00e4usl 31",
    "sg:city":"Altlengbach",
    "sg:orig_category":"Imkereien",
    "sg:phone":"+43 676 3704380",
    "sg:postcode":"3033",
    "sg:province":"Nieder\u00f6sterreich",
    "wof:name":"Franzke Georg Ernst Wienerwald Imkerei Meisterbetrieb Sum Sum",
    "wof:placetype":"venue"
},
  "geometry": {"coordinates":[15.9308271408,48.1525306702],"type":"Point"}
}