{
  "type": "Feature",
  "properties": {
    "addr:full":"Marktstr 26 Neukirchen am Gro\u00dfvenediger Salzburg 5741",
    "addr:housenumber":"26",
    "addr:postcode":"5741",
    "addr:street":"Marktstr;Salzburg",
    "iso:country":"AT",
    "sg:address":"Marktstr 26",
    "sg:city":"Neukirchen am Gro\u00dfvenediger",
    "sg:classifiers":[
        {
            "category":"Travel",
            "subcategory":"Hotels & Motels",
            "type":"Entertainment"
        }
    ],
    "sg:phone":"+43 4365 6562260",
    "sg:postcode":"5741",
    "sg:province":"Salzburg",
    "wof:name":"Unterbrunn",
    "wof:placetype":"venue"
},
  "geometry": {"coordinates":[12.2707414627,47.2507743835],"type":"Point"}
}