{
  "type": "Feature",
  "properties": {
    "iso:country":"AT",
    "sg:address":"Stadtpl 22/2",
    "sg:city":"Braunau am Inn",
    "sg:orig_category":"Politische Parteien",
    "sg:phone":"+43 4377 22633710",
    "sg:postcode":"5280",
    "sg:province":"Ober\u00f6sterreich",
    "wof:name":"Haus- u Grundbesitzerbund Bez-Obm Josef Stranzinger",
    "wof:placetype":"venue"
},
  "geometry": {"coordinates":[13.0350933075,48.2577934265],"type":"Point"}
}