{
  "type": "Feature",
  "properties": {
    "iso:country":"AT",
    "sg:address":"Steindorf 188",
    "sg:city":"Stra\u00dfwalchen",
    "sg:orig_category":"Papier / Erzeugung U Gro\u00c3\u0178handel",
    "sg:phone":"+43 6215 68210",
    "sg:postcode":"5204",
    "sg:province":"Salzburg",
    "wof:name":"Europapier AG",
    "wof:placetype":"venue"
},
  "geometry": {"coordinates":[13.2277984619,47.9570655823],"type":"Point"}
}