{
  "type": "Feature",
  "properties": {
    "addr:full":"Bleiburger Str 16 Eberndorf K\u00e4rnten 9141",
    "addr:housenumber":"16",
    "addr:postcode":"9141",
    "addr:street":"Str;Kaernten",
    "iso:country":"AT",
    "sg:address":"Bleiburger Str 16",
    "sg:city":"Eberndorf",
    "sg:orig_category":"Apotheken",
    "sg:phone":"+43 4236 51100",
    "sg:postcode":"9141",
    "sg:province":"K\u00e4rnten",
    "wof:name":"Jauntal-Apotheke Mag pharm Klaus Bauer KG",
    "wof:placetype":"venue"
},
  "geometry": {"coordinates":[14.6413393021,46.5904312134],"type":"Point"}
}