{
  "type": "Feature",
  "properties": {
    "addr:full":"Hauptstr 28 Gablitz Nieder\u00f6sterreich 3003",
    "addr:housenumber":"28",
    "addr:postcode":"3003",
    "addr:street":"Hauptstr",
    "iso:country":"AT",
    "sg:address":"Hauptstr 28",
    "sg:city":"Gablitz",
    "sg:orig_category":"Tauchsportschulen U -Vereine",
    "sg:phone":"+43 4322 3165747",
    "sg:postcode":"3003",
    "sg:province":"Nieder\u00f6sterreich",
    "wof:name":"5 Star Dive Center - WAYANG SCUBA DIVING",
    "wof:placetype":"venue"
},
  "geometry": {"coordinates":[16.1518821716,48.2288703918],"type":"Point"}
}