{
  "type": "Feature",
  "properties": {
    "addr:full":"Ramsauer Str 95 Linz Ober\u00f6sterreich 4020",
    "addr:postcode":"4020",
    "addr:street":"Str 95",
    "iso:country":"AT",
    "sg:address":"Ramsauer Str 95",
    "sg:city":"Linz",
    "sg:classifiers":[
        {
            "category":"Taxi",
            "type":"Transportation"
        }
    ],
    "sg:phone":"+43 4373 2346618",
    "sg:postcode":"4020",
    "sg:province":"Ober\u00f6sterreich",
    "sg:tags":[
        "personentransporte",
        "u"
    ],
    "wof:name":"Katzmayr Leopold",
    "wof:placetype":"venue"
},
  "geometry": {"coordinates":[14.2885484695,48.2699623108],"type":"Point"}
}