{
  "type": "Feature",
  "properties": {
    "iso:country":"AT",
    "sg:address":"Rennweg 10a",
    "sg:city":"Innsbruck",
    "sg:orig_category":"Mautstra\u00c3\u0178en",
    "sg:phone":"+43 512 520120",
    "sg:postcode":"6020",
    "sg:province":"Tirol",
    "wof:name":"Alpen Stra\u00dfen AG",
    "wof:placetype":"venue"
},
  "geometry": {"coordinates":[11.3964719772,47.2737121582],"type":"Point"}
}