{
  "type": "Feature",
  "properties": {
    "iso:country":"AT",
    "sg:address":"Nachdemsee 22",
    "sg:city":"Altm\u00fcnster",
    "sg:classifiers":[
        {
            "category":"Restaurant",
            "type":"Food & Drink"
        }
    ],
    "sg:phone":"+43 761288409",
    "sg:postcode":"4813",
    "sg:province":"Ober\u00f6sterreich",
    "sg:tags":[
        "pizzeria"
    ],
    "wof:name":"Pizzeria-Ristorante San Angelo",
    "wof:placetype":"venue"
},
  "geometry": {"coordinates":[13.7674312592,47.8842658997],"type":"Point"}
}