{
  "type": "Feature",
  "properties": {
    "iso:country":"AT",
    "sg:address":"Priesterhausgasse 8/2",
    "sg:city":"Klagenfurt",
    "sg:classifiers":[
        {
            "category":"Building & Trades",
            "subcategory":"Construction",
            "type":"Services"
        }
    ],
    "sg:phone":"+43 463 5033100",
    "sg:postcode":"9020",
    "sg:province":"K\u00e4rnten",
    "sg:tags":[
        "component",
        "hydraulic"
    ],
    "sg:website":"inkla.com",
    "wof:name":"INKLA Trading & Engineering GmbH",
    "wof:placetype":"venue"
},
  "geometry": {"coordinates":[14.3114013672,46.6255302429],"type":"Point"}
}