{
  "type": "Feature",
  "properties": {
    "addr:full":"Gilmstr 2 Kufstein Tirol 6330",
    "addr:housenumber":"2",
    "addr:postcode":"6330",
    "addr:street":"Gilmstr;Tirol",
    "iso:country":"AT",
    "sg:address":"Gilmstr 2",
    "sg:city":"Kufstein",
    "sg:orig_category":"Schlossereien",
    "sg:phone":"+43 5372 621530",
    "sg:postcode":"6330",
    "sg:province":"Tirol",
    "wof:name":"J\u00e4ger Karl KG",
    "wof:placetype":"venue"
},
  "geometry": {"coordinates":[12.1690006256,47.5789070129],"type":"Point"}
}