{
  "type": "Feature",
  "properties": {
    "addr:full":"Herreng 13 Graz Steiermark 8010",
    "addr:housenumber":"13",
    "addr:postcode":"8010",
    "addr:street":"Herreng",
    "iso:country":"AT",
    "sg:address":"Herreng 13",
    "sg:city":"Graz",
    "sg:orig_category":"Damenmoden",
    "sg:phone":"+43 316 820360",
    "sg:postcode":"8010",
    "sg:province":"Steiermark",
    "wof:name":"NEW YORKER - NYer Hansen & Knapp KG",
    "wof:placetype":"venue"
},
  "geometry": {"coordinates":[15.4402351379,47.0699195862],"type":"Point"}
}