{
  "type": "Feature",
  "properties": {
    "addr:full":"Hietzinger Hauptstrasse 145 Wien Wien 1130",
    "addr:housenumber":"145",
    "addr:postcode":"1130",
    "addr:street":"Hietzinger Hauptstrasse",
    "iso:country":"AT",
    "sg:address":"Hietzinger Hauptstrasse 145",
    "sg:city":"Wien",
    "sg:orig_category":"Apparatuses For Determination Of Germination Index",
    "sg:phone":"+43 820 874464",
    "sg:postcode":"1130",
    "sg:province":"Wien",
    "sg:website":"millipore.com",
    "wof:name":"Millipore Ges.m.b.H.",
    "wof:placetype":"venue"
},
  "geometry": {"coordinates":[16.2680187225,48.1877975464],"type":"Point"}
}