{
  "type": "Feature",
  "properties": {
    "iso:country":"AT",
    "sg:address":"Industriestr. 1 ",
    "sg:city":"Gumpoldskirchen",
    "sg:classifiers":[
        {
            "category":"Wholesale",
            "subcategory":"Drugs",
            "type":"Manufacturing & Wholesale Goods"
        }
    ],
    "sg:phone":"+43 4322 52636300",
    "sg:postcode":"2352",
    "sg:province":"Nieder\u00f6sterreich",
    "sg:tags":[
        "chemical",
        "pharmaceutical"
    ],
    "wof:name":"GABRIEL CHEMIE GESMBH",
    "wof:placetype":"venue"
},
  "geometry": {"coordinates":[16.2896385193,48.0324134827],"type":"Point"}
}