{
  "type": "Feature",
  "properties": {
    "addr:full":"Kaiserstrasse 81 Wien Wien 1070",
    "addr:housenumber":"81",
    "addr:postcode":"1070",
    "addr:street":"Kaiserstrasse",
    "iso:country":"AT",
    "sg:address":"Kaiserstrasse 81",
    "sg:city":"Wien",
    "sg:classifiers":[
        {
            "category":"Communications",
            "subcategory":"Film & Video Production",
            "type":"Services"
        }
    ],
    "sg:phone":"+43 1 5234262",
    "sg:postcode":"1070",
    "sg:province":"Wien",
    "sg:tags":[
        "images",
        "graphic",
        "creating"
    ],
    "wof:name":"Emil Nowack",
    "wof:placetype":"venue"
},
  "geometry": {"coordinates":[16.3397388458,48.2048377991],"type":"Point"}
}