{
  "type": "Feature",
  "properties": {
    "iso:country":"AT",
    "sg:address":"Bahnstr 12",
    "sg:city":"Neumarkt an der Ybbs",
    "sg:orig_category":"Gie\u00c3\u0178ereien",
    "sg:phone":"+43 4374 1252529",
    "sg:postcode":"3371",
    "sg:province":"Nieder\u00f6sterreich",
    "wof:name":"Kirchner u S\u00f6hne GesmbH",
    "wof:placetype":"venue"
},
  "geometry": {"coordinates":[15.053360939,48.1421089172],"type":"Point"}
}