{
  "type": "Feature",
  "properties": {
    "addr:full":"Weihburgg 26 Wien Wien 1010",
    "addr:housenumber":"26",
    "addr:postcode":"1010",
    "addr:street":"Weihburgg",
    "iso:country":"AT",
    "sg:address":"Weihburgg 26",
    "sg:city":"Wien",
    "sg:orig_category":"Galerien",
    "sg:phone":"+43 4319 042004",
    "sg:postcode":"1010",
    "sg:province":"Wien",
    "wof:name":"Mauroner Contmporary Art",
    "wof:placetype":"venue"
},
  "geometry": {"coordinates":[16.3757743835,48.2051773071],"type":"Point"}
}