{
  "type": "Feature",
  "properties": {
    "addr:full":"Badbergstr 11 Bad Gastein Salzburg 5640",
    "addr:housenumber":"11",
    "addr:postcode":"5640",
    "addr:street":"Badbergstr;Salzburg",
    "iso:country":"AT",
    "sg:address":"Badbergstr 11",
    "sg:city":"Bad Gastein",
    "sg:orig_category":"Forschungsinstitute",
    "sg:phone":"+43 6434 2618",
    "sg:postcode":"5640",
    "sg:province":"Salzburg",
    "wof:name":"Forschungsinstitut Gastein d \u00f6sterreichischen Akademie d Wissenschaften",
    "wof:placetype":"venue"
},
  "geometry": {"coordinates":[13.1390199661,47.1201286316],"type":"Point"}
}