{
  "type": "Feature",
  "properties": {
    "iso:country":"AT",
    "sg:address":"Wiesingerstr 8",
    "sg:city":"Bad Ischl",
    "sg:orig_category":"Physiotherapie",
    "sg:phone":"+43 4361 3229190",
    "sg:postcode":"4820",
    "sg:province":"Ober\u00f6sterreich",
    "wof:name":"Harich Bernhard Dr",
    "wof:placetype":"venue"
},
  "geometry": {"coordinates":[13.6193008423,47.7125205994],"type":"Point"}
}