{
  "type": "Feature",
  "properties": {
    "iso:country":"AT",
    "sg:address":"Karfreitstr 14",
    "sg:city":"Klagenfurt",
    "sg:classifiers":[
        {
            "category":"Travel",
            "subcategory":"Hotels & Motels",
            "type":"Entertainment"
        }
    ],
    "sg:phone":"+43 463 573800",
    "sg:postcode":"9020",
    "sg:province":"K\u00e4rnten",
    "sg:website":"goldener-brunnen.at",
    "wof:name":"Hotel Goldener Brunnen",
    "wof:placetype":"venue"
},
  "geometry": {"coordinates":[14.3084564209,46.6223564148],"type":"Point"}
}