{
  "type": "Feature",
  "properties": {
    "addr:full":"Schl\u00f6sselg 11 Wien Wien 1080",
    "addr:housenumber":"11",
    "addr:postcode":"1080",
    "addr:street":"Schloesselg",
    "iso:country":"AT",
    "sg:address":"Schl\u00f6sselg 11",
    "sg:city":"Wien",
    "sg:orig_category":"Pensionen / Privatzimmer",
    "sg:phone":"+43 1 4053488",
    "sg:postcode":"1080",
    "sg:province":"Wien",
    "sg:website":"tourist-net.co.at/hotel/andreas",
    "wof:name":"Pension Andreas",
    "wof:placetype":"venue"
},
  "geometry": {"coordinates":[16.3430690765,48.2106552124],"type":"Point"}
}