{
  "type": "Feature",
  "properties": {
    "addr:full":"Mistelbacher Str 96 Wilfersdorf Nieder\u00f6sterreich 2193",
    "addr:housenumber":"96",
    "addr:postcode":"2193",
    "addr:street":"Str",
    "iso:country":"AT",
    "sg:address":"Mistelbacher Str 96",
    "sg:city":"Wilfersdorf",
    "sg:orig_category":"Tischlereien",
    "sg:phone":"+43 2573 252420",
    "sg:postcode":"2193",
    "sg:province":"Nieder\u00f6sterreich",
    "wof:name":"Neumayer GesmbH",
    "wof:placetype":"venue"
},
  "geometry": {"coordinates":[16.6348705292,48.5791091919],"type":"Point"}
}