{
  "type": "Feature",
  "properties": {
    "addr:full":"Bahnhofstr 35a Ried im Innkreis Ober\u00f6sterreich 4910",
    "addr:housenumber":"35a",
    "addr:postcode":"4910",
    "addr:street":"Bahnhofstr",
    "iso:country":"AT",
    "sg:address":"Bahnhofstr 35a",
    "sg:city":"Ried im Innkreis",
    "sg:orig_category":"Bauunternehmen",
    "sg:phone":"+43 2783 8754",
    "sg:postcode":"4910",
    "sg:province":"Ober\u00f6sterreich",
    "wof:name":"K N O P F Bau GmbH",
    "wof:placetype":"venue"
},
  "geometry": {"coordinates":[13.4892463684,48.2050170898],"type":"Point"}
}