{
  "type": "Feature",
  "properties": {
    "iso:country":"AT",
    "sg:address":"Speisinger Str 104",
    "sg:city":"Wien",
    "sg:orig_category":"Architekten",
    "sg:phone":"+43 676 9414301",
    "sg:postcode":"1130",
    "sg:province":"Wien",
    "wof:name":"Prinz Andreas Arch Dipl-Ing",
    "wof:placetype":"venue"
},
  "geometry": {"coordinates":[16.2791652679,48.1631317139],"type":"Point"}
}