{
  "type": "Feature",
  "properties": {
    "addr:full":"Lagerstr 8-10 Bruck an der Leitha Nieder\u00f6sterreich 2460",
    "addr:housenumber":"8-10",
    "addr:postcode":"2460",
    "iso:country":"AT",
    "sg:address":"Lagerstr 8-10",
    "sg:city":"Bruck an der Leitha",
    "sg:orig_category":"Stoffe / Erzeugung U Gro\u00c3\u0178handel",
    "sg:phone":"+43 2162 65927",
    "sg:postcode":"2460",
    "sg:province":"Nieder\u00f6sterreich",
    "wof:name":"M\u00fcller Franz Textilgro\u00df- und Detailhandel",
    "wof:placetype":"venue"
},
  "geometry": {"coordinates":[16.7778892517,48.0182380676],"type":"Point"}
}