{
  "type": "Feature",
  "properties": {
    "addr:full":"Obere Hauptstr 19 Hohenberg Nieder\u00f6sterreich 3192",
    "addr:housenumber":"19",
    "addr:postcode":"3192",
    "addr:street":"Obere Hauptstr",
    "iso:country":"AT",
    "sg:address":"Obere Hauptstr 19",
    "sg:city":"Hohenberg",
    "sg:orig_category":"Holzbe U -Verarbeitung",
    "sg:phone":"+43 4327 678285",
    "sg:postcode":"3192",
    "sg:province":"Nieder\u00f6sterreich",
    "wof:name":"Wallner's Johann Nfg Inh Erika Kropik",
    "wof:placetype":"venue"
},
  "geometry": {"coordinates":[15.6172227859,47.9142799377],"type":"Point"}
}