{
  "type": "Feature",
  "properties": {
    "addr:full":"Nr 18 Ebenau Salzburg 5323",
    "addr:postcode":"5323",
    "addr:street":"Nr;Ebenau",
    "iso:country":"AT",
    "sg:address":"Nr 18",
    "sg:city":"Ebenau",
    "sg:classifiers":[
        {
            "category":"Travel",
            "subcategory":"Hotels & Motels",
            "type":"Entertainment"
        }
    ],
    "sg:phone":"+43 6221 7236",
    "sg:postcode":"5323",
    "sg:province":"Salzburg",
    "wof:name":"Hotel Obermayr",
    "wof:placetype":"venue"
},
  "geometry": {"coordinates":[13.1745538712,47.7922706604],"type":"Point"}
}