{
  "type": "Feature",
  "properties": {
    "addr:full":"Au 19 Gro\u00dfarl Salzburg 5611",
    "addr:housenumber":"19",
    "addr:postcode":"5611",
    "addr:street":"Au;Salzburg",
    "iso:country":"AT",
    "sg:address":"Au 19",
    "sg:city":"Gro\u00dfarl",
    "sg:orig_category":"Appartements / Ferienwohnungen",
    "sg:phone":"+43 6414 8728",
    "sg:postcode":"5611",
    "sg:province":"Salzburg",
    "wof:name":"Prommegger Georg - Lambachbauer",
    "wof:placetype":"venue"
},
  "geometry": {"coordinates":[-114.0853424072,47.1626281738],"type":"Point"}
}