{
  "type": "Feature",
  "properties": {
    "addr:full":"Rhombergstrasse 1 Hall in Tirol Tirol 6060",
    "addr:housenumber":"1",
    "addr:postcode":"6060",
    "addr:street":"Rhombergstrasse;Tirol",
    "iso:country":"AT",
    "sg:address":"Rhombergstrasse 1",
    "sg:city":"Hall in Tirol",
    "sg:classifiers":[
        {
            "category":"Home & Garden",
            "subcategory":"Hardware",
            "type":"Retail Goods"
        }
    ],
    "sg:phone":"+43 5223 44477",
    "sg:postcode":"6060",
    "sg:province":"Tirol",
    "sg:tags":[
        "agricultural",
        "implement"
    ],
    "wof:name":"Markus Klausner",
    "wof:placetype":"venue"
},
  "geometry": {"coordinates":[11.5066928864,47.2984695435],"type":"Point"}
}