{
  "type": "Feature",
  "properties": {
    "addr:full":"Stadiong 6-8 Wien Wien 1010",
    "addr:housenumber":"6-8",
    "addr:postcode":"1010",
    "addr:street":"Stadiong",
    "iso:country":"AT",
    "sg:address":"Stadiong 6-8",
    "sg:city":"Wien",
    "sg:orig_category":"Botschaften",
    "sg:phone":"+43 1 4054249",
    "sg:postcode":"1010",
    "sg:province":"Wien",
    "wof:name":"Botschaft v Kolumbien",
    "wof:placetype":"venue"
},
  "geometry": {"coordinates":[16.3565883636,48.2093162537],"type":"Point"}
}