{
  "type": "Feature",
  "properties": {
    "addr:full":"Mistelbacher Strasse 19 Mistelbach Ober\u00f6sterreich 4613",
    "addr:housenumber":"19",
    "addr:postcode":"4613",
    "addr:street":"Mistelbacher Strasse;Oberoesterreich",
    "iso:country":"AT",
    "sg:address":"Mistelbacher Strasse 19",
    "sg:city":"Mistelbach",
    "sg:classifiers":[
        {
            "category":"Home & Garden",
            "subcategory":"Building Materials",
            "type":"Retail Goods"
        }
    ],
    "sg:phone":"+43 7243 571700",
    "sg:postcode":"4613",
    "sg:province":"Ober\u00f6sterreich",
    "sg:tags":[
        "aluminium",
        "window"
    ],
    "sg:website":"silberfenster.at",
    "wof:name":"Franz SILBER Fensterbau GmbH",
    "wof:placetype":"venue"
},
  "geometry": {"coordinates":[14.0629920959,48.2396697998],"type":"Point"}
}