{
  "type": "Feature",
  "properties": {
    "addr:full":"Wiener Strasse 2 Neumarkt am Wallersee Salzburg 5202",
    "addr:housenumber":"2",
    "addr:postcode":"5202",
    "addr:street":"Wiener Strasse;Salzburg",
    "iso:country":"AT",
    "sg:address":"Wiener Strasse 2",
    "sg:city":"Neumarkt am Wallersee",
    "sg:classifiers":[
        {
            "category":"Utilities",
            "subcategory":"Telephone",
            "type":"Services"
        }
    ],
    "sg:phone":"+43 6216 5164",
    "sg:postcode":"5202",
    "sg:province":"Salzburg",
    "sg:tags":[
        "e-mail",
        "server"
    ],
    "sg:website":"domaintechnik.at",
    "wof:name":"Domaintechnik.at Friedrich Ledl",
    "wof:placetype":"venue"
},
  "geometry": {"coordinates":[13.2246103287,47.9449386597],"type":"Point"}
}