{
  "type": "Feature",
  "properties": {
    "addr:full":"Krottenbachstr 4 Achau Nieder\u00f6sterreich 2481",
    "addr:housenumber":"4",
    "addr:postcode":"2481",
    "addr:street":"Krottenbachstr",
    "iso:country":"AT",
    "sg:address":"Krottenbachstr 4",
    "sg:city":"Achau",
    "sg:orig_category":"Architekten",
    "sg:phone":"+43 2236 71623",
    "sg:postcode":"2481",
    "sg:province":"Nieder\u00f6sterreich",
    "wof:name":"Larndorfer Johann Arch Dipl-Ing",
    "wof:placetype":"venue"
},
  "geometry": {"coordinates":[16.3842697144,48.0821685791],"type":"Point"}
}