{
  "type": "Feature",
  "properties": {
    "addr:full":"Vorgartenstr 92 Wien Wien 1200",
    "addr:housenumber":"92",
    "addr:postcode":"1200",
    "addr:street":"Vorgartenstr",
    "iso:country":"AT",
    "sg:address":"Vorgartenstr 92",
    "sg:city":"Wien",
    "sg:orig_category":"Tischlereien",
    "sg:phone":"+43 1 3325282",
    "sg:postcode":"1200",
    "sg:province":"Wien",
    "wof:name":"Kaufmann Raimund",
    "wof:placetype":"venue"
},
  "geometry": {"coordinates":[16.3908252716,48.2331085205],"type":"Point"}
}