{
  "type": "Feature",
  "properties": {
    "addr:full":"Gudrunstr 114/48 Wien Wien 1100",
    "addr:housenumber":"114 / 48",
    "addr:postcode":"1100",
    "iso:country":"AT",
    "sg:address":"Gudrunstr 114/48",
    "sg:city":"Wien",
    "sg:orig_category":"Immobilienmakler",
    "sg:phone":"+43 1 604377714",
    "sg:postcode":"1100",
    "sg:province":"Wien",
    "wof:name":"Slezak Immobilien GesmbH",
    "wof:placetype":"venue"
},
  "geometry": {"coordinates":[16.3793354034,48.1779823303],"type":"Point"}
}