{
  "type": "Feature",
  "properties": {
    "addr:full":"Aigner Str 83 Salzburg Salzburg 5020",
    "addr:housenumber":"83",
    "addr:postcode":"5020",
    "addr:street":"Str;Salzburg",
    "iso:country":"AT",
    "sg:address":"Aigner Str 83",
    "sg:city":"Salzburg",
    "sg:classifiers":[
        {
            "category":"Taxi",
            "type":"Transportation"
        }
    ],
    "sg:phone":"+43 4366 2636336",
    "sg:postcode":"5020",
    "sg:province":"Salzburg",
    "sg:tags":[
        "personentransporte",
        "u"
    ],
    "wof:name":"Khier Markus Taxiunternehmen",
    "wof:placetype":"venue"
},
  "geometry": {"coordinates":[13.0727300644,47.7930908203],"type":"Point"}
}