{
  "type": "Feature",
  "properties": {
    "addr:full":"Stutterheimstr 16-18/2/302 Wien Wien 1150",
    "addr:housenumber":"16-18 / 2 / 302",
    "addr:postcode":"1150",
    "iso:country":"AT",
    "sg:address":"Stutterheimstr 16-18/2/302",
    "sg:city":"Wien",
    "sg:classifiers":[
        {
            "category":"Organizations",
            "subcategory":"Community Association",
            "type":"Services"
        }
    ],
    "sg:phone":"+43 1 789061260",
    "sg:postcode":"1150",
    "sg:province":"Wien",
    "sg:tags":[
        "relation",
        "public"
    ],
    "wof:name":"ImPressRoom - Agentur f\u00fcr Kommunikation",
    "wof:placetype":"venue"
},
  "geometry": {"coordinates":[16.3320903778,48.2006416321],"type":"Point"}
}