{
  "type": "Feature",
  "properties": {
    "addr:full":"S\u00f6llnerg 3 St. Andr\u00e4 am Zicksee Burgenland 7161",
    "addr:housenumber":"3",
    "addr:postcode":"7161",
    "addr:street":"Soellnerg",
    "iso:country":"AT",
    "sg:address":"S\u00f6llnerg 3",
    "sg:city":"St. Andr\u00e4 am Zicksee",
    "sg:orig_category":"Samen U Saatgut",
    "sg:phone":"+43 4321 762230",
    "sg:postcode":"7161",
    "sg:province":"Burgenland",
    "wof:name":"Austrosaat \u00f6sterr Samenzucht- u Handels AG",
    "wof:placetype":"venue"
},
  "geometry": {"coordinates":[16.9444923401,47.7845726013],"type":"Point"}
}