{
  "type": "Feature",
  "properties": {
    "addr:full":"Wei\u00dfenbach 25 Hinterbr\u00fchl Nieder\u00f6sterreich 2371",
    "addr:housenumber":"25",
    "addr:postcode":"2371",
    "addr:street":"Weissenbach;Niederoesterreich",
    "iso:country":"AT",
    "sg:address":"Wei\u00dfenbach 25",
    "sg:city":"Hinterbr\u00fchl",
    "sg:orig_category":"Alarmanlagen U Sicherheitssysteme",
    "sg:phone":"+43 4322 3642792",
    "sg:postcode":"2371",
    "sg:province":"Nieder\u00f6sterreich",
    "sg:website":"arnold.co.at",
    "wof:name":"Alarmanlagen Arnold",
    "wof:placetype":"venue"
},
  "geometry": {"coordinates":[16.2272663116,48.0805244446],"type":"Point"}
}