{
  "type": "Feature",
  "properties": {
    "addr:full":"Breitenbuch 53 Kirchbach in Steiermark Steiermark 8082",
    "addr:housenumber":"53",
    "addr:postcode":"8082",
    "addr:street":"Breitenbuch",
    "iso:country":"AT",
    "sg:address":"Breitenbuch 53",
    "sg:city":"Kirchbach in Steiermark",
    "sg:orig_category":"Installationsunternehmen",
    "sg:phone":"+43 3116 27462",
    "sg:postcode":"8082",
    "sg:province":"Steiermark",
    "wof:name":"Kahr Gerhard Installationsunternehmen",
    "wof:placetype":"venue"
},
  "geometry": {"coordinates":[15.6700839996,46.9780960083],"type":"Point"}
}