{
  "type": "Feature",
  "properties": {
    "addr:full":"Buchenstr 43 Pinsdorf Ober\u00f6sterreich 4812",
    "addr:housenumber":"43",
    "addr:postcode":"4812",
    "addr:street":"Buchenstr",
    "iso:country":"AT",
    "sg:address":"Buchenstr 43",
    "sg:city":"Pinsdorf",
    "sg:orig_category":"Massagen",
    "sg:phone":"+43 761276743",
    "sg:postcode":"4812",
    "sg:province":"Ober\u00f6sterreich",
    "wof:name":"Kastenhuber Maximillian",
    "wof:placetype":"venue"
},
  "geometry": {"coordinates":[13.781003952,47.9361877441],"type":"Point"}
}