{
  "type": "Feature",
  "properties": {
    "addr:full":"Eitweg K\u00e4rnten 9421",
    "addr:postcode":"9421",
    "addr:street":"Kaernten",
    "iso:country":"AT",
    "sg:city":"Eitweg",
    "sg:orig_category":"Feuerwehren",
    "sg:phone":"+43 4355 2152",
    "sg:postcode":"9421",
    "sg:province":"K\u00e4rnten",
    "wof:name":"Freiwillige Feuerwehr Gemmersdorf",
    "wof:placetype":"venue"
},
  "geometry": {"coordinates":[14.9024848938,46.758190155],"type":"Point"}
}