{
  "type": "Feature",
  "properties": {
    "addr:full":"10.-Oktober-Str 8 Feldkirchen in K\u00e4rnten K\u00e4rnten 9560",
    "addr:housenumber":"8",
    "addr:postcode":"9560",
    "addr:street":"10.-Oktober-Str;Kaernten",
    "iso:country":"AT",
    "sg:address":"10.-Oktober-Str 8",
    "sg:city":"Feldkirchen in K\u00e4rnten",
    "sg:orig_category":"Drogerien",
    "sg:phone":"+43 4342 763311",
    "sg:postcode":"9560",
    "sg:province":"K\u00e4rnten",
    "wof:name":"dm drogerie markt GmbH",
    "wof:placetype":"venue"
},
  "geometry": {"coordinates":[14.0920295715,46.7234268188],"type":"Point"}
}