{
  "type": "Feature",
  "properties": {
    "addr:full":"Schickeng 6 Sulz-R\u00f6this Vorarlberg 6832",
    "addr:housenumber":"6",
    "addr:postcode":"6832",
    "addr:street":"Schickeng",
    "iso:country":"AT",
    "sg:address":"Schickeng 6",
    "sg:city":"Sulz-R\u00f6this",
    "sg:orig_category":"Bauleitung U -Betreuung",
    "sg:phone":"+43 5522 43034",
    "sg:postcode":"6832",
    "sg:province":"Vorarlberg",
    "wof:name":"Hornig Baubetreuungs GmbH",
    "wof:placetype":"venue"
},
  "geometry": {"coordinates":[9.6658267975,47.2794189453],"type":"Point"}
}