{
  "type": "Feature",
  "properties": {
    "addr:full":"Wiener Str 86 Krems an der Donau Nieder\u00f6sterreich 3500",
    "addr:postcode":"3500",
    "addr:street":"86",
    "iso:country":"AT",
    "sg:address":"Wiener Str 86",
    "sg:city":"Krems an der Donau",
    "sg:orig_category":"Autohandel",
    "sg:phone":"+43 2732 78200",
    "sg:postcode":"3500",
    "sg:province":"Nieder\u00f6sterreich",
    "wof:name":"Auer J\u00fcrgen GesmbH & Co KG",
    "wof:placetype":"venue"
},
  "geometry": {"coordinates":[15.6185035706,48.4156951904],"type":"Point"}
}