{
  "type": "Feature",
  "properties": {
    "addr:full":"Leibnitzer Str. 76 Lebring Steiermark 8403",
    "addr:housenumber":"76",
    "addr:postcode":"8403",
    "addr:street":"Str.",
    "iso:country":"AT",
    "sg:address":"Leibnitzer Str. 76",
    "sg:city":"Lebring",
    "sg:classifiers":[
        {
            "category":"Autos & Motor Vehicles",
            "subcategory":"Automobile Sales",
            "type":"Retail Goods"
        }
    ],
    "sg:phone":"+43 4331 8224570",
    "sg:postcode":"8403",
    "sg:province":"Steiermark",
    "sg:tags":[
        "motor-cars"
    ],
    "wof:name":"GADY GES.MBH",
    "wof:placetype":"venue"
},
  "geometry": {"coordinates":[15.53789711,46.8467216492],"type":"Point"}
}