{
  "type": "Feature",
  "properties": {
    "iso:country":"AT",
    "sg:address":"Messendorfgrund 17",
    "sg:city":"St. Peter",
    "sg:orig_category":"Personalbereitstellung",
    "sg:phone":"+43 316 403383",
    "sg:postcode":"8042",
    "sg:province":"Steiermark",
    "wof:name":"Personalleasing Wiedner Alfred",
    "wof:placetype":"venue"
},
  "geometry": {"coordinates":[15.4799203873,47.0419769287],"type":"Point"}
}