{
  "type": "Feature",
  "properties": {
    "addr:full":"Kirchenstr 37 Langenrohr Nieder\u00f6sterreich 3442",
    "addr:housenumber":"37",
    "addr:postcode":"3442",
    "addr:street":"Kirchenstr",
    "iso:country":"AT",
    "sg:address":"Kirchenstr 37",
    "sg:city":"Langenrohr",
    "sg:orig_category":"Non-Classified Establishments",
    "sg:phone":"+43 2272 7234",
    "sg:postcode":"3442",
    "sg:province":"Nieder\u00f6sterreich",
    "wof:name":"Pfarramt",
    "wof:placetype":"venue"
},
  "geometry": {"coordinates":[16.0053596497,48.3069190979],"type":"Point"}
}