{
  "type": "Feature",
  "properties": {
    "iso:country":"AT",
    "sg:address":"Dr.-K\u00f6rner-Strasse 6",
    "sg:city":"Trumau",
    "sg:orig_category":"Half Cabins For Fork Lift Trucks",
    "sg:phone":"+43 2253 62640",
    "sg:postcode":"2521",
    "sg:province":"Nieder\u00f6sterreich",
    "wof:name":"Ernst Hofmann Ges.m.b.H.",
    "wof:placetype":"venue"
},
  "geometry": {"coordinates":[16.3445339203,47.9976997375],"type":"Point"}
}