{
  "type": "Feature",
  "properties": {
    "addr:full":"Parschluger Str 32 Kapfenberg Steiermark 8605",
    "addr:postcode":"8605",
    "addr:street":"Str 32",
    "iso:country":"AT",
    "sg:address":"Parschluger Str 32",
    "sg:city":"Kapfenberg",
    "sg:orig_category":"Handelsagenturen",
    "sg:phone":"+43 3862 21624",
    "sg:postcode":"8605",
    "sg:province":"Steiermark",
    "wof:name":"Reithofer Peter",
    "wof:placetype":"venue"
},
  "geometry": {"coordinates":[15.3163604736,47.4747123718],"type":"Point"}
}