{
  "type": "Feature",
  "properties": {
    "iso:country":"AT",
    "sg:address":"Goldbergstr 16",
    "sg:city":"Bad Hofgastein",
    "sg:orig_category":"Pensionen / Privatzimmer",
    "sg:phone":"+43 6432 6608",
    "sg:postcode":"5630",
    "sg:province":"Salzburg",
    "wof:name":"Piller Katharina",
    "wof:placetype":"venue"
},
  "geometry": {"coordinates":[13.1024103165,47.1744232178],"type":"Point"}
}