{
  "type": "Feature",
  "properties": {
    "iso:country":"AT",
    "sg:address":"Gritzen 32",
    "sg:city":"St. Veit in Defereggen",
    "sg:orig_category":"Telefonanlagen",
    "sg:phone":"+43 4369 913338000",
    "sg:postcode":"9962",
    "sg:province":"Tirol",
    "sg:website":"berger-com.com",
    "wof:name":"Berger Communication",
    "wof:placetype":"venue"
},
  "geometry": {"coordinates":[12.4097270966,46.9206619263],"type":"Point"}
}