{
  "type": "Feature",
  "properties": {
    "iso:country":"AT",
    "sg:address":"Weinzierler Str 8",
    "sg:city":"Bad Leonfelden",
    "sg:orig_category":"Transportunternehmen",
    "sg:phone":"+43 7213 6468",
    "sg:postcode":"4190",
    "sg:province":"Ober\u00f6sterreich",
    "wof:name":"Baumgartner G\u00fctertransport GesmbH",
    "wof:placetype":"venue"
},
  "geometry": {"coordinates":[14.2995882034,48.5223121643],"type":"Point"}
}