{
  "type": "Feature",
  "properties": {
    "iso:country":"AT",
    "sg:address":"Alexanderhofstr 250",
    "sg:city":"Millstatt",
    "sg:classifiers":[
        {
            "category":"Wholesale",
            "subcategory":"Stationery",
            "type":"Manufacturing & Wholesale Goods"
        }
    ],
    "sg:phone":"+43 4347 662991",
    "sg:postcode":"9872",
    "sg:province":"K\u00e4rnten",
    "sg:tags":[
        "sport-",
        "u",
        "sponsoring-agenturen"
    ],
    "wof:name":"WESCO Werthner Sport Consulting KEG",
    "wof:placetype":"venue"
},
  "geometry": {"coordinates":[13.5624103546,46.809261322],"type":"Point"}
}