{
  "type": "Feature",
  "properties": {
    "addr:full":"Raiffeisenstr. 38-40 Graz Steiermark 8010",
    "addr:postcode":"38-40;8010",
    "iso:country":"AT",
    "sg:address":"Raiffeisenstr. 38-40",
    "sg:city":"Graz",
    "sg:classifiers":[
        {
            "category":"Manufacturing",
            "subcategory":"Motor Vehicles & Parts",
            "type":"Manufacturing & Wholesale Goods"
        }
    ],
    "sg:phone":"+43 4331 64715240",
    "sg:postcode":"8010",
    "sg:province":"Steiermark",
    "sg:tags":[
        "engine"
    ],
    "wof:name":"KUMMERA ANTRIEBSTECHNK GMBH",
    "wof:placetype":"venue"
},
  "geometry": {"coordinates":[15.4467725754,47.0529937744],"type":"Point"}
}