{
  "type": "Feature",
  "properties": {
    "addr:full":"Erzstr 21 Leoben Steiermark 8700",
    "addr:housenumber":"21",
    "addr:postcode":"8700",
    "addr:street":"Erzstr",
    "iso:country":"AT",
    "sg:address":"Erzstr 21",
    "sg:city":"Leoben",
    "sg:orig_category":"Weiterbildungsinstitute M Allg U Berufl Bildungsangebot",
    "sg:phone":"+43 3842 268660",
    "sg:postcode":"8700",
    "sg:province":"Steiermark",
    "wof:name":"BFI Berufsf\u00f6rderungsinstitut",
    "wof:placetype":"venue"
},
  "geometry": {"coordinates":[15.0623264313,47.3783721924],"type":"Point"}
}