{
  "type": "Feature",
  "properties": {
    "addr:full":"Baumgarten 18 Reichenau im M\u00fchlkreis Ober\u00f6sterreich 4204",
    "addr:housenumber":"18",
    "addr:postcode":"4204",
    "addr:street":"Baumgarten;Im Muehlkreis Oberoesterreich",
    "iso:country":"AT",
    "sg:address":"Baumgarten 18",
    "sg:city":"Reichenau im M\u00fchlkreis",
    "sg:orig_category":"Werbegestalter",
    "sg:phone":"+43 7211 20045",
    "sg:postcode":"4204",
    "sg:province":"Ober\u00f6sterreich",
    "wof:name":"Fragner Simone - Schauwerbegestaltung",
    "wof:placetype":"venue"
},
  "geometry": {"coordinates":[14.3540039062,48.4218597412],"type":"Point"}
}