{
  "type": "Feature",
  "properties": {
    "iso:country":"AT",
    "sg:address":"Riesstrasse 102",
    "sg:city":"Graz",
    "sg:orig_category":"Furniture, General",
    "sg:phone":"+43 316 321592",
    "sg:postcode":"8010",
    "sg:province":"Steiermark",
    "wof:name":"Kompacher GesmbH",
    "wof:placetype":"venue"
},
  "geometry": {"coordinates":[15.4675369263,47.0790405273],"type":"Point"}
}