{
  "type": "Feature",
  "properties": {
    "addr:full":"Werndlstr 25 Gallspach Ober\u00f6sterreich 4713",
    "addr:housenumber":"25",
    "addr:postcode":"4713",
    "addr:street":"Werndlstr",
    "iso:country":"AT",
    "sg:address":"Werndlstr 25",
    "sg:city":"Gallspach",
    "sg:orig_category":"Handelsagenturen",
    "sg:phone":"+43 7248 68572",
    "sg:postcode":"4713",
    "sg:province":"Ober\u00f6sterreich",
    "wof:name":"Sallaberger Georg",
    "wof:placetype":"venue"
},
  "geometry": {"coordinates":[13.8185710907,48.2040748596],"type":"Point"}
}