{
  "type": "Feature",
  "properties": {
    "iso:country":"AT",
    "sg:address":"Pyrkerstr 20",
    "sg:city":"Bad Hofgastein",
    "sg:classifiers":[
        {
            "category":"Restaurant",
            "type":"Food & Drink"
        }
    ],
    "sg:phone":"+43 6432 6335",
    "sg:postcode":"5630",
    "sg:province":"Salzburg",
    "wof:name":"Tr\u00f6pferl",
    "wof:placetype":"venue"
},
  "geometry": {"coordinates":[13.1087388992,47.1695861816],"type":"Point"}
}