{
  "type": "Feature",
  "properties": {
    "iso:country":"AT",
    "sg:address":"Bahnhofstr 81",
    "sg:city":"Feistritz an der Drau",
    "sg:orig_category":"Wasserbetten",
    "sg:phone":"+43 4245 2327",
    "sg:postcode":"9710",
    "sg:province":"K\u00e4rnten",
    "wof:name":"Lesacher Hermann Dipl-Ing Dr",
    "wof:placetype":"venue"
},
  "geometry": {"coordinates":[13.6812143326,46.6893577576],"type":"Point"}
}