{
  "type": "Feature",
  "properties": {
    "addr:full":"Ziegelgraben 3 Krenglbach Ober\u00f6sterreich 4631",
    "addr:housenumber":"3",
    "addr:postcode":"4631",
    "addr:street":"Ziegelgraben",
    "iso:country":"AT",
    "sg:address":"Ziegelgraben 3",
    "sg:city":"Krenglbach",
    "sg:orig_category":"Fleischereimaschinen U -Einrichtungen",
    "sg:phone":"+43 4372 4946178",
    "sg:postcode":"4631",
    "sg:province":"Ober\u00f6sterreich",
    "wof:name":"Hygiene & Lebensmitteltechnik - G Lischka",
    "wof:placetype":"venue"
},
  "geometry": {"coordinates":[13.9719200134,48.1940116882],"type":"Point"}
}