{
  "type": "Feature",
  "properties": {
    "addr:full":"Franz-Aringer-Str 14 Hausleiten Nieder\u00f6sterreich 3464",
    "addr:housenumber":"14",
    "addr:postcode":"3464",
    "addr:street":"Franz-Aringer-Str",
    "iso:country":"AT",
    "sg:address":"Franz-Aringer-Str 14",
    "sg:city":"Hausleiten",
    "sg:orig_category":"Holzhandel",
    "sg:phone":"+43 2265 6470",
    "sg:postcode":"3464",
    "sg:province":"Nieder\u00f6sterreich",
    "wof:name":"Gass Johann",
    "wof:placetype":"venue"
},
  "geometry": {"coordinates":[16.1117191315,48.3915214539],"type":"Point"}
}