{
  "type": "Feature",
  "properties": {
    "iso:country":"AT",
    "sg:address":"Hauptstr 14",
    "sg:city":"Hermagor",
    "sg:orig_category":"Tourismusinformation U -Organisationen",
    "sg:phone":"+43 4282 31310",
    "sg:postcode":"9620",
    "sg:province":"K\u00e4rnten",
    "wof:name":"Karnische Tourismus GesmbH",
    "wof:placetype":"venue"
},
  "geometry": {"coordinates":[13.3681230545,46.6274490356],"type":"Point"}
}