{
  "type": "Feature",
  "properties": {
    "addr:full":"Jakominipl 18 Graz Steiermark 8010",
    "addr:housenumber":"18",
    "addr:postcode":"8010",
    "addr:street":"Jakominipl",
    "iso:country":"AT",
    "sg:address":"Jakominipl 18",
    "sg:city":"Graz",
    "sg:orig_category":"Bildungsservice / Allgemeine Informationsstellen",
    "sg:phone":"+43 316 821137",
    "sg:postcode":"8010",
    "sg:province":"Steiermark",
    "wof:name":"S\u00fcdwind-Agentur Die Agentur f S\u00fcd-Nord Bildungs-u \u00d6ffentlichkeitsarbeit GesmbH",
    "wof:placetype":"venue"
},
  "geometry": {"coordinates":[15.4416189194,47.0666923523],"type":"Point"}
}