{
  "type": "Feature",
  "properties": {
    "addr:full":"Kieferng 7 Ternitz Nieder\u00f6sterreich 2630",
    "addr:housenumber":"7",
    "addr:postcode":"2630",
    "addr:street":"Kieferng",
    "iso:country":"AT",
    "sg:address":"Kieferng 7",
    "sg:city":"Ternitz",
    "sg:orig_category":"Musikverlage",
    "sg:phone":"+43 4326 3030190",
    "sg:postcode":"2630",
    "sg:province":"Nieder\u00f6sterreich",
    "wof:name":"Jet Sound Music Musikverlag u Produktion Kurt Brunthaler",
    "wof:placetype":"venue"
},
  "geometry": {"coordinates":[16.0438518524,47.7093238831],"type":"Point"}
}