{
  "type": "Feature",
  "properties": {
    "addr:full":"Reitschulg 15A St. Margarethen im Burgenland Burgenland 7062",
    "addr:housenumber":"15a",
    "addr:postcode":"7062",
    "addr:street":"Reitschulg",
    "iso:country":"AT",
    "sg:address":"Reitschulg 15A",
    "sg:city":"St. Margarethen im Burgenland",
    "sg:orig_category":"\u00c3\u201erzte / F Allgemeinmedizin",
    "sg:phone":"+43 4326 807071",
    "sg:postcode":"7062",
    "sg:province":"Burgenland",
    "wof:name":"Haberhauer Arnold Dr",
    "wof:placetype":"venue"
},
  "geometry": {"coordinates":[16.6044235229,47.7992286682],"type":"Point"}
}