{
  "type": "Feature",
  "properties": {
    "addr:full":"Franz-Fischer-Str 7 Innsbruck Tirol 6020",
    "addr:housenumber":"7",
    "addr:postcode":"6020",
    "addr:street":"Franz-Fischer-Str;Tirol",
    "iso:country":"AT",
    "sg:address":"Franz-Fischer-Str 7",
    "sg:city":"Innsbruck",
    "sg:classifiers":[
        {
            "category":"Organizations",
            "subcategory":"Community Association",
            "type":"Services"
        }
    ],
    "sg:phone":"+43 512 5638400",
    "sg:postcode":"6020",
    "sg:province":"Tirol",
    "sg:tags":[
        "relation",
        "public"
    ],
    "wof:name":"wiko wirtschaftskommunikation GmbH",
    "wof:placetype":"venue"
},
  "geometry": {"coordinates":[11.3950386047,47.2581558228],"type":"Point"}
}