{
  "type": "Feature",
  "properties": {
    "addr:full":"Netzg 11 Graz Steiermark 8020",
    "addr:housenumber":"11",
    "addr:postcode":"8020",
    "addr:street":"Netzg",
    "iso:country":"AT",
    "sg:address":"Netzg 11",
    "sg:city":"Graz",
    "sg:orig_category":"Automaten",
    "sg:phone":"+43 316 714468",
    "sg:postcode":"8020",
    "sg:province":"Steiermark",
    "wof:name":"Lindenau & Co GesmbH",
    "wof:placetype":"venue"
},
  "geometry": {"coordinates":[15.4310359955,47.0777854919],"type":"Point"}
}