{
  "type": "Feature",
  "properties": {
    "iso:country":"AT",
    "sg:address":"Waltersdorfer Strasse 31",
    "sg:city":"Baden",
    "sg:classifiers":[
        {
            "category":"Professional",
            "subcategory":"Advertising",
            "type":"Services"
        }
    ],
    "sg:phone":"+43 2252 254106",
    "sg:postcode":"2500",
    "sg:province":"Nieder\u00f6sterreich",
    "sg:tags":[
        "gift"
    ],
    "sg:website":"www.xxpro.at",
    "wof:name":"xpro-WarenhandelsgesmbH",
    "wof:placetype":"venue"
},
  "geometry": {"coordinates":[16.2476978302,48.0013961792],"type":"Point"}
}