{
  "type": "Feature",
  "properties": {
    "addr:full":"Nr 73 Goldegg Salzburg 5622",
    "addr:postcode":"5622",
    "addr:street":"Nr 73;Salzburg",
    "iso:country":"AT",
    "sg:address":"Nr 73",
    "sg:city":"Goldegg",
    "sg:orig_category":"Physiotherapie",
    "sg:phone":"+43 6415 8565",
    "sg:postcode":"5622",
    "sg:province":"Salzburg",
    "wof:name":"Dum Eva Dipl-PT",
    "wof:placetype":"venue"
},
  "geometry": {"coordinates":[13.0795726776,47.3298606873],"type":"Point"}
}