{
  "type": "Feature",
  "properties": {
    "addr:full":"Raabser Str 64 Horn Nieder\u00f6sterreich 3580",
    "addr:housenumber":"64",
    "addr:postcode":"3580",
    "addr:street":"Str",
    "iso:country":"AT",
    "sg:address":"Raabser Str 64",
    "sg:city":"Horn",
    "sg:orig_category":"Lebensmittel / Einzelhandel",
    "sg:phone":"+43 2982 60136",
    "sg:postcode":"3580",
    "sg:province":"Nieder\u00f6sterreich",
    "wof:name":"SPAR \u00f6sterreichische Warenhandels-AG",
    "wof:placetype":"venue"
},
  "geometry": {"coordinates":[15.6517629623,48.6736679077],"type":"Point"}
}