{
  "type": "Feature",
  "properties": {
    "addr:full":"Inzenreithstr 1 Eschenau an der Traisen Nieder\u00f6sterreich 3153",
    "addr:housenumber":"1",
    "addr:postcode":"3153",
    "addr:street":"Inzenreithstr",
    "iso:country":"AT",
    "sg:address":"Inzenreithstr 1",
    "sg:city":"Eschenau an der Traisen",
    "sg:orig_category":"Lebensmittel / Einzelhandel",
    "sg:phone":"+43 4327 6267267",
    "sg:postcode":"3153",
    "sg:province":"Nieder\u00f6sterreich",
    "wof:name":"Spar Markt - Edith Nagl",
    "wof:placetype":"venue"
},
  "geometry": {"coordinates":[15.5678768158,48.0486564636],"type":"Point"}
}