{
  "type": "Feature",
  "properties": {
    "addr:full":"Inntalcenter Kufstein Tirol 6330",
    "addr:postcode":"6330",
    "iso:country":"AT",
    "sg:address":"Inntalcenter",
    "sg:city":"Kufstein",
    "sg:orig_category":"Damenmoden",
    "sg:phone":"+43 5372 65120",
    "sg:postcode":"6330",
    "sg:province":"Tirol",
    "wof:name":"Top Line HandelsgmbH",
    "wof:placetype":"venue"
},
  "geometry": {"coordinates":[12.1717987061,47.5847892761],"type":"Point"}
}