{
  "type": "Feature",
  "properties": {
    "iso:country":"AT",
    "sg:address":"Hauptpl 3",
    "sg:city":"Graz",
    "sg:orig_category":"Lebensmittel / Einzelhandel",
    "sg:phone":"+43 316 850240",
    "sg:postcode":"8010",
    "sg:province":"Steiermark",
    "wof:name":"Billa AG Abt Corso",
    "wof:placetype":"venue"
},
  "geometry": {"coordinates":[15.4378662109,47.0706329346],"type":"Point"}
}