{
  "type": "Feature",
  "properties": {
    "iso:country":"AT",
    "sg:address":"Keilerg 88a",
    "sg:city":"Schlitters",
    "sg:orig_category":"Graveure",
    "sg:phone":"+43 4352 8887106",
    "sg:postcode":"6262",
    "sg:province":"Tirol",
    "wof:name":"Neuhold Hermine",
    "wof:placetype":"venue"
},
  "geometry": {"coordinates":[11.850769043,47.3908348083],"type":"Point"}
}