{
  "type": "Feature",
  "properties": {
    "addr:full":"Loibacher Str 13 Bleiburg K\u00e4rnten 9150",
    "addr:housenumber":"13",
    "addr:postcode":"9150",
    "addr:street":"Str;Kaernten",
    "iso:country":"AT",
    "sg:address":"Loibacher Str 13",
    "sg:city":"Bleiburg",
    "sg:orig_category":"Non-Classified Establishments",
    "sg:phone":"+43 4235 21040",
    "sg:postcode":"9150",
    "sg:province":"K\u00e4rnten",
    "wof:name":"Bundesheer Goigingerkaserne",
    "wof:placetype":"venue"
},
  "geometry": {"coordinates":[14.7998247147,46.5818023682],"type":"Point"}
}