{
  "type": "Feature",
  "properties": {
    "iso:country":"AT",
    "sg:address":"Faistenbichl 6",
    "sg:city":"Ellmau",
    "sg:classifiers":[
        {
            "category":"Travel",
            "subcategory":"Hotels & Motels",
            "type":"Entertainment"
        }
    ],
    "sg:phone":"+43 5358 35350",
    "sg:postcode":"6352",
    "sg:province":"Tirol",
    "wof:name":"Hotel Christoph",
    "wof:placetype":"venue"
},
  "geometry": {"coordinates":[12.2733459473,47.5127296448],"type":"Point"}
}