{
  "type": "Feature",
  "properties": {
    "iso:country":"AT",
    "sg:address":"Dorfstr 29",
    "sg:city":"Vandans",
    "sg:orig_category":"Friseure U Frisiersalons",
    "sg:phone":"+43 5556 73536",
    "sg:postcode":"6773",
    "sg:province":"Vorarlberg",
    "wof:name":"Piesl Renate",
    "wof:placetype":"venue"
},
  "geometry": {"coordinates":[9.864613533,47.0965232849],"type":"Point"}
}