{
  "type": "Feature",
  "properties": {
    "addr:full":"Nachts\u00f6llberg 99 Westendorf Tirol 6363",
    "addr:housenumber":"99",
    "addr:postcode":"6363",
    "addr:street":"Nachtsoellberg;Tirol",
    "iso:country":"AT",
    "sg:address":"Nachts\u00f6llberg 99",
    "sg:city":"Westendorf",
    "sg:classifiers":[
        {
            "category":"Restaurant",
            "type":"Food & Drink"
        }
    ],
    "sg:phone":"+43 5334 6129",
    "sg:postcode":"6363",
    "sg:province":"Tirol",
    "wof:name":"Bergrestaurant Choralpe",
    "wof:placetype":"venue"
},
  "geometry": {"coordinates":[12.2147397995,47.4321594238],"type":"Point"}
}