{
  "type": "Feature",
  "properties": {
    "addr:full":"Nr 125 Katsch an der Mur Steiermark 8842",
    "addr:postcode":"8842",
    "addr:street":"Nr",
    "iso:country":"AT",
    "sg:address":"Nr 125",
    "sg:city":"Katsch an der Mur",
    "sg:orig_category":"Schneidereien",
    "sg:phone":"+43 3588 5200",
    "sg:postcode":"8842",
    "sg:province":"Steiermark",
    "wof:name":"Gusel Kurt",
    "wof:placetype":"venue"
},
  "geometry": {"coordinates":[14.282959938,47.1429824829],"type":"Point"}
}