{
  "type": "Feature",
  "properties": {
    "iso:country":"AT",
    "sg:address":"Pappelstrasse 2",
    "sg:city":"Langenzersdorf",
    "sg:classifiers":[
        {
            "category":"Wholesale",
            "subcategory":"Fruits & Vegetables",
            "type":"Manufacturing & Wholesale Goods"
        }
    ],
    "sg:phone":"+43 2244 307990",
    "sg:postcode":"2103",
    "sg:province":"Nieder\u00f6sterreich",
    "sg:tags":[
        "product",
        "cereal"
    ],
    "sg:website":"biogast.at",
    "wof:name":"BIOGAST GmbH",
    "wof:placetype":"venue"
},
  "geometry": {"coordinates":[16.363073349,48.2865447998],"type":"Point"}
}