{
  "type": "Feature",
  "properties": {
    "addr:full":"Braunsdorfer Str 17 Krems an der Donau Nieder\u00f6sterreich 3500",
    "addr:postcode":"3500",
    "addr:street":"Str 17",
    "iso:country":"AT",
    "sg:address":"Braunsdorfer Str 17",
    "sg:city":"Krems an der Donau",
    "sg:orig_category":"Ingenieurkonsulenten / Zivilingenieure",
    "sg:phone":"+43 2732 412800",
    "sg:postcode":"3500",
    "sg:province":"Nieder\u00f6sterreich",
    "wof:name":"HARRER ANTON DIPL-ING Ziviltechniker GesmbH",
    "wof:placetype":"venue"
},
  "geometry": {"coordinates":[15.5636501312,48.4168510437],"type":"Point"}
}