{
  "type": "Feature",
  "properties": {
    "iso:country":"AT",
    "sg:address":"Am Kanal 111",
    "sg:city":"Wien",
    "sg:orig_category":"Tischlereien",
    "sg:phone":"+43 1 7682389",
    "sg:postcode":"1110",
    "sg:province":"Wien",
    "wof:name":"ALST Design Heinrich KEG",
    "wof:placetype":"venue"
},
  "geometry": {"coordinates":[16.4222812653,48.1617546082],"type":"Point"}
}