{
  "type": "Feature",
  "properties": {
    "addr:full":"Nr 36 Bad Hofgastein Salzburg 5630",
    "addr:housenumber":"36",
    "addr:postcode":"5630",
    "addr:street":"Nr;Salzburg",
    "iso:country":"AT",
    "sg:address":"Nr 36",
    "sg:city":"Bad Hofgastein",
    "sg:orig_category":"Pensionen / Privatzimmer",
    "sg:phone":"+43 6432 2546",
    "sg:postcode":"5630",
    "sg:province":"Salzburg",
    "wof:name":"Lackenbauerhof - Gasthaus-Pension",
    "wof:placetype":"venue"
},
  "geometry": {"coordinates":[13.1028347015,47.1707115173],"type":"Point"}
}