{
  "type": "Feature",
  "properties": {
    "iso:country":"AT",
    "sg:address":"Wagramer Str 134",
    "sg:city":"Wien",
    "sg:orig_category":"Friseure U Frisiersalons",
    "sg:phone":"+43 4312 030340",
    "sg:postcode":"1220",
    "sg:province":"Wien",
    "wof:name":"K\u00f6rperkult - Peter Vogelauer",
    "wof:placetype":"venue"
},
  "geometry": {"coordinates":[16.442199707,48.2482643127],"type":"Point"}
}