{
  "type": "Feature",
  "properties": {
    "addr:full":"Gr\u00fcnschacher Weg 36 Villach K\u00e4rnten 9500",
    "addr:housenumber":"36",
    "addr:postcode":"9500",
    "addr:street":"Gruenschacher Weg;Kaernten",
    "iso:country":"AT",
    "sg:address":"Gr\u00fcnschacher Weg 36",
    "sg:city":"Villach",
    "sg:classifiers":[
        {
            "category":"Home & Garden",
            "subcategory":"Building Materials",
            "type":"Retail Goods"
        }
    ],
    "sg:phone":"+43 4242 582413",
    "sg:postcode":"9500",
    "sg:province":"K\u00e4rnten",
    "sg:tags":[
        "installation",
        "electric"
    ],
    "wof:name":"EHW Elektroinstallations GmbH",
    "wof:placetype":"venue"
},
  "geometry": {"coordinates":[13.8491945267,46.618106842],"type":"Point"}
}