{
  "type": "Feature",
  "properties": {
    "addr:full":"Nr 235 Miesenbach Nieder\u00f6sterreich 2761",
    "addr:postcode":"2761",
    "addr:street":"Nr;Miesenbach",
    "iso:country":"AT",
    "sg:address":"Nr 235",
    "sg:city":"Miesenbach",
    "sg:orig_category":"Abfallentsorgung U -Verwertung",
    "sg:phone":"+43 4326 328547",
    "sg:postcode":"2761",
    "sg:province":"Nieder\u00f6sterreich",
    "wof:name":"Wertstoffzentrum der Gemeinde Miesenbach",
    "wof:placetype":"venue"
},
  "geometry": {"coordinates":[15.9799060822,47.8700790405],"type":"Point"}
}