{
  "type": "Feature",
  "properties": {
    "addr:full":"Simmeringer Hauptstrasse 13 Wien Wien 1110",
    "addr:housenumber":"13",
    "addr:postcode":"1110",
    "addr:street":"Simmeringer Hauptstrasse",
    "iso:country":"AT",
    "sg:address":"Simmeringer Hauptstrasse 13",
    "sg:city":"Wien",
    "sg:classifiers":[
        {
            "category":"Utilities",
            "subcategory":"Natural Gas",
            "type":"Services"
        }
    ],
    "sg:phone":"+43 1 7497120",
    "sg:postcode":"1110",
    "sg:province":"Wien",
    "sg:tags":[
        "heater",
        "electric"
    ],
    "wof:name":"Elektro-Friedrich GmbH",
    "wof:placetype":"venue"
},
  "geometry": {"coordinates":[16.4067420959,48.1832199097],"type":"Point"}
}