{
  "type": "Feature",
  "properties": {
    "iso:country":"AT",
    "sg:address":"Aichfeld 112",
    "sg:city":"Krieglach",
    "sg:orig_category":"Installationsunternehmen",
    "sg:phone":"+43 3855 27070",
    "sg:postcode":"8670",
    "sg:province":"Steiermark",
    "wof:name":"K\u00f6nigshofer Rudolf",
    "wof:placetype":"venue"
},
  "geometry": {"coordinates":[15.5516910553,47.5423698425],"type":"Point"}
}