{
  "type": "Feature",
  "properties": {
    "addr:full":"Neues Feld 1 Pinkafeld Burgenland 7423",
    "addr:housenumber":"1",
    "addr:postcode":"7423",
    "addr:street":"Neues Feld",
    "iso:country":"AT",
    "sg:address":"Neues Feld 1",
    "sg:city":"Pinkafeld",
    "sg:orig_category":"Futtermittel",
    "sg:phone":"+43 4333 592871",
    "sg:postcode":"7423",
    "sg:province":"Burgenland",
    "wof:name":"MSO Mischanlagen S\u00fcd Ost BetriebsgesmbH u Co KG",
    "wof:placetype":"venue"
},
  "geometry": {"coordinates":[16.124250412,47.3718299866],"type":"Point"}
}