{
  "type": "Feature",
  "properties": {
    "addr:full":"Eisenstr 45 Losenstein Ober\u00f6sterreich 4460",
    "addr:housenumber":"45",
    "addr:postcode":"4460",
    "addr:street":"Eisenstr",
    "iso:country":"AT",
    "sg:address":"Eisenstr 45",
    "sg:city":"Losenstein",
    "sg:orig_category":"Tourismusinformation U -Organisationen",
    "sg:phone":"+43 7255 60000",
    "sg:postcode":"4460",
    "sg:province":"Ober\u00f6sterreich",
    "wof:name":"Tourismusverband",
    "wof:placetype":"venue"
},
  "geometry": {"coordinates":[14.4326095581,47.9263267517],"type":"Point"}
}