{
  "type": "Feature",
  "properties": {
    "addr:full":"Plenerg 15 Wien Wien 1180",
    "addr:housenumber":"15",
    "addr:postcode":"1180",
    "addr:street":"Plenerg",
    "iso:country":"AT",
    "sg:address":"Plenerg 15",
    "sg:city":"Wien",
    "sg:orig_category":"Messen U Ausstellungen",
    "sg:phone":"+43 1 4027355",
    "sg:postcode":"1180",
    "sg:province":"Wien",
    "wof:name":"IMPULS messegesmbH",
    "wof:placetype":"venue"
},
  "geometry": {"coordinates":[16.3367443085,48.2270050049],"type":"Point"}
}