{
  "type": "Feature",
  "properties": {
    "addr:full":"Kanaltaler Str 17 Klagenfurt K\u00e4rnten 9020",
    "addr:housenumber":"17",
    "addr:postcode":"9020",
    "addr:street":"Str;Kaernten",
    "iso:country":"AT",
    "sg:address":"Kanaltaler Str 17",
    "sg:city":"Klagenfurt",
    "sg:classifiers":[
        {
            "category":"Professional",
            "subcategory":"Testing Lab",
            "type":"Services"
        }
    ],
    "sg:phone":"+43 463 245645",
    "sg:postcode":"9020",
    "sg:province":"K\u00e4rnten",
    "sg:tags":[
        "magistrate"
    ],
    "wof:name":"Magistrat der Landeshauptstadt Klagenfurt - Infostelle",
    "wof:placetype":"venue"
},
  "geometry": {"coordinates":[14.28495121,46.6136054993],"type":"Point"}
}