{
  "type": "Feature",
  "properties": {
    "addr:full":"Ferihumerstr 38 Linz Ober\u00f6sterreich 4040",
    "addr:housenumber":"38",
    "addr:postcode":"4040",
    "addr:street":"Ferihumerstr",
    "iso:country":"AT",
    "sg:address":"Ferihumerstr 38",
    "sg:city":"Linz",
    "sg:orig_category":"\u00c3\u201erzte / F Allgemeinmedizin",
    "sg:phone":"+43 676 6861860",
    "sg:postcode":"4040",
    "sg:province":"Ober\u00f6sterreich",
    "wof:name":"Kicin Jasim Dr",
    "wof:placetype":"venue"
},
  "geometry": {"coordinates":[14.2891435623,48.3147926331],"type":"Point"}
}