{
  "type": "Feature",
  "properties": {
    "addr:full":"Gartenstr 446 Wals Salzburg 5071",
    "addr:housenumber":"446",
    "addr:postcode":"5071",
    "addr:street":"Wals Salzburg",
    "iso:country":"AT",
    "sg:address":"Gartenstr 446",
    "sg:city":"Wals",
    "sg:orig_category":"Garten- U Landschaftsgestaltung",
    "sg:phone":"+43 662 855121",
    "sg:postcode":"5071",
    "sg:province":"Salzburg",
    "wof:name":"Vogel Gerhard",
    "wof:placetype":"venue"
},
  "geometry": {"coordinates":[12.9826545715,47.8063964844],"type":"Point"}
}