{
  "type": "Feature",
  "properties": {
    "iso:country":"AT",
    "sg:address":"Nr 194",
    "sg:city":"Leibnitz",
    "sg:orig_category":"Antriebstechnik",
    "sg:phone":"+43 3452 76708",
    "sg:postcode":"8430",
    "sg:province":"Steiermark",
    "wof:name":"SANKYO Oilless Industries GmbH",
    "wof:placetype":"venue"
},
  "geometry": {"coordinates":[15.5377645493,46.7811355591],"type":"Point"}
}