{
  "type": "Feature",
  "properties": {
    "iso:country":"AT",
    "sg:address":"Nr 90",
    "sg:city":"Aigen im Ennstal",
    "sg:orig_category":"Installationsunternehmen",
    "sg:phone":"+43 4336 82239000",
    "sg:postcode":"8943",
    "sg:province":"Steiermark",
    "wof:name":"H\u00e4usler Peter - Gas Wasser Heizung",
    "wof:placetype":"venue"
},
  "geometry": {"coordinates":[14.1433391571,47.5205230713],"type":"Point"}
}