{
  "type": "Feature",
  "properties": {
    "addr:full":"Heinrich-Ott-Gasse 2/i Laxenburg Nieder\u00f6sterreich 2361",
    "addr:housenumber":"2 / i",
    "addr:postcode":"2361",
    "addr:street":"Heinrich-Ott-Gasse",
    "iso:country":"AT",
    "sg:address":"Heinrich-Ott-Gasse 2/i",
    "sg:city":"Laxenburg",
    "sg:classifiers":[
        {
            "category":"Communications",
            "subcategory":"Film & Video Production",
            "type":"Services"
        }
    ],
    "sg:phone":"+43 2236 710392",
    "sg:postcode":"2361",
    "sg:province":"Nieder\u00f6sterreich",
    "sg:tags":[
        "recording",
        "data"
    ],
    "sg:website":"bueroservice-bednar.com",
    "wof:name":"b\u00fcroservice-bednar",
    "wof:placetype":"venue"
},
  "geometry": {"coordinates":[16.3462543488,48.0644035339],"type":"Point"}
}