{
  "type": "Feature",
  "properties": {
    "addr:full":"Nr 28 Egg K\u00e4rnten 9624",
    "addr:housenumber":"9624",
    "addr:street":"Nr;Egg Kaernten",
    "iso:country":"AT",
    "sg:address":"Nr 28",
    "sg:city":"Egg",
    "sg:orig_category":"Volksschulen",
    "sg:phone":"+43 4342 822638",
    "sg:postcode":"9624",
    "sg:province":"K\u00e4rnten",
    "wof:name":"Volksschule",
    "wof:placetype":"venue"
},
  "geometry": {"coordinates":[13.4396696091,46.6203384399],"type":"Point"}
}