{
  "type": "Feature",
  "properties": {
    "iso:country":"AT",
    "sg:address":"Am Messezentrum 6",
    "sg:city":"Salzburg",
    "sg:orig_category":"Alarmanlagen U Sicherheitssysteme",
    "sg:phone":"+43 662 449770",
    "sg:postcode":"5020",
    "sg:province":"Salzburg",
    "wof:name":"System Objekt Schutz GesmbH",
    "wof:placetype":"venue"
},
  "geometry": {"coordinates":[13.0279626846,47.8223457336],"type":"Point"}
}