{
  "type": "Feature",
  "properties": {
    "addr:full":"Oberndorfer Str 47 Kirchbichl Tirol 6322",
    "addr:housenumber":"47",
    "addr:postcode":"6322",
    "addr:street":"Oberndorfer Str;Tirol",
    "iso:country":"AT",
    "sg:address":"Oberndorfer Str 47",
    "sg:city":"Kirchbichl",
    "sg:orig_category":"Damenmoden",
    "sg:phone":"+43 5332 87173",
    "sg:postcode":"6322",
    "sg:province":"Tirol",
    "wof:name":"Daxacher-Moden GesmbH",
    "wof:placetype":"venue"
},
  "geometry": {"coordinates":[12.0850296021,47.5078582764],"type":"Point"}
}