{
  "type": "Feature",
  "properties": {
    "iso:country":"AT",
    "sg:address":"Gutenbergstr 1",
    "sg:city":"Schwarzach",
    "sg:orig_category":"Fernseh- U Radiogesellschaften",
    "sg:phone":"+43 4355 72501601",
    "sg:postcode":"6858",
    "sg:province":"Vorarlberg",
    "wof:name":"Antenne Vorarlberg",
    "wof:placetype":"venue"
},
  "geometry": {"coordinates":[9.7586736679,47.438331604],"type":"Point"}
}