{
  "type": "Feature",
  "properties": {
    "addr:full":"Arnbach 75c Sillian Tirol 9920",
    "addr:housenumber":"75c",
    "addr:postcode":"9920",
    "addr:street":"Arnbach;Tirol",
    "iso:country":"AT",
    "sg:address":"Arnbach 75c",
    "sg:city":"Sillian",
    "sg:orig_category":"Zimmereien",
    "sg:phone":"+43 4842 20040",
    "sg:postcode":"9920",
    "sg:province":"Tirol",
    "wof:name":"Zimmerei Senfter GmbH",
    "wof:placetype":"venue"
},
  "geometry": {"coordinates":[12.3943500519,46.7448310852],"type":"Point"}
}