{
  "type": "Feature",
  "properties": {
    "addr:full":"Apfelgasse 15 Schwarzach Vorarlberg 6858",
    "addr:housenumber":"15",
    "addr:postcode":"6858",
    "addr:street":"Apfelgasse",
    "iso:country":"AT",
    "sg:address":"Apfelgasse 15",
    "sg:city":"Schwarzach",
    "sg:classifiers":[
        {
            "category":"Manufacturing",
            "subcategory":"Wood Products",
            "type":"Manufacturing & Wholesale Goods"
        }
    ],
    "sg:phone":"+43 5572 5869312",
    "sg:postcode":"6858",
    "sg:province":"Vorarlberg",
    "sg:tags":[
        "solid",
        "ceiling",
        "made",
        "panel"
    ],
    "wof:name":"Immler Edelbert",
    "wof:placetype":"venue"
},
  "geometry": {"coordinates":[9.7607889175,47.4485244751],"type":"Point"}
}