{
  "type": "Feature",
  "properties": {
    "iso:country":"AT",
    "sg:address":"C v H\u00f6tzendorf-Str 84",
    "sg:city":"Graz",
    "sg:classifiers":[
        {
            "category":"Professional",
            "subcategory":"Computer Services",
            "type":"Services"
        }
    ],
    "sg:phone":"+43 316 8331110",
    "sg:postcode":"8010",
    "sg:province":"Steiermark",
    "sg:tags":[
        "software"
    ],
    "wof:name":"Analytika Betriebsberatung GesmbH",
    "wof:placetype":"venue"
},
  "geometry": {"coordinates":[15.4431800842,47.0685653687],"type":"Point"}
}