{
  "type": "Feature",
  "properties": {
    "addr:full":"Obere Feldstr 73 Pitten Nieder\u00f6sterreich 2823",
    "addr:housenumber":"73",
    "addr:postcode":"2823",
    "addr:street":"Obere Feldstr",
    "iso:country":"AT",
    "sg:address":"Obere Feldstr 73",
    "sg:city":"Pitten",
    "sg:orig_category":"Fleischhauereien",
    "sg:phone":"+43 2627 822200",
    "sg:postcode":"2823",
    "sg:province":"Nieder\u00f6sterreich",
    "wof:name":"Hampel Friedrich",
    "wof:placetype":"venue"
},
  "geometry": {"coordinates":[16.1796455383,47.7151565552],"type":"Point"}
}