{
  "type": "Feature",
  "properties": {
    "addr:full":"Bundesstr St. Lorenzen Steiermark 8715",
    "addr:postcode":"8715",
    "iso:country":"AT",
    "sg:address":"Bundesstr",
    "sg:city":"St. Lorenzen",
    "sg:orig_category":"Tischlereien",
    "sg:phone":"+43 4366 43154288",
    "sg:postcode":"8715",
    "sg:province":"Steiermark",
    "wof:name":"Egger Thomas Montagetischlerei",
    "wof:placetype":"venue"
},
  "geometry": {"coordinates":[14.9069385529,47.2681427002],"type":"Point"}
}