{
  "type": "Feature",
  "properties": {
    "addr:full":"Stiegeng 4 Enns Ober\u00f6sterreich 4470",
    "addr:housenumber":"4",
    "addr:postcode":"4470",
    "addr:street":"Stiegeng",
    "iso:country":"AT",
    "sg:address":"Stiegeng 4",
    "sg:city":"Enns",
    "sg:orig_category":"Schlankheitsinstitute",
    "sg:phone":"+43 7223 89276",
    "sg:postcode":"4470",
    "sg:province":"Ober\u00f6sterreich",
    "wof:name":"My Body Wellness-Oase",
    "wof:placetype":"venue"
},
  "geometry": {"coordinates":[14.4796562195,48.21326828],"type":"Point"}
}