{
  "type": "Feature",
  "properties": {
    "addr:full":"Juns 607 Tux Tirol 6293",
    "addr:housenumber":"607",
    "addr:postcode":"6293",
    "addr:street":"Juns;Tirol",
    "iso:country":"AT",
    "sg:address":"Juns 607",
    "sg:city":"Tux",
    "sg:orig_category":"Pensionen / Privatzimmer",
    "sg:phone":"+43 4352 8787642",
    "sg:postcode":"6293",
    "sg:province":"Tirol",
    "wof:name":"Haus Innertal",
    "wof:placetype":"venue"
},
  "geometry": {"coordinates":[11.6970243454,47.1270294189],"type":"Point"}
}