{
  "type": "Feature",
  "properties": {
    "iso:country":"AT",
    "sg:address":"Pollheimerstr 15",
    "sg:city":"Wels",
    "sg:orig_category":"Immobilienmakler",
    "sg:phone":"+43 7242 46620",
    "sg:postcode":"4600",
    "sg:province":"Ober\u00f6sterreich",
    "wof:name":"Realb\u00fcro Meir GmbH",
    "wof:placetype":"venue"
},
  "geometry": {"coordinates":[14.0220842361,48.1562767029],"type":"Point"}
}