{
  "type": "Feature",
  "properties": {
    "addr:full":"Niederthanstr 97 Wels Ober\u00f6sterreich 4600",
    "addr:housenumber":"97",
    "addr:postcode":"4600",
    "addr:street":"Niederthanstr;Oberoesterreich",
    "iso:country":"AT",
    "sg:address":"Niederthanstr 97",
    "sg:city":"Wels",
    "sg:orig_category":"Hafnereien",
    "sg:phone":"+43 7242 45211",
    "sg:postcode":"4600",
    "sg:province":"Ober\u00f6sterreich",
    "wof:name":"Kachelstudio Nimmervoll GmbH",
    "wof:placetype":"venue"
},
  "geometry": {"coordinates":[13.990527153,48.1845054626],"type":"Point"}
}