{
  "type": "Feature",
  "properties": {
    "addr:full":"Turmstr 44 4031",
    "addr:housenumber":"44",
    "addr:postcode":"4031",
    "addr:street":"Turmstr",
    "iso:country":"AT",
    "sg:address":"Turmstr 44",
    "sg:orig_category":"Modellbau",
    "sg:phone":"+43 4373 265923144",
    "sg:postcode":"4031",
    "wof:name":"Voest-Alpine Industrieanlagenbau GmbH - Modellatelier",
    "wof:placetype":"venue"
},
  "geometry": {"coordinates":[14.3219690323,48.2749671936],"type":"Point"}
}