{
  "type": "Feature",
  "properties": {
    "addr:full":"Nr 562 Achenkirch Tirol 6215",
    "addr:postcode":"6215",
    "addr:street":"Nr;Achenkirch Tirol",
    "iso:country":"AT",
    "sg:address":"Nr 562",
    "sg:city":"Achenkirch",
    "sg:orig_category":"Motoreninstandsetzung",
    "sg:phone":"+43 5246 20110",
    "sg:postcode":"6215",
    "sg:province":"Tirol",
    "wof:name":"Storm August GmbH & Co KG",
    "wof:placetype":"venue"
},
  "geometry": {"coordinates":[11.7065629959,47.5290184021],"type":"Point"}
}