{
  "type": "Feature",
  "properties": {
    "addr:full":"Sagederg 13 Wien Wien 1120",
    "addr:housenumber":"13",
    "addr:postcode":"1120",
    "addr:street":"Sagederg",
    "iso:country":"AT",
    "sg:address":"Sagederg 13",
    "sg:city":"Wien",
    "sg:orig_category":"Drogerien",
    "sg:phone":"+43 1 6627918",
    "sg:postcode":"1120",
    "sg:province":"Wien",
    "wof:name":"dm drogerie markt GmbH",
    "wof:placetype":"venue"
},
  "geometry": {"coordinates":[16.3191394806,48.1610679626],"type":"Point"}
}