{
  "type": "Feature",
  "properties": {
    "addr:full":"Innsbrucker Str 5 W\u00f6rgl Tirol 6300",
    "addr:housenumber":"5",
    "addr:postcode":"6300",
    "addr:street":"Str;Tirol",
    "iso:country":"AT",
    "sg:address":"Innsbrucker Str 5",
    "sg:city":"W\u00f6rgl",
    "sg:orig_category":"Textilwaren / Einzelhandel",
    "sg:phone":"+43 5332 71001",
    "sg:postcode":"6300",
    "sg:province":"Tirol",
    "wof:name":"TPS",
    "wof:placetype":"venue"
},
  "geometry": {"coordinates":[-69.3131027222,-51.6091995239],"type":"Point"}
}