{
  "type": "Feature",
  "properties": {
    "addr:full":"Austrasse 9 Mautern Nieder\u00f6sterreich 3512",
    "addr:housenumber":"9",
    "addr:postcode":"3512",
    "addr:street":"Austrasse",
    "iso:country":"AT",
    "sg:address":"Austrasse 9",
    "sg:city":"Mautern",
    "sg:classifiers":[
        {
            "category":"Home & Garden",
            "subcategory":"Furniture",
            "type":"Retail Goods"
        }
    ],
    "sg:phone":"+43 2732 84872",
    "sg:postcode":"3512",
    "sg:province":"Nieder\u00f6sterreich",
    "sg:tags":[
        "solid",
        "wood",
        "made",
        "childrens"
    ],
    "wof:name":"Franz Sch\u00f6llbauer KEG",
    "wof:placetype":"venue"
},
  "geometry": {"coordinates":[15.5512466431,48.3772163391],"type":"Point"}
}