{
  "type": "Feature",
  "properties": {
    "addr:full":"Tulpenweg 2 Bleiburg K\u00e4rnten 9150",
    "addr:housenumber":"2",
    "addr:postcode":"9150",
    "addr:street":"Tulpenweg;Kaernten",
    "iso:country":"AT",
    "sg:address":"Tulpenweg 2",
    "sg:city":"Bleiburg",
    "sg:classifiers":[
        {
            "category":"Taxi",
            "type":"Transportation"
        }
    ],
    "sg:phone":"+43 4342 352056",
    "sg:postcode":"9150",
    "sg:province":"K\u00e4rnten",
    "sg:tags":[
        "personentransporte",
        "u"
    ],
    "wof:name":"Taxi Kuehs",
    "wof:placetype":"venue"
},
  "geometry": {"coordinates":[14.7953987122,46.5857315063],"type":"Point"}
}