{
  "type": "Feature",
  "properties": {
    "addr:full":"Anton-Baumgartner-Str 125/6 Wien Wien 1230",
    "addr:housenumber":"125 / 6",
    "addr:postcode":"1230",
    "iso:country":"AT",
    "sg:address":"Anton-Baumgartner-Str 125/6",
    "sg:city":"Wien",
    "sg:orig_category":"Restaurants: Italienisch",
    "sg:phone":"+43 4316 627925",
    "sg:postcode":"1230",
    "sg:province":"Wien",
    "wof:name":"Porto del Vino",
    "wof:placetype":"venue"
},
  "geometry": {"coordinates":[16.3152484894,48.1504364014],"type":"Point"}
}