{
  "type": "Feature",
  "properties": {
    "addr:full":"Chlumeckypl 43 Bad Aussee Steiermark 8990",
    "addr:housenumber":"43",
    "addr:postcode":"8990",
    "addr:street":"Chlumeckypl",
    "iso:country":"AT",
    "sg:address":"Chlumeckypl 43",
    "sg:city":"Bad Aussee",
    "sg:orig_category":"Friseure U Frisiersalons",
    "sg:phone":"+43 4336 2252333",
    "sg:postcode":"8990",
    "sg:province":"Steiermark",
    "wof:name":"Chaos hairconcept",
    "wof:placetype":"venue"
},
  "geometry": {"coordinates":[13.7837629318,47.6109809875],"type":"Point"}
}