{
  "type": "Feature",
  "properties": {
    "addr:full":"Dorf 1 Fieberbrunn Tirol 6391",
    "addr:housenumber":"1",
    "addr:postcode":"6391",
    "addr:street":"Dorf;Tirol",
    "iso:country":"AT",
    "sg:address":"Dorf 1",
    "sg:city":"Fieberbrunn",
    "sg:orig_category":"Appartements / Ferienwohnungen",
    "sg:phone":"+43 5354 88171",
    "sg:postcode":"6391",
    "sg:province":"Tirol",
    "wof:name":"Wimmerhof Fam Adelsberger",
    "wof:placetype":"venue"
},
  "geometry": {"coordinates":[12.5583047867,47.5011558533],"type":"Point"}
}