{
  "type": "Feature",
  "properties": {
    "addr:full":"Marktpl 11 Eggelsberg Ober\u00f6sterreich 5142",
    "addr:housenumber":"11",
    "addr:postcode":"5142",
    "addr:street":"Marktpl;Oberoesterreich",
    "iso:country":"AT",
    "sg:address":"Marktpl 11",
    "sg:city":"Eggelsberg",
    "sg:orig_category":"Hauptschulen",
    "sg:phone":"+43 4377 486103",
    "sg:postcode":"5142",
    "sg:province":"Ober\u00f6sterreich",
    "wof:name":"Hauptschule u Polytechnische Schule",
    "wof:placetype":"venue"
},
  "geometry": {"coordinates":[12.9914608002,48.0783691406],"type":"Point"}
}