{
  "type": "Feature",
  "properties": {
    "addr:full":"Hermann Gmeiner-Weg 58 Stra\u00dfgang Steiermark 8054",
    "addr:housenumber":"58",
    "addr:postcode":"8054",
    "addr:street":"Gmeiner-Weg",
    "iso:country":"AT",
    "sg:address":"Hermann Gmeiner-Weg 58",
    "sg:city":"Stra\u00dfgang",
    "sg:orig_category":"Sandstrahlarbeiten",
    "sg:phone":"+43 316 282649",
    "sg:postcode":"8054",
    "sg:province":"Steiermark",
    "wof:name":"Pichler Sandstrahlunternehmen",
    "wof:placetype":"venue"
},
  "geometry": {"coordinates":[15.4053497314,47.0282897949],"type":"Point"}
}