{
  "type": "Feature",
  "properties": {
    "iso:country":"AT",
    "sg:address":"Am Schie\u00dfpl 5",
    "sg:city":"Sollenau",
    "sg:orig_category":"Fenster",
    "sg:phone":"+43 4326 2862419",
    "sg:postcode":"2601",
    "sg:province":"Nieder\u00f6sterreich",
    "sg:website":"sollenau.at",
    "wof:name":"Reisner H GmbH & Co KG",
    "wof:placetype":"venue"
},
  "geometry": {"coordinates":[16.2542190552,47.8933296204],"type":"Point"}
}