{
  "type": "Feature",
  "properties": {
    "addr:full":"Hoveng 3/4 Korneuburg Nieder\u00f6sterreich 2100",
    "addr:housenumber":"3 / 4",
    "addr:postcode":"2100",
    "addr:street":"Hoveng;Niederoesterreich",
    "iso:country":"AT",
    "sg:address":"Hoveng 3/4",
    "sg:city":"Korneuburg",
    "sg:orig_category":"Papier- U Schreibwaren / Einzelhandel",
    "sg:phone":"+43 4322 6271269",
    "sg:postcode":"2100",
    "sg:province":"Nieder\u00f6sterreich",
    "wof:name":"Irschik Elisabeth",
    "wof:placetype":"venue"
},
  "geometry": {"coordinates":[16.3315029144,48.3408889771],"type":"Point"}
}