{
  "type": "Feature",
  "properties": {
    "addr:full":"Dr.-Linecker-Weg 2 Mattsee Salzburg 5163",
    "addr:housenumber":"2",
    "addr:postcode":"5163",
    "addr:street":"Dr.-Linecker-Weg;Salzburg",
    "iso:country":"AT",
    "sg:address":"Dr.-Linecker-Weg 2",
    "sg:city":"Mattsee",
    "sg:orig_category":"Tischlereien",
    "sg:phone":"+43 4362 1783160",
    "sg:postcode":"5163",
    "sg:province":"Salzburg",
    "wof:name":"Eder Robert",
    "wof:placetype":"venue"
},
  "geometry": {"coordinates":[13.0822706223,48.0071144104],"type":"Point"}
}