{
  "type": "Feature",
  "properties": {
    "iso:country":"AT",
    "sg:address":"Werdertorg 12",
    "sg:city":"Wien",
    "sg:orig_category":"Orientteppiche",
    "sg:phone":"+43 4313 307567",
    "sg:postcode":"1010",
    "sg:province":"Wien",
    "wof:name":"Qureshi Jawaid",
    "wof:placetype":"venue"
},
  "geometry": {"coordinates":[16.3711662292,48.2153434753],"type":"Point"}
}