{
  "type": "Feature",
  "properties": {
    "iso:country":"AT",
    "sg:address":"Klagenfurter Str 3",
    "sg:city":"Villach",
    "sg:orig_category":"Bilderrahmen",
    "sg:phone":"+43 4242 264488",
    "sg:postcode":"9500",
    "sg:province":"K\u00e4rnten",
    "wof:name":"Michis Bilderrahmenservice",
    "wof:placetype":"venue"
},
  "geometry": {"coordinates":[13.8495998383,46.6170501709],"type":"Point"}
}