{
  "type": "Feature",
  "properties": {
    "addr:full":"Landhaus Innsbruck Tirol 6020",
    "addr:postcode":"6020",
    "iso:country":"AT",
    "sg:address":"Landhaus",
    "sg:city":"Innsbruck",
    "sg:orig_category":"Politische Parteien",
    "sg:phone":"+43 512 5083072",
    "sg:postcode":"6020",
    "sg:province":"Tirol",
    "wof:name":"SP\u00f6 Landtagsclub",
    "wof:placetype":"venue"
},
  "geometry": {"coordinates":[11.3474578857,47.250125885],"type":"Point"}
}