{
  "type": "Feature",
  "properties": {
    "addr:full":"Maria Theresien-Str 1 Innsbruck Tirol 6020",
    "addr:housenumber":"1",
    "addr:postcode":"6020",
    "addr:street":"Tirol",
    "iso:country":"AT",
    "sg:address":"Maria Theresien-Str 1",
    "sg:city":"Innsbruck",
    "sg:classifiers":[
        {
            "category":"Shopping",
            "subcategory":"Party Supplies",
            "type":"Retail Goods"
        }
    ],
    "sg:phone":"+43 512 566493",
    "sg:postcode":"6020",
    "sg:province":"Tirol",
    "sg:tags":[
        "u",
        "lichtanlagen",
        "ton-"
    ],
    "sg:website":"www.lichtundton.com",
    "wof:name":"Licht & Ton Veranstaltungstechnik Michael Weis",
    "wof:placetype":"venue"
},
  "geometry": {"coordinates":[11.393737793,47.2669563293],"type":"Point"}
}