{
  "type": "Feature",
  "properties": {
    "addr:full":"Ullmannstr 37 Wien Wien 1150",
    "addr:housenumber":"37",
    "addr:postcode":"1150",
    "addr:street":"Ullmannstr",
    "iso:country":"AT",
    "sg:address":"Ullmannstr 37",
    "sg:city":"Wien",
    "sg:orig_category":"Druckereien",
    "sg:phone":"+43 1 89368550",
    "sg:postcode":"1150",
    "sg:province":"Wien",
    "sg:website":"steiner-druck.at",
    "wof:name":"Druckerei Steiner",
    "wof:placetype":"venue"
},
  "geometry": {"coordinates":[16.3330287933,48.1875419617],"type":"Point"}
}