{
  "type": "Feature",
  "properties": {
    "addr:full":"Flurg 8 Schwarzenau Nieder\u00f6sterreich 3900",
    "addr:housenumber":"8",
    "addr:postcode":"3900",
    "addr:street":"Flurg",
    "iso:country":"AT",
    "sg:address":"Flurg 8",
    "sg:city":"Schwarzenau",
    "sg:orig_category":"Tischlereien",
    "sg:phone":"+43 2849 22430",
    "sg:postcode":"3900",
    "sg:province":"Nieder\u00f6sterreich",
    "wof:name":"Altrichter Werner",
    "wof:placetype":"venue"
},
  "geometry": {"coordinates":[15.2654790878,48.7450370789],"type":"Point"}
}