{
  "type": "Feature",
  "properties": {
    "addr:full":"Hauptstr 46 Unterrabnitz Burgenland 7371",
    "addr:housenumber":"46",
    "addr:postcode":"7371",
    "addr:street":"Hauptstr",
    "iso:country":"AT",
    "sg:address":"Hauptstr 46",
    "sg:city":"Unterrabnitz",
    "sg:orig_category":"Elektromotoren / Reparatur U Wickelei",
    "sg:phone":"+43 2616 8516",
    "sg:postcode":"7371",
    "sg:province":"Burgenland",
    "wof:name":"Hei\u00dfenberger GesmbH",
    "wof:placetype":"venue"
},
  "geometry": {"coordinates":[16.3759250641,47.4554786682],"type":"Point"}
}