{
  "type": "Feature",
  "properties": {
    "addr:full":"Humboldtg 40 Wien Wien 1100",
    "addr:housenumber":"40",
    "addr:postcode":"1100",
    "addr:street":"Humboldtg",
    "iso:country":"AT",
    "sg:address":"Humboldtg 40",
    "sg:city":"Wien",
    "sg:classifiers":[
        {
            "category":"Professional",
            "subcategory":"Art Services",
            "type":"Services"
        }
    ],
    "sg:phone":"+43 1 6076094",
    "sg:postcode":"1100",
    "sg:province":"Wien",
    "sg:tags":[
        "designer"
    ],
    "wof:name":"Buttinger Lioba A Mag art",
    "wof:placetype":"venue"
},
  "geometry": {"coordinates":[16.3777217865,48.178565979],"type":"Point"}
}