{
  "type": "Feature",
  "properties": {
    "addr:full":"Bruck 34 Peuerbach Ober\u00f6sterreich 4722",
    "addr:housenumber":"34",
    "addr:postcode":"4722",
    "addr:street":"Bruck",
    "iso:country":"AT",
    "sg:address":"Bruck 34",
    "sg:city":"Peuerbach",
    "sg:orig_category":"Bierlokale-Pubs",
    "sg:phone":"+43 4372 7635344",
    "sg:postcode":"4722",
    "sg:province":"Ober\u00f6sterreich",
    "wof:name":"Pub Fellini",
    "wof:placetype":"venue"
},
  "geometry": {"coordinates":[13.7726068497,48.3340148926],"type":"Point"}
}