{
  "type": "Feature",
  "properties": {
    "addr:full":"Nr 99 Thomasroith Ober\u00f6sterreich 4905",
    "addr:housenumber":"4905",
    "addr:street":"Nr 99 Thomasroith Oberoesterreich",
    "iso:country":"AT",
    "sg:address":"Nr 99",
    "sg:city":"Thomasroith",
    "sg:orig_category":"Lebensmittel / Einzelhandel",
    "sg:phone":"+43 76767248",
    "sg:postcode":"4905",
    "sg:province":"Ober\u00f6sterreich",
    "wof:name":"Sterrer Rudolf",
    "wof:placetype":"venue"
},
  "geometry": {"coordinates":[13.6177854538,48.0808944702],"type":"Point"}
}