{
  "type": "Feature",
  "properties": {
    "addr:full":"Felix Slavik-Str 3/4 Wien Wien 1210",
    "addr:housenumber":"3 / 4",
    "addr:postcode":"1210",
    "addr:street":"Slavik-Str",
    "iso:country":"AT",
    "sg:address":"Felix Slavik-Str 3/4",
    "sg:city":"Wien",
    "sg:orig_category":"Webdesign",
    "sg:phone":"+43 1 2947808",
    "sg:postcode":"1210",
    "sg:province":"Wien",
    "wof:name":"Lemontree.at",
    "wof:placetype":"venue"
},
  "geometry": {"coordinates":[16.4128799438,48.2915878296],"type":"Point"}
}