{
  "type": "Feature",
  "properties": {
    "iso:country":"AT",
    "sg:address":"Marktstr 14",
    "sg:city":"St. Anton am Arlberg",
    "sg:orig_category":"Pensionen / Privatzimmer",
    "sg:phone":"+43 5446 2831",
    "sg:postcode":"6580",
    "sg:province":"Tirol",
    "wof:name":"Haus Moostal",
    "wof:placetype":"venue"
},
  "geometry": {"coordinates":[10.2689695358,47.1308364868],"type":"Point"}
}