{
  "type": "Feature",
  "properties": {
    "addr:full":"Apostelg 5 Wien Wien 1030",
    "addr:housenumber":"5",
    "addr:postcode":"1030",
    "addr:street":"Apostelg",
    "iso:country":"AT",
    "sg:address":"Apostelg 5",
    "sg:city":"Wien",
    "sg:orig_category":"Volksschulen",
    "sg:phone":"+43 1 713533142",
    "sg:postcode":"1030",
    "sg:province":"Wien",
    "wof:name":"VS St Franziskus d Schulschwestern v 3. Orden d hl Franziskus m Halbinternat",
    "wof:placetype":"venue"
},
  "geometry": {"coordinates":[16.3977432251,48.1999320984],"type":"Point"}
}