{
  "type": "Feature",
  "properties": {
    "addr:full":"Industriestr 1 G\u00f6tzendorf an der Leitha Nieder\u00f6sterreich 2434",
    "addr:housenumber":"1",
    "addr:postcode":"2434",
    "addr:street":"Industriestr;An Der Leitha",
    "iso:country":"AT",
    "sg:address":"Industriestr 1",
    "sg:city":"G\u00f6tzendorf an der Leitha",
    "sg:orig_category":"Transportunternehmen",
    "sg:phone":"+43 4321 6928430",
    "sg:postcode":"2434",
    "sg:province":"Nieder\u00f6sterreich",
    "wof:name":"Bauch Peter KEG",
    "wof:placetype":"venue"
},
  "geometry": {"coordinates":[-101.6332702637,46.3577537537],"type":"Point"}
}