{
  "type": "Feature",
  "properties": {
    "addr:full":"Hamplpl 6 Bad Hofgastein Salzburg 5630",
    "addr:housenumber":"6",
    "addr:postcode":"5630",
    "addr:street":"Hamplpl;Salzburg",
    "iso:country":"AT",
    "sg:address":"Hamplpl 6",
    "sg:city":"Bad Hofgastein",
    "sg:orig_category":"Bildhauer",
    "sg:phone":"+43 6432 6456",
    "sg:postcode":"5630",
    "sg:province":"Salzburg",
    "wof:name":"Winkler Brunhild",
    "wof:placetype":"venue"
},
  "geometry": {"coordinates":[13.1064119339,47.1706314087],"type":"Point"}
}