{
  "type": "Feature",
  "properties": {
    "addr:full":"Nr 155 Bad H\u00e4ring Tirol 6323",
    "addr:postcode":"6323",
    "addr:street":"Nr",
    "iso:country":"AT",
    "sg:address":"Nr 155",
    "sg:city":"Bad H\u00e4ring",
    "sg:orig_category":"Pensionen / Privatzimmer",
    "sg:phone":"+43 5332 87434",
    "sg:postcode":"6323",
    "sg:province":"Tirol",
    "wof:name":"G\u00e4stehaus Quellenhof",
    "wof:placetype":"venue"
},
  "geometry": {"coordinates":[-88.67497253419999,43.9075889587],"type":"Point"}
}