{
  "type": "Feature",
  "properties": {
    "addr:full":"Austra\u00dfensdlg 35 Salzburg Salzburg 5020",
    "addr:housenumber":"35",
    "addr:postcode":"5020",
    "addr:street":"Austrassensdlg;Salzburg",
    "iso:country":"AT",
    "sg:address":"Austra\u00dfensdlg 35",
    "sg:city":"Salzburg",
    "sg:orig_category":"Bauunternehmen",
    "sg:phone":"+43 662 4511990",
    "sg:postcode":"5020",
    "sg:province":"Salzburg",
    "wof:name":"Felbermayr Bau GmbH & Co KG - NL Salzburg",
    "wof:placetype":"venue"
},
  "geometry": {"coordinates":[13.0348577499,47.8228912354],"type":"Point"}
}