{
  "type": "Feature",
  "properties": {
    "addr:full":"Mirnockstr 72 Millstatt K\u00e4rnten 9872",
    "addr:housenumber":"72",
    "addr:postcode":"9872",
    "addr:street":"Mirnockstr;Kaernten",
    "iso:country":"AT",
    "sg:address":"Mirnockstr 72",
    "sg:city":"Millstatt",
    "sg:orig_category":"Pensionen / Privatzimmer",
    "sg:phone":"+43 4766 26540",
    "sg:postcode":"9872",
    "sg:province":"K\u00e4rnten",
    "wof:name":"Pension Villa Margarethe",
    "wof:placetype":"venue"
},
  "geometry": {"coordinates":[13.5755233765,46.8036575317],"type":"Point"}
}