{
  "type": "Feature",
  "properties": {
    "addr:full":"Ankershofenstr 2 Klagenfurt K\u00e4rnten 9020",
    "addr:housenumber":"2",
    "addr:postcode":"9020",
    "addr:street":"Ankershofenstr;Kaernten",
    "iso:country":"AT",
    "sg:address":"Ankershofenstr 2",
    "sg:city":"Klagenfurt",
    "sg:orig_category":"Elektroinstallationsunternehmen",
    "sg:phone":"+43 463 511282",
    "sg:postcode":"9020",
    "sg:province":"K\u00e4rnten",
    "wof:name":"Elektro Laure",
    "wof:placetype":"venue"
},
  "geometry": {"coordinates":[14.3004207611,46.6169204712],"type":"Point"}
}