{
  "type": "Feature",
  "properties": {
    "addr:full":"Hauptpl 10 Bad St. Leonhard im Lavanttal K\u00e4rnten 9462",
    "addr:housenumber":"10",
    "addr:postcode":"9462",
    "addr:street":"Hauptpl",
    "iso:country":"AT",
    "sg:address":"Hauptpl 10",
    "sg:city":"Bad St. Leonhard im Lavanttal",
    "sg:orig_category":"Apotheken",
    "sg:phone":"+43 4343 5023080",
    "sg:postcode":"9462",
    "sg:province":"K\u00e4rnten",
    "wof:name":"Stadtapotheke Mag pharm Monika Clar",
    "wof:placetype":"venue"
},
  "geometry": {"coordinates":[14.7913532257,46.9637336731],"type":"Point"}
}