{
  "type": "Feature",
  "properties": {
    "addr:full":"Linzer Str 89-91 Gablitz Nieder\u00f6sterreich 3003",
    "addr:postcode":"89-91;3003",
    "addr:street":"Linzer Str;Niederoesterreich",
    "iso:country":"AT",
    "sg:address":"Linzer Str 89-91",
    "sg:city":"Gablitz",
    "sg:orig_category":"Montagen U Montagetechnik",
    "sg:phone":"+43 676 5219415",
    "sg:postcode":"3003",
    "sg:province":"Nieder\u00f6sterreich",
    "wof:name":"Bruckberger Andreas",
    "wof:placetype":"venue"
},
  "geometry": {"coordinates":[16.1552391052,48.2281532288],"type":"Point"}
}