{
  "type": "Feature",
  "properties": {
    "addr:full":"Urban-Loritz-Pl 4 Wien Wien 1070",
    "addr:housenumber":"4",
    "addr:postcode":"1070",
    "addr:street":"Urban-Loritz-Pl",
    "iso:country":"AT",
    "sg:address":"Urban-Loritz-Pl 4",
    "sg:city":"Wien",
    "sg:orig_category":"Psychotherapie",
    "sg:phone":"+43 1 5236753",
    "sg:postcode":"1070",
    "sg:province":"Wien",
    "wof:name":"Bolterauer Johanna Mag",
    "wof:placetype":"venue"
},
  "geometry": {"coordinates":[16.3383846283,48.2022895813],"type":"Point"}
}