{
  "type": "Feature",
  "properties": {
    "addr:full":"Ferdinandstr 5/7 Wien Wien 1020",
    "addr:housenumber":"5 / 7",
    "addr:postcode":"1020",
    "addr:street":"Ferdinandstr",
    "iso:country":"AT",
    "sg:address":"Ferdinandstr 5/7",
    "sg:city":"Wien",
    "sg:orig_category":"Escortservice",
    "sg:phone":"+43 1 9551476",
    "sg:postcode":"1020",
    "sg:province":"Wien",
    "wof:name":"Absolut Escort",
    "wof:placetype":"venue"
},
  "geometry": {"coordinates":[16.3819503784,48.2130851746],"type":"Point"}
}