{
  "type": "Feature",
  "properties": {
    "addr:full":"Wiener Strasse 1a Langenzersdorf Nieder\u00f6sterreich 2103",
    "addr:housenumber":"1a",
    "addr:postcode":"2103",
    "addr:street":"Wiener Strasse",
    "iso:country":"AT",
    "sg:address":"Wiener Strasse 1a",
    "sg:city":"Langenzersdorf",
    "sg:classifiers":[
        {
            "category":"Home & Garden",
            "subcategory":"Home Furnishings",
            "type":"Retail Goods"
        }
    ],
    "sg:phone":"+43 2244 2320",
    "sg:postcode":"2103",
    "sg:province":"Nieder\u00f6sterreich",
    "sg:tags":[
        "bathroom",
        "wc",
        "fitting"
    ],
    "wof:name":"Johann Hinteregger Heizung - Sanit\u00e4r Nfg. Karl Molnar",
    "wof:placetype":"venue"
},
  "geometry": {"coordinates":[16.3582172394,48.3091316223],"type":"Point"}
}