{
  "type": "Feature",
  "properties": {
    "addr:full":"Breitenlohe 49 Michaelbeuern Salzburg 5152",
    "addr:housenumber":"49",
    "addr:postcode":"5152",
    "addr:street":"Breitenlohe;Salzburg",
    "iso:country":"AT",
    "sg:address":"Breitenlohe 49",
    "sg:city":"Michaelbeuern",
    "sg:orig_category":"Transportunternehmen",
    "sg:phone":"+43 6274 8680",
    "sg:postcode":"5152",
    "sg:province":"Salzburg",
    "wof:name":"Honetra TransportgesmbH",
    "wof:placetype":"venue"
},
  "geometry": {"coordinates":[13.0150594711,48.0233306885],"type":"Point"}
}