{
  "type": "Feature",
  "properties": {
    "iso:country":"AT",
    "sg:address":"Schulg 1",
    "sg:city":"Kohfidisch",
    "sg:orig_category":"Hauptschulen",
    "sg:phone":"+43 4333 6676594",
    "sg:postcode":"7512",
    "sg:province":"Burgenland",
    "wof:name":"Hauptschule",
    "wof:placetype":"venue"
},
  "geometry": {"coordinates":[16.3555355072,47.1741256714],"type":"Point"}
}