{
  "type": "Feature",
  "properties": {
    "addr:full":"Hauptstr 6 Felixdorf Nieder\u00f6sterreich 2603",
    "addr:housenumber":"6",
    "addr:postcode":"2603",
    "addr:street":"Hauptstr",
    "iso:country":"AT",
    "sg:address":"Hauptstr 6",
    "sg:city":"Felixdorf",
    "sg:orig_category":"Feuerwehren",
    "sg:phone":"+43 2628 62750",
    "sg:postcode":"2603",
    "sg:province":"Nieder\u00f6sterreich",
    "wof:name":"Freiwillige Feuerwehr",
    "wof:placetype":"venue"
},
  "geometry": {"coordinates":[16.2457103729,47.8844070435],"type":"Point"}
}