{
  "type": "Feature",
  "properties": {
    "addr:full":"Industriestr 4 Timelkam Ober\u00f6sterreich 4850",
    "addr:housenumber":"4",
    "addr:postcode":"4850",
    "addr:street":"Industriestr",
    "iso:country":"AT",
    "sg:address":"Industriestr 4",
    "sg:city":"Timelkam",
    "sg:orig_category":"Transportunternehmen",
    "sg:phone":"+43 767295433",
    "sg:postcode":"4850",
    "sg:province":"Ober\u00f6sterreich",
    "sg:website":"eckl-transporte.at; eckl-transporte.com",
    "wof:name":"Eckl GesmbH",
    "wof:placetype":"venue"
},
  "geometry": {"coordinates":[13.5974273682,47.9976119995],"type":"Point"}
}