{
  "type": "Feature",
  "properties": {
    "iso:country":"AT",
    "sg:address":"Hauptstr. 34 ",
    "sg:city":"Oberpullendorf",
    "sg:classifiers":[
        {
            "category":"Banks & Credit Unions",
            "subcategory":"Bank",
            "type":"Services"
        }
    ],
    "sg:phone":"+43 4326 12423340",
    "sg:postcode":"7350",
    "sg:province":"Burgenland",
    "sg:tags":[
        "banking",
        "institution"
    ],
    "wof:name":"RAIFFEISENBEZIRKSBANK OBER-PULENDORF GMBH",
    "wof:placetype":"venue"
},
  "geometry": {"coordinates":[16.5056915283,47.4999008179],"type":"Point"}
}