{
  "type": "Feature",
  "properties": {
    "iso:country":"AT",
    "sg:address":"Gmachlstr 783",
    "sg:city":"Kaprun",
    "sg:orig_category":"Lebensmittel / Erzeugung U Gro\u00c3\u0178handel",
    "sg:phone":"+43 4365 4770127",
    "sg:postcode":"5710",
    "sg:province":"Salzburg",
    "wof:name":"AUSTRO GOURMET Wuthe & Klugmayer OEG",
    "wof:placetype":"venue"
},
  "geometry": {"coordinates":[12.7546634674,47.2828140259],"type":"Point"}
}