{
  "type": "Feature",
  "properties": {
    "addr:full":"Oberlech 55 Lech Vorarlberg 6764",
    "addr:housenumber":"55",
    "addr:postcode":"6764",
    "addr:street":"Oberlech",
    "iso:country":"AT",
    "sg:address":"Oberlech 55",
    "sg:city":"Lech",
    "sg:classifiers":[
        {
            "category":"Travel",
            "subcategory":"Travel Agent",
            "type":"Entertainment"
        }
    ],
    "sg:phone":"+43 4355 8321470",
    "sg:postcode":"6764",
    "sg:province":"Vorarlberg",
    "sg:tags":[
        "business"
    ],
    "wof:name":"HOTEL SONNENBURG GESMBH",
    "wof:placetype":"venue"
},
  "geometry": {"coordinates":[10.1373634338,47.2166786194],"type":"Point"}
}