{
  "type": "Feature",
  "properties": {
    "iso:country":"AT",
    "sg:address":"Theresianumg. 21 A ",
    "sg:city":"Wien",
    "sg:classifiers":[
        {
            "category":"Travel",
            "subcategory":"Travel Agent",
            "type":"Entertainment"
        }
    ],
    "sg:phone":"+43 4315 051696",
    "sg:postcode":"1040",
    "sg:province":"Wien",
    "sg:tags":[
        "business"
    ],
    "wof:name":"CLIMA CITY",
    "wof:placetype":"venue"
},
  "geometry": {"coordinates":[16.3745346069,48.1916999817],"type":"Point"}
}