{
  "type": "Feature",
  "properties": {
    "iso:country":"AT",
    "sg:address":"Urschastr 7",
    "sg:city":"Eggersdorf",
    "sg:orig_category":"Werbegrafik- U Grafik-Design",
    "sg:phone":"+43 4331 173479",
    "sg:postcode":"8063",
    "sg:province":"Steiermark",
    "wof:name":"HB Graphik-Designerwerkst\u00e4tte",
    "wof:placetype":"venue"
},
  "geometry": {"coordinates":[15.6049871445,47.1270294189],"type":"Point"}
}