{
  "type": "Feature",
  "properties": {
    "iso:country":"AT",
    "sg:address":"Hagenstr 3",
    "sg:city":"St. Valentin",
    "sg:orig_category":"Werbegrafik- U Grafik-Design",
    "sg:phone":"+43 4366 43958923",
    "sg:postcode":"4300",
    "sg:province":"Nieder\u00f6sterreich",
    "wof:name":"Mannsberger Melanie",
    "wof:placetype":"venue"
},
  "geometry": {"coordinates":[14.5191364288,48.1708221436],"type":"Point"}
}