{
  "type": "Feature",
  "properties": {
    "addr:full":"Pappelstr 1 Persenbeug Nieder\u00f6sterreich 3680",
    "addr:housenumber":"1",
    "addr:postcode":"3680",
    "addr:street":"Pappelstr",
    "iso:country":"AT",
    "sg:address":"Pappelstr 1",
    "sg:city":"Persenbeug",
    "sg:orig_category":"Erdarbeiten",
    "sg:phone":"+43 7412 55835",
    "sg:postcode":"3680",
    "sg:province":"Nieder\u00f6sterreich",
    "wof:name":"P\u00f6cksteiner Friedrich",
    "wof:placetype":"venue"
},
  "geometry": {"coordinates":[15.0869932175,48.1836624146],"type":"Point"}
}