{
  "type": "Feature",
  "properties": {
    "addr:full":"Krinnerweg 2 Bad Zell Ober\u00f6sterreich 4283",
    "addr:housenumber":"2",
    "addr:postcode":"4283",
    "addr:street":"Krinnerweg",
    "iso:country":"AT",
    "sg:address":"Krinnerweg 2",
    "sg:city":"Bad Zell",
    "sg:orig_category":"\u00c3\u201erzte / F Allgemeinmedizin",
    "sg:phone":"+43 7263 7204",
    "sg:postcode":"4283",
    "sg:province":"Ober\u00f6sterreich",
    "wof:name":"Gruber Gottfried MedR Dr",
    "wof:placetype":"venue"
},
  "geometry": {"coordinates":[14.6713123322,48.3477973938],"type":"Point"}
}