{
  "type": "Feature",
  "properties": {
    "iso:country":"AT",
    "sg:address":"Speckbacherstrasse 5",
    "sg:city":"W\u00f6rgl",
    "sg:classifiers":[
        {
            "category":"Health Services",
            "subcategory":"Nursing And Care Facility",
            "type":"Services"
        }
    ],
    "sg:phone":"+43 512 579722",
    "sg:postcode":"6300",
    "sg:province":"Tirol",
    "sg:tags":[
        "battery",
        "aid",
        "hearing"
    ],
    "wof:name":"Corradini Denifl OEG",
    "wof:placetype":"venue"
},
  "geometry": {"coordinates":[-69.3131027222,-51.6091995239],"type":"Point"}
}