{
  "type": "Feature",
  "properties": {
    "iso:country":"AT",
    "sg:address":"Glanfurtg 78",
    "sg:city":"Klagenfurt-Viktring",
    "sg:orig_category":"Maler, Anstreicher U Lackierer",
    "sg:phone":"+43 463 281205",
    "sg:postcode":"9073",
    "sg:province":"K\u00e4rnten",
    "wof:name":"Malerei Woath",
    "wof:placetype":"venue"
},
  "geometry": {"coordinates":[14.2721529007,46.5989723206],"type":"Point"}
}