{
  "type": "Feature",
  "properties": {
    "addr:full":"Dr.-Karl-L\u00fcger-Rg. 12  Wien Wien 1010",
    "addr:housenumber":"12",
    "addr:postcode":"1010",
    "addr:street":"Dr.-Karl-Lueger-Rg.",
    "iso:country":"AT",
    "sg:address":"Dr.-Karl-L\u00fcger-Rg. 12 ",
    "sg:city":"Wien",
    "sg:classifiers":[
        {
            "category":"Manufacturing",
            "subcategory":"Metals",
            "type":"Manufacturing & Wholesale Goods"
        }
    ],
    "sg:phone":"+43 4315 3366460",
    "sg:postcode":"1010",
    "sg:province":"Wien",
    "sg:tags":[
        "metallurgy",
        "metalworking"
    ],
    "wof:name":"METALLSCHMELZE TATTENDORF GMBH",
    "wof:placetype":"venue"
},
  "geometry": {"coordinates":[16.3688049316,48.2025489807],"type":"Point"}
}