{
  "type": "Feature",
  "properties": {
    "addr:full":"Sch\u00f6nbrunner Strasse 14a Wien Wien 1050",
    "addr:housenumber":"14a",
    "addr:postcode":"1050",
    "addr:street":"Schoenbrunner Strasse",
    "iso:country":"AT",
    "sg:address":"Sch\u00f6nbrunner Strasse 14a",
    "sg:city":"Wien",
    "sg:classifiers":[
        {
            "category":"Home & Garden",
            "subcategory":"Carpets & Floor Coverings",
            "type":"Retail Goods"
        }
    ],
    "sg:phone":"+43 1 5870139",
    "sg:postcode":"1050",
    "sg:province":"Wien",
    "sg:tags":[
        "supraregional",
        "flooring"
    ],
    "wof:name":"Zillner Ges.m.b.H.",
    "wof:placetype":"venue"
},
  "geometry": {"coordinates":[16.3595695496,48.1942939758],"type":"Point"}
}