{
  "type": "Feature",
  "properties": {
    "iso:country":"AT",
    "sg:address":"Hauptpl 20",
    "sg:city":"Bruck an der Leitha",
    "sg:orig_category":"Textilwaren / Einzelhandel",
    "sg:phone":"+43 2162 624330",
    "sg:postcode":"2460",
    "sg:province":"Nieder\u00f6sterreich",
    "wof:name":"Kuntner Textil",
    "wof:placetype":"venue"
},
  "geometry": {"coordinates":[16.7790794373,48.0248603821],"type":"Point"}
}