{
  "type": "Feature",
  "properties": {
    "iso:country":"AT",
    "sg:address":"Sporg 16",
    "sg:city":"Graz",
    "sg:orig_category":"Stahlwaren",
    "sg:phone":"+43 316 831789",
    "sg:postcode":"8010",
    "sg:province":"Steiermark",
    "sg:website":"messerscala.com",
    "wof:name":"Scala Peter",
    "wof:placetype":"venue"
},
  "geometry": {"coordinates":[15.4389352798,47.0722122192],"type":"Point"}
}