{
  "type": "Feature",
  "properties": {
    "addr:full":"Fabiganstr 27 Wien Wien 1110",
    "addr:housenumber":"27",
    "addr:postcode":"1110",
    "addr:street":"Fabiganstr",
    "iso:country":"AT",
    "sg:address":"Fabiganstr 27",
    "sg:city":"Wien",
    "sg:orig_category":"Transportunternehmen",
    "sg:phone":"+43 1 7697800",
    "sg:postcode":"1110",
    "sg:province":"Wien",
    "wof:name":"Klein Hans",
    "wof:placetype":"venue"
},
  "geometry": {"coordinates":[16.4163513184,48.1607551575],"type":"Point"}
}