{
  "type": "Feature",
  "properties": {
    "addr:full":"Schlesingerpl 2 Wien Wien 1080",
    "addr:housenumber":"2",
    "addr:postcode":"1080",
    "addr:street":"Schlesingerpl",
    "iso:country":"AT",
    "sg:address":"Schlesingerpl 2",
    "sg:city":"Wien",
    "sg:orig_category":"Familien / Beratung",
    "sg:phone":"+43 1 4013408890",
    "sg:postcode":"1080",
    "sg:province":"Wien",
    "wof:name":"MAG ELF - Elternberatungsstelle der Stadt Wien",
    "wof:placetype":"venue"
},
  "geometry": {"coordinates":[16.346244812,48.2124671936],"type":"Point"}
}