{
  "type": "Feature",
  "properties": {
    "addr:full":"Nr 61 Polling im Innkreis Ober\u00f6sterreich 4951",
    "addr:postcode":"4951",
    "addr:street":"Nr 61",
    "iso:country":"AT",
    "sg:address":"Nr 61",
    "sg:city":"Polling im Innkreis",
    "sg:orig_category":"Friseure U Frisiersalons",
    "sg:phone":"+43 4377 236409",
    "sg:postcode":"4951",
    "sg:province":"Ober\u00f6sterreich",
    "wof:name":"Haarstudio Helene Hagn",
    "wof:placetype":"venue"
},
  "geometry": {"coordinates":[13.2834358215,48.2301521301],"type":"Point"}
}