{
  "type": "Feature",
  "properties": {
    "iso:country":"AT",
    "sg:address":"Weblinger Str 28",
    "sg:city":"Stra\u00dfgang",
    "sg:orig_category":"Autohandel",
    "sg:phone":"+43 316 252425",
    "sg:postcode":"8054",
    "sg:province":"Steiermark",
    "wof:name":"Vogl West - Renaulth\u00e4ndler",
    "wof:placetype":"venue"
},
  "geometry": {"coordinates":[15.4027462006,47.0309181213],"type":"Point"}
}