{
  "type": "Feature",
  "properties": {
    "iso:country":"AT",
    "sg:address":"Nr 5",
    "sg:city":"Waldenstein",
    "sg:orig_category":"Banken U Sparkassen",
    "sg:phone":"+43 2855 234",
    "sg:postcode":"3961",
    "sg:province":"Nieder\u00f6sterreich",
    "wof:name":"Raiffeisenbank Oberes Waldviertel regGenmbH",
    "wof:placetype":"venue"
},
  "geometry": {"coordinates":[15.0196552277,48.7288703918],"type":"Point"}
}