{
  "type": "Feature",
  "properties": {
    "addr:full":"Denisg 9 Wien Wien 1200",
    "addr:housenumber":"9",
    "addr:postcode":"1200",
    "addr:street":"Denisg",
    "iso:country":"AT",
    "sg:address":"Denisg 9",
    "sg:city":"Wien",
    "sg:orig_category":"Hunde- U Katzensalons",
    "sg:phone":"+43 4313 339073",
    "sg:postcode":"1200",
    "sg:province":"Wien",
    "wof:name":"Kilic Slava",
    "wof:placetype":"venue"
},
  "geometry": {"coordinates":[16.3734645844,48.2306060791],"type":"Point"}
}