{
  "type": "Feature",
  "properties": {
    "addr:full":"Wiener Str 40 Graz Steiermark 8020",
    "addr:housenumber":"40",
    "addr:postcode":"8020",
    "iso:country":"AT",
    "sg:address":"Wiener Str 40",
    "sg:city":"Graz",
    "sg:orig_category":"Bewachungsunternehmen",
    "sg:phone":"+43 4366 42220149",
    "sg:postcode":"8020",
    "sg:province":"Steiermark",
    "sg:website":"udf-system.at",
    "wof:name":"UDF-System Sicherheitsausbildungen",
    "wof:placetype":"venue"
},
  "geometry": {"coordinates":[15.4252023697,47.0798149109],"type":"Point"}
}