{
  "type": "Feature",
  "properties": {
    "iso:country":"AT",
    "sg:address":"G\u00e4rtnerstr 12",
    "sg:city":"Lustenau",
    "sg:orig_category":"Friseure U Frisiersalons",
    "sg:phone":"+43 4355 7786266",
    "sg:postcode":"6890",
    "sg:province":"Vorarlberg",
    "wof:name":"Jennerwein Karin",
    "wof:placetype":"venue"
},
  "geometry": {"coordinates":[9.6557302475,47.4274520874],"type":"Point"}
}