{
  "type": "Feature",
  "properties": {
    "addr:full":"Georgenweg 24 Telfs Tirol 6410",
    "addr:housenumber":"24",
    "addr:postcode":"6410",
    "addr:street":"Georgenweg;Tirol",
    "iso:country":"AT",
    "sg:address":"Georgenweg 24",
    "sg:city":"Telfs",
    "sg:classifiers":[
        {
            "category":"Train Station",
            "subcategory":"Light Rail",
            "type":"Transportation"
        }
    ],
    "sg:phone":"+43 5262 62153",
    "sg:postcode":"6410",
    "sg:province":"Tirol",
    "sg:tags":[
        "luminous",
        "sign"
    ],
    "wof:name":"Prast Schilder Leuchtwerbung",
    "wof:placetype":"venue"
},
  "geometry": {"coordinates":[11.0741853714,47.3108863831],"type":"Point"}
}