{
  "type": "Feature",
  "properties": {
    "iso:country":"AT",
    "sg:address":"Pariser Strasse 6",
    "sg:city":"Lauterach",
    "sg:classifiers":[
        {
            "category":"Home & Garden",
            "subcategory":"Household Appliances",
            "type":"Retail Goods"
        }
    ],
    "sg:phone":"+43 5574 71224",
    "sg:postcode":"6923",
    "sg:province":"Vorarlberg",
    "sg:tags":[
        "electric"
    ],
    "wof:name":"Willi Maier",
    "wof:placetype":"venue"
},
  "geometry": {"coordinates":[9.7284584045,47.4729766846],"type":"Point"}
}