{
  "type": "Feature",
  "properties": {
    "iso:country":"AT",
    "sg:address":"Friedrich Engels-Pl 4",
    "sg:city":"Wien",
    "sg:orig_category":"Gesundheitsvorsorge",
    "sg:phone":"+43 699 10773806",
    "sg:postcode":"1200",
    "sg:province":"Wien",
    "wof:name":"Majefsky G\u00fcnter - Trainer f K\u00f6rper und Pers\u00f6nlichkeitsentwicklung",
    "wof:placetype":"venue"
},
  "geometry": {"coordinates":[16.3775405884,48.2458724976],"type":"Point"}
}