{
  "type": "Feature",
  "properties": {
    "addr:full":"Althanstr 47/2 Wien Wien 1090",
    "addr:housenumber":"47 / 2",
    "addr:postcode":"1090",
    "addr:street":"Althanstr",
    "iso:country":"AT",
    "sg:address":"Althanstr 47/2",
    "sg:city":"Wien",
    "sg:orig_category":"Nachhilfe U Lernbetreuung",
    "sg:phone":"+43 4313 69500976",
    "sg:postcode":"1090",
    "sg:province":"Wien",
    "wof:name":"Lernfreunde Nachhilfe & Lern- Coaching",
    "wof:placetype":"venue"
},
  "geometry": {"coordinates":[16.3576488495,48.229259491],"type":"Point"}
}