{
  "type": "Feature",
  "properties": {
    "addr:full":"Almegg 43 Scharnstein Ober\u00f6sterreich 4644",
    "addr:housenumber":"43",
    "addr:postcode":"4644",
    "addr:street":"Almegg",
    "iso:country":"AT",
    "sg:address":"Almegg 43",
    "sg:city":"Scharnstein",
    "sg:orig_category":"Appartements / Ferienwohnungen",
    "sg:phone":"+43 76168563",
    "sg:postcode":"4644",
    "sg:province":"Ober\u00f6sterreich",
    "wof:name":"Ferienhof Grendelgraben Fam Holzinger",
    "wof:placetype":"venue"
},
  "geometry": {"coordinates":[13.938791275,47.8660621643],"type":"Point"}
}