{
  "type": "Feature",
  "properties": {
    "addr:full":"Au\u00dfersalvenberg 19 Hopfgarten im Brixental Tirol 6361",
    "addr:housenumber":"19",
    "addr:postcode":"6361",
    "addr:street":"Aussersalvenberg;Tirol",
    "iso:country":"AT",
    "sg:address":"Au\u00dfersalvenberg 19",
    "sg:city":"Hopfgarten im Brixental",
    "sg:orig_category":"Fenster",
    "sg:phone":"+43 4353 3550064",
    "sg:postcode":"6361",
    "sg:province":"Tirol",
    "wof:name":"Sieberer Balthasar",
    "wof:placetype":"venue"
},
  "geometry": {"coordinates":[12.1706438065,47.4641723633],"type":"Point"}
}