{
  "type": "Feature",
  "properties": {
    "addr:full":"V\u00f6cklabrucker Str 24 Ampflwang im Hausruckwald Ober\u00f6sterreich 4843",
    "addr:housenumber":"24",
    "addr:postcode":"4843",
    "addr:street":"Str",
    "iso:country":"AT",
    "sg:address":"V\u00f6cklabrucker Str 24",
    "sg:city":"Ampflwang im Hausruckwald",
    "sg:orig_category":"Restaurants: Italienisch",
    "sg:phone":"+43 767539570",
    "sg:postcode":"4843",
    "sg:province":"Ober\u00f6sterreich",
    "wof:name":"Ristorante Pizzeria Vino Rosso",
    "wof:placetype":"venue"
},
  "geometry": {"coordinates":[13.5665845871,48.0902557373],"type":"Point"}
}