{
  "type": "Feature",
  "properties": {
    "addr:full":"Nr 355 Loibichl Ober\u00f6sterreich 5311",
    "addr:housenumber":"5311",
    "addr:street":"Nr;Loibichl Oberoesterreich",
    "iso:country":"AT",
    "sg:address":"Nr 355",
    "sg:city":"Loibichl",
    "sg:orig_category":"Handelsagenturen",
    "sg:phone":"+43 4362 325199",
    "sg:postcode":"5311",
    "sg:province":"Ober\u00f6sterreich",
    "wof:name":"KSA - ALTERNATIVENERGIEN",
    "wof:placetype":"venue"
},
  "geometry": {"coordinates":[13.4032068253,47.8300895691],"type":"Point"}
}