{
  "type": "Feature",
  "properties": {
    "addr:full":"Michael Koch-Str 18a Mattersburg Burgenland 7210",
    "addr:housenumber":"18a",
    "addr:postcode":"7210",
    "iso:country":"AT",
    "sg:address":"Michael Koch-Str 18a",
    "sg:city":"Mattersburg",
    "sg:orig_category":"Freizeit- U Sportbekleidung",
    "sg:phone":"+43 2626 62200",
    "sg:postcode":"7210",
    "sg:province":"Burgenland",
    "wof:name":"Glatter Moden OHG",
    "wof:placetype":"venue"
},
  "geometry": {"coordinates":[16.3989772797,47.7386245728],"type":"Point"}
}