{
  "type": "Feature",
  "properties": {
    "addr:full":"Gablonzer Weg 7 Linz Ober\u00f6sterreich 4030",
    "addr:housenumber":"7",
    "addr:postcode":"4030",
    "addr:street":"Gablonzer Weg",
    "iso:country":"AT",
    "sg:address":"Gablonzer Weg 7",
    "sg:city":"Linz",
    "sg:orig_category":"Metallwaren / Erzeugung U Gro\u00c3\u0178handel",
    "sg:phone":"+43 732 380084",
    "sg:postcode":"4030",
    "sg:province":"Ober\u00f6sterreich",
    "wof:name":"R\u00f6ssler Helmut",
    "wof:placetype":"venue"
},
  "geometry": {"coordinates":[14.2835712433,48.2495651245],"type":"Point"}
}