{
  "type": "Feature",
  "properties": {
    "addr:full":"Weidenweg 6 Wiener Neudorf Nieder\u00f6sterreich 2351",
    "addr:housenumber":"6",
    "addr:postcode":"2351",
    "addr:street":"Weidenweg",
    "iso:country":"AT",
    "sg:address":"Weidenweg 6",
    "sg:city":"Wiener Neudorf",
    "sg:classifiers":[
        {
            "category":"Community Center",
            "subcategory":"Ethnic",
            "type":"Public Place"
        }
    ],
    "sg:phone":"+43 2236 62569",
    "sg:postcode":"2351",
    "sg:province":"Nieder\u00f6sterreich",
    "sg:tags":[
        "cardiac",
        "pace-makers"
    ],
    "sg:website":"riesmedizin.at",
    "wof:name":"RIES Medizin Technik HandelsGmbH",
    "wof:placetype":"venue"
},
  "geometry": {"coordinates":[16.3307952881,48.0817527771],"type":"Point"}
}