{
  "type": "Feature",
  "properties": {
    "addr:full":"Ledochovskastr 1-3 Loosdorf Nieder\u00f6sterreich 3382",
    "addr:housenumber":"1-3",
    "addr:postcode":"3382",
    "addr:street":"Ledochovskastr",
    "iso:country":"AT",
    "sg:address":"Ledochovskastr 1-3",
    "sg:city":"Loosdorf",
    "sg:orig_category":"Behinderungen / Leben Mit Behinderungen",
    "sg:phone":"+43 2754 6377",
    "sg:postcode":"3382",
    "sg:province":"Nieder\u00f6sterreich",
    "wof:name":"Kinderheim d Schulwestern",
    "wof:placetype":"venue"
},
  "geometry": {"coordinates":[15.3811845779,48.1837120056],"type":"Point"}
}