{
  "type": "Feature",
  "properties": {
    "iso:country":"AT",
    "sg:address":"Hammerweg 2",
    "sg:city":"Zwettl",
    "sg:orig_category":"Volksschulen",
    "sg:phone":"+43 2822 527340",
    "sg:postcode":"3910",
    "sg:province":"Nieder\u00f6sterreich",
    "wof:name":"Volksschule",
    "wof:placetype":"venue"
},
  "geometry": {"coordinates":[15.1615428925,48.6072273254],"type":"Point"}
}