{
  "type": "Feature",
  "properties": {
    "addr:full":"B\u00e4ckerg 23 Stadl-Paura Ober\u00f6sterreich 4651",
    "addr:housenumber":"23",
    "addr:postcode":"4651",
    "addr:street":"Baeckerg",
    "iso:country":"AT",
    "sg:address":"B\u00e4ckerg 23",
    "sg:city":"Stadl-Paura",
    "sg:orig_category":"Bestattungsunternehmen",
    "sg:phone":"+43 7245 28827",
    "sg:postcode":"4651",
    "sg:province":"Ober\u00f6sterreich",
    "wof:name":"Bestattung Gr\u00fcnzweig",
    "wof:placetype":"venue"
},
  "geometry": {"coordinates":[13.8598508835,48.0781326294],"type":"Point"}
}