{
  "type": "Feature",
  "properties": {
    "addr:full":"Wolkersbergenstr 1 Wien Wien 1130",
    "addr:housenumber":"1",
    "addr:postcode":"1130",
    "addr:street":"Wolkersbergenstr",
    "iso:country":"AT",
    "sg:address":"Wolkersbergenstr 1",
    "sg:city":"Wien",
    "sg:orig_category":"Forschungsinstitute",
    "sg:phone":"+43 1 801102293",
    "sg:postcode":"1130",
    "sg:province":"Wien",
    "wof:name":"Ludwig Boltzmann Institut f gyn\u00e4kologische Onkologie und Fortpflanzungsmedizin",
    "wof:placetype":"venue"
},
  "geometry": {"coordinates":[16.2794780731,48.1689376831],"type":"Point"}
}