{
  "type": "Feature",
  "properties": {
    "addr:full":"Nr 26 M\u00f6derbrugg Steiermark 8763",
    "addr:postcode":"8763",
    "addr:street":"Nr 26 Moederbrugg Steiermark",
    "iso:country":"AT",
    "sg:address":"Nr 26",
    "sg:city":"M\u00f6derbrugg",
    "sg:orig_category":"Feuerwehren",
    "sg:phone":"+43 3571 2322",
    "sg:postcode":"8763",
    "sg:province":"Steiermark",
    "wof:name":"Freiwillige Feuerwehr St Oswald",
    "wof:placetype":"venue"
},
  "geometry": {"coordinates":[14.4165143967,47.3350410461],"type":"Point"}
}