{
  "type": "Feature",
  "properties": {
    "iso:country":"AT",
    "sg:address":"Nr 85",
    "sg:city":"Kirchdorf an der Krems",
    "sg:orig_category":"Non-Classified Establishments",
    "sg:phone":"+43 7582 63636",
    "sg:postcode":"4560",
    "sg:province":"Ober\u00f6sterreich",
    "wof:name":"Reifinger GesmbH",
    "wof:placetype":"venue"
},
  "geometry": {"coordinates":[14.1225223541,47.9058189392],"type":"Point"}
}