{
  "type": "Feature",
  "properties": {
    "addr:full":"Hauptstr 21 Ehrwald Tirol 6632",
    "addr:housenumber":"21",
    "addr:postcode":"6632",
    "addr:street":"Hauptstr;Tirol",
    "iso:country":"AT",
    "sg:address":"Hauptstr 21",
    "sg:city":"Ehrwald",
    "sg:classifiers":[
        {
            "category":"Restaurant",
            "type":"Food & Drink"
        }
    ],
    "sg:phone":"+43 5673 2766",
    "sg:postcode":"6632",
    "sg:province":"Tirol",
    "wof:name":"Restaurant Mooswirt",
    "wof:placetype":"venue"
},
  "geometry": {"coordinates":[10.9185066223,47.4014701843],"type":"Point"}
}