{
  "type": "Feature",
  "properties": {
    "iso:country":"AT",
    "sg:address":"10.Oktober-Pl 32",
    "sg:city":"Bleiburg",
    "sg:orig_category":"Friseure U Frisiersalons",
    "sg:phone":"+43 4235 2214",
    "sg:postcode":"9150",
    "sg:province":"K\u00e4rnten",
    "wof:name":"Haarstudio Doris Inh Roschitz Doris",
    "wof:placetype":"venue"
},
  "geometry": {"coordinates":[14.7975435257,46.5902099609],"type":"Point"}
}