{
  "type": "Feature",
  "properties": {
    "addr:full":"Wiener Strasse 127 Krems an der Donau Nieder\u00f6sterreich 3500",
    "addr:housenumber":"127",
    "addr:postcode":"3500",
    "addr:street":"Wiener Strasse",
    "iso:country":"AT",
    "sg:address":"Wiener Strasse 127",
    "sg:city":"Krems an der Donau",
    "sg:classifiers":[
        {
            "category":"Building & Trades",
            "subcategory":"Construction",
            "type":"Services"
        }
    ],
    "sg:phone":"+43 2732 865860",
    "sg:postcode":"3500",
    "sg:province":"Nieder\u00f6sterreich",
    "sg:tags":[
        "flat",
        "steep",
        "roof",
        "waterproofing"
    ],
    "sg:website":"nestlergmbh.at",
    "wof:name":"Ing. Nestler Ges.m.b.H.",
    "wof:placetype":"venue"
},
  "geometry": {"coordinates":[15.63027668,48.4190635681],"type":"Point"}
}