{
  "type": "Feature",
  "properties": {
    "addr:full":"Favoritenstr 239 Hansson Zentrum Top 21 Wien Wien 1100",
    "addr:housenumber":"239",
    "addr:postcode":"1100",
    "addr:street":"Hansson",
    "iso:country":"AT",
    "sg:address":"Favoritenstr 239 Hansson Zentrum Top 21",
    "sg:city":"Wien",
    "sg:orig_category":"Banken U Sparkassen",
    "sg:phone":"+43 4316 8979810",
    "sg:postcode":"1100",
    "sg:province":"Wien",
    "wof:name":"Bank f Arbeit u Wirtschaft AG",
    "wof:placetype":"venue"
},
  "geometry": {"coordinates":[16.3744049072,48.1782684326],"type":"Point"}
}