{
  "type": "Feature",
  "properties": {
    "iso:country":"AT",
    "sg:address":"Lustenauer Str 25",
    "sg:city":"Dornbirn",
    "sg:orig_category":"Architekten",
    "sg:phone":"+43 5572 398100",
    "sg:postcode":"6850",
    "sg:province":"Vorarlberg",
    "wof:name":"Schaffer Peter Dipl-Ing",
    "wof:placetype":"venue"
},
  "geometry": {"coordinates":[9.7356271744,47.406627655],"type":"Point"}
}