{
  "type": "Feature",
  "properties": {
    "addr:full":"Osterleiteng 2 Wien Wien 1190",
    "addr:housenumber":"2",
    "addr:postcode":"1190",
    "addr:street":"Osterleiteng",
    "iso:country":"AT",
    "sg:address":"Osterleiteng 2",
    "sg:city":"Wien",
    "sg:orig_category":"Psychotherapie",
    "sg:phone":"+43 1 3683227",
    "sg:postcode":"1190",
    "sg:province":"Wien",
    "wof:name":"Wille-R\u00f6mer Gertrude Dr",
    "wof:placetype":"venue"
},
  "geometry": {"coordinates":[16.3555831909,48.239730835],"type":"Point"}
}