{
  "type": "Feature",
  "properties": {
    "iso:country":"AT",
    "sg:address":"Raiffeisenstrasse 118-120",
    "sg:city":"Liebenau",
    "sg:classifiers":[
        {
            "category":"Professional",
            "subcategory":"Advertising",
            "type":"Services"
        }
    ],
    "sg:phone":"+43 316 4655190",
    "sg:postcode":"8041",
    "sg:province":"Steiermark",
    "sg:tags":[
        "agency"
    ],
    "wof:name":"Werner M\u00f6rth Ges.m.b.H.",
    "wof:placetype":"venue"
},
  "geometry": {"coordinates":[15.4524297714,47.0459976196],"type":"Point"}
}