{
  "type": "Feature",
  "properties": {
    "addr:full":"Mittertorstr 5-7 Mureck Steiermark 8480",
    "addr:housenumber":"5-7",
    "addr:postcode":"8480",
    "addr:street":"Mittertorstr",
    "iso:country":"AT",
    "sg:address":"Mittertorstr 5-7",
    "sg:city":"Mureck",
    "sg:classifiers":[
        {
            "category":"Home & Garden",
            "subcategory":"Building Materials",
            "type":"Retail Goods"
        }
    ],
    "sg:phone":"+43 3472 21260",
    "sg:postcode":"8480",
    "sg:province":"Steiermark",
    "sg:tags":[
        "baustoffe",
        "-material",
        "u"
    ],
    "wof:name":"Baumeister Frohnwieser Baustoffhandel GesmbH",
    "wof:placetype":"venue"
},
  "geometry": {"coordinates":[15.7766599655,46.7106018066],"type":"Point"}
}