{
  "type": "Feature",
  "properties": {
    "iso:country":"AT",
    "sg:address":"Hauptstr 48a",
    "sg:city":"Bernstein",
    "sg:orig_category":"Friseure U Frisiersalons",
    "sg:phone":"+43 4333 546567",
    "sg:postcode":"7434",
    "sg:province":"Burgenland",
    "wof:name":"Beigelbeck Martin",
    "wof:placetype":"venue"
},
  "geometry": {"coordinates":[16.2594852448,47.4060401917],"type":"Point"}
}