{
  "type": "Feature",
  "properties": {
    "iso:country":"AT",
    "sg:address":"Hofriedenstr 17",
    "sg:city":"Lochau",
    "sg:orig_category":"Tankstellen",
    "sg:phone":"+43 4355 74436740",
    "sg:postcode":"6911",
    "sg:province":"Vorarlberg",
    "wof:name":"OMV AG",
    "wof:placetype":"venue"
},
  "geometry": {"coordinates":[9.7520647049,47.5345344543],"type":"Point"}
}