{
  "type": "Feature",
  "properties": {
    "addr:full":"Ameisbergstr 9 Putzleinsdorf Ober\u00f6sterreich 4134",
    "addr:housenumber":"9",
    "addr:postcode":"4134",
    "addr:street":"Ameisbergstr",
    "iso:country":"AT",
    "sg:address":"Ameisbergstr 9",
    "sg:city":"Putzleinsdorf",
    "sg:orig_category":"Transportunternehmen",
    "sg:phone":"+43 7286 8286",
    "sg:postcode":"4134",
    "sg:province":"Ober\u00f6sterreich",
    "wof:name":"Schneeberger Karl GesmbH & Co KG",
    "wof:placetype":"venue"
},
  "geometry": {"coordinates":[13.87454319,48.5186843872],"type":"Point"}
}