{
  "type": "Feature",
  "properties": {
    "iso:country":"AT",
    "sg:address":"Leutschacher Strasse 37",
    "sg:city":"Arnfels",
    "sg:classifiers":[
        {
            "category":"Professional",
            "subcategory":"Advertising",
            "type":"Services"
        }
    ],
    "sg:phone":"+43 3455 6644",
    "sg:postcode":"8454",
    "sg:province":"Steiermark",
    "sg:tags":[
        "gift"
    ],
    "sg:website":"klapothek.at",
    "wof:name":"Sallfellner & Jauk OEG",
    "wof:placetype":"venue"
},
  "geometry": {"coordinates":[15.4054317474,46.6760787964],"type":"Point"}
}