{
  "type": "Feature",
  "properties": {
    "addr:full":"Nr 17a St. Anna am Aigen Steiermark 8354",
    "addr:postcode":"8354",
    "addr:street":"Nr 17A St.;Am Aigen Steiermark",
    "iso:country":"AT",
    "sg:address":"Nr 17a",
    "sg:city":"St. Anna am Aigen",
    "sg:orig_category":"Massagen",
    "sg:phone":"+43 3158 2848",
    "sg:postcode":"8354",
    "sg:province":"Steiermark",
    "wof:name":"Massagepraxis Cornelia Seidl",
    "wof:placetype":"venue"
},
  "geometry": {"coordinates":[6.563270092,50.9379005432],"type":"Point"}
}