{
  "type": "Feature",
  "properties": {
    "addr:full":"Spitalstr 15 Oberpullendorf Burgenland 7350",
    "addr:housenumber":"15",
    "addr:postcode":"7350",
    "addr:street":"Spitalstr",
    "iso:country":"AT",
    "sg:address":"Spitalstr 15",
    "sg:city":"Oberpullendorf",
    "sg:orig_category":"Bandagen U Bandagisten",
    "sg:phone":"+43 2612 43650",
    "sg:postcode":"7350",
    "sg:province":"Burgenland",
    "wof:name":"Sanit\u00e4tshaus Novotny und Pistora GmbH",
    "wof:placetype":"venue"
},
  "geometry": {"coordinates":[16.5053730011,47.5041007996],"type":"Point"}
}