{
  "type": "Feature",
  "properties": {
    "addr:full":"Hof 257 Lingenau Vorarlberg 6951",
    "addr:housenumber":"257",
    "addr:postcode":"6951",
    "addr:street":"Hof",
    "iso:country":"AT",
    "sg:address":"Hof 257",
    "sg:city":"Lingenau",
    "sg:orig_category":"Banken U Sparkassen",
    "sg:phone":"+43 4355 136121",
    "sg:postcode":"6951",
    "sg:province":"Vorarlberg",
    "wof:name":"Raiffeisenbank Lingenau regGenmbH",
    "wof:placetype":"venue"
},
  "geometry": {"coordinates":[9.920044899,47.4501609802],"type":"Point"}
}