{
  "type": "Feature",
  "properties": {
    "addr:full":"Goldschlagstr 157 Wien Wien 1140",
    "addr:housenumber":"157",
    "addr:postcode":"1140",
    "iso:country":"AT",
    "sg:address":"Goldschlagstr 157",
    "sg:city":"Wien",
    "sg:orig_category":"Notare",
    "sg:phone":"+43 1 98203830",
    "sg:postcode":"1140",
    "sg:province":"Wien",
    "wof:name":"Diwald Karl Dr",
    "wof:placetype":"venue"
},
  "geometry": {"coordinates":[16.3063297272,48.1957244873],"type":"Point"}
}