{
  "type": "Feature",
  "properties": {
    "addr:full":"Rosentaler Str 136 Klagenfurt K\u00e4rnten 9020",
    "addr:housenumber":"136",
    "addr:postcode":"9020",
    "addr:street":"Kaernten",
    "iso:country":"AT",
    "sg:address":"Rosentaler Str 136",
    "sg:city":"Klagenfurt",
    "sg:orig_category":"Damenmoden",
    "sg:phone":"+43 463 502727",
    "sg:postcode":"9020",
    "sg:province":"K\u00e4rnten",
    "wof:name":"Linea U'woman fashion",
    "wof:placetype":"venue"
},
  "geometry": {"coordinates":[14.2999286652,46.609790802],"type":"Point"}
}