{
  "type": "Feature",
  "properties": {
    "iso:country":"AT",
    "sg:address":"Obenberg",
    "sg:city":"Ried in der Riedmark",
    "sg:orig_category":"Feuerwehren",
    "sg:phone":"+43 7238 2805",
    "sg:postcode":"4312",
    "sg:province":"Ober\u00f6sterreich",
    "wof:name":"Freiwillige Feuerwehr Obenberg",
    "wof:placetype":"venue"
},
  "geometry": {"coordinates":[14.545006752,48.2749862671],"type":"Point"}
}