{
  "type": "Feature",
  "properties": {
    "iso:country":"AT",
    "sg:address":"Nr 108",
    "sg:city":"Fehring",
    "sg:orig_category":"Tischlereien",
    "sg:phone":"+43 4331 552602",
    "sg:postcode":"8350",
    "sg:province":"Steiermark",
    "wof:name":"Einrichtungswerkst\u00e4tte Gro\u00df GmbH & Co KG",
    "wof:placetype":"venue"
},
  "geometry": {"coordinates":[16.066734314,46.9451332092],"type":"Point"}
}