{
  "type": "Feature",
  "properties": {
    "iso:country":"AT",
    "sg:address":"Nr 48",
    "sg:city":"Fiss",
    "sg:orig_category":"Appartements / Ferienwohnungen",
    "sg:phone":"+43 5476 6428",
    "sg:postcode":"6533",
    "sg:province":"Tirol",
    "wof:name":"Ferienwohnungen Schimpf\u00f6\u00dfl",
    "wof:placetype":"venue"
},
  "geometry": {"coordinates":[10.618268013,47.0554733276],"type":"Point"}
}