{
  "type": "Feature",
  "properties": {
    "addr:full":"Heinrich-Paris-G 7 Lunz am See Nieder\u00f6sterreich 3293",
    "addr:housenumber":"7",
    "addr:postcode":"3293",
    "addr:street":"Heinrich-Paris-G;Niederoesterreich",
    "iso:country":"AT",
    "sg:address":"Heinrich-Paris-G 7",
    "sg:city":"Lunz am See",
    "sg:orig_category":"Baumeister",
    "sg:phone":"+43 7486 8788",
    "sg:postcode":"3293",
    "sg:province":"Nieder\u00f6sterreich",
    "wof:name":"En\u00f6ckl GmbH",
    "wof:placetype":"venue"
},
  "geometry": {"coordinates":[15.02323246,47.8591117859],"type":"Point"}
}