{
  "type": "Feature",
  "properties": {
    "iso:country":"AT",
    "sg:address":"Am Rennfeld 9",
    "sg:city":"Gleisdorf",
    "sg:orig_category":"Massagen",
    "sg:phone":"+43 3112 2069",
    "sg:postcode":"8200",
    "sg:province":"Steiermark",
    "wof:name":"Fank Elfi",
    "wof:placetype":"venue"
},
  "geometry": {"coordinates":[15.7139863968,47.1001434326],"type":"Point"}
}