{
  "type": "Feature",
  "properties": {
    "iso:country":"AT",
    "sg:address":"Schart 4",
    "sg:city":"Vorchdorf",
    "sg:classifiers":[
        {
            "category":"Manufacturing",
            "subcategory":"Motor Vehicles & Parts",
            "type":"Manufacturing & Wholesale Goods"
        }
    ],
    "sg:phone":"+43 76146477",
    "sg:postcode":"4655",
    "sg:province":"Ober\u00f6sterreich",
    "sg:tags":[
        "component",
        "hydraulic"
    ],
    "wof:name":"Franz L\u00f6berbauer",
    "wof:placetype":"venue"
},
  "geometry": {"coordinates":[13.9501934052,48.0275917053],"type":"Point"}
}