{
  "type": "Feature",
  "properties": {
    "addr:full":"Goldegg 2 Wien Wien 1040",
    "addr:housenumber":"2",
    "addr:postcode":"1040",
    "addr:street":"Goldegg",
    "iso:country":"AT",
    "sg:address":"Goldegg 2",
    "sg:city":"Wien",
    "sg:orig_category":"Betriebsbeteiligungen",
    "sg:phone":"+43 1 5054268",
    "sg:postcode":"1040",
    "sg:province":"Wien",
    "wof:name":"Kirchner BeteiligungsgesmbH",
    "wof:placetype":"venue"
},
  "geometry": {"coordinates":[16.3796253204,48.190448761],"type":"Point"}
}