{
  "type": "Feature",
  "properties": {
    "addr:full":"Lindeng 52 Wien Wien 1070",
    "addr:housenumber":"52",
    "addr:postcode":"1070",
    "addr:street":"Lindeng",
    "iso:country":"AT",
    "sg:address":"Lindeng 52",
    "sg:city":"Wien",
    "sg:orig_category":"Zeitungen U Zeitschriften / Vertrieb",
    "sg:phone":"+43 1 521300",
    "sg:postcode":"1070",
    "sg:province":"Wien",
    "wof:name":"Mediaprint ZeitungsvertriebsgesmbH & Co KG",
    "wof:placetype":"venue"
},
  "geometry": {"coordinates":[16.3464603424,48.1996688843],"type":"Point"}
}