{
  "type": "Feature",
  "properties": {
    "addr:full":"Landstra\u00dfer Hauptstr 60 Wien Wien 1030",
    "addr:housenumber":"60",
    "addr:postcode":"1030",
    "addr:street":"Landstrasser Hauptstr",
    "iso:country":"AT",
    "sg:address":"Landstra\u00dfer Hauptstr 60",
    "sg:city":"Wien",
    "sg:orig_category":"Nachhilfe U Lernbetreuung",
    "sg:phone":"+43 1 7155644",
    "sg:postcode":"1030",
    "sg:province":"Wien",
    "wof:name":"LernQuadrat",
    "wof:placetype":"venue"
},
  "geometry": {"coordinates":[16.3911876678,48.2018127441],"type":"Point"}
}