{
  "type": "Feature",
  "properties": {
    "iso:country":"AT",
    "sg:address":"Kircheng 15",
    "sg:city":"Haringsee",
    "sg:orig_category":"Autoreparatur",
    "sg:phone":"+43 2214 84088",
    "sg:postcode":"2286",
    "sg:province":"Nieder\u00f6sterreich",
    "wof:name":"Winterleitner Johann Ing",
    "wof:placetype":"venue"
},
  "geometry": {"coordinates":[16.7849998474,48.1926956177],"type":"Point"}
}