{
  "type": "Feature",
  "properties": {
    "iso:country":"AT",
    "sg:address":"Irnfriedstr 2",
    "sg:city":"Ybbs an der Donau",
    "sg:classifiers":[
        {
            "category":"Internet Cafe",
            "subcategory":"None",
            "type":"Food & Drink"
        }
    ],
    "sg:phone":"+43 7412 55501",
    "sg:postcode":"3370",
    "sg:province":"Nieder\u00f6sterreich",
    "wof:name":"Weber Michael KEG",
    "wof:placetype":"venue"
},
  "geometry": {"coordinates":[15.0770254135,48.1800308228],"type":"Point"}
}