{
  "type": "Feature",
  "properties": {
    "addr:full":"Unterwaltersdorfer Str 101 Gramatneusiedl Nieder\u00f6sterreich 2440",
    "addr:housenumber":"101",
    "addr:postcode":"2440",
    "iso:country":"AT",
    "sg:address":"Unterwaltersdorfer Str 101",
    "sg:city":"Gramatneusiedl",
    "sg:orig_category":"Wasserwerke",
    "sg:phone":"+43 4322 3478412",
    "sg:postcode":"2440",
    "sg:province":"Nieder\u00f6sterreich",
    "wof:name":"Wasserwerk d Gemeinde M\u00f6dling",
    "wof:placetype":"venue"
},
  "geometry": {"coordinates":[16.4527893066,48.011100769],"type":"Point"}
}