{
  "type": "Feature",
  "properties": {
    "addr:full":"Marktg 34 Bernstein Burgenland 7434",
    "addr:housenumber":"34",
    "addr:postcode":"7434",
    "addr:street":"Marktg",
    "iso:country":"AT",
    "sg:address":"Marktg 34",
    "sg:city":"Bernstein",
    "sg:orig_category":"Geschenkartikel",
    "sg:phone":"+43 3354 6034",
    "sg:postcode":"7434",
    "sg:province":"Burgenland",
    "wof:name":"Holzdesign Eichberger",
    "wof:placetype":"venue"
},
  "geometry": {"coordinates":[16.2558078766,47.4056777954],"type":"Point"}
}