{
  "type": "Feature",
  "properties": {
    "addr:full":"Ritzstrasse 8 Marchtrenk Ober\u00f6sterreich 4614",
    "addr:housenumber":"8",
    "addr:postcode":"4614",
    "addr:street":"Ritzstrasse",
    "iso:country":"AT",
    "sg:address":"Ritzstrasse 8",
    "sg:city":"Marchtrenk",
    "sg:classifiers":[
        {
            "category":"Retail",
            "subcategory":"Driving School",
            "type":"Services"
        }
    ],
    "sg:phone":"+43 7243 535860",
    "sg:postcode":"4614",
    "sg:province":"Ober\u00f6sterreich",
    "sg:tags":[
        "drive"
    ],
    "sg:website":"keb.at",
    "wof:name":"KEB-Antriebstechnik Austria GmbH",
    "wof:placetype":"venue"
},
  "geometry": {"coordinates":[14.1329479218,48.1923027039],"type":"Point"}
}