{
  "type": "Feature",
  "properties": {
    "iso:country":"AT",
    "sg:address":"St Valentiner Str 23",
    "sg:city":"Wimpassing im Schwarzatale",
    "sg:classifiers":[
        {
            "category":"Professional",
            "subcategory":"Management & Consulting",
            "type":"Services"
        }
    ],
    "sg:phone":"+43 2630 35694",
    "sg:postcode":"2632",
    "sg:province":"Nieder\u00f6sterreich",
    "sg:tags":[
        "supervision"
    ],
    "wof:name":"Meixner Margarete",
    "wof:placetype":"venue"
},
  "geometry": {"coordinates":[16.0243911743,47.6970901489],"type":"Point"}
}