{
  "type": "Feature",
  "properties": {
    "iso:country":"AT",
    "sg:address":"Markt 10",
    "sg:city":"Edlitz",
    "sg:orig_category":"Zahntechnische Laboratorien",
    "sg:phone":"+43 2644 2212",
    "sg:postcode":"2842",
    "sg:province":"Nieder\u00f6sterreich",
    "wof:name":"Mayrhofer & Guzmich GesmbH",
    "wof:placetype":"venue"
},
  "geometry": {"coordinates":[16.1358203888,47.6015663147],"type":"Point"}
}