{
  "type": "Feature",
  "properties": {
    "addr:full":"Breitenleer Str 106 Wien Wien 1220",
    "addr:housenumber":"106",
    "addr:postcode":"1220",
    "iso:country":"AT",
    "sg:address":"Breitenleer Str 106",
    "sg:city":"Wien",
    "sg:orig_category":"Lebensmittel / Einzelhandel",
    "sg:phone":"+43 1 7342646",
    "sg:postcode":"1220",
    "sg:province":"Wien",
    "wof:name":"Hofer KG",
    "wof:placetype":"venue"
},
  "geometry": {"coordinates":[16.4694900513,48.2514915466],"type":"Point"}
}