{
  "type": "Feature",
  "properties": {
    "iso:country":"AT",
    "sg:address":"Hafenstr 47-51",
    "sg:city":"Linz",
    "sg:orig_category":"Werbeagenturen",
    "sg:phone":"+43 7235 63923888",
    "sg:postcode":"4020",
    "sg:province":"Ober\u00f6sterreich",
    "wof:name":"iManufaktur Campbell KEG - Agentur f interaktive Kommunikation",
    "wof:placetype":"venue"
},
  "geometry": {"coordinates":[14.3066530228,48.317943573],"type":"Point"}
}