{
  "type": "Feature",
  "properties": {
    "iso:country":"AT",
    "sg:address":"Wiener Str 93",
    "sg:city":"Linz",
    "sg:orig_category":"Tabaktrafiken",
    "sg:phone":"+43 732 667137",
    "sg:postcode":"4020",
    "sg:province":"Ober\u00f6sterreich",
    "wof:name":"Kerschbaummayr Erwin",
    "wof:placetype":"venue"
},
  "geometry": {"coordinates":[14.3049631119,48.2838516235],"type":"Point"}
}