{
  "type": "Feature",
  "properties": {
    "addr:full":"Rosensteing 69 Wien Wien 1170",
    "addr:housenumber":"69",
    "addr:postcode":"1170",
    "addr:street":"Rosensteing",
    "iso:country":"AT",
    "sg:address":"Rosensteing 69",
    "sg:city":"Wien",
    "sg:classifiers":[
        {
            "category":"Professional",
            "subcategory":"Computer Services",
            "type":"Services"
        }
    ],
    "sg:phone":"+43 4314 803924",
    "sg:postcode":"1170",
    "sg:province":"Wien",
    "sg:tags":[
        "software"
    ],
    "wof:name":"HITEL High Tech Electronic Entwicklungs- u HandelsgesmbH",
    "wof:placetype":"venue"
},
  "geometry": {"coordinates":[16.3265590668,48.2199058533],"type":"Point"}
}