{
  "type": "Feature",
  "properties": {
    "addr:full":"Liesinger Pl 1 Wien Wien 1230",
    "addr:housenumber":"1",
    "addr:postcode":"1230",
    "addr:street":"Liesinger Pl",
    "iso:country":"AT",
    "sg:address":"Liesinger Pl 1",
    "sg:city":"Wien",
    "sg:orig_category":"Schlankheitsinstitute",
    "sg:phone":"+43 4318 652086",
    "sg:postcode":"1230",
    "sg:province":"Wien",
    "wof:name":"Figurella International GmbH",
    "wof:placetype":"venue"
},
  "geometry": {"coordinates":[16.2832775116,48.1353530884],"type":"Point"}
}