{
  "type": "Feature",
  "properties": {
    "iso:country":"AT",
    "sg:address":"Quellenstr 72/4",
    "sg:city":"Wien",
    "sg:orig_category":"Nachhilfe U Lernbetreuung",
    "sg:phone":"+43 4316 074856",
    "sg:postcode":"1100",
    "sg:province":"Wien",
    "wof:name":"Ph\u00f6nix-Institut f Kultur-Bildung-Sport",
    "wof:placetype":"venue"
},
  "geometry": {"coordinates":[16.3761081696,48.1755714417],"type":"Point"}
}