{
  "type": "Feature",
  "properties": {
    "iso:country":"AT",
    "sg:address":"Richterstr 6",
    "sg:city":"Lambach",
    "sg:orig_category":"Architekten",
    "sg:phone":"+43 7245 28053",
    "sg:postcode":"4650",
    "sg:province":"Ober\u00f6sterreich",
    "wof:name":"Holzleithner Walter Dipl-Ing",
    "wof:placetype":"venue"
},
  "geometry": {"coordinates":[13.8674697876,48.0900917053],"type":"Point"}
}