{
  "type": "Feature",
  "properties": {
    "addr:full":"Hietzinger Hauptstr 15 Wien Wien 1130",
    "addr:housenumber":"15",
    "addr:postcode":"1130",
    "addr:street":"Hietzinger Hauptstr",
    "iso:country":"AT",
    "sg:address":"Hietzinger Hauptstr 15",
    "sg:city":"Wien",
    "sg:orig_category":"Drogerien",
    "sg:phone":"+43 1 8773210",
    "sg:postcode":"1130",
    "sg:province":"Wien",
    "wof:name":"dm drogerie markt GmbH",
    "wof:placetype":"venue"
},
  "geometry": {"coordinates":[16.2996082306,48.1861572266],"type":"Point"}
}