{
  "type": "Feature",
  "properties": {
    "addr:full":"Dr.-Glatz-Str 20 Innsbruck Tirol 6020",
    "addr:housenumber":"20",
    "addr:postcode":"6020",
    "addr:street":"Dr.-Glatz-Str;Tirol",
    "iso:country":"AT",
    "sg:address":"Dr.-Glatz-Str 20",
    "sg:city":"Innsbruck",
    "sg:classifiers":[
        {
            "category":"Travel",
            "subcategory":"Hotels & Motels",
            "type":"Entertainment"
        }
    ],
    "sg:phone":"+43 512 334360",
    "sg:postcode":"6020",
    "sg:province":"Tirol",
    "wof:name":"ARThotel GmbH",
    "wof:placetype":"venue"
},
  "geometry": {"coordinates":[11.41431427,47.2600708008],"type":"Point"}
}