{
  "type": "Feature",
  "properties": {
    "iso:country":"AT",
    "sg:address":"Dorf 106",
    "sg:city":"Bad H\u00e4ring",
    "sg:orig_category":"Alternativtherapie",
    "sg:phone":"+43 5332 90500717",
    "sg:postcode":"6323",
    "sg:province":"Tirol",
    "wof:name":"Zimmermann Gerald Dr",
    "wof:placetype":"venue"
},
  "geometry": {"coordinates":[-88.67497253419999,43.9075889587],"type":"Point"}
}