{
  "type": "Feature",
  "properties": {
    "iso:country":"AT",
    "sg:address":"Kirchberger Str 9",
    "sg:city":"Pasching",
    "sg:orig_category":"Autohandel",
    "sg:phone":"+43 7221 88770",
    "sg:postcode":"4061",
    "sg:province":"Ober\u00f6sterreich",
    "wof:name":"Kr\u00fcgel Hermann",
    "wof:placetype":"venue"
},
  "geometry": {"coordinates":[14.1903181076,48.2678718567],"type":"Point"}
}