{
  "type": "Feature",
  "properties": {
    "addr:full":"Leisach 48 Lienz Tirol 9900",
    "addr:housenumber":"48",
    "addr:postcode":"9900",
    "addr:street":"Leisach;Tirol",
    "iso:country":"AT",
    "sg:address":"Leisach 48",
    "sg:city":"Lienz",
    "sg:classifiers":[
        {
            "category":"Manufacturing",
            "subcategory":"Signs",
            "type":"Manufacturing & Wholesale Goods"
        }
    ],
    "sg:phone":"+43 4852 62109",
    "sg:postcode":"9900",
    "sg:province":"Tirol",
    "sg:tags":[
        "car",
        "lettering"
    ],
    "wof:name":"Michael Musner",
    "wof:placetype":"venue"
},
  "geometry": {"coordinates":[12.7540426254,46.8172225952],"type":"Point"}
}