{
  "type": "Feature",
  "properties": {
    "addr:full":"Wiener Str 88 Kapfenberg Steiermark 8605",
    "addr:postcode":"8605",
    "addr:street":"88",
    "iso:country":"AT",
    "sg:address":"Wiener Str 88",
    "sg:city":"Kapfenberg",
    "sg:classifiers":[
        {
            "category":"Taxi",
            "type":"Transportation"
        }
    ],
    "sg:phone":"+43 3862 27227",
    "sg:postcode":"8605",
    "sg:province":"Steiermark",
    "sg:tags":[
        "personentransporte",
        "u"
    ],
    "wof:name":"Taxi-Service Manuela Laresser OEG",
    "wof:placetype":"venue"
},
  "geometry": {"coordinates":[15.303519249,47.4470596313],"type":"Point"}
}