{
  "type": "Feature",
  "properties": {
    "addr:full":"Hag 3 Telfs Tirol 6410",
    "addr:housenumber":"3",
    "addr:postcode":"6410",
    "addr:street":"Hag;Tirol",
    "iso:country":"AT",
    "sg:address":"Hag 3",
    "sg:city":"Telfs",
    "sg:classifiers":[
        {
            "category":"Home & Garden",
            "subcategory":"Building Materials",
            "type":"Retail Goods"
        }
    ],
    "sg:phone":"+43 5262 63067",
    "sg:postcode":"6410",
    "sg:province":"Tirol",
    "sg:tags":[
        "aluminium",
        "gutter"
    ],
    "wof:name":"August K\u00f6ll GesmbH",
    "wof:placetype":"venue"
},
  "geometry": {"coordinates":[11.0979223251,47.3155212402],"type":"Point"}
}