{
  "type": "Feature",
  "properties": {
    "addr:full":"Edelsinnstr 16 Wien Wien 1120",
    "addr:housenumber":"16",
    "addr:postcode":"1120",
    "addr:street":"Edelsinnstr",
    "iso:country":"AT",
    "sg:address":"Edelsinnstr 16",
    "sg:city":"Wien",
    "sg:orig_category":"Tankstellen",
    "sg:phone":"+43 4318 133834",
    "sg:postcode":"1120",
    "sg:province":"Wien",
    "wof:name":"AVANTI TankstellenbetriebsgesmbH",
    "wof:placetype":"venue"
},
  "geometry": {"coordinates":[16.3194332123,48.1723060608],"type":"Point"}
}