{
  "type": "Feature",
  "properties": {
    "addr:full":"Marktg 4 Murau Steiermark 8850",
    "addr:housenumber":"4",
    "addr:postcode":"8850",
    "addr:street":"Marktg",
    "iso:country":"AT",
    "sg:address":"Marktg 4",
    "sg:city":"Murau",
    "sg:orig_category":"Museen / Ausstellungen",
    "sg:phone":"+43 3532 2015",
    "sg:postcode":"8850",
    "sg:province":"Steiermark",
    "wof:name":"Evangelisches Di\u00f6zesanmuseum",
    "wof:placetype":"venue"
},
  "geometry": {"coordinates":[14.1716346741,47.1107406616],"type":"Point"}
}