{
  "type": "Feature",
  "properties": {
    "addr:full":"Nr 109 St. Margarethen an der Sierning Nieder\u00f6sterreich 3231",
    "addr:postcode":"3231",
    "addr:street":"Nr 109",
    "iso:country":"AT",
    "sg:address":"Nr 109",
    "sg:city":"St. Margarethen an der Sierning",
    "sg:orig_category":"Normteile",
    "sg:phone":"+43 4327 4767690",
    "sg:postcode":"3231",
    "sg:province":"Nieder\u00f6sterreich",
    "wof:name":"B-S-D Spanntechnik GmbH",
    "wof:placetype":"venue"
},
  "geometry": {"coordinates":[15.4920043945,48.1588020325],"type":"Point"}
}