{
  "type": "Feature",
  "properties": {
    "addr:full":"Rasumofskyg. 2  Wien Wien 1030",
    "addr:housenumber":"2",
    "addr:postcode":"1030",
    "addr:street":"Rasumofskyg.",
    "iso:country":"AT",
    "sg:address":"Rasumofskyg. 2 ",
    "sg:city":"Wien",
    "sg:classifiers":[
        {
            "category":"Travel",
            "subcategory":"Travel Agent",
            "type":"Entertainment"
        }
    ],
    "sg:phone":"+43 4317 1351680",
    "sg:postcode":"1030",
    "sg:province":"Wien",
    "sg:tags":[
        "business"
    ],
    "wof:name":"RESTAURANT STEIERERECK GESMBH",
    "wof:placetype":"venue"
},
  "geometry": {"coordinates":[16.3958702087,48.2059860229],"type":"Point"}
}