{
  "type": "Feature",
  "properties": {
    "iso:country":"AT",
    "sg:address":"Welser Str 56",
    "sg:city":"Gunskirchen",
    "sg:orig_category":"Tischlereien",
    "sg:phone":"+43 7246 63090",
    "sg:postcode":"4623",
    "sg:province":"Ober\u00f6sterreich",
    "sg:website":"hummelbrunner.at",
    "wof:name":"Hummelbrunner Harald",
    "wof:placetype":"venue"
},
  "geometry": {"coordinates":[13.95429039,48.1370773315],"type":"Point"}
}