{
  "type": "Feature",
  "properties": {
    "addr:full":"Sonnensteinstrasse 1 Linz Ober\u00f6sterreich 4040",
    "addr:housenumber":"1",
    "addr:postcode":"4040",
    "addr:street":"Sonnensteinstrasse",
    "iso:country":"AT",
    "sg:address":"Sonnensteinstrasse 1",
    "sg:city":"Linz",
    "sg:classifiers":[
        {
            "category":"Health Services",
            "subcategory":"Clinic",
            "type":"Services"
        }
    ],
    "sg:phone":"+43 732 738316",
    "sg:postcode":"4040",
    "sg:province":"Ober\u00f6sterreich",
    "sg:tags":[
        "dental",
        "chair"
    ],
    "wof:name":"Bandagist HEINDL Ges.m.b.H.",
    "wof:placetype":"venue"
},
  "geometry": {"coordinates":[14.2835302353,48.3128013611],"type":"Point"}
}