{
  "type": "Feature",
  "properties": {
    "addr:full":"Nr 29 St. Margarethen im Lavanttal K\u00e4rnten 9412",
    "addr:postcode":"9412",
    "addr:street":"Nr 29",
    "iso:country":"AT",
    "sg:address":"Nr 29",
    "sg:city":"St. Margarethen im Lavanttal",
    "sg:orig_category":"Volksschulen",
    "sg:phone":"+43 4343 5261131",
    "sg:postcode":"9412",
    "sg:province":"K\u00e4rnten",
    "wof:name":"Volksschule",
    "wof:placetype":"venue"
},
  "geometry": {"coordinates":[14.8014202118,46.8557281494],"type":"Point"}
}