{
  "type": "Feature",
  "properties": {
    "addr:full":"Paulitschg 11 Klagenfurt K\u00e4rnten 9020",
    "addr:housenumber":"11",
    "addr:postcode":"9020",
    "addr:street":"Paulitschg;Kaernten",
    "iso:country":"AT",
    "sg:address":"Paulitschg 11",
    "sg:city":"Klagenfurt",
    "sg:orig_category":"Freizeit- U Sportbekleidung",
    "sg:phone":"+43 4346 3500497",
    "sg:postcode":"9020",
    "sg:province":"K\u00e4rnten",
    "wof:name":"FACTORY OUTLET HandelsGmbH",
    "wof:placetype":"venue"
},
  "geometry": {"coordinates":[14.308842659,46.6216392517],"type":"Point"}
}