{
  "type": "Feature",
  "properties": {
    "addr:full":"Langefelder Str 14 Trofaiach Steiermark 8793",
    "addr:postcode":"8793",
    "addr:street":"Str 14",
    "iso:country":"AT",
    "sg:address":"Langefelder Str 14",
    "sg:city":"Trofaiach",
    "sg:orig_category":"Banken U Sparkassen",
    "sg:phone":"+43 4350 10036246",
    "sg:postcode":"8793",
    "sg:province":"Steiermark",
    "wof:name":"Steierm\u00e4rkische Bank u Sparkassen AG",
    "wof:placetype":"venue"
},
  "geometry": {"coordinates":[14.9976854324,47.4243621826],"type":"Point"}
}