{
  "type": "Feature",
  "properties": {
    "iso:country":"AT",
    "sg:address":"Humelfeldstrasse 13",
    "sg:city":"St. Valentin",
    "sg:classifiers":[
        {
            "category":"Shopping",
            "subcategory":"Crafts & Fabrics",
            "type":"Retail Goods"
        }
    ],
    "sg:phone":"+43 7435 59065",
    "sg:postcode":"4300",
    "sg:province":"Nieder\u00f6sterreich",
    "sg:tags":[
        "adhesive"
    ],
    "sg:website":"soudal.com",
    "wof:name":"SOUDAL NV",
    "wof:placetype":"venue"
},
  "geometry": {"coordinates":[14.5187797546,48.1914710999],"type":"Point"}
}