{
  "type": "Feature",
  "properties": {
    "addr:full":"Tullnerbachstr 128 Untertullnerbach Nieder\u00f6sterreich 3011",
    "addr:housenumber":"128",
    "addr:postcode":"3011",
    "iso:country":"AT",
    "sg:address":"Tullnerbachstr 128",
    "sg:city":"Untertullnerbach",
    "sg:orig_category":"Autohandel",
    "sg:phone":"+43 4322 3166990",
    "sg:postcode":"3011",
    "sg:province":"Nieder\u00f6sterreich",
    "wof:name":"R. H. Automobile",
    "wof:placetype":"venue"
},
  "geometry": {"coordinates":[16.0999546051,48.2046432495],"type":"Point"}
}