{
  "type": "Feature",
  "properties": {
    "addr:full":"Linzer Str 15 Freistadt Ober\u00f6sterreich 4240",
    "addr:housenumber":"15",
    "addr:postcode":"4240",
    "addr:street":"Linzer Str",
    "iso:country":"AT",
    "sg:address":"Linzer Str 15",
    "sg:city":"Freistadt",
    "sg:orig_category":"\u00c3\u201erzte / F Allgemeinmedizin",
    "sg:phone":"+43 7942 72032",
    "sg:postcode":"4240",
    "sg:province":"Ober\u00f6sterreich",
    "wof:name":"Danhofer Ulrike Dr",
    "wof:placetype":"venue"
},
  "geometry": {"coordinates":[14.5029420853,48.5070800781],"type":"Point"}
}