{
  "type": "Feature",
  "properties": {
    "addr:full":"Hauptpl 17 Korneuburg Nieder\u00f6sterreich 2100",
    "addr:housenumber":"17",
    "addr:postcode":"2100",
    "addr:street":"Hauptpl;Niederoesterreich",
    "iso:country":"AT",
    "sg:address":"Hauptpl 17",
    "sg:city":"Korneuburg",
    "sg:orig_category":"Fotoapparate U -Artikel / Einzelhandel",
    "sg:phone":"+43 4322 6261555",
    "sg:postcode":"2100",
    "sg:province":"Nieder\u00f6sterreich",
    "wof:name":"Hartlauer HandelsgesmbH",
    "wof:placetype":"venue"
},
  "geometry": {"coordinates":[16.3339328766,48.3435058594],"type":"Point"}
}