{
  "type": "Feature",
  "properties": {
    "addr:full":"Robert-Stolz-G 42 Gro\u00df-Enzersdorf Nieder\u00f6sterreich 2301",
    "addr:housenumber":"42",
    "addr:postcode":"2301",
    "addr:street":"Robert-Stolz-G;Niederoesterreich",
    "iso:country":"AT",
    "sg:address":"Robert-Stolz-G 42",
    "sg:city":"Gro\u00df-Enzersdorf",
    "sg:orig_category":"Elektroinstallationsunternehmen",
    "sg:phone":"+43 2249 28321",
    "sg:postcode":"2301",
    "sg:province":"Nieder\u00f6sterreich",
    "wof:name":"ETA Harrer GesmbH",
    "wof:placetype":"venue"
},
  "geometry": {"coordinates":[16.5715274811,48.1960487366],"type":"Point"}
}