{
  "type": "Feature",
  "properties": {
    "addr:full":"Bahnhofstr 2 Stockerau Nieder\u00f6sterreich 2000",
    "addr:housenumber":"2",
    "addr:postcode":"2000",
    "addr:street":"Bahnhofstr",
    "iso:country":"AT",
    "sg:address":"Bahnhofstr 2",
    "sg:city":"Stockerau",
    "sg:classifiers":[
        {
            "category":"Restaurant",
            "type":"Food & Drink"
        }
    ],
    "sg:phone":"+43 2266 72310",
    "sg:postcode":"2000",
    "sg:province":"Nieder\u00f6sterreich",
    "sg:tags":[
        "pizzeria"
    ],
    "wof:name":"Pizzeria ma veloce",
    "wof:placetype":"venue"
},
  "geometry": {"coordinates":[16.2100982666,48.3847846985],"type":"Point"}
}