{
  "type": "Feature",
  "properties": {
    "addr:full":"Tavernstr 5 Wolfern Ober\u00f6sterreich 4493",
    "addr:housenumber":"5",
    "addr:postcode":"4493",
    "addr:street":"Tavernstr",
    "iso:country":"AT",
    "sg:address":"Tavernstr 5",
    "sg:city":"Wolfern",
    "sg:orig_category":"Unterhaltungselektronik / Einzelhandel",
    "sg:phone":"+43 7253 83330",
    "sg:postcode":"4493",
    "sg:province":"Ober\u00f6sterreich",
    "wof:name":"Ru\u00dfmann TV GesmbH",
    "wof:placetype":"venue"
},
  "geometry": {"coordinates":[14.372628212,48.082698822],"type":"Point"}
}