{
  "type": "Feature",
  "properties": {
    "addr:full":"M\u00e4lzerweg 5 Puntigam Steiermark 8055",
    "addr:housenumber":"5",
    "addr:postcode":"8055",
    "addr:street":"Maelzerweg",
    "iso:country":"AT",
    "sg:address":"M\u00e4lzerweg 5",
    "sg:city":"Puntigam",
    "sg:orig_category":"High-Temperature Resistant Rubber Products",
    "sg:phone":"+43 316 291001",
    "sg:postcode":"8055",
    "sg:province":"Steiermark",
    "sg:website":"ing-neugebauer.at",
    "wof:name":"Ing. Neugebauer GmbH Erzeugung techn. Gummi - und Kunststoffwaren",
    "wof:placetype":"venue"
},
  "geometry": {"coordinates":[15.4370822906,47.0253067017],"type":"Point"}
}