{
  "type": "Feature",
  "properties": {
    "iso:country":"AT",
    "sg:address":"Neunkirchner Str 90",
    "sg:city":"Wiener Neustadt",
    "sg:orig_category":"Autohandel",
    "sg:phone":"+43 4326 22235910",
    "sg:postcode":"2700",
    "sg:province":"Nieder\u00f6sterreich",
    "wof:name":"Porsche Inter Auto GmbH & Co KG - ZWNL Porsche Wiener Neustadt",
    "wof:placetype":"venue"
},
  "geometry": {"coordinates":[16.2249755859,47.7986297607],"type":"Point"}
}