{
  "type": "Feature",
  "properties": {
    "addr:full":"Rechte Glanzzeile 22 Salzburg Salzburg 5020",
    "addr:housenumber":"22",
    "addr:postcode":"5020",
    "addr:street":"Salzburg",
    "iso:country":"AT",
    "sg:address":"Rechte Glanzzeile 22",
    "sg:city":"Salzburg",
    "sg:classifiers":[
        {
            "category":"Autos & Motor Vehicles",
            "subcategory":"Automobile Sales",
            "type":"Retail Goods"
        }
    ],
    "sg:phone":"+43 4366 2430651",
    "sg:postcode":"5020",
    "sg:province":"Salzburg",
    "sg:tags":[
        "industrial"
    ],
    "wof:name":"P.O.S. TECHNIC-RECHENSYSTEME GES.MBH",
    "wof:placetype":"venue"
},
  "geometry": {"coordinates":[13.0272026062,47.8173141479],"type":"Point"}
}