{
  "type": "Feature",
  "properties": {
    "addr:full":"Salurner Str 42-44 Kufstein Tirol 6330",
    "addr:postcode":"42-44;6330",
    "addr:street":"Str;Tirol",
    "iso:country":"AT",
    "sg:address":"Salurner Str 42-44",
    "sg:city":"Kufstein",
    "sg:orig_category":"Lebensmittel / Einzelhandel",
    "sg:phone":"+43 5372 625760",
    "sg:postcode":"6330",
    "sg:province":"Tirol",
    "wof:name":"SuperM",
    "wof:placetype":"venue"
},
  "geometry": {"coordinates":[12.1573915482,47.5743522644],"type":"Point"}
}