{
  "type": "Feature",
  "properties": {
    "iso:country":"AT",
    "sg:address":"Brennaustr 10",
    "sg:city":"Krems an der Donau",
    "sg:orig_category":"Abfall-, Entsorgungs- U Deponietechnik",
    "sg:phone":"+43 4327 328890",
    "sg:postcode":"3500",
    "sg:province":"Nieder\u00f6sterreich",
    "sg:website":"brantner.com",
    "wof:name":"Baurestmassen - Zentrum GesmbH",
    "wof:placetype":"venue"
},
  "geometry": {"coordinates":[15.6518163681,48.4093551636],"type":"Point"}
}