{
  "type": "Feature",
  "properties": {
    "iso:country":"AT",
    "sg:address":"Landstrasse 15-17",
    "sg:city":"Zistersdorf",
    "sg:classifiers":[
        {
            "category":"Parking",
            "subcategory":"Garage",
            "type":"Transportation"
        }
    ],
    "sg:phone":"+43 2532 22570",
    "sg:postcode":"2225",
    "sg:province":"Nieder\u00f6sterreich",
    "sg:tags":[
        "agricultural",
        "trailer"
    ],
    "sg:website":"stetzl.at",
    "wof:name":"Stetzl & S\u00f6hne Ges.m.b.H.",
    "wof:placetype":"venue"
},
  "geometry": {"coordinates":[16.7661075592,48.5433654785],"type":"Point"}
}