{
  "type": "Feature",
  "properties": {
    "iso:country":"AT",
    "sg:address":"Kleindorf 59",
    "sg:city":"Flattach",
    "sg:orig_category":"Appartements / Ferienwohnungen",
    "sg:phone":"+43 4347 8520710",
    "sg:postcode":"9831",
    "sg:province":"K\u00e4rnten",
    "wof:name":"Appartementhaus Gugganig",
    "wof:placetype":"venue"
},
  "geometry": {"coordinates":[13.1141176224,46.9356651306],"type":"Point"}
}