{
  "type": "Feature",
  "properties": {
    "addr:full":"Lofer 23 Lofer Salzburg 5090",
    "addr:housenumber":"23",
    "addr:postcode":"5090",
    "addr:street":"Lofer;Salzburg",
    "iso:country":"AT",
    "sg:address":"Lofer 23",
    "sg:city":"Lofer",
    "sg:classifiers":[
        {
            "category":"Shopping",
            "subcategory":"Jewelry",
            "type":"Retail Goods"
        }
    ],
    "sg:phone":"+43 6588 8305",
    "sg:postcode":"5090",
    "sg:province":"Salzburg",
    "sg:tags":[
        "gemstone",
        "jewellery"
    ],
    "wof:name":"Kurt Gerathwohl",
    "wof:placetype":"venue"
},
  "geometry": {"coordinates":[12.6925487518,47.5864982605],"type":"Point"}
}