{
  "type": "Feature",
  "properties": {
    "iso:country":"AT",
    "sg:address":"Nr 105",
    "sg:city":"Edlitz",
    "sg:orig_category":"Banken U Sparkassen",
    "sg:phone":"+43 4326 4472620",
    "sg:postcode":"2842",
    "sg:province":"Nieder\u00f6sterreich",
    "wof:name":"Raiffeisenbank Aspang-Krumbach regGenmbH",
    "wof:placetype":"venue"
},
  "geometry": {"coordinates":[16.1426143646,47.5682220459],"type":"Point"}
}