{
  "type": "Feature",
  "properties": {
    "addr:full":"Schremser Str 4 Gm\u00fcnd Nieder\u00f6sterreich 3950",
    "addr:housenumber":"4",
    "addr:postcode":"3950",
    "addr:street":"Str;Niederoesterreich",
    "iso:country":"AT",
    "sg:address":"Schremser Str 4",
    "sg:city":"Gm\u00fcnd",
    "sg:orig_category":"Beratungsstellen",
    "sg:phone":"+43 2852 20435",
    "sg:postcode":"3950",
    "sg:province":"Nieder\u00f6sterreich",
    "wof:name":"Kinderschutzzentrum Waldviertel - Gm\u00fcnd",
    "wof:placetype":"venue"
},
  "geometry": {"coordinates":[14.985704422,48.7716331482],"type":"Point"}
}