{
  "type": "Feature",
  "properties": {
    "iso:country":"AT",
    "sg:address":"Margaretenhof 2/18",
    "sg:city":"Wien",
    "sg:orig_category":"Werbegrafik- U Grafik-Design",
    "sg:phone":"+43 4315 454757",
    "sg:postcode":"1050",
    "sg:province":"Wien",
    "wof:name":"Dunkl Corporate Design",
    "wof:placetype":"venue"
},
  "geometry": {"coordinates":[16.357208252,48.1916046143],"type":"Point"}
}