{
  "type": "Feature",
  "properties": {
    "iso:country":"AT",
    "sg:address":"Hinterkaiserweg 30",
    "sg:city":"St. Johann in Tirol",
    "sg:orig_category":"Holzhandel",
    "sg:phone":"+43 5352 64522",
    "sg:postcode":"6380",
    "sg:province":"Tirol",
    "wof:name":"Heim Georg",
    "wof:placetype":"venue"
},
  "geometry": {"coordinates":[12.4188022614,47.5286254883],"type":"Point"}
}