{
  "type": "Feature",
  "properties": {
    "addr:full":"Hinterkaiserweg 30 St. Johann in Tirol Tirol 6380",
    "addr:housenumber":"30",
    "addr:postcode":"6380",
    "addr:street":"Hinterkaiserweg;Tirol",
    "iso:country":"AT",
    "sg:address":"Hinterkaiserweg 30",
    "sg:city":"St. Johann in Tirol",
    "sg:orig_category":"Holzhandel",
    "sg:phone":"+43 5352 64522",
    "sg:postcode":"6380",
    "sg:province":"Tirol",
    "wof:name":"Heim Georg",
    "wof:placetype":"venue"
},
  "geometry": {"coordinates":[12.4188022614,47.5286254883],"type":"Point"}
}