{
  "type": "Feature",
  "properties": {
    "addr:full":"Salcherstr 76 St. P\u00f6lten-Harland Nieder\u00f6sterreich 3104",
    "addr:housenumber":"76",
    "addr:postcode":"3104",
    "addr:street":"Salcherstr",
    "iso:country":"AT",
    "sg:address":"Salcherstr 76",
    "sg:city":"St. P\u00f6lten-Harland",
    "sg:orig_category":"Bibliotheken",
    "sg:phone":"+43 2742 881664",
    "sg:postcode":"3104",
    "sg:province":"Nieder\u00f6sterreich",
    "wof:name":"Stadtb\u00fccherei Harland",
    "wof:placetype":"venue"
},
  "geometry": {"coordinates":[15.6388530731,48.1606216431],"type":"Point"}
}