{
  "type": "Feature",
  "properties": {
    "iso:country":"AT",
    "sg:address":"Hellbrunner Str 30",
    "sg:city":"Anif",
    "sg:orig_category":"Innenarchitekten",
    "sg:phone":"+43 6246 729750",
    "sg:postcode":"5081",
    "sg:province":"Salzburg",
    "wof:name":"Galerie Anif",
    "wof:placetype":"venue"
},
  "geometry": {"coordinates":[13.0649404526,47.7518692017],"type":"Point"}
}