{
  "type": "Feature",
  "properties": {
    "addr:full":"Cumberlandstr. 32-34 Wien Wien 1140",
    "addr:postcode":"32-34;1140",
    "iso:country":"AT",
    "sg:address":"Cumberlandstr. 32-34",
    "sg:city":"Wien",
    "sg:classifiers":[
        {
            "category":"Shopping",
            "subcategory":"Computers & Home Electronics",
            "type":"Retail Goods"
        }
    ],
    "sg:phone":"+43 4318 9990",
    "sg:postcode":"1140",
    "sg:province":"Wien",
    "sg:tags":[
        "electronic",
        "electrical",
        "equipment"
    ],
    "wof:name":"ELIN EBG TRACTION GMBH",
    "wof:placetype":"venue"
},
  "geometry": {"coordinates":[16.305229187,48.1920471191],"type":"Point"}
}