{
  "type": "Feature",
  "properties": {
    "addr:full":"Walfischg 3 Wien Wien 1010",
    "addr:housenumber":"3",
    "addr:postcode":"1010",
    "addr:street":"Walfischg",
    "iso:country":"AT",
    "sg:address":"Walfischg 3",
    "sg:city":"Wien",
    "sg:orig_category":"Ambulatorien",
    "sg:phone":"+43 1 5127926",
    "sg:postcode":"1010",
    "sg:province":"Wien",
    "sg:website":"allergie-wien1.at",
    "wof:name":"Allergie-Ambulatorium Innere Stadt",
    "wof:placetype":"venue"
},
  "geometry": {"coordinates":[16.3708076477,48.2036361694],"type":"Point"}
}