{
  "type": "Feature",
  "properties": {
    "addr:full":"Johann-Georg-Ulmer-Str 3 Dornbirn Vorarlberg 6850",
    "addr:housenumber":"3",
    "addr:postcode":"6850",
    "addr:street":"Johann-Georg-Ulmer-Str",
    "iso:country":"AT",
    "sg:address":"Johann-Georg-Ulmer-Str 3",
    "sg:city":"Dornbirn",
    "sg:orig_category":"Fitnesscenter",
    "sg:phone":"+43 4355 7234444",
    "sg:postcode":"6850",
    "sg:province":"Vorarlberg",
    "wof:name":"Magic Fit",
    "wof:placetype":"venue"
},
  "geometry": {"coordinates":[9.7399368286,47.4263076782],"type":"Point"}
}