{
  "type": "Feature",
  "properties": {
    "iso:country":"AT",
    "sg:address":"W\u00e4hringer Str 173-181",
    "sg:city":"Wien",
    "sg:orig_category":"Volksschulen",
    "sg:phone":"+43 1 4791176111",
    "sg:postcode":"1180",
    "sg:province":"Wien",
    "wof:name":"Schule der Stadt Wien",
    "wof:placetype":"venue"
},
  "geometry": {"coordinates":[16.331741333,48.2288169861],"type":"Point"}
}