{
  "type": "Feature",
  "properties": {
    "addr:full":"Mozartpl 7 Bad Gastein Salzburg 5640",
    "addr:housenumber":"7",
    "addr:postcode":"5640",
    "addr:street":"Mozartpl;Salzburg",
    "iso:country":"AT",
    "sg:address":"Mozartpl 7",
    "sg:city":"Bad Gastein",
    "sg:orig_category":"Trachtenbekleidung",
    "sg:phone":"+43 6434 2182",
    "sg:postcode":"5640",
    "sg:province":"Salzburg",
    "wof:name":"Trachten Gabriela",
    "wof:placetype":"venue"
},
  "geometry": {"coordinates":[13.1342859268,47.1191749573],"type":"Point"}
}