{
  "type": "Feature",
  "properties": {
    "iso:country":"AT",
    "sg:address":"Nr 9",
    "sg:city":"Aschbach Markt",
    "sg:orig_category":"Papier / Erzeugung U Gro\u00c3\u0178handel",
    "sg:phone":"+43 4374 7677677",
    "sg:postcode":"3361",
    "sg:province":"Nieder\u00f6sterreich",
    "wof:name":"RP Papier GesmbH",
    "wof:placetype":"venue"
},
  "geometry": {"coordinates":[14.7494697571,48.072845459],"type":"Point"}
}