{
  "type": "Feature",
  "properties": {
    "addr:full":"Am Gr\u00fcnberg 2 Bad Zell Ober\u00f6sterreich 4283",
    "addr:housenumber":"2",
    "addr:postcode":"4283",
    "addr:street":"Am Gruenberg",
    "iso:country":"AT",
    "sg:address":"Am Gr\u00fcnberg 2",
    "sg:city":"Bad Zell",
    "sg:orig_category":"Drechslereien",
    "sg:phone":"+43 7263 72520",
    "sg:postcode":"4283",
    "sg:province":"Ober\u00f6sterreich",
    "wof:name":"Lehner Markus",
    "wof:placetype":"venue"
},
  "geometry": {"coordinates":[14.6694526672,48.3498420715],"type":"Point"}
}