{
  "type": "Feature",
  "properties": {
    "addr:full":"Goldegg 1-3 Wien Wien 1040",
    "addr:housenumber":"1-3",
    "addr:postcode":"1040",
    "addr:street":"Goldegg",
    "iso:country":"AT",
    "sg:address":"Goldegg 1-3",
    "sg:city":"Wien",
    "sg:classifiers":[
        {
            "category":"Professional",
            "subcategory":"Management & Consulting",
            "type":"Services"
        }
    ],
    "sg:phone":"+43 664 2080283",
    "sg:postcode":"1040",
    "sg:province":"Wien",
    "wof:name":"Dorfmeister Informationsmanagement Beratung GmbH",
    "wof:placetype":"venue"
},
  "geometry": {"coordinates":[16.3797950745,48.1902008057],"type":"Point"}
}