{
  "type": "Feature",
  "properties": {
    "addr:full":"Wiesbauerstr 9 Salzburg Salzburg 5020",
    "addr:housenumber":"9",
    "addr:postcode":"5020",
    "addr:street":"Wiesbauerstr;Salzburg",
    "iso:country":"AT",
    "sg:address":"Wiesbauerstr 9",
    "sg:city":"Salzburg",
    "sg:orig_category":"Werbeagenturen",
    "sg:phone":"+43 662 833678",
    "sg:postcode":"5020",
    "sg:province":"Salzburg",
    "wof:name":"Media + Verlagsservice Lueger KEG",
    "wof:placetype":"venue"
},
  "geometry": {"coordinates":[13.0248212814,47.7994270325],"type":"Point"}
}