{
  "type": "Feature",
  "properties": {
    "addr:full":"Leopoldstr 39 Innsbruck Tirol 6020",
    "addr:housenumber":"39",
    "addr:postcode":"6020",
    "addr:street":"Leopoldstr;Tirol",
    "iso:country":"AT",
    "sg:address":"Leopoldstr 39",
    "sg:city":"Innsbruck",
    "sg:orig_category":"Immobilienmakler",
    "sg:phone":"+43 512 582396",
    "sg:postcode":"6020",
    "sg:province":"Tirol",
    "wof:name":"Fink R & Co OHG Alleininh Regina Pruckmayr",
    "wof:placetype":"venue"
},
  "geometry": {"coordinates":[11.3973045349,47.257686615],"type":"Point"}
}