{
  "type": "Feature",
  "properties": {
    "addr:full":"Lichtensteg 1 Wien Wien 1010",
    "addr:housenumber":"1",
    "addr:postcode":"1010",
    "addr:street":"Lichtensteg",
    "iso:country":"AT",
    "sg:address":"Lichtensteg 1",
    "sg:city":"Wien",
    "sg:orig_category":"Waren Aller Art",
    "sg:phone":"+43 4315 352886",
    "sg:postcode":"1010",
    "sg:province":"Wien",
    "wof:name":"Weltladen",
    "wof:placetype":"venue"
},
  "geometry": {"coordinates":[16.3738250732,48.2101249695],"type":"Point"}
}