{
  "type": "Feature",
  "properties": {
    "addr:full":"Nr 46 Elbigenalp Tirol 6652",
    "addr:postcode":"6652",
    "addr:street":"Nr;Elbigenalp Tirol",
    "iso:country":"AT",
    "sg:address":"Nr 46",
    "sg:city":"Elbigenalp",
    "sg:classifiers":[
        {
            "category":"Restaurant",
            "type":"Food & Drink"
        }
    ],
    "sg:phone":"+43 5634 619118",
    "sg:postcode":"6652",
    "sg:province":"Tirol",
    "sg:tags":[
        "pizzeria"
    ],
    "wof:name":"Pizzeria Lechpark",
    "wof:placetype":"venue"
},
  "geometry": {"coordinates":[10.4359750748,47.2906074524],"type":"Point"}
}