{
  "type": "Feature",
  "properties": {
    "iso:country":"AT",
    "sg:address":"Salitergasse 14",
    "sg:city":"Frauenkirchen",
    "sg:classifiers":[
        {
            "category":"Communications",
            "subcategory":"Film & Video Production",
            "type":"Services"
        }
    ],
    "sg:phone":"+43 2172 3514",
    "sg:postcode":"7132",
    "sg:province":"Burgenland",
    "sg:tags":[
        "images",
        "graphic",
        "creating"
    ],
    "sg:website":"stacs-media.com",
    "wof:name":"STACS MEDIA PLP Management Consulting & Education GmbH & Co KEG",
    "wof:placetype":"venue"
},
  "geometry": {"coordinates":[16.9236774445,47.8401603699],"type":"Point"}
}