{
  "type": "Feature",
  "properties": {
    "addr:full":"Kalvarienbergg 39 Wien Wien 1170",
    "addr:housenumber":"39",
    "addr:postcode":"1170",
    "addr:street":"Kalvarienbergg",
    "iso:country":"AT",
    "sg:address":"Kalvarienbergg 39",
    "sg:city":"Wien",
    "sg:orig_category":"Textilwaren / Einzelhandel",
    "sg:phone":"+43 1 4035988",
    "sg:postcode":"1170",
    "sg:province":"Wien",
    "wof:name":"MTM",
    "wof:placetype":"venue"
},
  "geometry": {"coordinates":[16.332649231,48.219619751],"type":"Point"}
}