{
  "type": "Feature",
  "properties": {
    "addr:full":"Schwarzstr 30 Salzburg Salzburg 5020",
    "addr:housenumber":"30",
    "addr:postcode":"5020",
    "addr:street":"Schwarzstr;Salzburg",
    "iso:country":"AT",
    "sg:address":"Schwarzstr 30",
    "sg:city":"Salzburg",
    "sg:orig_category":"Banken U Sparkassen",
    "sg:phone":"+43 4366 28491710",
    "sg:postcode":"5020",
    "sg:province":"Salzburg",
    "wof:name":"Deutsche Bank AG",
    "wof:placetype":"venue"
},
  "geometry": {"coordinates":[13.0407571793,47.804107666],"type":"Point"}
}