{
  "type": "Feature",
  "properties": {
    "iso:country":"AT",
    "sg:address":"Spielbergstr 27",
    "sg:city":"Fieberbrunn",
    "sg:orig_category":"Steuerberatung",
    "sg:phone":"+43 664 4048488",
    "sg:postcode":"6391",
    "sg:province":"Tirol",
    "wof:name":"Schroll Florian Mag",
    "wof:placetype":"venue"
},
  "geometry": {"coordinates":[12.5462417603,47.4759597778],"type":"Point"}
}