{
  "type": "Feature",
  "properties": {
    "addr:full":"Dr.-Franz-Rehrl-Str 3 Zell am See Salzburg 5700",
    "addr:housenumber":"3",
    "addr:postcode":"5700",
    "addr:street":"Dr.-Franz-Rehrl-Str;Salzburg",
    "iso:country":"AT",
    "sg:address":"Dr.-Franz-Rehrl-Str 3",
    "sg:city":"Zell am See",
    "sg:orig_category":"Eisenwaren",
    "sg:phone":"+43 6542 724920",
    "sg:postcode":"5700",
    "sg:province":"Salzburg",
    "wof:name":"Rainer Otto",
    "wof:placetype":"venue"
},
  "geometry": {"coordinates":[12.7965984344,47.3214378357],"type":"Point"}
}