{
  "type": "Feature",
  "properties": {
    "addr:full":"Nr 41 Birkfeld Steiermark 8190",
    "addr:postcode":"8190",
    "addr:street":"Nr 41",
    "iso:country":"AT",
    "sg:address":"Nr 41",
    "sg:city":"Birkfeld",
    "sg:classifiers":[
        {
            "category":"Professional",
            "subcategory":"Computer Services",
            "type":"Services"
        }
    ],
    "sg:phone":"+43 3174 2060",
    "sg:postcode":"8190",
    "sg:province":"Steiermark",
    "sg:tags":[
        "software"
    ],
    "wof:name":"Real Time Concepts",
    "wof:placetype":"venue"
},
  "geometry": {"coordinates":[15.7014284134,47.3529853821],"type":"Point"}
}