{
  "type": "Feature",
  "properties": {
    "iso:country":"AT",
    "sg:address":"Hofkirchnerg 10",
    "sg:city":"Klosterneuburg",
    "sg:orig_category":"Bastelbedarf",
    "sg:phone":"+43 4322 4336548",
    "sg:postcode":"3400",
    "sg:province":"Nieder\u00f6sterreich",
    "wof:name":"Hobby-Kaiser",
    "wof:placetype":"venue"
},
  "geometry": {"coordinates":[16.3226222992,48.3078308105],"type":"Point"}
}