{
  "type": "Feature",
  "properties": {
    "addr:full":"Reitlweg 24 Elixhausen Salzburg 5161",
    "addr:housenumber":"24",
    "addr:postcode":"5161",
    "addr:street":"Reitlweg;Salzburg",
    "iso:country":"AT",
    "sg:address":"Reitlweg 24",
    "sg:city":"Elixhausen",
    "sg:orig_category":"\u00c3\u201erzte / F Allgemeinmedizin",
    "sg:phone":"+43 662 480468",
    "sg:postcode":"5161",
    "sg:province":"Salzburg",
    "wof:name":"Kirchlechner-Floretta Marion Dr",
    "wof:placetype":"venue"
},
  "geometry": {"coordinates":[13.0614318848,47.8635597229],"type":"Point"}
}