{
  "type": "Feature",
  "properties": {
    "iso:country":"AT",
    "sg:address":"Weizer Str 40C",
    "sg:city":"Gleisdorf",
    "sg:orig_category":"Non-Classified Establishments",
    "sg:phone":"+43 4331 1250065",
    "sg:postcode":"8200",
    "sg:province":"Steiermark",
    "wof:name":"L&M TOR-CENTER, T\u00dcREN-STUDIO",
    "wof:placetype":"venue"
},
  "geometry": {"coordinates":[15.7050237656,47.1111183167],"type":"Point"}
}