{
  "type": "Feature",
  "properties": {
    "iso:country":"AT",
    "sg:address":"Ischler Str 8",
    "sg:city":"Ebensee",
    "sg:orig_category":"Transportunternehmen",
    "sg:phone":"+43 6133 53440",
    "sg:postcode":"4802",
    "sg:province":"Ober\u00f6sterreich",
    "wof:name":"Neub\u00f6ck Alexander KG",
    "wof:placetype":"venue"
},
  "geometry": {"coordinates":[13.7685461044,47.8094902039],"type":"Point"}
}