{
  "type": "Feature",
  "properties": {
    "addr:full":"Aug 14 Ternitz Nieder\u00f6sterreich 2630",
    "addr:housenumber":"14",
    "addr:postcode":"2630",
    "addr:street":"Aug",
    "iso:country":"AT",
    "sg:address":"Aug 14",
    "sg:city":"Ternitz",
    "sg:classifiers":[
        {
            "category":"Taxi",
            "type":"Transportation"
        }
    ],
    "sg:phone":"+43 664 4537677",
    "sg:postcode":"2630",
    "sg:province":"Nieder\u00f6sterreich",
    "sg:tags":[
        "personentransporte",
        "u"
    ],
    "wof:name":"Taxi-Botendienst Bj\u00f6rkhagen",
    "wof:placetype":"venue"
},
  "geometry": {"coordinates":[16.0209465027,47.7058067322],"type":"Point"}
}