{
  "type": "Feature",
  "properties": {
    "iso:country":"AT",
    "sg:address":"Nr 44",
    "sg:city":"Feldbach",
    "sg:orig_category":"Autohandel",
    "sg:phone":"+43 3152 77000",
    "sg:postcode":"8330",
    "sg:province":"Steiermark",
    "wof:name":"Strassnitzky Th Autohaus GmbH",
    "wof:placetype":"venue"
},
  "geometry": {"coordinates":[15.9065151215,46.9382896423],"type":"Point"}
}