{
  "type": "Feature",
  "properties": {
    "iso:country":"AT",
    "sg:address":"Oberdorf 4",
    "sg:city":"Bizau",
    "sg:orig_category":"Transportunternehmen",
    "sg:phone":"+43 5514 2132",
    "sg:postcode":"6874",
    "sg:province":"Vorarlberg",
    "sg:website":"bischofberger.at",
    "wof:name":"Bischofberger Transporte GesmbH & Co KG",
    "wof:placetype":"venue"
},
  "geometry": {"coordinates":[9.9334011078,47.3651924133],"type":"Point"}
}