{
  "type": "Feature",
  "properties": {
    "iso:country":"AT",
    "sg:address":"Hannesgrub 5",
    "sg:city":"Ried im Innkreis",
    "sg:orig_category":"Autoersatzteile",
    "sg:phone":"+43 7752 846050",
    "sg:postcode":"4910",
    "sg:province":"Ober\u00f6sterreich",
    "wof:name":"Forstinger Handel und Service GmbH",
    "wof:placetype":"venue"
},
  "geometry": {"coordinates":[13.4946289062,48.2175483704],"type":"Point"}
}