{
  "type": "Feature",
  "properties": {
    "addr:full":"Hauptstrasse 40 St. Stefan im Lavanttal K\u00e4rnten 9431",
    "addr:housenumber":"40",
    "addr:postcode":"9431",
    "addr:street":"Hauptstrasse",
    "iso:country":"AT",
    "sg:address":"Hauptstrasse 40",
    "sg:city":"St. Stefan im Lavanttal",
    "sg:classifiers":[
        {
            "category":"Organizations",
            "subcategory":"Labor Organization",
            "type":"Services"
        }
    ],
    "sg:phone":"+43 4352 36536",
    "sg:postcode":"9431",
    "sg:province":"K\u00e4rnten",
    "sg:tags":[
        "personnel",
        "providing"
    ],
    "sg:website":"fug.at",
    "wof:name":"F&G Anlagenbau u. Personalbereitstellung Ing. Reinhold Fellner",
    "wof:placetype":"venue"
},
  "geometry": {"coordinates":[14.8493328094,46.8059158325],"type":"Point"}
}