{
  "type": "Feature",
  "properties": {
    "addr:full":"Dultstr 22 Gratkorn Steiermark 8101",
    "addr:housenumber":"22",
    "addr:postcode":"8101",
    "addr:street":"Dultstr",
    "iso:country":"AT",
    "sg:address":"Dultstr 22",
    "sg:city":"Gratkorn",
    "sg:orig_category":"Schneidereien",
    "sg:phone":"+43 4331 2422481",
    "sg:postcode":"8101",
    "sg:province":"Steiermark",
    "wof:name":"Fink Hubert",
    "wof:placetype":"venue"
},
  "geometry": {"coordinates":[15.3578643799,47.1263542175],"type":"Point"}
}