{
  "type": "Feature",
  "properties": {
    "addr:full":"Klosterwiesg 32 Graz Steiermark 8010",
    "addr:housenumber":"32",
    "addr:postcode":"8010",
    "addr:street":"Klosterwiesg",
    "iso:country":"AT",
    "sg:address":"Klosterwiesg 32",
    "sg:city":"Graz",
    "sg:orig_category":"Lebensmittel / Einzelhandel",
    "sg:phone":"+43 316 829687",
    "sg:postcode":"8010",
    "sg:province":"Steiermark",
    "wof:name":"A & O Nahversorgung - pro mente Steiermark",
    "wof:placetype":"venue"
},
  "geometry": {"coordinates":[15.4448051453,47.0646247864],"type":"Point"}
}