{
  "type": "Feature",
  "properties": {
    "addr:full":"Hauptpl 13 Mureck Steiermark 8480",
    "addr:housenumber":"13",
    "addr:postcode":"8480",
    "addr:street":"Hauptpl",
    "iso:country":"AT",
    "sg:address":"Hauptpl 13",
    "sg:city":"Mureck",
    "sg:orig_category":"Waren Aller Art",
    "sg:phone":"+43 3472 3694",
    "sg:postcode":"8480",
    "sg:province":"Steiermark",
    "wof:name":"Quelle Shop - Sommer Sabine",
    "wof:placetype":"venue"
},
  "geometry": {"coordinates":[15.7730207443,46.7075881958],"type":"Point"}
}