{
  "type": "Feature",
  "properties": {
    "iso:country":"AT",
    "sg:address":"Hagenstr 3",
    "sg:city":"Klagenfurt",
    "sg:orig_category":"Lebensmittel / Erzeugung U Gro\u00c3\u0178handel",
    "sg:phone":"+43 463 463620",
    "sg:postcode":"9020",
    "sg:province":"K\u00e4rnten",
    "wof:name":"Classico-Agrochem HandelsgesmbH",
    "wof:placetype":"venue"
},
  "geometry": {"coordinates":[14.3253698349,46.6329536438],"type":"Point"}
}