{
  "type": "Feature",
  "properties": {
    "addr:full":"Nr 35 Schwarzenberg am B\u00f6hmerwald Ober\u00f6sterreich 4164",
    "addr:postcode":"4164",
    "addr:street":"Nr 35",
    "iso:country":"AT",
    "sg:address":"Nr 35",
    "sg:city":"Schwarzenberg am B\u00f6hmerwald",
    "sg:orig_category":"Webereien U Spinnereien",
    "sg:phone":"+43 7280 298",
    "sg:postcode":"4164",
    "sg:province":"Ober\u00f6sterreich",
    "wof:name":"Hoheneder Alois",
    "wof:placetype":"venue"
},
  "geometry": {"coordinates":[8.3865814209,48.600189209],"type":"Point"}
}