{
  "type": "Feature",
  "properties": {
    "addr:full":"Dorfstr 50A Rattenberg Tirol 6240",
    "addr:housenumber":"50a",
    "addr:postcode":"6240",
    "addr:street":"Dorfstr",
    "iso:country":"AT",
    "sg:address":"Dorfstr 50A",
    "sg:city":"Rattenberg",
    "sg:classifiers":[
        {
            "category":"Shopping",
            "subcategory":"Thrift Store",
            "type":"Retail Goods"
        }
    ],
    "sg:phone":"+43 5337 64233",
    "sg:postcode":"6240",
    "sg:province":"Tirol",
    "sg:tags":[
        "second-hand-shops"
    ],
    "wof:name":"M\u00fchlegger Sonja",
    "wof:placetype":"venue"
},
  "geometry": {"coordinates":[11.9041719437,47.4463653564],"type":"Point"}
}