{
  "type": "Feature",
  "properties": {
    "addr:full":"Residenzpl 3 Salzburg Salzburg 5020",
    "addr:housenumber":"3",
    "addr:postcode":"5020",
    "addr:street":"Residenzpl;Salzburg",
    "iso:country":"AT",
    "sg:address":"Residenzpl 3",
    "sg:city":"Salzburg",
    "sg:orig_category":"Gerbereien",
    "sg:phone":"+43 4366 2842610",
    "sg:postcode":"5020",
    "sg:province":"Salzburg",
    "wof:name":"Jahn - Markl",
    "wof:placetype":"venue"
},
  "geometry": {"coordinates":[13.0457429886,47.7989311218],"type":"Point"}
}