{
  "type": "Feature",
  "properties": {
    "iso:country":"AT",
    "sg:address":"Stubenring 14",
    "sg:city":"Wien",
    "sg:orig_category":"Immobilienverwaltungen",
    "sg:phone":"+43 1 5124379",
    "sg:postcode":"1010",
    "sg:province":"Wien",
    "wof:name":"Weber Erich KG",
    "wof:placetype":"venue"
},
  "geometry": {"coordinates":[16.381729126,48.2088508606],"type":"Point"}
}