{
  "type": "Feature",
  "properties": {
    "addr:full":"Bachgasse 7 Horitschon Burgenland 7312",
    "addr:housenumber":"7",
    "addr:postcode":"7312",
    "addr:street":"Bachgasse",
    "iso:country":"AT",
    "sg:address":"Bachgasse 7",
    "sg:city":"Horitschon",
    "sg:classifiers":[
        {
            "category":"Home & Garden",
            "subcategory":"Household Appliances",
            "type":"Retail Goods"
        }
    ],
    "sg:phone":"+43 2610 42039",
    "sg:postcode":"7312",
    "sg:province":"Burgenland",
    "sg:tags":[
        "electric"
    ],
    "wof:name":"Helmut Wessely",
    "wof:placetype":"venue"
},
  "geometry": {"coordinates":[16.5462875366,47.5861816406],"type":"Point"}
}