{
  "type": "Feature",
  "properties": {
    "iso:country":"AT",
    "sg:address":"Dorfstr 39",
    "sg:city":"Waidring",
    "sg:orig_category":"Spirituosen / Erzeugung U Gro\u00c3\u0178handel",
    "sg:phone":"+43 4353 535235",
    "sg:postcode":"6384",
    "sg:province":"Tirol",
    "wof:name":"Brandtner Georg",
    "wof:placetype":"venue"
},
  "geometry": {"coordinates":[12.5584354401,47.587928772],"type":"Point"}
}