{
  "type": "Feature",
  "properties": {
    "addr:full":"Speckbacherstr 10 St. Johann in Tirol Tirol 6380",
    "addr:housenumber":"10",
    "addr:postcode":"6380",
    "addr:street":"Speckbacherstr;Tirol",
    "iso:country":"AT",
    "sg:address":"Speckbacherstr 10",
    "sg:city":"St. Johann in Tirol",
    "sg:orig_category":"Lebensmittel / Einzelhandel",
    "sg:phone":"+43 5352 66944",
    "sg:postcode":"6380",
    "sg:province":"Tirol",
    "wof:name":"SPAR \u00f6sterreichische Warenhandels-AG",
    "wof:placetype":"venue"
},
  "geometry": {"coordinates":[12.4267063141,47.5212478638],"type":"Point"}
}