{
  "type": "Feature",
  "properties": {
    "addr:full":"Grazer Str 311/5 Deutschfeistritz Steiermark 8121",
    "addr:housenumber":"311 / 5",
    "addr:postcode":"8121",
    "iso:country":"AT",
    "sg:address":"Grazer Str 311/5",
    "sg:city":"Deutschfeistritz",
    "sg:orig_category":"Gesundheit / Allgemeine Informationsstellen",
    "sg:phone":"+43 3127 41228",
    "sg:postcode":"8121",
    "sg:province":"Steiermark",
    "wof:name":"Maria's GEMP-Training Gesundheits-Energie-Mental-Pers\u00f6nlichkeitstraining",
    "wof:placetype":"venue"
},
  "geometry": {"coordinates":[15.3356399536,47.1943855286],"type":"Point"}
}