{
  "type": "Feature",
  "properties": {
    "iso:country":"AT",
    "sg:address":"Dammstrasse 39",
    "sg:city":"Wien",
    "sg:classifiers":[
        {
            "category":"Professional",
            "subcategory":"Advertising",
            "type":"Services"
        }
    ],
    "sg:phone":"+43 1 3307533",
    "sg:postcode":"1200",
    "sg:province":"Wien",
    "sg:tags":[
        "gingerbread",
        "made",
        "item"
    ],
    "sg:website":"wiener-lebkuchen.at",
    "wof:name":"Karl Kammerer KG",
    "wof:placetype":"venue"
},
  "geometry": {"coordinates":[16.3741569519,48.2346572876],"type":"Point"}
}