{
  "type": "Feature",
  "properties": {
    "addr:full":"Auweg 10 Ansfelden Ober\u00f6sterreich 4052",
    "addr:housenumber":"10",
    "addr:postcode":"4052",
    "addr:street":"Auweg",
    "iso:country":"AT",
    "sg:address":"Auweg 10",
    "sg:city":"Ansfelden",
    "sg:orig_category":"Damenmoden",
    "sg:phone":"+43 7229 78409",
    "sg:postcode":"4052",
    "sg:province":"Ober\u00f6sterreich",
    "wof:name":"Charles V\u00f6gele (Austria) AG",
    "wof:placetype":"venue"
},
  "geometry": {"coordinates":[14.2756471634,48.2154388428],"type":"Point"}
}