{
  "type": "Feature",
  "properties": {
    "addr:full":"Stadtpl 58 Mattighofen Ober\u00f6sterreich 5230",
    "addr:housenumber":"58",
    "addr:postcode":"5230",
    "addr:street":"Stadtpl",
    "iso:country":"AT",
    "sg:address":"Stadtpl 58",
    "sg:city":"Mattighofen",
    "sg:orig_category":"Massagen",
    "sg:phone":"+43 7742 3638",
    "sg:postcode":"5230",
    "sg:province":"Ober\u00f6sterreich",
    "wof:name":"Massage-Fachinstitut - G\u00fcnter Neubacher",
    "wof:placetype":"venue"
},
  "geometry": {"coordinates":[13.1502857208,48.1026115417],"type":"Point"}
}