{
  "type": "Feature",
  "properties": {
    "iso:country":"AT",
    "sg:address":"Patrizig 12",
    "sg:city":"Wien",
    "sg:orig_category":"Graveure, Textildruckereien",
    "sg:phone":"+43 1 2785109",
    "sg:postcode":"1210",
    "sg:province":"Wien",
    "sg:website":"pr-direkt.at",
    "wof:name":"PR-Direkt",
    "wof:placetype":"venue"
},
  "geometry": {"coordinates":[16.4066619873,48.2558860779],"type":"Point"}
}