{
  "type": "Feature",
  "properties": {
    "iso:country":"AT",
    "sg:address":"Herbststr 45",
    "sg:city":"Wien",
    "sg:classifiers":[
        {
            "category":"Restaurant",
            "type":"Food & Drink"
        }
    ],
    "sg:phone":"+43 1 4959232",
    "sg:postcode":"1160",
    "sg:province":"Wien",
    "wof:name":"9er Eck",
    "wof:placetype":"venue"
},
  "geometry": {"coordinates":[16.3274745941,48.2061653137],"type":"Point"}
}