{
  "type": "Feature",
  "properties": {
    "addr:full":"Gusentalstr 23 St. Georgen an der Gusen Ober\u00f6sterreich 4222",
    "addr:housenumber":"23",
    "addr:postcode":"4222",
    "addr:street":"Gusentalstr",
    "iso:country":"AT",
    "sg:address":"Gusentalstr 23",
    "sg:city":"St. Georgen an der Gusen",
    "sg:orig_category":"Chemikalien",
    "sg:phone":"+43 4366 42006387",
    "sg:postcode":"4222",
    "sg:province":"Ober\u00f6sterreich",
    "wof:name":"Angermayer Wolfgang",
    "wof:placetype":"venue"
},
  "geometry": {"coordinates":[14.4485216141,48.2763061523],"type":"Point"}
}