{
  "type": "Feature",
  "properties": {
    "addr:full":"Marxerg 21 Wien Wien 1030",
    "addr:housenumber":"21",
    "addr:postcode":"1030",
    "addr:street":"Marxerg",
    "iso:country":"AT",
    "sg:address":"Marxerg 21",
    "sg:city":"Wien",
    "sg:orig_category":"Psychotherapie",
    "sg:phone":"+43 4313 156879",
    "sg:postcode":"1030",
    "sg:province":"Wien",
    "wof:name":"Pepelnik-Gr\u00fcndler Hedwig Mag",
    "wof:placetype":"venue"
},
  "geometry": {"coordinates":[16.3920650482,48.2063865662],"type":"Point"}
}