{
  "type": "Feature",
  "properties": {
    "addr:full":"Dahlienstr 3 Allhaming Ober\u00f6sterreich 4511",
    "addr:housenumber":"3",
    "addr:postcode":"4511",
    "addr:street":"Dahlienstr",
    "iso:country":"AT",
    "sg:address":"Dahlienstr 3",
    "sg:city":"Allhaming",
    "sg:classifiers":[
        {
            "category":"Recreation",
            "subcategory":"Theme Park",
            "type":"Entertainment"
        }
    ],
    "sg:phone":"+43 7227 20869",
    "sg:postcode":"4511",
    "sg:province":"Ober\u00f6sterreich",
    "sg:tags":[
        "stahl"
    ],
    "wof:name":"Betonstahlservice Meinhart Sorg",
    "wof:placetype":"venue"
},
  "geometry": {"coordinates":[14.1732034683,48.1544723511],"type":"Point"}
}