{
  "type": "Feature",
  "properties": {
    "addr:full":"Pernsteinerweg 1 Micheldorf in Ober\u00f6sterreich Ober\u00f6sterreich 4563",
    "addr:housenumber":"1",
    "addr:postcode":"4563",
    "addr:street":"Pernsteinerweg",
    "iso:country":"AT",
    "sg:address":"Pernsteinerweg 1",
    "sg:city":"Micheldorf in Ober\u00f6sterreich",
    "sg:orig_category":"Erdarbeiten",
    "sg:phone":"+43 664 3362118",
    "sg:postcode":"4563",
    "sg:province":"Ober\u00f6sterreich",
    "wof:name":"Burgholzer Andreas",
    "wof:placetype":"venue"
},
  "geometry": {"coordinates":[14.1356201172,47.8800735474],"type":"Point"}
}