{
  "type": "Feature",
  "properties": {
    "iso:country":"AT",
    "sg:address":"Maxglaner Hauptstr 1b",
    "sg:city":"Salzburg",
    "sg:orig_category":"Boutiquen",
    "sg:phone":"+43 662 834463",
    "sg:postcode":"5020",
    "sg:province":"Salzburg",
    "wof:name":"Gr\u00fcnauer Ingrid",
    "wof:placetype":"venue"
},
  "geometry": {"coordinates":[13.0264968872,47.7961807251],"type":"Point"}
}