{
  "type": "Feature",
  "properties": {
    "addr:full":"Winterthurerstr 5a Hall in Tirol Tirol 6060",
    "addr:housenumber":"5a",
    "addr:postcode":"6060",
    "addr:street":"Winterthurerstr;Tirol",
    "iso:country":"AT",
    "sg:address":"Winterthurerstr 5a",
    "sg:city":"Hall in Tirol",
    "sg:orig_category":"Maler, Anstreicher U Lackierer",
    "sg:phone":"+43 4352 2342110",
    "sg:postcode":"6060",
    "sg:province":"Tirol",
    "wof:name":"Ghetta Wolfgang",
    "wof:placetype":"venue"
},
  "geometry": {"coordinates":[11.4990148544,47.2794113159],"type":"Point"}
}