{
  "type": "Feature",
  "properties": {
    "addr:full":"Dr Oertel-G 2 Wiener Neustadt Nieder\u00f6sterreich 2700",
    "addr:housenumber":"2",
    "addr:postcode":"2700",
    "iso:country":"AT",
    "sg:address":"Dr Oertel-G 2",
    "sg:city":"Wiener Neustadt",
    "sg:orig_category":"Maler, Anstreicher U Lackierer, Schilder- U Schriftenmaler",
    "sg:phone":"+43 4326 2228211",
    "sg:postcode":"2700",
    "sg:province":"Nieder\u00f6sterreich",
    "sg:website":"malerkrumschmid.at",
    "wof:name":"Krumschmid Josef",
    "wof:placetype":"venue"
},
  "geometry": {"coordinates":[16.2355499268,47.8452186584],"type":"Point"}
}