{
  "type": "Feature",
  "properties": {
    "iso:country":"AT",
    "sg:address":"Walter-Eder-Str 2",
    "sg:city":"Neidling",
    "sg:orig_category":"\u00c3\u201erzte / F Allgemeinmedizin",
    "sg:phone":"+43 2741 86720",
    "sg:postcode":"3110",
    "sg:province":"Nieder\u00f6sterreich",
    "wof:name":"Schultes Gernot Dr",
    "wof:placetype":"venue"
},
  "geometry": {"coordinates":[15.5568723679,48.2376899719],"type":"Point"}
}