{
  "type": "Feature",
  "properties": {
    "iso:country":"AT",
    "sg:address":"Hainburger Str 22",
    "sg:city":"Fischamend",
    "sg:orig_category":"Psychologen",
    "sg:phone":"+43 4322 3277425",
    "sg:postcode":"2401",
    "sg:province":"Nieder\u00f6sterreich",
    "wof:name":"Siegl Ursula Mag",
    "wof:placetype":"venue"
},
  "geometry": {"coordinates":[16.6169147491,48.1188468933],"type":"Point"}
}