{
  "type": "Feature",
  "properties": {
    "addr:full":"Josef Jessernig-Str 3 Stockerau Nieder\u00f6sterreich 2000",
    "addr:housenumber":"3",
    "addr:postcode":"2000",
    "addr:street":"Jessernig-Str",
    "iso:country":"AT",
    "sg:address":"Josef Jessernig-Str 3",
    "sg:city":"Stockerau",
    "sg:orig_category":"Transportunternehmen",
    "sg:phone":"+43 2266 634430",
    "sg:postcode":"2000",
    "sg:province":"Nieder\u00f6sterreich",
    "wof:name":"Groiss Transport und HandelsgesmbH",
    "wof:placetype":"venue"
},
  "geometry": {"coordinates":[16.2310676575,48.3877487183],"type":"Point"}
}