{
  "type": "Feature",
  "properties": {
    "iso:country":"AT",
    "sg:address":"Harland 6",
    "sg:city":"Persenbeug",
    "sg:orig_category":"Pensionen / Privatzimmer",
    "sg:phone":"+43 7412 55484",
    "sg:postcode":"3680",
    "sg:province":"Nieder\u00f6sterreich",
    "wof:name":"Fr\u00fchst\u00fcckspension Rosa Porranzl",
    "wof:placetype":"venue"
},
  "geometry": {"coordinates":[15.0676450729,48.2106742859],"type":"Point"}
}