{
  "type": "Feature",
  "properties": {
    "addr:full":"Hauptpl 1 Traun Ober\u00f6sterreich 4050",
    "addr:housenumber":"1",
    "addr:postcode":"4050",
    "addr:street":"Hauptpl",
    "iso:country":"AT",
    "sg:address":"Hauptpl 1",
    "sg:city":"Traun",
    "sg:orig_category":"Gemeinden",
    "sg:phone":"+43 7229 6880",
    "sg:postcode":"4050",
    "sg:province":"Ober\u00f6sterreich",
    "wof:name":"Stadtgemeinde Traun",
    "wof:placetype":"venue"
},
  "geometry": {"coordinates":[14.2374353409,48.2209091187],"type":"Point"}
}