{
  "type": "Feature",
  "properties": {
    "addr:full":"Agramsg 8a Hall in Tirol Tirol 6060",
    "addr:housenumber":"8a",
    "addr:postcode":"6060",
    "addr:street":"Agramsg;Tirol",
    "iso:country":"AT",
    "sg:address":"Agramsg 8a",
    "sg:city":"Hall in Tirol",
    "sg:orig_category":"Damenmoden",
    "sg:phone":"+43 5223 54922",
    "sg:postcode":"6060",
    "sg:province":"Tirol",
    "wof:name":"In-Shop",
    "wof:placetype":"venue"
},
  "geometry": {"coordinates":[11.5087842941,47.2824668884],"type":"Point"}
}