{
  "type": "Feature",
  "properties": {
    "iso:country":"AT",
    "sg:address":"Wiener G 45",
    "sg:city":"Perchtoldsdorf",
    "sg:orig_category":"\u00c3\u201enderungsschneidereien",
    "sg:phone":"+43 1 8656225",
    "sg:postcode":"2380",
    "sg:province":"Nieder\u00f6sterreich",
    "wof:name":"Lillys \u00e4nderungssalon",
    "wof:placetype":"venue"
},
  "geometry": {"coordinates":[16.2690906525,48.1231117249],"type":"Point"}
}