{
  "type": "Feature",
  "properties": {
    "iso:country":"AT",
    "sg:address":"Aichholzg 27",
    "sg:city":"Wien",
    "sg:orig_category":"Filmproduktionen",
    "sg:phone":"+43 1 8104994",
    "sg:postcode":"1120",
    "sg:province":"Wien",
    "wof:name":"K\u00f6hler Walter Filmproduktionen",
    "wof:placetype":"venue"
},
  "geometry": {"coordinates":[16.3244304657,48.1797866821],"type":"Point"}
}