{
  "type": "Feature",
  "properties": {
    "addr:full":"Hintenburg 47a Sillian Tirol 9920",
    "addr:housenumber":"47a",
    "addr:postcode":"9920",
    "addr:street":"Hintenburg;Tirol",
    "iso:country":"AT",
    "sg:address":"Hintenburg 47a",
    "sg:city":"Sillian",
    "sg:orig_category":"Tischlereien",
    "sg:phone":"+43 4846 6712",
    "sg:postcode":"9920",
    "sg:province":"Tirol",
    "wof:name":"Mayr Josef",
    "wof:placetype":"venue"
},
  "geometry": {"coordinates":[12.4941663742,46.7597961426],"type":"Point"}
}