{
  "type": "Feature",
  "properties": {
    "addr:full":"Jacquing 16-18 Wien Wien 1030",
    "addr:postcode":"16-18;1030",
    "iso:country":"AT",
    "sg:address":"Jacquing 16-18",
    "sg:city":"Wien",
    "sg:orig_category":"Bausparkassen",
    "sg:phone":"+43 1 797420",
    "sg:postcode":"1030",
    "sg:province":"Wien",
    "wof:name":"LBA LandesBausparkasse AG",
    "wof:placetype":"venue"
},
  "geometry": {"coordinates":[16.3841381073,48.1891059875],"type":"Point"}
}