{
  "type": "Feature",
  "properties": {
    "addr:full":"Merang 41 Graz Steiermark 8010",
    "addr:housenumber":"41",
    "addr:postcode":"8010",
    "addr:street":"Merang",
    "iso:country":"AT",
    "sg:address":"Merang 41",
    "sg:city":"Graz",
    "sg:classifiers":[
        {
            "category":"Military Area",
            "subcategory":"Army Base",
            "type":"Public Place"
        }
    ],
    "sg:phone":"+43 4367 63037556",
    "sg:postcode":"8010",
    "sg:province":"Steiermark",
    "sg:tags":[
        "shiatsu"
    ],
    "wof:name":"Tisch - Merkus Daniela - SHIATSU",
    "wof:placetype":"venue"
},
  "geometry": {"coordinates":[15.4553918839,47.0727081299],"type":"Point"}
}