{
  "type": "Feature",
  "properties": {
    "addr:full":"Hochstr 35 Lieboch Steiermark 8501",
    "addr:housenumber":"35",
    "addr:postcode":"8501",
    "addr:street":"Hochstr",
    "iso:country":"AT",
    "sg:address":"Hochstr 35",
    "sg:city":"Lieboch",
    "sg:orig_category":"Transportunternehmen",
    "sg:phone":"+43 3136 61213",
    "sg:postcode":"8501",
    "sg:province":"Steiermark",
    "wof:name":"Strommer Wilhelmine",
    "wof:placetype":"venue"
},
  "geometry": {"coordinates":[15.324133873,46.981628418],"type":"Point"}
}