{
  "type": "Feature",
  "properties": {
    "addr:full":"Hirnsdorf 107 Hirnsdorf Steiermark 8221",
    "addr:housenumber":"107",
    "addr:postcode":"8221",
    "addr:street":"Hirnsdorf",
    "iso:country":"AT",
    "sg:address":"Hirnsdorf 107",
    "sg:city":"Hirnsdorf",
    "sg:classifiers":[
        {
            "category":"Retail",
            "subcategory":"Repair Shop",
            "type":"Services"
        }
    ],
    "sg:phone":"+43 3113 2421",
    "sg:postcode":"8221",
    "sg:province":"Steiermark",
    "sg:tags":[
        "agricultural",
        "machinery"
    ],
    "sg:website":"hlindner.at",
    "wof:name":"Harald Lindner -Landmaschinen KFZ Reparaturwerkst\u00e4tte",
    "wof:placetype":"venue"
},
  "geometry": {"coordinates":[15.8271846771,47.1937179565],"type":"Point"}
}