{
  "type": "Feature",
  "properties": {
    "addr:full":"Hengstpa\u00df Landesstr 35 Windischgarsten Ober\u00f6sterreich 4580",
    "addr:housenumber":"35",
    "addr:postcode":"4580",
    "iso:country":"AT",
    "sg:address":"Hengstpa\u00df Landesstr 35",
    "sg:city":"Windischgarsten",
    "sg:orig_category":"Appartements / Ferienwohnungen",
    "sg:phone":"+43 7562 8061",
    "sg:postcode":"4580",
    "sg:province":"Ober\u00f6sterreich",
    "wof:name":"Ferienhof Wasserbauer",
    "wof:placetype":"venue"
},
  "geometry": {"coordinates":[14.3353090286,47.7206954956],"type":"Point"}
}