{
  "type": "Feature",
  "properties": {
    "addr:full":"Salzamtsg 4 Graz Steiermark 8010",
    "addr:housenumber":"4",
    "addr:postcode":"8010",
    "addr:street":"Salzamtsg",
    "iso:country":"AT",
    "sg:address":"Salzamtsg 4",
    "sg:city":"Graz",
    "sg:orig_category":"Lederwaren / Erzeugung U Gro\u00c3\u0178handel",
    "sg:phone":"+43 316 829118",
    "sg:postcode":"8010",
    "sg:province":"Steiermark",
    "wof:name":"P\u00f6lzer Konrad",
    "wof:placetype":"venue"
},
  "geometry": {"coordinates":[15.4435052872,47.0708007812],"type":"Point"}
}