{
  "type": "Feature",
  "properties": {
    "addr:full":"Einfang 29 Schwaz Tirol 6130",
    "addr:housenumber":"29",
    "addr:postcode":"6130",
    "addr:street":"Einfang;Tirol",
    "iso:country":"AT",
    "sg:address":"Einfang 29",
    "sg:city":"Schwaz",
    "sg:orig_category":"Installationsunternehmen",
    "sg:phone":"+43 5242 645350",
    "sg:postcode":"6130",
    "sg:province":"Tirol",
    "wof:name":"Brunner Max",
    "wof:placetype":"venue"
},
  "geometry": {"coordinates":[11.7215518951,47.3589439392],"type":"Point"}
}