{
  "type": "Feature",
  "properties": {
    "iso:country":"AT",
    "sg:address":"Nr 446",
    "sg:city":"Lech",
    "sg:orig_category":"Appartements / Ferienwohnungen",
    "sg:phone":"+43 5583 2116",
    "sg:postcode":"6764",
    "sg:province":"Vorarlberg",
    "wof:name":"Appartements Almajur",
    "wof:placetype":"venue"
},
  "geometry": {"coordinates":[10.1417798996,47.2082939148],"type":"Point"}
}