{
  "type": "Feature",
  "properties": {
    "iso:country":"AT",
    "sg:address":"Sch\u00e4rdinger Str 29",
    "sg:city":"Ried im Innkreis",
    "sg:orig_category":"Massagen",
    "sg:phone":"+43 676 5061495",
    "sg:postcode":"4910",
    "sg:province":"Ober\u00f6sterreich",
    "wof:name":"Pichlerbauer Renate Anna Energetik - Heilmasseurin",
    "wof:placetype":"venue"
},
  "geometry": {"coordinates":[13.4900550842,48.2098655701],"type":"Point"}
}