{
  "type": "Feature",
  "properties": {
    "iso:country":"AT",
    "sg:address":"Edelhofstr 14",
    "sg:city":"Micheldorf in Ober\u00f6sterreich",
    "sg:orig_category":"Apothekenbedarf U -Einrichtungen",
    "sg:phone":"+43 4375 82626370",
    "sg:postcode":"4563",
    "sg:province":"Ober\u00f6sterreich",
    "wof:name":"KLINGER M\u00f6belbau GmbH - Apothekeneinrichtungen",
    "wof:placetype":"venue"
},
  "geometry": {"coordinates":[14.118522644,47.8900985718],"type":"Point"}
}