{
  "type": "Feature",
  "properties": {
    "addr:full":"Putzinger Str 24 Gro\u00dfebersdorf Nieder\u00f6sterreich 2203",
    "addr:postcode":"2203",
    "addr:street":"Str 24",
    "iso:country":"AT",
    "sg:address":"Putzinger Str 24",
    "sg:city":"Gro\u00dfebersdorf",
    "sg:orig_category":"\u00c3\u201erzte / F Allgemeinmedizin",
    "sg:phone":"+43 2245 83570",
    "sg:postcode":"2203",
    "sg:province":"Nieder\u00f6sterreich",
    "wof:name":"Ballner Gabriele Dr",
    "wof:placetype":"venue"
},
  "geometry": {"coordinates":[16.4330348969,48.386341095],"type":"Point"}
}