{
  "type": "Feature",
  "properties": {
    "addr:full":"Neustift 1a Maria Neustift Ober\u00f6sterreich 4443",
    "addr:housenumber":"1a",
    "addr:postcode":"4443",
    "addr:street":"Neustift",
    "iso:country":"AT",
    "sg:address":"Neustift 1a",
    "sg:city":"Maria Neustift",
    "sg:orig_category":"Weiterbildungsinstitute M Allg U Berufl Bildungsangebot",
    "sg:phone":"+43 7250 50756",
    "sg:postcode":"4443",
    "sg:province":"Ober\u00f6sterreich",
    "wof:name":"hc Regional Akademie",
    "wof:placetype":"venue"
},
  "geometry": {"coordinates":[14.5829429626,47.9169654846],"type":"Point"}
}