{
  "type": "Feature",
  "properties": {
    "addr:full":"Siedersbergg 13 Klosterneuburg Nieder\u00f6sterreich 3400",
    "addr:housenumber":"13",
    "addr:postcode":"3400",
    "addr:street":"Siedersbergg;Niederoesterreich",
    "iso:country":"AT",
    "sg:address":"Siedersbergg 13",
    "sg:city":"Klosterneuburg",
    "sg:orig_category":"Finanz- U Wirtschaftsberatung",
    "sg:phone":"+43 2243 25283",
    "sg:postcode":"3400",
    "sg:province":"Nieder\u00f6sterreich",
    "wof:name":"Financial Services Research GesmbH",
    "wof:placetype":"venue"
},
  "geometry": {"coordinates":[16.3127059937,48.2858200073],"type":"Point"}
}