{
  "type": "Feature",
  "properties": {
    "addr:full":"Bahnhofstr 15 Villach K\u00e4rnten 9500",
    "addr:housenumber":"15",
    "addr:postcode":"9500",
    "addr:street":"Bahnhofstr;Kaernten",
    "iso:country":"AT",
    "sg:address":"Bahnhofstr 15",
    "sg:city":"Villach",
    "sg:orig_category":"Fotoapparate U -Artikel / Einzelhandel",
    "sg:phone":"+43 4242 244200",
    "sg:postcode":"9500",
    "sg:province":"K\u00e4rnten",
    "wof:name":"Photo Kofler GesmbH",
    "wof:placetype":"venue"
},
  "geometry": {"coordinates":[13.8485536575,46.6174888611],"type":"Point"}
}