{
  "type": "Feature",
  "properties": {
    "addr:full":"St P\u00f6ltner Str 8 Karlstetten Nieder\u00f6sterreich 3121",
    "addr:housenumber":"8",
    "addr:postcode":"3121",
    "addr:street":"Str",
    "iso:country":"AT",
    "sg:address":"St P\u00f6ltner Str 8",
    "sg:city":"Karlstetten",
    "sg:orig_category":"Autoreparatur",
    "sg:phone":"+43 2741 8249",
    "sg:postcode":"3121",
    "sg:province":"Nieder\u00f6sterreich",
    "wof:name":"Barta Kraftfahrzeughandel und Reparatur GmbH",
    "wof:placetype":"venue"
},
  "geometry": {"coordinates":[15.5689992905,48.2581138611],"type":"Point"}
}