{
  "type": "Feature",
  "properties": {
    "addr:full":"Girakstr 7 Korneuburg Nieder\u00f6sterreich 2100",
    "addr:housenumber":"7",
    "addr:postcode":"2100",
    "addr:street":"Girakstr;Niederoesterreich",
    "iso:country":"AT",
    "sg:address":"Girakstr 7",
    "sg:city":"Korneuburg",
    "sg:classifiers":[
        {
            "category":"Professional",
            "subcategory":"Computer Services",
            "type":"Services"
        }
    ],
    "sg:phone":"+43 2262 6900",
    "sg:postcode":"2100",
    "sg:province":"Nieder\u00f6sterreich",
    "sg:tags":[
        "software"
    ],
    "wof:name":"Gemdat N\u00f6 Gemeinde-Datenservice GesmbH",
    "wof:placetype":"venue"
},
  "geometry": {"coordinates":[16.3288116455,48.3599624634],"type":"Point"}
}