{
  "type": "Feature",
  "properties": {
    "addr:full":"Mistelbacher Str 41 Ernstbrunn Nieder\u00f6sterreich 2115",
    "addr:postcode":"2115",
    "addr:street":"Str 41",
    "iso:country":"AT",
    "sg:address":"Mistelbacher Str 41",
    "sg:city":"Ernstbrunn",
    "sg:orig_category":"Tischlereien",
    "sg:phone":"+43 2576 2110",
    "sg:postcode":"2115",
    "sg:province":"Nieder\u00f6sterreich",
    "wof:name":"Langschwert Karl",
    "wof:placetype":"venue"
},
  "geometry": {"coordinates":[16.3708267212,48.5281219482],"type":"Point"}
}