{
  "type": "Feature",
  "properties": {
    "iso:country":"AT",
    "sg:address":"Herzg 86",
    "sg:city":"Wien",
    "sg:orig_category":"Hunde- U Katzensalons",
    "sg:phone":"+43 4316 418424",
    "sg:postcode":"1100",
    "sg:province":"Wien",
    "wof:name":"Hundesalon Akita",
    "wof:placetype":"venue"
},
  "geometry": {"coordinates":[16.3655643463,48.1703033447],"type":"Point"}
}