{
  "type": "Feature",
  "properties": {
    "addr:full":"Hofg 2 Innsbruck Tirol 6020",
    "addr:housenumber":"2",
    "addr:postcode":"6020",
    "addr:street":"Hofg;Tirol",
    "iso:country":"AT",
    "sg:address":"Hofg 2",
    "sg:city":"Innsbruck",
    "sg:orig_category":"Mineralien",
    "sg:phone":"+43 512 585789",
    "sg:postcode":"6020",
    "sg:province":"Tirol",
    "wof:name":"Hofmann Erich",
    "wof:placetype":"venue"
},
  "geometry": {"coordinates":[11.3913040161,47.2679977417],"type":"Point"}
}