{
  "type": "Feature",
  "properties": {
    "addr:full":"Gmachlstr 823a+b Kaprun Salzburg 5710",
    "addr:postcode":"5710",
    "iso:country":"AT",
    "sg:address":"Gmachlstr 823a+b",
    "sg:city":"Kaprun",
    "sg:orig_category":"Glasereien",
    "sg:phone":"+43 4365 4783440",
    "sg:postcode":"5710",
    "sg:province":"Salzburg",
    "wof:name":"Marcher Glas- u Dachbau GmbH",
    "wof:placetype":"venue"
},
  "geometry": {"coordinates":[12.7575788498,47.2708206177],"type":"Point"}
}