{
  "type": "Feature",
  "properties": {
    "addr:full":"Grenzgasse 1 Schottwien Nieder\u00f6sterreich 2641",
    "addr:housenumber":"1",
    "addr:postcode":"2641",
    "addr:street":"Grenzgasse",
    "iso:country":"AT",
    "sg:address":"Grenzgasse 1",
    "sg:city":"Schottwien",
    "sg:classifiers":[
        {
            "category":"Manufacturing",
            "subcategory":"Wood Products",
            "type":"Manufacturing & Wholesale Goods"
        }
    ],
    "sg:phone":"+43 2663 8370",
    "sg:postcode":"2641",
    "sg:province":"Nieder\u00f6sterreich",
    "sg:tags":[
        "gate",
        "made",
        "door"
    ],
    "wof:name":"Manfred Schneeweiss",
    "wof:placetype":"venue"
},
  "geometry": {"coordinates":[15.903134346,47.6590156555],"type":"Point"}
}