{
  "type": "Feature",
  "properties": {
    "iso:country":"AT",
    "sg:address":"Meinhardstr 16",
    "sg:city":"Innsbruck",
    "sg:orig_category":"Fotografen",
    "sg:phone":"+43 512 560770",
    "sg:postcode":"6020",
    "sg:province":"Tirol",
    "wof:name":"Die Fotografen - Tanja & Charly Lair",
    "wof:placetype":"venue"
},
  "geometry": {"coordinates":[11.3985738754,47.2652664185],"type":"Point"}
}