{
  "type": "Feature",
  "properties": {
    "iso:country":"AT",
    "sg:address":"Glockeng 4",
    "sg:city":"Wien",
    "sg:orig_category":"Immobilienverwaltungen",
    "sg:phone":"+43 1 2126021",
    "sg:postcode":"1020",
    "sg:province":"Wien",
    "wof:name":"Ortner Immobilien GmbH",
    "wof:placetype":"venue"
},
  "geometry": {"coordinates":[16.3815631866,48.2172966003],"type":"Point"}
}