{
  "type": "Feature",
  "properties": {
    "addr:full":"Kaltenleutgebner Str 9a/2 Wien Wien 1230",
    "addr:housenumber":"2",
    "addr:postcode":"1230",
    "addr:street":"Str 9A /",
    "iso:country":"AT",
    "sg:address":"Kaltenleutgebner Str 9a/2",
    "sg:city":"Wien",
    "sg:classifiers":[
        {
            "category":"Internet Cafe",
            "subcategory":"None",
            "type":"Food & Drink"
        }
    ],
    "sg:phone":"+43 1 9567350",
    "sg:postcode":"1230",
    "sg:province":"Wien",
    "wof:name":"e-4you.at Spitzm\u00fcller",
    "wof:placetype":"venue"
},
  "geometry": {"coordinates":[16.2417793274,48.1311607361],"type":"Point"}
}