{
  "type": "Feature",
  "properties": {
    "iso:country":"AT",
    "sg:address":"Ketzerg 376",
    "sg:city":"Wien",
    "sg:orig_category":"Berufsbekleidung / Erzeugung U Gro\u00c3\u0178handel",
    "sg:phone":"+43 4318 861075",
    "sg:postcode":"1230",
    "sg:province":"Wien",
    "sg:website":"birdy.at",
    "wof:name":"Birdy Bestickungen Birgit Richter",
    "wof:placetype":"venue"
},
  "geometry": {"coordinates":[16.2590332031,48.1333312988],"type":"Point"}
}