{
  "type": "Feature",
  "properties": {
    "addr:full":"Nr 201 Scheffau am Wilden Kaiser Tirol 6351",
    "addr:postcode":"6351",
    "addr:street":"Nr 201;Wilden Kaiser",
    "iso:country":"AT",
    "sg:address":"Nr 201",
    "sg:city":"Scheffau am Wilden Kaiser",
    "sg:orig_category":"Lebensmittel / Einzelhandel",
    "sg:phone":"+43 5358 8374",
    "sg:postcode":"6351",
    "sg:province":"Tirol",
    "wof:name":"Spar-Markt Inh Gerhard Krieglsteiner",
    "wof:placetype":"venue"
},
  "geometry": {"coordinates":[12.2500114441,47.5286445618],"type":"Point"}
}