{
  "type": "Feature",
  "properties": {
    "iso:country":"AT",
    "sg:address":"Nr 62",
    "sg:city":"Desselbrunn",
    "sg:orig_category":"Banken U Sparkassen",
    "sg:phone":"+43 4376 733717",
    "sg:postcode":"4693",
    "sg:province":"Ober\u00f6sterreich",
    "wof:name":"Raiffeisenkasse Desselbrunn regGenmbH",
    "wof:placetype":"venue"
},
  "geometry": {"coordinates":[13.7724685669,48.0213432312],"type":"Point"}
}