{
  "type": "Feature",
  "properties": {
    "iso:country":"AT",
    "sg:address":"Tiefenweg 6",
    "sg:city":"Rutzenmoos",
    "sg:classifiers":[
        {
            "category":"Home & Garden",
            "subcategory":"Carpets & Floor Coverings",
            "type":"Retail Goods"
        }
    ],
    "sg:phone":"+43 761265041",
    "sg:postcode":"4845",
    "sg:province":"Ober\u00f6sterreich",
    "sg:tags":[
        "stone",
        "natural",
        "panel"
    ],
    "sg:website":"pesendorfer.net",
    "wof:name":"Pesendorfer GmbH",
    "wof:placetype":"venue"
},
  "geometry": {"coordinates":[13.7094717026,47.9627571106],"type":"Point"}
}