{
  "type": "Feature",
  "properties": {
    "iso:country":"AT",
    "sg:address":"Eferdinger Str 20/1",
    "sg:city":"Wilhering",
    "sg:orig_category":"Restaurants: Chinesisch",
    "sg:phone":"+43 7226 3570",
    "sg:postcode":"4073",
    "sg:province":"Ober\u00f6sterreich",
    "wof:name":"Asiatisches Restaurant Oriental Park",
    "wof:placetype":"venue"
},
  "geometry": {"coordinates":[14.1663713455,48.2995948792],"type":"Point"}
}