{
  "type": "Feature",
  "properties": {
    "addr:full":"Markenschlagrotte 41 Frankenfels Nieder\u00f6sterreich 3213",
    "addr:housenumber":"41",
    "addr:postcode":"3213",
    "addr:street":"Markenschlagrotte",
    "iso:country":"AT",
    "sg:address":"Markenschlagrotte 41",
    "sg:city":"Frankenfels",
    "sg:orig_category":"Transportunternehmen",
    "sg:phone":"+43 4327 25408",
    "sg:postcode":"3213",
    "sg:province":"Nieder\u00f6sterreich",
    "wof:name":"Humpelstetter Franz",
    "wof:placetype":"venue"
},
  "geometry": {"coordinates":[15.2996454239,47.967212677],"type":"Point"}
}