{
  "type": "Feature",
  "properties": {
    "iso:country":"AT",
    "sg:address":"Hainburger Str 2",
    "sg:city":"Fischamend",
    "sg:orig_category":"Tabaktrafiken",
    "sg:phone":"+43 2232 76606",
    "sg:postcode":"2401",
    "sg:province":"Nieder\u00f6sterreich",
    "wof:name":"Gabmaier Erich",
    "wof:placetype":"venue"
},
  "geometry": {"coordinates":[16.6117286682,48.118888855],"type":"Point"}
}