{
  "type": "Feature",
  "properties": {
    "iso:country":"AT",
    "sg:address":"Sieveringer Str 80",
    "sg:city":"Wien",
    "sg:orig_category":"Aufsperrdienste",
    "sg:phone":"+43 4313 2015810",
    "sg:postcode":"1190",
    "sg:province":"Wien",
    "wof:name":"Schlosserei W Krutisch GmbH",
    "wof:placetype":"venue"
},
  "geometry": {"coordinates":[16.3281822205,48.2485427856],"type":"Point"}
}