{
  "type": "Feature",
  "properties": {
    "iso:country":"AT",
    "sg:city":"Bischofshofen",
    "sg:classifiers":[
        {
            "category":"Taxi",
            "type":"Transportation"
        }
    ],
    "sg:phone":"+43 4366 43203121",
    "sg:postcode":"5500",
    "sg:province":"Salzburg",
    "sg:tags":[
        "personentransporte",
        "u"
    ],
    "wof:name":"Maier Bert's Taxi",
    "wof:placetype":"venue"
},
  "geometry": {"coordinates":[13.219584465,47.4166107178],"type":"Point"}
}