{
  "type": "Feature",
  "properties": {
    "addr:full":"Albertg 24 Wien Wien 1080",
    "addr:housenumber":"24",
    "addr:postcode":"1080",
    "addr:street":"Albertg",
    "iso:country":"AT",
    "sg:address":"Albertg 24",
    "sg:city":"Wien",
    "sg:orig_category":"Friseure U Frisiersalons",
    "sg:phone":"+43 1 4055047",
    "sg:postcode":"1080",
    "sg:province":"Wien",
    "wof:name":"Friseur DORIS Cuba",
    "wof:placetype":"venue"
},
  "geometry": {"coordinates":[16.3430690765,48.2106552124],"type":"Point"}
}