{
  "type": "Feature",
  "properties": {
    "addr:full":"Haspingerstr 4 Radstadt Salzburg 5550",
    "addr:housenumber":"4",
    "addr:postcode":"5550",
    "addr:street":"Haspingerstr;Salzburg",
    "iso:country":"AT",
    "sg:address":"Haspingerstr 4",
    "sg:city":"Radstadt",
    "sg:orig_category":"Maler, Anstreicher U Lackierer",
    "sg:phone":"+43 4364 525476",
    "sg:postcode":"5550",
    "sg:province":"Salzburg",
    "wof:name":"St\u00fccklschweiger Harald jun",
    "wof:placetype":"venue"
},
  "geometry": {"coordinates":[13.4598932266,47.3856925964],"type":"Point"}
}