{
  "type": "Feature",
  "properties": {
    "addr:full":"Pfarrerberg 3 St. Peter am Wimberg Ober\u00f6sterreich 4171",
    "addr:housenumber":"3",
    "addr:postcode":"4171",
    "addr:street":"Pfarrerberg",
    "iso:country":"AT",
    "sg:address":"Pfarrerberg 3",
    "sg:city":"St. Peter am Wimberg",
    "sg:orig_category":"Volksschulen",
    "sg:phone":"+43 4372 82804612",
    "sg:postcode":"4171",
    "sg:province":"Ober\u00f6sterreich",
    "wof:name":"Volksschule",
    "wof:placetype":"venue"
},
  "geometry": {"coordinates":[14.0821895599,48.504032135],"type":"Point"}
}