{
  "type": "Feature",
  "properties": {
    "addr:full":"\u00e4gidipl 4 Stegersbach Burgenland 7551",
    "addr:housenumber":"4",
    "addr:postcode":"7551",
    "addr:street":"Aegidipl",
    "iso:country":"AT",
    "sg:address":"\u00e4gidipl 4",
    "sg:city":"Stegersbach",
    "sg:orig_category":"Bewachungsunternehmen",
    "sg:phone":"+43 3326 54819",
    "sg:postcode":"7551",
    "sg:province":"Burgenland",
    "wof:name":"CSC Paal",
    "wof:placetype":"venue"
},
  "geometry": {"coordinates":[16.1668128967,47.1612892151],"type":"Point"}
}