{
  "type": "Feature",
  "properties": {
    "addr:full":"Kopalgasse 72/6 Wien Wien 1110",
    "addr:housenumber":"72 / 6",
    "addr:postcode":"1110",
    "addr:street":"Kopalgasse",
    "iso:country":"AT",
    "sg:address":"Kopalgasse 72/6",
    "sg:city":"Wien",
    "sg:classifiers":[
        {
            "category":"Shopping",
            "subcategory":"Books",
            "type":"Retail Goods"
        }
    ],
    "sg:phone":"+43 1 7434120",
    "sg:postcode":"1110",
    "sg:province":"Wien",
    "sg:website":"punktzwoelf.at",
    "wof:name":"Punkt Zw\u00f6lf Verlag",
    "wof:placetype":"venue"
},
  "geometry": {"coordinates":[16.4241542816,48.179725647],"type":"Point"}
}