{
  "type": "Feature",
  "properties": {
    "addr:full":"Hietzinger Hauptstr 108 Wien Wien 1130",
    "addr:housenumber":"108",
    "addr:postcode":"1130",
    "addr:street":"Hietzinger Hauptstr",
    "iso:country":"AT",
    "sg:address":"Hietzinger Hauptstr 108",
    "sg:city":"Wien",
    "sg:orig_category":"Tapezierer U Dekorateure",
    "sg:phone":"+43 1 8779314",
    "sg:postcode":"1130",
    "sg:province":"Wien",
    "sg:website":"www.malerei-nimmerrichter.at",
    "wof:name":"Nimmerrichter Franz",
    "wof:placetype":"venue"
},
  "geometry": {"coordinates":[16.2785758972,48.1877708435],"type":"Point"}
}