{
  "type": "Feature",
  "properties": {
    "iso:country":"AT",
    "sg:address":"Nr 62",
    "sg:city":"Birkfeld",
    "sg:orig_category":"Forstverwaltungen",
    "sg:phone":"+43 3174 4808",
    "sg:postcode":"8190",
    "sg:province":"Steiermark",
    "wof:name":"Forsthaus Waisenegg",
    "wof:placetype":"venue"
},
  "geometry": {"coordinates":[15.7014284134,47.3529853821],"type":"Point"}
}