{
  "type": "Feature",
  "properties": {
    "iso:country":"AT",
    "sg:address":"Krottenseestr 45",
    "sg:city":"Gmunden",
    "sg:orig_category":"Werbegrafik- U Grafik-Design",
    "sg:phone":"+43 761290034301",
    "sg:postcode":"4810",
    "sg:province":"Ober\u00f6sterreich",
    "wof:name":"designb\u00fcro formschluss",
    "wof:placetype":"venue"
},
  "geometry": {"coordinates":[13.8145132065,47.9281044006],"type":"Point"}
}