{
  "type": "Feature",
  "properties": {
    "addr:full":"Wiener Str 297 G\u00f6sting Steiermark 8051",
    "addr:housenumber":"297",
    "addr:postcode":"8051",
    "addr:street":"Goesting Steiermark",
    "iso:country":"AT",
    "sg:address":"Wiener Str 297",
    "sg:city":"G\u00f6sting",
    "sg:orig_category":"Holzhandel",
    "sg:phone":"+43 316 6796000",
    "sg:postcode":"8051",
    "sg:province":"Steiermark",
    "wof:name":"T & F Holzfachgesch\u00e4ft GmbH",
    "wof:placetype":"venue"
},
  "geometry": {"coordinates":[15.3543653488,47.0787315369],"type":"Point"}
}