{
  "type": "Feature",
  "properties": {
    "addr:full":"Pfarrg 7 Imst Tirol 6460",
    "addr:housenumber":"7",
    "addr:postcode":"6460",
    "addr:street":"Pfarrg;Tirol",
    "iso:country":"AT",
    "sg:address":"Pfarrg 7",
    "sg:city":"Imst",
    "sg:orig_category":"\u00c3\u201erzte / F Allgemeinmedizin",
    "sg:phone":"+43 5412 66248",
    "sg:postcode":"6460",
    "sg:province":"Tirol",
    "wof:name":"Jenewein Kurt Dr",
    "wof:placetype":"venue"
},
  "geometry": {"coordinates":[10.7387533188,47.2428588867],"type":"Point"}
}