{
  "type": "Feature",
  "properties": {
    "iso:country":"AT",
    "sg:address":"Auweg 5",
    "sg:city":"Anthering",
    "sg:classifiers":[
        {
            "category":"Taxi",
            "type":"Transportation"
        }
    ],
    "sg:phone":"+43 6223 2325",
    "sg:postcode":"5102",
    "sg:province":"Salzburg",
    "sg:tags":[
        "personentransporte",
        "u"
    ],
    "wof:name":"P\u00f6schl Leopold",
    "wof:placetype":"venue"
},
  "geometry": {"coordinates":[13.0089254379,47.8808403015],"type":"Point"}
}