{
  "type": "Feature",
  "properties": {
    "addr:full":"Fabrikstrasse 31 Steyr Ober\u00f6sterreich 4400",
    "addr:housenumber":"31",
    "addr:postcode":"4400",
    "addr:street":"Fabrikstrasse;Oberoesterreich",
    "iso:country":"AT",
    "sg:address":"Fabrikstrasse 31",
    "sg:city":"Steyr",
    "sg:classifiers":[
        {
            "category":"Banks & Credit Unions",
            "subcategory":"Bureau De Change",
            "type":"Services"
        }
    ],
    "sg:phone":"+43 7252 71093",
    "sg:postcode":"4400",
    "sg:province":"Ober\u00f6sterreich",
    "sg:tags":[
        "pipe",
        "organ"
    ],
    "wof:name":"Kurt Apfelthaler",
    "wof:placetype":"venue"
},
  "geometry": {"coordinates":[14.4063024521,48.0429153442],"type":"Point"}
}