{
  "type": "Feature",
  "properties": {
    "addr:full":"Breitenfurter Str 114 Wien Wien 1120",
    "addr:housenumber":"114",
    "addr:postcode":"1120",
    "addr:street":"Str",
    "iso:country":"AT",
    "sg:address":"Breitenfurter Str 114",
    "sg:city":"Wien",
    "sg:orig_category":"Tabaktrafiken",
    "sg:phone":"+43 4319 241976",
    "sg:postcode":"1120",
    "sg:province":"Wien",
    "wof:name":"Dallinger Gerhard",
    "wof:placetype":"venue"
},
  "geometry": {"coordinates":[16.3089084625,48.1599502563],"type":"Point"}
}