{
  "type": "Feature",
  "properties": {
    "addr:full":"Stadtpl 1 Vils Tirol 6682",
    "addr:housenumber":"1",
    "addr:postcode":"6682",
    "addr:street":"Stadtpl;Tirol",
    "iso:country":"AT",
    "sg:address":"Stadtpl 1",
    "sg:city":"Vils",
    "sg:orig_category":"Gemeinden",
    "sg:phone":"+43 5677 82040",
    "sg:postcode":"6682",
    "sg:province":"Tirol",
    "wof:name":"Stadtgemeinde Vils",
    "wof:placetype":"venue"
},
  "geometry": {"coordinates":[10.6306695938,47.5493049622],"type":"Point"}
}