{
  "type": "Feature",
  "properties": {
    "iso:country":"AT",
    "sg:address":"Johann Roithner-Str 3",
    "sg:city":"Traun",
    "sg:orig_category":"Non-Classified Establishments",
    "sg:phone":"+43 7229 722520",
    "sg:postcode":"4050",
    "sg:province":"Ober\u00f6sterreich",
    "wof:name":"Kirchenbeitragsstelle",
    "wof:placetype":"venue"
},
  "geometry": {"coordinates":[14.2387523651,48.2220115662],"type":"Point"}
}