{
  "type": "Feature",
  "properties": {
    "iso:country":"AT",
    "sg:address":"Grazer Str 18",
    "sg:city":"F\u00fcrstenfeld",
    "sg:orig_category":"Non-Classified Establishments",
    "sg:phone":"+43 3382 55510",
    "sg:postcode":"8280",
    "sg:province":"Steiermark",
    "wof:name":"Tor Center F\u00fcrstenfeld",
    "wof:placetype":"venue"
},
  "geometry": {"coordinates":[16.0679264069,47.0581665039],"type":"Point"}
}