{
  "type": "Feature",
  "properties": {
    "iso:country":"AT",
    "sg:address":"Oberlienz 162",
    "sg:city":"Lienz",
    "sg:classifiers":[
        {
            "category":"Home & Garden",
            "subcategory":"Building Materials",
            "type":"Retail Goods"
        }
    ],
    "sg:phone":"+43 4852 67770",
    "sg:postcode":"9900",
    "sg:province":"Tirol",
    "sg:tags":[
        "window",
        "plastic"
    ],
    "sg:website":"tischlerei-florin.at",
    "wof:name":"Thomas Kratzer",
    "wof:placetype":"venue"
},
  "geometry": {"coordinates":[12.7684783936,46.8281173706],"type":"Point"}
}