{
  "type": "Feature",
  "properties": {
    "iso:country":"AT",
    "sg:address":"Riegersdorf 46",
    "sg:city":"Hainersdorf",
    "sg:orig_category":"Tischlereien",
    "sg:phone":"+43 4333 85516",
    "sg:postcode":"8264",
    "sg:province":"Steiermark",
    "wof:name":"Meister Ferdinand",
    "wof:placetype":"venue"
},
  "geometry": {"coordinates":[15.9670476913,47.1033477783],"type":"Point"}
}