{
  "type": "Feature",
  "properties": {
    "addr:full":"Nr 1 Lichtenegg Nieder\u00f6sterreich 2813",
    "addr:postcode":"2813",
    "addr:street":"Nr;Lichtenegg",
    "iso:country":"AT",
    "sg:address":"Nr 1",
    "sg:city":"Lichtenegg",
    "sg:orig_category":"Maler, Anstreicher U Lackierer",
    "sg:phone":"+43 4326 432377",
    "sg:postcode":"2813",
    "sg:province":"Nieder\u00f6sterreich",
    "wof:name":"Willke Thomas",
    "wof:placetype":"venue"
},
  "geometry": {"coordinates":[16.1972618103,47.5997505188],"type":"Point"}
}