{
  "type": "Feature",
  "properties": {
    "addr:full":"Grazer Vorstadt 80 Voitsberg Steiermark 8570",
    "addr:housenumber":"80",
    "addr:postcode":"8570",
    "addr:street":"Grazer Vorstadt",
    "iso:country":"AT",
    "sg:address":"Grazer Vorstadt 80",
    "sg:city":"Voitsberg",
    "sg:classifiers":[
        {
            "category":"Restaurant",
            "type":"Food & Drink"
        }
    ],
    "sg:phone":"+43 3142 22445",
    "sg:postcode":"8570",
    "sg:province":"Steiermark",
    "sg:tags":[
        "pizzeria"
    ],
    "wof:name":"Alberto's Pizzeria",
    "wof:placetype":"venue"
},
  "geometry": {"coordinates":[15.1602315903,47.0438194275],"type":"Point"}
}