{
  "type": "Feature",
  "properties": {
    "addr:full":"Bahnhofstr 2 Hallein Salzburg 5400",
    "addr:housenumber":"2",
    "addr:postcode":"5400",
    "addr:street":"Bahnhofstr;Salzburg",
    "iso:country":"AT",
    "sg:address":"Bahnhofstr 2",
    "sg:city":"Hallein",
    "sg:orig_category":"Optiker",
    "sg:phone":"+43 6245 84444",
    "sg:postcode":"5400",
    "sg:province":"Salzburg",
    "wof:name":"St\u00f6ckl Optik",
    "wof:placetype":"venue"
},
  "geometry": {"coordinates":[13.097990036,47.6836242676],"type":"Point"}
}