{
  "type": "Feature",
  "properties": {
    "addr:full":"Kirchenpl 7 Gro\u00df-Enzersdorf Nieder\u00f6sterreich 2301",
    "addr:housenumber":"7",
    "addr:postcode":"2301",
    "addr:street":"Kirchenpl;Niederoesterreich",
    "iso:country":"AT",
    "sg:address":"Kirchenpl 7",
    "sg:city":"Gro\u00df-Enzersdorf",
    "sg:orig_category":"Brautkleider U -Artikel",
    "sg:phone":"+43 4367 66347273",
    "sg:postcode":"2301",
    "sg:province":"Nieder\u00f6sterreich",
    "sg:website":"brautboutique-sonja.at",
    "wof:name":"Brautboutique Sonja - Harwath Sonja",
    "wof:placetype":"venue"
},
  "geometry": {"coordinates":[16.5499687195,48.2032165527],"type":"Point"}
}