{
  "type": "Feature",
  "properties": {
    "addr:full":"S\u00fcdlandstr 5 Amstetten Nieder\u00f6sterreich 3300",
    "addr:housenumber":"5",
    "addr:postcode":"3300",
    "addr:street":"Suedlandstr;Niederoesterreich",
    "iso:country":"AT",
    "sg:address":"S\u00fcdlandstr 5",
    "sg:city":"Amstetten",
    "sg:orig_category":"Genossenschaften",
    "sg:phone":"+43 7472 624120",
    "sg:postcode":"3300",
    "sg:province":"Nieder\u00f6sterreich",
    "wof:name":"Wigof Wirtschaftsgenossenschaft der Fleischer Ober\u00f6sterreichs regGenmbH",
    "wof:placetype":"venue"
},
  "geometry": {"coordinates":[14.8706607819,48.1244812012],"type":"Point"}
}