{
  "type": "Feature",
  "properties": {
    "iso:country":"AT",
    "sg:address":"Hauptstrasse 15",
    "sg:city":"Mooskirchen",
    "sg:classifiers":[
        {
            "category":"Structure",
            "subcategory":"Building",
            "type":"Public Place"
        }
    ],
    "sg:phone":"+43 3137 23110",
    "sg:postcode":"8562",
    "sg:province":"Steiermark",
    "sg:tags":[
        "apartment"
    ],
    "wof:name":"Johann Trost Bauges.m.b.H.",
    "wof:placetype":"venue"
},
  "geometry": {"coordinates":[15.281373024,46.9874725342],"type":"Point"}
}