{
  "type": "Feature",
  "properties": {
    "iso:country":"AT",
    "sg:address":"Maria-Theresien-Str. 7 ",
    "sg:city":"Innsbruck",
    "sg:classifiers":[
        {
            "category":"Shopping",
            "subcategory":"Clothing, Apparel, & Fashions",
            "type":"Retail Goods"
        }
    ],
    "sg:phone":"+43 4351 2587022",
    "sg:postcode":"6020",
    "sg:province":"Tirol",
    "sg:tags":[
        "clothes"
    ],
    "wof:name":"HELMUT SCHMARDA",
    "wof:placetype":"venue"
},
  "geometry": {"coordinates":[11.3938808441,47.2667884827],"type":"Point"}
}