{
  "type": "Feature",
  "properties": {
    "iso:country":"AT",
    "sg:address":"Str d Gendarmerie 5",
    "sg:city":"Wiener Neustadt",
    "sg:orig_category":"Polizei U Gendarmerie",
    "sg:phone":"+43 4326 223330",
    "sg:postcode":"2700",
    "sg:province":"Nieder\u00f6sterreich",
    "wof:name":"Gendarmerieeinsatzkommando",
    "wof:placetype":"venue"
},
  "geometry": {"coordinates":[16.2084026337,47.8370018005],"type":"Point"}
}