{
  "type": "Feature",
  "properties": {
    "iso:country":"AT",
    "sg:address":"Brixner Str 2",
    "sg:city":"Innsbruck",
    "sg:orig_category":"Immobilienmakler",
    "sg:phone":"+43 512 584156",
    "sg:postcode":"6020",
    "sg:province":"Tirol",
    "wof:name":"Immorealit\u00e4ten Immobilienvermittlung und -verwaltung GesmbH",
    "wof:placetype":"venue"
},
  "geometry": {"coordinates":[11.398273468,47.264881134],"type":"Point"}
}