{
  "type": "Feature",
  "properties": {
    "addr:full":"Eisenhandstr 48 Linz Ober\u00f6sterreich 4020",
    "addr:housenumber":"48",
    "addr:postcode":"4020",
    "addr:street":"Eisenhandstr",
    "iso:country":"AT",
    "sg:address":"Eisenhandstr 48",
    "sg:city":"Linz",
    "sg:orig_category":"Damenmoden",
    "sg:phone":"+43 732 7814280",
    "sg:postcode":"4020",
    "sg:province":"Ober\u00f6sterreich",
    "wof:name":"Wolfsteiner Christine",
    "wof:placetype":"venue"
},
  "geometry": {"coordinates":[14.3000612259,48.3017082214],"type":"Point"}
}