{
  "type": "Feature",
  "properties": {
    "addr:full":"Bahnstr 17 Knittelfeld Steiermark 8720",
    "addr:housenumber":"17",
    "addr:postcode":"8720",
    "addr:street":"Bahnstr",
    "iso:country":"AT",
    "sg:address":"Bahnstr 17",
    "sg:city":"Knittelfeld",
    "sg:orig_category":"Friseure U Frisiersalons",
    "sg:phone":"+43 4335 12826260",
    "sg:postcode":"8720",
    "sg:province":"Steiermark",
    "wof:name":"Frisiersalon Stuppacher",
    "wof:placetype":"venue"
},
  "geometry": {"coordinates":[14.8315944672,47.2154960632],"type":"Point"}
}