{
  "type": "Feature",
  "properties": {
    "addr:full":"Hauptstr 12 Untersiebenbrunn Nieder\u00f6sterreich 2284",
    "addr:housenumber":"12",
    "addr:postcode":"2284",
    "addr:street":"Hauptstr",
    "iso:country":"AT",
    "sg:address":"Hauptstr 12",
    "sg:city":"Untersiebenbrunn",
    "sg:orig_category":"Volksschulen",
    "sg:phone":"+43 2286 2294",
    "sg:postcode":"2284",
    "sg:province":"Nieder\u00f6sterreich",
    "wof:name":"Volksschule",
    "wof:placetype":"venue"
},
  "geometry": {"coordinates":[16.7453212738,48.2555809021],"type":"Point"}
}