{
  "type": "Feature",
  "properties": {
    "addr:full":"Kirchenpl 2 Ertl Nieder\u00f6sterreich 3355",
    "addr:housenumber":"2",
    "addr:postcode":"3355",
    "addr:street":"Kirchenpl",
    "iso:country":"AT",
    "sg:address":"Kirchenpl 2",
    "sg:city":"Ertl",
    "sg:orig_category":"Baumeister",
    "sg:phone":"+43 7477 20102",
    "sg:postcode":"3355",
    "sg:province":"Nieder\u00f6sterreich",
    "wof:name":"Hackl Erwin Ing",
    "wof:placetype":"venue"
},
  "geometry": {"coordinates":[14.631070137,47.9763450623],"type":"Point"}
}