{
  "type": "Feature",
  "properties": {
    "addr:full":"Westermayerg 11 Wien Wien 1140",
    "addr:housenumber":"11",
    "addr:postcode":"1140",
    "addr:street":"Westermayerg",
    "iso:country":"AT",
    "sg:address":"Westermayerg 11",
    "sg:city":"Wien",
    "sg:orig_category":"Ingenieurkonsulenten / Zivilingenieure",
    "sg:phone":"+43 1 9144117",
    "sg:postcode":"1140",
    "sg:province":"Wien",
    "wof:name":"Nussbaumer Bernhard Dipl-Ing",
    "wof:placetype":"venue"
},
  "geometry": {"coordinates":[16.2741222382,48.1958122253],"type":"Point"}
}