{
  "type": "Feature",
  "properties": {
    "addr:full":"Josef Herold-Str 17 Kitzb\u00fchel Tirol 6370",
    "addr:housenumber":"17",
    "addr:postcode":"6370",
    "addr:street":"Kitzbuehel Tirol",
    "iso:country":"AT",
    "sg:address":"Josef Herold-Str 17",
    "sg:city":"Kitzb\u00fchel",
    "sg:classifiers":[
        {
            "category":"Restaurant",
            "type":"Food & Drink"
        }
    ],
    "sg:phone":"+43 5356 67013",
    "sg:postcode":"6370",
    "sg:province":"Tirol",
    "wof:name":"Streifer'l Bar-Restaurant",
    "wof:placetype":"venue"
},
  "geometry": {"coordinates":[12.3902196884,47.4439544678],"type":"Point"}
}