{
  "type": "Feature",
  "properties": {
    "iso:country":"AT",
    "sg:address":"Markgraf-R\u00fcdiger-Strasse 1",
    "sg:city":"Wien",
    "sg:classifiers":[
        {
            "category":"Cafe",
            "type":"Food & Drink"
        }
    ],
    "sg:phone":"+43 1 98223610",
    "sg:postcode":"1150",
    "sg:province":"Wien",
    "sg:tags":[
        "outfitter",
        "expedition"
    ],
    "sg:website":"turecek.at",
    "wof:name":"Hof & Turecek Ges.m.b.H.",
    "wof:placetype":"venue"
},
  "geometry": {"coordinates":[16.3320903778,48.2006416321],"type":"Point"}
}