{
  "type": "Feature",
  "properties": {
    "addr:full":"Fischerstr 16 Radenthein K\u00e4rnten 9545",
    "addr:housenumber":"16",
    "addr:postcode":"9545",
    "addr:street":"Fischerstr;Kaernten",
    "iso:country":"AT",
    "sg:address":"Fischerstr 16",
    "sg:city":"Radenthein",
    "sg:orig_category":"Volksschulen",
    "sg:phone":"+43 4246 282113",
    "sg:postcode":"9545",
    "sg:province":"K\u00e4rnten",
    "wof:name":"Volksschule 2",
    "wof:placetype":"venue"
},
  "geometry": {"coordinates":[13.7061100006,46.7989692688],"type":"Point"}
}