{
  "type": "Feature",
  "properties": {
    "iso:country":"AT",
    "sg:address":"St. Jakober Dorfstr 218",
    "sg:city":"St. Anton am Arlberg",
    "sg:orig_category":"Pensionen / Privatzimmer",
    "sg:phone":"+43 5446 2139",
    "sg:postcode":"6580",
    "sg:province":"Tirol",
    "wof:name":"Haus Untergand",
    "wof:placetype":"venue"
},
  "geometry": {"coordinates":[10.3044586182,47.1441955566],"type":"Point"}
}