{
  "type": "Feature",
  "properties": {
    "addr:full":"Bundesstrasse 45 Weiz Steiermark 8160",
    "addr:housenumber":"45",
    "addr:postcode":"8160",
    "addr:street":"Bundesstrasse",
    "iso:country":"AT",
    "sg:address":"Bundesstrasse 45",
    "sg:city":"Weiz",
    "sg:classifiers":[
        {
            "category":"Manufacturing",
            "subcategory":"Rubber & Plastics",
            "type":"Manufacturing & Wholesale Goods"
        }
    ],
    "sg:phone":"+43 3172 23400",
    "sg:postcode":"8160",
    "sg:province":"Steiermark",
    "sg:tags":[
        "item",
        "household",
        "made"
    ],
    "sg:website":"teko-plastic.com",
    "wof:name":"Teko - Plastic Kunststoffwerk E. Schr\u00f6ck Ges.m.b.H.",
    "wof:placetype":"venue"
},
  "geometry": {"coordinates":[15.6215696335,47.2169532776],"type":"Point"}
}