{
  "type": "Feature",
  "properties": {
    "addr:full":"Kreuzg 9 Tschagguns Vorarlberg 6774",
    "addr:housenumber":"9",
    "addr:postcode":"6774",
    "addr:street":"Kreuzg",
    "iso:country":"AT",
    "sg:address":"Kreuzg 9",
    "sg:city":"Tschagguns",
    "sg:classifiers":[
        {
            "category":"Travel",
            "subcategory":"Hotels & Motels",
            "type":"Entertainment"
        }
    ],
    "sg:phone":"+43 5556 71000",
    "sg:postcode":"6774",
    "sg:province":"Vorarlberg",
    "wof:name":"Hotel Montafonerhof",
    "wof:placetype":"venue"
},
  "geometry": {"coordinates":[9.9022932053,47.0776329041],"type":"Point"}
}