{
  "type": "Feature",
  "properties": {
    "addr:full":"Taborstr 52a/12 Wien Wien 1020",
    "addr:housenumber":"52a / 12",
    "addr:postcode":"1020",
    "addr:street":"Taborstr",
    "iso:country":"AT",
    "sg:address":"Taborstr 52a/12",
    "sg:city":"Wien",
    "sg:orig_category":"Feldenkraismethode",
    "sg:phone":"+43 1 9255455",
    "sg:postcode":"1020",
    "sg:province":"Wien",
    "wof:name":"Treipl Monika",
    "wof:placetype":"venue"
},
  "geometry": {"coordinates":[16.3818721771,48.2206993103],"type":"Point"}
}