{
  "type": "Feature",
  "properties": {
    "iso:country":"AT",
    "sg:address":"Edelsinnstr 2",
    "sg:city":"Wien",
    "sg:orig_category":"Optiker",
    "sg:phone":"+43 1 8134133",
    "sg:postcode":"1120",
    "sg:province":"Wien",
    "sg:website":"medvey.optiker.at",
    "wof:name":"Augenoptik Medvey",
    "wof:placetype":"venue"
},
  "geometry": {"coordinates":[16.3300323486,48.1744918823],"type":"Point"}
}