{
  "type": "Feature",
  "properties": {
    "addr:full":"Erbpostg 7 Wien Wien 1210",
    "addr:housenumber":"7",
    "addr:postcode":"1210",
    "addr:street":"Erbpostg",
    "iso:country":"AT",
    "sg:address":"Erbpostg 7",
    "sg:city":"Wien",
    "sg:orig_category":"Massagen",
    "sg:phone":"+43 1 2928888",
    "sg:postcode":"1210",
    "sg:province":"Wien",
    "wof:name":"Strasser Johanna - Shiatzu",
    "wof:placetype":"venue"
},
  "geometry": {"coordinates":[16.4209136963,48.3038024902],"type":"Point"}
}