{
  "type": "Feature",
  "properties": {
    "addr:full":"Bahnstr 1 Parndorf Burgenland 7111",
    "addr:housenumber":"1",
    "addr:postcode":"7111",
    "addr:street":"Bahnstr",
    "iso:country":"AT",
    "sg:address":"Bahnstr 1",
    "sg:city":"Parndorf",
    "sg:orig_category":"Werbeagenturen",
    "sg:phone":"+43 650 9469883",
    "sg:postcode":"7111",
    "sg:province":"Burgenland",
    "wof:name":"Steger Christoph",
    "wof:placetype":"venue"
},
  "geometry": {"coordinates":[16.8592357635,47.9914474487],"type":"Point"}
}