{
  "type": "Feature",
  "properties": {
    "addr:full":"Jakobstr 18 Neustadtl Nieder\u00f6sterreich 3323",
    "addr:housenumber":"18",
    "addr:postcode":"3323",
    "addr:street":"Jakobstr",
    "iso:country":"AT",
    "sg:address":"Jakobstr 18",
    "sg:city":"Neustadtl",
    "sg:orig_category":"Banken U Sparkassen",
    "sg:phone":"+43 4374 7122500",
    "sg:postcode":"3323",
    "sg:province":"Nieder\u00f6sterreich",
    "wof:name":"Raiffeisenbank Amstetten-Ybbs regGenmbH",
    "wof:placetype":"venue"
},
  "geometry": {"coordinates":[20.3330097198,47.9864997864],"type":"Point"}
}