{
  "type": "Feature",
  "properties": {
    "iso:country":"AT",
    "sg:address":"Rudolf-von-Alt-Pl 4/4",
    "sg:city":"Wien",
    "sg:orig_category":"Steuerberatung",
    "sg:phone":"+43 4317 1321010",
    "sg:postcode":"1030",
    "sg:province":"Wien",
    "sg:website":"kretzschmar.at",
    "wof:name":"Kretzschmar Renate Mag",
    "wof:placetype":"venue"
},
  "geometry": {"coordinates":[16.3931121826,48.2066307068],"type":"Point"}
}