{
  "type": "Feature",
  "properties": {
    "addr:full":"Hauptstr 16 Maria Ellend Nieder\u00f6sterreich 2402",
    "addr:housenumber":"16",
    "addr:postcode":"2402",
    "addr:street":"Hauptstr",
    "iso:country":"AT",
    "sg:address":"Hauptstr 16",
    "sg:city":"Maria Ellend",
    "sg:orig_category":"Pensionen / Privatzimmer",
    "sg:phone":"+43 4322 3280037",
    "sg:postcode":"2402",
    "sg:province":"Nieder\u00f6sterreich",
    "wof:name":"Sailer Andreas",
    "wof:placetype":"venue"
},
  "geometry": {"coordinates":[16.7158679962,48.1177368164],"type":"Point"}
}