{
  "type": "Feature",
  "properties": {
    "addr:full":"Hauptstr 34 Ebensee Ober\u00f6sterreich 4802",
    "addr:housenumber":"34",
    "addr:postcode":"4802",
    "addr:street":"Hauptstr",
    "iso:country":"AT",
    "sg:address":"Hauptstr 34",
    "sg:city":"Ebensee",
    "sg:orig_category":"Tourismusinformation U -Organisationen",
    "sg:phone":"+43 6133 8016",
    "sg:postcode":"4802",
    "sg:province":"Ober\u00f6sterreich",
    "wof:name":"Tourismusb\u00fcro Ebensee",
    "wof:placetype":"venue"
},
  "geometry": {"coordinates":[13.774353981,47.8119697571],"type":"Point"}
}