{
  "type": "Feature",
  "properties": {
    "addr:full":"Lehen 1 Mank Nieder\u00f6sterreich 3240",
    "addr:housenumber":"1",
    "addr:postcode":"3240",
    "addr:street":"Lehen;Niederoesterreich",
    "iso:country":"AT",
    "sg:address":"Lehen 1",
    "sg:city":"Mank",
    "sg:classifiers":[
        {
            "category":"Autos & Motor Vehicles",
            "subcategory":"Recreational Vehicle Sales",
            "type":"Retail Goods"
        }
    ],
    "sg:phone":"+43 2755 40030",
    "sg:postcode":"3240",
    "sg:province":"Nieder\u00f6sterreich",
    "sg:tags":[
        "machine",
        "equipment",
        "tool",
        "automation"
    ],
    "sg:website":"inaut.net",
    "wof:name":"INAUT Automatisierungstechnik GMBH",
    "wof:placetype":"venue"
},
  "geometry": {"coordinates":[15.3422441483,48.0904884338],"type":"Point"}
}