{
  "type": "Feature",
  "properties": {
    "iso:country":"AT",
    "sg:address":"Hauptstr 104",
    "sg:city":"Eben im Pongau",
    "sg:orig_category":"\u00c3\u201enderungsschneidereien",
    "sg:phone":"+43 4364 588538",
    "sg:postcode":"5531",
    "sg:province":"Salzburg",
    "wof:name":"Huber Sylvia",
    "wof:placetype":"venue"
},
  "geometry": {"coordinates":[13.3952989578,47.4079742432],"type":"Point"}
}