{
  "type": "Feature",
  "properties": {
    "addr:full":"In der Hofm\u00fchle 4 Haid Ober\u00f6sterreich 4053",
    "addr:housenumber":"4",
    "addr:postcode":"4053",
    "addr:street":"In Der Hofmuehle",
    "iso:country":"AT",
    "sg:address":"In der Hofm\u00fchle 4",
    "sg:city":"Haid",
    "sg:classifiers":[
        {
            "category":"Wholesale",
            "subcategory":"Vending Machines",
            "type":"Manufacturing & Wholesale Goods"
        }
    ],
    "sg:phone":"+43 4372 2757730",
    "sg:postcode":"4053",
    "sg:province":"Ober\u00f6sterreich",
    "sg:tags":[
        "filter"
    ],
    "sg:website":"filcom.at",
    "wof:name":"Filcom Umwelttechnologie HandelsgesmbH",
    "wof:placetype":"venue"
},
  "geometry": {"coordinates":[14.2510099411,48.2047348022],"type":"Point"}
}