{
  "type": "Feature",
  "properties": {
    "iso:country":"AT",
    "sg:address":"Nr 106",
    "sg:city":"Satteins",
    "sg:orig_category":"Banken U Sparkassen",
    "sg:phone":"+43 4355 242119",
    "sg:postcode":"6822",
    "sg:province":"Vorarlberg",
    "wof:name":"Raiffeisenbank Frastanz-Satteins regGenmbH",
    "wof:placetype":"venue"
},
  "geometry": {"coordinates":[8.9956197739,45.9606285095],"type":"Point"}
}