{
  "type": "Feature",
  "properties": {
    "addr:full":"Bahnhofstr 8 Klagenfurt K\u00e4rnten 9020",
    "addr:housenumber":"8",
    "addr:postcode":"9020",
    "addr:street":"Bahnhofstr;Kaernten",
    "iso:country":"AT",
    "sg:address":"Bahnhofstr 8",
    "sg:city":"Klagenfurt",
    "sg:orig_category":"Pelze U Pelzwaren",
    "sg:phone":"+43 463 55076",
    "sg:postcode":"9020",
    "sg:province":"K\u00e4rnten",
    "wof:name":"Scala Pelze & Leder",
    "wof:placetype":"venue"
},
  "geometry": {"coordinates":[14.3103218079,46.6253356934],"type":"Point"}
}