{
  "type": "Feature",
  "properties": {
    "iso:country":"AT",
    "sg:address":"Keplerpl 11",
    "sg:city":"Wien",
    "sg:orig_category":"Optiker",
    "sg:phone":"+43 1 6043782",
    "sg:postcode":"1100",
    "sg:province":"Wien",
    "wof:name":"Pearle \u00f6sterreich GmbH",
    "wof:placetype":"venue"
},
  "geometry": {"coordinates":[16.3764381409,48.1790161133],"type":"Point"}
}