{
  "type": "Feature",
  "properties": {
    "addr:full":"Leopold-Leuthner-Str 9 Haugsdorf Nieder\u00f6sterreich 2054",
    "addr:housenumber":"9",
    "addr:postcode":"2054",
    "addr:street":"Leopold-Leuthner-Str",
    "iso:country":"AT",
    "sg:address":"Leopold-Leuthner-Str 9",
    "sg:city":"Haugsdorf",
    "sg:orig_category":"Polizei U Gendarmerie",
    "sg:phone":"+43 4359 1333414",
    "sg:postcode":"2054",
    "sg:province":"Nieder\u00f6sterreich",
    "wof:name":"Gendarmerie",
    "wof:placetype":"venue"
},
  "geometry": {"coordinates":[16.073633194,48.7089767456],"type":"Point"}
}