{
  "type": "Feature",
  "properties": {
    "addr:full":"Welser Str 35 Leonding Ober\u00f6sterreich 4060",
    "addr:postcode":"4060",
    "addr:street":"Str 35",
    "iso:country":"AT",
    "sg:address":"Welser Str 35",
    "sg:city":"Leonding",
    "sg:orig_category":"Apotheken",
    "sg:phone":"+43 732 672066",
    "sg:postcode":"4060",
    "sg:province":"Ober\u00f6sterreich",
    "wof:name":"Apotheke im Park",
    "wof:placetype":"venue"
},
  "geometry": {"coordinates":[14.2662982941,48.2683563232],"type":"Point"}
}