{
  "type": "Feature",
  "properties": {
    "addr:full":"Franz-Fischer-Str 33 Innsbruck Tirol 6020",
    "addr:housenumber":"33",
    "addr:postcode":"6020",
    "addr:street":"Franz-Fischer-Str;Tirol",
    "iso:country":"AT",
    "sg:address":"Franz-Fischer-Str 33",
    "sg:city":"Innsbruck",
    "sg:orig_category":"Behinderungen / Leben Mit Behinderungen",
    "sg:phone":"+43 4351 2576925",
    "sg:postcode":"6020",
    "sg:province":"Tirol",
    "wof:name":"\u00f6ZIV - \u00f6sterreichischer Zivil-Invalidenverband Bezirksb\u00fcro",
    "wof:placetype":"venue"
},
  "geometry": {"coordinates":[11.3897972107,47.2582969666],"type":"Point"}
}