{
  "type": "Feature",
  "properties": {
    "addr:full":"Hauptpl 3 Judenburg Steiermark 8750",
    "addr:housenumber":"3",
    "addr:postcode":"8750",
    "addr:street":"Hauptpl",
    "iso:country":"AT",
    "sg:address":"Hauptpl 3",
    "sg:city":"Judenburg",
    "sg:orig_category":"Tabaktrafiken",
    "sg:phone":"+43 3572 82851",
    "sg:postcode":"8750",
    "sg:province":"Steiermark",
    "wof:name":"Liebenberger Renate",
    "wof:placetype":"venue"
},
  "geometry": {"coordinates":[14.660569191,47.1692085266],"type":"Point"}
}