{
  "type": "Feature",
  "properties": {
    "addr:full":"Reisnerstr. 55 Wien Wien 1030",
    "addr:housenumber":"55",
    "addr:postcode":"1030",
    "addr:street":"Reisnerstr.",
    "iso:country":"AT",
    "sg:address":"Reisnerstr. 55",
    "sg:city":"Wien",
    "sg:classifiers":[
        {
            "category":"Professional",
            "subcategory":"Business Services",
            "type":"Services"
        }
    ],
    "sg:phone":"+43 4317 156692",
    "sg:postcode":"1030",
    "sg:province":"Wien",
    "sg:tags":[
        "advice"
    ],
    "wof:name":"K\u00d6NIGLICH NORWEGISCHE BOTSCHAFT",
    "wof:placetype":"venue"
},
  "geometry": {"coordinates":[16.3838920593,48.1964302063],"type":"Point"}
}