{
  "type": "Feature",
  "properties": {
    "iso:country":"AT",
    "sg:address":"1. Haidequerstr 3-5",
    "sg:city":"Wien",
    "sg:orig_category":"Elektroinstallationsmaterial",
    "sg:phone":"+43 4317 60760",
    "sg:postcode":"1110",
    "sg:province":"Wien",
    "sg:website":"dietzel-univolt.com",
    "wof:name":"Dietzel GmbH",
    "wof:placetype":"venue"
},
  "geometry": {"coordinates":[16.4300956726,48.1828536987],"type":"Point"}
}