{
  "type": "Feature",
  "properties": {
    "addr:full":"Stifterg 8 Gm\u00fcnd Nieder\u00f6sterreich 3950",
    "addr:housenumber":"8",
    "addr:postcode":"3950",
    "addr:street":"Stifterg;Niederoesterreich",
    "iso:country":"AT",
    "sg:address":"Stifterg 8",
    "sg:city":"Gm\u00fcnd",
    "sg:orig_category":"Tabaktrafiken",
    "sg:phone":"+43 2852 52534",
    "sg:postcode":"3950",
    "sg:province":"Nieder\u00f6sterreich",
    "wof:name":"Winkler Harald",
    "wof:placetype":"venue"
},
  "geometry": {"coordinates":[14.9708833694,48.7598266602],"type":"Point"}
}