{
  "type": "Feature",
  "properties": {
    "addr:full":"Rottweilerstr 14 Imst Tirol 6460",
    "addr:housenumber":"14",
    "addr:postcode":"6460",
    "addr:street":"Rottweilerstr;Tirol",
    "iso:country":"AT",
    "sg:address":"Rottweilerstr 14",
    "sg:city":"Imst",
    "sg:orig_category":"Installationsunternehmen",
    "sg:phone":"+43 5412 66221",
    "sg:postcode":"6460",
    "sg:province":"Tirol",
    "wof:name":"Fl\u00fcr & Pr\u00f6ssel OEG",
    "wof:placetype":"venue"
},
  "geometry": {"coordinates":[10.7299718857,47.2334365845],"type":"Point"}
}