{
  "type": "Feature",
  "properties": {
    "addr:full":"H\u00fctteldorfer Strasse 81a Wien Wien 1150",
    "addr:housenumber":"81a",
    "addr:postcode":"1150",
    "addr:street":"Huetteldorfer Strasse",
    "iso:country":"AT",
    "sg:address":"H\u00fctteldorfer Strasse 81a",
    "sg:city":"Wien",
    "sg:classifiers":[
        {
            "category":"Home & Garden",
            "subcategory":"Building Materials",
            "type":"Retail Goods"
        }
    ],
    "sg:phone":"+43 1 9821007",
    "sg:postcode":"1150",
    "sg:province":"Wien",
    "sg:tags":[
        "installation",
        "electric"
    ],
    "wof:name":"Erwin Lindner",
    "wof:placetype":"venue"
},
  "geometry": {"coordinates":[16.3320903778,48.2006416321],"type":"Point"}
}