{
  "type": "Feature",
  "properties": {
    "addr:full":"Anton-Melzer-Str 10 Innsbruck Tirol 6020",
    "addr:housenumber":"10",
    "addr:postcode":"6020",
    "addr:street":"Anton-Melzer-Str;Tirol",
    "iso:country":"AT",
    "sg:address":"Anton-Melzer-Str 10",
    "sg:city":"Innsbruck",
    "sg:orig_category":"Tankstellen",
    "sg:phone":"+43 4351 2580354",
    "sg:postcode":"6020",
    "sg:province":"Tirol",
    "wof:name":"OMV AG",
    "wof:placetype":"venue"
},
  "geometry": {"coordinates":[11.3948774338,47.2564544678],"type":"Point"}
}