{
  "type": "Feature",
  "properties": {
    "addr:full":"Hauptpl 1 Prottes Nieder\u00f6sterreich 2242",
    "addr:housenumber":"1",
    "addr:postcode":"2242",
    "addr:street":"Hauptpl",
    "iso:country":"AT",
    "sg:address":"Hauptpl 1",
    "sg:city":"Prottes",
    "sg:orig_category":"Gemeinden",
    "sg:phone":"+43 2282 2182",
    "sg:postcode":"2242",
    "sg:province":"Nieder\u00f6sterreich",
    "wof:name":"Gemeindeamt Prottes",
    "wof:placetype":"venue"
},
  "geometry": {"coordinates":[16.7390365601,48.3860015869],"type":"Point"}
}