{
  "type": "Feature",
  "properties": {
    "addr:full":"Wiener Strasse 219 Spillern Nieder\u00f6sterreich 2104",
    "addr:housenumber":"219",
    "addr:postcode":"2104",
    "addr:street":"Wiener Strasse",
    "iso:country":"AT",
    "sg:address":"Wiener Strasse 219",
    "sg:city":"Spillern",
    "sg:orig_category":"Arbors For Shell Reamers, Countersinks And Counterbores, Insertion Plugs",
    "sg:phone":"+43 2266 803480",
    "sg:postcode":"2104",
    "sg:province":"Nieder\u00f6sterreich",
    "wof:name":"Josef Haas Ges.m.b.H.",
    "wof:placetype":"venue"
},
  "geometry": {"coordinates":[16.2727203369,48.3761405945],"type":"Point"}
}