{
  "type": "Feature",
  "properties": {
    "addr:full":"Hauptstr 16 Linz Ober\u00f6sterreich 4040",
    "addr:housenumber":"16",
    "addr:postcode":"4040",
    "addr:street":"Hauptstr",
    "iso:country":"AT",
    "sg:address":"Hauptstr 16",
    "sg:city":"Linz",
    "sg:orig_category":"Friseure U Frisiersalons",
    "sg:phone":"+43 732 719582",
    "sg:postcode":"4040",
    "sg:province":"Ober\u00f6sterreich",
    "wof:name":"Coiffeur Huemer",
    "wof:placetype":"venue"
},
  "geometry": {"coordinates":[14.2834043503,48.3110198975],"type":"Point"}
}