{
  "type": "Feature",
  "properties": {
    "addr:full":"Bergstr 2 Haslach an der M\u00fchl Ober\u00f6sterreich 4170",
    "addr:housenumber":"2",
    "addr:postcode":"4170",
    "addr:street":"Bergstr;Oberoesterreich",
    "iso:country":"AT",
    "sg:address":"Bergstr 2",
    "sg:city":"Haslach an der M\u00fchl",
    "sg:orig_category":"Installationsunternehmen",
    "sg:phone":"+43 7289 715750",
    "sg:postcode":"4170",
    "sg:province":"Ober\u00f6sterreich",
    "wof:name":"Lauss Wilfried GesmbH & Co KG",
    "wof:placetype":"venue"
},
  "geometry": {"coordinates":[14.0414466858,48.5785179138],"type":"Point"}
}