{
  "type": "Feature",
  "properties": {
    "iso:country":"AT",
    "sg:address":"Leberstr 122",
    "sg:city":"Wien",
    "sg:orig_category":"Holdinggesellschaften",
    "sg:phone":"+43 1 74095",
    "sg:postcode":"1110",
    "sg:province":"Wien",
    "wof:name":"Bohmann LiegenschaftsverwaltungsgesmbH",
    "wof:placetype":"venue"
},
  "geometry": {"coordinates":[16.4113960266,48.1680297852],"type":"Point"}
}