{
  "type": "Feature",
  "properties": {
    "iso:country":"AT",
    "sg:address":"Blumensteinstr. 1",
    "sg:city":"Salzburg",
    "sg:classifiers":[
        {
            "category":"Professional",
            "subcategory":"Printing & Photocopies",
            "type":"Services"
        }
    ],
    "sg:phone":"+43 4366 2642879",
    "sg:postcode":"5020",
    "sg:province":"Salzburg",
    "wof:name":"JORDIS KG",
    "wof:placetype":"venue"
},
  "geometry": {"coordinates":[13.0605516434,47.8010597229],"type":"Point"}
}