{
  "type": "Feature",
  "properties": {
    "iso:country":"AT",
    "sg:address":"S\u00f6llheimer Berg 4",
    "sg:city":"Hallwang",
    "sg:classifiers":[
        {
            "category":"Professional",
            "subcategory":"Art Services",
            "type":"Services"
        }
    ],
    "sg:phone":"+43 662 660103",
    "sg:postcode":"5300",
    "sg:province":"Salzburg",
    "sg:tags":[
        "designer"
    ],
    "wof:name":"Klor Nora",
    "wof:placetype":"venue"
},
  "geometry": {"coordinates":[13.0793266296,47.8398132324],"type":"Point"}
}