{
  "type": "Feature",
  "properties": {
    "iso:country":"AT",
    "sg:address":"Hauptpl 3/18",
    "sg:city":"Tulln an der Donau",
    "sg:orig_category":"Immobilienmakler",
    "sg:phone":"+43 2272 666360",
    "sg:postcode":"3430",
    "sg:province":"Nieder\u00f6sterreich",
    "wof:name":"Immobilien Andrea Riedl GmbH",
    "wof:placetype":"venue"
},
  "geometry": {"coordinates":[16.0523509979,48.3309402466],"type":"Point"}
}