{
  "type": "Feature",
  "properties": {
    "addr:full":"Gaizwiesweg 8 Anthering Salzburg 5102",
    "addr:housenumber":"8",
    "addr:postcode":"5102",
    "addr:street":"Gaizwiesweg;Salzburg",
    "iso:country":"AT",
    "sg:address":"Gaizwiesweg 8",
    "sg:city":"Anthering",
    "sg:orig_category":"Weiterbildungsinstitute M Allg U Berufl Bildungsangebot",
    "sg:phone":"+43 4366 43602095",
    "sg:postcode":"5102",
    "sg:province":"Salzburg",
    "wof:name":"LIVE Training Claudia Thaller",
    "wof:placetype":"venue"
},
  "geometry": {"coordinates":[13.0149154663,47.8777236938],"type":"Point"}
}