{
  "type": "Feature",
  "properties": {
    "addr:full":"Tragweiner Str 12 Pregarten Ober\u00f6sterreich 4230",
    "addr:postcode":"4230",
    "addr:street":"Str 12",
    "iso:country":"AT",
    "sg:address":"Tragweiner Str 12",
    "sg:city":"Pregarten",
    "sg:orig_category":"Sonnenstudios",
    "sg:phone":"+43 7236 7939",
    "sg:postcode":"4230",
    "sg:province":"Ober\u00f6sterreich",
    "wof:name":"Lucky-Sun",
    "wof:placetype":"venue"
},
  "geometry": {"coordinates":[14.5316877365,48.3544578552],"type":"Point"}
}