{
  "type": "Feature",
  "properties": {
    "addr:full":"H\u00fcttenberger Str 1 Br\u00fcckl K\u00e4rnten 9371",
    "addr:housenumber":"1",
    "addr:postcode":"9371",
    "addr:street":"Str;Kaernten",
    "iso:country":"AT",
    "sg:address":"H\u00fcttenberger Str 1",
    "sg:city":"Br\u00fcckl",
    "sg:orig_category":"Banken U Sparkassen",
    "sg:phone":"+43 4342 1422230",
    "sg:postcode":"9371",
    "sg:province":"K\u00e4rnten",
    "wof:name":"Bankomat d Raiffeisenbank Br\u00fcckl-Eberstein-Klein St Paul-Waisenberg regGenmbH",
    "wof:placetype":"venue"
},
  "geometry": {"coordinates":[168.71675109860001,-44.8405303955],"type":"Point"}
}