{
  "type": "Feature",
  "properties": {
    "iso:country":"AT",
    "sg:address":"Rohrbacher Str 4",
    "sg:city":"Helfenberg",
    "sg:orig_category":"Non-Classified Establishments",
    "sg:phone":"+43 7216 6230",
    "sg:postcode":"4184",
    "sg:province":"Ober\u00f6sterreich",
    "wof:name":"Pfarramt Helfenberg",
    "wof:placetype":"venue"
},
  "geometry": {"coordinates":[14.141658783,48.5420913696],"type":"Point"}
}