{
  "type": "Feature",
  "properties": {
    "iso:country":"AT",
    "sg:address":"Wilhelminenstr 66",
    "sg:city":"Wien",
    "sg:orig_category":"Elektroinstallationsunternehmen",
    "sg:phone":"+43 4314 861358",
    "sg:postcode":"1160",
    "sg:province":"Wien",
    "sg:website":"stoess.at",
    "wof:name":"St\u00f6ss GesmbH",
    "wof:placetype":"venue"
},
  "geometry": {"coordinates":[16.3121681213,48.217250824],"type":"Point"}
}