{
  "type": "Feature",
  "properties": {
    "addr:full":"Wiener Str 360 Sommerein Nieder\u00f6sterreich 2453",
    "addr:housenumber":"360;2453",
    "addr:street":"Sommerein Niederoesterreich",
    "iso:country":"AT",
    "sg:address":"Wiener Str 360",
    "sg:city":"Sommerein",
    "sg:orig_category":"Non-Classified Establishments",
    "sg:phone":"+43 2168 631300",
    "sg:postcode":"2453",
    "sg:province":"Nieder\u00f6sterreich",
    "wof:name":"Wallenstein-Kaserne",
    "wof:placetype":"venue"
},
  "geometry": {"coordinates":[16.658870697,47.9908905029],"type":"Point"}
}