{
  "type": "Feature",
  "properties": {
    "iso:country":"AT",
    "sg:address":"Nr 44",
    "sg:city":"Kapfenstein",
    "sg:orig_category":"Pensionen / Privatzimmer",
    "sg:phone":"+43 3157 2566",
    "sg:postcode":"8353",
    "sg:province":"Steiermark",
    "wof:name":"Sitzwohl Maria",
    "wof:placetype":"venue"
},
  "geometry": {"coordinates":[15.9740009308,46.8857727051],"type":"Point"}
}