{
  "type": "Feature",
  "properties": {
    "addr:full":"Ischler Str 397 Strobl Salzburg 5350",
    "addr:housenumber":"397",
    "addr:postcode":"5350",
    "addr:street":"Str;Salzburg",
    "iso:country":"AT",
    "sg:address":"Ischler Str 397",
    "sg:city":"Strobl",
    "sg:orig_category":"Fleischhauereien",
    "sg:phone":"+43 6137 5226",
    "sg:postcode":"5350",
    "sg:province":"Salzburg",
    "wof:name":"Englj\u00e4hringer Friedrich",
    "wof:placetype":"venue"
},
  "geometry": {"coordinates":[13.4847316742,47.7146072388],"type":"Point"}
}