{
  "type": "Feature",
  "properties": {
    "iso:country":"AT",
    "sg:address":"S\u00e4gerstr 45",
    "sg:city":"Lustenau",
    "sg:orig_category":"Metallbau",
    "sg:phone":"+43 4355 7789996",
    "sg:postcode":"6890",
    "sg:province":"Vorarlberg",
    "sg:website":"neuko-metallbau.at",
    "wof:name":"NEUKO Netzer & Kobelt OEG",
    "wof:placetype":"venue"
},
  "geometry": {"coordinates":[9.673822403,47.4239654541],"type":"Point"}
}