{
  "type": "Feature",
  "properties": {
    "addr:full":"Bahng 30 Wiener Neustadt Nieder\u00f6sterreich 2700",
    "addr:housenumber":"30",
    "addr:postcode":"2700",
    "addr:street":"Bahng",
    "iso:country":"AT",
    "sg:address":"Bahng 30",
    "sg:city":"Wiener Neustadt",
    "sg:orig_category":"Damenmoden",
    "sg:phone":"+43 2622 23457",
    "sg:postcode":"2700",
    "sg:province":"Nieder\u00f6sterreich",
    "wof:name":"Rumpler Franz & Co Inh Nitzlader Edith",
    "wof:placetype":"venue"
},
  "geometry": {"coordinates":[16.2404022217,47.8111419678],"type":"Point"}
}