{
  "type": "Feature",
  "properties": {
    "addr:full":"Nr 25 Hollersbach im Pinzgau Salzburg 5731",
    "addr:postcode":"5731",
    "addr:street":"Nr 25;Salzburg",
    "iso:country":"AT",
    "sg:address":"Nr 25",
    "sg:city":"Hollersbach im Pinzgau",
    "sg:orig_category":"Banken U Sparkassen",
    "sg:phone":"+43 4365 6282140",
    "sg:postcode":"5731",
    "sg:province":"Salzburg",
    "wof:name":"Bankomat d Raiffeisenkasse Mittersill-Hollersbach-Stuhlfelden regGenmbH",
    "wof:placetype":"venue"
},
  "geometry": {"coordinates":[12.4197301865,47.2750968933],"type":"Point"}
}