{
  "type": "Feature",
  "properties": {
    "addr:full":"Resselg 17 Graz Steiermark 8020",
    "addr:housenumber":"17",
    "addr:postcode":"8020",
    "addr:street":"Resselg",
    "iso:country":"AT",
    "sg:address":"Resselg 17",
    "sg:city":"Graz",
    "sg:orig_category":"Automaten",
    "sg:phone":"+43 316 5748440",
    "sg:postcode":"8020",
    "sg:province":"Steiermark",
    "wof:name":"Polanz H GesmbH & Co KG",
    "wof:placetype":"venue"
},
  "geometry": {"coordinates":[15.4085702896,47.0827827454],"type":"Point"}
}