{
  "type": "Feature",
  "properties": {
    "addr:full":"Saalachstr 51 Salzburg Salzburg 5020",
    "addr:housenumber":"51",
    "addr:postcode":"5020",
    "addr:street":"Saalachstr;Salzburg",
    "iso:country":"AT",
    "sg:address":"Saalachstr 51",
    "sg:city":"Salzburg",
    "sg:orig_category":"Sprechanlagen",
    "sg:phone":"+43 662 856225",
    "sg:postcode":"5020",
    "sg:province":"Salzburg",
    "wof:name":"Commend International GmbH",
    "wof:placetype":"venue"
},
  "geometry": {"coordinates":[12.9921064377,47.8312606812],"type":"Point"}
}