{
  "type": "Feature",
  "properties": {
    "iso:country":"AT",
    "sg:address":"Saalachstr 51",
    "sg:city":"Salzburg",
    "sg:orig_category":"Sprechanlagen",
    "sg:phone":"+43 662 856225",
    "sg:postcode":"5020",
    "sg:province":"Salzburg",
    "wof:name":"Commend International GmbH",
    "wof:placetype":"venue"
},
  "geometry": {"coordinates":[12.9921064377,47.8312606812],"type":"Point"}
}