{
  "type": "Feature",
  "properties": {
    "addr:full":"M\u00fchlbachweg 9 Serfaus Tirol 6534",
    "addr:housenumber":"9",
    "addr:postcode":"6534",
    "addr:street":"Muehlbachweg;Tirol",
    "iso:country":"AT",
    "sg:address":"M\u00fchlbachweg 9",
    "sg:city":"Serfaus",
    "sg:orig_category":"Appartements / Ferienwohnungen",
    "sg:phone":"+43 4354 766373",
    "sg:postcode":"6534",
    "sg:province":"Tirol",
    "wof:name":"Haus Waldblick",
    "wof:placetype":"venue"
},
  "geometry": {"coordinates":[10.6053447723,47.0386734009],"type":"Point"}
}