{
  "type": "Feature",
  "properties": {
    "addr:full":"Angersdlg 131 Flaurling Tirol 6403",
    "addr:housenumber":"131",
    "addr:postcode":"6403",
    "addr:street":"Flaurling Tirol",
    "iso:country":"AT",
    "sg:address":"Angersdlg 131",
    "sg:city":"Flaurling",
    "sg:orig_category":"Pumpen, Dosieranlagen U -Pumpen, Elektroinstallationsunternehmen",
    "sg:phone":"+43 4366 42535592",
    "sg:postcode":"6403",
    "sg:province":"Tirol",
    "sg:website":"efmatic.at",
    "wof:name":"EFMATIC Furtner GmbH - GRI for Austria",
    "wof:placetype":"venue"
},
  "geometry": {"coordinates":[11.1237049103,47.2917556763],"type":"Point"}
}