{
  "type": "Feature",
  "properties": {
    "iso:country":"AT",
    "sg:address":"Redtenbacherg 6",
    "sg:city":"Wien",
    "sg:classifiers":[
        {
            "category":"Restaurant",
            "type":"Food & Drink"
        }
    ],
    "sg:phone":"+43 1 4899599",
    "sg:postcode":"1160",
    "sg:province":"Wien",
    "wof:name":"Kupferpfandl",
    "wof:placetype":"venue"
},
  "geometry": {"coordinates":[16.3149585724,48.2139053345],"type":"Point"}
}