{
  "type": "Feature",
  "properties": {
    "addr:full":"Eisengasse 41 Dornbirn Vorarlberg 6850",
    "addr:housenumber":"41",
    "addr:postcode":"6850",
    "addr:street":"Eisengasse",
    "iso:country":"AT",
    "sg:address":"Eisengasse 41",
    "sg:city":"Dornbirn",
    "sg:classifiers":[
        {
            "category":"Professional",
            "subcategory":"Accounting & Tax Preparation",
            "type":"Services"
        }
    ],
    "sg:phone":"+43 5572 258120",
    "sg:postcode":"6850",
    "sg:province":"Vorarlberg",
    "sg:tags":[
        "application",
        "software",
        "cad"
    ],
    "wof:name":"Steco Data Computers & Systems Ing. Anton Stepanek",
    "wof:placetype":"venue"
},
  "geometry": {"coordinates":[9.7467479706,47.4191703796],"type":"Point"}
}