{
  "type": "Feature",
  "properties": {
    "iso:country":"AT",
    "sg:address":"Dorfstr 48",
    "sg:city":"Leibnitz",
    "sg:orig_category":"Schmieden U Schmiedeeisenelemente",
    "sg:phone":"+43 4334 5282697",
    "sg:postcode":"8430",
    "sg:province":"Steiermark",
    "wof:name":"Juranek Wilhelm",
    "wof:placetype":"venue"
},
  "geometry": {"coordinates":[15.5216016769,46.809425354],"type":"Point"}
}