{
  "type": "Feature",
  "properties": {
    "addr:full":"Rathausstr 19 Eggenburg Nieder\u00f6sterreich 3730",
    "addr:housenumber":"19",
    "addr:postcode":"3730",
    "addr:street":"Rathausstr",
    "iso:country":"AT",
    "sg:address":"Rathausstr 19",
    "sg:city":"Eggenburg",
    "sg:orig_category":"Textilwaren / Einzelhandel",
    "sg:phone":"+43 2984 3031",
    "sg:postcode":"3730",
    "sg:province":"Nieder\u00f6sterreich",
    "wof:name":"Scheidl Wolfgang",
    "wof:placetype":"venue"
},
  "geometry": {"coordinates":[15.8198575974,48.6437492371],"type":"Point"}
}