{
  "type": "Feature",
  "properties": {
    "addr:full":"Sonnwiesenweg 3a Hopfgarten im Brixental Tirol 6361",
    "addr:housenumber":"3a",
    "addr:postcode":"6361",
    "addr:street":"Sonnwiesenweg;Tirol",
    "iso:country":"AT",
    "sg:address":"Sonnwiesenweg 3a",
    "sg:city":"Hopfgarten im Brixental",
    "sg:orig_category":"Offsetdruckereien",
    "sg:phone":"+43 5335 22730",
    "sg:postcode":"6361",
    "sg:province":"Tirol",
    "wof:name":"Salvendruck GmbH",
    "wof:placetype":"venue"
},
  "geometry": {"coordinates":[12.1574897766,47.4497718811],"type":"Point"}
}