{
  "type": "Feature",
  "properties": {
    "addr:full":"Hochlitten Riefensberg Vorarlberg 6943",
    "addr:housenumber":"6943",
    "iso:country":"AT",
    "sg:address":"Hochlitten",
    "sg:city":"Riefensberg",
    "sg:orig_category":"Bergbahnen",
    "sg:phone":"+43 4355 138239",
    "sg:postcode":"6943",
    "sg:province":"Vorarlberg",
    "wof:name":"Schilifte Hochlitten",
    "wof:placetype":"venue"
},
  "geometry": {"coordinates":[9.9783296585,47.5083694458],"type":"Point"}
}