{
  "type": "Feature",
  "properties": {
    "addr:full":"Hauptplatz 24 Hadersdorf am Kamp Nieder\u00f6sterreich 3493",
    "addr:housenumber":"24",
    "addr:postcode":"3493",
    "addr:street":"Hauptplatz;Niederoesterreich",
    "iso:country":"AT",
    "sg:address":"Hauptplatz 24",
    "sg:city":"Hadersdorf am Kamp",
    "sg:classifiers":[
        {
            "category":"Farming",
            "subcategory":"Fish & Marine Products",
            "type":"Manufacturing & Wholesale Goods"
        }
    ],
    "sg:phone":"+43 2735 5563",
    "sg:postcode":"3493",
    "sg:province":"Nieder\u00f6sterreich",
    "sg:tags":[
        "ceramic"
    ],
    "sg:website":"keramik-kail.at",
    "wof:name":"Gerlinde Kail",
    "wof:placetype":"venue"
},
  "geometry": {"coordinates":[15.7212705612,48.45835495],"type":"Point"}
}