{
  "type": "Feature",
  "properties": {
    "addr:full":"Wienerbergstr. 25 B  Wien Wien 1100",
    "addr:housenumber":"25 b",
    "addr:postcode":"1100",
    "addr:street":"Wienerbergstr.",
    "iso:country":"AT",
    "sg:address":"Wienerbergstr. 25 B ",
    "sg:city":"Wien",
    "sg:classifiers":[
        {
            "category":"Utilities",
            "subcategory":"Electric",
            "type":"Services"
        }
    ],
    "sg:phone":"+43 4316 0156",
    "sg:postcode":"1100",
    "sg:province":"Wien",
    "sg:tags":[
        "component",
        "electronic"
    ],
    "wof:name":"FLECK GMBH",
    "wof:placetype":"venue"
},
  "geometry": {"coordinates":[16.3402271271,48.1705436707],"type":"Point"}
}