{
  "type": "Feature",
  "properties": {
    "iso:country":"AT",
    "sg:address":"Galvanistr 4",
    "sg:city":"Linz",
    "sg:orig_category":"Fotografen",
    "sg:phone":"+43 4373 2750860",
    "sg:postcode":"4040",
    "sg:province":"Ober\u00f6sterreich",
    "sg:website":"dall.at",
    "wof:name":"Dall Fotografie",
    "wof:placetype":"venue"
},
  "geometry": {"coordinates":[14.3026676178,48.3326759338],"type":"Point"}
}