{
  "type": "Feature",
  "properties": {
    "iso:country":"AT",
    "sg:address":"Niederalm Untersbergstr 10",
    "sg:city":"Anif",
    "sg:orig_category":"Waren Aller Art",
    "sg:phone":"+43 4362 4672949",
    "sg:postcode":"5081",
    "sg:province":"Salzburg",
    "wof:name":"One and 2 HandelsgesmbH",
    "wof:placetype":"venue"
},
  "geometry": {"coordinates":[13.0639257431,47.7499694824],"type":"Point"}
}