{
  "type": "Feature",
  "properties": {
    "addr:full":"Kremstalstr 90 Traun Ober\u00f6sterreich 4050",
    "addr:housenumber":"90",
    "addr:postcode":"4050",
    "addr:street":"Kremstalstr",
    "iso:country":"AT",
    "sg:address":"Kremstalstr 90",
    "sg:city":"Traun",
    "sg:orig_category":"Beratungsstellen",
    "sg:phone":"+43 7229 62533",
    "sg:postcode":"4050",
    "sg:province":"Ober\u00f6sterreich",
    "wof:name":"Frauenbetreuungs- und Frauenservicestellen BABSI",
    "wof:placetype":"venue"
},
  "geometry": {"coordinates":[14.233912468,48.2294197083],"type":"Point"}
}