{
  "type": "Feature",
  "properties": {
    "iso:country":"AT",
    "sg:address":"Hernalser Hauptstr 86",
    "sg:city":"Wien",
    "sg:orig_category":"Sonnenstudios",
    "sg:phone":"+43 1 4857686",
    "sg:postcode":"1170",
    "sg:province":"Wien",
    "wof:name":"Sonnenstudio Sunrise",
    "wof:placetype":"venue"
},
  "geometry": {"coordinates":[16.3293056488,48.2185401917],"type":"Point"}
}