{
  "type": "Feature",
  "properties": {
    "iso:country":"AT",
    "sg:address":"Gr\u00f6diger Weg 364",
    "sg:city":"Wals",
    "sg:orig_category":"Tankstellen",
    "sg:phone":"+43 662 854392",
    "sg:postcode":"5071",
    "sg:province":"Salzburg",
    "wof:name":"Leikermoser Mineral\u00f6lhandelsgesmbH",
    "wof:placetype":"venue"
},
  "geometry": {"coordinates":[12.9693145752,47.7897644043],"type":"Point"}
}