{
  "type": "Feature",
  "properties": {
    "addr:full":"Hauptstr 40 Mannersdorf am Leithagebirge Nieder\u00f6sterreich 2452",
    "addr:housenumber":"40",
    "addr:postcode":"2452",
    "addr:street":"Hauptstr",
    "iso:country":"AT",
    "sg:address":"Hauptstr 40",
    "sg:city":"Mannersdorf am Leithagebirge",
    "sg:orig_category":"Boutiquen",
    "sg:phone":"+43 2168 62129",
    "sg:postcode":"2452",
    "sg:province":"Nieder\u00f6sterreich",
    "wof:name":"Boutique Zenk GmbH & Co KG",
    "wof:placetype":"venue"
},
  "geometry": {"coordinates":[16.6024589539,47.9736099243],"type":"Point"}
}