{
  "type": "Feature",
  "properties": {
    "addr:full":"Austeing 30 Graz Steiermark 8020",
    "addr:housenumber":"30",
    "addr:postcode":"8020",
    "addr:street":"Austeing",
    "iso:country":"AT",
    "sg:address":"Austeing 30",
    "sg:city":"Graz",
    "sg:orig_category":"Autoersatzteile",
    "sg:phone":"+43 4366 44336822",
    "sg:postcode":"8020",
    "sg:province":"Steiermark",
    "wof:name":"Sch\u00f6ller Alexander KEG",
    "wof:placetype":"venue"
},
  "geometry": {"coordinates":[15.4198045731,47.0844421387],"type":"Point"}
}