{
  "type": "Feature",
  "properties": {
    "addr:full":"Wildbichler Str 19 Ebbs Tirol 6341",
    "addr:housenumber":"19",
    "addr:postcode":"6341",
    "addr:street":"Str;Tirol",
    "iso:country":"AT",
    "sg:address":"Wildbichler Str 19",
    "sg:city":"Ebbs",
    "sg:classifiers":[
        {
            "category":"Restaurant",
            "type":"Food & Drink"
        }
    ],
    "sg:phone":"+43 5373 42031",
    "sg:postcode":"6341",
    "sg:province":"Tirol",
    "wof:name":"Saliterer Stuben",
    "wof:placetype":"venue"
},
  "geometry": {"coordinates":[12.2146320343,47.6284179688],"type":"Point"}
}