{
  "type": "Feature",
  "properties": {
    "addr:full":"Schmalzg 13 Hopfgarten im Brixental Tirol 6361",
    "addr:housenumber":"13",
    "addr:postcode":"6361",
    "addr:street":"Schmalzg;Tirol",
    "iso:country":"AT",
    "sg:address":"Schmalzg 13",
    "sg:city":"Hopfgarten im Brixental",
    "sg:orig_category":"Folien",
    "sg:phone":"+43 4353 3538070",
    "sg:postcode":"6361",
    "sg:province":"Tirol",
    "sg:website":"samaco.at",
    "wof:name":"SAMACO Werbe- u Industrieverpackungen GmbH",
    "wof:placetype":"venue"
},
  "geometry": {"coordinates":[12.159154892,47.448764801],"type":"Point"}
}