{
  "type": "Feature",
  "properties": {
    "addr:full":"Mostnystr 20 Linz Ober\u00f6sterreich 4040",
    "addr:housenumber":"20",
    "addr:postcode":"4040",
    "addr:street":"Mostnystr",
    "iso:country":"AT",
    "sg:address":"Mostnystr 20",
    "sg:city":"Linz",
    "sg:orig_category":"Autohandel",
    "sg:phone":"+43 4373 27570660",
    "sg:postcode":"4040",
    "sg:province":"Ober\u00f6sterreich",
    "wof:name":"Ford City Linz-AC Auto Vertrieb u Service GesmbH",
    "wof:placetype":"venue"
},
  "geometry": {"coordinates":[14.3164386749,48.328742981],"type":"Point"}
}