{
  "type": "Feature",
  "properties": {
    "iso:country":"AT",
    "sg:address":"Teufenbach 34a",
    "sg:city":"Teufenbach",
    "sg:classifiers":[
        {
            "category":"Home & Garden",
            "subcategory":"Home Furnishings",
            "type":"Retail Goods"
        }
    ],
    "sg:phone":"+43 3582 8395",
    "sg:postcode":"8833",
    "sg:province":"Steiermark",
    "sg:tags":[
        "air-conditioners"
    ],
    "sg:website":"pachlinger.at",
    "wof:name":"Wilfried Pachlinger",
    "wof:placetype":"venue"
},
  "geometry": {"coordinates":[14.3611803055,47.1318092346],"type":"Point"}
}