{
  "type": "Feature",
  "properties": {
    "addr:full":"Danielstr 7 Lermoos Tirol 6631",
    "addr:housenumber":"7",
    "addr:postcode":"6631",
    "addr:street":"Danielstr;Tirol",
    "iso:country":"AT",
    "sg:address":"Danielstr 7",
    "sg:city":"Lermoos",
    "sg:classifiers":[
        {
            "category":"Travel",
            "subcategory":"Hotels & Motels",
            "type":"Entertainment"
        }
    ],
    "sg:phone":"+43 5673 2214",
    "sg:postcode":"6631",
    "sg:province":"Tirol",
    "wof:name":"Hotel Edelwei\u00df",
    "wof:placetype":"venue"
},
  "geometry": {"coordinates":[10.8802995682,47.4026374817],"type":"Point"}
}