{
  "type": "Feature",
  "properties": {
    "iso:country":"AT",
    "sg:address":"Am Corso 108",
    "sg:city":"Reifnitz",
    "sg:classifiers":[
        {
            "category":"Travel",
            "subcategory":"Hotels & Motels",
            "type":"Entertainment"
        }
    ],
    "sg:phone":"+43 4273 22370",
    "sg:postcode":"9081",
    "sg:province":"K\u00e4rnten",
    "wof:name":"Strandhotel Sille",
    "wof:placetype":"venue"
},
  "geometry": {"coordinates":[14.1833629608,46.6064949036],"type":"Point"}
}