{
  "type": "Feature",
  "properties": {
    "addr:full":"Traun Ober\u00f6sterreich 4050",
    "addr:postcode":"4050",
    "iso:country":"AT",
    "sg:city":"Traun",
    "sg:orig_category":"Polizei U Gendarmerie",
    "sg:phone":"+43 4372 29688121",
    "sg:postcode":"4050",
    "sg:province":"Ober\u00f6sterreich",
    "wof:name":"St\u00e4dtische Sicherheitswache Traun",
    "wof:placetype":"venue"
},
  "geometry": {"coordinates":[14.2384881973,48.221572876],"type":"Point"}
}