{
  "type": "Feature",
  "properties": {
    "addr:full":"Waltendorfer Hauptstr 99 Graz Steiermark 8010",
    "addr:housenumber":"99",
    "addr:postcode":"8010",
    "addr:street":"Waltendorfer Hauptstr",
    "iso:country":"AT",
    "sg:address":"Waltendorfer Hauptstr 99",
    "sg:city":"Graz",
    "sg:orig_category":"Lebensmittel / Einzelhandel",
    "sg:phone":"+43 4331 6471025",
    "sg:postcode":"8010",
    "sg:province":"Steiermark",
    "sg:website":"sauer.co.at",
    "wof:name":"Partydienst Sauer",
    "wof:placetype":"venue"
},
  "geometry": {"coordinates":[15.4810466766,47.0669975281],"type":"Point"}
}