{
  "type": "Feature",
  "properties": {
    "addr:full":"Leharstr 21 Linz Ober\u00f6sterreich 4020",
    "addr:housenumber":"21",
    "addr:postcode":"4020",
    "addr:street":"Leharstr",
    "iso:country":"AT",
    "sg:address":"Leharstr 21",
    "sg:city":"Linz",
    "sg:orig_category":"Banken U Sparkassen",
    "sg:phone":"+43 4373 2652025",
    "sg:postcode":"4020",
    "sg:province":"Ober\u00f6sterreich",
    "wof:name":"Bankomat d Raiffeisenlandesbank Ober\u00f6sterreich Aktiengesellschaft",
    "wof:placetype":"venue"
},
  "geometry": {"coordinates":[14.2764558792,48.2868041992],"type":"Point"}
}