{
  "type": "Feature",
  "properties": {
    "iso:country":"AT",
    "sg:address":"Autokaderstr 33 ",
    "sg:city":"Wien",
    "sg:classifiers":[
        {
            "category":"Shopping",
            "subcategory":"Clothing, Apparel, & Fashions",
            "type":"Retail Goods"
        }
    ],
    "sg:phone":"+43 4312 783534",
    "sg:postcode":"1210",
    "sg:province":"Wien",
    "sg:tags":[
        "clothes"
    ],
    "wof:name":"LICONA BEKLEIDUNGSWERK M LIEGLE & CO",
    "wof:placetype":"venue"
},
  "geometry": {"coordinates":[16.3802013397,48.2841453552],"type":"Point"}
}