{
  "type": "Feature",
  "properties": {
    "iso:country":"AT",
    "sg:address":"Ort 57",
    "sg:city":"Ampflwang im Hausruckwald",
    "sg:classifiers":[
        {
            "category":"Military Area",
            "subcategory":"Air Force Base",
            "type":"Public Place"
        }
    ],
    "sg:phone":"+43 76753550",
    "sg:postcode":"4843",
    "sg:province":"Ober\u00f6sterreich",
    "sg:tags":[
        "polypropylene",
        "pp",
        "polyethylene",
        "board",
        "pe",
        "roll"
    ],
    "sg:website":"iroplastics.com",
    "wof:name":"IROPLASTICS Ges.m.b.H.",
    "wof:placetype":"venue"
},
  "geometry": {"coordinates":[13.5677623749,48.0890731812],"type":"Point"}
}