{
  "type": "Feature",
  "properties": {
    "addr:full":"Nr 113 Yspertal Nieder\u00f6sterreich 3683",
    "addr:postcode":"3683",
    "addr:street":"Nr;Niederoesterreich",
    "iso:country":"AT",
    "sg:address":"Nr 113",
    "sg:city":"Yspertal",
    "sg:orig_category":"Tankstellen",
    "sg:phone":"+43 7415 7344",
    "sg:postcode":"3683",
    "sg:province":"Nieder\u00f6sterreich",
    "wof:name":"OMV AG",
    "wof:placetype":"venue"
},
  "geometry": {"coordinates":[15.065489769,48.282119751],"type":"Point"}
}