{
  "type": "Feature",
  "properties": {
    "iso:country":"AT",
    "sg:address":"Liechtensteinstr 105",
    "sg:city":"Wien",
    "sg:orig_category":"Psychotherapie",
    "sg:phone":"+43 1 3151864",
    "sg:postcode":"1090",
    "sg:province":"Wien",
    "wof:name":"Wesenauer Gabriela",
    "wof:placetype":"venue"
},
  "geometry": {"coordinates":[16.3559875488,48.2278137207],"type":"Point"}
}