{
  "type": "Feature",
  "properties": {
    "addr:full":"Ottokar Kernstock-G 388 Gars am Kamp Nieder\u00f6sterreich 3571",
    "addr:housenumber":"388",
    "addr:postcode":"3571",
    "addr:street":"Ottokar Kernstock-G",
    "iso:country":"AT",
    "sg:address":"Ottokar Kernstock-G 388",
    "sg:city":"Gars am Kamp",
    "sg:orig_category":"Fertigteilbau",
    "sg:phone":"+43 2985 30805",
    "sg:postcode":"3571",
    "sg:province":"Nieder\u00f6sterreich",
    "wof:name":"Hofbauer KEG",
    "wof:placetype":"venue"
},
  "geometry": {"coordinates":[15.6669111252,48.5991630554],"type":"Point"}
}