{
  "type": "Feature",
  "properties": {
    "addr:full":"Leobner Str 76 Bruck an der Mur Steiermark 8600",
    "addr:postcode":"8600",
    "addr:street":"Str 76",
    "iso:country":"AT",
    "sg:address":"Leobner Str 76",
    "sg:city":"Bruck an der Mur",
    "sg:orig_category":"Installationsunternehmen",
    "sg:phone":"+43 4338 6253273",
    "sg:postcode":"8600",
    "sg:province":"Steiermark",
    "wof:name":"Pantak GesmbH",
    "wof:placetype":"venue"
},
  "geometry": {"coordinates":[15.2436180115,47.4015197754],"type":"Point"}
}