{
  "type": "Feature",
  "properties": {
    "addr:full":"Dannerhof 3 Judenburg Steiermark 8750",
    "addr:housenumber":"3",
    "addr:postcode":"8750",
    "addr:street":"Dannerhof",
    "iso:country":"AT",
    "sg:address":"Dannerhof 3",
    "sg:city":"Judenburg",
    "sg:orig_category":"Immobilienverwaltungen",
    "sg:phone":"+43 3572 84909",
    "sg:postcode":"8750",
    "sg:province":"Steiermark",
    "wof:name":"Kosjek-Lesser Immobilienverwaltung GmbH",
    "wof:placetype":"venue"
},
  "geometry": {"coordinates":[14.6499223709,47.1700286865],"type":"Point"}
}