{
  "type": "Feature",
  "properties": {
    "addr:full":"Bucheng 15 Zeltweg Steiermark 8740",
    "addr:housenumber":"15",
    "addr:postcode":"8740",
    "addr:street":"Bucheng",
    "iso:country":"AT",
    "sg:address":"Bucheng 15",
    "sg:city":"Zeltweg",
    "sg:orig_category":"Botendienste",
    "sg:phone":"+43 3577 26495",
    "sg:postcode":"8740",
    "sg:province":"Steiermark",
    "wof:name":"Europaexpress Sturm",
    "wof:placetype":"venue"
},
  "geometry": {"coordinates":[14.7405109406,47.1923103333],"type":"Point"}
}