{
  "type": "Feature",
  "properties": {
    "addr:full":"Kirchpl 7 Schruns Vorarlberg 6780",
    "addr:housenumber":"7",
    "addr:postcode":"6780",
    "addr:street":"Kirchpl",
    "iso:country":"AT",
    "sg:address":"Kirchpl 7",
    "sg:city":"Schruns",
    "sg:orig_category":"Blumeneinzelhandel",
    "sg:phone":"+43 4355 5672458",
    "sg:postcode":"6780",
    "sg:province":"Vorarlberg",
    "wof:name":"Bitschnau Stefan",
    "wof:placetype":"venue"
},
  "geometry": {"coordinates":[9.9189453125,47.0804252625],"type":"Point"}
}