{
  "type": "Feature",
  "properties": {
    "addr:full":"Peberinger Strasse 25 Eugendorf Salzburg 5301",
    "addr:housenumber":"25",
    "addr:postcode":"5301",
    "addr:street":"Peberinger Strasse;Salzburg",
    "iso:country":"AT",
    "sg:address":"Peberinger Strasse 25",
    "sg:city":"Eugendorf",
    "sg:classifiers":[
        {
            "category":"Building & Trades",
            "subcategory":"Construction",
            "type":"Services"
        }
    ],
    "sg:phone":"+43 6225 7574",
    "sg:postcode":"5301",
    "sg:province":"Salzburg",
    "sg:tags":[
        "component",
        "hydraulic"
    ],
    "sg:website":"oelhydraulik-garstenauer.at",
    "wof:name":"\u00d6lhydraulik Garstenauer GmbH",
    "wof:placetype":"venue"
},
  "geometry": {"coordinates":[13.116271019,47.855342865],"type":"Point"}
}