{
  "type": "Feature",
  "properties": {
    "iso:country":"AT",
    "sg:address":"Goethestr 7",
    "sg:city":"Hohenems",
    "sg:orig_category":"Zahntechnische Laboratorien",
    "sg:phone":"+43 4355 7672222",
    "sg:postcode":"6845",
    "sg:province":"Vorarlberg",
    "wof:name":"Strecker Arno Dental Atelier",
    "wof:placetype":"venue"
},
  "geometry": {"coordinates":[9.6837072372,47.3644676208],"type":"Point"}
}