{
  "type": "Feature",
  "properties": {
    "iso:country":"AT",
    "sg:address":"Am Bach 280",
    "sg:city":"Miesenbach",
    "sg:orig_category":"Mess-, Steuer- U Regeltechnik",
    "sg:phone":"+43 4326 3286410",
    "sg:postcode":"2761",
    "sg:province":"Nieder\u00f6sterreich",
    "wof:name":"J\u00e4gersberger Andreas",
    "wof:placetype":"venue"
},
  "geometry": {"coordinates":[15.9799060822,47.8700790405],"type":"Point"}
}