{
  "type": "Feature",
  "properties": {
    "iso:country":"AT",
    "sg:address":"Wolfganger Str 18",
    "sg:city":"Bad Ischl",
    "sg:orig_category":"Banken U Sparkassen",
    "sg:phone":"+43 4361 32263550",
    "sg:postcode":"4820",
    "sg:province":"Ober\u00f6sterreich",
    "wof:name":"Bankomat d Raiffeisenbank Inneres Salzkammergut regGenmbH",
    "wof:placetype":"venue"
},
  "geometry": {"coordinates":[13.5869779587,47.718963623],"type":"Point"}
}