{
  "type": "Feature",
  "properties": {
    "addr:full":"M\u00fchlenstrasse 20 Kirchham Ober\u00f6sterreich 4656",
    "addr:housenumber":"20",
    "addr:postcode":"4656",
    "addr:street":"Muehlenstrasse",
    "iso:country":"AT",
    "sg:address":"M\u00fchlenstrasse 20",
    "sg:city":"Kirchham",
    "sg:classifiers":[
        {
            "category":"Education",
            "subcategory":"Special Training",
            "type":"Public Place"
        }
    ],
    "sg:phone":"+43 76192013",
    "sg:postcode":"4656",
    "sg:province":"Ober\u00f6sterreich",
    "sg:tags":[
        "bread"
    ],
    "wof:name":"Franz Danzer Ges.m.b.H. & Co KG",
    "wof:placetype":"venue"
},
  "geometry": {"coordinates":[13.8986949921,47.9711112976],"type":"Point"}
}