{
  "type": "Feature",
  "properties": {
    "addr:full":"Nr 232 Loipersdorf Steiermark 8282",
    "addr:postcode":"8282",
    "addr:street":"Nr",
    "iso:country":"AT",
    "sg:address":"Nr 232",
    "sg:city":"Loipersdorf",
    "sg:orig_category":"Pensionen / Privatzimmer",
    "sg:phone":"+43 4333 8285880",
    "sg:postcode":"8282",
    "sg:province":"Steiermark",
    "wof:name":"Pension Thermenland",
    "wof:placetype":"venue"
},
  "geometry": {"coordinates":[16.1014595032,47.012878418],"type":"Point"}
}