{
  "type": "Feature",
  "properties": {
    "iso:country":"AT",
    "sg:address":"Anton-Reichel-Str 2",
    "sg:city":"St. Veit an der Glan",
    "sg:orig_category":"Anlagenbau U -Technik",
    "sg:phone":"+43 4342 1239502",
    "sg:postcode":"9300",
    "sg:province":"K\u00e4rnten",
    "wof:name":"RATEC Rationalisierungstechnik & Verfahrenstechnik GmbH",
    "wof:placetype":"venue"
},
  "geometry": {"coordinates":[14.3636922836,46.7633743286],"type":"Point"}
}