{
  "type": "Feature",
  "properties": {
    "addr:full":"Rot-Kreuz-G 100 St. Michael im Lungau Salzburg 5582",
    "addr:housenumber":"100",
    "addr:postcode":"5582",
    "addr:street":"Salzburg",
    "iso:country":"AT",
    "sg:address":"Rot-Kreuz-G 100",
    "sg:city":"St. Michael im Lungau",
    "sg:orig_category":"Tourismusinformation U -Organisationen",
    "sg:phone":"+43 4364 7789880",
    "sg:postcode":"5582",
    "sg:province":"Salzburg",
    "wof:name":"Ferienregion Lungau",
    "wof:placetype":"venue"
},
  "geometry": {"coordinates":[13.6377477646,47.0995559692],"type":"Point"}
}