{
  "type": "Feature",
  "properties": {
    "iso:country":"AT",
    "sg:address":"Franz-Reisch-Str 24",
    "sg:city":"Kitzb\u00fchel",
    "sg:classifiers":[
        {
            "category":"Utilities",
            "subcategory":"Refuse",
            "type":"Services"
        }
    ],
    "sg:phone":"+43 4366 42096560",
    "sg:postcode":"6370",
    "sg:province":"Tirol",
    "sg:tags":[
        "catering"
    ],
    "wof:name":"KA + CA Catering GesmbH & Co KG",
    "wof:placetype":"venue"
},
  "geometry": {"coordinates":[12.3864994049,47.446975708],"type":"Point"}
}