{
  "type": "Feature",
  "properties": {
    "addr:full":"Hauptstr 86 Pamhagen Burgenland 7152",
    "addr:housenumber":"86",
    "addr:postcode":"7152",
    "addr:street":"Hauptstr",
    "iso:country":"AT",
    "sg:address":"Hauptstr 86",
    "sg:city":"Pamhagen",
    "sg:orig_category":"Weine / Einzelhandel",
    "sg:phone":"+43 664 5355609",
    "sg:postcode":"7152",
    "sg:province":"Burgenland",
    "wof:name":"Mein Klang - Wein aus biologische Anbau",
    "wof:placetype":"venue"
},
  "geometry": {"coordinates":[16.9038047791,47.6973686218],"type":"Point"}
}