{
  "type": "Feature",
  "properties": {
    "iso:country":"AT",
    "sg:address":"Sportplatzsdlg 1",
    "sg:city":"St. Paul im Lavanttal",
    "sg:orig_category":"Maler, Anstreicher U Lackierer",
    "sg:phone":"+43 4343 572453",
    "sg:postcode":"9470",
    "sg:province":"K\u00e4rnten",
    "wof:name":"Klingbacher Marianne",
    "wof:placetype":"venue"
},
  "geometry": {"coordinates":[14.8709354401,46.7051811218],"type":"Point"}
}