{
  "type": "Feature",
  "properties": {
    "addr:full":"Schl\u00fc\u00dflberg 2 Grieskirchen Ober\u00f6sterreich 4710",
    "addr:housenumber":"2",
    "addr:postcode":"4710",
    "addr:street":"Schluesslberg",
    "iso:country":"AT",
    "sg:address":"Schl\u00fc\u00dflberg 2",
    "sg:city":"Grieskirchen",
    "sg:orig_category":"Autoverwertung",
    "sg:phone":"+43 7248 63575",
    "sg:postcode":"4710",
    "sg:province":"Ober\u00f6sterreich",
    "wof:name":"Rathwallner F Auto GesmbH",
    "wof:placetype":"venue"
},
  "geometry": {"coordinates":[13.8257322311,48.2358856201],"type":"Point"}
}