{
  "type": "Feature",
  "properties": {
    "addr:full":"Hauptpl 15/2 Hollabrunn Nieder\u00f6sterreich 2020",
    "addr:housenumber":"15 / 2",
    "addr:postcode":"2020",
    "addr:street":"Hauptpl",
    "iso:country":"AT",
    "sg:address":"Hauptpl 15/2",
    "sg:city":"Hollabrunn",
    "sg:orig_category":"Nachhilfe U Lernbetreuung",
    "sg:phone":"+43 4329 5253643",
    "sg:postcode":"2020",
    "sg:province":"Nieder\u00f6sterreich",
    "wof:name":"Hilfswerk Hollabrunn - Rund ums Lernen",
    "wof:placetype":"venue"
},
  "geometry": {"coordinates":[16.0792675018,48.562210083],"type":"Point"}
}