{
  "type": "Feature",
  "properties": {
    "iso:country":"AT",
    "sg:address":"Niederranna 66",
    "sg:city":"Wesenufer",
    "sg:classifiers":[
        {
            "category":"Autos & Motor Vehicles",
            "subcategory":"Automobile Sales",
            "type":"Retail Goods"
        }
    ],
    "sg:phone":"+43 4372 855360",
    "sg:postcode":"4085",
    "sg:province":"Ober\u00f6sterreich",
    "sg:tags":[
        "motor-cars"
    ],
    "wof:name":"STALLINGER GMBH MAZDA & KIA",
    "wof:placetype":"venue"
},
  "geometry": {"coordinates":[13.82264328,48.4403686523],"type":"Point"}
}