{
  "type": "Feature",
  "properties": {
    "iso:country":"AT",
    "sg:address":"Oberer Stadtpl 13",
    "sg:city":"Hall in Tirol",
    "sg:orig_category":"Juwelen, Gold- U Silberwaren / Einzelhandel",
    "sg:phone":"+43 4352 2356128",
    "sg:postcode":"6060",
    "sg:province":"Tirol",
    "wof:name":"Uhren-Schmuck Katrin",
    "wof:placetype":"venue"
},
  "geometry": {"coordinates":[11.50694561,47.2817192078],"type":"Point"}
}