{
  "type": "Feature",
  "properties": {
    "addr:full":"Hauptstr 13 Rosental an der Kainach Steiermark 8582",
    "addr:housenumber":"13",
    "addr:postcode":"8582",
    "addr:street":"Hauptstr",
    "iso:country":"AT",
    "sg:address":"Hauptstr 13",
    "sg:city":"Rosental an der Kainach",
    "sg:orig_category":"Transportunternehmen",
    "sg:phone":"+43 4331 42224910",
    "sg:postcode":"8582",
    "sg:province":"Steiermark",
    "wof:name":"Grillitsch GesmbH & Co KG",
    "wof:placetype":"venue"
},
  "geometry": {"coordinates":[15.127327919,47.0522727966],"type":"Point"}
}