{
  "type": "Feature",
  "properties": {
    "addr:full":"Allendepl 1 Linz Ober\u00f6sterreich 4030",
    "addr:housenumber":"1",
    "addr:postcode":"4030",
    "addr:street":"Allendepl",
    "iso:country":"AT",
    "sg:address":"Allendepl 1",
    "sg:city":"Linz",
    "sg:orig_category":"Volksschulen",
    "sg:phone":"+43 732 305293",
    "sg:postcode":"4030",
    "sg:province":"Ober\u00f6sterreich",
    "wof:name":"Volksschule",
    "wof:placetype":"venue"
},
  "geometry": {"coordinates":[14.3109846115,48.2504692078],"type":"Point"}
}