{
  "type": "Feature",
  "properties": {
    "iso:country":"AT",
    "sg:address":"Vormarktstrasse 29",
    "sg:city":"Mauthausen",
    "sg:classifiers":[
        {
            "category":"Manufacturing",
            "subcategory":"Textiles",
            "type":"Manufacturing & Wholesale Goods"
        }
    ],
    "sg:phone":"+43 7238 2278",
    "sg:postcode":"4310",
    "sg:province":"Ober\u00f6sterreich",
    "sg:tags":[
        "curtain",
        "fabric"
    ],
    "wof:name":"Dietmar Heigl",
    "wof:placetype":"venue"
},
  "geometry": {"coordinates":[14.5237522125,48.2401885986],"type":"Point"}
}