{
  "type": "Feature",
  "properties": {
    "iso:country":"AT",
    "sg:address":"Haid 30",
    "sg:city":"V\u00f6cklamarkt",
    "sg:orig_category":"Installationsunternehmen",
    "sg:phone":"+43 768227880",
    "sg:postcode":"4870",
    "sg:province":"Ober\u00f6sterreich",
    "wof:name":"Resch Matthias GesmbH",
    "wof:placetype":"venue"
},
  "geometry": {"coordinates":[13.5025262833,47.9888114929],"type":"Point"}
}