{
  "type": "Feature",
  "properties": {
    "addr:full":"Puintweg 6 Fiss Tirol 6533",
    "addr:housenumber":"6",
    "addr:postcode":"6533",
    "addr:street":"Puintweg;Tirol",
    "iso:country":"AT",
    "sg:address":"Puintweg 6",
    "sg:city":"Fiss",
    "sg:orig_category":"Appartements / Ferienwohnungen",
    "sg:phone":"+43 4354 766428",
    "sg:postcode":"6533",
    "sg:province":"Tirol",
    "wof:name":"Ferienwohnungen Schimpf\u00f6\u00dfl",
    "wof:placetype":"venue"
},
  "geometry": {"coordinates":[10.6195335388,47.0560913086],"type":"Point"}
}