{
  "type": "Feature",
  "properties": {
    "addr:full":"Wiener Str. 7 M\u00fcrzzuschlag Steiermark 8680",
    "addr:housenumber":"7",
    "addr:postcode":"8680",
    "addr:street":"Str.",
    "iso:country":"AT",
    "sg:address":"Wiener Str. 7",
    "sg:city":"M\u00fcrzzuschlag",
    "sg:classifiers":[
        {
            "category":"Shopping",
            "subcategory":"Clothing, Apparel, & Fashions",
            "type":"Retail Goods"
        }
    ],
    "sg:phone":"+43 4338 522376",
    "sg:postcode":"8680",
    "sg:province":"Steiermark",
    "sg:tags":[
        "clothes"
    ],
    "wof:name":"RONALD FUCHS",
    "wof:placetype":"venue"
},
  "geometry": {"coordinates":[16.3542709351,48.159198761],"type":"Point"}
}