{
  "type": "Feature",
  "properties": {
    "addr:full":"Weizer Str 7 Mariatrost Steiermark 8044",
    "addr:housenumber":"7",
    "addr:postcode":"8044",
    "addr:street":"Str",
    "iso:country":"AT",
    "sg:address":"Weizer Str 7",
    "sg:city":"Mariatrost",
    "sg:orig_category":"Transportunternehmen",
    "sg:phone":"+43 3132 24370",
    "sg:postcode":"8044",
    "sg:province":"Steiermark",
    "wof:name":"Meinhart Franz GesmbH",
    "wof:placetype":"venue"
},
  "geometry": {"coordinates":[15.5206708908,47.1366882324],"type":"Point"}
}