{
  "type": "Feature",
  "properties": {
    "iso:country":"AT",
    "sg:address":"Oberhof 26",
    "sg:city":"Goldegg",
    "sg:orig_category":"Elektroinstallationsunternehmen",
    "sg:phone":"+43 4366 41600251",
    "sg:postcode":"5622",
    "sg:province":"Salzburg",
    "wof:name":"Elektrotechnik B\u00fcrgler & Mooslechner OEG",
    "wof:placetype":"venue"
},
  "geometry": {"coordinates":[13.099439621,47.3187294006],"type":"Point"}
}