{
  "type": "Feature",
  "properties": {
    "addr:full":"Ischler Str 16 St. Gilgen Salzburg 5340",
    "addr:housenumber":"16",
    "addr:postcode":"5340",
    "addr:street":"Str",
    "iso:country":"AT",
    "sg:address":"Ischler Str 16",
    "sg:city":"St. Gilgen",
    "sg:classifiers":[
        {
            "category":"Restaurant",
            "type":"Food & Drink"
        }
    ],
    "sg:phone":"+43 6227 7040",
    "sg:postcode":"5340",
    "sg:province":"Salzburg",
    "sg:tags":[
        "pizzeria"
    ],
    "wof:name":"Cafe-Restaurant Pizzeria Papageno",
    "wof:placetype":"venue"
},
  "geometry": {"coordinates":[13.367816925,47.7658424377],"type":"Point"}
}