{
  "type": "Feature",
  "properties": {
    "addr:full":"Hauptstr 436a Mayrhofen Tirol 6290",
    "addr:housenumber":"436a",
    "addr:postcode":"6290",
    "addr:street":"Hauptstr;Tirol",
    "iso:country":"AT",
    "sg:address":"Hauptstr 436a",
    "sg:city":"Mayrhofen",
    "sg:orig_category":"Drogerien",
    "sg:phone":"+43 5285 6000",
    "sg:postcode":"6290",
    "sg:province":"Tirol",
    "wof:name":"Rieser-Malzer Team GmbH",
    "wof:placetype":"venue"
},
  "geometry": {"coordinates":[11.8627376556,47.166847229],"type":"Point"}
}