{
  "type": "Feature",
  "properties": {
    "addr:full":"Markt 22 Schenkenfelden Ober\u00f6sterreich 4192",
    "addr:housenumber":"22",
    "addr:postcode":"4192",
    "addr:street":"Markt",
    "iso:country":"AT",
    "sg:address":"Markt 22",
    "sg:city":"Schenkenfelden",
    "sg:orig_category":"Banken U Sparkassen",
    "sg:phone":"+43 4372 1444320",
    "sg:postcode":"4192",
    "sg:province":"Ober\u00f6sterreich",
    "wof:name":"Raiffeisenbank Region Bad Leonfelden regGenmbH",
    "wof:placetype":"venue"
},
  "geometry": {"coordinates":[14.3608064651,48.5029144287],"type":"Point"}
}