{
  "type": "Feature",
  "properties": {
    "addr:full":"Lidmanskyg 8 Klagenfurt K\u00e4rnten 9020",
    "addr:housenumber":"8",
    "addr:postcode":"9020",
    "addr:street":"Lidmanskyg;Kaernten",
    "iso:country":"AT",
    "sg:address":"Lidmanskyg 8",
    "sg:city":"Klagenfurt",
    "sg:orig_category":"Galerien",
    "sg:phone":"+43 463 512337",
    "sg:postcode":"9020",
    "sg:province":"K\u00e4rnten",
    "wof:name":"Diakoniezentrum Sozial- und Gesundheitsbetriebe GmbH",
    "wof:placetype":"venue"
},
  "geometry": {"coordinates":[14.3082752228,46.622303009],"type":"Point"}
}