{
  "type": "Feature",
  "properties": {
    "addr:full":"Antonsg 14 Baden Nieder\u00f6sterreich 2500",
    "addr:housenumber":"14",
    "addr:postcode":"2500",
    "addr:street":"Antonsg;Niederoesterreich",
    "iso:country":"AT",
    "sg:address":"Antonsg 14",
    "sg:city":"Baden",
    "sg:orig_category":"Geschenkartikel",
    "sg:phone":"+43 2252 85249",
    "sg:postcode":"2500",
    "sg:province":"Nieder\u00f6sterreich",
    "wof:name":"Tr\u00e4umen-Leben-Gestalten Renate",
    "wof:placetype":"venue"
},
  "geometry": {"coordinates":[16.2392063141,48.0093765259],"type":"Point"}
}