{
  "type": "Feature",
  "properties": {
    "addr:full":"Mautner Markhof-G 76 Wien Wien 1110",
    "addr:housenumber":"76",
    "addr:postcode":"1110",
    "iso:country":"AT",
    "sg:address":"Mautner Markhof-G 76",
    "sg:city":"Wien",
    "sg:orig_category":"Telekommunikation",
    "sg:phone":"+43 1 7433170",
    "sg:postcode":"1110",
    "sg:province":"Wien",
    "wof:name":"phone&more",
    "wof:placetype":"venue"
},
  "geometry": {"coordinates":[16.4202346802,48.1733016968],"type":"Point"}
}