{
  "type": "Feature",
  "properties": {
    "addr:full":"Erleng 544 Maria Anzbach Nieder\u00f6sterreich 3034",
    "addr:housenumber":"544",
    "addr:postcode":"3034",
    "addr:street":"Erleng",
    "iso:country":"AT",
    "sg:address":"Erleng 544",
    "sg:city":"Maria Anzbach",
    "sg:orig_category":"Datenverarbeitung",
    "sg:phone":"+43 2772 51685",
    "sg:postcode":"3034",
    "sg:province":"Nieder\u00f6sterreich",
    "wof:name":"Hohl Eva",
    "wof:placetype":"venue"
},
  "geometry": {"coordinates":[15.9302406311,48.1954689026],"type":"Point"}
}