{
  "type": "Feature",
  "properties": {
    "iso:country":"AT",
    "sg:address":"Wiener Str 120",
    "sg:city":"Friedberg",
    "sg:orig_category":"Apotheken",
    "sg:phone":"+43 4333 3922728",
    "sg:postcode":"8240",
    "sg:province":"Steiermark",
    "wof:name":"Apotheke Zur Maria Heil der Kranken",
    "wof:placetype":"venue"
},
  "geometry": {"coordinates":[16.0587272644,47.4413452148],"type":"Point"}
}