{
  "type": "Feature",
  "properties": {
    "addr:full":"Hofstatt 2 Deutsch Brodersdorf Nieder\u00f6sterreich 2443",
    "addr:housenumber":"2",
    "addr:postcode":"2443",
    "addr:street":"Hofstatt",
    "iso:country":"AT",
    "sg:address":"Hofstatt 2",
    "sg:city":"Deutsch Brodersdorf",
    "sg:orig_category":"Volksschulen",
    "sg:phone":"+43 2255 8235",
    "sg:postcode":"2443",
    "sg:province":"Nieder\u00f6sterreich",
    "wof:name":"Volksschule",
    "wof:placetype":"venue"
},
  "geometry": {"coordinates":[16.5480766296,47.9054832458],"type":"Point"}
}