{
  "type": "Feature",
  "properties": {
    "addr:full":"Siebenst\u00e4dterstr 20 Salzburg Salzburg 5020",
    "addr:housenumber":"20",
    "addr:postcode":"5020",
    "addr:street":"Siebenstaedterstr;Salzburg",
    "iso:country":"AT",
    "sg:address":"Siebenst\u00e4dterstr 20",
    "sg:city":"Salzburg",
    "sg:orig_category":"Elektroinstallationsunternehmen",
    "sg:phone":"+43 662 4352950",
    "sg:postcode":"5020",
    "sg:province":"Salzburg",
    "sg:website":"elektro-markl.at",
    "wof:name":"Elektro Markl Anlagentechnik GesmbH",
    "wof:placetype":"venue"
},
  "geometry": {"coordinates":[13.0331630707,47.8129653931],"type":"Point"}
}