{
  "type": "Feature",
  "properties": {
    "addr:full":"Dr Koss-Str 4 Wels Ober\u00f6sterreich 4600",
    "addr:housenumber":"4",
    "addr:postcode":"4600",
    "addr:street":"Oberoesterreich",
    "iso:country":"AT",
    "sg:address":"Dr Koss-Str 4",
    "sg:city":"Wels",
    "sg:orig_category":"Weiterbildungsinstitute M Allg U Berufl Bildungsangebot",
    "sg:phone":"+43 4357 0005910",
    "sg:postcode":"4600",
    "sg:province":"Ober\u00f6sterreich",
    "wof:name":"WIFI d Wirtschaftskammer Ober\u00f6sterreich",
    "wof:placetype":"venue"
},
  "geometry": {"coordinates":[14.0202894211,48.1589889526],"type":"Point"}
}