{
  "type": "Feature",
  "properties": {
    "iso:country":"AT",
    "sg:address":"Nr 134",
    "sg:city":"Schwarzau im Gebirge",
    "sg:orig_category":"Transportunternehmen",
    "sg:phone":"+43 4326 67309",
    "sg:postcode":"2662",
    "sg:province":"Nieder\u00f6sterreich",
    "wof:name":"Sch\u00f6ll Ralf",
    "wof:placetype":"venue"
},
  "geometry": {"coordinates":[15.7038021088,47.8127593994],"type":"Point"}
}