{
  "type": "Feature",
  "properties": {
    "iso:country":"AT",
    "sg:address":"Europastr. 15",
    "sg:city":"Feldbach",
    "sg:classifiers":[
        {
            "category":"Shopping",
            "subcategory":"Clothing, Apparel, & Fashions",
            "type":"Retail Goods"
        }
    ],
    "sg:phone":"+43 4331 523041",
    "sg:postcode":"8330",
    "sg:province":"Steiermark",
    "sg:tags":[
        "clothes"
    ],
    "wof:name":"PELZGERBEREI LINDENAU GES. MBH & CO.KG",
    "wof:placetype":"venue"
},
  "geometry": {"coordinates":[15.9072132111,46.9529685974],"type":"Point"}
}