{
  "type": "Feature",
  "properties": {
    "iso:country":"AT",
    "sg:address":"Leopoldauer Strasse 159",
    "sg:city":"Wien",
    "sg:classifiers":[
        {
            "category":"Home & Garden",
            "subcategory":"Building Materials",
            "type":"Retail Goods"
        }
    ],
    "sg:phone":"+43 1 25965460",
    "sg:postcode":"1210",
    "sg:province":"Wien",
    "sg:tags":[
        "installation",
        "electric"
    ],
    "sg:website":"seipelt.at",
    "wof:name":"Metallkonstruktionen f\u00fcr Elektrobau Elektrobau, Freileitungsbau und Elektroinstallationen Ing. Seip",
    "wof:placetype":"venue"
},
  "geometry": {"coordinates":[16.4281997681,48.2624702454],"type":"Point"}
}