{
  "type": "Feature",
  "properties": {
    "addr:full":"Ziegelstr 10 Inzing Tirol 6401",
    "addr:housenumber":"10",
    "addr:postcode":"6401",
    "addr:street":"Ziegelstr;Tirol",
    "iso:country":"AT",
    "sg:address":"Ziegelstr 10",
    "sg:city":"Inzing",
    "sg:orig_category":"Dichtungen",
    "sg:phone":"+43 5238 88530",
    "sg:postcode":"6401",
    "sg:province":"Tirol",
    "wof:name":"Egomat Dichtstoff GesmbH",
    "wof:placetype":"venue"
},
  "geometry": {"coordinates":[11.1963348389,47.2715454102],"type":"Point"}
}