{
  "type": "Feature",
  "properties": {
    "addr:full":"Hauptstr 17a Liezen Steiermark 8940",
    "addr:housenumber":"17a",
    "addr:postcode":"8940",
    "addr:street":"Hauptstr",
    "iso:country":"AT",
    "sg:address":"Hauptstr 17a",
    "sg:city":"Liezen",
    "sg:orig_category":"Unternehmensberatung",
    "sg:phone":"+43 3612 22278",
    "sg:postcode":"8940",
    "sg:province":"Steiermark",
    "wof:name":"impuls Consulting & Fahrschulservice GmbH",
    "wof:placetype":"venue"
},
  "geometry": {"coordinates":[14.243689537,47.5670471191],"type":"Point"}
}