{
  "type": "Feature",
  "properties": {
    "addr:full":"Schulweg 3 Zell am See Salzburg 5700",
    "addr:housenumber":"3",
    "addr:postcode":"5700",
    "addr:street":"Schulweg;Salzburg",
    "iso:country":"AT",
    "sg:address":"Schulweg 3",
    "sg:city":"Zell am See",
    "sg:orig_category":"Volksschulen",
    "sg:phone":"+43 6542 572580",
    "sg:postcode":"5700",
    "sg:province":"Salzburg",
    "wof:name":"Volksschule Sch\u00fcttdorf",
    "wof:placetype":"venue"
},
  "geometry": {"coordinates":[12.795674324,47.3228111267],"type":"Point"}
}