{
  "type": "Feature",
  "properties": {
    "addr:full":"Wildbacher Str 3 Deutschlandsberg Steiermark 8530",
    "addr:housenumber":"3",
    "addr:postcode":"8530",
    "addr:street":"Wildbacher Str",
    "iso:country":"AT",
    "sg:address":"Wildbacher Str 3",
    "sg:city":"Deutschlandsberg",
    "sg:orig_category":"Forstverwaltungen",
    "sg:phone":"+43 4334 6222220",
    "sg:postcode":"8530",
    "sg:province":"Steiermark",
    "wof:name":"Forstdirektion Prinz DI Alfred Liechtenstein",
    "wof:placetype":"venue"
},
  "geometry": {"coordinates":[15.2140703201,46.8189315796],"type":"Point"}
}