{
  "type": "Feature",
  "properties": {
    "addr:full":"Ober-Siegendorf 7 H\u00fcrm Nieder\u00f6sterreich 3383",
    "addr:housenumber":"7",
    "addr:postcode":"3383",
    "addr:street":"Ober-Siegendorf;Niederoesterreich",
    "iso:country":"AT",
    "sg:address":"Ober-Siegendorf 7",
    "sg:city":"H\u00fcrm",
    "sg:classifiers":[
        {
            "category":"Government",
            "subcategory":"Fire Station",
            "type":"Public Place"
        }
    ],
    "sg:phone":"+43 2754 8114",
    "sg:postcode":"3383",
    "sg:province":"Nieder\u00f6sterreich",
    "sg:tags":[
        "fitting",
        "furniture",
        "kitchen"
    ],
    "sg:website":"obruca.at",
    "wof:name":"Eduard Obruca jun.",
    "wof:placetype":"venue"
},
  "geometry": {"coordinates":[15.4048547745,48.1329193115],"type":"Point"}
}