{
  "type": "Feature",
  "properties": {
    "addr:full":"Hauptstr 6 Eberstalzell Ober\u00f6sterreich 4653",
    "addr:housenumber":"6",
    "addr:postcode":"4653",
    "addr:street":"Hauptstr",
    "iso:country":"AT",
    "sg:address":"Hauptstr 6",
    "sg:city":"Eberstalzell",
    "sg:orig_category":"Friseure U Frisiersalons",
    "sg:phone":"+43 4372 415577",
    "sg:postcode":"4653",
    "sg:province":"Ober\u00f6sterreich",
    "wof:name":"Kohler Herbert",
    "wof:placetype":"venue"
},
  "geometry": {"coordinates":[13.9817657471,48.0440101624],"type":"Point"}
}