{
  "type": "Feature",
  "properties": {
    "iso:country":"AT",
    "sg:address":"Roseggerg 43",
    "sg:city":"Wien",
    "sg:orig_category":"Exporteure U Importeure",
    "sg:phone":"+43 4314 941906",
    "sg:postcode":"1160",
    "sg:province":"Wien",
    "wof:name":"Celebic Mirsad KEG",
    "wof:placetype":"venue"
},
  "geometry": {"coordinates":[16.3083114624,48.2119979858],"type":"Point"}
}