{
  "type": "Feature",
  "properties": {
    "iso:country":"AT",
    "sg:address":"M\u00f6bersdorf 7",
    "sg:city":"Zeltweg",
    "sg:orig_category":"Loden",
    "sg:phone":"+43 3577 815050",
    "sg:postcode":"8740",
    "sg:province":"Steiermark",
    "sg:website":"leichtfried-loden.co.at",
    "wof:name":"Leichtfried GmbH & Co KG Lodenfabrik",
    "wof:placetype":"venue"
},
  "geometry": {"coordinates":[14.7515068054,47.1885032654],"type":"Point"}
}