{
  "type": "Feature",
  "properties": {
    "iso:country":"AT",
    "sg:address":"Kulstrunkstr 26",
    "sg:city":"Aigen",
    "sg:orig_category":"Psychotherapie",
    "sg:phone":"+43 662 642636",
    "sg:postcode":"5026",
    "sg:province":"Salzburg",
    "wof:name":"Strasser Ph Dr Klinische- und Gesundheitspsychologin",
    "wof:placetype":"venue"
},
  "geometry": {"coordinates":[13.0819101334,47.7969551086],"type":"Point"}
}