{
  "type": "Feature",
  "properties": {
    "addr:full":"Bahnhofstr 84 Rattersdorf-Liebing Burgenland 7443",
    "addr:housenumber":"84",
    "addr:postcode":"7443",
    "addr:street":"Bahnhofstr",
    "iso:country":"AT",
    "sg:address":"Bahnhofstr 84",
    "sg:city":"Rattersdorf-Liebing",
    "sg:orig_category":"Polizei U Gendarmerie",
    "sg:phone":"+43 4359 1331235",
    "sg:postcode":"7443",
    "sg:province":"Burgenland",
    "wof:name":"Gendarmerie Grenzkontrollstelle",
    "wof:placetype":"venue"
},
  "geometry": {"coordinates":[16.5087852478,47.4091033936],"type":"Point"}
}