{
  "type": "Feature",
  "properties": {
    "addr:full":"Hauptstr 3 Hermagor K\u00e4rnten 9620",
    "addr:housenumber":"3",
    "addr:postcode":"9620",
    "addr:street":"Hauptstr;Kaernten",
    "iso:country":"AT",
    "sg:address":"Hauptstr 3",
    "sg:city":"Hermagor",
    "sg:orig_category":"Spielwaren U Spiele",
    "sg:phone":"+43 4367 65455231",
    "sg:postcode":"9620",
    "sg:province":"K\u00e4rnten",
    "wof:name":"Spielwaren Floh Wolfgang M\u00fchlbach",
    "wof:placetype":"venue"
},
  "geometry": {"coordinates":[13.3704023361,46.6271438599],"type":"Point"}
}