{
  "type": "Feature",
  "properties": {
    "addr:full":"Lindenplatz 7 Kapfenberg Steiermark 8605",
    "addr:housenumber":"7",
    "addr:postcode":"8605",
    "addr:street":"Lindenplatz",
    "iso:country":"AT",
    "sg:address":"Lindenplatz 7",
    "sg:city":"Kapfenberg",
    "sg:classifiers":[
        {
            "category":"Professional",
            "subcategory":"Art Services",
            "type":"Services"
        }
    ],
    "sg:phone":"+43 3862 22592",
    "sg:postcode":"8605",
    "sg:province":"Steiermark",
    "sg:tags":[
        "artistic",
        "glazings"
    ],
    "wof:name":"Glas Oppitz Ges.m.b.H.",
    "wof:placetype":"venue"
},
  "geometry": {"coordinates":[15.2879886627,47.4401054382],"type":"Point"}
}