{
  "type": "Feature",
  "properties": {
    "addr:full":"Schallerbacherhofstr 4/9 Bad Schallerbach Ober\u00f6sterreich 4701",
    "addr:housenumber":"4 / 9",
    "addr:postcode":"4701",
    "addr:street":"Schallerbacherhofstr",
    "iso:country":"AT",
    "sg:address":"Schallerbacherhofstr 4/9",
    "sg:city":"Bad Schallerbach",
    "sg:orig_category":"Rettungsdienste",
    "sg:phone":"+43 676 840384200",
    "sg:postcode":"4701",
    "sg:province":"Ober\u00f6sterreich",
    "wof:name":"\u00f6sterreichische Wasser-Rettung EL Bez WL-GR-EF & Donau",
    "wof:placetype":"venue"
},
  "geometry": {"coordinates":[13.9227848053,48.2296676636],"type":"Point"}
}