{
  "type": "Feature",
  "properties": {
    "iso:country":"AT",
    "sg:address":"Martin Gusinde-G 10",
    "sg:city":"Maria Enzersdorf",
    "sg:orig_category":"Textilwaren / Einzelhandel",
    "sg:phone":"+43 2236 225540",
    "sg:postcode":"2344",
    "sg:province":"Nieder\u00f6sterreich",
    "wof:name":"Aron Ilia GesmbH",
    "wof:placetype":"venue"
},
  "geometry": {"coordinates":[16.2612895966,48.0980300903],"type":"Point"}
}