{
  "type": "Feature",
  "properties": {
    "iso:country":"AT",
    "sg:address":"Reiherweg 23",
    "sg:city":"Wien",
    "sg:orig_category":"Tabaktrafiken",
    "sg:phone":"+43 1 2805117",
    "sg:postcode":"1220",
    "sg:province":"Wien",
    "wof:name":"Schiefer Eleonore",
    "wof:placetype":"venue"
},
  "geometry": {"coordinates":[16.4747772217,48.2020454407],"type":"Point"}
}