{
  "type": "Feature",
  "properties": {
    "addr:full":"Schottenfeldg 41-43/2 Wien Wien 1070",
    "addr:housenumber":"41-43 / 2",
    "addr:postcode":"1070",
    "iso:country":"AT",
    "sg:address":"Schottenfeldg 41-43/2",
    "sg:city":"Wien",
    "sg:orig_category":"Non-Classified Establishments",
    "sg:phone":"+43 1 5249463",
    "sg:postcode":"1070",
    "sg:province":"Wien",
    "wof:name":"City Church Wien Christengemeinde n neutestamentlichem Bild",
    "wof:placetype":"venue"
},
  "geometry": {"coordinates":[16.3383293152,48.2016792297],"type":"Point"}
}