{
  "type": "Feature",
  "properties": {
    "iso:country":"AT",
    "sg:address":"Hochosterwitz 1",
    "sg:city":"Launsdorf",
    "sg:classifiers":[
        {
            "category":"Restaurant",
            "type":"Food & Drink"
        }
    ],
    "sg:phone":"+43 4213 20100",
    "sg:postcode":"9314",
    "sg:province":"K\u00e4rnten",
    "wof:name":"Hochosterwitz Burg-Restaurant",
    "wof:placetype":"venue"
},
  "geometry": {"coordinates":[14.4554748535,46.7681846619],"type":"Point"}
}