{
  "type": "Feature",
  "properties": {
    "addr:full":"Rudolfstr 15 Tulln an der Donau Nieder\u00f6sterreich 3430",
    "addr:housenumber":"15",
    "addr:postcode":"3430",
    "addr:street":"Rudolfstr",
    "iso:country":"AT",
    "sg:address":"Rudolfstr 15",
    "sg:city":"Tulln an der Donau",
    "sg:orig_category":"Physiotherapie",
    "sg:phone":"+43 2272 61804",
    "sg:postcode":"3430",
    "sg:province":"Nieder\u00f6sterreich",
    "wof:name":"Winkler-Behr Angela",
    "wof:placetype":"venue"
},
  "geometry": {"coordinates":[16.0527572632,48.3324775696],"type":"Point"}
}