{
  "type": "Feature",
  "properties": {
    "iso:country":"AT",
    "sg:address":"Hauptstr 39",
    "sg:city":"Limberg",
    "sg:orig_category":"Granitwerke",
    "sg:phone":"+43 2958 882230",
    "sg:postcode":"3721",
    "sg:province":"Nieder\u00f6sterreich",
    "wof:name":"Bitustein Stra\u00dfenbaustoffe GesmbH",
    "wof:placetype":"venue"
},
  "geometry": {"coordinates":[15.8577203751,48.5957489014],"type":"Point"}
}