{
  "type": "Feature",
  "properties": {
    "iso:country":"AT",
    "sg:address":"Herreng 20",
    "sg:city":"Hartberg",
    "sg:orig_category":"Boutiquen",
    "sg:phone":"+43 3332 63141",
    "sg:postcode":"8230",
    "sg:province":"Steiermark",
    "wof:name":"Flexx Fashion Store",
    "wof:placetype":"venue"
},
  "geometry": {"coordinates":[15.9678525925,47.279750824],"type":"Point"}
}