{
  "type": "Feature",
  "properties": {
    "addr:full":"Landstra\u00dfer Hauptstr 95 Wien Wien 1030",
    "addr:housenumber":"95",
    "addr:postcode":"1030",
    "addr:street":"Landstrasser Hauptstr",
    "iso:country":"AT",
    "sg:address":"Landstra\u00dfer Hauptstr 95",
    "sg:city":"Wien",
    "sg:orig_category":"Lebensmittel / Erzeugung U Gro\u00c3\u0178handel",
    "sg:phone":"+43 4317 123350",
    "sg:postcode":"1030",
    "sg:province":"Wien",
    "wof:name":"Haas Adolf GmbH",
    "wof:placetype":"venue"
},
  "geometry": {"coordinates":[16.3947200775,48.1987991333],"type":"Point"}
}