{
  "type": "Feature",
  "properties": {
    "iso:country":"AT",
    "sg:address":"Watzelsdorfer Hauptstr 16",
    "sg:city":"Neidling",
    "sg:orig_category":"Holzhandel",
    "sg:phone":"+43 4366 44030587",
    "sg:postcode":"3110",
    "sg:province":"Nieder\u00f6sterreich",
    "wof:name":"Stern Josef - S\u00e4gewerk & Holzhandel",
    "wof:placetype":"venue"
},
  "geometry": {"coordinates":[15.546298027,48.2321281433],"type":"Point"}
}