{
  "type": "Feature",
  "properties": {
    "addr:full":"Puchstr 4 Graz Steiermark 8020",
    "addr:housenumber":"4",
    "addr:postcode":"8020",
    "addr:street":"Puchstr",
    "iso:country":"AT",
    "sg:address":"Puchstr 4",
    "sg:city":"Graz",
    "sg:orig_category":"Restaurants: Chinesisch",
    "sg:phone":"+43 316 271979",
    "sg:postcode":"8020",
    "sg:province":"Steiermark",
    "wof:name":"China-Restaurant Kun Lun",
    "wof:placetype":"venue"
},
  "geometry": {"coordinates":[15.4328327179,47.0521087646],"type":"Point"}
}