{
  "type": "Feature",
  "properties": {
    "addr:full":"Magdalenenhofstr 22a Langenzersdorf Nieder\u00f6sterreich 2103",
    "addr:housenumber":"22a",
    "addr:postcode":"2103",
    "addr:street":"Magdalenenhofstr",
    "iso:country":"AT",
    "sg:address":"Magdalenenhofstr 22a",
    "sg:city":"Langenzersdorf",
    "sg:orig_category":"Ballettschulen",
    "sg:phone":"+43 2244 4347",
    "sg:postcode":"2103",
    "sg:province":"Nieder\u00f6sterreich",
    "wof:name":"Tanzstudio Elizabeth Mills",
    "wof:placetype":"venue"
},
  "geometry": {"coordinates":[16.3688373566,48.3099746704],"type":"Point"}
}