{
  "type": "Feature",
  "properties": {
    "addr:full":"Schmiedgraben 11 Linz Ober\u00f6sterreich 4040",
    "addr:housenumber":"11",
    "addr:postcode":"4040",
    "addr:street":"Schmiedgraben",
    "iso:country":"AT",
    "sg:address":"Schmiedgraben 11",
    "sg:city":"Linz",
    "sg:orig_category":"Schmieden U Schmiedeeisenelemente",
    "sg:phone":"+43 4372 396247",
    "sg:postcode":"4040",
    "sg:province":"Ober\u00f6sterreich",
    "wof:name":"Eidenberger KEG",
    "wof:placetype":"venue"
},
  "geometry": {"coordinates":[14.282374382,48.3151435852],"type":"Point"}
}