{
  "type": "Feature",
  "properties": {
    "addr:full":"Rainerstr 6-8 Linz Ober\u00f6sterreich 4020",
    "addr:housenumber":"6-8",
    "addr:postcode":"4020",
    "addr:street":"Rainerstr",
    "iso:country":"AT",
    "sg:address":"Rainerstr 6-8",
    "sg:city":"Linz",
    "sg:orig_category":"Zeitungen U Zeitschriften",
    "sg:phone":"+43 4373 2779262",
    "sg:postcode":"4020",
    "sg:province":"Ober\u00f6sterreich",
    "wof:name":"Fu\u00dfballzeitung Ankick",
    "wof:placetype":"venue"
},
  "geometry": {"coordinates":[14.2903518677,48.2978897095],"type":"Point"}
}