{
  "type": "Feature",
  "properties": {
    "addr:full":"Ebersdorf 86 Ebersdorf Steiermark 8273",
    "addr:housenumber":"86",
    "addr:postcode":"8273",
    "addr:street":"Ebersdorf",
    "iso:country":"AT",
    "sg:address":"Ebersdorf 86",
    "sg:city":"Ebersdorf",
    "sg:classifiers":[
        {
            "category":"Manufacturing",
            "subcategory":"Wood Products",
            "type":"Manufacturing & Wholesale Goods"
        }
    ],
    "sg:phone":"+43 3333 2309",
    "sg:postcode":"8273",
    "sg:province":"Steiermark",
    "sg:tags":[
        "gate",
        "made",
        "door"
    ],
    "sg:website":"hoerzer.co.at",
    "wof:name":"M\u00f6beltischlerei Franz H\u00f6rzer",
    "wof:placetype":"venue"
},
  "geometry": {"coordinates":[15.9831638336,47.196937561],"type":"Point"}
}