{
  "type": "Feature",
  "properties": {
    "addr:full":"Schmerlingstr 2/16 Innsbruck Tirol 6020",
    "addr:housenumber":"2 / 16",
    "addr:postcode":"6020",
    "addr:street":"Schmerlingstr;Tirol",
    "iso:country":"AT",
    "sg:address":"Schmerlingstr 2/16",
    "sg:city":"Innsbruck",
    "sg:orig_category":"Modellagenturen",
    "sg:phone":"+43 4351 2934413",
    "sg:postcode":"6020",
    "sg:province":"Tirol",
    "wof:name":"Unic Events Int",
    "wof:placetype":"venue"
},
  "geometry": {"coordinates":[11.3918247223,47.2636947632],"type":"Point"}
}