{
  "type": "Feature",
  "properties": {
    "iso:country":"AT",
    "sg:address":"Achenseestrasse 62",
    "sg:city":"Jenbach",
    "sg:classifiers":[
        {
            "category":"Structure",
            "subcategory":"Building",
            "type":"Public Place"
        }
    ],
    "sg:phone":"+43 5244 62287",
    "sg:postcode":"6200",
    "sg:province":"Tirol",
    "sg:tags":[
        "apartment"
    ],
    "wof:name":"Aste & Ausserladscheider GesmbH",
    "wof:placetype":"venue"
},
  "geometry": {"coordinates":[11.771109581,47.395324707],"type":"Point"}
}