{
  "type": "Feature",
  "properties": {
    "addr:full":"Industriestr 22 Wolfsberg K\u00e4rnten 9400",
    "addr:housenumber":"22;kaernten",
    "addr:postcode":"9400",
    "addr:street":"Industriestr",
    "iso:country":"AT",
    "sg:address":"Industriestr 22",
    "sg:city":"Wolfsberg",
    "sg:orig_category":"Schlossereien",
    "sg:phone":"+43 4352 28840",
    "sg:postcode":"9400",
    "sg:province":"K\u00e4rnten",
    "wof:name":"Pfennich Michael",
    "wof:placetype":"venue"
},
  "geometry": {"coordinates":[14.8408641815,46.8210868835],"type":"Point"}
}