{
  "type": "Feature",
  "properties": {
    "addr:full":"Lorenz-Mandl-G 62/12 Wien Wien 1160",
    "addr:housenumber":"62 / 12",
    "addr:postcode":"1160",
    "addr:street":"Lorenz-Mandl-G",
    "iso:country":"AT",
    "sg:address":"Lorenz-Mandl-G 62/12",
    "sg:city":"Wien",
    "sg:orig_category":"Appartements / Ferienwohnungen",
    "sg:phone":"+43 4314 933257",
    "sg:postcode":"1160",
    "sg:province":"Wien",
    "sg:website":"vienna.apartments.at",
    "wof:name":"Apartmentpension Ing Walter Szabo VIENNA APARTMENTS",
    "wof:placetype":"venue"
},
  "geometry": {"coordinates":[16.3078422546,48.2130126953],"type":"Point"}
}