{
  "type": "Feature",
  "properties": {
    "addr:full":"Nr 24 Thening Ober\u00f6sterreich 4062",
    "addr:postcode":"4062",
    "addr:street":"Nr 24 Thening Oberoesterreich",
    "iso:country":"AT",
    "sg:address":"Nr 24",
    "sg:city":"Thening",
    "sg:orig_category":"Optische Artikel",
    "sg:phone":"+43 4372 21608",
    "sg:postcode":"4062",
    "sg:province":"Ober\u00f6sterreich",
    "wof:name":"MORGAN Marketing u Vertriebs GmbH",
    "wof:placetype":"venue"
},
  "geometry": {"coordinates":[14.1588783264,48.2645797729],"type":"Point"}
}