{
  "type": "Feature",
  "properties": {
    "addr:full":"Nr 92 Holzgau Tirol 6654",
    "addr:postcode":"6654",
    "addr:street":"Nr;Holzgau Tirol",
    "iso:country":"AT",
    "sg:address":"Nr 92",
    "sg:city":"Holzgau",
    "sg:orig_category":"Pensionen / Privatzimmer",
    "sg:phone":"+43 5633 5294",
    "sg:postcode":"6654",
    "sg:province":"Tirol",
    "wof:name":"G\u00e4stehaus Alpenruh",
    "wof:placetype":"venue"
},
  "geometry": {"coordinates":[10.3436069489,47.2595977783],"type":"Point"}
}