{
  "type": "Feature",
  "properties": {
    "addr:full":"Euring 8 Saalfelden am Steinernen Meer Salzburg 5760",
    "addr:housenumber":"8",
    "addr:postcode":"5760",
    "addr:street":"Euring",
    "iso:country":"AT",
    "sg:address":"Euring 8",
    "sg:city":"Saalfelden am Steinernen Meer",
    "sg:orig_category":"Tischlereien",
    "sg:phone":"+43 4366 42250504",
    "sg:postcode":"5760",
    "sg:province":"Salzburg",
    "wof:name":"Tischlerei Zand-Hotter",
    "wof:placetype":"venue"
},
  "geometry": {"coordinates":[12.8199071884,47.4512329102],"type":"Point"}
}