{
  "type": "Feature",
  "properties": {
    "iso:country":"AT",
    "sg:address":"Bahng 42",
    "sg:city":"Wiener Neustadt",
    "sg:orig_category":"Personalbereitstellung",
    "sg:phone":"+43 664 3206437",
    "sg:postcode":"2700",
    "sg:province":"Nieder\u00f6sterreich",
    "wof:name":"Help PersonalbereitstellungsgesmbH",
    "wof:placetype":"venue"
},
  "geometry": {"coordinates":[16.2388801575,47.8113555908],"type":"Point"}
}