{
  "type": "Feature",
  "properties": {
    "addr:full":"Eitweg K\u00e4rnten 9421",
    "addr:postcode":"9421",
    "addr:street":"Kaernten",
    "iso:country":"AT",
    "sg:city":"Eitweg",
    "sg:orig_category":"Non-Classified Establishments",
    "sg:phone":"+43 4355 3073",
    "sg:postcode":"9421",
    "sg:province":"K\u00e4rnten",
    "wof:name":"Bundesheer ORS Speikkogel",
    "wof:placetype":"venue"
},
  "geometry": {"coordinates":[14.8929834366,46.7751846313],"type":"Point"}
}