{
  "type": "Feature",
  "properties": {
    "addr:full":"Lehenweg 4 Rankweil Vorarlberg 6830",
    "addr:housenumber":"4",
    "addr:postcode":"6830",
    "addr:street":"Lehenweg",
    "iso:country":"AT",
    "sg:address":"Lehenweg 4",
    "sg:city":"Rankweil",
    "sg:orig_category":"Installationsmaterialien",
    "sg:phone":"+43 4355 2260113",
    "sg:postcode":"6830",
    "sg:province":"Vorarlberg",
    "wof:name":"Wolseley Austria AG",
    "wof:placetype":"venue"
},
  "geometry": {"coordinates":[9.6239156723,47.2717056274],"type":"Point"}
}