{
  "type": "Feature",
  "properties": {
    "iso:country":"AT",
    "sg:address":"Weinbergg 15",
    "sg:city":"Krummnu\u00dfbaum",
    "sg:orig_category":"Werbegestalter",
    "sg:phone":"+43 2757 85580",
    "sg:postcode":"3375",
    "sg:province":"Nieder\u00f6sterreich",
    "wof:name":"Mail & Plott",
    "wof:placetype":"venue"
},
  "geometry": {"coordinates":[-90.31578063960001,39.3304100037],"type":"Point"}
}