{
  "type": "Feature",
  "properties": {
    "iso:country":"AT",
    "sg:address":"Stadtpl 30",
    "sg:city":"Steyr",
    "sg:orig_category":"Schlankheitsinstitute",
    "sg:phone":"+43 7252 45412",
    "sg:postcode":"4400",
    "sg:province":"Ober\u00f6sterreich",
    "wof:name":"Figurella International GesmbH",
    "wof:placetype":"venue"
},
  "geometry": {"coordinates":[14.4190254211,48.0390396118],"type":"Point"}
}