{
  "type": "Feature",
  "properties": {
    "addr:full":"Rathausplatz 51  Weitra Nieder\u00f6sterreich 3970",
    "addr:housenumber":"51",
    "addr:postcode":"3970",
    "addr:street":"Rathausplatz",
    "iso:country":"AT",
    "sg:address":"Rathausplatz 51 ",
    "sg:city":"Weitra",
    "sg:classifiers":[
        {
            "category":"Building & Trades",
            "subcategory":"Plumbing",
            "type":"Services"
        }
    ],
    "sg:phone":"+43 2856 2250",
    "sg:postcode":"3970",
    "sg:province":"Nieder\u00f6sterreich",
    "sg:tags":[
        "supraregional",
        "gas"
    ],
    "wof:name":"Ernest Zederbauer",
    "wof:placetype":"venue"
},
  "geometry": {"coordinates":[14.8918180466,48.7006492615],"type":"Point"}
}