{
  "type": "Feature",
  "properties": {
    "addr:full":"Breitstetter Str 12 Leopoldsdorf im Marchfelde Nieder\u00f6sterreich 2285",
    "addr:postcode":"2285",
    "addr:street":"Str 12",
    "iso:country":"AT",
    "sg:address":"Breitstetter Str 12",
    "sg:city":"Leopoldsdorf im Marchfelde",
    "sg:orig_category":"Autoelektrik U -Ersatzteile",
    "sg:phone":"+43 4322 162325",
    "sg:postcode":"2285",
    "sg:province":"Nieder\u00f6sterreich",
    "wof:name":"Kunze J",
    "wof:placetype":"venue"
},
  "geometry": {"coordinates":[16.7075176239,48.2018241882],"type":"Point"}
}