{
  "type": "Feature",
  "properties": {
    "iso:country":"AT",
    "sg:address":"Wagramer Str 5",
    "sg:city":"Wien",
    "sg:orig_category":"Ingenieurkonsulenten / Zivilingenieure",
    "sg:phone":"+43 1 2696369",
    "sg:postcode":"1220",
    "sg:province":"Wien",
    "wof:name":"aetas Ziviltechniker GmbH Dipl-Ing",
    "wof:placetype":"venue"
},
  "geometry": {"coordinates":[16.4171276093,48.23254776],"type":"Point"}
}