{
  "type": "Feature",
  "properties": {
    "addr:full":"Dorf 20 Gurten Ober\u00f6sterreich 4942",
    "addr:housenumber":"20",
    "addr:postcode":"4942",
    "addr:street":"Dorf",
    "iso:country":"AT",
    "sg:address":"Dorf 20",
    "sg:city":"Gurten",
    "sg:classifiers":[
        {
            "category":"Home & Garden",
            "subcategory":"Building Materials",
            "type":"Retail Goods"
        }
    ],
    "sg:phone":"+43 7757 6531",
    "sg:postcode":"4942",
    "sg:province":"Ober\u00f6sterreich",
    "sg:tags":[
        "wood",
        "banister"
    ],
    "sg:website":"wohnqualitaet.co.at",
    "wof:name":"Herbert Daxberger",
    "wof:placetype":"venue"
},
  "geometry": {"coordinates":[13.3715734482,48.2603683472],"type":"Point"}
}