{
  "type": "Feature",
  "properties": {
    "addr:full":"Linke Wienzeile 236 Wien Wien 1150",
    "addr:housenumber":"236",
    "addr:postcode":"1150",
    "addr:street":"Linke Wienzeile",
    "iso:country":"AT",
    "sg:address":"Linke Wienzeile 236",
    "sg:city":"Wien",
    "sg:orig_category":"Steuerberatung",
    "sg:phone":"+43 1 5993535",
    "sg:postcode":"1150",
    "sg:province":"Wien",
    "wof:name":"\u00d6sterreicher Heinz Dkfm",
    "wof:placetype":"venue"
},
  "geometry": {"coordinates":[16.3346176147,48.1853637695],"type":"Point"}
}