{
  "type": "Feature",
  "properties": {
    "addr:full":"Kircheng 9 Wampersdorf Nieder\u00f6sterreich 2485",
    "addr:housenumber":"9",
    "addr:postcode":"2485",
    "addr:street":"Kircheng",
    "iso:country":"AT",
    "sg:address":"Kircheng 9",
    "sg:city":"Wampersdorf",
    "sg:orig_category":"Elektronische Bauelemente U Bauteile",
    "sg:phone":"+43 4326 2375968",
    "sg:postcode":"2485",
    "sg:province":"Nieder\u00f6sterreich",
    "wof:name":"MC - Components Ewald Mogg GmbH",
    "wof:placetype":"venue"
},
  "geometry": {"coordinates":[16.4313144684,47.9171142578],"type":"Point"}
}