{
  "type": "Feature",
  "properties": {
    "iso:country":"AT",
    "sg:address":"Jasomirgottstr 3-5",
    "sg:city":"Wien",
    "sg:orig_category":"Weine / Einzelhandel",
    "sg:phone":"+43 1 53509160",
    "sg:postcode":"1010",
    "sg:province":"Wien",
    "wof:name":"Wein & Co HandelsgesmbH",
    "wof:placetype":"venue"
},
  "geometry": {"coordinates":[16.3718070984,48.208946228],"type":"Point"}
}