{
  "type": "Feature",
  "properties": {
    "addr:full":"Marktpl 1 Haag am Hausruck Ober\u00f6sterreich 4680",
    "addr:housenumber":"1",
    "addr:postcode":"4680",
    "addr:street":"Marktpl",
    "iso:country":"AT",
    "sg:address":"Marktpl 1",
    "sg:city":"Haag am Hausruck",
    "sg:orig_category":"Installationsunternehmen",
    "sg:phone":"+43 7732 20250",
    "sg:postcode":"4680",
    "sg:province":"Ober\u00f6sterreich",
    "wof:name":"TRAXLER InstallationsgmbH",
    "wof:placetype":"venue"
},
  "geometry": {"coordinates":[13.6409282684,48.1849136353],"type":"Point"}
}