{
  "type": "Feature",
  "properties": {
    "addr:full":"Pfarrhofgasse 13 Wien Wien 1030",
    "addr:housenumber":"13",
    "addr:postcode":"1030",
    "addr:street":"Pfarrhofgasse",
    "iso:country":"AT",
    "sg:address":"Pfarrhofgasse 13",
    "sg:city":"Wien",
    "sg:classifiers":[
        {
            "category":"Professional",
            "subcategory":"Printing & Photocopies",
            "type":"Services"
        }
    ],
    "sg:phone":"+43 1 71333510",
    "sg:postcode":"1030",
    "sg:province":"Wien",
    "sg:tags":[
        "full-service"
    ],
    "sg:website":"druck-seitz.at",
    "wof:name":"Druckerei Seitz Ges.m.b.H.",
    "wof:placetype":"venue"
},
  "geometry": {"coordinates":[16.3913173676,48.2005805969],"type":"Point"}
}