{
  "type": "Feature",
  "properties": {
    "addr:full":"G\u00fcssinger Strasse 1 Gerersdorf Burgenland 7542",
    "addr:housenumber":"1",
    "addr:postcode":"7542",
    "addr:street":"Guessinger Strasse",
    "iso:country":"AT",
    "sg:address":"G\u00fcssinger Strasse 1",
    "sg:city":"Gerersdorf",
    "sg:classifiers":[
        {
            "category":"Food & Beverages",
            "subcategory":"Fruits & Vegetables",
            "type":"Retail Goods"
        }
    ],
    "sg:phone":"+43 3322 421210",
    "sg:postcode":"7542",
    "sg:province":"Burgenland",
    "sg:tags":[
        "juice",
        "nectar"
    ],
    "sg:website":"guessinger.at",
    "wof:name":"G\u00fcssinger Mineralwasser Ges.m.b.H.",
    "wof:placetype":"venue"
},
  "geometry": {"coordinates":[16.2526264191,47.0685806274],"type":"Point"}
}