{
  "type": "Feature",
  "properties": {
    "iso:country":"AT",
    "sg:address":"Sterneckstr 15",
    "sg:city":"Klagenfurt",
    "sg:orig_category":"Forschungsinstitute",
    "sg:phone":"+43 463 27006100",
    "sg:postcode":"9020",
    "sg:province":"K\u00e4rnten",
    "wof:name":"Institut f Interdisziplin\u00e4re Forschung und Fortbildung",
    "wof:placetype":"venue"
},
  "geometry": {"coordinates":[14.2999477386,46.6265182495],"type":"Point"}
}