{
  "type": "Feature",
  "properties": {
    "iso:country":"AT",
    "sg:address":"Budinskyg 12",
    "sg:city":"Wien",
    "sg:orig_category":"Freizeit- U Sportbekleidung",
    "sg:phone":"+43 4313 679444",
    "sg:postcode":"1190",
    "sg:province":"Wien",
    "wof:name":"CASALL SPORTSWEAR Generalvertr f \u00f6sterreich L\u00fctze Handels Nfg GmbH & CO KEG",
    "wof:placetype":"venue"
},
  "geometry": {"coordinates":[16.336648941,48.2419891357],"type":"Point"}
}