{
  "type": "Feature",
  "properties": {
    "iso:country":"AT",
    "sg:address":"Karningstr 11",
    "sg:city":"Leonding",
    "sg:orig_category":"Werbegrafik- U Grafik-Design",
    "sg:phone":"+43 732 674672",
    "sg:postcode":"4060",
    "sg:province":"Ober\u00f6sterreich",
    "wof:name":"Hopf Wilfried Ass Prof",
    "wof:placetype":"venue"
},
  "geometry": {"coordinates":[14.2443256378,48.2805137634],"type":"Point"}
}