{
  "type": "Feature",
  "properties": {
    "addr:full":"Maria-Theresien-Str 16/3 Innsbruck Tirol 6020",
    "addr:housenumber":"16 / 3",
    "addr:postcode":"6020",
    "addr:street":"Maria-Theresien-Str;Tirol",
    "iso:country":"AT",
    "sg:address":"Maria-Theresien-Str 16/3",
    "sg:city":"Innsbruck",
    "sg:orig_category":"Politische Parteien",
    "sg:phone":"+43 512 539060",
    "sg:postcode":"6020",
    "sg:province":"Tirol",
    "wof:name":"\u00f6VP - Tiroler Volkspartei Tiroler Frauenbewegung",
    "wof:placetype":"venue"
},
  "geometry": {"coordinates":[11.3938131332,47.2658729553],"type":"Point"}
}