{
  "type": "Feature",
  "properties": {
    "iso:country":"AT",
    "sg:address":"Hauptpl 32",
    "sg:city":"Voitsberg",
    "sg:orig_category":"Filmproduktionen",
    "sg:phone":"+43 676 6366700",
    "sg:postcode":"8570",
    "sg:province":"Steiermark",
    "wof:name":"Boomerang Video",
    "wof:placetype":"venue"
},
  "geometry": {"coordinates":[15.149933815,47.0497322083],"type":"Point"}
}