{
  "type": "Feature",
  "properties": {
    "addr:full":"Piaristeng 45 Wien Wien 1080",
    "addr:housenumber":"45",
    "addr:postcode":"1080",
    "addr:street":"Piaristeng",
    "iso:country":"AT",
    "sg:address":"Piaristeng 45",
    "sg:city":"Wien",
    "sg:classifiers":[
        {
            "category":"Restaurant",
            "type":"Food & Drink"
        }
    ],
    "sg:phone":"+43 1 4059152",
    "sg:postcode":"1080",
    "sg:province":"Wien",
    "wof:name":"K & K Restaurant Piaristenkeller",
    "wof:placetype":"venue"
},
  "geometry": {"coordinates":[16.3500652313,48.210849762],"type":"Point"}
}