{
  "type": "Feature",
  "properties": {
    "addr:full":"Schillerstr 7-9 Weiz Steiermark 8160",
    "addr:housenumber":"7-9",
    "addr:postcode":"8160",
    "addr:street":"Schillerstr",
    "iso:country":"AT",
    "sg:address":"Schillerstr 7-9",
    "sg:city":"Weiz",
    "sg:orig_category":"Psychotherapie",
    "sg:phone":"+43 3172 355615",
    "sg:postcode":"8160",
    "sg:province":"Steiermark",
    "wof:name":"Psychotherapeutische Praxis - Harald Sattler - Gottfried Engelmann",
    "wof:placetype":"venue"
},
  "geometry": {"coordinates":[15.631149292,47.2195091248],"type":"Point"}
}