{
  "type": "Feature",
  "properties": {
    "addr:full":"F Trautenberger-Str 33 Purkersdorf Nieder\u00f6sterreich 3002",
    "addr:housenumber":"33",
    "addr:postcode":"3002",
    "iso:country":"AT",
    "sg:address":"F Trautenberger-Str 33",
    "sg:city":"Purkersdorf",
    "sg:orig_category":"Immobilienmakler",
    "sg:phone":"+43 2231 61231",
    "sg:postcode":"3002",
    "sg:province":"Nieder\u00f6sterreich",
    "wof:name":"Moser Immobilien",
    "wof:placetype":"venue"
},
  "geometry": {"coordinates":[16.1680526733,48.2102737427],"type":"Point"}
}