{
  "type": "Feature",
  "properties": {
    "addr:full":"Schlo\u00dfstrasse 1 Paternion K\u00e4rnten 9711",
    "addr:housenumber":"1",
    "addr:postcode":"9711",
    "addr:street":"Schlossstrasse;Kaernten",
    "iso:country":"AT",
    "sg:address":"Schlo\u00dfstrasse 1",
    "sg:city":"Paternion",
    "sg:classifiers":[
        {
            "category":"Manufacturing",
            "subcategory":"Wood Products",
            "type":"Manufacturing & Wholesale Goods"
        }
    ],
    "sg:phone":"+43 4245 24310",
    "sg:postcode":"9711",
    "sg:province":"K\u00e4rnten",
    "sg:tags":[
        "firewood"
    ],
    "wof:name":"KARINZIA Holz GesmbH & Co KG",
    "wof:placetype":"venue"
},
  "geometry": {"coordinates":[13.6386032104,46.7113304138],"type":"Point"}
}