{
  "type": "Feature",
  "properties": {
    "addr:full":"Nibelungenstr 48 Persenbeug Nieder\u00f6sterreich 3680",
    "addr:housenumber":"48",
    "addr:postcode":"3680",
    "addr:street":"Nibelungenstr",
    "iso:country":"AT",
    "sg:address":"Nibelungenstr 48",
    "sg:city":"Persenbeug",
    "sg:orig_category":"Tapezierer U Dekorateure",
    "sg:phone":"+43 4374 12525090",
    "sg:postcode":"3680",
    "sg:province":"Nieder\u00f6sterreich",
    "wof:name":"Brandstetter GesmbH & Co KG",
    "wof:placetype":"venue"
},
  "geometry": {"coordinates":[15.0926437378,48.1889419556],"type":"Point"}
}