{
  "type": "Feature",
  "properties": {
    "addr:full":"Josef Heroldstr. 15 Kitzb\u00fchel Tirol 6370",
    "addr:housenumber":"15",
    "addr:postcode":"6370",
    "addr:street":"Kitzbuehel Tirol",
    "iso:country":"AT",
    "sg:address":"Josef Heroldstr. 15",
    "sg:city":"Kitzb\u00fchel",
    "sg:classifiers":[
        {
            "category":"Personal",
            "subcategory":"Shoe Repair & Shine",
            "type":"Services"
        }
    ],
    "sg:phone":"+43 4353 5664261",
    "sg:postcode":"6370",
    "sg:province":"Tirol",
    "sg:tags":[
        "leather"
    ],
    "wof:name":"KASPAR FRAUENSCHUH GESMBH",
    "wof:placetype":"venue"
},
  "geometry": {"coordinates":[12.390370369,47.4440727234],"type":"Point"}
}