{
  "type": "Feature",
  "properties": {
    "iso:country":"AT",
    "sg:address":"Mautner-Markhof-G 40",
    "sg:city":"Wien",
    "sg:orig_category":"Personalbereitstellung",
    "sg:phone":"+43 4317 483505",
    "sg:postcode":"1110",
    "sg:province":"Wien",
    "wof:name":"FairWork Personalmanagement GmbH",
    "wof:placetype":"venue"
},
  "geometry": {"coordinates":[16.4206485748,48.1767692566],"type":"Point"}
}