{
  "type": "Feature",
  "properties": {
    "addr:full":"Schlo\u00dfpl 13 Laxenburg Nieder\u00f6sterreich 2361",
    "addr:housenumber":"13",
    "addr:postcode":"2361",
    "addr:street":"Schlosspl",
    "iso:country":"AT",
    "sg:address":"Schlo\u00dfpl 13",
    "sg:city":"Laxenburg",
    "sg:orig_category":"Ingenieurkonsulenten / Zivilingenieure",
    "sg:phone":"+43 2236 710344",
    "sg:postcode":"2361",
    "sg:province":"Nieder\u00f6sterreich",
    "wof:name":"Water & Waste Ziviltechniker-GesmbH",
    "wof:placetype":"venue"
},
  "geometry": {"coordinates":[16.3563690186,48.0674743652],"type":"Point"}
}