{
  "type": "Feature",
  "properties": {
    "addr:full":"Ankershofenstr. 43 Klagenfurt K\u00e4rnten 9020",
    "addr:housenumber":"43",
    "addr:postcode":"9020",
    "addr:street":"Ankershofenstr.;Kaernten",
    "iso:country":"AT",
    "sg:address":"Ankershofenstr. 43",
    "sg:city":"Klagenfurt",
    "sg:classifiers":[
        {
            "category":"Manufacturing",
            "subcategory":"Glass & Minerals",
            "type":"Manufacturing & Wholesale Goods"
        }
    ],
    "sg:phone":"+43 4346 357797",
    "sg:postcode":"9020",
    "sg:province":"K\u00e4rnten",
    "wof:name":"FRITZ STARZACHER INH. MAG. CHRISTIAN STARZACHER",
    "wof:placetype":"venue"
},
  "geometry": {"coordinates":[14.296040535,46.6169967651],"type":"Point"}
}