{
  "type": "Feature",
  "properties": {
    "iso:country":"AT",
    "sg:address":"Markgraf-R\u00fcdiger-Str 3/Top 7-8",
    "sg:city":"Wien",
    "sg:orig_category":"Videoanlagen / Vermietung",
    "sg:phone":"+43 4312 081040",
    "sg:postcode":"1150",
    "sg:province":"Wien",
    "wof:name":"mediaprofis.net",
    "wof:placetype":"venue"
},
  "geometry": {"coordinates":[16.3320903778,48.2006416321],"type":"Point"}
}