{
  "type": "Feature",
  "properties": {
    "addr:full":"Georgig 25 Graz Steiermark 8020",
    "addr:housenumber":"25",
    "addr:postcode":"8020",
    "addr:street":"Georgig",
    "iso:country":"AT",
    "sg:address":"Georgig 25",
    "sg:city":"Graz",
    "sg:orig_category":"Fahrschulen",
    "sg:phone":"+43 316 464000",
    "sg:postcode":"8020",
    "sg:province":"Steiermark",
    "wof:name":"Fahrschule Powerdrive Eggenberg",
    "wof:placetype":"venue"
},
  "geometry": {"coordinates":[15.4046449661,47.0728149414],"type":"Point"}
}