{
  "type": "Feature",
  "properties": {
    "addr:full":"Kaplanstr. 3  Lambach Ober\u00f6sterreich 4650",
    "addr:housenumber":"3",
    "addr:postcode":"4650",
    "addr:street":"Kaplanstr.",
    "iso:country":"AT",
    "sg:address":"Kaplanstr. 3 ",
    "sg:city":"Lambach",
    "sg:classifiers":[
        {
            "category":"Manufacturing",
            "subcategory":"Metals",
            "type":"Manufacturing & Wholesale Goods"
        }
    ],
    "sg:phone":"+43 4372 45243240",
    "sg:postcode":"4650",
    "sg:province":"Ober\u00f6sterreich",
    "sg:tags":[
        "processing"
    ],
    "wof:name":"KEPP-STANZTECHNIK GES.MBH",
    "wof:placetype":"venue"
},
  "geometry": {"coordinates":[13.857011795,48.0898361206],"type":"Point"}
}