{
  "type": "Feature",
  "properties": {
    "addr:full":"Forellenweg 42 Hallwang Salzburg 5300",
    "addr:housenumber":"42",
    "addr:postcode":"5300",
    "addr:street":"Forellenweg;Salzburg",
    "iso:country":"AT",
    "sg:address":"Forellenweg 42",
    "sg:city":"Hallwang",
    "sg:orig_category":"Fische U Fischwaren / Erzeugung U Gro\u00c3\u0178handel",
    "sg:phone":"+43 662 660190",
    "sg:postcode":"5300",
    "sg:province":"Salzburg",
    "wof:name":"Krieg Reinhard",
    "wof:placetype":"venue"
},
  "geometry": {"coordinates":[13.0866565704,47.8578681946],"type":"Point"}
}