{
  "type": "Feature",
  "properties": {
    "addr:full":"Uferg 18 Obernberg am Inn Ober\u00f6sterreich 4982",
    "addr:housenumber":"18",
    "addr:postcode":"4982",
    "addr:street":"Uferg",
    "iso:country":"AT",
    "sg:address":"Uferg 18",
    "sg:city":"Obernberg am Inn",
    "sg:orig_category":"\u00c3\u201erzte / F Allgemeinmedizin",
    "sg:phone":"+43 7758 22600",
    "sg:postcode":"4982",
    "sg:province":"Ober\u00f6sterreich",
    "wof:name":"Koller Ortwin Dr",
    "wof:placetype":"venue"
},
  "geometry": {"coordinates":[13.3326597214,48.321269989],"type":"Point"}
}