{
  "type": "Feature",
  "properties": {
    "iso:country":"AT",
    "sg:address":"Untere Walserberger Str 131",
    "sg:city":"Wals",
    "sg:orig_category":"Zahntechnische Laboratorien",
    "sg:phone":"+43 4366 2854539",
    "sg:postcode":"5071",
    "sg:province":"Salzburg",
    "wof:name":"Dental Technik Wilhelm Eder GesmbH",
    "wof:placetype":"venue"
},
  "geometry": {"coordinates":[12.9512901306,47.7780342102],"type":"Point"}
}