{
  "type": "Feature",
  "properties": {
    "addr:full":"Hauptstr 56 St. Johann im Pongau Salzburg 5600",
    "addr:housenumber":"56",
    "addr:postcode":"5600",
    "addr:street":"Hauptstr;Salzburg",
    "iso:country":"AT",
    "sg:address":"Hauptstr 56",
    "sg:city":"St. Johann im Pongau",
    "sg:orig_category":"Damenmoden",
    "sg:phone":"+43 6412 4237",
    "sg:postcode":"5600",
    "sg:province":"Salzburg",
    "wof:name":"Gasser Ida",
    "wof:placetype":"venue"
},
  "geometry": {"coordinates":[13.1995458603,47.3453483582],"type":"Point"}
}