{
  "type": "Feature",
  "properties": {
    "iso:country":"AT",
    "sg:address":"Landstr 26",
    "sg:city":"Linz",
    "sg:classifiers":[
        {
            "category":"Organizations",
            "subcategory":"Community Association",
            "type":"Services"
        }
    ],
    "sg:phone":"+43 4373 2784777",
    "sg:postcode":"4020",
    "sg:province":"Ober\u00f6sterreich",
    "sg:tags":[
        "relation",
        "public"
    ],
    "wof:name":"PLEON PUBLICO Public Relations GmbH",
    "wof:placetype":"venue"
},
  "geometry": {"coordinates":[14.2891712189,48.30260849],"type":"Point"}
}