{
  "type": "Feature",
  "properties": {
    "iso:country":"AT",
    "sg:address":"Nr 36",
    "sg:city":"Marbach an der Donau",
    "sg:orig_category":"Volksschulen",
    "sg:phone":"+43 4374 13374",
    "sg:postcode":"3671",
    "sg:province":"Nieder\u00f6sterreich",
    "wof:name":"Volksschule",
    "wof:placetype":"venue"
},
  "geometry": {"coordinates":[15.1509618759,48.2142028809],"type":"Point"}
}