{
  "type": "Feature",
  "properties": {
    "addr:full":"Emmerich Berger-Str 13 Gm\u00fcnd Nieder\u00f6sterreich 3950",
    "addr:housenumber":"13",
    "addr:postcode":"3950",
    "addr:street":"Berger-Str;Niederoesterreich",
    "iso:country":"AT",
    "sg:address":"Emmerich Berger-Str 13",
    "sg:city":"Gm\u00fcnd",
    "sg:orig_category":"Freizeit- U Sportbekleidung",
    "sg:phone":"+43 2852 54241",
    "sg:postcode":"3950",
    "sg:province":"Nieder\u00f6sterreich",
    "wof:name":"Sport St\u00f6ckl GesmbH",
    "wof:placetype":"venue"
},
  "geometry": {"coordinates":[14.977730751,48.7657661438],"type":"Point"}
}