{
  "type": "Feature",
  "properties": {
    "addr:full":"Judendorfer Str 27 Gratwein Steiermark 8112",
    "addr:postcode":"8112",
    "addr:street":"Str",
    "iso:country":"AT",
    "sg:address":"Judendorfer Str 27",
    "sg:city":"Gratwein",
    "sg:orig_category":"Furniere",
    "sg:phone":"+43 3124 516500",
    "sg:postcode":"8112",
    "sg:province":"Steiermark",
    "wof:name":"Furnierwerk Merkscha GesmbH",
    "wof:placetype":"venue"
},
  "geometry": {"coordinates":[15.3240289688,47.1272392273],"type":"Point"}
}