{
  "type": "Feature",
  "properties": {
    "addr:full":"Hofmark 60 Goldegg Salzburg 5622",
    "addr:housenumber":"60",
    "addr:postcode":"5622",
    "addr:street":"Hofmark;Salzburg",
    "iso:country":"AT",
    "sg:address":"Hofmark 60",
    "sg:city":"Goldegg",
    "sg:classifiers":[
        {
            "category":"Taxi",
            "type":"Transportation"
        }
    ],
    "sg:phone":"+43 4364 158106",
    "sg:postcode":"5622",
    "sg:province":"Salzburg",
    "sg:tags":[
        "personentransporte",
        "u"
    ],
    "wof:name":"Harlander Wolfgang",
    "wof:placetype":"venue"
},
  "geometry": {"coordinates":[13.099439621,47.3187294006],"type":"Point"}
}