{
  "type": "Feature",
  "properties": {
    "addr:full":"Gro\u00dftraberg 50 Traberg Ober\u00f6sterreich 4183",
    "addr:housenumber":"50",
    "addr:postcode":"4183",
    "addr:street":"Grosstraberg;Oberoesterreich",
    "iso:country":"AT",
    "sg:address":"Gro\u00dftraberg 50",
    "sg:city":"Traberg",
    "sg:orig_category":"Tischlereien",
    "sg:phone":"+43 7218 253",
    "sg:postcode":"4183",
    "sg:province":"Ober\u00f6sterreich",
    "wof:name":"Keplinger Alfred",
    "wof:placetype":"venue"
},
  "geometry": {"coordinates":[14.2051534653,48.512172699],"type":"Point"}
}