{
  "type": "Feature",
  "properties": {
    "addr:full":"Hauptstr 31-33 Kindberg Steiermark 8650",
    "addr:postcode":"31-33;8650",
    "addr:street":"Hauptstr",
    "iso:country":"AT",
    "sg:address":"Hauptstr 31-33",
    "sg:city":"Kindberg",
    "sg:orig_category":"Installationsunternehmen",
    "sg:phone":"+43 4338 652275",
    "sg:postcode":"8650",
    "sg:province":"Steiermark",
    "wof:name":"Rischan Friedrich",
    "wof:placetype":"venue"
},
  "geometry": {"coordinates":[15.4498682022,47.506023407],"type":"Point"}
}