{
  "type": "Feature",
  "properties": {
    "addr:full":"Am Anger 14 Zirl Tirol 6170",
    "addr:housenumber":"14",
    "addr:postcode":"6170",
    "addr:street":"Am Anger;Tirol",
    "iso:country":"AT",
    "sg:address":"Am Anger 14",
    "sg:city":"Zirl",
    "sg:orig_category":"Hauptschulen",
    "sg:phone":"+43 5238 54013",
    "sg:postcode":"6170",
    "sg:province":"Tirol",
    "wof:name":"Hauptschule",
    "wof:placetype":"venue"
},
  "geometry": {"coordinates":[11.2390604019,47.2688827515],"type":"Point"}
}