{
  "type": "Feature",
  "properties": {
    "addr:full":"Schalser Str 20 Jenbach Tirol 6200",
    "addr:postcode":"6200",
    "addr:street":"Str 20;Tirol",
    "iso:country":"AT",
    "sg:address":"Schalser Str 20",
    "sg:city":"Jenbach",
    "sg:orig_category":"Tabaktrafiken",
    "sg:phone":"+43 5244 64521",
    "sg:postcode":"6200",
    "sg:province":"Tirol",
    "wof:name":"Stuiber Anneliese",
    "wof:placetype":"venue"
},
  "geometry": {"coordinates":[11.7763729095,47.3921318054],"type":"Point"}
}