{
  "type": "Feature",
  "properties": {
    "addr:full":"Herberthstr 2 Wolfsberg K\u00e4rnten 9400",
    "addr:housenumber":"2;kaernten",
    "addr:postcode":"9400",
    "addr:street":"Herberthstr",
    "iso:country":"AT",
    "sg:address":"Herberthstr 2",
    "sg:city":"Wolfsberg",
    "sg:orig_category":"Versicherungsunternehmen",
    "sg:phone":"+43 4352 514020",
    "sg:postcode":"9400",
    "sg:province":"K\u00e4rnten",
    "wof:name":"Generali Versicherung AG",
    "wof:placetype":"venue"
},
  "geometry": {"coordinates":[14.8400363922,46.8406295776],"type":"Point"}
}