{
  "type": "Feature",
  "properties": {
    "addr:full":"Stolbergg 20 Wien Wien 1050",
    "addr:housenumber":"20",
    "addr:postcode":"1050",
    "addr:street":"Stolbergg",
    "iso:country":"AT",
    "sg:address":"Stolbergg 20",
    "sg:city":"Wien",
    "sg:orig_category":"\u00c3\u201erzte / F Allgemeinmedizin",
    "sg:phone":"+43 1 54579550",
    "sg:postcode":"1050",
    "sg:province":"Wien",
    "wof:name":"Krapfenbauer Luzia Dr",
    "wof:placetype":"venue"
},
  "geometry": {"coordinates":[16.3609733582,48.186668396],"type":"Point"}
}