{
  "type": "Feature",
  "properties": {
    "addr:full":"Renng 10 Wien Wien 1010",
    "addr:housenumber":"10",
    "addr:postcode":"1010",
    "addr:street":"Renng",
    "iso:country":"AT",
    "sg:address":"Renng 10",
    "sg:city":"Wien",
    "sg:orig_category":"Banken U Sparkassen",
    "sg:phone":"+43 1 531350",
    "sg:postcode":"1010",
    "sg:province":"Wien",
    "wof:name":"Investkredit Bank AG",
    "wof:placetype":"venue"
},
  "geometry": {"coordinates":[16.3671607971,48.2125511169],"type":"Point"}
}