{
  "type": "Feature",
  "properties": {
    "addr:full":"Passauer Str 17 Eferding Ober\u00f6sterreich 4070",
    "addr:postcode":"4070",
    "addr:street":"Str 17",
    "iso:country":"AT",
    "sg:address":"Passauer Str 17",
    "sg:city":"Eferding",
    "sg:orig_category":"Tischlereien",
    "sg:phone":"+43 7272 3380",
    "sg:postcode":"4070",
    "sg:province":"Ober\u00f6sterreich",
    "wof:name":"MK-M\u00f6bel Stickler Jungreithmayr OEG",
    "wof:placetype":"venue"
},
  "geometry": {"coordinates":[14.0147800446,48.3093643188],"type":"Point"}
}