{
  "type": "Feature",
  "properties": {
    "addr:full":"Stattersdorf Hptstr 97 St. P\u00f6lten Nieder\u00f6sterreich 3100",
    "addr:housenumber":"97",
    "addr:postcode":"3100",
    "addr:street":"St. Poelten",
    "iso:country":"AT",
    "sg:address":"Stattersdorf Hptstr 97",
    "sg:city":"St. P\u00f6lten",
    "sg:orig_category":"Maler, Anstreicher U Lackierer",
    "sg:phone":"+43 2742 257330",
    "sg:postcode":"3100",
    "sg:province":"Nieder\u00f6sterreich",
    "wof:name":"REKO Malerei-Anstrich GmbH",
    "wof:placetype":"venue"
},
  "geometry": {"coordinates":[15.6423578262,48.1844291687],"type":"Point"}
}