{
  "type": "Feature",
  "properties": {
    "addr:full":"Binderg 10a Salzburg Salzburg 5020",
    "addr:housenumber":"10a",
    "addr:postcode":"5020",
    "addr:street":"Binderg;Salzburg",
    "iso:country":"AT",
    "sg:address":"Binderg 10a",
    "sg:city":"Salzburg",
    "sg:orig_category":"Ingenieurkonsulenten / Zivilingenieure",
    "sg:phone":"+43 662 435201",
    "sg:postcode":"5020",
    "sg:province":"Salzburg",
    "wof:name":"Kaltenb\u00f6ck Herbert Dipl-Ing",
    "wof:placetype":"venue"
},
  "geometry": {"coordinates":[13.0211305618,47.8026771545],"type":"Point"}
}