{
  "type": "Feature",
  "properties": {
    "addr:full":"Hohenbergstr 42a Wien Wien 1120",
    "addr:housenumber":"42a",
    "addr:postcode":"1120",
    "addr:street":"Hohenbergstr",
    "iso:country":"AT",
    "sg:address":"Hohenbergstr 42a",
    "sg:city":"Wien",
    "sg:orig_category":"Studentenheime",
    "sg:phone":"+43 1 8102365",
    "sg:postcode":"1120",
    "sg:province":"Wien",
    "wof:name":"Studentenheim - Pfarre Gatterh\u00f6lzl",
    "wof:placetype":"venue"
},
  "geometry": {"coordinates":[16.3189888,48.1759757996],"type":"Point"}
}