{
  "type": "Feature",
  "properties": {
    "addr:full":"Brucknerstr 39 Ried im Innkreis Ober\u00f6sterreich 4910",
    "addr:housenumber":"39",
    "addr:postcode":"4910",
    "addr:street":"Brucknerstr",
    "iso:country":"AT",
    "sg:address":"Brucknerstr 39",
    "sg:city":"Ried im Innkreis",
    "sg:orig_category":"Messen U Ausstellungen",
    "sg:phone":"+43 4377 52840110",
    "sg:postcode":"4910",
    "sg:province":"Ober\u00f6sterreich",
    "wof:name":"Rieder Messe GmbH",
    "wof:placetype":"venue"
},
  "geometry": {"coordinates":[13.481675148,48.210269928],"type":"Point"}
}