{
  "type": "Feature",
  "properties": {
    "addr:full":"Hamburgersdlg 1 Seebenstein Nieder\u00f6sterreich 2824",
    "addr:housenumber":"1",
    "addr:postcode":"2824",
    "addr:street":"Hamburgersdlg",
    "iso:country":"AT",
    "sg:address":"Hamburgersdlg 1",
    "sg:city":"Seebenstein",
    "sg:orig_category":"Ingenieurkonsulenten / Zivilingenieure",
    "sg:phone":"+43 2627 821970",
    "sg:postcode":"2824",
    "sg:province":"Nieder\u00f6sterreich",
    "wof:name":"IUT Ingenieurgemeinschaft Innovative Umwelttechnik GmbH",
    "wof:placetype":"venue"
},
  "geometry": {"coordinates":[16.1443691254,47.6989631653],"type":"Point"}
}