{
  "type": "Feature",
  "properties": {
    "iso:country":"AT",
    "sg:address":"Raaberbahng 3/10/9",
    "sg:city":"Sollenau",
    "sg:orig_category":"Werbeagenturen",
    "sg:phone":"+43 676 9496108",
    "sg:postcode":"2601",
    "sg:province":"Nieder\u00f6sterreich",
    "wof:name":"Werbeagentur - Gerald Spiess",
    "wof:placetype":"venue"
},
  "geometry": {"coordinates":[16.2494049072,47.8965682983],"type":"Point"}
}