{
  "type": "Feature",
  "properties": {
    "addr:full":"Am Bahnhof 12 Wien Wien 1220",
    "addr:housenumber":"12",
    "addr:postcode":"1220",
    "addr:street":"Am Bahnhof",
    "iso:country":"AT",
    "sg:address":"Am Bahnhof 12",
    "sg:city":"Wien",
    "sg:orig_category":"Optiker",
    "sg:phone":"+43 1 28251990",
    "sg:postcode":"1220",
    "sg:province":"Wien",
    "wof:name":"Fellner Optiker GesmbH",
    "wof:placetype":"venue"
},
  "geometry": {"coordinates":[16.4509449005,48.2233505249],"type":"Point"}
}