{
  "type": "Feature",
  "properties": {
    "addr:full":"Schopenhauerstr 3 Wien Wien 1180",
    "addr:housenumber":"3",
    "addr:postcode":"1180",
    "addr:street":"Schopenhauerstr",
    "iso:country":"AT",
    "sg:address":"Schopenhauerstr 3",
    "sg:city":"Wien",
    "sg:classifiers":[
        {
            "category":"Restaurant",
            "type":"Food & Drink"
        }
    ],
    "sg:phone":"+43 1 4022132",
    "sg:postcode":"1180",
    "sg:province":"Wien",
    "wof:name":"Stangl Heinz",
    "wof:placetype":"venue"
},
  "geometry": {"coordinates":[16.3477191925,48.2237281799],"type":"Point"}
}