{
  "type": "Feature",
  "properties": {
    "addr:full":"Wermeschstr 20 Traun Ober\u00f6sterreich 4050",
    "addr:housenumber":"20",
    "addr:postcode":"4050",
    "addr:street":"Wermeschstr",
    "iso:country":"AT",
    "sg:address":"Wermeschstr 20",
    "sg:city":"Traun",
    "sg:orig_category":"Massagen",
    "sg:phone":"+43 4372 2973882",
    "sg:postcode":"4050",
    "sg:province":"Ober\u00f6sterreich",
    "wof:name":"Oser Sabina",
    "wof:placetype":"venue"
},
  "geometry": {"coordinates":[14.2275104523,48.2301254272],"type":"Point"}
}