{
  "type": "Feature",
  "properties": {
    "addr:full":"Haseng 38 Wien Wien 1100",
    "addr:housenumber":"38",
    "addr:postcode":"1100",
    "addr:street":"Haseng",
    "iso:country":"AT",
    "sg:address":"Haseng 38",
    "sg:city":"Wien",
    "sg:orig_category":"Bibliotheken",
    "sg:phone":"+43 1 6073311",
    "sg:postcode":"1100",
    "sg:province":"Wien",
    "wof:name":"B\u00fcchereien St\u00e4dtische",
    "wof:placetype":"venue"
},
  "geometry": {"coordinates":[16.3664951324,48.1796531677],"type":"Point"}
}