{
  "type": "Feature",
  "properties": {
    "addr:full":"Wiener Str 12 Wiener Neustadt Nieder\u00f6sterreich 2700",
    "addr:postcode":"2700",
    "addr:street":"12",
    "iso:country":"AT",
    "sg:address":"Wiener Str 12",
    "sg:city":"Wiener Neustadt",
    "sg:orig_category":"Drogerien",
    "sg:phone":"+43 2622 23430",
    "sg:postcode":"2700",
    "sg:province":"Nieder\u00f6sterreich",
    "wof:name":"Gewu\u00dft wie Drogerie - Prokopp",
    "wof:placetype":"venue"
},
  "geometry": {"coordinates":[16.2455158234,47.8128814697],"type":"Point"}
}