{
  "type": "Feature",
  "properties": {
    "addr:full":"Nr 96 Leogang Salzburg 5771",
    "addr:postcode":"5771",
    "addr:street":"Nr;Leogang",
    "iso:country":"AT",
    "sg:address":"Nr 96",
    "sg:city":"Leogang",
    "sg:orig_category":"Drogerien",
    "sg:phone":"+43 6583 8437",
    "sg:postcode":"5771",
    "sg:province":"Salzburg",
    "wof:name":"St Leonhard Drogerie",
    "wof:placetype":"venue"
},
  "geometry": {"coordinates":[12.7606391907,47.4386634827],"type":"Point"}
}