{
  "type": "Feature",
  "properties": {
    "addr:full":"Grillparzg 11 Tulbing Nieder\u00f6sterreich 3434",
    "addr:housenumber":"11",
    "addr:postcode":"3434",
    "addr:street":"Grillparzg",
    "iso:country":"AT",
    "sg:address":"Grillparzg 11",
    "sg:city":"Tulbing",
    "sg:orig_category":"Chemikalien",
    "sg:phone":"+43 2273 5422",
    "sg:postcode":"3434",
    "sg:province":"Nieder\u00f6sterreich",
    "wof:name":"VDV Chemie Gro\u00dfhandel GmbH",
    "wof:placetype":"venue"
},
  "geometry": {"coordinates":[16.1047916412,48.2719764709],"type":"Point"}
}