{
  "type": "Feature",
  "properties": {
    "addr:full":"Lassallestr. 7 Wien Wien 1020",
    "addr:housenumber":"7",
    "addr:postcode":"1020",
    "addr:street":"Lassallestr.",
    "iso:country":"AT",
    "sg:address":"Lassallestr. 7",
    "sg:city":"Wien",
    "sg:classifiers":[
        {
            "category":"Banks & Credit Unions",
            "subcategory":"Financial Services",
            "type":"Services"
        }
    ],
    "sg:phone":"+43 4312 17200",
    "sg:postcode":"1020",
    "sg:province":"Wien",
    "sg:tags":[
        "banking",
        "finance",
        "insurance"
    ],
    "wof:name":"Z\u00dcRICH VERSICHERUNGS AG",
    "wof:placetype":"venue"
},
  "geometry": {"coordinates":[16.3976764679,48.2222900391],"type":"Point"}
}