{
  "type": "Feature",
  "properties": {
    "addr:full":"Ossiacher See-S\u00fcduferstr 39B Landskron K\u00e4rnten 9523",
    "addr:housenumber":"39b",
    "addr:postcode":"9523",
    "addr:street":"Kaernten",
    "iso:country":"AT",
    "sg:address":"Ossiacher See-S\u00fcduferstr 39B",
    "sg:city":"Landskron",
    "sg:classifiers":[
        {
            "category":"Professional",
            "subcategory":"Computer Services",
            "type":"Services"
        }
    ],
    "sg:phone":"+43 4342 42431848",
    "sg:postcode":"9523",
    "sg:province":"K\u00e4rnten",
    "sg:tags":[
        "software"
    ],
    "wof:name":"Stiegler Helmut - Softwareentwicklung u IT-Beratung",
    "wof:placetype":"venue"
},
  "geometry": {"coordinates":[13.8834161758,46.6343688965],"type":"Point"}
}