{
  "type": "Feature",
  "properties": {
    "addr:full":"Hunoldstr 3 Innsbruck Tirol 6020",
    "addr:housenumber":"3",
    "addr:postcode":"6020",
    "addr:street":"Hunoldstr;Tirol",
    "iso:country":"AT",
    "sg:address":"Hunoldstr 3",
    "sg:city":"Innsbruck",
    "sg:orig_category":"Friseure U Frisiersalons",
    "sg:phone":"+43 4351 2393810",
    "sg:postcode":"6020",
    "sg:province":"Tirol",
    "wof:name":"Degler Hair-Art",
    "wof:placetype":"venue"
},
  "geometry": {"coordinates":[11.4056911469,47.2635917664],"type":"Point"}
}