{
  "type": "Feature",
  "properties": {
    "addr:full":"Neusiedler Str 35-37 Eisenstadt Burgenland 7000",
    "addr:postcode":"35-37;7000",
    "addr:street":"Str",
    "iso:country":"AT",
    "sg:address":"Neusiedler Str 35-37",
    "sg:city":"Eisenstadt",
    "sg:orig_category":"Textilreinigung",
    "sg:phone":"+43 2682 67739",
    "sg:postcode":"7000",
    "sg:province":"Burgenland",
    "wof:name":"MITTERBAUER Maria GesmbH",
    "wof:placetype":"venue"
},
  "geometry": {"coordinates":[16.5306816101,47.8471336365],"type":"Point"}
}