{
  "type": "Feature",
  "properties": {
    "iso:country":"AT",
    "sg:address":"Paradeiserg 9",
    "sg:city":"Klagenfurt",
    "sg:orig_category":"Betriebseinrichtungen",
    "sg:phone":"+43 463 5021710",
    "sg:postcode":"9020",
    "sg:province":"K\u00e4rnten",
    "wof:name":"Alpos HandelsgesmbH",
    "wof:placetype":"venue"
},
  "geometry": {"coordinates":[14.3109560013,46.6237983704],"type":"Point"}
}