{
  "type": "Feature",
  "properties": {
    "iso:country":"AT",
    "sg:address":"Peter-Johann-Pl 5",
    "sg:city":"Wimpassing im Schwarzatale",
    "sg:orig_category":"Banken U Sparkassen",
    "sg:phone":"+43 4326 30371250",
    "sg:postcode":"2632",
    "sg:province":"Nieder\u00f6sterreich",
    "wof:name":"Raiffeisenbank N\u00f6-S\u00fcd Alpin regGenmbH",
    "wof:placetype":"venue"
},
  "geometry": {"coordinates":[16.0159130096,47.6862411499],"type":"Point"}
}