{
  "type": "Feature",
  "properties": {
    "addr:full":"Nr 68 Rosenbach K\u00e4rnten 9183",
    "addr:postcode":"9183",
    "addr:street":"Nr;Rosenbach Kaernten",
    "iso:country":"AT",
    "sg:address":"Nr 68",
    "sg:city":"Rosenbach",
    "sg:orig_category":"Volksschulen",
    "sg:phone":"+43 4253 8211",
    "sg:postcode":"9183",
    "sg:province":"K\u00e4rnten",
    "wof:name":"Volksschule",
    "wof:placetype":"venue"
},
  "geometry": {"coordinates":[14.0542936325,46.539478302],"type":"Point"}
}