{
  "type": "Feature",
  "properties": {
    "addr:full":"Nr 9 Bad Leonfelden Ober\u00f6sterreich 4190",
    "addr:housenumber":"9",
    "addr:postcode":"4190",
    "addr:street":"Nr",
    "iso:country":"AT",
    "sg:address":"Nr 9",
    "sg:city":"Bad Leonfelden",
    "sg:orig_category":"Hunde U Hundeartikel",
    "sg:phone":"+43 4372 1320528",
    "sg:postcode":"4190",
    "sg:province":"Ober\u00f6sterreich",
    "wof:name":"Irish Wolfhound from Starstone - Fam Mayrw\u00f6ger",
    "wof:placetype":"venue"
},
  "geometry": {"coordinates":[14.2936611176,48.5224494934],"type":"Point"}
}