{
  "type": "Feature",
  "properties": {
    "addr:full":"Wiesenweg 5 Bad Hofgastein Salzburg 5630",
    "addr:housenumber":"5",
    "addr:postcode":"5630",
    "addr:street":"Wiesenweg;Salzburg",
    "iso:country":"AT",
    "sg:address":"Wiesenweg 5",
    "sg:city":"Bad Hofgastein",
    "sg:orig_category":"Pensionen / Privatzimmer",
    "sg:phone":"+43 6432 6462",
    "sg:postcode":"5630",
    "sg:province":"Salzburg",
    "wof:name":"Fr\u00fchst\u00fcckspension Breitenfellner",
    "wof:placetype":"venue"
},
  "geometry": {"coordinates":[13.1006813049,47.1697044373],"type":"Point"}
}