{
  "type": "Feature",
  "properties": {
    "addr:full":"Sportplatzstr 553 Kaprun Salzburg 5710",
    "addr:housenumber":"553",
    "addr:postcode":"5710",
    "addr:street":"Kaprun Salzburg",
    "iso:country":"AT",
    "sg:address":"Sportplatzstr 553",
    "sg:city":"Kaprun",
    "sg:orig_category":"Appartements / Ferienwohnungen",
    "sg:phone":"+43 6547 7124",
    "sg:postcode":"5710",
    "sg:province":"Salzburg",
    "wof:name":"Haus am Hang - Voithofer Franziska",
    "wof:placetype":"venue"
},
  "geometry": {"coordinates":[12.750620842,47.2661895752],"type":"Point"}
}