{
  "type": "Feature",
  "properties": {
    "addr:full":"Auland 44 Reith Tirol 6103",
    "addr:housenumber":"44",
    "addr:postcode":"6103",
    "addr:street":"Auland",
    "iso:country":"AT",
    "sg:address":"Auland 44",
    "sg:city":"Reith",
    "sg:orig_category":"Abschleppdienste",
    "sg:phone":"+43 5212 2411",
    "sg:postcode":"6103",
    "sg:province":"Tirol",
    "wof:name":"Haslwanter Helmut",
    "wof:placetype":"venue"
},
  "geometry": {"coordinates":[11.1993103027,47.3138923645],"type":"Point"}
}