{
  "type": "Feature",
  "properties": {
    "addr:full":"Donaufelder Str 24 Wien Wien 1210",
    "addr:postcode":"1210",
    "addr:street":"Str 24",
    "iso:country":"AT",
    "sg:address":"Donaufelder Str 24",
    "sg:city":"Wien",
    "sg:orig_category":"Fleischhauereien",
    "sg:phone":"+43 1 2701341",
    "sg:postcode":"1210",
    "sg:province":"Wien",
    "wof:name":"Scharmitzer Alfred",
    "wof:placetype":"venue"
},
  "geometry": {"coordinates":[16.4111537933,48.2539024353],"type":"Point"}
}