{
  "type": "Feature",
  "properties": {
    "addr:full":"Nr 71 Uderns Tirol 6271",
    "addr:postcode":"6271",
    "addr:street":"Nr 71;Tirol",
    "iso:country":"AT",
    "sg:address":"Nr 71",
    "sg:city":"Uderns",
    "sg:orig_category":"Volksschulen",
    "sg:phone":"+43 4352 8862981",
    "sg:postcode":"6271",
    "sg:province":"Tirol",
    "wof:name":"Volksschule",
    "wof:placetype":"venue"
},
  "geometry": {"coordinates":[11.8642072678,47.3266906738],"type":"Point"}
}