{
  "type": "Feature",
  "properties": {
    "addr:full":"Kochstr 10 Innsbruck Tirol 6020",
    "addr:housenumber":"10",
    "addr:postcode":"6020",
    "addr:street":"Kochstr;Tirol",
    "iso:country":"AT",
    "sg:address":"Kochstr 10",
    "sg:city":"Innsbruck",
    "sg:orig_category":"Werbegrafik- U Grafik-Design",
    "sg:phone":"+43 4351 25751510",
    "sg:postcode":"6020",
    "sg:province":"Tirol",
    "wof:name":"H\u00f6retzeder Schett Senfter OEG Circus Reclameherstellung",
    "wof:placetype":"venue"
},
  "geometry": {"coordinates":[11.4018564224,47.2717170715],"type":"Point"}
}