{
  "type": "Feature",
  "properties": {
    "iso:country":"AT",
    "sg:address":"Ybbsstr 48/8",
    "sg:city":"Wien",
    "sg:orig_category":"Tabaktrafiken",
    "sg:phone":"+43 1 7294940",
    "sg:postcode":"1020",
    "sg:province":"Wien",
    "wof:name":"Tripunovic Boban",
    "wof:placetype":"venue"
},
  "geometry": {"coordinates":[16.4025497437,48.2231674194],"type":"Point"}
}