{
  "type": "Feature",
  "properties": {
    "iso:country":"AT",
    "sg:address":"Hans-Richter-G 1a",
    "sg:city":"Wien",
    "sg:orig_category":"Marketingberatung",
    "sg:phone":"+43 1 3698953",
    "sg:postcode":"1190",
    "sg:province":"Wien",
    "wof:name":"Laupp Robert G Dkfm",
    "wof:placetype":"venue"
},
  "geometry": {"coordinates":[16.3410491943,48.2382659912],"type":"Point"}
}