{
  "type": "Feature",
  "properties": {
    "addr:full":"Untere Landstr 17 Furth Nieder\u00f6sterreich 3511",
    "addr:housenumber":"17",
    "addr:postcode":"3511",
    "addr:street":"Untere Landstr",
    "iso:country":"AT",
    "sg:address":"Untere Landstr 17",
    "sg:city":"Furth",
    "sg:orig_category":"Gemeinden",
    "sg:phone":"+43 2732 846220",
    "sg:postcode":"3511",
    "sg:province":"Nieder\u00f6sterreich",
    "wof:name":"Gemeindeamt Furth",
    "wof:placetype":"venue"
},
  "geometry": {"coordinates":[15.6124811172,48.3740921021],"type":"Point"}
}