{
  "type": "Feature",
  "properties": {
    "addr:full":"Oberer Markt 14 Ottenschlag Nieder\u00f6sterreich 3631",
    "addr:housenumber":"14",
    "addr:postcode":"3631",
    "addr:street":"Oberer Markt",
    "iso:country":"AT",
    "sg:address":"Oberer Markt 14",
    "sg:city":"Ottenschlag",
    "sg:orig_category":"Lebensmittel / Einzelhandel",
    "sg:phone":"+43 2872 7419",
    "sg:postcode":"3631",
    "sg:province":"Nieder\u00f6sterreich",
    "wof:name":"Spar-Markt Apolt Karl Christian",
    "wof:placetype":"venue"
},
  "geometry": {"coordinates":[15.2206697464,48.4239692688],"type":"Point"}
}