{
  "type": "Feature",
  "properties": {
    "addr:full":"Ornetsm\u00fchl 4 Ried im Innkreis Ober\u00f6sterreich 4910",
    "addr:housenumber":"4",
    "addr:postcode":"4910",
    "addr:street":"Ornetsmuehl",
    "iso:country":"AT",
    "sg:address":"Ornetsm\u00fchl 4",
    "sg:city":"Ried im Innkreis",
    "sg:orig_category":"Holzhandel",
    "sg:phone":"+43 7752 82893",
    "sg:postcode":"4910",
    "sg:province":"Ober\u00f6sterreich",
    "wof:name":"Holzpartner GesmbH",
    "wof:placetype":"venue"
},
  "geometry": {"coordinates":[13.4900550842,48.2098655701],"type":"Point"}
}