{
  "type": "Feature",
  "properties": {
    "addr:full":"Badgasse 52 Knittelfeld Steiermark 8720",
    "addr:housenumber":"52",
    "addr:postcode":"8720",
    "addr:street":"Badgasse",
    "iso:country":"AT",
    "sg:address":"Badgasse 52",
    "sg:city":"Knittelfeld",
    "sg:classifiers":[
        {
            "category":"Professional",
            "type":"Services"
        }
    ],
    "sg:phone":"+43 3512 83221",
    "sg:postcode":"8720",
    "sg:province":"Steiermark",
    "sg:tags":[
        "mould",
        "construction"
    ],
    "sg:website":"promotechformenbau.at",
    "wof:name":"Promotech Formenbau Ges.m.b.H.",
    "wof:placetype":"venue"
},
  "geometry": {"coordinates":[14.8050413132,47.2150306702],"type":"Point"}
}