{
  "type": "Feature",
  "properties": {
    "addr:full":"Lothringerstrasse 2 Wien Wien 1040",
    "addr:housenumber":"2",
    "addr:postcode":"1040",
    "addr:street":"Lothringerstrasse",
    "iso:country":"AT",
    "sg:address":"Lothringerstrasse 2",
    "sg:city":"Wien",
    "sg:classifiers":[
        {
            "category":"Manufacturing",
            "subcategory":"Printing",
            "type":"Manufacturing & Wholesale Goods"
        }
    ],
    "sg:phone":"+43 1 5051097",
    "sg:postcode":"1040",
    "sg:province":"Wien",
    "sg:tags":[
        "house",
        "book"
    ],
    "wof:name":"Buchdruckerei Victor Klaushofer",
    "wof:placetype":"venue"
},
  "geometry": {"coordinates":[16.3737487793,48.1996192932],"type":"Point"}
}