{
  "type": "Feature",
  "properties": {
    "iso:country":"AT",
    "sg:address":"Kirchdorf 169",
    "sg:city":"Doren",
    "sg:orig_category":"Banken U Sparkassen",
    "sg:phone":"+43 5516 20160",
    "sg:postcode":"6933",
    "sg:province":"Vorarlberg",
    "wof:name":"Raiffeisenbank Wei\u00dfachtal regGenmbH",
    "wof:placetype":"venue"
},
  "geometry": {"coordinates":[9.8796796799,47.4928436279],"type":"Point"}
}