{
  "type": "Feature",
  "properties": {
    "addr:full":"Industriestr II/13 Hornstein Burgenland 7053",
    "addr:housenumber":"13",
    "addr:postcode":"7053",
    "iso:country":"AT",
    "sg:address":"Industriestr II/13",
    "sg:city":"Hornstein",
    "sg:orig_category":"Maler, Anstreicher U Lackierer",
    "sg:phone":"+43 2689 2739",
    "sg:postcode":"7053",
    "sg:province":"Burgenland",
    "wof:name":"Szinovatz & Wolfsbauer GesmbH",
    "wof:placetype":"venue"
},
  "geometry": {"coordinates":[16.4282855988,47.8758735657],"type":"Point"}
}