{
  "type": "Feature",
  "properties": {
    "iso:country":"AT",
    "sg:address":"Dr.-Billroth-Weg 50",
    "sg:city":"Leibnitz",
    "sg:orig_category":"Beschriftungen",
    "sg:phone":"+43 4334 5286732",
    "sg:postcode":"8430",
    "sg:province":"Steiermark",
    "wof:name":"trim-line Design u Beschriftungen Langbauer Erich",
    "wof:placetype":"venue"
},
  "geometry": {"coordinates":[15.5565004349,46.7877120972],"type":"Point"}
}