{
  "type": "Feature",
  "properties": {
    "addr:full":"Lasserstr 21/8 Salzburg Salzburg 5020",
    "addr:housenumber":"21 / 8",
    "addr:postcode":"5020",
    "addr:street":"Lasserstr;Salzburg",
    "iso:country":"AT",
    "sg:address":"Lasserstr 21/8",
    "sg:city":"Salzburg",
    "sg:orig_category":"Unternehmensberatung",
    "sg:phone":"+43 662 8784970",
    "sg:postcode":"5020",
    "sg:province":"Salzburg",
    "wof:name":"FCI Fischer International GesmbH",
    "wof:placetype":"venue"
},
  "geometry": {"coordinates":[13.0485458374,47.8079338074],"type":"Point"}
}