{
  "type": "Feature",
  "properties": {
    "iso:country":"AT",
    "sg:address":"Landstra\u00dfer Hauptstr 70",
    "sg:city":"Wien",
    "sg:orig_category":"Juweliere, Gold- U Silberschmiede",
    "sg:phone":"+43 1 7136460",
    "sg:postcode":"1030",
    "sg:province":"Wien",
    "wof:name":"Jacobsen Juwelen & Uhren",
    "wof:placetype":"venue"
},
  "geometry": {"coordinates":[16.3920192719,48.2011070251],"type":"Point"}
}