{
  "type": "Feature",
  "properties": {
    "addr:full":"Gewerbestr 8 Sollenau Nieder\u00f6sterreich 2601",
    "addr:housenumber":"8",
    "addr:postcode":"2601",
    "addr:street":"Gewerbestr",
    "iso:country":"AT",
    "sg:address":"Gewerbestr 8",
    "sg:city":"Sollenau",
    "sg:orig_category":"Anlagenbau U -Technik",
    "sg:phone":"+43 4326 2849192",
    "sg:postcode":"2601",
    "sg:province":"Nieder\u00f6sterreich",
    "wof:name":"D.P.A. Anlagenbau GmbH",
    "wof:placetype":"venue"
},
  "geometry": {"coordinates":[16.2735080719,47.9051399231],"type":"Point"}
}