{
  "type": "Feature",
  "properties": {
    "addr:full":"Speckkarstr 51 Mils Tirol 6068",
    "addr:housenumber":"51",
    "addr:postcode":"6068",
    "addr:street":"Speckkarstr;Tirol",
    "iso:country":"AT",
    "sg:address":"Speckkarstr 51",
    "sg:city":"Mils",
    "sg:orig_category":"Handelsagenturen",
    "sg:phone":"+43 5223 43036",
    "sg:postcode":"6068",
    "sg:province":"Tirol",
    "wof:name":"Vettorazzi Waltraud",
    "wof:placetype":"venue"
},
  "geometry": {"coordinates":[-99.4334869385,42.926410675],"type":"Point"}
}