{
  "type": "Feature",
  "properties": {
    "addr:full":"Pilzg 16A Wien Wien 1210",
    "addr:housenumber":"16a",
    "addr:postcode":"1210",
    "addr:street":"Pilzg",
    "iso:country":"AT",
    "sg:address":"Pilzg 16A",
    "sg:city":"Wien",
    "sg:orig_category":"Psychotherapie",
    "sg:phone":"+43 664 1430987",
    "sg:postcode":"1210",
    "sg:province":"Wien",
    "wof:name":"Karlhuber Veronika",
    "wof:placetype":"venue"
},
  "geometry": {"coordinates":[16.4060516357,48.258644104],"type":"Point"}
}