{
  "type": "Feature",
  "properties": {
    "addr:full":"Promenade 37 Linz Ober\u00f6sterreich 4020",
    "addr:housenumber":"37",
    "addr:postcode":"4020",
    "addr:street":"Promenade",
    "iso:country":"AT",
    "sg:address":"Promenade 37",
    "sg:city":"Linz",
    "sg:orig_category":"Institute",
    "sg:phone":"+43 4373 277200",
    "sg:postcode":"4020",
    "sg:province":"Ober\u00f6sterreich",
    "wof:name":"Amt d O\u00f6 Landesregierung - Institut f Kulturf\u00f6rderung",
    "wof:placetype":"venue"
},
  "geometry": {"coordinates":[14.2830219269,48.3032493591],"type":"Point"}
}