{
  "type": "Feature",
  "properties": {
    "iso:country":"AT",
    "sg:address":"Drosselweg 16",
    "sg:city":"Engerwitzdorf",
    "sg:orig_category":"Botendienste",
    "sg:phone":"+43 664 2558555",
    "sg:postcode":"4209",
    "sg:province":"Ober\u00f6sterreich",
    "wof:name":"Bruckner G\u00fcterbef\u00f6rderungs GmbH",
    "wof:placetype":"venue"
},
  "geometry": {"coordinates":[14.4361200333,48.3464012146],"type":"Point"}
}