{
  "type": "Feature",
  "properties": {
    "iso:country":"AT",
    "sg:address":"Meidlinger Hauptstr 22",
    "sg:city":"Wien",
    "sg:orig_category":"Damenmoden",
    "sg:phone":"+43 1 8100255",
    "sg:postcode":"1120",
    "sg:province":"Wien",
    "wof:name":"Turek-Moden",
    "wof:placetype":"venue"
},
  "geometry": {"coordinates":[16.3296699524,48.1807594299],"type":"Point"}
}