{
  "type": "Feature",
  "properties": {
    "iso:country":"AT",
    "sg:address":"Angererweg 50",
    "sg:city":"Tulfes",
    "sg:orig_category":"Zimmereien",
    "sg:phone":"+43 5223 78691",
    "sg:postcode":"6075",
    "sg:province":"Tirol",
    "sg:website":"moser-moser-holzbau.at",
    "wof:name":"Moser & Moser Holzbau GesmbH",
    "wof:placetype":"venue"
},
  "geometry": {"coordinates":[11.5357542038,47.2585258484],"type":"Point"}
}