{
  "type": "Feature",
  "properties": {
    "addr:full":"Burgauer Str 26c F\u00fcrstenfeld Steiermark 8280",
    "addr:housenumber":"26c",
    "addr:postcode":"8280",
    "addr:street":"Str",
    "iso:country":"AT",
    "sg:address":"Burgauer Str 26c",
    "sg:city":"F\u00fcrstenfeld",
    "sg:orig_category":"Steinmetzbetriebe",
    "sg:phone":"+43 3382 51545",
    "sg:postcode":"8280",
    "sg:province":"Steiermark",
    "wof:name":"Kahr Alois",
    "wof:placetype":"venue"
},
  "geometry": {"coordinates":[16.0771999359,47.0622138977],"type":"Point"}
}