{
  "type": "Feature",
  "properties": {
    "addr:full":"G\u00e4rtnerg 13/1 Korneuburg Nieder\u00f6sterreich 2100",
    "addr:housenumber":"13 / 1",
    "addr:postcode":"2100",
    "addr:street":"Gaertnerg;Niederoesterreich",
    "iso:country":"AT",
    "sg:address":"G\u00e4rtnerg 13/1",
    "sg:city":"Korneuburg",
    "sg:orig_category":"Immobilienmakler",
    "sg:phone":"+43 2262 754300",
    "sg:postcode":"2100",
    "sg:province":"Nieder\u00f6sterreich",
    "sg:website":"mukstadt.at",
    "wof:name":"Mukstadt GmbH",
    "wof:placetype":"venue"
},
  "geometry": {"coordinates":[16.3329143524,48.3437843323],"type":"Point"}
}