{
  "type": "Feature",
  "properties": {
    "addr:full":"Tigerg 33 Wien Wien 1080",
    "addr:housenumber":"33",
    "addr:postcode":"1080",
    "addr:street":"Tigerg",
    "iso:country":"AT",
    "sg:address":"Tigerg 33",
    "sg:city":"Wien",
    "sg:orig_category":"Psychologen",
    "sg:phone":"+43 1 4087247",
    "sg:postcode":"1080",
    "sg:province":"Wien",
    "wof:name":"Ulm Susanne Mag",
    "wof:placetype":"venue"
},
  "geometry": {"coordinates":[16.3446216583,48.2099189758],"type":"Point"}
}