{
  "type": "Feature",
  "properties": {
    "addr:full":"Kehlerstr 81a Dornbirn Vorarlberg 6850",
    "addr:housenumber":"81a",
    "addr:postcode":"6850",
    "addr:street":"Kehlerstr",
    "iso:country":"AT",
    "sg:address":"Kehlerstr 81a",
    "sg:city":"Dornbirn",
    "sg:orig_category":"Furniere",
    "sg:phone":"+43 5572 22829",
    "sg:postcode":"6850",
    "sg:province":"Vorarlberg",
    "wof:name":"M\u00e4ser-Furniere GesmbH",
    "wof:placetype":"venue"
},
  "geometry": {"coordinates":[9.7559814453,47.4237289429],"type":"Point"}
}