{
  "type": "Feature",
  "properties": {
    "addr:full":"Reitherspitzstr. 294  Seefeld in Tirol Tirol 6100",
    "addr:housenumber":"294",
    "addr:postcode":"6100",
    "addr:street":"Seefeld;Tirol",
    "iso:country":"AT",
    "sg:address":"Reitherspitzstr. 294 ",
    "sg:city":"Seefeld in Tirol",
    "sg:classifiers":[
        {
            "category":"Food & Beverages",
            "subcategory":"Groceries & Convenience Stores",
            "type":"Retail Goods"
        }
    ],
    "sg:phone":"+43 4352 124444",
    "sg:postcode":"6100",
    "sg:province":"Tirol",
    "sg:tags":[
        "drink"
    ],
    "wof:name":"ERNST SEYRLING KG GETR\u00c4NKEHANDEL",
    "wof:placetype":"venue"
},
  "geometry": {"coordinates":[11.1465129852,47.3113555908],"type":"Point"}
}