{
  "type": "Feature",
  "properties": {
    "addr:full":"Stockerauer Str 16 Korneuburg Nieder\u00f6sterreich 2100",
    "addr:postcode":"2100",
    "addr:street":"Str 16",
    "iso:country":"AT",
    "sg:address":"Stockerauer Str 16",
    "sg:city":"Korneuburg",
    "sg:orig_category":"Tabaktrafiken",
    "sg:phone":"+43 2262 72165",
    "sg:postcode":"2100",
    "sg:province":"Nieder\u00f6sterreich",
    "wof:name":"Radike Gertrude",
    "wof:placetype":"venue"
},
  "geometry": {"coordinates":[16.3309955597,48.34557724],"type":"Point"}
}