{
  "type": "Feature",
  "properties": {
    "addr:full":"F\u00f6dermayrstr 50-52 Enns Ober\u00f6sterreich 4470",
    "addr:postcode":"4470",
    "addr:street":"Oberoesterreich",
    "iso:country":"AT",
    "sg:address":"F\u00f6dermayrstr 50-52",
    "sg:city":"Enns",
    "sg:orig_category":"Bijouteriewaren",
    "sg:phone":"+43 7223 82280",
    "sg:postcode":"4470",
    "sg:province":"Ober\u00f6sterreich",
    "wof:name":"Scheibler Michael",
    "wof:placetype":"venue"
},
  "geometry": {"coordinates":[14.4723463058,48.2074813843],"type":"Point"}
}