{
  "type": "Feature",
  "properties": {
    "iso:country":"AT",
    "sg:address":"Laaer Wald 35",
    "sg:city":"Wien",
    "sg:orig_category":"Minigolfanlagen U -Bedarf",
    "sg:phone":"+43 4316 885544",
    "sg:postcode":"1100",
    "sg:province":"Wien",
    "wof:name":"Minigolf Inh Geissler Henriette",
    "wof:placetype":"venue"
},
  "geometry": {"coordinates":[16.3973751068,48.1686592102],"type":"Point"}
}