{
  "type": "Feature",
  "properties": {
    "iso:country":"AT",
    "sg:address":"Wegscheider Str. 15",
    "sg:city":"Linz",
    "sg:classifiers":[
        {
            "category":"Professional",
            "subcategory":"Engineering",
            "type":"Services"
        }
    ],
    "sg:phone":"+43 4373 23739",
    "sg:postcode":"4020",
    "sg:province":"Ober\u00f6sterreich",
    "sg:tags":[
        "machine",
        "-",
        "mechanical"
    ],
    "wof:name":"DR. ERNST FEHRER AG",
    "wof:placetype":"venue"
},
  "geometry": {"coordinates":[14.2785778046,48.2542037964],"type":"Point"}
}