{
  "type": "Feature",
  "properties": {
    "addr:full":"Hauptpl 15 Freistadt Ober\u00f6sterreich 4240",
    "addr:housenumber":"15",
    "addr:postcode":"4240",
    "addr:street":"Hauptpl",
    "iso:country":"AT",
    "sg:address":"Hauptpl 15",
    "sg:city":"Freistadt",
    "sg:orig_category":"Banken U Sparkassen",
    "sg:phone":"+43 4350 10040160",
    "sg:postcode":"4240",
    "sg:province":"Ober\u00f6sterreich",
    "wof:name":"Sparkasse Ober\u00f6sterreich Bank AG",
    "wof:placetype":"venue"
},
  "geometry": {"coordinates":[14.5058193207,48.5114936829],"type":"Point"}
}