{
  "type": "Feature",
  "properties": {
    "addr:full":"Stegg 8 Graz Steiermark 8010",
    "addr:housenumber":"8",
    "addr:postcode":"8010",
    "addr:street":"Stegg",
    "iso:country":"AT",
    "sg:address":"Stegg 8",
    "sg:city":"Graz",
    "sg:orig_category":"Sprechanlagen",
    "sg:phone":"+43 316 675090",
    "sg:postcode":"8010",
    "sg:province":"Steiermark",
    "wof:name":"Hohenadler Ferdinand",
    "wof:placetype":"venue"
},
  "geometry": {"coordinates":[15.4251308441,47.0867805481],"type":"Point"}
}