{
  "type": "Feature",
  "properties": {
    "addr:full":"Feldg 38 Tulln an der Donau Nieder\u00f6sterreich 3430",
    "addr:housenumber":"38",
    "addr:postcode":"3430",
    "addr:street":"Feldg",
    "iso:country":"AT",
    "sg:address":"Feldg 38",
    "sg:city":"Tulln an der Donau",
    "sg:classifiers":[
        {
            "category":"Park",
            "subcategory":"Provincial",
            "type":"Public Place"
        }
    ],
    "sg:phone":"+43 4322 7262921",
    "sg:postcode":"3430",
    "sg:province":"Nieder\u00f6sterreich",
    "sg:tags":[
        "u",
        "ski-",
        "snowboardschulen"
    ],
    "wof:name":"Haginger Alfred",
    "wof:placetype":"venue"
},
  "geometry": {"coordinates":[16.0497398376,48.3306999207],"type":"Point"}
}