{
  "type": "Feature",
  "properties": {
    "addr:full":"Neugablonz 6-8 Enns Ober\u00f6sterreich 4470",
    "addr:housenumber":"6-8",
    "addr:postcode":"4470",
    "addr:street":"Neugablonz",
    "iso:country":"AT",
    "sg:address":"Neugablonz 6-8",
    "sg:city":"Enns",
    "sg:orig_category":"Galvanisieranstalten",
    "sg:phone":"+43 7223 82548",
    "sg:postcode":"4470",
    "sg:province":"Ober\u00f6sterreich",
    "wof:name":"J\u00e4kel Metallwaren GesmbH",
    "wof:placetype":"venue"
},
  "geometry": {"coordinates":[14.4794635773,48.2057685852],"type":"Point"}
}