{
  "type": "Feature",
  "properties": {
    "addr:full":"Unterbergg 172 Flachau Salzburg 5542",
    "addr:housenumber":"172",
    "addr:postcode":"5542",
    "addr:street":"Unterbergg;Salzburg",
    "iso:country":"AT",
    "sg:address":"Unterbergg 172",
    "sg:city":"Flachau",
    "sg:classifiers":[
        {
            "category":"Travel",
            "subcategory":"Hotels & Motels",
            "type":"Entertainment"
        }
    ],
    "sg:phone":"+43 6457 23790",
    "sg:postcode":"5542",
    "sg:province":"Salzburg",
    "wof:name":"Lacknerhof Hotel",
    "wof:placetype":"venue"
},
  "geometry": {"coordinates":[13.3886060715,47.3558082581],"type":"Point"}
}