{
  "type": "Feature",
  "properties": {
    "iso:country":"AT",
    "sg:address":"Gersdorf an der Feistritz 105",
    "sg:city":"Pischelsdorf in Steiermark",
    "sg:classifiers":[
        {
            "category":"Manufacturing",
            "subcategory":"Glass & Minerals",
            "type":"Manufacturing & Wholesale Goods"
        }
    ],
    "sg:phone":"+43 3113 3751",
    "sg:postcode":"8212",
    "sg:province":"Steiermark",
    "sg:tags":[
        "decorative",
        "artistic"
    ],
    "sg:website":"egger-glas.at",
    "wof:name":"EGGER GLAS Isolier- und Sicherheitsglaserzeugnung GmbH",
    "wof:placetype":"venue"
},
  "geometry": {"coordinates":[15.8060102463,47.1733627319],"type":"Point"}
}