{
  "type": "Feature",
  "properties": {
    "addr:full":"Andauer Str 38 Tadten Burgenland 7162",
    "addr:housenumber":"38",
    "addr:postcode":"7162",
    "addr:street":"Str",
    "iso:country":"AT",
    "sg:address":"Andauer Str 38",
    "sg:city":"Tadten",
    "sg:orig_category":"Friseure U Frisiersalons",
    "sg:phone":"+43 2176 28578",
    "sg:postcode":"7162",
    "sg:province":"Burgenland",
    "wof:name":"Fris\u00f6r Daniel Inh Lausch Eva",
    "wof:placetype":"venue"
},
  "geometry": {"coordinates":[16.9913406372,47.765838623],"type":"Point"}
}