{
  "type": "Feature",
  "properties": {
    "addr:full":"Omesberg 331 Lech Vorarlberg 6764",
    "addr:housenumber":"331",
    "addr:postcode":"6764",
    "addr:street":"Omesberg",
    "iso:country":"AT",
    "sg:address":"Omesberg 331",
    "sg:city":"Lech",
    "sg:classifiers":[
        {
            "category":"Travel",
            "subcategory":"Travel Agent",
            "type":"Entertainment"
        }
    ],
    "sg:postcode":"6764",
    "sg:province":"Vorarlberg",
    "sg:website":"slh.com/kristiania/",
    "wof:name":"Sporthotel Kristiania",
    "wof:placetype":"venue"
},
  "geometry": {"coordinates":[-92.3896636963,35.7329483032],"type":"Point"}
}