{
  "type": "Feature",
  "properties": {
    "addr:full":"Dorotheerg 6-8/Top 14c Wien Wien 1010",
    "addr:housenumber":"6-8 / top 14c",
    "addr:postcode":"1010",
    "addr:street":"Dorotheerg",
    "iso:country":"AT",
    "sg:address":"Dorotheerg 6-8/Top 14c",
    "sg:city":"Wien",
    "sg:orig_category":"Dolmetscher",
    "sg:phone":"+43 4366 44312353",
    "sg:postcode":"1010",
    "sg:province":"Wien",
    "sg:website":"1a-translator.at",
    "wof:name":"1A-translator.at Mag Tomasz Olszewski",
    "wof:placetype":"venue"
},
  "geometry": {"coordinates":[16.3688049316,48.2025489807],"type":"Point"}
}