{
  "type": "Feature",
  "properties": {
    "addr:full":"Knasweg 15 Moosburg K\u00e4rnten 9062",
    "addr:housenumber":"15",
    "addr:postcode":"9062",
    "addr:street":"Knasweg;Kaernten",
    "iso:country":"AT",
    "sg:address":"Knasweg 15",
    "sg:city":"Moosburg",
    "sg:orig_category":"Architekten",
    "sg:phone":"+43 4272 82872",
    "sg:postcode":"9062",
    "sg:province":"K\u00e4rnten",
    "wof:name":"Zelloth Wolfgang Dipl-Ing",
    "wof:placetype":"venue"
},
  "geometry": {"coordinates":[14.1466732025,46.678943634],"type":"Point"}
}