{
  "type": "Feature",
  "properties": {
    "iso:country":"AT",
    "sg:address":"Steigtalstr 27",
    "sg:city":"Leoben",
    "sg:orig_category":"Holzgro\u00c3\u0178handel",
    "sg:phone":"+43 4338 423003000",
    "sg:postcode":"8700",
    "sg:province":"Steiermark",
    "wof:name":"Holzbeschaffungs- und Logistik GmbH",
    "wof:placetype":"venue"
},
  "geometry": {"coordinates":[15.0981693268,47.3614044189],"type":"Point"}
}