{
  "type": "Feature",
  "properties": {
    "addr:full":"Leharg 4 Oberwart Burgenland 7400",
    "addr:housenumber":"4",
    "addr:postcode":"7400",
    "addr:street":"Leharg",
    "iso:country":"AT",
    "sg:address":"Leharg 4",
    "sg:city":"Oberwart",
    "sg:orig_category":"Friseure U Frisiersalons",
    "sg:phone":"+43 3352 385951",
    "sg:postcode":"7400",
    "sg:province":"Burgenland",
    "wof:name":"Schmidt Natalie",
    "wof:placetype":"venue"
},
  "geometry": {"coordinates":[16.2078533173,47.2892913818],"type":"Point"}
}