{
  "type": "Feature",
  "properties": {
    "addr:full":"Wiener Str 225 Langenzersdorf Nieder\u00f6sterreich 2103",
    "addr:housenumber":"225",
    "addr:postcode":"2103",
    "iso:country":"AT",
    "sg:address":"Wiener Str 225",
    "sg:city":"Langenzersdorf",
    "sg:orig_category":"Speditionen",
    "sg:phone":"+43 2244 33293",
    "sg:postcode":"2103",
    "sg:province":"Nieder\u00f6sterreich",
    "wof:name":"Asia Logistic Internationale Speditions- und HandelsgesmbH",
    "wof:placetype":"venue"
},
  "geometry": {"coordinates":[16.3757858276,48.2985153198],"type":"Point"}
}