{
  "type": "Feature",
  "properties": {
    "addr:full":"K Schwaighofer-Str 2 Mondsee Ober\u00f6sterreich 5310",
    "addr:housenumber":"2",
    "addr:postcode":"5310",
    "addr:street":"Schwaighofer-Str;Oberoesterreich",
    "iso:country":"AT",
    "sg:address":"K Schwaighofer-Str 2",
    "sg:city":"Mondsee",
    "sg:orig_category":"Nachhilfe U Lernbetreuung",
    "sg:phone":"+43 662 453905",
    "sg:postcode":"5310",
    "sg:province":"Ober\u00f6sterreich",
    "wof:name":"A bis Z - Lernstudio",
    "wof:placetype":"venue"
},
  "geometry": {"coordinates":[13.3401203156,47.8567733765],"type":"Point"}
}