{
  "type": "Feature",
  "properties": {
    "iso:country":"AT",
    "sg:address":"Schlo\u00dfstr 50/5",
    "sg:city":"Langenlois",
    "sg:orig_category":"Architekten",
    "sg:phone":"+43 2734 4461",
    "sg:postcode":"3550",
    "sg:province":"Nieder\u00f6sterreich",
    "wof:name":"Koller Alice Arch Dipl-Ing",
    "wof:placetype":"venue"
},
  "geometry": {"coordinates":[15.6913156509,48.4604034424],"type":"Point"}
}