{
  "type": "Feature",
  "properties": {
    "addr:full":"Wehrbr\u00fccklstr 21 Wien Wien 1220",
    "addr:housenumber":"21",
    "addr:postcode":"1220",
    "addr:street":"Wehrbruecklstr",
    "iso:country":"AT",
    "sg:address":"Wehrbr\u00fccklstr 21",
    "sg:city":"Wien",
    "sg:orig_category":"Parkettbodenverlegung",
    "sg:phone":"+43 1 7741262",
    "sg:postcode":"1220",
    "sg:province":"Wien",
    "wof:name":"Csekei Imre",
    "wof:placetype":"venue"
},
  "geometry": {"coordinates":[16.444606781,48.2497138977],"type":"Point"}
}