{
  "type": "Feature",
  "properties": {
    "addr:full":"Prinz-Eugen-Str 27 Wien Wien 1030",
    "addr:housenumber":"27",
    "addr:postcode":"1030",
    "addr:street":"Prinz-Eugen-Str",
    "iso:country":"AT",
    "sg:address":"Prinz-Eugen-Str 27",
    "sg:city":"Wien",
    "sg:classifiers":[
        {
            "category":"Restaurant",
            "type":"Food & Drink"
        }
    ],
    "sg:phone":"+43 4317 988888",
    "sg:postcode":"1030",
    "sg:province":"Wien",
    "wof:name":"Cafe-Restaurant Schlo\u00df Belvedere",
    "wof:placetype":"venue"
},
  "geometry": {"coordinates":[16.3795986176,48.191619873],"type":"Point"}
}