{
  "type": "Feature",
  "properties": {
    "iso:country":"AT",
    "sg:address":"Schrofensteinstr 5",
    "sg:city":"Landeck",
    "sg:orig_category":"Banken U Sparkassen",
    "sg:phone":"+43 4354 42638880",
    "sg:postcode":"6500",
    "sg:province":"Tirol",
    "wof:name":"Volksbank Landeck regGenmbH",
    "wof:placetype":"venue"
},
  "geometry": {"coordinates":[10.5714025497,47.1478538513],"type":"Point"}
}