{
  "type": "Feature",
  "properties": {
    "addr:full":"Prager Str 138 Wien Wien 1210",
    "addr:housenumber":"138",
    "addr:postcode":"1210",
    "iso:country":"AT",
    "sg:address":"Prager Str 138",
    "sg:city":"Wien",
    "sg:orig_category":"Tankstellen",
    "sg:phone":"+43 1 2717587",
    "sg:postcode":"1210",
    "sg:province":"Wien",
    "wof:name":"AWI-Diskont",
    "wof:placetype":"venue"
},
  "geometry": {"coordinates":[16.3875694275,48.2789382935],"type":"Point"}
}