{
  "type": "Feature",
  "properties": {
    "addr:full":"Gradnerstr 141 Stra\u00dfgang Steiermark 8054",
    "addr:housenumber":"141",
    "addr:postcode":"8054",
    "iso:country":"AT",
    "sg:address":"Gradnerstr 141",
    "sg:city":"Stra\u00dfgang",
    "sg:orig_category":"Abfallentsorgung U -Verwertung",
    "sg:phone":"+43 316 251152",
    "sg:postcode":"8054",
    "sg:province":"Steiermark",
    "wof:name":"AHS Abfall & Entsorgungs GmbH",
    "wof:placetype":"venue"
},
  "geometry": {"coordinates":[15.4093341827,47.0209350586],"type":"Point"}
}