{
  "type": "Feature",
  "properties": {
    "iso:country":"AT",
    "sg:address":"Mariahilfer Str. 54 ",
    "sg:city":"Wien",
    "sg:classifiers":[
        {
            "category":"Banks & Credit Unions",
            "subcategory":"Bank",
            "type":"Services"
        }
    ],
    "sg:phone":"+43 4315 0505",
    "sg:postcode":"1070",
    "sg:province":"Wien",
    "sg:tags":[
        "banking",
        "institution"
    ],
    "wof:name":"BANK AUSTRIA CREDITANSTALT AG",
    "wof:placetype":"venue"
},
  "geometry": {"coordinates":[16.3520927429,48.1992874146],"type":"Point"}
}