{
  "type": "Feature",
  "properties": {
    "addr:full":"Wiener G 72 Perchtoldsdorf Nieder\u00f6sterreich 2380",
    "addr:housenumber":"72",
    "addr:postcode":"2380",
    "addr:street":"Wiener G",
    "iso:country":"AT",
    "sg:address":"Wiener G 72",
    "sg:city":"Perchtoldsdorf",
    "sg:orig_category":"Tabaktrafiken",
    "sg:phone":"+43 1 8654313",
    "sg:postcode":"2380",
    "sg:province":"Nieder\u00f6sterreich",
    "wof:name":"Neuhuber Isabella",
    "wof:placetype":"venue"
},
  "geometry": {"coordinates":[16.2711734772,48.1240234375],"type":"Point"}
}