{
  "type": "Feature",
  "properties": {
    "addr:full":"Nr 18 Haugsdorf Nieder\u00f6sterreich 2054",
    "addr:postcode":"2054",
    "addr:street":"Nr;Niederoesterreich",
    "iso:country":"AT",
    "sg:address":"Nr 18",
    "sg:city":"Haugsdorf",
    "sg:orig_category":"Speditionen",
    "sg:phone":"+43 2944 2561",
    "sg:postcode":"2054",
    "sg:province":"Nieder\u00f6sterreich",
    "wof:name":"Royal Sped SpeditionsgesmbH",
    "wof:placetype":"venue"
},
  "geometry": {"coordinates":[16.1005096436,48.7056617737],"type":"Point"}
}