{
  "type": "Feature",
  "properties": {
    "addr:full":"Ungarg 48 Wien Wien 1030",
    "addr:housenumber":"48",
    "addr:postcode":"1030",
    "addr:street":"Ungarg",
    "iso:country":"AT",
    "sg:address":"Ungarg 48",
    "sg:city":"Wien",
    "sg:orig_category":"Unternehmensberatung",
    "sg:phone":"+43 4317 104104",
    "sg:postcode":"1030",
    "sg:province":"Wien",
    "wof:name":"EcoLine HandelsgesmbH",
    "wof:placetype":"venue"
},
  "geometry": {"coordinates":[16.3872108459,48.1993942261],"type":"Point"}
}