{
  "type": "Feature",
  "properties": {
    "addr:full":"Maximilianstr 2 Innsbruck Tirol 6020",
    "addr:housenumber":"2",
    "addr:postcode":"6020",
    "addr:street":"Maximilianstr;Tirol",
    "iso:country":"AT",
    "sg:address":"Maximilianstr 2",
    "sg:city":"Innsbruck",
    "sg:orig_category":"Telekommunikation",
    "sg:phone":"+43 800 100100",
    "sg:postcode":"6020",
    "sg:province":"Tirol",
    "wof:name":"Telekom Austria Shop",
    "wof:placetype":"venue"
},
  "geometry": {"coordinates":[11.3937578201,47.262714386],"type":"Point"}
}