{
  "type": "Feature",
  "properties": {
    "iso:country":"AT",
    "sg:address":"Wiesenstr 85",
    "sg:city":"Pinsdorf",
    "sg:orig_category":"Transportunternehmen",
    "sg:phone":"+43 761266784",
    "sg:postcode":"4812",
    "sg:province":"Ober\u00f6sterreich",
    "wof:name":"Wiesmayr Josef",
    "wof:placetype":"venue"
},
  "geometry": {"coordinates":[13.7445583344,47.9579696655],"type":"Point"}
}