{
  "type": "Feature",
  "properties": {
    "iso:country":"AT",
    "sg:address":"Leopold-Luger-Strasse 5",
    "sg:city":"Saalfelden am Steinernen Meer",
    "sg:classifiers":[
        {
            "category":"Banks & Credit Unions",
            "subcategory":"Investment Brokerage",
            "type":"Services"
        }
    ],
    "sg:phone":"+43 6582 767130",
    "sg:postcode":"5760",
    "sg:province":"Salzburg",
    "sg:tags":[
        "bearing",
        "ball"
    ],
    "wof:name":"Manfred Schell",
    "wof:placetype":"venue"
},
  "geometry": {"coordinates":[12.8329429626,47.4203033447],"type":"Point"}
}