{
  "type": "Feature",
  "properties": {
    "addr:full":"Auweg 1 Kolsass Tirol 6114",
    "addr:housenumber":"1",
    "addr:postcode":"6114",
    "addr:street":"Auweg;Tirol",
    "iso:country":"AT",
    "sg:address":"Auweg 1",
    "sg:city":"Kolsass",
    "sg:orig_category":"Tankstellen",
    "sg:phone":"+43 5224 67678",
    "sg:postcode":"6114",
    "sg:province":"Tirol",
    "wof:name":"OIL Tankstellen GmbH",
    "wof:placetype":"venue"
},
  "geometry": {"coordinates":[11.6376562119,47.3050422668],"type":"Point"}
}