{
  "type": "Feature",
  "properties": {
    "addr:full":"Linzer Strasse 23 Gablitz Nieder\u00f6sterreich 3003",
    "addr:housenumber":"23",
    "addr:postcode":"3003",
    "addr:street":"Linzer Strasse",
    "iso:country":"AT",
    "sg:address":"Linzer Strasse 23",
    "sg:city":"Gablitz",
    "sg:classifiers":[
        {
            "category":"Manufacturing",
            "subcategory":"Furniture",
            "type":"Manufacturing & Wholesale Goods"
        }
    ],
    "sg:phone":"+43 2231 66066",
    "sg:postcode":"3003",
    "sg:province":"Nieder\u00f6sterreich",
    "sg:tags":[
        "bedroom"
    ],
    "sg:website":"tischlerei-pachhammer.at",
    "wof:name":"Ing. Ernst Pachhammer",
    "wof:placetype":"venue"
},
  "geometry": {"coordinates":[16.1630306244,48.2213439941],"type":"Point"}
}