{
  "type": "Feature",
  "properties": {
    "addr:full":"Rainer Harbachstr. 11 Spittal an der Drau K\u00e4rnten 9800",
    "addr:housenumber":"11",
    "addr:postcode":"9800",
    "addr:street":"Kaernten",
    "iso:country":"AT",
    "sg:address":"Rainer Harbachstr. 11",
    "sg:city":"Spittal an der Drau",
    "sg:orig_category":"Immobilien U Baugewerbe, Immobilienmarkt U Kleinanzeigen",
    "sg:phone":"+43 4762 4087",
    "sg:postcode":"9800",
    "sg:province":"K\u00e4rnten",
    "sg:website":"http://members.aon.at/ecobau",
    "wof:name":"ecobau Bautr\u00e4ger & Consulting GmbH",
    "wof:placetype":"venue"
},
  "geometry": {"coordinates":[13.5027856827,46.7887268066],"type":"Point"}
}