{
  "type": "Feature",
  "properties": {
    "addr:full":"Marktpl 11 Zwettl an der Rodl Ober\u00f6sterreich 4180",
    "addr:housenumber":"11",
    "addr:postcode":"4180",
    "addr:street":"Marktpl",
    "iso:country":"AT",
    "sg:address":"Marktpl 11",
    "sg:city":"Zwettl an der Rodl",
    "sg:orig_category":"Banken U Sparkassen",
    "sg:phone":"+43 4372 126292",
    "sg:postcode":"4180",
    "sg:province":"Ober\u00f6sterreich",
    "wof:name":"Raiffeisenbank Mittleres Rodltal regGenmbH",
    "wof:placetype":"venue"
},
  "geometry": {"coordinates":[14.2716856003,48.4657897949],"type":"Point"}
}