{
  "type": "Feature",
  "properties": {
    "addr:full":"Zeinisjoch Galt\u00fcr Tirol 6563",
    "addr:postcode":"6563",
    "iso:country":"AT",
    "sg:address":"Zeinisjoch",
    "sg:city":"Galt\u00fcr",
    "sg:orig_category":"Appartements / Ferienwohnungen",
    "sg:phone":"+43 4354 438562",
    "sg:postcode":"6563",
    "sg:province":"Tirol",
    "wof:name":"Fremdenheim Zeinissee",
    "wof:placetype":"venue"
},
  "geometry": {"coordinates":[10.152762413,46.955116272],"type":"Point"}
}