{
  "type": "Feature",
  "properties": {
    "addr:full":"Ulrich-Lichtenstein-G 12 Liebenau Steiermark 8041",
    "addr:housenumber":"12",
    "addr:postcode":"8041",
    "addr:street":"Ulrich-Lichtenstein-G",
    "iso:country":"AT",
    "sg:address":"Ulrich-Lichtenstein-G 12",
    "sg:city":"Liebenau",
    "sg:orig_category":"Stiegen U Treppen",
    "sg:phone":"+43 4366 44435741",
    "sg:postcode":"8041",
    "sg:province":"Steiermark",
    "wof:name":"Rintal Treppen Handels GmbH",
    "wof:placetype":"venue"
},
  "geometry": {"coordinates":[15.4543609619,47.0475769043],"type":"Point"}
}