{
  "type": "Feature",
  "properties": {
    "addr:full":"Firmiang 47 Wien Wien 1130",
    "addr:housenumber":"47",
    "addr:postcode":"1130",
    "addr:street":"Firmiang",
    "iso:country":"AT",
    "sg:address":"Firmiang 47",
    "sg:city":"Wien",
    "sg:orig_category":"Institute",
    "sg:phone":"+43 4315 136073",
    "sg:postcode":"1130",
    "sg:province":"Wien",
    "wof:name":"GALEA - Institut f Humanenergetik u biodynamische Analyse",
    "wof:placetype":"venue"
},
  "geometry": {"coordinates":[16.2686901093,48.1913986206],"type":"Point"}
}