{
  "type": "Feature",
  "properties": {
    "iso:country":"AT",
    "sg:address":"Dorf 20",
    "sg:city":"Neidling",
    "sg:orig_category":"Feuerwehren",
    "sg:phone":"+43 2741 7088",
    "sg:postcode":"3110",
    "sg:province":"Nieder\u00f6sterreich",
    "wof:name":"Freiwillige Feuerwehr Neidling",
    "wof:placetype":"venue"
},
  "geometry": {"coordinates":[15.5568723679,48.2376899719],"type":"Point"}
}