{
  "type": "Feature",
  "properties": {
    "iso:country":"AT",
    "sg:address":"Sieveringer Strasse 126/2",
    "sg:city":"Wien",
    "sg:orig_category":"Accumulator Measuring/Charging Sets",
    "sg:phone":"+43 1 4405513",
    "sg:postcode":"1190",
    "sg:province":"Wien",
    "sg:website":"braunsteiner.at",
    "wof:name":"Braunsteiner Batterien und Akkusysteme GmbH",
    "wof:placetype":"venue"
},
  "geometry": {"coordinates":[16.3230857849,48.2516059875],"type":"Point"}
}