{
  "type": "Feature",
  "properties": {
    "iso:country":"AT",
    "sg:address":"Staatsbahnstr 19a",
    "sg:city":"Laa an der Thaya",
    "sg:orig_category":"Tabaktrafiken",
    "sg:phone":"+43 2522 8241",
    "sg:postcode":"2136",
    "sg:province":"Nieder\u00f6sterreich",
    "wof:name":"Landauer Johann",
    "wof:placetype":"venue"
},
  "geometry": {"coordinates":[16.3877887726,48.719619751],"type":"Point"}
}