{
  "type": "Feature",
  "properties": {
    "addr:full":"Ganz 1 Matrei in Osttirol Tirol 9971",
    "addr:housenumber":"1",
    "addr:postcode":"9971",
    "addr:street":"Ganz;Tirol",
    "iso:country":"AT",
    "sg:address":"Ganz 1",
    "sg:city":"Matrei in Osttirol",
    "sg:orig_category":"Pensionen / Privatzimmer",
    "sg:phone":"+43 4875 6818",
    "sg:postcode":"9971",
    "sg:province":"Tirol",
    "wof:name":"G\u00e4stehaus Maria P\u00f6tscher",
    "wof:placetype":"venue"
},
  "geometry": {"coordinates":[12.5585384369,47.013835907],"type":"Point"}
}