{
  "type": "Feature",
  "properties": {
    "iso:country":"AT",
    "sg:address":"Sturneng 6",
    "sg:city":"Bludenz",
    "sg:orig_category":"Boutiquen",
    "sg:phone":"+43 5552 65302",
    "sg:postcode":"6700",
    "sg:province":"Vorarlberg",
    "wof:name":"Schickeria Boutique",
    "wof:placetype":"venue"
},
  "geometry": {"coordinates":[9.8189811707,47.156085968],"type":"Point"}
}