{
  "type": "Feature",
  "properties": {
    "addr:full":"Teisenbergg 15/3 Salzburg Salzburg 5020",
    "addr:housenumber":"15 / 3",
    "addr:postcode":"5020",
    "addr:street":"Teisenbergg;Salzburg",
    "iso:country":"AT",
    "sg:address":"Teisenbergg 15/3",
    "sg:city":"Salzburg",
    "sg:classifiers":[
        {
            "category":"Restaurant",
            "type":"Food & Drink"
        }
    ],
    "sg:phone":"+43 4366 41326601",
    "sg:postcode":"5020",
    "sg:province":"Salzburg",
    "wof:name":"Lindtner Johann",
    "wof:placetype":"venue"
},
  "geometry": {"coordinates":[13.0044651031,47.8044815063],"type":"Point"}
}