{
  "type": "Feature",
  "properties": {
    "addr:full":"Julius-Berger-G 18 Wien Wien 1170",
    "addr:housenumber":"18",
    "addr:postcode":"1170",
    "addr:street":"Julius-Berger-G",
    "iso:country":"AT",
    "sg:address":"Julius-Berger-G 18",
    "sg:city":"Wien",
    "sg:orig_category":"Datenverarbeitung",
    "sg:phone":"+43 4314 862842",
    "sg:postcode":"1170",
    "sg:province":"Wien",
    "wof:name":"DV-Organisation u gewerbliche Buchhaltung GmbH",
    "wof:placetype":"venue"
},
  "geometry": {"coordinates":[16.2856636047,48.2352905273],"type":"Point"}
}