{
  "type": "Feature",
  "properties": {
    "addr:full":"Hartigg 4 Graz Steiermark 8010",
    "addr:housenumber":"4",
    "addr:postcode":"8010",
    "addr:street":"Hartigg",
    "iso:country":"AT",
    "sg:address":"Hartigg 4",
    "sg:city":"Graz",
    "sg:orig_category":"Museen / Ausstellungen",
    "sg:phone":"+43 4331 6816172",
    "sg:postcode":"8010",
    "sg:province":"Steiermark",
    "wof:name":"Pichler M & Sohn GesmbH - Spielzeug- u Puppenmuseen",
    "wof:placetype":"venue"
},
  "geometry": {"coordinates":[15.4415359497,47.0736083984],"type":"Point"}
}