{
  "type": "Feature",
  "properties": {
    "addr:full":"Arndtstr 66 Wien Wien 1120",
    "addr:housenumber":"66",
    "addr:postcode":"1120",
    "addr:street":"Arndtstr",
    "iso:country":"AT",
    "sg:address":"Arndtstr 66",
    "sg:city":"Wien",
    "sg:orig_category":"Lebensmittel / Erzeugung U Gro\u00c3\u0178handel",
    "sg:phone":"+43 1 8176501",
    "sg:postcode":"1120",
    "sg:province":"Wien",
    "wof:name":"AO DA Handels GmbH",
    "wof:placetype":"venue"
},
  "geometry": {"coordinates":[16.3352546692,48.1830024719],"type":"Point"}
}