{
  "type": "Feature",
  "properties": {
    "addr:full":"Hadergasse 13 Bramberg am Wildkogel Salzburg 5733",
    "addr:housenumber":"13",
    "addr:postcode":"5733",
    "addr:street":"Hadergasse;Salzburg",
    "iso:country":"AT",
    "sg:address":"Hadergasse 13",
    "sg:city":"Bramberg am Wildkogel",
    "sg:classifiers":[
        {
            "category":"Arts & Performance",
            "subcategory":"Art Gallery",
            "type":"Entertainment"
        }
    ],
    "sg:phone":"+43 6562 83420",
    "sg:postcode":"5733",
    "sg:province":"Salzburg",
    "sg:tags":[
        "baseboard",
        "wood",
        "made"
    ],
    "sg:website":"holz-profil.at",
    "wof:name":"Holzprofil-Produktionsges.m.b.H.",
    "wof:placetype":"venue"
},
  "geometry": {"coordinates":[12.3472499847,47.2725601196],"type":"Point"}
}