{
  "type": "Feature",
  "properties": {
    "iso:country":"AT",
    "sg:address":"F\u00f6hrenweg 2",
    "sg:city":"K\u00fchnsdorf",
    "sg:orig_category":"Fleischhauereien",
    "sg:phone":"+43 4232 6106",
    "sg:postcode":"9125",
    "sg:province":"K\u00e4rnten",
    "wof:name":"Stefitz Wolfgang",
    "wof:placetype":"venue"
},
  "geometry": {"coordinates":[14.7058506012,46.6068992615],"type":"Point"}
}