{
  "type": "Feature",
  "properties": {
    "addr:full":"Josefstr 123 St. P\u00f6lten Nieder\u00f6sterreich 3100",
    "addr:housenumber":"123",
    "addr:postcode":"3100",
    "addr:street":"Josefstr",
    "iso:country":"AT",
    "sg:address":"Josefstr 123",
    "sg:city":"St. P\u00f6lten",
    "sg:orig_category":"Weiterbildungsinstitute M Allg U Berufl Bildungsangebot",
    "sg:phone":"+43 4327 428930",
    "sg:postcode":"3100",
    "sg:province":"Nieder\u00f6sterreich",
    "wof:name":"WIFI Wirtschaftsf\u00f6rderungsinstitut d Wirtschaftskammer - Seminarzentrum Schwaighof",
    "wof:placetype":"venue"
},
  "geometry": {"coordinates":[-76.07303619379999,41.7845001221],"type":"Point"}
}