{
  "type": "Feature",
  "properties": {
    "addr:full":"Bundesstr 20 Schwarzenau Nieder\u00f6sterreich 3900",
    "addr:housenumber":"20",
    "addr:postcode":"3900",
    "addr:street":"Bundesstr",
    "iso:country":"AT",
    "sg:address":"Bundesstr 20",
    "sg:city":"Schwarzenau",
    "sg:orig_category":"Friseure U Frisiersalons",
    "sg:phone":"+43 4328 492224",
    "sg:postcode":"3900",
    "sg:province":"Nieder\u00f6sterreich",
    "wof:name":"Widhalm Brigitte",
    "wof:placetype":"venue"
},
  "geometry": {"coordinates":[15.2588510513,48.7434196472],"type":"Point"}
}