{
  "type": "Feature",
  "properties": {
    "addr:full":"Grazer Bundesstr 36b Gnigl Salzburg 5023",
    "addr:housenumber":"36b",
    "addr:postcode":"5023",
    "iso:country":"AT",
    "sg:address":"Grazer Bundesstr 36b",
    "sg:city":"Gnigl",
    "sg:orig_category":"Werbeartikel U -Geschenke",
    "sg:phone":"+43 662 640710",
    "sg:postcode":"5023",
    "sg:province":"Salzburg",
    "wof:name":"Huber Manfred Ing - neue produkte",
    "wof:placetype":"venue"
},
  "geometry": {"coordinates":[13.0846748352,47.8126983643],"type":"Point"}
}