{
  "type": "Feature",
  "properties": {
    "addr:full":"Harterfeldstr 52 Leonding Ober\u00f6sterreich 4060",
    "addr:housenumber":"52",
    "addr:postcode":"4060",
    "addr:street":"Harterfeldstr",
    "iso:country":"AT",
    "sg:address":"Harterfeldstr 52",
    "sg:city":"Leonding",
    "sg:orig_category":"Elektroinstallationsunternehmen",
    "sg:phone":"+43 732 6716780",
    "sg:postcode":"4060",
    "sg:province":"Ober\u00f6sterreich",
    "wof:name":"Elektro Rudolf Zellinger GesmbH",
    "wof:placetype":"venue"
},
  "geometry": {"coordinates":[14.2527036667,48.2598266602],"type":"Point"}
}