{
  "type": "Feature",
  "properties": {
    "iso:country":"AT",
    "sg:address":"Nr 209",
    "sg:city":"Annaberg",
    "sg:orig_category":"Rettungsdienste",
    "sg:phone":"+43 6463 60008",
    "sg:postcode":"5524",
    "sg:province":"Salzburg",
    "wof:name":"Bergrettung",
    "wof:placetype":"venue"
},
  "geometry": {"coordinates":[13.4312047958,47.513458252],"type":"Point"}
}