{
  "type": "Feature",
  "properties": {
    "iso:country":"AT",
    "sg:address":"Bach 15",
    "sg:city":"Gro\u00dfarl",
    "sg:orig_category":"Hafnereien",
    "sg:phone":"+43 6414 656",
    "sg:postcode":"5611",
    "sg:province":"Salzburg",
    "wof:name":"Prommegger Christoph",
    "wof:placetype":"venue"
},
  "geometry": {"coordinates":[13.1992197037,47.2111587524],"type":"Point"}
}