{
  "type": "Feature",
  "properties": {
    "addr:full":"Schwefel 38 Dornbirn Vorarlberg 6850",
    "addr:housenumber":"38",
    "addr:postcode":"6850",
    "addr:street":"Schwefel",
    "iso:country":"AT",
    "sg:address":"Schwefel 38",
    "sg:city":"Dornbirn",
    "sg:orig_category":"Dieselmotoren U -Reparaturen",
    "sg:phone":"+43 4355 7252515",
    "sg:postcode":"6850",
    "sg:province":"Vorarlberg",
    "wof:name":"Diesel-Service Ehrhart Rainer",
    "wof:placetype":"venue"
},
  "geometry": {"coordinates":[9.7413682938,47.4254341125],"type":"Point"}
}