{
  "type": "Feature",
  "properties": {
    "iso:country":"AT",
    "sg:address":"Wolfgangg 25",
    "sg:city":"Wien",
    "sg:orig_category":"Bauunternehmen",
    "sg:phone":"+43 1 8174998",
    "sg:postcode":"1120",
    "sg:province":"Wien",
    "wof:name":"D & K Dach und Bau GmbH",
    "wof:placetype":"venue"
},
  "geometry": {"coordinates":[16.3427772522,48.1826248169],"type":"Point"}
}