{
  "type": "Feature",
  "properties": {
    "iso:country":"AT",
    "sg:address":"Getreideg 47",
    "sg:city":"Salzburg",
    "sg:orig_category":"Trachtenbekleidung",
    "sg:phone":"+43 662 842864",
    "sg:postcode":"5020",
    "sg:province":"Salzburg",
    "wof:name":"Kaiser Franz Josef Trachten",
    "wof:placetype":"venue"
},
  "geometry": {"coordinates":[13.040148735,47.7999267578],"type":"Point"}
}