{
  "type": "Feature",
  "properties": {
    "addr:full":"H\u00f6henstr 20 Fohnsdorf Steiermark 8753",
    "addr:housenumber":"20",
    "addr:postcode":"8753",
    "addr:street":"Hoehenstr",
    "iso:country":"AT",
    "sg:address":"H\u00f6henstr 20",
    "sg:city":"Fohnsdorf",
    "sg:orig_category":"Tischlereien",
    "sg:phone":"+43 4335 732950",
    "sg:postcode":"8753",
    "sg:province":"Steiermark",
    "wof:name":"Seirer Tischlerei",
    "wof:placetype":"venue"
},
  "geometry": {"coordinates":[14.6821212769,47.2107048035],"type":"Point"}
}