{
  "type": "Feature",
  "properties": {
    "addr:full":"Steig 234 Strengen Tirol 6571",
    "addr:housenumber":"234",
    "addr:postcode":"6571",
    "addr:street":"Steig;Strengen Tirol",
    "iso:country":"AT",
    "sg:address":"Steig 234",
    "sg:city":"Strengen",
    "sg:orig_category":"Tischlereien",
    "sg:phone":"+43 5447 5706",
    "sg:postcode":"6571",
    "sg:province":"Tirol",
    "wof:name":"Sch\u00f6pf Sch\u00f6nes Wohnen Der Tischler",
    "wof:placetype":"venue"
},
  "geometry": {"coordinates":[10.4759836197,47.1212615967],"type":"Point"}
}