{
  "type": "Feature",
  "properties": {
    "iso:country":"AT",
    "sg:address":"Flurweg 6",
    "sg:city":"Ennsdorf",
    "sg:orig_category":"Gartencenter",
    "sg:phone":"+43 7223 82059",
    "sg:postcode":"4482",
    "sg:province":"Nieder\u00f6sterreich",
    "wof:name":"Bellaflora Gartencenter GmbH",
    "wof:placetype":"venue"
},
  "geometry": {"coordinates":[14.5264797211,48.2271881104],"type":"Point"}
}