{
  "type": "Feature",
  "properties": {
    "addr:full":"Untere Hauptstr 1 Illmitz Burgenland 7142",
    "addr:housenumber":"1",
    "addr:postcode":"7142",
    "addr:street":"Untere Hauptstr",
    "iso:country":"AT",
    "sg:address":"Untere Hauptstr 1",
    "sg:city":"Illmitz",
    "sg:orig_category":"Non-Classified Establishments",
    "sg:phone":"+43 2175 2306",
    "sg:postcode":"7142",
    "sg:province":"Burgenland",
    "wof:name":"Pfarramt",
    "wof:placetype":"venue"
},
  "geometry": {"coordinates":[16.7999286652,47.7621078491],"type":"Point"}
}