{
  "type": "Feature",
  "properties": {
    "addr:full":"Dr Fraundorfer-G 8 Ternitz Nieder\u00f6sterreich 2630",
    "addr:housenumber":"8",
    "addr:postcode":"2630",
    "addr:street":"Niederoesterreich",
    "iso:country":"AT",
    "sg:address":"Dr Fraundorfer-G 8",
    "sg:city":"Ternitz",
    "sg:orig_category":"Friseure U Frisiersalons",
    "sg:phone":"+43 2630 36370",
    "sg:postcode":"2630",
    "sg:province":"Nieder\u00f6sterreich",
    "wof:name":"Salon Kurt Eisenk\u00f6lbl",
    "wof:placetype":"venue"
},
  "geometry": {"coordinates":[16.0350227356,47.7197036743],"type":"Point"}
}