{
  "type": "Feature",
  "properties": {
    "iso:country":"AT",
    "sg:address":"Nr 2",
    "sg:city":"Obritzberg",
    "sg:orig_category":"Gutsverwaltungen",
    "sg:phone":"+43 2741 8221",
    "sg:postcode":"3123",
    "sg:province":"Nieder\u00f6sterreich",
    "wof:name":"Gutsverwaltung Karlstetten",
    "wof:placetype":"venue"
},
  "geometry": {"coordinates":[15.5941095352,48.2923965454],"type":"Point"}
}