{
  "type": "Feature",
  "properties": {
    "iso:country":"AT",
    "sg:address":"Friedrich-Hillegeist-Str 2",
    "sg:city":"Wien",
    "sg:orig_category":"Personalbereitstellung",
    "sg:phone":"+43 4369 918206006",
    "sg:postcode":"1020",
    "sg:province":"Wien",
    "wof:name":"AVANTI F & M Personalbereitstellung GesmbH",
    "wof:placetype":"venue"
},
  "geometry": {"coordinates":[16.3981437683,48.2291374207],"type":"Point"}
}