{
  "type": "Feature",
  "properties": {
    "iso:country":"AT",
    "sg:address":"Nr 17",
    "sg:city":"Petzenkirchen",
    "sg:orig_category":"Wasseraufbereitung U -Reinigung",
    "sg:phone":"+43 4374 1653475",
    "sg:postcode":"3252",
    "sg:province":"Nieder\u00f6sterreich",
    "wof:name":"WELLNESS-SYSTEMS",
    "wof:placetype":"venue"
},
  "geometry": {"coordinates":[15.152964592,48.1433868408],"type":"Point"}
}