{
  "type": "Feature",
  "properties": {
    "addr:full":"Karl Marx-Str 7 Klagenfurt K\u00e4rnten 9020",
    "addr:housenumber":"7",
    "addr:postcode":"9020",
    "addr:street":"Marx-Str;Kaernten",
    "iso:country":"AT",
    "sg:address":"Karl Marx-Str 7",
    "sg:city":"Klagenfurt",
    "sg:orig_category":"Exporteure U Importeure",
    "sg:phone":"+43 463 358093",
    "sg:postcode":"9020",
    "sg:province":"K\u00e4rnten",
    "wof:name":"R & A Tifinger-Hertelendi",
    "wof:placetype":"venue"
},
  "geometry": {"coordinates":[14.308347702,46.6116333008],"type":"Point"}
}