{
  "type": "Feature",
  "properties": {
    "addr:full":"Industriestr 2 Friesach K\u00e4rnten 9360",
    "addr:housenumber":"2",
    "addr:postcode":"9360",
    "addr:street":"Industriestr;Kaernten",
    "iso:country":"AT",
    "sg:address":"Industriestr 2",
    "sg:city":"Friesach",
    "sg:orig_category":"Lebensmittel / Einzelhandel",
    "sg:phone":"+43 4268 50006",
    "sg:postcode":"9360",
    "sg:province":"K\u00e4rnten",
    "wof:name":"ADEG Contra Markt",
    "wof:placetype":"venue"
},
  "geometry": {"coordinates":[14.4135656357,46.952922821],"type":"Point"}
}