{
  "type": "Feature",
  "properties": {
    "addr:full":"Eduard-Klinger-Str 19 St. Andr\u00e4-W\u00f6rdern Nieder\u00f6sterreich 3423",
    "addr:housenumber":"19",
    "addr:postcode":"3423",
    "addr:street":"Eduard-Klinger-Str",
    "iso:country":"AT",
    "sg:address":"Eduard-Klinger-Str 19",
    "sg:city":"St. Andr\u00e4-W\u00f6rdern",
    "sg:orig_category":"Tonstudios",
    "sg:phone":"+43 2242 31338",
    "sg:postcode":"3423",
    "sg:province":"Nieder\u00f6sterreich",
    "wof:name":"Sound Fabrik-Musicproduction",
    "wof:placetype":"venue"
},
  "geometry": {"coordinates":[16.1984844208,48.3309898376],"type":"Point"}
}