{
  "type": "Feature",
  "properties": {
    "iso:country":"AT",
    "sg:address":"Habsburgerg 10",
    "sg:city":"Wien",
    "sg:orig_category":"Forschungsinstitute",
    "sg:phone":"+43 1 5350686",
    "sg:postcode":"1010",
    "sg:province":"Wien",
    "wof:name":"MECOSAN wissenschaftliche Gesellschaft",
    "wof:placetype":"venue"
},
  "geometry": {"coordinates":[16.3681373596,48.2082328796],"type":"Point"}
}