{
  "type": "Feature",
  "properties": {
    "addr:full":"Waidhofner Str 45 Weyer Ober\u00f6sterreich 3335",
    "addr:housenumber":"45",
    "addr:postcode":"3335",
    "addr:street":"Str",
    "iso:country":"AT",
    "sg:address":"Waidhofner Str 45",
    "sg:city":"Weyer",
    "sg:orig_category":"Psychotherapie",
    "sg:phone":"+43 7355 635411",
    "sg:postcode":"3335",
    "sg:province":"Ober\u00f6sterreich",
    "wof:name":"Neubauer Maria Barbara",
    "wof:placetype":"venue"
},
  "geometry": {"coordinates":[14.6713399887,47.8654518127],"type":"Point"}
}