{
  "type": "Feature",
  "properties": {
    "addr:full":"Gleichenberg Dorf 15 Bad Gleichenberg Steiermark 8344",
    "addr:housenumber":"15",
    "addr:postcode":"8344",
    "addr:street":"Gleichenberg Dorf",
    "iso:country":"AT",
    "sg:address":"Gleichenberg Dorf 15",
    "sg:city":"Bad Gleichenberg",
    "sg:orig_category":"Landwirtschaftliche Produkte",
    "sg:phone":"+43 4331 592255",
    "sg:postcode":"8344",
    "sg:province":"Steiermark",
    "wof:name":"Rauch Johann",
    "wof:placetype":"venue"
},
  "geometry": {"coordinates":[15.8806381226,46.8993911743],"type":"Point"}
}