{
  "type": "Feature",
  "properties": {
    "addr:full":"Wiesenweg 184 Furth Nieder\u00f6sterreich 3511",
    "addr:housenumber":"184",
    "addr:postcode":"3511",
    "addr:street":"Wiesenweg",
    "iso:country":"AT",
    "sg:address":"Wiesenweg 184",
    "sg:city":"Furth",
    "sg:classifiers":[
        {
            "category":"Professional",
            "subcategory":"Management & Consulting",
            "type":"Services"
        }
    ],
    "sg:phone":"+43 2736 20010",
    "sg:postcode":"3511",
    "sg:province":"Nieder\u00f6sterreich",
    "wof:name":"Klausner Simon - Golfplatzberatung",
    "wof:placetype":"venue"
},
  "geometry": {"coordinates":[15.6125049591,48.374168396],"type":"Point"}
}