{
  "type": "Feature",
  "properties": {
    "iso:country":"AT",
    "sg:address":"Nr 50",
    "sg:city":"Au",
    "sg:orig_category":"Maschinenbau",
    "sg:phone":"+43 3863 27880",
    "sg:postcode":"8624",
    "sg:province":"Steiermark",
    "wof:name":"Heldeco Cad/Cam Fertigungstechnik GesmbH",
    "wof:placetype":"venue"
},
  "geometry": {"coordinates":[166.9221496582,-0.5282999873],"type":"Point"}
}