{
  "type": "Feature",
  "properties": {
    "addr:full":"Kohlreitstr 382/2 Neulengbach Nieder\u00f6sterreich 3040",
    "addr:housenumber":"382 / 2",
    "addr:postcode":"3040",
    "iso:country":"AT",
    "sg:address":"Kohlreitstr 382/2",
    "sg:city":"Neulengbach",
    "sg:orig_category":"\u00c3\u201erzte / F Allgemeinmedizin",
    "sg:phone":"+43 2772 53950",
    "sg:postcode":"3040",
    "sg:province":"Nieder\u00f6sterreich",
    "wof:name":"Fohringer Herbert Dr",
    "wof:placetype":"venue"
},
  "geometry": {"coordinates":[15.9114942551,48.1909561157],"type":"Point"}
}