{
  "type": "Feature",
  "properties": {
    "addr:full":"Innsbrucker Str 24 Seefeld in Tirol Tirol 6100",
    "addr:housenumber":"24",
    "addr:postcode":"6100",
    "addr:street":"Str;Tirol",
    "iso:country":"AT",
    "sg:address":"Innsbrucker Str 24",
    "sg:city":"Seefeld in Tirol",
    "sg:orig_category":"Spirituosen / Erzeugung U Gro\u00c3\u0178handel",
    "sg:phone":"+43 4352 1252895",
    "sg:postcode":"6100",
    "sg:province":"Tirol",
    "wof:name":"The fruit & herbal drinks company HandelsGmbH",
    "wof:placetype":"venue"
},
  "geometry": {"coordinates":[11.1876659393,47.3281593323],"type":"Point"}
}