{
  "type": "Feature",
  "properties": {
    "addr:full":"Hauptstr 154 Muthmannsdorf Nieder\u00f6sterreich 2723",
    "addr:housenumber":"154",
    "addr:postcode":"2723",
    "addr:street":"Hauptstr;Niederoesterreich",
    "iso:country":"AT",
    "sg:address":"Hauptstr 154",
    "sg:city":"Muthmannsdorf",
    "sg:classifiers":[
        {
            "category":"Personal",
            "subcategory":"Sauna",
            "type":"Services"
        }
    ],
    "sg:phone":"+43 4326 3888032",
    "sg:postcode":"2723",
    "sg:province":"Nieder\u00f6sterreich",
    "sg:tags":[
        "u",
        "dampfbad"
    ],
    "sg:website":"goodwood.at",
    "wof:name":"Linsberger Richard Ing - Wellness-Systeme",
    "wof:placetype":"venue"
},
  "geometry": {"coordinates":[16.1099853516,47.8364143372],"type":"Point"}
}