{
  "type": "Feature",
  "properties": {
    "iso:country":"AT",
    "sg:address":"Mariahilfer Str 143",
    "sg:city":"Wien",
    "sg:orig_category":"Briefmarken Philatelie",
    "sg:phone":"+43 1 8936633",
    "sg:postcode":"1150",
    "sg:province":"Wien",
    "wof:name":"Gilg Gerhard",
    "wof:placetype":"venue"
},
  "geometry": {"coordinates":[16.3362617493,48.1945648193],"type":"Point"}
}