{
  "type": "Feature",
  "properties": {
    "addr:full":"Hauptstr 63 Linz Ober\u00f6sterreich 4040",
    "addr:housenumber":"63",
    "addr:postcode":"4040",
    "addr:street":"Hauptstr",
    "iso:country":"AT",
    "sg:address":"Hauptstr 63",
    "sg:city":"Linz",
    "sg:orig_category":"Fernsehservice",
    "sg:phone":"+43 4373 2731520",
    "sg:postcode":"4040",
    "sg:province":"Ober\u00f6sterreich",
    "wof:name":"Probst- R\u00f6ck KG",
    "wof:placetype":"venue"
},
  "geometry": {"coordinates":[14.2811174393,48.3139305115],"type":"Point"}
}