{
  "type": "Feature",
  "properties": {
    "addr:full":"Darreweg 16 Serfaus Tirol 6534",
    "addr:housenumber":"16",
    "addr:postcode":"6534",
    "addr:street":"Darreweg;Tirol",
    "iso:country":"AT",
    "sg:address":"Darreweg 16",
    "sg:city":"Serfaus",
    "sg:orig_category":"Appartements / Ferienwohnungen",
    "sg:phone":"+43 4354 766632",
    "sg:postcode":"6534",
    "sg:province":"Tirol",
    "wof:name":"Katzinger Anna",
    "wof:placetype":"venue"
},
  "geometry": {"coordinates":[10.603348732,47.0401649475],"type":"Point"}
}