{
  "type": "Feature",
  "properties": {
    "addr:full":"Hardegg 65 Wien Wien 1220",
    "addr:housenumber":"65",
    "addr:postcode":"1220",
    "addr:street":"Hardegg",
    "iso:country":"AT",
    "sg:address":"Hardegg 65",
    "sg:city":"Wien",
    "sg:orig_category":"Volksschulen",
    "sg:phone":"+43 1 283213815",
    "sg:postcode":"1220",
    "sg:province":"Wien",
    "wof:name":"Katholische Privatschule VS d Schwestern v Armen Kinde Jesus Maria Frieden",
    "wof:placetype":"venue"
},
  "geometry": {"coordinates":[16.4576797485,48.218837738],"type":"Point"}
}