{
  "type": "Feature",
  "properties": {
    "iso:country":"AT",
    "sg:address":"Haberedt 20",
    "sg:city":"Taufkirchen an der Pram",
    "sg:classifiers":[
        {
            "category":"Utilities",
            "subcategory":"Cable",
            "type":"Services"
        }
    ],
    "sg:phone":"+43 7719 8008",
    "sg:postcode":"4775",
    "sg:province":"Ober\u00f6sterreich",
    "sg:tags":[
        "drum"
    ],
    "sg:website":"brennenstuhl.com",
    "wof:name":"LECTRA Technik Ges.m.b.H.",
    "wof:placetype":"venue"
},
  "geometry": {"coordinates":[13.5129365921,48.4046554565],"type":"Point"}
}