{
  "type": "Feature",
  "properties": {
    "addr:full":"Pachernbergweg 8 Hart Steiermark 8075",
    "addr:housenumber":"8",
    "addr:postcode":"8075",
    "addr:street":"Pachernbergweg",
    "iso:country":"AT",
    "sg:address":"Pachernbergweg 8",
    "sg:city":"Hart",
    "sg:orig_category":"Handelsagenturen",
    "sg:phone":"+43 4366 43402011",
    "sg:postcode":"8075",
    "sg:province":"Steiermark",
    "wof:name":"K\u00fcgerl Wolfgang",
    "wof:placetype":"venue"
},
  "geometry": {"coordinates":[15.5220136642,47.0463829041],"type":"Point"}
}