{
  "type": "Feature",
  "properties": {
    "addr:full":"Austr 2 Fuschl am See Salzburg 5330",
    "addr:housenumber":"2",
    "addr:postcode":"5330",
    "addr:street":"Austr",
    "iso:country":"AT",
    "sg:address":"Austr 2",
    "sg:city":"Fuschl am See",
    "sg:orig_category":"Schlossereien",
    "sg:phone":"+43 4362 268441",
    "sg:postcode":"5330",
    "sg:province":"Salzburg",
    "wof:name":"Winkler Johannes",
    "wof:placetype":"venue"
},
  "geometry": {"coordinates":[13.2933015823,47.7920608521],"type":"Point"}
}