{
  "type": "Feature",
  "properties": {
    "addr:full":"Erzh Rainer-Ring 5 Baden Nieder\u00f6sterreich 2500",
    "addr:housenumber":"5",
    "addr:postcode":"2500",
    "addr:street":"Rainer-Ring;Niederoesterreich",
    "iso:country":"AT",
    "sg:address":"Erzh Rainer-Ring 5",
    "sg:city":"Baden",
    "sg:orig_category":"Banken U Sparkassen",
    "sg:phone":"+43 4350 50530490",
    "sg:postcode":"2500",
    "sg:province":"Nieder\u00f6sterreich",
    "wof:name":"Bank Austria Creditanstalt AG",
    "wof:placetype":"venue"
},
  "geometry": {"coordinates":[16.2145595551,47.9845733643],"type":"Point"}
}