{
  "type": "Feature",
  "properties": {
    "iso:country":"AT",
    "sg:address":"Wr Neust\u00e4dter Str 15",
    "sg:city":"Pottendorf",
    "sg:orig_category":"Hufschmiede",
    "sg:phone":"+43 4326 2374083",
    "sg:postcode":"2486",
    "sg:province":"Nieder\u00f6sterreich",
    "wof:name":"Zickbauer Peter",
    "wof:placetype":"venue"
},
  "geometry": {"coordinates":[16.3865890503,47.9095191956],"type":"Point"}
}