{
  "type": "Feature",
  "properties": {
    "addr:full":"Pinzgerhausweg 15 Kaltenbach Tirol 6272",
    "addr:housenumber":"15",
    "addr:postcode":"6272",
    "addr:street":"Pinzgerhausweg",
    "iso:country":"AT",
    "sg:address":"Pinzgerhausweg 15",
    "sg:city":"Kaltenbach",
    "sg:orig_category":"Pensionen / Privatzimmer",
    "sg:phone":"+43 5283 2432",
    "sg:postcode":"6272",
    "sg:province":"Tirol",
    "wof:name":"Stippler Walter",
    "wof:placetype":"venue"
},
  "geometry": {"coordinates":[11.8948783875,47.2826728821],"type":"Point"}
}