{
  "type": "Feature",
  "properties": {
    "addr:full":"Perfektastr 86 Wien Wien 1230",
    "addr:housenumber":"86",
    "addr:postcode":"1230",
    "addr:street":"Perfektastr",
    "iso:country":"AT",
    "sg:address":"Perfektastr 86",
    "sg:city":"Wien",
    "sg:orig_category":"Digitaldruck",
    "sg:phone":"+43 4318 6540570",
    "sg:postcode":"1230",
    "sg:province":"Wien",
    "wof:name":"VSG Direktwerbung GmbH",
    "wof:placetype":"venue"
},
  "geometry": {"coordinates":[16.3084049225,48.1368408203],"type":"Point"}
}