{
  "type": "Feature",
  "properties": {
    "addr:full":"Weidach 4 Alkoven Ober\u00f6sterreich 4072",
    "addr:housenumber":"4",
    "addr:postcode":"4072",
    "addr:street":"Weidach",
    "iso:country":"AT",
    "sg:address":"Weidach 4",
    "sg:city":"Alkoven",
    "sg:classifiers":[
        {
            "category":"Home & Garden",
            "subcategory":"Kitchen Supply",
            "type":"Retail Goods"
        }
    ],
    "sg:phone":"+43 7274 20266",
    "sg:postcode":"4072",
    "sg:province":"Ober\u00f6sterreich",
    "sg:tags":[
        "counter",
        "display",
        "refrigerated",
        "showcase"
    ],
    "sg:website":"cubic-ladenbau.at",
    "wof:name":"Cubic Ladenbau GmbH",
    "wof:placetype":"venue"
},
  "geometry": {"coordinates":[14.0975732803,48.278968811],"type":"Point"}
}