{
  "type": "Feature",
  "properties": {
    "addr:full":"Hauptstr 21 Wolkersdorf im Weinviertel Nieder\u00f6sterreich 2120",
    "addr:housenumber":"21",
    "addr:postcode":"2120",
    "addr:street":"Hauptstr",
    "iso:country":"AT",
    "sg:address":"Hauptstr 21",
    "sg:city":"Wolkersdorf im Weinviertel",
    "sg:orig_category":"Installationsunternehmen",
    "sg:phone":"+43 2245 31150",
    "sg:postcode":"2120",
    "sg:province":"Nieder\u00f6sterreich",
    "wof:name":"B\u00f6hm W GesmbH & Co KG",
    "wof:placetype":"venue"
},
  "geometry": {"coordinates":[16.5250434875,48.3680953979],"type":"Point"}
}