{
  "type": "Feature",
  "properties": {
    "addr:full":"Egg 525 Kappl Tirol 6555",
    "addr:housenumber":"525",
    "addr:postcode":"6555",
    "addr:street":"Egg;Tirol",
    "iso:country":"AT",
    "sg:address":"Egg 525",
    "sg:city":"Kappl",
    "sg:orig_category":"Appartements / Ferienwohnungen",
    "sg:phone":"+43 4354 456743",
    "sg:postcode":"6555",
    "sg:province":"Tirol",
    "wof:name":"Apart Christine",
    "wof:placetype":"venue"
},
  "geometry": {"coordinates":[10.3725948334,47.064655304],"type":"Point"}
}