{
  "type": "Feature",
  "properties": {
    "addr:full":"Im Stadtgut 1a Gleink Ober\u00f6sterreich 4407",
    "addr:housenumber":"1a",
    "addr:postcode":"4407",
    "addr:street":"Im Stadtgut",
    "iso:country":"AT",
    "sg:address":"Im Stadtgut 1a",
    "sg:city":"Gleink",
    "sg:classifiers":[
        {
            "category":"Autos & Motor Vehicles",
            "subcategory":"Automobile Sales",
            "type":"Retail Goods"
        }
    ],
    "sg:phone":"+43 4372 52220500",
    "sg:postcode":"4407",
    "sg:province":"Ober\u00f6sterreich",
    "sg:tags":[
        "industrial"
    ],
    "wof:name":"KAPPA ARBEITSSCHUTZ & UMWELTTECHNIK GESMBH",
    "wof:placetype":"venue"
},
  "geometry": {"coordinates":[14.4159860611,48.0908508301],"type":"Point"}
}