{
  "type": "Feature",
  "properties": {
    "addr:full":"Ragnitzstr 303 Ragnitz Steiermark 8047",
    "addr:housenumber":"303",
    "addr:postcode":"8047",
    "iso:country":"AT",
    "sg:address":"Ragnitzstr 303",
    "sg:city":"Ragnitz",
    "sg:orig_category":"Installationsunternehmen",
    "sg:phone":"+43 316 302152",
    "sg:postcode":"8047",
    "sg:province":"Steiermark",
    "wof:name":"Weinhandl Hermann",
    "wof:placetype":"venue"
},
  "geometry": {"coordinates":[15.5069093704,47.0750694275],"type":"Point"}
}