{
  "type": "Feature",
  "properties": {
    "iso:country":"AT",
    "sg:address":"Neutorg 18/3",
    "sg:city":"Wien",
    "sg:orig_category":"Forschungsinstitute",
    "sg:phone":"+43 1 5311466061",
    "sg:postcode":"1010",
    "sg:province":"Wien",
    "wof:name":"Ludwig Boltzmann Institut f Gesundheits\u00f6konomie",
    "wof:placetype":"venue"
},
  "geometry": {"coordinates":[16.3681049347,48.2158699036],"type":"Point"}
}