{
  "type": "Feature",
  "properties": {
    "addr:full":"Hauptpl 1 Illmitz Burgenland 7142",
    "addr:housenumber":"1",
    "addr:postcode":"7142",
    "addr:street":"Hauptpl",
    "iso:country":"AT",
    "sg:address":"Hauptpl 1",
    "sg:city":"Illmitz",
    "sg:orig_category":"Banken U Sparkassen",
    "sg:phone":"+43 4350 10020259",
    "sg:postcode":"7142",
    "sg:province":"Burgenland",
    "wof:name":"Sparkasse Hainburg-Bruck-Neusiedl AG",
    "wof:placetype":"venue"
},
  "geometry": {"coordinates":[16.7999286652,47.7621078491],"type":"Point"}
}