{
  "type": "Feature",
  "properties": {
    "iso:country":"AT",
    "sg:address":"Trientlg 30",
    "sg:city":"Innsbruck",
    "sg:orig_category":"Anlagenbau U -Technik",
    "sg:phone":"+43 4351 2343621",
    "sg:postcode":"6020",
    "sg:province":"Tirol",
    "wof:name":"Telekom Building Systems GmbH",
    "wof:placetype":"venue"
},
  "geometry": {"coordinates":[11.434469223,47.2696914673],"type":"Point"}
}