{
  "type": "Feature",
  "properties": {
    "iso:country":"AT",
    "sg:address":"Au\u00dferberg 7",
    "sg:city":"Weerberg",
    "sg:orig_category":"Autoreparatur",
    "sg:phone":"+43 4366 05214069",
    "sg:postcode":"6133",
    "sg:province":"Tirol",
    "wof:name":"Lieb Markus",
    "wof:placetype":"venue"
},
  "geometry": {"coordinates":[11.665719986,47.2984085083],"type":"Point"}
}