{
  "type": "Feature",
  "properties": {
    "addr:full":"Kierlinger Str 1 Klosterneuburg Nieder\u00f6sterreich 3400",
    "addr:housenumber":"1",
    "addr:postcode":"3400",
    "addr:street":"Str;Niederoesterreich",
    "iso:country":"AT",
    "sg:address":"Kierlinger Str 1",
    "sg:city":"Klosterneuburg",
    "sg:orig_category":"Banken U Sparkassen",
    "sg:phone":"+43 2243 34322",
    "sg:postcode":"3400",
    "sg:province":"Nieder\u00f6sterreich",
    "wof:name":"Oberbank AG",
    "wof:placetype":"venue"
},
  "geometry": {"coordinates":[16.3220729828,48.3078308105],"type":"Point"}
}