{
  "type": "Feature",
  "properties": {
    "addr:full":"Am Riedelwald 5 Seekirchen am Wallersee Salzburg 5201",
    "addr:housenumber":"5",
    "addr:postcode":"5201",
    "addr:street":"Am Riedelwald;Salzburg",
    "iso:country":"AT",
    "sg:address":"Am Riedelwald 5",
    "sg:city":"Seekirchen am Wallersee",
    "sg:orig_category":"Maler, Anstreicher U Lackierer",
    "sg:phone":"+43 6212 7858",
    "sg:postcode":"5201",
    "sg:province":"Salzburg",
    "wof:name":"Naderer Hermann",
    "wof:placetype":"venue"
},
  "geometry": {"coordinates":[13.1205911636,47.9094696045],"type":"Point"}
}