{
  "type": "Feature",
  "properties": {
    "addr:full":"Siebenbrunneng 57 Wien Wien 1050",
    "addr:housenumber":"57",
    "addr:postcode":"1050",
    "addr:street":"Siebenbrunneng",
    "iso:country":"AT",
    "sg:address":"Siebenbrunneng 57",
    "sg:city":"Wien",
    "sg:orig_category":"Tachometer",
    "sg:phone":"+43 1 5441324",
    "sg:postcode":"1050",
    "sg:province":"Wien",
    "sg:website":"havlik-instruments.at",
    "wof:name":"Autoarmaturen Havlik H",
    "wof:placetype":"venue"
},
  "geometry": {"coordinates":[16.3529586792,48.1847419739],"type":"Point"}
}