{
  "type": "Feature",
  "properties": {
    "addr:full":"Karl-Schwed-G 99 Wien Wien 1230",
    "addr:housenumber":"99",
    "addr:postcode":"1230",
    "addr:street":"Karl-Schwed-G",
    "iso:country":"AT",
    "sg:address":"Karl-Schwed-G 99",
    "sg:city":"Wien",
    "sg:orig_category":"Gartenarchitekten",
    "sg:phone":"+43 1 8882104",
    "sg:postcode":"1230",
    "sg:province":"Wien",
    "wof:name":"Hauser Gerold Ing",
    "wof:placetype":"venue"
},
  "geometry": {"coordinates":[16.2797813416,48.152961731],"type":"Point"}
}