{
  "type": "Feature",
  "properties": {
    "addr:full":"Ludlg 16 Linz Ober\u00f6sterreich 4020",
    "addr:housenumber":"16",
    "addr:postcode":"4020",
    "addr:street":"Ludlg",
    "iso:country":"AT",
    "sg:address":"Ludlg 16",
    "sg:city":"Linz",
    "sg:orig_category":"Tonstudios",
    "sg:phone":"+43 664 4346538",
    "sg:postcode":"4020",
    "sg:province":"Ober\u00f6sterreich",
    "wof:name":"VICOM Audioproduction",
    "wof:placetype":"venue"
},
  "geometry": {"coordinates":[14.2451400757,48.3018455505],"type":"Point"}
}