{
  "type": "Feature",
  "properties": {
    "addr:full":"Vogelweider Str 3b Wels Ober\u00f6sterreich 4600",
    "addr:housenumber":"3b",
    "addr:postcode":"4600",
    "addr:street":"Str;Oberoesterreich",
    "iso:country":"AT",
    "sg:address":"Vogelweider Str 3b",
    "sg:city":"Wels",
    "sg:orig_category":"Schlankheitsinstitute",
    "sg:phone":"+43 7242 910484",
    "sg:postcode":"4600",
    "sg:province":"Ober\u00f6sterreich",
    "wof:name":"Figurstudio - Hypoxi Center Wels",
    "wof:placetype":"venue"
},
  "geometry": {"coordinates":[14.0184679031,48.1606826782],"type":"Point"}
}