{
  "type": "Feature",
  "properties": {
    "iso:country":"AT",
    "sg:address":"P\u00f6tschachg 1",
    "sg:city":"Kapfenberg",
    "sg:orig_category":"Restaurants: Griechisch",
    "sg:phone":"+43 4338 6234076",
    "sg:postcode":"8605",
    "sg:province":"Steiermark",
    "wof:name":"Restaurant Poseidon",
    "wof:placetype":"venue"
},
  "geometry": {"coordinates":[15.3366880417,47.4585876465],"type":"Point"}
}