{
  "type": "Feature",
  "properties": {
    "addr:full":"Inneralpbach 20 Alpbach Tirol 6236",
    "addr:housenumber":"20",
    "addr:postcode":"6236",
    "addr:street":"Inneralpbach;Tirol",
    "iso:country":"AT",
    "sg:address":"Inneralpbach 20",
    "sg:city":"Alpbach",
    "sg:orig_category":"Bauunternehmen",
    "sg:phone":"+43 5336 5687",
    "sg:postcode":"6236",
    "sg:province":"Tirol",
    "wof:name":"Lederer Hansj\u00f6rg GesmbH & Co KG",
    "wof:placetype":"venue"
},
  "geometry": {"coordinates":[11.9435110092,47.3986091614],"type":"Point"}
}