{
  "type": "Feature",
  "properties": {
    "addr:full":"Radetzkystr 9 Klagenfurt K\u00e4rnten 9020",
    "addr:housenumber":"9",
    "addr:postcode":"9020",
    "addr:street":"Radetzkystr;Kaernten",
    "iso:country":"AT",
    "sg:address":"Radetzkystr 9",
    "sg:city":"Klagenfurt",
    "sg:orig_category":"Inkassoinstitute",
    "sg:phone":"+43 463 55916",
    "sg:postcode":"9020",
    "sg:province":"K\u00e4rnten",
    "wof:name":"Austria Kreditorengesellschaft OHG Dr Wrulich & Co Nachf",
    "wof:placetype":"venue"
},
  "geometry": {"coordinates":[14.2998332977,46.627204895],"type":"Point"}
}