{
  "type": "Feature",
  "properties": {
    "addr:full":"Kirchbichl Tirol 6322",
    "addr:postcode":"6322",
    "addr:street":"Kirchbichl Tirol",
    "iso:country":"AT",
    "sg:city":"Kirchbichl",
    "sg:orig_category":"Feuerwehren",
    "sg:phone":"+43 5332 87477",
    "sg:postcode":"6322",
    "sg:province":"Tirol",
    "wof:name":"Freiwillige Feuerwehr Kirchbichl",
    "wof:placetype":"venue"
},
  "geometry": {"coordinates":[12.0880002975,47.5128707886],"type":"Point"}
}