{
  "type": "Feature",
  "properties": {
    "addr:full":"Kaiserstr 98 Wien Wien 1070",
    "addr:housenumber":"98",
    "addr:postcode":"1070",
    "addr:street":"Kaiserstr",
    "iso:country":"AT",
    "sg:address":"Kaiserstr 98",
    "sg:city":"Wien",
    "sg:orig_category":"Restaurants: Persisch",
    "sg:phone":"+43 1 5239936",
    "sg:postcode":"1070",
    "sg:province":"Wien",
    "wof:name":"Restaurant Hafes",
    "wof:placetype":"venue"
},
  "geometry": {"coordinates":[16.3396186829,48.2072601318],"type":"Point"}
}