{
  "type": "Feature",
  "properties": {
    "addr:full":"Wagramer Str 278 Gerasdorf Nieder\u00f6sterreich 2201",
    "addr:housenumber":"278;2201",
    "addr:street":"Gerasdorf Niederoesterreich",
    "iso:country":"AT",
    "sg:address":"Wagramer Str 278",
    "sg:city":"Gerasdorf",
    "sg:orig_category":"Beton- U Betonsteinwerke",
    "sg:phone":"+43 4317 347374",
    "sg:postcode":"2201",
    "sg:province":"Nieder\u00f6sterreich",
    "wof:name":"Betonwerk Mery",
    "wof:placetype":"venue"
},
  "geometry": {"coordinates":[16.4789562225,48.2754249573],"type":"Point"}
}