{
  "type": "Feature",
  "properties": {
    "addr:full":"Dorfstr 19 Fuschl am See Salzburg 5330",
    "addr:housenumber":"19",
    "addr:postcode":"5330",
    "addr:street":"Dorfstr",
    "iso:country":"AT",
    "sg:address":"Dorfstr 19",
    "sg:city":"Fuschl am See",
    "sg:orig_category":"Pensionen / Privatzimmer",
    "sg:phone":"+43 6226 8414",
    "sg:postcode":"5330",
    "sg:province":"Salzburg",
    "wof:name":"Pension Schoberblick",
    "wof:placetype":"venue"
},
  "geometry": {"coordinates":[13.2997331619,47.7964134216],"type":"Point"}
}