{
  "type": "Feature",
  "properties": {
    "addr:full":"Kircheng 4 Ulrichsberg Ober\u00f6sterreich 4161",
    "addr:housenumber":"4",
    "addr:postcode":"4161",
    "addr:street":"Kircheng",
    "iso:country":"AT",
    "sg:address":"Kircheng 4",
    "sg:city":"Ulrichsberg",
    "sg:classifiers":[
        {
            "category":"Restaurant",
            "type":"Food & Drink"
        }
    ],
    "sg:phone":"+43 7288 2218",
    "sg:postcode":"4161",
    "sg:province":"Ober\u00f6sterreich",
    "wof:name":"Hotel Restaurant B\u00f6hmerwaldhof",
    "wof:placetype":"venue"
},
  "geometry": {"coordinates":[13.9109706879,48.6753807068],"type":"Point"}
}