{
  "type": "Feature",
  "properties": {
    "addr:full":"Stattegger Str 135 Andritz Steiermark 8045",
    "addr:housenumber":"135",
    "addr:postcode":"8045",
    "addr:street":"Str",
    "iso:country":"AT",
    "sg:address":"Stattegger Str 135",
    "sg:city":"Andritz",
    "sg:orig_category":"Pensionen / Privatzimmer",
    "sg:phone":"+43 316 691169",
    "sg:postcode":"8045",
    "sg:province":"Steiermark",
    "wof:name":"Pension z Scherwirt",
    "wof:placetype":"venue"
},
  "geometry": {"coordinates":[15.4245986938,47.1248855591],"type":"Point"}
}