{
  "type": "Feature",
  "properties": {
    "addr:full":"Elisabethallee 61-63 Wien Wien 1130",
    "addr:postcode":"61-63;1130",
    "addr:street":"Elisabethallee",
    "iso:country":"AT",
    "sg:address":"Elisabethallee 61-63",
    "sg:city":"Wien",
    "sg:orig_category":"Banken U Sparkassen",
    "sg:phone":"+43 4350 10020133",
    "sg:postcode":"1130",
    "sg:province":"Wien",
    "wof:name":"Erste Bank d oesterreichischen Sparkassen AG",
    "wof:placetype":"venue"
},
  "geometry": {"coordinates":[16.2983455658,48.1747322083],"type":"Point"}
}