{
  "type": "Feature",
  "properties": {
    "iso:country":"AT",
    "sg:address":"Industriezeile 11",
    "sg:city":"Braunau am Inn",
    "sg:classifiers":[
        {
            "category":"Home & Garden",
            "subcategory":"Furniture",
            "type":"Retail Goods"
        }
    ],
    "sg:phone":"+43 7722 65878",
    "sg:postcode":"5280",
    "sg:province":"Ober\u00f6sterreich",
    "sg:tags":[
        "bathroom"
    ],
    "sg:website":"wohndesign-kraxenberger.at",
    "wof:name":"Peter Kraxenberger",
    "wof:placetype":"venue"
},
  "geometry": {"coordinates":[13.0650262833,48.2495956421],"type":"Point"}
}