{
  "type": "Feature",
  "properties": {
    "addr:full":"Eisenst\u00e4dter Str 94 Oberpullendorf Burgenland 7350",
    "addr:housenumber":"94",
    "addr:postcode":"7350",
    "addr:street":"Str",
    "iso:country":"AT",
    "sg:address":"Eisenst\u00e4dter Str 94",
    "sg:city":"Oberpullendorf",
    "sg:orig_category":"Installationsunternehmen",
    "sg:phone":"+43 4326 1242512",
    "sg:postcode":"7350",
    "sg:province":"Burgenland",
    "wof:name":"Installationstechnik Adolf Kozar",
    "wof:placetype":"venue"
},
  "geometry": {"coordinates":[16.5076637268,47.5043067932],"type":"Point"}
}