{
  "type": "Feature",
  "properties": {
    "addr:full":"Madelg 860 Oberalm Salzburg 5411",
    "addr:housenumber":"860",
    "addr:postcode":"5411",
    "addr:street":"Salzburg",
    "iso:country":"AT",
    "sg:address":"Madelg 860",
    "sg:city":"Oberalm",
    "sg:classifiers":[
        {
            "category":"Professional",
            "subcategory":"Computer Services",
            "type":"Services"
        }
    ],
    "sg:phone":"+43 6245 830900",
    "sg:postcode":"5411",
    "sg:province":"Salzburg",
    "sg:tags":[
        "software"
    ],
    "wof:name":"SOL-Software L\u00f6sungen GesmbH",
    "wof:placetype":"venue"
},
  "geometry": {"coordinates":[13.0987501144,47.7005195618],"type":"Point"}
}