{
  "type": "Feature",
  "properties": {
    "iso:country":"AT",
    "sg:address":"J Nepomuk Berger-Pl 5",
    "sg:city":"Wien",
    "sg:orig_category":"Handelsagenturen",
    "sg:phone":"+43 1 4803145",
    "sg:postcode":"1160",
    "sg:province":"Wien",
    "wof:name":"Fuchs Johannes",
    "wof:placetype":"venue"
},
  "geometry": {"coordinates":[16.3265132904,48.2123146057],"type":"Point"}
}