{
  "type": "Feature",
  "properties": {
    "addr:full":"Gmundner Str 1 Laakirchen Ober\u00f6sterreich 4663",
    "addr:housenumber":"1",
    "addr:postcode":"4663",
    "addr:street":"Str",
    "iso:country":"AT",
    "sg:address":"Gmundner Str 1",
    "sg:city":"Laakirchen",
    "sg:orig_category":"Drogerien",
    "sg:phone":"+43 76132218",
    "sg:postcode":"4663",
    "sg:province":"Ober\u00f6sterreich",
    "wof:name":"Drogerie Gr\u00e4finger Druckenthaner KEG",
    "wof:placetype":"venue"
},
  "geometry": {"coordinates":[13.8239250183,47.9815635681],"type":"Point"}
}