{
  "type": "Feature",
  "properties": {
    "iso:country":"AT",
    "sg:address":"Industriestr 306",
    "sg:city":"Markt Hartmannsdorf",
    "sg:orig_category":"Abfallentsorgung U -Verwertung",
    "sg:phone":"+43 4331 1420210",
    "sg:postcode":"8311",
    "sg:province":"Steiermark",
    "wof:name":"M\u00fcllex Umwelt-S\u00e4uberung GesmbH",
    "wof:placetype":"venue"
},
  "geometry": {"coordinates":[15.8428945541,47.0542297363],"type":"Point"}
}