{
  "type": "Feature",
  "properties": {
    "addr:full":"Jubil\u00e4umspl 7 Lambach Ober\u00f6sterreich 4650",
    "addr:housenumber":"7",
    "addr:postcode":"4650",
    "addr:street":"Jubilaeumspl",
    "iso:country":"AT",
    "sg:address":"Jubil\u00e4umspl 7",
    "sg:city":"Lambach",
    "sg:orig_category":"Glasereien",
    "sg:phone":"+43 4372 4528379",
    "sg:postcode":"4650",
    "sg:province":"Ober\u00f6sterreich",
    "wof:name":"Niedermair-Fr\u00f6schl Gabriele",
    "wof:placetype":"venue"
},
  "geometry": {"coordinates":[13.8777017593,48.0913200378],"type":"Point"}
}