{
  "type": "Feature",
  "properties": {
    "iso:country":"AT",
    "sg:address":"Hauptpl 33",
    "sg:city":"Mureck",
    "sg:orig_category":"Damenmoden",
    "sg:phone":"+43 4334 7221070",
    "sg:postcode":"8480",
    "sg:province":"Steiermark",
    "wof:name":"Obal Michael GesmbH & Co KG",
    "wof:placetype":"venue"
},
  "geometry": {"coordinates":[15.7746982574,46.7077636719],"type":"Point"}
}