{
  "type": "Feature",
  "properties": {
    "addr:full":"Nr 34 St. Kathrein am Hauenstein Steiermark 8672",
    "addr:postcode":"8672",
    "addr:street":"Nr 34",
    "iso:country":"AT",
    "sg:address":"Nr 34",
    "sg:city":"St. Kathrein am Hauenstein",
    "sg:orig_category":"Pensionen / Privatzimmer",
    "sg:phone":"+43 4331 732711",
    "sg:postcode":"8672",
    "sg:province":"Steiermark",
    "wof:name":"ROSEGGERHOF - Steindl Edith",
    "wof:placetype":"venue"
},
  "geometry": {"coordinates":[15.6930246353,47.4891395569],"type":"Point"}
}