{
  "type": "Feature",
  "properties": {
    "iso:country":"AT",
    "sg:address":"Altes Dorf 45",
    "sg:city":"Markgrafneusiedl",
    "sg:orig_category":"Autoreparatur",
    "sg:phone":"+43 2248 22890",
    "sg:postcode":"2282",
    "sg:province":"Nieder\u00f6sterreich",
    "wof:name":"Haidweger Erich",
    "wof:placetype":"venue"
},
  "geometry": {"coordinates":[16.6322822571,48.2664489746],"type":"Point"}
}