{
  "type": "Feature",
  "properties": {
    "addr:full":"Kerpelystr 199 Leoben Steiermark 8700",
    "addr:housenumber":"199",
    "addr:postcode":"8700",
    "iso:country":"AT",
    "sg:address":"Kerpelystr 199",
    "sg:city":"Leoben",
    "sg:orig_category":"Metallbe- U -Verarbeitung",
    "sg:phone":"+43 3842 2020",
    "sg:postcode":"8700",
    "sg:province":"Steiermark",
    "wof:name":"VOEST-ALPINE SCHIENEN GmbH",
    "wof:placetype":"venue"
},
  "geometry": {"coordinates":[15.0597066879,47.3799171448],"type":"Point"}
}