{
  "type": "Feature",
  "properties": {
    "addr:full":"Riegersdorf 30 Riegersdorf K\u00e4rnten 9587",
    "addr:housenumber":"30",
    "addr:postcode":"9587",
    "addr:street":"Riegersdorf;Kaernten",
    "iso:country":"AT",
    "sg:address":"Riegersdorf 30",
    "sg:city":"Riegersdorf",
    "sg:orig_category":"Granite Pavers",
    "sg:phone":"+43 4257 2305",
    "sg:postcode":"9587",
    "sg:province":"K\u00e4rnten",
    "wof:name":"Bernhard Hebenstreit",
    "wof:placetype":"venue"
},
  "geometry": {"coordinates":[13.7839460373,46.5487213135],"type":"Point"}
}