{
  "type": "Feature",
  "properties": {
    "addr:full":"Premweg 1 St. Johann im Pongau Salzburg 5600",
    "addr:housenumber":"1",
    "addr:postcode":"5600",
    "addr:street":"Premweg;Salzburg",
    "iso:country":"AT",
    "sg:address":"Premweg 1",
    "sg:city":"St. Johann im Pongau",
    "sg:orig_category":"Dekorationen",
    "sg:phone":"+43 6412 73230",
    "sg:postcode":"5600",
    "sg:province":"Salzburg",
    "wof:name":"Fantasy Production - Perwein & Kirchmayr GmbH & Co KG",
    "wof:placetype":"venue"
},
  "geometry": {"coordinates":[13.2067899704,47.3504104614],"type":"Point"}
}