{
  "type": "Feature",
  "properties": {
    "addr:full":"Bahnhofstr 1 Kolsass Tirol 6114",
    "addr:housenumber":"1",
    "addr:postcode":"6114",
    "addr:street":"Bahnhofstr;Tirol",
    "iso:country":"AT",
    "sg:address":"Bahnhofstr 1",
    "sg:city":"Kolsass",
    "sg:orig_category":"Speditionen",
    "sg:phone":"+43 4352 2466450",
    "sg:postcode":"6114",
    "sg:province":"Tirol",
    "wof:name":"Transatlas Speditions- u HandelsgesmbH",
    "wof:placetype":"venue"
},
  "geometry": {"coordinates":[11.6400489807,47.304725647],"type":"Point"}
}