{
  "type": "Feature",
  "properties": {
    "iso:country":"AT",
    "sg:address":"Dr Franz Peyerl-Str 11",
    "sg:city":"Gr\u00f6dig",
    "sg:orig_category":"Physiotherapie",
    "sg:phone":"+43 6246 77404",
    "sg:postcode":"5082",
    "sg:province":"Salzburg",
    "wof:name":"Presslmayr J\u00fcrgen Dipl-PT",
    "wof:placetype":"venue"
},
  "geometry": {"coordinates":[-76.2684555054,37.4373283386],"type":"Point"}
}