{
  "type": "Feature",
  "properties": {
    "addr:full":"Waldhof 64 Abtenau Salzburg 5441",
    "addr:housenumber":"64",
    "addr:postcode":"5441",
    "addr:street":"Waldhof;Salzburg",
    "iso:country":"AT",
    "sg:address":"Waldhof 64",
    "sg:city":"Abtenau",
    "sg:orig_category":"Sportschulen",
    "sg:phone":"+43 6243 3069",
    "sg:postcode":"5441",
    "sg:province":"Salzburg",
    "wof:name":"Zwilling David",
    "wof:placetype":"venue"
},
  "geometry": {"coordinates":[13.3099889755,47.593662262],"type":"Point"}
}