{
  "type": "Feature",
  "properties": {
    "addr:full":"Molkereistrasse 4 Wiener Neustadt Nieder\u00f6sterreich 2700",
    "addr:housenumber":"4",
    "addr:postcode":"2700",
    "addr:street":"Molkereistrasse",
    "iso:country":"AT",
    "sg:address":"Molkereistrasse 4",
    "sg:city":"Wiener Neustadt",
    "sg:classifiers":[
        {
            "category":"Manufacturing",
            "subcategory":"Rubber & Plastics",
            "type":"Manufacturing & Wholesale Goods"
        }
    ],
    "sg:phone":"+43 2622 220730",
    "sg:postcode":"2700",
    "sg:province":"Nieder\u00f6sterreich",
    "sg:tags":[
        "balcony"
    ],
    "wof:name":"ITRACO ChemikalienhandelsgesmbH",
    "wof:placetype":"venue"
},
  "geometry": {"coordinates":[16.2218894958,47.794921875],"type":"Point"}
}