{
  "type": "Feature",
  "properties": {
    "addr:full":"Gustav-Kramer-Str 5b Kapfenberg Steiermark 8605",
    "addr:housenumber":"5b",
    "addr:postcode":"8605",
    "addr:street":"Gustav-Kramer-Str",
    "iso:country":"AT",
    "sg:address":"Gustav-Kramer-Str 5b",
    "sg:city":"Kapfenberg",
    "sg:orig_category":"Apparatebau",
    "sg:phone":"+43 3862 250250",
    "sg:postcode":"8605",
    "sg:province":"Steiermark",
    "wof:name":"Apparatebau-Schwei\u00dftechnik GesmbH",
    "wof:placetype":"venue"
},
  "geometry": {"coordinates":[15.2759485245,47.432723999],"type":"Point"}
}