{
  "type": "Feature",
  "properties": {
    "addr:full":"Schmittenstr 8 Zell am See Salzburg 5700",
    "addr:housenumber":"8",
    "addr:postcode":"5700",
    "addr:street":"Schmittenstr;Salzburg",
    "iso:country":"AT",
    "sg:address":"Schmittenstr 8",
    "sg:city":"Zell am See",
    "sg:orig_category":"Eisenwaren",
    "sg:phone":"+43 6542 725240",
    "sg:postcode":"5700",
    "sg:province":"Salzburg",
    "wof:name":"Kleineisen F GesmbH",
    "wof:placetype":"venue"
},
  "geometry": {"coordinates":[12.7946338654,47.3239593506],"type":"Point"}
}