{
  "type": "Feature",
  "properties": {
    "addr:full":"Habring 42 Bad H\u00e4ring Tirol 6323",
    "addr:housenumber":"42",
    "addr:postcode":"6323",
    "addr:street":"Habring;Tirol",
    "iso:country":"AT",
    "sg:address":"Habring 42",
    "sg:city":"Bad H\u00e4ring",
    "sg:orig_category":"Transportunternehmen",
    "sg:phone":"+43 5372 58008",
    "sg:postcode":"6323",
    "sg:province":"Tirol",
    "wof:name":"Meyer Josef",
    "wof:placetype":"venue"
},
  "geometry": {"coordinates":[-88.67497253419999,43.9075889587],"type":"Point"}
}