{
  "type": "Feature",
  "properties": {
    "addr:full":"Gmachlstr 781 Kaprun Salzburg 5710",
    "addr:housenumber":"781",
    "addr:postcode":"5710",
    "addr:street":"Kaprun Salzburg",
    "iso:country":"AT",
    "sg:address":"Gmachlstr 781",
    "sg:city":"Kaprun",
    "sg:orig_category":"Spenglereien",
    "sg:phone":"+43 6547 8720",
    "sg:postcode":"5710",
    "sg:province":"Salzburg",
    "wof:name":"Hartl Josef GmbH & Co KEG",
    "wof:placetype":"venue"
},
  "geometry": {"coordinates":[12.7546634674,47.2828140259],"type":"Point"}
}