{
  "type": "Feature",
  "properties": {
    "addr:full":"St. Isidor 1 Leonding Ober\u00f6sterreich 4060",
    "addr:housenumber":"1",
    "addr:postcode":"4060",
    "addr:street":"St. Isidor",
    "iso:country":"AT",
    "sg:address":"St. Isidor 1",
    "sg:city":"Leonding",
    "sg:orig_category":"Waren Aller Art",
    "sg:phone":"+43 732 674161",
    "sg:postcode":"4060",
    "sg:province":"Ober\u00f6sterreich",
    "wof:name":"HandOver Sozial-Handelsagentur GmbH",
    "wof:placetype":"venue"
},
  "geometry": {"coordinates":[14.2655277252,48.2640953064],"type":"Point"}
}