{
  "type": "Feature",
  "properties": {
    "iso:country":"AT",
    "sg:address":"Industriestrasse 235",
    "sg:city":"St. Margarethen an der Raab",
    "sg:classifiers":[
        {
            "category":"Government",
            "subcategory":"Fire Station",
            "type":"Public Place"
        }
    ],
    "sg:phone":"+43 3115 61160",
    "sg:postcode":"8321",
    "sg:province":"Steiermark",
    "sg:tags":[
        "central",
        "fired",
        "biomass",
        "heating",
        "boiler",
        "fuel"
    ],
    "sg:website":"kwb.at",
    "wof:name":"KWB - Kraft und W\u00e4rme aus Biomasse GmbH",
    "wof:placetype":"venue"
},
  "geometry": {"coordinates":[15.7470998764,47.0482559204],"type":"Point"}
}