{
  "type": "Feature",
  "properties": {
    "iso:country":"AT",
    "sg:address":"Blaiken 62",
    "sg:city":"Scheffau am Wilden Kaiser",
    "sg:orig_category":"Rauchfangkehrer",
    "sg:phone":"+43 5358 8121",
    "sg:postcode":"6351",
    "sg:province":"Tirol",
    "wof:name":"Prem Josef",
    "wof:placetype":"venue"
},
  "geometry": {"coordinates":[12.2495040894,47.5211524963],"type":"Point"}
}