{
  "type": "Feature",
  "properties": {
    "iso:country":"AT",
    "sg:address":"Schie\u00dfst\u00e4ttgasse 27-29",
    "sg:city":"Neunkirchen",
    "sg:classifiers":[
        {
            "category":"Home & Garden",
            "subcategory":"Building Materials",
            "type":"Retail Goods"
        }
    ],
    "sg:phone":"+43 2635 651500",
    "sg:postcode":"2620",
    "sg:province":"Nieder\u00f6sterreich",
    "sg:tags":[
        "tile",
        "ceramic"
    ],
    "sg:website":"bocksrucker.at",
    "wof:name":"Bocksrucker Ges.m.b.H.",
    "wof:placetype":"venue"
},
  "geometry": {"coordinates":[16.0825557709,47.7204246521],"type":"Point"}
}