{
  "type": "Feature",
  "properties": {
    "addr:full":"Wilfern 32 Assling Tirol 9911",
    "addr:housenumber":"32",
    "addr:postcode":"9911",
    "addr:street":"Wilfern;Tirol",
    "iso:country":"AT",
    "sg:address":"Wilfern 32",
    "sg:city":"Assling",
    "sg:orig_category":"Baumeister",
    "sg:phone":"+43 4855 8154",
    "sg:postcode":"9911",
    "sg:province":"Tirol",
    "wof:name":"Libiseller Wilhelm Ing",
    "wof:placetype":"venue"
},
  "geometry": {"coordinates":[12.6411066055,46.7863693237],"type":"Point"}
}