{
  "type": "Feature",
  "properties": {
    "addr:full":"Getreideg 13/I Klagenfurt K\u00e4rnten 9020",
    "addr:housenumber":"13 / i",
    "addr:postcode":"9020",
    "addr:street":"Getreideg;Kaernten",
    "iso:country":"AT",
    "sg:address":"Getreideg 13/I",
    "sg:city":"Klagenfurt",
    "sg:orig_category":"Friseure U Frisiersalons",
    "sg:phone":"+43 4346 3511838",
    "sg:postcode":"9020",
    "sg:province":"K\u00e4rnten",
    "wof:name":"Friseursalon Monique",
    "wof:placetype":"venue"
},
  "geometry": {"coordinates":[14.3274202347,46.6254196167],"type":"Point"}
}