{
  "type": "Feature",
  "properties": {
    "iso:country":"AT",
    "sg:address":"Birkenhain 5",
    "sg:city":"Lutzmannsburg",
    "sg:orig_category":"Appartements / Ferienwohnungen",
    "sg:phone":"+43 664 9827189",
    "sg:postcode":"7361",
    "sg:province":"Burgenland",
    "wof:name":"Huber Christine",
    "wof:placetype":"venue"
},
  "geometry": {"coordinates":[16.6310138702,47.4626960754],"type":"Point"}
}