{
  "type": "Feature",
  "properties": {
    "addr:full":"Pfarrpl 5 Baden Nieder\u00f6sterreich 2500",
    "addr:housenumber":"5",
    "addr:postcode":"2500",
    "addr:street":"Pfarrpl;Niederoesterreich",
    "iso:country":"AT",
    "sg:address":"Pfarrpl 5",
    "sg:city":"Baden",
    "sg:orig_category":"Friseure U Frisiersalons",
    "sg:phone":"+43 4322 5247960",
    "sg:postcode":"2500",
    "sg:province":"Nieder\u00f6sterreich",
    "wof:name":"Laschitz Guido",
    "wof:placetype":"venue"
},
  "geometry": {"coordinates":[16.2370262146,48.0097503662],"type":"Point"}
}