{
  "type": "Feature",
  "properties": {
    "iso:country":"AT",
    "sg:address":"Haselbach 100",
    "sg:city":"Eibiswald",
    "sg:classifiers":[
        {
            "category":"Building & Trades",
            "subcategory":"Construction",
            "type":"Services"
        }
    ],
    "sg:phone":"+43 3466 470250",
    "sg:postcode":"8552",
    "sg:province":"Steiermark",
    "sg:tags":[
        "cnc",
        "milling",
        "axis"
    ],
    "sg:website":"fuchshofer.at",
    "wof:name":"Fuchshofer GmbH",
    "wof:placetype":"venue"
},
  "geometry": {"coordinates":[15.2274599075,46.6824150085],"type":"Point"}
}