{
  "type": "Feature",
  "properties": {
    "addr:full":"Industriestr. 25 Haid Ober\u00f6sterreich 4053",
    "addr:housenumber":"25",
    "addr:postcode":"4053",
    "addr:street":"Industriestr.",
    "iso:country":"AT",
    "sg:address":"Industriestr. 25",
    "sg:city":"Haid",
    "sg:classifiers":[
        {
            "category":"Manufacturing",
            "subcategory":"Metals",
            "type":"Manufacturing & Wholesale Goods"
        }
    ],
    "sg:phone":"+43 4372 2988701",
    "sg:postcode":"4053",
    "sg:province":"Ober\u00f6sterreich",
    "sg:tags":[
        "metallurgy",
        "metalworking"
    ],
    "wof:name":"BEST-BAUEISEN-U. STAHLBEARBEITUNGS GES.MBH",
    "wof:placetype":"venue"
},
  "geometry": {"coordinates":[14.2602996826,48.2097244263],"type":"Point"}
}