{
  "type": "Feature",
  "properties": {
    "addr:full":"Schneeberg 31 Thiersee Tirol 6335",
    "addr:housenumber":"31",
    "addr:postcode":"6335",
    "addr:street":"Schneeberg;Tirol",
    "iso:country":"AT",
    "sg:address":"Schneeberg 31",
    "sg:city":"Thiersee",
    "sg:orig_category":"Hafnereien",
    "sg:phone":"+43 5376 5377",
    "sg:postcode":"6335",
    "sg:province":"Tirol",
    "wof:name":"Ofenbau J\u00e4ger",
    "wof:placetype":"venue"
},
  "geometry": {"coordinates":[12.0985555649,47.5829620361],"type":"Point"}
}