{
  "type": "Feature",
  "properties": {
    "addr:full":"Stephanspl 7 Wien Wien 1010",
    "addr:housenumber":"7",
    "addr:postcode":"1010",
    "addr:street":"Stephanspl",
    "iso:country":"AT",
    "sg:address":"Stephanspl 7",
    "sg:city":"Wien",
    "sg:classifiers":[
        {
            "category":"Restaurant",
            "type":"Food & Drink"
        }
    ],
    "sg:phone":"+43 1 5121444",
    "sg:postcode":"1010",
    "sg:province":"Wien",
    "sg:tags":[
        "pizzeria"
    ],
    "wof:name":"Spaghetti & Co",
    "wof:placetype":"venue"
},
  "geometry": {"coordinates":[16.3733787537,48.2090415955],"type":"Point"}
}