{
  "type": "Feature",
  "properties": {
    "iso:country":"AT",
    "sg:address":"Harl 25",
    "sg:city":"Puch",
    "sg:orig_category":"Heurigen / Buschenschank",
    "sg:phone":"+43 4331 773117",
    "sg:postcode":"8182",
    "sg:province":"Steiermark",
    "wof:name":"Haus d Apfels - steir Obstbaumuseum",
    "wof:placetype":"venue"
},
  "geometry": {"coordinates":[15.7093105316,47.243473053],"type":"Point"}
}