{
  "type": "Feature",
  "properties": {
    "iso:country":"AT",
    "sg:address":"Starkfriedgasse 46",
    "sg:city":"Wien",
    "sg:classifiers":[
        {
            "category":"Professional",
            "subcategory":"Employment Agencies",
            "type":"Services"
        }
    ],
    "sg:phone":"+43 1 47081720",
    "sg:postcode":"1190",
    "sg:province":"Wien",
    "sg:tags":[
        "pr",
        "relation",
        "public"
    ],
    "wof:name":"Ilse Zembaty Public Relations",
    "wof:placetype":"venue"
},
  "geometry": {"coordinates":[16.3095550537,48.2446136475],"type":"Point"}
}