{
  "type": "Feature",
  "properties": {
    "addr:full":"Kalham Gewerbestr 11 Eugendorf Salzburg 5301",
    "addr:housenumber":"11",
    "addr:postcode":"5301",
    "addr:street":"Eugendorf Salzburg",
    "iso:country":"AT",
    "sg:address":"Kalham Gewerbestr 11",
    "sg:city":"Eugendorf",
    "sg:orig_category":"Metallwaren / Erzeugung U Gro\u00c3\u0178handel",
    "sg:phone":"+43 4362 258292",
    "sg:postcode":"5301",
    "sg:province":"Salzburg",
    "wof:name":"Rachbauer M GmbH & Co KG",
    "wof:placetype":"venue"
},
  "geometry": {"coordinates":[13.1306285858,47.8585700989],"type":"Point"}
}