{
  "type": "Feature",
  "properties": {
    "iso:country":"AT",
    "sg:address":"Edelaustr 20",
    "sg:city":"Prinzersdorf",
    "sg:orig_category":"Tischlereien",
    "sg:phone":"+43 2749 8681",
    "sg:postcode":"3385",
    "sg:province":"Nieder\u00f6sterreich",
    "wof:name":"Plank Franz Ing GmbH",
    "wof:placetype":"venue"
},
  "geometry": {"coordinates":[15.5107288361,48.2082061768],"type":"Point"}
}