{
  "type": "Feature",
  "properties": {
    "iso:country":"AT",
    "sg:address":"Nr 7",
    "sg:city":"Dellach im Drautal",
    "sg:orig_category":"Autoreparatur",
    "sg:phone":"+43 4347 142260",
    "sg:postcode":"9772",
    "sg:province":"K\u00e4rnten",
    "wof:name":"Shell Austria GmbH",
    "wof:placetype":"venue"
},
  "geometry": {"coordinates":[13.0824251175,46.7413406372],"type":"Point"}
}