{
  "type": "Feature",
  "properties": {
    "addr:full":"Hauptstrasse 4 Peuerbach Ober\u00f6sterreich 4722",
    "addr:housenumber":"4",
    "addr:postcode":"4722",
    "addr:street":"Hauptstrasse",
    "iso:country":"AT",
    "sg:address":"Hauptstrasse 4",
    "sg:city":"Peuerbach",
    "sg:classifiers":[
        {
            "category":"Food & Beverages",
            "subcategory":"Meat & Fish",
            "type":"Retail Goods"
        }
    ],
    "sg:phone":"+43 7276 2181",
    "sg:postcode":"4722",
    "sg:province":"Ober\u00f6sterreich",
    "sg:tags":[
        "sausage",
        "cured",
        "product",
        "dried"
    ],
    "sg:website":"salami.at",
    "wof:name":"Wiesenberger Ges.m.b.H. & Co KG",
    "wof:placetype":"venue"
},
  "geometry": {"coordinates":[13.7724437714,48.3436508179],"type":"Point"}
}