{
  "type": "Feature",
  "properties": {
    "addr:full":"Nr 228 Heiligenkreuz im Lafnitztal Burgenland 7561",
    "addr:postcode":"7561",
    "addr:street":"Nr",
    "iso:country":"AT",
    "sg:address":"Nr 228",
    "sg:city":"Heiligenkreuz im Lafnitztal",
    "sg:orig_category":"Raumausstattung",
    "sg:phone":"+43 4333 254212",
    "sg:postcode":"7561",
    "sg:province":"Burgenland",
    "wof:name":"Gibiser Wohnmode",
    "wof:placetype":"venue"
},
  "geometry": {"coordinates":[16.2584495544,46.9887466431],"type":"Point"}
}