{
  "type": "Feature",
  "properties": {
    "iso:country":"AT",
    "sg:address":"Marcusstrasse 17",
    "sg:city":"Wels",
    "sg:classifiers":[
        {
            "category":"Health Services",
            "subcategory":"Hospital",
            "type":"Services"
        }
    ],
    "sg:phone":"+43 7242 456520",
    "sg:postcode":"4600",
    "sg:province":"Ober\u00f6sterreich",
    "sg:tags":[
        "rinsing",
        "bedpan",
        "sink",
        "apparatus"
    ],
    "sg:website":"hesta.at",
    "wof:name":"HESTA - Gro\u00dfk\u00fcchen Einrichtungsges.m.b.H.",
    "wof:placetype":"venue"
},
  "geometry": {"coordinates":[14.0526247025,48.1604347229],"type":"Point"}
}