{
  "type": "Feature",
  "properties": {
    "addr:full":"Marktstr 33 Altm\u00fcnster Ober\u00f6sterreich 4813",
    "addr:housenumber":"33",
    "addr:postcode":"4813",
    "addr:street":"Marktstr;Oberoesterreich",
    "iso:country":"AT",
    "sg:address":"Marktstr 33",
    "sg:city":"Altm\u00fcnster",
    "sg:orig_category":"Staubsauger",
    "sg:phone":"+43 761289289",
    "sg:postcode":"4813",
    "sg:province":"Ober\u00f6sterreich",
    "wof:name":"Staubsauger Spie\u00dfberger",
    "wof:placetype":"venue"
},
  "geometry": {"coordinates":[13.7609844208,47.899936676],"type":"Point"}
}