{
  "type": "Feature",
  "properties": {
    "addr:full":"Eichholz 5 Lienz Tirol 9900",
    "addr:housenumber":"5",
    "addr:postcode":"9900",
    "addr:street":"Eichholz;Tirol",
    "iso:country":"AT",
    "sg:address":"Eichholz 5",
    "sg:city":"Lienz",
    "sg:orig_category":"Fernseh- U Radiogesellschaften",
    "sg:phone":"+43 4348 5262754",
    "sg:postcode":"9900",
    "sg:province":"Tirol",
    "wof:name":"ORF \u00f6sterreichischer Rundfunk",
    "wof:placetype":"venue"
},
  "geometry": {"coordinates":[12.7733354568,46.8203086853],"type":"Point"}
}