{
  "type": "Feature",
  "properties": {
    "addr:full":"Nr 11 Hinterstoder Ober\u00f6sterreich 4573",
    "addr:postcode":"4573",
    "addr:street":"Nr;Hinterstoder Oberoesterreich",
    "iso:country":"AT",
    "sg:address":"Nr 11",
    "sg:city":"Hinterstoder",
    "sg:classifiers":[
        {
            "category":"Restaurant",
            "type":"Food & Drink"
        }
    ],
    "sg:phone":"+43 7564 55507",
    "sg:postcode":"4573",
    "sg:province":"Ober\u00f6sterreich",
    "sg:tags":[
        "pizzeria"
    ],
    "wof:name":"Pizza MamamiA Bar",
    "wof:placetype":"venue"
},
  "geometry": {"coordinates":[14.1566810608,47.7001152039],"type":"Point"}
}