{
  "type": "Feature",
  "properties": {
    "addr:full":"Hauptstr 67 Gramatneusiedl Nieder\u00f6sterreich 2440",
    "addr:housenumber":"67",
    "addr:postcode":"2440",
    "addr:street":"Hauptstr",
    "iso:country":"AT",
    "sg:address":"Hauptstr 67",
    "sg:city":"Gramatneusiedl",
    "sg:orig_category":"Friseure U Frisiersalons",
    "sg:phone":"+43 4322 3474414",
    "sg:postcode":"2440",
    "sg:province":"Nieder\u00f6sterreich",
    "wof:name":"Trieb Monika",
    "wof:placetype":"venue"
},
  "geometry": {"coordinates":[16.4626922607,48.0198669434],"type":"Point"}
}