{
  "type": "Feature",
  "properties": {
    "iso:country":"AT",
    "sg:address":"Raiffeiseng 26",
    "sg:city":"F\u00fcrstenfeld",
    "sg:orig_category":"Steinmetzbetriebe",
    "sg:phone":"+43 4333 8252535",
    "sg:postcode":"8280",
    "sg:province":"Steiermark",
    "wof:name":"K\u00f6nig Helmut",
    "wof:placetype":"venue"
},
  "geometry": {"coordinates":[16.0779876709,47.0439109802],"type":"Point"}
}