{
  "type": "Feature",
  "properties": {
    "addr:full":"Traiseng 18 Wien Wien 1200",
    "addr:housenumber":"18",
    "addr:postcode":"1200",
    "addr:street":"Traiseng",
    "iso:country":"AT",
    "sg:address":"Traiseng 18",
    "sg:city":"Wien",
    "sg:orig_category":"Installationsunternehmen",
    "sg:phone":"+43 1 3328663",
    "sg:postcode":"1200",
    "sg:province":"Wien",
    "wof:name":"Swoboda Leopold",
    "wof:placetype":"venue"
},
  "geometry": {"coordinates":[16.3890304565,48.2360916138],"type":"Point"}
}