{
  "type": "Feature",
  "properties": {
    "addr:full":"Nr 33 Traunstein Nieder\u00f6sterreich 3632",
    "addr:postcode":"3632",
    "addr:street":"Nr 33",
    "iso:country":"AT",
    "sg:address":"Nr 33",
    "sg:city":"Traunstein",
    "sg:orig_category":"Autoreparatur",
    "sg:phone":"+43 2878 6888",
    "sg:postcode":"3632",
    "sg:province":"Nieder\u00f6sterreich",
    "wof:name":"Hammerl Erich",
    "wof:placetype":"venue"
},
  "geometry": {"coordinates":[15.1159744263,48.4355010986],"type":"Point"}
}