{
  "type": "Feature",
  "properties": {
    "iso:country":"AT",
    "sg:address":"Nr 200",
    "sg:city":"Vorau",
    "sg:orig_category":"Musikunterricht",
    "sg:phone":"+43 3337 29800",
    "sg:postcode":"8250",
    "sg:province":"Steiermark",
    "wof:name":"Musikschule",
    "wof:placetype":"venue"
},
  "geometry": {"coordinates":[15.8873929977,47.4056854248],"type":"Point"}
}