{
  "type": "Feature",
  "properties": {
    "iso:country":"AT",
    "sg:address":"Schie\u00dfstattg 10",
    "sg:city":"Stockerau",
    "sg:orig_category":"\u00c3\u201erzte / F Allgemeinmedizin",
    "sg:phone":"+43 2266 64108",
    "sg:postcode":"2000",
    "sg:province":"Nieder\u00f6sterreich",
    "wof:name":"El-Hagin Anwar MedR Dr",
    "wof:placetype":"venue"
},
  "geometry": {"coordinates":[16.2105731964,48.3866424561],"type":"Point"}
}