{
  "type": "Feature",
  "properties": {
    "addr:full":"Kleine Stadtgutgasse 6-8 Wien Wien 1020",
    "addr:housenumber":"6-8",
    "addr:postcode":"1020",
    "addr:street":"Kleine Stadtgutgasse",
    "iso:country":"AT",
    "sg:address":"Kleine Stadtgutgasse 6-8",
    "sg:city":"Wien",
    "sg:classifiers":[
        {
            "category":"Banks & Credit Unions",
            "subcategory":"Bureau De Change",
            "type":"Services"
        }
    ],
    "sg:phone":"+43 1 2128683",
    "sg:postcode":"1020",
    "sg:province":"Wien",
    "sg:tags":[
        "image",
        "processing",
        "system",
        "digital"
    ],
    "sg:website":"painthouse.at",
    "wof:name":"Daniel Tarmann Werbegrafik GmbH & Co KEG",
    "wof:placetype":"venue"
},
  "geometry": {"coordinates":[16.3883666992,48.2187995911],"type":"Point"}
}