{
  "type": "Feature",
  "properties": {
    "addr:full":"Fred-Hochschwarzer-Weg 2 Schwaz Tirol 6130",
    "addr:housenumber":"2",
    "addr:postcode":"6130",
    "addr:street":"Fred-Hochschwarzer-Weg;Tirol",
    "iso:country":"AT",
    "sg:address":"Fred-Hochschwarzer-Weg 2",
    "sg:city":"Schwaz",
    "sg:orig_category":"Development Of Vending Machines",
    "sg:phone":"+43 5242 67642",
    "sg:postcode":"6130",
    "sg:province":"Tirol",
    "sg:website":"vendidata.com",
    "wof:name":"Vendidata Software Entwicklung GmbH",
    "wof:placetype":"venue"
},
  "geometry": {"coordinates":[11.7027702332,47.3430213928],"type":"Point"}
}