{
  "type": "Feature",
  "properties": {
    "addr:full":"Steinberg 20 Hitzendorf Steiermark 8151",
    "addr:housenumber":"20",
    "addr:postcode":"8151",
    "addr:street":"Steinberg",
    "iso:country":"AT",
    "sg:address":"Steinberg 20",
    "sg:city":"Hitzendorf",
    "sg:orig_category":"Personalbereitstellung",
    "sg:phone":"+43 676 7823875",
    "sg:postcode":"8151",
    "sg:province":"Steiermark",
    "wof:name":"Hemmer Marion - Ihr Partner f\u00fcr Zeitarbeit",
    "wof:placetype":"venue"
},
  "geometry": {"coordinates":[15.3087186813,47.0603141785],"type":"Point"}
}