{
  "type": "Feature",
  "properties": {
    "addr:full":"Auenweg 84c Bad St. Leonhard im Lavanttal K\u00e4rnten 9462",
    "addr:housenumber":"84c",
    "addr:postcode":"9462",
    "addr:street":"Auenweg",
    "iso:country":"AT",
    "sg:address":"Auenweg 84c",
    "sg:city":"Bad St. Leonhard im Lavanttal",
    "sg:orig_category":"Betonsanierungen",
    "sg:phone":"+43 4343 503117",
    "sg:postcode":"9462",
    "sg:province":"K\u00e4rnten",
    "wof:name":"KBB/MEISSL Oberfl\u00e4chentechnik Produktions GmbH",
    "wof:placetype":"venue"
},
  "geometry": {"coordinates":[14.8049173355,46.9542999268],"type":"Point"}
}