{
  "type": "Feature",
  "properties": {
    "iso:country":"AT",
    "sg:address":"Wasserg 2",
    "sg:city":"Baden",
    "sg:orig_category":"Glasereien",
    "sg:phone":"+43 2252 44374",
    "sg:postcode":"2500",
    "sg:province":"Nieder\u00f6sterreich",
    "wof:name":"Scharrer Franz",
    "wof:placetype":"venue"
},
  "geometry": {"coordinates":[16.2347183228,48.0072097778],"type":"Point"}
}