{
  "type": "Feature",
  "properties": {
    "iso:country":"AT",
    "sg:address":"S\u00fcdtiroler Str 20",
    "sg:city":"Rattenberg",
    "sg:orig_category":"Blumeneinzelhandel",
    "sg:phone":"+43 5337 63651",
    "sg:postcode":"6240",
    "sg:province":"Tirol",
    "wof:name":"Margreiter Christine",
    "wof:placetype":"venue"
},
  "geometry": {"coordinates":[11.9111118317,47.4462547302],"type":"Point"}
}