{
  "type": "Feature",
  "properties": {
    "addr:full":"Ramingtal 39 Kleinraming Ober\u00f6sterreich 4442",
    "addr:housenumber":"39",
    "addr:postcode":"4442",
    "addr:street":"Ramingtal",
    "iso:country":"AT",
    "sg:address":"Ramingtal 39",
    "sg:city":"Kleinraming",
    "sg:orig_category":"Volkshochschulen",
    "sg:phone":"+43 4372 5231017",
    "sg:postcode":"4442",
    "sg:province":"Ober\u00f6sterreich",
    "wof:name":"Volkshochschule Kleinramig",
    "wof:placetype":"venue"
},
  "geometry": {"coordinates":[14.4917802811,48.0093688965],"type":"Point"}
}