{
  "type": "Feature",
  "properties": {
    "addr:full":"Anton-Brugger-Str 11a Tschagguns Vorarlberg 6774",
    "addr:housenumber":"11a",
    "addr:postcode":"6774",
    "addr:street":"Anton-Brugger-Str",
    "iso:country":"AT",
    "sg:address":"Anton-Brugger-Str 11a",
    "sg:city":"Tschagguns",
    "sg:orig_category":"Appartements / Ferienwohnungen",
    "sg:phone":"+43 4355 5675441",
    "sg:postcode":"6774",
    "sg:province":"Vorarlberg",
    "wof:name":"Landhaus Schneider - Nadja u Harald Bitschnau",
    "wof:placetype":"venue"
},
  "geometry": {"coordinates":[9.9018363953,47.0745849609],"type":"Point"}
}