{
  "type": "Feature",
  "properties": {
    "addr:full":"Am Leopoldsgrund 68 Puntigam Steiermark 8055",
    "addr:housenumber":"68",
    "addr:postcode":"8055",
    "addr:street":"Am Leopoldsgrund",
    "iso:country":"AT",
    "sg:address":"Am Leopoldsgrund 68",
    "sg:city":"Puntigam",
    "sg:orig_category":"Waren Aller Art",
    "sg:phone":"+43 664 4121212",
    "sg:postcode":"8055",
    "sg:province":"Steiermark",
    "wof:name":"Stadler Manfred Reinigungsbedarf-Stadlers Supertuch",
    "wof:placetype":"venue"
},
  "geometry": {"coordinates":[15.4255685806,47.0214271545],"type":"Point"}
}