{
  "type": "Feature",
  "properties": {
    "iso:country":"AT",
    "sg:address":"Taborstrasse 2",
    "sg:city":"Fehring",
    "sg:classifiers":[
        {
            "category":"Home & Garden",
            "subcategory":"Household Appliances",
            "type":"Retail Goods"
        }
    ],
    "sg:phone":"+43 3155 2632",
    "sg:postcode":"8350",
    "sg:province":"Steiermark",
    "sg:tags":[
        "electric"
    ],
    "wof:name":"Expert Wohlmuther",
    "wof:placetype":"venue"
},
  "geometry": {"coordinates":[16.0110015869,46.9361915588],"type":"Point"}
}