{
  "type": "Feature",
  "properties": {
    "iso:country":"AT",
    "sg:address":"Nr 92",
    "sg:city":"Tragwein",
    "sg:orig_category":"Schlossereien",
    "sg:phone":"+43 7263 88011",
    "sg:postcode":"4284",
    "sg:province":"Ober\u00f6sterreich",
    "wof:name":"Haider Schlosserei GmbH",
    "wof:placetype":"venue"
},
  "geometry": {"coordinates":[14.622010231,48.3314437866],"type":"Point"}
}