{
  "type": "Feature",
  "properties": {
    "addr:full":"Donau-City-Str 1 Wien Wien 1220",
    "addr:housenumber":"1",
    "addr:postcode":"1220",
    "addr:street":"Donau-City-Str",
    "iso:country":"AT",
    "sg:address":"Donau-City-Str 1",
    "sg:city":"Wien",
    "sg:orig_category":"Datenverarbeitung",
    "sg:phone":"+43 1 5262967",
    "sg:postcode":"1220",
    "sg:province":"Wien",
    "wof:name":"UMA Information Technology AG",
    "wof:placetype":"venue"
},
  "geometry": {"coordinates":[16.4138431549,48.2321853638],"type":"Point"}
}