{
  "type": "Feature",
  "properties": {
    "iso:country":"AT",
    "sg:address":"Kopfingdorfer Str 74",
    "sg:city":"Kopfing im Innkreis",
    "sg:orig_category":"Fenster",
    "sg:phone":"+43 7763 2261",
    "sg:postcode":"4794",
    "sg:province":"Ober\u00f6sterreich",
    "wof:name":"Hamedinger Fritz GesmbH & Co KG",
    "wof:placetype":"venue"
},
  "geometry": {"coordinates":[13.6546430588,48.4428138733],"type":"Point"}
}