{
  "type": "Feature",
  "properties": {
    "iso:country":"AT",
    "sg:address":"Nr 7",
    "sg:city":"Gnas",
    "sg:orig_category":"Non-Classified Establishments",
    "sg:phone":"+43 3151 2428",
    "sg:postcode":"8342",
    "sg:province":"Steiermark",
    "wof:name":"H\u00fctter Maria KEG",
    "wof:placetype":"venue"
},
  "geometry": {"coordinates":[15.8265724182,46.8743095398],"type":"Point"}
}