{
  "type": "Feature",
  "properties": {
    "addr:full":"Nr 4 Neukirchen Ober\u00f6sterreich 4814",
    "addr:postcode":"4814",
    "addr:street":"Nr",
    "iso:country":"AT",
    "sg:address":"Nr 4",
    "sg:city":"Neukirchen",
    "sg:orig_category":"Volksschulen",
    "sg:phone":"+43 76187005",
    "sg:postcode":"4814",
    "sg:province":"Ober\u00f6sterreich",
    "wof:name":"Volksschule",
    "wof:placetype":"venue"
},
  "geometry": {"coordinates":[146.76252746579999,-19.2921791077],"type":"Point"}
}