{
  "type": "Feature",
  "properties": {
    "addr:full":"Feldkirchner Str 319 W\u00f6lfnitz K\u00e4rnten 9061",
    "addr:housenumber":"319",
    "addr:postcode":"9061",
    "addr:street":"Str;Kaernten",
    "iso:country":"AT",
    "sg:address":"Feldkirchner Str 319",
    "sg:city":"W\u00f6lfnitz",
    "sg:orig_category":"Autoreparatur",
    "sg:phone":"+43 463 49133",
    "sg:postcode":"9061",
    "sg:province":"K\u00e4rnten",
    "wof:name":"Huainig Georg Kfz-Reparatur und HandelsgesmbH",
    "wof:placetype":"venue"
},
  "geometry": {"coordinates":[14.2754106522,46.6588935852],"type":"Point"}
}