{
  "type": "Feature",
  "properties": {
    "addr:full":"Karl-Punzer-Str 42 Steyr Ober\u00f6sterreich 4400",
    "addr:housenumber":"42",
    "addr:postcode":"4400",
    "addr:street":"Karl-Punzer-Str;Oberoesterreich",
    "iso:country":"AT",
    "sg:address":"Karl-Punzer-Str 42",
    "sg:city":"Steyr",
    "sg:orig_category":"Banken U Sparkassen",
    "sg:phone":"+43 4372 5282474",
    "sg:postcode":"4400",
    "sg:province":"Ober\u00f6sterreich",
    "wof:name":"Raiffeisenbank St Ulrich-Steyr regGenmbH",
    "wof:placetype":"venue"
},
  "geometry": {"coordinates":[14.4411115646,48.0524368286],"type":"Point"}
}