{
  "type": "Feature",
  "properties": {
    "addr:full":"Linzenberg 25 Schwarzach Vorarlberg 6858",
    "addr:housenumber":"25",
    "addr:postcode":"6858",
    "addr:street":"Linzenberg",
    "iso:country":"AT",
    "sg:address":"Linzenberg 25",
    "sg:city":"Schwarzach",
    "sg:orig_category":"Isolierungen",
    "sg:phone":"+43 5572 386790",
    "sg:postcode":"6858",
    "sg:province":"Vorarlberg",
    "wof:name":"AS-Isolierungen GmbH - W\u00e4rme-, K\u00e4lte-, Blechisolierungen",
    "wof:placetype":"venue"
},
  "geometry": {"coordinates":[9.7657346725,47.4462509155],"type":"Point"}
}