{
  "type": "Feature",
  "properties": {
    "addr:full":"Nr 30a Gaschurn Vorarlberg 6793",
    "addr:postcode":"6793",
    "addr:street":"Nr 30A",
    "iso:country":"AT",
    "sg:address":"Nr 30a",
    "sg:city":"Gaschurn",
    "sg:orig_category":"Appartements / Ferienwohnungen",
    "sg:phone":"+43 5558 8392",
    "sg:postcode":"6793",
    "sg:province":"Vorarlberg",
    "wof:name":"Haus Tramontana",
    "wof:placetype":"venue"
},
  "geometry": {"coordinates":[10.0248842239,46.9886512756],"type":"Point"}
}