{
  "type": "Feature",
  "properties": {
    "addr:full":"Kaiserstr 41/2 Wien Wien 1070",
    "addr:housenumber":"41 / 2",
    "addr:postcode":"1070",
    "addr:street":"Kaiserstr",
    "iso:country":"AT",
    "sg:address":"Kaiserstr 41/2",
    "sg:city":"Wien",
    "sg:orig_category":"Filmproduktionen",
    "sg:phone":"+43 4315 240208",
    "sg:postcode":"1070",
    "sg:province":"Wien",
    "wof:name":"A & B Film u Video",
    "wof:placetype":"venue"
},
  "geometry": {"coordinates":[16.3404846191,48.2009086609],"type":"Point"}
}