{
  "type": "Feature",
  "properties": {
    "iso:country":"AT",
    "sg:address":"Nr 7",
    "sg:city":"Ruden",
    "sg:orig_category":"Metallbau",
    "sg:phone":"+43 4234 5069",
    "sg:postcode":"9113",
    "sg:province":"K\u00e4rnten",
    "wof:name":"Metallbau Natek GmbH",
    "wof:placetype":"venue"
},
  "geometry": {"coordinates":[14.7703266144,46.6569061279],"type":"Point"}
}