{
  "type": "Feature",
  "properties": {
    "iso:country":"AT",
    "sg:address":"Unterer Markt 167",
    "sg:city":"St. Gallen",
    "sg:orig_category":"Pensionen / Privatzimmer",
    "sg:phone":"+43 4336 32458",
    "sg:postcode":"8933",
    "sg:province":"Steiermark",
    "wof:name":"Peter Robert u Theresia",
    "wof:placetype":"venue"
},
  "geometry": {"coordinates":[14.6218385696,47.697052002],"type":"Point"}
}