{
  "type": "Feature",
  "properties": {
    "addr:full":"Rankeng 28 Graz Steiermark 8020",
    "addr:housenumber":"28",
    "addr:postcode":"8020",
    "addr:street":"Rankeng",
    "iso:country":"AT",
    "sg:address":"Rankeng 28",
    "sg:city":"Graz",
    "sg:orig_category":"Forschungsinstitute",
    "sg:phone":"+43 316 7651140",
    "sg:postcode":"8020",
    "sg:province":"Steiermark",
    "wof:name":"JSW-Research Forschungslabor GmbH",
    "wof:placetype":"venue"
},
  "geometry": {"coordinates":[15.4317789078,47.0609054565],"type":"Point"}
}