{
  "type": "Feature",
  "properties": {
    "addr:full":"Kindermanng 4a Graz Steiermark 8020",
    "addr:housenumber":"4a",
    "addr:postcode":"8020",
    "addr:street":"Kindermanng",
    "iso:country":"AT",
    "sg:address":"Kindermanng 4a",
    "sg:city":"Graz",
    "sg:orig_category":"Maler, Anstreicher U Lackierer",
    "sg:phone":"+43 4331 6721010",
    "sg:postcode":"8020",
    "sg:province":"Steiermark",
    "wof:name":"Malermeister Leber GmbH",
    "wof:placetype":"venue"
},
  "geometry": {"coordinates":[15.4249343872,47.0685157776],"type":"Point"}
}