{
  "type": "Feature",
  "properties": {
    "iso:country":"AT",
    "sg:address":"Landstr 40",
    "sg:city":"Zwettl",
    "sg:orig_category":"Glasereien",
    "sg:phone":"+43 2822 52397",
    "sg:postcode":"3910",
    "sg:province":"Nieder\u00f6sterreich",
    "wof:name":"Ertl Glasbau GesmbH",
    "wof:placetype":"venue"
},
  "geometry": {"coordinates":[15.1662120819,48.6054801941],"type":"Point"}
}