{
  "type": "Feature",
  "properties": {
    "addr:full":"Flachg 53 Wien Wien 1150",
    "addr:housenumber":"53",
    "addr:postcode":"1150",
    "addr:street":"Flachg",
    "iso:country":"AT",
    "sg:address":"Flachg 53",
    "sg:city":"Wien",
    "sg:orig_category":"Architekten",
    "sg:phone":"+43 4319 8230000",
    "sg:postcode":"1150",
    "sg:province":"Wien",
    "wof:name":"Wimmer Albert ZT - GmbH",
    "wof:placetype":"venue"
},
  "geometry": {"coordinates":[16.3150749207,48.1986923218],"type":"Point"}
}