{
  "type": "Feature",
  "properties": {
    "addr:full":"Hetzendorfer Str 43-45 Wien Wien 1120",
    "addr:postcode":"43-45;1120",
    "addr:street":"Str",
    "iso:country":"AT",
    "sg:address":"Hetzendorfer Str 43-45",
    "sg:city":"Wien",
    "sg:orig_category":"Autobusunternehmen",
    "sg:phone":"+43 1 8041653",
    "sg:postcode":"1120",
    "sg:province":"Wien",
    "wof:name":"PLETTER REISEN Verkehrsbetrieb + Reiseb\u00fcro GmbH",
    "wof:placetype":"venue"
},
  "geometry": {"coordinates":[16.315870285,48.1640663147],"type":"Point"}
}