{
  "type": "Feature",
  "properties": {
    "addr:full":"Hauptstr 69 F\u00fcgen Tirol 6263",
    "addr:housenumber":"69",
    "addr:postcode":"6263",
    "addr:street":"Hauptstr;Tirol",
    "iso:country":"AT",
    "sg:address":"Hauptstr 69",
    "sg:city":"F\u00fcgen",
    "sg:orig_category":"Fotografen",
    "sg:phone":"+43 4352 8862054",
    "sg:postcode":"6263",
    "sg:province":"Tirol",
    "wof:name":"Fotostudio Sandra",
    "wof:placetype":"venue"
},
  "geometry": {"coordinates":[11.8509092331,47.3445549011],"type":"Point"}
}