{
  "type": "Feature",
  "properties": {
    "iso:country":"AT",
    "sg:address":"Harmannsteiner Str 120",
    "sg:city":"Gro\u00dfsch\u00f6nau",
    "sg:orig_category":"Tourismusinformation U -Organisationen",
    "sg:phone":"+43 4328 1570030",
    "sg:postcode":"3922",
    "sg:province":"Nieder\u00f6sterreich",
    "wof:name":"Fremdenverkehrsverein",
    "wof:placetype":"venue"
},
  "geometry": {"coordinates":[-87.4639205933,33.9982299805],"type":"Point"}
}