{
  "type": "Feature",
  "properties": {
    "iso:country":"AT",
    "sg:address":"Brandling 5",
    "sg:city":"Unterrabnitz",
    "sg:orig_category":"Elektroinstallationsunternehmen",
    "sg:phone":"+43 2616 8990",
    "sg:postcode":"7371",
    "sg:province":"Burgenland",
    "wof:name":"Mandl Hannes",
    "wof:placetype":"venue"
},
  "geometry": {"coordinates":[16.4088726044,47.4484596252],"type":"Point"}
}