{
  "type": "Feature",
  "properties": {
    "addr:full":"Anton-\u00d6fner-Strasse 24 Schwaz Tirol 6130",
    "addr:housenumber":"24",
    "addr:postcode":"6130",
    "addr:street":"Anton-Oefner-Strasse;Tirol",
    "iso:country":"AT",
    "sg:address":"Anton-\u00d6fner-Strasse 24",
    "sg:city":"Schwaz",
    "sg:classifiers":[
        {
            "category":"Home & Garden",
            "subcategory":"Home Furnishings",
            "type":"Retail Goods"
        }
    ],
    "sg:phone":"+43 5242 63154",
    "sg:postcode":"6130",
    "sg:province":"Tirol",
    "sg:tags":[
        "air-conditioners"
    ],
    "wof:name":"Heribert Fermitsch",
    "wof:placetype":"venue"
},
  "geometry": {"coordinates":[11.7151098251,47.3545341492],"type":"Point"}
}