{
  "type": "Feature",
  "properties": {
    "addr:full":"Salzburger Str 19 Bruck an der Gro\u00dfglocknerstra\u00dfe Salzburg 5671",
    "addr:housenumber":"19",
    "addr:postcode":"5671",
    "addr:street":"Salzburger Str;Grossglocknerstrasse Salzburg",
    "iso:country":"AT",
    "sg:address":"Salzburger Str 19",
    "sg:city":"Bruck an der Gro\u00dfglocknerstra\u00dfe",
    "sg:orig_category":"Fenster",
    "sg:phone":"+43 4366 49825041",
    "sg:postcode":"5671",
    "sg:province":"Salzburg",
    "wof:name":"Bodner Josef",
    "wof:placetype":"venue"
},
  "geometry": {"coordinates":[12.8281164169,47.2863273621],"type":"Point"}
}