{
  "type": "Feature",
  "properties": {
    "addr:full":"H\u00f6rmannstr 11 Linz Ober\u00f6sterreich 4020",
    "addr:housenumber":"11",
    "addr:postcode":"4020",
    "addr:street":"Hoermannstr",
    "iso:country":"AT",
    "sg:address":"H\u00f6rmannstr 11",
    "sg:city":"Linz",
    "sg:orig_category":"Immobilienmakler",
    "sg:phone":"+43 732 604585",
    "sg:postcode":"4020",
    "sg:province":"Ober\u00f6sterreich",
    "wof:name":"Investbau - Immobilien GmbH",
    "wof:placetype":"venue"
},
  "geometry": {"coordinates":[14.286157608,48.2871322632],"type":"Point"}
}