{
  "type": "Feature",
  "properties": {
    "addr:full":"Josef-Joachim-Str 11 Eisenstadt Burgenland 7000",
    "addr:housenumber":"11",
    "addr:postcode":"7000",
    "addr:street":"Josef-Joachim-Str",
    "iso:country":"AT",
    "sg:address":"Josef-Joachim-Str 11",
    "sg:city":"Eisenstadt",
    "sg:orig_category":"Immobilienmakler",
    "sg:phone":"+43 2682 62986",
    "sg:postcode":"7000",
    "sg:province":"Burgenland",
    "wof:name":"Gerbl Hermann",
    "wof:placetype":"venue"
},
  "geometry": {"coordinates":[16.5223827362,47.8439903259],"type":"Point"}
}