{
  "type": "Feature",
  "properties": {
    "iso:country":"AT",
    "sg:address":"Niederau 278",
    "sg:city":"Wildsch\u00f6nau-Niederau",
    "sg:orig_category":"Autohandel",
    "sg:phone":"+43 4353 398592",
    "sg:postcode":"6314",
    "sg:province":"Tirol",
    "wof:name":"MOBILE - POINT KFZ Handels GmbH",
    "wof:placetype":"venue"
},
  "geometry": {"coordinates":[12.105055809,47.4490509033],"type":"Point"}
}