{
  "type": "Feature",
  "properties": {
    "addr:full":"Pointnersdlg 2 Waldneukirchen Ober\u00f6sterreich 4595",
    "addr:housenumber":"2",
    "addr:postcode":"4595",
    "addr:street":"Pointnersdlg",
    "iso:country":"AT",
    "sg:address":"Pointnersdlg 2",
    "sg:city":"Waldneukirchen",
    "sg:orig_category":"Registrierkassen",
    "sg:phone":"+43 7259 5185",
    "sg:postcode":"4595",
    "sg:province":"Ober\u00f6sterreich",
    "wof:name":"Bernecker Christian - Gastro Partner Team",
    "wof:placetype":"venue"
},
  "geometry": {"coordinates":[14.2929992676,48.0069656372],"type":"Point"}
}