{
  "type": "Feature",
  "properties": {
    "addr:full":"Haidbrunng 52 Wiener Neustadt Nieder\u00f6sterreich 2700",
    "addr:housenumber":"52",
    "addr:postcode":"2700",
    "addr:street":"Haidbrunng",
    "iso:country":"AT",
    "sg:address":"Haidbrunng 52",
    "sg:city":"Wiener Neustadt",
    "sg:orig_category":"Autobusunternehmen",
    "sg:phone":"+43 4326 2227420",
    "sg:postcode":"2700",
    "sg:province":"Nieder\u00f6sterreich",
    "wof:name":"Partsch M Erste Wr Neust\u00e4dter Autobusunternehmung VerkehrsbetriebsgesmbH",
    "wof:placetype":"venue"
},
  "geometry": {"coordinates":[16.2253055573,47.8013839722],"type":"Point"}
}