{
  "type": "Feature",
  "properties": {
    "addr:full":"Auleiten 20 Ried im Innkreis Ober\u00f6sterreich 4910",
    "addr:housenumber":"20",
    "addr:postcode":"4910",
    "addr:street":"Auleiten",
    "iso:country":"AT",
    "sg:address":"Auleiten 20",
    "sg:city":"Ried im Innkreis",
    "sg:orig_category":"Lebensmittel / Einzelhandel",
    "sg:phone":"+43 7752 82781",
    "sg:postcode":"4910",
    "sg:province":"Ober\u00f6sterreich",
    "wof:name":"Billa AG",
    "wof:placetype":"venue"
},
  "geometry": {"coordinates":[13.4987974167,48.1933403015],"type":"Point"}
}