{
  "type": "Feature",
  "properties": {
    "addr:full":"Welser Str 29 Gunskirchen Ober\u00f6sterreich 4623",
    "addr:postcode":"4623",
    "addr:street":"Str 29",
    "iso:country":"AT",
    "sg:address":"Welser Str 29",
    "sg:city":"Gunskirchen",
    "sg:orig_category":"Stiegen U Treppen",
    "sg:phone":"+43 7246 6278",
    "sg:postcode":"4623",
    "sg:province":"Ober\u00f6sterreich",
    "wof:name":"Pfeffer Johann",
    "wof:placetype":"venue"
},
  "geometry": {"coordinates":[13.9476547241,48.1362991333],"type":"Point"}
}