{
  "type": "Feature",
  "properties": {
    "addr:full":"Kircheng 1 Mondsee Ober\u00f6sterreich 5310",
    "addr:housenumber":"1",
    "addr:postcode":"5310",
    "addr:street":"Kircheng;Oberoesterreich",
    "iso:country":"AT",
    "sg:address":"Kircheng 1",
    "sg:city":"Mondsee",
    "sg:orig_category":"Non-Classified Establishments",
    "sg:phone":"+43 6232 41660",
    "sg:postcode":"5310",
    "sg:province":"Ober\u00f6sterreich",
    "wof:name":"Pfarramt",
    "wof:placetype":"venue"
},
  "geometry": {"coordinates":[13.349562645,47.855255127],"type":"Point"}
}