{
  "type": "Feature",
  "properties": {
    "addr:full":"Nr 51a Gries am Brenner Tirol 6156",
    "addr:housenumber":"51a",
    "addr:postcode":"6156",
    "addr:street":"Nr;Tirol",
    "iso:country":"AT",
    "sg:address":"Nr 51a",
    "sg:city":"Gries am Brenner",
    "sg:orig_category":"Appartements / Ferienwohnungen",
    "sg:phone":"+43 5274 86130",
    "sg:postcode":"6156",
    "sg:province":"Tirol",
    "wof:name":"Ferienhaus Padrins",
    "wof:placetype":"venue"
},
  "geometry": {"coordinates":[11.4193086624,47.0162277222],"type":"Point"}
}