{
  "type": "Feature",
  "properties": {
    "addr:full":"Nr 156 Loipersdorf Steiermark 8282",
    "addr:postcode":"8282",
    "addr:street":"Nr",
    "iso:country":"AT",
    "sg:address":"Nr 156",
    "sg:city":"Loipersdorf",
    "sg:classifiers":[
        {
            "category":"Travel",
            "subcategory":"Hotels & Motels",
            "type":"Entertainment"
        }
    ],
    "sg:phone":"+43 3382 84800",
    "sg:postcode":"8282",
    "sg:province":"Steiermark",
    "wof:name":"Die Herberge",
    "wof:placetype":"venue"
},
  "geometry": {"coordinates":[16.1014671326,47.0128898621],"type":"Point"}
}