{
  "type": "Feature",
  "properties": {
    "addr:full":"Moritschstr 3 Villach K\u00e4rnten 9500",
    "addr:housenumber":"3",
    "addr:postcode":"9500",
    "addr:street":"Moritschstr;Kaernten",
    "iso:country":"AT",
    "sg:address":"Moritschstr 3",
    "sg:city":"Villach",
    "sg:orig_category":"Damenmoden",
    "sg:phone":"+43 4242 26856",
    "sg:postcode":"9500",
    "sg:province":"K\u00e4rnten",
    "wof:name":"De Pretis Moden",
    "wof:placetype":"venue"
},
  "geometry": {"coordinates":[13.8468360901,46.612361908],"type":"Point"}
}