{
  "type": "Feature",
  "properties": {
    "addr:full":"Schieflinger Strasse 32 Schiefling am See K\u00e4rnten 9535",
    "addr:housenumber":"32",
    "addr:postcode":"9535",
    "addr:street":"Schieflinger Strasse",
    "iso:country":"AT",
    "sg:address":"Schieflinger Strasse 32",
    "sg:city":"Schiefling am See",
    "sg:classifiers":[
        {
            "category":"Military Area",
            "subcategory":"Air Force Base",
            "type":"Public Place"
        }
    ],
    "sg:phone":"+43 4274 4347",
    "sg:postcode":"9535",
    "sg:province":"K\u00e4rnten",
    "sg:tags":[
        "assembly",
        "furniture"
    ],
    "wof:name":"Bau- u. M\u00f6beltischlerei Moswitzer",
    "wof:placetype":"venue"
},
  "geometry": {"coordinates":[14.0854177475,46.6082267761],"type":"Point"}
}