{
  "type": "Feature",
  "properties": {
    "iso:country":"AT",
    "sg:address":"Salzburger Str 70",
    "sg:city":"Bad Hofgastein",
    "sg:orig_category":"Flugschulen",
    "sg:phone":"+43 4366 44232322",
    "sg:postcode":"5630",
    "sg:province":"Salzburg",
    "wof:name":"Para-Taxi Gastein Lois Grugger",
    "wof:placetype":"venue"
},
  "geometry": {"coordinates":[13.1020784378,47.1807250977],"type":"Point"}
}