{
  "type": "Feature",
  "properties": {
    "addr:full":"Seeburgstr 8 Seekirchen am Wallersee Salzburg 5201",
    "addr:housenumber":"8",
    "addr:postcode":"5201",
    "addr:street":"Seeburgstr;Salzburg",
    "iso:country":"AT",
    "sg:address":"Seeburgstr 8",
    "sg:city":"Seekirchen am Wallersee",
    "sg:orig_category":"Tourismusinformation U -Organisationen",
    "sg:phone":"+43 4362 1230370",
    "sg:postcode":"5201",
    "sg:province":"Salzburg",
    "sg:website":"salzburger-seenland.at",
    "wof:name":"Salzburger Seenland Tourismus GmbH",
    "wof:placetype":"venue"
},
  "geometry": {"coordinates":[13.1362743378,47.9028663635],"type":"Point"}
}