{
  "type": "Feature",
  "properties": {
    "addr:full":"Niederland 174 Unken Salzburg 5091",
    "addr:housenumber":"174",
    "addr:postcode":"5091",
    "addr:street":"Niederland;Salzburg",
    "iso:country":"AT",
    "sg:address":"Niederland 174",
    "sg:city":"Unken",
    "sg:classifiers":[
        {
            "category":"Restaurant",
            "type":"Food & Drink"
        }
    ],
    "sg:phone":"+43 6589 42980",
    "sg:postcode":"5091",
    "sg:province":"Salzburg",
    "wof:name":"Cafe-Restaurant-Pension An der Josefsallee",
    "wof:placetype":"venue"
},
  "geometry": {"coordinates":[12.7301282883,47.6490058899],"type":"Point"}
}