{
  "type": "Feature",
  "properties": {
    "addr:full":"Br\u00fcnner Strasse 28 Gerasdorf Nieder\u00f6sterreich 2201",
    "addr:housenumber":"28",
    "addr:postcode":"2201",
    "addr:street":"Bruenner Strasse",
    "iso:country":"AT",
    "sg:address":"Br\u00fcnner Strasse 28",
    "sg:city":"Gerasdorf",
    "sg:classifiers":[
        {
            "category":"Structure",
            "subcategory":"Tunnel",
            "type":"Public Place"
        }
    ],
    "sg:phone":"+43 2246 27888",
    "sg:postcode":"2201",
    "sg:province":"Nieder\u00f6sterreich",
    "sg:tags":[
        "aluminium",
        "fence"
    ],
    "sg:website":"falken.at",
    "wof:name":"Falken-Tore/Z\u00e4une",
    "wof:placetype":"venue"
},
  "geometry": {"coordinates":[16.4562244415,48.3326835632],"type":"Point"}
}