{
  "type": "Feature",
  "properties": {
    "iso:country":"AT",
    "sg:address":"Grazer Str 60",
    "sg:city":"Fernitz",
    "sg:orig_category":"Immobilienverwaltungen",
    "sg:phone":"+43 3135 55055",
    "sg:postcode":"8072",
    "sg:province":"Steiermark",
    "wof:name":"H\u00f6ller Evelin",
    "wof:placetype":"venue"
},
  "geometry": {"coordinates":[15.4965934753,46.9777526855],"type":"Point"}
}