{
  "type": "Feature",
  "properties": {
    "iso:country":"AT",
    "sg:address":"Rathauspl 54",
    "sg:city":"Weitra",
    "sg:orig_category":"Bestattungsunternehmen",
    "sg:phone":"+43 2856 2333",
    "sg:postcode":"3970",
    "sg:province":"Nieder\u00f6sterreich",
    "wof:name":"Fischer I & J Fischer OEG",
    "wof:placetype":"venue"
},
  "geometry": {"coordinates":[14.8923530579,48.7008590698],"type":"Point"}
}