{
  "type": "Feature",
  "properties": {
    "addr:full":"Stadionstr 6 Wiener Neustadt Nieder\u00f6sterreich 2700",
    "addr:housenumber":"6",
    "addr:postcode":"2700",
    "addr:street":"Stadionstr",
    "iso:country":"AT",
    "sg:address":"Stadionstr 6",
    "sg:city":"Wiener Neustadt",
    "sg:orig_category":"Tankstellen",
    "sg:phone":"+43 2622 24533",
    "sg:postcode":"2700",
    "sg:province":"Nieder\u00f6sterreich",
    "wof:name":"Agip Austria GmbH",
    "wof:placetype":"venue"
},
  "geometry": {"coordinates":[16.2565803528,47.8231124878],"type":"Point"}
}