{
  "type": "Feature",
  "properties": {
    "iso:country":"AT",
    "sg:address":"Franz Strickner-Str 2",
    "sg:city":"Wattens",
    "sg:orig_category":"Banken U Sparkassen",
    "sg:phone":"+43 5224 58330",
    "sg:postcode":"6112",
    "sg:province":"Tirol",
    "wof:name":"Raiffeisenbank Wattens und Umgebung regGenmbH",
    "wof:placetype":"venue"
},
  "geometry": {"coordinates":[11.591337204,47.2916374207],"type":"Point"}
}