{
  "type": "Feature",
  "properties": {
    "addr:full":"Nr 11 Sinabelkirchen Steiermark 8261",
    "addr:postcode":"8261",
    "addr:street":"Nr",
    "iso:country":"AT",
    "sg:address":"Nr 11",
    "sg:city":"Sinabelkirchen",
    "sg:orig_category":"Bauunternehmen",
    "sg:phone":"+43 3118 22880",
    "sg:postcode":"8261",
    "sg:province":"Steiermark",
    "wof:name":"Wilfling Johann Bau GmbH & Co KG",
    "wof:placetype":"venue"
},
  "geometry": {"coordinates":[15.8282032013,47.1025505066],"type":"Point"}
}