{
  "type": "Feature",
  "properties": {
    "addr:full":"Rainerstr 21 Kieselpassage Top 22a Salzburg Salzburg 5020",
    "addr:housenumber":"21;22a",
    "addr:postcode":"5020",
    "addr:street":"Rainerstr;Top;Salzburg",
    "iso:country":"AT",
    "sg:address":"Rainerstr 21 Kieselpassage Top 22a",
    "sg:city":"Salzburg",
    "sg:orig_category":"Waren Aller Art",
    "sg:phone":"+43 4366 2878029",
    "sg:postcode":"5020",
    "sg:province":"Salzburg",
    "wof:name":"Knall auf Fall - Aktionsshop",
    "wof:placetype":"venue"
},
  "geometry": {"coordinates":[13.0433769226,47.8006744385],"type":"Point"}
}