{
  "type": "Feature",
  "properties": {
    "iso:country":"AT",
    "sg:address":"Kautscheleweg 13",
    "sg:city":"Klagenfurt",
    "sg:classifiers":[
        {
            "category":"Shopping",
            "subcategory":"Computers & Home Electronics",
            "type":"Retail Goods"
        }
    ],
    "sg:phone":"+43 4346 345107",
    "sg:postcode":"9020",
    "sg:province":"K\u00e4rnten",
    "sg:tags":[
        "electronic",
        "electrical",
        "equipment"
    ],
    "wof:name":"OTTO KOHLA",
    "wof:placetype":"venue"
},
  "geometry": {"coordinates":[14.2977895737,46.6498146057],"type":"Point"}
}