{
  "type": "Feature",
  "properties": {
    "addr:full":"Nr 8 Asparn an der Zaya Nieder\u00f6sterreich 2151",
    "addr:postcode":"2151",
    "addr:street":"Nr",
    "iso:country":"AT",
    "sg:address":"Nr 8",
    "sg:city":"Asparn an der Zaya",
    "sg:orig_category":"Museen / Ausstellungen",
    "sg:phone":"+43 2525 64037",
    "sg:postcode":"2151",
    "sg:province":"Nieder\u00f6sterreich",
    "wof:name":"Nieder\u00f6sterreichisches Schulmuseum",
    "wof:placetype":"venue"
},
  "geometry": {"coordinates":[16.4961643219,48.5871963501],"type":"Point"}
}