{
  "type": "Feature",
  "properties": {
    "addr:full":"Kleine Sperlg 1 Wien Wien 1020",
    "addr:housenumber":"1",
    "addr:postcode":"1020",
    "iso:country":"AT",
    "sg:address":"Kleine Sperlg 1",
    "sg:city":"Wien",
    "sg:orig_category":"Immobilienverwaltungen",
    "sg:phone":"+43 1 211362639",
    "sg:postcode":"1020",
    "sg:province":"Wien",
    "wof:name":"Dianazentrum Realit\u00e4tengesmbH",
    "wof:placetype":"venue"
},
  "geometry": {"coordinates":[16.3777942657,48.2162094116],"type":"Point"}
}