{
  "type": "Feature",
  "properties": {
    "addr:full":"Carl-Spaeter-Str 109 Dorf Veitsch Steiermark 8663",
    "addr:housenumber":"109",
    "addr:postcode":"8663",
    "addr:street":"Dorf",
    "iso:country":"AT",
    "sg:address":"Carl-Spaeter-Str 109",
    "sg:city":"Dorf Veitsch",
    "sg:orig_category":"Fleischhauereien",
    "sg:phone":"+43 4338 5661060",
    "sg:postcode":"8663",
    "sg:province":"Steiermark",
    "wof:name":"Leitner KG",
    "wof:placetype":"venue"
},
  "geometry": {"coordinates":[15.4928483963,47.5800666809],"type":"Point"}
}