{
  "type": "Feature",
  "properties": {
    "addr:full":"Pater-Bernhard-Rodlberger-Str 59 Wels Ober\u00f6sterreich 4600",
    "addr:housenumber":"59",
    "addr:postcode":"4600",
    "addr:street":"Pater-Bernhard-Rodlberger-Str;Oberoesterreich",
    "iso:country":"AT",
    "sg:address":"Pater-Bernhard-Rodlberger-Str 59",
    "sg:city":"Wels",
    "sg:orig_category":"Beschriftungen",
    "sg:phone":"+43 4372 42677300",
    "sg:postcode":"4600",
    "sg:province":"Ober\u00f6sterreich",
    "wof:name":"DOT-Printer GmbH",
    "wof:placetype":"venue"
},
  "geometry": {"coordinates":[14.0432338715,48.1516723633],"type":"Point"}
}