{
  "type": "Feature",
  "properties": {
    "iso:country":"AT",
    "sg:address":"Franz Wernhart-Str 5",
    "sg:city":"Laab im Walde",
    "sg:orig_category":"Tiefbau",
    "sg:phone":"+43 2239 6084",
    "sg:postcode":"2381",
    "sg:province":"Nieder\u00f6sterreich",
    "wof:name":"SOLETANCHE Spezialtiefbau GesmbH",
    "wof:placetype":"venue"
},
  "geometry": {"coordinates":[16.1821784973,48.1558494568],"type":"Point"}
}