{
  "type": "Feature",
  "properties": {
    "iso:country":"AT",
    "sg:address":"F\u00e4rberg 45",
    "sg:city":"St. Johann im Pongau",
    "sg:orig_category":"Billardcafes",
    "sg:phone":"+43 6412 7795",
    "sg:postcode":"5600",
    "sg:province":"Salzburg",
    "wof:name":"Billard-Pub Ballazo",
    "wof:placetype":"venue"
},
  "geometry": {"coordinates":[13.2019701004,47.3485641479],"type":"Point"}
}