{
  "type": "Feature",
  "properties": {
    "addr:full":"Steinackerstr 4 Lustenau Vorarlberg 6890",
    "addr:housenumber":"4",
    "addr:postcode":"6890",
    "addr:street":"Steinackerstr",
    "iso:country":"AT",
    "sg:address":"Steinackerstr 4",
    "sg:city":"Lustenau",
    "sg:orig_category":"Friseure U Frisiersalons",
    "sg:phone":"+43 4355 7783825",
    "sg:postcode":"6890",
    "sg:province":"Vorarlberg",
    "wof:name":"Loitzberger Gerd",
    "wof:placetype":"venue"
},
  "geometry": {"coordinates":[9.658780098,47.4324188232],"type":"Point"}
}