{
  "type": "Feature",
  "properties": {
    "iso:country":"AT",
    "sg:address":"Leopoldsdorfer Str 1",
    "sg:city":"Maria Lanzendorf",
    "sg:orig_category":"Tabaktrafiken",
    "sg:phone":"+43 2235 42503",
    "sg:postcode":"2326",
    "sg:province":"Nieder\u00f6sterreich",
    "wof:name":"Trinkl Peter",
    "wof:placetype":"venue"
},
  "geometry": {"coordinates":[16.4173908234,48.0987358093],"type":"Point"}
}