{
  "type": "Feature",
  "properties": {
    "addr:full":"Hauptstr 142 Krumpendorf K\u00e4rnten 9201",
    "addr:housenumber":"142",
    "addr:postcode":"9201",
    "addr:street":"Hauptstr;Kaernten",
    "iso:country":"AT",
    "sg:address":"Hauptstr 142",
    "sg:city":"Krumpendorf",
    "sg:classifiers":[
        {
            "category":"Restaurant",
            "type":"Food & Drink"
        }
    ],
    "sg:phone":"+43 4229 39700",
    "sg:postcode":"9201",
    "sg:province":"K\u00e4rnten",
    "wof:name":"St Petersburg Restaurant-Variete",
    "wof:placetype":"venue"
},
  "geometry": {"coordinates":[14.2145185471,46.6265449524],"type":"Point"}
}