{
  "type": "Feature",
  "properties": {
    "iso:country":"AT",
    "sg:address":"Felseng 3",
    "sg:city":"Neustadtl",
    "sg:orig_category":"Bildhauer",
    "sg:phone":"+43 7471 2562",
    "sg:postcode":"3323",
    "sg:province":"Nieder\u00f6sterreich",
    "wof:name":"B\u00fchringer Johann",
    "wof:placetype":"venue"
},
  "geometry": {"coordinates":[20.3330097198,47.9864997864],"type":"Point"}
}