{
  "type": "Feature",
  "properties": {
    "addr:full":"Hauptstr 39 Pinkafeld Burgenland 7423",
    "addr:housenumber":"39",
    "addr:postcode":"7423",
    "addr:street":"Hauptstr",
    "iso:country":"AT",
    "sg:address":"Hauptstr 39",
    "sg:city":"Pinkafeld",
    "sg:orig_category":"Papier- U Schreibwaren / Einzelhandel",
    "sg:phone":"+43 3357 462010",
    "sg:postcode":"7423",
    "sg:province":"Burgenland",
    "wof:name":"Desch-Drexler",
    "wof:placetype":"venue"
},
  "geometry": {"coordinates":[16.1236286163,47.3677902222],"type":"Point"}
}