{
  "type": "Feature",
  "properties": {
    "addr:full":"Keplerstr 2 Linz Ober\u00f6sterreich 4040",
    "addr:housenumber":"2",
    "addr:postcode":"4040",
    "addr:street":"Keplerstr",
    "iso:country":"AT",
    "sg:address":"Keplerstr 2",
    "sg:city":"Linz",
    "sg:orig_category":"Fahrschulen",
    "sg:phone":"+43 732 718017",
    "sg:postcode":"4040",
    "sg:province":"Ober\u00f6sterreich",
    "wof:name":"Fahrschule Stoiber",
    "wof:placetype":"venue"
},
  "geometry": {"coordinates":[14.283700943,48.3272590637],"type":"Point"}
}