{
  "type": "Feature",
  "properties": {
    "addr:full":"Hetmanekg 9 Wien Wien 1230",
    "addr:housenumber":"9",
    "addr:postcode":"1230",
    "addr:street":"Hetmanekg",
    "iso:country":"AT",
    "sg:address":"Hetmanekg 9",
    "sg:city":"Wien",
    "sg:orig_category":"\u00c3\u201erzte- U Spitalsbedarf",
    "sg:phone":"+43 4366 44424728",
    "sg:postcode":"1230",
    "sg:province":"Wien",
    "wof:name":"FIAL medica med Einrichtungen Planungs- u Ausstattungs GmbH",
    "wof:placetype":"venue"
},
  "geometry": {"coordinates":[16.3164310455,48.1346626282],"type":"Point"}
}