{
  "type": "Feature",
  "properties": {
    "iso:country":"AT",
    "sg:address":"Salzburger Str 293",
    "sg:city":"Linz",
    "sg:orig_category":"Botendienste",
    "sg:phone":"+43 4366 43821795",
    "sg:postcode":"4030",
    "sg:province":"Ober\u00f6sterreich",
    "wof:name":"Schnell Paket Service Darius Tokarz",
    "wof:placetype":"venue"
},
  "geometry": {"coordinates":[14.2772188187,48.2520446777],"type":"Point"}
}