{
  "type": "Feature",
  "properties": {
    "iso:country":"AT",
    "sg:address":"Speckbacherstr 23",
    "sg:city":"St. Johann in Tirol",
    "sg:classifiers":[
        {
            "category":"Travel",
            "subcategory":"Hotels & Motels",
            "type":"Entertainment"
        }
    ],
    "sg:phone":"+43 5352 622510",
    "sg:postcode":"6380",
    "sg:province":"Tirol",
    "wof:name":"Domina Vacanze GmbH Hotel Goldener L\u00f6we",
    "wof:placetype":"venue"
},
  "geometry": {"coordinates":[12.4266662598,47.52085495],"type":"Point"}
}