{
  "type": "Feature",
  "properties": {
    "addr:full":"Brucknerstrasse 24 Linz Ober\u00f6sterreich 4020",
    "addr:housenumber":"24",
    "addr:postcode":"4020",
    "addr:street":"Brucknerstrasse",
    "iso:country":"AT",
    "sg:address":"Brucknerstrasse 24",
    "sg:city":"Linz",
    "sg:classifiers":[
        {
            "category":"Home & Garden",
            "subcategory":"Garden Supply",
            "type":"Retail Goods"
        }
    ],
    "sg:phone":"+43 732 6553100",
    "sg:postcode":"4020",
    "sg:province":"Ober\u00f6sterreich",
    "sg:tags":[
        "aerator"
    ],
    "wof:name":"Ing. G\u00fcnter Boyer techn. B\u00fcro",
    "wof:placetype":"venue"
},
  "geometry": {"coordinates":[14.2958106995,48.2865982056],"type":"Point"}
}