{
  "type": "Feature",
  "properties": {
    "iso:country":"AT",
    "sg:address":"Rosenweg 10",
    "sg:city":"Schwarzach",
    "sg:orig_category":"Juweliere, Gold- U Silberschmiede",
    "sg:phone":"+43 4355 7241452",
    "sg:postcode":"6858",
    "sg:province":"Vorarlberg",
    "wof:name":"art of b Stahlschmuckherstellung",
    "wof:placetype":"venue"
},
  "geometry": {"coordinates":[9.7646102905,47.443031311],"type":"Point"}
}