{
  "type": "Feature",
  "properties": {
    "addr:full":"Trewaldstr 37 Ybbs an der Donau Nieder\u00f6sterreich 3370",
    "addr:housenumber":"37",
    "addr:postcode":"3370",
    "addr:street":"Trewaldstr",
    "iso:country":"AT",
    "sg:address":"Trewaldstr 37",
    "sg:city":"Ybbs an der Donau",
    "sg:orig_category":"Blumenbinder",
    "sg:phone":"+43 7412 523170",
    "sg:postcode":"3370",
    "sg:province":"Nieder\u00f6sterreich",
    "wof:name":"Korner Anton",
    "wof:placetype":"venue"
},
  "geometry": {"coordinates":[15.0770320892,48.1735458374],"type":"Point"}
}