{
  "type": "Feature",
  "properties": {
    "addr:full":"Arnbach 75 Sillian Tirol 9920",
    "addr:housenumber":"75",
    "addr:postcode":"9920",
    "addr:street":"Arnbach;Tirol",
    "iso:country":"AT",
    "sg:address":"Arnbach 75",
    "sg:city":"Sillian",
    "sg:orig_category":"Tankstellen",
    "sg:phone":"+43 4842 6343",
    "sg:postcode":"9920",
    "sg:province":"Tirol",
    "wof:name":"OMV AG",
    "wof:placetype":"venue"
},
  "geometry": {"coordinates":[12.3908557892,46.7448654175],"type":"Point"}
}