{
  "type": "Feature",
  "properties": {
    "addr:full":"Spinnereistr 3/7/71 Linz Ober\u00f6sterreich 4030",
    "addr:housenumber":"3 / 7 / 71",
    "addr:postcode":"4030",
    "addr:street":"Spinnereistr",
    "iso:country":"AT",
    "sg:address":"Spinnereistr 3/7/71",
    "sg:city":"Linz",
    "sg:orig_category":"Online-Service",
    "sg:phone":"+43 4366 06515295",
    "sg:postcode":"4030",
    "sg:province":"Ober\u00f6sterreich",
    "wof:name":"Buch und Spiel Onlinshop",
    "wof:placetype":"venue"
},
  "geometry": {"coordinates":[14.3069601059,48.2325248718],"type":"Point"}
}