{
  "type": "Feature",
  "properties": {
    "iso:country":"AT",
    "sg:address":"Holz\u00f6ster 23",
    "sg:city":"Franking",
    "sg:orig_category":"Furniture, General",
    "sg:phone":"+43 6277 8122",
    "sg:postcode":"5131",
    "sg:province":"Ober\u00f6sterreich",
    "wof:name":"Martin Huber Fenster-, Bau- und M\u00f6beltischlerei GmbH",
    "wof:placetype":"venue"
},
  "geometry": {"coordinates":[12.9114017487,48.0522384644],"type":"Point"}
}