{
  "type": "Feature",
  "properties": {
    "addr:full":"Kaing 45 Wien Wien 1210",
    "addr:housenumber":"45",
    "addr:postcode":"1210",
    "addr:street":"Kaing",
    "iso:country":"AT",
    "sg:address":"Kaing 45",
    "sg:city":"Wien",
    "sg:orig_category":"Steuerberatung",
    "sg:phone":"+43 1 29215640",
    "sg:postcode":"1210",
    "sg:province":"Wien",
    "wof:name":"Allconsult Wirtschaftstreuhand GesmbH",
    "wof:placetype":"venue"
},
  "geometry": {"coordinates":[16.3797855377,48.2982292175],"type":"Point"}
}