{
  "type": "Feature",
  "properties": {
    "addr:full":"Nr 60 Weilbach Ober\u00f6sterreich 4984",
    "addr:postcode":"4984",
    "addr:street":"Nr;Oberoesterreich",
    "iso:country":"AT",
    "sg:address":"Nr 60",
    "sg:city":"Weilbach",
    "sg:orig_category":"Holzbe U -Verarbeitung",
    "sg:phone":"+43 4377 576788",
    "sg:postcode":"4984",
    "sg:province":"Ober\u00f6sterreich",
    "wof:name":"Forstunternehmung Streif Anton jun",
    "wof:placetype":"venue"
},
  "geometry": {"coordinates":[13.3731956482,48.2770767212],"type":"Point"}
}