{
  "type": "Feature",
  "properties": {
    "addr:full":"Atterseestr 49 Lenzing Ober\u00f6sterreich 4860",
    "addr:housenumber":"49",
    "addr:postcode":"4860",
    "addr:street":"Atterseestr",
    "iso:country":"AT",
    "sg:address":"Atterseestr 49",
    "sg:city":"Lenzing",
    "sg:orig_category":"Friseure U Frisiersalons",
    "sg:phone":"+43 4376 7296770",
    "sg:postcode":"4860",
    "sg:province":"Ober\u00f6sterreich",
    "wof:name":"Frisiersalon Roswitha Haas - Frisiersalon GesmbH",
    "wof:placetype":"venue"
},
  "geometry": {"coordinates":[13.6102657318,47.9758834839],"type":"Point"}
}