{
  "type": "Feature",
  "properties": {
    "addr:full":"Hintzerstr 6 Wien Wien 1030",
    "addr:housenumber":"6",
    "addr:postcode":"1030",
    "addr:street":"Hintzerstr",
    "iso:country":"AT",
    "sg:address":"Hintzerstr 6",
    "sg:city":"Wien",
    "sg:orig_category":"Tauschvermittler",
    "sg:phone":"+43 1 7148480",
    "sg:postcode":"1030",
    "sg:province":"Wien",
    "wof:name":"Tauschboutique Brunner Christine",
    "wof:placetype":"venue"
},
  "geometry": {"coordinates":[16.3919029236,48.200428009],"type":"Point"}
}