{
  "type": "Feature",
  "properties": {
    "addr:full":"Emichg Wien Wien 1220",
    "addr:postcode":"1220",
    "iso:country":"AT",
    "sg:address":"Emichg",
    "sg:city":"Wien",
    "sg:orig_category":"Sportanlagen",
    "sg:phone":"+43 1 2826372",
    "sg:postcode":"1220",
    "sg:province":"Wien",
    "wof:name":"Kinder- und Jugendsportanlage",
    "wof:placetype":"venue"
},
  "geometry": {"coordinates":[16.4721355438,48.2349891663],"type":"Point"}
}