{
  "type": "Feature",
  "properties": {
    "addr:full":"Europastr 11 Kirchbichl Tirol 6322",
    "addr:housenumber":"11",
    "addr:postcode":"6322",
    "addr:street":"Europastr;Tirol",
    "iso:country":"AT",
    "sg:address":"Europastr 11",
    "sg:city":"Kirchbichl",
    "sg:orig_category":"Autohandel",
    "sg:phone":"+43 5332 70176",
    "sg:postcode":"6322",
    "sg:province":"Tirol",
    "wof:name":"Mercedes-Benz Retterwerk AG",
    "wof:placetype":"venue"
},
  "geometry": {"coordinates":[12.0783576965,47.4982414246],"type":"Point"}
}