{
  "type": "Feature",
  "properties": {
    "iso:country":"AT",
    "sg:address":"Weidmanng 17",
    "sg:city":"Wien",
    "sg:orig_category":"Elektroinstallationsunternehmen",
    "sg:phone":"+43 4314 0379350",
    "sg:postcode":"1170",
    "sg:province":"Wien",
    "wof:name":"Elag Elektrotechn Licht- u Anlagenbau-GesmbH",
    "wof:placetype":"venue"
},
  "geometry": {"coordinates":[16.3327102661,48.2215652466],"type":"Point"}
}