{
  "type": "Feature",
  "properties": {
    "addr:full":"Millst\u00e4tter Strasse 82 Feld am See K\u00e4rnten 9544",
    "addr:housenumber":"82",
    "addr:postcode":"9544",
    "addr:street":"Millstaetter Strasse;Kaernten",
    "iso:country":"AT",
    "sg:address":"Millst\u00e4tter Strasse 82",
    "sg:city":"Feld am See",
    "sg:classifiers":[
        {
            "category":"Communications",
            "subcategory":"Television Station",
            "type":"Services"
        }
    ],
    "sg:phone":"+43 4246 39590",
    "sg:postcode":"9544",
    "sg:province":"K\u00e4rnten",
    "sg:tags":[
        "broadcast",
        "antenna"
    ],
    "wof:name":"Elektro-Tisch GmbH",
    "wof:placetype":"venue"
},
  "geometry": {"coordinates":[13.7399091721,46.7815475464],"type":"Point"}
}