{
  "type": "Feature",
  "properties": {
    "addr:full":"Marktpl 13 Aigen im M\u00fchlkreis Ober\u00f6sterreich 4160",
    "addr:housenumber":"13",
    "addr:postcode":"4160",
    "addr:street":"Marktpl",
    "iso:country":"AT",
    "sg:address":"Marktpl 13",
    "sg:city":"Aigen im M\u00fchlkreis",
    "sg:orig_category":"Fleischhauereien",
    "sg:phone":"+43 4372 816204",
    "sg:postcode":"4160",
    "sg:province":"Ober\u00f6sterreich",
    "wof:name":"Bitter Rudolf",
    "wof:placetype":"venue"
},
  "geometry": {"coordinates":[13.9712705612,48.6465492249],"type":"Point"}
}