{
  "type": "Feature",
  "properties": {
    "addr:full":"Rotenturmstr 11 Wien Wien 1010",
    "addr:housenumber":"11",
    "addr:postcode":"1010",
    "addr:street":"Rotenturmstr",
    "iso:country":"AT",
    "sg:address":"Rotenturmstr 11",
    "sg:city":"Wien",
    "sg:orig_category":"Optiker",
    "sg:phone":"+43 1 5334584",
    "sg:postcode":"1010",
    "sg:province":"Wien",
    "sg:website":"schau-schau.at",
    "wof:name":"Schau-Schau Brillen Inh Peter Kozich",
    "wof:placetype":"venue"
},
  "geometry": {"coordinates":[16.3732624054,48.2096138],"type":"Point"}
}