{
  "type": "Feature",
  "properties": {
    "addr:full":"Burggasse 117 Wien Wien 1070",
    "addr:housenumber":"117",
    "addr:postcode":"1070",
    "addr:street":"Burggasse",
    "iso:country":"AT",
    "sg:address":"Burggasse 117",
    "sg:city":"Wien",
    "sg:classifiers":[
        {
            "category":"Home & Garden",
            "subcategory":"Carpets & Floor Coverings",
            "type":"Retail Goods"
        }
    ],
    "sg:phone":"+43 1 5237382",
    "sg:postcode":"1070",
    "sg:province":"Wien",
    "sg:tags":[
        "supraregional",
        "flooring"
    ],
    "sg:website":"hofer-parkett.at",
    "wof:name":"Hofer Parkett Handels GmbH",
    "wof:placetype":"venue"
},
  "geometry": {"coordinates":[16.339017868,48.2041969299],"type":"Point"}
}