{
  "type": "Feature",
  "properties": {
    "addr:full":"Nr 24 Lofer Salzburg 5090",
    "addr:postcode":"5090",
    "addr:street":"Nr;Lofer",
    "iso:country":"AT",
    "sg:address":"Nr 24",
    "sg:city":"Lofer",
    "sg:orig_category":"Banken U Sparkassen",
    "sg:phone":"+43 5 010041010",
    "sg:postcode":"5090",
    "sg:province":"Salzburg",
    "wof:name":"Salzburger Sparkasse Bank AG",
    "wof:placetype":"venue"
},
  "geometry": {"coordinates":[12.6930541992,47.5873069763],"type":"Point"}
}