{
  "type": "Feature",
  "properties": {
    "addr:full":"Neuer Markt 2 Senftenberg Nieder\u00f6sterreich 3541",
    "addr:housenumber":"2",
    "addr:postcode":"3541",
    "addr:street":"Neuer Markt",
    "iso:country":"AT",
    "sg:address":"Neuer Markt 2",
    "sg:city":"Senftenberg",
    "sg:orig_category":"Banken U Sparkassen",
    "sg:phone":"+43 2719 22450",
    "sg:postcode":"3541",
    "sg:province":"Nieder\u00f6sterreich",
    "wof:name":"Raiffeisenbank Krems regGenmbH",
    "wof:placetype":"venue"
},
  "geometry": {"coordinates":[15.5524196625,48.4512214661],"type":"Point"}
}