{
  "type": "Feature",
  "properties": {
    "iso:country":"AT",
    "sg:address":"Kelsenstr 39",
    "sg:city":"Linz",
    "sg:classifiers":[
        {
            "category":"Home & Garden",
            "subcategory":"Building Materials",
            "type":"Retail Goods"
        }
    ],
    "sg:phone":"+43 4373 275734543",
    "sg:postcode":"4040",
    "sg:province":"Ober\u00f6sterreich",
    "sg:tags":[
        "baustoffe",
        "-material",
        "u"
    ],
    "wof:name":"TRIPAN Leichtbauteile Wimmer+Sch\u00f6ftner GmbH & Co KG",
    "wof:placetype":"venue"
},
  "geometry": {"coordinates":[14.2966451645,48.3420295715],"type":"Point"}
}