{
  "type": "Feature",
  "properties": {
    "iso:country":"AT",
    "sg:address":"Sch\u00fctzenstrasse 10",
    "sg:city":"Innsbruck",
    "sg:classifiers":[
        {
            "category":"Bakery",
            "type":"Food & Drink"
        }
    ],
    "sg:phone":"+43 512 2613920",
    "sg:postcode":"6020",
    "sg:province":"Tirol",
    "sg:tags":[
        "scale"
    ],
    "sg:website":"tirol.com/waagen-schatz",
    "wof:name":"Schatz Ges.m.b.H.",
    "wof:placetype":"venue"
},
  "geometry": {"coordinates":[11.3913040161,47.2679977417],"type":"Point"}
}