{
  "type": "Feature",
  "properties": {
    "addr:full":"Nr 81 Drasenhofen Nieder\u00f6sterreich 2165",
    "addr:postcode":"2165",
    "addr:street":"Nr 81",
    "iso:country":"AT",
    "sg:address":"Nr 81",
    "sg:city":"Drasenhofen",
    "sg:classifiers":[
        {
            "category":"Home & Garden",
            "subcategory":"Building Materials",
            "type":"Retail Goods"
        }
    ],
    "sg:phone":"+43 2554 82200",
    "sg:postcode":"2165",
    "sg:province":"Nieder\u00f6sterreich",
    "sg:tags":[
        "baustoffe",
        "-material",
        "u"
    ],
    "wof:name":"Eisinger Ziegelwerk und Baustoffe KG",
    "wof:placetype":"venue"
},
  "geometry": {"coordinates":[150.94784545900001,-33.8690414429],"type":"Point"}
}