{
  "type": "Feature",
  "properties": {
    "iso:country":"AT",
    "sg:address":"Tauernstr 20",
    "sg:city":"M\u00f6derbrugg",
    "sg:orig_category":"Natursteine U -Platten",
    "sg:phone":"+43 4366 44208761",
    "sg:postcode":"8763",
    "sg:province":"Steiermark",
    "wof:name":"Felber Thomas Natursteine Granit Marmor",
    "wof:placetype":"venue"
},
  "geometry": {"coordinates":[14.4848823547,47.2887611389],"type":"Point"}
}