{
  "type": "Feature",
  "properties": {
    "addr:full":"Von-Klenze-Weg 4 Mittelberg Vorarlberg 6993",
    "addr:housenumber":"4",
    "addr:postcode":"6993",
    "addr:street":"Von-Klenze-Weg",
    "iso:country":"AT",
    "sg:address":"Von-Klenze-Weg 4",
    "sg:city":"Mittelberg",
    "sg:classifiers":[
        {
            "category":"Recreation",
            "type":"Entertainment"
        }
    ],
    "sg:phone":"+43 4367 67562909",
    "sg:postcode":"6993",
    "sg:province":"Vorarlberg",
    "sg:tags":[
        "sport",
        "adventure"
    ],
    "wof:name":"Walser Bike Tours - Metzger-M\u00fcller-Steixner OEG",
    "wof:placetype":"venue"
},
  "geometry": {"coordinates":[10.1622514725,47.3335800171],"type":"Point"}
}