{
  "type": "Feature",
  "properties": {
    "addr:full":"D\u00fcrrwienstr 11 Pressbaum Nieder\u00f6sterreich 3021",
    "addr:housenumber":"11",
    "addr:postcode":"3021",
    "addr:street":"Duerrwienstr;Niederoesterreich",
    "iso:country":"AT",
    "sg:address":"D\u00fcrrwienstr 11",
    "sg:city":"Pressbaum",
    "sg:orig_category":"Waren Aller Art",
    "sg:phone":"+43 2233 52507",
    "sg:postcode":"3021",
    "sg:province":"Nieder\u00f6sterreich",
    "wof:name":"Richter & Co Au\u00dfenhandels GesmbH",
    "wof:placetype":"venue"
},
  "geometry": {"coordinates":[16.0784683228,48.1801757812],"type":"Point"}
}