{
  "type": "Feature",
  "properties": {
    "addr:full":"Saxen Ober\u00f6sterreich 4351",
    "addr:housenumber":"4351",
    "iso:country":"AT",
    "sg:city":"Saxen",
    "sg:orig_category":"Feuerwehren",
    "sg:phone":"+43 7269 305",
    "sg:postcode":"4351",
    "sg:province":"Ober\u00f6sterreich",
    "wof:name":"Freiwillige Feuerwehr Saxen",
    "wof:placetype":"venue"
},
  "geometry": {"coordinates":[14.7900476456,48.2081375122],"type":"Point"}
}