{
  "type": "Feature",
  "properties": {
    "addr:full":"Hinterhagweg 332 Saalbach Salzburg 5753",
    "addr:housenumber":"332",
    "addr:postcode":"5753",
    "addr:street":"Hinterhagweg;Salzburg",
    "iso:country":"AT",
    "sg:address":"Hinterhagweg 332",
    "sg:city":"Saalbach",
    "sg:orig_category":"Gastronomie- U Hotelbedarf",
    "sg:phone":"+43 664 4140561",
    "sg:postcode":"5753",
    "sg:province":"Salzburg",
    "wof:name":"Gellery Saalbach Art Print Verlag Eva Hinterberger",
    "wof:placetype":"venue"
},
  "geometry": {"coordinates":[12.6367301941,47.3899307251],"type":"Point"}
}