{
  "type": "Feature",
  "properties": {
    "addr:full":"Industriegel\u00e4nde 34 Oberpullendorf Burgenland 7350",
    "addr:housenumber":"34",
    "addr:postcode":"7350",
    "addr:street":"Industriegelaende",
    "iso:country":"AT",
    "sg:address":"Industriegel\u00e4nde 34",
    "sg:city":"Oberpullendorf",
    "sg:orig_category":"Versicherungsunternehmen",
    "sg:phone":"+43 2612 42683",
    "sg:postcode":"7350",
    "sg:province":"Burgenland",
    "wof:name":"Basler Versicherungs AG in \u00f6sterreich - Dienstleistungszentrum",
    "wof:placetype":"venue"
},
  "geometry": {"coordinates":[16.513759613,47.4956016541],"type":"Point"}
}