{
  "type": "Feature",
  "properties": {
    "addr:full":"Michael-Pacher-Str 28 Salzburg Salzburg 5020",
    "addr:housenumber":"28",
    "addr:postcode":"5020",
    "addr:street":"Michael-Pacher-Str;Salzburg",
    "iso:country":"AT",
    "sg:address":"Michael-Pacher-Str 28",
    "sg:city":"Salzburg",
    "sg:orig_category":"Beratungsstellen",
    "sg:phone":"+43 4366 280424041",
    "sg:postcode":"5020",
    "sg:province":"Salzburg",
    "wof:name":"B\u00fcro f Frauenfragen u Gleichbehandlung",
    "wof:placetype":"venue"
},
  "geometry": {"coordinates":[13.0651636124,47.7888298035],"type":"Point"}
}