{
  "type": "Feature",
  "properties": {
    "addr:full":"Innsbrucker Str 33 Scharnitz Tirol 6108",
    "addr:postcode":"6108",
    "addr:street":"Str 33;Tirol",
    "iso:country":"AT",
    "sg:address":"Innsbrucker Str 33",
    "sg:city":"Scharnitz",
    "sg:orig_category":"Pensionen / Privatzimmer",
    "sg:phone":"+43 5213 5282",
    "sg:postcode":"6108",
    "sg:province":"Tirol",
    "wof:name":"Landhaus Romana Klotz",
    "wof:placetype":"venue"
},
  "geometry": {"coordinates":[11.2620210648,47.3881416321],"type":"Point"}
}