{
  "type": "Feature",
  "properties": {
    "addr:full":"Garnisong 3 Wien Wien 1090",
    "addr:housenumber":"3",
    "addr:postcode":"1090",
    "addr:street":"Garnisong",
    "iso:country":"AT",
    "sg:address":"Garnisong 3",
    "sg:city":"Wien",
    "sg:orig_category":"Institute",
    "sg:phone":"+43 4314 27746701",
    "sg:postcode":"1090",
    "sg:province":"Wien",
    "wof:name":"Institut f Erziehungswissenschaft d Universit\u00e4t Wien",
    "wof:placetype":"venue"
},
  "geometry": {"coordinates":[16.3564071655,48.2152938843],"type":"Point"}
}