{
  "type": "Feature",
  "properties": {
    "addr:full":"Schutzenbichl 4 Bad Ischl Ober\u00f6sterreich 4820",
    "addr:housenumber":"4",
    "addr:postcode":"4820",
    "addr:street":"Schutzenbichl",
    "iso:country":"AT",
    "sg:address":"Schutzenbichl 4",
    "sg:city":"Bad Ischl",
    "sg:orig_category":"Beratungsstellen",
    "sg:phone":"+43 6132 28290",
    "sg:postcode":"4820",
    "sg:province":"Ober\u00f6sterreich",
    "wof:name":"Kinderschutzzentrum K\u00e4nguru",
    "wof:placetype":"venue"
},
  "geometry": {"coordinates":[13.6206064224,47.7134017944],"type":"Point"}
}