{
  "type": "Feature",
  "properties": {
    "addr:full":"Gewerbepark 2 Strengberg Nieder\u00f6sterreich 3314",
    "addr:housenumber":"2",
    "addr:postcode":"3314",
    "addr:street":"Gewerbepark",
    "iso:country":"AT",
    "sg:address":"Gewerbepark 2",
    "sg:city":"Strengberg",
    "sg:orig_category":"Autospenglereien",
    "sg:phone":"+43 7432 20076",
    "sg:postcode":"3314",
    "sg:province":"Nieder\u00f6sterreich",
    "wof:name":"Glaser & Steinbichler GmbH",
    "wof:placetype":"venue"
},
  "geometry": {"coordinates":[14.6340332031,48.145778656],"type":"Point"}
}