{
  "type": "Feature",
  "properties": {
    "iso:country":"AT",
    "sg:address":"Waagpl 5",
    "sg:city":"Salzburg",
    "sg:orig_category":"Damenmoden",
    "sg:phone":"+43 662 8417560",
    "sg:postcode":"5020",
    "sg:province":"Salzburg",
    "wof:name":"Hoflehner am Waagplatz GesmbH & Co KG",
    "wof:placetype":"venue"
},
  "geometry": {"coordinates":[13.0466566086,47.7990837097],"type":"Point"}
}