{
  "type": "Feature",
  "properties": {
    "iso:country":"AT",
    "sg:address":"Hub 63",
    "sg:city":"Egg",
    "sg:classifiers":[
        {
            "category":"Manufacturing",
            "subcategory":"Wood Products",
            "type":"Manufacturing & Wholesale Goods"
        }
    ],
    "sg:phone":"+43 5512 39700",
    "sg:postcode":"6863",
    "sg:province":"Vorarlberg",
    "sg:tags":[
        "lumber"
    ],
    "sg:website":"s-holz.com",
    "wof:name":"Sutterl\u00fcty Holzwerk Ges.m.b.H. & Co",
    "wof:placetype":"venue"
},
  "geometry": {"coordinates":[9.9063167572,47.430355072],"type":"Point"}
}