{
  "type": "Feature",
  "properties": {
    "iso:country":"AT",
    "sg:address":"Hauptstr 5",
    "sg:city":"Mitterbach am Erlaufsee",
    "sg:classifiers":[
        {
            "category":"Travel",
            "subcategory":"Hotels & Motels",
            "type":"Entertainment"
        }
    ],
    "sg:phone":"+43 4338 822615",
    "sg:postcode":"3224",
    "sg:province":"Nieder\u00f6sterreich",
    "wof:name":"Hotel Hulatsch",
    "wof:placetype":"venue"
},
  "geometry": {"coordinates":[15.2952346802,47.8132286072],"type":"Point"}
}