{
  "type": "Feature",
  "properties": {
    "addr:full":"Kemmelbach Nieder\u00f6sterreich 3373",
    "addr:postcode":"3373",
    "addr:street":"Niederoesterreich",
    "iso:country":"AT",
    "sg:city":"Kemmelbach",
    "sg:orig_category":"Finanzen, Sonstige Finanzangelegenheiten",
    "sg:postcode":"3373",
    "sg:province":"Nieder\u00f6sterreich",
    "sg:website":"http://www.eberlein.at",
    "wof:name":"Rasthaus Kemmelbach Eberlein",
    "wof:placetype":"venue"
},
  "geometry": {"coordinates":[15.0943393707,48.1549682617],"type":"Point"}
}