{
  "type": "Feature",
  "properties": {
    "iso:country":"AT",
    "sg:address":"Marktgraben 14",
    "sg:city":"Innsbruck",
    "sg:orig_category":"Stukkateure U Trockenausbauer",
    "sg:phone":"+43 512 589164",
    "sg:postcode":"6020",
    "sg:province":"Tirol",
    "wof:name":"Kalkus Artur",
    "wof:placetype":"venue"
},
  "geometry": {"coordinates":[11.3929738998,47.2667808533],"type":"Point"}
}