{
  "type": "Feature",
  "properties": {
    "iso:country":"AT",
    "sg:address":"Nr 191",
    "sg:city":"Kaindorf",
    "sg:orig_category":"Immobilienverwaltungen",
    "sg:phone":"+43 4333 343400",
    "sg:postcode":"8224",
    "sg:province":"Steiermark",
    "wof:name":"M G Immobilienverwaltungs GmbH",
    "wof:placetype":"venue"
},
  "geometry": {"coordinates":[15.8505401611,47.2258033752],"type":"Point"}
}