{
  "type": "Feature",
  "properties": {
    "addr:full":"Praterstr 50 Wien Wien 1020",
    "addr:housenumber":"50",
    "addr:postcode":"1020",
    "addr:street":"Praterstr",
    "iso:country":"AT",
    "sg:address":"Praterstr 50",
    "sg:city":"Wien",
    "sg:orig_category":"Banken U Sparkassen",
    "sg:phone":"+43 5 050532415",
    "sg:postcode":"1020",
    "sg:province":"Wien",
    "wof:name":"Bank Austria Creditanstalt AG",
    "wof:placetype":"venue"
},
  "geometry": {"coordinates":[16.3868274689,48.2158088684],"type":"Point"}
}