{
  "type": "Feature",
  "properties": {
    "iso:country":"AT",
    "sg:address":"Murrstr 2/74",
    "sg:city":"Wien",
    "sg:orig_category":"Hundeabrichtung U -Schulen",
    "sg:phone":"+43 4312 573976",
    "sg:postcode":"1220",
    "sg:province":"Wien",
    "wof:name":"\u00d6sterr Gebrauchshundeverein DVW-Donaustadt",
    "wof:placetype":"venue"
},
  "geometry": {"coordinates":[16.4427089691,48.2596054077],"type":"Point"}
}