{
  "type": "Feature",
  "properties": {
    "iso:country":"AT",
    "sg:address":"Ringstr 23",
    "sg:city":"Feldbach",
    "sg:orig_category":"Volksschulen",
    "sg:phone":"+43 3152 2287",
    "sg:postcode":"8330",
    "sg:province":"Steiermark",
    "wof:name":"Volksschule 1",
    "wof:placetype":"venue"
},
  "geometry": {"coordinates":[15.8858203888,46.951965332],"type":"Point"}
}