{
  "type": "Feature",
  "properties": {
    "addr:full":"Kochstr 10 Innsbruck Tirol 6020",
    "addr:housenumber":"10",
    "addr:postcode":"6020",
    "addr:street":"Kochstr;Tirol",
    "iso:country":"AT",
    "sg:address":"Kochstr 10",
    "sg:city":"Innsbruck",
    "sg:orig_category":"Fotografen",
    "sg:phone":"+43 512 572385",
    "sg:postcode":"6020",
    "sg:province":"Tirol",
    "wof:name":"Margreiter Rudolf",
    "wof:placetype":"venue"
},
  "geometry": {"coordinates":[11.4018564224,47.2717170715],"type":"Point"}
}