{
  "type": "Feature",
  "properties": {
    "addr:full":"Seestr 12 Feld am See K\u00e4rnten 9544",
    "addr:housenumber":"12",
    "addr:postcode":"9544",
    "addr:street":"Seestr;Kaernten",
    "iso:country":"AT",
    "sg:address":"Seestr 12",
    "sg:city":"Feld am See",
    "sg:orig_category":"Pensionen / Privatzimmer",
    "sg:phone":"+43 4246 2495",
    "sg:postcode":"9544",
    "sg:province":"K\u00e4rnten",
    "wof:name":"Sportpension Seehof",
    "wof:placetype":"venue"
},
  "geometry": {"coordinates":[13.7500267029,46.7751655579],"type":"Point"}
}