{
  "type": "Feature",
  "properties": {
    "addr:full":"Tischlerstr 7 Bad Hall Ober\u00f6sterreich 4540",
    "addr:housenumber":"7",
    "addr:postcode":"4540",
    "addr:street":"Tischlerstr",
    "iso:country":"AT",
    "sg:address":"Tischlerstr 7",
    "sg:city":"Bad Hall",
    "sg:orig_category":"Rohrleitungen U Rohrleitungsbau",
    "sg:phone":"+43 4372 5853530",
    "sg:postcode":"4540",
    "sg:province":"Ober\u00f6sterreich",
    "wof:name":"Tomic Versorgungstechnik GesmbH",
    "wof:placetype":"venue"
},
  "geometry": {"coordinates":[14.1890516281,48.0295333862],"type":"Point"}
}