{
  "type": "Feature",
  "properties": {
    "addr:full":"Ringstr 52 Krems an der Donau Nieder\u00f6sterreich 3500",
    "addr:housenumber":"52",
    "addr:postcode":"3500",
    "addr:street":"Ringstr",
    "iso:country":"AT",
    "sg:address":"Ringstr 52",
    "sg:city":"Krems an der Donau",
    "sg:orig_category":"Zeitungen U Zeitschriften",
    "sg:phone":"+43 4327 3270459",
    "sg:postcode":"3500",
    "sg:province":"Nieder\u00f6sterreich",
    "wof:name":"Unser Gratisblatt",
    "wof:placetype":"venue"
},
  "geometry": {"coordinates":[15.597694397,48.4079971313],"type":"Point"}
}