{
  "type": "Feature",
  "properties": {
    "addr:full":"Maysederg 2 Wien Wien 1010",
    "addr:housenumber":"2",
    "addr:postcode":"1010",
    "addr:street":"Maysederg",
    "iso:country":"AT",
    "sg:address":"Maysederg 2",
    "sg:city":"Wien",
    "sg:classifiers":[
        {
            "category":"Restaurant",
            "type":"Food & Drink"
        }
    ],
    "sg:phone":"+43 1 51234580",
    "sg:postcode":"1010",
    "sg:province":"Wien",
    "wof:name":"Rosenberger Marktrestaurant Wien",
    "wof:placetype":"venue"
},
  "geometry": {"coordinates":[16.3701553345,48.2043647766],"type":"Point"}
}