{
  "type": "Feature",
  "properties": {
    "addr:full":"Sch\u00f6neggsdlg 28 Hall in Tirol Tirol 6060",
    "addr:housenumber":"28",
    "addr:postcode":"6060",
    "addr:street":"Schoeneggsdlg;Tirol",
    "iso:country":"AT",
    "sg:address":"Sch\u00f6neggsdlg 28",
    "sg:city":"Hall in Tirol",
    "sg:orig_category":"Installationsunternehmen",
    "sg:phone":"+43 5223 45549",
    "sg:postcode":"6060",
    "sg:province":"Tirol",
    "wof:name":"Rasant B\u00e4derservice GmbH",
    "wof:placetype":"venue"
},
  "geometry": {"coordinates":[11.5065698624,47.2818107605],"type":"Point"}
}