{
  "type": "Feature",
  "properties": {
    "addr:full":"Gmundner Str 21 Sch\u00f6rfling am Attersee Ober\u00f6sterreich 4861",
    "addr:postcode":"4861",
    "addr:street":"Str 21;Am",
    "iso:country":"AT",
    "sg:address":"Gmundner Str 21",
    "sg:city":"Sch\u00f6rfling am Attersee",
    "sg:orig_category":"Volksschulen",
    "sg:phone":"+43 4376 626483",
    "sg:postcode":"4861",
    "sg:province":"Ober\u00f6sterreich",
    "wof:name":"Volksschule Sch\u00f6rfling",
    "wof:placetype":"venue"
},
  "geometry": {"coordinates":[13.6080598831,47.9477996826],"type":"Point"}
}