{
  "type": "Feature",
  "properties": {
    "addr:full":"Innsbrucker Str 37 Ehrwald Tirol 6632",
    "addr:postcode":"6632",
    "addr:street":"Str 37;Tirol",
    "iso:country":"AT",
    "sg:address":"Innsbrucker Str 37",
    "sg:city":"Ehrwald",
    "sg:orig_category":"Lebensmittel / Einzelhandel",
    "sg:phone":"+43 5673 24460",
    "sg:postcode":"6632",
    "sg:province":"Tirol",
    "wof:name":"MPREIS WarenvertriebsgesmbH",
    "wof:placetype":"venue"
},
  "geometry": {"coordinates":[10.914978981,47.3957595825],"type":"Point"}
}