{
  "type": "Feature",
  "properties": {
    "addr:full":"Nr 70 Dalaas Vorarlberg 6752",
    "addr:postcode":"6752",
    "addr:street":"Nr 70",
    "iso:country":"AT",
    "sg:address":"Nr 70",
    "sg:city":"Dalaas",
    "sg:orig_category":"Banken U Sparkassen",
    "sg:phone":"+43 4355 857213",
    "sg:postcode":"6752",
    "sg:province":"Vorarlberg",
    "wof:name":"Raiffeisenbank Bludenz regGenmbH",
    "wof:placetype":"venue"
},
  "geometry": {"coordinates":[9.9998960495,47.1229896545],"type":"Point"}
}