{
  "type": "Feature",
  "properties": {
    "addr:full":"Obere Dorfstr 2 Wei\u00dfkirchen an der Traun Ober\u00f6sterreich 4616",
    "addr:housenumber":"2",
    "addr:postcode":"4616",
    "addr:street":"Obere Dorfstr",
    "iso:country":"AT",
    "sg:address":"Obere Dorfstr 2",
    "sg:city":"Wei\u00dfkirchen an der Traun",
    "sg:orig_category":"Banken U Sparkassen",
    "sg:phone":"+43 4372 4356810",
    "sg:postcode":"4616",
    "sg:province":"Ober\u00f6sterreich",
    "wof:name":"Sparkasse Neuhofen Bank AG",
    "wof:placetype":"venue"
},
  "geometry": {"coordinates":[14.1260967255,48.163734436],"type":"Point"}
}