{
  "type": "Feature",
  "properties": {
    "addr:full":"Hauptstr 6 Pressbaum Nieder\u00f6sterreich 3021",
    "addr:housenumber":"6",
    "addr:postcode":"3021",
    "addr:street":"Hauptstr;Niederoesterreich",
    "iso:country":"AT",
    "sg:address":"Hauptstr 6",
    "sg:city":"Pressbaum",
    "sg:orig_category":"Papier- U Schreibwaren / Einzelhandel",
    "sg:phone":"+43 2233 525760",
    "sg:postcode":"3021",
    "sg:province":"Nieder\u00f6sterreich",
    "wof:name":"Papierfachgesch\u00e4ft M Thoma",
    "wof:placetype":"venue"
},
  "geometry": {"coordinates":[16.0907058716,48.1833763123],"type":"Point"}
}