{
  "type": "Feature",
  "properties": {
    "iso:country":"AT",
    "sg:address":"Firmiang 47/2",
    "sg:city":"Wien",
    "sg:orig_category":"Psychotherapie",
    "sg:phone":"+43 1 8779383",
    "sg:postcode":"1130",
    "sg:province":"Wien",
    "wof:name":"Fritz-Deckenbach Angelika Dr",
    "wof:placetype":"venue"
},
  "geometry": {"coordinates":[16.2686901093,48.1913986206],"type":"Point"}
}