{
  "type": "Feature",
  "properties": {
    "addr:full":"Hauptstr 417 Mayrhofen Tirol 6290",
    "addr:housenumber":"417",
    "addr:postcode":"6290",
    "addr:street":"Hauptstr;Tirol",
    "iso:country":"AT",
    "sg:address":"Hauptstr 417",
    "sg:city":"Mayrhofen",
    "sg:orig_category":"Freizeit- U Sportbekleidung",
    "sg:phone":"+43 5285 63298",
    "sg:postcode":"6290",
    "sg:province":"Tirol",
    "wof:name":"Creation Bair GmbH",
    "wof:placetype":"venue"
},
  "geometry": {"coordinates":[11.8633069992,47.1672821045],"type":"Point"}
}