{
  "type": "Feature",
  "properties": {
    "iso:country":"AT",
    "sg:address":"Alte Bundesstr 287",
    "sg:city":"Uttendorf",
    "sg:orig_category":"Banken U Sparkassen",
    "sg:phone":"+43 4365 6383110",
    "sg:postcode":"5723",
    "sg:province":"Salzburg",
    "wof:name":"Sparkasse Mittersill Bank AG - Fil Uttendorf",
    "wof:placetype":"venue"
},
  "geometry": {"coordinates":[12.5631933212,47.2843933105],"type":"Point"}
}