{
  "type": "Feature",
  "properties": {
    "addr:full":"Tullner Str 117 Langenlebarn Nieder\u00f6sterreich 3425",
    "addr:housenumber":"117",
    "addr:postcode":"3425",
    "iso:country":"AT",
    "sg:address":"Tullner Str 117",
    "sg:city":"Langenlebarn",
    "sg:classifiers":[
        {
            "category":"Shopping",
            "subcategory":"Gifts & Souvenirs",
            "type":"Retail Goods"
        }
    ],
    "sg:phone":"+43 2272 817170",
    "sg:postcode":"3425",
    "sg:province":"Nieder\u00f6sterreich",
    "wof:name":"Fan-Shop Strobl Versand",
    "wof:placetype":"venue"
},
  "geometry": {"coordinates":[16.102645874,48.3304023743],"type":"Point"}
}