{
  "type": "Feature",
  "properties": {
    "iso:country":"AT",
    "sg:address":"Wiener Str 22",
    "sg:city":"Kindberg",
    "sg:orig_category":"Rettungsdienste",
    "sg:phone":"+43 3865 2444",
    "sg:postcode":"8650",
    "sg:province":"Steiermark",
    "wof:name":"Rotes Kreuz \u00f6sterr Ortsstelle Kindberg",
    "wof:placetype":"venue"
},
  "geometry": {"coordinates":[15.4648513794,47.5153694153],"type":"Point"}
}