{
  "type": "Feature",
  "properties": {
    "iso:country":"AT",
    "sg:address":"Kollonitschstr 7A",
    "sg:city":"Graz",
    "sg:orig_category":"\u00c3\u201erzte / F Allgemeinmedizin",
    "sg:phone":"+43 316 382256",
    "sg:postcode":"8010",
    "sg:province":"Steiermark",
    "wof:name":"Al-Tikriti Farouk Dr",
    "wof:placetype":"venue"
},
  "geometry": {"coordinates":[15.4804840088,47.0878181458],"type":"Point"}
}