{
  "type": "Feature",
  "properties": {
    "addr:full":"Hauptstr 40 Ulrichskirchen Nieder\u00f6sterreich 2122",
    "addr:housenumber":"40",
    "addr:postcode":"2122",
    "addr:street":"Hauptstr",
    "iso:country":"AT",
    "sg:address":"Hauptstr 40",
    "sg:city":"Ulrichskirchen",
    "sg:orig_category":"Werbegestalter",
    "sg:phone":"+43 2245 3149",
    "sg:postcode":"2122",
    "sg:province":"Nieder\u00f6sterreich",
    "wof:name":"Finger Renate",
    "wof:placetype":"venue"
},
  "geometry": {"coordinates":[16.4721355438,48.3866729736],"type":"Point"}
}