{
  "type": "Feature",
  "properties": {
    "addr:full":"Nr 5 Rosenau Schlo\u00df Nieder\u00f6sterreich 3924",
    "addr:postcode":"3924",
    "addr:street":"Nr;Rosenau;Niederoesterreich",
    "iso:country":"AT",
    "sg:address":"Nr 5",
    "sg:city":"Rosenau Schlo\u00df",
    "sg:orig_category":"Pensionen / Privatzimmer",
    "sg:phone":"+43 2822 53855",
    "sg:postcode":"3924",
    "sg:province":"Nieder\u00f6sterreich",
    "wof:name":"Weichselbaum Karl",
    "wof:placetype":"venue"
},
  "geometry": {"coordinates":[15.054441452,48.6025543213],"type":"Point"}
}