{
  "type": "Feature",
  "properties": {
    "addr:full":"Nr 66 Hollersbach im Pinzgau Salzburg 5731",
    "addr:postcode":"5731",
    "addr:street":"Nr 66;Salzburg",
    "iso:country":"AT",
    "sg:address":"Nr 66",
    "sg:city":"Hollersbach im Pinzgau",
    "sg:orig_category":"Schmieden U Schmiedeeisenelemente",
    "sg:phone":"+43 4365 628134",
    "sg:postcode":"5731",
    "sg:province":"Salzburg",
    "wof:name":"Wallner Franz",
    "wof:placetype":"venue"
},
  "geometry": {"coordinates":[12.4197301865,47.2750968933],"type":"Point"}
}