{
  "type": "Feature",
  "properties": {
    "addr:full":"Kircheng 7 Wien Wien 1070",
    "addr:housenumber":"7",
    "addr:postcode":"1070",
    "addr:street":"Kircheng",
    "iso:country":"AT",
    "sg:address":"Kircheng 7",
    "sg:city":"Wien",
    "sg:classifiers":[
        {
            "category":"Professional",
            "subcategory":"Computer Services",
            "type":"Services"
        }
    ],
    "sg:phone":"+43 1 52648250",
    "sg:postcode":"1070",
    "sg:province":"Wien",
    "sg:tags":[
        "software"
    ],
    "wof:name":"MSB Mikrocomputer Software HandelsgesmbH",
    "wof:placetype":"venue"
},
  "geometry": {"coordinates":[16.3522777557,48.2003631592],"type":"Point"}
}