{
  "type": "Feature",
  "properties": {
    "addr:full":"Wildbachberg 16 Bad Gams Steiermark 8524",
    "addr:housenumber":"16",
    "addr:postcode":"8524",
    "addr:street":"Wildbachberg",
    "iso:country":"AT",
    "sg:address":"Wildbachberg 16",
    "sg:city":"Bad Gams",
    "sg:orig_category":"Weine / Einzelhandel",
    "sg:phone":"+43 4334 627727",
    "sg:postcode":"8524",
    "sg:province":"Steiermark",
    "wof:name":"Deutsch-Maier Weinbau u Vinothek",
    "wof:placetype":"venue"
},
  "geometry": {"coordinates":[15.2210273743,46.850643158],"type":"Point"}
}