{
  "type": "Feature",
  "properties": {
    "iso:country":"AT",
    "sg:address":"Wildbachberg 16",
    "sg:city":"Bad Gams",
    "sg:orig_category":"Weine / Einzelhandel",
    "sg:phone":"+43 4334 627727",
    "sg:postcode":"8524",
    "sg:province":"Steiermark",
    "wof:name":"Deutsch-Maier Weinbau u Vinothek",
    "wof:placetype":"venue"
},
  "geometry": {"coordinates":[15.2210273743,46.850643158],"type":"Point"}
}