{
  "type": "Feature",
  "properties": {
    "iso:country":"AT",
    "sg:address":"Obere Hauptstr 18",
    "sg:city":"Dorf Veitsch",
    "sg:orig_category":"Gemeinden",
    "sg:phone":"+43 4338 5622220",
    "sg:postcode":"8663",
    "sg:province":"Steiermark",
    "wof:name":"Marktgemeindeamt Veitsch",
    "wof:placetype":"venue"
},
  "geometry": {"coordinates":[15.4896583557,47.5791320801],"type":"Point"}
}