{
  "type": "Feature",
  "properties": {
    "addr:full":"B\u00f6cksteiner Bundesstr 25 Bad Gastein Salzburg 5640",
    "addr:housenumber":"25",
    "addr:postcode":"5640",
    "addr:street":"Salzburg",
    "iso:country":"AT",
    "sg:address":"B\u00f6cksteiner Bundesstr 25",
    "sg:city":"Bad Gastein",
    "sg:orig_category":"Fliesen- U Plattenverlegungen",
    "sg:phone":"+43 4364 3423800",
    "sg:postcode":"5640",
    "sg:province":"Salzburg",
    "wof:name":"Bader Christof KG",
    "wof:placetype":"venue"
},
  "geometry": {"coordinates":[13.1295318604,47.1019058228],"type":"Point"}
}