{
  "type": "Feature",
  "properties": {
    "addr:full":"Nr 7 Turnau Steiermark 8625",
    "addr:postcode":"8625",
    "addr:street":"Nr",
    "iso:country":"AT",
    "sg:address":"Nr 7",
    "sg:city":"Turnau",
    "sg:orig_category":"Banken U Sparkassen",
    "sg:phone":"+43 4338 632332",
    "sg:postcode":"8625",
    "sg:province":"Steiermark",
    "wof:name":"Steierm\u00e4rkische Bank u Sparkassen AG",
    "wof:placetype":"venue"
},
  "geometry": {"coordinates":[15.3370742798,47.5582237244],"type":"Point"}
}