{
  "type": "Feature",
  "properties": {
    "iso:country":"AT",
    "sg:address":"Angernstrasse 17",
    "sg:city":"Garsten",
    "sg:classifiers":[
        {
            "category":"Home & Garden",
            "subcategory":"Household Appliances",
            "type":"Retail Goods"
        }
    ],
    "sg:phone":"+43 7259 4632",
    "sg:postcode":"4451",
    "sg:province":"Ober\u00f6sterreich",
    "sg:tags":[
        "stove",
        "chimney"
    ],
    "sg:website":"goedl.co.at",
    "wof:name":"Spenglerei & Solartechnik G\u00d6DL Ges.m.b.H.",
    "wof:placetype":"venue"
},
  "geometry": {"coordinates":[14.3795909882,47.9725227356],"type":"Point"}
}