{
  "type": "Feature",
  "properties": {
    "iso:country":"AT",
    "sg:address":"Sulzer Str 36",
    "sg:city":"Hohenruppersdorf",
    "sg:orig_category":"Tischlereien",
    "sg:phone":"+43 2574 83790",
    "sg:postcode":"2223",
    "sg:province":"Nieder\u00f6sterreich",
    "wof:name":"Glassl Erhard",
    "wof:placetype":"venue"
},
  "geometry": {"coordinates":[16.6573562622,48.4645462036],"type":"Point"}
}