{
  "type": "Feature",
  "properties": {
    "addr:full":"Langg 5 Imst Tirol 6460",
    "addr:housenumber":"5",
    "addr:postcode":"6460",
    "addr:street":"Langg;Tirol",
    "iso:country":"AT",
    "sg:address":"Langg 5",
    "sg:city":"Imst",
    "sg:orig_category":"Physiotherapie",
    "sg:phone":"+43 664 2800630",
    "sg:postcode":"6460",
    "sg:province":"Tirol",
    "wof:name":"Knapp Nikola Dipl-PT",
    "wof:placetype":"venue"
},
  "geometry": {"coordinates":[10.737487793,47.2392234802],"type":"Point"}
}