{
  "type": "Feature",
  "properties": {
    "iso:country":"AT",
    "sg:address":"Am Graben 6",
    "sg:city":"Gmunden",
    "sg:orig_category":"Damenmoden",
    "sg:phone":"+43 761266896",
    "sg:postcode":"4810",
    "sg:province":"Ober\u00f6sterreich",
    "wof:name":"Top Line HandelsgmbH",
    "wof:placetype":"venue"
},
  "geometry": {"coordinates":[13.798368454,47.9185600281],"type":"Point"}
}