{
  "type": "Feature",
  "properties": {
    "addr:full":"Tendlerg 3 Wien Wien 1090",
    "addr:housenumber":"3",
    "addr:postcode":"1090",
    "addr:street":"Tendlerg",
    "iso:country":"AT",
    "sg:address":"Tendlerg 3",
    "sg:city":"Wien",
    "sg:classifiers":[
        {
            "category":"Restaurant",
            "type":"Food & Drink"
        }
    ],
    "sg:phone":"+43 4314 085778",
    "sg:postcode":"1090",
    "sg:province":"Wien",
    "sg:tags":[
        "pizzeria"
    ],
    "wof:name":"Pizzeria Giuliano",
    "wof:placetype":"venue"
},
  "geometry": {"coordinates":[16.3522129059,48.2209663391],"type":"Point"}
}