{
  "type": "Feature",
  "properties": {
    "addr:full":"Kirchboden 97 Wagrain Salzburg 5602",
    "addr:housenumber":"97",
    "addr:postcode":"5602",
    "addr:street":"Kirchboden;Salzburg",
    "iso:country":"AT",
    "sg:address":"Kirchboden 97",
    "sg:city":"Wagrain",
    "sg:classifiers":[
        {
            "category":"Travel",
            "subcategory":"Hotels & Motels",
            "type":"Entertainment"
        }
    ],
    "sg:phone":"+43 6413 83370",
    "sg:postcode":"5602",
    "sg:province":"Salzburg",
    "wof:name":"Hotel Alpina",
    "wof:placetype":"venue"
},
  "geometry": {"coordinates":[13.3065805435,47.3315391541],"type":"Point"}
}