{
  "type": "Feature",
  "properties": {
    "addr:full":"Witthauerg 38 Wien Wien 1180",
    "addr:housenumber":"38",
    "addr:postcode":"1180",
    "addr:street":"Witthauerg",
    "iso:country":"AT",
    "sg:address":"Witthauerg 38",
    "sg:city":"Wien",
    "sg:orig_category":"Immobilienverwaltungen",
    "sg:phone":"+43 1 47015160",
    "sg:postcode":"1180",
    "sg:province":"Wien",
    "wof:name":"Academia Immobilientreuhand GesmbH",
    "wof:placetype":"venue"
},
  "geometry": {"coordinates":[16.3251934052,48.2358398438],"type":"Point"}
}