{
  "type": "Feature",
  "properties": {
    "iso:country":"AT",
    "sg:address":"Rosentaler Str 102",
    "sg:city":"Klagenfurt",
    "sg:orig_category":"Tankstellen",
    "sg:phone":"+43 463 204947",
    "sg:postcode":"9020",
    "sg:province":"K\u00e4rnten",
    "wof:name":"JET Tankstelle",
    "wof:placetype":"venue"
},
  "geometry": {"coordinates":[14.300743103,46.6118392944],"type":"Point"}
}