{
  "type": "Feature",
  "properties": {
    "addr:full":"Waidach 20a Adnet Salzburg 5421",
    "addr:housenumber":"20a",
    "addr:postcode":"5421",
    "addr:street":"Waidach;Salzburg",
    "iso:country":"AT",
    "sg:address":"Waidach 20a",
    "sg:city":"Adnet",
    "sg:classifiers":[
        {
            "category":"Travel",
            "subcategory":"Hotels & Motels",
            "type":"Entertainment"
        }
    ],
    "sg:phone":"+43 6245 89840",
    "sg:postcode":"5421",
    "sg:province":"Salzburg",
    "sg:website":"hotel-hubertushof.at",
    "wof:name":"Hotel Hubertushof Fam Hager",
    "wof:placetype":"venue"
},
  "geometry": {"coordinates":[13.1378803253,47.6893005371],"type":"Point"}
}