{
  "type": "Feature",
  "properties": {
    "iso:country":"AT",
    "sg:address":"Amraser-See-Str 20",
    "sg:city":"Innsbruck",
    "sg:orig_category":"Raumausstattung",
    "sg:phone":"+43 4351 2546900",
    "sg:postcode":"6020",
    "sg:province":"Tirol",
    "wof:name":"Polsterservice Tirol",
    "wof:placetype":"venue"
},
  "geometry": {"coordinates":[11.42228508,47.2612800598],"type":"Point"}
}