{
  "type": "Feature",
  "properties": {
    "iso:country":"AT",
    "sg:address":"Bergmannstr 12",
    "sg:city":"Hohenems",
    "sg:orig_category":"Physiotherapie",
    "sg:phone":"+43 5576 73470",
    "sg:postcode":"6845",
    "sg:province":"Vorarlberg",
    "wof:name":"Aberer Ulrike Dipl-PT",
    "wof:placetype":"venue"
},
  "geometry": {"coordinates":[9.6850299835,47.3611488342],"type":"Point"}
}