{
  "type": "Feature",
  "properties": {
    "addr:full":"Auerspergstr 14 Salzburg Salzburg 5020",
    "addr:housenumber":"14",
    "addr:postcode":"5020",
    "addr:street":"Auerspergstr;Salzburg",
    "iso:country":"AT",
    "sg:address":"Auerspergstr 14",
    "sg:city":"Salzburg",
    "sg:orig_category":"Personalbereitstellung",
    "sg:phone":"+43 662 871681",
    "sg:postcode":"5020",
    "sg:province":"Salzburg",
    "wof:name":"Manpower GmbH",
    "wof:placetype":"venue"
},
  "geometry": {"coordinates":[13.0429821014,47.8076782227],"type":"Point"}
}