{
  "type": "Feature",
  "properties": {
    "iso:country":"AT",
    "sg:address":"Augasse 24",
    "sg:city":"Oberwart",
    "sg:classifiers":[
        {
            "category":"Home & Garden",
            "subcategory":"Home Furnishings",
            "type":"Retail Goods"
        }
    ],
    "sg:phone":"+43 4333 52380370",
    "sg:postcode":"7400",
    "sg:province":"Burgenland",
    "sg:tags":[
        "household"
    ],
    "wof:name":"SCHLOFFER GMBH",
    "wof:placetype":"venue"
},
  "geometry": {"coordinates":[16.2056159973,47.2994384766],"type":"Point"}
}