{
  "type": "Feature",
  "properties": {
    "addr:full":"Landstr 33 Zwettl Nieder\u00f6sterreich 3910",
    "addr:housenumber":"33",
    "addr:postcode":"3910",
    "addr:street":"Landstr;Niederoesterreich",
    "iso:country":"AT",
    "sg:address":"Landstr 33",
    "sg:city":"Zwettl",
    "sg:orig_category":"Boutiquen",
    "sg:phone":"+43 2822 52450",
    "sg:postcode":"3910",
    "sg:province":"Nieder\u00f6sterreich",
    "wof:name":"Schwarz Franz Nfg Franz Wagner",
    "wof:placetype":"venue"
},
  "geometry": {"coordinates":[15.1660404205,48.6049728394],"type":"Point"}
}