{
  "type": "Feature",
  "properties": {
    "iso:country":"AT",
    "sg:address":"Nr 678",
    "sg:city":"Gosau",
    "sg:orig_category":"Autoreparatur",
    "sg:phone":"+43 6136 8619",
    "sg:postcode":"4824",
    "sg:province":"Ober\u00f6sterreich",
    "wof:name":"Gamsj\u00e4ger Franz",
    "wof:placetype":"venue"
},
  "geometry": {"coordinates":[13.5339212418,47.5838432312],"type":"Point"}
}