{
  "type": "Feature",
  "properties": {
    "addr:full":"Nr 47 Stubenberg am See Steiermark 8223",
    "addr:postcode":"8223",
    "addr:street":"Nr;Stubenberg Am See Steiermark",
    "iso:country":"AT",
    "sg:address":"Nr 47",
    "sg:city":"Stubenberg am See",
    "sg:classifiers":[
        {
            "category":"Professional",
            "subcategory":"Computer Services",
            "type":"Services"
        }
    ],
    "sg:phone":"+43 3176 20039",
    "sg:postcode":"8223",
    "sg:province":"Steiermark",
    "sg:tags":[
        "software"
    ],
    "wof:name":"LSP Vertriebs- und mediale Dienstleistungs GmbH",
    "wof:placetype":"venue"
},
  "geometry": {"coordinates":[15.7882232666,47.2304573059],"type":"Point"}
}