{
  "type": "Feature",
  "properties": {
    "addr:full":"Schelleing 24-26 Wien Wien 1040",
    "addr:postcode":"24-26;1040",
    "iso:country":"AT",
    "sg:address":"Schelleing 24-26",
    "sg:city":"Wien",
    "sg:orig_category":"Rettungsdienste",
    "sg:phone":"+43 1 5057057",
    "sg:postcode":"1040",
    "sg:province":"Wien",
    "wof:name":"\u00f6sterreichischer Bergrettungsdienst Landesleitung Wien-N\u00f6",
    "wof:placetype":"venue"
},
  "geometry": {"coordinates":[16.3722953796,48.1868209839],"type":"Point"}
}