{
  "type": "Feature",
  "properties": {
    "addr:full":"Gauderg 21 Zell am Ziller Tirol 6280",
    "addr:housenumber":"21",
    "addr:postcode":"6280",
    "addr:street":"Gauderg;Tirol",
    "iso:country":"AT",
    "sg:address":"Gauderg 21",
    "sg:city":"Zell am Ziller",
    "sg:orig_category":"Antriebstechnik",
    "sg:phone":"+43 5282 22450",
    "sg:postcode":"6280",
    "sg:province":"Tirol",
    "wof:name":"Langesee Hans GesmbH",
    "wof:placetype":"venue"
},
  "geometry": {"coordinates":[11.8876190186,47.2299766541],"type":"Point"}
}