{
  "type": "Feature",
  "properties": {
    "addr:full":"Hauptstr 28 Oberpullendorf Burgenland 7350",
    "addr:housenumber":"28",
    "addr:postcode":"7350",
    "addr:street":"Hauptstr",
    "iso:country":"AT",
    "sg:address":"Hauptstr 28",
    "sg:city":"Oberpullendorf",
    "sg:orig_category":"Textilwaren / Einzelhandel",
    "sg:phone":"+43 2612 42609",
    "sg:postcode":"7350",
    "sg:province":"Burgenland",
    "wof:name":"Jeitler Andreas Ing Woll- und Seidenweberei GesmbH",
    "wof:placetype":"venue"
},
  "geometry": {"coordinates":[16.5055732727,47.5003204346],"type":"Point"}
}