{
  "type": "Feature",
  "properties": {
    "addr:full":"Sommerg 3/14 Wien Wien 1190",
    "addr:housenumber":"3 / 14",
    "addr:postcode":"1190",
    "addr:street":"Sommerg",
    "iso:country":"AT",
    "sg:address":"Sommerg 3/14",
    "sg:city":"Wien",
    "sg:orig_category":"\u00c3\u201erzte / F Allgemeinmedizin",
    "sg:phone":"+43 1 3694222",
    "sg:postcode":"1190",
    "sg:province":"Wien",
    "wof:name":"Exel Wolfgang Dr",
    "wof:placetype":"venue"
},
  "geometry": {"coordinates":[16.3537425995,48.2350387573],"type":"Point"}
}