{
  "type": "Feature",
  "properties": {
    "addr:full":"Kircheng 3 Stinatz Burgenland 7552",
    "addr:housenumber":"3",
    "addr:postcode":"7552",
    "addr:street":"Kircheng",
    "iso:country":"AT",
    "sg:address":"Kircheng 3",
    "sg:city":"Stinatz",
    "sg:orig_category":"Weine / Einzelhandel",
    "sg:phone":"+43 3358 2426",
    "sg:postcode":"7552",
    "sg:province":"Burgenland",
    "wof:name":"Stipsits Georg",
    "wof:placetype":"venue"
},
  "geometry": {"coordinates":[16.1328601837,47.203250885],"type":"Point"}
}