{
  "type": "Feature",
  "properties": {
    "iso:country":"AT",
    "sg:address":"Siedlungsstr. 10 ",
    "sg:city":"Haiming",
    "sg:classifiers":[
        {
            "category":"Food & Beverages",
            "subcategory":"Groceries & Convenience Stores",
            "type":"Retail Goods"
        }
    ],
    "sg:phone":"+43 4352 6688326",
    "sg:postcode":"6425",
    "sg:province":"Tirol",
    "sg:tags":[
        "product",
        "related"
    ],
    "wof:name":"EWALD H\u00d6PPERGER MIETGES.",
    "wof:placetype":"venue"
},
  "geometry": {"coordinates":[10.8802490234,47.2554473877],"type":"Point"}
}