{
  "type": "Feature",
  "properties": {
    "addr:full":"Rosenegg 61 Fieberbrunn Tirol 6391",
    "addr:housenumber":"61",
    "addr:postcode":"6391",
    "addr:street":"Rosenegg;Tirol",
    "iso:country":"AT",
    "sg:address":"Rosenegg 61",
    "sg:city":"Fieberbrunn",
    "sg:classifiers":[
        {
            "category":"Restaurant",
            "type":"Food & Drink"
        }
    ],
    "sg:phone":"+43 5354 56442",
    "sg:postcode":"6391",
    "sg:province":"Tirol",
    "wof:name":"Restaurant La Pampa",
    "wof:placetype":"venue"
},
  "geometry": {"coordinates":[12.5307435989,47.4868240356],"type":"Point"}
}