{
  "type": "Feature",
  "properties": {
    "iso:country":"AT",
    "sg:address":"Naarner Str 30a",
    "sg:city":"Perg",
    "sg:orig_category":"Abdichtungen",
    "sg:phone":"+43 4372 6257108",
    "sg:postcode":"4320",
    "sg:province":"Ober\u00f6sterreich",
    "wof:name":"DEMAN Feuchtigkeitsabdichtungen & Porositbeschichtungen",
    "wof:placetype":"venue"
},
  "geometry": {"coordinates":[14.6286764145,48.246509552],"type":"Point"}
}