{
  "type": "Feature",
  "properties": {
    "addr:full":"Lindhofstr 6 Salzburg Salzburg 5020",
    "addr:housenumber":"6",
    "addr:postcode":"5020",
    "addr:street":"Lindhofstr;Salzburg",
    "iso:country":"AT",
    "sg:address":"Lindhofstr 6",
    "sg:city":"Salzburg",
    "sg:orig_category":"Blumeneinzelhandel",
    "sg:phone":"+43 662 435891",
    "sg:postcode":"5020",
    "sg:province":"Salzburg",
    "wof:name":"Feichtenschlager Paul",
    "wof:placetype":"venue"
},
  "geometry": {"coordinates":[13.031999588,47.8051261902],"type":"Point"}
}