{
  "type": "Feature",
  "properties": {
    "addr:full":"Stockerauer Str 31 Korneuburg Nieder\u00f6sterreich 2100",
    "addr:postcode":"2100",
    "addr:street":"Str 31",
    "iso:country":"AT",
    "sg:address":"Stockerauer Str 31",
    "sg:city":"Korneuburg",
    "sg:orig_category":"Banken U Sparkassen",
    "sg:phone":"+43 4322 6261081",
    "sg:postcode":"2100",
    "sg:province":"Nieder\u00f6sterreich",
    "wof:name":"Bankomat der Volksbank Donau-Weinland regGenmbH",
    "wof:placetype":"venue"
},
  "geometry": {"coordinates":[16.3305797577,48.345500946],"type":"Point"}
}