{
  "type": "Feature",
  "properties": {
    "iso:country":"AT",
    "sg:address":"Dorf 40",
    "sg:city":"Niederndorf",
    "sg:orig_category":"Biologische Produkte",
    "sg:phone":"+43 664 1511261",
    "sg:postcode":"6342",
    "sg:province":"Tirol",
    "wof:name":"Rudig's Landprodukte",
    "wof:placetype":"venue"
},
  "geometry": {"coordinates":[12.2162857056,47.6501083374],"type":"Point"}
}