{
  "type": "Feature",
  "properties": {
    "addr:full":"Bundesstr 45  Weiz Steiermark 8160",
    "addr:housenumber":"45",
    "addr:postcode":"8160",
    "addr:street":"Bundesstr",
    "iso:country":"AT",
    "sg:address":"Bundesstr 45 ",
    "sg:city":"Weiz",
    "sg:classifiers":[
        {
            "category":"Manufacturing",
            "subcategory":"Rubber & Plastics",
            "type":"Manufacturing & Wholesale Goods"
        }
    ],
    "sg:phone":"+43 4331 722340",
    "sg:postcode":"8160",
    "sg:province":"Steiermark",
    "wof:name":"TEKO PLASTIC GMBH",
    "wof:placetype":"venue"
},
  "geometry": {"coordinates":[15.6215696335,47.2169532776],"type":"Point"}
}