{
  "type": "Feature",
  "properties": {
    "addr:full":"Puchheimer Str 40 Attnang-Puchheim Ober\u00f6sterreich 4800",
    "addr:housenumber":"40",
    "addr:postcode":"4800",
    "addr:street":"Puchheimer Str",
    "iso:country":"AT",
    "sg:address":"Puchheimer Str 40",
    "sg:city":"Attnang-Puchheim",
    "sg:orig_category":"Bestattungsunternehmen",
    "sg:phone":"+43 767464284",
    "sg:postcode":"4800",
    "sg:province":"Ober\u00f6sterreich",
    "wof:name":"Hauser Karl",
    "wof:placetype":"venue"
},
  "geometry": {"coordinates":[13.7158336639,48.002784729],"type":"Point"}
}