{
  "type": "Feature",
  "properties": {
    "iso:country":"AT",
    "sg:address":"Haiden 171",
    "sg:city":"Bad Ischl",
    "sg:orig_category":"Landwirtschaftliche Produkte",
    "sg:phone":"+43 6132 230540",
    "sg:postcode":"4820",
    "sg:province":"Ober\u00f6sterreich",
    "wof:name":"Unterberger Hans GesmbH & Co KG",
    "wof:placetype":"venue"
},
  "geometry": {"coordinates":[13.5800170898,47.7264595032],"type":"Point"}
}