{
  "type": "Feature",
  "properties": {
    "addr:full":"Walterstr 1 Gm\u00fcnd Nieder\u00f6sterreich 3950",
    "addr:housenumber":"1",
    "addr:postcode":"3950",
    "addr:street":"Walterstr;Niederoesterreich",
    "iso:country":"AT",
    "sg:address":"Walterstr 1",
    "sg:city":"Gm\u00fcnd",
    "sg:orig_category":"Zahngesundheitsvorsorge",
    "sg:phone":"+43 2852 525660660",
    "sg:postcode":"3950",
    "sg:province":"Nieder\u00f6sterreich",
    "wof:name":"Zahnambulatorium d Nieder\u00f6sterr Gebietskrankenkasse",
    "wof:placetype":"venue"
},
  "geometry": {"coordinates":[14.9864187241,48.7715492249],"type":"Point"}
}