{
  "type": "Feature",
  "properties": {
    "addr:full":"La\u00dfberg 5 Lochen Ober\u00f6sterreich 5221",
    "addr:housenumber":"5",
    "addr:postcode":"5221",
    "addr:street":"Lassberg",
    "iso:country":"AT",
    "sg:address":"La\u00dfberg 5",
    "sg:city":"Lochen",
    "sg:orig_category":"Psychotherapie",
    "sg:phone":"+43 7745 8963",
    "sg:postcode":"5221",
    "sg:province":"Ober\u00f6sterreich",
    "wof:name":"Moore-Moser Brigitte",
    "wof:placetype":"venue"
},
  "geometry": {"coordinates":[13.1802692413,48.0075187683],"type":"Point"}
}