{
  "type": "Feature",
  "properties": {
    "iso:country":"AT",
    "sg:address":"Paris Lodron-Str 22",
    "sg:city":"Salzburg",
    "sg:orig_category":"Immobilienmakler",
    "sg:phone":"+43 662 845247",
    "sg:postcode":"5020",
    "sg:province":"Salzburg",
    "wof:name":"Lichtenegger Karl Dr",
    "wof:placetype":"venue"
},
  "geometry": {"coordinates":[13.0485267639,47.8059043884],"type":"Point"}
}