{
  "type": "Feature",
  "properties": {
    "addr:full":"Klampfererweg 12 Bad Hofgastein Salzburg 5630",
    "addr:housenumber":"12",
    "addr:postcode":"5630",
    "addr:street":"Klampfererweg;Salzburg",
    "iso:country":"AT",
    "sg:address":"Klampfererweg 12",
    "sg:city":"Bad Hofgastein",
    "sg:orig_category":"Appartements / Ferienwohnungen",
    "sg:phone":"+43 6432 8482",
    "sg:postcode":"5630",
    "sg:province":"Salzburg",
    "wof:name":"Landhaus Grie\u00dfer",
    "wof:placetype":"venue"
},
  "geometry": {"coordinates":[13.106637001,47.1735839844],"type":"Point"}
}