{
  "type": "Feature",
  "properties": {
    "addr:full":"Badg 303 Alland Nieder\u00f6sterreich 2534",
    "addr:housenumber":"303;2534",
    "addr:street":"Alland Niederoesterreich",
    "iso:country":"AT",
    "sg:address":"Badg 303",
    "sg:city":"Alland",
    "sg:classifiers":[
        {
            "category":"Personal",
            "subcategory":"Sauna",
            "type":"Services"
        }
    ],
    "sg:phone":"+43 4322 582430",
    "sg:postcode":"2534",
    "sg:province":"Nieder\u00f6sterreich",
    "sg:tags":[
        "u",
        "dampfbad"
    ],
    "wof:name":"Sauna Alland",
    "wof:placetype":"venue"
},
  "geometry": {"coordinates":[16.0783996582,48.0584259033],"type":"Point"}
}