{
  "type": "Feature",
  "properties": {
    "addr:full":"Hohenauerg 7 Wien Wien 1190",
    "addr:housenumber":"7",
    "addr:postcode":"1190",
    "addr:street":"Hohenauerg",
    "iso:country":"AT",
    "sg:address":"Hohenauerg 7",
    "sg:city":"Wien",
    "sg:orig_category":"Immobilienmakler",
    "sg:phone":"+43 1 32840440",
    "sg:postcode":"1190",
    "sg:province":"Wien",
    "wof:name":"WMR Immobilienmakler GmbH",
    "wof:placetype":"venue"
},
  "geometry": {"coordinates":[16.3468494415,48.2448921204],"type":"Point"}
}