{
  "type": "Feature",
  "properties": {
    "addr:full":"Hugo-Wollner-Strasse 5 Blumau-Neuri\u00dfhof Nieder\u00f6sterreich 2602",
    "addr:housenumber":"5;2602",
    "addr:street":"Hugo-Wollner-Strasse;Niederoesterreich",
    "iso:country":"AT",
    "sg:address":"Hugo-Wollner-Strasse 5",
    "sg:city":"Blumau-Neuri\u00dfhof",
    "sg:classifiers":[
        {
            "category":"Government",
            "subcategory":"Fire Station",
            "type":"Public Place"
        }
    ],
    "sg:phone":"+43 2628 48901",
    "sg:postcode":"2602",
    "sg:province":"Nieder\u00f6sterreich",
    "sg:tags":[
        "steel",
        "chimney"
    ],
    "wof:name":"Josef Maier Ges.m.b.H.",
    "wof:placetype":"venue"
},
  "geometry": {"coordinates":[16.3010654449,47.9223175049],"type":"Point"}
}