{
  "type": "Feature",
  "properties": {
    "addr:full":"Dorf 11 Lech Vorarlberg 6764",
    "addr:housenumber":"11",
    "addr:postcode":"6764",
    "addr:street":"Dorf",
    "iso:country":"AT",
    "sg:address":"Dorf 11",
    "sg:city":"Lech",
    "sg:orig_category":"Blumeneinzelhandel",
    "sg:phone":"+43 5583 41852",
    "sg:postcode":"6764",
    "sg:province":"Vorarlberg",
    "wof:name":"Blumen-Kopf GesmbH & Co KG",
    "wof:placetype":"venue"
},
  "geometry": {"coordinates":[10.1413106918,47.207408905],"type":"Point"}
}