{
  "type": "Feature",
  "properties": {
    "addr:full":"Grie\u00dfbachweg 301 Kitzb\u00fchel Tirol 6370",
    "addr:housenumber":"301",
    "addr:postcode":"6370",
    "addr:street":"Kitzbuehel Tirol",
    "iso:country":"AT",
    "sg:address":"Grie\u00dfbachweg 301",
    "sg:city":"Kitzb\u00fchel",
    "sg:orig_category":"Pensionen / Privatzimmer",
    "sg:phone":"+43 5356 65272",
    "sg:postcode":"6370",
    "sg:province":"Tirol",
    "wof:name":"Pension Zimmermann",
    "wof:placetype":"venue"
},
  "geometry": {"coordinates":[12.3514947891,47.4643859863],"type":"Point"}
}