{
  "type": "Feature",
  "properties": {
    "addr:full":"Murau 50 St. Georgen ob Murau Steiermark 8861",
    "addr:housenumber":"50",
    "addr:postcode":"8861",
    "addr:street":"St.",
    "iso:country":"AT",
    "sg:address":"Murau 50",
    "sg:city":"St. Georgen ob Murau",
    "sg:classifiers":[
        {
            "category":"Utilities",
            "subcategory":"Fuel Oil & Lpg",
            "type":"Services"
        }
    ],
    "sg:phone":"+43 3537 234",
    "sg:postcode":"8861",
    "sg:province":"Steiermark",
    "sg:tags":[
        "blasting",
        "explosive"
    ],
    "sg:website":"pain-beraus.at",
    "wof:name":"Pain-Beraus GmbH",
    "wof:placetype":"venue"
},
  "geometry": {"coordinates":[14.0995817184,47.1049461365],"type":"Point"}
}