{
  "type": "Feature",
  "properties": {
    "iso:country":"AT",
    "sg:address":"Untere Hauptstr 62",
    "sg:city":"Jois",
    "sg:orig_category":"Appartements / Ferienwohnungen",
    "sg:phone":"+43 2160 8324",
    "sg:postcode":"7093",
    "sg:province":"Burgenland",
    "wof:name":"Altenburger Matthias",
    "wof:placetype":"venue"
},
  "geometry": {"coordinates":[16.7962837219,47.9603271484],"type":"Point"}
}