{
  "type": "Feature",
  "properties": {
    "addr:full":"Ennser Str 83 Gleink Ober\u00f6sterreich 4407",
    "addr:housenumber":"83",
    "addr:postcode":"4407",
    "addr:street":"Str",
    "iso:country":"AT",
    "sg:address":"Ennser Str 83",
    "sg:city":"Gleink",
    "sg:orig_category":"Holdinggesellschaften",
    "sg:phone":"+43 7252 727910",
    "sg:postcode":"4407",
    "sg:province":"Ober\u00f6sterreich",
    "wof:name":"Braunsberger Holding GmbH",
    "wof:placetype":"venue"
},
  "geometry": {"coordinates":[14.4258317947,48.0778770447],"type":"Point"}
}