{
  "type": "Feature",
  "properties": {
    "iso:country":"AT",
    "sg:address":"Nr 2",
    "sg:city":"Eisentratten",
    "sg:orig_category":"Transportunternehmen",
    "sg:phone":"+43 4732 2773",
    "sg:postcode":"9861",
    "sg:province":"K\u00e4rnten",
    "wof:name":"Wandaller Ernst",
    "wof:placetype":"venue"
},
  "geometry": {"coordinates":[13.5780506134,46.9226989746],"type":"Point"}
}