{
  "type": "Feature",
  "properties": {
    "addr:full":"Nr 2 Eisentratten K\u00e4rnten 9861",
    "addr:postcode":"9861",
    "addr:street":"Nr;Eisentratten",
    "iso:country":"AT",
    "sg:address":"Nr 2",
    "sg:city":"Eisentratten",
    "sg:orig_category":"Transportunternehmen",
    "sg:phone":"+43 4732 2773",
    "sg:postcode":"9861",
    "sg:province":"K\u00e4rnten",
    "wof:name":"Wandaller Ernst",
    "wof:placetype":"venue"
},
  "geometry": {"coordinates":[13.5780506134,46.9226989746],"type":"Point"}
}