{
  "type": "Feature",
  "properties": {
    "addr:full":"Bahnstr 8 Parndorf Burgenland 7111",
    "addr:housenumber":"8",
    "addr:postcode":"7111",
    "addr:street":"Bahnstr",
    "iso:country":"AT",
    "sg:address":"Bahnstr 8",
    "sg:city":"Parndorf",
    "sg:orig_category":"Zimmereien",
    "sg:phone":"+43 2166 2322",
    "sg:postcode":"7111",
    "sg:province":"Burgenland",
    "wof:name":"Weber Franz Ing",
    "wof:placetype":"venue"
},
  "geometry": {"coordinates":[16.8590679169,47.9909591675],"type":"Point"}
}