{
  "type": "Feature",
  "properties": {
    "iso:country":"AT",
    "sg:address":"Hirschmillerstr. 38",
    "sg:city":"Ernstbrunn",
    "sg:classifiers":[
        {
            "category":"Wholesale",
            "subcategory":"Machinery & Supplies",
            "type":"Manufacturing & Wholesale Goods"
        }
    ],
    "sg:phone":"+43 4325 762476",
    "sg:postcode":"2115",
    "sg:province":"Nieder\u00f6sterreich",
    "sg:tags":[
        "equipment",
        "-",
        "instrument",
        "measurement"
    ],
    "wof:name":"DIETER NENTWIG GESMBH",
    "wof:placetype":"venue"
},
  "geometry": {"coordinates":[16.3729972839,48.5249519348],"type":"Point"}
}