{
  "type": "Feature",
  "properties": {
    "addr:full":"Marktpl 58 Hallstatt Ober\u00f6sterreich 4830",
    "addr:housenumber":"58",
    "addr:postcode":"4830",
    "addr:street":"Marktpl",
    "iso:country":"AT",
    "sg:address":"Marktpl 58",
    "sg:city":"Hallstatt",
    "sg:orig_category":"Banken U Sparkassen",
    "sg:phone":"+43 4361 3485070",
    "sg:postcode":"4830",
    "sg:province":"Ober\u00f6sterreich",
    "wof:name":"Sparkasse Bad Ischl AG - Zweigst Hallstatt",
    "wof:placetype":"venue"
},
  "geometry": {"coordinates":[13.6487932205,47.562286377],"type":"Point"}
}