{
  "type": "Feature",
  "properties": {
    "addr:full":"Fabriksgel\u00e4nde 1 Siegendorf im Burgenland Burgenland 7011",
    "addr:housenumber":"1",
    "addr:postcode":"7011",
    "addr:street":"Fabriksgelaende",
    "iso:country":"AT",
    "sg:address":"Fabriksgel\u00e4nde 1",
    "sg:city":"Siegendorf im Burgenland",
    "sg:orig_category":"Gewerbeparks",
    "sg:phone":"+43 4326 87481800",
    "sg:postcode":"7011",
    "sg:province":"Burgenland",
    "wof:name":"Gewerbezone Ost Errichtungs- u BetriebsgesmbH",
    "wof:placetype":"venue"
},
  "geometry": {"coordinates":[16.5153503418,47.7649040222],"type":"Point"}
}