{
  "type": "Feature",
  "properties": {
    "iso:country":"AT",
    "sg:address":"Lamezanstrasse 7",
    "sg:city":"Wien",
    "sg:classifiers":[
        {
            "category":"Manufacturing",
            "subcategory":"Wood Products",
            "type":"Manufacturing & Wholesale Goods"
        }
    ],
    "sg:phone":"+43 1 614200",
    "sg:postcode":"1230",
    "sg:province":"Wien",
    "sg:tags":[
        "lumber"
    ],
    "sg:website":"lichtenstein.co.at",
    "wof:name":"LIECHTENSTEIN - Holzhandelsges.m.b.H.",
    "wof:placetype":"venue"
},
  "geometry": {"coordinates":[16.3390426636,48.1402130127],"type":"Point"}
}