{
  "type": "Feature",
  "properties": {
    "addr:full":"Aupoint 5  Bergheim Salzburg 5101",
    "addr:housenumber":"5",
    "addr:postcode":"5101",
    "addr:street":"Aupoint;Salzburg",
    "iso:country":"AT",
    "sg:address":"Aupoint 5 ",
    "sg:city":"Bergheim",
    "sg:classifiers":[
        {
            "category":"Manufacturing",
            "subcategory":"Metals",
            "type":"Manufacturing & Wholesale Goods"
        }
    ],
    "sg:phone":"+43 4366 2452070",
    "sg:postcode":"5101",
    "sg:province":"Salzburg",
    "sg:tags":[
        "processing"
    ],
    "wof:name":"BERGHEIMER VERZINKEREI GES.MBH & CO KG",
    "wof:placetype":"venue"
},
  "geometry": {"coordinates":[13.010014534,47.8643608093],"type":"Point"}
}