{
  "type": "Feature",
  "properties": {
    "iso:country":"AT",
    "sg:address":"Vorderstoder 63",
    "sg:city":"Vorderstoder",
    "sg:classifiers":[
        {
            "category":"Home & Garden",
            "subcategory":"Furniture",
            "type":"Retail Goods"
        }
    ],
    "sg:phone":"+43 7564 8306",
    "sg:postcode":"4574",
    "sg:province":"Ober\u00f6sterreich",
    "sg:tags":[
        "bathroom"
    ],
    "wof:name":"Friederike Rohregger",
    "wof:placetype":"venue"
},
  "geometry": {"coordinates":[14.194893837,47.7200202942],"type":"Point"}
}