{
  "type": "Feature",
  "properties": {
    "iso:country":"AT",
    "sg:address":"Knappenweg 1",
    "sg:city":"Voitsberg",
    "sg:classifiers":[
        {
            "category":"Manufacturing",
            "subcategory":"Metals",
            "type":"Manufacturing & Wholesale Goods"
        }
    ],
    "sg:phone":"+43 3142 23749",
    "sg:postcode":"8570",
    "sg:province":"Steiermark",
    "sg:tags":[
        "aluminium",
        "sheet",
        "strip"
    ],
    "wof:name":"Harald Huberts",
    "wof:placetype":"venue"
},
  "geometry": {"coordinates":[15.1561183929,47.0488586426],"type":"Point"}
}