{
  "type": "Feature",
  "properties": {
    "addr:full":"Untermarendebach 3a Gries im Sellrain Tirol 6182",
    "addr:housenumber":"3a",
    "addr:postcode":"6182",
    "addr:street":"Untermarendebach;Tirol",
    "iso:country":"AT",
    "sg:address":"Untermarendebach 3a",
    "sg:city":"Gries im Sellrain",
    "sg:orig_category":"Imkereien",
    "sg:phone":"+43 5236 454",
    "sg:postcode":"6182",
    "sg:province":"Tirol",
    "wof:name":"Baier Helga",
    "wof:placetype":"venue"
},
  "geometry": {"coordinates":[11.100684166,47.2032012939],"type":"Point"}
}