{
  "type": "Feature",
  "properties": {
    "addr:full":"Ottakringer Strasse 58 Wien Wien 1170",
    "addr:housenumber":"58",
    "addr:postcode":"1170",
    "addr:street":"Ottakringer Strasse",
    "iso:country":"AT",
    "sg:address":"Ottakringer Strasse 58",
    "sg:city":"Wien",
    "sg:classifiers":[
        {
            "category":"Home & Garden",
            "subcategory":"Building Materials",
            "type":"Retail Goods"
        }
    ],
    "sg:phone":"+43 1 4038547",
    "sg:postcode":"1170",
    "sg:province":"Wien",
    "sg:tags":[
        "tile",
        "ceramic"
    ],
    "sg:website":"come.to/alfredszekely",
    "wof:name":"Alfred Szekely",
    "wof:placetype":"venue"
},
  "geometry": {"coordinates":[16.3328456879,48.2144851685],"type":"Point"}
}