{
  "type": "Feature",
  "properties": {
    "iso:country":"AT",
    "sg:address":"Radingerstr 6",
    "sg:city":"Wien",
    "sg:orig_category":"Autoreparatur",
    "sg:phone":"+43 1 7281840",
    "sg:postcode":"1020",
    "sg:province":"Wien",
    "wof:name":"Kaspar Klaus",
    "wof:placetype":"venue"
},
  "geometry": {"coordinates":[16.4005126953,48.222820282],"type":"Point"}
}