{
  "type": "Feature",
  "properties": {
    "addr:full":"Spittelauer L\u00e4nde 29 Wien Wien 1090",
    "addr:housenumber":"29",
    "addr:postcode":"1090",
    "iso:country":"AT",
    "sg:address":"Spittelauer L\u00e4nde 29",
    "sg:city":"Wien",
    "sg:orig_category":"Spenglereien",
    "sg:phone":"+43 1 3170240",
    "sg:postcode":"1090",
    "sg:province":"Wien",
    "wof:name":"IRIK Cebar KEG",
    "wof:placetype":"venue"
},
  "geometry": {"coordinates":[16.3615894318,48.2306556702],"type":"Point"}
}