{
  "type": "Feature",
  "properties": {
    "addr:full":"Nr. 90  Leibnitz Steiermark 8430",
    "addr:postcode":"8430",
    "iso:country":"AT",
    "sg:address":"Nr. 90 ",
    "sg:city":"Leibnitz",
    "sg:classifiers":[
        {
            "category":"Autos & Motor Vehicles",
            "subcategory":"Automobile Sales",
            "type":"Retail Goods"
        }
    ],
    "sg:phone":"+43 4334 5284934",
    "sg:postcode":"8430",
    "sg:province":"Steiermark",
    "sg:tags":[
        "motor-cars"
    ],
    "wof:name":"STERNAD GESMBH & CO KG",
    "wof:placetype":"venue"
},
  "geometry": {"coordinates":[15.5377645493,46.7811355591],"type":"Point"}
}