{
  "type": "Feature",
  "properties": {
    "addr:full":"Nr 35 Dellach im Drautal K\u00e4rnten 9772",
    "addr:postcode":"9772",
    "addr:street":"Nr;Dellach",
    "iso:country":"AT",
    "sg:address":"Nr 35",
    "sg:city":"Dellach im Drautal",
    "sg:orig_category":"Bauunternehmen",
    "sg:phone":"+43 4714 241",
    "sg:postcode":"9772",
    "sg:province":"K\u00e4rnten",
    "wof:name":"Machne Peter Inh Ing Peter Fina",
    "wof:placetype":"venue"
},
  "geometry": {"coordinates":[13.0824251175,46.7413406372],"type":"Point"}
}