{
  "type": "Feature",
  "properties": {
    "iso:country":"AT",
    "sg:address":"Flurg 1",
    "sg:city":"Gleisdorf",
    "sg:orig_category":"Psychotherapie",
    "sg:phone":"+43 4366 43801248",
    "sg:postcode":"8200",
    "sg:province":"Steiermark",
    "wof:name":"Wilding Mario",
    "wof:placetype":"venue"
},
  "geometry": {"coordinates":[15.7109699249,47.1018981934],"type":"Point"}
}