{
  "type": "Feature",
  "properties": {
    "addr:full":"Hauptstr 26 St. Johann im Pongau Salzburg 5600",
    "addr:housenumber":"26",
    "addr:postcode":"5600",
    "addr:street":"Hauptstr;Salzburg",
    "iso:country":"AT",
    "sg:address":"Hauptstr 26",
    "sg:city":"St. Johann im Pongau",
    "sg:orig_category":"Versicherungsunternehmen",
    "sg:phone":"+43 6412 43010",
    "sg:postcode":"5600",
    "sg:province":"Salzburg",
    "wof:name":"Generali Versicherung AG",
    "wof:placetype":"venue"
},
  "geometry": {"coordinates":[13.2028837204,47.3494262695],"type":"Point"}
}