{
  "type": "Feature",
  "properties": {
    "addr:full":"Willersdorfer Str 67 St. Radegund Steiermark 8061",
    "addr:housenumber":"67",
    "addr:postcode":"8061",
    "addr:street":"Str",
    "iso:country":"AT",
    "sg:address":"Willersdorfer Str 67",
    "sg:city":"St. Radegund",
    "sg:orig_category":"Tankstellen",
    "sg:phone":"+43 4331 323501",
    "sg:postcode":"8061",
    "sg:province":"Steiermark",
    "wof:name":"M\u00f6stl Friedrich - Tankstelle-Landtechnik",
    "wof:placetype":"venue"
},
  "geometry": {"coordinates":[15.5027999878,47.1945724487],"type":"Point"}
}