{
  "type": "Feature",
  "properties": {
    "addr:full":"Andreas Hofer-Str 2 Kufstein Tirol 6330",
    "addr:housenumber":"2",
    "addr:postcode":"6330",
    "addr:street":"Tirol",
    "iso:country":"AT",
    "sg:address":"Andreas Hofer-Str 2",
    "sg:city":"Kufstein",
    "sg:orig_category":"Bestattungsunternehmen",
    "sg:phone":"+43 5372 6231530",
    "sg:postcode":"6330",
    "sg:province":"Tirol",
    "wof:name":"Bestattung Z\u00f6ttl Otto",
    "wof:placetype":"venue"
},
  "geometry": {"coordinates":[12.1734447479,47.5827178955],"type":"Point"}
}