{
  "type": "Feature",
  "properties": {
    "addr:full":"Hauserstr 10 Natternbach Ober\u00f6sterreich 4723",
    "addr:housenumber":"10",
    "addr:postcode":"4723",
    "addr:street":"Hauserstr",
    "iso:country":"AT",
    "sg:address":"Hauserstr 10",
    "sg:city":"Natternbach",
    "sg:orig_category":"Tankstellen",
    "sg:phone":"+43 7943 8227",
    "sg:postcode":"4723",
    "sg:province":"Ober\u00f6sterreich",
    "wof:name":"Shell Austria GmbH",
    "wof:placetype":"venue"
},
  "geometry": {"coordinates":[13.7493047714,48.394695282],"type":"Point"}
}