{
  "type": "Feature",
  "properties": {
    "addr:full":"Unterer Stadtpl 6 Waidhofen an der Ybbs Nieder\u00f6sterreich 3340",
    "addr:housenumber":"6",
    "addr:postcode":"3340",
    "addr:street":"Unterer Stadtpl",
    "iso:country":"AT",
    "sg:address":"Unterer Stadtpl 6",
    "sg:city":"Waidhofen an der Ybbs",
    "sg:orig_category":"Fotoapparate U -Artikel / Einzelhandel",
    "sg:phone":"+43 4374 42524630",
    "sg:postcode":"3340",
    "sg:province":"Nieder\u00f6sterreich",
    "wof:name":"Hartlauer HandelsgesmbH",
    "wof:placetype":"venue"
},
  "geometry": {"coordinates":[14.7736129761,47.9610328674],"type":"Point"}
}