{
  "type": "Feature",
  "properties": {
    "iso:country":"AT",
    "sg:address":"Oberrotte 89",
    "sg:city":"St. Jakob in Defereggen",
    "sg:orig_category":"Physiotherapie",
    "sg:phone":"+43 4348 735541",
    "sg:postcode":"9963",
    "sg:province":"Tirol",
    "wof:name":"Fabich Ulrike",
    "wof:placetype":"venue"
},
  "geometry": {"coordinates":[12.292140007,46.9098014832],"type":"Point"}
}