{
  "type": "Feature",
  "properties": {
    "addr:full":"Badener Str 14 Oberwaltersdorf Nieder\u00f6sterreich 2522",
    "addr:housenumber":"14",
    "addr:postcode":"2522",
    "addr:street":"Badener Str",
    "iso:country":"AT",
    "sg:address":"Badener Str 14",
    "sg:city":"Oberwaltersdorf",
    "sg:orig_category":"Puppen",
    "sg:phone":"+43 2253 6413",
    "sg:postcode":"2522",
    "sg:province":"Nieder\u00f6sterreich",
    "wof:name":"Mayer Karoline",
    "wof:placetype":"venue"
},
  "geometry": {"coordinates":[16.3215713501,47.9777030945],"type":"Point"}
}