{
  "type": "Feature",
  "properties": {
    "addr:full":"Oberhauser Str 176 Haus Steiermark 8967",
    "addr:housenumber":"176",
    "addr:postcode":"8967",
    "addr:street":"Haus",
    "iso:country":"AT",
    "sg:address":"Oberhauser Str 176",
    "sg:city":"Haus",
    "sg:orig_category":"Schlossereien",
    "sg:phone":"+43 4336 862503",
    "sg:postcode":"8967",
    "sg:province":"Steiermark",
    "wof:name":"Reiter Herbert",
    "wof:placetype":"venue"
},
  "geometry": {"coordinates":[13.7542915344,47.4072341919],"type":"Point"}
}