{
  "type": "Feature",
  "properties": {
    "addr:full":"Brunner Str 35 Waidhofen an der Thaya Nieder\u00f6sterreich 3830",
    "addr:postcode":"3830",
    "addr:street":"Str 35",
    "iso:country":"AT",
    "sg:address":"Brunner Str 35",
    "sg:city":"Waidhofen an der Thaya",
    "sg:orig_category":"Installationsunternehmen",
    "sg:phone":"+43 4328 42525750",
    "sg:postcode":"3830",
    "sg:province":"Nieder\u00f6sterreich",
    "sg:website":"schatzinsel.cc",
    "wof:name":"Krenn Gerald Ing",
    "wof:placetype":"venue"
},
  "geometry": {"coordinates":[15.2674074173,48.8115310669],"type":"Point"}
}