{
  "type": "Feature",
  "properties": {
    "addr:full":"Eichstr 17A Gnigl Salzburg 5023",
    "addr:housenumber":"17a",
    "addr:postcode":"5023",
    "addr:street":"Eichstr",
    "iso:country":"AT",
    "sg:address":"Eichstr 17A",
    "sg:city":"Gnigl",
    "sg:orig_category":"Schneidereien",
    "sg:phone":"+43 662 645569",
    "sg:postcode":"5023",
    "sg:province":"Salzburg",
    "wof:name":"Stadlbauer Renate",
    "wof:placetype":"venue"
},
  "geometry": {"coordinates":[13.0696020126,47.8092727661],"type":"Point"}
}