{
  "type": "Feature",
  "properties": {
    "iso:country":"AT",
    "sg:address":"Villacher Str 235",
    "sg:city":"Klagenfurt",
    "sg:orig_category":"Freizeitangebote U -Einrichtungen",
    "sg:phone":"+43 4346 323659",
    "sg:postcode":"9020",
    "sg:province":"K\u00e4rnten",
    "wof:name":"Freizeitzentrum Europapark",
    "wof:placetype":"venue"
},
  "geometry": {"coordinates":[14.2675962448,46.6198539734],"type":"Point"}
}