{
  "type": "Feature",
  "properties": {
    "addr:full":"Hernalser Hauptstr 36 Wien Wien 1170",
    "addr:housenumber":"36",
    "addr:postcode":"1170",
    "addr:street":"Hernalser Hauptstr",
    "iso:country":"AT",
    "sg:address":"Hernalser Hauptstr 36",
    "sg:city":"Wien",
    "sg:orig_category":"Tabaktrafiken",
    "sg:phone":"+43 1 4031849",
    "sg:postcode":"1170",
    "sg:province":"Wien",
    "wof:name":"Popp Herbert",
    "wof:placetype":"venue"
},
  "geometry": {"coordinates":[16.3377952576,48.2173461914],"type":"Point"}
}