{
  "type": "Feature",
  "properties": {
    "addr:full":"Stadionstr 23a Judenburg Steiermark 8750",
    "addr:housenumber":"23a",
    "addr:postcode":"8750",
    "addr:street":"Stadionstr",
    "iso:country":"AT",
    "sg:address":"Stadionstr 23a",
    "sg:city":"Judenburg",
    "sg:orig_category":"Beteiligungen U Finanzierungen",
    "sg:phone":"+43 664 2820976",
    "sg:postcode":"8750",
    "sg:province":"Steiermark",
    "wof:name":"s Immobilienfinanzierungsberatung GmbH",
    "wof:placetype":"venue"
},
  "geometry": {"coordinates":[14.6793603897,47.1775512695],"type":"Point"}
}