{
  "type": "Feature",
  "properties": {
    "iso:country":"AT",
    "sg:address":"Sonnfeld 8",
    "sg:city":"Rattenberg",
    "sg:orig_category":"Handelsagenturen",
    "sg:phone":"+43 4367 66043441",
    "sg:postcode":"6240",
    "sg:province":"Tirol",
    "wof:name":"Trobos Martin",
    "wof:placetype":"venue"
},
  "geometry": {"coordinates":[11.9058189392,47.4464416504],"type":"Point"}
}