{
  "type": "Feature",
  "properties": {
    "addr:full":"Gewerbestr 7 Gerasdorf Nieder\u00f6sterreich 2201",
    "addr:housenumber":"7",
    "addr:postcode":"2201",
    "addr:street":"Gewerbestr",
    "iso:country":"AT",
    "sg:address":"Gewerbestr 7",
    "sg:city":"Gerasdorf",
    "sg:orig_category":"Betriebseinrichtungen",
    "sg:phone":"+43 2246 34670",
    "sg:postcode":"2201",
    "sg:province":"Nieder\u00f6sterreich",
    "wof:name":"Alreg Stefancic GesmbH Betriebseinrichtungen",
    "wof:placetype":"venue"
},
  "geometry": {"coordinates":[16.4503173828,48.3317947388],"type":"Point"}
}