{
  "type": "Feature",
  "properties": {
    "addr:full":"Hauptstr 42 Gro\u00dfru\u00dfbach Nieder\u00f6sterreich 2114",
    "addr:housenumber":"42",
    "addr:postcode":"2114",
    "addr:street":"Hauptstr;Niederoesterreich",
    "iso:country":"AT",
    "sg:address":"Hauptstr 42",
    "sg:city":"Gro\u00dfru\u00dfbach",
    "sg:classifiers":[
        {
            "category":"Restaurant",
            "type":"Food & Drink"
        }
    ],
    "sg:phone":"+43 2263 6845",
    "sg:postcode":"2114",
    "sg:province":"Nieder\u00f6sterreich",
    "wof:name":"Marchesani Katharina",
    "wof:placetype":"venue"
},
  "geometry": {"coordinates":[16.4451026917,48.4629859924],"type":"Point"}
}