{
  "type": "Feature",
  "properties": {
    "iso:country":"AT",
    "sg:address":"Karl-Morre-Str 19",
    "sg:city":"Feldkirchen",
    "sg:orig_category":"Transportunternehmen",
    "sg:phone":"+43 664 1338509",
    "sg:postcode":"8073",
    "sg:province":"Steiermark",
    "wof:name":"Ru\u00df Josef",
    "wof:placetype":"venue"
},
  "geometry": {"coordinates":[15.4386024475,47.0114822388],"type":"Point"}
}