{
  "type": "Feature",
  "properties": {
    "iso:country":"AT",
    "sg:address":"Jakoministr 13",
    "sg:city":"Graz",
    "sg:orig_category":"Fleischhauereien",
    "sg:phone":"+43 316 827745",
    "sg:postcode":"8010",
    "sg:province":"Steiermark",
    "wof:name":"Zotter Christina & Gerhard OEG",
    "wof:placetype":"venue"
},
  "geometry": {"coordinates":[15.4424533844,47.0658760071],"type":"Point"}
}