{
  "type": "Feature",
  "properties": {
    "addr:full":"Mitterweg 118 Innsbruck Tirol 6020",
    "addr:housenumber":"118",
    "addr:postcode":"6020",
    "addr:street":"Mitterweg;Tirol",
    "iso:country":"AT",
    "sg:address":"Mitterweg 118",
    "sg:city":"Innsbruck",
    "sg:orig_category":"Telekommunikation",
    "sg:phone":"+43 512 272898",
    "sg:postcode":"6020",
    "sg:province":"Tirol",
    "wof:name":"riwitec rieck + winter oeg",
    "wof:placetype":"venue"
},
  "geometry": {"coordinates":[11.3652648926,47.2567138672],"type":"Point"}
}