{
  "type": "Feature",
  "properties": {
    "addr:full":"Kirchpl 4 Oberndorf Salzburg 5110",
    "addr:housenumber":"4",
    "addr:postcode":"5110",
    "addr:street":"Kirchpl",
    "iso:country":"AT",
    "sg:address":"Kirchpl 4",
    "sg:city":"Oberndorf",
    "sg:orig_category":"Fleischhauereien",
    "sg:phone":"+43 4362 724235",
    "sg:postcode":"5110",
    "sg:province":"Salzburg",
    "wof:name":"Ablinger Franz & Co Fleischhauereibetriebs GesmbH",
    "wof:placetype":"venue"
},
  "geometry": {"coordinates":[12.9431333542,47.9393386841],"type":"Point"}
}