{
  "type": "Feature",
  "properties": {
    "addr:full":"M\u00fchlg 3 Himberg Nieder\u00f6sterreich 2325",
    "addr:housenumber":"3",
    "addr:postcode":"2325",
    "addr:street":"Muehlg",
    "iso:country":"AT",
    "sg:address":"M\u00fchlg 3",
    "sg:city":"Himberg",
    "sg:orig_category":"Politische Parteien",
    "sg:phone":"+43 2235 84533",
    "sg:postcode":"2325",
    "sg:province":"Nieder\u00f6sterreich",
    "wof:name":"Sozialistische Partei \u00f6sterreichs",
    "wof:placetype":"venue"
},
  "geometry": {"coordinates":[16.4394855499,48.0822868347],"type":"Point"}
}