{
  "type": "Feature",
  "properties": {
    "addr:full":"G\u00fcrtelstr. 22 / A Linz Ober\u00f6sterreich 4020",
    "addr:housenumber":"22 / a",
    "addr:postcode":"4020",
    "addr:street":"Guertelstr.",
    "iso:country":"AT",
    "sg:address":"G\u00fcrtelstr. 22 / A",
    "sg:city":"Linz",
    "sg:classifiers":[
        {
            "category":"Autos & Motor Vehicles",
            "subcategory":"Automobile Sales",
            "type":"Retail Goods"
        }
    ],
    "sg:phone":"+43 4373 26511160",
    "sg:postcode":"4020",
    "sg:province":"Ober\u00f6sterreich",
    "sg:tags":[
        "motor-cars"
    ],
    "wof:name":"PAPINSKI-KAROSSERIE GES.MBH & CO KG",
    "wof:placetype":"venue"
},
  "geometry": {"coordinates":[14.2451400757,48.3018455505],"type":"Point"}
}