{
  "type": "Feature",
  "properties": {
    "addr:full":"Dorfbahnstr 38 Serfaus Tirol 6534",
    "addr:housenumber":"38",
    "addr:postcode":"6534",
    "addr:street":"Dorfbahnstr;Tirol",
    "iso:country":"AT",
    "sg:address":"Dorfbahnstr 38",
    "sg:city":"Serfaus",
    "sg:classifiers":[
        {
            "category":"Travel",
            "subcategory":"Hotels & Motels",
            "type":"Entertainment"
        }
    ],
    "sg:phone":"+43 5476 6264",
    "sg:postcode":"6534",
    "sg:province":"Tirol",
    "wof:name":"Hotel-Restaurant Rex",
    "wof:placetype":"venue"
},
  "geometry": {"coordinates":[10.6063785553,47.0387649536],"type":"Point"}
}