{
  "type": "Feature",
  "properties": {
    "iso:country":"AT",
    "sg:address":"Lugeck 2",
    "sg:city":"Wien",
    "sg:orig_category":"Optiker",
    "sg:phone":"+43 1 5331377",
    "sg:postcode":"1010",
    "sg:province":"Wien",
    "wof:name":"Lugeck Optik GmbH",
    "wof:placetype":"venue"
},
  "geometry": {"coordinates":[16.3747634888,48.2099761963],"type":"Point"}
}