{
  "type": "Feature",
  "properties": {
    "addr:full":"Wagramer Str 95 Wien Wien 1220",
    "addr:postcode":"1220",
    "addr:street":"Str 95",
    "iso:country":"AT",
    "sg:address":"Wagramer Str 95",
    "sg:city":"Wien",
    "sg:orig_category":"Friseure U Frisiersalons",
    "sg:phone":"+43 4312 049595",
    "sg:postcode":"1220",
    "sg:province":"Wien",
    "wof:name":"Allerbauer Karin - Trendcoiffeur",
    "wof:placetype":"venue"
},
  "geometry": {"coordinates":[16.437833786,48.2446937561],"type":"Point"}
}