{
  "type": "Feature",
  "properties": {
    "addr:full":"Schulg 7 Thaur Tirol 6065",
    "addr:housenumber":"7",
    "addr:postcode":"6065",
    "addr:street":"Schulg;Tirol",
    "iso:country":"AT",
    "sg:address":"Schulg 7",
    "sg:city":"Thaur",
    "sg:orig_category":"Volksschulen",
    "sg:phone":"+43 5223 49286122",
    "sg:postcode":"6065",
    "sg:province":"Tirol",
    "wof:name":"Volksschule",
    "wof:placetype":"venue"
},
  "geometry": {"coordinates":[11.4744997025,47.2922668457],"type":"Point"}
}