{
  "type": "Feature",
  "properties": {
    "addr:full":"Neud\u00f6rfler Str 3 Wiener Neustadt Nieder\u00f6sterreich 2700",
    "addr:postcode":"2700",
    "addr:street":"Str",
    "iso:country":"AT",
    "sg:address":"Neud\u00f6rfler Str 3",
    "sg:city":"Wiener Neustadt",
    "sg:classifiers":[
        {
            "category":"Restaurant",
            "type":"Food & Drink"
        }
    ],
    "sg:phone":"+43 4326 2261800",
    "sg:postcode":"2700",
    "sg:province":"Nieder\u00f6sterreich",
    "sg:tags":[
        "pizzeria"
    ],
    "wof:name":"Pizzeria Pepone",
    "wof:placetype":"venue"
},
  "geometry": {"coordinates":[16.2455158234,47.8128814697],"type":"Point"}
}