{
  "type": "Feature",
  "properties": {
    "addr:full":"Bockg 2b Linz Ober\u00f6sterreich 4020",
    "addr:housenumber":"2b",
    "addr:postcode":"4020",
    "addr:street":"Bockg",
    "iso:country":"AT",
    "sg:address":"Bockg 2b",
    "sg:city":"Linz",
    "sg:classifiers":[
        {
            "category":"Professional",
            "subcategory":"Computer Services",
            "type":"Services"
        }
    ],
    "sg:phone":"+43 732 668940",
    "sg:postcode":"4020",
    "sg:province":"Ober\u00f6sterreich",
    "sg:tags":[
        "software"
    ],
    "wof:name":"Braunbock Gerwin",
    "wof:placetype":"venue"
},
  "geometry": {"coordinates":[14.2843284607,48.2934494019],"type":"Point"}
}