{
  "type": "Feature",
  "properties": {
    "iso:country":"AT",
    "sg:address":"Kaiserebersdorfer Str 238",
    "sg:city":"Wien",
    "sg:orig_category":"Bastelbedarf",
    "sg:phone":"+43 4317 6764880",
    "sg:postcode":"1110",
    "sg:province":"Wien",
    "sg:website":"soergel.at",
    "wof:name":"S\u00f6rgel Rudolf GmbH",
    "wof:placetype":"venue"
},
  "geometry": {"coordinates":[16.456653595,48.1601448059],"type":"Point"}
}