{
  "type": "Feature",
  "properties": {
    "iso:country":"AT",
    "sg:address":"H\u00f6henstr 108",
    "sg:city":"Innsbruck",
    "sg:orig_category":"Architekten",
    "sg:phone":"+43 512 291834",
    "sg:postcode":"6020",
    "sg:province":"Tirol",
    "wof:name":"Grass G\u00fcnter Dipl-Ing Dr",
    "wof:placetype":"venue"
},
  "geometry": {"coordinates":[11.3965320587,47.2845649719],"type":"Point"}
}