{
  "type": "Feature",
  "properties": {
    "iso:country":"AT",
    "sg:address":"Ing.-Etzel-Strasse 30",
    "sg:city":"Innsbruck",
    "sg:orig_category":"Artworks, Digital",
    "sg:phone":"+43 5 0403",
    "sg:postcode":"6020",
    "sg:province":"Tirol",
    "sg:website":"tirol.com/tt/",
    "wof:name":"Intergraphik Ges.m.b.H.",
    "wof:placetype":"venue"
},
  "geometry": {"coordinates":[11.3895988464,47.2564315796],"type":"Point"}
}