{
  "type": "Feature",
  "properties": {
    "addr:full":"Gumpendorfer Str 22 Wien Wien 1060",
    "addr:postcode":"1060",
    "addr:street":"Str 22",
    "iso:country":"AT",
    "sg:address":"Gumpendorfer Str 22",
    "sg:city":"Wien",
    "sg:orig_category":"Blumeneinzelhandel",
    "sg:phone":"+43 1 5862514",
    "sg:postcode":"1060",
    "sg:province":"Wien",
    "wof:name":"Blumen Czihal-Steinhauser",
    "wof:placetype":"venue"
},
  "geometry": {"coordinates":[16.3595523834,48.1994934082],"type":"Point"}
}