{
  "type": "Feature",
  "properties": {
    "iso:country":"AT",
    "sg:address":"Linzer Str 21",
    "sg:city":"Prinzersdorf",
    "sg:orig_category":"Werbeagenturen",
    "sg:phone":"+43 4327 4930175",
    "sg:postcode":"3385",
    "sg:province":"Nieder\u00f6sterreich",
    "wof:name":"Aussenwerbung Media GmbH",
    "wof:placetype":"venue"
},
  "geometry": {"coordinates":[15.5117378235,48.2008743286],"type":"Point"}
}