{
  "type": "Feature",
  "properties": {
    "iso:country":"AT",
    "sg:address":"Sch\u00f6nbrunner Str 38",
    "sg:city":"Wien",
    "sg:orig_category":"Blumeneinzelhandel",
    "sg:phone":"+43 1 5813478",
    "sg:postcode":"1050",
    "sg:province":"Wien",
    "wof:name":"Blumen B & B R Bigl GesmbH",
    "wof:placetype":"venue"
},
  "geometry": {"coordinates":[16.3584918976,48.19165802],"type":"Point"}
}