{
  "type": "Feature",
  "properties": {
    "iso:country":"AT",
    "sg:address":"Nr 31",
    "sg:city":"Freistadt",
    "sg:orig_category":"Volksschulen",
    "sg:phone":"+43 7942 8296",
    "sg:postcode":"4240",
    "sg:province":"Ober\u00f6sterreich",
    "wof:name":"Volksschule",
    "wof:placetype":"venue"
},
  "geometry": {"coordinates":[14.5049953461,48.5119857788],"type":"Point"}
}