{
  "type": "Feature",
  "properties": {
    "iso:country":"AT",
    "sg:address":"Burgstr 1",
    "sg:city":"Knittelfeld",
    "sg:orig_category":"Diskotheken",
    "sg:phone":"+43 4335 7722167",
    "sg:postcode":"8720",
    "sg:province":"Steiermark",
    "sg:website":"die-burg.at",
    "wof:name":"Die verr\u00fcckte Burg",
    "wof:placetype":"venue"
},
  "geometry": {"coordinates":[14.7973117828,47.2074241638],"type":"Point"}
}