{
  "type": "Feature",
  "properties": {
    "addr:full":"Nr 8 Penk K\u00e4rnten 9816",
    "addr:postcode":"9816",
    "addr:street":"Nr;Penk",
    "iso:country":"AT",
    "sg:address":"Nr 8",
    "sg:city":"Penk",
    "sg:orig_category":"Appartements / Ferienwohnungen",
    "sg:phone":"+43 4783 2459",
    "sg:postcode":"9816",
    "sg:province":"K\u00e4rnten",
    "wof:name":"Almferienhaus Ladinig",
    "wof:placetype":"venue"
},
  "geometry": {"coordinates":[13.2661018372,46.8871536255],"type":"Point"}
}