{
  "type": "Feature",
  "properties": {
    "iso:country":"AT",
    "sg:address":"Sonnental 22",
    "sg:city":"Velden am W\u00f6rther See",
    "sg:orig_category":"Landwirtschaftliche Produkte",
    "sg:phone":"+43 4342 744991",
    "sg:postcode":"9220",
    "sg:province":"K\u00e4rnten",
    "wof:name":"Sonnentaler Bauernspezialit\u00e4ten",
    "wof:placetype":"venue"
},
  "geometry": {"coordinates":[14.0203809738,46.6290931702],"type":"Point"}
}