{
  "type": "Feature",
  "properties": {
    "addr:full":"Klaus 257 Mellau Vorarlberg 6881",
    "addr:housenumber":"257",
    "addr:postcode":"6881",
    "addr:street":"Klaus",
    "iso:country":"AT",
    "sg:address":"Klaus 257",
    "sg:city":"Mellau",
    "sg:orig_category":"Fleischhauereien",
    "sg:phone":"+43 4355 182217",
    "sg:postcode":"6881",
    "sg:province":"Vorarlberg",
    "wof:name":"Broger Hermann",
    "wof:placetype":"venue"
},
  "geometry": {"coordinates":[9.8773021698,47.3637924194],"type":"Point"}
}