{
  "type": "Feature",
  "properties": {
    "addr:full":"Mariahilfer Str 150 Wien Wien 1150",
    "addr:housenumber":"150",
    "addr:postcode":"1150",
    "iso:country":"AT",
    "sg:address":"Mariahilfer Str 150",
    "sg:city":"Wien",
    "sg:orig_category":"Banken U Sparkassen",
    "sg:phone":"+43 1 8923446",
    "sg:postcode":"1150",
    "sg:province":"Wien",
    "wof:name":"Volksbank Wien AG",
    "wof:placetype":"venue"
},
  "geometry": {"coordinates":[16.3346652985,48.1940307617],"type":"Point"}
}