{
  "type": "Feature",
  "properties": {
    "addr:full":"Staudg 40 Wien Wien 1180",
    "addr:housenumber":"40",
    "addr:postcode":"1180",
    "addr:street":"Staudg",
    "iso:country":"AT",
    "sg:address":"Staudg 40",
    "sg:city":"Wien",
    "sg:orig_category":"Maler, Anstreicher U Lackierer",
    "sg:phone":"+43 1 40333240",
    "sg:postcode":"1180",
    "sg:province":"Wien",
    "wof:name":"Schwedler Leopold Nfg Walter Hoffmann GesmbH Nfg KG",
    "wof:placetype":"venue"
},
  "geometry": {"coordinates":[16.3445625305,48.2262420654],"type":"Point"}
}