{
  "type": "Feature",
  "properties": {
    "addr:full":"Linzer Str 189 Wels Ober\u00f6sterreich 4600",
    "addr:housenumber":"189",
    "addr:postcode":"4600",
    "addr:street":"Linzer Str;Oberoesterreich",
    "iso:country":"AT",
    "sg:address":"Linzer Str 189",
    "sg:city":"Wels",
    "sg:orig_category":"Tankstellen",
    "sg:phone":"+43 7242 472390",
    "sg:postcode":"4600",
    "sg:province":"Ober\u00f6sterreich",
    "wof:name":"BP Austria Marketing GmbH",
    "wof:placetype":"venue"
},
  "geometry": {"coordinates":[14.0551757812,48.1745796204],"type":"Point"}
}