{
  "type": "Feature",
  "properties": {
    "addr:full":"Marktplatz 13 Neumarkt im Hausruckkreis Ober\u00f6sterreich 4720",
    "addr:housenumber":"13",
    "addr:postcode":"4720",
    "addr:street":"Marktplatz",
    "iso:country":"AT",
    "sg:address":"Marktplatz 13",
    "sg:city":"Neumarkt im Hausruckkreis",
    "sg:classifiers":[
        {
            "category":"Shopping",
            "subcategory":"Crafts & Fabrics",
            "type":"Retail Goods"
        }
    ],
    "sg:phone":"+43 7733 7055",
    "sg:postcode":"4720",
    "sg:province":"Ober\u00f6sterreich",
    "sg:tags":[
        "adhesive"
    ],
    "sg:website":"ipz.at",
    "wof:name":"XINTEX ZECHMEISTER KEG",
    "wof:placetype":"venue"
},
  "geometry": {"coordinates":[13.7243757248,48.2731361389],"type":"Point"}
}