{
  "type": "Feature",
  "properties": {
    "iso:country":"AT",
    "sg:address":"Bahnhofstr 1",
    "sg:city":"Gmunden",
    "sg:orig_category":"Versicherungsunternehmen",
    "sg:phone":"+43 761273955",
    "sg:postcode":"4810",
    "sg:province":"Ober\u00f6sterreich",
    "wof:name":"Allianz Elementar Versicherungs-AG",
    "wof:placetype":"venue"
},
  "geometry": {"coordinates":[13.7974405289,47.919342041],"type":"Point"}
}