{
  "type": "Feature",
  "properties": {
    "addr:full":"Burgg 117a Judenburg Steiermark 8750",
    "addr:housenumber":"117a",
    "addr:postcode":"8750",
    "iso:country":"AT",
    "sg:address":"Burgg 117a",
    "sg:city":"Judenburg",
    "sg:classifiers":[
        {
            "category":"Taxi",
            "type":"Transportation"
        }
    ],
    "sg:phone":"+43 3572 85185",
    "sg:postcode":"8750",
    "sg:province":"Steiermark",
    "sg:tags":[
        "personentransporte",
        "u"
    ],
    "wof:name":"Hammer Eva-Maria",
    "wof:placetype":"venue"
},
  "geometry": {"coordinates":[14.6401834488,47.1705665588],"type":"Point"}
}