{
  "type": "Feature",
  "properties": {
    "addr:full":"Hockeg 23 Wien Wien 1180",
    "addr:housenumber":"23",
    "addr:postcode":"1180",
    "addr:street":"Hockeg",
    "iso:country":"AT",
    "sg:address":"Hockeg 23",
    "sg:city":"Wien",
    "sg:orig_category":"Tischlereien",
    "sg:phone":"+43 1 4791165",
    "sg:postcode":"1180",
    "sg:province":"Wien",
    "wof:name":"Sadofsky Eduard",
    "wof:placetype":"venue"
},
  "geometry": {"coordinates":[16.3237342834,48.2357673645],"type":"Point"}
}