{
  "type": "Feature",
  "properties": {
    "iso:country":"AT",
    "sg:address":"Maltschach 7",
    "sg:city":"Feldkirchen in K\u00e4rnten",
    "sg:orig_category":"Pensionen / Privatzimmer",
    "sg:phone":"+43 4276 3487",
    "sg:postcode":"9560",
    "sg:province":"K\u00e4rnten",
    "wof:name":"Stark Hubert",
    "wof:placetype":"venue"
},
  "geometry": {"coordinates":[14.1357841492,46.702922821],"type":"Point"}
}