{
  "type": "Feature",
  "properties": {
    "iso:country":"AT",
    "sg:address":"Straucherg 17/20",
    "sg:city":"Graz",
    "sg:orig_category":"Architekturmodellbau",
    "sg:phone":"+43 699 10967557",
    "sg:postcode":"8020",
    "sg:province":"Steiermark",
    "wof:name":"Baumgartner Herwig - Architekturvisualisierung",
    "wof:placetype":"venue"
},
  "geometry": {"coordinates":[15.4264717102,47.0716896057],"type":"Point"}
}