{
  "type": "Feature",
  "properties": {
    "addr:full":"Kirchbergstr 266 Grafendorf Steiermark 8232",
    "addr:housenumber":"266",
    "addr:postcode":"8232",
    "iso:country":"AT",
    "sg:address":"Kirchbergstr 266",
    "sg:city":"Grafendorf",
    "sg:orig_category":"Autoreparatur",
    "sg:phone":"+43 3338 4162",
    "sg:postcode":"8232",
    "sg:province":"Steiermark",
    "wof:name":"Kundegraber Hermann",
    "wof:placetype":"venue"
},
  "geometry": {"coordinates":[15.9899759293,47.3405075073],"type":"Point"}
}