{
  "type": "Feature",
  "properties": {
    "addr:full":"Kendlerstrasse 138 Salzburg Salzburg 5020",
    "addr:housenumber":"138",
    "addr:postcode":"5020",
    "addr:street":"Kendlerstrasse;Salzburg",
    "iso:country":"AT",
    "sg:address":"Kendlerstrasse 138",
    "sg:city":"Salzburg",
    "sg:classifiers":[
        {
            "category":"Place Of Worship",
            "subcategory":"Church",
            "type":"Public Place"
        }
    ],
    "sg:phone":"+43 662 825106",
    "sg:postcode":"5020",
    "sg:province":"Salzburg",
    "sg:tags":[
        "restoration"
    ],
    "wof:name":"Maria Offenhauser",
    "wof:placetype":"venue"
},
  "geometry": {"coordinates":[13.0040664673,47.7795372009],"type":"Point"}
}