{
  "type": "Feature",
  "properties": {
    "iso:country":"AT",
    "sg:address":"Industriestr 8",
    "sg:city":"Horitschon",
    "sg:orig_category":"Bauunternehmen",
    "sg:phone":"+43 2610 422010",
    "sg:postcode":"7312",
    "sg:province":"Burgenland",
    "wof:name":"Bader-Bau GmbH",
    "wof:placetype":"venue"
},
  "geometry": {"coordinates":[16.5360488892,47.5888023376],"type":"Point"}
}