{
  "type": "Feature",
  "properties": {
    "addr:full":"Sternwartestr 23 Wien Wien 1180",
    "addr:housenumber":"23",
    "addr:postcode":"1180",
    "addr:street":"Sternwartestr",
    "iso:country":"AT",
    "sg:address":"Sternwartestr 23",
    "sg:city":"Wien",
    "sg:orig_category":"Tankstellen",
    "sg:phone":"+43 1 4796884",
    "sg:postcode":"1180",
    "sg:province":"Wien",
    "wof:name":"AWI-Diskont",
    "wof:placetype":"venue"
},
  "geometry": {"coordinates":[16.3461647034,48.2295646667],"type":"Point"}
}