{
  "type": "Feature",
  "properties": {
    "addr:full":"Eduardg 6-8 Wien Wien 1180",
    "addr:housenumber":"6-8",
    "addr:postcode":"1180",
    "addr:street":"Eduardg",
    "iso:country":"AT",
    "sg:address":"Eduardg 6-8",
    "sg:city":"Wien",
    "sg:orig_category":"Offsetdruckereien",
    "sg:phone":"+43 1 40672210",
    "sg:postcode":"1180",
    "sg:province":"Wien",
    "wof:name":"Edelbacher Druck GesmbH",
    "wof:placetype":"venue"
},
  "geometry": {"coordinates":[16.3445625305,48.2262420654],"type":"Point"}
}