{
  "type": "Feature",
  "properties": {
    "iso:country":"AT",
    "sg:address":"Tsch\u00f6raner Weg 23",
    "sg:city":"Bodensdorf",
    "sg:orig_category":"Pensionen / Privatzimmer",
    "sg:phone":"+43 4243 2253",
    "sg:postcode":"9551",
    "sg:province":"K\u00e4rnten",
    "wof:name":"Sch\u00fctzenhofer Herbert",
    "wof:placetype":"venue"
},
  "geometry": {"coordinates":[13.9651889801,46.6831626892],"type":"Point"}
}