{
  "type": "Feature",
  "properties": {
    "iso:country":"AT",
    "sg:address":"Unterlochnerstrasse 2a",
    "sg:city":"Mattighofen",
    "sg:classifiers":[
        {
            "category":"Retail",
            "subcategory":"Repair Shop",
            "type":"Services"
        }
    ],
    "sg:phone":"+43 7742 57110",
    "sg:postcode":"5230",
    "sg:province":"Ober\u00f6sterreich",
    "sg:tags":[
        "agricultural",
        "machinery"
    ],
    "wof:name":"Josef Bucheder's S\u00f6hne KG",
    "wof:placetype":"venue"
},
  "geometry": {"coordinates":[13.1470603943,48.1087646484],"type":"Point"}
}