{
  "type": "Feature",
  "properties": {
    "addr:full":"Brauhausstr 47 Schwechat Nieder\u00f6sterreich 2320",
    "addr:housenumber":"47",
    "addr:postcode":"2320",
    "addr:street":"Brauhausstr;Niederoesterreich",
    "iso:country":"AT",
    "sg:address":"Brauhausstr 47",
    "sg:city":"Schwechat",
    "sg:orig_category":"Bankomat-Standorte",
    "sg:phone":"+43 1 7076231",
    "sg:postcode":"2320",
    "sg:province":"Nieder\u00f6sterreich",
    "wof:name":"Bankomat d PSK",
    "wof:placetype":"venue"
},
  "geometry": {"coordinates":[16.4655685425,48.1288223267],"type":"Point"}
}