{
  "type": "Feature",
  "properties": {
    "iso:country":"AT",
    "sg:address":"Rettlsteinerweg 22",
    "sg:city":"Wattens",
    "sg:classifiers":[
        {
            "category":"Building & Trades",
            "subcategory":"Electrical",
            "type":"Services"
        }
    ],
    "sg:phone":"+43 5224 56772",
    "sg:postcode":"6112",
    "sg:province":"Tirol",
    "sg:tags":[
        "work",
        "installation"
    ],
    "sg:website":"daxer.biz",
    "wof:name":"Franz Daxer",
    "wof:placetype":"venue"
},
  "geometry": {"coordinates":[11.5990915298,47.2902183533],"type":"Point"}
}