{
  "type": "Feature",
  "properties": {
    "iso:country":"AT",
    "sg:address":"Johann-Roithner-Str 103",
    "sg:city":"Traun",
    "sg:orig_category":"Massagen",
    "sg:phone":"+43 4372 2988383",
    "sg:postcode":"4050",
    "sg:province":"Ober\u00f6sterreich",
    "wof:name":"Kirchmayr Michaela",
    "wof:placetype":"venue"
},
  "geometry": {"coordinates":[14.2481803894,48.2247505188],"type":"Point"}
}