{
  "type": "Feature",
  "properties": {
    "addr:full":"Lastenstrasse 1 Graz Steiermark 8020",
    "addr:housenumber":"1",
    "addr:postcode":"8020",
    "addr:street":"Lastenstrasse",
    "iso:country":"AT",
    "sg:address":"Lastenstrasse 1",
    "sg:city":"Graz",
    "sg:classifiers":[
        {
            "category":"Building & Trades",
            "subcategory":"Construction",
            "type":"Services"
        }
    ],
    "sg:phone":"+43 316 714949",
    "sg:postcode":"8020",
    "sg:province":"Steiermark",
    "sg:tags":[
        "bitumen",
        "road"
    ],
    "wof:name":"Fuchs & H\u00f6lzl Ges.m.b.H.",
    "wof:placetype":"venue"
},
  "geometry": {"coordinates":[15.4149398804,47.0811195374],"type":"Point"}
}