{
  "type": "Feature",
  "properties": {
    "iso:country":"AT",
    "sg:address":"Petzoldg 14",
    "sg:city":"Stockerau",
    "sg:orig_category":"Hunde- U Katzensalons",
    "sg:phone":"+43 664 3109284",
    "sg:postcode":"2000",
    "sg:province":"Nieder\u00f6sterreich",
    "wof:name":"Hundesalon Mimi",
    "wof:placetype":"venue"
},
  "geometry": {"coordinates":[16.2185173035,48.3911399841],"type":"Point"}
}