{
  "type": "Feature",
  "properties": {
    "iso:country":"AT",
    "sg:address":"Himmelpfortg 1",
    "sg:city":"Wien",
    "sg:orig_category":"Transportunternehmen",
    "sg:phone":"+43 1 51647",
    "sg:postcode":"1010",
    "sg:province":"Wien",
    "wof:name":"P & O Nedlloyd Limited Branch Austria",
    "wof:placetype":"venue"
},
  "geometry": {"coordinates":[16.3716449738,48.2060623169],"type":"Point"}
}