{
  "type": "Feature",
  "properties": {
    "addr:full":"Gladiolenweg 21/5 Wien Wien 1220",
    "addr:housenumber":"21 / 5",
    "addr:postcode":"1220",
    "addr:street":"Gladiolenweg",
    "iso:country":"AT",
    "sg:address":"Gladiolenweg 21/5",
    "sg:city":"Wien",
    "sg:orig_category":"Lebens- U Sozialberatung",
    "sg:phone":"+43 1 2806114",
    "sg:postcode":"1220",
    "sg:province":"Wien",
    "wof:name":"Kamhuber Eva",
    "wof:placetype":"venue"
},
  "geometry": {"coordinates":[16.4780769348,48.2351417542],"type":"Point"}
}