{
  "type": "Feature",
  "properties": {
    "addr:full":"Gusentalstr 1a Gallneukirchen Ober\u00f6sterreich 4210",
    "addr:housenumber":"1a",
    "addr:postcode":"4210",
    "addr:street":"Gusentalstr;Oberoesterreich",
    "iso:country":"AT",
    "sg:address":"Gusentalstr 1a",
    "sg:city":"Gallneukirchen",
    "sg:orig_category":"Gemeinden",
    "sg:phone":"+43 7235 630140",
    "sg:postcode":"4210",
    "sg:province":"Ober\u00f6sterreich",
    "wof:name":"Gemeindeamt Unterweitersdorf",
    "wof:placetype":"venue"
},
  "geometry": {"coordinates":[14.4672746658,48.3681945801],"type":"Point"}
}