{
  "type": "Feature",
  "properties": {
    "iso:country":"AT",
    "sg:address":"Nr 151",
    "sg:city":"Kukmirn",
    "sg:orig_category":"Feuerwehren",
    "sg:phone":"+43 3328 32938",
    "sg:postcode":"7543",
    "sg:province":"Burgenland",
    "wof:name":"Freiwillige Feuerwehr Limbach",
    "wof:placetype":"venue"
},
  "geometry": {"coordinates":[16.2055358887,47.072227478],"type":"Point"}
}