{
  "type": "Feature",
  "properties": {
    "addr:full":"Nr 19 Sillian Tirol 9920",
    "addr:postcode":"9920",
    "addr:street":"Nr;Sillian Tirol",
    "iso:country":"AT",
    "sg:address":"Nr 19",
    "sg:city":"Sillian",
    "sg:orig_category":"Maler, Anstreicher U Lackierer",
    "sg:phone":"+43 4842 5109",
    "sg:postcode":"9920",
    "sg:province":"Tirol",
    "wof:name":"Atelier Optimal - Designer Maler - Josef Gruber",
    "wof:placetype":"venue"
},
  "geometry": {"coordinates":[12.4398870468,46.7495117188],"type":"Point"}
}