{
  "type": "Feature",
  "properties": {
    "addr:full":"Kagraner Pl 5 Wien Wien 1220",
    "addr:housenumber":"5",
    "addr:postcode":"1220",
    "addr:street":"Kagraner Pl",
    "iso:country":"AT",
    "sg:address":"Kagraner Pl 5",
    "sg:city":"Wien",
    "sg:orig_category":"Zeitungen U Zeitschriften",
    "sg:phone":"+43 1 2034360",
    "sg:postcode":"1220",
    "sg:province":"Wien",
    "wof:name":"Romantausch und Zeitschriftenhandel Bitterer OEG",
    "wof:placetype":"venue"
},
  "geometry": {"coordinates":[16.4449138641,48.249786377],"type":"Point"}
}