{
  "type": "Feature",
  "properties": {
    "iso:country":"AT",
    "sg:address":"Fischauer G 136",
    "sg:city":"Wiener Neustadt",
    "sg:orig_category":"Unterhaltungselektronik / Einzelhandel",
    "sg:phone":"+43 699 11349705",
    "sg:postcode":"2700",
    "sg:province":"Nieder\u00f6sterreich",
    "wof:name":"TV Felix",
    "wof:placetype":"venue"
},
  "geometry": {"coordinates":[16.2215042114,47.8222999573],"type":"Point"}
}