{
  "type": "Feature",
  "properties": {
    "addr:full":"Vivenotgasse 31 Wien Wien 1120",
    "addr:housenumber":"31",
    "addr:postcode":"1120",
    "addr:street":"Vivenotgasse",
    "iso:country":"AT",
    "sg:address":"Vivenotgasse 31",
    "sg:city":"Wien",
    "sg:classifiers":[
        {
            "category":"Manufacturing",
            "subcategory":"Buildings",
            "type":"Manufacturing & Wholesale Goods"
        }
    ],
    "sg:phone":"+43 1 8139116",
    "sg:postcode":"1120",
    "sg:province":"Wien",
    "sg:tags":[
        "grating",
        "balcony"
    ],
    "wof:name":"Bauschlosserei Blemensch\u00fctz Ges.m.b.H.",
    "wof:placetype":"venue"
},
  "geometry": {"coordinates":[16.3315029144,48.1784133911],"type":"Point"}
}