{
  "type": "Feature",
  "properties": {
    "addr:full":"Ruedlstrasse 40 Ternitz Nieder\u00f6sterreich 2630",
    "addr:housenumber":"40",
    "addr:postcode":"2630",
    "addr:street":"Ruedlstrasse",
    "iso:country":"AT",
    "sg:address":"Ruedlstrasse 40",
    "sg:city":"Ternitz",
    "sg:classifiers":[
        {
            "category":"Home & Garden",
            "subcategory":"Building Materials",
            "type":"Retail Goods"
        }
    ],
    "sg:phone":"+43 2630 38445",
    "sg:postcode":"2630",
    "sg:province":"Nieder\u00f6sterreich",
    "sg:tags":[
        "aluminium",
        "gutter"
    ],
    "wof:name":"Johann u. Ruth Wagner",
    "wof:placetype":"venue"
},
  "geometry": {"coordinates":[16.0389118195,47.7190437317],"type":"Point"}
}