{
  "type": "Feature",
  "properties": {
    "addr:full":"Peregrinstr 8 Salzburg Salzburg 5020",
    "addr:housenumber":"8",
    "addr:postcode":"5020",
    "addr:street":"Peregrinstr;Salzburg",
    "iso:country":"AT",
    "sg:address":"Peregrinstr 8",
    "sg:city":"Salzburg",
    "sg:orig_category":"Architekten",
    "sg:phone":"+43 662 827445",
    "sg:postcode":"5020",
    "sg:province":"Salzburg",
    "wof:name":"ACP Arch Consult Projekt ZT GmbH",
    "wof:placetype":"venue"
},
  "geometry": {"coordinates":[13.0517292023,47.7917938232],"type":"Point"}
}