{
  "type": "Feature",
  "properties": {
    "addr:full":"Zirkusstr 29 Leoben Steiermark 8700",
    "addr:housenumber":"29",
    "addr:postcode":"8700",
    "addr:street":"Zirkusstr",
    "iso:country":"AT",
    "sg:address":"Zirkusstr 29",
    "sg:city":"Leoben",
    "sg:orig_category":"Farben U Lacke / Erzeugung U Gro\u00c3\u0178handel",
    "sg:phone":"+43 3842 26120",
    "sg:postcode":"8700",
    "sg:province":"Steiermark",
    "wof:name":"Stromberger OHG",
    "wof:placetype":"venue"
},
  "geometry": {"coordinates":[15.0884838104,47.3714675903],"type":"Point"}
}