{
  "type": "Feature",
  "properties": {
    "iso:country":"AT",
    "sg:address":"Brennerstr 3",
    "sg:city":"Innsbruck",
    "sg:orig_category":"Handelsagenturen",
    "sg:phone":"+43 512 571886",
    "sg:postcode":"6020",
    "sg:province":"Tirol",
    "wof:name":"Jax Alfred Dipl-Vw KG",
    "wof:placetype":"venue"
},
  "geometry": {"coordinates":[11.3990869522,47.2510185242],"type":"Point"}
}