{
  "type": "Feature",
  "properties": {
    "addr:full":"Ischler Str 71a Bad Aussee Steiermark 8990",
    "addr:housenumber":"71a",
    "addr:postcode":"8990",
    "addr:street":"Str",
    "iso:country":"AT",
    "sg:address":"Ischler Str 71a",
    "sg:city":"Bad Aussee",
    "sg:orig_category":"Immobilienmakler",
    "sg:phone":"+43 3622 53744",
    "sg:postcode":"8990",
    "sg:province":"Steiermark",
    "wof:name":"Ausseerland Immobilien GesmbH",
    "wof:placetype":"venue"
},
  "geometry": {"coordinates":[13.7821416855,47.609336853],"type":"Point"}
}