{
  "type": "Feature",
  "properties": {
    "addr:full":"Bahnstr 1 Pamhagen Burgenland 7152",
    "addr:housenumber":"1",
    "addr:postcode":"7152",
    "addr:street":"Bahnstr",
    "iso:country":"AT",
    "sg:address":"Bahnstr 1",
    "sg:city":"Pamhagen",
    "sg:orig_category":"Tourismusinformation U -Organisationen",
    "sg:phone":"+43 4321 742093",
    "sg:postcode":"7152",
    "sg:province":"Burgenland",
    "wof:name":"Tourismusverband Pamhagen",
    "wof:placetype":"venue"
},
  "geometry": {"coordinates":[16.9065303802,47.7007293701],"type":"Point"}
}