{
  "type": "Feature",
  "properties": {
    "addr:full":"H\u00f6dlg 17 Wien Wien 1230",
    "addr:housenumber":"17",
    "addr:postcode":"1230",
    "addr:street":"Hoedlg",
    "iso:country":"AT",
    "sg:address":"H\u00f6dlg 17",
    "sg:city":"Wien",
    "sg:orig_category":"Raumausstattung",
    "sg:phone":"+43 1 21482600",
    "sg:postcode":"1230",
    "sg:province":"Wien",
    "wof:name":"Burger Josef KG",
    "wof:placetype":"venue"
},
  "geometry": {"coordinates":[16.2822799683,48.1347465515],"type":"Point"}
}