{
  "type": "Feature",
  "properties": {
    "iso:country":"AT",
    "sg:address":"Neud\u00f6rflstr 15",
    "sg:city":"Neuberg an der M\u00fcrz",
    "sg:orig_category":"Massagen",
    "sg:phone":"+43 3857 8632",
    "sg:postcode":"8692",
    "sg:province":"Steiermark",
    "wof:name":"Waidhofer Christian",
    "wof:placetype":"venue"
},
  "geometry": {"coordinates":[15.5808916092,47.66822052],"type":"Point"}
}