{
  "type": "Feature",
  "properties": {
    "addr:full":"Quellenstr 1 Steinerkirchen an der Traun Ober\u00f6sterreich 4652",
    "addr:housenumber":"1",
    "addr:postcode":"4652",
    "addr:street":"Quellenstr",
    "iso:country":"AT",
    "sg:address":"Quellenstr 1",
    "sg:city":"Steinerkirchen an der Traun",
    "sg:orig_category":"Bauunternehmen",
    "sg:phone":"+43 4372 412600",
    "sg:postcode":"4652",
    "sg:province":"Ober\u00f6sterreich",
    "wof:name":"Stockinger Friedrich",
    "wof:placetype":"venue"
},
  "geometry": {"coordinates":[13.9542636871,48.0747337341],"type":"Point"}
}