{
  "type": "Feature",
  "properties": {
    "addr:full":"Faberstr 6 Salzburg Salzburg 5020",
    "addr:housenumber":"6",
    "addr:postcode":"5020",
    "addr:street":"Faberstr;Salzburg",
    "iso:country":"AT",
    "sg:address":"Faberstr 6",
    "sg:city":"Salzburg",
    "sg:orig_category":"Markt- U Meinungsforschung",
    "sg:phone":"+43 4366 2875522",
    "sg:postcode":"5020",
    "sg:province":"Salzburg",
    "wof:name":"SOMAS - Institut f Sozial- u Marktforschung",
    "wof:placetype":"venue"
},
  "geometry": {"coordinates":[13.0449142456,47.8059997559],"type":"Point"}
}