{
  "type": "Feature",
  "properties": {
    "addr:full":"Teinfaltstr 3 Wien Wien 1010",
    "addr:housenumber":"3",
    "addr:postcode":"1010",
    "addr:street":"Teinfaltstr",
    "iso:country":"AT",
    "sg:address":"Teinfaltstr 3",
    "sg:city":"Wien",
    "sg:orig_category":"Bilderrahmen",
    "sg:phone":"+43 1 5358029",
    "sg:postcode":"1010",
    "sg:province":"Wien",
    "wof:name":"Rahmen Heinz Frank",
    "wof:placetype":"venue"
},
  "geometry": {"coordinates":[16.363615036,48.2116317749],"type":"Point"}
}