{
  "type": "Feature",
  "properties": {
    "addr:full":"Ennser Str 91 Gleink Ober\u00f6sterreich 4407",
    "addr:housenumber":"91",
    "addr:postcode":"4407",
    "addr:street":"Str",
    "iso:country":"AT",
    "sg:address":"Ennser Str 91",
    "sg:city":"Gleink",
    "sg:orig_category":"Fliesen U Platten",
    "sg:phone":"+43 7252 385410",
    "sg:postcode":"4407",
    "sg:province":"Ober\u00f6sterreich",
    "wof:name":"Gilly's Fliesenladen Inh Peter Gilly",
    "wof:placetype":"venue"
},
  "geometry": {"coordinates":[14.4271993637,48.0809898376],"type":"Point"}
}