{
  "type": "Feature",
  "properties": {
    "addr:full":"Marieng 11 Wien Wien 1170",
    "addr:housenumber":"11",
    "addr:postcode":"1170",
    "addr:street":"Marieng",
    "iso:country":"AT",
    "sg:address":"Marieng 11",
    "sg:city":"Wien",
    "sg:orig_category":"Autoreparatur",
    "sg:phone":"+43 1 4857671",
    "sg:postcode":"1170",
    "sg:province":"Wien",
    "wof:name":"Schmolik KFZ-Reparatur-Center Hernals",
    "wof:placetype":"venue"
},
  "geometry": {"coordinates":[16.3256511688,48.2184638977],"type":"Point"}
}