{
  "type": "Feature",
  "properties": {
    "iso:country":"AT",
    "sg:address":"Zellermoosstr 17",
    "sg:city":"Zell am See",
    "sg:orig_category":"Appartements / Ferienwohnungen",
    "sg:phone":"+43 6542 57934",
    "sg:postcode":"5700",
    "sg:province":"Salzburg",
    "wof:name":"Appartement Garger",
    "wof:placetype":"venue"
},
  "geometry": {"coordinates":[12.7836236954,47.2939834595],"type":"Point"}
}