{
  "type": "Feature",
  "properties": {
    "addr:full":"Ing.-Julius-Raab-Str 11 Pinkafeld Burgenland 7423",
    "addr:housenumber":"11",
    "addr:postcode":"7423",
    "addr:street":"Ing.-Julius-Raab-Str",
    "iso:country":"AT",
    "sg:address":"Ing.-Julius-Raab-Str 11",
    "sg:city":"Pinkafeld",
    "sg:orig_category":"Installationsunternehmen",
    "sg:phone":"+43 3357 423540",
    "sg:postcode":"7423",
    "sg:province":"Burgenland",
    "wof:name":"Hofer Richard GesmbH",
    "wof:placetype":"venue"
},
  "geometry": {"coordinates":[16.1163845062,47.3684577942],"type":"Point"}
}