{
  "type": "Feature",
  "properties": {
    "addr:full":"Innerschwand 201 Loibichl Ober\u00f6sterreich 5311",
    "addr:housenumber":"201",
    "addr:postcode":"5311",
    "addr:street":"Innerschwand;Oberoesterreich",
    "iso:country":"AT",
    "sg:address":"Innerschwand 201",
    "sg:city":"Loibichl",
    "sg:classifiers":[
        {
            "category":"Taxi",
            "type":"Transportation"
        }
    ],
    "sg:phone":"+43 6233 8246",
    "sg:postcode":"5311",
    "sg:province":"Ober\u00f6sterreich",
    "sg:tags":[
        "personentransporte",
        "u"
    ],
    "wof:name":"Wageneder Veronika",
    "wof:placetype":"venue"
},
  "geometry": {"coordinates":[13.4032068253,47.8300895691],"type":"Point"}
}