{
  "type": "Feature",
  "properties": {
    "addr:full":"Bodingbachstr 4 Lunz am See Nieder\u00f6sterreich 3293",
    "addr:housenumber":"4",
    "addr:postcode":"3293",
    "addr:street":"Bodingbachstr;Niederoesterreich",
    "iso:country":"AT",
    "sg:address":"Bodingbachstr 4",
    "sg:city":"Lunz am See",
    "sg:orig_category":"Schmieden U Schmiedeeisenelemente",
    "sg:phone":"+43 4374 8682670",
    "sg:postcode":"3293",
    "sg:province":"Nieder\u00f6sterreich",
    "wof:name":"Hauser Siegfried",
    "wof:placetype":"venue"
},
  "geometry": {"coordinates":[15.0195541382,47.8636360168],"type":"Point"}
}