{
  "type": "Feature",
  "properties": {
    "addr:full":"Josef-Lindner-Str 2c Wals Salzburg 5071",
    "addr:housenumber":"2c",
    "addr:postcode":"5071",
    "addr:street":"Josef-Lindner-Str;Salzburg",
    "iso:country":"AT",
    "sg:address":"Josef-Lindner-Str 2c",
    "sg:city":"Wals",
    "sg:classifiers":[
        {
            "category":"Restaurant",
            "type":"Food & Drink"
        }
    ],
    "sg:phone":"+43 4366 2853488",
    "sg:postcode":"5071",
    "sg:province":"Salzburg",
    "wof:name":"Rincon Latino",
    "wof:placetype":"venue"
},
  "geometry": {"coordinates":[12.9693145752,47.7897644043],"type":"Point"}
}