{
  "type": "Feature",
  "properties": {
    "addr:full":"Maigener Str 10 Sigmundsherberg Nieder\u00f6sterreich 3751",
    "addr:postcode":"3751",
    "addr:street":"Str;Niederoesterreich",
    "iso:country":"AT",
    "sg:address":"Maigener Str 10",
    "sg:city":"Sigmundsherberg",
    "sg:orig_category":"Weiterbildungsinstitute M Allg U Berufl Bildungsangebot",
    "sg:phone":"+43 4329 8326150",
    "sg:postcode":"3751",
    "sg:province":"Nieder\u00f6sterreich",
    "wof:name":"Berufsf\u00f6rderungsinstitut N\u00f6 Regionalstelle",
    "wof:placetype":"venue"
},
  "geometry": {"coordinates":[15.7563266754,48.6853103638],"type":"Point"}
}