{
  "type": "Feature",
  "properties": {
    "iso:country":"AT",
    "sg:address":"Hauptpl 9-10",
    "sg:city":"Schwechat",
    "sg:orig_category":"Lederwaren / Einzelhandel",
    "sg:phone":"+43 1 7078204",
    "sg:postcode":"2320",
    "sg:province":"Nieder\u00f6sterreich",
    "wof:name":"Kases Wolfgang",
    "wof:placetype":"venue"
},
  "geometry": {"coordinates":[16.4771347046,48.1392593384],"type":"Point"}
}