{
  "type": "Feature",
  "properties": {
    "iso:country":"AT",
    "sg:address":"Industriestr 2-8",
    "sg:city":"Gerasdorf",
    "sg:orig_category":"Fleisch-, Wurst- U Selchwaren / Erzeugung U Gro\u00c3\u0178handel",
    "sg:phone":"+43 4317 3466600",
    "sg:postcode":"2201",
    "sg:province":"Nieder\u00f6sterreich",
    "wof:name":"Stastnik GesmbH",
    "wof:placetype":"venue"
},
  "geometry": {"coordinates":[16.4816436768,48.2841262817],"type":"Point"}
}