{
  "type": "Feature",
  "properties": {
    "iso:country":"AT",
    "sg:address":"Bundesstr 6-8",
    "sg:city":"Klaus-Weiler",
    "sg:orig_category":"Werbegrafik- U Grafik-Design",
    "sg:phone":"+43 4355 23585640",
    "sg:postcode":"6833",
    "sg:province":"Vorarlberg",
    "wof:name":"K\u00f6hnlein Fritz",
    "wof:placetype":"venue"
},
  "geometry": {"coordinates":[9.6528644562,47.3032798767],"type":"Point"}
}