{
  "type": "Feature",
  "properties": {
    "addr:full":"Annabichler Strasse 36 Klagenfurt K\u00e4rnten 9020",
    "addr:housenumber":"36",
    "addr:postcode":"9020",
    "addr:street":"Annabichler Strasse;Kaernten",
    "iso:country":"AT",
    "sg:address":"Annabichler Strasse 36",
    "sg:city":"Klagenfurt",
    "sg:classifiers":[
        {
            "category":"Home & Garden",
            "subcategory":"Furniture",
            "type":"Retail Goods"
        }
    ],
    "sg:phone":"+43 463 47122",
    "sg:postcode":"9020",
    "sg:province":"K\u00e4rnten",
    "sg:tags":[
        "bathroom"
    ],
    "wof:name":"Karl Wernig",
    "wof:placetype":"venue"
},
  "geometry": {"coordinates":[14.3255901337,46.6383857727],"type":"Point"}
}