{
  "type": "Feature",
  "properties": {
    "addr:full":"Stifterstr 36 Perg Ober\u00f6sterreich 4320",
    "addr:housenumber":"36",
    "addr:postcode":"4320",
    "addr:street":"Stifterstr",
    "iso:country":"AT",
    "sg:address":"Stifterstr 36",
    "sg:city":"Perg",
    "sg:orig_category":"Paketdienste",
    "sg:phone":"+43 7262 57945",
    "sg:postcode":"4320",
    "sg:province":"Ober\u00f6sterreich",
    "wof:name":"Toms Paket Express",
    "wof:placetype":"venue"
},
  "geometry": {"coordinates":[14.6318702698,48.2425003052],"type":"Point"}
}