{
  "type": "Feature",
  "properties": {
    "iso:country":"AT",
    "sg:address":"Hauptstr 63",
    "sg:city":"Eichgraben",
    "sg:classifiers":[
        {
            "category":"Internet Cafe",
            "subcategory":"None",
            "type":"Food & Drink"
        }
    ],
    "sg:phone":"+43 2773 43150",
    "sg:postcode":"3032",
    "sg:province":"Nieder\u00f6sterreich",
    "wof:name":"JustBe-Projects (JBP) - elektronik-edv & internet - Ing Baumgartner Erich",
    "wof:placetype":"venue"
},
  "geometry": {"coordinates":[15.9853878021,48.172744751],"type":"Point"}
}