{
  "type": "Feature",
  "properties": {
    "addr:full":"Breitweg 4B Hall in Tirol Tirol 6060",
    "addr:housenumber":"4b",
    "addr:postcode":"6060",
    "addr:street":"Breitweg;Tirol",
    "iso:country":"AT",
    "sg:address":"Breitweg 4B",
    "sg:city":"Hall in Tirol",
    "sg:orig_category":"Steuerberatung",
    "sg:phone":"+43 5223 44361",
    "sg:postcode":"6060",
    "sg:province":"Tirol",
    "wof:name":"Gsaxner Bettina",
    "wof:placetype":"venue"
},
  "geometry": {"coordinates":[11.501625061,47.2857780457],"type":"Point"}
}