{
  "type": "Feature",
  "properties": {
    "addr:full":"Pfarrstr 22 Mariapfarr Salzburg 5571",
    "addr:housenumber":"22",
    "addr:postcode":"5571",
    "addr:street":"Pfarrstr;Salzburg",
    "iso:country":"AT",
    "sg:address":"Pfarrstr 22",
    "sg:city":"Mariapfarr",
    "sg:orig_category":"Pensionen / Privatzimmer",
    "sg:phone":"+43 6473 8258",
    "sg:postcode":"5571",
    "sg:province":"Salzburg",
    "wof:name":"Rosenkranz Franz - Fr\u00fchst\u00fcckspension",
    "wof:placetype":"venue"
},
  "geometry": {"coordinates":[13.7457036972,47.1497344971],"type":"Point"}
}