{
  "type": "Feature",
  "properties": {
    "addr:full":"Pater-Gratian-Leser-Str 5 G\u00fcssing Burgenland 7540",
    "addr:housenumber":"5",
    "addr:postcode":"7540",
    "addr:street":"Pater-Gratian-Leser-Str",
    "iso:country":"AT",
    "sg:address":"Pater-Gratian-Leser-Str 5",
    "sg:city":"G\u00fcssing",
    "sg:orig_category":"Elektroinstallationsunternehmen",
    "sg:phone":"+43 4333 22423610",
    "sg:postcode":"7540",
    "sg:province":"Burgenland",
    "wof:name":"Bieber Franz GmbH & Co KG",
    "wof:placetype":"venue"
},
  "geometry": {"coordinates":[16.3241653442,47.0594215393],"type":"Point"}
}