{
  "type": "Feature",
  "properties": {
    "addr:full":"Stadtpl 22 Laa an der Thaya Nieder\u00f6sterreich 2136",
    "addr:housenumber":"22",
    "addr:postcode":"2136",
    "addr:street":"Stadtpl",
    "iso:country":"AT",
    "sg:address":"Stadtpl 22",
    "sg:city":"Laa an der Thaya",
    "sg:orig_category":"Gerichte",
    "sg:phone":"+43 2522 24450",
    "sg:postcode":"2136",
    "sg:province":"Nieder\u00f6sterreich",
    "wof:name":"Bezirksgericht Laa an der Thaya",
    "wof:placetype":"venue"
},
  "geometry": {"coordinates":[16.3837223053,48.7218055725],"type":"Point"}
}