{
  "type": "Feature",
  "properties": {
    "addr:full":"Salzburger Str 5 Hall in Tirol Tirol 6060",
    "addr:housenumber":"5",
    "addr:postcode":"6060",
    "addr:street":"Salzburger Str;Tirol",
    "iso:country":"AT",
    "sg:address":"Salzburger Str 5",
    "sg:city":"Hall in Tirol",
    "sg:orig_category":"Architekten",
    "sg:phone":"+43 4352 23427000",
    "sg:postcode":"6060",
    "sg:province":"Tirol",
    "wof:name":"Brunner Herbert Dipl-Ing u. Sallmann Werner Dipl-Ing",
    "wof:placetype":"venue"
},
  "geometry": {"coordinates":[11.5091600418,47.2806243896],"type":"Point"}
}