{
  "type": "Feature",
  "properties": {
    "addr:full":"Kaiser-Franz-Josef-Str 6a Hohenems Vorarlberg 6845",
    "addr:housenumber":"6a",
    "addr:postcode":"6845",
    "addr:street":"Kaiser-Franz-Josef-Str",
    "iso:country":"AT",
    "sg:address":"Kaiser-Franz-Josef-Str 6a",
    "sg:city":"Hohenems",
    "sg:orig_category":"Immobilienmakler",
    "sg:phone":"+43 4355 7672523",
    "sg:postcode":"6845",
    "sg:province":"Vorarlberg",
    "sg:website":"immobilien.vvb.at",
    "wof:name":"Immobilienservice Vorarlberger Volksbank GmbH Nfg OEG",
    "wof:placetype":"venue"
},
  "geometry": {"coordinates":[9.6869802475,47.3611793518],"type":"Point"}
}