{
  "type": "Feature",
  "properties": {
    "iso:country":"AT",
    "sg:address":"Quelleng 16",
    "sg:city":"Dornbirn",
    "sg:orig_category":"Wasserwerke",
    "sg:phone":"+43 4355 7225475",
    "sg:postcode":"6850",
    "sg:province":"Vorarlberg",
    "wof:name":"Wasserwerk d Stadt Dornbirn",
    "wof:placetype":"venue"
},
  "geometry": {"coordinates":[9.7443237305,47.421459198],"type":"Point"}
}