{
  "type": "Feature",
  "properties": {
    "iso:country":"AT",
    "sg:address":"Nr 152",
    "sg:city":"Mureck",
    "sg:orig_category":"Lebensmittel / Einzelhandel",
    "sg:phone":"+43 3472 3009",
    "sg:postcode":"8480",
    "sg:province":"Steiermark",
    "wof:name":"SPAR \u00d6sterreichische Warenhandels-AG",
    "wof:placetype":"venue"
},
  "geometry": {"coordinates":[15.7676620483,46.7260055542],"type":"Point"}
}