{
  "type": "Feature",
  "properties": {
    "addr:full":"Unterwei\u00dfbach 3 Wei\u00dfbach Salzburg 5093",
    "addr:housenumber":"3",
    "addr:postcode":"5093",
    "addr:street":"Unterweissbach;Salzburg",
    "iso:country":"AT",
    "sg:address":"Unterwei\u00dfbach 3",
    "sg:city":"Wei\u00dfbach",
    "sg:orig_category":"Pensionen / Privatzimmer",
    "sg:phone":"+43 6582 8316",
    "sg:postcode":"5093",
    "sg:province":"Salzburg",
    "wof:name":"Pension Pisterlhof",
    "wof:placetype":"venue"
},
  "geometry": {"coordinates":[12.752612114,47.5205612183],"type":"Point"}
}