{
  "type": "Feature",
  "properties": {
    "addr:full":"Burgunderweg 4 Rankweil Vorarlberg 6830",
    "addr:housenumber":"4",
    "addr:postcode":"6830",
    "addr:street":"Burgunderweg",
    "iso:country":"AT",
    "sg:address":"Burgunderweg 4",
    "sg:city":"Rankweil",
    "sg:classifiers":[
        {
            "category":"Home & Garden",
            "subcategory":"Building Materials",
            "type":"Retail Goods"
        }
    ],
    "sg:phone":"+43 4355 2243502",
    "sg:postcode":"6830",
    "sg:province":"Vorarlberg",
    "sg:tags":[
        "baustoffe",
        "-material",
        "u"
    ],
    "wof:name":"EcoBeton",
    "wof:placetype":"venue"
},
  "geometry": {"coordinates":[9.6283769608,47.2738342285],"type":"Point"}
}