{
  "type": "Feature",
  "properties": {
    "addr:full":"Kiebachg 14 Innsbruck Tirol 6020",
    "addr:housenumber":"14",
    "addr:postcode":"6020",
    "addr:street":"Kiebachg;Tirol",
    "iso:country":"AT",
    "sg:address":"Kiebachg 14",
    "sg:city":"Innsbruck",
    "sg:orig_category":"Antiquariate",
    "sg:phone":"+43 512 581386",
    "sg:postcode":"6020",
    "sg:province":"Tirol",
    "wof:name":"Boschi Rudolf",
    "wof:placetype":"venue"
},
  "geometry": {"coordinates":[11.3925209045,47.2672729492],"type":"Point"}
}