{
  "type": "Feature",
  "properties": {
    "addr:full":"\u00dcbermellen 108 Mellau Vorarlberg 6881",
    "addr:housenumber":"108",
    "addr:postcode":"6881",
    "addr:street":"U\u0308Bermellen",
    "iso:country":"AT",
    "sg:address":"\u00dcbermellen 108",
    "sg:city":"Mellau",
    "sg:orig_category":"Fotografen",
    "sg:phone":"+43 4355 182328",
    "sg:postcode":"6881",
    "sg:province":"Vorarlberg",
    "wof:name":"Felder Tourismuswerbung GmbH",
    "wof:placetype":"venue"
},
  "geometry": {"coordinates":[9.8813295364,47.353313446],"type":"Point"}
}