{
  "type": "Feature",
  "properties": {
    "addr:full":"Mauthausner Str 11 Enns Ober\u00f6sterreich 4470",
    "addr:postcode":"4470",
    "addr:street":"Str 11",
    "iso:country":"AT",
    "sg:address":"Mauthausner Str 11",
    "sg:city":"Enns",
    "sg:orig_category":"Freizeitangebote U -Einrichtungen",
    "sg:phone":"+43 4372 2382680",
    "sg:postcode":"4470",
    "sg:province":"Ober\u00f6sterreich",
    "wof:name":"netstorm Sch\u00fcler- und Jugend Kommunikationszentrum",
    "wof:placetype":"venue"
},
  "geometry": {"coordinates":[14.4799804688,48.2156105042],"type":"Point"}
}