{
  "type": "Feature",
  "properties": {
    "iso:country":"AT",
    "sg:address":"Spielmanng 8",
    "sg:city":"Wien",
    "sg:orig_category":"Sportanlagen",
    "sg:phone":"+43 1 3300656",
    "sg:postcode":"1200",
    "sg:province":"Wien",
    "wof:name":"Sportanlage d Gemeinde Wien",
    "wof:placetype":"venue"
},
  "geometry": {"coordinates":[16.3701648712,48.2427787781],"type":"Point"}
}