{
  "type": "Feature",
  "properties": {
    "addr:full":"Hafferlstr 18 Lambach Ober\u00f6sterreich 4650",
    "addr:housenumber":"18",
    "addr:postcode":"4650",
    "addr:street":"Hafferlstr",
    "iso:country":"AT",
    "sg:address":"Hafferlstr 18",
    "sg:city":"Lambach",
    "sg:orig_category":"Erdarbeiten",
    "sg:phone":"+43 7245 24992",
    "sg:postcode":"4650",
    "sg:province":"Ober\u00f6sterreich",
    "wof:name":"Huemer Leopold GesmbH",
    "wof:placetype":"venue"
},
  "geometry": {"coordinates":[13.8672475815,48.0899162292],"type":"Point"}
}