{
  "type": "Feature",
  "properties": {
    "iso:country":"AT",
    "sg:address":"Wiener Str 51",
    "sg:city":"Hornstein",
    "sg:orig_category":"Massagen",
    "sg:phone":"+43 2689 3399",
    "sg:postcode":"7053",
    "sg:province":"Burgenland",
    "wof:name":"Danek Johanna",
    "wof:placetype":"venue"
},
  "geometry": {"coordinates":[16.4389190674,47.8862037659],"type":"Point"}
}