{
  "type": "Feature",
  "properties": {
    "addr:full":"Viktringer Pl 5 Klagenfurt-Viktring K\u00e4rnten 9073",
    "addr:housenumber":"5",
    "addr:postcode":"9073",
    "addr:street":"Viktringer Pl;Kaernten",
    "iso:country":"AT",
    "sg:address":"Viktringer Pl 5",
    "sg:city":"Klagenfurt-Viktring",
    "sg:classifiers":[
        {
            "category":"Internet Cafe",
            "subcategory":"None",
            "type":"Food & Drink"
        }
    ],
    "sg:phone":"+43 463 2929990",
    "sg:postcode":"9073",
    "sg:province":"K\u00e4rnten",
    "sg:tags":[
        "internet-provider"
    ],
    "wof:name":"HAPPYnet Dienstleistungs GmbH",
    "wof:placetype":"venue"
},
  "geometry": {"coordinates":[14.2695817947,46.5939674377],"type":"Point"}
}