{
  "type": "Feature",
  "properties": {
    "iso:country":"AT",
    "sg:address":"Harbach 89",
    "sg:city":"Bad Hofgastein",
    "sg:orig_category":"Schlossereien",
    "sg:phone":"+43 4364 328770",
    "sg:postcode":"5630",
    "sg:province":"Salzburg",
    "wof:name":"N\u00e4hr GmbH & Co KG",
    "wof:placetype":"venue"
},
  "geometry": {"coordinates":[13.1119976044,47.2121734619],"type":"Point"}
}