{
  "type": "Feature",
  "properties": {
    "addr:full":"Fuchsluckengasse 5 Steyr Ober\u00f6sterreich 4400",
    "addr:housenumber":"5",
    "addr:postcode":"4400",
    "addr:street":"Fuchsluckengasse;Oberoesterreich",
    "iso:country":"AT",
    "sg:address":"Fuchsluckengasse 5",
    "sg:city":"Steyr",
    "sg:classifiers":[
        {
            "category":"Government",
            "subcategory":"Fire Station",
            "type":"Public Place"
        }
    ],
    "sg:phone":"+43 7252 53110",
    "sg:postcode":"4400",
    "sg:province":"Ober\u00f6sterreich",
    "sg:tags":[
        "equipment",
        "extinguishing"
    ],
    "wof:name":"Dietmar R\u00f6tzer Ges.m.b.H.",
    "wof:placetype":"venue"
},
  "geometry": {"coordinates":[14.4251117706,48.038192749],"type":"Point"}
}