{
  "type": "Feature",
  "properties": {
    "addr:full":"Am Irrsee 10 Mondsee Ober\u00f6sterreich 5310",
    "addr:housenumber":"10",
    "addr:postcode":"5310",
    "addr:street":"Am Irrsee;Oberoesterreich",
    "iso:country":"AT",
    "sg:address":"Am Irrsee 10",
    "sg:city":"Mondsee",
    "sg:orig_category":"Appartements / Ferienwohnungen",
    "sg:phone":"+43 6234 8272",
    "sg:postcode":"5310",
    "sg:province":"Ober\u00f6sterreich",
    "wof:name":"Babyhof Schink",
    "wof:placetype":"venue"
},
  "geometry": {"coordinates":[13.3008441925,47.8907051086],"type":"Point"}
}