{
  "type": "Feature",
  "properties": {
    "iso:country":"AT",
    "sg:address":"Landstr 84/3",
    "sg:city":"Linz",
    "sg:orig_category":"Werbeagenturen",
    "sg:phone":"+43 732 66305921",
    "sg:postcode":"4020",
    "sg:province":"Ober\u00f6sterreich",
    "wof:name":"Pillcom Werbung",
    "wof:placetype":"venue"
},
  "geometry": {"coordinates":[14.2917804718,48.2963523865],"type":"Point"}
}