{
  "type": "Feature",
  "properties": {
    "iso:country":"AT",
    "sg:address":"Klosterg 18",
    "sg:city":"Pressbaum",
    "sg:orig_category":"Non-Classified Establishments",
    "sg:phone":"+43 2233 52172",
    "sg:postcode":"3021",
    "sg:province":"Nieder\u00f6sterreich",
    "wof:name":"Konvent d Elisabethinen",
    "wof:placetype":"venue"
},
  "geometry": {"coordinates":[16.079990387,48.1833305359],"type":"Point"}
}