{
  "type": "Feature",
  "properties": {
    "iso:country":"AT",
    "sg:address":"Hauptstr. 65",
    "sg:city":"Deutschkreutz",
    "sg:classifiers":[
        {
            "category":"Bars & Pubs",
            "subcategory":"Nightclub",
            "type":"Food & Drink"
        }
    ],
    "sg:phone":"+43 4326 1380229",
    "sg:postcode":"7301",
    "sg:province":"Burgenland",
    "sg:tags":[
        "cake",
        "bread"
    ],
    "wof:name":"PRUNNER BROT GESMBH",
    "wof:placetype":"venue"
},
  "geometry": {"coordinates":[16.6259593964,47.5992050171],"type":"Point"}
}