{
  "type": "Feature",
  "properties": {
    "iso:country":"AT",
    "sg:address":"St.-Veit-G 18",
    "sg:city":"Wien",
    "sg:orig_category":"Architekten",
    "sg:phone":"+43 1 877495420",
    "sg:postcode":"1130",
    "sg:province":"Wien",
    "wof:name":"J\u00f6chlinger Ursula Dipl-Ing",
    "wof:placetype":"venue"
},
  "geometry": {"coordinates":[16.2836513519,48.1847877502],"type":"Point"}
}