{
  "type": "Feature",
  "properties": {
    "addr:full":"Himmelreichweg 1 Wattens Tirol 6112",
    "addr:housenumber":"1",
    "addr:postcode":"6112",
    "addr:street":"Himmelreichweg;Tirol",
    "iso:country":"AT",
    "sg:address":"Himmelreichweg 1",
    "sg:city":"Wattens",
    "sg:orig_category":"Lebensmittel / Einzelhandel",
    "sg:phone":"+43 5224 55233",
    "sg:postcode":"6112",
    "sg:province":"Tirol",
    "wof:name":"Billa AG",
    "wof:placetype":"venue"
},
  "geometry": {"coordinates":[11.5833215714,47.288898468],"type":"Point"}
}