{
  "type": "Feature",
  "properties": {
    "iso:country":"AT",
    "sg:address":"Greben 570",
    "sg:city":"Bezau",
    "sg:orig_category":"Appartements / Ferienwohnungen",
    "sg:phone":"+43 4355 142937",
    "sg:postcode":"6870",
    "sg:province":"Vorarlberg",
    "wof:name":"Natter Marlene",
    "wof:placetype":"venue"
},
  "geometry": {"coordinates":[9.9000997543,47.3822059631],"type":"Point"}
}