{
  "type": "Feature",
  "properties": {
    "iso:country":"AT",
    "sg:address":"Peterspl 9",
    "sg:city":"Wien",
    "sg:orig_category":"Immobilienmakler",
    "sg:phone":"+43 1 53308870",
    "sg:postcode":"1010",
    "sg:province":"Wien",
    "sg:website":"www.stanzel.at",
    "wof:name":"Stanzel & Co Wohnungs- und Gesch\u00e4ftsvermittlung GmbH",
    "wof:placetype":"venue"
},
  "geometry": {"coordinates":[16.3703708649,48.2096977234],"type":"Point"}
}