{
  "type": "Feature",
  "properties": {
    "addr:full":"Oberlangkampfen 129 Kirchbichl Tirol 6322",
    "addr:housenumber":"129",
    "addr:postcode":"6322",
    "addr:street":"Oberlangkampfen;Tirol",
    "iso:country":"AT",
    "sg:address":"Oberlangkampfen 129",
    "sg:city":"Kirchbichl",
    "sg:orig_category":"Unternehmensberatung",
    "sg:phone":"+43 5332 81202",
    "sg:postcode":"6322",
    "sg:province":"Tirol",
    "wof:name":"A S Gefahrgutberatung - Alfred Schmid OEG",
    "wof:placetype":"venue"
},
  "geometry": {"coordinates":[12.0880002975,47.5128707886],"type":"Point"}
}