{
  "type": "Feature",
  "properties": {
    "addr:full":"Spanheimerstr 5 Wolfsberg K\u00e4rnten 9400",
    "addr:housenumber":"5;kaernten",
    "addr:postcode":"9400",
    "addr:street":"Spanheimerstr",
    "iso:country":"AT",
    "sg:address":"Spanheimerstr 5",
    "sg:city":"Wolfsberg",
    "sg:classifiers":[
        {
            "category":"Manufacturing",
            "subcategory":"Rubber & Plastics",
            "type":"Manufacturing & Wholesale Goods"
        }
    ],
    "sg:phone":"+43 4352 52045",
    "sg:postcode":"9400",
    "sg:province":"K\u00e4rnten",
    "sg:tags":[
        "safe",
        "u",
        "tresore"
    ],
    "wof:name":"Schutz & Sicherheit Mosgan",
    "wof:placetype":"venue"
},
  "geometry": {"coordinates":[14.8403682709,46.8401412964],"type":"Point"}
}