{
  "type": "Feature",
  "properties": {
    "addr:full":"Burgstallweg 23 Kapfenberg Steiermark 8605",
    "addr:housenumber":"23",
    "addr:postcode":"8605",
    "addr:street":"Burgstallweg",
    "iso:country":"AT",
    "sg:address":"Burgstallweg 23",
    "sg:city":"Kapfenberg",
    "sg:orig_category":"Drehereien",
    "sg:phone":"+43 3862 35521",
    "sg:postcode":"8605",
    "sg:province":"Steiermark",
    "wof:name":"Stelzer Fertigungstechnik GmbH",
    "wof:placetype":"venue"
},
  "geometry": {"coordinates":[15.3431682587,47.4590873718],"type":"Point"}
}