{
  "type": "Feature",
  "properties": {
    "addr:full":"Litzelhofenstr 9/1 Spittal an der Drau K\u00e4rnten 9800",
    "addr:housenumber":"9 / 1",
    "addr:postcode":"9800",
    "addr:street":"Litzelhofenstr;Kaernten",
    "iso:country":"AT",
    "sg:address":"Litzelhofenstr 9/1",
    "sg:city":"Spittal an der Drau",
    "sg:orig_category":"Lebens- U Sozialberatung",
    "sg:phone":"+43 4347 62339290",
    "sg:postcode":"9800",
    "sg:province":"K\u00e4rnten",
    "wof:name":"IFP Institut f Familienberatung u Psychotherapie d Caritas",
    "wof:placetype":"venue"
},
  "geometry": {"coordinates":[13.4965162277,46.7956466675],"type":"Point"}
}