{
  "type": "Feature",
  "properties": {
    "addr:full":"Industriegel\u00e4nde Neufeld an der Leitha Burgenland 2491",
    "addr:postcode":"2491",
    "iso:country":"AT",
    "sg:address":"Industriegel\u00e4nde",
    "sg:city":"Neufeld an der Leitha",
    "sg:orig_category":"Autohandel",
    "sg:phone":"+43 2624 53951",
    "sg:postcode":"2491",
    "sg:province":"Burgenland",
    "wof:name":"Saile Sylvia",
    "wof:placetype":"venue"
},
  "geometry": {"coordinates":[16.3943119049,47.8553848267],"type":"Point"}
}