{
  "type": "Feature",
  "properties": {
    "addr:full":"Wilding 13 Geboltskirchen Ober\u00f6sterreich 4682",
    "addr:housenumber":"13",
    "addr:postcode":"4682",
    "addr:street":"Wilding",
    "iso:country":"AT",
    "sg:address":"Wilding 13",
    "sg:city":"Geboltskirchen",
    "sg:orig_category":"Pianos, Historical",
    "sg:phone":"+43 7732 3958",
    "sg:postcode":"4682",
    "sg:province":"Ober\u00f6sterreich",
    "wof:name":"Alfred Knoglinger - Gebrauchtklaviere",
    "wof:placetype":"venue"
},
  "geometry": {"coordinates":[13.6535558701,48.1637458801],"type":"Point"}
}