{
  "type": "Feature",
  "properties": {
    "addr:full":"Nr 28 St. Christophen Nieder\u00f6sterreich 3051",
    "addr:postcode":"3051",
    "addr:street":"Nr 28",
    "iso:country":"AT",
    "sg:address":"Nr 28",
    "sg:city":"St. Christophen",
    "sg:orig_category":"Erdarbeiten",
    "sg:phone":"+43 2774 6370",
    "sg:postcode":"3051",
    "sg:province":"Nieder\u00f6sterreich",
    "wof:name":"D\u00fcrer GesmbH",
    "wof:placetype":"venue"
},
  "geometry": {"coordinates":[15.8867139816,48.1740989685],"type":"Point"}
}