{
  "type": "Feature",
  "properties": {
    "addr:full":"R\u00e4cking 7 Melk Nieder\u00f6sterreich 3390",
    "addr:housenumber":"7",
    "addr:postcode":"3390",
    "addr:street":"Raecking",
    "iso:country":"AT",
    "sg:address":"R\u00e4cking 7",
    "sg:city":"Melk",
    "sg:orig_category":"Waagen / Reparatur U Service",
    "sg:phone":"+43 2752 52463",
    "sg:postcode":"3390",
    "sg:province":"Nieder\u00f6sterreich",
    "wof:name":"Gassner Wiege- und Me\u00dftechnik GmbH",
    "wof:placetype":"venue"
},
  "geometry": {"coordinates":[15.331870079,48.230178833],"type":"Point"}
}