{
  "type": "Feature",
  "properties": {
    "addr:full":"M\u00fcllerviertel 2 Micheldorf in Ober\u00f6sterreich Ober\u00f6sterreich 4563",
    "addr:housenumber":"2",
    "addr:postcode":"4563",
    "addr:street":"Muellerviertel",
    "iso:country":"AT",
    "sg:address":"M\u00fcllerviertel 2",
    "sg:city":"Micheldorf in Ober\u00f6sterreich",
    "sg:classifiers":[
        {
            "category":"Manufacturing",
            "subcategory":"Tools & Machinery",
            "type":"Manufacturing & Wholesale Goods"
        }
    ],
    "sg:phone":"+43 7582 60922",
    "sg:postcode":"4563",
    "sg:province":"Ober\u00f6sterreich",
    "sg:tags":[
        "extrusion"
    ],
    "sg:website":"emo.at",
    "wof:name":"EMO Extrusion Molding Ges.m.b.H.",
    "wof:placetype":"venue"
},
  "geometry": {"coordinates":[14.1334323883,47.877910614],"type":"Point"}
}