{
  "type": "Feature",
  "properties": {
    "iso:country":"AT",
    "sg:address":"Wilhelmstr 14",
    "sg:city":"Tulln an der Donau",
    "sg:orig_category":"Fliesen U Platten",
    "sg:phone":"+43 4322 7264500",
    "sg:postcode":"3430",
    "sg:province":"Nieder\u00f6sterreich",
    "wof:name":"Hallach GmbH",
    "wof:placetype":"venue"
},
  "geometry": {"coordinates":[16.0565738678,48.3296966553],"type":"Point"}
}