{
  "type": "Feature",
  "properties": {
    "addr:full":"Nr 71a Kaltenbach Tirol 6272",
    "addr:postcode":"6272",
    "addr:street":"Nr 71A Kaltenbach",
    "iso:country":"AT",
    "sg:address":"Nr 71a",
    "sg:city":"Kaltenbach",
    "sg:orig_category":"Pensionen / Privatzimmer",
    "sg:phone":"+43 5283 2456",
    "sg:postcode":"6272",
    "sg:province":"Tirol",
    "wof:name":"G\u00e4stehaus Abacher",
    "wof:placetype":"venue"
},
  "geometry": {"coordinates":[11.8752498627,47.2923049927],"type":"Point"}
}