{
  "type": "Feature",
  "properties": {
    "addr:full":"Teichstr 1 Waldneukirchen Ober\u00f6sterreich 4595",
    "addr:housenumber":"1",
    "addr:postcode":"4595",
    "addr:street":"Teichstr",
    "iso:country":"AT",
    "sg:address":"Teichstr 1",
    "sg:city":"Waldneukirchen",
    "sg:orig_category":"Feuerwehren",
    "sg:phone":"+43 7258 4122",
    "sg:postcode":"4595",
    "sg:province":"Ober\u00f6sterreich",
    "wof:name":"Freiwillige Feuerwehr Waldneukirchen",
    "wof:placetype":"venue"
},
  "geometry": {"coordinates":[14.258348465,47.9963989258],"type":"Point"}
}