{
  "type": "Feature",
  "properties": {
    "addr:full":"Freiherr-von-Rost-Weg 10 Vils Tirol 6682",
    "addr:housenumber":"10",
    "addr:postcode":"6682",
    "addr:street":"Freiherr-Von-Rost-Weg;Tirol",
    "iso:country":"AT",
    "sg:address":"Freiherr-von-Rost-Weg 10",
    "sg:city":"Vils",
    "sg:orig_category":"Weiterbildungsinstitute M Allg U Berufl Bildungsangebot",
    "sg:phone":"+43 4356 778636",
    "sg:postcode":"6682",
    "sg:province":"Tirol",
    "wof:name":"Erwachsenenschule Vils",
    "wof:placetype":"venue"
},
  "geometry": {"coordinates":[10.6340112686,47.5461349487],"type":"Point"}
}