{
  "type": "Feature",
  "properties": {
    "addr:full":"Eferdinger Str 51 Wels Ober\u00f6sterreich 4600",
    "addr:housenumber":"51",
    "addr:postcode":"4600",
    "addr:street":"Str;Oberoesterreich",
    "iso:country":"AT",
    "sg:address":"Eferdinger Str 51",
    "sg:city":"Wels",
    "sg:orig_category":"Tanzcafes",
    "sg:phone":"+43 699 13000084",
    "sg:postcode":"4600",
    "sg:province":"Ober\u00f6sterreich",
    "wof:name":"Kupferdachl",
    "wof:placetype":"venue"
},
  "geometry": {"coordinates":[14.0268192291,48.1762809753],"type":"Point"}
}