{
  "type": "Feature",
  "properties": {
    "iso:country":"AT",
    "sg:address":"Kirchenpl 8",
    "sg:city":"Zeiselmauer",
    "sg:orig_category":"Papier- U Schreibwaren / Einzelhandel",
    "sg:phone":"+43 2242 72003",
    "sg:postcode":"3424",
    "sg:province":"Nieder\u00f6sterreich",
    "wof:name":"Sch\u00f6n R & J OEG",
    "wof:placetype":"venue"
},
  "geometry": {"coordinates":[16.1768188477,48.3293991089],"type":"Point"}
}