{
  "type": "Feature",
  "properties": {
    "addr:full":"Klagenfurter Str Velden am W\u00f6rther See K\u00e4rnten 9220",
    "addr:postcode":"9220",
    "addr:street":"Str Velden Am Woerther;Kaernten",
    "iso:country":"AT",
    "sg:address":"Klagenfurter Str",
    "sg:city":"Velden am W\u00f6rther See",
    "sg:orig_category":"Transportunternehmen",
    "sg:phone":"+43 4274 2081",
    "sg:postcode":"9220",
    "sg:province":"K\u00e4rnten",
    "wof:name":"Schurian Andreas",
    "wof:placetype":"venue"
},
  "geometry": {"coordinates":[14.0697746277,46.6221504211],"type":"Point"}
}