{
  "type": "Feature",
  "properties": {
    "iso:country":"AT",
    "sg:address":"Nr 47",
    "sg:city":"Getzersdorf",
    "sg:orig_category":"Tonstudios",
    "sg:phone":"+43 4327 8285013",
    "sg:postcode":"3131",
    "sg:province":"Nieder\u00f6sterreich",
    "wof:name":"Tonstudio Parzer",
    "wof:placetype":"venue"
},
  "geometry": {"coordinates":[15.703040123,48.3295707703],"type":"Point"}
}