{
  "type": "Feature",
  "properties": {
    "addr:full":"Haller Str 201a Innsbruck Tirol 6020",
    "addr:postcode":"6020",
    "addr:street":"Str 201A;Tirol",
    "iso:country":"AT",
    "sg:address":"Haller Str 201a",
    "sg:city":"Innsbruck",
    "sg:orig_category":"Kosmetische Produkte / Einzelhandel",
    "sg:phone":"+43 512 3906063",
    "sg:postcode":"6020",
    "sg:province":"Tirol",
    "wof:name":"Snik Suncosmetics Austria",
    "wof:placetype":"venue"
},
  "geometry": {"coordinates":[11.4379816055,47.2765312195],"type":"Point"}
}