{
  "type": "Feature",
  "properties": {
    "addr:full":"Nr 8 Pischelsdorf am Engelbach Ober\u00f6sterreich 5233",
    "addr:postcode":"5233",
    "addr:street":"Nr;Pischelsdorf",
    "iso:country":"AT",
    "sg:address":"Nr 8",
    "sg:city":"Pischelsdorf am Engelbach",
    "sg:orig_category":"Fleischhauereien",
    "sg:phone":"+43 4377 427201",
    "sg:postcode":"5233",
    "sg:province":"Ober\u00f6sterreich",
    "wof:name":"S\u00e4gm\u00fcller Josef",
    "wof:placetype":"venue"
},
  "geometry": {"coordinates":[13.0833120346,48.1299591064],"type":"Point"}
}