{
  "type": "Feature",
  "properties": {
    "iso:country":"AT",
    "sg:address":"Steinamangerer Str 67",
    "sg:city":"Oberwart",
    "sg:orig_category":"Nachtclubs-Bars",
    "sg:phone":"+43 676 9272777",
    "sg:postcode":"7400",
    "sg:province":"Burgenland",
    "wof:name":"Blue Night Bar",
    "wof:placetype":"venue"
},
  "geometry": {"coordinates":[16.2205028534,47.2820739746],"type":"Point"}
}