{
  "type": "Feature",
  "properties": {
    "iso:country":"AT",
    "sg:address":"Etrichstr 34/6",
    "sg:city":"Wien",
    "sg:orig_category":"Apotheken",
    "sg:phone":"+43 1 7670845",
    "sg:postcode":"1110",
    "sg:province":"Wien",
    "wof:name":"Regenbogenapotheke Am Leberberg",
    "wof:placetype":"venue"
},
  "geometry": {"coordinates":[16.4651069641,48.1534042358],"type":"Point"}
}