{
  "type": "Feature",
  "properties": {
    "iso:country":"AT",
    "sg:address":"Obere Hauptstr 12",
    "sg:city":"Sieggraben",
    "sg:orig_category":"Non-Classified Establishments",
    "sg:phone":"+43 2621 2546",
    "sg:postcode":"7223",
    "sg:province":"Burgenland",
    "wof:name":"Pfarramt",
    "wof:placetype":"venue"
},
  "geometry": {"coordinates":[16.3795204163,47.6504745483],"type":"Point"}
}