{
  "type": "Feature",
  "properties": {
    "addr:full":"R\u00f6cklbrunnstr 39b Salzburg Salzburg 5020",
    "addr:housenumber":"39b",
    "addr:postcode":"5020",
    "addr:street":"Roecklbrunnstr;Salzburg",
    "iso:country":"AT",
    "sg:address":"R\u00f6cklbrunnstr 39b",
    "sg:city":"Salzburg",
    "sg:orig_category":"Acrylglas",
    "sg:phone":"+43 4366 28747750",
    "sg:postcode":"5020",
    "sg:province":"Salzburg",
    "wof:name":"Winkler Werner GmbH & Co KEG",
    "wof:placetype":"venue"
},
  "geometry": {"coordinates":[13.0573043823,47.8122711182],"type":"Point"}
}