{
  "type": "Feature",
  "properties": {
    "iso:country":"AT",
    "sg:address":"Brenner Str 77",
    "sg:city":"Matrei am Brenner",
    "sg:orig_category":"Friseure U Frisiersalons",
    "sg:phone":"+43 4352 736366",
    "sg:postcode":"6143",
    "sg:province":"Tirol",
    "wof:name":"Geier Gustav",
    "wof:placetype":"venue"
},
  "geometry": {"coordinates":[11.4523620605,47.133644104],"type":"Point"}
}