{
  "type": "Feature",
  "properties": {
    "iso:country":"AT",
    "sg:address":"Stadtpl 17",
    "sg:city":"Laa an der Thaya",
    "sg:orig_category":"Lebens- U Sozialberatung",
    "sg:phone":"+43 4325 2284670",
    "sg:postcode":"2136",
    "sg:province":"Nieder\u00f6sterreich",
    "wof:name":"Ehe- Familien- u Lebensberatung",
    "wof:placetype":"venue"
},
  "geometry": {"coordinates":[16.3841266632,48.72108078],"type":"Point"}
}