{
  "type": "Feature",
  "properties": {
    "iso:country":"AT",
    "sg:address":"Leonhardstr 104",
    "sg:city":"Graz",
    "sg:orig_category":"Unternehmensberatung",
    "sg:phone":"+43 316 338338900",
    "sg:postcode":"8010",
    "sg:province":"Steiermark",
    "wof:name":"Consulting Team UnternehmensberatungsgesmbH",
    "wof:placetype":"venue"
},
  "geometry": {"coordinates":[15.4612770081,47.0762138367],"type":"Point"}
}