{
  "type": "Feature",
  "properties": {
    "addr:full":"Hauptplatz 9 Wiener Neustadt Nieder\u00f6sterreich 2700",
    "addr:housenumber":"9",
    "addr:postcode":"2700",
    "addr:street":"Hauptplatz",
    "iso:country":"AT",
    "sg:address":"Hauptplatz 9",
    "sg:city":"Wiener Neustadt",
    "sg:classifiers":[
        {
            "category":"Arena",
            "subcategory":"Bull Ring",
            "type":"Entertainment"
        }
    ],
    "sg:phone":"+43 2622 26890",
    "sg:postcode":"2700",
    "sg:province":"Nieder\u00f6sterreich",
    "sg:tags":[
        "brooch"
    ],
    "wof:name":"Gerhard G\u00f6tz",
    "wof:placetype":"venue"
},
  "geometry": {"coordinates":[16.2425708771,47.8134117126],"type":"Point"}
}