{
  "type": "Feature",
  "properties": {
    "addr:full":"Berlepschgasse 1 Wien Wien 1100",
    "addr:housenumber":"1",
    "addr:postcode":"1100",
    "addr:street":"Berlepschgasse",
    "iso:country":"AT",
    "sg:address":"Berlepschgasse 1",
    "sg:city":"Wien",
    "sg:classifiers":[
        {
            "category":"Building & Trades",
            "subcategory":"Pest Control",
            "type":"Services"
        }
    ],
    "sg:phone":"+43 1 68821510",
    "sg:postcode":"1100",
    "sg:province":"Wien",
    "sg:tags":[
        "agricultural",
        "chain"
    ],
    "sg:website":"amw-pewag.com",
    "wof:name":"AMW HandelsgmbH u. Co KG",
    "wof:placetype":"venue"
},
  "geometry": {"coordinates":[16.3840446472,48.1423797607],"type":"Point"}
}