{
  "type": "Feature",
  "properties": {
    "addr:full":"Franziskanerpl 6 Wien Wien 1010",
    "addr:housenumber":"6",
    "addr:postcode":"1010",
    "addr:street":"Franziskanerpl",
    "iso:country":"AT",
    "sg:address":"Franziskanerpl 6",
    "sg:city":"Wien",
    "sg:orig_category":"Juweliere, Gold- U Silberschmiede",
    "sg:phone":"+43 4315 128818",
    "sg:postcode":"1010",
    "sg:province":"Wien",
    "sg:website":"michael-w-fischer.at",
    "wof:name":"Fischer Michael Wolfgang",
    "wof:placetype":"venue"
},
  "geometry": {"coordinates":[16.3740158081,48.2063941956],"type":"Point"}
}