{
  "type": "Feature",
  "properties": {
    "addr:full":"Roseng 1 Lienz Tirol 9900",
    "addr:housenumber":"1",
    "addr:postcode":"9900",
    "addr:street":"Roseng;Tirol",
    "iso:country":"AT",
    "sg:address":"Roseng 1",
    "sg:city":"Lienz",
    "sg:orig_category":"Damenmoden",
    "sg:phone":"+43 4348 5264148",
    "sg:postcode":"9900",
    "sg:province":"Tirol",
    "wof:name":"H & M Hennes & Mauritz GesmbH",
    "wof:placetype":"venue"
},
  "geometry": {"coordinates":[12.7661933899,46.829410553],"type":"Point"}
}