{
  "type": "Feature",
  "properties": {
    "iso:country":"AT",
    "sg:address":"Wolf-Dietrich-Str 5",
    "sg:city":"Salzburg",
    "sg:orig_category":"Galerien",
    "sg:phone":"+43 650 7287349",
    "sg:postcode":"5020",
    "sg:province":"Salzburg",
    "wof:name":"Galerie Offener Kreis",
    "wof:placetype":"venue"
},
  "geometry": {"coordinates":[13.0480546951,47.8045845032],"type":"Point"}
}