{
  "type": "Feature",
  "properties": {
    "iso:country":"AT",
    "sg:address":"Nr 146",
    "sg:city":"Gro\u00dfwilfersdorf",
    "sg:classifiers":[
        {
            "category":"Home & Garden",
            "subcategory":"Garden Supply",
            "type":"Retail Goods"
        }
    ],
    "sg:phone":"+43 4333 85435",
    "sg:postcode":"8263",
    "sg:province":"Steiermark",
    "sg:tags":[
        "schotter",
        "sand",
        "u"
    ],
    "wof:name":"G\u00f6lles Josef",
    "wof:placetype":"venue"
},
  "geometry": {"coordinates":[166.9221496582,-0.5282999873],"type":"Point"}
}