{
  "type": "Feature",
  "properties": {
    "iso:country":"AT",
    "sg:address":"Nr 65",
    "sg:city":"St. Johann am Wimberg",
    "sg:orig_category":"Autohandel",
    "sg:phone":"+43 4372 177202",
    "sg:postcode":"4172",
    "sg:province":"Ober\u00f6sterreich",
    "wof:name":"Krauck Franz",
    "wof:placetype":"venue"
},
  "geometry": {"coordinates":[14.1302614212,48.4888267517],"type":"Point"}
}