{
  "type": "Feature",
  "properties": {
    "addr:full":"Obere Donaustrasse 43 Wien Wien 1020",
    "addr:housenumber":"43",
    "addr:postcode":"1020",
    "addr:street":"Obere Donaustrasse",
    "iso:country":"AT",
    "sg:address":"Obere Donaustrasse 43",
    "sg:city":"Wien",
    "sg:classifiers":[
        {
            "category":"Autos & Motor Vehicles",
            "subcategory":"Auto Supplies",
            "type":"Retail Goods"
        }
    ],
    "sg:phone":"+43 1 33034840",
    "sg:postcode":"1020",
    "sg:province":"Wien",
    "sg:tags":[
        "clutch"
    ],
    "sg:website":"renold.at",
    "wof:name":"Renold Ges.m.b.H.",
    "wof:placetype":"venue"
},
  "geometry": {"coordinates":[16.3708553314,48.2195358276],"type":"Point"}
}