{
  "type": "Feature",
  "properties": {
    "addr:full":"Herberweg 5 Piberbach Ober\u00f6sterreich 4533",
    "addr:housenumber":"5",
    "addr:postcode":"4533",
    "addr:street":"Herberweg",
    "iso:country":"AT",
    "sg:address":"Herberweg 5",
    "sg:city":"Piberbach",
    "sg:orig_category":"Stillberatung",
    "sg:phone":"+43 7227 4180",
    "sg:postcode":"4533",
    "sg:province":"Ober\u00f6sterreich",
    "wof:name":"Stillberatung - La Leche Liga Ober\u00f6sterreich - Secilia K\u00f6glberger",
    "wof:placetype":"venue"
},
  "geometry": {"coordinates":[14.2425413132,48.1313018799],"type":"Point"}
}