{
  "type": "Feature",
  "properties": {
    "addr:full":"Hauptstr 33 Unterpullendorf Burgenland 7452",
    "addr:housenumber":"33",
    "addr:postcode":"7452",
    "addr:street":"Hauptstr",
    "iso:country":"AT",
    "sg:address":"Hauptstr 33",
    "sg:city":"Unterpullendorf",
    "sg:orig_category":"Wasserschadensanierung",
    "sg:phone":"+43 2641 23390",
    "sg:postcode":"7452",
    "sg:province":"Burgenland",
    "wof:name":"Me Tro Tech Mess- und Trockentechnik",
    "wof:placetype":"venue"
},
  "geometry": {"coordinates":[16.5346488953,47.4776268005],"type":"Point"}
}