{
  "type": "Feature",
  "properties": {
    "iso:country":"AT",
    "sg:address":"Stieglstr 1a",
    "sg:city":"Salzburg",
    "sg:classifiers":[
        {
            "category":"Shopping",
            "subcategory":"Thrift Store",
            "type":"Retail Goods"
        }
    ],
    "sg:phone":"+43 662 831509",
    "sg:postcode":"5020",
    "sg:province":"Salzburg",
    "sg:tags":[
        "second-hand-shops"
    ],
    "wof:name":"B\u00e4rli Second Hand Shop f Kinder",
    "wof:placetype":"venue"
},
  "geometry": {"coordinates":[13.0233621597,47.79637146],"type":"Point"}
}