{
  "type": "Feature",
  "properties": {
    "addr:full":"Innbachtalstr 3 Pichl Ober\u00f6sterreich 4632",
    "addr:housenumber":"3",
    "addr:postcode":"4632",
    "addr:street":"Innbachtalstr",
    "iso:country":"AT",
    "sg:address":"Innbachtalstr 3",
    "sg:city":"Pichl",
    "sg:orig_category":"Fleischhauereien",
    "sg:phone":"+43 4372 478711",
    "sg:postcode":"4632",
    "sg:province":"Ober\u00f6sterreich",
    "wof:name":"Gasthaus Bruck Wirt",
    "wof:placetype":"venue"
},
  "geometry": {"coordinates":[13.8999576569,48.1844367981],"type":"Point"}
}