{
  "type": "Feature",
  "properties": {
    "iso:country":"AT",
    "sg:address":"Gmeingrube 8",
    "sg:city":"Trofaiach",
    "sg:orig_category":"Erdarbeiten",
    "sg:phone":"+43 664 1312655",
    "sg:postcode":"8793",
    "sg:province":"Steiermark",
    "wof:name":"Erdbau Transporte Hebenstreit Johann",
    "wof:placetype":"venue"
},
  "geometry": {"coordinates":[15.024974823,47.4117774963],"type":"Point"}
}