{
  "type": "Feature",
  "properties": {
    "addr:full":"Bahnhofstrasse 37 Ebensee Ober\u00f6sterreich 4802",
    "addr:housenumber":"37",
    "addr:postcode":"4802",
    "addr:street":"Bahnhofstrasse",
    "iso:country":"AT",
    "sg:address":"Bahnhofstrasse 37",
    "sg:city":"Ebensee",
    "sg:classifiers":[
        {
            "category":"Banks & Credit Unions",
            "subcategory":"Investment Brokerage",
            "type":"Services"
        }
    ],
    "sg:phone":"+43 6133 61610",
    "sg:postcode":"4802",
    "sg:province":"Ober\u00f6sterreich",
    "sg:tags":[
        "audio",
        "accessory"
    ],
    "wof:name":"Horst Neub\u00f6ck",
    "wof:placetype":"venue"
},
  "geometry": {"coordinates":[13.771437645,47.806438446],"type":"Point"}
}