{
  "type": "Feature",
  "properties": {
    "addr:full":"Kadischenallee 27 Warmbad K\u00e4rnten 9504",
    "addr:housenumber":"27",
    "addr:postcode":"9504",
    "addr:street":"Kadischenallee;Kaernten",
    "iso:country":"AT",
    "sg:address":"Kadischenallee 27",
    "sg:city":"Warmbad",
    "sg:orig_category":"Damenmoden",
    "sg:phone":"+43 4242 312313",
    "sg:postcode":"9504",
    "sg:province":"K\u00e4rnten",
    "wof:name":"Egger Klaus KEG",
    "wof:placetype":"venue"
},
  "geometry": {"coordinates":[13.8266592026,46.5881271362],"type":"Point"}
}