{
  "type": "Feature",
  "properties": {
    "addr:full":"Nr 121 Weiten Nieder\u00f6sterreich 3653",
    "addr:postcode":"3653",
    "addr:street":"Nr 121",
    "iso:country":"AT",
    "sg:address":"Nr 121",
    "sg:city":"Weiten",
    "sg:orig_category":"Banken U Sparkassen",
    "sg:phone":"+43 4327 588220",
    "sg:postcode":"3653",
    "sg:province":"Nieder\u00f6sterreich",
    "wof:name":"Raiffeisenbank Region Melk regGenmbH",
    "wof:placetype":"venue"
},
  "geometry": {"coordinates":[15.2651672363,48.2922363281],"type":"Point"}
}