{
  "type": "Feature",
  "properties": {
    "iso:country":"AT",
    "sg:address":"Landstra\u00dfer Hauptstr 21/11",
    "sg:city":"Wien",
    "sg:orig_category":"\u00c3\u201erzte / F Allgemeinmedizin",
    "sg:phone":"+43 1 7143418",
    "sg:postcode":"1030",
    "sg:province":"Wien",
    "wof:name":"Kapl Gerlinde MedR Dr",
    "wof:placetype":"venue"
},
  "geometry": {"coordinates":[16.3884677887,48.2045783997],"type":"Point"}
}