{
  "type": "Feature",
  "properties": {
    "addr:full":"Gruberstr 11 Heiligenkreuz im Wienerwald Nieder\u00f6sterreich 2532",
    "addr:housenumber":"11",
    "addr:postcode":"2532",
    "addr:street":"Gruberstr",
    "iso:country":"AT",
    "sg:address":"Gruberstr 11",
    "sg:city":"Heiligenkreuz im Wienerwald",
    "sg:orig_category":"Ballonfahrten",
    "sg:phone":"+43 4322 588566",
    "sg:postcode":"2532",
    "sg:province":"Nieder\u00f6sterreich",
    "sg:website":"ballonfahrt.at",
    "wof:name":"Balloon Exclusive Air",
    "wof:placetype":"venue"
},
  "geometry": {"coordinates":[16.1262493134,48.0570030212],"type":"Point"}
}