{
  "type": "Feature",
  "properties": {
    "addr:full":"Mittelgasse 38 Tribuswinkel Nieder\u00f6sterreich 2512",
    "addr:housenumber":"38",
    "addr:postcode":"2512",
    "addr:street":"Mittelgasse",
    "iso:country":"AT",
    "sg:address":"Mittelgasse 38",
    "sg:city":"Tribuswinkel",
    "sg:classifiers":[
        {
            "category":"Building & Trades",
            "subcategory":"Landscaping Services",
            "type":"Services"
        }
    ],
    "sg:phone":"+43 2253 89911",
    "sg:postcode":"2512",
    "sg:province":"Nieder\u00f6sterreich",
    "sg:tags":[
        "horticulture",
        "gardening",
        "landscape"
    ],
    "wof:name":"Gartendesign GmbH",
    "wof:placetype":"venue"
},
  "geometry": {"coordinates":[16.2946853638,47.9884490967],"type":"Point"}
}