{
  "type": "Feature",
  "properties": {
    "addr:full":"Nr 49 Hopfgarten in Defereggen Tirol 9961",
    "addr:postcode":"9961",
    "addr:street":"Nr 49",
    "iso:country":"AT",
    "sg:address":"Nr 49",
    "sg:city":"Hopfgarten in Defereggen",
    "sg:orig_category":"Holzschnitzereien",
    "sg:phone":"+43 4872 5266",
    "sg:postcode":"9961",
    "sg:province":"Tirol",
    "wof:name":"Blassnig Meisterwerkst\u00e4tte GmbH",
    "wof:placetype":"venue"
},
  "geometry": {"coordinates":[12.5194997787,46.9212799072],"type":"Point"}
}