{
  "type": "Feature",
  "properties": {
    "addr:full":"Landstr 22 Lochau Vorarlberg 6911",
    "addr:housenumber":"22",
    "addr:postcode":"6911",
    "addr:street":"Landstr",
    "iso:country":"AT",
    "sg:address":"Landstr 22",
    "sg:city":"Lochau",
    "sg:orig_category":"Gemeinden",
    "sg:phone":"+43 5574 421680",
    "sg:postcode":"6911",
    "sg:province":"Vorarlberg",
    "wof:name":"Gemeindeamt Lochau",
    "wof:placetype":"venue"
},
  "geometry": {"coordinates":[9.7514095306,47.5289802551],"type":"Point"}
}