{
  "type": "Feature",
  "properties": {
    "addr:full":"Nr 227 Rohrbach an der Lafnitz Steiermark 8234",
    "addr:postcode":"8234",
    "addr:street":"Nr 227",
    "iso:country":"AT",
    "sg:address":"Nr 227",
    "sg:city":"Rohrbach an der Lafnitz",
    "sg:orig_category":"Hauptschulen",
    "sg:phone":"+43 4333 3826090",
    "sg:postcode":"8234",
    "sg:province":"Steiermark",
    "wof:name":"Hauptschule",
    "wof:placetype":"venue"
},
  "geometry": {"coordinates":[15.9732465744,47.3812446594],"type":"Point"}
}