{
  "type": "Feature",
  "properties": {
    "addr:full":"Salzburger Str 20 W\u00f6rgl Tirol 6300",
    "addr:housenumber":"20",
    "addr:postcode":"6300",
    "addr:street":"Salzburger Str;Tirol",
    "iso:country":"AT",
    "sg:address":"Salzburger Str 20",
    "sg:city":"W\u00f6rgl",
    "sg:orig_category":"Waren Aller Art",
    "sg:phone":"+43 4353 3275012",
    "sg:postcode":"6300",
    "sg:province":"Tirol",
    "wof:name":"easy-sale OEG",
    "wof:placetype":"venue"
},
  "geometry": {"coordinates":[-69.3131027222,-51.6091995239],"type":"Point"}
}