{
  "type": "Feature",
  "properties": {
    "addr:full":"Neudeggerg 1/18 Wien Wien 1080",
    "addr:housenumber":"1 / 18",
    "addr:postcode":"1080",
    "addr:street":"Neudeggerg",
    "iso:country":"AT",
    "sg:address":"Neudeggerg 1/18",
    "sg:city":"Wien",
    "sg:orig_category":"Unternehmensberatung",
    "sg:phone":"+43 1 4054985",
    "sg:postcode":"1080",
    "sg:province":"Wien",
    "wof:name":"Bereuter & Partner Consulting GesmbH",
    "wof:placetype":"venue"
},
  "geometry": {"coordinates":[16.3517780304,48.2065887451],"type":"Point"}
}