{
  "type": "Feature",
  "properties": {
    "addr:full":"Steinerg. 32  Wien Wien 1230",
    "addr:housenumber":"32",
    "addr:postcode":"1230",
    "addr:street":"Steinerg.",
    "iso:country":"AT",
    "sg:address":"Steinerg. 32 ",
    "sg:city":"Wien",
    "sg:classifiers":[
        {
            "category":"Home & Garden",
            "subcategory":"Home Furnishings",
            "type":"Retail Goods"
        }
    ],
    "sg:phone":"+43 4318 659283",
    "sg:postcode":"1230",
    "sg:province":"Wien",
    "sg:tags":[
        "household"
    ],
    "wof:name":"KARASEK ST & CO",
    "wof:placetype":"venue"
},
  "geometry": {"coordinates":[16.2890758514,48.1425437927],"type":"Point"}
}