{
  "type": "Feature",
  "properties": {
    "addr:full":"Hietzinger Hauptstrasse 93 Wien Wien 1130",
    "addr:housenumber":"93",
    "addr:postcode":"1130",
    "addr:street":"Hietzinger Hauptstrasse",
    "iso:country":"AT",
    "sg:address":"Hietzinger Hauptstrasse 93",
    "sg:city":"Wien",
    "sg:classifiers":[
        {
            "category":"Retail",
            "subcategory":"Auto Repair",
            "type":"Services"
        }
    ],
    "sg:phone":"+43 1 87741180",
    "sg:postcode":"1130",
    "sg:province":"Wien",
    "sg:tags":[
        "machine",
        "fax",
        "system"
    ],
    "sg:website":"webhofer.at",
    "wof:name":"Franz Webhofer",
    "wof:placetype":"venue"
},
  "geometry": {"coordinates":[16.2793579102,48.1872901917],"type":"Point"}
}