{
  "type": "Feature",
  "properties": {
    "addr:full":"Sperlingweg 15 Gnigl Salzburg 5023",
    "addr:housenumber":"15",
    "addr:postcode":"5023",
    "addr:street":"Sperlingweg",
    "iso:country":"AT",
    "sg:address":"Sperlingweg 15",
    "sg:city":"Gnigl",
    "sg:orig_category":"Abdichtungen",
    "sg:phone":"+43 662 665163",
    "sg:postcode":"5023",
    "sg:province":"Salzburg",
    "wof:name":"Bauschutz Setscheny Stephan",
    "wof:placetype":"venue"
},
  "geometry": {"coordinates":[13.0778560638,47.823425293],"type":"Point"}
}