{
  "type": "Feature",
  "properties": {
    "iso:country":"AT",
    "sg:address":"Maria-Theresien-Str 5",
    "sg:city":"Wien",
    "sg:orig_category":"Spielkarten",
    "sg:phone":"+43 1 3194684",
    "sg:postcode":"1090",
    "sg:province":"Wien",
    "wof:name":"Fath Josef",
    "wof:placetype":"venue"
},
  "geometry": {"coordinates":[16.3626747131,48.2151031494],"type":"Point"}
}