{
  "type": "Feature",
  "properties": {
    "addr:full":"Nr 159 Dellach im Drautal K\u00e4rnten 9772",
    "addr:postcode":"9772",
    "addr:street":"Nr;Dellach;Drautal Kaernten",
    "iso:country":"AT",
    "sg:address":"Nr 159",
    "sg:city":"Dellach im Drautal",
    "sg:orig_category":"Maler, Anstreicher U Lackierer",
    "sg:phone":"+43 4347 14203",
    "sg:postcode":"9772",
    "sg:province":"K\u00e4rnten",
    "wof:name":"Breitegger Albert",
    "wof:placetype":"venue"
},
  "geometry": {"coordinates":[13.0824251175,46.7413406372],"type":"Point"}
}