{
  "type": "Feature",
  "properties": {
    "addr:full":"Wilhelm-Greil-Str 21 Innsbruck Tirol 6020",
    "addr:housenumber":"21",
    "addr:postcode":"6020",
    "addr:street":"Wilhelm-Greil-Str;Tirol",
    "iso:country":"AT",
    "sg:address":"Wilhelm-Greil-Str 21",
    "sg:city":"Innsbruck",
    "sg:orig_category":"Freizeit- U Sportbekleidung",
    "sg:phone":"+43 4351 2560531",
    "sg:postcode":"6020",
    "sg:province":"Tirol",
    "wof:name":"Replay - Jeansshop",
    "wof:placetype":"venue"
},
  "geometry": {"coordinates":[11.3968553543,47.2637023926],"type":"Point"}
}