{
  "type": "Feature",
  "properties": {
    "addr:full":"Rinnholzpl 6 Gmunden Ober\u00f6sterreich 4810",
    "addr:housenumber":"6",
    "addr:postcode":"4810",
    "addr:street":"Rinnholzpl;Oberoesterreich",
    "iso:country":"AT",
    "sg:address":"Rinnholzpl 6",
    "sg:city":"Gmunden",
    "sg:orig_category":"Fleischhauereien",
    "sg:phone":"+43 761264296",
    "sg:postcode":"4810",
    "sg:province":"Ober\u00f6sterreich",
    "wof:name":"Reiter - Innviertler Fleischwaren",
    "wof:placetype":"venue"
},
  "geometry": {"coordinates":[13.7986602783,47.9194107056],"type":"Point"}
}