{
  "type": "Feature",
  "properties": {
    "iso:country":"AT",
    "sg:address":"Bahnhofstrasse 2",
    "sg:city":"Deutsch Wagram",
    "sg:classifiers":[
        {
            "category":"Building & Trades",
            "subcategory":"Electrical",
            "type":"Services"
        }
    ],
    "sg:phone":"+43 2247 2253",
    "sg:postcode":"2232",
    "sg:province":"Nieder\u00f6sterreich",
    "sg:tags":[
        "work",
        "installation"
    ],
    "sg:website":"elektro-dietrich.at",
    "wof:name":"Ing. Franz Dietrich",
    "wof:placetype":"venue"
},
  "geometry": {"coordinates":[16.5607070923,48.2972679138],"type":"Point"}
}