{
  "type": "Feature",
  "properties": {
    "addr:full":"Kaiserspitz 45 Rekawinkel Nieder\u00f6sterreich 3031",
    "addr:housenumber":"45",
    "addr:postcode":"3031",
    "addr:street":"Kaiserspitz",
    "iso:country":"AT",
    "sg:address":"Kaiserspitz 45",
    "sg:city":"Rekawinkel",
    "sg:orig_category":"Transportunternehmen",
    "sg:phone":"+43 4322 3356551",
    "sg:postcode":"3031",
    "sg:province":"Nieder\u00f6sterreich",
    "wof:name":"M V Transport Vince Marcsanyi",
    "wof:placetype":"venue"
},
  "geometry": {"coordinates":[16.0026702881,48.182510376],"type":"Point"}
}