{
  "type": "Feature",
  "properties": {
    "addr:full":"Schlachthausg 16 Wien Wien 1030",
    "addr:housenumber":"16",
    "addr:postcode":"1030",
    "addr:street":"Schlachthausg",
    "iso:country":"AT",
    "sg:address":"Schlachthausg 16",
    "sg:city":"Wien",
    "sg:orig_category":"Personalbereitstellung",
    "sg:phone":"+43 1 7148998",
    "sg:postcode":"1030",
    "sg:province":"Wien",
    "wof:name":"AZDS Personalleasing GmbH",
    "wof:placetype":"venue"
},
  "geometry": {"coordinates":[16.4076595306,48.1952705383],"type":"Point"}
}