{
  "type": "Feature",
  "properties": {
    "addr:full":"Bisamberger Str 14 Korneuburg Nieder\u00f6sterreich 2100",
    "addr:postcode":"2100",
    "addr:street":"Str 14",
    "iso:country":"AT",
    "sg:address":"Bisamberger Str 14",
    "sg:city":"Korneuburg",
    "sg:orig_category":"Versicherungsunternehmen",
    "sg:phone":"+43 2262 721550",
    "sg:postcode":"2100",
    "sg:province":"Nieder\u00f6sterreich",
    "wof:name":"Wiener St\u00e4dtische Allgemeine Versicherung AG",
    "wof:placetype":"venue"
},
  "geometry": {"coordinates":[16.336435318,48.3426742554],"type":"Point"}
}