{
  "type": "Feature",
  "properties": {
    "iso:country":"AT",
    "sg:address":"Hans-List-Str 3",
    "sg:city":"Judenburg",
    "sg:orig_category":"Werbeagenturen",
    "sg:phone":"+43 4335 7242644",
    "sg:postcode":"8750",
    "sg:province":"Steiermark",
    "wof:name":"creARTeam Werbeagentur",
    "wof:placetype":"venue"
},
  "geometry": {"coordinates":[14.6714277267,47.1836929321],"type":"Point"}
}