{
  "type": "Feature",
  "properties": {
    "addr:full":"Starhembergg 13 Graz Steiermark 8020",
    "addr:housenumber":"13",
    "addr:postcode":"8020",
    "addr:street":"Starhembergg",
    "iso:country":"AT",
    "sg:address":"Starhembergg 13",
    "sg:city":"Graz",
    "sg:orig_category":"Schwei\u00c3\u0178arbeiten",
    "sg:phone":"+43 316 5756560",
    "sg:postcode":"8020",
    "sg:province":"Steiermark",
    "wof:name":"C & W Tools - Reinhold Pust",
    "wof:placetype":"venue"
},
  "geometry": {"coordinates":[15.4113588333,47.0747299194],"type":"Point"}
}