{
  "type": "Feature",
  "properties": {
    "addr:full":"Wiener Str 20b Hornstein Burgenland 7053",
    "addr:postcode":"7053",
    "addr:street":"Str 20B",
    "iso:country":"AT",
    "sg:address":"Wiener Str 20b",
    "sg:city":"Hornstein",
    "sg:orig_category":"Feuerwehren",
    "sg:phone":"+43 2689 2458",
    "sg:postcode":"7053",
    "sg:province":"Burgenland",
    "wof:name":"Freiwillige Feuerwehr Hornstein",
    "wof:placetype":"venue"
},
  "geometry": {"coordinates":[16.4406738281,47.8832397461],"type":"Point"}
}