{
  "type": "Feature",
  "properties": {
    "iso:country":"AT",
    "sg:address":"Edlau 47",
    "sg:city":"Lasberg",
    "sg:orig_category":"Stahlbau",
    "sg:phone":"+43 7947 20666",
    "sg:postcode":"4291",
    "sg:province":"Ober\u00f6sterreich",
    "wof:name":"Systembeh\u00e4lter Pfeifer GmbH",
    "wof:placetype":"venue"
},
  "geometry": {"coordinates":[14.5280380249,48.479019165],"type":"Point"}
}