{
  "type": "Feature",
  "properties": {
    "iso:country":"AT",
    "sg:address":"Steinamangerer Str 163",
    "sg:city":"Oberwart",
    "sg:orig_category":"Stahlbau",
    "sg:phone":"+43 3352 335240",
    "sg:postcode":"7400",
    "sg:province":"Burgenland",
    "sg:website":"ungersteel.com",
    "wof:name":"Unger Stahlbau GesmbH",
    "wof:placetype":"venue"
},
  "geometry": {"coordinates":[16.2309303284,47.275428772],"type":"Point"}
}