{
  "type": "Feature",
  "properties": {
    "addr:full":"Grazer Str 13 Deutschlandsberg Steiermark 8530",
    "addr:postcode":"8530",
    "addr:street":"Str 13",
    "iso:country":"AT",
    "sg:address":"Grazer Str 13",
    "sg:city":"Deutschlandsberg",
    "sg:orig_category":"Appartements / Ferienwohnungen",
    "sg:phone":"+43 3462 2655",
    "sg:postcode":"8530",
    "sg:province":"Steiermark",
    "wof:name":"Penzinger Anton",
    "wof:placetype":"venue"
},
  "geometry": {"coordinates":[15.219373703,46.8154830933],"type":"Point"}
}