{
  "type": "Feature",
  "properties": {
    "addr:full":"Stubaitalstr 3 Mieders Tirol 6142",
    "addr:housenumber":"3",
    "addr:postcode":"6142",
    "addr:street":"Stubaitalstr;Tirol",
    "iso:country":"AT",
    "sg:address":"Stubaitalstr 3",
    "sg:city":"Mieders",
    "sg:orig_category":"Pensionen / Privatzimmer",
    "sg:phone":"+43 5225 62657",
    "sg:postcode":"6142",
    "sg:province":"Tirol",
    "wof:name":"G\u00e4stehaus Veronika Danzl",
    "wof:placetype":"venue"
},
  "geometry": {"coordinates":[11.3922128677,47.1773872375],"type":"Point"}
}