{
  "type": "Feature",
  "properties": {
    "addr:full":"Parz/3553/2 Hadres Nieder\u00f6sterreich 2061",
    "addr:housenumber":"3553 / 2;2061",
    "addr:street":"Hadres Niederoesterreich",
    "iso:country":"AT",
    "sg:address":"Parz/3553/2",
    "sg:city":"Hadres",
    "sg:orig_category":"Feuerwehren",
    "sg:phone":"+43 2943 2222",
    "sg:postcode":"2061",
    "sg:province":"Nieder\u00f6sterreich",
    "wof:name":"Freiwillige Feuerwehr Hadres",
    "wof:placetype":"venue"
},
  "geometry": {"coordinates":[16.1328372955,48.7088470459],"type":"Point"}
}