{
  "type": "Feature",
  "properties": {
    "addr:full":"Ledererg 4 Wiener Neustadt Nieder\u00f6sterreich 2700",
    "addr:housenumber":"4",
    "addr:postcode":"2700",
    "addr:street":"Ledererg",
    "iso:country":"AT",
    "sg:address":"Ledererg 4",
    "sg:city":"Wiener Neustadt",
    "sg:orig_category":"Friseure U Frisiersalons",
    "sg:phone":"+43 4326 2224970",
    "sg:postcode":"2700",
    "sg:province":"Nieder\u00f6sterreich",
    "wof:name":"Weinberger Andrea",
    "wof:placetype":"venue"
},
  "geometry": {"coordinates":[16.2414169312,47.8120994568],"type":"Point"}
}