{
  "type": "Feature",
  "properties": {
    "addr:full":"Villacher Str 23 Spittal an der Drau K\u00e4rnten 9800",
    "addr:housenumber":"23",
    "addr:postcode":"9800",
    "addr:street":"Str;Kaernten",
    "iso:country":"AT",
    "sg:address":"Villacher Str 23",
    "sg:city":"Spittal an der Drau",
    "sg:orig_category":"Farben U Lacke / Erzeugung U Gro\u00c3\u0178handel",
    "sg:phone":"+43 4347 624830",
    "sg:postcode":"9800",
    "sg:province":"K\u00e4rnten",
    "wof:name":"Henelit-Lackfabrik Gr\u00fcninger GmbH",
    "wof:placetype":"venue"
},
  "geometry": {"coordinates":[13.504784584,46.793674469],"type":"Point"}
}