{
  "type": "Feature",
  "properties": {
    "addr:full":"Hengsberg 52 Hengsberg Steiermark 8411",
    "addr:housenumber":"52",
    "addr:postcode":"8411",
    "addr:street":"Hengsberg",
    "iso:country":"AT",
    "sg:address":"Hengsberg 52",
    "sg:city":"Hengsberg",
    "sg:classifiers":[
        {
            "category":"Home & Garden",
            "subcategory":"Building Materials",
            "type":"Retail Goods"
        }
    ],
    "sg:phone":"+43 3185 3296",
    "sg:postcode":"8411",
    "sg:province":"Steiermark",
    "sg:tags":[
        "tile",
        "granite"
    ],
    "wof:name":"Petrovic Fliesen-Plattenverlegung",
    "wof:placetype":"venue"
},
  "geometry": {"coordinates":[15.4465389252,46.8662757874],"type":"Point"}
}