{
  "type": "Feature",
  "properties": {
    "addr:full":"Kaiser-Franz-Pl 3 Bad Hofgastein Salzburg 5630",
    "addr:housenumber":"3",
    "addr:postcode":"5630",
    "addr:street":"Kaiser-Franz-Pl;Salzburg",
    "iso:country":"AT",
    "sg:address":"Kaiser-Franz-Pl 3",
    "sg:city":"Bad Hofgastein",
    "sg:orig_category":"Juweliere, Gold- U Silberschmiede",
    "sg:phone":"+43 4364 3284660",
    "sg:postcode":"5630",
    "sg:province":"Salzburg",
    "wof:name":"Beck Rene",
    "wof:placetype":"venue"
},
  "geometry": {"coordinates":[13.1061077118,47.1713371277],"type":"Point"}
}