{
  "type": "Feature",
  "properties": {
    "addr:full":"Andreas-Hofer-Str 14 Wien Wien 1210",
    "addr:housenumber":"14",
    "addr:postcode":"1210",
    "addr:street":"Andreas-Hofer-Str",
    "iso:country":"AT",
    "sg:address":"Andreas-Hofer-Str 14",
    "sg:city":"Wien",
    "sg:orig_category":"Immobilienverwaltungen",
    "sg:phone":"+43 1 2703329",
    "sg:postcode":"1210",
    "sg:province":"Wien",
    "wof:name":"Immobilienkanzlei Vrtala GmbH",
    "wof:placetype":"venue"
},
  "geometry": {"coordinates":[16.4094829559,48.2557678223],"type":"Point"}
}