{
  "type": "Feature",
  "properties": {
    "addr:full":"Herzog Friedrich-Str 18 Innsbruck Tirol 6020",
    "addr:housenumber":"18",
    "addr:postcode":"6020",
    "addr:street":"Friedrich-Str;Tirol",
    "iso:country":"AT",
    "sg:address":"Herzog Friedrich-Str 18",
    "sg:city":"Innsbruck",
    "sg:orig_category":"Juweliere, Gold- U Silberschmiede",
    "sg:phone":"+43 512 571130",
    "sg:postcode":"6020",
    "sg:province":"Tirol",
    "wof:name":"Reiter Karl",
    "wof:placetype":"venue"
},
  "geometry": {"coordinates":[11.3932409286,47.2680549622],"type":"Point"}
}