{
  "type": "Feature",
  "properties": {
    "addr:full":"Wimm 2 Naarn im Machlande Ober\u00f6sterreich 4331",
    "addr:housenumber":"2",
    "addr:postcode":"4331",
    "addr:street":"Wimm",
    "iso:country":"AT",
    "sg:address":"Wimm 2",
    "sg:city":"Naarn im Machlande",
    "sg:classifiers":[
        {
            "category":"Farming",
            "subcategory":"Livestock Farm",
            "type":"Manufacturing & Wholesale Goods"
        }
    ],
    "sg:phone":"+43 4372 6258057",
    "sg:postcode":"4331",
    "sg:province":"Ober\u00f6sterreich",
    "sg:tags":[
        "-handel",
        "viehzucht",
        "u"
    ],
    "wof:name":"Wahl Erwin",
    "wof:placetype":"venue"
},
  "geometry": {"coordinates":[14.6224851608,48.2343177795],"type":"Point"}
}