{
  "type": "Feature",
  "properties": {
    "iso:country":"AT",
    "sg:address":"Keplerstr 114c",
    "sg:city":"Graz",
    "sg:orig_category":"Weine / Gro\u00c3\u0178handel",
    "sg:phone":"+43 316 7113500",
    "sg:postcode":"8020",
    "sg:province":"Steiermark",
    "wof:name":"Sch\u00e4ffer GesmbH",
    "wof:placetype":"venue"
},
  "geometry": {"coordinates":[15.4191427231,47.0734176636],"type":"Point"}
}