{
  "type": "Feature",
  "properties": {
    "addr:full":"Deutschwaldstr 16 Purkersdorf Nieder\u00f6sterreich 3002",
    "addr:housenumber":"16",
    "addr:postcode":"3002",
    "addr:street":"Deutschwaldstr",
    "iso:country":"AT",
    "sg:address":"Deutschwaldstr 16",
    "sg:city":"Purkersdorf",
    "sg:orig_category":"Physiotherapie",
    "sg:phone":"+43 2231 63570",
    "sg:postcode":"3002",
    "sg:province":"Nieder\u00f6sterreich",
    "wof:name":"Rumler Elisabeth Dipl-PT",
    "wof:placetype":"venue"
},
  "geometry": {"coordinates":[16.1679706573,48.1953086853],"type":"Point"}
}