{
  "type": "Feature",
  "properties": {
    "addr:full":"Nr 180 Gosdorf Steiermark 8482",
    "addr:postcode":"8482",
    "addr:street":"Nr 180",
    "iso:country":"AT",
    "sg:address":"Nr 180",
    "sg:city":"Gosdorf",
    "sg:orig_category":"Gemeinden",
    "sg:phone":"+43 3472 24030",
    "sg:postcode":"8482",
    "sg:province":"Steiermark",
    "wof:name":"Gemeindeamt Gosdorf",
    "wof:placetype":"venue"
},
  "geometry": {"coordinates":[15.7965946198,46.7270584106],"type":"Point"}
}