{
  "type": "Feature",
  "properties": {
    "addr:full":"Knappenbergstr 5 H\u00fcttenberg K\u00e4rnten 9375",
    "addr:housenumber":"5",
    "addr:postcode":"9375",
    "addr:street":"Knappenbergstr;Kaernten",
    "iso:country":"AT",
    "sg:address":"Knappenbergstr 5",
    "sg:city":"H\u00fcttenberg",
    "sg:orig_category":"Hauptschulen",
    "sg:phone":"+43 4263 2800",
    "sg:postcode":"9375",
    "sg:province":"K\u00e4rnten",
    "wof:name":"Hauptschule",
    "wof:placetype":"venue"
},
  "geometry": {"coordinates":[14.5501651764,46.9364814758],"type":"Point"}
}