{
  "type": "Feature",
  "properties": {
    "addr:full":"Hauptpl 19 Ferlach K\u00e4rnten 9170",
    "addr:housenumber":"19",
    "addr:postcode":"9170",
    "addr:street":"Hauptpl;Kaernten",
    "iso:country":"AT",
    "sg:address":"Hauptpl 19",
    "sg:city":"Ferlach",
    "sg:orig_category":"Banken U Sparkassen",
    "sg:phone":"+43 4342 2728180",
    "sg:postcode":"9170",
    "sg:province":"K\u00e4rnten",
    "wof:name":"Bank f Arbeit u Wirtschaft AG",
    "wof:placetype":"venue"
},
  "geometry": {"coordinates":[14.3000402451,46.5263938904],"type":"Point"}
}