{
  "type": "Feature",
  "properties": {
    "addr:full":"Lindenweg 160 F\u00fcgen Tirol 6263",
    "addr:housenumber":"160",
    "addr:postcode":"6263",
    "addr:street":"Lindenweg;Tirol",
    "iso:country":"AT",
    "sg:address":"Lindenweg 160",
    "sg:city":"F\u00fcgen",
    "sg:orig_category":"Sonderschulen",
    "sg:phone":"+43 5288 622420",
    "sg:postcode":"6263",
    "sg:province":"Tirol",
    "wof:name":"Sondererziehungsschule Volks- und Hauptschule Bubenburg",
    "wof:placetype":"venue"
},
  "geometry": {"coordinates":[11.8504800797,47.342300415],"type":"Point"}
}