{
  "type": "Feature",
  "properties": {
    "addr:full":"Pfarrg 1 Schrems Nieder\u00f6sterreich 3943",
    "addr:housenumber":"1",
    "addr:postcode":"3943",
    "addr:street":"Pfarrg",
    "iso:country":"AT",
    "sg:address":"Pfarrg 1",
    "sg:city":"Schrems",
    "sg:orig_category":"Behinderungen / Leben Mit Behinderungen",
    "sg:phone":"+43 2853 76656",
    "sg:postcode":"3943",
    "sg:province":"Nieder\u00f6sterreich",
    "wof:name":"Caritas - Tagesheim f geistig behinderte Menschen",
    "wof:placetype":"venue"
},
  "geometry": {"coordinates":[15.0693044662,48.7938728333],"type":"Point"}
}