{
  "type": "Feature",
  "properties": {
    "addr:full":"Ragnitztalweg 70 Ragnitz Steiermark 8047",
    "addr:housenumber":"70",
    "addr:postcode":"8047",
    "addr:street":"Ragnitztalweg",
    "iso:country":"AT",
    "sg:address":"Ragnitztalweg 70",
    "sg:city":"Ragnitz",
    "sg:orig_category":"Autoreparatur",
    "sg:phone":"+43 316 3011190",
    "sg:postcode":"8047",
    "sg:province":"Steiermark",
    "wof:name":"Hadl Ing GesmbH",
    "wof:placetype":"venue"
},
  "geometry": {"coordinates":[15.5076665878,47.0727539062],"type":"Point"}
}