{
  "type": "Feature",
  "properties": {
    "addr:full":"Presseggen 23 G\u00f6rtschach K\u00e4rnten 9615",
    "addr:housenumber":"23",
    "addr:postcode":"9615",
    "addr:street":"Presseggen;Kaernten",
    "iso:country":"AT",
    "sg:address":"Presseggen 23",
    "sg:city":"G\u00f6rtschach",
    "sg:orig_category":"Appartements / Ferienwohnungen",
    "sg:phone":"+43 4282 27480",
    "sg:postcode":"9615",
    "sg:province":"K\u00e4rnten",
    "wof:name":"Pock Rudolf",
    "wof:placetype":"venue"
},
  "geometry": {"coordinates":[13.4657897949,46.6346893311],"type":"Point"}
}