{
  "type": "Feature",
  "properties": {
    "addr:full":"Leobersdorfer Strasse 24 Hirtenberg Nieder\u00f6sterreich 2552",
    "addr:housenumber":"24",
    "addr:postcode":"2552",
    "addr:street":"Leobersdorfer Strasse",
    "iso:country":"AT",
    "sg:address":"Leobersdorfer Strasse 24",
    "sg:city":"Hirtenberg",
    "sg:classifiers":[
        {
            "category":"Government",
            "subcategory":"Department Of Motor Vehicles",
            "type":"Public Place"
        }
    ],
    "sg:phone":"+43 2256 8010",
    "sg:postcode":"2552",
    "sg:province":"Nieder\u00f6sterreich",
    "sg:tags":[
        "part",
        "bought-in"
    ],
    "sg:website":"alcar.at",
    "wof:name":"Alcar HERING-RAD GmbH",
    "wof:placetype":"venue"
},
  "geometry": {"coordinates":[16.175951004,47.9312133789],"type":"Point"}
}