{
  "type": "Feature",
  "properties": {
    "addr:full":"Am Edh\u00fcgel 80 Kleinzell im M\u00fchlkreis Ober\u00f6sterreich 4115",
    "addr:housenumber":"80",
    "addr:postcode":"4115",
    "addr:street":"Am Edhuegel;Im Muehlkreis Oberoesterreich",
    "iso:country":"AT",
    "sg:address":"Am Edh\u00fcgel 80",
    "sg:city":"Kleinzell im M\u00fchlkreis",
    "sg:orig_category":"Transportunternehmen",
    "sg:phone":"+43 4372 825282",
    "sg:postcode":"4115",
    "sg:province":"Ober\u00f6sterreich",
    "wof:name":"Holly Markus",
    "wof:placetype":"venue"
},
  "geometry": {"coordinates":[13.9926204681,48.4571800232],"type":"Point"}
}