{
  "type": "Feature",
  "properties": {
    "addr:full":"Florianig 66 Wien Wien 1080",
    "addr:housenumber":"66",
    "addr:postcode":"1080",
    "addr:street":"Florianig",
    "iso:country":"AT",
    "sg:address":"Florianig 66",
    "sg:city":"Wien",
    "sg:orig_category":"Bierlokale-Pubs",
    "sg:phone":"+43 1 4080601",
    "sg:postcode":"1080",
    "sg:province":"Wien",
    "wof:name":"Genius Irish Pub",
    "wof:placetype":"venue"
},
  "geometry": {"coordinates":[16.3415393829,48.2122154236],"type":"Point"}
}