{
  "type": "Feature",
  "properties": {
    "addr:full":"Wollsberg 37 Steinerkirchen an der Traun Ober\u00f6sterreich 4652",
    "addr:housenumber":"37",
    "addr:postcode":"4652",
    "addr:street":"Wollsberg",
    "iso:country":"AT",
    "sg:address":"Wollsberg 37",
    "sg:city":"Steinerkirchen an der Traun",
    "sg:orig_category":"Tankstellen",
    "sg:phone":"+43 7241 5316",
    "sg:postcode":"4652",
    "sg:province":"Ober\u00f6sterreich",
    "wof:name":"Scheureder Anna",
    "wof:placetype":"venue"
},
  "geometry": {"coordinates":[13.9987297058,48.0778121948],"type":"Point"}
}