{
  "type": "Feature",
  "properties": {
    "addr:full":"Illweg 10 N\u00fcziders Vorarlberg 6714",
    "addr:housenumber":"10",
    "addr:postcode":"6714",
    "addr:street":"Illweg",
    "iso:country":"AT",
    "sg:address":"Illweg 10",
    "sg:city":"N\u00fcziders",
    "sg:orig_category":"Bergbahnen",
    "sg:phone":"+43 4355 5232277",
    "sg:postcode":"6714",
    "sg:province":"Vorarlberg",
    "wof:name":"COASTER Verkehrssysteme Vertriebs GmbH",
    "wof:placetype":"venue"
},
  "geometry": {"coordinates":[9.7825555801,47.1720275879],"type":"Point"}
}