{
  "type": "Feature",
  "properties": {
    "iso:country":"AT",
    "sg:address":"Kalsdorfer Str 48",
    "sg:city":"Feldkirchen",
    "sg:orig_category":"Bauunternehmen",
    "sg:phone":"+43 316 242807",
    "sg:postcode":"8073",
    "sg:province":"Steiermark",
    "wof:name":"G\u00f6dl Dietmar Ing BaugesmbH",
    "wof:placetype":"venue"
},
  "geometry": {"coordinates":[15.450928688,46.9866714478],"type":"Point"}
}