{
  "type": "Feature",
  "properties": {
    "iso:country":"AT",
    "sg:address":"Hobelweg 20 ",
    "sg:city":"Pucking",
    "sg:orig_category":"Dog Bones, Simulated",
    "sg:phone":"+43 7229 661770",
    "sg:postcode":"4055",
    "sg:province":"Ober\u00f6sterreich",
    "sg:website":"www.propet-austria.com",
    "wof:name":"PRO PET AUSTRIA Heimtiernahrung GmbH",
    "wof:placetype":"venue"
},
  "geometry": {"coordinates":[14.2089576721,48.1935653687],"type":"Point"}
}