{
  "type": "Feature",
  "properties": {
    "addr:full":"Nr 90 Rohrbach an der Lafnitz Steiermark 8234",
    "addr:postcode":"8234",
    "addr:street":"Nr 90",
    "iso:country":"AT",
    "sg:address":"Nr 90",
    "sg:city":"Rohrbach an der Lafnitz",
    "sg:orig_category":"Gemeinden",
    "sg:phone":"+43 3338 25500",
    "sg:postcode":"8234",
    "sg:province":"Steiermark",
    "wof:name":"Gemeindeamt Eichberg",
    "wof:placetype":"venue"
},
  "geometry": {"coordinates":[15.9732465744,47.3812446594],"type":"Point"}
}