{
  "type": "Feature",
  "properties": {
    "iso:country":"AT",
    "sg:address":"Hauptstr 38",
    "sg:city":"Ternitz",
    "sg:orig_category":"Restaurants: Chinesisch",
    "sg:phone":"+43 2630 37277",
    "sg:postcode":"2630",
    "sg:province":"Nieder\u00f6sterreich",
    "wof:name":"China-Restaurant Gro\u00dfe Mauer",
    "wof:placetype":"venue"
},
  "geometry": {"coordinates":[16.0404148102,47.7168693542],"type":"Point"}
}