{
  "type": "Feature",
  "properties": {
    "iso:country":"AT",
    "sg:address":"Ennsl\u00e4nde 2",
    "sg:city":"Enns",
    "sg:classifiers":[
        {
            "category":"Professional",
            "subcategory":"Art Services",
            "type":"Services"
        }
    ],
    "sg:phone":"+43 699 18058513",
    "sg:postcode":"4470",
    "sg:province":"Ober\u00f6sterreich",
    "sg:tags":[
        "homepage",
        "designing"
    ],
    "sg:website":"elogix.at",
    "wof:name":"ELOGIX Websolutions",
    "wof:placetype":"venue"
},
  "geometry": {"coordinates":[14.4792346954,48.2137947083],"type":"Point"}
}