{
  "type": "Feature",
  "properties": {
    "addr:full":"Burgrg 16 Graz Steiermark 8010",
    "addr:housenumber":"16",
    "addr:postcode":"8010",
    "addr:street":"Burgrg",
    "iso:country":"AT",
    "sg:address":"Burgrg 16",
    "sg:city":"Graz",
    "sg:classifiers":[
        {
            "category":"Banks & Credit Unions",
            "subcategory":"Bank",
            "type":"Services"
        }
    ],
    "sg:phone":"+43 4331 680710",
    "sg:postcode":"8010",
    "sg:province":"Steiermark",
    "sg:tags":[
        "banking",
        "institution"
    ],
    "wof:name":"CAPITAL BANK GRAW GRUPPE AG",
    "wof:placetype":"venue"
},
  "geometry": {"coordinates":[15.4441280365,47.071182251],"type":"Point"}
}