{
  "type": "Feature",
  "properties": {
    "addr:full":"Oberer Stadtpl 17 Waidhofen an der Ybbs Nieder\u00f6sterreich 3340",
    "addr:housenumber":"17",
    "addr:postcode":"3340",
    "addr:street":"Oberer Stadtpl",
    "iso:country":"AT",
    "sg:address":"Oberer Stadtpl 17",
    "sg:city":"Waidhofen an der Ybbs",
    "sg:orig_category":"Elektroinstallationsunternehmen",
    "sg:phone":"+43 4374 42523780",
    "sg:postcode":"3340",
    "sg:province":"Nieder\u00f6sterreich",
    "wof:name":"Rigler Franz Ing",
    "wof:placetype":"venue"
},
  "geometry": {"coordinates":[14.7752227783,47.9607315063],"type":"Point"}
}