{
  "type": "Feature",
  "properties": {
    "addr:full":"Mariazeller Str 134 St. P\u00f6lten Nieder\u00f6sterreich 3100",
    "addr:housenumber":"134",
    "addr:postcode":"3100",
    "addr:street":"Str",
    "iso:country":"AT",
    "sg:address":"Mariazeller Str 134",
    "sg:city":"St. P\u00f6lten",
    "sg:orig_category":"Tankstellen",
    "sg:phone":"+43 2742 77350",
    "sg:postcode":"3100",
    "sg:province":"Nieder\u00f6sterreich",
    "wof:name":"Shell Austria GmbH",
    "wof:placetype":"venue"
},
  "geometry": {"coordinates":[-76.07303619379999,41.7845001221],"type":"Point"}
}