{
  "type": "Feature",
  "properties": {
    "iso:country":"AT",
    "sg:address":"Hauptstrasse 104/19",
    "sg:city":"Kritzendorf",
    "sg:classifiers":[
        {
            "category":"Shopping",
            "subcategory":"Books",
            "type":"Retail Goods"
        }
    ],
    "sg:phone":"+43 2243 36868",
    "sg:postcode":"3420",
    "sg:province":"Nieder\u00f6sterreich",
    "sg:website":"breitschopf-verlag.com",
    "wof:name":"Verlagsbuchhandlung Julius Breitschopf GmbH & Co KG",
    "wof:placetype":"venue"
},
  "geometry": {"coordinates":[16.2978954315,48.3364868164],"type":"Point"}
}