{
  "type": "Feature",
  "properties": {
    "iso:country":"AT",
    "sg:address":"Schauersberg 50",
    "sg:city":"Wels",
    "sg:orig_category":"Steuerberatung",
    "sg:phone":"+43 7242 270180",
    "sg:postcode":"4600",
    "sg:province":"Ober\u00f6sterreich",
    "wof:name":"Pointner Regina",
    "wof:placetype":"venue"
},
  "geometry": {"coordinates":[14.005607605,48.136932373],"type":"Point"}
}