{
  "type": "Feature",
  "properties": {
    "addr:full":"Leoprechting 6 Taufkirchen an der Pram Ober\u00f6sterreich 4775",
    "addr:housenumber":"6",
    "addr:postcode":"4775",
    "addr:street":"Leoprechting",
    "iso:country":"AT",
    "sg:address":"Leoprechting 6",
    "sg:city":"Taufkirchen an der Pram",
    "sg:orig_category":"Pensionen / Privatzimmer",
    "sg:phone":"+43 4377 197221",
    "sg:postcode":"4775",
    "sg:province":"Ober\u00f6sterreich",
    "wof:name":"Demmelbauer Flotzinger Marianne u Johann",
    "wof:placetype":"venue"
},
  "geometry": {"coordinates":[13.542309761,48.4105606079],"type":"Point"}
}