{
  "type": "Feature",
  "properties": {
    "iso:country":"AT",
    "sg:address":"Hauptstr 193",
    "sg:city":"Krumpendorf",
    "sg:orig_category":"Weiterbildungsinstitute M Allg U Berufl Bildungsangebot",
    "sg:phone":"+43 4359 13320",
    "sg:postcode":"9201",
    "sg:province":"K\u00e4rnten",
    "wof:name":"BILDUNGSZENTREN d Sicherheitsexekutive K\u00e4rnten",
    "wof:placetype":"venue"
},
  "geometry": {"coordinates":[14.2076101303,46.6263809204],"type":"Point"}
}