{
  "type": "Feature",
  "properties": {
    "addr:full":"Teichweg 9 Enns Ober\u00f6sterreich 4470",
    "addr:housenumber":"9",
    "addr:postcode":"4470",
    "addr:street":"Teichweg",
    "iso:country":"AT",
    "sg:address":"Teichweg 9",
    "sg:city":"Enns",
    "sg:orig_category":"Steuerberatung",
    "sg:phone":"+43 7223 832410",
    "sg:postcode":"4470",
    "sg:province":"Ober\u00f6sterreich",
    "wof:name":"Bl\u00f6chl Johann Ing",
    "wof:placetype":"venue"
},
  "geometry": {"coordinates":[14.4754514694,48.2180938721],"type":"Point"}
}