{
  "type": "Feature",
  "properties": {
    "addr:full":"Franz-Grill-Str 5 Wien Wien 1030",
    "addr:housenumber":"5",
    "addr:postcode":"1030",
    "addr:street":"Franz-Grill-Str",
    "iso:country":"AT",
    "sg:address":"Franz-Grill-Str 5",
    "sg:city":"Wien",
    "sg:orig_category":"Forschungsinstitute",
    "sg:phone":"+43 1 7981601",
    "sg:postcode":"1030",
    "sg:province":"Wien",
    "wof:name":"Ofi Technologie & Innovation GmbH",
    "wof:placetype":"venue"
},
  "geometry": {"coordinates":[16.397983551,48.1804008484],"type":"Point"}
}