{
  "type": "Feature",
  "properties": {
    "iso:country":"AT",
    "sg:address":"Jochberger Str 129",
    "sg:city":"Kitzb\u00fchel",
    "sg:classifiers":[
        {
            "category":"Utilities",
            "subcategory":"Refuse",
            "type":"Services"
        }
    ],
    "sg:phone":"+43 5356 643600",
    "sg:postcode":"6370",
    "sg:province":"Tirol",
    "sg:tags":[
        "catering"
    ],
    "wof:name":"KA + CA Catering GesmbH & Co KG",
    "wof:placetype":"venue"
},
  "geometry": {"coordinates":[12.4092206955,47.4300193787],"type":"Point"}
}