{
  "type": "Feature",
  "properties": {
    "addr:full":"Kiesweg 2 Langkampfen Tirol 6336",
    "addr:housenumber":"2",
    "addr:postcode":"6336",
    "addr:street":"Kiesweg;Tirol",
    "iso:country":"AT",
    "sg:address":"Kiesweg 2",
    "sg:city":"Langkampfen",
    "sg:orig_category":"Bauunternehmen",
    "sg:phone":"+43 5332 885050",
    "sg:postcode":"6336",
    "sg:province":"Tirol",
    "wof:name":"Kurz Josef & Co",
    "wof:placetype":"venue"
},
  "geometry": {"coordinates":[12.0957460403,47.5353012085],"type":"Point"}
}