{
  "type": "Feature",
  "properties": {
    "addr:full":"Rathauspl 10 Aschbach Markt Nieder\u00f6sterreich 3361",
    "addr:housenumber":"10",
    "addr:postcode":"3361",
    "addr:street":"Rathauspl",
    "iso:country":"AT",
    "sg:address":"Rathauspl 10",
    "sg:city":"Aschbach Markt",
    "sg:orig_category":"Banken U Sparkassen",
    "sg:phone":"+43 4374 7677408",
    "sg:postcode":"3361",
    "sg:province":"Nieder\u00f6sterreich",
    "wof:name":"Bankomat der Volksbank Alpenvorland regGenmbH",
    "wof:placetype":"venue"
},
  "geometry": {"coordinates":[14.7487611771,48.0731964111],"type":"Point"}
}