{
  "type": "Feature",
  "properties": {
    "iso:country":"AT",
    "sg:address":"Parscher Str 43/3",
    "sg:city":"Gnigl",
    "sg:orig_category":"Gartenarchitekten",
    "sg:phone":"+43 664 2224601",
    "sg:postcode":"5023",
    "sg:province":"Salzburg",
    "wof:name":"Soyoye Hadwig Dipl-Ing",
    "wof:placetype":"venue"
},
  "geometry": {"coordinates":[13.0709295273,47.8084220886],"type":"Point"}
}