{
  "type": "Feature",
  "properties": {
    "iso:country":"AT",
    "sg:address":"F\u00fcrstenstrasse 16 ",
    "sg:city":"Traun",
    "sg:classifiers":[
        {
            "category":"Building & Trades",
            "subcategory":"Plumbing",
            "type":"Services"
        }
    ],
    "sg:phone":"+43 7229 72408",
    "sg:postcode":"4050",
    "sg:province":"Ober\u00f6sterreich",
    "sg:tags":[
        "supraregional",
        "gas"
    ],
    "wof:name":"Matthias Huprich",
    "wof:placetype":"venue"
},
  "geometry": {"coordinates":[14.2384881973,48.221572876],"type":"Point"}
}