{
  "type": "Feature",
  "properties": {
    "addr:full":"R\u00f6hrlgraben 14 Bad Zell Ober\u00f6sterreich 4283",
    "addr:housenumber":"14",
    "addr:postcode":"4283",
    "addr:street":"Roehrlgraben",
    "iso:country":"AT",
    "sg:address":"R\u00f6hrlgraben 14",
    "sg:city":"Bad Zell",
    "sg:orig_category":"Solaranlagen",
    "sg:phone":"+43 4372 636368",
    "sg:postcode":"4283",
    "sg:province":"Ober\u00f6sterreich",
    "wof:name":"Lindsberger Franz Josef",
    "wof:placetype":"venue"
},
  "geometry": {"coordinates":[14.6680231094,48.352809906],"type":"Point"}
}