{
  "type": "Feature",
  "properties": {
    "addr:full":"Nr 4 Desselbrunn Ober\u00f6sterreich 4693",
    "addr:postcode":"4693",
    "addr:street":"Nr;Desselbrunn",
    "iso:country":"AT",
    "sg:address":"Nr 4",
    "sg:city":"Desselbrunn",
    "sg:orig_category":"Restaurants: Griechisch",
    "sg:phone":"+43 76733716",
    "sg:postcode":"4693",
    "sg:province":"Ober\u00f6sterreich",
    "wof:name":"Der Grieche - Dorf Restaurant",
    "wof:placetype":"venue"
},
  "geometry": {"coordinates":[13.7724685669,48.0213432312],"type":"Point"}
}