{
  "type": "Feature",
  "properties": {
    "addr:full":"Mariazeller Str 10 Rabenstein an der Pielach Nieder\u00f6sterreich 3203",
    "addr:housenumber":"10",
    "addr:postcode":"3203",
    "addr:street":"Str",
    "iso:country":"AT",
    "sg:address":"Mariazeller Str 10",
    "sg:city":"Rabenstein an der Pielach",
    "sg:orig_category":"Feuerwehren",
    "sg:phone":"+43 2723 2727",
    "sg:postcode":"3203",
    "sg:province":"Nieder\u00f6sterreich",
    "wof:name":"Freiwillige Feuerwehr Rabenstein a d Pielach",
    "wof:placetype":"venue"
},
  "geometry": {"coordinates":[15.4639339447,48.0623970032],"type":"Point"}
}