{
  "type": "Feature",
  "properties": {
    "addr:full":"Franz-Kirch-Str 4 Ybbs an der Donau Nieder\u00f6sterreich 3370",
    "addr:housenumber":"4",
    "addr:postcode":"3370",
    "addr:street":"Franz-Kirch-Str",
    "iso:country":"AT",
    "sg:address":"Franz-Kirch-Str 4",
    "sg:city":"Ybbs an der Donau",
    "sg:orig_category":"Fotografen",
    "sg:phone":"+43 4374 1254500",
    "sg:postcode":"3370",
    "sg:province":"Nieder\u00f6sterreich",
    "wof:name":"Foto Luks - Erika Riedler",
    "wof:placetype":"venue"
},
  "geometry": {"coordinates":[15.084356308,48.1774635315],"type":"Point"}
}