{
  "type": "Feature",
  "properties": {
    "addr:full":"Winkl 69 Kramsach Tirol 6233",
    "addr:housenumber":"69",
    "addr:postcode":"6233",
    "addr:street":"Winkl;Tirol",
    "iso:country":"AT",
    "sg:address":"Winkl 69",
    "sg:city":"Kramsach",
    "sg:orig_category":"Tischlereien",
    "sg:phone":"+43 5337 63913",
    "sg:postcode":"6233",
    "sg:province":"Tirol",
    "wof:name":"Ager Othmar",
    "wof:placetype":"venue"
},
  "geometry": {"coordinates":[11.8723554611,47.4422340393],"type":"Point"}
}