{
  "type": "Feature",
  "properties": {
    "iso:country":"AT",
    "sg:address":"Hauptstr 28",
    "sg:city":"Windischgarsten",
    "sg:classifiers":[
        {
            "category":"Park",
            "subcategory":"Provincial",
            "type":"Public Place"
        }
    ],
    "sg:phone":"+43 4375 626020",
    "sg:postcode":"4580",
    "sg:province":"Ober\u00f6sterreich",
    "sg:tags":[
        "u",
        "ski-",
        "snowboardschulen"
    ],
    "wof:name":"Schischulen Wurzeralm",
    "wof:placetype":"venue"
},
  "geometry": {"coordinates":[14.3295001984,47.7217826843],"type":"Point"}
}