{
  "type": "Feature",
  "properties": {
    "addr:full":"Edlau 36 Lasberg Ober\u00f6sterreich 4291",
    "addr:housenumber":"36",
    "addr:postcode":"4291",
    "addr:street":"Edlau",
    "iso:country":"AT",
    "sg:address":"Edlau 36",
    "sg:city":"Lasberg",
    "sg:orig_category":"Tischlereien",
    "sg:phone":"+43 7947 6859",
    "sg:postcode":"4291",
    "sg:province":"Ober\u00f6sterreich",
    "wof:name":"Freudenthaler Manfred",
    "wof:placetype":"venue"
},
  "geometry": {"coordinates":[14.5280380249,48.479019165],"type":"Point"}
}