{
  "type": "Feature",
  "properties": {
    "addr:full":"Waldgasse 39 Bad Sauerbrunn Burgenland 7202",
    "addr:housenumber":"39",
    "addr:postcode":"7202",
    "addr:street":"Waldgasse",
    "iso:country":"AT",
    "sg:address":"Waldgasse 39",
    "sg:city":"Bad Sauerbrunn",
    "sg:classifiers":[
        {
            "category":"Professional",
            "subcategory":"Detective & Security Services",
            "type":"Services"
        }
    ],
    "sg:phone":"+43 2625 32106",
    "sg:postcode":"7202",
    "sg:province":"Burgenland",
    "sg:tags":[
        "agency"
    ],
    "sg:website":"detektivunternehmen.com",
    "wof:name":"Detektivunternehmen Reiser",
    "wof:placetype":"venue"
},
  "geometry": {"coordinates":[16.316400528,47.7793579102],"type":"Point"}
}