{
  "type": "Feature",
  "properties": {
    "addr:full":"Schwemmstr 10 M\u00fcnzbach Ober\u00f6sterreich 4323",
    "addr:housenumber":"10",
    "addr:postcode":"4323",
    "addr:street":"Schwemmstr;Oberoesterreich",
    "iso:country":"AT",
    "sg:address":"Schwemmstr 10",
    "sg:city":"M\u00fcnzbach",
    "sg:orig_category":"Fleischhauereien",
    "sg:phone":"+43 7264 4519",
    "sg:postcode":"4323",
    "sg:province":"Ober\u00f6sterreich",
    "wof:name":"Neugschwandtner Fleischwaren GmbH",
    "wof:placetype":"venue"
},
  "geometry": {"coordinates":[14.7111606598,48.2689437866],"type":"Point"}
}