{
  "type": "Feature",
  "properties": {
    "iso:country":"AT",
    "sg:address":"Kaiserg 14a",
    "sg:city":"Linz",
    "sg:orig_category":"Notare",
    "sg:phone":"+43 732 797877",
    "sg:postcode":"4020",
    "sg:province":"Ober\u00f6sterreich",
    "sg:website":"hohla-partner.at",
    "wof:name":"\u00f6ffentlicher Notar Dr J\u00fcrgen Hohla & Partner",
    "wof:placetype":"venue"
},
  "geometry": {"coordinates":[14.2937526703,48.3071670532],"type":"Point"}
}