{
  "type": "Feature",
  "properties": {
    "iso:country":"AT",
    "sg:address":"Obere Hauptstr 97",
    "sg:city":"Zurndorf",
    "sg:orig_category":"Lebensmittel / Einzelhandel",
    "sg:phone":"+43 4321 4720081",
    "sg:postcode":"2424",
    "sg:province":"Burgenland",
    "wof:name":"Billa AG",
    "wof:placetype":"venue"
},
  "geometry": {"coordinates":[17.0112037659,47.9758262634],"type":"Point"}
}