{
  "type": "Feature",
  "properties": {
    "addr:full":"Franz-Plattner-Str 44 Zirl Tirol 6170",
    "addr:housenumber":"44",
    "addr:postcode":"6170",
    "addr:street":"Franz-Plattner-Str;Tirol",
    "iso:country":"AT",
    "sg:address":"Franz-Plattner-Str 44",
    "sg:city":"Zirl",
    "sg:orig_category":"Autoverwertung",
    "sg:phone":"+43 5238 52618",
    "sg:postcode":"6170",
    "sg:province":"Tirol",
    "wof:name":"Elsler Martin",
    "wof:placetype":"venue"
},
  "geometry": {"coordinates":[11.2363901138,47.2702064514],"type":"Point"}
}