{
  "type": "Feature",
  "properties": {
    "iso:country":"AT",
    "sg:address":"Hellbrunner Str 73",
    "sg:city":"Anif",
    "sg:classifiers":[
        {
            "category":"Travel",
            "subcategory":"Hotels & Motels",
            "type":"Entertainment"
        }
    ],
    "sg:phone":"+43 662 820934",
    "sg:postcode":"5081",
    "sg:province":"Salzburg",
    "wof:name":"Hotel am Tiergarten",
    "wof:placetype":"venue"
},
  "geometry": {"coordinates":[13.0606851578,47.7592124939],"type":"Point"}
}