{
  "type": "Feature",
  "properties": {
    "addr:full":"Nr 100 Strass im Zillertal Tirol 6261",
    "addr:postcode":"6261",
    "addr:street":"Nr 100;Zillertal Tirol",
    "iso:country":"AT",
    "sg:address":"Nr 100",
    "sg:city":"Strass im Zillertal",
    "sg:orig_category":"Banken U Sparkassen",
    "sg:phone":"+43 4352 4462144",
    "sg:postcode":"6261",
    "sg:province":"Tirol",
    "wof:name":"Bankomat d Raiffeisenkasse Buch-Gallzein-Strass regGenmbH",
    "wof:placetype":"venue"
},
  "geometry": {"coordinates":[11.8219985962,47.3957252502],"type":"Point"}
}