{
  "type": "Feature",
  "properties": {
    "addr:full":"Herreng 12 Wien Wien 1010",
    "addr:housenumber":"12",
    "addr:postcode":"1010",
    "addr:street":"Herreng",
    "iso:country":"AT",
    "sg:address":"Herreng 12",
    "sg:city":"Wien",
    "sg:classifiers":[
        {
            "category":"Travel",
            "subcategory":"Hotels & Motels",
            "type":"Entertainment"
        }
    ],
    "sg:phone":"+43 4312 27800",
    "sg:postcode":"1010",
    "sg:province":"Wien",
    "wof:name":"Style Hotel Vienna",
    "wof:placetype":"venue"
},
  "geometry": {"coordinates":[16.365562439,48.2100753784],"type":"Point"}
}