{
  "type": "Feature",
  "properties": {
    "addr:full":"Erzherzog Johann-Str 6 Leoben Steiermark 8700",
    "addr:housenumber":"6",
    "addr:postcode":"8700",
    "iso:country":"AT",
    "sg:address":"Erzherzog Johann-Str 6",
    "sg:city":"Leoben",
    "sg:orig_category":"Arbeitsinspektorate",
    "sg:phone":"+43 3842 42265",
    "sg:postcode":"8700",
    "sg:province":"Steiermark",
    "wof:name":"Arbeitsinspektorat f d 12. Aufsichtsbezirk",
    "wof:placetype":"venue"
},
  "geometry": {"coordinates":[15.0914649963,47.3814125061],"type":"Point"}
}