{
  "type": "Feature",
  "properties": {
    "addr:full":"Grinzinger Str 72 Wien Wien 1190",
    "addr:postcode":"1190",
    "addr:street":"Str 72",
    "iso:country":"AT",
    "sg:address":"Grinzinger Str 72",
    "sg:city":"Wien",
    "sg:orig_category":"Exporteure U Importeure",
    "sg:phone":"+43 1 37045760",
    "sg:postcode":"1190",
    "sg:province":"Wien",
    "wof:name":"Stipkovich Walter Dr WarenhandelsgesmbH",
    "wof:placetype":"venue"
},
  "geometry": {"coordinates":[16.3540458679,48.2535705566],"type":"Point"}
}