{
  "type": "Feature",
  "properties": {
    "addr:full":"Falkenberg 2 Senftenberg Nieder\u00f6sterreich 3541",
    "addr:housenumber":"2",
    "addr:postcode":"3541",
    "addr:street":"Falkenberg",
    "iso:country":"AT",
    "sg:address":"Falkenberg 2",
    "sg:city":"Senftenberg",
    "sg:orig_category":"Non-Classified Establishments",
    "sg:phone":"+43 2719 21630",
    "sg:postcode":"3541",
    "sg:province":"Nieder\u00f6sterreich",
    "wof:name":"Dobrovits Jonny",
    "wof:placetype":"venue"
},
  "geometry": {"coordinates":[15.5378828049,48.4562454224],"type":"Point"}
}