{
  "type": "Feature",
  "properties": {
    "addr:full":"Seepromenade 12 Lunz am See Nieder\u00f6sterreich 3293",
    "addr:housenumber":"12",
    "addr:postcode":"3293",
    "addr:street":"Seepromenade",
    "iso:country":"AT",
    "sg:address":"Seepromenade 12",
    "sg:city":"Lunz am See",
    "sg:orig_category":"Tischlereien",
    "sg:phone":"+43 7486 8248",
    "sg:postcode":"3293",
    "sg:province":"Nieder\u00f6sterreich",
    "wof:name":"Garnweidner Gottfried",
    "wof:placetype":"venue"
},
  "geometry": {"coordinates":[15.0320901871,47.8588981628],"type":"Point"}
}