{
  "type": "Feature",
  "properties": {
    "addr:full":"Traung 10 Wels Ober\u00f6sterreich 4600",
    "addr:housenumber":"10",
    "addr:postcode":"4600",
    "addr:street":"Traung;Oberoesterreich",
    "iso:country":"AT",
    "sg:address":"Traung 10",
    "sg:city":"Wels",
    "sg:orig_category":"Raumgestaltung",
    "sg:phone":"+43 7242 47695",
    "sg:postcode":"4600",
    "sg:province":"Ober\u00f6sterreich",
    "wof:name":"Zwettler & Bruckm\u00fcller GmbH & Co KG",
    "wof:placetype":"venue"
},
  "geometry": {"coordinates":[14.0256385803,48.1562690735],"type":"Point"}
}