{
  "type": "Feature",
  "properties": {
    "iso:country":"AT",
    "sg:address":"Dirnbach 41",
    "sg:city":"Straden",
    "sg:classifiers":[
        {
            "category":"Ice Cream",
            "type":"Food & Drink"
        }
    ],
    "sg:phone":"+43 3473 7849",
    "sg:postcode":"8345",
    "sg:province":"Steiermark",
    "sg:tags":[
        "seed",
        "oil",
        "pumpkin"
    ],
    "sg:website":"naturnahhof.at",
    "wof:name":"Baumgartner Naturnahhof - K\u00fcrbiskern\u00f6l",
    "wof:placetype":"venue"
},
  "geometry": {"coordinates":[15.8692350388,46.8074264526],"type":"Point"}
}