{
  "type": "Feature",
  "properties": {
    "addr:full":"Dr Mitterbauer-Str 8 Laakirchen Ober\u00f6sterreich 4663",
    "addr:housenumber":"8",
    "addr:postcode":"4663",
    "iso:country":"AT",
    "sg:address":"Dr Mitterbauer-Str 8",
    "sg:city":"Laakirchen",
    "sg:orig_category":"Maler, Anstreicher U Lackierer",
    "sg:phone":"+43 76132649",
    "sg:postcode":"4663",
    "sg:province":"Ober\u00f6sterreich",
    "wof:name":"Ganzenbacher-Waldl Ferdinand",
    "wof:placetype":"venue"
},
  "geometry": {"coordinates":[13.8199329376,47.9818878174],"type":"Point"}
}