{
  "type": "Feature",
  "properties": {
    "addr:full":"Stra\u00dfganger Str 198 Wetzelsdorf Steiermark 8052",
    "addr:housenumber":"198",
    "addr:postcode":"8052",
    "iso:country":"AT",
    "sg:address":"Stra\u00dfganger Str 198",
    "sg:city":"Wetzelsdorf",
    "sg:orig_category":"Steuerberatung",
    "sg:phone":"+43 316 585650",
    "sg:postcode":"8052",
    "sg:province":"Steiermark",
    "wof:name":"WPI Steuerberatungsgesellschaft mbH",
    "wof:placetype":"venue"
},
  "geometry": {"coordinates":[15.3945636749,47.0510482788],"type":"Point"}
}