{
  "type": "Feature",
  "properties": {
    "iso:country":"AT",
    "sg:address":"Traisner Str 5",
    "sg:city":"Hainfeld",
    "sg:orig_category":"Geschenkartikel",
    "sg:phone":"+43 2764 30388",
    "sg:postcode":"3170",
    "sg:province":"Nieder\u00f6sterreich",
    "wof:name":"Knusperh\u00e4uschen Silvia Auer",
    "wof:placetype":"venue"
},
  "geometry": {"coordinates":[15.7557296753,48.0395812988],"type":"Point"}
}