{
  "type": "Feature",
  "properties": {
    "addr:full":"Bichlg 20 Wei\u00dfenbach am Lech Tirol 6671",
    "addr:housenumber":"20",
    "addr:postcode":"6671",
    "addr:street":"Bichlg;Tirol",
    "iso:country":"AT",
    "sg:address":"Bichlg 20",
    "sg:city":"Wei\u00dfenbach am Lech",
    "sg:orig_category":"Architekturmodellbau",
    "sg:phone":"+43 5678 5360",
    "sg:postcode":"6671",
    "sg:province":"Tirol",
    "wof:name":"Modellbau Kern",
    "wof:placetype":"venue"
},
  "geometry": {"coordinates":[-90.9634475708,29.8630008698],"type":"Point"}
}