{
  "type": "Feature",
  "properties": {
    "addr:full":"Teschnergasse 3  Wien Wien 1180",
    "addr:housenumber":"3",
    "addr:postcode":"1180",
    "addr:street":"Teschnergasse",
    "iso:country":"AT",
    "sg:address":"Teschnergasse 3 ",
    "sg:city":"Wien",
    "sg:classifiers":[
        {
            "category":"Autos & Motor Vehicles",
            "subcategory":"Automobile Sales",
            "type":"Retail Goods"
        }
    ],
    "sg:phone":"+43 4314 054317",
    "sg:postcode":"1180",
    "sg:province":"Wien",
    "sg:tags":[
        "industrial"
    ],
    "wof:name":"LINDNER GERITZER GESMBH",
    "wof:placetype":"venue"
},
  "geometry": {"coordinates":[16.3359642029,48.223575592],"type":"Point"}
}