{
  "type": "Feature",
  "properties": {
    "addr:full":"Mattersburger Str 35 Eisenstadt Burgenland 7000",
    "addr:postcode":"7000",
    "addr:street":"Str 35",
    "iso:country":"AT",
    "sg:address":"Mattersburger Str 35",
    "sg:city":"Eisenstadt",
    "sg:orig_category":"Lebensmittel / Einzelhandel",
    "sg:phone":"+43 4326 8264787",
    "sg:postcode":"7000",
    "sg:province":"Burgenland",
    "wof:name":"Hofer KG",
    "wof:placetype":"venue"
},
  "geometry": {"coordinates":[16.5236339569,47.8290290833],"type":"Point"}
}