{
  "type": "Feature",
  "properties": {
    "iso:country":"AT",
    "sg:address":"Nr 8",
    "sg:city":"Hippach",
    "sg:orig_category":"Unternehmensberatung",
    "sg:phone":"+43 5282 3010",
    "sg:postcode":"6283",
    "sg:province":"Tirol",
    "wof:name":"Hei\u00df Christian Ing",
    "wof:placetype":"venue"
},
  "geometry": {"coordinates":[11.8661670685,47.2039108276],"type":"Point"}
}