{
  "type": "Feature",
  "properties": {
    "addr:full":"Hauptstrasse 124 Altenmarkt im Pongau Salzburg 5541",
    "addr:housenumber":"124",
    "addr:postcode":"5541",
    "addr:street":"Hauptstrasse;Salzburg",
    "iso:country":"AT",
    "sg:address":"Hauptstrasse 124",
    "sg:city":"Altenmarkt im Pongau",
    "sg:classifiers":[
        {
            "category":"Shopping",
            "subcategory":"News",
            "type":"Retail Goods"
        }
    ],
    "sg:phone":"+43 6452 78780",
    "sg:postcode":"5541",
    "sg:province":"Salzburg",
    "sg:tags":[
        "anorak"
    ],
    "sg:website":"schneidersports.com",
    "wof:name":"Schneider pants + sportswear",
    "wof:placetype":"venue"
},
  "geometry": {"coordinates":[13.3878822327,47.3718566895],"type":"Point"}
}