{
  "type": "Feature",
  "properties": {
    "addr:full":"Thaliastr 25 Wien Wien 1160",
    "addr:housenumber":"25",
    "addr:postcode":"1160",
    "addr:street":"Thaliastr",
    "iso:country":"AT",
    "sg:address":"Thaliastr 25",
    "sg:city":"Wien",
    "sg:orig_category":"Juweliere, Gold- U Silberschmiede",
    "sg:phone":"+43 4314 920847",
    "sg:postcode":"1160",
    "sg:province":"Wien",
    "wof:name":"Knobloch Helmut",
    "wof:placetype":"venue"
},
  "geometry": {"coordinates":[16.3341140747,48.2091255188],"type":"Point"}
}