{
  "type": "Feature",
  "properties": {
    "iso:country":"AT",
    "sg:address":"Lannerweg 20b",
    "sg:city":"Krumpendorf",
    "sg:orig_category":"Werbeagenturen",
    "sg:phone":"+43 4342 2934200",
    "sg:postcode":"9201",
    "sg:province":"K\u00e4rnten",
    "wof:name":"Print Connect GmbH",
    "wof:placetype":"venue"
},
  "geometry": {"coordinates":[14.2167196274,46.6275520325],"type":"Point"}
}