{
  "type": "Feature",
  "properties": {
    "addr:full":"Nr 53 Kirchbichl Tirol 6322",
    "addr:postcode":"6322",
    "addr:street":"Nr 53;Tirol",
    "iso:country":"AT",
    "sg:address":"Nr 53",
    "sg:city":"Kirchbichl",
    "sg:orig_category":"Glasbe- U -Verarbeitung",
    "sg:phone":"+43 5332 56957",
    "sg:postcode":"6322",
    "sg:province":"Tirol",
    "wof:name":"Glasbl\u00e4serei Weinmayer",
    "wof:placetype":"venue"
},
  "geometry": {"coordinates":[12.0880002975,47.5128707886],"type":"Point"}
}