{
  "type": "Feature",
  "properties": {
    "addr:full":"Rainerstr 54 Mondsee Ober\u00f6sterreich 5310",
    "addr:housenumber":"54",
    "addr:postcode":"5310",
    "addr:street":"Rainerstr;Oberoesterreich",
    "iso:country":"AT",
    "sg:address":"Rainerstr 54",
    "sg:city":"Mondsee",
    "sg:orig_category":"Elektroinstallationsunternehmen",
    "sg:phone":"+43 6232 2672",
    "sg:postcode":"5310",
    "sg:province":"Ober\u00f6sterreich",
    "wof:name":"Planberger Wolfgang",
    "wof:placetype":"venue"
},
  "geometry": {"coordinates":[13.3454837799,47.8528289795],"type":"Point"}
}