{
  "type": "Feature",
  "properties": {
    "iso:country":"AT",
    "sg:address":"Schirning 155",
    "sg:city":"Gratwein",
    "sg:classifiers":[
        {
            "category":"Manufacturing",
            "subcategory":"Tools & Machinery",
            "type":"Manufacturing & Wholesale Goods"
        }
    ],
    "sg:phone":"+43 3123 2282",
    "sg:postcode":"8112",
    "sg:province":"Steiermark",
    "sg:tags":[
        "part",
        "turned",
        "cnc"
    ],
    "wof:name":"Merkan Ges.m.b.H.",
    "wof:placetype":"venue"
},
  "geometry": {"coordinates":[15.2980356216,47.1217002869],"type":"Point"}
}