{
  "type": "Feature",
  "properties": {
    "addr:full":"Fasang 35-37 Wien Wien 1030",
    "addr:postcode":"35-37;1030",
    "iso:country":"AT",
    "sg:address":"Fasang 35-37",
    "sg:city":"Wien",
    "sg:classifiers":[
        {
            "category":"Retail",
            "subcategory":"Event Space",
            "type":"Services"
        }
    ],
    "sg:phone":"+43 4317 983903",
    "sg:postcode":"1030",
    "sg:province":"Wien",
    "sg:tags":[
        "hand-",
        "u",
        "fu\u00c3\u0178pflege"
    ],
    "wof:name":"Egyed Charlotte",
    "wof:placetype":"venue"
},
  "geometry": {"coordinates":[16.3858394623,48.1908950806],"type":"Point"}
}