{
  "type": "Feature",
  "properties": {
    "iso:country":"AT",
    "sg:address":"Badg 38",
    "sg:city":"Dornbirn",
    "sg:orig_category":"Beton- U Betonsteinwerke",
    "sg:phone":"+43 4355 72224030",
    "sg:postcode":"6850",
    "sg:province":"Vorarlberg",
    "wof:name":"Rhomberg's Joh Nep Nfg GesmbH & Co KG",
    "wof:placetype":"venue"
},
  "geometry": {"coordinates":[9.7437801361,47.4131889343],"type":"Point"}
}