{
  "type": "Feature",
  "properties": {
    "addr:full":"Nr 112 Z\u00fcrs Vorarlberg 6763",
    "addr:postcode":"6763",
    "addr:street":"Nr 112 Zuers",
    "iso:country":"AT",
    "sg:address":"Nr 112",
    "sg:city":"Z\u00fcrs",
    "sg:classifiers":[
        {
            "category":"Travel",
            "subcategory":"Hotels & Motels",
            "type":"Entertainment"
        }
    ],
    "sg:phone":"+43 5583 22540",
    "sg:postcode":"6763",
    "sg:province":"Vorarlberg",
    "wof:name":"Sporthotel Lor\u00fcnser",
    "wof:placetype":"venue"
},
  "geometry": {"coordinates":[166.9221496582,-0.5282999873],"type":"Point"}
}