{
  "type": "Feature",
  "properties": {
    "iso:country":"AT",
    "sg:address":"Nr 5",
    "sg:city":"Strass im Zillertal",
    "sg:orig_category":"Erdarbeiten",
    "sg:phone":"+43 5244 62104",
    "sg:postcode":"6261",
    "sg:province":"Tirol",
    "wof:name":"Knapp Johann",
    "wof:placetype":"venue"
},
  "geometry": {"coordinates":[11.8219985962,47.3957252502],"type":"Point"}
}