{
  "type": "Feature",
  "properties": {
    "addr:full":"Hauptstrasse 31 Altenmarkt-Thenneberg Nieder\u00f6sterreich 2571",
    "addr:housenumber":"31",
    "addr:postcode":"2571",
    "addr:street":"Hauptstrasse;Niederoesterreich",
    "iso:country":"AT",
    "sg:address":"Hauptstrasse 31",
    "sg:city":"Altenmarkt-Thenneberg",
    "sg:classifiers":[
        {
            "category":"Government",
            "subcategory":"Post Office",
            "type":"Public Place"
        }
    ],
    "sg:phone":"+43 2673 7005",
    "sg:postcode":"2571",
    "sg:province":"Nieder\u00f6sterreich",
    "sg:tags":[
        "technical",
        "injection",
        "parts",
        "moulded"
    ],
    "sg:website":"mack.co.at",
    "wof:name":"Josef Mack Ges.m.b.H.",
    "wof:placetype":"venue"
},
  "geometry": {"coordinates":[15.99771595,48.0151939392],"type":"Point"}
}