{
  "type": "Feature",
  "properties": {
    "addr:full":"Bahnstrasse 60  Schrems Nieder\u00f6sterreich 3943",
    "addr:housenumber":"60",
    "addr:postcode":"3943",
    "addr:street":"Bahnstrasse",
    "iso:country":"AT",
    "sg:address":"Bahnstrasse 60 ",
    "sg:city":"Schrems",
    "sg:classifiers":[
        {
            "category":"Manufacturing",
            "subcategory":"Lumber",
            "type":"Manufacturing & Wholesale Goods"
        }
    ],
    "sg:phone":"+43 2853 77378",
    "sg:postcode":"3943",
    "sg:province":"Nieder\u00f6sterreich",
    "sg:tags":[
        "hardwood",
        "sawmill"
    ],
    "sg:website":"www.zwickl.wvnet.at",
    "wof:name":"Dipl.-Ing. Johannes Zwickl",
    "wof:placetype":"venue"
},
  "geometry": {"coordinates":[15.0704898834,48.78647995],"type":"Point"}
}