{
  "type": "Feature",
  "properties": {
    "addr:full":"Ziehrerg 2 Judenburg Steiermark 8750",
    "addr:housenumber":"2",
    "addr:postcode":"8750",
    "addr:street":"Ziehrerg",
    "iso:country":"AT",
    "sg:address":"Ziehrerg 2",
    "sg:city":"Judenburg",
    "sg:orig_category":"Gastronomie- U Hotelbetriebsgesellschaften",
    "sg:phone":"+43 4335 7242424",
    "sg:postcode":"8750",
    "sg:province":"Steiermark",
    "wof:name":"LBF-Handels u Betriebs GesmbH",
    "wof:placetype":"venue"
},
  "geometry": {"coordinates":[14.6606082916,47.1684303284],"type":"Point"}
}