{
  "type": "Feature",
  "properties": {
    "iso:country":"AT",
    "sg:address":"Kopernikusg 7",
    "sg:city":"Graz",
    "sg:orig_category":"Architekten",
    "sg:phone":"+43 4331 6812299",
    "sg:postcode":"8010",
    "sg:province":"Steiermark",
    "wof:name":"Kadletz Michael Arch Dipl-Ing",
    "wof:placetype":"venue"
},
  "geometry": {"coordinates":[15.4489603043,47.0660171509],"type":"Point"}
}