{
  "type": "Feature",
  "properties": {
    "addr:full":"Mitterg 4 Saalfelden am Steinernen Meer Salzburg 5760",
    "addr:housenumber":"4",
    "addr:postcode":"5760",
    "addr:street":"Mitterg",
    "iso:country":"AT",
    "sg:address":"Mitterg 4",
    "sg:city":"Saalfelden am Steinernen Meer",
    "sg:orig_category":"Geschenkartikel",
    "sg:phone":"+43 4365 8275099",
    "sg:postcode":"5760",
    "sg:province":"Salzburg",
    "wof:name":"Maja's Geschenksboutique Oase der Sinne",
    "wof:placetype":"venue"
},
  "geometry": {"coordinates":[12.8474216461,47.4273986816],"type":"Point"}
}