{
  "type": "Feature",
  "properties": {
    "iso:country":"AT",
    "sg:address":"Baudi\u00dfg 5-7",
    "sg:city":"Wien",
    "sg:orig_category":"Transportunternehmen",
    "sg:phone":"+43 1 76780800",
    "sg:postcode":"1110",
    "sg:province":"Wien",
    "wof:name":"In-night Express GmbH",
    "wof:placetype":"venue"
},
  "geometry": {"coordinates":[16.4623947144,48.1463737488],"type":"Point"}
}