{
  "type": "Feature",
  "properties": {
    "iso:country":"AT",
    "sg:address":"Moatelerweg 8",
    "sg:city":"Volders",
    "sg:orig_category":"Zimmereien",
    "sg:phone":"+43 4352 2453053",
    "sg:postcode":"6111",
    "sg:province":"Tirol",
    "wof:name":"Egger Alfons",
    "wof:placetype":"venue"
},
  "geometry": {"coordinates":[11.5704030991,47.2868041992],"type":"Point"}
}