{
  "type": "Feature",
  "properties": {
    "addr:full":"Hetzendorfer Strasse 141 Wien Wien 1120",
    "addr:housenumber":"141",
    "addr:postcode":"1120",
    "addr:street":"Hetzendorfer Strasse",
    "iso:country":"AT",
    "sg:address":"Hetzendorfer Strasse 141",
    "sg:city":"Wien",
    "sg:classifiers":[
        {
            "category":"Utilities",
            "subcategory":"Cable",
            "type":"Services"
        }
    ],
    "sg:phone":"+43 1 80481410",
    "sg:postcode":"1120",
    "sg:province":"Wien",
    "sg:tags":[
        "tv",
        "installation"
    ],
    "sg:website":"tplus.at",
    "wof:name":"Tplus Kabel & Kommunikation GmbH",
    "wof:placetype":"venue"
},
  "geometry": {"coordinates":[16.3004875183,48.1696510315],"type":"Point"}
}