{
  "type": "Feature",
  "properties": {
    "iso:country":"AT",
    "sg:address":"Maximilianstr 37",
    "sg:city":"Blindenmarkt",
    "sg:orig_category":"Transportunternehmen",
    "sg:phone":"+43 7473 6885",
    "sg:postcode":"3372",
    "sg:province":"Nieder\u00f6sterreich",
    "wof:name":"W\u00f6gerer Regina",
    "wof:placetype":"venue"
},
  "geometry": {"coordinates":[14.9852466583,48.1310081482],"type":"Point"}
}