{
  "type": "Feature",
  "properties": {
    "iso:country":"AT",
    "sg:address":"Hernalser Hauptstr 202",
    "sg:city":"Wien",
    "sg:orig_category":"Elektroinstallationsunternehmen",
    "sg:phone":"+43 1 4861169",
    "sg:postcode":"1170",
    "sg:province":"Wien",
    "wof:name":"Pfeffer Peter",
    "wof:placetype":"venue"
},
  "geometry": {"coordinates":[16.3126926422,48.2248153687],"type":"Point"}
}