{
  "type": "Feature",
  "properties": {
    "addr:full":"Viktorg 5 Wien Wien 1040",
    "addr:housenumber":"5",
    "addr:postcode":"1040",
    "addr:street":"Viktorg",
    "iso:country":"AT",
    "sg:address":"Viktorg 5",
    "sg:city":"Wien",
    "sg:orig_category":"Metallbau",
    "sg:phone":"+43 1 5052166",
    "sg:postcode":"1040",
    "sg:province":"Wien",
    "sg:website":"www.wernermetall.at",
    "wof:name":"Werner Metalltechnik GmbH",
    "wof:placetype":"venue"
},
  "geometry": {"coordinates":[16.3736286163,48.1908073425],"type":"Point"}
}