{
  "type": "Feature",
  "properties": {
    "addr:full":"Unterdorf 52 Hopfgarten im Brixental Tirol 6361",
    "addr:housenumber":"52",
    "addr:postcode":"6361",
    "addr:street":"Unterdorf;Tirol",
    "iso:country":"AT",
    "sg:address":"Unterdorf 52",
    "sg:city":"Hopfgarten im Brixental",
    "sg:orig_category":"Lebensmittel / Einzelhandel",
    "sg:phone":"+43 5335 8260",
    "sg:postcode":"6361",
    "sg:province":"Tirol",
    "wof:name":"Nah & Frisch Markt",
    "wof:placetype":"venue"
},
  "geometry": {"coordinates":[12.133852005,47.3900337219],"type":"Point"}
}