{
  "type": "Feature",
  "properties": {
    "addr:full":"Kreuzpl 20 Bad Ischl Ober\u00f6sterreich 4820",
    "addr:housenumber":"20",
    "addr:postcode":"4820",
    "addr:street":"Kreuzpl",
    "iso:country":"AT",
    "sg:address":"Kreuzpl 20",
    "sg:city":"Bad Ischl",
    "sg:orig_category":"Banken U Sparkassen",
    "sg:phone":"+43 4361 32261810",
    "sg:postcode":"4820",
    "sg:province":"Ober\u00f6sterreich",
    "wof:name":"Bankomat d Raiffeisenbank Inneres Salzkammergut regGenmbH",
    "wof:placetype":"venue"
},
  "geometry": {"coordinates":[13.6216726303,47.7129631042],"type":"Point"}
}