{
  "type": "Feature",
  "properties": {
    "addr:full":"Spiegelg 6 Wien Wien 1010",
    "addr:housenumber":"6",
    "addr:postcode":"1010",
    "addr:street":"Spiegelg",
    "iso:country":"AT",
    "sg:address":"Spiegelg 6",
    "sg:city":"Wien",
    "sg:orig_category":"Boutiquen",
    "sg:phone":"+43 1 5138443",
    "sg:postcode":"1010",
    "sg:province":"Wien",
    "wof:name":"Henryk's Classics",
    "wof:placetype":"venue"
},
  "geometry": {"coordinates":[16.3700618744,48.2075309753],"type":"Point"}
}