{
  "type": "Feature",
  "properties": {
    "addr:full":"Fischauer G 45-47 Wiener Neustadt Nieder\u00f6sterreich 2700",
    "addr:postcode":"45-47;2700",
    "addr:street":"Fischauer G;Niederoesterreich",
    "iso:country":"AT",
    "sg:address":"Fischauer G 45-47",
    "sg:city":"Wiener Neustadt",
    "sg:orig_category":"Lebensmittel / Einzelhandel",
    "sg:phone":"+43 2622 26366",
    "sg:postcode":"2700",
    "sg:province":"Nieder\u00f6sterreich",
    "wof:name":"Zielpunkt Warenhandel GmbH & Co KG",
    "wof:placetype":"venue"
},
  "geometry": {"coordinates":[16.2415103912,47.8224182129],"type":"Point"}
}