{
  "type": "Feature",
  "properties": {
    "addr:full":"Eisteichstr 11 Wien Wien 1110",
    "addr:housenumber":"11",
    "addr:postcode":"1110",
    "addr:street":"Eisteichstr",
    "iso:country":"AT",
    "sg:address":"Eisteichstr 11",
    "sg:city":"Wien",
    "sg:orig_category":"Unterhaltungselektronik / Reparatur",
    "sg:phone":"+43 1 7493330",
    "sg:postcode":"1110",
    "sg:province":"Wien",
    "wof:name":"Jozefowski Radio- und Fernseh-Service GesmbH",
    "wof:placetype":"venue"
},
  "geometry": {"coordinates":[16.4147663116,48.1802787781],"type":"Point"}
}