{
  "type": "Feature",
  "properties": {
    "addr:full":"Salurner G 9 Dornbirn Vorarlberg 6850",
    "addr:housenumber":"9",
    "addr:postcode":"6850",
    "addr:street":"Salurner G",
    "iso:country":"AT",
    "sg:address":"Salurner G 9",
    "sg:city":"Dornbirn",
    "sg:orig_category":"Fahrschulen",
    "sg:phone":"+43 4355 72216660",
    "sg:postcode":"6850",
    "sg:province":"Vorarlberg",
    "wof:name":"Easy Drivers Fahrschule Inh Heufelder Rudi",
    "wof:placetype":"venue"
},
  "geometry": {"coordinates":[9.7365188599,47.4121131897],"type":"Point"}
}