{
  "type": "Feature",
  "properties": {
    "addr:full":"Marktpl 39 Aurolzm\u00fcnster Ober\u00f6sterreich 4971",
    "addr:housenumber":"39",
    "addr:postcode":"4971",
    "addr:street":"Marktpl;Oberoesterreich",
    "iso:country":"AT",
    "sg:address":"Marktpl 39",
    "sg:city":"Aurolzm\u00fcnster",
    "sg:orig_category":"Banken U Sparkassen",
    "sg:phone":"+43 4377 52830350",
    "sg:postcode":"4971",
    "sg:province":"Ober\u00f6sterreich",
    "wof:name":"Bankomat d Raiffeisenbank Region Ried regGenmbH",
    "wof:placetype":"venue"
},
  "geometry": {"coordinates":[13.4540681839,48.2487983704],"type":"Point"}
}