{
  "type": "Feature",
  "properties": {
    "iso:country":"AT",
    "sg:address":"Hausmanning 54",
    "sg:city":"Schlierbach",
    "sg:orig_category":"Feuerwehren",
    "sg:phone":"+43 7582 63125",
    "sg:postcode":"4553",
    "sg:province":"Ober\u00f6sterreich",
    "wof:name":"Freiwillige Feuerwehr Oberschlierbach",
    "wof:placetype":"venue"
},
  "geometry": {"coordinates":[14.1536102295,47.9212112427],"type":"Point"}
}