{
  "type": "Feature",
  "properties": {
    "addr:full":"Erlaaer Str 74 Wien Wien 1230",
    "addr:postcode":"1230",
    "addr:street":"Str 74",
    "iso:country":"AT",
    "sg:address":"Erlaaer Str 74",
    "sg:city":"Wien",
    "sg:orig_category":"Volksschulen",
    "sg:phone":"+43 1 8690248",
    "sg:postcode":"1230",
    "sg:province":"Wien",
    "wof:name":"Schulen d Stadt Wien",
    "wof:placetype":"venue"
},
  "geometry": {"coordinates":[16.3120632172,48.1426734924],"type":"Point"}
}