{
  "type": "Feature",
  "properties": {
    "addr:full":"Arriach K\u00e4rnten 9543",
    "addr:housenumber":"9543",
    "iso:country":"AT",
    "sg:city":"Arriach",
    "sg:orig_category":"Feuerwehren",
    "sg:phone":"+43 4247 8122",
    "sg:postcode":"9543",
    "sg:province":"K\u00e4rnten",
    "wof:name":"Feuerwehr Laastadt",
    "wof:placetype":"venue"
},
  "geometry": {"coordinates":[13.8503751755,46.7427215576],"type":"Point"}
}