{
  "type": "Feature",
  "properties": {
    "iso:country":"AT",
    "sg:address":"Ferihumerstrasse 9",
    "sg:city":"Linz",
    "sg:classifiers":[
        {
            "category":"Government",
            "subcategory":"Department Of Motor Vehicles",
            "type":"Public Place"
        }
    ],
    "sg:phone":"+43 732 732502",
    "sg:postcode":"4040",
    "sg:province":"Ober\u00f6sterreich",
    "sg:tags":[
        "car",
        "rental",
        "brokerage"
    ],
    "wof:name":"Dr. Slavko Mihalic",
    "wof:placetype":"venue"
},
  "geometry": {"coordinates":[14.2855234146,48.3126182556],"type":"Point"}
}