{
  "type": "Feature",
  "properties": {
    "addr:full":"Zierhofweg 6 Grimmenstein Nieder\u00f6sterreich 2840",
    "addr:housenumber":"6",
    "addr:postcode":"2840",
    "addr:street":"Zierhofweg",
    "iso:country":"AT",
    "sg:address":"Zierhofweg 6",
    "sg:city":"Grimmenstein",
    "sg:orig_category":"Feuerwehren",
    "sg:phone":"+43 2644 8384",
    "sg:postcode":"2840",
    "sg:province":"Nieder\u00f6sterreich",
    "wof:name":"Freiwillige Feuerwehr Grimmenstein",
    "wof:placetype":"venue"
},
  "geometry": {"coordinates":[16.0891628265,47.6381034851],"type":"Point"}
}