{
  "type": "Feature",
  "properties": {
    "addr:full":"Industriezone Burgerfeld 7 Wilhelmsburg an der Traisen Nieder\u00f6sterreich 3150",
    "addr:housenumber":"7",
    "addr:postcode":"3150",
    "addr:street":"Industriezone Burgerfeld",
    "iso:country":"AT",
    "sg:address":"Industriezone Burgerfeld 7",
    "sg:city":"Wilhelmsburg an der Traisen",
    "sg:classifiers":[
        {
            "category":"Utilities",
            "subcategory":"Recycling",
            "type":"Services"
        }
    ],
    "sg:phone":"+43 4327 464040",
    "sg:postcode":"3150",
    "sg:province":"Nieder\u00f6sterreich",
    "wof:name":"NOVA Recycling GesmbH",
    "wof:placetype":"venue"
},
  "geometry": {"coordinates":[15.6089849472,48.116104126],"type":"Point"}
}