{
  "type": "Feature",
  "properties": {
    "addr:full":"Nr 12 Traunstein Nieder\u00f6sterreich 3632",
    "addr:postcode":"3632",
    "addr:street":"Nr 12",
    "iso:country":"AT",
    "sg:address":"Nr 12",
    "sg:city":"Traunstein",
    "sg:orig_category":"Appartements / Ferienwohnungen",
    "sg:phone":"+43 4328 786822",
    "sg:postcode":"3632",
    "sg:province":"Nieder\u00f6sterreich",
    "wof:name":"H\u00f6barth Martha",
    "wof:placetype":"venue"
},
  "geometry": {"coordinates":[15.1159744263,48.4355010986],"type":"Point"}
}