{
  "type": "Feature",
  "properties": {
    "addr:full":"Am Winterhafen 13 Linz Ober\u00f6sterreich 4020",
    "addr:housenumber":"13",
    "addr:postcode":"4020",
    "addr:street":"Am Winterhafen",
    "iso:country":"AT",
    "sg:address":"Am Winterhafen 13",
    "sg:city":"Linz",
    "sg:orig_category":"Datenverarbeitung",
    "sg:phone":"+43 732 779748",
    "sg:postcode":"4020",
    "sg:province":"Ober\u00f6sterreich",
    "wof:name":"MBI - Niederwimmer GesmbH",
    "wof:placetype":"venue"
},
  "geometry": {"coordinates":[14.3034849167,48.3191947937],"type":"Point"}
}