{
  "type": "Feature",
  "properties": {
    "iso:country":"AT",
    "sg:address":"Dommayerg 7",
    "sg:city":"Wien",
    "sg:orig_category":"Waren Aller Art",
    "sg:phone":"+43 1 87789410",
    "sg:postcode":"1130",
    "sg:province":"Wien",
    "wof:name":"Madal Bal AG & Co GmbH",
    "wof:placetype":"venue"
},
  "geometry": {"coordinates":[16.2990970612,48.1879005432],"type":"Point"}
}