{
  "type": "Feature",
  "properties": {
    "addr:full":"Haymong 1 Innsbruck Tirol 6020",
    "addr:housenumber":"1",
    "addr:postcode":"6020",
    "addr:street":"Haymong;Tirol",
    "iso:country":"AT",
    "sg:address":"Haymong 1",
    "sg:city":"Innsbruck",
    "sg:orig_category":"Restaurants: Griechisch",
    "sg:phone":"+43 512 561231",
    "sg:postcode":"6020",
    "sg:province":"Tirol",
    "wof:name":"Taverna Dionysos",
    "wof:placetype":"venue"
},
  "geometry": {"coordinates":[11.3978052139,47.2554397583],"type":"Point"}
}