{
  "type": "Feature",
  "properties": {
    "addr:full":"Lambacher Str 11 Vorchdorf Ober\u00f6sterreich 4655",
    "addr:postcode":"4655",
    "addr:street":"Str 11",
    "iso:country":"AT",
    "sg:address":"Lambacher Str 11",
    "sg:city":"Vorchdorf",
    "sg:orig_category":"Autohandel",
    "sg:phone":"+43 761479330",
    "sg:postcode":"4655",
    "sg:province":"Ober\u00f6sterreich",
    "wof:name":"Auto Esthofer Team GmbH - Autohaus Vorchdorf",
    "wof:placetype":"venue"
},
  "geometry": {"coordinates":[13.9215574265,48.0040855408],"type":"Point"}
}