{
  "type": "Feature",
  "properties": {
    "iso:country":"AT",
    "sg:address":"Alplstr 43",
    "sg:city":"Krieglach",
    "sg:orig_category":"Rettungsdienste",
    "sg:phone":"+43 3855 2444",
    "sg:postcode":"8670",
    "sg:province":"Steiermark",
    "wof:name":"Rotes Kreuz \u00f6sterr Ortsstelle Krieglach",
    "wof:placetype":"venue"
},
  "geometry": {"coordinates":[15.5645799637,47.5454711914],"type":"Point"}
}