{
  "type": "Feature",
  "properties": {
    "addr:full":"Rosentaler Str. 17 Klagenfurt K\u00e4rnten 9020",
    "addr:housenumber":"17",
    "addr:postcode":"9020",
    "addr:street":"Str.;Kaernten",
    "iso:country":"AT",
    "sg:address":"Rosentaler Str. 17",
    "sg:city":"Klagenfurt",
    "sg:classifiers":[
        {
            "category":"Shopping",
            "subcategory":"Computers & Home Electronics",
            "type":"Retail Goods"
        }
    ],
    "sg:phone":"+43 4346 35114450",
    "sg:postcode":"9020",
    "sg:province":"K\u00e4rnten",
    "sg:tags":[
        "electronic",
        "electrical",
        "equipment"
    ],
    "wof:name":"VORWER AUSTRIA GMBH & CO. KG",
    "wof:placetype":"venue"
},
  "geometry": {"coordinates":[14.3021507263,46.6173057556],"type":"Point"}
}