{
  "type": "Feature",
  "properties": {
    "addr:full":"Moostratten 9 Gm\u00fcnd K\u00e4rnten 9853",
    "addr:housenumber":"9",
    "addr:postcode":"9853",
    "addr:street":"Moostratten;Kaernten",
    "iso:country":"AT",
    "sg:address":"Moostratten 9",
    "sg:city":"Gm\u00fcnd",
    "sg:orig_category":"Maschinenhandel",
    "sg:phone":"+43 4732 31650",
    "sg:postcode":"9853",
    "sg:province":"K\u00e4rnten",
    "wof:name":"Sagmeister-Feichter Martina",
    "wof:placetype":"venue"
},
  "geometry": {"coordinates":[13.5352258682,46.9030456543],"type":"Point"}
}