{
  "type": "Feature",
  "properties": {
    "addr:full":"Herbersteinstr 4 Graz Steiermark 8020",
    "addr:housenumber":"4",
    "addr:postcode":"8020",
    "addr:street":"Herbersteinstr",
    "iso:country":"AT",
    "sg:address":"Herbersteinstr 4",
    "sg:city":"Graz",
    "sg:orig_category":"Weiterbildungsinstitute M Allg U Berufl Bildungsangebot",
    "sg:phone":"+43 316 585458",
    "sg:postcode":"8020",
    "sg:province":"Steiermark",
    "wof:name":"ESC - Education Service Center GmbH",
    "wof:placetype":"venue"
},
  "geometry": {"coordinates":[15.3951396942,47.0719947815],"type":"Point"}
}