{
  "type": "Feature",
  "properties": {
    "addr:full":"Nr 175 Schrattenthal Nieder\u00f6sterreich 2073",
    "addr:postcode":"2073",
    "addr:street":"Nr;Schrattenthal Niederoesterreich",
    "iso:country":"AT",
    "sg:address":"Nr 175",
    "sg:city":"Schrattenthal",
    "sg:orig_category":"Stickereien",
    "sg:phone":"+43 676 5202907",
    "sg:postcode":"2073",
    "sg:province":"Nieder\u00f6sterreich",
    "wof:name":"Stickwerk",
    "wof:placetype":"venue"
},
  "geometry": {"coordinates":[15.9088430405,48.7167282104],"type":"Point"}
}