{
  "type": "Feature",
  "properties": {
    "iso:country":"AT",
    "sg:address":"Nr 1",
    "sg:city":"Scheifling",
    "sg:orig_category":"Transportunternehmen",
    "sg:phone":"+43 4335 828348",
    "sg:postcode":"8811",
    "sg:province":"Steiermark",
    "wof:name":"Hainzl Florian",
    "wof:placetype":"venue"
},
  "geometry": {"coordinates":[14.4103889465,47.1504631042],"type":"Point"}
}