{
  "type": "Feature",
  "properties": {
    "iso:country":"AT",
    "sg:address":"M\u00fchltal 36",
    "sg:city":"W\u00f6rgl",
    "sg:orig_category":"Tischlereien",
    "sg:phone":"+43 5332 743060",
    "sg:postcode":"6300",
    "sg:province":"Tirol",
    "wof:name":"Decker Josef",
    "wof:placetype":"venue"
},
  "geometry": {"coordinates":[12.1438121796,47.4709892273],"type":"Point"}
}