{
  "type": "Feature",
  "properties": {
    "addr:full":"Am Hausberg 35 Gratkorn Steiermark 8101",
    "addr:housenumber":"35",
    "addr:postcode":"8101",
    "addr:street":"Am Hausberg",
    "iso:country":"AT",
    "sg:address":"Am Hausberg 35",
    "sg:city":"Gratkorn",
    "sg:orig_category":"Beratungsstellen",
    "sg:phone":"+43 676 848786100",
    "sg:postcode":"8101",
    "sg:province":"Steiermark",
    "wof:name":"Promod4teens",
    "wof:placetype":"venue"
},
  "geometry": {"coordinates":[15.3366365433,47.1389122009],"type":"Point"}
}