{
  "type": "Feature",
  "properties": {
    "iso:country":"AT",
    "sg:address":"Wiener Str 112",
    "sg:city":"Pfaffst\u00e4tten",
    "sg:orig_category":"Stahlbau",
    "sg:phone":"+43 4322 52206789",
    "sg:postcode":"2511",
    "sg:province":"Nieder\u00f6sterreich",
    "wof:name":"Hanjes & Co Stahlbau GesmbH",
    "wof:placetype":"venue"
},
  "geometry": {"coordinates":[-80.22747802729999,40.6339416504],"type":"Point"}
}