{
  "type": "Feature",
  "properties": {
    "addr:full":"Hauptstr 50 Stockerau Nieder\u00f6sterreich 2000",
    "addr:housenumber":"50",
    "addr:postcode":"2000",
    "addr:street":"Hauptstr",
    "iso:country":"AT",
    "sg:address":"Hauptstr 50",
    "sg:city":"Stockerau",
    "sg:orig_category":"Damenmoden",
    "sg:phone":"+43 2266 62603",
    "sg:postcode":"2000",
    "sg:province":"Nieder\u00f6sterreich",
    "wof:name":"Schneider Franz GesmbH & Co KG",
    "wof:placetype":"venue"
},
  "geometry": {"coordinates":[16.2157402039,48.3859596252],"type":"Point"}
}