{
  "type": "Feature",
  "properties": {
    "addr:full":"Nr 16 Waxenberg Ober\u00f6sterreich 4182",
    "addr:postcode":"4182",
    "addr:street":"Nr;Waxenberg",
    "iso:country":"AT",
    "sg:address":"Nr 16",
    "sg:city":"Waxenberg",
    "sg:orig_category":"Fotografen",
    "sg:phone":"+43 664 2097450",
    "sg:postcode":"4182",
    "sg:province":"Ober\u00f6sterreich",
    "wof:name":"Laresser Rudolf Online Fotoagentur",
    "wof:placetype":"venue"
},
  "geometry": {"coordinates":[14.1926040649,48.4773483276],"type":"Point"}
}