{
  "type": "Feature",
  "properties": {
    "addr:full":"Hauptpl 17 Knittelfeld Steiermark 8720",
    "addr:housenumber":"17",
    "addr:postcode":"8720",
    "addr:street":"Hauptpl",
    "iso:country":"AT",
    "sg:address":"Hauptpl 17",
    "sg:city":"Knittelfeld",
    "sg:orig_category":"Bekleidung / Einzelhandel",
    "sg:phone":"+43 4335 1284396",
    "sg:postcode":"8720",
    "sg:province":"Steiermark",
    "wof:name":"Sch\u00f6ps Richard & Co AG",
    "wof:placetype":"venue"
},
  "geometry": {"coordinates":[14.8298921585,47.2151527405],"type":"Point"}
}