{
  "type": "Feature",
  "properties": {
    "iso:country":"AT",
    "sg:address":"Linzer G 25",
    "sg:city":"Salzburg",
    "sg:orig_category":"Handelsagenturen",
    "sg:phone":"+43 662 452832",
    "sg:postcode":"5020",
    "sg:province":"Salzburg",
    "wof:name":"Teufl Christian Kollektion",
    "wof:placetype":"venue"
},
  "geometry": {"coordinates":[13.0464582443,47.8031921387],"type":"Point"}
}