{
  "type": "Feature",
  "properties": {
    "addr:full":"Kalzitstrasse 15 Buchkirchen Ober\u00f6sterreich 4611",
    "addr:housenumber":"15",
    "addr:postcode":"4611",
    "addr:street":"Kalzitstrasse",
    "iso:country":"AT",
    "sg:address":"Kalzitstrasse 15",
    "sg:city":"Buchkirchen",
    "sg:classifiers":[
        {
            "category":"Shopping Center",
            "type":"Public Place"
        }
    ],
    "sg:phone":"+43 7243 51823",
    "sg:postcode":"4611",
    "sg:province":"Ober\u00f6sterreich",
    "sg:tags":[
        "aluminium",
        "section"
    ],
    "sg:website":"alutechnik.at",
    "wof:name":"ALUTECHNIK Produktions-Ges.m.b.H.",
    "wof:placetype":"venue"
},
  "geometry": {"coordinates":[14.0783281326,48.1996307373],"type":"Point"}
}