{
  "type": "Feature",
  "properties": {
    "addr:full":"Widag 9 Dornbirn Vorarlberg 6850",
    "addr:housenumber":"9",
    "addr:postcode":"6850",
    "addr:street":"Widag",
    "iso:country":"AT",
    "sg:address":"Widag 9",
    "sg:city":"Dornbirn",
    "sg:orig_category":"Galerien",
    "sg:phone":"+43 5572 312310",
    "sg:postcode":"6850",
    "sg:province":"Vorarlberg",
    "wof:name":"c.art Prantl & Boch Galerie u. Verlag GmbH",
    "wof:placetype":"venue"
},
  "geometry": {"coordinates":[9.7437801361,47.4131889343],"type":"Point"}
}