{
  "type": "Feature",
  "properties": {
    "addr:full":"An der Bahn 50 St. Peter in der Au Nieder\u00f6sterreich 3352",
    "addr:housenumber":"50",
    "addr:postcode":"3352",
    "addr:street":"An Der Bahn",
    "iso:country":"AT",
    "sg:address":"An der Bahn 50",
    "sg:city":"St. Peter in der Au",
    "sg:orig_category":"Freizeitangebote U -Einrichtungen",
    "sg:phone":"+43 4374 7742788",
    "sg:postcode":"3352",
    "sg:province":"Nieder\u00f6sterreich",
    "wof:name":"Gasthaus Lazelsberger",
    "wof:placetype":"venue"
},
  "geometry": {"coordinates":[14.64798069,48.0539665222],"type":"Point"}
}