{
  "type": "Feature",
  "properties": {
    "addr:full":"Radetzkystr 10 Klagenfurt K\u00e4rnten 9020",
    "addr:housenumber":"10",
    "addr:postcode":"9020",
    "addr:street":"Radetzkystr;Kaernten",
    "iso:country":"AT",
    "sg:address":"Radetzkystr 10",
    "sg:city":"Klagenfurt",
    "sg:orig_category":"Tierkliniken",
    "sg:phone":"+43 463 5129690",
    "sg:postcode":"9020",
    "sg:province":"K\u00e4rnten",
    "wof:name":"Kreuzbergl Tierklinik",
    "wof:placetype":"venue"
},
  "geometry": {"coordinates":[14.2998733521,46.6274719238],"type":"Point"}
}