{
  "type": "Feature",
  "properties": {
    "iso:country":"AT",
    "sg:address":"Ferdinand-Wedenig-Strasse 49a/3",
    "sg:city":"Villach",
    "sg:classifiers":[
        {
            "category":"Utilities",
            "subcategory":"Cable",
            "type":"Services"
        }
    ],
    "sg:phone":"+43 4252 24653",
    "sg:postcode":"9500",
    "sg:province":"K\u00e4rnten",
    "sg:website":"edv-nischelwitzer.at",
    "wof:name":"EDV Service Roland Nischelwitzer",
    "wof:placetype":"venue"
},
  "geometry": {"coordinates":[13.910241127,46.6227722168],"type":"Point"}
}