{
  "type": "Feature",
  "properties": {
    "addr:full":"Nr 15 Pennewang Ober\u00f6sterreich 4624",
    "addr:postcode":"4624",
    "addr:street":"Nr 15",
    "iso:country":"AT",
    "sg:address":"Nr 15",
    "sg:city":"Pennewang",
    "sg:orig_category":"Non-Classified Establishments",
    "sg:phone":"+43 7245 26177",
    "sg:postcode":"4624",
    "sg:province":"Ober\u00f6sterreich",
    "wof:name":"Pfarramt",
    "wof:placetype":"venue"
},
  "geometry": {"coordinates":[13.8426761627,48.1287078857],"type":"Point"}
}