{
  "type": "Feature",
  "properties": {
    "addr:full":"Bahnhofstr 11 Windischgarsten Ober\u00f6sterreich 4580",
    "addr:housenumber":"11",
    "addr:postcode":"4580",
    "addr:street":"Bahnhofstr",
    "iso:country":"AT",
    "sg:address":"Bahnhofstr 11",
    "sg:city":"Windischgarsten",
    "sg:orig_category":"Textilwaren / Einzelhandel",
    "sg:phone":"+43 7562 20632",
    "sg:postcode":"4580",
    "sg:province":"Ober\u00f6sterreich",
    "wof:name":"TPS",
    "wof:placetype":"venue"
},
  "geometry": {"coordinates":[14.3282003403,47.7204093933],"type":"Point"}
}