{
  "type": "Feature",
  "properties": {
    "iso:country":"AT",
    "sg:address":"Berglandstr 28",
    "sg:city":"Saalfelden am Steinernen Meer",
    "sg:orig_category":"Freizeitangebote U -Einrichtungen",
    "sg:phone":"+43 6582 70288",
    "sg:postcode":"5760",
    "sg:province":"Salzburg",
    "wof:name":"Kinder- und Jugendzentrum d \u00d6sterreichische Kinderfreunde",
    "wof:placetype":"venue"
},
  "geometry": {"coordinates":[12.8532018661,47.422088623],"type":"Point"}
}