{
  "type": "Feature",
  "properties": {
    "addr:full":"Watzing 10 St. Roman Ober\u00f6sterreich 4793",
    "addr:housenumber":"10",
    "addr:postcode":"4793",
    "addr:street":"Watzing",
    "iso:country":"AT",
    "sg:address":"Watzing 10",
    "sg:city":"St. Roman",
    "sg:orig_category":"Granitwerke",
    "sg:phone":"+43 4377 167371",
    "sg:postcode":"4793",
    "sg:province":"Ober\u00f6sterreich",
    "wof:name":"H\u00f6ller KEG",
    "wof:placetype":"venue"
},
  "geometry": {"coordinates":[13.6362953186,48.4968605042],"type":"Point"}
}