{
  "type": "Feature",
  "properties": {
    "addr:full":"Carlbergergasse 38 Wien Wien 1230",
    "addr:housenumber":"38",
    "addr:postcode":"1230",
    "addr:street":"Carlbergergasse",
    "iso:country":"AT",
    "sg:address":"Carlbergergasse 38",
    "sg:city":"Wien",
    "sg:classifiers":[
        {
            "category":"Train Station",
            "subcategory":"Light Rail",
            "type":"Transportation"
        }
    ],
    "sg:phone":"+43 1 8654397",
    "sg:postcode":"1230",
    "sg:province":"Wien",
    "sg:tags":[
        "sprocket",
        "drives",
        "chain"
    ],
    "sg:website":"optibelt.com",
    "wof:name":"Optibelt \u00d6sterreich GmbH",
    "wof:placetype":"venue"
},
  "geometry": {"coordinates":[16.2932910919,48.141254425],"type":"Point"}
}