{
  "type": "Feature",
  "properties": {
    "addr:full":"Glanzingg 23 Wien Wien 1190",
    "addr:housenumber":"23",
    "addr:postcode":"1190",
    "addr:street":"Glanzingg",
    "iso:country":"AT",
    "sg:address":"Glanzingg 23",
    "sg:city":"Wien",
    "sg:orig_category":"Beratungsstellen",
    "sg:phone":"+43 1 4700110",
    "sg:postcode":"1190",
    "sg:province":"Wien",
    "wof:name":"Kleemann & Partner Tourismusconsulting GesmbH",
    "wof:placetype":"venue"
},
  "geometry": {"coordinates":[16.3153247833,48.2440109253],"type":"Point"}
}