{
  "type": "Feature",
  "properties": {
    "addr:full":"Bahnhofstr 8 Ebensee Ober\u00f6sterreich 4802",
    "addr:housenumber":"8",
    "addr:postcode":"4802",
    "addr:street":"Bahnhofstr",
    "iso:country":"AT",
    "sg:address":"Bahnhofstr 8",
    "sg:city":"Ebensee",
    "sg:orig_category":"Restaurants: Chinesisch",
    "sg:phone":"+43 6133 6833",
    "sg:postcode":"4802",
    "sg:province":"Ober\u00f6sterreich",
    "wof:name":"China-Restaurant Jasmin",
    "wof:placetype":"venue"
},
  "geometry": {"coordinates":[13.7718791962,47.8083610535],"type":"Point"}
}