{
  "type": "Feature",
  "properties": {
    "iso:country":"AT",
    "sg:address":"Robert-Lach-G 36",
    "sg:city":"Wien",
    "sg:orig_category":"Musikverlage",
    "sg:phone":"+43 1 2593811",
    "sg:postcode":"1210",
    "sg:province":"Wien",
    "wof:name":"Chmela Horst",
    "wof:placetype":"venue"
},
  "geometry": {"coordinates":[16.4394378662,48.271774292],"type":"Point"}
}