{
  "type": "Feature",
  "properties": {
    "addr:full":"Wei\u00dfgerberl\u00e4nde 38 Wien Wien 1030",
    "addr:housenumber":"38",
    "addr:postcode":"1030",
    "addr:street":"Weissgerberlaende",
    "iso:country":"AT",
    "sg:address":"Wei\u00dfgerberl\u00e4nde 38",
    "sg:city":"Wien",
    "sg:classifiers":[
        {
            "category":"Professional",
            "subcategory":"Business Services",
            "type":"Services"
        }
    ],
    "sg:phone":"+43 4317 133733",
    "sg:postcode":"1030",
    "sg:province":"Wien",
    "sg:tags":[
        "advice"
    ],
    "wof:name":"BEKO ING. P. KOTAUCZEK GMBH",
    "wof:placetype":"venue"
},
  "geometry": {"coordinates":[16.4025096893,48.1936683655],"type":"Point"}
}