{
  "type": "Feature",
  "properties": {
    "iso:country":"AT",
    "sg:address":"Wilhelminenstr 71",
    "sg:city":"Wien",
    "sg:orig_category":"Fotoausarbeitungen",
    "sg:phone":"+43 4314 841528",
    "sg:postcode":"1160",
    "sg:province":"Wien",
    "wof:name":"Bildermacher",
    "wof:placetype":"venue"
},
  "geometry": {"coordinates":[16.3105602264,48.217212677],"type":"Point"}
}