{
  "type": "Feature",
  "properties": {
    "iso:country":"AT",
    "sg:address":"Wiedner Hauptstr 70",
    "sg:city":"Wien",
    "sg:orig_category":"Friseure U Frisiersalons",
    "sg:phone":"+43 1 587669415",
    "sg:postcode":"1040",
    "sg:province":"Wien",
    "wof:name":"Ihr dm Friseur Studio",
    "wof:placetype":"venue"
},
  "geometry": {"coordinates":[16.3657608032,48.1899299622],"type":"Point"}
}