{
  "type": "Feature",
  "properties": {
    "addr:full":"Augartenstrasse 27 Lustenau Vorarlberg 6890",
    "addr:housenumber":"27",
    "addr:postcode":"6890",
    "addr:street":"Augartenstrasse",
    "iso:country":"AT",
    "sg:address":"Augartenstrasse 27",
    "sg:city":"Lustenau",
    "sg:orig_category":"Cnc-Milled Parts",
    "sg:phone":"+43 5577 833870",
    "sg:postcode":"6890",
    "sg:province":"Vorarlberg",
    "sg:website":"spannfix.at",
    "wof:name":"Witzemann & Fritz GmbH",
    "wof:placetype":"venue"
},
  "geometry": {"coordinates":[9.6518230438,47.4410705566],"type":"Point"}
}