{
  "type": "Feature",
  "properties": {
    "iso:country":"AT",
    "sg:address":"Alser Strasse 24",
    "sg:city":"Wien",
    "sg:classifiers":[
        {
            "category":"Shopping",
            "subcategory":"Books",
            "type":"Retail Goods"
        }
    ],
    "sg:phone":"+43 1 40444172",
    "sg:postcode":"1090",
    "sg:province":"Wien",
    "sg:website":"ueberreuter.at",
    "wof:name":"Verlag Carl Ueberreuter GmbH",
    "wof:placetype":"venue"
},
  "geometry": {"coordinates":[16.347694397,48.2154846191],"type":"Point"}
}