{
  "type": "Feature",
  "properties": {
    "addr:full":"Katztal 34 Munderfing Ober\u00f6sterreich 5222",
    "addr:housenumber":"34",
    "addr:postcode":"5222",
    "addr:street":"Katztal",
    "iso:country":"AT",
    "sg:address":"Katztal 34",
    "sg:city":"Munderfing",
    "sg:classifiers":[
        {
            "category":"Professional",
            "subcategory":"Art Services",
            "type":"Services"
        }
    ],
    "sg:phone":"+43 7744 8182",
    "sg:postcode":"5222",
    "sg:province":"Ober\u00f6sterreich",
    "sg:tags":[
        "metalwork"
    ],
    "wof:name":"Gebr\u00fcder Weing GnbR",
    "wof:placetype":"venue"
},
  "geometry": {"coordinates":[13.1928691864,48.0616035461],"type":"Point"}
}