{
  "type": "Feature",
  "properties": {
    "addr:full":"Ettendorfer Str 3 Stainz Steiermark 8510",
    "addr:housenumber":"3",
    "addr:postcode":"8510",
    "addr:street":"Str",
    "iso:country":"AT",
    "sg:address":"Ettendorfer Str 3",
    "sg:city":"Stainz",
    "sg:orig_category":"Tourismusinformation U -Organisationen",
    "sg:phone":"+43 3463 4950",
    "sg:postcode":"8510",
    "sg:province":"Steiermark",
    "wof:name":"Tourismusregionalverband Weststeiermark",
    "wof:placetype":"venue"
},
  "geometry": {"coordinates":[15.2682723999,46.8939781189],"type":"Point"}
}