{
  "type": "Feature",
  "properties": {
    "addr:full":"S\u00e4ngerhofg 47 Tribuswinkel Nieder\u00f6sterreich 2512",
    "addr:housenumber":"47",
    "addr:postcode":"2512",
    "addr:street":"Saengerhofg",
    "iso:country":"AT",
    "sg:address":"S\u00e4ngerhofg 47",
    "sg:city":"Tribuswinkel",
    "sg:orig_category":"Tischlereien",
    "sg:phone":"+43 4322 5245079",
    "sg:postcode":"2512",
    "sg:province":"Nieder\u00f6sterreich",
    "wof:name":"Herberts Meistertischlerei",
    "wof:placetype":"venue"
},
  "geometry": {"coordinates":[16.2946853638,47.9884490967],"type":"Point"}
}