{
  "type": "Feature",
  "properties": {
    "addr:full":"Adolf Pichler-Pl 8 Innsbruck Tirol 6020",
    "addr:housenumber":"8",
    "addr:postcode":"6020",
    "addr:street":"Tirol",
    "iso:country":"AT",
    "sg:address":"Adolf Pichler-Pl 8",
    "sg:city":"Innsbruck",
    "sg:orig_category":"Galerien",
    "sg:phone":"+43 512 5722360",
    "sg:postcode":"6020",
    "sg:province":"Tirol",
    "wof:name":"Fotoforum West",
    "wof:placetype":"venue"
},
  "geometry": {"coordinates":[11.3913288116,47.2660217285],"type":"Point"}
}