{
  "type": "Feature",
  "properties": {
    "addr:full":"Wickenburgg 12/501 Wien Wien 1080",
    "addr:housenumber":"12 / 501",
    "addr:postcode":"1080",
    "addr:street":"Wickenburgg",
    "iso:country":"AT",
    "sg:address":"Wickenburgg 12/501",
    "sg:city":"Wien",
    "sg:orig_category":"Gewerkschaften",
    "sg:phone":"+43 4314 063394",
    "sg:postcode":"1080",
    "sg:province":"Wien",
    "wof:name":"\u00f6sterreichischer Gewerkschaftsbund - 19. Bundessektion Justizwachegewerkschaft",
    "wof:placetype":"venue"
},
  "geometry": {"coordinates":[16.3543014526,48.2129974365],"type":"Point"}
}