{
  "type": "Feature",
  "properties": {
    "addr:full":"Goldschlagstr 133 Wien Wien 1140",
    "addr:housenumber":"133",
    "addr:postcode":"1140",
    "iso:country":"AT",
    "sg:address":"Goldschlagstr 133",
    "sg:city":"Wien",
    "sg:orig_category":"Glasbe- U -Verarbeitung",
    "sg:phone":"+43 4319 857548",
    "sg:postcode":"1140",
    "sg:province":"Wien",
    "sg:website":"glas-trotberger.at",
    "wof:name":"Trotberger Wolfgang",
    "wof:placetype":"venue"
},
  "geometry": {"coordinates":[16.3122882843,48.1954345703],"type":"Point"}
}