{
  "type": "Feature",
  "properties": {
    "addr:full":"Mahlerstr 11 Wien Wien 1010",
    "addr:housenumber":"11",
    "addr:postcode":"1010",
    "addr:street":"Mahlerstr",
    "iso:country":"AT",
    "sg:address":"Mahlerstr 11",
    "sg:city":"Wien",
    "sg:orig_category":"Geigen",
    "sg:phone":"+43 1 5122077",
    "sg:postcode":"1010",
    "sg:province":"Wien",
    "wof:name":"Tunkowitsch Peter",
    "wof:placetype":"venue"
},
  "geometry": {"coordinates":[16.3727397919,48.202583313],"type":"Point"}
}