{
  "type": "Feature",
  "properties": {
    "iso:country":"AT",
    "sg:address":"Kajetanerpl 4",
    "sg:city":"Salzburg",
    "sg:orig_category":"Lebensmittel / Einzelhandel",
    "sg:phone":"+43 4366 2848168",
    "sg:postcode":"5020",
    "sg:province":"Salzburg",
    "wof:name":"Shake & Snack's Minimarket",
    "wof:placetype":"venue"
},
  "geometry": {"coordinates":[13.0514593124,47.7965888977],"type":"Point"}
}