{
  "type": "Feature",
  "properties": {
    "iso:country":"AT",
    "sg:address":"Pfarrg 22",
    "sg:city":"Imst",
    "sg:orig_category":"Immobilienverwaltungen",
    "sg:phone":"+43 5412 65543",
    "sg:postcode":"6460",
    "sg:province":"Tirol",
    "wof:name":"Kugler Becker OEG",
    "wof:placetype":"venue"
},
  "geometry": {"coordinates":[10.7392578125,47.2440567017],"type":"Point"}
}