{
  "type": "Feature",
  "properties": {
    "addr:full":"Nr 1 St. Konrad Ober\u00f6sterreich 4817",
    "addr:housenumber":"1",
    "addr:postcode":"4817",
    "addr:street":"Nr;Oberoesterreich",
    "iso:country":"AT",
    "sg:address":"Nr 1",
    "sg:city":"St. Konrad",
    "sg:orig_category":"Tankstellen",
    "sg:phone":"+43 4376 158009",
    "sg:postcode":"4817",
    "sg:province":"Ober\u00f6sterreich",
    "wof:name":"BP Austria Marketing GmbH",
    "wof:placetype":"venue"
},
  "geometry": {"coordinates":[13.8887310028,47.9127082825],"type":"Point"}
}