{
  "type": "Feature",
  "properties": {
    "addr:full":"Kapellenweg 2 Munderfing Ober\u00f6sterreich 5222",
    "addr:housenumber":"2",
    "addr:postcode":"5222",
    "addr:street":"Kapellenweg",
    "iso:country":"AT",
    "sg:address":"Kapellenweg 2",
    "sg:city":"Munderfing",
    "sg:orig_category":"Tischlereien",
    "sg:phone":"+43 7744 6653",
    "sg:postcode":"5222",
    "sg:province":"Ober\u00f6sterreich",
    "wof:name":"Hansel G\u00fcnther",
    "wof:placetype":"venue"
},
  "geometry": {"coordinates":[13.1795539856,48.0670928955],"type":"Point"}
}