{
  "type": "Feature",
  "properties": {
    "addr:full":"Werkg 3 Aspang-Markt Nieder\u00f6sterreich 2870",
    "addr:housenumber":"3",
    "addr:postcode":"2870",
    "addr:street":"Werkg;Niederoesterreich",
    "iso:country":"AT",
    "sg:address":"Werkg 3",
    "sg:city":"Aspang-Markt",
    "sg:orig_category":"Maler, Anstreicher U Lackierer",
    "sg:phone":"+43 2642 52401",
    "sg:postcode":"2870",
    "sg:province":"Nieder\u00f6sterreich",
    "wof:name":"Traint Alfred",
    "wof:placetype":"venue"
},
  "geometry": {"coordinates":[16.099691391,47.5694961548],"type":"Point"}
}