{
  "type": "Feature",
  "properties": {
    "iso:country":"AT",
    "sg:address":"Teichsdlg 167",
    "sg:city":"Gutenbrunn",
    "sg:orig_category":"Schneidereien",
    "sg:phone":"+43 2874 6356",
    "sg:postcode":"3665",
    "sg:province":"Nieder\u00f6sterreich",
    "wof:name":"Redl Kornelia",
    "wof:placetype":"venue"
},
  "geometry": {"coordinates":[15.1187696457,48.3656806946],"type":"Point"}
}