{
  "type": "Feature",
  "properties": {
    "addr:full":"Bahnhofstr 43 Pregarten Ober\u00f6sterreich 4230",
    "addr:postcode":"4230",
    "addr:street":"Bahnhofstr 43",
    "iso:country":"AT",
    "sg:address":"Bahnhofstr 43",
    "sg:city":"Pregarten",
    "sg:orig_category":"Hafnereien",
    "sg:phone":"+43 7236 3460",
    "sg:postcode":"4230",
    "sg:province":"Ober\u00f6sterreich",
    "wof:name":"Frieske Werner",
    "wof:placetype":"venue"
},
  "geometry": {"coordinates":[14.5246343613,48.355266571],"type":"Point"}
}