{
  "type": "Feature",
  "properties": {
    "addr:full":"Am Exerzierfeld 27 Leonding Ober\u00f6sterreich 4060",
    "addr:housenumber":"27",
    "addr:postcode":"4060",
    "addr:street":"Am Exerzierfeld",
    "iso:country":"AT",
    "sg:address":"Am Exerzierfeld 27",
    "sg:city":"Leonding",
    "sg:orig_category":"Ingenieurkonsulenten / Zivilingenieure",
    "sg:phone":"+43 732 782726",
    "sg:postcode":"4060",
    "sg:province":"Ober\u00f6sterreich",
    "wof:name":"Hanser Siegmar Dipl-Ing Dr",
    "wof:placetype":"venue"
},
  "geometry": {"coordinates":[14.2636518478,48.2932357788],"type":"Point"}
}