{
  "type": "Feature",
  "properties": {
    "iso:country":"AT",
    "sg:address":"Roseggerstr 40",
    "sg:city":"Krieglach",
    "sg:orig_category":"Raumausstattung",
    "sg:phone":"+43 3855 3280",
    "sg:postcode":"8670",
    "sg:province":"Steiermark",
    "wof:name":"M\u00f6bel Anninger GmbH",
    "wof:placetype":"venue"
},
  "geometry": {"coordinates":[15.562921524,47.5469741821],"type":"Point"}
}