{
  "type": "Feature",
  "properties": {
    "addr:full":"Nr 22 Eckartsau Nieder\u00f6sterreich 2305",
    "addr:postcode":"2305",
    "addr:street":"Nr 22 Eckartsau",
    "iso:country":"AT",
    "sg:address":"Nr 22",
    "sg:city":"Eckartsau",
    "sg:orig_category":"Baumeister",
    "sg:phone":"+43 2214 2205",
    "sg:postcode":"2305",
    "sg:province":"Nieder\u00f6sterreich",
    "wof:name":"Windisch Johann Dipl-Ing",
    "wof:placetype":"venue"
},
  "geometry": {"coordinates":[16.7954540253,48.1472091675],"type":"Point"}
}