{
  "type": "Feature",
  "properties": {
    "iso:country":"AT",
    "sg:address":"Angerg 13",
    "sg:city":"Sieggraben",
    "sg:orig_category":"Tapezierer U Dekorateure",
    "sg:phone":"+43 2621 2237",
    "sg:postcode":"7223",
    "sg:province":"Burgenland",
    "wof:name":"Kern Silvia KEG",
    "wof:placetype":"venue"
},
  "geometry": {"coordinates":[16.383190155,47.6483039856],"type":"Point"}
}