{
  "type": "Feature",
  "properties": {
    "iso:country":"AT",
    "sg:address":"Sankt Johann im Saggautal 49",
    "sg:city":"St. Johann im Saggautal",
    "sg:orig_category":"Anti-Mould Coatings",
    "sg:phone":"+43 3455 385",
    "sg:postcode":"8453",
    "sg:province":"Steiermark",
    "wof:name":"Richard Reiterer",
    "wof:placetype":"venue"
},
  "geometry": {"coordinates":[15.4114570618,46.7167243958],"type":"Point"}
}