{
  "type": "Feature",
  "properties": {
    "addr:full":"Mariahilfer Str 53 Wien Wien 1060",
    "addr:postcode":"1060",
    "addr:street":"Str 53",
    "iso:country":"AT",
    "sg:address":"Mariahilfer Str 53",
    "sg:city":"Wien",
    "sg:orig_category":"Immobilienverwaltungen",
    "sg:phone":"+43 1 58786700",
    "sg:postcode":"1060",
    "sg:province":"Wien",
    "wof:name":"B\u00f6hm Hedwig",
    "wof:placetype":"venue"
},
  "geometry": {"coordinates":[16.3536453247,48.1995391846],"type":"Point"}
}