{
  "type": "Feature",
  "properties": {
    "addr:full":"Hauptstr 354 Kalsdorf Steiermark 8401",
    "addr:housenumber":"354",
    "addr:postcode":"8401",
    "addr:street":"Hauptstr",
    "iso:country":"AT",
    "sg:address":"Hauptstr 354",
    "sg:city":"Kalsdorf",
    "sg:orig_category":"Landwirtschaftliche Produkte",
    "sg:phone":"+43 4331 3552806",
    "sg:postcode":"8401",
    "sg:province":"Steiermark",
    "wof:name":"Schwarz Julius",
    "wof:placetype":"venue"
},
  "geometry": {"coordinates":[15.4812793732,46.9529418945],"type":"Point"}
}