{
  "type": "Feature",
  "properties": {
    "addr:full":"Nr 147 Arzl im Pitztal Tirol 6471",
    "addr:postcode":"6471",
    "addr:street":"Nr 147;Tirol",
    "iso:country":"AT",
    "sg:address":"Nr 147",
    "sg:city":"Arzl im Pitztal",
    "sg:orig_category":"Pensionen / Privatzimmer",
    "sg:phone":"+43 4354 1264397",
    "sg:postcode":"6471",
    "sg:province":"Tirol",
    "wof:name":"Haus Burgstall Familie Krismer",
    "wof:placetype":"venue"
},
  "geometry": {"coordinates":[10.7617301941,47.2069854736],"type":"Point"}
}