{
  "type": "Feature",
  "properties": {
    "addr:full":"Posenerg 14/4/17 Andritz Steiermark 8045",
    "addr:housenumber":"14 / 4 / 17",
    "addr:postcode":"8045",
    "addr:street":"Posenerg",
    "iso:country":"AT",
    "sg:address":"Posenerg 14/4/17",
    "sg:city":"Andritz",
    "sg:orig_category":"Werbeagenturen",
    "sg:phone":"+43 664 4457328",
    "sg:postcode":"8045",
    "sg:province":"Steiermark",
    "wof:name":"1. S\u00dcDFLUG Luftwerbung GesbR",
    "wof:placetype":"venue"
},
  "geometry": {"coordinates":[15.4198312759,47.1376914978],"type":"Point"}
}