{
  "type": "Feature",
  "properties": {
    "addr:full":"Ossiacher Zeile 74 Villach K\u00e4rnten 9500",
    "addr:housenumber":"74",
    "addr:postcode":"9500",
    "addr:street":"Ossiacher Zeile;Kaernten",
    "iso:country":"AT",
    "sg:address":"Ossiacher Zeile 74",
    "sg:city":"Villach",
    "sg:orig_category":"Autoreparatur",
    "sg:phone":"+43 4242 431220",
    "sg:postcode":"9500",
    "sg:province":"K\u00e4rnten",
    "wof:name":"Fastbox Autoservice GmbH & Co KG",
    "wof:placetype":"venue"
},
  "geometry": {"coordinates":[13.8604698181,46.6176300049],"type":"Point"}
}