{
  "type": "Feature",
  "properties": {
    "addr:full":"Kaiserstr 10 Zistersdorf Nieder\u00f6sterreich 2225",
    "addr:housenumber":"10",
    "addr:postcode":"2225",
    "addr:street":"Kaiserstr;Niederoesterreich",
    "iso:country":"AT",
    "sg:address":"Kaiserstr 10",
    "sg:city":"Zistersdorf",
    "sg:orig_category":"Medizinische Institute",
    "sg:phone":"+43 2532 80188",
    "sg:postcode":"2225",
    "sg:province":"Nieder\u00f6sterreich",
    "wof:name":"Institut f\u00fcr Alternative Gesundheitsberatung - Dr Alfred Klabuschnigg",
    "wof:placetype":"venue"
},
  "geometry": {"coordinates":[16.758731842,48.5456047058],"type":"Point"}
}