{
  "type": "Feature",
  "properties": {
    "addr:full":"Schalchner Str 12 Mattighofen Ober\u00f6sterreich 5230",
    "addr:postcode":"5230",
    "addr:street":"Str 12",
    "iso:country":"AT",
    "sg:address":"Schalchner Str 12",
    "sg:city":"Mattighofen",
    "sg:orig_category":"Kinderbetreuung",
    "sg:phone":"+43 7742 3045",
    "sg:postcode":"5230",
    "sg:province":"Ober\u00f6sterreich",
    "wof:name":"Kindergarten d Stadtgemeinde",
    "wof:placetype":"venue"
},
  "geometry": {"coordinates":[13.1554765701,48.1095123291],"type":"Point"}
}