{
  "type": "Feature",
  "properties": {
    "addr:full":"Saalachstr 1 Salzburg Salzburg 5020",
    "addr:housenumber":"1",
    "addr:postcode":"5020",
    "addr:street":"Saalachstr;Salzburg",
    "iso:country":"AT",
    "sg:address":"Saalachstr 1",
    "sg:city":"Salzburg",
    "sg:orig_category":"Reifen U Reifendienste",
    "sg:phone":"+43 662 4352160",
    "sg:postcode":"5020",
    "sg:province":"Salzburg",
    "sg:website":"www.reifen-john.com",
    "wof:name":"Reifen John HandelsgesmbH",
    "wof:placetype":"venue"
},
  "geometry": {"coordinates":[13.0019836426,47.8301086426],"type":"Point"}
}