{
  "type": "Feature",
  "properties": {
    "addr:full":"Wiesenau 33 Bad St. Leonhard im Lavanttal K\u00e4rnten 9462",
    "addr:housenumber":"33",
    "addr:postcode":"9462",
    "addr:street":"Wiesenau",
    "iso:country":"AT",
    "sg:address":"Wiesenau 33",
    "sg:city":"Bad St. Leonhard im Lavanttal",
    "sg:orig_category":"Bauunternehmen",
    "sg:phone":"+43 4366 43206529",
    "sg:postcode":"9462",
    "sg:province":"K\u00e4rnten",
    "wof:name":"St\u00fcckler G\u00fcnther",
    "wof:placetype":"venue"
},
  "geometry": {"coordinates":[14.8133554459,46.9448890686],"type":"Point"}
}