{
  "type": "Feature",
  "properties": {
    "addr:full":"Stra\u00df 42 Lech Vorarlberg 6764",
    "addr:housenumber":"42",
    "addr:postcode":"6764",
    "addr:street":"Strass",
    "iso:country":"AT",
    "sg:address":"Stra\u00df 42",
    "sg:city":"Lech",
    "sg:orig_category":"Pensionen / Privatzimmer",
    "sg:phone":"+43 5583 29850",
    "sg:postcode":"6764",
    "sg:province":"Vorarlberg",
    "wof:name":"Hotel-Pension Almrausch",
    "wof:placetype":"venue"
},
  "geometry": {"coordinates":[10.1417798996,47.2082939148],"type":"Point"}
}