{
  "type": "Feature",
  "properties": {
    "addr:full":"Bilgeristr 4 Innsbruck-Igls Tirol 6080",
    "addr:housenumber":"4",
    "addr:postcode":"6080",
    "addr:street":"Bilgeristr",
    "iso:country":"AT",
    "sg:address":"Bilgeristr 4",
    "sg:city":"Innsbruck-Igls",
    "sg:orig_category":"Appartements / Ferienwohnungen",
    "sg:phone":"+43 512 3772210",
    "sg:postcode":"6080",
    "sg:province":"Tirol",
    "wof:name":"Appartementhaus Bellevue-Igls",
    "wof:placetype":"venue"
},
  "geometry": {"coordinates":[11.410949707,47.2305793762],"type":"Point"}
}