{
  "type": "Feature",
  "properties": {
    "addr:full":"Nr 56a Brixlegg Tirol 6230",
    "addr:postcode":"6230",
    "addr:street":"Nr 56A;Tirol",
    "iso:country":"AT",
    "sg:address":"Nr 56a",
    "sg:city":"Brixlegg",
    "sg:orig_category":"\u00c3\u201enderungsschneidereien",
    "sg:phone":"+43 5337 63540",
    "sg:postcode":"6230",
    "sg:province":"Tirol",
    "wof:name":"Scheidnagl Erna",
    "wof:placetype":"venue"
},
  "geometry": {"coordinates":[11.8779993057,47.4296073914],"type":"Point"}
}