{
  "type": "Feature",
  "properties": {
    "addr:full":"Kirchfeld 1 Rattenberg Tirol 6240",
    "addr:housenumber":"1",
    "addr:postcode":"6240",
    "addr:street":"Kirchfeld;Tirol",
    "iso:country":"AT",
    "sg:address":"Kirchfeld 1",
    "sg:city":"Rattenberg",
    "sg:orig_category":"Volksschulen",
    "sg:phone":"+43 5337 63901",
    "sg:postcode":"6240",
    "sg:province":"Tirol",
    "wof:name":"Volksschule",
    "wof:placetype":"venue"
},
  "geometry": {"coordinates":[11.9094696045,47.4501419067],"type":"Point"}
}