{
  "type": "Feature",
  "properties": {
    "iso:country":"AT",
    "sg:address":"Nr 40",
    "sg:city":"Weinburg am Sa\u00dfbach",
    "sg:orig_category":"Abfallentsorgung U -Verwertung",
    "sg:phone":"+43 4366 43372421",
    "sg:postcode":"8481",
    "sg:province":"Steiermark",
    "wof:name":"Leicht & Leicht Kompostierung GmbH",
    "wof:placetype":"venue"
},
  "geometry": {"coordinates":[15.7206382751,46.7537765503],"type":"Point"}
}