{
  "type": "Feature",
  "properties": {
    "addr:full":"Brucknerstr 20 Ried im Innkreis Ober\u00f6sterreich 4910",
    "addr:housenumber":"20",
    "addr:postcode":"4910",
    "addr:street":"Brucknerstr",
    "iso:country":"AT",
    "sg:address":"Brucknerstr 20",
    "sg:city":"Ried im Innkreis",
    "sg:orig_category":"Hauptschulen",
    "sg:phone":"+43 7752 825940",
    "sg:postcode":"4910",
    "sg:province":"Ober\u00f6sterreich",
    "wof:name":"Hauptschule 1",
    "wof:placetype":"venue"
},
  "geometry": {"coordinates":[13.4807043076,48.2072219849],"type":"Point"}
}