{
  "type": "Feature",
  "properties": {
    "addr:full":"Christian-Blattl-Weg 7 St. Johann in Tirol Tirol 6380",
    "addr:housenumber":"7",
    "addr:postcode":"6380",
    "addr:street":"Christian-Blattl-Weg;Tirol",
    "iso:country":"AT",
    "sg:address":"Christian-Blattl-Weg 7",
    "sg:city":"St. Johann in Tirol",
    "sg:classifiers":[
        {
            "category":"Travel",
            "subcategory":"Hotels & Motels",
            "type":"Entertainment"
        }
    ],
    "sg:phone":"+43 5352 63564",
    "sg:postcode":"6380",
    "sg:province":"Tirol",
    "sg:website":"www.hotel-sonne.com",
    "wof:name":"Hotel Sonne",
    "wof:placetype":"venue"
},
  "geometry": {"coordinates":[12.4238967896,47.5179481506],"type":"Point"}
}