{
  "type": "Feature",
  "properties": {
    "addr:full":"Sebastianstr 46 Oggau Burgenland 7063",
    "addr:housenumber":"46",
    "addr:postcode":"7063",
    "addr:street":"Sebastianstr",
    "iso:country":"AT",
    "sg:address":"Sebastianstr 46",
    "sg:city":"Oggau",
    "sg:orig_category":"Friseure U Frisiersalons",
    "sg:phone":"+43 4326 857288",
    "sg:postcode":"7063",
    "sg:province":"Burgenland",
    "wof:name":"Posch Christa",
    "wof:placetype":"venue"
},
  "geometry": {"coordinates":[16.6667728424,47.8344078064],"type":"Point"}
}