{
  "type": "Feature",
  "properties": {
    "iso:country":"AT",
    "sg:address":"Nr 224",
    "sg:city":"Saalbach",
    "sg:orig_category":"Pensionen / Privatzimmer",
    "sg:phone":"+43 6541 8233",
    "sg:postcode":"5753",
    "sg:province":"Salzburg",
    "wof:name":"Pension Schneider",
    "wof:placetype":"venue"
},
  "geometry": {"coordinates":[166.9221496582,-0.5282999873],"type":"Point"}
}