{
  "type": "Feature",
  "properties": {
    "addr:full":"Kirchpl 1 Ehrwald Tirol 6632",
    "addr:housenumber":"1",
    "addr:postcode":"6632",
    "addr:street":"Kirchpl;Tirol",
    "iso:country":"AT",
    "sg:address":"Kirchpl 1",
    "sg:city":"Ehrwald",
    "sg:orig_category":"Tourismusinformation U -Organisationen",
    "sg:phone":"+43 4356 7320000",
    "sg:postcode":"6632",
    "sg:province":"Tirol",
    "wof:name":"Tourismusregion Tiroler Zugspitz Arena",
    "wof:placetype":"venue"
},
  "geometry": {"coordinates":[10.91913414,47.3990287781],"type":"Point"}
}