{
  "type": "Feature",
  "properties": {
    "addr:full":"Zillner Str 19 Salzburg Salzburg 5020",
    "addr:housenumber":"19",
    "addr:postcode":"5020",
    "addr:street":"Str;Salzburg",
    "iso:country":"AT",
    "sg:address":"Zillner Str 19",
    "sg:city":"Salzburg",
    "sg:orig_category":"Bauunternehmen",
    "sg:phone":"+43 4366 2421920",
    "sg:postcode":"5020",
    "sg:province":"Salzburg",
    "wof:name":"Ringler Injektionstechnik",
    "wof:placetype":"venue"
},
  "geometry": {"coordinates":[13.0307350159,47.8036804199],"type":"Point"}
}