{
  "type": "Feature",
  "properties": {
    "iso:country":"AT",
    "sg:address":"Billrothstr. 99",
    "sg:city":"Wels",
    "sg:classifiers":[
        {
            "category":"Shopping",
            "subcategory":"Clothing, Apparel, & Fashions",
            "type":"Retail Goods"
        }
    ],
    "sg:phone":"+43 4372 42600000",
    "sg:postcode":"4600",
    "sg:province":"Ober\u00f6sterreich",
    "sg:tags":[
        "clothing",
        "accessory"
    ],
    "wof:name":"STAUDINGER HANDELS- GES.MBH & CO KG",
    "wof:placetype":"venue"
},
  "geometry": {"coordinates":[13.9992341995,48.1616096497],"type":"Point"}
}