{
  "type": "Feature",
  "properties": {
    "addr:full":"Albrechtskreithg 19-21 Wien Wien 1160",
    "addr:postcode":"19-21;1160",
    "iso:country":"AT",
    "sg:address":"Albrechtskreithg 19-21",
    "sg:city":"Wien",
    "sg:orig_category":"Familien / Beratung",
    "sg:phone":"+43 4318 7812390",
    "sg:postcode":"1160",
    "sg:province":"Wien",
    "wof:name":"Caritas d Erzdi\u00f6zese Wien Familienhilfe d Caritas Wien",
    "wof:placetype":"venue"
},
  "geometry": {"coordinates":[16.3162326813,48.2203826904],"type":"Point"}
}