{
  "type": "Feature",
  "properties": {
    "addr:full":"Wiener Str 38 Krems an der Donau Nieder\u00f6sterreich 3500",
    "addr:postcode":"3500",
    "addr:street":"38",
    "iso:country":"AT",
    "sg:address":"Wiener Str 38",
    "sg:city":"Krems an der Donau",
    "sg:orig_category":"Mineralien",
    "sg:phone":"+43 4327 3286863",
    "sg:postcode":"3500",
    "sg:province":"Nieder\u00f6sterreich",
    "wof:name":"Reither Christopher - Edelsteine & Mineralien/Ghdl",
    "wof:placetype":"venue"
},
  "geometry": {"coordinates":[15.6107082367,48.4132118225],"type":"Point"}
}