{
  "type": "Feature",
  "properties": {
    "addr:full":"Nr 137 Breitenfeld an der Rittschein Steiermark 8313",
    "addr:postcode":"8313",
    "addr:street":"Nr",
    "iso:country":"AT",
    "sg:address":"Nr 137",
    "sg:city":"Breitenfeld an der Rittschein",
    "sg:orig_category":"Finanz- U Wirtschaftsberatung",
    "sg:phone":"+43 4367 69541405",
    "sg:postcode":"8313",
    "sg:province":"Steiermark",
    "wof:name":"MONEX",
    "wof:placetype":"venue"
},
  "geometry": {"coordinates":[15.9435653687,47.048248291],"type":"Point"}
}