{
  "type": "Feature",
  "properties": {
    "addr:full":"Suppanstr 69 Klagenfurt K\u00e4rnten 9020",
    "addr:housenumber":"69",
    "addr:postcode":"9020",
    "addr:street":"Suppanstr;Kaernten",
    "iso:country":"AT",
    "sg:address":"Suppanstr 69",
    "sg:city":"Klagenfurt",
    "sg:orig_category":"Audiovisuelle Produktionen",
    "sg:phone":"+43 676 7213450",
    "sg:postcode":"9020",
    "sg:province":"K\u00e4rnten",
    "wof:name":"DRUCKS ProduktionsgesmbH",
    "wof:placetype":"venue"
},
  "geometry": {"coordinates":[14.2942228317,46.6484870911],"type":"Point"}
}