{
  "type": "Feature",
  "properties": {
    "iso:country":"AT",
    "sg:address":"Europastr 14",
    "sg:city":"Maria Lanzendorf",
    "sg:orig_category":"Baumeister",
    "sg:phone":"+43 4322 35429680",
    "sg:postcode":"2326",
    "sg:province":"Nieder\u00f6sterreich",
    "wof:name":"WK - Bau GmbH",
    "wof:placetype":"venue"
},
  "geometry": {"coordinates":[16.4184589386,48.1011924744],"type":"Point"}
}