{
  "type": "Feature",
  "properties": {
    "iso:country":"AT",
    "sg:address":"Seestr 152",
    "sg:city":"Obertraun",
    "sg:classifiers":[
        {
            "category":"Travel",
            "subcategory":"Hotels & Motels",
            "type":"Entertainment"
        }
    ],
    "sg:phone":"+43 6131 4620",
    "sg:postcode":"4831",
    "sg:province":"Ober\u00f6sterreich",
    "wof:name":"Seehotel Wenk",
    "wof:placetype":"venue"
},
  "geometry": {"coordinates":[13.6827783585,47.5589904785],"type":"Point"}
}