{
  "type": "Feature",
  "properties": {
    "addr:full":"Neuklosterpl 2 Wiener Neustadt Nieder\u00f6sterreich 2700",
    "addr:housenumber":"2",
    "addr:postcode":"2700",
    "addr:street":"Neuklosterpl",
    "iso:country":"AT",
    "sg:address":"Neuklosterpl 2",
    "sg:city":"Wiener Neustadt",
    "sg:orig_category":"Versicherungsunternehmen",
    "sg:phone":"+43 2622 24959",
    "sg:postcode":"2700",
    "sg:province":"Nieder\u00f6sterreich",
    "wof:name":"Grazer Wechselseitige Versicherung AG",
    "wof:placetype":"venue"
},
  "geometry": {"coordinates":[16.2458515167,47.8120956421],"type":"Point"}
}