{
  "type": "Feature",
  "properties": {
    "addr:full":"Wurzingerg 2 Wien Wien 1180",
    "addr:housenumber":"2",
    "addr:postcode":"1180",
    "addr:street":"Wurzingerg",
    "iso:country":"AT",
    "sg:address":"Wurzingerg 2",
    "sg:city":"Wien",
    "sg:orig_category":"Isolierungen",
    "sg:phone":"+43 1 4780747",
    "sg:postcode":"1180",
    "sg:province":"Wien",
    "wof:name":"Ridisser A GesmbH",
    "wof:placetype":"venue"
},
  "geometry": {"coordinates":[16.3162631989,48.2391281128],"type":"Point"}
}