{
  "type": "Feature",
  "properties": {
    "addr:full":"Dr.-Theodor-K\u00f6rner-Platz 3 Bruck an der Leitha Nieder\u00f6sterreich 2460",
    "addr:housenumber":"3",
    "addr:postcode":"2460",
    "addr:street":"Dr.-Theodor-Koerner-Platz",
    "iso:country":"AT",
    "sg:address":"Dr.-Theodor-K\u00f6rner-Platz 3",
    "sg:city":"Bruck an der Leitha",
    "sg:classifiers":[
        {
            "category":"Government",
            "subcategory":"Fire Station",
            "type":"Public Place"
        }
    ],
    "sg:phone":"+43 2162 65865",
    "sg:postcode":"2460",
    "sg:province":"Nieder\u00f6sterreich",
    "sg:tags":[
        "steel",
        "chimney"
    ],
    "wof:name":"Spenglerei Baswald",
    "wof:placetype":"venue"
},
  "geometry": {"coordinates":[16.7785491943,48.022026062],"type":"Point"}
}