{
  "type": "Feature",
  "properties": {
    "addr:full":"Markt 32 Pabneukirchen Ober\u00f6sterreich 4363",
    "addr:housenumber":"32",
    "addr:postcode":"4363",
    "addr:street":"Markt",
    "iso:country":"AT",
    "sg:address":"Markt 32",
    "sg:city":"Pabneukirchen",
    "sg:orig_category":"Friseure U Frisiersalons",
    "sg:phone":"+43 4372 655225",
    "sg:postcode":"4363",
    "sg:province":"Ober\u00f6sterreich",
    "wof:name":"Dumfart Alfred",
    "wof:placetype":"venue"
},
  "geometry": {"coordinates":[14.8168287277,48.3218002319],"type":"Point"}
}