{
  "type": "Feature",
  "properties": {
    "addr:full":"Museumstr 1 Innsbruck Tirol 6020",
    "addr:housenumber":"1",
    "addr:postcode":"6020",
    "addr:street":"Museumstr;Tirol",
    "iso:country":"AT",
    "sg:address":"Museumstr 1",
    "sg:city":"Innsbruck",
    "sg:orig_category":"Optiker",
    "sg:phone":"+43 512 581067",
    "sg:postcode":"6020",
    "sg:province":"Tirol",
    "wof:name":"Pearle \u00f6sterreich GmbH",
    "wof:placetype":"venue"
},
  "geometry": {"coordinates":[11.3955106735,47.2673721313],"type":"Point"}
}