{
  "type": "Feature",
  "properties": {
    "addr:full":"Kleiststr 17 Wels Ober\u00f6sterreich 4600",
    "addr:housenumber":"17",
    "addr:postcode":"4600",
    "addr:street":"Kleiststr;Oberoesterreich",
    "iso:country":"AT",
    "sg:address":"Kleiststr 17",
    "sg:city":"Wels",
    "sg:classifiers":[
        {
            "category":"Taxi",
            "type":"Transportation"
        }
    ],
    "sg:phone":"+43 7242 63780",
    "sg:postcode":"4600",
    "sg:province":"Ober\u00f6sterreich",
    "sg:tags":[
        "personentransporte",
        "u"
    ],
    "wof:name":"Klement Kurt",
    "wof:placetype":"venue"
},
  "geometry": {"coordinates":[14.0572385788,48.1697845459],"type":"Point"}
}