{
  "type": "Feature",
  "properties": {
    "iso:country":"AT",
    "sg:address":"Reichsstrasse 147",
    "sg:city":"Feldkirch",
    "sg:classifiers":[
        {
            "category":"Travel",
            "subcategory":"Hotels & Motels",
            "type":"Entertainment"
        }
    ],
    "sg:phone":"+43 5522 70295",
    "sg:postcode":"6800",
    "sg:province":"Vorarlberg",
    "sg:tags":[
        "equipment",
        "hotels",
        "restaurant"
    ],
    "sg:website":"aufundzu.com",
    "wof:name":"HENSS Innenausbau Ges.m.b.H.",
    "wof:placetype":"venue"
},
  "geometry": {"coordinates":[9.607424736,47.2449188232],"type":"Point"}
}