{
  "type": "Feature",
  "properties": {
    "iso:country":"AT",
    "sg:address":"Nr 166",
    "sg:city":"Kleinreifling",
    "sg:classifiers":[
        {
            "category":"Restaurant",
            "type":"Food & Drink"
        }
    ],
    "sg:phone":"+43 7357 216",
    "sg:postcode":"4464",
    "sg:province":"Ober\u00f6sterreich",
    "wof:name":"Hrubes Helmut",
    "wof:placetype":"venue"
},
  "geometry": {"coordinates":[14.6398630142,47.8204917908],"type":"Point"}
}