{
  "type": "Feature",
  "properties": {
    "iso:country":"AT",
    "sg:address":"Pfarrg 14",
    "sg:city":"Wels",
    "sg:orig_category":"Bierlokale-Pubs",
    "sg:phone":"+43 7242 46001",
    "sg:postcode":"4600",
    "sg:province":"Ober\u00f6sterreich",
    "wof:name":"Ovilaba-Pub",
    "wof:placetype":"venue"
},
  "geometry": {"coordinates":[14.0259714127,48.159362793],"type":"Point"}
}