{
  "type": "Feature",
  "properties": {
    "addr:full":"Schleppepl 5 Klagenfurt K\u00e4rnten 9020",
    "addr:housenumber":"5",
    "addr:postcode":"9020",
    "addr:street":"Schleppepl;Kaernten",
    "iso:country":"AT",
    "sg:address":"Schleppepl 5",
    "sg:city":"Klagenfurt",
    "sg:orig_category":"Dentalwaren",
    "sg:phone":"+43 4346 3542040",
    "sg:postcode":"9020",
    "sg:province":"K\u00e4rnten",
    "wof:name":"Austrodent HandelsgesmbH",
    "wof:placetype":"venue"
},
  "geometry": {"coordinates":[14.2880325317,46.6406173706],"type":"Point"}
}