{
  "type": "Feature",
  "properties": {
    "iso:country":"AT",
    "sg:address":"Mariahilfer Str 142",
    "sg:city":"Wien",
    "sg:classifiers":[
        {
            "category":"Shopping",
            "subcategory":"Thrift Store",
            "type":"Retail Goods"
        }
    ],
    "sg:phone":"+43 1 8959968",
    "sg:postcode":"1150",
    "sg:province":"Wien",
    "sg:tags":[
        "second-hand-shops"
    ],
    "wof:name":"Humana - Verein z F\u00f6rderung notleidender Menschen i d Dritten Welt",
    "wof:placetype":"venue"
},
  "geometry": {"coordinates":[16.3356761932,48.194683075],"type":"Point"}
}