{
  "type": "Feature",
  "properties": {
    "iso:country":"AT",
    "sg:address":"Eugen-Getzner-Str 7",
    "sg:city":"Nenzing",
    "sg:orig_category":"Bilderrahmen",
    "sg:phone":"+43 4355 2562115",
    "sg:postcode":"6710",
    "sg:province":"Vorarlberg",
    "wof:name":"Bild & Rahmen Kropshofer - Fabriksverkauf",
    "wof:placetype":"venue"
},
  "geometry": {"coordinates":[9.7071847916,47.1848297119],"type":"Point"}
}