{
  "type": "Feature",
  "properties": {
    "iso:country":"AT",
    "sg:address":"Hasnerstr 85",
    "sg:city":"Wien",
    "sg:orig_category":"Lebensmittel / Einzelhandel",
    "sg:phone":"+43 1 9291651",
    "sg:postcode":"1160",
    "sg:province":"Wien",
    "wof:name":"Billa AG",
    "wof:placetype":"venue"
},
  "geometry": {"coordinates":[16.3220901489,48.2095985413],"type":"Point"}
}