{
  "type": "Feature",
  "properties": {
    "addr:full":"B\u00e4ckerstr 5 Wals Salzburg 5071",
    "addr:housenumber":"5",
    "addr:postcode":"5071",
    "addr:street":"Baeckerstr;Salzburg",
    "iso:country":"AT",
    "sg:address":"B\u00e4ckerstr 5",
    "sg:city":"Wals",
    "sg:orig_category":"Hafnereien",
    "sg:phone":"+43 662 824200",
    "sg:postcode":"5071",
    "sg:province":"Salzburg",
    "wof:name":"Zoll Wolfgang",
    "wof:placetype":"venue"
},
  "geometry": {"coordinates":[13.0023546219,47.7748146057],"type":"Point"}
}