{
  "type": "Feature",
  "properties": {
    "addr:full":"Industriestr 14 St. Johann im Pongau Salzburg 5600",
    "addr:housenumber":"14",
    "addr:postcode":"5600",
    "addr:street":"Industriestr;Salzburg",
    "iso:country":"AT",
    "sg:address":"Industriestr 14",
    "sg:city":"St. Johann im Pongau",
    "sg:orig_category":"Elektroinstallationsunternehmen",
    "sg:phone":"+43 6412 67870",
    "sg:postcode":"5600",
    "sg:province":"Salzburg",
    "sg:website":"eltkauf.de/elektro-huber",
    "wof:name":"Elektro Huber",
    "wof:placetype":"venue"
},
  "geometry": {"coordinates":[13.1978902817,47.3525466919],"type":"Point"}
}