{
  "type": "Feature",
  "properties": {
    "iso:country":"AT",
    "sg:address":"Nr 175",
    "sg:city":"St. Anton am Arlberg",
    "sg:classifiers":[
        {
            "category":"Restaurant",
            "type":"Food & Drink"
        }
    ],
    "sg:phone":"+43 5446 23020",
    "sg:postcode":"6580",
    "sg:province":"Tirol",
    "wof:name":"Fonduerestaurant Montjola",
    "wof:placetype":"venue"
},
  "geometry": {"coordinates":[10.2640428543,47.127532959],"type":"Point"}
}