{
  "type": "Feature",
  "properties": {
    "iso:country":"AT",
    "sg:address":"Au 11",
    "sg:city":"Vomp",
    "sg:orig_category":"Maschinenbau",
    "sg:phone":"+43 5242 71348",
    "sg:postcode":"6134",
    "sg:province":"Tirol",
    "wof:name":"Troger Gerald Ing",
    "wof:placetype":"venue"
},
  "geometry": {"coordinates":[11.683139801,47.3420982361],"type":"Point"}
}