{
  "type": "Feature",
  "properties": {
    "addr:full":"Grub 1 Wallern an der Trattnach Ober\u00f6sterreich 4702",
    "addr:housenumber":"1",
    "addr:postcode":"4702",
    "addr:street":"Grub",
    "iso:country":"AT",
    "sg:address":"Grub 1",
    "sg:city":"Wallern an der Trattnach",
    "sg:orig_category":"Appartements / Ferienwohnungen",
    "sg:phone":"+43 4372 4943265",
    "sg:postcode":"4702",
    "sg:province":"Ober\u00f6sterreich",
    "wof:name":"Reingruberhof",
    "wof:placetype":"venue"
},
  "geometry": {"coordinates":[13.9527015686,48.2366523743],"type":"Point"}
}