{
  "type": "Feature",
  "properties": {
    "iso:country":"AT",
    "sg:address":"M\u00fcnichau 544",
    "sg:city":"Kitzb\u00fchel",
    "sg:orig_category":"Transportunternehmen",
    "sg:phone":"+43 4353 56664040",
    "sg:postcode":"6370",
    "sg:province":"Tirol",
    "wof:name":"Reither Transport u Logistik GmbH",
    "wof:placetype":"venue"
},
  "geometry": {"coordinates":[106.0698394775,30.7620105743],"type":"Point"}
}