{
  "type": "Feature",
  "properties": {
    "addr:full":"Nr 66 Mariazell Steiermark 8630",
    "addr:postcode":"8630",
    "addr:street":"Nr 66",
    "iso:country":"AT",
    "sg:address":"Nr 66",
    "sg:city":"Mariazell",
    "sg:orig_category":"Lebensmittel / Einzelhandel",
    "sg:phone":"+43 3333 2950",
    "sg:postcode":"8630",
    "sg:province":"Steiermark",
    "wof:name":"Billa AG",
    "wof:placetype":"venue"
},
  "geometry": {"coordinates":[15.3180360794,47.7734832764],"type":"Point"}
}