{
  "type": "Feature",
  "properties": {
    "addr:full":"Platz 375 Bezau Vorarlberg 6870",
    "addr:housenumber":"375",
    "addr:postcode":"6870",
    "addr:street":"Platz",
    "iso:country":"AT",
    "sg:address":"Platz 375",
    "sg:city":"Bezau",
    "sg:orig_category":"Energieberatung U -Untersuchung",
    "sg:phone":"+43 5514 221316",
    "sg:postcode":"6870",
    "sg:province":"Vorarlberg",
    "wof:name":"Energieberatung Hinterer Bregenzerwald",
    "wof:placetype":"venue"
},
  "geometry": {"coordinates":[9.9022083282,47.3848991394],"type":"Point"}
}