{
  "type": "Feature",
  "properties": {
    "addr:full":"Redtenbacherg 7 Wien Wien 1160",
    "addr:housenumber":"7",
    "addr:postcode":"1160",
    "addr:street":"Redtenbacherg",
    "iso:country":"AT",
    "sg:address":"Redtenbacherg 7",
    "sg:city":"Wien",
    "sg:orig_category":"Autobeschriftungen",
    "sg:phone":"+43 1 4853965",
    "sg:postcode":"1160",
    "sg:province":"Wien",
    "wof:name":"Jernits Herbert",
    "wof:placetype":"venue"
},
  "geometry": {"coordinates":[16.3147182465,48.2144699097],"type":"Point"}
}