{
  "type": "Feature",
  "properties": {
    "iso:country":"AT",
    "sg:address":"Nr 54",
    "sg:city":"Gamlitz",
    "sg:orig_category":"Pensionen / Privatzimmer",
    "sg:phone":"+43 3453 42120",
    "sg:postcode":"8462",
    "sg:province":"Steiermark",
    "wof:name":"Brolli Helga",
    "wof:placetype":"venue"
},
  "geometry": {"coordinates":[15.5537004471,46.7205543518],"type":"Point"}
}