{
  "type": "Feature",
  "properties": {
    "addr:full":"Dambachstrasse 83 Garsten Ober\u00f6sterreich 4451",
    "addr:housenumber":"83",
    "addr:postcode":"4451",
    "addr:street":"Dambachstrasse",
    "iso:country":"AT",
    "sg:address":"Dambachstrasse 83",
    "sg:city":"Garsten",
    "sg:classifiers":[
        {
            "category":"Manufacturing",
            "subcategory":"Wood Products",
            "type":"Manufacturing & Wholesale Goods"
        }
    ],
    "sg:phone":"+43 7252 541970",
    "sg:postcode":"4451",
    "sg:province":"Ober\u00f6sterreich",
    "sg:tags":[
        "firewood"
    ],
    "wof:name":"Karl Sallinger",
    "wof:placetype":"venue"
},
  "geometry": {"coordinates":[14.4488067627,47.9824562073],"type":"Point"}
}