{
  "type": "Feature",
  "properties": {
    "addr:full":"Weidach 49 Vorchdorf Ober\u00f6sterreich 4655",
    "addr:housenumber":"49",
    "addr:postcode":"4655",
    "addr:street":"Weidach",
    "iso:country":"AT",
    "sg:address":"Weidach 49",
    "sg:city":"Vorchdorf",
    "sg:orig_category":"Freizeitangebote U -Einrichtungen",
    "sg:phone":"+43 76147111",
    "sg:postcode":"4655",
    "sg:province":"Ober\u00f6sterreich",
    "wof:name":"Farmaland GmbH",
    "wof:placetype":"venue"
},
  "geometry": {"coordinates":[13.9136476517,47.9936180115],"type":"Point"}
}