{
  "type": "Feature",
  "properties": {
    "addr:full":"Gosauzwang 7 Steeg Ober\u00f6sterreich 4823",
    "addr:housenumber":"7",
    "addr:postcode":"4823",
    "addr:street":"Gosauzwang",
    "iso:country":"AT",
    "sg:address":"Gosauzwang 7",
    "sg:city":"Steeg",
    "sg:orig_category":"Bauleitung U -Betreuung",
    "sg:phone":"+43 4369 910286033",
    "sg:postcode":"4823",
    "sg:province":"Ober\u00f6sterreich",
    "wof:name":"Steiner Barbara",
    "wof:placetype":"venue"
},
  "geometry": {"coordinates":[13.6535558701,47.5907554626],"type":"Point"}
}