{
  "type": "Feature",
  "properties": {
    "addr:full":"Runastr 90 Feldkirch Vorarlberg 6800",
    "addr:housenumber":"90",
    "addr:postcode":"6800",
    "addr:street":"Runastr",
    "iso:country":"AT",
    "sg:address":"Runastr 90",
    "sg:city":"Feldkirch",
    "sg:orig_category":"Bauunternehmen",
    "sg:phone":"+43 4355 2270195",
    "sg:postcode":"6800",
    "sg:province":"Vorarlberg",
    "wof:name":"STRABAG AG - Direktion AF",
    "wof:placetype":"venue"
},
  "geometry": {"coordinates":[9.6028470993,47.2669830322],"type":"Point"}
}