{
  "type": "Feature",
  "properties": {
    "addr:full":"Gartengasse 2 Wiener Neustadt Nieder\u00f6sterreich 2700",
    "addr:housenumber":"2",
    "addr:postcode":"2700",
    "addr:street":"Gartengasse",
    "iso:country":"AT",
    "sg:address":"Gartengasse 2",
    "sg:city":"Wiener Neustadt",
    "sg:classifiers":[
        {
            "category":"Manufacturing",
            "subcategory":"Wood Products",
            "type":"Manufacturing & Wholesale Goods"
        }
    ],
    "sg:phone":"+43 2622 20654",
    "sg:postcode":"2700",
    "sg:province":"Nieder\u00f6sterreich",
    "sg:tags":[
        "gate",
        "made",
        "door"
    ],
    "sg:website":"fensterstudio.at",
    "wof:name":"Fensterstudio GmbH",
    "wof:placetype":"venue"
},
  "geometry": {"coordinates":[16.2582702637,47.813709259],"type":"Point"}
}