{
  "type": "Feature",
  "properties": {
    "addr:full":"Kainachtalstr 7 Wildon Steiermark 8410",
    "addr:housenumber":"7",
    "addr:postcode":"8410",
    "addr:street":"Kainachtalstr;Steiermark",
    "iso:country":"AT",
    "sg:address":"Kainachtalstr 7",
    "sg:city":"Wildon",
    "sg:orig_category":"Lebensmittel / Einzelhandel",
    "sg:phone":"+43 3182 4070",
    "sg:postcode":"8410",
    "sg:province":"Steiermark",
    "wof:name":"Unimarkt HandelsgesmbH & Co KG",
    "wof:placetype":"venue"
},
  "geometry": {"coordinates":[15.5004863739,46.8868942261],"type":"Point"}
}