{
  "type": "Feature",
  "properties": {
    "iso:country":"AT",
    "sg:city":"Zell am Moos",
    "sg:orig_category":"Freizeit, Musik",
    "sg:postcode":"4893",
    "sg:province":"Ober\u00f6sterreich",
    "sg:website":"http://members.magnet.at/astroexklusiv/index.html",
    "wof:name":"ASTROLOGIE EXKLUSIV",
    "wof:placetype":"venue"
},
  "geometry": {"coordinates":[13.3187847137,47.9021682739],"type":"Point"}
}