{
  "type": "Feature",
  "properties": {
    "iso:country":"AT",
    "sg:address":"Aufeldstr 17-23",
    "sg:city":"Klosterneuburg",
    "sg:orig_category":"Holdinggesellschaften",
    "sg:phone":"+43 2243 4100",
    "sg:postcode":"3400",
    "sg:province":"Nieder\u00f6sterreich",
    "wof:name":"Sch\u00f6mer Fritz GesmbH",
    "wof:placetype":"venue"
},
  "geometry": {"coordinates":[16.3352031708,48.2977218628],"type":"Point"}
}