{
  "type": "Feature",
  "properties": {
    "addr:full":"Vorberg 482 Ramsau am Dachstein Steiermark 8972",
    "addr:housenumber":"482",
    "addr:postcode":"8972",
    "addr:street":"Vorberg",
    "iso:country":"AT",
    "sg:address":"Vorberg 482",
    "sg:city":"Ramsau am Dachstein",
    "sg:orig_category":"Appartements / Ferienwohnungen",
    "sg:phone":"+43 4336 87826340",
    "sg:postcode":"8972",
    "sg:province":"Steiermark",
    "wof:name":"Landhaus Bellevue - Pitzer Maria u J\u00fcrgen",
    "wof:placetype":"venue"
},
  "geometry": {"coordinates":[13.6386823654,47.4179039001],"type":"Point"}
}