{
  "type": "Feature",
  "properties": {
    "addr:full":"St.-Peter-Str 5 Elsbethen-Glasenbach Salzburg 5061",
    "addr:housenumber":"5",
    "addr:postcode":"5061",
    "addr:street":"St.-Peter-Str;Salzburg",
    "iso:country":"AT",
    "sg:address":"St.-Peter-Str 5",
    "sg:city":"Elsbethen-Glasenbach",
    "sg:orig_category":"Tanzschulen",
    "sg:phone":"+43 4366 2851241",
    "sg:postcode":"5061",
    "sg:province":"Salzburg",
    "wof:name":"Tanzstudio Mirabell Astrid u Haro Decho",
    "wof:placetype":"venue"
},
  "geometry": {"coordinates":[13.0791311264,47.7613296509],"type":"Point"}
}