{
  "type": "Feature",
  "properties": {
    "iso:country":"AT",
    "sg:address":"Sportplatzweg 3",
    "sg:city":"Maishofen",
    "sg:orig_category":"Tischlereien",
    "sg:phone":"+43 6542 80111",
    "sg:postcode":"5751",
    "sg:province":"Salzburg",
    "wof:name":"Rattensberger Josef",
    "wof:placetype":"venue"
},
  "geometry": {"coordinates":[12.8106498718,47.3605613708],"type":"Point"}
}