{
  "type": "Feature",
  "properties": {
    "iso:country":"AT",
    "sg:address":"Gewerbezone 8B",
    "sg:city":"Ebenfurth",
    "sg:orig_category":"Zimmereien",
    "sg:phone":"+43 4326 2454023",
    "sg:postcode":"2490",
    "sg:province":"Nieder\u00f6sterreich",
    "wof:name":"ECKENFELLNER PETER GmbH",
    "wof:placetype":"venue"
},
  "geometry": {"coordinates":[16.360616684,47.8798561096],"type":"Point"}
}