{
  "type": "Feature",
  "properties": {
    "iso:country":"AT",
    "sg:address":"Halleiner Landesstr 7",
    "sg:city":"Hallein",
    "sg:orig_category":"Physiotherapie",
    "sg:phone":"+43 664 5226545",
    "sg:postcode":"5400",
    "sg:province":"Salzburg",
    "wof:name":"Am Almbach Physiotherapie",
    "wof:placetype":"venue"
},
  "geometry": {"coordinates":[13.0996809006,47.6897926331],"type":"Point"}
}