{
  "type": "Feature",
  "properties": {
    "addr:full":"Sportg 10 M\u00fcrzhofen Steiermark 8644",
    "addr:housenumber":"10",
    "addr:postcode":"8644",
    "addr:street":"Sportg",
    "iso:country":"AT",
    "sg:address":"Sportg 10",
    "sg:city":"M\u00fcrzhofen",
    "sg:orig_category":"Spirituosen / Erzeugung U Gro\u00c3\u0178handel",
    "sg:phone":"+43 4338 642431",
    "sg:postcode":"8644",
    "sg:province":"Steiermark",
    "wof:name":"Kristandl Heribert",
    "wof:placetype":"venue"
},
  "geometry": {"coordinates":[15.3961839676,47.4819374084],"type":"Point"}
}