{
  "type": "Feature",
  "properties": {
    "iso:country":"AT",
    "sg:address":"Klopstockg 47",
    "sg:city":"Wien",
    "sg:orig_category":"Galvanisieranstalten",
    "sg:phone":"+43 1 4863608",
    "sg:postcode":"1170",
    "sg:province":"Wien",
    "wof:name":"Reiss Edith GesmbH",
    "wof:placetype":"venue"
},
  "geometry": {"coordinates":[16.3235206604,48.2194213867],"type":"Point"}
}