{
  "type": "Feature",
  "properties": {
    "addr:full":"Au 61 Abtenau Salzburg 5441",
    "addr:housenumber":"61",
    "addr:postcode":"5441",
    "addr:street":"Au;Salzburg",
    "iso:country":"AT",
    "sg:address":"Au 61",
    "sg:city":"Abtenau",
    "sg:orig_category":"Transportunternehmen",
    "sg:phone":"+43 6243 23210",
    "sg:postcode":"5441",
    "sg:province":"Salzburg",
    "wof:name":"Abtenau - Schnitzhofer",
    "wof:placetype":"venue"
},
  "geometry": {"coordinates":[13.3500528336,47.5612564087],"type":"Point"}
}