{
  "type": "Feature",
  "properties": {
    "iso:country":"AT",
    "sg:address":"Hauptpl 3",
    "sg:city":"Mistelbach",
    "sg:orig_category":"Psychotherapie",
    "sg:phone":"+43 2572 4843",
    "sg:postcode":"2130",
    "sg:province":"Nieder\u00f6sterreich",
    "wof:name":"Mehling Reinhold Mag",
    "wof:placetype":"venue"
},
  "geometry": {"coordinates":[16.5720901489,48.5704421997],"type":"Point"}
}