{
  "type": "Feature",
  "properties": {
    "addr:full":"Stadtpl 56 Laa an der Thaya Nieder\u00f6sterreich 2136",
    "addr:housenumber":"56",
    "addr:postcode":"2136",
    "addr:street":"Stadtpl",
    "iso:country":"AT",
    "sg:address":"Stadtpl 56",
    "sg:city":"Laa an der Thaya",
    "sg:orig_category":"Banken U Sparkassen",
    "sg:phone":"+43 4325 2223750",
    "sg:postcode":"2136",
    "sg:province":"Nieder\u00f6sterreich",
    "wof:name":"Bankomat der Raiffeisen-Bezirksbank Laa an der Thaya regGenmbH",
    "wof:placetype":"venue"
},
  "geometry": {"coordinates":[16.3848896027,48.7221717834],"type":"Point"}
}