{
  "type": "Feature",
  "properties": {
    "addr:full":"Murweg 1 Gro\u00dflobming Steiermark 8734",
    "addr:housenumber":"1",
    "addr:postcode":"8734",
    "addr:street":"Murweg",
    "iso:country":"AT",
    "sg:address":"Murweg 1",
    "sg:city":"Gro\u00dflobming",
    "sg:orig_category":"Non-Classified Establishments",
    "sg:phone":"+43 3512 82957",
    "sg:postcode":"8734",
    "sg:province":"Steiermark",
    "wof:name":"Pfarramt",
    "wof:placetype":"venue"
},
  "geometry": {"coordinates":[14.8084917068,47.1866722107],"type":"Point"}
}