{
  "type": "Feature",
  "properties": {
    "iso:country":"AT",
    "sg:address":"Grazer Str 35",
    "sg:city":"Fohnsdorf",
    "sg:orig_category":"Arbeitsvermittlung",
    "sg:phone":"+43 3573 57910",
    "sg:postcode":"8753",
    "sg:province":"Steiermark",
    "wof:name":"S\u00d6BSA - Sozial-, \u00d6ko- und Besch\u00e4ftigungsservice GmbH",
    "wof:placetype":"venue"
},
  "geometry": {"coordinates":[14.6920757294,47.2032928467],"type":"Point"}
}