{
  "type": "Feature",
  "properties": {
    "addr:full":"Ing.-Julius-Raab-Str Bad Fischau Nieder\u00f6sterreich 2721",
    "addr:postcode":"2721",
    "iso:country":"AT",
    "sg:address":"Ing.-Julius-Raab-Str",
    "sg:city":"Bad Fischau",
    "sg:classifiers":[
        {
            "category":"Utilities",
            "subcategory":"Recycling",
            "type":"Services"
        }
    ],
    "sg:phone":"+43 2622 42016",
    "sg:postcode":"2721",
    "sg:province":"Nieder\u00f6sterreich",
    "wof:name":"Asphalt & Beton GmbH Nfg OHG",
    "wof:placetype":"venue"
},
  "geometry": {"coordinates":[16.1869525909,47.8342933655],"type":"Point"}
}