{
  "type": "Feature",
  "properties": {
    "iso:country":"AT",
    "sg:address":"Andreas-Hofer-Str. 17 ",
    "sg:city":"Hall in Tirol",
    "sg:classifiers":[
        {
            "category":"Shopping",
            "subcategory":"Computers & Home Electronics",
            "type":"Retail Goods"
        }
    ],
    "sg:phone":"+43 4352 2356095",
    "sg:postcode":"6060",
    "sg:province":"Tirol",
    "sg:tags":[
        "electronic",
        "electrical",
        "equipment"
    ],
    "wof:name":"KATTNIG LICHT U. GLAS GES.MBH",
    "wof:placetype":"venue"
},
  "geometry": {"coordinates":[11.5065698624,47.2818107605],"type":"Point"}
}