{
  "type": "Feature",
  "properties": {
    "addr:full":"Linden 26 St. Georgen am Walde Ober\u00f6sterreich 4372",
    "addr:housenumber":"26",
    "addr:postcode":"4372",
    "addr:street":"Linden",
    "iso:country":"AT",
    "sg:address":"Linden 26",
    "sg:city":"St. Georgen am Walde",
    "sg:orig_category":"CarpenterS Work Supraregional",
    "sg:phone":"+43 7954 2214",
    "sg:postcode":"4372",
    "sg:province":"Ober\u00f6sterreich",
    "wof:name":"Wolfgang Freyenschlag",
    "wof:placetype":"venue"
},
  "geometry": {"coordinates":[14.9110250473,48.367931366],"type":"Point"}
}