{
  "type": "Feature",
  "properties": {
    "addr:full":"Breitenfurter Str 343 Wien Wien 1230",
    "addr:housenumber":"343",
    "addr:postcode":"1230",
    "addr:street":"Str",
    "iso:country":"AT",
    "sg:address":"Breitenfurter Str 343",
    "sg:city":"Wien",
    "sg:orig_category":"Restaurants: Chinesisch",
    "sg:phone":"+43 1 8690440",
    "sg:postcode":"1230",
    "sg:province":"Wien",
    "wof:name":"China-Restaurant Kao-Ming",
    "wof:placetype":"venue"
},
  "geometry": {"coordinates":[16.2917823792,48.1413726807],"type":"Point"}
}