{
  "type": "Feature",
  "properties": {
    "addr:full":"Liechtensteinstr 56/4 Wien Wien 1090",
    "addr:housenumber":"56 / 4",
    "addr:postcode":"1090",
    "addr:street":"Liechtensteinstr",
    "iso:country":"AT",
    "sg:address":"Liechtensteinstr 56/4",
    "sg:city":"Wien",
    "sg:orig_category":"Elektroinstallationsunternehmen",
    "sg:phone":"+43 664 4442628",
    "sg:postcode":"1090",
    "sg:province":"Wien",
    "wof:name":"Elektro Monte - St\u00f6rungsdienst 0-24 Uhr",
    "wof:placetype":"venue"
},
  "geometry": {"coordinates":[16.3570823669,48.2258529663],"type":"Point"}
}