{
  "type": "Feature",
  "properties": {
    "addr:full":"Weyrer Str 23 Waidhofen an der Ybbs Nieder\u00f6sterreich 3340",
    "addr:postcode":"3340",
    "addr:street":"Str 23",
    "iso:country":"AT",
    "sg:address":"Weyrer Str 23",
    "sg:city":"Waidhofen an der Ybbs",
    "sg:orig_category":"Restaurants: Chinesisch",
    "sg:phone":"+43 4374 4254524",
    "sg:postcode":"3340",
    "sg:province":"Nieder\u00f6sterreich",
    "wof:name":"China-Restaurant Chinatown",
    "wof:placetype":"venue"
},
  "geometry": {"coordinates":[14.7689409256,47.9567565918],"type":"Point"}
}