{
  "type": "Feature",
  "properties": {
    "addr:full":"Triester Str 285-287 Wien Wien 1230",
    "addr:housenumber":"285-287",
    "addr:postcode":"1230",
    "addr:street":"Str",
    "iso:country":"AT",
    "sg:address":"Triester Str 285-287",
    "sg:city":"Wien",
    "sg:orig_category":"Tankstellen",
    "sg:phone":"+43 1 6673109",
    "sg:postcode":"1230",
    "sg:province":"Wien",
    "wof:name":"Esso Austria GmbH",
    "wof:placetype":"venue"
},
  "geometry": {"coordinates":[16.3292751312,48.1412391663],"type":"Point"}
}