{
  "type": "Feature",
  "properties": {
    "addr:full":"Nr 6 St. Johann Steiermark 8222",
    "addr:housenumber":"6",
    "addr:postcode":"8222",
    "addr:street":"Nr",
    "iso:country":"AT",
    "sg:address":"Nr 6",
    "sg:city":"St. Johann",
    "sg:orig_category":"Pensionen / Privatzimmer",
    "sg:phone":"+43 4331 138385",
    "sg:postcode":"8222",
    "sg:province":"Steiermark",
    "wof:name":"Terler Anna - Almbauer Zimmervermietung",
    "wof:placetype":"venue"
},
  "geometry": {"coordinates":[15.786567688,47.2127380371],"type":"Point"}
}