{
  "type": "Feature",
  "properties": {
    "addr:full":"Nr 4 Freiland Nieder\u00f6sterreich 3183",
    "addr:postcode":"3183",
    "addr:street":"Nr;Freiland",
    "iso:country":"AT",
    "sg:address":"Nr 4",
    "sg:city":"Freiland",
    "sg:orig_category":"Non-Classified Establishments",
    "sg:phone":"+43 2762 524120",
    "sg:postcode":"3183",
    "sg:province":"Nieder\u00f6sterreich",
    "wof:name":"Stra\u00dfenmeisterei Lilienfeld",
    "wof:placetype":"venue"
},
  "geometry": {"coordinates":[15.5521612167,47.9612503052],"type":"Point"}
}