{
  "type": "Feature",
  "properties": {
    "addr:full":"Hauptstr 41 Kronstorf Ober\u00f6sterreich 4484",
    "addr:housenumber":"41",
    "addr:postcode":"4484",
    "addr:street":"Hauptstr",
    "iso:country":"AT",
    "sg:address":"Hauptstr 41",
    "sg:city":"Kronstorf",
    "sg:orig_category":"Banken U Sparkassen",
    "sg:phone":"+43 4372 2583320",
    "sg:postcode":"4484",
    "sg:province":"Ober\u00f6sterreich",
    "wof:name":"Raiffeisenbank Enns regGenmbH",
    "wof:placetype":"venue"
},
  "geometry": {"coordinates":[14.4645214081,48.1405792236],"type":"Point"}
}