{
  "type": "Feature",
  "properties": {
    "addr:full":"Kleine Zeile 56 Wulkaprodersdorf Burgenland 7041",
    "addr:housenumber":"56",
    "addr:postcode":"7041",
    "addr:street":"Kleine Zeile",
    "iso:country":"AT",
    "sg:address":"Kleine Zeile 56",
    "sg:city":"Wulkaprodersdorf",
    "sg:orig_category":"Alteisen U Altmetalle",
    "sg:phone":"+43 2687 62874",
    "sg:postcode":"7041",
    "sg:province":"Burgenland",
    "wof:name":"Puff Andreas",
    "wof:placetype":"venue"
},
  "geometry": {"coordinates":[16.4698925018,47.7727890015],"type":"Point"}
}