{
  "type": "Feature",
  "properties": {
    "addr:full":"Dechant-Thaller-Str 37 Leibnitz Steiermark 8430",
    "addr:housenumber":"37",
    "addr:postcode":"8430",
    "addr:street":"Dechant-Thaller-Str;Steiermark",
    "iso:country":"AT",
    "sg:address":"Dechant-Thaller-Str 37",
    "sg:city":"Leibnitz",
    "sg:orig_category":"Badezimmer U Badezimmereinrichtungen",
    "sg:phone":"+43 4334 5270725",
    "sg:postcode":"8430",
    "sg:province":"Steiermark",
    "wof:name":"Wilux Austria",
    "wof:placetype":"venue"
},
  "geometry": {"coordinates":[15.5401163101,46.7882728577],"type":"Point"}
}