{
  "type": "Feature",
  "properties": {
    "iso:country":"AT",
    "sg:address":"Kreiennest 5",
    "sg:city":"Schwarzach",
    "sg:orig_category":"Berufsbekleidung / Erzeugung U Gro\u00c3\u0178handel",
    "sg:phone":"+43 5572 58140",
    "sg:postcode":"6858",
    "sg:province":"Vorarlberg",
    "wof:name":"Fr\u00f6wis Josef",
    "wof:placetype":"venue"
},
  "geometry": {"coordinates":[9.7551937103,47.4516334534],"type":"Point"}
}