{
  "type": "Feature",
  "properties": {
    "iso:country":"AT",
    "sg:address":"Gleisdorfer G 17",
    "sg:city":"Graz",
    "sg:classifiers":[
        {
            "category":"Professional",
            "type":"Services"
        }
    ],
    "sg:phone":"+43 316 8110510",
    "sg:postcode":"8010",
    "sg:province":"Steiermark",
    "sg:tags":[
        "leasing"
    ],
    "wof:name":"Leasing-West GesmbH & Co KG",
    "wof:placetype":"venue"
},
  "geometry": {"coordinates":[15.4450359344,47.068145752],"type":"Point"}
}