{
  "type": "Feature",
  "properties": {
    "addr:full":"Nodbachweg 4 St. Margarethen im Burgenland Burgenland 7062",
    "addr:housenumber":"4",
    "addr:postcode":"7062",
    "addr:street":"Nodbachweg",
    "iso:country":"AT",
    "sg:address":"Nodbachweg 4",
    "sg:city":"St. Margarethen im Burgenland",
    "sg:orig_category":"Zimmereien",
    "sg:phone":"+43 4326 802731",
    "sg:postcode":"7062",
    "sg:province":"Burgenland",
    "wof:name":"Miehl Josef",
    "wof:placetype":"venue"
},
  "geometry": {"coordinates":[16.6043243408,47.8131637573],"type":"Point"}
}