{
  "type": "Feature",
  "properties": {
    "addr:full":"Dr.-Karl-Renner-Str 47 Ternitz Nieder\u00f6sterreich 2630",
    "addr:housenumber":"47",
    "addr:postcode":"2630",
    "addr:street":"Dr.-Karl-Renner-Str",
    "iso:country":"AT",
    "sg:address":"Dr.-Karl-Renner-Str 47",
    "sg:city":"Ternitz",
    "sg:orig_category":"Tabaktrafiken",
    "sg:phone":"+43 2630 34016",
    "sg:postcode":"2630",
    "sg:province":"Nieder\u00f6sterreich",
    "wof:name":"Simon Wilma",
    "wof:placetype":"venue"
},
  "geometry": {"coordinates":[16.007932663,47.7047119141],"type":"Point"}
}