{
  "type": "Feature",
  "properties": {
    "addr:full":"Wasserbrunnenweg 1 Bad Kleinkirchheim K\u00e4rnten 9546",
    "addr:housenumber":"1",
    "addr:postcode":"9546",
    "addr:street":"Wasserbrunnenweg",
    "iso:country":"AT",
    "sg:address":"Wasserbrunnenweg 1",
    "sg:city":"Bad Kleinkirchheim",
    "sg:orig_category":"Appartements / Ferienwohnungen",
    "sg:phone":"+43 4240 816211",
    "sg:postcode":"9546",
    "sg:province":"K\u00e4rnten",
    "wof:name":"Haus Alpenruhe",
    "wof:placetype":"venue"
},
  "geometry": {"coordinates":[13.7860431671,46.8130645752],"type":"Point"}
}