{
  "type": "Feature",
  "properties": {
    "iso:country":"AT",
    "sg:address":"Rembrandtweg 7",
    "sg:city":"Hohenems",
    "sg:orig_category":"Rauchfangkehrer",
    "sg:phone":"+43 4355 7678448",
    "sg:postcode":"6845",
    "sg:province":"Vorarlberg",
    "wof:name":"Loretz Ludwig",
    "wof:placetype":"venue"
},
  "geometry": {"coordinates":[9.6951227188,47.3722076416],"type":"Point"}
}