{
  "type": "Feature",
  "properties": {
    "iso:country":"AT",
    "sg:address":"Linzer Str 40",
    "sg:city":"Purkersdorf",
    "sg:orig_category":"Versicherungsunternehmen",
    "sg:phone":"+43 2231 64195",
    "sg:postcode":"3002",
    "sg:province":"Nieder\u00f6sterreich",
    "wof:name":"Generali Versicherung AG",
    "wof:placetype":"venue"
},
  "geometry": {"coordinates":[16.171995163,48.2131919861],"type":"Point"}
}