{
  "type": "Feature",
  "properties": {
    "addr:full":"Dreherstrasse 23a Wien Wien 1110",
    "addr:housenumber":"23a",
    "addr:postcode":"1110",
    "addr:street":"Dreherstrasse",
    "iso:country":"AT",
    "sg:address":"Dreherstrasse 23a",
    "sg:city":"Wien",
    "sg:classifiers":[
        {
            "category":"Utilities",
            "subcategory":"Telephone",
            "type":"Services"
        }
    ],
    "sg:phone":"+43 1 7693069",
    "sg:postcode":"1110",
    "sg:province":"Wien",
    "sg:tags":[
        "platform",
        "aerial"
    ],
    "sg:website":"voelkl.at",
    "wof:name":"Ing. A. V\u00f6lkl Gesellschaft m.b.H.",
    "wof:placetype":"venue"
},
  "geometry": {"coordinates":[16.4725532532,48.1552047729],"type":"Point"}
}