{
  "type": "Feature",
  "properties": {
    "addr:full":"Marktstr 84 Rauris Salzburg 5661",
    "addr:housenumber":"84",
    "addr:postcode":"5661",
    "addr:street":"Marktstr;Salzburg",
    "iso:country":"AT",
    "sg:address":"Marktstr 84",
    "sg:city":"Rauris",
    "sg:orig_category":"Pensionen / Privatzimmer",
    "sg:phone":"+43 6544 65500",
    "sg:postcode":"5661",
    "sg:province":"Salzburg",
    "wof:name":"Haus Weinschreiber",
    "wof:placetype":"venue"
},
  "geometry": {"coordinates":[12.9933862686,47.2243919373],"type":"Point"}
}