{
  "type": "Feature",
  "properties": {
    "addr:full":"Wiener Str 113 Gars am Kamp Nieder\u00f6sterreich 3571",
    "addr:housenumber":"113",
    "addr:postcode":"3571",
    "iso:country":"AT",
    "sg:address":"Wiener Str 113",
    "sg:city":"Gars am Kamp",
    "sg:orig_category":"Bestattungsunternehmen",
    "sg:phone":"+43 664 1639252",
    "sg:postcode":"3571",
    "sg:province":"Nieder\u00f6sterreich",
    "wof:name":"Bestattung Gars GmbH",
    "wof:placetype":"venue"
},
  "geometry": {"coordinates":[15.6756095886,48.598285675],"type":"Point"}
}