{
  "type": "Feature",
  "properties": {
    "addr:full":"Gewerbepark Alemannenstr 49 Rankweil Vorarlberg 6830",
    "addr:housenumber":"49",
    "addr:postcode":"6830",
    "addr:street":"Gewerbepark",
    "iso:country":"AT",
    "sg:address":"Gewerbepark Alemannenstr 49",
    "sg:city":"Rankweil",
    "sg:orig_category":"Billardcafes",
    "sg:phone":"+43 4355 2248928",
    "sg:postcode":"6830",
    "sg:province":"Vorarlberg",
    "sg:website":"patricks.at",
    "wof:name":"Patricks Canadian Taverne",
    "wof:placetype":"venue"
},
  "geometry": {"coordinates":[9.6431694031,47.2692146301],"type":"Point"}
}