{
  "type": "Feature",
  "properties": {
    "addr:full":"Ottakringer Str 190-192/Top 73 Wien Wien 1160",
    "addr:housenumber":"190-192 / top 73",
    "addr:postcode":"1160",
    "addr:street":"Str",
    "iso:country":"AT",
    "sg:address":"Ottakringer Str 190-192/Top 73",
    "sg:city":"Wien",
    "sg:orig_category":"Werbeagenturen",
    "sg:phone":"+43 1 9247152",
    "sg:postcode":"1160",
    "sg:province":"Wien",
    "sg:website":"www.image-company.at",
    "wof:name":"Image Company",
    "wof:placetype":"venue"
},
  "geometry": {"coordinates":[16.2961292267,48.214931488],"type":"Point"}
}