{
  "type": "Feature",
  "properties": {
    "iso:country":"AT",
    "sg:address":"Viktor-Franz-Str 15",
    "sg:city":"G\u00f6sting",
    "sg:orig_category":"Tankanlagen",
    "sg:phone":"+43 4331 66770110",
    "sg:postcode":"8051",
    "sg:province":"Steiermark",
    "wof:name":"TANKTECHNIK GmbH",
    "wof:placetype":"venue"
},
  "geometry": {"coordinates":[15.4147367477,47.0903892517],"type":"Point"}
}