{
  "type": "Feature",
  "properties": {
    "addr:full":"Bahnhofstr 8 Obersch\u00fctzen Burgenland 7432",
    "addr:housenumber":"8",
    "addr:postcode":"7432",
    "addr:street":"Bahnhofstr",
    "iso:country":"AT",
    "sg:address":"Bahnhofstr 8",
    "sg:city":"Obersch\u00fctzen",
    "sg:orig_category":"Autoreparatur",
    "sg:phone":"+43 664 3564433",
    "sg:postcode":"7432",
    "sg:province":"Burgenland",
    "sg:website":"www.perfect-auto.at",
    "wof:name":"Perfect Autokosmetik",
    "wof:placetype":"venue"
},
  "geometry": {"coordinates":[16.2110214233,47.3492431641],"type":"Point"}
}