{
  "type": "Feature",
  "properties": {
    "addr:full":"Leebgasse 61 Wien Wien 1100",
    "addr:housenumber":"61",
    "addr:postcode":"1100",
    "addr:street":"Leebgasse",
    "iso:country":"AT",
    "sg:address":"Leebgasse 61",
    "sg:city":"Wien",
    "sg:classifiers":[
        {
            "category":"Building & Trades",
            "subcategory":"Electrical",
            "type":"Services"
        }
    ],
    "sg:phone":"+43 1 6045210",
    "sg:postcode":"1100",
    "sg:province":"Wien",
    "sg:tags":[
        "component",
        "elevator",
        "accessory"
    ],
    "sg:website":"dima.at",
    "wof:name":"Dima-Liftservice GesmbH",
    "wof:placetype":"venue"
},
  "geometry": {"coordinates":[16.3695087433,48.1721801758],"type":"Point"}
}