{
  "type": "Feature",
  "properties": {
    "iso:country":"AT",
    "sg:address":"Seeauerweg 9/4",
    "sg:city":"Linz",
    "sg:classifiers":[
        {
            "category":"Structure",
            "subcategory":"Office Building",
            "type":"Public Place"
        }
    ],
    "sg:phone":"+43 732 681962",
    "sg:postcode":"4020",
    "sg:province":"Ober\u00f6sterreich",
    "sg:tags":[
        "industrial",
        "assembly"
    ],
    "wof:name":"ALBIN MONTAGE",
    "wof:placetype":"venue"
},
  "geometry": {"coordinates":[14.2777719498,48.2752914429],"type":"Point"}
}