{
  "type": "Feature",
  "properties": {
    "addr:full":"Gartenstr 1 D\u00f6briach K\u00e4rnten 9873",
    "addr:housenumber":"1",
    "addr:postcode":"9873",
    "addr:street":"Gartenstr;Kaernten",
    "iso:country":"AT",
    "sg:address":"Gartenstr 1",
    "sg:city":"D\u00f6briach",
    "sg:orig_category":"Pensionen / Privatzimmer",
    "sg:phone":"+43 4246 7247",
    "sg:postcode":"9873",
    "sg:province":"K\u00e4rnten",
    "wof:name":"Hotel-Pension L\u00e4rchenhof",
    "wof:placetype":"venue"
},
  "geometry": {"coordinates":[7.6371488571,48.0116882324],"type":"Point"}
}