{
  "type": "Feature",
  "properties": {
    "iso:country":"AT",
    "sg:address":"B\u00fcchlstrasse 9",
    "sg:city":"Weiz",
    "sg:classifiers":[
        {
            "category":"Manufacturing",
            "subcategory":"Wood Products",
            "type":"Manufacturing & Wholesale Goods"
        }
    ],
    "sg:phone":"+43 3172 2477",
    "sg:postcode":"8160",
    "sg:province":"Steiermark",
    "sg:tags":[
        "bending"
    ],
    "wof:name":"G\u00f6\u00dflbauer GesmbH & Co KG",
    "wof:placetype":"venue"
},
  "geometry": {"coordinates":[15.6215696335,47.2169532776],"type":"Point"}
}