{
  "type": "Feature",
  "properties": {
    "addr:full":"Hauptpl 1 Sitzendorf an der Schmida Nieder\u00f6sterreich 3714",
    "addr:housenumber":"1",
    "addr:postcode":"3714",
    "addr:street":"Hauptpl",
    "iso:country":"AT",
    "sg:address":"Hauptpl 1",
    "sg:city":"Sitzendorf an der Schmida",
    "sg:orig_category":"Hauptschulen",
    "sg:phone":"+43 4329 5924460",
    "sg:postcode":"3714",
    "sg:province":"Nieder\u00f6sterreich",
    "wof:name":"Hauptschule",
    "wof:placetype":"venue"
},
  "geometry": {"coordinates":[15.9428014755,48.598941803],"type":"Point"}
}