{
  "type": "Feature",
  "properties": {
    "addr:full":"Nr 5 Feistritz an der Gail K\u00e4rnten 9613",
    "addr:housenumber":"9613",
    "addr:street":"Nr;Feistritz An Der Gail Kaernten",
    "iso:country":"AT",
    "sg:address":"Nr 5",
    "sg:city":"Feistritz an der Gail",
    "sg:orig_category":"Unterhaltungselektronik / Einzelhandel",
    "sg:phone":"+43 4342 562166",
    "sg:postcode":"9613",
    "sg:province":"K\u00e4rnten",
    "wof:name":"Wiegele Ignaz",
    "wof:placetype":"venue"
},
  "geometry": {"coordinates":[13.6032962799,46.5754203796],"type":"Point"}
}