{
  "type": "Feature",
  "properties": {
    "addr:full":"Haberlandtweg 11 Andritz Steiermark 8045",
    "addr:housenumber":"11",
    "addr:postcode":"8045",
    "addr:street":"Haberlandtweg",
    "iso:country":"AT",
    "sg:address":"Haberlandtweg 11",
    "sg:city":"Andritz",
    "sg:orig_category":"\u00c3\u201erzte / F Allgemeinmedizin",
    "sg:phone":"+43 316 6915560",
    "sg:postcode":"8045",
    "sg:province":"Steiermark",
    "wof:name":"Bohr Helmut Dr",
    "wof:placetype":"venue"
},
  "geometry": {"coordinates":[15.4234113693,47.1049537659],"type":"Point"}
}