{
  "type": "Feature",
  "properties": {
    "addr:full":"Nr 200 Maurach Tirol 6212",
    "addr:postcode":"6212",
    "addr:street":"Nr;Maurach Tirol",
    "iso:country":"AT",
    "sg:address":"Nr 200",
    "sg:city":"Maurach",
    "sg:classifiers":[
        {
            "category":"Park",
            "subcategory":"Provincial",
            "type":"Public Place"
        }
    ],
    "sg:phone":"+43 5243 43100",
    "sg:postcode":"6212",
    "sg:province":"Tirol",
    "sg:tags":[
        "u",
        "ski-",
        "snowboardschulen"
    ],
    "wof:name":"Skischule Maurach",
    "wof:placetype":"venue"
},
  "geometry": {"coordinates":[11.7518672943,47.4225006104],"type":"Point"}
}