{
  "type": "Feature",
  "properties": {
    "addr:full":"Billrothstr 62 Wien Wien 1190",
    "addr:housenumber":"62",
    "addr:postcode":"1190",
    "addr:street":"Billrothstr",
    "iso:country":"AT",
    "sg:address":"Billrothstr 62",
    "sg:city":"Wien",
    "sg:orig_category":"Friseure U Frisiersalons",
    "sg:phone":"+43 4369 919252614",
    "sg:postcode":"1190",
    "sg:province":"Wien",
    "wof:name":"Hair by Franz Wiesm\u00fcller",
    "wof:placetype":"venue"
},
  "geometry": {"coordinates":[16.3489112854,48.241065979],"type":"Point"}
}