{
  "type": "Feature",
  "properties": {
    "addr:full":"Nr 13 Thalgau Salzburg 5303",
    "addr:postcode":"5303",
    "addr:street":"Nr;Salzburg",
    "iso:country":"AT",
    "sg:address":"Nr 13",
    "sg:city":"Thalgau",
    "sg:orig_category":"Garten- U Landschaftsgestaltung",
    "sg:phone":"+43 676 5198515",
    "sg:postcode":"5303",
    "sg:province":"Salzburg",
    "wof:name":"Germann Thomas - Garten- und Schwimmteichgestaltung",
    "wof:placetype":"venue"
},
  "geometry": {"coordinates":[13.2537765503,47.8417167664],"type":"Point"}
}