{
  "type": "Feature",
  "properties": {
    "addr:full":"Grazer G 9 Leibnitz Steiermark 8430",
    "addr:housenumber":"9",
    "addr:postcode":"8430",
    "addr:street":"Grazer G;Steiermark",
    "iso:country":"AT",
    "sg:address":"Grazer G 9",
    "sg:city":"Leibnitz",
    "sg:orig_category":"Damenmoden",
    "sg:phone":"+43 3452 82631",
    "sg:postcode":"8430",
    "sg:province":"Steiermark",
    "wof:name":"Sgerm Erich",
    "wof:placetype":"venue"
},
  "geometry": {"coordinates":[15.5386638641,46.7825584412],"type":"Point"}
}