{
  "type": "Feature",
  "properties": {
    "iso:country":"AT",
    "sg:address":"Singerstr 8",
    "sg:city":"Wien",
    "sg:orig_category":"Optiker",
    "sg:phone":"+43 1 51214890",
    "sg:postcode":"1010",
    "sg:province":"Wien",
    "wof:name":"Hartmann Optik",
    "wof:placetype":"venue"
},
  "geometry": {"coordinates":[16.3726100922,48.2075653076],"type":"Point"}
}