{
  "type": "Feature",
  "properties": {
    "iso:country":"AT",
    "sg:address":"Bahnhofstr 4",
    "sg:city":"Altheim",
    "sg:orig_category":"Glasbe- U -Verarbeitung",
    "sg:phone":"+43 4377 2342270",
    "sg:postcode":"4950",
    "sg:province":"Ober\u00f6sterreich",
    "wof:name":"Neum\u00fcller Klaus",
    "wof:placetype":"venue"
},
  "geometry": {"coordinates":[13.2330513,48.2506484985],"type":"Point"}
}