{
  "type": "Feature",
  "properties": {
    "iso:country":"AT",
    "sg:address":"M\u00f6dlinger Str 3",
    "sg:city":"Guntramsdorf",
    "sg:orig_category":"Papier- U Schreibwaren / Einzelhandel",
    "sg:phone":"+43 4322 36506393",
    "sg:postcode":"2353",
    "sg:province":"Nieder\u00f6sterreich",
    "wof:name":"Aigner Michaela",
    "wof:placetype":"venue"
},
  "geometry": {"coordinates":[16.3131484985,48.0491676331],"type":"Point"}
}