{
  "type": "Feature",
  "properties": {
    "addr:full":"Dikat 440 Jenbach Tirol 6200",
    "addr:housenumber":"440",
    "addr:postcode":"6200",
    "addr:street":"Dikat;Tirol",
    "iso:country":"AT",
    "sg:address":"Dikat 440",
    "sg:city":"Jenbach",
    "sg:orig_category":"Erdarbeiten",
    "sg:phone":"+43 5244 64886",
    "sg:postcode":"6200",
    "sg:province":"Tirol",
    "wof:name":"Thaler Manfred",
    "wof:placetype":"venue"
},
  "geometry": {"coordinates":[11.8092718124,47.4065933228],"type":"Point"}
}