{
  "type": "Feature",
  "properties": {
    "addr:full":"Hauptpl 7 Wieselburg an der Erlauf Nieder\u00f6sterreich 3250",
    "addr:housenumber":"7",
    "addr:postcode":"3250",
    "addr:street":"Hauptpl",
    "iso:country":"AT",
    "sg:address":"Hauptpl 7",
    "sg:city":"Wieselburg an der Erlauf",
    "sg:orig_category":"Museen / Ausstellungen",
    "sg:phone":"+43 4374 165231933",
    "sg:postcode":"3250",
    "sg:province":"Nieder\u00f6sterreich",
    "wof:name":"Ur- und Fr\u00fchgeschichtliches Museum der Stadtgemeinde Wieselburg",
    "wof:placetype":"venue"
},
  "geometry": {"coordinates":[15.1380252838,48.1304283142],"type":"Point"}
}