{
  "type": "Feature",
  "properties": {
    "addr:full":"Nr 29 Nu\u00dfdorf am Haunsberg Salzburg 5151",
    "addr:postcode":"5151",
    "addr:street":"Nr 29;Salzburg",
    "iso:country":"AT",
    "sg:address":"Nr 29",
    "sg:city":"Nu\u00dfdorf am Haunsberg",
    "sg:orig_category":"Volksschulen",
    "sg:phone":"+43 4362 76264",
    "sg:postcode":"5151",
    "sg:province":"Salzburg",
    "wof:name":"Volksschule",
    "wof:placetype":"venue"
},
  "geometry": {"coordinates":[166.9221496582,-0.5282999873],"type":"Point"}
}