{
  "type": "Feature",
  "properties": {
    "addr:full":"Paulweg 1 Leibnitz Steiermark 8430",
    "addr:housenumber":"1",
    "addr:postcode":"8430",
    "addr:street":"Paulweg;Steiermark",
    "iso:country":"AT",
    "sg:address":"Paulweg 1",
    "sg:city":"Leibnitz",
    "sg:orig_category":"Schlossereien",
    "sg:phone":"+43 4334 5272600",
    "sg:postcode":"8430",
    "sg:province":"Steiermark",
    "wof:name":"Schwarzl Johann",
    "wof:placetype":"venue"
},
  "geometry": {"coordinates":[15.5295324326,46.8075828552],"type":"Point"}
}