{
  "type": "Feature",
  "properties": {
    "addr:full":"Thalgaustr 37 Mondsee Ober\u00f6sterreich 5310",
    "addr:housenumber":"37",
    "addr:postcode":"5310",
    "addr:street":"Thalgaustr;Oberoesterreich",
    "iso:country":"AT",
    "sg:address":"Thalgaustr 37",
    "sg:city":"Mondsee",
    "sg:orig_category":"Autohandel",
    "sg:phone":"+43 4362 3228480",
    "sg:postcode":"5310",
    "sg:province":"Ober\u00f6sterreich",
    "wof:name":"Auto Sesser GesmbH",
    "wof:placetype":"venue"
},
  "geometry": {"coordinates":[13.3344697952,47.8458900452],"type":"Point"}
}