{
  "type": "Feature",
  "properties": {
    "iso:country":"AT",
    "sg:address":"Maximilianstr 4",
    "sg:city":"Wels",
    "sg:orig_category":"Friseure U Frisiersalons",
    "sg:phone":"+43 7242 67484",
    "sg:postcode":"4600",
    "sg:province":"Ober\u00f6sterreich",
    "wof:name":"Friseur-Salon-City",
    "wof:placetype":"venue"
},
  "geometry": {"coordinates":[14.0257472992,48.1619186401],"type":"Point"}
}