{
  "type": "Feature",
  "properties": {
    "addr:full":"Nr 57 Rohr im Gebirge Nieder\u00f6sterreich 2663",
    "addr:postcode":"2663",
    "addr:street":"Nr",
    "iso:country":"AT",
    "sg:address":"Nr 57",
    "sg:city":"Rohr im Gebirge",
    "sg:orig_category":"Banken U Sparkassen",
    "sg:phone":"+43 4326 678223",
    "sg:postcode":"2663",
    "sg:province":"Nieder\u00f6sterreich",
    "wof:name":"Raiffeisenbank Piestingtal regGenmbH",
    "wof:placetype":"venue"
},
  "geometry": {"coordinates":[15.7363061905,47.8951377869],"type":"Point"}
}