{
  "type": "Feature",
  "properties": {
    "addr:full":"Kalkofenweg 8 Hallein Salzburg 5400",
    "addr:housenumber":"8",
    "addr:postcode":"5400",
    "addr:street":"Kalkofenweg;Salzburg",
    "iso:country":"AT",
    "sg:address":"Kalkofenweg 8",
    "sg:city":"Hallein",
    "sg:orig_category":"Elektroinstallationsmaterial",
    "sg:phone":"+43 6245 833700",
    "sg:postcode":"5400",
    "sg:province":"Salzburg",
    "wof:name":"EL-NE Elektrotechnik GesmbH",
    "wof:placetype":"venue"
},
  "geometry": {"coordinates":[13.1089820862,47.6709518433],"type":"Point"}
}