{
  "type": "Feature",
  "properties": {
    "addr:full":"Josef-Marberger-Str 13 Silz Tirol 6424",
    "addr:housenumber":"13",
    "addr:postcode":"6424",
    "addr:street":"Josef-Marberger-Str;Tirol",
    "iso:country":"AT",
    "sg:address":"Josef-Marberger-Str 13",
    "sg:city":"Silz",
    "sg:orig_category":"Fensterrenovierung, -Reparatur U -Service",
    "sg:phone":"+43 4352 6363770",
    "sg:postcode":"6424",
    "sg:province":"Tirol",
    "sg:website":"haslwanter.portas.at",
    "wof:name":"Portas Fachbetrieb - Josef Haslwanter",
    "wof:placetype":"venue"
},
  "geometry": {"coordinates":[10.9343490601,47.26927948],"type":"Point"}
}