{
  "type": "Feature",
  "properties": {
    "addr:full":"Wieshof 9 Krenglbach Ober\u00f6sterreich 4631",
    "addr:housenumber":"9",
    "addr:postcode":"4631",
    "addr:street":"Wieshof",
    "iso:country":"AT",
    "sg:address":"Wieshof 9",
    "sg:city":"Krenglbach",
    "sg:orig_category":"Springbrunnen",
    "sg:phone":"+43 7249 48866",
    "sg:postcode":"4631",
    "sg:province":"Ober\u00f6sterreich",
    "wof:name":"Josef Kappelmayr - Springbrunnen-Wassertechnik",
    "wof:placetype":"venue"
},
  "geometry": {"coordinates":[13.9542961121,48.2106552124],"type":"Point"}
}