{
  "type": "Feature",
  "properties": {
    "addr:full":"Innsbruck Bundesstr 36 Salzburg Salzburg 5020",
    "addr:housenumber":"36",
    "addr:postcode":"5020",
    "addr:street":"Salzburg",
    "iso:country":"AT",
    "sg:address":"Innsbruck Bundesstr 36",
    "sg:city":"Salzburg",
    "sg:orig_category":"Friseure U Frisiersalons",
    "sg:phone":"+43 662 423293",
    "sg:postcode":"5020",
    "sg:province":"Salzburg",
    "wof:name":"Frisiersalon Gabi",
    "wof:placetype":"venue"
},
  "geometry": {"coordinates":[13.020813942,47.8052253723],"type":"Point"}
}