{
  "type": "Feature",
  "properties": {
    "iso:country":"AT",
    "sg:address":"Am Steindl 62",
    "sg:city":"Krems an der Donau",
    "sg:orig_category":"Steuerberatung",
    "sg:phone":"+43 4327 3282705",
    "sg:postcode":"3500",
    "sg:province":"Nieder\u00f6sterreich",
    "wof:name":"Hintermayer Michael MMag",
    "wof:placetype":"venue"
},
  "geometry": {"coordinates":[15.6045656204,48.4190979004],"type":"Point"}
}