{
  "type": "Feature",
  "properties": {
    "addr:full":"Josef-Haydn-G 51 Laa an der Thaya Nieder\u00f6sterreich 2136",
    "addr:housenumber":"51",
    "addr:postcode":"2136",
    "addr:street":"Josef-Haydn-G",
    "iso:country":"AT",
    "sg:address":"Josef-Haydn-G 51",
    "sg:city":"Laa an der Thaya",
    "sg:orig_category":"Elektroinstallationsunternehmen",
    "sg:phone":"+43 2522 8986",
    "sg:postcode":"2136",
    "sg:province":"Nieder\u00f6sterreich",
    "wof:name":"Langer Johann",
    "wof:placetype":"venue"
},
  "geometry": {"coordinates":[16.3972187042,48.7253036499],"type":"Point"}
}