{
  "type": "Feature",
  "properties": {
    "iso:country":"AT",
    "sg:address":"Laim 32",
    "sg:city":"St. Gilgen",
    "sg:orig_category":"Elektroinstallationsunternehmen",
    "sg:phone":"+43 6227 2636",
    "sg:postcode":"5340",
    "sg:province":"Salzburg",
    "wof:name":"Proksch Heinz",
    "wof:placetype":"venue"
},
  "geometry": {"coordinates":[13.3555192947,47.7671890259],"type":"Point"}
}