{
  "type": "Feature",
  "properties": {
    "addr:full":"Haydng 2 Deutsch Wagram Nieder\u00f6sterreich 2232",
    "addr:housenumber":"2",
    "addr:postcode":"2232",
    "addr:street":"Haydng",
    "iso:country":"AT",
    "sg:address":"Haydng 2",
    "sg:city":"Deutsch Wagram",
    "sg:orig_category":"Landwirtschaftliche Produkte",
    "sg:phone":"+43 2247 40000",
    "sg:postcode":"2232",
    "sg:province":"Nieder\u00f6sterreich",
    "wof:name":"Hasitschka M Agrarhandels GmbH",
    "wof:placetype":"venue"
},
  "geometry": {"coordinates":[16.5697593689,48.3038406372],"type":"Point"}
}