{
  "type": "Feature",
  "properties": {
    "addr:full":"Dachsbergg 5 Krems an der Donau Nieder\u00f6sterreich 3500",
    "addr:housenumber":"5",
    "addr:postcode":"3500",
    "addr:street":"Dachsbergg",
    "iso:country":"AT",
    "sg:address":"Dachsbergg 5",
    "sg:city":"Krems an der Donau",
    "sg:orig_category":"Fotografen",
    "sg:phone":"+43 2732 833820",
    "sg:postcode":"3500",
    "sg:province":"Nieder\u00f6sterreich",
    "wof:name":"Fotostudio Gartler",
    "wof:placetype":"venue"
},
  "geometry": {"coordinates":[15.6000099182,48.4104309082],"type":"Point"}
}