{
  "type": "Feature",
  "properties": {
    "iso:country":"AT",
    "sg:address":"Prager Str 74",
    "sg:city":"Wien",
    "sg:orig_category":"Handelsagenturen",
    "sg:phone":"+43 1 27163390",
    "sg:postcode":"1210",
    "sg:province":"Wien",
    "wof:name":"FHK Handelsagentur Ing Friedrich Holek",
    "wof:placetype":"venue"
},
  "geometry": {"coordinates":[16.39220047,48.2689399719],"type":"Point"}
}