{
  "type": "Feature",
  "properties": {
    "addr:full":"Im Dorf 7 Klaus-Weiler Vorarlberg 6833",
    "addr:housenumber":"7",
    "addr:postcode":"6833",
    "addr:street":"Im Dorf",
    "iso:country":"AT",
    "sg:address":"Im Dorf 7",
    "sg:city":"Klaus-Weiler",
    "sg:orig_category":"Non-Classified Establishments",
    "sg:phone":"+43 5523 54118",
    "sg:postcode":"6833",
    "sg:province":"Vorarlberg",
    "wof:name":"Pfarreib\u00fcro Fraxern - Pfarrhof",
    "wof:placetype":"venue"
},
  "geometry": {"coordinates":[9.6736211777,47.3146705627],"type":"Point"}
}