{
  "type": "Feature",
  "properties": {
    "addr:full":"Blumengasse 51 Wien Wien 1170",
    "addr:housenumber":"51",
    "addr:postcode":"1170",
    "addr:street":"Blumengasse",
    "iso:country":"AT",
    "sg:address":"Blumengasse 51",
    "sg:city":"Wien",
    "sg:classifiers":[
        {
            "category":"Home & Garden",
            "subcategory":"Building Materials",
            "type":"Retail Goods"
        }
    ],
    "sg:phone":"+43 1 4062308",
    "sg:postcode":"1170",
    "sg:province":"Wien",
    "sg:tags":[
        "steel",
        "metal",
        "made",
        "door",
        "gate"
    ],
    "sg:website":"eha.at",
    "wof:name":"EHA Stahlbau Ges.m.b.H.",
    "wof:placetype":"venue"
},
  "geometry": {"coordinates":[16.3321380615,48.2212028503],"type":"Point"}
}