{
  "type": "Feature",
  "properties": {
    "addr:full":"Lechtaler Str 33a Reutte Tirol 6600",
    "addr:postcode":"6600",
    "addr:street":"Str 33A;Tirol",
    "iso:country":"AT",
    "sg:address":"Lechtaler Str 33a",
    "sg:city":"Reutte",
    "sg:orig_category":"Fliesen U Platten",
    "sg:phone":"+43 4356 7265046",
    "sg:postcode":"6600",
    "sg:province":"Tirol",
    "wof:name":"Eiter Hermann Fliesen-Design",
    "wof:placetype":"venue"
},
  "geometry": {"coordinates":[10.7035427094,47.4825592041],"type":"Point"}
}