{
  "type": "Feature",
  "properties": {
    "iso:country":"AT",
    "sg:address":"Sch\u00f6pfstr 23",
    "sg:city":"Innsbruck",
    "sg:orig_category":"Zahntechnische Laboratorien",
    "sg:phone":"+43 512 583164",
    "sg:postcode":"6020",
    "sg:province":"Tirol",
    "wof:name":"Oss Hans-Peter",
    "wof:placetype":"venue"
},
  "geometry": {"coordinates":[11.390162468,47.2601928711],"type":"Point"}
}