{
  "type": "Feature",
  "properties": {
    "addr:full":"Seezeile 24 Rust Burgenland 7071",
    "addr:housenumber":"24",
    "addr:postcode":"7071",
    "addr:street":"Seezeile",
    "iso:country":"AT",
    "sg:address":"Seezeile 24",
    "sg:city":"Rust",
    "sg:classifiers":[
        {
            "category":"Restaurant",
            "type":"Food & Drink"
        }
    ],
    "sg:phone":"+43 2685 64180",
    "sg:postcode":"7071",
    "sg:province":"Burgenland",
    "wof:name":"Restaurant Alte Schmiede",
    "wof:placetype":"venue"
},
  "geometry": {"coordinates":[16.67710495,47.8000793457],"type":"Point"}
}