{
  "type": "Feature",
  "properties": {
    "iso:country":"AT",
    "sg:address":"Maroltingerg 36-38",
    "sg:city":"Wien",
    "sg:orig_category":"Videotheken",
    "sg:phone":"+43 1 7864631",
    "sg:postcode":"1160",
    "sg:province":"Wien",
    "wof:name":"Stiegler Karl KG",
    "wof:placetype":"venue"
},
  "geometry": {"coordinates":[16.3045482635,48.2069282532],"type":"Point"}
}