{
  "type": "Feature",
  "properties": {
    "addr:full":"Fromillerstr 20 Klagenfurt K\u00e4rnten 9020",
    "addr:housenumber":"20",
    "addr:postcode":"9020",
    "addr:street":"Fromillerstr;Kaernten",
    "iso:country":"AT",
    "sg:address":"Fromillerstr 20",
    "sg:city":"Klagenfurt",
    "sg:orig_category":"Lebens- U Sozialberatung",
    "sg:phone":"+43 463 51203516",
    "sg:postcode":"9020",
    "sg:province":"K\u00e4rnten",
    "wof:name":"P\u00e4dagogisch-Psychologischer Dienst d Arbeitsvereinigung d Sozialhilfe K\u00e4rntens",
    "wof:placetype":"venue"
},
  "geometry": {"coordinates":[14.3090600967,46.6186447144],"type":"Point"}
}