{
  "type": "Feature",
  "properties": {
    "addr:full":"Ulrichstr 36 Steyr Ober\u00f6sterreich 4400",
    "addr:housenumber":"36",
    "addr:postcode":"4400",
    "addr:street":"Ulrichstr;Oberoesterreich",
    "iso:country":"AT",
    "sg:address":"Ulrichstr 36",
    "sg:city":"Steyr",
    "sg:orig_category":"Ingenieurkonsulenten / Zivilingenieure",
    "sg:phone":"+43 7252 52425",
    "sg:postcode":"4400",
    "sg:province":"Ober\u00f6sterreich",
    "wof:name":"Breinesberger Walter Dipl-Ing",
    "wof:placetype":"venue"
},
  "geometry": {"coordinates":[14.4230155945,48.0221595764],"type":"Point"}
}