{
  "type": "Feature",
  "properties": {
    "iso:country":"AT",
    "sg:address":"M\u00fcllerstr 3",
    "sg:city":"Lustenau",
    "sg:orig_category":"Etiketten",
    "sg:phone":"+43 4355 7782394",
    "sg:postcode":"6890",
    "sg:province":"Vorarlberg",
    "wof:name":"Alge Etiketten KG",
    "wof:placetype":"venue"
},
  "geometry": {"coordinates":[9.6590452194,47.4262237549],"type":"Point"}
}