{
  "type": "Feature",
  "properties": {
    "iso:country":"AT",
    "sg:address":"Landstra\u00dfer Hauptstr 60/14",
    "sg:city":"Wien",
    "sg:orig_category":"Ingenieurkonsulenten / Zivilingenieure",
    "sg:phone":"+43 4317 106360",
    "sg:postcode":"1030",
    "sg:province":"Wien",
    "wof:name":"K\u00f6hler- Matheis-Rabl & Partner ZT GesmbH",
    "wof:placetype":"venue"
},
  "geometry": {"coordinates":[16.3911876678,48.2018127441],"type":"Point"}
}