{
  "type": "Feature",
  "properties": {
    "iso:country":"AT",
    "sg:address":"Satzlweg 4",
    "sg:city":"Krems an der Donau",
    "sg:orig_category":"Physiotherapie",
    "sg:phone":"+43 2732 41382",
    "sg:postcode":"3500",
    "sg:province":"Nieder\u00f6sterreich",
    "wof:name":"Schauer Mechthild Dipl-PT",
    "wof:placetype":"venue"
},
  "geometry": {"coordinates":[15.5598163605,48.4200782776],"type":"Point"}
}