{
  "type": "Feature",
  "properties": {
    "addr:full":"Hauptpl 20 Neumarkt in Steiermark Steiermark 8820",
    "addr:housenumber":"20",
    "addr:postcode":"8820",
    "addr:street":"Hauptpl",
    "iso:country":"AT",
    "sg:address":"Hauptpl 20",
    "sg:city":"Neumarkt in Steiermark",
    "sg:orig_category":"Glasereien",
    "sg:phone":"+43 4335 843824",
    "sg:postcode":"8820",
    "sg:province":"Steiermark",
    "wof:name":"Tichatschek Ulrike",
    "wof:placetype":"venue"
},
  "geometry": {"coordinates":[14.42603302,47.0738716125],"type":"Point"}
}