{
  "type": "Feature",
  "properties": {
    "addr:full":"Gobelsburger Str 23 Langenlois Nieder\u00f6sterreich 3550",
    "addr:housenumber":"23",
    "addr:postcode":"3550",
    "addr:street":"Gobelsburger Str",
    "iso:country":"AT",
    "sg:address":"Gobelsburger Str 23",
    "sg:city":"Langenlois",
    "sg:orig_category":"Spenglereien",
    "sg:phone":"+43 2734 3539",
    "sg:postcode":"3550",
    "sg:province":"Nieder\u00f6sterreich",
    "wof:name":"Wutzl Alfred",
    "wof:placetype":"venue"
},
  "geometry": {"coordinates":[15.6879558563,48.4690322876],"type":"Point"}
}