{
  "type": "Feature",
  "properties": {
    "addr:full":"Hauptstr 154 Altenmarkt im Pongau Salzburg 5541",
    "addr:housenumber":"154",
    "addr:postcode":"5541",
    "addr:street":"Hauptstr;Salzburg",
    "iso:country":"AT",
    "sg:address":"Hauptstr 154",
    "sg:city":"Altenmarkt im Pongau",
    "sg:orig_category":"Elektroinstallationsunternehmen",
    "sg:phone":"+43 6452 5416",
    "sg:postcode":"5541",
    "sg:province":"Salzburg",
    "wof:name":"Patrias Eelectric Automation GmbH",
    "wof:placetype":"venue"
},
  "geometry": {"coordinates":[13.4270744324,47.3801040649],"type":"Point"}
}