{
  "type": "Feature",
  "properties": {
    "iso:country":"AT",
    "sg:address":"Kremstalstrasse 90",
    "sg:city":"Traun",
    "sg:orig_category":"Granite Pavers",
    "sg:phone":"+43 7229 51537",
    "sg:postcode":"4050",
    "sg:province":"Ober\u00f6sterreich",
    "sg:website":"marmor-lux.at",
    "wof:name":"MARMOR LUX Steinmetz GmbH",
    "wof:placetype":"venue"
},
  "geometry": {"coordinates":[14.233912468,48.2294197083],"type":"Point"}
}