{
  "type": "Feature",
  "properties": {
    "addr:full":"Arena am Waldfeld 28 Fohnsdorf Steiermark 8753",
    "addr:housenumber":"28",
    "addr:postcode":"8753",
    "addr:street":"Arena Am Waldfeld",
    "iso:country":"AT",
    "sg:address":"Arena am Waldfeld 28",
    "sg:city":"Fohnsdorf",
    "sg:orig_category":"Lederbekleidung",
    "sg:phone":"+43 3572 47215",
    "sg:postcode":"8753",
    "sg:province":"Steiermark",
    "wof:name":"Ledermoden Doris",
    "wof:placetype":"venue"
},
  "geometry": {"coordinates":[14.685256958,47.1844749451],"type":"Point"}
}