{
  "type": "Feature",
  "properties": {
    "addr:full":"Sautergasse 20 Wien Wien 1170",
    "addr:housenumber":"20",
    "addr:postcode":"1170",
    "addr:street":"Sautergasse",
    "iso:country":"AT",
    "sg:address":"Sautergasse 20",
    "sg:city":"Wien",
    "sg:classifiers":[
        {
            "category":"Sports & Exercise",
            "subcategory":"Playing Field",
            "type":"Entertainment"
        }
    ],
    "sg:phone":"+43 1 9292815",
    "sg:postcode":"1170",
    "sg:province":"Wien",
    "sg:tags":[
        "application",
        "programming"
    ],
    "sg:website":"heureka.co.at",
    "wof:name":"Heureka Ges. f\u00fcr Kommunikations- und Anwender-Software GmbH",
    "wof:placetype":"venue"
},
  "geometry": {"coordinates":[16.3214206696,48.2204627991],"type":"Point"}
}