{
  "type": "Feature",
  "properties": {
    "iso:country":"AT",
    "sg:address":"Leoprechting",
    "sg:city":"Taufkirchen an der Pram",
    "sg:orig_category":"Tischlereien",
    "sg:phone":"+43 4377 198372",
    "sg:postcode":"4775",
    "sg:province":"Ober\u00f6sterreich",
    "wof:name":"Dollereder Manfred",
    "wof:placetype":"venue"
},
  "geometry": {"coordinates":[13.542309761,48.4105606079],"type":"Point"}
}