{
  "type": "Feature",
  "properties": {
    "addr:full":"Korneuburg Nieder\u00f6sterreich 2100",
    "addr:postcode":"2100",
    "addr:street":"Niederoesterreich",
    "iso:country":"AT",
    "sg:city":"Korneuburg",
    "sg:orig_category":"Tankstellen",
    "sg:phone":"+43 2262 74589",
    "sg:postcode":"2100",
    "sg:province":"Nieder\u00f6sterreich",
    "wof:name":"Agip Austria GmbH",
    "wof:placetype":"venue"
},
  "geometry": {"coordinates":[16.3329143524,48.3437843323],"type":"Point"}
}