{
  "type": "Feature",
  "properties": {
    "iso:country":"AT",
    "sg:address":"Gewerbepark 2",
    "sg:city":"Atzenbrugg",
    "sg:orig_category":"Maschinenbau",
    "sg:phone":"+43 4322 7541483",
    "sg:postcode":"3452",
    "sg:province":"Nieder\u00f6sterreich",
    "wof:name":"A.I.S. Anlageninstandhaltungs u -service GmbH",
    "wof:placetype":"venue"
},
  "geometry": {"coordinates":[15.9042654037,48.2924804688],"type":"Point"}
}