{
  "type": "Feature",
  "properties": {
    "addr:full":"Hauptstr 8 Berndorf Nieder\u00f6sterreich 2560",
    "addr:housenumber":"8",
    "addr:postcode":"2560",
    "addr:street":"Hauptstr",
    "iso:country":"AT",
    "sg:address":"Hauptstr 8",
    "sg:city":"Berndorf",
    "sg:orig_category":"Tischlereien",
    "sg:phone":"+43 2672 87738",
    "sg:postcode":"2560",
    "sg:province":"Nieder\u00f6sterreich",
    "wof:name":"Hahn Karl Heinz",
    "wof:placetype":"venue"
},
  "geometry": {"coordinates":[16.1551246643,47.9385185242],"type":"Point"}
}