{
  "type": "Feature",
  "properties": {
    "addr:full":"Nr 145 Kartitsch Tirol 9941",
    "addr:postcode":"9941",
    "addr:street":"Nr;Kartitsch Tirol",
    "iso:country":"AT",
    "sg:address":"Nr 145",
    "sg:city":"Kartitsch",
    "sg:orig_category":"Transportunternehmen",
    "sg:phone":"+43 4848 5276",
    "sg:postcode":"9941",
    "sg:province":"Tirol",
    "wof:name":"Kofler Josef",
    "wof:placetype":"venue"
},
  "geometry": {"coordinates":[12.4975404739,46.7263145447],"type":"Point"}
}