{
  "type": "Feature",
  "properties": {
    "addr:full":"Dreihausgasse 19 Wien Wien 1150",
    "addr:housenumber":"19",
    "addr:postcode":"1150",
    "addr:street":"Dreihausgasse",
    "iso:country":"AT",
    "sg:address":"Dreihausgasse 19",
    "sg:city":"Wien",
    "sg:classifiers":[
        {
            "category":"Manufacturing",
            "subcategory":"Wood Products",
            "type":"Manufacturing & Wholesale Goods"
        }
    ],
    "sg:phone":"+43 1 8936044",
    "sg:postcode":"1150",
    "sg:province":"Wien",
    "sg:tags":[
        "leg",
        "furniture"
    ],
    "sg:website":"peschak.at",
    "wof:name":"G\u00fcnther Peschak Holzdrechslerei",
    "wof:placetype":"venue"
},
  "geometry": {"coordinates":[16.3257083893,48.1881828308],"type":"Point"}
}