{
  "type": "Feature",
  "properties": {
    "addr:full":"Kircheng 3 Ternitz Nieder\u00f6sterreich 2630",
    "addr:housenumber":"3",
    "addr:postcode":"2630",
    "addr:street":"Kircheng",
    "iso:country":"AT",
    "sg:address":"Kircheng 3",
    "sg:city":"Ternitz",
    "sg:orig_category":"Non-Classified Establishments",
    "sg:phone":"+43 2630 38433",
    "sg:postcode":"2630",
    "sg:province":"Nieder\u00f6sterreich",
    "wof:name":"Pfarramt",
    "wof:placetype":"venue"
},
  "geometry": {"coordinates":[16.0002212524,47.7036857605],"type":"Point"}
}