{
  "type": "Feature",
  "properties": {
    "addr:full":"Hauptstr 150 Wien Wien 1140",
    "addr:housenumber":"150",
    "addr:postcode":"1140",
    "addr:street":"Hauptstr",
    "iso:country":"AT",
    "sg:address":"Hauptstr 150",
    "sg:city":"Wien",
    "sg:orig_category":"Immobilienverwaltungen",
    "sg:phone":"+43 4319 794918",
    "sg:postcode":"1140",
    "sg:province":"Wien",
    "wof:name":"Seeb VerwaltungsgesmbH",
    "wof:placetype":"venue"
},
  "geometry": {"coordinates":[16.2076034546,48.2069664001],"type":"Point"}
}