{
  "type": "Feature",
  "properties": {
    "addr:full":"Albrechtstr 34 Klosterneuburg Nieder\u00f6sterreich 3400",
    "addr:housenumber":"34",
    "addr:postcode":"3400",
    "addr:street":"Albrechtstr;Niederoesterreich",
    "iso:country":"AT",
    "sg:address":"Albrechtstr 34",
    "sg:city":"Klosterneuburg",
    "sg:orig_category":"Installationsunternehmen",
    "sg:phone":"+43 2243 35793",
    "sg:postcode":"3400",
    "sg:province":"Nieder\u00f6sterreich",
    "wof:name":"Balluch Peter",
    "wof:placetype":"venue"
},
  "geometry": {"coordinates":[16.3208084106,48.3096885681],"type":"Point"}
}