{
  "type": "Feature",
  "properties": {
    "addr:full":"Kirchg 6 St. Veit an der Glan K\u00e4rnten 9300",
    "addr:housenumber":"6",
    "addr:postcode":"9300",
    "addr:street":"Kirchg;Kaernten",
    "iso:country":"AT",
    "sg:address":"Kirchg 6",
    "sg:city":"St. Veit an der Glan",
    "sg:orig_category":"Fleischhauereien",
    "sg:phone":"+43 4212 2945",
    "sg:postcode":"9300",
    "sg:province":"K\u00e4rnten",
    "wof:name":"Weiss Fleischveredelung GmbH",
    "wof:placetype":"venue"
},
  "geometry": {"coordinates":[14.3584327698,46.7671012878],"type":"Point"}
}