{
  "type": "Feature",
  "properties": {
    "iso:country":"AT",
    "sg:address":"Kirchweg 3",
    "sg:city":"Rietz",
    "sg:orig_category":"Handelsagenturen",
    "sg:phone":"+43 5262 64713",
    "sg:postcode":"6421",
    "sg:province":"Tirol",
    "wof:name":"Sandbichler Peter",
    "wof:placetype":"venue"
},
  "geometry": {"coordinates":[11.0390987396,47.286491394],"type":"Point"}
}