{
  "type": "Feature",
  "properties": {
    "addr:full":"Margarethenstr 22 Lebring Steiermark 8403",
    "addr:housenumber":"22",
    "addr:postcode":"8403",
    "addr:street":"Margarethenstr",
    "iso:country":"AT",
    "sg:address":"Margarethenstr 22",
    "sg:city":"Lebring",
    "sg:orig_category":"Transportunternehmen",
    "sg:phone":"+43 4331 8224340",
    "sg:postcode":"8403",
    "sg:province":"Steiermark",
    "wof:name":"Roj Rafael GesmbH",
    "wof:placetype":"venue"
},
  "geometry": {"coordinates":[15.518201828,46.8559188843],"type":"Point"}
}