{
  "type": "Feature",
  "properties": {
    "addr:full":"Schultestr 6 Linz Ober\u00f6sterreich 4020",
    "addr:housenumber":"6",
    "addr:postcode":"4020",
    "addr:street":"Schultestr",
    "iso:country":"AT",
    "sg:address":"Schultestr 6",
    "sg:city":"Linz",
    "sg:orig_category":"Ingenieurkonsulenten / Zivilingenieure",
    "sg:phone":"+43 732 609890",
    "sg:postcode":"4020",
    "sg:province":"Ober\u00f6sterreich",
    "wof:name":"Feilmayr Eberhard Dipl-Ing",
    "wof:placetype":"venue"
},
  "geometry": {"coordinates":[14.2830753326,48.2885856628],"type":"Point"}
}