{
  "type": "Feature",
  "properties": {
    "iso:country":"AT",
    "sg:address":"Gewerbegebiet 1",
    "sg:city":"Weikendorf",
    "sg:orig_category":"Insektenschutzgitter",
    "sg:phone":"+43 2282 60222",
    "sg:postcode":"2253",
    "sg:province":"Nieder\u00f6sterreich",
    "wof:name":"Gr\u00fcnefeldt Insektengitter-Systeme",
    "wof:placetype":"venue"
},
  "geometry": {"coordinates":[16.7665348053,48.3444709778],"type":"Point"}
}