{
  "type": "Feature",
  "properties": {
    "addr:full":"Rechbauerstrasse 22 Graz Steiermark 8010",
    "addr:housenumber":"22",
    "addr:postcode":"8010",
    "addr:street":"Rechbauerstrasse",
    "iso:country":"AT",
    "sg:address":"Rechbauerstrasse 22",
    "sg:city":"Graz",
    "sg:orig_category":"Immobilien U Baugewerbe, Architektur U Design",
    "sg:phone":"+43 4331 6831968",
    "sg:postcode":"8010",
    "sg:province":"Steiermark",
    "sg:website":"homepage.sime.com/jkollegger/",
    "wof:name":"Architekt Joe W. Kollegger",
    "wof:placetype":"venue"
},
  "geometry": {"coordinates":[15.4523410797,47.068775177],"type":"Point"}
}