{
  "type": "Feature",
  "properties": {
    "iso:country":"AT",
    "sg:address":"Andechsstr 52d",
    "sg:city":"Innsbruck",
    "sg:orig_category":"Psychotherapie",
    "sg:phone":"+43 512 395774",
    "sg:postcode":"6020",
    "sg:province":"Tirol",
    "wof:name":"Laimb\u00f6ck Annemarie Dr",
    "wof:placetype":"venue"
},
  "geometry": {"coordinates":[11.4211454391,47.2679901123],"type":"Point"}
}