{
  "type": "Feature",
  "properties": {
    "addr:full":"Ruflinger Str 17 Leonding Ober\u00f6sterreich 4060",
    "addr:postcode":"4060",
    "addr:street":"Str 17",
    "iso:country":"AT",
    "sg:address":"Ruflinger Str 17",
    "sg:city":"Leonding",
    "sg:orig_category":"Physiotherapie",
    "sg:phone":"+43 699 17335566",
    "sg:postcode":"4060",
    "sg:province":"Ober\u00f6sterreich",
    "wof:name":"W\u00f6gerbauer Reinhard",
    "wof:placetype":"venue"
},
  "geometry": {"coordinates":[14.2478046417,48.279750824],"type":"Point"}
}