{
  "type": "Feature",
  "properties": {
    "addr:full":"Kirchenstr 9 Bad Hall Ober\u00f6sterreich 4540",
    "addr:housenumber":"9",
    "addr:postcode":"4540",
    "addr:street":"Kirchenstr",
    "iso:country":"AT",
    "sg:address":"Kirchenstr 9",
    "sg:city":"Bad Hall",
    "sg:orig_category":"Damenmoden",
    "sg:phone":"+43 7258 2237",
    "sg:postcode":"4540",
    "sg:province":"Ober\u00f6sterreich",
    "wof:name":"Moden Thanner",
    "wof:placetype":"venue"
},
  "geometry": {"coordinates":[14.2068710327,48.0357322693],"type":"Point"}
}