{
  "type": "Feature",
  "properties": {
    "addr:full":"Fraueng 1/Im Rathaus Knittelfeld Steiermark 8720",
    "addr:housenumber":"1 / im",
    "addr:postcode":"8720",
    "addr:street":"Fraueng",
    "iso:country":"AT",
    "sg:address":"Fraueng 1/Im Rathaus",
    "sg:city":"Knittelfeld",
    "sg:classifiers":[
        {
            "category":"Organizations",
            "subcategory":"Political Organization",
            "type":"Services"
        }
    ],
    "sg:phone":"+43 4335 1286786",
    "sg:postcode":"8720",
    "sg:province":"Steiermark",
    "sg:tags":[
        "mediation"
    ],
    "wof:name":"K.O.N.S.E.N.S. - Praxisgemeinschaft f Mediation- u Konfliktregelung",
    "wof:placetype":"venue"
},
  "geometry": {"coordinates":[14.8291902542,47.2139434814],"type":"Point"}
}