{
  "type": "Feature",
  "properties": {
    "addr:full":"Feichten 56 Westendorf Tirol 6363",
    "addr:housenumber":"56",
    "addr:postcode":"6363",
    "addr:street":"Feichten;Tirol",
    "iso:country":"AT",
    "sg:address":"Feichten 56",
    "sg:city":"Westendorf",
    "sg:orig_category":"Pensionen / Privatzimmer",
    "sg:phone":"+43 5334 6253",
    "sg:postcode":"6363",
    "sg:province":"Tirol",
    "wof:name":"Krimbacher Anneliese",
    "wof:placetype":"venue"
},
  "geometry": {"coordinates":[12.1992712021,47.4373588562],"type":"Point"}
}