{
  "type": "Feature",
  "properties": {
    "iso:country":"AT",
    "sg:address":"G\u00e4rtnerstrasse 5",
    "sg:city":"Buchkirchen",
    "sg:classifiers":[
        {
            "category":"Communications",
            "type":"Services"
        }
    ],
    "sg:phone":"+43 7243 54450",
    "sg:postcode":"4611",
    "sg:province":"Ober\u00f6sterreich",
    "sg:tags":[
        "translation"
    ],
    "sg:website":"ehmeier.at",
    "wof:name":"Mag. Liselotte Ehmeier",
    "wof:placetype":"venue"
},
  "geometry": {"coordinates":[14.0194101334,48.22315979],"type":"Point"}
}