{
  "type": "Feature",
  "properties": {
    "iso:country":"AT",
    "sg:address":"Hauptpl 7",
    "sg:city":"Judenburg",
    "sg:orig_category":"Glasereien",
    "sg:phone":"+43 4335 7282140",
    "sg:postcode":"8750",
    "sg:province":"Steiermark",
    "wof:name":"Prebio Ingeborg",
    "wof:placetype":"venue"
},
  "geometry": {"coordinates":[14.6612949371,47.1689758301],"type":"Point"}
}