{
  "type": "Feature",
  "properties": {
    "iso:country":"AT",
    "sg:address":"Hernstorferstrasse 27/22",
    "sg:city":"Wien",
    "sg:orig_category":"Bildung And Forschung, Sonstiges Zu Bildung U Forschung",
    "sg:phone":"+43 1 9146000",
    "sg:postcode":"1140",
    "sg:province":"Wien",
    "sg:website":"http://www.somcon.com",
    "wof:name":"SOMCON",
    "wof:placetype":"venue"
},
  "geometry": {"coordinates":[16.2884216309,48.1978569031],"type":"Point"}
}