{
  "type": "Feature",
  "properties": {
    "addr:full":"Ringstr 41 Wels Ober\u00f6sterreich 4600",
    "addr:housenumber":"41",
    "addr:postcode":"4600",
    "addr:street":"Ringstr;Oberoesterreich",
    "iso:country":"AT",
    "sg:address":"Ringstr 41",
    "sg:city":"Wels",
    "sg:orig_category":"Geschenkartikel",
    "sg:phone":"+43 7242 207810",
    "sg:postcode":"4600",
    "sg:province":"Ober\u00f6sterreich",
    "wof:name":"Ursuladen",
    "wof:placetype":"venue"
},
  "geometry": {"coordinates":[14.0264806747,48.1592407227],"type":"Point"}
}