{
  "type": "Feature",
  "properties": {
    "addr:full":"Arlbergstr. 15  Dornbirn Vorarlberg 6850",
    "addr:housenumber":"15",
    "addr:postcode":"6850",
    "addr:street":"Arlbergstr.",
    "iso:country":"AT",
    "sg:address":"Arlbergstr. 15 ",
    "sg:city":"Dornbirn",
    "sg:classifiers":[
        {
            "category":"Banks & Credit Unions",
            "subcategory":"Financial Services",
            "type":"Services"
        }
    ],
    "sg:phone":"+43 4355 7237430",
    "sg:postcode":"6850",
    "sg:province":"Vorarlberg",
    "sg:tags":[
        "banking",
        "finance",
        "insurance"
    ],
    "wof:name":"DONAU ALLGEMEINE VERSICHERUNGS AG",
    "wof:placetype":"venue"
},
  "geometry": {"coordinates":[9.7369356155,47.4008369446],"type":"Point"}
}