{
  "type": "Feature",
  "properties": {
    "iso:country":"AT",
    "sg:address":"Quellenstr 4",
    "sg:city":"Hausmening",
    "sg:orig_category":"Innenarchitekten",
    "sg:phone":"+43 699 10408520",
    "sg:postcode":"3363",
    "sg:province":"Nieder\u00f6sterreich",
    "wof:name":"Praher Herbert Innenarchitekt H.R.B.T. - Konzept-Design",
    "wof:placetype":"venue"
},
  "geometry": {"coordinates":[14.8137149811,48.0781707764],"type":"Point"}
}