{
  "type": "Feature",
  "properties": {
    "addr:full":"St. Gertraud K\u00e4rnten 9413",
    "addr:postcode":"9413",
    "iso:country":"AT",
    "sg:city":"St. Gertraud",
    "sg:orig_category":"Non-Classified Establishments",
    "sg:phone":"+43 4352 71732",
    "sg:postcode":"9413",
    "sg:province":"K\u00e4rnten",
    "wof:name":"Pfarramt",
    "wof:placetype":"venue"
},
  "geometry": {"coordinates":[14.8722267151,46.864616394],"type":"Point"}
}