{
  "type": "Feature",
  "properties": {
    "addr:full":"M\u00fcllerbachstr 27 Gschwandt Ober\u00f6sterreich 4816",
    "addr:housenumber":"27",
    "addr:postcode":"4816",
    "addr:street":"Muellerbachstr",
    "iso:country":"AT",
    "sg:address":"M\u00fcllerbachstr 27",
    "sg:city":"Gschwandt",
    "sg:orig_category":"Drehereien",
    "sg:phone":"+43 4376 12654190",
    "sg:postcode":"4816",
    "sg:province":"Ober\u00f6sterreich",
    "wof:name":"MEKUTECH Metall- u Kunststofftechnologie GmbH",
    "wof:placetype":"venue"
},
  "geometry": {"coordinates":[13.8447246552,47.9346351624],"type":"Point"}
}