{
  "type": "Feature",
  "properties": {
    "addr:full":"Klein Veitschstr 2 Dorf Veitsch Steiermark 8663",
    "addr:housenumber":"2",
    "addr:postcode":"8663",
    "addr:street":"Klein Veitschstr",
    "iso:country":"AT",
    "sg:address":"Klein Veitschstr 2",
    "sg:city":"Dorf Veitsch",
    "sg:orig_category":"Papier- U Schreibwaren / Einzelhandel",
    "sg:phone":"+43 3856 2319",
    "sg:postcode":"8663",
    "sg:province":"Steiermark",
    "wof:name":"Leodolter Christian",
    "wof:placetype":"venue"
},
  "geometry": {"coordinates":[15.5020503998,47.5673103333],"type":"Point"}
}