{
  "type": "Feature",
  "properties": {
    "addr:full":"Thaya Park 16 Laa an der Thaya Nieder\u00f6sterreich 2136",
    "addr:housenumber":"16",
    "addr:postcode":"2136",
    "addr:street":"Thaya Park",
    "iso:country":"AT",
    "sg:address":"Thaya Park 16",
    "sg:city":"Laa an der Thaya",
    "sg:classifiers":[
        {
            "category":"Professional",
            "subcategory":"Printing & Photocopies",
            "type":"Services"
        }
    ],
    "sg:phone":"+43 2522 2202",
    "sg:postcode":"2136",
    "sg:province":"Nieder\u00f6sterreich",
    "sg:tags":[
        "offset"
    ],
    "wof:name":"Laadruck - Christian Speck",
    "wof:placetype":"venue"
},
  "geometry": {"coordinates":[16.3749103546,48.71434021],"type":"Point"}
}