{
  "type": "Feature",
  "properties": {
    "addr:full":"Markt 4 Klaffer am Hochficht Ober\u00f6sterreich 4163",
    "addr:housenumber":"4",
    "addr:postcode":"4163",
    "addr:street":"Markt",
    "iso:country":"AT",
    "sg:address":"Markt 4",
    "sg:city":"Klaffer am Hochficht",
    "sg:orig_category":"Banken U Sparkassen",
    "sg:phone":"+43 4372 886594",
    "sg:postcode":"4163",
    "sg:province":"Ober\u00f6sterreich",
    "wof:name":"Raiffeisenbank B\u00f6hmerwald regGenmbH",
    "wof:placetype":"venue"
},
  "geometry": {"coordinates":[13.8818359375,48.6953315735],"type":"Point"}
}