{
  "type": "Feature",
  "properties": {
    "iso:country":"AT",
    "sg:address":"Kircheng 22",
    "sg:city":"Bruck an der Leitha",
    "sg:orig_category":"Raumgestaltung",
    "sg:phone":"+43 2162 62501",
    "sg:postcode":"2460",
    "sg:province":"Nieder\u00f6sterreich",
    "wof:name":"Svenoha Alfred jun",
    "wof:placetype":"venue"
},
  "geometry": {"coordinates":[16.7778282166,48.023109436],"type":"Point"}
}