{
  "type": "Feature",
  "properties": {
    "iso:country":"AT",
    "sg:address":"Postplattenstr 5",
    "sg:city":"Hof",
    "sg:orig_category":"Volksschulen",
    "sg:phone":"+43 6229 2269",
    "sg:postcode":"5322",
    "sg:province":"Salzburg",
    "wof:name":"Volksschule",
    "wof:placetype":"venue"
},
  "geometry": {"coordinates":[13.2131595612,47.8199005127],"type":"Point"}
}