{
  "type": "Feature",
  "properties": {
    "addr:full":"Pamperlallee 35-37 Krumpendorf K\u00e4rnten 9201",
    "addr:postcode":"35-37;9201",
    "addr:street":"Pamperlallee",
    "iso:country":"AT",
    "sg:address":"Pamperlallee 35-37",
    "sg:city":"Krumpendorf",
    "sg:orig_category":"Fahrradverleih",
    "sg:phone":"+43 4342 292155",
    "sg:postcode":"9201",
    "sg:province":"K\u00e4rnten",
    "wof:name":"Fahrradverleih-Parkbad",
    "wof:placetype":"venue"
},
  "geometry": {"coordinates":[14.216137886,46.6221084595],"type":"Point"}
}