{
  "type": "Feature",
  "properties": {
    "addr:full":"Seestr 1 Gr\u00e4n Tirol 6673",
    "addr:housenumber":"1",
    "addr:postcode":"6673",
    "addr:street":"Seestr;Tirol",
    "iso:country":"AT",
    "sg:address":"Seestr 1",
    "sg:city":"Gr\u00e4n",
    "sg:orig_category":"Molkereien U Molkereiprodukte",
    "sg:phone":"+43 4356 756463",
    "sg:postcode":"6673",
    "sg:province":"Tirol",
    "wof:name":"Biedermann Otto HandelsgesmbH & Co KG",
    "wof:placetype":"venue"
},
  "geometry": {"coordinates":[10.5594797134,47.4942398071],"type":"Point"}
}