{
  "type": "Feature",
  "properties": {
    "addr:full":"Gumpendorfer Str 81 Wien Wien 1060",
    "addr:postcode":"1060",
    "addr:street":"Str 81",
    "iso:country":"AT",
    "sg:address":"Gumpendorfer Str 81",
    "sg:city":"Wien",
    "sg:orig_category":"Friseure U Frisiersalons",
    "sg:phone":"+43 1 5968766",
    "sg:postcode":"1060",
    "sg:province":"Wien",
    "wof:name":"Martineo Gerald",
    "wof:placetype":"venue"
},
  "geometry": {"coordinates":[16.3498935699,48.1938247681],"type":"Point"}
}