{
  "type": "Feature",
  "properties": {
    "addr:full":"Sigmund-Nachbaur-Str 2 Rankweil Vorarlberg 6830",
    "addr:housenumber":"2",
    "addr:postcode":"6830",
    "addr:street":"Sigmund-Nachbaur-Str",
    "iso:country":"AT",
    "sg:address":"Sigmund-Nachbaur-Str 2",
    "sg:city":"Rankweil",
    "sg:orig_category":"Optiker",
    "sg:phone":"+43 5522 43104",
    "sg:postcode":"6830",
    "sg:province":"Vorarlberg",
    "wof:name":"M\u00fcller Optik",
    "wof:placetype":"venue"
},
  "geometry": {"coordinates":[9.6102304459,47.2801742554],"type":"Point"}
}