{
  "type": "Feature",
  "properties": {
    "iso:country":"AT",
    "sg:address":"Nr 78",
    "sg:city":"Sipbachzell",
    "sg:orig_category":"Tischlereien",
    "sg:phone":"+43 7240 8272",
    "sg:postcode":"4621",
    "sg:province":"Ober\u00f6sterreich",
    "wof:name":"Lederhilger J GmbH - Portas Fachbetrieb",
    "wof:placetype":"venue"
},
  "geometry": {"coordinates":[14.1100311279,48.0970726013],"type":"Point"}
}