{
  "type": "Feature",
  "properties": {
    "addr:full":"Bambergerstr 4 Wolfsberg K\u00e4rnten 9400",
    "addr:housenumber":"4;kaernten",
    "addr:postcode":"9400",
    "addr:street":"Bambergerstr",
    "iso:country":"AT",
    "sg:address":"Bambergerstr 4",
    "sg:city":"Wolfsberg",
    "sg:classifiers":[
        {
            "category":"Retail",
            "subcategory":"Event Space",
            "type":"Services"
        }
    ],
    "sg:phone":"+43 4352 2536",
    "sg:postcode":"9400",
    "sg:province":"K\u00e4rnten",
    "sg:tags":[
        "hand-",
        "u",
        "fu\u00c3\u0178pflege"
    ],
    "wof:name":"Kosmetik-Fu\u00dfpflege Traudl",
    "wof:placetype":"venue"
},
  "geometry": {"coordinates":[14.8418922424,46.8403396606],"type":"Point"}
}