{
  "type": "Feature",
  "properties": {
    "addr:full":"Strau\u00dfg 14 Leoben Steiermark 8700",
    "addr:housenumber":"14",
    "addr:postcode":"8700",
    "addr:street":"Straussg",
    "iso:country":"AT",
    "sg:address":"Strau\u00dfg 14",
    "sg:city":"Leoben",
    "sg:orig_category":"Damenmoden",
    "sg:phone":"+43 3842 424130",
    "sg:postcode":"8700",
    "sg:province":"Steiermark",
    "wof:name":"MISS MELONE",
    "wof:placetype":"venue"
},
  "geometry": {"coordinates":[15.093378067,47.3803901672],"type":"Point"}
}