{
  "type": "Feature",
  "properties": {
    "iso:country":"AT",
    "sg:address":"Botanikerstr 11",
    "sg:city":"Innsbruck",
    "sg:orig_category":"Handelsagenturen",
    "sg:phone":"+43 512 273354",
    "sg:postcode":"6020",
    "sg:province":"Tirol",
    "wof:name":"Stimpfl Christa und Alfred",
    "wof:placetype":"venue"
},
  "geometry": {"coordinates":[11.3812971115,47.2676544189],"type":"Point"}
}