{
  "type": "Feature",
  "properties": {
    "addr:full":"Nr 51 M\u00fcnichreith am Ostrong Nieder\u00f6sterreich 3662",
    "addr:postcode":"3662",
    "addr:street":"Nr 51;Am Ostrong",
    "iso:country":"AT",
    "sg:address":"Nr 51",
    "sg:city":"M\u00fcnichreith am Ostrong",
    "sg:orig_category":"Transportunternehmen",
    "sg:phone":"+43 7413 7722",
    "sg:postcode":"3662",
    "sg:province":"Nieder\u00f6sterreich",
    "wof:name":"Jagsch Johann",
    "wof:placetype":"venue"
},
  "geometry": {"coordinates":[116.8501205444,25.5747890472],"type":"Point"}
}