{
  "type": "Feature",
  "properties": {
    "addr:full":"L\u00e4ngenfeldg 3-5 Wien Wien 1120",
    "addr:housenumber":"3-5",
    "addr:postcode":"1120",
    "addr:street":"Laengenfeldg",
    "iso:country":"AT",
    "sg:address":"L\u00e4ngenfeldg 3-5",
    "sg:city":"Wien",
    "sg:orig_category":"Lebensmittel / Einzelhandel",
    "sg:phone":"+43 1 8102921",
    "sg:postcode":"1120",
    "sg:province":"Wien",
    "wof:name":"EMMA Otto",
    "wof:placetype":"venue"
},
  "geometry": {"coordinates":[16.3362312317,48.1845169067],"type":"Point"}
}