{
  "type": "Feature",
  "properties": {
    "addr:full":"Niedenau 61 - 63 60325",
    "addr:housenumber":"61 63",
    "addr:postcode":"60325",
    "addr:street":"Niedenau",
    "iso:country":"AT",
    "sg:address":"Niedenau 61 - 63",
    "sg:orig_category":"Immobilien U Baugewerbe, Sonstige Immobiliendienstleistungen",
    "sg:phone":"+43 697 191370",
    "sg:postcode":"60325",
    "sg:website":"http://www.ghgmbh.de",
    "wof:name":"Gesellschaft f\u00fcr Haus- und Grundbesitz m.b.H.",
    "wof:placetype":"venue"
},
  "geometry": {"coordinates":[8.6665210724,50.1159744263],"type":"Point"}
}