{
  "type": "Feature",
  "properties": {
    "iso:country":"AT",
    "sg:address":"Technikerstr 4",
    "sg:city":"Graz",
    "sg:orig_category":"Bibliotheken",
    "sg:phone":"+43 4331 68736151",
    "sg:postcode":"8010",
    "sg:province":"Steiermark",
    "wof:name":"Universit\u00e4tsbibliothek d Technischen Universit\u00e4t Graz",
    "wof:placetype":"venue"
},
  "geometry": {"coordinates":[15.450381279,47.0683059692],"type":"Point"}
}