{
  "type": "Feature",
  "properties": {
    "addr:full":"Kurgartenstr 29 Bad Hofgastein Salzburg 5630",
    "addr:housenumber":"29",
    "addr:postcode":"5630",
    "addr:street":"Kurgartenstr;Salzburg",
    "iso:country":"AT",
    "sg:address":"Kurgartenstr 29",
    "sg:city":"Bad Hofgastein",
    "sg:orig_category":"Freizeit- U Sportbekleidung",
    "sg:phone":"+43 4364 3264420",
    "sg:postcode":"5630",
    "sg:province":"Salzburg",
    "wof:name":"Sporthaus Patzner",
    "wof:placetype":"venue"
},
  "geometry": {"coordinates":[13.101395607,47.1703681946],"type":"Point"}
}