{
  "type": "Feature",
  "properties": {
    "iso:country":"AT",
    "sg:address":"Nr 161",
    "sg:city":"Paldau",
    "sg:orig_category":"Lebensmittel / Einzelhandel",
    "sg:phone":"+43 4331 502205",
    "sg:postcode":"8341",
    "sg:province":"Steiermark",
    "wof:name":"Rossmann Johann",
    "wof:placetype":"venue"
},
  "geometry": {"coordinates":[15.7963991165,46.9407424927],"type":"Point"}
}