{
  "type": "Feature",
  "properties": {
    "addr:full":"Kinkstr 29 Kufstein Tirol 6330",
    "addr:housenumber":"29",
    "addr:postcode":"6330",
    "addr:street":"Kinkstr;Tirol",
    "iso:country":"AT",
    "sg:address":"Kinkstr 29",
    "sg:city":"Kufstein",
    "sg:orig_category":"Tankstellen",
    "sg:phone":"+43 4353 7262981",
    "sg:postcode":"6330",
    "sg:province":"Tirol",
    "wof:name":"AVANTI TankstellenbetriebsgesmbH",
    "wof:placetype":"venue"
},
  "geometry": {"coordinates":[12.1683826447,47.5790710449],"type":"Point"}
}