{
  "type": "Feature",
  "properties": {
    "addr:full":"Hauptstr 17 Kaisersdorf Burgenland 7342",
    "addr:housenumber":"17",
    "addr:postcode":"7342",
    "addr:street":"Hauptstr",
    "iso:country":"AT",
    "sg:address":"Hauptstr 17",
    "sg:city":"Kaisersdorf",
    "sg:orig_category":"Volksschulen",
    "sg:phone":"+43 2617 2934",
    "sg:postcode":"7342",
    "sg:province":"Burgenland",
    "wof:name":"Volksschule",
    "wof:placetype":"venue"
},
  "geometry": {"coordinates":[16.3930473328,47.5369186401],"type":"Point"}
}