{
  "type": "Feature",
  "properties": {
    "addr:full":"Ungarg 18 Wiener Neustadt Nieder\u00f6sterreich 2700",
    "addr:housenumber":"18",
    "addr:postcode":"2700",
    "addr:street":"Ungarg",
    "iso:country":"AT",
    "sg:address":"Ungarg 18",
    "sg:city":"Wiener Neustadt",
    "sg:orig_category":"Garagen Parkgaragen",
    "sg:phone":"+43 2622 373459",
    "sg:postcode":"2700",
    "sg:province":"Nieder\u00f6sterreich",
    "wof:name":"Ungar-Garage",
    "wof:placetype":"venue"
},
  "geometry": {"coordinates":[16.2491855621,47.8124580383],"type":"Point"}
}