{
  "type": "Feature",
  "properties": {
    "addr:full":"Nr 1 Sandl Ober\u00f6sterreich 4251",
    "addr:postcode":"4251",
    "addr:street":"Nr;Sandl Oberoesterreich",
    "iso:country":"AT",
    "sg:address":"Nr 1",
    "sg:city":"Sandl",
    "sg:orig_category":"Non-Classified Establishments",
    "sg:phone":"+43 7944 8220",
    "sg:postcode":"4251",
    "sg:province":"Ober\u00f6sterreich",
    "wof:name":"Pfarramt",
    "wof:placetype":"venue"
},
  "geometry": {"coordinates":[14.6452903748,48.5599403381],"type":"Point"}
}