{
  "type": "Feature",
  "properties": {
    "addr:full":"Hauptstr 77 Gie\u00dfh\u00fcbl Nieder\u00f6sterreich 2372",
    "addr:housenumber":"77",
    "addr:postcode":"2372",
    "addr:street":"Hauptstr;Niederoesterreich",
    "iso:country":"AT",
    "sg:address":"Hauptstr 77",
    "sg:city":"Gie\u00dfh\u00fcbl",
    "sg:orig_category":"Banken U Sparkassen",
    "sg:phone":"+43 4322 36451530",
    "sg:postcode":"2372",
    "sg:province":"Nieder\u00f6sterreich",
    "wof:name":"Raiffeisenbank Perchtoldsdorf-Maria Enzersdorf regGenmbH",
    "wof:placetype":"venue"
},
  "geometry": {"coordinates":[16.3687992096,48.2025413513],"type":"Point"}
}