{
  "type": "Feature",
  "properties": {
    "addr:full":"Persal 225 Finkenberg Tirol 6292",
    "addr:housenumber":"225",
    "addr:postcode":"6292",
    "addr:street":"Persal",
    "iso:country":"AT",
    "sg:address":"Persal 225",
    "sg:city":"Finkenberg",
    "sg:orig_category":"Feuerwehren",
    "sg:phone":"+43 5285 63442",
    "sg:postcode":"6292",
    "sg:province":"Tirol",
    "wof:name":"Freiwillige Feuerwehr Finkenberg",
    "wof:placetype":"venue"
},
  "geometry": {"coordinates":[11.819475174,47.1515960693],"type":"Point"}
}