{
  "type": "Feature",
  "properties": {
    "addr:full":"Hauptstr 2 Niederkreuzstetten Nieder\u00f6sterreich 2124",
    "addr:housenumber":"2",
    "addr:postcode":"2124",
    "addr:street":"Hauptstr",
    "iso:country":"AT",
    "sg:address":"Hauptstr 2",
    "sg:city":"Niederkreuzstetten",
    "sg:orig_category":"Feuerwehren",
    "sg:phone":"+43 2263 8587",
    "sg:postcode":"2124",
    "sg:province":"Nieder\u00f6sterreich",
    "wof:name":"Freiwillige Feuerwehr Kreuzstetten",
    "wof:placetype":"venue"
},
  "geometry": {"coordinates":[16.4765090942,48.4806404114],"type":"Point"}
}