{
  "type": "Feature",
  "properties": {
    "addr:full":"Ziegelbrennerstr 20 Radstadt Salzburg 5550",
    "addr:housenumber":"20",
    "addr:postcode":"5550",
    "addr:street":"Ziegelbrennerstr;Salzburg",
    "iso:country":"AT",
    "sg:address":"Ziegelbrennerstr 20",
    "sg:city":"Radstadt",
    "sg:orig_category":"Maler, Anstreicher U Lackierer",
    "sg:phone":"+43 6452 6532",
    "sg:postcode":"5550",
    "sg:province":"Salzburg",
    "wof:name":"Laiminger Helmut",
    "wof:placetype":"venue"
},
  "geometry": {"coordinates":[13.4759788513,47.3813743591],"type":"Point"}
}