{
  "type": "Feature",
  "properties": {
    "addr:full":"In der Hagenau 7 Wien Wien 1130",
    "addr:housenumber":"7",
    "addr:postcode":"1130",
    "addr:street":"In Der Hagenau",
    "iso:country":"AT",
    "sg:address":"In der Hagenau 7",
    "sg:city":"Wien",
    "sg:orig_category":"Sprachschulen U -Unterricht",
    "sg:phone":"+43 1 8797548",
    "sg:postcode":"1130",
    "sg:province":"Wien",
    "wof:name":"English Language Centre Hietzing",
    "wof:placetype":"venue"
},
  "geometry": {"coordinates":[16.272310257,48.1798095703],"type":"Point"}
}