{
  "type": "Feature",
  "properties": {
    "addr:full":"Hauptstr.  9",
    "addr:housenumber":"9",
    "addr:street":"Hauptstr.",
    "iso:country":"AT",
    "sg:address":"Hauptstr. ",
    "sg:classifiers":[
        {
            "category":"Banks & Credit Unions",
            "subcategory":"Bank",
            "type":"Services"
        }
    ],
    "sg:phone":"+43 2612 2193",
    "sg:postcode":"9",
    "wof:name":"Hypo-Bank Burgenland",
    "wof:placetype":"venue"
},
  "geometry": {"coordinates":[16.5055484772,47.5010795593],"type":"Point"}
}