{
  "type": "Feature",
  "properties": {
    "addr:full":"Ungarg 27 Wiener Neustadt Nieder\u00f6sterreich 2700",
    "addr:housenumber":"27",
    "addr:postcode":"2700",
    "addr:street":"Ungarg",
    "iso:country":"AT",
    "sg:address":"Ungarg 27",
    "sg:city":"Wiener Neustadt",
    "sg:orig_category":"Restaurants: Chinesisch",
    "sg:phone":"+43 2622 22779",
    "sg:postcode":"2700",
    "sg:province":"Nieder\u00f6sterreich",
    "wof:name":"China-Restaurant Hong Kong",
    "wof:placetype":"venue"
},
  "geometry": {"coordinates":[16.2496623993,47.8125991821],"type":"Point"}
}