{
  "type": "Feature",
  "properties": {
    "iso:country":"AT",
    "sg:address":"Schlo\u00dfg 6-8",
    "sg:city":"Bruck an der Leitha",
    "sg:classifiers":[
        {
            "category":"Government",
            "subcategory":"Post Office",
            "type":"Public Place"
        }
    ],
    "sg:phone":"+43 4321 6268196",
    "sg:postcode":"2460",
    "sg:province":"Nieder\u00f6sterreich",
    "sg:tags":[
        "-handel",
        "tierzucht",
        "u"
    ],
    "wof:name":"Lipizzanerhof",
    "wof:placetype":"venue"
},
  "geometry": {"coordinates":[16.7814273834,48.0247917175],"type":"Point"}
}