{
  "type": "Feature",
  "properties": {
    "iso:country":"AT",
    "sg:address":"Seblas 30",
    "sg:city":"Matrei in Osttirol",
    "sg:classifiers":[
        {
            "category":"Restaurant",
            "type":"Food & Drink"
        }
    ],
    "sg:phone":"+43 4875 5363",
    "sg:postcode":"9971",
    "sg:province":"Tirol",
    "wof:name":"Restaurant Malham",
    "wof:placetype":"venue"
},
  "geometry": {"coordinates":[12.5496110916,46.9851760864],"type":"Point"}
}