{
  "type": "Feature",
  "properties": {
    "addr:full":"Bahnhofstr 8 Vils Tirol 6682",
    "addr:housenumber":"8",
    "addr:postcode":"6682",
    "addr:street":"Bahnhofstr;Tirol",
    "iso:country":"AT",
    "sg:address":"Bahnhofstr 8",
    "sg:city":"Vils",
    "sg:orig_category":"Polizei U Gendarmerie",
    "sg:phone":"+43 4359 1337156",
    "sg:postcode":"6682",
    "sg:province":"Tirol",
    "wof:name":"Gendarmerie",
    "wof:placetype":"venue"
},
  "geometry": {"coordinates":[10.6319265366,47.5483474731],"type":"Point"}
}