{
  "type": "Feature",
  "properties": {
    "addr:full":"Pichlerg 22 Liebenau Steiermark 8041",
    "addr:housenumber":"22",
    "addr:postcode":"8041",
    "addr:street":"Pichlerg",
    "iso:country":"AT",
    "sg:address":"Pichlerg 22",
    "sg:city":"Liebenau",
    "sg:orig_category":"Sportanlagen",
    "sg:phone":"+43 316 462780",
    "sg:postcode":"8041",
    "sg:province":"Steiermark",
    "wof:name":"Sportcenter Graz",
    "wof:placetype":"venue"
},
  "geometry": {"coordinates":[15.4439239502,47.0433959961],"type":"Point"}
}