{
  "type": "Feature",
  "properties": {
    "addr:full":"Grazer Vorstadt 120a Voitsberg Steiermark 8570",
    "addr:housenumber":"120a",
    "addr:postcode":"8570",
    "addr:street":"Grazer Vorstadt",
    "iso:country":"AT",
    "sg:address":"Grazer Vorstadt 120a",
    "sg:city":"Voitsberg",
    "sg:orig_category":"Metallbau",
    "sg:phone":"+43 3142 255900",
    "sg:postcode":"8570",
    "sg:province":"Steiermark",
    "wof:name":"Schuster Metallbau GesmbH",
    "wof:placetype":"venue"
},
  "geometry": {"coordinates":[15.1664009094,47.0385818481],"type":"Point"}
}