{
  "type": "Feature",
  "properties": {
    "iso:country":"AT",
    "sg:address":"Praterstr 40/20",
    "sg:city":"Wien",
    "sg:orig_category":"Umwelttechnik",
    "sg:phone":"+43 1 21495200",
    "sg:postcode":"1020",
    "sg:province":"Wien",
    "wof:name":"UV & P Umweltmanagement-Verfahrenstechnik Neubacher & Partner GesmbH",
    "wof:placetype":"venue"
},
  "geometry": {"coordinates":[16.3853664398,48.2150650024],"type":"Point"}
}