{
  "type": "Feature",
  "properties": {
    "iso:country":"AT",
    "sg:address":"Brucker Bundesstr 100",
    "sg:city":"Zell am See",
    "sg:orig_category":"Tabaktrafiken",
    "sg:phone":"+43 6542 574914",
    "sg:postcode":"5700",
    "sg:province":"Salzburg",
    "wof:name":"Anderle Gerwald",
    "wof:placetype":"venue"
},
  "geometry": {"coordinates":[121.5151977539,25.0351200104],"type":"Point"}
}