{
  "type": "Feature",
  "properties": {
    "addr:full":"Andorf Ober\u00f6sterreich 4770",
    "addr:postcode":"4770",
    "iso:country":"AT",
    "sg:city":"Andorf",
    "sg:orig_category":"Feuerwehren",
    "sg:phone":"+43 7766 2838",
    "sg:postcode":"4770",
    "sg:province":"Ober\u00f6sterreich",
    "wof:name":"Freiwillige Feuerwehr Linden",
    "wof:placetype":"venue"
},
  "geometry": {"coordinates":[13.5837945938,48.3395233154],"type":"Point"}
}