{
  "type": "Feature",
  "properties": {
    "addr:full":"Hauptstr 75/2 Oggau Burgenland 7063",
    "addr:housenumber":"75 / 2",
    "addr:postcode":"7063",
    "addr:street":"Hauptstr;Oggau",
    "iso:country":"AT",
    "sg:address":"Hauptstr 75/2",
    "sg:city":"Oggau",
    "sg:orig_category":"Fu\u00c3\u0178pflege U Fu\u00c3\u0178pflegesalons",
    "sg:phone":"+43 664 4037153",
    "sg:postcode":"7063",
    "sg:province":"Burgenland",
    "wof:name":"Amtmann Mobile Fusspflege",
    "wof:placetype":"venue"
},
  "geometry": {"coordinates":[16.6622886658,47.8314361572],"type":"Point"}
}