{
  "type": "Feature",
  "properties": {
    "addr:full":"Birkenweg 727 Seefeld in Tirol Tirol 6100",
    "addr:housenumber":"727",
    "addr:postcode":"6100",
    "addr:street":"Birkenweg;Tirol",
    "iso:country":"AT",
    "sg:address":"Birkenweg 727",
    "sg:city":"Seefeld in Tirol",
    "sg:orig_category":"Appartements / Ferienwohnungen",
    "sg:phone":"+43 5212 2113",
    "sg:postcode":"6100",
    "sg:province":"Tirol",
    "wof:name":"Haus Annelies",
    "wof:placetype":"venue"
},
  "geometry": {"coordinates":[11.1941146851,47.328338623],"type":"Point"}
}