{
  "type": "Feature",
  "properties": {
    "iso:country":"AT",
    "sg:address":"Hauptstr 46",
    "sg:city":"Gschwandt",
    "sg:orig_category":"Autohandel",
    "sg:phone":"+43 7612626020",
    "sg:postcode":"4816",
    "sg:province":"Ober\u00f6sterreich",
    "wof:name":"Hummer GmbH & Co KG",
    "wof:placetype":"venue"
},
  "geometry": {"coordinates":[13.8507862091,47.9382667542],"type":"Point"}
}