{
  "type": "Feature",
  "properties": {
    "addr:full":"Karmeliterpl 8 Graz Steiermark 8010",
    "addr:housenumber":"8",
    "addr:postcode":"8010",
    "addr:street":"Karmeliterpl",
    "iso:country":"AT",
    "sg:address":"Karmeliterpl 8",
    "sg:city":"Graz",
    "sg:orig_category":"Friseure U Frisiersalons",
    "sg:phone":"+43 4331 6827379",
    "sg:postcode":"8010",
    "sg:province":"Steiermark",
    "wof:name":"Hair-Style Paul Mitchell",
    "wof:placetype":"venue"
},
  "geometry": {"coordinates":[15.4401788712,47.0737533569],"type":"Point"}
}