{
  "type": "Feature",
  "properties": {
    "addr:full":"Marktler Str 25 Lilienfeld Nieder\u00f6sterreich 3180",
    "addr:housenumber":"25",
    "addr:postcode":"3180",
    "addr:street":"Str",
    "iso:country":"AT",
    "sg:address":"Marktler Str 25",
    "sg:city":"Lilienfeld",
    "sg:orig_category":"Offsetdruckereien",
    "sg:phone":"+43 2762 53507",
    "sg:postcode":"3180",
    "sg:province":"Nieder\u00f6sterreich",
    "wof:name":"Waschhofer Leopold",
    "wof:placetype":"venue"
},
  "geometry": {"coordinates":[15.6006002426,48.0225982666],"type":"Point"}
}