{
  "type": "Feature",
  "properties": {
    "addr:full":"Nr 77b Gries im Sellrain Tirol 6182",
    "addr:housenumber":"77b",
    "addr:postcode":"6182",
    "addr:street":"Nr;Tirol",
    "iso:country":"AT",
    "sg:address":"Nr 77b",
    "sg:city":"Gries im Sellrain",
    "sg:orig_category":"Tischlereien",
    "sg:phone":"+43 5236 492",
    "sg:postcode":"6182",
    "sg:province":"Tirol",
    "wof:name":"P & B Tischler Team GesmbH",
    "wof:placetype":"venue"
},
  "geometry": {"coordinates":[11.100684166,47.2032012939],"type":"Point"}
}