{
  "type": "Feature",
  "properties": {
    "iso:country":"AT",
    "sg:address":"Dorfstr 64",
    "sg:city":"St. Anton am Arlberg",
    "sg:orig_category":"Drogerien",
    "sg:phone":"+43 5446 2191",
    "sg:postcode":"6580",
    "sg:province":"Tirol",
    "wof:name":"Drogerie-Reform",
    "wof:placetype":"venue"
},
  "geometry": {"coordinates":[10.2672595978,47.1302909851],"type":"Point"}
}