{
  "type": "Feature",
  "properties": {
    "addr:full":"Dorfstr 64 St. Anton am Arlberg Tirol 6580",
    "addr:housenumber":"64",
    "addr:postcode":"6580",
    "addr:street":"Dorfstr",
    "iso:country":"AT",
    "sg:address":"Dorfstr 64",
    "sg:city":"St. Anton am Arlberg",
    "sg:orig_category":"Drogerien",
    "sg:phone":"+43 5446 2191",
    "sg:postcode":"6580",
    "sg:province":"Tirol",
    "wof:name":"Drogerie-Reform",
    "wof:placetype":"venue"
},
  "geometry": {"coordinates":[10.2672595978,47.1302909851],"type":"Point"}
}