{
  "type": "Feature",
  "properties": {
    "iso:country":"AT",
    "sg:address":"Arndtstrasse 53",
    "sg:city":"Vienna",
    "sg:classifiers":[
        {
            "category":"Professional",
            "subcategory":"Computer Services",
            "type":"Services"
        }
    ],
    "sg:postcode":"1120",
    "sg:tags":[
        "golf",
        "community",
        "golf-score",
        "score",
        "austria"
    ],
    "sg:website":"http://golfit.at",
    "wof:name":"Golfit.at",
    "wof:placetype":"venue"
},
  "geometry": {"coordinates":[16.3355204,48.1828172],"type":"Point"}
}