{
  "type": "Feature",
  "properties": {
    "addr:full":"Staatsbahnstr 4 Laa an der Thaya Nieder\u00f6sterreich 2136",
    "addr:housenumber":"4",
    "addr:postcode":"2136",
    "addr:street":"Staatsbahnstr",
    "iso:country":"AT",
    "sg:address":"Staatsbahnstr 4",
    "sg:city":"Laa an der Thaya",
    "sg:orig_category":"Lederbekleidung",
    "sg:phone":"+43 2522 84036",
    "sg:postcode":"2136",
    "sg:province":"Nieder\u00f6sterreich",
    "wof:name":"Stuff's",
    "wof:placetype":"venue"
},
  "geometry": {"coordinates":[16.3863391876,48.7202301025],"type":"Point"}
}