{
  "type": "Feature",
  "properties": {
    "addr:full":"Dorf 199 Lech Vorarlberg 6764",
    "addr:housenumber":"199",
    "addr:postcode":"6764",
    "addr:street":"Dorf",
    "iso:country":"AT",
    "sg:address":"Dorf 199",
    "sg:city":"Lech",
    "sg:classifiers":[
        {
            "category":"Restaurant",
            "type":"Food & Drink"
        }
    ],
    "sg:phone":"+43 5583 3741",
    "sg:postcode":"6764",
    "sg:province":"Vorarlberg",
    "wof:name":"Restaurant Bistro Casarole",
    "wof:placetype":"venue"
},
  "geometry": {"coordinates":[10.1413106918,47.207408905],"type":"Point"}
}