{
  "type": "Feature",
  "properties": {
    "addr:full":"Heiligenst\u00e4dter Str 81-87 Wien Wien 1190",
    "addr:postcode":"81-87;1190",
    "addr:street":"Str",
    "iso:country":"AT",
    "sg:address":"Heiligenst\u00e4dter Str 81-87",
    "sg:city":"Wien",
    "sg:orig_category":"Versicherungsunternehmen",
    "sg:phone":"+43 4313 698000",
    "sg:postcode":"1190",
    "sg:province":"Wien",
    "wof:name":"Generali Versicherung AG",
    "wof:placetype":"venue"
},
  "geometry": {"coordinates":[16.3615245819,48.2447853088],"type":"Point"}
}