{
  "type": "Feature",
  "properties": {
    "iso:country":"AT",
    "sg:address":"Werkstrasse 231",
    "sg:city":"Maria Lankowitz",
    "sg:classifiers":[
        {
            "category":"Home & Garden",
            "subcategory":"Building Materials",
            "type":"Retail Goods"
        }
    ],
    "sg:phone":"+43 3144 3428",
    "sg:postcode":"8591",
    "sg:province":"Steiermark",
    "sg:tags":[
        "aluminium",
        "gutter"
    ],
    "wof:name":"Kebau-Bauges.m.b.H.",
    "wof:placetype":"venue"
},
  "geometry": {"coordinates":[15.0626077652,47.0525817871],"type":"Point"}
}