{
  "type": "Feature",
  "properties": {
    "iso:country":"AT",
    "sg:address":"Degengasse 70/3a",
    "sg:city":"Wien",
    "sg:classifiers":[
        {
            "category":"Manufacturing",
            "subcategory":"Tools & Machinery",
            "type":"Manufacturing & Wholesale Goods"
        }
    ],
    "sg:phone":"+43 1 4861387",
    "sg:postcode":"1160",
    "sg:province":"Wien",
    "sg:tags":[
        "bending",
        "press",
        "presses",
        "folding"
    ],
    "wof:name":"F. u. A. Arnold Maschinenbau OHG",
    "wof:placetype":"venue"
},
  "geometry": {"coordinates":[16.3068504333,48.2167663574],"type":"Point"}
}