{
  "type": "Feature",
  "properties": {
    "addr:full":"Taborstrasse  12",
    "addr:housenumber":"12",
    "addr:street":"Taborstrasse",
    "iso:country":"AT",
    "sg:address":"Taborstrasse ",
    "sg:classifiers":[
        {
            "category":"Travel",
            "subcategory":"Travel Agent",
            "type":"Entertainment"
        }
    ],
    "sg:postcode":"12",
    "wof:name":"Best Western Hotel Stefanie",
    "wof:placetype":"venue"
},
  "geometry": {"coordinates":[16.3802165985,48.2143135071],"type":"Point"}
}