{
  "type": "Feature",
  "properties": {
    "addr:full":"Dr. Pfaff G. 5  St. Peter Steiermark 8042",
    "addr:housenumber":"5",
    "addr:postcode":"8042",
    "addr:street":"G.",
    "iso:country":"AT",
    "sg:address":"Dr. Pfaff G. 5 ",
    "sg:city":"St. Peter",
    "sg:classifiers":[
        {
            "category":"Farming",
            "subcategory":"Livestock Farm",
            "type":"Manufacturing & Wholesale Goods"
        }
    ],
    "sg:phone":"+43 4331 6471319",
    "sg:postcode":"8042",
    "sg:province":"Steiermark",
    "sg:tags":[
        "agriculture"
    ],
    "wof:name":"BAUMSCHULE VIELLIEBER",
    "wof:placetype":"venue"
},
  "geometry": {"coordinates":[15.4756803513,47.0525054932],"type":"Point"}
}