{
  "type": "Feature",
  "properties": {
    "addr:full":"Kircheng 23 Haringsee Nieder\u00f6sterreich 2286",
    "addr:housenumber":"23",
    "addr:postcode":"2286",
    "addr:street":"Kircheng",
    "iso:country":"AT",
    "sg:address":"Kircheng 23",
    "sg:city":"Haringsee",
    "sg:orig_category":"Gemeinden",
    "sg:phone":"+43 4322 14840040",
    "sg:postcode":"2286",
    "sg:province":"Nieder\u00f6sterreich",
    "wof:name":"Gemeindeamt Haringsee",
    "wof:placetype":"venue"
},
  "geometry": {"coordinates":[16.7842502594,48.1923217773],"type":"Point"}
}