{
  "type": "Feature",
  "properties": {
    "addr:full":"Nr 17 Studenzen Steiermark 8322",
    "addr:postcode":"8322",
    "addr:street":"Nr",
    "iso:country":"AT",
    "sg:address":"Nr 17",
    "sg:city":"Studenzen",
    "sg:orig_category":"Autoverwertung",
    "sg:phone":"+43 3115 2438",
    "sg:postcode":"8322",
    "sg:province":"Steiermark",
    "wof:name":"Seninger Reinhard",
    "wof:placetype":"venue"
},
  "geometry": {"coordinates":[15.7906103134,47.0232505798],"type":"Point"}
}