{
  "type": "Feature",
  "properties": {
    "addr:full":"Morzger Str 64 Salzburg Salzburg 5020",
    "addr:housenumber":"64",
    "addr:postcode":"5020",
    "addr:street":"Str;Salzburg",
    "iso:country":"AT",
    "sg:address":"Morzger Str 64",
    "sg:city":"Salzburg",
    "sg:orig_category":"Handelsagenturen",
    "sg:phone":"+43 662 833303",
    "sg:postcode":"5020",
    "sg:province":"Salzburg",
    "wof:name":"Vanjin Igor",
    "wof:placetype":"venue"
},
  "geometry": {"coordinates":[13.0581293106,47.7719612122],"type":"Point"}
}