{
  "type": "Feature",
  "properties": {
    "addr:full":"W\u00e4hringer Str 59 Wien Wien 1090",
    "addr:postcode":"1090",
    "addr:street":"Str 59",
    "iso:country":"AT",
    "sg:address":"W\u00e4hringer Str 59",
    "sg:city":"Wien",
    "sg:classifiers":[
        {
            "category":"Restaurant",
            "type":"Food & Drink"
        }
    ],
    "sg:phone":"+43 1 4087224",
    "sg:postcode":"1090",
    "sg:province":"Wien",
    "wof:name":"Statt-Beisl d Vereins z F\u00f6rderung und Errichtung v Kommunikationsm\u00f6glichkeiten",
    "wof:placetype":"venue"
},
  "geometry": {"coordinates":[16.3513355255,48.2233123779],"type":"Point"}
}