{
  "type": "Feature",
  "properties": {
    "addr:full":"Herreng 15 St. P\u00f6lten Nieder\u00f6sterreich 3100",
    "addr:housenumber":"15",
    "addr:postcode":"3100",
    "addr:street":"Herreng",
    "iso:country":"AT",
    "sg:address":"Herreng 15",
    "sg:city":"St. P\u00f6lten",
    "sg:orig_category":"Polizei U Gendarmerie",
    "sg:phone":"+43 4359 13330",
    "sg:postcode":"3100",
    "sg:province":"Nieder\u00f6sterreich",
    "wof:name":"Landesgendarmeriekommando f N\u00f6",
    "wof:placetype":"venue"
},
  "geometry": {"coordinates":[-76.07303619379999,41.7845001221],"type":"Point"}
}