{
  "type": "Feature",
  "properties": {
    "iso:country":"AT",
    "sg:address":"Bahnhofstr 4",
    "sg:city":"Hallein",
    "sg:orig_category":"Optiker",
    "sg:phone":"+43 6245 80752",
    "sg:postcode":"5400",
    "sg:province":"Salzburg",
    "wof:name":"Brillen Binder",
    "wof:placetype":"venue"
},
  "geometry": {"coordinates":[13.0982713699,47.6840629578],"type":"Point"}
}