{
  "type": "Feature",
  "properties": {
    "addr:full":"Eichenstr 2C/1/20 Wien Wien 1120",
    "addr:housenumber":"2c / 1 / 20",
    "addr:postcode":"1120",
    "addr:street":"Eichenstr",
    "iso:country":"AT",
    "sg:address":"Eichenstr 2C/1/20",
    "sg:city":"Wien",
    "sg:orig_category":"Datenverarbeitung",
    "sg:phone":"+43 1 8125936",
    "sg:postcode":"1120",
    "sg:province":"Wien",
    "wof:name":"Brinskele Wolfgang",
    "wof:placetype":"venue"
},
  "geometry": {"coordinates":[16.3290939331,48.1824874878],"type":"Point"}
}