{
  "type": "Feature",
  "properties": {
    "iso:country":"AT",
    "sg:address":"Mitterweg 2",
    "sg:city":"Mattighofen",
    "sg:orig_category":"Garten- U Landschaftsgestaltung",
    "sg:phone":"+43 4377 426827",
    "sg:postcode":"5230",
    "sg:province":"Ober\u00f6sterreich",
    "wof:name":"Burger & Gr\u00f6sslinger OEG",
    "wof:placetype":"venue"
},
  "geometry": {"coordinates":[13.1476564407,48.1085166931],"type":"Point"}
}