{
  "type": "Feature",
  "properties": {
    "iso:country":"AT",
    "sg:address":"Kirchenstr 44",
    "sg:city":"Poysbrunn",
    "sg:orig_category":"Weine / Einzelhandel",
    "sg:phone":"+43 2554 85409",
    "sg:postcode":"2161",
    "sg:province":"Nieder\u00f6sterreich",
    "wof:name":"Hugl Weine Inh Franz Hugl",
    "wof:placetype":"venue"
},
  "geometry": {"coordinates":[16.6235351562,48.7178573608],"type":"Point"}
}