{
  "type": "Feature",
  "properties": {
    "addr:full":"Vogelsang 208 Stans Tirol 6135",
    "addr:housenumber":"208",
    "addr:postcode":"6135",
    "addr:street":"Vogelsang;Tirol",
    "iso:country":"AT",
    "sg:address":"Vogelsang 208",
    "sg:city":"Stans",
    "sg:orig_category":"Friseure U Frisiersalons",
    "sg:phone":"+43 4352 4263006",
    "sg:postcode":"6135",
    "sg:province":"Tirol",
    "wof:name":"Haarstudio-Coiffeur Team Hohenauer",
    "wof:placetype":"venue"
},
  "geometry": {"coordinates":[11.7170000076,47.36977005],"type":"Point"}
}