{
  "type": "Feature",
  "properties": {
    "addr:full":"Neudeggerg 8 Wien Wien 1080",
    "addr:housenumber":"8",
    "addr:postcode":"1080",
    "addr:street":"Neudeggerg",
    "iso:country":"AT",
    "sg:address":"Neudeggerg 8",
    "sg:city":"Wien",
    "sg:orig_category":"Massagen",
    "sg:phone":"+43 1 5331730",
    "sg:postcode":"1080",
    "sg:province":"Wien",
    "wof:name":"Shiatsu School of Attunement",
    "wof:placetype":"venue"
},
  "geometry": {"coordinates":[16.3520355225,48.2070846558],"type":"Point"}
}