{
  "type": "Feature",
  "properties": {
    "addr:full":"Kalkofenstr 27 Wels Ober\u00f6sterreich 4600",
    "addr:housenumber":"27",
    "addr:postcode":"4600",
    "addr:street":"Kalkofenstr;Oberoesterreich",
    "iso:country":"AT",
    "sg:address":"Kalkofenstr 27",
    "sg:city":"Wels",
    "sg:orig_category":"Lebensmittel / Einzelhandel",
    "sg:phone":"+43 7242 47619",
    "sg:postcode":"4600",
    "sg:province":"Ober\u00f6sterreich",
    "wof:name":"Spar-Markt Inh Maria Hoheneder",
    "wof:placetype":"venue"
},
  "geometry": {"coordinates":[14.042714119,48.1591644287],"type":"Point"}
}