{
  "type": "Feature",
  "properties": {
    "addr:full":"Bahnhofstr 34 B\u00fcrmoos Salzburg 5111",
    "addr:housenumber":"34",
    "addr:postcode":"5111",
    "addr:street":"Bahnhofstr",
    "iso:country":"AT",
    "sg:address":"Bahnhofstr 34",
    "sg:city":"B\u00fcrmoos",
    "sg:orig_category":"Friseure U Frisiersalons",
    "sg:phone":"+43 4362 747264",
    "sg:postcode":"5111",
    "sg:province":"Salzburg",
    "wof:name":"Frisiersalon Romana",
    "wof:placetype":"venue"
},
  "geometry": {"coordinates":[12.9243631363,47.9820823669],"type":"Point"}
}