{
  "type": "Feature",
  "properties": {
    "addr:full":"Ufer 44 Grein Ober\u00f6sterreich 4360",
    "addr:housenumber":"44",
    "addr:postcode":"4360",
    "addr:street":"Ufer",
    "iso:country":"AT",
    "sg:address":"Ufer 44",
    "sg:city":"Grein",
    "sg:orig_category":"Tischlereien",
    "sg:phone":"+43 7268 4080",
    "sg:postcode":"4360",
    "sg:province":"Ober\u00f6sterreich",
    "wof:name":"Fr\u00f6schl Michael Ing",
    "wof:placetype":"venue"
},
  "geometry": {"coordinates":[14.8518400192,48.2203712463],"type":"Point"}
}