{
  "type": "Feature",
  "properties": {
    "addr:full":"Rautenweg 2 Wien Wien 1220",
    "addr:housenumber":"2",
    "addr:postcode":"1220",
    "addr:street":"Rautenweg",
    "iso:country":"AT",
    "sg:address":"Rautenweg 2",
    "sg:city":"Wien",
    "sg:orig_category":"Autoersatzteile",
    "sg:phone":"+43 1 2565758",
    "sg:postcode":"1220",
    "sg:province":"Wien",
    "wof:name":"Forstinger Handel und Service GmbH",
    "wof:placetype":"venue"
},
  "geometry": {"coordinates":[16.4561233521,48.2643013],"type":"Point"}
}