{
  "type": "Feature",
  "properties": {
    "addr:full":"Vordertambergau 37 Vorderstoder Ober\u00f6sterreich 4574",
    "addr:housenumber":"37",
    "addr:postcode":"4574",
    "addr:street":"Vordertambergau",
    "iso:country":"AT",
    "sg:address":"Vordertambergau 37",
    "sg:city":"Vorderstoder",
    "sg:orig_category":"Pensionen / Privatzimmer",
    "sg:phone":"+43 7564 8291",
    "sg:postcode":"4574",
    "sg:province":"Ober\u00f6sterreich",
    "wof:name":"Baby- & Kinderhof Mittermair",
    "wof:placetype":"venue"
},
  "geometry": {"coordinates":[14.2474517822,47.7175483704],"type":"Point"}
}