{
  "type": "Feature",
  "properties": {
    "addr:full":"Bachg 2 Sitzenberg-Reidling Nieder\u00f6sterreich 3454",
    "addr:housenumber":"2",
    "addr:postcode":"3454",
    "addr:street":"Bachg",
    "iso:country":"AT",
    "sg:address":"Bachg 2",
    "sg:city":"Sitzenberg-Reidling",
    "sg:orig_category":"Feuerwehren",
    "sg:phone":"+43 2276 2626",
    "sg:postcode":"3454",
    "sg:province":"Nieder\u00f6sterreich",
    "wof:name":"Freiwillige Feuerwehr Reidling",
    "wof:placetype":"venue"
},
  "geometry": {"coordinates":[15.8168420792,48.3195571899],"type":"Point"}
}