{
  "type": "Feature",
  "properties": {
    "addr:full":"Hauptpl 12 Neunkirchen Nieder\u00f6sterreich 2620",
    "addr:housenumber":"12",
    "addr:postcode":"2620",
    "addr:street":"Hauptpl",
    "iso:country":"AT",
    "sg:address":"Hauptpl 12",
    "sg:city":"Neunkirchen",
    "sg:orig_category":"Bijouteriewaren",
    "sg:phone":"+43 2635 61910",
    "sg:postcode":"2620",
    "sg:province":"Nieder\u00f6sterreich",
    "wof:name":"Halmer Christine",
    "wof:placetype":"venue"
},
  "geometry": {"coordinates":[16.0812492371,47.7212181091],"type":"Point"}
}