{
  "type": "Feature",
  "properties": {
    "addr:full":"Mautner Markhof-G 50-54 Wien Wien 1110",
    "addr:postcode":"50-54;1110",
    "iso:country":"AT",
    "sg:address":"Mautner Markhof-G 50-54",
    "sg:city":"Wien",
    "sg:orig_category":"Finanz- U Wirtschaftsberatung",
    "sg:phone":"+43 699 12383941",
    "sg:postcode":"1110",
    "sg:province":"Wien",
    "wof:name":"APLC Management und Leasing Consulting Asinger und Poeckh OEG",
    "wof:placetype":"venue"
},
  "geometry": {"coordinates":[16.4203357697,48.1761245728],"type":"Point"}
}