{
  "type": "Feature",
  "properties": {
    "addr:full":"Biberwier Tirol 6633",
    "addr:postcode":"6633",
    "addr:street":"Biberwier Tirol",
    "iso:country":"AT",
    "sg:city":"Biberwier",
    "sg:orig_category":"Bergbahnen",
    "sg:phone":"+43 5673 21110",
    "sg:postcode":"6633",
    "sg:province":"Tirol",
    "wof:name":"Skilift Biberwier Berglifte Giselher Langes GesmbH & Co KG",
    "wof:placetype":"venue"
},
  "geometry": {"coordinates":[10.8920450211,47.3836898804],"type":"Point"}
}