{
  "type": "Feature",
  "properties": {
    "addr:full":"Kaufpark 14 St. Valentin Nieder\u00f6sterreich 4300",
    "addr:housenumber":"14",
    "addr:postcode":"4300",
    "addr:street":"Kaufpark",
    "iso:country":"AT",
    "sg:address":"Kaufpark 14",
    "sg:city":"St. Valentin",
    "sg:classifiers":[
        {
            "category":"Personal",
            "subcategory":"Adult",
            "type":"Services"
        }
    ],
    "sg:phone":"+43 7435 58662",
    "sg:postcode":"4300",
    "sg:province":"Nieder\u00f6sterreich",
    "sg:tags":[
        "sex-shops"
    ],
    "wof:name":"ORION Erotik Fachgesch\u00e4ft",
    "wof:placetype":"venue"
},
  "geometry": {"coordinates":[14.5193338394,48.1912651062],"type":"Point"}
}