{
  "type": "Feature",
  "properties": {
    "iso:country":"AT",
    "sg:address":"Politzen 33",
    "sg:city":"Ferndorf",
    "sg:classifiers":[
        {
            "category":"Manufacturing",
            "subcategory":"Metals",
            "type":"Manufacturing & Wholesale Goods"
        }
    ],
    "sg:phone":"+43 4767 352",
    "sg:postcode":"9702",
    "sg:province":"K\u00e4rnten",
    "sg:tags":[
        "machine",
        "band",
        "sawing"
    ],
    "sg:website":"shsmaschinen.at",
    "wof:name":"S H S Maschinen und Ger\u00e4tebau Ges.m.b.H.",
    "wof:placetype":"venue"
},
  "geometry": {"coordinates":[13.607213974,46.7514457703],"type":"Point"}
}