{
  "type": "Feature",
  "properties": {
    "addr:full":"Maysederg 4 Wien Wien 1010",
    "addr:housenumber":"4",
    "addr:postcode":"1010",
    "addr:street":"Maysederg",
    "iso:country":"AT",
    "sg:address":"Maysederg 4",
    "sg:city":"Wien",
    "sg:orig_category":"Boutiquen",
    "sg:phone":"+43 1 5134663",
    "sg:postcode":"1010",
    "sg:province":"Wien",
    "wof:name":"Ferre Gianfranco Boutique",
    "wof:placetype":"venue"
},
  "geometry": {"coordinates":[16.3696556091,48.2044715881],"type":"Point"}
}