{
  "type": "Feature",
  "properties": {
    "iso:country":"AT",
    "sg:address":"Dorf 3",
    "sg:city":"Obertilliach",
    "sg:orig_category":"Pensionen / Privatzimmer",
    "sg:phone":"+43 4847 5223",
    "sg:postcode":"9942",
    "sg:province":"Tirol",
    "wof:name":"G\u00e4stehaus Ganner",
    "wof:placetype":"venue"
},
  "geometry": {"coordinates":[12.6132011414,46.7110023499],"type":"Point"}
}