{
  "type": "Feature",
  "properties": {
    "iso:country":"AT",
    "sg:address":"Mariahilfer Str 13",
    "sg:city":"Wien",
    "sg:orig_category":"Friseure U Frisiersalons",
    "sg:phone":"+43 4319 741497",
    "sg:postcode":"1060",
    "sg:province":"Wien",
    "wof:name":"absoluthaar",
    "wof:placetype":"venue"
},
  "geometry": {"coordinates":[16.3595142365,48.2010879517],"type":"Point"}
}