{
  "type": "Feature",
  "properties": {
    "addr:full":"Nr 31 Gallizien K\u00e4rnten 9132",
    "addr:postcode":"9132",
    "addr:street":"Nr 31;Kaernten",
    "iso:country":"AT",
    "sg:address":"Nr 31",
    "sg:city":"Gallizien",
    "sg:orig_category":"Non-Classified Establishments",
    "sg:phone":"+43 4221 2637",
    "sg:postcode":"9132",
    "sg:province":"K\u00e4rnten",
    "wof:name":"Pfarramt",
    "wof:placetype":"venue"
},
  "geometry": {"coordinates":[14.5081481934,46.5587844849],"type":"Point"}
}