{
  "type": "Feature",
  "properties": {
    "iso:country":"AT",
    "sg:address":"Salzgries 12",
    "sg:city":"Wien",
    "sg:orig_category":"Tanzschulen",
    "sg:phone":"+43 1 5353711",
    "sg:postcode":"1010",
    "sg:province":"Wien",
    "sg:website":"watzek.at",
    "wof:name":"Tanzschule Watzek",
    "wof:placetype":"venue"
},
  "geometry": {"coordinates":[16.3714885712,48.2133979797],"type":"Point"}
}