{
  "type": "Feature",
  "properties": {
    "addr:full":"Engereweg 8 Imst Tirol 6460",
    "addr:housenumber":"8",
    "addr:postcode":"6460",
    "addr:street":"Engereweg;Tirol",
    "iso:country":"AT",
    "sg:address":"Engereweg 8",
    "sg:city":"Imst",
    "sg:orig_category":"Installationsunternehmen",
    "sg:phone":"+43 5412 63362",
    "sg:postcode":"6460",
    "sg:province":"Tirol",
    "wof:name":"Bouvier Erwin GesmbH & Co KG",
    "wof:placetype":"venue"
},
  "geometry": {"coordinates":[10.7434206009,47.2439994812],"type":"Point"}
}