{
  "type": "Feature",
  "properties": {
    "iso:country":"AT",
    "sg:address":"Hamiltong 5-9",
    "sg:city":"Wien",
    "sg:orig_category":"\u00c3\u201erzte / F Allgemeinmedizin",
    "sg:phone":"+43 1 9141287",
    "sg:postcode":"1140",
    "sg:province":"Wien",
    "wof:name":"Fink Udo Dr",
    "wof:placetype":"venue"
},
  "geometry": {"coordinates":[16.2600841522,48.2011528015],"type":"Point"}
}