{
  "type": "Feature",
  "properties": {
    "addr:full":"Gatterederweg 5 Linz Ober\u00f6sterreich 4040",
    "addr:housenumber":"5",
    "addr:postcode":"4040",
    "addr:street":"Gatterederweg",
    "iso:country":"AT",
    "sg:address":"Gatterederweg 5",
    "sg:city":"Linz",
    "sg:orig_category":"Steuerberatung",
    "sg:phone":"+43 732 221883",
    "sg:postcode":"4040",
    "sg:province":"Ober\u00f6sterreich",
    "wof:name":"Karl Brigitte",
    "wof:placetype":"venue"
},
  "geometry": {"coordinates":[14.2266292572,48.3228302002],"type":"Point"}
}