{
  "type": "Feature",
  "properties": {
    "iso:country":"AT",
    "sg:address":"Haid 6",
    "sg:city":"Wagrain",
    "sg:classifiers":[
        {
            "category":"Internet Cafe",
            "subcategory":"None",
            "type":"Food & Drink"
        }
    ],
    "sg:phone":"+43 6413 8144",
    "sg:postcode":"5602",
    "sg:province":"Salzburg",
    "sg:website":"systemnet.at",
    "wof:name":"System Net",
    "wof:placetype":"venue"
},
  "geometry": {"coordinates":[13.3006591797,47.3319702148],"type":"Point"}
}