{
  "type": "Feature",
  "properties": {
    "addr:full":"Brunnenstr 19 Hainburg an der Donau Nieder\u00f6sterreich 2410",
    "addr:housenumber":"19",
    "addr:postcode":"2410",
    "addr:street":"Brunnenstr",
    "iso:country":"AT",
    "sg:address":"Brunnenstr 19",
    "sg:city":"Hainburg an der Donau",
    "sg:orig_category":"Polizei U Gendarmerie",
    "sg:phone":"+43 4359 1333324",
    "sg:postcode":"2410",
    "sg:province":"Nieder\u00f6sterreich",
    "wof:name":"Gendarmerie",
    "wof:placetype":"venue"
},
  "geometry": {"coordinates":[16.9542102814,48.1398391724],"type":"Point"}
}