{
  "type": "Feature",
  "properties": {
    "addr:full":"Nr 185 Fiss Tirol 6533",
    "addr:postcode":"6533",
    "addr:street":"Nr;Tirol",
    "iso:country":"AT",
    "sg:address":"Nr 185",
    "sg:city":"Fiss",
    "sg:classifiers":[
        {
            "category":"Travel",
            "subcategory":"Travel Agent",
            "type":"Entertainment"
        }
    ],
    "sg:phone":"+43 4354 766354",
    "sg:postcode":"6533",
    "sg:province":"Tirol",
    "sg:tags":[
        "business"
    ],
    "wof:name":"PALE HOTEL LASINGA GESMBH",
    "wof:placetype":"venue"
},
  "geometry": {"coordinates":[10.618268013,47.0554733276],"type":"Point"}
}