{
  "type": "Feature",
  "properties": {
    "iso:country":"AT",
    "sg:address":"Plankenb\u00fcchlerg 6",
    "sg:city":"Wien",
    "sg:classifiers":[
        {
            "category":"Home & Garden",
            "subcategory":"Building Materials",
            "type":"Retail Goods"
        }
    ],
    "sg:phone":"+43 4312 726113",
    "sg:postcode":"1210",
    "sg:province":"Wien",
    "sg:tags":[
        "baustoffe",
        "-material",
        "u"
    ],
    "wof:name":"Hafenscher Franz",
    "wof:placetype":"venue"
},
  "geometry": {"coordinates":[16.3978404999,48.2579994202],"type":"Point"}
}