{
  "type": "Feature",
  "properties": {
    "addr:full":"Platz am Graben 1/3 St. Veit an der Glan K\u00e4rnten 9300",
    "addr:housenumber":"1 / 3",
    "addr:postcode":"9300",
    "addr:street":"Platz Am Graben;Kaernten",
    "iso:country":"AT",
    "sg:address":"Platz am Graben 1/3",
    "sg:city":"St. Veit an der Glan",
    "sg:orig_category":"Schneidereien",
    "sg:phone":"+43 4212 36540",
    "sg:postcode":"9300",
    "sg:province":"K\u00e4rnten",
    "wof:name":"Mayer Maria",
    "wof:placetype":"venue"
},
  "geometry": {"coordinates":[14.3603067398,46.7668228149],"type":"Point"}
}