{
  "type": "Feature",
  "properties": {
    "addr:full":"Nr 15 Z\u00fcrs Vorarlberg 6763",
    "addr:postcode":"6763",
    "addr:street":"Nr 15 Zuers",
    "iso:country":"AT",
    "sg:address":"Nr 15",
    "sg:city":"Z\u00fcrs",
    "sg:orig_category":"Non-Classified Establishments",
    "sg:phone":"+43 5583 2512",
    "sg:postcode":"6763",
    "sg:province":"Vorarlberg",
    "wof:name":"Pfarramt",
    "wof:placetype":"venue"
},
  "geometry": {"coordinates":[8.7782497406,46.5036811829],"type":"Point"}
}