{
  "type": "Feature",
  "properties": {
    "addr:full":"Unterschwarza 45 Spielfeld Steiermark 8471",
    "addr:housenumber":"45",
    "addr:postcode":"8471",
    "addr:street":"Unterschwarza",
    "iso:country":"AT",
    "sg:address":"Unterschwarza 45",
    "sg:city":"Spielfeld",
    "sg:orig_category":"Maler, Anstreicher U Lackierer",
    "sg:phone":"+43 3472 3688",
    "sg:postcode":"8471",
    "sg:province":"Steiermark",
    "wof:name":"Lorber Rupert",
    "wof:placetype":"venue"
},
  "geometry": {"coordinates":[15.6304121017,46.7054443359],"type":"Point"}
}