{
  "type": "Feature",
  "properties": {
    "iso:country":"AT",
    "sg:address":"Mayrwiesstr 4",
    "sg:city":"Hallwang",
    "sg:orig_category":"Alarmanlagen U Sicherheitssysteme",
    "sg:phone":"+43 4366 26615800",
    "sg:postcode":"5300",
    "sg:province":"Salzburg",
    "wof:name":"Elektronische Haustechnik Laimer GmbH",
    "wof:placetype":"venue"
},
  "geometry": {"coordinates":[13.0835151672,47.831363678],"type":"Point"}
}