{
  "type": "Feature",
  "properties": {
    "addr:full":"Wegscheider Str 3 Linz Ober\u00f6sterreich 4020",
    "addr:housenumber":"3",
    "addr:postcode":"4020",
    "addr:street":"Str",
    "iso:country":"AT",
    "sg:address":"Wegscheider Str 3",
    "sg:city":"Linz",
    "sg:orig_category":"Bekleidung / Einzelhandel",
    "sg:phone":"+43 732 372830",
    "sg:postcode":"4020",
    "sg:province":"Ober\u00f6sterreich",
    "wof:name":"FUSSL FLY - FUSSL MODESTRASSE Mayr GmbH",
    "wof:placetype":"venue"
},
  "geometry": {"coordinates":[14.2803926468,48.2541923523],"type":"Point"}
}