{
  "type": "Feature",
  "properties": {
    "addr:full":"Neusiedlerstr 6 Haid Ober\u00f6sterreich 4053",
    "addr:housenumber":"6",
    "addr:postcode":"4053",
    "addr:street":"Neusiedlerstr",
    "iso:country":"AT",
    "sg:address":"Neusiedlerstr 6",
    "sg:city":"Haid",
    "sg:orig_category":"Bauunternehmen",
    "sg:phone":"+43 7229 88303",
    "sg:postcode":"4053",
    "sg:province":"Ober\u00f6sterreich",
    "wof:name":"BSP Bau und Sanierungs GmbH",
    "wof:placetype":"venue"
},
  "geometry": {"coordinates":[14.2477388382,48.2026863098],"type":"Point"}
}