{
  "type": "Feature",
  "properties": {
    "addr:full":"Kotzinastrasse 3 Linz Ober\u00f6sterreich 4030",
    "addr:housenumber":"3",
    "addr:postcode":"4030",
    "addr:street":"Kotzinastrasse",
    "iso:country":"AT",
    "sg:address":"Kotzinastrasse 3",
    "sg:city":"Linz",
    "sg:classifiers":[
        {
            "category":"Utilities",
            "subcategory":"Natural Gas",
            "type":"Services"
        }
    ],
    "sg:phone":"+43 732 371718",
    "sg:postcode":"4030",
    "sg:province":"Ober\u00f6sterreich",
    "sg:tags":[
        "block",
        "chimney"
    ],
    "sg:website":"ruegg-kamine.at",
    "wof:name":"R\u00fcegg Kamine GmbH",
    "wof:placetype":"venue"
},
  "geometry": {"coordinates":[14.2840337753,48.2405853271],"type":"Point"}
}