{
  "type": "Feature",
  "properties": {
    "addr:full":"Industriestr 26/FMZ Zwettl Nieder\u00f6sterreich 3910",
    "addr:housenumber":"26 /",
    "addr:postcode":"3910",
    "addr:street":"Industriestr;Niederoesterreich",
    "iso:country":"AT",
    "sg:address":"Industriestr 26/FMZ",
    "sg:city":"Zwettl",
    "sg:orig_category":"Friseure U Frisiersalons",
    "sg:phone":"+43 4328 2234023",
    "sg:postcode":"3910",
    "sg:province":"Nieder\u00f6sterreich",
    "wof:name":"FRIS\u00f6R KLIER GesmbH",
    "wof:placetype":"venue"
},
  "geometry": {"coordinates":[15.1681003571,48.6041564941],"type":"Point"}
}