{
  "type": "Feature",
  "properties": {
    "addr:full":"Lobaustr 4 Gro\u00df-Enzersdorf Nieder\u00f6sterreich 2301",
    "addr:housenumber":"4",
    "addr:postcode":"2301",
    "addr:street":"Lobaustr;Niederoesterreich",
    "iso:country":"AT",
    "sg:address":"Lobaustr 4",
    "sg:city":"Gro\u00df-Enzersdorf",
    "sg:orig_category":"Lebensmittel / Einzelhandel",
    "sg:phone":"+43 2249 4559",
    "sg:postcode":"2301",
    "sg:province":"Nieder\u00f6sterreich",
    "wof:name":"Billa AG",
    "wof:placetype":"venue"
},
  "geometry": {"coordinates":[16.5492267609,48.1992530823],"type":"Point"}
}