{
  "type": "Feature",
  "properties": {
    "addr:full":"Fritz-Knoll-Str 3 Gleisdorf Steiermark 8200",
    "addr:housenumber":"3",
    "addr:postcode":"8200",
    "addr:street":"Fritz-Knoll-Str",
    "iso:country":"AT",
    "sg:address":"Fritz-Knoll-Str 3",
    "sg:city":"Gleisdorf",
    "sg:orig_category":"Elektronik",
    "sg:phone":"+43 3112 36026",
    "sg:postcode":"8200",
    "sg:province":"Steiermark",
    "wof:name":"THERM-IC Products GmbH Nfg & Co KG",
    "wof:placetype":"venue"
},
  "geometry": {"coordinates":[15.7108602524,47.0973358154],"type":"Point"}
}