{
  "type": "Feature",
  "properties": {
    "iso:country":"AT",
    "sg:address":"Hauptstr 1",
    "sg:city":"Timmersdorf",
    "sg:orig_category":"Weine / Einzelhandel",
    "sg:phone":"+43 3833 8514",
    "sg:postcode":"8772",
    "sg:province":"Steiermark",
    "wof:name":"Reinhard Prein",
    "wof:placetype":"venue"
},
  "geometry": {"coordinates":[14.9615402222,47.3770904541],"type":"Point"}
}