{
  "type": "Feature",
  "properties": {
    "addr:full":"Hauptstr 1 Timmersdorf Steiermark 8772",
    "addr:housenumber":"1",
    "addr:postcode":"8772",
    "addr:street":"Hauptstr",
    "iso:country":"AT",
    "sg:address":"Hauptstr 1",
    "sg:city":"Timmersdorf",
    "sg:orig_category":"Weine / Einzelhandel",
    "sg:phone":"+43 3833 8514",
    "sg:postcode":"8772",
    "sg:province":"Steiermark",
    "wof:name":"Reinhard Prein",
    "wof:placetype":"venue"
},
  "geometry": {"coordinates":[14.9615402222,47.3770904541],"type":"Point"}
}