{
  "type": "Feature",
  "properties": {
    "addr:full":"Herrenstr 2 Linz Ober\u00f6sterreich 4020",
    "addr:housenumber":"2",
    "addr:postcode":"4020",
    "addr:street":"Herrenstr",
    "iso:country":"AT",
    "sg:address":"Herrenstr 2",
    "sg:city":"Linz",
    "sg:orig_category":"Apotheken",
    "sg:phone":"+43 732 778227",
    "sg:postcode":"4020",
    "sg:province":"Ober\u00f6sterreich",
    "wof:name":"Schutzengel-Apotheke",
    "wof:placetype":"venue"
},
  "geometry": {"coordinates":[14.2855892181,48.3033790588],"type":"Point"}
}