{
  "type": "Feature",
  "properties": {
    "addr:full":"Seenstr 22 Reifnitz K\u00e4rnten 9081",
    "addr:housenumber":"22",
    "addr:postcode":"9081",
    "addr:street":"Seenstr;Kaernten",
    "iso:country":"AT",
    "sg:address":"Seenstr 22",
    "sg:city":"Reifnitz",
    "sg:classifiers":[
        {
            "category":"Restaurant",
            "type":"Food & Drink"
        }
    ],
    "sg:phone":"+43 4273 22940",
    "sg:postcode":"9081",
    "sg:province":"K\u00e4rnten",
    "wof:name":"Rosmann Gertrude",
    "wof:placetype":"venue"
},
  "geometry": {"coordinates":[14.175368309,46.6042938232],"type":"Point"}
}