{
  "type": "Feature",
  "properties": {
    "addr:full":"Nr 6 Attersee Ober\u00f6sterreich 4864",
    "addr:postcode":"4864",
    "addr:street":"Nr;Oberoesterreich",
    "iso:country":"AT",
    "sg:address":"Nr 6",
    "sg:city":"Attersee",
    "sg:orig_category":"Appartements / Ferienwohnungen",
    "sg:phone":"+43 4376 667661",
    "sg:postcode":"4864",
    "sg:province":"Ober\u00f6sterreich",
    "wof:name":"Leitner Georg u Heidi",
    "wof:placetype":"venue"
},
  "geometry": {"coordinates":[13.5341110229,47.9135665894],"type":"Point"}
}