{
  "type": "Feature",
  "properties": {
    "addr:full":"Siederg 89 Schladming Steiermark 8970",
    "addr:housenumber":"89",
    "addr:postcode":"8970",
    "addr:street":"Siederg",
    "iso:country":"AT",
    "sg:address":"Siederg 89",
    "sg:city":"Schladming",
    "sg:orig_category":"Brauereien",
    "sg:phone":"+43 4336 8724459",
    "sg:postcode":"8970",
    "sg:province":"Steiermark",
    "wof:name":"Das Kleine Brauhaus",
    "wof:placetype":"venue"
},
  "geometry": {"coordinates":[13.6899137497,47.3926239014],"type":"Point"}
}