{
  "type": "Feature",
  "properties": {
    "addr:full":"Hanriederstr 9 Rohrbach in Ober\u00f6sterreich Ober\u00f6sterreich 4150",
    "addr:housenumber":"9",
    "addr:postcode":"4150",
    "addr:street":"Hanriederstr",
    "iso:country":"AT",
    "sg:address":"Hanriederstr 9",
    "sg:city":"Rohrbach in Ober\u00f6sterreich",
    "sg:orig_category":"Politische Parteien",
    "sg:phone":"+43 4366 48257614",
    "sg:postcode":"4150",
    "sg:province":"Ober\u00f6sterreich",
    "wof:name":"Freiheitliche Partei \u00f6sterreichs (FP\u00f6) Bezirksgesch\u00e4ftsstelle Rohrbach",
    "wof:placetype":"venue"
},
  "geometry": {"coordinates":[13.9951534271,48.5746955872],"type":"Point"}
}