{
  "type": "Feature",
  "properties": {
    "addr:full":"Kreuzbrunn 15c Mauerbach Nieder\u00f6sterreich 3001",
    "addr:housenumber":"15c",
    "addr:postcode":"3001",
    "addr:street":"Kreuzbrunn",
    "iso:country":"AT",
    "sg:address":"Kreuzbrunn 15c",
    "sg:city":"Mauerbach",
    "sg:orig_category":"Feng-Shui",
    "sg:phone":"+43 4319 794520",
    "sg:postcode":"3001",
    "sg:province":"Nieder\u00f6sterreich",
    "sg:website":"qi-balance.com",
    "wof:name":"QI Balance",
    "wof:placetype":"venue"
},
  "geometry": {"coordinates":[16.1757736206,48.240776062],"type":"Point"}
}