{
  "type": "Feature",
  "properties": {
    "iso:country":"AT",
    "sg:address":"Lange G 58",
    "sg:city":"Wien",
    "sg:orig_category":"Ultraschalltechnik",
    "sg:phone":"+43 4314 080841",
    "sg:postcode":"1080",
    "sg:province":"Wien",
    "wof:name":"OMEGA MED- TECH - Melmuka - Dental - Import",
    "wof:placetype":"venue"
},
  "geometry": {"coordinates":[16.3430690765,48.2106552124],"type":"Point"}
}