{
  "type": "Feature",
  "properties": {
    "addr:full":"Bundesstr 97 Lauterach Vorarlberg 6923",
    "addr:housenumber":"97",
    "addr:postcode":"6923",
    "addr:street":"Bundesstr",
    "iso:country":"AT",
    "sg:address":"Bundesstr 97",
    "sg:city":"Lauterach",
    "sg:orig_category":"Tankstellen",
    "sg:phone":"+43 5574 73380",
    "sg:postcode":"6923",
    "sg:province":"Vorarlberg",
    "wof:name":"AVANTI TankstellenbetriebsgesmbH",
    "wof:placetype":"venue"
},
  "geometry": {"coordinates":[9.7288227081,47.4700813293],"type":"Point"}
}