{
  "type": "Feature",
  "properties": {
    "addr:full":"Milders 526 Neustift im Stubaital Tirol 6167",
    "addr:housenumber":"526",
    "addr:postcode":"6167",
    "addr:street":"Milders;Tirol",
    "iso:country":"AT",
    "sg:address":"Milders 526",
    "sg:city":"Neustift im Stubaital",
    "sg:orig_category":"Banken U Sparkassen",
    "sg:phone":"+43 4352 262870",
    "sg:postcode":"6167",
    "sg:province":"Tirol",
    "wof:name":"Bankomat d Raiffeisenkasse Neustift im Stubaital",
    "wof:placetype":"venue"
},
  "geometry": {"coordinates":[11.3075504303,47.1104850769],"type":"Point"}
}