{
  "type": "Feature",
  "properties": {
    "addr:full":"Nr 84a Kartitsch Tirol 9941",
    "addr:postcode":"9941",
    "addr:street":"Nr;Kartitsch Tirol",
    "iso:country":"AT",
    "sg:address":"Nr 84a",
    "sg:city":"Kartitsch",
    "sg:orig_category":"Lebensmittel / Einzelhandel",
    "sg:phone":"+43 4848 63030",
    "sg:postcode":"9941",
    "sg:province":"Tirol",
    "wof:name":"Adeg aktiv Markt Inh Michael Aichner",
    "wof:placetype":"venue"
},
  "geometry": {"coordinates":[12.4975404739,46.7263145447],"type":"Point"}
}