{
  "type": "Feature",
  "properties": {
    "addr:full":"Bergmillerg 3 Wien Wien 1140",
    "addr:housenumber":"3",
    "addr:postcode":"1140",
    "addr:street":"Bergmillerg",
    "iso:country":"AT",
    "sg:address":"Bergmillerg 3",
    "sg:city":"Wien",
    "sg:orig_category":"Decken- U Wandverkleidungen",
    "sg:phone":"+43 4314 168584",
    "sg:postcode":"1140",
    "sg:province":"Wien",
    "wof:name":"Knauf AMF Deckesysteme GesmbH",
    "wof:placetype":"venue"
},
  "geometry": {"coordinates":[16.2570838928,48.2015151978],"type":"Point"}
}