{
  "type": "Feature",
  "properties": {
    "addr:full":"Schulg 15 Westendorf Tirol 6363",
    "addr:housenumber":"15",
    "addr:postcode":"6363",
    "addr:street":"Schulg;Tirol",
    "iso:country":"AT",
    "sg:address":"Schulg 15",
    "sg:city":"Westendorf",
    "sg:classifiers":[
        {
            "category":"Taxi",
            "type":"Transportation"
        }
    ],
    "sg:phone":"+43 4353 3430400",
    "sg:postcode":"6363",
    "sg:province":"Tirol",
    "sg:tags":[
        "personentransporte",
        "u"
    ],
    "wof:name":"Taxi Ideal",
    "wof:placetype":"venue"
},
  "geometry": {"coordinates":[12.2196149826,47.4324493408],"type":"Point"}
}