{
  "type": "Feature",
  "properties": {
    "addr:full":"Emprechting 40 Ried im Innkreis Ober\u00f6sterreich 4910",
    "addr:housenumber":"40",
    "addr:postcode":"4910",
    "addr:street":"Emprechting",
    "iso:country":"AT",
    "sg:address":"Emprechting 40",
    "sg:city":"Ried im Innkreis",
    "sg:classifiers":[
        {
            "category":"Manufacturing",
            "subcategory":"Printing",
            "type":"Manufacturing & Wholesale Goods"
        }
    ],
    "sg:phone":"+43 7752 88588",
    "sg:postcode":"4910",
    "sg:province":"Ober\u00f6sterreich",
    "sg:tags":[
        "house",
        "book"
    ],
    "sg:website":"moserbauer.at",
    "wof:name":"Moserbauer Druck und VerlagsgmbH & Co KG",
    "wof:placetype":"venue"
},
  "geometry": {"coordinates":[13.4900550842,48.2098655701],"type":"Point"}
}