{
  "type": "Feature",
  "properties": {
    "addr:full":"Griespl 10 Graz Steiermark 8020",
    "addr:housenumber":"10",
    "addr:postcode":"8020",
    "addr:street":"Griespl",
    "iso:country":"AT",
    "sg:address":"Griespl 10",
    "sg:city":"Graz",
    "sg:orig_category":"Politische Parteien",
    "sg:phone":"+43 316 70720",
    "sg:postcode":"8020",
    "sg:province":"Steiermark",
    "wof:name":"FP\u00d6-Die Freiheitlichen",
    "wof:placetype":"venue"
},
  "geometry": {"coordinates":[15.431801796,47.0651130676],"type":"Point"}
}