{
  "type": "Feature",
  "properties": {
    "addr:full":"Wiesengasse 31 Stoob Burgenland 7344",
    "addr:housenumber":"31",
    "addr:postcode":"stoob;7344",
    "addr:street":"Wiesengasse",
    "iso:country":"AT",
    "sg:address":"Wiesengasse 31",
    "sg:city":"Stoob",
    "sg:classifiers":[
        {
            "category":"Manufacturing",
            "subcategory":"Toys & Sporting Goods",
            "type":"Manufacturing & Wholesale Goods"
        }
    ],
    "sg:phone":"+43 2612 43110",
    "sg:postcode":"7344",
    "sg:province":"Burgenland",
    "sg:tags":[
        "ceramic",
        "figurine"
    ],
    "wof:name":"Stoober Keramik Hobbykurse - Schr\u00f6dl Thumberger GmbH & Co KG",
    "wof:placetype":"venue"
},
  "geometry": {"coordinates":[16.4795684814,47.5240325928],"type":"Point"}
}