{
  "type": "Feature",
  "properties": {
    "iso:country":"AT",
    "sg:address":"Nr 185",
    "sg:city":"Filzmoos",
    "sg:orig_category":"Appartements / Ferienwohnungen",
    "sg:phone":"+43 6453 85970",
    "sg:postcode":"5532",
    "sg:province":"Salzburg",
    "wof:name":"Wurzer Manfred",
    "wof:placetype":"venue"
},
  "geometry": {"coordinates":[13.5202980042,47.4332199097],"type":"Point"}
}