{
  "type": "Feature",
  "properties": {
    "iso:country":"AT",
    "sg:address":"Langenzersdorfer Str 3",
    "sg:city":"Wien",
    "sg:orig_category":"Garten- U Landschaftsgestaltung",
    "sg:phone":"+43 4312 929795",
    "sg:postcode":"1210",
    "sg:province":"Wien",
    "sg:website":"landschaftsgaertner.at",
    "wof:name":"Kubacek Franz Ing",
    "wof:placetype":"venue"
},
  "geometry": {"coordinates":[16.3884658813,48.2958641052],"type":"Point"}
}