{
  "type": "Feature",
  "properties": {
    "iso:country":"AT",
    "sg:address":"Industriestr 16",
    "sg:city":"Lannach",
    "sg:orig_category":"Abfallentsorgung U -Verwertung",
    "sg:phone":"+43 3136 824800",
    "sg:postcode":"8502",
    "sg:province":"Steiermark",
    "wof:name":"Saubermacher Dienstleistungs-AG",
    "wof:placetype":"venue"
},
  "geometry": {"coordinates":[15.3310937881,46.9549064636],"type":"Point"}
}