{
  "type": "Feature",
  "properties": {
    "iso:country":"AT",
    "sg:address":"Salzburger Str 88",
    "sg:city":"Wels",
    "sg:orig_category":"Installationsunternehmen",
    "sg:phone":"+43 4372 4277960",
    "sg:postcode":"4600",
    "sg:province":"Ober\u00f6sterreich",
    "wof:name":"B.A.I.E.R. Installationen GesmbH",
    "wof:placetype":"venue"
},
  "geometry": {"coordinates":[14.0111122131,48.1581115723],"type":"Point"}
}