{
  "type": "Feature",
  "properties": {
    "addr:full":"Wasserg 3 Baden Nieder\u00f6sterreich 2500",
    "addr:housenumber":"3",
    "addr:postcode":"2500",
    "addr:street":"Wasserg;Niederoesterreich",
    "iso:country":"AT",
    "sg:address":"Wasserg 3",
    "sg:city":"Baden",
    "sg:orig_category":"Boutiquen",
    "sg:phone":"+43 4322 5224565",
    "sg:postcode":"2500",
    "sg:province":"Nieder\u00f6sterreich",
    "wof:name":"Boutique MOMO",
    "wof:placetype":"venue"
},
  "geometry": {"coordinates":[16.2351055145,48.0073356628],"type":"Point"}
}