{
  "type": "Feature",
  "properties": {
    "iso:country":"AT",
    "sg:address":"Storcheng 1",
    "sg:city":"Wien",
    "sg:orig_category":"Architekten",
    "sg:phone":"+43 1 89977",
    "sg:postcode":"1150",
    "sg:province":"Wien",
    "wof:name":"Atelier Hayde Architekten Ziviltechniker GmbH",
    "wof:placetype":"venue"
},
  "geometry": {"coordinates":[16.3329277039,48.1851081848],"type":"Point"}
}