{
  "type": "Feature",
  "properties": {
    "addr:full":"Nr 48 Geistthal Steiermark 8153",
    "addr:postcode":"8153",
    "addr:street":"Nr",
    "iso:country":"AT",
    "sg:address":"Nr 48",
    "sg:city":"Geistthal",
    "sg:classifiers":[
        {
            "category":"Taxi",
            "type":"Transportation"
        }
    ],
    "sg:phone":"+43 4366 44970575",
    "sg:postcode":"8153",
    "sg:province":"Steiermark",
    "sg:tags":[
        "personentransporte",
        "u"
    ],
    "wof:name":"Nestler - Taxi- u Mietwagen",
    "wof:placetype":"venue"
},
  "geometry": {"coordinates":[15.1865959167,47.1377792358],"type":"Point"}
}