{
  "type": "Feature",
  "properties": {
    "addr:full":"Industriezone 411 Pischelsdorf in Steiermark Steiermark 8212",
    "addr:housenumber":"411",
    "addr:postcode":"8212",
    "addr:street":"Industriezone",
    "iso:country":"AT",
    "sg:address":"Industriezone 411",
    "sg:city":"Pischelsdorf in Steiermark",
    "sg:classifiers":[
        {
            "category":"Manufacturing",
            "subcategory":"Chemicals & Compounds",
            "type":"Manufacturing & Wholesale Goods"
        }
    ],
    "sg:phone":"+43 3113 3488",
    "sg:postcode":"8212",
    "sg:province":"Steiermark",
    "sg:tags":[
        "carbide",
        "dy"
    ],
    "wof:name":"Tool tec Werkzeugbau GmbH",
    "wof:placetype":"venue"
},
  "geometry": {"coordinates":[15.8060102463,47.1733627319],"type":"Point"}
}