{
  "type": "Feature",
  "properties": {
    "iso:country":"AT",
    "sg:address":"Nordwestbahnstr 8-10",
    "sg:city":"Wien",
    "sg:orig_category":"Bekleidung / Einzelhandel",
    "sg:phone":"+43 1 33005250",
    "sg:postcode":"1200",
    "sg:province":"Wien",
    "wof:name":"Sch\u00f6ps Richard & Co AG - Zentrale",
    "wof:placetype":"venue"
},
  "geometry": {"coordinates":[16.3802108765,48.2294006348],"type":"Point"}
}