{
  "type": "Feature",
  "properties": {
    "addr:full":"Guntramsdorfer Str 7 Laxenburg Nieder\u00f6sterreich 2361",
    "addr:housenumber":"7",
    "addr:postcode":"2361",
    "addr:street":"Str",
    "iso:country":"AT",
    "sg:address":"Guntramsdorfer Str 7",
    "sg:city":"Laxenburg",
    "sg:orig_category":"Polizei U Gendarmerie",
    "sg:phone":"+43 4359 1333338",
    "sg:postcode":"2361",
    "sg:province":"Nieder\u00f6sterreich",
    "wof:name":"Gendarmerie",
    "wof:placetype":"venue"
},
  "geometry": {"coordinates":[16.3524875641,48.0650291443],"type":"Point"}
}