{
  "type": "Feature",
  "properties": {
    "addr:full":"Hahneng 5 Linz Ober\u00f6sterreich 4020",
    "addr:housenumber":"5",
    "addr:postcode":"4020",
    "addr:street":"Hahneng",
    "iso:country":"AT",
    "sg:address":"Hahneng 5",
    "sg:city":"Linz",
    "sg:orig_category":"Bildungsservice / Allgemeine Informationsstellen",
    "sg:phone":"+43 732 770451",
    "sg:postcode":"4020",
    "sg:province":"Ober\u00f6sterreich",
    "wof:name":"learn - das Lerncenter - VSG",
    "wof:placetype":"venue"
},
  "geometry": {"coordinates":[14.284778595,48.3052520752],"type":"Point"}
}