{
  "type": "Feature",
  "properties": {
    "iso:country":"AT",
    "sg:address":"Zenzlweg 15",
    "sg:city":"Gratkorn",
    "sg:orig_category":"Bauunternehmen",
    "sg:phone":"+43 3124 23537",
    "sg:postcode":"8101",
    "sg:province":"Steiermark",
    "wof:name":"Hederer Heribert Bauunternehmung GesmbH",
    "wof:placetype":"venue"
},
  "geometry": {"coordinates":[15.3240118027,47.1540336609],"type":"Point"}
}