{
  "type": "Feature",
  "properties": {
    "addr:full":"Nr 237 Steinbach am Ziehberg Ober\u00f6sterreich 4562",
    "addr:postcode":"4562",
    "addr:street":"Nr 237;Ziehberg",
    "iso:country":"AT",
    "sg:address":"Nr 237",
    "sg:city":"Steinbach am Ziehberg",
    "sg:orig_category":"Sonnenschutzanlagen",
    "sg:phone":"+43 4366 49104371",
    "sg:postcode":"4562",
    "sg:province":"Ober\u00f6sterreich",
    "wof:name":"Mayr Markus",
    "wof:placetype":"venue"
},
  "geometry": {"coordinates":[14.0288743973,47.8925628662],"type":"Point"}
}