{
  "type": "Feature",
  "properties": {
    "addr:full":"Donawitz Zellenfeldg 11 Leoben Steiermark 8700",
    "addr:housenumber":"11",
    "addr:postcode":"8700",
    "iso:country":"AT",
    "sg:address":"Donawitz Zellenfeldg 11",
    "sg:city":"Leoben",
    "sg:orig_category":"Beton- U Betonsteinwerke",
    "sg:phone":"+43 4338 42212770",
    "sg:postcode":"8700",
    "sg:province":"Steiermark",
    "wof:name":"Scardelli August",
    "wof:placetype":"venue"
},
  "geometry": {"coordinates":[15.0506801605,47.3832473755],"type":"Point"}
}