{
  "type": "Feature",
  "properties": {
    "iso:country":"AT",
    "sg:address":"Gschwandnerg 41",
    "sg:city":"Wien",
    "sg:orig_category":"Bauunternehmen",
    "sg:phone":"+43 1 4857986",
    "sg:postcode":"1170",
    "sg:province":"Wien",
    "wof:name":"Prom-Bau GesmbH",
    "wof:placetype":"venue"
},
  "geometry": {"coordinates":[16.3248996735,48.2191505432],"type":"Point"}
}