{
  "type": "Feature",
  "properties": {
    "addr:full":"Korneuburger Str 77 Langenzersdorf Nieder\u00f6sterreich 2103",
    "addr:postcode":"2103",
    "addr:street":"Str 77",
    "iso:country":"AT",
    "sg:address":"Korneuburger Str 77",
    "sg:city":"Langenzersdorf",
    "sg:orig_category":"Marketingberatung",
    "sg:phone":"+43 2244 306500",
    "sg:postcode":"2103",
    "sg:province":"Nieder\u00f6sterreich",
    "wof:name":"Jirgal WerbegesmbH",
    "wof:placetype":"venue"
},
  "geometry": {"coordinates":[16.3542385101,48.3153800964],"type":"Point"}
}