{
  "type": "Feature",
  "properties": {
    "addr:full":"Alterbachstr 13 Salzburg Salzburg 5020",
    "addr:housenumber":"13",
    "addr:postcode":"5020",
    "addr:street":"Alterbachstr;Salzburg",
    "iso:country":"AT",
    "sg:address":"Alterbachstr 13",
    "sg:city":"Salzburg",
    "sg:orig_category":"Glasereien",
    "sg:phone":"+43 4366 24512880",
    "sg:postcode":"5020",
    "sg:province":"Salzburg",
    "wof:name":"Holzer Guido",
    "wof:placetype":"venue"
},
  "geometry": {"coordinates":[13.0511083603,47.8255805969],"type":"Point"}
}