{
  "type": "Feature",
  "properties": {
    "addr:full":"Rosenweg 35 Wals Salzburg 5071",
    "addr:housenumber":"35",
    "addr:postcode":"5071",
    "addr:street":"Rosenweg;Salzburg",
    "iso:country":"AT",
    "sg:address":"Rosenweg 35",
    "sg:city":"Wals",
    "sg:orig_category":"Fleischhauereien",
    "sg:phone":"+43 662 852482",
    "sg:postcode":"5071",
    "sg:province":"Salzburg",
    "wof:name":"Mitteregger Reinhold",
    "wof:placetype":"venue"
},
  "geometry": {"coordinates":[12.9486551285,47.7808418274],"type":"Point"}
}