{
  "type": "Feature",
  "properties": {
    "addr:full":"Walser Str 46 Mittelberg Vorarlberg 6993",
    "addr:housenumber":"46",
    "addr:postcode":"6993",
    "addr:street":"Str",
    "iso:country":"AT",
    "sg:address":"Walser Str 46",
    "sg:city":"Mittelberg",
    "sg:classifiers":[
        {
            "category":"Travel",
            "subcategory":"Hotels & Motels",
            "type":"Entertainment"
        }
    ],
    "sg:phone":"+43 5517 33640",
    "sg:postcode":"6993",
    "sg:province":"Vorarlberg",
    "wof:name":"IFA Hotel Alpenrose",
    "wof:placetype":"venue"
},
  "geometry": {"coordinates":[10.1587352753,47.3288078308],"type":"Point"}
}