{
  "type": "Feature",
  "properties": {
    "iso:country":"AT",
    "sg:address":"Hadeldorfstr 51",
    "sg:city":"Rankweil",
    "sg:orig_category":"Transportunternehmen",
    "sg:phone":"+43 5522 44112",
    "sg:postcode":"6830",
    "sg:province":"Vorarlberg",
    "wof:name":"Branner Franz Transport GmbH & Co KG",
    "wof:placetype":"venue"
},
  "geometry": {"coordinates":[9.6371908188,47.2767219543],"type":"Point"}
}