{
  "type": "Feature",
  "properties": {
    "addr:full":"Krahuletzpl 1 Eggenburg Nieder\u00f6sterreich 3730",
    "addr:housenumber":"1",
    "addr:postcode":"3730",
    "addr:street":"Krahuletzpl",
    "iso:country":"AT",
    "sg:address":"Krahuletzpl 1",
    "sg:city":"Eggenburg",
    "sg:orig_category":"Museen / Ausstellungen",
    "sg:phone":"+43 2984 34000",
    "sg:postcode":"3730",
    "sg:province":"Nieder\u00f6sterreich",
    "wof:name":"Krahuletz-Museum",
    "wof:placetype":"venue"
},
  "geometry": {"coordinates":[15.8175983429,48.6399116516],"type":"Point"}
}