{
  "type": "Feature",
  "properties": {
    "addr:full":"Igler Str 16 Innsbruck-Igls Tirol 6080",
    "addr:housenumber":"16",
    "addr:postcode":"6080",
    "addr:street":"Str",
    "iso:country":"AT",
    "sg:address":"Igler Str 16",
    "sg:city":"Innsbruck-Igls",
    "sg:orig_category":"Tischlereien",
    "sg:phone":"+43 512 370090",
    "sg:postcode":"6080",
    "sg:province":"Tirol",
    "sg:website":"hero-tischlerei.at",
    "wof:name":"Rofner Hermann",
    "wof:placetype":"venue"
},
  "geometry": {"coordinates":[11.4012298584,47.2370223999],"type":"Point"}
}