{
  "type": "Feature",
  "properties": {
    "addr:full":"Fuchsg 15 G\u00f6tzens Tirol 6091",
    "addr:housenumber":"15",
    "addr:postcode":"6091",
    "addr:street":"Fuchsg;Tirol",
    "iso:country":"AT",
    "sg:address":"Fuchsg 15",
    "sg:city":"G\u00f6tzens",
    "sg:orig_category":"Automaten",
    "sg:phone":"+43 5234 33466",
    "sg:postcode":"6091",
    "sg:province":"Tirol",
    "wof:name":"Automaten Rainer",
    "wof:placetype":"venue"
},
  "geometry": {"coordinates":[11.3000040054,47.238445282],"type":"Point"}
}