{
  "type": "Feature",
  "properties": {
    "addr:full":"Burgfriedstr 7 Amstetten Nieder\u00f6sterreich 3300",
    "addr:housenumber":"7",
    "addr:postcode":"3300",
    "addr:street":"Burgfriedstr;Niederoesterreich",
    "iso:country":"AT",
    "sg:address":"Burgfriedstr 7",
    "sg:city":"Amstetten",
    "sg:orig_category":"Damenmoden",
    "sg:phone":"+43 7472 68435",
    "sg:postcode":"3300",
    "sg:province":"Nieder\u00f6sterreich",
    "wof:name":"Leimlehner Karoline",
    "wof:placetype":"venue"
},
  "geometry": {"coordinates":[14.8752508163,48.1230201721],"type":"Point"}
}