{
  "type": "Feature",
  "properties": {
    "iso:country":"AT",
    "sg:address":"Seckauer Str 3a",
    "sg:city":"Knittelfeld",
    "sg:orig_category":"Fassbindereien",
    "sg:phone":"+43 4335 1282497",
    "sg:postcode":"8720",
    "sg:province":"Steiermark",
    "wof:name":"Eiletz Fa\u00dfbinderei Holz- u Korbwaren",
    "wof:placetype":"venue"
},
  "geometry": {"coordinates":[14.8340082169,47.2168045044],"type":"Point"}
}