{
  "type": "Feature",
  "properties": {
    "addr:full":"Birkenwald 14 Jenbach Tirol 6200",
    "addr:housenumber":"14",
    "addr:postcode":"6200",
    "addr:street":"Birkenwald;Tirol",
    "iso:country":"AT",
    "sg:address":"Birkenwald 14",
    "sg:city":"Jenbach",
    "sg:orig_category":"Feldenkraismethode",
    "sg:phone":"+43 4352 4493293",
    "sg:postcode":"6200",
    "sg:province":"Tirol",
    "wof:name":"Gemeinschaftspraxis Dr Gabriela Proksch & Mag Gerhard Proksch",
    "wof:placetype":"venue"
},
  "geometry": {"coordinates":[11.7620296478,47.3929214478],"type":"Point"}
}