{
  "type": "Feature",
  "properties": {
    "addr:full":"Hauptstr 5b Fohnsdorf Steiermark 8753",
    "addr:housenumber":"5b",
    "addr:postcode":"8753",
    "addr:street":"Hauptstr",
    "iso:country":"AT",
    "sg:address":"Hauptstr 5b",
    "sg:city":"Fohnsdorf",
    "sg:orig_category":"\u00c3\u201erzte / F Allgemeinmedizin",
    "sg:phone":"+43 664 5224660",
    "sg:postcode":"8753",
    "sg:province":"Steiermark",
    "wof:name":"Grohs Andreas Dr",
    "wof:placetype":"venue"
},
  "geometry": {"coordinates":[14.6766605377,47.2076835632],"type":"Point"}
}