{
  "type": "Feature",
  "properties": {
    "addr:full":"Am Golfplatz 4 Bad Tatzmannsdorf Burgenland 7431",
    "addr:housenumber":"4",
    "addr:postcode":"7431",
    "addr:street":"Am Golfplatz",
    "iso:country":"AT",
    "sg:address":"Am Golfplatz 4",
    "sg:city":"Bad Tatzmannsdorf",
    "sg:classifiers":[
        {
            "category":"Travel",
            "subcategory":"Hotels & Motels",
            "type":"Entertainment"
        }
    ],
    "sg:phone":"+43 3353 88550",
    "sg:postcode":"7431",
    "sg:province":"Burgenland",
    "wof:name":"Reiter's Avance Hotel Bad Tatzmannsdorf",
    "wof:placetype":"venue"
},
  "geometry": {"coordinates":[16.2396831512,47.3250198364],"type":"Point"}
}