{
  "type": "Feature",
  "properties": {
    "addr:full":"Nr 55 Maria Luggau K\u00e4rnten 9655",
    "addr:postcode":"9655",
    "addr:street":"Nr",
    "iso:country":"AT",
    "sg:address":"Nr 55",
    "sg:city":"Maria Luggau",
    "sg:orig_category":"Volksschulen",
    "sg:phone":"+43 4347 16502",
    "sg:postcode":"9655",
    "sg:province":"K\u00e4rnten",
    "wof:name":"Volksschule",
    "wof:placetype":"venue"
},
  "geometry": {"coordinates":[12.7352161407,46.7049674988],"type":"Point"}
}