{
  "type": "Feature",
  "properties": {
    "addr:full":"Herreng 5 Wels Ober\u00f6sterreich 4600",
    "addr:housenumber":"5",
    "addr:postcode":"4600",
    "addr:street":"Herreng;Oberoesterreich",
    "iso:country":"AT",
    "sg:address":"Herreng 5",
    "sg:city":"Wels",
    "sg:orig_category":"Personalbereitstellung",
    "sg:phone":"+43 7242 35727",
    "sg:postcode":"4600",
    "sg:province":"Ober\u00f6sterreich",
    "sg:website":"osc.cc",
    "wof:name":"OSC Personaldienstleistungen Brigitte Trattner GesmbH",
    "wof:placetype":"venue"
},
  "geometry": {"coordinates":[14.0283021927,48.1598243713],"type":"Point"}
}