{
  "type": "Feature",
  "properties": {
    "iso:country":"AT",
    "sg:address":"Hasnerstr 12",
    "sg:city":"Linz",
    "sg:orig_category":"Juwelen, Gold- U Silberwaren / Erzeugung U Gro\u00c3\u0178handel",
    "sg:phone":"+43 4373 2653150",
    "sg:postcode":"4020",
    "sg:province":"Ober\u00f6sterreich",
    "wof:name":"Sabitzer Edith",
    "wof:placetype":"venue"
},
  "geometry": {"coordinates":[14.2986869812,48.2859802246],"type":"Point"}
}