{
  "type": "Feature",
  "properties": {
    "addr:full":"Wiener Str 114 Ebreichsdorf Nieder\u00f6sterreich 2483",
    "addr:housenumber":"114",
    "addr:postcode":"2483",
    "iso:country":"AT",
    "sg:address":"Wiener Str 114",
    "sg:city":"Ebreichsdorf",
    "sg:orig_category":"Maschinenbau",
    "sg:phone":"+43 2254 73763",
    "sg:postcode":"2483",
    "sg:province":"Nieder\u00f6sterreich",
    "sg:website":"kammererform.com",
    "wof:name":"Kammerer Karl",
    "wof:placetype":"venue"
},
  "geometry": {"coordinates":[16.3966178894,47.9769554138],"type":"Point"}
}