{
  "type": "Feature",
  "properties": {
    "iso:country":"AT",
    "sg:address":"Unterdorf 5",
    "sg:city":"Egg",
    "sg:classifiers":[
        {
            "category":"Home & Garden",
            "subcategory":"Building Materials",
            "type":"Retail Goods"
        }
    ],
    "sg:phone":"+43 5512 3157",
    "sg:postcode":"6863",
    "sg:province":"Vorarlberg",
    "sg:tags":[
        "gravel",
        "crushed"
    ],
    "wof:name":"Leo Ratz",
    "wof:placetype":"venue"
},
  "geometry": {"coordinates":[9.9179897308,47.4338035583],"type":"Point"}
}