{
  "type": "Feature",
  "properties": {
    "iso:country":"AT",
    "sg:address":"Breitenfurter Strasse 331",
    "sg:city":"Wien",
    "sg:classifiers":[
        {
            "category":"Building & Trades",
            "subcategory":"Plumbing",
            "type":"Services"
        }
    ],
    "sg:phone":"+43 1 86923810",
    "sg:postcode":"1230",
    "sg:province":"Wien",
    "sg:tags":[
        "supraregional",
        "gas"
    ],
    "wof:name":"M\u00fcck-Sanit\u00e4r-Heizungs- und L\u00fcftungsanlagenbau Ges.m.b.H. & Co KG",
    "wof:placetype":"venue"
},
  "geometry": {"coordinates":[16.292432785,48.1426353455],"type":"Point"}
}