{
  "type": "Feature",
  "properties": {
    "addr:full":"Weimarer Str 5 Wien Wien 1180",
    "addr:housenumber":"5",
    "addr:postcode":"1180",
    "addr:street":"Str",
    "iso:country":"AT",
    "sg:address":"Weimarer Str 5",
    "sg:city":"Wien",
    "sg:orig_category":"Werbeagenturen",
    "sg:phone":"+43 1 40279190",
    "sg:postcode":"1180",
    "sg:province":"Wien",
    "wof:name":"Swennen GesmbH",
    "wof:placetype":"venue"
},
  "geometry": {"coordinates":[16.3402118683,48.2264022827],"type":"Point"}
}