{
  "type": "Feature",
  "properties": {
    "addr:full":"Hauptstr 18 Oberweiden Nieder\u00f6sterreich 2295",
    "addr:housenumber":"18;2295",
    "addr:street":"Hauptstr;Niederoesterreich",
    "iso:country":"AT",
    "sg:address":"Hauptstr 18",
    "sg:city":"Oberweiden",
    "sg:orig_category":"Non-Classified Establishments",
    "sg:phone":"+43 2284 20144",
    "sg:postcode":"2295",
    "sg:province":"Nieder\u00f6sterreich",
    "wof:name":"Schwestern vom Heiligen Johannes",
    "wof:placetype":"venue"
},
  "geometry": {"coordinates":[16.8277072906,48.3078346252],"type":"Point"}
}