{
  "type": "Feature",
  "properties": {
    "addr:full":"Favoritenstr 196 Wien Wien 1100",
    "addr:housenumber":"196",
    "addr:postcode":"1100",
    "iso:country":"AT",
    "sg:address":"Favoritenstr 196",
    "sg:city":"Wien",
    "sg:orig_category":"Glasereien",
    "sg:phone":"+43 1 6031403",
    "sg:postcode":"1100",
    "sg:province":"Wien",
    "wof:name":"Hollosi Franz",
    "wof:placetype":"venue"
},
  "geometry": {"coordinates":[16.3817253113,48.1649436951],"type":"Point"}
}