{
  "type": "Feature",
  "properties": {
    "addr:full":"Albrechtstr 29 Klosterneuburg Nieder\u00f6sterreich 3400",
    "addr:housenumber":"29",
    "addr:postcode":"3400",
    "addr:street":"Albrechtstr;Niederoesterreich",
    "iso:country":"AT",
    "sg:address":"Albrechtstr 29",
    "sg:city":"Klosterneuburg",
    "sg:orig_category":"Bekleidung / Einzelhandel",
    "sg:phone":"+43 2243 32918",
    "sg:postcode":"3400",
    "sg:province":"Nieder\u00f6sterreich",
    "wof:name":"Mariannes Mollig Moden",
    "wof:placetype":"venue"
},
  "geometry": {"coordinates":[16.321554184,48.3085441589],"type":"Point"}
}