{
  "type": "Feature",
  "properties": {
    "iso:country":"AT",
    "sg:address":"Am F\u00f6hrenwald 17",
    "sg:city":"Krumpendorf",
    "sg:classifiers":[
        {
            "category":"Travel",
            "subcategory":"Hotels & Motels",
            "type":"Entertainment"
        }
    ],
    "sg:phone":"+43 4342 2924760",
    "sg:postcode":"9201",
    "sg:province":"K\u00e4rnten",
    "wof:name":"Hotel F\u00f6hrenhof",
    "wof:placetype":"venue"
},
  "geometry": {"coordinates":[14.2104196548,46.6270256042],"type":"Point"}
}