{
  "type": "Feature",
  "properties": {
    "addr:full":"Trinser Str 2 Steinach am Brenner Tirol 6150",
    "addr:housenumber":"2",
    "addr:postcode":"6150",
    "addr:street":"Str;Tirol",
    "iso:country":"AT",
    "sg:address":"Trinser Str 2",
    "sg:city":"Steinach am Brenner",
    "sg:orig_category":"Pensionen / Privatzimmer",
    "sg:phone":"+43 5272 6215",
    "sg:postcode":"6150",
    "sg:province":"Tirol",
    "wof:name":"Haus Plattner - Fr\u00fcnst\u00fcckspension",
    "wof:placetype":"venue"
},
  "geometry": {"coordinates":[11.4651527405,47.0942306519],"type":"Point"}
}