{
  "type": "Feature",
  "properties": {
    "iso:country":"AT",
    "sg:address":"Alte Arlbergstr 7",
    "sg:city":"St. Anton am Arlberg",
    "sg:orig_category":"Werbeagenturen",
    "sg:phone":"+43 5446 2276",
    "sg:postcode":"6580",
    "sg:province":"Tirol",
    "wof:name":"Spiss Josef",
    "wof:placetype":"venue"
},
  "geometry": {"coordinates":[10.2623081207,47.1268424988],"type":"Point"}
}