{
  "type": "Feature",
  "properties": {
    "addr:full":"Nr 44 Windischgarsten Ober\u00f6sterreich 4580",
    "addr:postcode":"4580",
    "addr:street":"Nr;Oberoesterreich",
    "iso:country":"AT",
    "sg:address":"Nr 44",
    "sg:city":"Windischgarsten",
    "sg:orig_category":"Appartements / Ferienwohnungen",
    "sg:phone":"+43 7566 305",
    "sg:postcode":"4580",
    "sg:province":"Ober\u00f6sterreich",
    "wof:name":"Ferienhof Knirsch Fam Polz",
    "wof:placetype":"venue"
},
  "geometry": {"coordinates":[14.3275403976,47.7224311829],"type":"Point"}
}