{
  "type": "Feature",
  "properties": {
    "addr:full":"Hutteng 71-75 Wien Wien 1160",
    "addr:postcode":"71-75;1160",
    "iso:country":"AT",
    "sg:address":"Hutteng 71-75",
    "sg:city":"Wien",
    "sg:orig_category":"Non-Classified Establishments",
    "sg:phone":"+43 1 49313120",
    "sg:postcode":"1160",
    "sg:province":"Wien",
    "wof:name":"Huber & Huber GesmbH",
    "wof:placetype":"venue"
},
  "geometry": {"coordinates":[16.3101787567,48.2107276917],"type":"Point"}
}