{
  "type": "Feature",
  "properties": {
    "addr:full":"Vormarkt 16 Neumarkt im Hausruckkreis Ober\u00f6sterreich 4720",
    "addr:housenumber":"16",
    "addr:postcode":"4720",
    "addr:street":"Vormarkt",
    "iso:country":"AT",
    "sg:address":"Vormarkt 16",
    "sg:city":"Neumarkt im Hausruckkreis",
    "sg:orig_category":"Massagen",
    "sg:phone":"+43 4377 337867",
    "sg:postcode":"4720",
    "sg:province":"Ober\u00f6sterreich",
    "wof:name":"Massage-Fachinstitut Ziegler",
    "wof:placetype":"venue"
},
  "geometry": {"coordinates":[13.7239208221,48.2754173279],"type":"Point"}
}