{
  "type": "Feature",
  "properties": {
    "addr:full":"Bennopl 8/18 Wien Wien 1080",
    "addr:housenumber":"8 / 18",
    "addr:postcode":"1080",
    "addr:street":"Bennopl",
    "iso:country":"AT",
    "sg:address":"Bennopl 8/18",
    "sg:city":"Wien",
    "sg:orig_category":"Ergotherapie",
    "sg:phone":"+43 1 4024908",
    "sg:postcode":"1080",
    "sg:province":"Wien",
    "wof:name":"Moser Manuela Dipl-Erg",
    "wof:placetype":"venue"
},
  "geometry": {"coordinates":[16.3428440094,48.212184906],"type":"Point"}
}