{
  "type": "Feature",
  "properties": {
    "iso:country":"AT",
    "sg:address":"Taborstr 9",
    "sg:city":"Wien",
    "sg:orig_category":"Optiker",
    "sg:phone":"+43 4314 894600",
    "sg:postcode":"1020",
    "sg:province":"Wien",
    "wof:name":"Panorama Augenoptik GmbH",
    "wof:placetype":"venue"
},
  "geometry": {"coordinates":[16.3795166016,48.2136573792],"type":"Point"}
}