{
  "type": "Feature",
  "properties": {
    "addr:full":"Gutshofstr 18 Mistelbach Nieder\u00f6sterreich 2130",
    "addr:housenumber":"18",
    "addr:postcode":"2130",
    "addr:street":"Gutshofstr;Niederoesterreich",
    "iso:country":"AT",
    "sg:address":"Gutshofstr 18",
    "sg:city":"Mistelbach",
    "sg:orig_category":"Kosmetikanwendungsberatung",
    "sg:phone":"+43 2572 3939",
    "sg:postcode":"2130",
    "sg:province":"Nieder\u00f6sterreich",
    "wof:name":"Channoine Cosmetic",
    "wof:placetype":"venue"
},
  "geometry": {"coordinates":[16.547296524,48.5393333435],"type":"Point"}
}