{
  "type": "Feature",
  "properties": {
    "iso:country":"AT",
    "sg:address":"Bodenegg 34",
    "sg:city":"S\u00f6lden",
    "sg:orig_category":"Appartements / Ferienwohnungen",
    "sg:phone":"+43 5254 2865",
    "sg:postcode":"6450",
    "sg:province":"Tirol",
    "wof:name":"Rohrer Serafine",
    "wof:placetype":"venue"
},
  "geometry": {"coordinates":[10.9962701797,46.9261207581],"type":"Point"}
}