{
  "type": "Feature",
  "properties": {
    "iso:country":"AT",
    "sg:address":"Groissaustr 20",
    "sg:city":"Mauerbach",
    "sg:orig_category":"Bekleidung / Erzeugung U Gro\u00c3\u0178handel",
    "sg:phone":"+43 2273 7333",
    "sg:postcode":"3001",
    "sg:province":"Nieder\u00f6sterreich",
    "wof:name":"Schimanek Heinz Ing",
    "wof:placetype":"venue"
},
  "geometry": {"coordinates":[16.1535987854,48.2711219788],"type":"Point"}
}