{
  "type": "Feature",
  "properties": {
    "iso:country":"AT",
    "sg:address":"Hyrtlstr 22",
    "sg:city":"Brunn am Gebirge",
    "sg:orig_category":"Unternehmensberatung",
    "sg:phone":"+43 4322 36331820",
    "sg:postcode":"2345",
    "sg:province":"Nieder\u00f6sterreich",
    "wof:name":"GAA Automationstechnik GmbH Ing",
    "wof:placetype":"venue"
},
  "geometry": {"coordinates":[16.2782917023,48.1101379395],"type":"Point"}
}