{
  "type": "Feature",
  "properties": {
    "addr:full":"Westbahnstr 31 Wien Wien 1070",
    "addr:housenumber":"31",
    "addr:postcode":"1070",
    "addr:street":"Westbahnstr",
    "iso:country":"AT",
    "sg:address":"Westbahnstr 31",
    "sg:city":"Wien",
    "sg:orig_category":"Detekteien",
    "sg:phone":"+43 4315 221372",
    "sg:postcode":"1070",
    "sg:province":"Wien",
    "sg:website":"bm-investigations.at",
    "wof:name":"Auskunftei- Sicherheits- u Detektivunternehmen Mag Bernhard Maier",
    "wof:placetype":"venue"
},
  "geometry": {"coordinates":[16.3416805267,48.2017021179],"type":"Point"}
}