{
  "type": "Feature",
  "properties": {
    "addr:full":"Europastrasse 26 Feldbach Steiermark 8330",
    "addr:housenumber":"26",
    "addr:postcode":"8330",
    "addr:street":"Europastrasse",
    "iso:country":"AT",
    "sg:address":"Europastrasse 26",
    "sg:city":"Feldbach",
    "sg:classifiers":[
        {
            "category":"Food & Beverages",
            "subcategory":"Fruits & Vegetables",
            "type":"Retail Goods"
        }
    ],
    "sg:phone":"+43 3152 35120",
    "sg:postcode":"8330",
    "sg:province":"Steiermark",
    "sg:tags":[
        "canned"
    ],
    "sg:website":"feldbacher.at",
    "wof:name":"Feldbacher Konserven Ges.m.b.H.",
    "wof:placetype":"venue"
},
  "geometry": {"coordinates":[15.9029912949,46.9535560608],"type":"Point"}
}