{
  "type": "Feature",
  "properties": {
    "addr:full":"Alte Hauptstr 4 Hohenberg Nieder\u00f6sterreich 3192",
    "addr:housenumber":"4",
    "addr:postcode":"3192",
    "addr:street":"Alte Hauptstr",
    "iso:country":"AT",
    "sg:address":"Alte Hauptstr 4",
    "sg:city":"Hohenberg",
    "sg:orig_category":"Friseure U Frisiersalons",
    "sg:phone":"+43 4327 678302",
    "sg:postcode":"3192",
    "sg:province":"Nieder\u00f6sterreich",
    "wof:name":"Waidhofer Ulrike",
    "wof:placetype":"venue"
},
  "geometry": {"coordinates":[15.6185674667,47.911315918],"type":"Point"}
}