{
  "type": "Feature",
  "properties": {
    "iso:country":"AT",
    "sg:address":"Rosental Bundesstr 145",
    "sg:city":"Neukirchen am Gro\u00dfvenediger",
    "sg:orig_category":"Schmieden U Schmiedeeisenelemente",
    "sg:phone":"+43 4365 656284",
    "sg:postcode":"5741",
    "sg:province":"Salzburg",
    "wof:name":"Karl Siegfried",
    "wof:placetype":"venue"
},
  "geometry": {"coordinates":[12.2524347305,47.2472953796],"type":"Point"}
}