{
  "type": "Feature",
  "properties": {
    "addr:full":"Staudenweg 14 Dornbirn Vorarlberg 6850",
    "addr:housenumber":"14",
    "addr:postcode":"6850",
    "addr:street":"Staudenweg",
    "iso:country":"AT",
    "sg:address":"Staudenweg 14",
    "sg:city":"Dornbirn",
    "sg:orig_category":"Detekteien",
    "sg:phone":"+43 5572 52891",
    "sg:postcode":"6850",
    "sg:province":"Vorarlberg",
    "wof:name":"Detektei Lingg",
    "wof:placetype":"venue"
},
  "geometry": {"coordinates":[9.7494401932,47.4334411621],"type":"Point"}
}