{
  "type": "Feature",
  "properties": {
    "iso:country":"AT",
    "sg:address":"M\u00fcnzwardeing 4",
    "sg:city":"Wien",
    "sg:orig_category":"Notare",
    "sg:phone":"+43 1 5861212",
    "sg:postcode":"1060",
    "sg:province":"Wien",
    "wof:name":"Altmann Werner Dr",
    "wof:placetype":"venue"
},
  "geometry": {"coordinates":[16.3504657745,48.1947135925],"type":"Point"}
}