{
  "type": "Feature",
  "properties": {
    "addr:full":"Kirchenpl 7 Wolkersdorf im Weinviertel Nieder\u00f6sterreich 2120",
    "addr:housenumber":"7",
    "addr:postcode":"2120",
    "addr:street":"Kirchenpl",
    "iso:country":"AT",
    "sg:address":"Kirchenpl 7",
    "sg:city":"Wolkersdorf im Weinviertel",
    "sg:orig_category":"Sonderschulen",
    "sg:phone":"+43 4322 452794",
    "sg:postcode":"2120",
    "sg:province":"Nieder\u00f6sterreich",
    "wof:name":"Allgemeine Sonderschule",
    "wof:placetype":"venue"
},
  "geometry": {"coordinates":[16.5189800262,48.3824157715],"type":"Point"}
}