{
  "type": "Feature",
  "properties": {
    "addr:full":"Seenstr 50 Reifnitz K\u00e4rnten 9081",
    "addr:housenumber":"50",
    "addr:postcode":"9081",
    "addr:street":"Seenstr;Kaernten",
    "iso:country":"AT",
    "sg:address":"Seenstr 50",
    "sg:city":"Reifnitz",
    "sg:orig_category":"\u00c3\u201erzte / F Allgemeinmedizin",
    "sg:phone":"+43 4273 3238",
    "sg:postcode":"9081",
    "sg:province":"K\u00e4rnten",
    "wof:name":"Schulz Norbert Dr",
    "wof:placetype":"venue"
},
  "geometry": {"coordinates":[14.1737747192,46.5999031067],"type":"Point"}
}