{
  "type": "Feature",
  "properties": {
    "iso:country":"AT",
    "sg:address":"Linzer Bundesstr 25",
    "sg:city":"Gnigl",
    "sg:orig_category":"Bekleidung / Einzelhandel",
    "sg:phone":"+43 662 6428270",
    "sg:postcode":"5023",
    "sg:province":"Salzburg",
    "sg:website":"gollackner.at",
    "wof:name":"Mode Gollackner - Walter Gollackner",
    "wof:placetype":"venue"
},
  "geometry": {"coordinates":[13.0680036545,47.813835144],"type":"Point"}
}