{
  "type": "Feature",
  "properties": {
    "addr:full":"Beethoveng 3/5 Wien Wien 1090",
    "addr:housenumber":"3 / 5",
    "addr:postcode":"1090",
    "addr:street":"Beethoveng",
    "iso:country":"AT",
    "sg:address":"Beethoveng 3/5",
    "sg:city":"Wien",
    "sg:orig_category":"\u00c3\u201erzte / F Allgemeinmedizin",
    "sg:phone":"+43 699 19585808",
    "sg:postcode":"1090",
    "sg:province":"Wien",
    "wof:name":"Bodisch Astrid Dr",
    "wof:placetype":"venue"
},
  "geometry": {"coordinates":[16.3566398621,48.2176361084],"type":"Point"}
}