{
  "type": "Feature",
  "properties": {
    "addr:full":"St. Leonharder Str 31 Landskron K\u00e4rnten 9523",
    "addr:housenumber":"31",
    "addr:postcode":"9523",
    "addr:street":"St.;Str;Kaernten",
    "iso:country":"AT",
    "sg:address":"St. Leonharder Str 31",
    "sg:city":"Landskron",
    "sg:orig_category":"Lebensmittel / Einzelhandel",
    "sg:phone":"+43 4242 45425",
    "sg:postcode":"9523",
    "sg:province":"K\u00e4rnten",
    "wof:name":"SPAR \u00f6sterreichische Warenhandels AG",
    "wof:placetype":"venue"
},
  "geometry": {"coordinates":[13.8641653061,46.6278953552],"type":"Point"}
}