{
  "type": "Feature",
  "properties": {
    "iso:country":"AT",
    "sg:address":"Hauptstr 7",
    "sg:city":"Dra\u00dfmarkt",
    "sg:orig_category":"Teigwaren",
    "sg:phone":"+43 2617 2216",
    "sg:postcode":"7372",
    "sg:province":"Burgenland",
    "wof:name":"Werkovits Frischeier GesmbH & Co KG",
    "wof:placetype":"venue"
},
  "geometry": {"coordinates":[-79.06452178959999,41.010345459],"type":"Point"}
}