{
  "type": "Feature",
  "properties": {
    "addr:full":"Kirchg 1 Mittersill Salzburg 5730",
    "addr:housenumber":"1",
    "addr:postcode":"5730",
    "addr:street":"Kirchg;Salzburg",
    "iso:country":"AT",
    "sg:address":"Kirchg 1",
    "sg:city":"Mittersill",
    "sg:orig_category":"Blumeneinzelhandel",
    "sg:phone":"+43 6562 63060",
    "sg:postcode":"5730",
    "sg:province":"Salzburg",
    "wof:name":"Blumenecke Tildach Roswitha",
    "wof:placetype":"venue"
},
  "geometry": {"coordinates":[12.4822015762,47.2807769775],"type":"Point"}
}