{
  "type": "Feature",
  "properties": {
    "iso:country":"AT",
    "sg:address":"Meinhardstr 7/1",
    "sg:city":"Innsbruck",
    "sg:orig_category":"Sonnenstudios",
    "sg:phone":"+43 512 571011",
    "sg:postcode":"6020",
    "sg:province":"Tirol",
    "wof:name":"Sonnenstudio SOLEIT",
    "wof:placetype":"venue"
},
  "geometry": {"coordinates":[11.3991346359,47.2658309937],"type":"Point"}
}