{
  "type": "Feature",
  "properties": {
    "iso:country":"AT",
    "sg:address":"Industriestr 1",
    "sg:city":"Amstetten",
    "sg:orig_category":"Damenmoden",
    "sg:phone":"+43 7472 23203",
    "sg:postcode":"3300",
    "sg:province":"Nieder\u00f6sterreich",
    "wof:name":"KiK Textilien und Non-Food GesmbH",
    "wof:placetype":"venue"
},
  "geometry": {"coordinates":[14.9071817398,48.1187133789],"type":"Point"}
}