{
  "type": "Feature",
  "properties": {
    "addr:full":"Klosterg 9 Wien Wien 1180",
    "addr:housenumber":"9",
    "addr:postcode":"1180",
    "addr:street":"Klosterg",
    "iso:country":"AT",
    "sg:address":"Klosterg 9",
    "sg:city":"Wien",
    "sg:orig_category":"Markt- U Meinungsforschung",
    "sg:phone":"+43 1 47966200",
    "sg:postcode":"1180",
    "sg:province":"Wien",
    "wof:name":"Marketing Data",
    "wof:placetype":"venue"
},
  "geometry": {"coordinates":[16.333278656,48.225353241],"type":"Point"}
}