{
  "type": "Feature",
  "properties": {
    "addr:full":"Frauentaler Str 58 Deutschlandsberg Steiermark 8530",
    "addr:postcode":"8530",
    "addr:street":"Str 58",
    "iso:country":"AT",
    "sg:address":"Frauentaler Str 58",
    "sg:city":"Deutschlandsberg",
    "sg:orig_category":"Rechenzentren",
    "sg:phone":"+43 3462 43106",
    "sg:postcode":"8530",
    "sg:province":"Steiermark",
    "wof:name":"AHP Achleitner EDV OEG",
    "wof:placetype":"venue"
},
  "geometry": {"coordinates":[15.2240467072,46.818145752],"type":"Point"}
}