{
  "type": "Feature",
  "properties": {
    "addr:full":"Am Kuhberg 3 EKZ Horn Horn Nieder\u00f6sterreich 3580",
    "addr:housenumber":"3",
    "addr:postcode":"3580",
    "addr:street":"Am Kuhberg;Niederoesterreich",
    "iso:country":"AT",
    "sg:address":"Am Kuhberg 3 EKZ Horn",
    "sg:city":"Horn",
    "sg:orig_category":"Restaurants: Amerikanisch",
    "sg:phone":"+43 4329 8220355",
    "sg:postcode":"3580",
    "sg:province":"Nieder\u00f6sterreich",
    "wof:name":"McDonald's Restaurant - McDrive",
    "wof:placetype":"venue"
},
  "geometry": {"coordinates":[15.6574287415,48.6637763977],"type":"Point"}
}