{
  "type": "Feature",
  "properties": {
    "addr:full":"Staig 32 Schwanenstadt Ober\u00f6sterreich 4690",
    "addr:housenumber":"32",
    "addr:postcode":"4690",
    "addr:street":"Staig",
    "iso:country":"AT",
    "sg:address":"Staig 32",
    "sg:city":"Schwanenstadt",
    "sg:classifiers":[
        {
            "category":"Bus Stop",
            "subcategory":"None",
            "type":"Transportation"
        }
    ],
    "sg:phone":"+43 767369960",
    "sg:postcode":"4690",
    "sg:province":"Ober\u00f6sterreich",
    "sg:tags":[
        "current",
        "direct",
        "generator"
    ],
    "sg:website":"kwg.at",
    "wof:name":"Kraftwerk Glatzing- R\u00fcstorf reg.Gen.m.b.H.",
    "wof:placetype":"venue"
},
  "geometry": {"coordinates":[13.7819442749,48.0625152588],"type":"Point"}
}