{
  "type": "Feature",
  "properties": {
    "addr:full":"Unternberg 10 Neufelden Ober\u00f6sterreich 4120",
    "addr:housenumber":"10",
    "addr:postcode":"4120",
    "addr:street":"Unternberg",
    "iso:country":"AT",
    "sg:address":"Unternberg 10",
    "sg:city":"Neufelden",
    "sg:orig_category":"Transportunternehmen",
    "sg:phone":"+43 7282 62460",
    "sg:postcode":"4120",
    "sg:province":"Ober\u00f6sterreich",
    "wof:name":"Erlacher Kurt",
    "wof:placetype":"venue"
},
  "geometry": {"coordinates":[14.0024909973,48.4814758301],"type":"Point"}
}