{
  "type": "Feature",
  "properties": {
    "addr:full":"Friedrich Schmidt-Pl 5 Wien Wien 1080",
    "addr:housenumber":"5",
    "addr:postcode":"1080",
    "iso:country":"AT",
    "sg:address":"Friedrich Schmidt-Pl 5",
    "sg:city":"Wien",
    "sg:classifiers":[
        {
            "category":"Professional",
            "subcategory":"Testing Lab",
            "type":"Services"
        }
    ],
    "sg:phone":"+43 1 400013",
    "sg:postcode":"1080",
    "sg:province":"Wien",
    "sg:tags":[
        "magistrate"
    ],
    "wof:name":"Magistrat d Stadt Wien - MA 13 - Bildung und au\u00dferschulische Jugendbetreuung",
    "wof:placetype":"venue"
},
  "geometry": {"coordinates":[16.3550262451,48.211265564],"type":"Point"}
}