{
  "type": "Feature",
  "properties": {
    "addr:full":"10.Oktober-Str 28 Steinfeld K\u00e4rnten 9754",
    "addr:housenumber":"28",
    "addr:postcode":"9754",
    "addr:street":"10.Oktober-Str",
    "iso:country":"AT",
    "sg:address":"10.Oktober-Str 28",
    "sg:city":"Steinfeld",
    "sg:orig_category":"Volksschulen",
    "sg:phone":"+43 4347 17351",
    "sg:postcode":"9754",
    "sg:province":"K\u00e4rnten",
    "wof:name":"Volksschule Steinfeld",
    "wof:placetype":"venue"
},
  "geometry": {"coordinates":[13.2566356659,46.7601127625],"type":"Point"}
}