{
  "type": "Feature",
  "properties": {
    "addr:full":"Schaumburgerg 7 Wien Wien 1040",
    "addr:housenumber":"7",
    "addr:postcode":"1040",
    "addr:street":"Schaumburgerg",
    "iso:country":"AT",
    "sg:address":"Schaumburgerg 7",
    "sg:city":"Wien",
    "sg:orig_category":"Hauptschulen",
    "sg:phone":"+43 1 5057440",
    "sg:postcode":"1040",
    "sg:province":"Wien",
    "wof:name":"Schulen d Stadt Wien",
    "wof:placetype":"venue"
},
  "geometry": {"coordinates":[16.3681049347,48.1910057068],"type":"Point"}
}