{
  "type": "Feature",
  "properties": {
    "iso:country":"AT",
    "sg:address":"Schwarzseestr 2",
    "sg:city":"Kitzb\u00fchel",
    "sg:orig_category":"Innenausbau",
    "sg:phone":"+43 5356 62575",
    "sg:postcode":"6370",
    "sg:province":"Tirol",
    "wof:name":"Weixlbaumer Josef",
    "wof:placetype":"venue"
},
  "geometry": {"coordinates":[12.3857469559,47.4476242065],"type":"Point"}
}