{
  "type": "Feature",
  "properties": {
    "iso:country":"AT",
    "sg:address":"Landstra\u00dfer Hauptstr 9",
    "sg:city":"Wien",
    "sg:orig_category":"Baumeister",
    "sg:phone":"+43 1 71895220",
    "sg:postcode":"1030",
    "sg:province":"Wien",
    "wof:name":"Rameder Gerald Ing",
    "wof:placetype":"venue"
},
  "geometry": {"coordinates":[16.3869514465,48.2055168152],"type":"Point"}
}