{
  "type": "Feature",
  "properties": {
    "addr:full":"Graf-Mailath-G 2 Hinterbr\u00fchl Nieder\u00f6sterreich 2371",
    "addr:housenumber":"2",
    "addr:postcode":"2371",
    "addr:street":"Graf-Mailath-G;Niederoesterreich",
    "iso:country":"AT",
    "sg:address":"Graf-Mailath-G 2",
    "sg:city":"Hinterbr\u00fchl",
    "sg:orig_category":"Tabaktrafiken",
    "sg:phone":"+43 2236 864128",
    "sg:postcode":"2371",
    "sg:province":"Nieder\u00f6sterreich",
    "wof:name":"Glaser Alexander",
    "wof:placetype":"venue"
},
  "geometry": {"coordinates":[-90.86995697019999,42.493938446],"type":"Point"}
}