{
  "type": "Feature",
  "properties": {
    "addr:full":"Dorfbahnstr 22 Serfaus Tirol 6534",
    "addr:housenumber":"22",
    "addr:postcode":"6534",
    "addr:street":"Dorfbahnstr;Tirol",
    "iso:country":"AT",
    "sg:address":"Dorfbahnstr 22",
    "sg:city":"Serfaus",
    "sg:orig_category":"Pensionen / Privatzimmer",
    "sg:phone":"+43 5476 62190",
    "sg:postcode":"6534",
    "sg:province":"Tirol",
    "wof:name":"Haus Alpina",
    "wof:placetype":"venue"
},
  "geometry": {"coordinates":[10.6089048386,47.0382652283],"type":"Point"}
}