{
  "type": "Feature",
  "properties": {
    "addr:full":"Haidfeldstr 25 Leonding Ober\u00f6sterreich 4060",
    "addr:housenumber":"25",
    "addr:postcode":"4060",
    "addr:street":"Haidfeldstr",
    "iso:country":"AT",
    "sg:address":"Haidfeldstr 25",
    "sg:city":"Leonding",
    "sg:orig_category":"Schilder, Graveure",
    "sg:phone":"+43 732 6821960",
    "sg:postcode":"4060",
    "sg:province":"Ober\u00f6sterreich",
    "sg:website":"schwark.at",
    "wof:name":"Schwark Dieter",
    "wof:placetype":"venue"
},
  "geometry": {"coordinates":[14.2599143982,48.2564353943],"type":"Point"}
}