{
  "type": "Feature",
  "properties": {
    "addr:full":"Schulg 1 Bad Ischl Ober\u00f6sterreich 4820",
    "addr:housenumber":"1",
    "addr:postcode":"4820",
    "addr:street":"Schulg",
    "iso:country":"AT",
    "sg:address":"Schulg 1",
    "sg:city":"Bad Ischl",
    "sg:orig_category":"Boutiquen",
    "sg:phone":"+43 6132 282770",
    "sg:postcode":"4820",
    "sg:province":"Ober\u00f6sterreich",
    "wof:name":"Boutique Brigitte Couture Inh Brigitte Reiter",
    "wof:placetype":"venue"
},
  "geometry": {"coordinates":[13.6222372055,47.7112808228],"type":"Point"}
}