{
  "type": "Feature",
  "properties": {
    "iso:country":"AT",
    "sg:address":"Im Astenfeld 5",
    "sg:city":"St. Florian",
    "sg:orig_category":"Natursteine U -Platten",
    "sg:phone":"+43 4372 2465860",
    "sg:postcode":"4490",
    "sg:province":"Ober\u00f6sterreich",
    "sg:website":"steindiscount.com",
    "wof:name":"Steindiscount",
    "wof:placetype":"venue"
},
  "geometry": {"coordinates":[14.3969602585,48.2236061096],"type":"Point"}
}