{
  "type": "Feature",
  "properties": {
    "addr:full":"St Peter-Str 5a/1/180 Klagenfurt K\u00e4rnten 9020",
    "addr:housenumber":"5a / 1 / 180",
    "addr:postcode":"9020",
    "addr:street":"Kaernten",
    "iso:country":"AT",
    "sg:address":"St Peter-Str 5a/1/180",
    "sg:city":"Klagenfurt",
    "sg:classifiers":[
        {
            "category":"Internet Cafe",
            "subcategory":"None",
            "type":"Food & Drink"
        }
    ],
    "sg:phone":"+43 463 503221",
    "sg:postcode":"9020",
    "sg:province":"K\u00e4rnten",
    "sg:tags":[
        "internet-provider"
    ],
    "wof:name":"Chin Thai Electronics Network",
    "wof:placetype":"venue"
},
  "geometry": {"coordinates":[14.3274202347,46.6254196167],"type":"Point"}
}