{
  "type": "Feature",
  "properties": {
    "iso:country":"AT",
    "sg:address":"Linzer Str 6",
    "sg:city":"Gallneukirchen",
    "sg:orig_category":"Non-Classified Establishments",
    "sg:phone":"+43 5 91334330",
    "sg:postcode":"4210",
    "sg:province":"Ober\u00f6sterreich",
    "wof:name":"Gendarmerieposten",
    "wof:placetype":"venue"
},
  "geometry": {"coordinates":[14.4125652313,48.3509902954],"type":"Point"}
}