{
  "type": "Feature",
  "properties": {
    "addr:full":"Au bei Ed 5 Natternbach Ober\u00f6sterreich 4723",
    "addr:housenumber":"5",
    "addr:postcode":"4723",
    "addr:street":"Au Bei Ed",
    "iso:country":"AT",
    "sg:address":"Au bei Ed 5",
    "sg:city":"Natternbach",
    "sg:orig_category":"Pensionen / Privatzimmer",
    "sg:phone":"+43 7278 8467",
    "sg:postcode":"4723",
    "sg:province":"Ober\u00f6sterreich",
    "wof:name":"Ferienhof Wimmer",
    "wof:placetype":"venue"
},
  "geometry": {"coordinates":[13.7073917389,48.3970603943],"type":"Point"}
}