{
  "type": "Feature",
  "properties": {
    "addr:full":"Nr 288 Zellerndorf Nieder\u00f6sterreich 2051",
    "addr:postcode":"2051",
    "addr:street":"Nr",
    "iso:country":"AT",
    "sg:address":"Nr 288",
    "sg:city":"Zellerndorf",
    "sg:orig_category":"Gemeinden",
    "sg:phone":"+43 2945 2214",
    "sg:postcode":"2051",
    "sg:province":"Nieder\u00f6sterreich",
    "wof:name":"Gemeindeamt Zellerndorf",
    "wof:placetype":"venue"
},
  "geometry": {"coordinates":[15.9574575424,48.6949920654],"type":"Point"}
}