{
  "type": "Feature",
  "properties": {
    "iso:country":"AT",
    "sg:address":"Haberditzlg 1-3",
    "sg:city":"Wien",
    "sg:classifiers":[
        {
            "category":"Restaurant",
            "type":"Food & Drink"
        }
    ],
    "sg:phone":"+43 1 2598383",
    "sg:postcode":"1210",
    "sg:province":"Wien",
    "wof:name":"Restaurant zur Kastanie",
    "wof:placetype":"venue"
},
  "geometry": {"coordinates":[16.4525680542,48.2704963684],"type":"Point"}
}