{
  "type": "Feature",
  "properties": {
    "addr:full":"Anton-Krieger-G 186 Wien Wien 1230",
    "addr:housenumber":"186",
    "addr:postcode":"1230",
    "iso:country":"AT",
    "sg:address":"Anton-Krieger-G 186",
    "sg:city":"Wien",
    "sg:classifiers":[
        {
            "category":"Taxi",
            "type":"Transportation"
        }
    ],
    "sg:phone":"+43 4366 44444888",
    "sg:postcode":"1230",
    "sg:province":"Wien",
    "sg:tags":[
        "personentransporte",
        "u"
    ],
    "wof:name":"Markov Lucian",
    "wof:placetype":"venue"
},
  "geometry": {"coordinates":[16.2580451965,48.1450958252],"type":"Point"}
}