{
  "type": "Feature",
  "properties": {
    "addr:full":"Josef-Berghold-Str.5  Traiskirchen Nieder\u00f6sterreich 2514",
    "addr:postcode":"2514",
    "addr:street":"Niederoesterreich",
    "iso:country":"AT",
    "sg:address":"Josef-Berghold-Str.5 ",
    "sg:city":"Traiskirchen",
    "sg:classifiers":[
        {
            "category":"Bars & Pubs",
            "subcategory":"Nightclub",
            "type":"Food & Drink"
        }
    ],
    "sg:phone":"+43 4322 5252314",
    "sg:postcode":"2514",
    "sg:province":"Nieder\u00f6sterreich",
    "sg:tags":[
        "cake",
        "bread"
    ],
    "wof:name":"HARALD W\u00d6BER",
    "wof:placetype":"venue"
},
  "geometry": {"coordinates":[16.303144455,48.0256958008],"type":"Point"}
}