{
  "type": "Feature",
  "properties": {
    "addr:full":"Wilhelmstr 47 Wien Wien 1120",
    "addr:housenumber":"47",
    "addr:postcode":"1120",
    "addr:street":"Wilhelmstr",
    "iso:country":"AT",
    "sg:address":"Wilhelmstr 47",
    "sg:city":"Wien",
    "sg:classifiers":[
        {
            "category":"Professional",
            "subcategory":"Art Services",
            "type":"Services"
        }
    ],
    "sg:phone":"+43 1 8126835",
    "sg:postcode":"1120",
    "sg:province":"Wien",
    "sg:tags":[
        "designer"
    ],
    "wof:name":"Hohenecker Harald Ing - Industrial Design",
    "wof:placetype":"venue"
},
  "geometry": {"coordinates":[16.33253479,48.1753845215],"type":"Point"}
}