{
  "type": "Feature",
  "properties": {
    "addr:full":"Swatoschg 3 Wien Wien 1110",
    "addr:housenumber":"3",
    "addr:postcode":"1110",
    "addr:street":"Swatoschg",
    "iso:country":"AT",
    "sg:address":"Swatoschg 3",
    "sg:city":"Wien",
    "sg:orig_category":"Tabaktrafiken",
    "sg:phone":"+43 1 7492189",
    "sg:postcode":"1110",
    "sg:province":"Wien",
    "wof:name":"K\u00f6nig Caroline",
    "wof:placetype":"venue"
},
  "geometry": {"coordinates":[16.4121856689,48.166595459],"type":"Point"}
}