{
  "type": "Feature",
  "properties": {
    "addr:full":"Perfektastr 57 Wien Wien 1230",
    "addr:housenumber":"57",
    "addr:postcode":"1230",
    "addr:street":"Perfektastr",
    "iso:country":"AT",
    "sg:address":"Perfektastr 57",
    "sg:city":"Wien",
    "sg:orig_category":"Abflussdienste",
    "sg:phone":"+43 4316 99090",
    "sg:postcode":"1230",
    "sg:province":"Wien",
    "sg:website":"sus.at",
    "wof:name":"SUS Abflu\u00dfdienst GesmbH",
    "wof:placetype":"venue"
},
  "geometry": {"coordinates":[16.3159275055,48.1369018555],"type":"Point"}
}