{
  "type": "Feature",
  "properties": {
    "addr:full":"Larnhauserweg 1 Leonding Ober\u00f6sterreich 4060",
    "addr:housenumber":"1",
    "addr:postcode":"4060",
    "addr:street":"Larnhauserweg",
    "iso:country":"AT",
    "sg:address":"Larnhauserweg 1",
    "sg:city":"Leonding",
    "sg:orig_category":"Installationsunternehmen",
    "sg:phone":"+43 664 7817430",
    "sg:postcode":"4060",
    "sg:province":"Ober\u00f6sterreich",
    "wof:name":"Gumpenberger Werner",
    "wof:placetype":"venue"
},
  "geometry": {"coordinates":[14.2735567093,48.2740898132],"type":"Point"}
}