{
  "type": "Feature",
  "properties": {
    "addr:full":"Georg Pirmoser-Str 7 Kufstein Tirol 6330",
    "addr:housenumber":"7",
    "addr:postcode":"6330",
    "addr:street":"Tirol",
    "iso:country":"AT",
    "sg:address":"Georg Pirmoser-Str 7",
    "sg:city":"Kufstein",
    "sg:orig_category":"Friseure U Frisiersalons",
    "sg:phone":"+43 4353 7261916",
    "sg:postcode":"6330",
    "sg:province":"Tirol",
    "wof:name":"Haarstudio B",
    "wof:placetype":"venue"
},
  "geometry": {"coordinates":[12.1720523834,47.5829086304],"type":"Point"}
}