{
  "type": "Feature",
  "properties": {
    "addr:full":"Czeija-Nissl-G. 6 Wien Wien 1210",
    "addr:housenumber":"6",
    "addr:postcode":"1210",
    "addr:street":"Czeija-Nissl-G.",
    "iso:country":"AT",
    "sg:address":"Czeija-Nissl-G. 6",
    "sg:city":"Wien",
    "sg:classifiers":[
        {
            "category":"Parking",
            "subcategory":"Lot",
            "type":"Transportation"
        }
    ],
    "sg:phone":"+43 4312 7060880",
    "sg:postcode":"1210",
    "sg:province":"Wien",
    "sg:tags":[
        "transport",
        "road"
    ],
    "wof:name":"R\u00d6MER GES.MBH",
    "wof:placetype":"venue"
},
  "geometry": {"coordinates":[16.3751888275,48.2848587036],"type":"Point"}
}