{
  "type": "Feature",
  "properties": {
    "addr:full":"Nr 129 Obervellach K\u00e4rnten 9821",
    "addr:postcode":"9821",
    "addr:street":"Nr 129;Kaernten",
    "iso:country":"AT",
    "sg:address":"Nr 129",
    "sg:city":"Obervellach",
    "sg:orig_category":"Bauunternehmen",
    "sg:phone":"+43 4782 29870",
    "sg:postcode":"9821",
    "sg:province":"K\u00e4rnten",
    "wof:name":"MBZ M\u00f6lltaler Bauzentrum GesmbH",
    "wof:placetype":"venue"
},
  "geometry": {"coordinates":[13.202000618,46.9322319031],"type":"Point"}
}