{
  "type": "Feature",
  "properties": {
    "addr:full":"Hinterkaiserweg 26 St. Johann in Tirol Tirol 6380",
    "addr:housenumber":"26",
    "addr:postcode":"6380",
    "addr:street":"Hinterkaiserweg;Tirol",
    "iso:country":"AT",
    "sg:address":"Hinterkaiserweg 26",
    "sg:city":"St. Johann in Tirol",
    "sg:orig_category":"Zimmereien",
    "sg:phone":"+43 5352 63501",
    "sg:postcode":"6380",
    "sg:province":"Tirol",
    "wof:name":"Meickl Raimund GmbH & Co KG",
    "wof:placetype":"venue"
},
  "geometry": {"coordinates":[12.4191131592,47.5277824402],"type":"Point"}
}