{
  "type": "Feature",
  "properties": {
    "addr:full":"Robinigstr 15 Salzburg Salzburg 5020",
    "addr:housenumber":"15",
    "addr:postcode":"5020",
    "addr:street":"Robinigstr;Salzburg",
    "iso:country":"AT",
    "sg:address":"Robinigstr 15",
    "sg:city":"Salzburg",
    "sg:classifiers":[
        {
            "category":"Restaurant",
            "type":"Food & Drink"
        }
    ],
    "sg:phone":"+43 662 882486",
    "sg:postcode":"5020",
    "sg:province":"Salzburg",
    "sg:tags":[
        "pizzeria"
    ],
    "wof:name":"Pizzeria Da Ciro",
    "wof:placetype":"venue"
},
  "geometry": {"coordinates":[13.0593824387,47.8109817505],"type":"Point"}
}