{
  "type": "Feature",
  "properties": {
    "addr:full":"Martinstr 92 Wien Wien 1180",
    "addr:housenumber":"92",
    "addr:postcode":"1180",
    "addr:street":"Martinstr",
    "iso:country":"AT",
    "sg:address":"Martinstr 92",
    "sg:city":"Wien",
    "sg:orig_category":"Politische Parteien",
    "sg:phone":"+43 1 40641650",
    "sg:postcode":"1180",
    "sg:province":"Wien",
    "wof:name":"\u00f6sterreichische Volkspartei",
    "wof:placetype":"venue"
},
  "geometry": {"coordinates":[16.3423461914,48.2259254456],"type":"Point"}
}