{
  "type": "Feature",
  "properties": {
    "addr:full":"S\u00fc\u00dfenbrunner Strasse 66/3/18 Wien Wien 1220",
    "addr:housenumber":"66 / 3 / 18",
    "addr:postcode":"1220",
    "addr:street":"Suessenbrunner Strasse",
    "iso:country":"AT",
    "sg:address":"S\u00fc\u00dfenbrunner Strasse 66/3/18",
    "sg:city":"Wien",
    "sg:classifiers":[
        {
            "category":"Wholesale",
            "subcategory":"Office Equipment",
            "type":"Manufacturing & Wholesale Goods"
        }
    ],
    "sg:phone":"+43 1 7344978",
    "sg:postcode":"1220",
    "sg:province":"Wien",
    "sg:tags":[
        "agency",
        "internet"
    ],
    "sg:website":"asantic.at",
    "wof:name":"ASANTIC Internet Solutions",
    "wof:placetype":"venue"
},
  "geometry": {"coordinates":[16.444606781,48.2497138977],"type":"Point"}
}