{
  "type": "Feature",
  "properties": {
    "addr:full":"Dirnbergerstr 3 Perg Ober\u00f6sterreich 4320",
    "addr:housenumber":"3",
    "addr:postcode":"4320",
    "addr:street":"Dirnbergerstr",
    "iso:country":"AT",
    "sg:address":"Dirnbergerstr 3",
    "sg:city":"Perg",
    "sg:orig_category":"Friseure U Frisiersalons",
    "sg:phone":"+43 4372 6252374",
    "sg:postcode":"4320",
    "sg:province":"Ober\u00f6sterreich",
    "wof:name":"Hanl Martin",
    "wof:placetype":"venue"
},
  "geometry": {"coordinates":[14.634771347,48.2479743958],"type":"Point"}
}