{
  "type": "Feature",
  "properties": {
    "addr:full":"Ing.-Etzel-Str 31a Innsbruck Tirol 6020",
    "addr:housenumber":"31a",
    "addr:postcode":"6020",
    "addr:street":"Ing.-Etzel-Str;Tirol",
    "iso:country":"AT",
    "sg:address":"Ing.-Etzel-Str 31a",
    "sg:city":"Innsbruck",
    "sg:orig_category":"Tabaktrafiken",
    "sg:phone":"+43 512 587195",
    "sg:postcode":"6020",
    "sg:province":"Tirol",
    "wof:name":"Lowin Andreas",
    "wof:placetype":"venue"
},
  "geometry": {"coordinates":[11.4038295746,47.2708816528],"type":"Point"}
}