{
  "type": "Feature",
  "properties": {
    "iso:country":"AT",
    "sg:address":"Ragnitzstr 66",
    "sg:city":"Graz",
    "sg:orig_category":"Dolmetscher",
    "sg:phone":"+43 316 337367",
    "sg:postcode":"8010",
    "sg:province":"Steiermark",
    "wof:name":"Vanek-Enyinnaya Angelika Mag",
    "wof:placetype":"venue"
},
  "geometry": {"coordinates":[15.480758667,47.0787162781],"type":"Point"}
}