{
  "type": "Feature",
  "properties": {
    "addr:full":"Iz-N\u00f6-S\u00fcd Str. 1 69 Wiener Neudorf Nieder\u00f6sterreich 2351",
    "addr:housenumber":"69",
    "addr:postcode":"2351",
    "addr:street":"Str. 1",
    "iso:country":"AT",
    "sg:address":"Iz-N\u00f6-S\u00fcd Str. 1 69",
    "sg:city":"Wiener Neudorf",
    "sg:classifiers":[
        {
            "category":"Professional",
            "subcategory":"Engineering",
            "type":"Services"
        }
    ],
    "sg:phone":"+43 4322 36677077",
    "sg:postcode":"2351",
    "sg:province":"Nieder\u00f6sterreich",
    "sg:tags":[
        "machine",
        "-",
        "mechanical"
    ],
    "wof:name":"WIESMAYR KLIMATECHNIK GES.MBH",
    "wof:placetype":"venue"
},
  "geometry": {"coordinates":[16.3183326721,48.0863113403],"type":"Point"}
}