{
  "type": "Feature",
  "properties": {
    "iso:country":"AT",
    "sg:address":"Gewerbestr 20",
    "sg:city":"Kapfenberg",
    "sg:orig_category":"Personalbereitstellung",
    "sg:phone":"+43 4338 6231378",
    "sg:postcode":"8605",
    "sg:province":"Steiermark",
    "wof:name":"PUM Personalbereitstellung u Montage GmbH",
    "wof:placetype":"venue"
},
  "geometry": {"coordinates":[15.3407497406,47.4680671692],"type":"Point"}
}