{
  "type": "Feature",
  "properties": {
    "addr:full":"Sankt Oswalder Strasse 5c Gutau Ober\u00f6sterreich 4293",
    "addr:housenumber":"5c",
    "addr:postcode":"4293",
    "addr:street":"Sankt Oswalder Strasse",
    "iso:country":"AT",
    "sg:address":"Sankt Oswalder Strasse 5c",
    "sg:city":"Gutau",
    "sg:orig_category":"Hardware For Steel Doors",
    "sg:phone":"+43 7946 20506",
    "sg:postcode":"4293",
    "sg:province":"Ober\u00f6sterreich",
    "sg:website":"glutz.at",
    "wof:name":"Glutz GmbH",
    "wof:placetype":"venue"
},
  "geometry": {"coordinates":[14.6142454147,48.420375824],"type":"Point"}
}