{
  "type": "Feature",
  "properties": {
    "addr:full":"Mondscheing 4/2 Graz Steiermark 8010",
    "addr:housenumber":"4 / 2",
    "addr:postcode":"8010",
    "addr:street":"Mondscheing",
    "iso:country":"AT",
    "sg:address":"Mondscheing 4/2",
    "sg:city":"Graz",
    "sg:orig_category":"Zahntechnische Laboratorien",
    "sg:phone":"+43 316 822630",
    "sg:postcode":"8010",
    "sg:province":"Steiermark",
    "wof:name":"Zahnprothek Langer KEG",
    "wof:placetype":"venue"
},
  "geometry": {"coordinates":[15.4444246292,47.0665130615],"type":"Point"}
}