{
  "type": "Feature",
  "properties": {
    "addr:full":"Braunauer Str 10 Mattighofen Ober\u00f6sterreich 5230",
    "addr:postcode":"5230",
    "addr:street":"Str 10",
    "iso:country":"AT",
    "sg:address":"Braunauer Str 10",
    "sg:city":"Mattighofen",
    "sg:orig_category":"Tankstellen",
    "sg:phone":"+43 7742 23000",
    "sg:postcode":"5230",
    "sg:province":"Ober\u00f6sterreich",
    "wof:name":"BP Austria Marketing GmbH",
    "wof:placetype":"venue"
},
  "geometry": {"coordinates":[13.1512155533,48.1103210449],"type":"Point"}
}