{
  "type": "Feature",
  "properties": {
    "addr:full":"Rathausstr 92 Etsdorf am Kamp Nieder\u00f6sterreich 3492",
    "addr:housenumber":"92",
    "addr:postcode":"3492",
    "addr:street":"Rathausstr;Niederoesterreich",
    "iso:country":"AT",
    "sg:address":"Rathausstr 92",
    "sg:city":"Etsdorf am Kamp",
    "sg:orig_category":"Feuerwehren",
    "sg:phone":"+43 2735 5522",
    "sg:postcode":"3492",
    "sg:province":"Nieder\u00f6sterreich",
    "wof:name":"Freiwillige Feuerwehr Etsdorf",
    "wof:placetype":"venue"
},
  "geometry": {"coordinates":[15.7430467606,48.4443740845],"type":"Point"}
}