{
  "type": "Feature",
  "properties": {
    "addr:full":"IZ N\u00d6-S\u00fcd, Stra\u00dfe 4 Objekt 8 Wiener Neudorf Nieder\u00f6sterreich 2351",
    "addr:housenumber":"objekt 8",
    "addr:postcode":"2351",
    "addr:street":"Noe-Sued Strasse 4",
    "iso:country":"AT",
    "sg:address":"IZ N\u00d6-S\u00fcd, Stra\u00dfe 4 Objekt 8",
    "sg:city":"Wiener Neudorf",
    "sg:classifiers":[
        {
            "category":"Manufacturing",
            "subcategory":"Tools & Machinery",
            "type":"Manufacturing & Wholesale Goods"
        }
    ],
    "sg:phone":"+43 2236 638700",
    "sg:postcode":"2351",
    "sg:province":"Nieder\u00f6sterreich",
    "sg:tags":[
        "bending",
        "press",
        "presses",
        "folding"
    ],
    "sg:website":"hesse-maschinen.com",
    "wof:name":"Maschinenfabrik Joh. M\u00fcller's Nfg. Hesse & Co GmbH",
    "wof:placetype":"venue"
},
  "geometry": {"coordinates":[16.3183326721,48.0863113403],"type":"Point"}
}