{
  "type": "Feature",
  "properties": {
    "addr:full":"Ramsstr 298 Kirchberg am Wechsel Nieder\u00f6sterreich 2880",
    "addr:housenumber":"298",
    "addr:postcode":"2880",
    "iso:country":"AT",
    "sg:address":"Ramsstr 298",
    "sg:city":"Kirchberg am Wechsel",
    "sg:orig_category":"Holzbau",
    "sg:phone":"+43 2641 2501",
    "sg:postcode":"2880",
    "sg:province":"Nieder\u00f6sterreich",
    "wof:name":"Ringhofer Johann jun",
    "wof:placetype":"venue"
},
  "geometry": {"coordinates":[16.0127601624,47.6285629272],"type":"Point"}
}