{
  "type": "Feature",
  "properties": {
    "addr:full":"Wallnerstr 8 Wien Wien 1010",
    "addr:housenumber":"8",
    "addr:postcode":"1010",
    "addr:street":"Wallnerstr",
    "iso:country":"AT",
    "sg:address":"Wallnerstr 8",
    "sg:city":"Wien",
    "sg:orig_category":"Arbeitsschutz U Arbeitsschutzartikel",
    "sg:phone":"+43 4315 3385500",
    "sg:postcode":"1010",
    "sg:province":"Wien",
    "sg:website":"albis.at",
    "wof:name":"Albis Vertrieb techn Bedarfsartikel Inh J u H Schulz",
    "wof:placetype":"venue"
},
  "geometry": {"coordinates":[16.3660449982,48.210308075],"type":"Point"}
}