{
  "type": "Feature",
  "properties": {
    "addr:full":"Josef Bauer-Str 58 Biedermannsdorf Nieder\u00f6sterreich 2362",
    "addr:housenumber":"58",
    "addr:postcode":"2362",
    "iso:country":"AT",
    "sg:address":"Josef Bauer-Str 58",
    "sg:city":"Biedermannsdorf",
    "sg:orig_category":"Friseure U Frisiersalons",
    "sg:phone":"+43 2236 71613",
    "sg:postcode":"2362",
    "sg:province":"Nieder\u00f6sterreich",
    "wof:name":"Susky Alexandra",
    "wof:placetype":"venue"
},
  "geometry": {"coordinates":[16.3376483917,48.0860099792],"type":"Point"}
}