{
  "type": "Feature",
  "properties": {
    "addr:full":"M\u00e4rzenstr 9 Kaltenbach Tirol 6272",
    "addr:housenumber":"9",
    "addr:postcode":"6272",
    "addr:street":"Maerzenstr",
    "iso:country":"AT",
    "sg:address":"M\u00e4rzenstr 9",
    "sg:city":"Kaltenbach",
    "sg:orig_category":"Transportunternehmen",
    "sg:phone":"+43 5283 2369",
    "sg:postcode":"6272",
    "sg:province":"Tirol",
    "wof:name":"Hauser Transporte GesmbH",
    "wof:placetype":"venue"
},
  "geometry": {"coordinates":[11.8829298019,47.2961883545],"type":"Point"}
}