{
  "type": "Feature",
  "properties": {
    "addr:full":"Lindenstr 2/1 Innsbruck Tirol 6020",
    "addr:housenumber":"2 / 1",
    "addr:postcode":"6020",
    "addr:street":"Lindenstr;Tirol",
    "iso:country":"AT",
    "sg:address":"Lindenstr 2/1",
    "sg:city":"Innsbruck",
    "sg:orig_category":"Steuerberatung",
    "sg:phone":"+43 512 3482680",
    "sg:postcode":"6020",
    "sg:province":"Tirol",
    "wof:name":"Lichtenberger Steuerberatung-Wirtschaftstreuhand",
    "wof:placetype":"venue"
},
  "geometry": {"coordinates":[11.4115247726,47.2642784119],"type":"Point"}
}