{
  "type": "Feature",
  "properties": {
    "addr:full":"Antiesen 13 Eberschwang Ober\u00f6sterreich 4906",
    "addr:housenumber":"13",
    "addr:postcode":"4906",
    "addr:street":"Antiesen",
    "iso:country":"AT",
    "sg:address":"Antiesen 13",
    "sg:city":"Eberschwang",
    "sg:orig_category":"Autolackierereien",
    "sg:phone":"+43 4377 5335618",
    "sg:postcode":"4906",
    "sg:province":"Ober\u00f6sterreich",
    "wof:name":"Autocenter Innviertel",
    "wof:placetype":"venue"
},
  "geometry": {"coordinates":[13.5545911789,48.1639633179],"type":"Point"}
}