{
  "type": "Feature",
  "properties": {
    "addr:full":"Reisnerstr 55-57 Wien Wien 1030",
    "addr:postcode":"55-57;1030",
    "iso:country":"AT",
    "sg:address":"Reisnerstr 55-57",
    "sg:city":"Wien",
    "sg:orig_category":"Versicherungsunternehmen",
    "sg:phone":"+43 4317 181097",
    "sg:postcode":"1030",
    "sg:province":"Wien",
    "wof:name":"Generali Versicherung AG",
    "wof:placetype":"venue"
},
  "geometry": {"coordinates":[16.3838920593,48.1964302063],"type":"Point"}
}