{
  "type": "Feature",
  "properties": {
    "iso:country":"AT",
    "sg:address":"Niederranna 21",
    "sg:city":"Wesenufer",
    "sg:classifiers":[
        {
            "category":"Personal",
            "subcategory":"Shoe Repair & Shine",
            "type":"Services"
        }
    ],
    "sg:phone":"+43 4372 85504",
    "sg:postcode":"4085",
    "sg:province":"Ober\u00f6sterreich",
    "sg:tags":[
        "leather"
    ],
    "wof:name":"GOTTFRID MAYER GMH & CO. KG",
    "wof:placetype":"venue"
},
  "geometry": {"coordinates":[13.82264328,48.4403686523],"type":"Point"}
}