{
  "type": "Feature",
  "properties": {
    "addr:full":"Schie\u00dfstattallee 6 St. Veit an der Glan K\u00e4rnten 9300",
    "addr:housenumber":"6",
    "addr:postcode":"9300",
    "addr:street":"Schiessstattallee;Kaernten",
    "iso:country":"AT",
    "sg:address":"Schie\u00dfstattallee 6",
    "sg:city":"St. Veit an der Glan",
    "sg:orig_category":"Autohandel",
    "sg:phone":"+43 4212 3495",
    "sg:postcode":"9300",
    "sg:province":"K\u00e4rnten",
    "wof:name":"Ford CAR-TECH GmbH",
    "wof:placetype":"venue"
},
  "geometry": {"coordinates":[14.3581790924,46.7578849792],"type":"Point"}
}