{
  "type": "Feature",
  "properties": {
    "addr:full":"Pre\u00dfbaumer Str 1 Sieghartskirchen Nieder\u00f6sterreich 3443",
    "addr:housenumber":"1",
    "addr:postcode":"3443",
    "addr:street":"Str;Niederoesterreich",
    "iso:country":"AT",
    "sg:address":"Pre\u00dfbaumer Str 1",
    "sg:city":"Sieghartskirchen",
    "sg:orig_category":"Banken U Sparkassen",
    "sg:phone":"+43 2274 25150",
    "sg:postcode":"3443",
    "sg:province":"Nieder\u00f6sterreich",
    "wof:name":"Tullnerfelder Volksbank regGenmbH",
    "wof:placetype":"venue"
},
  "geometry": {"coordinates":[16.0132713318,48.2548332214],"type":"Point"}
}