{
  "type": "Feature",
  "properties": {
    "iso:country":"AT",
    "sg:address":"Apfeldorf 12",
    "sg:city":"St. Johann in Tirol",
    "sg:orig_category":"Pensionen / Privatzimmer",
    "sg:phone":"+43 5352 62240",
    "sg:postcode":"6380",
    "sg:province":"Tirol",
    "wof:name":"Lacknerhof Jugendheim",
    "wof:placetype":"venue"
},
  "geometry": {"coordinates":[12.4171772003,47.5144004822],"type":"Point"}
}