{
  "type": "Feature",
  "properties": {
    "addr:full":"Pellendorfer Str 16 Himberg Nieder\u00f6sterreich 2325",
    "addr:postcode":"2325",
    "addr:street":"Str;Himberg",
    "iso:country":"AT",
    "sg:address":"Pellendorfer Str 16",
    "sg:city":"Himberg",
    "sg:orig_category":"Alarmanlagen U Sicherheitssysteme",
    "sg:phone":"+43 4322 3587760",
    "sg:postcode":"2325",
    "sg:province":"Nieder\u00f6sterreich",
    "sg:website":"weitmann-security.at",
    "wof:name":"Weitmann Security Alarmanlagen-Tresore-Sicherheitstechnik",
    "wof:placetype":"venue"
},
  "geometry": {"coordinates":[16.443813324,48.0898704529],"type":"Point"}
}