{
  "type": "Feature",
  "properties": {
    "addr:full":"Senefelderg 14 Wien Wien 1100",
    "addr:housenumber":"14",
    "addr:postcode":"1100",
    "addr:street":"Senefelderg",
    "iso:country":"AT",
    "sg:address":"Senefelderg 14",
    "sg:city":"Wien",
    "sg:orig_category":"Pizzazustellungen",
    "sg:phone":"+43 1 6068290",
    "sg:postcode":"1100",
    "sg:province":"Wien",
    "wof:name":"Pizza Schnitz'l Express - Boban Todorovic KEG",
    "wof:placetype":"venue"
},
  "geometry": {"coordinates":[16.3753681183,48.1761512756],"type":"Point"}
}