{
  "type": "Feature",
  "properties": {
    "addr:full":"Plainbachstr 7 Bergheim Salzburg 5101",
    "addr:housenumber":"7",
    "addr:postcode":"5101",
    "addr:street":"Plainbachstr;Salzburg",
    "iso:country":"AT",
    "sg:address":"Plainbachstr 7",
    "sg:city":"Bergheim",
    "sg:classifiers":[
        {
            "category":"Shopping",
            "subcategory":"Gifts & Souvenirs",
            "type":"Retail Goods"
        }
    ],
    "sg:phone":"+43 662 450239",
    "sg:postcode":"5101",
    "sg:province":"Salzburg",
    "wof:name":"Rauchenzauner GesmbH",
    "wof:placetype":"venue"
},
  "geometry": {"coordinates":[13.0348739624,47.841468811],"type":"Point"}
}