{
  "type": "Feature",
  "properties": {
    "iso:country":"AT",
    "sg:address":"Riemerschmiedg 7",
    "sg:city":"Maria Enzersdorf",
    "sg:orig_category":"Gemeinden",
    "sg:phone":"+43 2236 445010",
    "sg:postcode":"2344",
    "sg:province":"Nieder\u00f6sterreich",
    "wof:name":"Gemeindeamt d Marktgemeinde Maria Enzersdorf",
    "wof:placetype":"venue"
},
  "geometry": {"coordinates":[16.2858848572,48.0985717773],"type":"Point"}
}