{
  "type": "Feature",
  "properties": {
    "iso:country":"AT",
    "sg:address":"Industriezeile 52",
    "sg:city":"Linz",
    "sg:orig_category":"Banken U Sparkassen",
    "sg:phone":"+43 4350 50537240",
    "sg:postcode":"4020",
    "sg:province":"Ober\u00f6sterreich",
    "wof:name":"Bank Austria Creditanstalt AG",
    "wof:placetype":"venue"
},
  "geometry": {"coordinates":[14.3152542114,48.30809021],"type":"Point"}
}