{
  "type": "Feature",
  "properties": {
    "addr:full":"Panwinklerweg 20 Altenberg Ober\u00f6sterreich 4203",
    "addr:housenumber":"20",
    "addr:postcode":"4203",
    "addr:street":"Panwinklerweg",
    "iso:country":"AT",
    "sg:address":"Panwinklerweg 20",
    "sg:city":"Altenberg",
    "sg:orig_category":"Volkshochschulen",
    "sg:phone":"+43 4372 307435",
    "sg:postcode":"4203",
    "sg:province":"Ober\u00f6sterreich",
    "wof:name":"Volkshochschule Altenberg",
    "wof:placetype":"venue"
},
  "geometry": {"coordinates":[14.307759285,48.3684196472],"type":"Point"}
}