{
  "type": "Feature",
  "properties": {
    "iso:country":"AT",
    "sg:address":"Fraueng 31a",
    "sg:city":"Leibnitz",
    "sg:orig_category":"Tischlereien",
    "sg:phone":"+43 4334 52825010",
    "sg:postcode":"8430",
    "sg:province":"Steiermark",
    "wof:name":"Hengsberger Karl",
    "wof:placetype":"venue"
},
  "geometry": {"coordinates":[15.5338563919,46.7930717468],"type":"Point"}
}