{
  "type": "Feature",
  "properties": {
    "addr:full":"Hauptstr 49 Tarrenz Tirol 6464",
    "addr:housenumber":"49",
    "addr:postcode":"6464",
    "addr:street":"Hauptstr;Tirol",
    "iso:country":"AT",
    "sg:address":"Hauptstr 49",
    "sg:city":"Tarrenz",
    "sg:orig_category":"Tischlereien",
    "sg:phone":"+43 5412 63309",
    "sg:postcode":"6464",
    "sg:province":"Tirol",
    "wof:name":"Stafler Alois",
    "wof:placetype":"venue"
},
  "geometry": {"coordinates":[10.7584085464,47.2603149414],"type":"Point"}
}