{
  "type": "Feature",
  "properties": {
    "iso:country":"AT",
    "sg:address":"Salling 5",
    "sg:city":"Gunskirchen",
    "sg:orig_category":"Fleisch-, Wurst- U Selchwaren / Erzeugung U Gro\u00c3\u0178handel",
    "sg:phone":"+43 4372 468971",
    "sg:postcode":"4623",
    "sg:province":"Ober\u00f6sterreich",
    "wof:name":"K & K Steinerberger",
    "wof:placetype":"venue"
},
  "geometry": {"coordinates":[13.9462509155,48.1522064209],"type":"Point"}
}