{
  "type": "Feature",
  "properties": {
    "addr:full":"Auhofstr 15 Wien Wien 1130",
    "addr:housenumber":"15",
    "addr:postcode":"1130",
    "addr:street":"Auhofstr",
    "iso:country":"AT",
    "sg:address":"Auhofstr 15",
    "sg:city":"Wien",
    "sg:classifiers":[
        {
            "category":"Park",
            "subcategory":"Provincial",
            "type":"Public Place"
        }
    ],
    "sg:phone":"+43 1 87754030",
    "sg:postcode":"1130",
    "sg:province":"Wien",
    "sg:tags":[
        "u",
        "-archive",
        "bildagenturen"
    ],
    "wof:name":"Buenos Dias Bildagentur GesmbH",
    "wof:placetype":"venue"
},
  "geometry": {"coordinates":[16.2930603027,48.1875610352],"type":"Point"}
}