{
  "type": "Feature",
  "properties": {
    "addr:full":"Halleiner Landesstr 7 Hallein Salzburg 5400",
    "addr:housenumber":"7",
    "addr:postcode":"5400",
    "addr:street":"Landesstr;Salzburg",
    "iso:country":"AT",
    "sg:address":"Halleiner Landesstr 7",
    "sg:city":"Hallein",
    "sg:orig_category":"Friseure U Frisiersalons",
    "sg:phone":"+43 6245 84001",
    "sg:postcode":"5400",
    "sg:province":"Salzburg",
    "wof:name":"Professional Hairstyling - Manuela Scharler",
    "wof:placetype":"venue"
},
  "geometry": {"coordinates":[13.0996809006,47.6897926331],"type":"Point"}
}