{
  "type": "Feature",
  "properties": {
    "addr:full":"Johannes-Filzer-Str 30 Salzburg Salzburg 5020",
    "addr:housenumber":"30",
    "addr:postcode":"5020",
    "addr:street":"Johannes-Filzer-Str;Salzburg",
    "iso:country":"AT",
    "sg:address":"Johannes-Filzer-Str 30",
    "sg:city":"Salzburg",
    "sg:orig_category":"Bekleidung / Erzeugung U Gro\u00c3\u0178handel",
    "sg:phone":"+43 4366 2624027",
    "sg:postcode":"5020",
    "sg:province":"Salzburg",
    "wof:name":"Modeagentur Otmar Ellensohn",
    "wof:placetype":"venue"
},
  "geometry": {"coordinates":[13.067782402,47.7937660217],"type":"Point"}
}