{
  "type": "Feature",
  "properties": {
    "addr:full":"Friedrichstr 23 Baden Nieder\u00f6sterreich 2500",
    "addr:housenumber":"23",
    "addr:postcode":"2500",
    "addr:street":"Friedrichstr;Niederoesterreich",
    "iso:country":"AT",
    "sg:address":"Friedrichstr 23",
    "sg:city":"Baden",
    "sg:classifiers":[
        {
            "category":"Professional",
            "subcategory":"Computer Services",
            "type":"Services"
        }
    ],
    "sg:phone":"+43 2252 21746",
    "sg:postcode":"2500",
    "sg:province":"Nieder\u00f6sterreich",
    "sg:tags":[
        "software"
    ],
    "wof:name":"HSD Hardware Software Development GesmbH",
    "wof:placetype":"venue"
},
  "geometry": {"coordinates":[16.216337204,48.0011100769],"type":"Point"}
}