{
  "type": "Feature",
  "properties": {
    "iso:country":"AT",
    "sg:address":"Steindorfer Str. 7",
    "sg:city":"Seewalchen am Attersee",
    "sg:classifiers":[
        {
            "category":"Personal",
            "subcategory":"Shoe Repair & Shine",
            "type":"Services"
        }
    ],
    "sg:phone":"+43 4376 623401",
    "sg:postcode":"4863",
    "sg:province":"Ober\u00f6sterreich",
    "sg:tags":[
        "leather"
    ],
    "wof:name":"MAYER MARKENSCHUHE GMBH",
    "wof:placetype":"venue"
},
  "geometry": {"coordinates":[13.5836610794,47.9553833008],"type":"Point"}
}