{
  "type": "Feature",
  "properties": {
    "addr:full":"Liechtensteiner Str 96 Feldkirch Vorarlberg 6800",
    "addr:postcode":"6800",
    "addr:street":"Str 96",
    "iso:country":"AT",
    "sg:address":"Liechtensteiner Str 96",
    "sg:city":"Feldkirch",
    "sg:orig_category":"Restaurants: Chinesisch",
    "sg:phone":"+43 5522 71583",
    "sg:postcode":"6800",
    "sg:province":"Vorarlberg",
    "wof:name":"China-Restaurant Hu Xin",
    "wof:placetype":"venue"
},
  "geometry": {"coordinates":[9.5815401077,47.2252006531],"type":"Point"}
}