{
  "type": "Feature",
  "properties": {
    "iso:country":"AT",
    "sg:address":"Wilhelm-Hohenheim-Str 5",
    "sg:city":"Villach",
    "sg:orig_category":"Architekten",
    "sg:phone":"+43 4342 42214124",
    "sg:postcode":"9500",
    "sg:province":"K\u00e4rnten",
    "wof:name":"G\u00e4rtner Wolfgang Arch Dipl-Ing",
    "wof:placetype":"venue"
},
  "geometry": {"coordinates":[13.8455123901,46.6076545715],"type":"Point"}
}