{
  "type": "Feature",
  "properties": {
    "addr:full":"Weng 34 Werfenweng Salzburg 5453",
    "addr:housenumber":"34",
    "addr:postcode":"5453",
    "addr:street":"Weng;Salzburg",
    "iso:country":"AT",
    "sg:address":"Weng 34",
    "sg:city":"Werfenweng",
    "sg:classifiers":[
        {
            "category":"Restaurant",
            "type":"Food & Drink"
        }
    ],
    "sg:phone":"+43 4364 6620034",
    "sg:postcode":"5453",
    "sg:province":"Salzburg",
    "wof:name":"Restaurant Wenger Alpenhof",
    "wof:placetype":"venue"
},
  "geometry": {"coordinates":[13.2557001114,47.4620361328],"type":"Point"}
}