{
  "type": "Feature",
  "properties": {
    "addr:full":"Liechtensteinstr 68-70 Wien Wien 1090",
    "addr:postcode":"68-70;1090",
    "iso:country":"AT",
    "sg:address":"Liechtensteinstr 68-70",
    "sg:city":"Wien",
    "sg:orig_category":"Juweliere, Gold- U Silberschmiede",
    "sg:phone":"+43 4313 176714",
    "sg:postcode":"1090",
    "sg:province":"Wien",
    "wof:name":"Studio Gabry",
    "wof:placetype":"venue"
},
  "geometry": {"coordinates":[16.3567886353,48.2266578674],"type":"Point"}
}