{
  "type": "Feature",
  "properties": {
    "iso:country":"AT",
    "sg:address":"Am Heumarkt 1 ",
    "sg:city":"Wien",
    "sg:classifiers":[
        {
            "category":"Manufacturing",
            "subcategory":"Metals",
            "type":"Manufacturing & Wholesale Goods"
        }
    ],
    "sg:phone":"+43 4317 17150",
    "sg:postcode":"1030",
    "sg:province":"Wien",
    "sg:tags":[
        "processing"
    ],
    "wof:name":"OESTERREICHISCHE M\u00dcNZ AG",
    "wof:placetype":"venue"
},
  "geometry": {"coordinates":[16.3824577332,48.2035140991],"type":"Point"}
}