{
  "type": "Feature",
  "properties": {
    "iso:country":"AT",
    "sg:address":"Stiftg 6/2/Top 4",
    "sg:city":"Wien",
    "sg:orig_category":"Marketingberatung",
    "sg:phone":"+43 1 3708808",
    "sg:postcode":"1070",
    "sg:province":"Wien",
    "wof:name":"suchtreffer@edv-services GmbH",
    "wof:placetype":"venue"
},
  "geometry": {"coordinates":[16.3383293152,48.2016792297],"type":"Point"}
}