{
  "type": "Feature",
  "properties": {
    "addr:full":"Hoher Markt 7 Waidhofen an der Ybbs Nieder\u00f6sterreich 3340",
    "addr:housenumber":"7",
    "addr:postcode":"3340",
    "addr:street":"Hoher Markt",
    "iso:country":"AT",
    "sg:address":"Hoher Markt 7",
    "sg:city":"Waidhofen an der Ybbs",
    "sg:orig_category":"Versicherungsunternehmen",
    "sg:phone":"+43 4374 42521430",
    "sg:postcode":"3340",
    "sg:province":"Nieder\u00f6sterreich",
    "wof:name":"Wiener St\u00e4dtische Allgemeine Versicherung AG",
    "wof:placetype":"venue"
},
  "geometry": {"coordinates":[14.7751274109,47.9601287842],"type":"Point"}
}