{
  "type": "Feature",
  "properties": {
    "addr:full":"Auer Welsbach-G 25 Puntigam Steiermark 8055",
    "addr:housenumber":"25",
    "addr:postcode":"8055",
    "iso:country":"AT",
    "sg:address":"Auer Welsbach-G 25",
    "sg:city":"Puntigam",
    "sg:orig_category":"Abfallentsorgung U -Verwertung",
    "sg:phone":"+43 316 2927910",
    "sg:postcode":"8055",
    "sg:province":"Steiermark",
    "wof:name":"A.S.A. Abfall Service AG",
    "wof:placetype":"venue"
},
  "geometry": {"coordinates":[15.4466581345,47.0276870728],"type":"Point"}
}