{
  "type": "Feature",
  "properties": {
    "addr:full":"Bayrhamerpl 8/1 Hallein Salzburg 5400",
    "addr:housenumber":"8 / 1",
    "addr:postcode":"5400",
    "addr:street":"Bayrhamerpl;Salzburg",
    "iso:country":"AT",
    "sg:address":"Bayrhamerpl 8/1",
    "sg:city":"Hallein",
    "sg:orig_category":"Friseure U Frisiersalons",
    "sg:phone":"+43 6245 87287",
    "sg:postcode":"5400",
    "sg:province":"Salzburg",
    "wof:name":"Friseur Struwwelpeter Inh Joachim Messner",
    "wof:placetype":"venue"
},
  "geometry": {"coordinates":[13.0945444107,47.6821975708],"type":"Point"}
}