{
  "type": "Feature",
  "properties": {
    "iso:country":"AT",
    "sg:address":"M\u00f6rtelsdorf 44",
    "sg:city":"Tamsweg",
    "sg:classifiers":[
        {
            "category":"Building & Trades",
            "subcategory":"Construction",
            "type":"Services"
        }
    ],
    "sg:phone":"+43 6474 2274",
    "sg:postcode":"5580",
    "sg:province":"Salzburg",
    "sg:tags":[
        "industrial",
        "timber"
    ],
    "wof:name":"Alois Maier",
    "wof:placetype":"venue"
},
  "geometry": {"coordinates":[13.7895002365,47.1288261414],"type":"Point"}
}