{
  "type": "Feature",
  "properties": {
    "iso:country":"AT",
    "sg:address":"Puitenweg 3",
    "sg:city":"Hatting",
    "sg:classifiers":[
        {
            "category":"Professional",
            "subcategory":"Computer Services",
            "type":"Services"
        }
    ],
    "sg:phone":"+43 4366 44148612",
    "sg:postcode":"6402",
    "sg:province":"Tirol",
    "sg:tags":[
        "software"
    ],
    "wof:name":"Steiner Christian Ing",
    "wof:placetype":"venue"
},
  "geometry": {"coordinates":[11.1684818268,47.2767410278],"type":"Point"}
}