{
  "type": "Feature",
  "properties": {
    "addr:full":"Weihburgg 3 Wien Wien 1010",
    "addr:housenumber":"3",
    "addr:postcode":"1010",
    "addr:street":"Weihburgg",
    "iso:country":"AT",
    "sg:address":"Weihburgg 3",
    "sg:city":"Wien",
    "sg:orig_category":"Tabaktrafiken",
    "sg:phone":"+43 1 5136099",
    "sg:postcode":"1010",
    "sg:province":"Wien",
    "wof:name":"Benesch Sylvia",
    "wof:placetype":"venue"
},
  "geometry": {"coordinates":[16.372013092,48.2071914673],"type":"Point"}
}