{
  "type": "Feature",
  "properties": {
    "addr:full":"Winterdorf 19 St. Ruprecht an der Raab Steiermark 8181",
    "addr:housenumber":"19",
    "addr:postcode":"8181",
    "addr:street":"Winterdorf",
    "iso:country":"AT",
    "sg:address":"Winterdorf 19",
    "sg:city":"St. Ruprecht an der Raab",
    "sg:orig_category":"Webereien U Spinnereien",
    "sg:phone":"+43 4331 782566",
    "sg:postcode":"8181",
    "sg:province":"Steiermark",
    "wof:name":"Kohlf\u00fcrst Walter",
    "wof:placetype":"venue"
},
  "geometry": {"coordinates":[15.6658182144,47.1803436279],"type":"Point"}
}