{
  "type": "Feature",
  "properties": {
    "addr:full":"Stiegerg 12 Wien Wien 1150",
    "addr:housenumber":"12",
    "addr:postcode":"1150",
    "addr:street":"Stiegerg",
    "iso:country":"AT",
    "sg:address":"Stiegerg 12",
    "sg:city":"Wien",
    "sg:orig_category":"Schleifereien",
    "sg:phone":"+43 1 8936707",
    "sg:postcode":"1150",
    "sg:province":"Wien",
    "wof:name":"Schweiger Johann",
    "wof:placetype":"venue"
},
  "geometry": {"coordinates":[16.334154129,48.1868896484],"type":"Point"}
}