{
  "type": "Feature",
  "properties": {
    "addr:full":"Hauptstr 77 Oetz Tirol 6433",
    "addr:housenumber":"77",
    "addr:postcode":"6433",
    "addr:street":"Hauptstr;Tirol",
    "iso:country":"AT",
    "sg:address":"Hauptstr 77",
    "sg:city":"Oetz",
    "sg:classifiers":[
        {
            "category":"Restaurant",
            "type":"Food & Drink"
        }
    ],
    "sg:phone":"+43 5252 6407",
    "sg:postcode":"6433",
    "sg:province":"Tirol",
    "wof:name":"Restaurant-Pizzeria Oetzer Stuben",
    "wof:placetype":"venue"
},
  "geometry": {"coordinates":[10.8994245529,47.2011413574],"type":"Point"}
}