{
  "type": "Feature",
  "properties": {
    "iso:country":"AT",
    "sg:address":"Castellezg 6/1",
    "sg:city":"Wien",
    "sg:classifiers":[
        {
            "category":"Professional",
            "subcategory":"Computer Services",
            "type":"Services"
        }
    ],
    "sg:phone":"+43 664 3389006",
    "sg:postcode":"1020",
    "sg:province":"Wien",
    "sg:tags":[
        "software"
    ],
    "wof:name":"FELIX Michael KEG",
    "wof:placetype":"venue"
},
  "geometry": {"coordinates":[16.3806324005,48.2203445435],"type":"Point"}
}