{
  "type": "Feature",
  "properties": {
    "addr:full":"Davisstr 38 Hallein Salzburg 5400",
    "addr:housenumber":"38",
    "addr:postcode":"5400",
    "addr:street":"Davisstr;Salzburg",
    "iso:country":"AT",
    "sg:address":"Davisstr 38",
    "sg:city":"Hallein",
    "sg:orig_category":"Non-Classified Establishments",
    "sg:phone":"+43 6245 806280",
    "sg:postcode":"5400",
    "sg:province":"Salzburg",
    "wof:name":"Evangelisches Pfarramt",
    "wof:placetype":"venue"
},
  "geometry": {"coordinates":[13.100684166,47.6778907776],"type":"Point"}
}