{
  "type": "Feature",
  "properties": {
    "addr:full":"Erzherzog-Karl-Str 5a Wien Wien 1220",
    "addr:housenumber":"5a",
    "addr:postcode":"1220",
    "addr:street":"Erzherzog-Karl-Str",
    "iso:country":"AT",
    "sg:address":"Erzherzog-Karl-Str 5a",
    "sg:city":"Wien",
    "sg:orig_category":"Immobilienmakler",
    "sg:phone":"+43 1 20337470",
    "sg:postcode":"1220",
    "sg:province":"Wien",
    "wof:name":"Poth H Immobilien GmbH",
    "wof:placetype":"venue"
},
  "geometry": {"coordinates":[16.4319591522,48.2388343811],"type":"Point"}
}