{
  "type": "Feature",
  "properties": {
    "addr:full":"Hauptstr 77 Linz Ober\u00f6sterreich 4040",
    "addr:housenumber":"77",
    "addr:postcode":"4040",
    "addr:street":"Hauptstr",
    "iso:country":"AT",
    "sg:address":"Hauptstr 77",
    "sg:city":"Linz",
    "sg:orig_category":"Juwelen, Gold- U Silberwaren / Erzeugung U Gro\u00c3\u0178handel",
    "sg:phone":"+43 4373 27156000",
    "sg:postcode":"4040",
    "sg:province":"Ober\u00f6sterreich",
    "wof:name":"Oberhell B GesmbH",
    "wof:placetype":"venue"
},
  "geometry": {"coordinates":[14.2805709839,48.3148956299],"type":"Point"}
}