{
  "type": "Feature",
  "properties": {
    "iso:country":"AT",
    "sg:address":"Nr 43a",
    "sg:city":"Judenau",
    "sg:orig_category":"Wasseraufbereitung U -Reinigung",
    "sg:phone":"+43 4322 7541082",
    "sg:postcode":"3441",
    "sg:province":"Nieder\u00f6sterreich",
    "sg:website":"hgw-wassertechnik.at",
    "wof:name":"HGW Haus- u Gewerbewassertechnik GmbH",
    "wof:placetype":"venue"
},
  "geometry": {"coordinates":[16.0334529877,48.2829017639],"type":"Point"}
}