{
  "type": "Feature",
  "properties": {
    "addr:full":"Nr 21 Kuchl Salzburg 5431",
    "addr:postcode":"5431",
    "addr:street":"Nr;Salzburg",
    "iso:country":"AT",
    "sg:address":"Nr 21",
    "sg:city":"Kuchl",
    "sg:orig_category":"Tischlereien",
    "sg:phone":"+43 6244 6498",
    "sg:postcode":"5431",
    "sg:province":"Salzburg",
    "wof:name":"Rettenbacher Johann",
    "wof:placetype":"venue"
},
  "geometry": {"coordinates":[13.1438808441,47.625667572],"type":"Point"}
}