{
  "type": "Feature",
  "properties": {
    "addr:full":"Wlassakstr 2 Wien Wien 1130",
    "addr:housenumber":"2",
    "addr:postcode":"1130",
    "addr:street":"Wlassakstr",
    "iso:country":"AT",
    "sg:address":"Wlassakstr 2",
    "sg:city":"Wien",
    "sg:orig_category":"Lebensmittel / Einzelhandel",
    "sg:phone":"+43 1 8797453",
    "sg:postcode":"1130",
    "sg:province":"Wien",
    "wof:name":"Zielpunkt Warenhandel GmbH & Co KG",
    "wof:placetype":"venue"
},
  "geometry": {"coordinates":[16.2706813812,48.177898407],"type":"Point"}
}