{
  "type": "Feature",
  "properties": {
    "iso:country":"AT",
    "sg:address":"Schulstr 6",
    "sg:city":"Aspach",
    "sg:orig_category":"Rauchfangkehrer",
    "sg:phone":"+43 7755 6478",
    "sg:postcode":"5252",
    "sg:province":"Ober\u00f6sterreich",
    "wof:name":"Winterberger Karl Hans",
    "wof:placetype":"venue"
},
  "geometry": {"coordinates":[13.3044681549,48.18592453],"type":"Point"}
}