{
  "type": "Feature",
  "properties": {
    "addr:full":"Nr 43 Eberndorf K\u00e4rnten 9141",
    "addr:postcode":"9141",
    "addr:street":"Nr;Kaernten",
    "iso:country":"AT",
    "sg:address":"Nr 43",
    "sg:city":"Eberndorf",
    "sg:classifiers":[
        {
            "category":"Professional",
            "subcategory":"Computer Services",
            "type":"Services"
        }
    ],
    "sg:phone":"+43 4367 687727363",
    "sg:postcode":"9141",
    "sg:province":"K\u00e4rnten",
    "sg:tags":[
        "software"
    ],
    "wof:name":"SQUIB Mediadesign - Marko Haschej",
    "wof:placetype":"venue"
},
  "geometry": {"coordinates":[14.6411848068,46.5912818909],"type":"Point"}
}