{
  "type": "Feature",
  "properties": {
    "addr:full":"Laufenstr 50 Salzburg Salzburg 5020",
    "addr:housenumber":"50",
    "addr:postcode":"5020",
    "addr:street":"Laufenstr;Salzburg",
    "iso:country":"AT",
    "sg:address":"Laufenstr 50",
    "sg:city":"Salzburg",
    "sg:orig_category":"Volksschulen",
    "sg:phone":"+43 662 4334080",
    "sg:postcode":"5020",
    "sg:province":"Salzburg",
    "wof:name":"Volksschule Liefering II",
    "wof:placetype":"venue"
},
  "geometry": {"coordinates":[13.0228128433,47.8238143921],"type":"Point"}
}