{
  "type": "Feature",
  "properties": {
    "addr:full":"Natzing 2 Pram Ober\u00f6sterreich 4742",
    "addr:housenumber":"2",
    "addr:postcode":"4742",
    "addr:street":"Natzing",
    "iso:country":"AT",
    "sg:address":"Natzing 2",
    "sg:city":"Pram",
    "sg:orig_category":"Unternehmensberatung",
    "sg:phone":"+43 7736 20088",
    "sg:postcode":"4742",
    "sg:province":"Ober\u00f6sterreich",
    "wof:name":"Finance Consult Managementberatung GesmbH",
    "wof:placetype":"venue"
},
  "geometry": {"coordinates":[13.6083259583,48.2489738464],"type":"Point"}
}