{
  "type": "Feature",
  "properties": {
    "addr:full":"Westbahnstr 40 Wien Wien 1070",
    "addr:housenumber":"40",
    "addr:postcode":"1070",
    "addr:street":"Westbahnstr",
    "iso:country":"AT",
    "sg:address":"Westbahnstr 40",
    "sg:city":"Wien",
    "sg:orig_category":"Fotoapparate U -Artikel / Einzelhandel",
    "sg:phone":"+43 4315 2356590",
    "sg:postcode":"1070",
    "sg:province":"Wien",
    "wof:name":"Leica Shop - Coeln Peter GesmbH",
    "wof:placetype":"venue"
},
  "geometry": {"coordinates":[16.3422622681,48.2019691467],"type":"Point"}
}