{
  "type": "Feature",
  "properties": {
    "iso:country":"AT",
    "sg:address":"Hauptstr 39",
    "sg:city":"Grafenstein",
    "sg:orig_category":"Tabaktrafiken",
    "sg:phone":"+43 4225 2054",
    "sg:postcode":"9131",
    "sg:province":"K\u00e4rnten",
    "wof:name":"Wutti Gottfried",
    "wof:placetype":"venue"
},
  "geometry": {"coordinates":[14.4631490707,46.6188583374],"type":"Point"}
}