{
  "type": "Feature",
  "properties": {
    "addr:full":"Salzachtal Bdstr S\u00fcd 50a Hallein Salzburg 5400",
    "addr:housenumber":"50a",
    "addr:postcode":"5400",
    "addr:street":"Sued;Salzburg",
    "iso:country":"AT",
    "sg:address":"Salzachtal Bdstr S\u00fcd 50a",
    "sg:city":"Hallein",
    "sg:orig_category":"Fahrschulen",
    "sg:phone":"+43 6245 820800",
    "sg:postcode":"5400",
    "sg:province":"Salzburg",
    "wof:name":"Fahrschule H\u00f6glinger",
    "wof:placetype":"venue"
},
  "geometry": {"coordinates":[13.0926103592,47.6814613342],"type":"Point"}
}