{
  "type": "Feature",
  "properties": {
    "addr:full":"H\u00f6pflinger Weg NB Mattighofen Ober\u00f6sterreich 5230",
    "addr:postcode":"5230",
    "addr:street":"Hoepflinger Weg",
    "iso:country":"AT",
    "sg:address":"H\u00f6pflinger Weg NB",
    "sg:city":"Mattighofen",
    "sg:orig_category":"Friseure U Frisiersalons",
    "sg:phone":"+43 7742 3729",
    "sg:postcode":"5230",
    "sg:province":"Ober\u00f6sterreich",
    "wof:name":"Hartinger Franziska",
    "wof:placetype":"venue"
},
  "geometry": {"coordinates":[13.1500482559,48.1035919189],"type":"Point"}
}