{
  "type": "Feature",
  "properties": {
    "iso:country":"AT",
    "sg:address":"Walgaustr 21",
    "sg:city":"Rankweil",
    "sg:orig_category":"Forstverwaltungen",
    "sg:phone":"+43 5522 44523",
    "sg:postcode":"6830",
    "sg:province":"Vorarlberg",
    "wof:name":"Agrargemeinschaft Rankweil",
    "wof:placetype":"venue"
},
  "geometry": {"coordinates":[9.644241333,47.2641868591],"type":"Point"}
}