{
  "type": "Feature",
  "properties": {
    "addr:full":"Leopoldstr 11 Klosterneuburg Nieder\u00f6sterreich 3400",
    "addr:housenumber":"11",
    "addr:postcode":"3400",
    "addr:street":"Leopoldstr;Niederoesterreich",
    "iso:country":"AT",
    "sg:address":"Leopoldstr 11",
    "sg:city":"Klosterneuburg",
    "sg:orig_category":"Fleischhauereien",
    "sg:phone":"+43 2243 32498",
    "sg:postcode":"3400",
    "sg:province":"Nieder\u00f6sterreich",
    "wof:name":"Aichinger Ernst GmbH",
    "wof:placetype":"venue"
},
  "geometry": {"coordinates":[16.3258132935,48.3041954041],"type":"Point"}
}