{
  "type": "Feature",
  "properties": {
    "addr:full":"Bacher Weg 2 Bad Kleinkirchheim K\u00e4rnten 9546",
    "addr:housenumber":"2",
    "addr:postcode":"9546",
    "addr:street":"Bacher Weg",
    "iso:country":"AT",
    "sg:address":"Bacher Weg 2",
    "sg:city":"Bad Kleinkirchheim",
    "sg:orig_category":"Pensionen / Privatzimmer",
    "sg:phone":"+43 4342 40623",
    "sg:postcode":"9546",
    "sg:province":"K\u00e4rnten",
    "wof:name":"Kurpension Alfred u Erika Fortin",
    "wof:placetype":"venue"
},
  "geometry": {"coordinates":[13.7776517868,46.8137130737],"type":"Point"}
}