{
  "type": "Feature",
  "properties": {
    "addr:full":"K\u00f6stenbaumg 17 Graz Steiermark 8020",
    "addr:housenumber":"17",
    "addr:postcode":"8020",
    "addr:street":"Koestenbaumg",
    "iso:country":"AT",
    "sg:address":"K\u00f6stenbaumg 17",
    "sg:city":"Graz",
    "sg:orig_category":"Wasserwerke",
    "sg:phone":"+43 316 712372",
    "sg:postcode":"8020",
    "sg:province":"Steiermark",
    "wof:name":"Das \u00e4ltere M\u00fchl-Consortium - Wasserwerks-Genossenschaft",
    "wof:placetype":"venue"
},
  "geometry": {"coordinates":[15.4284543991,47.0614852905],"type":"Point"}
}