{
  "type": "Feature",
  "properties": {
    "addr:full":"Bauerstr 4 Bad Ischl Ober\u00f6sterreich 4820",
    "addr:housenumber":"4",
    "addr:postcode":"4820",
    "addr:street":"Bauerstr",
    "iso:country":"AT",
    "sg:address":"Bauerstr 4",
    "sg:city":"Bad Ischl",
    "sg:orig_category":"Pensionen / Privatzimmer",
    "sg:phone":"+43 6132 25501",
    "sg:postcode":"4820",
    "sg:province":"Ober\u00f6sterreich",
    "wof:name":"Pilz Wilhelm",
    "wof:placetype":"venue"
},
  "geometry": {"coordinates":[13.6152248383,47.7092590332],"type":"Point"}
}