{
  "type": "Feature",
  "properties": {
    "addr:full":"Kreuzg 34 Wien Wien 1180",
    "addr:housenumber":"34",
    "addr:postcode":"1180",
    "addr:street":"Kreuzg",
    "iso:country":"AT",
    "sg:address":"Kreuzg 34",
    "sg:city":"Wien",
    "sg:orig_category":"Installationsunternehmen",
    "sg:phone":"+43 1 4082097",
    "sg:postcode":"1180",
    "sg:province":"Wien",
    "wof:name":"Pichler Installations GmbH",
    "wof:placetype":"venue"
},
  "geometry": {"coordinates":[16.338924408,48.22315979],"type":"Point"}
}