{
  "type": "Feature",
  "properties": {
    "addr:full":"Eichenstr 20 Wien Wien 1120",
    "addr:housenumber":"20",
    "addr:postcode":"1120",
    "addr:street":"Eichenstr",
    "iso:country":"AT",
    "sg:address":"Eichenstr 20",
    "sg:city":"Wien",
    "sg:orig_category":"Ingenieurkonsulenten / Zivilingenieure",
    "sg:phone":"+43 1 8101400",
    "sg:postcode":"1120",
    "sg:province":"Wien",
    "wof:name":"3P Geotechnik ZT GmbH",
    "wof:placetype":"venue"
},
  "geometry": {"coordinates":[16.3392963409,48.1763763428],"type":"Point"}
}