{
  "type": "Feature",
  "properties": {
    "addr:full":"Wolfsegger Str 22b Attnang-Puchheim Ober\u00f6sterreich 4800",
    "addr:housenumber":"22b",
    "addr:postcode":"4800",
    "addr:street":"Str",
    "iso:country":"AT",
    "sg:address":"Wolfsegger Str 22b",
    "sg:city":"Attnang-Puchheim",
    "sg:orig_category":"Imkereien",
    "sg:phone":"+43 767465938",
    "sg:postcode":"4800",
    "sg:province":"Ober\u00f6sterreich",
    "wof:name":"Adam Friedrich",
    "wof:placetype":"venue"
},
  "geometry": {"coordinates":[13.7153816223,48.0205612183],"type":"Point"}
}