{
  "type": "Feature",
  "properties": {
    "addr:full":"Linke Wienzeile 8 Wien Wien 1060",
    "addr:housenumber":"8",
    "addr:postcode":"1060",
    "addr:street":"Linke Wienzeile",
    "iso:country":"AT",
    "sg:address":"Linke Wienzeile 8",
    "sg:city":"Wien",
    "sg:orig_category":"Ingenieurkonsulenten / Zivilingenieure",
    "sg:phone":"+43 1 58772100",
    "sg:postcode":"1060",
    "sg:province":"Wien",
    "wof:name":"Habian Wolfgang Dipl-Ing",
    "wof:placetype":"venue"
},
  "geometry": {"coordinates":[16.3640766144,48.1993141174],"type":"Point"}
}