{
  "type": "Feature",
  "properties": {
    "addr:full":"An-der-Lan-Str 33 Innsbruck Tirol 6020",
    "addr:housenumber":"33",
    "addr:postcode":"6020",
    "addr:street":"An-Der-Lan-Str;Tirol",
    "iso:country":"AT",
    "sg:address":"An-der-Lan-Str 33",
    "sg:city":"Innsbruck",
    "sg:orig_category":"Tabaktrafiken",
    "sg:phone":"+43 512 263233",
    "sg:postcode":"6020",
    "sg:province":"Tirol",
    "wof:name":"Berauer Hiltrud",
    "wof:placetype":"venue"
},
  "geometry": {"coordinates":[11.4416093826,47.2726020813],"type":"Point"}
}