{
  "type": "Feature",
  "properties": {
    "iso:country":"AT",
    "sg:address":"\u00dcberfuhrstr 59",
    "sg:city":"Wien",
    "sg:classifiers":[
        {
            "category":"Internet Cafe",
            "subcategory":"None",
            "type":"Food & Drink"
        }
    ],
    "sg:phone":"+43 4316 175628",
    "sg:postcode":"1210",
    "sg:province":"Wien",
    "wof:name":"ITeN Internet, Netzwerk u Telekommunikations GmbH",
    "wof:placetype":"venue"
},
  "geometry": {"coordinates":[16.3830680847,48.2702445984],"type":"Point"}
}