{
  "type": "Feature",
  "properties": {
    "addr:full":"Ungarg 71 Wien Wien 1030",
    "addr:housenumber":"71",
    "addr:postcode":"1030",
    "addr:street":"Ungarg",
    "iso:country":"AT",
    "sg:address":"Ungarg 71",
    "sg:city":"Wien",
    "sg:orig_category":"Architekten",
    "sg:phone":"+43 1 7188605",
    "sg:postcode":"1030",
    "sg:province":"Wien",
    "wof:name":"Lindner Heinz Arch Dipl-Ing",
    "wof:placetype":"venue"
},
  "geometry": {"coordinates":[16.3866119385,48.1953964233],"type":"Point"}
}