{
  "type": "Feature",
  "properties": {
    "addr:full":"Schulg 1 Gm\u00fcnd Nieder\u00f6sterreich 3950",
    "addr:housenumber":"1",
    "addr:postcode":"3950",
    "addr:street":"Schulg;Niederoesterreich",
    "iso:country":"AT",
    "sg:address":"Schulg 1",
    "sg:city":"Gm\u00fcnd",
    "sg:orig_category":"Hauptschulen",
    "sg:phone":"+43 2852 521040",
    "sg:postcode":"3950",
    "sg:province":"Nieder\u00f6sterreich",
    "wof:name":"Hauptschule 2",
    "wof:placetype":"venue"
},
  "geometry": {"coordinates":[14.9858999252,48.7695922852],"type":"Point"}
}