{
  "type": "Feature",
  "properties": {
    "addr:full":"Hauptpl 5 Pinggau Steiermark 8243",
    "addr:housenumber":"5",
    "addr:postcode":"8243",
    "addr:street":"Hauptpl",
    "iso:country":"AT",
    "sg:address":"Hauptpl 5",
    "sg:city":"Pinggau",
    "sg:orig_category":"Fleischhauereien",
    "sg:phone":"+43 3339 24330",
    "sg:postcode":"8243",
    "sg:province":"Steiermark",
    "wof:name":"Schirnhofer FleischwarenvertriebsgesmbH & Co",
    "wof:placetype":"venue"
},
  "geometry": {"coordinates":[16.0643997192,47.4439849854],"type":"Point"}
}