{
  "type": "Feature",
  "properties": {
    "iso:country":"AT",
    "sg:address":"Doerenkampgasse 3 ",
    "sg:city":"Wien",
    "sg:classifiers":[
        {
            "category":"Professional",
            "subcategory":"Computer Services",
            "type":"Services"
        }
    ],
    "sg:phone":"+43 4317 8000",
    "sg:postcode":"1100",
    "sg:province":"Wien",
    "sg:tags":[
        "information",
        "technology"
    ],
    "wof:name":"FANCY MEDIA HANDELS UND PRODUKTIONGES. MBH",
    "wof:placetype":"venue"
},
  "geometry": {"coordinates":[16.3799247742,48.1430206299],"type":"Point"}
}