{
  "type": "Feature",
  "properties": {
    "addr:full":"Paris-Lodron-Str 2 Salzburg Salzburg 5020",
    "addr:housenumber":"2",
    "addr:postcode":"5020",
    "addr:street":"Paris-Lodron-Str;Salzburg",
    "iso:country":"AT",
    "sg:address":"Paris-Lodron-Str 2",
    "sg:city":"Salzburg",
    "sg:orig_category":"Optiker",
    "sg:phone":"+43 662 873693",
    "sg:postcode":"5020",
    "sg:province":"Salzburg",
    "wof:name":"Brillenwerkstatt Roland Pf\u00f6ss",
    "wof:placetype":"venue"
},
  "geometry": {"coordinates":[13.0448646545,47.8045578003],"type":"Point"}
}