{
  "type": "Feature",
  "properties": {
    "iso:country":"AT",
    "sg:address":"Leopoldsdorfer Str 25",
    "sg:city":"Maria Lanzendorf",
    "sg:orig_category":"Alarmanlagen U Sicherheitssysteme",
    "sg:phone":"+43 4322 3542828",
    "sg:postcode":"2326",
    "sg:province":"Nieder\u00f6sterreich",
    "wof:name":"GNC Grasnek & Nell Communication Systems GmbH",
    "wof:placetype":"venue"
},
  "geometry": {"coordinates":[16.4148693085,48.0993690491],"type":"Point"}
}