{
  "type": "Feature",
  "properties": {
    "addr:full":"Friedensstr 5 Salzburg Salzburg 5020",
    "addr:housenumber":"5",
    "addr:postcode":"5020",
    "addr:street":"Friedensstr;Salzburg",
    "iso:country":"AT",
    "sg:address":"Friedensstr 5",
    "sg:city":"Salzburg",
    "sg:orig_category":"Non-Classified Establishments",
    "sg:phone":"+43 662 6204230",
    "sg:postcode":"5020",
    "sg:province":"Salzburg",
    "wof:name":"Kloster Herrnau",
    "wof:placetype":"venue"
},
  "geometry": {"coordinates":[13.0650033951,47.7857475281],"type":"Point"}
}