{
  "type": "Feature",
  "properties": {
    "addr:full":"Roseggerstrasse 5 Ternberg Ober\u00f6sterreich 4452",
    "addr:housenumber":"5",
    "addr:postcode":"4452",
    "addr:street":"Roseggerstrasse",
    "iso:country":"AT",
    "sg:address":"Roseggerstrasse 5",
    "sg:city":"Ternberg",
    "sg:classifiers":[
        {
            "category":"Banks & Credit Unions",
            "subcategory":"Bureau De Change",
            "type":"Services"
        }
    ],
    "sg:phone":"+43 7256 8849",
    "sg:postcode":"4452",
    "sg:province":"Ober\u00f6sterreich",
    "sg:tags":[
        "flat",
        "construction",
        "roof"
    ],
    "wof:name":"Gerold Weinberger",
    "wof:placetype":"venue"
},
  "geometry": {"coordinates":[14.359703064,47.9426307678],"type":"Point"}
}