{
  "type": "Feature",
  "properties": {
    "addr:full":"Brauhausgasse 2 Obertrum am See Salzburg 5162",
    "addr:housenumber":"2",
    "addr:postcode":"5162",
    "addr:street":"Brauhausgasse;Salzburg",
    "iso:country":"AT",
    "sg:address":"Brauhausgasse 2",
    "sg:city":"Obertrum am See",
    "sg:classifiers":[
        {
            "category":"Wholesale",
            "subcategory":"Beer",
            "type":"Manufacturing & Wholesale Goods"
        }
    ],
    "sg:phone":"+43 6219 74110",
    "sg:postcode":"5162",
    "sg:province":"Salzburg",
    "sg:website":"trumer.pils.at",
    "wof:name":"Privatbrauerei Josef Sigl",
    "wof:placetype":"venue"
},
  "geometry": {"coordinates":[13.0777101517,47.9378013611],"type":"Point"}
}