{
  "type": "Feature",
  "properties": {
    "addr:full":"Felberstrasse 3 Wien Wien 1150",
    "addr:housenumber":"3",
    "addr:postcode":"1150",
    "addr:street":"Felberstrasse",
    "iso:country":"AT",
    "sg:address":"Felberstrasse 3",
    "sg:city":"Wien",
    "sg:classifiers":[
        {
            "category":"Manufacturing",
            "subcategory":"Paper Products",
            "type":"Manufacturing & Wholesale Goods"
        }
    ],
    "sg:phone":"+43 1 98234560",
    "sg:postcode":"1150",
    "sg:province":"Wien",
    "sg:tags":[
        "brochure",
        "production"
    ],
    "wof:name":"Felix Neuhold Ges.m.b.H.",
    "wof:placetype":"venue"
},
  "geometry": {"coordinates":[16.3341197968,48.1969833374],"type":"Point"}
}