{
  "type": "Feature",
  "properties": {
    "addr:full":"Nr 31 Irnfritz Nieder\u00f6sterreich 3754",
    "addr:postcode":"3754",
    "addr:street":"Nr 31 Irnfritz",
    "iso:country":"AT",
    "sg:address":"Nr 31",
    "sg:city":"Irnfritz",
    "sg:orig_category":"Maler, Anstreicher U Lackierer, Werbegrafik- U Grafik-Design",
    "sg:phone":"+43 2986 64110",
    "sg:postcode":"3754",
    "sg:province":"Nieder\u00f6sterreich",
    "sg:website":"www.kristobal.at",
    "wof:name":"Studio Kristobal",
    "wof:placetype":"venue"
},
  "geometry": {"coordinates":[15.5585279465,48.7394676208],"type":"Point"}
}