{
  "type": "Feature",
  "properties": {
    "addr:full":"Neulerchenfelder Str 58 Wien Wien 1160",
    "addr:postcode":"1160",
    "addr:street":"Str 58",
    "iso:country":"AT",
    "sg:address":"Neulerchenfelder Str 58",
    "sg:city":"Wien",
    "sg:classifiers":[
        {
            "category":"Professional",
            "subcategory":"Management & Consulting",
            "type":"Services"
        }
    ],
    "sg:phone":"+43 676 7331037",
    "sg:postcode":"1160",
    "sg:province":"Wien",
    "sg:tags":[
        "supervision"
    ],
    "wof:name":"Schmid Maria",
    "wof:placetype":"venue"
},
  "geometry": {"coordinates":[16.3322238922,48.2117004395],"type":"Point"}
}