{
  "type": "Feature",
  "properties": {
    "addr:full":"Pratergasse 138 Bad Aussee Steiermark 8990",
    "addr:housenumber":"138",
    "addr:postcode":"8990",
    "addr:street":"Pratergasse",
    "iso:country":"AT",
    "sg:address":"Pratergasse 138",
    "sg:city":"Bad Aussee",
    "sg:classifiers":[
        {
            "category":"Building & Trades",
            "subcategory":"Electrical",
            "type":"Services"
        }
    ],
    "sg:phone":"+43 3622 520400",
    "sg:postcode":"8990",
    "sg:province":"Steiermark",
    "sg:tags":[
        "work",
        "installation"
    ],
    "sg:website":"ewerk.at",
    "wof:name":"Schwarz, Wagendorffer & Co Elektrizit\u00e4tswerk GmbH",
    "wof:placetype":"venue"
},
  "geometry": {"coordinates":[13.7847232819,47.6079368591],"type":"Point"}
}