{
  "type": "Feature",
  "properties": {
    "addr:full":"Greiseneckerg 31 Wien Wien 1200",
    "addr:housenumber":"31",
    "addr:postcode":"1200",
    "addr:street":"Greiseneckerg",
    "iso:country":"AT",
    "sg:address":"Greiseneckerg 31",
    "sg:city":"Wien",
    "sg:orig_category":"Hauptschulen",
    "sg:phone":"+43 1 3325354",
    "sg:postcode":"1200",
    "sg:province":"Wien",
    "wof:name":"Schulen d Stadt Wien",
    "wof:placetype":"venue"
},
  "geometry": {"coordinates":[16.3744544983,48.231628418],"type":"Point"}
}