{
  "type": "Feature",
  "properties": {
    "addr:full":"Schwarzhorngasse 9 Wien Wien 1050",
    "addr:housenumber":"9",
    "addr:postcode":"1050",
    "addr:street":"Schwarzhorngasse",
    "iso:country":"AT",
    "sg:address":"Schwarzhorngasse 9",
    "sg:city":"Wien",
    "sg:classifiers":[
        {
            "category":"Home & Garden",
            "subcategory":"Carpets & Floor Coverings",
            "type":"Retail Goods"
        }
    ],
    "sg:phone":"+43 1 5447145",
    "sg:postcode":"1050",
    "sg:province":"Wien",
    "sg:tags":[
        "carpeting"
    ],
    "sg:website":"h-o.at",
    "wof:name":"Hans Ortner Ges.m.b.H.",
    "wof:placetype":"venue"
},
  "geometry": {"coordinates":[16.3535881042,48.1871871948],"type":"Point"}
}