{
  "type": "Feature",
  "properties": {
    "iso:country":"AT",
    "sg:address":"Triester Str 359",
    "sg:city":"Puntigam",
    "sg:orig_category":"Brauereien",
    "sg:phone":"+43 316 5020",
    "sg:postcode":"8055",
    "sg:province":"Steiermark",
    "wof:name":"Brau Union \u00f6sterreich AG Brauerei Puntigam",
    "wof:placetype":"venue"
},
  "geometry": {"coordinates":[15.4321517944,47.0300827026],"type":"Point"}
}