{
  "type": "Feature",
  "properties": {
    "iso:country":"AT",
    "sg:address":"Landstr 38",
    "sg:city":"Linz",
    "sg:orig_category":"Steuerberatung",
    "sg:phone":"+43 732 770037",
    "sg:postcode":"4020",
    "sg:province":"Ober\u00f6sterreich",
    "sg:website":"www.braunschmid.at",
    "wof:name":"Braunschmid Karl Mag Dr",
    "wof:placetype":"venue"
},
  "geometry": {"coordinates":[14.2901582718,48.3012733459],"type":"Point"}
}