{
  "type": "Feature",
  "properties": {
    "iso:country":"AT",
    "sg:address":"Piaristeng 18/2a",
    "sg:city":"Wien",
    "sg:orig_category":"Abzeichen U Embleme",
    "sg:phone":"+43 1 40875530",
    "sg:postcode":"1080",
    "sg:province":"Wien",
    "sg:website":"www.nordemail.com",
    "wof:name":"Nord Email - DI I Komnacky",
    "wof:placetype":"venue"
},
  "geometry": {"coordinates":[16.3512821198,48.2074775696],"type":"Point"}
}