{
  "type": "Feature",
  "properties": {
    "addr:full":"Bahnhofstr Schwaz Tirol 6130",
    "addr:postcode":"6130",
    "addr:street":"Bahnhofstr Schwaz Tirol",
    "iso:country":"AT",
    "sg:address":"Bahnhofstr",
    "sg:city":"Schwaz",
    "sg:orig_category":"Tabaktrafiken",
    "sg:phone":"+43 4352 4271293",
    "sg:postcode":"6130",
    "sg:province":"Tirol",
    "wof:name":"Invaliden-Wohnheim Schwaz GesmbH - Kiosk",
    "wof:placetype":"venue"
},
  "geometry": {"coordinates":[11.7035980225,47.348651886],"type":"Point"}
}