{
  "type": "Feature",
  "properties": {
    "addr:full":"Frauentaler Str 123 Deutschlandsberg Steiermark 8530",
    "addr:housenumber":"123",
    "addr:postcode":"8530",
    "iso:country":"AT",
    "sg:address":"Frauentaler Str 123",
    "sg:city":"Deutschlandsberg",
    "sg:orig_category":"Autohandel",
    "sg:phone":"+43 4334 623977",
    "sg:postcode":"8530",
    "sg:province":"Steiermark",
    "wof:name":"Roschker GesmbH",
    "wof:placetype":"venue"
},
  "geometry": {"coordinates":[15.2369947433,46.8208656311],"type":"Point"}
}