{
  "type": "Feature",
  "properties": {
    "addr:full":"Jahnstr 8 Innsbruck Tirol 6020",
    "addr:housenumber":"8",
    "addr:postcode":"6020",
    "addr:street":"Jahnstr;Tirol",
    "iso:country":"AT",
    "sg:address":"Jahnstr 8",
    "sg:city":"Innsbruck",
    "sg:orig_category":"Bildungsservice / Allgemeine Informationsstellen",
    "sg:phone":"+43 512 560606",
    "sg:postcode":"6020",
    "sg:province":"Tirol",
    "wof:name":"Verein z F\u00f6rderung d freien Waldorfschule in Innsbruck",
    "wof:placetype":"venue"
},
  "geometry": {"coordinates":[11.4041023254,47.2689666748],"type":"Point"}
}