{
  "type": "Feature",
  "properties": {
    "addr:full":"Laxenburger Strasse 250 Wien Wien 1230",
    "addr:housenumber":"250",
    "addr:postcode":"1230",
    "addr:street":"Laxenburger Strasse",
    "iso:country":"AT",
    "sg:address":"Laxenburger Strasse 250",
    "sg:city":"Wien",
    "sg:classifiers":[
        {
            "category":"Deli",
            "type":"Food & Drink"
        }
    ],
    "sg:phone":"+43 1 81585050",
    "sg:postcode":"1230",
    "sg:province":"Wien",
    "sg:tags":[
        "delicatessen"
    ],
    "sg:website":"wojnar.at",
    "wof:name":"WOJNAR'S WIENER LECKERBISSEN Delikatessenerzeugung GmbH",
    "wof:placetype":"venue"
},
  "geometry": {"coordinates":[16.3565406799,48.1356048584],"type":"Point"}
}