{
  "type": "Feature",
  "properties": {
    "iso:country":"AT",
    "sg:address":"Breitenseer Str 38",
    "sg:city":"Wien",
    "sg:orig_category":"Autoersatzteile",
    "sg:phone":"+43 1 9827423",
    "sg:postcode":"1140",
    "sg:province":"Wien",
    "sg:website":"christcarconcept.at",
    "wof:name":"Christ Peter",
    "wof:placetype":"venue"
},
  "geometry": {"coordinates":[16.3094577789,48.2013511658],"type":"Point"}
}