{
  "type": "Feature",
  "properties": {
    "addr:full":"Meierhofpl 3 Pinkafeld Burgenland 7423",
    "addr:housenumber":"3",
    "addr:postcode":"7423",
    "addr:street":"Meierhofpl",
    "iso:country":"AT",
    "sg:address":"Meierhofpl 3",
    "sg:city":"Pinkafeld",
    "sg:orig_category":"Pensionen / Privatzimmer",
    "sg:phone":"+43 4333 5742230",
    "sg:postcode":"7423",
    "sg:province":"Burgenland",
    "wof:name":"Sagmeister-Hof",
    "wof:placetype":"venue"
},
  "geometry": {"coordinates":[16.1209621429,47.3660125732],"type":"Point"}
}