{
  "type": "Feature",
  "properties": {
    "iso:country":"AT",
    "sg:address":"Nr 67",
    "sg:city":"Hohenwarth",
    "sg:orig_category":"Banken U Sparkassen",
    "sg:phone":"+43 2957 217",
    "sg:postcode":"3472",
    "sg:province":"Nieder\u00f6sterreich",
    "wof:name":"Raiffeisenbank Langenlois regGenmbH",
    "wof:placetype":"venue"
},
  "geometry": {"coordinates":[15.827583313,48.5075111389],"type":"Point"}
}