{
  "type": "Feature",
  "properties": {
    "iso:country":"AT",
    "sg:address":"Allmeinteilweg 15",
    "sg:city":"Ludesch",
    "sg:orig_category":"Schneidereien",
    "sg:phone":"+43 5550 24300",
    "sg:postcode":"6713",
    "sg:province":"Vorarlberg",
    "sg:website":"www.members.aon.at/fashion",
    "wof:name":"Kaufmann Edith - Mass-Schneiderei",
    "wof:placetype":"venue"
},
  "geometry": {"coordinates":[9.7697496414,47.1842918396],"type":"Point"}
}