{
  "type": "Feature",
  "properties": {
    "addr:full":"Durisolstr 5 Mautern in Steiermark Steiermark 8774",
    "addr:housenumber":"5",
    "addr:postcode":"8774",
    "addr:street":"Durisolstr",
    "iso:country":"AT",
    "sg:address":"Durisolstr 5",
    "sg:city":"Mautern in Steiermark",
    "sg:classifiers":[
        {
            "category":"Autos & Motor Vehicles",
            "subcategory":"Auto Supplies",
            "type":"Retail Goods"
        }
    ],
    "sg:phone":"+43 4338 452295",
    "sg:postcode":"8774",
    "sg:province":"Steiermark",
    "sg:tags":[
        "regale"
    ],
    "wof:name":"Durisol Vinothek",
    "wof:placetype":"venue"
},
  "geometry": {"coordinates":[14.8350515366,47.3960494995],"type":"Point"}
}