{
  "type": "Feature",
  "properties": {
    "addr:full":"Industrieg. Ii-11  Hornstein Burgenland 7053",
    "addr:postcode":"7053",
    "iso:country":"AT",
    "sg:address":"Industrieg. Ii-11 ",
    "sg:city":"Hornstein",
    "sg:classifiers":[
        {
            "category":"Utilities",
            "subcategory":"Electric",
            "type":"Services"
        }
    ],
    "sg:phone":"+43 4326 8927440",
    "sg:postcode":"7053",
    "sg:province":"Burgenland",
    "sg:tags":[
        "component",
        "electronic"
    ],
    "wof:name":"TRAFOMODERN-TRANSFORMATOREN- GES.MBH",
    "wof:placetype":"venue"
},
  "geometry": {"coordinates":[16.4282855988,47.8758735657],"type":"Point"}
}