{
  "type": "Feature",
  "properties": {
    "iso:country":"AT",
    "sg:address":"Heliosallee 106/34",
    "sg:city":"Linz",
    "sg:orig_category":"Webdesign",
    "sg:phone":"+43 4373 2917489",
    "sg:postcode":"4030",
    "sg:province":"Ober\u00f6sterreich",
    "wof:name":"cyberkanzlei Punz GmbH",
    "wof:placetype":"venue"
},
  "geometry": {"coordinates":[14.3632040024,48.2567100525],"type":"Point"}
}