{
  "type": "Feature",
  "properties": {
    "iso:country":"AT",
    "sg:address":"Franz-Josef-Str 25",
    "sg:city":"Schwaz",
    "sg:orig_category":"Boutiquen",
    "sg:phone":"+43 5242 63315",
    "sg:postcode":"6130",
    "sg:province":"Tirol",
    "wof:name":"Boutique Tandem",
    "wof:placetype":"venue"
},
  "geometry": {"coordinates":[11.7090406418,47.3462219238],"type":"Point"}
}