{
  "type": "Feature",
  "properties": {
    "addr:full":"Paul Hackhofer-Str 10 Wolfsberg K\u00e4rnten 9400",
    "addr:housenumber":"10",
    "addr:postcode":"9400",
    "addr:street":"Wolfsberg Kaernten",
    "iso:country":"AT",
    "sg:address":"Paul Hackhofer-Str 10",
    "sg:city":"Wolfsberg",
    "sg:orig_category":"\u00c3\u201erzte / F Allgemeinmedizin",
    "sg:phone":"+43 4352 371000",
    "sg:postcode":"9400",
    "sg:province":"K\u00e4rnten",
    "wof:name":"Brunnbauer Christian Mag Dr",
    "wof:placetype":"venue"
},
  "geometry": {"coordinates":[14.8461437225,46.8349533081],"type":"Point"}
}