{
  "type": "Feature",
  "properties": {
    "addr:full":"Alser Str 71/9 Wien Wien 1080",
    "addr:housenumber":"71 / 9",
    "addr:postcode":"1080",
    "addr:street":"Str",
    "iso:country":"AT",
    "sg:address":"Alser Str 71/9",
    "sg:city":"Wien",
    "sg:orig_category":"Webdesign",
    "sg:phone":"+43 4366 41526010",
    "sg:postcode":"1080",
    "sg:province":"Wien",
    "wof:name":"CCS - Cerberos Computer Solutions",
    "wof:placetype":"venue"
},
  "geometry": {"coordinates":[16.3416080475,48.2150115967],"type":"Point"}
}