{
  "type": "Feature",
  "properties": {
    "addr:full":"Faunastr 2 Wetzelsdorf Steiermark 8052",
    "addr:housenumber":"2",
    "addr:postcode":"8052",
    "addr:street":"Faunastr",
    "iso:country":"AT",
    "sg:address":"Faunastr 2",
    "sg:city":"Wetzelsdorf",
    "sg:orig_category":"Autohandel",
    "sg:phone":"+43 316 5756440",
    "sg:postcode":"8052",
    "sg:province":"Steiermark",
    "wof:name":"Wiesinger & B\u00e4ck Kfz-Handels OHG",
    "wof:placetype":"venue"
},
  "geometry": {"coordinates":[15.4038743973,47.0591049194],"type":"Point"}
}