{
  "type": "Feature",
  "properties": {
    "addr:full":"Hauptstr 51 Eggendorf Nieder\u00f6sterreich 2492",
    "addr:housenumber":"51",
    "addr:postcode":"2492",
    "addr:street":"Hauptstr",
    "iso:country":"AT",
    "sg:address":"Hauptstr 51",
    "sg:city":"Eggendorf",
    "sg:orig_category":"Blumeneinzelhandel",
    "sg:phone":"+43 4326 2274286",
    "sg:postcode":"2492",
    "sg:province":"Nieder\u00f6sterreich",
    "wof:name":"Ruess Marietta",
    "wof:placetype":"venue"
},
  "geometry": {"coordinates":[8.1344404221,49.3539199829],"type":"Point"}
}