{
  "type": "Feature",
  "properties": {
    "addr:full":"Fieberbrunner Strasse 18 St. Johann in Tirol Tirol 6380",
    "addr:housenumber":"18",
    "addr:postcode":"6380",
    "addr:street":"Fieberbrunner Strasse;Tirol",
    "iso:country":"AT",
    "sg:address":"Fieberbrunner Strasse 18",
    "sg:city":"St. Johann in Tirol",
    "sg:classifiers":[
        {
            "category":"Manufacturing",
            "subcategory":"Paper Products",
            "type":"Manufacturing & Wholesale Goods"
        }
    ],
    "sg:phone":"+43 5352 62425",
    "sg:postcode":"6380",
    "sg:province":"Tirol",
    "sg:tags":[
        "brochure",
        "production"
    ],
    "sg:website":"dingerdruck.com",
    "wof:name":"Dinger Stempel KG",
    "wof:placetype":"venue"
},
  "geometry": {"coordinates":[12.4340543747,47.520526886],"type":"Point"}
}