{
  "type": "Feature",
  "properties": {
    "iso:country":"AT",
    "sg:address":"Marktpl 4",
    "sg:city":"Obernberg am Inn",
    "sg:orig_category":"Apotheken",
    "sg:phone":"+43 7758 22230",
    "sg:postcode":"4982",
    "sg:province":"Ober\u00f6sterreich",
    "sg:website":"apotheke-obernberg.at",
    "wof:name":"Apotheke z hl Jungfrau",
    "wof:placetype":"venue"
},
  "geometry": {"coordinates":[13.3355798721,48.3223381042],"type":"Point"}
}