{
  "type": "Feature",
  "properties": {
    "addr:full":"Hauptpl 16/2 St. Veit an der Glan K\u00e4rnten 9300",
    "addr:housenumber":"16 / 2",
    "addr:postcode":"9300",
    "addr:street":"Hauptpl;Kaernten",
    "iso:country":"AT",
    "sg:address":"Hauptpl 16/2",
    "sg:city":"St. Veit an der Glan",
    "sg:orig_category":"Lebens- U Sozialberatung",
    "sg:phone":"+43 4366 49419130",
    "sg:postcode":"9300",
    "sg:province":"K\u00e4rnten",
    "wof:name":"Haag Ulrich Dipl-P\u00e4d - Paar- Familienberater",
    "wof:placetype":"venue"
},
  "geometry": {"coordinates":[14.3576250076,46.766872406],"type":"Point"}
}