{
  "type": "Feature",
  "properties": {
    "addr:full":"Mariatroster Str 289 Mariatrost Steiermark 8044",
    "addr:housenumber":"289",
    "addr:postcode":"8044",
    "iso:country":"AT",
    "sg:address":"Mariatroster Str 289",
    "sg:city":"Mariatrost",
    "sg:orig_category":"Friseure U Frisiersalons",
    "sg:phone":"+43 4331 6394189",
    "sg:postcode":"8044",
    "sg:province":"Steiermark",
    "wof:name":"Krenn Berta vereh Demut",
    "wof:placetype":"venue"
},
  "geometry": {"coordinates":[15.4882707596,47.1062049866],"type":"Point"}
}