{
  "type": "Feature",
  "properties": {
    "addr:full":"Volksgartenstr 24 Linz Ober\u00f6sterreich 4020",
    "addr:housenumber":"24",
    "addr:postcode":"4020",
    "addr:street":"Volksgartenstr",
    "iso:country":"AT",
    "sg:address":"Volksgartenstr 24",
    "sg:city":"Linz",
    "sg:orig_category":"Friseure U Frisiersalons",
    "sg:phone":"+43 732 664498",
    "sg:postcode":"4020",
    "sg:province":"Ober\u00f6sterreich",
    "wof:name":"Stockmayr Gerhard",
    "wof:placetype":"venue"
},
  "geometry": {"coordinates":[14.2896566391,48.2958183289],"type":"Point"}
}