{
  "type": "Feature",
  "properties": {
    "addr:full":"Lasberger Str 12 Freistadt Ober\u00f6sterreich 4240",
    "addr:housenumber":"12",
    "addr:postcode":"4240",
    "addr:street":"Str",
    "iso:country":"AT",
    "sg:address":"Lasberger Str 12",
    "sg:city":"Freistadt",
    "sg:orig_category":"Non-Classified Establishments",
    "sg:phone":"+43 7942 724940",
    "sg:postcode":"4240",
    "sg:province":"Ober\u00f6sterreich",
    "wof:name":"Tilly-Kaserne",
    "wof:placetype":"venue"
},
  "geometry": {"coordinates":[14.5049953461,48.5119857788],"type":"Point"}
}