{
  "type": "Feature",
  "properties": {
    "addr:full":"Opernring 1R Wien Wien 1010",
    "addr:housenumber":"1r",
    "addr:postcode":"1010",
    "addr:street":"Opernring",
    "iso:country":"AT",
    "sg:address":"Opernring 1R",
    "sg:city":"Wien",
    "sg:classifiers":[
        {
            "category":"Manufacturing",
            "subcategory":"Food",
            "type":"Manufacturing & Wholesale Goods"
        }
    ],
    "sg:phone":"+43 1 6156177",
    "sg:postcode":"1010",
    "sg:province":"Wien",
    "sg:tags":[
        "packaging",
        "machine"
    ],
    "wof:name":"impex trading Maschinenges.m.b.H.",
    "wof:placetype":"venue"
},
  "geometry": {"coordinates":[16.36901474,48.2022247314],"type":"Point"}
}