{
  "type": "Feature",
  "properties": {
    "iso:country":"AT",
    "sg:address":"Torren 239",
    "sg:city":"Golling an der Salzach",
    "sg:orig_category":"Physiotherapie",
    "sg:phone":"+43 6244 6096",
    "sg:postcode":"5440",
    "sg:province":"Salzburg",
    "wof:name":"Panhofer Maria Dipl-PT",
    "wof:placetype":"venue"
},
  "geometry": {"coordinates":[13.2115449905,47.5899581909],"type":"Point"}
}