{
  "type": "Feature",
  "properties": {
    "iso:country":"AT",
    "sg:address":"Nr 34",
    "sg:city":"Obertraun",
    "sg:orig_category":"Appartements / Ferienwohnungen",
    "sg:phone":"+43 6131 569",
    "sg:postcode":"4831",
    "sg:province":"Ober\u00f6sterreich",
    "wof:name":"Ferienhof Osl Fam Renner",
    "wof:placetype":"venue"
},
  "geometry": {"coordinates":[13.6863412857,47.5574989319],"type":"Point"}
}