{
  "type": "Feature",
  "properties": {
    "addr:full":"Theodor-K\u00f6rner-G 9 Purkersdorf Nieder\u00f6sterreich 3002",
    "addr:housenumber":"9",
    "addr:postcode":"3002",
    "addr:street":"Theodor-Koerner-G",
    "iso:country":"AT",
    "sg:address":"Theodor-K\u00f6rner-G 9",
    "sg:city":"Purkersdorf",
    "sg:orig_category":"Fenster",
    "sg:phone":"+43 2231 64121",
    "sg:postcode":"3002",
    "sg:province":"Nieder\u00f6sterreich",
    "sg:website":"www.fenstersani.at",
    "wof:name":"Lettner & Co KEG",
    "wof:placetype":"venue"
},
  "geometry": {"coordinates":[16.1678066254,48.2012023926],"type":"Point"}
}