{
  "type": "Feature",
  "properties": {
    "addr:full":"Landstr 3 Nenzing Vorarlberg 6710",
    "addr:housenumber":"3",
    "addr:postcode":"6710",
    "addr:street":"Landstr",
    "iso:country":"AT",
    "sg:address":"Landstr 3",
    "sg:city":"Nenzing",
    "sg:orig_category":"Blumeneinzelhandel",
    "sg:phone":"+43 5525 63690",
    "sg:postcode":"6710",
    "sg:province":"Vorarlberg",
    "wof:name":"G\u00e4nseblume Latzer-Violand Ingrid",
    "wof:placetype":"venue"
},
  "geometry": {"coordinates":[9.7051916122,47.1845932007],"type":"Point"}
}