{
  "type": "Feature",
  "properties": {
    "addr:full":"Wiener Str 13 Knittelfeld Steiermark 8720",
    "addr:postcode":"8720",
    "iso:country":"AT",
    "sg:address":"Wiener Str 13",
    "sg:city":"Knittelfeld",
    "sg:orig_category":"Restaurants: Amerikanisch",
    "sg:phone":"+43 3512 82199",
    "sg:postcode":"8720",
    "sg:province":"Steiermark",
    "wof:name":"McDonald's Restaurant - McDrive",
    "wof:placetype":"venue"
},
  "geometry": {"coordinates":[14.8273124695,47.2170677185],"type":"Point"}
}