{
  "type": "Feature",
  "properties": {
    "addr:full":"Alte Bundesstr 177 Kuchl Salzburg 5431",
    "addr:housenumber":"177",
    "addr:postcode":"5431",
    "addr:street":"Salzburg",
    "iso:country":"AT",
    "sg:address":"Alte Bundesstr 177",
    "sg:city":"Kuchl",
    "sg:orig_category":"Messen U Ausstellungen",
    "sg:phone":"+43 6245 823490",
    "sg:postcode":"5431",
    "sg:province":"Salzburg",
    "wof:name":"Orion Messe- und AusstellungsgesmbH & Co KG",
    "wof:placetype":"venue"
},
  "geometry": {"coordinates":[13.135052681,47.6471939087],"type":"Point"}
}