{
  "type": "Feature",
  "properties": {
    "addr:full":"Ferihumerstr 44 Linz Ober\u00f6sterreich 4040",
    "addr:housenumber":"44",
    "addr:postcode":"4040",
    "addr:street":"Ferihumerstr",
    "iso:country":"AT",
    "sg:address":"Ferihumerstr 44",
    "sg:city":"Linz",
    "sg:orig_category":"Tabaktrafiken",
    "sg:phone":"+43 732 731156",
    "sg:postcode":"4040",
    "sg:province":"Ober\u00f6sterreich",
    "wof:name":"Stadlhuber Barbara",
    "wof:placetype":"venue"
},
  "geometry": {"coordinates":[14.2896280289,48.3154907227],"type":"Point"}
}