{
  "type": "Feature",
  "properties": {
    "addr:full":"Goldschneiderhofweg 3 Salzburg Salzburg 5020",
    "addr:housenumber":"3",
    "addr:postcode":"5020",
    "addr:street":"Goldschneiderhofweg;Salzburg",
    "iso:country":"AT",
    "sg:address":"Goldschneiderhofweg 3",
    "sg:city":"Salzburg",
    "sg:orig_category":"Garten- U Landschaftsgestaltung",
    "sg:phone":"+43 662 821116",
    "sg:postcode":"5020",
    "sg:province":"Salzburg",
    "wof:name":"Schuster Gartengestaltung OEG",
    "wof:placetype":"venue"
},
  "geometry": {"coordinates":[13.040148735,47.7733688354],"type":"Point"}
}