{
  "type": "Feature",
  "properties": {
    "addr:full":"Rathauspl 7 Persenbeug Nieder\u00f6sterreich 3680",
    "addr:housenumber":"7",
    "addr:postcode":"3680",
    "addr:street":"Rathauspl",
    "iso:country":"AT",
    "sg:address":"Rathauspl 7",
    "sg:city":"Persenbeug",
    "sg:orig_category":"Gerichte",
    "sg:phone":"+43 7412 522180",
    "sg:postcode":"3680",
    "sg:province":"Nieder\u00f6sterreich",
    "wof:name":"Bezirksgericht Ybbs - Gerichtstag Persenbeug",
    "wof:placetype":"venue"
},
  "geometry": {"coordinates":[15.0793991089,48.1880302429],"type":"Point"}
}