{
  "type": "Feature",
  "properties": {
    "addr:full":"Nr 11 St. Margarethen an der Raab Steiermark 8321",
    "addr:postcode":"8321",
    "addr:street":"Nr 11",
    "iso:country":"AT",
    "sg:address":"Nr 11",
    "sg:city":"St. Margarethen an der Raab",
    "sg:orig_category":"Banken U Sparkassen",
    "sg:phone":"+43 4331 1524880",
    "sg:postcode":"8321",
    "sg:province":"Steiermark",
    "wof:name":"Bankomat d Raiffeisenbank Gleisdorf regGenmbH",
    "wof:placetype":"venue"
},
  "geometry": {"coordinates":[15.7453098297,47.0449333191],"type":"Point"}
}