{
  "type": "Feature",
  "properties": {
    "iso:country":"AT",
    "sg:address":"Eckperg 31",
    "sg:city":"Wien",
    "sg:orig_category":"Immobilienmakler",
    "sg:phone":"+43 1 4700162",
    "sg:postcode":"1180",
    "sg:province":"Wien",
    "sg:website":"rtimmo.at",
    "wof:name":"Toth Renate",
    "wof:placetype":"venue"
},
  "geometry": {"coordinates":[16.3154678345,48.2353019714],"type":"Point"}
}