{
  "type": "Feature",
  "properties": {
    "iso:country":"AT",
    "sg:address":"Schererstr 10",
    "sg:city":"Wien",
    "sg:orig_category":"Schrauben, Muttern U Nieten",
    "sg:phone":"+43 4312 50290",
    "sg:postcode":"1210",
    "sg:province":"Wien",
    "sg:website":"mueller-wilde.com",
    "wof:name":"M\u00dcLLER & WILDE Schraubengro\u00dfhandlung GesmbH & Co KG",
    "wof:placetype":"venue"
},
  "geometry": {"coordinates":[16.4396343231,48.2745857239],"type":"Point"}
}