{
  "type": "Feature",
  "properties": {
    "addr:full":"Zieglerstr 9b Hohenems Vorarlberg 6845",
    "addr:housenumber":"9b",
    "addr:postcode":"6845",
    "addr:street":"Zieglerstr",
    "iso:country":"AT",
    "sg:address":"Zieglerstr 9b",
    "sg:city":"Hohenems",
    "sg:classifiers":[
        {
            "category":"Taxi",
            "type":"Transportation"
        }
    ],
    "sg:phone":"+43 4355 7673173",
    "sg:postcode":"6845",
    "sg:province":"Vorarlberg",
    "sg:tags":[
        "personentransporte",
        "u"
    ],
    "wof:name":"Taxi Mathis GmbH",
    "wof:placetype":"venue"
},
  "geometry": {"coordinates":[9.6765365601,47.3615264893],"type":"Point"}
}