{
  "type": "Feature",
  "properties": {
    "addr:full":"Erzherzog-Johann-Str 278 Stainach Steiermark 8950",
    "addr:housenumber":"278",
    "addr:postcode":"8950",
    "iso:country":"AT",
    "sg:address":"Erzherzog-Johann-Str 278",
    "sg:city":"Stainach",
    "sg:orig_category":"Massagen",
    "sg:phone":"+43 3682 23188",
    "sg:postcode":"8950",
    "sg:province":"Steiermark",
    "wof:name":"Kraxner Marion",
    "wof:placetype":"venue"
},
  "geometry": {"coordinates":[14.1108541489,47.5313873291],"type":"Point"}
}