{
  "type": "Feature",
  "properties": {
    "iso:country":"AT",
    "sg:address":"M\u00f6slestr 19",
    "sg:city":"Altach",
    "sg:orig_category":"Partyservice",
    "sg:phone":"+43 664 3423455",
    "sg:postcode":"6844",
    "sg:province":"Vorarlberg",
    "wof:name":"s'F\u00e4scht Sila",
    "wof:placetype":"venue"
},
  "geometry": {"coordinates":[9.6464767456,47.3481369019],"type":"Point"}
}