{
  "type": "Feature",
  "properties": {
    "iso:country":"AT",
    "sg:address":"Elisabethstr 15",
    "sg:city":"Wien",
    "sg:orig_category":"Fotografen",
    "sg:phone":"+43 1 5331467",
    "sg:postcode":"1010",
    "sg:province":"Wien",
    "wof:name":"Cerny Fotostudio - Studio C",
    "wof:placetype":"venue"
},
  "geometry": {"coordinates":[16.3632946014,48.2028961182],"type":"Point"}
}