{
  "type": "Feature",
  "properties": {
    "iso:country":"AT",
    "sg:address":"Bahnstrasse 37",
    "sg:city":"Pottendorf",
    "sg:classifiers":[
        {
            "category":"Building & Trades",
            "subcategory":"Pest Control",
            "type":"Services"
        }
    ],
    "sg:phone":"+43 2623 740100",
    "sg:postcode":"2486",
    "sg:province":"Nieder\u00f6sterreich",
    "sg:tags":[
        "automation"
    ],
    "sg:website":"berthold.at",
    "wof:name":"Rudolf Berthold Ges.m.b.H.",
    "wof:placetype":"venue"
},
  "geometry": {"coordinates":[16.3969039917,47.9064865112],"type":"Point"}
}