{
  "type": "Feature",
  "properties": {
    "addr:full":"Nr 4 St. Oswald Steiermark 8113",
    "addr:housenumber":"4",
    "addr:postcode":"8113",
    "addr:street":"Nr",
    "iso:country":"AT",
    "sg:address":"Nr 4",
    "sg:city":"St. Oswald",
    "sg:orig_category":"Installationsunternehmen",
    "sg:phone":"+43 3123 39985",
    "sg:postcode":"8113",
    "sg:province":"Steiermark",
    "wof:name":"Hammer Haustechnik GmbH",
    "wof:placetype":"venue"
},
  "geometry": {"coordinates":[15.2193155289,47.1025161743],"type":"Point"}
}