{
  "type": "Feature",
  "properties": {
    "addr:full":"Brunnenstrasse 31 Bad Gleichenberg Steiermark 8344",
    "addr:housenumber":"31",
    "addr:postcode":"8344",
    "addr:street":"Brunnenstrasse",
    "iso:country":"AT",
    "sg:address":"Brunnenstrasse 31",
    "sg:city":"Bad Gleichenberg",
    "sg:classifiers":[
        {
            "category":"Utilities",
            "subcategory":"Water",
            "type":"Services"
        }
    ],
    "sg:phone":"+43 3159 22940",
    "sg:postcode":"8344",
    "sg:province":"Steiermark",
    "sg:tags":[
        "waters",
        "natural",
        "mineral"
    ],
    "sg:website":"kurtherme.at",
    "wof:name":"Gleichenberger und Johannisbrunnen AG",
    "wof:placetype":"venue"
},
  "geometry": {"coordinates":[15.906206131,46.8702163696],"type":"Point"}
}