{
  "type": "Feature",
  "properties": {
    "addr:full":"Prinz- Eugen- Str. 8 Wien Wien 1040",
    "addr:housenumber":"8",
    "addr:postcode":"1040",
    "addr:street":"Prinz;Str.",
    "iso:country":"AT",
    "sg:address":"Prinz- Eugen- Str. 8",
    "sg:city":"Wien",
    "sg:classifiers":[
        {
            "category":"Banks & Credit Unions",
            "subcategory":"Financial Services",
            "type":"Services"
        }
    ],
    "sg:phone":"+43 4315 058000",
    "sg:postcode":"1040",
    "sg:province":"Wien",
    "sg:tags":[
        "banking",
        "finance",
        "insurance"
    ],
    "wof:name":"MFAG GMBH",
    "wof:placetype":"venue"
},
  "geometry": {"coordinates":[16.375667572,48.1965637207],"type":"Point"}
}