{
  "type": "Feature",
  "properties": {
    "addr:full":"Industriegebiet 12 Parndorf Burgenland 7111",
    "addr:housenumber":"12",
    "addr:postcode":"7111",
    "addr:street":"Industriegebiet",
    "iso:country":"AT",
    "sg:address":"Industriegebiet 12",
    "sg:city":"Parndorf",
    "sg:orig_category":"Textilwaren / Einzelhandel",
    "sg:phone":"+43 2166 20147",
    "sg:postcode":"7111",
    "sg:province":"Burgenland",
    "wof:name":"Miroglio Textil GesmbH",
    "wof:placetype":"venue"
},
  "geometry": {"coordinates":[16.8575897217,47.9981613159],"type":"Point"}
}