{
  "type": "Feature",
  "properties": {
    "addr:full":"Hauptstr 32 Jennersdorf Burgenland 8380",
    "addr:housenumber":"32",
    "addr:postcode":"8380",
    "addr:street":"Hauptstr",
    "iso:country":"AT",
    "sg:address":"Hauptstr 32",
    "sg:city":"Jennersdorf",
    "sg:orig_category":"Autohandel",
    "sg:phone":"+43 3329 45285",
    "sg:postcode":"8380",
    "sg:province":"Burgenland",
    "wof:name":"Schwarzer Auto- und Zweirad HandelsgesmbH",
    "wof:placetype":"venue"
},
  "geometry": {"coordinates":[16.1352539062,46.9370231628],"type":"Point"}
}