{
  "type": "Feature",
  "properties": {
    "iso:country":"AT",
    "sg:address":"B K\u00f6llersperger-Str 6",
    "sg:city":"Thaur",
    "sg:orig_category":"Eisenwaren",
    "sg:phone":"+43 5223 5050",
    "sg:postcode":"6065",
    "sg:province":"Tirol",
    "wof:name":"Schmidt's Josef Erben GesmbH & Co KG Niederlassung K\u00f6llensperger",
    "wof:placetype":"venue"
},
  "geometry": {"coordinates":[11.4727048874,47.2938156128],"type":"Point"}
}