{
  "type": "Feature",
  "properties": {
    "addr:full":"Auhofstr 17 Blindenmarkt Nieder\u00f6sterreich 3372",
    "addr:housenumber":"17",
    "addr:postcode":"3372",
    "addr:street":"Auhofstr",
    "iso:country":"AT",
    "sg:address":"Auhofstr 17",
    "sg:city":"Blindenmarkt",
    "sg:orig_category":"Feuerwehren",
    "sg:phone":"+43 7473 22220",
    "sg:postcode":"3372",
    "sg:province":"Nieder\u00f6sterreich",
    "wof:name":"Freiwillige Feuerwehr Blindenmarkt",
    "wof:placetype":"venue"
},
  "geometry": {"coordinates":[14.9874916077,48.1257781982],"type":"Point"}
}