{
  "type": "Feature",
  "properties": {
    "addr:full":"Steinbacherstrasse 1 W\u00f6rgl Tirol 6300",
    "addr:housenumber":"1",
    "addr:postcode":"6300",
    "addr:street":"Steinbacherstrasse;Tirol",
    "iso:country":"AT",
    "sg:address":"Steinbacherstrasse 1",
    "sg:city":"W\u00f6rgl",
    "sg:orig_category":"Internet, Alle Internetdienstleistungen",
    "sg:phone":"+43 5332 75464",
    "sg:postcode":"6300",
    "sg:province":"Tirol",
    "sg:website":"http://www.aweb.at",
    "wof:name":"AWeb",
    "wof:placetype":"venue"
},
  "geometry": {"coordinates":[12.064291954,47.4881134033],"type":"Point"}
}