{
  "type": "Feature",
  "properties": {
    "addr:full":"Freisinger Str 34 Obervellach K\u00e4rnten 9821",
    "addr:housenumber":"34",
    "addr:postcode":"9821",
    "addr:street":"Str;Kaernten",
    "iso:country":"AT",
    "sg:address":"Freisinger Str 34",
    "sg:city":"Obervellach",
    "sg:orig_category":"Fliesen U Platten",
    "sg:phone":"+43 4347 822026",
    "sg:postcode":"9821",
    "sg:province":"K\u00e4rnten",
    "wof:name":"Lader Lorenz",
    "wof:placetype":"venue"
},
  "geometry": {"coordinates":[13.1996669769,46.9353713989],"type":"Point"}
}