{
  "type": "Feature",
  "properties": {
    "iso:country":"AT",
    "sg:address":"Nr 43",
    "sg:city":"Allhartsberg",
    "sg:orig_category":"Pensionen / Privatzimmer",
    "sg:phone":"+43 7448 5282",
    "sg:postcode":"3365",
    "sg:province":"Nieder\u00f6sterreich",
    "wof:name":"Hora Christine und Franz",
    "wof:placetype":"venue"
},
  "geometry": {"coordinates":[14.7922697067,48.0268287659],"type":"Point"}
}