{
  "type": "Feature",
  "properties": {
    "addr:full":"Zwischenweger 10 Oberhofen im Inntal Tirol 6406",
    "addr:housenumber":"10",
    "addr:postcode":"6406",
    "addr:street":"Zwischenweger;Tirol",
    "iso:country":"AT",
    "sg:address":"Zwischenweger 10",
    "sg:city":"Oberhofen im Inntal",
    "sg:orig_category":"Spirituosen / Erzeugung U Gro\u00c3\u0178handel",
    "sg:phone":"+43 4352 6262733",
    "sg:postcode":"6406",
    "sg:province":"Tirol",
    "wof:name":"Brennerei Mader",
    "wof:placetype":"venue"
},
  "geometry": {"coordinates":[11.0987739563,47.3010063171],"type":"Point"}
}