{
  "type": "Feature",
  "properties": {
    "addr:full":"Kaiser Josef-Pl 6 Villach K\u00e4rnten 9500",
    "addr:housenumber":"6",
    "addr:postcode":"9500",
    "addr:street":"Josef-Pl;Kaernten",
    "iso:country":"AT",
    "sg:address":"Kaiser Josef-Pl 6",
    "sg:city":"Villach",
    "sg:orig_category":"Banken U Sparkassen",
    "sg:phone":"+43 4242 27377",
    "sg:postcode":"9500",
    "sg:province":"K\u00e4rnten",
    "wof:name":"Posojilnica Bank Zila rzzoj Kreditbank Gailtal regGenmbH",
    "wof:placetype":"venue"
},
  "geometry": {"coordinates":[13.8453130722,46.61510849],"type":"Point"}
}