{
  "type": "Feature",
  "properties": {
    "iso:country":"AT",
    "sg:address":"Bahnhofstrasse 23",
    "sg:city":"Rohrbach in Ober\u00f6sterreich",
    "sg:classifiers":[
        {
            "category":"Banks & Credit Unions",
            "subcategory":"Investment Brokerage",
            "type":"Services"
        }
    ],
    "sg:phone":"+43 7289 4279",
    "sg:postcode":"4150",
    "sg:province":"Ober\u00f6sterreich",
    "sg:tags":[
        "cast",
        "stone",
        "figurine"
    ],
    "wof:name":"G\u00fcnther Steidl",
    "wof:placetype":"venue"
},
  "geometry": {"coordinates":[13.9899520874,48.5770568848],"type":"Point"}
}