{
  "type": "Feature",
  "properties": {
    "addr:full":"Dornbirner Str 36 Lustenau Vorarlberg 6890",
    "addr:housenumber":"36",
    "addr:postcode":"6890",
    "addr:street":"Str",
    "iso:country":"AT",
    "sg:address":"Dornbirner Str 36",
    "sg:city":"Lustenau",
    "sg:orig_category":"Bierlokale-Pubs",
    "sg:phone":"+43 5577 8505713",
    "sg:postcode":"6890",
    "sg:province":"Vorarlberg",
    "wof:name":"Pub Blaue Sau",
    "wof:placetype":"venue"
},
  "geometry": {"coordinates":[9.6700820923,47.4176292419],"type":"Point"}
}