{
  "type": "Feature",
  "properties": {
    "addr:full":"Gewerbestrasse 1 Karlstetten Nieder\u00f6sterreich 3121",
    "addr:housenumber":"1",
    "addr:postcode":"3121",
    "addr:street":"Gewerbestrasse",
    "iso:country":"AT",
    "sg:address":"Gewerbestrasse 1",
    "sg:city":"Karlstetten",
    "sg:classifiers":[
        {
            "category":"Building & Trades",
            "subcategory":"Construction",
            "type":"Services"
        }
    ],
    "sg:phone":"+43 2741 83170",
    "sg:postcode":"3121",
    "sg:province":"Nieder\u00f6sterreich",
    "sg:tags":[
        "crane"
    ],
    "wof:name":"He\u00df GmbH",
    "wof:placetype":"venue"
},
  "geometry": {"coordinates":[15.5649213791,48.2545967102],"type":"Point"}
}