{
  "type": "Feature",
  "properties": {
    "addr:full":"Gemeindepl 1 Wei\u00dfkirchen in Steiermark Steiermark 8741",
    "addr:housenumber":"1",
    "addr:postcode":"8741",
    "addr:street":"Gemeindepl",
    "iso:country":"AT",
    "sg:address":"Gemeindepl 1",
    "sg:city":"Wei\u00dfkirchen in Steiermark",
    "sg:orig_category":"Polizei U Gendarmerie",
    "sg:phone":"+43 4359 1336306",
    "sg:postcode":"8741",
    "sg:province":"Steiermark",
    "wof:name":"Gendarmerie",
    "wof:placetype":"venue"
},
  "geometry": {"coordinates":[14.7388620377,47.1520881653],"type":"Point"}
}