{
  "type": "Feature",
  "properties": {
    "addr:full":"Jakob-Gapp-Str 10 Reutte Tirol 6600",
    "addr:housenumber":"10",
    "addr:postcode":"6600",
    "addr:street":"Jakob-Gapp-Str;Tirol",
    "iso:country":"AT",
    "sg:address":"Jakob-Gapp-Str 10",
    "sg:city":"Reutte",
    "sg:orig_category":"Steuerberatung",
    "sg:phone":"+43 4356 7269660",
    "sg:postcode":"6600",
    "sg:province":"Tirol",
    "sg:website":"abelshauser-preindl.at",
    "wof:name":"Abelshauser & Preindl Steuerberatungs OEG",
    "wof:placetype":"venue"
},
  "geometry": {"coordinates":[10.7125177383,47.4824981689],"type":"Point"}
}