{
  "type": "Feature",
  "properties": {
    "addr:full":"Maximilianstr 2 Klagenfurt K\u00e4rnten 9020",
    "addr:housenumber":"2",
    "addr:postcode":"9020",
    "addr:street":"Maximilianstr;Kaernten",
    "iso:country":"AT",
    "sg:address":"Maximilianstr 2",
    "sg:city":"Klagenfurt",
    "sg:orig_category":"Personalbereitstellung",
    "sg:phone":"+43 463 242077",
    "sg:postcode":"9020",
    "sg:province":"K\u00e4rnten",
    "wof:name":"Kuchar Montagen I.S.P.",
    "wof:placetype":"venue"
},
  "geometry": {"coordinates":[14.2995100021,46.6142272949],"type":"Point"}
}