{
  "type": "Feature",
  "properties": {
    "addr:full":"Seilerst\u00e4tte 1 Steyregg Ober\u00f6sterreich 4221",
    "addr:housenumber":"1",
    "addr:postcode":"4221",
    "addr:street":"Seilerstaette",
    "iso:country":"AT",
    "sg:address":"Seilerst\u00e4tte 1",
    "sg:city":"Steyregg",
    "sg:orig_category":"Bauunternehmen",
    "sg:phone":"+43 732 6400290",
    "sg:postcode":"4221",
    "sg:province":"Ober\u00f6sterreich",
    "wof:name":"Lackinger Hans GesmbH & Co KG",
    "wof:placetype":"venue"
},
  "geometry": {"coordinates":[14.3735351562,48.2844543457],"type":"Point"}
}