{
  "type": "Feature",
  "properties": {
    "addr:full":"Dreyhausenstr 14 Wien Wien 1140",
    "addr:housenumber":"14",
    "addr:postcode":"1140",
    "addr:street":"Dreyhausenstr",
    "iso:country":"AT",
    "sg:address":"Dreyhausenstr 14",
    "sg:city":"Wien",
    "sg:orig_category":"Baumeister",
    "sg:phone":"+43 1 9905463",
    "sg:postcode":"1140",
    "sg:province":"Wien",
    "wof:name":"Drim-Haus Bau GmbH",
    "wof:placetype":"venue"
},
  "geometry": {"coordinates":[16.3032741547,48.1975440979],"type":"Point"}
}