{
  "type": "Feature",
  "properties": {
    "addr:full":"Unterschildbach 12 Bischofstetten Nieder\u00f6sterreich 3232",
    "addr:housenumber":"12",
    "addr:postcode":"3232",
    "addr:street":"Unterschildbach;Niederoesterreich",
    "iso:country":"AT",
    "sg:address":"Unterschildbach 12",
    "sg:city":"Bischofstetten",
    "sg:classifiers":[
        {
            "category":"Military Area",
            "subcategory":"Air Force Base",
            "type":"Public Place"
        }
    ],
    "sg:phone":"+43 2748 82930",
    "sg:postcode":"3232",
    "sg:province":"Nieder\u00f6sterreich",
    "sg:tags":[
        "window",
        "skylight",
        "dormer"
    ],
    "sg:website":"hager-holzbau.at",
    "wof:name":"Florian Hager Ges.m.b.H.",
    "wof:placetype":"venue"
},
  "geometry": {"coordinates":[15.4520940781,48.1231613159],"type":"Point"}
}