{
  "type": "Feature",
  "properties": {
    "addr:full":"Wei\u00dfenwolffstr 14 Steyregg Ober\u00f6sterreich 4221",
    "addr:housenumber":"14",
    "addr:postcode":"4221",
    "addr:street":"Weissenwolffstr",
    "iso:country":"AT",
    "sg:address":"Wei\u00dfenwolffstr 14",
    "sg:city":"Steyregg",
    "sg:orig_category":"Lichtschranken",
    "sg:phone":"+43 732 640591",
    "sg:postcode":"4221",
    "sg:province":"Ober\u00f6sterreich",
    "wof:name":"Sitronic Sicherheit und Scanner Technik GesmbH",
    "wof:placetype":"venue"
},
  "geometry": {"coordinates":[14.3730096817,48.2857704163],"type":"Point"}
}