{
  "type": "Feature",
  "properties": {
    "addr:full":"Waldweg 2 Altm\u00fcnster Ober\u00f6sterreich 4813",
    "addr:housenumber":"2",
    "addr:postcode":"4813",
    "addr:street":"Waldweg;Oberoesterreich",
    "iso:country":"AT",
    "sg:address":"Waldweg 2",
    "sg:city":"Altm\u00fcnster",
    "sg:orig_category":"Schneidereien",
    "sg:phone":"+43 761288653",
    "sg:postcode":"4813",
    "sg:province":"Ober\u00f6sterreich",
    "wof:name":"Leili Gertraud",
    "wof:placetype":"venue"
},
  "geometry": {"coordinates":[13.7544803619,47.8999061584],"type":"Point"}
}