{
  "type": "Feature",
  "properties": {
    "addr:full":"Bahnstr 53 Wallern im Burgenland Burgenland 7151",
    "addr:housenumber":"53",
    "addr:postcode":"7151",
    "addr:street":"Bahnstr",
    "iso:country":"AT",
    "sg:address":"Bahnstr 53",
    "sg:city":"Wallern im Burgenland",
    "sg:orig_category":"Lebensmittel / Einzelhandel",
    "sg:phone":"+43 4321 743303",
    "sg:postcode":"7151",
    "sg:province":"Burgenland",
    "wof:name":"Kastner EinzelhandelsgesmbH",
    "wof:placetype":"venue"
},
  "geometry": {"coordinates":[16.9335403442,47.7281799316],"type":"Point"}
}