{
  "type": "Feature",
  "properties": {
    "addr:full":"Atterseestr 87 Timelkam Ober\u00f6sterreich 4850",
    "addr:housenumber":"87",
    "addr:postcode":"4850",
    "addr:street":"Atterseestr",
    "iso:country":"AT",
    "sg:address":"Atterseestr 87",
    "sg:city":"Timelkam",
    "sg:orig_category":"Schlossereien",
    "sg:phone":"+43 767295400",
    "sg:postcode":"4850",
    "sg:province":"Ober\u00f6sterreich",
    "wof:name":"Schn\u00f6tzinger Walter",
    "wof:placetype":"venue"
},
  "geometry": {"coordinates":[13.6230602264,47.9995689392],"type":"Point"}
}