{
  "type": "Feature",
  "properties": {
    "addr:full":"Imming 16f Schlitters Tirol 6262",
    "addr:housenumber":"16f",
    "addr:postcode":"6262",
    "addr:street":"Imming;Tirol",
    "iso:country":"AT",
    "sg:address":"Imming 16f",
    "sg:city":"Schlitters",
    "sg:orig_category":"Holzgro\u00c3\u0178handel",
    "sg:phone":"+43 5288 72355",
    "sg:postcode":"6262",
    "sg:province":"Tirol",
    "wof:name":"Eberharter Josef",
    "wof:placetype":"venue"
},
  "geometry": {"coordinates":[11.8619804382,47.3725090027],"type":"Point"}
}