{
  "type": "Feature",
  "properties": {
    "addr:full":"Hauptstr 6 Neuberg an der M\u00fcrz Steiermark 8692",
    "addr:housenumber":"6;8692",
    "addr:street":"Hauptstr",
    "iso:country":"AT",
    "sg:address":"Hauptstr 6",
    "sg:city":"Neuberg an der M\u00fcrz",
    "sg:orig_category":"Polizei U Gendarmerie",
    "sg:phone":"+43 4359 1336255",
    "sg:postcode":"8692",
    "sg:province":"Steiermark",
    "wof:name":"Gendarmerie",
    "wof:placetype":"venue"
},
  "geometry": {"coordinates":[15.5755310059,47.6655349731],"type":"Point"}
}