{
  "type": "Feature",
  "properties": {
    "addr:full":"Haidlstr 14 Dr\u00f6sing Nieder\u00f6sterreich 2265",
    "addr:housenumber":"14",
    "addr:postcode":"2265",
    "addr:street":"Haidlstr;Niederoesterreich",
    "iso:country":"AT",
    "sg:address":"Haidlstr 14",
    "sg:city":"Dr\u00f6sing",
    "sg:orig_category":"Friseure U Frisiersalons",
    "sg:phone":"+43 4325 362214",
    "sg:postcode":"2265",
    "sg:province":"Nieder\u00f6sterreich",
    "wof:name":"Dersch Karin",
    "wof:placetype":"venue"
},
  "geometry": {"coordinates":[-93.41316223139999,30.6534614563],"type":"Point"}
}