{
  "type": "Feature",
  "properties": {
    "addr:full":"Dr.-C.-Pfeiffenberger-Str 16/1 Imst Tirol 6460",
    "addr:housenumber":"16 / 1",
    "addr:postcode":"6460",
    "addr:street":"Dr.-C.-Pfeiffenberger-Str;Tirol",
    "iso:country":"AT",
    "sg:address":"Dr.-C.-Pfeiffenberger-Str 16/1",
    "sg:city":"Imst",
    "sg:orig_category":"Transportbeton",
    "sg:phone":"+43 4354 1264431",
    "sg:postcode":"6460",
    "sg:province":"Tirol",
    "wof:name":"Thurner Ing Franz Bau GmbH & Co KG",
    "wof:placetype":"venue"
},
  "geometry": {"coordinates":[10.7384700775,47.2380142212],"type":"Point"}
}