{
  "type": "Feature",
  "properties": {
    "iso:country":"AT",
    "sg:address":"Nr 16",
    "sg:classifiers":[
        {
            "category":"Travel",
            "subcategory":"Hotels & Motels",
            "type":"Entertainment"
        }
    ],
    "sg:phone":"+43 4872 5507",
    "sg:postcode":"9953",
    "wof:name":"Haus Sportland",
    "wof:placetype":"venue"
},
  "geometry": {"coordinates":[12.573764801,46.9368247986],"type":"Point"}
}