{
  "type": "Feature",
  "properties": {
    "addr:full":"Reichsratsstr 3 Wien Wien 1010",
    "addr:housenumber":"3",
    "addr:postcode":"1010",
    "addr:street":"Reichsratsstr",
    "iso:country":"AT",
    "sg:address":"Reichsratsstr 3",
    "sg:city":"Wien",
    "sg:orig_category":"Handelsagenturen",
    "sg:phone":"+43 1 40531610",
    "sg:postcode":"1010",
    "sg:province":"Wien",
    "wof:name":"GBM Handels- und VertretungsGmbH",
    "wof:placetype":"venue"
},
  "geometry": {"coordinates":[16.3572006226,48.2078285217],"type":"Point"}
}