{
  "type": "Feature",
  "properties": {
    "addr:full":"Obergail 4 Liesing K\u00e4rnten 9653",
    "addr:housenumber":"4",
    "addr:postcode":"9653",
    "addr:street":"Obergail;Kaernten",
    "iso:country":"AT",
    "sg:address":"Obergail 4",
    "sg:city":"Liesing",
    "sg:classifiers":[
        {
            "category":"Government",
            "subcategory":"Customs House",
            "type":"Public Place"
        }
    ],
    "sg:phone":"+43 4716 431",
    "sg:postcode":"9653",
    "sg:province":"K\u00e4rnten",
    "sg:tags":[
        "generating",
        "electrical",
        "plant",
        "power"
    ],
    "wof:name":"Strieder Kleinkraftwerk KEG",
    "wof:placetype":"venue"
},
  "geometry": {"coordinates":[12.8082408905,46.694065094],"type":"Point"}
}