{
  "type": "Feature",
  "properties": {
    "iso:country":"AT",
    "sg:address":"Jubil\u00e4umsstr 43",
    "sg:city":"Gumpoldskirchen",
    "sg:orig_category":"Genossenschaften",
    "sg:phone":"+43 2252 62129",
    "sg:postcode":"2352",
    "sg:province":"Nieder\u00f6sterreich",
    "wof:name":"Gumpoldskirchner Winzergenossenschaft regGenmbH",
    "wof:placetype":"venue"
},
  "geometry": {"coordinates":[16.2815723419,48.0450134277],"type":"Point"}
}