{
  "type": "Feature",
  "properties": {
    "addr:full":"Neug 2 Aspang-Markt Nieder\u00f6sterreich 2870",
    "addr:housenumber":"2",
    "addr:postcode":"2870",
    "addr:street":"Neug;Niederoesterreich",
    "iso:country":"AT",
    "sg:address":"Neug 2",
    "sg:city":"Aspang-Markt",
    "sg:orig_category":"Volksschulen",
    "sg:phone":"+43 2642 52395",
    "sg:postcode":"2870",
    "sg:province":"Nieder\u00f6sterreich",
    "wof:name":"Volksschule",
    "wof:placetype":"venue"
},
  "geometry": {"coordinates":[16.090839386,47.554725647],"type":"Point"}
}