{
  "type": "Feature",
  "properties": {
    "addr:full":"Porzellang 24 Wien Wien 1090",
    "addr:housenumber":"24",
    "addr:postcode":"1090",
    "addr:street":"Porzellang",
    "iso:country":"AT",
    "sg:address":"Porzellang 24",
    "sg:city":"Wien",
    "sg:orig_category":"Juweliere, Gold- U Silberschmiede",
    "sg:phone":"+43 4313 196156",
    "sg:postcode":"1090",
    "sg:province":"Wien",
    "wof:name":"Kainz Johann Gold- u Silberschmiedemeister - Uhrmachermeister",
    "wof:placetype":"venue"
},
  "geometry": {"coordinates":[16.3608188629,48.2210273743],"type":"Point"}
}