{
  "type": "Feature",
  "properties": {
    "addr:full":"Marktstr 26 Brixlegg Tirol 6230",
    "addr:housenumber":"26",
    "addr:postcode":"6230",
    "addr:street":"Marktstr;Tirol",
    "iso:country":"AT",
    "sg:address":"Marktstr 26",
    "sg:city":"Brixlegg",
    "sg:orig_category":"Werbegrafik- U Grafik-Design",
    "sg:phone":"+43 5337 66345",
    "sg:postcode":"6230",
    "sg:province":"Tirol",
    "wof:name":"Copy Shop Mando",
    "wof:placetype":"venue"
},
  "geometry": {"coordinates":[11.8787994385,47.4305381775],"type":"Point"}
}