{
  "type": "Feature",
  "properties": {
    "addr:full":"Klagenfurter Strasse 98a St. Veit an der Glan K\u00e4rnten 9300",
    "addr:housenumber":"98a",
    "addr:postcode":"9300",
    "addr:street":"Klagenfurter Strasse",
    "iso:country":"AT",
    "sg:address":"Klagenfurter Strasse 98a",
    "sg:city":"St. Veit an der Glan",
    "sg:classifiers":[
        {
            "category":"Building & Trades",
            "subcategory":"Electrical",
            "type":"Services"
        }
    ],
    "sg:phone":"+43 664 5010286",
    "sg:postcode":"9300",
    "sg:province":"K\u00e4rnten",
    "sg:tags":[
        "plants",
        "plant",
        "industrial",
        "buildings",
        "construction"
    ],
    "wof:name":"Ing. Michael Begusch Maschinenbau",
    "wof:placetype":"venue"
},
  "geometry": {"coordinates":[14.3577518463,46.7791061401],"type":"Point"}
}