{
  "type": "Feature",
  "properties": {
    "addr:full":"Unteramt 223 Gresten Nieder\u00f6sterreich 3264",
    "addr:housenumber":"223",
    "addr:postcode":"3264",
    "addr:street":"Unteramt",
    "iso:country":"AT",
    "sg:address":"Unteramt 223",
    "sg:city":"Gresten",
    "sg:orig_category":"Waren Aller Art",
    "sg:phone":"+43 7487 21959",
    "sg:postcode":"3264",
    "sg:province":"Nieder\u00f6sterreich",
    "wof:name":"Loibl Karl - Naturbetten",
    "wof:placetype":"venue"
},
  "geometry": {"coordinates":[15.0137853622,47.9914665222],"type":"Point"}
}