{
  "type": "Feature",
  "properties": {
    "addr:full":"Rohrbach in Ober\u00f6sterreich Ober\u00f6sterreich 4150",
    "addr:postcode":"4150",
    "addr:street":"Oberoesterreich",
    "iso:country":"AT",
    "sg:city":"Rohrbach in Ober\u00f6sterreich",
    "sg:orig_category":"Feuerwehren",
    "sg:phone":"+43 7289 4985",
    "sg:postcode":"4150",
    "sg:province":"Ober\u00f6sterreich",
    "wof:name":"Freiwillige Feuerwehr Perwolfing",
    "wof:placetype":"venue"
},
  "geometry": {"coordinates":[13.987663269,48.6047172546],"type":"Point"}
}