{
  "type": "Feature",
  "properties": {
    "addr:full":"Handelskai 340 Wien Wien 1020",
    "addr:housenumber":"340",
    "addr:postcode":"1020",
    "addr:street":"Handelskai",
    "iso:country":"AT",
    "sg:address":"Handelskai 340",
    "sg:city":"Wien",
    "sg:orig_category":"Telekommunikation",
    "sg:phone":"+43 1 727140",
    "sg:postcode":"1020",
    "sg:province":"Wien",
    "wof:name":"MCI WorldCom Telecommunication Services Austria GesmbH",
    "wof:placetype":"venue"
},
  "geometry": {"coordinates":[16.428188324,48.2085647583],"type":"Point"}
}