{
  "type": "Feature",
  "properties": {
    "addr:full":"Wimmerg 13 Wien Wien 1050",
    "addr:housenumber":"13",
    "addr:postcode":"1050",
    "addr:street":"Wimmerg",
    "iso:country":"AT",
    "sg:address":"Wimmerg 13",
    "sg:city":"Wien",
    "sg:orig_category":"Elektroinstallationsunternehmen",
    "sg:phone":"+43 1 5456164",
    "sg:postcode":"1050",
    "sg:province":"Wien",
    "wof:name":"Maiwald Dipl-Ing Elektrotechnik GesmbH",
    "wof:placetype":"venue"
},
  "geometry": {"coordinates":[16.3586044312,48.1848487854],"type":"Point"}
}