{
  "type": "Feature",
  "properties": {
    "addr:full":"Radegunder Str 10 Andritz Steiermark 8045",
    "addr:housenumber":"10",
    "addr:postcode":"8045",
    "addr:street":"Str",
    "iso:country":"AT",
    "sg:address":"Radegunder Str 10",
    "sg:city":"Andritz",
    "sg:orig_category":"Friseure U Frisiersalons",
    "sg:phone":"+43 316 675052",
    "sg:postcode":"8045",
    "sg:province":"Steiermark",
    "wof:name":"Coiffeur Headline",
    "wof:placetype":"venue"
},
  "geometry": {"coordinates":[15.4262428284,47.103313446],"type":"Point"}
}