{
  "type": "Feature",
  "properties": {
    "addr:full":"Nr 13 Thernberg Nieder\u00f6sterreich 2832",
    "addr:postcode":"2832",
    "addr:street":"Nr 13 Thernberg",
    "iso:country":"AT",
    "sg:address":"Nr 13",
    "sg:city":"Thernberg",
    "sg:orig_category":"Elektroinstallationsunternehmen",
    "sg:phone":"+43 2629 2590",
    "sg:postcode":"2832",
    "sg:province":"Nieder\u00f6sterreich",
    "wof:name":"Schuch Wilhelm Ing",
    "wof:placetype":"venue"
},
  "geometry": {"coordinates":[16.1771736145,47.6614875793],"type":"Point"}
}