{
  "type": "Feature",
  "properties": {
    "iso:country":"AT",
    "sg:address":"Feldgasse 14 ",
    "sg:classifiers":[
        {
            "category":"Building & Trades",
            "subcategory":"Construction",
            "type":"Services"
        }
    ],
    "sg:phone":"+43 4331 62711110",
    "sg:postcode":"8022",
    "sg:tags":[
        "work",
        "public"
    ],
    "wof:name":"GRANIT BAUUNTERNEHMUNG GES.MBH",
    "wof:placetype":"venue"
},
  "geometry": {"coordinates":[15.4243011475,47.0542793274],"type":"Point"}
}