{
  "type": "Feature",
  "properties": {
    "addr:full":"Hauptstr 11 Bad Sch\u00f6nau Nieder\u00f6sterreich 2853",
    "addr:housenumber":"11",
    "addr:postcode":"2853",
    "addr:street":"Hauptstr",
    "iso:country":"AT",
    "sg:address":"Hauptstr 11",
    "sg:city":"Bad Sch\u00f6nau",
    "sg:orig_category":"Rettungsdienste",
    "sg:phone":"+43 2646 27129",
    "sg:postcode":"2853",
    "sg:province":"Nieder\u00f6sterreich",
    "wof:name":"\u00f6sterreichisches Rotes Kreuz",
    "wof:placetype":"venue"
},
  "geometry": {"coordinates":[-87.4919509888,33.9798126221],"type":"Point"}
}