{
  "type": "Feature",
  "properties": {
    "addr:full":"Hauptpl 4 Ferlach K\u00e4rnten 9170",
    "addr:housenumber":"4",
    "addr:postcode":"9170",
    "addr:street":"Hauptpl;Kaernten",
    "iso:country":"AT",
    "sg:address":"Hauptpl 4",
    "sg:city":"Ferlach",
    "sg:orig_category":"Tabaktrafiken",
    "sg:phone":"+43 4227 3633",
    "sg:postcode":"9170",
    "sg:province":"K\u00e4rnten",
    "wof:name":"Sterneck Ilse Maria",
    "wof:placetype":"venue"
},
  "geometry": {"coordinates":[14.3009748459,46.5263519287],"type":"Point"}
}