{
  "type": "Feature",
  "properties": {
    "addr:full":"Liechtensteinstr 69 Wien Wien 1090",
    "addr:housenumber":"69",
    "addr:postcode":"1090",
    "addr:street":"Liechtensteinstr",
    "iso:country":"AT",
    "sg:address":"Liechtensteinstr 69",
    "sg:city":"Wien",
    "sg:orig_category":"Abflussdienste",
    "sg:phone":"+43 4313 107676",
    "sg:postcode":"1090",
    "sg:province":"Wien",
    "sg:website":"rohr-rettung.at",
    "wof:name":"Rohr-Rettung Scheed GmbH",
    "wof:placetype":"venue"
},
  "geometry": {"coordinates":[16.3571281433,48.2243309021],"type":"Point"}
}