{
  "type": "Feature",
  "properties": {
    "iso:country":"AT",
    "sg:address":"Moosheim 113",
    "sg:city":"Gr\u00f6bming",
    "sg:orig_category":"Flugschulen",
    "sg:phone":"+43 3685 223330",
    "sg:postcode":"8962",
    "sg:province":"Steiermark",
    "sg:website":"skyclub-austria.com",
    "wof:name":"Sky Club Austria",
    "wof:placetype":"venue"
},
  "geometry": {"coordinates":[13.8970880508,47.4261856079],"type":"Point"}
}