{
  "type": "Feature",
  "properties": {
    "iso:country":"AT",
    "sg:address":"Hauptstr 27a",
    "sg:city":"Rosental an der Kainach",
    "sg:orig_category":"Werbegrafik- U Grafik-Design",
    "sg:phone":"+43 4331 4222931",
    "sg:postcode":"8582",
    "sg:province":"Steiermark",
    "wof:name":"Butterfly Design",
    "wof:placetype":"venue"
},
  "geometry": {"coordinates":[15.1233062744,47.0527267456],"type":"Point"}
}