{
  "type": "Feature",
  "properties": {
    "iso:country":"AT",
    "sg:address":"Vorderstadt 7",
    "sg:city":"Kitzb\u00fchel",
    "sg:orig_category":"Psychotherapie",
    "sg:phone":"+43 4353 5667428",
    "sg:postcode":"6370",
    "sg:province":"Tirol",
    "wof:name":"Prisma Psychotherapeutische Praxis Dr Karl \u00dcbelh\u00f6r",
    "wof:placetype":"venue"
},
  "geometry": {"coordinates":[12.3908166885,47.4471092224],"type":"Point"}
}