{
  "type": "Feature",
  "properties": {
    "addr:full":"Buchauer Str. 103 St. Gallen Steiermark 8933",
    "addr:housenumber":"103",
    "addr:postcode":"8933",
    "addr:street":"Str.",
    "iso:country":"AT",
    "sg:address":"Buchauer Str. 103",
    "sg:city":"St. Gallen",
    "sg:classifiers":[
        {
            "category":"Professional",
            "subcategory":"Engineering",
            "type":"Services"
        }
    ],
    "sg:phone":"+43 4336 326810",
    "sg:postcode":"8933",
    "sg:province":"Steiermark",
    "sg:tags":[
        "machine",
        "-",
        "mechanical"
    ],
    "wof:name":"ALPEN-MAY-KESTAG GES.MBH",
    "wof:placetype":"venue"
},
  "geometry": {"coordinates":[14.6177816391,47.6849517822],"type":"Point"}
}