{
  "type": "Feature",
  "properties": {
    "addr:full":"Nr 226 Turnau Steiermark 8625",
    "addr:postcode":"8625",
    "addr:street":"Nr 226",
    "iso:country":"AT",
    "sg:address":"Nr 226",
    "sg:city":"Turnau",
    "sg:orig_category":"Werbeagenturen",
    "sg:phone":"+43 676 5045433",
    "sg:postcode":"8625",
    "sg:province":"Steiermark",
    "wof:name":"Jaksch Michael",
    "wof:placetype":"venue"
},
  "geometry": {"coordinates":[15.3370742798,47.5582237244],"type":"Point"}
}