{
  "type": "Feature",
  "properties": {
    "iso:country":"AT",
    "sg:address":"Hauptstr 9",
    "sg:city":"Warth",
    "sg:orig_category":"Psychologen",
    "sg:phone":"+43 4326 295008",
    "sg:postcode":"2831",
    "sg:province":"Nieder\u00f6sterreich",
    "wof:name":"Kn\u00f6bel Johann Dr",
    "wof:placetype":"venue"
},
  "geometry": {"coordinates":[-96.9972000122,37.2408103943],"type":"Point"}
}