{
  "type": "Feature",
  "properties": {
    "iso:country":"AT",
    "sg:address":"Industriestr 3",
    "sg:city":"St. Johann im Pongau",
    "sg:orig_category":"Biologische Produkte",
    "sg:phone":"+43 6412 20134",
    "sg:postcode":"5600",
    "sg:province":"Salzburg",
    "wof:name":"Naturladen Schwab KEG",
    "wof:placetype":"venue"
},
  "geometry": {"coordinates":[13.1965141296,47.3508453369],"type":"Point"}
}