{
  "type": "Feature",
  "properties": {
    "addr:full":"Teinfaltstr. 8 Wien Wien 1010",
    "addr:housenumber":"8",
    "addr:postcode":"1010",
    "addr:street":"Teinfaltstr.",
    "iso:country":"AT",
    "sg:address":"Teinfaltstr. 8",
    "sg:city":"Wien",
    "sg:classifiers":[
        {
            "category":"Real Estate",
            "subcategory":"Architect",
            "type":"Services"
        }
    ],
    "sg:phone":"+43 4315 352531",
    "sg:postcode":"1010",
    "sg:province":"Wien",
    "sg:tags":[
        "textile",
        "clothing"
    ],
    "wof:name":"INTER CORUS MODE-HANDELSGES. MBH",
    "wof:placetype":"venue"
},
  "geometry": {"coordinates":[16.3624324799,48.2114868164],"type":"Point"}
}