{
  "type": "Feature",
  "properties": {
    "addr:full":"Bozner Str 2 St. Johann in Tirol Tirol 6380",
    "addr:housenumber":"2",
    "addr:postcode":"6380",
    "addr:street":"Bozner Str;Tirol",
    "iso:country":"AT",
    "sg:address":"Bozner Str 2",
    "sg:city":"St. Johann in Tirol",
    "sg:orig_category":"Lebensmittel / Einzelhandel",
    "sg:phone":"+43 5352 634520",
    "sg:postcode":"6380",
    "sg:province":"Tirol",
    "wof:name":"SPAR \u00f6sterreichische Warenhandels-AG",
    "wof:placetype":"venue"
},
  "geometry": {"coordinates":[12.4308633804,47.5221977234],"type":"Point"}
}