{
  "type": "Feature",
  "properties": {
    "iso:country":"AT",
    "sg:address":"Ferdinand-Wedenig-Str 67",
    "sg:city":"Klagenfurt-Viktring",
    "sg:orig_category":"Pensionen / Privatzimmer",
    "sg:phone":"+43 4346 3281632",
    "sg:postcode":"9073",
    "sg:province":"K\u00e4rnten",
    "wof:name":"Pack Regina u Walter",
    "wof:placetype":"venue"
},
  "geometry": {"coordinates":[14.2682952881,46.5998497009],"type":"Point"}
}