{
  "type": "Feature",
  "properties": {
    "addr:full":"Jahrsdorf 10 St. Peter am Hart Ober\u00f6sterreich 4963",
    "addr:housenumber":"10",
    "addr:postcode":"4963",
    "addr:street":"Jahrsdorf",
    "iso:country":"AT",
    "sg:address":"Jahrsdorf 10",
    "sg:city":"St. Peter am Hart",
    "sg:orig_category":"Autohandel",
    "sg:phone":"+43 4377 2262475",
    "sg:postcode":"4963",
    "sg:province":"Ober\u00f6sterreich",
    "wof:name":"Moser Max GesmbH",
    "wof:placetype":"venue"
},
  "geometry": {"coordinates":[13.0792827606,48.2532730103],"type":"Point"}
}