{
  "type": "Feature",
  "properties": {
    "addr:full":"Wiedner Hauptstr 84-86 Wien Wien 1050",
    "addr:postcode":"84-86;1050",
    "addr:street":"Hauptstr",
    "iso:country":"AT",
    "sg:address":"Wiedner Hauptstr 84-86",
    "sg:city":"Wien",
    "sg:orig_category":"Banken U Sparkassen",
    "sg:phone":"+43 4315 444967",
    "sg:postcode":"1050",
    "sg:province":"Wien",
    "wof:name":"Volksbank Wien AG",
    "wof:placetype":"venue"
},
  "geometry": {"coordinates":[16.3641052246,48.1880645752],"type":"Point"}
}