{
  "type": "Feature",
  "properties": {
    "addr:full":"Bahnhofstr 79 Zeltweg Steiermark 8740",
    "addr:housenumber":"79",
    "addr:postcode":"8740",
    "addr:street":"Bahnhofstr",
    "iso:country":"AT",
    "sg:address":"Bahnhofstr 79",
    "sg:city":"Zeltweg",
    "sg:orig_category":"Non-Classified Establishments",
    "sg:phone":"+43 5 91336307",
    "sg:postcode":"8740",
    "sg:province":"Steiermark",
    "wof:name":"Gendarmerie",
    "wof:placetype":"venue"
},
  "geometry": {"coordinates":[14.7477426529,47.1892166138],"type":"Point"}
}