{
  "type": "Feature",
  "properties": {
    "iso:country":"AT",
    "sg:address":"Wiener Str 20",
    "sg:city":"Wiener Neudorf",
    "sg:orig_category":"Tabaktrafiken",
    "sg:phone":"+43 2236 63380",
    "sg:postcode":"2351",
    "sg:province":"Nieder\u00f6sterreich",
    "wof:name":"K\u00f6hler Ilse",
    "wof:placetype":"venue"
},
  "geometry": {"coordinates":[16.3140296936,48.0877456665],"type":"Point"}
}