{
  "type": "Feature",
  "properties": {
    "addr:full":"Moos 10  Grieskirchen Ober\u00f6sterreich 4710",
    "addr:housenumber":"10",
    "addr:postcode":"4710",
    "addr:street":"Moos",
    "iso:country":"AT",
    "sg:address":"Moos 10 ",
    "sg:city":"Grieskirchen",
    "sg:classifiers":[
        {
            "category":"Shopping",
            "subcategory":"Clothing, Apparel, & Fashions",
            "type":"Retail Goods"
        }
    ],
    "sg:phone":"+43 4372 4868171",
    "sg:postcode":"4710",
    "sg:province":"Ober\u00f6sterreich",
    "sg:tags":[
        "clothes"
    ],
    "wof:name":"SICKER KLEIDUNG JOHANN SICKINGER",
    "wof:placetype":"venue"
},
  "geometry": {"coordinates":[13.8262605667,48.2323570251],"type":"Point"}
}