{
  "type": "Feature",
  "properties": {
    "addr:full":"Schmiedg 30 Freistadt Ober\u00f6sterreich 4240",
    "addr:housenumber":"30",
    "addr:postcode":"4240",
    "addr:street":"Schmiedg",
    "iso:country":"AT",
    "sg:address":"Schmiedg 30",
    "sg:city":"Freistadt",
    "sg:orig_category":"Tischlereien",
    "sg:phone":"+43 7942 72355",
    "sg:postcode":"4240",
    "sg:province":"Ober\u00f6sterreich",
    "wof:name":"Freudenthaler Karl",
    "wof:placetype":"venue"
},
  "geometry": {"coordinates":[14.5074558258,48.5150566101],"type":"Point"}
}