{
  "type": "Feature",
  "properties": {
    "addr:full":"Rauhholzstr 16c Hard Vorarlberg 6971",
    "addr:housenumber":"16c",
    "addr:postcode":"6971",
    "addr:street":"Rauhholzstr",
    "iso:country":"AT",
    "sg:address":"Rauhholzstr 16c",
    "sg:city":"Hard",
    "sg:orig_category":"Drucklufttechnik",
    "sg:phone":"+43 5574 70314",
    "sg:postcode":"6971",
    "sg:province":"Vorarlberg",
    "wof:name":"AGRE - Anton Hinderegger",
    "wof:placetype":"venue"
},
  "geometry": {"coordinates":[9.7007236481,47.4881782532],"type":"Point"}
}