{
  "type": "Feature",
  "properties": {
    "addr:full":"Aslang 59 Wien Wien 1190",
    "addr:housenumber":"59",
    "addr:postcode":"1190",
    "addr:street":"Aslang",
    "iso:country":"AT",
    "sg:address":"Aslang 59",
    "sg:city":"Wien",
    "sg:orig_category":"Spielwaren U Spiele",
    "sg:phone":"+43 4319 426403",
    "sg:postcode":"1190",
    "sg:province":"Wien",
    "wof:name":"Teddy & Co",
    "wof:placetype":"venue"
},
  "geometry": {"coordinates":[16.3361358643,48.2529983521],"type":"Point"}
}