{
  "type": "Feature",
  "properties": {
    "iso:country":"AT",
    "sg:address":"Raiffeisenstr 28",
    "sg:city":"St. Michael in Obersteiermark",
    "sg:orig_category":"Tabaktrafiken",
    "sg:phone":"+43 4338 433286",
    "sg:postcode":"8770",
    "sg:province":"Steiermark",
    "wof:name":"Wagner Hans Michael",
    "wof:placetype":"venue"
},
  "geometry": {"coordinates":[15.0196866989,47.3365249634],"type":"Point"}
}