{
  "type": "Feature",
  "properties": {
    "addr:full":"Arnikaweg 124/66 Wien Wien 1220",
    "addr:housenumber":"124 / 66",
    "addr:postcode":"1220",
    "addr:street":"Arnikaweg",
    "iso:country":"AT",
    "sg:address":"Arnikaweg 124/66",
    "sg:city":"Wien",
    "sg:orig_category":"Filmproduktionen",
    "sg:phone":"+43 4367 64806703",
    "sg:postcode":"1220",
    "sg:province":"Wien",
    "wof:name":"Mo-Mo Productions",
    "wof:placetype":"venue"
},
  "geometry": {"coordinates":[16.480096817,48.2511177063],"type":"Point"}
}