{
  "type": "Feature",
  "properties": {
    "addr:full":"Hauptstr 4/5 B\u00fcrs Vorarlberg 6706",
    "addr:housenumber":"4 / 5",
    "addr:postcode":"6706",
    "addr:street":"Hauptstr;Buers Vorarlberg",
    "iso:country":"AT",
    "sg:address":"Hauptstr 4/5",
    "sg:city":"B\u00fcrs",
    "sg:orig_category":"Weiterbildungsinstitute M Allg U Berufl Bildungsangebot",
    "sg:phone":"+43 4355 52638310",
    "sg:postcode":"6706",
    "sg:province":"Vorarlberg",
    "wof:name":"Institut f Gesundheits- u Krankenpflege",
    "wof:placetype":"venue"
},
  "geometry": {"coordinates":[9.8089761734,47.1518325806],"type":"Point"}
}