{
  "type": "Feature",
  "properties": {
    "addr:full":"Nr 1 Seitenstetten Nieder\u00f6sterreich 3353",
    "addr:postcode":"3353",
    "addr:street":"Nr;Niederoesterreich",
    "iso:country":"AT",
    "sg:address":"Nr 1",
    "sg:city":"Seitenstetten",
    "sg:orig_category":"Non-Classified Establishments",
    "sg:phone":"+43 7476 8201",
    "sg:postcode":"3353",
    "sg:province":"Nieder\u00f6sterreich",
    "wof:name":"Pfarramt",
    "wof:placetype":"venue"
},
  "geometry": {"coordinates":[14.7085561752,48.0289573669],"type":"Point"}
}