{
  "type": "Feature",
  "properties": {
    "addr:full":"Nr 14 Obergurgl Tirol 6456",
    "addr:postcode":"6456",
    "addr:street":"Nr;Tirol",
    "iso:country":"AT",
    "sg:address":"Nr 14",
    "sg:city":"Obergurgl",
    "sg:orig_category":"Appartements / Ferienwohnungen",
    "sg:phone":"+43 5256 65240",
    "sg:postcode":"6456",
    "sg:province":"Tirol",
    "wof:name":"Appartementhaus Alt Poschach",
    "wof:placetype":"venue"
},
  "geometry": {"coordinates":[11.0263767242,46.8701171875],"type":"Point"}
}