{
  "type": "Feature",
  "properties": {
    "iso:country":"AT",
    "sg:address":"Freiw Sch\u00fctzen-Str 6",
    "sg:city":"Gmunden",
    "sg:orig_category":"Ultraschalltechnik",
    "sg:phone":"+43 761262034",
    "sg:postcode":"4810",
    "sg:province":"Ober\u00f6sterreich",
    "wof:name":"KLU - Ultraschalltechnik",
    "wof:placetype":"venue"
},
  "geometry": {"coordinates":[13.7981462479,47.918598175],"type":"Point"}
}