{
  "type": "Feature",
  "properties": {
    "addr:full":"Hauptplatz 21 Kittsee Burgenland 2421",
    "addr:housenumber":"21",
    "addr:postcode":"2421",
    "addr:street":"Hauptplatz",
    "iso:country":"AT",
    "sg:address":"Hauptplatz 21",
    "sg:city":"Kittsee",
    "sg:classifiers":[
        {
            "category":"Building & Trades",
            "subcategory":"Electrical",
            "type":"Services"
        }
    ],
    "sg:phone":"+43 2143 2269",
    "sg:postcode":"2421",
    "sg:province":"Burgenland",
    "sg:tags":[
        "installation"
    ],
    "sg:website":"borbely.at",
    "wof:name":"Johann Borbely",
    "wof:placetype":"venue"
},
  "geometry": {"coordinates":[17.0665855408,48.0907669067],"type":"Point"}
}