{
  "type": "Feature",
  "properties": {
    "iso:country":"AT",
    "sg:address":"Hollabrunner Str 12",
    "sg:city":"Ziersdorf",
    "sg:orig_category":"Hauptschulen",
    "sg:phone":"+43 2956 2258",
    "sg:postcode":"3710",
    "sg:province":"Nieder\u00f6sterreich",
    "wof:name":"Hauptschule",
    "wof:placetype":"venue"
},
  "geometry": {"coordinates":[15.9296302795,48.527973175],"type":"Point"}
}