{
  "type": "Feature",
  "properties": {
    "addr:full":"Agsdorfer Str 90 St. Andr\u00e4 K\u00e4rnten 9433",
    "addr:housenumber":"90",
    "addr:postcode":"9433",
    "addr:street":"Str;Kaernten",
    "iso:country":"AT",
    "sg:address":"Agsdorfer Str 90",
    "sg:city":"St. Andr\u00e4",
    "sg:orig_category":"Friseure U Frisiersalons",
    "sg:phone":"+43 4343 582530",
    "sg:postcode":"9433",
    "sg:province":"K\u00e4rnten",
    "wof:name":"Pongratz Hildegard - Dein Friseur",
    "wof:placetype":"venue"
},
  "geometry": {"coordinates":[14.821849823,46.7685317993],"type":"Point"}
}