{
  "type": "Feature",
  "properties": {
    "addr:full":"Paulanerg 13 Wien Wien 1040",
    "addr:housenumber":"13",
    "addr:postcode":"1040",
    "addr:street":"Paulanerg",
    "iso:country":"AT",
    "sg:address":"Paulanerg 13",
    "sg:city":"Wien",
    "sg:orig_category":"Lebensmittel / Einzelhandel",
    "sg:phone":"+43 4315 810410",
    "sg:postcode":"1040",
    "sg:province":"Wien",
    "wof:name":"Hofer KG",
    "wof:placetype":"venue"
},
  "geometry": {"coordinates":[16.3656635284,48.1959609985],"type":"Point"}
}