{
  "type": "Feature",
  "properties": {
    "addr:full":"Nr 1 St. Anton am Arlberg Tirol 6580",
    "addr:housenumber":"1",
    "addr:postcode":"6580",
    "addr:street":"Nr;Tirol",
    "iso:country":"AT",
    "sg:address":"Nr 1",
    "sg:city":"St. Anton am Arlberg",
    "sg:orig_category":"Pensionen / Privatzimmer",
    "sg:phone":"+43 4354 462832",
    "sg:postcode":"6580",
    "sg:province":"Tirol",
    "wof:name":"Zoller G\u00e4stehaus - Obermaier Susanne",
    "wof:placetype":"venue"
},
  "geometry": {"coordinates":[10.2640428543,47.127532959],"type":"Point"}
}