{
  "type": "Feature",
  "properties": {
    "addr:full":"Lagerstrasse 36 Langenzersdorf Nieder\u00f6sterreich 2103",
    "addr:housenumber":"36",
    "addr:postcode":"2103",
    "addr:street":"Lagerstrasse",
    "iso:country":"AT",
    "sg:address":"Lagerstrasse 36",
    "sg:city":"Langenzersdorf",
    "sg:classifiers":[
        {
            "category":"Exhibition Hall",
            "type":"Public Place"
        }
    ],
    "sg:phone":"+43 2244 27870",
    "sg:postcode":"2103",
    "sg:province":"Nieder\u00f6sterreich",
    "sg:tags":[
        "conversion"
    ],
    "wof:name":"Mayer & N\u00f6hrer Ges.m.b.H.",
    "wof:placetype":"venue"
},
  "geometry": {"coordinates":[16.3669986725,48.2826576233],"type":"Point"}
}