{
  "type": "Feature",
  "properties": {
    "iso:country":"AT",
    "sg:address":"Pfarrgasse 8",
    "sg:city":"Imst",
    "sg:classifiers":[
        {
            "category":"Professional",
            "subcategory":"Art Services",
            "type":"Services"
        }
    ],
    "sg:phone":"+43 5412 64317",
    "sg:postcode":"6460",
    "sg:province":"Tirol",
    "sg:tags":[
        "design"
    ],
    "wof:name":"Feuerkunst Inh. Gebhard Schatz",
    "wof:placetype":"venue"
},
  "geometry": {"coordinates":[10.7390098572,47.2427482605],"type":"Point"}
}