{
  "type": "Feature",
  "properties": {
    "addr:full":"Grillweg 15 Neuhart Steiermark 8053",
    "addr:housenumber":"15",
    "addr:postcode":"8053",
    "addr:street":"Grillweg",
    "iso:country":"AT",
    "sg:address":"Grillweg 15",
    "sg:city":"Neuhart",
    "sg:orig_category":"Offsetdruckereien",
    "sg:phone":"+43 4331 625000",
    "sg:postcode":"8053",
    "sg:province":"Steiermark",
    "sg:website":"wallgroup.com",
    "wof:name":"Rotoform Druckformen GesmbH",
    "wof:placetype":"venue"
},
  "geometry": {"coordinates":[15.4069709778,47.0400161743],"type":"Point"}
}