{
  "type": "Feature",
  "properties": {
    "addr:full":"Maria-Theresien-Str 5 Lustenau Vorarlberg 6890",
    "addr:housenumber":"5",
    "addr:postcode":"6890",
    "addr:street":"Maria-Theresien-Str",
    "iso:country":"AT",
    "sg:address":"Maria-Theresien-Str 5",
    "sg:city":"Lustenau",
    "sg:orig_category":"Damenmoden",
    "sg:phone":"+43 4355 7783653",
    "sg:postcode":"6890",
    "sg:province":"Vorarlberg",
    "wof:name":"Sperger Rudolf GmbH & Co KG",
    "wof:placetype":"venue"
},
  "geometry": {"coordinates":[9.6586904526,47.426940918],"type":"Point"}
}