{
  "type": "Feature",
  "properties": {
    "iso:country":"AT",
    "sg:address":"Industriestr 10",
    "sg:city":"Gerasdorf",
    "sg:orig_category":"Immobilienverwaltungen",
    "sg:phone":"+43 2246 215016",
    "sg:postcode":"2201",
    "sg:province":"Nieder\u00f6sterreich",
    "wof:name":"Zgonc Immobilien GmbH",
    "wof:placetype":"venue"
},
  "geometry": {"coordinates":[16.4572868347,48.3339576721],"type":"Point"}
}