{
  "type": "Feature",
  "properties": {
    "addr:full":"Oberau 375 Wildsch\u00f6nau-Oberau Tirol 6311",
    "addr:housenumber":"375",
    "addr:postcode":"6311",
    "addr:street":"Oberau;Tirol",
    "iso:country":"AT",
    "sg:address":"Oberau 375",
    "sg:city":"Wildsch\u00f6nau-Oberau",
    "sg:orig_category":"Appartements / Ferienwohnungen",
    "sg:phone":"+43 4353 392192",
    "sg:postcode":"6311",
    "sg:province":"Tirol",
    "wof:name":"Ferienwohnung Fuchs",
    "wof:placetype":"venue"
},
  "geometry": {"coordinates":[12.049654007,47.4430465698],"type":"Point"}
}