{
  "type": "Feature",
  "properties": {
    "iso:country":"AT",
    "sg:address":"Quellenstr 103",
    "sg:city":"Wien",
    "sg:orig_category":"Friseure U Frisiersalons",
    "sg:phone":"+43 1 6004026",
    "sg:postcode":"1100",
    "sg:province":"Wien",
    "wof:name":"C'HAARISMA",
    "wof:placetype":"venue"
},
  "geometry": {"coordinates":[16.3795108795,48.1750717163],"type":"Point"}
}