{
  "type": "Feature",
  "properties": {
    "addr:full":"Johann-Tagwerker-Strasse 8 Gmunden Ober\u00f6sterreich 4810",
    "addr:housenumber":"8",
    "addr:postcode":"4810",
    "addr:street":"Johann-Tagwerker-Strasse;Oberoesterreich",
    "iso:country":"AT",
    "sg:address":"Johann-Tagwerker-Strasse 8",
    "sg:city":"Gmunden",
    "sg:classifiers":[
        {
            "category":"Wholesale",
            "subcategory":"Fruits & Vegetables",
            "type":"Manufacturing & Wholesale Goods"
        }
    ],
    "sg:phone":"+43 761271169",
    "sg:postcode":"4810",
    "sg:province":"Ober\u00f6sterreich",
    "sg:tags":[
        "product",
        "cereal"
    ],
    "wof:name":"Ing. Gerhard Pesendorfer Vollwertern\u00e4hrung",
    "wof:placetype":"venue"
},
  "geometry": {"coordinates":[13.7973470688,47.9207954407],"type":"Point"}
}