{
  "type": "Feature",
  "properties": {
    "addr:full":"Kolpingstr 7 Poysdorf Nieder\u00f6sterreich 2170",
    "addr:housenumber":"7",
    "addr:postcode":"2170",
    "addr:street":"Kolpingstr",
    "iso:country":"AT",
    "sg:address":"Kolpingstr 7",
    "sg:city":"Poysdorf",
    "sg:orig_category":"Tourismusinformation U -Organisationen",
    "sg:phone":"+43 2552 3515",
    "sg:postcode":"2170",
    "sg:province":"Nieder\u00f6sterreich",
    "wof:name":"Weinviertel Tourismus GmbH",
    "wof:placetype":"venue"
},
  "geometry": {"coordinates":[16.6308097839,48.6715698242],"type":"Point"}
}