{
  "type": "Feature",
  "properties": {
    "addr:full":"Mariahilfer Str. 26-30  Wien Wien 1070",
    "addr:postcode":"26-30;1070",
    "addr:street":"Str.",
    "iso:country":"AT",
    "sg:address":"Mariahilfer Str. 26-30 ",
    "sg:city":"Wien",
    "sg:classifiers":[
        {
            "category":"Shopping",
            "subcategory":"Clothing, Apparel, & Fashions",
            "type":"Retail Goods"
        }
    ],
    "sg:phone":"+43 4315 25610",
    "sg:postcode":"1070",
    "sg:province":"Wien",
    "sg:tags":[
        "clothes"
    ],
    "wof:name":"PEEK & CLOPPENBURG GMBH & CO KG",
    "wof:placetype":"venue"
},
  "geometry": {"coordinates":[16.3556308746,48.2004051208],"type":"Point"}
}