{
  "type": "Feature",
  "properties": {
    "addr:full":"Am Brauteich 4 Kirchdorf an der Krems Ober\u00f6sterreich 4560",
    "addr:housenumber":"4",
    "addr:postcode":"4560",
    "addr:street":"Am Brauteich",
    "iso:country":"AT",
    "sg:address":"Am Brauteich 4",
    "sg:city":"Kirchdorf an der Krems",
    "sg:orig_category":"Autoersatzteile",
    "sg:phone":"+43 4375 82609200",
    "sg:postcode":"4560",
    "sg:province":"Ober\u00f6sterreich",
    "wof:name":"Forstinger Handel und Service GmbH",
    "wof:placetype":"venue"
},
  "geometry": {"coordinates":[14.1264801025,47.8963127136],"type":"Point"}
}