{
  "type": "Feature",
  "properties": {
    "addr:full":"Untere Donaul\u00e4nde 12 Linz Ober\u00f6sterreich 4020",
    "addr:housenumber":"12",
    "addr:postcode":"4020",
    "addr:street":"Untere Donaulaende",
    "iso:country":"AT",
    "sg:address":"Untere Donaul\u00e4nde 12",
    "sg:city":"Linz",
    "sg:orig_category":"Cd, Dvd,Musikkassetten U Schallplatten",
    "sg:phone":"+43 732 784794",
    "sg:postcode":"4020",
    "sg:province":"Ober\u00f6sterreich",
    "wof:name":"Con Trust Music Lehner & Klein OEG",
    "wof:placetype":"venue"
},
  "geometry": {"coordinates":[14.2893810272,48.3080062866],"type":"Point"}
}