{
  "type": "Feature",
  "properties": {
    "addr:full":"Nr 67 St. Andr\u00e4 K\u00e4rnten 9433",
    "addr:postcode":"9433",
    "addr:street":"Nr 67",
    "iso:country":"AT",
    "sg:address":"Nr 67",
    "sg:city":"St. Andr\u00e4",
    "sg:orig_category":"Textilwaren / Einzelhandel",
    "sg:phone":"+43 4343 5828257",
    "sg:postcode":"9433",
    "sg:province":"K\u00e4rnten",
    "wof:name":"NKD",
    "wof:placetype":"venue"
},
  "geometry": {"coordinates":[14.821849823,46.7685317993],"type":"Point"}
}