{
  "type": "Feature",
  "properties": {
    "iso:country":"AT",
    "sg:address":"Gleinkerseestr 8",
    "sg:city":"Windischgarsten",
    "sg:orig_category":"Lebensmittel / Einzelhandel",
    "sg:phone":"+43 7562 5545",
    "sg:postcode":"4580",
    "sg:province":"Ober\u00f6sterreich",
    "wof:name":"ADEG-Aktiv Rohregger",
    "wof:placetype":"venue"
},
  "geometry": {"coordinates":[14.3179397583,47.7178192139],"type":"Point"}
}