{
  "type": "Feature",
  "properties": {
    "addr:full":"Reumannpl 7/6 Wien Wien 1100",
    "addr:housenumber":"7 / 6",
    "addr:postcode":"1100",
    "addr:street":"Reumannpl",
    "iso:country":"AT",
    "sg:address":"Reumannpl 7/6",
    "sg:city":"Wien",
    "sg:classifiers":[
        {
            "category":"Professional",
            "subcategory":"Computer Services",
            "type":"Services"
        }
    ],
    "sg:phone":"+43 4313 670544",
    "sg:postcode":"1100",
    "sg:province":"Wien",
    "sg:tags":[
        "software"
    ],
    "wof:name":"ALTRAN Beteiligung GmbH",
    "wof:placetype":"venue"
},
  "geometry": {"coordinates":[16.3780822754,48.1729888916],"type":"Point"}
}