{
  "type": "Feature",
  "properties": {
    "addr:full":"Hauptstr 20 Hermagor K\u00e4rnten 9620",
    "addr:housenumber":"20",
    "addr:postcode":"9620",
    "addr:street":"Hauptstr;Kaernten",
    "iso:country":"AT",
    "sg:address":"Hauptstr 20",
    "sg:city":"Hermagor",
    "sg:orig_category":"Handarbeiten",
    "sg:phone":"+43 4282 4096",
    "sg:postcode":"9620",
    "sg:province":"K\u00e4rnten",
    "wof:name":"Novak Gottfriede",
    "wof:placetype":"venue"
},
  "geometry": {"coordinates":[13.3676576614,46.6275138855],"type":"Point"}
}