{
  "type": "Feature",
  "properties": {
    "addr:full":"Elisabethstrasse 10/4 Wien Wien 1010",
    "addr:housenumber":"10 / 4",
    "addr:postcode":"1010",
    "addr:street":"Elisabethstrasse",
    "iso:country":"AT",
    "sg:address":"Elisabethstrasse 10/4",
    "sg:city":"Wien",
    "sg:classifiers":[
        {
            "category":"Autos & Motor Vehicles",
            "subcategory":"Fuel & Gas Station",
            "type":"Retail Goods"
        }
    ],
    "sg:phone":"+43 1 5855473",
    "sg:postcode":"1010",
    "sg:province":"Wien",
    "sg:tags":[
        "engine",
        "petrol",
        "turbine",
        "diesel"
    ],
    "wof:name":"Petrol-Trade Handelsges.m.b.H.",
    "wof:placetype":"venue"
},
  "geometry": {"coordinates":[16.3670883179,48.2022476196],"type":"Point"}
}