{
  "type": "Feature",
  "properties": {
    "addr:full":"Josef-Jessernig-Str. 19  Stockerau Nieder\u00f6sterreich 2000",
    "addr:housenumber":"19",
    "addr:postcode":"2000",
    "addr:street":"Josef-Jessernig-Str.",
    "iso:country":"AT",
    "sg:address":"Josef-Jessernig-Str. 19 ",
    "sg:city":"Stockerau",
    "sg:classifiers":[
        {
            "category":"Autos & Motor Vehicles",
            "subcategory":"Automobile Sales",
            "type":"Retail Goods"
        }
    ],
    "sg:phone":"+43 4322 6661250",
    "sg:postcode":"2000",
    "sg:province":"Nieder\u00f6sterreich",
    "sg:tags":[
        "industrial"
    ],
    "wof:name":"INTERAD VERTRIEBSGESMBH",
    "wof:placetype":"venue"
},
  "geometry": {"coordinates":[16.237701416,48.3875579834],"type":"Point"}
}