{
  "type": "Feature",
  "properties": {
    "addr:full":"Dornacher Str 2 Gleink Ober\u00f6sterreich 4407",
    "addr:housenumber":"2",
    "addr:postcode":"4407",
    "addr:street":"Str",
    "iso:country":"AT",
    "sg:address":"Dornacher Str 2",
    "sg:city":"Gleink",
    "sg:orig_category":"Autohandel",
    "sg:phone":"+43 7252 816000",
    "sg:postcode":"4407",
    "sg:province":"Ober\u00f6sterreich",
    "wof:name":"Autoland Hinterleitner GesmbH",
    "wof:placetype":"venue"
},
  "geometry": {"coordinates":[14.4241361618,48.070941925],"type":"Point"}
}