{
  "type": "Feature",
  "properties": {
    "iso:country":"AT",
    "sg:address":"Nr 35",
    "sg:city":"Gm\u00fcnd",
    "sg:orig_category":"Maler, Anstreicher U Lackierer",
    "sg:phone":"+43 4366 45369363",
    "sg:postcode":"9853",
    "sg:province":"K\u00e4rnten",
    "wof:name":"Malerei Pacher Wolfgang",
    "wof:placetype":"venue"
},
  "geometry": {"coordinates":[13.5357999802,46.906955719],"type":"Point"}
}