{
  "type": "Feature",
  "properties": {
    "addr:full":"Herreng 16 Rechnitz Burgenland 7471",
    "addr:housenumber":"16",
    "addr:postcode":"7471",
    "addr:street":"Herreng",
    "iso:country":"AT",
    "sg:address":"Herreng 16",
    "sg:city":"Rechnitz",
    "sg:orig_category":"Juweliere, Gold- U Silberschmiede",
    "sg:phone":"+43 4333 6377482",
    "sg:postcode":"7471",
    "sg:province":"Burgenland",
    "wof:name":"Gager Werner",
    "wof:placetype":"venue"
},
  "geometry": {"coordinates":[16.4392871857,47.3045578003],"type":"Point"}
}