{
  "type": "Feature",
  "properties": {
    "addr:full":"Kremser Str 8 Eggenburg Nieder\u00f6sterreich 3730",
    "addr:housenumber":"8",
    "addr:postcode":"3730",
    "addr:street":"Str",
    "iso:country":"AT",
    "sg:address":"Kremser Str 8",
    "sg:city":"Eggenburg",
    "sg:classifiers":[
        {
            "category":"Travel",
            "subcategory":"Hotels & Motels",
            "type":"Entertainment"
        }
    ],
    "sg:phone":"+43 2984 35310",
    "sg:postcode":"3730",
    "sg:province":"Nieder\u00f6sterreich",
    "wof:name":"Stadthotel",
    "wof:placetype":"venue"
},
  "geometry": {"coordinates":[15.8172426224,48.6414794922],"type":"Point"}
}