{
  "type": "Feature",
  "properties": {
    "addr:full":"Atterseestr 22 Seewalchen am Attersee Ober\u00f6sterreich 4863",
    "addr:housenumber":"22",
    "addr:postcode":"4863",
    "addr:street":"Atterseestr",
    "iso:country":"AT",
    "sg:address":"Atterseestr 22",
    "sg:city":"Seewalchen am Attersee",
    "sg:orig_category":"Boutiquen",
    "sg:phone":"+43 4376 622551",
    "sg:postcode":"4863",
    "sg:province":"Ober\u00f6sterreich",
    "wof:name":"Jeronimo Mode",
    "wof:placetype":"venue"
},
  "geometry": {"coordinates":[13.5942640305,47.9495010376],"type":"Point"}
}