{
  "type": "Feature",
  "properties": {
    "addr:full":"Niederland 90 Unken Salzburg 5091",
    "addr:housenumber":"90",
    "addr:postcode":"5091",
    "addr:street":"Niederland;Salzburg",
    "iso:country":"AT",
    "sg:address":"Niederland 90",
    "sg:city":"Unken",
    "sg:orig_category":"Gemeinden",
    "sg:phone":"+43 6589 42020",
    "sg:postcode":"5091",
    "sg:province":"Salzburg",
    "wof:name":"Gemeindeamt Unken",
    "wof:placetype":"venue"
},
  "geometry": {"coordinates":[12.7301282883,47.6490058899],"type":"Point"}
}