{
  "type": "Feature",
  "properties": {
    "addr:full":"Ringstr 60 Braunau am Inn Ober\u00f6sterreich 5280",
    "addr:housenumber":"60",
    "addr:postcode":"5280",
    "addr:street":"Ringstr",
    "iso:country":"AT",
    "sg:address":"Ringstr 60",
    "sg:city":"Braunau am Inn",
    "sg:orig_category":"Friseure U Frisiersalons",
    "sg:phone":"+43 4377 22804442",
    "sg:postcode":"5280",
    "sg:province":"Ober\u00f6sterreich",
    "wof:name":"Schwarzlm\u00fcller Gabriele Friseursalon",
    "wof:placetype":"venue"
},
  "geometry": {"coordinates":[13.0334882736,48.2554092407],"type":"Point"}
}