{
  "type": "Feature",
  "properties": {
    "addr:full":"Kirchpl 147 Leutasch Tirol 6105",
    "addr:housenumber":"147",
    "addr:postcode":"6105",
    "addr:street":"Leutasch Tirol",
    "iso:country":"AT",
    "sg:address":"Kirchpl 147",
    "sg:city":"Leutasch",
    "sg:classifiers":[
        {
            "category":"Restaurant",
            "type":"Food & Drink"
        }
    ],
    "sg:phone":"+43 5214 6589",
    "sg:postcode":"6105",
    "sg:province":"Tirol",
    "wof:name":"Restaurant Kirchenwirt",
    "wof:placetype":"venue"
},
  "geometry": {"coordinates":[11.1422395706,47.3693161011],"type":"Point"}
}