{
  "type": "Feature",
  "properties": {
    "iso:country":"AT",
    "sg:address":"Thaliastr 154a",
    "sg:city":"Wien",
    "sg:orig_category":"Blumeneinzelhandel",
    "sg:phone":"+43 1 4859610",
    "sg:postcode":"1160",
    "sg:province":"Wien",
    "wof:name":"Zvara's Baccara BlumenhandelsgesmbH",
    "wof:placetype":"venue"
},
  "geometry": {"coordinates":[16.3075141907,48.2134437561],"type":"Point"}
}