{
  "type": "Feature",
  "properties": {
    "iso:country":"AT",
    "sg:address":"Fabriksteig 8a",
    "sg:city":"Villach",
    "sg:orig_category":"Satellitenempfangsanlagen",
    "sg:phone":"+43 4242 25610",
    "sg:postcode":"9500",
    "sg:province":"K\u00e4rnten",
    "wof:name":"Urleb Herbert",
    "wof:placetype":"venue"
},
  "geometry": {"coordinates":[13.8515710831,46.6127204895],"type":"Point"}
}