{
  "type": "Feature",
  "properties": {
    "addr:full":"Burgstallweg 27 Kapfenberg Steiermark 8605",
    "addr:housenumber":"27",
    "addr:postcode":"8605",
    "addr:street":"Burgstallweg",
    "iso:country":"AT",
    "sg:address":"Burgstallweg 27",
    "sg:city":"Kapfenberg",
    "sg:classifiers":[
        {
            "category":"Professional",
            "subcategory":"Detective & Security Services",
            "type":"Services"
        }
    ],
    "sg:phone":"+43 3862 34144",
    "sg:postcode":"8605",
    "sg:province":"Steiermark",
    "sg:tags":[
        "abrasion",
        "protection"
    ],
    "sg:website":"balzers.at",
    "wof:name":"Balzers GmbH",
    "wof:placetype":"venue"
},
  "geometry": {"coordinates":[15.3431682587,47.4590873718],"type":"Point"}
}