{
  "type": "Feature",
  "properties": {
    "iso:country":"AT",
    "sg:address":"K\u00f6rmender Str 11",
    "sg:city":"F\u00fcrstenfeld",
    "sg:orig_category":"Autohandel",
    "sg:phone":"+43 3382 54300",
    "sg:postcode":"8280",
    "sg:province":"Steiermark",
    "wof:name":"K\u00e4fer KG",
    "wof:placetype":"venue"
},
  "geometry": {"coordinates":[16.0765228271,47.055896759],"type":"Point"}
}