{
  "type": "Feature",
  "properties": {
    "addr:full":"Bahnhofstrasse 20 H\u00fcttenberg K\u00e4rnten 9375",
    "addr:housenumber":"20",
    "addr:postcode":"9375",
    "addr:street":"Bahnhofstrasse;Kaernten",
    "iso:country":"AT",
    "sg:address":"Bahnhofstrasse 20",
    "sg:city":"H\u00fcttenberg",
    "sg:classifiers":[
        {
            "category":"Manufacturing",
            "subcategory":"Wood Products",
            "type":"Manufacturing & Wholesale Goods"
        }
    ],
    "sg:phone":"+43 4263 297",
    "sg:postcode":"9375",
    "sg:province":"K\u00e4rnten",
    "sg:tags":[
        "gate",
        "made",
        "door"
    ],
    "wof:name":"Schaffer Tischlereibetriebsges.m.b.H.",
    "wof:placetype":"venue"
},
  "geometry": {"coordinates":[14.547296524,46.9353942871],"type":"Point"}
}