{
  "type": "Feature",
  "properties": {
    "iso:country":"AT",
    "sg:address":"Halirschgasse 19/49",
    "sg:city":"Wien",
    "sg:classifiers":[
        {
            "category":"Shopping",
            "subcategory":"Department Store",
            "type":"Retail Goods"
        }
    ],
    "sg:phone":"+43 1 5331041",
    "sg:postcode":"1170",
    "sg:province":"Wien",
    "sg:tags":[
        "linen",
        "bed"
    ],
    "sg:website":"gardenia.hu",
    "wof:name":"GARDENIA Textilhandelsges.m.b.H.",
    "wof:placetype":"venue"
},
  "geometry": {"coordinates":[16.3171977997,48.2243728638],"type":"Point"}
}