{
  "type": "Feature",
  "properties": {
    "addr:full":"In den H\u00e4gen 1 Hirschegg Vorarlberg 6992",
    "addr:housenumber":"1",
    "addr:postcode":"6992",
    "addr:street":"In Den Haegen",
    "iso:country":"AT",
    "sg:address":"In den H\u00e4gen 1",
    "sg:city":"Hirschegg",
    "sg:orig_category":"Appartements / Ferienwohnungen",
    "sg:phone":"+43 4355 1720068",
    "sg:postcode":"6992",
    "sg:province":"Vorarlberg",
    "wof:name":"G\u00e4stehaus B\u00fcchele",
    "wof:placetype":"venue"
},
  "geometry": {"coordinates":[10.1720600128,47.3498039246],"type":"Point"}
}