{
  "type": "Feature",
  "properties": {
    "addr:full":"Fraueng 2 Baden Nieder\u00f6sterreich 2500",
    "addr:housenumber":"2",
    "addr:postcode":"2500",
    "addr:street":"Fraueng;Niederoesterreich",
    "iso:country":"AT",
    "sg:address":"Fraueng 2",
    "sg:city":"Baden",
    "sg:orig_category":"Notare",
    "sg:phone":"+43 2252 485320",
    "sg:postcode":"2500",
    "sg:province":"Nieder\u00f6sterreich",
    "wof:name":"Br\u00fcll Richard Dr",
    "wof:placetype":"venue"
},
  "geometry": {"coordinates":[16.2340335846,48.0072174072],"type":"Point"}
}