{
  "type": "Feature",
  "properties": {
    "addr:full":"Pichlwangerstr 4 Neuhofen an der Krems Ober\u00f6sterreich 4501",
    "addr:housenumber":"4",
    "addr:postcode":"4501",
    "addr:street":"Pichlwangerstr",
    "iso:country":"AT",
    "sg:address":"Pichlwangerstr 4",
    "sg:city":"Neuhofen an der Krems",
    "sg:orig_category":"Industrievertretungen",
    "sg:phone":"+43 4372 27577525",
    "sg:postcode":"4501",
    "sg:province":"Ober\u00f6sterreich",
    "wof:name":"Zachhuber KEG",
    "wof:placetype":"venue"
},
  "geometry": {"coordinates":[14.2485408783,48.1350479126],"type":"Point"}
}