{
  "type": "Feature",
  "properties": {
    "addr:full":"Kaig 39 Salzburg Salzburg 5020",
    "addr:housenumber":"39",
    "addr:postcode":"5020",
    "addr:street":"Kaig;Salzburg",
    "iso:country":"AT",
    "sg:address":"Kaig 39",
    "sg:city":"Salzburg",
    "sg:orig_category":"Friseure U Frisiersalons",
    "sg:phone":"+43 4366 2840147",
    "sg:postcode":"5020",
    "sg:province":"Salzburg",
    "wof:name":"Haar'y",
    "wof:placetype":"venue"
},
  "geometry": {"coordinates":[13.0433769226,47.8006744385],"type":"Point"}
}