{
  "type": "Feature",
  "properties": {
    "addr:full":"Pfongauerstr.13 Neumarkt am Wallersee Salzburg 5202",
    "addr:postcode":"5202",
    "addr:street":"Salzburg",
    "iso:country":"AT",
    "sg:address":"Pfongauerstr.13",
    "sg:city":"Neumarkt am Wallersee",
    "sg:classifiers":[
        {
            "category":"Shopping",
            "subcategory":"Stationery & Office Supplies",
            "type":"Retail Goods"
        }
    ],
    "sg:phone":"+43 4362 164465",
    "sg:postcode":"5202",
    "sg:province":"Salzburg",
    "sg:tags":[
        "professional"
    ],
    "wof:name":"MODL GESMBH",
    "wof:placetype":"venue"
},
  "geometry": {"coordinates":[13.230219841,47.9497566223],"type":"Point"}
}