{
  "type": "Feature",
  "properties": {
    "iso:country":"AT",
    "sg:address":"Wieseng. 2",
    "sg:city":"Hartberg",
    "sg:classifiers":[
        {
            "category":"Banks & Credit Unions",
            "subcategory":"Bank",
            "type":"Services"
        }
    ],
    "sg:phone":"+43 4333 3263516",
    "sg:postcode":"8230",
    "sg:province":"Steiermark",
    "sg:tags":[
        "banking",
        "institution"
    ],
    "wof:name":"RAIFFEISENBANK HARTBERG REG.GEN.MBH",
    "wof:placetype":"venue"
},
  "geometry": {"coordinates":[15.9733400345,47.281288147],"type":"Point"}
}