{
  "type": "Feature",
  "properties": {
    "addr:full":"10.-Oktober-Strasse 30 Treibach-Althofen K\u00e4rnten 9330",
    "addr:housenumber":"30",
    "addr:postcode":"9330",
    "addr:street":"10.-Oktober-Strasse;Kaernten",
    "iso:country":"AT",
    "sg:address":"10.-Oktober-Strasse 30",
    "sg:city":"Treibach-Althofen",
    "sg:classifiers":[
        {
            "category":"Internet Cafe",
            "subcategory":"None",
            "type":"Food & Drink"
        }
    ],
    "sg:phone":"+43 676 5269525",
    "sg:postcode":"9330",
    "sg:province":"K\u00e4rnten",
    "sg:tags":[
        "web",
        "server",
        "servers"
    ],
    "sg:website":"atlantic.at",
    "wof:name":"AtlanticSoft",
    "wof:placetype":"venue"
},
  "geometry": {"coordinates":[14.4656963348,46.8716506958],"type":"Point"}
}