{
  "type": "Feature",
  "properties": {
    "addr:full":"Eichbachgasse 157 Liebenau Steiermark 8041",
    "addr:housenumber":"157",
    "addr:postcode":"8041",
    "addr:street":"Eichbachgasse",
    "iso:country":"AT",
    "sg:address":"Eichbachgasse 157",
    "sg:city":"Liebenau",
    "sg:classifiers":[
        {
            "category":"Building & Trades",
            "subcategory":"Plumbing",
            "type":"Services"
        }
    ],
    "sg:phone":"+43 316 401457",
    "sg:postcode":"8041",
    "sg:province":"Steiermark",
    "sg:tags":[
        "supraregional",
        "gas"
    ],
    "sg:website":"ederegger.at",
    "wof:name":"Fritz Ederegger",
    "wof:placetype":"venue"
},
  "geometry": {"coordinates":[15.462767601,47.0164108276],"type":"Point"}
}