{
  "type": "Feature",
  "properties": {
    "addr:full":"Dr Steger-G 5 Pottenbrunn Nieder\u00f6sterreich 3140",
    "addr:housenumber":"5",
    "addr:postcode":"3140",
    "addr:street":"Niederoesterreich",
    "iso:country":"AT",
    "sg:address":"Dr Steger-G 5",
    "sg:city":"Pottenbrunn",
    "sg:orig_category":"Banken U Sparkassen",
    "sg:phone":"+43 2742 42250",
    "sg:postcode":"3140",
    "sg:province":"Nieder\u00f6sterreich",
    "wof:name":"Raiffeisenbank Region St P\u00f6lten regGenmbH",
    "wof:placetype":"venue"
},
  "geometry": {"coordinates":[15.6936063766,48.2376747131],"type":"Point"}
}