{
  "type": "Feature",
  "properties": {
    "iso:country":"AT",
    "sg:address":"Koloman-Wallisch-Pl 17",
    "sg:city":"Bruck an der Mur",
    "sg:orig_category":"Damenmoden",
    "sg:phone":"+43 3862 58109",
    "sg:postcode":"8600",
    "sg:province":"Steiermark",
    "wof:name":"City Classic - Schrittwieser GmbH,",
    "wof:placetype":"venue"
},
  "geometry": {"coordinates":[15.270195961,47.4094238281],"type":"Point"}
}