{
  "type": "Feature",
  "properties": {
    "iso:country":"AT",
    "sg:address":"Blauensteinerstrasse 11b",
    "sg:city":"Lengenfeld",
    "sg:classifiers":[
        {
            "category":"Government",
            "subcategory":"Fire Station",
            "type":"Public Place"
        }
    ],
    "sg:phone":"+43 2719 8302",
    "sg:postcode":"3552",
    "sg:province":"Nieder\u00f6sterreich",
    "sg:tags":[
        "bitumen",
        "roof",
        "shingle"
    ],
    "wof:name":"Mobile Spenglerei Klaus Kopetzky",
    "wof:placetype":"venue"
},
  "geometry": {"coordinates":[15.5985889435,48.4682350159],"type":"Point"}
}