{
  "type": "Feature",
  "properties": {
    "addr:full":"Bahnhofstr 17-19 Bregenz Vorarlberg 6900",
    "addr:postcode":"17-19;6900",
    "addr:street":"Bahnhofstr",
    "iso:country":"AT",
    "sg:address":"Bahnhofstr 17-19",
    "sg:city":"Bregenz",
    "sg:orig_category":"Banken U Sparkassen",
    "sg:phone":"+43 4355 74432430",
    "sg:postcode":"6900",
    "sg:province":"Vorarlberg",
    "wof:name":"Bank f Arbeit u Wirtschaft AG",
    "wof:placetype":"venue"
},
  "geometry": {"coordinates":[9.742931366,47.5029144287],"type":"Point"}
}