{
  "type": "Feature",
  "properties": {
    "addr:full":"Landstra\u00dfer Hauptstrasse 82/9a Wien Wien 1030",
    "addr:housenumber":"82 / 9a",
    "addr:postcode":"1030",
    "addr:street":"Landstrasser Hauptstrasse",
    "iso:country":"AT",
    "sg:address":"Landstra\u00dfer Hauptstrasse 82/9a",
    "sg:city":"Wien",
    "sg:classifiers":[
        {
            "category":"Professional",
            "subcategory":"Management & Consulting",
            "type":"Services"
        }
    ],
    "sg:phone":"+43 1 4164529",
    "sg:postcode":"1030",
    "sg:province":"Wien",
    "sg:tags":[
        "facility"
    ],
    "wof:name":"R.E.M. Geb\u00e4udereinigung u. -management GmbH",
    "wof:placetype":"venue"
},
  "geometry": {"coordinates":[16.3929157257,48.2002944946],"type":"Point"}
}