{
  "type": "Feature",
  "properties": {
    "iso:country":"AT",
    "sg:address":"Karl-von-Lutterotti-Str 2",
    "sg:city":"Imst",
    "sg:orig_category":"Zeitungen U Zeitschriften",
    "sg:phone":"+43 4350 4030133",
    "sg:postcode":"6460",
    "sg:province":"Tirol",
    "wof:name":"Tiroler Tageszeitung",
    "wof:placetype":"venue"
},
  "geometry": {"coordinates":[10.7386779785,47.2363853455],"type":"Point"}
}