{
  "type": "Feature",
  "properties": {
    "iso:country":"AT",
    "sg:address":"Bl\u00e4tterstr 2",
    "sg:city":"Steinabr\u00fcckl",
    "sg:orig_category":"Logistik",
    "sg:phone":"+43 2622 43788",
    "sg:postcode":"2751",
    "sg:province":"Nieder\u00f6sterreich",
    "wof:name":"Distrilux Logistik GmbH Nfg KG",
    "wof:placetype":"venue"
},
  "geometry": {"coordinates":[16.2047634125,47.8627433777],"type":"Point"}
}