{
  "type": "Feature",
  "properties": {
    "addr:full":"Lorch 17 Enns Ober\u00f6sterreich 4470",
    "addr:housenumber":"17",
    "addr:postcode":"4470",
    "addr:street":"Lorch",
    "iso:country":"AT",
    "sg:address":"Lorch 17",
    "sg:city":"Enns",
    "sg:classifiers":[
        {
            "category":"Internet Cafe",
            "subcategory":"None",
            "type":"Food & Drink"
        }
    ],
    "sg:phone":"+43 7223 89029",
    "sg:postcode":"4470",
    "sg:province":"Ober\u00f6sterreich",
    "wof:name":"bliem.IT",
    "wof:placetype":"venue"
},
  "geometry": {"coordinates":[14.4664821625,48.2260665894],"type":"Point"}
}