{
  "type": "Feature",
  "properties": {
    "addr:full":"Bahnhofstrasse 117 Bad Aussee Steiermark 8990",
    "addr:housenumber":"117",
    "addr:postcode":"8990",
    "addr:street":"Bahnhofstrasse",
    "iso:country":"AT",
    "sg:address":"Bahnhofstrasse 117",
    "sg:city":"Bad Aussee",
    "sg:classifiers":[
        {
            "category":"Banks & Credit Unions",
            "subcategory":"Investment Brokerage",
            "type":"Services"
        }
    ],
    "sg:phone":"+43 3622 53108",
    "sg:postcode":"8990",
    "sg:province":"Steiermark",
    "sg:tags":[
        "absorption",
        "refrigerator"
    ],
    "wof:name":"Alois K\u00f6berl",
    "wof:placetype":"venue"
},
  "geometry": {"coordinates":[13.7768774033,47.599029541],"type":"Point"}
}