{
  "type": "Feature",
  "properties": {
    "addr:full":"Glocknerstr 12 Bruck an der Gro\u00dfglocknerstra\u00dfe Salzburg 5671",
    "addr:housenumber":"12",
    "addr:postcode":"5671",
    "addr:street":"Glocknerstr;Grossglocknerstrasse Salzburg",
    "iso:country":"AT",
    "sg:address":"Glocknerstr 12",
    "sg:city":"Bruck an der Gro\u00dfglocknerstra\u00dfe",
    "sg:orig_category":"Bars-Cafes",
    "sg:phone":"+43 4365 4520013",
    "sg:postcode":"5671",
    "sg:province":"Salzburg",
    "wof:name":"Pinzgauer Laterndl",
    "wof:placetype":"venue"
},
  "geometry": {"coordinates":[12.8235054016,47.286491394],"type":"Point"}
}