{
  "type": "Feature",
  "properties": {
    "addr:full":"Buxera 19 Klaus-Weiler Vorarlberg 6833",
    "addr:housenumber":"19",
    "addr:postcode":"6833",
    "addr:street":"Buxera",
    "iso:country":"AT",
    "sg:address":"Buxera 19",
    "sg:city":"Klaus-Weiler",
    "sg:orig_category":"Beschichtungen",
    "sg:phone":"+43 5523 51351",
    "sg:postcode":"6833",
    "sg:province":"Vorarlberg",
    "sg:website":"beschichtungen.at",
    "wof:name":"Vondrak Alfred",
    "wof:placetype":"venue"
},
  "geometry": {"coordinates":[9.6427125931,47.3027114868],"type":"Point"}
}