{
  "type": "Feature",
  "properties": {
    "addr:full":"Wiener Str 23A Schwechat Nieder\u00f6sterreich 2320",
    "addr:postcode":"2320",
    "addr:street":"Str 23A Schwechat Niederoesterreich",
    "iso:country":"AT",
    "sg:address":"Wiener Str 23A",
    "sg:city":"Schwechat",
    "sg:orig_category":"Bibliotheken",
    "sg:phone":"+43 1 7074131",
    "sg:postcode":"2320",
    "sg:province":"Nieder\u00f6sterreich",
    "wof:name":"B\u00fccherei d Stadtgemeinde Schwechat",
    "wof:placetype":"venue"
},
  "geometry": {"coordinates":[16.472366333,48.1431617737],"type":"Point"}
}