{
  "type": "Feature",
  "properties": {
    "addr:full":"Industriepark Gampern Ober\u00f6sterreich 4851",
    "addr:postcode":"4851",
    "addr:street":"Industriepark Gampern",
    "iso:country":"AT",
    "sg:address":"Industriepark",
    "sg:city":"Gampern",
    "sg:classifiers":[
        {
            "category":"Autos & Motor Vehicles",
            "subcategory":"Auto Supplies",
            "type":"Retail Goods"
        }
    ],
    "sg:phone":"+43 768239080",
    "sg:postcode":"4851",
    "sg:province":"Ober\u00f6sterreich",
    "sg:tags":[
        "clutch"
    ],
    "sg:website":"albert.at",
    "wof:name":"Maschinenfabrik ALBERT GmbH Ein Unternehmen der INKOMA-Group",
    "wof:placetype":"venue"
},
  "geometry": {"coordinates":[13.5552349091,47.989364624],"type":"Point"}
}