{
  "type": "Feature",
  "properties": {
    "addr:full":"Andreas Hofer-Str 8 Innsbruck Tirol 6020",
    "addr:housenumber":"8",
    "addr:postcode":"6020",
    "addr:street":"Tirol",
    "iso:country":"AT",
    "sg:address":"Andreas Hofer-Str 8",
    "sg:city":"Innsbruck",
    "sg:orig_category":"Psychotherapie",
    "sg:phone":"+43 512 580811",
    "sg:postcode":"6020",
    "sg:province":"Tirol",
    "wof:name":"Maca Pia Mag rer nat",
    "wof:placetype":"venue"
},
  "geometry": {"coordinates":[11.3912210464,47.2615814209],"type":"Point"}
}