{
  "type": "Feature",
  "properties": {
    "iso:country":"AT",
    "sg:address":"Dorf 26",
    "sg:city":"Ellmau",
    "sg:orig_category":"Damenmoden",
    "sg:phone":"+43 5358 44324",
    "sg:postcode":"6352",
    "sg:province":"Tirol",
    "wof:name":"Gabi's Moden",
    "wof:placetype":"venue"
},
  "geometry": {"coordinates":[12.302069664,47.515838623],"type":"Point"}
}