{
  "type": "Feature",
  "properties": {
    "addr:full":"Quadenstr 15-19 Wien Wien 1220",
    "addr:postcode":"15-19;1220",
    "iso:country":"AT",
    "sg:address":"Quadenstr 15-19",
    "sg:city":"Wien",
    "sg:orig_category":"Museen / Ausstellungen",
    "sg:phone":"+43 4312 8076310",
    "sg:postcode":"1220",
    "sg:province":"Wien",
    "wof:name":"Blumeng\u00e4rten u Palmenhaus Hirschstetten",
    "wof:placetype":"venue"
},
  "geometry": {"coordinates":[16.4724998474,48.2361450195],"type":"Point"}
}