{
  "type": "Feature",
  "properties": {
    "addr:full":"Schaumburgerg 20 Wien Wien 1040",
    "addr:housenumber":"20",
    "addr:postcode":"1040",
    "addr:street":"Schaumburgerg",
    "iso:country":"AT",
    "sg:address":"Schaumburgerg 20",
    "sg:city":"Wien",
    "sg:orig_category":"Innungen",
    "sg:phone":"+43 4315 056950126",
    "sg:postcode":"1040",
    "sg:province":"Wien",
    "wof:name":"Bundesinnungsgruppe f Metall-Elektro-Sanit\u00e4r",
    "wof:placetype":"venue"
},
  "geometry": {"coordinates":[16.3686408997,48.1898078918],"type":"Point"}
}