{
  "type": "Feature",
  "properties": {
    "addr:full":"Springerg 3 Wien Wien 1020",
    "addr:housenumber":"3",
    "addr:postcode":"1020",
    "addr:street":"Springerg",
    "iso:country":"AT",
    "sg:address":"Springerg 3",
    "sg:city":"Wien",
    "sg:classifiers":[
        {
            "category":"Professional",
            "subcategory":"Computer Services",
            "type":"Services"
        }
    ],
    "sg:phone":"+43 1 21987900",
    "sg:postcode":"1020",
    "sg:province":"Wien",
    "sg:tags":[
        "software"
    ],
    "wof:name":"beiT Consulting GmbH",
    "wof:placetype":"venue"
},
  "geometry": {"coordinates":[16.3869419098,48.2209663391],"type":"Point"}
}