{
  "type": "Feature",
  "properties": {
    "addr:full":"Robert Preu\u00dfler-Str 13 Salzburg Salzburg 5020",
    "addr:housenumber":"13",
    "addr:postcode":"5020",
    "addr:street":"Salzburg",
    "iso:country":"AT",
    "sg:address":"Robert Preu\u00dfler-Str 13",
    "sg:city":"Salzburg",
    "sg:orig_category":"Psychologen",
    "sg:phone":"+43 662 621265",
    "sg:postcode":"5020",
    "sg:province":"Salzburg",
    "wof:name":"Stroblmair Manuela Mag phil",
    "wof:placetype":"venue"
},
  "geometry": {"coordinates":[13.0727815628,47.7720108032],"type":"Point"}
}