{
  "type": "Feature",
  "properties": {
    "addr:full":"Michael-Koch-Str 16 Mattersburg Burgenland 7210",
    "addr:housenumber":"16",
    "addr:postcode":"7210",
    "addr:street":"Michael-Koch-Str",
    "iso:country":"AT",
    "sg:address":"Michael-Koch-Str 16",
    "sg:city":"Mattersburg",
    "sg:orig_category":"Bestattungsunternehmen",
    "sg:phone":"+43 664 3087616",
    "sg:postcode":"7210",
    "sg:province":"Burgenland",
    "wof:name":"Bestattungsunternehmen Concordia",
    "wof:placetype":"venue"
},
  "geometry": {"coordinates":[16.3987007141,47.7385787964],"type":"Point"}
}