{
  "type": "Feature",
  "properties": {
    "addr:full":"Margaretenstr 66 Wien Wien 1050",
    "addr:housenumber":"66",
    "addr:postcode":"1050",
    "addr:street":"Margaretenstr",
    "iso:country":"AT",
    "sg:address":"Margaretenstr 66",
    "sg:city":"Wien",
    "sg:orig_category":"Friseure U Frisiersalons",
    "sg:phone":"+43 1 5863840",
    "sg:postcode":"1050",
    "sg:province":"Wien",
    "wof:name":"Prenner Franz",
    "wof:placetype":"venue"
},
  "geometry": {"coordinates":[16.3608379364,48.1931686401],"type":"Point"}
}