{
  "type": "Feature",
  "properties": {
    "addr:full":"Marktpl 79 Altenmarkt im Pongau Salzburg 5541",
    "addr:housenumber":"79",
    "addr:postcode":"5541",
    "addr:street":"Marktpl;Salzburg",
    "iso:country":"AT",
    "sg:address":"Marktpl 79",
    "sg:city":"Altenmarkt im Pongau",
    "sg:classifiers":[
        {
            "category":"Travel",
            "subcategory":"Hotels & Motels",
            "type":"Entertainment"
        }
    ],
    "sg:phone":"+43 4364 5269110",
    "sg:postcode":"5541",
    "sg:province":"Salzburg",
    "wof:name":"Hotel Lebzelter",
    "wof:placetype":"venue"
},
  "geometry": {"coordinates":[13.4237203598,47.3784751892],"type":"Point"}
}