{
  "type": "Feature",
  "properties": {
    "addr:full":"Rottweg 84 Salzburg Salzburg 5020",
    "addr:housenumber":"84",
    "addr:postcode":"5020",
    "addr:street":"Rottweg;Salzburg",
    "iso:country":"AT",
    "sg:address":"Rottweg 84",
    "sg:city":"Salzburg",
    "sg:orig_category":"Installationsunternehmen",
    "sg:phone":"+43 662 4353410",
    "sg:postcode":"5020",
    "sg:province":"Salzburg",
    "wof:name":"Seeleitner Otto GesmbH",
    "wof:placetype":"venue"
},
  "geometry": {"coordinates":[12.9976005554,47.829158783],"type":"Point"}
}