{
  "type": "Feature",
  "properties": {
    "iso:country":"AT",
    "sg:address":"Nr 18",
    "sg:city":"Keutschach",
    "sg:orig_category":"Lederwaren / Einzelhandel",
    "sg:phone":"+43 4273 3631",
    "sg:postcode":"9074",
    "sg:province":"K\u00e4rnten",
    "wof:name":"Ledergold",
    "wof:placetype":"venue"
},
  "geometry": {"coordinates":[-154.38163757320001,63.0122718811],"type":"Point"}
}