{
  "type": "Feature",
  "properties": {
    "addr:full":"Grabenstr 23 Graz Steiermark 8010",
    "addr:housenumber":"23",
    "addr:postcode":"8010",
    "addr:street":"Grabenstr",
    "iso:country":"AT",
    "sg:address":"Grabenstr 23",
    "sg:city":"Graz",
    "sg:orig_category":"Architekten",
    "sg:phone":"+43 316 8254400",
    "sg:postcode":"8010",
    "sg:province":"Steiermark",
    "wof:name":"Peyker Herfried Dipl-Ing",
    "wof:placetype":"venue"
},
  "geometry": {"coordinates":[15.4381322861,47.0817565918],"type":"Point"}
}