{
  "type": "Feature",
  "properties": {
    "iso:country":"AT",
    "sg:address":"Aspettenstr 48",
    "sg:city":"Perchtoldsdorf",
    "sg:orig_category":"Elektroinstallationsunternehmen",
    "sg:phone":"+43 1 6175687",
    "sg:postcode":"2380",
    "sg:province":"Nieder\u00f6sterreich",
    "wof:name":"Nentronics Nendwich und Rotter Elektrotechnik OEG",
    "wof:placetype":"venue"
},
  "geometry": {"coordinates":[16.2843532562,48.1242256165],"type":"Point"}
}