{
  "type": "Feature",
  "properties": {
    "addr:full":"Gr\u00fcnaug 14 Prellenkirchen Nieder\u00f6sterreich 2472",
    "addr:housenumber":"14",
    "addr:postcode":"2472",
    "addr:street":"Gruenaug",
    "iso:country":"AT",
    "sg:address":"Gr\u00fcnaug 14",
    "sg:city":"Prellenkirchen",
    "sg:orig_category":"Innenausbau",
    "sg:phone":"+43 2145 24004",
    "sg:postcode":"2472",
    "sg:province":"Nieder\u00f6sterreich",
    "wof:name":"Akustikinnenausbau Inh Sch\u00e4tzinger Johann",
    "wof:placetype":"venue"
},
  "geometry": {"coordinates":[16.9520206451,48.0750274658],"type":"Point"}
}