{
  "type": "Feature",
  "properties": {
    "iso:country":"AT",
    "sg:address":"Linzer Str 237a",
    "sg:city":"Wien",
    "sg:classifiers":[
        {
            "category":"Restaurant",
            "type":"Food & Drink"
        }
    ],
    "sg:phone":"+43 4314 198026",
    "sg:postcode":"1140",
    "sg:province":"Wien",
    "wof:name":"Restaurant Retsina",
    "wof:placetype":"venue"
},
  "geometry": {"coordinates":[16.2872142792,48.1945152283],"type":"Point"}
}