{
  "type": "Feature",
  "properties": {
    "iso:country":"AT",
    "sg:address":"Nr 27",
    "sg:city":"Unterstinkenbrunn",
    "sg:orig_category":"Feuerwehren",
    "sg:phone":"+43 2526 6177",
    "sg:postcode":"2154",
    "sg:province":"Nieder\u00f6sterreich",
    "wof:name":"Freiwillige Feuerwehr Unterstinkenbrunn",
    "wof:placetype":"venue"
},
  "geometry": {"coordinates":[16.3802204132,48.6551513672],"type":"Point"}
}