{
  "type": "Feature",
  "properties": {
    "addr:full":"Negrellistr 35 Lustenau Vorarlberg 6890",
    "addr:housenumber":"35",
    "addr:postcode":"6890",
    "addr:street":"Negrellistr",
    "iso:country":"AT",
    "sg:address":"Negrellistr 35",
    "sg:city":"Lustenau",
    "sg:orig_category":"Stickereien",
    "sg:phone":"+43 5577 85736",
    "sg:postcode":"6890",
    "sg:province":"Vorarlberg",
    "wof:name":"Ender Maria",
    "wof:placetype":"venue"
},
  "geometry": {"coordinates":[9.6543111801,47.4173278809],"type":"Point"}
}