{
  "type": "Feature",
  "properties": {
    "addr:full":"Bairisch K\u00f6lldorf 266 Bad Gleichenberg Steiermark 8344",
    "addr:housenumber":"266",
    "addr:postcode":"8344",
    "iso:country":"AT",
    "sg:address":"Bairisch K\u00f6lldorf 266",
    "sg:city":"Bad Gleichenberg",
    "sg:classifiers":[
        {
            "category":"Wholesale",
            "subcategory":"Machinery & Supplies",
            "type":"Manufacturing & Wholesale Goods"
        }
    ],
    "sg:phone":"+43 4331 5930010",
    "sg:postcode":"8344",
    "sg:province":"Steiermark",
    "sg:tags":[
        "equipment",
        "-",
        "instrument",
        "measurement"
    ],
    "wof:name":"HIQUEL-ELEKTRONIK-UND ANLAGENBAU GMBH",
    "wof:placetype":"venue"
},
  "geometry": {"coordinates":[15.923743248,46.8854370117],"type":"Point"}
}