{
  "type": "Feature",
  "properties": {
    "iso:country":"AT",
    "sg:address":"Breitenfurter Str 282",
    "sg:city":"Wien",
    "sg:orig_category":"Notare",
    "sg:phone":"+43 1 8693841",
    "sg:postcode":"1230",
    "sg:province":"Wien",
    "wof:name":"Matschiner Franz Dr",
    "wof:placetype":"venue"
},
  "geometry": {"coordinates":[16.2924308777,48.1433753967],"type":"Point"}
}