{
  "type": "Feature",
  "properties": {
    "iso:country":"AT",
    "sg:address":"Hofriedenstr 26",
    "sg:city":"Lochau",
    "sg:classifiers":[
        {
            "category":"Personal",
            "subcategory":"Adult",
            "type":"Services"
        }
    ],
    "sg:phone":"+43 5574 471110",
    "sg:postcode":"6911",
    "sg:province":"Vorarlberg",
    "sg:tags":[
        "sex-shops"
    ],
    "wof:name":"Amor Medien Handels GesmbH",
    "wof:placetype":"venue"
},
  "geometry": {"coordinates":[9.7524089813,47.5350418091],"type":"Point"}
}