{
  "type": "Feature",
  "properties": {
    "addr:full":"Hauptpl 16 Rechnitz Burgenland 7471",
    "addr:housenumber":"16",
    "addr:postcode":"7471",
    "addr:street":"Hauptpl",
    "iso:country":"AT",
    "sg:address":"Hauptpl 16",
    "sg:city":"Rechnitz",
    "sg:orig_category":"Blumeneinzelhandel",
    "sg:phone":"+43 3363 79250",
    "sg:postcode":"7471",
    "sg:province":"Burgenland",
    "wof:name":"Klepsch Emmerich",
    "wof:placetype":"venue"
},
  "geometry": {"coordinates":[16.4408321381,47.3049659729],"type":"Point"}
}