{
  "type": "Feature",
  "properties": {
    "addr:full":"Gewerbepark 239 Tamsweg Salzburg 5580",
    "addr:housenumber":"239",
    "addr:postcode":"5580",
    "addr:street":"Gewerbepark;Salzburg",
    "iso:country":"AT",
    "sg:address":"Gewerbepark 239",
    "sg:city":"Tamsweg",
    "sg:orig_category":"Stukkateure U Trockenausbauer",
    "sg:phone":"+43 6474 81910",
    "sg:postcode":"5580",
    "sg:province":"Salzburg",
    "wof:name":"Pagitsch GesmbH",
    "wof:placetype":"venue"
},
  "geometry": {"coordinates":[13.7957859039,47.1323242188],"type":"Point"}
}