{
  "type": "Feature",
  "properties": {
    "addr:full":"Gersthofer Str 61 Wien Wien 1180",
    "addr:postcode":"1180",
    "addr:street":"Str 61",
    "iso:country":"AT",
    "sg:address":"Gersthofer Str 61",
    "sg:city":"Wien",
    "sg:orig_category":"Apotheken",
    "sg:phone":"+43 1 47913100",
    "sg:postcode":"1180",
    "sg:province":"Wien",
    "wof:name":"Gersthofer Apotheke Mag pharm und Sommeregger KG",
    "wof:placetype":"venue"
},
  "geometry": {"coordinates":[16.3282108307,48.2321929932],"type":"Point"}
}