{
  "type": "Feature",
  "properties": {
    "addr:full":"Neug 2 Halbturn Burgenland 7131",
    "addr:housenumber":"2",
    "addr:postcode":"7131",
    "addr:street":"Neug",
    "iso:country":"AT",
    "sg:address":"Neug 2",
    "sg:city":"Halbturn",
    "sg:orig_category":"Dachdeckereien",
    "sg:phone":"+43 2172 8593",
    "sg:postcode":"7131",
    "sg:province":"Burgenland",
    "wof:name":"Resch Josef",
    "wof:placetype":"venue"
},
  "geometry": {"coordinates":[16.9740753174,47.8713951111],"type":"Point"}
}