{
  "type": "Feature",
  "properties": {
    "addr:full":"Wei\u00dfenbildstr 29 Lauterach Vorarlberg 6923",
    "addr:housenumber":"29",
    "addr:postcode":"6923",
    "addr:street":"Weissenbildstr",
    "iso:country":"AT",
    "sg:address":"Wei\u00dfenbildstr 29",
    "sg:city":"Lauterach",
    "sg:orig_category":"Metallbe- U -Verarbeitung",
    "sg:phone":"+43 5574 624680",
    "sg:postcode":"6923",
    "sg:province":"Vorarlberg",
    "wof:name":"Stadelmann Wolfgang",
    "wof:placetype":"venue"
},
  "geometry": {"coordinates":[9.7314901352,47.4773216248],"type":"Point"}
}