{
  "type": "Feature",
  "properties": {
    "addr:full":"Rankweil Vorarlberg 6830",
    "addr:postcode":"6830",
    "iso:country":"AT",
    "sg:city":"Rankweil",
    "sg:orig_category":"Volksschulen",
    "sg:phone":"+43 5526 324",
    "sg:postcode":"6830",
    "sg:province":"Vorarlberg",
    "wof:name":"Volksschule",
    "wof:placetype":"venue"
},
  "geometry": {"coordinates":[9.702750206,47.2661933899],"type":"Point"}
}