{
  "type": "Feature",
  "properties": {
    "iso:country":"AT",
    "sg:address":"Waldeggstr 59",
    "sg:city":"Linz",
    "sg:orig_category":"Architekten",
    "sg:phone":"+43 732 660669",
    "sg:postcode":"4020",
    "sg:province":"Ober\u00f6sterreich",
    "wof:name":"Helly Peter Prof Dipl-Ing",
    "wof:placetype":"venue"
},
  "geometry": {"coordinates":[14.2875528336,48.2873191833],"type":"Point"}
}