{
  "type": "Feature",
  "properties": {
    "addr:full":"Bergstr 11 Dornbirn Vorarlberg 6850",
    "addr:housenumber":"11",
    "addr:postcode":"6850",
    "addr:street":"Bergstr",
    "iso:country":"AT",
    "sg:address":"Bergstr 11",
    "sg:city":"Dornbirn",
    "sg:orig_category":"Maler, Anstreicher U Lackierer",
    "sg:phone":"+43 4355 7253688",
    "sg:postcode":"6850",
    "sg:province":"Vorarlberg",
    "wof:name":"Sevgi S\u00fckr\u00fc",
    "wof:placetype":"venue"
},
  "geometry": {"coordinates":[9.751540184,47.4106864929],"type":"Point"}
}