{
  "type": "Feature",
  "properties": {
    "addr:full":"Trattenbach 62 Wald im Pinzgau Salzburg 5742",
    "addr:housenumber":"62",
    "addr:postcode":"5742",
    "addr:street":"Trattenbach",
    "iso:country":"AT",
    "sg:address":"Trattenbach 62",
    "sg:city":"Wald im Pinzgau",
    "sg:classifiers":[
        {
            "category":"Travel",
            "subcategory":"Hotels & Motels",
            "type":"Entertainment"
        }
    ],
    "sg:phone":"+43 4365 656417",
    "sg:postcode":"5742",
    "sg:province":"Salzburg",
    "wof:name":"Hotel Jagdschlo\u00df Graf Recke",
    "wof:placetype":"venue"
},
  "geometry": {"coordinates":[12.2310342789,47.2461929321],"type":"Point"}
}