{
  "type": "Feature",
  "properties": {
    "addr:full":"Hauptpl 3 Horn Nieder\u00f6sterreich 3580",
    "addr:housenumber":"3",
    "addr:postcode":"3580",
    "addr:street":"Hauptpl;Niederoesterreich",
    "iso:country":"AT",
    "sg:address":"Hauptpl 3",
    "sg:city":"Horn",
    "sg:orig_category":"Friseure U Frisiersalons",
    "sg:phone":"+43 4329 824144",
    "sg:postcode":"3580",
    "sg:province":"Nieder\u00f6sterreich",
    "wof:name":"Frisurenstudio Herbert Schellenberger",
    "wof:placetype":"venue"
},
  "geometry": {"coordinates":[15.6569137573,48.6634864807],"type":"Point"}
}