{
  "type": "Feature",
  "properties": {
    "addr:full":"Baumkircher G 5 Stadtschlaining Burgenland 7461",
    "addr:housenumber":"5",
    "addr:postcode":"7461",
    "addr:street":"Baumkircher G",
    "iso:country":"AT",
    "sg:address":"Baumkircher G 5",
    "sg:city":"Stadtschlaining",
    "sg:orig_category":"Bankomat-Standorte",
    "sg:phone":"+43 4333 552223",
    "sg:postcode":"7461",
    "sg:province":"Burgenland",
    "wof:name":"Bankomat d Raiffeisenbezirksbank Oberwart regGenmbH",
    "wof:placetype":"venue"
},
  "geometry": {"coordinates":[16.2788238525,47.324256897],"type":"Point"}
}