{
  "type": "Feature",
  "properties": {
    "addr:full":"Julius Raab Pl. 1  Salzburg Salzburg 5020",
    "addr:housenumber":"1",
    "addr:postcode":"5020",
    "addr:street":"Julius Raab Pl.;Salzburg",
    "iso:country":"AT",
    "sg:address":"Julius Raab Pl. 1 ",
    "sg:city":"Salzburg",
    "sg:classifiers":[
        {
            "category":"Professional",
            "subcategory":"Business Services",
            "type":"Services"
        }
    ],
    "sg:phone":"+43 4366 288880",
    "sg:postcode":"5020",
    "sg:province":"Salzburg",
    "sg:tags":[
        "advice"
    ],
    "wof:name":"WIRTSCHAFTSKAMMER SALZBURG",
    "wof:placetype":"venue"
},
  "geometry": {"coordinates":[13.0446243286,47.808265686],"type":"Point"}
}