{
  "type": "Feature",
  "properties": {
    "iso:country":"AT",
    "sg:address":"Parkring 8",
    "sg:city":"Raaba",
    "sg:orig_category":"Werbeagenturen",
    "sg:phone":"+43 4331 62915120",
    "sg:postcode":"8074",
    "sg:province":"Steiermark",
    "wof:name":"AD-Ventures Werbeagentur GmbH",
    "wof:placetype":"venue"
},
  "geometry": {"coordinates":[15.4996156693,47.0198783875],"type":"Point"}
}