{
  "type": "Feature",
  "properties": {
    "iso:country":"AT",
    "sg:address":"Hegerg 26",
    "sg:city":"Wien",
    "sg:orig_category":"Psychotherapie",
    "sg:phone":"+43 1 7962010",
    "sg:postcode":"1030",
    "sg:province":"Wien",
    "wof:name":"Smitzitz Katja Dr",
    "wof:placetype":"venue"
},
  "geometry": {"coordinates":[16.3903331757,48.1914520264],"type":"Point"}
}