{
  "type": "Feature",
  "properties": {
    "addr:full":"Wegscheider Str 78 Linz Ober\u00f6sterreich 4020",
    "addr:postcode":"4020",
    "addr:street":"Str 78",
    "iso:country":"AT",
    "sg:address":"Wegscheider Str 78",
    "sg:city":"Linz",
    "sg:orig_category":"Bierlokale-Pubs",
    "sg:phone":"+43 732 370272",
    "sg:postcode":"4020",
    "sg:province":"Ober\u00f6sterreich",
    "wof:name":"Christa's Pub",
    "wof:placetype":"venue"
},
  "geometry": {"coordinates":[14.2719078064,48.2588996887],"type":"Point"}
}