{
  "type": "Feature",
  "properties": {
    "iso:country":"AT",
    "sg:address":"Nr 99",
    "sg:city":"Thiersee",
    "sg:orig_category":"Feuerwehren",
    "sg:phone":"+43 5376 5676",
    "sg:postcode":"6335",
    "sg:province":"Tirol",
    "wof:name":"Freiwillige Feuerwehr Thiersee",
    "wof:placetype":"venue"
},
  "geometry": {"coordinates":[12.0649995804,47.584148407],"type":"Point"}
}