{
  "type": "Feature",
  "properties": {
    "addr:full":"Nu\u00dfdorfer Strasse 68 Wien Wien 1090",
    "addr:housenumber":"68",
    "addr:postcode":"1090",
    "addr:street":"Nussdorfer Strasse",
    "iso:country":"AT",
    "sg:address":"Nu\u00dfdorfer Strasse 68",
    "sg:city":"Wien",
    "sg:classifiers":[
        {
            "category":"Manufacturing",
            "subcategory":"Tools & Machinery",
            "type":"Manufacturing & Wholesale Goods"
        }
    ],
    "sg:phone":"+43 1 3173563",
    "sg:postcode":"1090",
    "sg:province":"Wien",
    "sg:tags":[
        "bending",
        "press",
        "presses",
        "folding"
    ],
    "sg:website":"jarma.at",
    "wof:name":"Jarma Maschinen und Werkzeugbau Stanztechnik - Signiertechnik",
    "wof:placetype":"venue"
},
  "geometry": {"coordinates":[16.3550395966,48.2284622192],"type":"Point"}
}