{
  "type": "Feature",
  "properties": {
    "addr:full":"Caracallastrasse 16 Enns Ober\u00f6sterreich 4470",
    "addr:housenumber":"16",
    "addr:postcode":"4470",
    "addr:street":"Caracallastrasse",
    "iso:country":"AT",
    "sg:address":"Caracallastrasse 16",
    "sg:city":"Enns",
    "sg:classifiers":[
        {
            "category":"Military Area",
            "subcategory":"Coast Guard Base",
            "type":"Public Place"
        }
    ],
    "sg:phone":"+43 7223 814490",
    "sg:postcode":"4470",
    "sg:province":"Ober\u00f6sterreich",
    "sg:tags":[
        "grip",
        "barrel"
    ],
    "sg:website":"pfeifer.de",
    "wof:name":"Pfeifer Seil- und Hebetechnik KG",
    "wof:placetype":"venue"
},
  "geometry": {"coordinates":[14.4630470276,48.2191467285],"type":"Point"}
}