{
  "type": "Feature",
  "properties": {
    "addr:full":"Mitterweg 107 Innsbruck Tirol 6020",
    "addr:housenumber":"107",
    "addr:postcode":"6020",
    "addr:street":"Mitterweg;Tirol",
    "iso:country":"AT",
    "sg:address":"Mitterweg 107",
    "sg:city":"Innsbruck",
    "sg:orig_category":"Tischlereien",
    "sg:phone":"+43 512 282513",
    "sg:postcode":"6020",
    "sg:province":"Tirol",
    "wof:name":"Baumgartner Franz",
    "wof:placetype":"venue"
},
  "geometry": {"coordinates":[11.3659801483,47.2564964294],"type":"Point"}
}