{
  "type": "Feature",
  "properties": {
    "iso:country":"AT",
    "sg:address":"Spiegelgasse 14",
    "sg:city":"Wien",
    "sg:classifiers":[
        {
            "category":"Shopping",
            "subcategory":"Jewelry",
            "type":"Retail Goods"
        }
    ],
    "sg:phone":"+43 1 5136751",
    "sg:postcode":"1010",
    "sg:province":"Wien",
    "sg:tags":[
        "amber",
        "jewellery"
    ],
    "wof:name":"Ambros Moritz KG",
    "wof:placetype":"venue"
},
  "geometry": {"coordinates":[16.3691902161,48.2063865662],"type":"Point"}
}