{
  "type": "Feature",
  "properties": {
    "addr:full":"S\u00fcdstr 3 Loosdorf Nieder\u00f6sterreich 3382",
    "addr:housenumber":"3",
    "addr:postcode":"3382",
    "addr:street":"Suedstr",
    "iso:country":"AT",
    "sg:address":"S\u00fcdstr 3",
    "sg:city":"Loosdorf",
    "sg:classifiers":[
        {
            "category":"Personal",
            "subcategory":"Adult",
            "type":"Services"
        }
    ],
    "sg:phone":"+43 2754 73359",
    "sg:postcode":"3382",
    "sg:province":"Nieder\u00f6sterreich",
    "sg:tags":[
        "sex-shops"
    ],
    "wof:name":"BU HandelsgmbH",
    "wof:placetype":"venue"
},
  "geometry": {"coordinates":[15.3811845779,48.1837120056],"type":"Point"}
}