{
  "type": "Feature",
  "properties": {
    "iso:country":"AT",
    "sg:address":"Volderau 12",
    "sg:city":"Neustift im Stubaital",
    "sg:orig_category":"Appartements / Ferienwohnungen",
    "sg:phone":"+43 4352 262287",
    "sg:postcode":"6167",
    "sg:province":"Tirol",
    "wof:name":"Tonis Appartments - Anton Volderauer",
    "wof:placetype":"venue"
},
  "geometry": {"coordinates":[11.2553930283,47.0675201416],"type":"Point"}
}