{
  "type": "Feature",
  "properties": {
    "iso:country":"AT",
    "sg:address":"Andritzer Reichsstr 57",
    "sg:city":"Andritz",
    "sg:orig_category":"Eisenwaren",
    "sg:phone":"+43 316 692380",
    "sg:postcode":"8045",
    "sg:province":"Steiermark",
    "wof:name":"Gerhard Peter",
    "wof:placetype":"venue"
},
  "geometry": {"coordinates":[15.4204626083,47.1061935425],"type":"Point"}
}