{
  "type": "Feature",
  "properties": {
    "addr:full":"Wiesenweg 2 Wartberg im M\u00fcrztal Steiermark 8661",
    "addr:housenumber":"2",
    "addr:postcode":"8661",
    "addr:street":"Wiesenweg",
    "iso:country":"AT",
    "sg:address":"Wiesenweg 2",
    "sg:city":"Wartberg im M\u00fcrztal",
    "sg:orig_category":"Filmproduktionen",
    "sg:phone":"+43 4366 43941615",
    "sg:postcode":"8661",
    "sg:province":"Steiermark",
    "sg:website":"ap-c.at",
    "wof:name":"AP-C Andreas Pesendorfer",
    "wof:placetype":"venue"
},
  "geometry": {"coordinates":[15.4884386063,47.5222625732],"type":"Point"}
}