{
  "type": "Feature",
  "properties": {
    "addr:full":"Eben 64 Pertisau Tirol 6213",
    "addr:housenumber":"64",
    "addr:postcode":"6213",
    "addr:street":"Eben",
    "iso:country":"AT",
    "sg:address":"Eben 64",
    "sg:city":"Pertisau",
    "sg:classifiers":[
        {
            "category":"Shopping",
            "subcategory":"Gifts & Souvenirs",
            "type":"Retail Goods"
        }
    ],
    "sg:phone":"+43 5243 5606",
    "sg:postcode":"6213",
    "sg:province":"Tirol",
    "wof:name":"Tirol Souvenier",
    "wof:placetype":"venue"
},
  "geometry": {"coordinates":[11.6961479187,47.4396896362],"type":"Point"}
}