{
  "type": "Feature",
  "properties": {
    "addr:full":"Unterberg 2 Gro\u00dfarl Salzburg 5611",
    "addr:housenumber":"2",
    "addr:postcode":"5611",
    "addr:street":"Unterberg;Salzburg",
    "iso:country":"AT",
    "sg:address":"Unterberg 2",
    "sg:city":"Gro\u00dfarl",
    "sg:orig_category":"Pensionen / Privatzimmer",
    "sg:phone":"+43 6414 321",
    "sg:postcode":"5611",
    "sg:province":"Salzburg",
    "wof:name":"Hotel-Pension Roslehen Inh C\u00e4cilia Alois Ammerer",
    "wof:placetype":"venue"
},
  "geometry": {"coordinates":[13.1961202621,47.2405586243],"type":"Point"}
}