{
  "type": "Feature",
  "properties": {
    "addr:full":"Sankt-Peter-Strasse 10 Gurk K\u00e4rnten 9342",
    "addr:housenumber":"10",
    "addr:postcode":"9342",
    "addr:street":"Sankt-Peter-Strasse;Kaernten",
    "iso:country":"AT",
    "sg:address":"Sankt-Peter-Strasse 10",
    "sg:city":"Gurk",
    "sg:classifiers":[
        {
            "category":"Retail",
            "subcategory":"Storage",
            "type":"Services"
        }
    ],
    "sg:phone":"+43 4266 8163",
    "sg:postcode":"9342",
    "sg:province":"K\u00e4rnten",
    "sg:tags":[
        "fuel",
        "transportation"
    ],
    "wof:name":"Kathi Isopp Ges.m.b.H.",
    "wof:placetype":"venue"
},
  "geometry": {"coordinates":[14.2865037918,46.8744697571],"type":"Point"}
}