{
  "type": "Feature",
  "properties": {
    "addr:full":"Unterer Pl 22 St. Veit an der Glan K\u00e4rnten 9300",
    "addr:housenumber":"22",
    "addr:postcode":"9300",
    "addr:street":"Unterer Pl;Kaernten",
    "iso:country":"AT",
    "sg:address":"Unterer Pl 22",
    "sg:city":"St. Veit an der Glan",
    "sg:orig_category":"Apotheken",
    "sg:phone":"+43 4212 21580",
    "sg:postcode":"9300",
    "sg:province":"K\u00e4rnten",
    "wof:name":"B\u00e4ren-Apotheke Dr Karl Schn\u00fcrch & Co",
    "wof:placetype":"venue"
},
  "geometry": {"coordinates":[14.3587532043,46.7677116394],"type":"Point"}
}