{
  "type": "Feature",
  "properties": {
    "addr:full":"Anichstr 3 Innsbruck Tirol 6020",
    "addr:housenumber":"3",
    "addr:postcode":"6020",
    "addr:street":"Anichstr;Tirol",
    "iso:country":"AT",
    "sg:address":"Anichstr 3",
    "sg:city":"Innsbruck",
    "sg:orig_category":"Physiotherapie",
    "sg:phone":"+43 512 587760",
    "sg:postcode":"6020",
    "sg:province":"Tirol",
    "wof:name":"Schneider Helmut Dipl-PT",
    "wof:placetype":"venue"
},
  "geometry": {"coordinates":[11.3937397003,47.2649993896],"type":"Point"}
}