{
  "type": "Feature",
  "properties": {
    "addr:full":"Promenade 4 Linz Ober\u00f6sterreich 4020",
    "addr:housenumber":"4",
    "addr:postcode":"4020",
    "addr:street":"Promenade",
    "iso:country":"AT",
    "sg:address":"Promenade 4",
    "sg:city":"Linz",
    "sg:orig_category":"Damenmoden",
    "sg:phone":"+43 732 773349",
    "sg:postcode":"4020",
    "sg:province":"Ober\u00f6sterreich",
    "wof:name":"Derflinger Otto",
    "wof:placetype":"venue"
},
  "geometry": {"coordinates":[14.2877721786,48.3042297363],"type":"Point"}
}