{
  "type": "Feature",
  "properties": {
    "iso:country":"AT",
    "sg:address":"Auerspergstr 20",
    "sg:city":"Salzburg",
    "sg:orig_category":"Ingenieurkonsulenten / Zivilingenieure",
    "sg:phone":"+43 662 8827710",
    "sg:postcode":"5020",
    "sg:province":"Salzburg",
    "wof:name":"Strasser Rudolf Dipl-Ing",
    "wof:placetype":"venue"
},
  "geometry": {"coordinates":[13.044549942,47.8079452515],"type":"Point"}
}