{
  "type": "Feature",
  "properties": {
    "addr:full":"Schlo\u00dfg 5-7 Ebenfurth Nieder\u00f6sterreich 2490",
    "addr:housenumber":"5-7",
    "addr:postcode":"2490",
    "addr:street":"Schlossg",
    "iso:country":"AT",
    "sg:address":"Schlo\u00dfg 5-7",
    "sg:city":"Ebenfurth",
    "sg:orig_category":"Tischlereien",
    "sg:phone":"+43 4326 24522630",
    "sg:postcode":"2490",
    "sg:province":"Nieder\u00f6sterreich",
    "wof:name":"F\u00fcrlinger Hermann",
    "wof:placetype":"venue"
},
  "geometry": {"coordinates":[16.3694343567,47.8767471313],"type":"Point"}
}