{
  "type": "Feature",
  "properties": {
    "addr:full":"Fischerweg 6 Traun Ober\u00f6sterreich 4050",
    "addr:housenumber":"6",
    "addr:postcode":"4050",
    "addr:street":"Fischerweg",
    "iso:country":"AT",
    "sg:address":"Fischerweg 6",
    "sg:city":"Traun",
    "sg:orig_category":"Tischlereien",
    "sg:phone":"+43 7229 70737",
    "sg:postcode":"4050",
    "sg:province":"Ober\u00f6sterreich",
    "wof:name":"Hartl Josef",
    "wof:placetype":"venue"
},
  "geometry": {"coordinates":[14.2541036606,48.2230186462],"type":"Point"}
}