{
  "type": "Feature",
  "properties": {
    "addr:full":"Hauptstr 37 Wolfsgraben Nieder\u00f6sterreich 3012",
    "addr:housenumber":"37",
    "addr:postcode":"3012",
    "addr:street":"Hauptstr",
    "iso:country":"AT",
    "sg:address":"Hauptstr 37",
    "sg:city":"Wolfsgraben",
    "sg:orig_category":"Elektroinstallationsunternehmen",
    "sg:phone":"+43 2233 56812",
    "sg:postcode":"3012",
    "sg:province":"Nieder\u00f6sterreich",
    "wof:name":"Talaber Andreas - Elektro und Netzwerktechnik",
    "wof:placetype":"venue"
},
  "geometry": {"coordinates":[16.1204414368,48.1612243652],"type":"Point"}
}