{
  "type": "Feature",
  "properties": {
    "addr:full":"Krappfelder Str 28 Treibach-Althofen K\u00e4rnten 9330",
    "addr:postcode":"9330",
    "addr:street":"Str 28 Treibach-Althofen Kaernten",
    "iso:country":"AT",
    "sg:address":"Krappfelder Str 28",
    "sg:city":"Treibach-Althofen",
    "sg:orig_category":"Schlossereien",
    "sg:phone":"+43 4262 2808",
    "sg:postcode":"9330",
    "sg:province":"K\u00e4rnten",
    "wof:name":"Fally Manfred",
    "wof:placetype":"venue"
},
  "geometry": {"coordinates":[14.4634380341,46.8647460938],"type":"Point"}
}