{
  "type": "Feature",
  "properties": {
    "addr:full":"Lehrer-Frick-Strasse 2 Feldkirch Vorarlberg 6800",
    "addr:housenumber":"2",
    "addr:postcode":"6800",
    "addr:street":"Lehrer-Frick-Strasse",
    "iso:country":"AT",
    "sg:address":"Lehrer-Frick-Strasse 2",
    "sg:city":"Feldkirch",
    "sg:classifiers":[
        {
            "category":"Structure",
            "subcategory":"Building",
            "type":"Public Place"
        }
    ],
    "sg:phone":"+43 5522 75682",
    "sg:postcode":"6800",
    "sg:province":"Vorarlberg",
    "sg:tags":[
        "installation",
        "supraregional",
        "system",
        "air",
        "equipment",
        "heating"
    ],
    "wof:name":"Installationen Schakmann",
    "wof:placetype":"venue"
},
  "geometry": {"coordinates":[9.5960483551,47.2610244751],"type":"Point"}
}