{
  "type": "Feature",
  "properties": {
    "addr:full":"Eschengasse 18 Biedermannsdorf Nieder\u00f6sterreich 2362",
    "addr:housenumber":"18",
    "addr:postcode":"2362",
    "addr:street":"Eschengasse",
    "iso:country":"AT",
    "sg:address":"Eschengasse 18",
    "sg:city":"Biedermannsdorf",
    "sg:classifiers":[
        {
            "category":"Professional",
            "subcategory":"Advertising",
            "type":"Services"
        }
    ],
    "sg:phone":"+43 2236 710525",
    "sg:postcode":"2362",
    "sg:province":"Nieder\u00f6sterreich",
    "sg:tags":[
        "agency"
    ],
    "sg:website":"members.kabsi.at/twk",
    "wof:name":"Telefon Wertkarten Design & VertriebsgesmbH",
    "wof:placetype":"venue"
},
  "geometry": {"coordinates":[16.347650528,48.0901412964],"type":"Point"}
}