{
  "type": "Feature",
  "properties": {
    "addr:full":"Dorfstr 50 Bad Kleinkirchheim K\u00e4rnten 9546",
    "addr:housenumber":"50",
    "addr:postcode":"9546",
    "addr:street":"Dorfstr",
    "iso:country":"AT",
    "sg:address":"Dorfstr 50",
    "sg:city":"Bad Kleinkirchheim",
    "sg:orig_category":"Banken U Sparkassen",
    "sg:phone":"+43 4342 402310",
    "sg:postcode":"9546",
    "sg:province":"K\u00e4rnten",
    "wof:name":"Raiffeisenbank Radenthein-Bad Kleinkirchheim regGenmbH",
    "wof:placetype":"venue"
},
  "geometry": {"coordinates":[13.79210186,46.8132171631],"type":"Point"}
}