{
  "type": "Feature",
  "properties": {
    "addr:full":"Hochgatterstr 8 Enns Ober\u00f6sterreich 4470",
    "addr:housenumber":"8",
    "addr:postcode":"4470",
    "addr:street":"Hochgatterstr",
    "iso:country":"AT",
    "sg:address":"Hochgatterstr 8",
    "sg:city":"Enns",
    "sg:orig_category":"Fenster",
    "sg:phone":"+43 7223 89272",
    "sg:postcode":"4470",
    "sg:province":"Ober\u00f6sterreich",
    "wof:name":"Studirach Josef",
    "wof:placetype":"venue"
},
  "geometry": {"coordinates":[14.4596242905,48.2149238586],"type":"Point"}
}