{
  "type": "Feature",
  "properties": {
    "addr:full":"Maria-Theresien-Str 24/4 Wien Wien 1010",
    "addr:housenumber":"24 / 4",
    "addr:postcode":"1010",
    "addr:street":"Maria-Theresien-Str",
    "iso:country":"AT",
    "sg:address":"Maria-Theresien-Str 24/4",
    "sg:city":"Wien",
    "sg:orig_category":"Forschungsinstitute",
    "sg:phone":"+43 1 3194445",
    "sg:postcode":"1010",
    "sg:province":"Wien",
    "wof:name":"PLG Paul Lazarsfeld Gesellschaft f Sozialforschung",
    "wof:placetype":"venue"
},
  "geometry": {"coordinates":[16.3671703339,48.2168617249],"type":"Point"}
}