{
  "type": "Feature",
  "properties": {
    "addr:full":"Johann-Wilhelm-Klein-Str 13 Linz Ober\u00f6sterreich 4040",
    "addr:housenumber":"13",
    "addr:postcode":"4040",
    "addr:street":"Johann-Wilhelm-Klein-Str",
    "iso:country":"AT",
    "sg:address":"Johann-Wilhelm-Klein-Str 13",
    "sg:city":"Linz",
    "sg:orig_category":"Lebensmittel / Einzelhandel",
    "sg:phone":"+43 4373 2246003",
    "sg:postcode":"4040",
    "sg:province":"Ober\u00f6sterreich",
    "wof:name":"SPAR \u00f6sterreichische Warenhandels-AG",
    "wof:placetype":"venue"
},
  "geometry": {"coordinates":[14.2578554153,48.3602561951],"type":"Point"}
}