{
  "type": "Feature",
  "properties": {
    "iso:country":"AT",
    "sg:address":"Hauptstrasse 48",
    "sg:city":"Henndorf am Wallersee",
    "sg:classifiers":[
        {
            "category":"Communications",
            "subcategory":"Television Station",
            "type":"Services"
        }
    ],
    "sg:phone":"+43 6214 6608",
    "sg:postcode":"5302",
    "sg:province":"Salzburg",
    "sg:tags":[
        "array",
        "satellite",
        "aerial",
        "reception",
        "antenna"
    ],
    "sg:website":"elektro-langer.at",
    "wof:name":"Elektrotechnik Langer GmbH",
    "wof:placetype":"venue"
},
  "geometry": {"coordinates":[13.1875696182,47.8980903625],"type":"Point"}
}