{
  "type": "Feature",
  "properties": {
    "iso:country":"AT",
    "sg:address":"Negrellistr. 61 ",
    "sg:city":"Wels",
    "sg:classifiers":[
        {
            "category":"Wholesale",
            "subcategory":"Machinery & Supplies",
            "type":"Manufacturing & Wholesale Goods"
        }
    ],
    "sg:phone":"+43 4372 4261041",
    "sg:postcode":"4600",
    "sg:province":"Ober\u00f6sterreich",
    "sg:tags":[
        "-",
        "agriculture",
        "equipment"
    ],
    "wof:name":"MAT-IMPORT GES.MBH",
    "wof:placetype":"venue"
},
  "geometry": {"coordinates":[14.0584487915,48.1649208069],"type":"Point"}
}