{
  "type": "Feature",
  "properties": {
    "addr:full":"Linzer Str 195 Gablitz Nieder\u00f6sterreich 3003",
    "addr:housenumber":"195",
    "addr:postcode":"3003",
    "addr:street":"Linzer Str",
    "iso:country":"AT",
    "sg:address":"Linzer Str 195",
    "sg:city":"Gablitz",
    "sg:orig_category":"Sondermaschinenbau",
    "sg:phone":"+43 4322 3167575",
    "sg:postcode":"3003",
    "sg:province":"Nieder\u00f6sterreich",
    "wof:name":"Macho G\u00fcnter - Feinmechanik u Vorrichtungsbau",
    "wof:placetype":"venue"
},
  "geometry": {"coordinates":[16.1347408295,48.2403793335],"type":"Point"}
}