{
  "type": "Feature",
  "properties": {
    "addr:full":"Gamlitzer Str 103 Ehrenhausen Steiermark 8461",
    "addr:housenumber":"103",
    "addr:postcode":"8461",
    "iso:country":"AT",
    "sg:address":"Gamlitzer Str 103",
    "sg:city":"Ehrenhausen",
    "sg:orig_category":"Sektkellereien",
    "sg:phone":"+43 4334 5321280",
    "sg:postcode":"8461",
    "sg:province":"Steiermark",
    "wof:name":"Sieber Winery Inc",
    "wof:placetype":"venue"
},
  "geometry": {"coordinates":[15.5851249695,46.7201652527],"type":"Point"}
}