{
  "type": "Feature",
  "properties": {
    "iso:country":"AT",
    "sg:address":"Tiefenbachstr 36a",
    "sg:city":"Elixhausen",
    "sg:orig_category":"Handelsagenturen",
    "sg:phone":"+43 662 480078",
    "sg:postcode":"5161",
    "sg:province":"Salzburg",
    "wof:name":"Ortner Wolfgang",
    "wof:placetype":"venue"
},
  "geometry": {"coordinates":[13.0728759766,47.8664894104],"type":"Point"}
}