{
  "type": "Feature",
  "properties": {
    "addr:full":"Oberdam\u00fcls 148 Dam\u00fcls Vorarlberg 6884",
    "addr:housenumber":"148",
    "addr:postcode":"6884",
    "addr:street":"Oberdamuels",
    "iso:country":"AT",
    "sg:address":"Oberdam\u00fcls 148",
    "sg:city":"Dam\u00fcls",
    "sg:orig_category":"Pensionen / Privatzimmer",
    "sg:phone":"+43 5510 2280",
    "sg:postcode":"6884",
    "sg:province":"Vorarlberg",
    "sg:website":"www.tiscover.com/lucia",
    "wof:name":"Gasthof-Pension Lucia",
    "wof:placetype":"venue"
},
  "geometry": {"coordinates":[9.8766202927,47.2910194397],"type":"Point"}
}