{
  "type": "Feature",
  "properties": {
    "addr:full":"Marchfeldstrasse 4 Wien Wien 1200",
    "addr:housenumber":"4",
    "addr:postcode":"1200",
    "addr:street":"Marchfeldstrasse",
    "iso:country":"AT",
    "sg:address":"Marchfeldstrasse 4",
    "sg:city":"Wien",
    "sg:orig_category":"Delicatessen, Vegetarian",
    "sg:phone":"+43 1 3325427",
    "sg:postcode":"1200",
    "sg:province":"Wien",
    "wof:name":"Vegetarische Feinkost Produktion Peter Hiel",
    "wof:placetype":"venue"
},
  "geometry": {"coordinates":[16.377986908,48.2411384583],"type":"Point"}
}