{
  "type": "Feature",
  "properties": {
    "addr:full":"Technikerstr 9b Innsbruck Tirol 6020",
    "addr:housenumber":"9b",
    "addr:postcode":"6020",
    "addr:street":"Technikerstr;Tirol",
    "iso:country":"AT",
    "sg:address":"Technikerstr 9b",
    "sg:city":"Innsbruck",
    "sg:classifiers":[
        {
            "category":"Restaurant",
            "type":"Food & Drink"
        }
    ],
    "sg:phone":"+43 512 282449",
    "sg:postcode":"6020",
    "sg:province":"Tirol",
    "wof:name":"Papa Jolly's",
    "wof:placetype":"venue"
},
  "geometry": {"coordinates":[11.3471450806,47.2639389038],"type":"Point"}
}