{
  "type": "Feature",
  "properties": {
    "addr:full":"Schopperpl 13 Aschach an der Donau Ober\u00f6sterreich 4082",
    "addr:housenumber":"13",
    "addr:postcode":"4082",
    "addr:street":"Schopperpl",
    "iso:country":"AT",
    "sg:address":"Schopperpl 13",
    "sg:city":"Aschach an der Donau",
    "sg:orig_category":"Tourismusinformation U -Organisationen",
    "sg:phone":"+43 4372 737000",
    "sg:postcode":"4082",
    "sg:province":"Ober\u00f6sterreich",
    "wof:name":"WGD Tourismus GmbH",
    "wof:placetype":"venue"
},
  "geometry": {"coordinates":[14.0215539932,48.3821640015],"type":"Point"}
}