{
  "type": "Feature",
  "properties": {
    "addr:full":"Erdbergstrasse 47 Wien Wien 1030",
    "addr:housenumber":"47",
    "addr:postcode":"1030",
    "addr:street":"Erdbergstrasse",
    "iso:country":"AT",
    "sg:address":"Erdbergstrasse 47",
    "sg:city":"Wien",
    "sg:classifiers":[
        {
            "category":"Professional",
            "subcategory":"Advertising",
            "type":"Services"
        }
    ],
    "sg:phone":"+43 1 7128291",
    "sg:postcode":"1030",
    "sg:province":"Wien",
    "sg:tags":[
        "flag",
        "banner"
    ],
    "sg:website":"fahnenprofi.at",
    "wof:name":"MARGARETE SCEVIK Ges.m.b.H.",
    "wof:placetype":"venue"
},
  "geometry": {"coordinates":[16.3986988068,48.2001533508],"type":"Point"}
}