{
  "type": "Feature",
  "properties": {
    "addr:full":"Eyerspergring 4 Wiener Neustadt Nieder\u00f6sterreich 2700",
    "addr:housenumber":"4",
    "addr:postcode":"2700",
    "addr:street":"Eyerspergring",
    "iso:country":"AT",
    "sg:address":"Eyerspergring 4",
    "sg:city":"Wiener Neustadt",
    "sg:orig_category":"Weiterbildungsinstitute M Allg U Berufl Bildungsangebot",
    "sg:phone":"+43 4326 2223088",
    "sg:postcode":"2700",
    "sg:province":"Nieder\u00f6sterreich",
    "wof:name":"Business Coaching Partners GmbH",
    "wof:placetype":"venue"
},
  "geometry": {"coordinates":[16.2453155518,47.8160247803],"type":"Point"}
}