{
  "type": "Feature",
  "properties": {
    "addr:full":"Sch\u00e4fferhofstrasse 14 Hard Vorarlberg 6971",
    "addr:housenumber":"14",
    "addr:postcode":"6971",
    "addr:street":"Schaefferhofstrasse",
    "iso:country":"AT",
    "sg:address":"Sch\u00e4fferhofstrasse 14",
    "sg:city":"Hard",
    "sg:classifiers":[
        {
            "category":"Food & Beverages",
            "subcategory":"Groceries & Convenience Stores",
            "type":"Retail Goods"
        }
    ],
    "sg:phone":"+43 5574 6940",
    "sg:postcode":"6971",
    "sg:province":"Vorarlberg",
    "sg:tags":[
        "frozen",
        "goods",
        "baked"
    ],
    "sg:website":"huegli.com",
    "wof:name":"H\u00fcgli N\u00e4hrmittel Erzeugung Ges.m.b.H.",
    "wof:placetype":"venue"
},
  "geometry": {"coordinates":[9.7137718201,47.4871253967],"type":"Point"}
}