{
  "type": "Feature",
  "properties": {
    "addr:full":"Schulg 2 Wien Wien 1180",
    "addr:housenumber":"2",
    "addr:postcode":"1180",
    "addr:street":"Schulg",
    "iso:country":"AT",
    "sg:address":"Schulg 2",
    "sg:city":"Wien",
    "sg:classifiers":[
        {
            "category":"Retail",
            "subcategory":"Event Space",
            "type":"Services"
        }
    ],
    "sg:phone":"+43 1 4054542",
    "sg:postcode":"1180",
    "sg:province":"Wien",
    "sg:tags":[
        "hand-",
        "u",
        "fu\u00c3\u0178pflege"
    ],
    "wof:name":"Pausch Gertrude GesmbH",
    "wof:placetype":"venue"
},
  "geometry": {"coordinates":[16.3487319946,48.2247581482],"type":"Point"}
}