{
  "type": "Feature",
  "properties": {
    "addr:full":"Schulstr 223 Feistritz an der Drau K\u00e4rnten 9710",
    "addr:housenumber":"223",
    "addr:postcode":"9710",
    "iso:country":"AT",
    "sg:address":"Schulstr 223",
    "sg:city":"Feistritz an der Drau",
    "sg:orig_category":"Musikunterricht",
    "sg:phone":"+43 4245 25102",
    "sg:postcode":"9710",
    "sg:province":"K\u00e4rnten",
    "wof:name":"Musikschule",
    "wof:placetype":"venue"
},
  "geometry": {"coordinates":[13.6812143326,46.6893577576],"type":"Point"}
}