{
  "type": "Feature",
  "properties": {
    "addr:full":"Kollergerng 6 Wien Wien 1060",
    "addr:housenumber":"6",
    "addr:postcode":"1060",
    "addr:street":"Kollergerng",
    "iso:country":"AT",
    "sg:address":"Kollergerng 6",
    "sg:city":"Wien",
    "sg:orig_category":"Banken U Sparkassen",
    "sg:phone":"+43 4350 10020612",
    "sg:postcode":"1060",
    "sg:province":"Wien",
    "wof:name":"Erste Bank d oesterreichischen Sparkassen AG",
    "wof:placetype":"venue"
},
  "geometry": {"coordinates":[16.351392746,48.198638916],"type":"Point"}
}