{
  "type": "Feature",
  "properties": {
    "addr:full":"Ennser Str 54a Gleink Ober\u00f6sterreich 4407",
    "addr:housenumber":"54a",
    "addr:postcode":"4407",
    "addr:street":"Str",
    "iso:country":"AT",
    "sg:address":"Ennser Str 54a",
    "sg:city":"Gleink",
    "sg:orig_category":"Bauunternehmen",
    "sg:phone":"+43 7252 85080",
    "sg:postcode":"4407",
    "sg:province":"Ober\u00f6sterreich",
    "wof:name":"Alpine Mayreder Bau GmbH",
    "wof:placetype":"venue"
},
  "geometry": {"coordinates":[14.4239358902,48.070602417],"type":"Point"}
}