{
  "type": "Feature",
  "properties": {
    "addr:full":"Mozartstr 17 Linz Ober\u00f6sterreich 4020",
    "addr:housenumber":"17",
    "addr:postcode":"4020",
    "addr:street":"Mozartstr",
    "iso:country":"AT",
    "sg:address":"Mozartstr 17",
    "sg:city":"Linz",
    "sg:orig_category":"Geschenkartikel",
    "sg:phone":"+43 732 792293",
    "sg:postcode":"4020",
    "sg:province":"Ober\u00f6sterreich",
    "wof:name":"Sammelsurium Hannelore Klinger",
    "wof:placetype":"venue"
},
  "geometry": {"coordinates":[14.2926950455,48.3014945984],"type":"Point"}
}