{
  "type": "Feature",
  "properties": {
    "iso:country":"AT",
    "sg:address":"Dr.-Schauer-Str 6",
    "sg:city":"Wels",
    "sg:orig_category":"Friseure U Frisiersalons",
    "sg:phone":"+43 4372 4258225",
    "sg:postcode":"4600",
    "sg:province":"Ober\u00f6sterreich",
    "wof:name":"Gutwein Hermann",
    "wof:placetype":"venue"
},
  "geometry": {"coordinates":[14.0303049088,48.1621665955],"type":"Point"}
}