{
  "type": "Feature",
  "properties": {
    "iso:country":"AT",
    "sg:address":"Absbergg 47",
    "sg:city":"Wien",
    "sg:orig_category":"Umwelttechnik",
    "sg:phone":"+43 5 06260",
    "sg:postcode":"1100",
    "sg:province":"Wien",
    "wof:name":"Porr Umwelttechnik GesmbH",
    "wof:placetype":"venue"
},
  "geometry": {"coordinates":[16.3872184753,48.1684799194],"type":"Point"}
}