{
  "type": "Feature",
  "properties": {
    "addr:full":"Etrichstr. 12 Wels Ober\u00f6sterreich 4600",
    "addr:housenumber":"12",
    "addr:postcode":"4600",
    "addr:street":"Etrichstr.;Oberoesterreich",
    "iso:country":"AT",
    "sg:address":"Etrichstr. 12",
    "sg:city":"Wels",
    "sg:classifiers":[
        {
            "category":"Shopping",
            "subcategory":"Clothing, Apparel, & Fashions",
            "type":"Retail Goods"
        }
    ],
    "sg:phone":"+43 4372 42613340",
    "sg:postcode":"4600",
    "sg:province":"Ober\u00f6sterreich",
    "sg:tags":[
        "clothing",
        "accessory"
    ],
    "wof:name":"CONDOR-G\u00dcRTEL GES. MBH",
    "wof:placetype":"venue"
},
  "geometry": {"coordinates":[14.067609787,48.1780319214],"type":"Point"}
}