{
  "type": "Feature",
  "properties": {
    "addr:full":"Parkstr 2/6 Salzburg Salzburg 5020",
    "addr:housenumber":"2 / 6",
    "addr:postcode":"5020",
    "addr:street":"Parkstr;Salzburg",
    "iso:country":"AT",
    "sg:address":"Parkstr 2/6",
    "sg:city":"Salzburg",
    "sg:orig_category":"Werbeagenturen",
    "sg:phone":"+43 662 642484",
    "sg:postcode":"5020",
    "sg:province":"Salzburg",
    "wof:name":"Windhagauer & Partner Werbeagentur GesmbH",
    "wof:placetype":"venue"
},
  "geometry": {"coordinates":[13.0698871613,47.8001060486],"type":"Point"}
}