{
  "type": "Feature",
  "properties": {
    "iso:country":"AT",
    "sg:address":"Schilfweg 2",
    "sg:city":"Fu\u00dfach",
    "sg:orig_category":"Schalungen / Verleih",
    "sg:phone":"+43 5578 72630",
    "sg:postcode":"6972",
    "sg:province":"Vorarlberg",
    "wof:name":"Stibo GmbH",
    "wof:placetype":"venue"
},
  "geometry": {"coordinates":[-79.8480834961,39.8919715881],"type":"Point"}
}