{
  "type": "Feature",
  "properties": {
    "addr:full":"Fasaneriestr. 35  Salzburg Salzburg 5020",
    "addr:housenumber":"35",
    "addr:postcode":"5020",
    "addr:street":"Fasaneriestr.;Salzburg",
    "iso:country":"AT",
    "sg:address":"Fasaneriestr. 35 ",
    "sg:city":"Salzburg",
    "sg:classifiers":[
        {
            "category":"Autos & Motor Vehicles",
            "subcategory":"Automobile Sales",
            "type":"Retail Goods"
        }
    ],
    "sg:phone":"+43 4366 244780",
    "sg:postcode":"5020",
    "sg:province":"Salzburg",
    "sg:tags":[
        "industrial"
    ],
    "wof:name":"MERCEDES BENZ OSTERREICH VERTRIEBS GESMBH",
    "wof:placetype":"venue"
},
  "geometry": {"coordinates":[13.0284557343,47.8170471191],"type":"Point"}
}