{
  "type": "Feature",
  "properties": {
    "addr:full":"Annenstr 50 Graz Steiermark 8020",
    "addr:housenumber":"50",
    "addr:postcode":"8020",
    "addr:street":"Annenstr",
    "iso:country":"AT",
    "sg:address":"Annenstr 50",
    "sg:city":"Graz",
    "sg:classifiers":[
        {
            "category":"Internet Cafe",
            "subcategory":"None",
            "type":"Food & Drink"
        }
    ],
    "sg:phone":"+43 4331 6713948",
    "sg:postcode":"8020",
    "sg:province":"Steiermark",
    "sg:website":"sevian7.com",
    "wof:name":"sevian7 IT Development GmbH",
    "wof:placetype":"venue"
},
  "geometry": {"coordinates":[15.4236726761,47.0714073181],"type":"Point"}
}