{
  "type": "Feature",
  "properties": {
    "addr:full":"Meidlinger Hauptstr 61 Wien Wien 1120",
    "addr:housenumber":"61",
    "addr:postcode":"1120",
    "addr:street":"Meidlinger Hauptstr",
    "iso:country":"AT",
    "sg:address":"Meidlinger Hauptstr 61",
    "sg:city":"Wien",
    "sg:orig_category":"Fotoausarbeitungen",
    "sg:phone":"+43 1 8121850",
    "sg:postcode":"1120",
    "sg:province":"Wien",
    "wof:name":"Bildermacher",
    "wof:placetype":"venue"
},
  "geometry": {"coordinates":[16.3304023743,48.1760177612],"type":"Point"}
}