{
  "type": "Feature",
  "properties": {
    "iso:country":"AT",
    "sg:address":"Zieglerg 77",
    "sg:city":"Wien",
    "sg:orig_category":"Offsetdruckereien",
    "sg:phone":"+43 1 5235573",
    "sg:postcode":"1070",
    "sg:province":"Wien",
    "wof:name":"Koisser Otto & Co KG",
    "wof:placetype":"venue"
},
  "geometry": {"coordinates":[16.3447875977,48.2061271667],"type":"Point"}
}