{
  "type": "Feature",
  "properties": {
    "addr:full":"Viktor-Franz-Hess-Str 16 Innsbruck Tirol 6020",
    "addr:housenumber":"16",
    "addr:postcode":"6020",
    "addr:street":"Viktor-Franz-Hess-Str;Tirol",
    "iso:country":"AT",
    "sg:address":"Viktor-Franz-Hess-Str 16",
    "sg:city":"Innsbruck",
    "sg:orig_category":"Detekteien",
    "sg:phone":"+43 4351 2288175",
    "sg:postcode":"6020",
    "sg:province":"Tirol",
    "wof:name":"Detektei P.O.M",
    "wof:placetype":"venue"
},
  "geometry": {"coordinates":[11.3470754623,47.2667999268],"type":"Point"}
}