{
  "type": "Feature",
  "properties": {
    "iso:country":"AT",
    "sg:address":"Leonhardpl 3",
    "sg:city":"Graz",
    "sg:orig_category":"Apotheken",
    "sg:phone":"+43 316 3221030",
    "sg:postcode":"8010",
    "sg:province":"Steiermark",
    "sg:website":"leonhard-apotheke.com",
    "wof:name":"Apotheke Zum heiligen Leonhard Mag pharm Brettner KG",
    "wof:placetype":"venue"
},
  "geometry": {"coordinates":[15.4639081955,47.0785942078],"type":"Point"}
}