{
  "type": "Feature",
  "properties": {
    "iso:country":"AT",
    "sg:address":"Weekendstra\u00dfe I 32",
    "sg:city":"Neufeld an der Leitha",
    "sg:orig_category":"Marketingberatung",
    "sg:phone":"+43 4326 2454414",
    "sg:postcode":"2491",
    "sg:province":"Burgenland",
    "wof:name":"LEAD-TECH Marketing Consulting GmbH",
    "wof:placetype":"venue"
},
  "geometry": {"coordinates":[16.3767261505,47.8670654297],"type":"Point"}
}