{
  "type": "Feature",
  "properties": {
    "iso:country":"AT",
    "sg:address":"K\u00e4rntner Strasse 512",
    "sg:city":"Stra\u00dfgang",
    "sg:orig_category":"Electric Motor-Driven Cable Pulls",
    "sg:phone":"+43 316 283558",
    "sg:postcode":"8054",
    "sg:province":"Steiermark",
    "sg:website":"krasser-seilwinden.at",
    "wof:name":"Krasser Seilwinden Inh. Alfred Krasser",
    "wof:placetype":"venue"
},
  "geometry": {"coordinates":[15.3988399506,47.0139694214],"type":"Point"}
}