{
  "type": "Feature",
  "properties": {
    "iso:country":"AT",
    "sg:address":"Fabriksstr 2",
    "sg:city":"Pitten",
    "sg:orig_category":"Tischlereien",
    "sg:phone":"+43 2627 82111",
    "sg:postcode":"2823",
    "sg:province":"Nieder\u00f6sterreich",
    "wof:name":"Kaltenbacher Peter",
    "wof:placetype":"venue"
},
  "geometry": {"coordinates":[16.1942920685,47.7202072144],"type":"Point"}
}