{
  "type": "Feature",
  "properties": {
    "iso:country":"AT",
    "sg:address":"Gramartstr 8",
    "sg:city":"Innsbruck",
    "sg:orig_category":"Feuerwehren",
    "sg:phone":"+43 512 292429",
    "sg:postcode":"6020",
    "sg:province":"Tirol",
    "wof:name":"Freiwillige Feuerwehr Hungerburg",
    "wof:placetype":"venue"
},
  "geometry": {"coordinates":[11.395198822,47.2862091064],"type":"Point"}
}