{
  "type": "Feature",
  "properties": {
    "iso:country":"AT",
    "sg:address":"Nr 28",
    "sg:city":"Stall",
    "sg:orig_category":"Non-Classified Establishments",
    "sg:phone":"+43 4823 323",
    "sg:postcode":"9832",
    "sg:province":"K\u00e4rnten",
    "wof:name":"Pfarramt",
    "wof:placetype":"venue"
},
  "geometry": {"coordinates":[13.0356664658,46.8876571655],"type":"Point"}
}