{
  "type": "Feature",
  "properties": {
    "addr:full":"Pfaffendorf 11 St. Georgen im Lavanttal K\u00e4rnten 9423",
    "addr:housenumber":"11",
    "addr:postcode":"9423",
    "addr:street":"Pfaffendorf",
    "iso:country":"AT",
    "sg:address":"Pfaffendorf 11",
    "sg:city":"St. Georgen im Lavanttal",
    "sg:classifiers":[
        {
            "category":"Organizations",
            "subcategory":"Professional Association",
            "type":"Services"
        }
    ],
    "sg:phone":"+43 4357 2143",
    "sg:postcode":"9423",
    "sg:province":"K\u00e4rnten",
    "sg:tags":[
        "control",
        "industrial"
    ],
    "wof:name":"Elektro Wagner- Fernsehservicecenter KG",
    "wof:placetype":"venue"
},
  "geometry": {"coordinates":[14.9159784317,46.7182693481],"type":"Point"}
}