{
  "type": "Feature",
  "properties": {
    "iso:country":"AT",
    "sg:address":"Semleitnerweg 21",
    "sg:city":"Walding",
    "sg:classifiers":[
        {
            "category":"Shopping",
            "subcategory":"Party Supplies",
            "type":"Retail Goods"
        }
    ],
    "sg:phone":"+43 676 4018754",
    "sg:postcode":"4111",
    "sg:province":"Ober\u00f6sterreich",
    "sg:tags":[
        "u",
        "lichtanlagen",
        "ton-"
    ],
    "wof:name":"Sound & Design Inh Michael Oberhofer",
    "wof:placetype":"venue"
},
  "geometry": {"coordinates":[14.1419754028,48.358757019],"type":"Point"}
}