{
  "type": "Feature",
  "properties": {
    "addr:full":"Untere Dorfstr 2 Gallneukirchen Ober\u00f6sterreich 4210",
    "addr:housenumber":"2",
    "addr:postcode":"4210",
    "addr:street":"Untere Dorfstr;Oberoesterreich",
    "iso:country":"AT",
    "sg:address":"Untere Dorfstr 2",
    "sg:city":"Gallneukirchen",
    "sg:orig_category":"Banken U Sparkassen",
    "sg:phone":"+43 4372 35627300",
    "sg:postcode":"4210",
    "sg:province":"Ober\u00f6sterreich",
    "wof:name":"Raiffeisenbank Region Gallneukirchen regGenmbH",
    "wof:placetype":"venue"
},
  "geometry": {"coordinates":[14.4670600891,48.3677825928],"type":"Point"}
}