{
  "type": "Feature",
  "properties": {
    "addr:full":"Schwarzenbach 10 St. Wolfgang im Salzkammergut Ober\u00f6sterreich 5360",
    "addr:housenumber":"10",
    "addr:postcode":"5360",
    "addr:street":"Schwarzenbach",
    "iso:country":"AT",
    "sg:address":"Schwarzenbach 10",
    "sg:city":"St. Wolfgang im Salzkammergut",
    "sg:orig_category":"Pensionen / Privatzimmer",
    "sg:phone":"+43 4361 383472",
    "sg:postcode":"5360",
    "sg:province":"Ober\u00f6sterreich",
    "wof:name":"Raudaschlhof",
    "wof:placetype":"venue"
},
  "geometry": {"coordinates":[13.4782447815,47.7303886414],"type":"Point"}
}