{
  "type": "Feature",
  "properties": {
    "addr:full":"Nr 81 St. Lorenzen im Lesachtal K\u00e4rnten 9654",
    "addr:postcode":"9654",
    "addr:street":"Nr 81",
    "iso:country":"AT",
    "sg:address":"Nr 81",
    "sg:city":"St. Lorenzen im Lesachtal",
    "sg:orig_category":"Volksschulen",
    "sg:phone":"+43 4347 16247",
    "sg:postcode":"9654",
    "sg:province":"K\u00e4rnten",
    "wof:name":"Volksschule",
    "wof:placetype":"venue"
},
  "geometry": {"coordinates":[12.7822761536,46.7015838623],"type":"Point"}
}