{
  "type": "Feature",
  "properties": {
    "iso:country":"AT",
    "sg:address":"Josef-Krainer-Str 5",
    "sg:city":"Raaba",
    "sg:orig_category":"Fleischhauereien",
    "sg:phone":"+43 316 401212",
    "sg:postcode":"8074",
    "sg:province":"Steiermark",
    "wof:name":"Sch\u00f6nberger Karl",
    "wof:placetype":"venue"
},
  "geometry": {"coordinates":[15.4931173325,47.0349617004],"type":"Point"}
}