{
  "type": "Feature",
  "properties": {
    "addr:full":"Sch\u00f6nbrunn Tierg Wien Wien 1130",
    "addr:postcode":"1130",
    "iso:country":"AT",
    "sg:address":"Sch\u00f6nbrunn Tierg",
    "sg:city":"Wien",
    "sg:orig_category":"Bankomat-Standorte",
    "sg:phone":"+43 800 204880",
    "sg:postcode":"1130",
    "sg:province":"Wien",
    "wof:name":"Bankomat d Bank Austria Creditanstalt AG",
    "wof:placetype":"venue"
},
  "geometry": {"coordinates":[16.3013801575,48.18592453],"type":"Point"}
}