{
  "type": "Feature",
  "properties": {
    "addr:full":"Nr 23 Bad Blumau Steiermark 8283",
    "addr:housenumber":"23",
    "addr:postcode":"8283",
    "addr:street":"Nr",
    "iso:country":"AT",
    "sg:address":"Nr 23",
    "sg:city":"Bad Blumau",
    "sg:orig_category":"Volksschulen",
    "sg:phone":"+43 3383 2244",
    "sg:postcode":"8283",
    "sg:province":"Steiermark",
    "wof:name":"Volksschule Bad Blumau",
    "wof:placetype":"venue"
},
  "geometry": {"coordinates":[16.0523548126,47.1159667969],"type":"Point"}
}