{
  "type": "Feature",
  "properties": {
    "addr:full":"Hart 65  Pischelsdorf in Steiermark Steiermark 8212",
    "addr:housenumber":"65",
    "addr:postcode":"8212",
    "addr:street":"Hart",
    "iso:country":"AT",
    "sg:address":"Hart 65 ",
    "sg:city":"Pischelsdorf in Steiermark",
    "sg:orig_category":"CarpenterS Work Supraregional",
    "sg:phone":"+43 3113 3388",
    "sg:postcode":"8212",
    "sg:province":"Steiermark",
    "sg:website":"www.kulmer-bau.at",
    "wof:name":"Kulmer Holz-Leimbau Ges.m.b.H.",
    "wof:placetype":"venue"
},
  "geometry": {"coordinates":[15.8060102463,47.1733627319],"type":"Point"}
}