{
  "type": "Feature",
  "properties": {
    "addr:full":"Grazer Bundesstr 33 Gnigl Salzburg 5023",
    "addr:housenumber":"33",
    "addr:postcode":"5023",
    "iso:country":"AT",
    "sg:address":"Grazer Bundesstr 33",
    "sg:city":"Gnigl",
    "sg:orig_category":"Non-Classified Establishments",
    "sg:phone":"+43 662 640371",
    "sg:postcode":"5023",
    "sg:province":"Salzburg",
    "wof:name":"Schwarzmaier Martin",
    "wof:placetype":"venue"
},
  "geometry": {"coordinates":[13.0792722702,47.8140106201],"type":"Point"}
}