{
  "type": "Feature",
  "properties": {
    "addr:full":"Fischamender Str 31 Schwadorf Nieder\u00f6sterreich 2432",
    "addr:postcode":"2432",
    "addr:street":"Str;Schwadorf",
    "iso:country":"AT",
    "sg:address":"Fischamender Str 31",
    "sg:city":"Schwadorf",
    "sg:orig_category":"Abfallentsorgung U -Verwertung",
    "sg:phone":"+43 4322 3027230",
    "sg:postcode":"2432",
    "sg:province":"Nieder\u00f6sterreich",
    "wof:name":"Lengel GesmbH",
    "wof:placetype":"venue"
},
  "geometry": {"coordinates":[16.5861625671,48.0724945068],"type":"Point"}
}