{
  "type": "Feature",
  "properties": {
    "addr:full":"Spiegelg 21 Wien Wien 1010",
    "addr:housenumber":"21",
    "addr:postcode":"1010",
    "addr:street":"Spiegelg",
    "iso:country":"AT",
    "sg:address":"Spiegelg 21",
    "sg:city":"Wien",
    "sg:orig_category":"Beleuchtung",
    "sg:phone":"+43 1 5123720",
    "sg:postcode":"1010",
    "sg:province":"Wien",
    "sg:website":"www.schreinerleuchten.at",
    "wof:name":"Schreiner Leuchten GesmbH",
    "wof:placetype":"venue"
},
  "geometry": {"coordinates":[16.3694496155,48.2061576843],"type":"Point"}
}