{
  "type": "Feature",
  "properties": {
    "addr:full":"Nr 129 Raggal Vorarlberg 6741",
    "addr:postcode":"6741",
    "addr:street":"Nr 129",
    "iso:country":"AT",
    "sg:address":"Nr 129",
    "sg:city":"Raggal",
    "sg:orig_category":"Appartements / Ferienwohnungen",
    "sg:phone":"+43 5553 205",
    "sg:postcode":"6741",
    "sg:province":"Vorarlberg",
    "wof:name":"Appartementhaus Toya",
    "wof:placetype":"venue"
},
  "geometry": {"coordinates":[9.8354673386,47.2117118835],"type":"Point"}
}