{
  "type": "Feature",
  "properties": {
    "iso:country":"AT",
    "sg:city":"W\u00f6rgl",
    "sg:orig_category":"Feuerwehren",
    "sg:phone":"+43 5335 4242",
    "sg:postcode":"6300",
    "sg:province":"Tirol",
    "wof:name":"Freiwillige Feuerwehr Ittler",
    "wof:placetype":"venue"
},
  "geometry": {"coordinates":[12.1438121796,47.4709892273],"type":"Point"}
}