{
  "type": "Feature",
  "properties": {
    "addr:full":"Possingerg 12-26 Wien Wien 1160",
    "addr:postcode":"12-26;1160",
    "iso:country":"AT",
    "sg:address":"Possingerg 12-26",
    "sg:city":"Wien",
    "sg:orig_category":"Fliesen- U Plattenverlegungen, Fliesen U Platten",
    "sg:phone":"+43 1 4920760",
    "sg:postcode":"1160",
    "sg:province":"Wien",
    "sg:website":"www.prims.at",
    "wof:name":"Prims & Co GesmbH",
    "wof:placetype":"venue"
},
  "geometry": {"coordinates":[16.317653656,48.2067451477],"type":"Point"}
}