{
  "type": "Feature",
  "properties": {
    "addr:full":"Georgenberg 34 Kuchl Salzburg 5431",
    "addr:housenumber":"34",
    "addr:postcode":"5431",
    "addr:street":"Georgenberg;Salzburg",
    "iso:country":"AT",
    "sg:address":"Georgenberg 34",
    "sg:city":"Kuchl",
    "sg:orig_category":"Pensionen / Privatzimmer",
    "sg:phone":"+43 6244 6556",
    "sg:postcode":"5431",
    "sg:province":"Salzburg",
    "wof:name":"Sillfeichtengut",
    "wof:placetype":"venue"
},
  "geometry": {"coordinates":[13.1509180069,47.6254463196],"type":"Point"}
}