{
  "type": "Feature",
  "properties": {
    "iso:country":"AT",
    "sg:address":"Goldschlagstrasse 182",
    "sg:city":"Wien",
    "sg:classifiers":[
        {
            "category":"Home & Garden",
            "subcategory":"Building Materials",
            "type":"Retail Goods"
        }
    ],
    "sg:phone":"+43 664 4207851",
    "sg:postcode":"1140",
    "sg:province":"Wien",
    "sg:tags":[
        "installation",
        "electric"
    ],
    "wof:name":"ELNOVA Elektroinstallationen Ges.m.b.H.",
    "wof:placetype":"venue"
},
  "geometry": {"coordinates":[16.2986030579,48.1946182251],"type":"Point"}
}