{
  "type": "Feature",
  "properties": {
    "addr:full":"Zollg 1 Dornbirn Vorarlberg 6850",
    "addr:housenumber":"1",
    "addr:postcode":"6850",
    "addr:street":"Zollg",
    "iso:country":"AT",
    "sg:address":"Zollg 1",
    "sg:city":"Dornbirn",
    "sg:orig_category":"Beratungsstellen",
    "sg:phone":"+43 5572 52212",
    "sg:postcode":"6850",
    "sg:province":"Vorarlberg",
    "sg:website":"aha.or.at",
    "wof:name":"aha - Tipps und Infos f\u00fcr Junge Leute - Jugendinformationszentrum Vorarlberg",
    "wof:placetype":"venue"
},
  "geometry": {"coordinates":[9.7437801361,47.4131889343],"type":"Point"}
}