{
  "type": "Feature",
  "properties": {
    "iso:country":"AT",
    "sg:address":"Bundesstr. 66 ",
    "sg:city":"Zeltweg",
    "sg:classifiers":[
        {
            "category":"Manufacturing",
            "subcategory":"Rubber & Plastics",
            "type":"Manufacturing & Wholesale Goods"
        }
    ],
    "sg:phone":"+43 4335 7725624",
    "sg:postcode":"8740",
    "sg:province":"Steiermark",
    "wof:name":"KUNSTSTOFF BEARBEITUNGS GES.MBH",
    "wof:placetype":"venue"
},
  "geometry": {"coordinates":[14.7316274643,47.1963233948],"type":"Point"}
}