{
  "type": "Feature",
  "properties": {
    "iso:country":"AT",
    "sg:address":"Feschnigstr 76",
    "sg:city":"Klagenfurt",
    "sg:orig_category":"Gastronomie- U Hotelbedarf",
    "sg:phone":"+43 4346 343665",
    "sg:postcode":"9020",
    "sg:province":"K\u00e4rnten",
    "wof:name":"Rist-Gro\u00dfhandel GesmbH",
    "wof:placetype":"venue"
},
  "geometry": {"coordinates":[14.3028879166,46.6389961243],"type":"Point"}
}