{
  "type": "Feature",
  "properties": {
    "iso:country":"AT",
    "sg:address":"Widumg 2",
    "sg:city":"Mieders",
    "sg:orig_category":"Non-Classified Establishments",
    "sg:phone":"+43 5225 62526",
    "sg:postcode":"6142",
    "sg:province":"Tirol",
    "wof:name":"Pfarramt",
    "wof:placetype":"venue"
},
  "geometry": {"coordinates":[11.3818302155,47.1687355042],"type":"Point"}
}