{
  "type": "Feature",
  "properties": {
    "addr:full":"Schulg 6 Kirchberg an der Pielach Nieder\u00f6sterreich 3204",
    "addr:housenumber":"6",
    "addr:postcode":"3204",
    "addr:street":"Schulg",
    "iso:country":"AT",
    "sg:address":"Schulg 6",
    "sg:city":"Kirchberg an der Pielach",
    "sg:orig_category":"Volksschulen",
    "sg:phone":"+43 4327 227228",
    "sg:postcode":"3204",
    "sg:province":"Nieder\u00f6sterreich",
    "wof:name":"Volksschule u allgemeine Sonderschule",
    "wof:placetype":"venue"
},
  "geometry": {"coordinates":[15.4318275452,48.0265274048],"type":"Point"}
}