{
  "type": "Feature",
  "properties": {
    "addr:full":"Alte Str 39 Hard Vorarlberg 6971",
    "addr:housenumber":"39",
    "addr:postcode":"6971",
    "addr:street":"Alte Str",
    "iso:country":"AT",
    "sg:address":"Alte Str 39",
    "sg:city":"Hard",
    "sg:orig_category":"Estriche",
    "sg:phone":"+43 4355 7476710",
    "sg:postcode":"6971",
    "sg:province":"Vorarlberg",
    "wof:name":"K\u00fcng Jochen",
    "wof:placetype":"venue"
},
  "geometry": {"coordinates":[9.6960754395,47.4855232239],"type":"Point"}
}