{
  "type": "Feature",
  "properties": {
    "addr:full":"St. Anna am Aigen Steiermark 8354",
    "addr:postcode":"8354",
    "addr:street":"Am Aigen Steiermark",
    "iso:country":"AT",
    "sg:city":"St. Anna am Aigen",
    "sg:orig_category":"Genossenschaften",
    "sg:phone":"+43 3158 2234",
    "sg:postcode":"8354",
    "sg:province":"Steiermark",
    "wof:name":"Steirische Beerenobstgenossenschaft regGenmbH",
    "wof:placetype":"venue"
},
  "geometry": {"coordinates":[15.9691562653,46.8632049561],"type":"Point"}
}