{
  "type": "Feature",
  "properties": {
    "iso:country":"AT",
    "sg:address":"Linzer Str 1-2",
    "sg:city":"Windischgarsten",
    "sg:orig_category":"Gerbereien",
    "sg:phone":"+43 7562 5253",
    "sg:postcode":"4580",
    "sg:province":"Ober\u00f6sterreich",
    "wof:name":"Purgleitner Max Wolfgang",
    "wof:placetype":"venue"
},
  "geometry": {"coordinates":[14.3216514587,47.7224159241],"type":"Point"}
}