{
  "type": "Feature",
  "properties": {
    "addr:full":"Jasminstr 9 Kronstorf Ober\u00f6sterreich 4484",
    "addr:housenumber":"9",
    "addr:postcode":"4484",
    "addr:street":"Jasminstr",
    "iso:country":"AT",
    "sg:address":"Jasminstr 9",
    "sg:city":"Kronstorf",
    "sg:orig_category":"Immobilienverwaltungen",
    "sg:phone":"+43 7223 85283",
    "sg:postcode":"4484",
    "sg:province":"Ober\u00f6sterreich",
    "wof:name":"Ballmann Beteiligungs- und Betriebs GmbH",
    "wof:placetype":"venue"
},
  "geometry": {"coordinates":[14.4748020172,48.1737480164],"type":"Point"}
}