{
  "type": "Feature",
  "properties": {
    "addr:full":"Schubertstr 26 Linz Ober\u00f6sterreich 4020",
    "addr:housenumber":"26",
    "addr:postcode":"4020",
    "addr:street":"Schubertstr",
    "iso:country":"AT",
    "sg:address":"Schubertstr 26",
    "sg:city":"Linz",
    "sg:orig_category":"Selbstverteidigung",
    "sg:phone":"+43 676 4875593",
    "sg:postcode":"4020",
    "sg:province":"Ober\u00f6sterreich",
    "wof:name":"AVCI WING TSUN KUNG FU & ESCRIMA",
    "wof:placetype":"venue"
},
  "geometry": {"coordinates":[14.2963600159,48.298160553],"type":"Point"}
}