{
  "type": "Feature",
  "properties": {
    "addr:full":"Eichkogelstr 40 Guntramsdorf Nieder\u00f6sterreich 2353",
    "addr:housenumber":"40",
    "addr:postcode":"2353",
    "addr:street":"Eichkogelstr",
    "iso:country":"AT",
    "sg:address":"Eichkogelstr 40",
    "sg:city":"Guntramsdorf",
    "sg:orig_category":"Druckereimaschinen U -Bedarf",
    "sg:phone":"+43 4322 3645507",
    "sg:postcode":"2353",
    "sg:province":"Nieder\u00f6sterreich",
    "wof:name":"Freundorfer & Partner KEG",
    "wof:placetype":"venue"
},
  "geometry": {"coordinates":[16.3208179474,48.0582962036],"type":"Point"}
}