{
  "type": "Feature",
  "properties": {
    "iso:country":"AT",
    "sg:address":"Roseggerstr 17",
    "sg:city":"Velden am W\u00f6rther See",
    "sg:orig_category":"Bankomat-Standorte",
    "sg:phone":"+43 5 0909",
    "sg:postcode":"9220",
    "sg:province":"K\u00e4rnten",
    "wof:name":"Bankomat d Volksbank Gewerbe- und Handelsbank K\u00e4rnten AG",
    "wof:placetype":"venue"
},
  "geometry": {"coordinates":[14.0229578018,46.6019210815],"type":"Point"}
}