{
  "type": "Feature",
  "properties": {
    "iso:country":"AT",
    "sg:address":"Hauptpl 5",
    "sg:city":"Ybbs an der Donau",
    "sg:orig_category":"Optiker",
    "sg:phone":"+43 7412 560600",
    "sg:postcode":"3370",
    "sg:province":"Nieder\u00f6sterreich",
    "wof:name":"Forster Optik GesmbH",
    "wof:placetype":"venue"
},
  "geometry": {"coordinates":[15.0848932266,48.1773834229],"type":"Point"}
}