{
  "type": "Feature",
  "properties": {
    "iso:country":"AT",
    "sg:address":"\u00f6tscherlandstr 14",
    "sg:city":"Purgstall an der Erlauf",
    "sg:orig_category":"Damenmoden",
    "sg:phone":"+43 4374 8930086",
    "sg:postcode":"3251",
    "sg:province":"Nieder\u00f6sterreich",
    "wof:name":"Steinecker Moden GmbH",
    "wof:placetype":"venue"
},
  "geometry": {"coordinates":[15.1404304504,48.0561103821],"type":"Point"}
}