{
  "type": "Feature",
  "properties": {
    "addr:full":"Grazer Str 33 Stainz Steiermark 8510",
    "addr:housenumber":"33",
    "addr:postcode":"8510",
    "addr:street":"Str",
    "iso:country":"AT",
    "sg:address":"Grazer Str 33",
    "sg:city":"Stainz",
    "sg:orig_category":"Lebensmittel / Einzelhandel",
    "sg:phone":"+43 3463 4063",
    "sg:postcode":"8510",
    "sg:province":"Steiermark",
    "wof:name":"SPAR \u00d6sterreichische Warenhandels-AG",
    "wof:placetype":"venue"
},
  "geometry": {"coordinates":[15.2680416107,46.8969345093],"type":"Point"}
}