{
  "type": "Feature",
  "properties": {
    "addr:full":"Marktpl 10 Thalgau Salzburg 5303",
    "addr:housenumber":"10",
    "addr:postcode":"5303",
    "addr:street":"Marktpl;Salzburg",
    "iso:country":"AT",
    "sg:address":"Marktpl 10",
    "sg:city":"Thalgau",
    "sg:orig_category":"Blumeneinzelhandel",
    "sg:phone":"+43 4362 356391",
    "sg:postcode":"5303",
    "sg:province":"Salzburg",
    "wof:name":"Blumen Ferner",
    "wof:placetype":"venue"
},
  "geometry": {"coordinates":[13.253865242,47.8415985107],"type":"Point"}
}