{
  "type": "Feature",
  "properties": {
    "iso:country":"AT",
    "sg:address":"Abt Haberl-Str 13",
    "sg:city":"Mondsee",
    "sg:orig_category":"Feuerwehren",
    "sg:phone":"+43 6232 4413",
    "sg:postcode":"5310",
    "sg:province":"Ober\u00f6sterreich",
    "wof:name":"Bezirksfeuerwehrkommando V\u00f6cklabruck",
    "wof:placetype":"venue"
},
  "geometry": {"coordinates":[13.3534078598,47.8554344177],"type":"Point"}
}