{
  "type": "Feature",
  "properties": {
    "iso:country":"AT",
    "sg:address":"Mandellstr 28",
    "sg:city":"Graz",
    "sg:orig_category":"Orientteppiche",
    "sg:phone":"+43 316 832267",
    "sg:postcode":"8010",
    "sg:province":"Steiermark",
    "wof:name":"Farzi Towigh",
    "wof:placetype":"venue"
},
  "geometry": {"coordinates":[15.4504365921,47.0669898987],"type":"Point"}
}