{
  "type": "Feature",
  "properties": {
    "addr:full":"Hauptstr 21 Neufeld an der Leitha Burgenland 2491",
    "addr:housenumber":"21",
    "addr:postcode":"2491",
    "addr:street":"Hauptstr",
    "iso:country":"AT",
    "sg:address":"Hauptstr 21",
    "sg:city":"Neufeld an der Leitha",
    "sg:orig_category":"Fenster",
    "sg:phone":"+43 2624 58992",
    "sg:postcode":"2491",
    "sg:province":"Burgenland",
    "wof:name":"Infeld Ariane",
    "wof:placetype":"venue"
},
  "geometry": {"coordinates":[16.3767261505,47.8670654297],"type":"Point"}
}