{
  "type": "Feature",
  "properties": {
    "addr:full":"Reininghausstr 60 Graz Steiermark 8020",
    "addr:housenumber":"60",
    "addr:postcode":"8020",
    "addr:street":"Reininghausstr",
    "iso:country":"AT",
    "sg:address":"Reininghausstr 60",
    "sg:city":"Graz",
    "sg:orig_category":"Friseure U Frisiersalons",
    "sg:phone":"+43 316 585830",
    "sg:postcode":"8020",
    "sg:province":"Steiermark",
    "wof:name":"Kreiner Josef",
    "wof:placetype":"venue"
},
  "geometry": {"coordinates":[15.4009599686,47.0636177063],"type":"Point"}
}