{
  "type": "Feature",
  "properties": {
    "iso:country":"AT",
    "sg:address":"Kreitnerg 43",
    "sg:city":"Wien",
    "sg:orig_category":"Gesundheit / Allgemeine Informationsstellen",
    "sg:phone":"+43 1 4919616287",
    "sg:postcode":"1160",
    "sg:province":"Wien",
    "wof:name":"Gesundheitsf\u00fcrsorgestelle f d 14. 15. 16. und 17. Bezirk",
    "wof:placetype":"venue"
},
  "geometry": {"coordinates":[16.3236942291,48.2100715637],"type":"Point"}
}