{
  "type": "Feature",
  "properties": {
    "addr:full":"H\u00f6henweg 113 Steinach am Brenner Tirol 6150",
    "addr:housenumber":"113",
    "addr:postcode":"6150",
    "addr:street":"Tirol",
    "iso:country":"AT",
    "sg:address":"H\u00f6henweg 113",
    "sg:city":"Steinach am Brenner",
    "sg:orig_category":"Maler, Anstreicher U Lackierer",
    "sg:phone":"+43 4352 726455",
    "sg:postcode":"6150",
    "sg:province":"Tirol",
    "wof:name":"Fattor Malerei GesmbH",
    "wof:placetype":"venue"
},
  "geometry": {"coordinates":[11.4712095261,47.0888671875],"type":"Point"}
}