{
  "type": "Feature",
  "properties": {
    "iso:country":"AT",
    "sg:address":"Landgutg 15",
    "sg:city":"Wien",
    "sg:orig_category":"Berufsbekleidung / Einzelhandel, Berufsbekleidung / Erzeugung U Gro\u00c3\u0178handel",
    "sg:phone":"+43 1 60442310",
    "sg:postcode":"1100",
    "sg:province":"Wien",
    "sg:website":"www.derwalter.at",
    "wof:name":"Walter Berufskleidung - Der Walter",
    "wof:placetype":"venue"
},
  "geometry": {"coordinates":[16.3765735626,48.1811218262],"type":"Point"}
}