{
  "type": "Feature",
  "properties": {
    "iso:country":"AT",
    "sg:address":"Ottendorf 1",
    "sg:city":"Strengberg",
    "sg:classifiers":[
        {
            "category":"Manufacturing",
            "subcategory":"Wood Products",
            "type":"Manufacturing & Wholesale Goods"
        }
    ],
    "sg:phone":"+43 7432 22880",
    "sg:postcode":"3314",
    "sg:province":"Nieder\u00f6sterreich",
    "sg:tags":[
        "lumber"
    ],
    "sg:website":"wagner-hardwoods.com",
    "wof:name":"Franz Wagner GesmbH & Co KG",
    "wof:placetype":"venue"
},
  "geometry": {"coordinates":[14.6740436554,48.1349067688],"type":"Point"}
}