{
  "type": "Feature",
  "properties": {
    "addr:full":"Hauptstr 110 Seeboden K\u00e4rnten 9871",
    "addr:housenumber":"110",
    "addr:postcode":"9871",
    "addr:street":"Hauptstr;Kaernten",
    "iso:country":"AT",
    "sg:address":"Hauptstr 110",
    "sg:city":"Seeboden",
    "sg:orig_category":"Banken U Sparkassen",
    "sg:phone":"+43 4347 6281344",
    "sg:postcode":"9871",
    "sg:province":"K\u00e4rnten",
    "wof:name":"Volksbank Oberk\u00e4rnten regGenmbH",
    "wof:placetype":"venue"
},
  "geometry": {"coordinates":[13.5211248398,46.8191261292],"type":"Point"}
}