{
  "type": "Feature",
  "properties": {
    "addr:full":"Neunkirchner Str 90 Wiener Neustadt Nieder\u00f6sterreich 2700",
    "addr:postcode":"2700",
    "addr:street":"Str 90",
    "iso:country":"AT",
    "sg:address":"Neunkirchner Str 90",
    "sg:city":"Wiener Neustadt",
    "sg:orig_category":"Tankstellen",
    "sg:phone":"+43 2622 2359165",
    "sg:postcode":"2700",
    "sg:province":"Nieder\u00f6sterreich",
    "wof:name":"OMV AG",
    "wof:placetype":"venue"
},
  "geometry": {"coordinates":[16.2249755859,47.7986297607],"type":"Point"}
}