{
  "type": "Feature",
  "properties": {
    "addr:full":"Silberg 5 Oberperfuss Tirol 6173",
    "addr:housenumber":"5",
    "addr:postcode":"6173",
    "addr:street":"Silberg;Tirol",
    "iso:country":"AT",
    "sg:address":"Silberg 5",
    "sg:city":"Oberperfuss",
    "sg:orig_category":"Baumeister",
    "sg:phone":"+43 5232 77114",
    "sg:postcode":"6173",
    "sg:province":"Tirol",
    "wof:name":"Anich Peter GesmbH & Co KG",
    "wof:placetype":"venue"
},
  "geometry": {"coordinates":[11.2443246841,47.2451858521],"type":"Point"}
}