{
  "type": "Feature",
  "properties": {
    "addr:full":"Alxingerg 8 Wien Wien 1100",
    "addr:housenumber":"8",
    "addr:postcode":"1100",
    "addr:street":"Alxingerg",
    "iso:country":"AT",
    "sg:address":"Alxingerg 8",
    "sg:city":"Wien",
    "sg:orig_category":"Volksschulen",
    "sg:phone":"+43 1 604374514",
    "sg:postcode":"1100",
    "sg:province":"Wien",
    "wof:name":"Katholische Privatschule d Dienerinnen d Hl Geistes",
    "wof:placetype":"venue"
},
  "geometry": {"coordinates":[16.3682823181,48.1804962158],"type":"Point"}
}