{
  "type": "Feature",
  "properties": {
    "addr:full":"Grieskirchner Str 66 Wels Ober\u00f6sterreich 4600",
    "addr:housenumber":"66",
    "addr:postcode":"4600",
    "addr:street":"Str;Oberoesterreich",
    "iso:country":"AT",
    "sg:address":"Grieskirchner Str 66",
    "sg:city":"Wels",
    "sg:orig_category":"Autoersatzteile",
    "sg:phone":"+43 7242 440970",
    "sg:postcode":"4600",
    "sg:province":"Ober\u00f6sterreich",
    "wof:name":"Forstinger Handel und Service GmbH",
    "wof:placetype":"venue"
},
  "geometry": {"coordinates":[14.0220918655,48.1761550903],"type":"Point"}
}