{
  "type": "Feature",
  "properties": {
    "iso:country":"AT",
    "sg:address":"Schulg 12",
    "sg:city":"N\u00fcziders",
    "sg:orig_category":"Familien / Beratung",
    "sg:phone":"+43 5552 68010",
    "sg:postcode":"6714",
    "sg:province":"Vorarlberg",
    "wof:name":"M\u00fctterberatungsstelle",
    "wof:placetype":"venue"
},
  "geometry": {"coordinates":[9.7999696732,47.1700744629],"type":"Point"}
}