{
  "type": "Feature",
  "properties": {
    "addr:full":"Dornbacher Str Wien Wien 1170",
    "addr:postcode":"1170",
    "addr:street":"Str Wien",
    "iso:country":"AT",
    "sg:address":"Dornbacher Str",
    "sg:city":"Wien",
    "sg:orig_category":"Non-Classified Establishments",
    "sg:phone":"+43 1 4863259",
    "sg:postcode":"1170",
    "sg:province":"Wien",
    "wof:name":"TAXI-TEL Standplatztelefon Betriebs GmbH",
    "wof:placetype":"venue"
},
  "geometry": {"coordinates":[16.2907600403,48.2343139648],"type":"Point"}
}