{
  "type": "Feature",
  "properties": {
    "addr:full":"Tragweiner Str 29 Pregarten Ober\u00f6sterreich 4230",
    "addr:postcode":"4230",
    "addr:street":"Str 29",
    "iso:country":"AT",
    "sg:address":"Tragweiner Str 29",
    "sg:city":"Pregarten",
    "sg:orig_category":"Bezirkshauptmannschaften",
    "sg:phone":"+43 7236 22410",
    "sg:postcode":"4230",
    "sg:province":"Ober\u00f6sterreich",
    "wof:name":"Bezirkshauptmannschaft Freistadt",
    "wof:placetype":"venue"
},
  "geometry": {"coordinates":[14.5353317261,48.3534927368],"type":"Point"}
}