{
  "type": "Feature",
  "properties": {
    "addr:full":"Lenkgasse 29 Wien Wien 1220",
    "addr:housenumber":"29",
    "addr:postcode":"1220",
    "addr:street":"Lenkgasse",
    "iso:country":"AT",
    "sg:address":"Lenkgasse 29",
    "sg:city":"Wien",
    "sg:classifiers":[
        {
            "category":"Wholesale",
            "subcategory":"Metals & Minerals",
            "type":"Manufacturing & Wholesale Goods"
        }
    ],
    "sg:phone":"+43 1 2037372",
    "sg:postcode":"1220",
    "sg:province":"Wien",
    "sg:tags":[
        "dental",
        "gold"
    ],
    "wof:name":"K\u00fchnel & Co. Ges.m.b.H.",
    "wof:placetype":"venue"
},
  "geometry": {"coordinates":[16.4409332275,48.2439041138],"type":"Point"}
}