{
  "type": "Feature",
  "properties": {
    "addr:full":"Hauptpl 20 Frohnleiten Steiermark 8130",
    "addr:housenumber":"20",
    "addr:postcode":"8130",
    "addr:street":"Hauptpl",
    "iso:country":"AT",
    "sg:address":"Hauptpl 20",
    "sg:city":"Frohnleiten",
    "sg:orig_category":"Rauchfangsanierungen U -Ausschleifungen, Kamin- U Schornsteinbau",
    "sg:phone":"+43 3126 50960",
    "sg:postcode":"8130",
    "sg:province":"Steiermark",
    "sg:website":"www.kaminsanierung.com",
    "wof:name":"Sorian Kamin SOS GmbH",
    "wof:placetype":"venue"
},
  "geometry": {"coordinates":[15.3261404037,47.2707901001],"type":"Point"}
}