{
  "type": "Feature",
  "properties": {
    "iso:country":"AT",
    "sg:address":"Nr 6",
    "sg:city":"Zirl",
    "sg:classifiers":[
        {
            "category":"Communications",
            "subcategory":"Film & Video Production",
            "type":"Services"
        }
    ],
    "sg:phone":"+43 5238 52795",
    "sg:postcode":"6170",
    "sg:province":"Tirol",
    "sg:tags":[
        "multimedia"
    ],
    "wof:name":"infowerk software-entwicklungs Gmbh",
    "wof:placetype":"venue"
},
  "geometry": {"coordinates":[101.7013626099,26.3987903595],"type":"Point"}
}