{
  "type": "Feature",
  "properties": {
    "iso:country":"AT",
    "sg:address":"Im Grund 40",
    "sg:city":"Senftenberg",
    "sg:classifiers":[
        {
            "category":"Restaurant",
            "type":"Food & Drink"
        }
    ],
    "sg:phone":"+43 2719 2217",
    "sg:postcode":"3541",
    "sg:province":"Nieder\u00f6sterreich",
    "wof:name":"Restaurant Hoflehner",
    "wof:placetype":"venue"
},
  "geometry": {"coordinates":[15.5512485504,48.4528808594],"type":"Point"}
}