{
  "type": "Feature",
  "properties": {
    "addr:full":"Reitbergstr 2 Schwertberg Ober\u00f6sterreich 4311",
    "addr:housenumber":"2",
    "addr:postcode":"4311",
    "addr:street":"Reitbergstr",
    "iso:country":"AT",
    "sg:address":"Reitbergstr 2",
    "sg:city":"Schwertberg",
    "sg:orig_category":"Hauptschulen",
    "sg:phone":"+43 7262 6125611",
    "sg:postcode":"4311",
    "sg:province":"Ober\u00f6sterreich",
    "wof:name":"Hauptschule",
    "wof:placetype":"venue"
},
  "geometry": {"coordinates":[14.5722303391,48.2719802856],"type":"Point"}
}