{
  "type": "Feature",
  "properties": {
    "iso:country":"AT",
    "sg:address":"Rudolf H Bartsch-G 6",
    "sg:city":"Leibnitz",
    "sg:orig_category":"Lebensmittel / Einzelhandel",
    "sg:phone":"+43 3452 76411",
    "sg:postcode":"8430",
    "sg:province":"Steiermark",
    "wof:name":"MONDO Lebensmitteldiskonter",
    "wof:placetype":"venue"
},
  "geometry": {"coordinates":[15.5353298187,46.7807693481],"type":"Point"}
}