{
  "type": "Feature",
  "properties": {
    "addr:full":"Marktpl 27 Mattighofen Ober\u00f6sterreich 5230",
    "addr:housenumber":"27",
    "addr:postcode":"5230",
    "addr:street":"Marktpl",
    "iso:country":"AT",
    "sg:address":"Marktpl 27",
    "sg:city":"Mattighofen",
    "sg:orig_category":"Optiker",
    "sg:phone":"+43 4377 422553",
    "sg:postcode":"5230",
    "sg:province":"Ober\u00f6sterreich",
    "wof:name":"Brillenmacher Slatner u Reisinger GesmbH",
    "wof:placetype":"venue"
},
  "geometry": {"coordinates":[13.1500482559,48.1035919189],"type":"Point"}
}