{
  "type": "Feature",
  "properties": {
    "addr:full":"Nr 33 St. Peter am Wimberg Ober\u00f6sterreich 4171",
    "addr:postcode":"4171",
    "addr:street":"Nr 33",
    "iso:country":"AT",
    "sg:address":"Nr 33",
    "sg:city":"St. Peter am Wimberg",
    "sg:orig_category":"Hauptschulen",
    "sg:phone":"+43 4372 828046",
    "sg:postcode":"4171",
    "sg:province":"Ober\u00f6sterreich",
    "wof:name":"Hauptschule",
    "wof:placetype":"venue"
},
  "geometry": {"coordinates":[14.0817623138,48.5021438599],"type":"Point"}
}