{
  "type": "Feature",
  "properties": {
    "addr:full":"Ferdinandstr 20 Wien Wien 1020",
    "addr:housenumber":"20",
    "addr:postcode":"1020",
    "addr:street":"Ferdinandstr",
    "iso:country":"AT",
    "sg:address":"Ferdinandstr 20",
    "sg:city":"Wien",
    "sg:orig_category":"Versicherungsunternehmen",
    "sg:phone":"+43 1 211092858",
    "sg:postcode":"1020",
    "sg:province":"Wien",
    "sg:website":"calldirect.at",
    "wof:name":"CALL Direct Versicherung AG",
    "wof:placetype":"venue"
},
  "geometry": {"coordinates":[16.3841972351,48.2131500244],"type":"Point"}
}