{
  "type": "Feature",
  "properties": {
    "addr:full":"Saline 17 Hall in Tirol Tirol 6060",
    "addr:housenumber":"17",
    "addr:postcode":"6060",
    "addr:street":"Saline;Tirol",
    "iso:country":"AT",
    "sg:address":"Saline 17",
    "sg:city":"Hall in Tirol",
    "sg:orig_category":"Beratungsstellen",
    "sg:phone":"+43 5223 53830",
    "sg:postcode":"6060",
    "sg:province":"Tirol",
    "wof:name":"INTEGRATION TIROL",
    "wof:placetype":"venue"
},
  "geometry": {"coordinates":[11.5050430298,47.2789497375],"type":"Point"}
}