{
  "type": "Feature",
  "properties": {
    "addr:full":"Villenweg 1 Mattighofen Ober\u00f6sterreich 5230",
    "addr:housenumber":"1",
    "addr:postcode":"5230",
    "addr:street":"Villenweg",
    "iso:country":"AT",
    "sg:address":"Villenweg 1",
    "sg:city":"Mattighofen",
    "sg:orig_category":"Immobilienmakler",
    "sg:phone":"+43 7742 2396",
    "sg:postcode":"5230",
    "sg:province":"Ober\u00f6sterreich",
    "wof:name":"Teichst\u00e4tter Marianne",
    "wof:placetype":"venue"
},
  "geometry": {"coordinates":[13.1526708603,48.1022224426],"type":"Point"}
}