{
  "type": "Feature",
  "properties": {
    "addr:full":"Claudiastr 472 Seefeld in Tirol Tirol 6100",
    "addr:housenumber":"472",
    "addr:postcode":"6100",
    "addr:street":"Seefeld;Tirol",
    "iso:country":"AT",
    "sg:address":"Claudiastr 472",
    "sg:city":"Seefeld in Tirol",
    "sg:orig_category":"Pensionen / Privatzimmer",
    "sg:phone":"+43 5212 2238",
    "sg:postcode":"6100",
    "sg:province":"Tirol",
    "wof:name":"Haus Franziska",
    "wof:placetype":"venue"
},
  "geometry": {"coordinates":[11.192278862,47.3305969238],"type":"Point"}
}