{
  "type": "Feature",
  "properties": {
    "addr:full":"Weitraer Str 34 Gm\u00fcnd Nieder\u00f6sterreich 3950",
    "addr:postcode":"3950",
    "addr:street":"Str 34 Gmuend",
    "iso:country":"AT",
    "sg:address":"Weitraer Str 34",
    "sg:city":"Gm\u00fcnd",
    "sg:orig_category":"Steinmetzbetriebe",
    "sg:phone":"+43 2852 54629",
    "sg:postcode":"3950",
    "sg:province":"Nieder\u00f6sterreich",
    "wof:name":"Joanna Naturstein GesmbH",
    "wof:placetype":"venue"
},
  "geometry": {"coordinates":[14.9808197021,48.7691078186],"type":"Point"}
}