{
  "type": "Feature",
  "properties": {
    "iso:country":"AT",
    "sg:address":"Bahnstr 2",
    "sg:city":"Eisenstadt",
    "sg:orig_category":"Musikunterricht",
    "sg:phone":"+43 2682 68063",
    "sg:postcode":"7000",
    "sg:province":"Burgenland",
    "wof:name":"Musikschule Eisenstadt",
    "wof:placetype":"venue"
},
  "geometry": {"coordinates":[16.5236053467,47.844291687],"type":"Point"}
}