{
  "type": "Feature",
  "properties": {
    "iso:country":"AT",
    "sg:address":"Rohrbacher Str 6",
    "sg:city":"Neunkirchen",
    "sg:orig_category":"Versicherungsunternehmen",
    "sg:phone":"+43 2635 62781",
    "sg:postcode":"2620",
    "sg:province":"Nieder\u00f6sterreich",
    "wof:name":"Donau Versicherung",
    "wof:placetype":"venue"
},
  "geometry": {"coordinates":[16.0805072784,47.7261924744],"type":"Point"}
}