{
  "type": "Feature",
  "properties": {
    "iso:country":"AT",
    "sg:address":"Piburger Str 4",
    "sg:city":"Oetz",
    "sg:orig_category":"Galerien",
    "sg:phone":"+43 5252 6485",
    "sg:postcode":"6433",
    "sg:province":"Tirol",
    "wof:name":"J\u00e4ger Hans",
    "wof:placetype":"venue"
},
  "geometry": {"coordinates":[10.8925561905,47.2038536072],"type":"Point"}
}