{
  "type": "Feature",
  "properties": {
    "addr:full":"Lagerg 41 Graz Steiermark 8020",
    "addr:housenumber":"41",
    "addr:postcode":"8020",
    "addr:street":"Lagerg",
    "iso:country":"AT",
    "sg:address":"Lagerg 41",
    "sg:city":"Graz",
    "sg:orig_category":"Volksschulen",
    "sg:phone":"+43 316 712464",
    "sg:postcode":"8020",
    "sg:province":"Steiermark",
    "wof:name":"Volksschule",
    "wof:placetype":"venue"
},
  "geometry": {"coordinates":[15.4327335358,47.0633277893],"type":"Point"}
}