{
  "type": "Feature",
  "properties": {
    "addr:full":"Nr 243 Ischgl Tirol 6561",
    "addr:postcode":"6561",
    "addr:street":"Nr 243;Tirol",
    "iso:country":"AT",
    "sg:address":"Nr 243",
    "sg:city":"Ischgl",
    "sg:classifiers":[
        {
            "category":"Travel",
            "subcategory":"Hotels & Motels",
            "type":"Entertainment"
        }
    ],
    "sg:phone":"+43 5444 51700",
    "sg:postcode":"6561",
    "sg:province":"Tirol",
    "wof:name":"Hotel Garni Angela",
    "wof:placetype":"venue"
},
  "geometry": {"coordinates":[10.2881736755,47.0111351013],"type":"Point"}
}