{
  "type": "Feature",
  "properties": {
    "addr:full":"Nr 51 S\u00f6lden Tirol 6450",
    "addr:postcode":"6450",
    "addr:street":"Nr 51 Soelden Tirol",
    "iso:country":"AT",
    "sg:address":"Nr 51",
    "sg:city":"S\u00f6lden",
    "sg:orig_category":"Weiterbildungsinstitute M Allg U Berufl Bildungsangebot",
    "sg:phone":"+43 5254 2757",
    "sg:postcode":"6450",
    "sg:province":"Tirol",
    "wof:name":"Erwachsenenschule Inner\u00f6tztal",
    "wof:placetype":"venue"
},
  "geometry": {"coordinates":[11.0096664429,46.9695510864],"type":"Point"}
}