{
  "type": "Feature",
  "properties": {
    "addr:full":"Nr 20 Pramet Ober\u00f6sterreich 4925",
    "addr:postcode":"4925",
    "addr:street":"Nr;Pramet",
    "iso:country":"AT",
    "sg:address":"Nr 20",
    "sg:city":"Pramet",
    "sg:classifiers":[
        {
            "category":"Shopping",
            "subcategory":"Party Supplies",
            "type":"Retail Goods"
        }
    ],
    "sg:phone":"+43 4377 548531",
    "sg:postcode":"4925",
    "sg:province":"Ober\u00f6sterreich",
    "sg:tags":[
        "u",
        "lichtanlagen",
        "ton-"
    ],
    "wof:name":"Ton- u Lichttechnik Ing G\u00fcnter Katzlinger",
    "wof:placetype":"venue"
},
  "geometry": {"coordinates":[13.4648046494,48.1459617615],"type":"Point"}
}