{
  "type": "Feature",
  "properties": {
    "addr:full":"Wiener Str 26 Sieghartskirchen Nieder\u00f6sterreich 3443",
    "addr:postcode":"3443",
    "addr:street":"Niederoesterreich",
    "iso:country":"AT",
    "sg:address":"Wiener Str 26",
    "sg:city":"Sieghartskirchen",
    "sg:orig_category":"Tankstellen",
    "sg:phone":"+43 2274 2365",
    "sg:postcode":"3443",
    "sg:province":"Nieder\u00f6sterreich",
    "wof:name":"OMV Tankstelle",
    "wof:placetype":"venue"
},
  "geometry": {"coordinates":[16.0195713043,48.25415802],"type":"Point"}
}