{
  "type": "Feature",
  "properties": {
    "addr:full":"Hauptstr 25 Gr\u00fcnburg Ober\u00f6sterreich 4594",
    "addr:housenumber":"25",
    "addr:postcode":"4594",
    "addr:street":"Hauptstr;Oberoesterreich",
    "iso:country":"AT",
    "sg:address":"Hauptstr 25",
    "sg:city":"Gr\u00fcnburg",
    "sg:orig_category":"Banken U Sparkassen",
    "sg:phone":"+43 4350 10040048",
    "sg:postcode":"4594",
    "sg:province":"Ober\u00f6sterreich",
    "wof:name":"Allgemeine Sparkasse Ober\u00f6sterreich Bank AG",
    "wof:placetype":"venue"
},
  "geometry": {"coordinates":[14.2637214661,47.9705352783],"type":"Point"}
}