{
  "type": "Feature",
  "properties": {
    "addr:full":"Karl-Praunseys-Str 8 Gerasdorf Nieder\u00f6sterreich 2201",
    "addr:housenumber":"8",
    "addr:postcode":"2201",
    "addr:street":"Karl-Praunseys-Str",
    "iso:country":"AT",
    "sg:address":"Karl-Praunseys-Str 8",
    "sg:city":"Gerasdorf",
    "sg:orig_category":"Autoverwertung",
    "sg:phone":"+43 4322 464435",
    "sg:postcode":"2201",
    "sg:province":"Nieder\u00f6sterreich",
    "sg:website":"reilaender.at.tf",
    "wof:name":"Reil\u00e4nder Eva",
    "wof:placetype":"venue"
},
  "geometry": {"coordinates":[16.4402561188,48.3214149475],"type":"Point"}
}