{
  "type": "Feature",
  "properties": {
    "addr:full":"Ratschkyg 40 Wien Wien 1120",
    "addr:housenumber":"40",
    "addr:postcode":"1120",
    "addr:street":"Ratschkyg",
    "iso:country":"AT",
    "sg:address":"Ratschkyg 40",
    "sg:city":"Wien",
    "sg:orig_category":"Raumgestaltung",
    "sg:phone":"+43 1 8154222",
    "sg:postcode":"1120",
    "sg:province":"Wien",
    "wof:name":"Danzinger Ronald",
    "wof:placetype":"venue"
},
  "geometry": {"coordinates":[16.3230628967,48.1777839661],"type":"Point"}
}