{
  "type": "Feature",
  "properties": {
    "addr:full":"Rainerg 5/18 Wien Wien 1040",
    "addr:housenumber":"5 / 18",
    "addr:postcode":"1040",
    "addr:street":"Rainerg",
    "iso:country":"AT",
    "sg:address":"Rainerg 5/18",
    "sg:city":"Wien",
    "sg:classifiers":[
        {
            "category":"Professional",
            "subcategory":"Management & Consulting",
            "type":"Services"
        }
    ],
    "sg:phone":"+43 1 9675760",
    "sg:postcode":"1040",
    "sg:province":"Wien",
    "sg:tags":[
        "supervision"
    ],
    "wof:name":"D\u00f6ller Hans Mag",
    "wof:placetype":"venue"
},
  "geometry": {"coordinates":[16.3710918427,48.1896896362],"type":"Point"}
}