{
  "type": "Feature",
  "properties": {
    "addr:full":"Lizumstr 14a Axams Tirol 6094",
    "addr:housenumber":"14a",
    "addr:postcode":"6094",
    "addr:street":"Lizumstr;Tirol",
    "iso:country":"AT",
    "sg:address":"Lizumstr 14a",
    "sg:city":"Axams",
    "sg:orig_category":"Pensionen / Privatzimmer",
    "sg:phone":"+43 4352 3468560",
    "sg:postcode":"6094",
    "sg:province":"Tirol",
    "wof:name":"G\u00e4stehaus Stratton Fam Gruber",
    "wof:placetype":"venue"
},
  "geometry": {"coordinates":[11.2755441666,47.2291526794],"type":"Point"}
}