{
  "type": "Feature",
  "properties": {
    "iso:country":"AT",
    "sg:address":"Primoschgasse 3",
    "sg:city":"Klagenfurt",
    "sg:classifiers":[
        {
            "category":"Exhibition Hall",
            "type":"Public Place"
        }
    ],
    "sg:phone":"+43 463 3535070",
    "sg:postcode":"9020",
    "sg:province":"K\u00e4rnten",
    "sg:tags":[
        "equipping",
        "sale",
        "room",
        "show"
    ],
    "sg:website":"edd.at",
    "wof:name":"EDD-Designentwicklungs GmbH",
    "wof:placetype":"venue"
},
  "geometry": {"coordinates":[14.3291044235,46.6105499268],"type":"Point"}
}