{
  "type": "Feature",
  "properties": {
    "addr:full":"Gentzgasse 38/7 Wien Wien 1180",
    "addr:housenumber":"38 / 7",
    "addr:postcode":"1180",
    "addr:street":"Gentzgasse",
    "iso:country":"AT",
    "sg:address":"Gentzgasse 38/7",
    "sg:city":"Wien",
    "sg:classifiers":[
        {
            "category":"Professional",
            "subcategory":"Advertising",
            "type":"Services"
        }
    ],
    "sg:phone":"+43 1 47022030",
    "sg:postcode":"1180",
    "sg:province":"Wien",
    "sg:tags":[
        "item"
    ],
    "wof:name":"communication agency prihoda GmbH",
    "wof:placetype":"venue"
},
  "geometry": {"coordinates":[16.3433208466,48.2271156311],"type":"Point"}
}