{
  "type": "Feature",
  "properties": {
    "iso:country":"AT",
    "sg:address":"Langg 35",
    "sg:city":"Bad Radkersburg",
    "sg:orig_category":"Textilwaren / Einzelhandel",
    "sg:phone":"+43 3476 3866",
    "sg:postcode":"8490",
    "sg:province":"Steiermark",
    "wof:name":"Helleis Moden",
    "wof:placetype":"venue"
},
  "geometry": {"coordinates":[15.9888820648,46.6908340454],"type":"Point"}
}