{
  "type": "Feature",
  "properties": {
    "addr:full":"Obere Landstr 14 Krems an der Donau Nieder\u00f6sterreich 3500",
    "addr:housenumber":"14",
    "addr:postcode":"3500",
    "addr:street":"Obere Landstr",
    "iso:country":"AT",
    "sg:address":"Obere Landstr 14",
    "sg:city":"Krems an der Donau",
    "sg:orig_category":"Juweliere, Gold- U Silberschmiede",
    "sg:phone":"+43 4327 3270901",
    "sg:postcode":"3500",
    "sg:province":"Nieder\u00f6sterreich",
    "wof:name":"Jurtschitsch Karl",
    "wof:placetype":"venue"
},
  "geometry": {"coordinates":[15.5988559723,48.4106369019],"type":"Point"}
}