{
  "type": "Feature",
  "properties": {
    "iso:country":"AT",
    "sg:address":"Eggenberg 37",
    "sg:city":"Vorchdorf",
    "sg:orig_category":"Installationsunternehmen",
    "sg:phone":"+43 76146691",
    "sg:postcode":"4655",
    "sg:province":"Ober\u00f6sterreich",
    "wof:name":"Neuhofer Heli",
    "wof:placetype":"venue"
},
  "geometry": {"coordinates":[13.9219179153,47.9906425476],"type":"Point"}
}