{
  "type": "Feature",
  "properties": {
    "addr:full":"Langefelder Str 3 Trofaiach Steiermark 8793",
    "addr:housenumber":"3",
    "addr:postcode":"8793",
    "addr:street":"Str",
    "iso:country":"AT",
    "sg:address":"Langefelder Str 3",
    "sg:city":"Trofaiach",
    "sg:orig_category":"Marketingberatung",
    "sg:phone":"+43 3847 8131",
    "sg:postcode":"8793",
    "sg:province":"Steiermark",
    "wof:name":"EMD EDV-Marketing und DienstleistungsgmbH",
    "wof:placetype":"venue"
},
  "geometry": {"coordinates":[15.0012588501,47.4234542847],"type":"Point"}
}