{
  "type": "Feature",
  "properties": {
    "addr:full":"Thalstrasse 14 G\u00f6sting Steiermark 8051",
    "addr:housenumber":"14",
    "addr:postcode":"8051",
    "addr:street":"Thalstrasse",
    "iso:country":"AT",
    "sg:address":"Thalstrasse 14",
    "sg:city":"G\u00f6sting",
    "sg:orig_category":"Bleaching Plants For The Paper And Pulp Industry",
    "sg:phone":"+43 316 6827200",
    "sg:postcode":"8051",
    "sg:province":"Steiermark",
    "sg:website":"utg.at",
    "wof:name":"UTG Universaltechnik-Maier Industrieanlagenbau GmbH",
    "wof:placetype":"venue"
},
  "geometry": {"coordinates":[15.3911046982,47.1001434326],"type":"Point"}
}