{
  "type": "Feature",
  "properties": {
    "addr:full":"Hernalser Hauptstr 123 Wien Wien 1170",
    "addr:housenumber":"123",
    "addr:postcode":"1170",
    "addr:street":"Hernalser Hauptstr",
    "iso:country":"AT",
    "sg:address":"Hernalser Hauptstr 123",
    "sg:city":"Wien",
    "sg:orig_category":"Beschriftungen",
    "sg:phone":"+43 4314 892519",
    "sg:postcode":"1170",
    "sg:province":"Wien",
    "sg:website":"cs-shop.at",
    "wof:name":"CS-Shop Sparer Christian",
    "wof:placetype":"venue"
},
  "geometry": {"coordinates":[16.3225326538,48.2207870483],"type":"Point"}
}