{
  "type": "Feature",
  "properties": {
    "iso:country":"AT",
    "sg:address":"Maximilianstr 9",
    "sg:city":"Altm\u00fcnster",
    "sg:orig_category":"Tischlereien",
    "sg:phone":"+43 7612871210",
    "sg:postcode":"4813",
    "sg:province":"Ober\u00f6sterreich",
    "wof:name":"Ahammer H KG",
    "wof:placetype":"venue"
},
  "geometry": {"coordinates":[13.7636156082,47.8947181702],"type":"Point"}
}