{
  "type": "Feature",
  "properties": {
    "iso:country":"AT",
    "sg:address":"Gerichtsbergenstrasse 16",
    "sg:city":"F\u00fcrstenfeld",
    "sg:classifiers":[
        {
            "category":"Manufacturing",
            "subcategory":"Wood Products",
            "type":"Manufacturing & Wholesale Goods"
        }
    ],
    "sg:phone":"+43 3382 53978",
    "sg:postcode":"8280",
    "sg:province":"Steiermark",
    "sg:tags":[
        "gate",
        "made",
        "door"
    ],
    "wof:name":"Harald Sopper",
    "wof:placetype":"venue"
},
  "geometry": {"coordinates":[16.0713672638,47.0478286743],"type":"Point"}
}