{
  "type": "Feature",
  "properties": {
    "addr:full":"Lindeng 32/19 Wien Wien 1070",
    "addr:housenumber":"32 / 19",
    "addr:postcode":"1070",
    "addr:street":"Lindeng",
    "iso:country":"AT",
    "sg:address":"Lindeng 32/19",
    "sg:city":"Wien",
    "sg:orig_category":"Filmproduktionen",
    "sg:phone":"+43 1 5230382",
    "sg:postcode":"1070",
    "sg:province":"Wien",
    "wof:name":"AGENCE MONDIALE",
    "wof:placetype":"venue"
},
  "geometry": {"coordinates":[16.350320816,48.2001876831],"type":"Point"}
}