{
  "type": "Feature",
  "properties": {
    "addr:full":"Hauptstr 29 Seekirchen am Wallersee Salzburg 5201",
    "addr:housenumber":"29",
    "addr:postcode":"5201",
    "addr:street":"Hauptstr;Salzburg",
    "iso:country":"AT",
    "sg:address":"Hauptstr 29",
    "sg:city":"Seekirchen am Wallersee",
    "sg:orig_category":"Reifen U Reifendienste",
    "sg:phone":"+43 6212 4110",
    "sg:postcode":"5201",
    "sg:province":"Salzburg",
    "wof:name":"Top Reifen Team GmbH & Co KG",
    "wof:placetype":"venue"
},
  "geometry": {"coordinates":[13.1252088547,47.8941421509],"type":"Point"}
}