{
  "type": "Feature",
  "properties": {
    "addr:full":"M\u00e4lzerweg 9 Puntigam Steiermark 8055",
    "addr:housenumber":"9",
    "addr:postcode":"8055",
    "addr:street":"Maelzerweg",
    "iso:country":"AT",
    "sg:address":"M\u00e4lzerweg 9",
    "sg:city":"Puntigam",
    "sg:orig_category":"Installationsunternehmen",
    "sg:phone":"+43 316 2912090",
    "sg:postcode":"8055",
    "sg:province":"Steiermark",
    "wof:name":"Aqua-Therm Installationen - H Rabitsch & Sohn nunmehr GmbH & Co KG",
    "wof:placetype":"venue"
},
  "geometry": {"coordinates":[15.4372148514,47.0248451233],"type":"Point"}
}