{
  "type": "Feature",
  "properties": {
    "addr:full":"Salzburger Str 173 Wels Ober\u00f6sterreich 4600",
    "addr:housenumber":"173",
    "addr:postcode":"4600",
    "addr:street":"Salzburger Str;Oberoesterreich",
    "iso:country":"AT",
    "sg:address":"Salzburger Str 173",
    "sg:city":"Wels",
    "sg:orig_category":"Abwasseraufbereitung U -Reinigung",
    "sg:phone":"+43 7242 6310",
    "sg:postcode":"4600",
    "sg:province":"Ober\u00f6sterreich",
    "wof:name":"Hausleitner & Schweitzer GmbH",
    "wof:placetype":"venue"
},
  "geometry": {"coordinates":[13.9888715744,48.153011322],"type":"Point"}
}