{
  "type": "Feature",
  "properties": {
    "addr:full":"Eberschwang 30 Eberschwang Ober\u00f6sterreich 4906",
    "addr:housenumber":"30",
    "addr:postcode":"4906",
    "addr:street":"Eberschwang",
    "iso:country":"AT",
    "sg:address":"Eberschwang 30",
    "sg:city":"Eberschwang",
    "sg:classifiers":[
        {
            "category":"Home & Garden",
            "subcategory":"Building Materials",
            "type":"Retail Goods"
        }
    ],
    "sg:phone":"+43 7753 2316",
    "sg:postcode":"4906",
    "sg:province":"Ober\u00f6sterreich",
    "sg:tags":[
        "banister"
    ],
    "sg:website":"stiegenbau.at",
    "wof:name":"Andreas Lederbauer",
    "wof:placetype":"venue"
},
  "geometry": {"coordinates":[13.5600013733,48.155921936],"type":"Point"}
}