{
  "type": "Feature",
  "properties": {
    "addr:full":"B\u00f6hmerg 5 Freistadt Ober\u00f6sterreich 4240",
    "addr:housenumber":"5",
    "addr:postcode":"4240",
    "addr:street":"Boehmerg",
    "iso:country":"AT",
    "sg:address":"B\u00f6hmerg 5",
    "sg:city":"Freistadt",
    "sg:orig_category":"Friseure U Frisiersalons",
    "sg:phone":"+43 4379 4272442",
    "sg:postcode":"4240",
    "sg:province":"Ober\u00f6sterreich",
    "wof:name":"Friseur Elisabeth",
    "wof:placetype":"venue"
},
  "geometry": {"coordinates":[14.5049953461,48.5119857788],"type":"Point"}
}