{
  "type": "Feature",
  "properties": {
    "addr:full":"Industriestr 6 Sulz-R\u00f6this Vorarlberg 6832",
    "addr:housenumber":"6",
    "addr:postcode":"6832",
    "addr:street":"Industriestr",
    "iso:country":"AT",
    "sg:address":"Industriestr 6",
    "sg:city":"Sulz-R\u00f6this",
    "sg:orig_category":"Tischlereien",
    "sg:phone":"+43 664 4118106",
    "sg:postcode":"6832",
    "sg:province":"Vorarlberg",
    "wof:name":"Ludescher Helmut",
    "wof:placetype":"venue"
},
  "geometry": {"coordinates":[9.6222352982,47.3003349304],"type":"Point"}
}