{
  "type": "Feature",
  "properties": {
    "addr:full":"Angerweg 11 Aschbach Markt Nieder\u00f6sterreich 3361",
    "addr:housenumber":"11",
    "addr:postcode":"3361",
    "addr:street":"Angerweg",
    "iso:country":"AT",
    "sg:address":"Angerweg 11",
    "sg:city":"Aschbach Markt",
    "sg:orig_category":"Lebens- U Sozialberatung",
    "sg:phone":"+43 4366 44504509",
    "sg:postcode":"3361",
    "sg:province":"Nieder\u00f6sterreich",
    "wof:name":"M\u00f6rx Christa",
    "wof:placetype":"venue"
},
  "geometry": {"coordinates":[14.7356452942,48.0726165771],"type":"Point"}
}