{
  "type": "Feature",
  "properties": {
    "addr:full":"Bergsteigg 37 Wien Wien 1170",
    "addr:housenumber":"37",
    "addr:postcode":"1170",
    "addr:street":"Bergsteigg",
    "iso:country":"AT",
    "sg:address":"Bergsteigg 37",
    "sg:city":"Wien",
    "sg:orig_category":"Fassbindereien",
    "sg:phone":"+43 4314 082695",
    "sg:postcode":"1170",
    "sg:province":"Wien",
    "wof:name":"Schredl Ernst",
    "wof:placetype":"venue"
},
  "geometry": {"coordinates":[16.3354053497,48.2186508179],"type":"Point"}
}