{
  "type": "Feature",
  "properties": {
    "iso:country":"AT",
    "sg:address":"Porschestrasse 13",
    "sg:city":"St. P\u00f6lten",
    "sg:classifiers":[
        {
            "category":"Manufacturing",
            "subcategory":"Wood Products",
            "type":"Manufacturing & Wholesale Goods"
        }
    ],
    "sg:phone":"+43 2742 766300",
    "sg:postcode":"3100",
    "sg:province":"Nieder\u00f6sterreich",
    "sg:tags":[
        "high-quality",
        "board",
        "veneered"
    ],
    "sg:website":"holz-wallner.at/",
    "wof:name":"Br\u00fcder Wallner Sperrholzhandlung St. P\u00f6lten OHG",
    "wof:placetype":"venue"
},
  "geometry": {"coordinates":[-76.07303619379999,41.7845001221],"type":"Point"}
}