{
  "type": "Feature",
  "properties": {
    "addr:full":"Wirl 6b Galt\u00fcr Tirol 6563",
    "addr:housenumber":"6b",
    "addr:postcode":"6563",
    "addr:street":"Wirl;Tirol",
    "iso:country":"AT",
    "sg:address":"Wirl 6b",
    "sg:city":"Galt\u00fcr",
    "sg:classifiers":[
        {
            "category":"Travel",
            "subcategory":"Hotels & Motels",
            "type":"Entertainment"
        }
    ],
    "sg:phone":"+43 5443 85320",
    "sg:postcode":"6563",
    "sg:province":"Tirol",
    "wof:name":"Hotel Bel Ami",
    "wof:placetype":"venue"
},
  "geometry": {"coordinates":[10.1639299393,46.9657096863],"type":"Point"}
}