{
  "type": "Feature",
  "properties": {
    "addr:full":"Pierlstr 5 Klagenfurt K\u00e4rnten 9020",
    "addr:housenumber":"5",
    "addr:postcode":"9020",
    "addr:street":"Pierlstr;Kaernten",
    "iso:country":"AT",
    "sg:address":"Pierlstr 5",
    "sg:city":"Klagenfurt",
    "sg:orig_category":"Wassertechnik",
    "sg:phone":"+43 463 513034",
    "sg:postcode":"9020",
    "sg:province":"K\u00e4rnten",
    "wof:name":"Messtechnik - GesmbH",
    "wof:placetype":"venue"
},
  "geometry": {"coordinates":[14.2942380905,46.6236076355],"type":"Point"}
}