{
  "type": "Feature",
  "properties": {
    "iso:country":"AT",
    "sg:address":"Pichl 25",
    "sg:city":"Weyer",
    "sg:orig_category":"Beton- U Betonsteinwerke",
    "sg:phone":"+43 4373 557407",
    "sg:postcode":"3335",
    "sg:province":"Ober\u00f6sterreich",
    "wof:name":"Papst Markus Dipl-Ing GmbH & Co KG",
    "wof:placetype":"venue"
},
  "geometry": {"coordinates":[14.7162399292,47.8386268616],"type":"Point"}
}