{
  "type": "Feature",
  "properties": {
    "addr:full":"Schnelling 15 Steinerkirchen an der Traun Ober\u00f6sterreich 4652",
    "addr:housenumber":"15",
    "addr:postcode":"4652",
    "addr:street":"Schnelling",
    "iso:country":"AT",
    "sg:address":"Schnelling 15",
    "sg:city":"Steinerkirchen an der Traun",
    "sg:orig_category":"Architekten",
    "sg:phone":"+43 4372 4128158",
    "sg:postcode":"4652",
    "sg:province":"Ober\u00f6sterreich",
    "wof:name":"Brunbauer Johann",
    "wof:placetype":"venue"
},
  "geometry": {"coordinates":[13.9432344437,48.0415878296],"type":"Point"}
}