{
  "type": "Feature",
  "properties": {
    "addr:full":"Baumkirchnerring 7 Wiener Neustadt Nieder\u00f6sterreich 2700",
    "addr:housenumber":"7",
    "addr:postcode":"2700",
    "addr:street":"Baumkirchnerring",
    "iso:country":"AT",
    "sg:address":"Baumkirchnerring 7",
    "sg:city":"Wiener Neustadt",
    "sg:orig_category":"Familien / Beratung",
    "sg:phone":"+43 2622 28085",
    "sg:postcode":"2700",
    "sg:province":"Nieder\u00f6sterreich",
    "wof:name":"Familienzentrum N\u00f6-S\u00fcd d Caritas",
    "wof:placetype":"venue"
},
  "geometry": {"coordinates":[16.2418670654,47.81665802],"type":"Point"}
}