{
  "type": "Feature",
  "properties": {
    "addr:full":"Hans Mauracher-Str 75 Mariatrost Steiermark 8044",
    "addr:housenumber":"75",
    "addr:postcode":"8044",
    "iso:country":"AT",
    "sg:address":"Hans Mauracher-Str 75",
    "sg:city":"Mariatrost",
    "sg:orig_category":"Immobilienverwaltungen",
    "sg:phone":"+43 316 3911752",
    "sg:postcode":"8044",
    "sg:province":"Steiermark",
    "wof:name":"CTF Finanzierungsberatungs- und Betreiber GmbH",
    "wof:placetype":"venue"
},
  "geometry": {"coordinates":[15.4765729904,47.0971183777],"type":"Point"}
}