{
  "type": "Feature",
  "properties": {
    "addr:full":"Teilenstrasse 25a Lustenau Vorarlberg 6890",
    "addr:housenumber":"25a",
    "addr:postcode":"6890",
    "addr:street":"Teilenstrasse",
    "iso:country":"AT",
    "sg:address":"Teilenstrasse 25a",
    "sg:city":"Lustenau",
    "sg:classifiers":[
        {
            "category":"Professional",
            "subcategory":"Computer Services",
            "type":"Services"
        }
    ],
    "sg:phone":"+43 5577 62291",
    "sg:postcode":"6890",
    "sg:province":"Vorarlberg",
    "sg:tags":[
        "informatics",
        "consulting"
    ],
    "wof:name":"IT-SOLUTIONS Grabher GmbH",
    "wof:placetype":"venue"
},
  "geometry": {"coordinates":[9.6667032242,47.4282341003],"type":"Point"}
}