{
  "type": "Feature",
  "properties": {
    "iso:country":"AT",
    "sg:address":"Triebener Bundesstr 19",
    "sg:city":"Trieben",
    "sg:orig_category":"Volksschulen",
    "sg:phone":"+43 3615 21005",
    "sg:postcode":"8784",
    "sg:province":"Steiermark",
    "wof:name":"Volksschule",
    "wof:placetype":"venue"
},
  "geometry": {"coordinates":[14.4859895706,47.4637145996],"type":"Point"}
}