{
  "type": "Feature",
  "properties": {
    "iso:country":"AT",
    "sg:address":"Aigner Str 52",
    "sg:city":"Aigen",
    "sg:orig_category":"Architekten",
    "sg:phone":"+43 662 6239000",
    "sg:postcode":"5026",
    "sg:province":"Salzburg",
    "wof:name":"Burgstaller Volkmar Atelier ZT GmbH",
    "wof:placetype":"venue"
},
  "geometry": {"coordinates":[13.0757961273,47.7896003723],"type":"Point"}
}