{
  "type": "Feature",
  "properties": {
    "iso:country":"AT",
    "sg:address":"Wegscheidg 2a",
    "sg:city":"Kitzb\u00fchel",
    "sg:orig_category":"Werbeagenturen",
    "sg:phone":"+43 4353 5667177",
    "sg:postcode":"6370",
    "sg:province":"Tirol",
    "wof:name":"C plus Werbeagentur",
    "wof:placetype":"venue"
},
  "geometry": {"coordinates":[12.3910188675,47.4488258362],"type":"Point"}
}