{
  "type": "Feature",
  "properties": {
    "addr:full":"Waldhofweg 20c Mariatrost Steiermark 8044",
    "addr:housenumber":"20c",
    "addr:postcode":"8044",
    "addr:street":"Waldhofweg",
    "iso:country":"AT",
    "sg:address":"Waldhofweg 20c",
    "sg:city":"Mariatrost",
    "sg:classifiers":[
        {
            "category":"Professional",
            "subcategory":"Computer Services",
            "type":"Services"
        }
    ],
    "sg:phone":"+43 664 5164843",
    "sg:postcode":"8044",
    "sg:province":"Steiermark",
    "sg:tags":[
        "software"
    ],
    "wof:name":"Tertschnig Dr KEG",
    "wof:placetype":"venue"
},
  "geometry": {"coordinates":[15.4787015915,47.0959968567],"type":"Point"}
}