{
  "type": "Feature",
  "properties": {
    "addr:full":"Waltherstrasse 24 Linz Ober\u00f6sterreich 4020",
    "addr:housenumber":"24",
    "addr:postcode":"4020",
    "addr:street":"Waltherstrasse",
    "iso:country":"AT",
    "sg:address":"Waltherstrasse 24",
    "sg:city":"Linz",
    "sg:classifiers":[
        {
            "category":"Manufacturing",
            "subcategory":"Printing",
            "type":"Manufacturing & Wholesale Goods"
        }
    ],
    "sg:phone":"+43 732 777627",
    "sg:postcode":"4020",
    "sg:province":"Ober\u00f6sterreich",
    "sg:tags":[
        "embossed"
    ],
    "wof:name":"Ernst Ammering vorm. Kielar",
    "wof:placetype":"venue"
},
  "geometry": {"coordinates":[14.2847604752,48.3011665344],"type":"Point"}
}