{
  "type": "Feature",
  "properties": {
    "iso:country":"AT",
    "sg:address":"Stifter Str 41",
    "sg:city":"Peilstein im M\u00fchlviertel",
    "sg:orig_category":"Massageapparate U -Einrichtungen",
    "sg:phone":"+43 4372 877243",
    "sg:postcode":"4153",
    "sg:province":"Ober\u00f6sterreich",
    "wof:name":"Falkner Massagetische",
    "wof:placetype":"venue"
},
  "geometry": {"coordinates":[13.8933668137,48.6185073853],"type":"Point"}
}