{
  "type": "Feature",
  "properties": {
    "iso:country":"AT",
    "sg:address":"Gymnasiumstrasse 32 ",
    "sg:city":"Wien",
    "sg:classifiers":[
        {
            "category":"Government",
            "subcategory":"Fire Station",
            "type":"Public Place"
        }
    ],
    "sg:phone":"+43 1 47828290",
    "sg:postcode":"1180",
    "sg:province":"Wien",
    "sg:tags":[
        "supraregional",
        "plant",
        "installation",
        "heating"
    ],
    "wof:name":"Eck KG",
    "wof:placetype":"venue"
},
  "geometry": {"coordinates":[16.3450946808,48.2300682068],"type":"Point"}
}