{
  "type": "Feature",
  "properties": {
    "iso:country":"AT",
    "sg:address":"Nr 40",
    "sg:city":"Liesing",
    "sg:classifiers":[
        {
            "category":"Travel",
            "subcategory":"Hotels & Motels",
            "type":"Entertainment"
        }
    ],
    "sg:phone":"+43 4716 230",
    "sg:postcode":"9653",
    "sg:province":"K\u00e4rnten",
    "wof:name":"Hotel-Pension Lesachtalerhof",
    "wof:placetype":"venue"
},
  "geometry": {"coordinates":[12.8082408905,46.694065094],"type":"Point"}
}