{
  "type": "Feature",
  "properties": {
    "addr:full":"Steindorf 105 Stra\u00dfwalchen Salzburg 5204",
    "addr:housenumber":"105",
    "addr:postcode":"5204",
    "addr:street":"Steindorf;Salzburg",
    "iso:country":"AT",
    "sg:address":"Steindorf 105",
    "sg:city":"Stra\u00dfwalchen",
    "sg:orig_category":"Lebensmittel / Einzelhandel",
    "sg:phone":"+43 6215 20104",
    "sg:postcode":"5204",
    "sg:province":"Salzburg",
    "wof:name":"Hofer KG",
    "wof:placetype":"venue"
},
  "geometry": {"coordinates":[13.2367544174,47.9617347717],"type":"Point"}
}