{
  "type": "Feature",
  "properties": {
    "addr:full":"Esterhazypl 2 Eisenstadt Burgenland 7000",
    "addr:housenumber":"2",
    "addr:postcode":"7000",
    "addr:street":"Esterhazypl",
    "iso:country":"AT",
    "sg:address":"Esterhazypl 2",
    "sg:city":"Eisenstadt",
    "sg:orig_category":"Banken U Sparkassen",
    "sg:phone":"+43 4326 82627180",
    "sg:postcode":"7000",
    "sg:province":"Burgenland",
    "wof:name":"Bankomat d Oesterreichische Nationalbank",
    "wof:placetype":"venue"
},
  "geometry": {"coordinates":[16.5188655853,47.8455200195],"type":"Point"}
}