{
  "type": "Feature",
  "properties": {
    "iso:country":"AT",
    "sg:address":"Grillparzerstr 26",
    "sg:city":"Graz",
    "sg:orig_category":"Bildungsservice / Allgemeine Informationsstellen",
    "sg:phone":"+43 4331 6689310",
    "sg:postcode":"8010",
    "sg:province":"Steiermark",
    "wof:name":"Schul- u Ausbildungsberatung",
    "wof:placetype":"venue"
},
  "geometry": {"coordinates":[15.4424247742,47.0817756653],"type":"Point"}
}