{
  "type": "Feature",
  "properties": {
    "addr:full":"Karl-Mayr-Str 116 Nassereith Tirol 6465",
    "addr:housenumber":"116",
    "addr:postcode":"6465",
    "addr:street":"Tirol",
    "iso:country":"AT",
    "sg:address":"Karl-Mayr-Str 116",
    "sg:city":"Nassereith",
    "sg:orig_category":"Dekorationen",
    "sg:phone":"+43 676 6045642",
    "sg:postcode":"6465",
    "sg:province":"Tirol",
    "wof:name":"Floracreativa - Dekorationen mit Kunstpflanzen - Seelos Thomas",
    "wof:placetype":"venue"
},
  "geometry": {"coordinates":[10.8377714157,47.3145332336],"type":"Point"}
}