{
  "type": "Feature",
  "properties": {
    "addr:full":"Linzer Str 34 Gallspach Ober\u00f6sterreich 4713",
    "addr:housenumber":"34",
    "addr:postcode":"4713",
    "addr:street":"Linzer Str",
    "iso:country":"AT",
    "sg:address":"Linzer Str 34",
    "sg:city":"Gallspach",
    "sg:orig_category":"Tierschutz",
    "sg:phone":"+43 7248 62721",
    "sg:postcode":"4713",
    "sg:province":"Ober\u00f6sterreich",
    "wof:name":"Tierschutzorganisation Gestiefelter Kater",
    "wof:placetype":"venue"
},
  "geometry": {"coordinates":[13.8167171478,48.209022522],"type":"Point"}
}