{
  "type": "Feature",
  "properties": {
    "addr:full":"Glemmtaler Landesstra\u00dfe 205 Hinterglemm Salzburg 5754",
    "addr:housenumber":"205",
    "addr:postcode":"5754",
    "addr:street":"Glemmtaler Landesstrasse;Salzburg",
    "iso:country":"AT",
    "sg:address":"Glemmtaler Landesstra\u00dfe 205",
    "sg:city":"Hinterglemm",
    "sg:orig_category":"Reisen, Tourismusinfo",
    "sg:phone":"+43 6541 6640",
    "sg:postcode":"5754",
    "sg:province":"Salzburg",
    "sg:website":"http://www.alpinparadies.at/index.htm",
    "wof:name":"Alpin Paradies der Partnerhotels Hinterglemm",
    "wof:placetype":"venue"
},
  "geometry": {"coordinates":[12.6063899994,47.3832817078],"type":"Point"}
}