{
  "type": "Feature",
  "properties": {
    "addr:full":"Kirchfeldg 14 M\u00fcnchendorf Nieder\u00f6sterreich 2482",
    "addr:housenumber":"14",
    "addr:postcode":"2482",
    "addr:street":"Kirchfeldg;Niederoesterreich",
    "iso:country":"AT",
    "sg:address":"Kirchfeldg 14",
    "sg:city":"M\u00fcnchendorf",
    "sg:orig_category":"Stahlbau",
    "sg:phone":"+43 4322 592226",
    "sg:postcode":"2482",
    "sg:province":"Nieder\u00f6sterreich",
    "wof:name":"Hajsan Stahl- u Alubau",
    "wof:placetype":"venue"
},
  "geometry": {"coordinates":[16.3766002655,48.0300598145],"type":"Point"}
}