{
  "type": "Feature",
  "properties": {
    "iso:country":"AT",
    "sg:address":"Kirchsteig 1",
    "sg:city":"Leutschach",
    "sg:orig_category":"Non-Classified Establishments",
    "sg:phone":"+43 3454 217",
    "sg:postcode":"8463",
    "sg:province":"Steiermark",
    "wof:name":"Pfarramt",
    "wof:placetype":"venue"
},
  "geometry": {"coordinates":[15.4682769775,46.6665229797],"type":"Point"}
}