{
  "type": "Feature",
  "properties": {
    "addr:full":"Helferstorfer Str 3 Sollenau Nieder\u00f6sterreich 2601",
    "addr:housenumber":"3",
    "addr:postcode":"2601",
    "addr:street":"Str",
    "iso:country":"AT",
    "sg:address":"Helferstorfer Str 3",
    "sg:city":"Sollenau",
    "sg:orig_category":"Autohandel",
    "sg:phone":"+43 4366 45213513",
    "sg:postcode":"2601",
    "sg:province":"Nieder\u00f6sterreich",
    "wof:name":"Merlin Motors - Handel & Service von historischen Fahrzeugen",
    "wof:placetype":"venue"
},
  "geometry": {"coordinates":[16.2478618622,47.8999595642],"type":"Point"}
}