{
  "type": "Feature",
  "properties": {
    "iso:country":"AT",
    "sg:address":"Florianerweg 8",
    "sg:city":"Enns",
    "sg:orig_category":"Medizintechnik",
    "sg:phone":"+43 7223 83498",
    "sg:postcode":"4470",
    "sg:province":"Ober\u00f6sterreich",
    "wof:name":"P\u00fchringer E",
    "wof:placetype":"venue"
},
  "geometry": {"coordinates":[14.468870163,48.2135505676],"type":"Point"}
}