{
  "type": "Feature",
  "properties": {
    "addr:full":"Mariagr\u00fcner Str 29 Kroisbach Steiermark 8043",
    "addr:housenumber":"29",
    "addr:postcode":"8043",
    "addr:street":"Str",
    "iso:country":"AT",
    "sg:address":"Mariagr\u00fcner Str 29",
    "sg:city":"Kroisbach",
    "sg:classifiers":[
        {
            "category":"Restaurant",
            "type":"Food & Drink"
        }
    ],
    "sg:phone":"+43 316 323190",
    "sg:postcode":"8043",
    "sg:province":"Steiermark",
    "wof:name":"Restaurant Baumgartner zum Kaltenbrunn",
    "wof:placetype":"venue"
},
  "geometry": {"coordinates":[15.4606399536,47.0999107361],"type":"Point"}
}