{
  "type": "Feature",
  "properties": {
    "iso:country":"AT",
    "sg:address":"Kornpl 1",
    "sg:city":"Langenlois",
    "sg:orig_category":"Damenmoden",
    "sg:phone":"+43 2734 3506",
    "sg:postcode":"3550",
    "sg:province":"Nieder\u00f6sterreich",
    "wof:name":"Zimm Mode",
    "wof:placetype":"venue"
},
  "geometry": {"coordinates":[15.6768093109,48.4734954834],"type":"Point"}
}