{
  "type": "Feature",
  "properties": {
    "addr:full":"Wiesl 461 Mayrhofen Tirol 6290",
    "addr:housenumber":"461",
    "addr:postcode":"6290",
    "addr:street":"Wiesl;Tirol",
    "iso:country":"AT",
    "sg:address":"Wiesl 461",
    "sg:city":"Mayrhofen",
    "sg:orig_category":"Pensionen / Privatzimmer",
    "sg:phone":"+43 5285 62612",
    "sg:postcode":"6290",
    "sg:province":"Tirol",
    "wof:name":"Haus St Bernhard",
    "wof:placetype":"venue"
},
  "geometry": {"coordinates":[11.8612766266,47.1651573181],"type":"Point"}
}