{
  "type": "Feature",
  "properties": {
    "iso:country":"AT",
    "sg:address":"Am Markt 26",
    "sg:city":"Orth an der Donau",
    "sg:orig_category":"Psychotherapie",
    "sg:phone":"+43 676 7573015",
    "sg:postcode":"2304",
    "sg:province":"Nieder\u00f6sterreich",
    "wof:name":"Manzano Charlotte",
    "wof:placetype":"venue"
},
  "geometry": {"coordinates":[16.7035446167,48.1462783813],"type":"Point"}
}