{
  "type": "Feature",
  "properties": {
    "iso:country":"AT",
    "sg:address":"Nr 14",
    "sg:city":"Donnersbach",
    "sg:orig_category":"Gemeinden",
    "sg:phone":"+43 3683 22340",
    "sg:postcode":"8953",
    "sg:province":"Steiermark",
    "wof:name":"Gemeindeamt Donnersbach",
    "wof:placetype":"venue"
},
  "geometry": {"coordinates":[14.1284208298,47.465587616],"type":"Point"}
}