{
  "type": "Feature",
  "properties": {
    "addr:full":"Aigner Strasse 35 Aigen Salzburg 5026",
    "addr:housenumber":"35",
    "addr:postcode":"5026",
    "addr:street":"Aigner Strasse;Salzburg",
    "iso:country":"AT",
    "sg:address":"Aigner Strasse 35",
    "sg:city":"Aigen",
    "sg:classifiers":[
        {
            "category":"Shopping",
            "subcategory":"Pets & Pet Supplies",
            "type":"Retail Goods"
        }
    ],
    "sg:phone":"+43 662 6450200",
    "sg:postcode":"5026",
    "sg:province":"Salzburg",
    "sg:tags":[
        "cat"
    ],
    "sg:website":"perro.at",
    "wof:name":"Perro GmbH",
    "wof:placetype":"venue"
},
  "geometry": {"coordinates":[13.0728998184,47.7928504944],"type":"Point"}
}