{
  "type": "Feature",
  "properties": {
    "addr:full":"Hauptpl 14 Gnas Steiermark 8342",
    "addr:housenumber":"14",
    "addr:postcode":"8342",
    "addr:street":"Hauptpl",
    "iso:country":"AT",
    "sg:address":"Hauptpl 14",
    "sg:city":"Gnas",
    "sg:orig_category":"Tabaktrafiken",
    "sg:phone":"+43 3151 225137",
    "sg:postcode":"8342",
    "sg:province":"Steiermark",
    "wof:name":"Roth Trafik",
    "wof:placetype":"venue"
},
  "geometry": {"coordinates":[15.826833725,46.8737869263],"type":"Point"}
}