{
  "type": "Feature",
  "properties": {
    "addr:full":"Nr 55 Bad St. Leonhard im Lavanttal K\u00e4rnten 9462",
    "addr:housenumber":"55",
    "addr:postcode":"9462",
    "addr:street":"Nr",
    "iso:country":"AT",
    "sg:address":"Nr 55",
    "sg:city":"Bad St. Leonhard im Lavanttal",
    "sg:orig_category":"Feuerwehren",
    "sg:phone":"+43 4350 2441",
    "sg:postcode":"9462",
    "sg:province":"K\u00e4rnten",
    "wof:name":"Freiwillige Feuerwehr Bad St Leonhard i Lavanttal",
    "wof:placetype":"venue"
},
  "geometry": {"coordinates":[12.3305559158,48.0921058655],"type":"Point"}
}