{
  "type": "Feature",
  "properties": {
    "addr:full":"Stiftstr 6 Engelhartszell Ober\u00f6sterreich 4090",
    "addr:housenumber":"6",
    "addr:postcode":"4090",
    "addr:street":"Stiftstr",
    "iso:country":"AT",
    "sg:address":"Stiftstr 6",
    "sg:city":"Engelhartszell",
    "sg:orig_category":"Spirituosen / Erzeugung U Gro\u00c3\u0178handel",
    "sg:phone":"+43 7717 80100",
    "sg:postcode":"4090",
    "sg:province":"Ober\u00f6sterreich",
    "wof:name":"Stift Engelszell",
    "wof:placetype":"venue"
},
  "geometry": {"coordinates":[13.7333393097,48.5013198853],"type":"Point"}
}