{
  "type": "Feature",
  "properties": {
    "iso:country":"AT",
    "sg:address":"Obere Landstr 15",
    "sg:city":"Krems an der Donau",
    "sg:orig_category":"Drogerien",
    "sg:phone":"+43 2732 779750",
    "sg:postcode":"3500",
    "sg:province":"Nieder\u00f6sterreich",
    "wof:name":"MHA Reinhard M\u00fcller HandelsgmbH & Co KG",
    "wof:placetype":"venue"
},
  "geometry": {"coordinates":[15.5987653732,48.4106369019],"type":"Point"}
}