{
  "type": "Feature",
  "properties": {
    "iso:country":"AT",
    "sg:address":"Dresdner Str 55-57",
    "sg:city":"Wien",
    "sg:orig_category":"Blumeneinzelhandel",
    "sg:phone":"+43 1 3336929",
    "sg:postcode":"1200",
    "sg:province":"Wien",
    "wof:name":"Zvara's Baccara BlumenhandelsgesmbH",
    "wof:placetype":"venue"
},
  "geometry": {"coordinates":[16.3809528351,48.2359275818],"type":"Point"}
}