{
  "type": "Feature",
  "properties": {
    "iso:country":"AT",
    "sg:address":"Schauflerg 6",
    "sg:city":"Wien",
    "sg:classifiers":[
        {
            "category":"Restaurant",
            "type":"Food & Drink"
        }
    ],
    "sg:phone":"+43 1 5331309",
    "sg:postcode":"1010",
    "sg:province":"Wien",
    "wof:name":"Beisl Restaurant Kanzleramt",
    "wof:placetype":"venue"
},
  "geometry": {"coordinates":[16.3649215698,48.2084617615],"type":"Point"}
}