{
  "type": "Feature",
  "properties": {
    "addr:full":"Karolingerstr. 40  5021",
    "addr:housenumber":"40",
    "addr:postcode":"5021",
    "addr:street":"Karolingerstr.",
    "iso:country":"AT",
    "sg:address":"Karolingerstr. 40 ",
    "sg:classifiers":[
        {
            "category":"Manufacturing",
            "subcategory":"Printing",
            "type":"Manufacturing & Wholesale Goods"
        }
    ],
    "sg:phone":"+43 4366 28373",
    "sg:postcode":"5021",
    "sg:tags":[
        "publishing"
    ],
    "wof:name":"SALZBURGER NACHRICHTEN VERLAGSGESELLSCHAFT MBH & CO KG",
    "wof:placetype":"venue"
},
  "geometry": {"coordinates":[13.0117502213,47.7926979065],"type":"Point"}
}