{
  "type": "Feature",
  "properties": {
    "addr:full":"Gustav Degen-G 13 Mattersburg Burgenland 7210",
    "addr:housenumber":"13",
    "addr:postcode":"7210",
    "iso:country":"AT",
    "sg:address":"Gustav Degen-G 13",
    "sg:city":"Mattersburg",
    "sg:orig_category":"Gerichte",
    "sg:phone":"+43 2626 627150",
    "sg:postcode":"7210",
    "sg:province":"Burgenland",
    "wof:name":"Bezirksgericht Mattersburg",
    "wof:placetype":"venue"
},
  "geometry": {"coordinates":[16.3990936279,47.7371559143],"type":"Point"}
}