{
  "type": "Feature",
  "properties": {
    "addr:full":"Schmalkr\u00e4fteng 16 Purbach am Neusiedler See Burgenland 7083",
    "addr:housenumber":"16",
    "addr:postcode":"7083",
    "addr:street":"Schmalkraefteng",
    "iso:country":"AT",
    "sg:address":"Schmalkr\u00e4fteng 16",
    "sg:city":"Purbach am Neusiedler See",
    "sg:orig_category":"Handelsagenturen",
    "sg:phone":"+43 2683 5486",
    "sg:postcode":"7083",
    "sg:province":"Burgenland",
    "wof:name":"Brun\u00e4cker Elisabeth",
    "wof:placetype":"venue"
},
  "geometry": {"coordinates":[16.6938114166,47.9162139893],"type":"Point"}
}