{
  "type": "Feature",
  "properties": {
    "iso:country":"AT",
    "sg:address":"Hannakstr 1",
    "sg:city":"Gnigl",
    "sg:orig_category":"Physiotherapie",
    "sg:phone":"+43 4365 09663380",
    "sg:postcode":"5023",
    "sg:province":"Salzburg",
    "wof:name":"Ruschitzka Birgit Dipl-PT",
    "wof:placetype":"venue"
},
  "geometry": {"coordinates":[13.0663671494,47.8235244751],"type":"Point"}
}