{
  "type": "Feature",
  "properties": {
    "addr:full":"Schulweg 247 Markt Hartmannsdorf Steiermark 8311",
    "addr:housenumber":"247",
    "addr:postcode":"8311",
    "addr:street":"Schulweg",
    "iso:country":"AT",
    "sg:address":"Schulweg 247",
    "sg:city":"Markt Hartmannsdorf",
    "sg:orig_category":"Sporthallen",
    "sg:phone":"+43 3114 22010",
    "sg:postcode":"8311",
    "sg:province":"Steiermark",
    "wof:name":"Sporthalle Marktgemeinde Markt Hartmannsdorf",
    "wof:placetype":"venue"
},
  "geometry": {"coordinates":[15.8448295593,47.0531463623],"type":"Point"}
}