{
  "type": "Feature",
  "properties": {
    "addr:full":"Alser Str 45 Wien Wien 1080",
    "addr:postcode":"1080",
    "addr:street":"Str 45",
    "iso:country":"AT",
    "sg:address":"Alser Str 45",
    "sg:city":"Wien",
    "sg:orig_category":"Architekten",
    "sg:phone":"+43 1 4075117",
    "sg:postcode":"1080",
    "sg:province":"Wien",
    "wof:name":"Kallina Herbert Dipl-Ing",
    "wof:placetype":"venue"
},
  "geometry": {"coordinates":[16.3466796875,48.2152137756],"type":"Point"}
}