{
  "type": "Feature",
  "properties": {
    "addr:full":"Satoristr 29 Gmunden Ober\u00f6sterreich 4810",
    "addr:housenumber":"29",
    "addr:postcode":"4810",
    "addr:street":"Satoristr;Oberoesterreich",
    "iso:country":"AT",
    "sg:address":"Satoristr 29",
    "sg:city":"Gmunden",
    "sg:orig_category":"Dentalwaren",
    "sg:phone":"+43 761264343",
    "sg:postcode":"4810",
    "sg:province":"Ober\u00f6sterreich",
    "wof:name":"Schraberger Horst Dental Depot GmbH",
    "wof:placetype":"venue"
},
  "geometry": {"coordinates":[13.7912130356,47.9168891907],"type":"Point"}
}