{
  "type": "Feature",
  "properties": {
    "iso:country":"AT",
    "sg:address":"Fischergasse 17",
    "sg:city":"Salzburg",
    "sg:classifiers":[
        {
            "category":"Manufacturing",
            "subcategory":"Glass & Minerals",
            "type":"Manufacturing & Wholesale Goods"
        }
    ],
    "sg:phone":"+43 662 856370",
    "sg:postcode":"5020",
    "sg:province":"Salzburg",
    "sg:tags":[
        "fibre",
        "network"
    ],
    "sg:website":"ebinger.at",
    "wof:name":"Ebinger Netzwerktechnik GmbH",
    "wof:placetype":"venue"
},
  "geometry": {"coordinates":[13.0101747513,47.8278388977],"type":"Point"}
}