{
  "type": "Feature",
  "properties": {
    "addr:full":"Brachterg 6 Weiz Steiermark 8160",
    "addr:housenumber":"6",
    "addr:postcode":"8160",
    "addr:street":"Brachterg",
    "iso:country":"AT",
    "sg:address":"Brachterg 6",
    "sg:city":"Weiz",
    "sg:orig_category":"Optiker",
    "sg:phone":"+43 4366 41010575",
    "sg:postcode":"8160",
    "sg:province":"Steiermark",
    "wof:name":"Groh Optik GmbH & Co KG",
    "wof:placetype":"venue"
},
  "geometry": {"coordinates":[15.6266336441,47.2204055786],"type":"Point"}
}