{
  "type": "Feature",
  "properties": {
    "addr:full":"Schwarzenbergkaserne Wals Salzburg 5071",
    "addr:postcode":"5071",
    "iso:country":"AT",
    "sg:address":"Schwarzenbergkaserne",
    "sg:city":"Wals",
    "sg:orig_category":"Tabaktrafiken",
    "sg:phone":"+43 662 850841",
    "sg:postcode":"5071",
    "sg:province":"Salzburg",
    "wof:name":"Grabuschnig Erich",
    "wof:placetype":"venue"
},
  "geometry": {"coordinates":[12.9829912186,47.7975349426],"type":"Point"}
}