{
  "type": "Feature",
  "properties": {
    "iso:country":"AT",
    "sg:address":"Brauhofstr 6",
    "sg:city":"Scharnstein",
    "sg:orig_category":"Immobilienmakler",
    "sg:phone":"+43 76152387",
    "sg:postcode":"4644",
    "sg:province":"Ober\u00f6sterreich",
    "wof:name":"Servus Immobilien Gastronomie GmbH",
    "wof:placetype":"venue"
},
  "geometry": {"coordinates":[13.9625911713,47.9060974121],"type":"Point"}
}