{
  "type": "Feature",
  "properties": {
    "addr:full":"Nr 257 Stein an der Enns Steiermark 8961",
    "addr:postcode":"8961",
    "addr:street":"Nr 257;An Der Enns Steiermark",
    "iso:country":"AT",
    "sg:address":"Nr 257",
    "sg:city":"Stein an der Enns",
    "sg:classifiers":[
        {
            "category":"Home & Garden",
            "subcategory":"Building Materials",
            "type":"Retail Goods"
        }
    ],
    "sg:phone":"+43 4336 85244440",
    "sg:postcode":"8961",
    "sg:province":"Steiermark",
    "sg:tags":[
        "baustoffe",
        "-material",
        "u"
    ],
    "wof:name":"Bau Partner Zelzer & Co GesmbH",
    "wof:placetype":"venue"
},
  "geometry": {"coordinates":[13.9389886856,47.3949966431],"type":"Point"}
}