{
  "type": "Feature",
  "properties": {
    "iso:country":"AT",
    "sg:address":"Schwanberger Str 9",
    "sg:city":"Deutschlandsberg",
    "sg:orig_category":"Behinderungen / Leben Mit Behinderungen",
    "sg:phone":"+43 4334 6230404",
    "sg:postcode":"8530",
    "sg:province":"Steiermark",
    "wof:name":"TFS Tagesf\u00f6rderst\u00e4tte / TWS Tageswerkst\u00e4tte - Lebenshilfe Graz u Umgebung-Voitsberg",
    "wof:placetype":"venue"
},
  "geometry": {"coordinates":[15.2225904465,46.814365387],"type":"Point"}
}