{
  "type": "Feature",
  "properties": {
    "addr:full":"Buchh\u00f6hestrasse 637 Gro\u00dfgmain Salzburg 5084",
    "addr:housenumber":"637",
    "addr:postcode":"5084",
    "addr:street":"Buchhoehestrasse;Salzburg",
    "iso:country":"AT",
    "sg:address":"Buchh\u00f6hestrasse 637",
    "sg:city":"Gro\u00dfgmain",
    "sg:classifiers":[
        {
            "category":"Wholesale",
            "subcategory":"Home Furnishings",
            "type":"Manufacturing & Wholesale Goods"
        }
    ],
    "sg:phone":"+43 6247 20130",
    "sg:postcode":"5084",
    "sg:province":"Salzburg",
    "sg:tags":[
        "chair"
    ],
    "wof:name":"Josef Candido",
    "wof:placetype":"venue"
},
  "geometry": {"coordinates":[12.0809497833,48.0439414978],"type":"Point"}
}