{
  "type": "Feature",
  "properties": {
    "addr:full":"Leobner Str 100 Niklasdorf Steiermark 8712",
    "addr:housenumber":"100",
    "addr:postcode":"8712",
    "iso:country":"AT",
    "sg:address":"Leobner Str 100",
    "sg:city":"Niklasdorf",
    "sg:orig_category":"Speditionen",
    "sg:phone":"+43 4338 4283800",
    "sg:postcode":"8712",
    "sg:province":"Steiermark",
    "wof:name":"Huber Johann Spedition- u TransportgesmbH",
    "wof:placetype":"venue"
},
  "geometry": {"coordinates":[15.1338758469,47.3883743286],"type":"Point"}
}