{
  "type": "Feature",
  "properties": {
    "addr:full":"Schmelz 17 Dellach im Drautal K\u00e4rnten 9772",
    "addr:housenumber":"17",
    "addr:postcode":"9772",
    "addr:street":"Schmelz",
    "iso:country":"AT",
    "sg:address":"Schmelz 17",
    "sg:city":"Dellach im Drautal",
    "sg:orig_category":"Pensionen / Privatzimmer",
    "sg:phone":"+43 4347 14211",
    "sg:postcode":"9772",
    "sg:province":"K\u00e4rnten",
    "wof:name":"Haus Sonnenschein",
    "wof:placetype":"venue"
},
  "geometry": {"coordinates":[13.0910167694,46.7464828491],"type":"Point"}
}