{
  "type": "Feature",
  "properties": {
    "iso:country":"AT",
    "sg:address":"Kirchmayergasse 2",
    "sg:city":"Klosterneuburg",
    "sg:classifiers":[
        {
            "category":"Home & Garden",
            "subcategory":"Home Furnishings",
            "type":"Retail Goods"
        }
    ],
    "sg:phone":"+43 4322 4335809",
    "sg:postcode":"3400",
    "sg:province":"Nieder\u00f6sterreich",
    "sg:tags":[
        "household"
    ],
    "wof:name":"DETA RAUMAUSSTATTUNGS GES.MBH",
    "wof:placetype":"venue"
},
  "geometry": {"coordinates":[16.3116703033,48.290397644],"type":"Point"}
}