{
  "type": "Feature",
  "properties": {
    "addr:full":"Marktstr 18 Hard Vorarlberg 6971",
    "addr:housenumber":"18",
    "addr:postcode":"6971",
    "addr:street":"Marktstr",
    "iso:country":"AT",
    "sg:address":"Marktstr 18",
    "sg:city":"Hard",
    "sg:orig_category":"Wasserwerke",
    "sg:phone":"+43 4355 7469748",
    "sg:postcode":"6971",
    "sg:province":"Vorarlberg",
    "wof:name":"Wasserwerk d Marktgemeinde Hard",
    "wof:placetype":"venue"
},
  "geometry": {"coordinates":[9.6913928986,47.4889144897],"type":"Point"}
}