{
  "type": "Feature",
  "properties": {
    "addr:full":"Lechen 14 Neuberg an der M\u00fcrz Steiermark 8692",
    "addr:housenumber":"14;8692",
    "addr:street":"Lechen",
    "iso:country":"AT",
    "sg:address":"Lechen 14",
    "sg:city":"Neuberg an der M\u00fcrz",
    "sg:classifiers":[
        {
            "category":"Manufacturing",
            "subcategory":"Wood Products",
            "type":"Manufacturing & Wholesale Goods"
        }
    ],
    "sg:phone":"+43 3857 82050",
    "sg:postcode":"8692",
    "sg:province":"Steiermark",
    "sg:tags":[
        "case"
    ],
    "sg:website":"nhk.at",
    "wof:name":"Neuberger Holz- und Kunststoffindustrie Gesellschaft m.b.H.",
    "wof:placetype":"venue"
},
  "geometry": {"coordinates":[15.5969028473,47.6563034058],"type":"Point"}
}