{
  "type": "Feature",
  "properties": {
    "iso:country":"AT",
    "sg:address":"Huben 101",
    "sg:city":"L\u00e4ngenfeld",
    "sg:orig_category":"Botendienste",
    "sg:phone":"+43 5253 5518",
    "sg:postcode":"6444",
    "sg:province":"Tirol",
    "wof:name":"Eiltransporte Kuprian - Peppa's Express",
    "wof:placetype":"venue"
},
  "geometry": {"coordinates":[10.975815773,47.0403213501],"type":"Point"}
}