{
  "type": "Feature",
  "properties": {
    "addr:full":"Hinterstadt 26 Kitzb\u00fchel Tirol 6370",
    "addr:housenumber":"26",
    "addr:postcode":"6370",
    "addr:street":"Hinterstadt;Tirol",
    "iso:country":"AT",
    "sg:address":"Hinterstadt 26",
    "sg:city":"Kitzb\u00fchel",
    "sg:orig_category":"Freizeit- U Sportbekleidung",
    "sg:phone":"+43 5356 65028",
    "sg:postcode":"6370",
    "sg:province":"Tirol",
    "wof:name":"Benetton",
    "wof:placetype":"venue"
},
  "geometry": {"coordinates":[12.3909597397,47.4457435608],"type":"Point"}
}