{
  "type": "Feature",
  "properties": {
    "addr:full":"Dorfstr 22 St. Anton am Arlberg Tirol 6580",
    "addr:housenumber":"22",
    "addr:postcode":"6580",
    "addr:street":"Dorfstr;Tirol",
    "iso:country":"AT",
    "sg:address":"Dorfstr 22",
    "sg:city":"St. Anton am Arlberg",
    "sg:orig_category":"Pensionen / Privatzimmer",
    "sg:phone":"+43 5446 2205",
    "sg:postcode":"6580",
    "sg:province":"Tirol",
    "wof:name":"Ebster Egon",
    "wof:placetype":"venue"
},
  "geometry": {"coordinates":[10.2648744583,47.127872467],"type":"Point"}
}