{
  "type": "Feature",
  "properties": {
    "iso:country":"AT",
    "sg:address":"Palfen 129",
    "sg:city":"Altenmarkt im Pongau",
    "sg:orig_category":"Appartements / Ferienwohnungen",
    "sg:phone":"+43 4364 524016",
    "sg:postcode":"5541",
    "sg:province":"Salzburg",
    "wof:name":"Appartementhaus Panorama",
    "wof:placetype":"venue"
},
  "geometry": {"coordinates":[13.4581956863,47.2931518555],"type":"Point"}
}