{
  "type": "Feature",
  "properties": {
    "addr:full":"Rudolf-Buchinger-Str 12A Tulln an der Donau Nieder\u00f6sterreich 3430",
    "addr:housenumber":"12a",
    "addr:postcode":"3430",
    "addr:street":"Rudolf-Buchinger-Str",
    "iso:country":"AT",
    "sg:address":"Rudolf-Buchinger-Str 12A",
    "sg:city":"Tulln an der Donau",
    "sg:orig_category":"Versicherungsunternehmen",
    "sg:phone":"+43 2272 62203",
    "sg:postcode":"3430",
    "sg:province":"Nieder\u00f6sterreich",
    "wof:name":"Donau Versicherung",
    "wof:placetype":"venue"
},
  "geometry": {"coordinates":[16.0469474792,48.3303413391],"type":"Point"}
}