{
  "type": "Feature",
  "properties": {
    "addr:full":"Untere Augartenstr 16 Wien Wien 1020",
    "addr:housenumber":"16",
    "addr:postcode":"1020",
    "addr:street":"Untere Augartenstr",
    "iso:country":"AT",
    "sg:address":"Untere Augartenstr 16",
    "sg:city":"Wien",
    "sg:orig_category":"Installationsunternehmen, Heizungen",
    "sg:phone":"+43 1 21469690",
    "sg:postcode":"1020",
    "sg:province":"Wien",
    "sg:website":"www.passler.at",
    "wof:name":"Passler Ekkehard GmbH",
    "wof:placetype":"venue"
},
  "geometry": {"coordinates":[16.3724555969,48.2203063965],"type":"Point"}
}