{
  "type": "Feature",
  "properties": {
    "addr:full":"Dr.-C.-Pfeiffenberger-Str 24 Imst Tirol 6460",
    "addr:housenumber":"24",
    "addr:postcode":"6460",
    "addr:street":"Dr.-C.-Pfeiffenberger-Str;Tirol",
    "iso:country":"AT",
    "sg:address":"Dr.-C.-Pfeiffenberger-Str 24",
    "sg:city":"Imst",
    "sg:orig_category":"Psychotherapie",
    "sg:phone":"+43 4354 1264032",
    "sg:postcode":"6460",
    "sg:province":"Tirol",
    "wof:name":"Ennemoser Arnold Dr med",
    "wof:placetype":"venue"
},
  "geometry": {"coordinates":[10.7387609482,47.2370147705],"type":"Point"}
}