{
  "type": "Feature",
  "properties": {
    "iso:country":"AT",
    "sg:address":"Kapaunpl 1",
    "sg:city":"Graz",
    "sg:orig_category":"Weinstuben",
    "sg:phone":"+43 316 822122",
    "sg:postcode":"8010",
    "sg:province":"Steiermark",
    "wof:name":"Hold Helmut",
    "wof:placetype":"venue"
},
  "geometry": {"coordinates":[15.4366464615,47.070980072],"type":"Point"}
}