{
  "type": "Feature",
  "properties": {
    "addr:full":"Johann W Klein-Str 18 Linz Ober\u00f6sterreich 4040",
    "addr:housenumber":"18",
    "addr:postcode":"4040",
    "addr:street":"Johann W Klein-Str",
    "iso:country":"AT",
    "sg:address":"Johann W Klein-Str 18",
    "sg:city":"Linz",
    "sg:orig_category":"Steuerberatung",
    "sg:phone":"+43 732 2506060",
    "sg:postcode":"4040",
    "sg:province":"Ober\u00f6sterreich",
    "wof:name":"W\u00f6lflingseder & Partner",
    "wof:placetype":"venue"
},
  "geometry": {"coordinates":[14.3131942749,48.3314094543],"type":"Point"}
}