{
  "type": "Feature",
  "properties": {
    "addr:full":"Seestr 25 Walchsee Tirol 6344",
    "addr:housenumber":"25",
    "addr:postcode":"6344",
    "addr:street":"Seestr;Tirol",
    "iso:country":"AT",
    "sg:address":"Seestr 25",
    "sg:city":"Walchsee",
    "sg:orig_category":"Appartements / Ferienwohnungen",
    "sg:phone":"+43 4353 745340",
    "sg:postcode":"6344",
    "sg:province":"Tirol",
    "wof:name":"Lamplhof Planer",
    "wof:placetype":"venue"
},
  "geometry": {"coordinates":[12.3144931793,47.6439666748],"type":"Point"}
}