{
  "type": "Feature",
  "properties": {
    "addr:full":"Silbergasse 25  Wien Wien 1190",
    "addr:housenumber":"25",
    "addr:postcode":"1190",
    "addr:street":"Silbergasse",
    "iso:country":"AT",
    "sg:address":"Silbergasse 25 ",
    "sg:city":"Wien",
    "sg:classifiers":[
        {
            "category":"Building & Trades",
            "subcategory":"Plumbing",
            "type":"Services"
        }
    ],
    "sg:phone":"+43 1 32053350",
    "sg:postcode":"1190",
    "sg:province":"Wien",
    "sg:tags":[
        "supraregional",
        "gas"
    ],
    "sg:website":"www.schachl-wien.at",
    "wof:name":"Schachl Ges.m.b.H.",
    "wof:placetype":"venue"
},
  "geometry": {"coordinates":[16.3497848511,48.2468986511],"type":"Point"}
}