{
  "type": "Feature",
  "properties": {
    "addr:full":"Goldg 12 Salzburg Salzburg 5020",
    "addr:housenumber":"12",
    "addr:postcode":"5020",
    "addr:street":"Goldg;Salzburg",
    "iso:country":"AT",
    "sg:address":"Goldg 12",
    "sg:city":"Salzburg",
    "sg:orig_category":"Antiquariate",
    "sg:phone":"+43 662 848115",
    "sg:postcode":"5020",
    "sg:province":"Salzburg",
    "wof:name":"M\u00fcller Johannes",
    "wof:placetype":"venue"
},
  "geometry": {"coordinates":[13.0433769226,47.8006744385],"type":"Point"}
}