{
  "type": "Feature",
  "properties": {
    "iso:country":"AT",
    "sg:address":"Franz-Josef-Str 8",
    "sg:city":"Oberzeiring",
    "sg:orig_category":"Hafnereien",
    "sg:phone":"+43 3571 2517",
    "sg:postcode":"8762",
    "sg:province":"Steiermark",
    "wof:name":"Gruber Rudolf",
    "wof:placetype":"venue"
},
  "geometry": {"coordinates":[14.4941158295,47.2514762878],"type":"Point"}
}