{
  "type": "Feature",
  "properties": {
    "addr:full":"J\u00f6rgerstr 13 Wien Wien 1170",
    "addr:housenumber":"13",
    "addr:postcode":"1170",
    "addr:street":"Joergerstr",
    "iso:country":"AT",
    "sg:address":"J\u00f6rgerstr 13",
    "sg:city":"Wien",
    "sg:orig_category":"Waschmaschinen / Reparatur",
    "sg:phone":"+43 4314 04470",
    "sg:postcode":"1170",
    "sg:province":"Wien",
    "wof:name":"Karal Walter GesmbH",
    "wof:placetype":"venue"
},
  "geometry": {"coordinates":[16.3308048248,48.2193107605],"type":"Point"}
}