{
  "type": "Feature",
  "properties": {
    "addr:full":"Hauptstr 25 Donnerskirchen Burgenland 7082",
    "addr:housenumber":"25",
    "addr:postcode":"7082",
    "addr:street":"Hauptstr",
    "iso:country":"AT",
    "sg:address":"Hauptstr 25",
    "sg:city":"Donnerskirchen",
    "sg:orig_category":"Schmieden U Schmiedeeisenelemente",
    "sg:phone":"+43 2683 8303",
    "sg:postcode":"7082",
    "sg:province":"Burgenland",
    "wof:name":"Kritsch Stefan",
    "wof:placetype":"venue"
},
  "geometry": {"coordinates":[16.6449794769,47.8959617615],"type":"Point"}
}