{
  "type": "Feature",
  "properties": {
    "iso:country":"AT",
    "sg:address":"Grabenweg 3",
    "sg:city":"Innsbruck",
    "sg:orig_category":"Finanz- U Wirtschaftsberatung",
    "sg:phone":"+43 512 283494",
    "sg:postcode":"6020",
    "sg:province":"Tirol",
    "wof:name":"b + k consult - DDr Werner K\u00f6nigshofer",
    "wof:placetype":"venue"
},
  "geometry": {"coordinates":[11.4337320328,47.2648735046],"type":"Point"}
}