{
  "type": "Feature",
  "properties": {
    "iso:country":"AT",
    "sg:address":"Maxglaner Hauptstr 21/2",
    "sg:city":"Salzburg",
    "sg:orig_category":"Psychologen",
    "sg:phone":"+43 650 8236220",
    "sg:postcode":"5020",
    "sg:province":"Salzburg",
    "wof:name":"Lorber-Burghuber Susanna Dr",
    "wof:placetype":"venue"
},
  "geometry": {"coordinates":[13.0235137939,47.796749115],"type":"Point"}
}