{
  "type": "Feature",
  "properties": {
    "addr:full":"Georgstr 9 Gmunden Ober\u00f6sterreich 4810",
    "addr:housenumber":"9",
    "addr:postcode":"4810",
    "addr:street":"Georgstr;Oberoesterreich",
    "iso:country":"AT",
    "sg:address":"Georgstr 9",
    "sg:city":"Gmunden",
    "sg:orig_category":"Non-Classified Establishments",
    "sg:phone":"+43 761264237",
    "sg:postcode":"4810",
    "sg:province":"Ober\u00f6sterreich",
    "wof:name":"Evangelisches Pfarramt",
    "wof:placetype":"venue"
},
  "geometry": {"coordinates":[13.8052425385,47.9184761047],"type":"Point"}
}