{
  "type": "Feature",
  "properties": {
    "addr:full":"Wolfgangseestr 37 Hof Salzburg 5322",
    "addr:housenumber":"37",
    "addr:postcode":"5322",
    "addr:street":"Wolfgangseestr;Salzburg",
    "iso:country":"AT",
    "sg:address":"Wolfgangseestr 37",
    "sg:city":"Hof",
    "sg:orig_category":"Elektroinstallationsunternehmen",
    "sg:phone":"+43 6229 2236",
    "sg:postcode":"5322",
    "sg:province":"Salzburg",
    "wof:name":"Elektro Frimbichler GmbH",
    "wof:placetype":"venue"
},
  "geometry": {"coordinates":[13.1807441711,47.813533783],"type":"Point"}
}