{
  "type": "Feature",
  "properties": {
    "iso:country":"AT",
    "sg:address":"Ehamg 4",
    "sg:city":"Wien",
    "sg:orig_category":"Apotheken",
    "sg:phone":"+43 1 7492345",
    "sg:postcode":"1110",
    "sg:province":"Wien",
    "wof:name":"Herder Apotheke Mag pharm Richard Bernreiter",
    "wof:placetype":"venue"
},
  "geometry": {"coordinates":[16.4095630646,48.1740150452],"type":"Point"}
}