{
  "type": "Feature",
  "properties": {
    "addr:full":"Mayrwiesstr 23 Hallwang Salzburg 5300",
    "addr:housenumber":"23",
    "addr:postcode":"5300",
    "addr:street":"Mayrwiesstr;Salzburg",
    "iso:country":"AT",
    "sg:address":"Mayrwiesstr 23",
    "sg:city":"Hallwang",
    "sg:orig_category":"Druckereien",
    "sg:phone":"+43 662 6617370",
    "sg:postcode":"5300",
    "sg:province":"Salzburg",
    "wof:name":"Druckerei Roser GesmbH & Co KG",
    "wof:placetype":"venue"
},
  "geometry": {"coordinates":[13.0857639313,47.835067749],"type":"Point"}
}