{
  "type": "Feature",
  "properties": {
    "addr:full":"Fasching 8 Unterach am Attersee Ober\u00f6sterreich 4866",
    "addr:housenumber":"8",
    "addr:postcode":"4866",
    "addr:street":"Fasching",
    "iso:country":"AT",
    "sg:address":"Fasching 8",
    "sg:city":"Unterach am Attersee",
    "sg:orig_category":"Pensionen / Privatzimmer",
    "sg:phone":"+43 766584300",
    "sg:postcode":"4866",
    "sg:province":"Ober\u00f6sterreich",
    "wof:name":"Fr\u00fchst\u00fcckspension Christina",
    "wof:placetype":"venue"
},
  "geometry": {"coordinates":[13.5057992935,47.817073822],"type":"Point"}
}