{
  "type": "Feature",
  "properties": {
    "addr:full":"Kaltenleutgebner Str. 125 Wien Wien 1230",
    "addr:housenumber":"125",
    "addr:postcode":"1230",
    "addr:street":"Str.",
    "iso:country":"AT",
    "sg:address":"Kaltenleutgebner Str. 125",
    "sg:city":"Wien",
    "sg:classifiers":[
        {
            "category":"Shopping",
            "type":"Retail Goods"
        }
    ],
    "sg:phone":"+43 4318 8933940",
    "sg:postcode":"1230",
    "sg:province":"Wien",
    "sg:tags":[
        "finished",
        "-",
        "metallic"
    ],
    "wof:name":"KARIN ZACH GESMBH",
    "wof:placetype":"venue"
},
  "geometry": {"coordinates":[16.2392501831,48.1308097839],"type":"Point"}
}