{
  "type": "Feature",
  "properties": {
    "iso:country":"AT",
    "sg:address":"Mariazeller Str 5",
    "sg:city":"Lilienfeld",
    "sg:orig_category":"Lebensmittel / Einzelhandel",
    "sg:phone":"+43 4327 62525660",
    "sg:postcode":"3180",
    "sg:province":"Nieder\u00f6sterreich",
    "wof:name":"Spar-Markt Binder GmbH",
    "wof:placetype":"venue"
},
  "geometry": {"coordinates":[15.5924406052,48.0140457153],"type":"Point"}
}