{
  "type": "Feature",
  "properties": {
    "addr:full":"Hauptstr 138 Raab Ober\u00f6sterreich 4760",
    "addr:housenumber":"138",
    "addr:postcode":"4760",
    "addr:street":"Hauptstr;Oberoesterreich",
    "iso:country":"AT",
    "sg:address":"Hauptstr 138",
    "sg:city":"Raab",
    "sg:orig_category":"Feuerwehren",
    "sg:phone":"+43 7762 4137",
    "sg:postcode":"4760",
    "sg:province":"Ober\u00f6sterreich",
    "wof:name":"Freiwillige Feuerwehr Raab - Feuerwehrhaus",
    "wof:placetype":"venue"
},
  "geometry": {"coordinates":[13.6461172104,48.3543930054],"type":"Point"}
}