{
  "type": "Feature",
  "properties": {
    "addr:full":"Au\u00dferweg 119 Matrei am Brenner Tirol 6143",
    "addr:housenumber":"119",
    "addr:postcode":"6143",
    "addr:street":"Ausserweg;Am Brenner",
    "iso:country":"AT",
    "sg:address":"Au\u00dferweg 119",
    "sg:city":"Matrei am Brenner",
    "sg:orig_category":"Holzbearbeitungsmaschinen U -Werkzeuge",
    "sg:phone":"+43 4352 736429",
    "sg:postcode":"6143",
    "sg:province":"Tirol",
    "sg:website":"obojes-maschinen.at",
    "wof:name":"Obojes Anton",
    "wof:placetype":"venue"
},
  "geometry": {"coordinates":[11.4604654312,47.1421813965],"type":"Point"}
}