{
  "type": "Feature",
  "properties": {
    "addr:full":"Hans-Resel-G 2 Knittelfeld Steiermark 8720",
    "addr:housenumber":"2",
    "addr:postcode":"8720",
    "addr:street":"Hans-Resel-G",
    "iso:country":"AT",
    "sg:address":"Hans-Resel-G 2",
    "sg:city":"Knittelfeld",
    "sg:orig_category":"Gewerkschaften",
    "sg:phone":"+43 4335 12824350",
    "sg:postcode":"8720",
    "sg:province":"Steiermark",
    "wof:name":"Gewerkschaftsbund \u00f6sterreichischer",
    "wof:placetype":"venue"
},
  "geometry": {"coordinates":[14.8232488632,47.2147521973],"type":"Point"}
}