{
  "type": "Feature",
  "properties": {
    "addr:full":"Theodor-K\u00f6rner-Pl 6 Ternitz Nieder\u00f6sterreich 2630",
    "addr:housenumber":"6",
    "addr:postcode":"2630",
    "addr:street":"Theodor-Koerner-Pl",
    "iso:country":"AT",
    "sg:address":"Theodor-K\u00f6rner-Pl 6",
    "sg:city":"Ternitz",
    "sg:orig_category":"Mineralien",
    "sg:phone":"+43 2630 34342",
    "sg:postcode":"2630",
    "sg:province":"Nieder\u00f6sterreich",
    "wof:name":"Bloderer Andrea",
    "wof:placetype":"venue"
},
  "geometry": {"coordinates":[16.0354118347,47.7161598206],"type":"Point"}
}