{
  "type": "Feature",
  "properties": {
    "addr:full":"Amraser Str 41/2 Innsbruck Tirol 6020",
    "addr:housenumber":"41 / 2",
    "addr:postcode":"6020",
    "addr:street":"Amraser Str;Tirol",
    "iso:country":"AT",
    "sg:address":"Amraser Str 41/2",
    "sg:city":"Innsbruck",
    "sg:orig_category":"Werbeagenturen",
    "sg:phone":"+43 512 392771",
    "sg:postcode":"6020",
    "sg:province":"Tirol",
    "wof:name":"Konsequent Werbe GesmbH",
    "wof:placetype":"venue"
},
  "geometry": {"coordinates":[11.4118070602,47.2628288269],"type":"Point"}
}