{
  "type": "Feature",
  "properties": {
    "addr:full":"Petersbergenstr 119 St. Peter Steiermark 8042",
    "addr:housenumber":"119",
    "addr:postcode":"8042",
    "iso:country":"AT",
    "sg:address":"Petersbergenstr 119",
    "sg:city":"St. Peter",
    "sg:orig_category":"Werbeagenturen",
    "sg:phone":"+43 4331 6474400",
    "sg:postcode":"8042",
    "sg:province":"Steiermark",
    "wof:name":"med-makk-med marketing",
    "wof:placetype":"venue"
},
  "geometry": {"coordinates":[15.5047836304,47.0660820007],"type":"Point"}
}