{
  "type": "Feature",
  "properties": {
    "iso:country":"AT",
    "sg:address":"Bayernstr 20",
    "sg:city":"Salzburg",
    "sg:classifiers":[
        {
            "category":"Professional",
            "subcategory":"Art Services",
            "type":"Services"
        }
    ],
    "sg:phone":"+43 662 833415",
    "sg:postcode":"5020",
    "sg:province":"Salzburg",
    "sg:tags":[
        "designer"
    ],
    "wof:name":"Enzenhofer Andreas",
    "wof:placetype":"venue"
},
  "geometry": {"coordinates":[13.0266580582,47.7996025085],"type":"Point"}
}