{
  "type": "Feature",
  "properties": {
    "addr:full":"S\u00e4gewerkstr 3 Hard Vorarlberg 6971",
    "addr:housenumber":"3",
    "addr:postcode":"6971",
    "addr:street":"Saegewerkstr",
    "iso:country":"AT",
    "sg:address":"S\u00e4gewerkstr 3",
    "sg:city":"Hard",
    "sg:orig_category":"Fleischhauereien",
    "sg:phone":"+43 4355 7472315",
    "sg:postcode":"6971",
    "sg:province":"Vorarlberg",
    "wof:name":"Broger Norbert",
    "wof:placetype":"venue"
},
  "geometry": {"coordinates":[9.6930561066,47.4903488159],"type":"Point"}
}