{
  "type": "Feature",
  "properties": {
    "addr:full":"Kobernau\u00dferwaldstr 49 Schneegattern Ober\u00f6sterreich 5212",
    "addr:housenumber":"49",
    "addr:postcode":"5212",
    "addr:street":"Kobernausserwaldstr",
    "iso:country":"AT",
    "sg:address":"Kobernau\u00dferwaldstr 49",
    "sg:city":"Schneegattern",
    "sg:orig_category":"Glasgraveure U -\u00c3\u201etzereien",
    "sg:phone":"+43 4377 462462",
    "sg:postcode":"5212",
    "sg:province":"Ober\u00f6sterreich",
    "wof:name":"Nussbaumer Wolfgang",
    "wof:placetype":"venue"
},
  "geometry": {"coordinates":[13.2957286835,48.0248222351],"type":"Point"}
}