{
  "type": "Feature",
  "properties": {
    "iso:country":"AT",
    "sg:address":"W\u00fcstenrotpl 3",
    "sg:city":"Linz",
    "sg:orig_category":"Politische Parteien",
    "sg:phone":"+43 732 317627",
    "sg:postcode":"4030",
    "sg:province":"Ober\u00f6sterreich",
    "wof:name":"Freiheitliche Partei \u00f6sterreichs (FP\u00f6) - Ortsgruppe Linz-S\u00fcd",
    "wof:placetype":"venue"
},
  "geometry": {"coordinates":[14.3069601059,48.2325248718],"type":"Point"}
}