{
  "type": "Feature",
  "properties": {
    "addr:full":"Brauereistr 4 Mattighofen Ober\u00f6sterreich 5230",
    "addr:housenumber":"4",
    "addr:postcode":"5230",
    "addr:street":"Brauereistr",
    "iso:country":"AT",
    "sg:address":"Brauereistr 4",
    "sg:city":"Mattighofen",
    "sg:orig_category":"Finanz- U Wirtschaftsberatung",
    "sg:phone":"+43 7742 58778",
    "sg:postcode":"5230",
    "sg:province":"Ober\u00f6sterreich",
    "wof:name":"AWD Beratungszentrum Mattighofen",
    "wof:placetype":"venue"
},
  "geometry": {"coordinates":[13.1480340958,48.105304718],"type":"Point"}
}