{
  "type": "Feature",
  "properties": {
    "iso:country":"AT",
    "sg:address":"Wiener Str 112",
    "sg:city":"Gumpoldskirchen",
    "sg:orig_category":"Elektroinstallationsunternehmen",
    "sg:phone":"+43 2252 632120",
    "sg:postcode":"2352",
    "sg:province":"Nieder\u00f6sterreich",
    "wof:name":"Mirt & K\u00fchn GesmbH Elektro- und Beleuchtungstechnik",
    "wof:placetype":"venue"
},
  "geometry": {"coordinates":[16.2846508026,48.0419044495],"type":"Point"}
}