{
  "type": "Feature",
  "properties": {
    "iso:country":"AT",
    "sg:address":"Mayrwiesstr. 12 ",
    "sg:city":"Hallwang",
    "sg:classifiers":[
        {
            "category":"Home & Garden",
            "subcategory":"Home Furnishings",
            "type":"Retail Goods"
        }
    ],
    "sg:phone":"+43 4366 2664202",
    "sg:postcode":"5300",
    "sg:province":"Salzburg",
    "sg:tags":[
        "household"
    ],
    "wof:name":"VALLI & VALLI GMBH & CO KG",
    "wof:placetype":"venue"
},
  "geometry": {"coordinates":[13.0828437805,47.8340377808],"type":"Point"}
}