{
  "type": "Feature",
  "properties": {
    "iso:country":"AT",
    "sg:address":"Triester Str 200",
    "sg:city":"Wien",
    "sg:orig_category":"Transportunternehmen",
    "sg:phone":"+43 4316 6526000",
    "sg:postcode":"1230",
    "sg:province":"Wien",
    "wof:name":"Pils E u G GmbH & Co KG",
    "wof:placetype":"venue"
},
  "geometry": {"coordinates":[16.3298244476,48.1425476074],"type":"Point"}
}