{
  "type": "Feature",
  "properties": {
    "addr:full":"Nr 11 Pischeldorf K\u00e4rnten 9064",
    "addr:postcode":"9064",
    "addr:street":"Nr;Pischeldorf Kaernten",
    "iso:country":"AT",
    "sg:address":"Nr 11",
    "sg:city":"Pischeldorf",
    "sg:orig_category":"Non-Classified Establishments",
    "sg:phone":"+43 4224 2103",
    "sg:postcode":"9064",
    "sg:province":"K\u00e4rnten",
    "wof:name":"Krenn Herwig",
    "wof:placetype":"venue"
},
  "geometry": {"coordinates":[14.4197463989,46.6829566956],"type":"Point"}
}