{
  "type": "Feature",
  "properties": {
    "addr:full":"Kreuzg 63 Wien Wien 1180",
    "addr:housenumber":"63",
    "addr:postcode":"1180",
    "addr:street":"Kreuzg",
    "iso:country":"AT",
    "sg:address":"Kreuzg 63",
    "sg:city":"Wien",
    "sg:classifiers":[
        {
            "category":"Home & Garden",
            "subcategory":"Kitchen Supply",
            "type":"Retail Goods"
        }
    ],
    "sg:phone":"+43 4314 703864",
    "sg:postcode":"1180",
    "sg:province":"Wien",
    "sg:tags":[
        "espresso-",
        "u",
        "kaffeemaschinen"
    ],
    "wof:name":"Laurenzio - Gr\u00f6bl-Grundmann OEG",
    "wof:placetype":"venue"
},
  "geometry": {"coordinates":[16.3329563141,48.2255592346],"type":"Point"}
}