{
  "type": "Feature",
  "properties": {
    "addr:full":"Sch\u00f6mergasse 1/Top10 Klosterneuburg Nieder\u00f6sterreich 3400",
    "addr:housenumber":"1 / top10",
    "addr:postcode":"3400",
    "addr:street":"Schoemergasse;Niederoesterreich",
    "iso:country":"AT",
    "sg:address":"Sch\u00f6mergasse 1/Top10",
    "sg:city":"Klosterneuburg",
    "sg:classifiers":[
        {
            "category":"Manufacturing",
            "subcategory":"Rubber & Plastics",
            "type":"Manufacturing & Wholesale Goods"
        }
    ],
    "sg:phone":"+43 2243 202340",
    "sg:postcode":"3400",
    "sg:province":"Nieder\u00f6sterreich",
    "sg:tags":[
        "made",
        "covering",
        "athletic",
        "facility",
        "recycled",
        "floor"
    ],
    "sg:website":"engelhard-recycling.com",
    "wof:name":"Manfred Engelhard Recyclingprodukte",
    "wof:placetype":"venue"
},
  "geometry": {"coordinates":[16.3252258301,48.3049087524],"type":"Point"}
}