{
  "type": "Feature",
  "properties": {
    "iso:country":"AT",
    "sg:address":"Universit\u00e4tsstr 10",
    "sg:city":"Innsbruck",
    "sg:orig_category":"Tabaktrafiken",
    "sg:phone":"+43 512 581462",
    "sg:postcode":"6020",
    "sg:province":"Tirol",
    "wof:name":"Posch G\u00fcnter",
    "wof:placetype":"venue"
},
  "geometry": {"coordinates":[11.399143219,47.2691040039],"type":"Point"}
}