{
  "type": "Feature",
  "properties": {
    "addr:full":"Neudorf 22 Reith im Alpbachtal Tirol 6235",
    "addr:housenumber":"22",
    "addr:postcode":"6235",
    "addr:street":"Neudorf;Alpbachtal Tirol",
    "iso:country":"AT",
    "sg:address":"Neudorf 22",
    "sg:city":"Reith im Alpbachtal",
    "sg:orig_category":"Freizeitangebote U -Einrichtungen",
    "sg:phone":"+43 4353 3762428",
    "sg:postcode":"6235",
    "sg:province":"Tirol",
    "wof:name":"Alpbachtaler Kinderpark",
    "wof:placetype":"venue"
},
  "geometry": {"coordinates":[11.8640794754,47.4158935547],"type":"Point"}
}