{
  "type": "Feature",
  "properties": {
    "addr:full":"Steinbruch 1 Bad Ischl Ober\u00f6sterreich 4820",
    "addr:housenumber":"1",
    "addr:postcode":"4820",
    "addr:street":"Steinbruch",
    "iso:country":"AT",
    "sg:address":"Steinbruch 1",
    "sg:city":"Bad Ischl",
    "sg:orig_category":"Tankstellen",
    "sg:phone":"+43 6132 25270",
    "sg:postcode":"4820",
    "sg:province":"Ober\u00f6sterreich",
    "wof:name":"BP Austria Marketing GmbH",
    "wof:placetype":"venue"
},
  "geometry": {"coordinates":[13.5912094116,47.7174072266],"type":"Point"}
}