{
  "type": "Feature",
  "properties": {
    "addr:full":"Nibelungeng 2 Graz Steiermark 8010",
    "addr:housenumber":"2",
    "addr:postcode":"8010",
    "addr:street":"Nibelungeng",
    "iso:country":"AT",
    "sg:address":"Nibelungeng 2",
    "sg:city":"Graz",
    "sg:orig_category":"\u00c3\u201erzte / F Allgemeinmedizin",
    "sg:phone":"+43 316 819043",
    "sg:postcode":"8010",
    "sg:province":"Steiermark",
    "wof:name":"Bakos Stefan Dr",
    "wof:placetype":"venue"
},
  "geometry": {"coordinates":[15.4535160065,47.0671615601],"type":"Point"}
}