{
  "type": "Feature",
  "properties": {
    "addr:full":"Schnopfhagenpl 5 St. Veit im M\u00fchlkreis Ober\u00f6sterreich 4173",
    "addr:housenumber":"5",
    "addr:postcode":"4173",
    "addr:street":"Schnopfhagenpl",
    "iso:country":"AT",
    "sg:address":"Schnopfhagenpl 5",
    "sg:city":"St. Veit im M\u00fchlkreis",
    "sg:orig_category":"Fleischhauereien",
    "sg:phone":"+43 4372 176046",
    "sg:postcode":"4173",
    "sg:province":"Ober\u00f6sterreich",
    "wof:name":"Hainy Leopold",
    "wof:placetype":"venue"
},
  "geometry": {"coordinates":[14.1638479233,48.4678916931],"type":"Point"}
}