{
  "type": "Feature",
  "properties": {
    "iso:country":"AT",
    "sg:address":"Innsbruck Bundesstr 53",
    "sg:city":"Salzburg",
    "sg:orig_category":"Tauchsportartikel, Tauchsportschulen U -Vereine",
    "sg:phone":"+43 4366 2827645",
    "sg:postcode":"5020",
    "sg:province":"Salzburg",
    "sg:website":"tauchcenter.at",
    "wof:name":"Erstes Salzburger Tauchcenter",
    "wof:placetype":"venue"
},
  "geometry": {"coordinates":[13.0173873901,47.8017654419],"type":"Point"}
}