{
  "type": "Feature",
  "properties": {
    "addr:full":"Reisnerstr 41 Wien Wien 1030",
    "addr:housenumber":"41",
    "addr:postcode":"1030",
    "addr:street":"Reisnerstr",
    "iso:country":"AT",
    "sg:address":"Reisnerstr 41",
    "sg:city":"Wien",
    "sg:orig_category":"Holdinggesellschaften",
    "sg:phone":"+43 1 7105535",
    "sg:postcode":"1030",
    "sg:province":"Wien",
    "wof:name":"Jupiter VerlagsgesmbH",
    "wof:placetype":"venue"
},
  "geometry": {"coordinates":[16.3840751648,48.1984863281],"type":"Point"}
}