{
  "type": "Feature",
  "properties": {
    "addr:full":"Hauptplatz 8 Atzenbrugg Nieder\u00f6sterreich 3452",
    "addr:housenumber":"8",
    "addr:postcode":"3452",
    "addr:street":"Hauptplatz",
    "iso:country":"AT",
    "sg:address":"Hauptplatz 8",
    "sg:city":"Atzenbrugg",
    "sg:classifiers":[
        {
            "category":"Home & Garden",
            "subcategory":"Carpets & Floor Coverings",
            "type":"Retail Goods"
        }
    ],
    "sg:phone":"+43 2275 56560",
    "sg:postcode":"3452",
    "sg:province":"Nieder\u00f6sterreich",
    "sg:tags":[
        "plug",
        "connector",
        "high",
        "connectors",
        "frequency",
        "coaxial"
    ],
    "sg:website":"multi-contact.com",
    "wof:name":"Multi-Contact Handelsges.m.b.H.",
    "wof:placetype":"venue"
},
  "geometry": {"coordinates":[15.8940782547,48.2996673584],"type":"Point"}
}