{
  "type": "Feature",
  "properties": {
    "addr:full":"Hauptstr 61a Mauerbach Nieder\u00f6sterreich 3001",
    "addr:housenumber":"61a",
    "addr:postcode":"3001",
    "addr:street":"Hauptstr",
    "iso:country":"AT",
    "sg:address":"Hauptstr 61a",
    "sg:city":"Mauerbach",
    "sg:orig_category":"Bauunternehmen",
    "sg:phone":"+43 1 5772742",
    "sg:postcode":"3001",
    "sg:province":"Nieder\u00f6sterreich",
    "wof:name":"Felzmann Michael BaugesmbH",
    "wof:placetype":"venue"
},
  "geometry": {"coordinates":[16.1721191406,48.2416610718],"type":"Point"}
}