{
  "type": "Feature",
  "properties": {
    "addr:full":"Dorfstr 56 St. Anton am Arlberg Tirol 6580",
    "addr:housenumber":"56",
    "addr:postcode":"6580",
    "addr:street":"Dorfstr",
    "iso:country":"AT",
    "sg:address":"Dorfstr 56",
    "sg:city":"St. Anton am Arlberg",
    "sg:orig_category":"Lebensmittel / Einzelhandel",
    "sg:phone":"+43 5446 3581",
    "sg:postcode":"6580",
    "sg:province":"Tirol",
    "wof:name":"Nah & Frisch - Wedl & Dick GesmbH",
    "wof:placetype":"venue"
},
  "geometry": {"coordinates":[10.2664823532,47.1294059753],"type":"Point"}
}