{
  "type": "Feature",
  "properties": {
    "iso:country":"AT",
    "sg:address":"Petersbachstr 8",
    "sg:city":"Perchtoldsdorf",
    "sg:orig_category":"Ingenieurkonsulenten / Zivilingenieure",
    "sg:phone":"+43 1 8694701",
    "sg:postcode":"2380",
    "sg:province":"Nieder\u00f6sterreich",
    "wof:name":"Matthias Heinz-Bernd o Prof Dipl-Ing Dr",
    "wof:placetype":"venue"
},
  "geometry": {"coordinates":[16.2903633118,48.1276054382],"type":"Point"}
}