{
  "type": "Feature",
  "properties": {
    "iso:country":"AT",
    "sg:address":"Nr 85",
    "sg:city":"Strau",
    "sg:orig_category":"Friseureinrichtungen",
    "sg:phone":"+43 4342 282700",
    "sg:postcode":"9162",
    "sg:province":"K\u00e4rnten",
    "wof:name":"Gabriel Planungs- u EinrichtungsgesmbH & Co KG",
    "wof:placetype":"venue"
},
  "geometry": {"coordinates":[14.2556695938,46.538898468],"type":"Point"}
}