{
  "type": "Feature",
  "properties": {
    "iso:country":"AT",
    "sg:address":"Mariahilfer Str 206 ",
    "sg:city":"Wien",
    "sg:classifiers":[
        {
            "category":"Professional",
            "subcategory":"Computer Services",
            "type":"Services"
        }
    ],
    "sg:phone":"+43 4318 924156",
    "sg:postcode":"1150",
    "sg:province":"Wien",
    "sg:tags":[
        "information",
        "technology"
    ],
    "wof:name":"PLUSCOM VERTRIEBGESELLSCHAFT M.B.H.",
    "wof:placetype":"venue"
},
  "geometry": {"coordinates":[16.3235397339,48.190738678],"type":"Point"}
}