{
  "type": "Feature",
  "properties": {
    "addr:full":"Rennweg 78/2 Wien Wien 1030",
    "addr:housenumber":"78 / 2",
    "addr:postcode":"1030",
    "addr:street":"Rennweg",
    "iso:country":"AT",
    "sg:address":"Rennweg 78/2",
    "sg:city":"Wien",
    "sg:classifiers":[
        {
            "category":"Professional",
            "subcategory":"Accounting & Tax Preparation",
            "type":"Services"
        }
    ],
    "sg:phone":"+43 1 7988436",
    "sg:postcode":"1030",
    "sg:province":"Wien",
    "sg:tags":[
        "data",
        "acquisition"
    ],
    "sg:website":"idss.at",
    "wof:name":"Ing. Dieter Schildberg Ges.m.b.H.",
    "wof:placetype":"venue"
},
  "geometry": {"coordinates":[16.3956890106,48.1912193298],"type":"Point"}
}