{
  "type": "Feature",
  "properties": {
    "addr:full":"Thaliastr 124 Wien Wien 1160",
    "addr:housenumber":"124",
    "addr:postcode":"1160",
    "iso:country":"AT",
    "sg:address":"Thaliastr 124",
    "sg:city":"Wien",
    "sg:orig_category":"Hafnereien",
    "sg:phone":"+43 4314 864256",
    "sg:postcode":"1160",
    "sg:province":"Wien",
    "sg:website":"kachelofen.at",
    "wof:name":"Mahrhofer Erhard OHG Nfg KG",
    "wof:placetype":"venue"
},
  "geometry": {"coordinates":[16.3146457672,48.2123565674],"type":"Point"}
}