{
  "type": "Feature",
  "properties": {
    "addr:full":"In der Telle 1 Kennelbach Vorarlberg 6921",
    "addr:housenumber":"1",
    "addr:postcode":"6921",
    "addr:street":"In Der Telle",
    "iso:country":"AT",
    "sg:address":"In der Telle 1",
    "sg:city":"Kennelbach",
    "sg:orig_category":"Weiterbildungsinstitute M Allg U Berufl Bildungsangebot",
    "sg:phone":"+43 4355 74780210",
    "sg:postcode":"6921",
    "sg:province":"Vorarlberg",
    "wof:name":"ZTN Training & Consulting GmbH & Co KG",
    "wof:placetype":"venue"
},
  "geometry": {"coordinates":[9.7611627579,47.4809913635],"type":"Point"}
}