{
  "type": "Feature",
  "properties": {
    "addr:full":"Hauptstr 24 Prottes Nieder\u00f6sterreich 2242",
    "addr:housenumber":"24",
    "addr:postcode":"2242",
    "addr:street":"Hauptstr",
    "iso:country":"AT",
    "sg:address":"Hauptstr 24",
    "sg:city":"Prottes",
    "sg:orig_category":"Fleischhauereien",
    "sg:phone":"+43 2282 2191",
    "sg:postcode":"2242",
    "sg:province":"Nieder\u00f6sterreich",
    "wof:name":"Panzer Robert",
    "wof:placetype":"venue"
},
  "geometry": {"coordinates":[16.7402172089,48.3843841553],"type":"Point"}
}