{
  "type": "Feature",
  "properties": {
    "iso:country":"AT",
    "sg:address":"Neue-Welt-H\u00f6he 44b",
    "sg:city":"St. Peter",
    "sg:orig_category":"Ingenieurkonsulenten / Zivilingenieure",
    "sg:phone":"+43 316 463125",
    "sg:postcode":"8042",
    "sg:province":"Steiermark",
    "wof:name":"Hinterberger Wilhelm Dipl-Ing",
    "wof:placetype":"venue"
},
  "geometry": {"coordinates":[15.4928913116,47.063835144],"type":"Point"}
}