{
  "type": "Feature",
  "properties": {
    "addr:full":"Neuhausen 15 Franking Ober\u00f6sterreich 5131",
    "addr:housenumber":"15",
    "addr:postcode":"5131",
    "addr:street":"Neuhausen",
    "iso:country":"AT",
    "sg:address":"Neuhausen 15",
    "sg:city":"Franking",
    "sg:orig_category":"Erdarbeiten",
    "sg:phone":"+43 6277 81130",
    "sg:postcode":"5131",
    "sg:province":"Ober\u00f6sterreich",
    "wof:name":"Pfaffinger Franz",
    "wof:placetype":"venue"
},
  "geometry": {"coordinates":[12.8973865509,48.0453834534],"type":"Point"}
}