{
  "type": "Feature",
  "properties": {
    "addr:full":"Platz 62 Schwarzenbach Nieder\u00f6sterreich 2803",
    "addr:housenumber":"62",
    "addr:postcode":"2803",
    "addr:street":"Platz;Niederoesterreich",
    "iso:country":"AT",
    "sg:address":"Platz 62",
    "sg:city":"Schwarzenbach",
    "sg:orig_category":"Forstverwaltungen",
    "sg:phone":"+43 2645 5456",
    "sg:postcode":"2803",
    "sg:province":"Nieder\u00f6sterreich",
    "wof:name":"Esterhazy Forstverwaltung",
    "wof:placetype":"venue"
},
  "geometry": {"coordinates":[16.3440246582,47.6393699646],"type":"Point"}
}