{
  "type": "Feature",
  "properties": {
    "addr:full":"Gustav-Degen-G 8 Mattersburg Burgenland 7210",
    "addr:housenumber":"8",
    "addr:postcode":"7210",
    "addr:street":"Gustav-Degen-G",
    "iso:country":"AT",
    "sg:address":"Gustav-Degen-G 8",
    "sg:city":"Mattersburg",
    "sg:orig_category":"Bierlokale-Pubs",
    "sg:phone":"+43 2626 62843",
    "sg:postcode":"7210",
    "sg:province":"Burgenland",
    "wof:name":"PEAKOCK-PUB - Irish-Pub",
    "wof:placetype":"venue"
},
  "geometry": {"coordinates":[16.3993473053,47.737071991],"type":"Point"}
}