{
  "type": "Feature",
  "properties": {
    "addr:full":"Grillparzerstr 17 Linz Ober\u00f6sterreich 4020",
    "addr:housenumber":"17",
    "addr:postcode":"4020",
    "addr:street":"Grillparzerstr",
    "iso:country":"AT",
    "sg:address":"Grillparzerstr 17",
    "sg:city":"Linz",
    "sg:orig_category":"Filmproduktionen",
    "sg:phone":"+43 4369 919573092",
    "sg:postcode":"4020",
    "sg:province":"Ober\u00f6sterreich",
    "sg:website":"dieschnittstelle.at",
    "wof:name":"die schniTTstelle",
    "wof:placetype":"venue"
},
  "geometry": {"coordinates":[14.2974538803,48.2930870056],"type":"Point"}
}