{
  "type": "Feature",
  "properties": {
    "addr:full":"Bahnhofstr 8 Ehrwald Tirol 6632",
    "addr:housenumber":"8",
    "addr:postcode":"6632",
    "addr:street":"Bahnhofstr;Tirol",
    "iso:country":"AT",
    "sg:address":"Bahnhofstr 8",
    "sg:city":"Ehrwald",
    "sg:orig_category":"Pensionen / Privatzimmer",
    "sg:phone":"+43 5673 2426",
    "sg:postcode":"6632",
    "sg:province":"Tirol",
    "wof:name":"Schennach Helmut",
    "wof:placetype":"venue"
},
  "geometry": {"coordinates":[10.9164228439,47.4074134827],"type":"Point"}
}