{
  "type": "Feature",
  "properties": {
    "iso:country":"AT",
    "sg:address":"Nr. 29",
    "sg:city":"Pennewang",
    "sg:orig_category":"Industrie, Maschinenbau",
    "sg:phone":"+43 4372 4526179",
    "sg:postcode":"4624",
    "sg:province":"Ober\u00f6sterreich",
    "sg:website":"http://www.leitenbauer.at/",
    "wof:name":"Leitenbauer GMBH",
    "wof:placetype":"venue"
},
  "geometry": {"coordinates":[13.8426761627,48.1287078857],"type":"Point"}
}