{
  "type": "Feature",
  "properties": {
    "addr:full":"Breiter Weg 21a Feldkirch Vorarlberg 6800",
    "addr:housenumber":"21a",
    "addr:postcode":"6800",
    "addr:street":"Breiter Weg",
    "iso:country":"AT",
    "sg:address":"Breiter Weg 21a",
    "sg:city":"Feldkirch",
    "sg:orig_category":"Unternehmensberatung",
    "sg:phone":"+43 5522 31562",
    "sg:postcode":"6800",
    "sg:province":"Vorarlberg",
    "wof:name":"Grobner Marianne Dr & Partner KEG",
    "wof:placetype":"venue"
},
  "geometry": {"coordinates":[9.5617570877,47.2599525452],"type":"Point"}
}