{
  "type": "Feature",
  "properties": {
    "addr:full":"Kernstockg 20 Graz Steiermark 8020",
    "addr:housenumber":"20",
    "addr:postcode":"8020",
    "addr:street":"Kernstockg",
    "iso:country":"AT",
    "sg:address":"Kernstockg 20",
    "sg:city":"Graz",
    "sg:orig_category":"Textilwaren / Einzelhandel",
    "sg:phone":"+43 316 719120",
    "sg:postcode":"8020",
    "sg:province":"Steiermark",
    "wof:name":"MATEX HandelsgesmbH",
    "wof:placetype":"venue"
},
  "geometry": {"coordinates":[15.4281148911,47.0696372986],"type":"Point"}
}