{
  "type": "Feature",
  "properties": {
    "iso:country":"AT",
    "sg:address":"Marktpl 6",
    "sg:city":"Reichenthal",
    "sg:orig_category":"Elektroinstallationsunternehmen",
    "sg:phone":"+43 7214 4027",
    "sg:postcode":"4193",
    "sg:province":"Ober\u00f6sterreich",
    "wof:name":"Elektro-Pachner GmbH & Co KG",
    "wof:placetype":"venue"
},
  "geometry": {"coordinates":[14.3845033646,48.543510437],"type":"Point"}
}