{
  "type": "Feature",
  "properties": {
    "addr:full":"Viktringer Ring 1B Klagenfurt K\u00e4rnten 9020",
    "addr:housenumber":"1b",
    "addr:postcode":"9020",
    "addr:street":"Viktringer Ring;Kaernten",
    "iso:country":"AT",
    "sg:address":"Viktringer Ring 1B",
    "sg:city":"Klagenfurt",
    "sg:classifiers":[
        {
            "category":"Organizations",
            "subcategory":"Political Organization",
            "type":"Services"
        }
    ],
    "sg:phone":"+43 4367 65106774",
    "sg:postcode":"9020",
    "sg:province":"K\u00e4rnten",
    "sg:tags":[
        "mediation"
    ],
    "sg:website":"dermediator.at",
    "wof:name":"Der Mediator/Die Mediatorin Krasser/Amann OEG",
    "wof:placetype":"venue"
},
  "geometry": {"coordinates":[14.3142843246,46.6201705933],"type":"Point"}
}