{
  "type": "Feature",
  "properties": {
    "iso:country":"AT",
    "sg:address":"Otto-Gl\u00f6ckel-Str 6",
    "sg:city":"Traiskirchen",
    "sg:orig_category":"Elektroinstallationsunternehmen",
    "sg:phone":"+43 2252 52291",
    "sg:postcode":"2514",
    "sg:province":"Nieder\u00f6sterreich",
    "wof:name":"Nigl Elektro GesmbH",
    "wof:placetype":"venue"
},
  "geometry": {"coordinates":[16.2906360626,48.014755249],"type":"Point"}
}