{
  "type": "Feature",
  "properties": {
    "addr:full":"Marktplatz 4 Grieskirchen Ober\u00f6sterreich 4710",
    "addr:housenumber":"4",
    "addr:postcode":"4710",
    "addr:street":"Marktplatz",
    "iso:country":"AT",
    "sg:address":"Marktplatz 4",
    "sg:city":"Grieskirchen",
    "sg:classifiers":[
        {
            "category":"Manufacturing",
            "subcategory":"Metals",
            "type":"Manufacturing & Wholesale Goods"
        }
    ],
    "sg:phone":"+43 4372 4868151",
    "sg:postcode":"4710",
    "sg:province":"Ober\u00f6sterreich",
    "sg:tags":[
        "metallurgy",
        "metalworking"
    ],
    "wof:name":"KL\u00d6CKNER STAHL UND METALL GESMBH ZWEIGNIEDERL. GRIESKIRCHEN",
    "wof:placetype":"venue"
},
  "geometry": {"coordinates":[13.8257322311,48.2358856201],"type":"Point"}
}