{
  "type": "Feature",
  "properties": {
    "addr:full":"Schranneng 7A Salzburg Salzburg 5020",
    "addr:housenumber":"7a",
    "addr:postcode":"5020",
    "addr:street":"Schranneng;Salzburg",
    "iso:country":"AT",
    "sg:address":"Schranneng 7A",
    "sg:city":"Salzburg",
    "sg:orig_category":"Arbeitsvermittlung",
    "sg:phone":"+43 662 887293",
    "sg:postcode":"5020",
    "sg:province":"Salzburg",
    "sg:website":"teamwork-one.at",
    "wof:name":"Arbeitsvermittlung teamwork one",
    "wof:placetype":"venue"
},
  "geometry": {"coordinates":[13.0456409454,47.8060340881],"type":"Point"}
}