{
  "type": "Feature",
  "properties": {
    "addr:full":"Kinostr 174 Uttendorf Salzburg 5723",
    "addr:housenumber":"174",
    "addr:postcode":"5723",
    "addr:street":"Uttendorf Salzburg",
    "iso:country":"AT",
    "sg:address":"Kinostr 174",
    "sg:city":"Uttendorf",
    "sg:orig_category":"Pensionen / Privatzimmer",
    "sg:phone":"+43 6563 8315",
    "sg:postcode":"5723",
    "sg:province":"Salzburg",
    "wof:name":"Breitner Fr\u00fchst\u00fcckspension",
    "wof:placetype":"venue"
},
  "geometry": {"coordinates":[12.5663747787,47.2860145569],"type":"Point"}
}