{
  "type": "Feature",
  "properties": {
    "addr:full":"Gruben 15a Axams Tirol 6094",
    "addr:housenumber":"15a",
    "addr:postcode":"6094",
    "addr:street":"Gruben;Tirol",
    "iso:country":"AT",
    "sg:address":"Gruben 15a",
    "sg:city":"Axams",
    "sg:orig_category":"Tischlereien",
    "sg:phone":"+43 4366 41128106",
    "sg:postcode":"6094",
    "sg:province":"Tirol",
    "wof:name":"Haid Daniel",
    "wof:placetype":"venue"
},
  "geometry": {"coordinates":[11.2652816772,47.2360305786],"type":"Point"}
}