{
  "type": "Feature",
  "properties": {
    "addr:full":"Leonfeldner Str 250 Linz Ober\u00f6sterreich 4040",
    "addr:housenumber":"250",
    "addr:postcode":"4040",
    "iso:country":"AT",
    "sg:address":"Leonfeldner Str 250",
    "sg:city":"Linz",
    "sg:orig_category":"Restaurants: Griechisch",
    "sg:phone":"+43 4373 2759808",
    "sg:postcode":"4040",
    "sg:province":"Ober\u00f6sterreich",
    "wof:name":"Restaurant Pomodoro",
    "wof:placetype":"venue"
},
  "geometry": {"coordinates":[14.292637825,48.340927124],"type":"Point"}
}