{
  "type": "Feature",
  "properties": {
    "addr:full":"Josef-Schraffl-Str 2 Lienz Tirol 9900",
    "addr:housenumber":"2",
    "addr:postcode":"9900",
    "addr:street":"Josef-Schraffl-Str;Tirol",
    "iso:country":"AT",
    "sg:address":"Josef-Schraffl-Str 2",
    "sg:city":"Lienz",
    "sg:orig_category":"Isolierungen",
    "sg:phone":"+43 4348 52619610",
    "sg:postcode":"9900",
    "sg:province":"Tirol",
    "wof:name":"AKIT Isolierungen u. Pflasterungen GmbH",
    "wof:placetype":"venue"
},
  "geometry": {"coordinates":[12.7750291824,46.8322143555],"type":"Point"}
}