{
  "type": "Feature",
  "properties": {
    "iso:country":"AT",
    "sg:address":"Martinstr 96",
    "sg:city":"Wien",
    "sg:orig_category":"Tanzschulen",
    "sg:phone":"+43 1 4065709",
    "sg:postcode":"1180",
    "sg:province":"Wien",
    "wof:name":"Tanzschule Wiater",
    "wof:placetype":"venue"
},
  "geometry": {"coordinates":[16.3423843384,48.2262191772],"type":"Point"}
}