{
  "type": "Feature",
  "properties": {
    "iso:country":"AT",
    "sg:address":"Dragonerstr 44",
    "sg:city":"Wels",
    "sg:orig_category":"Tabaktrafiken",
    "sg:phone":"+43 7242 45121",
    "sg:postcode":"4600",
    "sg:province":"Ober\u00f6sterreich",
    "wof:name":"Balasch Peter",
    "wof:placetype":"venue"
},
  "geometry": {"coordinates":[14.0104637146,48.1558265686],"type":"Point"}
}