{
  "type": "Feature",
  "properties": {
    "addr:full":"Nr 53 Deutsch Kaltenbrunn Burgenland 7572",
    "addr:postcode":"7572",
    "addr:street":"Nr",
    "iso:country":"AT",
    "sg:address":"Nr 53",
    "sg:city":"Deutsch Kaltenbrunn",
    "sg:classifiers":[
        {
            "category":"Sports & Exercise",
            "subcategory":"Gym",
            "type":"Entertainment"
        }
    ],
    "sg:phone":"+43 3383 30521",
    "sg:postcode":"7572",
    "sg:province":"Burgenland",
    "sg:tags":[
        "meditation"
    ],
    "wof:name":"Meditationshaus Rohrbrunn - Holosophische Ges \u00f6sterreich",
    "wof:placetype":"venue"
},
  "geometry": {"coordinates":[16.1058235168,47.090461731],"type":"Point"}
}