{
  "type": "Feature",
  "properties": {
    "addr:full":"Pelzg 3 Baden Nieder\u00f6sterreich 2500",
    "addr:housenumber":"3",
    "addr:postcode":"2500",
    "addr:street":"Pelzg;Niederoesterreich",
    "iso:country":"AT",
    "sg:address":"Pelzg 3",
    "sg:city":"Baden",
    "sg:orig_category":"Pensionen / Privatzimmer",
    "sg:phone":"+43 2252 44561",
    "sg:postcode":"2500",
    "sg:province":"Nieder\u00f6sterreich",
    "wof:name":"Hotel Rauch",
    "wof:placetype":"venue"
},
  "geometry": {"coordinates":[16.2266941071,48.0076751709],"type":"Point"}
}