{
  "type": "Feature",
  "properties": {
    "addr:full":"Hauptstr 2 Hermagor K\u00e4rnten 9620",
    "addr:housenumber":"2",
    "addr:postcode":"9620",
    "addr:street":"Hauptstr;Kaernten",
    "iso:country":"AT",
    "sg:address":"Hauptstr 2",
    "sg:city":"Hermagor",
    "sg:orig_category":"Fleischhauereien",
    "sg:phone":"+43 4282 2129",
    "sg:postcode":"9620",
    "sg:province":"K\u00e4rnten",
    "wof:name":"Fercher KG",
    "wof:placetype":"venue"
},
  "geometry": {"coordinates":[13.3708114624,46.6273841858],"type":"Point"}
}