{
  "type": "Feature",
  "properties": {
    "addr:full":"Lassallestrasse 9 Wien Wien 1020",
    "addr:housenumber":"9",
    "addr:postcode":"1020",
    "addr:street":"Lassallestrasse",
    "iso:country":"AT",
    "sg:address":"Lassallestrasse 9",
    "sg:city":"Wien",
    "sg:classifiers":[
        {
            "category":"Banks & Credit Unions",
            "subcategory":"Investment Brokerage",
            "type":"Services"
        }
    ],
    "sg:phone":"+43 1 501450",
    "sg:postcode":"1020",
    "sg:province":"Wien",
    "sg:tags":[
        "training",
        "application",
        "processing",
        "consulting",
        "course",
        "data"
    ],
    "sg:website":"telekom.at",
    "wof:name":"Telekom Austria GmbH",
    "wof:placetype":"venue"
},
  "geometry": {"coordinates":[16.3992786407,48.2231216431],"type":"Point"}
}