{
  "type": "Feature",
  "properties": {
    "addr:full":"Hadrawagasse 36 Wien Wien 1220",
    "addr:housenumber":"36",
    "addr:postcode":"1220",
    "addr:street":"Hadrawagasse",
    "iso:country":"AT",
    "sg:address":"Hadrawagasse 36",
    "sg:city":"Wien",
    "sg:classifiers":[
        {
            "category":"Utilities",
            "subcategory":"Water",
            "type":"Services"
        }
    ],
    "sg:phone":"+43 1 2032814",
    "sg:postcode":"1220",
    "sg:province":"Wien",
    "sg:tags":[
        "measuring",
        "electromagnetic",
        "compatibility",
        "emc",
        "equipment"
    ],
    "sg:website":"mtm.at",
    "wof:name":"MTM-Systeme",
    "wof:placetype":"venue"
},
  "geometry": {"coordinates":[16.5371627808,48.2137832642],"type":"Point"}
}