{
  "type": "Feature",
  "properties": {
    "iso:country":"AT",
    "sg:address":"Rochusg 4",
    "sg:city":"Salzburg",
    "sg:orig_category":"Unternehmensberatung",
    "sg:phone":"+43 662 8492590",
    "sg:postcode":"5020",
    "sg:province":"Salzburg",
    "wof:name":"GFB & Partner Unternehmensberatung Ges f betriebswirtschaftliche Beratung GesmbH & Co",
    "wof:placetype":"venue"
},
  "geometry": {"coordinates":[13.0212240219,47.7964134216],"type":"Point"}
}