{
  "type": "Feature",
  "properties": {
    "iso:country":"AT",
    "sg:address":"Klosterstrasse 73",
    "sg:orig_category":"Medien, Zeitungen And Zeitschriften",
    "sg:phone":"+43 4372 5280717",
    "sg:postcode":"4403",
    "sg:website":"http://www.infomed.at",
    "wof:name":"Redaktionsb\u00fcro Riener",
    "wof:placetype":"venue"
},
  "geometry": {"coordinates":[14.4123268127,48.0631980896],"type":"Point"}
}