{
  "type": "Feature",
  "properties": {
    "iso:country":"AT",
    "sg:address":"Hauptpl 34",
    "sg:city":"Retz",
    "sg:classifiers":[
        {
            "category":"Shopping",
            "subcategory":"Thrift Store",
            "type":"Retail Goods"
        }
    ],
    "sg:phone":"+43 4329 4228145",
    "sg:postcode":"2070",
    "sg:province":"Nieder\u00f6sterreich",
    "sg:tags":[
        "second-hand-shops"
    ],
    "wof:name":"Schatztruhe - Caritas Projekt Carla Retz",
    "wof:placetype":"venue"
},
  "geometry": {"coordinates":[15.9513998032,48.7571487427],"type":"Point"}
}