{
  "type": "Feature",
  "properties": {
    "iso:country":"AT",
    "sg:address":"Mariazeller Str 52",
    "sg:city":"Kapfenberg",
    "sg:orig_category":"\u00c3\u201erzte / F Allgemeinmedizin",
    "sg:phone":"+43 4338 6225655",
    "sg:postcode":"8605",
    "sg:province":"Steiermark",
    "wof:name":"Schulhofer Hannes Dr",
    "wof:placetype":"venue"
},
  "geometry": {"coordinates":[15.2800159454,47.4470291138],"type":"Point"}
}