{
  "type": "Feature",
  "properties": {
    "addr:full":"Oberham 18 Krenglbach Ober\u00f6sterreich 4631",
    "addr:housenumber":"18",
    "addr:postcode":"4631",
    "addr:street":"Oberham",
    "iso:country":"AT",
    "sg:address":"Oberham 18",
    "sg:city":"Krenglbach",
    "sg:orig_category":"Botendienste",
    "sg:phone":"+43 7249 46502",
    "sg:postcode":"4631",
    "sg:province":"Ober\u00f6sterreich",
    "wof:name":"K. Luttinger - Express-Botendienst",
    "wof:placetype":"venue"
},
  "geometry": {"coordinates":[13.9564571381,48.1882591248],"type":"Point"}
}