{
  "type": "Feature",
  "properties": {
    "iso:country":"AT",
    "sg:address":"Hauptpl 12",
    "sg:city":"Gleisdorf",
    "sg:orig_category":"Eventmarketing, Videogro\u00c3\u0178bildprojektionen, Videoanlagen / Vermietung, Kongress- U Seminarorganisati",
    "sg:phone":"+43 3112 38377",
    "sg:postcode":"8200",
    "sg:province":"Steiermark",
    "sg:website":"www.4events.at",
    "wof:name":"4Events Werbung und Marketing",
    "wof:placetype":"venue"
},
  "geometry": {"coordinates":[15.710682869,47.1053276062],"type":"Point"}
}