{
  "type": "Feature",
  "properties": {
    "iso:country":"AT",
    "sg:address":"Ro\u00dfmanng 41a",
    "sg:city":"Graz",
    "sg:orig_category":"Psychotherapie",
    "sg:phone":"+43 699 10060933",
    "sg:postcode":"8010",
    "sg:province":"Steiermark",
    "wof:name":"Pereira de Castro Lobo Ruth Mag",
    "wof:placetype":"venue"
},
  "geometry": {"coordinates":[15.4704008102,47.0862731934],"type":"Point"}
}