{
  "type": "Feature",
  "properties": {
    "addr:full":"Am Waldrand 47 Seeboden K\u00e4rnten 9871",
    "addr:housenumber":"47",
    "addr:postcode":"9871",
    "addr:street":"Am Waldrand;Kaernten",
    "iso:country":"AT",
    "sg:address":"Am Waldrand 47",
    "sg:city":"Seeboden",
    "sg:orig_category":"Pensionen / Privatzimmer",
    "sg:phone":"+43 4762 82801",
    "sg:postcode":"9871",
    "sg:province":"K\u00e4rnten",
    "wof:name":"G\u00e4stehaus Johanna",
    "wof:placetype":"venue"
},
  "geometry": {"coordinates":[13.5341157913,46.8178710938],"type":"Point"}
}