{
  "type": "Feature",
  "properties": {
    "addr:full":"Cobenzlg 34 Wien Wien 1190",
    "addr:housenumber":"34",
    "addr:postcode":"1190",
    "addr:street":"Cobenzlg",
    "iso:country":"AT",
    "sg:address":"Cobenzlg 34",
    "sg:city":"Wien",
    "sg:orig_category":"Heurigen / Buschenschank",
    "sg:phone":"+43 1 32032330",
    "sg:postcode":"1190",
    "sg:province":"Wien",
    "wof:name":"Zum Martin Sepp",
    "wof:placetype":"venue"
},
  "geometry": {"coordinates":[16.3385429382,48.257724762],"type":"Point"}
}