{
  "type": "Feature",
  "properties": {
    "addr:full":"Millst\u00e4tter Str 31 Feld am See K\u00e4rnten 9544",
    "addr:postcode":"9544",
    "addr:street":"Str 31;Kaernten",
    "iso:country":"AT",
    "sg:address":"Millst\u00e4tter Str 31",
    "sg:city":"Feld am See",
    "sg:orig_category":"Pensionen / Privatzimmer",
    "sg:phone":"+43 676 7542580",
    "sg:postcode":"9544",
    "sg:province":"K\u00e4rnten",
    "wof:name":"Winkler Christine",
    "wof:placetype":"venue"
},
  "geometry": {"coordinates":[13.7459144592,46.7742156982],"type":"Point"}
}