{
  "type": "Feature",
  "properties": {
    "iso:country":"AT",
    "sg:address":"Bahnhofstr 8",
    "sg:city":"Kematen in Tirol",
    "sg:orig_category":"Banken U Sparkassen",
    "sg:phone":"+43 4352 322365",
    "sg:postcode":"6175",
    "sg:province":"Tirol",
    "wof:name":"Tiroler Sparkasse Bank AG Innsbruck",
    "wof:placetype":"venue"
},
  "geometry": {"coordinates":[11.2718572617,47.255821228],"type":"Point"}
}