{
  "type": "Feature",
  "properties": {
    "iso:country":"AT",
    "sg:address":"Wischerstr 8",
    "sg:city":"Linz",
    "sg:orig_category":"Lebens- U Sozialberatung",
    "sg:phone":"+43 4366 47868377",
    "sg:postcode":"4040",
    "sg:province":"Ober\u00f6sterreich",
    "wof:name":"Dirnberger Ulli Lebens u Sozialberatung",
    "wof:placetype":"venue"
},
  "geometry": {"coordinates":[14.2788219452,48.31615448],"type":"Point"}
}