{
  "type": "Feature",
  "properties": {
    "addr:full":"Hauptstr 25 Kronstorf Ober\u00f6sterreich 4484",
    "addr:housenumber":"25",
    "addr:postcode":"4484",
    "addr:street":"Hauptstr",
    "iso:country":"AT",
    "sg:address":"Hauptstr 25",
    "sg:city":"Kronstorf",
    "sg:orig_category":"Immobilienmakler",
    "sg:phone":"+43 676 6800100",
    "sg:postcode":"4484",
    "sg:province":"Ober\u00f6sterreich",
    "wof:name":"PLF Projektentwicklung & Management GmbH",
    "wof:placetype":"venue"
},
  "geometry": {"coordinates":[14.4656057358,48.1434783936],"type":"Point"}
}