{
  "type": "Feature",
  "properties": {
    "addr:full":"Hauptpl 19 Leibnitz Steiermark 8430",
    "addr:housenumber":"19",
    "addr:postcode":"8430",
    "addr:street":"Hauptpl;Steiermark",
    "iso:country":"AT",
    "sg:address":"Hauptpl 19",
    "sg:city":"Leibnitz",
    "sg:orig_category":"Werbeagenturen",
    "sg:phone":"+43 3452 71135",
    "sg:postcode":"8430",
    "sg:province":"Steiermark",
    "wof:name":"Public Relations Group - Mag Guido Jaklitsch",
    "wof:placetype":"venue"
},
  "geometry": {"coordinates":[15.5393371582,46.7816390991],"type":"Point"}
}