{
  "type": "Feature",
  "properties": {
    "iso:country":"AT",
    "sg:address":"St. Georgener Str 5",
    "sg:city":"Traismauer",
    "sg:orig_category":"Heurigen / Buschenschank",
    "sg:phone":"+43 2783 5970",
    "sg:postcode":"3133",
    "sg:province":"Nieder\u00f6sterreich",
    "wof:name":"Zum Dorfheurigen",
    "wof:placetype":"venue"
},
  "geometry": {"coordinates":[15.7391004562,48.3664665222],"type":"Point"}
}