{
  "type": "Feature",
  "properties": {
    "iso:country":"AT",
    "sg:address":"Nr 62",
    "sg:city":"Arnfels",
    "sg:orig_category":"Pensionen / Privatzimmer",
    "sg:phone":"+43 3455 465",
    "sg:postcode":"8454",
    "sg:province":"Steiermark",
    "wof:name":"Silberschneider - Urlaub am Bauernhof",
    "wof:placetype":"venue"
},
  "geometry": {"coordinates":[15.4017324448,46.6779937744],"type":"Point"}
}