{
  "type": "Feature",
  "properties": {
    "addr:full":"Gst\u00f6ttnerhofstrasse 8 Linz Ober\u00f6sterreich 4040",
    "addr:housenumber":"8",
    "addr:postcode":"4040",
    "addr:street":"Gstoettnerhofstrasse",
    "iso:country":"AT",
    "sg:address":"Gst\u00f6ttnerhofstrasse 8",
    "sg:city":"Linz",
    "sg:classifiers":[
        {
            "category":"Professional",
            "subcategory":"Management & Consulting",
            "type":"Services"
        }
    ],
    "sg:phone":"+43 732 737375",
    "sg:postcode":"4040",
    "sg:province":"Ober\u00f6sterreich",
    "sg:tags":[
        "hr",
        "resource",
        "consultancy",
        "human"
    ],
    "sg:website":"www.yourjob.at",
    "wof:name":"Yourjob Service GmbH",
    "wof:placetype":"venue"
},
  "geometry": {"coordinates":[14.2827129364,48.3160171509],"type":"Point"}
}