{
  "type": "Feature",
  "properties": {
    "addr:full":"Prof.-Dr.-Anton-Kathrein-Strasse 2 Niederndorf Tirol 6342",
    "addr:housenumber":"2",
    "addr:postcode":"6342",
    "addr:street":"Prof.-Dr.-Anton-Kathrein-Strasse",
    "iso:country":"AT",
    "sg:address":"Prof.-Dr.-Anton-Kathrein-Strasse 2",
    "sg:city":"Niederndorf",
    "sg:classifiers":[
        {
            "category":"Communications",
            "subcategory":"Radio Station",
            "type":"Services"
        }
    ],
    "sg:phone":"+43 5373 62190",
    "sg:postcode":"6342",
    "sg:province":"Tirol",
    "sg:tags":[
        "steel",
        "stainless",
        "fitting"
    ],
    "sg:website":"gronbach.at",
    "wof:name":"Wilhelm Gronbach GmbH & Co KG",
    "wof:placetype":"venue"
},
  "geometry": {"coordinates":[12.1972293854,47.6475524902],"type":"Point"}
}