{
  "type": "Feature",
  "properties": {
    "addr:full":"Sahulkastr 3/6 Wien Wien 1100",
    "addr:housenumber":"3 / 6",
    "addr:postcode":"1100",
    "addr:street":"Sahulkastr",
    "iso:country":"AT",
    "sg:address":"Sahulkastr 3/6",
    "sg:city":"Wien",
    "sg:orig_category":"Tabaktrafiken",
    "sg:phone":"+43 1 6161577",
    "sg:postcode":"1100",
    "sg:province":"Wien",
    "wof:name":"Neubauer Norbert",
    "wof:placetype":"venue"
},
  "geometry": {"coordinates":[16.3647899628,48.1632995605],"type":"Point"}
}