{
  "type": "Feature",
  "properties": {
    "addr:full":"Schl Altendorff-Str 2 Hallein Salzburg 5400",
    "addr:housenumber":"2",
    "addr:postcode":"5400",
    "addr:street":"Altendorff-Str;Salzburg",
    "iso:country":"AT",
    "sg:address":"Schl Altendorff-Str 2",
    "sg:city":"Hallein",
    "sg:orig_category":"Restaurants: Spanisch",
    "sg:phone":"+43 6245 84223",
    "sg:postcode":"5400",
    "sg:province":"Salzburg",
    "wof:name":"Restaurant Toro Toro",
    "wof:placetype":"venue"
},
  "geometry": {"coordinates":[13.1115207672,47.6932296753],"type":"Point"}
}