{
  "type": "Feature",
  "properties": {
    "iso:country":"AT",
    "sg:address":"Gfiederleiten 1",
    "sg:city":"Ottensheim",
    "sg:orig_category":"Fotografen",
    "sg:phone":"+43 4372 3482468",
    "sg:postcode":"4100",
    "sg:province":"Ober\u00f6sterreich",
    "wof:name":"Rubra - Brandst\u00e4tter Rudolf",
    "wof:placetype":"venue"
},
  "geometry": {"coordinates":[14.1870527267,48.3397369385],"type":"Point"}
}