{
  "type": "Feature",
  "properties": {
    "addr:full":"Gsaritzen 20 St. Veit in Defereggen Tirol 9962",
    "addr:housenumber":"20",
    "addr:postcode":"9962",
    "addr:street":"Gsaritzen;Tirol",
    "iso:country":"AT",
    "sg:address":"Gsaritzen 20",
    "sg:city":"St. Veit in Defereggen",
    "sg:orig_category":"Volksschulen",
    "sg:phone":"+43 4348 79253",
    "sg:postcode":"9962",
    "sg:province":"Tirol",
    "wof:name":"Volksschule",
    "wof:placetype":"venue"
},
  "geometry": {"coordinates":[12.4215183258,46.92628479],"type":"Point"}
}