{
  "type": "Feature",
  "properties": {
    "addr:full":"Markt 10 Peilstein im M\u00fchlviertel Ober\u00f6sterreich 4153",
    "addr:housenumber":"10",
    "addr:postcode":"4153",
    "addr:street":"Markt;Im Muehlviertel Oberoesterreich",
    "iso:country":"AT",
    "sg:address":"Markt 10",
    "sg:city":"Peilstein im M\u00fchlviertel",
    "sg:orig_category":"Spenglereien",
    "sg:phone":"+43 4372 8772170",
    "sg:postcode":"4153",
    "sg:province":"Ober\u00f6sterreich",
    "wof:name":"Dolzer Karl",
    "wof:placetype":"venue"
},
  "geometry": {"coordinates":[13.8940515518,48.6182785034],"type":"Point"}
}