{
  "type": "Feature",
  "properties": {
    "addr:full":"Teichstr 43 Neuzeug Ober\u00f6sterreich 4523",
    "addr:housenumber":"43",
    "addr:postcode":"4523",
    "addr:street":"Teichstr",
    "iso:country":"AT",
    "sg:address":"Teichstr 43",
    "sg:city":"Neuzeug",
    "sg:orig_category":"Solartechnik",
    "sg:phone":"+43 4372 594973",
    "sg:postcode":"4523",
    "sg:province":"Ober\u00f6sterreich",
    "wof:name":"Phocos Europe GmbH",
    "wof:placetype":"venue"
},
  "geometry": {"coordinates":[14.3221750259,48.0261383057],"type":"Point"}
}