{
  "type": "Feature",
  "properties": {
    "addr:full":"Weilhartstr 84 Ostermiething Ober\u00f6sterreich 5121",
    "addr:housenumber":"84",
    "addr:postcode":"5121",
    "addr:street":"Weilhartstr",
    "iso:country":"AT",
    "sg:address":"Weilhartstr 84",
    "sg:city":"Ostermiething",
    "sg:orig_category":"Rettungsdienste",
    "sg:phone":"+43 6278 6244",
    "sg:postcode":"5121",
    "sg:province":"Ober\u00f6sterreich",
    "wof:name":"Rotes Kreuz \u00f6sterr Ortsstelle Riedersbach",
    "wof:placetype":"venue"
},
  "geometry": {"coordinates":[12.8373250961,48.0346221924],"type":"Point"}
}