{
  "type": "Feature",
  "properties": {
    "addr:full":"Rotenturmstr 29 Wien Wien 1010",
    "addr:housenumber":"29",
    "addr:postcode":"1010",
    "addr:street":"Rotenturmstr",
    "iso:country":"AT",
    "sg:address":"Rotenturmstr 29",
    "sg:city":"Wien",
    "sg:orig_category":"Restaurants: Amerikanisch",
    "sg:phone":"+43 4315 332072",
    "sg:postcode":"1010",
    "sg:province":"Wien",
    "wof:name":"McDonald's Restaurant",
    "wof:placetype":"venue"
},
  "geometry": {"coordinates":[16.3758678436,48.2117347717],"type":"Point"}
}