{
  "type": "Feature",
  "properties": {
    "addr:full":"Landstra\u00dfer Hauptstra\u00dfe 71/2 Wien Wien 1030",
    "addr:housenumber":"71 / 2",
    "addr:postcode":"1030",
    "addr:street":"Landstrasser Hauptstrasse",
    "iso:country":"AT",
    "sg:address":"Landstra\u00dfer Hauptstra\u00dfe 71/2",
    "sg:city":"Wien",
    "sg:orig_category":"Dienstleistungen, Sonstige Dienstleistungen",
    "sg:phone":"+43 4317 1728429",
    "sg:postcode":"1030",
    "sg:province":"Wien",
    "sg:website":"http://www.stratcon.at",
    "wof:name":"STRATCON Management Consulting",
    "wof:placetype":"venue"
},
  "geometry": {"coordinates":[16.4025096893,48.1936683655],"type":"Point"}
}