{
  "type": "Feature",
  "properties": {
    "iso:country":"AT",
    "sg:address":"Nr 9",
    "sg:city":"Diersbach",
    "sg:orig_category":"Autohandel",
    "sg:phone":"+43 7763 2212",
    "sg:postcode":"4776",
    "sg:province":"Ober\u00f6sterreich",
    "wof:name":"Alteneder Josef",
    "wof:placetype":"venue"
},
  "geometry": {"coordinates":[13.571803093,48.4126396179],"type":"Point"}
}