{
  "type": "Feature",
  "properties": {
    "iso:country":"AT",
    "sg:address":"Wollsberg 30a",
    "sg:city":"Steinerkirchen an der Traun",
    "sg:classifiers":[
        {
            "category":"Building & Trades",
            "subcategory":"Plumbing",
            "type":"Services"
        }
    ],
    "sg:phone":"+43 7241 5905",
    "sg:postcode":"4652",
    "sg:province":"Ober\u00f6sterreich",
    "sg:tags":[
        "supraregional",
        "gas"
    ],
    "wof:name":"Johann Scheureder",
    "wof:placetype":"venue"
},
  "geometry": {"coordinates":[14.0156898499,48.0741004944],"type":"Point"}
}