{
  "type": "Feature",
  "properties": {
    "iso:country":"AT",
    "sg:address":"Maria-Theresia-Str. 41",
    "sg:city":"Wels",
    "sg:classifiers":[
        {
            "category":"Food & Beverages",
            "subcategory":"Groceries & Convenience Stores",
            "type":"Retail Goods"
        }
    ],
    "sg:phone":"+43 4372 4241848",
    "sg:postcode":"4600",
    "sg:province":"Ober\u00f6sterreich",
    "sg:tags":[
        "drink"
    ],
    "wof:name":"DIAMANT-NAHRUNGSMITTEL GESMBH & CO KG",
    "wof:placetype":"venue"
},
  "geometry": {"coordinates":[14.0128498077,48.1539382935],"type":"Point"}
}