{
  "type": "Feature",
  "properties": {
    "addr:full":"Meister Thomas-Str 10 Villach K\u00e4rnten 9500",
    "addr:housenumber":"10",
    "addr:postcode":"9500",
    "addr:street":"Kaernten",
    "iso:country":"AT",
    "sg:address":"Meister Thomas-Str 10",
    "sg:city":"Villach",
    "sg:orig_category":"\u00c3\u201erzte / F Allgemeinmedizin",
    "sg:phone":"+43 4242 230874",
    "sg:postcode":"9500",
    "sg:province":"K\u00e4rnten",
    "wof:name":"Jakob Gerd Dr",
    "wof:placetype":"venue"
},
  "geometry": {"coordinates":[13.8458061218,46.6248703003],"type":"Point"}
}