{
  "type": "Feature",
  "properties": {
    "iso:country":"AT",
    "sg:address":"Pfeifferg 6",
    "sg:city":"Wien",
    "sg:orig_category":"Immobilienmakler",
    "sg:phone":"+43 1 8939696",
    "sg:postcode":"1150",
    "sg:province":"Wien",
    "wof:name":"Kern & Partner OEG Realit\u00e4tenkanzlei",
    "wof:placetype":"venue"
},
  "geometry": {"coordinates":[16.3359203339,48.1881370544],"type":"Point"}
}