{
  "type": "Feature",
  "properties": {
    "addr:full":"Bundesstr 68 Wimpassing im Schwarzatale Nieder\u00f6sterreich 2632",
    "addr:housenumber":"68",
    "addr:postcode":"2632",
    "addr:street":"Bundesstr",
    "iso:country":"AT",
    "sg:address":"Bundesstr 68",
    "sg:city":"Wimpassing im Schwarzatale",
    "sg:orig_category":"Blumenbinder",
    "sg:phone":"+43 4326 3038901",
    "sg:postcode":"2632",
    "sg:province":"Nieder\u00f6sterreich",
    "wof:name":"Blumeninsel Spanbl\u00f6chl",
    "wof:placetype":"venue"
},
  "geometry": {"coordinates":[16.023607254,47.6983032227],"type":"Point"}
}