{
  "type": "Feature",
  "properties": {
    "addr:full":"Bahnhofstr 40 Gratwein Steiermark 8112",
    "addr:housenumber":"40",
    "addr:postcode":"8112",
    "addr:street":"Bahnhofstr",
    "iso:country":"AT",
    "sg:address":"Bahnhofstr 40",
    "sg:city":"Gratwein",
    "sg:classifiers":[
        {
            "category":"Travel",
            "subcategory":"Hotels & Motels",
            "type":"Entertainment"
        }
    ],
    "sg:phone":"+43 4331 2451276",
    "sg:postcode":"8112",
    "sg:province":"Steiermark",
    "wof:name":"Hotel-Restaurant Fischerwirt",
    "wof:placetype":"venue"
},
  "geometry": {"coordinates":[15.3237466812,47.1303596497],"type":"Point"}
}