{
  "type": "Feature",
  "properties": {
    "iso:country":"AT",
    "sg:address":"Amtmannsweg 2",
    "sg:city":"Krumpendorf",
    "sg:orig_category":"Pensionen / Privatzimmer",
    "sg:phone":"+43 4342 292766",
    "sg:postcode":"9201",
    "sg:province":"K\u00e4rnten",
    "wof:name":"Pension Sonnenh\u00fcgel",
    "wof:placetype":"venue"
},
  "geometry": {"coordinates":[14.2174348831,46.6263999939],"type":"Point"}
}