{
  "type": "Feature",
  "properties": {
    "addr:full":"Bennopl 4 Wien Wien 1080",
    "addr:housenumber":"4",
    "addr:postcode":"1080",
    "addr:street":"Bennopl",
    "iso:country":"AT",
    "sg:address":"Bennopl 4",
    "sg:city":"Wien",
    "sg:orig_category":"Tankstellen",
    "sg:phone":"+43 1 40651110",
    "sg:postcode":"1080",
    "sg:province":"Wien",
    "wof:name":"AWI-Diskont",
    "wof:placetype":"venue"
},
  "geometry": {"coordinates":[16.3418102264,48.2119026184],"type":"Point"}
}