{
  "type": "Feature",
  "properties": {
    "addr:full":"V\u00f6lklpl 2 St. P\u00f6lten Nieder\u00f6sterreich 3100",
    "addr:housenumber":"2",
    "addr:postcode":"3100",
    "addr:street":"Voelklpl",
    "iso:country":"AT",
    "sg:address":"V\u00f6lklpl 2",
    "sg:city":"St. P\u00f6lten",
    "sg:orig_category":"Politische Parteien",
    "sg:phone":"+43 2742 3520190",
    "sg:postcode":"3100",
    "sg:province":"Nieder\u00f6sterreich",
    "wof:name":"\u00f6sterreichische Volkspartei (\u00f6VP)",
    "wof:placetype":"venue"
},
  "geometry": {"coordinates":[-76.07303619379999,41.7845001221],"type":"Point"}
}