{
  "type": "Feature",
  "properties": {
    "iso:country":"AT",
    "sg:address":"Wipplingerstr 23",
    "sg:city":"Wien",
    "sg:classifiers":[
        {
            "category":"Professional",
            "subcategory":"Computer Services",
            "type":"Services"
        }
    ],
    "sg:phone":"+43 4312 4777",
    "sg:postcode":"1010",
    "sg:province":"Wien",
    "sg:tags":[
        "software"
    ],
    "wof:name":"A4 Business Solutions GmbH",
    "wof:placetype":"venue"
},
  "geometry": {"coordinates":[16.3680953979,48.212802887],"type":"Point"}
}