{
  "type": "Feature",
  "properties": {
    "addr:full":"Drautalstrasse 8 Feistritz an der Drau K\u00e4rnten 9710",
    "addr:housenumber":"8",
    "addr:postcode":"9710",
    "addr:street":"Drautalstrasse",
    "iso:country":"AT",
    "sg:address":"Drautalstrasse 8",
    "sg:city":"Feistritz an der Drau",
    "sg:classifiers":[
        {
            "category":"Retail",
            "subcategory":"Auto Repair",
            "type":"Services"
        }
    ],
    "sg:phone":"+43 4245 2091",
    "sg:postcode":"9710",
    "sg:province":"K\u00e4rnten",
    "sg:tags":[
        "body",
        "car"
    ],
    "wof:name":"Kurt Schaller",
    "wof:placetype":"venue"
},
  "geometry": {"coordinates":[13.6812143326,46.6893577576],"type":"Point"}
}