{
  "type": "Feature",
  "properties": {
    "iso:country":"AT",
    "sg:address":"Fritz-Konir-Gasse 35",
    "sg:city":"Breitenfurt",
    "sg:classifiers":[
        {
            "category":"Banks & Credit Unions",
            "subcategory":"Bank",
            "type":"Services"
        }
    ],
    "sg:phone":"+43 2239 2576",
    "sg:postcode":"2384",
    "sg:province":"Nieder\u00f6sterreich",
    "sg:tags":[
        "hydraulics",
        "high-pressure"
    ],
    "wof:name":"Rositta R\u00fchrer",
    "wof:placetype":"venue"
},
  "geometry": {"coordinates":[16.1833515167,48.1283607483],"type":"Point"}
}