{
  "type": "Feature",
  "properties": {
    "addr:full":"Zemannstr 32 Freistadt Ober\u00f6sterreich 4240",
    "addr:housenumber":"32",
    "addr:postcode":"4240",
    "addr:street":"Zemannstr",
    "iso:country":"AT",
    "sg:address":"Zemannstr 32",
    "sg:city":"Freistadt",
    "sg:orig_category":"Rauchfangkehrer",
    "sg:phone":"+43 7942 72290",
    "sg:postcode":"4240",
    "sg:province":"Ober\u00f6sterreich",
    "wof:name":"M\u00fcller KEG",
    "wof:placetype":"venue"
},
  "geometry": {"coordinates":[14.504237175,48.5064125061],"type":"Point"}
}