{
  "type": "Feature",
  "properties": {
    "iso:country":"AT",
    "sg:address":"Nr 57",
    "sg:city":"Paldau",
    "sg:orig_category":"Alteisen U Altmetalle",
    "sg:phone":"+43 4331 5022650",
    "sg:postcode":"8341",
    "sg:province":"Steiermark",
    "wof:name":"Hadler Otmar",
    "wof:placetype":"venue"
},
  "geometry": {"coordinates":[15.7963991165,46.9407424927],"type":"Point"}
}