{
  "type": "Feature",
  "properties": {
    "addr:full":"Ebentaler Strasse 140 Klagenfurt K\u00e4rnten 9020",
    "addr:housenumber":"140",
    "addr:postcode":"9020",
    "addr:street":"Ebentaler Strasse;Kaernten",
    "iso:country":"AT",
    "sg:address":"Ebentaler Strasse 140",
    "sg:city":"Klagenfurt",
    "sg:classifiers":[
        {
            "category":"Building & Trades",
            "subcategory":"Electrical",
            "type":"Services"
        }
    ],
    "sg:phone":"+43 463 3834",
    "sg:postcode":"9020",
    "sg:province":"K\u00e4rnten",
    "sg:tags":[
        "aluminium",
        "electrolytic",
        "capacitor"
    ],
    "sg:website":"bccomponents.com",
    "wof:name":"BCcomponents Austria GmbH",
    "wof:placetype":"venue"
},
  "geometry": {"coordinates":[14.338637352,46.6143989563],"type":"Point"}
}