{
  "type": "Feature",
  "properties": {
    "iso:country":"AT",
    "sg:address":"Gewerbehofstr 359",
    "sg:city":"Wals",
    "sg:orig_category":"Reifen U Reifendienste",
    "sg:phone":"+43 4366 28529290",
    "sg:postcode":"5071",
    "sg:province":"Salzburg",
    "wof:name":"Reifen Bruckm\u00fcller",
    "wof:placetype":"venue"
},
  "geometry": {"coordinates":[12.9948348999,47.8155632019],"type":"Point"}
}