{
  "type": "Feature",
  "properties": {
    "addr:full":"Loferer Str 11 Saalfelden am Steinernen Meer Salzburg 5760",
    "addr:postcode":"5760",
    "addr:street":"Str 11;Salzburg",
    "iso:country":"AT",
    "sg:address":"Loferer Str 11",
    "sg:city":"Saalfelden am Steinernen Meer",
    "sg:orig_category":"Non-Classified Establishments",
    "sg:phone":"+43 6582 723820",
    "sg:postcode":"5760",
    "sg:province":"Salzburg",
    "wof:name":"Pfarramt r\u00f6m kath",
    "wof:placetype":"venue"
},
  "geometry": {"coordinates":[12.8487949371,47.4275131226],"type":"Point"}
}