{
  "type": "Feature",
  "properties": {
    "addr:full":"Villacher Str 2 St. Veit an der Glan K\u00e4rnten 9300",
    "addr:housenumber":"2",
    "addr:postcode":"9300",
    "addr:street":"Str;Kaernten",
    "iso:country":"AT",
    "sg:address":"Villacher Str 2",
    "sg:city":"St. Veit an der Glan",
    "sg:orig_category":"Tabaktrafiken",
    "sg:phone":"+43 4212 3529",
    "sg:postcode":"9300",
    "sg:province":"K\u00e4rnten",
    "wof:name":"Schneider Eugen",
    "wof:placetype":"venue"
},
  "geometry": {"coordinates":[14.3551645279,46.7656517029],"type":"Point"}
}