{
  "type": "Feature",
  "properties": {
    "addr:full":"Peilsteinerstr 21 Salzburg Salzburg 5020",
    "addr:housenumber":"21",
    "addr:postcode":"5020",
    "addr:street":"Peilsteinerstr;Salzburg",
    "iso:country":"AT",
    "sg:address":"Peilsteinerstr 21",
    "sg:city":"Salzburg",
    "sg:orig_category":"Baumeister",
    "sg:phone":"+43 662 4284420",
    "sg:postcode":"5020",
    "sg:province":"Salzburg",
    "wof:name":"Birgmann Roland Ing B\u00fcro f\u00fcr Planung - Bauleitung - BauKG",
    "wof:placetype":"venue"
},
  "geometry": {"coordinates":[13.023771286,47.8171577454],"type":"Point"}
}