{
  "type": "Feature",
  "properties": {
    "addr:full":"Hauptpl 23 Waidhofen an der Thaya Nieder\u00f6sterreich 3830",
    "addr:housenumber":"23",
    "addr:postcode":"3830",
    "addr:street":"Hauptpl",
    "iso:country":"AT",
    "sg:address":"Hauptpl 23",
    "sg:city":"Waidhofen an der Thaya",
    "sg:orig_category":"Fu\u00c3\u0178pflege U Fu\u00c3\u0178pflegesalons",
    "sg:phone":"+43 4328 4254801",
    "sg:postcode":"3830",
    "sg:province":"Nieder\u00f6sterreich",
    "wof:name":"Fu\u00dfpflegesalon - Massage Inge Rosenauer",
    "wof:placetype":"venue"
},
  "geometry": {"coordinates":[15.2864427567,48.8154830933],"type":"Point"}
}