{
  "type": "Feature",
  "properties": {
    "addr:full":"Hanselmayerg 14 Wien Wien 1130",
    "addr:housenumber":"14",
    "addr:postcode":"1130",
    "addr:street":"Hanselmayerg",
    "iso:country":"AT",
    "sg:address":"Hanselmayerg 14",
    "sg:city":"Wien",
    "sg:orig_category":"Fernseh- U Radiogesellschaften",
    "sg:phone":"+43 4318 7664010",
    "sg:postcode":"1130",
    "sg:province":"Wien",
    "wof:name":"ARD H\u00f6rfunkstudio f S\u00fcdosteuropa",
    "wof:placetype":"venue"
},
  "geometry": {"coordinates":[16.2947788239,48.1787948608],"type":"Point"}
}