{
  "type": "Feature",
  "properties": {
    "addr:full":"Dorf 38 Jerzens Tirol 6474",
    "addr:housenumber":"38",
    "addr:postcode":"6474",
    "addr:street":"Dorf;Tirol",
    "iso:country":"AT",
    "sg:address":"Dorf 38",
    "sg:city":"Jerzens",
    "sg:orig_category":"Non-Classified Establishments",
    "sg:phone":"+43 5414 87351",
    "sg:postcode":"6474",
    "sg:province":"Tirol",
    "wof:name":"Pfarramt",
    "wof:placetype":"venue"
},
  "geometry": {"coordinates":[10.7465543747,47.1491737366],"type":"Point"}
}