{
  "type": "Feature",
  "properties": {
    "addr:full":"Klenaug 7 Wien Wien 1220",
    "addr:housenumber":"7",
    "addr:postcode":"1220",
    "addr:street":"Klenaug",
    "iso:country":"AT",
    "sg:address":"Klenaug 7",
    "sg:city":"Wien",
    "sg:orig_category":"Alarmanlagen U Sicherheitssysteme",
    "sg:phone":"+43 1 3502070",
    "sg:postcode":"1220",
    "sg:province":"Wien",
    "wof:name":"Sitas HandelsgesmbH",
    "wof:placetype":"venue"
},
  "geometry": {"coordinates":[16.4824924469,48.2917327881],"type":"Point"}
}