{
  "type": "Feature",
  "properties": {
    "iso:country":"AT",
    "sg:address":"Mag.-Eduard Angerer-Weg 35",
    "sg:city":"St. Johann in Tirol",
    "sg:orig_category":"Pensionen / Privatzimmer",
    "sg:phone":"+43 4353 5262787",
    "sg:postcode":"6380",
    "sg:province":"Tirol",
    "wof:name":"Prem Hansj\u00f6rg",
    "wof:placetype":"venue"
},
  "geometry": {"coordinates":[12.438287735,47.5149917603],"type":"Point"}
}