{
  "type": "Feature",
  "properties": {
    "iso:country":"AT",
    "sg:address":"Neudorfer Str 106",
    "sg:city":"Guntramsdorf",
    "sg:orig_category":"Lebensmittel / Einzelhandel",
    "sg:phone":"+43 2236 893101",
    "sg:postcode":"2353",
    "sg:province":"Nieder\u00f6sterreich",
    "wof:name":"Zielpunkt Warenhandel GmbH & Co KG",
    "wof:placetype":"venue"
},
  "geometry": {"coordinates":[16.323846817,48.0581474304],"type":"Point"}
}