{
  "type": "Feature",
  "properties": {
    "iso:country":"AT",
    "sg:address":"Wasserfallweg 2",
    "sg:city":"Bad Kleinkirchheim",
    "sg:orig_category":"Pensionen / Privatzimmer",
    "sg:phone":"+43 4240 521",
    "sg:postcode":"9546",
    "sg:province":"K\u00e4rnten",
    "wof:name":"Grasser Erika",
    "wof:placetype":"venue"
},
  "geometry": {"coordinates":[13.774356842,46.8120155334],"type":"Point"}
}