{
  "type": "Feature",
  "properties": {
    "addr:full":"Hostauerstr 62-68 Ottensheim Ober\u00f6sterreich 4100",
    "addr:postcode":"4100",
    "addr:street":"Oberoesterreich",
    "iso:country":"AT",
    "sg:address":"Hostauerstr 62-68",
    "sg:city":"Ottensheim",
    "sg:orig_category":"Eisenwaren",
    "sg:phone":"+43 7234 822620",
    "sg:postcode":"4100",
    "sg:province":"Ober\u00f6sterreich",
    "wof:name":"Reisinger Wolfgang",
    "wof:placetype":"venue"
},
  "geometry": {"coordinates":[14.1681346893,48.3401412964],"type":"Point"}
}