{
  "type": "Feature",
  "properties": {
    "addr:full":"R\u00f6sselm\u00fchlg. 18 Graz Steiermark 8020",
    "addr:housenumber":"18",
    "addr:postcode":"8020",
    "addr:street":"Roesselmuehlg.",
    "iso:country":"AT",
    "sg:address":"R\u00f6sselm\u00fchlg. 18",
    "sg:city":"Graz",
    "sg:classifiers":[
        {
            "category":"Banks & Credit Unions",
            "subcategory":"Financial Services",
            "type":"Services"
        }
    ],
    "sg:phone":"+43 4331 6712207",
    "sg:postcode":"8020",
    "sg:province":"Steiermark",
    "sg:tags":[
        "banking",
        "finance",
        "insurance"
    ],
    "wof:name":"D.A.S. \u00d6STERR.ALLGEMEINE RECHTSSCHUTZ-VERSICHERUNGS-AG",
    "wof:placetype":"venue"
},
  "geometry": {"coordinates":[15.4111499786,47.0689201355],"type":"Point"}
}