{
  "type": "Feature",
  "properties": {
    "iso:country":"AT",
    "sg:address":"Maria-Theresien-Str. 51-53 ",
    "sg:city":"Innsbruck",
    "sg:classifiers":[
        {
            "category":"Banks & Credit Unions",
            "subcategory":"Financial Services",
            "type":"Services"
        }
    ],
    "sg:phone":"+43 4351 2599600",
    "sg:postcode":"6020",
    "sg:province":"Tirol",
    "sg:tags":[
        "banking",
        "finance",
        "insurance"
    ],
    "wof:name":"INTERUNFALL VERSICHERUNGS AG",
    "wof:placetype":"venue"
},
  "geometry": {"coordinates":[11.3949642181,47.2632904053],"type":"Point"}
}