{
  "type": "Feature",
  "properties": {
    "addr:full":"Rupertsbergerg 4 Linz Ober\u00f6sterreich 4030",
    "addr:housenumber":"4",
    "addr:postcode":"4030",
    "addr:street":"Rupertsbergerg",
    "iso:country":"AT",
    "sg:address":"Rupertsbergerg 4",
    "sg:city":"Linz",
    "sg:orig_category":"Cad/Cae/Cam/Cim-Systeme",
    "sg:phone":"+43 732 303244",
    "sg:postcode":"4030",
    "sg:province":"Ober\u00f6sterreich",
    "wof:name":"DACAD - Danninger G\u00fcnter Ing",
    "wof:placetype":"venue"
},
  "geometry": {"coordinates":[14.3295984268,48.2400665283],"type":"Point"}
}