{
  "type": "Feature",
  "properties": {
    "addr:full":"Ehrentletzbergerstr 2-4 Linz Ober\u00f6sterreich 4020",
    "addr:housenumber":"2-4",
    "addr:postcode":"4020",
    "addr:street":"Ehrentletzbergerstr",
    "iso:country":"AT",
    "sg:address":"Ehrentletzbergerstr 2-4",
    "sg:city":"Linz",
    "sg:orig_category":"Elektromotoren U -Maschinen",
    "sg:phone":"+43 732 7708820",
    "sg:postcode":"4020",
    "sg:province":"Ober\u00f6sterreich",
    "wof:name":"Riegler R GesmbH",
    "wof:placetype":"venue"
},
  "geometry": {"coordinates":[14.3281822205,48.3077201843],"type":"Point"}
}