{
  "type": "Feature",
  "properties": {
    "addr:full":"Dobrovastrasse 15 Villach K\u00e4rnten 9500",
    "addr:housenumber":"15",
    "addr:postcode":"9500",
    "addr:street":"Dobrovastrasse;Kaernten",
    "iso:country":"AT",
    "sg:address":"Dobrovastrasse 15",
    "sg:city":"Villach",
    "sg:orig_category":"Canalisation",
    "sg:phone":"+43 4242 33160",
    "sg:postcode":"9500",
    "sg:province":"K\u00e4rnten",
    "wof:name":"HB Hochkofler Betriebe GmbH & Co KG",
    "wof:placetype":"venue"
},
  "geometry": {"coordinates":[13.8802833557,46.5937347412],"type":"Point"}
}