{
  "type": "Feature",
  "properties": {
    "addr:full":"General-Feurstein-Str 3B Innsbruck Tirol 6020",
    "addr:housenumber":"3b",
    "addr:postcode":"6020",
    "addr:street":"General-Feurstein-Str;Tirol",
    "iso:country":"AT",
    "sg:address":"General-Feurstein-Str 3B",
    "sg:city":"Innsbruck",
    "sg:orig_category":"Architekten",
    "sg:phone":"+43 4351 2261951",
    "sg:postcode":"6020",
    "sg:province":"Tirol",
    "wof:name":"Architektenatelier Dipl Ing Georg Martin Wieland",
    "wof:placetype":"venue"
},
  "geometry": {"coordinates":[11.4345235825,47.2860107422],"type":"Point"}
}