{
  "type": "Feature",
  "properties": {
    "addr:full":"Franz-Josef-Str 41 Mistelbach Nieder\u00f6sterreich 2130",
    "addr:housenumber":"41",
    "addr:postcode":"2130",
    "addr:street":"Franz-Josef-Str;Niederoesterreich",
    "iso:country":"AT",
    "sg:address":"Franz-Josef-Str 41",
    "sg:city":"Mistelbach",
    "sg:orig_category":"Stahl / Gro\u00c3\u0178handel",
    "sg:phone":"+43 4366 42368263",
    "sg:postcode":"2130",
    "sg:province":"Nieder\u00f6sterreich",
    "wof:name":"Montan Rohrstahl Handels GesmbH",
    "wof:placetype":"venue"
},
  "geometry": {"coordinates":[16.5704421997,48.5702362061],"type":"Point"}
}