{
  "type": "Feature",
  "properties": {
    "addr:full":"Seespitz 8 Seeboden K\u00e4rnten 9871",
    "addr:housenumber":"8",
    "addr:postcode":"9871",
    "addr:street":"Seespitz;Kaernten",
    "iso:country":"AT",
    "sg:address":"Seespitz 8",
    "sg:city":"Seeboden",
    "sg:orig_category":"Appartements / Ferienwohnungen",
    "sg:phone":"+43 4347 6281285",
    "sg:postcode":"9871",
    "sg:province":"K\u00e4rnten",
    "wof:name":"Haus Fr\u00fchauf",
    "wof:placetype":"venue"
},
  "geometry": {"coordinates":[13.5131216049,46.8152809143],"type":"Point"}
}