{
  "type": "Feature",
  "properties": {
    "addr:full":"Nr 73 Feistritz an der Gail K\u00e4rnten 9613",
    "addr:postcode":"9613",
    "addr:street":"Nr;Feistritz",
    "iso:country":"AT",
    "sg:address":"Nr 73",
    "sg:city":"Feistritz an der Gail",
    "sg:orig_category":"Genossenschaften",
    "sg:phone":"+43 4256 25904",
    "sg:postcode":"9613",
    "sg:province":"K\u00e4rnten",
    "wof:name":"Zadruga Market Pliberk-Bleiberg regzzoj",
    "wof:placetype":"venue"
},
  "geometry": {"coordinates":[13.6317987442,46.5595397949],"type":"Point"}
}