{
  "type": "Feature",
  "properties": {
    "addr:full":"Goldschlagstr 113 Wien Wien 1150",
    "addr:housenumber":"113",
    "addr:postcode":"1150",
    "iso:country":"AT",
    "sg:address":"Goldschlagstr 113",
    "sg:city":"Wien",
    "sg:orig_category":"Volksschulen",
    "sg:phone":"+43 1 7868430111",
    "sg:postcode":"1150",
    "sg:province":"Wien",
    "wof:name":"Schulen d Stadt Wien",
    "wof:placetype":"venue"
},
  "geometry": {"coordinates":[16.3153839111,48.194694519],"type":"Point"}
}