{
  "type": "Feature",
  "properties": {
    "iso:country":"AT",
    "sg:address":"Obergallaberg 2",
    "sg:city":"Timelkam",
    "sg:orig_category":"Bestattungsunternehmen",
    "sg:phone":"+43 767292826",
    "sg:postcode":"4850",
    "sg:province":"Ober\u00f6sterreich",
    "wof:name":"Bestattung Eckl",
    "wof:placetype":"venue"
},
  "geometry": {"coordinates":[13.6127004623,48.00157547],"type":"Point"}
}