{
  "type": "Feature",
  "properties": {
    "addr:full":"Sportplatzg 2 Weiz Steiermark 8160",
    "addr:housenumber":"2",
    "addr:postcode":"8160",
    "addr:street":"Sportplatzg",
    "iso:country":"AT",
    "sg:address":"Sportplatzg 2",
    "sg:city":"Weiz",
    "sg:orig_category":"Finanz- U Wirtschaftsberatung",
    "sg:phone":"+43 4331 723173",
    "sg:postcode":"8160",
    "sg:province":"Steiermark",
    "wof:name":"H\u00f6rl Peter",
    "wof:placetype":"venue"
},
  "geometry": {"coordinates":[15.6441364288,47.2142295837],"type":"Point"}
}