{
  "type": "Feature",
  "properties": {
    "addr:full":"Hiesbergstr 7 Matzleinsdorf Nieder\u00f6sterreich 3393",
    "addr:housenumber":"7",
    "addr:postcode":"3393",
    "addr:street":"Hiesbergstr;Niederoesterreich",
    "iso:country":"AT",
    "sg:address":"Hiesbergstr 7",
    "sg:city":"Matzleinsdorf",
    "sg:orig_category":"Feuerwehren",
    "sg:phone":"+43 2752 53636",
    "sg:postcode":"3393",
    "sg:province":"Nieder\u00f6sterreich",
    "wof:name":"Freiwillige Feuerwehr Matzleinsdorf",
    "wof:placetype":"venue"
},
  "geometry": {"coordinates":[15.2776498795,48.2026596069],"type":"Point"}
}