{
  "type": "Feature",
  "properties": {
    "addr:full":"Kartause 3 Gaming Nieder\u00f6sterreich 3292",
    "addr:housenumber":"3",
    "addr:postcode":"3292",
    "addr:street":"Kartause",
    "iso:country":"AT",
    "sg:address":"Kartause 3",
    "sg:city":"Gaming",
    "sg:orig_category":"Institute",
    "sg:phone":"+43 7485 975700",
    "sg:postcode":"3292",
    "sg:province":"Nieder\u00f6sterreich",
    "wof:name":"Internationales Theologisches Institut",
    "wof:placetype":"venue"
},
  "geometry": {"coordinates":[15.0818386078,47.9231796265],"type":"Point"}
}