{
  "type": "Feature",
  "properties": {
    "iso:country":"AT",
    "sg:address":"Kanaltaler Str 17",
    "sg:city":"Villach",
    "sg:orig_category":"Blitzableiter U Blitzschutzanlagen",
    "sg:phone":"+43 4342 4223182",
    "sg:postcode":"9500",
    "sg:province":"K\u00e4rnten",
    "wof:name":"Felderer Adolf",
    "wof:placetype":"venue"
},
  "geometry": {"coordinates":[13.8541097641,46.6221466064],"type":"Point"}
}