{
  "type": "Feature",
  "properties": {
    "addr:full":"Jakominipl 1 Graz Steiermark 8010",
    "addr:housenumber":"1",
    "addr:postcode":"8010",
    "addr:street":"Jakominipl",
    "iso:country":"AT",
    "sg:address":"Jakominipl 1",
    "sg:city":"Graz",
    "sg:orig_category":"Psychotherapie",
    "sg:phone":"+43 699 10825289",
    "sg:postcode":"8010",
    "sg:province":"Steiermark",
    "wof:name":"Haas-Hasiba Susanne",
    "wof:placetype":"venue"
},
  "geometry": {"coordinates":[15.4422187805,47.067779541],"type":"Point"}
}