{
  "type": "Feature",
  "properties": {
    "addr:full":"Lorbeerg 39a Gutenstein Nieder\u00f6sterreich 2770",
    "addr:housenumber":"39a",
    "addr:postcode":"2770",
    "addr:street":"Lorbeerg",
    "iso:country":"AT",
    "sg:address":"Lorbeerg 39a",
    "sg:city":"Gutenstein",
    "sg:orig_category":"Autovermietung",
    "sg:phone":"+43 2634 7506",
    "sg:postcode":"2770",
    "sg:province":"Nieder\u00f6sterreich",
    "wof:name":"Rotheneder Sabine",
    "wof:placetype":"venue"
},
  "geometry": {"coordinates":[15.8909635544,47.8753013611],"type":"Point"}
}