{
  "type": "Feature",
  "properties": {
    "addr:full":"Freist\u00e4dter Str 307 Linz Ober\u00f6sterreich 4040",
    "addr:housenumber":"307",
    "addr:postcode":"4040",
    "addr:street":"Str",
    "iso:country":"AT",
    "sg:address":"Freist\u00e4dter Str 307",
    "sg:city":"Linz",
    "sg:orig_category":"Bauleitung U -Betreuung",
    "sg:phone":"+43 732 6617530",
    "sg:postcode":"4040",
    "sg:province":"Ober\u00f6sterreich",
    "wof:name":"BWG O\u00d6 Bauwirtschafts-F\u00f6rderungsgesmbH",
    "wof:placetype":"venue"
},
  "geometry": {"coordinates":[14.3170166016,48.3298912048],"type":"Point"}
}