{
  "type": "Feature",
  "properties": {
    "addr:full":"Wiener Str 200 Spillern Nieder\u00f6sterreich 2104",
    "addr:housenumber":"200",
    "addr:postcode":"2104",
    "iso:country":"AT",
    "sg:address":"Wiener Str 200",
    "sg:city":"Spillern",
    "sg:orig_category":"Reinigungsbedarf U Reinigungsmittel",
    "sg:phone":"+43 4322 66803710",
    "sg:postcode":"2104",
    "sg:province":"Nieder\u00f6sterreich",
    "wof:name":"S\u00f6KE HandelsgmbH",
    "wof:placetype":"venue"
},
  "geometry": {"coordinates":[16.2789878845,48.3750724792],"type":"Point"}
}