{
  "type": "Feature",
  "properties": {
    "addr:full":"Conrad-von-H\u00f6tzendorf-Str 37a Graz Steiermark 8010",
    "addr:housenumber":"37a",
    "addr:postcode":"8010",
    "addr:street":"Conrad-Von-Hoetzendorf-Str",
    "iso:country":"AT",
    "sg:address":"Conrad-von-H\u00f6tzendorf-Str 37a",
    "sg:city":"Graz",
    "sg:orig_category":"Immobilienmakler",
    "sg:phone":"+43 4331 6815915",
    "sg:postcode":"8010",
    "sg:province":"Steiermark",
    "sg:website":"remax-graz-sued.at",
    "wof:name":"RE/MAX Graz-S\u00fcd Immobilien Mag Hofst\u00e4tter & Kletzenbauer OEG",
    "wof:placetype":"venue"
},
  "geometry": {"coordinates":[15.4450283051,47.0601844788],"type":"Point"}
}