{
  "type": "Feature",
  "properties": {
    "iso:country":"AT",
    "sg:address":"Hauptstr 571",
    "sg:city":"Altenmarkt im Pongau",
    "sg:orig_category":"Lebensmittel / Einzelhandel",
    "sg:phone":"+43 4364 526559",
    "sg:postcode":"5541",
    "sg:province":"Salzburg",
    "wof:name":"ADEG Aktiv Markt",
    "wof:placetype":"venue"
},
  "geometry": {"coordinates":[13.4270744324,47.3801040649],"type":"Point"}
}