{
  "type": "Feature",
  "properties": {
    "iso:country":"AT",
    "sg:address":"Alter Markt 6",
    "sg:city":"Salzburg",
    "sg:orig_category":"Apotheken",
    "sg:phone":"+43 662 8436230",
    "sg:postcode":"5020",
    "sg:province":"Salzburg",
    "wof:name":"Alte f e Hofapotheke Mag pharm Lorenz Biskup KG",
    "wof:placetype":"venue"
},
  "geometry": {"coordinates":[13.0452356339,47.7993354797],"type":"Point"}
}