{
  "type": "Feature",
  "properties": {
    "iso:country":"AT",
    "sg:address":"Ressavarstrasse 46",
    "sg:city":"Hartberg",
    "sg:classifiers":[
        {
            "category":"Home & Garden",
            "subcategory":"Building Materials",
            "type":"Retail Goods"
        }
    ],
    "sg:phone":"+43 3332 64890",
    "sg:postcode":"8230",
    "sg:province":"Steiermark",
    "sg:tags":[
        "aluminium",
        "window"
    ],
    "sg:website":"wolffenster.at",
    "wof:name":"Andreas Wolf",
    "wof:placetype":"venue"
},
  "geometry": {"coordinates":[15.9736814499,47.2816696167],"type":"Point"}
}