{
  "type": "Feature",
  "properties": {
    "addr:full":"Neubaug 39 Deutschkreutz Burgenland 7301",
    "addr:housenumber":"39",
    "addr:postcode":"7301",
    "addr:street":"Neubaug",
    "iso:country":"AT",
    "sg:address":"Neubaug 39",
    "sg:city":"Deutschkreutz",
    "sg:orig_category":"Weine / Einzelhandel",
    "sg:phone":"+43 4326 1380421",
    "sg:postcode":"7301",
    "sg:province":"Burgenland",
    "wof:name":"Reumann Josef u Maria",
    "wof:placetype":"venue"
},
  "geometry": {"coordinates":[16.6256313324,47.5992851257],"type":"Point"}
}