{
  "type": "Feature",
  "properties": {
    "iso:country":"AT",
    "sg:address":"Dorf 8",
    "sg:city":"Egg",
    "sg:classifiers":[
        {
            "category":"Internet Cafe",
            "subcategory":"None",
            "type":"Food & Drink"
        }
    ],
    "sg:phone":"+43 664 1722900",
    "sg:postcode":"6863",
    "sg:province":"Vorarlberg",
    "wof:name":"sigar Internet Systeme",
    "wof:placetype":"venue"
},
  "geometry": {"coordinates":[9.897102356,47.4310417175],"type":"Point"}
}