{
  "type": "Feature",
  "properties": {
    "addr:full":"Sperrg 3 Wien Wien 1150",
    "addr:housenumber":"3",
    "addr:postcode":"1150",
    "addr:street":"Sperrg",
    "iso:country":"AT",
    "sg:address":"Sperrg 3",
    "sg:city":"Wien",
    "sg:orig_category":"\u00c3\u201erzte / F Allgemeinmedizin",
    "sg:phone":"+43 1 8923570",
    "sg:postcode":"1150",
    "sg:province":"Wien",
    "wof:name":"Korschil Rudolf MedR Dr",
    "wof:placetype":"venue"
},
  "geometry": {"coordinates":[16.3324546814,48.1931724548],"type":"Point"}
}