{
  "type": "Feature",
  "properties": {
    "addr:full":"Siedlung 26a Obdach Steiermark 8742",
    "addr:housenumber":"26a",
    "addr:postcode":"8742",
    "addr:street":"Siedlung",
    "iso:country":"AT",
    "sg:address":"Siedlung 26a",
    "sg:city":"Obdach",
    "sg:orig_category":"Baumeister",
    "sg:phone":"+43 3578 4060",
    "sg:postcode":"8742",
    "sg:province":"Steiermark",
    "wof:name":"Reiter Johann Bmstr Ing",
    "wof:placetype":"venue"
},
  "geometry": {"coordinates":[14.6945495605,47.0659294128],"type":"Point"}
}