{
  "type": "Feature",
  "properties": {
    "addr:full":"Dornschneiderg 29 Graz Steiermark 8020",
    "addr:housenumber":"29",
    "addr:postcode":"8020",
    "addr:street":"Dornschneiderg",
    "iso:country":"AT",
    "sg:address":"Dornschneiderg 29",
    "sg:city":"Graz",
    "sg:orig_category":"Baumaschinenverleih",
    "sg:phone":"+43 316 262000",
    "sg:postcode":"8020",
    "sg:province":"Steiermark",
    "wof:name":"Theisen Mietpark Baumaschinen GmbH & Co KG",
    "wof:placetype":"venue"
},
  "geometry": {"coordinates":[15.4334468842,47.0491294861],"type":"Point"}
}