{
  "type": "Feature",
  "properties": {
    "iso:country":"AT",
    "sg:address":"Dr.-Richard-Hartmann-Str 5",
    "sg:city":"Gr\u00f6dig",
    "sg:orig_category":"Hauskrankenpflege / Heimhilfe",
    "sg:phone":"+43 4362 4674939",
    "sg:postcode":"5082",
    "sg:province":"Salzburg",
    "wof:name":"Aktiv Hauskrankenpflege u Seniorenbetreuung",
    "wof:placetype":"venue"
},
  "geometry": {"coordinates":[-76.2684555054,37.4373283386],"type":"Point"}
}