{
  "type": "Feature",
  "properties": {
    "addr:full":"Marktstr 25 Altm\u00fcnster Ober\u00f6sterreich 4813",
    "addr:housenumber":"25",
    "addr:postcode":"4813",
    "addr:street":"Marktstr;Oberoesterreich",
    "iso:country":"AT",
    "sg:address":"Marktstr 25",
    "sg:city":"Altm\u00fcnster",
    "sg:orig_category":"Musikunterricht",
    "sg:phone":"+43 761288770",
    "sg:postcode":"4813",
    "sg:province":"Ober\u00f6sterreich",
    "wof:name":"Landesmusikschule",
    "wof:placetype":"venue"
},
  "geometry": {"coordinates":[13.7628335953,47.9005966187],"type":"Point"}
}