{
  "type": "Feature",
  "properties": {
    "addr:full":"Haitzendorf 7 Neustift Ober\u00f6sterreich 4143",
    "addr:housenumber":"7",
    "addr:postcode":"4143",
    "addr:street":"Haitzendorf",
    "iso:country":"AT",
    "sg:address":"Haitzendorf 7",
    "sg:city":"Neustift",
    "sg:orig_category":"Appartements / Ferienwohnungen",
    "sg:phone":"+43 7284 8330",
    "sg:postcode":"4143",
    "sg:province":"Ober\u00f6sterreich",
    "wof:name":"Ferienhof Leitenm\u00fchle",
    "wof:placetype":"venue"
},
  "geometry": {"coordinates":[13.7417211533,48.5244598389],"type":"Point"}
}