{
  "type": "Feature",
  "properties": {
    "iso:country":"AT",
    "sg:address":"Markt 17",
    "sg:city":"Wagrain",
    "sg:orig_category":"Fleischhauereien",
    "sg:phone":"+43 6413 8568",
    "sg:postcode":"5602",
    "sg:province":"Salzburg",
    "wof:name":"Obauer Johann",
    "wof:placetype":"venue"
},
  "geometry": {"coordinates":[13.2967300415,47.3329200745],"type":"Point"}
}