{
  "type": "Feature",
  "properties": {
    "addr:full":"Steinwiesen 4 Schlins Vorarlberg 6824",
    "addr:housenumber":"4",
    "addr:postcode":"6824",
    "addr:street":"Steinwiesen",
    "iso:country":"AT",
    "sg:address":"Steinwiesen 4",
    "sg:city":"Schlins",
    "sg:classifiers":[
        {
            "category":"Banks & Credit Unions",
            "subcategory":"Investment Brokerage",
            "type":"Services"
        }
    ],
    "sg:phone":"+43 5524 84300",
    "sg:postcode":"6824",
    "sg:province":"Vorarlberg",
    "sg:tags":[
        "machine",
        "ticket",
        "automatic",
        "machines",
        "parking"
    ],
    "sg:website":"bilexa-ag.com",
    "wof:name":"Bilexa AG Vertriebs und Vermietungsges.m.b.H.",
    "wof:placetype":"venue"
},
  "geometry": {"coordinates":[9.6967878342,47.2030639648],"type":"Point"}
}