{
  "type": "Feature",
  "properties": {
    "addr:full":"Unterleithen 3 Wels Ober\u00f6sterreich 4600",
    "addr:housenumber":"3",
    "addr:postcode":"4600",
    "addr:street":"Unterleithen;Oberoesterreich",
    "iso:country":"AT",
    "sg:address":"Unterleithen 3",
    "sg:city":"Wels",
    "sg:orig_category":"Damenmoden",
    "sg:phone":"+43 4372 4277412",
    "sg:postcode":"4600",
    "sg:province":"Ober\u00f6sterreich",
    "wof:name":"Trachtenhof Wels - Augustina Zittmayr-Hacker",
    "wof:placetype":"venue"
},
  "geometry": {"coordinates":[14.0340948105,48.1909675598],"type":"Point"}
}