{
  "type": "Feature",
  "properties": {
    "addr:full":"Pyrkerstr 48 Bad Hofgastein Salzburg 5630",
    "addr:housenumber":"48",
    "addr:postcode":"5630",
    "addr:street":"Pyrkerstr;Salzburg",
    "iso:country":"AT",
    "sg:address":"Pyrkerstr 48",
    "sg:city":"Bad Hofgastein",
    "sg:orig_category":"Appartements / Ferienwohnungen",
    "sg:phone":"+43 6432 6621",
    "sg:postcode":"5630",
    "sg:province":"Salzburg",
    "wof:name":"Appartementhaus Christine",
    "wof:placetype":"venue"
},
  "geometry": {"coordinates":[13.1104850769,47.1654815674],"type":"Point"}
}