{
  "type": "Feature",
  "properties": {
    "addr:full":"Hauptstr 16 Pyhra Nieder\u00f6sterreich 3143",
    "addr:housenumber":"16",
    "addr:postcode":"3143",
    "addr:street":"Hauptstr",
    "iso:country":"AT",
    "sg:address":"Hauptstr 16",
    "sg:city":"Pyhra",
    "sg:orig_category":"Tabaktrafiken",
    "sg:phone":"+43 4327 452201",
    "sg:postcode":"3143",
    "sg:province":"Nieder\u00f6sterreich",
    "wof:name":"Schober Stephan",
    "wof:placetype":"venue"
},
  "geometry": {"coordinates":[15.6861581802,48.1581611633],"type":"Point"}
}