{
  "type": "Feature",
  "properties": {
    "addr:full":"Oberhof-Schattseite 1 Metnitz K\u00e4rnten 9363",
    "addr:housenumber":"1",
    "addr:postcode":"9363",
    "addr:street":"Oberhof-Schattseite;Kaernten",
    "iso:country":"AT",
    "sg:address":"Oberhof-Schattseite 1",
    "sg:city":"Metnitz",
    "sg:classifiers":[
        {
            "category":"Autos & Motor Vehicles",
            "subcategory":"Motorcycle Sales",
            "type":"Retail Goods"
        }
    ],
    "sg:phone":"+43 4267 8423",
    "sg:postcode":"9363",
    "sg:province":"K\u00e4rnten",
    "sg:tags":[
        "battery",
        "car"
    ],
    "wof:name":"Markus Wolfger",
    "wof:placetype":"venue"
},
  "geometry": {"coordinates":[14.140004158,46.956829071],"type":"Point"}
}