{
  "type": "Feature",
  "properties": {
    "iso:country":"AT",
    "sg:address":"Kurhauspl. 298",
    "sg:city":"Bad Aussee",
    "sg:classifiers":[
        {
            "category":"Banks & Credit Unions",
            "subcategory":"Bank",
            "type":"Services"
        }
    ],
    "sg:phone":"+43 4336 22525510",
    "sg:postcode":"8990",
    "sg:province":"Steiermark",
    "sg:tags":[
        "banking",
        "institution"
    ],
    "wof:name":"VOLKSBANK STEIRISCHES SALZKAMMERGUT REG. GEN.MBH",
    "wof:placetype":"venue"
},
  "geometry": {"coordinates":[13.783372879,47.6095199585],"type":"Point"}
}