{
  "type": "Feature",
  "properties": {
    "iso:country":"AT",
    "sg:address":"Oberdorf 711",
    "sg:city":"Wenns",
    "sg:classifiers":[
        {
            "category":"Travel",
            "subcategory":"Hotels & Motels",
            "type":"Entertainment"
        }
    ],
    "sg:phone":"+43 5414 861110",
    "sg:postcode":"6473",
    "sg:province":"Tirol",
    "wof:name":"Hotel-Garni Jagdhof",
    "wof:placetype":"venue"
},
  "geometry": {"coordinates":[10.7310228348,47.1683654785],"type":"Point"}
}