{
  "type": "Feature",
  "properties": {
    "addr:full":"Graben 27 Wien Wien 1010",
    "addr:housenumber":"27",
    "addr:postcode":"1010",
    "addr:street":"Graben",
    "iso:country":"AT",
    "sg:address":"Graben 27",
    "sg:city":"Wien",
    "sg:orig_category":"Immobilienmakler",
    "sg:phone":"+43 1 53370750",
    "sg:postcode":"1010",
    "sg:province":"Wien",
    "wof:name":"Riemer Brigitte",
    "wof:placetype":"venue"
},
  "geometry": {"coordinates":[16.3696422577,48.2088356018],"type":"Point"}
}