{
  "type": "Feature",
  "properties": {
    "addr:full":"Nr 66 Gro\u00dfkirchheim K\u00e4rnten 9843",
    "addr:postcode":"9843",
    "addr:street":"Nr;Kaernten",
    "iso:country":"AT",
    "sg:address":"Nr 66",
    "sg:city":"Gro\u00dfkirchheim",
    "sg:orig_category":"Elektromotoren U -Maschinen",
    "sg:phone":"+43 4825 6127",
    "sg:postcode":"9843",
    "sg:province":"K\u00e4rnten",
    "wof:name":"Warmuth Josef",
    "wof:placetype":"venue"
},
  "geometry": {"coordinates":[12.8957948685,46.9726448059],"type":"Point"}
}