{
  "type": "Feature",
  "properties": {
    "addr:full":"Hauptpl. 5  Enns Ober\u00f6sterreich 4470",
    "addr:housenumber":"5",
    "addr:postcode":"4470",
    "addr:street":"Hauptpl.",
    "iso:country":"AT",
    "sg:address":"Hauptpl. 5 ",
    "sg:city":"Enns",
    "sg:classifiers":[
        {
            "category":"Banks & Credit Unions",
            "subcategory":"Bank",
            "type":"Services"
        }
    ],
    "sg:phone":"+43 4372 2384941",
    "sg:postcode":"4470",
    "sg:province":"Ober\u00f6sterreich",
    "sg:tags":[
        "banking",
        "institution"
    ],
    "wof:name":"RAIFFEISENBANK ENNS REG. GEN. MBH",
    "wof:placetype":"venue"
},
  "geometry": {"coordinates":[14.4791278839,48.2143211365],"type":"Point"}
}