{
  "type": "Feature",
  "properties": {
    "iso:country":"AT",
    "sg:address":"Grazer Str 2",
    "sg:city":"Judendorf-Stra\u00dfengel",
    "sg:orig_category":"Tabaktrafiken",
    "sg:phone":"+43 3124 56046",
    "sg:postcode":"8111",
    "sg:province":"Steiermark",
    "wof:name":"Pucher Flora",
    "wof:placetype":"venue"
},
  "geometry": {"coordinates":[15.336558342,47.1122398376],"type":"Point"}
}