{
  "type": "Feature",
  "properties": {
    "addr:full":"Sparkasseg 36 Hollabrunn Nieder\u00f6sterreich 2020",
    "addr:housenumber":"36",
    "addr:postcode":"2020",
    "addr:street":"Sparkasseg",
    "iso:country":"AT",
    "sg:address":"Sparkasseg 36",
    "sg:city":"Hollabrunn",
    "sg:orig_category":"Psychologen",
    "sg:phone":"+43 2952 20313",
    "sg:postcode":"2020",
    "sg:province":"Nieder\u00f6sterreich",
    "wof:name":"Widl Hermine Mag",
    "wof:placetype":"venue"
},
  "geometry": {"coordinates":[16.0800113678,48.565776825],"type":"Point"}
}