{
  "type": "Feature",
  "properties": {
    "addr:full":"Ungarnstr 2 Fehring Steiermark 8350",
    "addr:housenumber":"2",
    "addr:postcode":"8350",
    "addr:street":"Ungarnstr",
    "iso:country":"AT",
    "sg:address":"Ungarnstr 2",
    "sg:city":"Fehring",
    "sg:orig_category":"Friseure U Frisiersalons",
    "sg:phone":"+43 4331 552496",
    "sg:postcode":"8350",
    "sg:province":"Steiermark",
    "wof:name":"Schnedl Regina",
    "wof:placetype":"venue"
},
  "geometry": {"coordinates":[16.0116348267,46.9360427856],"type":"Point"}
}