{
  "type": "Feature",
  "properties": {
    "addr:full":"Marktpl 8-9 Uttendorf Ober\u00f6sterreich 5261",
    "addr:housenumber":"8-9",
    "addr:postcode":"5261",
    "addr:street":"Marktpl",
    "iso:country":"AT",
    "sg:address":"Marktpl 8-9",
    "sg:city":"Uttendorf",
    "sg:orig_category":"Farben U Lacke / Erzeugung U Gro\u00c3\u0178handel",
    "sg:phone":"+43 7724 24050",
    "sg:postcode":"5261",
    "sg:province":"Ober\u00f6sterreich",
    "wof:name":"Okalin Karl Obermayer Farbenerzeugungs GmbH",
    "wof:placetype":"venue"
},
  "geometry": {"coordinates":[13.117980957,48.1551856995],"type":"Point"}
}