{
  "type": "Feature",
  "properties": {
    "addr:full":"Friedhofg 3 Murau Steiermark 8850",
    "addr:housenumber":"3",
    "addr:postcode":"8850",
    "addr:street":"Friedhofg",
    "iso:country":"AT",
    "sg:address":"Friedhofg 3",
    "sg:city":"Murau",
    "sg:orig_category":"Volksschulen",
    "sg:phone":"+43 3532 2487",
    "sg:postcode":"8850",
    "sg:province":"Steiermark",
    "wof:name":"Volksschule",
    "wof:placetype":"venue"
},
  "geometry": {"coordinates":[14.1749811172,47.1135177612],"type":"Point"}
}