{
  "type": "Feature",
  "properties": {
    "addr:full":"Pfarrberg 23 Reichenthal Ober\u00f6sterreich 4193",
    "addr:housenumber":"23",
    "addr:postcode":"4193",
    "addr:street":"Pfarrberg",
    "iso:country":"AT",
    "sg:address":"Pfarrberg 23",
    "sg:city":"Reichenthal",
    "sg:orig_category":"Baumeister",
    "sg:phone":"+43 7214 4787",
    "sg:postcode":"4193",
    "sg:province":"Ober\u00f6sterreich",
    "wof:name":"Reisinger Wilhelm Bmstr",
    "wof:placetype":"venue"
},
  "geometry": {"coordinates":[14.3837747574,48.5458183289],"type":"Point"}
}