{
  "type": "Feature",
  "properties": {
    "addr:full":"Technikerstr 5 Graz Steiermark 8010",
    "addr:housenumber":"5",
    "addr:postcode":"8010",
    "addr:street":"Technikerstr",
    "iso:country":"AT",
    "sg:address":"Technikerstr 5",
    "sg:city":"Graz",
    "sg:orig_category":"Ingenieurkonsulenten / Zivilingenieure",
    "sg:phone":"+43 316 832062",
    "sg:postcode":"8010",
    "sg:province":"Steiermark",
    "wof:name":"Kautsch Peter Univ Doz DDr",
    "wof:placetype":"venue"
},
  "geometry": {"coordinates":[15.4508991241,47.0685310364],"type":"Point"}
}