{
  "type": "Feature",
  "properties": {
    "addr:full":"Sachsenpl 3 Wien Wien 1200",
    "addr:housenumber":"3",
    "addr:postcode":"1200",
    "addr:street":"Sachsenpl",
    "iso:country":"AT",
    "sg:address":"Sachsenpl 3",
    "sg:city":"Wien",
    "sg:orig_category":"Innenausbau",
    "sg:phone":"+43 4313 307691",
    "sg:postcode":"1200",
    "sg:province":"Wien",
    "wof:name":".. DIV Innenausbau ..Vujicic & S\u00f6hne GesmbH",
    "wof:placetype":"venue"
},
  "geometry": {"coordinates":[16.3759498596,48.2317047119],"type":"Point"}
}