{
  "type": "Feature",
  "properties": {
    "addr:full":"Innrain 1 Innsbruck Tirol 6020",
    "addr:housenumber":"1",
    "addr:postcode":"6020",
    "addr:street":"Innrain;Tirol",
    "iso:country":"AT",
    "sg:address":"Innrain 1",
    "sg:city":"Innsbruck",
    "sg:orig_category":"Friseure U Frisiersalons",
    "sg:phone":"+43 4351 2570474",
    "sg:postcode":"6020",
    "sg:province":"Tirol",
    "wof:name":"Hair Cut Team Inh Sowa Renate",
    "wof:placetype":"venue"
},
  "geometry": {"coordinates":[11.3915567398,47.2680282593],"type":"Point"}
}