{
  "type": "Feature",
  "properties": {
    "addr:full":"Kardinalpl 6 Klagenfurt K\u00e4rnten 9020",
    "addr:housenumber":"6",
    "addr:postcode":"9020",
    "addr:street":"Kardinalpl;Kaernten",
    "iso:country":"AT",
    "sg:address":"Kardinalpl 6",
    "sg:city":"Klagenfurt",
    "sg:orig_category":"Feinkost",
    "sg:phone":"+43 463 54072",
    "sg:postcode":"9020",
    "sg:province":"K\u00e4rnten",
    "wof:name":"Reinprecht Werner",
    "wof:placetype":"venue"
},
  "geometry": {"coordinates":[14.3117637634,46.6238021851],"type":"Point"}
}