{
  "type": "Feature",
  "properties": {
    "addr:full":"null Wellnes/Dorf/Seiwald Going am Wilden Kaiser Tirol 6353",
    "addr:postcode":"6353",
    "addr:street":"Wilden Kaiser",
    "iso:country":"AT",
    "sg:address":"null Wellnes/Dorf/Seiwald",
    "sg:city":"Going am Wilden Kaiser",
    "sg:orig_category":"Massagen",
    "sg:phone":"+43 4366 41705230",
    "sg:postcode":"6353",
    "sg:province":"Tirol",
    "wof:name":"H\u00e4ntschel Bernadette",
    "wof:placetype":"venue"
},
  "geometry": {"coordinates":[12.3282499313,47.5145301819],"type":"Point"}
}