{
  "type": "Feature",
  "properties": {
    "addr:full":"Achenweg 10d Saalfelden am Steinernen Meer Salzburg 5760",
    "addr:housenumber":"10d",
    "addr:postcode":"5760",
    "addr:street":"Achenweg",
    "iso:country":"AT",
    "sg:address":"Achenweg 10d",
    "sg:city":"Saalfelden am Steinernen Meer",
    "sg:orig_category":"Maler, Anstreicher U Lackierer",
    "sg:phone":"+43 6582 741290",
    "sg:postcode":"5760",
    "sg:province":"Salzburg",
    "wof:name":"Eder Franz",
    "wof:placetype":"venue"
},
  "geometry": {"coordinates":[12.8503112793,47.4222717285],"type":"Point"}
}