{
  "type": "Feature",
  "properties": {
    "addr:full":"Dreihackeng 4/6 Wien Wien 1090",
    "addr:housenumber":"4 / 6",
    "addr:postcode":"1090",
    "addr:street":"Dreihackeng",
    "iso:country":"AT",
    "sg:address":"Dreihackeng 4/6",
    "sg:city":"Wien",
    "sg:orig_category":"Steinmetzbetriebe",
    "sg:phone":"+43 1 3190522",
    "sg:postcode":"1090",
    "sg:province":"Wien",
    "wof:name":"Dr\u00e4xler Thomas Steinmetzmeister",
    "wof:placetype":"venue"
},
  "geometry": {"coordinates":[16.3546409607,48.226184845],"type":"Point"}
}