{
  "type": "Feature",
  "properties": {
    "addr:full":"Clusiusg 6 Wien Wien 1090",
    "addr:housenumber":"6",
    "addr:postcode":"1090",
    "addr:street":"Clusiusg",
    "iso:country":"AT",
    "sg:address":"Clusiusg 6",
    "sg:city":"Wien",
    "sg:orig_category":"Elektroinstallationsunternehmen",
    "sg:phone":"+43 1 3170339",
    "sg:postcode":"1090",
    "sg:province":"Wien",
    "wof:name":"Bl\u00fcmel Rudolf Ing GmbH & Co KG",
    "wof:placetype":"venue"
},
  "geometry": {"coordinates":[16.3642063141,48.2253952026],"type":"Point"}
}