{
  "type": "Feature",
  "properties": {
    "addr:full":"Franz-Kollmannstr. 2 Amstetten Nieder\u00f6sterreich 3300",
    "addr:housenumber":"2",
    "addr:postcode":"3300",
    "addr:street":"Franz-Kollmannstr.;Niederoesterreich",
    "iso:country":"AT",
    "sg:address":"Franz-Kollmannstr. 2",
    "sg:city":"Amstetten",
    "sg:classifiers":[
        {
            "category":"Building & Trades",
            "subcategory":"Construction",
            "type":"Services"
        }
    ],
    "sg:phone":"+43 4374 7261879",
    "sg:postcode":"3300",
    "sg:province":"Nieder\u00f6sterreich",
    "sg:tags":[
        "work",
        "public"
    ],
    "wof:name":"ALPINE -MAYREDER BAU GMBH",
    "wof:placetype":"venue"
},
  "geometry": {"coordinates":[14.9081945419,48.117351532],"type":"Point"}
}