{
  "type": "Feature",
  "properties": {
    "addr:full":"Minoritenpl 2 Tulln an der Donau Nieder\u00f6sterreich 3430",
    "addr:housenumber":"2",
    "addr:postcode":"3430",
    "addr:street":"Minoritenpl",
    "iso:country":"AT",
    "sg:address":"Minoritenpl 2",
    "sg:city":"Tulln an der Donau",
    "sg:orig_category":"Tourismusinformation U -Organisationen",
    "sg:phone":"+43 4322 72675660",
    "sg:postcode":"3430",
    "sg:province":"Nieder\u00f6sterreich",
    "wof:name":"Donau Nieder\u00f6sterreich Tourismus GmbH - Regionalb\u00fcro Tullner Donauraum",
    "wof:placetype":"venue"
},
  "geometry": {"coordinates":[16.0500335693,48.3322067261],"type":"Point"}
}