{
  "type": "Feature",
  "properties": {
    "addr:full":"Drosselg 10 Lieboch Steiermark 8501",
    "addr:housenumber":"10",
    "addr:postcode":"8501",
    "addr:street":"Drosselg",
    "iso:country":"AT",
    "sg:address":"Drosselg 10",
    "sg:city":"Lieboch",
    "sg:orig_category":"Forschungsinstitute",
    "sg:phone":"+43 4331 3661043",
    "sg:postcode":"8501",
    "sg:province":"Steiermark",
    "wof:name":"Ludwig Boltzmann Forschungstelle f Biosensorik u Bioenerget Umweltforschung",
    "wof:placetype":"venue"
},
  "geometry": {"coordinates":[15.3189821243,46.9830741882],"type":"Point"}
}