{
  "type": "Feature",
  "properties": {
    "iso:country":"AT",
    "sg:address":"Leharstr 11",
    "sg:city":"Wels",
    "sg:orig_category":"Elektroinstallationsunternehmen",
    "sg:phone":"+43 7242 68135",
    "sg:postcode":"4600",
    "sg:province":"Ober\u00f6sterreich",
    "wof:name":"Innerhuber Andreas",
    "wof:placetype":"venue"
},
  "geometry": {"coordinates":[14.0063791275,48.173740387],"type":"Point"}
}