{
  "type": "Feature",
  "properties": {
    "addr:full":"Leharstr 11 Wels Ober\u00f6sterreich 4600",
    "addr:housenumber":"11",
    "addr:postcode":"4600",
    "addr:street":"Leharstr;Oberoesterreich",
    "iso:country":"AT",
    "sg:address":"Leharstr 11",
    "sg:city":"Wels",
    "sg:orig_category":"Elektroinstallationsunternehmen",
    "sg:phone":"+43 7242 68135",
    "sg:postcode":"4600",
    "sg:province":"Ober\u00f6sterreich",
    "wof:name":"Innerhuber Andreas",
    "wof:placetype":"venue"
},
  "geometry": {"coordinates":[14.0063791275,48.173740387],"type":"Point"}
}