{
  "type": "Feature",
  "properties": {
    "addr:full":"Johann Schorsch-G 3 Wien Wien 1140",
    "addr:housenumber":"3",
    "addr:postcode":"1140",
    "iso:country":"AT",
    "sg:address":"Johann Schorsch-G 3",
    "sg:city":"Wien",
    "sg:orig_category":"Lebensmittel / Erzeugung U Gro\u00c3\u0178handel",
    "sg:phone":"+43 1 9794806",
    "sg:postcode":"1140",
    "sg:province":"Wien",
    "wof:name":"Backaldrin \u00d6sterreich GmbH",
    "wof:placetype":"venue"
},
  "geometry": {"coordinates":[16.21925354,48.20677948],"type":"Point"}
}