{
  "type": "Feature",
  "properties": {
    "addr:full":"Seeberg 21 Sonntag Vorarlberg 6731",
    "addr:housenumber":"21",
    "addr:postcode":"6731",
    "addr:street":"Seeberg",
    "iso:country":"AT",
    "sg:address":"Seeberg 21",
    "sg:city":"Sonntag",
    "sg:orig_category":"Fahrzeugbau",
    "sg:phone":"+43 5554 5156",
    "sg:postcode":"6731",
    "sg:province":"Vorarlberg",
    "wof:name":"Burtscher Gebhard Fahrzeugtechnik & Service",
    "wof:placetype":"venue"
},
  "geometry": {"coordinates":[9.9197187424,47.2440948486],"type":"Point"}
}