{
  "type": "Feature",
  "properties": {
    "addr:full":"Nr 149 Ottnang am Hausruck Ober\u00f6sterreich 4901",
    "addr:postcode":"4901",
    "addr:street":"Nr 149",
    "iso:country":"AT",
    "sg:address":"Nr 149",
    "sg:city":"Ottnang am Hausruck",
    "sg:orig_category":"Volksschulen",
    "sg:phone":"+43 4376 767541",
    "sg:postcode":"4901",
    "sg:province":"Ober\u00f6sterreich",
    "wof:name":"Volksschule",
    "wof:placetype":"venue"
},
  "geometry": {"coordinates":[13.6660804749,48.0968818665],"type":"Point"}
}