{
  "type": "Feature",
  "properties": {
    "addr:full":"Birkenstr 7 Hallwang Salzburg 5300",
    "addr:housenumber":"7",
    "addr:postcode":"5300",
    "addr:street":"Birkenstr;Salzburg",
    "iso:country":"AT",
    "sg:address":"Birkenstr 7",
    "sg:city":"Hallwang",
    "sg:orig_category":"Bauleitung U -Betreuung",
    "sg:phone":"+43 4366 26617000",
    "sg:postcode":"5300",
    "sg:province":"Salzburg",
    "wof:name":"Bautec Schwarzl GmbH",
    "wof:placetype":"venue"
},
  "geometry": {"coordinates":[13.0838794708,47.8332176208],"type":"Point"}
}