{
  "type": "Feature",
  "properties": {
    "addr:full":"Unterberg 1 Gro\u00dfarl Salzburg 5611",
    "addr:housenumber":"1",
    "addr:postcode":"5611",
    "addr:street":"Unterberg;Salzburg",
    "iso:country":"AT",
    "sg:address":"Unterberg 1",
    "sg:city":"Gro\u00dfarl",
    "sg:orig_category":"Pensionen / Privatzimmer",
    "sg:phone":"+43 6414 336",
    "sg:postcode":"5611",
    "sg:province":"Salzburg",
    "wof:name":"Neudegger Hermann",
    "wof:placetype":"venue"
},
  "geometry": {"coordinates":[13.1961202621,47.2405586243],"type":"Point"}
}