{
  "type": "Feature",
  "properties": {
    "iso:country":"AT",
    "sg:address":"Nr 4",
    "sg:city":"Steinbach am Attersee",
    "sg:orig_category":"Tourismusinformation U -Organisationen",
    "sg:phone":"+43 4376 63401",
    "sg:postcode":"4853",
    "sg:province":"Ober\u00f6sterreich",
    "wof:name":"Tourismusverband Steinbach am Attersee",
    "wof:placetype":"venue"
},
  "geometry": {"coordinates":[13.5459318161,47.8310089111],"type":"Point"}
}