{
  "type": "Feature",
  "properties": {
    "iso:country":"AT",
    "sg:address":"Frey-Gasse 15",
    "sg:city":"Gmunden",
    "sg:classifiers":[
        {
            "category":"Shopping",
            "subcategory":"Crafts & Fabrics",
            "type":"Retail Goods"
        }
    ],
    "sg:phone":"+43 761264537",
    "sg:postcode":"4810",
    "sg:province":"Ober\u00f6sterreich",
    "sg:tags":[
        "decorative",
        "ceramic",
        "artistic"
    ],
    "sg:website":"gmundner-porzelan.at",
    "wof:name":"Pesendorfer-Keramik Ges.m.b.H.",
    "wof:placetype":"venue"
},
  "geometry": {"coordinates":[13.7981462479,47.918598175],"type":"Point"}
}