{
  "type": "Feature",
  "properties": {
    "addr:full":"Hauptstr 48 St. Radegund Steiermark 8061",
    "addr:housenumber":"48",
    "addr:postcode":"8061",
    "addr:street":"Hauptstr",
    "iso:country":"AT",
    "sg:address":"Hauptstr 48",
    "sg:city":"St. Radegund",
    "sg:orig_category":"Werbeagenturen",
    "sg:phone":"+43 4331 323628",
    "sg:postcode":"8061",
    "sg:province":"Steiermark",
    "wof:name":"Adler-K\u00f6nig Andrea",
    "wof:placetype":"venue"
},
  "geometry": {"coordinates":[15.491692543,47.1784286499],"type":"Point"}
}