{
  "type": "Feature",
  "properties": {
    "addr:full":"Johannes Gutenberg-Str 5 Wiener Neustadt Nieder\u00f6sterreich 2700",
    "addr:housenumber":"5",
    "addr:postcode":"2700",
    "addr:street":"Johannes Gutenberg-Str",
    "iso:country":"AT",
    "sg:address":"Johannes Gutenberg-Str 5",
    "sg:city":"Wiener Neustadt",
    "sg:classifiers":[
        {
            "category":"Manufacturing",
            "subcategory":"Printing",
            "type":"Manufacturing & Wholesale Goods"
        }
    ],
    "sg:phone":"+43 4326 2228261",
    "sg:postcode":"2700",
    "sg:province":"Nieder\u00f6sterreich",
    "sg:tags":[
        "publishing"
    ],
    "wof:name":"LEYKAM DRUCK UNIVERSIT\u00c4TSBUCHDRUCKEREI GMBH",
    "wof:placetype":"venue"
},
  "geometry": {"coordinates":[16.2499523163,47.8381385803],"type":"Point"}
}