{
  "type": "Feature",
  "properties": {
    "addr:full":"Wiener Str 73 Theresienfeld Nieder\u00f6sterreich 2604",
    "addr:postcode":"2604",
    "addr:street":"Niederoesterreich",
    "iso:country":"AT",
    "sg:address":"Wiener Str 73",
    "sg:city":"Theresienfeld",
    "sg:orig_category":"Autoreparatur",
    "sg:phone":"+43 2622 714030",
    "sg:postcode":"2604",
    "sg:province":"Nieder\u00f6sterreich",
    "wof:name":"Mayer Ludwig",
    "wof:placetype":"venue"
},
  "geometry": {"coordinates":[16.2490692139,47.8730430603],"type":"Point"}
}