{
  "type": "Feature",
  "properties": {
    "addr:full":"Bogen 33 Tannheim Tirol 6675",
    "addr:housenumber":"33",
    "addr:postcode":"6675",
    "addr:street":"Bogen;Tirol",
    "iso:country":"AT",
    "sg:address":"Bogen 33",
    "sg:city":"Tannheim",
    "sg:classifiers":[
        {
            "category":"Park",
            "subcategory":"Provincial",
            "type":"Public Place"
        }
    ],
    "sg:phone":"+43 4356 756881",
    "sg:postcode":"6675",
    "sg:province":"Tirol",
    "sg:tags":[
        "u",
        "ski-",
        "snowboardschulen"
    ],
    "wof:name":"Ullis Erlebnisschischule",
    "wof:placetype":"venue"
},
  "geometry": {"coordinates":[10.5200738907,47.4932174683],"type":"Point"}
}