{
  "type": "Feature",
  "properties": {
    "addr:full":"Fraueng 13 Bad Ischl Ober\u00f6sterreich 4820",
    "addr:housenumber":"13",
    "addr:postcode":"4820",
    "addr:street":"Fraueng",
    "iso:country":"AT",
    "sg:address":"Fraueng 13",
    "sg:city":"Bad Ischl",
    "sg:orig_category":"Pensionen / Privatzimmer",
    "sg:phone":"+43 4361 3223406",
    "sg:postcode":"4820",
    "sg:province":"Ober\u00f6sterreich",
    "wof:name":"Schlager Walter u Hedy",
    "wof:placetype":"venue"
},
  "geometry": {"coordinates":[13.6248149872,47.7094764709],"type":"Point"}
}