{
  "type": "Feature",
  "properties": {
    "iso:country":"AT",
    "sg:address":"Liebenauer Hauptstr 242",
    "sg:city":"Liebenau",
    "sg:orig_category":"Tischlereien",
    "sg:phone":"+43 316 401160",
    "sg:postcode":"8041",
    "sg:province":"Steiermark",
    "wof:name":"Gr\u00fcbler Georg GmbH",
    "wof:placetype":"venue"
},
  "geometry": {"coordinates":[15.4681901932,47.0248603821],"type":"Point"}
}