{
  "type": "Feature",
  "properties": {
    "iso:country":"AT",
    "sg:address":"Industriestr 39",
    "sg:city":"Guntramsdorf",
    "sg:orig_category":"Speditionen",
    "sg:phone":"+43 2236 44099",
    "sg:postcode":"2353",
    "sg:province":"Nieder\u00f6sterreich",
    "wof:name":"Weisi Wolfgang GmbH",
    "wof:placetype":"venue"
},
  "geometry": {"coordinates":[16.3245697021,48.0620994568],"type":"Point"}
}