{
  "type": "Feature",
  "properties": {
    "addr:full":"Linzer Strasse 80 Wien Wien 1140",
    "addr:housenumber":"80",
    "addr:postcode":"1140",
    "addr:street":"Linzer Strasse",
    "iso:country":"AT",
    "sg:address":"Linzer Strasse 80",
    "sg:city":"Wien",
    "sg:orig_category":"Drawn And Punched Parts For Motor Vehicles",
    "sg:phone":"+43 1 9822214",
    "sg:postcode":"1140",
    "sg:province":"Wien",
    "wof:name":"Br\u00fcder Settmacher",
    "wof:placetype":"venue"
},
  "geometry": {"coordinates":[16.3052349091,48.1940116882],"type":"Point"}
}