{
  "type": "Feature",
  "properties": {
    "iso:country":"AT",
    "sg:address":"Glemmtaler Landesstr 483",
    "sg:city":"Saalbach",
    "sg:orig_category":"Energiespartechnik",
    "sg:phone":"+43 6541 62734",
    "sg:postcode":"5753",
    "sg:province":"Salzburg",
    "wof:name":"Freizeit und Technik GesmbH",
    "wof:placetype":"venue"
},
  "geometry": {"coordinates":[12.6380796432,47.3894271851],"type":"Point"}
}