{
  "type": "Feature",
  "properties": {
    "addr:full":"Unterer Paspelsweg 46 Rankweil Vorarlberg 6830",
    "addr:housenumber":"46",
    "addr:postcode":"6830",
    "addr:street":"Unterer Paspelsweg",
    "iso:country":"AT",
    "sg:address":"Unterer Paspelsweg 46",
    "sg:city":"Rankweil",
    "sg:classifiers":[
        {
            "category":"Home & Garden",
            "subcategory":"Building Materials",
            "type":"Retail Goods"
        }
    ],
    "sg:phone":"+43 5522 83583",
    "sg:postcode":"6830",
    "sg:province":"Vorarlberg",
    "sg:tags":[
        "baustoffe",
        "-material",
        "u"
    ],
    "wof:name":"AMW Asphalt Mischwerk GmbH",
    "wof:placetype":"venue"
},
  "geometry": {"coordinates":[9.5855340958,47.285861969],"type":"Point"}
}