{
  "type": "Feature",
  "properties": {
    "iso:country":"AT",
    "sg:address":"Sch\u00f6nowitzstr 18",
    "sg:city":"Leoben",
    "sg:orig_category":"\u00c3\u201erzte / F Allgemeinmedizin",
    "sg:phone":"+43 3842 81586",
    "sg:postcode":"8700",
    "sg:province":"Steiermark",
    "wof:name":"Krainer Theresia Dr",
    "wof:placetype":"venue"
},
  "geometry": {"coordinates":[15.1174612045,47.3815040588],"type":"Point"}
}