{
  "type": "Feature",
  "properties": {
    "addr:full":"Gewerbepark Stubai 2 Mieders Tirol 6142",
    "addr:housenumber":"2",
    "addr:postcode":"6142",
    "addr:street":"Gewerbepark Stubai;Tirol",
    "iso:country":"AT",
    "sg:address":"Gewerbepark Stubai 2",
    "sg:city":"Mieders",
    "sg:orig_category":"Beton- U Betonsteinwerke",
    "sg:phone":"+43 5225 64366",
    "sg:postcode":"6142",
    "sg:province":"Tirol",
    "wof:name":"K Innerebner GmbH",
    "wof:placetype":"venue"
},
  "geometry": {"coordinates":[11.3796854019,47.1693458557],"type":"Point"}
}