{
  "type": "Feature",
  "properties": {
    "iso:country":"AT",
    "sg:address":"Radetzkystr 37",
    "sg:city":"Klagenfurt",
    "sg:orig_category":"Non-Classified Establishments",
    "sg:phone":"+43 463 500625",
    "sg:postcode":"9020",
    "sg:province":"K\u00e4rnten",
    "wof:name":"Kreuzschwestern",
    "wof:placetype":"venue"
},
  "geometry": {"coordinates":[14.2955036163,46.6279640198],"type":"Point"}
}