{
  "type": "Feature",
  "properties": {
    "addr:full":"Karnerviertel 76 Bruck an der Lafnitz Steiermark 8251",
    "addr:housenumber":"76",
    "addr:postcode":"8251",
    "addr:street":"Karnerviertel",
    "iso:country":"AT",
    "sg:address":"Karnerviertel 76",
    "sg:city":"Bruck an der Lafnitz",
    "sg:orig_category":"Schmieden U Schmiedeeisenelemente",
    "sg:phone":"+43 4333 3123920",
    "sg:postcode":"8251",
    "sg:province":"Steiermark",
    "wof:name":"Fally Josef",
    "wof:placetype":"venue"
},
  "geometry": {"coordinates":[15.9161109924,47.4382095337],"type":"Point"}
}