{
  "type": "Feature",
  "properties": {
    "addr:full":"Sch\u00e4rdinger Str 1 Pasching Ober\u00f6sterreich 4061",
    "addr:housenumber":"1",
    "addr:postcode":"4061",
    "addr:street":"Str;Oberoesterreich",
    "iso:country":"AT",
    "sg:address":"Sch\u00e4rdinger Str 1",
    "sg:city":"Pasching",
    "sg:orig_category":"Genossenschaften",
    "sg:phone":"+43 7229 6840",
    "sg:postcode":"4061",
    "sg:province":"Ober\u00f6sterreich",
    "wof:name":"Berglandmilch registrierte Genossenschaft mit beschr\u00e4nkter Haftung",
    "wof:placetype":"venue"
},
  "geometry": {"coordinates":[14.2019853592,48.2585906982],"type":"Point"}
}