{
  "type": "Feature",
  "properties": {
    "addr:full":"Dorf 120 Maria Alm am Steinernen Meer Salzburg 5761",
    "addr:housenumber":"120",
    "addr:postcode":"5761",
    "addr:street":"Dorf;Alm",
    "iso:country":"AT",
    "sg:address":"Dorf 120",
    "sg:city":"Maria Alm am Steinernen Meer",
    "sg:orig_category":"Volksschulen",
    "sg:phone":"+43 4365 8477730",
    "sg:postcode":"5761",
    "sg:province":"Salzburg",
    "wof:name":"Volksschule",
    "wof:placetype":"venue"
},
  "geometry": {"coordinates":[12.9026556015,47.4013557434],"type":"Point"}
}