{
  "type": "Feature",
  "properties": {
    "addr:full":"Ebnersteig 23 Fulpmes Tirol 6166",
    "addr:housenumber":"23",
    "addr:postcode":"6166",
    "addr:street":"Ebnersteig;Tirol",
    "iso:country":"AT",
    "sg:address":"Ebnersteig 23",
    "sg:city":"Fulpmes",
    "sg:orig_category":"Bodenverlegung",
    "sg:phone":"+43 5225 63105",
    "sg:postcode":"6166",
    "sg:province":"Tirol",
    "wof:name":"Vogelsberger Ernst",
    "wof:placetype":"venue"
},
  "geometry": {"coordinates":[11.347943306,47.1417236328],"type":"Point"}
}