{
  "type": "Feature",
  "properties": {
    "addr:full":"Grieskai 52/2 Graz Steiermark 8020",
    "addr:housenumber":"52 / 2",
    "addr:postcode":"8020",
    "addr:street":"Grieskai",
    "iso:country":"AT",
    "sg:address":"Grieskai 52/2",
    "sg:city":"Graz",
    "sg:orig_category":"Werbeagenturen",
    "sg:phone":"+43 316 822922",
    "sg:postcode":"8020",
    "sg:province":"Steiermark",
    "wof:name":"Fuisz-Moodley + Wagner",
    "wof:placetype":"venue"
},
  "geometry": {"coordinates":[15.4337921143,47.0648002625],"type":"Point"}
}