{
  "type": "Feature",
  "properties": {
    "addr:full":"Hauptstr 50 Gramatneusiedl Nieder\u00f6sterreich 2440",
    "addr:housenumber":"50",
    "addr:postcode":"2440",
    "addr:street":"Hauptstr",
    "iso:country":"AT",
    "sg:address":"Hauptstr 50",
    "sg:city":"Gramatneusiedl",
    "sg:orig_category":"Fleischhauereien",
    "sg:phone":"+43 2234 73476",
    "sg:postcode":"2440",
    "sg:province":"Nieder\u00f6sterreich",
    "wof:name":"Fleisch-Wurst-Graf GmbH",
    "wof:placetype":"venue"
},
  "geometry": {"coordinates":[16.4924373627,48.0240936279],"type":"Point"}
}