{
  "type": "Feature",
  "properties": {
    "iso:country":"AT",
    "sg:address":"Arbesbach 67",
    "sg:city":"Arbesbach",
    "sg:classifiers":[
        {
            "category":"Manufacturing",
            "subcategory":"Wood Products",
            "type":"Manufacturing & Wholesale Goods"
        }
    ],
    "sg:phone":"+43 2813 240",
    "sg:postcode":"3925",
    "sg:province":"Nieder\u00f6sterreich",
    "sg:tags":[
        "gate",
        "made",
        "door"
    ],
    "sg:website":"stemmer.at",
    "wof:name":"Josef Stemmer GesmbH",
    "wof:placetype":"venue"
},
  "geometry": {"coordinates":[14.9514341354,48.4862365723],"type":"Point"}
}