{
  "type": "Feature",
  "properties": {
    "iso:country":"AT",
    "sg:address":"Landstr 59-61",
    "sg:city":"Linz",
    "sg:orig_category":"Banken U Sparkassen",
    "sg:phone":"+43 4373 2663335",
    "sg:postcode":"4020",
    "sg:province":"Ober\u00f6sterreich",
    "wof:name":"PSK - Point",
    "wof:placetype":"venue"
},
  "geometry": {"coordinates":[14.291557312,48.2988929749],"type":"Point"}
}