{
  "type": "Feature",
  "properties": {
    "addr:full":"Niederottnang 15 Ottnang am Hausruck Ober\u00f6sterreich 4901",
    "addr:housenumber":"15",
    "addr:postcode":"4901",
    "addr:street":"Niederottnang",
    "iso:country":"AT",
    "sg:address":"Niederottnang 15",
    "sg:city":"Ottnang am Hausruck",
    "sg:classifiers":[
        {
            "category":"Building & Trades",
            "subcategory":"Landfill",
            "type":"Services"
        }
    ],
    "sg:phone":"+43 76768860",
    "sg:postcode":"4901",
    "sg:province":"Ober\u00f6sterreich",
    "sg:tags":[
        "floor",
        "laying",
        "parquet"
    ],
    "wof:name":"B\u00dcROCENTER MAIR",
    "wof:placetype":"venue"
},
  "geometry": {"coordinates":[13.665930748,48.0873031616],"type":"Point"}
}