{
  "type": "Feature",
  "properties": {
    "addr:full":"Steing 38 Wien Wien 1030",
    "addr:housenumber":"38",
    "addr:postcode":"1030",
    "addr:street":"Steing",
    "iso:country":"AT",
    "sg:address":"Steing 38",
    "sg:city":"Wien",
    "sg:orig_category":"Installationsunternehmen",
    "sg:phone":"+43 1 7987284",
    "sg:postcode":"1030",
    "sg:province":"Wien",
    "wof:name":"JAK Installationen GmbH",
    "wof:placetype":"venue"
},
  "geometry": {"coordinates":[16.3926582336,48.1922874451],"type":"Point"}
}