{
  "type": "Feature",
  "properties": {
    "iso:country":"AT",
    "sg:address":"Kircheng 21",
    "sg:city":"Wien",
    "sg:orig_category":"Blumenvermittlung, Blumeneinzelhandel",
    "sg:phone":"+43 1 5238389",
    "sg:postcode":"1070",
    "sg:province":"Wien",
    "sg:website":"flowers.at",
    "wof:name":"Fleur-Blumen Naderer",
    "wof:placetype":"venue"
},
  "geometry": {"coordinates":[16.3516273499,48.2019271851],"type":"Point"}
}