{
  "type": "Feature",
  "properties": {
    "addr:full":"Taufkirchner Str 20 Andorf Ober\u00f6sterreich 4770",
    "addr:postcode":"4770",
    "addr:street":"Str;Andorf",
    "iso:country":"AT",
    "sg:address":"Taufkirchner Str 20",
    "sg:city":"Andorf",
    "sg:orig_category":"Dachdeckereien",
    "sg:phone":"+43 7766 2336",
    "sg:postcode":"4770",
    "sg:province":"Ober\u00f6sterreich",
    "wof:name":"Rechtorik G\u00fcnther GesmbH",
    "wof:placetype":"venue"
},
  "geometry": {"coordinates":[13.5776348114,48.371761322],"type":"Point"}
}