{
  "type": "Feature",
  "properties": {
    "addr:full":"Falkstrasse 1/1 Innsbruck Tirol 6020",
    "addr:housenumber":"1 / 1",
    "addr:postcode":"6020",
    "addr:street":"Falkstrasse;Tirol",
    "iso:country":"AT",
    "sg:address":"Falkstrasse 1/1",
    "sg:city":"Innsbruck",
    "sg:classifiers":[
        {
            "category":"Shopping",
            "subcategory":"Books",
            "type":"Retail Goods"
        }
    ],
    "sg:phone":"+43 512 580733",
    "sg:postcode":"6020",
    "sg:province":"Tirol",
    "sg:website":"obelisk-verlag.at",
    "wof:name":"Obelisk - Verlag Inhaber Helga Buchroithner",
    "wof:placetype":"venue"
},
  "geometry": {"coordinates":[11.4022312164,47.2722015381],"type":"Point"}
}