{
  "type": "Feature",
  "properties": {
    "addr:full":"Walgaustrasse 8 Th\u00fcringen Vorarlberg 6712",
    "addr:housenumber":"8",
    "addr:postcode":"6712",
    "addr:street":"Walgaustrasse",
    "iso:country":"AT",
    "sg:address":"Walgaustrasse 8",
    "sg:city":"Th\u00fcringen",
    "sg:classifiers":[
        {
            "category":"Banks & Credit Unions",
            "subcategory":"Investment Brokerage",
            "type":"Services"
        }
    ],
    "sg:phone":"+43 5550 2213",
    "sg:postcode":"6712",
    "sg:province":"Vorarlberg",
    "sg:tags":[
        "absorption",
        "refrigerator"
    ],
    "sg:website":"ib-brugger.com",
    "wof:name":"Elektro Brugger",
    "wof:placetype":"venue"
},
  "geometry": {"coordinates":[9.7684850693,47.1981925964],"type":"Point"}
}