{
  "type": "Feature",
  "properties": {
    "iso:country":"AT",
    "sg:address":"Trientlg 57",
    "sg:city":"Innsbruck",
    "sg:orig_category":"Maler, Anstreicher U Lackierer",
    "sg:phone":"+43 4351 2344625",
    "sg:postcode":"6020",
    "sg:province":"Tirol",
    "wof:name":"Kaya Fikret Malerbetrieb",
    "wof:placetype":"venue"
},
  "geometry": {"coordinates":[11.4367752075,47.2689247131],"type":"Point"}
}