{
  "type": "Feature",
  "properties": {
    "addr:full":"Lorettostrasse 22 Hall in Tirol Tirol 6060",
    "addr:housenumber":"22",
    "addr:postcode":"6060",
    "addr:street":"Lorettostrasse;Tirol",
    "iso:country":"AT",
    "sg:address":"Lorettostrasse 22",
    "sg:city":"Hall in Tirol",
    "sg:classifiers":[
        {
            "category":"Manufacturing",
            "subcategory":"Wood Products",
            "type":"Manufacturing & Wholesale Goods"
        }
    ],
    "sg:phone":"+43 5223 575410",
    "sg:postcode":"6060",
    "sg:province":"Tirol",
    "sg:tags":[
        "solid",
        "ceiling",
        "made",
        "panel"
    ],
    "wof:name":"Romed Posch Tischlerei",
    "wof:placetype":"venue"
},
  "geometry": {"coordinates":[11.4784069061,47.2772064209],"type":"Point"}
}