{
  "type": "Feature",
  "properties": {
    "addr:full":"Katsdorf Ober\u00f6sterreich 4223",
    "addr:postcode":"4223",
    "iso:country":"AT",
    "sg:city":"Katsdorf",
    "sg:orig_category":"Feuerwehren",
    "sg:phone":"+43 7235 88726",
    "sg:postcode":"4223",
    "sg:province":"Ober\u00f6sterreich",
    "wof:name":"Freiwillige Feuerwehr Ruhstetten",
    "wof:placetype":"venue"
},
  "geometry": {"coordinates":[14.474240303,48.3178596497],"type":"Point"}
}