{
  "type": "Feature",
  "properties": {
    "addr:full":"Greifenburg 281 Greifenburg K\u00e4rnten 9761",
    "addr:housenumber":"281",
    "addr:postcode":"9761",
    "addr:street":"Greifenburg;Kaernten",
    "iso:country":"AT",
    "sg:address":"Greifenburg 281",
    "sg:city":"Greifenburg",
    "sg:classifiers":[
        {
            "category":"Home & Garden",
            "subcategory":"Household Appliances",
            "type":"Retail Goods"
        }
    ],
    "sg:phone":"+43 4712 312",
    "sg:postcode":"9761",
    "sg:province":"K\u00e4rnten",
    "sg:tags":[
        "electric"
    ],
    "wof:name":"Hans Assam jun.",
    "wof:placetype":"venue"
},
  "geometry": {"coordinates":[13.1805706024,46.7507743835],"type":"Point"}
}