{
  "type": "Feature",
  "properties": {
    "iso:country":"AT",
    "sg:address":"Nr 5",
    "sg:city":"Wegscheid",
    "sg:orig_category":"Imkereien",
    "sg:phone":"+43 4338 84550",
    "sg:postcode":"8634",
    "sg:province":"Steiermark",
    "wof:name":"Singer Harald",
    "wof:placetype":"venue"
},
  "geometry": {"coordinates":[15.3247861862,47.6854286194],"type":"Point"}
}