{
  "type": "Feature",
  "properties": {
    "iso:country":"AT",
    "sg:address":"Hauerweg 6",
    "sg:city":"Tulbing",
    "sg:orig_category":"Raumgestaltung",
    "sg:phone":"+43 2273 2668",
    "sg:postcode":"3434",
    "sg:province":"Nieder\u00f6sterreich",
    "wof:name":"Pichler-H\u00f6ller Ingrid - IPH-Design",
    "wof:placetype":"venue"
},
  "geometry": {"coordinates":[16.1226959229,48.290435791],"type":"Point"}
}