{
  "type": "Feature",
  "properties": {
    "addr:full":"Mitte 96 K\u00fchnsdorf K\u00e4rnten 9125",
    "addr:housenumber":"96",
    "addr:postcode":"9125",
    "addr:street":"Mitte;Kaernten",
    "iso:country":"AT",
    "sg:address":"Mitte 96",
    "sg:city":"K\u00fchnsdorf",
    "sg:classifiers":[
        {
            "category":"Shopping",
            "subcategory":"Crafts & Fabrics",
            "type":"Retail Goods"
        }
    ],
    "sg:phone":"+43 4342 3249490",
    "sg:postcode":"9125",
    "sg:province":"K\u00e4rnten",
    "wof:name":"FUNDER GMBH",
    "wof:placetype":"venue"
},
  "geometry": {"coordinates":[14.6350193024,46.6194801331],"type":"Point"}
}