{
  "type": "Feature",
  "properties": {
    "addr:full":"Wickenburgg 13/1 Wien Wien 1080",
    "addr:housenumber":"13 / 1",
    "addr:postcode":"1080",
    "addr:street":"Wickenburgg",
    "iso:country":"AT",
    "sg:address":"Wickenburgg 13/1",
    "sg:city":"Wien",
    "sg:orig_category":"Logistik",
    "sg:phone":"+43 4314 0301830",
    "sg:postcode":"1080",
    "sg:province":"Wien",
    "wof:name":"LESCHACO AUSTRIA Logistik GmbH",
    "wof:placetype":"venue"
},
  "geometry": {"coordinates":[16.3538093567,48.2133598328],"type":"Point"}
}