{
  "type": "Feature",
  "properties": {
    "addr:full":"Kalvarienbergstr 18 Neusiedl am See Burgenland 7100",
    "addr:housenumber":"18",
    "addr:postcode":"7100",
    "addr:street":"Kalvarienbergstr",
    "iso:country":"AT",
    "sg:address":"Kalvarienbergstr 18",
    "sg:city":"Neusiedl am See",
    "sg:orig_category":"Friseure U Frisiersalons",
    "sg:phone":"+43 4321 678718",
    "sg:postcode":"7100",
    "sg:province":"Burgenland",
    "wof:name":"Frisurenstudio Gabriela",
    "wof:placetype":"venue"
},
  "geometry": {"coordinates":[16.849691391,47.9443321228],"type":"Point"}
}