{
  "type": "Feature",
  "properties": {
    "addr:full":"Altlenzing 31 Lenzing Ober\u00f6sterreich 4860",
    "addr:housenumber":"31",
    "addr:postcode":"4860",
    "addr:street":"Altlenzing",
    "iso:country":"AT",
    "sg:address":"Altlenzing 31",
    "sg:city":"Lenzing",
    "sg:orig_category":"Volksschulen",
    "sg:phone":"+43 767295019",
    "sg:postcode":"4860",
    "sg:province":"Ober\u00f6sterreich",
    "wof:name":"Volksschule Altlenzing",
    "wof:placetype":"venue"
},
  "geometry": {"coordinates":[13.6246995926,47.9719276428],"type":"Point"}
}