{
  "type": "Feature",
  "properties": {
    "iso:country":"AT",
    "sg:address":"Endach 40",
    "sg:city":"Kufstein",
    "sg:classifiers":[
        {
            "category":"Shopping",
            "subcategory":"Clothing, Apparel, & Fashions",
            "type":"Retail Goods"
        }
    ],
    "sg:phone":"+43 4353 726970",
    "sg:postcode":"6330",
    "sg:province":"Tirol",
    "sg:tags":[
        "clothes"
    ],
    "wof:name":"ANITA DR HELBIG GMBH",
    "wof:placetype":"venue"
},
  "geometry": {"coordinates":[12.150302887,47.5668792725],"type":"Point"}
}