{
  "type": "Feature",
  "properties": {
    "iso:country":"AT",
    "sg:address":"Khemeterg 8",
    "sg:city":"Wien",
    "sg:orig_category":"Apotheken",
    "sg:phone":"+43 1 8885144",
    "sg:postcode":"1230",
    "sg:province":"Wien",
    "wof:name":"Birken-Apotheke Mag pharm Hans Baumgartner",
    "wof:placetype":"venue"
},
  "geometry": {"coordinates":[16.2849407196,48.146270752],"type":"Point"}
}