{
  "type": "Feature",
  "properties": {
    "iso:country":"AT",
    "sg:address":"Manker Stra\u00dfe 26",
    "sg:city":"P\u00f6chlarn",
    "sg:orig_category":"Freizeit, Tiere U Pflanzen",
    "sg:phone":"+43 4327 572805",
    "sg:postcode":"3380",
    "sg:province":"Nieder\u00f6sterreich",
    "sg:website":"http://www.hela.at/",
    "wof:name":"Hela Zoo-Versand",
    "wof:placetype":"venue"
},
  "geometry": {"coordinates":[-79.38526153559999,41.2145881653],"type":"Point"}
}