{
  "type": "Feature",
  "properties": {
    "iso:country":"AT",
    "sg:address":"Lastenstr 15",
    "sg:city":"Treibach-Althofen",
    "sg:classifiers":[
        {
            "category":"Taxi",
            "type":"Transportation"
        }
    ],
    "sg:phone":"+43 4342 624620",
    "sg:postcode":"9330",
    "sg:province":"K\u00e4rnten",
    "sg:tags":[
        "personentransporte",
        "u"
    ],
    "wof:name":"Citytaxi Gerald Lackner",
    "wof:placetype":"venue"
},
  "geometry": {"coordinates":[14.469953537,46.8701858521],"type":"Point"}
}