{
  "type": "Feature",
  "properties": {
    "addr:full":"Tschidererweg 8 Hall in Tirol Tirol 6060",
    "addr:housenumber":"8",
    "addr:postcode":"6060",
    "addr:street":"Tschidererweg;Tirol",
    "iso:country":"AT",
    "sg:address":"Tschidererweg 8",
    "sg:city":"Hall in Tirol",
    "sg:orig_category":"Salze",
    "sg:phone":"+43 5223 56295",
    "sg:postcode":"6060",
    "sg:province":"Tirol",
    "wof:name":"Salz Wei\u00df GesmbH",
    "wof:placetype":"venue"
},
  "geometry": {"coordinates":[11.5007810593,47.2776641846],"type":"Point"}
}