{
  "type": "Feature",
  "properties": {
    "addr:full":"Ybbsitzer Str 39 Waidhofen an der Ybbs Nieder\u00f6sterreich 3340",
    "addr:postcode":"3340",
    "addr:street":"Str 39",
    "iso:country":"AT",
    "sg:address":"Ybbsitzer Str 39",
    "sg:city":"Waidhofen an der Ybbs",
    "sg:orig_category":"Modellbau",
    "sg:phone":"+43 4374 4253890",
    "sg:postcode":"3340",
    "sg:province":"Nieder\u00f6sterreich",
    "wof:name":"Buxbaum Hans",
    "wof:placetype":"venue"
},
  "geometry": {"coordinates":[14.782869339,47.9570388794],"type":"Point"}
}