{
  "type": "Feature",
  "properties": {
    "addr:full":"Vereinsheimstrasse 6  Hallein Salzburg 5400",
    "addr:housenumber":"6",
    "addr:postcode":"5400",
    "addr:street":"Vereinsheimstrasse;Salzburg",
    "iso:country":"AT",
    "sg:address":"Vereinsheimstrasse 6 ",
    "sg:city":"Hallein",
    "sg:classifiers":[
        {
            "category":"Government",
            "subcategory":"Fire Station",
            "type":"Public Place"
        }
    ],
    "sg:phone":"+43 6245 87610",
    "sg:postcode":"5400",
    "sg:province":"Salzburg",
    "sg:tags":[
        "supraregional",
        "plant",
        "installation",
        "heating"
    ],
    "wof:name":"Werner Fraunhuber Installationen GmbH",
    "wof:placetype":"venue"
},
  "geometry": {"coordinates":[13.0810089111,47.7272491455],"type":"Point"}
}