{
  "type": "Feature",
  "properties": {
    "addr:full":"Annag 5/T\u00fcr 210 Wien Wien 1010",
    "addr:housenumber":"5 / tuer 210",
    "addr:postcode":"1010",
    "addr:street":"Annag",
    "iso:country":"AT",
    "sg:address":"Annag 5/T\u00fcr 210",
    "sg:city":"Wien",
    "sg:classifiers":[
        {
            "category":"Restaurant",
            "type":"Food & Drink"
        }
    ],
    "sg:phone":"+43 1 5128060",
    "sg:postcode":"1010",
    "sg:province":"Wien",
    "wof:name":"Atelier f Papierrestaurierungen Marie Kastner",
    "wof:placetype":"venue"
},
  "geometry": {"coordinates":[16.3688049316,48.2025489807],"type":"Point"}
}