{
  "type": "Feature",
  "properties": {
    "iso:country":"AT",
    "sg:address":"Waschanger 24",
    "sg:city":"Gm\u00fcnd",
    "sg:orig_category":"Autoreparatur",
    "sg:phone":"+43 4732 3889",
    "sg:postcode":"9853",
    "sg:province":"K\u00e4rnten",
    "wof:name":"Pirker Fritz",
    "wof:placetype":"venue"
},
  "geometry": {"coordinates":[13.5373802185,46.9085006714],"type":"Point"}
}