{
  "type": "Feature",
  "properties": {
    "iso:country":"AT",
    "sg:address":"Frachtenstr 3",
    "sg:city":"M\u00fcrzzuschlag",
    "sg:orig_category":"Feuerwehren",
    "sg:phone":"+43 3852 23010",
    "sg:postcode":"8680",
    "sg:province":"Steiermark",
    "wof:name":"Freiwillige Feuerwehr M\u00fcrzzuschlag",
    "wof:placetype":"venue"
},
  "geometry": {"coordinates":[15.6761932373,47.6073455811],"type":"Point"}
}