{
  "type": "Feature",
  "properties": {
    "addr:full":"Feldg 6 Raggendorf Nieder\u00f6sterreich 2215",
    "addr:housenumber":"6",
    "addr:postcode":"2215",
    "addr:street":"Feldg;Niederoesterreich",
    "iso:country":"AT",
    "sg:address":"Feldg 6",
    "sg:city":"Raggendorf",
    "sg:orig_category":"Weine / Einzelhandel",
    "sg:phone":"+43 2289 2444",
    "sg:postcode":"2215",
    "sg:province":"Nieder\u00f6sterreich",
    "wof:name":"Klenkhart Hermann",
    "wof:placetype":"venue"
},
  "geometry": {"coordinates":[16.6567173004,48.3949775696],"type":"Point"}
}