{
  "type": "Feature",
  "properties": {
    "addr:full":"Danner 10 Aurolzm\u00fcnster Ober\u00f6sterreich 4971",
    "addr:housenumber":"10",
    "addr:postcode":"4971",
    "addr:street":"Danner;Oberoesterreich",
    "iso:country":"AT",
    "sg:address":"Danner 10",
    "sg:city":"Aurolzm\u00fcnster",
    "sg:orig_category":"Autohandel",
    "sg:phone":"+43 7752 85588",
    "sg:postcode":"4971",
    "sg:province":"Ober\u00f6sterreich",
    "wof:name":"Wirth Siegfried Ing",
    "wof:placetype":"venue"
},
  "geometry": {"coordinates":[13.4786472321,48.2293167114],"type":"Point"}
}