{
  "type": "Feature",
  "properties": {
    "iso:country":"AT",
    "sg:address":"Ragnitzstr 34a",
    "sg:city":"Ragnitz",
    "sg:orig_category":"Spenglereien, Blitzableiter U Blitzschutzanlagen",
    "sg:phone":"+43 316 3242170",
    "sg:postcode":"8047",
    "sg:province":"Steiermark",
    "wof:name":"Blitzschutzbau Schabauer Helmut",
    "wof:placetype":"venue"
},
  "geometry": {"coordinates":[15.4767599106,47.0783119202],"type":"Point"}
}