{
  "type": "Feature",
  "properties": {
    "addr:full":"Hinterrinnweg 15 Aldrans Tirol 6071",
    "addr:housenumber":"15",
    "addr:postcode":"6071",
    "addr:street":"Hinterrinnweg;Tirol",
    "iso:country":"AT",
    "sg:address":"Hinterrinnweg 15",
    "sg:city":"Aldrans",
    "sg:orig_category":"Unternehmensberatung",
    "sg:phone":"+43 512 360318",
    "sg:postcode":"6071",
    "sg:province":"Tirol",
    "wof:name":"Berger Dr Consult OEG",
    "wof:placetype":"venue"
},
  "geometry": {"coordinates":[11.4500017166,47.2476005554],"type":"Point"}
}