{
  "type": "Feature",
  "properties": {
    "addr:full":"Roseggerstr 2 Innsbruck Tirol 6020",
    "addr:housenumber":"2",
    "addr:postcode":"6020",
    "addr:street":"Roseggerstr;Tirol",
    "iso:country":"AT",
    "sg:address":"Roseggerstr 2",
    "sg:city":"Innsbruck",
    "sg:orig_category":"Physiotherapie",
    "sg:phone":"+43 512 364054",
    "sg:postcode":"6020",
    "sg:province":"Tirol",
    "wof:name":"Klema Astrid Dipl-PT",
    "wof:placetype":"venue"
},
  "geometry": {"coordinates":[11.4107961655,47.2626266479],"type":"Point"}
}