{
  "type": "Feature",
  "properties": {
    "addr:full":"Gmundner Str 9 Schwanenstadt Ober\u00f6sterreich 4690",
    "addr:housenumber":"9",
    "addr:postcode":"4690",
    "addr:street":"Str",
    "iso:country":"AT",
    "sg:address":"Gmundner Str 9",
    "sg:city":"Schwanenstadt",
    "sg:orig_category":"Restaurants: Chinesisch",
    "sg:phone":"+43 76732266",
    "sg:postcode":"4690",
    "sg:province":"Ober\u00f6sterreich",
    "wof:name":"China-Restaurant Lotos",
    "wof:placetype":"venue"
},
  "geometry": {"coordinates":[13.7772388458,48.0527763367],"type":"Point"}
}