{
  "type": "Feature",
  "properties": {
    "iso:country":"AT",
    "sg:address":"Wiener Str 5",
    "sg:city":"Theresienfeld",
    "sg:orig_category":"Botendienste",
    "sg:phone":"+43 2622 72223",
    "sg:postcode":"2604",
    "sg:province":"Nieder\u00f6sterreich",
    "wof:name":"Lipp Christian",
    "wof:placetype":"venue"
},
  "geometry": {"coordinates":[16.2478046417,47.8617630005],"type":"Point"}
}