{
  "type": "Feature",
  "properties": {
    "addr:full":"Linzer Str 182 Wien Wien 1140",
    "addr:housenumber":"182",
    "addr:postcode":"1140",
    "addr:street":"Linzer Str",
    "iso:country":"AT",
    "sg:address":"Linzer Str 182",
    "sg:city":"Wien",
    "sg:classifiers":[
        {
            "category":"Restaurant",
            "type":"Food & Drink"
        }
    ],
    "sg:phone":"+43 1 4199276",
    "sg:postcode":"1140",
    "sg:province":"Wien",
    "sg:tags":[
        "pizzeria"
    ],
    "wof:name":"Pizzeria Cavallo",
    "wof:placetype":"venue"
},
  "geometry": {"coordinates":[16.289768219,48.1948432922],"type":"Point"}
}