{
  "type": "Feature",
  "properties": {
    "addr:full":"Elterleinpl 8 Wien Wien 1170",
    "addr:housenumber":"8",
    "addr:postcode":"1170",
    "addr:street":"Elterleinpl",
    "iso:country":"AT",
    "sg:address":"Elterleinpl 8",
    "sg:city":"Wien",
    "sg:orig_category":"Immobilienverwaltungen, Immobilienmakler",
    "sg:phone":"+43 1 48614660",
    "sg:postcode":"1170",
    "sg:province":"Wien",
    "wof:name":"Halmer Heinz-J\u00fcrgen Dkfm",
    "wof:placetype":"venue"
},
  "geometry": {"coordinates":[16.3309440613,48.2181053162],"type":"Point"}
}