{
  "type": "Feature",
  "properties": {
    "iso:country":"AT",
    "sg:address":"Hebbelpl 7",
    "sg:city":"Wien",
    "sg:orig_category":"Grafische Maschinen U Reparaturen",
    "sg:phone":"+43 4316 01400",
    "sg:postcode":"1100",
    "sg:province":"Wien",
    "sg:website":"at.heidelberg.com",
    "wof:name":"Heidelberger Druckmaschinen Austria Vertriebs-GmbH",
    "wof:placetype":"venue"
},
  "geometry": {"coordinates":[16.3788719177,48.1661376953],"type":"Point"}
}