{
  "type": "Feature",
  "properties": {
    "iso:country":"AT",
    "sg:address":"Meinhardstr 10",
    "sg:city":"Innsbruck",
    "sg:orig_category":"Medizintechnik",
    "sg:phone":"+43 512 575730",
    "sg:postcode":"6020",
    "sg:province":"Tirol",
    "wof:name":"Glaser & Co KG",
    "wof:placetype":"venue"
},
  "geometry": {"coordinates":[11.3987445831,47.2658805847],"type":"Point"}
}