{
  "type": "Feature",
  "properties": {
    "addr:full":"R\u00f6merstr. 16 A Bregenz Vorarlberg 6900",
    "addr:housenumber":"16 a",
    "addr:postcode":"6900",
    "addr:street":"Roemerstr.",
    "iso:country":"AT",
    "sg:address":"R\u00f6merstr. 16 A",
    "sg:city":"Bregenz",
    "sg:classifiers":[
        {
            "category":"Shopping",
            "subcategory":"Crafts & Fabrics",
            "type":"Retail Goods"
        }
    ],
    "sg:phone":"+43 4355 74442870",
    "sg:postcode":"6900",
    "sg:province":"Vorarlberg",
    "sg:tags":[
        "ceramic"
    ],
    "wof:name":"ALOIS KEMPTER GESMBH & CO KG",
    "wof:placetype":"venue"
},
  "geometry": {"coordinates":[9.7443914413,47.5015563965],"type":"Point"}
}