{
  "type": "Feature",
  "properties": {
    "addr:full":"Georg-Bucher-Str 7 Axams Tirol 6094",
    "addr:housenumber":"7",
    "addr:postcode":"6094",
    "addr:street":"Georg-Bucher-Str;Tirol",
    "iso:country":"AT",
    "sg:address":"Georg-Bucher-Str 7",
    "sg:city":"Axams",
    "sg:classifiers":[
        {
            "category":"Restaurant",
            "type":"Food & Drink"
        }
    ],
    "sg:phone":"+43 5234 68357",
    "sg:postcode":"6094",
    "sg:province":"Tirol",
    "wof:name":"Restaurant B\u00fcrgerstuben",
    "wof:placetype":"venue"
},
  "geometry": {"coordinates":[11.2783231735,47.2304496765],"type":"Point"}
}