{
  "type": "Feature",
  "properties": {
    "addr:full":"Stillfriedpl 4 Wien Wien 1160",
    "addr:housenumber":"4",
    "addr:postcode":"1160",
    "addr:street":"Stillfriedpl",
    "iso:country":"AT",
    "sg:address":"Stillfriedpl 4",
    "sg:city":"Wien",
    "sg:orig_category":"Apotheken",
    "sg:phone":"+43 1 4931349",
    "sg:postcode":"1160",
    "sg:province":"Wien",
    "wof:name":"Antonius Apotheke Mag pharm Hans Stehno KG",
    "wof:placetype":"venue"
},
  "geometry": {"coordinates":[16.3094902039,48.2121963501],"type":"Point"}
}