{
  "type": "Feature",
  "properties": {
    "addr:full":"Witzmanng 4 Baden Nieder\u00f6sterreich 2500",
    "addr:housenumber":"4",
    "addr:postcode":"2500",
    "addr:street":"Witzmanng;Niederoesterreich",
    "iso:country":"AT",
    "sg:address":"Witzmanng 4",
    "sg:city":"Baden",
    "sg:orig_category":"Psychotherapie",
    "sg:phone":"+43 676 5579122",
    "sg:postcode":"2500",
    "sg:province":"Nieder\u00f6sterreich",
    "wof:name":"Kern Bettina Mag",
    "wof:placetype":"venue"
},
  "geometry": {"coordinates":[16.2236919403,48.0100097656],"type":"Point"}
}