{
  "type": "Feature",
  "properties": {
    "addr:full":"Hauptstr. 144-146  Auersthal Nieder\u00f6sterreich 2214",
    "addr:housenumber":"144-146",
    "addr:postcode":"2214",
    "addr:street":"Hauptstr.",
    "iso:country":"AT",
    "sg:address":"Hauptstr. 144-146 ",
    "sg:city":"Auersthal",
    "sg:classifiers":[
        {
            "category":"Autos & Motor Vehicles",
            "subcategory":"Automobile Sales",
            "type":"Retail Goods"
        }
    ],
    "sg:phone":"+43 4322 8822040",
    "sg:postcode":"2214",
    "sg:province":"Nieder\u00f6sterreich",
    "sg:tags":[
        "motor-cars"
    ],
    "wof:name":"VOCK & SEITER KG",
    "wof:placetype":"venue"
},
  "geometry": {"coordinates":[16.6436882019,48.3718757629],"type":"Point"}
}