{
  "type": "Feature",
  "properties": {
    "addr:full":"Linzer Str 160 Wien Wien 1140",
    "addr:housenumber":"160",
    "addr:postcode":"1140",
    "addr:street":"Linzer Str",
    "iso:country":"AT",
    "sg:address":"Linzer Str 160",
    "sg:city":"Wien",
    "sg:orig_category":"Datenverarbeitung",
    "sg:phone":"+43 1 7869150",
    "sg:postcode":"1140",
    "sg:province":"Wien",
    "wof:name":"Himmelbauer Sonja",
    "wof:placetype":"venue"
},
  "geometry": {"coordinates":[16.2935066223,48.1944656372],"type":"Point"}
}