{
  "type": "Feature",
  "properties": {
    "iso:country":"AT",
    "sg:address":"Seilerg 4",
    "sg:city":"Innsbruck",
    "sg:orig_category":"Boutiquen",
    "sg:phone":"+43 512 565130",
    "sg:postcode":"6020",
    "sg:province":"Tirol",
    "wof:name":"Blaim Ingrid",
    "wof:placetype":"venue"
},
  "geometry": {"coordinates":[11.3927755356,47.2681808472],"type":"Point"}
}