{
  "type": "Feature",
  "properties": {
    "addr:full":"Landammanng 11 Rankweil Vorarlberg 6830",
    "addr:housenumber":"11",
    "addr:postcode":"6830",
    "addr:street":"Landammanng",
    "iso:country":"AT",
    "sg:address":"Landammanng 11",
    "sg:city":"Rankweil",
    "sg:orig_category":"Friseure U Frisiersalons",
    "sg:phone":"+43 4355 2260100",
    "sg:postcode":"6830",
    "sg:province":"Vorarlberg",
    "wof:name":"Kamm & Co",
    "wof:placetype":"venue"
},
  "geometry": {"coordinates":[9.6379404068,47.2735595703],"type":"Point"}
}