{
  "type": "Feature",
  "properties": {
    "addr:full":"Nr 22 St. Stefan im Lavanttal K\u00e4rnten 9431",
    "addr:postcode":"9431",
    "addr:street":"Nr 22",
    "iso:country":"AT",
    "sg:address":"Nr 22",
    "sg:city":"St. Stefan im Lavanttal",
    "sg:orig_category":"Hauptschulen",
    "sg:phone":"+43 4352 81150",
    "sg:postcode":"9431",
    "sg:province":"K\u00e4rnten",
    "wof:name":"Hauptschule",
    "wof:placetype":"venue"
},
  "geometry": {"coordinates":[166.9221496582,-0.5282999873],"type":"Point"}
}