{
  "type": "Feature",
  "properties": {
    "iso:country":"AT",
    "sg:address":"Seeb\u00fchel 28",
    "sg:city":"Kramsach",
    "sg:orig_category":"Pensionen / Privatzimmer",
    "sg:phone":"+43 5337 63171",
    "sg:postcode":"6233",
    "sg:province":"Tirol",
    "wof:name":"Pension Christoph",
    "wof:placetype":"venue"
},
  "geometry": {"coordinates":[11.8835477829,47.4473342896],"type":"Point"}
}