{
  "type": "Feature",
  "properties": {
    "addr:full":"Neubauerstr 95 Traun Ober\u00f6sterreich 4050",
    "addr:housenumber":"95",
    "addr:postcode":"4050",
    "addr:street":"Neubauerstr",
    "iso:country":"AT",
    "sg:address":"Neubauerstr 95",
    "sg:city":"Traun",
    "sg:orig_category":"Autospenglereien",
    "sg:phone":"+43 7229 73086",
    "sg:postcode":"4050",
    "sg:province":"Ober\u00f6sterreich",
    "wof:name":"Autohaus Staufer GesmbH & Co KG",
    "wof:placetype":"venue"
},
  "geometry": {"coordinates":[14.226360321,48.2188110352],"type":"Point"}
}