{
  "type": "Feature",
  "properties": {
    "iso:country":"AT",
    "sg:address":"Bahnstr",
    "sg:city":"Lassee",
    "sg:orig_category":"Tabaktrafiken",
    "sg:phone":"+43 2213 2241",
    "sg:postcode":"2291",
    "sg:province":"Nieder\u00f6sterreich",
    "wof:name":"Grill Maria",
    "wof:placetype":"venue"
},
  "geometry": {"coordinates":[-76.4168395996,37.452419281],"type":"Point"}
}