{
  "type": "Feature",
  "properties": {
    "addr:full":"Wiener Bundesstr 15 Traun Ober\u00f6sterreich 4050",
    "addr:housenumber":"15",
    "addr:postcode":"4050",
    "iso:country":"AT",
    "sg:address":"Wiener Bundesstr 15",
    "sg:city":"Traun",
    "sg:orig_category":"\u00c3\u201erzte / F Allgemeinmedizin",
    "sg:phone":"+43 732 3818530",
    "sg:postcode":"4050",
    "sg:province":"Ober\u00f6sterreich",
    "wof:name":"Kornbichler Franz Dr",
    "wof:placetype":"venue"
},
  "geometry": {"coordinates":[14.2326755524,48.2340774536],"type":"Point"}
}