{
  "type": "Feature",
  "properties": {
    "iso:country":"AT",
    "sg:address":"Weberstr 26",
    "sg:city":"Kirchdorf an der Krems",
    "sg:orig_category":"\u00c3\u201erzte / F Allgemeinmedizin",
    "sg:phone":"+43 4375 82636400",
    "sg:postcode":"4560",
    "sg:province":"Ober\u00f6sterreich",
    "wof:name":"Diwald Heinrich Dr",
    "wof:placetype":"venue"
},
  "geometry": {"coordinates":[14.122628212,47.901309967],"type":"Point"}
}