{
  "type": "Feature",
  "properties": {
    "iso:country":"AT",
    "sg:address":"Werk-IV-Str 49",
    "sg:city":"Kapfenberg",
    "sg:orig_category":"Bars-Cafes",
    "sg:phone":"+43 4367 63116150",
    "sg:postcode":"8605",
    "sg:province":"Steiermark",
    "wof:name":"Cafe Diamond",
    "wof:placetype":"venue"
},
  "geometry": {"coordinates":[15.2912454605,47.4438438416],"type":"Point"}
}