{
  "type": "Feature",
  "properties": {
    "addr:full":"B\u00fcrstadtstr 6 Krieglach Steiermark 8670",
    "addr:housenumber":"6",
    "addr:postcode":"8670",
    "addr:street":"Buerstadtstr",
    "iso:country":"AT",
    "sg:address":"B\u00fcrstadtstr 6",
    "sg:city":"Krieglach",
    "sg:orig_category":"Gemeinden",
    "sg:phone":"+43 3855 23550",
    "sg:postcode":"8670",
    "sg:province":"Steiermark",
    "wof:name":"Marktgemeinde Krieglach",
    "wof:placetype":"venue"
},
  "geometry": {"coordinates":[15.5594148636,47.5454101562],"type":"Point"}
}