{
  "type": "Feature",
  "properties": {
    "addr:full":"Pre\u00dfbaumer Str 11 Sieghartskirchen Nieder\u00f6sterreich 3443",
    "addr:postcode":"3443",
    "addr:street":"Str 11",
    "iso:country":"AT",
    "sg:address":"Pre\u00dfbaumer Str 11",
    "sg:city":"Sieghartskirchen",
    "sg:orig_category":"Elektroinstallationsunternehmen",
    "sg:phone":"+43 2274 22380",
    "sg:postcode":"3443",
    "sg:province":"Nieder\u00f6sterreich",
    "wof:name":"Hochrieder GmbH",
    "wof:placetype":"venue"
},
  "geometry": {"coordinates":[16.0144271851,48.2530632019],"type":"Point"}
}