{
  "type": "Feature",
  "properties": {
    "iso:country":"AT",
    "sg:address":"Steinhauserstr 14a",
    "sg:city":"Salzburg",
    "sg:classifiers":[
        {
            "category":"Professional",
            "subcategory":"Computer Services",
            "type":"Services"
        }
    ],
    "sg:phone":"+43 662 881292",
    "sg:postcode":"5020",
    "sg:province":"Salzburg",
    "sg:tags":[
        "software"
    ],
    "wof:name":"Promok Simon - EDV Dienstleistungen",
    "wof:placetype":"venue"
},
  "geometry": {"coordinates":[13.0567903519,47.8144340515],"type":"Point"}
}