{
  "type": "Feature",
  "properties": {
    "iso:country":"AT",
    "sg:address":"Ramperstorfferg 41",
    "sg:city":"Wien",
    "sg:orig_category":"Fotografen",
    "sg:phone":"+43 4317 151986",
    "sg:postcode":"1050",
    "sg:province":"Wien",
    "wof:name":"Schauer Josef Fotografie",
    "wof:placetype":"venue"
},
  "geometry": {"coordinates":[16.3571643829,48.1876564026],"type":"Point"}
}