{
  "type": "Feature",
  "properties": {
    "iso:country":"AT",
    "sg:address":"Alauntalstr 21",
    "sg:city":"Krems an der Donau",
    "sg:orig_category":"Ingenieurkonsulenten / Zivilingenieure",
    "sg:phone":"+43 2732 797900",
    "sg:postcode":"3500",
    "sg:province":"Nieder\u00f6sterreich",
    "wof:name":"Salzbauer Gerhard Dipl-Ing",
    "wof:placetype":"venue"
},
  "geometry": {"coordinates":[15.5916404724,48.4108047485],"type":"Point"}
}