{
  "type": "Feature",
  "properties": {
    "addr:full":"Tweng Salzburg 5563",
    "addr:postcode":"5563",
    "addr:street":"Salzburg",
    "iso:country":"AT",
    "sg:city":"Tweng",
    "sg:orig_category":"Feuerwehren",
    "sg:phone":"+43 6471 21715",
    "sg:postcode":"5563",
    "sg:province":"Salzburg",
    "wof:name":"Feuerwehr Tweng",
    "wof:placetype":"venue"
},
  "geometry": {"coordinates":[13.5998849869,47.1909255981],"type":"Point"}
}