{
  "type": "Feature",
  "properties": {
    "iso:country":"AT",
    "sg:address":"Serlesstr 12",
    "sg:city":"Fulpmes",
    "sg:orig_category":"Pensionen / Privatzimmer",
    "sg:phone":"+43 5225 62269",
    "sg:postcode":"6166",
    "sg:province":"Tirol",
    "wof:name":"Pension Edith",
    "wof:placetype":"venue"
},
  "geometry": {"coordinates":[11.35268116,47.1525192261],"type":"Point"}
}