{
  "type": "Feature",
  "properties": {
    "addr:full":"Hauptstr 88 Rottenmann Steiermark 8786",
    "addr:housenumber":"88",
    "addr:postcode":"8786",
    "addr:street":"Hauptstr",
    "iso:country":"AT",
    "sg:address":"Hauptstr 88",
    "sg:city":"Rottenmann",
    "sg:classifiers":[
        {
            "category":"Personal",
            "subcategory":"Sauna",
            "type":"Services"
        }
    ],
    "sg:phone":"+43 3614 2620",
    "sg:postcode":"8786",
    "sg:province":"Steiermark",
    "sg:tags":[
        "u",
        "dampfbad"
    ],
    "wof:name":"Sauna d Stadtgemeindeamtes",
    "wof:placetype":"venue"
},
  "geometry": {"coordinates":[14.3544006348,47.5244674683],"type":"Point"}
}