{
  "type": "Feature",
  "properties": {
    "iso:country":"AT",
    "sg:address":"Wienerbruckstr 79",
    "sg:city":"Maria Enzersdorf",
    "sg:orig_category":"Unternehmensberatung",
    "sg:phone":"+43 2236 44389",
    "sg:postcode":"2344",
    "sg:province":"Nieder\u00f6sterreich",
    "wof:name":"Kiessler Evelyn",
    "wof:placetype":"venue"
},
  "geometry": {"coordinates":[16.3082809448,48.0992698669],"type":"Point"}
}