{
  "type": "Feature",
  "properties": {
    "iso:country":"AT",
    "sg:address":"Nr 28",
    "sg:city":"Gargellen",
    "sg:classifiers":[
        {
            "category":"Travel",
            "subcategory":"Hotels & Motels",
            "type":"Entertainment"
        }
    ],
    "sg:phone":"+43 4355 576133",
    "sg:postcode":"6787",
    "sg:province":"Vorarlberg",
    "wof:name":"Almhof Tilisuna",
    "wof:placetype":"venue"
},
  "geometry": {"coordinates":[9.9181804657,46.9698066711],"type":"Point"}
}