{
  "type": "Feature",
  "properties": {
    "addr:full":"Eisteichg 14 Graz Steiermark 8010",
    "addr:housenumber":"14",
    "addr:postcode":"8010",
    "addr:street":"Eisteichg",
    "iso:country":"AT",
    "sg:address":"Eisteichg 14",
    "sg:city":"Graz",
    "sg:orig_category":"Musikunterricht",
    "sg:phone":"+43 4331 6427094",
    "sg:postcode":"8010",
    "sg:province":"Steiermark",
    "wof:name":"Johann-Joseph-Fux-Konservatorium",
    "wof:placetype":"venue"
},
  "geometry": {"coordinates":[15.4696769714,47.0603408813],"type":"Point"}
}