{
  "type": "Feature",
  "properties": {
    "addr:full":"Friedrich-Thurner-Str 16 Ried im Innkreis Ober\u00f6sterreich 4910",
    "addr:housenumber":"16",
    "addr:postcode":"4910",
    "addr:street":"Friedrich-Thurner-Str",
    "iso:country":"AT",
    "sg:address":"Friedrich-Thurner-Str 16",
    "sg:city":"Ried im Innkreis",
    "sg:orig_category":"Versicherungsunternehmen",
    "sg:phone":"+43 4377 5285988",
    "sg:postcode":"4910",
    "sg:province":"Ober\u00f6sterreich",
    "wof:name":"Donau Versicherung",
    "wof:placetype":"venue"
},
  "geometry": {"coordinates":[13.4843053818,48.2120018005],"type":"Point"}
}