{
  "type": "Feature",
  "properties": {
    "iso:country":"AT",
    "sg:address":"Hauptpl 9",
    "sg:city":"Krieglach",
    "sg:orig_category":"Friseure U Frisiersalons",
    "sg:phone":"+43 3855 2337",
    "sg:postcode":"8670",
    "sg:province":"Steiermark",
    "wof:name":"Hairdesign Inh Leitner Barbara",
    "wof:placetype":"venue"
},
  "geometry": {"coordinates":[15.5599813461,47.5448913574],"type":"Point"}
}