{
  "type": "Feature",
  "properties": {
    "addr:full":"null Freibad Pfunds Tirol 6542",
    "addr:postcode":"6542",
    "iso:country":"AT",
    "sg:address":"null Freibad",
    "sg:city":"Pfunds",
    "sg:classifiers":[
        {
            "category":"Recreation",
            "type":"Entertainment"
        }
    ],
    "sg:phone":"+43 4354 745788",
    "sg:postcode":"6542",
    "sg:province":"Tirol",
    "sg:tags":[
        "sport",
        "adventure"
    ],
    "wof:name":"Liquid Bliss Adventures Schuchter & Hind OEG",
    "wof:placetype":"venue"
},
  "geometry": {"coordinates":[10.5369300842,46.9696540833],"type":"Point"}
}