{
  "type": "Feature",
  "properties": {
    "iso:country":"AT",
    "sg:address":"B\u00e4ckenbr\u00fcnnlg. 7b",
    "sg:city":"Wien",
    "sg:classifiers":[
        {
            "category":"Communications",
            "subcategory":"Television Station",
            "type":"Services"
        }
    ],
    "sg:phone":"+43 4314 701511",
    "sg:postcode":"1180",
    "sg:province":"Wien",
    "sg:tags":[
        "audio-visual"
    ],
    "wof:name":"LEITZ-AUSTRIA VERTRIEBSGES.MBH",
    "wof:placetype":"venue"
},
  "geometry": {"coordinates":[16.3445625305,48.2262420654],"type":"Point"}
}