{
  "type": "Feature",
  "properties": {
    "iso:country":"AT",
    "sg:address":"Hauptstr 33",
    "sg:city":"Scheibbs",
    "sg:orig_category":"Restaurants: Chinesisch",
    "sg:phone":"+43 4374 8243980",
    "sg:postcode":"3270",
    "sg:province":"Nieder\u00f6sterreich",
    "wof:name":"China Restaurant Jin Sui",
    "wof:placetype":"venue"
},
  "geometry": {"coordinates":[15.1669998169,48.0056381226],"type":"Point"}
}