{
  "type": "Feature",
  "properties": {
    "addr:full":"Kirchbacher Str Leibnitz Steiermark 8430",
    "addr:postcode":"8430",
    "addr:street":"Str Leibnitz Steiermark",
    "iso:country":"AT",
    "sg:address":"Kirchbacher Str",
    "sg:city":"Leibnitz",
    "sg:orig_category":"Damenmoden",
    "sg:phone":"+43 3452 74790",
    "sg:postcode":"8430",
    "sg:province":"Steiermark",
    "wof:name":"NEW YORKER - NYer Hansen & Knapp KG",
    "wof:placetype":"venue"
},
  "geometry": {"coordinates":[15.5634403229,46.8063735962],"type":"Point"}
}