{
  "type": "Feature",
  "properties": {
    "iso:country":"AT",
    "sg:address":"Hauptstr 418",
    "sg:city":"Mayrhofen",
    "sg:orig_category":"Bankomat-Standorte",
    "sg:phone":"+43 5 07007400",
    "sg:postcode":"6290",
    "sg:province":"Tirol",
    "wof:name":"Bankomat d Hypo Tirol Bank AG",
    "wof:placetype":"venue"
},
  "geometry": {"coordinates":[11.8629388809,47.1673812866],"type":"Point"}
}