{
  "type": "Feature",
  "properties": {
    "iso:country":"AT",
    "sg:address":"Raffelspergerg 54",
    "sg:city":"Wien",
    "sg:orig_category":"Anlagenbau U -Technik",
    "sg:phone":"+43 4314 790208",
    "sg:postcode":"1190",
    "sg:province":"Wien",
    "wof:name":"Befa HandelsgesmbH",
    "wof:placetype":"venue"
},
  "geometry": {"coordinates":[16.31366539,48.2456665039],"type":"Point"}
}