{
  "type": "Feature",
  "properties": {
    "iso:country":"AT",
    "sg:address":"Hauptstr 32",
    "sg:city":"Sattledt",
    "sg:orig_category":"Holzbearbeitungsmaschinen U -Werkzeuge",
    "sg:phone":"+43 4372 448931",
    "sg:postcode":"4642",
    "sg:province":"Ober\u00f6sterreich",
    "wof:name":"Kaiser Rudolf Ing GesmbH",
    "wof:placetype":"venue"
},
  "geometry": {"coordinates":[14.0588197708,48.0731086731],"type":"Point"}
}