{
  "type": "Feature",
  "properties": {
    "addr:full":"Henckellg 12 Wien Wien 1140",
    "addr:housenumber":"12",
    "addr:postcode":"1140",
    "addr:street":"Henckellg",
    "iso:country":"AT",
    "sg:address":"Henckellg 12",
    "sg:city":"Wien",
    "sg:orig_category":"Unternehmensberatung",
    "sg:phone":"+43 1 9141246",
    "sg:postcode":"1140",
    "sg:province":"Wien",
    "wof:name":"Bartolitius Alfred",
    "wof:placetype":"venue"
},
  "geometry": {"coordinates":[16.259393692,48.2058105469],"type":"Point"}
}