{
  "type": "Feature",
  "properties": {
    "addr:full":"Pamesserg 6 Langenzersdorf Nieder\u00f6sterreich 2103",
    "addr:housenumber":"6",
    "addr:postcode":"2103",
    "addr:street":"Pamesserg",
    "iso:country":"AT",
    "sg:address":"Pamesserg 6",
    "sg:city":"Langenzersdorf",
    "sg:orig_category":"Heurigen / Buschenschank",
    "sg:phone":"+43 2244 2788",
    "sg:postcode":"2103",
    "sg:province":"Nieder\u00f6sterreich",
    "wof:name":"Terrassenheuriger Trimmel",
    "wof:placetype":"venue"
},
  "geometry": {"coordinates":[16.3562679291,48.3149299622],"type":"Point"}
}