{
  "type": "Feature",
  "properties": {
    "addr:full":"Villacher Str 53 Spittal an der Drau K\u00e4rnten 9800",
    "addr:housenumber":"53",
    "addr:postcode":"9800",
    "addr:street":"Str;Kaernten",
    "iso:country":"AT",
    "sg:address":"Villacher Str 53",
    "sg:city":"Spittal an der Drau",
    "sg:orig_category":"Diskotheken",
    "sg:phone":"+43 4347 6235487",
    "sg:postcode":"9800",
    "sg:province":"K\u00e4rnten",
    "wof:name":"Tollhaus",
    "wof:placetype":"venue"
},
  "geometry": {"coordinates":[13.5091810226,46.7920646667],"type":"Point"}
}