{
  "type": "Feature",
  "properties": {
    "addr:full":"Rudolfskai 28 Salzburg Salzburg 5020",
    "addr:housenumber":"28",
    "addr:postcode":"5020",
    "addr:street":"Rudolfskai;Salzburg",
    "iso:country":"AT",
    "sg:address":"Rudolfskai 28",
    "sg:city":"Salzburg",
    "sg:classifiers":[
        {
            "category":"Restaurant",
            "type":"Food & Drink"
        }
    ],
    "sg:phone":"+43 662 843091",
    "sg:postcode":"5020",
    "sg:province":"Salzburg",
    "wof:name":"Restaurant Koala",
    "wof:placetype":"venue"
},
  "geometry": {"coordinates":[13.0475120544,47.7996025085],"type":"Point"}
}