{
  "type": "Feature",
  "properties": {
    "addr:full":"Winzendorf 158 P\u00f6llau Steiermark 8225",
    "addr:housenumber":"158",
    "addr:postcode":"8225",
    "addr:street":"Winzendorf",
    "iso:country":"AT",
    "sg:address":"Winzendorf 158",
    "sg:city":"P\u00f6llau",
    "sg:orig_category":"Autohandel",
    "sg:phone":"+43 4366 45400626",
    "sg:postcode":"8225",
    "sg:province":"Steiermark",
    "wof:name":"Fahrzeugb\u00f6rse privat-privat",
    "wof:placetype":"venue"
},
  "geometry": {"coordinates":[15.8337945938,47.301990509],"type":"Point"}
}