{
  "type": "Feature",
  "properties": {
    "addr:full":"Holzstr 8 Linz Ober\u00f6sterreich 4020",
    "addr:housenumber":"8",
    "addr:postcode":"4020",
    "addr:street":"Holzstr",
    "iso:country":"AT",
    "sg:address":"Holzstr 8",
    "sg:city":"Linz",
    "sg:classifiers":[
        {
            "category":"Restaurant",
            "type":"Food & Drink"
        }
    ],
    "sg:phone":"+43 732 770193",
    "sg:postcode":"4020",
    "sg:province":"Ober\u00f6sterreich",
    "wof:name":"Restaurant Vogelk\u00e4fig",
    "wof:placetype":"venue"
},
  "geometry": {"coordinates":[14.3014993668,48.3126831055],"type":"Point"}
}