{
  "type": "Feature",
  "properties": {
    "iso:country":"AT",
    "sg:address":"Gymnasiumstr 38",
    "sg:city":"Wien",
    "sg:orig_category":"Fotoausarbeitungen",
    "sg:phone":"+43 1 4795494",
    "sg:postcode":"1180",
    "sg:province":"Wien",
    "wof:name":"Nikolaus Helga",
    "wof:placetype":"venue"
},
  "geometry": {"coordinates":[16.345533371,48.2305183411],"type":"Point"}
}