{
  "type": "Feature",
  "properties": {
    "iso:country":"AT",
    "sg:address":"Kirchstr 24",
    "sg:city":"Lustenau",
    "sg:orig_category":"Markisen",
    "sg:phone":"+43 5577 89677",
    "sg:postcode":"6890",
    "sg:province":"Vorarlberg",
    "wof:name":"Granig Gerhard S & W Montagen",
    "wof:placetype":"venue"
},
  "geometry": {"coordinates":[9.6526842117,47.4268875122],"type":"Point"}
}