{
  "type": "Feature",
  "properties": {
    "addr:full":"Mollardg 65 Wien Wien 1060",
    "addr:housenumber":"65",
    "addr:postcode":"1060",
    "addr:street":"Mollardg",
    "iso:country":"AT",
    "sg:address":"Mollardg 65",
    "sg:city":"Wien",
    "sg:orig_category":"Gastronomie- U Hotelbedarf",
    "sg:phone":"+43 1 5972558",
    "sg:postcode":"1060",
    "sg:province":"Wien",
    "wof:name":"Buchdruckerei Taborsky Heinrich KG",
    "wof:placetype":"venue"
},
  "geometry": {"coordinates":[16.3504657745,48.1947135925],"type":"Point"}
}