{
  "type": "Feature",
  "properties": {
    "addr:full":"Znaimer Str 12 Retz Nieder\u00f6sterreich 2070",
    "addr:postcode":"2070",
    "addr:street":"Str 12",
    "iso:country":"AT",
    "sg:address":"Znaimer Str 12",
    "sg:city":"Retz",
    "sg:orig_category":"Tabaktrafiken",
    "sg:phone":"+43 2942 2293",
    "sg:postcode":"2070",
    "sg:province":"Nieder\u00f6sterreich",
    "wof:name":"Egerer Alexa",
    "wof:placetype":"venue"
},
  "geometry": {"coordinates":[15.9521284103,48.7584152222],"type":"Point"}
}