{
  "type": "Feature",
  "properties": {
    "addr:full":"Hauptpl 43 Passail Steiermark 8162",
    "addr:housenumber":"43",
    "addr:postcode":"8162",
    "addr:street":"Hauptpl",
    "iso:country":"AT",
    "sg:address":"Hauptpl 43",
    "sg:city":"Passail",
    "sg:orig_category":"Banken U Sparkassen",
    "sg:phone":"+43 3179 236200",
    "sg:postcode":"8162",
    "sg:province":"Steiermark",
    "wof:name":"Steierm\u00e4rkische Bank und Sparkassen AG",
    "wof:placetype":"venue"
},
  "geometry": {"coordinates":[15.5150938034,47.2814102173],"type":"Point"}
}