{
  "type": "Feature",
  "properties": {
    "iso:country":"AT",
    "sg:address":"K\u00e4rntner Str 82",
    "sg:city":"Leoben",
    "sg:orig_category":"Blumeneinzelhandel",
    "sg:phone":"+43 3842 46991",
    "sg:postcode":"8700",
    "sg:province":"Steiermark",
    "wof:name":"Blumen Glauninger",
    "wof:placetype":"venue"
},
  "geometry": {"coordinates":[15.1100149155,47.3824691772],"type":"Point"}
}