{
  "type": "Feature",
  "properties": {
    "iso:country":"AT",
    "sg:address":"Grabnerg 4-6",
    "sg:city":"Wien",
    "sg:orig_category":"Wasserwerke",
    "sg:phone":"+43 1 599590",
    "sg:postcode":"1060",
    "sg:province":"Wien",
    "wof:name":"Wasserwerk d Stadt Wien",
    "wof:placetype":"venue"
},
  "geometry": {"coordinates":[16.3504066467,48.1909408569],"type":"Point"}
}