{
  "type": "Feature",
  "properties": {
    "addr:full":"Nr 57 W\u00f6rth an der Lafnitz Steiermark 8293",
    "addr:postcode":"8293",
    "addr:street":"Nr;An Der Lafnitz Steiermark",
    "iso:country":"AT",
    "sg:address":"Nr 57",
    "sg:city":"W\u00f6rth an der Lafnitz",
    "sg:classifiers":[
        {
            "category":"Taxi",
            "type":"Transportation"
        }
    ],
    "sg:phone":"+43 4333 3264363",
    "sg:postcode":"8293",
    "sg:province":"Steiermark",
    "sg:tags":[
        "personentransporte",
        "u"
    ],
    "wof:name":"Schlemmer Eva",
    "wof:placetype":"venue"
},
  "geometry": {"coordinates":[16.0995140076,47.225025177],"type":"Point"}
}