{
  "type": "Feature",
  "properties": {
    "iso:country":"AT",
    "sg:address":"Schneebergstr 10",
    "sg:city":"Gr\u00fcnbach am Schneeberg",
    "sg:orig_category":"Lebensmittel / Einzelhandel",
    "sg:phone":"+43 2637 2366",
    "sg:postcode":"2733",
    "sg:province":"Nieder\u00f6sterreich",
    "wof:name":"Spar-Markt Werdnik Karl",
    "wof:placetype":"venue"
},
  "geometry": {"coordinates":[9.2478504181,49.6403236389],"type":"Point"}
}