{
  "type": "Feature",
  "properties": {
    "addr:full":"Hauptstr 67 Auersthal Nieder\u00f6sterreich 2214",
    "addr:housenumber":"67",
    "addr:postcode":"2214",
    "addr:street":"Hauptstr",
    "iso:country":"AT",
    "sg:address":"Hauptstr 67",
    "sg:city":"Auersthal",
    "sg:orig_category":"Banken U Sparkassen",
    "sg:phone":"+43 4322 8820082",
    "sg:postcode":"2214",
    "sg:province":"Nieder\u00f6sterreich",
    "wof:name":"Weinviertler Volksbank regGenmbH",
    "wof:placetype":"venue"
},
  "geometry": {"coordinates":[16.6355552673,48.3742332458],"type":"Point"}
}