{
  "type": "Feature",
  "properties": {
    "addr:full":"Luegerstr 6 Klagenfurt K\u00e4rnten 9020",
    "addr:housenumber":"6",
    "addr:postcode":"9020",
    "addr:street":"Luegerstr;Kaernten",
    "iso:country":"AT",
    "sg:address":"Luegerstr 6",
    "sg:city":"Klagenfurt",
    "sg:orig_category":"Textilreinigung",
    "sg:phone":"+43 463 22130",
    "sg:postcode":"9020",
    "sg:province":"K\u00e4rnten",
    "wof:name":"Fagitsch-Textilreinigung KG",
    "wof:placetype":"venue"
},
  "geometry": {"coordinates":[14.2835359573,46.6197547913],"type":"Point"}
}