{
  "type": "Feature",
  "properties": {
    "addr:full":"Bundesstr. 2a  Rum Tirol 6063",
    "addr:housenumber":"2a",
    "addr:postcode":"6063",
    "addr:street":"Bundesstr.;Tirol",
    "iso:country":"AT",
    "sg:address":"Bundesstr. 2a ",
    "sg:city":"Rum",
    "sg:classifiers":[
        {
            "category":"Professional",
            "subcategory":"Advertising",
            "type":"Services"
        }
    ],
    "sg:phone":"+43 4351 2248050",
    "sg:postcode":"6063",
    "sg:province":"Tirol",
    "sg:tags":[
        "communication",
        "medium"
    ],
    "wof:name":"SITOUR PRODUKTIONS- & WERBE GES. MBH",
    "wof:placetype":"venue"
},
  "geometry": {"coordinates":[11.4500389099,47.2780265808],"type":"Point"}
}