{
  "type": "Feature",
  "properties": {
    "addr:full":"Salzstrasse 6 Zirl Tirol 6170",
    "addr:housenumber":"6",
    "addr:postcode":"6170",
    "addr:street":"Salzstrasse;Tirol",
    "iso:country":"AT",
    "sg:address":"Salzstrasse 6",
    "sg:city":"Zirl",
    "sg:classifiers":[
        {
            "category":"Community Center",
            "subcategory":"Ethnic",
            "type":"Public Place"
        }
    ],
    "sg:phone":"+43 5238 528000",
    "sg:postcode":"6170",
    "sg:province":"Tirol",
    "sg:tags":[
        "paste",
        "cleaning",
        "hand"
    ],
    "sg:website":"hollu.com",
    "wof:name":"Julius Holluschek Ges.m.b.H.",
    "wof:placetype":"venue"
},
  "geometry": {"coordinates":[11.2278232574,47.2635879517],"type":"Point"}
}