{
  "type": "Feature",
  "properties": {
    "iso:country":"AT",
    "sg:address":"Ing.-Josef-Heckl-Str 5",
    "sg:city":"Stockerau",
    "sg:orig_category":"Glasereien",
    "sg:phone":"+43 2266 61759",
    "sg:postcode":"2000",
    "sg:province":"Nieder\u00f6sterreich",
    "wof:name":"Schober Johannes GesmbH",
    "wof:placetype":"venue"
},
  "geometry": {"coordinates":[16.1883506775,48.3884963989],"type":"Point"}
}