{
  "type": "Feature",
  "properties": {
    "iso:country":"AT",
    "sg:address":"Wengerstr 4",
    "sg:city":"Grieskirchen",
    "sg:orig_category":"Autohandel",
    "sg:phone":"+43 7248 680890",
    "sg:postcode":"4710",
    "sg:province":"Ober\u00f6sterreich",
    "wof:name":"Lang G\u00fcnther GmbH",
    "wof:placetype":"venue"
},
  "geometry": {"coordinates":[13.825097084,48.231918335],"type":"Point"}
}