{
  "type": "Feature",
  "properties": {
    "addr:full":"Wenedikterstr 5 Villach K\u00e4rnten 9500",
    "addr:housenumber":"5",
    "addr:postcode":"9500",
    "addr:street":"Wenedikterstr;Kaernten",
    "iso:country":"AT",
    "sg:address":"Wenedikterstr 5",
    "sg:city":"Villach",
    "sg:orig_category":"Musikgruppen",
    "sg:phone":"+43 4242 287955",
    "sg:postcode":"9500",
    "sg:province":"K\u00e4rnten",
    "wof:name":"Schwarzkogelecho",
    "wof:placetype":"venue"
},
  "geometry": {"coordinates":[13.8433599472,46.6215782166],"type":"Point"}
}