{
  "type": "Feature",
  "properties": {
    "addr:full":"Forchheimergasse 32 Wien Wien 1230",
    "addr:housenumber":"32",
    "addr:postcode":"1230",
    "addr:street":"Forchheimergasse",
    "iso:country":"AT",
    "sg:address":"Forchheimergasse 32",
    "sg:city":"Wien",
    "sg:classifiers":[
        {
            "category":"Utilities",
            "subcategory":"Cable",
            "type":"Services"
        }
    ],
    "sg:phone":"+43 1 86943010",
    "sg:postcode":"1230",
    "sg:province":"Wien",
    "sg:tags":[
        "transmission",
        "bus",
        "automatic",
        "vehicle"
    ],
    "sg:website":"kwdrive.at",
    "wof:name":"K & W Drive Systems Knopf und Wallisch Getriebe und Motoren Vertriebs-Ges.m.b.H.",
    "wof:placetype":"venue"
},
  "geometry": {"coordinates":[16.3059024811,48.1384963989],"type":"Point"}
}