{
  "type": "Feature",
  "properties": {
    "addr:full":"Sikorastr 12 Hallein Salzburg 5400",
    "addr:housenumber":"12",
    "addr:postcode":"5400",
    "addr:street":"Sikorastr;Salzburg",
    "iso:country":"AT",
    "sg:address":"Sikorastr 12",
    "sg:city":"Hallein",
    "sg:orig_category":"Stiegen U Treppen",
    "sg:phone":"+43 4366 49256806",
    "sg:postcode":"5400",
    "sg:province":"Salzburg",
    "wof:name":"dress-treppenrenovierung-austria Riedel Roland",
    "wof:placetype":"venue"
},
  "geometry": {"coordinates":[13.0916795731,47.6940116882],"type":"Point"}
}