{
  "type": "Feature",
  "properties": {
    "addr:full":"Am Winterhafen 1 Linz Ober\u00f6sterreich 4020",
    "addr:housenumber":"1",
    "addr:postcode":"4020",
    "addr:street":"Am Winterhafen",
    "iso:country":"AT",
    "sg:address":"Am Winterhafen 1",
    "sg:city":"Linz",
    "sg:orig_category":"Telekommunikation",
    "sg:phone":"+43 732 779500",
    "sg:postcode":"4020",
    "sg:province":"Ober\u00f6sterreich",
    "wof:name":"Ericsson Service Center",
    "wof:placetype":"venue"
},
  "geometry": {"coordinates":[14.3047246933,48.3180580139],"type":"Point"}
}