{
  "type": "Feature",
  "properties": {
    "addr:full":"Grazer Str 66A Langenwang Steiermark 8665",
    "addr:housenumber":"66a",
    "addr:postcode":"8665",
    "addr:street":"Str",
    "iso:country":"AT",
    "sg:address":"Grazer Str 66A",
    "sg:city":"Langenwang",
    "sg:orig_category":"Stuckateure U Trockenausbauer",
    "sg:phone":"+43 4338 542822",
    "sg:postcode":"8665",
    "sg:province":"Steiermark",
    "wof:name":"Fiedler Hugo",
    "wof:placetype":"venue"
},
  "geometry": {"coordinates":[15.6137065887,47.5634231567],"type":"Point"}
}