{
  "type": "Feature",
  "properties": {
    "addr:full":"Wiedenbergweg 270 Passail Steiermark 8162",
    "addr:housenumber":"270",
    "addr:postcode":"8162",
    "addr:street":"Wiedenbergweg",
    "iso:country":"AT",
    "sg:address":"Wiedenbergweg 270",
    "sg:city":"Passail",
    "sg:orig_category":"Bars-Cafes",
    "sg:phone":"+43 664 1050712",
    "sg:postcode":"8162",
    "sg:province":"Steiermark",
    "wof:name":"Cafe Anneliese",
    "wof:placetype":"venue"
},
  "geometry": {"coordinates":[15.5150938034,47.2814102173],"type":"Point"}
}