{
  "type": "Feature",
  "properties": {
    "iso:country":"AT",
    "sg:address":"Salzburger Str 6",
    "sg:city":"St. Johann im Pongau",
    "sg:orig_category":"Installationsunternehmen",
    "sg:phone":"+43 4364 126147",
    "sg:postcode":"5600",
    "sg:province":"Salzburg",
    "wof:name":"Pr\u00e4auer Peter Installation u Fliesen GmbH",
    "wof:placetype":"venue"
},
  "geometry": {"coordinates":[13.2056646347,47.3547019958],"type":"Point"}
}