{
  "type": "Feature",
  "properties": {
    "addr:full":"M\u00fchlg 4 Weiz Steiermark 8160",
    "addr:housenumber":"4",
    "addr:postcode":"8160",
    "addr:street":"Muehlg",
    "iso:country":"AT",
    "sg:address":"M\u00fchlg 4",
    "sg:city":"Weiz",
    "sg:classifiers":[
        {
            "category":"Restaurant",
            "type":"Food & Drink"
        }
    ],
    "sg:phone":"+43 3172 44910",
    "sg:postcode":"8160",
    "sg:province":"Steiermark",
    "sg:tags":[
        "pizzeria"
    ],
    "wof:name":"Pizzeria Little Italy",
    "wof:placetype":"venue"
},
  "geometry": {"coordinates":[15.6215696335,47.2169532776],"type":"Point"}
}