{
  "type": "Feature",
  "properties": {
    "addr:full":"Steinfeldg. 46  Guntramsdorf Nieder\u00f6sterreich 2353",
    "addr:housenumber":"46",
    "addr:postcode":"2353",
    "addr:street":"Steinfeldg.",
    "iso:country":"AT",
    "sg:address":"Steinfeldg. 46 ",
    "sg:city":"Guntramsdorf",
    "sg:classifiers":[
        {
            "category":"Farming",
            "subcategory":"Livestock Farm",
            "type":"Manufacturing & Wholesale Goods"
        }
    ],
    "sg:phone":"+43 4322 36535550",
    "sg:postcode":"2353",
    "sg:province":"Nieder\u00f6sterreich",
    "sg:tags":[
        "agriculture"
    ],
    "wof:name":"ASSMANNM\u00dcHLEN GESMBH",
    "wof:placetype":"venue"
},
  "geometry": {"coordinates":[16.3137645721,48.0435905457],"type":"Point"}
}