{
  "type": "Feature",
  "properties": {
    "addr:full":"Wilhelm-Jentsch-Strasse 2 Peggau Steiermark 8120",
    "addr:housenumber":"2",
    "addr:postcode":"8120",
    "addr:street":"Wilhelm-Jentsch-Strasse",
    "iso:country":"AT",
    "sg:address":"Wilhelm-Jentsch-Strasse 2",
    "sg:city":"Peggau",
    "sg:orig_category":"Bar Lead-Ins For Transformers",
    "sg:phone":"+43 3127 209400",
    "sg:postcode":"8120",
    "sg:province":"Steiermark",
    "sg:website":"gipro.at",
    "wof:name":"GIPRO Gie\u00dfharz - Industrieprodukte Gesellschaft m.b.H.",
    "wof:placetype":"venue"
},
  "geometry": {"coordinates":[15.3418970108,47.2034454346],"type":"Point"}
}