{
  "type": "Feature",
  "properties": {
    "addr:full":"Volksfeststr 1 Linz Ober\u00f6sterreich 4020",
    "addr:housenumber":"1",
    "addr:postcode":"4020",
    "addr:street":"Volksfeststr",
    "iso:country":"AT",
    "sg:address":"Volksfeststr 1",
    "sg:city":"Linz",
    "sg:orig_category":"Apotheken",
    "sg:phone":"+43 732 779259",
    "sg:postcode":"4020",
    "sg:province":"Ober\u00f6sterreich",
    "wof:name":"Hessenplatz-Apotheke Mag pharm Margit M\u00fcller",
    "wof:placetype":"venue"
},
  "geometry": {"coordinates":[14.2950210571,48.3013954163],"type":"Point"}
}