{
  "type": "Feature",
  "properties": {
    "addr:full":"Bahnhofstr 88 Admont Steiermark 8911",
    "addr:housenumber":"88",
    "addr:postcode":"8911",
    "addr:street":"Bahnhofstr",
    "iso:country":"AT",
    "sg:address":"Bahnhofstr 88",
    "sg:city":"Admont",
    "sg:orig_category":"Steinmetzbetriebe",
    "sg:phone":"+43 4336 132370",
    "sg:postcode":"8911",
    "sg:province":"Steiermark",
    "wof:name":"Kaltenb\u00f6ck Anton GesmbH",
    "wof:placetype":"venue"
},
  "geometry": {"coordinates":[14.4628324509,47.5731048584],"type":"Point"}
}