{
  "type": "Feature",
  "properties": {
    "addr:full":"Stifterstr 29 Linz Ober\u00f6sterreich 4020",
    "addr:housenumber":"29",
    "addr:postcode":"4020",
    "addr:street":"Stifterstr",
    "iso:country":"AT",
    "sg:address":"Stifterstr 29",
    "sg:city":"Linz",
    "sg:orig_category":"Zahntechnische Laboratorien",
    "sg:phone":"+43 732 794242",
    "sg:postcode":"4020",
    "sg:province":"Ober\u00f6sterreich",
    "wof:name":"M & W Zahntechnik GmbH - Kieferorthop\u00e4discher Fachbetrieb",
    "wof:placetype":"venue"
},
  "geometry": {"coordinates":[14.2833299637,48.2991142273],"type":"Point"}
}