{
  "type": "Feature",
  "properties": {
    "addr:full":"Inding 15 Taufkirchen an der Pram Ober\u00f6sterreich 4775",
    "addr:housenumber":"15",
    "addr:postcode":"4775",
    "addr:street":"Inding",
    "iso:country":"AT",
    "sg:address":"Inding 15",
    "sg:city":"Taufkirchen an der Pram",
    "sg:classifiers":[
        {
            "category":"Conference Center",
            "type":"Public Place"
        }
    ],
    "sg:phone":"+43 7719 8263",
    "sg:postcode":"4775",
    "sg:province":"Ober\u00f6sterreich",
    "sg:tags":[
        "lumber",
        "list",
        "customized",
        "timber"
    ],
    "wof:name":"Anton Mairleithner",
    "wof:placetype":"venue"
},
  "geometry": {"coordinates":[13.5362701416,48.4104499817],"type":"Point"}
}