{
  "type": "Feature",
  "properties": {
    "addr:full":"Sporg 32 Graz Steiermark 8010",
    "addr:housenumber":"32",
    "addr:postcode":"8010",
    "addr:street":"Sporg",
    "iso:country":"AT",
    "sg:address":"Sporg 32",
    "sg:city":"Graz",
    "sg:orig_category":"Waren Aller Art",
    "sg:phone":"+43 316 817691",
    "sg:postcode":"8010",
    "sg:province":"Steiermark",
    "wof:name":"Grossauer & Strausz OEG",
    "wof:placetype":"venue"
},
  "geometry": {"coordinates":[15.4397115707,47.0730819702],"type":"Point"}
}