{
  "type": "Feature",
  "properties": {
    "addr:full":"Winklerstr 26 Kapfenberg Steiermark 8605",
    "addr:housenumber":"26",
    "addr:postcode":"8605",
    "addr:street":"Winklerstr",
    "iso:country":"AT",
    "sg:address":"Winklerstr 26",
    "sg:city":"Kapfenberg",
    "sg:orig_category":"Technische Gase",
    "sg:phone":"+43 5 042734",
    "sg:postcode":"8605",
    "sg:province":"Steiermark",
    "wof:name":"LINDE GAS GmbH",
    "wof:placetype":"venue"
},
  "geometry": {"coordinates":[15.2696399689,47.4486999512],"type":"Point"}
}