{
  "type": "Feature",
  "properties": {
    "addr:full":"Fischerstiege 10/16 Wien Wien 1010",
    "addr:housenumber":"10 / 16",
    "addr:postcode":"1010",
    "addr:street":"Fischerstiege",
    "iso:country":"AT",
    "sg:address":"Fischerstiege 10/16",
    "sg:city":"Wien",
    "sg:orig_category":"Weiterbildungsinstitute M Allg U Berufl Bildungsangebot",
    "sg:phone":"+43 4315 332390",
    "sg:postcode":"1010",
    "sg:province":"Wien",
    "wof:name":"Open University Business School in Austria",
    "wof:placetype":"venue"
},
  "geometry": {"coordinates":[16.3721923828,48.2129554749],"type":"Point"}
}