{
  "type": "Feature",
  "properties": {
    "addr:full":"Wiedner Hauptstr 74 Wien Wien 1040",
    "addr:housenumber":"74",
    "addr:postcode":"1040",
    "addr:street":"Hauptstr",
    "iso:country":"AT",
    "sg:address":"Wiedner Hauptstr 74",
    "sg:city":"Wien",
    "sg:orig_category":"Banken U Sparkassen",
    "sg:phone":"+43 1 58756550",
    "sg:postcode":"1040",
    "sg:province":"Wien",
    "wof:name":"PSK - Point",
    "wof:placetype":"venue"
},
  "geometry": {"coordinates":[16.365322113,48.1894989014],"type":"Point"}
}