{
  "type": "Feature",
  "properties": {
    "addr:full":"Werk-VI-Str 27 Kapfenberg Steiermark 8605",
    "addr:housenumber":"27",
    "addr:postcode":"8605",
    "addr:street":"Werk-Vi-Str",
    "iso:country":"AT",
    "sg:address":"Werk-VI-Str 27",
    "sg:city":"Kapfenberg",
    "sg:orig_category":"Automaten",
    "sg:phone":"+43 4366 43030405",
    "sg:postcode":"8605",
    "sg:province":"Steiermark",
    "wof:name":"hgaplus Rudolf P\u00f6llabauer GmbH",
    "wof:placetype":"venue"
},
  "geometry": {"coordinates":[15.3163309097,47.4504203796],"type":"Point"}
}