{
  "type": "Feature",
  "properties": {
    "addr:full":"Kaiserstr 30 St. Johann in Tirol Tirol 6380",
    "addr:housenumber":"30",
    "addr:postcode":"6380",
    "addr:street":"Kaiserstr;Tirol",
    "iso:country":"AT",
    "sg:address":"Kaiserstr 30",
    "sg:city":"St. Johann in Tirol",
    "sg:orig_category":"Friseure U Frisiersalons",
    "sg:phone":"+43 4353 5262355",
    "sg:postcode":"6380",
    "sg:province":"Tirol",
    "wof:name":"Eberl Franz Josef Friseursalon",
    "wof:placetype":"venue"
},
  "geometry": {"coordinates":[12.4231281281,47.5230560303],"type":"Point"}
}