{
  "type": "Feature",
  "properties": {
    "iso:country":"AT",
    "sg:address":"Wiesenweg 2",
    "sg:city":"Latschach ober dem Faaker See",
    "sg:orig_category":"Pensionen / Privatzimmer",
    "sg:phone":"+43 4254 2709",
    "sg:postcode":"9582",
    "sg:province":"K\u00e4rnten",
    "wof:name":"Sportpension Aichholzer",
    "wof:placetype":"venue"
},
  "geometry": {"coordinates":[13.925901413,46.5608177185],"type":"Point"}
}