{
  "type": "Feature",
  "properties": {
    "addr:full":"Zinckg 6 Wien Wien 1150",
    "addr:housenumber":"6",
    "addr:postcode":"1150",
    "addr:street":"Zinckg",
    "iso:country":"AT",
    "sg:address":"Zinckg 6",
    "sg:city":"Wien",
    "sg:orig_category":"Bauunternehmen",
    "sg:phone":"+43 1 7897007",
    "sg:postcode":"1150",
    "sg:province":"Wien",
    "wof:name":"Feldgrill Bau GmbH",
    "wof:placetype":"venue"
},
  "geometry": {"coordinates":[16.3355617523,48.198223114],"type":"Point"}
}