{
  "type": "Feature",
  "properties": {
    "addr:full":"Lindenallee 12a Knittelfeld Steiermark 8720",
    "addr:housenumber":"12a",
    "addr:postcode":"8720",
    "addr:street":"Lindenallee",
    "iso:country":"AT",
    "sg:address":"Lindenallee 12a",
    "sg:city":"Knittelfeld",
    "sg:orig_category":"Hunde- U Katzensalons",
    "sg:phone":"+43 4366 49771262",
    "sg:postcode":"8720",
    "sg:province":"Steiermark",
    "wof:name":"Wuffis Hundestudio - Bianca Seidl",
    "wof:placetype":"venue"
},
  "geometry": {"coordinates":[14.8155088425,47.2144737244],"type":"Point"}
}