{
  "type": "Feature",
  "properties": {
    "addr:full":"Dr.-Robert-Braun-Str 11 Brunn an der Wild Nieder\u00f6sterreich 3595",
    "addr:housenumber":"11",
    "addr:postcode":"3595",
    "addr:street":"Dr.-Robert-Braun-Str",
    "iso:country":"AT",
    "sg:address":"Dr.-Robert-Braun-Str 11",
    "sg:city":"Brunn an der Wild",
    "sg:orig_category":"Rauchfangkehrer",
    "sg:phone":"+43 2989 2268",
    "sg:postcode":"3595",
    "sg:province":"Nieder\u00f6sterreich",
    "wof:name":"Bauer Franz",
    "wof:placetype":"venue"
},
  "geometry": {"coordinates":[15.5167388916,48.6928787231],"type":"Point"}
}