{
  "type": "Feature",
  "properties": {
    "addr:full":"Pilgramg 1 Wien Wien 1050",
    "addr:housenumber":"1",
    "addr:postcode":"1050",
    "addr:street":"Pilgramg",
    "iso:country":"AT",
    "sg:address":"Pilgramg 1",
    "sg:city":"Wien",
    "sg:orig_category":"Architekten",
    "sg:phone":"+43 664 1505555",
    "sg:postcode":"1050",
    "sg:province":"Wien",
    "wof:name":"Wanek Hans Arch Mag",
    "wof:placetype":"venue"
},
  "geometry": {"coordinates":[16.3576202393,48.1915245056],"type":"Point"}
}