{
  "type": "Feature",
  "properties": {
    "iso:country":"AT",
    "sg:address":"Weidfeldstr 177",
    "sg:city":"Traun",
    "sg:orig_category":"Handelsagenturen",
    "sg:phone":"+43 7229 74238",
    "sg:postcode":"4050",
    "sg:province":"Ober\u00f6sterreich",
    "wof:name":"Schmoll Richard",
    "wof:placetype":"venue"
},
  "geometry": {"coordinates":[14.24330616,48.2295227051],"type":"Point"}
}