{
  "type": "Feature",
  "properties": {
    "addr:full":"Ludwig-Angerer-G 12 Mondsee Ober\u00f6sterreich 5310",
    "addr:housenumber":"12",
    "addr:postcode":"5310",
    "addr:street":"Ludwig-Angerer-G;Oberoesterreich",
    "iso:country":"AT",
    "sg:address":"Ludwig-Angerer-G 12",
    "sg:city":"Mondsee",
    "sg:orig_category":"Immobilienmakler",
    "sg:phone":"+43 6232 63600",
    "sg:postcode":"5310",
    "sg:province":"Ober\u00f6sterreich",
    "wof:name":"SELINA Immobilien Hausverwaltung Wohnbau GesmbH",
    "wof:placetype":"venue"
},
  "geometry": {"coordinates":[13.3446588516,47.854057312],"type":"Point"}
}