{
  "type": "Feature",
  "properties": {
    "iso:country":"AT",
    "sg:address":"Nr 44",
    "sg:city":"Gaishorn am See",
    "sg:orig_category":"Betonerzeugnisse",
    "sg:phone":"+43 4336 172406",
    "sg:postcode":"8783",
    "sg:province":"Steiermark",
    "wof:name":"Stallit GesmbH & Co KG",
    "wof:placetype":"venue"
},
  "geometry": {"coordinates":[14.5492944717,47.4914245605],"type":"Point"}
}