{
  "type": "Feature",
  "properties": {
    "addr:full":"Nr 46a St. Peter am Ottersbach Steiermark 8093",
    "addr:postcode":"8093",
    "addr:street":"Nr 46A",
    "iso:country":"AT",
    "sg:address":"Nr 46a",
    "sg:city":"St. Peter am Ottersbach",
    "sg:orig_category":"Massagen",
    "sg:phone":"+43 3477 29927",
    "sg:postcode":"8093",
    "sg:province":"Steiermark",
    "wof:name":"Bittermann Dieter",
    "wof:placetype":"venue"
},
  "geometry": {"coordinates":[15.7594327927,46.79920578],"type":"Point"}
}