{
  "type": "Feature",
  "properties": {
    "addr:full":"Fuxmageng 28 Hall in Tirol Tirol 6060",
    "addr:housenumber":"28",
    "addr:postcode":"6060",
    "addr:street":"Fuxmageng;Tirol",
    "iso:country":"AT",
    "sg:address":"Fuxmageng 28",
    "sg:city":"Hall in Tirol",
    "sg:orig_category":"Feinkost",
    "sg:phone":"+43 5223 42614",
    "sg:postcode":"6060",
    "sg:province":"Tirol",
    "wof:name":"Binder Andrea - Spezialit\u00e4ten aus d Toscana",
    "wof:placetype":"venue"
},
  "geometry": {"coordinates":[11.5064821243,47.2864189148],"type":"Point"}
}