{
  "type": "Feature",
  "properties": {
    "addr:full":"Nr 74-75 Pertisau Tirol 6213",
    "addr:postcode":"6213",
    "addr:street":"Nr;Pertisau",
    "iso:country":"AT",
    "sg:address":"Nr 74-75",
    "sg:city":"Pertisau",
    "sg:classifiers":[
        {
            "category":"Travel",
            "subcategory":"Hotels & Motels",
            "type":"Entertainment"
        }
    ],
    "sg:phone":"+43 5243 53660",
    "sg:postcode":"6213",
    "sg:province":"Tirol",
    "wof:name":"Hotel-Pension Einwaller",
    "wof:placetype":"venue"
},
  "geometry": {"coordinates":[11.6961479187,47.4396896362],"type":"Point"}
}