{
  "type": "Feature",
  "properties": {
    "addr:full":"Talgasse 4 Neunkirchen Nieder\u00f6sterreich 2620",
    "addr:housenumber":"4",
    "addr:postcode":"2620",
    "addr:street":"Talgasse",
    "iso:country":"AT",
    "sg:address":"Talgasse 4",
    "sg:city":"Neunkirchen",
    "sg:classifiers":[
        {
            "category":"Food & Beverages",
            "subcategory":"Meat & Fish",
            "type":"Retail Goods"
        }
    ],
    "sg:phone":"+43 2635 62430",
    "sg:postcode":"2620",
    "sg:province":"Nieder\u00f6sterreich",
    "sg:tags":[
        "sausage"
    ],
    "wof:name":"Feinste Wurst-, Fleisch- und Selchwaren Martin Osterbauer KG",
    "wof:placetype":"venue"
},
  "geometry": {"coordinates":[16.0788936615,47.7219467163],"type":"Point"}
}