{
  "type": "Feature",
  "properties": {
    "iso:country":"AT",
    "sg:address":"Fechterg 16/1",
    "sg:city":"Wien",
    "sg:orig_category":"Psychotherapie",
    "sg:phone":"+43 1 3151910",
    "sg:postcode":"1090",
    "sg:province":"Wien",
    "sg:website":"psyweb.at/boehmer-laufer",
    "wof:name":"B\u00f6hmer-Laufer Evelyn Mag",
    "wof:placetype":"venue"
},
  "geometry": {"coordinates":[16.3587112427,48.226146698],"type":"Point"}
}