{
  "type": "Feature",
  "properties": {
    "iso:country":"AT",
    "sg:address":"Uferstr. 42",
    "sg:city":"Oberndorf",
    "sg:classifiers":[
        {
            "category":"Shopping",
            "subcategory":"Computers & Home Electronics",
            "type":"Retail Goods"
        }
    ],
    "sg:phone":"+43 4362 725553",
    "sg:postcode":"5110",
    "sg:province":"Salzburg",
    "sg:tags":[
        "electronic",
        "electrical",
        "equipment"
    ],
    "wof:name":"FORSTNER ELECTRONICS GESMBH",
    "wof:placetype":"venue"
},
  "geometry": {"coordinates":[12.9399595261,47.9383010864],"type":"Point"}
}