{
  "type": "Feature",
  "properties": {
    "addr:full":"Puchheimer Strasse 5 Attnang-Puchheim Ober\u00f6sterreich 4800",
    "addr:housenumber":"5",
    "addr:postcode":"4800",
    "addr:street":"Puchheimer Strasse",
    "iso:country":"AT",
    "sg:address":"Puchheimer Strasse 5",
    "sg:city":"Attnang-Puchheim",
    "sg:classifiers":[
        {
            "category":"Home & Garden",
            "subcategory":"Furniture",
            "type":"Retail Goods"
        }
    ],
    "sg:phone":"+43 767464937",
    "sg:postcode":"4800",
    "sg:province":"Ober\u00f6sterreich",
    "sg:tags":[
        "designer"
    ],
    "wof:name":"Walter Hauser M\u00f6bel Design",
    "wof:placetype":"venue"
},
  "geometry": {"coordinates":[13.716750145,48.0072631836],"type":"Point"}
}