{
  "type": "Feature",
  "properties": {
    "addr:full":"Hauptstr 67 Ferschnitz Nieder\u00f6sterreich 3325",
    "addr:housenumber":"67",
    "addr:postcode":"3325",
    "addr:street":"Hauptstr;Niederoesterreich",
    "iso:country":"AT",
    "sg:address":"Hauptstr 67",
    "sg:city":"Ferschnitz",
    "sg:classifiers":[
        {
            "category":"Home & Garden",
            "subcategory":"Building Materials",
            "type":"Retail Goods"
        }
    ],
    "sg:phone":"+43 4374 738600",
    "sg:postcode":"3325",
    "sg:province":"Nieder\u00f6sterreich",
    "sg:tags":[
        "baustoffe",
        "-material",
        "u"
    ],
    "wof:name":"Roseneder Karl KEG",
    "wof:placetype":"venue"
},
  "geometry": {"coordinates":[14.9866275787,48.0950088501],"type":"Point"}
}