{
  "type": "Feature",
  "properties": {
    "addr:full":"Ignaz Glaser-Str 17 B\u00fcrmoos Salzburg 5111",
    "addr:housenumber":"17",
    "addr:postcode":"5111",
    "addr:street":"Ignaz Glaser-Str",
    "iso:country":"AT",
    "sg:address":"Ignaz Glaser-Str 17",
    "sg:city":"B\u00fcrmoos",
    "sg:orig_category":"Installationsunternehmen, Energietechnik",
    "sg:phone":"+43 6274 76675",
    "sg:postcode":"5111",
    "sg:province":"Salzburg",
    "wof:name":"Holzapfel Energietechnik & Installationen",
    "wof:placetype":"venue"
},
  "geometry": {"coordinates":[12.9248943329,47.983165741],"type":"Point"}
}