{
  "type": "Feature",
  "properties": {
    "addr:full":"Untermarktstr 2 Telfs Tirol 6410",
    "addr:housenumber":"2",
    "addr:postcode":"6410",
    "addr:street":"Untermarktstr;Tirol",
    "iso:country":"AT",
    "sg:address":"Untermarktstr 2",
    "sg:city":"Telfs",
    "sg:orig_category":"Bankomat-Standorte",
    "sg:phone":"+43 5262 69810",
    "sg:postcode":"6410",
    "sg:province":"Tirol",
    "wof:name":"Bankomat d Raiffeisen-Regionalbank Telfs regGenmbH",
    "wof:placetype":"venue"
},
  "geometry": {"coordinates":[11.0715703964,47.3064994812],"type":"Point"}
}