{
  "type": "Feature",
  "properties": {
    "iso:country":"AT",
    "sg:address":"Hauptstr 20",
    "sg:city":"Haugsdorf",
    "sg:orig_category":"Weine / Einzelhandel",
    "sg:phone":"+43 2944 2369",
    "sg:postcode":"2054",
    "sg:province":"Nieder\u00f6sterreich",
    "wof:name":"D\u00f6tzl-Strobl Elisabeth - Winzerhof",
    "wof:placetype":"venue"
},
  "geometry": {"coordinates":[16.0746326447,48.7075996399],"type":"Point"}
}