{
  "type": "Feature",
  "properties": {
    "iso:country":"AT",
    "sg:address":"Schie\u00dflgang 7",
    "sg:city":"Linz",
    "sg:orig_category":"Tabaktrafiken",
    "sg:phone":"+43 732 370263",
    "sg:postcode":"4030",
    "sg:province":"Ober\u00f6sterreich",
    "wof:name":"Sch\u00fctz Sonja",
    "wof:placetype":"venue"
},
  "geometry": {"coordinates":[14.286986351,48.2517814636],"type":"Point"}
}