{
  "type": "Feature",
  "properties": {
    "addr:full":"Reisnerstrasse 55 - 57 -  Wien Wien 1030",
    "addr:housenumber":"55 57",
    "addr:postcode":"1030",
    "addr:street":"Reisnerstrasse",
    "iso:country":"AT",
    "sg:address":"Reisnerstrasse 55 - 57 - ",
    "sg:city":"Wien",
    "sg:classifiers":[
        {
            "category":"Professional",
            "subcategory":"Art Services",
            "type":"Services"
        }
    ],
    "sg:phone":"+43 4317 156692",
    "sg:postcode":"1030",
    "sg:province":"Wien",
    "sg:tags":[
        "export-import"
    ],
    "sg:website":"http://www.norway.at",
    "wof:name":"Royal Norwegian Embassy",
    "wof:placetype":"venue"
},
  "geometry": {"coordinates":[16.3838920593,48.1964302063],"type":"Point"}
}