{
  "type": "Feature",
  "properties": {
    "addr:full":"Viktor-Adler-Pl 4 Wien Wien 1100",
    "addr:housenumber":"4",
    "addr:postcode":"1100",
    "addr:street":"Viktor-Adler-Pl",
    "iso:country":"AT",
    "sg:address":"Viktor-Adler-Pl 4",
    "sg:city":"Wien",
    "sg:orig_category":"Lebensmittel / Einzelhandel",
    "sg:phone":"+43 1 6042760",
    "sg:postcode":"1100",
    "sg:province":"Wien",
    "wof:name":"MONDO Lebensmitteldiskonter",
    "wof:placetype":"venue"
},
  "geometry": {"coordinates":[16.3758144379,48.1763458252],"type":"Point"}
}