{
  "type": "Feature",
  "properties": {
    "iso:country":"AT",
    "sg:address":"Jahnstr 7",
    "sg:city":"Korneuburg",
    "sg:orig_category":"Rettungsdienste",
    "sg:phone":"+43 2262 7770",
    "sg:postcode":"2100",
    "sg:province":"Nieder\u00f6sterreich",
    "wof:name":"Rotes Kreuz \u00f6sterr Bezirksstelle Korneuburg",
    "wof:placetype":"venue"
},
  "geometry": {"coordinates":[16.3354892731,48.3389205933],"type":"Point"}
}