{
  "type": "Feature",
  "properties": {
    "addr:full":"Peintnerstr 10 Leonding Ober\u00f6sterreich 4060",
    "addr:housenumber":"10",
    "addr:postcode":"4060",
    "addr:street":"Peintnerstr",
    "iso:country":"AT",
    "sg:address":"Peintnerstr 10",
    "sg:city":"Leonding",
    "sg:orig_category":"Fotografen",
    "sg:phone":"+43 732 330216",
    "sg:postcode":"4060",
    "sg:province":"Ober\u00f6sterreich",
    "sg:website":"www.fotowerkstatt-pilz.at",
    "wof:name":"Fotowerkstatt Manuela Pilz",
    "wof:placetype":"venue"
},
  "geometry": {"coordinates":[14.2379436493,48.2466850281],"type":"Point"}
}