{
  "type": "Feature",
  "properties": {
    "iso:country":"AT",
    "sg:address":"St Veiter Str 258",
    "sg:city":"Klagenfurt",
    "sg:orig_category":"Tankstellen",
    "sg:phone":"+43 463 41319",
    "sg:postcode":"9020",
    "sg:province":"K\u00e4rnten",
    "wof:name":"OMV AG",
    "wof:placetype":"venue"
},
  "geometry": {"coordinates":[14.3137989044,46.6534423828],"type":"Point"}
}