{
  "type": "Feature",
  "properties": {
    "iso:country":"AT",
    "sg:address":"Arnulfpl. 2 ",
    "sg:city":"Klagenfurt",
    "sg:classifiers":[
        {
            "category":"Utilities",
            "subcategory":"Electric",
            "type":"Services"
        }
    ],
    "sg:phone":"+43 4346 3525",
    "sg:postcode":"9020",
    "sg:province":"K\u00e4rnten",
    "sg:tags":[
        "electricity"
    ],
    "wof:name":"K\u00c4RNTNER ELEKTRIZIT\u00c4TSWERK AG",
    "wof:placetype":"venue"
},
  "geometry": {"coordinates":[14.3107805252,46.6209983826],"type":"Point"}
}