{
  "type": "Feature",
  "properties": {
    "addr:full":"Perfektastr 45 Wien Wien 1230",
    "addr:housenumber":"45",
    "addr:postcode":"1230",
    "addr:street":"Perfektastr",
    "iso:country":"AT",
    "sg:address":"Perfektastr 45",
    "sg:city":"Wien",
    "sg:orig_category":"Mauertrockenlegungen",
    "sg:phone":"+43 4316 981086",
    "sg:postcode":"1230",
    "sg:province":"Wien",
    "wof:name":"Matrolan Fachbetrieb f Mauerentfeuchtung u Sanierung GmbH",
    "wof:placetype":"venue"
},
  "geometry": {"coordinates":[16.3175525665,48.1372833252],"type":"Point"}
}