{
  "type": "Feature",
  "properties": {
    "addr:full":"Niederau Sonnbergweg 227 Wildsch\u00f6nau-Niederau Tirol 6314",
    "addr:housenumber":"227",
    "addr:postcode":"6314",
    "addr:street":"Sonnbergweg;Tirol",
    "iso:country":"AT",
    "sg:address":"Niederau Sonnbergweg 227",
    "sg:city":"Wildsch\u00f6nau-Niederau",
    "sg:orig_category":"Pensionen / Privatzimmer",
    "sg:phone":"+43 4353 398736",
    "sg:postcode":"6314",
    "sg:province":"Tirol",
    "wof:name":"Haus Bergfried - Konrad Gwiggner",
    "wof:placetype":"venue"
},
  "geometry": {"coordinates":[12.105055809,47.4490509033],"type":"Point"}
}