{
  "type": "Feature",
  "properties": {
    "addr:full":"Bahnhofstr 4/2 Saalfelden am Steinernen Meer Salzburg 5760",
    "addr:housenumber":"4 / 2",
    "addr:postcode":"5760",
    "addr:street":"Bahnhofstr",
    "iso:country":"AT",
    "sg:address":"Bahnhofstr 4/2",
    "sg:city":"Saalfelden am Steinernen Meer",
    "sg:orig_category":"Optiker",
    "sg:phone":"+43 4365 8275980",
    "sg:postcode":"5760",
    "sg:province":"Salzburg",
    "wof:name":"Ohlicher Wolfgang",
    "wof:placetype":"venue"
},
  "geometry": {"coordinates":[12.846408844,47.427028656],"type":"Point"}
}