{
  "type": "Feature",
  "properties": {
    "iso:country":"AT",
    "sg:address":"Roittnerstrasse 5-7",
    "sg:city":"Salzburg",
    "sg:classifiers":[
        {
            "category":"Structure",
            "subcategory":"Office Building",
            "type":"Public Place"
        }
    ],
    "sg:phone":"+43 662 872716",
    "sg:postcode":"5020",
    "sg:province":"Salzburg",
    "sg:tags":[
        "equipment",
        "ceiling",
        "integral",
        "ventilation"
    ],
    "sg:website":"breuninger.co.at",
    "wof:name":"M. Breuninger & Co GmbH",
    "wof:placetype":"venue"
},
  "geometry": {"coordinates":[13.05854702,47.8107032776],"type":"Point"}
}