{
  "type": "Feature",
  "properties": {
    "addr:full":"Kaiser-Franz-Platz 1 Bad Hofgastein Salzburg 5630",
    "addr:housenumber":"1",
    "addr:postcode":"5630",
    "addr:street":"Kaiser-Franz-Platz;Salzburg",
    "iso:country":"AT",
    "sg:address":"Kaiser-Franz-Platz 1",
    "sg:city":"Bad Hofgastein",
    "sg:classifiers":[
        {
            "category":"Banks & Credit Unions",
            "subcategory":"Investment Brokerage",
            "type":"Services"
        }
    ],
    "sg:phone":"+43 6432 7964",
    "sg:postcode":"5630",
    "sg:province":"Salzburg",
    "sg:tags":[
        "case",
        "spectacle"
    ],
    "sg:website":"reinhold-optik.com",
    "wof:name":"Reinhold Optik",
    "wof:placetype":"venue"
},
  "geometry": {"coordinates":[13.1055908203,47.1717796326],"type":"Point"}
}