{
  "type": "Feature",
  "properties": {
    "iso:country":"AT",
    "sg:address":"Rotholzerweg 14",
    "sg:city":"Jenbach",
    "sg:classifiers":[
        {
            "category":"Home & Garden",
            "subcategory":"Home Furnishings",
            "type":"Retail Goods"
        }
    ],
    "sg:phone":"+43 5244 64466",
    "sg:postcode":"6200",
    "sg:province":"Tirol",
    "sg:tags":[
        "air-conditioners"
    ],
    "sg:website":"solar.at",
    "wof:name":"Siko Energiesysteme GmbH & Co KG",
    "wof:placetype":"venue"
},
  "geometry": {"coordinates":[11.780216217,47.3898963928],"type":"Point"}
}