{
  "type": "Feature",
  "properties": {
    "addr:full":"IG Outlet-Center Top 13/BlockC Parndorf Burgenland 7111",
    "addr:postcode":"7111",
    "iso:country":"AT",
    "sg:address":"IG Outlet-Center Top 13/BlockC",
    "sg:city":"Parndorf",
    "sg:orig_category":"Porzellan U Porzellanwaren",
    "sg:phone":"+43 2166 31030",
    "sg:postcode":"7111",
    "sg:province":"Burgenland",
    "wof:name":"Villeroy & Boch Austria HandelsgesmbH",
    "wof:placetype":"venue"
},
  "geometry": {"coordinates":[16.8575897217,47.9981613159],"type":"Point"}
}