{
  "type": "Feature",
  "properties": {
    "addr:full":"Josefsthaler Strasse 34 Tribuswinkel Nieder\u00f6sterreich 2512",
    "addr:housenumber":"34",
    "addr:postcode":"2512",
    "addr:street":"Josefsthaler Strasse",
    "iso:country":"AT",
    "sg:address":"Josefsthaler Strasse 34",
    "sg:city":"Tribuswinkel",
    "sg:classifiers":[
        {
            "category":"Shopping",
            "subcategory":"Crafts & Fabrics",
            "type":"Retail Goods"
        }
    ],
    "sg:phone":"+43 2252 802130",
    "sg:postcode":"2512",
    "sg:province":"Nieder\u00f6sterreich",
    "sg:tags":[
        "adhesive"
    ],
    "sg:website":"ulbrich.at",
    "wof:name":"ULBRICH Maschinenbau- und Export-Import BetriebsGmbH",
    "wof:placetype":"venue"
},
  "geometry": {"coordinates":[16.2695484161,48.0013656616],"type":"Point"}
}