{
  "type": "Feature",
  "properties": {
    "iso:country":"AT",
    "sg:address":"Nr 52",
    "sg:city":"Kainach",
    "sg:orig_category":"Fischzucht",
    "sg:phone":"+43 4331 487271",
    "sg:postcode":"8573",
    "sg:province":"Steiermark",
    "wof:name":"Hamedinger Max",
    "wof:placetype":"venue"
},
  "geometry": {"coordinates":[15.1205244064,47.1084861755],"type":"Point"}
}