{
  "type": "Feature",
  "properties": {
    "iso:country":"AT",
    "sg:address":"Thomasweg 13",
    "sg:city":"Bludesch",
    "sg:orig_category":"Erdarbeiten",
    "sg:phone":"+43 5525 63600",
    "sg:postcode":"6719",
    "sg:province":"Vorarlberg",
    "wof:name":"P\u00f6hl Burghard",
    "wof:placetype":"venue"
},
  "geometry": {"coordinates":[9.7223749161,47.1956291199],"type":"Point"}
}