{
  "type": "Feature",
  "properties": {
    "addr:full":"Danubiastr. 21-25  Schwechat Nieder\u00f6sterreich 2320",
    "addr:postcode":"21-25;2320",
    "addr:street":"Niederoesterreich",
    "iso:country":"AT",
    "sg:address":"Danubiastr. 21-25 ",
    "sg:city":"Schwechat",
    "sg:classifiers":[
        {
            "category":"Manufacturing",
            "subcategory":"Rubber & Plastics",
            "type":"Manufacturing & Wholesale Goods"
        }
    ],
    "sg:phone":"+43 4317 0111",
    "sg:postcode":"2320",
    "sg:province":"Nieder\u00f6sterreich",
    "wof:name":"BOREALES GMBH",
    "wof:placetype":"venue"
},
  "geometry": {"coordinates":[16.5102157593,48.1437034607],"type":"Point"}
}