{
  "type": "Feature",
  "properties": {
    "addr:full":"Niederottnang 44 Ottnang am Hausruck Ober\u00f6sterreich 4901",
    "addr:housenumber":"44",
    "addr:postcode":"4901",
    "addr:street":"Niederottnang",
    "iso:country":"AT",
    "sg:address":"Niederottnang 44",
    "sg:city":"Ottnang am Hausruck",
    "sg:orig_category":"Lebensmittel / Einzelhandel",
    "sg:phone":"+43 767680300",
    "sg:postcode":"4901",
    "sg:province":"Ober\u00f6sterreich",
    "wof:name":"ADEG Contra Markt",
    "wof:placetype":"venue"
},
  "geometry": {"coordinates":[13.6660804749,48.0968818665],"type":"Point"}
}