{
  "type": "Feature",
  "properties": {
    "addr:full":"Mendelssohng 7 Wien Wien 1220",
    "addr:housenumber":"7",
    "addr:postcode":"1220",
    "addr:street":"Mendelssohng",
    "iso:country":"AT",
    "sg:address":"Mendelssohng 7",
    "sg:city":"Wien",
    "sg:orig_category":"Sonnenstudios",
    "sg:phone":"+43 1 2633505",
    "sg:postcode":"1220",
    "sg:province":"Wien",
    "wof:name":"Sunsation Br\u00e4unungsstudio",
    "wof:placetype":"venue"
},
  "geometry": {"coordinates":[16.4231853485,48.2248001099],"type":"Point"}
}