{
  "type": "Feature",
  "properties": {
    "addr:full":"Nr 16 Taufkirchen an der Trattnach Ober\u00f6sterreich 4715",
    "addr:postcode":"4715",
    "addr:street":"Nr 16",
    "iso:country":"AT",
    "sg:address":"Nr 16",
    "sg:city":"Taufkirchen an der Trattnach",
    "sg:classifiers":[
        {
            "category":"Home & Garden",
            "subcategory":"Building Materials",
            "type":"Retail Goods"
        }
    ],
    "sg:phone":"+43 4369 911156665",
    "sg:postcode":"4715",
    "sg:province":"Ober\u00f6sterreich",
    "sg:tags":[
        "baustoffe",
        "-material",
        "u"
    ],
    "wof:name":"LUGMAIR Produkt Consulting GesmbH",
    "wof:placetype":"venue"
},
  "geometry": {"coordinates":[13.7491598129,48.2472038269],"type":"Point"}
}