{
  "type": "Feature",
  "properties": {
    "addr:full":"Puckinger Str 2 Pucking Ober\u00f6sterreich 4055",
    "addr:housenumber":"2",
    "addr:postcode":"4055",
    "addr:street":"Str",
    "iso:country":"AT",
    "sg:address":"Puckinger Str 2",
    "sg:city":"Pucking",
    "sg:orig_category":"Banken U Sparkassen",
    "sg:phone":"+43 4372 2989015",
    "sg:postcode":"4055",
    "sg:province":"Ober\u00f6sterreich",
    "wof:name":"Sparkasse Neuhofen Bank AG",
    "wof:placetype":"venue"
},
  "geometry": {"coordinates":[14.185251236,48.1880607605],"type":"Point"}
}