{
  "type": "Feature",
  "properties": {
    "addr:full":"Rauscherstr 6 Wien Wien 1200",
    "addr:housenumber":"6",
    "addr:postcode":"1200",
    "addr:street":"Rauscherstr",
    "iso:country":"AT",
    "sg:address":"Rauscherstr 6",
    "sg:city":"Wien",
    "sg:orig_category":"Schleif- U Poliermittel",
    "sg:phone":"+43 1 3329218",
    "sg:postcode":"1200",
    "sg:province":"Wien",
    "wof:name":"Soukal Robert",
    "wof:placetype":"venue"
},
  "geometry": {"coordinates":[16.3758296967,48.2303085327],"type":"Point"}
}