{
  "type": "Feature",
  "properties": {
    "iso:country":"AT",
    "sg:address":"Unterweg 60",
    "sg:city":"Matrei am Brenner",
    "sg:classifiers":[
        {
            "category":"Building & Trades",
            "subcategory":"Construction",
            "type":"Services"
        }
    ],
    "sg:phone":"+43 5278 6203",
    "sg:postcode":"6143",
    "sg:province":"Tirol",
    "sg:tags":[
        "interior",
        "work"
    ],
    "wof:name":"Markus Penz",
    "wof:placetype":"venue"
},
  "geometry": {"coordinates":[11.4936552048,47.124671936],"type":"Point"}
}