{
  "type": "Feature",
  "properties": {
    "addr:full":"Hietzinger Kai 125 Wien Wien 1130",
    "addr:housenumber":"125",
    "addr:postcode":"1130",
    "addr:street":"Hietzinger Kai",
    "iso:country":"AT",
    "sg:address":"Hietzinger Kai 125",
    "sg:city":"Wien",
    "sg:orig_category":"Autohandel",
    "sg:phone":"+43 1 870000",
    "sg:postcode":"1130",
    "sg:province":"Wien",
    "wof:name":"Porsche Inter Auto KG - Zweigniederlassung Porsche Wien-Hietzing",
    "wof:placetype":"venue"
},
  "geometry": {"coordinates":[16.2835559845,48.1911277771],"type":"Point"}
}