{
  "type": "Feature",
  "properties": {
    "iso:country":"AT",
    "sg:address":"Furth 17",
    "sg:city":"B\u00f6heimkirchen",
    "sg:classifiers":[
        {
            "category":"Government",
            "subcategory":"Office",
            "type":"Public Place"
        }
    ],
    "sg:phone":"+43 2744 52750",
    "sg:postcode":"3071",
    "sg:province":"Nieder\u00f6sterreich",
    "sg:tags":[
        "building",
        "industrial",
        "equipping",
        "furnishing"
    ],
    "sg:website":"hochgerner.at",
    "wof:name":"Hochgerner M\u00f6belwerkst\u00e4tten Ges.m.b.H. & Co KG",
    "wof:placetype":"venue"
},
  "geometry": {"coordinates":[7.7127490044,49.574382782],"type":"Point"}
}