{
  "type": "Feature",
  "properties": {
    "iso:country":"AT",
    "sg:address":"Winterg 75-77",
    "sg:city":"Purkersdorf",
    "sg:orig_category":"Psychotherapie",
    "sg:phone":"+43 2231 63154",
    "sg:postcode":"3002",
    "sg:province":"Nieder\u00f6sterreich",
    "wof:name":"Fally Margit Mag",
    "wof:placetype":"venue"
},
  "geometry": {"coordinates":[16.1907749176,48.2085266113],"type":"Point"}
}