{
  "type": "Feature",
  "properties": {
    "addr:full":"Lagerstr 31 Gm\u00fcnd Nieder\u00f6sterreich 3950",
    "addr:housenumber":"31",
    "addr:postcode":"3950",
    "addr:street":"Lagerstr;Niederoesterreich",
    "iso:country":"AT",
    "sg:address":"Lagerstr 31",
    "sg:city":"Gm\u00fcnd",
    "sg:orig_category":"Steuerberatung",
    "sg:phone":"+43 4328 52538850",
    "sg:postcode":"3950",
    "sg:province":"Nieder\u00f6sterreich",
    "wof:name":"Correcta Lang & Co Wirtschaftstreuhand GmbH",
    "wof:placetype":"venue"
},
  "geometry": {"coordinates":[14.9787158966,48.7602539062],"type":"Point"}
}