{
  "type": "Feature",
  "properties": {
    "addr:full":"Hauptstr 53 Gaspoltshofen Ober\u00f6sterreich 4673",
    "addr:housenumber":"53",
    "addr:postcode":"4673",
    "addr:street":"Hauptstr",
    "iso:country":"AT",
    "sg:address":"Hauptstr 53",
    "sg:city":"Gaspoltshofen",
    "sg:orig_category":"Polizei U Gendarmerie",
    "sg:phone":"+43 4359 1334232",
    "sg:postcode":"4673",
    "sg:province":"Ober\u00f6sterreich",
    "wof:name":"Gendarmerie",
    "wof:placetype":"venue"
},
  "geometry": {"coordinates":[13.735874176,48.1400299072],"type":"Point"}
}