{
  "type": "Feature",
  "properties": {
    "iso:country":"AT",
    "sg:address":"Liesinger Pl",
    "sg:city":"Wien",
    "sg:orig_category":"Non-Classified Establishments",
    "sg:phone":"+43 1 8693838",
    "sg:postcode":"1230",
    "sg:province":"Wien",
    "wof:name":"TAXI-TEL Standplatztelefon Betriebs GmbH",
    "wof:placetype":"venue"
},
  "geometry": {"coordinates":[16.28282547,48.1348190308],"type":"Point"}
}