{
  "type": "Feature",
  "properties": {
    "iso:country":"AT",
    "sg:address":"Salzburger Str 255",
    "sg:city":"Linz",
    "sg:orig_category":"Fahrschulen",
    "sg:phone":"+43 732 380244",
    "sg:postcode":"4030",
    "sg:province":"Ober\u00f6sterreich",
    "sg:website":"members.aon.at/stoiber",
    "wof:name":"Fahrschule Stoiber",
    "wof:placetype":"venue"
},
  "geometry": {"coordinates":[14.282169342,48.2534103394],"type":"Point"}
}