{
  "type": "Feature",
  "properties": {
    "iso:country":"AT",
    "sg:address":"St. Peter Hauptstr 75a",
    "sg:city":"St. Peter",
    "sg:orig_category":"Geschenkartikel",
    "sg:phone":"+43 4331 6463555",
    "sg:postcode":"8042",
    "sg:province":"Steiermark",
    "wof:name":"Kastner & Kastner - Kunsthandwerke & Geschenke",
    "wof:placetype":"venue"
},
  "geometry": {"coordinates":[15.4734573364,47.0553703308],"type":"Point"}
}