{
  "type": "Feature",
  "properties": {
    "addr:full":"Mariahilfstr 42-44 Innsbruck Tirol 6020",
    "addr:housenumber":"42-44",
    "addr:postcode":"6020",
    "addr:street":"Tirol",
    "iso:country":"AT",
    "sg:address":"Mariahilfstr 42-44",
    "sg:city":"Innsbruck",
    "sg:orig_category":"Banken U Sparkassen",
    "sg:phone":"+43 512 284153",
    "sg:postcode":"6020",
    "sg:province":"Tirol",
    "wof:name":"Tiroler Sparkasse Bank AG Innsbruck",
    "wof:placetype":"venue"
},
  "geometry": {"coordinates":[11.3884706497,47.2680969238],"type":"Point"}
}