{
  "type": "Feature",
  "properties": {
    "addr:full":"Pischeldorfer Str 125 Klagenfurt K\u00e4rnten 9020",
    "addr:housenumber":"125",
    "addr:postcode":"9020",
    "addr:street":"Kaernten",
    "iso:country":"AT",
    "sg:address":"Pischeldorfer Str 125",
    "sg:city":"Klagenfurt",
    "sg:classifiers":[
        {
            "category":"Restaurant",
            "type":"Food & Drink"
        }
    ],
    "sg:phone":"+43 463 410763",
    "sg:postcode":"9020",
    "sg:province":"K\u00e4rnten",
    "wof:name":"Zum Valentin Wohlf\u00fchlrestaurant",
    "wof:placetype":"venue"
},
  "geometry": {"coordinates":[14.3283452988,46.6369094849],"type":"Point"}
}