{
  "type": "Feature",
  "properties": {
    "iso:country":"AT",
    "sg:address":"Sylvester-Jordan-Str 12",
    "sg:city":"Axams",
    "sg:orig_category":"Polizei U Gendarmerie",
    "sg:phone":"+43 4359 1337111",
    "sg:postcode":"6094",
    "sg:province":"Tirol",
    "wof:name":"Gendarmerie",
    "wof:placetype":"venue"
},
  "geometry": {"coordinates":[11.2800760269,47.2326545715],"type":"Point"}
}