{
  "type": "Feature",
  "properties": {
    "addr:full":"Waldfeldweg 631 Mayrhofen Tirol 6290",
    "addr:housenumber":"631",
    "addr:postcode":"6290",
    "addr:street":"Waldfeldweg;Tirol",
    "iso:country":"AT",
    "sg:address":"Waldfeldweg 631",
    "sg:city":"Mayrhofen",
    "sg:orig_category":"Pensionen / Privatzimmer",
    "sg:phone":"+43 5285 62744",
    "sg:postcode":"6290",
    "sg:province":"Tirol",
    "wof:name":"Haus Mariandl",
    "wof:placetype":"venue"
},
  "geometry": {"coordinates":[11.8570461273,47.1650161743],"type":"Point"}
}