{
  "type": "Feature",
  "properties": {
    "addr:full":"Baumbachstr. 15 Linz Ober\u00f6sterreich 4020",
    "addr:housenumber":"15",
    "addr:postcode":"4020",
    "addr:street":"Baumbachstr.",
    "iso:country":"AT",
    "sg:address":"Baumbachstr. 15",
    "sg:city":"Linz",
    "sg:orig_category":"Dienstleistungen, Druck U Beschriftungen",
    "sg:phone":"+43 4373 2777535",
    "sg:postcode":"4020",
    "sg:province":"Ober\u00f6sterreich",
    "sg:website":"http://www.pibi.at",
    "wof:name":"B\u00fcttner Peter - Pibi",
    "wof:placetype":"venue"
},
  "geometry": {"coordinates":[14.2838439941,48.3005638123],"type":"Point"}
}