{
  "type": "Feature",
  "properties": {
    "addr:full":"Jochberger Str Kitzb\u00fchel Tirol 6370",
    "addr:postcode":"6370",
    "addr:street":"Str Kitzbuehel Tirol",
    "iso:country":"AT",
    "sg:address":"Jochberger Str",
    "sg:city":"Kitzb\u00fchel",
    "sg:orig_category":"Lebensmittel / Einzelhandel",
    "sg:phone":"+43 5356 72976",
    "sg:postcode":"6370",
    "sg:province":"Tirol",
    "wof:name":"Billa AG",
    "wof:placetype":"venue"
},
  "geometry": {"coordinates":[12.4092206955,47.4300193787],"type":"Point"}
}