{
  "type": "Feature",
  "properties": {
    "iso:country":"AT",
    "sg:address":"Dr.-Paul-Schwarzkopf-Str 10",
    "sg:city":"Reutte",
    "sg:classifiers":[
        {
            "category":"Restaurant",
            "type":"Food & Drink"
        }
    ],
    "sg:phone":"+43 4356 7265920",
    "sg:postcode":"6600",
    "sg:province":"Tirol",
    "sg:tags":[
        "pizzeria"
    ],
    "wof:name":"Pizzeria Nati",
    "wof:placetype":"venue"
},
  "geometry": {"coordinates":[10.7326183319,47.4980278015],"type":"Point"}
}