{
  "type": "Feature",
  "properties": {
    "addr:full":"Eggedinger Strasse 4 St. Marienkirchen Ober\u00f6sterreich 4774",
    "addr:housenumber":"4",
    "addr:postcode":"4774",
    "addr:street":"Eggedinger Strasse",
    "iso:country":"AT",
    "sg:address":"Eggedinger Strasse 4",
    "sg:city":"St. Marienkirchen",
    "sg:classifiers":[
        {
            "category":"Home & Garden",
            "subcategory":"Building Materials",
            "type":"Retail Goods"
        }
    ],
    "sg:phone":"+43 7711 2260",
    "sg:postcode":"4774",
    "sg:province":"Ober\u00f6sterreich",
    "sg:tags":[
        "installation",
        "electric"
    ],
    "wof:name":"Zaglmayr Ges.m.b.H. & Co KG",
    "wof:placetype":"venue"
},
  "geometry": {"coordinates":[13.4512290955,48.3879585266],"type":"Point"}
}