{
  "type": "Feature",
  "properties": {
    "addr:full":"Weiherburgg 5 Innsbruck Tirol 6020",
    "addr:housenumber":"5",
    "addr:postcode":"6020",
    "addr:street":"Weiherburgg;Tirol",
    "iso:country":"AT",
    "sg:address":"Weiherburgg 5",
    "sg:city":"Innsbruck",
    "sg:orig_category":"Exporteure U Importeure",
    "sg:phone":"+43 4351 2281515",
    "sg:postcode":"6020",
    "sg:province":"Tirol",
    "wof:name":"Top Products Trade GmbH",
    "wof:placetype":"venue"
},
  "geometry": {"coordinates":[11.3925962448,47.2754173279],"type":"Point"}
}