{
  "type": "Feature",
  "properties": {
    "addr:full":"Solvaystr 12 Ebensee Ober\u00f6sterreich 4802",
    "addr:housenumber":"12",
    "addr:postcode":"4802",
    "addr:street":"Solvaystr",
    "iso:country":"AT",
    "sg:address":"Solvaystr 12",
    "sg:city":"Ebensee",
    "sg:orig_category":"Werbegrafik- U Grafik-Design",
    "sg:phone":"+43 6133 79210",
    "sg:postcode":"4802",
    "sg:province":"Ober\u00f6sterreich",
    "wof:name":"Brenner Johannes",
    "wof:placetype":"venue"
},
  "geometry": {"coordinates":[13.7732400894,47.8066101074],"type":"Point"}
}