{
  "type": "Feature",
  "properties": {
    "addr:full":"Wiedner Hauptstrasse 120-124 Wien Wien 1050",
    "addr:housenumber":"120-124",
    "addr:postcode":"1050",
    "addr:street":"Wiedner Hauptstrasse",
    "iso:country":"AT",
    "sg:address":"Wiedner Hauptstrasse 120-124",
    "sg:city":"Wien",
    "sg:classifiers":[
        {
            "category":"Wholesale",
            "subcategory":"Books, Periodicals, & Newspapers",
            "type":"Manufacturing & Wholesale Goods"
        }
    ],
    "sg:phone":"+43 1 546640",
    "sg:postcode":"1050",
    "sg:province":"Wien",
    "sg:tags":[
        "professional",
        "journal",
        "journals",
        "publisher"
    ],
    "sg:website":"wirtschaftverlag.at",
    "wof:name":"\u00d6sterreichischer Wirtschaftsverlag GmbH",
    "wof:placetype":"venue"
},
  "geometry": {"coordinates":[16.361623764,48.1847572327],"type":"Point"}
}