{
  "type": "Feature",
  "properties": {
    "iso:country":"AT",
    "sg:city":"Mellau",
    "sg:orig_category":"Feuerwehren",
    "sg:phone":"+43 5518 220421",
    "sg:postcode":"6881",
    "sg:province":"Vorarlberg",
    "wof:name":"Feuerwehr Mellau",
    "wof:placetype":"venue"
},
  "geometry": {"coordinates":[9.8822097778,47.3512458801],"type":"Point"}
}