{
  "type": "Feature",
  "properties": {
    "addr:full":"Schie\u00dfstand 8 Inzing Tirol 6401",
    "addr:housenumber":"8",
    "addr:postcode":"6401",
    "addr:street":"Schiessstand;Tirol",
    "iso:country":"AT",
    "sg:address":"Schie\u00dfstand 8",
    "sg:city":"Inzing",
    "sg:orig_category":"Unternehmensberatung",
    "sg:phone":"+43 4352 38539340",
    "sg:postcode":"6401",
    "sg:province":"Tirol",
    "wof:name":"Freudenthaler Institut f Analytik u Beratung GmbH",
    "wof:placetype":"venue"
},
  "geometry": {"coordinates":[11.2193517685,47.2664604187],"type":"Point"}
}