{
  "type": "Feature",
  "properties": {
    "addr:full":"Planseestr 5 Reutte Tirol 6600",
    "addr:housenumber":"5",
    "addr:postcode":"6600",
    "addr:street":"Planseestr;Tirol",
    "iso:country":"AT",
    "sg:address":"Planseestr 5",
    "sg:city":"Reutte",
    "sg:classifiers":[
        {
            "category":"Travel",
            "subcategory":"Hotels & Motels",
            "type":"Entertainment"
        }
    ],
    "sg:phone":"+43 5672 78120",
    "sg:postcode":"6600",
    "sg:province":"Tirol",
    "wof:name":"Hotel Seespitze",
    "wof:placetype":"venue"
},
  "geometry": {"coordinates":[10.7202129364,47.4905853271],"type":"Point"}
}