{
  "type": "Feature",
  "properties": {
    "iso:country":"AT",
    "sg:address":"Heinrichsgasse 2/9",
    "sg:city":"Wien",
    "sg:classifiers":[
        {
            "category":"Home & Garden",
            "subcategory":"Home Furnishings",
            "type":"Retail Goods"
        }
    ],
    "sg:phone":"+43 1 5336534",
    "sg:postcode":"1010",
    "sg:province":"Wien",
    "sg:tags":[
        "consulting"
    ],
    "sg:website":"architecture.at",
    "wof:name":"Architekturb\u00fcro Dipl.-Ing. Michael Schluder",
    "wof:placetype":"venue"
},
  "geometry": {"coordinates":[16.3704051971,48.2137870789],"type":"Point"}
}