{
  "type": "Feature",
  "properties": {
    "addr:full":"Koppler Str 78 Koppl Salzburg 5321",
    "addr:postcode":"5321",
    "addr:street":"Str 78;Salzburg",
    "iso:country":"AT",
    "sg:address":"Koppler Str 78",
    "sg:city":"Koppl",
    "sg:orig_category":"Appartements / Ferienwohnungen",
    "sg:phone":"+43 6221 7356",
    "sg:postcode":"5321",
    "sg:province":"Salzburg",
    "wof:name":"Deisl Mathias und Christine - Ferienwohnungen",
    "wof:placetype":"venue"
},
  "geometry": {"coordinates":[13.1560792923,47.8074684143],"type":"Point"}
}