{
  "type": "Feature",
  "properties": {
    "iso:country":"AT",
    "sg:address":"Innrain 80",
    "sg:city":"Innsbruck",
    "sg:orig_category":"Institute",
    "sg:phone":"+43 4351 25078211",
    "sg:postcode":"6020",
    "sg:province":"Tirol",
    "wof:name":"Institut f \u00f6ffentliches Recht - Finazrecht u Politik",
    "wof:placetype":"venue"
},
  "geometry": {"coordinates":[11.3812322617,47.2596664429],"type":"Point"}
}