{
  "type": "Feature",
  "properties": {
    "addr:full":"Hauptstr 6a Strasshof an der Nordbahn Nieder\u00f6sterreich 2231",
    "addr:housenumber":"6a",
    "addr:postcode":"2231",
    "addr:street":"Hauptstr",
    "iso:country":"AT",
    "sg:address":"Hauptstr 6a",
    "sg:city":"Strasshof an der Nordbahn",
    "sg:orig_category":"Autoreparatur",
    "sg:phone":"+43 4322 873116",
    "sg:postcode":"2231",
    "sg:province":"Nieder\u00f6sterreich",
    "wof:name":"Hrdinka Helmut",
    "wof:placetype":"venue"
},
  "geometry": {"coordinates":[16.6089553833,48.3115234375],"type":"Point"}
}