{
  "type": "Feature",
  "properties": {
    "addr:full":"In Der Braike 14 Bregenz Vorarlberg 6900",
    "addr:housenumber":"14",
    "addr:postcode":"6900",
    "addr:street":"In Der Braike",
    "iso:country":"AT",
    "sg:address":"In Der Braike 14",
    "sg:city":"Bregenz",
    "sg:classifiers":[
        {
            "category":"Retail",
            "subcategory":"Animal Services",
            "type":"Services"
        }
    ],
    "sg:phone":"+43 4355 7467670",
    "sg:postcode":"6900",
    "sg:province":"Vorarlberg",
    "sg:tags":[
        "breeding"
    ],
    "wof:name":"VORARLBERGER M\u00dcHLEN U. MISCHFUTTERWERKE GES.MBH",
    "wof:placetype":"venue"
},
  "geometry": {"coordinates":[9.7285442352,47.4997558594],"type":"Point"}
}