{
  "type": "Feature",
  "properties": {
    "addr:full":"S\u00fcdring 242 Klagenfurt K\u00e4rnten 9020",
    "addr:housenumber":"242",
    "addr:postcode":"9020",
    "addr:street":"Kaernten",
    "iso:country":"AT",
    "sg:address":"S\u00fcdring 242",
    "sg:city":"Klagenfurt",
    "sg:classifiers":[
        {
            "category":"Home & Garden",
            "subcategory":"Building Materials",
            "type":"Retail Goods"
        }
    ],
    "sg:phone":"+43 463 3865593",
    "sg:postcode":"9020",
    "sg:province":"K\u00e4rnten",
    "sg:tags":[
        "baustoffe",
        "-material",
        "u"
    ],
    "wof:name":"AFS Franchise Systeme GmbH",
    "wof:placetype":"venue"
},
  "geometry": {"coordinates":[14.3274202347,46.6254196167],"type":"Point"}
}