{
  "type": "Feature",
  "properties": {
    "addr:full":"Nr 15 Wolfsberg im Schwarzautal Steiermark 8421",
    "addr:postcode":"8421",
    "addr:street":"Nr",
    "iso:country":"AT",
    "sg:address":"Nr 15",
    "sg:city":"Wolfsberg im Schwarzautal",
    "sg:orig_category":"Glasereien",
    "sg:phone":"+43 664 2317150",
    "sg:postcode":"8421",
    "sg:province":"Steiermark",
    "wof:name":"Ihr Glaser Steiner",
    "wof:placetype":"venue"
},
  "geometry": {"coordinates":[15.6596889496,46.8450279236],"type":"Point"}
}