{
  "type": "Feature",
  "properties": {
    "addr:full":"Nr 106 St. Margarethen an der Raab Steiermark 8321",
    "addr:postcode":"8321",
    "addr:street":"Nr 106",
    "iso:country":"AT",
    "sg:address":"Nr 106",
    "sg:city":"St. Margarethen an der Raab",
    "sg:orig_category":"Transportunternehmen",
    "sg:phone":"+43 4331 152294",
    "sg:postcode":"8321",
    "sg:province":"Steiermark",
    "wof:name":"Gohla Erich",
    "wof:placetype":"venue"
},
  "geometry": {"coordinates":[15.7453098297,47.0449333191],"type":"Point"}
}