{
  "type": "Feature",
  "properties": {
    "addr:full":"Dr.-Alexander-Sch\u00e4rf-Strasse 8 Wiener Neustadt Nieder\u00f6sterreich 2700",
    "addr:housenumber":"8",
    "addr:postcode":"2700",
    "addr:street":"Dr.-Alexander-Schaerf-Strasse",
    "iso:country":"AT",
    "sg:address":"Dr.-Alexander-Sch\u00e4rf-Strasse 8",
    "sg:city":"Wiener Neustadt",
    "sg:classifiers":[
        {
            "category":"Manufacturing",
            "subcategory":"Tools & Machinery",
            "type":"Manufacturing & Wholesale Goods"
        }
    ],
    "sg:phone":"+43 2622 223810",
    "sg:postcode":"2700",
    "sg:province":"Nieder\u00f6sterreich",
    "sg:tags":[
        "part",
        "turned",
        "cnc"
    ],
    "sg:website":"gnm.at",
    "wof:name":"Gebr\u00fcder Nemetz Maschinenbau Ges.m.b.H.",
    "wof:placetype":"venue"
},
  "geometry": {"coordinates":[16.2420711517,47.8385238647],"type":"Point"}
}