{
  "type": "Feature",
  "properties": {
    "iso:country":"AT",
    "sg:address":"Edlastr 3",
    "sg:city":"Weissenbach an der Triesting",
    "sg:orig_category":"Massagen",
    "sg:phone":"+43 4326 7487487",
    "sg:postcode":"2564",
    "sg:province":"Nieder\u00f6sterreich",
    "wof:name":"Massage - Suhrada Brigitte",
    "wof:placetype":"venue"
},
  "geometry": {"coordinates":[16.0331707001,47.9858055115],"type":"Point"}
}