{
  "type": "Feature",
  "properties": {
    "addr:full":"Franzosengraben 12 Wien Wien 1030",
    "addr:housenumber":"12",
    "addr:postcode":"1030",
    "addr:street":"Franzosengraben",
    "iso:country":"AT",
    "sg:address":"Franzosengraben 12",
    "sg:city":"Wien",
    "sg:orig_category":"Automatisierungstechnik",
    "sg:phone":"+43 1 795520",
    "sg:postcode":"1030",
    "sg:province":"Wien",
    "wof:name":"Metso Automation GmbH",
    "wof:placetype":"venue"
},
  "geometry": {"coordinates":[16.4138774872,48.1881790161],"type":"Point"}
}