{
  "type": "Feature",
  "properties": {
    "addr:full":"Rosentaler Str 105 Klagenfurt K\u00e4rnten 9020",
    "addr:housenumber":"105",
    "addr:postcode":"9020",
    "addr:street":"Kaernten",
    "iso:country":"AT",
    "sg:address":"Rosentaler Str 105",
    "sg:city":"Klagenfurt",
    "sg:orig_category":"Friseure U Frisiersalons",
    "sg:phone":"+43 463 22334",
    "sg:postcode":"9020",
    "sg:province":"K\u00e4rnten",
    "wof:name":"Frisiersalon Ingrid",
    "wof:placetype":"venue"
},
  "geometry": {"coordinates":[14.3001031876,46.6092948914],"type":"Point"}
}