{
  "type": "Feature",
  "properties": {
    "iso:country":"AT",
    "sg:address":"Wattgasse 49",
    "sg:city":"Wien",
    "sg:classifiers":[
        {
            "category":"Building & Trades",
            "subcategory":"Electrical",
            "type":"Services"
        }
    ],
    "sg:phone":"+43 1 4813099",
    "sg:postcode":"1160",
    "sg:province":"Wien",
    "sg:tags":[
        "installation"
    ],
    "sg:website":"latt.at",
    "wof:name":"Latt & Co GesmbH",
    "wof:placetype":"venue"
},
  "geometry": {"coordinates":[16.3199367523,48.2181510925],"type":"Point"}
}