{
  "type": "Feature",
  "properties": {
    "addr:full":"Bundesstr 5 Weiz Steiermark 8160",
    "addr:housenumber":"5",
    "addr:postcode":"8160",
    "addr:street":"Bundesstr",
    "iso:country":"AT",
    "sg:address":"Bundesstr 5",
    "sg:city":"Weiz",
    "sg:orig_category":"Lebensmittel / Einzelhandel",
    "sg:phone":"+43 3172 38638",
    "sg:postcode":"8160",
    "sg:province":"Steiermark",
    "wof:name":"Hofer KG",
    "wof:placetype":"venue"
},
  "geometry": {"coordinates":[15.6393699646,47.2049407959],"type":"Point"}
}