{
  "type": "Feature",
  "properties": {
    "addr:full":"Bergstr 41 Haslach an der M\u00fchl Ober\u00f6sterreich 4170",
    "addr:housenumber":"41",
    "addr:postcode":"4170",
    "addr:street":"Bergstr;Oberoesterreich",
    "iso:country":"AT",
    "sg:address":"Bergstr 41",
    "sg:city":"Haslach an der M\u00fchl",
    "sg:orig_category":"Webereien U Spinnereien",
    "sg:phone":"+43 4372 89710390",
    "sg:postcode":"4170",
    "sg:province":"Ober\u00f6sterreich",
    "wof:name":"Bayer Hermann",
    "wof:placetype":"venue"
},
  "geometry": {"coordinates":[14.0420589447,48.5829353333],"type":"Point"}
}