{
  "type": "Feature",
  "properties": {
    "addr:full":"Muldenweg 6 Wolfsberg K\u00e4rnten 9400",
    "addr:housenumber":"6;kaernten",
    "addr:postcode":"9400",
    "addr:street":"Muldenweg",
    "iso:country":"AT",
    "sg:address":"Muldenweg 6",
    "sg:city":"Wolfsberg",
    "sg:orig_category":"Waren Aller Art",
    "sg:phone":"+43 4366 45404392",
    "sg:postcode":"9400",
    "sg:province":"K\u00e4rnten",
    "wof:name":"NVD - Nilo Vazzoler Dienstleistungsunternehmen",
    "wof:placetype":"venue"
},
  "geometry": {"coordinates":[14.8311481476,46.8283004761],"type":"Point"}
}