{
  "type": "Feature",
  "properties": {
    "iso:country":"AT",
    "sg:address":"Linzer Str 156",
    "sg:city":"Wels",
    "sg:orig_category":"Stempel",
    "sg:phone":"+43 7242 239",
    "sg:postcode":"4600",
    "sg:province":"Ober\u00f6sterreich",
    "wof:name":"Trodat Produktions GmbH",
    "wof:placetype":"venue"
},
  "geometry": {"coordinates":[14.0503950119,48.1692504883],"type":"Point"}
}