{
  "type": "Feature",
  "properties": {
    "iso:country":"AT",
    "sg:address":"Morzger Str 71",
    "sg:city":"Salzburg",
    "sg:orig_category":"Physiotherapie",
    "sg:phone":"+43 664 4004400",
    "sg:postcode":"5020",
    "sg:province":"Salzburg",
    "wof:name":"Steger-Puhr Waltraud Mag",
    "wof:placetype":"venue"
},
  "geometry": {"coordinates":[13.0585699081,47.7698059082],"type":"Point"}
}