{
  "type": "Feature",
  "properties": {
    "iso:country":"AT",
    "sg:address":"Gutheil-Schoder-G 9",
    "sg:city":"Wien",
    "sg:orig_category":"Sportschulen",
    "sg:phone":"+43 676 84911436",
    "sg:postcode":"1100",
    "sg:province":"Wien",
    "sg:website":"takedabudo.at",
    "wof:name":"Takeda Budokan Wien",
    "wof:placetype":"venue"
},
  "geometry": {"coordinates":[16.3394031525,48.1629943848],"type":"Point"}
}