{
  "type": "Feature",
  "properties": {
    "addr:full":"Nr 123 Hollersbach im Pinzgau Salzburg 5731",
    "addr:postcode":"5731",
    "addr:street":"Nr 123;Salzburg",
    "iso:country":"AT",
    "sg:address":"Nr 123",
    "sg:city":"Hollersbach im Pinzgau",
    "sg:orig_category":"Friseure U Frisiersalons",
    "sg:phone":"+43 4366 42629129",
    "sg:postcode":"5731",
    "sg:province":"Salzburg",
    "wof:name":"Knapp Karola",
    "wof:placetype":"venue"
},
  "geometry": {"coordinates":[12.4197301865,47.2750968933],"type":"Point"}
}