{
  "type": "Feature",
  "properties": {
    "addr:full":"Hochstr 10 Hellmons\u00f6dt Ober\u00f6sterreich 4202",
    "addr:housenumber":"10",
    "addr:postcode":"4202",
    "addr:street":"Hochstr;Oberoesterreich",
    "iso:country":"AT",
    "sg:address":"Hochstr 10",
    "sg:city":"Hellmons\u00f6dt",
    "sg:orig_category":"Bergbahnen",
    "sg:phone":"+43 7215 3297",
    "sg:postcode":"4202",
    "sg:province":"Ober\u00f6sterreich",
    "wof:name":"Angerer Wilhelm",
    "wof:placetype":"venue"
},
  "geometry": {"coordinates":[14.2859697342,48.423740387],"type":"Point"}
}