{
  "type": "Feature",
  "properties": {
    "addr:full":"Kr\u00f6llendorf 44 Hausmening Nieder\u00f6sterreich 3363",
    "addr:housenumber":"44",
    "addr:postcode":"3363",
    "addr:street":"Kroellendorf",
    "iso:country":"AT",
    "sg:address":"Kr\u00f6llendorf 44",
    "sg:city":"Hausmening",
    "sg:classifiers":[
        {
            "category":"Community Center",
            "subcategory":"Senior",
            "type":"Public Place"
        }
    ],
    "sg:phone":"+43 7448 7090",
    "sg:postcode":"3363",
    "sg:province":"Nieder\u00f6sterreich",
    "sg:tags":[
        "front",
        "wood",
        "door"
    ],
    "wof:name":"Hirtl GmbH",
    "wof:placetype":"venue"
},
  "geometry": {"coordinates":[14.8137149811,48.0781707764],"type":"Point"}
}