{
  "type": "Feature",
  "properties": {
    "addr:full":"Hochofenstr 3 Eisenerz Steiermark 8790",
    "addr:housenumber":"3",
    "addr:postcode":"8790",
    "addr:street":"Hochofenstr",
    "iso:country":"AT",
    "sg:address":"Hochofenstr 3",
    "sg:city":"Eisenerz",
    "sg:orig_category":"Autoglas",
    "sg:phone":"+43 3848 22800",
    "sg:postcode":"8790",
    "sg:province":"Steiermark",
    "wof:name":"Pilkington Automotive Austria GesmbH",
    "wof:placetype":"venue"
},
  "geometry": {"coordinates":[14.8730783463,47.551109314],"type":"Point"}
}