{
  "type": "Feature",
  "properties": {
    "iso:country":"AT",
    "sg:address":"Gleisdorfer Str 2",
    "sg:city":"Weiz",
    "sg:orig_category":"Steuerberatung",
    "sg:phone":"+43 4331 7220610",
    "sg:postcode":"8160",
    "sg:province":"Steiermark",
    "sg:website":"absenger-rathausky.at",
    "wof:name":"Absenger-Dr Rathausky Wirtschaftstreuhand GmbH",
    "wof:placetype":"venue"
},
  "geometry": {"coordinates":[15.6265087128,47.216594696],"type":"Point"}
}