{
  "type": "Feature",
  "properties": {
    "addr:full":"Leoganger Str 18/17 Saalfelden am Steinernen Meer Salzburg 5760",
    "addr:housenumber":"18 / 17",
    "addr:postcode":"5760",
    "addr:street":"Str;Salzburg",
    "iso:country":"AT",
    "sg:address":"Leoganger Str 18/17",
    "sg:city":"Saalfelden am Steinernen Meer",
    "sg:orig_category":"Damenmoden",
    "sg:phone":"+43 6582 73041",
    "sg:postcode":"5760",
    "sg:province":"Salzburg",
    "wof:name":"Charles V\u00f6gele (Austria) AG",
    "wof:placetype":"venue"
},
  "geometry": {"coordinates":[12.8424301147,47.4294281006],"type":"Point"}
}