{
  "type": "Feature",
  "properties": {
    "addr:full":"Julius-Tandler-Pl 8 Wien Wien 1090",
    "addr:housenumber":"8",
    "addr:postcode":"1090",
    "addr:street":"Julius-Tandler-Pl",
    "iso:country":"AT",
    "sg:address":"Julius-Tandler-Pl 8",
    "sg:city":"Wien",
    "sg:orig_category":"Drogerien",
    "sg:phone":"+43 1 3175587",
    "sg:postcode":"1090",
    "sg:province":"Wien",
    "wof:name":"dm drogerie markt GmbH",
    "wof:placetype":"venue"
},
  "geometry": {"coordinates":[16.3616008759,48.2254486084],"type":"Point"}
}