{
  "type": "Feature",
  "properties": {
    "iso:country":"AT",
    "sg:address":"Marktpl 15",
    "sg:city":"Mauthausen",
    "sg:orig_category":"Tabaktrafiken",
    "sg:phone":"+43 7238 2234",
    "sg:postcode":"4310",
    "sg:province":"Ober\u00f6sterreich",
    "wof:name":"Wimmer Johann",
    "wof:placetype":"venue"
},
  "geometry": {"coordinates":[14.5171947479,48.240852356],"type":"Point"}
}