{
  "type": "Feature",
  "properties": {
    "addr:full":"Franz-Josef-Str 7 Leoben Steiermark 8700",
    "addr:housenumber":"7",
    "addr:postcode":"8700",
    "addr:street":"Franz-Josef-Str",
    "iso:country":"AT",
    "sg:address":"Franz-Josef-Str 7",
    "sg:city":"Leoben",
    "sg:orig_category":"Apotheken",
    "sg:phone":"+43 4338 42432640",
    "sg:postcode":"8700",
    "sg:province":"Steiermark",
    "wof:name":"Josefee-Apotheke",
    "wof:placetype":"venue"
},
  "geometry": {"coordinates":[15.0934257507,47.3826637268],"type":"Point"}
}