{
  "type": "Feature",
  "properties": {
    "addr:full":"Wassergspreng 1 Hinterbr\u00fchl Nieder\u00f6sterreich 2371",
    "addr:housenumber":"1",
    "addr:postcode":"2371",
    "addr:street":"Wassergspreng;Niederoesterreich",
    "iso:country":"AT",
    "sg:address":"Wassergspreng 1",
    "sg:city":"Hinterbr\u00fchl",
    "sg:orig_category":"Hobbyvereine",
    "sg:phone":"+43 4322 3626666",
    "sg:postcode":"2371",
    "sg:province":"Nieder\u00f6sterreich",
    "wof:name":"Pfadfinder und Pfadfinderinnen \u00d6sterreichs",
    "wof:placetype":"venue"
},
  "geometry": {"coordinates":[16.2097663879,48.0912857056],"type":"Point"}
}