{
  "type": "Feature",
  "properties": {
    "addr:full":"Tobelm\u00fchlstr 10 Seeham Salzburg 5164",
    "addr:housenumber":"10",
    "addr:postcode":"5164",
    "addr:street":"Tobelmuehlstr;Salzburg",
    "iso:country":"AT",
    "sg:address":"Tobelm\u00fchlstr 10",
    "sg:city":"Seeham",
    "sg:orig_category":"Wasseraufbereitung U -Reinigung",
    "sg:phone":"+43 4362 176792",
    "sg:postcode":"5164",
    "sg:province":"Salzburg",
    "wof:name":"Strasser Josef KG",
    "wof:placetype":"venue"
},
  "geometry": {"coordinates":[13.078578949,47.9681854248],"type":"Point"}
}