{
  "type": "Feature",
  "properties": {
    "addr:full":"Albrechtg 7 Graz Steiermark 8010",
    "addr:housenumber":"7",
    "addr:postcode":"8010",
    "addr:street":"Albrechtg",
    "iso:country":"AT",
    "sg:address":"Albrechtg 7",
    "sg:city":"Graz",
    "sg:orig_category":"Medizinische Beratung",
    "sg:phone":"+43 316 579996",
    "sg:postcode":"8010",
    "sg:province":"Steiermark",
    "wof:name":"Medizinische Gesellschaft f Inkontinenzhilfe \u00f6sterreich",
    "wof:placetype":"venue"
},
  "geometry": {"coordinates":[15.4368677139,47.0696105957],"type":"Point"}
}