{
  "type": "Feature",
  "properties": {
    "addr:full":"Gutenbrunner Str 1 Baden Nieder\u00f6sterreich 2500",
    "addr:housenumber":"1",
    "addr:postcode":"2500",
    "addr:street":"Str;Niederoesterreich",
    "iso:country":"AT",
    "sg:address":"Gutenbrunner Str 1",
    "sg:city":"Baden",
    "sg:orig_category":"Maschinenhandel",
    "sg:phone":"+43 664 4301047",
    "sg:postcode":"2500",
    "sg:province":"Nieder\u00f6sterreich",
    "wof:name":"WIESER Maschinen GesmbH",
    "wof:placetype":"venue"
},
  "geometry": {"coordinates":[16.2299861908,48.0067214966],"type":"Point"}
}