{
  "type": "Feature",
  "properties": {
    "iso:country":"AT",
    "sg:address":"Annenstr 25",
    "sg:city":"Graz",
    "sg:orig_category":"Werbeagenturen",
    "sg:phone":"+43 316 20917",
    "sg:postcode":"8020",
    "sg:province":"Steiermark",
    "wof:name":"GMK Gesellschaft f Marketing und Kommunikation mbH",
    "wof:placetype":"venue"
},
  "geometry": {"coordinates":[15.4278154373,47.0709762573],"type":"Point"}
}