{
  "type": "Feature",
  "properties": {
    "iso:country":"AT",
    "sg:address":"Josefig 2",
    "sg:city":"F\u00fcrstenfeld",
    "sg:orig_category":"Tischlereien",
    "sg:phone":"+43 4333 8252475",
    "sg:postcode":"8280",
    "sg:province":"Steiermark",
    "wof:name":"Herbsthofer Egid",
    "wof:placetype":"venue"
},
  "geometry": {"coordinates":[16.0724925995,47.0515823364],"type":"Point"}
}