{
  "type": "Feature",
  "properties": {
    "iso:country":"AT",
    "sg:address":"Lunzerstr 64",
    "sg:orig_category":"Dosieranlagen U -Pumpen",
    "sg:phone":"+43 4373 269898368",
    "sg:postcode":"4031",
    "wof:name":"Eurodos Dosiertechnik GmbH",
    "wof:placetype":"venue"
},
  "geometry": {"coordinates":[14.3401556015,48.2647514343],"type":"Point"}
}