{
  "type": "Feature",
  "properties": {
    "iso:country":"AT",
    "sg:address":"Kellnerfeldstr 626",
    "sg:city":"Kaprun",
    "sg:orig_category":"Pensionen / Privatzimmer",
    "sg:phone":"+43 6547 8866",
    "sg:postcode":"5710",
    "sg:province":"Salzburg",
    "wof:name":"Katherinenhof Inh Fam Schmidbauer",
    "wof:placetype":"venue"
},
  "geometry": {"coordinates":[12.7551755905,47.2681236267],"type":"Point"}
}