{
  "type": "Feature",
  "properties": {
    "addr:full":"Rohrweg 19 Mittelberg Vorarlberg 6993",
    "addr:housenumber":"19",
    "addr:postcode":"6993",
    "addr:street":"Rohrweg",
    "iso:country":"AT",
    "sg:address":"Rohrweg 19",
    "sg:city":"Mittelberg",
    "sg:orig_category":"Pensionen / Privatzimmer",
    "sg:phone":"+43 4355 175132",
    "sg:postcode":"6993",
    "sg:province":"Vorarlberg",
    "wof:name":"Berghaus Sonnenuhr",
    "wof:placetype":"venue"
},
  "geometry": {"coordinates":[10.1602430344,47.3375205994],"type":"Point"}
}