{
  "type": "Feature",
  "properties": {
    "iso:country":"AT",
    "sg:address":"Gottestaler Str 39",
    "sg:city":"Wernberg",
    "sg:orig_category":"Pensionen / Privatzimmer",
    "sg:phone":"+43 4252 2752",
    "sg:postcode":"9241",
    "sg:province":"K\u00e4rnten",
    "wof:name":"Ulbing Hans",
    "wof:placetype":"venue"
},
  "geometry": {"coordinates":[13.9433479309,46.6090621948],"type":"Point"}
}