{
  "type": "Feature",
  "properties": {
    "iso:country":"AT",
    "sg:address":"Max Ott-Pl 6",
    "sg:city":"Salzburg",
    "sg:orig_category":"Nachhilfe U Lernbetreuung",
    "sg:phone":"+43 4366 2881988",
    "sg:postcode":"5020",
    "sg:province":"Salzburg",
    "wof:name":"Salzburger Lernzentrum",
    "wof:placetype":"venue"
},
  "geometry": {"coordinates":[13.0411968231,47.8080978394],"type":"Point"}
}