{
  "type": "Feature",
  "properties": {
    "iso:country":"AT",
    "sg:address":"Andechsstr 44",
    "sg:city":"Innsbruck",
    "sg:orig_category":"Friseure U Frisiersalons",
    "sg:phone":"+43 4351 2393955",
    "sg:postcode":"6020",
    "sg:province":"Tirol",
    "wof:name":"Haardesign Turri",
    "wof:placetype":"venue"
},
  "geometry": {"coordinates":[11.4203567505,47.2686309814],"type":"Point"}
}