{
  "type": "Feature",
  "properties": {
    "iso:country":"AT",
    "sg:address":"Steinfelden 26",
    "sg:city":"Scharnstein",
    "sg:orig_category":"Badezimmer U Badezimmereinrichtungen",
    "sg:phone":"+43 4376 152300",
    "sg:postcode":"4644",
    "sg:province":"Ober\u00f6sterreich",
    "wof:name":"MIRABELLA BAD - Braunesberger Fred F GmbH",
    "wof:placetype":"venue"
},
  "geometry": {"coordinates":[13.9911575317,47.9157066345],"type":"Point"}
}