{
  "type": "Feature",
  "properties": {
    "iso:country":"AT",
    "sg:address":"Meinhardstr 5a",
    "sg:city":"Innsbruck",
    "sg:classifiers":[
        {
            "category":"Professional",
            "type":"Services"
        }
    ],
    "sg:phone":"+43 5 010027300",
    "sg:postcode":"6020",
    "sg:province":"Tirol",
    "sg:tags":[
        "leasing"
    ],
    "wof:name":"Immorent West GesmbH",
    "wof:placetype":"venue"
},
  "geometry": {"coordinates":[11.3991918564,47.2660331726],"type":"Point"}
}