{
  "type": "Feature",
  "properties": {
    "addr:full":"Linzer Str 18 Marchtrenk Ober\u00f6sterreich 4614",
    "addr:housenumber":"18",
    "addr:postcode":"4614",
    "addr:street":"Linzer Str",
    "iso:country":"AT",
    "sg:address":"Linzer Str 18",
    "sg:city":"Marchtrenk",
    "sg:orig_category":"Friseure U Frisiersalons",
    "sg:phone":"+43 4372 4350585",
    "sg:postcode":"4614",
    "sg:province":"Ober\u00f6sterreich",
    "wof:name":"Friseursalon Edith",
    "wof:placetype":"venue"
},
  "geometry": {"coordinates":[14.1131229401,48.1901855469],"type":"Point"}
}