{
  "type": "Feature",
  "properties": {
    "addr:full":"Schellingg 5 Wien Wien 1010",
    "addr:housenumber":"5",
    "addr:postcode":"1010",
    "addr:street":"Schellingg",
    "iso:country":"AT",
    "sg:address":"Schellingg 5",
    "sg:city":"Wien",
    "sg:orig_category":"Elektronische Bauelemente U Bauteile",
    "sg:phone":"+43 1 5125450",
    "sg:postcode":"1010",
    "sg:province":"Wien",
    "wof:name":"Behage WarenhandelsgesmbH",
    "wof:placetype":"venue"
},
  "geometry": {"coordinates":[16.3754749298,48.2043838501],"type":"Point"}
}