{
  "type": "Feature",
  "properties": {
    "iso:country":"AT",
    "sg:address":"Pfarrg 12",
    "sg:city":"Hollabrunn",
    "sg:orig_category":"Friseure U Frisiersalons",
    "sg:phone":"+43 2952 2363",
    "sg:postcode":"2020",
    "sg:province":"Nieder\u00f6sterreich",
    "wof:name":"Modefriseur Elfi - Babinsky Elfriede",
    "wof:placetype":"venue"
},
  "geometry": {"coordinates":[16.0788230896,48.5610847473],"type":"Point"}
}