{
  "type": "Feature",
  "properties": {
    "addr:full":"Johann-Strau\u00df-Str 1 Wels Ober\u00f6sterreich 4600",
    "addr:housenumber":"1",
    "addr:postcode":"4600",
    "addr:street":"Johann-Strauss-Str;Oberoesterreich",
    "iso:country":"AT",
    "sg:address":"Johann-Strau\u00df-Str 1",
    "sg:city":"Wels",
    "sg:orig_category":"Bauunternehmen",
    "sg:phone":"+43 4372 42454590",
    "sg:postcode":"4600",
    "sg:province":"Ober\u00f6sterreich",
    "wof:name":"Gugenberger Dipl Ing Hoch- u Tiefbau GesmbH",
    "wof:placetype":"venue"
},
  "geometry": {"coordinates":[14.0101337433,48.1636238098],"type":"Point"}
}