{
  "type": "Feature",
  "properties": {
    "addr:full":"Kaiser-Franz-Josef-Kai 2 Graz Steiermark 8010",
    "addr:housenumber":"2",
    "addr:postcode":"8010",
    "addr:street":"Kaiser-Franz-Josef-Kai",
    "iso:country":"AT",
    "sg:address":"Kaiser-Franz-Josef-Kai 2",
    "sg:city":"Graz",
    "sg:orig_category":"Familien / Beratung",
    "sg:phone":"+43 4331 68296330",
    "sg:postcode":"8010",
    "sg:province":"Steiermark",
    "wof:name":"Pflegeelternverein Steiermark - Kinder- u Jugendf\u00f6rderung",
    "wof:placetype":"venue"
},
  "geometry": {"coordinates":[15.4356813431,47.0711135864],"type":"Point"}
}