{
  "type": "Feature",
  "properties": {
    "iso:country":"AT",
    "sg:address":"Wiener G 31",
    "sg:city":"Perchtoldsdorf",
    "sg:classifiers":[
        {
            "category":"Professional",
            "subcategory":"Computer Services",
            "type":"Services"
        }
    ],
    "sg:phone":"+43 4318 652915",
    "sg:postcode":"2380",
    "sg:province":"Nieder\u00f6sterreich",
    "sg:tags":[
        "software"
    ],
    "wof:name":"P&P Software u Consulting GmbH",
    "wof:placetype":"venue"
},
  "geometry": {"coordinates":[16.2680835724,48.1221122742],"type":"Point"}
}