{
  "type": "Feature",
  "properties": {
    "addr:full":"Hinterstein 8 Bad Ischl Ober\u00f6sterreich 4820",
    "addr:housenumber":"8",
    "addr:postcode":"4820",
    "addr:street":"Hinterstein;Oberoesterreich",
    "iso:country":"AT",
    "sg:address":"Hinterstein 8",
    "sg:city":"Bad Ischl",
    "sg:orig_category":"Pensionen / Privatzimmer",
    "sg:phone":"+43 6132 23228",
    "sg:postcode":"4820",
    "sg:province":"Ober\u00f6sterreich",
    "wof:name":"Sams Christine",
    "wof:placetype":"venue"
},
  "geometry": {"coordinates":[13.6420097351,47.7075805664],"type":"Point"}
}