{
  "type": "Feature",
  "properties": {
    "addr:full":"Neusetzg 7/15 Wien Wien 1100",
    "addr:housenumber":"7 / 15",
    "addr:postcode":"1100",
    "addr:street":"Neusetzg",
    "iso:country":"AT",
    "sg:address":"Neusetzg 7/15",
    "sg:city":"Wien",
    "sg:orig_category":"Architekten",
    "sg:phone":"+43 1 6076169",
    "sg:postcode":"1100",
    "sg:province":"Wien",
    "wof:name":"Pretsch Robert Arch Dipl-Ing",
    "wof:placetype":"venue"
},
  "geometry": {"coordinates":[16.37799263,48.1724357605],"type":"Point"}
}