{
  "type": "Feature",
  "properties": {
    "addr:full":"Lassigg 35 Imst Tirol 6460",
    "addr:housenumber":"35",
    "addr:postcode":"6460",
    "addr:street":"Lassigg;Tirol",
    "iso:country":"AT",
    "sg:address":"Lassigg 35",
    "sg:city":"Imst",
    "sg:orig_category":"Galerien",
    "sg:phone":"+43 5412 64444",
    "sg:postcode":"6460",
    "sg:province":"Tirol",
    "wof:name":"Galerie Peintner",
    "wof:placetype":"venue"
},
  "geometry": {"coordinates":[10.7420892715,47.2530670166],"type":"Point"}
}