{
  "type": "Feature",
  "properties": {
    "addr:full":"TVS-Str 2 Guntramsdorf Nieder\u00f6sterreich 2353",
    "addr:housenumber":"2",
    "addr:postcode":"2353",
    "addr:street":"Tvs-Str",
    "iso:country":"AT",
    "sg:address":"TVS-Str 2",
    "sg:city":"Guntramsdorf",
    "sg:orig_category":"Speditionen",
    "sg:phone":"+43 4322 368080",
    "sg:postcode":"2353",
    "sg:province":"Nieder\u00f6sterreich",
    "wof:name":"TVS Transport Vermittlungs- u SpeditionsgesmbH",
    "wof:placetype":"venue"
},
  "geometry": {"coordinates":[16.3092899323,48.067615509],"type":"Point"}
}