{
  "type": "Feature",
  "properties": {
    "addr:full":"12.-Februar-Str 6 Kapfenberg Steiermark 8605",
    "addr:housenumber":"6",
    "addr:postcode":"8605",
    "addr:street":"12.-Februar-Str",
    "iso:country":"AT",
    "sg:address":"12.-Februar-Str 6",
    "sg:city":"Kapfenberg",
    "sg:orig_category":"Fu\u00c3\u0178pflege U Fu\u00c3\u0178pflegesalons",
    "sg:phone":"+43 4338 6226927",
    "sg:postcode":"8605",
    "sg:province":"Steiermark",
    "wof:name":"Bauer Roswitha - Mobile Fu\u00dfpflege",
    "wof:placetype":"venue"
},
  "geometry": {"coordinates":[15.2881450653,47.4397087097],"type":"Point"}
}