{
  "type": "Feature",
  "properties": {
    "addr:full":"Herbert-B\u00f6ckl-G 10 Liebenau Steiermark 8041",
    "addr:housenumber":"10",
    "addr:postcode":"8041",
    "addr:street":"Herbert-Boeckl-G",
    "iso:country":"AT",
    "sg:address":"Herbert-B\u00f6ckl-G 10",
    "sg:city":"Liebenau",
    "sg:orig_category":"Putze",
    "sg:phone":"+43 4331 64725920",
    "sg:postcode":"8041",
    "sg:province":"Steiermark",
    "wof:name":"ALL-HA-BAU GesmbH",
    "wof:placetype":"venue"
},
  "geometry": {"coordinates":[15.4693021774,47.0347557068],"type":"Point"}
}