{
  "type": "Feature",
  "properties": {
    "addr:full":"Thomas-Koschat-Str 6 Maria Rain K\u00e4rnten 9161",
    "addr:housenumber":"6",
    "addr:postcode":"9161",
    "addr:street":"Thomas-Koschat-Str;Kaernten",
    "iso:country":"AT",
    "sg:address":"Thomas-Koschat-Str 6",
    "sg:city":"Maria Rain",
    "sg:orig_category":"Tischlereien",
    "sg:phone":"+43 4220 28000",
    "sg:postcode":"9161",
    "sg:province":"K\u00e4rnten",
    "wof:name":"Suppanz Albert",
    "wof:placetype":"venue"
},
  "geometry": {"coordinates":[14.2785158157,46.5691490173],"type":"Point"}
}