{
  "type": "Feature",
  "properties": {
    "addr:full":"Villenstr 2 Deutschlandsberg Steiermark 8530",
    "addr:housenumber":"2",
    "addr:postcode":"8530",
    "addr:street":"Villenstr",
    "iso:country":"AT",
    "sg:address":"Villenstr 2",
    "sg:city":"Deutschlandsberg",
    "sg:orig_category":"Lebens- U Sozialberatung",
    "sg:phone":"+43 4334 625439",
    "sg:postcode":"8530",
    "sg:province":"Steiermark",
    "wof:name":"LFI-Aktivgruppe",
    "wof:placetype":"venue"
},
  "geometry": {"coordinates":[15.2123498917,46.8176879883],"type":"Point"}
}