{
  "type": "Feature",
  "properties": {
    "iso:country":"AT",
    "sg:address":"Lindeng 61",
    "sg:city":"Wien",
    "sg:orig_category":"Psychotherapie",
    "sg:phone":"+43 1 5232103",
    "sg:postcode":"1070",
    "sg:province":"Wien",
    "wof:name":"Schrage Margit",
    "wof:placetype":"venue"
},
  "geometry": {"coordinates":[16.3447055817,48.199092865],"type":"Point"}
}