{
  "type": "Feature",
  "properties": {
    "addr:full":"Handelsstr 4/2 Eisenstadt Burgenland 7000",
    "addr:housenumber":"4 / 2",
    "addr:postcode":"7000",
    "addr:street":"Handelsstr",
    "iso:country":"AT",
    "sg:address":"Handelsstr 4/2",
    "sg:city":"Eisenstadt",
    "sg:classifiers":[
        {
            "category":"Professional",
            "type":"Services"
        }
    ],
    "sg:phone":"+43 5 010076796",
    "sg:postcode":"7000",
    "sg:province":"Burgenland",
    "sg:tags":[
        "leasing"
    ],
    "wof:name":"EBV Leasing GesmbH",
    "wof:placetype":"venue"
},
  "geometry": {"coordinates":[16.5317249298,47.8287200928],"type":"Point"}
}