{
  "type": "Feature",
  "properties": {
    "addr:full":"Dornbacher Str 88 Wien Wien 1170",
    "addr:postcode":"1170",
    "addr:street":"Str 88",
    "iso:country":"AT",
    "sg:address":"Dornbacher Str 88",
    "sg:city":"Wien",
    "sg:orig_category":"Filmproduktionen",
    "sg:phone":"+43 1 48950270",
    "sg:postcode":"1170",
    "sg:province":"Wien",
    "wof:name":"Fernsehfilmproduktion Dr Heinz Scheiderbauer GesmbH",
    "wof:placetype":"venue"
},
  "geometry": {"coordinates":[16.2934455872,48.2321472168],"type":"Point"}
}