{
  "type": "Feature",
  "properties": {
    "iso:country":"AT",
    "sg:address":"Allerheiligenpl 1",
    "sg:city":"Wien",
    "sg:orig_category":"Friseure U Frisiersalons",
    "sg:phone":"+43 4313 322806",
    "sg:postcode":"1200",
    "sg:province":"Wien",
    "wof:name":"Friseur am Park",
    "wof:placetype":"venue"
},
  "geometry": {"coordinates":[16.3848590851,48.2372550964],"type":"Point"}
}