{
  "type": "Feature",
  "properties": {
    "iso:country":"AT",
    "sg:address":"Mariahilfer Strasse 121a",
    "sg:city":"Wien",
    "sg:classifiers":[
        {
            "category":"Manufacturing",
            "subcategory":"Jewelry",
            "type":"Manufacturing & Wholesale Goods"
        }
    ],
    "sg:phone":"+43 1 5963116",
    "sg:postcode":"1060",
    "sg:province":"Wien",
    "sg:tags":[
        "diamond",
        "jewellery",
        "diamonds"
    ],
    "sg:website":"gold.co.at",
    "wof:name":"Gold Impex HandelsgesmbH",
    "wof:placetype":"venue"
},
  "geometry": {"coordinates":[16.3414382935,48.1960754395],"type":"Point"}
}