{
  "type": "Feature",
  "properties": {
    "addr:full":"Nr 11 Rosenau Schlo\u00df Nieder\u00f6sterreich 3924",
    "addr:postcode":"3924",
    "addr:street":"Nr;Rosenau;Niederoesterreich",
    "iso:country":"AT",
    "sg:address":"Nr 11",
    "sg:city":"Rosenau Schlo\u00df",
    "sg:orig_category":"Museen / Ausstellungen",
    "sg:phone":"+43 2822 51441",
    "sg:postcode":"3924",
    "sg:province":"Nieder\u00f6sterreich",
    "wof:name":"M\u00e4rchenhaus & Puppenmuseum",
    "wof:placetype":"venue"
},
  "geometry": {"coordinates":[-118.89874267579999,46.7143325806],"type":"Point"}
}