{
  "type": "Feature",
  "properties": {
    "addr:full":"Arnbach 27 Sillian Tirol 9920",
    "addr:housenumber":"27",
    "addr:postcode":"9920",
    "addr:street":"Arnbach;Tirol",
    "iso:country":"AT",
    "sg:address":"Arnbach 27",
    "sg:city":"Sillian",
    "sg:orig_category":"Appartements / Ferienwohnungen",
    "sg:phone":"+43 4842 6277",
    "sg:postcode":"9920",
    "sg:province":"Tirol",
    "wof:name":"Pranter Josef",
    "wof:placetype":"venue"
},
  "geometry": {"coordinates":[12.3908557892,46.7448654175],"type":"Point"}
}