{
  "type": "Feature",
  "properties": {
    "addr:full":"Heiliggeiststr 1 Innsbruck Tirol 6020",
    "addr:housenumber":"1",
    "addr:postcode":"6020",
    "addr:street":"Heiliggeiststr;Tirol",
    "iso:country":"AT",
    "sg:address":"Heiliggeiststr 1",
    "sg:city":"Innsbruck",
    "sg:orig_category":"Weiterbildungsinstitute M Allg U Berufl Bildungsangebot",
    "sg:phone":"+43 676 3231872",
    "sg:postcode":"6020",
    "sg:province":"Tirol",
    "wof:name":"Natopia - Institut f Didaktik",
    "wof:placetype":"venue"
},
  "geometry": {"coordinates":[11.3955154419,47.2614173889],"type":"Point"}
}