{
  "type": "Feature",
  "properties": {
    "addr:full":"Hauptstrasse 26 Gloggnitz Nieder\u00f6sterreich 2640",
    "addr:housenumber":"26",
    "addr:postcode":"2640",
    "addr:street":"Hauptstrasse",
    "iso:country":"AT",
    "sg:address":"Hauptstrasse 26",
    "sg:city":"Gloggnitz",
    "sg:classifiers":[
        {
            "category":"Professional",
            "subcategory":"Advertising",
            "type":"Services"
        }
    ],
    "sg:phone":"+43 2662 42424",
    "sg:postcode":"2640",
    "sg:province":"Nieder\u00f6sterreich",
    "sg:tags":[
        "column",
        "made",
        "metal"
    ],
    "wof:name":"Leskovar Ges.m.b.H.",
    "wof:placetype":"venue"
},
  "geometry": {"coordinates":[15.9359025955,47.6760826111],"type":"Point"}
}