{
  "type": "Feature",
  "properties": {
    "addr:full":"Wiesbergg 7 Wien Wien 1160",
    "addr:housenumber":"7",
    "addr:postcode":"1160",
    "addr:street":"Wiesbergg",
    "iso:country":"AT",
    "sg:address":"Wiesbergg 7",
    "sg:city":"Wien",
    "sg:orig_category":"Hauptschulen",
    "sg:phone":"+43 1 4931410",
    "sg:postcode":"1160",
    "sg:province":"Wien",
    "wof:name":"Schulen d Stadt Wien",
    "wof:placetype":"venue"
},
  "geometry": {"coordinates":[16.3081264496,48.2090988159],"type":"Point"}
}