{
  "type": "Feature",
  "properties": {
    "iso:country":"AT",
    "sg:address":"Brolsstr 11-15",
    "sg:city":"Altach",
    "sg:orig_category":"Installationsunternehmen",
    "sg:phone":"+43 5576 724830",
    "sg:postcode":"6844",
    "sg:province":"Vorarlberg",
    "wof:name":"H\u00f6rburger GmbH",
    "wof:placetype":"venue"
},
  "geometry": {"coordinates":[9.646613121,47.3530197144],"type":"Point"}
}