{
  "type": "Feature",
  "properties": {
    "addr:full":"Waagpl 7/3 Klagenfurt K\u00e4rnten 9020",
    "addr:housenumber":"7 / 3",
    "addr:postcode":"9020",
    "addr:street":"Waagpl;Kaernten",
    "iso:country":"AT",
    "sg:address":"Waagpl 7/3",
    "sg:city":"Klagenfurt",
    "sg:orig_category":"Werbegrafik- U Grafik-Design",
    "sg:phone":"+43 4346 3501500",
    "sg:postcode":"9020",
    "sg:province":"K\u00e4rnten",
    "wof:name":"Lions Design",
    "wof:placetype":"venue"
},
  "geometry": {"coordinates":[14.311712265,46.6264762878],"type":"Point"}
}