{
  "type": "Feature",
  "properties": {
    "addr:full":"Feldg 34 Bruck an der Leitha Nieder\u00f6sterreich 2460",
    "addr:housenumber":"34",
    "addr:postcode":"2460",
    "addr:street":"Feldg",
    "iso:country":"AT",
    "sg:address":"Feldg 34",
    "sg:city":"Bruck an der Leitha",
    "sg:orig_category":"Elektroinstallationsunternehmen",
    "sg:phone":"+43 2162 636580",
    "sg:postcode":"2460",
    "sg:province":"Nieder\u00f6sterreich",
    "wof:name":"Strohmayer Siegfried Ing",
    "wof:placetype":"venue"
},
  "geometry": {"coordinates":[16.7784805298,48.0248832703],"type":"Point"}
}