{
  "type": "Feature",
  "properties": {
    "iso:country":"AT",
    "sg:address":"Obere Leiten 266",
    "sg:city":"Ramsau am Dachstein",
    "sg:orig_category":"Pensionen / Privatzimmer",
    "sg:phone":"+43 4336 87810910",
    "sg:postcode":"8972",
    "sg:province":"Steiermark",
    "wof:name":"Pension Concordia Josef Putz",
    "wof:placetype":"venue"
},
  "geometry": {"coordinates":[13.6962718964,47.4168128967],"type":"Point"}
}