{
  "type": "Feature",
  "properties": {
    "addr:full":"R\u00f6merweg 27/Haus 8 Brunn am Gebirge Nieder\u00f6sterreich 2345",
    "addr:housenumber":"27 / haus 8",
    "addr:postcode":"2345",
    "addr:street":"Roemerweg",
    "iso:country":"AT",
    "sg:address":"R\u00f6merweg 27/Haus 8",
    "sg:city":"Brunn am Gebirge",
    "sg:orig_category":"Werbeagenturen",
    "sg:phone":"+43 4322 36379969",
    "sg:postcode":"2345",
    "sg:province":"Nieder\u00f6sterreich",
    "wof:name":"Matyasek Annette - Werbemanagement",
    "wof:placetype":"venue"
},
  "geometry": {"coordinates":[16.2839355469,48.107170105],"type":"Point"}
}