{
  "type": "Feature",
  "properties": {
    "iso:country":"AT",
    "sg:address":"Ennser Str. 14",
    "sg:city":"Steyr",
    "sg:classifiers":[
        {
            "category":"Professional",
            "subcategory":"Engineering",
            "type":"Services"
        }
    ],
    "sg:phone":"+43 4372 528980",
    "sg:postcode":"4400",
    "sg:province":"Ober\u00f6sterreich",
    "sg:tags":[
        "machine",
        "-",
        "mechanical"
    ],
    "wof:name":"GFM GMBH",
    "wof:placetype":"venue"
},
  "geometry": {"coordinates":[14.4207706451,48.0567169189],"type":"Point"}
}