{
  "type": "Feature",
  "properties": {
    "addr:full":"Bundesstr 401 Bad Hofgastein Salzburg 5630",
    "addr:housenumber":"401",
    "addr:postcode":"5630",
    "addr:street":"Salzburg",
    "iso:country":"AT",
    "sg:address":"Bundesstr 401",
    "sg:city":"Bad Hofgastein",
    "sg:orig_category":"Autobusunternehmen",
    "sg:phone":"+43 6432 3000",
    "sg:postcode":"5630",
    "sg:province":"Salzburg",
    "wof:name":"Rainer Reisen GesmbH & Co KG",
    "wof:placetype":"venue"
},
  "geometry": {"coordinates":[13.1028347015,47.1707115173],"type":"Point"}
}