{
  "type": "Feature",
  "properties": {
    "addr:full":"Feldkirchenstr 8-12 Kalsdorf Steiermark 8401",
    "addr:housenumber":"8-12",
    "addr:postcode":"8401",
    "iso:country":"AT",
    "sg:address":"Feldkirchenstr 8-12",
    "sg:city":"Kalsdorf",
    "sg:classifiers":[
        {
            "category":"Recreation",
            "subcategory":"Theme Park",
            "type":"Entertainment"
        }
    ],
    "sg:phone":"+43 3135 564100",
    "sg:postcode":"8401",
    "sg:province":"Steiermark",
    "sg:tags":[
        "stahl"
    ],
    "wof:name":"BSS-Baustahlservice GesmbH",
    "wof:placetype":"venue"
},
  "geometry": {"coordinates":[15.4613113403,46.9671936035],"type":"Point"}
}