{
  "type": "Feature",
  "properties": {
    "iso:country":"AT",
    "sg:address":"Schwimmbadstr 164",
    "sg:city":"Piesendorf",
    "sg:orig_category":"Appartements / Ferienwohnungen",
    "sg:phone":"+43 6549 72280",
    "sg:postcode":"5721",
    "sg:province":"Salzburg",
    "wof:name":"Mariandl",
    "wof:placetype":"venue"
},
  "geometry": {"coordinates":[12.7145357132,47.2893753052],"type":"Point"}
}