{
  "type": "Feature",
  "properties": {
    "addr:full":"Glantersberg 61 Hopfgarten im Brixental Tirol 6361",
    "addr:housenumber":"61",
    "addr:postcode":"6361",
    "addr:street":"Glantersberg;Tirol",
    "iso:country":"AT",
    "sg:address":"Glantersberg 61",
    "sg:city":"Hopfgarten im Brixental",
    "sg:orig_category":"Appartements / Ferienwohnungen",
    "sg:phone":"+43 5335 2873",
    "sg:postcode":"6361",
    "sg:province":"Tirol",
    "wof:name":"Ferienhof Siedler",
    "wof:placetype":"venue"
},
  "geometry": {"coordinates":[12.1464948654,47.4094352722],"type":"Point"}
}