{
  "type": "Feature",
  "properties": {
    "addr:full":"Nr 73 Arnoldstein K\u00e4rnten 9601",
    "addr:postcode":"9601",
    "addr:street":"Nr;Kaernten",
    "iso:country":"AT",
    "sg:address":"Nr 73",
    "sg:city":"Arnoldstein",
    "sg:orig_category":"Transportunternehmen",
    "sg:phone":"+43 4255 2593",
    "sg:postcode":"9601",
    "sg:province":"K\u00e4rnten",
    "wof:name":"Katholnig Hermann",
    "wof:placetype":"venue"
},
  "geometry": {"coordinates":[13.701584816,46.5500564575],"type":"Point"}
}