{
  "type": "Feature",
  "properties": {
    "iso:country":"AT",
    "sg:address":"Nr 152",
    "sg:city":"F\u00fcrstenfeld",
    "sg:orig_category":"Spenglereien",
    "sg:phone":"+43 4333 8251762",
    "sg:postcode":"8280",
    "sg:province":"Steiermark",
    "wof:name":"Gutmeier Erwin",
    "wof:placetype":"venue"
},
  "geometry": {"coordinates":[16.0748786926,47.0515441895],"type":"Point"}
}