{
  "type": "Feature",
  "properties": {
    "addr:full":"Gutenbrunner Str 12 Baden Nieder\u00f6sterreich 2500",
    "addr:housenumber":"12",
    "addr:postcode":"2500",
    "addr:street":"Str;Niederoesterreich",
    "iso:country":"AT",
    "sg:address":"Gutenbrunner Str 12",
    "sg:city":"Baden",
    "sg:orig_category":"Banken U Sparkassen",
    "sg:phone":"+43 4322 52418900",
    "sg:postcode":"2500",
    "sg:province":"Nieder\u00f6sterreich",
    "wof:name":"GE Capital Bank GmbH",
    "wof:placetype":"venue"
},
  "geometry": {"coordinates":[16.2291488647,48.0070953369],"type":"Point"}
}