{
  "type": "Feature",
  "properties": {
    "addr:full":"Nr 55 Nappersdorf Nieder\u00f6sterreich 2023",
    "addr:postcode":"2023",
    "addr:street":"Nr 55 Nappersdorf",
    "iso:country":"AT",
    "sg:address":"Nr 55",
    "sg:city":"Nappersdorf",
    "sg:orig_category":"Non-Classified Establishments",
    "sg:phone":"+43 2953 2243",
    "sg:postcode":"2023",
    "sg:province":"Nieder\u00f6sterreich",
    "wof:name":"Pfarramt",
    "wof:placetype":"venue"
},
  "geometry": {"coordinates":[16.1849422455,48.6285476685],"type":"Point"}
}