{
  "type": "Feature",
  "properties": {
    "addr:full":"Kirchengasse 18 Bad Goisern Ober\u00f6sterreich 4822",
    "addr:housenumber":"18",
    "addr:postcode":"4822",
    "addr:street":"Kirchengasse",
    "iso:country":"AT",
    "sg:address":"Kirchengasse 18",
    "sg:city":"Bad Goisern",
    "sg:orig_category":"Reisen, Tourismusinfo",
    "sg:postcode":"4822",
    "sg:province":"Ober\u00f6sterreich",
    "sg:website":"http://www.moserwirt.at",
    "wof:name":"Gasthof Moserwirt Bad Goisern, Ferien in Bad Goisern, Urlaub",
    "wof:placetype":"venue"
},
  "geometry": {"coordinates":[13.6166954041,47.6421012878],"type":"Point"}
}