{
  "type": "Feature",
  "properties": {
    "addr:full":"Kardinal Rauscher-Pl 5 Wien Wien 1150",
    "addr:housenumber":"5",
    "addr:postcode":"1150",
    "addr:street":"Rauscher-Pl",
    "iso:country":"AT",
    "sg:address":"Kardinal Rauscher-Pl 5",
    "sg:city":"Wien",
    "sg:orig_category":"Banken U Sparkassen",
    "sg:phone":"+43 1 98261610",
    "sg:postcode":"1150",
    "sg:province":"Wien",
    "wof:name":"Raiffeisenlandesbank N\u00d6-Wien AG",
    "wof:placetype":"venue"
},
  "geometry": {"coordinates":[16.324420929,48.1975440979],"type":"Point"}
}