{
  "type": "Feature",
  "properties": {
    "addr:full":"Nr 152 Finkenberg Tirol 6292",
    "addr:postcode":"6292",
    "addr:street":"Nr 152;Tirol",
    "iso:country":"AT",
    "sg:address":"Nr 152",
    "sg:city":"Finkenberg",
    "sg:orig_category":"Blumeneinzelhandel",
    "sg:phone":"+43 5285 64472",
    "sg:postcode":"6292",
    "sg:province":"Tirol",
    "wof:name":"Die Blumenwerkstatt Inh Martina Troppmair",
    "wof:placetype":"venue"
},
  "geometry": {"coordinates":[11.8239097595,47.153465271],"type":"Point"}
}