{
  "type": "Feature",
  "properties": {
    "addr:full":"Nikolaus-August-Otto-Str 3A Wiener Neustadt Nieder\u00f6sterreich 2700",
    "addr:housenumber":"3a",
    "addr:postcode":"2700",
    "addr:street":"Nikolaus-August-Otto-Str",
    "iso:country":"AT",
    "sg:address":"Nikolaus-August-Otto-Str 3A",
    "sg:city":"Wiener Neustadt",
    "sg:orig_category":"Flugschulen",
    "sg:phone":"+43 4326 2223872",
    "sg:postcode":"2700",
    "sg:province":"Nieder\u00f6sterreich",
    "wof:name":"Heli Academy Luftfahrerschule GmbH",
    "wof:placetype":"venue"
},
  "geometry": {"coordinates":[16.2479534149,47.8436508179],"type":"Point"}
}