{
  "type": "Feature",
  "properties": {
    "addr:full":"Nr 44 Hengsberg Steiermark 8411",
    "addr:postcode":"8411",
    "addr:street":"Nr",
    "iso:country":"AT",
    "sg:address":"Nr 44",
    "sg:city":"Hengsberg",
    "sg:orig_category":"Baumaschinenverleih",
    "sg:phone":"+43 3182 7630",
    "sg:postcode":"8411",
    "sg:province":"Steiermark",
    "wof:name":"Bauger\u00e4te Tillmitsch VerleihgesmbH",
    "wof:placetype":"venue"
},
  "geometry": {"coordinates":[15.4505081177,46.8692131042],"type":"Point"}
}