{
  "type": "Feature",
  "properties": {
    "addr:full":"Glocknerstr 129 Fusch an der Gro\u00dfglocknerstra\u00dfe Salzburg 5672",
    "addr:housenumber":"129",
    "addr:postcode":"5672",
    "addr:street":"Fusch;Grossglocknerstrasse Salzburg",
    "iso:country":"AT",
    "sg:address":"Glocknerstr 129",
    "sg:city":"Fusch an der Gro\u00dfglocknerstra\u00dfe",
    "sg:orig_category":"Erdbau",
    "sg:phone":"+43 4365 457333",
    "sg:postcode":"5672",
    "sg:province":"Salzburg",
    "wof:name":"Laschalt GesnbR",
    "wof:placetype":"venue"
},
  "geometry": {"coordinates":[12.8243951797,47.2667274475],"type":"Point"}
}