{
  "type": "Feature",
  "properties": {
    "addr:full":"Perfektastr 77/1 Wien Wien 1230",
    "addr:housenumber":"77 / 1",
    "addr:postcode":"1230",
    "addr:street":"Perfektastr",
    "iso:country":"AT",
    "sg:address":"Perfektastr 77/1",
    "sg:city":"Wien",
    "sg:orig_category":"Energieberatung U -Untersuchung",
    "sg:phone":"+43 1 8957932",
    "sg:postcode":"1230",
    "sg:province":"Wien",
    "wof:name":"PowerSolution Energieberatung GmbH",
    "wof:placetype":"venue"
},
  "geometry": {"coordinates":[16.3050079346,48.1364974976],"type":"Point"}
}