{
  "type": "Feature",
  "properties": {
    "addr:full":"Bundesstr 76 Wimpassing im Schwarzatale Nieder\u00f6sterreich 2632",
    "addr:housenumber":"76",
    "addr:postcode":"2632",
    "addr:street":"Bundesstr",
    "iso:country":"AT",
    "sg:address":"Bundesstr 76",
    "sg:city":"Wimpassing im Schwarzatale",
    "sg:orig_category":"Banken U Sparkassen",
    "sg:phone":"+43 4326 3037369",
    "sg:postcode":"2632",
    "sg:province":"Nieder\u00f6sterreich",
    "wof:name":"Volksbank Nieder\u00f6sterreich S\u00fcd regGenmbH",
    "wof:placetype":"venue"
},
  "geometry": {"coordinates":[16.0227108002,47.69789505],"type":"Point"}
}