{
  "type": "Feature",
  "properties": {
    "addr:full":"Bahnstr 39 Ravelsbach Nieder\u00f6sterreich 3720",
    "addr:housenumber":"39",
    "addr:postcode":"3720",
    "addr:street":"Bahnstr",
    "iso:country":"AT",
    "sg:address":"Bahnstr 39",
    "sg:city":"Ravelsbach",
    "sg:orig_category":"Feuerwehren",
    "sg:phone":"+43 2958 82222",
    "sg:postcode":"3720",
    "sg:province":"Nieder\u00f6sterreich",
    "wof:name":"Freiwillige Feuerwehr Ravelsbach",
    "wof:placetype":"venue"
},
  "geometry": {"coordinates":[15.8593225479,48.5530166626],"type":"Point"}
}