{
  "type": "Feature",
  "properties": {
    "iso:country":"AT",
    "sg:address":"Triester Str 166",
    "sg:city":"Feldkirchen",
    "sg:orig_category":"Tischlereien",
    "sg:phone":"+43 316 291268",
    "sg:postcode":"8073",
    "sg:province":"Steiermark",
    "wof:name":"Katter Josef Franz",
    "wof:placetype":"venue"
},
  "geometry": {"coordinates":[15.450838089,46.9994773865],"type":"Point"}
}