{
  "type": "Feature",
  "properties": {
    "iso:country":"AT",
    "sg:address":"Ziegeleistr 13",
    "sg:city":"Klagenfurt",
    "sg:orig_category":"Bauunternehmen",
    "sg:phone":"+43 463 713200",
    "sg:postcode":"9020",
    "sg:province":"K\u00e4rnten",
    "wof:name":"Steiner Bau GesmbH",
    "wof:placetype":"venue"
},
  "geometry": {"coordinates":[14.373175621,46.6321792603],"type":"Point"}
}