{
  "type": "Feature",
  "properties": {
    "iso:country":"AT",
    "sg:address":"Mariahilfer Str 89",
    "sg:city":"Wien",
    "sg:orig_category":"Steuerberatung",
    "sg:phone":"+43 1 6994424",
    "sg:postcode":"1060",
    "sg:province":"Wien",
    "wof:name":"Bucher Johannes Dipl-Ing",
    "wof:placetype":"venue"
},
  "geometry": {"coordinates":[16.3479766846,48.1974754333],"type":"Point"}
}