{
  "type": "Feature",
  "properties": {
    "addr:full":"Wiener Str 51 Langenlois Nieder\u00f6sterreich 3550",
    "addr:postcode":"3550",
    "addr:street":"Niederoesterreich",
    "iso:country":"AT",
    "sg:address":"Wiener Str 51",
    "sg:city":"Langenlois",
    "sg:orig_category":"Autoreparatur",
    "sg:phone":"+43 2734 24490",
    "sg:postcode":"3550",
    "sg:province":"Nieder\u00f6sterreich",
    "wof:name":"Auto-Ruiner GesmbH",
    "wof:placetype":"venue"
},
  "geometry": {"coordinates":[15.6941757202,48.4754714966],"type":"Point"}
}