{
  "type": "Feature",
  "properties": {
    "addr:full":"Sternwartestr 69 Wien Wien 1180",
    "addr:housenumber":"69",
    "addr:postcode":"1180",
    "addr:street":"Sternwartestr",
    "iso:country":"AT",
    "sg:address":"Sternwartestr 69",
    "sg:city":"Wien",
    "sg:orig_category":"Tourismusunternehmen",
    "sg:phone":"+43 1 4792808",
    "sg:postcode":"1180",
    "sg:province":"Wien",
    "wof:name":"Vienna Scenic Tours and Events - Vienna Heurigen Express",
    "wof:placetype":"venue"
},
  "geometry": {"coordinates":[16.3373622894,48.2318534851],"type":"Point"}
}