{
  "type": "Feature",
  "properties": {
    "addr:full":"Schulstr 4 B\u00fcrs Vorarlberg 6706",
    "addr:housenumber":"4",
    "addr:postcode":"6706",
    "addr:street":"Schulstr",
    "iso:country":"AT",
    "sg:address":"Schulstr 4",
    "sg:city":"B\u00fcrs",
    "sg:orig_category":"Volksschulen",
    "sg:phone":"+43 5552 66390",
    "sg:postcode":"6706",
    "sg:province":"Vorarlberg",
    "wof:name":"Volksschule",
    "wof:placetype":"venue"
},
  "geometry": {"coordinates":[9.8052663803,47.1531105042],"type":"Point"}
}