{
  "type": "Feature",
  "properties": {
    "addr:full":"Dr.-Skala-Strasse 3-5 Wien Wien 1210",
    "addr:housenumber":"3-5",
    "addr:postcode":"1210",
    "addr:street":"Dr.-Skala-Strasse",
    "iso:country":"AT",
    "sg:address":"Dr.-Skala-Strasse 3-5",
    "sg:city":"Wien",
    "sg:orig_category":"Packing Firms",
    "sg:phone":"+43 1 2927676",
    "sg:postcode":"1210",
    "sg:province":"Wien",
    "sg:website":"schreibmeier.at",
    "wof:name":"Schreibmeier & Partner GmbH",
    "wof:placetype":"venue"
},
  "geometry": {"coordinates":[16.4191150665,48.2992897034],"type":"Point"}
}