{
  "type": "Feature",
  "properties": {
    "addr:full":"M\u00e4rzstr 27 Wien Wien 1150",
    "addr:housenumber":"27",
    "addr:postcode":"1150",
    "addr:street":"Maerzstr",
    "iso:country":"AT",
    "sg:address":"M\u00e4rzstr 27",
    "sg:city":"Wien",
    "sg:orig_category":"Restaurants: Afrikanisch",
    "sg:phone":"+43 4319 238760",
    "sg:postcode":"1150",
    "sg:province":"Wien",
    "wof:name":"Feed Restaurant",
    "wof:placetype":"venue"
},
  "geometry": {"coordinates":[16.3320903778,48.2006416321],"type":"Point"}
}