{
  "type": "Feature",
  "properties": {
    "iso:country":"AT",
    "sg:address":"Hoch\u00e4ckerstr 3",
    "sg:city":"Tulln an der Donau",
    "sg:orig_category":"Tischlereien",
    "sg:phone":"+43 4322 7265065",
    "sg:postcode":"3430",
    "sg:province":"Nieder\u00f6sterreich",
    "wof:name":"Wohn- u Bettenstudio Taibel GesmbH",
    "wof:placetype":"venue"
},
  "geometry": {"coordinates":[16.0751667023,48.3214378357],"type":"Point"}
}