{
  "type": "Feature",
  "properties": {
    "iso:country":"AT",
    "sg:address":"Gablenzg 4/8",
    "sg:city":"Wien",
    "sg:classifiers":[
        {
            "category":"Professional",
            "subcategory":"Art Services",
            "type":"Services"
        }
    ],
    "sg:phone":"+43 1 4944950",
    "sg:postcode":"1160",
    "sg:province":"Wien",
    "sg:tags":[
        "designer"
    ],
    "wof:name":"Bisovsky Susanne",
    "wof:placetype":"venue"
},
  "geometry": {"coordinates":[16.3360366821,48.2043190002],"type":"Point"}
}