{
  "type": "Feature",
  "properties": {
    "iso:country":"AT",
    "sg:address":"Brauhausstr 44",
    "sg:city":"Schwechat",
    "sg:orig_category":"Apotheken",
    "sg:phone":"+43 1 70653880",
    "sg:postcode":"2320",
    "sg:province":"Nieder\u00f6sterreich",
    "wof:name":"Wallhof-Apotheke",
    "wof:placetype":"venue"
},
  "geometry": {"coordinates":[16.465549469,48.1296806335],"type":"Point"}
}