{
  "type": "Feature",
  "properties": {
    "iso:country":"AT",
    "sg:address":"Talwieseng 2",
    "sg:city":"Miesenbach",
    "sg:orig_category":"Transportunternehmen",
    "sg:phone":"+43 2632 8205",
    "sg:postcode":"2761",
    "sg:province":"Nieder\u00f6sterreich",
    "wof:name":"Wegerer Franz",
    "wof:placetype":"venue"
},
  "geometry": {"coordinates":[15.983247757,47.8706626892],"type":"Point"}
}