{
  "type": "Feature",
  "properties": {
    "addr:full":"Grazer Str 35 M\u00fcrzhofen Steiermark 8644",
    "addr:postcode":"8644",
    "addr:street":"Str 35 Muerzhofen Steiermark",
    "iso:country":"AT",
    "sg:address":"Grazer Str 35",
    "sg:city":"M\u00fcrzhofen",
    "sg:orig_category":"Baumschulen",
    "sg:phone":"+43 3864 4627",
    "sg:postcode":"8644",
    "sg:province":"Steiermark",
    "wof:name":"Pflanzenwelt Wei\u00dfenbacher",
    "wof:placetype":"venue"
},
  "geometry": {"coordinates":[15.3914222717,47.4823608398],"type":"Point"}
}