{
  "type": "Feature",
  "properties": {
    "iso:country":"AT",
    "sg:address":"Lohnau 74",
    "sg:city":"Uttendorf",
    "sg:orig_category":"Ziegeleien",
    "sg:phone":"+43 7724 34700",
    "sg:postcode":"5261",
    "sg:province":"Ober\u00f6sterreich",
    "wof:name":"Wienerberger Ziegelindustrie AG",
    "wof:placetype":"venue"
},
  "geometry": {"coordinates":[13.1169176102,48.1526031494],"type":"Point"}
}