{
  "type": "Feature",
  "properties": {
    "addr:full":"Weitmoserg 82 Wien Wien 1100",
    "addr:housenumber":"82",
    "addr:postcode":"1100",
    "addr:street":"Weitmoserg",
    "iso:country":"AT",
    "sg:address":"Weitmoserg 82",
    "sg:city":"Wien",
    "sg:orig_category":"Massagen",
    "sg:phone":"+43 1 6172306",
    "sg:postcode":"1100",
    "sg:province":"Wien",
    "wof:name":"Massageinstitut am Wienerberg",
    "wof:placetype":"venue"
},
  "geometry": {"coordinates":[16.3523254395,48.1676979065],"type":"Point"}
}