{
  "type": "Feature",
  "properties": {
    "addr:full":"Burgstall 4 Mixnitz Steiermark 8131",
    "addr:housenumber":"4",
    "addr:postcode":"8131",
    "addr:street":"Burgstall",
    "iso:country":"AT",
    "sg:address":"Burgstall 4",
    "sg:city":"Mixnitz",
    "sg:orig_category":"Forstverwaltungen",
    "sg:phone":"+43 3867 8664",
    "sg:postcode":"8131",
    "sg:province":"Steiermark",
    "wof:name":"Mayr-Melnhof-Saurau Forstbetrieb",
    "wof:placetype":"venue"
},
  "geometry": {"coordinates":[15.3676347733,47.3086738586],"type":"Point"}
}