{
  "type": "Feature",
  "properties": {
    "addr:full":"Markus-Pernhart-Str 10 Velden am W\u00f6rther See K\u00e4rnten 9220",
    "addr:housenumber":"10",
    "addr:postcode":"9220",
    "addr:street":"Markus-Pernhart-Str;Kaernten",
    "iso:country":"AT",
    "sg:address":"Markus-Pernhart-Str 10",
    "sg:city":"Velden am W\u00f6rther See",
    "sg:orig_category":"Pensionen / Privatzimmer",
    "sg:phone":"+43 4342 7428420",
    "sg:postcode":"9220",
    "sg:province":"K\u00e4rnten",
    "wof:name":"G\u00e4stehaus Fertschey",
    "wof:placetype":"venue"
},
  "geometry": {"coordinates":[14.0357751846,46.6117782593],"type":"Point"}
}