{
  "type": "Feature",
  "properties": {
    "addr:full":"Nr 7 Asperhofen Nieder\u00f6sterreich 3041",
    "addr:postcode":"3041",
    "addr:street":"Nr;Niederoesterreich",
    "iso:country":"AT",
    "sg:address":"Nr 7",
    "sg:city":"Asperhofen",
    "sg:orig_category":"Landwirtschaftliche Produkte",
    "sg:phone":"+43 2772 52115",
    "sg:postcode":"3041",
    "sg:province":"Nieder\u00f6sterreich",
    "wof:name":"Hei\u00df Maria",
    "wof:placetype":"venue"
},
  "geometry": {"coordinates":[15.9243936539,48.2437896729],"type":"Point"}
}