{
  "type": "Feature",
  "properties": {
    "addr:full":"Klosterwiesg 4 Graz Steiermark 8010",
    "addr:housenumber":"4",
    "addr:postcode":"8010",
    "addr:street":"Klosterwiesg",
    "iso:country":"AT",
    "sg:address":"Klosterwiesg 4",
    "sg:city":"Graz",
    "sg:orig_category":"Tabaktrafiken",
    "sg:phone":"+43 316 832936",
    "sg:postcode":"8010",
    "sg:province":"Steiermark",
    "wof:name":"Kocijaz G\u00fcnther",
    "wof:placetype":"venue"
},
  "geometry": {"coordinates":[15.4428749084,47.0668182373],"type":"Point"}
}