{
  "type": "Feature",
  "properties": {
    "addr:full":"M\u00fcnchner Bundesstr 107 Salzburg Salzburg 5020",
    "addr:housenumber":"107",
    "addr:postcode":"5020",
    "addr:street":"Salzburg",
    "iso:country":"AT",
    "sg:address":"M\u00fcnchner Bundesstr 107",
    "sg:city":"Salzburg",
    "sg:orig_category":"Weine / Gro\u00c3\u0178handel",
    "sg:phone":"+43 662 4214640",
    "sg:postcode":"5020",
    "sg:province":"Salzburg",
    "wof:name":"Wein Wolf Import GmbH & Co Vertriebs KG",
    "wof:placetype":"venue"
},
  "geometry": {"coordinates":[13.0433769226,47.8006744385],"type":"Point"}
}