{
  "type": "Feature",
  "properties": {
    "iso:country":"AT",
    "sg:address":"Nr. 310 ",
    "sg:city":"Schlierbach",
    "sg:classifiers":[
        {
            "category":"Utilities",
            "subcategory":"Electric",
            "type":"Services"
        }
    ],
    "sg:phone":"+43 4375 8281900",
    "sg:postcode":"4553",
    "sg:province":"Ober\u00f6sterreich",
    "sg:tags":[
        "component",
        "electronic"
    ],
    "wof:name":"EL-TEAM ELEKTRO GES.MBH",
    "wof:placetype":"venue"
},
  "geometry": {"coordinates":[14.1261034012,47.9373321533],"type":"Point"}
}