{
  "type": "Feature",
  "properties": {
    "addr:full":"Eslarng 13 Wien Wien 1030",
    "addr:housenumber":"13",
    "addr:postcode":"1030",
    "addr:street":"Eslarng",
    "iso:country":"AT",
    "sg:address":"Eslarng 13",
    "sg:city":"Wien",
    "sg:classifiers":[
        {
            "category":"Organizations",
            "subcategory":"Community Association",
            "type":"Services"
        }
    ],
    "sg:phone":"+43 1 7134838",
    "sg:postcode":"1030",
    "sg:province":"Wien",
    "sg:tags":[
        "relation",
        "public"
    ],
    "wof:name":"Mramor Brigitte",
    "wof:placetype":"venue"
},
  "geometry": {"coordinates":[16.3943157196,48.1948204041],"type":"Point"}
}