{
  "type": "Feature",
  "properties": {
    "addr:full":"Ganglgutstr. 13 Traun Ober\u00f6sterreich 4050",
    "addr:housenumber":"13",
    "addr:postcode":"4050",
    "addr:street":"Ganglgutstr.",
    "iso:country":"AT",
    "sg:address":"Ganglgutstr. 13",
    "sg:city":"Traun",
    "sg:classifiers":[
        {
            "category":"Wholesale",
            "subcategory":"Machinery & Supplies",
            "type":"Manufacturing & Wholesale Goods"
        }
    ],
    "sg:phone":"+43 4372 29702700",
    "sg:postcode":"4050",
    "sg:province":"Ober\u00f6sterreich",
    "sg:tags":[
        "-",
        "agriculture",
        "equipment"
    ],
    "wof:name":"ING. A. FRITZ VOITH GESMBH & CO KG",
    "wof:placetype":"venue"
},
  "geometry": {"coordinates":[14.2175216675,48.2125778198],"type":"Point"}
}