{
  "type": "Feature",
  "properties": {
    "addr:full":"Kaltenbachstr 62 Bad Ischl Ober\u00f6sterreich 4820",
    "addr:housenumber":"62",
    "addr:postcode":"4820",
    "addr:street":"Kaltenbachstr",
    "iso:country":"AT",
    "sg:address":"Kaltenbachstr 62",
    "sg:city":"Bad Ischl",
    "sg:orig_category":"Bergbahnen",
    "sg:phone":"+43 4361 3223788",
    "sg:postcode":"4820",
    "sg:province":"Ober\u00f6sterreich",
    "wof:name":"Katrin-Seilbahn AG",
    "wof:placetype":"venue"
},
  "geometry": {"coordinates":[13.6070575714,47.698890686],"type":"Point"}
}