{
  "type": "Feature",
  "properties": {
    "addr:full":"Gschnallenh\u00f6fe 4 Imst Tirol 6460",
    "addr:housenumber":"4",
    "addr:postcode":"6460",
    "addr:street":"Gschnallenhoefe;Tirol",
    "iso:country":"AT",
    "sg:address":"Gschnallenh\u00f6fe 4",
    "sg:city":"Imst",
    "sg:orig_category":"Tischlereien",
    "sg:phone":"+43 4367 63756901",
    "sg:postcode":"6460",
    "sg:province":"Tirol",
    "wof:name":"Huber Peter GmbH",
    "wof:placetype":"venue"
},
  "geometry": {"coordinates":[10.737487793,47.2392234802],"type":"Point"}
}