{
  "type": "Feature",
  "properties": {
    "iso:country":"AT",
    "sg:address":"Lindenbauerg 5",
    "sg:city":"Wien",
    "sg:orig_category":"Astrologie",
    "sg:phone":"+43 1 7684921",
    "sg:postcode":"1110",
    "sg:province":"Wien",
    "wof:name":"P\u00f6ffel Gerlinde Astrologin -Studio f psychologische Astrologie",
    "wof:placetype":"venue"
},
  "geometry": {"coordinates":[16.4268054962,48.1747703552],"type":"Point"}
}