{
  "type": "Feature",
  "properties": {
    "iso:country":"AT",
    "sg:address":"Hormayrg 9",
    "sg:city":"Wien",
    "sg:classifiers":[
        {
            "category":"Restaurant",
            "type":"Food & Drink"
        }
    ],
    "sg:phone":"+43 1 599100",
    "sg:postcode":"1170",
    "sg:province":"Wien",
    "sg:tags":[
        "pizzeria"
    ],
    "wof:name":"Pizza Flitzer",
    "wof:placetype":"venue"
},
  "geometry": {"coordinates":[16.3307209015,48.2196884155],"type":"Point"}
}