{
  "type": "Feature",
  "properties": {
    "addr:full":"Gentzg 103 Wien Wien 1180",
    "addr:housenumber":"103",
    "addr:postcode":"1180",
    "iso:country":"AT",
    "sg:address":"Gentzg 103",
    "sg:city":"Wien",
    "sg:orig_category":"Fleischhauereien",
    "sg:phone":"+43 1 4791545",
    "sg:postcode":"1180",
    "sg:province":"Wien",
    "wof:name":"Stephan Karl",
    "wof:placetype":"venue"
},
  "geometry": {"coordinates":[16.3342323303,48.2289733887],"type":"Point"}
}