{
  "type": "Feature",
  "properties": {
    "iso:country":"AT",
    "sg:address":"Svetelskystr 8",
    "sg:city":"Wien",
    "sg:orig_category":"Blumeneinzelhandel",
    "sg:phone":"+43 1 7670101",
    "sg:postcode":"1110",
    "sg:province":"Wien",
    "wof:name":"Floristik am Leberberg Inh Gabriele Hertl",
    "wof:placetype":"venue"
},
  "geometry": {"coordinates":[16.4637317657,48.1544265747],"type":"Point"}
}