{
  "type": "Feature",
  "properties": {
    "addr:full":"Miglberg 35 Weyregg am Attersee Ober\u00f6sterreich 4852",
    "addr:housenumber":"35",
    "addr:postcode":"4852",
    "addr:street":"Miglberg",
    "iso:country":"AT",
    "sg:address":"Miglberg 35",
    "sg:city":"Weyregg am Attersee",
    "sg:orig_category":"Appartements / Ferienwohnungen",
    "sg:phone":"+43 76643257",
    "sg:postcode":"4852",
    "sg:province":"Ober\u00f6sterreich",
    "wof:name":"Ferienhof Grabensimerl Fam Rauchenzauner",
    "wof:placetype":"venue"
},
  "geometry": {"coordinates":[13.62545681,47.9061470032],"type":"Point"}
}