{
  "type": "Feature",
  "properties": {
    "iso:country":"AT",
    "sg:address":"Reichsstr 73",
    "sg:city":"Lustenau",
    "sg:orig_category":"Autoersatzteile",
    "sg:phone":"+43 5577 88396",
    "sg:postcode":"6890",
    "sg:province":"Vorarlberg",
    "wof:name":"Off Road Shop Vorarlberg",
    "wof:placetype":"venue"
},
  "geometry": {"coordinates":[9.6556282043,47.4369125366],"type":"Point"}
}