{
  "type": "Feature",
  "properties": {
    "addr:full":"Grabenweg 3 Innsbruck Tirol 6020",
    "addr:housenumber":"3",
    "addr:postcode":"6020",
    "addr:street":"Grabenweg;Tirol",
    "iso:country":"AT",
    "sg:address":"Grabenweg 3",
    "sg:city":"Innsbruck",
    "sg:classifiers":[
        {
            "category":"Professional",
            "subcategory":"Management & Consulting",
            "type":"Services"
        }
    ],
    "sg:phone":"+43 4351 2390296",
    "sg:postcode":"6020",
    "sg:province":"Tirol",
    "wof:name":"PRISMA Zentrum f Standort- u Regionalentwicklung GmbH - Zweigniederlassung Tirol",
    "wof:placetype":"venue"
},
  "geometry": {"coordinates":[11.4337320328,47.2648735046],"type":"Point"}
}