{
  "type": "Feature",
  "properties": {
    "addr:full":"Zimmermanng 13 Wien Wien 1090",
    "addr:housenumber":"13",
    "addr:postcode":"1090",
    "addr:street":"Zimmermanng",
    "iso:country":"AT",
    "sg:address":"Zimmermanng 13",
    "sg:city":"Wien",
    "sg:orig_category":"Nachhilfe U Lernbetreuung",
    "sg:phone":"+43 1 9685844",
    "sg:postcode":"1090",
    "sg:province":"Wien",
    "wof:name":"Paedagogicum",
    "wof:placetype":"venue"
},
  "geometry": {"coordinates":[16.3432178497,48.2175979614],"type":"Point"}
}