{
  "type": "Feature",
  "properties": {
    "addr:full":"Elisabethstr 32 Graz Steiermark 8010",
    "addr:housenumber":"32",
    "addr:postcode":"8010",
    "addr:street":"Elisabethstr",
    "iso:country":"AT",
    "sg:address":"Elisabethstr 32",
    "sg:city":"Graz",
    "sg:orig_category":"Handelsagenturen",
    "sg:phone":"+43 316 327946",
    "sg:postcode":"8010",
    "sg:province":"Steiermark",
    "wof:name":"Winter E & B HandelsgesmbH",
    "wof:placetype":"venue"
},
  "geometry": {"coordinates":[15.4518518448,47.0748062134],"type":"Point"}
}