{
  "type": "Feature",
  "properties": {
    "addr:full":"Schie\u00dfstandg 10a Innsbruck Tirol 6020",
    "addr:housenumber":"10a",
    "addr:postcode":"6020",
    "addr:street":"Schiessstandg;Tirol",
    "iso:country":"AT",
    "sg:address":"Schie\u00dfstandg 10a",
    "sg:city":"Innsbruck",
    "sg:orig_category":"Transportunternehmen",
    "sg:phone":"+43 512 276158",
    "sg:postcode":"6020",
    "sg:province":"Tirol",
    "wof:name":"Holzner Wilhelm",
    "wof:placetype":"venue"
},
  "geometry": {"coordinates":[11.3779354095,47.2720069885],"type":"Point"}
}