{
  "type": "Feature",
  "properties": {
    "iso:country":"AT",
    "sg:address":"Nebingerstrasse 7a",
    "sg:city":"Linz",
    "sg:classifiers":[
        {
            "category":"Manufacturing",
            "subcategory":"Metals",
            "type":"Manufacturing & Wholesale Goods"
        }
    ],
    "sg:phone":"+43 732 664015",
    "sg:postcode":"4020",
    "sg:province":"Ober\u00f6sterreich",
    "sg:tags":[
        "processing"
    ],
    "sg:website":"bernado.at",
    "wof:name":"PWA Handelsges.m.b.H.",
    "wof:placetype":"venue"
},
  "geometry": {"coordinates":[14.3292827606,48.299079895],"type":"Point"}
}