{
  "type": "Feature",
  "properties": {
    "iso:country":"AT",
    "sg:address":"Gewerbepark 5",
    "sg:city":"Mooskirchen",
    "sg:orig_category":"Elektroinstallationsunternehmen",
    "sg:phone":"+43 3137 6137",
    "sg:postcode":"8562",
    "sg:province":"Steiermark",
    "wof:name":"Elektro Schwar & Co OEG",
    "wof:placetype":"venue"
},
  "geometry": {"coordinates":[15.2869586945,46.9819831848],"type":"Point"}
}