{
  "type": "Feature",
  "properties": {
    "addr:full":"Kaplanstrasse 1 Lambach Ober\u00f6sterreich 4650",
    "addr:housenumber":"1",
    "addr:postcode":"4650",
    "addr:street":"Kaplanstrasse",
    "iso:country":"AT",
    "sg:address":"Kaplanstrasse 1",
    "sg:city":"Lambach",
    "sg:classifiers":[
        {
            "category":"Building & Trades",
            "subcategory":"Cleaning & Sanitation",
            "type":"Services"
        }
    ],
    "sg:phone":"+43 7245 323240",
    "sg:postcode":"4650",
    "sg:province":"Ober\u00f6sterreich",
    "sg:tags":[
        "sanitary",
        "supply"
    ],
    "wof:name":"Robert Ulm GmbH",
    "wof:placetype":"venue"
},
  "geometry": {"coordinates":[13.8567781448,48.0905532837],"type":"Point"}
}