{
  "type": "Feature",
  "properties": {
    "addr:full":"Untere Teichstr 63 Graz Steiermark 8010",
    "addr:housenumber":"63",
    "addr:postcode":"8010",
    "addr:street":"Untere Teichstr",
    "iso:country":"AT",
    "sg:address":"Untere Teichstr 63",
    "sg:city":"Graz",
    "sg:orig_category":"Zahntechnische Laboratorien",
    "sg:phone":"+43 316 461813",
    "sg:postcode":"8010",
    "sg:province":"Steiermark",
    "wof:name":"Kolar Harald",
    "wof:placetype":"venue"
},
  "geometry": {"coordinates":[15.4813709259,47.07056427],"type":"Point"}
}