{
  "type": "Feature",
  "properties": {
    "addr:full":"Deutschstr 4 Wien Wien 1230",
    "addr:housenumber":"4",
    "addr:postcode":"1230",
    "addr:street":"Deutschstr",
    "iso:country":"AT",
    "sg:address":"Deutschstr 4",
    "sg:city":"Wien",
    "sg:orig_category":"Telekommunikation",
    "sg:phone":"+43 1 6163090",
    "sg:postcode":"1230",
    "sg:province":"Wien",
    "wof:name":"WNT Telecommunication",
    "wof:placetype":"venue"
},
  "geometry": {"coordinates":[16.3578224182,48.1436271667],"type":"Point"}
}