{
  "type": "Feature",
  "properties": {
    "iso:country":"AT",
    "sg:address":"Bergg 21",
    "sg:city":"Neusiedl am See",
    "sg:orig_category":"Bootsvermietung",
    "sg:phone":"+43 4321 672782",
    "sg:postcode":"7100",
    "sg:province":"Burgenland",
    "wof:name":"Baumgartner Franz",
    "wof:placetype":"venue"
},
  "geometry": {"coordinates":[16.834482193,47.9544715881],"type":"Point"}
}