{
  "type": "Feature",
  "properties": {
    "addr:full":"Autobahnsn Walserbg Wals Salzburg 5071",
    "addr:postcode":"5071",
    "addr:street":"Wals",
    "iso:country":"AT",
    "sg:address":"Autobahnsn Walserbg",
    "sg:city":"Wals",
    "sg:orig_category":"Tabaktrafiken",
    "sg:phone":"+43 662 8505250",
    "sg:postcode":"5071",
    "sg:province":"Salzburg",
    "wof:name":"Schilcher Josef",
    "wof:placetype":"venue"
},
  "geometry": {"coordinates":[13.0006475449,47.7622108459],"type":"Point"}
}