{
  "type": "Feature",
  "properties": {
    "iso:country":"AT",
    "sg:address":"H\u00f6henstr 15",
    "sg:city":"Langenlois",
    "sg:orig_category":"Baumschulen",
    "sg:phone":"+43 2734 3151",
    "sg:postcode":"3550",
    "sg:province":"Nieder\u00f6sterreich",
    "wof:name":"Ebner Robert",
    "wof:placetype":"venue"
},
  "geometry": {"coordinates":[15.67689991,48.4733161926],"type":"Point"}
}