{
  "type": "Feature",
  "properties": {
    "addr:full":"Kehlhof 33 Abtenau Salzburg 5441",
    "addr:housenumber":"33",
    "addr:postcode":"5441",
    "addr:street":"Kehlhof;Salzburg",
    "iso:country":"AT",
    "sg:address":"Kehlhof 33",
    "sg:city":"Abtenau",
    "sg:orig_category":"Appartements / Ferienwohnungen",
    "sg:phone":"+43 6243 2797",
    "sg:postcode":"5441",
    "sg:province":"Salzburg",
    "wof:name":"Katholnigg Wilhelm und Gerlinde",
    "wof:placetype":"venue"
},
  "geometry": {"coordinates":[13.3463354111,47.5727653503],"type":"Point"}
}