{
  "type": "Feature",
  "properties": {
    "addr:full":"Waldemar-Hering-Strasse 5 Oberndorf Salzburg 5110",
    "addr:housenumber":"5",
    "addr:postcode":"5110",
    "addr:street":"Waldemar-Hering-Strasse",
    "iso:country":"AT",
    "sg:address":"Waldemar-Hering-Strasse 5",
    "sg:city":"Oberndorf",
    "sg:classifiers":[
        {
            "category":"Professional",
            "subcategory":"Engineering",
            "type":"Services"
        }
    ],
    "sg:phone":"+43 6272 7634",
    "sg:postcode":"5110",
    "sg:province":"Salzburg",
    "sg:tags":[
        "length",
        "technology",
        "measurement"
    ],
    "wof:name":"Strametz Industrieelectronic",
    "wof:placetype":"venue"
},
  "geometry": {"coordinates":[12.9325675964,47.9608917236],"type":"Point"}
}