{
  "type": "Feature",
  "properties": {
    "addr:full":"Hauptstr 152 Warth Nieder\u00f6sterreich 2831",
    "addr:housenumber":"152",
    "addr:postcode":"2831",
    "addr:street":"Hauptstr",
    "iso:country":"AT",
    "sg:address":"Hauptstr 152",
    "sg:city":"Warth",
    "sg:orig_category":"Tabaktrafiken",
    "sg:phone":"+43 2629 3103",
    "sg:postcode":"2831",
    "sg:province":"Nieder\u00f6sterreich",
    "wof:name":"Fritz Helga",
    "wof:placetype":"venue"
},
  "geometry": {"coordinates":[16.1305046082,47.6614608765],"type":"Point"}
}