{
  "type": "Feature",
  "properties": {
    "addr:full":"Kr\u00e4utlerweg 18 A Salzburg Salzburg 5020",
    "addr:housenumber":"18 a",
    "addr:postcode":"5020",
    "addr:street":"Kraeutlerweg;Salzburg",
    "iso:country":"AT",
    "sg:address":"Kr\u00e4utlerweg 18 A",
    "sg:city":"Salzburg",
    "sg:orig_category":"Werbegrafik- U Grafik-Design",
    "sg:phone":"+43 662 834743",
    "sg:postcode":"5020",
    "sg:province":"Salzburg",
    "wof:name":"Dankl Heribert",
    "wof:placetype":"venue"
},
  "geometry": {"coordinates":[13.0080852509,47.7793693542],"type":"Point"}
}