{
  "type": "Feature",
  "properties": {
    "addr:full":"Wiener Strasse 7 Poysdorf Nieder\u00f6sterreich 2170",
    "addr:housenumber":"7",
    "addr:postcode":"2170",
    "addr:street":"Wiener Strasse",
    "iso:country":"AT",
    "sg:address":"Wiener Strasse 7",
    "sg:city":"Poysdorf",
    "sg:classifiers":[
        {
            "category":"Home & Garden",
            "subcategory":"Building Materials",
            "type":"Retail Goods"
        }
    ],
    "sg:phone":"+43 2552 2127",
    "sg:postcode":"2170",
    "sg:province":"Nieder\u00f6sterreich",
    "sg:tags":[
        "glass",
        "enclosures",
        "balcony"
    ],
    "wof:name":"Glas - Spiess",
    "wof:placetype":"venue"
},
  "geometry": {"coordinates":[16.6285438538,48.6659812927],"type":"Point"}
}