{
  "type": "Feature",
  "properties": {
    "addr:full":"Hofangerstr 34 Filzmoos Salzburg 5532",
    "addr:housenumber":"34",
    "addr:postcode":"5532",
    "addr:street":"Hofangerstr;Salzburg",
    "iso:country":"AT",
    "sg:address":"Hofangerstr 34",
    "sg:city":"Filzmoos",
    "sg:orig_category":"Pensionen / Privatzimmer, Appartements / Ferienwohnungen",
    "sg:phone":"+43 6453 82210",
    "sg:postcode":"5532",
    "sg:province":"Salzburg",
    "sg:website":"www.oberhofalm.at, www.oberhofgut.at",
    "wof:name":"Ferienwohnungen Oberhof",
    "wof:placetype":"venue"
},
  "geometry": {"coordinates":[13.5202980042,47.4332199097],"type":"Point"}
}