{
  "type": "Feature",
  "properties": {
    "addr:full":"Breitenseer Str 4 Wien Wien 1140",
    "addr:housenumber":"4",
    "addr:postcode":"1140",
    "addr:street":"Str",
    "iso:country":"AT",
    "sg:address":"Breitenseer Str 4",
    "sg:city":"Wien",
    "sg:orig_category":"Lebensmittel / Einzelhandel",
    "sg:phone":"+43 4317 862395",
    "sg:postcode":"1140",
    "sg:province":"Wien",
    "wof:name":"Penny Markt",
    "wof:placetype":"venue"
},
  "geometry": {"coordinates":[16.31291008,48.1993522644],"type":"Point"}
}