{
  "type": "Feature",
  "properties": {
    "addr:full":"Hauptstr 15/1 Radenthein K\u00e4rnten 9545",
    "addr:housenumber":"15 / 1",
    "addr:postcode":"9545",
    "addr:street":"Hauptstr;Kaernten",
    "iso:country":"AT",
    "sg:address":"Hauptstr 15/1",
    "sg:city":"Radenthein",
    "sg:orig_category":"Werbegrafik- U Grafik-Design",
    "sg:phone":"+43 676 7013096",
    "sg:postcode":"9545",
    "sg:province":"K\u00e4rnten",
    "wof:name":"Edgetype Grafik & Webdesign",
    "wof:placetype":"venue"
},
  "geometry": {"coordinates":[13.7058038712,46.8015975952],"type":"Point"}
}