{
  "type": "Feature",
  "properties": {
    "addr:full":"Nr 157 Lendorf K\u00e4rnten 9811",
    "addr:postcode":"9811",
    "addr:street":"Nr;Lendorf",
    "iso:country":"AT",
    "sg:address":"Nr 157",
    "sg:city":"Lendorf",
    "sg:orig_category":"Fliesen- U Plattenverlegungen",
    "sg:phone":"+43 4762 33772",
    "sg:postcode":"9811",
    "sg:province":"K\u00e4rnten",
    "wof:name":"Ha\u00dflitzer Hans",
    "wof:placetype":"venue"
},
  "geometry": {"coordinates":[13.4237203598,46.8308448792],"type":"Point"}
}