{
  "type": "Feature",
  "properties": {
    "addr:full":"Georg v Trapp-Str 16 Aigen Salzburg 5026",
    "addr:housenumber":"16",
    "addr:postcode":"5026",
    "addr:street":"Trapp-Str;Salzburg",
    "iso:country":"AT",
    "sg:address":"Georg v Trapp-Str 16",
    "sg:city":"Aigen",
    "sg:orig_category":"Architekten",
    "sg:phone":"+43 662 625236",
    "sg:postcode":"5026",
    "sg:province":"Salzburg",
    "wof:name":"Huber Peter Arch Dipl-Ing",
    "wof:placetype":"venue"
},
  "geometry": {"coordinates":[13.1170120239,47.7886009216],"type":"Point"}
}