{
  "type": "Feature",
  "properties": {
    "addr:full":"Untersbergstr 54 Gartenau-St. Leonhard Salzburg 5083",
    "addr:housenumber":"54;5083",
    "addr:street":"Untersbergstr;Leonhard Salzburg",
    "iso:country":"AT",
    "sg:address":"Untersbergstr 54",
    "sg:city":"Gartenau-St. Leonhard",
    "sg:orig_category":"Zementwerke",
    "sg:phone":"+43 4362 468810",
    "sg:postcode":"5083",
    "sg:province":"Salzburg",
    "wof:name":"Zementwerk Leube GesmbH",
    "wof:placetype":"venue"
},
  "geometry": {"coordinates":[13.0414104462,47.727558136],"type":"Point"}
}