{
  "type": "Feature",
  "properties": {
    "iso:country":"AT",
    "sg:address":"Gentzg 70",
    "sg:city":"Wien",
    "sg:orig_category":"Umwelttechnik",
    "sg:phone":"+43 1 4707528",
    "sg:postcode":"1180",
    "sg:province":"Wien",
    "wof:name":"DIGI Technologies GmbH",
    "wof:placetype":"venue"
},
  "geometry": {"coordinates":[16.3393745422,48.2279129028],"type":"Point"}
}