{
  "type": "Feature",
  "properties": {
    "addr:full":"Wolfersbergg 13/3 Wien Wien 1140",
    "addr:housenumber":"13 / 3",
    "addr:postcode":"1140",
    "addr:street":"Wolfersbergg",
    "iso:country":"AT",
    "sg:address":"Wolfersbergg 13/3",
    "sg:city":"Wien",
    "sg:orig_category":"Filmproduktionen",
    "sg:phone":"+43 664 3378429",
    "sg:postcode":"1140",
    "sg:province":"Wien",
    "wof:name":"Vlasak Ulrich",
    "wof:placetype":"venue"
},
  "geometry": {"coordinates":[16.2527351379,48.2074966431],"type":"Point"}
}