{
  "type": "Feature",
  "properties": {
    "iso:country":"AT",
    "sg:address":"Waidhofner Str 1",
    "sg:city":"Heidenreichstein",
    "sg:classifiers":[
        {
            "category":"Restaurant",
            "type":"Food & Drink"
        }
    ],
    "sg:phone":"+43 2862 589930",
    "sg:postcode":"3860",
    "sg:province":"Nieder\u00f6sterreich",
    "wof:name":"Burgst\u00fcberl Restaurant",
    "wof:placetype":"venue"
},
  "geometry": {"coordinates":[15.1223468781,48.8649597168],"type":"Point"}
}