{
  "type": "Feature",
  "properties": {
    "addr:full":"Nr 5 Natternbach Ober\u00f6sterreich 4723",
    "addr:postcode":"4723",
    "addr:street":"Nr;Oberoesterreich",
    "iso:country":"AT",
    "sg:address":"Nr 5",
    "sg:city":"Natternbach",
    "sg:orig_category":"Metallbe- U -Verarbeitung",
    "sg:phone":"+43 4372 788403",
    "sg:postcode":"4723",
    "sg:province":"Ober\u00f6sterreich",
    "wof:name":"Berndorfer Leder GmbH",
    "wof:placetype":"venue"
},
  "geometry": {"coordinates":[13.7493953705,48.396736145],"type":"Point"}
}