{
  "type": "Feature",
  "properties": {
    "iso:country":"AT",
    "sg:address":"Nr 464",
    "sg:city":"Spital am Pyhrn",
    "sg:orig_category":"Holzhandel",
    "sg:phone":"+43 7563 698",
    "sg:postcode":"4582",
    "sg:province":"Ober\u00f6sterreich",
    "wof:name":"Mitterhauser Franz",
    "wof:placetype":"venue"
},
  "geometry": {"coordinates":[14.3418207169,47.6654434204],"type":"Point"}
}