{
  "type": "Feature",
  "properties": {
    "addr:full":"Neuhof 23 Ottenschlag Nieder\u00f6sterreich 3631",
    "addr:housenumber":"23",
    "addr:postcode":"3631",
    "addr:street":"Neuhof",
    "iso:country":"AT",
    "sg:address":"Neuhof 23",
    "sg:city":"Ottenschlag",
    "sg:orig_category":"Pensionen / Privatzimmer",
    "sg:phone":"+43 4328 726686",
    "sg:postcode":"3631",
    "sg:province":"Nieder\u00f6sterreich",
    "wof:name":"Hofbauer Rudolf",
    "wof:placetype":"venue"
},
  "geometry": {"coordinates":[15.1863431931,48.4290809631],"type":"Point"}
}