{
  "type": "Feature",
  "properties": {
    "addr:full":"Theobaldgasse 19 Wien Wien 1060",
    "addr:housenumber":"19",
    "addr:postcode":"1060",
    "addr:street":"Theobaldgasse",
    "iso:country":"AT",
    "sg:address":"Theobaldgasse 19",
    "sg:city":"Wien",
    "sg:classifiers":[
        {
            "category":"Wholesale",
            "subcategory":"Medical Equipment & Supplies",
            "type":"Manufacturing & Wholesale Goods"
        }
    ],
    "sg:phone":"+43 1 205060",
    "sg:postcode":"1060",
    "sg:province":"Wien",
    "sg:tags":[
        "gastronomy",
        "entertainment"
    ],
    "sg:website":"bignet.at",
    "wof:name":"Bignet Telecommunications GmbH",
    "wof:placetype":"venue"
},
  "geometry": {"coordinates":[16.3584594727,48.2004585266],"type":"Point"}
}