{
  "type": "Feature",
  "properties": {
    "addr:full":"Sengsschmiedstr 8 Kirchdorf an der Krems Ober\u00f6sterreich 4560",
    "addr:housenumber":"8",
    "addr:postcode":"4560",
    "addr:street":"Sengsschmiedstr",
    "iso:country":"AT",
    "sg:address":"Sengsschmiedstr 8",
    "sg:city":"Kirchdorf an der Krems",
    "sg:orig_category":"Fahrschulen",
    "sg:phone":"+43 4375 8263183",
    "sg:postcode":"4560",
    "sg:province":"Ober\u00f6sterreich",
    "wof:name":"Fahrschule Staudinger",
    "wof:placetype":"venue"
},
  "geometry": {"coordinates":[14.1203708649,47.9068069458],"type":"Point"}
}