{
  "type": "Feature",
  "properties": {
    "addr:full":"Salitererg 10 Ebbs Tirol 6341",
    "addr:housenumber":"10",
    "addr:postcode":"6341",
    "addr:street":"Salitererg;Tirol",
    "iso:country":"AT",
    "sg:address":"Salitererg 10",
    "sg:city":"Ebbs",
    "sg:orig_category":"Maler, Anstreicher U Lackierer",
    "sg:phone":"+43 4353 7342476",
    "sg:postcode":"6341",
    "sg:province":"Tirol",
    "wof:name":"Kronbichler Emil",
    "wof:placetype":"venue"
},
  "geometry": {"coordinates":[12.2144241333,47.6297264099],"type":"Point"}
}