{
  "type": "Feature",
  "properties": {
    "addr:full":"Wegerichg 31 Wien Wien 1140",
    "addr:housenumber":"31",
    "addr:postcode":"1140",
    "addr:street":"Wegerichg",
    "iso:country":"AT",
    "sg:address":"Wegerichg 31",
    "sg:city":"Wien",
    "sg:orig_category":"Non-Classified Establishments",
    "sg:phone":"+43 1 9145091",
    "sg:postcode":"1140",
    "sg:province":"Wien",
    "wof:name":"Pfarramt Mutter d Gnade",
    "wof:placetype":"venue"
},
  "geometry": {"coordinates":[16.2510910034,48.2178535461],"type":"Point"}
}