{
  "type": "Feature",
  "properties": {
    "addr:full":"Innsbruck Tirol 6020",
    "addr:postcode":"6020",
    "iso:country":"AT",
    "sg:city":"Innsbruck",
    "sg:orig_category":"Lebens- U Sozialberatung",
    "sg:phone":"+43 4351 2565787",
    "sg:postcode":"6020",
    "sg:province":"Tirol",
    "wof:name":"Arbeitsgemeinschaft Mensch & Arbeit",
    "wof:placetype":"venue"
},
  "geometry": {"coordinates":[11.3913040161,47.2679977417],"type":"Point"}
}