{
  "type": "Feature",
  "properties": {
    "iso:country":"AT",
    "sg:address":"Leitermayerg 25",
    "sg:city":"Wien",
    "sg:orig_category":"Stanzformen U Stanzformenbau",
    "sg:phone":"+43 1 40859650",
    "sg:postcode":"1170",
    "sg:province":"Wien",
    "wof:name":"Cahak Laserstanzformen KG",
    "wof:placetype":"venue"
},
  "geometry": {"coordinates":[16.3362483978,48.2225227356],"type":"Point"}
}