{
  "type": "Feature",
  "properties": {
    "iso:country":"AT",
    "sg:address":"Schweizer Str 3",
    "sg:city":"Altach",
    "sg:orig_category":"Non-Classified Establishments",
    "sg:phone":"+43 5576 42010",
    "sg:postcode":"6844",
    "sg:province":"Vorarlberg",
    "wof:name":"Pfarramt",
    "wof:placetype":"venue"
},
  "geometry": {"coordinates":[9.6511898041,47.3536758423],"type":"Point"}
}