{
  "type": "Feature",
  "properties": {
    "addr:full":"Nr 77 Ossiach K\u00e4rnten 9570",
    "addr:postcode":"9570",
    "addr:street":"Nr;Kaernten",
    "iso:country":"AT",
    "sg:address":"Nr 77",
    "sg:city":"Ossiach",
    "sg:orig_category":"Pensionen / Privatzimmer",
    "sg:phone":"+43 4243 2087",
    "sg:postcode":"9570",
    "sg:province":"K\u00e4rnten",
    "wof:name":"Seehaus Kircher",
    "wof:placetype":"venue"
},
  "geometry": {"coordinates":[13.9840993881,46.6746025085],"type":"Point"}
}