{
  "type": "Feature",
  "properties": {
    "addr:full":"Nr 34 Hohenruppersdorf Nieder\u00f6sterreich 2223",
    "addr:postcode":"2223",
    "addr:street":"Nr;Hohenruppersdorf",
    "iso:country":"AT",
    "sg:address":"Nr 34",
    "sg:city":"Hohenruppersdorf",
    "sg:orig_category":"Weine / Einzelhandel",
    "sg:phone":"+43 2574 8855",
    "sg:postcode":"2223",
    "sg:province":"Nieder\u00f6sterreich",
    "wof:name":"W\u00f6tzl Richard",
    "wof:placetype":"venue"
},
  "geometry": {"coordinates":[16.6530265808,48.4634246826],"type":"Point"}
}