{
  "type": "Feature",
  "properties": {
    "addr:full":"Hauptpl 9 Leoben Steiermark 8700",
    "addr:housenumber":"9",
    "addr:postcode":"8700",
    "addr:street":"Hauptpl",
    "iso:country":"AT",
    "sg:address":"Hauptpl 9",
    "sg:city":"Leoben",
    "sg:orig_category":"Polizei U Gendarmerie",
    "sg:phone":"+43 3842 22600580",
    "sg:postcode":"8700",
    "sg:province":"Steiermark",
    "wof:name":"Polizeiwachzimmer",
    "wof:placetype":"venue"
},
  "geometry": {"coordinates":[15.0946483612,47.3799133301],"type":"Point"}
}