{
  "type": "Feature",
  "properties": {
    "iso:country":"AT",
    "sg:address":"Schlachthausgasse 1",
    "sg:city":"Feldkirchen in K\u00e4rnten",
    "sg:classifiers":[
        {
            "category":"Government",
            "subcategory":"Department Of Motor Vehicles",
            "type":"Public Place"
        }
    ],
    "sg:phone":"+43 4276 2232",
    "sg:postcode":"9560",
    "sg:province":"K\u00e4rnten",
    "sg:tags":[
        "truck",
        "purpose"
    ],
    "wof:name":"Seebacher Transporte Ges.m.b.H.",
    "wof:placetype":"venue"
},
  "geometry": {"coordinates":[14.0967063904,46.7251739502],"type":"Point"}
}