{
  "type": "Feature",
  "properties": {
    "addr:full":"Blumeng 6 Kufstein Tirol 6330",
    "addr:housenumber":"6",
    "addr:postcode":"6330",
    "addr:street":"Blumeng;Tirol",
    "iso:country":"AT",
    "sg:address":"Blumeng 6",
    "sg:city":"Kufstein",
    "sg:orig_category":"Musikgruppen",
    "sg:phone":"+43 4366 01141969",
    "sg:postcode":"6330",
    "sg:province":"Tirol",
    "wof:name":"Planet Music - Stefan Fritz",
    "wof:placetype":"venue"
},
  "geometry": {"coordinates":[12.1711959839,47.5867958069],"type":"Point"}
}