{
  "type": "Feature",
  "properties": {
    "addr:full":"Nr 156 Weitersfeld Nieder\u00f6sterreich 2084",
    "addr:postcode":"2084",
    "addr:street":"Nr 156",
    "iso:country":"AT",
    "sg:address":"Nr 156",
    "sg:city":"Weitersfeld",
    "sg:orig_category":"Spenglereien",
    "sg:phone":"+43 2948 8239",
    "sg:postcode":"2084",
    "sg:province":"Nieder\u00f6sterreich",
    "wof:name":"Vrbicky Ronald",
    "wof:placetype":"venue"
},
  "geometry": {"coordinates":[15.8108301163,48.7819595337],"type":"Point"}
}