{
  "type": "Feature",
  "properties": {
    "addr:full":"Obere Hauptstr 72 Bad Pirawarth Nieder\u00f6sterreich 2222",
    "addr:housenumber":"72",
    "addr:postcode":"2222",
    "addr:street":"Obere Hauptstr;Niederoesterreich",
    "iso:country":"AT",
    "sg:address":"Obere Hauptstr 72",
    "sg:city":"Bad Pirawarth",
    "sg:orig_category":"Bauunternehmen",
    "sg:phone":"+43 2574 23350",
    "sg:postcode":"2222",
    "sg:province":"Nieder\u00f6sterreich",
    "wof:name":"Lahofer Gerhard Ing GesmbH - Baumeisterhaus",
    "wof:placetype":"venue"
},
  "geometry": {"coordinates":[16.6041355133,48.4457817078],"type":"Point"}
}