{
  "type": "Feature",
  "properties": {
    "iso:country":"AT",
    "sg:address":"Brunneng 17",
    "sg:city":"Wien",
    "sg:orig_category":"\u00c3\u201erzte / F Allgemeinmedizin",
    "sg:phone":"+43 1 4956622",
    "sg:postcode":"1160",
    "sg:province":"Wien",
    "wof:name":"Herrgesell Eva Susanne Dr",
    "wof:placetype":"venue"
},
  "geometry": {"coordinates":[16.3345298767,48.2070884705],"type":"Point"}
}