{
  "type": "Feature",
  "properties": {
    "iso:country":"AT",
    "sg:address":"Maria-Gailer-Str 27",
    "sg:city":"Villach",
    "sg:orig_category":"Steuerberatung",
    "sg:phone":"+43 4242 328360",
    "sg:postcode":"9500",
    "sg:province":"K\u00e4rnten",
    "wof:name":"Pirker Dietfried Ing",
    "wof:placetype":"venue"
},
  "geometry": {"coordinates":[13.862988472,46.6054191589],"type":"Point"}
}