{
  "type": "Feature",
  "properties": {
    "addr:full":"Mattersburger Str 27 Eisenstadt Burgenland 7000",
    "addr:postcode":"7000",
    "addr:street":"Str 27",
    "iso:country":"AT",
    "sg:address":"Mattersburger Str 27",
    "sg:city":"Eisenstadt",
    "sg:orig_category":"Fenster",
    "sg:phone":"+43 2682 72393",
    "sg:postcode":"7000",
    "sg:province":"Burgenland",
    "wof:name":"JOSKO Fenster und T\u00fcren - Studio Mayerhofer",
    "wof:placetype":"venue"
},
  "geometry": {"coordinates":[16.5234031677,47.8312721252],"type":"Point"}
}