{
  "type": "Feature",
  "properties": {
    "addr:full":"Bundesstr 211 Werndorf Steiermark 8402",
    "addr:housenumber":"211",
    "addr:postcode":"8402",
    "iso:country":"AT",
    "sg:address":"Bundesstr 211",
    "sg:city":"Werndorf",
    "sg:orig_category":"Autoverwertung",
    "sg:phone":"+43 4331 3554461",
    "sg:postcode":"8402",
    "sg:province":"Steiermark",
    "sg:website":"auto-reichhardt.com",
    "wof:name":"Auto - Reichhardt Opel & Ford Gebrauchtteile",
    "wof:placetype":"venue"
},
  "geometry": {"coordinates":[15.4790563583,46.91355896],"type":"Point"}
}