{
  "type": "Feature",
  "properties": {
    "addr:full":"Linzer Bundesstr 90 Gnigl Salzburg 5023",
    "addr:housenumber":"90",
    "addr:postcode":"5023",
    "iso:country":"AT",
    "sg:address":"Linzer Bundesstr 90",
    "sg:city":"Gnigl",
    "sg:orig_category":"Physiotherapie",
    "sg:phone":"+43 662 661854",
    "sg:postcode":"5023",
    "sg:province":"Salzburg",
    "wof:name":"Heindl Reinhard Dipl-PT",
    "wof:placetype":"venue"
},
  "geometry": {"coordinates":[13.0781288147,47.822883606],"type":"Point"}
}