{
  "type": "Feature",
  "properties": {
    "iso:country":"AT",
    "sg:address":"Pirath 2",
    "sg:city":"Geinberg",
    "sg:orig_category":"Pensionen / Privatzimmer",
    "sg:phone":"+43 7758 2936",
    "sg:postcode":"4943",
    "sg:province":"Ober\u00f6sterreich",
    "wof:name":"G\u00e4stehof Thermenblick",
    "wof:placetype":"venue"
},
  "geometry": {"coordinates":[13.2941713333,48.2649269104],"type":"Point"}
}