{
  "type": "Feature",
  "properties": {
    "addr:full":"Zirkusg 13 Wien Wien 1020",
    "addr:housenumber":"13",
    "addr:postcode":"1020",
    "addr:street":"Zirkusg",
    "iso:country":"AT",
    "sg:address":"Zirkusg 13",
    "sg:city":"Wien",
    "sg:orig_category":"Druckereien",
    "sg:phone":"+43 4312 1431700",
    "sg:postcode":"1020",
    "sg:province":"Wien",
    "sg:website":"gerin.co.at",
    "wof:name":"Gerin Paul",
    "wof:placetype":"venue"
},
  "geometry": {"coordinates":[16.3832759857,48.2154159546],"type":"Point"}
}