{
  "type": "Feature",
  "properties": {
    "iso:country":"AT",
    "sg:address":"Burgg 7-9",
    "sg:city":"Wien",
    "sg:orig_category":"Personalbereitstellung",
    "sg:phone":"+43 1 52688800",
    "sg:postcode":"1070",
    "sg:province":"Wien",
    "wof:name":"MANPOWER AUSTRIA Tempor\u00e4rpersonal GmbH",
    "wof:placetype":"venue"
},
  "geometry": {"coordinates":[16.3561229706,48.2042579651],"type":"Point"}
}