{
  "type": "Feature",
  "properties": {
    "iso:country":"AT",
    "sg:address":"Spertendorf 68",
    "sg:city":"Kirchberg in Tirol",
    "sg:orig_category":"Pensionen / Privatzimmer",
    "sg:phone":"+43 5357 2772",
    "sg:postcode":"6365",
    "sg:province":"Tirol",
    "wof:name":"Pension Franglhof",
    "wof:placetype":"venue"
},
  "geometry": {"coordinates":[12.3017702103,47.4521217346],"type":"Point"}
}