{
  "type": "Feature",
  "properties": {
    "addr:full":"Weiherweg 3 P\u00f6chlarn Nieder\u00f6sterreich 3380",
    "addr:housenumber":"3",
    "addr:postcode":"3380",
    "addr:street":"Weiherweg;Niederoesterreich",
    "iso:country":"AT",
    "sg:address":"Weiherweg 3",
    "sg:city":"P\u00f6chlarn",
    "sg:orig_category":"Werbegrafik- U Grafik-Design",
    "sg:phone":"+43 4327 574558",
    "sg:postcode":"3380",
    "sg:province":"Nieder\u00f6sterreich",
    "wof:name":"Bruckner Markus",
    "wof:placetype":"venue"
},
  "geometry": {"coordinates":[-79.38526153559999,41.2145881653],"type":"Point"}
}