{
  "type": "Feature",
  "properties": {
    "addr:full":"Industriegel\u00e4nde Zone A 8, Zone A Fulpmes Tirol 6166",
    "addr:housenumber":"8",
    "addr:postcode":"6166",
    "addr:street":"Zone A;A Fulpmes",
    "iso:country":"AT",
    "sg:address":"Industriegel\u00e4nde Zone A 8, Zone A",
    "sg:city":"Fulpmes",
    "sg:classifiers":[
        {
            "category":"Parking",
            "subcategory":"Garage",
            "type":"Transportation"
        }
    ],
    "sg:phone":"+43 5225 62612",
    "sg:postcode":"6166",
    "sg:province":"Tirol",
    "sg:tags":[
        "carport"
    ],
    "wof:name":"REFI Reinhard Fiechtl Glaserei-Spenglerei GmbH",
    "wof:placetype":"venue"
},
  "geometry": {"coordinates":[11.3487129211,47.1532936096],"type":"Point"}
}