{
  "type": "Feature",
  "properties": {
    "addr:full":"Oberhof 5 Goldegg Salzburg 5622",
    "addr:housenumber":"5",
    "addr:postcode":"5622",
    "addr:street":"Oberhof;Salzburg",
    "iso:country":"AT",
    "sg:address":"Oberhof 5",
    "sg:city":"Goldegg",
    "sg:orig_category":"Appartements / Ferienwohnungen",
    "sg:phone":"+43 6415 81620",
    "sg:postcode":"5622",
    "sg:province":"Salzburg",
    "wof:name":"Mittersteiner-Gruber Siegfried",
    "wof:placetype":"venue"
},
  "geometry": {"coordinates":[13.099439621,47.3187294006],"type":"Point"}
}