{
  "type": "Feature",
  "properties": {
    "addr:full":"Karl-Heinz-Str 67/11 Wien Wien 1230",
    "addr:housenumber":"67 / 11",
    "addr:postcode":"1230",
    "addr:street":"Karl-Heinz-Str",
    "iso:country":"AT",
    "sg:address":"Karl-Heinz-Str 67/11",
    "sg:city":"Wien",
    "sg:orig_category":"Tischlereien",
    "sg:phone":"+43 1 6626260",
    "sg:postcode":"1230",
    "sg:province":"Wien",
    "wof:name":"K\u00f6nighofer Franz",
    "wof:placetype":"venue"
},
  "geometry": {"coordinates":[16.3124294281,48.1548728943],"type":"Point"}
}