{
  "type": "Feature",
  "properties": {
    "addr:full":"Grazbachg 53 Graz Steiermark 8010",
    "addr:housenumber":"53",
    "addr:postcode":"8010",
    "addr:street":"Grazbachg",
    "iso:country":"AT",
    "sg:address":"Grazbachg 53",
    "sg:city":"Graz",
    "sg:orig_category":"Stahl / Gro\u00c3\u0178handel",
    "sg:phone":"+43 316 8287880",
    "sg:postcode":"8010",
    "sg:province":"Steiermark",
    "wof:name":"Gratzer StahlgesmbH",
    "wof:placetype":"venue"
},
  "geometry": {"coordinates":[15.4423084259,47.0641746521],"type":"Point"}
}