{
  "type": "Feature",
  "properties": {
    "addr:full":"Auerweg 3 Dornbirn Vorarlberg 6850",
    "addr:housenumber":"3",
    "addr:postcode":"6850",
    "addr:street":"Auerweg",
    "iso:country":"AT",
    "sg:address":"Auerweg 3",
    "sg:city":"Dornbirn",
    "sg:orig_category":"Befestigungstechnik",
    "sg:phone":"+43 5572 23520",
    "sg:postcode":"6850",
    "sg:province":"Vorarlberg",
    "wof:name":"Gabriel GesmbH",
    "wof:placetype":"venue"
},
  "geometry": {"coordinates":[9.7271795273,47.410949707],"type":"Point"}
}