{
  "type": "Feature",
  "properties": {
    "addr:full":"Nr 297 Aflenz Kurort Steiermark 8623",
    "addr:postcode":"8623",
    "addr:street":"Nr 297",
    "iso:country":"AT",
    "sg:address":"Nr 297",
    "sg:city":"Aflenz Kurort",
    "sg:orig_category":"Bergbahnen",
    "sg:phone":"+43 3861 2339",
    "sg:postcode":"8623",
    "sg:province":"Steiermark",
    "wof:name":"Schiregion Aflenz B\u00fcrgeralm Bergbahnen GmbH & Co KG",
    "wof:placetype":"venue"
},
  "geometry": {"coordinates":[15.2384824753,47.5437736511],"type":"Point"}
}