{
  "type": "Feature",
  "properties": {
    "iso:country":"AT",
    "sg:address":"Albert Schweitzer-G 6",
    "sg:city":"Wien",
    "sg:classifiers":[
        {
            "category":"Restaurant",
            "type":"Food & Drink"
        }
    ],
    "sg:phone":"+43 1 9792390",
    "sg:postcode":"1140",
    "sg:province":"Wien",
    "wof:name":"Gourmet Auhof",
    "wof:placetype":"venue"
},
  "geometry": {"coordinates":[16.217338562,48.2078437805],"type":"Point"}
}