{
  "type": "Feature",
  "properties": {
    "addr:full":"Maximilianstrasse 8 Innsbruck Tirol 6020",
    "addr:housenumber":"8",
    "addr:postcode":"6020",
    "addr:street":"Maximilianstrasse;Tirol",
    "iso:country":"AT",
    "sg:address":"Maximilianstrasse 8",
    "sg:city":"Innsbruck",
    "sg:classifiers":[
        {
            "category":"Shopping",
            "subcategory":"Books",
            "type":"Retail Goods"
        }
    ],
    "sg:phone":"+43 512 574772",
    "sg:postcode":"6020",
    "sg:province":"Tirol",
    "sg:website":"uibk.ac.at/c/cb/cb26",
    "wof:name":"Reschverlag",
    "wof:placetype":"venue"
},
  "geometry": {"coordinates":[11.3898172379,47.2623405457],"type":"Point"}
}