{
  "type": "Feature",
  "properties": {
    "iso:country":"AT",
    "sg:address":"Nr 19",
    "sg:city":"Wenigzell",
    "sg:orig_category":"Transportunternehmen",
    "sg:phone":"+43 4333 362217",
    "sg:postcode":"8254",
    "sg:province":"Steiermark",
    "wof:name":"Maderbacher Anton",
    "wof:placetype":"venue"
},
  "geometry": {"coordinates":[15.78606987,47.4261932373],"type":"Point"}
}