{
  "type": "Feature",
  "properties": {
    "addr:full":"Dechant-Pfeifer-Str 4 Hollabrunn Nieder\u00f6sterreich 2020",
    "addr:housenumber":"4",
    "addr:postcode":"2020",
    "addr:street":"Dechant-Pfeifer-Str",
    "iso:country":"AT",
    "sg:address":"Dechant-Pfeifer-Str 4",
    "sg:city":"Hollabrunn",
    "sg:orig_category":"Zelte / Vermietung",
    "sg:phone":"+43 2952 20943",
    "sg:postcode":"2020",
    "sg:province":"Nieder\u00f6sterreich",
    "wof:name":"Sch\u00f6bel Herbert",
    "wof:placetype":"venue"
},
  "geometry": {"coordinates":[16.0712623596,48.5611801147],"type":"Point"}
}