{
  "type": "Feature",
  "properties": {
    "addr:full":"Nr 237 Pettenbach Ober\u00f6sterreich 4643",
    "addr:postcode":"4643",
    "addr:street":"Nr 237",
    "iso:country":"AT",
    "sg:address":"Nr 237",
    "sg:city":"Pettenbach",
    "sg:orig_category":"Brautkleider U -Artikel",
    "sg:phone":"+43 7586 8171",
    "sg:postcode":"4643",
    "sg:province":"Ober\u00f6sterreich",
    "wof:name":"Weigerstorfer Karin",
    "wof:placetype":"venue"
},
  "geometry": {"coordinates":[14.0165214539,47.9612464905],"type":"Point"}
}