{
  "type": "Feature",
  "properties": {
    "addr:full":"Marchtrenk Ober\u00f6sterreich 4614",
    "addr:postcode":"4614",
    "iso:country":"AT",
    "sg:city":"Marchtrenk",
    "sg:orig_category":"Freizeit, Musik",
    "sg:postcode":"4614",
    "sg:province":"Ober\u00f6sterreich",
    "sg:website":"http://www.net4you.co.at/user/schlapak/Startseite.htm",
    "wof:name":"Tanzband \u00b4Barbados\u00b4  a happy sound music",
    "wof:placetype":"venue"
},
  "geometry": {"coordinates":[14.1149396896,48.190826416],"type":"Point"}
}