{
  "type": "Feature",
  "properties": {
    "addr:full":"Nr 39g Pertisau Tirol 6213",
    "addr:postcode":"6213",
    "addr:street":"Nr;Pertisau",
    "iso:country":"AT",
    "sg:address":"Nr 39g",
    "sg:city":"Pertisau",
    "sg:orig_category":"Appartements / Ferienwohnungen",
    "sg:phone":"+43 4352 436316",
    "sg:postcode":"6213",
    "sg:province":"Tirol",
    "wof:name":"Huber Alois-u Maria",
    "wof:placetype":"venue"
},
  "geometry": {"coordinates":[11.6961479187,47.4396896362],"type":"Point"}
}