{
  "type": "Feature",
  "properties": {
    "iso:country":"AT",
    "sg:address":"Badner Str 1A",
    "sg:city":"Kottingbrunn",
    "sg:orig_category":"Lebensmittel / Einzelhandel",
    "sg:phone":"+43 2252 78077",
    "sg:postcode":"2542",
    "sg:province":"Nieder\u00f6sterreich",
    "wof:name":"MONDO Lebensmitteldiskonter",
    "wof:placetype":"venue"
},
  "geometry": {"coordinates":[16.2220001221,47.9499168396],"type":"Point"}
}