{
  "type": "Feature",
  "properties": {
    "addr:full":"Kirchenpl 4 Gmunden Ober\u00f6sterreich 4810",
    "addr:housenumber":"4",
    "addr:postcode":"4810",
    "addr:street":"Kirchenpl;Oberoesterreich",
    "iso:country":"AT",
    "sg:address":"Kirchenpl 4",
    "sg:city":"Gmunden",
    "sg:orig_category":"Non-Classified Establishments",
    "sg:phone":"+43 761264176",
    "sg:postcode":"4810",
    "sg:province":"Ober\u00f6sterreich",
    "wof:name":"Kirchenbeitragsstelle",
    "wof:placetype":"venue"
},
  "geometry": {"coordinates":[13.7992916107,47.9198112488],"type":"Point"}
}