{
  "type": "Feature",
  "properties": {
    "addr:full":"Nr 18 Haslach an der M\u00fchl Ober\u00f6sterreich 4170",
    "addr:postcode":"4170",
    "addr:street":"Nr 18;Oberoesterreich",
    "iso:country":"AT",
    "sg:address":"Nr 18",
    "sg:city":"Haslach an der M\u00fchl",
    "sg:orig_category":"Gemeinden",
    "sg:phone":"+43 4372 8971555",
    "sg:postcode":"4170",
    "sg:province":"Ober\u00f6sterreich",
    "wof:name":"Gemeinde Lichtenau im M\u00fchlkreis",
    "wof:placetype":"venue"
},
  "geometry": {"coordinates":[14.0414218903,48.5752792358],"type":"Point"}
}