{
  "type": "Feature",
  "properties": {
    "iso:country":"AT",
    "sg:address":"Springsiedelg 25",
    "sg:city":"Wien",
    "sg:orig_category":"Steuerberatung",
    "sg:phone":"+43 1 3201459",
    "sg:postcode":"1190",
    "sg:province":"Wien",
    "wof:name":"Lummerstorfer Andreas Mag",
    "wof:placetype":"venue"
},
  "geometry": {"coordinates":[16.3534030914,48.2573318481],"type":"Point"}
}