{
  "type": "Feature",
  "properties": {
    "addr:full":"Thaliastr 94 Wien Wien 1160",
    "addr:housenumber":"94",
    "addr:postcode":"1160",
    "addr:street":"Thaliastr",
    "iso:country":"AT",
    "sg:address":"Thaliastr 94",
    "sg:city":"Wien",
    "sg:orig_category":"Banken U Sparkassen",
    "sg:phone":"+43 4314 8480000",
    "sg:postcode":"1160",
    "sg:province":"Wien",
    "wof:name":"Bank f Arbeit u Wirtschaft AG",
    "wof:placetype":"venue"
},
  "geometry": {"coordinates":[16.3187961578,48.2117347717],"type":"Point"}
}