{
  "type": "Feature",
  "properties": {
    "addr:full":"F Wedenig-Str 23 Klagenfurt-Viktring K\u00e4rnten 9073",
    "addr:housenumber":"23",
    "addr:postcode":"9073",
    "addr:street":"Klagenfurt-Viktring Kaernten",
    "iso:country":"AT",
    "sg:address":"F Wedenig-Str 23",
    "sg:city":"Klagenfurt-Viktring",
    "sg:orig_category":"Transportunternehmen",
    "sg:phone":"+43 463 281342",
    "sg:postcode":"9073",
    "sg:province":"K\u00e4rnten",
    "wof:name":"Hribernig Anton",
    "wof:placetype":"venue"
},
  "geometry": {"coordinates":[14.2686777115,46.5980758667],"type":"Point"}
}