{
  "type": "Feature",
  "properties": {
    "iso:country":"AT",
    "sg:address":"Nr 49e",
    "sg:city":"Sillian",
    "sg:orig_category":"Bergbahnen",
    "sg:phone":"+43 4842 6880",
    "sg:postcode":"9920",
    "sg:province":"Tirol",
    "wof:name":"Hochpustertaler Bergbahnen Nfg GesmbH & Co KG",
    "wof:placetype":"venue"
},
  "geometry": {"coordinates":[12.4398870468,46.7495117188],"type":"Point"}
}