{
  "type": "Feature",
  "properties": {
    "iso:country":"AT",
    "sg:address":"Ungarg 60",
    "sg:city":"Wien",
    "sg:classifiers":[
        {
            "category":"Shopping",
            "subcategory":"Gifts & Souvenirs",
            "type":"Retail Goods"
        }
    ],
    "sg:phone":"+43 1 7145001",
    "sg:postcode":"1030",
    "sg:province":"Wien",
    "wof:name":"Lo Verso Francesco",
    "wof:placetype":"venue"
},
  "geometry": {"coordinates":[16.387052536,48.1974487305],"type":"Point"}
}