{
  "type": "Feature",
  "properties": {
    "iso:country":"AT",
    "sg:address":"Loferer Str 2",
    "sg:city":"Kirchbichl",
    "sg:orig_category":"Landwirtschaftliche Produkte",
    "sg:phone":"+43 664 1511261",
    "sg:postcode":"6322",
    "sg:province":"Tirol",
    "wof:name":"Rudig's Landprodukte",
    "wof:placetype":"venue"
},
  "geometry": {"coordinates":[12.0831613541,47.4942893982],"type":"Point"}
}