{
  "type": "Feature",
  "properties": {
    "iso:country":"AT",
    "sg:address":"Gerbe 1144",
    "sg:city":"Egg",
    "sg:orig_category":"Hauskrankenpflege / Heimhilfe",
    "sg:phone":"+43 676 5409275",
    "sg:postcode":"6863",
    "sg:province":"Vorarlberg",
    "wof:name":"Krankenpflegeverein Egg-Gro\u00dfdorf",
    "wof:placetype":"venue"
},
  "geometry": {"coordinates":[9.8974208832,47.4320640564],"type":"Point"}
}