{
  "type": "Feature",
  "properties": {
    "addr:full":"K\u00f6nigsh\u00fcgelg 1A Sollenau Nieder\u00f6sterreich 2601",
    "addr:housenumber":"1a",
    "addr:postcode":"2601",
    "addr:street":"Koenigshuegelg",
    "iso:country":"AT",
    "sg:address":"K\u00f6nigsh\u00fcgelg 1A",
    "sg:city":"Sollenau",
    "sg:classifiers":[
        {
            "category":"Professional",
            "subcategory":"Computer Services",
            "type":"Services"
        }
    ],
    "sg:phone":"+43 4326 28619000",
    "sg:postcode":"2601",
    "sg:province":"Nieder\u00f6sterreich",
    "sg:tags":[
        "software"
    ],
    "wof:name":"DR Software GmbH",
    "wof:placetype":"venue"
},
  "geometry": {"coordinates":[16.2494049072,47.8965682983],"type":"Point"}
}