{
  "type": "Feature",
  "properties": {
    "iso:country":"AT",
    "sg:address":"Obere Hauptstr 11",
    "sg:city":"Wilhelmsburg an der Traisen",
    "sg:orig_category":"Glaskunst U -Gestaltung",
    "sg:phone":"+43 2746 5901",
    "sg:postcode":"3150",
    "sg:province":"Nieder\u00f6sterreich",
    "wof:name":"Kaiser Erika",
    "wof:placetype":"venue"
},
  "geometry": {"coordinates":[15.6558494568,48.0672073364],"type":"Point"}
}