{
  "type": "Feature",
  "properties": {
    "addr:full":"Neudorf 13 Wildon Steiermark 8410",
    "addr:housenumber":"13",
    "addr:postcode":"8410",
    "addr:street":"Neudorf;Steiermark",
    "iso:country":"AT",
    "sg:address":"Neudorf 13",
    "sg:city":"Wildon",
    "sg:orig_category":"Autohandel",
    "sg:phone":"+43 3182 3972",
    "sg:postcode":"8410",
    "sg:province":"Steiermark",
    "wof:name":"Mayer Gerhard",
    "wof:placetype":"venue"
},
  "geometry": {"coordinates":[15.4746255875,46.8975753784],"type":"Point"}
}