{
  "type": "Feature",
  "properties": {
    "addr:full":"Kandlgasse 15/5 Wien Wien 1070",
    "addr:housenumber":"15 / 5",
    "addr:postcode":"1070",
    "addr:street":"Kandlgasse",
    "iso:country":"AT",
    "sg:address":"Kandlgasse 15/5",
    "sg:city":"Wien",
    "sg:orig_category":"Dtp Applications",
    "sg:phone":"+43 1 52458500",
    "sg:postcode":"1070",
    "sg:province":"Wien",
    "sg:website":"pixelwings.com",
    "wof:name":"Pixelwings Medien GmbH",
    "wof:placetype":"venue"
},
  "geometry": {"coordinates":[16.3428916931,48.2025871277],"type":"Point"}
}