{
  "type": "Feature",
  "properties": {
    "addr:full":"Rotenm\u00fchlg 45 Wien Wien 1120",
    "addr:housenumber":"45",
    "addr:postcode":"1120",
    "addr:street":"Rotenmuehlg",
    "iso:country":"AT",
    "sg:address":"Rotenm\u00fchlg 45",
    "sg:city":"Wien",
    "sg:orig_category":"Tierschutz",
    "sg:phone":"+43 4367 64014929",
    "sg:postcode":"1120",
    "sg:province":"Wien",
    "wof:name":"Hilfe f Pferde u andere Vierbeiner",
    "wof:placetype":"venue"
},
  "geometry": {"coordinates":[16.3290939331,48.1824874878],"type":"Point"}
}