{
  "type": "Feature",
  "properties": {
    "iso:country":"AT",
    "sg:address":"Shopping City S\u00fcd",
    "sg:city":"V\u00f6sendorf-S\u00fcd",
    "sg:classifiers":[
        {
            "category":"Home & Garden",
            "subcategory":"Home Furnishings",
            "type":"Retail Goods"
        }
    ],
    "sg:phone":"+43 4316 9000",
    "sg:postcode":"2334",
    "sg:province":"Nieder\u00f6sterreich",
    "sg:tags":[
        "household"
    ],
    "wof:name":"IKEA M\u00d6BELVERTRIEB OHG",
    "wof:placetype":"venue"
},
  "geometry": {"coordinates":[117.01132202150001,33.0038909912],"type":"Point"}
}