{
  "type": "Feature",
  "properties": {
    "addr:full":"Ottensheimer Str 55 Linz Ober\u00f6sterreich 4040",
    "addr:postcode":"4040",
    "addr:street":"Str 55",
    "iso:country":"AT",
    "sg:address":"Ottensheimer Str 55",
    "sg:city":"Linz",
    "sg:classifiers":[
        {
            "category":"Internet Cafe",
            "subcategory":"None",
            "type":"Food & Drink"
        }
    ],
    "sg:phone":"+43 732 714320",
    "sg:postcode":"4040",
    "sg:province":"Ober\u00f6sterreich",
    "wof:name":"WWW-shuttle + internetservice GmbH",
    "wof:placetype":"venue"
},
  "geometry": {"coordinates":[14.2749128342,48.3064956665],"type":"Point"}
}