{
  "type": "Feature",
  "properties": {
    "addr:full":"Siriusstr 13 Klagenfurt K\u00e4rnten 9020",
    "addr:housenumber":"13",
    "addr:postcode":"9020",
    "addr:street":"Siriusstr;Kaernten",
    "iso:country":"AT",
    "sg:address":"Siriusstr 13",
    "sg:city":"Klagenfurt",
    "sg:orig_category":"Biologische Produkte",
    "sg:phone":"+43 463 328277",
    "sg:postcode":"9020",
    "sg:province":"K\u00e4rnten",
    "wof:name":"Edelweiss Warenhandel Werner Kulle",
    "wof:placetype":"venue"
},
  "geometry": {"coordinates":[14.3204908371,46.6180038452],"type":"Point"}
}