{
  "type": "Feature",
  "properties": {
    "addr:full":"Rauth 2 Keutschach K\u00e4rnten 9074",
    "addr:housenumber":"2",
    "addr:postcode":"9074",
    "addr:street":"Rauth;Kaernten",
    "iso:country":"AT",
    "sg:address":"Rauth 2",
    "sg:city":"Keutschach",
    "sg:orig_category":"Pensionen / Privatzimmer",
    "sg:phone":"+43 4273 2464",
    "sg:postcode":"9074",
    "sg:province":"K\u00e4rnten",
    "wof:name":"Setz Josef",
    "wof:placetype":"venue"
},
  "geometry": {"coordinates":[14.1858158112,46.5947608948],"type":"Point"}
}