{
  "type": "Feature",
  "properties": {
    "iso:country":"AT",
    "sg:address":"Marcusstrasse 6",
    "sg:city":"Buchkirchen",
    "sg:classifiers":[
        {
            "category":"Education",
            "subcategory":"School",
            "type":"Public Place"
        }
    ],
    "sg:phone":"+43 7242 206034",
    "sg:postcode":"4611",
    "sg:province":"Ober\u00f6sterreich",
    "sg:tags":[
        "motivation",
        "training",
        "staff"
    ],
    "sg:website":"trainandcoach.net",
    "wof:name":"Train and Coach .net",
    "wof:placetype":"venue"
},
  "geometry": {"coordinates":[14.0408000946,48.2101211548],"type":"Point"}
}