{
  "type": "Feature",
  "properties": {
    "addr:full":"Markt 35 Abtenau Salzburg 5441",
    "addr:housenumber":"35",
    "addr:postcode":"5441",
    "addr:street":"Markt;Salzburg",
    "iso:country":"AT",
    "sg:address":"Markt 35",
    "sg:city":"Abtenau",
    "sg:orig_category":"Webdesign",
    "sg:phone":"+43 664 5020910",
    "sg:postcode":"5441",
    "sg:province":"Salzburg",
    "wof:name":"at work volker boeckl",
    "wof:placetype":"venue"
},
  "geometry": {"coordinates":[13.3462638855,47.563495636],"type":"Point"}
}