{
  "type": "Feature",
  "properties": {
    "addr:full":"W\u00f6rndlestr 19 Innsbruck Tirol 6020",
    "addr:housenumber":"19",
    "addr:postcode":"6020",
    "addr:street":"Woerndlestr;Tirol",
    "iso:country":"AT",
    "sg:address":"W\u00f6rndlestr 19",
    "sg:city":"Innsbruck",
    "sg:orig_category":"Bastelbedarf",
    "sg:phone":"+43 512 346040",
    "sg:postcode":"6020",
    "sg:province":"Tirol",
    "wof:name":"Helga's bastel- und Ideenladen",
    "wof:placetype":"venue"
},
  "geometry": {"coordinates":[11.4195165634,47.2731742859],"type":"Point"}
}