{
  "type": "Feature",
  "properties": {
    "addr:full":"Langfeld 5 Wildon Steiermark 8410",
    "addr:housenumber":"5",
    "addr:postcode":"8410",
    "addr:street":"Langfeld;Steiermark",
    "iso:country":"AT",
    "sg:address":"Langfeld 5",
    "sg:city":"Wildon",
    "sg:orig_category":"Altbausanierungen",
    "sg:phone":"+43 4331 838582",
    "sg:postcode":"8410",
    "sg:province":"Steiermark",
    "wof:name":"Schwarz A KEG",
    "wof:placetype":"venue"
},
  "geometry": {"coordinates":[15.521490097,46.8895111084],"type":"Point"}
}