{
  "type": "Feature",
  "properties": {
    "iso:country":"AT",
    "sg:address":"Untersbergstr 52",
    "sg:city":"Gartenau-St. Leonhard",
    "sg:orig_category":"Beton- U Betonsteinwerke",
    "sg:phone":"+43 662 8108",
    "sg:postcode":"5083",
    "sg:province":"Salzburg",
    "wof:name":"Ebenseer Betonwerke GmbH",
    "wof:placetype":"venue"
},
  "geometry": {"coordinates":[13.0414104462,47.727558136],"type":"Point"}
}