{
  "type": "Feature",
  "properties": {
    "addr:full":"Althofenweg 1 Lochau Vorarlberg 6911",
    "addr:housenumber":"1",
    "addr:postcode":"6911",
    "addr:street":"Althofenweg",
    "iso:country":"AT",
    "sg:address":"Althofenweg 1",
    "sg:city":"Lochau",
    "sg:orig_category":"Berufsschulen",
    "sg:phone":"+43 5574 429060",
    "sg:postcode":"6911",
    "sg:province":"Vorarlberg",
    "wof:name":"Landes-Berufsschule Lochau",
    "wof:placetype":"venue"
},
  "geometry": {"coordinates":[9.7578411102,47.5353622437],"type":"Point"}
}