{
  "type": "Feature",
  "properties": {
    "addr:full":"Mollner Str 9 Molln Ober\u00f6sterreich 4591",
    "addr:housenumber":"9",
    "addr:postcode":"4591",
    "addr:street":"Str",
    "iso:country":"AT",
    "sg:address":"Mollner Str 9",
    "sg:city":"Molln",
    "sg:orig_category":"Elektroinstallationsunternehmen",
    "sg:phone":"+43 4375 843215",
    "sg:postcode":"4591",
    "sg:province":"Ober\u00f6sterreich",
    "wof:name":"ETECH Schmid u Pachler Elektrotechnik GmbH & Co KG",
    "wof:placetype":"venue"
},
  "geometry": {"coordinates":[14.2575998306,47.8856582642],"type":"Point"}
}