{
  "type": "Feature",
  "properties": {
    "addr:full":"Schreinerg 1 Ober-Grafendorf Nieder\u00f6sterreich 3200",
    "addr:housenumber":"1",
    "addr:postcode":"3200",
    "addr:street":"Schreinerg",
    "iso:country":"AT",
    "sg:address":"Schreinerg 1",
    "sg:city":"Ober-Grafendorf",
    "sg:orig_category":"Tischlereien",
    "sg:phone":"+43 2747 2267",
    "sg:postcode":"3200",
    "sg:province":"Nieder\u00f6sterreich",
    "wof:name":"H\u00f6rmann Walter",
    "wof:placetype":"venue"
},
  "geometry": {"coordinates":[15.5444259644,48.1481819153],"type":"Point"}
}