{
  "type": "Feature",
  "properties": {
    "addr:full":"W\u00e4hringer Str 39 und 41 Wien Wien 1090",
    "addr:housenumber":"und 41",
    "addr:postcode":"1090",
    "addr:street":"Str",
    "iso:country":"AT",
    "sg:address":"W\u00e4hringer Str 39 und 41",
    "sg:city":"Wien",
    "sg:orig_category":"Familien / Beratung",
    "sg:phone":"+43 1 4003409340",
    "sg:postcode":"1090",
    "sg:province":"Wien",
    "wof:name":"MAG ELF - Regionalstellen Soziale Arbeit mit Familien f d 6, 7, 8, 9, Bez",
    "wof:placetype":"venue"
},
  "geometry": {"coordinates":[16.351474762,48.2234115601],"type":"Point"}
}