{
  "type": "Feature",
  "properties": {
    "addr:full":"Gamperdonaweg 21 Nenzing Vorarlberg 6710",
    "addr:housenumber":"21",
    "addr:postcode":"6710",
    "addr:street":"Gamperdonaweg",
    "iso:country":"AT",
    "sg:address":"Gamperdonaweg 21",
    "sg:city":"Nenzing",
    "sg:orig_category":"Appartements / Ferienwohnungen",
    "sg:phone":"+43 5525 62166",
    "sg:postcode":"6710",
    "sg:province":"Vorarlberg",
    "wof:name":"Haus Sponna",
    "wof:placetype":"venue"
},
  "geometry": {"coordinates":[9.700009346,47.1804237366],"type":"Point"}
}