{
  "type": "Feature",
  "properties": {
    "addr:full":"Salcherstr 25 St. P\u00f6lten-Harland Nieder\u00f6sterreich 3104",
    "addr:housenumber":"25",
    "addr:postcode":"3104",
    "addr:street":"Salcherstr",
    "iso:country":"AT",
    "sg:address":"Salcherstr 25",
    "sg:city":"St. P\u00f6lten-Harland",
    "sg:orig_category":"Banken U Sparkassen",
    "sg:phone":"+43 5 010073014",
    "sg:postcode":"3104",
    "sg:province":"Nieder\u00f6sterreich",
    "wof:name":"Sparkasse Nieder\u00f6sterreich Mitte West AG",
    "wof:placetype":"venue"
},
  "geometry": {"coordinates":[15.6385402679,48.170211792],"type":"Point"}
}