{
  "type": "Feature",
  "properties": {
    "addr:full":"Langobardenstr 126/7 Wien Wien 1220",
    "addr:housenumber":"126 / 7",
    "addr:postcode":"1220",
    "iso:country":"AT",
    "sg:address":"Langobardenstr 126/7",
    "sg:city":"Wien",
    "sg:orig_category":"Umweltschutz",
    "sg:phone":"+43 1 2859548",
    "sg:postcode":"1220",
    "sg:province":"Wien",
    "wof:name":"Haug Gudula Dipl-Ing Landschafts\u00f6kologie und -planung",
    "wof:placetype":"venue"
},
  "geometry": {"coordinates":[16.4717731476,48.2181816101],"type":"Point"}
}