{
  "type": "Feature",
  "properties": {
    "addr:full":"Gmunden Ober\u00f6sterreich 4810",
    "addr:postcode":"4810",
    "addr:street":"Oberoesterreich",
    "iso:country":"AT",
    "sg:city":"Gmunden",
    "sg:orig_category":"Internet, Webseiten U -Systeme",
    "sg:phone":"+43 4322 4333572",
    "sg:postcode":"4810",
    "sg:province":"Ober\u00f6sterreich",
    "sg:website":"http://www.traunsee.com",
    "wof:name":"traunsee online",
    "wof:placetype":"venue"
},
  "geometry": {"coordinates":[13.7981462479,47.918598175],"type":"Point"}
}