{
  "type": "Feature",
  "properties": {
    "addr:full":"Teichstr 2 Reifnitz K\u00e4rnten 9081",
    "addr:housenumber":"2",
    "addr:postcode":"9081",
    "addr:street":"Teichstr;Kaernten",
    "iso:country":"AT",
    "sg:address":"Teichstr 2",
    "sg:city":"Reifnitz",
    "sg:orig_category":"Unternehmensberatung",
    "sg:phone":"+43 4273 2661",
    "sg:postcode":"9081",
    "sg:province":"K\u00e4rnten",
    "wof:name":"AD.CON - ADLASSNIG Qualitiy & Management Consulting Dipl-Ing Johann Adla\u00dfnig",
    "wof:placetype":"venue"
},
  "geometry": {"coordinates":[14.1815433502,46.6068840027],"type":"Point"}
}