{
  "type": "Feature",
  "properties": {
    "addr:full":"Weinzierler Str 56 Velden am W\u00f6rther See K\u00e4rnten 9220",
    "addr:postcode":"9220",
    "addr:street":"Str 56;Kaernten",
    "iso:country":"AT",
    "sg:address":"Weinzierler Str 56",
    "sg:city":"Velden am W\u00f6rther See",
    "sg:orig_category":"Erdarbeiten",
    "sg:phone":"+43 4342 744443",
    "sg:postcode":"9220",
    "sg:province":"K\u00e4rnten",
    "wof:name":"Tschofenig Walter",
    "wof:placetype":"venue"
},
  "geometry": {"coordinates":[14.0104694366,46.6155281067],"type":"Point"}
}