{
  "type": "Feature",
  "properties": {
    "addr:full":"Lobaustrasse 81 Gro\u00df-Enzersdorf Nieder\u00f6sterreich 2301",
    "addr:housenumber":"81",
    "addr:postcode":"2301",
    "addr:street":"Lobaustrasse;Niederoesterreich",
    "iso:country":"AT",
    "sg:address":"Lobaustrasse 81",
    "sg:city":"Gro\u00df-Enzersdorf",
    "sg:classifiers":[
        {
            "category":"Shopping",
            "subcategory":"Crafts & Fabrics",
            "type":"Retail Goods"
        }
    ],
    "sg:phone":"+43 2249 26640",
    "sg:postcode":"2301",
    "sg:province":"Nieder\u00f6sterreich",
    "sg:tags":[
        "polishing",
        "cloth",
        "cleaning"
    ],
    "sg:website":"oepula.at",
    "wof:name":"\u00d6pula Rohstoff-Recycling Ges.m.b.H.",
    "wof:placetype":"venue"
},
  "geometry": {"coordinates":[16.5402755737,48.1867675781],"type":"Point"}
}