{
  "type": "Feature",
  "properties": {
    "addr:full":"Teichg 3 B\u00fcrs Vorarlberg 6706",
    "addr:housenumber":"3",
    "addr:postcode":"6706",
    "addr:street":"Teichg",
    "iso:country":"AT",
    "sg:address":"Teichg 3",
    "sg:city":"B\u00fcrs",
    "sg:orig_category":"Schleifereien",
    "sg:phone":"+43 5552 66880",
    "sg:postcode":"6706",
    "sg:province":"Vorarlberg",
    "wof:name":"Schrottenbaum G\u00fcnter",
    "wof:placetype":"venue"
},
  "geometry": {"coordinates":[9.8033332825,47.1510047913],"type":"Point"}
}