{
  "type": "Feature",
  "properties": {
    "addr:full":"Schulg 62 Dornbirn Vorarlberg 6850",
    "addr:housenumber":"62",
    "addr:postcode":"6850",
    "addr:street":"Schulg",
    "iso:country":"AT",
    "sg:address":"Schulg 62",
    "sg:city":"Dornbirn",
    "sg:orig_category":"Hobbyvereine",
    "sg:phone":"+43 5572 21775",
    "sg:postcode":"6850",
    "sg:province":"Vorarlberg",
    "wof:name":"Pfadfindergruppe Dornbirn",
    "wof:placetype":"venue"
},
  "geometry": {"coordinates":[9.7401838303,47.4080810547],"type":"Point"}
}