{
  "type": "Feature",
  "properties": {
    "iso:country":"AT",
    "sg:address":"Bruckdorf 57",
    "sg:city":"Mariapfarr",
    "sg:orig_category":"Pensionen / Privatzimmer",
    "sg:phone":"+43 6473 8412",
    "sg:postcode":"5571",
    "sg:province":"Salzburg",
    "wof:name":"Fr\u00fchst\u00fcckspension Haus Elisabeth",
    "wof:placetype":"venue"
},
  "geometry": {"coordinates":[13.7240209579,47.153678894],"type":"Point"}
}