{
  "type": "Feature",
  "properties": {
    "addr:full":"Gersthofer Str 85/4 Wien Wien 1180",
    "addr:housenumber":"85 / 4",
    "addr:postcode":"1180",
    "addr:street":"Str",
    "iso:country":"AT",
    "sg:address":"Gersthofer Str 85/4",
    "sg:city":"Wien",
    "sg:orig_category":"Hobbyvereine",
    "sg:phone":"+43 1 4707864",
    "sg:postcode":"1180",
    "sg:province":"Wien",
    "wof:name":"\u00f6sterreichischer Alpenverein - Sektion alpine Gesellschaft",
    "wof:placetype":"venue"
},
  "geometry": {"coordinates":[16.3262767792,48.2358436584],"type":"Point"}
}