{
  "type": "Feature",
  "properties": {
    "addr:full":"Kerngasse 38 Wien Wien 1230",
    "addr:housenumber":"38",
    "addr:postcode":"1230",
    "addr:street":"Kerngasse",
    "iso:country":"AT",
    "sg:address":"Kerngasse 38",
    "sg:city":"Wien",
    "sg:classifiers":[
        {
            "category":"Government",
            "subcategory":"Fire Station",
            "type":"Public Place"
        }
    ],
    "sg:phone":"+43 1 88855450",
    "sg:postcode":"1230",
    "sg:province":"Wien",
    "sg:tags":[
        "filter",
        "air"
    ],
    "sg:website":"felcon.at",
    "wof:name":"Felcon Reinraum- und Proze\u00dftechnische Anlagen Produktionsges.m.b.H.",
    "wof:placetype":"venue"
},
  "geometry": {"coordinates":[16.2672367096,48.1366081238],"type":"Point"}
}