{
  "type": "Feature",
  "properties": {
    "addr:full":"Nr 18 Warth Vorarlberg 6767",
    "addr:postcode":"6767",
    "addr:street":"Nr;Warth",
    "iso:country":"AT",
    "sg:address":"Nr 18",
    "sg:city":"Warth",
    "sg:orig_category":"Volksschulen",
    "sg:phone":"+43 5583 3214",
    "sg:postcode":"6767",
    "sg:province":"Vorarlberg",
    "wof:name":"Volksschule Lechleiten",
    "wof:placetype":"venue"
},
  "geometry": {"coordinates":[10.1830291748,47.2582550049],"type":"Point"}
}