{
  "type": "Feature",
  "properties": {
    "addr:full":"Hauptstr 93 Breitenfurt Nieder\u00f6sterreich 2384",
    "addr:housenumber":"93",
    "addr:postcode":"2384",
    "addr:street":"Hauptstr",
    "iso:country":"AT",
    "sg:address":"Hauptstr 93",
    "sg:city":"Breitenfurt",
    "sg:orig_category":"Schlossereien",
    "sg:phone":"+43 2239 34445",
    "sg:postcode":"2384",
    "sg:province":"Nieder\u00f6sterreich",
    "wof:name":"Sedlmayer Egon",
    "wof:placetype":"venue"
},
  "geometry": {"coordinates":[16.1821041107,48.1342201233],"type":"Point"}
}