{
  "type": "Feature",
  "properties": {
    "addr:full":"Gechelbachg 6 Dornbirn Vorarlberg 6850",
    "addr:housenumber":"6",
    "addr:postcode":"6850",
    "addr:street":"Gechelbachg",
    "iso:country":"AT",
    "sg:address":"Gechelbachg 6",
    "sg:city":"Dornbirn",
    "sg:orig_category":"Hausbetreuung",
    "sg:phone":"+43 664 1636856",
    "sg:postcode":"6850",
    "sg:province":"Vorarlberg",
    "wof:name":"Fahrender-Hausmeister Lingg",
    "wof:placetype":"venue"
},
  "geometry": {"coordinates":[9.7517614365,47.403137207],"type":"Point"}
}