{
  "type": "Feature",
  "properties": {
    "addr:full":"Gasteiger Str 3 St. Johann in Tirol Tirol 6380",
    "addr:housenumber":"3",
    "addr:postcode":"6380",
    "addr:street":"Str;Tirol",
    "iso:country":"AT",
    "sg:address":"Gasteiger Str 3",
    "sg:city":"St. Johann in Tirol",
    "sg:orig_category":"Zahntechnische Laboratorien",
    "sg:phone":"+43 5352 63368",
    "sg:postcode":"6380",
    "sg:province":"Tirol",
    "wof:name":"Laggner Dieter",
    "wof:placetype":"venue"
},
  "geometry": {"coordinates":[12.4248476028,47.5233383179],"type":"Point"}
}