{
  "type": "Feature",
  "properties": {
    "addr:full":"M\u00fchlgasse 93 Perchtoldsdorf Nieder\u00f6sterreich 2380",
    "addr:housenumber":"93",
    "addr:postcode":"2380",
    "addr:street":"Muehlgasse",
    "iso:country":"AT",
    "sg:address":"M\u00fchlgasse 93",
    "sg:city":"Perchtoldsdorf",
    "sg:classifiers":[
        {
            "category":"Home & Garden",
            "subcategory":"Hardware",
            "type":"Retail Goods"
        }
    ],
    "sg:phone":"+43 1 86596370",
    "sg:postcode":"2380",
    "sg:province":"Nieder\u00f6sterreich",
    "sg:tags":[
        "agricultural",
        "implement"
    ],
    "sg:website":"stihl.at",
    "wof:name":"Stihl Ges.m.b.H.",
    "wof:placetype":"venue"
},
  "geometry": {"coordinates":[16.2652320862,48.1192970276],"type":"Point"}
}