{
  "type": "Feature",
  "properties": {
    "iso:country":"AT",
    "sg:address":"Lebenberg",
    "sg:city":"Kitzb\u00fchel",
    "sg:orig_category":"Sportanlagen",
    "sg:phone":"+43 5356 62444",
    "sg:postcode":"6370",
    "sg:province":"Tirol",
    "wof:name":"Kunsteisbahn Kitzb\u00fchel",
    "wof:placetype":"venue"
},
  "geometry": {"coordinates":[12.388671875,47.4490470886],"type":"Point"}
}