{
  "type": "Feature",
  "properties": {
    "addr:full":"Wiedner Hauptstr /60b/III/5 Wien Wien 1040",
    "addr:housenumber":"60b / iii / 5",
    "addr:postcode":"1040",
    "iso:country":"AT",
    "sg:address":"Wiedner Hauptstr /60b/III/5",
    "sg:city":"Wien",
    "sg:orig_category":"Psychotherapie",
    "sg:phone":"+43 1 5811224",
    "sg:postcode":"1040",
    "sg:province":"Wien",
    "wof:name":"Hohenbruck Gerburg Mag",
    "wof:placetype":"venue"
},
  "geometry": {"coordinates":[16.3671455383,48.1940345764],"type":"Point"}
}