{
  "type": "Feature",
  "properties": {
    "addr:full":"Sporerg 2 Wolfsberg K\u00e4rnten 9400",
    "addr:housenumber":"2;kaernten",
    "addr:postcode":"9400",
    "addr:street":"Sporerg",
    "iso:country":"AT",
    "sg:address":"Sporerg 2",
    "sg:city":"Wolfsberg",
    "sg:orig_category":"Friseure U Frisiersalons",
    "sg:phone":"+43 4343 522363",
    "sg:postcode":"9400",
    "sg:province":"K\u00e4rnten",
    "wof:name":"Salon Kamm On - Inh Markus Valentin",
    "wof:placetype":"venue"
},
  "geometry": {"coordinates":[14.8431243896,46.8408927917],"type":"Point"}
}