{
  "type": "Feature",
  "properties": {
    "iso:country":"AT",
    "sg:address":"Hauptstr 453",
    "sg:city":"Mayrhofen",
    "sg:orig_category":"Trachtenbekleidung",
    "sg:phone":"+43 5285 64713",
    "sg:postcode":"6290",
    "sg:province":"Tirol",
    "wof:name":"Tracht & Mode",
    "wof:placetype":"venue"
},
  "geometry": {"coordinates":[11.8622894287,47.1647949219],"type":"Point"}
}