{
  "type": "Feature",
  "properties": {
    "addr:full":"Hauptstr 115 Stoob Burgenland 7344",
    "addr:housenumber":"115",
    "addr:postcode":"stoob;7344",
    "addr:street":"Hauptstr",
    "iso:country":"AT",
    "sg:address":"Hauptstr 115",
    "sg:city":"Stoob",
    "sg:orig_category":"Non-Classified Establishments",
    "sg:phone":"+43 2612 42424",
    "sg:postcode":"7344",
    "sg:province":"Burgenland",
    "wof:name":"Halwax Erich",
    "wof:placetype":"venue"
},
  "geometry": {"coordinates":[16.4791030884,47.5272026062],"type":"Point"}
}