{
  "type": "Feature",
  "properties": {
    "addr:full":"Unterer Markt 9 Steinakirchen am Forst Nieder\u00f6sterreich 3261",
    "addr:housenumber":"9",
    "addr:postcode":"3261",
    "addr:street":"Unterer Markt",
    "iso:country":"AT",
    "sg:address":"Unterer Markt 9",
    "sg:city":"Steinakirchen am Forst",
    "sg:orig_category":"Banken U Sparkassen",
    "sg:phone":"+43 4374 88715440",
    "sg:postcode":"3261",
    "sg:province":"Nieder\u00f6sterreich",
    "wof:name":"Bankomat d Volksbank \u00f6tscherland regGenmbH",
    "wof:placetype":"venue"
},
  "geometry": {"coordinates":[15.0495500565,48.0672988892],"type":"Point"}
}