{
  "type": "Feature",
  "properties": {
    "iso:country":"AT",
    "sg:address":"Z\u00f6chbauerstrasse 4",
    "sg:city":"Wien",
    "sg:classifiers":[
        {
            "category":"Shopping",
            "subcategory":"Crafts & Fabrics",
            "type":"Retail Goods"
        }
    ],
    "sg:phone":"+43 1 9838108",
    "sg:postcode":"1160",
    "sg:province":"Wien",
    "sg:tags":[
        "adhesive"
    ],
    "wof:name":"Supachem Handelsges.m.b.H.",
    "wof:placetype":"venue"
},
  "geometry": {"coordinates":[16.3080692291,48.2071380615],"type":"Point"}
}