{
  "type": "Feature",
  "properties": {
    "addr:full":"Hauptstr 16A Seekirchen am Wallersee Salzburg 5201",
    "addr:housenumber":"16a",
    "addr:postcode":"5201",
    "addr:street":"Hauptstr;Salzburg",
    "iso:country":"AT",
    "sg:address":"Hauptstr 16A",
    "sg:city":"Seekirchen am Wallersee",
    "sg:orig_category":"Aluminiumbe- U -Verarbeitung",
    "sg:phone":"+43 4362 1230320",
    "sg:postcode":"5201",
    "sg:province":"Salzburg",
    "sg:website":"lp-trading.com",
    "wof:name":"LP Trading GmbH",
    "wof:placetype":"venue"
},
  "geometry": {"coordinates":[13.1264982224,47.8926315308],"type":"Point"}
}