{
  "type": "Feature",
  "properties": {
    "addr:full":"Jakob-Prandtauer-Str 11 Melk Nieder\u00f6sterreich 3390",
    "addr:housenumber":"11",
    "addr:postcode":"3390",
    "addr:street":"Jakob-Prandtauer-Str",
    "iso:country":"AT",
    "sg:address":"Jakob-Prandtauer-Str 11",
    "sg:city":"Melk",
    "sg:orig_category":"Tischlereien",
    "sg:phone":"+43 2752 524910",
    "sg:postcode":"3390",
    "sg:province":"Nieder\u00f6sterreich",
    "wof:name":"F\u00fcrst Fritz GesmbH",
    "wof:placetype":"venue"
},
  "geometry": {"coordinates":[15.3352413177,48.2255477905],"type":"Point"}
}