{
  "type": "Feature",
  "properties": {
    "iso:country":"AT",
    "sg:address":"Keplerg 54",
    "sg:city":"Ternitz",
    "sg:orig_category":"Werbegrafik- U Grafik-Design",
    "sg:phone":"+43 2630 33318",
    "sg:postcode":"2630",
    "sg:province":"Nieder\u00f6sterreich",
    "wof:name":"Lorenz Regina",
    "wof:placetype":"venue"
},
  "geometry": {"coordinates":[16.0104923248,47.7085571289],"type":"Point"}
}