{
  "type": "Feature",
  "properties": {
    "addr:full":"Grashofg 3/7 Wien Wien 1010",
    "addr:housenumber":"3 / 7",
    "addr:postcode":"1010",
    "addr:street":"Grashofg",
    "iso:country":"AT",
    "sg:address":"Grashofg 3/7",
    "sg:city":"Wien",
    "sg:orig_category":"Frottierwaren",
    "sg:phone":"+43 1 5123812",
    "sg:postcode":"1010",
    "sg:province":"Wien",
    "wof:name":"Ziegler Werner Ing KG",
    "wof:placetype":"venue"
},
  "geometry": {"coordinates":[16.3761787415,48.2103462219],"type":"Point"}
}