{
  "type": "Feature",
  "properties": {
    "iso:country":"AT",
    "sg:address":"Auhofstr 144/1",
    "sg:city":"Wien",
    "sg:orig_category":"Psychotherapie",
    "sg:phone":"+43 4318 761640",
    "sg:postcode":"1130",
    "sg:province":"Wien",
    "wof:name":"Hausleithner-Jilch Susanne",
    "wof:placetype":"venue"
},
  "geometry": {"coordinates":[16.2697315216,48.1913146973],"type":"Point"}
}