{
  "type": "Feature",
  "properties": {
    "addr:full":"Forstseestr 14 Velden am W\u00f6rther See K\u00e4rnten 9220",
    "addr:housenumber":"14",
    "addr:postcode":"9220",
    "addr:street":"Forstseestr;Kaernten",
    "iso:country":"AT",
    "sg:address":"Forstseestr 14",
    "sg:city":"Velden am W\u00f6rther See",
    "sg:orig_category":"Appartements / Ferienwohnungen",
    "sg:phone":"+43 4342 7452443",
    "sg:postcode":"9220",
    "sg:province":"K\u00e4rnten",
    "wof:name":"Ferienhaus ISIS",
    "wof:placetype":"venue"
},
  "geometry": {"coordinates":[14.0471382141,46.6212806702],"type":"Point"}
}