{
  "type": "Feature",
  "properties": {
    "iso:country":"AT",
    "sg:address":"Hauptstr 475",
    "sg:city":"Mayrhofen",
    "sg:orig_category":"Fleischhauereien",
    "sg:phone":"+43 5285 62450",
    "sg:postcode":"6290",
    "sg:province":"Tirol",
    "wof:name":"Gasser Johann",
    "wof:placetype":"venue"
},
  "geometry": {"coordinates":[11.8614358902,47.1633758545],"type":"Point"}
}