{
  "type": "Feature",
  "properties": {
    "addr:full":"Alberner Hafen 1.Molostr/Zollgeb\u00e4ude Wien Wien 1110",
    "addr:postcode":"1110",
    "iso:country":"AT",
    "sg:address":"Alberner Hafen 1.Molostr/Zollgeb\u00e4ude",
    "sg:city":"Wien",
    "sg:orig_category":"Speditionen",
    "sg:phone":"+43 1 7988549",
    "sg:postcode":"1110",
    "sg:province":"Wien",
    "wof:name":"VAC SpeditionsgesmbH",
    "wof:placetype":"venue"
},
  "geometry": {"coordinates":[16.495344162,48.1586723328],"type":"Point"}
}