{
  "type": "Feature",
  "properties": {
    "iso:country":"AT",
    "sg:address":"Haidlmairstr. 1",
    "sg:city":"Nu\u00dfbach",
    "sg:classifiers":[
        {
            "category":"Shopping",
            "type":"Retail Goods"
        }
    ],
    "sg:phone":"+43 4375 876001",
    "sg:postcode":"4542",
    "sg:province":"Ober\u00f6sterreich",
    "sg:tags":[
        "finished",
        "-",
        "metallic"
    ],
    "wof:name":"HAIDLMAIR GESMBH",
    "wof:placetype":"venue"
},
  "geometry": {"coordinates":[-95.720664978,34.9212265015],"type":"Point"}
}