{
  "type": "Feature",
  "properties": {
    "iso:country":"AT",
    "sg:address":"Beda-Weber-G 20",
    "sg:city":"Lienz",
    "sg:orig_category":"Gewerkschaften",
    "sg:phone":"+43 4852 62102",
    "sg:postcode":"9900",
    "sg:province":"Tirol",
    "wof:name":"Gewerkschaftsbund \u00f6sterreichischer",
    "wof:placetype":"venue"
},
  "geometry": {"coordinates":[12.7669553757,46.8334884644],"type":"Point"}
}