{
  "type": "Feature",
  "properties": {
    "iso:country":"AT",
    "sg:address":"Villacher Str 25/4",
    "sg:city":"Klagenfurt",
    "sg:orig_category":"Immobilienmakler",
    "sg:phone":"+43 4346 3502060",
    "sg:postcode":"9020",
    "sg:province":"K\u00e4rnten",
    "wof:name":"Immobilien u Realit\u00e4ten Perkonig",
    "wof:placetype":"venue"
},
  "geometry": {"coordinates":[14.2999954224,46.62292099],"type":"Point"}
}