{
  "type": "Feature",
  "properties": {
    "addr:full":"Wolfau Roppen Tirol 6426",
    "addr:postcode":"6426",
    "addr:street":"Wolfau;Tirol",
    "iso:country":"AT",
    "sg:address":"Wolfau",
    "sg:city":"Roppen",
    "sg:orig_category":"Schlossereien",
    "sg:phone":"+43 5417 5232",
    "sg:postcode":"6426",
    "sg:province":"Tirol",
    "wof:name":"Ambrosi Martin",
    "wof:placetype":"venue"
},
  "geometry": {"coordinates":[10.8271894455,47.2212562561],"type":"Point"}
}