{
  "type": "Feature",
  "properties": {
    "iso:country":"AT",
    "sg:address":"St.-Peter-Str 45",
    "sg:city":"Klagenfurt",
    "sg:orig_category":"Hobbyvereine",
    "sg:phone":"+43 4346 3381475",
    "sg:postcode":"9020",
    "sg:province":"K\u00e4rnten",
    "wof:name":"K\u00e4rntner Billard Verband",
    "wof:placetype":"venue"
},
  "geometry": {"coordinates":[14.3273506165,46.6208114624],"type":"Point"}
}