{
  "type": "Feature",
  "properties": {
    "iso:country":"AT",
    "sg:address":"Sch\u00f6rgelg 45",
    "sg:city":"Graz",
    "sg:orig_category":"Rauchfangkehrer",
    "sg:phone":"+43 316 820201",
    "sg:postcode":"8010",
    "sg:province":"Steiermark",
    "wof:name":"Mischak GesmbH",
    "wof:placetype":"venue"
},
  "geometry": {"coordinates":[15.4537935257,47.0662193298],"type":"Point"}
}