{
  "type": "Feature",
  "properties": {
    "addr:full":"Schmelz 47 Dellach im Drautal K\u00e4rnten 9772",
    "addr:housenumber":"47",
    "addr:postcode":"9772",
    "addr:street":"Schmelz",
    "iso:country":"AT",
    "sg:address":"Schmelz 47",
    "sg:city":"Dellach im Drautal",
    "sg:orig_category":"Metallwaren / Erzeugung U Gro\u00c3\u0178handel",
    "sg:phone":"+43 4347 1429912",
    "sg:postcode":"9772",
    "sg:province":"K\u00e4rnten",
    "wof:name":"Feldmann Metall- und Schmiedekunst GmbH",
    "wof:placetype":"venue"
},
  "geometry": {"coordinates":[13.0910167694,46.7464828491],"type":"Point"}
}