{
  "type": "Feature",
  "properties": {
    "addr:full":"Dresdner Str 55-57 Wien Wien 1200",
    "addr:postcode":"55-57;1200",
    "addr:street":"Str",
    "iso:country":"AT",
    "sg:address":"Dresdner Str 55-57",
    "sg:city":"Wien",
    "sg:orig_category":"Lebensmittel / Einzelhandel",
    "sg:phone":"+43 4313 331666",
    "sg:postcode":"1200",
    "sg:province":"Wien",
    "wof:name":"Vural Mehmet & Co GesmbH",
    "wof:placetype":"venue"
},
  "geometry": {"coordinates":[16.3809528351,48.2359275818],"type":"Point"}
}