{
  "type": "Feature",
  "properties": {
    "addr:full":"Troststr 84 Wien Wien 1100",
    "addr:housenumber":"84",
    "addr:postcode":"1100",
    "addr:street":"Troststr",
    "iso:country":"AT",
    "sg:address":"Troststr 84",
    "sg:city":"Wien",
    "sg:orig_category":"Textilreinigung",
    "sg:phone":"+43 1 6043326",
    "sg:postcode":"1100",
    "sg:province":"Wien",
    "wof:name":"Petermann & Co",
    "wof:placetype":"venue"
},
  "geometry": {"coordinates":[16.3589706421,48.1709899902],"type":"Point"}
}