{
  "type": "Feature",
  "properties": {
    "addr:full":"Lagerg 1 Wien Wien 1030",
    "addr:housenumber":"1",
    "addr:postcode":"1030",
    "addr:street":"Lagerg",
    "iso:country":"AT",
    "sg:address":"Lagerg 1",
    "sg:city":"Wien",
    "sg:orig_category":"Ingenieurkonsulenten / Zivilingenieure",
    "sg:phone":"+43 1 7145797",
    "sg:postcode":"1030",
    "sg:province":"Wien",
    "wof:name":"Charlemont Helmut Dipl-Ing",
    "wof:placetype":"venue"
},
  "geometry": {"coordinates":[16.3794155121,48.2007789612],"type":"Point"}
}