{
  "type": "Feature",
  "properties": {
    "addr:full":"Wiener Str 35 Oberwart Burgenland 7400",
    "addr:postcode":"7400",
    "iso:country":"AT",
    "sg:address":"Wiener Str 35",
    "sg:city":"Oberwart",
    "sg:orig_category":"Personalbereitstellung",
    "sg:phone":"+43 4333 5233670",
    "sg:postcode":"7400",
    "sg:province":"Burgenland",
    "wof:name":"Trenkwalder Personaldienste AG",
    "wof:placetype":"venue"
},
  "geometry": {"coordinates":[16.2071228027,47.2915344238],"type":"Point"}
}