{
  "type": "Feature",
  "properties": {
    "iso:country":"AT",
    "sg:address":"Daimlerstrasse 3",
    "sg:city":"Mauthausen",
    "sg:classifiers":[
        {
            "category":"Home & Garden",
            "subcategory":"Building Materials",
            "type":"Retail Goods"
        }
    ],
    "sg:phone":"+43 7238 29200",
    "sg:postcode":"4310",
    "sg:province":"Ober\u00f6sterreich",
    "sg:tags":[
        "tile",
        "granite"
    ],
    "wof:name":"Hirtl & Bauernfeind GmbH",
    "wof:placetype":"venue"
},
  "geometry": {"coordinates":[14.5482301712,48.2434768677],"type":"Point"}
}