{
  "type": "Feature",
  "properties": {
    "addr:full":"Cumberlandpark 1 Gmunden Ober\u00f6sterreich 4810",
    "addr:housenumber":"1",
    "addr:postcode":"4810",
    "addr:street":"Cumberlandpark;Oberoesterreich",
    "iso:country":"AT",
    "sg:address":"Cumberlandpark 1",
    "sg:city":"Gmunden",
    "sg:orig_category":"Bankomat-Standorte",
    "sg:phone":"+43 761262674",
    "sg:postcode":"4810",
    "sg:province":"Ober\u00f6sterreich",
    "wof:name":"Bankomat d Raiffeisenbank Salzkammergut Nord regGenmbH",
    "wof:placetype":"venue"
},
  "geometry": {"coordinates":[13.8061800003,47.9283065796],"type":"Point"}
}