{
  "type": "Feature",
  "properties": {
    "addr:full":"Iglaseeg 49 Wien Wien 1190",
    "addr:housenumber":"49",
    "addr:postcode":"1190",
    "addr:street":"Iglaseeg",
    "iso:country":"AT",
    "sg:address":"Iglaseeg 49",
    "sg:city":"Wien",
    "sg:orig_category":"Immobilienverwaltungen",
    "sg:phone":"+43 1 3209675",
    "sg:postcode":"1190",
    "sg:province":"Wien",
    "wof:name":"Benesch Brigitte",
    "wof:placetype":"venue"
},
  "geometry": {"coordinates":[16.3446063995,48.247303009],"type":"Point"}
}