{
  "type": "Feature",
  "properties": {
    "iso:country":"AT",
    "sg:address":"Jauresgasse 9 - ",
    "sg:city":"Wien",
    "sg:classifiers":[
        {
            "category":"Professional",
            "subcategory":"Art Services",
            "type":"Services"
        }
    ],
    "sg:phone":"+43 4317 122657",
    "sg:postcode":"1030",
    "sg:province":"Wien",
    "sg:tags":[
        "export-import"
    ],
    "sg:website":"http://www.iran.embassy.at",
    "wof:name":"Iran Embassy",
    "wof:placetype":"venue"
},
  "geometry": {"coordinates":[16.384054184,48.1971130371],"type":"Point"}
}