{
  "type": "Feature",
  "properties": {
    "addr:full":"Grossendorf 65 Ried im Traunkreis Ober\u00f6sterreich 4551",
    "addr:housenumber":"65",
    "addr:postcode":"4551",
    "addr:street":"Grossendorf",
    "iso:country":"AT",
    "sg:address":"Grossendorf 65",
    "sg:city":"Ried im Traunkreis",
    "sg:classifiers":[
        {
            "category":"Utilities",
            "subcategory":"Natural Gas",
            "type":"Services"
        }
    ],
    "sg:phone":"+43 7588 72820",
    "sg:postcode":"4551",
    "sg:province":"Ober\u00f6sterreich",
    "sg:tags":[
        "aerosol"
    ],
    "sg:website":"kanol.com",
    "wof:name":"Kanol Chemie Ges.m.b.H.",
    "wof:placetype":"venue"
},
  "geometry": {"coordinates":[14.0738592148,48.0253601074],"type":"Point"}
}