{
  "type": "Feature",
  "properties": {
    "iso:country":"AT",
    "sg:address":"Amthorstr 18a",
    "sg:city":"Innsbruck",
    "sg:orig_category":"Fotografen",
    "sg:phone":"+43 512 580198",
    "sg:postcode":"6020",
    "sg:province":"Tirol",
    "wof:name":"Gro\u00dfruck Bernhard",
    "wof:placetype":"venue"
},
  "geometry": {"coordinates":[11.4117641449,47.266746521],"type":"Point"}
}