{
  "type": "Feature",
  "properties": {
    "addr:full":"S\u00f6llnerweg 47 Going am Wilden Kaiser Tirol 6353",
    "addr:housenumber":"47",
    "addr:postcode":"6353",
    "addr:street":"Soellnerweg;Tirol",
    "iso:country":"AT",
    "sg:address":"S\u00f6llnerweg 47",
    "sg:city":"Going am Wilden Kaiser",
    "sg:orig_category":"Online-Service",
    "sg:phone":"+43 4353 5844128",
    "sg:postcode":"6353",
    "sg:province":"Tirol",
    "wof:name":"Poppeller Florian",
    "wof:placetype":"venue"
},
  "geometry": {"coordinates":[12.3325834274,47.5130462646],"type":"Point"}
}