{
  "type": "Feature",
  "properties": {
    "addr:full":"Teichg 8 G\u00fcssing Burgenland 7540",
    "addr:housenumber":"8",
    "addr:postcode":"7540",
    "addr:street":"Teichg",
    "iso:country":"AT",
    "sg:address":"Teichg 8",
    "sg:city":"G\u00fcssing",
    "sg:orig_category":"Fischzucht",
    "sg:phone":"+43 3322 423490",
    "sg:postcode":"7540",
    "sg:province":"Burgenland",
    "wof:name":"Hoffmann Rudolf GmbH",
    "wof:placetype":"venue"
},
  "geometry": {"coordinates":[16.3187484741,47.0555458069],"type":"Point"}
}