{
  "type": "Feature",
  "properties": {
    "iso:country":"AT",
    "sg:address":"M\u00fchldorf 159a",
    "sg:city":"Feldbach",
    "sg:classifiers":[
        {
            "category":"Building & Trades",
            "subcategory":"Construction",
            "type":"Services"
        }
    ],
    "sg:phone":"+43 3152 2162",
    "sg:postcode":"8330",
    "sg:province":"Steiermark",
    "sg:tags":[
        "cast",
        "stone"
    ],
    "sg:website":"interpal.at",
    "wof:name":"Andreas H\u00f6dl",
    "wof:placetype":"venue"
},
  "geometry": {"coordinates":[15.8557338715,46.9628982544],"type":"Point"}
}