{
  "type": "Feature",
  "properties": {
    "addr:full":"Hauptpl 25 Villach K\u00e4rnten 9500",
    "addr:housenumber":"25",
    "addr:postcode":"9500",
    "addr:street":"Hauptpl;Kaernten",
    "iso:country":"AT",
    "sg:address":"Hauptpl 25",
    "sg:city":"Villach",
    "sg:orig_category":"Papierwaren / Erzeugung U Gro\u00c3\u0178handel",
    "sg:phone":"+43 4342 42214286",
    "sg:postcode":"9500",
    "sg:province":"K\u00e4rnten",
    "wof:name":"CAPO Caspar & Poltnig",
    "wof:placetype":"venue"
},
  "geometry": {"coordinates":[13.8464508057,46.6135177612],"type":"Point"}
}