{
  "type": "Feature",
  "properties": {
    "addr:full":"Nr 314 Wildsch\u00f6nau-Oberau Tirol 6311",
    "addr:postcode":"6311",
    "addr:street":"Nr 314 Wildschoenau-Oberau Tirol",
    "iso:country":"AT",
    "sg:address":"Nr 314",
    "sg:city":"Wildsch\u00f6nau-Oberau",
    "sg:orig_category":"Banken U Sparkassen",
    "sg:phone":"+43 4353 3981670",
    "sg:postcode":"6311",
    "sg:province":"Tirol",
    "wof:name":"Bankomat d Raiffeisenkasse Wildsch\u00f6nau regGenmbH",
    "wof:placetype":"venue"
},
  "geometry": {"coordinates":[12.0532751083,47.4453582764],"type":"Point"}
}