{
  "type": "Feature",
  "properties": {
    "addr:full":"Max Ott-Pl 5 Salzburg Salzburg 5020",
    "addr:housenumber":"5",
    "addr:postcode":"5020",
    "addr:street":"Ott-Pl;Salzburg",
    "iso:country":"AT",
    "sg:address":"Max Ott-Pl 5",
    "sg:city":"Salzburg",
    "sg:orig_category":"Banken U Sparkassen",
    "sg:phone":"+43 662 889000",
    "sg:postcode":"5020",
    "sg:province":"Salzburg",
    "wof:name":"Bank f Arbeit und Wirtschaft AG - BAWAG/PSK Gruppe",
    "wof:placetype":"venue"
},
  "geometry": {"coordinates":[13.0413169861,47.8079833984],"type":"Point"}
}