{
  "type": "Feature",
  "properties": {
    "addr:full":"St\u00f6cklhubsdlg 19 St. Johann im Pongau Salzburg 5600",
    "addr:housenumber":"19",
    "addr:postcode":"5600",
    "addr:street":"Stoecklhubsdlg;Salzburg",
    "iso:country":"AT",
    "sg:address":"St\u00f6cklhubsdlg 19",
    "sg:city":"St. Johann im Pongau",
    "sg:orig_category":"\u00c3\u201erzte / F Allgemeinmedizin",
    "sg:phone":"+43 6412 43970",
    "sg:postcode":"5600",
    "sg:province":"Salzburg",
    "wof:name":"Schmidjell-Penthor Monika Dr",
    "wof:placetype":"venue"
},
  "geometry": {"coordinates":[13.1972837448,47.3439903259],"type":"Point"}
}