{
  "type": "Feature",
  "properties": {
    "addr:full":"Keplerstrasse 47  Graz Steiermark 8020",
    "addr:housenumber":"47",
    "addr:postcode":"8020",
    "addr:street":"Keplerstrasse",
    "iso:country":"AT",
    "sg:address":"Keplerstrasse 47 ",
    "sg:city":"Graz",
    "sg:classifiers":[
        {
            "category":"Military Area",
            "subcategory":"Restricted Area",
            "type":"Public Place"
        }
    ],
    "sg:phone":"+43 316 718245",
    "sg:postcode":"8020",
    "sg:province":"Steiermark",
    "sg:tags":[
        "lan",
        "local",
        "network"
    ],
    "sg:website":"www.retzl.at",
    "wof:name":"Dieter Retzl Computer-Elektronik",
    "wof:placetype":"venue"
},
  "geometry": {"coordinates":[15.4269170761,47.075252533],"type":"Point"}
}