{
  "type": "Feature",
  "properties": {
    "addr:full":"Spitzweg 1 Linz Ober\u00f6sterreich 4040",
    "addr:housenumber":"1",
    "addr:postcode":"4040",
    "addr:street":"Spitzweg",
    "iso:country":"AT",
    "sg:address":"Spitzweg 1",
    "sg:city":"Linz",
    "sg:orig_category":"Unternehmensberatung",
    "sg:phone":"+43 732 245865",
    "sg:postcode":"4040",
    "sg:province":"Ober\u00f6sterreich",
    "wof:name":"BwB Betriebswirtschaftliche Beratung Dr Klaus Peter",
    "wof:placetype":"venue"
},
  "geometry": {"coordinates":[14.3157329559,48.3301277161],"type":"Point"}
}