{
  "type": "Feature",
  "properties": {
    "iso:country":"AT",
    "sg:address":"Salzburger Str 44",
    "sg:city":"Schwanenstadt",
    "sg:orig_category":"Maschinenbau",
    "sg:phone":"+43 767374740",
    "sg:postcode":"4690",
    "sg:province":"Ober\u00f6sterreich",
    "wof:name":"Spie\u00dfberger GmbH",
    "wof:placetype":"venue"
},
  "geometry": {"coordinates":[13.7615003586,48.0476951599],"type":"Point"}
}