{
  "type": "Feature",
  "properties": {
    "addr:full":"Kleiner Ring 13 Wien Wien 1130",
    "addr:housenumber":"13",
    "addr:postcode":"1130",
    "addr:street":"Kleiner Ring",
    "iso:country":"AT",
    "sg:address":"Kleiner Ring 13",
    "sg:city":"Wien",
    "sg:orig_category":"Satzherstellung",
    "sg:phone":"+43 1 8040827",
    "sg:postcode":"1130",
    "sg:province":"Wien",
    "wof:name":"Schmid Horst",
    "wof:placetype":"venue"
},
  "geometry": {"coordinates":[16.2571411133,48.1679267883],"type":"Point"}
}