{
  "type": "Feature",
  "properties": {
    "addr:full":"Montafoner Str 29 Bludenz Vorarlberg 6700",
    "addr:housenumber":"29",
    "addr:postcode":"6700",
    "addr:street":"Str",
    "iso:country":"AT",
    "sg:address":"Montafoner Str 29",
    "sg:city":"Bludenz",
    "sg:orig_category":"Tankstellen",
    "sg:phone":"+43 5552 67744",
    "sg:postcode":"6700",
    "sg:province":"Vorarlberg",
    "wof:name":"BP Austria Marketing GmbH",
    "wof:placetype":"venue"
},
  "geometry": {"coordinates":[9.8337516785,47.1409645081],"type":"Point"}
}