{
  "type": "Feature",
  "properties": {
    "addr:full":"Donnersbach Steiermark 8953",
    "addr:postcode":"8953",
    "iso:country":"AT",
    "sg:city":"Donnersbach",
    "sg:orig_category":"Feuerwehren",
    "sg:phone":"+43 3683 2550",
    "sg:postcode":"8953",
    "sg:province":"Steiermark",
    "wof:name":"Freiwillige Feuerwehr Donnersbach",
    "wof:placetype":"venue"
},
  "geometry": {"coordinates":[14.1284208298,47.465587616],"type":"Point"}
}