{
  "type": "Feature",
  "properties": {
    "addr:full":"Stockerauer Str 22 Spillern Nieder\u00f6sterreich 2104",
    "addr:postcode":"2104",
    "addr:street":"Str 22",
    "iso:country":"AT",
    "sg:address":"Stockerauer Str 22",
    "sg:city":"Spillern",
    "sg:orig_category":"Gutsverwaltungen",
    "sg:phone":"+43 2266 803910",
    "sg:postcode":"2104",
    "sg:province":"Nieder\u00f6sterreich",
    "wof:name":"Harmer KG",
    "wof:placetype":"venue"
},
  "geometry": {"coordinates":[16.2537994385,48.3792266846],"type":"Point"}
}