{
  "type": "Feature",
  "properties": {
    "addr:full":"Am Neuri\u00df 36 Stockerau Nieder\u00f6sterreich 2000",
    "addr:housenumber":"36",
    "addr:postcode":"2000",
    "addr:street":"Am Neuriss",
    "iso:country":"AT",
    "sg:address":"Am Neuri\u00df 36",
    "sg:city":"Stockerau",
    "sg:orig_category":"Transportunternehmen",
    "sg:phone":"+43 2266 68560",
    "sg:postcode":"2000",
    "sg:province":"Nieder\u00f6sterreich",
    "wof:name":"Europatransporte - Christian Meier",
    "wof:placetype":"venue"
},
  "geometry": {"coordinates":[16.2309532166,48.3812141418],"type":"Point"}
}