{
  "type": "Feature",
  "properties": {
    "addr:full":"Mitterweg 13 Wels Ober\u00f6sterreich 4600",
    "addr:housenumber":"13",
    "addr:postcode":"4600",
    "addr:street":"Mitterweg;Oberoesterreich",
    "iso:country":"AT",
    "sg:address":"Mitterweg 13",
    "sg:city":"Wels",
    "sg:orig_category":"Bodenverlegung",
    "sg:phone":"+43 4372 42206661",
    "sg:postcode":"4600",
    "sg:province":"Ober\u00f6sterreich",
    "wof:name":"Uslu KEG",
    "wof:placetype":"venue"
},
  "geometry": {"coordinates":[14.0387201309,48.1682777405],"type":"Point"}
}