{
  "type": "Feature",
  "properties": {
    "addr:full":"Josef Wilberger-Str 9a Innsbruck Tirol 6020",
    "addr:housenumber":"9a",
    "addr:postcode":"6020",
    "addr:street":"Wilberger-Str;Tirol",
    "iso:country":"AT",
    "sg:address":"Josef Wilberger-Str 9a",
    "sg:city":"Innsbruck",
    "sg:orig_category":"Webdesign",
    "sg:phone":"+43 676 9021010",
    "sg:postcode":"6020",
    "sg:province":"Tirol",
    "wof:name":"Visual Productions Multimedia KEG",
    "wof:placetype":"venue"
},
  "geometry": {"coordinates":[11.4341316223,47.2773780823],"type":"Point"}
}