{
  "type": "Feature",
  "properties": {
    "addr:full":"Marokkanerg 19/3 Wien Wien 1030",
    "addr:housenumber":"19 / 3",
    "addr:postcode":"1030",
    "addr:street":"Marokkanerg",
    "iso:country":"AT",
    "sg:address":"Marokkanerg 19/3",
    "sg:city":"Wien",
    "sg:orig_category":"Psychotherapie",
    "sg:phone":"+43 4369 911014483",
    "sg:postcode":"1030",
    "sg:province":"Wien",
    "wof:name":"Pichlh\u00f6fer Christine iAuS - Burnout, Sucht, Depression, Beziehung, Krise",
    "wof:placetype":"venue"
},
  "geometry": {"coordinates":[16.380607605,48.1978187561],"type":"Point"}
}