{
  "type": "Feature",
  "properties": {
    "iso:country":"AT",
    "sg:address":"Emil Kralik-G 6",
    "sg:city":"Wien",
    "sg:orig_category":"Lebensmittel / Erzeugung U Gro\u00c3\u0178handel",
    "sg:phone":"+43 1 546710",
    "sg:postcode":"1050",
    "sg:province":"Wien",
    "wof:name":"Nestle \u00d6sterreich GmbH",
    "wof:placetype":"venue"
},
  "geometry": {"coordinates":[16.3442897797,48.1867828369],"type":"Point"}
}