{
  "type": "Feature",
  "properties": {
    "addr:full":"Oberdorfstr 17 Wien Wien 1220",
    "addr:housenumber":"17",
    "addr:postcode":"1220",
    "addr:street":"Oberdorfstr",
    "iso:country":"AT",
    "sg:address":"Oberdorfstr 17",
    "sg:city":"Wien",
    "sg:orig_category":"Altwaren",
    "sg:phone":"+43 1 2808769",
    "sg:postcode":"1220",
    "sg:province":"Wien",
    "wof:name":"Kirchmayer Ursula",
    "wof:placetype":"venue"
},
  "geometry": {"coordinates":[16.4805335999,48.2190971375],"type":"Point"}
}