{
  "type": "Feature",
  "properties": {
    "iso:country":"AT",
    "sg:address":"Ferihumerstr 50",
    "sg:city":"Linz",
    "sg:orig_category":"Berufsbekleidung / Einzelhandel",
    "sg:phone":"+43 732 252868",
    "sg:postcode":"4040",
    "sg:province":"Ober\u00f6sterreich",
    "wof:name":"W\u00f6rndl Helmut",
    "wof:placetype":"venue"
},
  "geometry": {"coordinates":[14.2907266617,48.3164138794],"type":"Point"}
}