{
  "type": "Feature",
  "properties": {
    "addr:full":"Wehrstr 5 M\u00f6llbr\u00fccke K\u00e4rnten 9813",
    "addr:housenumber":"5",
    "addr:postcode":"9813",
    "addr:street":"Wehrstr;Kaernten",
    "iso:country":"AT",
    "sg:address":"Wehrstr 5",
    "sg:city":"M\u00f6llbr\u00fccke",
    "sg:orig_category":"Spenglereien",
    "sg:phone":"+43 4769 22350",
    "sg:postcode":"9813",
    "sg:province":"K\u00e4rnten",
    "wof:name":"Striedner Norbert",
    "wof:placetype":"venue"
},
  "geometry": {"coordinates":[13.3735132217,46.8349456787],"type":"Point"}
}