{
  "type": "Feature",
  "properties": {
    "addr:full":"H\u00f6rtlerg 3-5 Waidhofen an der Ybbs Nieder\u00f6sterreich 3340",
    "addr:housenumber":"3-5",
    "addr:postcode":"3340",
    "addr:street":"Hoertlerg",
    "iso:country":"AT",
    "sg:address":"H\u00f6rtlerg 3-5",
    "sg:city":"Waidhofen an der Ybbs",
    "sg:orig_category":"Bergsportartikel",
    "sg:phone":"+43 4374 4253284",
    "sg:postcode":"3340",
    "sg:province":"Nieder\u00f6sterreich",
    "wof:name":"Condor Bergsport - Riegler Karla",
    "wof:placetype":"venue"
},
  "geometry": {"coordinates":[14.7743349075,47.9616470337],"type":"Point"}
}