{
  "type": "Feature",
  "properties": {
    "iso:country":"AT",
    "sg:address":"10.-Oktober-Str 17",
    "sg:city":"Feldkirchen in K\u00e4rnten",
    "sg:orig_category":"\u00c3\u201erzte / F Allgemeinmedizin",
    "sg:phone":"+43 4342 7633040",
    "sg:postcode":"9560",
    "sg:province":"K\u00e4rnten",
    "wof:name":"Huber Benedikt Dr",
    "wof:placetype":"venue"
},
  "geometry": {"coordinates":[14.09461689,46.7241668701],"type":"Point"}
}