{
  "type": "Feature",
  "properties": {
    "iso:country":"AT",
    "sg:address":"Neulingg 27",
    "sg:city":"Wien",
    "sg:classifiers":[
        {
            "category":"Transit Center",
            "subcategory":"Freight",
            "type":"Transportation"
        }
    ],
    "sg:phone":"+43 4317 125384",
    "sg:postcode":"1030",
    "sg:province":"Wien",
    "sg:tags":[
        "thermometer"
    ],
    "wof:name":"FTH Kfz Zubeh\u00f6r u Me\u00dfinstrumenten Service GesmbH",
    "wof:placetype":"venue"
},
  "geometry": {"coordinates":[16.4025096893,48.1936683655],"type":"Point"}
}