{
  "type": "Feature",
  "properties": {
    "addr:full":"Hauptstr 25 Pamhagen Burgenland 7152",
    "addr:housenumber":"25",
    "addr:postcode":"7152",
    "addr:street":"Hauptstr",
    "iso:country":"AT",
    "sg:address":"Hauptstr 25",
    "sg:city":"Pamhagen",
    "sg:orig_category":"Bauunternehmen",
    "sg:phone":"+43 664 5102784",
    "sg:postcode":"7152",
    "sg:province":"Burgenland",
    "wof:name":"Bleich KEG",
    "wof:placetype":"venue"
},
  "geometry": {"coordinates":[16.9082527161,47.6973075867],"type":"Point"}
}