{
  "type": "Feature",
  "properties": {
    "addr:full":"Brunner Strasse 59 Wien Wien 1230",
    "addr:housenumber":"59",
    "addr:postcode":"1230",
    "addr:street":"Brunner Strasse",
    "iso:country":"AT",
    "sg:address":"Brunner Strasse 59",
    "sg:city":"Wien",
    "sg:classifiers":[
        {
            "category":"Health Services",
            "subcategory":"Nursing And Care Facility",
            "type":"Services"
        }
    ],
    "sg:phone":"+43 1 866570",
    "sg:postcode":"1230",
    "sg:province":"Wien",
    "sg:tags":[
        "circulatory",
        "cardiac",
        "complaint",
        "remedy",
        "stimulant"
    ],
    "wof:name":"Novartis Pharma GmbH",
    "wof:placetype":"venue"
},
  "geometry": {"coordinates":[16.2982521057,48.1406211853],"type":"Point"}
}