{
  "type": "Feature",
  "properties": {
    "addr:full":"Grazer Str 40 Bruck an der Mur Steiermark 8600",
    "addr:postcode":"8600",
    "addr:street":"Str 40",
    "iso:country":"AT",
    "sg:address":"Grazer Str 40",
    "sg:city":"Bruck an der Mur",
    "sg:orig_category":"Tankstellen",
    "sg:phone":"+43 3862 51407",
    "sg:postcode":"8600",
    "sg:province":"Steiermark",
    "wof:name":"Agip Austria GmbH",
    "wof:placetype":"venue"
},
  "geometry": {"coordinates":[15.2742795944,47.4067687988],"type":"Point"}
}