{
  "type": "Feature",
  "properties": {
    "iso:country":"AT",
    "sg:address":"Nr 8",
    "sg:city":"Assling",
    "sg:orig_category":"Appartements / Ferienwohnungen",
    "sg:phone":"+43 4855 8515",
    "sg:postcode":"9911",
    "sg:province":"Tirol",
    "wof:name":"Ferienhof Kleinmoar Fam Unterweger",
    "wof:placetype":"venue"
},
  "geometry": {"coordinates":[12.6411066055,46.7863693237],"type":"Point"}
}