{
  "type": "Feature",
  "properties": {
    "addr:full":"Franz Bayer-Str 5/7 Mistelbach Nieder\u00f6sterreich 2130",
    "addr:housenumber":"5 / 7",
    "addr:postcode":"2130",
    "addr:street":"Niederoesterreich",
    "iso:country":"AT",
    "sg:address":"Franz Bayer-Str 5/7",
    "sg:city":"Mistelbach",
    "sg:orig_category":"Friseure U Frisiersalons",
    "sg:phone":"+43 699 14455045",
    "sg:postcode":"2130",
    "sg:province":"Nieder\u00f6sterreich",
    "wof:name":"Mobilfriseurin Bettina Rutschek",
    "wof:placetype":"venue"
},
  "geometry": {"coordinates":[16.5665683746,48.5738754272],"type":"Point"}
}