{
  "type": "Feature",
  "properties": {
    "addr:full":"Grabenhofstr 1 Gansbach Nieder\u00f6sterreich 3122",
    "addr:housenumber":"1",
    "addr:postcode":"3122",
    "addr:street":"Grabenhofstr",
    "iso:country":"AT",
    "sg:address":"Grabenhofstr 1",
    "sg:city":"Gansbach",
    "sg:orig_category":"\u00c3\u201erzte / F Allgemeinmedizin",
    "sg:phone":"+43 2753 70005",
    "sg:postcode":"3122",
    "sg:province":"Nieder\u00f6sterreich",
    "wof:name":"Sch\u00f6nberger Josef Dr",
    "wof:placetype":"venue"
},
  "geometry": {"coordinates":[15.4730443954,48.3041992188],"type":"Point"}
}