{
  "type": "Feature",
  "properties": {
    "iso:country":"AT",
    "sg:address":"Hildebrandg 22",
    "sg:city":"Wien",
    "sg:orig_category":"Fenster",
    "sg:phone":"+43 1 4024541",
    "sg:postcode":"1180",
    "sg:province":"Wien",
    "wof:name":"Dietrich Johann GesmbH & Co KG",
    "wof:placetype":"venue"
},
  "geometry": {"coordinates":[16.3379058838,48.222038269],"type":"Point"}
}