{
  "type": "Feature",
  "properties": {
    "addr:full":"Persal 230 Finkenberg Tirol 6292",
    "addr:housenumber":"230",
    "addr:postcode":"6292",
    "addr:street":"Persal",
    "iso:country":"AT",
    "sg:address":"Persal 230",
    "sg:city":"Finkenberg",
    "sg:orig_category":"Appartements / Ferienwohnungen",
    "sg:phone":"+43 4352 8562130",
    "sg:postcode":"6292",
    "sg:province":"Tirol",
    "wof:name":"Haus Patscheider",
    "wof:placetype":"venue"
},
  "geometry": {"coordinates":[11.818362236,47.1517944336],"type":"Point"}
}