{
  "type": "Feature",
  "properties": {
    "addr:full":"Untere Donaul\u00e4nde 21-25 Linz Ober\u00f6sterreich 4020",
    "addr:postcode":"21-25;4020",
    "addr:street":"Untere Donaulaende;Oberoesterreich",
    "iso:country":"AT",
    "sg:address":"Untere Donaul\u00e4nde 21-25",
    "sg:city":"Linz",
    "sg:orig_category":"Physiotherapie",
    "sg:phone":"+43 4373 290101110",
    "sg:postcode":"4020",
    "sg:province":"Ober\u00f6sterreich",
    "sg:website":"medicentlinz.com",
    "wof:name":"Institut Schmidinger OEG",
    "wof:placetype":"venue"
},
  "geometry": {"coordinates":[14.3001947403,48.3146286011],"type":"Point"}
}