{
  "type": "Feature",
  "properties": {
    "addr:full":"Gewerbestr 9 Gro\u00dfebersdorf Nieder\u00f6sterreich 2203",
    "addr:housenumber":"9",
    "addr:postcode":"2203",
    "addr:street":"Gewerbestr",
    "iso:country":"AT",
    "sg:address":"Gewerbestr 9",
    "sg:city":"Gro\u00dfebersdorf",
    "sg:orig_category":"Gummi U Gummiwaren",
    "sg:phone":"+43 2245 28082",
    "sg:postcode":"2203",
    "sg:province":"Nieder\u00f6sterreich",
    "wof:name":"Hagn Technische Elastomere GesmbH",
    "wof:placetype":"venue"
},
  "geometry": {"coordinates":[16.4689350128,48.3628768921],"type":"Point"}
}