{
  "type": "Feature",
  "properties": {
    "addr:full":"Steinacker 15 Dornbirn Vorarlberg 6850",
    "addr:housenumber":"15",
    "addr:postcode":"6850",
    "addr:street":"Steinacker",
    "iso:country":"AT",
    "sg:address":"Steinacker 15",
    "sg:city":"Dornbirn",
    "sg:orig_category":"Erdarbeiten",
    "sg:phone":"+43 5572 31615",
    "sg:postcode":"6850",
    "sg:province":"Vorarlberg",
    "wof:name":"Schertler Norbert",
    "wof:placetype":"venue"
},
  "geometry": {"coordinates":[9.7350664139,47.3969116211],"type":"Point"}
}