{
  "type": "Feature",
  "properties": {
    "iso:country":"AT",
    "sg:address":"Bergingenweg 8",
    "sg:city":"Kitzb\u00fchel",
    "sg:classifiers":[
        {
            "category":"Manufacturing",
            "subcategory":"Textiles",
            "type":"Manufacturing & Wholesale Goods"
        }
    ],
    "sg:phone":"+43 5356 63673",
    "sg:postcode":"6370",
    "sg:province":"Tirol",
    "sg:tags":[
        "curtain",
        "fabric"
    ],
    "wof:name":"Heinz Dorn",
    "wof:placetype":"venue"
},
  "geometry": {"coordinates":[12.4170484543,47.4149017334],"type":"Point"}
}