{
  "type": "Feature",
  "properties": {
    "iso:country":"AT",
    "sg:address":"Schattauer G 407",
    "sg:city":"Altenmarkt im Pongau",
    "sg:orig_category":"Rauchfangkehrer",
    "sg:phone":"+43 6452 71910",
    "sg:postcode":"5541",
    "sg:province":"Salzburg",
    "wof:name":"Burmann Heinz",
    "wof:placetype":"venue"
},
  "geometry": {"coordinates":[13.4253692627,47.3686523438],"type":"Point"}
}