{
  "type": "Feature",
  "properties": {
    "iso:country":"AT",
    "sg:address":"Weizberg 13",
    "sg:city":"Weiz",
    "sg:orig_category":"Non-Classified Establishments",
    "sg:phone":"+43 3172 23630",
    "sg:postcode":"8160",
    "sg:province":"Steiermark",
    "wof:name":"Pfarramt",
    "wof:placetype":"venue"
},
  "geometry": {"coordinates":[15.6355724335,47.2240753174],"type":"Point"}
}