{
  "type": "Feature",
  "properties": {
    "addr:full":"Keutschacher Str 135 Klagenfurt-Viktring K\u00e4rnten 9073",
    "addr:housenumber":"135",
    "addr:postcode":"9073",
    "addr:street":"Klagenfurt-Viktring Kaernten",
    "iso:country":"AT",
    "sg:address":"Keutschacher Str 135",
    "sg:city":"Klagenfurt-Viktring",
    "sg:orig_category":"Tankstellen",
    "sg:phone":"+43 463 281222",
    "sg:postcode":"9073",
    "sg:province":"K\u00e4rnten",
    "wof:name":"OMV AG",
    "wof:placetype":"venue"
},
  "geometry": {"coordinates":[14.2715234756,46.5919303894],"type":"Point"}
}