{
  "type": "Feature",
  "properties": {
    "addr:full":"Hafnerstr. 36 Stra\u00dfgang Steiermark 8054",
    "addr:housenumber":"36",
    "addr:postcode":"8054",
    "addr:street":"Hafnerstr.",
    "iso:country":"AT",
    "sg:address":"Hafnerstr. 36",
    "sg:city":"Stra\u00dfgang",
    "sg:classifiers":[
        {
            "category":"Wholesale",
            "subcategory":"Drugs",
            "type":"Manufacturing & Wholesale Goods"
        }
    ],
    "sg:phone":"+43 4331 62490",
    "sg:postcode":"8054",
    "sg:province":"Steiermark",
    "sg:tags":[
        "chemical",
        "pharmaceutical"
    ],
    "wof:name":"FRESENIUS KABI AUSTRIA GMBH",
    "wof:placetype":"venue"
},
  "geometry": {"coordinates":[15.414850235,47.0254516602],"type":"Point"}
}