{
  "type": "Feature",
  "properties": {
    "iso:country":"AT",
    "sg:address":"Ma\u00dfweger Str 60",
    "sg:city":"Knittelfeld",
    "sg:orig_category":"Musikgruppen",
    "sg:phone":"+43 4335 1272563",
    "sg:postcode":"8720",
    "sg:province":"Steiermark",
    "wof:name":"Musikverein Spielberg",
    "wof:placetype":"venue"
},
  "geometry": {"coordinates":[14.7973117828,47.2074241638],"type":"Point"}
}