{
  "type": "Feature",
  "properties": {
    "iso:country":"AT",
    "sg:address":"Johann-Offner-Str 10",
    "sg:city":"Wolfsberg",
    "sg:orig_category":"Drogerien",
    "sg:phone":"+43 4352 4058",
    "sg:postcode":"9400",
    "sg:province":"K\u00e4rnten",
    "wof:name":"Gewu\u00dft wie Drogerie",
    "wof:placetype":"venue"
},
  "geometry": {"coordinates":[14.8455839157,46.8382949829],"type":"Point"}
}