{
  "type": "Feature",
  "properties": {
    "addr:full":"Kettenbr\u00fcckeng 10 Wien Wien 1040",
    "addr:housenumber":"10",
    "addr:postcode":"1040",
    "addr:street":"Kettenbrueckeng",
    "iso:country":"AT",
    "sg:address":"Kettenbr\u00fcckeng 10",
    "sg:city":"Wien",
    "sg:orig_category":"Tabaktrafiken",
    "sg:phone":"+43 1 5872931",
    "sg:postcode":"1040",
    "sg:province":"Wien",
    "wof:name":"L\u00f6w Peter",
    "wof:placetype":"venue"
},
  "geometry": {"coordinates":[16.3671455383,48.1940345764],"type":"Point"}
}