{
  "type": "Feature",
  "properties": {
    "addr:full":"Albert Schweitzer-G 7 Traisen Nieder\u00f6sterreich 3160",
    "addr:housenumber":"7",
    "addr:postcode":"3160",
    "iso:country":"AT",
    "sg:address":"Albert Schweitzer-G 7",
    "sg:city":"Traisen",
    "sg:orig_category":"Non-Classified Establishments",
    "sg:phone":"+43 2762 62120",
    "sg:postcode":"3160",
    "sg:province":"Nieder\u00f6sterreich",
    "wof:name":"Evangelisches Pfarramt",
    "wof:placetype":"venue"
},
  "geometry": {"coordinates":[15.6107702255,48.0446052551],"type":"Point"}
}