{
  "type": "Feature",
  "properties": {
    "iso:country":"AT",
    "sg:address":"Markt 44",
    "sg:city":"St. Gallen",
    "sg:orig_category":"Forstverwaltungen",
    "sg:phone":"+43 3632 2010",
    "sg:postcode":"8933",
    "sg:province":"Steiermark",
    "wof:name":"Landesforste Steierm Forstverwaltung",
    "wof:placetype":"venue"
},
  "geometry": {"coordinates":[14.6172552109,47.6922798157],"type":"Point"}
}