{
  "type": "Feature",
  "properties": {
    "addr:full":"Alte Landesstr 6 Zell am See Salzburg 5700",
    "addr:housenumber":"6",
    "addr:postcode":"5700",
    "addr:street":"Salzburg",
    "iso:country":"AT",
    "sg:address":"Alte Landesstr 6",
    "sg:city":"Zell am See",
    "sg:classifiers":[
        {
            "category":"Travel",
            "subcategory":"Hotels & Motels",
            "type":"Entertainment"
        }
    ],
    "sg:phone":"+43 6542 54330",
    "sg:postcode":"5700",
    "sg:province":"Salzburg",
    "wof:name":"Hotel-Restaurant Alpenblick",
    "wof:placetype":"venue"
},
  "geometry": {"coordinates":[11.4882249832,44.6670303345],"type":"Point"}
}