{
  "type": "Feature",
  "properties": {
    "addr:full":"Vogelweiderstr 72 Salzburg Salzburg 5020",
    "addr:housenumber":"72",
    "addr:postcode":"5020",
    "addr:street":"Vogelweiderstr;Salzburg",
    "iso:country":"AT",
    "sg:address":"Vogelweiderstr 72",
    "sg:city":"Salzburg",
    "sg:orig_category":"Tapezierer U Dekorateure",
    "sg:phone":"+43 4366 2881433",
    "sg:postcode":"5020",
    "sg:province":"Salzburg",
    "wof:name":"Bugl Werner",
    "wof:placetype":"venue"
},
  "geometry": {"coordinates":[13.0538787842,47.8152503967],"type":"Point"}
}