{
  "type": "Feature",
  "properties": {
    "addr:full":"Frankenbergg 10 Wien Wien 1040",
    "addr:housenumber":"10",
    "addr:postcode":"1040",
    "addr:street":"Frankenbergg",
    "iso:country":"AT",
    "sg:address":"Frankenbergg 10",
    "sg:city":"Wien",
    "sg:classifiers":[
        {
            "category":"Travel",
            "subcategory":"Hotels & Motels",
            "type":"Entertainment"
        }
    ],
    "sg:phone":"+43 1 50517010",
    "sg:postcode":"1040",
    "sg:province":"Wien",
    "sg:website":"www.hotel-kaiserhof.at",
    "wof:name":"Best Western - Hotel Kaiserhof",
    "wof:placetype":"venue"
},
  "geometry": {"coordinates":[16.3685016632,48.197555542],"type":"Point"}
}