{
  "type": "Feature",
  "properties": {
    "iso:country":"AT",
    "sg:address":"Sportplatzstr 597",
    "sg:city":"Kaprun",
    "sg:orig_category":"Pensionen / Privatzimmer",
    "sg:phone":"+43 6547 85260",
    "sg:postcode":"5710",
    "sg:province":"Salzburg",
    "wof:name":"Fr\u00fchst\u00fcckspension Christophorus",
    "wof:placetype":"venue"
},
  "geometry": {"coordinates":[12.750620842,47.2661895752],"type":"Point"}
}