{
  "type": "Feature",
  "properties": {
    "iso:country":"AT",
    "sg:address":"Frojach 5",
    "sg:city":"Frojach",
    "sg:orig_category":"Bankomat-Standorte",
    "sg:phone":"+43 3588 2050",
    "sg:postcode":"8841",
    "sg:province":"Steiermark",
    "wof:name":"Bankomat d Steierm\u00e4rkische Bank- und Sparkassen",
    "wof:placetype":"venue"
},
  "geometry": {"coordinates":[14.3013896942,47.1253128052],"type":"Point"}
}