{
  "type": "Feature",
  "properties": {
    "addr:full":"Hauptstrasse 52 Gr\u00fcnburg Ober\u00f6sterreich 4594",
    "addr:housenumber":"52",
    "addr:postcode":"4594",
    "addr:street":"Hauptstrasse;Oberoesterreich",
    "iso:country":"AT",
    "sg:address":"Hauptstrasse 52",
    "sg:city":"Gr\u00fcnburg",
    "sg:classifiers":[
        {
            "category":"Building & Trades",
            "subcategory":"Plumbing",
            "type":"Services"
        }
    ],
    "sg:phone":"+43 7257 7056",
    "sg:postcode":"4594",
    "sg:province":"Ober\u00f6sterreich",
    "sg:tags":[
        "tub",
        "bath"
    ],
    "sg:website":"folie.at",
    "wof:name":"Bruno Folie",
    "wof:placetype":"venue"
},
  "geometry": {"coordinates":[14.2579908371,47.9686431885],"type":"Point"}
}