{
  "type": "Feature",
  "properties": {
    "addr:full":"Leobner Strasse 45 Bruck an der Mur Steiermark 8600",
    "addr:housenumber":"45",
    "addr:postcode":"8600",
    "addr:street":"Leobner Strasse",
    "iso:country":"AT",
    "sg:address":"Leobner Strasse 45",
    "sg:city":"Bruck an der Mur",
    "sg:classifiers":[
        {
            "category":"Ice Cream",
            "type":"Food & Drink"
        }
    ],
    "sg:phone":"+43 3862 51322",
    "sg:postcode":"8600",
    "sg:province":"Steiermark",
    "sg:tags":[
        "beverages",
        "alcoholic"
    ],
    "wof:name":"Stefanie Rabensteiner",
    "wof:placetype":"venue"
},
  "geometry": {"coordinates":[15.2678117752,47.406375885],"type":"Point"}
}