{
  "type": "Feature",
  "properties": {
    "addr:full":"Maria-Steflitsch-G 4/1 Leibnitz Steiermark 8430",
    "addr:housenumber":"4 / 1",
    "addr:postcode":"8430",
    "addr:street":"Maria-Steflitsch-G;Steiermark",
    "iso:country":"AT",
    "sg:address":"Maria-Steflitsch-G 4/1",
    "sg:city":"Leibnitz",
    "sg:orig_category":"Alternativtherapie",
    "sg:phone":"+43 4334 5284690",
    "sg:postcode":"8430",
    "sg:province":"Steiermark",
    "sg:website":"gesundheitstrainer.at",
    "wof:name":"Z\u00f6hrer Josef u Waltraud",
    "wof:placetype":"venue"
},
  "geometry": {"coordinates":[15.5563983917,46.7854919434],"type":"Point"}
}