{
  "type": "Feature",
  "properties": {
    "addr:full":"Hauptstr 30 Bisamberg Nieder\u00f6sterreich 2102",
    "addr:housenumber":"30",
    "addr:postcode":"2102",
    "addr:street":"Hauptstr",
    "iso:country":"AT",
    "sg:address":"Hauptstr 30",
    "sg:city":"Bisamberg",
    "sg:orig_category":"Volksschulen",
    "sg:phone":"+43 2262 62080",
    "sg:postcode":"2102",
    "sg:province":"Nieder\u00f6sterreich",
    "wof:name":"Volksschule",
    "wof:placetype":"venue"
},
  "geometry": {"coordinates":[16.3591594696,48.3298187256],"type":"Point"}
}