{
  "type": "Feature",
  "properties": {
    "iso:country":"AT",
    "sg:address":"Petrifelderstr 25",
    "sg:city":"St. Peter",
    "sg:orig_category":"Friseure U Frisiersalons",
    "sg:phone":"+43 4331 6471289",
    "sg:postcode":"8042",
    "sg:province":"Steiermark",
    "wof:name":"Pfeifer Josef",
    "wof:placetype":"venue"
},
  "geometry": {"coordinates":[15.4704122543,47.0522117615],"type":"Point"}
}