{
  "type": "Feature",
  "properties": {
    "addr:full":"Ellbognerstr. 60 Linz Ober\u00f6sterreich 4020",
    "addr:housenumber":"60",
    "addr:postcode":"4020",
    "addr:street":"Ellbognerstr.",
    "iso:country":"AT",
    "sg:address":"Ellbognerstr. 60",
    "sg:city":"Linz",
    "sg:classifiers":[
        {
            "category":"Communications",
            "subcategory":"Newspaper",
            "type":"Services"
        }
    ],
    "sg:phone":"+43 4373 2371616",
    "sg:postcode":"4020",
    "sg:province":"Ober\u00f6sterreich",
    "sg:tags":[
        "advertising"
    ],
    "wof:name":"HUMAN ADVERTISING WERBEAGENTUR GMBH",
    "wof:placetype":"venue"
},
  "geometry": {"coordinates":[14.2831459045,48.2612571716],"type":"Point"}
}