{
  "type": "Feature",
  "properties": {
    "addr:full":"Alexanderhofstr 47 Millstatt K\u00e4rnten 9872",
    "addr:housenumber":"47",
    "addr:postcode":"9872",
    "addr:street":"Alexanderhofstr;Kaernten",
    "iso:country":"AT",
    "sg:address":"Alexanderhofstr 47",
    "sg:city":"Millstatt",
    "sg:orig_category":"Pensionen / Privatzimmer",
    "sg:phone":"+43 4347 662744",
    "sg:postcode":"9872",
    "sg:province":"K\u00e4rnten",
    "wof:name":"Fr\u00fchst\u00fcckspension Haus Anna",
    "wof:placetype":"venue"
},
  "geometry": {"coordinates":[13.5624103546,46.809261322],"type":"Point"}
}