{
  "type": "Feature",
  "properties": {
    "addr:full":"Aurachtalstr 15 Reichenfels K\u00e4rnten 9463",
    "addr:housenumber":"15",
    "addr:postcode":"9463",
    "addr:street":"Aurachtalstr;Kaernten",
    "iso:country":"AT",
    "sg:address":"Aurachtalstr 15",
    "sg:city":"Reichenfels",
    "sg:orig_category":"Fenster",
    "sg:phone":"+43 4359 2178",
    "sg:postcode":"9463",
    "sg:province":"K\u00e4rnten",
    "wof:name":"Baumgartner Reinhard",
    "wof:placetype":"venue"
},
  "geometry": {"coordinates":[14.7432556152,47.0093078613],"type":"Point"}
}