{
  "type": "Feature",
  "properties": {
    "addr:full":"Unterstiftung 23a Bad Leonfelden Ober\u00f6sterreich 4190",
    "addr:housenumber":"23a",
    "addr:postcode":"4190",
    "addr:street":"Unterstiftung",
    "iso:country":"AT",
    "sg:address":"Unterstiftung 23a",
    "sg:city":"Bad Leonfelden",
    "sg:orig_category":"Gabelstapler",
    "sg:phone":"+43 7213 6820",
    "sg:postcode":"4190",
    "sg:province":"Ober\u00f6sterreich",
    "wof:name":"Mauritz Hilda",
    "wof:placetype":"venue"
},
  "geometry": {"coordinates":[14.3052902222,48.4973869324],"type":"Point"}
}