{
  "type": "Feature",
  "properties": {
    "addr:full":"Hietzinger Hauptstr 5 Wien Wien 1130",
    "addr:housenumber":"5",
    "addr:postcode":"1130",
    "addr:street":"Hietzinger Hauptstr",
    "iso:country":"AT",
    "sg:address":"Hietzinger Hauptstr 5",
    "sg:city":"Wien",
    "sg:orig_category":"Friseure U Frisiersalons",
    "sg:phone":"+43 1 8769053",
    "sg:postcode":"1130",
    "sg:province":"Wien",
    "wof:name":"Intercoiffeur Strassl",
    "wof:placetype":"venue"
},
  "geometry": {"coordinates":[16.3010616302,48.1860160828],"type":"Point"}
}