{
  "type": "Feature",
  "properties": {
    "addr:full":"Fillgraderg 9 Wien Wien 1060",
    "addr:housenumber":"9",
    "addr:postcode":"1060",
    "addr:street":"Fillgraderg",
    "iso:country":"AT",
    "sg:address":"Fillgraderg 9",
    "sg:city":"Wien",
    "sg:orig_category":"Psychologen",
    "sg:phone":"+43 1 5877979",
    "sg:postcode":"1060",
    "sg:province":"Wien",
    "wof:name":"Wakolbinger Christine Mag",
    "wof:placetype":"venue"
},
  "geometry": {"coordinates":[16.3583545685,48.1996116638],"type":"Point"}
}