{
  "type": "Feature",
  "properties": {
    "addr:full":"Achstr 43 Wolfurt-Bahnhof Vorarlberg 6960",
    "addr:housenumber":"43",
    "addr:postcode":"6960",
    "addr:street":"Achstr",
    "iso:country":"AT",
    "sg:address":"Achstr 43",
    "sg:city":"Wolfurt-Bahnhof",
    "sg:orig_category":"Finanz- U Wirtschaftsberatung",
    "sg:phone":"+43 5574 71383",
    "sg:postcode":"6960",
    "sg:province":"Vorarlberg",
    "wof:name":"M\u00e4hr Walter Finanzierungen-Anlageberatung-Versicherungen",
    "wof:placetype":"venue"
},
  "geometry": {"coordinates":[9.7446241379,47.4819297791],"type":"Point"}
}