{
  "type": "Feature",
  "properties": {
    "iso:country":"AT",
    "sg:address":"Nr 81",
    "sg:city":"Ardning",
    "sg:orig_category":"Forstverwaltungen",
    "sg:phone":"+43 3612 7208",
    "sg:postcode":"8904",
    "sg:province":"Steiermark",
    "wof:name":"Forstverwaltung Stift Admont",
    "wof:placetype":"venue"
},
  "geometry": {"coordinates":[14.3644237518,47.5910682678],"type":"Point"}
}