{
  "type": "Feature",
  "properties": {
    "addr:full":"Rotdornallee 2 Wien Wien 1120",
    "addr:housenumber":"2",
    "addr:postcode":"1120",
    "addr:street":"Rotdornallee",
    "iso:country":"AT",
    "sg:address":"Rotdornallee 2",
    "sg:city":"Wien",
    "sg:orig_category":"Friseure U Frisiersalons",
    "sg:phone":"+43 1 6029567",
    "sg:postcode":"1120",
    "sg:province":"Wien",
    "wof:name":"Pivonka Peter - Friseur Peter",
    "wof:placetype":"venue"
},
  "geometry": {"coordinates":[16.3431625366,48.1711730957],"type":"Point"}
}