{
  "type": "Feature",
  "properties": {
    "iso:country":"AT",
    "sg:address":"Raunacher Str 16",
    "sg:city":"Reifnitz",
    "sg:orig_category":"Appartements / Ferienwohnungen",
    "sg:phone":"+43 4273 2223",
    "sg:postcode":"9081",
    "sg:province":"K\u00e4rnten",
    "wof:name":"Appartements Perdacher",
    "wof:placetype":"venue"
},
  "geometry": {"coordinates":[14.1818599701,46.6026229858],"type":"Point"}
}