{
  "type": "Feature",
  "properties": {
    "addr:full":"Bahnhofstr 45 Kalsdorf Steiermark 8401",
    "addr:housenumber":"45",
    "addr:postcode":"8401",
    "addr:street":"Bahnhofstr",
    "iso:country":"AT",
    "sg:address":"Bahnhofstr 45",
    "sg:city":"Kalsdorf",
    "sg:classifiers":[
        {
            "category":"Restaurant",
            "type":"Food & Drink"
        }
    ],
    "sg:phone":"+43 4331 3552410",
    "sg:postcode":"8401",
    "sg:province":"Steiermark",
    "wof:name":"Meyer Manfred",
    "wof:placetype":"venue"
},
  "geometry": {"coordinates":[15.4702157974,46.9648323059],"type":"Point"}
}