{
  "type": "Feature",
  "properties": {
    "iso:country":"AT",
    "sg:address":"G\u00e4rtnerstr 7",
    "sg:city":"Wels",
    "sg:orig_category":"Restaurants: Griechisch",
    "sg:phone":"+43 7242 45597",
    "sg:postcode":"4600",
    "sg:province":"Ober\u00f6sterreich",
    "wof:name":"Akropolis Hotel Pfefferm\u00fchle",
    "wof:placetype":"venue"
},
  "geometry": {"coordinates":[14.0262079239,48.1668395996],"type":"Point"}
}