{
  "type": "Feature",
  "properties": {
    "addr:full":"Hauptstr 58 Rottenmann Steiermark 8786",
    "addr:housenumber":"58",
    "addr:postcode":"8786",
    "addr:street":"Hauptstr",
    "iso:country":"AT",
    "sg:address":"Hauptstr 58",
    "sg:city":"Rottenmann",
    "sg:classifiers":[
        {
            "category":"Restaurant",
            "type":"Food & Drink"
        }
    ],
    "sg:phone":"+43 4336 1421031",
    "sg:postcode":"8786",
    "sg:province":"Steiermark",
    "sg:tags":[
        "pizzeria"
    ],
    "wof:name":"Pizzeria Dilans",
    "wof:placetype":"venue"
},
  "geometry": {"coordinates":[14.3574810028,47.5253753662],"type":"Point"}
}