{
  "type": "Feature",
  "properties": {
    "iso:country":"AT",
    "sg:address":"Leopold-P\u00f6schl-G 6",
    "sg:city":"B\u00fcrmoos",
    "sg:orig_category":"Unterhaltungselektronik / Einzelhandel",
    "sg:phone":"+43 4366 45133807",
    "sg:postcode":"5111",
    "sg:province":"Salzburg",
    "wof:name":"Hess Rudolf Hifi u High End-Anlagen",
    "wof:placetype":"venue"
},
  "geometry": {"coordinates":[12.9367456436,47.9917068481],"type":"Point"}
}