{
  "type": "Feature",
  "properties": {
    "addr:full":"Derffelgasse 1 Atzenbrugg Nieder\u00f6sterreich 3452",
    "addr:housenumber":"1",
    "addr:postcode":"3452",
    "addr:street":"Derffelgasse",
    "iso:country":"AT",
    "sg:address":"Derffelgasse 1",
    "sg:city":"Atzenbrugg",
    "sg:classifiers":[
        {
            "category":"Structure",
            "subcategory":"Tunnel",
            "type":"Public Place"
        }
    ],
    "sg:phone":"+43 2275 5036",
    "sg:postcode":"3452",
    "sg:province":"Nieder\u00f6sterreich",
    "sg:tags":[
        "aluminium",
        "fence"
    ],
    "wof:name":"Franz Haselmayer",
    "wof:placetype":"venue"
},
  "geometry": {"coordinates":[15.9075183868,48.2899284363],"type":"Point"}
}