{
  "type": "Feature",
  "properties": {
    "iso:country":"AT",
    "sg:address":"Bahnstr 27",
    "sg:city":"Hollabrunn",
    "sg:orig_category":"Versicherungsunternehmen",
    "sg:phone":"+43 4329 522864",
    "sg:postcode":"2020",
    "sg:province":"Nieder\u00f6sterreich",
    "wof:name":"Generali Gruppe",
    "wof:placetype":"venue"
},
  "geometry": {"coordinates":[16.0739688873,48.5628204346],"type":"Point"}
}