{
  "type": "Feature",
  "properties": {
    "addr:full":"Neudeggerg 17 Wien Wien 1080",
    "addr:housenumber":"17",
    "addr:postcode":"1080",
    "addr:street":"Neudeggerg",
    "iso:country":"AT",
    "sg:address":"Neudeggerg 17",
    "sg:city":"Wien",
    "sg:orig_category":"Rauchfangkehrer",
    "sg:phone":"+43 1 5239465",
    "sg:postcode":"1080",
    "sg:province":"Wien",
    "wof:name":"Walters Willibald Wwe Edith Walter",
    "wof:placetype":"venue"
},
  "geometry": {"coordinates":[16.3514785767,48.2075386047],"type":"Point"}
}