{
  "type": "Feature",
  "properties": {
    "addr:full":"Linzer G 37a Salzburg Salzburg 5020",
    "addr:housenumber":"37a",
    "addr:postcode":"5020",
    "addr:street":"Linzer G;Salzburg",
    "iso:country":"AT",
    "sg:address":"Linzer G 37a",
    "sg:city":"Salzburg",
    "sg:orig_category":"Tabaktrafiken",
    "sg:phone":"+43 662 884408",
    "sg:postcode":"5020",
    "sg:province":"Salzburg",
    "wof:name":"Hahnl Elke",
    "wof:placetype":"venue"
},
  "geometry": {"coordinates":[13.0472297668,47.8038063049],"type":"Point"}
}