{
  "type": "Feature",
  "properties": {
    "iso:country":"AT",
    "sg:address":"Hauptpl 19",
    "sg:city":"Stainz",
    "sg:orig_category":"Glasereien",
    "sg:phone":"+43 3463 21520",
    "sg:postcode":"8510",
    "sg:province":"Steiermark",
    "wof:name":"Fa\u00dfwald GesmbH",
    "wof:placetype":"venue"
},
  "geometry": {"coordinates":[15.2648382187,46.8936233521],"type":"Point"}
}