{
  "type": "Feature",
  "properties": {
    "addr:full":"Innsbruck Bundesstr 35 Salzburg Salzburg 5020",
    "addr:housenumber":"35",
    "addr:postcode":"5020",
    "addr:street":"Salzburg",
    "iso:country":"AT",
    "sg:address":"Innsbruck Bundesstr 35",
    "sg:city":"Salzburg",
    "sg:orig_category":"Physiotherapie",
    "sg:phone":"+43 662 90103300",
    "sg:postcode":"5020",
    "sg:province":"Salzburg",
    "wof:name":"physioplus - Physiotherapie Gemeinschaftspraxis",
    "wof:placetype":"venue"
},
  "geometry": {"coordinates":[13.0192985535,47.8044624329],"type":"Point"}
}