{
  "type": "Feature",
  "properties": {
    "addr:full":"Markt 4 Schenkenfelden Ober\u00f6sterreich 4192",
    "addr:housenumber":"4",
    "addr:postcode":"4192",
    "addr:street":"Markt",
    "iso:country":"AT",
    "sg:address":"Markt 4",
    "sg:city":"Schenkenfelden",
    "sg:orig_category":"Volksschulen",
    "sg:phone":"+43 4372 144350",
    "sg:postcode":"4192",
    "sg:province":"Ober\u00f6sterreich",
    "wof:name":"Volksschule",
    "wof:placetype":"venue"
},
  "geometry": {"coordinates":[14.362443924,48.502281189],"type":"Point"}
}