{
  "type": "Feature",
  "properties": {
    "addr:full":"Gellertg 36 Wien Wien 1100",
    "addr:housenumber":"36",
    "addr:postcode":"1100",
    "addr:street":"Gellertg",
    "iso:country":"AT",
    "sg:address":"Gellertg 36",
    "sg:city":"Wien",
    "sg:orig_category":"Waren Aller Art",
    "sg:phone":"+43 1 9610135",
    "sg:postcode":"1100",
    "sg:province":"Wien",
    "wof:name":"Gabi's Sammlertreff Inh Gabriele Vasina",
    "wof:placetype":"venue"
},
  "geometry": {"coordinates":[16.3744049072,48.1782684326],"type":"Point"}
}