{
  "type": "Feature",
  "properties": {
    "iso:country":"AT",
    "sg:address":"Am Ziegelofen 2A",
    "sg:city":"Schwadorf",
    "sg:classifiers":[
        {
            "category":"Restaurant",
            "type":"Food & Drink"
        }
    ],
    "sg:phone":"+43 2230 71446",
    "sg:postcode":"2432",
    "sg:province":"Nieder\u00f6sterreich",
    "wof:name":"Heurigenrestaurant am Ziegelofen",
    "wof:placetype":"venue"
},
  "geometry": {"coordinates":[16.577917099,48.0768356323],"type":"Point"}
}