{
  "type": "Feature",
  "properties": {
    "iso:country":"AT",
    "sg:address":"Nr 207",
    "sg:city":"Gro\u00dfarl",
    "sg:orig_category":"Drogerien",
    "sg:phone":"+43 6414 301",
    "sg:postcode":"5611",
    "sg:province":"Salzburg",
    "wof:name":"Vitzthum Helmut",
    "wof:placetype":"venue"
},
  "geometry": {"coordinates":[-87.1550292969,34.0147438049],"type":"Point"}
}