{
  "type": "Feature",
  "properties": {
    "addr:full":"Br\u00fcnner Str 138a/Top 3 Wien Wien 1210",
    "addr:housenumber":"138a / top 3",
    "addr:postcode":"1210",
    "addr:street":"Str",
    "iso:country":"AT",
    "sg:address":"Br\u00fcnner Str 138a/Top 3",
    "sg:city":"Wien",
    "sg:orig_category":"Boutiquen",
    "sg:phone":"+43 4312 925582",
    "sg:postcode":"1210",
    "sg:province":"Wien",
    "wof:name":"Boutique Sabine",
    "wof:placetype":"venue"
},
  "geometry": {"coordinates":[16.3978404999,48.2579994202],"type":"Point"}
}