{
  "type": "Feature",
  "properties": {
    "addr:full":"Oskar-Czeija-G 1 Wien Wien 1210",
    "addr:housenumber":"1",
    "addr:postcode":"1210",
    "addr:street":"Oskar-Czeija-G",
    "iso:country":"AT",
    "sg:address":"Oskar-Czeija-G 1",
    "sg:city":"Wien",
    "sg:orig_category":"Fernseh- U Radiogesellschaften",
    "sg:phone":"+43 4312 923559",
    "sg:postcode":"1210",
    "sg:province":"Wien",
    "wof:name":"ORF \u00f6sterreichischer Rundfunk",
    "wof:placetype":"venue"
},
  "geometry": {"coordinates":[16.382774353,48.3119430542],"type":"Point"}
}