{
  "type": "Feature",
  "properties": {
    "addr:full":"Badg 2 Gmunden Ober\u00f6sterreich 4810",
    "addr:housenumber":"2",
    "addr:postcode":"4810",
    "addr:street":"Badg;Oberoesterreich",
    "iso:country":"AT",
    "sg:address":"Badg 2",
    "sg:city":"Gmunden",
    "sg:orig_category":"Bekleidung / Einzelhandel",
    "sg:phone":"+43 761265271",
    "sg:postcode":"4810",
    "sg:province":"Ober\u00f6sterreich",
    "wof:name":"Benetton Gmunden",
    "wof:placetype":"venue"
},
  "geometry": {"coordinates":[13.7981462479,47.918598175],"type":"Point"}
}