{
  "type": "Feature",
  "properties": {
    "iso:country":"AT",
    "sg:address":"Bl\u00fchnbachstr 46",
    "sg:city":"Tenneck",
    "sg:orig_category":"Forstverwaltungen",
    "sg:phone":"+43 6468 52160",
    "sg:postcode":"5451",
    "sg:province":"Salzburg",
    "wof:name":"\u00d6sterreichische Bundesforste AG - Forstrevier Bl\u00fchnbach",
    "wof:placetype":"venue"
},
  "geometry": {"coordinates":[13.1755714417,47.4936599731],"type":"Point"}
}