{
  "type": "Feature",
  "properties": {
    "iso:country":"AT",
    "sg:address":"Florianig 14",
    "sg:city":"Absdorf",
    "sg:orig_category":"Installationsunternehmen",
    "sg:phone":"+43 2278 3110",
    "sg:postcode":"3462",
    "sg:province":"Nieder\u00f6sterreich",
    "wof:name":"Installationen Leutgeb",
    "wof:placetype":"venue"
},
  "geometry": {"coordinates":[15.9370012283,48.3903541565],"type":"Point"}
}