{
  "type": "Feature",
  "properties": {
    "addr:full":"Obere Donaustr 19 Wien Wien 1020",
    "addr:housenumber":"19",
    "addr:postcode":"1020",
    "addr:street":"Obere Donaustr",
    "iso:country":"AT",
    "sg:address":"Obere Donaustr 19",
    "sg:city":"Wien",
    "sg:orig_category":"Banken U Sparkassen",
    "sg:phone":"+43 1 331710",
    "sg:postcode":"1020",
    "sg:province":"Wien",
    "sg:website":"www.immotrust.at",
    "wof:name":"Bank Austria Creditanstalt ImmoTrust GmbH",
    "wof:placetype":"venue"
},
  "geometry": {"coordinates":[16.3697452545,48.2229957581],"type":"Point"}
}