{
  "type": "Feature",
  "properties": {
    "iso:country":"AT",
    "sg:address":"Emmerbergg 52",
    "sg:city":"Wiener Neustadt",
    "sg:orig_category":"Tischlereien",
    "sg:phone":"+43 2622 244570",
    "sg:postcode":"2700",
    "sg:province":"Nieder\u00f6sterreich",
    "wof:name":"Raidl Friedrich",
    "wof:placetype":"venue"
},
  "geometry": {"coordinates":[16.2236156464,47.809135437],"type":"Point"}
}