{
  "type": "Feature",
  "properties": {
    "addr:full":"Marxerg 39 Wien Wien 1030",
    "addr:housenumber":"39",
    "addr:postcode":"1030",
    "addr:street":"Marxerg",
    "iso:country":"AT",
    "sg:address":"Marxerg 39",
    "sg:city":"Wien",
    "sg:orig_category":"Innenarchitekten",
    "sg:phone":"+43 4369 912733079",
    "sg:postcode":"1030",
    "sg:province":"Wien",
    "wof:name":"studio th\u00f6rnblom - b\u00fcro f\u00fcr innenarchitektur",
    "wof:placetype":"venue"
},
  "geometry": {"coordinates":[16.3954029083,48.2052497864],"type":"Point"}
}