{
  "type": "Feature",
  "properties": {
    "addr:full":"Nr 9a Kirchberg an der Raab Steiermark 8324",
    "addr:postcode":"8324",
    "addr:street":"Nr 9A",
    "iso:country":"AT",
    "sg:address":"Nr 9a",
    "sg:city":"Kirchberg an der Raab",
    "sg:orig_category":"Bauunternehmen",
    "sg:phone":"+43 3115 40700",
    "sg:postcode":"8324",
    "sg:province":"Steiermark",
    "wof:name":"Platzer Gesamtbau",
    "wof:placetype":"venue"
},
  "geometry": {"coordinates":[15.7642307281,46.9871444702],"type":"Point"}
}