{
  "type": "Feature",
  "properties": {
    "iso:country":"AT",
    "sg:address":"Laabstr 100a",
    "sg:city":"Braunau am Inn",
    "sg:orig_category":"Blumeneinzelhandel",
    "sg:phone":"+43 7722 65911",
    "sg:postcode":"5280",
    "sg:province":"Ober\u00f6sterreich",
    "wof:name":"Blumenladen Maria Inh Maria Weber",
    "wof:placetype":"venue"
},
  "geometry": {"coordinates":[13.065123558,48.2557411194],"type":"Point"}
}