{
  "type": "Feature",
  "properties": {
    "addr:full":"Rettenbach 546 S\u00f6lden Tirol 6450",
    "addr:housenumber":"546",
    "addr:postcode":"6450",
    "addr:street":"Rettenbach;Tirol",
    "iso:country":"AT",
    "sg:address":"Rettenbach 546",
    "sg:city":"S\u00f6lden",
    "sg:orig_category":"Pensionen / Privatzimmer",
    "sg:phone":"+43 4352 542571",
    "sg:postcode":"6450",
    "sg:province":"Tirol",
    "wof:name":"G\u00e4stehaus Jasmin",
    "wof:placetype":"venue"
},
  "geometry": {"coordinates":[11.0101947784,46.9675750732],"type":"Point"}
}