{
  "type": "Feature",
  "properties": {
    "iso:country":"AT",
    "sg:address":"Piburg 16",
    "sg:city":"Oetz",
    "sg:orig_category":"Tischlereien",
    "sg:phone":"+43 5252 63450",
    "sg:postcode":"6433",
    "sg:province":"Tirol",
    "wof:name":"Plattner Ferdinand",
    "wof:placetype":"venue"
},
  "geometry": {"coordinates":[10.8800096512,47.1973342896],"type":"Point"}
}