{
  "type": "Feature",
  "properties": {
    "addr:full":"Taugl 28 St. Koloman Salzburg 5423",
    "addr:housenumber":"28",
    "addr:postcode":"5423",
    "addr:street":"Taugl",
    "iso:country":"AT",
    "sg:address":"Taugl 28",
    "sg:city":"St. Koloman",
    "sg:orig_category":"Non-Classified Establishments",
    "sg:phone":"+43 6241 214",
    "sg:postcode":"5423",
    "sg:province":"Salzburg",
    "wof:name":"Pfarramt",
    "wof:placetype":"venue"
},
  "geometry": {"coordinates":[13.2200908661,47.6502151489],"type":"Point"}
}