{
  "type": "Feature",
  "properties": {
    "addr:full":"Br\u00fcnner Strasse 282 Wien Wien 1210",
    "addr:housenumber":"282",
    "addr:postcode":"1210",
    "addr:street":"Bruenner Strasse",
    "iso:country":"AT",
    "sg:address":"Br\u00fcnner Strasse 282",
    "sg:city":"Wien",
    "sg:classifiers":[
        {
            "category":"Home & Garden",
            "subcategory":"Garden Supply",
            "type":"Retail Goods"
        }
    ],
    "sg:phone":"+43 1 2720330",
    "sg:postcode":"1210",
    "sg:province":"Wien",
    "sg:tags":[
        "equipment",
        "playground"
    ],
    "sg:website":"haiderspielplatz.at",
    "wof:name":"Austroplay Inh. Sabine Haider",
    "wof:placetype":"venue"
},
  "geometry": {"coordinates":[16.3978404999,48.2579994202],"type":"Point"}
}