{
  "type": "Feature",
  "properties": {
    "addr:full":"Pinnisweg 27 Neustift im Stubaital Tirol 6167",
    "addr:housenumber":"27",
    "addr:postcode":"6167",
    "addr:street":"Pinnisweg;Tirol",
    "iso:country":"AT",
    "sg:address":"Pinnisweg 27",
    "sg:city":"Neustift im Stubaital",
    "sg:classifiers":[
        {
            "category":"Taxi",
            "type":"Transportation"
        }
    ],
    "sg:phone":"+43 4352 262380",
    "sg:postcode":"6167",
    "sg:province":"Tirol",
    "sg:tags":[
        "personentransporte",
        "u"
    ],
    "wof:name":"Hofer Franz",
    "wof:placetype":"venue"
},
  "geometry": {"coordinates":[11.3275442123,47.1204223633],"type":"Point"}
}