{
  "type": "Feature",
  "properties": {
    "addr:full":"Urbarialsdlg 46 Parndorf Burgenland 7111",
    "addr:housenumber":"46",
    "addr:postcode":"7111",
    "addr:street":"Urbarialsdlg",
    "iso:country":"AT",
    "sg:address":"Urbarialsdlg 46",
    "sg:city":"Parndorf",
    "sg:orig_category":"Marketingberatung",
    "sg:phone":"+43 699 11407369",
    "sg:postcode":"7111",
    "sg:province":"Burgenland",
    "wof:name":"NetMarkPro",
    "wof:placetype":"venue"
},
  "geometry": {"coordinates":[16.8575897217,47.9981613159],"type":"Point"}
}