{
  "type": "Feature",
  "properties": {
    "addr:full":"Nr 76 Laimbach am Ostrong Nieder\u00f6sterreich 3663",
    "addr:postcode":"3663",
    "addr:street":"Nr 76",
    "iso:country":"AT",
    "sg:address":"Nr 76",
    "sg:city":"Laimbach am Ostrong",
    "sg:orig_category":"Banken U Sparkassen",
    "sg:phone":"+43 4327 585216",
    "sg:postcode":"3663",
    "sg:province":"Nieder\u00f6sterreich",
    "wof:name":"Raiffeisenbank Region Melk regGenmbH",
    "wof:placetype":"venue"
},
  "geometry": {"coordinates":[15.1219797134,48.3162994385],"type":"Point"}
}