{
  "type": "Feature",
  "properties": {
    "addr:full":"Alser Str 22 Wien Wien 1090",
    "addr:postcode":"1090",
    "addr:street":"Str 22",
    "iso:country":"AT",
    "sg:address":"Alser Str 22",
    "sg:city":"Wien",
    "sg:orig_category":"Psychologen",
    "sg:phone":"+43 1 4055423",
    "sg:postcode":"1090",
    "sg:province":"Wien",
    "wof:name":"Trallori David Mag",
    "wof:placetype":"venue"
},
  "geometry": {"coordinates":[16.3483352661,48.215423584],"type":"Point"}
}