{
  "type": "Feature",
  "properties": {
    "addr:full":"Bahnhofstr 43 Voitsberg Steiermark 8570",
    "addr:postcode":"8570",
    "addr:street":"Bahnhofstr 43",
    "iso:country":"AT",
    "sg:address":"Bahnhofstr 43",
    "sg:city":"Voitsberg",
    "sg:orig_category":"Bars-Cafes",
    "sg:phone":"+43 3142 28483",
    "sg:postcode":"8570",
    "sg:province":"Steiermark",
    "wof:name":"Taurer- Forstner & Partner OEG",
    "wof:placetype":"venue"
},
  "geometry": {"coordinates":[15.1497459412,47.0442695618],"type":"Point"}
}