{
  "type": "Feature",
  "properties": {
    "addr:full":"Burgenlandstr 18 Innsbruck Tirol 6020",
    "addr:housenumber":"18",
    "addr:postcode":"6020",
    "addr:street":"Burgenlandstr;Tirol",
    "iso:country":"AT",
    "sg:address":"Burgenlandstr 18",
    "sg:city":"Innsbruck",
    "sg:orig_category":"Autoreparatur",
    "sg:phone":"+43 512 566649",
    "sg:postcode":"6020",
    "sg:province":"Tirol",
    "wof:name":"Biechl Robert KEG",
    "wof:placetype":"venue"
},
  "geometry": {"coordinates":[11.4135427475,47.2592582703],"type":"Point"}
}