{
  "type": "Feature",
  "properties": {
    "addr:full":"Ungerg 6 Graz Steiermark 8020",
    "addr:housenumber":"6",
    "addr:postcode":"8020",
    "addr:street":"Ungerg",
    "iso:country":"AT",
    "sg:address":"Ungerg 6",
    "sg:city":"Graz",
    "sg:orig_category":"Friseure U Frisiersalons",
    "sg:phone":"+43 4331 6766067",
    "sg:postcode":"8020",
    "sg:province":"Steiermark",
    "wof:name":"Salon Adil",
    "wof:placetype":"venue"
},
  "geometry": {"coordinates":[15.4262647629,47.0673217773],"type":"Point"}
}