{
  "type": "Feature",
  "properties": {
    "addr:full":"Nr 444 Nauders Tirol 6543",
    "addr:postcode":"6543",
    "addr:street":"Nr 444;Tirol",
    "iso:country":"AT",
    "sg:address":"Nr 444",
    "sg:city":"Nauders",
    "sg:orig_category":"Appartements / Ferienwohnungen",
    "sg:phone":"+43 5473 87444",
    "sg:postcode":"6543",
    "sg:province":"Tirol",
    "wof:name":"Jennewein Hermann",
    "wof:placetype":"venue"
},
  "geometry": {"coordinates":[10.4996595383,46.8896980286],"type":"Point"}
}