{
  "type": "Feature",
  "properties": {
    "addr:full":"Sechtergasse 18 Wien Wien 1120",
    "addr:housenumber":"18",
    "addr:postcode":"1120",
    "addr:street":"Sechtergasse",
    "iso:country":"AT",
    "sg:address":"Sechtergasse 18",
    "sg:city":"Wien",
    "sg:classifiers":[
        {
            "category":"Manufacturing",
            "subcategory":"Metals",
            "type":"Manufacturing & Wholesale Goods"
        }
    ],
    "sg:phone":"+43 1 8132354",
    "sg:postcode":"1120",
    "sg:province":"Wien",
    "sg:tags":[
        "alloy",
        "construction",
        "lightweight"
    ],
    "sg:website":"metallportal.at",
    "wof:name":"Theodor Duchoslav Ges.m.b.H. & Co KG",
    "wof:placetype":"venue"
},
  "geometry": {"coordinates":[16.3307056427,48.1767311096],"type":"Point"}
}