{
  "type": "Feature",
  "properties": {
    "iso:country":"AT",
    "sg:address":"Industriestr 23",
    "sg:city":"Herzogenburg",
    "sg:orig_category":"Metallwaren / Erzeugung U Gro\u00c3\u0178handel",
    "sg:phone":"+43 2782 852470",
    "sg:postcode":"3130",
    "sg:province":"Nieder\u00f6sterreich",
    "wof:name":"RHEINZINK AUSTRIA GMBH",
    "wof:placetype":"venue"
},
  "geometry": {"coordinates":[15.692864418,48.2682113647],"type":"Point"}
}