{
  "type": "Feature",
  "properties": {
    "addr:full":"Eiseng. 44 Dornbirn Vorarlberg 6850",
    "addr:housenumber":"44",
    "addr:postcode":"6850",
    "addr:street":"Eiseng.",
    "iso:country":"AT",
    "sg:address":"Eiseng. 44",
    "sg:city":"Dornbirn",
    "sg:classifiers":[
        {
            "category":"Shopping",
            "subcategory":"Crafts & Fabrics",
            "type":"Retail Goods"
        }
    ],
    "sg:phone":"+43 4355 723990",
    "sg:postcode":"6850",
    "sg:province":"Vorarlberg",
    "wof:name":"F. M. HEMMERLE TEXTIELWERKE GMBH",
    "wof:placetype":"venue"
},
  "geometry": {"coordinates":[9.7437801361,47.4131889343],"type":"Point"}
}