{
  "type": "Feature",
  "properties": {
    "addr:full":"Bacherstrasse 1 Hirm Burgenland 7024",
    "addr:housenumber":"1",
    "addr:postcode":"7024",
    "addr:street":"Bacherstrasse",
    "iso:country":"AT",
    "sg:address":"Bacherstrasse 1",
    "sg:city":"Hirm",
    "sg:classifiers":[
        {
            "category":"Manufacturing",
            "subcategory":"Printing",
            "type":"Manufacturing & Wholesale Goods"
        }
    ],
    "sg:phone":"+43 2687 47510",
    "sg:postcode":"7024",
    "sg:province":"Burgenland",
    "sg:tags":[
        "house",
        "book"
    ],
    "sg:website":"kiss-edv.at/druckpartner",
    "wof:name":"Druck Partner GesmbH",
    "wof:placetype":"venue"
},
  "geometry": {"coordinates":[16.4570045471,47.785785675],"type":"Point"}
}