{
  "type": "Feature",
  "properties": {
    "addr:full":"Moosen 28 Brixen im Thale Tirol 6364",
    "addr:housenumber":"28",
    "addr:postcode":"6364",
    "addr:street":"Moosen;Tirol",
    "iso:country":"AT",
    "sg:address":"Moosen 28",
    "sg:city":"Brixen im Thale",
    "sg:orig_category":"Pensionen / Privatzimmer",
    "sg:phone":"+43 5334 6930",
    "sg:postcode":"6364",
    "sg:province":"Tirol",
    "wof:name":"Samerhof",
    "wof:placetype":"venue"
},
  "geometry": {"coordinates":[12.2265024185,47.4446525574],"type":"Point"}
}