{
  "type": "Feature",
  "properties": {
    "addr:full":"Kaiser-Franz-Josef-Str 3 Lustenau Vorarlberg 6890",
    "addr:housenumber":"3",
    "addr:postcode":"6890",
    "addr:street":"Kaiser-Franz-Josef-Str",
    "iso:country":"AT",
    "sg:address":"Kaiser-Franz-Josef-Str 3",
    "sg:city":"Lustenau",
    "sg:orig_category":"Stickereien",
    "sg:phone":"+43 4355 77825680",
    "sg:postcode":"6890",
    "sg:province":"Vorarlberg",
    "wof:name":"Alge Oskar GesmbH & Co",
    "wof:placetype":"venue"
},
  "geometry": {"coordinates":[9.6585502625,47.4256820679],"type":"Point"}
}