{
  "type": "Feature",
  "properties": {
    "iso:country":"AT",
    "sg:address":"W\u00e4hringer Str 96",
    "sg:city":"Wien",
    "sg:orig_category":"Zeitungen U Zeitschriften",
    "sg:phone":"+43 1 4796416",
    "sg:postcode":"1180",
    "sg:province":"Wien",
    "wof:name":"Die Anzeige - Peter H Boennecken",
    "wof:placetype":"venue"
},
  "geometry": {"coordinates":[16.3466148376,48.225692749],"type":"Point"}
}