{
  "type": "Feature",
  "properties": {
    "addr:full":"Nr. 9  Donnersbach Steiermark 8953",
    "addr:postcode":"8953",
    "iso:country":"AT",
    "sg:address":"Nr. 9 ",
    "sg:city":"Donnersbach",
    "sg:classifiers":[
        {
            "category":"Farming",
            "subcategory":"Livestock Farm",
            "type":"Manufacturing & Wholesale Goods"
        }
    ],
    "sg:phone":"+43 4336 832222",
    "sg:postcode":"8953",
    "sg:province":"Steiermark",
    "sg:tags":[
        "agriculture"
    ],
    "wof:name":"FORSTVERWALTUNG DONNERSBACH D. ALWA AG",
    "wof:placetype":"venue"
},
  "geometry": {"coordinates":[14.1284208298,47.465587616],"type":"Point"}
}