{
  "type": "Feature",
  "properties": {
    "addr:full":"Ungarg 111 Oberpullendorf Burgenland 7350",
    "addr:housenumber":"111",
    "addr:postcode":"7350",
    "iso:country":"AT",
    "sg:address":"Ungarg 111",
    "sg:city":"Oberpullendorf",
    "sg:orig_category":"Autoelektrik U -Ersatzteile",
    "sg:phone":"+43 4326 12426040",
    "sg:postcode":"7350",
    "sg:province":"Burgenland",
    "wof:name":"Kromberg & Schubert Austria GesmbH u Co KG",
    "wof:placetype":"venue"
},
  "geometry": {"coordinates":[16.5226325989,47.4882049561],"type":"Point"}
}