{
  "type": "Feature",
  "properties": {
    "iso:country":"AT",
    "sg:address":"Nr 348",
    "sg:city":"Wenns",
    "sg:orig_category":"Appartements / Ferienwohnungen",
    "sg:phone":"+43 5414 87415",
    "sg:postcode":"6473",
    "sg:province":"Tirol",
    "wof:name":"Pension Rosenheim",
    "wof:placetype":"venue"
},
  "geometry": {"coordinates":[10.7312002182,47.1684265137],"type":"Point"}
}