{
  "type": "Feature",
  "properties": {
    "iso:country":"AT",
    "sg:address":"Simmeringer Hauptstr 195a",
    "sg:city":"Wien",
    "sg:orig_category":"Tabaktrafiken",
    "sg:phone":"+43 1 7693248",
    "sg:postcode":"1110",
    "sg:province":"Wien",
    "wof:name":"Hawliczek Karl",
    "wof:placetype":"venue"
},
  "geometry": {"coordinates":[16.4239940643,48.1671524048],"type":"Point"}
}