{
  "type": "Feature",
  "properties": {
    "addr:full":"Oberschwende 118 Schwarzach Vorarlberg 6858",
    "addr:housenumber":"118",
    "addr:postcode":"6858",
    "addr:street":"Oberschwende",
    "iso:country":"AT",
    "sg:address":"Oberschwende 118",
    "sg:city":"Schwarzach",
    "sg:orig_category":"Erdarbeiten",
    "sg:phone":"+43 664 3359818",
    "sg:postcode":"6858",
    "sg:province":"Vorarlberg",
    "wof:name":"Niederbacher Werner",
    "wof:placetype":"venue"
},
  "geometry": {"coordinates":[9.7929859161,47.4505081177],"type":"Point"}
}