{
  "type": "Feature",
  "properties": {
    "iso:country":"AT",
    "sg:address":"Wexstr 19-23",
    "sg:city":"Wien",
    "sg:orig_category":"Papier- U Schreibwaren / Einzelhandel",
    "sg:phone":"+43 1 3343490",
    "sg:postcode":"1200",
    "sg:province":"Wien",
    "wof:name":"Schulshop TGM",
    "wof:placetype":"venue"
},
  "geometry": {"coordinates":[16.3679065704,48.2361450195],"type":"Point"}
}