{
  "type": "Feature",
  "properties": {
    "addr:full":"G\u00e4nserndorfer Str 32 Deutsch Wagram Nieder\u00f6sterreich 2232",
    "addr:housenumber":"32",
    "addr:postcode":"2232",
    "addr:street":"Str",
    "iso:country":"AT",
    "sg:address":"G\u00e4nserndorfer Str 32",
    "sg:city":"Deutsch Wagram",
    "sg:orig_category":"Lebensmittel / Einzelhandel",
    "sg:phone":"+43 2247 3393",
    "sg:postcode":"2232",
    "sg:province":"Nieder\u00f6sterreich",
    "wof:name":"Zielpunkt Warenhandel GmbH & Co KG",
    "wof:placetype":"venue"
},
  "geometry": {"coordinates":[16.5681190491,48.3001213074],"type":"Point"}
}