{
  "type": "Feature",
  "properties": {
    "addr:full":"Nr 12 Aggsbach Markt Nieder\u00f6sterreich 3641",
    "addr:housenumber":"3641",
    "addr:street":"Nr;Aggsbach;Niederoesterreich",
    "iso:country":"AT",
    "sg:address":"Nr 12",
    "sg:city":"Aggsbach Markt",
    "sg:orig_category":"Volksschulen",
    "sg:phone":"+43 2712 512",
    "sg:postcode":"3641",
    "sg:province":"Nieder\u00f6sterreich",
    "wof:name":"Volksschule Aggsbach Markt",
    "wof:placetype":"venue"
},
  "geometry": {"coordinates":[15.4036645889,48.2940368652],"type":"Point"}
}