{
  "type": "Feature",
  "properties": {
    "addr:full":"Weyringerg 30a Wien Wien 1040",
    "addr:housenumber":"30a",
    "addr:postcode":"1040",
    "addr:street":"Weyringerg",
    "iso:country":"AT",
    "sg:address":"Weyringerg 30a",
    "sg:city":"Wien",
    "sg:orig_category":"Cd-Roms, Dvd",
    "sg:phone":"+43 1 5046801",
    "sg:postcode":"1040",
    "sg:province":"Wien",
    "wof:name":"matic CD-Rom & Internet - Ladst\u00e4tter Stefan",
    "wof:placetype":"venue"
},
  "geometry": {"coordinates":[16.3751277924,48.1885070801],"type":"Point"}
}