{
  "type": "Feature",
  "properties": {
    "addr:full":"An der Bundesstr 13 Timmersdorf Steiermark 8772",
    "addr:housenumber":"13",
    "addr:postcode":"8772",
    "addr:street":"An Der Bundesstr",
    "iso:country":"AT",
    "sg:address":"An der Bundesstr 13",
    "sg:city":"Timmersdorf",
    "sg:orig_category":"Metallbe- U -Verarbeitung",
    "sg:phone":"+43 3833 8751",
    "sg:postcode":"8772",
    "sg:province":"Steiermark",
    "wof:name":"METRIS Fertigungstechnik GmbH",
    "wof:placetype":"venue"
},
  "geometry": {"coordinates":[14.9726171494,47.3791007996],"type":"Point"}
}