{
  "type": "Feature",
  "properties": {
    "addr:full":"Ringstr 8 St. Pantaleon Nieder\u00f6sterreich 4303",
    "addr:housenumber":"8",
    "addr:postcode":"4303",
    "addr:street":"Ringstr",
    "iso:country":"AT",
    "sg:address":"Ringstr 8",
    "sg:city":"St. Pantaleon",
    "sg:orig_category":"\u00c3\u201erzte / F Allgemeinmedizin",
    "sg:phone":"+43 4374 357570",
    "sg:postcode":"4303",
    "sg:province":"Nieder\u00f6sterreich",
    "wof:name":"Hagenhuber Fritz Dr",
    "wof:placetype":"venue"
},
  "geometry": {"coordinates":[14.5675086975,48.2103652954],"type":"Point"}
}