{
  "type": "Feature",
  "properties": {
    "addr:full":"K\u00e4rntner Str 25/II Graz Steiermark 8020",
    "addr:housenumber":"25 / ii",
    "addr:postcode":"8020",
    "addr:street":"Str",
    "iso:country":"AT",
    "sg:address":"K\u00e4rntner Str 25/II",
    "sg:city":"Graz",
    "sg:orig_category":"Behinderungen / Leben Mit Behinderungen",
    "sg:phone":"+43 316 716119",
    "sg:postcode":"8020",
    "sg:province":"Steiermark",
    "wof:name":"Jugend am Werk Steiermark GmbH - Wohnhaus",
    "wof:placetype":"venue"
},
  "geometry": {"coordinates":[15.4111499786,47.0689201355],"type":"Point"}
}