{
  "type": "Feature",
  "properties": {
    "addr:full":"Schulgarteng 6 Prinzersdorf Nieder\u00f6sterreich 3385",
    "addr:housenumber":"6",
    "addr:postcode":"3385",
    "addr:street":"Schulgarteng",
    "iso:country":"AT",
    "sg:address":"Schulgarteng 6",
    "sg:city":"Prinzersdorf",
    "sg:orig_category":"Friseure U Frisiersalons",
    "sg:phone":"+43 664 2208930",
    "sg:postcode":"3385",
    "sg:province":"Nieder\u00f6sterreich",
    "wof:name":"Mobilfriseur Daniela Bernd",
    "wof:placetype":"venue"
},
  "geometry": {"coordinates":[15.5011911392,48.1929016113],"type":"Point"}
}