{
  "type": "Feature",
  "properties": {
    "addr:full":"Richard Wagner-Str 22 Villach K\u00e4rnten 9500",
    "addr:housenumber":"22",
    "addr:postcode":"9500",
    "addr:street":"Kaernten",
    "iso:country":"AT",
    "sg:address":"Richard Wagner-Str 22",
    "sg:city":"Villach",
    "sg:orig_category":"Friseure U Frisiersalons",
    "sg:phone":"+43 4242 24481",
    "sg:postcode":"9500",
    "sg:province":"K\u00e4rnten",
    "wof:name":"Buser Astrid",
    "wof:placetype":"venue"
},
  "geometry": {"coordinates":[13.8452720642,46.6065368652],"type":"Point"}
}