{
  "type": "Feature",
  "properties": {
    "addr:full":"null NB Stadtschlaining Burgenland 7461",
    "addr:postcode":"7461",
    "iso:country":"AT",
    "sg:address":"null NB",
    "sg:city":"Stadtschlaining",
    "sg:classifiers":[
        {
            "category":"Home & Garden",
            "subcategory":"Building Materials",
            "type":"Retail Goods"
        }
    ],
    "sg:phone":"+43 4333 5522580",
    "sg:postcode":"7461",
    "sg:province":"Burgenland",
    "sg:tags":[
        "baustoffe",
        "-material",
        "u"
    ],
    "wof:name":"AWT Asphaltwerk GmbH",
    "wof:placetype":"venue"
},
  "geometry": {"coordinates":[16.2792205811,47.3237075806],"type":"Point"}
}