{
  "type": "Feature",
  "properties": {
    "addr:full":"Kaindorf Steiermark 8224",
    "addr:postcode":"8224",
    "iso:country":"AT",
    "sg:city":"Kaindorf",
    "sg:orig_category":"Bauunternehmen",
    "sg:phone":"+43 4333 3424100",
    "sg:postcode":"8224",
    "sg:province":"Steiermark",
    "wof:name":"Swietelsky BaugesmbH",
    "wof:placetype":"venue"
},
  "geometry": {"coordinates":[15.8666696548,47.2195091248],"type":"Point"}
}