{
  "type": "Feature",
  "properties": {
    "addr:full":"Lange G 454 Schladming Steiermark 8970",
    "addr:housenumber":"454",
    "addr:postcode":"8970",
    "addr:street":"Lange G",
    "iso:country":"AT",
    "sg:address":"Lange G 454",
    "sg:city":"Schladming",
    "sg:orig_category":"Friseure U Frisiersalons",
    "sg:phone":"+43 3687 24155",
    "sg:postcode":"8970",
    "sg:province":"Steiermark",
    "wof:name":"Look - Dein Friseur",
    "wof:placetype":"venue"
},
  "geometry": {"coordinates":[13.692243576,47.3941307068],"type":"Point"}
}