{
  "type": "Feature",
  "properties": {
    "addr:full":"Ausstellungsstr 17 Wien Wien 1020",
    "addr:housenumber":"17",
    "addr:postcode":"1020",
    "addr:street":"Ausstellungsstr",
    "iso:country":"AT",
    "sg:address":"Ausstellungsstr 17",
    "sg:city":"Wien",
    "sg:orig_category":"Psychotherapie",
    "sg:phone":"+43 1 7283911",
    "sg:postcode":"1020",
    "sg:province":"Wien",
    "sg:website":"members.surfeu.at/zipp",
    "wof:name":"ZIPP-Zentrum f Integrative Psychosomatik und Psychotherapie",
    "wof:placetype":"venue"
},
  "geometry": {"coordinates":[16.3999767303,48.2181663513],"type":"Point"}
}