{
  "type": "Feature",
  "properties": {
    "addr:full":"F\u00f6hrenweg 5 Treffen K\u00e4rnten 9521",
    "addr:housenumber":"5",
    "addr:postcode":"9521",
    "addr:street":"Foehrenweg;Kaernten",
    "iso:country":"AT",
    "sg:address":"F\u00f6hrenweg 5",
    "sg:city":"Treffen",
    "sg:orig_category":"Webdesign",
    "sg:phone":"+43 650 4400022",
    "sg:postcode":"9521",
    "sg:province":"K\u00e4rnten",
    "wof:name":"IT-CONSULTING",
    "wof:placetype":"venue"
},
  "geometry": {"coordinates":[13.8552322388,46.6679840088],"type":"Point"}
}