{
  "type": "Feature",
  "properties": {
    "addr:full":"St Peter Hauptstr 2 St. Peter Steiermark 8042",
    "addr:housenumber":"2",
    "addr:postcode":"8042",
    "addr:street":"Hauptstr",
    "iso:country":"AT",
    "sg:address":"St Peter Hauptstr 2",
    "sg:city":"St. Peter",
    "sg:orig_category":"Friseure U Frisiersalons",
    "sg:phone":"+43 316 462300",
    "sg:postcode":"8042",
    "sg:province":"Steiermark",
    "wof:name":"Kamm on",
    "wof:placetype":"venue"
},
  "geometry": {"coordinates":[15.4742012024,47.0548553467],"type":"Point"}
}