{
  "type": "Feature",
  "properties": {
    "iso:country":"AT",
    "sg:address":"Markt 24",
    "sg:city":"Abtenau",
    "sg:orig_category":"Trachtenbekleidung",
    "sg:phone":"+43 6243 2408",
    "sg:postcode":"5441",
    "sg:province":"Salzburg",
    "wof:name":"Abtenauer Trachtenstube Marianne Gsenger",
    "wof:placetype":"venue"
},
  "geometry": {"coordinates":[13.3385505676,47.5679168701],"type":"Point"}
}