{
  "type": "Feature",
  "properties": {
    "iso:country":"AT",
    "sg:address":"G\u00fcssinger Strasse 243",
    "sg:city":"St. Michael im Burgenland",
    "sg:classifiers":[
        {
            "category":"Home & Garden",
            "subcategory":"Building Materials",
            "type":"Retail Goods"
        }
    ],
    "sg:phone":"+43 3327 2430",
    "sg:postcode":"7535",
    "sg:province":"Burgenland",
    "sg:tags":[
        "steel",
        "metal",
        "made",
        "door",
        "gate"
    ],
    "sg:website":"gerger-steel.at",
    "wof:name":"Stahlbau Gerger GmbH",
    "wof:placetype":"venue"
},
  "geometry": {"coordinates":[16.2596359253,47.1686592102],"type":"Point"}
}