{
  "type": "Feature",
  "properties": {
    "addr:full":"Pantherstr 13 Judenburg Steiermark 8750",
    "addr:housenumber":"13",
    "addr:postcode":"8750",
    "addr:street":"Pantherstr",
    "iso:country":"AT",
    "sg:address":"Pantherstr 13",
    "sg:city":"Judenburg",
    "sg:orig_category":"Fitnesscenter",
    "sg:phone":"+43 4366 42230565",
    "sg:postcode":"8750",
    "sg:province":"Steiermark",
    "wof:name":"Fitnesscenter Body Form",
    "wof:placetype":"venue"
},
  "geometry": {"coordinates":[14.6741724014,47.1763839722],"type":"Point"}
}