{
  "type": "Feature",
  "properties": {
    "addr:full":"Wiener Str 6 Enns Ober\u00f6sterreich 4470",
    "addr:postcode":"4470",
    "addr:street":"Oberoesterreich",
    "iso:country":"AT",
    "sg:address":"Wiener Str 6",
    "sg:city":"Enns",
    "sg:orig_category":"Physiotherapie",
    "sg:phone":"+43 4367 64294280",
    "sg:postcode":"4470",
    "sg:province":"Ober\u00f6sterreich",
    "wof:name":"Weinberger Gertrude Dipl-PT",
    "wof:placetype":"venue"
},
  "geometry": {"coordinates":[14.4791498184,48.2126502991],"type":"Point"}
}