{
  "type": "Feature",
  "properties": {
    "iso:country":"AT",
    "sg:address":"Forstamtsg 100",
    "sg:city":"Tamsweg",
    "sg:orig_category":"Steuerberatung",
    "sg:phone":"+43 6474 25300",
    "sg:postcode":"5580",
    "sg:province":"Salzburg",
    "wof:name":"Etschbacher Renate",
    "wof:placetype":"venue"
},
  "geometry": {"coordinates":[13.8100452423,47.1273956299],"type":"Point"}
}