{
  "type": "Feature",
  "properties": {
    "iso:country":"AT",
    "sg:address":"Nr 46",
    "sg:city":"Strau",
    "sg:orig_category":"Elektroinstallationsunternehmen",
    "sg:phone":"+43 4227 5617",
    "sg:postcode":"9162",
    "sg:province":"K\u00e4rnten",
    "wof:name":"Stern Stefan",
    "wof:placetype":"venue"
},
  "geometry": {"coordinates":[14.2556695938,46.538898468],"type":"Point"}
}