{
  "type": "Feature",
  "properties": {
    "addr:full":"Mittriedstr. 13 Hard Vorarlberg 6971",
    "addr:housenumber":"13",
    "addr:postcode":"6971",
    "addr:street":"Mittriedstr.",
    "iso:country":"AT",
    "sg:address":"Mittriedstr. 13",
    "sg:city":"Hard",
    "sg:classifiers":[
        {
            "category":"Shopping",
            "subcategory":"Clothing, Apparel, & Fashions",
            "type":"Retail Goods"
        }
    ],
    "sg:phone":"+43 4355 746781",
    "sg:postcode":"6971",
    "sg:province":"Vorarlberg",
    "sg:tags":[
        "clothes"
    ],
    "wof:name":"VORARLBERGER WIRKWARENFABRIK GEBR WOLFF GESMBH",
    "wof:placetype":"venue"
},
  "geometry": {"coordinates":[9.6924295425,47.4867286682],"type":"Point"}
}