{
  "type": "Feature",
  "properties": {
    "iso:country":"AT",
    "sg:address":"Hintere Ortsstr 44",
    "sg:city":"Himberg",
    "sg:orig_category":"Galvanisieranstalten",
    "sg:phone":"+43 2235 86715",
    "sg:postcode":"2325",
    "sg:province":"Nieder\u00f6sterreich",
    "wof:name":"Christian Oberfl\u00e4chentechnik GmbH",
    "wof:placetype":"venue"
},
  "geometry": {"coordinates":[16.4406776428,48.0839958191],"type":"Point"}
}