{
  "type": "Feature",
  "properties": {
    "addr:full":"Carl-Blum-Str 3-5 Wels Ober\u00f6sterreich 4600",
    "addr:housenumber":"3-5",
    "addr:postcode":"4600",
    "addr:street":"Carl-Blum-Str;Oberoesterreich",
    "iso:country":"AT",
    "sg:address":"Carl-Blum-Str 3-5",
    "sg:city":"Wels",
    "sg:orig_category":"Technische Bedarfsartikel",
    "sg:phone":"+43 7242 440420",
    "sg:postcode":"4600",
    "sg:province":"Ober\u00f6sterreich",
    "wof:name":"H\u00f6dl H GmbH & Co KG",
    "wof:placetype":"venue"
},
  "geometry": {"coordinates":[14.032743454,48.1623687744],"type":"Point"}
}