{
  "type": "Feature",
  "properties": {
    "addr:full":"Nr 111 Mauterndorf Salzburg 5570",
    "addr:postcode":"5570",
    "addr:street":"Nr 111;Salzburg",
    "iso:country":"AT",
    "sg:address":"Nr 111",
    "sg:city":"Mauterndorf",
    "sg:orig_category":"Lebensmittel / Einzelhandel",
    "sg:phone":"+43 6472 75800",
    "sg:postcode":"5570",
    "sg:province":"Salzburg",
    "wof:name":"Erster Lungauer Wirtschaftsverein Tamsweg regGenmbH",
    "wof:placetype":"venue"
},
  "geometry": {"coordinates":[13.6835899353,47.1336402893],"type":"Point"}
}