{
  "type": "Feature",
  "properties": {
    "addr:full":"Starkweg 1 Irnfritz Nieder\u00f6sterreich 3754",
    "addr:housenumber":"1",
    "addr:postcode":"3754",
    "addr:street":"Starkweg;Niederoesterreich",
    "iso:country":"AT",
    "sg:address":"Starkweg 1",
    "sg:city":"Irnfritz",
    "sg:orig_category":"Alteisen U Altmetalle, Entsorgungen, Containerdienste, Abfallentsorgung U -Verwertung",
    "sg:phone":"+43 2986 6655",
    "sg:postcode":"3754",
    "sg:province":"Nieder\u00f6sterreich",
    "wof:name":"Stark GmbH",
    "wof:placetype":"venue"
},
  "geometry": {"coordinates":[15.5585279465,48.7394676208],"type":"Point"}
}