{
  "type": "Feature",
  "properties": {
    "addr:full":"Scharitzerstrasse 10 Linz Ober\u00f6sterreich 4020",
    "addr:housenumber":"10",
    "addr:postcode":"4020",
    "addr:street":"Scharitzerstrasse",
    "iso:country":"AT",
    "sg:address":"Scharitzerstrasse 10",
    "sg:city":"Linz",
    "sg:classifiers":[
        {
            "category":"Social Services",
            "subcategory":"Adult Care",
            "type":"Services"
        }
    ],
    "sg:phone":"+43 732 656046",
    "sg:postcode":"4020",
    "sg:province":"Ober\u00f6sterreich",
    "sg:tags":[
        "limb",
        "artificial"
    ],
    "sg:website":"schuheinlagen.at",
    "wof:name":"Gustav Schaper",
    "wof:placetype":"venue"
},
  "geometry": {"coordinates":[14.2940387726,48.2956962585],"type":"Point"}
}