{
  "type": "Feature",
  "properties": {
    "addr:full":"Denglerg 7/16 Wien Wien 1150",
    "addr:housenumber":"7 / 16",
    "addr:postcode":"1150",
    "addr:street":"Denglerg",
    "iso:country":"AT",
    "sg:address":"Denglerg 7/16",
    "sg:city":"Wien",
    "sg:orig_category":"Webdesign",
    "sg:phone":"+43 1 9419396",
    "sg:postcode":"1150",
    "sg:province":"Wien",
    "wof:name":"maxxdesign - the maximum Design",
    "wof:placetype":"venue"
},
  "geometry": {"coordinates":[16.3284492493,48.192401886],"type":"Point"}
}