{
  "type": "Feature",
  "properties": {
    "addr:full":"Resthofstr 64/1 Steyr Ober\u00f6sterreich 4400",
    "addr:housenumber":"64 / 1",
    "addr:postcode":"4400",
    "addr:street":"Resthofstr;Oberoesterreich",
    "iso:country":"AT",
    "sg:address":"Resthofstr 64/1",
    "sg:city":"Steyr",
    "sg:classifiers":[
        {
            "category":"Taxi",
            "type":"Transportation"
        }
    ],
    "sg:phone":"+43 4372 5276555",
    "sg:postcode":"4400",
    "sg:province":"Ober\u00f6sterreich",
    "sg:tags":[
        "personentransporte",
        "u"
    ],
    "wof:name":"Rexeisen Hanna",
    "wof:placetype":"venue"
},
  "geometry": {"coordinates":[14.4254236221,48.0618019104],"type":"Point"}
}