{
  "type": "Feature",
  "properties": {
    "iso:country":"AT",
    "sg:address":"Neumarkter Str 47",
    "sg:city":"Friesach",
    "sg:orig_category":"Autohandel",
    "sg:phone":"+43 4268 4884",
    "sg:postcode":"9360",
    "sg:province":"K\u00e4rnten",
    "wof:name":"Autohaus Striednig GesmbH",
    "wof:placetype":"venue"
},
  "geometry": {"coordinates":[14.4003896713,46.9612388611],"type":"Point"}
}