{
  "type": "Feature",
  "properties": {
    "addr:full":"Landstr 2 Hard Vorarlberg 6971",
    "addr:housenumber":"2",
    "addr:postcode":"6971",
    "addr:street":"Landstr",
    "iso:country":"AT",
    "sg:address":"Landstr 2",
    "sg:city":"Hard",
    "sg:orig_category":"Lebensmittel / Einzelhandel",
    "sg:phone":"+43 5574 63640",
    "sg:postcode":"6971",
    "sg:province":"Vorarlberg",
    "wof:name":"G\u00dcZEL HandelsgesmbH",
    "wof:placetype":"venue"
},
  "geometry": {"coordinates":[9.6901321411,47.4894790649],"type":"Point"}
}