{
  "type": "Feature",
  "properties": {
    "addr:full":"Klausner Str 6/Gruberau Sulz im Wienerwald Nieder\u00f6sterreich 2392",
    "addr:housenumber":"6 / gruberau",
    "addr:postcode":"2392",
    "addr:street":"Str;Niederoesterreich",
    "iso:country":"AT",
    "sg:address":"Klausner Str 6/Gruberau",
    "sg:city":"Sulz im Wienerwald",
    "sg:orig_category":"Brandschutz",
    "sg:phone":"+43 2238 8436",
    "sg:postcode":"2392",
    "sg:province":"Nieder\u00f6sterreich",
    "wof:name":"IBS-Feuerschutz GmbH",
    "wof:placetype":"venue"
},
  "geometry": {"coordinates":[16.1391887665,48.1020393372],"type":"Point"}
}