{
  "type": "Feature",
  "properties": {
    "addr:full":"Kirchengasse 34 Wien Wien 1070",
    "addr:housenumber":"34",
    "addr:postcode":"1070",
    "addr:street":"Kirchengasse",
    "iso:country":"AT",
    "sg:address":"Kirchengasse 34",
    "sg:city":"Wien",
    "sg:classifiers":[
        {
            "category":"Professional",
            "subcategory":"Art Services",
            "type":"Services"
        }
    ],
    "sg:phone":"+43 1 5234068",
    "sg:postcode":"1070",
    "sg:province":"Wien",
    "sg:tags":[
        "design",
        "audio-visual"
    ],
    "sg:website":"t-rax.at",
    "wof:name":"T-RAX Productions",
    "wof:placetype":"venue"
},
  "geometry": {"coordinates":[16.3518352509,48.2026748657],"type":"Point"}
}