{
  "type": "Feature",
  "properties": {
    "addr:full":"Hinterleiten 57 T Feistritz am Wechsel Nieder\u00f6sterreich 2873",
    "addr:housenumber":"57 t",
    "addr:postcode":"2873",
    "addr:street":"Hinterleiten;Feistritz Am Wechsel",
    "iso:country":"AT",
    "sg:address":"Hinterleiten 57 T",
    "sg:city":"Feistritz am Wechsel",
    "sg:classifiers":[
        {
            "category":"Manufacturing",
            "subcategory":"Building Materials",
            "type":"Manufacturing & Wholesale Goods"
        }
    ],
    "sg:phone":"+43 2641 6628",
    "sg:postcode":"2873",
    "sg:province":"Nieder\u00f6sterreich",
    "sg:tags":[
        "cover",
        "manhole"
    ],
    "sg:website":"huber.de",
    "wof:name":"Huber Edelstahlvertriebs-GmbH",
    "wof:placetype":"venue"
},
  "geometry": {"coordinates":[16.0537891388,47.5992698669],"type":"Point"}
}