{
  "type": "Feature",
  "properties": {
    "addr:full":"Uderns 49 Uderns Tirol 6271",
    "addr:housenumber":"49",
    "addr:postcode":"6271",
    "addr:street":"Uderns;Tirol",
    "iso:country":"AT",
    "sg:address":"Uderns 49",
    "sg:city":"Uderns",
    "sg:orig_category":"Canalisation",
    "sg:phone":"+43 5288 62567",
    "sg:postcode":"6271",
    "sg:province":"Tirol",
    "sg:website":"hollausbau.com",
    "wof:name":"Hollaus Bau-Ges.m.b.H.",
    "wof:placetype":"venue"
},
  "geometry": {"coordinates":[11.8642044067,47.3230743408],"type":"Point"}
}