{
  "type": "Feature",
  "properties": {
    "addr:full":"Drautendorf 44 Niederwaldkirchen Ober\u00f6sterreich 4174",
    "addr:housenumber":"44",
    "addr:postcode":"4174",
    "addr:street":"Drautendorf",
    "iso:country":"AT",
    "sg:address":"Drautendorf 44",
    "sg:city":"Niederwaldkirchen",
    "sg:orig_category":"Autohandel",
    "sg:phone":"+43 7231 3107",
    "sg:postcode":"4174",
    "sg:province":"Ober\u00f6sterreich",
    "wof:name":"Meindl Leopold",
    "wof:placetype":"venue"
},
  "geometry": {"coordinates":[14.061214447,48.4547958374],"type":"Point"}
}