{
  "type": "Feature",
  "properties": {
    "addr:full":"Daxluegstr 5 Hallwang Salzburg 5300",
    "addr:housenumber":"5",
    "addr:postcode":"5300",
    "addr:street":"Daxluegstr;Salzburg",
    "iso:country":"AT",
    "sg:address":"Daxluegstr 5",
    "sg:city":"Hallwang",
    "sg:classifiers":[
        {
            "category":"Restaurant",
            "type":"Food & Drink"
        }
    ],
    "sg:phone":"+43 4366 2665800",
    "sg:postcode":"5300",
    "sg:province":"Salzburg",
    "wof:name":"DAXLUEG - die Einkehr am Heuberg",
    "wof:placetype":"venue"
},
  "geometry": {"coordinates":[13.0853147507,47.8517684937],"type":"Point"}
}