{
  "type": "Feature",
  "properties": {
    "addr:full":"Rauscherstr 7 Wien Wien 1200",
    "addr:housenumber":"7",
    "addr:postcode":"1200",
    "addr:street":"Rauscherstr",
    "iso:country":"AT",
    "sg:address":"Rauscherstr 7",
    "sg:city":"Wien",
    "sg:orig_category":"Friseure U Frisiersalons",
    "sg:phone":"+43 1 3328178",
    "sg:postcode":"1200",
    "sg:province":"Wien",
    "wof:name":"Kuhn Wilhelm",
    "wof:placetype":"venue"
},
  "geometry": {"coordinates":[16.3764896393,48.2303276062],"type":"Point"}
}