{
  "type": "Feature",
  "properties": {
    "addr:full":"M\u00e4rzstr. 118 Wien Wien 1150",
    "addr:housenumber":"118",
    "addr:postcode":"1150",
    "iso:country":"AT",
    "sg:address":"M\u00e4rzstr. 118",
    "sg:city":"Wien",
    "sg:classifiers":[
        {
            "category":"Shopping",
            "type":"Retail Goods"
        }
    ],
    "sg:phone":"+43 4319 8242830",
    "sg:postcode":"1150",
    "sg:province":"Wien",
    "sg:tags":[
        "finished",
        "-",
        "metallic"
    ],
    "wof:name":"GERHARD KORINEK",
    "wof:placetype":"venue"
},
  "geometry": {"coordinates":[16.3320903778,48.2006416321],"type":"Point"}
}