{
  "type": "Feature",
  "properties": {
    "iso:country":"AT",
    "sg:address":"Andreas-Hofer-Str 1a",
    "sg:city":"Lienz",
    "sg:orig_category":"Versicherungsunternehmen",
    "sg:phone":"+43 4852 651150",
    "sg:postcode":"9900",
    "sg:province":"Tirol",
    "wof:name":"Wiener St\u00e4dtische Allgemeine Versicherung AG",
    "wof:placetype":"venue"
},
  "geometry": {"coordinates":[12.7628488541,46.8279037476],"type":"Point"}
}