{
  "type": "Feature",
  "properties": {
    "iso:country":"AT",
    "sg:address":"Haller Str 239",
    "sg:city":"Innsbruck",
    "sg:orig_category":"Autoreparatur",
    "sg:phone":"+43 512 244200",
    "sg:postcode":"6020",
    "sg:province":"Tirol",
    "wof:name":"Ellensohn Manfred GesmbH",
    "wof:placetype":"venue"
},
  "geometry": {"coordinates":[11.4414749146,47.2771148682],"type":"Point"}
}