{
  "type": "Feature",
  "properties": {
    "iso:country":"AT",
    "sg:address":"Villacher Str 171",
    "sg:city":"Klagenfurt",
    "sg:orig_category":"Lebensmittel / Einzelhandel",
    "sg:phone":"+43 463 2625510",
    "sg:postcode":"9020",
    "sg:province":"K\u00e4rnten",
    "wof:name":"SPAR \u00f6sterreichische Warenhandels-AG",
    "wof:placetype":"venue"
},
  "geometry": {"coordinates":[14.2781162262,46.6195907593],"type":"Point"}
}