{
  "type": "Feature",
  "properties": {
    "iso:country":"AT",
    "sg:address":"H Bahr-Promenade 2",
    "sg:city":"Salzburg",
    "sg:orig_category":"Sportanlagen",
    "sg:phone":"+43 662 6234110",
    "sg:postcode":"5020",
    "sg:province":"Salzburg",
    "wof:name":"Kunsteisbahn Salzburg",
    "wof:placetype":"venue"
},
  "geometry": {"coordinates":[13.0599403381,47.7982711792],"type":"Point"}
}