{
  "type": "Feature",
  "properties": {
    "addr:full":"Moldaustr 2 Aigen im M\u00fchlkreis Ober\u00f6sterreich 4160",
    "addr:housenumber":"2",
    "addr:postcode":"4160",
    "addr:street":"Moldaustr",
    "iso:country":"AT",
    "sg:address":"Moldaustr 2",
    "sg:city":"Aigen im M\u00fchlkreis",
    "sg:orig_category":"Feuerwehren",
    "sg:phone":"+43 7281 20500",
    "sg:postcode":"4160",
    "sg:province":"Ober\u00f6sterreich",
    "wof:name":"Freiwillige Feuerwehr Aigen",
    "wof:placetype":"venue"
},
  "geometry": {"coordinates":[13.9717626572,48.6492271423],"type":"Point"}
}