{
  "type": "Feature",
  "properties": {
    "addr:full":"Lilienbrunng 7-9 Wien Wien 1020",
    "addr:housenumber":"7-9",
    "addr:postcode":"1020",
    "addr:street":"Lilienbrunng",
    "iso:country":"AT",
    "sg:address":"Lilienbrunng 7-9",
    "sg:city":"Wien",
    "sg:classifiers":[
        {
            "category":"Professional",
            "subcategory":"Computer Services",
            "type":"Services"
        }
    ],
    "sg:phone":"+43 1 993990",
    "sg:postcode":"1020",
    "sg:province":"Wien",
    "sg:tags":[
        "software"
    ],
    "wof:name":"RACON EDV - Software GesmbH",
    "wof:placetype":"venue"
},
  "geometry": {"coordinates":[16.3775787354,48.2139930725],"type":"Point"}
}