{
  "type": "Feature",
  "properties": {
    "iso:country":"AT",
    "sg:address":"Untergasse 16",
    "sg:city":"Serfaus",
    "sg:orig_category":"Pensionen / Privatzimmer",
    "sg:phone":"+43 5476 6624",
    "sg:postcode":"6534",
    "sg:province":"Tirol",
    "wof:name":"Purtscher Erich",
    "wof:placetype":"venue"
},
  "geometry": {"coordinates":[10.6089982986,47.0366706848],"type":"Point"}
}