{
  "type": "Feature",
  "properties": {
    "addr:full":"Clemens-Hofbauer-Pl 13 Wien Wien 1170",
    "addr:housenumber":"13",
    "addr:postcode":"1170",
    "addr:street":"Clemens-Hofbauer-Pl",
    "iso:country":"AT",
    "sg:address":"Clemens-Hofbauer-Pl 13",
    "sg:city":"Wien",
    "sg:orig_category":"Familien / Beratung",
    "sg:phone":"+43 4314 847262",
    "sg:postcode":"1170",
    "sg:province":"Wien",
    "wof:name":"BRODESSER C\u00e4cilia OEG",
    "wof:placetype":"venue"
},
  "geometry": {"coordinates":[16.3214874268,48.218952179],"type":"Point"}
}