{
  "type": "Feature",
  "properties": {
    "addr:full":"Am Anger 2 Lilienfeld Nieder\u00f6sterreich 3180",
    "addr:housenumber":"2",
    "addr:postcode":"3180",
    "addr:street":"Am Anger",
    "iso:country":"AT",
    "sg:address":"Am Anger 2",
    "sg:city":"Lilienfeld",
    "sg:orig_category":"Bildungsservice / Allgemeine Informationsstellen",
    "sg:phone":"+43 2762 902531841",
    "sg:postcode":"3180",
    "sg:province":"Nieder\u00f6sterreich",
    "wof:name":"Bezirksschulrat",
    "wof:placetype":"venue"
},
  "geometry": {"coordinates":[15.5959501266,48.0164756775],"type":"Point"}
}