{
  "type": "Feature",
  "properties": {
    "iso:country":"AT",
    "sg:address":"Nr 429",
    "sg:city":"Wolfau",
    "sg:orig_category":"Webdesign",
    "sg:phone":"+43 664 5139761",
    "sg:postcode":"7412",
    "sg:province":"Burgenland",
    "wof:name":"IT&S Web Design & Computer Ing Roland Horvatits",
    "wof:placetype":"venue"
},
  "geometry": {"coordinates":[16.0957622528,47.256942749],"type":"Point"}
}