{
  "type": "Feature",
  "properties": {
    "addr:full":"Hackeng 31 Wien Wien 1150",
    "addr:housenumber":"31",
    "addr:postcode":"1150",
    "addr:street":"Hackeng",
    "iso:country":"AT",
    "sg:address":"Hackeng 31",
    "sg:city":"Wien",
    "sg:orig_category":"Galerien",
    "sg:phone":"+43 1 7869243",
    "sg:postcode":"1150",
    "sg:province":"Wien",
    "wof:name":"Atelier Beyer KEG",
    "wof:placetype":"venue"
},
  "geometry": {"coordinates":[16.3327083588,48.2002601624],"type":"Point"}
}