{
  "type": "Feature",
  "properties": {
    "iso:country":"AT",
    "sg:address":"Hauptstr 38",
    "sg:city":"Eichgraben",
    "sg:orig_category":"Satellitenempfangsanlagen",
    "sg:phone":"+43 4327 7342424",
    "sg:postcode":"3032",
    "sg:province":"Nieder\u00f6sterreich",
    "wof:name":"Weinmann TV Radio-Fernsehen-Antennen-Technik",
    "wof:placetype":"venue"
},
  "geometry": {"coordinates":[15.9869098663,48.1752166748],"type":"Point"}
}