{
  "type": "Feature",
  "properties": {
    "addr:full":"Aigen 27 Aigen-Voglhub Salzburg 5351",
    "addr:housenumber":"27;5351",
    "addr:street":"Aigen",
    "iso:country":"AT",
    "sg:address":"Aigen 27",
    "sg:city":"Aigen-Voglhub",
    "sg:orig_category":"Zimmereien",
    "sg:phone":"+43 6137 5921",
    "sg:postcode":"5351",
    "sg:province":"Salzburg",
    "wof:name":"Zimmerei Josef Zierler.zizi",
    "wof:placetype":"venue"
},
  "geometry": {"coordinates":[13.5139799118,47.7144966125],"type":"Point"}
}