{
  "type": "Feature",
  "properties": {
    "addr:full":"Kremser Str 4 Eggenburg Nieder\u00f6sterreich 3730",
    "addr:housenumber":"4",
    "addr:postcode":"3730",
    "addr:street":"Str",
    "iso:country":"AT",
    "sg:address":"Kremser Str 4",
    "sg:city":"Eggenburg",
    "sg:orig_category":"Friseure U Frisiersalons",
    "sg:phone":"+43 2984 2682",
    "sg:postcode":"3730",
    "sg:province":"Nieder\u00f6sterreich",
    "wof:name":"Buchinger Brigitte",
    "wof:placetype":"venue"
},
  "geometry": {"coordinates":[15.8171634674,48.641960144],"type":"Point"}
}