{
  "type": "Feature",
  "properties": {
    "addr:full":"Bahnhofstr 6 Ober-Grafendorf Nieder\u00f6sterreich 3200",
    "addr:housenumber":"6",
    "addr:postcode":"3200",
    "addr:street":"Bahnhofstr",
    "iso:country":"AT",
    "sg:address":"Bahnhofstr 6",
    "sg:city":"Ober-Grafendorf",
    "sg:orig_category":"Blumeneinzelhandel",
    "sg:phone":"+43 2747 2715",
    "sg:postcode":"3200",
    "sg:province":"Nieder\u00f6sterreich",
    "wof:name":"V\u00f6lk Edith",
    "wof:placetype":"venue"
},
  "geometry": {"coordinates":[15.5437870026,48.1523857117],"type":"Point"}
}