{
  "type": "Feature",
  "properties": {
    "addr:full":"Zollerstr 7 Innsbruck Tirol 6020",
    "addr:housenumber":"7",
    "addr:postcode":"6020",
    "addr:street":"Zollerstr;Tirol",
    "iso:country":"AT",
    "sg:address":"Zollerstr 7",
    "sg:city":"Innsbruck",
    "sg:orig_category":"Bekleidung / Einzelhandel",
    "sg:phone":"+43 4351 2890069",
    "sg:postcode":"6020",
    "sg:province":"Tirol",
    "wof:name":"monotool gmbH - Mode f\u00fcr Menschen im Rollstuhl",
    "wof:placetype":"venue"
},
  "geometry": {"coordinates":[11.388463974,47.2576789856],"type":"Point"}
}