{
  "type": "Feature",
  "properties": {
    "addr:full":"Nr 111 Jetzelsdorf Nieder\u00f6sterreich 2053",
    "addr:postcode":"2053",
    "addr:street":"Nr 111",
    "iso:country":"AT",
    "sg:address":"Nr 111",
    "sg:city":"Jetzelsdorf",
    "sg:orig_category":"Weine / Einzelhandel",
    "sg:phone":"+43 4329 442839",
    "sg:postcode":"2053",
    "sg:province":"Nieder\u00f6sterreich",
    "wof:name":"Weinhandelsagentur u Weinbau - Eleonore u Heinrich Sch\u00f6nauer",
    "wof:placetype":"venue"
},
  "geometry": {"coordinates":[16.056646347,48.7062911987],"type":"Point"}
}