{
  "type": "Feature",
  "properties": {
    "addr:full":"Nr 150 Mondsee Ober\u00f6sterreich 5310",
    "addr:postcode":"5310",
    "addr:street":"Nr 150",
    "iso:country":"AT",
    "sg:address":"Nr 150",
    "sg:city":"Mondsee",
    "sg:orig_category":"Transportunternehmen",
    "sg:phone":"+43 6232 2639",
    "sg:postcode":"5310",
    "sg:province":"Ober\u00f6sterreich",
    "wof:name":"Ebner Anton",
    "wof:placetype":"venue"
},
  "geometry": {"coordinates":[13.349562645,47.855255127],"type":"Point"}
}