{
  "type": "Feature",
  "properties": {
    "addr:full":"NB Strem Burgenland 7522",
    "addr:postcode":"strem;7522",
    "iso:country":"AT",
    "sg:address":"NB",
    "sg:city":"Strem",
    "sg:orig_category":"Feuerwehren",
    "sg:phone":"+43 3324 6247",
    "sg:postcode":"7522",
    "sg:province":"Burgenland",
    "wof:name":"Freiwillige Feuerwehr Heiligenbrunn",
    "wof:placetype":"venue"
},
  "geometry": {"coordinates":[16.4142494202,47.0441932678],"type":"Point"}
}