{
  "type": "Feature",
  "properties": {
    "addr:full":"Trattnachtalstr 5 Grieskirchen Ober\u00f6sterreich 4710",
    "addr:housenumber":"5",
    "addr:postcode":"4710",
    "addr:street":"Trattnachtalstr",
    "iso:country":"AT",
    "sg:address":"Trattnachtalstr 5",
    "sg:city":"Grieskirchen",
    "sg:orig_category":"Stukkateure U Trockenausbauer",
    "sg:phone":"+43 7248 61522",
    "sg:postcode":"4710",
    "sg:province":"Ober\u00f6sterreich",
    "wof:name":"Hofer Trockenbau GmbH",
    "wof:placetype":"venue"
},
  "geometry": {"coordinates":[13.8188009262,48.2369003296],"type":"Point"}
}