{
  "type": "Feature",
  "properties": {
    "addr:full":"Selzerg 7 Wien Wien 1150",
    "addr:housenumber":"7",
    "addr:postcode":"1150",
    "addr:street":"Selzerg",
    "iso:country":"AT",
    "sg:address":"Selzerg 7",
    "sg:city":"Wien",
    "sg:orig_category":"Schleifereien",
    "sg:phone":"+43 1 9820130",
    "sg:postcode":"1150",
    "sg:province":"Wien",
    "sg:website":"ibh-werkzeuge.at",
    "wof:name":"IBH Werkzeuge Werkzeugschleiferei GmbH",
    "wof:placetype":"venue"
},
  "geometry": {"coordinates":[16.3239440918,48.1949996948],"type":"Point"}
}