{
  "type": "Feature",
  "properties": {
    "iso:country":"AT",
    "sg:address":"Achstr 42",
    "sg:city":"Wolfurt-Bahnhof",
    "sg:orig_category":"Physiotherapie",
    "sg:phone":"+43 5574 31532",
    "sg:postcode":"6960",
    "sg:province":"Vorarlberg",
    "wof:name":"Spapens Arthur Physiotherapie",
    "wof:placetype":"venue"
},
  "geometry": {"coordinates":[9.7423458099,47.4827270508],"type":"Point"}
}