{
  "type": "Feature",
  "properties": {
    "addr:full":"Schremser Str 26 Heidenreichstein Nieder\u00f6sterreich 3860",
    "addr:housenumber":"26",
    "addr:postcode":"3860",
    "addr:street":"Str",
    "iso:country":"AT",
    "sg:address":"Schremser Str 26",
    "sg:city":"Heidenreichstein",
    "sg:orig_category":"Tabaktrafiken",
    "sg:phone":"+43 2862 53189",
    "sg:postcode":"3860",
    "sg:province":"Nieder\u00f6sterreich",
    "wof:name":"Wurz Martina",
    "wof:placetype":"venue"
},
  "geometry": {"coordinates":[15.1198472977,48.8646583557],"type":"Point"}
}