{
  "type": "Feature",
  "properties": {
    "addr:full":"Gusentalstr 2 Gallneukirchen Ober\u00f6sterreich 4210",
    "addr:housenumber":"2",
    "addr:postcode":"4210",
    "addr:street":"Gusentalstr;Oberoesterreich",
    "iso:country":"AT",
    "sg:address":"Gusentalstr 2",
    "sg:city":"Gallneukirchen",
    "sg:orig_category":"Bibliotheken",
    "sg:phone":"+43 7235 63015",
    "sg:postcode":"4210",
    "sg:province":"Ober\u00f6sterreich",
    "wof:name":"Gemeindebibliothek",
    "wof:placetype":"venue"
},
  "geometry": {"coordinates":[14.4676303864,48.3681297302],"type":"Point"}
}