{
  "type": "Feature",
  "properties": {
    "addr:full":"Mitterndorf 45 Pettenbach Ober\u00f6sterreich 4643",
    "addr:housenumber":"45",
    "addr:postcode":"4643",
    "addr:street":"Mitterndorf",
    "iso:country":"AT",
    "sg:address":"Mitterndorf 45",
    "sg:city":"Pettenbach",
    "sg:orig_category":"Holzhandel",
    "sg:phone":"+43 7586 7396",
    "sg:postcode":"4643",
    "sg:province":"Ober\u00f6sterreich",
    "wof:name":"Aitzetm\u00fcller Gerhard",
    "wof:placetype":"venue"
},
  "geometry": {"coordinates":[14.0035686493,47.947227478],"type":"Point"}
}