{
  "type": "Feature",
  "properties": {
    "iso:country":"AT",
    "sg:address":"An der Sch\u00fctzener Bundesstr 400",
    "sg:city":"Oslip",
    "sg:classifiers":[
        {
            "category":"Home & Garden",
            "subcategory":"Building Materials",
            "type":"Retail Goods"
        }
    ],
    "sg:phone":"+43 4326 82624210",
    "sg:postcode":"7064",
    "sg:province":"Burgenland",
    "sg:tags":[
        "baustoffe",
        "-material",
        "u"
    ],
    "wof:name":"Osliper Betonwerk u Baustoffhandlung Kummer & Co OHG",
    "wof:placetype":"venue"
},
  "geometry": {"coordinates":[16.6188659668,47.8291625977],"type":"Point"}
}