{
  "type": "Feature",
  "properties": {
    "addr:full":"Langobardenstr 52 Wien Wien 1220",
    "addr:housenumber":"52",
    "addr:postcode":"1220",
    "addr:street":"Langobardenstr",
    "iso:country":"AT",
    "sg:address":"Langobardenstr 52",
    "sg:city":"Wien",
    "sg:orig_category":"Physikalische Institute",
    "sg:phone":"+43 1 2848484",
    "sg:postcode":"1220",
    "sg:province":"Wien",
    "wof:name":"Kienbacher Thomas Dr",
    "wof:placetype":"venue"
},
  "geometry": {"coordinates":[16.4581184387,48.2217941284],"type":"Point"}
}