{
  "type": "Feature",
  "properties": {
    "addr:full":"Alm 5 Altenfelden Ober\u00f6sterreich 4121",
    "addr:housenumber":"5",
    "addr:postcode":"4121",
    "addr:street":"Alm",
    "iso:country":"AT",
    "sg:address":"Alm 5",
    "sg:city":"Altenfelden",
    "sg:orig_category":"Volksschulen",
    "sg:phone":"+43 7282 7444",
    "sg:postcode":"4121",
    "sg:province":"Ober\u00f6sterreich",
    "wof:name":"Sonderp\u00e4dagogisches Zentrum",
    "wof:placetype":"venue"
},
  "geometry": {"coordinates":[13.9714241028,48.4837989807],"type":"Point"}
}