{
  "type": "Feature",
  "properties": {
    "addr:full":"Walchhofweg 30 Radstadt Salzburg 5550",
    "addr:housenumber":"30",
    "addr:postcode":"5550",
    "addr:street":"Walchhofweg;Salzburg",
    "iso:country":"AT",
    "sg:address":"Walchhofweg 30",
    "sg:city":"Radstadt",
    "sg:orig_category":"Pensionen / Privatzimmer",
    "sg:phone":"+43 6452 7504",
    "sg:postcode":"5550",
    "sg:province":"Salzburg",
    "wof:name":"Pension Stieglerhof",
    "wof:placetype":"venue"
},
  "geometry": {"coordinates":[13.4945068359,47.3502235413],"type":"Point"}
}