{
  "type": "Feature",
  "properties": {
    "iso:country":"AT",
    "sg:address":"Bundesstr 270",
    "sg:city":"Semmering",
    "sg:orig_category":"Tabaktrafiken",
    "sg:phone":"+43 2664 2545",
    "sg:postcode":"2680",
    "sg:province":"Nieder\u00f6sterreich",
    "wof:name":"Hofer Andrea",
    "wof:placetype":"venue"
},
  "geometry": {"coordinates":[15.8318758011,47.6336936951],"type":"Point"}
}