{
  "type": "Feature",
  "properties": {
    "addr:full":"Salzachstr 11 Wien Wien 1200",
    "addr:housenumber":"11",
    "addr:postcode":"1200",
    "addr:street":"Salzachstr",
    "iso:country":"AT",
    "sg:address":"Salzachstr 11",
    "sg:city":"Wien",
    "sg:orig_category":"Friseure U Frisiersalons",
    "sg:phone":"+43 1 3300254",
    "sg:postcode":"1200",
    "sg:province":"Wien",
    "wof:name":"Ferstl Elisabeth",
    "wof:placetype":"venue"
},
  "geometry": {"coordinates":[16.3868541718,48.2359199524],"type":"Point"}
}