{
  "type": "Feature",
  "properties": {
    "addr:full":"Kremser Str 7 Melk Nieder\u00f6sterreich 3390",
    "addr:housenumber":"7",
    "addr:postcode":"3390",
    "addr:street":"Str",
    "iso:country":"AT",
    "sg:address":"Kremser Str 7",
    "sg:city":"Melk",
    "sg:orig_category":"Restaurants: Chinesisch",
    "sg:phone":"+43 2752 53670",
    "sg:postcode":"3390",
    "sg:province":"Nieder\u00f6sterreich",
    "wof:name":"China-Restaurant Krone",
    "wof:placetype":"venue"
},
  "geometry": {"coordinates":[15.329120636,48.2271537781],"type":"Point"}
}