{
  "type": "Feature",
  "properties": {
    "addr:full":"Nr 19a Steeg Tirol 6655",
    "addr:postcode":"6655",
    "addr:street":"Nr 19A Steeg Tirol",
    "iso:country":"AT",
    "sg:address":"Nr 19a",
    "sg:city":"Steeg",
    "sg:orig_category":"Lebensmittel / Einzelhandel",
    "sg:phone":"+43 5633 5494",
    "sg:postcode":"6655",
    "sg:province":"Tirol",
    "wof:name":"Spar-Markt Inh Walch G\u00fcnter",
    "wof:placetype":"venue"
},
  "geometry": {"coordinates":[10.294090271,47.2430381775],"type":"Point"}
}