{
  "type": "Feature",
  "properties": {
    "addr:full":"Bahnhofstr 75 Gmunden Ober\u00f6sterreich 4810",
    "addr:postcode":"4810",
    "addr:street":"Bahnhofstr 75",
    "iso:country":"AT",
    "sg:address":"Bahnhofstr 75",
    "sg:city":"Gmunden",
    "sg:orig_category":"Autohandel",
    "sg:phone":"+43 761264043",
    "sg:postcode":"4810",
    "sg:province":"Ober\u00f6sterreich",
    "wof:name":"Autohaus Swoboda GesmbH & Co KG",
    "wof:placetype":"venue"
},
  "geometry": {"coordinates":[13.7857255936,47.9260978699],"type":"Point"}
}