{
  "type": "Feature",
  "properties": {
    "addr:full":"Konradg 1 Wien Wien 1020",
    "addr:housenumber":"1",
    "addr:postcode":"1020",
    "addr:street":"Konradg",
    "iso:country":"AT",
    "sg:address":"Konradg 1",
    "sg:city":"Wien",
    "sg:orig_category":"Psychotherapie",
    "sg:phone":"+43 1 2125229",
    "sg:postcode":"1020",
    "sg:province":"Wien",
    "wof:name":"Klein Evelyn Dr phil",
    "wof:placetype":"venue"
},
  "geometry": {"coordinates":[16.3823108673,48.2214889526],"type":"Point"}
}