{
  "type": "Feature",
  "properties": {
    "addr:full":"Schulstr 5 Lunz am See Nieder\u00f6sterreich 3293",
    "addr:housenumber":"5",
    "addr:postcode":"3293",
    "addr:street":"Schulstr;Niederoesterreich",
    "iso:country":"AT",
    "sg:address":"Schulstr 5",
    "sg:city":"Lunz am See",
    "sg:orig_category":"Hauptschulen",
    "sg:phone":"+43 4374 8620010",
    "sg:postcode":"3293",
    "sg:province":"Nieder\u00f6sterreich",
    "wof:name":"Hauptschule",
    "wof:placetype":"venue"
},
  "geometry": {"coordinates":[15.0295028687,47.8611946106],"type":"Point"}
}