{
  "type": "Feature",
  "properties": {
    "iso:country":"AT",
    "sg:address":"Bergg 7",
    "sg:city":"Wien",
    "sg:orig_category":"Bibliotheken",
    "sg:phone":"+43 1 31740200",
    "sg:postcode":"1090",
    "sg:province":"Wien",
    "wof:name":"Frauensolidarit\u00e4t Zeitschrift Bibliothek & Dokumentation",
    "wof:placetype":"venue"
},
  "geometry": {"coordinates":[16.3607158661,48.2178573608],"type":"Point"}
}