{
  "type": "Feature",
  "properties": {
    "addr:full":"St. Georgener Hauptstr 46 Eisenstadt Burgenland 7000",
    "addr:housenumber":"46",
    "addr:postcode":"7000",
    "addr:street":"St. Georgener Hauptstr",
    "iso:country":"AT",
    "sg:address":"St. Georgener Hauptstr 46",
    "sg:city":"Eisenstadt",
    "sg:orig_category":"Pensionen / Privatzimmer",
    "sg:phone":"+43 4326 8268738",
    "sg:postcode":"7000",
    "sg:province":"Burgenland",
    "wof:name":"H\u00f6fer Karl",
    "wof:placetype":"venue"
},
  "geometry": {"coordinates":[16.5512695312,47.8523406982],"type":"Point"}
}