{
  "type": "Feature",
  "properties": {
    "iso:country":"AT",
    "sg:address":"Stefan-Fadinger-Str 20",
    "sg:city":"Wels",
    "sg:orig_category":"Damenmoden",
    "sg:phone":"+43 4372 4269412",
    "sg:postcode":"4600",
    "sg:province":"Ober\u00f6sterreich",
    "wof:name":"VERPASS-Bekleidungsfabrikation - Swoboda u Rigotti",
    "wof:placetype":"venue"
},
  "geometry": {"coordinates":[14.025636673,48.1680221558],"type":"Point"}
}