{
  "type": "Feature",
  "properties": {
    "addr:full":"Steinerzaun 52/13 St. Roman Ober\u00f6sterreich 4793",
    "addr:housenumber":"52 / 13",
    "addr:postcode":"4793",
    "addr:street":"Steinerzaun;St. Roman Oberoesterreich",
    "iso:country":"AT",
    "sg:address":"Steinerzaun 52/13",
    "sg:city":"St. Roman",
    "sg:classifiers":[
        {
            "category":"Building & Trades",
            "subcategory":"Plumbing",
            "type":"Services"
        }
    ],
    "sg:phone":"+43 7716 7394",
    "sg:postcode":"4793",
    "sg:province":"Ober\u00f6sterreich",
    "sg:tags":[
        "supraregional",
        "gas"
    ],
    "sg:website":"wiesinger-bad.at",
    "wof:name":"Walter Wiesinger",
    "wof:placetype":"venue"
},
  "geometry": {"coordinates":[13.6184692383,48.4570388794],"type":"Point"}
}