{
  "type": "Feature",
  "properties": {
    "iso:country":"AT",
    "sg:address":"Fischeraustr. 13",
    "sg:city":"G\u00f6sting",
    "sg:classifiers":[
        {
            "category":"Shopping",
            "subcategory":"Clothing, Apparel, & Fashions",
            "type":"Retail Goods"
        }
    ],
    "sg:phone":"+43 4331 66834440",
    "sg:postcode":"8051",
    "sg:province":"Steiermark",
    "sg:tags":[
        "clothes"
    ],
    "wof:name":"SAN REMO",
    "wof:placetype":"venue"
},
  "geometry": {"coordinates":[15.4099702835,47.094959259],"type":"Point"}
}