{
  "type": "Feature",
  "properties": {
    "addr:full":"Hehenberg 29 Bad Hall Ober\u00f6sterreich 4540",
    "addr:housenumber":"29",
    "addr:postcode":"4540",
    "addr:street":"Hehenberg",
    "iso:country":"AT",
    "sg:address":"Hehenberg 29",
    "sg:city":"Bad Hall",
    "sg:classifiers":[
        {
            "category":"Structure",
            "subcategory":"Building",
            "type":"Public Place"
        }
    ],
    "sg:phone":"+43 7258 6279",
    "sg:postcode":"4540",
    "sg:province":"Ober\u00f6sterreich",
    "sg:tags":[
        "profiled",
        "aluminium",
        "fence"
    ],
    "wof:name":"R & S R\u00fchrlinger & Sch\u00e4dl OEG Tore aller Art, Berner und Nice-Torantriebe, Aluz\u00e4une",
    "wof:placetype":"venue"
},
  "geometry": {"coordinates":[14.1932287216,48.0446777344],"type":"Point"}
}