{
  "type": "Feature",
  "properties": {
    "addr:full":"Richard Mayr-G 1 Salzburg Salzburg 5020",
    "addr:housenumber":"1",
    "addr:postcode":"5020",
    "addr:street":"Salzburg",
    "iso:country":"AT",
    "sg:address":"Richard Mayr-G 1",
    "sg:city":"Salzburg",
    "sg:classifiers":[
        {
            "category":"Restaurant",
            "type":"Food & Drink"
        }
    ],
    "sg:phone":"+43 662 8772970",
    "sg:postcode":"5020",
    "sg:province":"Salzburg",
    "wof:name":"Mattseer Stiftskeller - B\u00fcro",
    "wof:placetype":"venue"
},
  "geometry": {"coordinates":[13.0450153351,47.8027763367],"type":"Point"}
}