{
  "type": "Feature",
  "properties": {
    "iso:country":"AT",
    "sg:address":"Enzersberg 109",
    "sg:city":"Thalgau",
    "sg:orig_category":"Non-Classified Establishments",
    "sg:phone":"+43 6235 6378",
    "sg:postcode":"5303",
    "sg:province":"Salzburg",
    "wof:name":"Jedermann Truthahnschinken Schindecker GesmbH",
    "wof:placetype":"venue"
},
  "geometry": {"coordinates":[13.1954441071,47.8485679626],"type":"Point"}
}