{
  "type": "Feature",
  "properties": {
    "addr:full":"Industriegel\u00e4nde 7 Steinbrunn Burgenland 7035",
    "addr:housenumber":"7",
    "addr:postcode":"7035",
    "addr:street":"Industriegelaende",
    "iso:country":"AT",
    "sg:address":"Industriegel\u00e4nde 7",
    "sg:city":"Steinbrunn",
    "sg:orig_category":"Non-Classified Establishments",
    "sg:phone":"+43 2624 58492",
    "sg:postcode":"7035",
    "sg:province":"Burgenland",
    "wof:name":"Marco Treppen Liegenschaftsvermietungs GmbH",
    "wof:placetype":"venue"
},
  "geometry": {"coordinates":[16.4131641388,47.8366889954],"type":"Point"}
}