{
  "type": "Feature",
  "properties": {
    "addr:full":"Franz-Josef-Str 52 Mistelbach Nieder\u00f6sterreich 2130",
    "addr:housenumber":"52",
    "addr:postcode":"2130",
    "addr:street":"Franz-Josef-Str;Niederoesterreich",
    "iso:country":"AT",
    "sg:address":"Franz-Josef-Str 52",
    "sg:city":"Mistelbach",
    "sg:orig_category":"Versicherungsunternehmen",
    "sg:phone":"+43 2572 2684",
    "sg:postcode":"2130",
    "sg:province":"Nieder\u00f6sterreich",
    "wof:name":"Donau Versicherung",
    "wof:placetype":"venue"
},
  "geometry": {"coordinates":[16.5710582733,48.5713005066],"type":"Point"}
}