{
  "type": "Feature",
  "properties": {
    "addr:full":"Industriestrasse 3 Prinzersdorf Nieder\u00f6sterreich 3385",
    "addr:housenumber":"3",
    "addr:postcode":"3385",
    "addr:street":"Industriestrasse",
    "iso:country":"AT",
    "sg:address":"Industriestrasse 3",
    "sg:city":"Prinzersdorf",
    "sg:classifiers":[
        {
            "category":"Wholesale",
            "subcategory":"Chemicals & Plastics",
            "type":"Manufacturing & Wholesale Goods"
        }
    ],
    "sg:phone":"+43 6472 7275",
    "sg:postcode":"3385",
    "sg:province":"Nieder\u00f6sterreich",
    "sg:tags":[
        "disposal"
    ],
    "sg:website":"spreitzer-abfall.at",
    "wof:name":"Spreitzer Entsorgung GmbH",
    "wof:placetype":"venue"
},
  "geometry": {"coordinates":[15.5187358856,48.2078666687],"type":"Point"}
}