{
  "type": "Feature",
  "properties": {
    "iso:country":"AT",
    "sg:address":"Raiffeisenstr 3",
    "sg:city":"Taxenbach",
    "sg:orig_category":"Notare",
    "sg:phone":"+43 6543 52530",
    "sg:postcode":"5660",
    "sg:province":"Salzburg",
    "wof:name":"Eberl Isabella Dr",
    "wof:placetype":"venue"
},
  "geometry": {"coordinates":[12.9636411667,47.2923622131],"type":"Point"}
}