{
  "type": "Feature",
  "properties": {
    "iso:country":"AT",
    "sg:address":"Nr 53",
    "sg:city":"W\u00f6rgl",
    "sg:orig_category":"Transportunternehmen",
    "sg:phone":"+43 5332 74241",
    "sg:postcode":"6300",
    "sg:province":"Tirol",
    "wof:name":"Leonhardt Stanislaus",
    "wof:placetype":"venue"
},
  "geometry": {"coordinates":[12.0642328262,47.506893158],"type":"Point"}
}