{
  "type": "Feature",
  "properties": {
    "addr:full":"Nr 2 K\u00f6flach Steiermark 8580",
    "addr:postcode":"8580",
    "addr:street":"Nr",
    "iso:country":"AT",
    "sg:address":"Nr 2",
    "sg:city":"K\u00f6flach",
    "sg:orig_category":"Non-Classified Establishments",
    "sg:phone":"+43 3144 2761",
    "sg:postcode":"8580",
    "sg:province":"Steiermark",
    "wof:name":"Pfarramt",
    "wof:placetype":"venue"
},
  "geometry": {"coordinates":[15.0835552216,47.0640258789],"type":"Point"}
}