{
  "type": "Feature",
  "properties": {
    "addr:full":"Lothringerstr 11 Wien Wien 1010",
    "addr:housenumber":"11",
    "addr:postcode":"1010",
    "addr:street":"Lothringerstr",
    "iso:country":"AT",
    "sg:address":"Lothringerstr 11",
    "sg:city":"Wien",
    "sg:orig_category":"Geigen",
    "sg:phone":"+43 1 7181058",
    "sg:postcode":"1010",
    "sg:province":"Wien",
    "wof:name":"Neubauer Walter",
    "wof:placetype":"venue"
},
  "geometry": {"coordinates":[16.3776493073,48.2022743225],"type":"Point"}
}