{
  "type": "Feature",
  "properties": {
    "iso:country":"AT",
    "sg:address":"Vordere Dorfg 5",
    "sg:city":"Kohfidisch",
    "sg:orig_category":"Maler, Anstreicher U Lackierer",
    "sg:phone":"+43 3366 77237",
    "sg:postcode":"7512",
    "sg:province":"Burgenland",
    "wof:name":"Polzer Hubert",
    "wof:placetype":"venue"
},
  "geometry": {"coordinates":[16.3484344482,47.1620864868],"type":"Point"}
}