{
  "type": "Feature",
  "properties": {
    "addr:full":"Schie\u00dfst\u00e4ttg 29 Pottenstein Nieder\u00f6sterreich 2563",
    "addr:housenumber":"29",
    "addr:postcode":"2563",
    "addr:street":"Schiessstaettg",
    "iso:country":"AT",
    "sg:address":"Schie\u00dfst\u00e4ttg 29",
    "sg:city":"Pottenstein",
    "sg:orig_category":"Tischlereien",
    "sg:phone":"+43 4326 72825270",
    "sg:postcode":"2563",
    "sg:province":"Nieder\u00f6sterreich",
    "wof:name":"Zehetbauer Richard Ing GesmbH",
    "wof:placetype":"venue"
},
  "geometry": {"coordinates":[16.3519897461,48.0015106201],"type":"Point"}
}