{
  "type": "Feature",
  "properties": {
    "addr:full":"Walser Str 6 Mittelberg Vorarlberg 6993",
    "addr:housenumber":"6",
    "addr:postcode":"6993",
    "addr:street":"Str",
    "iso:country":"AT",
    "sg:address":"Walser Str 6",
    "sg:city":"Mittelberg",
    "sg:orig_category":"Pensionen / Privatzimmer",
    "sg:phone":"+43 5517 5558",
    "sg:postcode":"6993",
    "sg:province":"Vorarlberg",
    "wof:name":"Schwendinger Erich",
    "wof:placetype":"venue"
},
  "geometry": {"coordinates":[10.1620998383,47.334487915],"type":"Point"}
}