{
  "type": "Feature",
  "properties": {
    "addr:full":"Hartgewerbestr. 16 Amstetten Nieder\u00f6sterreich 3300",
    "addr:housenumber":"16",
    "addr:postcode":"3300",
    "addr:street":"Hartgewerbestr.;Niederoesterreich",
    "iso:country":"AT",
    "sg:address":"Hartgewerbestr. 16",
    "sg:city":"Amstetten",
    "sg:classifiers":[
        {
            "category":"Autos & Motor Vehicles",
            "subcategory":"Automobile Sales",
            "type":"Retail Goods"
        }
    ],
    "sg:phone":"+43 4374 72612630",
    "sg:postcode":"3300",
    "sg:province":"Nieder\u00f6sterreich",
    "sg:tags":[
        "industrial"
    ],
    "wof:name":"FRANZ GSTETTENHOFER GESMBH",
    "wof:placetype":"venue"
},
  "geometry": {"coordinates":[14.8706607819,48.1244812012],"type":"Point"}
}