{
  "type": "Feature",
  "properties": {
    "iso:country":"AT",
    "sg:address":"Hauptg 31",
    "sg:city":"Andau",
    "sg:classifiers":[
        {
            "category":"Home & Garden",
            "subcategory":"Building Materials",
            "type":"Retail Goods"
        }
    ],
    "sg:phone":"+43 4321 7623080",
    "sg:postcode":"7163",
    "sg:province":"Burgenland",
    "sg:tags":[
        "baustoffe",
        "-material",
        "u"
    ],
    "wof:name":"Gelbmann Franz Handels- u Transport GesmbH",
    "wof:placetype":"venue"
},
  "geometry": {"coordinates":[17.0324306488,47.7754859924],"type":"Point"}
}