{
  "type": "Feature",
  "properties": {
    "iso:country":"AT",
    "sg:address":"Markt 77",
    "sg:city":"Pabneukirchen",
    "sg:orig_category":"Volksschulen",
    "sg:phone":"+43 7265 5511",
    "sg:postcode":"4363",
    "sg:province":"Ober\u00f6sterreich",
    "wof:name":"Volksschule",
    "wof:placetype":"venue"
},
  "geometry": {"coordinates":[14.81731987,48.3200263977],"type":"Point"}
}