{
  "type": "Feature",
  "properties": {
    "iso:country":"AT",
    "sg:address":"Liechtensteinstr 90",
    "sg:city":"Wien",
    "sg:orig_category":"Installationsunternehmen",
    "sg:phone":"+43 1 3196578",
    "sg:postcode":"1090",
    "sg:province":"Wien",
    "wof:name":"Paser & Kocher GesmbH",
    "wof:placetype":"venue"
},
  "geometry": {"coordinates":[16.3563156128,48.228302002],"type":"Point"}
}