{
  "type": "Feature",
  "properties": {
    "addr:full":"Linzer Str 383 Wien Wien 1140",
    "addr:housenumber":"383",
    "addr:postcode":"1140",
    "addr:street":"Linzer Str",
    "iso:country":"AT",
    "sg:address":"Linzer Str 383",
    "sg:city":"Wien",
    "sg:orig_category":"Lebensmittel / Einzelhandel",
    "sg:phone":"+43 1 4165232",
    "sg:postcode":"1140",
    "sg:province":"Wien",
    "wof:name":"SPAR \u00f6sterreichische Warenhandels-AG",
    "wof:placetype":"venue"
},
  "geometry": {"coordinates":[16.2614650726,48.2015190125],"type":"Point"}
}