{
  "type": "Feature",
  "properties": {
    "iso:country":"AT",
    "sg:address":"Hamerlingstr. 19 ",
    "sg:city":"Zwettl",
    "sg:classifiers":[
        {
            "category":"Manufacturing",
            "subcategory":"Rubber & Plastics",
            "type":"Manufacturing & Wholesale Goods"
        }
    ],
    "sg:phone":"+43 4328 2252841",
    "sg:postcode":"3910",
    "sg:province":"Nieder\u00f6sterreich",
    "wof:name":"REIFENHAUS SILVESTRI",
    "wof:placetype":"venue"
},
  "geometry": {"coordinates":[15.1681003571,48.6041564941],"type":"Point"}
}