{
  "type": "Feature",
  "properties": {
    "iso:country":"AT",
    "sg:address":"Neue Heimat Str. 1",
    "sg:city":"Gr\u00f6dig",
    "sg:classifiers":[
        {
            "category":"Retail",
            "subcategory":"Animal Services",
            "type":"Services"
        }
    ],
    "sg:phone":"+43 4362 46722080",
    "sg:postcode":"5082",
    "sg:province":"Salzburg",
    "sg:tags":[
        "breeding"
    ],
    "wof:name":"VITAN SPEZIALFUTTER GESMBH",
    "wof:placetype":"venue"
},
  "geometry": {"coordinates":[-76.2684555054,37.4373283386],"type":"Point"}
}