{
  "type": "Feature",
  "properties": {
    "addr:full":"Wallpachg 8 Hall in Tirol Tirol 6060",
    "addr:housenumber":"8",
    "addr:postcode":"6060",
    "addr:street":"Wallpachg;Tirol",
    "iso:country":"AT",
    "sg:address":"Wallpachg 8",
    "sg:city":"Hall in Tirol",
    "sg:orig_category":"Freizeit- U Sportbekleidung",
    "sg:phone":"+43 4352 235667718",
    "sg:postcode":"6060",
    "sg:province":"Tirol",
    "wof:name":"Jeansl\u00e4nd - Jeans u Blazer",
    "wof:placetype":"venue"
},
  "geometry": {"coordinates":[11.507932663,47.282497406],"type":"Point"}
}