{
  "type": "Feature",
  "properties": {
    "iso:country":"AT",
    "sg:address":"Wallpachg 8",
    "sg:city":"Hall in Tirol",
    "sg:orig_category":"Freizeit- U Sportbekleidung",
    "sg:phone":"+43 4352 235667718",
    "sg:postcode":"6060",
    "sg:province":"Tirol",
    "wof:name":"Jeansl\u00e4nd - Jeans u Blazer",
    "wof:placetype":"venue"
},
  "geometry": {"coordinates":[11.507932663,47.282497406],"type":"Point"}
}