{
  "type": "Feature",
  "properties": {
    "addr:full":"Hietzinger Hauptstr 99 Wien Wien 1130",
    "addr:housenumber":"99",
    "addr:postcode":"1130",
    "addr:street":"Hietzinger Hauptstr",
    "iso:country":"AT",
    "sg:address":"Hietzinger Hauptstr 99",
    "sg:city":"Wien",
    "sg:orig_category":"Banken U Sparkassen",
    "sg:phone":"+43 4350 50539270",
    "sg:postcode":"1130",
    "sg:province":"Wien",
    "wof:name":"Bank Austria Creditanstalt AG",
    "wof:placetype":"venue"
},
  "geometry": {"coordinates":[16.2783699036,48.1873283386],"type":"Point"}
}