{
  "type": "Feature",
  "properties": {
    "addr:full":"Nr 84 Klausen-Leopoldsdorf Nieder\u00f6sterreich 2533",
    "addr:postcode":"2533",
    "addr:street":"Nr;Klausen-Leopoldsdorf",
    "iso:country":"AT",
    "sg:address":"Nr 84",
    "sg:city":"Klausen-Leopoldsdorf",
    "sg:orig_category":"Gemeinden",
    "sg:phone":"+43 2257 236",
    "sg:postcode":"2533",
    "sg:province":"Nieder\u00f6sterreich",
    "wof:name":"Gemeindeamt Klausen-Leopoldsdorf",
    "wof:placetype":"venue"
},
  "geometry": {"coordinates":[16.0146903992,48.0881881714],"type":"Point"}
}