{
  "type": "Feature",
  "properties": {
    "addr:full":"Dorf 11 Hopfgarten in Defereggen Tirol 9961",
    "addr:housenumber":"11",
    "addr:postcode":"9961",
    "addr:street":"Dorf;Tirol",
    "iso:country":"AT",
    "sg:address":"Dorf 11",
    "sg:city":"Hopfgarten in Defereggen",
    "sg:orig_category":"Lebensmittel / Einzelhandel",
    "sg:phone":"+43 4348 725342",
    "sg:postcode":"9961",
    "sg:province":"Tirol",
    "wof:name":"Bla\u00dfnig Anna",
    "wof:placetype":"venue"
},
  "geometry": {"coordinates":[12.5203895569,46.9213523865],"type":"Point"}
}