{
  "type": "Feature",
  "properties": {
    "iso:country":"AT",
    "sg:address":"Schulerstr 10",
    "sg:city":"Wien",
    "sg:classifiers":[
        {
            "category":"Restaurant",
            "type":"Food & Drink"
        }
    ],
    "sg:phone":"+43 1 5158415",
    "sg:postcode":"1010",
    "sg:province":"Wien",
    "wof:name":"Restaurant K\u00f6nig von Ungarn",
    "wof:placetype":"venue"
},
  "geometry": {"coordinates":[16.3753929138,48.2081108093],"type":"Point"}
}