{
  "type": "Feature",
  "properties": {
    "iso:country":"AT",
    "sg:address":"Putzendoplerg 4",
    "sg:city":"Wien",
    "sg:orig_category":"Musikunterricht",
    "sg:phone":"+43 1 6675482",
    "sg:postcode":"1230",
    "sg:province":"Wien",
    "wof:name":"Musikschule Alterlaa",
    "wof:placetype":"venue"
},
  "geometry": {"coordinates":[16.3199996948,48.150352478],"type":"Point"}
}