{
  "type": "Feature",
  "properties": {
    "addr:full":"Nikolaus-August-Otto-Str 20 Wiener Neustadt Nieder\u00f6sterreich 2700",
    "addr:housenumber":"20",
    "addr:postcode":"2700",
    "addr:street":"Nikolaus-August-Otto-Str",
    "iso:country":"AT",
    "sg:address":"Nikolaus-August-Otto-Str 20",
    "sg:city":"Wiener Neustadt",
    "sg:orig_category":"Steuerberatung",
    "sg:phone":"+43 4326 22223570",
    "sg:postcode":"2700",
    "sg:province":"Nieder\u00f6sterreich",
    "wof:name":"Bollenberger & Bollenberger Unternehmensberatungs GmbH",
    "wof:placetype":"venue"
},
  "geometry": {"coordinates":[16.2486095428,47.8413314819],"type":"Point"}
}