{
  "type": "Feature",
  "properties": {
    "addr:full":"Alte Landstr 38 Ostermiething Ober\u00f6sterreich 5121",
    "addr:housenumber":"38",
    "addr:postcode":"5121",
    "addr:street":"Alte Landstr",
    "iso:country":"AT",
    "sg:address":"Alte Landstr 38",
    "sg:city":"Ostermiething",
    "sg:orig_category":"Autobusunternehmen",
    "sg:phone":"+43 6278 62810",
    "sg:postcode":"5121",
    "sg:province":"Ober\u00f6sterreich",
    "wof:name":"Felber Reinhard",
    "wof:placetype":"venue"
},
  "geometry": {"coordinates":[12.8309011459,48.0505943298],"type":"Point"}
}