{
  "type": "Feature",
  "properties": {
    "iso:country":"AT",
    "sg:address":"Industriestr. 23 ",
    "sg:city":"Arnoldstein",
    "sg:classifiers":[
        {
            "category":"Wholesale",
            "subcategory":"Drugs",
            "type":"Manufacturing & Wholesale Goods"
        }
    ],
    "sg:phone":"+43 4342 5522260",
    "sg:postcode":"9601",
    "sg:province":"K\u00e4rnten",
    "sg:tags":[
        "chemical",
        "pharmaceutical"
    ],
    "wof:name":"CHEMETALL GMBH",
    "wof:placetype":"venue"
},
  "geometry": {"coordinates":[13.6947393417,46.5571250916],"type":"Point"}
}