{
  "type": "Feature",
  "properties": {
    "iso:country":"AT",
    "sg:address":"Hag 27",
    "sg:city":"Lustenau",
    "sg:orig_category":"Tankstellen",
    "sg:phone":"+43 4355 7786782",
    "sg:postcode":"6890",
    "sg:province":"Vorarlberg",
    "wof:name":"OMV AG",
    "wof:placetype":"venue"
},
  "geometry": {"coordinates":[9.664689064,47.4496078491],"type":"Point"}
}