{
  "type": "Feature",
  "properties": {
    "iso:country":"AT",
    "sg:address":"Vorachstr 53b",
    "sg:city":"Lustenau",
    "sg:orig_category":"Estriche",
    "sg:phone":"+43 4355 7785735",
    "sg:postcode":"6890",
    "sg:province":"Vorarlberg",
    "wof:name":"Ebner Helmut",
    "wof:placetype":"venue"
},
  "geometry": {"coordinates":[9.6709117889,47.4257087708],"type":"Point"}
}