{
  "type": "Feature",
  "properties": {
    "addr:full":"Oswald Redlich Str. 11 Wien Wien 1210",
    "addr:postcode":"1210",
    "addr:street":"Str. 11",
    "iso:country":"AT",
    "sg:address":"Oswald Redlich Str. 11",
    "sg:city":"Wien",
    "sg:classifiers":[
        {
            "category":"Manufacturing",
            "subcategory":"Metals",
            "type":"Manufacturing & Wholesale Goods"
        }
    ],
    "sg:phone":"+43 4312 582107",
    "sg:postcode":"1210",
    "sg:province":"Wien",
    "sg:tags":[
        "metallurgy",
        "metalworking"
    ],
    "wof:name":"HEINZ B\u00dcHNEN GMBH & CO KG",
    "wof:placetype":"venue"
},
  "geometry": {"coordinates":[16.441072464,48.2734069824],"type":"Point"}
}