{
  "type": "Feature",
  "properties": {
    "addr:full":"Rathausg 12 Ybbs an der Donau Nieder\u00f6sterreich 3370",
    "addr:housenumber":"12",
    "addr:postcode":"3370",
    "addr:street":"Rathausg",
    "iso:country":"AT",
    "sg:address":"Rathausg 12",
    "sg:city":"Ybbs an der Donau",
    "sg:orig_category":"Fitnesscenter",
    "sg:phone":"+43 664 4320057",
    "sg:postcode":"3370",
    "sg:province":"Nieder\u00f6sterreich",
    "wof:name":"Sedlacek Gerhard",
    "wof:placetype":"venue"
},
  "geometry": {"coordinates":[15.0850696564,48.1771202087],"type":"Point"}
}