{
  "type": "Feature",
  "properties": {
    "addr:full":"Stubenring 4/11 Wien Wien 1010",
    "addr:housenumber":"4 / 11",
    "addr:postcode":"1010",
    "addr:street":"Stubenring",
    "iso:country":"AT",
    "sg:address":"Stubenring 4/11",
    "sg:city":"Wien",
    "sg:orig_category":"Unternehmensberatung",
    "sg:phone":"+43 1 5127308",
    "sg:postcode":"1010",
    "sg:province":"Wien",
    "wof:name":"Bogner W. KEG",
    "wof:placetype":"venue"
},
  "geometry": {"coordinates":[16.382270813,48.2104721069],"type":"Point"}
}