{
  "type": "Feature",
  "properties": {
    "addr:full":"Exerzierplatzstr 60 G\u00f6sting Steiermark 8051",
    "addr:housenumber":"60",
    "addr:postcode":"8051",
    "addr:street":"Exerzierplatzstr",
    "iso:country":"AT",
    "sg:address":"Exerzierplatzstr 60",
    "sg:city":"G\u00f6sting",
    "sg:orig_category":"Botendienste",
    "sg:phone":"+43 316 5863330",
    "sg:postcode":"8051",
    "sg:province":"Steiermark",
    "wof:name":"Funktrans Termintransporte GmbH",
    "wof:placetype":"venue"
},
  "geometry": {"coordinates":[15.4109220505,47.0984458923],"type":"Point"}
}