{
  "type": "Feature",
  "properties": {
    "iso:country":"AT",
    "sg:address":"Haide\u00e4ckerstr 8",
    "sg:city":"Himberg",
    "sg:orig_category":"Samen U Saatgut",
    "sg:phone":"+43 4322 35873910",
    "sg:postcode":"2325",
    "sg:province":"Nieder\u00f6sterreich",
    "wof:name":"HESA Saatengro\u00dfhandlung GesmbH & Co Nfg KG",
    "wof:placetype":"venue"
},
  "geometry": {"coordinates":[16.4475708008,48.0854301453],"type":"Point"}
}