{
  "type": "Feature",
  "properties": {
    "addr:full":"Sebi 330 Niederndorf Tirol 6342",
    "addr:housenumber":"330",
    "addr:postcode":"6342",
    "addr:street":"Sebi",
    "iso:country":"AT",
    "sg:address":"Sebi 330",
    "sg:city":"Niederndorf",
    "sg:orig_category":"Marketingberatung",
    "sg:phone":"+43 5373 61984",
    "sg:postcode":"6342",
    "sg:province":"Tirol",
    "wof:name":"Hangel Elfriede und Gottfried",
    "wof:placetype":"venue"
},
  "geometry": {"coordinates":[12.2304801941,47.6475410461],"type":"Point"}
}