{
  "type": "Feature",
  "properties": {
    "addr:full":"Nr 1 G\u00fcssing Burgenland 7540",
    "addr:postcode":"7540",
    "addr:street":"Nr;Guessing",
    "iso:country":"AT",
    "sg:address":"Nr 1",
    "sg:city":"G\u00fcssing",
    "sg:orig_category":"Gemeinden",
    "sg:phone":"+43 3325 4256",
    "sg:postcode":"7540",
    "sg:province":"Burgenland",
    "wof:name":"Gemeinde Neustift bei G\u00fcssing",
    "wof:placetype":"venue"
},
  "geometry": {"coordinates":[16.2575492859,47.0234718323],"type":"Point"}
}