{
  "type": "Feature",
  "properties": {
    "iso:country":"AT",
    "sg:address":"Zillerweg 1",
    "sg:city":"Kaltenbach",
    "sg:orig_category":"Appartements / Ferienwohnungen",
    "sg:phone":"+43 4352 832716",
    "sg:postcode":"6272",
    "sg:province":"Tirol",
    "wof:name":"Haus Anita",
    "wof:placetype":"venue"
},
  "geometry": {"coordinates":[11.8930873871,47.2787971497],"type":"Point"}
}