{
  "type": "Feature",
  "properties": {
    "addr:full":"Werk-VI-Str 25a Kapfenberg Steiermark 8605",
    "addr:housenumber":"25a",
    "addr:postcode":"8605",
    "addr:street":"Werk-Vi-Str",
    "iso:country":"AT",
    "sg:address":"Werk-VI-Str 25a",
    "sg:city":"Kapfenberg",
    "sg:orig_category":"Bauunternehmen",
    "sg:phone":"+43 664 2133778",
    "sg:postcode":"8605",
    "sg:province":"Steiermark",
    "wof:name":"Borino Bau GmbH",
    "wof:placetype":"venue"
},
  "geometry": {"coordinates":[15.3153114319,47.4504013062],"type":"Point"}
}