{
  "type": "Feature",
  "properties": {
    "addr:full":"Laaer Str 121 Poysdorf Nieder\u00f6sterreich 2170",
    "addr:housenumber":"121",
    "addr:postcode":"2170",
    "addr:street":"Str",
    "iso:country":"AT",
    "sg:address":"Laaer Str 121",
    "sg:city":"Poysdorf",
    "sg:orig_category":"Non-Classified Establishments",
    "sg:phone":"+43 2552 24350",
    "sg:postcode":"2170",
    "sg:province":"Nieder\u00f6sterreich",
    "wof:name":"Stra\u00dfenmeisterei Poysdorf",
    "wof:placetype":"venue"
},
  "geometry": {"coordinates":[16.6161708832,48.665096283],"type":"Point"}
}