{
  "type": "Feature",
  "properties": {
    "addr:full":"Bolzanistr 10-12 Tullnerbach Nieder\u00f6sterreich 3013",
    "addr:postcode":"10-12;3013",
    "addr:street":"Niederoesterreich",
    "iso:country":"AT",
    "sg:address":"Bolzanistr 10-12",
    "sg:city":"Tullnerbach",
    "sg:orig_category":"Endlosformulare U -Papier",
    "sg:phone":"+43 2233 538640",
    "sg:postcode":"3013",
    "sg:province":"Nieder\u00f6sterreich",
    "wof:name":"Allform Gesch\u00e4ftsdrucksorten GesmbH",
    "wof:placetype":"venue"
},
  "geometry": {"coordinates":[16.1032676697,48.185295105],"type":"Point"}
}