{
  "type": "Feature",
  "properties": {
    "addr:full":"Scho\u00dfbachstr 10 Wolfsberg K\u00e4rnten 9400",
    "addr:housenumber":"10;kaernten",
    "addr:postcode":"9400",
    "addr:street":"Schossbachstr",
    "iso:country":"AT",
    "sg:address":"Scho\u00dfbachstr 10",
    "sg:city":"Wolfsberg",
    "sg:orig_category":"Finanz- U Wirtschaftsberatung",
    "sg:phone":"+43 4352 3513011",
    "sg:postcode":"9400",
    "sg:province":"K\u00e4rnten",
    "wof:name":"Life In Line Invest Reitmair KEG",
    "wof:placetype":"venue"
},
  "geometry": {"coordinates":[14.8483419418,46.8399276733],"type":"Point"}
}