{
  "type": "Feature",
  "properties": {
    "iso:country":"AT",
    "sg:address":"Breiten 71",
    "sg:city":"Thiersee",
    "sg:orig_category":"Massagen",
    "sg:phone":"+43 5376 5445",
    "sg:postcode":"6335",
    "sg:province":"Tirol",
    "wof:name":"Massagestudio Renate Dillersberger",
    "wof:placetype":"venue"
},
  "geometry": {"coordinates":[12.1312999725,47.5921936035],"type":"Point"}
}