{
  "type": "Feature",
  "properties": {
    "iso:country":"AT",
    "sg:address":"Strohmayerg 11",
    "sg:city":"Wien",
    "sg:orig_category":"Baumeister",
    "sg:phone":"+43 1 8041441",
    "sg:postcode":"1060",
    "sg:province":"Wien",
    "wof:name":"Albrecht Peter Dipl-Ing",
    "wof:placetype":"venue"
},
  "geometry": {"coordinates":[16.3401985168,48.1918296814],"type":"Point"}
}