{
  "type": "Feature",
  "properties": {
    "addr:full":"Hutterstr 453 Puch Salzburg 5412",
    "addr:housenumber":"453",
    "addr:postcode":"5412",
    "addr:street":"Salzburg",
    "iso:country":"AT",
    "sg:address":"Hutterstr 453",
    "sg:city":"Puch",
    "sg:orig_category":"Eisenwaren",
    "sg:phone":"+43 6245 830700",
    "sg:postcode":"5412",
    "sg:province":"Salzburg",
    "wof:name":"HSH Heizung-Sanit\u00e4r-HandelsgesmbH",
    "wof:placetype":"venue"
},
  "geometry": {"coordinates":[13.088809967,47.7129859924],"type":"Point"}
}