{
  "type": "Feature",
  "properties": {
    "addr:full":"B\u00fcrgerg 5 Graz Steiermark 8010",
    "addr:housenumber":"5",
    "addr:postcode":"8010",
    "addr:street":"Buergerg",
    "iso:country":"AT",
    "sg:address":"B\u00fcrgerg 5",
    "sg:city":"Graz",
    "sg:orig_category":"Galerien",
    "sg:phone":"+43 316 819518",
    "sg:postcode":"8010",
    "sg:province":"Steiermark",
    "wof:name":"Galerie Kunst & Handel - Sommer GmbH",
    "wof:placetype":"venue"
},
  "geometry": {"coordinates":[15.4431800842,47.0685653687],"type":"Point"}
}