{
  "type": "Feature",
  "properties": {
    "addr:full":"Ro\u00dfmarkt 10 Grieskirchen Ober\u00f6sterreich 4710",
    "addr:housenumber":"10",
    "addr:postcode":"4710",
    "addr:street":"Rossmarkt",
    "iso:country":"AT",
    "sg:address":"Ro\u00dfmarkt 10",
    "sg:city":"Grieskirchen",
    "sg:orig_category":"Fotoapparate U -Artikel / Einzelhandel",
    "sg:phone":"+43 4372 4862560",
    "sg:postcode":"4710",
    "sg:province":"Ober\u00f6sterreich",
    "wof:name":"Foto Paradies",
    "wof:placetype":"venue"
},
  "geometry": {"coordinates":[13.8257322311,48.2358856201],"type":"Point"}
}