{
  "type": "Feature",
  "properties": {
    "iso:country":"AT",
    "sg:address":"Gschl\u00f6sslweg 12",
    "sg:city":"Deutsch Brodersdorf",
    "sg:orig_category":"Schneidereien",
    "sg:phone":"+43 2255 6652",
    "sg:postcode":"2443",
    "sg:province":"Nieder\u00f6sterreich",
    "wof:name":"Pastler Gabriele",
    "wof:placetype":"venue"
},
  "geometry": {"coordinates":[16.4829349518,47.9341850281],"type":"Point"}
}