{
  "type": "Feature",
  "properties": {
    "addr:full":"Lindenallee 6 Jennersdorf Burgenland 8380",
    "addr:housenumber":"6",
    "addr:postcode":"8380",
    "addr:street":"Lindenallee",
    "iso:country":"AT",
    "sg:address":"Lindenallee 6",
    "sg:city":"Jennersdorf",
    "sg:orig_category":"Lebensmittel / Einzelhandel",
    "sg:phone":"+43 3329 46076",
    "sg:postcode":"8380",
    "sg:province":"Burgenland",
    "wof:name":"Spar-Markt Christandl Johannes",
    "wof:placetype":"venue"
},
  "geometry": {"coordinates":[16.1427268982,46.9407348633],"type":"Point"}
}