{
  "type": "Feature",
  "properties": {
    "addr:full":"Linke Br\u00fcckenstr 8 Linz Ober\u00f6sterreich 4040",
    "addr:housenumber":"8",
    "addr:postcode":"4040",
    "addr:street":"Linke Brueckenstr",
    "iso:country":"AT",
    "sg:address":"Linke Br\u00fcckenstr 8",
    "sg:city":"Linz",
    "sg:orig_category":"Bandagen U Bandagisten",
    "sg:phone":"+43 732 736990",
    "sg:postcode":"4040",
    "sg:province":"Ober\u00f6sterreich",
    "wof:name":"Bandagist & Orthop\u00e4die Gattringer",
    "wof:placetype":"venue"
},
  "geometry": {"coordinates":[14.2578554153,48.3602561951],"type":"Point"}
}