{
  "type": "Feature",
  "properties": {
    "addr:full":"Kindergartensdlg 223 Hirschbach Nieder\u00f6sterreich 3942",
    "addr:housenumber":"223",
    "addr:postcode":"3942",
    "addr:street":"Hirschbach Niederoesterreich",
    "iso:country":"AT",
    "sg:address":"Kindergartensdlg 223",
    "sg:city":"Hirschbach",
    "sg:orig_category":"Maler, Anstreicher U Lackierer",
    "sg:phone":"+43 2854 6637",
    "sg:postcode":"3942",
    "sg:province":"Nieder\u00f6sterreich",
    "wof:name":"Fuchs Andreas",
    "wof:placetype":"venue"
},
  "geometry": {"coordinates":[15.1296796799,48.7429466248],"type":"Point"}
}