{
  "type": "Feature",
  "properties": {
    "addr:full":"Kainach bei Voitsberg 24 Kainach Steiermark 8573",
    "addr:housenumber":"24",
    "addr:postcode":"8573",
    "addr:street":"Kainach Bei Voitsberg",
    "iso:country":"AT",
    "sg:address":"Kainach bei Voitsberg 24",
    "sg:city":"Kainach",
    "sg:classifiers":[
        {
            "category":"Home & Garden",
            "subcategory":"Building Materials",
            "type":"Retail Goods"
        }
    ],
    "sg:phone":"+43 3148 229",
    "sg:postcode":"8573",
    "sg:province":"Steiermark",
    "sg:tags":[
        "wood",
        "banister"
    ],
    "wof:name":"Werner Patz",
    "wof:placetype":"venue"
},
  "geometry": {"coordinates":[15.0845594406,47.1350593567],"type":"Point"}
}