{
  "type": "Feature",
  "properties": {
    "addr:full":"Wiener Str Melk Nieder\u00f6sterreich 3390",
    "addr:postcode":"3390",
    "addr:street":"Melk",
    "iso:country":"AT",
    "sg:address":"Wiener Str",
    "sg:city":"Melk",
    "sg:orig_category":"Eissalons",
    "sg:phone":"+43 2752 52510",
    "sg:postcode":"3390",
    "sg:province":"Nieder\u00f6sterreich",
    "wof:name":"Il Palio",
    "wof:placetype":"venue"
},
  "geometry": {"coordinates":[15.3489713669,48.2249717712],"type":"Point"}
}