{
  "type": "Feature",
  "properties": {
    "addr:full":"Laim 54 St. Gilgen Salzburg 5340",
    "addr:housenumber":"54",
    "addr:postcode":"5340",
    "addr:street":"Laim",
    "iso:country":"AT",
    "sg:address":"Laim 54",
    "sg:city":"St. Gilgen",
    "sg:orig_category":"Parkettbodenverlegung",
    "sg:phone":"+43 6227 7702",
    "sg:postcode":"5340",
    "sg:province":"Salzburg",
    "wof:name":"Strasser Franz",
    "wof:placetype":"venue"
},
  "geometry": {"coordinates":[13.3557577133,47.7674026489],"type":"Point"}
}