{
  "type": "Feature",
  "properties": {
    "iso:country":"AT",
    "sg:address":"Laim 54",
    "sg:city":"St. Gilgen",
    "sg:orig_category":"Parkettbodenverlegung",
    "sg:phone":"+43 6227 7702",
    "sg:postcode":"5340",
    "sg:province":"Salzburg",
    "wof:name":"Strasser Franz",
    "wof:placetype":"venue"
},
  "geometry": {"coordinates":[13.3557577133,47.7674026489],"type":"Point"}
}