{
  "type": "Feature",
  "properties": {
    "addr:full":"Auf dem Kikel 381 Feistritz an der Drau K\u00e4rnten 9710",
    "addr:housenumber":"381",
    "addr:postcode":"9710",
    "addr:street":"Auf Dem Kikel",
    "iso:country":"AT",
    "sg:address":"Auf dem Kikel 381",
    "sg:city":"Feistritz an der Drau",
    "sg:orig_category":"Arbeitsschutz U Arbeitsschutzartikel",
    "sg:phone":"+43 4342 45651790",
    "sg:postcode":"9710",
    "sg:province":"K\u00e4rnten",
    "sg:website":"keweit.com",
    "wof:name":"KEWEIT Dienstleistungs- & Handelsagentur Inh Elke Weitgasser",
    "wof:placetype":"venue"
},
  "geometry": {"coordinates":[13.66314888,46.7018623352],"type":"Point"}
}