{
  "type": "Feature",
  "properties": {
    "addr:full":"Hofwaldweg 12 Innsbruck Tirol 6020",
    "addr:housenumber":"12",
    "addr:postcode":"6020",
    "addr:street":"Hofwaldweg;Tirol",
    "iso:country":"AT",
    "sg:address":"Hofwaldweg 12",
    "sg:city":"Innsbruck",
    "sg:orig_category":"Marketingberatung",
    "sg:phone":"+43 512 293635",
    "sg:postcode":"6020",
    "sg:province":"Tirol",
    "wof:name":"Impuls People to People Marketing GmbH",
    "wof:placetype":"venue"
},
  "geometry": {"coordinates":[11.3680925369,47.2704734802],"type":"Point"}
}