{
  "type": "Feature",
  "properties": {
    "iso:country":"AT",
    "sg:address":"Nr 74",
    "sg:city":"Altenmarkt-Thenneberg",
    "sg:orig_category":"Non-Classified Establishments",
    "sg:phone":"+43 2673 22710",
    "sg:postcode":"2571",
    "sg:province":"Nieder\u00f6sterreich",
    "wof:name":"Pfarramt Hafnerberg",
    "wof:placetype":"venue"
},
  "geometry": {"coordinates":[15.9934692383,48.0158538818],"type":"Point"}
}