{
  "type": "Feature",
  "properties": {
    "addr:full":"Schildlehen 19 Ramsau am Dachstein Steiermark 8972",
    "addr:housenumber":"19",
    "addr:postcode":"8972",
    "addr:street":"Schildlehen",
    "iso:country":"AT",
    "sg:address":"Schildlehen 19",
    "sg:city":"Ramsau am Dachstein",
    "sg:orig_category":"Pensionen / Privatzimmer",
    "sg:phone":"+43 4336 8781213",
    "sg:postcode":"8972",
    "sg:province":"Steiermark",
    "wof:name":"Mayerhofer Walter",
    "wof:placetype":"venue"
},
  "geometry": {"coordinates":[13.6250810623,47.4280967712],"type":"Point"}
}