{
  "type": "Feature",
  "properties": {
    "addr:full":"Obermauern 51 Virgen Tirol 9972",
    "addr:housenumber":"51",
    "addr:postcode":"9972",
    "addr:street":"Obermauern;Tirol",
    "iso:country":"AT",
    "sg:address":"Obermauern 51",
    "sg:city":"Virgen",
    "sg:orig_category":"Fenster",
    "sg:phone":"+43 4874 5484",
    "sg:postcode":"9972",
    "sg:province":"Tirol",
    "wof:name":"Stadler Josef - Fenster-T\u00fcren-Rolladen-M\u00f6bel",
    "wof:placetype":"venue"
},
  "geometry": {"coordinates":[12.4522361755,47.0038948059],"type":"Point"}
}