{
  "type": "Feature",
  "properties": {
    "addr:full":"Riesstr 146 Ragnitz Steiermark 8047",
    "addr:housenumber":"146",
    "addr:postcode":"8047",
    "iso:country":"AT",
    "sg:address":"Riesstr 146",
    "sg:city":"Ragnitz",
    "sg:classifiers":[
        {
            "category":"Professional",
            "subcategory":"Computer Services",
            "type":"Services"
        }
    ],
    "sg:phone":"+43 4331 6402837",
    "sg:postcode":"8047",
    "sg:province":"Steiermark",
    "sg:tags":[
        "software"
    ],
    "wof:name":"SMI Software & Messtechnik Institut GmbH",
    "wof:placetype":"venue"
},
  "geometry": {"coordinates":[15.4875822067,47.0845603943],"type":"Point"}
}