{
  "type": "Feature",
  "properties": {
    "addr:full":"Jedlersdorfer Str 99 Wien Wien 1210",
    "addr:postcode":"1210",
    "addr:street":"Str 99",
    "iso:country":"AT",
    "sg:address":"Jedlersdorfer Str 99",
    "sg:city":"Wien",
    "sg:orig_category":"Gartenbaubedarf",
    "sg:phone":"+43 1 47921040",
    "sg:postcode":"1210",
    "sg:province":"Wien",
    "wof:name":"Diwoky's Gartenfreund Fritz Hochauer",
    "wof:placetype":"venue"
},
  "geometry": {"coordinates":[16.4044837952,48.2765197754],"type":"Point"}
}