{
  "type": "Feature",
  "properties": {
    "addr:full":"Bahnhofstr 7 Wartberg an der Krems Ober\u00f6sterreich 4552",
    "addr:housenumber":"7",
    "addr:postcode":"4552",
    "addr:street":"Bahnhofstr",
    "iso:country":"AT",
    "sg:address":"Bahnhofstr 7",
    "sg:city":"Wartberg an der Krems",
    "sg:orig_category":"Baumeister",
    "sg:phone":"+43 4375 877551",
    "sg:postcode":"4552",
    "sg:province":"Ober\u00f6sterreich",
    "wof:name":"Lagerhaus Bau-Service regGenmbH & Co KG",
    "wof:placetype":"venue"
},
  "geometry": {"coordinates":[14.1209497452,47.9897117615],"type":"Point"}
}