{
  "type": "Feature",
  "properties": {
    "addr:full":"Zieglergasse 30 Wien Wien 1070",
    "addr:housenumber":"30",
    "addr:postcode":"1070",
    "addr:street":"Zieglergasse",
    "iso:country":"AT",
    "sg:address":"Zieglergasse 30",
    "sg:city":"Wien",
    "sg:classifiers":[
        {
            "category":"Manufacturing",
            "subcategory":"Glass & Minerals",
            "type":"Manufacturing & Wholesale Goods"
        }
    ],
    "sg:phone":"+43 1 5235405",
    "sg:postcode":"1070",
    "sg:province":"Wien",
    "sg:tags":[
        "flat"
    ],
    "wof:name":"ABC Glas Pelikan GesmbH",
    "wof:placetype":"venue"
},
  "geometry": {"coordinates":[16.3451347351,48.2007980347],"type":"Point"}
}