{
  "type": "Feature",
  "properties": {
    "addr:full":"Handelskay 388 Top 832  Wien Wien 1020",
    "addr:housenumber":"388;832",
    "addr:postcode":"1020",
    "addr:street":"Top",
    "iso:country":"AT",
    "sg:address":"Handelskay 388 Top 832 ",
    "sg:city":"Wien",
    "sg:classifiers":[
        {
            "category":"Marine",
            "type":"Transportation"
        }
    ],
    "sg:phone":"+43 4317 2869340",
    "sg:postcode":"1020",
    "sg:province":"Wien",
    "sg:tags":[
        "transport",
        "sea"
    ],
    "wof:name":"DANUBE SHIPPING MANAGEMENT SERVICE GESMBH",
    "wof:placetype":"venue"
},
  "geometry": {"coordinates":[16.3802642822,48.2153701782],"type":"Point"}
}