{
  "type": "Feature",
  "properties": {
    "addr:full":"An der oberen Alten Donau 193 Wien Wien 1220",
    "addr:housenumber":"193",
    "addr:postcode":"1220",
    "addr:street":"An Der Oberen Alten Donau",
    "iso:country":"AT",
    "sg:address":"An der oberen Alten Donau 193",
    "sg:city":"Wien",
    "sg:orig_category":"Gastronomie- U Hotelbetriebsgesellschaften",
    "sg:phone":"+43 4312 030271",
    "sg:postcode":"1220",
    "sg:province":"Wien",
    "wof:name":"Sunken City - Ho-Meer GesmbH",
    "wof:placetype":"venue"
},
  "geometry": {"coordinates":[16.4271278381,48.2405166626],"type":"Point"}
}