{
  "type": "Feature",
  "properties": {
    "addr:full":"Lamezanstrasse 12 Wien Wien 1230",
    "addr:housenumber":"12",
    "addr:postcode":"1230",
    "addr:street":"Lamezanstrasse",
    "iso:country":"AT",
    "sg:address":"Lamezanstrasse 12",
    "sg:city":"Wien",
    "sg:classifiers":[
        {
            "category":"Community Center",
            "subcategory":"Senior",
            "type":"Public Place"
        }
    ],
    "sg:phone":"+43 1 6174575",
    "sg:postcode":"1230",
    "sg:province":"Wien",
    "sg:tags":[
        "steel",
        "metal",
        "part",
        "sheet"
    ],
    "sg:website":"petristahl.at",
    "wof:name":"Johannes Huber",
    "wof:placetype":"venue"
},
  "geometry": {"coordinates":[16.3388328552,48.1391487122],"type":"Point"}
}