{
  "type": "Feature",
  "properties": {
    "iso:country":"AT",
    "sg:address":"Moosfeldstr 27",
    "sg:city":"Bergheim",
    "sg:orig_category":"Fu\u00c3\u0178pflege U Fu\u00c3\u0178pflegesalons",
    "sg:phone":"+43 664 5016472",
    "sg:postcode":"5101",
    "sg:province":"Salzburg",
    "wof:name":"Bauer Silvia",
    "wof:placetype":"venue"
},
  "geometry": {"coordinates":[13.0581693649,47.8420372009],"type":"Point"}
}