{
  "type": "Feature",
  "properties": {
    "addr:full":"Gartenring 6 Traismauer Nieder\u00f6sterreich 3133",
    "addr:housenumber":"6",
    "addr:postcode":"3133",
    "addr:street":"Gartenring",
    "iso:country":"AT",
    "sg:address":"Gartenring 6",
    "sg:city":"Traismauer",
    "sg:orig_category":"Polizei U Gendarmerie",
    "sg:phone":"+43 4359 1333176",
    "sg:postcode":"3133",
    "sg:province":"Nieder\u00f6sterreich",
    "wof:name":"Gendarmerie",
    "wof:placetype":"venue"
},
  "geometry": {"coordinates":[15.7462873459,48.3505516052],"type":"Point"}
}