{
  "type": "Feature",
  "properties": {
    "addr:full":"Hauptpl 28 Waidhofen an der Thaya Nieder\u00f6sterreich 3830",
    "addr:housenumber":"28",
    "addr:postcode":"3830",
    "addr:street":"Hauptpl",
    "iso:country":"AT",
    "sg:address":"Hauptpl 28",
    "sg:city":"Waidhofen an der Thaya",
    "sg:orig_category":"Fotoapparate U -Artikel / Einzelhandel",
    "sg:phone":"+43 4328 4252232",
    "sg:postcode":"3830",
    "sg:province":"Nieder\u00f6sterreich",
    "wof:name":"Hartlauer HandelsgesmbH",
    "wof:placetype":"venue"
},
  "geometry": {"coordinates":[15.2871379852,48.8154563904],"type":"Point"}
}