{
  "type": "Feature",
  "properties": {
    "addr:full":"Hauptstr 24 Hieflau Steiermark 8920",
    "addr:housenumber":"24",
    "addr:postcode":"8920",
    "addr:street":"Hauptstr",
    "iso:country":"AT",
    "sg:address":"Hauptstr 24",
    "sg:city":"Hieflau",
    "sg:orig_category":"Bankomat-Standorte",
    "sg:phone":"+43 3634 6770",
    "sg:postcode":"8920",
    "sg:province":"Steiermark",
    "wof:name":"Bankomat d Raiffeisenbank Trofaiach-Leoben",
    "wof:placetype":"venue"
},
  "geometry": {"coordinates":[14.746175766,47.6043891907],"type":"Point"}
}