{
  "type": "Feature",
  "properties": {
    "addr:full":"Bahnhofstr 5 St. Paul im Lavanttal K\u00e4rnten 9470",
    "addr:housenumber":"5",
    "addr:postcode":"9470",
    "addr:street":"Bahnhofstr",
    "iso:country":"AT",
    "sg:address":"Bahnhofstr 5",
    "sg:city":"St. Paul im Lavanttal",
    "sg:orig_category":"Lebensmittel / Einzelhandel",
    "sg:phone":"+43 4343 5736600",
    "sg:postcode":"9470",
    "sg:province":"K\u00e4rnten",
    "wof:name":"SPAR \u00f6sterreichische Warenhandels-AG",
    "wof:placetype":"venue"
},
  "geometry": {"coordinates":[14.8674526215,46.7052764893],"type":"Point"}
}