{
  "type": "Feature",
  "properties": {
    "addr:full":"Nr 202 Achenkirch Tirol 6215",
    "addr:postcode":"6215",
    "addr:street":"Nr;Achenkirch Tirol",
    "iso:country":"AT",
    "sg:address":"Nr 202",
    "sg:city":"Achenkirch",
    "sg:orig_category":"Tischlereien",
    "sg:phone":"+43 5246 6207",
    "sg:postcode":"6215",
    "sg:province":"Tirol",
    "wof:name":"Jaud Rudolf",
    "wof:placetype":"venue"
},
  "geometry": {"coordinates":[11.7065629959,47.5290184021],"type":"Point"}
}