{
  "type": "Feature",
  "properties": {
    "addr:full":"Salzburger Str 11 Braunau am Inn Ober\u00f6sterreich 5280",
    "addr:housenumber":"11",
    "addr:postcode":"5280",
    "addr:street":"Salzburger Str",
    "iso:country":"AT",
    "sg:address":"Salzburger Str 11",
    "sg:city":"Braunau am Inn",
    "sg:orig_category":"Tankstellen",
    "sg:phone":"+43 7722 627850",
    "sg:postcode":"5280",
    "sg:province":"Ober\u00f6sterreich",
    "wof:name":"BP Austria Marketing GmbH",
    "wof:placetype":"venue"
},
  "geometry": {"coordinates":[13.0361413956,48.2546272278],"type":"Point"}
}