{
  "type": "Feature",
  "properties": {
    "addr:full":"Hauptpl 4 Sollenau Nieder\u00f6sterreich 2601",
    "addr:housenumber":"4",
    "addr:postcode":"2601",
    "addr:street":"Hauptpl",
    "iso:country":"AT",
    "sg:address":"Hauptpl 4",
    "sg:city":"Sollenau",
    "sg:orig_category":"Banken U Sparkassen",
    "sg:phone":"+43 2628 474520",
    "sg:postcode":"2601",
    "sg:province":"Nieder\u00f6sterreich",
    "wof:name":"Raiffeisenregionalbank Wr Neustadt regGenmbH",
    "wof:placetype":"venue"
},
  "geometry": {"coordinates":[16.2497596741,47.8963890076],"type":"Point"}
}