{
  "type": "Feature",
  "properties": {
    "addr:full":"Arlbergstrasse 115 Bregenz Vorarlberg 6900",
    "addr:housenumber":"115",
    "addr:postcode":"6900",
    "addr:street":"Arlbergstrasse",
    "iso:country":"AT",
    "sg:address":"Arlbergstrasse 115",
    "sg:city":"Bregenz",
    "sg:classifiers":[
        {
            "category":"Home & Garden",
            "subcategory":"Carpets & Floor Coverings",
            "type":"Retail Goods"
        }
    ],
    "sg:phone":"+43 5574 72132",
    "sg:postcode":"6900",
    "sg:province":"Vorarlberg",
    "sg:tags":[
        "carpeting"
    ],
    "wof:name":"Vetter Raumausstattung GmbH & Co KG",
    "wof:placetype":"venue"
},
  "geometry": {"coordinates":[9.7333879471,47.4902076721],"type":"Point"}
}