{
  "type": "Feature",
  "properties": {
    "iso:country":"AT",
    "sg:address":"Alemannenstrasse 49",
    "sg:city":"Rankweil",
    "sg:classifiers":[
        {
            "category":"Home & Garden",
            "subcategory":"Carpets & Floor Coverings",
            "type":"Retail Goods"
        }
    ],
    "sg:phone":"+43 5522 43144",
    "sg:postcode":"6830",
    "sg:province":"Vorarlberg",
    "sg:tags":[
        "slab"
    ],
    "wof:name":"Mathis Alfons",
    "wof:placetype":"venue"
},
  "geometry": {"coordinates":[9.6574430466,47.276348114],"type":"Point"}
}