{
  "type": "Feature",
  "properties": {
    "addr:full":"Gregor Mendel-Str 16 Wien Wien 1180",
    "addr:housenumber":"16",
    "addr:postcode":"1180",
    "iso:country":"AT",
    "sg:address":"Gregor Mendel-Str 16",
    "sg:city":"Wien",
    "sg:orig_category":"Anlagenbau U -Technik",
    "sg:phone":"+43 4314 709963",
    "sg:postcode":"1180",
    "sg:province":"Wien",
    "wof:name":"ECKE Anlagenbau- u HandelsgesmbH",
    "wof:placetype":"venue"
},
  "geometry": {"coordinates":[16.3378276825,48.2314186096],"type":"Point"}
}