{
  "type": "Feature",
  "properties": {
    "addr:full":"Franziskanerpl 15 Graz Steiermark 8010",
    "addr:housenumber":"15",
    "addr:postcode":"8010",
    "addr:street":"Franziskanerpl",
    "iso:country":"AT",
    "sg:address":"Franziskanerpl 15",
    "sg:city":"Graz",
    "sg:orig_category":"Tabaktrafiken",
    "sg:phone":"+43 316 810510",
    "sg:postcode":"8010",
    "sg:province":"Steiermark",
    "wof:name":"Pommer Anneliese",
    "wof:placetype":"venue"
},
  "geometry": {"coordinates":[15.436621666,47.0707244873],"type":"Point"}
}