{
  "type": "Feature",
  "properties": {
    "addr:full":"Wr Neust\u00e4dter Str 51 Ebreichsdorf Nieder\u00f6sterreich 2483",
    "addr:postcode":"2483",
    "addr:street":"Str 51",
    "iso:country":"AT",
    "sg:address":"Wr Neust\u00e4dter Str 51",
    "sg:city":"Ebreichsdorf",
    "sg:orig_category":"Autoreparatur",
    "sg:phone":"+43 2254 73874",
    "sg:postcode":"2483",
    "sg:province":"Nieder\u00f6sterreich",
    "wof:name":"Mozelt Alfred",
    "wof:placetype":"venue"
},
  "geometry": {"coordinates":[16.4015541077,47.9631080627],"type":"Point"}
}