{
  "type": "Feature",
  "properties": {
    "iso:country":"AT",
    "sg:address":"Schwarzspanierstr 11",
    "sg:city":"Wien",
    "sg:orig_category":"Immobilienmakler",
    "sg:phone":"+43 1 4085249",
    "sg:postcode":"1090",
    "sg:province":"Wien",
    "wof:name":"Gross Detlev Mag",
    "wof:placetype":"venue"
},
  "geometry": {"coordinates":[16.3565063477,48.2164497375],"type":"Point"}
}