{
  "type": "Feature",
  "properties": {
    "addr:full":"Grillparzerstr 23 Attnang-Puchheim Ober\u00f6sterreich 4800",
    "addr:housenumber":"23",
    "addr:postcode":"4800",
    "addr:street":"Grillparzerstr",
    "iso:country":"AT",
    "sg:address":"Grillparzerstr 23",
    "sg:city":"Attnang-Puchheim",
    "sg:orig_category":"Werbeagenturen",
    "sg:phone":"+43 7674650670",
    "sg:postcode":"4800",
    "sg:province":"Ober\u00f6sterreich",
    "wof:name":"Kreaktiv Werbeagentur Hermann Bliem",
    "wof:placetype":"venue"
},
  "geometry": {"coordinates":[13.7095470428,48.0013656616],"type":"Point"}
}