{
  "type": "Feature",
  "properties": {
    "addr:full":"Rheinstr 243 Feldkirch Vorarlberg 6800",
    "addr:housenumber":"243",
    "addr:postcode":"6800",
    "iso:country":"AT",
    "sg:address":"Rheinstr 243",
    "sg:city":"Feldkirch",
    "sg:orig_category":"Polizei U Gendarmerie",
    "sg:phone":"+43 4359 1338162",
    "sg:postcode":"6800",
    "sg:province":"Vorarlberg",
    "wof:name":"Gendarmerie-Grenzkontrollstelle Feldkirch-Bangs",
    "wof:placetype":"venue"
},
  "geometry": {"coordinates":[9.5447406769,47.265827179],"type":"Point"}
}