{
  "type": "Feature",
  "properties": {
    "addr:full":"Luftbadg 14-16 Wien Wien 1060",
    "addr:postcode":"14-16;1060",
    "iso:country":"AT",
    "sg:address":"Luftbadg 14-16",
    "sg:city":"Wien",
    "sg:orig_category":"Beratungsstellen",
    "sg:phone":"+43 4319 610585",
    "sg:postcode":"1060",
    "sg:province":"Wien",
    "wof:name":"Equal - Gleiche Chancen im Betrieb",
    "wof:placetype":"venue"
},
  "geometry": {"coordinates":[16.3547477722,48.1975517273],"type":"Point"}
}