{
  "type": "Feature",
  "properties": {
    "addr:full":"Prangerstr 15 Breitenbrunn Burgenland 7091",
    "addr:housenumber":"15",
    "addr:postcode":"7091",
    "addr:street":"Prangerstr",
    "iso:country":"AT",
    "sg:address":"Prangerstr 15",
    "sg:city":"Breitenbrunn",
    "sg:orig_category":"Tabaktrafiken",
    "sg:phone":"+43 2683 5311",
    "sg:postcode":"7091",
    "sg:province":"Burgenland",
    "wof:name":"Feher Anna",
    "wof:placetype":"venue"
},
  "geometry": {"coordinates":[16.7335853577,47.9466171265],"type":"Point"}
}