{
  "type": "Feature",
  "properties": {
    "addr:full":"Loferer Str 4 Saalfelden am Steinernen Meer Salzburg 5760",
    "addr:housenumber":"4",
    "addr:postcode":"5760",
    "addr:street":"Str",
    "iso:country":"AT",
    "sg:address":"Loferer Str 4",
    "sg:city":"Saalfelden am Steinernen Meer",
    "sg:orig_category":"Boutiquen",
    "sg:phone":"+43 6582 747140",
    "sg:postcode":"5760",
    "sg:province":"Salzburg",
    "wof:name":"Brooks Fashion Concept Boutique H & O HandelsgesmbH",
    "wof:placetype":"venue"
},
  "geometry": {"coordinates":[12.8486824036,47.4254684448],"type":"Point"}
}