{
  "type": "Feature",
  "properties": {
    "addr:full":"Reichshofstr 2 Lustenau Vorarlberg 6890",
    "addr:housenumber":"2",
    "addr:postcode":"6890",
    "addr:street":"Reichshofstr",
    "iso:country":"AT",
    "sg:address":"Reichshofstr 2",
    "sg:city":"Lustenau",
    "sg:orig_category":"Optiker",
    "sg:phone":"+43 4355 7782098",
    "sg:postcode":"6890",
    "sg:province":"Vorarlberg",
    "wof:name":"Augenoptik Ender",
    "wof:placetype":"venue"
},
  "geometry": {"coordinates":[9.6511573792,47.4259719849],"type":"Point"}
}