{
  "type": "Feature",
  "properties": {
    "addr:full":"Loferer Bundesstr 1 Zell am See Salzburg 5700",
    "addr:housenumber":"1",
    "addr:postcode":"5700",
    "addr:street":"Bundesstr;Salzburg",
    "iso:country":"AT",
    "sg:address":"Loferer Bundesstr 1",
    "sg:city":"Zell am See",
    "sg:orig_category":"Elektroinstallationsunternehmen",
    "sg:phone":"+43 6542 72658",
    "sg:postcode":"5700",
    "sg:province":"Salzburg",
    "sg:website":"elektrorasser.at",
    "wof:name":"Rasser Siegmund Ing Elektro-Radio GesmbH",
    "wof:placetype":"venue"
},
  "geometry": {"coordinates":[12.796453476,47.3238716125],"type":"Point"}
}