{
  "type": "Feature",
  "properties": {
    "addr:full":"Achomitz 22 Feistritz an der Gail K\u00e4rnten 9613",
    "addr:housenumber":"22",
    "addr:postcode":"9613",
    "addr:street":"Achomitz",
    "iso:country":"AT",
    "sg:address":"Achomitz 22",
    "sg:city":"Feistritz an der Gail",
    "sg:classifiers":[
        {
            "category":"Home & Garden",
            "subcategory":"Carpets & Floor Coverings",
            "type":"Retail Goods"
        }
    ],
    "sg:phone":"+43 4256 2705",
    "sg:postcode":"9613",
    "sg:province":"K\u00e4rnten",
    "sg:tags":[
        "tile"
    ],
    "wof:name":"Robert Moser",
    "wof:placetype":"venue"
},
  "geometry": {"coordinates":[13.6317987442,46.5595397949],"type":"Point"}
}