{
  "type": "Feature",
  "properties": {
    "addr:full":"Laabstr 42 Braunau am Inn Ober\u00f6sterreich 5280",
    "addr:housenumber":"42",
    "addr:postcode":"5280",
    "addr:street":"Laabstr",
    "iso:country":"AT",
    "sg:address":"Laabstr 42",
    "sg:city":"Braunau am Inn",
    "sg:orig_category":"Autoersatzteile",
    "sg:phone":"+43 7722 833730",
    "sg:postcode":"5280",
    "sg:province":"Ober\u00f6sterreich",
    "wof:name":"Forstinger Handel und Service GmbH",
    "wof:placetype":"venue"
},
  "geometry": {"coordinates":[13.0482358932,48.2609367371],"type":"Point"}
}