{
  "type": "Feature",
  "properties": {
    "addr:full":"Rudolf-Waisenhorn-Gasse 3 Wien Wien 1230",
    "addr:housenumber":"3",
    "addr:postcode":"1230",
    "addr:street":"Rudolf-Waisenhorn-Gasse",
    "iso:country":"AT",
    "sg:address":"Rudolf-Waisenhorn-Gasse 3",
    "sg:city":"Wien",
    "sg:orig_category":"Candle Dyes",
    "sg:phone":"+43 1 86595810",
    "sg:postcode":"1230",
    "sg:province":"Wien",
    "sg:website":"vienna-color.com",
    "wof:name":"Anton Schimek, Erzeugung von Haushaltsfarben und Holzbeizen KG",
    "wof:placetype":"venue"
},
  "geometry": {"coordinates":[16.2869358063,48.1365394592],"type":"Point"}
}