{
  "type": "Feature",
  "properties": {
    "iso:country":"AT",
    "sg:address":"Linke Wienzeile 128",
    "sg:city":"Wien",
    "sg:orig_category":"Psychotherapie",
    "sg:phone":"+43 1 9200770",
    "sg:postcode":"1060",
    "sg:province":"Wien",
    "wof:name":"Mayerhofer Gabriele Mag",
    "wof:placetype":"venue"
},
  "geometry": {"coordinates":[16.352437973,48.1908798218],"type":"Point"}
}