{
  "type": "Feature",
  "properties": {
    "addr:full":"Ostmarkg 26 Wien Wien 1210",
    "addr:housenumber":"26",
    "addr:postcode":"1210",
    "addr:street":"Ostmarkg",
    "iso:country":"AT",
    "sg:address":"Ostmarkg 26",
    "sg:city":"Wien",
    "sg:orig_category":"Autoreparatur",
    "sg:phone":"+43 1 2727766",
    "sg:postcode":"1210",
    "sg:province":"Wien",
    "wof:name":"KFZ-Meisterbetrieb Dr\u00f6ssler & Divoky OEG",
    "wof:placetype":"venue"
},
  "geometry": {"coordinates":[16.4096374512,48.2567901611],"type":"Point"}
}