{
  "type": "Feature",
  "properties": {
    "addr:full":"F\u00fcrlingerberg 12 Rohrbach in Ober\u00f6sterreich Ober\u00f6sterreich 4150",
    "addr:housenumber":"12",
    "addr:postcode":"4150",
    "addr:street":"Fuerlingerberg",
    "iso:country":"AT",
    "sg:address":"F\u00fcrlingerberg 12",
    "sg:city":"Rohrbach in Ober\u00f6sterreich",
    "sg:classifiers":[
        {
            "category":"Organizations",
            "subcategory":"Non-profit Organization",
            "type":"Services"
        }
    ],
    "sg:phone":"+43 7289 8111",
    "sg:postcode":"4150",
    "sg:province":"Ober\u00f6sterreich",
    "sg:tags":[
        "alarm",
        "system"
    ],
    "wof:name":"Alois Schaubmair",
    "wof:placetype":"venue"
},
  "geometry": {"coordinates":[13.9905195236,48.5726852417],"type":"Point"}
}