{
  "type": "Feature",
  "properties": {
    "addr:full":"Kapr Generator-Str 37 Weiz Steiermark 8160",
    "addr:housenumber":"37",
    "addr:postcode":"8160",
    "iso:country":"AT",
    "sg:address":"Kapr Generator-Str 37",
    "sg:city":"Weiz",
    "sg:orig_category":"Medizinische Institute",
    "sg:phone":"+43 3172 41307",
    "sg:postcode":"8160",
    "sg:province":"Steiermark",
    "wof:name":"Institut f\u00fcr Computertomographie - Dr Thalhamer & Dr Z\u00f6hrer \u00c4rztepartnerschaft",
    "wof:placetype":"venue"
},
  "geometry": {"coordinates":[15.6259784698,47.2201538086],"type":"Point"}
}