{
  "type": "Feature",
  "properties": {
    "addr:full":"Wormser Str 5 Eisenstadt Burgenland 7000",
    "addr:housenumber":"5",
    "addr:postcode":"7000",
    "addr:street":"Wormser Str",
    "iso:country":"AT",
    "sg:address":"Wormser Str 5",
    "sg:city":"Eisenstadt",
    "sg:orig_category":"\u00c3\u201erzte / F Allgemeinmedizin",
    "sg:phone":"+43 2682 679160",
    "sg:postcode":"7000",
    "sg:province":"Burgenland",
    "wof:name":"B\u00f6hm Georg Dr",
    "wof:placetype":"venue"
},
  "geometry": {"coordinates":[16.5246391296,47.8420791626],"type":"Point"}
}