{
  "type": "Feature",
  "properties": {
    "iso:country":"AT",
    "sg:address":"Tullner Str 41",
    "sg:city":"Stockerau",
    "sg:orig_category":"Fitnesscenter",
    "sg:phone":"+43 4322 6665191",
    "sg:postcode":"2000",
    "sg:province":"Nieder\u00f6sterreich",
    "wof:name":"Fitaktivclub Gitti-City - Brigitte Scheidl GesmbH",
    "wof:placetype":"venue"
},
  "geometry": {"coordinates":[16.1829547882,48.384677887],"type":"Point"}
}