{
  "type": "Feature",
  "properties": {
    "addr:full":"Landstr. Hauptstr. 110  Wien Wien 1030",
    "addr:housenumber":"110",
    "addr:postcode":"1030",
    "addr:street":"Hauptstr.",
    "iso:country":"AT",
    "sg:address":"Landstr. Hauptstr. 110 ",
    "sg:city":"Wien",
    "sg:classifiers":[
        {
            "category":"Professional",
            "subcategory":"Business Services",
            "type":"Services"
        }
    ],
    "sg:phone":"+43 4317 135238",
    "sg:postcode":"1030",
    "sg:province":"Wien",
    "sg:tags":[
        "advice"
    ],
    "wof:name":"M\u00d6BEL KLEIN HANDELSGESMBH & CO KG, INH JOHANN KLEIN",
    "wof:placetype":"venue"
},
  "geometry": {"coordinates":[16.3951225281,48.197555542],"type":"Point"}
}