{
  "type": "Feature",
  "properties": {
    "iso:country":"AT",
    "sg:address":"Br\u00e4uhausg 10/2",
    "sg:city":"Salzburg",
    "sg:orig_category":"Psychotherapie",
    "sg:phone":"+43 662 834261",
    "sg:postcode":"5020",
    "sg:province":"Salzburg",
    "wof:name":"Schellenbacher Manfred Dr",
    "wof:placetype":"venue"
},
  "geometry": {"coordinates":[13.0243406296,47.7939338684],"type":"Point"}
}