{
  "type": "Feature",
  "properties": {
    "addr:full":"Gu\u00dfriegelstr 11 Wien Wien 1100",
    "addr:housenumber":"11",
    "addr:postcode":"1100",
    "addr:street":"Gussriegelstr",
    "iso:country":"AT",
    "sg:address":"Gu\u00dfriegelstr 11",
    "sg:city":"Wien",
    "sg:orig_category":"Lebensmittel / Einzelhandel",
    "sg:phone":"+43 1 6043522",
    "sg:postcode":"1100",
    "sg:province":"Wien",
    "wof:name":"Csenar Christine",
    "wof:placetype":"venue"
},
  "geometry": {"coordinates":[16.3592319489,48.1748275757],"type":"Point"}
}