{
  "type": "Feature",
  "properties": {
    "iso:country":"AT",
    "sg:address":"Eichbergweg 1",
    "sg:city":"Puchberg am Schneeberg",
    "sg:orig_category":"Mess-, Steuer- U Regeltechnik",
    "sg:phone":"+43 4326 362180",
    "sg:postcode":"2734",
    "sg:province":"Nieder\u00f6sterreich",
    "wof:name":"Zottl Walter",
    "wof:placetype":"venue"
},
  "geometry": {"coordinates":[15.9345407486,47.8042640686],"type":"Point"}
}