{
  "type": "Feature",
  "properties": {
    "addr:full":"Teichg 6 Ebenthal in K\u00e4rnten K\u00e4rnten 9065",
    "addr:housenumber":"6",
    "addr:postcode":"9065",
    "addr:street":"Teichg;Kaernten",
    "iso:country":"AT",
    "sg:address":"Teichg 6",
    "sg:city":"Ebenthal in K\u00e4rnten",
    "sg:orig_category":"Handelsagenturen",
    "sg:phone":"+43 463 73200",
    "sg:postcode":"9065",
    "sg:province":"K\u00e4rnten",
    "wof:name":"Zwipp Gabriele",
    "wof:placetype":"venue"
},
  "geometry": {"coordinates":[14.4087972641,46.6030006409],"type":"Point"}
}