{
  "type": "Feature",
  "properties": {
    "addr:full":"Loferer Str 29 Saalfelden am Steinernen Meer Salzburg 5760",
    "addr:postcode":"5760",
    "addr:street":"Str 29;Salzburg",
    "iso:country":"AT",
    "sg:address":"Loferer Str 29",
    "sg:city":"Saalfelden am Steinernen Meer",
    "sg:orig_category":"\u00c3\u201enderungsschneidereien",
    "sg:phone":"+43 6582 74591",
    "sg:postcode":"5760",
    "sg:province":"Salzburg",
    "wof:name":"Fischb\u00f6ck Sabine",
    "wof:placetype":"venue"
},
  "geometry": {"coordinates":[12.8462762833,47.4286956787],"type":"Point"}
}