{
  "type": "Feature",
  "properties": {
    "addr:full":"Stattersdorfer Hauptstr 14 St. P\u00f6lten Nieder\u00f6sterreich 3100",
    "addr:housenumber":"14",
    "addr:postcode":"3100",
    "addr:street":"Stattersdorfer Hauptstr",
    "iso:country":"AT",
    "sg:address":"Stattersdorfer Hauptstr 14",
    "sg:city":"St. P\u00f6lten",
    "sg:orig_category":"Tischlereien",
    "sg:phone":"+43 4327 42252179",
    "sg:postcode":"3100",
    "sg:province":"Nieder\u00f6sterreich",
    "wof:name":"Hollaus Josef",
    "wof:placetype":"venue"
},
  "geometry": {"coordinates":[15.6240940094,48.2076377869],"type":"Point"}
}