{
  "type": "Feature",
  "properties": {
    "iso:country":"AT",
    "sg:address":"Gst\u00e4tteng 16",
    "sg:city":"Salzburg",
    "sg:orig_category":"Tanzschulen",
    "sg:phone":"+43 662 833800",
    "sg:postcode":"5020",
    "sg:province":"Salzburg",
    "sg:website":"tanzschule-moll.at",
    "wof:name":"Tanzschule Moll KEG",
    "wof:placetype":"venue"
},
  "geometry": {"coordinates":[13.0386772156,47.8019752502],"type":"Point"}
}