{
  "type": "Feature",
  "properties": {
    "iso:country":"AT",
    "sg:city":"Uttendorf",
    "sg:orig_category":"Feuerwehren",
    "sg:phone":"+43 7724 3296",
    "sg:postcode":"5261",
    "sg:province":"Ober\u00f6sterreich",
    "wof:name":"Freiwillige Feuerwehr Uttendorf",
    "wof:placetype":"venue"
},
  "geometry": {"coordinates":[13.1183948517,48.1551017761],"type":"Point"}
}