{
  "type": "Feature",
  "properties": {
    "iso:country":"AT",
    "sg:address":"10.-Oktober-Str 16a",
    "sg:city":"Velden am W\u00f6rther See",
    "sg:orig_category":"Baumeister",
    "sg:phone":"+43 4342 742019",
    "sg:postcode":"9220",
    "sg:province":"K\u00e4rnten",
    "wof:name":"Huber Bau GesmbH",
    "wof:placetype":"venue"
},
  "geometry": {"coordinates":[14.0376386642,46.6120796204],"type":"Point"}
}