{
  "type": "Feature",
  "properties": {
    "addr:full":"Bauernfeldstr 2a Neuhofen an der Krems Ober\u00f6sterreich 4501",
    "addr:housenumber":"2a",
    "addr:postcode":"4501",
    "addr:street":"Bauernfeldstr",
    "iso:country":"AT",
    "sg:address":"Bauernfeldstr 2a",
    "sg:city":"Neuhofen an der Krems",
    "sg:orig_category":"Aquarien U Aquarienbedarf",
    "sg:phone":"+43 4372 2720700",
    "sg:postcode":"4501",
    "sg:province":"Ober\u00f6sterreich",
    "wof:name":"AQUA TREFF",
    "wof:placetype":"venue"
},
  "geometry": {"coordinates":[14.2402887344,48.1382331848],"type":"Point"}
}