{
  "type": "Feature",
  "properties": {
    "addr:full":"Schulring 9 Auersthal Nieder\u00f6sterreich 2214",
    "addr:housenumber":"9",
    "addr:postcode":"2214",
    "addr:street":"Schulring",
    "iso:country":"AT",
    "sg:address":"Schulring 9",
    "sg:city":"Auersthal",
    "sg:orig_category":"Volksschulen",
    "sg:phone":"+43 2288 2301",
    "sg:postcode":"2214",
    "sg:province":"Nieder\u00f6sterreich",
    "wof:name":"Volksschule",
    "wof:placetype":"venue"
},
  "geometry": {"coordinates":[16.638463974,48.3743400574],"type":"Point"}
}