{
  "type": "Feature",
  "properties": {
    "addr:full":"Dorf 135 Breitenbach am Inn Tirol 6252",
    "addr:housenumber":"135",
    "addr:postcode":"6252",
    "addr:street":"Dorf;Tirol",
    "iso:country":"AT",
    "sg:address":"Dorf 135",
    "sg:city":"Breitenbach am Inn",
    "sg:orig_category":"Tourismusinformation U -Organisationen",
    "sg:phone":"+43 4353 3877380",
    "sg:postcode":"6252",
    "sg:province":"Tirol",
    "wof:name":"Tourismusverband",
    "wof:placetype":"venue"
},
  "geometry": {"coordinates":[11.9796380997,47.4805908203],"type":"Point"}
}