{
  "type": "Feature",
  "properties": {
    "iso:country":"AT",
    "sg:address":"Froschberg 8",
    "sg:city":"Linz",
    "sg:orig_category":"Ingenieurkonsulenten / Zivilingenieure",
    "sg:phone":"+43 732 6587880",
    "sg:postcode":"4020",
    "sg:province":"Ober\u00f6sterreich",
    "wof:name":"Sternad Bruno Dipl-Ing Dr",
    "wof:placetype":"venue"
},
  "geometry": {"coordinates":[14.2819547653,48.2899742126],"type":"Point"}
}