{
  "type": "Feature",
  "properties": {
    "addr:full":"Dr.-Anton-Schneider-Strasse 5 Dornbirn Vorarlberg 6850",
    "addr:housenumber":"5",
    "addr:postcode":"6850",
    "addr:street":"Dr.-Anton-Schneider-Strasse",
    "iso:country":"AT",
    "sg:address":"Dr.-Anton-Schneider-Strasse 5",
    "sg:city":"Dornbirn",
    "sg:classifiers":[
        {
            "category":"Wholesale",
            "subcategory":"Auto Parts",
            "type":"Manufacturing & Wholesale Goods"
        }
    ],
    "sg:phone":"+43 5572 22654",
    "sg:postcode":"6850",
    "sg:province":"Vorarlberg",
    "sg:tags":[
        "wheel",
        "car",
        "alloy",
        "rims"
    ],
    "wof:name":"Reifen Fischer Ges.m.b.H.",
    "wof:placetype":"venue"
},
  "geometry": {"coordinates":[9.7463645935,47.4209747314],"type":"Point"}
}