{
  "type": "Feature",
  "properties": {
    "addr:full":"Manker Str 27 Wieselburg an der Erlauf Nieder\u00f6sterreich 3250",
    "addr:postcode":"3250",
    "addr:street":"Str 27",
    "iso:country":"AT",
    "sg:address":"Manker Str 27",
    "sg:city":"Wieselburg an der Erlauf",
    "sg:orig_category":"Dachdeckereien",
    "sg:phone":"+43 4374 1659000",
    "sg:postcode":"3250",
    "sg:province":"Nieder\u00f6sterreich",
    "wof:name":"Wanzmann GesmbH & Co KG",
    "wof:placetype":"venue"
},
  "geometry": {"coordinates":[15.143652916,48.1281776428],"type":"Point"}
}