{
  "type": "Feature",
  "properties": {
    "iso:country":"AT",
    "sg:address":"Griespl 11",
    "sg:city":"Graz",
    "sg:orig_category":"Immobilienmakler",
    "sg:phone":"+43 316 70990",
    "sg:postcode":"8020",
    "sg:province":"Steiermark",
    "wof:name":"L\u00e4nderrealit\u00e4ten J Hammerl GesmbH & Co KG",
    "wof:placetype":"venue"
},
  "geometry": {"coordinates":[15.4317121506,47.0649452209],"type":"Point"}
}