{
  "type": "Feature",
  "properties": {
    "addr:full":"Nr 27 St. Ruprecht an der Raab Steiermark 8181",
    "addr:postcode":"8181",
    "addr:street":"Nr 27",
    "iso:country":"AT",
    "sg:address":"Nr 27",
    "sg:city":"St. Ruprecht an der Raab",
    "sg:orig_category":"Musikunterricht",
    "sg:phone":"+43 4331 783130",
    "sg:postcode":"8181",
    "sg:province":"Steiermark",
    "wof:name":"Musikschule St Ruprecht",
    "wof:placetype":"venue"
},
  "geometry": {"coordinates":[15.6658182144,47.1803436279],"type":"Point"}
}