{
  "type": "Feature",
  "properties": {
    "addr:full":"Mariazeller Str 30a Wilhelmsburg an der Traisen Nieder\u00f6sterreich 3150",
    "addr:housenumber":"30a",
    "addr:postcode":"3150",
    "addr:street":"Str;An",
    "iso:country":"AT",
    "sg:address":"Mariazeller Str 30a",
    "sg:city":"Wilhelmsburg an der Traisen",
    "sg:classifiers":[
        {
            "category":"Restaurant",
            "type":"Food & Drink"
        }
    ],
    "sg:phone":"+43 2746 8501",
    "sg:postcode":"3150",
    "sg:province":"Nieder\u00f6sterreich",
    "sg:tags":[
        "pizzeria"
    ],
    "wof:name":"Pizzeria Hausleitner",
    "wof:placetype":"venue"
},
  "geometry": {"coordinates":[15.6558494568,48.0672073364],"type":"Point"}
}