{
  "type": "Feature",
  "properties": {
    "iso:country":"AT",
    "sg:address":"S Schallhammer-Str 718",
    "sg:city":"Tamsweg",
    "sg:orig_category":"Elektroinstallationsunternehmen",
    "sg:phone":"+43 6474 6909",
    "sg:postcode":"5580",
    "sg:province":"Salzburg",
    "wof:name":"K\u00f6nig Matthias",
    "wof:placetype":"venue"
},
  "geometry": {"coordinates":[13.8101902008,47.1263389587],"type":"Point"}
}