{
  "type": "Feature",
  "properties": {
    "iso:country":"AT",
    "sg:address":"Landstra\u00dfer Hauptstr 130",
    "sg:city":"Wien",
    "sg:orig_category":"Bekleidung / Erzeugung U Gro\u00c3\u0178handel",
    "sg:phone":"+43 1 71361140",
    "sg:postcode":"1030",
    "sg:province":"Wien",
    "wof:name":"Mostbeck Mag & Co GesmbH",
    "wof:placetype":"venue"
},
  "geometry": {"coordinates":[16.3963775635,48.1955680847],"type":"Point"}
}