{
  "type": "Feature",
  "properties": {
    "addr:full":"Eisenstr 11 Kronstorf Ober\u00f6sterreich 4484",
    "addr:housenumber":"11",
    "addr:postcode":"4484",
    "addr:street":"Eisenstr",
    "iso:country":"AT",
    "sg:address":"Eisenstr 11",
    "sg:city":"Kronstorf",
    "sg:orig_category":"Volkshochschulen",
    "sg:phone":"+43 4372 2385963",
    "sg:postcode":"4484",
    "sg:province":"Ober\u00f6sterreich",
    "wof:name":"Volkshochschule Kronstorf",
    "wof:placetype":"venue"
},
  "geometry": {"coordinates":[14.4759216309,48.1721382141],"type":"Point"}
}