{
  "type": "Feature",
  "properties": {
    "iso:country":"AT",
    "sg:address":"Jesenfeldrain 1",
    "sg:city":"Warmbad",
    "sg:classifiers":[
        {
            "category":"Travel",
            "subcategory":"Hotels & Motels",
            "type":"Entertainment"
        }
    ],
    "sg:phone":"+43 4342 4234259",
    "sg:postcode":"9504",
    "sg:province":"K\u00e4rnten",
    "wof:name":"Hotel Villa Mena",
    "wof:placetype":"venue"
},
  "geometry": {"coordinates":[13.8296642303,46.5939559937],"type":"Point"}
}