{
  "type": "Feature",
  "properties": {
    "addr:full":"Steinackergasse 17 Wien Wien 1120",
    "addr:housenumber":"17",
    "addr:postcode":"1120",
    "addr:street":"Steinackergasse",
    "iso:country":"AT",
    "sg:address":"Steinackergasse 17",
    "sg:city":"Wien",
    "sg:classifiers":[
        {
            "category":"Autos & Motor Vehicles",
            "subcategory":"Auto Supplies",
            "type":"Retail Goods"
        }
    ],
    "sg:phone":"+43 1 8156868",
    "sg:postcode":"1120",
    "sg:province":"Wien",
    "sg:tags":[
        "equipment",
        "electrical",
        "rail",
        "electronic"
    ],
    "sg:website":"hagn.at",
    "wof:name":"HAGN - Technische Elastomere Ges.m.b.H.",
    "wof:placetype":"venue"
},
  "geometry": {"coordinates":[16.3371295929,48.17628479],"type":"Point"}
}