{
  "type": "Feature",
  "properties": {
    "iso:country":"AT",
    "sg:address":"Porzellang 14-16/3",
    "sg:city":"Wien",
    "sg:orig_category":"Architekten",
    "sg:phone":"+43 1 3102438",
    "sg:postcode":"1090",
    "sg:province":"Wien",
    "wof:name":"Peer Maria Dipl-Ing",
    "wof:placetype":"venue"
},
  "geometry": {"coordinates":[16.351474762,48.2234115601],"type":"Point"}
}