{
  "type": "Feature",
  "properties": {
    "addr:full":"Dreiheiligenstr 17 Innsbruck Tirol 6020",
    "addr:housenumber":"17",
    "addr:postcode":"6020",
    "addr:street":"Dreiheiligenstr;Tirol",
    "iso:country":"AT",
    "sg:address":"Dreiheiligenstr 17",
    "sg:city":"Innsbruck",
    "sg:classifiers":[
        {
            "category":"Taxi",
            "type":"Transportation"
        }
    ],
    "sg:phone":"+43 4351 2561717",
    "sg:postcode":"6020",
    "sg:province":"Tirol",
    "sg:tags":[
        "personentransporte",
        "u"
    ],
    "wof:name":"Taxi Dreiheiligen",
    "wof:placetype":"venue"
},
  "geometry": {"coordinates":[11.4041719437,47.2686653137],"type":"Point"}
}