{
  "type": "Feature",
  "properties": {
    "addr:full":"Schulstr 1 St. Martin im M\u00fchlkreis Ober\u00f6sterreich 4113",
    "addr:housenumber":"1",
    "addr:postcode":"4113",
    "addr:street":"Schulstr;Im Muehlkreis Oberoesterreich",
    "iso:country":"AT",
    "sg:address":"Schulstr 1",
    "sg:city":"St. Martin im M\u00fchlkreis",
    "sg:orig_category":"Banken U Sparkassen",
    "sg:phone":"+43 4372 3222860",
    "sg:postcode":"4113",
    "sg:province":"Ober\u00f6sterreich",
    "wof:name":"Sparkasse M\u00fchlviertel-West Bank AG",
    "wof:placetype":"venue"
},
  "geometry": {"coordinates":[14.0388736725,48.4141349792],"type":"Point"}
}