{
  "type": "Feature",
  "properties": {
    "addr:full":"Nr 95 Knittelfeld Steiermark 8720",
    "addr:postcode":"8720",
    "addr:street":"Nr",
    "iso:country":"AT",
    "sg:address":"Nr 95",
    "sg:city":"Knittelfeld",
    "sg:orig_category":"Musikgruppen",
    "sg:phone":"+43 4366 45211034",
    "sg:postcode":"8720",
    "sg:province":"Steiermark",
    "wof:name":"C\u00e4pt'n Klug & Die ZwergSteirer",
    "wof:placetype":"venue"
},
  "geometry": {"coordinates":[14.7973117828,47.2074241638],"type":"Point"}
}