{
  "type": "Feature",
  "properties": {
    "addr:full":"Cumberlandstr 5-7/5 Wien Wien 1140",
    "addr:housenumber":"5-7 / 5",
    "addr:postcode":"1140",
    "addr:street":"Cumberlandstr",
    "iso:country":"AT",
    "sg:address":"Cumberlandstr 5-7/5",
    "sg:city":"Wien",
    "sg:orig_category":"Ingenieurkonsulenten / Zivilingenieure",
    "sg:phone":"+43 1 8942266",
    "sg:postcode":"1140",
    "sg:province":"Wien",
    "wof:name":"Spatz Peter Dipl-Ing",
    "wof:placetype":"venue"
},
  "geometry": {"coordinates":[16.2696990967,48.1994247437],"type":"Point"}
}