{
  "type": "Feature",
  "properties": {
    "addr:full":"Wachtbergstr 78 Weyregg am Attersee Ober\u00f6sterreich 4852",
    "addr:housenumber":"78",
    "addr:postcode":"4852",
    "addr:street":"Wachtbergstr",
    "iso:country":"AT",
    "sg:address":"Wachtbergstr 78",
    "sg:city":"Weyregg am Attersee",
    "sg:orig_category":"Appartements / Ferienwohnungen",
    "sg:phone":"+43 76642634",
    "sg:postcode":"4852",
    "sg:province":"Ober\u00f6sterreich",
    "wof:name":"Wachtberghof",
    "wof:placetype":"venue"
},
  "geometry": {"coordinates":[13.5787305832,47.8968429565],"type":"Point"}
}