{
  "type": "Feature",
  "properties": {
    "addr:full":"Dorfstr 136 St. Anton am Arlberg Tirol 6580",
    "addr:housenumber":"136",
    "addr:postcode":"6580",
    "addr:street":"Dorfstr;Tirol",
    "iso:country":"AT",
    "sg:address":"Dorfstr 136",
    "sg:city":"St. Anton am Arlberg",
    "sg:orig_category":"Tankstellen",
    "sg:phone":"+43 4354 463466",
    "sg:postcode":"6580",
    "sg:province":"Tirol",
    "wof:name":"Shell Austria GmbH",
    "wof:placetype":"venue"
},
  "geometry": {"coordinates":[10.274225235,47.1344261169],"type":"Point"}
}