{
  "type": "Feature",
  "properties": {
    "iso:country":"AT",
    "sg:address":"Hub 56",
    "sg:city":"St. Veit",
    "sg:orig_category":"Filmproduktionen",
    "sg:phone":"+43 4331 6386514",
    "sg:postcode":"8046",
    "sg:province":"Steiermark",
    "wof:name":"Sunspot-Film Josef Krainer",
    "wof:placetype":"venue"
},
  "geometry": {"coordinates":[15.4189796448,47.1503410339],"type":"Point"}
}