{
  "type": "Feature",
  "properties": {
    "addr:full":"Kappelding 1 Eferding Ober\u00f6sterreich 4070",
    "addr:housenumber":"1",
    "addr:postcode":"4070",
    "addr:street":"Kappelding",
    "iso:country":"AT",
    "sg:address":"Kappelding 1",
    "sg:city":"Eferding",
    "sg:orig_category":"Abfallentsorgung U -Verwertung",
    "sg:phone":"+43 7272 76800",
    "sg:postcode":"4070",
    "sg:province":"Ober\u00f6sterreich",
    "wof:name":"EKT-Eferdinger Kl\u00e4rschlammtrocknung-GmbH",
    "wof:placetype":"venue"
},
  "geometry": {"coordinates":[13.9979496002,48.2844848633],"type":"Point"}
}