{
  "type": "Feature",
  "properties": {
    "addr:full":"Hietzinger Kai 191 Wien Wien 1130",
    "addr:housenumber":"191",
    "addr:postcode":"1130",
    "addr:street":"Hietzinger Kai",
    "iso:country":"AT",
    "sg:address":"Hietzinger Kai 191",
    "sg:city":"Wien",
    "sg:orig_category":"Unternehmensberatung",
    "sg:phone":"+43 1 8760587",
    "sg:postcode":"1130",
    "sg:province":"Wien",
    "wof:name":"Iro & Partners Beteiligungs GesmbH",
    "wof:placetype":"venue"
},
  "geometry": {"coordinates":[16.27085495,48.1925163269],"type":"Point"}
}