{
  "type": "Feature",
  "properties": {
    "addr:full":"Joseph-Haydn-Pl 3 Bad Tatzmannsdorf Burgenland 7431",
    "addr:housenumber":"3",
    "addr:postcode":"7431",
    "addr:street":"Joseph-Haydn-Pl",
    "iso:country":"AT",
    "sg:address":"Joseph-Haydn-Pl 3",
    "sg:city":"Bad Tatzmannsdorf",
    "sg:orig_category":"Juwelen, Gold- U Silberwaren / Einzelhandel",
    "sg:phone":"+43 4333 538950",
    "sg:postcode":"7431",
    "sg:province":"Burgenland",
    "wof:name":"Wagner Helmut",
    "wof:placetype":"venue"
},
  "geometry": {"coordinates":[16.2299766541,47.3324928284],"type":"Point"}
}