{
  "type": "Feature",
  "properties": {
    "addr:full":"Nr 202 Oberhofen im Inntal Tirol 6406",
    "addr:postcode":"6406",
    "addr:street":"Nr;Tirol",
    "iso:country":"AT",
    "sg:address":"Nr 202",
    "sg:city":"Oberhofen im Inntal",
    "sg:orig_category":"Gemeinden",
    "sg:phone":"+43 5262 627470",
    "sg:postcode":"6406",
    "sg:province":"Tirol",
    "wof:name":"Gemeindeamt Oberhofen im Inntal",
    "wof:placetype":"venue"
},
  "geometry": {"coordinates":[11.0959024429,47.3035469055],"type":"Point"}
}