{
  "type": "Feature",
  "properties": {
    "iso:country":"AT",
    "sg:address":"Glemmer Str 21",
    "sg:city":"Maishofen",
    "sg:orig_category":"Steuerberatung",
    "sg:phone":"+43 6542 807060",
    "sg:postcode":"5751",
    "sg:province":"Salzburg",
    "wof:name":"Haberl Walter",
    "wof:placetype":"venue"
},
  "geometry": {"coordinates":[12.7925434113,47.3627471924],"type":"Point"}
}