{
  "type": "Feature",
  "properties": {
    "addr:full":"Dr M Laireiter-Str 7 Salzburg Salzburg 5020",
    "addr:housenumber":"7",
    "addr:postcode":"5020",
    "addr:street":"Salzburg",
    "iso:country":"AT",
    "sg:address":"Dr M Laireiter-Str 7",
    "sg:city":"Salzburg",
    "sg:orig_category":"Pensionen / Privatzimmer",
    "sg:phone":"+43 662 850031",
    "sg:postcode":"5020",
    "sg:province":"Salzburg",
    "wof:name":"Pension Hutter Inh Fam Haas",
    "wof:placetype":"venue"
},
  "geometry": {"coordinates":[13.0332632065,47.774559021],"type":"Point"}
}