{
  "type": "Feature",
  "properties": {
    "iso:country":"AT",
    "sg:address":"Quaring 16",
    "sg:city":"Wien",
    "sg:orig_category":"Tabaktrafiken",
    "sg:phone":"+43 1 6038040",
    "sg:postcode":"1100",
    "sg:province":"Wien",
    "wof:name":"Glatzmayer Werner",
    "wof:placetype":"venue"
},
  "geometry": {"coordinates":[16.3542194366,48.1714782715],"type":"Point"}
}