{
  "type": "Feature",
  "properties": {
    "iso:country":"AT",
    "sg:address":"Zirkusg 36",
    "sg:city":"Wien",
    "sg:classifiers":[
        {
            "category":"Shopping",
            "subcategory":"Bicycles & Sporting Goods",
            "type":"Retail Goods"
        }
    ],
    "sg:phone":"+43 4312 181466",
    "sg:postcode":"1020",
    "sg:province":"Wien",
    "sg:tags":[
        "snowboard"
    ],
    "wof:name":"Fame Skate- u Snowboard Shop",
    "wof:placetype":"venue"
},
  "geometry": {"coordinates":[16.3849964142,48.2166481018],"type":"Point"}
}