{
  "type": "Feature",
  "properties": {
    "addr:full":"Ludersdorf 175 Gleisdorf Steiermark 8200",
    "addr:housenumber":"175",
    "addr:postcode":"8200",
    "addr:street":"Ludersdorf",
    "iso:country":"AT",
    "sg:address":"Ludersdorf 175",
    "sg:city":"Gleisdorf",
    "sg:classifiers":[
        {
            "category":"Shopping",
            "subcategory":"Computers & Home Electronics",
            "type":"Retail Goods"
        }
    ],
    "sg:phone":"+43 3112 55800",
    "sg:postcode":"8200",
    "sg:province":"Steiermark",
    "sg:tags":[
        "system",
        "automation"
    ],
    "sg:website":"bt-anlagenbau.com",
    "wof:name":"BT- ANLAGENBAU GmbH & Co KG AUTOMATISIERUNG - INDUSTRIEMONTAGE - LAGERTECHNIK",
    "wof:placetype":"venue"
},
  "geometry": {"coordinates":[15.7010641098,47.1006278992],"type":"Point"}
}