{
  "type": "Feature",
  "properties": {
    "iso:country":"AT",
    "sg:address":"Krugerstr 18",
    "sg:city":"Wien",
    "sg:orig_category":"Immobilienmakler",
    "sg:phone":"+43 1 5138254",
    "sg:postcode":"1010",
    "sg:province":"Wien",
    "wof:name":"Axmann Dr GmbH Dr",
    "wof:placetype":"venue"
},
  "geometry": {"coordinates":[16.3729362488,48.2033996582],"type":"Point"}
}