{
  "type": "Feature",
  "properties": {
    "addr:full":"Peter-Neuschmid-Str 1 Westendorf Tirol 6363",
    "addr:housenumber":"1",
    "addr:postcode":"6363",
    "addr:street":"Peter-Neuschmid-Str",
    "iso:country":"AT",
    "sg:address":"Peter-Neuschmid-Str 1",
    "sg:city":"Westendorf",
    "sg:classifiers":[
        {
            "category":"Travel",
            "subcategory":"Hotels & Motels",
            "type":"Entertainment"
        }
    ],
    "sg:phone":"+43 5334 62450",
    "sg:postcode":"6363",
    "sg:province":"Tirol",
    "wof:name":"Sporthotel Jakobwirt GesmbH",
    "wof:placetype":"venue"
},
  "geometry": {"coordinates":[12.213842392,47.4323692322],"type":"Point"}
}