{
  "type": "Feature",
  "properties": {
    "addr:full":"Schulpl 2 Podersdorf am See Burgenland 7141",
    "addr:housenumber":"2",
    "addr:postcode":"7141",
    "addr:street":"Schulpl",
    "iso:country":"AT",
    "sg:address":"Schulpl 2",
    "sg:city":"Podersdorf am See",
    "sg:orig_category":"\u00c3\u201erzte / F Allgemeinmedizin",
    "sg:phone":"+43 2177 2330",
    "sg:postcode":"7141",
    "sg:province":"Burgenland",
    "wof:name":"Ganser Georg Dr",
    "wof:placetype":"venue"
},
  "geometry": {"coordinates":[16.8362426758,47.8533401489],"type":"Point"}
}