{
  "type": "Feature",
  "properties": {
    "iso:country":"AT",
    "sg:city":"Polling im Innkreis",
    "sg:orig_category":"Feuerwehren",
    "sg:phone":"+43 7755 6569",
    "sg:postcode":"4951",
    "sg:province":"Ober\u00f6sterreich",
    "wof:name":"Freiwillige Feuerwehr Ornading",
    "wof:placetype":"venue"
},
  "geometry": {"coordinates":[13.3273563385,48.2213439941],"type":"Point"}
}