{
  "type": "Feature",
  "properties": {
    "addr:full":"Gschmeidlerstrasse 32 Hollabrunn Nieder\u00f6sterreich 2020",
    "addr:housenumber":"32",
    "addr:postcode":"2020",
    "addr:street":"Gschmeidlerstrasse",
    "iso:country":"AT",
    "sg:address":"Gschmeidlerstrasse 32",
    "sg:city":"Hollabrunn",
    "sg:orig_category":"Freizeit, Sonstige Freizeitangebote",
    "sg:phone":"+43 2952 3222",
    "sg:postcode":"2020",
    "sg:province":"Nieder\u00f6sterreich",
    "sg:website":"http://www.landgasthof-wolf.at",
    "wof:name":"Landgasthof Wolf",
    "wof:placetype":"venue"
},
  "geometry": {"coordinates":[16.0737533569,48.5652198792],"type":"Point"}
}