{
  "type": "Feature",
  "properties": {
    "addr:full":"Postgasse 2 Gm\u00fcnd Nieder\u00f6sterreich 3950",
    "addr:housenumber":"2",
    "addr:postcode":"3950",
    "addr:street":"Postgasse;Niederoesterreich",
    "iso:country":"AT",
    "sg:address":"Postgasse 2",
    "sg:city":"Gm\u00fcnd",
    "sg:classifiers":[
        {
            "category":"Farming",
            "subcategory":"Fish & Marine Products",
            "type":"Manufacturing & Wholesale Goods"
        }
    ],
    "sg:phone":"+43 2852 5010",
    "sg:postcode":"3950",
    "sg:province":"Nieder\u00f6sterreich",
    "sg:tags":[
        "asphalt"
    ],
    "sg:website":"leyrer-graf.at",
    "wof:name":"Leyrer + Graf Bauges.m.b.H.",
    "wof:placetype":"venue"
},
  "geometry": {"coordinates":[14.9738311768,48.7628707886],"type":"Point"}
}