{
  "type": "Feature",
  "properties": {
    "addr:full":"Wiener Bundesstr 25 Hallwang Salzburg 5300",
    "addr:housenumber":"25",
    "addr:postcode":"5300",
    "addr:street":"Salzburg",
    "iso:country":"AT",
    "sg:address":"Wiener Bundesstr 25",
    "sg:city":"Hallwang",
    "sg:orig_category":"Architekten",
    "sg:phone":"+43 662 661538",
    "sg:postcode":"5300",
    "sg:province":"Salzburg",
    "wof:name":"ARCHITEKTURB\u00dcRO FREI-RAUM Sieberer ZT GmbH",
    "wof:placetype":"venue"
},
  "geometry": {"coordinates":[13.0868749619,47.8337593079],"type":"Point"}
}