{
  "type": "Feature",
  "properties": {
    "addr:full":"P\u00f6rtschacher Str 23 Moosburg K\u00e4rnten 9062",
    "addr:postcode":"9062",
    "addr:street":"Str 23;Kaernten",
    "iso:country":"AT",
    "sg:address":"P\u00f6rtschacher Str 23",
    "sg:city":"Moosburg",
    "sg:classifiers":[
        {
            "category":"Restaurant",
            "type":"Food & Drink"
        }
    ],
    "sg:phone":"+43 4272 2505",
    "sg:postcode":"9062",
    "sg:province":"K\u00e4rnten",
    "wof:name":"Dollenz G\u00fcnter - M\u00f6belrestaurator",
    "wof:placetype":"venue"
},
  "geometry": {"coordinates":[14.173746109,46.6578292847],"type":"Point"}
}