{
  "type": "Feature",
  "properties": {
    "iso:country":"AT",
    "sg:address":"12.-Februar-Str 57",
    "sg:city":"St. Michael in Obersteiermark",
    "sg:orig_category":"Versicherungsunternehmen",
    "sg:phone":"+43 4338 432420",
    "sg:postcode":"8770",
    "sg:province":"Steiermark",
    "wof:name":"Grazer Wechselseitige Versicherung AG",
    "wof:placetype":"venue"
},
  "geometry": {"coordinates":[15.010008812,47.3518981934],"type":"Point"}
}