{
  "type": "Feature",
  "properties": {
    "iso:country":"AT",
    "sg:address":"Passauer Pl 7",
    "sg:city":"Wien",
    "sg:orig_category":"Werbeagenturen",
    "sg:phone":"+43 1 5325540",
    "sg:postcode":"1010",
    "sg:province":"Wien",
    "wof:name":"WIENCOM Werbeberatungs GmbH",
    "wof:placetype":"venue"
},
  "geometry": {"coordinates":[16.3704662323,48.2131156921],"type":"Point"}
}