{
  "type": "Feature",
  "properties": {
    "addr:full":"Schachterlweg 58 Klagenfurt K\u00e4rnten 9020",
    "addr:housenumber":"58",
    "addr:postcode":"9020",
    "addr:street":"Schachterlweg;Kaernten",
    "iso:country":"AT",
    "sg:address":"Schachterlweg 58",
    "sg:city":"Klagenfurt",
    "sg:orig_category":"Glasereien",
    "sg:phone":"+43 4346 336843",
    "sg:postcode":"9020",
    "sg:province":"K\u00e4rnten",
    "wof:name":"Glaserei Kogler KEG",
    "wof:placetype":"venue"
},
  "geometry": {"coordinates":[14.3394317627,46.630443573],"type":"Point"}
}