{
  "type": "Feature",
  "properties": {
    "iso:country":"AT",
    "sg:address":"Hauptpl 21",
    "sg:city":"Linz",
    "sg:classifiers":[
        {
            "category":"Arts & Performance",
            "subcategory":"Theater",
            "type":"Entertainment"
        }
    ],
    "sg:phone":"+43 732 784120",
    "sg:postcode":"4020",
    "sg:province":"Ober\u00f6sterreich",
    "wof:name":"Linzer Kellertheater",
    "wof:placetype":"venue"
},
  "geometry": {"coordinates":[14.2863407135,48.3050422668],"type":"Point"}
}