{
  "type": "Feature",
  "properties": {
    "addr:full":"Zollernspergg 8 Wien Wien 1150",
    "addr:housenumber":"8",
    "addr:postcode":"1150",
    "addr:street":"Zollernspergg",
    "iso:country":"AT",
    "sg:address":"Zollernspergg 8",
    "sg:city":"Wien",
    "sg:orig_category":"Installationsunternehmen",
    "sg:phone":"+43 1 4945655",
    "sg:postcode":"1150",
    "sg:province":"Wien",
    "wof:name":"DELPHIN Vlajic Installations KEG",
    "wof:placetype":"venue"
},
  "geometry": {"coordinates":[16.3228797913,48.1914253235],"type":"Point"}
}