{
  "type": "Feature",
  "properties": {
    "addr:full":"Karmeliterg 21 Innsbruck Tirol 6020",
    "addr:housenumber":"21",
    "addr:postcode":"6020",
    "addr:street":"Karmeliterg;Tirol",
    "iso:country":"AT",
    "sg:address":"Karmeliterg 21",
    "sg:city":"Innsbruck",
    "sg:orig_category":"Autospenglereien",
    "sg:phone":"+43 512 571551",
    "sg:postcode":"6020",
    "sg:province":"Tirol",
    "wof:name":"Plangger Otto",
    "wof:placetype":"venue"
},
  "geometry": {"coordinates":[11.4002685547,47.2577705383],"type":"Point"}
}