{
  "type": "Feature",
  "properties": {
    "addr:full":"Alpenblick 4 Altenberg Ober\u00f6sterreich 4203",
    "addr:housenumber":"4",
    "addr:postcode":"4203",
    "addr:street":"Alpenblick",
    "iso:country":"AT",
    "sg:address":"Alpenblick 4",
    "sg:city":"Altenberg",
    "sg:orig_category":"Psychotherapie",
    "sg:phone":"+43 7230 8580",
    "sg:postcode":"4203",
    "sg:province":"Ober\u00f6sterreich",
    "wof:name":"Grossmann Konrad Peter Dr phil",
    "wof:placetype":"venue"
},
  "geometry": {"coordinates":[14.34395504,48.3546409607],"type":"Point"}
}