{
  "type": "Feature",
  "properties": {
    "iso:country":"AT",
    "sg:address":"Georg-Reitinger-Str 7",
    "sg:city":"Wels",
    "sg:orig_category":"Werbeagenturen",
    "sg:phone":"+43 4372 42411510",
    "sg:postcode":"4600",
    "sg:province":"Ober\u00f6sterreich",
    "wof:name":"Entenfellner & Partner Marketing- u Werbeagentur GmbH",
    "wof:placetype":"venue"
},
  "geometry": {"coordinates":[14.0276060104,48.1488723755],"type":"Point"}
}