{
  "type": "Feature",
  "properties": {
    "iso:country":"AT",
    "sg:address":"Kelsenstr 7",
    "sg:city":"Wien",
    "sg:orig_category":"Immobilienverwaltungen",
    "sg:phone":"+43 1 79507",
    "sg:postcode":"1030",
    "sg:province":"Wien",
    "wof:name":"Frapag Medienhaus AG",
    "wof:placetype":"venue"
},
  "geometry": {"coordinates":[16.3935279846,48.1864700317],"type":"Point"}
}