{
  "type": "Feature",
  "properties": {
    "iso:country":"AT",
    "sg:address":"Hauptstr 12",
    "sg:city":"Launsdorf",
    "sg:orig_category":"Banken U Sparkassen",
    "sg:phone":"+43 4342 1320680",
    "sg:postcode":"9314",
    "sg:province":"K\u00e4rnten",
    "wof:name":"Raiffeisenbank Launsdorf regGenmbH",
    "wof:placetype":"venue"
},
  "geometry": {"coordinates":[14.4558286667,46.7682304382],"type":"Point"}
}