{
  "type": "Feature",
  "properties": {
    "addr:full":"Pfarrg 8 Hollabrunn Nieder\u00f6sterreich 2020",
    "addr:housenumber":"8",
    "addr:postcode":"2020",
    "addr:street":"Pfarrg",
    "iso:country":"AT",
    "sg:address":"Pfarrg 8",
    "sg:city":"Hollabrunn",
    "sg:orig_category":"Reifen U Reifendienste",
    "sg:phone":"+43 2952 3225",
    "sg:postcode":"2020",
    "sg:province":"Nieder\u00f6sterreich",
    "wof:name":"Bartsch Thomas",
    "wof:placetype":"venue"
},
  "geometry": {"coordinates":[16.0786933899,48.5613975525],"type":"Point"}
}