{
  "type": "Feature",
  "properties": {
    "addr:full":"Nr 6 Sillian Tirol 9920",
    "addr:postcode":"9920",
    "addr:street":"Nr;Sillian Tirol",
    "iso:country":"AT",
    "sg:address":"Nr 6",
    "sg:city":"Sillian",
    "sg:classifiers":[
        {
            "category":"Travel",
            "subcategory":"Hotels & Motels",
            "type":"Entertainment"
        }
    ],
    "sg:phone":"+43 4846 63540",
    "sg:postcode":"9920",
    "sg:province":"Tirol",
    "wof:name":"Hotel Strasserwirt",
    "wof:placetype":"venue"
},
  "geometry": {"coordinates":[12.4398870468,46.7495117188],"type":"Point"}
}