{
  "type": "Feature",
  "properties": {
    "iso:country":"AT",
    "sg:address":"Grabenstr 8",
    "sg:city":"Graz",
    "sg:orig_category":"Telekommunikation",
    "sg:phone":"+43 316 60800",
    "sg:postcode":"8010",
    "sg:province":"Steiermark",
    "wof:name":"IT Symbiose Sprache-Daten-Bild-Kommunikations GmbH",
    "wof:placetype":"venue"
},
  "geometry": {"coordinates":[15.439034462,47.0797042847],"type":"Point"}
}