{
  "type": "Feature",
  "properties": {
    "iso:country":"AT",
    "sg:address":"Holzleitenweg 2",
    "sg:city":"W\u00fcrmla",
    "sg:orig_category":"Feuerwehren",
    "sg:phone":"+43 2275 8261",
    "sg:postcode":"3042",
    "sg:province":"Nieder\u00f6sterreich",
    "wof:name":"Freiwillige Feuerwehr",
    "wof:placetype":"venue"
},
  "geometry": {"coordinates":[15.8607988358,48.2573394775],"type":"Point"}
}