{
  "type": "Feature",
  "properties": {
    "addr:full":"Wies Steiermark 8551",
    "addr:postcode":"8551",
    "iso:country":"AT",
    "sg:city":"Wies",
    "sg:classifiers":[
        {
            "category":"Arts & Performance",
            "subcategory":"Theater",
            "type":"Entertainment"
        }
    ],
    "sg:phone":"+43 3465 3535",
    "sg:postcode":"8551",
    "sg:province":"Steiermark",
    "wof:name":"Theater im K\u00fcrbis",
    "wof:placetype":"venue"
},
  "geometry": {"coordinates":[15.239865303,46.7347831726],"type":"Point"}
}