{
  "type": "Feature",
  "properties": {
    "addr:full":"Hauptstr 100 Horitschon Burgenland 7312",
    "addr:housenumber":"100",
    "addr:postcode":"7312",
    "addr:street":"Hauptstr",
    "iso:country":"AT",
    "sg:address":"Hauptstr 100",
    "sg:city":"Horitschon",
    "sg:orig_category":"Installationsunternehmen",
    "sg:phone":"+43 2610 422460",
    "sg:postcode":"7312",
    "sg:province":"Burgenland",
    "wof:name":"Wallner GmbH",
    "wof:placetype":"venue"
},
  "geometry": {"coordinates":[16.5386161804,47.5914802551],"type":"Point"}
}