{
  "type": "Feature",
  "properties": {
    "addr:full":"Statzenbachg 17a Neumarkt am Wallersee Salzburg 5202",
    "addr:housenumber":"17a",
    "addr:postcode":"5202",
    "addr:street":"Statzenbachg;Salzburg",
    "iso:country":"AT",
    "sg:address":"Statzenbachg 17a",
    "sg:city":"Neumarkt am Wallersee",
    "sg:orig_category":"Genossenschaften",
    "sg:phone":"+43 4362 164428",
    "sg:postcode":"5202",
    "sg:province":"Salzburg",
    "wof:name":"Wassergenossenschaft Neumarkt am Wallersee",
    "wof:placetype":"venue"
},
  "geometry": {"coordinates":[13.2270202637,47.9423370361],"type":"Point"}
}