{
  "type": "Feature",
  "properties": {
    "addr:full":"Wimh\u00f6lzelstr 1 Linz Ober\u00f6sterreich 4020",
    "addr:housenumber":"1",
    "addr:postcode":"4020",
    "addr:street":"Wimhoelzelstr",
    "iso:country":"AT",
    "sg:address":"Wimh\u00f6lzelstr 1",
    "sg:city":"Linz",
    "sg:orig_category":"Videotheken",
    "sg:phone":"+43 732 604081",
    "sg:postcode":"4020",
    "sg:province":"Ober\u00f6sterreich",
    "wof:name":"Video Plus",
    "wof:placetype":"venue"
},
  "geometry": {"coordinates":[14.3114881516,48.2945365906],"type":"Point"}
}