{
  "type": "Feature",
  "properties": {
    "addr:full":"Schaunbergstr 20 Hartkirchen Ober\u00f6sterreich 4081",
    "addr:housenumber":"20",
    "addr:postcode":"4081",
    "addr:street":"Schaunbergstr",
    "iso:country":"AT",
    "sg:address":"Schaunbergstr 20",
    "sg:city":"Hartkirchen",
    "sg:orig_category":"Tankstellen",
    "sg:phone":"+43 7273 6177",
    "sg:postcode":"4081",
    "sg:province":"Ober\u00f6sterreich",
    "wof:name":"AVANTI TankstellenbetriebsgesmbH",
    "wof:placetype":"venue"
},
  "geometry": {"coordinates":[13.9948987961,48.3593406677],"type":"Point"}
}