{
  "type": "Feature",
  "properties": {
    "addr:full":"Reitberg 109 Eugendorf Salzburg 5301",
    "addr:housenumber":"109",
    "addr:postcode":"5301",
    "addr:street":"Reitberg;Salzburg",
    "iso:country":"AT",
    "sg:address":"Reitberg 109",
    "sg:city":"Eugendorf",
    "sg:orig_category":"Raumausstattung",
    "sg:phone":"+43 664 3041414",
    "sg:postcode":"5301",
    "sg:province":"Salzburg",
    "wof:name":"Hatzl Arnold",
    "wof:placetype":"venue"
},
  "geometry": {"coordinates":[13.1482000351,47.8604393005],"type":"Point"}
}