{
  "type": "Feature",
  "properties": {
    "iso:country":"AT",
    "sg:address":"Eben 1",
    "sg:city":"Greifenburg",
    "sg:classifiers":[
        {
            "category":"Manufacturing",
            "subcategory":"Wood Products",
            "type":"Manufacturing & Wholesale Goods"
        }
    ],
    "sg:phone":"+43 4712 298",
    "sg:postcode":"9761",
    "sg:province":"K\u00e4rnten",
    "sg:tags":[
        "firewood"
    ],
    "wof:name":"Kanzian Holz GesmbH",
    "wof:placetype":"venue"
},
  "geometry": {"coordinates":[13.178850174,46.7319869995],"type":"Point"}
}