{
  "type": "Feature",
  "properties": {
    "addr:full":"Glorietteg 29 Wien Wien 1130",
    "addr:housenumber":"29",
    "addr:postcode":"1130",
    "addr:street":"Glorietteg",
    "iso:country":"AT",
    "sg:address":"Glorietteg 29",
    "sg:city":"Wien",
    "sg:classifiers":[
        {
            "category":"Internet Cafe",
            "subcategory":"None",
            "type":"Food & Drink"
        }
    ],
    "sg:phone":"+43 1 6062070",
    "sg:postcode":"1130",
    "sg:province":"Wien",
    "wof:name":"IPO Board.Net AG",
    "wof:placetype":"venue"
},
  "geometry": {"coordinates":[16.2939033508,48.181728363],"type":"Point"}
}