{
  "type": "Feature",
  "properties": {
    "iso:country":"AT",
    "sg:address":"Durisolstr 2",
    "sg:city":"Wels",
    "sg:orig_category":"Logistik",
    "sg:phone":"+43 7242 210686",
    "sg:postcode":"4600",
    "sg:province":"Ober\u00f6sterreich",
    "wof:name":"ADL Abfalldisposition und Logistik GesmbH",
    "wof:placetype":"venue"
},
  "geometry": {"coordinates":[14.0085926056,48.1510124207],"type":"Point"}
}