{
  "type": "Feature",
  "properties": {
    "addr:full":"Eichenweg 232 Wals Salzburg 5071",
    "addr:housenumber":"232",
    "addr:postcode":"5071",
    "addr:street":"Eichenweg;Salzburg",
    "iso:country":"AT",
    "sg:address":"Eichenweg 232",
    "sg:city":"Wals",
    "sg:orig_category":"Baumeister",
    "sg:phone":"+43 699 10060500",
    "sg:postcode":"5071",
    "sg:province":"Salzburg",
    "wof:name":"Schaber Christian Ing",
    "wof:placetype":"venue"
},
  "geometry": {"coordinates":[12.9931211472,47.7722206116],"type":"Point"}
}