{
  "type": "Feature",
  "properties": {
    "addr:full":"Gewerbestrasse 16 Kapfenberg Steiermark 8605",
    "addr:housenumber":"16",
    "addr:postcode":"8605",
    "addr:street":"Gewerbestrasse",
    "iso:country":"AT",
    "sg:address":"Gewerbestrasse 16",
    "sg:city":"Kapfenberg",
    "sg:classifiers":[
        {
            "category":"Shopping",
            "subcategory":"Computers & Home Electronics",
            "type":"Retail Goods"
        }
    ],
    "sg:phone":"+43 3862 323640",
    "sg:postcode":"8605",
    "sg:province":"Steiermark",
    "sg:tags":[
        "system",
        "automation"
    ],
    "wof:name":"EHS Steuerungstechnik Ges.m.b.H.",
    "wof:placetype":"venue"
},
  "geometry": {"coordinates":[15.3396511078,47.4677200317],"type":"Point"}
}