{
  "type": "Feature",
  "properties": {
    "addr:full":"Erzherzog-Rainer-Ring 14  Baden Nieder\u00f6sterreich 2500",
    "addr:housenumber":"14",
    "addr:postcode":"2500",
    "addr:street":"Erzherzog-Rainer-Ring;Niederoesterreich",
    "iso:country":"AT",
    "sg:address":"Erzherzog-Rainer-Ring 14 ",
    "sg:city":"Baden",
    "sg:classifiers":[
        {
            "category":"Professional",
            "subcategory":"Business Services",
            "type":"Services"
        }
    ],
    "sg:phone":"+43 2252 48674",
    "sg:postcode":"2500",
    "sg:province":"Nieder\u00f6sterreich",
    "sg:tags":[
        "chilled",
        "transport",
        "refrigerated"
    ],
    "wof:name":"Manfred Hochst\u00f6ger Transport-Ges.m.b.H.",
    "wof:placetype":"venue"
},
  "geometry": {"coordinates":[16.2319717407,48.0082588196],"type":"Point"}
}