{
  "type": "Feature",
  "properties": {
    "iso:country":"AT",
    "sg:address":"Nr 3",
    "sg:city":"Schottwien",
    "sg:orig_category":"Immobilienmakler",
    "sg:phone":"+43 4326 6320066",
    "sg:postcode":"2641",
    "sg:province":"Nieder\u00f6sterreich",
    "wof:name":"Dibl & Partnerimmobilien beh.konz. Immobilien u Bautr\u00e4gerb\u00fcro Inh Roswitha Dibl-Fischer",
    "wof:placetype":"venue"
},
  "geometry": {"coordinates":[15.8718976974,47.6552085876],"type":"Point"}
}