{
  "type": "Feature",
  "properties": {
    "addr:full":"Hotterweg 19 Eisenstadt Burgenland 7000",
    "addr:housenumber":"19",
    "addr:postcode":"7000",
    "addr:street":"Hotterweg",
    "iso:country":"AT",
    "sg:address":"Hotterweg 19",
    "sg:city":"Eisenstadt",
    "sg:orig_category":"Bauunternehmen",
    "sg:phone":"+43 2682 64292",
    "sg:postcode":"7000",
    "sg:province":"Burgenland",
    "wof:name":"Schaller BaugesmbH",
    "wof:placetype":"venue"
},
  "geometry": {"coordinates":[16.521692276,47.8373031616],"type":"Point"}
}