{
  "type": "Feature",
  "properties": {
    "addr:full":"Mattseer Landesstr 1a Elixhausen Salzburg 5161",
    "addr:housenumber":"1a",
    "addr:postcode":"5161",
    "addr:street":"Salzburg",
    "iso:country":"AT",
    "sg:address":"Mattseer Landesstr 1a",
    "sg:city":"Elixhausen",
    "sg:orig_category":"Arbeitsschutz U Arbeitsschutzartikel",
    "sg:phone":"+43 662 4808110",
    "sg:postcode":"5161",
    "sg:province":"Salzburg",
    "wof:name":"Staffl Johann Mag",
    "wof:placetype":"venue"
},
  "geometry": {"coordinates":[13.0601949692,47.8613700867],"type":"Point"}
}