{
  "type": "Feature",
  "properties": {
    "addr:full":"Dorf 8 Hartkirchen Ober\u00f6sterreich 4081",
    "addr:housenumber":"8",
    "addr:postcode":"4081",
    "addr:street":"Dorf",
    "iso:country":"AT",
    "sg:address":"Dorf 8",
    "sg:city":"Hartkirchen",
    "sg:orig_category":"Bergbahnen",
    "sg:phone":"+43 7273 8207",
    "sg:postcode":"4081",
    "sg:province":"Ober\u00f6sterreich",
    "wof:name":"Schilift Brandtner Dorf",
    "wof:placetype":"venue"
},
  "geometry": {"coordinates":[14.003080368,48.3623580933],"type":"Point"}
}