{
  "type": "Feature",
  "properties": {
    "iso:country":"AT",
    "sg:address":"Weinitzenstr 32",
    "sg:city":"Andritz",
    "sg:orig_category":"Zimmereien",
    "sg:phone":"+43 316 6925120",
    "sg:postcode":"8045",
    "sg:province":"Steiermark",
    "wof:name":"Prix Karl",
    "wof:placetype":"venue"
},
  "geometry": {"coordinates":[15.4285650253,47.1162338257],"type":"Point"}
}