{
  "type": "Feature",
  "properties": {
    "iso:country":"AT",
    "sg:address":"Siedlungsstr 10",
    "sg:city":"Haiming",
    "sg:orig_category":"Geschenkartikel",
    "sg:phone":"+43 5266 88797",
    "sg:postcode":"6425",
    "sg:province":"Tirol",
    "wof:name":"Roswithas Geschenkideen",
    "wof:placetype":"venue"
},
  "geometry": {"coordinates":[10.8802490234,47.2554473877],"type":"Point"}
}