{
  "type": "Feature",
  "properties": {
    "addr:full":"Georgipl 11 Wildenau Ober\u00f6sterreich 4933",
    "addr:housenumber":"11",
    "addr:postcode":"4933",
    "addr:street":"Georgipl",
    "iso:country":"AT",
    "sg:address":"Georgipl 11",
    "sg:city":"Wildenau",
    "sg:orig_category":"Fleischhauereien",
    "sg:phone":"+43 7755 5206",
    "sg:postcode":"4933",
    "sg:province":"Ober\u00f6sterreich",
    "wof:name":"Hateier Herbert",
    "wof:placetype":"venue"
},
  "geometry": {"coordinates":[13.3190546036,48.1998977661],"type":"Point"}
}