{
  "type": "Feature",
  "properties": {
    "addr:full":"Levasseurg 15 Wien Wien 1230",
    "addr:housenumber":"15",
    "addr:postcode":"1230",
    "addr:street":"Levasseurg",
    "iso:country":"AT",
    "sg:address":"Levasseurg 15",
    "sg:city":"Wien",
    "sg:orig_category":"Blumeneinzelhandel",
    "sg:phone":"+43 1 8659719",
    "sg:postcode":"1230",
    "sg:province":"Wien",
    "sg:website":"blumen-christl.at",
    "wof:name":"Blumen Christl",
    "wof:placetype":"venue"
},
  "geometry": {"coordinates":[16.29504776,48.1468544006],"type":"Point"}
}