{
  "type": "Feature",
  "properties": {
    "addr:full":"W\u00e4hringer Str 79 Wien Wien 1180",
    "addr:postcode":"1180",
    "addr:street":"Str 79",
    "iso:country":"AT",
    "sg:address":"W\u00e4hringer Str 79",
    "sg:city":"Wien",
    "sg:orig_category":"Bilderrahmen",
    "sg:phone":"+43 1 4061392",
    "sg:postcode":"1180",
    "sg:province":"Wien",
    "wof:name":"Art Haus OTTO HANDEL OEG",
    "wof:placetype":"venue"
},
  "geometry": {"coordinates":[16.3475322723,48.2252731323],"type":"Point"}
}