{
  "type": "Feature",
  "properties": {
    "iso:country":"AT",
    "sg:address":"Litschauer Str 8",
    "sg:city":"Eggern",
    "sg:orig_category":"Volksschulen",
    "sg:phone":"+43 2863 298",
    "sg:postcode":"3861",
    "sg:province":"Nieder\u00f6sterreich",
    "wof:name":"Volksschule",
    "wof:placetype":"venue"
},
  "geometry": {"coordinates":[15.1458206177,48.9084472656],"type":"Point"}
}