{
  "type": "Feature",
  "properties": {
    "addr:full":"Hornsteiner Str 3 Steinbrunn Burgenland 7035",
    "addr:housenumber":"3",
    "addr:postcode":"7035",
    "addr:street":"Str",
    "iso:country":"AT",
    "sg:address":"Hornsteiner Str 3",
    "sg:city":"Steinbrunn",
    "sg:classifiers":[
        {
            "category":"Internet Cafe",
            "subcategory":"None",
            "type":"Food & Drink"
        }
    ],
    "sg:phone":"+43 2688 72400",
    "sg:postcode":"7035",
    "sg:province":"Burgenland",
    "wof:name":"POINT 2 Zethofer - Mezgolits OEG",
    "wof:placetype":"venue"
},
  "geometry": {"coordinates":[16.4165802002,47.8371315002],"type":"Point"}
}