{
  "type": "Feature",
  "properties": {
    "addr:full":"Favoritenstr. 111  Wien Wien 1100",
    "addr:housenumber":"111",
    "addr:postcode":"1100",
    "iso:country":"AT",
    "sg:address":"Favoritenstr. 111 ",
    "sg:city":"Wien",
    "sg:classifiers":[
        {
            "category":"Shopping",
            "subcategory":"Clothing, Apparel, & Fashions",
            "type":"Retail Goods"
        }
    ],
    "sg:phone":"+43 4316 041525",
    "sg:postcode":"1100",
    "sg:province":"Wien",
    "sg:tags":[
        "clothes"
    ],
    "wof:name":"WILHELM KLOUCEK KG",
    "wof:placetype":"venue"
},
  "geometry": {"coordinates":[16.3778591156,48.1755599976],"type":"Point"}
}