{
  "type": "Feature",
  "properties": {
    "addr:full":"Marktpl 8 Seibersdorf Nieder\u00f6sterreich 2444",
    "addr:housenumber":"8",
    "addr:postcode":"2444",
    "addr:street":"Marktpl",
    "iso:country":"AT",
    "sg:address":"Marktpl 8",
    "sg:city":"Seibersdorf",
    "sg:orig_category":"Lebensmittel / Erzeugung U Gro\u00c3\u0178handel",
    "sg:phone":"+43 4322 556422",
    "sg:postcode":"2444",
    "sg:province":"Nieder\u00f6sterreich",
    "wof:name":"Fr\u00f6hlich Alois",
    "wof:placetype":"venue"
},
  "geometry": {"coordinates":[16.5188465118,47.9576225281],"type":"Point"}
}