{
  "type": "Feature",
  "properties": {
    "addr:full":"Parkring 4 Wien Wien 1010",
    "addr:housenumber":"4",
    "addr:postcode":"1010",
    "addr:street":"Parkring",
    "iso:country":"AT",
    "sg:address":"Parkring 4",
    "sg:city":"Wien",
    "sg:orig_category":"Architekten",
    "sg:phone":"+43 1 2147307",
    "sg:postcode":"1010",
    "sg:province":"Wien",
    "wof:name":"Schwanzer Martin Arch Dipl-Ing",
    "wof:placetype":"venue"
},
  "geometry": {"coordinates":[16.3796863556,48.2067642212],"type":"Point"}
}