{
  "type": "Feature",
  "properties": {
    "addr:full":"Hauptstr 41 Eisenstadt Burgenland 7000",
    "addr:housenumber":"41",
    "addr:postcode":"7000",
    "addr:street":"Hauptstr",
    "iso:country":"AT",
    "sg:address":"Hauptstr 41",
    "sg:city":"Eisenstadt",
    "sg:orig_category":"Immobilienmakler",
    "sg:phone":"+43 2682 663620",
    "sg:postcode":"7000",
    "sg:province":"Burgenland",
    "wof:name":"Real 2000 ImmobilienbeteiligungsgesmbH",
    "wof:placetype":"venue"
},
  "geometry": {"coordinates":[16.5250015259,47.8468856812],"type":"Point"}
}