{
  "type": "Feature",
  "properties": {
    "addr:full":"Seestr 44 Breitenbrunn Burgenland 7091",
    "addr:housenumber":"44",
    "addr:postcode":"7091",
    "addr:street":"Seestr",
    "iso:country":"AT",
    "sg:address":"Seestr 44",
    "sg:city":"Breitenbrunn",
    "sg:orig_category":"Appartements / Ferienwohnungen",
    "sg:phone":"+43 2683 5225",
    "sg:postcode":"7091",
    "sg:province":"Burgenland",
    "wof:name":"Ferienwohnungen Christine",
    "wof:placetype":"venue"
},
  "geometry": {"coordinates":[16.7357120514,47.9424285889],"type":"Point"}
}