{
  "type": "Feature",
  "properties": {
    "iso:country":"AT",
    "sg:address":"Hirschstettner Str 34a",
    "sg:city":"Wien",
    "sg:orig_category":"Lebensmittel / Einzelhandel",
    "sg:phone":"+43 4312 035688",
    "sg:postcode":"1220",
    "sg:province":"Wien",
    "wof:name":"Hofer KG",
    "wof:placetype":"venue"
},
  "geometry": {"coordinates":[16.4571990967,48.2424736023],"type":"Point"}
}