{
  "type": "Feature",
  "properties": {
    "iso:country":"AT",
    "sg:address":"Porscheallee 77",
    "sg:city":"Zell am See",
    "sg:orig_category":"Restaurants: Mexikanisch",
    "sg:phone":"+43 6542 57357",
    "sg:postcode":"5700",
    "sg:province":"Salzburg",
    "wof:name":"Hazienda Santa Fe",
    "wof:placetype":"venue"
},
  "geometry": {"coordinates":[12.800909996,47.2992324829],"type":"Point"}
}