{
  "type": "Feature",
  "properties": {
    "addr:full":"Kr\u00f6pfelsteigstr 12 Hinterbr\u00fchl Nieder\u00f6sterreich 2371",
    "addr:housenumber":"12",
    "addr:postcode":"2371",
    "addr:street":"Kroepfelsteigstr;Niederoesterreich",
    "iso:country":"AT",
    "sg:address":"Kr\u00f6pfelsteigstr 12",
    "sg:city":"Hinterbr\u00fchl",
    "sg:orig_category":"Massagen",
    "sg:phone":"+43 4322 3686867",
    "sg:postcode":"2371",
    "sg:province":"Nieder\u00f6sterreich",
    "wof:name":"MASSAGEPRAXIS HEALTH & RELAX",
    "wof:placetype":"venue"
},
  "geometry": {"coordinates":[16.2391166687,48.0854187012],"type":"Point"}
}