{
  "type": "Feature",
  "properties": {
    "addr:full":"Nr 4 Immendorf Nieder\u00f6sterreich 2022",
    "addr:postcode":"2022",
    "addr:street":"Nr;Immendorf",
    "iso:country":"AT",
    "sg:address":"Nr 4",
    "sg:city":"Immendorf",
    "sg:orig_category":"Spielautomaten",
    "sg:phone":"+43 2953 27362",
    "sg:postcode":"2022",
    "sg:province":"Nieder\u00f6sterreich",
    "wof:name":"FUNGAMES Automaten Vertriebs GmbH",
    "wof:placetype":"venue"
},
  "geometry": {"coordinates":[16.1282634735,48.6451911926],"type":"Point"}
}