{
  "type": "Feature",
  "properties": {
    "iso:country":"AT",
    "sg:address":"Kristein 33",
    "sg:city":"Enns",
    "sg:orig_category":"Gastronomie- U Hotelbedarf",
    "sg:phone":"+43 4372 238155599",
    "sg:postcode":"4470",
    "sg:province":"Ober\u00f6sterreich",
    "wof:name":"VEGA VertriebsgmbH & Co KG",
    "wof:placetype":"venue"
},
  "geometry": {"coordinates":[14.4428033829,48.2127494812],"type":"Point"}
}