{
  "type": "Feature",
  "properties": {
    "addr:full":"Herrenstr 14 Mank Nieder\u00f6sterreich 3240",
    "addr:housenumber":"14",
    "addr:postcode":"3240",
    "addr:street":"Herrenstr;Niederoesterreich",
    "iso:country":"AT",
    "sg:address":"Herrenstr 14",
    "sg:city":"Mank",
    "sg:orig_category":"Maler, Anstreicher U Lackierer",
    "sg:phone":"+43 4327 552489",
    "sg:postcode":"3240",
    "sg:province":"Nieder\u00f6sterreich",
    "wof:name":"Bodner Alois",
    "wof:placetype":"venue"
},
  "geometry": {"coordinates":[15.3393468857,48.112487793],"type":"Point"}
}