{
  "type": "Feature",
  "properties": {
    "iso:country":"AT",
    "sg:address":"Nr 62",
    "sg:city":"Gro\u00dfsteinbach",
    "sg:orig_category":"Gemeinden",
    "sg:phone":"+43 4333 8682080",
    "sg:postcode":"8265",
    "sg:province":"Steiermark",
    "wof:name":"Gemeindeamt Gro\u00dfsteinbach",
    "wof:placetype":"venue"
},
  "geometry": {"coordinates":[13.1806230545,51.1235580444],"type":"Point"}
}