{
  "type": "Feature",
  "properties": {
    "addr:full":"Schottenfeldg 2-4 Wien Wien 1070",
    "addr:housenumber":"2-4",
    "addr:postcode":"1070",
    "addr:street":"Schottenfeldg",
    "iso:country":"AT",
    "sg:address":"Schottenfeldg 2-4",
    "sg:city":"Wien",
    "sg:orig_category":"Partyservice",
    "sg:phone":"+43 1 52697960",
    "sg:postcode":"1070",
    "sg:province":"Wien",
    "wof:name":"Vrana Klaus Imbi\u00df & Partyservice",
    "wof:placetype":"venue"
},
  "geometry": {"coordinates":[16.3443450928,48.1970024109],"type":"Point"}
}