{
  "type": "Feature",
  "properties": {
    "addr:full":"Alois-Reisinger-Str 6 Perchtoldsdorf Nieder\u00f6sterreich 2380",
    "addr:housenumber":"6",
    "addr:postcode":"2380",
    "addr:street":"Alois-Reisinger-Str",
    "iso:country":"AT",
    "sg:address":"Alois-Reisinger-Str 6",
    "sg:city":"Perchtoldsdorf",
    "sg:orig_category":"Massagen",
    "sg:phone":"+43 1 8654000",
    "sg:postcode":"2380",
    "sg:province":"Nieder\u00f6sterreich",
    "wof:name":"Holzapfel Johann",
    "wof:placetype":"venue"
},
  "geometry": {"coordinates":[16.2555446625,48.1150283813],"type":"Point"}
}