{
  "type": "Feature",
  "properties": {
    "iso:country":"AT",
    "sg:address":"Grafenweg 16",
    "sg:city":"Hard",
    "sg:orig_category":"Architekten",
    "sg:phone":"+43 5574 86567",
    "sg:postcode":"6971",
    "sg:province":"Vorarlberg",
    "wof:name":"Krischke Eckehard Arch Dipl-Ing",
    "wof:placetype":"venue"
},
  "geometry": {"coordinates":[9.6745319366,47.4733963013],"type":"Point"}
}