{
  "type": "Feature",
  "properties": {
    "iso:country":"AT",
    "sg:address":"Nr 138",
    "sg:city":"Fiss",
    "sg:orig_category":"Pensionen / Privatzimmer",
    "sg:phone":"+43 5476 6517",
    "sg:postcode":"6533",
    "sg:province":"Tirol",
    "wof:name":"Hammerle Willi",
    "wof:placetype":"venue"
},
  "geometry": {"coordinates":[10.618268013,47.0554733276],"type":"Point"}
}