{
  "type": "Feature",
  "properties": {
    "addr:full":"Schmiedviertel 80 M\u00f6nichwald Steiermark 8252",
    "addr:housenumber":"80",
    "addr:postcode":"8252",
    "addr:street":"Schmiedviertel",
    "iso:country":"AT",
    "sg:address":"Schmiedviertel 80",
    "sg:city":"M\u00f6nichwald",
    "sg:orig_category":"Pensionen / Privatzimmer",
    "sg:phone":"+43 4333 364533",
    "sg:postcode":"8252",
    "sg:province":"Steiermark",
    "wof:name":"Wiedner Patriz",
    "wof:placetype":"venue"
},
  "geometry": {"coordinates":[15.865322113,47.4500846863],"type":"Point"}
}