{
  "type": "Feature",
  "properties": {
    "iso:country":"AT",
    "sg:address":"Braunauer Str 5",
    "sg:city":"Altheim",
    "sg:orig_category":"Rettungsdienste",
    "sg:phone":"+43 7723 43366",
    "sg:postcode":"4950",
    "sg:province":"Ober\u00f6sterreich",
    "wof:name":"Rotes Kreuz \u00d6sterr Ortsstelle Altheim",
    "wof:placetype":"venue"
},
  "geometry": {"coordinates":[13.2288417816,48.2488174438],"type":"Point"}
}