{
  "type": "Feature",
  "properties": {
    "iso:country":"AT",
    "sg:address":"Salzburger Str 60-62",
    "sg:city":"Hall in Tirol",
    "sg:orig_category":"Autohandel",
    "sg:phone":"+43 4352 2358110",
    "sg:postcode":"6060",
    "sg:province":"Tirol",
    "wof:name":"Bacher Auto GmbH & Co KG",
    "wof:placetype":"venue"
},
  "geometry": {"coordinates":[11.5258216858,47.2799301147],"type":"Point"}
}