{
  "type": "Feature",
  "properties": {
    "iso:country":"AT",
    "sg:address":"Nr 135",
    "sg:city":"Antiesenhofen",
    "sg:orig_category":"Psychologen",
    "sg:phone":"+43 7759 5166",
    "sg:postcode":"4980",
    "sg:province":"Ober\u00f6sterreich",
    "wof:name":"Girzikovsky Andreas MMag",
    "wof:placetype":"venue"
},
  "geometry": {"coordinates":[13.4010677338,48.346862793],"type":"Point"}
}