{
  "type": "Feature",
  "properties": {
    "addr:full":"Wiener Str 64 Gloggnitz Nieder\u00f6sterreich 2640",
    "addr:postcode":"2640",
    "addr:street":"Niederoesterreich",
    "iso:country":"AT",
    "sg:address":"Wiener Str 64",
    "sg:city":"Gloggnitz",
    "sg:orig_category":"Tischlereien",
    "sg:phone":"+43 2662 42497",
    "sg:postcode":"2640",
    "sg:province":"Nieder\u00f6sterreich",
    "wof:name":"Hartberger Leopold",
    "wof:placetype":"venue"
},
  "geometry": {"coordinates":[15.9514703751,47.6724662781],"type":"Point"}
}