{
  "type": "Feature",
  "properties": {
    "addr:full":"Anton-Baumgartner-Str 131/1Stock Wien Wien 1230",
    "addr:housenumber":"131 / 1stock",
    "addr:postcode":"1230",
    "iso:country":"AT",
    "sg:address":"Anton-Baumgartner-Str 131/1Stock",
    "sg:city":"Wien",
    "sg:orig_category":"Juweliere, Gold- U Silberschmiede",
    "sg:phone":"+43 4319 823142",
    "sg:postcode":"1230",
    "sg:province":"Wien",
    "wof:name":"H\u00f6fner Peter",
    "wof:placetype":"venue"
},
  "geometry": {"coordinates":[16.3103942871,48.1490783691],"type":"Point"}
}