{
  "type": "Feature",
  "properties": {
    "addr:full":"Nr 52 Kaindorf Steiermark 8224",
    "addr:postcode":"8224",
    "addr:street":"Nr",
    "iso:country":"AT",
    "sg:address":"Nr 52",
    "sg:city":"Kaindorf",
    "sg:orig_category":"Volksschulen",
    "sg:phone":"+43 4333 342248",
    "sg:postcode":"8224",
    "sg:province":"Steiermark",
    "wof:name":"Volksschule",
    "wof:placetype":"venue"
},
  "geometry": {"coordinates":[15.9089851379,47.2246704102],"type":"Point"}
}