{
  "type": "Feature",
  "properties": {
    "addr:full":"Spiegelg 21/2/11 Wien Wien 1010",
    "addr:housenumber":"21 / 2 / 11",
    "addr:postcode":"1010",
    "addr:street":"Spiegelg",
    "iso:country":"AT",
    "sg:address":"Spiegelg 21/2/11",
    "sg:city":"Wien",
    "sg:orig_category":"Steuerberatung",
    "sg:phone":"+43 4315 124803",
    "sg:postcode":"1010",
    "sg:province":"Wien",
    "wof:name":"Folterbauer Hannes",
    "wof:placetype":"venue"
},
  "geometry": {"coordinates":[16.3688049316,48.2025489807],"type":"Point"}
}