{
  "type": "Feature",
  "properties": {
    "addr:full":"Im Bradafos 16 Frastanz Vorarlberg 6820",
    "addr:housenumber":"16",
    "addr:postcode":"6820",
    "addr:street":"Im Bradafos",
    "iso:country":"AT",
    "sg:address":"Im Bradafos 16",
    "sg:city":"Frastanz",
    "sg:orig_category":"Tischlereien",
    "sg:phone":"+43 4355 2252418",
    "sg:postcode":"6820",
    "sg:province":"Vorarlberg",
    "wof:name":"Tomaselli Michael",
    "wof:placetype":"venue"
},
  "geometry": {"coordinates":[9.6225996017,47.2247390747],"type":"Point"}
}