{
  "type": "Feature",
  "properties": {
    "addr:full":"Percostr 22 Wien Wien 1220",
    "addr:housenumber":"22",
    "addr:postcode":"1220",
    "addr:street":"Percostr",
    "iso:country":"AT",
    "sg:address":"Percostr 22",
    "sg:city":"Wien",
    "sg:orig_category":"Garten- U Landschaftsgestaltung",
    "sg:phone":"+43 4312 574233",
    "sg:postcode":"1220",
    "sg:province":"Wien",
    "sg:website":"sbg-spurny.at",
    "wof:name":"SBG Spurny GmbH",
    "wof:placetype":"venue"
},
  "geometry": {"coordinates":[16.4651088715,48.2689094543],"type":"Point"}
}