{
  "type": "Feature",
  "properties": {
    "addr:full":"Nr 23 Deutsch Griffen K\u00e4rnten 9572",
    "addr:postcode":"9572",
    "addr:street":"Nr",
    "iso:country":"AT",
    "sg:address":"Nr 23",
    "sg:city":"Deutsch Griffen",
    "sg:orig_category":"Gemeinden",
    "sg:phone":"+43 4279 7600",
    "sg:postcode":"9572",
    "sg:province":"K\u00e4rnten",
    "wof:name":"Gemeinde Deutsch Griffen",
    "wof:placetype":"venue"
},
  "geometry": {"coordinates":[14.0751237869,46.8549766541],"type":"Point"}
}