{
  "type": "Feature",
  "properties": {
    "iso:country":"AT",
    "sg:address":"Innerbergstr 4",
    "sg:city":"Schruns",
    "sg:orig_category":"Pensionen / Privatzimmer",
    "sg:phone":"+43 5556 73355",
    "sg:postcode":"6780",
    "sg:province":"Vorarlberg",
    "wof:name":"Haus Brigitte",
    "wof:placetype":"venue"
},
  "geometry": {"coordinates":[-91.3424530029,38.6716003418],"type":"Point"}
}