{
  "type": "Feature",
  "properties": {
    "iso:country":"AT",
    "sg:address":"Stolbergg 27/3",
    "sg:city":"Wien",
    "sg:orig_category":"Physiotherapie",
    "sg:phone":"+43 1 5451930",
    "sg:postcode":"1050",
    "sg:province":"Wien",
    "wof:name":"Steinmetz Vera",
    "wof:placetype":"venue"
},
  "geometry": {"coordinates":[16.3600463867,48.1858787537],"type":"Point"}
}