{
  "type": "Feature",
  "properties": {
    "addr:full":"Maculang 1 Wien Wien 1220",
    "addr:housenumber":"1",
    "addr:postcode":"1220",
    "addr:street":"Maculang",
    "iso:country":"AT",
    "sg:address":"Maculang 1",
    "sg:city":"Wien",
    "sg:orig_category":"Orientteppiche",
    "sg:phone":"+43 4312 591919",
    "sg:postcode":"1220",
    "sg:province":"Wien",
    "wof:name":"TRATEX Orientteppiche",
    "wof:placetype":"venue"
},
  "geometry": {"coordinates":[16.4540710449,48.2624855042],"type":"Point"}
}