{
  "type": "Feature",
  "properties": {
    "iso:country":"AT",
    "sg:address":"Lugendorf 7",
    "sg:city":"Tragwein",
    "sg:orig_category":"Appartements / Ferienwohnungen",
    "sg:phone":"+43 7263 88295",
    "sg:postcode":"4284",
    "sg:province":"Ober\u00f6sterreich",
    "wof:name":"Ferienhof Pankrazhofer Fam Eder",
    "wof:placetype":"venue"
},
  "geometry": {"coordinates":[14.6283369064,48.3530731201],"type":"Point"}
}