{
  "type": "Feature",
  "properties": {
    "addr:full":"Alpenstr 119 Salzburg Salzburg 5020",
    "addr:housenumber":"119",
    "addr:postcode":"5020",
    "addr:street":"Salzburg",
    "iso:country":"AT",
    "sg:address":"Alpenstr 119",
    "sg:city":"Salzburg",
    "sg:orig_category":"Immobilienmakler",
    "sg:phone":"+43 662 8802040",
    "sg:postcode":"5020",
    "sg:province":"Salzburg",
    "wof:name":"Bliem & Rauscher Immobilien GmbH",
    "wof:placetype":"venue"
},
  "geometry": {"coordinates":[13.0688991547,47.7738380432],"type":"Point"}
}