{
  "type": "Feature",
  "properties": {
    "addr:full":"Westbahnstr 33 Wien Wien 1070",
    "addr:housenumber":"33",
    "addr:postcode":"1070",
    "addr:street":"Westbahnstr",
    "iso:country":"AT",
    "sg:address":"Westbahnstr 33",
    "sg:city":"Wien",
    "sg:orig_category":"Immobilienmakler",
    "sg:phone":"+43 1 5262636",
    "sg:postcode":"1070",
    "sg:province":"Wien",
    "sg:website":"lind-immobilien.at",
    "wof:name":"LIND Immobilien KEG",
    "wof:placetype":"venue"
},
  "geometry": {"coordinates":[16.3413238525,48.2017021179],"type":"Point"}
}