{
  "type": "Feature",
  "properties": {
    "addr:full":"Nr 19 Brand Nieder\u00f6sterreich 3873",
    "addr:postcode":"3873",
    "addr:street":"Nr;Brand Niederoesterreich",
    "iso:country":"AT",
    "sg:address":"Nr 19",
    "sg:city":"Brand",
    "sg:orig_category":"Reinigungsbedarf U Reinigungsmittel",
    "sg:phone":"+43 2862 52095",
    "sg:postcode":"3873",
    "sg:province":"Nieder\u00f6sterreich",
    "wof:name":"Flicker Melitta -ENJO Reinigungsberaterin",
    "wof:placetype":"venue"
},
  "geometry": {"coordinates":[15.0122241974,48.8652191162],"type":"Point"}
}