{
  "type": "Feature",
  "properties": {
    "addr:full":"Fasanstrasse 25 Henndorf am Wallersee Salzburg 5302",
    "addr:housenumber":"25",
    "addr:postcode":"5302",
    "addr:street":"Fasanstrasse",
    "iso:country":"AT",
    "sg:address":"Fasanstrasse 25",
    "sg:city":"Henndorf am Wallersee",
    "sg:classifiers":[
        {
            "category":"Building & Trades",
            "subcategory":"Landscaping Services",
            "type":"Services"
        }
    ],
    "sg:phone":"+43 6214 8391",
    "sg:postcode":"5302",
    "sg:province":"Salzburg",
    "sg:tags":[
        "restoration",
        "old"
    ],
    "sg:website":"st-wohnbau.com",
    "wof:name":"ST-Wohnbau GmbH",
    "wof:placetype":"venue"
},
  "geometry": {"coordinates":[13.1951255798,47.8970756531],"type":"Point"}
}