{
  "type": "Feature",
  "properties": {
    "addr:full":"Nr 185 Rohrbach an der Lafnitz Steiermark 8234",
    "addr:postcode":"8234",
    "addr:street":"Nr",
    "iso:country":"AT",
    "sg:address":"Nr 185",
    "sg:city":"Rohrbach an der Lafnitz",
    "sg:orig_category":"Blumeneinzelhandel",
    "sg:phone":"+43 4333 383362",
    "sg:postcode":"8234",
    "sg:province":"Steiermark",
    "wof:name":"Blumen Christa",
    "wof:placetype":"venue"
},
  "geometry": {"coordinates":[15.9732465744,47.3812446594],"type":"Point"}
}