{
  "type": "Feature",
  "properties": {
    "iso:country":"AT",
    "sg:address":"Hofsteigstr 136",
    "sg:city":"Hard",
    "sg:orig_category":"Unterhaltungselektronik / Reparatur",
    "sg:phone":"+43 4355 7483990",
    "sg:postcode":"6971",
    "sg:province":"Vorarlberg",
    "wof:name":"Media Service",
    "wof:placetype":"venue"
},
  "geometry": {"coordinates":[9.7092161179,47.486907959],"type":"Point"}
}