{
  "type": "Feature",
  "properties": {
    "addr:full":"Bergstr 21 St. Stefan im Rosental Steiermark 8083",
    "addr:housenumber":"21",
    "addr:postcode":"8083",
    "addr:street":"Bergstr",
    "iso:country":"AT",
    "sg:address":"Bergstr 21",
    "sg:city":"St. Stefan im Rosental",
    "sg:orig_category":"Autoreparatur",
    "sg:phone":"+43 4331 1681291",
    "sg:postcode":"8083",
    "sg:province":"Steiermark",
    "wof:name":"Absenger Erwin",
    "wof:placetype":"venue"
},
  "geometry": {"coordinates":[15.7077274323,46.9003372192],"type":"Point"}
}