{
  "type": "Feature",
  "properties": {
    "addr:full":"Plan\u00f6tzenhofstr 24C Innsbruck Tirol 6020",
    "addr:housenumber":"24c",
    "addr:postcode":"6020",
    "addr:street":"Planoetzenhofstr;Tirol",
    "iso:country":"AT",
    "sg:address":"Plan\u00f6tzenhofstr 24C",
    "sg:city":"Innsbruck",
    "sg:orig_category":"Maler, Anstreicher U Lackierer",
    "sg:phone":"+43 4351 2346113",
    "sg:postcode":"6020",
    "sg:province":"Tirol",
    "wof:name":"Avi Marco",
    "wof:placetype":"venue"
},
  "geometry": {"coordinates":[11.3722391129,47.2733459473],"type":"Point"}
}