{
  "type": "Feature",
  "properties": {
    "iso:country":"AT",
    "sg:address":"Plan\u00f6tzenhofstr 24C",
    "sg:city":"Innsbruck",
    "sg:orig_category":"Maler, Anstreicher U Lackierer",
    "sg:phone":"+43 4351 2346113",
    "sg:postcode":"6020",
    "sg:province":"Tirol",
    "wof:name":"Avi Marco",
    "wof:placetype":"venue"
},
  "geometry": {"coordinates":[11.3722391129,47.2733459473],"type":"Point"}
}