{
  "type": "Feature",
  "properties": {
    "iso:country":"AT",
    "sg:address":"Maurer Lange G 64",
    "sg:city":"Wien",
    "sg:orig_category":"Offsetdruckereien",
    "sg:phone":"+43 1 8882673",
    "sg:postcode":"1230",
    "sg:province":"Wien",
    "wof:name":"Novographic Druck GmbH",
    "wof:placetype":"venue"
},
  "geometry": {"coordinates":[16.2674388885,48.14793396],"type":"Point"}
}