{
  "type": "Feature",
  "properties": {
    "addr:full":"Burgg 34 Petronell Nieder\u00f6sterreich 2404",
    "addr:housenumber":"34",
    "addr:postcode":"2404",
    "addr:street":"Burgg;Niederoesterreich",
    "iso:country":"AT",
    "sg:address":"Burgg 34",
    "sg:city":"Petronell",
    "sg:orig_category":"Baumeister",
    "sg:phone":"+43 2163 2988",
    "sg:postcode":"2404",
    "sg:province":"Nieder\u00f6sterreich",
    "wof:name":"Peiritsch Gerhard Ing",
    "wof:placetype":"venue"
},
  "geometry": {"coordinates":[16.8695030212,48.1120758057],"type":"Point"}
}