{
  "type": "Feature",
  "properties": {
    "iso:country":"AT",
    "sg:address":"Nr 4",
    "sg:city":"Maurach",
    "sg:orig_category":"Non-Classified Establishments",
    "sg:phone":"+43 5243 5227",
    "sg:postcode":"6212",
    "sg:province":"Tirol",
    "wof:name":"Pfarramt St Notburga",
    "wof:placetype":"venue"
},
  "geometry": {"coordinates":[11.7518672943,47.4225006104],"type":"Point"}
}