{
  "type": "Feature",
  "properties": {
    "addr:full":"Hosnedlg 11 Wien Wien 1220",
    "addr:housenumber":"11",
    "addr:postcode":"1220",
    "addr:street":"Hosnedlg",
    "iso:country":"AT",
    "sg:address":"Hosnedlg 11",
    "sg:city":"Wien",
    "sg:orig_category":"Galvanisieranstalten",
    "sg:phone":"+43 1 25975390",
    "sg:postcode":"1220",
    "sg:province":"Wien",
    "wof:name":"Stiefler GesmbH",
    "wof:placetype":"venue"
},
  "geometry": {"coordinates":[16.4621276855,48.2558059692],"type":"Point"}
}