{
  "type": "Feature",
  "properties": {
    "addr:full":"Mayg 41/I Graz Steiermark 8010",
    "addr:housenumber":"41 / i",
    "addr:postcode":"8010",
    "addr:street":"Mayg",
    "iso:country":"AT",
    "sg:address":"Mayg 41/I",
    "sg:city":"Graz",
    "sg:orig_category":"Sprachschulen U -Unterricht",
    "sg:phone":"+43 4331 6820253",
    "sg:postcode":"8010",
    "sg:province":"Steiermark",
    "sg:website":"schulungszentrum-graz.at",
    "wof:name":"SZG Schulungszentrum Graz",
    "wof:placetype":"venue"
},
  "geometry": {"coordinates":[15.4431800842,47.0685653687],"type":"Point"}
}