{
  "type": "Feature",
  "properties": {
    "addr:full":"Hauptpl 11 G\u00fcssing Burgenland 7540",
    "addr:housenumber":"11",
    "addr:postcode":"7540",
    "addr:street":"Hauptpl",
    "iso:country":"AT",
    "sg:address":"Hauptpl 11",
    "sg:city":"G\u00fcssing",
    "sg:orig_category":"Bankomat-Standorte",
    "sg:phone":"+43 3322 42271",
    "sg:postcode":"7540",
    "sg:province":"Burgenland",
    "wof:name":"Bankomat d PSK G\u00fcssing",
    "wof:placetype":"venue"
},
  "geometry": {"coordinates":[16.3229007721,47.059627533],"type":"Point"}
}