{
  "type": "Feature",
  "properties": {
    "iso:country":"AT",
    "sg:address":"Marktpl 30",
    "sg:city":"Kremsm\u00fcnster",
    "sg:orig_category":"Biologische Produkte",
    "sg:phone":"+43 4375 835228",
    "sg:postcode":"4550",
    "sg:province":"Ober\u00f6sterreich",
    "wof:name":"Milch & Most-Laden Fritz S\u00f6llradl",
    "wof:placetype":"venue"
},
  "geometry": {"coordinates":[14.1314268112,48.0532913208],"type":"Point"}
}