{
  "type": "Feature",
  "properties": {
    "addr:full":"Singerstr 30 Wien Wien 1010",
    "addr:housenumber":"30",
    "addr:postcode":"1010",
    "addr:street":"Singerstr",
    "iso:country":"AT",
    "sg:address":"Singerstr 30",
    "sg:city":"Wien",
    "sg:orig_category":"Altwaren",
    "sg:phone":"+43 1 5128892",
    "sg:postcode":"1010",
    "sg:province":"Wien",
    "wof:name":"Antik und Feind - Ingrid Hinterecker",
    "wof:placetype":"venue"
},
  "geometry": {"coordinates":[16.3763618469,48.2061157227],"type":"Point"}
}