{
  "type": "Feature",
  "properties": {
    "addr:full":"Nr 17-18 Waidhofen an der Thaya Nieder\u00f6sterreich 3830",
    "addr:postcode":"3830",
    "addr:street":"Nr 17-18;Niederoesterreich",
    "iso:country":"AT",
    "sg:address":"Nr 17-18",
    "sg:city":"Waidhofen an der Thaya",
    "sg:orig_category":"Tischlereien",
    "sg:phone":"+43 2842 53948",
    "sg:postcode":"3830",
    "sg:province":"Nieder\u00f6sterreich",
    "wof:name":"Vogler Erich",
    "wof:placetype":"venue"
},
  "geometry": {"coordinates":[166.9221496582,-0.5282999873],"type":"Point"}
}