{
  "type": "Feature",
  "properties": {
    "addr:full":"Amonstr 5 Lunz am See Nieder\u00f6sterreich 3293",
    "addr:housenumber":"5",
    "addr:postcode":"3293",
    "addr:street":"Amonstr;Niederoesterreich",
    "iso:country":"AT",
    "sg:address":"Amonstr 5",
    "sg:city":"Lunz am See",
    "sg:classifiers":[
        {
            "category":"Restaurant",
            "type":"Food & Drink"
        }
    ],
    "sg:phone":"+43 7486 8347",
    "sg:postcode":"3293",
    "sg:province":"Nieder\u00f6sterreich",
    "wof:name":"Amonst\u00fcberl",
    "wof:placetype":"venue"
},
  "geometry": {"coordinates":[15.0251541138,47.8609275818],"type":"Point"}
}