{
  "type": "Feature",
  "properties": {
    "addr:full":"Platzl 2 Salzburg Salzburg 5020",
    "addr:housenumber":"2",
    "addr:postcode":"5020",
    "addr:street":"Platzl;Salzburg",
    "iso:country":"AT",
    "sg:address":"Platzl 2",
    "sg:city":"Salzburg",
    "sg:orig_category":"Friseure U Frisiersalons",
    "sg:phone":"+43 4366 2881848",
    "sg:postcode":"5020",
    "sg:province":"Salzburg",
    "wof:name":"Hairline Modefriseur",
    "wof:placetype":"venue"
},
  "geometry": {"coordinates":[13.045091629,47.8017845154],"type":"Point"}
}