{
  "type": "Feature",
  "properties": {
    "iso:country":"AT",
    "sg:address":"Fohrenburgstrasse 4",
    "sg:city":"Bludenz",
    "sg:classifiers":[
        {
            "category":"Food & Beverages",
            "subcategory":"Chocolate",
            "type":"Retail Goods"
        }
    ],
    "sg:phone":"+43 5552 6090",
    "sg:postcode":"6700",
    "sg:province":"Vorarlberg",
    "sg:website":"suchard.at",
    "wof:name":"Kraft Suchard Schokolade GmbH",
    "wof:placetype":"venue"
},
  "geometry": {"coordinates":[9.8161411285,47.1555862427],"type":"Point"}
}