{
  "type": "Feature",
  "properties": {
    "addr:full":"Elisabethstr 13 Wien Wien 1010",
    "addr:housenumber":"13",
    "addr:postcode":"1010",
    "addr:street":"Elisabethstr",
    "iso:country":"AT",
    "sg:address":"Elisabethstr 13",
    "sg:city":"Wien",
    "sg:orig_category":"Restaurants: Italienisch",
    "sg:phone":"+43 4315 871958",
    "sg:postcode":"1010",
    "sg:province":"Wien",
    "wof:name":"Ristorante Pizzeria La Scala",
    "wof:placetype":"venue"
},
  "geometry": {"coordinates":[16.3640213013,48.2026672363],"type":"Point"}
}