{
  "type": "Feature",
  "properties": {
    "iso:country":"AT",
    "sg:address":"Florianig 3",
    "sg:city":"Wei\u00dfkirchen an der Traun",
    "sg:orig_category":"Feuerwehren",
    "sg:phone":"+43 7243 567000",
    "sg:postcode":"4616",
    "sg:province":"Ober\u00f6sterreich",
    "wof:name":"Freiwillige Feuerwehr Wei\u00dfkirchen/Traun",
    "wof:placetype":"venue"
},
  "geometry": {"coordinates":[14.1215801239,48.162273407],"type":"Point"}
}