{
  "type": "Feature",
  "properties": {
    "addr:full":"Minnesheimstr 20 Gnigl Salzburg 5023",
    "addr:housenumber":"20",
    "addr:postcode":"5023",
    "addr:street":"Minnesheimstr",
    "iso:country":"AT",
    "sg:address":"Minnesheimstr 20",
    "sg:city":"Gnigl",
    "sg:orig_category":"Non-Classified Establishments",
    "sg:phone":"+43 662 63835731",
    "sg:postcode":"5023",
    "sg:province":"Salzburg",
    "wof:name":"Polizei Gnigl",
    "wof:placetype":"venue"
},
  "geometry": {"coordinates":[13.0701122284,47.813117981],"type":"Point"}
}