{
  "type": "Feature",
  "properties": {
    "addr:full":"Schlo\u00dfbergweg 18 Landskron K\u00e4rnten 9523",
    "addr:housenumber":"18",
    "addr:postcode":"9523",
    "addr:street":"Schlossbergweg;Kaernten",
    "iso:country":"AT",
    "sg:address":"Schlo\u00dfbergweg 18",
    "sg:city":"Landskron",
    "sg:orig_category":"Tierparks",
    "sg:phone":"+43 664 4118540",
    "sg:postcode":"9523",
    "sg:province":"K\u00e4rnten",
    "wof:name":"Affenberg",
    "wof:placetype":"venue"
},
  "geometry": {"coordinates":[13.8834161758,46.6343688965],"type":"Point"}
}