{
  "type": "Feature",
  "properties": {
    "addr:full":"Mitterlaabstrasse 28 Wels Ober\u00f6sterreich 4600",
    "addr:housenumber":"28",
    "addr:postcode":"4600",
    "addr:street":"Mitterlaabstrasse;Oberoesterreich",
    "iso:country":"AT",
    "sg:address":"Mitterlaabstrasse 28",
    "sg:city":"Wels",
    "sg:classifiers":[
        {
            "category":"Manufacturing",
            "subcategory":"Furniture",
            "type":"Manufacturing & Wholesale Goods"
        }
    ],
    "sg:phone":"+43 7242 77743",
    "sg:postcode":"4600",
    "sg:province":"Ober\u00f6sterreich",
    "sg:tags":[
        "bedroom"
    ],
    "wof:name":"Josef Hager",
    "wof:placetype":"venue"
},
  "geometry": {"coordinates":[14.0455818176,48.2001991272],"type":"Point"}
}