{
  "type": "Feature",
  "properties": {
    "addr:full":"Dr W Hochsteiner-Str 4 Villach K\u00e4rnten 9500",
    "addr:housenumber":"4",
    "addr:postcode":"9500",
    "addr:street":"Dr W Hochsteiner-Str;Kaernten",
    "iso:country":"AT",
    "sg:address":"Dr W Hochsteiner-Str 4",
    "sg:city":"Villach",
    "sg:orig_category":"Sanatorien",
    "sg:phone":"+43 4242 30440",
    "sg:postcode":"9500",
    "sg:province":"K\u00e4rnten",
    "wof:name":"Privatklinik Villach GesmbH & Co KG",
    "wof:placetype":"venue"
},
  "geometry": {"coordinates":[13.8323163986,46.6105422974],"type":"Point"}
}