{
  "type": "Feature",
  "properties": {
    "addr:full":"Leopoldauer Pl 81 Wien Wien 1210",
    "addr:housenumber":"81",
    "addr:postcode":"1210",
    "addr:street":"Leopoldauer Pl",
    "iso:country":"AT",
    "sg:address":"Leopoldauer Pl 81",
    "sg:city":"Wien",
    "sg:orig_category":"Friseure U Frisiersalons",
    "sg:phone":"+43 1 2592573",
    "sg:postcode":"1210",
    "sg:province":"Wien",
    "wof:name":"Gruber Manfred",
    "wof:placetype":"venue"
},
  "geometry": {"coordinates":[16.4389667511,48.2629127502],"type":"Point"}
}