{
  "type": "Feature",
  "properties": {
    "iso:country":"AT",
    "sg:address":"Leobner Str. 93",
    "sg:city":"Bruck an der Mur",
    "sg:classifiers":[
        {
            "category":"Manufacturing",
            "subcategory":"Metals",
            "type":"Manufacturing & Wholesale Goods"
        }
    ],
    "sg:phone":"+43 4338 6251522",
    "sg:postcode":"8600",
    "sg:province":"Steiermark",
    "sg:tags":[
        "metallurgy",
        "metalworking"
    ],
    "wof:name":"ING ARNULF KRAKER",
    "wof:placetype":"venue"
},
  "geometry": {"coordinates":[15.2438983917,47.4012718201],"type":"Point"}
}