{
  "type": "Feature",
  "properties": {
    "iso:country":"AT",
    "sg:address":"Ratschkyg 15",
    "sg:city":"Wien",
    "sg:orig_category":"Fleischhauereien",
    "sg:phone":"+43 1 8177088",
    "sg:postcode":"1120",
    "sg:province":"Wien",
    "wof:name":"Rajic V. & J. GmbH",
    "wof:placetype":"venue"
},
  "geometry": {"coordinates":[16.3274345398,48.1770515442],"type":"Point"}
}