{
  "type": "Feature",
  "properties": {
    "addr:full":"Unterlandshaag 14 Feldkirchen an der Donau Ober\u00f6sterreich 4101",
    "addr:housenumber":"14",
    "addr:postcode":"4101",
    "addr:street":"Unterlandshaag",
    "iso:country":"AT",
    "sg:address":"Unterlandshaag 14",
    "sg:city":"Feldkirchen an der Donau",
    "sg:orig_category":"Werbeagenturen",
    "sg:phone":"+43 4372 336489",
    "sg:postcode":"4101",
    "sg:province":"Ober\u00f6sterreich",
    "wof:name":"Charismat - agentur & mehr",
    "wof:placetype":"venue"
},
  "geometry": {"coordinates":[14.0302028656,48.359249115],"type":"Point"}
}