{
  "type": "Feature",
  "properties": {
    "addr:full":"Peter-Singer-G 8 Salzburg Salzburg 5020",
    "addr:housenumber":"8",
    "addr:postcode":"5020",
    "addr:street":"Peter-Singer-G;Salzburg",
    "iso:country":"AT",
    "sg:address":"Peter-Singer-G 8",
    "sg:city":"Salzburg",
    "sg:orig_category":"Tierschutz",
    "sg:phone":"+43 662 843255",
    "sg:postcode":"5020",
    "sg:province":"Salzburg",
    "wof:name":"\u00f6sterreichischer Tierschutzverein",
    "wof:placetype":"venue"
},
  "geometry": {"coordinates":[13.0492801666,47.7887916565],"type":"Point"}
}