{
  "type": "Feature",
  "properties": {
    "iso:country":"AT",
    "sg:city":"P\u00f6llau",
    "sg:orig_category":"Fotografen",
    "sg:phone":"+43 664 2534515",
    "sg:postcode":"8225",
    "sg:province":"Steiermark",
    "wof:name":"Wiesenhofer Hans",
    "wof:placetype":"venue"
},
  "geometry": {"coordinates":[15.8241653442,47.2948150635],"type":"Point"}
}