{
  "type": "Feature",
  "properties": {
    "addr:full":"Wieserfeldpl 2 Steyr Ober\u00f6sterreich 4400",
    "addr:housenumber":"2",
    "addr:postcode":"4400",
    "addr:street":"Wieserfeldpl;Oberoesterreich",
    "iso:country":"AT",
    "sg:address":"Wieserfeldpl 2",
    "sg:city":"Steyr",
    "sg:orig_category":"Restaurants: Chinesisch",
    "sg:phone":"+43 7252 73662",
    "sg:postcode":"4400",
    "sg:province":"Ober\u00f6sterreich",
    "wof:name":"King Food Pagode",
    "wof:placetype":"venue"
},
  "geometry": {"coordinates":[14.4170980453,48.0453529358],"type":"Point"}
}