{
  "type": "Feature",
  "properties": {
    "iso:country":"AT",
    "sg:address":"Nr 11",
    "sg:city":"Kl\u00f6ch",
    "sg:orig_category":"Rebschulen",
    "sg:phone":"+43 3475 2288",
    "sg:postcode":"8493",
    "sg:province":"Steiermark",
    "wof:name":"Gangl Franz",
    "wof:placetype":"venue"
},
  "geometry": {"coordinates":[15.967171669,46.7641334534],"type":"Point"}
}