{
  "type": "Feature",
  "properties": {
    "addr:full":"Krugerstr 5 Wien Wien 1010",
    "addr:housenumber":"5",
    "addr:postcode":"1010",
    "addr:street":"Krugerstr",
    "iso:country":"AT",
    "sg:address":"Krugerstr 5",
    "sg:city":"Wien",
    "sg:orig_category":"Bars-Cafes",
    "sg:phone":"+43 1 5122455",
    "sg:postcode":"1010",
    "sg:province":"Wien",
    "wof:name":"KRUGER'S American Bar",
    "wof:placetype":"venue"
},
  "geometry": {"coordinates":[16.3712043762,48.2041358948],"type":"Point"}
}