{
  "type": "Feature",
  "properties": {
    "addr:full":"Galgenbergstr 32 Zwettl Nieder\u00f6sterreich 3910",
    "addr:housenumber":"32",
    "addr:postcode":"3910",
    "addr:street":"Galgenbergstr;Niederoesterreich",
    "iso:country":"AT",
    "sg:address":"Galgenbergstr 32",
    "sg:city":"Zwettl",
    "sg:orig_category":"Autobusunternehmen",
    "sg:phone":"+43 2822 5235060",
    "sg:postcode":"3910",
    "sg:province":"Nieder\u00f6sterreich",
    "wof:name":"Postbuszentrum Zwettl",
    "wof:placetype":"venue"
},
  "geometry": {"coordinates":[15.1769981384,48.6033439636],"type":"Point"}
}