{
  "type": "Feature",
  "properties": {
    "addr:full":"C v H\u00f6tzendorf-Str 11 Berndorf Nieder\u00f6sterreich 2560",
    "addr:housenumber":"11",
    "addr:postcode":"2560",
    "addr:street":"V Hoetzendorf-Str",
    "iso:country":"AT",
    "sg:address":"C v H\u00f6tzendorf-Str 11",
    "sg:city":"Berndorf",
    "sg:orig_category":"Graveure",
    "sg:phone":"+43 2672 87950",
    "sg:postcode":"2560",
    "sg:province":"Nieder\u00f6sterreich",
    "wof:name":"Schumak Walter",
    "wof:placetype":"venue"
},
  "geometry": {"coordinates":[16.1051998138,47.8947486877],"type":"Point"}
}