{
  "type": "Feature",
  "properties": {
    "addr:full":"Waldg 20 Schleinbach Nieder\u00f6sterreich 2123",
    "addr:housenumber":"20",
    "addr:postcode":"2123",
    "addr:street":"Waldg",
    "iso:country":"AT",
    "sg:address":"Waldg 20",
    "sg:city":"Schleinbach",
    "sg:orig_category":"Alarmanlagen U Sicherheitssysteme",
    "sg:phone":"+43 4322 4589042",
    "sg:postcode":"2123",
    "sg:province":"Nieder\u00f6sterreich",
    "wof:name":"Achter Sicherheitsanlagen und Spenglerei GmbH",
    "wof:placetype":"venue"
},
  "geometry": {"coordinates":[16.4917793274,48.446018219],"type":"Point"}
}