{
  "type": "Feature",
  "properties": {
    "iso:country":"AT",
    "sg:address":"Alxingerg 72",
    "sg:city":"Wien",
    "sg:orig_category":"Autoreparatur",
    "sg:phone":"+43 1 6044844",
    "sg:postcode":"1100",
    "sg:province":"Wien",
    "wof:name":"Wiesler Werner",
    "wof:placetype":"venue"
},
  "geometry": {"coordinates":[16.367149353,48.1718292236],"type":"Point"}
}