{
  "type": "Feature",
  "properties": {
    "addr:full":"Am Spitz 1/1 Wien Wien 1210",
    "addr:housenumber":"1 / 1",
    "addr:postcode":"1210",
    "addr:street":"Am Spitz",
    "iso:country":"AT",
    "sg:address":"Am Spitz 1/1",
    "sg:city":"Wien",
    "sg:orig_category":"Suchtberatung / Alkohol, Drogen, Zigaretten",
    "sg:phone":"+43 1 2722977",
    "sg:postcode":"1210",
    "sg:province":"Wien",
    "wof:name":"Dialog Hilfs- und Beratungsstelle f\u00fcr Suchtgiftgef\u00e4hrdete und deren Angeh\u00f6rige",
    "wof:placetype":"venue"
},
  "geometry": {"coordinates":[16.3972816467,48.2577781677],"type":"Point"}
}