{
  "type": "Feature",
  "properties": {
    "addr:full":"Undsdorfer Str 13 Treibach-Althofen K\u00e4rnten 9330",
    "addr:postcode":"9330",
    "addr:street":"Str 13 Treibach-Althofen Kaernten",
    "iso:country":"AT",
    "sg:address":"Undsdorfer Str 13",
    "sg:city":"Treibach-Althofen",
    "sg:orig_category":"Graveure",
    "sg:phone":"+43 4262 3837",
    "sg:postcode":"9330",
    "sg:province":"K\u00e4rnten",
    "wof:name":"Worofka Christian",
    "wof:placetype":"venue"
},
  "geometry": {"coordinates":[14.4733934402,46.8680915833],"type":"Point"}
}