{
  "type": "Feature",
  "properties": {
    "addr:full":"Bahnhofstr. 114  Kalsdorf Steiermark 8401",
    "addr:housenumber":"114",
    "addr:postcode":"8401",
    "addr:street":"Bahnhofstr.",
    "iso:country":"AT",
    "sg:address":"Bahnhofstr. 114 ",
    "sg:city":"Kalsdorf",
    "sg:classifiers":[
        {
            "category":"Autos & Motor Vehicles",
            "subcategory":"Automobile Sales",
            "type":"Retail Goods"
        }
    ],
    "sg:phone":"+43 4331 35535330",
    "sg:postcode":"8401",
    "sg:province":"Steiermark",
    "sg:tags":[
        "industrial"
    ],
    "wof:name":"SCANIA \u00d6STERREICH GES.MBH",
    "wof:placetype":"venue"
},
  "geometry": {"coordinates":[15.455575943,46.9678115845],"type":"Point"}
}