{
  "type": "Feature",
  "properties": {
    "addr:full":"Schwemmg 7 Gols Burgenland 7122",
    "addr:housenumber":"7",
    "addr:postcode":"7122",
    "addr:street":"Schwemmg",
    "iso:country":"AT",
    "sg:address":"Schwemmg 7",
    "sg:city":"Gols",
    "sg:orig_category":"Pumpen",
    "sg:phone":"+43 4321 7321336",
    "sg:postcode":"7122",
    "sg:province":"Burgenland",
    "wof:name":"R\u00f6der GmbH",
    "wof:placetype":"venue"
},
  "geometry": {"coordinates":[16.9115352631,47.8956947327],"type":"Point"}
}