{
  "type": "Feature",
  "properties": {
    "addr:full":"Kasernenstr 32 Eisenstadt Burgenland 7000",
    "addr:housenumber":"32",
    "addr:postcode":"7000",
    "addr:street":"Kasernenstr",
    "iso:country":"AT",
    "sg:address":"Kasernenstr 32",
    "sg:city":"Eisenstadt",
    "sg:classifiers":[
        {
            "category":"Taxi",
            "type":"Transportation"
        }
    ],
    "sg:phone":"+43 4326 8273737",
    "sg:postcode":"7000",
    "sg:province":"Burgenland",
    "sg:tags":[
        "personentransporte",
        "u"
    ],
    "wof:name":"Taxi Michalik",
    "wof:placetype":"venue"
},
  "geometry": {"coordinates":[16.5408935547,47.8497657776],"type":"Point"}
}