{
  "type": "Feature",
  "properties": {
    "addr:full":"Stahlstr 33 Linz Ober\u00f6sterreich 4030",
    "addr:housenumber":"33",
    "addr:postcode":"4030",
    "addr:street":"Stahlstr",
    "iso:country":"AT",
    "sg:address":"Stahlstr 33",
    "sg:city":"Linz",
    "sg:orig_category":"Genossenschaften",
    "sg:phone":"+43 732 65854430",
    "sg:postcode":"4030",
    "sg:province":"Ober\u00f6sterreich",
    "wof:name":"Sport-Kultur-Aktiv regGenmbH",
    "wof:placetype":"venue"
},
  "geometry": {"coordinates":[14.3069601059,48.2325248718],"type":"Point"}
}