{
  "type": "Feature",
  "properties": {
    "addr:full":"Leonsteiner Str 21 Leonstein Ober\u00f6sterreich 4592",
    "addr:postcode":"4592",
    "addr:street":"Str;Oberoesterreich",
    "iso:country":"AT",
    "sg:address":"Leonsteiner Str 21",
    "sg:city":"Leonstein",
    "sg:classifiers":[
        {
            "category":"Taxi",
            "type":"Transportation"
        }
    ],
    "sg:phone":"+43 4375 842322",
    "sg:postcode":"4592",
    "sg:province":"Ober\u00f6sterreich",
    "sg:tags":[
        "personentransporte",
        "u"
    ],
    "wof:name":"Riener Hermann",
    "wof:placetype":"venue"
},
  "geometry": {"coordinates":[14.2307872772,47.8972167969],"type":"Point"}
}