{
  "type": "Feature",
  "properties": {
    "iso:country":"AT",
    "sg:address":"Neustiftg 32",
    "sg:city":"Mistelbach",
    "sg:orig_category":"Steuerberatung",
    "sg:phone":"+43 4325 7231880",
    "sg:postcode":"2130",
    "sg:province":"Nieder\u00f6sterreich",
    "wof:name":"HEW Steuerberatungs u Wirtschaftstreuhand GmbH",
    "wof:placetype":"venue"
},
  "geometry": {"coordinates":[16.6020393372,48.5962486267],"type":"Point"}
}