{
  "type": "Feature",
  "properties": {
    "addr:full":"Auerspergstr 2/3 Salzburg Salzburg 5020",
    "addr:housenumber":"2 / 3",
    "addr:postcode":"5020",
    "addr:street":"Auerspergstr;Salzburg",
    "iso:country":"AT",
    "sg:address":"Auerspergstr 2/3",
    "sg:city":"Salzburg",
    "sg:orig_category":"\u00c3\u201erzte / F Allgemeinmedizin",
    "sg:phone":"+43 662 880634",
    "sg:postcode":"5020",
    "sg:province":"Salzburg",
    "wof:name":"Holfeld-Weitlof Gabriele Drmeduniv - Praxis f Gesundheit und Wohlbefinden",
    "wof:placetype":"venue"
},
  "geometry": {"coordinates":[13.0394248962,47.8066444397],"type":"Point"}
}