{
  "type": "Feature",
  "properties": {
    "addr:full":"Kreuzwiesensteig 17 Breitenfurt Nieder\u00f6sterreich 2384",
    "addr:housenumber":"17",
    "addr:postcode":"2384",
    "addr:street":"Kreuzwiesensteig",
    "iso:country":"AT",
    "sg:address":"Kreuzwiesensteig 17",
    "sg:city":"Breitenfurt",
    "sg:orig_category":"Psychotherapie",
    "sg:phone":"+43 2239 4567",
    "sg:postcode":"2384",
    "sg:province":"Nieder\u00f6sterreich",
    "wof:name":"Rass-Hubinek Gabriele Mag",
    "wof:placetype":"venue"
},
  "geometry": {"coordinates":[16.1500835419,48.1420288086],"type":"Point"}
}