{
  "type": "Feature",
  "properties": {
    "iso:country":"AT",
    "sg:address":"Marktpl 11",
    "sg:city":"Sarleinsbach",
    "sg:orig_category":"Banken U Sparkassen",
    "sg:phone":"+43 4372 8382390",
    "sg:postcode":"4152",
    "sg:province":"Ober\u00f6sterreich",
    "wof:name":"Sparkasse M\u00fchlviertel-West Bank AG",
    "wof:placetype":"venue"
},
  "geometry": {"coordinates":[13.9052410126,48.545917511],"type":"Point"}
}