{
  "type": "Feature",
  "properties": {
    "addr:full":"Triester Str 10/3/2 Wiener Neudorf Nieder\u00f6sterreich 2351",
    "addr:housenumber":"10 / 3 / 2",
    "addr:postcode":"2351",
    "addr:street":"Str",
    "iso:country":"AT",
    "sg:address":"Triester Str 10/3/2",
    "sg:city":"Wiener Neudorf",
    "sg:orig_category":"Gastronomie- U Hoteleinrichtungen",
    "sg:phone":"+43 4322 36864977",
    "sg:postcode":"2351",
    "sg:province":"Nieder\u00f6sterreich",
    "wof:name":"vetec - AG AUSTRIA",
    "wof:placetype":"venue"
},
  "geometry": {"coordinates":[16.3183326721,48.0863113403],"type":"Point"}
}