{
  "type": "Feature",
  "properties": {
    "addr:full":"Wien Wien 1220",
    "addr:postcode":"1220",
    "iso:country":"AT",
    "sg:city":"Wien",
    "sg:orig_category":"Freizeit, Spiel U Spa\u00c3\u0178",
    "sg:postcode":"1220",
    "sg:province":"Wien",
    "sg:website":"http://www.spartan-sport.at/",
    "wof:name":"Spartan Sport",
    "wof:placetype":"venue"
},
  "geometry": {"coordinates":[16.444606781,48.2497138977],"type":"Point"}
}