{
  "type": "Feature",
  "properties": {
    "addr:full":"Landstr 2d Enns Ober\u00f6sterreich 4470",
    "addr:housenumber":"2d",
    "addr:postcode":"4470",
    "addr:street":"Landstr",
    "iso:country":"AT",
    "sg:address":"Landstr 2d",
    "sg:city":"Enns",
    "sg:orig_category":"Mess-, Steuer- U Regeltechnik",
    "sg:phone":"+43 4372 2389040",
    "sg:postcode":"4470",
    "sg:province":"Ober\u00f6sterreich",
    "wof:name":"Controlmatic Ges f Automation u Elektrotechnik GmbH",
    "wof:placetype":"venue"
},
  "geometry": {"coordinates":[14.4634599686,48.2151145935],"type":"Point"}
}