{
  "type": "Feature",
  "properties": {
    "addr:full":"Rotenhofg 17 Wien Wien 1100",
    "addr:housenumber":"17",
    "addr:postcode":"1100",
    "addr:street":"Rotenhofg",
    "iso:country":"AT",
    "sg:address":"Rotenhofg 17",
    "sg:city":"Wien",
    "sg:orig_category":"Gerichtsdolmetscher",
    "sg:phone":"+43 1 60351410",
    "sg:postcode":"1100",
    "sg:province":"Wien",
    "wof:name":"Tomschizek Felix Mag",
    "wof:placetype":"venue"
},
  "geometry": {"coordinates":[16.3740444183,48.1739387512],"type":"Point"}
}