{
  "type": "Feature",
  "properties": {
    "addr:full":"Rudolfskai 6  Salzburg Salzburg 5020",
    "addr:housenumber":"6",
    "addr:postcode":"5020",
    "addr:street":"Rudolfskai;Salzburg",
    "iso:country":"AT",
    "sg:address":"Rudolfskai 6 ",
    "sg:city":"Salzburg",
    "sg:classifiers":[
        {
            "category":"Shopping",
            "subcategory":"Clothing, Apparel, & Fashions",
            "type":"Retail Goods"
        }
    ],
    "sg:phone":"+43 4366 2841213",
    "sg:postcode":"5020",
    "sg:province":"Salzburg",
    "sg:tags":[
        "clothes"
    ],
    "wof:name":"RESMANN COUTURE GMBH",
    "wof:placetype":"venue"
},
  "geometry": {"coordinates":[13.0450801849,47.8003501892],"type":"Point"}
}