{
  "type": "Feature",
  "properties": {
    "addr:full":"Pfaffingerweg 8 Aigen Salzburg 5026",
    "addr:housenumber":"8",
    "addr:postcode":"5026",
    "addr:street":"Pfaffingerweg;Salzburg",
    "iso:country":"AT",
    "sg:address":"Pfaffingerweg 8",
    "sg:city":"Aigen",
    "sg:orig_category":"Werbegrafik- U Grafik-Design",
    "sg:phone":"+43 4366 2621627",
    "sg:postcode":"5026",
    "sg:province":"Salzburg",
    "wof:name":"Bachmayr Andreas Mag",
    "wof:placetype":"venue"
},
  "geometry": {"coordinates":[13.0793037415,47.7777442932],"type":"Point"}
}