{
  "type": "Feature",
  "properties": {
    "iso:country":"AT",
    "sg:address":"Sch\u00f6nbrunner Strasse 179",
    "sg:city":"Wien",
    "sg:classifiers":[
        {
            "category":"Shopping",
            "subcategory":"Event Tickets",
            "type":"Retail Goods"
        }
    ],
    "sg:phone":"+43 1 8132346",
    "sg:postcode":"1120",
    "sg:province":"Wien",
    "sg:tags":[
        "admission",
        "roll",
        "block"
    ],
    "wof:name":"Billet Vertrieb-Ges.m.b.H.",
    "wof:placetype":"venue"
},
  "geometry": {"coordinates":[16.3389358521,48.1859703064],"type":"Point"}
}