{
  "type": "Feature",
  "properties": {
    "addr:full":"Steyrer G 114 Graz Steiermark 8010",
    "addr:housenumber":"114",
    "addr:postcode":"8010",
    "addr:street":"Steyrer G",
    "iso:country":"AT",
    "sg:address":"Steyrer G 114",
    "sg:city":"Graz",
    "sg:orig_category":"Bergbahnen",
    "sg:phone":"+43 316 887401",
    "sg:postcode":"8010",
    "sg:province":"Steiermark",
    "wof:name":"Sch\u00f6ckelseilbahn AG",
    "wof:placetype":"venue"
},
  "geometry": {"coordinates":[15.4422626495,47.060760498],"type":"Point"}
}