{
  "type": "Feature",
  "properties": {
    "addr:full":"Bahnhofstr 11 Dornbirn Vorarlberg 6850",
    "addr:housenumber":"11",
    "addr:postcode":"6850",
    "addr:street":"Bahnhofstr",
    "iso:country":"AT",
    "sg:address":"Bahnhofstr 11",
    "sg:city":"Dornbirn",
    "sg:orig_category":"Telekommunikation",
    "sg:phone":"+43 4318 863217",
    "sg:postcode":"6850",
    "sg:province":"Vorarlberg",
    "wof:name":"TELE SELECT MANSER OEG",
    "wof:placetype":"venue"
},
  "geometry": {"coordinates":[9.7398414612,47.4151191711],"type":"Point"}
}