{
  "type": "Feature",
  "properties": {
    "addr:full":"Oberlaaer Str 276 Wien Wien 1230",
    "addr:housenumber":"276",
    "addr:postcode":"1230",
    "iso:country":"AT",
    "sg:address":"Oberlaaer Str 276",
    "sg:city":"Wien",
    "sg:orig_category":"Cd, Dvd,Musikkassetten U Schallplatten",
    "sg:phone":"+43 4316 065521",
    "sg:postcode":"1230",
    "sg:province":"Wien",
    "wof:name":"Audiogram Tontr\u00e4ger HandelsgesmbH",
    "wof:placetype":"venue"
},
  "geometry": {"coordinates":[16.3667736053,48.1467437744],"type":"Point"}
}