{
  "type": "Feature",
  "properties": {
    "addr:full":"Hauptstr 7 Marchegg Nieder\u00f6sterreich 2293",
    "addr:housenumber":"7",
    "addr:postcode":"2293",
    "addr:street":"Hauptstr",
    "iso:country":"AT",
    "sg:address":"Hauptstr 7",
    "sg:city":"Marchegg",
    "sg:orig_category":"Installationsunternehmen",
    "sg:phone":"+43 2285 7300",
    "sg:postcode":"2293",
    "sg:province":"Nieder\u00f6sterreich",
    "wof:name":"Kast Josef GesmbH",
    "wof:placetype":"venue"
},
  "geometry": {"coordinates":[16.9107437134,48.2789840698],"type":"Point"}
}