{
  "type": "Feature",
  "properties": {
    "addr:full":"Kircheng 3 Traismauer Nieder\u00f6sterreich 3133",
    "addr:housenumber":"3",
    "addr:postcode":"3133",
    "addr:street":"Kircheng",
    "iso:country":"AT",
    "sg:address":"Kircheng 3",
    "sg:city":"Traismauer",
    "sg:orig_category":"Druckereien",
    "sg:phone":"+43 4327 8354508",
    "sg:postcode":"3133",
    "sg:province":"Nieder\u00f6sterreich",
    "wof:name":"Phil's Druckstudio - Philipp Egelseer",
    "wof:placetype":"venue"
},
  "geometry": {"coordinates":[15.7428569794,48.3494567871],"type":"Point"}
}