{
  "type": "Feature",
  "properties": {
    "iso:country":"AT",
    "sg:address":"Salztorg 6-8",
    "sg:city":"Wien",
    "sg:orig_category":"Sonnenstudios",
    "sg:phone":"+43 4315 326309",
    "sg:postcode":"1010",
    "sg:province":"Wien",
    "wof:name":"SUN & FUN Sonnenstudio",
    "wof:placetype":"venue"
},
  "geometry": {"coordinates":[16.3735694885,48.2135009766],"type":"Point"}
}