{
  "type": "Feature",
  "properties": {
    "addr:full":"Nr 149 Eltendorf Burgenland 7562",
    "addr:postcode":"7562",
    "addr:street":"Nr 149 Eltendorf",
    "iso:country":"AT",
    "sg:address":"Nr 149",
    "sg:city":"Eltendorf",
    "sg:orig_category":"Installationsunternehmen",
    "sg:phone":"+43 3325 2643",
    "sg:postcode":"7562",
    "sg:province":"Burgenland",
    "wof:name":"Gaal Roland InstallationsgmbH",
    "wof:placetype":"venue"
},
  "geometry": {"coordinates":[16.1975917816,47.0079803467],"type":"Point"}
}