{
  "type": "Feature",
  "properties": {
    "addr:full":"Prager Str 85 Horn Nieder\u00f6sterreich 3580",
    "addr:housenumber":"85",
    "addr:postcode":"3580",
    "addr:street":"Str",
    "iso:country":"AT",
    "sg:address":"Prager Str 85",
    "sg:city":"Horn",
    "sg:orig_category":"Autohandel",
    "sg:phone":"+43 2982 23150",
    "sg:postcode":"3580",
    "sg:province":"Nieder\u00f6sterreich",
    "wof:name":"Autohaus Lehr GmbH",
    "wof:placetype":"venue"
},
  "geometry": {"coordinates":[15.6373567581,48.6648712158],"type":"Point"}
}