{
  "type": "Feature",
  "properties": {
    "addr:full":"Wimh\u00f6lzelstr 27 Linz Ober\u00f6sterreich 4020",
    "addr:housenumber":"27",
    "addr:postcode":"4020",
    "addr:street":"Wimhoelzelstr",
    "iso:country":"AT",
    "sg:address":"Wimh\u00f6lzelstr 27",
    "sg:city":"Linz",
    "sg:orig_category":"Tabaktrafiken",
    "sg:phone":"+43 732 655270",
    "sg:postcode":"4020",
    "sg:province":"Ober\u00f6sterreich",
    "wof:name":"Horvath Doris",
    "wof:placetype":"venue"
},
  "geometry": {"coordinates":[14.3143997192,48.2953033447],"type":"Point"}
}