{
  "type": "Feature",
  "properties": {
    "addr:full":"Obere Landstr 20 Krems an der Donau Nieder\u00f6sterreich 3500",
    "addr:housenumber":"20",
    "addr:postcode":"3500",
    "addr:street":"Obere Landstr",
    "iso:country":"AT",
    "sg:address":"Obere Landstr 20",
    "sg:city":"Krems an der Donau",
    "sg:orig_category":"Fische U Fischwaren / Einzelhandel",
    "sg:phone":"+43 4327 3282045",
    "sg:postcode":"3500",
    "sg:province":"Nieder\u00f6sterreich",
    "wof:name":"Nordsee Verwaltung GesmbH",
    "wof:placetype":"venue"
},
  "geometry": {"coordinates":[15.6024017334,48.4114303589],"type":"Point"}
}