{
  "type": "Feature",
  "properties": {
    "addr:full":"Untere Marktstr 1 Bad Goisern Ober\u00f6sterreich 4822",
    "addr:housenumber":"1",
    "addr:postcode":"4822",
    "addr:street":"Untere Marktstr",
    "iso:country":"AT",
    "sg:address":"Untere Marktstr 1",
    "sg:city":"Bad Goisern",
    "sg:orig_category":"Beratungsstellen",
    "sg:phone":"+43 4361 35830117",
    "sg:postcode":"4822",
    "sg:province":"Ober\u00f6sterreich",
    "wof:name":"Mutterberatungsstelle",
    "wof:placetype":"venue"
},
  "geometry": {"coordinates":[13.6132440567,47.647693634],"type":"Point"}
}