{
  "type": "Feature",
  "properties": {
    "iso:country":"AT",
    "sg:address":"Engelbert-Kessler-Str 34",
    "sg:city":"Riezlern",
    "sg:orig_category":"Hauptschulen",
    "sg:phone":"+43 4355 175576",
    "sg:postcode":"6991",
    "sg:province":"Vorarlberg",
    "wof:name":"Schulzentrum Kleinwalsertal",
    "wof:placetype":"venue"
},
  "geometry": {"coordinates":[10.1861810684,47.3575248718],"type":"Point"}
}