{
  "type": "Feature",
  "properties": {
    "addr:full":"Wolf-Dietrich-Strasse 15 Salzburg Salzburg 5020",
    "addr:housenumber":"15",
    "addr:postcode":"5020",
    "addr:street":"Wolf-Dietrich-Strasse;Salzburg",
    "iso:country":"AT",
    "sg:address":"Wolf-Dietrich-Strasse 15",
    "sg:city":"Salzburg",
    "sg:classifiers":[
        {
            "category":"Ferry Terminal",
            "type":"Transportation"
        }
    ],
    "sg:phone":"+43 662 883852",
    "sg:postcode":"5020",
    "sg:province":"Salzburg",
    "sg:tags":[
        "casual",
        "shirt"
    ],
    "wof:name":"Hans Babitsch W\u00e4scheerzeugung",
    "wof:placetype":"venue"
},
  "geometry": {"coordinates":[13.047580719,47.8052368164],"type":"Point"}
}