{
  "type": "Feature",
  "properties": {
    "addr:full":"Dr.-Karl-Renner-Str 21 Ebergassing Nieder\u00f6sterreich 2435",
    "addr:housenumber":"21",
    "addr:postcode":"2435",
    "addr:street":"Dr.-Karl-Renner-Str",
    "iso:country":"AT",
    "sg:address":"Dr.-Karl-Renner-Str 21",
    "sg:city":"Ebergassing",
    "sg:orig_category":"Lebensmittel / Einzelhandel",
    "sg:phone":"+43 2234 73361",
    "sg:postcode":"2435",
    "sg:province":"Nieder\u00f6sterreich",
    "wof:name":"Schwoiger Josefine",
    "wof:placetype":"venue"
},
  "geometry": {"coordinates":[16.5178833008,48.0481300354],"type":"Point"}
}