{
  "type": "Feature",
  "properties": {
    "addr:full":"Maxendorf 43 Kirchbach in Steiermark Steiermark 8082",
    "addr:housenumber":"43",
    "addr:postcode":"8082",
    "addr:street":"Maxendorf",
    "iso:country":"AT",
    "sg:address":"Maxendorf 43",
    "sg:city":"Kirchbach in Steiermark",
    "sg:classifiers":[
        {
            "category":"Military Area",
            "subcategory":"Air Force Base",
            "type":"Public Place"
        }
    ],
    "sg:phone":"+43 3116 23740",
    "sg:postcode":"8082",
    "sg:province":"Steiermark",
    "sg:tags":[
        "facing",
        "brick",
        "cement"
    ],
    "sg:website":"comelli.at",
    "wof:name":"Comelli-Ziegel Ges.m.b.H.",
    "wof:placetype":"venue"
},
  "geometry": {"coordinates":[15.6817159653,46.9455757141],"type":"Point"}
}