{
  "type": "Feature",
  "properties": {
    "iso:country":"AT",
    "sg:address":"Bahnhofstr 39",
    "sg:city":"Klagenfurt",
    "sg:orig_category":"Umweltschutz",
    "sg:phone":"+43 4346 35166140",
    "sg:postcode":"9020",
    "sg:province":"K\u00e4rnten",
    "wof:name":"Institut f \u00f6kologie u Umweltplanung",
    "wof:placetype":"venue"
},
  "geometry": {"coordinates":[14.3115005493,46.6204299927],"type":"Point"}
}