{
  "type": "Feature",
  "properties": {
    "addr:full":"Salzachtal Bundesstrasse S\u00fcd 19 Hallein Salzburg 5400",
    "addr:housenumber":"19",
    "addr:postcode":"5400",
    "addr:street":"Salzachtal Bundesstrasse Sued;Salzburg",
    "iso:country":"AT",
    "sg:address":"Salzachtal Bundesstrasse S\u00fcd 19",
    "sg:city":"Hallein",
    "sg:orig_category":"CarpenterS Work Supraregional",
    "sg:phone":"+43 6245 80472",
    "sg:postcode":"5400",
    "sg:province":"Salzburg",
    "wof:name":"Sporn Zimmerei Ges.m.b.H.",
    "wof:placetype":"venue"
},
  "geometry": {"coordinates":[13.098236084,47.6830482483],"type":"Point"}
}