{
  "type": "Feature",
  "properties": {
    "addr:full":"Rheinstr 11 Bregenz Vorarlberg 6900",
    "addr:housenumber":"11",
    "addr:postcode":"6900",
    "addr:street":"Rheinstr",
    "iso:country":"AT",
    "sg:address":"Rheinstr 11",
    "sg:city":"Bregenz",
    "sg:classifiers":[
        {
            "category":"Professional",
            "type":"Services"
        }
    ],
    "sg:phone":"+43 5574 405251",
    "sg:postcode":"6900",
    "sg:province":"Vorarlberg",
    "sg:tags":[
        "leasing"
    ],
    "wof:name":"Raiffeisen-Leasing GesmbH LdsDion Vorarlberg",
    "wof:placetype":"venue"
},
  "geometry": {"coordinates":[9.7328033447,47.4981918335],"type":"Point"}
}