{
  "type": "Feature",
  "properties": {
    "addr:full":"Turmburgg 8 Wien Wien 1060",
    "addr:housenumber":"8",
    "addr:postcode":"1060",
    "addr:street":"Turmburgg",
    "iso:country":"AT",
    "sg:address":"Turmburgg 8",
    "sg:city":"Wien",
    "sg:orig_category":"Installationsunternehmen",
    "sg:phone":"+43 1 5954460",
    "sg:postcode":"1060",
    "sg:province":"Wien",
    "wof:name":"PS Klima InstallationsgesmbH",
    "wof:placetype":"venue"
},
  "geometry": {"coordinates":[16.3527412415,48.1924667358],"type":"Point"}
}