{
  "type": "Feature",
  "properties": {
    "addr:full":"Johannespl 2 Imst Tirol 6460",
    "addr:housenumber":"2",
    "addr:postcode":"6460",
    "addr:street":"Johannespl;Tirol",
    "iso:country":"AT",
    "sg:address":"Johannespl 2",
    "sg:city":"Imst",
    "sg:orig_category":"Lederwaren / Einzelhandel",
    "sg:phone":"+43 5412 66463",
    "sg:postcode":"6460",
    "sg:province":"Tirol",
    "wof:name":"J\u00e4ger Leder",
    "wof:placetype":"venue"
},
  "geometry": {"coordinates":[10.7387428284,47.2419013977],"type":"Point"}
}