{
  "type": "Feature",
  "properties": {
    "iso:country":"AT",
    "sg:address":"Hofmark 9",
    "sg:city":"Waldzell",
    "sg:orig_category":"Lebensmittel / Einzelhandel",
    "sg:phone":"+43 7754 2478",
    "sg:postcode":"4924",
    "sg:province":"Ober\u00f6sterreich",
    "wof:name":"Spar-Markt Inh Josef Kirchsteiger",
    "wof:placetype":"venue"
},
  "geometry": {"coordinates":[13.4262657166,48.1358413696],"type":"Point"}
}