{
  "type": "Feature",
  "properties": {
    "iso:country":"AT",
    "sg:address":"Rechte Wienzeile 25-27",
    "sg:city":"Wien",
    "sg:orig_category":"Elektronik",
    "sg:phone":"+43 1 5870359",
    "sg:postcode":"1040",
    "sg:province":"Wien",
    "wof:name":"Berg'e elektronische Ger\u00e4te VertriebsgesmbH",
    "wof:placetype":"venue"
},
  "geometry": {"coordinates":[16.3625469208,48.1975784302],"type":"Point"}
}