{
  "type": "Feature",
  "properties": {
    "iso:country":"AT",
    "sg:address":"Unterhaag 99a",
    "sg:city":"Oberhaag",
    "sg:orig_category":"Installationsunternehmen",
    "sg:phone":"+43 4366 44400867",
    "sg:postcode":"8455",
    "sg:province":"Steiermark",
    "wof:name":"Bochel Gerhard",
    "wof:placetype":"venue"
},
  "geometry": {"coordinates":[15.3556604385,46.6861114502],"type":"Point"}
}