{
  "type": "Feature",
  "properties": {
    "addr:full":"Lustenauer Str 19 Linz Ober\u00f6sterreich 4020",
    "addr:postcode":"4020",
    "addr:street":"Str 19",
    "iso:country":"AT",
    "sg:address":"Lustenauer Str 19",
    "sg:city":"Linz",
    "sg:classifiers":[
        {
            "category":"Sports & Exercise",
            "subcategory":"Gym",
            "type":"Entertainment"
        }
    ],
    "sg:phone":"+43 664 4615366",
    "sg:postcode":"4020",
    "sg:province":"Ober\u00f6sterreich",
    "sg:tags":[
        "meditation"
    ],
    "wof:name":"\u00f6sterreichische Gesellschaft f Maharishis Vedische Wissenschaft",
    "wof:placetype":"venue"
},
  "geometry": {"coordinates":[14.297700882,48.3011131287],"type":"Point"}
}