{
  "type": "Feature",
  "properties": {
    "iso:country":"AT",
    "sg:address":"Vordertambergau 31",
    "sg:city":"Vorderstoder",
    "sg:classifiers":[
        {
            "category":"Travel",
            "subcategory":"Hotels & Motels",
            "type":"Entertainment"
        }
    ],
    "sg:phone":"+43 7564 83830",
    "sg:postcode":"4574",
    "sg:province":"Ober\u00f6sterreich",
    "wof:name":"Landhotel Lindbichler",
    "wof:placetype":"venue"
},
  "geometry": {"coordinates":[14.2474517822,47.7175483704],"type":"Point"}
}