{
  "type": "Feature",
  "properties": {
    "addr:full":"Nr 8 Gnas Steiermark 8342",
    "addr:postcode":"8342",
    "addr:street":"Nr;Gnas",
    "iso:country":"AT",
    "sg:address":"Nr 8",
    "sg:city":"Gnas",
    "sg:orig_category":"Fassbindereien",
    "sg:phone":"+43 4331 512534",
    "sg:postcode":"8342",
    "sg:province":"Steiermark",
    "wof:name":"Neuhold Anton",
    "wof:placetype":"venue"
},
  "geometry": {"coordinates":[15.8265724182,46.8743095398],"type":"Point"}
}