{
  "type": "Feature",
  "properties": {
    "addr:full":"Sagbergstr 16 Julbach Ober\u00f6sterreich 4162",
    "addr:housenumber":"16",
    "addr:postcode":"4162",
    "addr:street":"Sagbergstr",
    "iso:country":"AT",
    "sg:address":"Sagbergstr 16",
    "sg:city":"Julbach",
    "sg:orig_category":"Installationsunternehmen",
    "sg:phone":"+43 7288 8380",
    "sg:postcode":"4162",
    "sg:province":"Ober\u00f6sterreich",
    "wof:name":"Luger Franz",
    "wof:placetype":"venue"
},
  "geometry": {"coordinates":[13.8577709198,48.6610946655],"type":"Point"}
}