{
  "type": "Feature",
  "properties": {
    "addr:full":"Hoher Mkt. 12  Wien Wien 1010",
    "addr:housenumber":"12",
    "addr:postcode":"1010",
    "addr:street":"Hoher Mkt.",
    "iso:country":"AT",
    "sg:address":"Hoher Mkt. 12 ",
    "sg:city":"Wien",
    "sg:classifiers":[
        {
            "category":"Communications",
            "subcategory":"Newspaper",
            "type":"Services"
        }
    ],
    "sg:phone":"+43 4315 3407",
    "sg:postcode":"1010",
    "sg:province":"Wien",
    "sg:tags":[
        "advertising"
    ],
    "wof:name":"ANK\u00dcNDER F\u00dcR AUSSENWERBUNG AG",
    "wof:placetype":"venue"
},
  "geometry": {"coordinates":[16.3688049316,48.2025489807],"type":"Point"}
}