{
  "type": "Feature",
  "properties": {
    "addr:full":"Angerer Str 24 Wien Wien 1210",
    "addr:postcode":"1210",
    "addr:street":"Str 24",
    "iso:country":"AT",
    "sg:address":"Angerer Str 24",
    "sg:city":"Wien",
    "sg:classifiers":[
        {
            "category":"Shopping",
            "subcategory":"Thrift Store",
            "type":"Retail Goods"
        }
    ],
    "sg:phone":"+43 1 2713245",
    "sg:postcode":"1210",
    "sg:province":"Wien",
    "sg:tags":[
        "second-hand-shops"
    ],
    "wof:name":"Second-Hand-Shop Elfie Cohen",
    "wof:placetype":"venue"
},
  "geometry": {"coordinates":[16.403673172,48.2578392029],"type":"Point"}
}