{
  "type": "Feature",
  "properties": {
    "addr:full":"Untermarkt 33 Reutte Tirol 6600",
    "addr:housenumber":"33",
    "addr:postcode":"6600",
    "addr:street":"Untermarkt;Tirol",
    "iso:country":"AT",
    "sg:address":"Untermarkt 33",
    "sg:city":"Reutte",
    "sg:orig_category":"Fernseh- U Radiogesellschaften",
    "sg:phone":"+43 512 361065",
    "sg:postcode":"6600",
    "sg:province":"Tirol",
    "wof:name":"Radio Arabella Au\u00dferfern",
    "wof:placetype":"venue"
},
  "geometry": {"coordinates":[10.7176218033,47.4919471741],"type":"Point"}
}