{
  "type": "Feature",
  "properties": {
    "addr:full":"Liebenauer Hauptstr 186 Liebenau Steiermark 8041",
    "addr:housenumber":"186",
    "addr:postcode":"8041",
    "addr:street":"Hauptstr",
    "iso:country":"AT",
    "sg:address":"Liebenauer Hauptstr 186",
    "sg:city":"Liebenau",
    "sg:orig_category":"Autoreparatur",
    "sg:phone":"+43 316 401417",
    "sg:postcode":"8041",
    "sg:province":"Steiermark",
    "wof:name":"Reiterer Fritz",
    "wof:placetype":"venue"
},
  "geometry": {"coordinates":[15.4644479752,47.0321159363],"type":"Point"}
}