{
  "type": "Feature",
  "properties": {
    "addr:full":"Hauptstr 51 Felixdorf Nieder\u00f6sterreich 2603",
    "addr:housenumber":"51",
    "addr:postcode":"2603",
    "addr:street":"Hauptstr",
    "iso:country":"AT",
    "sg:address":"Hauptstr 51",
    "sg:city":"Felixdorf",
    "sg:classifiers":[
        {
            "category":"Home & Garden",
            "subcategory":"Garden Supply",
            "type":"Retail Goods"
        }
    ],
    "sg:phone":"+43 4326 2863674",
    "sg:postcode":"2603",
    "sg:province":"Nieder\u00f6sterreich",
    "sg:tags":[
        "schotter",
        "sand",
        "u"
    ],
    "wof:name":"Gruber Leopold",
    "wof:placetype":"venue"
},
  "geometry": {"coordinates":[16.2390727997,47.8796882629],"type":"Point"}
}