{
  "type": "Feature",
  "properties": {
    "iso:country":"AT",
    "sg:address":"Nr 52",
    "sg:orig_category":"Feuerwehren",
    "sg:phone":"+43 4872 5600",
    "sg:postcode":"9953",
    "wof:name":"Freiwillige Feuerwehr Huben",
    "wof:placetype":"venue"
},
  "geometry": {"coordinates":[12.573764801,46.9368247986],"type":"Point"}
}