{
  "type": "Feature",
  "properties": {
    "addr:full":"Meidlinger Hauptstr 57-59 Wien Wien 1120",
    "addr:postcode":"57-59;1120",
    "addr:street":"Meidlinger Hauptstr",
    "iso:country":"AT",
    "sg:address":"Meidlinger Hauptstr 57-59",
    "sg:city":"Wien",
    "sg:orig_category":"Damenmoden",
    "sg:phone":"+43 4318 1574740",
    "sg:postcode":"1120",
    "sg:province":"Wien",
    "wof:name":"C & A Mode GesmbH & Co KG - C & A Mode",
    "wof:placetype":"venue"
},
  "geometry": {"coordinates":[16.330373764,48.1763000488],"type":"Point"}
}