{
  "type": "Feature",
  "properties": {
    "addr:full":"Bergwerkstr 41 Schwaz Tirol 6130",
    "addr:housenumber":"41",
    "addr:postcode":"6130",
    "addr:street":"Bergwerkstr;Tirol",
    "iso:country":"AT",
    "sg:address":"Bergwerkstr 41",
    "sg:city":"Schwaz",
    "sg:orig_category":"Fahrzeugbau",
    "sg:phone":"+43 5242 62526",
    "sg:postcode":"6130",
    "sg:province":"Tirol",
    "wof:name":"KA-Tech Sonderfahrzeugbau GmbH",
    "wof:placetype":"venue"
},
  "geometry": {"coordinates":[11.7217998505,47.3606567383],"type":"Point"}
}