{
  "type": "Feature",
  "properties": {
    "addr:full":"Krottendorf 10 Fernitz Steiermark 8072",
    "addr:housenumber":"10",
    "addr:postcode":"8072",
    "addr:street":"Krottendorf",
    "iso:country":"AT",
    "sg:address":"Krottendorf 10",
    "sg:city":"Fernitz",
    "sg:orig_category":"Estriche",
    "sg:phone":"+43 4331 3582561",
    "sg:postcode":"8072",
    "sg:province":"Steiermark",
    "wof:name":"Rathkolb GmbH",
    "wof:placetype":"venue"
},
  "geometry": {"coordinates":[15.530790329,46.9433441162],"type":"Point"}
}