{
  "type": "Feature",
  "properties": {
    "addr:full":"Schlo\u00dfpl 47 Haus Steiermark 8967",
    "addr:housenumber":"47",
    "addr:postcode":"8967",
    "addr:street":"Schlosspl",
    "iso:country":"AT",
    "sg:address":"Schlo\u00dfpl 47",
    "sg:city":"Haus",
    "sg:orig_category":"Polizei U Gendarmerie",
    "sg:phone":"+43 4359 1336353",
    "sg:postcode":"8967",
    "sg:province":"Steiermark",
    "wof:name":"Gendarmerie Haus",
    "wof:placetype":"venue"
},
  "geometry": {"coordinates":[13.7687940598,47.410118103],"type":"Point"}
}