{
  "type": "Feature",
  "properties": {
    "iso:country":"AT",
    "sg:address":"Unterh\u00f6fen 107",
    "sg:city":"Tannheim",
    "sg:orig_category":"Appartements / Ferienwohnungen",
    "sg:phone":"+43 4356 756350",
    "sg:postcode":"6675",
    "sg:province":"Tirol",
    "wof:name":"Appartementhaus Obwaller",
    "wof:placetype":"venue"
},
  "geometry": {"coordinates":[10.5161399841,47.4993400574],"type":"Point"}
}