{
  "type": "Feature",
  "properties": {
    "iso:country":"AT",
    "sg:address":"Nr 80",
    "sg:city":"Gro\u00dfpesendorf",
    "sg:orig_category":"Exporteure U Importeure",
    "sg:phone":"+43 4331 783477",
    "sg:postcode":"8211",
    "sg:province":"Steiermark",
    "wof:name":"Teller Erwin",
    "wof:placetype":"venue"
},
  "geometry": {"coordinates":[15.7626972198,47.1513366699],"type":"Point"}
}