{
  "type": "Feature",
  "properties": {
    "addr:full":"Europaallee 1 Weiz Steiermark 8160",
    "addr:housenumber":"1",
    "addr:postcode":"8160",
    "addr:street":"Europaallee",
    "iso:country":"AT",
    "sg:address":"Europaallee 1",
    "sg:city":"Weiz",
    "sg:orig_category":"Bankomat-Standorte",
    "sg:phone":"+43 3172 26050",
    "sg:postcode":"8160",
    "sg:province":"Steiermark",
    "wof:name":"Bankomat d Steierm\u00e4rkische Bank und Sparkassen AG",
    "wof:placetype":"venue"
},
  "geometry": {"coordinates":[15.6256227493,47.2182617188],"type":"Point"}
}