{
  "type": "Feature",
  "properties": {
    "iso:country":"AT",
    "sg:address":"Nr 45",
    "sg:city":"Thiersee",
    "sg:orig_category":"Feuerwehren",
    "sg:phone":"+43 5376 5440",
    "sg:postcode":"6335",
    "sg:province":"Tirol",
    "wof:name":"Freiwillige Feuerwehr Thiersee",
    "wof:placetype":"venue"
},
  "geometry": {"coordinates":[12.1183481216,47.5942153931],"type":"Point"}
}