{
  "type": "Feature",
  "properties": {
    "addr:full":"Obermarkt 22 Reutte Tirol 6600",
    "addr:housenumber":"22",
    "addr:postcode":"6600",
    "addr:street":"Obermarkt;Tirol",
    "iso:country":"AT",
    "sg:address":"Obermarkt 22",
    "sg:city":"Reutte",
    "sg:orig_category":"Tabaktrafiken",
    "sg:phone":"+43 5672 62376",
    "sg:postcode":"6600",
    "sg:province":"Tirol",
    "wof:name":"Schauer Gerald",
    "wof:placetype":"venue"
},
  "geometry": {"coordinates":[10.7193822861,47.4867897034],"type":"Point"}
}