{
  "type": "Feature",
  "properties": {
    "addr:full":"Nr 33 Haidershofen Nieder\u00f6sterreich 4431",
    "addr:postcode":"4431",
    "addr:street":"Nr;Niederoesterreich",
    "iso:country":"AT",
    "sg:address":"Nr 33",
    "sg:city":"Haidershofen",
    "sg:orig_category":"Metallbau",
    "sg:phone":"+43 7252 800800",
    "sg:postcode":"4431",
    "sg:province":"Nieder\u00f6sterreich",
    "wof:name":"Federer Metallbau GmbH & Co KG",
    "wof:placetype":"venue"
},
  "geometry": {"coordinates":[14.4578227997,48.0766983032],"type":"Point"}
}