{
  "type": "Feature",
  "properties": {
    "addr:full":"Birkeng 4 Prinzersdorf Nieder\u00f6sterreich 3385",
    "addr:housenumber":"4",
    "addr:postcode":"3385",
    "addr:street":"Birkeng",
    "iso:country":"AT",
    "sg:address":"Birkeng 4",
    "sg:city":"Prinzersdorf",
    "sg:orig_category":"Immobilienmakler",
    "sg:phone":"+43 664 3817061",
    "sg:postcode":"3385",
    "sg:province":"Nieder\u00f6sterreich",
    "wof:name":"De Icco Anton",
    "wof:placetype":"venue"
},
  "geometry": {"coordinates":[15.5544900894,48.1992416382],"type":"Point"}
}