{
  "type": "Feature",
  "properties": {
    "addr:full":"Wiener Strasse 161 Linz Ober\u00f6sterreich 4020",
    "addr:housenumber":"161",
    "addr:postcode":"4020",
    "addr:street":"Wiener Strasse",
    "iso:country":"AT",
    "sg:address":"Wiener Strasse 161",
    "sg:city":"Linz",
    "sg:classifiers":[
        {
            "category":"Community Center",
            "subcategory":"Ethnic",
            "type":"Public Place"
        }
    ],
    "sg:phone":"+43 732 343303",
    "sg:postcode":"4020",
    "sg:province":"Ober\u00f6sterreich",
    "sg:tags":[
        "battery",
        "alkaline"
    ],
    "wof:name":"IGB Industrie- und Gewerbebatterien, Feuerl\u00f6schger\u00e4te Vertriebs- und Wartungsges.m.b.H.",
    "wof:placetype":"venue"
},
  "geometry": {"coordinates":[14.3099451065,48.2797698975],"type":"Point"}
}