{
  "type": "Feature",
  "properties": {
    "addr:full":"Neuer Markt 1 Wien Wien 1010",
    "addr:housenumber":"1",
    "addr:postcode":"1010",
    "addr:street":"Neuer Markt",
    "iso:country":"AT",
    "sg:address":"Neuer Markt 1",
    "sg:city":"Wien",
    "sg:orig_category":"Steuerberatung",
    "sg:phone":"+43 4315 1256710",
    "sg:postcode":"1010",
    "sg:province":"Wien",
    "wof:name":"Ring Treuhand- u RevisionsgesmbH",
    "wof:placetype":"venue"
},
  "geometry": {"coordinates":[16.3711242676,48.2066116333],"type":"Point"}
}