{
  "type": "Feature",
  "properties": {
    "addr:full":"Bahnstr 7 Horn Nieder\u00f6sterreich 3580",
    "addr:housenumber":"7",
    "addr:postcode":"3580",
    "addr:street":"Bahnstr;Niederoesterreich",
    "iso:country":"AT",
    "sg:address":"Bahnstr 7",
    "sg:city":"Horn",
    "sg:orig_category":"Raumausstattung",
    "sg:phone":"+43 2982 4209",
    "sg:postcode":"3580",
    "sg:province":"Nieder\u00f6sterreich",
    "wof:name":"Teppichmarkt M Wunsch",
    "wof:placetype":"venue"
},
  "geometry": {"coordinates":[15.6635103226,48.6656112671],"type":"Point"}
}