{
  "type": "Feature",
  "properties": {
    "iso:country":"AT",
    "sg:address":"Laxenburger Str 39",
    "sg:city":"Wien",
    "sg:orig_category":"Friseure U Frisiersalons",
    "sg:phone":"+43 4316 043304",
    "sg:postcode":"1100",
    "sg:province":"Wien",
    "wof:name":"Friseur Elisa",
    "wof:placetype":"venue"
},
  "geometry": {"coordinates":[16.3740367889,48.179599762],"type":"Point"}
}