{
  "type": "Feature",
  "properties": {
    "addr:full":"Therme 152 Loipersdorf Steiermark 8282",
    "addr:housenumber":"152",
    "addr:postcode":"8282",
    "iso:country":"AT",
    "sg:address":"Therme 152",
    "sg:city":"Loipersdorf",
    "sg:orig_category":"Massageschulen U -Kurse",
    "sg:phone":"+43 3382 820467",
    "sg:postcode":"8282",
    "sg:province":"Steiermark",
    "wof:name":"Gesundheitsschule Steirisches Thermenland",
    "wof:placetype":"venue"
},
  "geometry": {"coordinates":[16.1014671326,47.0128898621],"type":"Point"}
}