{
  "type": "Feature",
  "properties": {
    "addr:full":"Kirchstr 30 Bregenz Vorarlberg 6900",
    "addr:housenumber":"30",
    "addr:postcode":"6900",
    "addr:street":"Kirchstr",
    "iso:country":"AT",
    "sg:address":"Kirchstr 30",
    "sg:city":"Bregenz",
    "sg:orig_category":"Beteiligungen U Finanzierungen",
    "sg:phone":"+43 5574 58181",
    "sg:postcode":"6900",
    "sg:province":"Vorarlberg",
    "wof:name":"ALL-FINANZ Finanzdienstleistung GmbH",
    "wof:placetype":"venue"
},
  "geometry": {"coordinates":[9.7464447021,47.5003852844],"type":"Point"}
}