{
  "type": "Feature",
  "properties": {
    "addr:full":"Robert-Stolz-Str 3 Linz Ober\u00f6sterreich 4020",
    "addr:housenumber":"3",
    "addr:postcode":"4020",
    "addr:street":"Robert-Stolz-Str",
    "iso:country":"AT",
    "sg:address":"Robert-Stolz-Str 3",
    "sg:city":"Linz",
    "sg:orig_category":"Datenverarbeitung",
    "sg:phone":"+43 732 658121",
    "sg:postcode":"4020",
    "sg:province":"Ober\u00f6sterreich",
    "wof:name":"Huber & Co EDV-GesmbH",
    "wof:placetype":"venue"
},
  "geometry": {"coordinates":[14.2769804001,48.2860527039],"type":"Point"}
}