{
  "type": "Feature",
  "properties": {
    "iso:country":"AT",
    "sg:address":"Nr 176",
    "sg:city":"Vorau",
    "sg:classifiers":[
        {
            "category":"Taxi",
            "type":"Transportation"
        }
    ],
    "sg:phone":"+43 4333 372322",
    "sg:postcode":"8250",
    "sg:province":"Steiermark",
    "sg:tags":[
        "personentransporte",
        "u"
    ],
    "wof:name":"P\u00f6tz Ewald",
    "wof:placetype":"venue"
},
  "geometry": {"coordinates":[15.8873929977,47.4056854248],"type":"Point"}
}