{
  "type": "Feature",
  "properties": {
    "iso:country":"AT",
    "sg:address":"Wiener Str 8",
    "sg:city":"Wolfsberg",
    "sg:orig_category":"Damenmoden",
    "sg:phone":"+43 4352 2023",
    "sg:postcode":"9400",
    "sg:province":"K\u00e4rnten",
    "wof:name":"Charles V\u00f6gele (Austria) AG",
    "wof:placetype":"venue"
},
  "geometry": {"coordinates":[14.8417463303,46.8419914246],"type":"Point"}
}