{
  "type": "Feature",
  "properties": {
    "addr:full":"Am Lorberkogel 40 Treibach-Althofen K\u00e4rnten 9330",
    "addr:housenumber":"40",
    "addr:postcode":"9330",
    "addr:street":"Am Lorberkogel;Kaernten",
    "iso:country":"AT",
    "sg:address":"Am Lorberkogel 40",
    "sg:city":"Treibach-Althofen",
    "sg:orig_category":"Maler, Anstreicher U Lackierer",
    "sg:phone":"+43 4342 622429",
    "sg:postcode":"9330",
    "sg:province":"K\u00e4rnten",
    "wof:name":"D\u00fcnhofen Rudolf",
    "wof:placetype":"venue"
},
  "geometry": {"coordinates":[14.4725809097,46.8684997559],"type":"Point"}
}