{
  "type": "Feature",
  "properties": {
    "iso:country":"AT",
    "sg:address":"Walchen 19a",
    "sg:city":"Piesendorf",
    "sg:orig_category":"Holzhandel",
    "sg:phone":"+43 4365 497995",
    "sg:postcode":"5721",
    "sg:province":"Salzburg",
    "wof:name":"Holzfachmarkt u Bilderrahmenatelier Marko Ernst",
    "wof:placetype":"venue"
},
  "geometry": {"coordinates":[12.6916799545,47.2892799377],"type":"Point"}
}