{
  "type": "Feature",
  "properties": {
    "addr:full":"Herrenstr 50 Linz Ober\u00f6sterreich 4020",
    "addr:housenumber":"50",
    "addr:postcode":"4020",
    "addr:street":"Herrenstr",
    "iso:country":"AT",
    "sg:address":"Herrenstr 50",
    "sg:city":"Linz",
    "sg:classifiers":[
        {
            "category":"Shopping",
            "subcategory":"Bicycles & Sporting Goods",
            "type":"Retail Goods"
        }
    ],
    "sg:phone":"+43 732 776281",
    "sg:postcode":"4020",
    "sg:province":"Ober\u00f6sterreich",
    "sg:tags":[
        "munition",
        "u",
        "waffen"
    ],
    "sg:website":"www.gunsmith.cc",
    "wof:name":"Schmid Marco Ing Waffen - Munition - Jagdartikel",
    "wof:placetype":"venue"
},
  "geometry": {"coordinates":[14.2874956131,48.2988243103],"type":"Point"}
}