{
  "type": "Feature",
  "properties": {
    "addr:full":"Nr 5 Eibiswald Steiermark 8552",
    "addr:postcode":"8552",
    "addr:street":"Nr",
    "iso:country":"AT",
    "sg:address":"Nr 5",
    "sg:city":"Eibiswald",
    "sg:orig_category":"Erdarbeiten",
    "sg:phone":"+43 3466 42109",
    "sg:postcode":"8552",
    "sg:province":"Steiermark",
    "wof:name":"Ropitsch Helmut",
    "wof:placetype":"venue"
},
  "geometry": {"coordinates":[15.2274599075,46.6824150085],"type":"Point"}
}