{
  "type": "Feature",
  "properties": {
    "addr:full":"Pichlbergstr 15 S\u00f6ding Steiermark 8561",
    "addr:housenumber":"15",
    "addr:postcode":"8561",
    "addr:street":"Pichlbergstr",
    "iso:country":"AT",
    "sg:address":"Pichlbergstr 15",
    "sg:city":"S\u00f6ding",
    "sg:orig_category":"Flugcharter",
    "sg:phone":"+43 3137 6129",
    "sg:postcode":"8561",
    "sg:province":"Steiermark",
    "wof:name":"Stf: Hail Air Hagelabwehr GesmbH",
    "wof:placetype":"venue"
},
  "geometry": {"coordinates":[-80.9476013184,38.6538276672],"type":"Point"}
}