{
  "type": "Feature",
  "properties": {
    "iso:country":"AT",
    "sg:address":"Am Bach 8",
    "sg:city":"Kufstein",
    "sg:orig_category":"Garagentore U -Antriebe",
    "sg:phone":"+43 5372 58819",
    "sg:postcode":"6330",
    "sg:province":"Tirol",
    "wof:name":"Kaufmann Franz",
    "wof:placetype":"venue"
},
  "geometry": {"coordinates":[12.1509380341,47.5363235474],"type":"Point"}
}