{
  "type": "Feature",
  "properties": {
    "addr:full":"Hauptpl 7 Dobersberg Nieder\u00f6sterreich 3843",
    "addr:housenumber":"7",
    "addr:postcode":"3843",
    "addr:street":"Hauptpl",
    "iso:country":"AT",
    "sg:address":"Hauptpl 7",
    "sg:city":"Dobersberg",
    "sg:orig_category":"Maler, Anstreicher U Lackierer",
    "sg:phone":"+43 4328 432337",
    "sg:postcode":"3843",
    "sg:province":"Nieder\u00f6sterreich",
    "wof:name":"Burian Thomas",
    "wof:placetype":"venue"
},
  "geometry": {"coordinates":[15.3224029541,48.914855957],"type":"Point"}
}