{
  "type": "Feature",
  "properties": {
    "iso:country":"AT",
    "sg:address":"Mittelberg 15",
    "sg:city":"Fontanella",
    "sg:orig_category":"Schlossereien",
    "sg:phone":"+43 5554 5545",
    "sg:postcode":"6733",
    "sg:province":"Vorarlberg",
    "wof:name":"Bickel Sebastian",
    "wof:placetype":"venue"
},
  "geometry": {"coordinates":[9.8867721558,47.2431488037],"type":"Point"}
}