{
  "type": "Feature",
  "properties": {
    "addr:full":"Anzengruberstr 3 Linz Ober\u00f6sterreich 4020",
    "addr:housenumber":"3",
    "addr:postcode":"4020",
    "addr:street":"Anzengruberstr",
    "iso:country":"AT",
    "sg:address":"Anzengruberstr 3",
    "sg:city":"Linz",
    "sg:orig_category":"Fahrschulen",
    "sg:phone":"+43 732 653127",
    "sg:postcode":"4020",
    "sg:province":"Ober\u00f6sterreich",
    "sg:website":"fahrschule-rauch.at",
    "wof:name":"Fahrschule Rauch",
    "wof:placetype":"venue"
},
  "geometry": {"coordinates":[14.296626091,48.2919044495],"type":"Point"}
}