{
  "type": "Feature",
  "properties": {
    "iso:country":"AT",
    "sg:address":"Mariahilfer Strasse 1d",
    "sg:city":"Wien",
    "sg:classifiers":[
        {
            "category":"Banks & Credit Unions",
            "subcategory":"Investment Brokerage",
            "type":"Services"
        }
    ],
    "sg:phone":"+43 1 5877776",
    "sg:postcode":"1060",
    "sg:province":"Wien",
    "sg:tags":[
        "case",
        "spectacle"
    ],
    "sg:website":"muelleroptik.at",
    "wof:name":"Carl M\u00fcller",
    "wof:placetype":"venue"
},
  "geometry": {"coordinates":[16.3606357574,48.2017021179],"type":"Point"}
}