{
  "type": "Feature",
  "properties": {
    "iso:country":"AT",
    "sg:address":"Kaiserebersdorferstr 328",
    "sg:city":"Wien",
    "sg:orig_category":"Friseure U Frisiersalons",
    "sg:phone":"+43 1 7694277",
    "sg:postcode":"1110",
    "sg:province":"Wien",
    "wof:name":"Friseursalon Zetl",
    "wof:placetype":"venue"
},
  "geometry": {"coordinates":[16.4715366364,48.1591911316],"type":"Point"}
}