{
  "type": "Feature",
  "properties": {
    "iso:country":"AT",
    "sg:address":"Nobelg 10",
    "sg:city":"Klagenfurt-Viktring",
    "sg:orig_category":"Dekorationen",
    "sg:phone":"+43 699 17061706",
    "sg:postcode":"9073",
    "sg:province":"K\u00e4rnten",
    "sg:website":"i-dee.com",
    "wof:name":"I-DEE Kleinberger Dekorationen & Design",
    "wof:placetype":"venue"
},
  "geometry": {"coordinates":[14.2700395584,46.5941810608],"type":"Point"}
}