{
  "type": "Feature",
  "properties": {
    "iso:country":"AT",
    "sg:address":"Weyerstr 21",
    "sg:city":"Gmunden",
    "sg:orig_category":"Tapezierer U Dekorateure",
    "sg:phone":"+43 761267956",
    "sg:postcode":"4810",
    "sg:province":"Ober\u00f6sterreich",
    "wof:name":"H\u00f6poltseder Gertraud",
    "wof:placetype":"venue"
},
  "geometry": {"coordinates":[13.8077554703,47.9140281677],"type":"Point"}
}