{
  "type": "Feature",
  "properties": {
    "addr:full":"Dr.-Neud\u00f6rfer-Str 9 Hohenems Vorarlberg 6845",
    "addr:housenumber":"9",
    "addr:postcode":"6845",
    "addr:street":"Dr.-Neudoerfer-Str",
    "iso:country":"AT",
    "sg:address":"Dr.-Neud\u00f6rfer-Str 9",
    "sg:city":"Hohenems",
    "sg:orig_category":"Glasereien",
    "sg:phone":"+43 4355 76724020",
    "sg:postcode":"6845",
    "sg:province":"Vorarlberg",
    "sg:website":"amannfenster.com",
    "wof:name":"Amann Herbert GmbH & Co KG",
    "wof:placetype":"venue"
},
  "geometry": {"coordinates":[9.6839723587,47.3662834167],"type":"Point"}
}