{
  "type": "Feature",
  "properties": {
    "iso:country":"AT",
    "sg:address":"Pater H Geist-Pl 1",
    "sg:city":"Mariazell",
    "sg:orig_category":"Gemeinden",
    "sg:phone":"+43 3882 22440",
    "sg:postcode":"8630",
    "sg:province":"Steiermark",
    "wof:name":"Stadtamt Mariazell",
    "wof:placetype":"venue"
},
  "geometry": {"coordinates":[15.3167905807,47.7734184265],"type":"Point"}
}