{
  "type": "Feature",
  "properties": {
    "iso:country":"AT",
    "sg:address":"Hofgrabeng 6",
    "sg:city":"Ebenfurth",
    "sg:orig_category":"Datenverarbeitung",
    "sg:phone":"+43 2624 536400",
    "sg:postcode":"2490",
    "sg:province":"Nieder\u00f6sterreich",
    "wof:name":"Baumgartner Edith",
    "wof:placetype":"venue"
},
  "geometry": {"coordinates":[16.362531662,47.8749885559],"type":"Point"}
}