{
  "type": "Feature",
  "properties": {
    "addr:full":"Wattg 6-8 Laa an der Thaya Nieder\u00f6sterreich 2136",
    "addr:housenumber":"6-8",
    "addr:postcode":"2136",
    "addr:street":"Wattg",
    "iso:country":"AT",
    "sg:address":"Wattg 6-8",
    "sg:city":"Laa an der Thaya",
    "sg:orig_category":"Autohandel",
    "sg:phone":"+43 2522 23170",
    "sg:postcode":"2136",
    "sg:province":"Nieder\u00f6sterreich",
    "sg:website":"parisch.at",
    "wof:name":"Parisch Autohaus GmbH",
    "wof:placetype":"venue"
},
  "geometry": {"coordinates":[16.3851604462,48.7205963135],"type":"Point"}
}