{
  "type": "Feature",
  "properties": {
    "addr:full":"Am Winklgarten 8 Linz Ober\u00f6sterreich 4030",
    "addr:housenumber":"8",
    "addr:postcode":"4030",
    "addr:street":"Am Winklgarten",
    "iso:country":"AT",
    "sg:address":"Am Winklgarten 8",
    "sg:city":"Linz",
    "sg:classifiers":[
        {
            "category":"Home & Garden",
            "subcategory":"Home Furnishings",
            "type":"Retail Goods"
        }
    ],
    "sg:phone":"+43 732 305204",
    "sg:postcode":"4030",
    "sg:province":"Ober\u00f6sterreich",
    "sg:tags":[
        "interior",
        "decoration"
    ],
    "wof:name":"Dipl.-Arch. G\u00fcnter Pineker",
    "wof:placetype":"venue"
},
  "geometry": {"coordinates":[14.3016767502,48.2522087097],"type":"Point"}
}