{
  "type": "Feature",
  "properties": {
    "addr:full":"Heimwald 164A Stans Tirol 6135",
    "addr:housenumber":"164a",
    "addr:postcode":"6135",
    "addr:street":"Heimwald;Tirol",
    "iso:country":"AT",
    "sg:address":"Heimwald 164A",
    "sg:city":"Stans",
    "sg:orig_category":"Maler, Anstreicher U Lackierer",
    "sg:phone":"+43 4352 4273967",
    "sg:postcode":"6135",
    "sg:province":"Tirol",
    "sg:website":"malerei-salchner.at",
    "wof:name":"Salchner Stefan",
    "wof:placetype":"venue"
},
  "geometry": {"coordinates":[11.7170000076,47.36977005],"type":"Point"}
}