{
  "type": "Feature",
  "properties": {
    "addr:full":"Kei\u00dflerg. 26 Wien Wien 1140",
    "addr:housenumber":"26",
    "addr:postcode":"1140",
    "addr:street":"Keisslerg.",
    "iso:country":"AT",
    "sg:address":"Kei\u00dflerg. 26",
    "sg:city":"Wien",
    "sg:classifiers":[
        {
            "category":"Manufacturing",
            "subcategory":"Glass & Minerals",
            "type":"Manufacturing & Wholesale Goods"
        }
    ],
    "sg:phone":"+43 4314 15650",
    "sg:postcode":"1140",
    "sg:province":"Wien",
    "wof:name":"ST\u00d6LZLE OBERGLAS AG & CO KG",
    "wof:placetype":"venue"
},
  "geometry": {"coordinates":[16.2696990967,48.1994247437],"type":"Point"}
}