{
  "type": "Feature",
  "properties": {
    "iso:country":"AT",
    "sg:address":"Interpark Focus 50",
    "sg:city":"Sulz-R\u00f6this",
    "sg:orig_category":"Speditionen",
    "sg:phone":"+43 4357 686255900",
    "sg:postcode":"6832",
    "sg:province":"Vorarlberg",
    "wof:name":"Schenker & Co AG",
    "wof:placetype":"venue"
},
  "geometry": {"coordinates":[-76.7671127319,39.2538833618],"type":"Point"}
}