{
  "type": "Feature",
  "properties": {
    "addr:full":"Gabelsbergerstr 25 Salzburg Salzburg 5020",
    "addr:housenumber":"25",
    "addr:postcode":"5020",
    "addr:street":"Gabelsbergerstr;Salzburg",
    "iso:country":"AT",
    "sg:address":"Gabelsbergerstr 25",
    "sg:city":"Salzburg",
    "sg:orig_category":"Projektoren / Vermietung, Tonanlagen / Vermietung, Veranstaltungstechnik, Videoanlagen / Vermietung,",
    "sg:phone":"+43 662 8748840",
    "sg:postcode":"5020",
    "sg:province":"Salzburg",
    "wof:name":"Geib VTG - Veranstaltungs-Technik",
    "wof:placetype":"venue"
},
  "geometry": {"coordinates":[13.0495281219,47.8087806702],"type":"Point"}
}