{
  "type": "Feature",
  "properties": {
    "addr:full":"Wiener Bundesstr 68 Pasching Ober\u00f6sterreich 4061",
    "addr:housenumber":"68",
    "addr:postcode":"4061",
    "addr:street":"Oberoesterreich",
    "iso:country":"AT",
    "sg:address":"Wiener Bundesstr 68",
    "sg:city":"Pasching",
    "sg:orig_category":"Massagen",
    "sg:phone":"+43 7229 64454",
    "sg:postcode":"4061",
    "sg:province":"Ober\u00f6sterreich",
    "wof:name":"Schlenhardt Silke",
    "wof:placetype":"venue"
},
  "geometry": {"coordinates":[14.2508029938,48.241607666],"type":"Point"}
}