{
  "type": "Feature",
  "properties": {
    "iso:country":"AT",
    "sg:address":"Bahnhofstr. 6",
    "sg:city":"Feldbach",
    "sg:classifiers":[
        {
            "category":"Manufacturing",
            "subcategory":"Paper Products",
            "type":"Manufacturing & Wholesale Goods"
        }
    ],
    "sg:phone":"+43 4331 5224350",
    "sg:postcode":"8330",
    "sg:province":"Steiermark",
    "sg:tags":[
        "cardboard"
    ],
    "wof:name":"KLIEMSTEIN PAPIERVERARBEITUNGS GES.MBH",
    "wof:placetype":"venue"
},
  "geometry": {"coordinates":[15.8907814026,46.958065033],"type":"Point"}
}