{
  "type": "Feature",
  "properties": {
    "addr:full":"Klingerstr 4 Wien Wien 1230",
    "addr:housenumber":"4",
    "addr:postcode":"1230",
    "addr:street":"Klingerstr",
    "iso:country":"AT",
    "sg:address":"Klingerstr 4",
    "sg:city":"Wien",
    "sg:orig_category":"Fenster",
    "sg:phone":"+43 4316 620224",
    "sg:postcode":"1230",
    "sg:province":"Wien",
    "wof:name":"Nutz Wolfgang",
    "wof:placetype":"venue"
},
  "geometry": {"coordinates":[16.3389530182,48.1486587524],"type":"Point"}
}