{
  "type": "Feature",
  "properties": {
    "addr:full":"Anton-Baumgartner-Str 125/2 Wien Wien 1230",
    "addr:housenumber":"125 / 2",
    "addr:postcode":"1230",
    "iso:country":"AT",
    "sg:address":"Anton-Baumgartner-Str 125/2",
    "sg:city":"Wien",
    "sg:orig_category":"Ingenieurkonsulenten / Zivilingenieure",
    "sg:phone":"+43 4319 828630",
    "sg:postcode":"1230",
    "sg:province":"Wien",
    "wof:name":"Buchner Roland Dr Ziviltechniker GmbH",
    "wof:placetype":"venue"
},
  "geometry": {"coordinates":[16.3152484894,48.1504364014],"type":"Point"}
}