{
  "type": "Feature",
  "properties": {
    "iso:country":"AT",
    "sg:address":"Hollandstrasse 20",
    "sg:city":"Wien",
    "sg:classifiers":[
        {
            "category":"Professional",
            "subcategory":"Printing & Photocopies",
            "type":"Services"
        }
    ],
    "sg:phone":"+43 1 2142900",
    "sg:postcode":"1020",
    "sg:province":"Wien",
    "sg:tags":[
        "digital"
    ],
    "sg:website":"produktionswerkstatt.at",
    "wof:name":"Produktionswerkstatt Thomas Kuhn und Mathias Koll OEG",
    "wof:placetype":"venue"
},
  "geometry": {"coordinates":[16.3777313232,48.2166595459],"type":"Point"}
}