{
  "type": "Feature",
  "properties": {
    "addr:full":"B\u00f6hmerstr 4 Bad Leonfelden Ober\u00f6sterreich 4190",
    "addr:housenumber":"4",
    "addr:postcode":"4190",
    "addr:street":"Boehmerstr",
    "iso:country":"AT",
    "sg:address":"B\u00f6hmerstr 4",
    "sg:city":"Bad Leonfelden",
    "sg:orig_category":"Innenarchitekten",
    "sg:phone":"+43 4372 1320555",
    "sg:postcode":"4190",
    "sg:province":"Ober\u00f6sterreich",
    "wof:name":"Wohn Design Brandstetter G\u00fcnther",
    "wof:placetype":"venue"
},
  "geometry": {"coordinates":[14.2929935455,48.5229225159],"type":"Point"}
}