{
  "type": "Feature",
  "properties": {
    "iso:country":"AT",
    "sg:address":"Minoritenpl 5",
    "sg:city":"Neunkirchen",
    "sg:orig_category":"Unterhaltungselektronik / Einzelhandel",
    "sg:phone":"+43 2635 63187",
    "sg:postcode":"2620",
    "sg:province":"Nieder\u00f6sterreich",
    "wof:name":"Auer Roland",
    "wof:placetype":"venue"
},
  "geometry": {"coordinates":[16.0795288086,47.7223243713],"type":"Point"}
}