{
  "type": "Feature",
  "properties": {
    "addr:full":"Engerthstr 191/2 Wien Wien 1020",
    "addr:housenumber":"191 / 2",
    "addr:postcode":"1020",
    "iso:country":"AT",
    "sg:address":"Engerthstr 191/2",
    "sg:city":"Wien",
    "sg:orig_category":"\u00c3\u201erzte / F Allgemeinmedizin",
    "sg:phone":"+43 1 7280300",
    "sg:postcode":"1020",
    "sg:province":"Wien",
    "wof:name":"Azem Huda MedR Dr",
    "wof:placetype":"venue"
},
  "geometry": {"coordinates":[16.4059658051,48.2226104736],"type":"Point"}
}