{
  "type": "Feature",
  "properties": {
    "addr:full":"Nr 493 Z\u00fcrs Vorarlberg 6763",
    "addr:postcode":"6763",
    "addr:street":"Nr 493 Zuers",
    "iso:country":"AT",
    "sg:address":"Nr 493",
    "sg:city":"Z\u00fcrs",
    "sg:orig_category":"Bankomat-Standorte",
    "sg:phone":"+43 5583 26260",
    "sg:postcode":"6763",
    "sg:province":"Vorarlberg",
    "wof:name":"Bankomat d Raiffeisenbank Lech/Arlberg",
    "wof:placetype":"venue"
},
  "geometry": {"coordinates":[8.7782497406,46.5036811829],"type":"Point"}
}