{
  "type": "Feature",
  "properties": {
    "addr:full":"Tannenweg 3 Krenglbach Ober\u00f6sterreich 4631",
    "addr:housenumber":"3",
    "addr:postcode":"4631",
    "addr:street":"Tannenweg",
    "iso:country":"AT",
    "sg:address":"Tannenweg 3",
    "sg:city":"Krenglbach",
    "sg:classifiers":[
        {
            "category":"Landmark",
            "subcategory":"Fountain",
            "type":"Public Place"
        }
    ],
    "sg:phone":"+43 7249 46840",
    "sg:postcode":"4631",
    "sg:province":"Ober\u00f6sterreich",
    "wof:name":"HEISSNER Gartenausstattungs-Ges.m.b.H.",
    "wof:placetype":"venue"
},
  "geometry": {"coordinates":[13.9647550583,48.192615509],"type":"Point"}
}