{
  "type": "Feature",
  "properties": {
    "addr:full":"Zerstreut 6 T Hochwolkersdorf Nieder\u00f6sterreich 2802",
    "addr:housenumber":"6 t",
    "addr:postcode":"2802",
    "addr:street":"Zerstreut",
    "iso:country":"AT",
    "sg:address":"Zerstreut 6 T",
    "sg:city":"Hochwolkersdorf",
    "sg:classifiers":[
        {
            "category":"Professional",
            "subcategory":"Detective & Security Services",
            "type":"Services"
        }
    ],
    "sg:phone":"+43 2645 8240",
    "sg:postcode":"2802",
    "sg:province":"Nieder\u00f6sterreich",
    "sg:tags":[
        "access",
        "control",
        "ac",
        "system"
    ],
    "sg:website":"alarmsystem.at",
    "wof:name":"ALARMSYSTEM GmbH",
    "wof:placetype":"venue"
},
  "geometry": {"coordinates":[16.2806987762,47.6611976624],"type":"Point"}
}