{
  "type": "Feature",
  "properties": {
    "addr:full":"Gleichenberg Dorf 20 Bad Gleichenberg Steiermark 8344",
    "addr:housenumber":"20",
    "addr:postcode":"8344",
    "addr:street":"Gleichenberg Dorf",
    "iso:country":"AT",
    "sg:address":"Gleichenberg Dorf 20",
    "sg:city":"Bad Gleichenberg",
    "sg:classifiers":[
        {
            "category":"Manufacturing",
            "subcategory":"Metals",
            "type":"Manufacturing & Wholesale Goods"
        }
    ],
    "sg:phone":"+43 4331 5924040",
    "sg:postcode":"8344",
    "sg:province":"Steiermark",
    "sg:tags":[
        "metallurgy",
        "metalworking"
    ],
    "wof:name":"HARALD KIEFER GMBH",
    "wof:placetype":"venue"
},
  "geometry": {"coordinates":[15.8838062286,46.8935546875],"type":"Point"}
}