{
  "type": "Feature",
  "properties": {
    "addr:full":"Nr 28/1 Kaindorf Steiermark 8224",
    "addr:housenumber":"1",
    "addr:postcode":"8224",
    "addr:street":"Nr 28 /",
    "iso:country":"AT",
    "sg:address":"Nr 28/1",
    "sg:city":"Kaindorf",
    "sg:orig_category":"Friseure U Frisiersalons",
    "sg:phone":"+43 4333 342811",
    "sg:postcode":"8224",
    "sg:province":"Steiermark",
    "wof:name":"Friseur Haareszeiten - M\u00fcller Erwin",
    "wof:placetype":"venue"
},
  "geometry": {"coordinates":[15.9089851379,47.2246704102],"type":"Point"}
}