{
  "type": "Feature",
  "properties": {
    "addr:full":"Bad Wimsbach-Neydharting Ober\u00f6sterreich 4654",
    "addr:housenumber":"wimsbach-neydharting",
    "addr:postcode":"4654",
    "iso:country":"AT",
    "sg:city":"Bad Wimsbach-Neydharting",
    "sg:orig_category":"Feuerwehren",
    "sg:phone":"+43 7245 25229",
    "sg:postcode":"4654",
    "sg:province":"Ober\u00f6sterreich",
    "wof:name":"Freiwillige Feuerwehr Bergham K\u00f6\u00dflwang",
    "wof:placetype":"venue"
},
  "geometry": {"coordinates":[13.9008865356,48.0625839233],"type":"Point"}
}