{
  "type": "Feature",
  "properties": {
    "iso:country":"AT",
    "sg:address":"Nr 84",
    "sg:city":"St. Martin",
    "sg:orig_category":"Raumausstattung",
    "sg:phone":"+43 4366 42667760",
    "sg:postcode":"5092",
    "sg:province":"Salzburg",
    "wof:name":"Grill Silvio",
    "wof:placetype":"venue"
},
  "geometry": {"coordinates":[12.7057151794,47.5662536621],"type":"Point"}
}