{
  "type": "Feature",
  "properties": {
    "addr:full":"Am Markt 21 Orth an der Donau Nieder\u00f6sterreich 2304",
    "addr:housenumber":"21",
    "addr:postcode":"2304",
    "addr:street":"Am Markt",
    "iso:country":"AT",
    "sg:address":"Am Markt 21",
    "sg:city":"Orth an der Donau",
    "sg:orig_category":"Banken U Sparkassen",
    "sg:phone":"+43 4322 1223810",
    "sg:postcode":"2304",
    "sg:province":"Nieder\u00f6sterreich",
    "wof:name":"Raiffeisenkasse Orth a d Donau regGenmbH",
    "wof:placetype":"venue"
},
  "geometry": {"coordinates":[16.7032718658,48.1465187073],"type":"Point"}
}