{
  "type": "Feature",
  "properties": {
    "addr:full":"Brucknerstr 34 St. Valentin Nieder\u00f6sterreich 4300",
    "addr:housenumber":"34",
    "addr:postcode":"4300",
    "addr:street":"Brucknerstr",
    "iso:country":"AT",
    "sg:address":"Brucknerstr 34",
    "sg:city":"St. Valentin",
    "sg:orig_category":"Rauchfangkehrer",
    "sg:phone":"+43 7435 52050",
    "sg:postcode":"4300",
    "sg:province":"Nieder\u00f6sterreich",
    "wof:name":"Lechner Ludwig",
    "wof:placetype":"venue"
},
  "geometry": {"coordinates":[14.53881073,48.1768608093],"type":"Point"}
}