{
  "type": "Feature",
  "properties": {
    "iso:country":"AT",
    "sg:address":"Weierfing 73",
    "sg:city":"St. Martin im Innkreis",
    "sg:orig_category":"Medien, Werbung, Marketing, Pr",
    "sg:phone":"+43 7752 87284",
    "sg:postcode":"4973",
    "sg:province":"Ober\u00f6sterreich",
    "sg:website":"http://members.magnet.at/users/e.d./",
    "wof:name":"MULTIMEDIA",
    "wof:placetype":"venue"
},
  "geometry": {"coordinates":[176.29011535640001,-40.2553482056],"type":"Point"}
}