{
  "type": "Feature",
  "properties": {
    "addr:full":"Mariazeller Str 51 Traisen Nieder\u00f6sterreich 3160",
    "addr:postcode":"3160",
    "addr:street":"Str 51",
    "iso:country":"AT",
    "sg:address":"Mariazeller Str 51",
    "sg:city":"Traisen",
    "sg:orig_category":"Fahrschulen",
    "sg:phone":"+43 2762 65035",
    "sg:postcode":"3160",
    "sg:province":"Nieder\u00f6sterreich",
    "wof:name":"Fahrschule Ing Mayer",
    "wof:placetype":"venue"
},
  "geometry": {"coordinates":[15.609459877,48.0424346924],"type":"Point"}
}