{
  "type": "Feature",
  "properties": {
    "addr:full":"Marktpl 11 Gansbach Nieder\u00f6sterreich 3122",
    "addr:housenumber":"11",
    "addr:postcode":"3122",
    "addr:street":"Marktpl",
    "iso:country":"AT",
    "sg:address":"Marktpl 11",
    "sg:city":"Gansbach",
    "sg:orig_category":"Gemeinden",
    "sg:phone":"+43 4327 53275",
    "sg:postcode":"3122",
    "sg:province":"Nieder\u00f6sterreich",
    "wof:name":"Gemeindeamt d Marktgde Dunkelsteinerwald i Gansbach",
    "wof:placetype":"venue"
},
  "geometry": {"coordinates":[15.4724578857,48.306312561],"type":"Point"}
}