{
  "type": "Feature",
  "properties": {
    "addr:full":"Lindaustr 17 Bad Ischl Ober\u00f6sterreich 4820",
    "addr:housenumber":"17",
    "addr:postcode":"4820",
    "addr:street":"Lindaustr",
    "iso:country":"AT",
    "sg:address":"Lindaustr 17",
    "sg:city":"Bad Ischl",
    "sg:orig_category":"Ergotherapie",
    "sg:phone":"+43 664 1045325",
    "sg:postcode":"4820",
    "sg:province":"Ober\u00f6sterreich",
    "wof:name":"Wieder Roswitha",
    "wof:placetype":"venue"
},
  "geometry": {"coordinates":[13.60638237,47.7089996338],"type":"Point"}
}