{
  "type": "Feature",
  "properties": {
    "addr:full":"Seestr 19 Natters Tirol 6161",
    "addr:housenumber":"19",
    "addr:postcode":"6161",
    "addr:street":"Seestr;Tirol",
    "iso:country":"AT",
    "sg:address":"Seestr 19",
    "sg:city":"Natters",
    "sg:orig_category":"Freizeitangebote U -Einrichtungen",
    "sg:phone":"+43 512 546710",
    "sg:postcode":"6161",
    "sg:province":"Tirol",
    "wof:name":"Raiffeisensportzentrum Natters",
    "wof:placetype":"venue"
},
  "geometry": {"coordinates":[11.3658161163,47.2351150513],"type":"Point"}
}