{
  "type": "Feature",
  "properties": {
    "addr:full":"Schulstr 5 Bad Hall Ober\u00f6sterreich 4540",
    "addr:housenumber":"5",
    "addr:postcode":"4540",
    "addr:street":"Schulstr",
    "iso:country":"AT",
    "sg:address":"Schulstr 5",
    "sg:city":"Bad Hall",
    "sg:orig_category":"Pensionen / Privatzimmer",
    "sg:phone":"+43 7258 2216",
    "sg:postcode":"4540",
    "sg:province":"Ober\u00f6sterreich",
    "wof:name":"Pension Albrecht",
    "wof:placetype":"venue"
},
  "geometry": {"coordinates":[14.2060623169,48.0372428894],"type":"Point"}
}