{
  "type": "Feature",
  "properties": {
    "addr:full":"Hauptstrasse 39  Sachsenburg K\u00e4rnten 9751",
    "addr:housenumber":"39",
    "addr:postcode":"9751",
    "addr:street":"Hauptstrasse;Kaernten",
    "iso:country":"AT",
    "sg:address":"Hauptstrasse 39 ",
    "sg:city":"Sachsenburg",
    "sg:classifiers":[
        {
            "category":"Government",
            "subcategory":"Fire Station",
            "type":"Public Place"
        }
    ],
    "sg:phone":"+43 4769 2551",
    "sg:postcode":"9751",
    "sg:province":"K\u00e4rnten",
    "sg:tags":[
        "supraregional",
        "plant",
        "installation",
        "heating"
    ],
    "wof:name":"Sepp Laber",
    "wof:placetype":"venue"
},
  "geometry": {"coordinates":[13.3556489944,46.8307151794],"type":"Point"}
}