{
  "type": "Feature",
  "properties": {
    "iso:country":"AT",
    "sg:address":"Rathausstr 11",
    "sg:city":"Ebenfurth",
    "sg:orig_category":"Schilder",
    "sg:phone":"+43 2624 52610",
    "sg:postcode":"2490",
    "sg:province":"Nieder\u00f6sterreich",
    "wof:name":"Stempel-Heinzel GesmbH",
    "wof:placetype":"venue"
},
  "geometry": {"coordinates":[16.3735294342,47.877281189],"type":"Point"}
}