{
  "type": "Feature",
  "properties": {
    "addr:full":"Grazer Str 241 Frauental an der La\u00dfnitz Steiermark 8523",
    "addr:housenumber":"241",
    "addr:postcode":"8523",
    "iso:country":"AT",
    "sg:address":"Grazer Str 241",
    "sg:city":"Frauental an der La\u00dfnitz",
    "sg:orig_category":"Lebensmittel / Einzelhandel",
    "sg:phone":"+43 4334 622508",
    "sg:postcode":"8523",
    "sg:province":"Steiermark",
    "wof:name":"ADEG Markt Greben Rosalia",
    "wof:placetype":"venue"
},
  "geometry": {"coordinates":[15.2548007965,46.8248329163],"type":"Point"}
}