{
  "type": "Feature",
  "properties": {
    "addr:full":"Wiener Str 51 Wiener Neustadt Nieder\u00f6sterreich 2700",
    "addr:postcode":"2700",
    "addr:street":"51",
    "iso:country":"AT",
    "sg:address":"Wiener Str 51",
    "sg:city":"Wiener Neustadt",
    "sg:orig_category":"Autohandel",
    "sg:phone":"+43 2622 241080",
    "sg:postcode":"2700",
    "sg:province":"Nieder\u00f6sterreich",
    "wof:name":"Autohaus Edgar Maurer",
    "wof:placetype":"venue"
},
  "geometry": {"coordinates":[16.2451057434,47.8180503845],"type":"Point"}
}