{
  "type": "Feature",
  "properties": {
    "iso:country":"AT",
    "sg:address":"Stra\u00dfenh\u00e4user 66",
    "sg:city":"Koblach",
    "sg:orig_category":"Bars-Cafes",
    "sg:phone":"+43 664 5453262",
    "sg:postcode":"6842",
    "sg:province":"Vorarlberg",
    "wof:name":"Finkst\u00fcble - cafe-bstro-bar",
    "wof:placetype":"venue"
},
  "geometry": {"coordinates":[9.6024236679,47.3305778503],"type":"Point"}
}