{
  "type": "Feature",
  "properties": {
    "addr:full":"Kircheng 12 Steyr Ober\u00f6sterreich 4400",
    "addr:housenumber":"12",
    "addr:postcode":"4400",
    "addr:street":"Kircheng;Oberoesterreich",
    "iso:country":"AT",
    "sg:address":"Kircheng 12",
    "sg:city":"Steyr",
    "sg:orig_category":"Partnervermittlung",
    "sg:phone":"+43 7252 87909",
    "sg:postcode":"4400",
    "sg:province":"Ober\u00f6sterreich",
    "wof:name":"Gl\u00fcckshafen",
    "wof:placetype":"venue"
},
  "geometry": {"coordinates":[14.4199333191,48.04347229],"type":"Point"}
}