{
  "type": "Feature",
  "properties": {
    "addr:full":"Ignaz Glaser-Str 24 B\u00fcrmoos Salzburg 5111",
    "addr:housenumber":"24",
    "addr:postcode":"5111",
    "addr:street":"Ignaz Glaser-Str",
    "iso:country":"AT",
    "sg:address":"Ignaz Glaser-Str 24",
    "sg:city":"B\u00fcrmoos",
    "sg:orig_category":"Blumeneinzelhandel",
    "sg:phone":"+43 6274 6245",
    "sg:postcode":"5111",
    "sg:province":"Salzburg",
    "wof:name":"Blumen Kager",
    "wof:placetype":"venue"
},
  "geometry": {"coordinates":[12.9242372513,47.983127594],"type":"Point"}
}