{
  "type": "Feature",
  "properties": {
    "addr:full":"Huttengasse 43 Wien Wien 1160",
    "addr:housenumber":"43",
    "addr:postcode":"1160",
    "addr:street":"Huttengasse",
    "iso:country":"AT",
    "sg:address":"Huttengasse 43",
    "sg:city":"Wien",
    "sg:classifiers":[
        {
            "category":"Wholesale",
            "subcategory":"Construction Materials",
            "type":"Manufacturing & Wholesale Goods"
        }
    ],
    "sg:phone":"+43 1 9822213",
    "sg:postcode":"1160",
    "sg:province":"Wien",
    "sg:tags":[
        "roadway",
        "chip",
        "spreader"
    ],
    "sg:website":"froestl.cc",
    "wof:name":"Josef Fr\u00f6stl Ges.m.b.H.",
    "wof:placetype":"venue"
},
  "geometry": {"coordinates":[16.3088874817,48.2070159912],"type":"Point"}
}