{
  "type": "Feature",
  "properties": {
    "addr:full":"Nr 7 Ybbsitz Nieder\u00f6sterreich 3341",
    "addr:postcode":"3341",
    "addr:street":"Nr;Niederoesterreich",
    "iso:country":"AT",
    "sg:address":"Nr 7",
    "sg:city":"Ybbsitz",
    "sg:orig_category":"Erdbau",
    "sg:phone":"+43 4374 4386330",
    "sg:postcode":"3341",
    "sg:province":"Nieder\u00f6sterreich",
    "wof:name":"EHF Maulwurftechnik - Erdbau Franz Henikl",
    "wof:placetype":"venue"
},
  "geometry": {"coordinates":[14.8938436508,47.9479408264],"type":"Point"}
}