{
  "type": "Feature",
  "properties": {
    "iso:country":"AT",
    "sg:address":"Franz-Josef-Str 20",
    "sg:city":"Gleisdorf",
    "sg:orig_category":"Tankstellen",
    "sg:phone":"+43 4331 1232250",
    "sg:postcode":"8200",
    "sg:province":"Steiermark",
    "wof:name":"Shell Austria GmbH",
    "wof:placetype":"venue"
},
  "geometry": {"coordinates":[15.713300705,47.1023521423],"type":"Point"}
}