{
  "type": "Feature",
  "properties": {
    "iso:country":"AT",
    "sg:address":"Bergg 13",
    "sg:city":"Prottes",
    "sg:orig_category":"Baumeister",
    "sg:phone":"+43 2282 5076",
    "sg:postcode":"2242",
    "sg:province":"Nieder\u00f6sterreich",
    "wof:name":"planbauwerk Planungs-u BaugesmbH",
    "wof:placetype":"venue"
},
  "geometry": {"coordinates":[16.739074707,48.3932418823],"type":"Point"}
}