{
  "type": "Feature",
  "properties": {
    "addr:full":"Gersthofer Str 26 Wien Wien 1180",
    "addr:postcode":"1180",
    "addr:street":"Str 26",
    "iso:country":"AT",
    "sg:address":"Gersthofer Str 26",
    "sg:city":"Wien",
    "sg:orig_category":"Fotoapparate U -Artikel / Einzelhandel",
    "sg:phone":"+43 4314 793387",
    "sg:postcode":"1180",
    "sg:province":"Wien",
    "wof:name":"Foto Herbeck",
    "wof:placetype":"venue"
},
  "geometry": {"coordinates":[16.3278198242,48.2342262268],"type":"Point"}
}