{
  "type": "Feature",
  "properties": {
    "addr:full":"Garbweg 1 Steyr Ober\u00f6sterreich 4400",
    "addr:housenumber":"1",
    "addr:postcode":"4400",
    "addr:street":"Garbweg;Oberoesterreich",
    "iso:country":"AT",
    "sg:address":"Garbweg 1",
    "sg:city":"Steyr",
    "sg:orig_category":"Garten- U Landschaftsgestaltung",
    "sg:phone":"+43 4365 06070200",
    "sg:postcode":"4400",
    "sg:province":"Ober\u00f6sterreich",
    "wof:name":"BIOASE Gartengestaltung-Gartenpflege Rudolf Rauscher",
    "wof:placetype":"venue"
},
  "geometry": {"coordinates":[14.4397945404,48.0226364136],"type":"Point"}
}