{
  "type": "Feature",
  "properties": {
    "iso:country":"AT",
    "sg:address":"M\u00fchleng 8",
    "sg:city":"Enzersfeld",
    "sg:orig_category":"Fenster",
    "sg:phone":"+43 2262 673372",
    "sg:postcode":"2202",
    "sg:province":"Nieder\u00f6sterreich",
    "wof:name":"Trawniczek Franz",
    "wof:placetype":"venue"
},
  "geometry": {"coordinates":[16.4239807129,48.3615112305],"type":"Point"}
}