{
  "type": "Feature",
  "properties": {
    "addr:full":"Seidlwinklstr 9 Rauris Salzburg 5661",
    "addr:housenumber":"9",
    "addr:postcode":"5661",
    "addr:street":"Seidlwinklstr;Salzburg",
    "iso:country":"AT",
    "sg:address":"Seidlwinklstr 9",
    "sg:city":"Rauris",
    "sg:orig_category":"Maler, Anstreicher U Lackierer",
    "sg:phone":"+43 4365 446408",
    "sg:postcode":"5661",
    "sg:province":"Salzburg",
    "wof:name":"Sommerer Horst",
    "wof:placetype":"venue"
},
  "geometry": {"coordinates":[12.963681221,47.195186615],"type":"Point"}
}