{
  "type": "Feature",
  "properties": {
    "addr:full":"Bahnhofstr 11a Leibnitz Steiermark 8430",
    "addr:housenumber":"11a",
    "addr:postcode":"8430",
    "addr:street":"Bahnhofstr;Steiermark",
    "iso:country":"AT",
    "sg:address":"Bahnhofstr 11a",
    "sg:city":"Leibnitz",
    "sg:orig_category":"Sonnenstudios",
    "sg:phone":"+43 3452 71450",
    "sg:postcode":"8430",
    "sg:province":"Steiermark",
    "wof:name":"Michis Sonnenstudio",
    "wof:placetype":"venue"
},
  "geometry": {"coordinates":[15.5439395905,46.7824821472],"type":"Point"}
}