{
  "type": "Feature",
  "properties": {
    "iso:country":"AT",
    "sg:address":"Sternhofweg 25a",
    "sg:city":"Salzburg",
    "sg:orig_category":"Bekleidung / Erzeugung U Gro\u00c3\u0178handel",
    "sg:phone":"+43 4366 2823101",
    "sg:postcode":"5020",
    "sg:province":"Salzburg",
    "wof:name":"Weiss Ellen",
    "wof:placetype":"venue"
},
  "geometry": {"coordinates":[13.0408802032,47.8001327515],"type":"Point"}
}