{
  "type": "Feature",
  "properties": {
    "addr:full":"Ruhringsdorf 7 Hofkirchen an der Trattnach Ober\u00f6sterreich 4716",
    "addr:housenumber":"7",
    "addr:postcode":"4716",
    "addr:street":"Ruhringsdorf",
    "iso:country":"AT",
    "sg:address":"Ruhringsdorf 7",
    "sg:city":"Hofkirchen an der Trattnach",
    "sg:orig_category":"Tischlereien",
    "sg:phone":"+43 7734 2948",
    "sg:postcode":"4716",
    "sg:province":"Ober\u00f6sterreich",
    "wof:name":"Wilflingseder Tischlerei GesmbH",
    "wof:placetype":"venue"
},
  "geometry": {"coordinates":[13.7364902496,48.2039413452],"type":"Point"}
}