{
  "type": "Feature",
  "properties": {
    "addr:full":"Bahnstr 19 Fulpmes Tirol 6166",
    "addr:housenumber":"19",
    "addr:postcode":"6166",
    "addr:street":"Bahnstr;Tirol",
    "iso:country":"AT",
    "sg:address":"Bahnstr 19",
    "sg:city":"Fulpmes",
    "sg:orig_category":"Juweliere, Gold- U Silberschmiede",
    "sg:phone":"+43 5225 64553",
    "sg:postcode":"6166",
    "sg:province":"Tirol",
    "wof:name":"Pirkner-Kunst-Schmuck-Design GmbH",
    "wof:placetype":"venue"
},
  "geometry": {"coordinates":[11.3484296799,47.1538162231],"type":"Point"}
}