{
  "type": "Feature",
  "properties": {
    "addr:full":"Forststr 14b Lustenau Vorarlberg 6890",
    "addr:housenumber":"14b",
    "addr:postcode":"6890",
    "addr:street":"Forststr",
    "iso:country":"AT",
    "sg:address":"Forststr 14b",
    "sg:city":"Lustenau",
    "sg:orig_category":"Transportunternehmen",
    "sg:phone":"+43 4355 7783593",
    "sg:postcode":"6890",
    "sg:province":"Vorarlberg",
    "wof:name":"Gunz Walter",
    "wof:placetype":"venue"
},
  "geometry": {"coordinates":[9.6622619629,47.4115943909],"type":"Point"}
}