{
  "type": "Feature",
  "properties": {
    "addr:full":"Faistenau 107 Faistenau Salzburg 5324",
    "addr:housenumber":"107",
    "addr:postcode":"5324",
    "addr:street":"Faistenau;Salzburg",
    "iso:country":"AT",
    "sg:address":"Faistenau 107",
    "sg:city":"Faistenau",
    "sg:classifiers":[
        {
            "category":"Home & Garden",
            "subcategory":"Carpets & Floor Coverings",
            "type":"Retail Goods"
        }
    ],
    "sg:phone":"+43 6228 2344",
    "sg:postcode":"5324",
    "sg:province":"Salzburg",
    "sg:tags":[
        "stone",
        "natural",
        "panel"
    ],
    "wof:name":"Natursteinbau Schmei\u00dfner",
    "wof:placetype":"venue"
},
  "geometry": {"coordinates":[13.2332620621,47.7780952454],"type":"Point"}
}