{
  "type": "Feature",
  "properties": {
    "addr:full":"Flughafen Wien Schwechat Obj 102/B104/104A Wien Wien 1300",
    "addr:housenumber":"102 / b104 / 104a",
    "addr:postcode":"1300",
    "addr:street":"Obj",
    "iso:country":"AT",
    "sg:address":"Flughafen Wien Schwechat Obj 102/B104/104A",
    "sg:city":"Wien",
    "sg:orig_category":"Wechselstuben",
    "sg:phone":"+43 4317 00735632",
    "sg:postcode":"1300",
    "sg:province":"Wien",
    "wof:name":"GOFFIN CHANGE Wechselstuben GmbH",
    "wof:placetype":"venue"
},
  "geometry": {"coordinates":[16.5561008453,48.1137504578],"type":"Point"}
}