{
  "type": "Feature",
  "properties": {
    "iso:country":"AT",
    "sg:address":"Bezirksgerichtsg 5",
    "sg:city":"Obernberg am Inn",
    "sg:orig_category":"Gerichte",
    "sg:phone":"+43 7758 22260",
    "sg:postcode":"4982",
    "sg:province":"Ober\u00f6sterreich",
    "wof:name":"Bezirksgericht Obernberg am Inn",
    "wof:placetype":"venue"
},
  "geometry": {"coordinates":[13.3348798752,48.3221435547],"type":"Point"}
}