{
  "type": "Feature",
  "properties": {
    "iso:country":"AT",
    "sg:address":"Markt 326",
    "sg:city":"Litzelsdorf",
    "sg:orig_category":"Ingenieurkonsulenten / Zivilingenieure",
    "sg:phone":"+43 3358 2050",
    "sg:postcode":"7532",
    "sg:province":"Burgenland",
    "wof:name":"Kath Dieter Dipl-Ing",
    "wof:placetype":"venue"
},
  "geometry": {"coordinates":[16.1615982056,47.2041702271],"type":"Point"}
}