{
  "type": "Feature",
  "properties": {
    "addr:full":"Auhofstr 123 Wien Wien 1130",
    "addr:housenumber":"123",
    "addr:postcode":"1130",
    "iso:country":"AT",
    "sg:address":"Auhofstr 123",
    "sg:city":"Wien",
    "sg:orig_category":"Schuhmachereien",
    "sg:phone":"+43 1 8761684",
    "sg:postcode":"1130",
    "sg:province":"Wien",
    "wof:name":"Preischl Peter",
    "wof:placetype":"venue"
},
  "geometry": {"coordinates":[16.273317337,48.1903266907],"type":"Point"}
}