{
  "type": "Feature",
  "properties": {
    "addr:full":"Gewerbegebiet Stra\u00df 4 Eugendorf Salzburg 5301",
    "addr:housenumber":"4",
    "addr:postcode":"5301",
    "addr:street":"Gewerbegebiet Strass;Salzburg",
    "iso:country":"AT",
    "sg:address":"Gewerbegebiet Stra\u00df 4",
    "sg:city":"Eugendorf",
    "sg:orig_category":"Handelsagenturen",
    "sg:phone":"+43 6225 7960",
    "sg:postcode":"5301",
    "sg:province":"Salzburg",
    "wof:name":"Hauser Manfred",
    "wof:placetype":"venue"
},
  "geometry": {"coordinates":[13.1289167404,47.8604278564],"type":"Point"}
}