{
  "type": "Feature",
  "properties": {
    "addr:full":"Ottendorf 14 Strengberg Nieder\u00f6sterreich 3314",
    "addr:housenumber":"14",
    "addr:postcode":"3314",
    "addr:street":"Ottendorf",
    "iso:country":"AT",
    "sg:address":"Ottendorf 14",
    "sg:city":"Strengberg",
    "sg:classifiers":[
        {
            "category":"Juice Bar",
            "subcategory":"None",
            "type":"Food & Drink"
        }
    ],
    "sg:phone":"+43 7432 2477",
    "sg:postcode":"3314",
    "sg:province":"Nieder\u00f6sterreich",
    "sg:tags":[
        "apple"
    ],
    "sg:website":"mostviertel.com/naturladen",
    "wof:name":"Wastlbauer",
    "wof:placetype":"venue"
},
  "geometry": {"coordinates":[14.673576355,48.1380157471],"type":"Point"}
}