{
  "type": "Feature",
  "properties": {
    "addr:full":"Eisenst\u00e4dter Str 23 Neufeld an der Leitha Burgenland 2491",
    "addr:housenumber":"23",
    "addr:postcode":"2491",
    "addr:street":"Str",
    "iso:country":"AT",
    "sg:address":"Eisenst\u00e4dter Str 23",
    "sg:city":"Neufeld an der Leitha",
    "sg:orig_category":"Tabaktrafiken",
    "sg:phone":"+43 4326 2452189",
    "sg:postcode":"2491",
    "sg:province":"Burgenland",
    "wof:name":"Weiss Silvia",
    "wof:placetype":"venue"
},
  "geometry": {"coordinates":[16.3819828033,47.8655967712],"type":"Point"}
}