{
  "type": "Feature",
  "properties": {
    "addr:full":"Alxingerg 7 Wien Wien 1100",
    "addr:housenumber":"7",
    "addr:postcode":"1100",
    "addr:street":"Alxingerg",
    "iso:country":"AT",
    "sg:address":"Alxingerg 7",
    "sg:city":"Wien",
    "sg:orig_category":"Lebensmittel / Einzelhandel",
    "sg:phone":"+43 4319 612410",
    "sg:postcode":"1100",
    "sg:province":"Wien",
    "wof:name":"Billa AG",
    "wof:placetype":"venue"
},
  "geometry": {"coordinates":[16.3686885834,48.1806335449],"type":"Point"}
}