{
  "type": "Feature",
  "properties": {
    "addr:full":"Porscheweg 9 Hallein Salzburg 5400",
    "addr:housenumber":"9",
    "addr:postcode":"5400",
    "addr:street":"Porscheweg;Salzburg",
    "iso:country":"AT",
    "sg:address":"Porscheweg 9",
    "sg:city":"Hallein",
    "sg:orig_category":"Autohandel",
    "sg:phone":"+43 6245 833330",
    "sg:postcode":"5400",
    "sg:province":"Salzburg",
    "wof:name":"Porsche Inter Auto KG - Zweigniederlassung Porsche Hallein",
    "wof:placetype":"venue"
},
  "geometry": {"coordinates":[13.1031675339,47.6831626892],"type":"Point"}
}