{
  "type": "Feature",
  "properties": {
    "addr:full":"Kirchpl 1 Moosburg K\u00e4rnten 9062",
    "addr:housenumber":"1",
    "addr:postcode":"9062",
    "addr:street":"Kirchpl;Kaernten",
    "iso:country":"AT",
    "sg:address":"Kirchpl 1",
    "sg:city":"Moosburg",
    "sg:orig_category":"Gemeinden",
    "sg:phone":"+43 4272 834000",
    "sg:postcode":"9062",
    "sg:province":"K\u00e4rnten",
    "wof:name":"Marktgemeindeamt Moosburg",
    "wof:placetype":"venue"
},
  "geometry": {"coordinates":[14.1739091873,46.6571540833],"type":"Point"}
}