{
  "type": "Feature",
  "properties": {
    "iso:country":"AT",
    "sg:address":"Landstra\u00dfer Hauptstrasse 99-101",
    "sg:city":"Wien",
    "sg:classifiers":[
        {
            "category":"Building & Trades",
            "subcategory":"Locksmith",
            "type":"Services"
        }
    ],
    "sg:phone":"+43 1 7129939",
    "sg:postcode":"1030",
    "sg:province":"Wien",
    "wof:name":"Ashraf Omran",
    "wof:placetype":"venue"
},
  "geometry": {"coordinates":[16.3949203491,48.1985054016],"type":"Point"}
}