{
  "type": "Feature",
  "properties": {
    "addr:full":"Nr 61 St. Jakob im Rosental K\u00e4rnten 9184",
    "addr:postcode":"9184",
    "addr:street":"Nr 61",
    "iso:country":"AT",
    "sg:address":"Nr 61",
    "sg:city":"St. Jakob im Rosental",
    "sg:orig_category":"Autoreparatur",
    "sg:phone":"+43 4253 4800",
    "sg:postcode":"9184",
    "sg:province":"K\u00e4rnten",
    "wof:name":"Zwittnig Herbert",
    "wof:placetype":"venue"
},
  "geometry": {"coordinates":[14.0561933517,46.5476112366],"type":"Point"}
}