{
  "type": "Feature",
  "properties": {
    "addr:full":"Eisenstr 13 Kronstorf Ober\u00f6sterreich 4484",
    "addr:housenumber":"13",
    "addr:postcode":"4484",
    "addr:street":"Eisenstr",
    "iso:country":"AT",
    "sg:address":"Eisenstr 13",
    "sg:city":"Kronstorf",
    "sg:orig_category":"Wasseraufbereitung U -Reinigung",
    "sg:phone":"+43 4372 23815590",
    "sg:postcode":"4484",
    "sg:province":"Ober\u00f6sterreich",
    "wof:name":"Belebtes Wasser durch Grander-Technologie Helmut Lupp",
    "wof:placetype":"venue"
},
  "geometry": {"coordinates":[14.475812912,48.1719207764],"type":"Point"}
}