{
  "type": "Feature",
  "properties": {
    "iso:country":"AT",
    "sg:address":"Gangsteig 5",
    "sg:city":"Fuschl am See",
    "sg:orig_category":"Pensionen / Privatzimmer",
    "sg:phone":"+43 6226 8297",
    "sg:postcode":"5330",
    "sg:province":"Salzburg",
    "wof:name":"Pension F\u00fcsslhof",
    "wof:placetype":"venue"
},
  "geometry": {"coordinates":[13.3011293411,47.7961502075],"type":"Point"}
}