{
  "type": "Feature",
  "properties": {
    "iso:country":"AT",
    "sg:address":"Leharstr 6",
    "sg:city":"Gallspach",
    "sg:orig_category":"Psychotherapie",
    "sg:phone":"+43 7248 64089",
    "sg:postcode":"4713",
    "sg:province":"Ober\u00f6sterreich",
    "wof:name":"Kreutzer Erwin",
    "wof:placetype":"venue"
},
  "geometry": {"coordinates":[13.7983922958,48.2095718384],"type":"Point"}
}