{
  "type": "Feature",
  "properties": {
    "iso:country":"AT",
    "sg:address":"Nr 209",
    "sg:city":"Seefeld-Gro\u00dfkadolz",
    "sg:orig_category":"Maschinenhandel",
    "sg:phone":"+43 2943 2417",
    "sg:postcode":"2062",
    "sg:province":"Nieder\u00f6sterreich",
    "wof:name":"Bauer Carmen",
    "wof:placetype":"venue"
},
  "geometry": {"coordinates":[16.1749153137,48.7184638977],"type":"Point"}
}