{
  "type": "Feature",
  "properties": {
    "iso:country":"AT",
    "sg:address":"Marktpl 56",
    "sg:city":"Golling an der Salzach",
    "sg:classifiers":[
        {
            "category":"Travel",
            "subcategory":"Hotels & Motels",
            "type":"Entertainment"
        }
    ],
    "sg:phone":"+43 4362 4442200",
    "sg:postcode":"5440",
    "sg:province":"Salzburg",
    "wof:name":"Geniesserhotel Goldener Stern",
    "wof:placetype":"venue"
},
  "geometry": {"coordinates":[13.1677923203,47.5966644287],"type":"Point"}
}