{
  "type": "Feature",
  "properties": {
    "addr:full":"Herrenpl 3 St. P\u00f6lten Nieder\u00f6sterreich 3100",
    "addr:housenumber":"3",
    "addr:postcode":"3100",
    "addr:street":"Herrenpl",
    "iso:country":"AT",
    "sg:address":"Herrenpl 3",
    "sg:city":"St. P\u00f6lten",
    "sg:orig_category":"Galerien",
    "sg:phone":"+43 2742 354277",
    "sg:postcode":"3100",
    "sg:province":"Nieder\u00f6sterreich",
    "sg:website":"galerie-maringer.at",
    "wof:name":"Galerie Maringer - Zentrum der modernen Kunst",
    "wof:placetype":"venue"
},
  "geometry": {"coordinates":[-76.07303619379999,41.7845001221],"type":"Point"}
}