{
  "type": "Feature",
  "properties": {
    "iso:country":"AT",
    "sg:address":"Rathauspl 6",
    "sg:city":"Tulln an der Donau",
    "sg:orig_category":"Boutiquen",
    "sg:phone":"+43 2272 62356",
    "sg:postcode":"3430",
    "sg:province":"Nieder\u00f6sterreich",
    "wof:name":"La Mez - Mode Exclusive",
    "wof:placetype":"venue"
},
  "geometry": {"coordinates":[16.0533237457,48.330909729],"type":"Point"}
}