{
  "type": "Feature",
  "properties": {
    "iso:country":"AT",
    "sg:address":"Andreas Hofer-Str 9",
    "sg:city":"Salzburg",
    "sg:orig_category":"Autobusunternehmen",
    "sg:phone":"+43 662 46600",
    "sg:postcode":"5020",
    "sg:province":"Salzburg",
    "wof:name":"Postauto Competence-Center \u00d6sterreich",
    "wof:placetype":"venue"
},
  "geometry": {"coordinates":[13.0429019928,47.8207550049],"type":"Point"}
}