{
  "type": "Feature",
  "properties": {
    "addr:full":"Einersdorf 82 Bleiburg K\u00e4rnten 9150",
    "addr:housenumber":"82",
    "addr:postcode":"9150",
    "addr:street":"Einersdorf;Kaernten",
    "iso:country":"AT",
    "sg:address":"Einersdorf 82",
    "sg:city":"Bleiburg",
    "sg:orig_category":"Zahntechnische Laboratorien",
    "sg:phone":"+43 4235 44133",
    "sg:postcode":"9150",
    "sg:province":"K\u00e4rnten",
    "wof:name":"Zahntechnisches Labor Fantitsch Richard",
    "wof:placetype":"venue"
},
  "geometry": {"coordinates":[14.8006982803,46.5989685059],"type":"Point"}
}