{
  "type": "Feature",
  "properties": {
    "addr:full":"Wiener Str 60 Kapfenberg Steiermark 8605",
    "addr:postcode":"8605",
    "addr:street":"60",
    "iso:country":"AT",
    "sg:address":"Wiener Str 60",
    "sg:city":"Kapfenberg",
    "sg:orig_category":"Handelsagenturen",
    "sg:phone":"+43 3862 23972",
    "sg:postcode":"8605",
    "sg:province":"Steiermark",
    "wof:name":"ME Marketing Agency GesmbH",
    "wof:placetype":"venue"
},
  "geometry": {"coordinates":[15.2943658829,47.4447555542],"type":"Point"}
}