{
  "type": "Feature",
  "properties": {
    "addr:full":"Kampl Serlesstr 39 Neustift im Stubaital Tirol 6167",
    "addr:housenumber":"39",
    "addr:postcode":"6167",
    "addr:street":"Tirol",
    "iso:country":"AT",
    "sg:address":"Kampl Serlesstr 39",
    "sg:city":"Neustift im Stubaital",
    "sg:orig_category":"Appartements / Ferienwohnungen",
    "sg:phone":"+43 4352 262793",
    "sg:postcode":"6167",
    "sg:province":"Tirol",
    "wof:name":"M\u00fcller Johann",
    "wof:placetype":"venue"
},
  "geometry": {"coordinates":[11.3075504303,47.1104850769],"type":"Point"}
}