{
  "type": "Feature",
  "properties": {
    "addr:full":"Verditzer Strasse 1 Afritz am See K\u00e4rnten 9542",
    "addr:housenumber":"1",
    "addr:postcode":"9542",
    "addr:street":"Verditzer Strasse;Kaernten",
    "iso:country":"AT",
    "sg:address":"Verditzer Strasse 1",
    "sg:city":"Afritz am See",
    "sg:classifiers":[
        {
            "category":"Utilities",
            "subcategory":"Electric",
            "type":"Services"
        }
    ],
    "sg:phone":"+43 4247 2129",
    "sg:postcode":"9542",
    "sg:province":"K\u00e4rnten",
    "sg:tags":[
        "planing",
        "metal"
    ],
    "wof:name":"Hans De Zordo",
    "wof:placetype":"venue"
},
  "geometry": {"coordinates":[13.8012094498,46.7251243591],"type":"Point"}
}