{
  "type": "Feature",
  "properties": {
    "addr:full":"Ing.-Ludwig-Pech-Strasse 1 St. Johann im Pongau Salzburg 5600",
    "addr:housenumber":"1",
    "addr:postcode":"5600",
    "addr:street":"Ing.-Ludwig-Pech-Strasse;Salzburg",
    "iso:country":"AT",
    "sg:address":"Ing.-Ludwig-Pech-Strasse 1",
    "sg:city":"St. Johann im Pongau",
    "sg:classifiers":[
        {
            "category":"Professional",
            "subcategory":"Advertising",
            "type":"Services"
        }
    ],
    "sg:phone":"+43 6412 4905",
    "sg:postcode":"5600",
    "sg:province":"Salzburg",
    "sg:tags":[
        "athletic"
    ],
    "sg:website":"salzburg.com",
    "wof:name":"Verlagshaus Ges.m.b.H.",
    "wof:placetype":"venue"
},
  "geometry": {"coordinates":[13.2023706436,47.3493347168],"type":"Point"}
}