{
  "type": "Feature",
  "properties": {
    "addr:full":"Mariahilfstr 6 Innsbruck Tirol 6020",
    "addr:housenumber":"6",
    "addr:postcode":"6020",
    "addr:street":"Mariahilfstr;Tirol",
    "iso:country":"AT",
    "sg:address":"Mariahilfstr 6",
    "sg:city":"Innsbruck",
    "sg:orig_category":"Bierlokale-Pubs",
    "sg:phone":"+43 512 2278460",
    "sg:postcode":"6020",
    "sg:province":"Tirol",
    "wof:name":"Innside-Pilspub",
    "wof:placetype":"venue"
},
  "geometry": {"coordinates":[11.3901939392,47.2688865662],"type":"Point"}
}