{
  "type": "Feature",
  "properties": {
    "iso:country":"AT",
    "sg:address":"Marktstr 187",
    "sg:city":"Haus",
    "sg:orig_category":"Lebensmittel / Einzelhandel",
    "sg:phone":"+43 3686 2332",
    "sg:postcode":"8967",
    "sg:province":"Steiermark",
    "wof:name":"Billa AG",
    "wof:placetype":"venue"
},
  "geometry": {"coordinates":[13.7689466476,47.4106216431],"type":"Point"}
}