{
  "type": "Feature",
  "properties": {
    "iso:country":"AT",
    "sg:address":"Einersdorf 59",
    "sg:city":"Bleiburg",
    "sg:orig_category":"Zimmereien",
    "sg:phone":"+43 4342 354340",
    "sg:postcode":"9150",
    "sg:province":"K\u00e4rnten",
    "wof:name":"HOLZBAU Pleschiutschnig -Zimmerei Dachst\u00fchle Innenausbau Stiegenbau Balkone u Winterg\u00e4rten",
    "wof:placetype":"venue"
},
  "geometry": {"coordinates":[14.8006982803,46.5989685059],"type":"Point"}
}