{
  "type": "Feature",
  "properties": {
    "iso:country":"AT",
    "sg:address":"M\u00fchlbachg 1",
    "sg:city":"Grieskirchen",
    "sg:orig_category":"Fleischhauereien",
    "sg:phone":"+43 7248 683950",
    "sg:postcode":"4710",
    "sg:province":"Ober\u00f6sterreich",
    "wof:name":"Englmaier Josef GesmbH & Co KG",
    "wof:placetype":"venue"
},
  "geometry": {"coordinates":[13.8257322311,48.2358856201],"type":"Point"}
}