{
  "type": "Feature",
  "properties": {
    "addr:full":"Hauptstrasse 26 Himberg Nieder\u00f6sterreich 2325",
    "addr:housenumber":"26",
    "addr:postcode":"2325",
    "addr:street":"Hauptstrasse",
    "iso:country":"AT",
    "sg:address":"Hauptstrasse 26",
    "sg:city":"Himberg",
    "sg:classifiers":[
        {
            "category":"Professional",
            "subcategory":"Accounting & Tax Preparation",
            "type":"Services"
        }
    ],
    "sg:phone":"+43 2235 862460",
    "sg:postcode":"2325",
    "sg:province":"Nieder\u00f6sterreich",
    "sg:tags":[
        "calendar",
        "appointment"
    ],
    "sg:website":"wvkalender-bertelsmann.co.at",
    "wof:name":"WV Kalender Verlag GmbH & Co KG",
    "wof:placetype":"venue"
},
  "geometry": {"coordinates":[16.4394931793,48.0847358704],"type":"Point"}
}