{
  "type": "Feature",
  "properties": {
    "addr:full":"Hauptstr 2 Knittelfeld Steiermark 8720",
    "addr:housenumber":"2",
    "addr:postcode":"8720",
    "addr:street":"Hauptstr",
    "iso:country":"AT",
    "sg:address":"Hauptstr 2",
    "sg:city":"Knittelfeld",
    "sg:orig_category":"Friseure U Frisiersalons",
    "sg:phone":"+43 4335 1286767",
    "sg:postcode":"8720",
    "sg:province":"Steiermark",
    "wof:name":"Kargl Ingrid",
    "wof:placetype":"venue"
},
  "geometry": {"coordinates":[14.8587293625,47.2268295288],"type":"Point"}
}