{
  "type": "Feature",
  "properties": {
    "iso:country":"AT",
    "sg:address":"Nr 12",
    "sg:city":"St. Georgen am L\u00e4ngsee",
    "sg:orig_category":"Psychologen",
    "sg:phone":"+43 676 6199613",
    "sg:postcode":"9313",
    "sg:province":"K\u00e4rnten",
    "wof:name":"Springer-Schlegl Inge Mag",
    "wof:placetype":"venue"
},
  "geometry": {"coordinates":[14.4314098358,46.7814407349],"type":"Point"}
}