{
  "type": "Feature",
  "properties": {
    "addr:full":"Lisztstr 20 Lackendorf Burgenland 7321",
    "addr:housenumber":"20",
    "addr:postcode":"7321",
    "addr:street":"Lisztstr",
    "iso:country":"AT",
    "sg:address":"Lisztstr 20",
    "sg:city":"Lackendorf",
    "sg:orig_category":"Metallbau",
    "sg:phone":"+43 2619 74860",
    "sg:postcode":"7321",
    "sg:province":"Burgenland",
    "wof:name":"Landauer OEG",
    "wof:placetype":"venue"
},
  "geometry": {"coordinates":[16.5303821564,47.5652656555],"type":"Point"}
}