{
  "type": "Feature",
  "properties": {
    "addr:full":"W\u00e4hringer Str 139 Wien Wien 1180",
    "addr:housenumber":"139",
    "addr:postcode":"1180",
    "addr:street":"Str",
    "iso:country":"AT",
    "sg:address":"W\u00e4hringer Str 139",
    "sg:city":"Wien",
    "sg:orig_category":"Friseure U Frisiersalons",
    "sg:phone":"+43 4314 063745",
    "sg:postcode":"1180",
    "sg:province":"Wien",
    "wof:name":"r:2 hairstyling",
    "wof:placetype":"venue"
},
  "geometry": {"coordinates":[16.3368701935,48.227771759],"type":"Point"}
}