{
  "type": "Feature",
  "properties": {
    "iso:country":"AT",
    "sg:address":"Schusterg 12",
    "sg:city":"Imst",
    "sg:classifiers":[
        {
            "category":"Professional",
            "subcategory":"Management & Consulting",
            "type":"Services"
        }
    ],
    "sg:phone":"+43 5412 64417",
    "sg:postcode":"6460",
    "sg:province":"Tirol",
    "wof:name":"Management Service K5",
    "wof:placetype":"venue"
},
  "geometry": {"coordinates":[10.7401981354,47.2387123108],"type":"Point"}
}