{
  "type": "Feature",
  "properties": {
    "addr:full":"Rohrbacher Str 9 Rottenegg Ober\u00f6sterreich 4112",
    "addr:housenumber":"9",
    "addr:postcode":"4112",
    "addr:street":"Str;Oberoesterreich",
    "iso:country":"AT",
    "sg:address":"Rohrbacher Str 9",
    "sg:city":"Rottenegg",
    "sg:orig_category":"Autohandel",
    "sg:phone":"+43 7234 870920",
    "sg:postcode":"4112",
    "sg:province":"Ober\u00f6sterreich",
    "wof:name":"W\u00f6gerbauer Manfred GesmbH",
    "wof:placetype":"venue"
},
  "geometry": {"coordinates":[14.1296854019,48.3839187622],"type":"Point"}
}