{
  "type": "Feature",
  "properties": {
    "iso:country":"AT",
    "sg:address":"Wiener Str 10",
    "sg:city":"St. Valentin",
    "sg:orig_category":"Werbeagenturen",
    "sg:phone":"+43 7435 522301",
    "sg:postcode":"4300",
    "sg:province":"Nieder\u00f6sterreich",
    "wof:name":"EM Marketing & Design Manfred Enzlm\u00fcller",
    "wof:placetype":"venue"
},
  "geometry": {"coordinates":[14.5236406326,48.1979255676],"type":"Point"}
}