{
  "type": "Feature",
  "properties": {
    "addr:full":"Minoritenplatz 6/1 Tulln an der Donau Nieder\u00f6sterreich 3430",
    "addr:housenumber":"6 / 1",
    "addr:postcode":"3430",
    "addr:street":"Minoritenplatz",
    "iso:country":"AT",
    "sg:address":"Minoritenplatz 6/1",
    "sg:city":"Tulln an der Donau",
    "sg:classifiers":[
        {
            "category":"Government",
            "subcategory":"Court House",
            "type":"Public Place"
        }
    ],
    "sg:phone":"+43 2272 622860",
    "sg:postcode":"3430",
    "sg:province":"Nieder\u00f6sterreich",
    "sg:tags":[
        "administration",
        "central"
    ],
    "wof:name":"Franz Binder Ges.m.b.H.",
    "wof:placetype":"venue"
},
  "geometry": {"coordinates":[16.0497398376,48.3306999207],"type":"Point"}
}