{
  "type": "Feature",
  "properties": {
    "iso:country":"AT",
    "sg:address":"Egger Lienz-Str 130",
    "sg:city":"Innsbruck",
    "sg:orig_category":"Weiterbildungsinstitute M Allg U Berufl Bildungsangebot",
    "sg:phone":"+43 512 560906",
    "sg:postcode":"6020",
    "sg:province":"Tirol",
    "wof:name":"Berufsf\u00f6rderungsinstitut Tirol Partner INn work",
    "wof:placetype":"venue"
},
  "geometry": {"coordinates":[11.3774061203,47.2544364929],"type":"Point"}
}