{
  "type": "Feature",
  "properties": {
    "addr:full":"Schulg 1 Fernitz Steiermark 8072",
    "addr:housenumber":"1",
    "addr:postcode":"8072",
    "addr:street":"Schulg",
    "iso:country":"AT",
    "sg:address":"Schulg 1",
    "sg:city":"Fernitz",
    "sg:orig_category":"Fu\u00c3\u0178pflege U Fu\u00c3\u0178pflegesalons",
    "sg:phone":"+43 3135 52200",
    "sg:postcode":"8072",
    "sg:province":"Steiermark",
    "wof:name":"Fu\u00dfpflege Charlotte Reichelt - Diab. Sonderausbildung",
    "wof:placetype":"venue"
},
  "geometry": {"coordinates":[15.5014123917,46.9738502502],"type":"Point"}
}