{
  "type": "Feature",
  "properties": {
    "iso:country":"AT",
    "sg:address":"Nr 46a",
    "sg:city":"Umhausen",
    "sg:orig_category":"Appartements / Ferienwohnungen",
    "sg:phone":"+43 4352 5550265",
    "sg:postcode":"6441",
    "sg:province":"Tirol",
    "wof:name":"Ferienhaus Knor",
    "wof:placetype":"venue"
},
  "geometry": {"coordinates":[10.9276542664,47.1393241882],"type":"Point"}
}