{
  "type": "Feature",
  "properties": {
    "addr:full":"Hartberg 1 Schrems Nieder\u00f6sterreich 3943",
    "addr:housenumber":"1",
    "addr:postcode":"3943",
    "addr:street":"Hartberg",
    "iso:country":"AT",
    "sg:address":"Hartberg 1",
    "sg:city":"Schrems",
    "sg:classifiers":[
        {
            "category":"Home & Garden",
            "subcategory":"Building Materials",
            "type":"Retail Goods"
        }
    ],
    "sg:phone":"+43 2853 77401",
    "sg:postcode":"3943",
    "sg:province":"Nieder\u00f6sterreich",
    "sg:tags":[
        "granite",
        "syenite"
    ],
    "wof:name":"Josef Widy's S\u00f6hne Steinmetzmeister Schrems GmbH & Co KG",
    "wof:placetype":"venue"
},
  "geometry": {"coordinates":[15.0927801132,48.809513092],"type":"Point"}
}