{
  "type": "Feature",
  "properties": {
    "iso:country":"AT",
    "sg:address":"Judeng 3",
    "sg:city":"Wien",
    "sg:orig_category":"Bars-Cafes",
    "sg:phone":"+43 664 1029367",
    "sg:postcode":"1010",
    "sg:province":"Wien",
    "wof:name":"Richi's",
    "wof:placetype":"venue"
},
  "geometry": {"coordinates":[16.3731937408,48.211265564],"type":"Point"}
}