{
  "type": "Feature",
  "properties": {
    "addr:full":"Bergg 15 Fischamend Nieder\u00f6sterreich 2401",
    "addr:housenumber":"15",
    "addr:postcode":"2401",
    "addr:street":"Bergg",
    "iso:country":"AT",
    "sg:address":"Bergg 15",
    "sg:city":"Fischamend",
    "sg:orig_category":"Druckereimaschinen U -Bedarf",
    "sg:phone":"+43 2232 76730",
    "sg:postcode":"2401",
    "sg:province":"Nieder\u00f6sterreich",
    "wof:name":"Huber Michael Austria",
    "wof:placetype":"venue"
},
  "geometry": {"coordinates":[16.6112651825,48.1179656982],"type":"Point"}
}