{
  "type": "Feature",
  "properties": {
    "addr:full":"Arsenal Objekt/3/19 Wien Wien 1030",
    "addr:housenumber":"3 / 19",
    "addr:postcode":"1030",
    "iso:country":"AT",
    "sg:address":"Arsenal Objekt/3/19",
    "sg:city":"Wien",
    "sg:orig_category":"Weiterbildungsinstitute M Allg U Berufl Bildungsangebot",
    "sg:phone":"+43 1 79965140",
    "sg:postcode":"1030",
    "sg:province":"Wien",
    "wof:name":"perfact training Personalentwicklung GmbH",
    "wof:placetype":"venue"
},
  "geometry": {"coordinates":[16.3892383575,48.1802597046],"type":"Point"}
}