{
  "type": "Feature",
  "properties": {
    "addr:full":"Triester Str 129 Feldkirchen Steiermark 8073",
    "addr:housenumber":"129",
    "addr:postcode":"8073",
    "iso:country":"AT",
    "sg:address":"Triester Str 129",
    "sg:city":"Feldkirchen",
    "sg:orig_category":"Fassaden",
    "sg:phone":"+43 4331 6292066",
    "sg:postcode":"8073",
    "sg:province":"Steiermark",
    "wof:name":"BP Fassadenbau GmbH",
    "wof:placetype":"venue"
},
  "geometry": {"coordinates":[15.4486961365,47.0034866333],"type":"Point"}
}