{
  "type": "Feature",
  "properties": {
    "iso:country":"AT",
    "sg:address":"Sachsenpl 11",
    "sg:city":"Wien",
    "sg:orig_category":"Autoreparatur",
    "sg:phone":"+43 1 33033910",
    "sg:postcode":"1200",
    "sg:province":"Wien",
    "wof:name":"Ladenberger Harald",
    "wof:placetype":"venue"
},
  "geometry": {"coordinates":[16.3766269684,48.232624054],"type":"Point"}
}