{
  "type": "Feature",
  "properties": {
    "addr:full":"Seideng. 11 Wien Wien 1070",
    "addr:housenumber":"11",
    "addr:postcode":"1070",
    "addr:street":"Seideng.",
    "iso:country":"AT",
    "sg:address":"Seideng. 11",
    "sg:city":"Wien",
    "sg:classifiers":[
        {
            "category":"Manufacturing",
            "subcategory":"Printing",
            "type":"Manufacturing & Wholesale Goods"
        }
    ],
    "sg:phone":"+43 4315 21000",
    "sg:postcode":"1070",
    "sg:province":"Wien",
    "sg:tags":[
        "publishing"
    ],
    "wof:name":"KURIER REDAKTIONS GES.MBH & CO. KG",
    "wof:placetype":"venue"
},
  "geometry": {"coordinates":[16.3457698822,48.2002677917],"type":"Point"}
}