{
  "type": "Feature",
  "properties": {
    "addr:full":"Kirchenpl Neulengbach Nieder\u00f6sterreich 3040",
    "addr:postcode":"3040",
    "addr:street":"Niederoesterreich",
    "iso:country":"AT",
    "sg:address":"Kirchenpl",
    "sg:city":"Neulengbach",
    "sg:orig_category":"Juwelen, Gold- U Silberwaren / Einzelhandel",
    "sg:phone":"+43 4327 72527200",
    "sg:postcode":"3040",
    "sg:province":"Nieder\u00f6sterreich",
    "wof:name":"Pickner Juwelen",
    "wof:placetype":"venue"
},
  "geometry": {"coordinates":[15.9114646912,48.2011184692],"type":"Point"}
}