{
  "type": "Feature",
  "properties": {
    "addr:full":"Wallenmahd, Stauss-Haus 2 Dornbirn Vorarlberg 6850",
    "addr:housenumber":"2",
    "addr:postcode":"6850",
    "addr:street":"Stauss-Haus",
    "iso:country":"AT",
    "sg:address":"Wallenmahd, Stauss-Haus 2",
    "sg:city":"Dornbirn",
    "sg:classifiers":[
        {
            "category":"Organizations",
            "subcategory":"Professional Association",
            "type":"Services"
        }
    ],
    "sg:phone":"+43 5572 221000",
    "sg:postcode":"6850",
    "sg:province":"Vorarlberg",
    "sg:tags":[
        "technique",
        "systems",
        "handling"
    ],
    "sg:website":"robotech.at",
    "wof:name":"ROBOTECH Logistiksysteme Ges.m.b.H.",
    "wof:placetype":"venue"
},
  "geometry": {"coordinates":[9.7310323715,47.3964424133],"type":"Point"}
}