{
  "type": "Feature",
  "properties": {
    "addr:full":"Maria Schmollner Str 18 Mauerkirchen Ober\u00f6sterreich 5270",
    "addr:postcode":"5270",
    "addr:street":"Str 18",
    "iso:country":"AT",
    "sg:address":"Maria Schmollner Str 18",
    "sg:city":"Mauerkirchen",
    "sg:orig_category":"Transportunternehmen",
    "sg:phone":"+43 664 3242296",
    "sg:postcode":"5270",
    "sg:province":"Ober\u00f6sterreich",
    "wof:name":"Bramberger GmbH",
    "wof:placetype":"venue"
},
  "geometry": {"coordinates":[13.1354789734,48.1829032898],"type":"Point"}
}