{
  "type": "Feature",
  "properties": {
    "addr:full":"Franz-Schmidt-G 10 Hartberg Steiermark 8230",
    "addr:housenumber":"10",
    "addr:postcode":"8230",
    "addr:street":"Franz-Schmidt-G",
    "iso:country":"AT",
    "sg:address":"Franz-Schmidt-G 10",
    "sg:city":"Hartberg",
    "sg:orig_category":"Musikunterricht",
    "sg:phone":"+43 4333 32624230",
    "sg:postcode":"8230",
    "sg:province":"Steiermark",
    "wof:name":"Musikschule",
    "wof:placetype":"venue"
},
  "geometry": {"coordinates":[15.9727478027,47.2819519043],"type":"Point"}
}