{
  "type": "Feature",
  "properties": {
    "addr:full":"Kirchensteig 3 Wernstein am Inn Ober\u00f6sterreich 4783",
    "addr:housenumber":"3",
    "addr:postcode":"4783",
    "addr:street":"Kirchensteig",
    "iso:country":"AT",
    "sg:address":"Kirchensteig 3",
    "sg:city":"Wernstein am Inn",
    "sg:orig_category":"Elektroinstallationsunternehmen",
    "sg:phone":"+43 7713 65970",
    "sg:postcode":"4783",
    "sg:province":"Ober\u00f6sterreich",
    "wof:name":"Schiebler Franz",
    "wof:placetype":"venue"
},
  "geometry": {"coordinates":[13.4600639343,48.505897522],"type":"Point"}
}