{
  "type": "Feature",
  "properties": {
    "addr:full":"Johann-Georg-Hartwagner-Str 11 Ried im Innkreis Ober\u00f6sterreich 4910",
    "addr:housenumber":"11",
    "addr:postcode":"4910",
    "addr:street":"Johann-Georg-Hartwagner-Str",
    "iso:country":"AT",
    "sg:address":"Johann-Georg-Hartwagner-Str 11",
    "sg:city":"Ried im Innkreis",
    "sg:orig_category":"Bandagen U Bandagisten",
    "sg:phone":"+43 4377 5287848",
    "sg:postcode":"4910",
    "sg:province":"Ober\u00f6sterreich",
    "wof:name":"Lambert Johann GesmbH",
    "wof:placetype":"venue"
},
  "geometry": {"coordinates":[13.4893941879,48.2114715576],"type":"Point"}
}