{
  "type": "Feature",
  "properties": {
    "iso:country":"AT",
    "sg:address":"Hauptstr 99",
    "sg:city":"Rottenmann",
    "sg:orig_category":"Versicherungsunternehmen",
    "sg:phone":"+43 4336 1423250",
    "sg:postcode":"8786",
    "sg:province":"Steiermark",
    "wof:name":"Grazer Wechselseitige Versicherung AG",
    "wof:placetype":"venue"
},
  "geometry": {"coordinates":[14.3564910889,47.5248336792],"type":"Point"}
}