{
  "type": "Feature",
  "properties": {
    "iso:country":"AT",
    "sg:address":"Florian-Gr\u00f6ger-Str 7",
    "sg:city":"Klagenfurt",
    "sg:orig_category":"Transportunternehmen",
    "sg:phone":"+43 699 10064781",
    "sg:postcode":"9020",
    "sg:province":"K\u00e4rnten",
    "wof:name":"Lindner Josef",
    "wof:placetype":"venue"
},
  "geometry": {"coordinates":[14.3071517944,46.6162605286],"type":"Point"}
}