{
  "type": "Feature",
  "properties": {
    "addr:full":"Allandgasse 24 Baden Nieder\u00f6sterreich 2500",
    "addr:housenumber":"24",
    "addr:postcode":"2500",
    "addr:street":"Allandgasse;Niederoesterreich",
    "iso:country":"AT",
    "sg:address":"Allandgasse 24",
    "sg:city":"Baden",
    "sg:classifiers":[
        {
            "category":"Structure",
            "subcategory":"Restrooms",
            "type":"Public Place"
        }
    ],
    "sg:phone":"+43 2252 47170",
    "sg:postcode":"2500",
    "sg:province":"Nieder\u00f6sterreich",
    "sg:tags":[
        "equipment",
        "bath"
    ],
    "wof:name":"Peter Lichtenauer",
    "wof:placetype":"venue"
},
  "geometry": {"coordinates":[16.2370586395,48.0001068115],"type":"Point"}
}