{
  "type": "Feature",
  "properties": {
    "addr:full":"Hauptstr 56 Wartberg an der Krems Ober\u00f6sterreich 4552",
    "addr:housenumber":"56",
    "addr:postcode":"4552",
    "addr:street":"Hauptstr",
    "iso:country":"AT",
    "sg:address":"Hauptstr 56",
    "sg:city":"Wartberg an der Krems",
    "sg:orig_category":"Fliesen U Platten",
    "sg:phone":"+43 4375 8774650",
    "sg:postcode":"4552",
    "sg:province":"Ober\u00f6sterreich",
    "wof:name":"Schnellnberger Alfred GesmbH",
    "wof:placetype":"venue"
},
  "geometry": {"coordinates":[14.1271944046,47.9900436401],"type":"Point"}
}