{
  "type": "Feature",
  "properties": {
    "iso:country":"AT",
    "sg:address":"Nr 43",
    "sg:city":"Aistersheim",
    "sg:orig_category":"Autoreparatur",
    "sg:phone":"+43 7734 3328",
    "sg:postcode":"4676",
    "sg:province":"Ober\u00f6sterreich",
    "wof:name":"Grafendorfer Walter",
    "wof:placetype":"venue"
},
  "geometry": {"coordinates":[13.7416276932,48.1866836548],"type":"Point"}
}