{
  "type": "Feature",
  "properties": {
    "addr:full":"Innstr 26 Innsbruck Tirol 6020",
    "addr:housenumber":"26",
    "addr:postcode":"6020",
    "addr:street":"Innstr;Tirol",
    "iso:country":"AT",
    "sg:address":"Innstr 26",
    "sg:city":"Innsbruck",
    "sg:orig_category":"Reifen U Reifendienste",
    "sg:phone":"+43 512 283377",
    "sg:postcode":"6020",
    "sg:province":"Tirol",
    "wof:name":"Thaler-Reifen",
    "wof:placetype":"venue"
},
  "geometry": {"coordinates":[11.3932695389,47.2725601196],"type":"Point"}
}