{
  "type": "Feature",
  "properties": {
    "addr:full":"Messerschmiedg 3 Judenburg Steiermark 8750",
    "addr:housenumber":"3",
    "addr:postcode":"8750",
    "addr:street":"Messerschmiedg",
    "iso:country":"AT",
    "sg:address":"Messerschmiedg 3",
    "sg:city":"Judenburg",
    "sg:orig_category":"Glasereien",
    "sg:phone":"+43 3572 845600",
    "sg:postcode":"8750",
    "sg:province":"Steiermark",
    "wof:name":"Ginter-Glaserei GesmbH",
    "wof:placetype":"venue"
},
  "geometry": {"coordinates":[14.6616687775,47.1694335938],"type":"Point"}
}