{
  "type": "Feature",
  "properties": {
    "addr:full":"Hauptstr. 125  Zeltweg Steiermark 8740",
    "addr:housenumber":"125",
    "addr:postcode":"8740",
    "addr:street":"Hauptstr.",
    "iso:country":"AT",
    "sg:address":"Hauptstr. 125 ",
    "sg:city":"Zeltweg",
    "sg:classifiers":[
        {
            "category":"Food & Beverages",
            "subcategory":"Dairy",
            "type":"Retail Goods"
        }
    ],
    "sg:phone":"+43 4335 77223300",
    "sg:postcode":"8740",
    "sg:province":"Steiermark",
    "sg:tags":[
        "product"
    ],
    "wof:name":"HUBMANN KG",
    "wof:placetype":"venue"
},
  "geometry": {"coordinates":[14.7448186874,47.190574646],"type":"Point"}
}