{
  "type": "Feature",
  "properties": {
    "addr:full":"Rosenweg 14 Uttendorf Ober\u00f6sterreich 5261",
    "addr:housenumber":"14",
    "addr:postcode":"5261",
    "addr:street":"Rosenweg",
    "iso:country":"AT",
    "sg:address":"Rosenweg 14",
    "sg:city":"Uttendorf",
    "sg:orig_category":"Schwei\u00c3\u0178- U Schneidetechnik",
    "sg:phone":"+43 4377 244377",
    "sg:postcode":"5261",
    "sg:province":"Ober\u00f6sterreich",
    "sg:website":"schweiss-technik.com",
    "wof:name":"Schwei\u00df Technik Simon",
    "wof:placetype":"venue"
},
  "geometry": {"coordinates":[13.1183948517,48.1551017761],"type":"Point"}
}