{
  "type": "Feature",
  "properties": {
    "addr:full":"Schmidham 2 V\u00f6cklamarkt Ober\u00f6sterreich 4870",
    "addr:housenumber":"2",
    "addr:postcode":"4870",
    "addr:street":"Schmidham;Oberoesterreich",
    "iso:country":"AT",
    "sg:address":"Schmidham 2",
    "sg:city":"V\u00f6cklamarkt",
    "sg:orig_category":"Werbeagenturen",
    "sg:phone":"+43 4376 826911",
    "sg:postcode":"4870",
    "sg:province":"Ober\u00f6sterreich",
    "wof:name":"Grininger Claudia",
    "wof:placetype":"venue"
},
  "geometry": {"coordinates":[13.4818000793,48.0179595947],"type":"Point"}
}