{
  "type": "Feature",
  "properties": {
    "iso:country":"AT",
    "sg:address":"Rainerstr 7",
    "sg:city":"Ried im Innkreis",
    "sg:orig_category":"Damenmoden",
    "sg:phone":"+43 7752 88074",
    "sg:postcode":"4910",
    "sg:province":"Ober\u00f6sterreich",
    "wof:name":"LUCIA Moden",
    "wof:placetype":"venue"
},
  "geometry": {"coordinates":[13.4868030548,48.207950592],"type":"Point"}
}