{
  "type": "Feature",
  "properties": {
    "iso:country":"AT",
    "sg:address":"Jedleseer Str 69",
    "sg:city":"Wien",
    "sg:orig_category":"Garderobeneinrichtungen",
    "sg:phone":"+43 4366 45304027",
    "sg:postcode":"1210",
    "sg:province":"Wien",
    "wof:name":"LOCKISTIK Spindsysteme GmbH",
    "wof:placetype":"venue"
},
  "geometry": {"coordinates":[16.3874320984,48.2615852356],"type":"Point"}
}