{
  "type": "Feature",
  "properties": {
    "addr:full":"Schirmitzb\u00fchelstrasse 10 Kapfenberg Steiermark 8605",
    "addr:housenumber":"10",
    "addr:postcode":"8605",
    "addr:street":"Schirmitzbuehelstrasse",
    "iso:country":"AT",
    "sg:address":"Schirmitzb\u00fchelstrasse 10",
    "sg:city":"Kapfenberg",
    "sg:classifiers":[
        {
            "category":"Food & Beverages",
            "subcategory":"Chocolate",
            "type":"Retail Goods"
        }
    ],
    "sg:phone":"+43 3862 312830",
    "sg:postcode":"8605",
    "sg:province":"Steiermark",
    "sg:tags":[
        "spread",
        "sandwich"
    ],
    "wof:name":"Feinkosterzeugung Rudolf und Susanne Aichinger Ges.m.b.H.",
    "wof:placetype":"venue"
},
  "geometry": {"coordinates":[15.2912454605,47.4438438416],"type":"Point"}
}