{
  "type": "Feature",
  "properties": {
    "iso:country":"AT",
    "sg:address":"Jacquing 1",
    "sg:city":"Wien",
    "sg:classifiers":[
        {
            "category":"Taxi",
            "type":"Transportation"
        }
    ],
    "sg:phone":"+43 676 879987813",
    "sg:postcode":"1030",
    "sg:province":"Wien",
    "sg:tags":[
        "personentransporte",
        "u"
    ],
    "wof:name":"Hauke Hans",
    "wof:placetype":"venue"
},
  "geometry": {"coordinates":[16.385635376,48.1946182251],"type":"Point"}
}