{
  "type": "Feature",
  "properties": {
    "iso:country":"AT",
    "sg:address":"Kasten 62",
    "sg:city":"St. Peter am Wimberg",
    "sg:classifiers":[
        {
            "category":"Manufacturing",
            "subcategory":"Wood Products",
            "type":"Manufacturing & Wholesale Goods"
        }
    ],
    "sg:phone":"+43 7289 71248",
    "sg:postcode":"4171",
    "sg:province":"Ober\u00f6sterreich",
    "sg:tags":[
        "gate",
        "made",
        "door"
    ],
    "sg:website":"eckal.at",
    "wof:name":"Alois Eckerstorfer Ges.m.b.H.",
    "wof:placetype":"venue"
},
  "geometry": {"coordinates":[14.0771446228,48.5545654297],"type":"Point"}
}