{
  "type": "Feature",
  "properties": {
    "addr:full":"Praunstr 33 Langenzersdorf Nieder\u00f6sterreich 2103",
    "addr:housenumber":"33",
    "addr:postcode":"2103",
    "addr:street":"Praunstr",
    "iso:country":"AT",
    "sg:address":"Praunstr 33",
    "sg:city":"Langenzersdorf",
    "sg:orig_category":"Transportunternehmen",
    "sg:phone":"+43 2244 30814",
    "sg:postcode":"2103",
    "sg:province":"Nieder\u00f6sterreich",
    "wof:name":"Botek Andrea Service Transporte GesmbH",
    "wof:placetype":"venue"
},
  "geometry": {"coordinates":[16.3500347137,48.301738739],"type":"Point"}
}