{
  "type": "Feature",
  "properties": {
    "addr:full":"Am Kirchh\u00fcgel 1 St. Stefan im Lavanttal K\u00e4rnten 9431",
    "addr:housenumber":"1",
    "addr:postcode":"9431",
    "addr:street":"Am Kirchhuegel",
    "iso:country":"AT",
    "sg:address":"Am Kirchh\u00fcgel 1",
    "sg:city":"St. Stefan im Lavanttal",
    "sg:orig_category":"Hobbyvereine",
    "sg:phone":"+43 4343 523403",
    "sg:postcode":"9431",
    "sg:province":"K\u00e4rnten",
    "wof:name":"Alpenverein \u00f6sterr Sektion Wolfsberg Obmann Ing Rudolf Kremser",
    "wof:placetype":"venue"
},
  "geometry": {"coordinates":[14.832036972,46.8094558716],"type":"Point"}
}