{
  "type": "Feature",
  "properties": {
    "addr:full":"Manglburg 10 Grieskirchen Ober\u00f6sterreich 4710",
    "addr:housenumber":"10",
    "addr:postcode":"4710",
    "addr:street":"Manglburg",
    "iso:country":"AT",
    "sg:address":"Manglburg 10",
    "sg:city":"Grieskirchen",
    "sg:orig_category":"Parkettbodenverlegung",
    "sg:phone":"+43 4372 4868001",
    "sg:postcode":"4710",
    "sg:province":"Ober\u00f6sterreich",
    "wof:name":"Sterrer Ingrid ZUHAUSE",
    "wof:placetype":"venue"
},
  "geometry": {"coordinates":[13.8266963959,48.2341384888],"type":"Point"}
}