{
  "type": "Feature",
  "properties": {
    "addr:full":"Industriestr 3 Steyr Ober\u00f6sterreich 4400",
    "addr:housenumber":"3",
    "addr:postcode":"4400",
    "addr:street":"Industriestr;Oberoesterreich",
    "iso:country":"AT",
    "sg:address":"Industriestr 3",
    "sg:city":"Steyr",
    "sg:orig_category":"Metallwaren / Erzeugung U Gro\u00c3\u0178handel",
    "sg:phone":"+43 7252 72919",
    "sg:postcode":"4400",
    "sg:province":"Ober\u00f6sterreich",
    "wof:name":"Landstra\u00dfer Metall- und Holzwarenfabrik GesmbH",
    "wof:placetype":"venue"
},
  "geometry": {"coordinates":[14.4195327759,48.046661377],"type":"Point"}
}