{
  "type": "Feature",
  "properties": {
    "addr:full":"Dorf 131 Finkenberg Tirol 6292",
    "addr:housenumber":"131",
    "addr:postcode":"6292",
    "addr:street":"Dorf",
    "iso:country":"AT",
    "sg:address":"Dorf 131",
    "sg:city":"Finkenberg",
    "sg:classifiers":[
        {
            "category":"Travel",
            "subcategory":"Hotels & Motels",
            "type":"Entertainment"
        }
    ],
    "sg:phone":"+43 5285 626670",
    "sg:postcode":"6292",
    "sg:province":"Tirol",
    "wof:name":"Hotel Eberl",
    "wof:placetype":"venue"
},
  "geometry": {"coordinates":[11.8250598907,47.1544189453],"type":"Point"}
}