{
  "type": "Feature",
  "properties": {
    "addr:full":"Deutsch Altenburger Str 1 Prellenkirchen Nieder\u00f6sterreich 2472",
    "addr:housenumber":"1",
    "addr:postcode":"2472",
    "iso:country":"AT",
    "sg:address":"Deutsch Altenburger Str 1",
    "sg:city":"Prellenkirchen",
    "sg:orig_category":"Tankstellen",
    "sg:phone":"+43 4321 452195",
    "sg:postcode":"2472",
    "sg:province":"Nieder\u00f6sterreich",
    "wof:name":"AWI Diskont Tankstelle",
    "wof:placetype":"venue"
},
  "geometry": {"coordinates":[16.9468955994,48.0767288208],"type":"Point"}
}