{
  "type": "Feature",
  "properties": {
    "addr:full":"Schulstr 12 Aschach an der Steyr Ober\u00f6sterreich 4421",
    "addr:housenumber":"12",
    "addr:postcode":"4421",
    "addr:street":"Schulstr",
    "iso:country":"AT",
    "sg:address":"Schulstr 12",
    "sg:city":"Aschach an der Steyr",
    "sg:orig_category":"Banken U Sparkassen",
    "sg:phone":"+43 4372 5934050",
    "sg:postcode":"4421",
    "sg:province":"Ober\u00f6sterreich",
    "wof:name":"Bankomat d Raiffeisenkasse Aschach a d Steyr regGenmbH",
    "wof:placetype":"venue"
},
  "geometry": {"coordinates":[14.3356571198,48.0113143921],"type":"Point"}
}