{
  "type": "Feature",
  "properties": {
    "iso:country":"AT",
    "sg:address":"Innsbrucker Bundesstrasse 55",
    "sg:city":"Salzburg",
    "sg:classifiers":[
        {
            "category":"Autos & Motor Vehicles",
            "subcategory":"Auto Supplies",
            "type":"Retail Goods"
        }
    ],
    "sg:phone":"+43 662 827639",
    "sg:postcode":"5020",
    "sg:province":"Salzburg",
    "sg:tags":[
        "body",
        "car",
        "truck",
        "trailer",
        "superstructure"
    ],
    "wof:name":"Leopold Schraml",
    "wof:placetype":"venue"
},
  "geometry": {"coordinates":[13.0170078278,47.8017616272],"type":"Point"}
}