{
  "type": "Feature",
  "properties": {
    "addr:full":"Bismarckstr 4 Feldbach Steiermark 8330",
    "addr:housenumber":"4",
    "addr:postcode":"8330",
    "addr:street":"Bismarckstr",
    "iso:country":"AT",
    "sg:address":"Bismarckstr 4",
    "sg:city":"Feldbach",
    "sg:orig_category":"Weiterbildungsinstitute M Allg U Berufl Bildungsangebot",
    "sg:phone":"+43 4331 526376",
    "sg:postcode":"8330",
    "sg:province":"Steiermark",
    "wof:name":"L\u00e4ndliches Fortbildungsinstitut (LFI) Steiermark",
    "wof:placetype":"venue"
},
  "geometry": {"coordinates":[15.8875541687,46.9521446228],"type":"Point"}
}