{
  "type": "Feature",
  "properties": {
    "iso:country":"AT",
    "sg:address":"Brauereistr 12",
    "sg:city":"Mattighofen",
    "sg:orig_category":"Bierdepots",
    "sg:phone":"+43 7742 2406",
    "sg:postcode":"5230",
    "sg:province":"Ober\u00f6sterreich",
    "wof:name":"Brau Union \u00f6sterreich AG",
    "wof:placetype":"venue"
},
  "geometry": {"coordinates":[13.1482048035,48.1040039062],"type":"Point"}
}