{
  "type": "Feature",
  "properties": {
    "iso:country":"AT",
    "sg:address":"Lerchenfelder Hauptpl 9",
    "sg:city":"Krems an der Donau",
    "sg:orig_category":"Lebensmittel / Einzelhandel",
    "sg:phone":"+43 4327 3283996",
    "sg:postcode":"3500",
    "sg:province":"Nieder\u00f6sterreich",
    "wof:name":"Spar-Markt Lenk Herta",
    "wof:placetype":"venue"
},
  "geometry": {"coordinates":[15.635351181,48.4137802124],"type":"Point"}
}