{
  "type": "Feature",
  "properties": {
    "addr:full":"Scheibbser Str. 17  Wieselburg an der Erlauf Nieder\u00f6sterreich 3250",
    "addr:postcode":"3250",
    "addr:street":"Str. 17",
    "iso:country":"AT",
    "sg:address":"Scheibbser Str. 17 ",
    "sg:city":"Wieselburg an der Erlauf",
    "sg:classifiers":[
        {
            "category":"Shopping",
            "subcategory":"Computers & Home Electronics",
            "type":"Retail Goods"
        }
    ],
    "sg:phone":"+43 4374 165050",
    "sg:postcode":"3250",
    "sg:province":"Nieder\u00f6sterreich",
    "sg:tags":[
        "electronic",
        "electrical",
        "equipment"
    ],
    "wof:name":"ZIZALA LICHTSYSTEME GMBH",
    "wof:placetype":"venue"
},
  "geometry": {"coordinates":[15.1376533508,48.1236076355],"type":"Point"}
}