{
  "type": "Feature",
  "properties": {
    "addr:full":"Bahnhofstr 29 Ottensheim Ober\u00f6sterreich 4100",
    "addr:housenumber":"29",
    "addr:postcode":"4100",
    "addr:street":"Bahnhofstr",
    "iso:country":"AT",
    "sg:address":"Bahnhofstr 29",
    "sg:city":"Ottensheim",
    "sg:orig_category":"Friseure U Frisiersalons",
    "sg:phone":"+43 7234 86077",
    "sg:postcode":"4100",
    "sg:province":"Ober\u00f6sterreich",
    "wof:name":"Die Haarschneider - Affenzeller & W\u00f6gerbauer OEG",
    "wof:placetype":"venue"
},
  "geometry": {"coordinates":[14.1759319305,48.3359069824],"type":"Point"}
}