{
  "type": "Feature",
  "properties": {
    "addr:full":"Lerchenfelder Str 13 Wien Wien 1070",
    "addr:housenumber":"13",
    "addr:postcode":"1070",
    "addr:street":"Lerchenfelder Str",
    "iso:country":"AT",
    "sg:address":"Lerchenfelder Str 13",
    "sg:city":"Wien",
    "sg:orig_category":"\u00c3\u201erzte / F Allgemeinmedizin",
    "sg:phone":"+43 1 8047130",
    "sg:postcode":"1070",
    "sg:province":"Wien",
    "wof:name":"Huber Michael Dr - Hom\u00f6opathische Ordination",
    "wof:placetype":"venue"
},
  "geometry": {"coordinates":[16.3529529572,48.206401825],"type":"Point"}
}