{
  "type": "Feature",
  "properties": {
    "addr:full":"Hilmteichstr 77a Graz Steiermark 8010",
    "addr:housenumber":"77a",
    "addr:postcode":"8010",
    "addr:street":"Hilmteichstr",
    "iso:country":"AT",
    "sg:address":"Hilmteichstr 77a",
    "sg:city":"Graz",
    "sg:orig_category":"Psychotherapie",
    "sg:phone":"+43 316 386406",
    "sg:postcode":"8010",
    "sg:province":"Steiermark",
    "wof:name":"Schwarzbauer Elisabeth",
    "wof:placetype":"venue"
},
  "geometry": {"coordinates":[15.4588308334,47.0847167969],"type":"Point"}
}