{
  "type": "Feature",
  "properties": {
    "iso:country":"AT",
    "sg:address":"Am Bindermichl 56",
    "sg:city":"Linz",
    "sg:orig_category":"Optiker",
    "sg:phone":"+43 732 341258",
    "sg:postcode":"4020",
    "sg:province":"Ober\u00f6sterreich",
    "wof:name":"Gumpelmayer Dr Augenoptik KG",
    "wof:placetype":"venue"
},
  "geometry": {"coordinates":[14.2924871445,48.269203186],"type":"Point"}
}