{
  "type": "Feature",
  "properties": {
    "iso:country":"AT",
    "sg:address":"Gewerbestr Ost 3",
    "sg:city":"Niedernsill",
    "sg:orig_category":"Tischlereien",
    "sg:phone":"+43 6548 87770",
    "sg:postcode":"5722",
    "sg:province":"Salzburg",
    "wof:name":"Hutter Gerhard",
    "wof:placetype":"venue"
},
  "geometry": {"coordinates":[12.6478881836,47.284324646],"type":"Point"}
}