{
  "type": "Feature",
  "properties": {
    "addr:full":"Reinhartsdorfg 19a Schwechat Nieder\u00f6sterreich 2320",
    "addr:housenumber":"19a",
    "addr:postcode":"2320",
    "addr:street":"Reinhartsdorfg;Niederoesterreich",
    "iso:country":"AT",
    "sg:address":"Reinhartsdorfg 19a",
    "sg:city":"Schwechat",
    "sg:orig_category":"Steinmetzbetriebe",
    "sg:phone":"+43 1 7063888",
    "sg:postcode":"2320",
    "sg:province":"Nieder\u00f6sterreich",
    "sg:website":"marmorbau-schaden.at",
    "wof:name":"Schaden Johann GesmbH",
    "wof:placetype":"venue"
},
  "geometry": {"coordinates":[16.4594116211,48.1168441772],"type":"Point"}
}