{
  "type": "Feature",
  "properties": {
    "addr:full":"Zaillachweg 6 Kammern im Liesingtal Steiermark 8773",
    "addr:housenumber":"6",
    "addr:postcode":"8773",
    "addr:street":"Zaillachweg",
    "iso:country":"AT",
    "sg:address":"Zaillachweg 6",
    "sg:city":"Kammern im Liesingtal",
    "sg:classifiers":[
        {
            "category":"Taxi",
            "type":"Transportation"
        }
    ],
    "sg:phone":"+43 4338 4481000",
    "sg:postcode":"8773",
    "sg:province":"Steiermark",
    "sg:tags":[
        "personentransporte",
        "u"
    ],
    "wof:name":"DWORSCHAK KEG",
    "wof:placetype":"venue"
},
  "geometry": {"coordinates":[14.8916091919,47.3928375244],"type":"Point"}
}