{
  "type": "Feature",
  "properties": {
    "addr:full":"Wachtbergstr 9 Weyregg am Attersee Ober\u00f6sterreich 4852",
    "addr:housenumber":"9",
    "addr:postcode":"4852",
    "addr:street":"Wachtbergstr",
    "iso:country":"AT",
    "sg:address":"Wachtbergstr 9",
    "sg:city":"Weyregg am Attersee",
    "sg:orig_category":"Pensionen / Privatzimmer",
    "sg:phone":"+43 4376 642900",
    "sg:postcode":"4852",
    "sg:province":"Ober\u00f6sterreich",
    "wof:name":"G\u00e4stehaus Heinrich Bichlm\u00fcller",
    "wof:placetype":"venue"
},
  "geometry": {"coordinates":[13.5805339813,47.8968772888],"type":"Point"}
}