{
  "type": "Feature",
  "properties": {
    "addr:full":"Stra\u00df 348 Lech Vorarlberg 6764",
    "addr:housenumber":"348",
    "addr:postcode":"6764",
    "addr:street":"Strass",
    "iso:country":"AT",
    "sg:address":"Stra\u00df 348",
    "sg:city":"Lech",
    "sg:orig_category":"Pensionen / Privatzimmer",
    "sg:phone":"+43 4355 8326640",
    "sg:postcode":"6764",
    "sg:province":"Vorarlberg",
    "wof:name":"Pension Gallus",
    "wof:placetype":"venue"
},
  "geometry": {"coordinates":[10.1417798996,47.2082939148],"type":"Point"}
}