{
  "type": "Feature",
  "properties": {
    "addr:full":"Rudolf-Biebl-Str 2 Salzburg Salzburg 5020",
    "addr:housenumber":"2",
    "addr:postcode":"5020",
    "addr:street":"Rudolf-Biebl-Str;Salzburg",
    "iso:country":"AT",
    "sg:address":"Rudolf-Biebl-Str 2",
    "sg:city":"Salzburg",
    "sg:orig_category":"Banken U Sparkassen",
    "sg:phone":"+43 4350 10041021",
    "sg:postcode":"5020",
    "sg:province":"Salzburg",
    "wof:name":"Salzburger Sparkasse Bank AG",
    "wof:placetype":"venue"
},
  "geometry": {"coordinates":[13.0268096924,47.80727005],"type":"Point"}
}