{
  "type": "Feature",
  "properties": {
    "addr:full":"Ginzkeypl 3 Salzburg Salzburg 5020",
    "addr:housenumber":"3",
    "addr:postcode":"5020",
    "addr:street":"Ginzkeypl;Salzburg",
    "iso:country":"AT",
    "sg:address":"Ginzkeypl 3",
    "sg:city":"Salzburg",
    "sg:orig_category":"Textilreinigung",
    "sg:phone":"+43 676 84819421",
    "sg:postcode":"5020",
    "sg:province":"Salzburg",
    "wof:name":"Mirabell Counde Textilpflege GesmbH",
    "wof:placetype":"venue"
},
  "geometry": {"coordinates":[13.0703849792,47.7736091614],"type":"Point"}
}