{
  "type": "Feature",
  "properties": {
    "addr:full":"Hauptpl 15 Unterwaltersdorf Nieder\u00f6sterreich 2442",
    "addr:housenumber":"15",
    "addr:postcode":"2442",
    "addr:street":"Hauptpl",
    "iso:country":"AT",
    "sg:address":"Hauptpl 15",
    "sg:city":"Unterwaltersdorf",
    "sg:orig_category":"Gesundheitsvorsorge",
    "sg:phone":"+43 2254 72733",
    "sg:postcode":"2442",
    "sg:province":"Nieder\u00f6sterreich",
    "wof:name":"Westhoff Waltraud",
    "wof:placetype":"venue"
},
  "geometry": {"coordinates":[16.4304733276,47.9604721069],"type":"Point"}
}