{
  "type": "Feature",
  "properties": {
    "addr:full":"Shuttleworthstrasse 27-29 Wien Wien 1210",
    "addr:postcode":"27-29;1210",
    "addr:street":"Shuttleworthstrasse",
    "iso:country":"AT",
    "sg:address":"Shuttleworthstrasse 27-29",
    "sg:city":"Wien",
    "sg:classifiers":[
        {
            "category":"Structure",
            "subcategory":"Tower",
            "type":"Public Place"
        }
    ],
    "sg:phone":"+43 1 2901634",
    "sg:postcode":"1210",
    "sg:province":"Wien",
    "sg:tags":[
        "aluminium",
        "scaffolding"
    ],
    "sg:website":"steininger.co.at",
    "wof:name":"Dominik J. Steininger GmbH Hymer Leichtmetallbau",
    "wof:placetype":"venue"
},
  "geometry": {"coordinates":[16.4123210907,48.270866394],"type":"Point"}
}