{
  "type": "Feature",
  "properties": {
    "addr:full":"Kaiserstr 11 Poysdorf Nieder\u00f6sterreich 2170",
    "addr:housenumber":"11",
    "addr:postcode":"2170",
    "addr:street":"Kaiserstr",
    "iso:country":"AT",
    "sg:address":"Kaiserstr 11",
    "sg:city":"Poysdorf",
    "sg:orig_category":"Steinmetzbetriebe",
    "sg:phone":"+43 2552 2601",
    "sg:postcode":"2170",
    "sg:province":"Nieder\u00f6sterreich",
    "wof:name":"Felzl Gerhard OHG",
    "wof:placetype":"venue"
},
  "geometry": {"coordinates":[16.6317100525,48.6534156799],"type":"Point"}
}