{
  "type": "Feature",
  "properties": {
    "addr:full":"Mitterberg 55 Weerberg Tirol 6133",
    "addr:housenumber":"55",
    "addr:postcode":"6133",
    "addr:street":"Mitterberg;Tirol",
    "iso:country":"AT",
    "sg:address":"Mitterberg 55",
    "sg:city":"Weerberg",
    "sg:classifiers":[
        {
            "category":"Park",
            "subcategory":"Provincial",
            "type":"Public Place"
        }
    ],
    "sg:phone":"+43 5224 68905",
    "sg:postcode":"6133",
    "sg:province":"Tirol",
    "sg:tags":[
        "u",
        "ski-",
        "snowboardschulen"
    ],
    "wof:name":"Schischule Weerberg",
    "wof:placetype":"venue"
},
  "geometry": {"coordinates":[11.6758117676,47.30260849],"type":"Point"}
}