{
  "type": "Feature",
  "properties": {
    "addr:full":"Wiesingerstr. 8 Bad Ischl Ober\u00f6sterreich 4820",
    "addr:housenumber":"8",
    "addr:postcode":"4820",
    "addr:street":"Wiesingerstr.;Oberoesterreich",
    "iso:country":"AT",
    "sg:address":"Wiesingerstr. 8",
    "sg:city":"Bad Ischl",
    "sg:classifiers":[
        {
            "category":"Shopping",
            "subcategory":"Stationery & Office Supplies",
            "type":"Retail Goods"
        }
    ],
    "sg:phone":"+43 4361 3227384",
    "sg:postcode":"4820",
    "sg:province":"Ober\u00f6sterreich",
    "sg:tags":[
        "professional"
    ],
    "wof:name":"PWL ANLAGETECHNIK HANDELSGESMBH",
    "wof:placetype":"venue"
},
  "geometry": {"coordinates":[13.6193008423,47.7125205994],"type":"Point"}
}