{
  "type": "Feature",
  "properties": {
    "iso:country":"AT",
    "sg:address":"Bahnhofstr 27",
    "sg:city":"Vils",
    "sg:orig_category":"Gips U Gipsprodukte",
    "sg:phone":"+43 5677 84010",
    "sg:postcode":"6682",
    "sg:province":"Tirol",
    "wof:name":"Gipswerk Schretter & Cie GesmbH",
    "wof:placetype":"venue"
},
  "geometry": {"coordinates":[10.6393165588,47.5485572815],"type":"Point"}
}