{
  "type": "Feature",
  "properties": {
    "addr:full":"Kaiser-Franz-Josef-Str 7 Gro\u00df-Enzersdorf Nieder\u00f6sterreich 2301",
    "addr:housenumber":"7",
    "addr:postcode":"2301",
    "addr:street":"Kaiser-Franz-Josef-Str;Niederoesterreich",
    "iso:country":"AT",
    "sg:address":"Kaiser-Franz-Josef-Str 7",
    "sg:city":"Gro\u00df-Enzersdorf",
    "sg:orig_category":"Kosmetische Produkte / Einzelhandel",
    "sg:phone":"+43 4322 492408",
    "sg:postcode":"2301",
    "sg:province":"Nieder\u00f6sterreich",
    "wof:name":"Unilever Cosmetics International Handels GmbH",
    "wof:placetype":"venue"
},
  "geometry": {"coordinates":[16.5485343933,48.1999282837],"type":"Point"}
}