{
  "type": "Feature",
  "properties": {
    "addr:full":"Prager Str 51 Wien Wien 1210",
    "addr:postcode":"1210",
    "addr:street":"Str 51",
    "iso:country":"AT",
    "sg:address":"Prager Str 51",
    "sg:city":"Wien",
    "sg:orig_category":"Optiker",
    "sg:phone":"+43 1 2727826",
    "sg:postcode":"1210",
    "sg:province":"Wien",
    "wof:name":"Dangl Optik",
    "wof:placetype":"venue"
},
  "geometry": {"coordinates":[16.3931732178,48.2654876709],"type":"Point"}
}