{
  "type": "Feature",
  "properties": {
    "iso:country":"AT",
    "sg:address":"Vogelweiderstr 68",
    "sg:city":"Salzburg",
    "sg:orig_category":"Schilder, Beschriftungen, Stempel",
    "sg:phone":"+43 662 8732770",
    "sg:postcode":"5020",
    "sg:province":"Salzburg",
    "sg:website":"www.schider-schilder.com",
    "wof:name":"Schider-Schilder Inh Reinhard Schider",
    "wof:placetype":"venue"
},
  "geometry": {"coordinates":[13.0538654327,47.8150024414],"type":"Point"}
}