{
  "type": "Feature",
  "properties": {
    "addr:full":"Lienzer Strasse 36 Matrei in Osttirol Tirol 9971",
    "addr:housenumber":"36",
    "addr:postcode":"9971",
    "addr:street":"Lienzer Strasse;Tirol",
    "iso:country":"AT",
    "sg:address":"Lienzer Strasse 36",
    "sg:city":"Matrei in Osttirol",
    "sg:classifiers":[
        {
            "category":"Farming",
            "subcategory":"Nursery",
            "type":"Manufacturing & Wholesale Goods"
        }
    ],
    "sg:phone":"+43 664 1923398",
    "sg:postcode":"9971",
    "sg:province":"Tirol",
    "sg:tags":[
        "growing",
        "flower"
    ],
    "wof:name":"Ernst Wibmer KEG",
    "wof:placetype":"venue"
},
  "geometry": {"coordinates":[12.5413990021,46.9951934814],"type":"Point"}
}