{
  "type": "Feature",
  "properties": {
    "addr:full":"Lanser Str 65 Innsbruck-Igls Tirol 6080",
    "addr:housenumber":"65",
    "addr:postcode":"6080",
    "addr:street":"Str",
    "iso:country":"AT",
    "sg:address":"Lanser Str 65",
    "sg:city":"Innsbruck-Igls",
    "sg:orig_category":"Handelsagenturen",
    "sg:phone":"+43 512 379308",
    "sg:postcode":"6080",
    "sg:province":"Tirol",
    "wof:name":"Proxauf Florian",
    "wof:placetype":"venue"
},
  "geometry": {"coordinates":[11.4049882889,47.2309532166],"type":"Point"}
}