{
  "type": "Feature",
  "properties": {
    "addr:full":"Neutorstr.8-9  Salzburg Salzburg 5020",
    "addr:postcode":"5020",
    "addr:street":"Neutorstr.8-9",
    "iso:country":"AT",
    "sg:address":"Neutorstr.8-9 ",
    "sg:city":"Salzburg",
    "sg:classifiers":[
        {
            "category":"Travel",
            "subcategory":"Travel Agent",
            "type":"Entertainment"
        }
    ],
    "sg:phone":"+43 4366 28441540",
    "sg:postcode":"5020",
    "sg:province":"Salzburg",
    "sg:tags":[
        "business"
    ],
    "wof:name":"HOTEL NEUTOR",
    "wof:placetype":"venue"
},
  "geometry": {"coordinates":[13.0371570587,47.7976722717],"type":"Point"}
}