{
  "type": "Feature",
  "properties": {
    "iso:country":"AT",
    "sg:address":"Schubertstr.36",
    "sg:city":"Atzenbrugg",
    "sg:classifiers":[
        {
            "category":"Farming",
            "subcategory":"Livestock Farm",
            "type":"Manufacturing & Wholesale Goods"
        }
    ],
    "sg:phone":"+43 4322 755603",
    "sg:postcode":"3452",
    "sg:province":"Nieder\u00f6sterreich",
    "sg:tags":[
        "agriculture"
    ],
    "wof:name":"MARKUS LEDERLEITNER GESMBH",
    "wof:placetype":"venue"
},
  "geometry": {"coordinates":[15.8982543945,48.2900276184],"type":"Point"}
}