{
  "type": "Feature",
  "properties": {
    "addr:full":"Kaiserweg 1 Langkampfen Tirol 6336",
    "addr:housenumber":"1",
    "addr:postcode":"6336",
    "addr:street":"Kaiserweg;Tirol",
    "iso:country":"AT",
    "sg:address":"Kaiserweg 1",
    "sg:city":"Langkampfen",
    "sg:orig_category":"Elektroinstallationsunternehmen",
    "sg:phone":"+43 4369 912905809",
    "sg:postcode":"6336",
    "sg:province":"Tirol",
    "wof:name":"Nagler Elektroservice",
    "wof:placetype":"venue"
},
  "geometry": {"coordinates":[12.1034955978,47.5498504639],"type":"Point"}
}