{
  "type": "Feature",
  "properties": {
    "addr:full":"Moostal 51 Gunskirchen Ober\u00f6sterreich 4623",
    "addr:housenumber":"51",
    "addr:postcode":"4623",
    "addr:street":"Moostal",
    "iso:country":"AT",
    "sg:address":"Moostal 51",
    "sg:city":"Gunskirchen",
    "sg:classifiers":[
        {
            "category":"Internet Cafe",
            "subcategory":"None",
            "type":"Food & Drink"
        }
    ],
    "sg:phone":"+43 664 3900406",
    "sg:postcode":"4623",
    "sg:province":"Ober\u00f6sterreich",
    "wof:name":"m-age internet complete",
    "wof:placetype":"venue"
},
  "geometry": {"coordinates":[13.9407653809,48.1326065063],"type":"Point"}
}