{
  "type": "Feature",
  "properties": {
    "iso:country":"AT",
    "sg:address":"Hauptstr 28",
    "sg:city":"Mitterndorf an der Fischa",
    "sg:orig_category":"Volksschulen",
    "sg:phone":"+43 4322 3478835",
    "sg:postcode":"2441",
    "sg:province":"Nieder\u00f6sterreich",
    "wof:name":"Volksschule Mitterndorf an der Fischa",
    "wof:placetype":"venue"
},
  "geometry": {"coordinates":[16.471572876,47.9975013733],"type":"Point"}
}