{
  "type": "Feature",
  "properties": {
    "addr:full":"Fischeredt 9 Frankenburg am Hausruck Ober\u00f6sterreich 4873",
    "addr:housenumber":"9",
    "addr:postcode":"4873",
    "addr:street":"Fischeredt",
    "iso:country":"AT",
    "sg:address":"Fischeredt 9",
    "sg:city":"Frankenburg am Hausruck",
    "sg:orig_category":"Zimmereien",
    "sg:phone":"+43 76838650",
    "sg:postcode":"4873",
    "sg:province":"Ober\u00f6sterreich",
    "wof:name":"Aigner Holzbau GmbH",
    "wof:placetype":"venue"
},
  "geometry": {"coordinates":[13.4651069641,48.0878677368],"type":"Point"}
}