{
  "type": "Feature",
  "properties": {
    "addr:full":"Archeng 19 Schwaz Tirol 6130",
    "addr:housenumber":"19",
    "addr:postcode":"6130",
    "addr:street":"Archeng;Tirol",
    "iso:country":"AT",
    "sg:address":"Archeng 19",
    "sg:city":"Schwaz",
    "sg:orig_category":"Physiotherapie",
    "sg:phone":"+43 5242 62169",
    "sg:postcode":"6130",
    "sg:province":"Tirol",
    "wof:name":"Sch\u00f6pf Barbara Dipl-PT",
    "wof:placetype":"venue"
},
  "geometry": {"coordinates":[11.7040491104,47.3498382568],"type":"Point"}
}