{
  "type": "Feature",
  "properties": {
    "addr:full":"Schulg 37 Nassereith Tirol 6465",
    "addr:housenumber":"37",
    "addr:postcode":"6465",
    "addr:street":"Schulg;Tirol",
    "iso:country":"AT",
    "sg:address":"Schulg 37",
    "sg:city":"Nassereith",
    "sg:orig_category":"Volksschulen",
    "sg:phone":"+43 5265 5271",
    "sg:postcode":"6465",
    "sg:province":"Tirol",
    "wof:name":"Volksschule",
    "wof:placetype":"venue"
},
  "geometry": {"coordinates":[10.8354043961,47.3179550171],"type":"Point"}
}