{
  "type": "Feature",
  "properties": {
    "addr:full":"Triester Str 195 Feldkirchen Steiermark 8073",
    "addr:housenumber":"195",
    "addr:postcode":"8073",
    "iso:country":"AT",
    "sg:address":"Triester Str 195",
    "sg:city":"Feldkirchen",
    "sg:orig_category":"Abbruchunternehmen",
    "sg:phone":"+43 4331 62973110",
    "sg:postcode":"8073",
    "sg:province":"Steiermark",
    "wof:name":"P D M Demontagen-Montagen u Abbrucharbeiten GmbH",
    "wof:placetype":"venue"
},
  "geometry": {"coordinates":[15.453253746,46.9959983826],"type":"Point"}
}