{
  "type": "Feature",
  "properties": {
    "addr:full":"G\u00f6stinger Str 222 G\u00f6sting Steiermark 8051",
    "addr:housenumber":"222",
    "addr:postcode":"8051",
    "addr:street":"Str",
    "iso:country":"AT",
    "sg:address":"G\u00f6stinger Str 222",
    "sg:city":"G\u00f6sting",
    "sg:classifiers":[
        {
            "category":"Home & Garden",
            "subcategory":"Building Materials",
            "type":"Retail Goods"
        }
    ],
    "sg:phone":"+43 4367 65701333",
    "sg:postcode":"8051",
    "sg:province":"Steiermark",
    "sg:tags":[
        "baustoffe",
        "-material",
        "u"
    ],
    "wof:name":"Schneebacher Fertigteilvertrieb KEG",
    "wof:placetype":"venue"
},
  "geometry": {"coordinates":[15.3543653488,47.0787315369],"type":"Point"}
}