{
  "type": "Feature",
  "properties": {
    "addr:full":"Gschwendt 190 Abersee Salzburg 5342",
    "addr:housenumber":"190",
    "addr:postcode":"5342",
    "addr:street":"Gschwendt;Salzburg",
    "iso:country":"AT",
    "sg:address":"Gschwendt 190",
    "sg:city":"Abersee",
    "sg:classifiers":[
        {
            "category":"Autos & Motor Vehicles",
            "subcategory":"Boat Sales",
            "type":"Retail Goods"
        }
    ],
    "sg:phone":"+43 6137 7110",
    "sg:postcode":"5342",
    "sg:province":"Salzburg",
    "sg:tags":[
        "machine",
        "beverage",
        "vending",
        "dispensing"
    ],
    "sg:website":"workerdrink.at",
    "wof:name":"H.O.K. Kling GmbH",
    "wof:placetype":"venue"
},
  "geometry": {"coordinates":[13.4090099335,47.7358894348],"type":"Point"}
}