{
  "type": "Feature",
  "properties": {
    "iso:country":"AT",
    "sg:address":"Ossiacher Zeile 54",
    "sg:city":"Villach",
    "sg:orig_category":"Automaten",
    "sg:phone":"+43 4242 29474",
    "sg:postcode":"9500",
    "sg:province":"K\u00e4rnten",
    "wof:name":"Wirtitsch Willibald Automaten",
    "wof:placetype":"venue"
},
  "geometry": {"coordinates":[13.8582029343,46.6137046814],"type":"Point"}
}