{
  "type": "Feature",
  "properties": {
    "addr:full":"Mergenthalerpl 8 Wien Wien 1220",
    "addr:housenumber":"8",
    "addr:postcode":"1220",
    "addr:street":"Mergenthalerpl",
    "iso:country":"AT",
    "sg:address":"Mergenthalerpl 8",
    "sg:city":"Wien",
    "sg:orig_category":"Friseure U Frisiersalons",
    "sg:phone":"+43 4312 043907",
    "sg:postcode":"1220",
    "sg:province":"Wien",
    "wof:name":"Coiffeur Thomas",
    "wof:placetype":"venue"
},
  "geometry": {"coordinates":[16.44713974,48.2433280945],"type":"Point"}
}