{
  "type": "Feature",
  "properties": {
    "addr:full":"Engelsdorfer Str 4 Eggenburg Nieder\u00f6sterreich 3730",
    "addr:housenumber":"4",
    "addr:postcode":"3730",
    "addr:street":"Str",
    "iso:country":"AT",
    "sg:address":"Engelsdorfer Str 4",
    "sg:city":"Eggenburg",
    "sg:orig_category":"Tischlereien",
    "sg:phone":"+43 2984 3766",
    "sg:postcode":"3730",
    "sg:province":"Nieder\u00f6sterreich",
    "wof:name":"Zeugswetter Hannes",
    "wof:placetype":"venue"
},
  "geometry": {"coordinates":[15.8196926117,48.6488227844],"type":"Point"}
}