{
  "type": "Feature",
  "properties": {
    "addr:full":"Neusiedl am See Burgenland 7100",
    "addr:postcode":"7100",
    "iso:country":"AT",
    "sg:city":"Neusiedl am See",
    "sg:orig_category":"Freizeit, Sport",
    "sg:postcode":"7100",
    "sg:province":"Burgenland",
    "sg:website":"http://uycns.nwy.at/",
    "wof:name":"Union Yacht Club Neusiedlersee",
    "wof:placetype":"venue"
},
  "geometry": {"coordinates":[16.841884613,47.9491081238],"type":"Point"}
}