{
  "type": "Feature",
  "properties": {
    "iso:country":"AT",
    "sg:address":"Leyserstr 5",
    "sg:city":"Wien",
    "sg:orig_category":"Stempel",
    "sg:phone":"+43 1 9146110",
    "sg:postcode":"1140",
    "sg:province":"Wien",
    "wof:name":"LIPPE Stempel Inh G\u00e4rdtner R & Co GesmbH",
    "wof:placetype":"venue"
},
  "geometry": {"coordinates":[16.3022518158,48.1987609863],"type":"Point"}
}