{
  "type": "Feature",
  "properties": {
    "addr:full":"Europastrasse 1  Vitis Nieder\u00f6sterreich 3902",
    "addr:housenumber":"1",
    "addr:postcode":"3902",
    "addr:street":"Europastrasse",
    "iso:country":"AT",
    "sg:address":"Europastrasse 1 ",
    "sg:city":"Vitis",
    "sg:classifiers":[
        {
            "category":"Building & Trades",
            "subcategory":"Plumbing",
            "type":"Services"
        }
    ],
    "sg:phone":"+43 2841 8685",
    "sg:postcode":"3902",
    "sg:province":"Nieder\u00f6sterreich",
    "sg:tags":[
        "supraregional",
        "gas"
    ],
    "wof:name":"FIDA-Installationen GmbH",
    "wof:placetype":"venue"
},
  "geometry": {"coordinates":[15.1932916641,48.7570075989],"type":"Point"}
}