{
  "type": "Feature",
  "properties": {
    "iso:country":"AT",
    "sg:address":"Technikerstrasse 2 - ",
    "sg:city":"Wien",
    "sg:classifiers":[
        {
            "category":"Professional",
            "subcategory":"Art Services",
            "type":"Services"
        }
    ],
    "sg:phone":"+43 1 502750",
    "sg:postcode":"1040",
    "sg:province":"Wien",
    "sg:tags":[
        "export-import"
    ],
    "sg:website":"http://www.ambafrance.at",
    "wof:name":"French Embassy",
    "wof:placetype":"venue"
},
  "geometry": {"coordinates":[16.374080658,48.1987304688],"type":"Point"}
}