{
  "type": "Feature",
  "properties": {
    "addr:full":"Gurnitzer Strasse 10  Ebenthal in K\u00e4rnten K\u00e4rnten 9065",
    "addr:housenumber":"10",
    "addr:postcode":"9065",
    "addr:street":"Gurnitzer Strasse;Kaernten",
    "iso:country":"AT",
    "sg:address":"Gurnitzer Strasse 10 ",
    "sg:city":"Ebenthal in K\u00e4rnten",
    "sg:classifiers":[
        {
            "category":"Building & Trades",
            "subcategory":"Plumbing",
            "type":"Services"
        }
    ],
    "sg:phone":"+43 463 73254",
    "sg:postcode":"9065",
    "sg:province":"K\u00e4rnten",
    "sg:tags":[
        "supraregional",
        "gas"
    ],
    "wof:name":"Klaus Kienzl",
    "wof:placetype":"venue"
},
  "geometry": {"coordinates":[14.3609018326,46.6046600342],"type":"Point"}
}