{
  "type": "Feature",
  "properties": {
    "addr:full":"Mariazeller Str 39 Traisen Nieder\u00f6sterreich 3160",
    "addr:postcode":"3160",
    "addr:street":"Str 39",
    "iso:country":"AT",
    "sg:address":"Mariazeller Str 39",
    "sg:city":"Traisen",
    "sg:orig_category":"Fleischhauereien",
    "sg:phone":"+43 2762 62421",
    "sg:postcode":"3160",
    "sg:province":"Nieder\u00f6sterreich",
    "wof:name":"Bertl Johann",
    "wof:placetype":"venue"
},
  "geometry": {"coordinates":[15.6092453003,48.0437774658],"type":"Point"}
}