{
  "type": "Feature",
  "properties": {
    "addr:full":"Leopoldskronstr 7 Salzburg Salzburg 5020",
    "addr:housenumber":"7",
    "addr:postcode":"5020",
    "addr:street":"Leopoldskronstr;Salzburg",
    "iso:country":"AT",
    "sg:address":"Leopoldskronstr 7",
    "sg:city":"Salzburg",
    "sg:orig_category":"Holzhandel",
    "sg:phone":"+43 662 829025",
    "sg:postcode":"5020",
    "sg:province":"Salzburg",
    "wof:name":"Eder Wolfgang",
    "wof:placetype":"venue"
},
  "geometry": {"coordinates":[13.0320520401,47.7952613831],"type":"Point"}
}