{
  "type": "Feature",
  "properties": {
    "addr:full":"Hirtenberger Str 6 B Kottingbrunn Nieder\u00f6sterreich 2542",
    "addr:housenumber":"6 b",
    "addr:postcode":"2542",
    "addr:street":"Str",
    "iso:country":"AT",
    "sg:address":"Hirtenberger Str 6 B",
    "sg:city":"Kottingbrunn",
    "sg:orig_category":"Maschinenbau",
    "sg:phone":"+43 2252 739720",
    "sg:postcode":"2542",
    "sg:province":"Nieder\u00f6sterreich",
    "wof:name":"Mannsberger & Co GmbH",
    "wof:placetype":"venue"
},
  "geometry": {"coordinates":[16.2197036743,47.9349899292],"type":"Point"}
}