{
  "type": "Feature",
  "properties": {
    "addr:full":"Gabelsberger Str 18 Baden Nieder\u00f6sterreich 2500",
    "addr:housenumber":"18",
    "addr:postcode":"2500",
    "addr:street":"Str;Niederoesterreich",
    "iso:country":"AT",
    "sg:address":"Gabelsberger Str 18",
    "sg:city":"Baden",
    "sg:orig_category":"Physiotherapie",
    "sg:phone":"+43 2252 84835",
    "sg:postcode":"2500",
    "sg:province":"Nieder\u00f6sterreich",
    "wof:name":"Lavicka Susanne Dipl-PT",
    "wof:placetype":"venue"
},
  "geometry": {"coordinates":[16.2505302429,48.0091171265],"type":"Point"}
}