{
  "type": "Feature",
  "properties": {
    "iso:country":"AT",
    "sg:address":"Landstra\u00dfer Hauptstr 83-85",
    "sg:city":"Wien",
    "sg:orig_category":"Handschuhe",
    "sg:phone":"+43 1 7159731",
    "sg:postcode":"1030",
    "sg:province":"Wien",
    "wof:name":"Handschuhpeter Erz und Hdl m Handschuhen aller Art Peter Peter",
    "wof:placetype":"venue"
},
  "geometry": {"coordinates":[16.393819809,48.1999130249],"type":"Point"}
}