{
  "type": "Feature",
  "properties": {
    "addr:full":"Steyrtalstr 83 Neuzeug Ober\u00f6sterreich 4523",
    "addr:housenumber":"83",
    "addr:postcode":"4523",
    "addr:street":"Steyrtalstr",
    "iso:country":"AT",
    "sg:address":"Steyrtalstr 83",
    "sg:city":"Neuzeug",
    "sg:orig_category":"Tankstellen",
    "sg:phone":"+43 7259 27200",
    "sg:postcode":"4523",
    "sg:province":"Ober\u00f6sterreich",
    "wof:name":"PETROL Corporation Betriebs GmbH",
    "wof:placetype":"venue"
},
  "geometry": {"coordinates":[14.330329895,48.0440711975],"type":"Point"}
}