{
  "type": "Feature",
  "properties": {
    "addr:full":"Sterneckstr 53 Klagenfurt K\u00e4rnten 9020",
    "addr:housenumber":"53",
    "addr:postcode":"9020",
    "addr:street":"Sterneckstr;Kaernten",
    "iso:country":"AT",
    "sg:address":"Sterneckstr 53",
    "sg:city":"Klagenfurt",
    "sg:orig_category":"Fu\u00c3\u0178pflege U Fu\u00c3\u0178pflegesalons",
    "sg:phone":"+43 463 5007060",
    "sg:postcode":"9020",
    "sg:province":"K\u00e4rnten",
    "wof:name":"la biovital K\u00f6rperpflege",
    "wof:placetype":"venue"
},
  "geometry": {"coordinates":[14.2928733826,46.6254577637],"type":"Point"}
}