{
  "type": "Feature",
  "properties": {
    "addr:full":"Pirching 90 Gleisdorf Steiermark 8200",
    "addr:housenumber":"90",
    "addr:postcode":"8200",
    "addr:street":"Pirching",
    "iso:country":"AT",
    "sg:address":"Pirching 90",
    "sg:city":"Gleisdorf",
    "sg:classifiers":[
        {
            "category":"Community Center",
            "subcategory":"Social",
            "type":"Public Place"
        }
    ],
    "sg:phone":"+43 4331 127366",
    "sg:postcode":"8200",
    "sg:province":"Steiermark",
    "sg:tags":[
        "profile"
    ],
    "wof:name":"SAPA Building System VertriebsgesmbH",
    "wof:placetype":"venue"
},
  "geometry": {"coordinates":[15.7400770187,47.0868225098],"type":"Point"}
}