{
  "type": "Feature",
  "properties": {
    "addr:full":"Wiener Str 12 Eichgraben Nieder\u00f6sterreich 3032",
    "addr:postcode":"3032",
    "addr:street":"Eichgraben",
    "iso:country":"AT",
    "sg:address":"Wiener Str 12",
    "sg:city":"Eichgraben",
    "sg:orig_category":"Blumengro\u00c3\u0178handel",
    "sg:phone":"+43 4327 7346749",
    "sg:postcode":"3032",
    "sg:province":"Nieder\u00f6sterreich",
    "wof:name":"Blumen Kaljosi KEG",
    "wof:placetype":"venue"
},
  "geometry": {"coordinates":[15.976061821,48.1822891235],"type":"Point"}
}