{
  "type": "Feature",
  "properties": {
    "addr:full":"Leondinger Str 35a Traun Ober\u00f6sterreich 4050",
    "addr:housenumber":"35a",
    "addr:postcode":"4050",
    "addr:street":"Str",
    "iso:country":"AT",
    "sg:address":"Leondinger Str 35a",
    "sg:city":"Traun",
    "sg:orig_category":"Ingenieurkonsulenten / Zivilingenieure",
    "sg:phone":"+43 7229 70672",
    "sg:postcode":"4050",
    "sg:province":"Ober\u00f6sterreich",
    "wof:name":"Sagl Franz Werner Dipl-Ing",
    "wof:placetype":"venue"
},
  "geometry": {"coordinates":[14.2610998154,48.240486145],"type":"Point"}
}