{
  "type": "Feature",
  "properties": {
    "addr:full":"Erzabt Klotz-Str 21 Salzburg Salzburg 5020",
    "addr:housenumber":"21",
    "addr:postcode":"5020",
    "addr:street":"Klotz-Str;Salzburg",
    "iso:country":"AT",
    "sg:address":"Erzabt Klotz-Str 21",
    "sg:city":"Salzburg",
    "sg:classifiers":[
        {
            "category":"Restaurant",
            "type":"Food & Drink"
        }
    ],
    "sg:phone":"+43 662 831827",
    "sg:postcode":"5020",
    "sg:province":"Salzburg",
    "wof:name":"SOG Bar-Trattoria",
    "wof:placetype":"venue"
},
  "geometry": {"coordinates":[13.0518960953,47.7924385071],"type":"Point"}
}