{
  "type": "Feature",
  "properties": {
    "addr:full":"Haidfeldstr. 37  Leonding Ober\u00f6sterreich 4060",
    "addr:housenumber":"37",
    "addr:postcode":"4060",
    "addr:street":"Haidfeldstr.",
    "iso:country":"AT",
    "sg:address":"Haidfeldstr. 37 ",
    "sg:city":"Leonding",
    "sg:classifiers":[
        {
            "category":"Wholesale",
            "subcategory":"Machinery & Supplies",
            "type":"Manufacturing & Wholesale Goods"
        }
    ],
    "sg:phone":"+43 4373 27753000",
    "sg:postcode":"4060",
    "sg:province":"Ober\u00f6sterreich",
    "sg:tags":[
        "-",
        "agriculture",
        "equipment"
    ],
    "wof:name":"MHT GMBH",
    "wof:placetype":"venue"
},
  "geometry": {"coordinates":[14.2599143982,48.2564353943],"type":"Point"}
}