{
  "type": "Feature",
  "properties": {
    "addr:full":"Vordernberger Str 24 Leoben Steiermark 8700",
    "addr:housenumber":"24",
    "addr:postcode":"8700",
    "addr:street":"Str",
    "iso:country":"AT",
    "sg:address":"Vordernberger Str 24",
    "sg:city":"Leoben",
    "sg:orig_category":"Immobilienmakler",
    "sg:phone":"+43 3842 25648",
    "sg:postcode":"8700",
    "sg:province":"Steiermark",
    "sg:website":"www.stengg-invest.at",
    "wof:name":"Stengg GmbH",
    "wof:placetype":"venue"
},
  "geometry": {"coordinates":[15.0891180038,47.3795967102],"type":"Point"}
}