{
  "type": "Feature",
  "properties": {
    "addr:full":"Zedlitzg 1 Wien Wien 1010",
    "addr:housenumber":"1",
    "addr:postcode":"1010",
    "addr:street":"Zedlitzg",
    "iso:country":"AT",
    "sg:address":"Zedlitzg 1",
    "sg:city":"Wien",
    "sg:orig_category":"Geschenkartikel",
    "sg:phone":"+43 1 5127212",
    "sg:postcode":"1010",
    "sg:province":"Wien",
    "wof:name":"BellArte - Geschenkboutique",
    "wof:placetype":"venue"
},
  "geometry": {"coordinates":[16.3775215149,48.2076072693],"type":"Point"}
}