{
  "type": "Feature",
  "properties": {
    "addr:full":"Koglehen 3a Fieberbrunn Tirol 6391",
    "addr:housenumber":"3a",
    "addr:postcode":"6391",
    "addr:street":"Koglehen;Tirol",
    "iso:country":"AT",
    "sg:address":"Koglehen 3a",
    "sg:city":"Fieberbrunn",
    "sg:orig_category":"Appartements / Ferienwohnungen",
    "sg:phone":"+43 5354 563840",
    "sg:postcode":"6391",
    "sg:province":"Tirol",
    "wof:name":"Haus Brigitte",
    "wof:placetype":"venue"
},
  "geometry": {"coordinates":[12.5477838516,47.4726028442],"type":"Point"}
}