{
  "type": "Feature",
  "properties": {
    "addr:full":"Michael Hofer Str. 133  Lichtenw\u00f6rth Nieder\u00f6sterreich 2493",
    "addr:housenumber":"133",
    "addr:postcode":"2493",
    "addr:street":"Str.;Niederoesterreich",
    "iso:country":"AT",
    "sg:address":"Michael Hofer Str. 133 ",
    "sg:city":"Lichtenw\u00f6rth",
    "sg:classifiers":[
        {
            "category":"Food & Beverages",
            "subcategory":"Bakery",
            "type":"Retail Goods"
        }
    ],
    "sg:phone":"+43 4326 2275203",
    "sg:postcode":"2493",
    "sg:province":"Nieder\u00f6sterreich",
    "sg:tags":[
        "grain",
        "cereal"
    ],
    "wof:name":"HANS HOFER GMBH",
    "wof:placetype":"venue"
},
  "geometry": {"coordinates":[16.2962799072,47.8375015259],"type":"Point"}
}