{
  "type": "Feature",
  "properties": {
    "iso:country":"AT",
    "sg:address":"Gro\u00dfmarktstr. 5b",
    "sg:city":"Wien",
    "sg:classifiers":[
        {
            "category":"Shopping",
            "subcategory":"Clothing, Apparel, & Fashions",
            "type":"Retail Goods"
        }
    ],
    "sg:phone":"+43 4316 1739290",
    "sg:postcode":"1230",
    "sg:province":"Wien",
    "sg:tags":[
        "clothing",
        "accessory"
    ],
    "wof:name":"SPIGO ETIKETTEN ERZEUGUNG & VERTRIEB GMBH",
    "wof:placetype":"venue"
},
  "geometry": {"coordinates":[16.3655891418,48.1435852051],"type":"Point"}
}