{
  "type": "Feature",
  "properties": {
    "addr:full":"Auwinkl 4 Ellmau Tirol 6352",
    "addr:housenumber":"4",
    "addr:postcode":"6352",
    "addr:street":"Auwinkl;Tirol",
    "iso:country":"AT",
    "sg:address":"Auwinkl 4",
    "sg:city":"Ellmau",
    "sg:orig_category":"Spirituosen / Erzeugung U Gro\u00c3\u0178handel",
    "sg:phone":"+43 4353 582540",
    "sg:postcode":"6352",
    "sg:province":"Tirol",
    "wof:name":"Brennerei Spielthenner",
    "wof:placetype":"venue"
},
  "geometry": {"coordinates":[12.2758407593,47.5181007385],"type":"Point"}
}