{
  "type": "Feature",
  "properties": {
    "addr:full":"Hollabererstrasse 4c Linz Ober\u00f6sterreich 4020",
    "addr:housenumber":"4c",
    "addr:postcode":"4020",
    "addr:street":"Hollabererstrasse",
    "iso:country":"AT",
    "sg:address":"Hollabererstrasse 4c",
    "sg:city":"Linz",
    "sg:classifiers":[
        {
            "category":"Military Area",
            "subcategory":"Air Force Base",
            "type":"Public Place"
        }
    ],
    "sg:phone":"+43 732 6611550",
    "sg:postcode":"4020",
    "sg:province":"Ober\u00f6sterreich",
    "sg:tags":[
        "fire",
        "restoration",
        "damage"
    ],
    "sg:website":"bws-sanierung.at",
    "wof:name":"BWS Brand-, Wasser- und Sturmschadensanierungs Ges.m.b.H. & Co KG",
    "wof:placetype":"venue"
},
  "geometry": {"coordinates":[14.3286962509,48.3007888794],"type":"Point"}
}