{
  "type": "Feature",
  "properties": {
    "iso:country":"AT",
    "sg:address":"Diesseits 145",
    "sg:city":"St. Martin im Innkreis",
    "sg:classifiers":[
        {
            "category":"Utilities",
            "subcategory":"Electric",
            "type":"Services"
        }
    ],
    "sg:phone":"+43 4377 5161220",
    "sg:postcode":"4973",
    "sg:province":"Ober\u00f6sterreich",
    "sg:tags":[
        "component",
        "electronic"
    ],
    "wof:name":"PC ELECTRIC GMBH",
    "wof:placetype":"venue"
},
  "geometry": {"coordinates":[13.4180746078,48.261505127],"type":"Point"}
}