{
  "type": "Feature",
  "properties": {
    "addr:full":"Birkenweg 2 St. Marienkirchen Ober\u00f6sterreich 4774",
    "addr:housenumber":"2",
    "addr:postcode":"4774",
    "addr:street":"Birkenweg",
    "iso:country":"AT",
    "sg:address":"Birkenweg 2",
    "sg:city":"St. Marienkirchen",
    "sg:orig_category":"Fenster",
    "sg:phone":"+43 4377 112431",
    "sg:postcode":"4774",
    "sg:province":"Ober\u00f6sterreich",
    "wof:name":"Reinthaler Hartmut",
    "wof:placetype":"venue"
},
  "geometry": {"coordinates":[13.4512290955,48.3879585266],"type":"Point"}
}