{
  "type": "Feature",
  "properties": {
    "addr:full":"Jacquing 25 Wien Wien 1030",
    "addr:housenumber":"25",
    "addr:postcode":"1030",
    "addr:street":"Jacquing",
    "iso:country":"AT",
    "sg:address":"Jacquing 25",
    "sg:city":"Wien",
    "sg:orig_category":"Autovermietung",
    "sg:phone":"+43 1 7987911",
    "sg:postcode":"1030",
    "sg:province":"Wien",
    "wof:name":"Oliva Thomas",
    "wof:placetype":"venue"
},
  "geometry": {"coordinates":[16.3850841522,48.1923751831],"type":"Point"}
}