{
  "type": "Feature",
  "properties": {
    "iso:country":"AT",
    "sg:address":"Franz-Auracher-Str 2",
    "sg:city":"Lenzing",
    "sg:orig_category":"Hauptschulen",
    "sg:phone":"+43 4376 7292917",
    "sg:postcode":"4860",
    "sg:province":"Ober\u00f6sterreich",
    "wof:name":"Hauptschule",
    "wof:placetype":"venue"
},
  "geometry": {"coordinates":[13.6312246323,47.9887275696],"type":"Point"}
}