{
  "type": "Feature",
  "properties": {
    "addr:full":"Schmalzhofg 2-4 Wien Wien 1060",
    "addr:housenumber":"2-4",
    "addr:postcode":"1060",
    "addr:street":"Schmalzhofg",
    "iso:country":"AT",
    "sg:address":"Schmalzhofg 2-4",
    "sg:city":"Wien",
    "sg:orig_category":"Leder",
    "sg:phone":"+43 1 59743160",
    "sg:postcode":"1060",
    "sg:province":"Wien",
    "wof:name":"Kaulich Hans GesmbH",
    "wof:placetype":"venue"
},
  "geometry": {"coordinates":[16.3481178284,48.196231842],"type":"Point"}
}