{
  "type": "Feature",
  "properties": {
    "addr:full":"Alser Str 17 Wien Wien 1080",
    "addr:postcode":"1080",
    "addr:street":"Str 17",
    "iso:country":"AT",
    "sg:address":"Alser Str 17",
    "sg:city":"Wien",
    "sg:orig_category":"Non-Classified Establishments",
    "sg:phone":"+43 1 40591420",
    "sg:postcode":"1080",
    "sg:province":"Wien",
    "wof:name":"Minoritenkonvent",
    "wof:placetype":"venue"
},
  "geometry": {"coordinates":[16.3527393341,48.2146911621],"type":"Point"}
}