{
  "type": "Feature",
  "properties": {
    "addr:full":"Wiener Str 65 Amstetten Nieder\u00f6sterreich 3300",
    "addr:postcode":"3300",
    "addr:street":"Niederoesterreich",
    "iso:country":"AT",
    "sg:address":"Wiener Str 65",
    "sg:city":"Amstetten",
    "sg:orig_category":"Installationsunternehmen",
    "sg:phone":"+43 7472 28103",
    "sg:postcode":"3300",
    "sg:province":"Nieder\u00f6sterreich",
    "wof:name":"Mac Therm Energie-Systeme Ing Alois Pfleger KEG",
    "wof:placetype":"venue"
},
  "geometry": {"coordinates":[14.8824987411,48.1230010986],"type":"Point"}
}