{
  "type": "Feature",
  "properties": {
    "iso:country":"AT",
    "sg:address":"Moosstr 78a",
    "sg:city":"Salzburg",
    "sg:orig_category":"Volksschulen",
    "sg:phone":"+43 662 8249410",
    "sg:postcode":"5020",
    "sg:province":"Salzburg",
    "wof:name":"Volksschule Leopoldskron",
    "wof:placetype":"venue"
},
  "geometry": {"coordinates":[13.0242452621,47.7806129456],"type":"Point"}
}