{
  "type": "Feature",
  "properties": {
    "addr:full":"Formerg 4 Lichtenw\u00f6rth Nieder\u00f6sterreich 2493",
    "addr:housenumber":"4",
    "addr:postcode":"2493",
    "addr:street":"Formerg;Niederoesterreich",
    "iso:country":"AT",
    "sg:address":"Formerg 4",
    "sg:city":"Lichtenw\u00f6rth",
    "sg:classifiers":[
        {
            "category":"Taxi",
            "type":"Transportation"
        }
    ],
    "sg:phone":"+43 4326 2275190",
    "sg:postcode":"2493",
    "sg:province":"Nieder\u00f6sterreich",
    "sg:tags":[
        "personentransporte",
        "u"
    ],
    "wof:name":"Michael Perner",
    "wof:placetype":"venue"
},
  "geometry": {"coordinates":[16.2965755463,47.8385543823],"type":"Point"}
}