{
  "type": "Feature",
  "properties": {
    "addr:full":"Nr 272 Gro\u00dfarl Salzburg 5611",
    "addr:postcode":"5611",
    "addr:street":"Nr 272;Salzburg",
    "iso:country":"AT",
    "sg:address":"Nr 272",
    "sg:city":"Gro\u00dfarl",
    "sg:classifiers":[
        {
            "category":"Travel",
            "subcategory":"Hotels & Motels",
            "type":"Entertainment"
        }
    ],
    "sg:phone":"+43 6414 88660",
    "sg:postcode":"5611",
    "sg:province":"Salzburg",
    "wof:name":"Hotel Waldhof",
    "wof:placetype":"venue"
},
  "geometry": {"coordinates":[-87.2457733154,34.0378608704],"type":"Point"}
}