{
  "type": "Feature",
  "properties": {
    "iso:country":"AT",
    "sg:address":"Hauptstrasse 16",
    "sg:city":"Gr\u00f6dig",
    "sg:classifiers":[
        {
            "category":"Food & Beverages",
            "subcategory":"Chocolate",
            "type":"Retail Goods"
        }
    ],
    "sg:phone":"+43 6246 75310",
    "sg:postcode":"5082",
    "sg:province":"Salzburg",
    "sg:website":"sweets.at",
    "wof:name":"Salzburg Sweets Produktions- und Vertriebsges.m.b.H & Co KG",
    "wof:placetype":"venue"
},
  "geometry": {"coordinates":[-76.2684555054,37.4373283386],"type":"Point"}
}