{
  "type": "Feature",
  "properties": {
    "addr:full":"Vogeltennweg 12 Waidring Tirol 6384",
    "addr:housenumber":"12",
    "addr:postcode":"6384",
    "addr:street":"Vogeltennweg;Tirol",
    "iso:country":"AT",
    "sg:address":"Vogeltennweg 12",
    "sg:city":"Waidring",
    "sg:orig_category":"Handelsagenturen",
    "sg:phone":"+43 4353 5352066",
    "sg:postcode":"6384",
    "sg:province":"Tirol",
    "wof:name":"Kunz Friedrich",
    "wof:placetype":"venue"
},
  "geometry": {"coordinates":[12.5633583069,47.5845756531],"type":"Point"}
}