{
  "type": "Feature",
  "properties": {
    "addr:full":"St Michaeler Str 44 Wolfsberg K\u00e4rnten 9400",
    "addr:housenumber":"44;kaernten",
    "addr:postcode":"9400",
    "addr:street":"St Michaeler Str",
    "iso:country":"AT",
    "sg:address":"St Michaeler Str 44",
    "sg:city":"Wolfsberg",
    "sg:orig_category":"Polizei U Gendarmerie",
    "sg:phone":"+43 5 91332171",
    "sg:postcode":"9400",
    "sg:province":"K\u00e4rnten",
    "wof:name":"Gendarmerie Autobahnau\u00dfenstelle Wolfsberg d Verkehrsabteilung",
    "wof:placetype":"venue"
},
  "geometry": {"coordinates":[14.826177597,46.8361549377],"type":"Point"}
}