{
  "type": "Feature",
  "properties": {
    "iso:country":"AT",
    "sg:address":"Conrad-von-H\u00f6tzendorf-Str 116",
    "sg:city":"Graz",
    "sg:classifiers":[
        {
            "category":"Community Center",
            "subcategory":"Social",
            "type":"Public Place"
        }
    ],
    "sg:phone":"+43 4331 64655200",
    "sg:postcode":"8010",
    "sg:province":"Steiermark",
    "sg:tags":[
        "profile"
    ],
    "wof:name":"Hoesch Bausysteme GmbH",
    "wof:placetype":"venue"
},
  "geometry": {"coordinates":[15.4493122101,47.0530319214],"type":"Point"}
}