{
  "type": "Feature",
  "properties": {
    "addr:full":"Dorf 5/6 Schwaz Tirol 6130",
    "addr:housenumber":"5 / 6",
    "addr:postcode":"6130",
    "addr:street":"Dorf;Tirol",
    "iso:country":"AT",
    "sg:address":"Dorf 5/6",
    "sg:city":"Schwaz",
    "sg:orig_category":"Spirituosen / Erzeugung U Gro\u00c3\u0178handel",
    "sg:phone":"+43 5242 632420",
    "sg:postcode":"6130",
    "sg:province":"Tirol",
    "wof:name":"BRELU Brennereifachbedarf",
    "wof:placetype":"venue"
},
  "geometry": {"coordinates":[11.6807641983,47.3193206787],"type":"Point"}
}