{
  "type": "Feature",
  "properties": {
    "addr:full":"Kirchenpl 6 Wolfern Ober\u00f6sterreich 4493",
    "addr:housenumber":"6",
    "addr:postcode":"4493",
    "addr:street":"Kirchenpl",
    "iso:country":"AT",
    "sg:address":"Kirchenpl 6",
    "sg:city":"Wolfern",
    "sg:orig_category":"Lebensmittel / Einzelhandel",
    "sg:phone":"+43 7253 82060",
    "sg:postcode":"4493",
    "sg:province":"Ober\u00f6sterreich",
    "wof:name":"Kaufhaus Zwicklhuber",
    "wof:placetype":"venue"
},
  "geometry": {"coordinates":[14.3780670166,48.0832977295],"type":"Point"}
}