{
  "type": "Feature",
  "properties": {
    "addr:full":"Muthg 18/Haus B Wien Wien 1190",
    "addr:housenumber":"18 / haus b",
    "addr:postcode":"1190",
    "addr:street":"Muthg",
    "iso:country":"AT",
    "sg:address":"Muthg 18/Haus B",
    "sg:city":"Wien",
    "sg:orig_category":"Institute",
    "sg:phone":"+43 1 360061205",
    "sg:postcode":"1190",
    "sg:province":"Wien",
    "wof:name":"Laboratorium f\u00fcr Betriebshygiene GmbH",
    "wof:placetype":"venue"
},
  "geometry": {"coordinates":[16.3493022919,48.2389793396],"type":"Point"}
}