{
  "type": "Feature",
  "properties": {
    "addr:full":"Neug 45 Gleisdorf Steiermark 8200",
    "addr:housenumber":"45",
    "addr:postcode":"8200",
    "addr:street":"Neug",
    "iso:country":"AT",
    "sg:address":"Neug 45",
    "sg:city":"Gleisdorf",
    "sg:orig_category":"Transportunternehmen",
    "sg:phone":"+43 3112 2033",
    "sg:postcode":"8200",
    "sg:province":"Steiermark",
    "wof:name":"Krautwaschl Alois",
    "wof:placetype":"venue"
},
  "geometry": {"coordinates":[15.6912050247,47.103477478],"type":"Point"}
}