{
  "type": "Feature",
  "properties": {
    "addr:full":"Schwimmbadweg 19 Zirl Tirol 6170",
    "addr:housenumber":"19",
    "addr:postcode":"6170",
    "addr:street":"Schwimmbadweg;Tirol",
    "iso:country":"AT",
    "sg:address":"Schwimmbadweg 19",
    "sg:city":"Zirl",
    "sg:orig_category":"Tischlereien",
    "sg:phone":"+43 5238 52002",
    "sg:postcode":"6170",
    "sg:province":"Tirol",
    "wof:name":"Donnerbauer Andreas",
    "wof:placetype":"venue"
},
  "geometry": {"coordinates":[11.2362203598,47.2762298584],"type":"Point"}
}