{
  "type": "Feature",
  "properties": {
    "addr:full":"Industriestr 1 Wolfsberg K\u00e4rnten 9400",
    "addr:housenumber":"1;kaernten",
    "addr:postcode":"9400",
    "addr:street":"Industriestr",
    "iso:country":"AT",
    "sg:address":"Industriestr 1",
    "sg:city":"Wolfsberg",
    "sg:orig_category":"Damenmoden",
    "sg:phone":"+43 4343 5236337",
    "sg:postcode":"9400",
    "sg:province":"K\u00e4rnten",
    "wof:name":"KiK Textilien u Non-Food GesmbH",
    "wof:placetype":"venue"
},
  "geometry": {"coordinates":[14.8414430618,46.8234786987],"type":"Point"}
}