{
  "type": "Feature",
  "properties": {
    "addr:full":"Nr 38a St. Stefan ob Stainz Steiermark 8511",
    "addr:postcode":"8511",
    "addr:street":"Nr 38A St.",
    "iso:country":"AT",
    "sg:address":"Nr 38a",
    "sg:city":"St. Stefan ob Stainz",
    "sg:orig_category":"Installationsunternehmen",
    "sg:phone":"+43 3463 81715",
    "sg:postcode":"8511",
    "sg:province":"Steiermark",
    "wof:name":"Sancar Inh Wolfgang Sattinger KEG",
    "wof:placetype":"venue"
},
  "geometry": {"coordinates":[15.2549381256,46.9294662476],"type":"Point"}
}