{
  "type": "Feature",
  "properties": {
    "addr:full":"Ebensee Ober\u00f6sterreich 4802",
    "addr:postcode":"4802",
    "iso:country":"AT",
    "sg:city":"Ebensee",
    "sg:orig_category":"Feuerwehren",
    "sg:phone":"+43 6133 4640",
    "sg:postcode":"4802",
    "sg:province":"Ober\u00f6sterreich",
    "wof:name":"Freiwillige Feuerwehr Rindbach",
    "wof:placetype":"venue"
},
  "geometry": {"coordinates":[13.7918968201,47.8058204651],"type":"Point"}
}