{
  "type": "Feature",
  "properties": {
    "addr:full":"Schlo\u00dfhof 1a Mondsee Ober\u00f6sterreich 5310",
    "addr:housenumber":"1a",
    "addr:postcode":"5310",
    "addr:street":"Schlosshof;Oberoesterreich",
    "iso:country":"AT",
    "sg:address":"Schlo\u00dfhof 1a",
    "sg:city":"Mondsee",
    "sg:classifiers":[
        {
            "category":"Travel",
            "subcategory":"Hotels & Motels",
            "type":"Entertainment"
        }
    ],
    "sg:phone":"+43 6232 50010",
    "sg:postcode":"5310",
    "sg:province":"Ober\u00f6sterreich",
    "wof:name":"Hotel Schloss Mondsee",
    "wof:placetype":"venue"
},
  "geometry": {"coordinates":[13.3499908447,47.8565254211],"type":"Point"}
}