{
  "type": "Feature",
  "properties": {
    "addr:full":"Warmbader Strasse 5 Villach K\u00e4rnten 9500",
    "addr:housenumber":"5",
    "addr:postcode":"9500",
    "addr:street":"Warmbader Strasse;Kaernten",
    "iso:country":"AT",
    "sg:address":"Warmbader Strasse 5",
    "sg:city":"Villach",
    "sg:classifiers":[
        {
            "category":"Organizations",
            "subcategory":"Professional Association",
            "type":"Services"
        }
    ],
    "sg:phone":"+43 4242 31033",
    "sg:postcode":"9500",
    "sg:province":"K\u00e4rnten",
    "sg:tags":[
        "ceiling",
        "heating",
        "system"
    ],
    "sg:website":"wikinger.energiequellen.at",
    "wof:name":"Wikinger Produktentwicklung Ges.m.b.H.",
    "wof:placetype":"venue"
},
  "geometry": {"coordinates":[13.8350982666,46.5997200012],"type":"Point"}
}