{
  "type": "Feature",
  "properties": {
    "addr:full":"Gaisbergstr 40A Salzburg Salzburg 5020",
    "addr:housenumber":"40a",
    "addr:postcode":"5020",
    "addr:street":"Gaisbergstr;Salzburg",
    "iso:country":"AT",
    "sg:address":"Gaisbergstr 40A",
    "sg:city":"Salzburg",
    "sg:orig_category":"Dolmetscher",
    "sg:phone":"+43 662 641557",
    "sg:postcode":"5020",
    "sg:province":"Salzburg",
    "wof:name":"Witek Sabine",
    "wof:placetype":"venue"
},
  "geometry": {"coordinates":[13.0740299225,47.8020782471],"type":"Point"}
}