{
  "type": "Feature",
  "properties": {
    "addr:full":"Gewerbeparkstr 3 Wien Wien 1220",
    "addr:housenumber":"3",
    "addr:postcode":"1220",
    "addr:street":"Gewerbeparkstr",
    "iso:country":"AT",
    "sg:address":"Gewerbeparkstr 3",
    "sg:city":"Wien",
    "sg:orig_category":"Autoersatzteile",
    "sg:phone":"+43 1 7344244",
    "sg:postcode":"1220",
    "sg:province":"Wien",
    "wof:name":"Forstinger Handel und Service GmbH",
    "wof:placetype":"venue"
},
  "geometry": {"coordinates":[16.4646835327,48.246837616],"type":"Point"}
}