{
  "type": "Feature",
  "properties": {
    "addr:full":"Hohenstein 7 Liebenfels K\u00e4rnten 9556",
    "addr:housenumber":"7",
    "addr:postcode":"9556",
    "addr:street":"Hohenstein;Kaernten",
    "iso:country":"AT",
    "sg:address":"Hohenstein 7",
    "sg:city":"Liebenfels",
    "sg:orig_category":"Transportunternehmen",
    "sg:phone":"+43 676 842614100",
    "sg:postcode":"9556",
    "sg:province":"K\u00e4rnten",
    "wof:name":"Kronawetter-Intern Transporte GesmbH",
    "wof:placetype":"venue"
},
  "geometry": {"coordinates":[14.2897233963,46.7452545166],"type":"Point"}
}