{
  "type": "Feature",
  "properties": {
    "addr:full":"Altenmarkt 52 Altenmarkt im Pongau Salzburg 5541",
    "addr:housenumber":"52",
    "addr:postcode":"5541",
    "addr:street":"Altenmarkt;Salzburg",
    "iso:country":"AT",
    "sg:address":"Altenmarkt 52",
    "sg:city":"Altenmarkt im Pongau",
    "sg:classifiers":[
        {
            "category":"Autos & Motor Vehicles",
            "subcategory":"Automobile Sales",
            "type":"Retail Goods"
        }
    ],
    "sg:phone":"+43 4364 526350",
    "sg:postcode":"5541",
    "sg:province":"Salzburg",
    "sg:tags":[
        "industrial"
    ],
    "wof:name":"GERNOT JURTIN GMBH & CO KG",
    "wof:placetype":"venue"
},
  "geometry": {"coordinates":[13.4235315323,47.3788032532],"type":"Point"}
}