{
  "type": "Feature",
  "properties": {
    "addr:full":"Weblinger Str 37 Stra\u00dfgang Steiermark 8054",
    "addr:housenumber":"37",
    "addr:postcode":"8054",
    "addr:street":"Weblinger Str",
    "iso:country":"AT",
    "sg:address":"Weblinger Str 37",
    "sg:city":"Stra\u00dfgang",
    "sg:classifiers":[
        {
            "category":"Home & Garden",
            "subcategory":"Building Materials",
            "type":"Retail Goods"
        }
    ],
    "sg:phone":"+43 4350 161646",
    "sg:postcode":"8054",
    "sg:province":"Steiermark",
    "sg:tags":[
        "baustoffe",
        "-material",
        "u"
    ],
    "wof:name":"Quester Baustoffhandel GmbH & Co KG",
    "wof:placetype":"venue"
},
  "geometry": {"coordinates":[15.402007103,47.030582428],"type":"Point"}
}