{
  "type": "Feature",
  "properties": {
    "addr:full":"Niederreithstr 43 Linz Ober\u00f6sterreich 4020",
    "addr:housenumber":"43",
    "addr:postcode":"4020",
    "addr:street":"Niederreithstr",
    "iso:country":"AT",
    "sg:address":"Niederreithstr 43",
    "sg:city":"Linz",
    "sg:orig_category":"Ingenieurkonsulenten / Zivilingenieure",
    "sg:phone":"+43 4373 2656088",
    "sg:postcode":"4020",
    "sg:province":"Ober\u00f6sterreich",
    "sg:website":"eitler.at",
    "wof:name":"Eitler Dipl-Ing & Partner Ziviltechniker OEG",
    "wof:placetype":"venue"
},
  "geometry": {"coordinates":[14.2825202942,48.2845802307],"type":"Point"}
}