{
  "type": "Feature",
  "properties": {
    "addr:full":"Senefelderg 37 Wien Wien 1100",
    "addr:housenumber":"37",
    "addr:postcode":"1100",
    "addr:street":"Senefelderg",
    "iso:country":"AT",
    "sg:address":"Senefelderg 37",
    "sg:city":"Wien",
    "sg:orig_category":"Telekommunikation",
    "sg:phone":"+43 1 6004062",
    "sg:postcode":"1100",
    "sg:province":"Wien",
    "wof:name":"FORA Nurettin CIVANDAG KEG",
    "wof:placetype":"venue"
},
  "geometry": {"coordinates":[16.3755226135,48.1741065979],"type":"Point"}
}