{
  "type": "Feature",
  "properties": {
    "addr:full":"Simmeringer Hauptstr 77 Wien Wien 1110",
    "addr:housenumber":"77",
    "addr:postcode":"1110",
    "addr:street":"Simmeringer Hauptstr",
    "iso:country":"AT",
    "sg:address":"Simmeringer Hauptstr 77",
    "sg:city":"Wien",
    "sg:orig_category":"\u00c3\u201enderungsschneidereien",
    "sg:phone":"+43 1 7492279",
    "sg:postcode":"1110",
    "sg:province":"Wien",
    "wof:name":"Saidler Horst",
    "wof:placetype":"venue"
},
  "geometry": {"coordinates":[16.4133701324,48.1774139404],"type":"Point"}
}