{
  "type": "Feature",
  "properties": {
    "iso:country":"AT",
    "sg:city":"K\u00fchnsdorf",
    "sg:classifiers":[
        {
            "category":"Home & Garden",
            "subcategory":"Building Materials",
            "type":"Retail Goods"
        }
    ],
    "sg:phone":"+43 4232 6273",
    "sg:postcode":"9125",
    "sg:province":"K\u00e4rnten",
    "sg:tags":[
        "baustoffe",
        "-material",
        "u"
    ],
    "wof:name":"ASPHALT & BETON GmbH",
    "wof:placetype":"venue"
},
  "geometry": {"coordinates":[14.6815252304,46.6218643188],"type":"Point"}
}