{
  "type": "Feature",
  "properties": {
    "addr:full":"Nonntaler Hauptstr 64/11 Salzburg Salzburg 5020",
    "addr:housenumber":"64 / 11",
    "addr:postcode":"5020",
    "addr:street":"Nonntaler Hauptstr;Salzburg",
    "iso:country":"AT",
    "sg:address":"Nonntaler Hauptstr 64/11",
    "sg:city":"Salzburg",
    "sg:orig_category":"Datenverarbeitung",
    "sg:phone":"+43 4366 2834826",
    "sg:postcode":"5020",
    "sg:province":"Salzburg",
    "wof:name":"GEO-Byte Gesellschaft f Analyse Simulation u Modellierung georelevanter Daten GesmbH",
    "wof:placetype":"venue"
},
  "geometry": {"coordinates":[13.0508899689,47.7877235413],"type":"Point"}
}