{
  "type": "Feature",
  "properties": {
    "addr:full":"Am Sonnenhang 2 Linz Ober\u00f6sterreich 4040",
    "addr:housenumber":"2",
    "addr:postcode":"4040",
    "addr:street":"Am Sonnenhang",
    "iso:country":"AT",
    "sg:address":"Am Sonnenhang 2",
    "sg:city":"Linz",
    "sg:orig_category":"Werbeagenturen",
    "sg:phone":"+43 512 940251",
    "sg:postcode":"4040",
    "sg:province":"Ober\u00f6sterreich",
    "wof:name":"factoryEC Kaltenhuber Kaufmann OEG - Marketing-Consulting - eBusiness",
    "wof:placetype":"venue"
},
  "geometry": {"coordinates":[14.3050889969,48.3374633789],"type":"Point"}
}