{
  "type": "Feature",
  "properties": {
    "addr:full":"Schnopfhagenpl 3 St. Veit im M\u00fchlkreis Ober\u00f6sterreich 4173",
    "addr:housenumber":"3",
    "addr:postcode":"4173",
    "addr:street":"Schnopfhagenpl",
    "iso:country":"AT",
    "sg:address":"Schnopfhagenpl 3",
    "sg:city":"St. Veit im M\u00fchlkreis",
    "sg:orig_category":"Gemeinden",
    "sg:phone":"+43 4372 176055",
    "sg:postcode":"4173",
    "sg:province":"Ober\u00f6sterreich",
    "wof:name":"Gemeinde St Veit im M\u00fchlkreis",
    "wof:placetype":"venue"
},
  "geometry": {"coordinates":[14.1646566391,48.4678955078],"type":"Point"}
}