{
  "type": "Feature",
  "properties": {
    "addr:full":"Gutensteiner Str 60 Pottenstein Nieder\u00f6sterreich 2563",
    "addr:postcode":"2563",
    "addr:street":"Str 60",
    "iso:country":"AT",
    "sg:address":"Gutensteiner Str 60",
    "sg:city":"Pottenstein",
    "sg:orig_category":"Steinmetzbetriebe",
    "sg:phone":"+43 4326 7282616",
    "sg:postcode":"2563",
    "sg:province":"Nieder\u00f6sterreich",
    "wof:name":"Brandauer Erich",
    "wof:placetype":"venue"
},
  "geometry": {"coordinates":[16.0846977234,47.9603729248],"type":"Point"}
}