{
  "type": "Feature",
  "properties": {
    "addr:full":"Nr 11 Purgstall an der Erlauf Nieder\u00f6sterreich 3251",
    "addr:postcode":"3251",
    "addr:street":"Nr 11;Niederoesterreich",
    "iso:country":"AT",
    "sg:address":"Nr 11",
    "sg:city":"Purgstall an der Erlauf",
    "sg:orig_category":"Reifen U Reifendienste",
    "sg:phone":"+43 7489 2481",
    "sg:postcode":"3251",
    "sg:province":"Nieder\u00f6sterreich",
    "wof:name":"Reifen Weichberger GmbH",
    "wof:placetype":"venue"
},
  "geometry": {"coordinates":[166.9221496582,-0.5282999873],"type":"Point"}
}