{
  "type": "Feature",
  "properties": {
    "iso:country":"AT",
    "sg:address":"Waldg 18",
    "sg:city":"Weiz",
    "sg:orig_category":"Transportunternehmen",
    "sg:phone":"+43 3172 53860",
    "sg:postcode":"8160",
    "sg:province":"Steiermark",
    "wof:name":"Matzhold Erwin",
    "wof:placetype":"venue"
},
  "geometry": {"coordinates":[15.6215696335,47.2169532776],"type":"Point"}
}