{
  "type": "Feature",
  "properties": {
    "addr:full":"Apetloner Str 56 Illmitz Burgenland 7142",
    "addr:postcode":"7142",
    "addr:street":"Str 56",
    "iso:country":"AT",
    "sg:address":"Apetloner Str 56",
    "sg:city":"Illmitz",
    "sg:classifiers":[
        {
            "category":"Travel",
            "subcategory":"Hotels & Motels",
            "type":"Entertainment"
        }
    ],
    "sg:phone":"+43 2175 36000",
    "sg:postcode":"7142",
    "sg:province":"Burgenland",
    "wof:name":"Hotel Nationalpark",
    "wof:placetype":"venue"
},
  "geometry": {"coordinates":[16.8102016449,47.758556366],"type":"Point"}
}