{
  "type": "Feature",
  "properties": {
    "addr:full":"Reichsstr 160-162 Feldkirch Vorarlberg 6800",
    "addr:postcode":"160-162;6800",
    "iso:country":"AT",
    "sg:address":"Reichsstr 160-162",
    "sg:city":"Feldkirch",
    "sg:classifiers":[
        {
            "category":"Home & Garden",
            "subcategory":"Building Materials",
            "type":"Retail Goods"
        }
    ],
    "sg:phone":"+43 5522 720140",
    "sg:postcode":"6800",
    "sg:province":"Vorarlberg",
    "sg:tags":[
        "baustoffe",
        "-material",
        "u"
    ],
    "wof:name":"P\u00fcmpel A & Co",
    "wof:placetype":"venue"
},
  "geometry": {"coordinates":[9.6050043106,47.2437782288],"type":"Point"}
}