{
  "type": "Feature",
  "properties": {
    "iso:country":"AT",
    "sg:address":"Wiener Str. 13 ",
    "sg:city":"Oberpullendorf",
    "sg:classifiers":[
        {
            "category":"Shopping",
            "subcategory":"Clothing, Apparel, & Fashions",
            "type":"Retail Goods"
        }
    ],
    "sg:phone":"+43 4326 1242368",
    "sg:postcode":"7350",
    "sg:province":"Burgenland",
    "sg:tags":[
        "clothes"
    ],
    "wof:name":"TRIUMPH INTERNATIONAL AG",
    "wof:placetype":"venue"
},
  "geometry": {"coordinates":[16.5046482086,47.5070037842],"type":"Point"}
}