{
  "type": "Feature",
  "properties": {
    "addr:full":"Helferstorferstr 5/5 Wien Wien 1010",
    "addr:housenumber":"5 / 5",
    "addr:postcode":"1010",
    "addr:street":"Helferstorferstr",
    "iso:country":"AT",
    "sg:address":"Helferstorferstr 5/5",
    "sg:city":"Wien",
    "sg:orig_category":"\u00c3\u201erzte / F Allgemeinmedizin",
    "sg:phone":"+43 1 5334713",
    "sg:postcode":"1010",
    "sg:province":"Wien",
    "wof:name":"Binder Ulrike Dr",
    "wof:placetype":"venue"
},
  "geometry": {"coordinates":[16.364118576,48.2133979797],"type":"Point"}
}