{
  "type": "Feature",
  "properties": {
    "addr:full":"Wiesbergg 15 Wien Wien 1160",
    "addr:housenumber":"15",
    "addr:postcode":"1160",
    "addr:street":"Wiesbergg",
    "iso:country":"AT",
    "sg:address":"Wiesbergg 15",
    "sg:city":"Wien",
    "sg:orig_category":"Ingenieurkonsulenten / Zivilingenieure",
    "sg:phone":"+43 1 4931515",
    "sg:postcode":"1160",
    "sg:province":"Wien",
    "wof:name":"Liebscher Bernhard Dipl-Ing",
    "wof:placetype":"venue"
},
  "geometry": {"coordinates":[16.306646347,48.2093353271],"type":"Point"}
}