{
  "type": "Feature",
  "properties": {
    "addr:full":"Batthyanystr 5 Rechnitz Burgenland 7471",
    "addr:housenumber":"5",
    "addr:postcode":"7471",
    "addr:street":"Batthyanystr",
    "iso:country":"AT",
    "sg:address":"Batthyanystr 5",
    "sg:city":"Rechnitz",
    "sg:orig_category":"Automaten",
    "sg:phone":"+43 3363 795350",
    "sg:postcode":"7471",
    "sg:province":"Burgenland",
    "wof:name":"Adelmann Klaus Ing",
    "wof:placetype":"venue"
},
  "geometry": {"coordinates":[16.4419517517,47.2999267578],"type":"Point"}
}