{
  "type": "Feature",
  "properties": {
    "addr:full":"Bahnhofstr 11 Rankweil Vorarlberg 6830",
    "addr:postcode":"6830",
    "addr:street":"Bahnhofstr 11",
    "iso:country":"AT",
    "sg:address":"Bahnhofstr 11",
    "sg:city":"Rankweil",
    "sg:orig_category":"Damenmoden",
    "sg:phone":"+43 5522 48791",
    "sg:postcode":"6830",
    "sg:province":"Vorarlberg",
    "wof:name":"CECIL woman",
    "wof:placetype":"venue"
},
  "geometry": {"coordinates":[9.6413860321,47.2707633972],"type":"Point"}
}