{
  "type": "Feature",
  "properties": {
    "addr:full":"Etrichstrasse 12 Wels Ober\u00f6sterreich 4600",
    "addr:housenumber":"12",
    "addr:postcode":"4600",
    "addr:street":"Etrichstrasse;Oberoesterreich",
    "iso:country":"AT",
    "sg:address":"Etrichstrasse 12",
    "sg:city":"Wels",
    "sg:classifiers":[
        {
            "category":"Manufacturing",
            "subcategory":"Leather Goods",
            "type":"Manufacturing & Wholesale Goods"
        }
    ],
    "sg:phone":"+43 7242 61334",
    "sg:postcode":"4600",
    "sg:province":"Ober\u00f6sterreich",
    "sg:tags":[
        "belt"
    ],
    "wof:name":"CONDOR G\u00fcrtel Ges.m.b.H.",
    "wof:placetype":"venue"
},
  "geometry": {"coordinates":[14.067609787,48.1780319214],"type":"Point"}
}