{
  "type": "Feature",
  "properties": {
    "iso:country":"AT",
    "sg:address":"Hans Wagner-Str 22",
    "sg:city":"Steyr",
    "sg:orig_category":"Genossenschaften",
    "sg:phone":"+43 7252 87008",
    "sg:postcode":"4400",
    "sg:province":"Ober\u00f6sterreich",
    "wof:name":"Wohnungsanlagen GesmbH",
    "wof:placetype":"venue"
},
  "geometry": {"coordinates":[14.4438390732,48.0538902283],"type":"Point"}
}