{
  "type": "Feature",
  "properties": {
    "addr:full":"Gewerbepark 10 Kalsdorf Steiermark 8401",
    "addr:housenumber":"10",
    "addr:postcode":"8401",
    "addr:street":"Gewerbepark",
    "iso:country":"AT",
    "sg:address":"Gewerbepark 10",
    "sg:city":"Kalsdorf",
    "sg:classifiers":[
        {
            "category":"Home & Garden",
            "subcategory":"Building Materials",
            "type":"Retail Goods"
        }
    ],
    "sg:phone":"+43 4331 35561600",
    "sg:postcode":"8401",
    "sg:province":"Steiermark",
    "sg:tags":[
        "baustoffe",
        "-material",
        "u"
    ],
    "wof:name":"R\u00f6fix AG",
    "wof:placetype":"venue"
},
  "geometry": {"coordinates":[15.4590454102,46.970085144],"type":"Point"}
}