{
  "type": "Feature",
  "properties": {
    "addr:full":"Nr 131 Kirchberg an der Raab Steiermark 8324",
    "addr:postcode":"8324",
    "addr:street":"Nr 131",
    "iso:country":"AT",
    "sg:address":"Nr 131",
    "sg:city":"Kirchberg an der Raab",
    "sg:orig_category":"Gemeinden",
    "sg:phone":"+43 3115 3440",
    "sg:postcode":"8324",
    "sg:province":"Steiermark",
    "wof:name":"Gemeindeamt Oberdorf am Hochegg",
    "wof:placetype":"venue"
},
  "geometry": {"coordinates":[15.7642307281,46.9871444702],"type":"Point"}
}