{
  "type": "Feature",
  "properties": {
    "addr:full":"Salzburger Str 99 Braunau am Inn Ober\u00f6sterreich 5280",
    "addr:housenumber":"99",
    "addr:postcode":"5280",
    "addr:street":"Salzburger Str",
    "iso:country":"AT",
    "sg:address":"Salzburger Str 99",
    "sg:city":"Braunau am Inn",
    "sg:orig_category":"Tankstellen",
    "sg:phone":"+43 7722 87227",
    "sg:postcode":"5280",
    "sg:province":"Ober\u00f6sterreich",
    "wof:name":"OMV Servicestation - Urban Reinhold",
    "wof:placetype":"venue"
},
  "geometry": {"coordinates":[13.0393772125,48.2472190857],"type":"Point"}
}