{
  "type": "Feature",
  "properties": {
    "addr:full":"Schiffsm\u00fchlenstr. 81 Wien Wien 1220",
    "addr:housenumber":"81",
    "addr:postcode":"1220",
    "addr:street":"Schiffsmuehlenstr.",
    "iso:country":"AT",
    "sg:address":"Schiffsm\u00fchlenstr. 81",
    "sg:city":"Wien",
    "sg:classifiers":[
        {
            "category":"Travel",
            "subcategory":"Travel Agent",
            "type":"Entertainment"
        }
    ],
    "sg:phone":"+43 4315 9910",
    "sg:postcode":"1220",
    "sg:province":"Wien",
    "sg:tags":[
        "business"
    ],
    "wof:name":"PIZZA-FLITZER GESMBH",
    "wof:placetype":"venue"
},
  "geometry": {"coordinates":[16.444606781,48.2497138977],"type":"Point"}
}