{
  "type": "Feature",
  "properties": {
    "iso:country":"AT",
    "sg:address":"Gro\u00dfdorf Heckisau 77",
    "sg:city":"Egg",
    "sg:orig_category":"Spirituosen / Erzeugung U Gro\u00c3\u0178handel",
    "sg:phone":"+43 4355 1244020",
    "sg:postcode":"6863",
    "sg:province":"Vorarlberg",
    "wof:name":"Gebr\u00fcder Bentele",
    "wof:placetype":"venue"
},
  "geometry": {"coordinates":[9.897102356,47.4310417175],"type":"Point"}
}