{
  "type": "Feature",
  "properties": {
    "addr:full":"Graben 46 Aschach an der Steyr Ober\u00f6sterreich 4421",
    "addr:housenumber":"46",
    "addr:postcode":"4421",
    "addr:street":"Graben",
    "iso:country":"AT",
    "sg:address":"Graben 46",
    "sg:city":"Aschach an der Steyr",
    "sg:orig_category":"Webdesign",
    "sg:phone":"+43 7259 3487",
    "sg:postcode":"4421",
    "sg:province":"Ober\u00f6sterreich",
    "wof:name":"Webwerkstatt - web design agentur",
    "wof:placetype":"venue"
},
  "geometry": {"coordinates":[14.3340787888,48.0213394165],"type":"Point"}
}