{
  "type": "Feature",
  "properties": {
    "addr:full":"Belvedereg 5 Stockerau Nieder\u00f6sterreich 2000",
    "addr:housenumber":"5",
    "addr:postcode":"2000",
    "addr:street":"Belvedereg",
    "iso:country":"AT",
    "sg:address":"Belvedereg 5",
    "sg:city":"Stockerau",
    "sg:orig_category":"Steuerberatung",
    "sg:phone":"+43 2266 718540",
    "sg:postcode":"2000",
    "sg:province":"Nieder\u00f6sterreich",
    "sg:website":"cts-partner.at",
    "wof:name":"CTS Steuerberatung GmbH",
    "wof:placetype":"venue"
},
  "geometry": {"coordinates":[16.208946228,48.3880157471],"type":"Point"}
}