{
  "type": "Feature",
  "properties": {
    "addr:full":"Sigmundsg 2 Wien Wien 1070",
    "addr:housenumber":"2",
    "addr:postcode":"1070",
    "addr:street":"Sigmundsg",
    "iso:country":"AT",
    "sg:address":"Sigmundsg 2",
    "sg:city":"Wien",
    "sg:orig_category":"Dekorationen",
    "sg:phone":"+43 1 5268000",
    "sg:postcode":"1070",
    "sg:province":"Wien",
    "wof:name":"Reichmann Florian - Filmarchitektur",
    "wof:placetype":"venue"
},
  "geometry": {"coordinates":[16.353843689,48.2026138306],"type":"Point"}
}