{
  "type": "Feature",
  "properties": {
    "addr:full":"Nr 27 Ischgl Tirol 6561",
    "addr:postcode":"6561",
    "addr:street":"Nr 27;Tirol",
    "iso:country":"AT",
    "sg:address":"Nr 27",
    "sg:city":"Ischgl",
    "sg:orig_category":"Tabaktrafiken",
    "sg:phone":"+43 5444 5250",
    "sg:postcode":"6561",
    "sg:province":"Tirol",
    "wof:name":"Zangerl Richard KG",
    "wof:placetype":"venue"
},
  "geometry": {"coordinates":[10.2881736755,47.0111351013],"type":"Point"}
}