{
  "type": "Feature",
  "properties": {
    "iso:country":"AT",
    "sg:address":"Nr 70",
    "sg:city":"Eberndorf",
    "sg:orig_category":"Transportunternehmen",
    "sg:phone":"+43 4236 2883",
    "sg:postcode":"9141",
    "sg:province":"K\u00e4rnten",
    "wof:name":"Kerth Walter",
    "wof:placetype":"venue"
},
  "geometry": {"coordinates":[166.9221496582,-0.5282999873],"type":"Point"}
}