{
  "type": "Feature",
  "properties": {
    "addr:full":"M\u00fchlgraben 43 a Erl Tirol 6343",
    "addr:housenumber":"43 a",
    "addr:postcode":"6343",
    "addr:street":"Muehlgraben;Tirol",
    "iso:country":"AT",
    "sg:address":"M\u00fchlgraben 43 a",
    "sg:city":"Erl",
    "sg:classifiers":[
        {
            "category":"Landmark",
            "subcategory":"Unesco World Heritage Site",
            "type":"Public Place"
        }
    ],
    "sg:phone":"+43 5373 76080",
    "sg:postcode":"6343",
    "sg:province":"Tirol",
    "sg:tags":[
        "dryer",
        "air"
    ],
    "sg:website":"mhm.at",
    "wof:name":"MHM Siebdruckmaschinen GmbH KG",
    "wof:placetype":"venue"
},
  "geometry": {"coordinates":[12.1806850433,47.6813354492],"type":"Point"}
}