{
  "type": "Feature",
  "properties": {
    "addr:full":"Schieferrollstrasse 2 Kundl Tirol 6250",
    "addr:housenumber":"2",
    "addr:postcode":"6250",
    "addr:street":"Schieferrollstrasse;Tirol",
    "iso:country":"AT",
    "sg:address":"Schieferrollstrasse 2",
    "sg:city":"Kundl",
    "sg:classifiers":[
        {
            "category":"Shopping Center",
            "type":"Public Place"
        }
    ],
    "sg:phone":"+43 5338 7302",
    "sg:postcode":"6250",
    "sg:province":"Tirol",
    "sg:tags":[
        "aluminium",
        "casting"
    ],
    "sg:website":"members.aon.at/metalkunstguss-margreiter",
    "wof:name":"G\u00fcnther Margreiter",
    "wof:placetype":"venue"
},
  "geometry": {"coordinates":[11.9887599945,47.4699859619],"type":"Point"}
}