{
  "type": "Feature",
  "properties": {
    "addr:full":"Leppersdorf 50 Scharten Ober\u00f6sterreich 4612",
    "addr:housenumber":"50",
    "addr:postcode":"4612",
    "addr:street":"Leppersdorf",
    "iso:country":"AT",
    "sg:address":"Leppersdorf 50",
    "sg:city":"Scharten",
    "sg:orig_category":"Brandschutz",
    "sg:phone":"+43 7272 5370",
    "sg:postcode":"4612",
    "sg:province":"Ober\u00f6sterreich",
    "wof:name":"Brandschutztechnik Rumpfhuber Peter",
    "wof:placetype":"venue"
},
  "geometry": {"coordinates":[14.0249357224,48.266620636],"type":"Point"}
}