{
  "type": "Feature",
  "properties": {
    "addr:full":"Garteng 3 Weiz Steiermark 8160",
    "addr:housenumber":"3",
    "addr:postcode":"8160",
    "addr:street":"Garteng",
    "iso:country":"AT",
    "sg:address":"Garteng 3",
    "sg:city":"Weiz",
    "sg:orig_category":"Maler, Anstreicher U Lackierer",
    "sg:phone":"+43 3172 41370",
    "sg:postcode":"8160",
    "sg:province":"Steiermark",
    "wof:name":"Farbenzauber",
    "wof:placetype":"venue"
},
  "geometry": {"coordinates":[15.6371202469,47.2104949951],"type":"Point"}
}