{
  "type": "Feature",
  "properties": {
    "addr:full":"Herrenstr 16 Linz Ober\u00f6sterreich 4020",
    "addr:housenumber":"16",
    "addr:postcode":"4020",
    "addr:street":"Herrenstr",
    "iso:country":"AT",
    "sg:address":"Herrenstr 16",
    "sg:city":"Linz",
    "sg:orig_category":"Papier- U Schreibwaren / Einzelhandel",
    "sg:phone":"+43 4373 2777447",
    "sg:postcode":"4020",
    "sg:province":"Ober\u00f6sterreich",
    "wof:name":"Becker C - Skribo GmbH",
    "wof:placetype":"venue"
},
  "geometry": {"coordinates":[14.2865962982,48.3019371033],"type":"Point"}
}