{
  "type": "Feature",
  "properties": {
    "addr:full":"Nr 134 St. Stefan ob Stainz Steiermark 8511",
    "addr:postcode":"8511",
    "addr:street":"Nr 134",
    "iso:country":"AT",
    "sg:address":"Nr 134",
    "sg:city":"St. Stefan ob Stainz",
    "sg:classifiers":[
        {
            "category":"Restaurant",
            "type":"Food & Drink"
        }
    ],
    "sg:phone":"+43 3463 82409",
    "sg:postcode":"8511",
    "sg:province":"Steiermark",
    "wof:name":"SCAMPI - Restaurant",
    "wof:placetype":"venue"
},
  "geometry": {"coordinates":[15.2549381256,46.9294662476],"type":"Point"}
}