{
  "type": "Feature",
  "properties": {
    "addr:full":"Freist\u00e4dter Str 230 Linz Ober\u00f6sterreich 4040",
    "addr:housenumber":"230",
    "addr:postcode":"4040",
    "addr:street":"Str",
    "iso:country":"AT",
    "sg:address":"Freist\u00e4dter Str 230",
    "sg:city":"Linz",
    "sg:orig_category":"Textilreinigung",
    "sg:phone":"+43 732 2464340",
    "sg:postcode":"4040",
    "sg:province":"Ober\u00f6sterreich",
    "wof:name":"Wozabal Textilservice GesmbH & Co KG",
    "wof:placetype":"venue"
},
  "geometry": {"coordinates":[14.3027009964,48.3265686035],"type":"Point"}
}