{
  "type": "Feature",
  "properties": {
    "iso:country":"AT",
    "sg:address":"Wiener Str 2",
    "sg:city":"Brunn am Gebirge",
    "sg:orig_category":"Tabaktrafiken",
    "sg:phone":"+43 2236 32694",
    "sg:postcode":"2345",
    "sg:province":"Nieder\u00f6sterreich",
    "wof:name":"Kurz Ferdinand",
    "wof:placetype":"venue"
},
  "geometry": {"coordinates":[16.2857837677,48.1055107117],"type":"Point"}
}