{
  "type": "Feature",
  "properties": {
    "addr:full":"Esplanade 12 Bad Ischl Ober\u00f6sterreich 4820",
    "addr:housenumber":"12",
    "addr:postcode":"4820",
    "addr:street":"Esplanade",
    "iso:country":"AT",
    "sg:address":"Esplanade 12",
    "sg:city":"Bad Ischl",
    "sg:orig_category":"Vinotheken",
    "sg:phone":"+43 6132 21531",
    "sg:postcode":"4820",
    "sg:province":"Ober\u00f6sterreich",
    "wof:name":"IN VINO VERITAS",
    "wof:placetype":"venue"
},
  "geometry": {"coordinates":[13.6197395325,47.7101135254],"type":"Point"}
}