{
  "type": "Feature",
  "properties": {
    "addr:full":"Nr 31 Heiligenkreuz im Wienerwald Nieder\u00f6sterreich 2532",
    "addr:postcode":"2532",
    "addr:street":"Nr",
    "iso:country":"AT",
    "sg:address":"Nr 31",
    "sg:city":"Heiligenkreuz im Wienerwald",
    "sg:orig_category":"Fotografen",
    "sg:phone":"+43 2258 8925",
    "sg:postcode":"2532",
    "sg:province":"Nieder\u00f6sterreich",
    "wof:name":"Creativ Foto A & R Wunderer OEG",
    "wof:placetype":"venue"
},
  "geometry": {"coordinates":[16.1279754639,48.0560836792],"type":"Point"}
}