{
  "type": "Feature",
  "properties": {
    "addr:full":"Sieveringer Str 133 Wien Wien 1190",
    "addr:housenumber":"133",
    "addr:postcode":"1190",
    "addr:street":"Sieveringer Str",
    "iso:country":"AT",
    "sg:address":"Sieveringer Str 133",
    "sg:city":"Wien",
    "sg:orig_category":"Genossenschaften",
    "sg:phone":"+43 1 32827700",
    "sg:postcode":"1190",
    "sg:province":"Wien",
    "wof:name":"EIGENTUM Gemeinn\u00fctzige Wohnungs- und SiedlungsgesmbH",
    "wof:placetype":"venue"
},
  "geometry": {"coordinates":[16.3256702423,48.2490653992],"type":"Point"}
}