{
  "type": "Feature",
  "properties": {
    "addr:full":"Untere Hauptstr 7 Nickelsdorf Burgenland 2425",
    "addr:housenumber":"7",
    "addr:postcode":"2425",
    "addr:street":"Untere Hauptstr",
    "iso:country":"AT",
    "sg:address":"Untere Hauptstr 7",
    "sg:city":"Nickelsdorf",
    "sg:orig_category":"Non-Classified Establishments",
    "sg:phone":"+43 2146 2227",
    "sg:postcode":"2425",
    "sg:province":"Burgenland",
    "wof:name":"Evangelisches Pfarramt AB",
    "wof:placetype":"venue"
},
  "geometry": {"coordinates":[17.0756168365,47.9383468628],"type":"Point"}
}