{
  "type": "Feature",
  "properties": {
    "addr:full":"Auleiten 2 Ried im Innkreis Ober\u00f6sterreich 4910",
    "addr:housenumber":"2",
    "addr:postcode":"4910",
    "addr:street":"Auleiten",
    "iso:country":"AT",
    "sg:address":"Auleiten 2",
    "sg:city":"Ried im Innkreis",
    "sg:orig_category":"Speditionen",
    "sg:phone":"+43 4377 52835210",
    "sg:postcode":"4910",
    "sg:province":"Ober\u00f6sterreich",
    "wof:name":"Angermayr GesmbH",
    "wof:placetype":"venue"
},
  "geometry": {"coordinates":[13.4967594147,48.1944847107],"type":"Point"}
}