{
  "type": "Feature",
  "properties": {
    "addr:full":"Hauptstr 27 Stockerau Nieder\u00f6sterreich 2000",
    "addr:housenumber":"27",
    "addr:postcode":"2000",
    "addr:street":"Hauptstr",
    "iso:country":"AT",
    "sg:address":"Hauptstr 27",
    "sg:city":"Stockerau",
    "sg:orig_category":"Galerien",
    "sg:phone":"+43 2266 625050",
    "sg:postcode":"2000",
    "sg:province":"Nieder\u00f6sterreich",
    "wof:name":"Galerie zum Alten Rathaus",
    "wof:placetype":"venue"
},
  "geometry": {"coordinates":[16.2116661072,48.385383606],"type":"Point"}
}