{
  "type": "Feature",
  "properties": {
    "addr:full":"Loranggasse 2a Mitterdorf im M\u00fcrztal Steiermark 8662",
    "addr:housenumber":"2a",
    "addr:postcode":"8662",
    "addr:street":"Loranggasse",
    "iso:country":"AT",
    "sg:address":"Loranggasse 2a",
    "sg:city":"Mitterdorf im M\u00fcrztal",
    "sg:classifiers":[
        {
            "category":"Home & Garden",
            "subcategory":"Building Materials",
            "type":"Retail Goods"
        }
    ],
    "sg:phone":"+43 3858 6111",
    "sg:postcode":"8662",
    "sg:province":"Steiermark",
    "sg:tags":[
        "installation",
        "electric"
    ],
    "sg:website":"ok-kammerhofer.at",
    "wof:name":"Otmar Kammerhofer Ges.m.b.H.",
    "wof:placetype":"venue"
},
  "geometry": {"coordinates":[15.5115642548,47.5428466797],"type":"Point"}
}