{
  "type": "Feature",
  "properties": {
    "addr:full":"Kirchg 6 Waidring Tirol 6384",
    "addr:housenumber":"6",
    "addr:postcode":"6384",
    "addr:street":"Kirchg;Tirol",
    "iso:country":"AT",
    "sg:address":"Kirchg 6",
    "sg:city":"Waidring",
    "sg:orig_category":"Volksschulen",
    "sg:phone":"+43 5353 5261",
    "sg:postcode":"6384",
    "sg:province":"Tirol",
    "wof:name":"Volksschule",
    "wof:placetype":"venue"
},
  "geometry": {"coordinates":[12.5694799423,47.5843238831],"type":"Point"}
}