{
  "type": "Feature",
  "properties": {
    "addr:full":"Nr 31 Fischbach Steiermark 8654",
    "addr:postcode":"8654",
    "addr:street":"Nr 31",
    "iso:country":"AT",
    "sg:address":"Nr 31",
    "sg:city":"Fischbach",
    "sg:orig_category":"Fleischhauereien",
    "sg:phone":"+43 4331 70208",
    "sg:postcode":"8654",
    "sg:province":"Steiermark",
    "wof:name":"Grabenhofer Franz",
    "wof:placetype":"venue"
},
  "geometry": {"coordinates":[15.6509952545,47.4420051575],"type":"Point"}
}