{
  "type": "Feature",
  "properties": {
    "iso:country":"AT",
    "sg:address":"Singerstrasse 18",
    "sg:city":"Wien",
    "sg:classifiers":[
        {
            "category":"Home & Garden",
            "subcategory":"Home Furnishings",
            "type":"Retail Goods"
        }
    ],
    "sg:phone":"+43 1 5128879",
    "sg:postcode":"1010",
    "sg:province":"Wien",
    "sg:tags":[
        "interior",
        "decoration"
    ],
    "wof:name":"Norbert F\u00fcllerer",
    "wof:placetype":"venue"
},
  "geometry": {"coordinates":[16.3739719391,48.2070503235],"type":"Point"}
}