{
  "type": "Feature",
  "properties": {
    "iso:country":"AT",
    "sg:address":"Wilhelmstr 16",
    "sg:city":"Tulln an der Donau",
    "sg:orig_category":"Pensionen / Privatzimmer",
    "sg:phone":"+43 2272 63337",
    "sg:postcode":"3430",
    "sg:province":"Nieder\u00f6sterreich",
    "wof:name":"Keindl Walter",
    "wof:placetype":"venue"
},
  "geometry": {"coordinates":[16.0568523407,48.3297538757],"type":"Point"}
}