{
  "type": "Feature",
  "properties": {
    "addr:full":"Siezenheimer Strasse 36u 40 Salzburg Salzburg 5020",
    "addr:housenumber":"36u 40",
    "addr:postcode":"5020",
    "addr:street":"Siezenheimer Strasse;Salzburg",
    "iso:country":"AT",
    "sg:address":"Siezenheimer Strasse 36u 40",
    "sg:city":"Salzburg",
    "sg:classifiers":[
        {
            "category":"Building & Trades",
            "subcategory":"Plumbing",
            "type":"Services"
        }
    ],
    "sg:phone":"+43 662 432364",
    "sg:postcode":"5020",
    "sg:province":"Salzburg",
    "sg:tags":[
        "supraregional",
        "gas"
    ],
    "sg:website":"rauscher.co.at",
    "wof:name":"Reinhold Rauscher GmbH",
    "wof:placetype":"venue"
},
  "geometry": {"coordinates":[13.0066986084,47.8060493469],"type":"Point"}
}