{
  "type": "Feature",
  "properties": {
    "addr:full":"Im Loch 2 Tschagguns Vorarlberg 6774",
    "addr:housenumber":"2",
    "addr:postcode":"6774",
    "addr:street":"Im Loch",
    "iso:country":"AT",
    "sg:address":"Im Loch 2",
    "sg:city":"Tschagguns",
    "sg:orig_category":"Pensionen / Privatzimmer",
    "sg:phone":"+43 5556 721650",
    "sg:postcode":"6774",
    "sg:province":"Vorarlberg",
    "wof:name":"St\u00fcttler Irene",
    "wof:placetype":"venue"
},
  "geometry": {"coordinates":[9.896241188,47.0778961182],"type":"Point"}
}