{
  "type": "Feature",
  "properties": {
    "addr:full":"Tragweiner Str 13 Pregarten Ober\u00f6sterreich 4230",
    "addr:postcode":"4230",
    "addr:street":"Str 13",
    "iso:country":"AT",
    "sg:address":"Tragweiner Str 13",
    "sg:city":"Pregarten",
    "sg:orig_category":"Textilwaren / Einzelhandel",
    "sg:phone":"+43 4372 3635100",
    "sg:postcode":"4230",
    "sg:province":"Ober\u00f6sterreich",
    "wof:name":"St\u00fcbl KEG",
    "wof:placetype":"venue"
},
  "geometry": {"coordinates":[14.533036232,48.3546447754],"type":"Point"}
}