{
  "type": "Feature",
  "properties": {
    "iso:country":"AT",
    "sg:address":"Haidweg 417",
    "sg:city":"Hinterglemm",
    "sg:orig_category":"Elektroinstallationsunternehmen",
    "sg:phone":"+43 6541 74420",
    "sg:postcode":"5754",
    "sg:province":"Salzburg",
    "wof:name":"Eberharter Walter",
    "wof:placetype":"venue"
},
  "geometry": {"coordinates":[12.5975790024,47.3776626587],"type":"Point"}
}