{
  "type": "Feature",
  "properties": {
    "iso:country":"AT",
    "sg:address":"Dresdner Str 48-54",
    "sg:city":"Wien",
    "sg:orig_category":"\u00c3\u201erzte / F Allgemeinmedizin",
    "sg:phone":"+43 1 3327402",
    "sg:postcode":"1200",
    "sg:province":"Wien",
    "wof:name":"Hengstschl\u00e4ger Birgit MedR Dr",
    "wof:placetype":"venue"
},
  "geometry": {"coordinates":[16.3781929016,48.2378044128],"type":"Point"}
}