{
  "type": "Feature",
  "properties": {
    "addr:full":"Stra\u00dfganger Str 436 Graz Steiermark 8020",
    "addr:housenumber":"436",
    "addr:postcode":"8020",
    "iso:country":"AT",
    "sg:address":"Stra\u00dfganger Str 436",
    "sg:city":"Graz",
    "sg:orig_category":"Tankstellen",
    "sg:phone":"+43 316 283868",
    "sg:postcode":"8020",
    "sg:province":"Steiermark",
    "wof:name":"OMV AG",
    "wof:placetype":"venue"
},
  "geometry": {"coordinates":[15.3966207504,47.0618515015],"type":"Point"}
}