{
  "type": "Feature",
  "properties": {
    "addr:full":"/Postfach/25 1071",
    "addr:housenumber":"25",
    "addr:postcode":"1071",
    "iso:country":"AT",
    "sg:address":"/Postfach/25",
    "sg:classifiers":[
        {
            "category":"Internet Cafe",
            "subcategory":"None",
            "type":"Food & Drink"
        }
    ],
    "sg:phone":"+43 1 52676580",
    "sg:postcode":"1071",
    "wof:name":"ONLINE Forum",
    "wof:placetype":"venue"
},
  "geometry": {"coordinates":[16.3489398956,48.2022285461],"type":"Point"}
}