{
  "type": "Feature",
  "properties": {
    "iso:country":"AT",
    "sg:address":"Gasser Pl 3",
    "sg:city":"Hermagor",
    "sg:orig_category":"Politische Parteien",
    "sg:phone":"+43 4282 2137",
    "sg:postcode":"9620",
    "sg:province":"K\u00e4rnten",
    "wof:name":"\u00f6sterreichische Volkspartei (\u00f6VP)",
    "wof:placetype":"venue"
},
  "geometry": {"coordinates":[13.3705835342,46.6271324158],"type":"Point"}
}