{
  "type": "Feature",
  "properties": {
    "iso:country":"AT",
    "sg:address":"Nr 23a",
    "sg:city":"Kirchbach in Steiermark",
    "sg:orig_category":"Elektroinstallationsunternehmen",
    "sg:phone":"+43 4331 162236",
    "sg:postcode":"8082",
    "sg:province":"Steiermark",
    "wof:name":"Dr\u00f6gsler Oswald",
    "wof:placetype":"venue"
},
  "geometry": {"coordinates":[15.6588878632,46.937297821],"type":"Point"}
}