{
  "type": "Feature",
  "properties": {
    "addr:full":"Laurenzg 11/1 Wien Wien 1050",
    "addr:housenumber":"11 / 1",
    "addr:postcode":"1050",
    "addr:street":"Laurenzg",
    "iso:country":"AT",
    "sg:address":"Laurenzg 11/1",
    "sg:city":"Wien",
    "sg:orig_category":"Gerichtsdolmetscher",
    "sg:phone":"+43 1 5459049",
    "sg:postcode":"1050",
    "sg:province":"Wien",
    "wof:name":"Sodeyfi Hana",
    "wof:placetype":"venue"
},
  "geometry": {"coordinates":[16.3634357452,48.1850013733],"type":"Point"}
}