{
  "type": "Feature",
  "properties": {
    "iso:country":"AT",
    "sg:address":"Lerchenfelder Str 124",
    "sg:city":"Wien",
    "sg:orig_category":"Bekleidung / Einzelhandel",
    "sg:phone":"+43 1 4097896",
    "sg:postcode":"1080",
    "sg:province":"Wien",
    "wof:name":"Salon Renate - Modellsalon Renate Klos-Luttenberger",
    "wof:placetype":"venue"
},
  "geometry": {"coordinates":[16.3425922394,48.2078704834],"type":"Point"}
}