{
  "type": "Feature",
  "properties": {
    "addr:full":"Johannes-Filzer-Str 26/55 Salzburg Salzburg 5020",
    "addr:housenumber":"26 / 55",
    "addr:postcode":"5020",
    "addr:street":"Johannes-Filzer-Str;Salzburg",
    "iso:country":"AT",
    "sg:address":"Johannes-Filzer-Str 26/55",
    "sg:city":"Salzburg",
    "sg:orig_category":"Institute",
    "sg:phone":"+43 662 635382",
    "sg:postcode":"5020",
    "sg:province":"Salzburg",
    "wof:name":"Institut f Studien in Salzburg",
    "wof:placetype":"venue"
},
  "geometry": {"coordinates":[13.0672950745,47.793926239],"type":"Point"}
}