{
  "type": "Feature",
  "properties": {
    "iso:country":"AT",
    "sg:address":"Oberhuemerstr 22",
    "sg:city":"Leonding",
    "sg:orig_category":"Baumeister",
    "sg:phone":"+43 4373 2671621",
    "sg:postcode":"4060",
    "sg:province":"Ober\u00f6sterreich",
    "wof:name":"H\u00f6fer Bau GmbH",
    "wof:placetype":"venue"
},
  "geometry": {"coordinates":[14.2576761246,48.2821578979],"type":"Point"}
}