{
  "type": "Feature",
  "properties": {
    "addr:full":"Linzer Str 40 Schwanenstadt Ober\u00f6sterreich 4690",
    "addr:housenumber":"40",
    "addr:postcode":"4690",
    "addr:street":"Linzer Str",
    "iso:country":"AT",
    "sg:address":"Linzer Str 40",
    "sg:city":"Schwanenstadt",
    "sg:orig_category":"Maschinenbau",
    "sg:phone":"+43 76732270",
    "sg:postcode":"4690",
    "sg:province":"Ober\u00f6sterreich",
    "wof:name":"K\u00fcchler Martin Ing",
    "wof:placetype":"venue"
},
  "geometry": {"coordinates":[13.7822551727,48.0590705872],"type":"Point"}
}