{
  "type": "Feature",
  "properties": {
    "addr:full":"T Pampichler-Str 23 Stockerau Nieder\u00f6sterreich 2000",
    "addr:housenumber":"23",
    "addr:postcode":"2000",
    "iso:country":"AT",
    "sg:address":"T Pampichler-Str 23",
    "sg:city":"Stockerau",
    "sg:orig_category":"Gerichte",
    "sg:phone":"+43 2266 621520",
    "sg:postcode":"2000",
    "sg:province":"Nieder\u00f6sterreich",
    "wof:name":"Bezirksgericht Stockerau",
    "wof:placetype":"venue"
},
  "geometry": {"coordinates":[16.2061843872,48.3893318176],"type":"Point"}
}