{
  "type": "Feature",
  "properties": {
    "iso:country":"AT",
    "sg:address":"Dorfpl 8",
    "sg:city":"Partenen",
    "sg:orig_category":"Tourismusinformation U -Organisationen",
    "sg:phone":"+43 5558 83150",
    "sg:postcode":"6794",
    "sg:province":"Vorarlberg",
    "wof:name":"Silvretta Partenen Tourismus",
    "wof:placetype":"venue"
},
  "geometry": {"coordinates":[10.0591773987,46.9696083069],"type":"Point"}
}