{
  "type": "Feature",
  "properties": {
    "addr:full":"Wagramer Str 177 Wien Wien 1220",
    "addr:housenumber":"177",
    "addr:postcode":"1220",
    "iso:country":"AT",
    "sg:address":"Wagramer Str 177",
    "sg:city":"Wien",
    "sg:orig_category":"Espresso- U Kaffeemaschinen, Kaffeeautomaten",
    "sg:phone":"+43 1 2596801",
    "sg:postcode":"1220",
    "sg:province":"Wien",
    "wof:name":"H S C Haushaltsservicecenter",
    "wof:placetype":"venue"
},
  "geometry": {"coordinates":[16.4498958588,48.2589149475],"type":"Point"}
}