{
  "type": "Feature",
  "properties": {
    "addr:full":"Himmelreichweg 80 Mariatrost Steiermark 8044",
    "addr:housenumber":"80",
    "addr:postcode":"8044",
    "addr:street":"Himmelreichweg",
    "iso:country":"AT",
    "sg:address":"Himmelreichweg 80",
    "sg:city":"Mariatrost",
    "sg:orig_category":"Institute",
    "sg:phone":"+43 316 392898",
    "sg:postcode":"8044",
    "sg:province":"Steiermark",
    "wof:name":"Rath Feldenkrais Methode",
    "wof:placetype":"venue"
},
  "geometry": {"coordinates":[15.4863386154,47.1078987122],"type":"Point"}
}