{
  "type": "Feature",
  "properties": {
    "addr:full":"Bundesstr 380 Nauders Tirol 6543",
    "addr:housenumber":"380",
    "addr:postcode":"6543",
    "addr:street":"Nauders Tirol",
    "iso:country":"AT",
    "sg:address":"Bundesstr 380",
    "sg:city":"Nauders",
    "sg:orig_category":"Autoreparatur",
    "sg:phone":"+43 5473 87739",
    "sg:postcode":"6543",
    "sg:province":"Tirol",
    "wof:name":"Sp\u00f6ttl Peter",
    "wof:placetype":"venue"
},
  "geometry": {"coordinates":[10.4984226227,46.8940391541],"type":"Point"}
}