{
  "type": "Feature",
  "properties": {
    "iso:country":"AT",
    "sg:address":"Kapuzinerg 10a",
    "sg:city":"Innsbruck",
    "sg:orig_category":"Detekteien",
    "sg:phone":"+43 512 345381",
    "sg:postcode":"6020",
    "sg:province":"Tirol",
    "wof:name":"EBS Sicherheitsagentur Gert Hofmann",
    "wof:placetype":"venue"
},
  "geometry": {"coordinates":[11.4038200378,47.2700462341],"type":"Point"}
}