{
  "type": "Feature",
  "properties": {
    "iso:country":"AT",
    "sg:address":"Brandstatt 20",
    "sg:city":"Frankenmarkt",
    "sg:orig_category":"Tischlereien",
    "sg:phone":"+43 76846580",
    "sg:postcode":"4890",
    "sg:province":"Ober\u00f6sterreich",
    "wof:name":"Fuchs Erwin",
    "wof:placetype":"venue"
},
  "geometry": {"coordinates":[13.422375679,47.9786109924],"type":"Point"}
}