{
  "type": "Feature",
  "properties": {
    "addr:full":"St. Peter Hauptstr 33b/I St. Peter Steiermark 8042",
    "addr:housenumber":"33b / i",
    "addr:postcode":"8042",
    "addr:street":"Hauptstr",
    "iso:country":"AT",
    "sg:address":"St. Peter Hauptstr 33b/I",
    "sg:city":"St. Peter",
    "sg:orig_category":"Ingenieurkonsulenten / Zivilingenieure",
    "sg:phone":"+43 316 4648000",
    "sg:postcode":"8042",
    "sg:province":"Steiermark",
    "wof:name":"Verderber Adolf Dipl-Ing",
    "wof:placetype":"venue"
},
  "geometry": {"coordinates":[15.4815740585,47.0515136719],"type":"Point"}
}