{
  "type": "Feature",
  "properties": {
    "iso:country":"AT",
    "sg:address":"Getreideg 15",
    "sg:city":"Salzburg",
    "sg:orig_category":"Feinkost",
    "sg:phone":"+43 662 8433940",
    "sg:postcode":"5020",
    "sg:province":"Salzburg",
    "wof:name":"Azwanger R F",
    "wof:placetype":"venue"
},
  "geometry": {"coordinates":[13.0428771973,47.7999267578],"type":"Point"}
}