{
  "type": "Feature",
  "properties": {
    "iso:country":"AT",
    "sg:address":"Wr Neust\u00e4dter Str 46",
    "sg:city":"Teesdorf",
    "sg:orig_category":"Banken U Sparkassen",
    "sg:phone":"+43 4350 10072220",
    "sg:postcode":"2524",
    "sg:province":"Nieder\u00f6sterreich",
    "wof:name":"Sparkasse Baden",
    "wof:placetype":"venue"
},
  "geometry": {"coordinates":[16.2822551727,47.949420929],"type":"Point"}
}