{
  "type": "Feature",
  "properties": {
    "addr:full":"Waldhoferweg 2 Treffen K\u00e4rnten 9521",
    "addr:housenumber":"2",
    "addr:postcode":"9521",
    "addr:street":"Waldhoferweg;Kaernten",
    "iso:country":"AT",
    "sg:address":"Waldhoferweg 2",
    "sg:city":"Treffen",
    "sg:orig_category":"Immobilienmakler",
    "sg:phone":"+43 4342 4830020",
    "sg:postcode":"9521",
    "sg:province":"K\u00e4rnten",
    "wof:name":"ATV Immobilien Dkfm Alfred Tischler",
    "wof:placetype":"venue"
},
  "geometry": {"coordinates":[13.8584299088,46.6581726074],"type":"Point"}
}