{
  "type": "Feature",
  "properties": {
    "addr:full":"Linzer Str 180 Gablitz Nieder\u00f6sterreich 3003",
    "addr:housenumber":"180",
    "addr:postcode":"3003",
    "addr:street":"Linzer Str",
    "iso:country":"AT",
    "sg:address":"Linzer Str 180",
    "sg:city":"Gablitz",
    "sg:orig_category":"Autoreparatur",
    "sg:phone":"+43 2231 634381",
    "sg:postcode":"3003",
    "sg:province":"Nieder\u00f6sterreich",
    "wof:name":"KFZ West 180 Hinner Ludwig",
    "wof:placetype":"venue"
},
  "geometry": {"coordinates":[16.1352386475,48.2404212952],"type":"Point"}
}