{
  "type": "Feature",
  "properties": {
    "addr:full":"Wiener Str 72 Neusiedl am See Burgenland 7100",
    "addr:housenumber":"72",
    "addr:postcode":"7100",
    "iso:country":"AT",
    "sg:address":"Wiener Str 72",
    "sg:city":"Neusiedl am See",
    "sg:orig_category":"Zimmereien",
    "sg:phone":"+43 2167 2693",
    "sg:postcode":"7100",
    "sg:province":"Burgenland",
    "wof:name":"Zimmerei Mock GesmbH",
    "wof:placetype":"venue"
},
  "geometry": {"coordinates":[16.8362445831,47.9606781006],"type":"Point"}
}