{
  "type": "Feature",
  "properties": {
    "addr:full":"Hollabrunner Str 35 Hollabrunn Nieder\u00f6sterreich 2020",
    "addr:housenumber":"35",
    "addr:postcode":"2020",
    "addr:street":"Str",
    "iso:country":"AT",
    "sg:address":"Hollabrunner Str 35",
    "sg:city":"Hollabrunn",
    "sg:orig_category":"Maler, Anstreicher U Lackierer",
    "sg:phone":"+43 4329 5227720",
    "sg:postcode":"2020",
    "sg:province":"Nieder\u00f6sterreich",
    "wof:name":"Weiss Friedrich",
    "wof:placetype":"venue"
},
  "geometry": {"coordinates":[16.0669784546,48.6014022827],"type":"Point"}
}