{
  "type": "Feature",
  "properties": {
    "iso:country":"AT",
    "sg:address":"H\u00fcgelweg 22",
    "sg:city":"Klagenfurt",
    "sg:orig_category":"Entsorgungen",
    "sg:phone":"+43 463 46050",
    "sg:postcode":"9020",
    "sg:province":"K\u00e4rnten",
    "wof:name":"Wei\u00df Ferdinand Hubert",
    "wof:placetype":"venue"
},
  "geometry": {"coordinates":[14.3274202347,46.6254196167],"type":"Point"}
}