{
  "type": "Feature",
  "properties": {
    "iso:country":"AT",
    "sg:address":"Kaiser-Franz-Josef-Ring 5a",
    "sg:city":"Baden",
    "sg:orig_category":"Garten- U Landschaftsgestaltung",
    "sg:phone":"+43 2252 86800530",
    "sg:postcode":"2500",
    "sg:province":"Nieder\u00f6sterreich",
    "wof:name":"Kurpark Stadtgarten-Verwaltung Baden",
    "wof:placetype":"venue"
},
  "geometry": {"coordinates":[16.2388076782,48.0039634705],"type":"Point"}
}