{
  "type": "Feature",
  "properties": {
    "addr:full":"Riggerweg 1 Aldrans Tirol 6071",
    "addr:housenumber":"1",
    "addr:postcode":"6071",
    "addr:street":"Riggerweg;Tirol",
    "iso:country":"AT",
    "sg:address":"Riggerweg 1",
    "sg:city":"Aldrans",
    "sg:orig_category":"Tischlereien",
    "sg:phone":"+43 512 365787",
    "sg:postcode":"6071",
    "sg:province":"Tirol",
    "wof:name":"Wagner Josef Montagetischlerei",
    "wof:placetype":"venue"
},
  "geometry": {"coordinates":[11.4421720505,47.2444648743],"type":"Point"}
}