{
  "type": "Feature",
  "properties": {
    "iso:country":"AT",
    "sg:address":"Industriestr 15",
    "sg:city":"Kleinneusiedl",
    "sg:orig_category":"Hallenvermietung",
    "sg:phone":"+43 4322 302308",
    "sg:postcode":"2431",
    "sg:province":"Nieder\u00f6sterreich",
    "wof:name":"Enzersdorfer Maschinenfabrik",
    "wof:placetype":"venue"
},
  "geometry": {"coordinates":[16.5966262817,48.0726966858],"type":"Point"}
}