{
  "type": "Feature",
  "properties": {
    "iso:country":"AT",
    "sg:address":"Ringstr 5",
    "sg:city":"Rankweil",
    "sg:orig_category":"Telekommunikation",
    "sg:phone":"+43 800 100100",
    "sg:postcode":"6830",
    "sg:province":"Vorarlberg",
    "wof:name":"Telekom Shop",
    "wof:placetype":"venue"
},
  "geometry": {"coordinates":[9.6426782608,47.2699012756],"type":"Point"}
}