{
  "type": "Feature",
  "properties": {
    "addr:full":"Suchenwirtpl 9 Wien Wien 1100",
    "addr:housenumber":"9",
    "addr:postcode":"1100",
    "addr:street":"Suchenwirtpl",
    "iso:country":"AT",
    "sg:address":"Suchenwirtpl 9",
    "sg:city":"Wien",
    "sg:orig_category":"Elektroinstallationsunternehmen",
    "sg:phone":"+43 664 1001019",
    "sg:postcode":"1100",
    "sg:province":"Wien",
    "wof:name":"Salamonski Tadeusz",
    "wof:placetype":"venue"
},
  "geometry": {"coordinates":[16.3735427856,48.1704902649],"type":"Point"}
}