{
  "type": "Feature",
  "properties": {
    "addr:full":"Gestetteng 21 Wien Wien 1030",
    "addr:housenumber":"21",
    "addr:postcode":"1030",
    "addr:street":"Gestetteng",
    "iso:country":"AT",
    "sg:address":"Gestetteng 21",
    "sg:city":"Wien",
    "sg:orig_category":"Non-Classified Establishments",
    "sg:phone":"+43 1 71429960",
    "sg:postcode":"1030",
    "sg:province":"Wien",
    "wof:name":"Kongregation Unserer lieben Frau von Sion",
    "wof:placetype":"venue"
},
  "geometry": {"coordinates":[16.4062290192,48.1953582764],"type":"Point"}
}