{
  "type": "Feature",
  "properties": {
    "addr:full":"Moarg 2 Pinsdorf Ober\u00f6sterreich 4812",
    "addr:housenumber":"2",
    "addr:postcode":"4812",
    "addr:street":"Moarg",
    "iso:country":"AT",
    "sg:address":"Moarg 2",
    "sg:city":"Pinsdorf",
    "sg:orig_category":"Non-Classified Establishments",
    "sg:phone":"+43 761263952",
    "sg:postcode":"4812",
    "sg:province":"Ober\u00f6sterreich",
    "wof:name":"Pfarramt",
    "wof:placetype":"venue"
},
  "geometry": {"coordinates":[13.7705440521,47.9294281006],"type":"Point"}
}