{
  "type": "Feature",
  "properties": {
    "addr:full":"Dorfstr 54 Kundl Tirol 6250",
    "addr:housenumber":"54",
    "addr:postcode":"6250",
    "addr:street":"Dorfstr;Tirol",
    "iso:country":"AT",
    "sg:address":"Dorfstr 54",
    "sg:city":"Kundl",
    "sg:classifiers":[
        {
            "category":"Professional",
            "subcategory":"Computer Services",
            "type":"Services"
        }
    ],
    "sg:phone":"+43 5338 88880",
    "sg:postcode":"6250",
    "sg:province":"Tirol",
    "sg:tags":[
        "software"
    ],
    "wof:name":"Thaler GesmbH",
    "wof:placetype":"venue"
},
  "geometry": {"coordinates":[11.9902296066,47.4709358215],"type":"Point"}
}