{
  "type": "Feature",
  "properties": {
    "iso:country":"AT",
    "sg:address":"Gobergasse 14/1",
    "sg:city":"Wien",
    "sg:classifiers":[
        {
            "category":"Shopping",
            "subcategory":"Computers & Home Electronics",
            "type":"Retail Goods"
        }
    ],
    "sg:phone":"+43 1 8798471",
    "sg:postcode":"1130",
    "sg:province":"Wien",
    "sg:tags":[
        "refill",
        "printer",
        "jet",
        "ink"
    ],
    "wof:name":"Euro Handelsges.m.b.H.",
    "wof:placetype":"venue"
},
  "geometry": {"coordinates":[16.2778835297,48.1784248352],"type":"Point"}
}