{
  "type": "Feature",
  "properties": {
    "iso:country":"AT",
    "sg:address":"Hart 9A",
    "sg:city":"Hargelsberg",
    "sg:orig_category":"Personalbereitstellung",
    "sg:phone":"+43 7225 20595",
    "sg:postcode":"4483",
    "sg:province":"Ober\u00f6sterreich",
    "wof:name":"ATEC Arbeits- Technologie-Personalservice GmbH",
    "wof:placetype":"venue"
},
  "geometry": {"coordinates":[14.4461421967,48.1605072021],"type":"Point"}
}