{
  "type": "Feature",
  "properties": {
    "addr:full":"Mitterndorf 10 Traunkirchen Ober\u00f6sterreich 4801",
    "addr:housenumber":"10",
    "addr:postcode":"4801",
    "addr:street":"Mitterndorf",
    "iso:country":"AT",
    "sg:address":"Mitterndorf 10",
    "sg:city":"Traunkirchen",
    "sg:orig_category":"Beratungsstellen",
    "sg:phone":"+43 76172224",
    "sg:postcode":"4801",
    "sg:province":"Ober\u00f6sterreich",
    "wof:name":"Mutterberatungsstelle",
    "wof:placetype":"venue"
},
  "geometry": {"coordinates":[13.7768621445,47.8583145142],"type":"Point"}
}