{
  "type": "Feature",
  "properties": {
    "addr:full":"Hauptpl. 9-12 Baden Nieder\u00f6sterreich 2500",
    "addr:housenumber":"9-12",
    "addr:postcode":"2500",
    "addr:street":"Baden Niederoesterreich",
    "iso:country":"AT",
    "sg:address":"Hauptpl. 9-12",
    "sg:city":"Baden",
    "sg:classifiers":[
        {
            "category":"Banks & Credit Unions",
            "subcategory":"Bank",
            "type":"Services"
        }
    ],
    "sg:phone":"+43 4322 5288300",
    "sg:postcode":"2500",
    "sg:province":"Nieder\u00f6sterreich",
    "sg:tags":[
        "banking",
        "institution"
    ],
    "wof:name":"VOLKSBANK REGGENMBH",
    "wof:placetype":"venue"
},
  "geometry": {"coordinates":[16.234205246,48.0082740784],"type":"Point"}
}