{
  "type": "Feature",
  "properties": {
    "addr:full":"Dr Waibel-Str 4 Dornbirn Vorarlberg 6850",
    "addr:housenumber":"4",
    "addr:postcode":"6850",
    "iso:country":"AT",
    "sg:address":"Dr Waibel-Str 4",
    "sg:city":"Dornbirn",
    "sg:orig_category":"Reinigungsbedarf U Reinigungsmittel",
    "sg:phone":"+43 5572 222460",
    "sg:postcode":"6850",
    "sg:province":"Vorarlberg",
    "wof:name":"Sonal Waschmittel KG",
    "wof:placetype":"venue"
},
  "geometry": {"coordinates":[9.74477005,47.412399292],"type":"Point"}
}