{
  "type": "Feature",
  "properties": {
    "addr:full":"Sportplatzweg 5 Langkampfen Tirol 6336",
    "addr:housenumber":"5",
    "addr:postcode":"6336",
    "addr:street":"Sportplatzweg;Tirol",
    "iso:country":"AT",
    "sg:address":"Sportplatzweg 5",
    "sg:city":"Langkampfen",
    "sg:orig_category":"Essenzen",
    "sg:phone":"+43 5372 622560",
    "sg:postcode":"6336",
    "sg:province":"Tirol",
    "wof:name":"\u00d6sterreichische Laberzeugung GmbH",
    "wof:placetype":"venue"
},
  "geometry": {"coordinates":[12.1112289429,47.550075531],"type":"Point"}
}