{
  "type": "Feature",
  "properties": {
    "addr:full":"Zetscheg 13 Wien Wien 1230",
    "addr:housenumber":"13",
    "addr:postcode":"1230",
    "addr:street":"Zetscheg",
    "iso:country":"AT",
    "sg:address":"Zetscheg 13",
    "sg:city":"Wien",
    "sg:classifiers":[
        {
            "category":"Professional",
            "subcategory":"Computer Services",
            "type":"Services"
        }
    ],
    "sg:phone":"+43 1 6627800816",
    "sg:postcode":"1230",
    "sg:province":"Wien",
    "sg:tags":[
        "software"
    ],
    "wof:name":"simply IT - Informationstechnologie GmbH",
    "wof:placetype":"venue"
},
  "geometry": {"coordinates":[16.3321990967,48.1411437988],"type":"Point"}
}