{
  "type": "Feature",
  "properties": {
    "addr:full":"Bahnhofstr. 32  Leibnitz Steiermark 8430",
    "addr:postcode":"8430",
    "addr:street":"Bahnhofstr. 32;Steiermark",
    "iso:country":"AT",
    "sg:address":"Bahnhofstr. 32 ",
    "sg:city":"Leibnitz",
    "sg:classifiers":[
        {
            "category":"Shopping",
            "subcategory":"Clothing, Apparel, & Fashions",
            "type":"Retail Goods"
        }
    ],
    "sg:phone":"+43 4334 52822340",
    "sg:postcode":"8430",
    "sg:province":"Steiermark",
    "sg:tags":[
        "clothes"
    ],
    "wof:name":"PFEIFER GESMBH",
    "wof:placetype":"venue"
},
  "geometry": {"coordinates":[15.5454940796,46.7821884155],"type":"Point"}
}