{
  "type": "Feature",
  "properties": {
    "addr:full":"Praunstr 27 Langenzersdorf Nieder\u00f6sterreich 2103",
    "addr:housenumber":"27",
    "addr:postcode":"2103",
    "addr:street":"Praunstr",
    "iso:country":"AT",
    "sg:address":"Praunstr 27",
    "sg:city":"Langenzersdorf",
    "sg:orig_category":"Reproanstalten",
    "sg:phone":"+43 2244 29157",
    "sg:postcode":"2103",
    "sg:province":"Nieder\u00f6sterreich",
    "wof:name":"Krammer-Repro Flexo Print GmbH",
    "wof:placetype":"venue"
},
  "geometry": {"coordinates":[16.3492565155,48.3022003174],"type":"Point"}
}