{
  "type": "Feature",
  "properties": {
    "iso:country":"AT",
    "sg:address":"Nr 19",
    "sg:city":"Rohr im Gebirge",
    "sg:orig_category":"Bodenverlegung",
    "sg:phone":"+43 2667 8240",
    "sg:postcode":"2663",
    "sg:province":"Nieder\u00f6sterreich",
    "wof:name":"Wagner Franz",
    "wof:placetype":"venue"
},
  "geometry": {"coordinates":[15.7363061905,47.8951377869],"type":"Point"}
}