{
  "type": "Feature",
  "properties": {
    "iso:country":"AT",
    "sg:address":"Siccardsburgg 49-51",
    "sg:city":"Wien",
    "sg:orig_category":"Ballettschulen",
    "sg:phone":"+43 1 6024573",
    "sg:postcode":"1100",
    "sg:province":"Wien",
    "sg:website":"ballettschule-favoriten.at",
    "wof:name":"Kinderballettschule Favoriten",
    "wof:placetype":"venue"
},
  "geometry": {"coordinates":[16.3707847595,48.1748123169],"type":"Point"}
}