{
  "type": "Feature",
  "properties": {
    "iso:country":"AT",
    "sg:address":"Stifterstr 10",
    "sg:city":"Linz",
    "sg:orig_category":"Handelsagenturen",
    "sg:phone":"+43 732 737234",
    "sg:postcode":"4020",
    "sg:province":"Ober\u00f6sterreich",
    "wof:name":"F\u00fcrtauer Kurt Textilagentur",
    "wof:placetype":"venue"
},
  "geometry": {"coordinates":[14.2849502563,48.2995834351],"type":"Point"}
}