{
  "type": "Feature",
  "properties": {
    "iso:country":"AT",
    "sg:address":"Nr 2",
    "sg:city":"Sch\u00f6rfling am Attersee",
    "sg:orig_category":"Gemeinden",
    "sg:phone":"+43 4376 6263110",
    "sg:postcode":"4861",
    "sg:province":"Ober\u00f6sterreich",
    "wof:name":"Gemeindeamt Aurach Hongar",
    "wof:placetype":"venue"
},
  "geometry": {"coordinates":[13.6041002274,47.9463386536],"type":"Point"}
}