{
  "type": "Feature",
  "properties": {
    "iso:country":"AT",
    "sg:address":"Gumpendorfer Strasse 147",
    "sg:city":"Wien",
    "sg:classifiers":[
        {
            "category":"Home & Garden",
            "subcategory":"Carpets & Floor Coverings",
            "type":"Retail Goods"
        }
    ],
    "sg:phone":"+43 1 5965118",
    "sg:postcode":"1060",
    "sg:province":"Wien",
    "sg:tags":[
        "restoration"
    ],
    "wof:name":"Johann Gross Ges.m.b.H.",
    "wof:placetype":"venue"
},
  "geometry": {"coordinates":[16.3398628235,48.1903953552],"type":"Point"}
}