{
  "type": "Feature",
  "properties": {
    "addr:full":"Industriezeile 63  Linz Ober\u00f6sterreich 4020",
    "addr:housenumber":"63",
    "addr:postcode":"4020",
    "addr:street":"Industriezeile",
    "iso:country":"AT",
    "sg:address":"Industriezeile 63 ",
    "sg:city":"Linz",
    "sg:classifiers":[
        {
            "category":"Shopping",
            "subcategory":"Clothing, Apparel, & Fashions",
            "type":"Retail Goods"
        }
    ],
    "sg:phone":"+43 4373 2779855",
    "sg:postcode":"4020",
    "sg:province":"Ober\u00f6sterreich",
    "sg:tags":[
        "clothes"
    ],
    "wof:name":"SCHERZER GMBH & CO.",
    "wof:placetype":"venue"
},
  "geometry": {"coordinates":[14.3191843033,48.3026390076],"type":"Point"}
}