{
  "type": "Feature",
  "properties": {
    "addr:full":"Linzer Str 114 Gablitz Nieder\u00f6sterreich 3003",
    "addr:housenumber":"114",
    "addr:postcode":"3003",
    "addr:street":"Linzer Str",
    "iso:country":"AT",
    "sg:address":"Linzer Str 114",
    "sg:city":"Gablitz",
    "sg:orig_category":"Dachdeckereien",
    "sg:phone":"+43 4322 3164852",
    "sg:postcode":"3003",
    "sg:province":"Nieder\u00f6sterreich",
    "wof:name":"Petrovic Zeljko",
    "wof:placetype":"venue"
},
  "geometry": {"coordinates":[16.1489925385,48.2311592102],"type":"Point"}
}