{
  "type": "Feature",
  "properties": {
    "iso:country":"AT",
    "sg:address":"Haselweg 5",
    "sg:city":"Wernberg",
    "sg:orig_category":"Architekten",
    "sg:phone":"+43 4252 4249",
    "sg:postcode":"9241",
    "sg:province":"K\u00e4rnten",
    "wof:name":"Revedin Jana DI Dr techn",
    "wof:placetype":"venue"
},
  "geometry": {"coordinates":[13.949757576,46.6302185059],"type":"Point"}
}