{
  "type": "Feature",
  "properties": {
    "addr:full":"Salzburger Str 229 Linz Ober\u00f6sterreich 4020",
    "addr:housenumber":"229",
    "addr:postcode":"4020",
    "addr:street":"Salzburger Str",
    "iso:country":"AT",
    "sg:address":"Salzburger Str 229",
    "sg:city":"Linz",
    "sg:orig_category":"Maler, Anstreicher U Lackierer",
    "sg:phone":"+43 732 330694",
    "sg:postcode":"4020",
    "sg:province":"Ober\u00f6sterreich",
    "wof:name":"Malerei POP",
    "wof:placetype":"venue"
},
  "geometry": {"coordinates":[14.2886800766,48.2556343079],"type":"Point"}
}