{
  "type": "Feature",
  "properties": {
    "addr:full":"Wagenham 25 Mattighofen Ober\u00f6sterreich 5230",
    "addr:housenumber":"25",
    "addr:postcode":"5230",
    "addr:street":"Wagenham",
    "iso:country":"AT",
    "sg:address":"Wagenham 25",
    "sg:city":"Mattighofen",
    "sg:classifiers":[
        {
            "category":"Manufacturing",
            "subcategory":"Wood Products",
            "type":"Manufacturing & Wholesale Goods"
        }
    ],
    "sg:phone":"+43 7742 2768",
    "sg:postcode":"5230",
    "sg:province":"Ober\u00f6sterreich",
    "sg:tags":[
        "made",
        "balcony"
    ],
    "wof:name":"Franz Jaidl Bau und M\u00f6beltischlerei",
    "wof:placetype":"venue"
},
  "geometry": {"coordinates":[13.1115522385,48.0954551697],"type":"Point"}
}