{
  "type": "Feature",
  "properties": {
    "addr:full":"Nibelungenstr 38 Persenbeug Nieder\u00f6sterreich 3680",
    "addr:housenumber":"38",
    "addr:postcode":"3680",
    "addr:street":"Nibelungenstr",
    "iso:country":"AT",
    "sg:address":"Nibelungenstr 38",
    "sg:city":"Persenbeug",
    "sg:orig_category":"Non-Classified Establishments",
    "sg:phone":"+43 5 91333141",
    "sg:postcode":"3680",
    "sg:province":"Nieder\u00f6sterreich",
    "wof:name":"Gendarmerie",
    "wof:placetype":"venue"
},
  "geometry": {"coordinates":[15.0903396606,48.1885223389],"type":"Point"}
}