{
  "type": "Feature",
  "properties": {
    "addr:full":"W\u00e4hringer G\u00fcrtel 97 Wien Wien 1180",
    "addr:housenumber":"97",
    "addr:postcode":"1180",
    "iso:country":"AT",
    "sg:address":"W\u00e4hringer G\u00fcrtel 97",
    "sg:city":"Wien",
    "sg:classifiers":[
        {
            "category":"Professional",
            "subcategory":"Advertising",
            "type":"Services"
        }
    ],
    "sg:phone":"+43 4314 76770",
    "sg:postcode":"1180",
    "sg:province":"Wien",
    "sg:tags":[
        "communication",
        "medium"
    ],
    "wof:name":"WIFI WIRTSCHAFTSF\u00d6RDERUNGINSTITUT D. WIRTSCHAFTSK. WIEN",
    "wof:placetype":"venue"
},
  "geometry": {"coordinates":[16.3445625305,48.2262420654],"type":"Point"}
}