{
  "type": "Feature",
  "properties": {
    "iso:country":"AT",
    "sg:address":"Lustenauer Str 58",
    "sg:city":"Dornbirn",
    "sg:orig_category":"Tiefbau",
    "sg:phone":"+43 4355 72398855",
    "sg:postcode":"6850",
    "sg:province":"Vorarlberg",
    "wof:name":"Grund- Pfahl- u Sonderbau GmbH",
    "wof:placetype":"venue"
},
  "geometry": {"coordinates":[9.7200269699,47.4105186462],"type":"Point"}
}