{
  "type": "Feature",
  "properties": {
    "addr:full":"Annenstrasse 66 Graz Steiermark 8020",
    "addr:housenumber":"66",
    "addr:postcode":"8020",
    "addr:street":"Annenstrasse",
    "iso:country":"AT",
    "sg:address":"Annenstrasse 66",
    "sg:city":"Graz",
    "sg:classifiers":[
        {
            "category":"Professional",
            "subcategory":"Advertising",
            "type":"Services"
        }
    ],
    "sg:phone":"+43 316 711017",
    "sg:postcode":"8020",
    "sg:province":"Steiermark",
    "sg:tags":[
        "articles"
    ],
    "sg:website":"werbe-weisz.at",
    "wof:name":"Gerd H. A. Wei\u00df",
    "wof:placetype":"venue"
},
  "geometry": {"coordinates":[15.4210224152,47.0714797974],"type":"Point"}
}