{
  "type": "Feature",
  "properties": {
    "addr:full":"Marktpl 2 B\u00f6heimkirchen Nieder\u00f6sterreich 3071",
    "addr:housenumber":"2",
    "addr:postcode":"3071",
    "addr:street":"Marktpl;Niederoesterreich",
    "iso:country":"AT",
    "sg:address":"Marktpl 2",
    "sg:city":"B\u00f6heimkirchen",
    "sg:orig_category":"Gemeinden",
    "sg:phone":"+43 2743 23180",
    "sg:postcode":"3071",
    "sg:province":"Nieder\u00f6sterreich",
    "wof:name":"Gemeinde B\u00f6heimkirchen",
    "wof:placetype":"venue"
},
  "geometry": {"coordinates":[7.7524180412,47.9154930115],"type":"Point"}
}