{
  "type": "Feature",
  "properties": {
    "iso:country":"AT",
    "sg:address":"Schreckg 19",
    "sg:city":"Wien",
    "sg:orig_category":"Non-Classified Establishments",
    "sg:phone":"+43 1 88841910",
    "sg:postcode":"1230",
    "sg:province":"Wien",
    "wof:name":"Pfarramt Rodaun",
    "wof:placetype":"venue"
},
  "geometry": {"coordinates":[16.2647838593,48.1377754211],"type":"Point"}
}