{
  "type": "Feature",
  "properties": {
    "addr:full":"Sonnenbergerstrasse 4 Frastanz Vorarlberg 6820",
    "addr:housenumber":"4",
    "addr:postcode":"6820",
    "addr:street":"Sonnenbergerstrasse",
    "iso:country":"AT",
    "sg:address":"Sonnenbergerstrasse 4",
    "sg:city":"Frastanz",
    "sg:classifiers":[
        {
            "category":"Utilities",
            "subcategory":"Cable",
            "type":"Services"
        }
    ],
    "sg:phone":"+43 5522 51710",
    "sg:postcode":"6820",
    "sg:province":"Vorarlberg",
    "sg:tags":[
        "cableways",
        "aerial",
        "accessory",
        "cable-lifts",
        "drag",
        "lift"
    ],
    "sg:website":"reisch.at",
    "wof:name":"Ing. Walter Reisch",
    "wof:placetype":"venue"
},
  "geometry": {"coordinates":[9.6294879913,47.2231292725],"type":"Point"}
}