{
  "type": "Feature",
  "properties": {
    "addr:full":"Industriestr 1 Eisenstadt Burgenland 7000",
    "addr:housenumber":"1",
    "addr:postcode":"7000",
    "addr:street":"Industriestr",
    "iso:country":"AT",
    "sg:address":"Industriestr 1",
    "sg:city":"Eisenstadt",
    "sg:orig_category":"Schlossereien",
    "sg:phone":"+43 2682 65995",
    "sg:postcode":"7000",
    "sg:province":"Burgenland",
    "wof:name":"Haiden Erich GesmbH",
    "wof:placetype":"venue"
},
  "geometry": {"coordinates":[16.5316314697,47.8322257996],"type":"Point"}
}