{
  "type": "Feature",
  "properties": {
    "iso:country":"AT",
    "sg:address":"Hartlg 4",
    "sg:city":"Pottendorf",
    "sg:orig_category":"\u00c3\u201erzte / F Allgemeinmedizin",
    "sg:phone":"+43 2623 73147",
    "sg:postcode":"2486",
    "sg:province":"Nieder\u00f6sterreich",
    "wof:name":"Sheriff Eiaz-Ahmed Dr",
    "wof:placetype":"venue"
},
  "geometry": {"coordinates":[16.3865890503,47.9095191956],"type":"Point"}
}