{
  "type": "Feature",
  "properties": {
    "addr:full":"Wiener Str 15 Zeiselmauer Nieder\u00f6sterreich 3424",
    "addr:postcode":"3424",
    "addr:street":"Niederoesterreich",
    "iso:country":"AT",
    "sg:address":"Wiener Str 15",
    "sg:city":"Zeiselmauer",
    "sg:orig_category":"Baumschulen",
    "sg:phone":"+43 664 1920114",
    "sg:postcode":"3424",
    "sg:province":"Nieder\u00f6sterreich",
    "wof:name":"LDW Baumschule Bogner OEG",
    "wof:placetype":"venue"
},
  "geometry": {"coordinates":[16.1807308197,48.3267936707],"type":"Point"}
}