{
  "type": "Feature",
  "properties": {
    "addr:full":"Albert Schweitzer-G 6 Wien Wien 1140",
    "addr:housenumber":"6",
    "addr:postcode":"1140",
    "iso:country":"AT",
    "sg:address":"Albert Schweitzer-G 6",
    "sg:city":"Wien",
    "sg:orig_category":"Tanzschulen",
    "sg:phone":"+43 1 8659656",
    "sg:postcode":"1140",
    "sg:province":"Wien",
    "wof:name":"Tanzschule Immervoll",
    "wof:placetype":"venue"
},
  "geometry": {"coordinates":[16.217338562,48.2078437805],"type":"Point"}
}