{
  "type": "Feature",
  "properties": {
    "iso:country":"AT",
    "sg:address":"Wickenburgg 17",
    "sg:city":"Wien",
    "sg:orig_category":"Schlossereien",
    "sg:phone":"+43 1 4081997",
    "sg:postcode":"1080",
    "sg:province":"Wien",
    "wof:name":"Schmalhardt Schlosserei - Schl\u00fcsseldienst",
    "wof:placetype":"venue"
},
  "geometry": {"coordinates":[16.353723526,48.2137718201],"type":"Point"}
}