{
  "type": "Feature",
  "properties": {
    "addr:full":"Schlo\u00dfpl 2 Judenau Nieder\u00f6sterreich 3441",
    "addr:housenumber":"2",
    "addr:postcode":"3441",
    "addr:street":"Schlosspl",
    "iso:country":"AT",
    "sg:address":"Schlo\u00dfpl 2",
    "sg:city":"Judenau",
    "sg:orig_category":"Non-Classified Establishments",
    "sg:phone":"+43 2274 7960",
    "sg:postcode":"3441",
    "sg:province":"Nieder\u00f6sterreich",
    "wof:name":"Pfarramt",
    "wof:placetype":"venue"
},
  "geometry": {"coordinates":[16.0104503632,48.2846717834],"type":"Point"}
}