{
  "type": "Feature",
  "properties": {
    "iso:country":"AT",
    "sg:address":"Hatschekstrasse 25",
    "sg:city":"Gmunden",
    "sg:classifiers":[
        {
            "category":"Manufacturing",
            "subcategory":"Building Materials",
            "type":"Manufacturing & Wholesale Goods"
        }
    ],
    "sg:phone":"+43 76127880",
    "sg:postcode":"4810",
    "sg:province":"Ober\u00f6sterreich",
    "sg:tags":[
        "cement"
    ],
    "sg:website":"gmundner-zement.at/",
    "wof:name":"Gmundner Zement Produktions- und Handels GmbH",
    "wof:placetype":"venue"
},
  "geometry": {"coordinates":[13.7981462479,47.918598175],"type":"Point"}
}