{
  "type": "Feature",
  "properties": {
    "iso:country":"AT",
    "sg:address":"Untere Ortsstrasse 34 ",
    "sg:city":"Gramatneusiedl",
    "sg:classifiers":[
        {
            "category":"Home & Garden",
            "subcategory":"Kitchen Supply",
            "type":"Retail Goods"
        }
    ],
    "sg:phone":"+43 2234 80251",
    "sg:postcode":"2440",
    "sg:province":"Nieder\u00f6sterreich",
    "sg:tags":[
        "household",
        "electric",
        "cooker"
    ],
    "wof:name":"Hermann Niessler Ges.m.b.H.",
    "wof:placetype":"venue"
},
  "geometry": {"coordinates":[16.5301303864,47.9979019165],"type":"Point"}
}