{
  "type": "Feature",
  "properties": {
    "addr:full":"Traunsteinstr 229 Gmunden Ober\u00f6sterreich 4810",
    "addr:housenumber":"229",
    "addr:postcode":"4810",
    "addr:street":"Oberoesterreich",
    "iso:country":"AT",
    "sg:address":"Traunsteinstr 229",
    "sg:city":"Gmunden",
    "sg:orig_category":"Tischlereien",
    "sg:phone":"+43 761263077",
    "sg:postcode":"4810",
    "sg:province":"Ober\u00f6sterreich",
    "wof:name":"Ebner Ferdinand",
    "wof:placetype":"venue"
},
  "geometry": {"coordinates":[13.808634758,47.8890762329],"type":"Point"}
}