{
  "type": "Feature",
  "properties": {
    "iso:country":"AT",
    "sg:address":"Judeng 5-7",
    "sg:city":"Salzburg",
    "sg:orig_category":"Internet-Cafes",
    "sg:phone":"+43 662 841470",
    "sg:postcode":"5020",
    "sg:province":"Salzburg",
    "wof:name":"BIGnet Internet Cafe",
    "wof:placetype":"venue"
},
  "geometry": {"coordinates":[13.0461015701,47.7999649048],"type":"Point"}
}