{
  "type": "Feature",
  "properties": {
    "addr:full":"Haller Str 7 Innsbruck Tirol 6020",
    "addr:housenumber":"7",
    "addr:postcode":"6020",
    "addr:street":"Str;Tirol",
    "iso:country":"AT",
    "sg:address":"Haller Str 7",
    "sg:city":"Innsbruck",
    "sg:classifiers":[
        {
            "category":"Travel",
            "subcategory":"Hotels & Motels",
            "type":"Entertainment"
        }
    ],
    "sg:phone":"+43 512 267506",
    "sg:postcode":"6020",
    "sg:province":"Tirol",
    "wof:name":"Hotel-Restaurant Dollinger",
    "wof:placetype":"venue"
},
  "geometry": {"coordinates":[11.4064321518,47.2813644409],"type":"Point"}
}