{
  "type": "Feature",
  "properties": {
    "iso:country":"AT",
    "sg:address":"Klammstr 11",
    "sg:city":"Weiz",
    "sg:orig_category":"Fotografen",
    "sg:phone":"+43 3172 2402",
    "sg:postcode":"8160",
    "sg:province":"Steiermark",
    "wof:name":"Gorkiewicz Foto",
    "wof:placetype":"venue"
},
  "geometry": {"coordinates":[15.6216554642,47.2186203003],"type":"Point"}
}