{
  "type": "Feature",
  "properties": {
    "addr:full":"Michaelig 31 Hartberg Steiermark 8230",
    "addr:housenumber":"31",
    "addr:postcode":"8230",
    "addr:street":"Michaelig",
    "iso:country":"AT",
    "sg:address":"Michaelig 31",
    "sg:city":"Hartberg",
    "sg:classifiers":[
        {
            "category":"Wholesale",
            "subcategory":"Motor Vehicles",
            "type":"Manufacturing & Wholesale Goods"
        }
    ],
    "sg:phone":"+43 4333 3262274",
    "sg:postcode":"8230",
    "sg:province":"Steiermark",
    "sg:tags":[
        "moped"
    ],
    "wof:name":"Kappler Karl Ing GesmbH & Co KG",
    "wof:placetype":"venue"
},
  "geometry": {"coordinates":[15.9727478027,47.2819519043],"type":"Point"}
}