{
  "type": "Feature",
  "properties": {
    "iso:country":"AT",
    "sg:address":"Hirschlitten 463",
    "sg:city":"Mellau",
    "sg:orig_category":"Appartements / Ferienwohnungen",
    "sg:phone":"+43 5518 20139",
    "sg:postcode":"6881",
    "sg:province":"Vorarlberg",
    "wof:name":"Lutz Ferienwohnungen",
    "wof:placetype":"venue"
},
  "geometry": {"coordinates":[9.884601593,47.3522987366],"type":"Point"}
}