{
  "type": "Feature",
  "properties": {
    "addr:full":"Domkapitelweg 15 Hallein Salzburg 5400",
    "addr:housenumber":"15",
    "addr:postcode":"5400",
    "addr:street":"Domkapitelweg;Salzburg",
    "iso:country":"AT",
    "sg:address":"Domkapitelweg 15",
    "sg:city":"Hallein",
    "sg:classifiers":[
        {
            "category":"Internet Cafe",
            "subcategory":"None",
            "type":"Food & Drink"
        }
    ],
    "sg:phone":"+43 6245 70473",
    "sg:postcode":"5400",
    "sg:province":"Salzburg",
    "wof:name":"Datashop Riedel KEG",
    "wof:placetype":"venue"
},
  "geometry": {"coordinates":[13.069272995,47.7070236206],"type":"Point"}
}