{
  "type": "Feature",
  "properties": {
    "iso:country":"AT",
    "sg:address":"Hauptstr. 107",
    "sg:city":"Breitenfurt",
    "sg:orig_category":"Miscellaneous Products",
    "sg:phone":"+43 4322 395058",
    "sg:postcode":"2384",
    "sg:province":"Nieder\u00f6sterreich",
    "wof:name":"TOPLAK GESELLSCHAFTM.B.H",
    "wof:placetype":"venue"
},
  "geometry": {"coordinates":[16.1931934357,48.1357727051],"type":"Point"}
}