{
  "type": "Feature",
  "properties": {
    "addr:full":"Dinghoferstr 63 Linz Ober\u00f6sterreich 4020",
    "addr:housenumber":"63",
    "addr:postcode":"4020",
    "addr:street":"Dinghoferstr",
    "iso:country":"AT",
    "sg:address":"Dinghoferstr 63",
    "sg:city":"Linz",
    "sg:orig_category":"Genossenschaften",
    "sg:phone":"+43 732 6581450",
    "sg:postcode":"4020",
    "sg:province":"Ober\u00f6sterreich",
    "wof:name":"Gemeinn\u00fctzige Wohnungs- und Siedlungsgenossenschaft Baureform-Wohnst\u00e4tte",
    "wof:placetype":"venue"
},
  "geometry": {"coordinates":[14.299071312,48.2973251343],"type":"Point"}
}