{
  "type": "Feature",
  "properties": {
    "iso:country":"AT",
    "sg:address":"K\u00e4rntner Ring 9-13",
    "sg:city":"Wien",
    "sg:classifiers":[
        {
            "category":"Travel",
            "subcategory":"Travel Agent",
            "type":"Entertainment"
        }
    ],
    "sg:phone":"+43 4315 1580",
    "sg:postcode":"1010",
    "sg:province":"Wien",
    "sg:tags":[
        "business"
    ],
    "wof:name":"ANA GRAND HOTEL WIEN",
    "wof:placetype":"venue"
},
  "geometry": {"coordinates":[16.3718757629,48.2020454407],"type":"Point"}
}