{
  "type": "Feature",
  "properties": {
    "addr:full":"Kirchg 7 Dornbirn Vorarlberg 6850",
    "addr:housenumber":"7",
    "addr:postcode":"6850",
    "addr:street":"Kirchg",
    "iso:country":"AT",
    "sg:address":"Kirchg 7",
    "sg:city":"Dornbirn",
    "sg:orig_category":"Friseure U Frisiersalons",
    "sg:phone":"+43 5572 386943",
    "sg:postcode":"6850",
    "sg:province":"Vorarlberg",
    "wof:name":"Fris\u00f6r Halime",
    "wof:placetype":"venue"
},
  "geometry": {"coordinates":[9.7524662018,47.4100761414],"type":"Point"}
}