{
  "type": "Feature",
  "properties": {
    "iso:country":"AT",
    "sg:address":"Warneckestr 9",
    "sg:city":"Wien",
    "sg:orig_category":"Speditionen",
    "sg:phone":"+43 1 760440",
    "sg:postcode":"1110",
    "sg:province":"Wien",
    "wof:name":"Logotec Logistikservice GmbH & Co KG",
    "wof:placetype":"venue"
},
  "geometry": {"coordinates":[16.4801044464,48.1642341614],"type":"Point"}
}