{
  "type": "Feature",
  "properties": {
    "iso:country":"AT",
    "sg:address":"Nr 72",
    "sg:city":"Annaberg",
    "sg:classifiers":[
        {
            "category":"Travel",
            "subcategory":"Hotels & Motels",
            "type":"Entertainment"
        }
    ],
    "sg:phone":"+43 6463 84660",
    "sg:postcode":"5524",
    "sg:province":"Salzburg",
    "sg:website":"sporthotel-dachsteinwest.at",
    "wof:name":"Sporthotel Dachstein West",
    "wof:placetype":"venue"
},
  "geometry": {"coordinates":[13.4312047958,47.513458252],"type":"Point"}
}