{
  "type": "Feature",
  "properties": {
    "iso:country":"AT",
    "sg:address":"Am Kaiserm\u00fchlendamm 53",
    "sg:city":"Wien",
    "sg:classifiers":[
        {
            "category":"Restaurant",
            "type":"Food & Drink"
        }
    ],
    "sg:phone":"+43 1 2692120",
    "sg:postcode":"1220",
    "sg:province":"Wien",
    "sg:tags":[
        "pizzeria"
    ],
    "wof:name":"Pizzakeller",
    "wof:placetype":"venue"
},
  "geometry": {"coordinates":[16.444606781,48.2497138977],"type":"Point"}
}