{
  "type": "Feature",
  "properties": {
    "addr:full":"Fernkorng 41 Wien Wien 1100",
    "addr:housenumber":"41",
    "addr:postcode":"1100",
    "addr:street":"Fernkorng",
    "iso:country":"AT",
    "sg:address":"Fernkorng 41",
    "sg:city":"Wien",
    "sg:orig_category":"Tischlereien",
    "sg:phone":"+43 1 6020288",
    "sg:postcode":"1100",
    "sg:province":"Wien",
    "wof:name":"Zobl G\u00fcnter",
    "wof:placetype":"venue"
},
  "geometry": {"coordinates":[16.3635482788,48.1746101379],"type":"Point"}
}