{
  "type": "Feature",
  "properties": {
    "addr:full":"Josef \u00d6sterreicher-G 25-29 Wien Wien 1230",
    "addr:postcode":"25-29;1230",
    "iso:country":"AT",
    "sg:address":"Josef \u00d6sterreicher-G 25-29",
    "sg:city":"Wien",
    "sg:orig_category":"Getriebe",
    "sg:phone":"+43 1 865950542",
    "sg:postcode":"1230",
    "sg:province":"Wien",
    "wof:name":"Modul Getriebe und Zahnr\u00e4der Handel und Service GesmbH",
    "wof:placetype":"venue"
},
  "geometry": {"coordinates":[16.3010730743,48.146446228],"type":"Point"}
}