{
  "type": "Feature",
  "properties": {
    "addr:full":"Hafenstr 53 Krems an der Donau Nieder\u00f6sterreich 3500",
    "addr:housenumber":"53",
    "addr:postcode":"3500",
    "addr:street":"Hafenstr",
    "iso:country":"AT",
    "sg:address":"Hafenstr 53",
    "sg:city":"Krems an der Donau",
    "sg:orig_category":"Lebensmittel / Einzelhandel",
    "sg:phone":"+43 2732 83377",
    "sg:postcode":"3500",
    "sg:province":"Nieder\u00f6sterreich",
    "wof:name":"Billa AG",
    "wof:placetype":"venue"
},
  "geometry": {"coordinates":[15.6288442612,48.4095954895],"type":"Point"}
}