{
  "type": "Feature",
  "properties": {
    "addr:full":"Hernalser Hauptstr 204 Wien Wien 1170",
    "addr:housenumber":"204",
    "addr:postcode":"1170",
    "addr:street":"Hernalser Hauptstr",
    "iso:country":"AT",
    "sg:address":"Hernalser Hauptstr 204",
    "sg:city":"Wien",
    "sg:orig_category":"Restaurants: Dalmatinisch",
    "sg:phone":"+43 1 4864311",
    "sg:postcode":"1170",
    "sg:province":"Wien",
    "wof:name":"BODULO - Fischrestaurant",
    "wof:placetype":"venue"
},
  "geometry": {"coordinates":[16.3122959137,48.2249603271],"type":"Point"}
}