{
  "type": "Feature",
  "properties": {
    "addr:full":"Dauphinestr 204 Linz Ober\u00f6sterreich 4030",
    "addr:housenumber":"204",
    "addr:postcode":"4030",
    "iso:country":"AT",
    "sg:address":"Dauphinestr 204",
    "sg:city":"Linz",
    "sg:orig_category":"Reinigungsservice",
    "sg:phone":"+43 4373 2301332",
    "sg:postcode":"4030",
    "sg:province":"Ober\u00f6sterreich",
    "wof:name":"Tuseva Clean KEG",
    "wof:placetype":"venue"
},
  "geometry": {"coordinates":[14.2899646759,48.2531700134],"type":"Point"}
}