{
  "type": "Feature",
  "properties": {
    "addr:full":"Bundesstrasse 33 Lauterach Vorarlberg 6923",
    "addr:housenumber":"33",
    "addr:postcode":"6923",
    "addr:street":"Bundesstrasse",
    "iso:country":"AT",
    "sg:address":"Bundesstrasse 33",
    "sg:city":"Lauterach",
    "sg:orig_category":"ArtistS Brushes",
    "sg:phone":"+43 5574 71256",
    "sg:postcode":"6923",
    "sg:province":"Vorarlberg",
    "wof:name":"Sternpinselfabrik Arno D\u00fcr",
    "wof:placetype":"venue"
},
  "geometry": {"coordinates":[9.7319927216,47.4797058105],"type":"Point"}
}