{
  "type": "Feature",
  "properties": {
    "iso:country":"AT",
    "sg:address":"L\u00e4ngenfeldgasse 27",
    "sg:city":"Wien",
    "sg:classifiers":[
        {
            "category":"Organizations",
            "subcategory":"Non-profit Organization",
            "type":"Services"
        }
    ],
    "sg:phone":"+43 1 81535080",
    "sg:postcode":"1120",
    "sg:province":"Wien",
    "sg:tags":[
        "alarm",
        "system"
    ],
    "sg:website":"dialog-urmet.at",
    "wof:name":"Dialog Elektroger\u00e4te Vertriebsges.m.b.H.",
    "wof:placetype":"venue"
},
  "geometry": {"coordinates":[16.3404750824,48.1792640686],"type":"Point"}
}