{
  "type": "Feature",
  "properties": {
    "addr:full":"Sulza 11 Gams Steiermark 8922",
    "addr:housenumber":"11",
    "addr:postcode":"8922",
    "addr:street":"Sulza",
    "iso:country":"AT",
    "sg:address":"Sulza 11",
    "sg:city":"Gams",
    "sg:orig_category":"Appartements / Ferienwohnungen",
    "sg:phone":"+43 3637 368",
    "sg:postcode":"8922",
    "sg:province":"Steiermark",
    "wof:name":"St\u00fccklerhof",
    "wof:placetype":"venue"
},
  "geometry": {"coordinates":[14.7837543488,47.6708869934],"type":"Point"}
}