{
  "type": "Feature",
  "properties": {
    "addr:full":"Radetzkystr 2 Klagenfurt K\u00e4rnten 9020",
    "addr:housenumber":"2",
    "addr:postcode":"9020",
    "addr:street":"Radetzkystr;Kaernten",
    "iso:country":"AT",
    "sg:address":"Radetzkystr 2",
    "sg:city":"Klagenfurt",
    "sg:orig_category":"Zahntechnische Laboratorien",
    "sg:phone":"+43 463 56518",
    "sg:postcode":"9020",
    "sg:province":"K\u00e4rnten",
    "wof:name":"Koinig Horst",
    "wof:placetype":"venue"
},
  "geometry": {"coordinates":[14.301404953,46.6272277832],"type":"Point"}
}