{
  "type": "Feature",
  "properties": {
    "addr:full":"Hauptstr 25 P\u00f6lfing-Brunn Steiermark 8544",
    "addr:housenumber":"25",
    "addr:postcode":"8544",
    "addr:street":"Hauptstr",
    "iso:country":"AT",
    "sg:address":"Hauptstr 25",
    "sg:city":"P\u00f6lfing-Brunn",
    "sg:orig_category":"Tankstellen",
    "sg:phone":"+43 4334 6525050",
    "sg:postcode":"8544",
    "sg:province":"Steiermark",
    "wof:name":"OMV AG",
    "wof:placetype":"venue"
},
  "geometry": {"coordinates":[15.2966852188,46.7287216187],"type":"Point"}
}