{
  "type": "Feature",
  "properties": {
    "addr:full":"Uferstr 15 Maishofen Salzburg 5751",
    "addr:housenumber":"15",
    "addr:postcode":"5751",
    "addr:street":"Uferstr;Salzburg",
    "iso:country":"AT",
    "sg:address":"Uferstr 15",
    "sg:city":"Maishofen",
    "sg:orig_category":"Fliesen U Platten",
    "sg:phone":"+43 4365 4280235",
    "sg:postcode":"5751",
    "sg:province":"Salzburg",
    "wof:name":"Holz M FliesengesmbH",
    "wof:placetype":"venue"
},
  "geometry": {"coordinates":[12.8250045776,47.38048172],"type":"Point"}
}