{
  "type": "Feature",
  "properties": {
    "iso:country":"AT",
    "sg:address":"Garberg 2",
    "sg:city":"Wattens",
    "sg:orig_category":"Feuerwehren",
    "sg:phone":"+43 5224 5800",
    "sg:postcode":"6112",
    "sg:province":"Tirol",
    "wof:name":"Freiwillige Feuerwehr Wattens",
    "wof:placetype":"venue"
},
  "geometry": {"coordinates":[11.5920343399,47.2899665833],"type":"Point"}
}