{
  "type": "Feature",
  "properties": {
    "addr:full":"Hauptstr 6 Attersee Ober\u00f6sterreich 4864",
    "addr:housenumber":"6",
    "addr:postcode":"4864",
    "addr:street":"Hauptstr",
    "iso:country":"AT",
    "sg:address":"Hauptstr 6",
    "sg:city":"Attersee",
    "sg:orig_category":"Non-Classified Establishments",
    "sg:phone":"+43 76667783",
    "sg:postcode":"4864",
    "sg:province":"Ober\u00f6sterreich",
    "wof:name":"Evangelisches Pfarramt AB",
    "wof:placetype":"venue"
},
  "geometry": {"coordinates":[13.5393486023,47.9150695801],"type":"Point"}
}