{
  "type": "Feature",
  "properties": {
    "addr:full":"Hauptstr 13 Sattledt Ober\u00f6sterreich 4642",
    "addr:housenumber":"13",
    "addr:postcode":"4642",
    "addr:street":"Hauptstr",
    "iso:country":"AT",
    "sg:address":"Hauptstr 13",
    "sg:city":"Sattledt",
    "sg:orig_category":"Bierlokale-Pubs",
    "sg:phone":"+43 4372 448920",
    "sg:postcode":"4642",
    "sg:province":"Ober\u00f6sterreich",
    "wof:name":"Voralpenbr\u00e4u",
    "wof:placetype":"venue"
},
  "geometry": {"coordinates":[14.0543518066,48.0739135742],"type":"Point"}
}