{
  "type": "Feature",
  "properties": {
    "addr:full":"Egger Str 14 Ledenitzen K\u00e4rnten 9581",
    "addr:postcode":"9581",
    "addr:street":"Str 14;Kaernten",
    "iso:country":"AT",
    "sg:address":"Egger Str 14",
    "sg:city":"Ledenitzen",
    "sg:orig_category":"Pensionen / Privatzimmer",
    "sg:phone":"+43 4254 3128",
    "sg:postcode":"9581",
    "sg:province":"K\u00e4rnten",
    "wof:name":"Maier Lorenz",
    "wof:placetype":"venue"
},
  "geometry": {"coordinates":[13.9645576477,46.5663948059],"type":"Point"}
}