{
  "type": "Feature",
  "properties": {
    "iso:country":"AT",
    "sg:address":"Starkenbach 80",
    "sg:city":"Sch\u00f6nwies",
    "sg:classifiers":[
        {
            "category":"Manufacturing",
            "subcategory":"Furniture",
            "type":"Manufacturing & Wholesale Goods"
        }
    ],
    "sg:phone":"+43 5418 5353",
    "sg:postcode":"6491",
    "sg:province":"Tirol",
    "sg:tags":[
        "ornament",
        "carving"
    ],
    "sg:website":"ragglthurner.at",
    "wof:name":"Raggl - Thurner Kunsttischlerei GesmbH & Co KG",
    "wof:placetype":"venue"
},
  "geometry": {"coordinates":[10.673327446,47.2056732178],"type":"Point"}
}