{
  "type": "Feature",
  "properties": {
    "iso:country":"AT",
    "sg:address":"Nr 80",
    "sg:city":"Weitersfeld an der Mur",
    "sg:orig_category":"Gemeinden",
    "sg:phone":"+43 4334 7223060",
    "sg:postcode":"8473",
    "sg:province":"Steiermark",
    "wof:name":"Gemeinde Murfeld",
    "wof:placetype":"venue"
},
  "geometry": {"coordinates":[15.6967058182,46.7113113403],"type":"Point"}
}