{
  "type": "Feature",
  "properties": {
    "addr:full":"Nebingerstr 13 Linz Ober\u00f6sterreich 4020",
    "addr:housenumber":"13",
    "addr:postcode":"4020",
    "addr:street":"Nebingerstr",
    "iso:country":"AT",
    "sg:address":"Nebingerstr 13",
    "sg:city":"Linz",
    "sg:orig_category":"Speditionen",
    "sg:phone":"+43 732 6505450",
    "sg:postcode":"4020",
    "sg:province":"Ober\u00f6sterreich",
    "sg:website":"birkart.com",
    "wof:name":"BIRKART GLOBISTICS Austria GmbH",
    "wof:placetype":"venue"
},
  "geometry": {"coordinates":[14.331495285,48.2990722656],"type":"Point"}
}