{
  "type": "Feature",
  "properties": {
    "addr:full":"Nr 85 Straden Steiermark 8345",
    "addr:postcode":"8345",
    "addr:street":"Nr",
    "iso:country":"AT",
    "sg:address":"Nr 85",
    "sg:city":"Straden",
    "sg:orig_category":"Bars-Cafes",
    "sg:phone":"+43 4334 7375936",
    "sg:postcode":"8345",
    "sg:province":"Steiermark",
    "wof:name":"LAVA Cafe Bar",
    "wof:placetype":"venue"
},
  "geometry": {"coordinates":[15.8692350388,46.8074264526],"type":"Point"}
}