{
  "type": "Feature",
  "properties": {
    "addr:full":"Schwarzenbergstr 4 Wien Wien 1010",
    "addr:housenumber":"4",
    "addr:postcode":"1010",
    "addr:street":"Schwarzenbergstr",
    "iso:country":"AT",
    "sg:address":"Schwarzenbergstr 4",
    "sg:city":"Wien",
    "sg:orig_category":"Restaurants: Koreanisch",
    "sg:phone":"+43 1 5129983",
    "sg:postcode":"1010",
    "sg:province":"Wien",
    "wof:name":"Restaurant Senara",
    "wof:placetype":"venue"
},
  "geometry": {"coordinates":[16.3732299805,48.2030334473],"type":"Point"}
}