{
  "type": "Feature",
  "properties": {
    "addr:full":"Alter Ziegelweg 41 Tulln an der Donau Nieder\u00f6sterreich 3430",
    "addr:housenumber":"41",
    "addr:postcode":"3430",
    "addr:street":"Alter Ziegelweg",
    "iso:country":"AT",
    "sg:address":"Alter Ziegelweg 41",
    "sg:city":"Tulln an der Donau",
    "sg:orig_category":"Hauskrankenpflege / Heimhilfe",
    "sg:phone":"+43 2272 68944",
    "sg:postcode":"3430",
    "sg:province":"Nieder\u00f6sterreich",
    "wof:name":"Caritas Hauskrankenpflege Sozialstation Tulln",
    "wof:placetype":"venue"
},
  "geometry": {"coordinates":[16.0644207001,48.3232383728],"type":"Point"}
}