{
  "type": "Feature",
  "properties": {
    "addr:full":"Salzburger Str 27 Schwanenstadt Ober\u00f6sterreich 4690",
    "addr:housenumber":"27",
    "addr:postcode":"4690",
    "addr:street":"Salzburger Str",
    "iso:country":"AT",
    "sg:address":"Salzburger Str 27",
    "sg:city":"Schwanenstadt",
    "sg:orig_category":"Lebensmittel / Einzelhandel",
    "sg:phone":"+43 76736654",
    "sg:postcode":"4690",
    "sg:province":"Ober\u00f6sterreich",
    "wof:name":"SPAR \u00d6sterreichische Warenhandels-AG",
    "wof:placetype":"venue"
},
  "geometry": {"coordinates":[13.7674255371,48.0510520935],"type":"Point"}
}