{
  "type": "Feature",
  "properties": {
    "addr:full":"Neuhart Steiermark 8053",
    "addr:postcode":"8053",
    "iso:country":"AT",
    "sg:city":"Neuhart",
    "sg:orig_category":"Industrie, Fahrzeugbau",
    "sg:postcode":"8053",
    "sg:province":"Steiermark",
    "sg:website":"http://www.wpo.at",
    "wof:name":"Technologieorientierte Wirtschaftsdatenbank",
    "wof:placetype":"venue"
},
  "geometry": {"coordinates":[15.3950767517,47.0450592041],"type":"Point"}
}