{
  "type": "Feature",
  "properties": {
    "addr:full":"Alter Pl 23 Klagenfurt K\u00e4rnten 9020",
    "addr:housenumber":"23",
    "addr:postcode":"9020",
    "addr:street":"Alter Pl;Kaernten",
    "iso:country":"AT",
    "sg:address":"Alter Pl 23",
    "sg:city":"Klagenfurt",
    "sg:orig_category":"Juwelen, Gold- U Silberwaren / Einzelhandel",
    "sg:phone":"+43 463 511716",
    "sg:postcode":"9020",
    "sg:province":"K\u00e4rnten",
    "wof:name":"Schmucktruhe",
    "wof:placetype":"venue"
},
  "geometry": {"coordinates":[14.3087720871,46.6251831055],"type":"Point"}
}