{
  "type": "Feature",
  "properties": {
    "iso:country":"AT",
    "sg:address":"Steyrtalstr 32",
    "sg:city":"Neuzeug",
    "sg:orig_category":"Tischlereien",
    "sg:phone":"+43 7259 2438",
    "sg:postcode":"4523",
    "sg:province":"Ober\u00f6sterreich",
    "wof:name":"Wallner Armin Ing",
    "wof:placetype":"venue"
},
  "geometry": {"coordinates":[14.332818985,48.0459518433],"type":"Point"}
}