{
  "type": "Feature",
  "properties": {
    "addr:full":"Linzer Str 18 Enns Ober\u00f6sterreich 4470",
    "addr:housenumber":"18",
    "addr:postcode":"4470",
    "addr:street":"Linzer Str",
    "iso:country":"AT",
    "sg:address":"Linzer Str 18",
    "sg:city":"Enns",
    "sg:orig_category":"Textilwaren / Einzelhandel",
    "sg:phone":"+43 7223 84994",
    "sg:postcode":"4470",
    "sg:province":"Ober\u00f6sterreich",
    "wof:name":"TPS",
    "wof:placetype":"venue"
},
  "geometry": {"coordinates":[14.477314949,48.2145462036],"type":"Point"}
}