{
  "type": "Feature",
  "properties": {
    "addr:full":"Hauptstrasse 146 T Mailberg Nieder\u00f6sterreich 2024",
    "addr:housenumber":"146 t;2024",
    "addr:street":"Hauptstrasse;Mailberg Niederoesterreich",
    "iso:country":"AT",
    "sg:address":"Hauptstrasse 146 T",
    "sg:city":"Mailberg",
    "sg:classifiers":[
        {
            "category":"Transit Center",
            "subcategory":"Passenger",
            "type":"Transportation"
        }
    ],
    "sg:phone":"+43 2943 2269",
    "sg:postcode":"2024",
    "sg:province":"Nieder\u00f6sterreich",
    "sg:tags":[
        "rolling",
        "industry",
        "door",
        "doors",
        "sectional"
    ],
    "wof:name":"F\u00fcrnkranz Ges.m.b.H.",
    "wof:placetype":"venue"
},
  "geometry": {"coordinates":[16.1827259064,48.6727828979],"type":"Point"}
}