{
  "type": "Feature",
  "properties": {
    "iso:country":"AT",
    "sg:address":"Scheiblberg 25",
    "sg:city":"Rohrbach in Ober\u00f6sterreich",
    "sg:orig_category":"Handelsagenturen",
    "sg:phone":"+43 7289 6584",
    "sg:postcode":"4150",
    "sg:province":"Ober\u00f6sterreich",
    "wof:name":"Geretschl\u00e4ger Herbert",
    "wof:placetype":"venue"
},
  "geometry": {"coordinates":[13.9922561646,48.5636558533],"type":"Point"}
}