{
  "type": "Feature",
  "properties": {
    "addr:full":"Reicharten 612a Langen Vorarlberg 6932",
    "addr:housenumber":"612a",
    "addr:postcode":"6932",
    "addr:street":"Reicharten",
    "iso:country":"AT",
    "sg:address":"Reicharten 612a",
    "sg:city":"Langen",
    "sg:orig_category":"Fliesen U Platten",
    "sg:phone":"+43 4355 7520144",
    "sg:postcode":"6932",
    "sg:province":"Vorarlberg",
    "wof:name":"Steurer Peter",
    "wof:placetype":"venue"
},
  "geometry": {"coordinates":[9.8273859024,47.5082244873],"type":"Point"}
}