{
  "type": "Feature",
  "properties": {
    "iso:country":"AT",
    "sg:address":"St. Georgener Hauptstr 107",
    "sg:city":"St. Georgen am Steinfelde",
    "sg:orig_category":"\u00c3\u201erzte / F Allgemeinmedizin",
    "sg:phone":"+43 4327 42885200",
    "sg:postcode":"3151",
    "sg:province":"Nieder\u00f6sterreich",
    "wof:name":"Forghani Khashayar Dr",
    "wof:placetype":"venue"
},
  "geometry": {"coordinates":[15.6138010025,48.1416816711],"type":"Point"}
}