{
  "type": "Feature",
  "properties": {
    "addr:full":"Wiener Str 33 Horn Nieder\u00f6sterreich 3580",
    "addr:housenumber":"33",
    "addr:postcode":"3580",
    "addr:street":"Horn Niederoesterreich",
    "iso:country":"AT",
    "sg:address":"Wiener Str 33",
    "sg:city":"Horn",
    "sg:orig_category":"Aufsperrdienste",
    "sg:phone":"+43 2982 20841",
    "sg:postcode":"3580",
    "sg:province":"Nieder\u00f6sterreich",
    "wof:name":"Aufsperrdienst Solomka Wolfgang & Co OEG",
    "wof:placetype":"venue"
},
  "geometry": {"coordinates":[15.6610527039,48.6652412415],"type":"Point"}
}