{
  "type": "Feature",
  "properties": {
    "addr:full":"Kulmg 27 Wien Wien 1170",
    "addr:housenumber":"27",
    "addr:postcode":"1170",
    "addr:street":"Kulmg",
    "iso:country":"AT",
    "sg:address":"Kulmg 27",
    "sg:city":"Wien",
    "sg:orig_category":"Pelze U Pelzwaren",
    "sg:phone":"+43 4314 8651780",
    "sg:postcode":"1170",
    "sg:province":"Wien",
    "wof:name":"Kurzbauer Anton",
    "wof:placetype":"venue"
},
  "geometry": {"coordinates":[16.3219127655,48.2175178528],"type":"Point"}
}