{
  "type": "Feature",
  "properties": {
    "addr:full":"Hernalser Hauptstr 130 Wien Wien 1170",
    "addr:housenumber":"130",
    "addr:postcode":"1170",
    "addr:street":"Hernalser Hauptstr",
    "iso:country":"AT",
    "sg:address":"Hernalser Hauptstr 130",
    "sg:city":"Wien",
    "sg:orig_category":"Folien",
    "sg:phone":"+43 1 48632420",
    "sg:postcode":"1170",
    "sg:province":"Wien",
    "wof:name":"Karba Dipl-Ing GesmbH",
    "wof:placetype":"venue"
},
  "geometry": {"coordinates":[16.3227386475,48.2212944031],"type":"Point"}
}