{
  "type": "Feature",
  "properties": {
    "addr:full":"Brandst\u00e4tte 7-9 Wien Wien 1010",
    "addr:housenumber":"7-9",
    "addr:postcode":"1010",
    "addr:street":"Brandstaette",
    "iso:country":"AT",
    "sg:address":"Brandst\u00e4tte 7-9",
    "sg:city":"Wien",
    "sg:orig_category":"Boutiquen",
    "sg:phone":"+43 1 53344430",
    "sg:postcode":"1010",
    "sg:province":"Wien",
    "wof:name":"Mac's Bekleidungs HandelsgesmbH",
    "wof:placetype":"venue"
},
  "geometry": {"coordinates":[16.3715057373,48.2096786499],"type":"Point"}
}