{
  "type": "Feature",
  "properties": {
    "addr:full":"Hollandstr 10/3 Wien Wien 1020",
    "addr:housenumber":"10 / 3",
    "addr:postcode":"1020",
    "addr:street":"Hollandstr",
    "iso:country":"AT",
    "sg:address":"Hollandstr 10/3",
    "sg:city":"Wien",
    "sg:orig_category":"Brillen U -Fassungen / Erzeugung U Gro\u00c3\u0178handel",
    "sg:phone":"+43 4312 1699210",
    "sg:postcode":"1020",
    "sg:province":"Wien",
    "wof:name":"Beryll Eyewear",
    "wof:placetype":"venue"
},
  "geometry": {"coordinates":[16.3769416809,48.2155685425],"type":"Point"}
}