{
  "type": "Feature",
  "properties": {
    "addr:full":"Nr 142 Brand Vorarlberg 6708",
    "addr:postcode":"6708",
    "addr:street":"Nr;Brand",
    "iso:country":"AT",
    "sg:address":"Nr 142",
    "sg:city":"Brand",
    "sg:orig_category":"Pensionen / Privatzimmer",
    "sg:phone":"+43 5559 274",
    "sg:postcode":"6708",
    "sg:province":"Vorarlberg",
    "wof:name":"Schreiber Olga",
    "wof:placetype":"venue"
},
  "geometry": {"coordinates":[9.7432384491,47.1094207764],"type":"Point"}
}