{
  "type": "Feature",
  "properties": {
    "addr:full":"Fr\u00fchlingsstrasse 16 Lustenau Vorarlberg 6890",
    "addr:housenumber":"16",
    "addr:postcode":"6890",
    "addr:street":"Fruehlingsstrasse",
    "iso:country":"AT",
    "sg:address":"Fr\u00fchlingsstrasse 16",
    "sg:city":"Lustenau",
    "sg:classifiers":[
        {
            "category":"Train Station",
            "subcategory":"Light Rail",
            "type":"Transportation"
        }
    ],
    "sg:phone":"+43 5577 82497",
    "sg:postcode":"6890",
    "sg:province":"Vorarlberg",
    "sg:tags":[
        "basket",
        "lamp"
    ],
    "sg:website":"members.aon.at/korb-koenig",
    "wof:name":"Werner K\u00f6nig",
    "wof:placetype":"venue"
},
  "geometry": {"coordinates":[9.6590452194,47.4262237549],"type":"Point"}
}