{
  "type": "Feature",
  "properties": {
    "iso:country":"AT",
    "sg:address":"Weinbergg 49",
    "sg:city":"Wien",
    "sg:orig_category":"Spielwaren U Spiele",
    "sg:phone":"+43 1 3672407",
    "sg:postcode":"1190",
    "sg:province":"Wien",
    "wof:name":"Spielkistchen",
    "wof:placetype":"venue"
},
  "geometry": {"coordinates":[16.3339996338,48.2433738708],"type":"Point"}
}