{
  "type": "Feature",
  "properties": {
    "addr:full":"Franz-Klein-G 5/1st floor Wien Wien 1190",
    "addr:housenumber":"5 / 1st floor",
    "addr:postcode":"1190",
    "addr:street":"Franz-Klein-G",
    "iso:country":"AT",
    "sg:address":"Franz-Klein-G 5/1st floor",
    "sg:city":"Wien",
    "sg:classifiers":[
        {
            "category":"Professional",
            "subcategory":"Computer Services",
            "type":"Services"
        }
    ],
    "sg:phone":"+43 4313 6770400",
    "sg:postcode":"1190",
    "sg:province":"Wien",
    "sg:tags":[
        "software"
    ],
    "wof:name":"Baan Austria GmbH / SSA Global",
    "wof:placetype":"venue"
},
  "geometry": {"coordinates":[16.3493022919,48.2389793396],"type":"Point"}
}