{
  "type": "Feature",
  "properties": {
    "addr:full":"Murm\u00fchle 33 Judendorf-Stra\u00dfengel Steiermark 8111",
    "addr:housenumber":"33",
    "addr:postcode":"8111",
    "addr:street":"Murmuehle",
    "iso:country":"AT",
    "sg:address":"Murm\u00fchle 33",
    "sg:city":"Judendorf-Stra\u00dfengel",
    "sg:orig_category":"Garten- U Landschaftsgestaltung",
    "sg:phone":"+43 3124 520000",
    "sg:postcode":"8111",
    "sg:province":"Steiermark",
    "wof:name":"Herneth G\u00fcnther",
    "wof:placetype":"venue"
},
  "geometry": {"coordinates":[15.3350353241,47.1136360168],"type":"Point"}
}