{
  "type": "Feature",
  "properties": {
    "addr:full":"Raiffeisenstr 3 Deutschlandsberg Steiermark 8530",
    "addr:housenumber":"3",
    "addr:postcode":"8530",
    "addr:street":"Raiffeisenstr",
    "iso:country":"AT",
    "sg:address":"Raiffeisenstr 3",
    "sg:city":"Deutschlandsberg",
    "sg:orig_category":"Fahrschulen",
    "sg:phone":"+43 4334 6230500",
    "sg:postcode":"8530",
    "sg:province":"Steiermark",
    "wof:name":"Fahrschule Piccadilly",
    "wof:placetype":"venue"
},
  "geometry": {"coordinates":[15.2258281708,46.8195915222],"type":"Point"}
}