{
  "type": "Feature",
  "properties": {
    "addr:full":"Kehlegg 100 Dornbirn Vorarlberg 6850",
    "addr:housenumber":"100",
    "addr:postcode":"6850",
    "addr:street":"Kehlegg",
    "iso:country":"AT",
    "sg:address":"Kehlegg 100",
    "sg:city":"Dornbirn",
    "sg:orig_category":"Stickereien",
    "sg:phone":"+43 4355 72232680",
    "sg:postcode":"6850",
    "sg:province":"Vorarlberg",
    "wof:name":"Bartl Kurt GesmbH",
    "wof:placetype":"venue"
},
  "geometry": {"coordinates":[9.7785205841,47.3992805481],"type":"Point"}
}