{
  "type": "Feature",
  "properties": {
    "addr:full":"Hockegasse 87 Wien Wien 1180",
    "addr:housenumber":"87",
    "addr:postcode":"1180",
    "addr:street":"Hockegasse",
    "iso:country":"AT",
    "sg:address":"Hockegasse 87",
    "sg:city":"Wien",
    "sg:classifiers":[
        {
            "category":"Manufacturing",
            "subcategory":"Chemicals & Compounds",
            "type":"Manufacturing & Wholesale Goods"
        }
    ],
    "sg:phone":"+43 1 47915400",
    "sg:postcode":"1180",
    "sg:province":"Wien",
    "sg:tags":[
        "industrial"
    ],
    "wof:name":"Pompe Chemie Handelsges.m.b.H. & Co KG",
    "wof:placetype":"venue"
},
  "geometry": {"coordinates":[16.3104076385,48.2390441895],"type":"Point"}
}