{
  "type": "Feature",
  "properties": {
    "iso:country":"AT",
    "sg:address":"Kirchboden 155",
    "sg:city":"Wagrain",
    "sg:orig_category":"Pensionen / Privatzimmer",
    "sg:phone":"+43 6413 8321",
    "sg:postcode":"5602",
    "sg:province":"Salzburg",
    "wof:name":"Tauernblick",
    "wof:placetype":"venue"
},
  "geometry": {"coordinates":[13.302895546,47.3332595825],"type":"Point"}
}