{
  "type": "Feature",
  "properties": {
    "addr:full":"Emmerich Assmann-G 1 Leibnitz Steiermark 8430",
    "addr:housenumber":"1",
    "addr:postcode":"8430",
    "addr:street":"Assmann-G;Steiermark",
    "iso:country":"AT",
    "sg:address":"Emmerich Assmann-G 1",
    "sg:city":"Leibnitz",
    "sg:orig_category":"Non-Classified Establishments",
    "sg:phone":"+43 3452 82334",
    "sg:postcode":"8430",
    "sg:province":"Steiermark",
    "wof:name":"Evangelische Pfarrgemeinde",
    "wof:placetype":"venue"
},
  "geometry": {"coordinates":[15.5450296402,46.7789802551],"type":"Point"}
}