{
  "type": "Feature",
  "properties": {
    "iso:country":"AT",
    "sg:address":"Landstr 31",
    "sg:city":"Linz",
    "sg:classifiers":[
        {
            "category":"Restaurant",
            "type":"Food & Drink"
        }
    ],
    "sg:phone":"+43 4373 27746860",
    "sg:postcode":"4020",
    "sg:province":"Ober\u00f6sterreich",
    "wof:name":"Papa Joe's Grill Cantina Bar",
    "wof:placetype":"venue"
},
  "geometry": {"coordinates":[14.289978981,48.30210495],"type":"Point"}
}