{
  "type": "Feature",
  "properties": {
    "iso:country":"AT",
    "sg:address":"Industriezone 26",
    "sg:city":"Imst",
    "sg:orig_category":"Non-Classified Establishments",
    "sg:phone":"+43 4350 108",
    "sg:postcode":"6460",
    "sg:province":"Tirol",
    "wof:name":"ASFINAG Alpenstra\u00dfen GmbH - Autobahnmeisterei Imst",
    "wof:placetype":"venue"
},
  "geometry": {"coordinates":[10.737487793,47.2392234802],"type":"Point"}
}