{
  "type": "Feature",
  "properties": {
    "addr:full":"Josefspl 14 Baden Nieder\u00f6sterreich 2500",
    "addr:housenumber":"14",
    "addr:postcode":"2500",
    "addr:street":"Josefspl;Niederoesterreich",
    "iso:country":"AT",
    "sg:address":"Josefspl 14",
    "sg:city":"Baden",
    "sg:orig_category":"Tabaktrafiken",
    "sg:phone":"+43 2252 44105",
    "sg:postcode":"2500",
    "sg:province":"Nieder\u00f6sterreich",
    "wof:name":"Trafik am Josefsplatz - Maximilian Hager",
    "wof:placetype":"venue"
},
  "geometry": {"coordinates":[16.2333469391,48.0055656433],"type":"Point"}
}