{
  "type": "Feature",
  "properties": {
    "addr:full":"Neuhauser Str 32 Gnigl Salzburg 5023",
    "addr:housenumber":"32",
    "addr:postcode":"5023",
    "addr:street":"Str",
    "iso:country":"AT",
    "sg:address":"Neuhauser Str 32",
    "sg:city":"Gnigl",
    "sg:orig_category":"Orgel- U Harmoniumbau",
    "sg:phone":"+43 4366 26468790",
    "sg:postcode":"5023",
    "sg:province":"Salzburg",
    "sg:website":"mertel-orgelbau.at",
    "wof:name":"Mertel Fritz",
    "wof:placetype":"venue"
},
  "geometry": {"coordinates":[13.0723819733,47.8081474304],"type":"Point"}
}