{
  "type": "Feature",
  "properties": {
    "addr:full":"Eltendorfer Str 290 Kukmirn Burgenland 7543",
    "addr:housenumber":"290",
    "addr:postcode":"7543",
    "addr:street":"Str",
    "iso:country":"AT",
    "sg:address":"Eltendorfer Str 290",
    "sg:city":"Kukmirn",
    "sg:classifiers":[
        {
            "category":"Government",
            "subcategory":"Post Office",
            "type":"Public Place"
        }
    ],
    "sg:phone":"+43 4333 2832579",
    "sg:postcode":"7543",
    "sg:province":"Burgenland",
    "sg:tags":[
        "u",
        "-material",
        "dachdeckereibedarf"
    ],
    "wof:name":"Rezyrit Kunststoffverwertung GmbH",
    "wof:placetype":"venue"
},
  "geometry": {"coordinates":[16.2055358887,47.072227478],"type":"Point"}
}