{
  "type": "Feature",
  "properties": {
    "addr:full":"Nr 1 St. Stefan an der Gail K\u00e4rnten 9623",
    "addr:housenumber":"1",
    "addr:postcode":"9623",
    "addr:street":"Nr",
    "iso:country":"AT",
    "sg:address":"Nr 1",
    "sg:city":"St. Stefan an der Gail",
    "sg:orig_category":"Webdesign",
    "sg:phone":"+43 650 2400518",
    "sg:postcode":"9623",
    "sg:province":"K\u00e4rnten",
    "wof:name":"JFB - Web Design",
    "wof:placetype":"venue"
},
  "geometry": {"coordinates":[13.516960144,46.6192092896],"type":"Point"}
}