{
  "type": "Feature",
  "properties": {
    "iso:country":"AT",
    "sg:address":"33.Str 2",
    "sg:city":"Kematen an der Ybbs",
    "sg:orig_category":"Tischlereien",
    "sg:phone":"+43 4374 4824020",
    "sg:postcode":"3331",
    "sg:province":"Nieder\u00f6sterreich",
    "wof:name":"Wasinger Erwin Bio- u Massivholzm\u00f6bel Tischlerei",
    "wof:placetype":"venue"
},
  "geometry": {"coordinates":[14.7749147415,48.0357055664],"type":"Point"}
}