{
  "type": "Feature",
  "properties": {
    "addr:full":"Reucklstr 1/1/5 Hollabrunn Nieder\u00f6sterreich 2020",
    "addr:housenumber":"1 / 1 / 5",
    "addr:postcode":"2020",
    "addr:street":"Reucklstr",
    "iso:country":"AT",
    "sg:address":"Reucklstr 1/1/5",
    "sg:city":"Hollabrunn",
    "sg:orig_category":"Suchtberatung / Alkohol, Drogen, Zigaretten",
    "sg:phone":"+43 2952 2072516",
    "sg:postcode":"2020",
    "sg:province":"Nieder\u00f6sterreich",
    "wof:name":"Suchtberatung N\u00f6",
    "wof:placetype":"venue"
},
  "geometry": {"coordinates":[16.0783004761,48.5624580383],"type":"Point"}
}