{
  "type": "Feature",
  "properties": {
    "addr:full":"Nr 300 Golling an der Salzach Salzburg 5440",
    "addr:postcode":"5440",
    "addr:street":"Nr 300",
    "iso:country":"AT",
    "sg:address":"Nr 300",
    "sg:city":"Golling an der Salzach",
    "sg:orig_category":"Gummi U Gummiwaren",
    "sg:phone":"+43 4362 4478880",
    "sg:postcode":"5440",
    "sg:province":"Salzburg",
    "wof:name":"ATRA Aufbereitungsanlagen- u Transportmittelservice GesmbH",
    "wof:placetype":"venue"
},
  "geometry": {"coordinates":[166.9221496582,-0.5282999873],"type":"Point"}
}