{
  "type": "Feature",
  "properties": {
    "iso:country":"AT",
    "sg:city":"Feldkirchen in K\u00e4rnten",
    "sg:orig_category":"Feuerwehren",
    "sg:phone":"+43 4276 4243",
    "sg:postcode":"9560",
    "sg:province":"K\u00e4rnten",
    "wof:name":"Feuerwehr Tiffen",
    "wof:placetype":"venue"
},
  "geometry": {"coordinates":[14.058839798,46.7078399658],"type":"Point"}
}