{
  "type": "Feature",
  "properties": {
    "addr:full":"Nr 41 Wies Steiermark 8551",
    "addr:postcode":"8551",
    "addr:street":"Nr",
    "iso:country":"AT",
    "sg:address":"Nr 41",
    "sg:city":"Wies",
    "sg:orig_category":"Pensionen / Privatzimmer",
    "sg:phone":"+43 3466 42103",
    "sg:postcode":"8551",
    "sg:province":"Steiermark",
    "wof:name":"Kraus Josef",
    "wof:placetype":"venue"
},
  "geometry": {"coordinates":[15.2706108093,46.7187728882],"type":"Point"}
}