{
  "type": "Feature",
  "properties": {
    "addr:full":"Hauptstr 6 Oetz Tirol 6433",
    "addr:housenumber":"6",
    "addr:postcode":"6433",
    "addr:street":"Hauptstr;Tirol",
    "iso:country":"AT",
    "sg:address":"Hauptstr 6",
    "sg:city":"Oetz",
    "sg:orig_category":"Pensionen / Privatzimmer",
    "sg:phone":"+43 5252 6825",
    "sg:postcode":"6433",
    "sg:province":"Tirol",
    "wof:name":"Alte M\u00fchle Pension",
    "wof:placetype":"venue"
},
  "geometry": {"coordinates":[10.8902053833,47.2050933838],"type":"Point"}
}