{
  "type": "Feature",
  "properties": {
    "iso:country":"AT",
    "sg:address":"Hauptstr 1",
    "sg:city":"F\u00fcrstenfeld",
    "sg:orig_category":"Tabaktrafiken",
    "sg:phone":"+43 3382 52286",
    "sg:postcode":"8280",
    "sg:province":"Steiermark",
    "wof:name":"Zirbisegger Walter",
    "wof:placetype":"venue"
},
  "geometry": {"coordinates":[9.1736345291,47.655216217],"type":"Point"}
}