{
  "type": "Feature",
  "properties": {
    "addr:full":"Nr 246 Engelhartstetten Nieder\u00f6sterreich 2292",
    "addr:postcode":"2292",
    "addr:street":"Nr;Niederoesterreich",
    "iso:country":"AT",
    "sg:address":"Nr 246",
    "sg:city":"Engelhartstetten",
    "sg:orig_category":"\u00c3\u201erzte / F Allgemeinmedizin",
    "sg:phone":"+43 2214 22910",
    "sg:postcode":"2292",
    "sg:province":"Nieder\u00f6sterreich",
    "wof:name":"Fragner Arnold Dr",
    "wof:placetype":"venue"
},
  "geometry": {"coordinates":[16.8847999573,48.1817092896],"type":"Point"}
}