{
  "type": "Feature",
  "properties": {
    "iso:country":"AT",
    "sg:address":"Hauptstr 24",
    "sg:city":"Ladendorf",
    "sg:orig_category":"Banken U Sparkassen",
    "sg:phone":"+43 4325 752283",
    "sg:postcode":"2126",
    "sg:province":"Nieder\u00f6sterreich",
    "wof:name":"Raiffeisenbank Mistelbach regGenmbH",
    "wof:placetype":"venue"
},
  "geometry": {"coordinates":[16.4960403442,48.5343513489],"type":"Point"}
}