{
  "type": "Feature",
  "properties": {
    "iso:country":"AT",
    "sg:address":"Ahorn 27",
    "sg:city":"Bad Ischl",
    "sg:orig_category":"Appartements / Ferienwohnungen",
    "sg:phone":"+43 6132 28748",
    "sg:postcode":"4820",
    "sg:province":"Ober\u00f6sterreich",
    "wof:name":"Ferienhof Sieglbauer Fam Stadlmann",
    "wof:placetype":"venue"
},
  "geometry": {"coordinates":[13.6095113754,47.7124099731],"type":"Point"}
}