{
  "type": "Feature",
  "properties": {
    "iso:country":"AT",
    "sg:address":"Hauptstr 51",
    "sg:city":"Markt St. Martin",
    "sg:orig_category":"Selbsthilfegruppen",
    "sg:phone":"+43 4367 63987638",
    "sg:postcode":"7341",
    "sg:province":"Burgenland",
    "wof:name":"CIA Cochlea Implantat Austria Bgld N\u00f6S\u00fcd",
    "wof:placetype":"venue"
},
  "geometry": {"coordinates":[16.4283771515,47.5642318726],"type":"Point"}
}