{
  "type": "Feature",
  "properties": {
    "addr:full":"Hauptpl 14 St. Michael im Burgenland Burgenland 7535",
    "addr:housenumber":"14",
    "addr:postcode":"7535",
    "addr:street":"Hauptpl",
    "iso:country":"AT",
    "sg:address":"Hauptpl 14",
    "sg:city":"St. Michael im Burgenland",
    "sg:orig_category":"Non-Classified Establishments",
    "sg:phone":"+43 4333 2725151",
    "sg:postcode":"7535",
    "sg:province":"Burgenland",
    "wof:name":"Torzentrum Mario Kremsner",
    "wof:placetype":"venue"
},
  "geometry": {"coordinates":[16.2694511414,47.127117157],"type":"Point"}
}