{
  "type": "Feature",
  "properties": {
    "addr:full":"Gudrunstr 141 Wien Wien 1100",
    "addr:housenumber":"141",
    "addr:postcode":"1100",
    "iso:country":"AT",
    "sg:address":"Gudrunstr 141",
    "sg:city":"Wien",
    "sg:orig_category":"Papier- U Schreibwaren / Einzelhandel",
    "sg:phone":"+43 4318 773900",
    "sg:postcode":"1100",
    "sg:province":"Wien",
    "wof:name":"Herlitz GmbH",
    "wof:placetype":"venue"
},
  "geometry": {"coordinates":[16.3775672913,48.1778450012],"type":"Point"}
}