{
  "type": "Feature",
  "properties": {
    "addr:full":"Landstr 14 Hard Vorarlberg 6971",
    "addr:housenumber":"14",
    "addr:postcode":"6971",
    "addr:street":"Landstr",
    "iso:country":"AT",
    "sg:address":"Landstr 14",
    "sg:city":"Hard",
    "sg:orig_category":"Bankomat-Standorte",
    "sg:phone":"+43 5574 68560",
    "sg:postcode":"6971",
    "sg:province":"Vorarlberg",
    "wof:name":"Bankomat d Raiffeisenbank am Bodensee",
    "wof:placetype":"venue"
},
  "geometry": {"coordinates":[9.6884126663,47.4884262085],"type":"Point"}
}