{
  "type": "Feature",
  "properties": {
    "addr:full":"Nr 5 Sonntag Vorarlberg 6731",
    "addr:postcode":"6731",
    "addr:street":"Nr;Sonntag",
    "iso:country":"AT",
    "sg:address":"Nr 5",
    "sg:city":"Sonntag",
    "sg:orig_category":"Pensionen / Privatzimmer",
    "sg:phone":"+43 5554 55910",
    "sg:postcode":"6731",
    "sg:province":"Vorarlberg",
    "wof:name":"Cafe Pension z J\u00e4ger",
    "wof:placetype":"venue"
},
  "geometry": {"coordinates":[9.9032316208,47.2396812439],"type":"Point"}
}