{
  "type": "Feature",
  "properties": {
    "iso:country":"AT",
    "sg:address":"Andorfer Landstr",
    "sg:city":"Utzenaich",
    "sg:orig_category":"Abfallentsorgung U -Verwertung",
    "sg:phone":"+43 7751 6262",
    "sg:postcode":"4972",
    "sg:province":"Ober\u00f6sterreich",
    "wof:name":"Altstoffsammelzentrum Utzenaich",
    "wof:placetype":"venue"
},
  "geometry": {"coordinates":[13.4963989258,48.2986602783],"type":"Point"}
}