{
  "type": "Feature",
  "properties": {
    "iso:country":"AT",
    "sg:address":"Kaarstr 25",
    "sg:city":"Linz",
    "sg:orig_category":"Brillen U -Fassungen / Erzeugung U Gro\u00c3\u0178handel",
    "sg:phone":"+43 4373 2731460",
    "sg:postcode":"4040",
    "sg:province":"Ober\u00f6sterreich",
    "wof:name":"frames & more Inh Mayr Oliver",
    "wof:placetype":"venue"
},
  "geometry": {"coordinates":[14.2790184021,48.3113174438],"type":"Point"}
}