{
  "type": "Feature",
  "properties": {
    "iso:country":"AT",
    "sg:address":"Imbergstr 17/2",
    "sg:city":"Salzburg",
    "sg:orig_category":"Bauunternehmen",
    "sg:phone":"+43 662 87234560",
    "sg:postcode":"5020",
    "sg:province":"Salzburg",
    "wof:name":"Heitkamp BaugesmbH",
    "wof:placetype":"venue"
},
  "geometry": {"coordinates":[13.0480365753,47.8008346558],"type":"Point"}
}