{
  "type": "Feature",
  "properties": {
    "addr:full":"Sparkassenpl 2 Bludenz Vorarlberg 6700",
    "addr:housenumber":"2",
    "addr:postcode":"6700",
    "addr:street":"Sparkassenpl",
    "iso:country":"AT",
    "sg:address":"Sparkassenpl 2",
    "sg:city":"Bludenz",
    "sg:orig_category":"Polizei U Gendarmerie",
    "sg:phone":"+43 4359 1338100",
    "sg:postcode":"6700",
    "sg:province":"Vorarlberg",
    "wof:name":"Gendarmerie Bludenz",
    "wof:placetype":"venue"
},
  "geometry": {"coordinates":[9.8210020065,47.1555786133],"type":"Point"}
}