{
  "type": "Feature",
  "properties": {
    "addr:full":"Nr 40c Krakaudorf Steiermark 8854",
    "addr:housenumber":"40c",
    "addr:postcode":"8854",
    "addr:street":"Nr",
    "iso:country":"AT",
    "sg:address":"Nr 40c",
    "sg:city":"Krakaudorf",
    "sg:orig_category":"Elektroinstallationsunternehmen",
    "sg:phone":"+43 3535 8677",
    "sg:postcode":"8854",
    "sg:province":"Steiermark",
    "wof:name":"Moser Hubert - TV Technik",
    "wof:placetype":"venue"
},
  "geometry": {"coordinates":[13.9644861221,47.1889724731],"type":"Point"}
}