{
  "type": "Feature",
  "properties": {
    "addr:full":"Marschallg 32 Graz Steiermark 8020",
    "addr:housenumber":"32",
    "addr:postcode":"8020",
    "addr:street":"Marschallg",
    "iso:country":"AT",
    "sg:address":"Marschallg 32",
    "sg:city":"Graz",
    "sg:orig_category":"Non-Classified Establishments",
    "sg:phone":"+43 316 713443",
    "sg:postcode":"8020",
    "sg:province":"Steiermark",
    "sg:website":"gypser.at",
    "wof:name":"Gypser Gernot Dr",
    "wof:placetype":"venue"
},
  "geometry": {"coordinates":[15.4308996201,47.0732307434],"type":"Point"}
}