{
  "type": "Feature",
  "properties": {
    "iso:country":"AT",
    "sg:address":"Wiener Str 1",
    "sg:city":"Gaweinstal",
    "sg:orig_category":"Banken U Sparkassen",
    "sg:phone":"+43 4325 742187",
    "sg:postcode":"2191",
    "sg:province":"Nieder\u00f6sterreich",
    "wof:name":"Raiffeisenbank im Weinviertel-Hohenruppersdorf regGenmbH",
    "wof:placetype":"venue"
},
  "geometry": {"coordinates":[16.5891456604,48.4753990173],"type":"Point"}
}