{
  "type": "Feature",
  "properties": {
    "addr:full":"Hauptpl 3 Neusiedl an der Zaya Nieder\u00f6sterreich 2183",
    "addr:housenumber":"3",
    "addr:postcode":"2183",
    "addr:street":"Hauptpl;Niederoesterreich",
    "iso:country":"AT",
    "sg:address":"Hauptpl 3",
    "sg:city":"Neusiedl an der Zaya",
    "sg:orig_category":"Banken U Sparkassen",
    "sg:phone":"+43 4325 33894200",
    "sg:postcode":"2183",
    "sg:province":"Nieder\u00f6sterreich",
    "wof:name":"Raiffeisenkasse Neusiedl/Zaya regGenmbH",
    "wof:placetype":"venue"
},
  "geometry": {"coordinates":[16.7873535156,48.6019592285],"type":"Point"}
}