{
  "type": "Feature",
  "properties": {
    "addr:full":"Sperken 1 Klam Ober\u00f6sterreich 4352",
    "addr:housenumber":"1",
    "addr:postcode":"4352",
    "addr:street":"Sperken",
    "iso:country":"AT",
    "sg:address":"Sperken 1",
    "sg:city":"Klam",
    "sg:orig_category":"Museen / Ausstellungen",
    "sg:phone":"+43 7269 72170",
    "sg:postcode":"4352",
    "sg:province":"Ober\u00f6sterreich",
    "wof:name":"Burgmuseum Clam",
    "wof:placetype":"venue"
},
  "geometry": {"coordinates":[14.772228241,48.2226371765],"type":"Point"}
}