{
  "type": "Feature",
  "properties": {
    "iso:country":"AT",
    "sg:address":"Fritz-Matzner-Weg 5",
    "sg:city":"Kalsdorf",
    "sg:orig_category":"Hauptschulen",
    "sg:phone":"+43 3135 525500",
    "sg:postcode":"8401",
    "sg:province":"Steiermark",
    "wof:name":"Hauptschule",
    "wof:placetype":"venue"
},
  "geometry": {"coordinates":[15.4787082672,46.9620437622],"type":"Point"}
}