{
  "type": "Feature",
  "properties": {
    "addr:full":"Klagenfurter Str 39a Wolfsberg K\u00e4rnten 9400",
    "addr:housenumber":"39a;kaernten",
    "addr:postcode":"9400",
    "addr:street":"Str",
    "iso:country":"AT",
    "sg:address":"Klagenfurter Str 39a",
    "sg:city":"Wolfsberg",
    "sg:orig_category":"Lebensmittel / Einzelhandel",
    "sg:phone":"+43 4352 35034",
    "sg:postcode":"9400",
    "sg:province":"K\u00e4rnten",
    "wof:name":"Billa AG",
    "wof:placetype":"venue"
},
  "geometry": {"coordinates":[14.8390226364,46.8232917786],"type":"Point"}
}