{
  "type": "Feature",
  "properties": {
    "addr:full":"Rosentaler Str 88 Klagenfurt K\u00e4rnten 9020",
    "addr:housenumber":"88",
    "addr:postcode":"9020",
    "addr:street":"Str;Kaernten",
    "iso:country":"AT",
    "sg:address":"Rosentaler Str 88",
    "sg:city":"Klagenfurt",
    "sg:orig_category":"Banken U Sparkassen",
    "sg:phone":"+43 5 010030814",
    "sg:postcode":"9020",
    "sg:province":"K\u00e4rnten",
    "wof:name":"K\u00e4rntner Sparkasse AG",
    "wof:placetype":"venue"
},
  "geometry": {"coordinates":[14.3011341095,46.6135063171],"type":"Point"}
}