{
  "type": "Feature",
  "properties": {
    "addr:full":"Firmianstr 37 Salzburg Salzburg 5020",
    "addr:housenumber":"37",
    "addr:postcode":"5020",
    "addr:street":"Firmianstr;Salzburg",
    "iso:country":"AT",
    "sg:address":"Firmianstr 37",
    "sg:city":"Salzburg",
    "sg:orig_category":"Filmproduktionen",
    "sg:phone":"+43 662 825015",
    "sg:postcode":"5020",
    "sg:province":"Salzburg",
    "wof:name":"Killer Johannes",
    "wof:placetype":"venue"
},
  "geometry": {"coordinates":[13.0263977051,47.7846641541],"type":"Point"}
}