{
  "type": "Feature",
  "properties": {
    "addr:full":"Syringg 1 Wien Wien 1170",
    "addr:housenumber":"1",
    "addr:postcode":"1170",
    "addr:street":"Syringg",
    "iso:country":"AT",
    "sg:address":"Syringg 1",
    "sg:city":"Wien",
    "sg:orig_category":"Tabaktrafiken",
    "sg:phone":"+43 1 4021525",
    "sg:postcode":"1170",
    "sg:province":"Wien",
    "wof:name":"Krischa Martin",
    "wof:placetype":"venue"
},
  "geometry": {"coordinates":[16.3308048248,48.2193107605],"type":"Point"}
}