{
  "type": "Feature",
  "properties": {
    "addr:full":"Karl-Heinrich-Waggerl-Str 20 Wagrain Salzburg 5602",
    "addr:housenumber":"20",
    "addr:postcode":"5602",
    "addr:street":"Karl-Heinrich-Waggerl-Str;Salzburg",
    "iso:country":"AT",
    "sg:address":"Karl-Heinrich-Waggerl-Str 20",
    "sg:city":"Wagrain",
    "sg:orig_category":"Volksschulen",
    "sg:phone":"+43 4364 138258",
    "sg:postcode":"5602",
    "sg:province":"Salzburg",
    "wof:name":"Volksschule Joseph Mohr",
    "wof:placetype":"venue"
},
  "geometry": {"coordinates":[13.3029193878,47.333896637],"type":"Point"}
}