{
  "type": "Feature",
  "properties": {
    "addr:full":"Klosterneuburger Str 19 Wien Wien 1200",
    "addr:postcode":"1200",
    "addr:street":"Str 19",
    "iso:country":"AT",
    "sg:address":"Klosterneuburger Str 19",
    "sg:city":"Wien",
    "sg:orig_category":"Tabaktrafiken",
    "sg:phone":"+43 1 3306875",
    "sg:postcode":"1200",
    "sg:province":"Wien",
    "wof:name":"Kohn Robert",
    "wof:placetype":"venue"
},
  "geometry": {"coordinates":[16.3680553436,48.2287940979],"type":"Point"}
}