{
  "type": "Feature",
  "properties": {
    "addr:full":"Wiener Str 116 Gumpoldskirchen Nieder\u00f6sterreich 2352",
    "addr:housenumber":"116",
    "addr:postcode":"2352",
    "iso:country":"AT",
    "sg:address":"Wiener Str 116",
    "sg:city":"Gumpoldskirchen",
    "sg:orig_category":"Friseure U Frisiersalons",
    "sg:phone":"+43 4322 5263366",
    "sg:postcode":"2352",
    "sg:province":"Nieder\u00f6sterreich",
    "wof:name":"Frisiersalon Herta Schwertf\u00fchrer",
    "wof:placetype":"venue"
},
  "geometry": {"coordinates":[16.2859477997,48.0411911011],"type":"Point"}
}