{
  "type": "Feature",
  "properties": {
    "addr:full":"Estepl 2 Wien Wien 1030",
    "addr:housenumber":"2",
    "addr:postcode":"1030",
    "addr:street":"Estepl",
    "iso:country":"AT",
    "sg:address":"Estepl 2",
    "sg:city":"Wien",
    "sg:orig_category":"Arbeitsvermittlung",
    "sg:phone":"+43 1 87871",
    "sg:postcode":"1030",
    "sg:province":"Wien",
    "wof:name":"Arbeitsmarktservice Wien AMS - Esteplatz f d Bezirke 1/3/11",
    "wof:placetype":"venue"
},
  "geometry": {"coordinates":[16.390586853,48.2053756714],"type":"Point"}
}