{
  "type": "Feature",
  "properties": {
    "iso:country":"AT",
    "sg:address":"Gemeindepl 2",
    "sg:city":"Pichl",
    "sg:orig_category":"Lebensmittel / Einzelhandel",
    "sg:phone":"+43 7247 8766",
    "sg:postcode":"4632",
    "sg:province":"Ober\u00f6sterreich",
    "wof:name":"Adeg Markt Hartl",
    "wof:placetype":"venue"
},
  "geometry": {"coordinates":[13.8998212814,48.1848182678],"type":"Point"}
}