{
  "type": "Feature",
  "properties": {
    "addr:full":"Hauptstrasse 27 Prinzersdorf Nieder\u00f6sterreich 3385",
    "addr:housenumber":"27",
    "addr:postcode":"3385",
    "addr:street":"Hauptstrasse",
    "iso:country":"AT",
    "sg:address":"Hauptstrasse 27",
    "sg:city":"Prinzersdorf",
    "sg:orig_category":"ChildrenS Furniture",
    "sg:phone":"+43 2749 26050",
    "sg:postcode":"3385",
    "sg:province":"Nieder\u00f6sterreich",
    "sg:website":"krumboeck.at",
    "wof:name":"KRUMB\u00d6CK GMBH",
    "wof:placetype":"venue"
},
  "geometry": {"coordinates":[15.5011911392,48.1929016113],"type":"Point"}
}