{
  "type": "Feature",
  "properties": {
    "iso:country":"AT",
    "sg:address":"Flo\u00dflendstr 18",
    "sg:city":"Graz",
    "sg:orig_category":"Hauskrankenpflege / Heimhilfe",
    "sg:phone":"+43 316 698405",
    "sg:postcode":"8020",
    "sg:province":"Steiermark",
    "wof:name":"compass Sozial- und Gesundheitsverein Mobilebetreuung",
    "wof:placetype":"venue"
},
  "geometry": {"coordinates":[15.4240369797,47.0849609375],"type":"Point"}
}