{
  "type": "Feature",
  "properties": {
    "iso:country":"AT",
    "sg:address":"Hauptpl 12-13",
    "sg:city":"Wallsee",
    "sg:orig_category":"Lebensmittel / Einzelhandel",
    "sg:phone":"+43 7433 2212",
    "sg:postcode":"3313",
    "sg:province":"Nieder\u00f6sterreich",
    "wof:name":"Kopplinger Martina",
    "wof:placetype":"venue"
},
  "geometry": {"coordinates":[14.7188100815,48.1655082703],"type":"Point"}
}