{
  "type": "Feature",
  "properties": {
    "addr:full":"Hauptstr 40 Rohrbach Burgenland 7222",
    "addr:housenumber":"40",
    "addr:postcode":"7222",
    "addr:street":"Hauptstr",
    "iso:country":"AT",
    "sg:address":"Hauptstr 40",
    "sg:city":"Rohrbach",
    "sg:orig_category":"Baumeister",
    "sg:phone":"+43 4326 2663016",
    "sg:postcode":"7222",
    "sg:province":"Burgenland",
    "wof:name":"Horning Hans Ing",
    "wof:placetype":"venue"
},
  "geometry": {"coordinates":[16.4249515533,47.7090682983],"type":"Point"}
}