{
  "type": "Feature",
  "properties": {
    "iso:country":"AT",
    "sg:address":"B\u00e4ckerg 1",
    "sg:city":"Enns",
    "sg:orig_category":"Bauunternehmen",
    "sg:phone":"+43 7223 86665",
    "sg:postcode":"4470",
    "sg:province":"Ober\u00f6sterreich",
    "wof:name":"Team Bau GmbH",
    "wof:placetype":"venue"
},
  "geometry": {"coordinates":[14.4775104523,48.2143287659],"type":"Point"}
}