{
  "type": "Feature",
  "properties": {
    "addr:full":"Meinhardstr 6 Innsbruck Tirol 6020",
    "addr:housenumber":"6",
    "addr:postcode":"6020",
    "addr:street":"Meinhardstr;Tirol",
    "iso:country":"AT",
    "sg:address":"Meinhardstr 6",
    "sg:city":"Innsbruck",
    "sg:orig_category":"Waren Aller Art",
    "sg:phone":"+43 4365 07772614",
    "sg:postcode":"6020",
    "sg:province":"Tirol",
    "wof:name":"NA SO WAS 75-Cent-Shop",
    "wof:placetype":"venue"
},
  "geometry": {"coordinates":[11.398859024,47.2662887573],"type":"Point"}
}