{
  "type": "Feature",
  "properties": {
    "addr:full":"Hauptpl 8 P\u00f6llau Steiermark 8225",
    "addr:housenumber":"8",
    "addr:postcode":"8225",
    "addr:street":"Hauptpl",
    "iso:country":"AT",
    "sg:address":"Hauptpl 8",
    "sg:city":"P\u00f6llau",
    "sg:orig_category":"Banken U Sparkassen",
    "sg:phone":"+43 4333 3522430",
    "sg:postcode":"8225",
    "sg:province":"Steiermark",
    "wof:name":"Bankomat d Raiffeisenbank Wies regGenmbH",
    "wof:placetype":"venue"
},
  "geometry": {"coordinates":[15.8337945938,47.301990509],"type":"Point"}
}