{
  "type": "Feature",
  "properties": {
    "iso:country":"AT",
    "sg:address":"Steinbachmauer 34",
    "sg:city":"G\u00f6stling an der Ybbs",
    "sg:classifiers":[
        {
            "category":"Manufacturing",
            "subcategory":"Signs",
            "type":"Manufacturing & Wholesale Goods"
        }
    ],
    "sg:phone":"+43 7484 5080",
    "sg:postcode":"3345",
    "sg:province":"Nieder\u00f6sterreich",
    "sg:tags":[
        "display"
    ],
    "wof:name":"Seitzberger GmbH",
    "wof:placetype":"venue"
},
  "geometry": {"coordinates":[14.7514295578,47.9857406616],"type":"Point"}
}