{
  "type": "Feature",
  "properties": {
    "addr:full":"Schubertstr 46 Linz Ober\u00f6sterreich 4020",
    "addr:housenumber":"46",
    "addr:postcode":"4020",
    "addr:street":"Schubertstr",
    "iso:country":"AT",
    "sg:address":"Schubertstr 46",
    "sg:city":"Linz",
    "sg:orig_category":"Alternativtherapie",
    "sg:phone":"+43 732 605849",
    "sg:postcode":"4020",
    "sg:province":"Ober\u00f6sterreich",
    "wof:name":"Institut Alexanderbewegung Dr Martina S\u00fcss",
    "wof:placetype":"venue"
},
  "geometry": {"coordinates":[14.2973356247,48.296546936],"type":"Point"}
}