{
  "type": "Feature",
  "properties": {
    "addr:full":"Pernerstorfergasse 35 Wien Wien 1100",
    "addr:housenumber":"35",
    "addr:postcode":"1100",
    "addr:street":"Pernerstorfergasse",
    "iso:country":"AT",
    "sg:address":"Pernerstorfergasse 35",
    "sg:city":"Wien",
    "sg:classifiers":[
        {
            "category":"Retail",
            "subcategory":"Laundry & Dry Cleaning",
            "type":"Services"
        }
    ],
    "sg:phone":"+43 1 6047166",
    "sg:postcode":"1100",
    "sg:province":"Wien",
    "sg:tags":[
        "oil",
        "fragrance"
    ],
    "wof:name":"Thomas Sperl GmbH",
    "wof:placetype":"venue"
},
  "geometry": {"coordinates":[16.3742637634,48.1764564514],"type":"Point"}
}