{
  "type": "Feature",
  "properties": {
    "addr:full":"St.-Martin-Sdlg 24 Wilhelmsburg an der Traisen Nieder\u00f6sterreich 3150",
    "addr:housenumber":"24",
    "addr:postcode":"3150",
    "addr:street":"St.-Martin-Sdlg;An",
    "iso:country":"AT",
    "sg:address":"St.-Martin-Sdlg 24",
    "sg:city":"Wilhelmsburg an der Traisen",
    "sg:orig_category":"Montagen U Montagetechnik",
    "sg:phone":"+43 4327 4620820",
    "sg:postcode":"3150",
    "sg:province":"Nieder\u00f6sterreich",
    "wof:name":"MBS BaugesmbH",
    "wof:placetype":"venue"
},
  "geometry": {"coordinates":[15.6061897278,48.1053657532],"type":"Point"}
}