{
  "type": "Feature",
  "properties": {
    "iso:country":"AT",
    "sg:address":"Alser Str 44",
    "sg:city":"Wien",
    "sg:orig_category":"Elektroinstallationsmaterial",
    "sg:phone":"+43 1 40515970",
    "sg:postcode":"1090",
    "sg:province":"Wien",
    "wof:name":"EGE - Einkaufsgenossenschaft \u00f6sterr Elektrizit\u00e4tswerke regGenmbH",
    "wof:placetype":"venue"
},
  "geometry": {"coordinates":[16.3440647125,48.215385437],"type":"Point"}
}