{
  "type": "Feature",
  "properties": {
    "addr:full":"Nr 3 St. Oswald Steiermark 8113",
    "addr:housenumber":"3",
    "addr:postcode":"8113",
    "addr:street":"Nr",
    "iso:country":"AT",
    "sg:address":"Nr 3",
    "sg:city":"St. Oswald",
    "sg:orig_category":"Heurigen / Buschenschank",
    "sg:phone":"+43 4331 232280",
    "sg:postcode":"8113",
    "sg:province":"Steiermark",
    "wof:name":"Strimbauer",
    "wof:placetype":"venue"
},
  "geometry": {"coordinates":[15.2193155289,47.1025161743],"type":"Point"}
}