{
  "type": "Feature",
  "properties": {
    "addr:full":"Kulstrunkstr 24 Aigen Salzburg 5026",
    "addr:housenumber":"24",
    "addr:postcode":"5026",
    "addr:street":"Kulstrunkstr;Salzburg",
    "iso:country":"AT",
    "sg:address":"Kulstrunkstr 24",
    "sg:city":"Aigen",
    "sg:classifiers":[
        {
            "category":"Organizations",
            "subcategory":"Community Association",
            "type":"Services"
        }
    ],
    "sg:phone":"+43 662 6492930",
    "sg:postcode":"5026",
    "sg:province":"Salzburg",
    "sg:tags":[
        "relation",
        "public"
    ],
    "wof:name":"Kommunikationsservice Mag Seyr OEG",
    "wof:placetype":"venue"
},
  "geometry": {"coordinates":[13.0819339752,47.7967529297],"type":"Point"}
}