{
  "type": "Feature",
  "properties": {
    "iso:country":"AT",
    "sg:address":"Hauptpl 12",
    "sg:city":"Waidhofen an der Thaya",
    "sg:orig_category":"Freizeit- U Sportbekleidung",
    "sg:phone":"+43 4328 4253740",
    "sg:postcode":"3830",
    "sg:province":"Nieder\u00f6sterreich",
    "wof:name":"M 8 Jeans & Sportswear",
    "wof:placetype":"venue"
},
  "geometry": {"coordinates":[15.2860746384,48.8143882751],"type":"Point"}
}