{
  "type": "Feature",
  "properties": {
    "addr:full":"Springwiese 5 Eferding Ober\u00f6sterreich 4070",
    "addr:housenumber":"5",
    "addr:postcode":"4070",
    "addr:street":"Springwiese",
    "iso:country":"AT",
    "sg:address":"Springwiese 5",
    "sg:city":"Eferding",
    "sg:orig_category":"Tabaktrafiken",
    "sg:phone":"+43 7272 4351",
    "sg:postcode":"4070",
    "sg:province":"Ober\u00f6sterreich",
    "wof:name":"Kagerer Gabriele",
    "wof:placetype":"venue"
},
  "geometry": {"coordinates":[14.0212364197,48.3127174377],"type":"Point"}
}