{
  "type": "Feature",
  "properties": {
    "iso:country":"AT",
    "sg:address":"Obere Hauptstr 107",
    "sg:city":"Riedlingsdorf",
    "sg:orig_category":"Transportunternehmen",
    "sg:phone":"+43 3357 424170",
    "sg:postcode":"7422",
    "sg:province":"Burgenland",
    "wof:name":"Huber Warenhandel- und Transport GmbH",
    "wof:placetype":"venue"
},
  "geometry": {"coordinates":[16.1306743622,47.3537368774],"type":"Point"}
}