{
  "type": "Feature",
  "properties": {
    "addr:full":"Harder Str 76 Lauterach Vorarlberg 6923",
    "addr:housenumber":"76",
    "addr:postcode":"6923",
    "addr:street":"Str",
    "iso:country":"AT",
    "sg:address":"Harder Str 76",
    "sg:city":"Lauterach",
    "sg:orig_category":"Metallwaren / Einzelhandel",
    "sg:phone":"+43 5574 70291",
    "sg:postcode":"6923",
    "sg:province":"Vorarlberg",
    "wof:name":"H\u00e4uselmann Metall",
    "wof:placetype":"venue"
},
  "geometry": {"coordinates":[9.7159833908,47.4843101501],"type":"Point"}
}