{
  "type": "Feature",
  "properties": {
    "addr:full":"Alma-Rose-G 2 Wien Wien 1100",
    "addr:housenumber":"2",
    "addr:postcode":"1100",
    "addr:street":"Alma-Rose-G",
    "iso:country":"AT",
    "sg:address":"Alma-Rose-G 2",
    "sg:city":"Wien",
    "sg:orig_category":"Banken U Sparkassen",
    "sg:phone":"+43 4316 8833270",
    "sg:postcode":"1100",
    "sg:province":"Wien",
    "wof:name":"Bankomat d Raiffeisenlandesbank N\u00f6-Wien AG",
    "wof:placetype":"venue"
},
  "geometry": {"coordinates":[16.3922996521,48.145942688],"type":"Point"}
}