{
  "type": "Feature",
  "properties": {
    "addr:full":"Schattwald 20 Schattwald Tirol 6677",
    "addr:housenumber":"20",
    "addr:postcode":"6677",
    "addr:street":"Schattwald;Tirol",
    "iso:country":"AT",
    "sg:address":"Schattwald 20",
    "sg:city":"Schattwald",
    "sg:classifiers":[
        {
            "category":"Manufacturing",
            "subcategory":"Wood Products",
            "type":"Manufacturing & Wholesale Goods"
        }
    ],
    "sg:phone":"+43 5675 6626",
    "sg:postcode":"6677",
    "sg:province":"Tirol",
    "sg:tags":[
        "gate",
        "made",
        "door"
    ],
    "wof:name":"Alexander M\u00fcller",
    "wof:placetype":"venue"
},
  "geometry": {"coordinates":[10.4631347656,47.5122451782],"type":"Point"}
}