{
  "type": "Feature",
  "properties": {
    "iso:country":"AT",
    "sg:address":"Rathausstr 17",
    "sg:city":"Ebenfurth",
    "sg:orig_category":"Rettungsdienste",
    "sg:phone":"+43 2624 52244",
    "sg:postcode":"2490",
    "sg:province":"Nieder\u00f6sterreich",
    "wof:name":"Rotes Kreuz \u00f6sterr Bezirksstelle Ebenfurth",
    "wof:placetype":"venue"
},
  "geometry": {"coordinates":[16.3738307953,47.8778762817],"type":"Point"}
}