{
  "type": "Feature",
  "properties": {
    "iso:country":"AT",
    "sg:address":"Ottakringer Str 77",
    "sg:city":"Wien",
    "sg:orig_category":"Bastelbedarf",
    "sg:phone":"+43 4314 864277",
    "sg:postcode":"1160",
    "sg:province":"Wien",
    "wof:name":"Suske Helmut",
    "wof:placetype":"venue"
},
  "geometry": {"coordinates":[16.3274860382,48.2133598328],"type":"Point"}
}