{
  "type": "Feature",
  "properties": {
    "addr:full":"Promenade 23 Linz Ober\u00f6sterreich 4020",
    "addr:housenumber":"23",
    "addr:postcode":"4020",
    "addr:street":"Promenade",
    "iso:country":"AT",
    "sg:address":"Promenade 23",
    "sg:city":"Linz",
    "sg:orig_category":"Zeitungen U Zeitschriften / Vertrieb",
    "sg:phone":"+43 732 78050",
    "sg:postcode":"4020",
    "sg:province":"Ober\u00f6sterreich",
    "wof:name":"O\u00d6Nachrichten",
    "wof:placetype":"venue"
},
  "geometry": {"coordinates":[14.2853212357,48.3032875061],"type":"Point"}
}