{
  "type": "Feature",
  "properties": {
    "addr:full":"Unterauer Str 13 Ybbs an der Donau Nieder\u00f6sterreich 3370",
    "addr:postcode":"3370",
    "addr:street":"Str 13",
    "iso:country":"AT",
    "sg:address":"Unterauer Str 13",
    "sg:city":"Ybbs an der Donau",
    "sg:orig_category":"Farben U Lacke / Einzelhandel",
    "sg:phone":"+43 4374 1255220",
    "sg:postcode":"3370",
    "sg:province":"Nieder\u00f6sterreich",
    "wof:name":"Farben-Grim - ADLER Farbenmeister",
    "wof:placetype":"venue"
},
  "geometry": {"coordinates":[15.0815467834,48.1683006287],"type":"Point"}
}