{
  "type": "Feature",
  "properties": {
    "addr:full":"Nr 13 Wei\u00dfensee K\u00e4rnten 9762",
    "addr:postcode":"9762",
    "addr:street":"Nr 13;Kaernten",
    "iso:country":"AT",
    "sg:address":"Nr 13",
    "sg:city":"Wei\u00dfensee",
    "sg:orig_category":"Pensionen / Privatzimmer",
    "sg:phone":"+43 4713 23610",
    "sg:postcode":"9762",
    "sg:province":"K\u00e4rnten",
    "wof:name":"Haus Binter",
    "wof:placetype":"venue"
},
  "geometry": {"coordinates":[13.2917070389,46.717880249],"type":"Point"}
}