{
  "type": "Feature",
  "properties": {
    "iso:country":"AT",
    "sg:address":"Erdbergstr. 191-193 ",
    "sg:city":"Wien",
    "sg:classifiers":[
        {
            "category":"Autos & Motor Vehicles",
            "subcategory":"Automobile Sales",
            "type":"Retail Goods"
        }
    ],
    "sg:phone":"+43 4317 4008",
    "sg:postcode":"1030",
    "sg:province":"Wien",
    "sg:tags":[
        "industrial"
    ],
    "wof:name":"WOLFGANG DENZEL KRAFTFAHRZEUGE AG",
    "wof:placetype":"venue"
},
  "geometry": {"coordinates":[16.4258041382,48.185760498],"type":"Point"}
}