{
  "type": "Feature",
  "properties": {
    "addr:full":"Bichlbach Tirol 6621",
    "addr:postcode":"6621",
    "addr:street":"Tirol",
    "iso:country":"AT",
    "sg:city":"Bichlbach",
    "sg:orig_category":"Bergbahnen",
    "sg:phone":"+43 5674 5350",
    "sg:postcode":"6621",
    "sg:province":"Tirol",
    "wof:name":"Bichlbacher Bergbahn GesmbH & Co KG",
    "wof:placetype":"venue"
},
  "geometry": {"coordinates":[10.7911348343,47.4200019836],"type":"Point"}
}