{
  "type": "Feature",
  "properties": {
    "addr:full":"D\u00fcrnbachstr 8 Ternberg Ober\u00f6sterreich 4452",
    "addr:housenumber":"8",
    "addr:postcode":"4452",
    "addr:street":"Duernbachstr",
    "iso:country":"AT",
    "sg:address":"D\u00fcrnbachstr 8",
    "sg:city":"Ternberg",
    "sg:orig_category":"Spenglereien",
    "sg:phone":"+43 4372 5620012",
    "sg:postcode":"4452",
    "sg:province":"Ober\u00f6sterreich",
    "wof:name":"Traunfellner Martin",
    "wof:placetype":"venue"
},
  "geometry": {"coordinates":[14.357000351,47.9458198547],"type":"Point"}
}