{
  "type": "Feature",
  "properties": {
    "addr:full":"Sch\u00f6nbichlweg 16 St. Johann in Tirol Tirol 6380",
    "addr:housenumber":"16",
    "addr:postcode":"6380",
    "addr:street":"Schoenbichlweg;Tirol",
    "iso:country":"AT",
    "sg:address":"Sch\u00f6nbichlweg 16",
    "sg:city":"St. Johann in Tirol",
    "sg:classifiers":[
        {
            "category":"Communications",
            "subcategory":"Film & Video Production",
            "type":"Services"
        }
    ],
    "sg:phone":"+43 5352 65577",
    "sg:postcode":"6380",
    "sg:province":"Tirol",
    "sg:tags":[
        "multimedia"
    ],
    "wof:name":"HTV Media Production GmbH",
    "wof:placetype":"venue"
},
  "geometry": {"coordinates":[12.4163236618,47.524559021],"type":"Point"}
}