{
  "type": "Feature",
  "properties": {
    "addr:full":"Wilhelminenstr 60 Wien Wien 1160",
    "addr:housenumber":"60",
    "addr:postcode":"1160",
    "addr:street":"Wilhelminenstr",
    "iso:country":"AT",
    "sg:address":"Wilhelminenstr 60",
    "sg:city":"Wien",
    "sg:orig_category":"Tonstudios",
    "sg:phone":"+43 1 5976950",
    "sg:postcode":"1160",
    "sg:province":"Wien",
    "wof:name":"More Music",
    "wof:placetype":"venue"
},
  "geometry": {"coordinates":[16.3130092621,48.2171325684],"type":"Point"}
}