{
  "type": "Feature",
  "properties": {
    "addr:full":"Riedg 19 Innsbruck Tirol 6020",
    "addr:housenumber":"19",
    "addr:postcode":"6020",
    "addr:street":"Riedg;Tirol",
    "iso:country":"AT",
    "sg:address":"Riedg 19",
    "sg:city":"Innsbruck",
    "sg:orig_category":"Ingenieurkonsulenten / Zivilingenieure",
    "sg:phone":"+43 512 286267",
    "sg:postcode":"6020",
    "sg:province":"Tirol",
    "wof:name":"Sporschill Karl Dipl-Ing",
    "wof:placetype":"venue"
},
  "geometry": {"coordinates":[11.3913040161,47.2679977417],"type":"Point"}
}