{
  "type": "Feature",
  "properties": {
    "addr:full":"Natterer Str 4 Mutters Tirol 6162",
    "addr:housenumber":"4",
    "addr:postcode":"6162",
    "addr:street":"Natterer Str;Tirol",
    "iso:country":"AT",
    "sg:address":"Natterer Str 4",
    "sg:city":"Mutters",
    "sg:orig_category":"Fleischhauereien",
    "sg:phone":"+43 512 548426",
    "sg:postcode":"6162",
    "sg:province":"Tirol",
    "wof:name":"Fritz Hermann",
    "wof:placetype":"venue"
},
  "geometry": {"coordinates":[11.3767280579,47.2296867371],"type":"Point"}
}