{
  "type": "Feature",
  "properties": {
    "addr:full":"Schulg 616 Schladming Steiermark 8970",
    "addr:housenumber":"616",
    "addr:postcode":"8970",
    "iso:country":"AT",
    "sg:address":"Schulg 616",
    "sg:city":"Schladming",
    "sg:classifiers":[
        {
            "category":"Taxi",
            "type":"Transportation"
        }
    ],
    "sg:phone":"+43 4336 87222220",
    "sg:postcode":"8970",
    "sg:province":"Steiermark",
    "sg:tags":[
        "personentransporte",
        "u"
    ],
    "wof:name":"Taxi Maxi",
    "wof:placetype":"venue"
},
  "geometry": {"coordinates":[13.6871089935,47.3925628662],"type":"Point"}
}