{
  "type": "Feature",
  "properties": {
    "addr:full":"Rainer Str 13 Wels Ober\u00f6sterreich 4600",
    "addr:housenumber":"13",
    "addr:postcode":"4600",
    "addr:street":"Oberoesterreich",
    "iso:country":"AT",
    "sg:address":"Rainer Str 13",
    "sg:city":"Wels",
    "sg:orig_category":"Banken U Sparkassen",
    "sg:phone":"+43 7242 4950",
    "sg:postcode":"4600",
    "sg:province":"Ober\u00f6sterreich",
    "wof:name":"Welser Volksbank regGenmbH",
    "wof:placetype":"venue"
},
  "geometry": {"coordinates":[14.0213813782,48.1621856689],"type":"Point"}
}