{
  "type": "Feature",
  "properties": {
    "iso:country":"AT",
    "sg:address":"Gf\u00f6llnerwald 26",
    "sg:city":"Prambachkirchen",
    "sg:orig_category":"Non-Classified Establishments",
    "sg:phone":"+43 7277 6555",
    "sg:postcode":"4731",
    "sg:province":"Ober\u00f6sterreich",
    "wof:name":"Franziskanische Gemeinschaft",
    "wof:placetype":"venue"
},
  "geometry": {"coordinates":[13.8909654617,48.3147888184],"type":"Point"}
}