{
  "type": "Feature",
  "properties": {
    "addr:full":"Kreuzpl 22 Bad Ischl Ober\u00f6sterreich 4820",
    "addr:housenumber":"22",
    "addr:postcode":"4820",
    "addr:street":"Kreuzpl",
    "iso:country":"AT",
    "sg:address":"Kreuzpl 22",
    "sg:city":"Bad Ischl",
    "sg:orig_category":"Friseure U Frisiersalons",
    "sg:phone":"+43 4361 3223654",
    "sg:postcode":"4820",
    "sg:province":"Ober\u00f6sterreich",
    "wof:name":"Haut & Haar Gmeiner Inh Birgit Gmeiner",
    "wof:placetype":"venue"
},
  "geometry": {"coordinates":[13.6209917068,47.712928772],"type":"Point"}
}