{
  "type": "Feature",
  "properties": {
    "iso:country":"AT",
    "sg:address":"Wiestalstr 10",
    "sg:city":"Oberalm",
    "sg:orig_category":"Steinmetzbetriebe",
    "sg:phone":"+43 6245 835040",
    "sg:postcode":"5411",
    "sg:province":"Salzburg",
    "wof:name":"Marmor Industrie Kiefer GesmbH",
    "wof:placetype":"venue"
},
  "geometry": {"coordinates":[13.127913475,47.7192192078],"type":"Point"}
}