{
  "type": "Feature",
  "properties": {
    "addr:full":"Firmiang 41 Wien Wien 1130",
    "addr:housenumber":"41",
    "addr:postcode":"1130",
    "addr:street":"Firmiang",
    "iso:country":"AT",
    "sg:address":"Firmiang 41",
    "sg:city":"Wien",
    "sg:orig_category":"Unternehmensberatung",
    "sg:phone":"+43 1 8793090",
    "sg:postcode":"1130",
    "sg:province":"Wien",
    "wof:name":"Jilg Herbert Beratung & Training GesmbH",
    "wof:placetype":"venue"
},
  "geometry": {"coordinates":[16.2681980133,48.1909255981],"type":"Point"}
}