{
  "type": "Feature",
  "properties": {
    "addr:full":"Hauptstr 72 Sinabelkirchen Steiermark 8261",
    "addr:housenumber":"72",
    "addr:postcode":"8261",
    "addr:street":"Hauptstr",
    "iso:country":"AT",
    "sg:address":"Hauptstr 72",
    "sg:city":"Sinabelkirchen",
    "sg:orig_category":"Friseure U Frisiersalons",
    "sg:phone":"+43 3118 2065",
    "sg:postcode":"8261",
    "sg:province":"Steiermark",
    "wof:name":"Fris\u00f6rsalon Le Coiffeur - Monika Grasser",
    "wof:placetype":"venue"
},
  "geometry": {"coordinates":[15.8313550949,47.1006507874],"type":"Point"}
}