{
  "type": "Feature",
  "properties": {
    "addr:full":"Klitschg 8-10/Stg A Wien Wien 1130",
    "addr:housenumber":"8-10 / stg a",
    "addr:postcode":"1130",
    "iso:country":"AT",
    "sg:address":"Klitschg 8-10/Stg A",
    "sg:city":"Wien",
    "sg:orig_category":"Beteiligungen U Finanzierungen",
    "sg:phone":"+43 4318 047256",
    "sg:postcode":"1130",
    "sg:province":"Wien",
    "wof:name":"Industriefinanzierungs- u ExportberatungsgesmbH",
    "wof:placetype":"venue"
},
  "geometry": {"coordinates":[16.3013801575,48.18592453],"type":"Point"}
}