{
  "type": "Feature",
  "properties": {
    "iso:country":"AT",
    "sg:address":"K\u00e4rntner Str 9",
    "sg:city":"Wien",
    "sg:orig_category":"Papier- U Schreibwaren / Einzelhandel",
    "sg:phone":"+43 4315 1236780",
    "sg:postcode":"1010",
    "sg:province":"Wien",
    "wof:name":"Theyer & Hardtmuth",
    "wof:placetype":"venue"
},
  "geometry": {"coordinates":[16.3718757629,48.2020454407],"type":"Point"}
}