{
  "type": "Feature",
  "properties": {
    "iso:country":"AT",
    "sg:address":"Vivenotg 51",
    "sg:city":"Wien",
    "sg:orig_category":"Chemisch-Technische Produkte",
    "sg:phone":"+43 664 2137934",
    "sg:postcode":"1120",
    "sg:province":"Wien",
    "wof:name":"Kondor Josef",
    "wof:placetype":"venue"
},
  "geometry": {"coordinates":[16.3316936493,48.1764335632],"type":"Point"}
}