{
  "type": "Feature",
  "properties": {
    "addr:full":"Schmiedweg 2 Altm\u00fcnster Ober\u00f6sterreich 4813",
    "addr:housenumber":"2",
    "addr:postcode":"4813",
    "addr:street":"Schmiedweg;Oberoesterreich",
    "iso:country":"AT",
    "sg:address":"Schmiedweg 2",
    "sg:city":"Altm\u00fcnster",
    "sg:classifiers":[
        {
            "category":"Organizations",
            "subcategory":"Labor Organization",
            "type":"Services"
        }
    ],
    "sg:phone":"+43 761289703",
    "sg:postcode":"4813",
    "sg:province":"Ober\u00f6sterreich",
    "sg:tags":[
        "on-site",
        "waste-water",
        "treatment",
        "system"
    ],
    "wof:name":"P\u00f6llhuber KG Stahlbau-Tankanlagen",
    "wof:placetype":"venue"
},
  "geometry": {"coordinates":[13.761507988,47.8964729309],"type":"Point"}
}