{
  "type": "Feature",
  "properties": {
    "addr:full":"Benjowskig 24 Wien Wien 1220",
    "addr:housenumber":"24",
    "addr:postcode":"1220",
    "addr:street":"Benjowskig",
    "iso:country":"AT",
    "sg:address":"Benjowskig 24",
    "sg:city":"Wien",
    "sg:orig_category":"Unterhaltungselektronik / Erzeugung U Gro\u00c3\u0178handel",
    "sg:phone":"+43 1 2800526",
    "sg:postcode":"1220",
    "sg:province":"Wien",
    "sg:website":"www.stello.at",
    "wof:name":"Stellovsky Manfred",
    "wof:placetype":"venue"
},
  "geometry": {"coordinates":[16.4861602783,48.2157707214],"type":"Point"}
}