{
  "type": "Feature",
  "properties": {
    "iso:country":"AT",
    "sg:address":"Hauptstr 455",
    "sg:city":"Mayrhofen",
    "sg:orig_category":"Handarbeiten",
    "sg:phone":"+43 5285 62790",
    "sg:postcode":"6290",
    "sg:province":"Tirol",
    "wof:name":"Feix Roger",
    "wof:placetype":"venue"
},
  "geometry": {"coordinates":[11.862206459,47.1645927429],"type":"Point"}
}