{
  "type": "Feature",
  "properties": {
    "addr:full":"Spitalg 17a Wien Wien 1090",
    "addr:housenumber":"17a",
    "addr:postcode":"1090",
    "addr:street":"Spitalg",
    "iso:country":"AT",
    "sg:address":"Spitalg 17a",
    "sg:city":"Wien",
    "sg:classifiers":[
        {
            "category":"Shopping",
            "subcategory":"Thrift Store",
            "type":"Retail Goods"
        }
    ],
    "sg:phone":"+43 4314 095220",
    "sg:postcode":"1090",
    "sg:province":"Wien",
    "sg:tags":[
        "second-hand-shops"
    ],
    "wof:name":"VHBI Volkshilfe Besch\u00e4ftigungsinitiativen - VOLKSHILFE BOX",
    "wof:placetype":"venue"
},
  "geometry": {"coordinates":[16.351474762,48.2234115601],"type":"Point"}
}