{
  "type": "Feature",
  "properties": {
    "iso:country":"AT",
    "sg:address":"Erdbergstr. 202",
    "sg:city":"Wien",
    "sg:classifiers":[
        {
            "category":"Building & Trades",
            "subcategory":"Construction",
            "type":"Services"
        }
    ],
    "sg:phone":"+43 4317 9090",
    "sg:postcode":"1030",
    "sg:province":"Wien",
    "sg:tags":[
        "work",
        "public"
    ],
    "wof:name":"WIENER LINIEN GES.MBH & CO KG",
    "wof:placetype":"venue"
},
  "geometry": {"coordinates":[16.4153442383,48.1901702881],"type":"Point"}
}