{
  "type": "Feature",
  "properties": {
    "addr:full":"Seezeile 22 Rust Burgenland 7071",
    "addr:housenumber":"22",
    "addr:postcode":"7071",
    "addr:street":"Seezeile",
    "iso:country":"AT",
    "sg:address":"Seezeile 22",
    "sg:city":"Rust",
    "sg:orig_category":"Weinstuben",
    "sg:phone":"+43 2685 6869",
    "sg:postcode":"7071",
    "sg:province":"Burgenland",
    "wof:name":"Weind\u00f6rfl Urbanihof",
    "wof:placetype":"venue"
},
  "geometry": {"coordinates":[16.6769733429,47.799861908],"type":"Point"}
}