{
  "type": "Feature",
  "properties": {
    "addr:full":"Kampl Gewerbezone 5 Neustift im Stubaital Tirol 6167",
    "addr:housenumber":"5",
    "addr:postcode":"6167",
    "addr:street":"Gewerbezone;Tirol",
    "iso:country":"AT",
    "sg:address":"Kampl Gewerbezone 5",
    "sg:city":"Neustift im Stubaital",
    "sg:orig_category":"Holzbau",
    "sg:phone":"+43 4352 262444",
    "sg:postcode":"6167",
    "sg:province":"Tirol",
    "wof:name":"Pfister Johann",
    "wof:placetype":"venue"
},
  "geometry": {"coordinates":[11.3396043777,47.1297645569],"type":"Point"}
}