{
  "type": "Feature",
  "properties": {
    "addr:full":"Bruck Hainburger Str 12 Schwechat Nieder\u00f6sterreich 2320",
    "addr:postcode":"2320",
    "addr:street":"Str 12 Schwechat Niederoesterreich",
    "iso:country":"AT",
    "sg:address":"Bruck Hainburger Str 12",
    "sg:city":"Schwechat",
    "sg:orig_category":"Autohandel",
    "sg:phone":"+43 1 7067961",
    "sg:postcode":"2320",
    "sg:province":"Nieder\u00f6sterreich",
    "wof:name":"AUTOHANSA Dr Johann Schuster",
    "wof:placetype":"venue"
},
  "geometry": {"coordinates":[16.4816665649,48.1404266357],"type":"Point"}
}