{
  "type": "Feature",
  "properties": {
    "addr:full":"Dorf 139 S\u00f6ll Tirol 6306",
    "addr:housenumber":"139",
    "addr:postcode":"6306",
    "addr:street":"Dorf;Tirol",
    "iso:country":"AT",
    "sg:address":"Dorf 139",
    "sg:city":"S\u00f6ll",
    "sg:classifiers":[
        {
            "category":"Travel",
            "subcategory":"Hotels & Motels",
            "type":"Entertainment"
        }
    ],
    "sg:phone":"+43 5333 5306",
    "sg:postcode":"6306",
    "sg:province":"Tirol",
    "wof:name":"Hotel Sch\u00f6nblick",
    "wof:placetype":"venue"
},
  "geometry": {"coordinates":[-73.28117370610001,42.2773971558],"type":"Point"}
}