{
  "type": "Feature",
  "properties": {
    "iso:country":"AT",
    "sg:address":"Waschanger 40",
    "sg:city":"Gm\u00fcnd",
    "sg:orig_category":"Lebensmittel / Einzelhandel",
    "sg:phone":"+43 4732 33930",
    "sg:postcode":"9853",
    "sg:province":"K\u00e4rnten",
    "wof:name":"SPAR \u00f6sterreichische Warenhandels-AG",
    "wof:placetype":"venue"
},
  "geometry": {"coordinates":[13.5388965607,46.9073905945],"type":"Point"}
}