{
  "type": "Feature",
  "properties": {
    "addr:full":"Hauptstr 67 St. Andr\u00e4 am Zicksee Burgenland 7161",
    "addr:housenumber":"67",
    "addr:postcode":"7161",
    "addr:street":"Hauptstr",
    "iso:country":"AT",
    "sg:address":"Hauptstr 67",
    "sg:city":"St. Andr\u00e4 am Zicksee",
    "sg:orig_category":"Fleischhauereien",
    "sg:phone":"+43 2176 2252",
    "sg:postcode":"7161",
    "sg:province":"Burgenland",
    "wof:name":"Gasthaus Seywerth",
    "wof:placetype":"venue"
},
  "geometry": {"coordinates":[16.9447669983,47.7850151062],"type":"Point"}
}