{
  "type": "Feature",
  "properties": {
    "addr:full":"Nr 5 G\u00f6stling an der Ybbs Nieder\u00f6sterreich 3345",
    "addr:postcode":"3345",
    "addr:street":"Nr;An Der Ybbs",
    "iso:country":"AT",
    "sg:address":"Nr 5",
    "sg:city":"G\u00f6stling an der Ybbs",
    "sg:orig_category":"Pensionen / Privatzimmer",
    "sg:phone":"+43 7484 2422",
    "sg:postcode":"3345",
    "sg:province":"Nieder\u00f6sterreich",
    "wof:name":"Zettel Monika",
    "wof:placetype":"venue"
},
  "geometry": {"coordinates":[11.992184639,47.9920768738],"type":"Point"}
}