{
  "type": "Feature",
  "properties": {
    "addr:full":"Michael Koch-Str 1 Mattersburg Burgenland 7210",
    "addr:housenumber":"1",
    "addr:postcode":"7210",
    "iso:country":"AT",
    "sg:address":"Michael Koch-Str 1",
    "sg:city":"Mattersburg",
    "sg:classifiers":[
        {
            "category":"Home & Garden",
            "subcategory":"Building Materials",
            "type":"Retail Goods"
        }
    ],
    "sg:phone":"+43 2626 622900",
    "sg:postcode":"7210",
    "sg:province":"Burgenland",
    "sg:tags":[
        "baustoffe",
        "-material",
        "u"
    ],
    "wof:name":"Koch Michael GesmbH",
    "wof:placetype":"venue"
},
  "geometry": {"coordinates":[16.3970546722,47.7378807068],"type":"Point"}
}