{
  "type": "Feature",
  "properties": {
    "addr:full":"Laaer Str 79 Korneuburg Nieder\u00f6sterreich 2100",
    "addr:postcode":"2100",
    "addr:street":"Str 79",
    "iso:country":"AT",
    "sg:address":"Laaer Str 79",
    "sg:city":"Korneuburg",
    "sg:orig_category":"Banken U Sparkassen",
    "sg:phone":"+43 4322 6263390",
    "sg:postcode":"2100",
    "sg:province":"Nieder\u00f6sterreich",
    "wof:name":"Raiffeisenbank Korneuburg regGenmbH",
    "wof:placetype":"venue"
},
  "geometry": {"coordinates":[16.340139389,48.3502616882],"type":"Point"}
}