{
  "type": "Feature",
  "properties": {
    "addr:full":"Schubertgasse 27 St. Christophen Nieder\u00f6sterreich 3051",
    "addr:housenumber":"27",
    "addr:postcode":"3051",
    "addr:street":"Schubertgasse",
    "iso:country":"AT",
    "sg:address":"Schubertgasse 27",
    "sg:city":"St. Christophen",
    "sg:classifiers":[
        {
            "category":"Home & Garden",
            "subcategory":"Building Materials",
            "type":"Retail Goods"
        }
    ],
    "sg:phone":"+43 2772 54227",
    "sg:postcode":"3051",
    "sg:province":"Nieder\u00f6sterreich",
    "sg:tags":[
        "gravel",
        "crushed"
    ],
    "wof:name":"Sturzeis-Transport GesmbH",
    "wof:placetype":"venue"
},
  "geometry": {"coordinates":[15.8855752945,48.176574707],"type":"Point"}
}