{
  "type": "Feature",
  "properties": {
    "iso:country":"AT",
    "sg:address":"Landstra\u00dfer Hauptstr 117",
    "sg:city":"Wien",
    "sg:classifiers":[
        {
            "category":"Restaurant",
            "type":"Food & Drink"
        }
    ],
    "sg:phone":"+43 1 7123712",
    "sg:postcode":"1030",
    "sg:province":"Wien",
    "wof:name":"Schuh Josef",
    "wof:placetype":"venue"
},
  "geometry": {"coordinates":[16.3963661194,48.1962738037],"type":"Point"}
}