{
  "type": "Feature",
  "properties": {
    "addr:full":"Untere Hauptstr 11 Weiden am See Burgenland 7121",
    "addr:housenumber":"11",
    "addr:postcode":"7121",
    "addr:street":"Untere Hauptstr",
    "iso:country":"AT",
    "sg:address":"Untere Hauptstr 11",
    "sg:city":"Weiden am See",
    "sg:orig_category":"Musikgruppen",
    "sg:phone":"+43 2167 7328",
    "sg:postcode":"7121",
    "sg:province":"Burgenland",
    "wof:name":"Fuhrmanntrio",
    "wof:placetype":"venue"
},
  "geometry": {"coordinates":[16.8700447083,47.9251747131],"type":"Point"}
}