{
  "type": "Feature",
  "properties": {
    "addr:full":"Heinrich-Heine-Str 31 Graz Steiermark 8020",
    "addr:housenumber":"31",
    "addr:postcode":"8020",
    "addr:street":"Heinrich-Heine-Str",
    "iso:country":"AT",
    "sg:address":"Heinrich-Heine-Str 31",
    "sg:city":"Graz",
    "sg:orig_category":"Handelsagenturen",
    "sg:phone":"+43 316 583965",
    "sg:postcode":"8020",
    "sg:province":"Steiermark",
    "wof:name":"Hammer Therese",
    "wof:placetype":"venue"
},
  "geometry": {"coordinates":[15.4047727585,47.0669212341],"type":"Point"}
}