{
  "type": "Feature",
  "properties": {
    "addr:full":"Wulzendorfstr 94 Wien Wien 1220",
    "addr:housenumber":"94",
    "addr:postcode":"1220",
    "addr:street":"Wulzendorfstr",
    "iso:country":"AT",
    "sg:address":"Wulzendorfstr 94",
    "sg:city":"Wien",
    "sg:classifiers":[
        {
            "category":"Taxi",
            "type":"Transportation"
        }
    ],
    "sg:phone":"+43 4369 917131313",
    "sg:postcode":"1220",
    "sg:province":"Wien",
    "sg:tags":[
        "personentransporte",
        "u"
    ],
    "sg:website":"airporttaxi-kolar.at",
    "wof:name":"Airporttaxi Kolar Tomas",
    "wof:placetype":"venue"
},
  "geometry": {"coordinates":[16.4753513336,48.2131156921],"type":"Point"}
}