{
  "type": "Feature",
  "properties": {
    "addr:full":"Kircheng 7 Bruck an der Leitha Nieder\u00f6sterreich 2460",
    "addr:housenumber":"7",
    "addr:postcode":"2460",
    "addr:street":"Kircheng",
    "iso:country":"AT",
    "sg:address":"Kircheng 7",
    "sg:city":"Bruck an der Leitha",
    "sg:orig_category":"Tabaktrafiken",
    "sg:phone":"+43 2162 66110",
    "sg:postcode":"2460",
    "sg:province":"Nieder\u00f6sterreich",
    "wof:name":"Holzer Michaela",
    "wof:placetype":"venue"
},
  "geometry": {"coordinates":[16.7783794403,48.0239181519],"type":"Point"}
}