{
  "type": "Feature",
  "properties": {
    "iso:country":"AT",
    "sg:address":"Garteng 1",
    "sg:city":"Dra\u00dfmarkt",
    "sg:orig_category":"Tischlereien",
    "sg:phone":"+43 2617 2258",
    "sg:postcode":"7372",
    "sg:province":"Burgenland",
    "wof:name":"Fruhmann Leopold",
    "wof:placetype":"venue"
},
  "geometry": {"coordinates":[16.3436355591,47.5088005066],"type":"Point"}
}