{
  "type": "Feature",
  "properties": {
    "addr:full":"Wilhelminenstr 59 Wien Wien 1160",
    "addr:housenumber":"59",
    "addr:postcode":"1160",
    "addr:street":"Wilhelminenstr",
    "iso:country":"AT",
    "sg:address":"Wilhelminenstr 59",
    "sg:city":"Wien",
    "sg:orig_category":"Tapezierer U Dekorateure, Raumausstattung",
    "sg:phone":"+43 1 4854493",
    "sg:postcode":"1160",
    "sg:province":"Wien",
    "sg:website":"www.luisser.at",
    "wof:name":"Luisser Wilhelm",
    "wof:placetype":"venue"
},
  "geometry": {"coordinates":[16.3127212524,48.2169189453],"type":"Point"}
}