{
  "type": "Feature",
  "properties": {
    "addr:full":"Hieflauer Str 5 Eisenerz Steiermark 8790",
    "addr:housenumber":"5",
    "addr:postcode":"8790",
    "addr:street":"Str",
    "iso:country":"AT",
    "sg:address":"Hieflauer Str 5",
    "sg:city":"Eisenerz",
    "sg:orig_category":"Waren Aller Art",
    "sg:phone":"+43 3848 60089",
    "sg:postcode":"8790",
    "sg:province":"Steiermark",
    "wof:name":"Quelle Agentur - Mann Robert",
    "wof:placetype":"venue"
},
  "geometry": {"coordinates":[14.8869867325,47.5413131714],"type":"Point"}
}