{
  "type": "Feature",
  "properties": {
    "addr:full":"Auerspergstr 2 Wien Wien 1010",
    "addr:housenumber":"2",
    "addr:postcode":"1010",
    "addr:street":"Auerspergstr",
    "iso:country":"AT",
    "sg:address":"Auerspergstr 2",
    "sg:city":"Wien",
    "sg:orig_category":"Restaurants: Chinesisch",
    "sg:phone":"+43 1 4052775",
    "sg:postcode":"1010",
    "sg:province":"Wien",
    "wof:name":"China-Restaurant Bambus",
    "wof:placetype":"venue"
},
  "geometry": {"coordinates":[16.3555011749,48.2077941895],"type":"Point"}
}