{
  "type": "Feature",
  "properties": {
    "addr:full":"Zinckg 10/15 Wien Wien 1150",
    "addr:housenumber":"10 / 15",
    "addr:postcode":"1150",
    "addr:street":"Zinckg",
    "iso:country":"AT",
    "sg:address":"Zinckg 10/15",
    "sg:city":"Wien",
    "sg:orig_category":"Tischlereien",
    "sg:phone":"+43 1 780800",
    "sg:postcode":"1150",
    "sg:province":"Wien",
    "wof:name":"Atlas Design GmbH",
    "wof:placetype":"venue"
},
  "geometry": {"coordinates":[16.3353271484,48.198589325],"type":"Point"}
}