{
  "type": "Feature",
  "properties": {
    "addr:full":"Industriestrasse B3 Brunn am Gebirge Nieder\u00f6sterreich 2345",
    "addr:postcode":"b3;2345",
    "addr:street":"Industriestrasse;Niederoesterreich",
    "iso:country":"AT",
    "sg:address":"Industriestrasse B3",
    "sg:city":"Brunn am Gebirge",
    "sg:classifiers":[
        {
            "category":"Wholesale",
            "subcategory":"Auto Parts",
            "type":"Manufacturing & Wholesale Goods"
        }
    ],
    "sg:phone":"+43 2236 316660",
    "sg:postcode":"2345",
    "sg:province":"Nieder\u00f6sterreich",
    "sg:tags":[
        "export",
        "precision"
    ],
    "sg:website":"barth-polygonverbindungen.at",
    "wof:name":"Barth Werkzeug- maschinenhandel Ges.m.b.H.",
    "wof:placetype":"venue"
},
  "geometry": {"coordinates":[16.2839355469,48.107170105],"type":"Point"}
}