{
  "type": "Feature",
  "properties": {
    "addr:full":"Nr 34 F\u00fcgen Tirol 6263",
    "addr:postcode":"6263",
    "addr:street":"Nr 34 Fuegen Tirol",
    "iso:country":"AT",
    "sg:address":"Nr 34",
    "sg:city":"F\u00fcgen",
    "sg:orig_category":"Gemeinden",
    "sg:phone":"+43 4352 88623310",
    "sg:postcode":"6263",
    "sg:province":"Tirol",
    "wof:name":"Gemeindeamt Hart im Zillertal",
    "wof:placetype":"venue"
},
  "geometry": {"coordinates":[11.8493213654,47.3472557068],"type":"Point"}
}