{
  "type": "Feature",
  "properties": {
    "iso:country":"AT",
    "sg:address":"Himberger Str 18-20",
    "sg:city":"Schwechat",
    "sg:orig_category":"Fenster",
    "sg:phone":"+43 1 7072713",
    "sg:postcode":"2320",
    "sg:province":"Nieder\u00f6sterreich",
    "wof:name":"Neubauer Andreas Ing",
    "wof:placetype":"venue"
},
  "geometry": {"coordinates":[16.4747123718,48.1374397278],"type":"Point"}
}