{
  "type": "Feature",
  "properties": {
    "iso:country":"AT",
    "sg:address":"Alte Landstr 8",
    "sg:city":"Hall in Tirol",
    "sg:classifiers":[
        {
            "category":"Taxi",
            "type":"Transportation"
        }
    ],
    "sg:phone":"+43 4352 2345500",
    "sg:postcode":"6060",
    "sg:province":"Tirol",
    "sg:tags":[
        "personentransporte",
        "u"
    ],
    "wof:name":"Kili Karlheinz",
    "wof:placetype":"venue"
},
  "geometry": {"coordinates":[11.4937162399,47.2802047729],"type":"Point"}
}