{
  "type": "Feature",
  "properties": {
    "addr:full":"Latz 34 Nenzing Vorarlberg 6710",
    "addr:housenumber":"34",
    "addr:postcode":"6710",
    "addr:street":"Latz",
    "iso:country":"AT",
    "sg:address":"Latz 34",
    "sg:city":"Nenzing",
    "sg:orig_category":"Personalbereitstellung",
    "sg:phone":"+43 5525 64603",
    "sg:postcode":"6710",
    "sg:province":"Vorarlberg",
    "sg:website":"www.pegasus.or.at",
    "wof:name":"Pegasus Bewachung - Berufsdetektive & Personalbereitstellung GmbH",
    "wof:placetype":"venue"
},
  "geometry": {"coordinates":[9.6602649689,47.1907653809],"type":"Point"}
}