{
  "type": "Feature",
  "properties": {
    "addr:full":"Dr Prem-Str 5 Kufstein Tirol 6330",
    "addr:housenumber":"5",
    "addr:postcode":"6330",
    "addr:street":"Tirol",
    "iso:country":"AT",
    "sg:address":"Dr Prem-Str 5",
    "sg:city":"Kufstein",
    "sg:orig_category":"Personalberatung",
    "sg:phone":"+43 5372 65180",
    "sg:postcode":"6330",
    "sg:province":"Tirol",
    "wof:name":"Institut f Kommunikation",
    "wof:placetype":"venue"
},
  "geometry": {"coordinates":[12.1608610153,47.5855636597],"type":"Point"}
}