{
  "type": "Feature",
  "properties": {
    "iso:country":"AT",
    "sg:address":"Wichnerstr 7",
    "sg:city":"Bludenz",
    "sg:orig_category":"Bauunternehmen",
    "sg:phone":"+43 5552 68080",
    "sg:postcode":"6700",
    "sg:province":"Vorarlberg",
    "wof:name":"Proma Projekt und Baumanagement",
    "wof:placetype":"venue"
},
  "geometry": {"coordinates":[9.8203296661,47.1549987793],"type":"Point"}
}