{
  "type": "Feature",
  "properties": {
    "addr:full":"Nr 6 Mitterkirchen Ober\u00f6sterreich 4343",
    "addr:postcode":"4343",
    "addr:street":"Nr;Mitterkirchen",
    "iso:country":"AT",
    "sg:address":"Nr 6",
    "sg:city":"Mitterkirchen",
    "sg:orig_category":"Bauunternehmen",
    "sg:phone":"+43 4372 6930310",
    "sg:postcode":"4343",
    "sg:province":"Ober\u00f6sterreich",
    "wof:name":"FM Bau GmbH",
    "wof:placetype":"venue"
},
  "geometry": {"coordinates":[14.7093400955,48.1854057312],"type":"Point"}
}