{
  "type": "Feature",
  "properties": {
    "iso:country":"AT",
    "sg:address":"Kiebachg 10",
    "sg:city":"Innsbruck",
    "sg:orig_category":"Aufsperrdienste",
    "sg:phone":"+43 4351 2586142",
    "sg:postcode":"6020",
    "sg:province":"Tirol",
    "sg:website":"sicherheitsprofi.at",
    "wof:name":"Schl\u00fcsselzentrale Seidemann KG",
    "wof:placetype":"venue"
},
  "geometry": {"coordinates":[11.3923187256,47.2674827576],"type":"Point"}
}