{
  "type": "Feature",
  "properties": {
    "addr:full":"Samstr 47 Salzburg Salzburg 5020",
    "addr:housenumber":"47",
    "addr:postcode":"5020",
    "addr:street":"Samstr;Salzburg",
    "iso:country":"AT",
    "sg:address":"Samstr 47",
    "sg:city":"Salzburg",
    "sg:orig_category":"Tapezierer U Dekorateure",
    "sg:phone":"+43 4366 2660122",
    "sg:postcode":"5020",
    "sg:province":"Salzburg",
    "wof:name":"Kienberger Johann",
    "wof:placetype":"venue"
},
  "geometry": {"coordinates":[13.0670566559,47.824672699],"type":"Point"}
}