{
  "type": "Feature",
  "properties": {
    "addr:full":"Langg 25 Rankweil Vorarlberg 6830",
    "addr:housenumber":"25",
    "addr:postcode":"6830",
    "addr:street":"Langg",
    "iso:country":"AT",
    "sg:address":"Langg 25",
    "sg:city":"Rankweil",
    "sg:orig_category":"Raumausstattung",
    "sg:phone":"+43 4355 2244238",
    "sg:postcode":"6830",
    "sg:province":"Vorarlberg",
    "wof:name":"Grabher KG",
    "wof:placetype":"venue"
},
  "geometry": {"coordinates":[9.6431694031,47.2692146301],"type":"Point"}
}