{
  "type": "Feature",
  "properties": {
    "iso:country":"AT",
    "sg:address":"Gewerbestr 4",
    "sg:city":"Zeiselmauer",
    "sg:orig_category":"Dachdeckereien",
    "sg:phone":"+43 2242 71087",
    "sg:postcode":"3424",
    "sg:province":"Nieder\u00f6sterreich",
    "wof:name":"Spenglerei & Dachdeckerei Gerhard Resch GesmbH",
    "wof:placetype":"venue"
},
  "geometry": {"coordinates":[16.177192688,48.3291931152],"type":"Point"}
}