{
  "type": "Feature",
  "properties": {
    "iso:country":"AT",
    "sg:address":"Nr 236",
    "sg:city":"Pettneu am Arlberg",
    "sg:orig_category":"Maschinenhandel",
    "sg:phone":"+43 5448 822444",
    "sg:postcode":"6574",
    "sg:province":"Tirol",
    "wof:name":"HSP Alpinservice Inh Armand Windisch",
    "wof:placetype":"venue"
},
  "geometry": {"coordinates":[10.3418588638,47.148349762],"type":"Point"}
}