{
  "type": "Feature",
  "properties": {
    "addr:full":"H\u00f6henstrasse 1 Katsdorf Ober\u00f6sterreich 4223",
    "addr:housenumber":"1",
    "addr:postcode":"4223",
    "addr:street":"Hoehenstrasse",
    "iso:country":"AT",
    "sg:address":"H\u00f6henstrasse 1",
    "sg:city":"Katsdorf",
    "sg:classifiers":[
        {
            "category":"Home & Garden",
            "subcategory":"Carpets & Floor Coverings",
            "type":"Retail Goods"
        }
    ],
    "sg:phone":"+43 664 2215699",
    "sg:postcode":"4223",
    "sg:province":"Ober\u00f6sterreich",
    "sg:tags":[
        "tile"
    ],
    "wof:name":"Franz Woldrich GesmbH",
    "wof:placetype":"venue"
},
  "geometry": {"coordinates":[14.4748802185,48.3203468323],"type":"Point"}
}