{
  "type": "Feature",
  "properties": {
    "addr:full":"Ramsauer Str 61 Linz Ober\u00f6sterreich 4020",
    "addr:postcode":"4020",
    "addr:street":"Str 61",
    "iso:country":"AT",
    "sg:address":"Ramsauer Str 61",
    "sg:city":"Linz",
    "sg:orig_category":"Hauptschulen",
    "sg:phone":"+43 732 3430050",
    "sg:postcode":"4020",
    "sg:province":"Ober\u00f6sterreich",
    "wof:name":"Hauptschule 22 Dr Ernst Koref Schule",
    "wof:placetype":"venue"
},
  "geometry": {"coordinates":[14.2884321213,48.2724075317],"type":"Point"}
}