{
  "type": "Feature",
  "properties": {
    "iso:country":"AT",
    "sg:address":"Nr 7",
    "sg:city":"Mautern",
    "sg:orig_category":"Pensionen / Privatzimmer",
    "sg:phone":"+43 2732 749490",
    "sg:postcode":"3512",
    "sg:province":"Nieder\u00f6sterreich",
    "wof:name":"Eder Winzerhof-G\u00e4stehaus",
    "wof:placetype":"venue"
},
  "geometry": {"coordinates":[15.577627182,48.3937988281],"type":"Point"}
}