{
  "type": "Feature",
  "properties": {
    "addr:full":"Gumpendorfer Str 83-85 Wien Wien 1060",
    "addr:postcode":"83-85;1060",
    "addr:street":"Str",
    "iso:country":"AT",
    "sg:address":"Gumpendorfer Str 83-85",
    "sg:city":"Wien",
    "sg:orig_category":"Psychotherapie",
    "sg:phone":"+43 1 5973100",
    "sg:postcode":"1060",
    "sg:province":"Wien",
    "wof:name":"Beer Josef",
    "wof:placetype":"venue"
},
  "geometry": {"coordinates":[16.3497657776,48.1936645508],"type":"Point"}
}