{
  "type": "Feature",
  "properties": {
    "iso:country":"AT",
    "sg:address":"Dametzstr 25",
    "sg:city":"Linz",
    "sg:orig_category":"Bilder",
    "sg:phone":"+43 4373 2770270",
    "sg:postcode":"4020",
    "sg:province":"Ober\u00f6sterreich",
    "wof:name":"Bilder Eigl GmbH & Co KG",
    "wof:placetype":"venue"
},
  "geometry": {"coordinates":[14.2913570404,48.3036003113],"type":"Point"}
}