{
  "type": "Feature",
  "properties": {
    "addr:full":"Mariahilfer Str 115 Wien Wien 1060",
    "addr:housenumber":"115",
    "addr:postcode":"1060",
    "iso:country":"AT",
    "sg:address":"Mariahilfer Str 115",
    "sg:city":"Wien",
    "sg:orig_category":"Textilwaren / Erzeugung U Gro\u00c3\u0178handel",
    "sg:phone":"+43 1 59794130",
    "sg:postcode":"1060",
    "sg:province":"Wien",
    "wof:name":"Gassner Egon",
    "wof:placetype":"venue"
},
  "geometry": {"coordinates":[16.3429660797,48.1963653564],"type":"Point"}
}