{
  "type": "Feature",
  "properties": {
    "iso:country":"AT",
    "sg:address":"Olivierstrasse 23",
    "sg:city":"Aigen",
    "sg:classifiers":[
        {
            "category":"Shopping",
            "subcategory":"Books",
            "type":"Retail Goods"
        }
    ],
    "sg:phone":"+43 662 640837",
    "sg:postcode":"5026",
    "sg:province":"Salzburg",
    "wof:name":"Dr. Franz Lageder B\u00fccher und Texte",
    "wof:placetype":"venue"
},
  "geometry": {"coordinates":[13.0771751404,47.7856712341],"type":"Point"}
}