{
  "type": "Feature",
  "properties": {
    "iso:country":"AT",
    "sg:address":"Franzosengraben 17",
    "sg:city":"Wien",
    "sg:orig_category":"Textilwaren / Erzeugung U Gro\u00c3\u0178handel",
    "sg:phone":"+43 4317 9862600",
    "sg:postcode":"1030",
    "sg:province":"Wien",
    "wof:name":"Haas A TextilhandelsgesmbH",
    "wof:placetype":"venue"
},
  "geometry": {"coordinates":[16.4138202667,48.1871604919],"type":"Point"}
}