{
  "type": "Feature",
  "properties": {
    "addr:full":"Dorffeld 1 Eisenerz Steiermark 8790",
    "addr:housenumber":"1",
    "addr:postcode":"8790",
    "addr:street":"Dorffeld",
    "iso:country":"AT",
    "sg:address":"Dorffeld 1",
    "sg:city":"Eisenerz",
    "sg:classifiers":[
        {
            "category":"Manufacturing",
            "subcategory":"Glass & Minerals",
            "type":"Manufacturing & Wholesale Goods"
        }
    ],
    "sg:phone":"+43 3848 2249",
    "sg:postcode":"8790",
    "sg:province":"Steiermark",
    "sg:tags":[
        "flat"
    ],
    "wof:name":"Rudolf Koschnik",
    "wof:placetype":"venue"
},
  "geometry": {"coordinates":[14.8848981857,47.5437850952],"type":"Point"}
}