{
  "type": "Feature",
  "properties": {
    "addr:full":"Stanglgraben 2 Bromberg Nieder\u00f6sterreich 2833",
    "addr:housenumber":"2;2833",
    "addr:street":"Stanglgraben;Bromberg Niederoesterreich",
    "iso:country":"AT",
    "sg:address":"Stanglgraben 2",
    "sg:city":"Bromberg",
    "sg:classifiers":[
        {
            "category":"Wholesale",
            "subcategory":"Vending Machines",
            "type":"Manufacturing & Wholesale Goods"
        }
    ],
    "sg:phone":"+43 2629 82480",
    "sg:postcode":"2833",
    "sg:province":"Nieder\u00f6sterreich",
    "sg:tags":[
        "sawing",
        "timber",
        "cut-off",
        "saw",
        "round",
        "machines",
        "circular"
    ],
    "wof:name":"Friedrich Seier Ges.m.b.H.",
    "wof:placetype":"venue"
},
  "geometry": {"coordinates":[16.2502403259,47.6414527893],"type":"Point"}
}