{
  "type": "Feature",
  "properties": {
    "addr:full":"Franz Xaver Renn-Str 1 Imst Tirol 6460",
    "addr:housenumber":"1",
    "addr:postcode":"6460",
    "addr:street":"Franz;Renn-Str;Tirol",
    "iso:country":"AT",
    "sg:address":"Franz Xaver Renn-Str 1",
    "sg:city":"Imst",
    "sg:orig_category":"Musikgruppen",
    "sg:phone":"+43 664 2066858",
    "sg:postcode":"6460",
    "sg:province":"Tirol",
    "wof:name":"Stadtmusik Imst",
    "wof:placetype":"venue"
},
  "geometry": {"coordinates":[10.7396888733,47.2427902222],"type":"Point"}
}