{
  "type": "Feature",
  "properties": {
    "addr:full":"Bahnhofstr 16 Feldkirchen in K\u00e4rnten K\u00e4rnten 9560",
    "addr:housenumber":"16",
    "addr:postcode":"9560",
    "addr:street":"Bahnhofstr;Kaernten",
    "iso:country":"AT",
    "sg:address":"Bahnhofstr 16",
    "sg:city":"Feldkirchen in K\u00e4rnten",
    "sg:orig_category":"Werbeagenturen",
    "sg:phone":"+43 4342 764673",
    "sg:postcode":"9560",
    "sg:province":"K\u00e4rnten",
    "wof:name":"B\u00fcrger Reinhard",
    "wof:placetype":"venue"
},
  "geometry": {"coordinates":[14.0945320129,46.7235221863],"type":"Point"}
}