{
  "type": "Feature",
  "properties": {
    "addr:full":"Helmberger Str 13 St. Georgen Salzburg 5113",
    "addr:housenumber":"13",
    "addr:postcode":"5113",
    "addr:street":"Str",
    "iso:country":"AT",
    "sg:address":"Helmberger Str 13",
    "sg:city":"St. Georgen",
    "sg:orig_category":"Volksschulen",
    "sg:phone":"+43 4362 747405",
    "sg:postcode":"5113",
    "sg:province":"Salzburg",
    "wof:name":"Volksschule",
    "wof:placetype":"venue"
},
  "geometry": {"coordinates":[12.9313955307,48.0156517029],"type":"Point"}
}