{
  "type": "Feature",
  "properties": {
    "iso:country":"AT",
    "sg:address":"Theresieng 67",
    "sg:city":"Wien",
    "sg:orig_category":"Exporteure U Importeure",
    "sg:phone":"+43 4314 0983930",
    "sg:postcode":"1180",
    "sg:province":"Wien",
    "wof:name":"WIMEX HandelsgesmbH",
    "wof:placetype":"venue"
},
  "geometry": {"coordinates":[16.3428974152,48.2235679626],"type":"Point"}
}