{
  "type": "Feature",
  "properties": {
    "addr:full":"Kircheng 17 Markt Piesting Nieder\u00f6sterreich 2753",
    "addr:housenumber":"17",
    "addr:postcode":"2753",
    "addr:street":"Kircheng",
    "iso:country":"AT",
    "sg:address":"Kircheng 17",
    "sg:city":"Markt Piesting",
    "sg:orig_category":"Dachdeckereien",
    "sg:phone":"+43 4326 33422420",
    "sg:postcode":"2753",
    "sg:province":"Nieder\u00f6sterreich",
    "wof:name":"Machacek Ing. Stefan u Ing. Ernst Dach u Fassade GmbH",
    "wof:placetype":"venue"
},
  "geometry": {"coordinates":[16.1312866211,47.8738517761],"type":"Point"}
}