{
  "type": "Feature",
  "properties": {
    "iso:country":"AT",
    "sg:address":"Brixentaler Strasse 4",
    "sg:city":"Hopfgarten im Brixental",
    "sg:classifiers":[
        {
            "category":"Home & Garden",
            "subcategory":"Home Furnishings",
            "type":"Retail Goods"
        }
    ],
    "sg:phone":"+43 5335 2338",
    "sg:postcode":"6361",
    "sg:province":"Tirol",
    "sg:tags":[
        "bathroom",
        "wc",
        "fitting"
    ],
    "sg:website":"pletzer.at",
    "wof:name":"Pletzer Anton GmbH",
    "wof:placetype":"venue"
},
  "geometry": {"coordinates":[12.1667003632,47.4500007629],"type":"Point"}
}