{
  "type": "Feature",
  "properties": {
    "addr:full":"Obere Hauptstr 20 Illmitz Burgenland 7142",
    "addr:housenumber":"20",
    "addr:postcode":"7142",
    "addr:street":"Obere Hauptstr",
    "iso:country":"AT",
    "sg:address":"Obere Hauptstr 20",
    "sg:city":"Illmitz",
    "sg:orig_category":"Pensionen / Privatzimmer",
    "sg:phone":"+43 2175 3345",
    "sg:postcode":"7142",
    "sg:province":"Burgenland",
    "wof:name":"Arkadenweingut-G\u00e4stehaus Fam Heiss",
    "wof:placetype":"venue"
},
  "geometry": {"coordinates":[16.8006401062,47.763381958],"type":"Point"}
}