{
  "type": "Feature",
  "properties": {
    "addr:full":"Leombach 78  Sipbachzell Ober\u00f6sterreich 4621",
    "addr:housenumber":"78",
    "addr:postcode":"4621",
    "addr:street":"Leombach",
    "iso:country":"AT",
    "sg:address":"Leombach 78 ",
    "sg:city":"Sipbachzell",
    "sg:classifiers":[
        {
            "category":"Home & Garden",
            "subcategory":"Home Furnishings",
            "type":"Retail Goods"
        }
    ],
    "sg:phone":"+43 4372 4082720",
    "sg:postcode":"4621",
    "sg:province":"Ober\u00f6sterreich",
    "sg:tags":[
        "household"
    ],
    "wof:name":"JOHANN LEDERHILGER",
    "wof:placetype":"venue"
},
  "geometry": {"coordinates":[14.0930614471,48.1200675964],"type":"Point"}
}