{
  "type": "Feature",
  "properties": {
    "addr:full":"Emil-Von-Behring-Str. 30  Villach K\u00e4rnten 9500",
    "addr:housenumber":"30",
    "addr:postcode":"9500",
    "addr:street":"Emil-Von-Behring-Str.;Kaernten",
    "iso:country":"AT",
    "sg:address":"Emil-Von-Behring-Str. 30 ",
    "sg:city":"Villach",
    "sg:classifiers":[
        {
            "category":"Manufacturing",
            "subcategory":"Motor Vehicles & Parts",
            "type":"Manufacturing & Wholesale Goods"
        }
    ],
    "sg:phone":"+43 4342 4241021",
    "sg:postcode":"9500",
    "sg:province":"K\u00e4rnten",
    "sg:tags":[
        "engine"
    ],
    "wof:name":"PLASOUNIG TECHNIK GMBH",
    "wof:placetype":"venue"
},
  "geometry": {"coordinates":[13.8656787872,46.6173706055],"type":"Point"}
}