{
  "type": "Feature",
  "properties": {
    "iso:country":"AT",
    "sg:address":"Arnikaweg 99",
    "sg:city":"Wien",
    "sg:classifiers":[
        {
            "category":"Professional",
            "subcategory":"Advertising",
            "type":"Services"
        }
    ],
    "sg:phone":"+43 1 7344499",
    "sg:postcode":"1220",
    "sg:province":"Wien",
    "sg:tags":[
        "t-shirt",
        "promotional"
    ],
    "sg:website":"gka.at",
    "wof:name":"GKA-Textildruck Werbegestaltung & Modedesign on T-Shirts",
    "wof:placetype":"venue"
},
  "geometry": {"coordinates":[16.4762973785,48.2477149963],"type":"Point"}
}