{
  "type": "Feature",
  "properties": {
    "iso:country":"AT",
    "sg:address":"Rauberg 10",
    "sg:city":"Graz",
    "sg:orig_category":"Museen / Ausstellungen",
    "sg:phone":"+43 316 80170",
    "sg:postcode":"8010",
    "sg:province":"Steiermark",
    "wof:name":"Landesmuseum Joanneum",
    "wof:placetype":"venue"
},
  "geometry": {"coordinates":[15.4383440018,47.0687828064],"type":"Point"}
}