{
  "type": "Feature",
  "properties": {
    "addr:full":"Angelika-Kauffmann-Str 20 Hohenems Vorarlberg 6845",
    "addr:housenumber":"20",
    "addr:postcode":"6845",
    "addr:street":"Angelika-Kauffmann-Str",
    "iso:country":"AT",
    "sg:address":"Angelika-Kauffmann-Str 20",
    "sg:city":"Hohenems",
    "sg:orig_category":"Textilreinigung",
    "sg:phone":"+43 4355 7642636",
    "sg:postcode":"6845",
    "sg:province":"Vorarlberg",
    "wof:name":"Sander Heinrich GesmbH & Co KG",
    "wof:placetype":"venue"
},
  "geometry": {"coordinates":[9.684173584,47.366645813],"type":"Point"}
}