{
  "type": "Feature",
  "properties": {
    "iso:country":"AT",
    "sg:address":"Eduard Klein-G 19",
    "sg:city":"Wien",
    "sg:orig_category":"Steuerberatung",
    "sg:phone":"+43 1 8794632",
    "sg:postcode":"1130",
    "sg:province":"Wien",
    "wof:name":"Trigon Wirtschaftstreuhand-Steuerberatungs-u Buchpr\u00fcfungs GmbH",
    "wof:placetype":"venue"
},
  "geometry": {"coordinates":[16.3008346558,48.1877098083],"type":"Point"}
}