{
  "type": "Feature",
  "properties": {
    "iso:country":"AT",
    "sg:address":"Villacher Str 20",
    "sg:city":"Feistritz an der Drau",
    "sg:orig_category":"Non-Classified Establishments",
    "sg:phone":"+43 4342 4527020",
    "sg:postcode":"9710",
    "sg:province":"K\u00e4rnten",
    "wof:name":"Seiler Albert",
    "wof:placetype":"venue"
},
  "geometry": {"coordinates":[13.6660671234,46.6996650696],"type":"Point"}
}