{
  "type": "Feature",
  "properties": {
    "addr:full":"Darwing 3 Wien Wien 1020",
    "addr:housenumber":"3",
    "addr:postcode":"1020",
    "addr:street":"Darwing",
    "iso:country":"AT",
    "sg:address":"Darwing 3",
    "sg:city":"Wien",
    "sg:classifiers":[
        {
            "category":"Professional",
            "subcategory":"Art Services",
            "type":"Services"
        }
    ],
    "sg:phone":"+43 1 2164252",
    "sg:postcode":"1020",
    "sg:province":"Wien",
    "sg:tags":[
        "designer"
    ],
    "wof:name":"Pinustyle - Isabella Pinu",
    "wof:placetype":"venue"
},
  "geometry": {"coordinates":[16.3831558228,48.2227325439],"type":"Point"}
}