{
  "type": "Feature",
  "properties": {
    "addr:full":"Nr 34 Koppl Salzburg 5321",
    "addr:postcode":"5321",
    "addr:street":"Nr;Koppl",
    "iso:country":"AT",
    "sg:address":"Nr 34",
    "sg:city":"Koppl",
    "sg:orig_category":"Installationsunternehmen",
    "sg:phone":"+43 6229 36633",
    "sg:postcode":"5321",
    "sg:province":"Salzburg",
    "wof:name":"F.I.C. Steinbichler",
    "wof:placetype":"venue"
},
  "geometry": {"coordinates":[13.1568012238,47.8079414368],"type":"Point"}
}