{
  "type": "Feature",
  "properties": {
    "addr:full":"Unionstr 61 Linz Ober\u00f6sterreich 4020",
    "addr:housenumber":"61",
    "addr:postcode":"4020",
    "addr:street":"Unionstr",
    "iso:country":"AT",
    "sg:address":"Unionstr 61",
    "sg:city":"Linz",
    "sg:orig_category":"Telekommunikation",
    "sg:phone":"+43 732 601261",
    "sg:postcode":"4020",
    "sg:province":"Ober\u00f6sterreich",
    "wof:name":"Mobiltech HandelsgmbH",
    "wof:placetype":"venue"
},
  "geometry": {"coordinates":[14.2910642624,48.2835731506],"type":"Point"}
}