{
  "type": "Feature",
  "properties": {
    "addr:full":"Lungitzer Str 16 St. Georgen an der Gusen Ober\u00f6sterreich 4222",
    "addr:housenumber":"16",
    "addr:postcode":"4222",
    "addr:street":"Str",
    "iso:country":"AT",
    "sg:address":"Lungitzer Str 16",
    "sg:city":"St. Georgen an der Gusen",
    "sg:orig_category":"Tischlereien",
    "sg:phone":"+43 4367 63446125",
    "sg:postcode":"4222",
    "sg:province":"Ober\u00f6sterreich",
    "wof:name":"Fuhrmann Markus",
    "wof:placetype":"venue"
},
  "geometry": {"coordinates":[14.4150066376,48.273021698],"type":"Point"}
}