{
  "type": "Feature",
  "properties": {
    "addr:full":"Nr 133 Laaben Nieder\u00f6sterreich 3053",
    "addr:postcode":"3053",
    "addr:street":"Nr;Laaben",
    "iso:country":"AT",
    "sg:address":"Nr 133",
    "sg:city":"Laaben",
    "sg:orig_category":"Feuerwehren",
    "sg:phone":"+43 2774 8222",
    "sg:postcode":"3053",
    "sg:province":"Nieder\u00f6sterreich",
    "wof:name":"Freiwillige Feuerwehr Brand-Laaben",
    "wof:placetype":"venue"
},
  "geometry": {"coordinates":[15.881729126,48.1093482971],"type":"Point"}
}