{
  "type": "Feature",
  "properties": {
    "addr:full":"Perfektastr 79 Wien Wien 1230",
    "addr:housenumber":"79",
    "addr:postcode":"1230",
    "addr:street":"Perfektastr",
    "iso:country":"AT",
    "sg:address":"Perfektastr 79",
    "sg:city":"Wien",
    "sg:orig_category":"Garagentore U -Antriebe, Tore, Torantriebe",
    "sg:phone":"+43 4318 659866",
    "sg:postcode":"1230",
    "sg:province":"Wien",
    "wof:name":"Alpenland Schaukastensysteme",
    "wof:placetype":"venue"
},
  "geometry": {"coordinates":[16.3040275574,48.1365699768],"type":"Point"}
}