{
  "type": "Feature",
  "properties": {
    "iso:country":"AT",
    "sg:address":"Hauptstr 1",
    "sg:city":"Donnerskirchen",
    "sg:orig_category":"Bauunternehmen",
    "sg:phone":"+43 2683 8536",
    "sg:postcode":"7082",
    "sg:province":"Burgenland",
    "wof:name":"Gruber Oskar Ing",
    "wof:placetype":"venue"
},
  "geometry": {"coordinates":[16.6471672058,47.8944511414],"type":"Point"}
}