{
  "type": "Feature",
  "properties": {
    "addr:full":"Landstr 1 Radenthein K\u00e4rnten 9545",
    "addr:housenumber":"1",
    "addr:postcode":"9545",
    "addr:street":"Landstr;Kaernten",
    "iso:country":"AT",
    "sg:address":"Landstr 1",
    "sg:city":"Radenthein",
    "sg:orig_category":"Elektroinstallationsunternehmen",
    "sg:phone":"+43 4246 4500",
    "sg:postcode":"9545",
    "sg:province":"K\u00e4rnten",
    "wof:name":"Elektro Ottacher",
    "wof:placetype":"venue"
},
  "geometry": {"coordinates":[13.707359314,46.801612854],"type":"Point"}
}