{
  "type": "Feature",
  "properties": {
    "addr:full":"Marktg 13 Knittelfeld Steiermark 8720",
    "addr:housenumber":"13",
    "addr:postcode":"8720",
    "addr:street":"Marktg",
    "iso:country":"AT",
    "sg:address":"Marktg 13",
    "sg:city":"Knittelfeld",
    "sg:orig_category":"Autospenglereien",
    "sg:phone":"+43 4335 12827590",
    "sg:postcode":"8720",
    "sg:province":"Steiermark",
    "wof:name":"Herk GmbH",
    "wof:placetype":"venue"
},
  "geometry": {"coordinates":[14.8291902542,47.2139434814],"type":"Point"}
}