{
  "type": "Feature",
  "properties": {
    "addr:full":"Mucharg 3A Lienz Tirol 9900",
    "addr:housenumber":"3a",
    "addr:postcode":"9900",
    "addr:street":"Mucharg;Tirol",
    "iso:country":"AT",
    "sg:address":"Mucharg 3A",
    "sg:city":"Lienz",
    "sg:orig_category":"Boutiquen",
    "sg:phone":"+43 4348 5263123",
    "sg:postcode":"9900",
    "sg:province":"Tirol",
    "wof:name":"Irina - Mode m Flair",
    "wof:placetype":"venue"
},
  "geometry": {"coordinates":[12.7663803101,46.8300361633],"type":"Point"}
}