{
  "type": "Feature",
  "properties": {
    "iso:country":"AT",
    "sg:address":"Wolfgangseestr 19/3",
    "sg:city":"Koppl",
    "sg:orig_category":"Metallbe- U -Verarbeitung",
    "sg:phone":"+43 662 646558",
    "sg:postcode":"5321",
    "sg:province":"Salzburg",
    "wof:name":"B\u00e4uml Thomas",
    "wof:placetype":"venue"
},
  "geometry": {"coordinates":[13.1351947784,47.8230552673],"type":"Point"}
}