{
  "type": "Feature",
  "properties": {
    "addr:full":"Tannenweg 1/11 Trofaiach Steiermark 8793",
    "addr:housenumber":"1 / 11",
    "addr:postcode":"8793",
    "addr:street":"Tannenweg",
    "iso:country":"AT",
    "sg:address":"Tannenweg 1/11",
    "sg:city":"Trofaiach",
    "sg:orig_category":"Beratungsstellen",
    "sg:phone":"+43 664 3123351",
    "sg:postcode":"8793",
    "sg:province":"Steiermark",
    "wof:name":"Neuhold Petra Lernberatung",
    "wof:placetype":"venue"
},
  "geometry": {"coordinates":[14.9939498901,47.4225082397],"type":"Point"}
}