{
  "type": "Feature",
  "properties": {
    "iso:country":"AT",
    "sg:address":"Franzosengraben 2-4",
    "sg:city":"Wien",
    "sg:orig_category":"Ballettschulen",
    "sg:phone":"+43 1 7963828",
    "sg:postcode":"1030",
    "sg:province":"Wien",
    "sg:website":"vdc.at",
    "wof:name":"Vienna Dance Center",
    "wof:placetype":"venue"
},
  "geometry": {"coordinates":[16.4143028259,48.1896286011],"type":"Point"}
}