{
  "type": "Feature",
  "properties": {
    "addr:full":"Unter der Burg 11 Waidhofen an der Ybbs Nieder\u00f6sterreich 3340",
    "addr:housenumber":"11",
    "addr:postcode":"3340",
    "addr:street":"Unter Der Burg",
    "iso:country":"AT",
    "sg:address":"Unter der Burg 11",
    "sg:city":"Waidhofen an der Ybbs",
    "sg:orig_category":"Friseure U Frisiersalons",
    "sg:phone":"+43 4374 4254536",
    "sg:postcode":"3340",
    "sg:province":"Nieder\u00f6sterreich",
    "wof:name":"Ahorner Ingrid",
    "wof:placetype":"venue"
},
  "geometry": {"coordinates":[14.7721748352,47.9609794617],"type":"Point"}
}