{
  "type": "Feature",
  "properties": {
    "addr:full":"Flurweg 6 Faak am See K\u00e4rnten 9583",
    "addr:housenumber":"6",
    "addr:postcode":"9583",
    "addr:street":"Flurweg;Kaernten",
    "iso:country":"AT",
    "sg:address":"Flurweg 6",
    "sg:city":"Faak am See",
    "sg:orig_category":"Pensionen / Privatzimmer",
    "sg:phone":"+43 4254 27460",
    "sg:postcode":"9583",
    "sg:province":"K\u00e4rnten",
    "wof:name":"Steiner Heidi",
    "wof:placetype":"venue"
},
  "geometry": {"coordinates":[13.9146604538,46.5667495728],"type":"Point"}
}