{
  "type": "Feature",
  "properties": {
    "iso:country":"AT",
    "sg:address":"Am See 31",
    "sg:city":"Trautmannsdorf an der Leitha",
    "sg:orig_category":"Handelsagenturen",
    "sg:phone":"+43 664 2057980",
    "sg:postcode":"2454",
    "sg:province":"Nieder\u00f6sterreich",
    "wof:name":"Nell Wilhelm-Michael Ing",
    "wof:placetype":"venue"
},
  "geometry": {"coordinates":[16.6375694275,48.0220909119],"type":"Point"}
}