{
  "type": "Feature",
  "properties": {
    "iso:country":"AT",
    "sg:address":"Hauptstr 5",
    "sg:city":"Scheibbs",
    "sg:orig_category":"Friseure U Frisiersalons",
    "sg:phone":"+43 4374 8242978",
    "sg:postcode":"3270",
    "sg:province":"Nieder\u00f6sterreich",
    "wof:name":"Top Hair Stadtfriseur - Kirstin Eszletzbichler",
    "wof:placetype":"venue"
},
  "geometry": {"coordinates":[15.1657867432,48.0072479248],"type":"Point"}
}