{
  "type": "Feature",
  "properties": {
    "addr:full":"Postg 2 Pyhra Nieder\u00f6sterreich 3143",
    "addr:housenumber":"2",
    "addr:postcode":"3143",
    "addr:street":"Postg",
    "iso:country":"AT",
    "sg:address":"Postg 2",
    "sg:city":"Pyhra",
    "sg:orig_category":"Polizei U Gendarmerie",
    "sg:phone":"+43 4359 1333172",
    "sg:postcode":"3143",
    "sg:province":"Nieder\u00f6sterreich",
    "wof:name":"Gendarmerie",
    "wof:placetype":"venue"
},
  "geometry": {"coordinates":[15.6855783463,48.1585044861],"type":"Point"}
}