{
  "type": "Feature",
  "properties": {
    "addr:full":"Hauptstr 1 St. Johann im Pongau Salzburg 5600",
    "addr:housenumber":"1",
    "addr:postcode":"5600",
    "addr:street":"Hauptstr;Salzburg",
    "iso:country":"AT",
    "sg:address":"Hauptstr 1",
    "sg:city":"St. Johann im Pongau",
    "sg:orig_category":"Bezirkshauptmannschaften",
    "sg:phone":"+43 4364 1261010",
    "sg:postcode":"5600",
    "sg:province":"Salzburg",
    "wof:name":"Bezirkshauptmannschaft St Johann im Pongau",
    "wof:placetype":"venue"
},
  "geometry": {"coordinates":[13.205329895,47.3514022827],"type":"Point"}
}