{
  "type": "Feature",
  "properties": {
    "iso:country":"AT",
    "sg:address":"Dorfstr 15",
    "sg:city":"Fieberbrunn",
    "sg:classifiers":[
        {
            "category":"Travel",
            "subcategory":"Hotels & Motels",
            "type":"Entertainment"
        }
    ],
    "sg:phone":"+43 4353 54562180",
    "sg:postcode":"6391",
    "sg:province":"Tirol",
    "wof:name":"Hotel Metzgerwirt",
    "wof:placetype":"venue"
},
  "geometry": {"coordinates":[12.5435380936,47.4764518738],"type":"Point"}
}