{
  "type": "Feature",
  "properties": {
    "addr:full":"Keplerstr 37 Graz Steiermark 8020",
    "addr:housenumber":"37",
    "addr:postcode":"8020",
    "addr:street":"Keplerstr",
    "iso:country":"AT",
    "sg:address":"Keplerstr 37",
    "sg:city":"Graz",
    "sg:orig_category":"Spielkasinos",
    "sg:phone":"+43 316 720281",
    "sg:postcode":"8020",
    "sg:province":"Steiermark",
    "wof:name":"Europlay",
    "wof:placetype":"venue"
},
  "geometry": {"coordinates":[15.4279327393,47.0754852295],"type":"Point"}
}