{
  "type": "Feature",
  "properties": {
    "addr:full":"Korbg 22 Wien Wien 1230",
    "addr:housenumber":"22",
    "addr:postcode":"1230",
    "addr:street":"Korbg",
    "iso:country":"AT",
    "sg:address":"Korbg 22",
    "sg:city":"Wien",
    "sg:orig_category":"Psychologen",
    "sg:phone":"+43 1 9231290",
    "sg:postcode":"1230",
    "sg:province":"Wien",
    "wof:name":"Lattacher Helene Mag",
    "wof:placetype":"venue"
},
  "geometry": {"coordinates":[16.2822799683,48.1347465515],"type":"Point"}
}