{
  "type": "Feature",
  "properties": {
    "addr:full":"Dresdner Str 82 Wien Wien 1200",
    "addr:postcode":"1200",
    "addr:street":"Str 82",
    "iso:country":"AT",
    "sg:address":"Dresdner Str 82",
    "sg:city":"Wien",
    "sg:orig_category":"Personalbereitstellung",
    "sg:phone":"+43 4312 185135",
    "sg:postcode":"1200",
    "sg:province":"Wien",
    "wof:name":"Interaktiv Personalservice GmbH",
    "wof:placetype":"venue"
},
  "geometry": {"coordinates":[16.3826789856,48.2340011597],"type":"Point"}
}