{
  "type": "Feature",
  "properties": {
    "addr:full":"Salzburger Str 27 Schwarzach im Pongau Salzburg 5620",
    "addr:housenumber":"27",
    "addr:postcode":"5620",
    "addr:street":"Salzburger Str;Salzburg",
    "iso:country":"AT",
    "sg:address":"Salzburger Str 27",
    "sg:city":"Schwarzach im Pongau",
    "sg:orig_category":"Farben U Lacke / Einzelhandel",
    "sg:phone":"+43 4364 157444",
    "sg:postcode":"5620",
    "sg:province":"Salzburg",
    "wof:name":"P\u00f6ll Kurt KG",
    "wof:placetype":"venue"
},
  "geometry": {"coordinates":[13.1481647491,47.3203010559],"type":"Point"}
}