{
  "type": "Feature",
  "properties": {
    "addr:full":"Waisach 12 Greifenburg K\u00e4rnten 9761",
    "addr:housenumber":"12",
    "addr:postcode":"9761",
    "addr:street":"Waisach;Kaernten",
    "iso:country":"AT",
    "sg:address":"Waisach 12",
    "sg:city":"Greifenburg",
    "sg:classifiers":[
        {
            "category":"Building & Trades",
            "subcategory":"Construction",
            "type":"Services"
        }
    ],
    "sg:phone":"+43 4712 82022",
    "sg:postcode":"9761",
    "sg:province":"K\u00e4rnten",
    "sg:tags":[
        "industrial",
        "timber"
    ],
    "wof:name":"Rudolf Baumgartner",
    "wof:placetype":"venue"
},
  "geometry": {"coordinates":[13.2050819397,46.7389450073],"type":"Point"}
}