{
  "type": "Feature",
  "properties": {
    "addr:full":"Goldanger 6 Wagrain Salzburg 5602",
    "addr:housenumber":"6",
    "addr:postcode":"5602",
    "addr:street":"Goldanger;Salzburg",
    "iso:country":"AT",
    "sg:address":"Goldanger 6",
    "sg:city":"Wagrain",
    "sg:orig_category":"Steinmetzbetriebe",
    "sg:phone":"+43 6413 7477",
    "sg:postcode":"5602",
    "sg:province":"Salzburg",
    "wof:name":"Stein Creativ - Andreas Scheffauer",
    "wof:placetype":"venue"
},
  "geometry": {"coordinates":[13.2926197052,47.3340911865],"type":"Point"}
}