{
  "type": "Feature",
  "properties": {
    "addr:full":"Haid 11 Wagrain Salzburg 5602",
    "addr:housenumber":"11",
    "addr:postcode":"5602",
    "addr:street":"Haid;Salzburg",
    "iso:country":"AT",
    "sg:address":"Haid 11",
    "sg:city":"Wagrain",
    "sg:orig_category":"Pensionen / Privatzimmer",
    "sg:phone":"+43 6413 8260",
    "sg:postcode":"5602",
    "sg:province":"Salzburg",
    "wof:name":"Zum Wilden Hannes",
    "wof:placetype":"venue"
},
  "geometry": {"coordinates":[13.3013801575,47.3319816589],"type":"Point"}
}