{
  "type": "Feature",
  "properties": {
    "iso:country":"AT",
    "sg:address":"Tragweiner Str 22",
    "sg:city":"Pregarten",
    "sg:orig_category":"Kontaktlinsenoptiker",
    "sg:phone":"+43 7236 2476",
    "sg:postcode":"4230",
    "sg:province":"Ober\u00f6sterreich",
    "wof:name":"Oppenborn Brillen-Kontaktlinsen GesmbH",
    "wof:placetype":"venue"
},
  "geometry": {"coordinates":[14.53236866,48.3544807434],"type":"Point"}
}