{
  "type": "Feature",
  "properties": {
    "addr:full":"Goldschlagstr 137 Wien Wien 1140",
    "addr:housenumber":"137",
    "addr:postcode":"1140",
    "iso:country":"AT",
    "sg:address":"Goldschlagstr 137",
    "sg:city":"Wien",
    "sg:orig_category":"Berufsschulen",
    "sg:phone":"+43 4315 991695802",
    "sg:postcode":"1140",
    "sg:province":"Wien",
    "wof:name":"Berufsschule f Haar- u K\u00f6rperpflege",
    "wof:placetype":"venue"
},
  "geometry": {"coordinates":[16.3113193512,48.1957168579],"type":"Point"}
}