{
  "type": "Feature",
  "properties": {
    "iso:country":"AT",
    "sg:address":"Fadingerstr 11",
    "sg:city":"Salzburg",
    "sg:orig_category":"Tai Chi, Tai Chi Chuan U Qi Gong",
    "sg:phone":"+43 662 633161",
    "sg:postcode":"5020",
    "sg:province":"Salzburg",
    "wof:name":"IQT\u00d6 Interessengemeinschaft d Qigong- und Taiji Quan-LehrerInnen \u00d6sterreichs E Dellasega",
    "wof:placetype":"venue"
},
  "geometry": {"coordinates":[13.0694932938,47.7992630005],"type":"Point"}
}