{
  "type": "Feature",
  "properties": {
    "iso:country":"AT",
    "sg:address":"Transportstr 4",
    "sg:city":"St. Veit an der Glan",
    "sg:orig_category":"Bierdepots",
    "sg:phone":"+43 4212 72778",
    "sg:postcode":"9300",
    "sg:province":"K\u00e4rnten",
    "wof:name":"Erste Obermurtaler Brauereigenossenschaft in Murau regGenmbH",
    "wof:placetype":"venue"
},
  "geometry": {"coordinates":[14.3534879684,46.7583732605],"type":"Point"}
}