{
  "type": "Feature",
  "properties": {
    "iso:country":"AT",
    "sg:address":"Ried 43",
    "sg:city":"Schwaz",
    "sg:orig_category":"Transportunternehmen",
    "sg:phone":"+43 5242 64554",
    "sg:postcode":"6130",
    "sg:province":"Tirol",
    "wof:name":"Wieser Josef TransportgesmbH",
    "wof:placetype":"venue"
},
  "geometry": {"coordinates":[11.734208107,47.3554039001],"type":"Point"}
}