{
  "type": "Feature",
  "properties": {
    "addr:full":"Dorfstr 41 Brixen im Thale Tirol 6364",
    "addr:housenumber":"41",
    "addr:postcode":"6364",
    "addr:street":"Dorfstr;Tirol",
    "iso:country":"AT",
    "sg:address":"Dorfstr 41",
    "sg:city":"Brixen im Thale",
    "sg:orig_category":"Elektroinstallationsunternehmen",
    "sg:phone":"+43 5334 81120",
    "sg:postcode":"6364",
    "sg:province":"Tirol",
    "wof:name":"Elektro Strobl GesmbH",
    "wof:placetype":"venue"
},
  "geometry": {"coordinates":[12.2591657639,47.4495391846],"type":"Point"}
}