{
  "type": "Feature",
  "properties": {
    "addr:full":"Nr 60a Markt Allhau Burgenland 7411",
    "addr:postcode":"7411",
    "addr:street":"Nr 60A",
    "iso:country":"AT",
    "sg:address":"Nr 60a",
    "sg:city":"Markt Allhau",
    "sg:orig_category":"Tankstellen",
    "sg:phone":"+43 3356 338",
    "sg:postcode":"7411",
    "sg:province":"Burgenland",
    "wof:name":"OMV AG",
    "wof:placetype":"venue"
},
  "geometry": {"coordinates":[16.0806007385,47.2934417725],"type":"Point"}
}