{
  "type": "Feature",
  "properties": {
    "addr:full":"Franzosengraben 10 Wien Wien 1030",
    "addr:housenumber":"10",
    "addr:postcode":"1030",
    "addr:street":"Franzosengraben",
    "iso:country":"AT",
    "sg:address":"Franzosengraben 10",
    "sg:city":"Wien",
    "sg:orig_category":"Telekommunikation",
    "sg:phone":"+43 1 20677",
    "sg:postcode":"1030",
    "sg:province":"Wien",
    "wof:name":"Klarium Telekommunikation GmbH",
    "wof:placetype":"venue"
},
  "geometry": {"coordinates":[16.4140758514,48.1883621216],"type":"Point"}
}