{
  "type": "Feature",
  "properties": {
    "addr:full":"Gunnersdorf 27  Lasberg Ober\u00f6sterreich 4291",
    "addr:housenumber":"27",
    "addr:postcode":"4291",
    "addr:street":"Gunnersdorf",
    "iso:country":"AT",
    "sg:address":"Gunnersdorf 27 ",
    "sg:city":"Lasberg",
    "sg:classifiers":[
        {
            "category":"Structure",
            "subcategory":"Office Building",
            "type":"Public Place"
        }
    ],
    "sg:phone":"+43 7942 72880",
    "sg:postcode":"4291",
    "sg:province":"Ober\u00f6sterreich",
    "sg:tags":[
        "facing",
        "frame",
        "door"
    ],
    "wof:name":"Lasberger Granitindustrie GmbH & Co KG",
    "wof:placetype":"venue"
},
  "geometry": {"coordinates":[14.5302848816,48.4973564148],"type":"Point"}
}