{
  "type": "Feature",
  "properties": {
    "addr:full":"Paracelsusg 3 Villach K\u00e4rnten 9500",
    "addr:housenumber":"3",
    "addr:postcode":"9500",
    "addr:street":"Paracelsusg;Kaernten",
    "iso:country":"AT",
    "sg:address":"Paracelsusg 3",
    "sg:city":"Villach",
    "sg:classifiers":[
        {
            "category":"Travel",
            "subcategory":"Hotels & Motels",
            "type":"Entertainment"
        }
    ],
    "sg:phone":"+43 4242 24808",
    "sg:postcode":"9500",
    "sg:province":"K\u00e4rnten",
    "wof:name":"Hotel Fugger",
    "wof:placetype":"venue"
},
  "geometry": {"coordinates":[13.8455629349,46.6144256592],"type":"Point"}
}