{
  "type": "Feature",
  "properties": {
    "addr:full":"Hechtstr 54 Seekirchen am Wallersee Salzburg 5201",
    "addr:housenumber":"54",
    "addr:postcode":"5201",
    "addr:street":"Hechtstr;Salzburg",
    "iso:country":"AT",
    "sg:address":"Hechtstr 54",
    "sg:city":"Seekirchen am Wallersee",
    "sg:classifiers":[
        {
            "category":"Professional",
            "subcategory":"Computer Services",
            "type":"Services"
        }
    ],
    "sg:phone":"+43 6212 400680",
    "sg:postcode":"5201",
    "sg:province":"Salzburg",
    "sg:tags":[
        "software"
    ],
    "wof:name":"Wiscom Peter Sauer KEG",
    "wof:placetype":"venue"
},
  "geometry": {"coordinates":[13.1312923431,47.8957176208],"type":"Point"}
}