{
  "type": "Feature",
  "properties": {
    "addr:full":"Hauptstr 18 Weissenbach an der Triesting Nieder\u00f6sterreich 2564",
    "addr:housenumber":"18",
    "addr:postcode":"2564",
    "addr:street":"Hauptstr",
    "iso:country":"AT",
    "sg:address":"Hauptstr 18",
    "sg:city":"Weissenbach an der Triesting",
    "sg:orig_category":"Rettungsdienste",
    "sg:phone":"+43 4326 7489245",
    "sg:postcode":"2564",
    "sg:province":"Nieder\u00f6sterreich",
    "wof:name":"Rotes Kreuz - Ortsstelle Weissenbach",
    "wof:placetype":"venue"
},
  "geometry": {"coordinates":[16.0407581329,47.982093811],"type":"Point"}
}