{
  "type": "Feature",
  "properties": {
    "addr:full":"Nr 7 Neuhaus Ober\u00f6sterreich 4114",
    "addr:postcode":"4114",
    "addr:street":"Nr;Neuhaus",
    "iso:country":"AT",
    "sg:address":"Nr 7",
    "sg:city":"Neuhaus",
    "sg:orig_category":"Granitwerke",
    "sg:phone":"+43 4372 825307",
    "sg:postcode":"4114",
    "sg:province":"Ober\u00f6sterreich",
    "wof:name":"Resch Anton Ing",
    "wof:placetype":"venue"
},
  "geometry": {"coordinates":[166.9221496582,-0.5282999873],"type":"Point"}
}