{
  "type": "Feature",
  "properties": {
    "iso:country":"AT",
    "sg:address":"Werksgel\u00e4nde 26",
    "sg:classifiers":[
        {
            "category":"Professional",
            "subcategory":"Art Services",
            "type":"Services"
        }
    ],
    "sg:phone":"+43 6462 8394",
    "sg:postcode":"5503",
    "sg:tags":[
        "designer"
    ],
    "wof:name":"Glasdesign Schmid & Hettegger OEG",
    "wof:placetype":"venue"
},
  "geometry": {"coordinates":[107.0046386719,27.0754508972],"type":"Point"}
}