{
  "type": "Feature",
  "properties": {
    "iso:country":"AT",
    "sg:address":"Hauptstr 15",
    "sg:city":"Eschenau an der Traisen",
    "sg:orig_category":"Transportunternehmen",
    "sg:phone":"+43 4327 6267273",
    "sg:postcode":"3153",
    "sg:province":"Nieder\u00f6sterreich",
    "wof:name":"Lee Norbert",
    "wof:placetype":"venue"
},
  "geometry": {"coordinates":[15.570810318,48.0525588989],"type":"Point"}
}