{
  "type": "Feature",
  "properties": {
    "addr:full":"Dr Koch-Str 33 Hadersdorf am Kamp Nieder\u00f6sterreich 3493",
    "addr:housenumber":"33",
    "addr:postcode":"3493",
    "addr:street":"Niederoesterreich",
    "iso:country":"AT",
    "sg:address":"Dr Koch-Str 33",
    "sg:city":"Hadersdorf am Kamp",
    "sg:orig_category":"Sonnenstudios",
    "sg:phone":"+43 2735 2092",
    "sg:postcode":"3493",
    "sg:province":"Nieder\u00f6sterreich",
    "wof:name":"Bielecki Kurt",
    "wof:placetype":"venue"
},
  "geometry": {"coordinates":[15.7263460159,48.4580078125],"type":"Point"}
}