{
  "type": "Feature",
  "properties": {
    "addr:full":"Priesterhausg 3 Klagenfurt K\u00e4rnten 9020",
    "addr:housenumber":"3",
    "addr:postcode":"9020",
    "addr:street":"Priesterhausg;Kaernten",
    "iso:country":"AT",
    "sg:address":"Priesterhausg 3",
    "sg:city":"Klagenfurt",
    "sg:orig_category":"Lederwaren / Erzeugung U Gro\u00c3\u0178handel",
    "sg:phone":"+43 4346 3512279",
    "sg:postcode":"9020",
    "sg:province":"K\u00e4rnten",
    "wof:name":"Schluga Koffer und Taschen GesmbH",
    "wof:placetype":"venue"
},
  "geometry": {"coordinates":[14.3114089966,46.6258010864],"type":"Point"}
}