{
  "type": "Feature",
  "properties": {
    "addr:full":"Untere Hauptstr 76A Weiden am See Burgenland 7121",
    "addr:housenumber":"76a",
    "addr:postcode":"7121",
    "addr:street":"Untere Hauptstr",
    "iso:country":"AT",
    "sg:address":"Untere Hauptstr 76A",
    "sg:city":"Weiden am See",
    "sg:orig_category":"Zahntechnische Laboratorien",
    "sg:phone":"+43 2167 7594",
    "sg:postcode":"7121",
    "sg:province":"Burgenland",
    "wof:name":"Ceramic Design Karner-Peck",
    "wof:placetype":"venue"
},
  "geometry": {"coordinates":[16.8743095398,47.9226951599],"type":"Point"}
}