{
  "type": "Feature",
  "properties": {
    "iso:country":"AT",
    "sg:address":"Alleeg 36",
    "sg:city":"Wolkersdorf im Weinviertel",
    "sg:orig_category":"Chemikalien",
    "sg:phone":"+43 2245 2671",
    "sg:postcode":"2120",
    "sg:province":"Nieder\u00f6sterreich",
    "wof:name":"Hirsch Montage-Technik",
    "wof:placetype":"venue"
},
  "geometry": {"coordinates":[16.5247249603,48.368560791],"type":"Point"}
}