{
  "type": "Feature",
  "properties": {
    "addr:full":"Nr 24b Kaltenbach Tirol 6272",
    "addr:postcode":"6272",
    "addr:street":"Nr 24B",
    "iso:country":"AT",
    "sg:address":"Nr 24b",
    "sg:city":"Kaltenbach",
    "sg:orig_category":"Datenverarbeitung",
    "sg:phone":"+43 664 4524158",
    "sg:postcode":"6272",
    "sg:province":"Tirol",
    "wof:name":"Margreiter Gerald - Elektronische Datenverarbeitung",
    "wof:placetype":"venue"
},
  "geometry": {"coordinates":[11.8866147995,47.2910232544],"type":"Point"}
}