{
  "type": "Feature",
  "properties": {
    "addr:full":"Hauptpl 5 Gro\u00df-Enzersdorf Nieder\u00f6sterreich 2301",
    "addr:housenumber":"5",
    "addr:postcode":"2301",
    "addr:street":"Hauptpl;Niederoesterreich",
    "iso:country":"AT",
    "sg:address":"Hauptpl 5",
    "sg:city":"Gro\u00df-Enzersdorf",
    "sg:orig_category":"Papierwaren / Erzeugung U Gro\u00c3\u0178handel",
    "sg:phone":"+43 2249 2272",
    "sg:postcode":"2301",
    "sg:province":"Nieder\u00f6sterreich",
    "wof:name":"Wolfram Walter",
    "wof:placetype":"venue"
},
  "geometry": {"coordinates":[16.5494880676,48.201259613],"type":"Point"}
}