{
  "type": "Feature",
  "properties": {
    "iso:country":"AT",
    "sg:address":"Obermarkt 14",
    "sg:city":"Reutte",
    "sg:orig_category":"Lederwaren / Einzelhandel",
    "sg:phone":"+43 5672 62753",
    "sg:postcode":"6600",
    "sg:province":"Tirol",
    "wof:name":"Zangerl Artur KG",
    "wof:placetype":"venue"
},
  "geometry": {"coordinates":[10.7191638947,47.4878807068],"type":"Point"}
}