{
  "type": "Feature",
  "properties": {
    "addr:full":"Hauptpl 42 Neusiedl am See Burgenland 7100",
    "addr:housenumber":"42",
    "addr:postcode":"7100",
    "addr:street":"Hauptpl",
    "iso:country":"AT",
    "sg:address":"Hauptpl 42",
    "sg:city":"Neusiedl am See",
    "sg:orig_category":"Lederwaren / Einzelhandel",
    "sg:phone":"+43 4321 678128",
    "sg:postcode":"7100",
    "sg:province":"Burgenland",
    "wof:name":"Prikler F u G OHG",
    "wof:placetype":"venue"
},
  "geometry": {"coordinates":[16.8409481049,47.9493293762],"type":"Point"}
}