{
  "type": "Feature",
  "properties": {
    "iso:country":"AT",
    "sg:address":"Rindermarkt 10",
    "sg:city":"Wolfsberg",
    "sg:orig_category":"Immobilienverwaltungen",
    "sg:phone":"+43 4352 35296",
    "sg:postcode":"9400",
    "sg:province":"K\u00e4rnten",
    "wof:name":"Labi Siegfried",
    "wof:placetype":"venue"
},
  "geometry": {"coordinates":[14.8446569443,46.8373794556],"type":"Point"}
}