{
  "type": "Feature",
  "properties": {
    "iso:country":"AT",
    "sg:address":"Oberer Markt 19a",
    "sg:city":"Kefermarkt",
    "sg:orig_category":"\u00c3\u201erzte / F Allgemeinmedizin",
    "sg:phone":"+43 7947 6205",
    "sg:postcode":"4292",
    "sg:province":"Ober\u00f6sterreich",
    "wof:name":"Fischbacher Daniela Dr",
    "wof:placetype":"venue"
},
  "geometry": {"coordinates":[14.5386152267,48.4426498413],"type":"Point"}
}