{
  "type": "Feature",
  "properties": {
    "addr:full":"Schulg 11 Deutschlandsberg Steiermark 8530",
    "addr:housenumber":"11",
    "addr:postcode":"8530",
    "addr:street":"Schulg",
    "iso:country":"AT",
    "sg:address":"Schulg 11",
    "sg:city":"Deutschlandsberg",
    "sg:orig_category":"Non-Classified Establishments",
    "sg:phone":"+43 3462 2781",
    "sg:postcode":"8530",
    "sg:province":"Steiermark",
    "wof:name":"Pfarramt",
    "wof:placetype":"venue"
},
  "geometry": {"coordinates":[15.2131853104,46.815776825],"type":"Point"}
}