{
  "type": "Feature",
  "properties": {
    "iso:country":"AT",
    "sg:address":"Dorf 32",
    "sg:city":"Maria Alm am Steinernen Meer",
    "sg:classifiers":[
        {
            "category":"Restaurant",
            "type":"Food & Drink"
        }
    ],
    "sg:phone":"+43 4365 8476150",
    "sg:postcode":"5761",
    "sg:province":"Salzburg",
    "wof:name":"Haller GmbH & Co KG",
    "wof:placetype":"venue"
},
  "geometry": {"coordinates":[12.9026556015,47.4013557434],"type":"Point"}
}