{
  "type": "Feature",
  "properties": {
    "addr:full":"Blindeng 50 Wien Wien 1080",
    "addr:housenumber":"50",
    "addr:postcode":"1080",
    "addr:street":"Blindeng",
    "iso:country":"AT",
    "sg:address":"Blindeng 50",
    "sg:city":"Wien",
    "sg:orig_category":"Architekten",
    "sg:phone":"+43 1 4077421",
    "sg:postcode":"1080",
    "sg:province":"Wien",
    "wof:name":"Kleisch Horst Ing Mag arch",
    "wof:placetype":"venue"
},
  "geometry": {"coordinates":[16.341884613,48.2145118713],"type":"Point"}
}