{
  "type": "Feature",
  "properties": {
    "addr:full":"Ausstellungsstr 33-35 Wien Wien 1020",
    "addr:postcode":"33-35;1020",
    "iso:country":"AT",
    "sg:address":"Ausstellungsstr 33-35",
    "sg:city":"Wien",
    "sg:orig_category":"Dachdeckereien",
    "sg:phone":"+43 1 7285737",
    "sg:postcode":"1020",
    "sg:province":"Wien",
    "wof:name":"Schmiedek & Pinterits GesmbH",
    "wof:placetype":"venue"
},
  "geometry": {"coordinates":[16.4035892487,48.2180404663],"type":"Point"}
}