{
  "type": "Feature",
  "properties": {
    "addr:full":"Gro\u00dfreifling 10  Landl Steiermark 8931",
    "addr:housenumber":"10",
    "addr:postcode":"8931",
    "addr:street":"Grossreifling",
    "iso:country":"AT",
    "sg:address":"Gro\u00dfreifling 10 ",
    "sg:city":"Landl",
    "sg:classifiers":[
        {
            "category":"Government",
            "subcategory":"Fire Station",
            "type":"Public Place"
        }
    ],
    "sg:phone":"+43 3633 2217",
    "sg:postcode":"8931",
    "sg:province":"Steiermark",
    "sg:tags":[
        "supraregional",
        "plant",
        "installation",
        "heating"
    ],
    "wof:name":"Max Sulzbacher",
    "wof:placetype":"venue"
},
  "geometry": {"coordinates":[14.7127380371,47.666519165],"type":"Point"}
}