{
  "type": "Feature",
  "properties": {
    "addr:full":"Hauptstr 9A Michelhausen Nieder\u00f6sterreich 3451",
    "addr:housenumber":"9a",
    "addr:postcode":"3451",
    "addr:street":"Hauptstr",
    "iso:country":"AT",
    "sg:address":"Hauptstr 9A",
    "sg:city":"Michelhausen",
    "sg:orig_category":"Feuerwehren",
    "sg:phone":"+43 2274 76911",
    "sg:postcode":"3451",
    "sg:province":"Nieder\u00f6sterreich",
    "wof:name":"Freiwillige Feuerwehr Plankenberg",
    "wof:placetype":"venue"
},
  "geometry": {"coordinates":[15.9400615692,48.2906227112],"type":"Point"}
}