{
  "type": "Feature",
  "properties": {
    "addr:full":"Hauptpl 10 Matzen Nieder\u00f6sterreich 2243",
    "addr:housenumber":"10",
    "addr:postcode":"2243",
    "addr:street":"Hauptpl",
    "iso:country":"AT",
    "sg:address":"Hauptpl 10",
    "sg:city":"Matzen",
    "sg:orig_category":"Tabaktrafiken",
    "sg:phone":"+43 2289 2282",
    "sg:postcode":"2243",
    "sg:province":"Nieder\u00f6sterreich",
    "wof:name":"Megyeri Tegelhofer Andrea",
    "wof:placetype":"venue"
},
  "geometry": {"coordinates":[16.6944599152,48.4024734497],"type":"Point"}
}