{
  "type": "Feature",
  "properties": {
    "addr:full":"Welser Str 9 Gunskirchen Ober\u00f6sterreich 4623",
    "addr:housenumber":"9",
    "addr:postcode":"4623",
    "addr:street":"Str",
    "iso:country":"AT",
    "sg:address":"Welser Str 9",
    "sg:city":"Gunskirchen",
    "sg:orig_category":"Friseure U Frisiersalons",
    "sg:phone":"+43 7246 7132",
    "sg:postcode":"4623",
    "sg:province":"Ober\u00f6sterreich",
    "wof:name":"Jeiter Margarete",
    "wof:placetype":"venue"
},
  "geometry": {"coordinates":[13.9429016113,48.1345481873],"type":"Point"}
}