{
  "type": "Feature",
  "properties": {
    "addr:full":"Kristallweg 5 Neuhofen an der Krems Ober\u00f6sterreich 4501",
    "addr:housenumber":"5",
    "addr:postcode":"4501",
    "addr:street":"Kristallweg",
    "iso:country":"AT",
    "sg:address":"Kristallweg 5",
    "sg:city":"Neuhofen an der Krems",
    "sg:orig_category":"Glasereien",
    "sg:phone":"+43 4372 276287",
    "sg:postcode":"4501",
    "sg:province":"Ober\u00f6sterreich",
    "wof:name":"Leitner Eduard",
    "wof:placetype":"venue"
},
  "geometry": {"coordinates":[14.2344779968,48.1388092041],"type":"Point"}
}