{
  "type": "Feature",
  "properties": {
    "iso:country":"AT",
    "sg:address":"Magazing 6",
    "sg:city":"Linz",
    "sg:orig_category":"Restaurants: Italienisch",
    "sg:phone":"+43 732 779922",
    "sg:postcode":"4020",
    "sg:province":"Ober\u00f6sterreich",
    "wof:name":"Casa Italiana",
    "wof:placetype":"venue"
},
  "geometry": {"coordinates":[14.2901849747,48.299949646],"type":"Point"}
}