{
  "type": "Feature",
  "properties": {
    "iso:country":"AT",
    "sg:address":"Auerspergstr 18",
    "sg:city":"Linz",
    "sg:orig_category":"Architekten",
    "sg:phone":"+43 732 661708",
    "sg:postcode":"4020",
    "sg:province":"Ober\u00f6sterreich",
    "wof:name":"Derschan G\u00fcnter Arch Dipl-Ing",
    "wof:placetype":"venue"
},
  "geometry": {"coordinates":[14.2889604568,48.2975997925],"type":"Point"}
}