{
  "type": "Feature",
  "properties": {
    "iso:country":"AT",
    "sg:address":"Eicheng 9",
    "sg:city":"Enzesfeld-Lindabrunn",
    "sg:orig_category":"Modellbau",
    "sg:phone":"+43 2256 811220",
    "sg:postcode":"2551",
    "sg:province":"Nieder\u00f6sterreich",
    "wof:name":"Webra Modellmotoren GesmbH & Co KG",
    "wof:placetype":"venue"
},
  "geometry": {"coordinates":[16.1844844818,47.9210205078],"type":"Point"}
}