{
  "type": "Feature",
  "properties": {
    "iso:country":"AT",
    "sg:address":"Nr 15",
    "sg:city":"Eitweg",
    "sg:orig_category":"Banken U Sparkassen",
    "sg:phone":"+43 4350 10030880",
    "sg:postcode":"9421",
    "sg:province":"K\u00e4rnten",
    "wof:name":"K\u00e4rntner Sparkasse AG",
    "wof:placetype":"venue"
},
  "geometry": {"coordinates":[14.8929834366,46.7751846313],"type":"Point"}
}