{
  "type": "Feature",
  "properties": {
    "iso:country":"AT",
    "sg:address":"Herreng 8",
    "sg:city":"Friesach",
    "sg:orig_category":"Polizei U Gendarmerie",
    "sg:phone":"+43 4359 1332122",
    "sg:postcode":"9360",
    "sg:province":"K\u00e4rnten",
    "wof:name":"Gendarmerie",
    "wof:placetype":"venue"
},
  "geometry": {"coordinates":[14.4062290192,46.9496574402],"type":"Point"}
}