{
  "type": "Feature",
  "properties": {
    "addr:full":"Braunhuberg 19 Wien Wien 1110",
    "addr:housenumber":"19",
    "addr:postcode":"1110",
    "addr:street":"Braunhuberg",
    "iso:country":"AT",
    "sg:address":"Braunhuberg 19",
    "sg:city":"Wien",
    "sg:classifiers":[
        {
            "category":"Restaurant",
            "type":"Food & Drink"
        }
    ],
    "sg:phone":"+43 1 7492311",
    "sg:postcode":"1110",
    "sg:province":"Wien",
    "sg:tags":[
        "pizzeria"
    ],
    "wof:name":"Perla Pizzeria",
    "wof:placetype":"venue"
},
  "geometry": {"coordinates":[16.4157314301,48.170337677],"type":"Point"}
}