{
  "type": "Feature",
  "properties": {
    "addr:full":"Schubertring 5 Wien Wien 1010",
    "addr:housenumber":"5",
    "addr:postcode":"1010",
    "addr:street":"Schubertring",
    "iso:country":"AT",
    "sg:address":"Schubertring 5",
    "sg:city":"Wien",
    "sg:orig_category":"Banken U Sparkassen",
    "sg:phone":"+43 5 0100",
    "sg:postcode":"1010",
    "sg:province":"Wien",
    "wof:name":"Finanzierungs-AG \u00d6sterreichischer Sparkassen",
    "wof:placetype":"venue"
},
  "geometry": {"coordinates":[16.3754692078,48.2021789551],"type":"Point"}
}