{
  "type": "Feature",
  "properties": {
    "iso:country":"AT",
    "sg:address":"Hauptstr 11",
    "sg:city":"Mautern in Steiermark",
    "sg:orig_category":"Installationsunternehmen",
    "sg:phone":"+43 4338 452359",
    "sg:postcode":"8774",
    "sg:province":"Steiermark",
    "wof:name":"Scher\u00fcbel KG",
    "wof:placetype":"venue"
},
  "geometry": {"coordinates":[14.8260993958,47.40001297],"type":"Point"}
}