{
  "type": "Feature",
  "properties": {
    "addr:full":"Schottenring 33 Wien Wien 1010",
    "addr:housenumber":"33",
    "addr:postcode":"1010",
    "addr:street":"Schottenring",
    "iso:country":"AT",
    "sg:address":"Schottenring 33",
    "sg:city":"Wien",
    "sg:orig_category":"Weiterbildungsinstitute M Allg U Berufl Bildungsangebot",
    "sg:phone":"+43 4313 16550",
    "sg:postcode":"1010",
    "sg:province":"Wien",
    "wof:name":"ONLINE Schulungs- und Beratungsges.mbH",
    "wof:placetype":"venue"
},
  "geometry": {"coordinates":[16.3693637848,48.2174072266],"type":"Point"}
}