{
  "type": "Feature",
  "properties": {
    "addr:full":"Strohbergg 21 Wien Wien 1120",
    "addr:housenumber":"21",
    "addr:postcode":"1120",
    "addr:street":"Strohbergg",
    "iso:country":"AT",
    "sg:address":"Strohbergg 21",
    "sg:city":"Wien",
    "sg:orig_category":"Architekten",
    "sg:phone":"+43 1 8042103",
    "sg:postcode":"1120",
    "sg:province":"Wien",
    "wof:name":"Gangemi Gerhard Arch Mag",
    "wof:placetype":"venue"
},
  "geometry": {"coordinates":[16.3121051788,48.1678466797],"type":"Point"}
}