{
  "type": "Feature",
  "properties": {
    "iso:country":"AT",
    "sg:city":"Kematen in Tirol",
    "sg:classifiers":[
        {
            "category":"Home & Garden",
            "subcategory":"Garden Supply",
            "type":"Retail Goods"
        }
    ],
    "sg:phone":"+43 4352 3281298",
    "sg:postcode":"6175",
    "sg:province":"Tirol",
    "sg:tags":[
        "schotter",
        "sand",
        "u"
    ],
    "wof:name":"Derfeser Betonwerk Ranggen GmbH",
    "wof:placetype":"venue"
},
  "geometry": {"coordinates":[11.2111520767,47.2575035095],"type":"Point"}
}