{
  "type": "Feature",
  "properties": {
    "addr:full":"Wasserwerkstr 42 Leibnitz Steiermark 8430",
    "addr:housenumber":"42",
    "addr:postcode":"8430",
    "addr:street":"Wasserwerkstr;Steiermark",
    "iso:country":"AT",
    "sg:address":"Wasserwerkstr 42",
    "sg:city":"Leibnitz",
    "sg:orig_category":"Autohandel",
    "sg:phone":"+43 3452 737730",
    "sg:postcode":"8430",
    "sg:province":"Steiermark",
    "wof:name":"Autohaus Wechtitsch",
    "wof:placetype":"venue"
},
  "geometry": {"coordinates":[15.559296608,46.7980690002],"type":"Point"}
}