{
  "type": "Feature",
  "properties": {
    "addr:full":"Sadrachstr 38 Innsbruck Tirol 6020",
    "addr:housenumber":"38",
    "addr:postcode":"6020",
    "addr:street":"Sadrachstr;Tirol",
    "iso:country":"AT",
    "sg:address":"Sadrachstr 38",
    "sg:city":"Innsbruck",
    "sg:orig_category":"Zelte / Vermietung",
    "sg:phone":"+43 512 281916",
    "sg:postcode":"6020",
    "sg:province":"Tirol",
    "wof:name":"M\u00e4hner Hans",
    "wof:placetype":"venue"
},
  "geometry": {"coordinates":[11.3671197891,47.2708053589],"type":"Point"}
}