{
  "type": "Feature",
  "properties": {
    "addr:full":"Weingartenstr 13 Ottensheim Ober\u00f6sterreich 4100",
    "addr:housenumber":"13",
    "addr:postcode":"4100",
    "addr:street":"Weingartenstr",
    "iso:country":"AT",
    "sg:address":"Weingartenstr 13",
    "sg:city":"Ottensheim",
    "sg:orig_category":"Autobeschriftungen",
    "sg:phone":"+43 4372 3484015",
    "sg:postcode":"4100",
    "sg:province":"Ober\u00f6sterreich",
    "sg:website":"humer-werbetechnik.at",
    "wof:name":"Humer Wilhelm",
    "wof:placetype":"venue"
},
  "geometry": {"coordinates":[14.1700897217,48.3412284851],"type":"Point"}
}