{
  "type": "Feature",
  "properties": {
    "addr:full":"Hatlerstr 69a Dornbirn Vorarlberg 6850",
    "addr:housenumber":"69a",
    "addr:postcode":"6850",
    "addr:street":"Hatlerstr",
    "iso:country":"AT",
    "sg:address":"Hatlerstr 69a",
    "sg:city":"Dornbirn",
    "sg:orig_category":"Maschinenbau",
    "sg:phone":"+43 5572 25610",
    "sg:postcode":"6850",
    "sg:province":"Vorarlberg",
    "wof:name":"Rangger Josef",
    "wof:placetype":"venue"
},
  "geometry": {"coordinates":[9.7320985794,47.398979187],"type":"Point"}
}