{
  "type": "Feature",
  "properties": {
    "addr:full":"Wallstr 31b Hard Vorarlberg 6971",
    "addr:housenumber":"31b",
    "addr:postcode":"6971",
    "addr:street":"Wallstr",
    "iso:country":"AT",
    "sg:address":"Wallstr 31b",
    "sg:city":"Hard",
    "sg:orig_category":"Schwimmbecken",
    "sg:phone":"+43 4366 43938555",
    "sg:postcode":"6971",
    "sg:province":"Vorarlberg",
    "wof:name":"Guderjahn Erdbewegung u Schwimmbadbau",
    "wof:placetype":"venue"
},
  "geometry": {"coordinates":[9.6998929977,47.4921417236],"type":"Point"}
}