{
  "type": "Feature",
  "properties": {
    "iso:country":"AT",
    "sg:address":"Franz Josef-Str 75",
    "sg:city":"Mistelbach",
    "sg:orig_category":"Ingenieurkonsulenten / Zivilingenieure",
    "sg:phone":"+43 2572 27020",
    "sg:postcode":"2130",
    "sg:province":"Nieder\u00f6sterreich",
    "sg:website":"vermessung.nanet.at",
    "wof:name":"Swatschina Gerhard Dipl-Ing",
    "wof:placetype":"venue"
},
  "geometry": {"coordinates":[16.5699386597,48.5732383728],"type":"Point"}
}