{
  "type": "Feature",
  "properties": {
    "addr:full":"Pfarrg 9 Imst Tirol 6460",
    "addr:housenumber":"9",
    "addr:postcode":"6460",
    "addr:street":"Pfarrg;Tirol",
    "iso:country":"AT",
    "sg:address":"Pfarrg 9",
    "sg:city":"Imst",
    "sg:orig_category":"Glasereien",
    "sg:phone":"+43 4354 1263338",
    "sg:postcode":"6460",
    "sg:province":"Tirol",
    "wof:name":"Glas & Kunst Kienel",
    "wof:placetype":"venue"
},
  "geometry": {"coordinates":[10.7388801575,47.242931366],"type":"Point"}
}