{
  "type": "Feature",
  "properties": {
    "addr:full":"Wagramer Str 149a Wien Wien 1220",
    "addr:postcode":"1220",
    "addr:street":"Str 149A",
    "iso:country":"AT",
    "sg:address":"Wagramer Str 149a",
    "sg:city":"Wien",
    "sg:orig_category":"Autohandel",
    "sg:phone":"+43 1 9614900",
    "sg:postcode":"1220",
    "sg:province":"Wien",
    "wof:name":"PEUGEOT WIEN",
    "wof:placetype":"venue"
},
  "geometry": {"coordinates":[16.4454307556,48.2527885437],"type":"Point"}
}