{
  "type": "Feature",
  "properties": {
    "iso:country":"AT",
    "sg:address":"Felberstr. 3",
    "sg:city":"Eggenburg",
    "sg:classifiers":[
        {
            "category":"Autos & Motor Vehicles",
            "subcategory":"Automobile Sales",
            "type":"Retail Goods"
        }
    ],
    "sg:phone":"+43 4329 842121",
    "sg:postcode":"3730",
    "sg:province":"Nieder\u00f6sterreich",
    "sg:tags":[
        "motor-cars"
    ],
    "wof:name":"RAIFFEISEN LAGERHAUS HORN REG. GES.MBH",
    "wof:placetype":"venue"
},
  "geometry": {"coordinates":[15.8220558167,48.6450424194],"type":"Point"}
}