{
  "type": "Feature",
  "properties": {
    "addr:full":"Vossenl\u00e4nde 1 Jennersdorf Burgenland 8380",
    "addr:housenumber":"1",
    "addr:postcode":"8380",
    "addr:street":"Vossenlaende",
    "iso:country":"AT",
    "sg:address":"Vossenl\u00e4nde 1",
    "sg:city":"Jennersdorf",
    "sg:orig_category":"Frottierwaren",
    "sg:phone":"+43 4333 294000",
    "sg:postcode":"8380",
    "sg:province":"Burgenland",
    "wof:name":"Vossen AG & Co KG",
    "wof:placetype":"venue"
},
  "geometry": {"coordinates":[16.1477832794,46.932762146],"type":"Point"}
}