{
  "type": "Feature",
  "properties": {
    "iso:country":"AT",
    "sg:address":"Arzberg 81",
    "sg:city":"Reichraming",
    "sg:orig_category":"Gewerbeparks",
    "sg:phone":"+43 4372 5420580",
    "sg:postcode":"4462",
    "sg:province":"Ober\u00f6sterreich",
    "wof:name":"Technologie- u Dienstleistungszentrum Ennstal",
    "wof:placetype":"venue"
},
  "geometry": {"coordinates":[14.4813766479,47.8970794678],"type":"Point"}
}