{
  "type": "Feature",
  "properties": {
    "addr:full":"Obere Dorfstr 6 Stra\u00df in Steiermark Steiermark 8472",
    "addr:housenumber":"6",
    "addr:postcode":"8472",
    "addr:street":"Obere Dorfstr",
    "iso:country":"AT",
    "sg:address":"Obere Dorfstr 6",
    "sg:city":"Stra\u00df in Steiermark",
    "sg:orig_category":"Gemeinden",
    "sg:phone":"+43 3453 2477",
    "sg:postcode":"8472",
    "sg:province":"Steiermark",
    "wof:name":"Gemeindeamt Vogau",
    "wof:placetype":"venue"
},
  "geometry": {"coordinates":[15.6023960114,46.7315063477],"type":"Point"}
}