{
  "type": "Feature",
  "properties": {
    "iso:country":"AT",
    "sg:address":"Simmeringer Hauptstr 261",
    "sg:city":"Wien",
    "sg:orig_category":"Autohandel",
    "sg:phone":"+43 1 760770",
    "sg:postcode":"1110",
    "sg:province":"Wien",
    "wof:name":"AHS - Autohandels und Service GmbH",
    "wof:placetype":"venue"
},
  "geometry": {"coordinates":[16.4302082062,48.1611976624],"type":"Point"}
}