{
  "type": "Feature",
  "properties": {
    "addr:full":"Nr 35 Passail Steiermark 8162",
    "addr:postcode":"8162",
    "addr:street":"Nr",
    "iso:country":"AT",
    "sg:address":"Nr 35",
    "sg:city":"Passail",
    "sg:orig_category":"Friseure U Frisiersalons",
    "sg:phone":"+43 3179 23177",
    "sg:postcode":"8162",
    "sg:province":"Steiermark",
    "wof:name":"Haarstudio M",
    "wof:placetype":"venue"
},
  "geometry": {"coordinates":[15.5150938034,47.2814102173],"type":"Point"}
}