{
  "type": "Feature",
  "properties": {
    "iso:country":"AT",
    "sg:address":"Albert-Schweitzer-Str 4",
    "sg:city":"Wels",
    "sg:orig_category":"Werbegrafik- U Grafik-Design",
    "sg:phone":"+43 4372 4266799",
    "sg:postcode":"4600",
    "sg:province":"Ober\u00f6sterreich",
    "wof:name":"Fleischhacker Walter",
    "wof:placetype":"venue"
},
  "geometry": {"coordinates":[13.9942617416,48.1620521545],"type":"Point"}
}