{
  "type": "Feature",
  "properties": {
    "iso:country":"AT",
    "sg:address":"Laudong 34",
    "sg:city":"Wien",
    "sg:orig_category":"Psychologen",
    "sg:phone":"+43 1 4095419",
    "sg:postcode":"1080",
    "sg:province":"Wien",
    "wof:name":"B\u00f6ck Gerda Mag",
    "wof:placetype":"venue"
},
  "geometry": {"coordinates":[16.3476448059,48.2133178711],"type":"Point"}
}