{
  "type": "Feature",
  "properties": {
    "addr:full":"Rainsberg 115 Reichenfels K\u00e4rnten 9463",
    "addr:housenumber":"115",
    "addr:postcode":"9463",
    "addr:street":"Rainsberg;Kaernten",
    "iso:country":"AT",
    "sg:address":"Rainsberg 115",
    "sg:city":"Reichenfels",
    "sg:classifiers":[
        {
            "category":"Travel",
            "subcategory":"Hotels & Motels",
            "type":"Entertainment"
        }
    ],
    "sg:phone":"+43 4359 2777",
    "sg:postcode":"9463",
    "sg:province":"K\u00e4rnten",
    "wof:name":"Hotel Rainsberghof GesmbH",
    "wof:placetype":"venue"
},
  "geometry": {"coordinates":[14.7358083725,46.9987220764],"type":"Point"}
}