{
  "type": "Feature",
  "properties": {
    "iso:country":"AT",
    "sg:address":"Kleinveitsch 4",
    "sg:city":"Dorf Veitsch",
    "sg:classifiers":[
        {
            "category":"Shopping",
            "subcategory":"Computers & Home Electronics",
            "type":"Retail Goods"
        }
    ],
    "sg:phone":"+43 3856 2252",
    "sg:postcode":"8663",
    "sg:province":"Steiermark",
    "sg:tags":[
        "cable"
    ],
    "wof:name":"Elektro Krug Ges.m.b.H.",
    "wof:placetype":"venue"
},
  "geometry": {"coordinates":[15.4944038391,47.5799293518],"type":"Point"}
}