{
  "type": "Feature",
  "properties": {
    "addr:full":"Rablstr 3 Wels Ober\u00f6sterreich 4600",
    "addr:housenumber":"3",
    "addr:postcode":"4600",
    "addr:street":"Rablstr;Oberoesterreich",
    "iso:country":"AT",
    "sg:address":"Rablstr 3",
    "sg:city":"Wels",
    "sg:classifiers":[
        {
            "category":"Military Area",
            "subcategory":"Army Base",
            "type":"Public Place"
        }
    ],
    "sg:phone":"+43 7242 69142",
    "sg:postcode":"4600",
    "sg:province":"Ober\u00f6sterreich",
    "sg:tags":[
        "shop"
    ],
    "wof:name":"Army Shop",
    "wof:placetype":"venue"
},
  "geometry": {"coordinates":[14.0247173309,48.1614341736],"type":"Point"}
}