{
  "type": "Feature",
  "properties": {
    "addr:full":"Nr 20 Hirschbach im M\u00fchlkreis Ober\u00f6sterreich 4242",
    "addr:postcode":"4242",
    "addr:street":"Nr 20",
    "iso:country":"AT",
    "sg:address":"Nr 20",
    "sg:city":"Hirschbach im M\u00fchlkreis",
    "sg:orig_category":"Transportunternehmen",
    "sg:phone":"+43 4379 48232",
    "sg:postcode":"4242",
    "sg:province":"Ober\u00f6sterreich",
    "wof:name":"Rauch Martin",
    "wof:placetype":"venue"
},
  "geometry": {"coordinates":[14.4116802216,48.4884796143],"type":"Point"}
}