{
  "type": "Feature",
  "properties": {
    "addr:full":"Rudolf-Virchow-Str 8 Wien Wien 1210",
    "addr:housenumber":"8",
    "addr:postcode":"1210",
    "addr:street":"Rudolf-Virchow-Str",
    "iso:country":"AT",
    "sg:address":"Rudolf-Virchow-Str 8",
    "sg:city":"Wien",
    "sg:orig_category":"Behinderungen / Leben Mit Behinderungen",
    "sg:phone":"+43 1 2717461",
    "sg:postcode":"1210",
    "sg:province":"Wien",
    "wof:name":"Jugend am Werk",
    "wof:placetype":"venue"
},
  "geometry": {"coordinates":[16.3871593475,48.2725563049],"type":"Point"}
}