{
  "type": "Feature",
  "properties": {
    "iso:country":"AT",
    "sg:address":"Aug 46",
    "sg:city":"Leibnitz",
    "sg:classifiers":[
        {
            "category":"Restaurant",
            "type":"Food & Drink"
        }
    ],
    "sg:phone":"+43 3452 86358",
    "sg:postcode":"8430",
    "sg:province":"Steiermark",
    "sg:tags":[
        "pizzeria"
    ],
    "wof:name":"Ristorante-Pizzeria Da Gino",
    "wof:placetype":"venue"
},
  "geometry": {"coordinates":[15.5377645493,46.7811355591],"type":"Point"}
}