{
  "type": "Feature",
  "properties": {
    "addr:full":"Nr 59 Schleinbach Nieder\u00f6sterreich 2123",
    "addr:postcode":"2123",
    "addr:street":"Nr",
    "iso:country":"AT",
    "sg:address":"Nr 59",
    "sg:city":"Schleinbach",
    "sg:orig_category":"Banken U Sparkassen",
    "sg:phone":"+43 2245 89241",
    "sg:postcode":"2123",
    "sg:province":"Nieder\u00f6sterreich",
    "wof:name":"Raiffeisenkasse Wolkersdorf regGenmbH",
    "wof:placetype":"venue"
},
  "geometry": {"coordinates":[16.4917793274,48.446018219],"type":"Point"}
}