{
  "type": "Feature",
  "properties": {
    "addr:full":"Stefan-Zweig-Str 3 Zell am See Salzburg 5700",
    "addr:housenumber":"3",
    "addr:postcode":"5700",
    "addr:street":"Stefan-Zweig-Str;Salzburg",
    "iso:country":"AT",
    "sg:address":"Stefan-Zweig-Str 3",
    "sg:city":"Zell am See",
    "sg:classifiers":[
        {
            "category":"Travel",
            "subcategory":"Hotels & Motels",
            "type":"Entertainment"
        }
    ],
    "sg:phone":"+43 6542 567370",
    "sg:postcode":"5700",
    "sg:province":"Salzburg",
    "wof:name":"Landhaus Zell am See",
    "wof:placetype":"venue"
},
  "geometry": {"coordinates":[12.7985019684,47.2997589111],"type":"Point"}
}