{
  "type": "Feature",
  "properties": {
    "addr:full":"Salzachtal Bundesstr Hallein Salzburg 5400",
    "addr:postcode":"5400",
    "iso:country":"AT",
    "sg:address":"Salzachtal Bundesstr",
    "sg:city":"Hallein",
    "sg:orig_category":"Autohandel",
    "sg:phone":"+43 6245 84060",
    "sg:postcode":"5400",
    "sg:province":"Salzburg",
    "wof:name":"Opel Hallein",
    "wof:placetype":"venue"
},
  "geometry": {"coordinates":[13.0773420334,47.6976051331],"type":"Point"}
}