{
  "type": "Feature",
  "properties": {
    "addr:full":"Stammersdorfer Str 71 Wien Wien 1210",
    "addr:postcode":"1210",
    "addr:street":"Str 71",
    "iso:country":"AT",
    "sg:address":"Stammersdorfer Str 71",
    "sg:city":"Wien",
    "sg:orig_category":"Galerien",
    "sg:phone":"+43 1 2901060",
    "sg:postcode":"1210",
    "sg:province":"Wien",
    "wof:name":"Galerie am Weinkeller",
    "wof:placetype":"venue"
},
  "geometry": {"coordinates":[16.4139518738,48.3015861511],"type":"Point"}
}