{
  "type": "Feature",
  "properties": {
    "addr:full":"\u00d6tscherstr 14 Mitterbach am Erlaufsee Nieder\u00f6sterreich 3224",
    "addr:housenumber":"14",
    "addr:postcode":"3224",
    "addr:street":"Oetscherstr",
    "iso:country":"AT",
    "sg:address":"\u00d6tscherstr 14",
    "sg:city":"Mitterbach am Erlaufsee",
    "sg:orig_category":"Forstverwaltungen",
    "sg:phone":"+43 3882 24050",
    "sg:postcode":"3224",
    "sg:province":"Nieder\u00f6sterreich",
    "wof:name":"Hagengut",
    "wof:placetype":"venue"
},
  "geometry": {"coordinates":[15.2949075699,47.814250946],"type":"Point"}
}