{
  "type": "Feature",
  "properties": {
    "addr:full":"Nr 228 Pinkafeld Burgenland 7423",
    "addr:postcode":"7423",
    "addr:street":"Nr",
    "iso:country":"AT",
    "sg:address":"Nr 228",
    "sg:city":"Pinkafeld",
    "sg:orig_category":"Transportunternehmen",
    "sg:phone":"+43 3359 2204",
    "sg:postcode":"7423",
    "sg:province":"Burgenland",
    "wof:name":"Seier GesmbH & Co KG",
    "wof:placetype":"venue"
},
  "geometry": {"coordinates":[16.124250412,47.3718299866],"type":"Point"}
}