{
  "type": "Feature",
  "properties": {
    "addr:full":"Triester Str 71 Wien Wien 1100",
    "addr:postcode":"1100",
    "addr:street":"Str 71",
    "iso:country":"AT",
    "sg:address":"Triester Str 71",
    "sg:city":"Wien",
    "sg:orig_category":"Elektroinstallationsunternehmen",
    "sg:phone":"+43 4316 0635350",
    "sg:postcode":"1100",
    "sg:province":"Wien",
    "wof:name":"HSG Heizung-Sanit\u00e4r & Gebrechendienst GesmbH",
    "wof:placetype":"venue"
},
  "geometry": {"coordinates":[16.3518199921,48.1716842651],"type":"Point"}
}