{
  "type": "Feature",
  "properties": {
    "addr:full":"Hauptstr 121 Velm-G\u00f6tzendorf Nieder\u00f6sterreich 2245",
    "addr:housenumber":"121",
    "addr:postcode":"2245",
    "addr:street":"Hauptstr;Niederoesterreich",
    "iso:country":"AT",
    "sg:address":"Hauptstr 121",
    "sg:city":"Velm-G\u00f6tzendorf",
    "sg:orig_category":"Banken U Sparkassen",
    "sg:phone":"+43 4325 3885427",
    "sg:postcode":"2245",
    "sg:province":"Nieder\u00f6sterreich",
    "wof:name":"Raiffeisenbank Zistersdorf-D\u00fcrnkrut regGenmbH",
    "wof:placetype":"venue"
},
  "geometry": {"coordinates":[16.7856903076,48.4703407288],"type":"Point"}
}