{
  "type": "Feature",
  "properties": {
    "iso:country":"AT",
    "sg:address":"Nr 238",
    "sg:city":"Aflenz Kurort",
    "sg:orig_category":"Forstverwaltungen",
    "sg:phone":"+43 3861 22150",
    "sg:postcode":"8623",
    "sg:province":"Steiermark",
    "wof:name":"Forstgut Aflenz d Pensionsversicherungsanstalt d Angestellten Wien",
    "wof:placetype":"venue"
},
  "geometry": {"coordinates":[15.2384824753,47.5437736511],"type":"Point"}
}