{
  "type": "Feature",
  "properties": {
    "iso:country":"AT",
    "sg:address":"Seestr 3",
    "sg:city":"Fuschl am See",
    "sg:orig_category":"Pensionen / Privatzimmer",
    "sg:phone":"+43 6226 82700",
    "sg:postcode":"5330",
    "sg:province":"Salzburg",
    "wof:name":"Pension Tannhof",
    "wof:placetype":"venue"
},
  "geometry": {"coordinates":[13.3004894257,47.7969818115],"type":"Point"}
}