{
  "type": "Feature",
  "properties": {
    "iso:country":"AT",
    "sg:address":"Nr 84",
    "sg:city":"Arnoldstein",
    "sg:orig_category":"Transportunternehmen",
    "sg:phone":"+43 4255 3126",
    "sg:postcode":"9601",
    "sg:province":"K\u00e4rnten",
    "wof:name":"Gallob Herbert",
    "wof:placetype":"venue"
},
  "geometry": {"coordinates":[13.701584816,46.5500564575],"type":"Point"}
}