{
  "type": "Feature",
  "properties": {
    "addr:full":"Eggenfelder Str 1 Gratkorn Steiermark 8101",
    "addr:housenumber":"1",
    "addr:postcode":"8101",
    "addr:street":"Str",
    "iso:country":"AT",
    "sg:address":"Eggenfelder Str 1",
    "sg:city":"Gratkorn",
    "sg:orig_category":"Steuerberatung",
    "sg:phone":"+43 4331 2422480",
    "sg:postcode":"8101",
    "sg:province":"Steiermark",
    "wof:name":"Muhr Margareta",
    "wof:placetype":"venue"
},
  "geometry": {"coordinates":[15.3331975937,47.1435394287],"type":"Point"}
}