{
  "type": "Feature",
  "properties": {
    "iso:country":"AT",
    "sg:address":"Stadlerstr 34",
    "sg:city":"Linz",
    "sg:orig_category":"Elektroinstallationsunternehmen",
    "sg:phone":"+43 732 330107",
    "sg:postcode":"4020",
    "sg:province":"Ober\u00f6sterreich",
    "wof:name":"Trinkl Gerhard Elektro GesmbH",
    "wof:placetype":"venue"
},
  "geometry": {"coordinates":[14.2893743515,48.2696838379],"type":"Point"}
}