{
  "type": "Feature",
  "properties": {
    "addr:full":"Adamg 5 Innsbruck Tirol 6020",
    "addr:housenumber":"5",
    "addr:postcode":"6020",
    "addr:street":"Adamg;Tirol",
    "iso:country":"AT",
    "sg:address":"Adamg 5",
    "sg:city":"Innsbruck",
    "sg:orig_category":"Immobilienmakler",
    "sg:phone":"+43 512 282222",
    "sg:postcode":"6020",
    "sg:province":"Tirol",
    "wof:name":"L\u00e4sser & Liebl Immobilien OEG",
    "wof:placetype":"venue"
},
  "geometry": {"coordinates":[11.3983058929,47.2635002136],"type":"Point"}
}