{
  "type": "Feature",
  "properties": {
    "addr:full":"Neue Heimat 16 Zell am See Salzburg 5700",
    "addr:housenumber":"16",
    "addr:postcode":"5700",
    "addr:street":"Neue Heimat;Salzburg",
    "iso:country":"AT",
    "sg:address":"Neue Heimat 16",
    "sg:city":"Zell am See",
    "sg:orig_category":"Botendienste",
    "sg:phone":"+43 676 3128290",
    "sg:postcode":"5700",
    "sg:province":"Salzburg",
    "wof:name":"Sitzenfrei Maria",
    "wof:placetype":"venue"
},
  "geometry": {"coordinates":[12.7903528214,47.3031387329],"type":"Point"}
}