{
  "type": "Feature",
  "properties": {
    "iso:country":"AT",
    "sg:address":"Altstadt 43-47",
    "sg:city":"Bruck an der Leitha",
    "sg:orig_category":"Autoreparatur",
    "sg:phone":"+43 4321 62622760",
    "sg:postcode":"2460",
    "sg:province":"Nieder\u00f6sterreich",
    "sg:website":"csebits.at",
    "wof:name":"Csebits GmbH",
    "wof:placetype":"venue"
},
  "geometry": {"coordinates":[16.7733535767,48.0217781067],"type":"Point"}
}