{
  "type": "Feature",
  "properties": {
    "iso:country":"AT",
    "sg:address":"Alte Bundesstr 23",
    "sg:city":"Haiming",
    "sg:orig_category":"Unterhaltungselektronik / Reparatur",
    "sg:phone":"+43 4352 6688309",
    "sg:postcode":"6425",
    "sg:province":"Tirol",
    "wof:name":"Golser Manfred",
    "wof:placetype":"venue"
},
  "geometry": {"coordinates":[10.8826999664,47.2572860718],"type":"Point"}
}