{
  "type": "Feature",
  "properties": {
    "addr:full":"Franz W Scherer-Str 34 Bergheim Salzburg 5101",
    "addr:housenumber":"34",
    "addr:postcode":"5101",
    "addr:street":"Salzburg",
    "iso:country":"AT",
    "sg:address":"Franz W Scherer-Str 34",
    "sg:city":"Bergheim",
    "sg:orig_category":"Transportunternehmen",
    "sg:phone":"+43 662 4674",
    "sg:postcode":"5101",
    "sg:province":"Salzburg",
    "wof:name":"Transconti Transport GmbH & Co KG",
    "wof:placetype":"venue"
},
  "geometry": {"coordinates":[13.06199646,47.832862854],"type":"Point"}
}