{
  "type": "Feature",
  "properties": {
    "addr:full":"Sattelberg 32 Klaus-Weiler Vorarlberg 6833",
    "addr:housenumber":"32",
    "addr:postcode":"6833",
    "addr:street":"Sattelberg",
    "iso:country":"AT",
    "sg:address":"Sattelberg 32",
    "sg:city":"Klaus-Weiler",
    "sg:orig_category":"Maler, Anstreicher U Lackierer",
    "sg:phone":"+43 4355 2356300",
    "sg:postcode":"6833",
    "sg:province":"Vorarlberg",
    "wof:name":"Sch\u00f6ch Malerbetrieb",
    "wof:placetype":"venue"
},
  "geometry": {"coordinates":[9.6382780075,47.3103294373],"type":"Point"}
}