{
  "type": "Feature",
  "properties": {
    "addr:full":"Druckerg 40 Bregenz Vorarlberg 6900",
    "addr:housenumber":"40",
    "addr:postcode":"6900",
    "addr:street":"Druckerg",
    "iso:country":"AT",
    "sg:address":"Druckerg 40",
    "sg:city":"Bregenz",
    "sg:orig_category":"Rettungsdienste",
    "sg:phone":"+43 5574 617000",
    "sg:postcode":"6900",
    "sg:province":"Vorarlberg",
    "wof:name":"\u00f6sterreichische Wasser-Rettung",
    "wof:placetype":"venue"
},
  "geometry": {"coordinates":[9.7302923203,47.5047874451],"type":"Point"}
}