{
  "type": "Feature",
  "properties": {
    "addr:full":"Nr 17 Grainbrunn Nieder\u00f6sterreich 3524",
    "addr:postcode":"3524",
    "addr:street":"Nr 17 Grainbrunn",
    "iso:country":"AT",
    "sg:address":"Nr 17",
    "sg:city":"Grainbrunn",
    "sg:orig_category":"Banken U Sparkassen",
    "sg:phone":"+43 2877 8258",
    "sg:postcode":"3524",
    "sg:province":"Nieder\u00f6sterreich",
    "wof:name":"Raiffeisenkasse Ottenschlag-Martinsberg regGenmbH",
    "wof:placetype":"venue"
},
  "geometry": {"coordinates":[15.2282648087,48.4819641113],"type":"Point"}
}