{
  "type": "Feature",
  "properties": {
    "addr:full":"Ringstr 302 Bad Gleichenberg Steiermark 8344",
    "addr:housenumber":"302",
    "addr:postcode":"8344",
    "iso:country":"AT",
    "sg:address":"Ringstr 302",
    "sg:city":"Bad Gleichenberg",
    "sg:orig_category":"Pensionen / Privatzimmer",
    "sg:phone":"+43 4331 592514",
    "sg:postcode":"8344",
    "sg:province":"Steiermark",
    "wof:name":"Genser Alois",
    "wof:placetype":"venue"
},
  "geometry": {"coordinates":[15.9055433273,46.8777656555],"type":"Point"}
}