{
  "type": "Feature",
  "properties": {
    "addr:full":"Niederhofstr 13 Wien Wien 1120",
    "addr:housenumber":"13",
    "addr:postcode":"1120",
    "addr:street":"Niederhofstr",
    "iso:country":"AT",
    "sg:address":"Niederhofstr 13",
    "sg:city":"Wien",
    "sg:orig_category":"Fitnesscenter",
    "sg:phone":"+43 1 8151823",
    "sg:postcode":"1120",
    "sg:province":"Wien",
    "wof:name":"Slender-Two-Studio Elisabeth Warnung",
    "wof:placetype":"venue"
},
  "geometry": {"coordinates":[16.3346195221,48.1809883118],"type":"Point"}
}