{
  "type": "Feature",
  "properties": {
    "iso:country":"AT",
    "sg:address":"Oberndorf 105",
    "sg:city":"Kirchbichl",
    "sg:classifiers":[
        {
            "category":"Organizations",
            "subcategory":"Non-profit Organization",
            "type":"Services"
        }
    ],
    "sg:phone":"+43 5332 871750",
    "sg:postcode":"6322",
    "sg:province":"Tirol",
    "sg:tags":[
        "alarm",
        "system"
    ],
    "sg:website":"ep.pellegrini.de.vu",
    "wof:name":"Ing. Ludwig Pellegrini",
    "wof:placetype":"venue"
},
  "geometry": {"coordinates":[12.0850296021,47.5078582764],"type":"Point"}
}