{
  "type": "Feature",
  "properties": {
    "iso:country":"AT",
    "sg:address":"Am W\u00fcstefeldgrund 9",
    "sg:city":"Trofaiach",
    "sg:orig_category":"Weine / Einzelhandel",
    "sg:phone":"+43 676 7053656",
    "sg:postcode":"8793",
    "sg:province":"Steiermark",
    "wof:name":"Felchlin Connection",
    "wof:placetype":"venue"
},
  "geometry": {"coordinates":[14.969628334,47.4129219055],"type":"Point"}
}