{
  "type": "Feature",
  "properties": {
    "addr:full":"Dornleiten 19 Hollenstein an der Ybbs Nieder\u00f6sterreich 3343",
    "addr:housenumber":"19",
    "addr:postcode":"3343",
    "addr:street":"Dornleiten",
    "iso:country":"AT",
    "sg:address":"Dornleiten 19",
    "sg:city":"Hollenstein an der Ybbs",
    "sg:orig_category":"Schlossereien",
    "sg:phone":"+43 4374 4570070",
    "sg:postcode":"3343",
    "sg:province":"Nieder\u00f6sterreich",
    "wof:name":"Schneiber Andreas",
    "wof:placetype":"venue"
},
  "geometry": {"coordinates":[14.7682542801,47.787776947],"type":"Point"}
}