{
  "type": "Feature",
  "properties": {
    "iso:country":"AT",
    "sg:address":"Auf der Gries 1",
    "sg:city":"Radenthein",
    "sg:orig_category":"Feuerwehren",
    "sg:phone":"+43 4246 2332",
    "sg:postcode":"9545",
    "sg:province":"K\u00e4rnten",
    "wof:name":"Freiwillige Feuerwehr Radenthein",
    "wof:placetype":"venue"
},
  "geometry": {"coordinates":[13.7050790787,46.8011779785],"type":"Point"}
}