{
  "type": "Feature",
  "properties": {
    "addr:full":"Rathausstr 1 Andorf Ober\u00f6sterreich 4770",
    "addr:housenumber":"1",
    "addr:postcode":"4770",
    "addr:street":"Rathausstr",
    "iso:country":"AT",
    "sg:address":"Rathausstr 1",
    "sg:city":"Andorf",
    "sg:orig_category":"Banken U Sparkassen",
    "sg:phone":"+43 4350 10040131",
    "sg:postcode":"4770",
    "sg:province":"Ober\u00f6sterreich",
    "wof:name":"Allgemeine Sparkasse Ober\u00f6sterreich Bank AG",
    "wof:placetype":"venue"
},
  "geometry": {"coordinates":[13.5735273361,48.3713340759],"type":"Point"}
}