{
  "type": "Feature",
  "properties": {
    "iso:country":"AT",
    "sg:address":"Apetloner Str 28",
    "sg:city":"Illmitz",
    "sg:orig_category":"Pensionen / Privatzimmer",
    "sg:phone":"+43 2175 3293",
    "sg:postcode":"7142",
    "sg:province":"Burgenland",
    "wof:name":"Egermann Johann",
    "wof:placetype":"venue"
},
  "geometry": {"coordinates":[16.8065090179,47.7609558105],"type":"Point"}
}