{
  "type": "Feature",
  "properties": {
    "addr:full":"Pustertaler Str Lienz Tirol 9900",
    "addr:postcode":"9900",
    "addr:street":"Str Lienz Tirol",
    "iso:country":"AT",
    "sg:address":"Pustertaler Str",
    "sg:city":"Lienz",
    "sg:orig_category":"Autohandel",
    "sg:phone":"+43 4348 5267233",
    "sg:postcode":"9900",
    "sg:province":"Tirol",
    "wof:name":"Brandst\u00e4tter Handels- u ReparaturgesmbH",
    "wof:placetype":"venue"
},
  "geometry": {"coordinates":[12.754699707,46.8192367554],"type":"Point"}
}