{
  "type": "Feature",
  "properties": {
    "addr:full":"Li\u00df 244 Jerzens Tirol 6474",
    "addr:housenumber":"244",
    "addr:postcode":"6474",
    "addr:street":"Liss;Tirol",
    "iso:country":"AT",
    "sg:address":"Li\u00df 244",
    "sg:city":"Jerzens",
    "sg:classifiers":[
        {
            "category":"Travel",
            "subcategory":"Hotels & Motels",
            "type":"Entertainment"
        }
    ],
    "sg:phone":"+43 4354 14861000",
    "sg:postcode":"6474",
    "sg:province":"Tirol",
    "wof:name":"Andy Sporthotel Inh Andreas Kirschner",
    "wof:placetype":"venue"
},
  "geometry": {"coordinates":[10.7465543747,47.1491737366],"type":"Point"}
}