{
  "type": "Feature",
  "properties": {
    "addr:full":"Bahnhofstr 6 Schwanenstadt Ober\u00f6sterreich 4690",
    "addr:housenumber":"6",
    "addr:postcode":"4690",
    "addr:street":"Bahnhofstr",
    "iso:country":"AT",
    "sg:address":"Bahnhofstr 6",
    "sg:city":"Schwanenstadt",
    "sg:orig_category":"Zahntechnische Laboratorien",
    "sg:phone":"+43 767380580",
    "sg:postcode":"4690",
    "sg:province":"Ober\u00f6sterreich",
    "wof:name":"Breuer Franz Thomas",
    "wof:placetype":"venue"
},
  "geometry": {"coordinates":[13.7706794739,48.0552101135],"type":"Point"}
}