{
  "type": "Feature",
  "properties": {
    "iso:country":"AT",
    "sg:address":"Amerling 116",
    "sg:city":"Kramsach",
    "sg:orig_category":"Stukkateure U Trockenausbauer",
    "sg:phone":"+43 676 842185200",
    "sg:postcode":"6233",
    "sg:province":"Tirol",
    "wof:name":"KF Trockenbau Felderer KEG",
    "wof:placetype":"venue"
},
  "geometry": {"coordinates":[11.8733320236,47.4367485046],"type":"Point"}
}