{
  "type": "Feature",
  "properties": {
    "addr:full":"Au\u00dferrain 6 Neustift im Stubaital Tirol 6167",
    "addr:housenumber":"6",
    "addr:postcode":"6167",
    "addr:street":"Ausserrain;Tirol",
    "iso:country":"AT",
    "sg:address":"Au\u00dferrain 6",
    "sg:city":"Neustift im Stubaital",
    "sg:classifiers":[
        {
            "category":"Travel",
            "subcategory":"Hotels & Motels",
            "type":"Entertainment"
        }
    ],
    "sg:phone":"+43 4352 2625150",
    "sg:postcode":"6167",
    "sg:province":"Tirol",
    "wof:name":"Hotel Cappella",
    "wof:placetype":"venue"
},
  "geometry": {"coordinates":[11.3075504303,47.1104850769],"type":"Point"}
}