{
  "type": "Feature",
  "properties": {
    "iso:country":"AT",
    "sg:address":"Perfektastrasse 73",
    "sg:city":"Wien",
    "sg:classifiers":[
        {
            "category":"Home & Garden",
            "subcategory":"Building Materials",
            "type":"Retail Goods"
        }
    ],
    "sg:phone":"+43 1 86517170",
    "sg:postcode":"1230",
    "sg:province":"Wien",
    "sg:tags":[
        "granite",
        "syenite"
    ],
    "sg:website":"aufhauser.at",
    "wof:name":"Aufhauser Natursteinwerk GmbH",
    "wof:placetype":"venue"
},
  "geometry": {"coordinates":[16.3083972931,48.1363296509],"type":"Point"}
}