{
  "type": "Feature",
  "properties": {
    "addr:full":"Nr 52 Bad Tatzmannsdorf Burgenland 7431",
    "addr:housenumber":"52",
    "addr:postcode":"7431",
    "addr:street":"Nr",
    "iso:country":"AT",
    "sg:address":"Nr 52",
    "sg:city":"Bad Tatzmannsdorf",
    "sg:orig_category":"Physiotherapie",
    "sg:phone":"+43 664 4018832",
    "sg:postcode":"7431",
    "sg:province":"Burgenland",
    "wof:name":"Ochsenhofer Gerald Dipl-PT",
    "wof:placetype":"venue"
},
  "geometry": {"coordinates":[16.229429245,47.3325119019],"type":"Point"}
}