{
  "type": "Feature",
  "properties": {
    "addr:full":"Burgfried 85 Gnas Steiermark 8342",
    "addr:housenumber":"85",
    "addr:postcode":"8342",
    "addr:street":"Burgfried",
    "iso:country":"AT",
    "sg:address":"Burgfried 85",
    "sg:city":"Gnas",
    "sg:classifiers":[
        {
            "category":"Real Estate",
            "subcategory":"Real Estate Services",
            "type":"Services"
        }
    ],
    "sg:phone":"+43 3151 8409",
    "sg:postcode":"8342",
    "sg:province":"Steiermark",
    "sg:tags":[
        "development",
        "management"
    ],
    "sg:website":"topos.at",
    "wof:name":"TOPOS Liegenschaftsverwaltung AG",
    "wof:placetype":"venue"
},
  "geometry": {"coordinates":[15.8180675507,46.8816986084],"type":"Point"}
}