{
  "type": "Feature",
  "properties": {
    "iso:country":"AT",
    "sg:address":"Franz-H\u00fctter-G 1A",
    "sg:city":"M\u00fcnchendorf",
    "sg:orig_category":"Installationsunternehmen",
    "sg:phone":"+43 4322 597601",
    "sg:postcode":"2482",
    "sg:province":"Nieder\u00f6sterreich",
    "wof:name":"Peischl Walter GesmbH",
    "wof:placetype":"venue"
},
  "geometry": {"coordinates":[153.43200683590001,-28.5555095673],"type":"Point"}
}