{
  "type": "Feature",
  "properties": {
    "addr:full":"Haller Str 75 Innsbruck Tirol 6020",
    "addr:postcode":"6020",
    "addr:street":"Str 75;Tirol",
    "iso:country":"AT",
    "sg:address":"Haller Str 75",
    "sg:city":"Innsbruck",
    "sg:orig_category":"Badezimmer U Badezimmereinrichtungen",
    "sg:phone":"+43 4351 2206000",
    "sg:postcode":"6020",
    "sg:province":"Tirol",
    "wof:name":"ceravit b\u00e4der & fliesen GmbH",
    "wof:placetype":"venue"
},
  "geometry": {"coordinates":[11.4176807404,47.2790794373],"type":"Point"}
}