{
  "type": "Feature",
  "properties": {
    "addr:full":"Seilerst\u00e4tte 24 Wien Wien 1010",
    "addr:housenumber":"24",
    "addr:postcode":"1010",
    "addr:street":"Seilerstaette",
    "iso:country":"AT",
    "sg:address":"Seilerst\u00e4tte 24",
    "sg:city":"Wien",
    "sg:orig_category":"Werbeagenturen",
    "sg:phone":"+43 1 5139337",
    "sg:postcode":"1010",
    "sg:province":"Wien",
    "wof:name":"c satek - Christian Satek Werbeagentur GesmbH",
    "wof:placetype":"venue"
},
  "geometry": {"coordinates":[16.3740367889,48.2046051025],"type":"Point"}
}