{
  "type": "Feature",
  "properties": {
    "addr:full":"Rebeng 21b Hard Vorarlberg 6971",
    "addr:housenumber":"21b",
    "addr:postcode":"6971",
    "addr:street":"Rebeng",
    "iso:country":"AT",
    "sg:address":"Rebeng 21b",
    "sg:city":"Hard",
    "sg:orig_category":"Friseure U Frisiersalons",
    "sg:phone":"+43 5574 61116",
    "sg:postcode":"6971",
    "sg:province":"Vorarlberg",
    "wof:name":"Beauty Team",
    "wof:placetype":"venue"
},
  "geometry": {"coordinates":[9.7019033432,47.4851837158],"type":"Point"}
}