{
  "type": "Feature",
  "properties": {
    "addr:full":"Nr 5 Faistenau Salzburg 5324",
    "addr:postcode":"5324",
    "addr:street":"Nr;Faistenau",
    "iso:country":"AT",
    "sg:address":"Nr 5",
    "sg:city":"Faistenau",
    "sg:classifiers":[
        {
            "category":"Travel",
            "subcategory":"Travel Agent",
            "type":"Entertainment"
        }
    ],
    "sg:phone":"+43 4362 2822050",
    "sg:postcode":"5324",
    "sg:province":"Salzburg",
    "sg:tags":[
        "business"
    ],
    "wof:name":"JOSEF GRILL",
    "wof:placetype":"venue"
},
  "geometry": {"coordinates":[13.2332620621,47.7780952454],"type":"Point"}
}