{
  "type": "Feature",
  "properties": {
    "addr:full":"Grazer Str 355 Friedberg Steiermark 8240",
    "addr:housenumber":"355",
    "addr:postcode":"8240",
    "iso:country":"AT",
    "sg:address":"Grazer Str 355",
    "sg:city":"Friedberg",
    "sg:orig_category":"Feuerwehren",
    "sg:phone":"+43 3339 22172",
    "sg:postcode":"8240",
    "sg:province":"Steiermark",
    "wof:name":"Freiwillige Feuerwehr Friedberg",
    "wof:placetype":"venue"
},
  "geometry": {"coordinates":[16.0527553558,47.4380455017],"type":"Point"}
}