{
  "type": "Feature",
  "properties": {
    "addr:full":"Bundesstr 80 Mieming Tirol 6414",
    "addr:housenumber":"80",
    "addr:postcode":"6414",
    "addr:street":"Bundesstr;Tirol",
    "iso:country":"AT",
    "sg:address":"Bundesstr 80",
    "sg:city":"Mieming",
    "sg:orig_category":"Fa\u00c3\u0178bindereien",
    "sg:phone":"+43 5264 20284",
    "sg:postcode":"6414",
    "sg:province":"Tirol",
    "wof:name":"Praxmarer Josef",
    "wof:placetype":"venue"
},
  "geometry": {"coordinates":[10.9781799316,47.3059082031],"type":"Point"}
}