{
  "type": "Feature",
  "properties": {
    "addr:full":"Alte Landstr 8 Th\u00fcringen Vorarlberg 6712",
    "addr:housenumber":"8",
    "addr:postcode":"6712",
    "addr:street":"Alte Landstr",
    "iso:country":"AT",
    "sg:address":"Alte Landstr 8",
    "sg:city":"Th\u00fcringen",
    "sg:orig_category":"Medizintechnik",
    "sg:phone":"+43 5550 49400",
    "sg:postcode":"6712",
    "sg:province":"Vorarlberg",
    "wof:name":"Bitsche GmbH",
    "wof:placetype":"venue"
},
  "geometry": {"coordinates":[9.7667789459,47.1997871399],"type":"Point"}
}