{
  "type": "Feature",
  "properties": {
    "iso:country":"AT",
    "sg:address":"Kircheng 11",
    "sg:city":"Gramatneusiedl",
    "sg:orig_category":"Volksschulen",
    "sg:phone":"+43 4322 3480566",
    "sg:postcode":"2440",
    "sg:province":"Nieder\u00f6sterreich",
    "wof:name":"Volksschule",
    "wof:placetype":"venue"
},
  "geometry": {"coordinates":[16.5258846283,48.0010108948],"type":"Point"}
}