{
  "type": "Feature",
  "properties": {
    "addr:full":"Rohrerg 4a Deutsch Wagram Nieder\u00f6sterreich 2232",
    "addr:housenumber":"4a",
    "addr:postcode":"2232",
    "addr:street":"Rohrerg",
    "iso:country":"AT",
    "sg:address":"Rohrerg 4a",
    "sg:city":"Deutsch Wagram",
    "sg:orig_category":"Transportunternehmen",
    "sg:phone":"+43 2247 34990",
    "sg:postcode":"2232",
    "sg:province":"Nieder\u00f6sterreich",
    "wof:name":"Kreuz Gert GesmbH",
    "wof:placetype":"venue"
},
  "geometry": {"coordinates":[16.5560073853,48.2968902588],"type":"Point"}
}