{
  "type": "Feature",
  "properties": {
    "addr:full":"Sponheimerstr 20 Klagenfurt K\u00e4rnten 9020",
    "addr:housenumber":"20",
    "addr:postcode":"9020",
    "addr:street":"Sponheimerstr;Kaernten",
    "iso:country":"AT",
    "sg:address":"Sponheimerstr 20",
    "sg:city":"Klagenfurt",
    "sg:orig_category":"Unternehmensberatung",
    "sg:phone":"+43 463 590120",
    "sg:postcode":"9020",
    "sg:province":"K\u00e4rnten",
    "wof:name":"Alpe-Adria Wirtschaftsberatung Dkfm Helmer Heitschel-Ghonau",
    "wof:placetype":"venue"
},
  "geometry": {"coordinates":[14.3012342453,46.6216430664],"type":"Point"}
}