{
  "type": "Feature",
  "properties": {
    "iso:country":"AT",
    "sg:address":"Europapl 2",
    "sg:city":"Attnang-Puchheim",
    "sg:orig_category":"Apotheken",
    "sg:phone":"+43 767462373",
    "sg:postcode":"4800",
    "sg:province":"Ober\u00f6sterreich",
    "wof:name":"Anna Apotheke Mag J\u00fcrgen Donath",
    "wof:placetype":"venue"
},
  "geometry": {"coordinates":[13.7187814713,48.0088653564],"type":"Point"}
}