{
  "type": "Feature",
  "properties": {
    "addr:full":"Aberlg 7 W\u00f6lfnitz K\u00e4rnten 9061",
    "addr:housenumber":"7",
    "addr:postcode":"9061",
    "addr:street":"Aberlg;Kaernten",
    "iso:country":"AT",
    "sg:address":"Aberlg 7",
    "sg:city":"W\u00f6lfnitz",
    "sg:orig_category":"Non-Classified Establishments",
    "sg:phone":"+43 4346 3499799",
    "sg:postcode":"9061",
    "sg:province":"K\u00e4rnten",
    "wof:name":"TAXI Klagenfurt",
    "wof:placetype":"venue"
},
  "geometry": {"coordinates":[14.2639198303,46.6675415039],"type":"Point"}
}