{
  "type": "Feature",
  "properties": {
    "iso:country":"AT",
    "sg:address":"Henriettenpl 6",
    "sg:city":"Wien",
    "sg:orig_category":"Maturaschulen",
    "sg:phone":"+43 1 89254330",
    "sg:postcode":"1150",
    "sg:province":"Wien",
    "wof:name":"Abendschule f Bundesrealgymnasium und wirtschaftskundl Bundesrealgymnasium f Berufst\u00e4tige",
    "wof:placetype":"venue"
},
  "geometry": {"coordinates":[16.3323936462,48.1904907227],"type":"Point"}
}