{
  "type": "Feature",
  "properties": {
    "addr:full":"Veronikag 30 Wien Wien 1170",
    "addr:housenumber":"30",
    "addr:postcode":"1170",
    "addr:street":"Veronikag",
    "iso:country":"AT",
    "sg:address":"Veronikag 30",
    "sg:city":"Wien",
    "sg:orig_category":"Werbeagenturen",
    "sg:phone":"+43 4312 760768",
    "sg:postcode":"1170",
    "sg:province":"Wien",
    "wof:name":"Eurot\u00fcrk \u00f6zkan KEG",
    "wof:placetype":"venue"
},
  "geometry": {"coordinates":[16.3388004303,48.2152671814],"type":"Point"}
}