{
  "type": "Feature",
  "properties": {
    "addr:full":"Birkenallee 18 Haringsee Nieder\u00f6sterreich 2286",
    "addr:housenumber":"18",
    "addr:postcode":"2286",
    "addr:street":"Birkenallee",
    "iso:country":"AT",
    "sg:address":"Birkenallee 18",
    "sg:city":"Haringsee",
    "sg:orig_category":"Tierpensionen",
    "sg:phone":"+43 2214 8587",
    "sg:postcode":"2286",
    "sg:province":"Nieder\u00f6sterreich",
    "sg:website":"petmedia.at/hundepension",
    "wof:name":"Hundepension Fuchsenbigl",
    "wof:placetype":"venue"
},
  "geometry": {"coordinates":[16.7490882874,48.2017669678],"type":"Point"}
}