{
  "type": "Feature",
  "properties": {
    "addr:full":"Goldschlagstrasse 47 Wien Wien 1150",
    "addr:housenumber":"47",
    "addr:postcode":"1150",
    "addr:street":"Goldschlagstrasse",
    "iso:country":"AT",
    "sg:address":"Goldschlagstrasse 47",
    "sg:city":"Wien",
    "sg:classifiers":[
        {
            "category":"Manufacturing",
            "subcategory":"Wood Products",
            "type":"Manufacturing & Wholesale Goods"
        }
    ],
    "sg:phone":"+43 1 9824515",
    "sg:postcode":"1150",
    "sg:province":"Wien",
    "sg:tags":[
        "gate",
        "made",
        "door"
    ],
    "sg:website":"rafetseder.com",
    "wof:name":"Erwin Rafetseder Tischlerei KG",
    "wof:placetype":"venue"
},
  "geometry": {"coordinates":[16.3278827667,48.1966438293],"type":"Point"}
}