{
  "type": "Feature",
  "properties": {
    "addr:full":"Marktpl 1 Stadl-Paura Ober\u00f6sterreich 4651",
    "addr:housenumber":"1",
    "addr:postcode":"4651",
    "addr:street":"Marktpl",
    "iso:country":"AT",
    "sg:address":"Marktpl 1",
    "sg:city":"Stadl-Paura",
    "sg:orig_category":"Gemeinden",
    "sg:phone":"+43 7245 280110",
    "sg:postcode":"4651",
    "sg:province":"Ober\u00f6sterreich",
    "wof:name":"Gemeindeamt des Marktes Stadl-Paura",
    "wof:placetype":"venue"
},
  "geometry": {"coordinates":[13.8692007065,48.0865898132],"type":"Point"}
}