{
  "type": "Feature",
  "properties": {
    "addr:full":"H\u00fchnerauweg 24  Hallein Salzburg 5400",
    "addr:housenumber":"24",
    "addr:postcode":"5400",
    "addr:street":"Huehnerauweg;Salzburg",
    "iso:country":"AT",
    "sg:address":"H\u00fchnerauweg 24 ",
    "sg:city":"Hallein",
    "sg:classifiers":[
        {
            "category":"Shopping",
            "type":"Retail Goods"
        }
    ],
    "sg:phone":"+43 4362 4580243",
    "sg:postcode":"5400",
    "sg:province":"Salzburg",
    "sg:tags":[
        "finished",
        "-",
        "metallic"
    ],
    "wof:name":"WOLFGANG STADLER",
    "wof:placetype":"venue"
},
  "geometry": {"coordinates":[13.0926103592,47.6814613342],"type":"Point"}
}