{
  "type": "Feature",
  "properties": {
    "addr:full":"Kiesstr 12 Marchtrenk Ober\u00f6sterreich 4614",
    "addr:housenumber":"12",
    "addr:postcode":"4614",
    "addr:street":"Kiesstr",
    "iso:country":"AT",
    "sg:address":"Kiesstr 12",
    "sg:city":"Marchtrenk",
    "sg:orig_category":"Immobilienverwaltungen",
    "sg:phone":"+43 7243 534510",
    "sg:postcode":"4614",
    "sg:province":"Ober\u00f6sterreich",
    "wof:name":"POLYTEC Immobilien AG",
    "wof:placetype":"venue"
},
  "geometry": {"coordinates":[14.1418037415,48.195022583],"type":"Point"}
}