{
  "type": "Feature",
  "properties": {
    "iso:country":"AT",
    "sg:address":"M\u00fchlbachstr. 14",
    "sg:city":"Wilhering",
    "sg:classifiers":[
        {
            "category":"Wholesale",
            "subcategory":"Machinery & Supplies",
            "type":"Manufacturing & Wholesale Goods"
        }
    ],
    "sg:phone":"+43 4372 262358",
    "sg:postcode":"4073",
    "sg:province":"Ober\u00f6sterreich",
    "sg:tags":[
        "equipment",
        "-",
        "instrument",
        "measurement"
    ],
    "wof:name":"JOSEF STADLER STEUERUNGSTECHNIK GMBH",
    "wof:placetype":"venue"
},
  "geometry": {"coordinates":[14.1893806458,48.3233795166],"type":"Point"}
}