{
  "type": "Feature",
  "properties": {
    "addr:full":"Morgenstr 11 Lustenau Vorarlberg 6890",
    "addr:housenumber":"11",
    "addr:postcode":"6890",
    "addr:street":"Morgenstr",
    "iso:country":"AT",
    "sg:address":"Morgenstr 11",
    "sg:city":"Lustenau",
    "sg:orig_category":"Stickereien",
    "sg:phone":"+43 4355 77823820",
    "sg:postcode":"6890",
    "sg:province":"Vorarlberg",
    "wof:name":"Riedesser K HandelsgesmH",
    "wof:placetype":"venue"
},
  "geometry": {"coordinates":[9.6566753387,47.4224586487],"type":"Point"}
}