{
  "type": "Feature",
  "properties": {
    "iso:country":"AT",
    "sg:address":"Haunspergstr 86/23",
    "sg:city":"Salzburg",
    "sg:orig_category":"Feldenkraismethode",
    "sg:phone":"+43 4366 2458240",
    "sg:postcode":"5020",
    "sg:province":"Salzburg",
    "sg:website":"feldenkraisunterricht.com",
    "wof:name":"Irmer Simone Mag",
    "wof:placetype":"venue"
},
  "geometry": {"coordinates":[13.0386819839,47.818977356],"type":"Point"}
}