{
  "type": "Feature",
  "properties": {
    "addr:full":"Dr.-Tschiggfrey-Str 30 Nauders Tirol 6543",
    "addr:housenumber":"30",
    "addr:postcode":"6543",
    "addr:street":"Dr.-Tschiggfrey-Str",
    "iso:country":"AT",
    "sg:address":"Dr.-Tschiggfrey-Str 30",
    "sg:city":"Nauders",
    "sg:orig_category":"Banken U Sparkassen",
    "sg:phone":"+43 4354 7387332",
    "sg:postcode":"6543",
    "sg:province":"Tirol",
    "wof:name":"Sparkasse Imst",
    "wof:placetype":"venue"
},
  "geometry": {"coordinates":[10.5017347336,46.8884353638],"type":"Point"}
}