{
  "type": "Feature",
  "properties": {
    "addr:full":"St.-Georgen-Str 60 Gries Salzburg 5662",
    "addr:housenumber":"60",
    "addr:postcode":"5662",
    "addr:street":"St.-Georgen-Str;Salzburg",
    "iso:country":"AT",
    "sg:address":"St.-Georgen-Str 60",
    "sg:city":"Gries",
    "sg:orig_category":"Kosmetikanwendungsberatung",
    "sg:phone":"+43 6543 8217",
    "sg:postcode":"5662",
    "sg:province":"Salzburg",
    "wof:name":"Gscho\u00dfmann Krimhilde - Lombagine Fachberatung",
    "wof:placetype":"venue"
},
  "geometry": {"coordinates":[12.8730392456,47.2868385315],"type":"Point"}
}