{
  "type": "Feature",
  "properties": {
    "iso:country":"AT",
    "sg:address":"Heiligenst\u00e4dter Strasse 150",
    "sg:city":"Wien",
    "sg:classifiers":[
        {
            "category":"Home & Garden",
            "subcategory":"Household Appliances",
            "type":"Retail Goods"
        }
    ],
    "sg:phone":"+43 1 3701307",
    "sg:postcode":"1190",
    "sg:province":"Wien",
    "sg:tags":[
        "stove",
        "chimney"
    ],
    "sg:website":"ofenmarkt.at",
    "wof:name":"Ofenmarkt Helmut Steinb\u00f6ck",
    "wof:placetype":"venue"
},
  "geometry": {"coordinates":[16.3665561676,48.2565727234],"type":"Point"}
}