{
  "type": "Feature",
  "properties": {
    "addr:full":"Johannes Messner-Weg 6 Schwaz Tirol 6130",
    "addr:housenumber":"6",
    "addr:postcode":"6130",
    "addr:street":"Johannes Messner-Weg;Tirol",
    "iso:country":"AT",
    "sg:address":"Johannes Messner-Weg 6",
    "sg:city":"Schwaz",
    "sg:orig_category":"Volksschulen",
    "sg:phone":"+43 5242 631081",
    "sg:postcode":"6130",
    "sg:province":"Tirol",
    "wof:name":"Volksschule Johannes Messner 2",
    "wof:placetype":"venue"
},
  "geometry": {"coordinates":[11.7146053314,47.3530540466],"type":"Point"}
}