{
  "type": "Feature",
  "properties": {
    "addr:full":"Nordlandstrasse 1 Amstetten Nieder\u00f6sterreich 3300",
    "addr:housenumber":"1",
    "addr:postcode":"3300",
    "addr:street":"Nordlandstrasse;Niederoesterreich",
    "iso:country":"AT",
    "sg:address":"Nordlandstrasse 1",
    "sg:city":"Amstetten",
    "sg:classifiers":[
        {
            "category":"Utilities",
            "subcategory":"Natural Gas",
            "type":"Services"
        }
    ],
    "sg:phone":"+43 7472 685660",
    "sg:postcode":"3300",
    "sg:province":"Nieder\u00f6sterreich",
    "sg:tags":[
        "plant",
        "fire-protection",
        "board"
    ],
    "sg:website":"isovolta.com",
    "wof:name":"Thermax-Brandschutzbauteile GmbH",
    "wof:placetype":"venue"
},
  "geometry": {"coordinates":[14.8364677429,48.106552124],"type":"Point"}
}