{
  "type": "Feature",
  "properties": {
    "addr:full":"Anton-Landerl-Weg 4 Sierning Ober\u00f6sterreich 4522",
    "addr:housenumber":"4",
    "addr:postcode":"4522",
    "addr:street":"Anton-Landerl-Weg",
    "iso:country":"AT",
    "sg:address":"Anton-Landerl-Weg 4",
    "sg:city":"Sierning",
    "sg:orig_category":"\u00c3\u201erzte / F Allgemeinmedizin",
    "sg:phone":"+43 7259 2217",
    "sg:postcode":"4522",
    "sg:province":"Ober\u00f6sterreich",
    "wof:name":"Binder Walter Dr",
    "wof:placetype":"venue"
},
  "geometry": {"coordinates":[14.3086938858,48.0408935547],"type":"Point"}
}