{
  "type": "Feature",
  "properties": {
    "addr:full":"Hauptpl 6 Leibnitz Steiermark 8430",
    "addr:housenumber":"6",
    "addr:postcode":"8430",
    "addr:street":"Hauptpl;Steiermark",
    "iso:country":"AT",
    "sg:address":"Hauptpl 6",
    "sg:city":"Leibnitz",
    "sg:orig_category":"Tabaktrafiken",
    "sg:phone":"+43 4334 5282873",
    "sg:postcode":"8430",
    "sg:province":"Steiermark",
    "wof:name":"Tabak-Trafik Vlay Inh Pfeifer Gabi",
    "wof:placetype":"venue"
},
  "geometry": {"coordinates":[15.5397853851,46.7821617126],"type":"Point"}
}