{
  "type": "Feature",
  "properties": {
    "iso:country":"AT",
    "sg:address":"Evangelimanng 5",
    "sg:city":"Graz",
    "sg:orig_category":"Farben U Lacke / Erzeugung U Gro\u00c3\u0178handel",
    "sg:phone":"+43 316 4713250",
    "sg:postcode":"8010",
    "sg:province":"Steiermark",
    "wof:name":"Wirtschaftliche Vereinigung d Maler und Anstreicher regGenmbH",
    "wof:placetype":"venue"
},
  "geometry": {"coordinates":[15.4533243179,47.0500335693],"type":"Point"}
}