{
  "type": "Feature",
  "properties": {
    "iso:country":"AT",
    "sg:address":"Vogelweiderstr. 69",
    "sg:city":"Salzburg",
    "sg:classifiers":[
        {
            "category":"Autos & Motor Vehicles",
            "subcategory":"Automobile Sales",
            "type":"Retail Goods"
        }
    ],
    "sg:phone":"+43 4366 280710",
    "sg:postcode":"5020",
    "sg:province":"Salzburg",
    "sg:tags":[
        "industrial"
    ],
    "wof:name":"PORSCHE INTER AUTO",
    "wof:placetype":"venue"
},
  "geometry": {"coordinates":[13.0534067154,47.8156700134],"type":"Point"}
}