{
  "type": "Feature",
  "properties": {
    "addr:full":"Messingg 8 Lienz Tirol 9900",
    "addr:housenumber":"8",
    "addr:postcode":"9900",
    "addr:street":"Messingg;Tirol",
    "iso:country":"AT",
    "sg:address":"Messingg 8",
    "sg:city":"Lienz",
    "sg:orig_category":"Boutiquen",
    "sg:phone":"+43 4852 65677",
    "sg:postcode":"9900",
    "sg:province":"Tirol",
    "wof:name":"Boutique Topline - Jeans & Sportswear",
    "wof:placetype":"venue"
},
  "geometry": {"coordinates":[12.7684783936,46.8281173706],"type":"Point"}
}