{
  "type": "Feature",
  "properties": {
    "addr:full":"Schmiedg 6 Feldkirch Vorarlberg 6800",
    "addr:housenumber":"6",
    "addr:postcode":"6800",
    "addr:street":"Schmiedg",
    "iso:country":"AT",
    "sg:address":"Schmiedg 6",
    "sg:city":"Feldkirch",
    "sg:orig_category":"Juwelen, Gold- U Silberwaren / Einzelhandel, Uhren / Einzelhandel",
    "sg:phone":"+43 5522 72114",
    "sg:postcode":"6800",
    "sg:province":"Vorarlberg",
    "wof:name":"Ritter Eugen",
    "wof:placetype":"venue"
},
  "geometry": {"coordinates":[9.5976524353,47.2377853394],"type":"Point"}
}