{
  "type": "Feature",
  "properties": {
    "addr:full":"Rauhensteingasse 7/40 Wien Wien 1010",
    "addr:housenumber":"7 / 40",
    "addr:postcode":"1010",
    "addr:street":"Rauhensteingasse",
    "iso:country":"AT",
    "sg:address":"Rauhensteingasse 7/40",
    "sg:city":"Wien",
    "sg:orig_category":"Freizeit, Kunst U Kultur",
    "sg:phone":"+43 4315 135381",
    "sg:postcode":"1010",
    "sg:province":"Wien",
    "sg:website":"http://members.magnet.at/e-m-j-braunias",
    "wof:name":"Filmarchitektur/ Produktion-Design/ B\u00fchnenbild Ausstellungen",
    "wof:placetype":"venue"
},
  "geometry": {"coordinates":[16.3726139069,48.2059059143],"type":"Point"}
}