{
  "type": "Feature",
  "properties": {
    "iso:country":"AT",
    "sg:address":"Gerbe 1135/Impuls/Zentrum",
    "sg:city":"Egg",
    "sg:orig_category":"Handelsagenturen",
    "sg:phone":"+43 5512 26488",
    "sg:postcode":"6863",
    "sg:province":"Vorarlberg",
    "wof:name":"DETEC Marketing GmbH",
    "wof:placetype":"venue"
},
  "geometry": {"coordinates":[9.897102356,47.4310417175],"type":"Point"}
}