{
  "type": "Feature",
  "properties": {
    "addr:full":"Friedhofweg 4 Oberpullendorf Burgenland 7350",
    "addr:housenumber":"4",
    "addr:postcode":"7350",
    "addr:street":"Friedhofweg",
    "iso:country":"AT",
    "sg:address":"Friedhofweg 4",
    "sg:city":"Oberpullendorf",
    "sg:orig_category":"Elektroinstallationsunternehmen",
    "sg:phone":"+43 2612 425790",
    "sg:postcode":"7350",
    "sg:province":"Burgenland",
    "wof:name":"F Flieszar GesmbH",
    "wof:placetype":"venue"
},
  "geometry": {"coordinates":[16.5052261353,47.4997749329],"type":"Point"}
}