{
  "type": "Feature",
  "properties": {
    "addr:full":"Straniakstr 34 Bergheim Salzburg 5101",
    "addr:housenumber":"34",
    "addr:postcode":"5101",
    "addr:street":"Straniakstr;Salzburg",
    "iso:country":"AT",
    "sg:address":"Straniakstr 34",
    "sg:city":"Bergheim",
    "sg:orig_category":"Schilder",
    "sg:phone":"+43 662 451110",
    "sg:postcode":"5101",
    "sg:province":"Salzburg",
    "wof:name":"Stubhann Gebr\u00fcder",
    "wof:placetype":"venue"
},
  "geometry": {"coordinates":[13.0230998993,47.8411369324],"type":"Point"}
}