{
  "type": "Feature",
  "properties": {
    "addr:full":"Diesseits 117 St. Martin im Innkreis Ober\u00f6sterreich 4973",
    "addr:housenumber":"117",
    "addr:postcode":"4973",
    "addr:street":"Diesseits",
    "iso:country":"AT",
    "sg:address":"Diesseits 117",
    "sg:city":"St. Martin im Innkreis",
    "sg:classifiers":[
        {
            "category":"Building & Trades",
            "subcategory":"Electrical",
            "type":"Services"
        }
    ],
    "sg:phone":"+43 7751 8101",
    "sg:postcode":"4973",
    "sg:province":"Ober\u00f6sterreich",
    "sg:tags":[
        "construction",
        "cad"
    ],
    "sg:website":"doetzlhofer.at",
    "wof:name":"Doetzlhofer Ralf - B\u00fcro f\u00fcr technische Zeichnungen",
    "wof:placetype":"venue"
},
  "geometry": {"coordinates":[13.4180746078,48.261505127],"type":"Point"}
}