{
  "type": "Feature",
  "properties": {
    "iso:country":"AT",
    "sg:address":"Stephansberg 14",
    "sg:city":"Horn",
    "sg:orig_category":"Hauskrankenpflege / Heimhilfe",
    "sg:phone":"+43 2982 3966",
    "sg:postcode":"3580",
    "sg:province":"Nieder\u00f6sterreich",
    "wof:name":"Hilfswerk Horn - Hilfe und Pflege daheim",
    "wof:placetype":"venue"
},
  "geometry": {"coordinates":[15.6523952484,48.6626586914],"type":"Point"}
}