{
  "type": "Feature",
  "properties": {
    "addr:full":"Dorfpl 7 Zell am See Salzburg 5700",
    "addr:housenumber":"7",
    "addr:postcode":"5700",
    "addr:street":"Dorfpl;Salzburg",
    "iso:country":"AT",
    "sg:address":"Dorfpl 7",
    "sg:city":"Zell am See",
    "sg:classifiers":[
        {
            "category":"Park",
            "subcategory":"Provincial",
            "type":"Public Place"
        }
    ],
    "sg:phone":"+43 6542 73171",
    "sg:postcode":"5700",
    "sg:province":"Salzburg",
    "sg:tags":[
        "u",
        "ski-",
        "snowboardschulen"
    ],
    "wof:name":"Schischule Thumersbach",
    "wof:placetype":"venue"
},
  "geometry": {"coordinates":[12.7963104248,47.3219909668],"type":"Point"}
}