{
  "type": "Feature",
  "properties": {
    "iso:country":"AT",
    "sg:address":"Bahnhofstr 2",
    "sg:city":"Ottensheim",
    "sg:orig_category":"Non-Classified Establishments",
    "sg:phone":"+43 7234 82227",
    "sg:postcode":"4100",
    "sg:province":"Ober\u00f6sterreich",
    "wof:name":"Pfarramt",
    "wof:placetype":"venue"
},
  "geometry": {"coordinates":[14.1760292053,48.3325157166],"type":"Point"}
}