{
  "type": "Feature",
  "properties": {
    "addr:full":"Untere Schmiedg 9 Deutschlandsberg Steiermark 8530",
    "addr:housenumber":"9",
    "addr:postcode":"8530",
    "addr:street":"Untere Schmiedg",
    "iso:country":"AT",
    "sg:address":"Untere Schmiedg 9",
    "sg:city":"Deutschlandsberg",
    "sg:orig_category":"Personalberatung",
    "sg:phone":"+43 4334 6251400",
    "sg:postcode":"8530",
    "sg:province":"Steiermark",
    "wof:name":"Regionale Frauenqualifizierung Zentrum f\u00fcr Ausbildungsmanagement",
    "wof:placetype":"venue"
},
  "geometry": {"coordinates":[15.2164525986,46.8142776489],"type":"Point"}
}