{
  "type": "Feature",
  "properties": {
    "addr:full":"Kremserbergweg 51 Voitsberg Steiermark 8570",
    "addr:housenumber":"51",
    "addr:postcode":"8570",
    "addr:street":"Kremserbergweg",
    "iso:country":"AT",
    "sg:address":"Kremserbergweg 51",
    "sg:city":"Voitsberg",
    "sg:orig_category":"Gartenpflege",
    "sg:phone":"+43 4367 64130425",
    "sg:postcode":"8570",
    "sg:province":"Steiermark",
    "wof:name":"Muchitsch Bernhard",
    "wof:placetype":"venue"
},
  "geometry": {"coordinates":[15.1854028702,47.0427207947],"type":"Point"}
}