{
  "type": "Feature",
  "properties": {
    "iso:country":"AT",
    "sg:address":"Schneeburgg 46",
    "sg:city":"Innsbruck",
    "sg:orig_category":"Hausbetreuung",
    "sg:phone":"+43 664 2554865",
    "sg:postcode":"6020",
    "sg:province":"Tirol",
    "wof:name":"Rubisoier Anton - Hausmeisterservice",
    "wof:placetype":"venue"
},
  "geometry": {"coordinates":[11.3789825439,47.2694129944],"type":"Point"}
}