{
  "type": "Feature",
  "properties": {
    "addr:full":"Hauptstr 69 St. Johann im Pongau Salzburg 5600",
    "addr:housenumber":"69",
    "addr:postcode":"5600",
    "addr:street":"Hauptstr;Salzburg",
    "iso:country":"AT",
    "sg:address":"Hauptstr 69",
    "sg:city":"St. Johann im Pongau",
    "sg:orig_category":"Bars-Cafes",
    "sg:phone":"+43 6412 7975",
    "sg:postcode":"5600",
    "sg:province":"Salzburg",
    "wof:name":"Musikpub TAO",
    "wof:placetype":"venue"
},
  "geometry": {"coordinates":[13.1988306046,47.3451423645],"type":"Point"}
}