{
  "type": "Feature",
  "properties": {
    "addr:full":"Salzg 8 Wien Wien 1010",
    "addr:housenumber":"8",
    "addr:postcode":"1010",
    "addr:street":"Salzg",
    "iso:country":"AT",
    "sg:address":"Salzg 8",
    "sg:city":"Wien",
    "sg:orig_category":"Bierlokale-Pubs",
    "sg:phone":"+43 1 5333320",
    "sg:postcode":"1010",
    "sg:province":"Wien",
    "wof:name":"New Country",
    "wof:placetype":"venue"
},
  "geometry": {"coordinates":[16.3740520477,48.2120819092],"type":"Point"}
}