{
  "type": "Feature",
  "properties": {
    "iso:country":"AT",
    "sg:address":"K\u00fchnsdorf Nord 106",
    "sg:city":"K\u00fchnsdorf",
    "sg:orig_category":"Schlossereien",
    "sg:phone":"+43 4342 328186",
    "sg:postcode":"9125",
    "sg:province":"K\u00e4rnten",
    "wof:name":"Grabner H P KEG",
    "wof:placetype":"venue"
},
  "geometry": {"coordinates":[14.6361494064,46.6237106323],"type":"Point"}
}