{
  "type": "Feature",
  "properties": {
    "addr:full":"Marktstr 6 Oberdrauburg K\u00e4rnten 9781",
    "addr:housenumber":"6",
    "addr:postcode":"9781",
    "addr:street":"Marktstr;Kaernten",
    "iso:country":"AT",
    "sg:address":"Marktstr 6",
    "sg:city":"Oberdrauburg",
    "sg:orig_category":"Banken U Sparkassen",
    "sg:phone":"+43 4710 22110",
    "sg:postcode":"9781",
    "sg:province":"K\u00e4rnten",
    "wof:name":"Raiffeisenbank Oberdrauburg regGenmbH",
    "wof:placetype":"venue"
},
  "geometry": {"coordinates":[12.9723615646,46.748588562],"type":"Point"}
}