{
  "type": "Feature",
  "properties": {
    "iso:country":"AT",
    "sg:address":"Zieglerg. 8",
    "sg:city":"Wien",
    "sg:classifiers":[
        {
            "category":"Wholesale",
            "subcategory":"Drugs",
            "type":"Manufacturing & Wholesale Goods"
        }
    ],
    "sg:phone":"+43 4315 2325010",
    "sg:postcode":"1070",
    "sg:province":"Wien",
    "sg:tags":[
        "chemical",
        "pharmaceutical"
    ],
    "wof:name":"SCH\u00dcLKE & MAYR GESMBH",
    "wof:placetype":"venue"
},
  "geometry": {"coordinates":[16.3456459045,48.1981239319],"type":"Point"}
}