{
  "type": "Feature",
  "properties": {
    "iso:country":"AT",
    "sg:address":"Pramer Strasse 11",
    "sg:city":"Taiskirchen im Innkreis",
    "sg:classifiers":[
        {
            "category":"Manufacturing",
            "subcategory":"Wood Products",
            "type":"Manufacturing & Wholesale Goods"
        }
    ],
    "sg:phone":"+43 7764 73510",
    "sg:postcode":"4753",
    "sg:province":"Ober\u00f6sterreich",
    "sg:tags":[
        "body",
        "press",
        "woodworking"
    ],
    "sg:website":"hoefer-maschinen.com",
    "wof:name":"Ing. Gerhardt H\u00f6fer & Co Maschinenproduktionsges.m.b.H.",
    "wof:placetype":"venue"
},
  "geometry": {"coordinates":[13.5817747116,48.2630081177],"type":"Point"}
}