{
  "type": "Feature",
  "properties": {
    "addr:full":"Joseph Haydn-G 40 Eisenstadt Burgenland 7000",
    "addr:housenumber":"40",
    "addr:postcode":"7000",
    "iso:country":"AT",
    "sg:address":"Joseph Haydn-G 40",
    "sg:city":"Eisenstadt",
    "sg:orig_category":"Steuerberatung",
    "sg:phone":"+43 2682 66312",
    "sg:postcode":"7000",
    "sg:province":"Burgenland",
    "wof:name":"EWT Wirtschaftstreuhand GesmbH",
    "wof:placetype":"venue"
},
  "geometry": {"coordinates":[16.5248298645,47.8472595215],"type":"Point"}
}