{
  "type": "Feature",
  "properties": {
    "iso:country":"AT",
    "sg:address":"Grabnerstr 43",
    "sg:city":"Linz",
    "sg:orig_category":"Zeitungen U Zeitschriften / Vertrieb",
    "sg:phone":"+43 4369 910071666",
    "sg:postcode":"4020",
    "sg:province":"Ober\u00f6sterreich",
    "wof:name":"Radwelt",
    "wof:placetype":"venue"
},
  "geometry": {"coordinates":[14.2739925385,48.2849807739],"type":"Point"}
}