{
  "type": "Feature",
  "properties": {
    "iso:country":"AT",
    "sg:address":"Untermarkter Str 13a",
    "sg:city":"Treibach-Althofen",
    "sg:orig_category":"Hafnereien",
    "sg:phone":"+43 4342 623164",
    "sg:postcode":"9330",
    "sg:province":"K\u00e4rnten",
    "wof:name":"Kugi Stadthafnerei u Fliesen GmbH",
    "wof:placetype":"venue"
},
  "geometry": {"coordinates":[14.4785118103,46.8704299927],"type":"Point"}
}