{
  "type": "Feature",
  "properties": {
    "addr:full":"Innstr 23 Wien Wien 1200",
    "addr:housenumber":"23",
    "addr:postcode":"1200",
    "addr:street":"Innstr",
    "iso:country":"AT",
    "sg:address":"Innstr 23",
    "sg:city":"Wien",
    "sg:orig_category":"Toilettenvermietung",
    "sg:phone":"+43 1 33255160",
    "sg:postcode":"1200",
    "sg:province":"Wien",
    "sg:website":"www.mobiclo.at",
    "wof:name":"Mobiclo Toiletten - Mietservice",
    "wof:placetype":"venue"
},
  "geometry": {"coordinates":[16.3908004761,48.2327651978],"type":"Point"}
}