{
  "type": "Feature",
  "properties": {
    "iso:country":"AT",
    "sg:address":"Hauptstr 54",
    "sg:city":"Unterrabnitz",
    "sg:orig_category":"Gemeinden",
    "sg:phone":"+43 4326 1688770",
    "sg:postcode":"7371",
    "sg:province":"Burgenland",
    "wof:name":"Gemeindeamt Unterrabnitz-Schwendgraben",
    "wof:placetype":"venue"
},
  "geometry": {"coordinates":[16.3764648438,47.4545555115],"type":"Point"}
}