{
  "type": "Feature",
  "properties": {
    "addr:full":"Perfektastrasse 81  Wien Wien 1230",
    "addr:housenumber":"81",
    "addr:postcode":"1230",
    "addr:street":"Perfektastrasse",
    "iso:country":"AT",
    "sg:address":"Perfektastrasse 81 ",
    "sg:city":"Wien",
    "sg:classifiers":[
        {
            "category":"Education",
            "subcategory":"Vocational School",
            "type":"Public Place"
        }
    ],
    "sg:phone":"+43 1 86514250",
    "sg:postcode":"1230",
    "sg:province":"Wien",
    "sg:tags":[
        "assembly",
        "testing",
        "printed",
        "circuit",
        "pcb",
        "board"
    ],
    "wof:name":"Fels Multiprint Ing. August Fels KG",
    "wof:placetype":"venue"
},
  "geometry": {"coordinates":[16.3023300171,48.13671875],"type":"Point"}
}