{
  "type": "Feature",
  "properties": {
    "addr:full":"Tannenbergg 15 Schwaz Tirol 6130",
    "addr:housenumber":"15",
    "addr:postcode":"6130",
    "addr:street":"Tannenbergg;Tirol",
    "iso:country":"AT",
    "sg:address":"Tannenbergg 15",
    "sg:city":"Schwaz",
    "sg:orig_category":"Non-Classified Establishments",
    "sg:phone":"+43 5242 62258",
    "sg:postcode":"6130",
    "sg:province":"Tirol",
    "wof:name":"Pfarramt Schwaz-Mariahimmelfahrt",
    "wof:placetype":"venue"
},
  "geometry": {"coordinates":[11.7095518112,47.3473510742],"type":"Point"}
}