{
  "type": "Feature",
  "properties": {
    "iso:country":"AT",
    "sg:address":"Salzburger Strasse 59",
    "sg:city":"Lambach",
    "sg:orig_category":"Axle-Load Weighers, Wheel-Load Weighers",
    "sg:phone":"+43 7245 282500",
    "sg:postcode":"4650",
    "sg:province":"Ober\u00f6sterreich",
    "sg:website":"dula.at",
    "wof:name":"Durstm\u00fcller Wiege- und Filtertechnik GmbH",
    "wof:placetype":"venue"
},
  "geometry": {"coordinates":[13.8612251282,48.0907707214],"type":"Point"}
}