{
  "type": "Feature",
  "properties": {
    "addr:full":"Kirchweg 23-27 Steindorf K\u00e4rnten 9552",
    "addr:postcode":"23-27;9552",
    "addr:street":"Kirchweg",
    "iso:country":"AT",
    "sg:address":"Kirchweg 23-27",
    "sg:city":"Steindorf",
    "sg:orig_category":"Tischlereien",
    "sg:phone":"+43 4243 2418",
    "sg:postcode":"9552",
    "sg:province":"K\u00e4rnten",
    "wof:name":"Tischlerstub'n - M\u00f6bel im Handwerk - Heiner Gernot",
    "wof:placetype":"venue"
},
  "geometry": {"coordinates":[14.0096626282,46.6974639893],"type":"Point"}
}