{
  "type": "Feature",
  "properties": {
    "addr:full":"Maria-Theresien-Str 20 Lustenau Vorarlberg 6890",
    "addr:housenumber":"20",
    "addr:postcode":"6890",
    "addr:street":"Maria-Theresien-Str",
    "iso:country":"AT",
    "sg:address":"Maria-Theresien-Str 20",
    "sg:city":"Lustenau",
    "sg:orig_category":"Immobilienmakler",
    "sg:phone":"+43 4355 7783111",
    "sg:postcode":"6890",
    "sg:province":"Vorarlberg",
    "wof:name":"Realb\u00fcro Hagen Immobilien GmbH",
    "wof:placetype":"venue"
},
  "geometry": {"coordinates":[9.6595811844,47.4285202026],"type":"Point"}
}