{
  "type": "Feature",
  "properties": {
    "addr:full":"Bahng 25 Deutschkreutz Burgenland 7301",
    "addr:housenumber":"25",
    "addr:postcode":"7301",
    "addr:street":"Bahng",
    "iso:country":"AT",
    "sg:address":"Bahng 25",
    "sg:city":"Deutschkreutz",
    "sg:orig_category":"Werbeagenturen",
    "sg:phone":"+43 664 1234007",
    "sg:postcode":"7301",
    "sg:province":"Burgenland",
    "wof:name":"Web 7 TV - Filmproduktionen und Kommunikation",
    "wof:placetype":"venue"
},
  "geometry": {"coordinates":[16.6155204773,47.602897644],"type":"Point"}
}