{
  "type": "Feature",
  "properties": {
    "iso:country":"AT",
    "sg:address":"Kritzendorfer Hauptstr 202",
    "sg:city":"Kritzendorf",
    "sg:orig_category":"Baumeister",
    "sg:phone":"+43 4322 4324478",
    "sg:postcode":"3420",
    "sg:province":"Nieder\u00f6sterreich",
    "wof:name":"Winkler Karl GesmbH",
    "wof:placetype":"venue"
},
  "geometry": {"coordinates":[16.3018398285,48.3276901245],"type":"Point"}
}