{
  "type": "Feature",
  "properties": {
    "addr:full":"Rabenwald 103 P\u00f6llau Steiermark 8225",
    "addr:housenumber":"103",
    "addr:postcode":"8225",
    "addr:street":"Rabenwald",
    "iso:country":"AT",
    "sg:address":"Rabenwald 103",
    "sg:city":"P\u00f6llau",
    "sg:classifiers":[
        {
            "category":"Manufacturing",
            "subcategory":"Wood Products",
            "type":"Manufacturing & Wholesale Goods"
        }
    ],
    "sg:phone":"+43 3335 2344",
    "sg:postcode":"8225",
    "sg:province":"Steiermark",
    "sg:tags":[
        "lumber"
    ],
    "wof:name":"S\u00e4gewerk Schweighofer Ges.m.b.H.",
    "wof:placetype":"venue"
},
  "geometry": {"coordinates":[15.8592996597,47.3172454834],"type":"Point"}
}