{
  "type": "Feature",
  "properties": {
    "iso:country":"AT",
    "sg:address":"Kupferschmiedgasse 8 Hagenbrunn",
    "sg:city":"Gerasdorf",
    "sg:orig_category":"Miscellaneous Products",
    "sg:phone":"+43 4322 463521",
    "sg:postcode":"2201",
    "sg:province":"Nieder\u00f6sterreich",
    "wof:name":"MAHR MASCHINENBAU GES.MBH",
    "wof:placetype":"venue"
},
  "geometry": {"coordinates":[16.4562244415,48.3326835632],"type":"Point"}
}