{
  "type": "Feature",
  "properties": {
    "iso:country":"AT",
    "sg:address":"Atzgersdorfer Str 76",
    "sg:city":"Wien",
    "sg:orig_category":"Farben U Lacke / Erzeugung U Gro\u00c3\u0178handel",
    "sg:phone":"+43 4318 6523000",
    "sg:postcode":"1230",
    "sg:province":"Wien",
    "wof:name":"Adler-Werk Lackfabrik Johann Berghofer GmbH & Co",
    "wof:placetype":"venue"
},
  "geometry": {"coordinates":[16.295747757,48.1511726379],"type":"Point"}
}