{
  "type": "Feature",
  "properties": {
    "addr:full":"Nr 110 M\u00fchlbach am Manhartsberg Nieder\u00f6sterreich 3473",
    "addr:postcode":"3473",
    "addr:street":"Nr;Muehlbach Am Manhartsberg",
    "iso:country":"AT",
    "sg:address":"Nr 110",
    "sg:city":"M\u00fchlbach am Manhartsberg",
    "sg:orig_category":"Banken U Sparkassen",
    "sg:phone":"+43 4329 57308",
    "sg:postcode":"3473",
    "sg:province":"Nieder\u00f6sterreich",
    "wof:name":"Raiffeisenbank Langenlois regGenmbH",
    "wof:placetype":"venue"
},
  "geometry": {"coordinates":[15.748749733,48.5439605713],"type":"Point"}
}