{
  "type": "Feature",
  "properties": {
    "addr:full":"St. P\u00f6ltner Str 70 Rabenstein an der Pielach Nieder\u00f6sterreich 3203",
    "addr:housenumber":"70",
    "addr:postcode":"3203",
    "addr:street":"Str",
    "iso:country":"AT",
    "sg:address":"St. P\u00f6ltner Str 70",
    "sg:city":"Rabenstein an der Pielach",
    "sg:orig_category":"Garagentore U -Antriebe",
    "sg:phone":"+43 4327 2322740",
    "sg:postcode":"3203",
    "sg:province":"Nieder\u00f6sterreich",
    "sg:website":"engl-tor.at",
    "wof:name":"Engl KG",
    "wof:placetype":"venue"
},
  "geometry": {"coordinates":[15.4803104401,48.0693778992],"type":"Point"}
}