{
  "type": "Feature",
  "properties": {
    "iso:country":"AT",
    "sg:address":"Reischau 6",
    "sg:city":"Haag am Hausruck",
    "sg:orig_category":"Abschleppdienste",
    "sg:phone":"+43 7732 2276",
    "sg:postcode":"4680",
    "sg:province":"Ober\u00f6sterreich",
    "wof:name":"Lang G\u00fcnther GmbH",
    "wof:placetype":"venue"
},
  "geometry": {"coordinates":[13.6362571716,48.1984863281],"type":"Point"}
}