{
  "type": "Feature",
  "properties": {
    "addr:full":"Werndlstr 63 St. Valentin Nieder\u00f6sterreich 4300",
    "addr:housenumber":"63",
    "addr:postcode":"4300",
    "addr:street":"Werndlstr",
    "iso:country":"AT",
    "sg:address":"Werndlstr 63",
    "sg:city":"St. Valentin",
    "sg:orig_category":"Handelsagenturen",
    "sg:phone":"+43 7435 540020",
    "sg:postcode":"4300",
    "sg:province":"Nieder\u00f6sterreich",
    "wof:name":"Sigl Peter",
    "wof:placetype":"venue"
},
  "geometry": {"coordinates":[14.504070282,48.1549072266],"type":"Point"}
}