{
  "type": "Feature",
  "properties": {
    "iso:country":"AT",
    "sg:address":"Annastr 4",
    "sg:city":"Gmunden",
    "sg:orig_category":"Volksschulen",
    "sg:phone":"+43 761274311",
    "sg:postcode":"4810",
    "sg:province":"Ober\u00f6sterreich",
    "wof:name":"Volksschule 2 Traundorf",
    "wof:placetype":"venue"
},
  "geometry": {"coordinates":[13.8066654205,47.9174957275],"type":"Point"}
}