{
  "type": "Feature",
  "properties": {
    "iso:country":"AT",
    "sg:address":"Freyung 8",
    "sg:city":"Wien",
    "sg:orig_category":"Museen / Ausstellungen",
    "sg:phone":"+43 1 537330",
    "sg:postcode":"1010",
    "sg:province":"Wien",
    "wof:name":"Bank Austria Kunstforum",
    "wof:placetype":"venue"
},
  "geometry": {"coordinates":[16.3660316467,48.2115097046],"type":"Point"}
}