{
  "type": "Feature",
  "properties": {
    "iso:country":"AT",
    "sg:address":"Hauptstr 67",
    "sg:city":"Donnerskirchen",
    "sg:orig_category":"Friseure U Frisiersalons",
    "sg:phone":"+43 2683 8574",
    "sg:postcode":"7082",
    "sg:province":"Burgenland",
    "wof:name":"Eder Maria",
    "wof:placetype":"venue"
},
  "geometry": {"coordinates":[16.6401844025,47.8983688354],"type":"Point"}
}