{
  "type": "Feature",
  "properties": {
    "iso:country":"AT",
    "sg:address":"Maria-Theresien-Str 5/1",
    "sg:city":"Innsbruck",
    "sg:orig_category":"Sonnenstudios",
    "sg:phone":"+43 4351 2562569",
    "sg:postcode":"6020",
    "sg:province":"Tirol",
    "wof:name":"Stadtsonne",
    "wof:placetype":"venue"
},
  "geometry": {"coordinates":[11.3938970566,47.2668533325],"type":"Point"}
}