{
  "type": "Feature",
  "properties": {
    "addr:full":"Neustadt 1 Feldkirch Vorarlberg 6800",
    "addr:housenumber":"1",
    "addr:postcode":"6800",
    "addr:street":"Neustadt",
    "iso:country":"AT",
    "sg:address":"Neustadt 1",
    "sg:city":"Feldkirch",
    "sg:orig_category":"Friseure U Frisiersalons",
    "sg:phone":"+43 4355 2279859",
    "sg:postcode":"6800",
    "sg:province":"Vorarlberg",
    "wof:name":"hair@dom Loibner Reinhold",
    "wof:placetype":"venue"
},
  "geometry": {"coordinates":[9.5982093811,47.2376785278],"type":"Point"}
}