{
  "type": "Feature",
  "properties": {
    "addr:full":"Traunreiterg 1 Ebensee Ober\u00f6sterreich 4802",
    "addr:housenumber":"1",
    "addr:postcode":"4802",
    "addr:street":"Traunreiterg",
    "iso:country":"AT",
    "sg:address":"Traunreiterg 1",
    "sg:city":"Ebensee",
    "sg:orig_category":"Bankomat-Standorte",
    "sg:phone":"+43 6133 70240",
    "sg:postcode":"4802",
    "sg:province":"Ober\u00f6sterreich",
    "wof:name":"Bankomat d Hagebank-Volksbank V\u00f6cklabruck-Traunsee regGenmbH",
    "wof:placetype":"venue"
},
  "geometry": {"coordinates":[13.7704296112,47.81067276],"type":"Point"}
}