{
  "type": "Feature",
  "properties": {
    "addr:full":"Alfred J\u00e4ger-Weg 4 Mondsee Ober\u00f6sterreich 5310",
    "addr:housenumber":"4",
    "addr:postcode":"5310",
    "addr:street":"Jaeger-Weg;Oberoesterreich",
    "iso:country":"AT",
    "sg:address":"Alfred J\u00e4ger-Weg 4",
    "sg:city":"Mondsee",
    "sg:orig_category":"Steuerberatung",
    "sg:phone":"+43 6232 40800",
    "sg:postcode":"5310",
    "sg:province":"Ober\u00f6sterreich",
    "wof:name":"Wiedlroither Johann M Mag",
    "wof:placetype":"venue"
},
  "geometry": {"coordinates":[13.3430566788,47.8567886353],"type":"Point"}
}