{
  "type": "Feature",
  "properties": {
    "addr:full":"Stremtalstr 17 Strem Burgenland 7522",
    "addr:housenumber":"17",
    "addr:postcode":"strem;7522",
    "addr:street":"Stremtalstr",
    "iso:country":"AT",
    "sg:address":"Stremtalstr 17",
    "sg:city":"Strem",
    "sg:orig_category":"Pensionen / Privatzimmer",
    "sg:phone":"+43 3324 7515",
    "sg:postcode":"7522",
    "sg:province":"Burgenland",
    "wof:name":"Fr\u00fchst\u00fcckspension zur alten M\u00fchle",
    "wof:placetype":"venue"
},
  "geometry": {"coordinates":[16.4100284576,47.0398368835],"type":"Point"}
}