{
  "type": "Feature",
  "properties": {
    "addr:full":"Landstra\u00dfer Hauptstr 2a Wien Wien 1030",
    "addr:housenumber":"2a",
    "addr:postcode":"1030",
    "addr:street":"Landstrasser Hauptstr",
    "iso:country":"AT",
    "sg:address":"Landstra\u00dfer Hauptstr 2a",
    "sg:city":"Wien",
    "sg:orig_category":"Bankomat-Standorte",
    "sg:phone":"+43 1 7187808",
    "sg:postcode":"1030",
    "sg:province":"Wien",
    "wof:name":"Bankomat d Raiffeisenlandesbank N\u00f6-Wien AG",
    "wof:placetype":"venue"
},
  "geometry": {"coordinates":[16.3845767975,48.2059020996],"type":"Point"}
}