{
  "type": "Feature",
  "properties": {
    "addr:full":"Glocknerstr 51 Bruck an der Gro\u00dfglocknerstra\u00dfe Salzburg 5671",
    "addr:housenumber":"51",
    "addr:postcode":"5671",
    "addr:street":"Glocknerstr;Grossglocknerstrasse Salzburg",
    "iso:country":"AT",
    "sg:address":"Glocknerstr 51",
    "sg:city":"Bruck an der Gro\u00dfglocknerstra\u00dfe",
    "sg:classifiers":[
        {
            "category":"Travel",
            "subcategory":"Hotels & Motels",
            "type":"Entertainment"
        }
    ],
    "sg:phone":"+43 4365 4572400",
    "sg:postcode":"5671",
    "sg:province":"Salzburg",
    "wof:name":"Hotel H\u00f6llern",
    "wof:placetype":"venue"
},
  "geometry": {"coordinates":[12.8261222839,47.2735290527],"type":"Point"}
}