{
  "type": "Feature",
  "properties": {
    "addr:full":"Margaretenstr 25 Wien Wien 1040",
    "addr:housenumber":"25",
    "addr:postcode":"1040",
    "addr:street":"Margaretenstr",
    "iso:country":"AT",
    "sg:address":"Margaretenstr 25",
    "sg:city":"Wien",
    "sg:orig_category":"Schneidereien",
    "sg:phone":"+43 1 58744440",
    "sg:postcode":"1040",
    "sg:province":"Wien",
    "wof:name":"Lambert Hofer Inh Olga Hofer",
    "wof:placetype":"venue"
},
  "geometry": {"coordinates":[16.3645935059,48.1957397461],"type":"Point"}
}