{
  "type": "Feature",
  "properties": {
    "addr:full":"Nordbahnstr. 5 Wien Wien 1020",
    "addr:housenumber":"5",
    "addr:postcode":"1020",
    "addr:street":"Nordbahnstr.",
    "iso:country":"AT",
    "sg:address":"Nordbahnstr. 5",
    "sg:city":"Wien",
    "sg:classifiers":[
        {
            "category":"Banks & Credit Unions",
            "subcategory":"Bank",
            "type":"Services"
        }
    ],
    "sg:phone":"+43 4312 1421620",
    "sg:postcode":"1020",
    "sg:province":"Wien",
    "sg:tags":[
        "banking",
        "institution"
    ],
    "wof:name":"SPARDA BANK AG",
    "wof:placetype":"venue"
},
  "geometry": {"coordinates":[16.3903808594,48.2207069397],"type":"Point"}
}