{
  "type": "Feature",
  "properties": {
    "addr:full":"Hauptpl 15 Leoben Steiermark 8700",
    "addr:housenumber":"15",
    "addr:postcode":"8700",
    "addr:street":"Hauptpl",
    "iso:country":"AT",
    "sg:address":"Hauptpl 15",
    "sg:city":"Leoben",
    "sg:orig_category":"Friseure U Frisiersalons",
    "sg:phone":"+43 4338 4242871",
    "sg:postcode":"8700",
    "sg:province":"Steiermark",
    "wof:name":"Lenzbauer Herbert",
    "wof:placetype":"venue"
},
  "geometry": {"coordinates":[15.0941410065,47.3809585571],"type":"Point"}
}