{
  "type": "Feature",
  "properties": {
    "iso:country":"AT",
    "sg:address":"Kaiserebersdorferstr 330",
    "sg:city":"Wien",
    "sg:classifiers":[
        {
            "category":"Restaurant",
            "type":"Food & Drink"
        }
    ],
    "sg:phone":"+43 4317 698776",
    "sg:postcode":"1110",
    "sg:province":"Wien",
    "wof:name":"Restaurant z schwarzen Adler",
    "wof:placetype":"venue"
},
  "geometry": {"coordinates":[16.4726371765,48.1587104797],"type":"Point"}
}