{
  "type": "Feature",
  "properties": {
    "addr:full":"Forstgartenstr 22 Spittal an der Drau K\u00e4rnten 9800",
    "addr:housenumber":"22",
    "addr:postcode":"9800",
    "addr:street":"Forstgartenstr;Kaernten",
    "iso:country":"AT",
    "sg:address":"Forstgartenstr 22",
    "sg:city":"Spittal an der Drau",
    "sg:orig_category":"Hafnereien",
    "sg:phone":"+43 4762 3150",
    "sg:postcode":"9800",
    "sg:province":"K\u00e4rnten",
    "wof:name":"Zm\u00f6lnig Richard",
    "wof:placetype":"venue"
},
  "geometry": {"coordinates":[13.4942560196,46.7900085449],"type":"Point"}
}