{
  "type": "Feature",
  "properties": {
    "addr:full":"Prater Parz 71 Wien Wien 1020",
    "addr:housenumber":"71",
    "addr:postcode":"1020",
    "addr:street":"Parz",
    "iso:country":"AT",
    "sg:address":"Prater Parz 71",
    "sg:city":"Wien",
    "sg:orig_category":"Freizeitangebote U -Einrichtungen",
    "sg:phone":"+43 1 7293556",
    "sg:postcode":"1020",
    "sg:province":"Wien",
    "wof:name":"Jenko Karin",
    "wof:placetype":"venue"
},
  "geometry": {"coordinates":[16.3802642822,48.2153701782],"type":"Point"}
}