{
  "type": "Feature",
  "properties": {
    "addr:full":"Kellerg 10 Linz Ober\u00f6sterreich 4020",
    "addr:housenumber":"10",
    "addr:postcode":"4020",
    "addr:street":"Kellerg",
    "iso:country":"AT",
    "sg:address":"Kellerg 10",
    "sg:city":"Linz",
    "sg:orig_category":"Fotografen",
    "sg:phone":"+43 732 614891",
    "sg:postcode":"4020",
    "sg:province":"Ober\u00f6sterreich",
    "wof:name":"Wohlschlager G\u00fcnter",
    "wof:placetype":"venue"
},
  "geometry": {"coordinates":[14.2844381332,48.2939682007],"type":"Point"}
}