{
  "type": "Feature",
  "properties": {
    "addr:full":"Hauptpl 7 Traismauer Nieder\u00f6sterreich 3133",
    "addr:housenumber":"7",
    "addr:postcode":"3133",
    "addr:street":"Hauptpl",
    "iso:country":"AT",
    "sg:address":"Hauptpl 7",
    "sg:city":"Traismauer",
    "sg:orig_category":"Handarbeiten",
    "sg:phone":"+43 2783 8792",
    "sg:postcode":"3133",
    "sg:province":"Nieder\u00f6sterreich",
    "wof:name":"Wollstube Sachs",
    "wof:placetype":"venue"
},
  "geometry": {"coordinates":[15.7430381775,48.3507614136],"type":"Point"}
}