{
  "type": "Feature",
  "properties": {
    "addr:full":"Industrieweg 1 Gro\u00df Siegharts Nieder\u00f6sterreich 3812",
    "addr:housenumber":"1",
    "addr:postcode":"3812",
    "addr:street":"Industrieweg",
    "iso:country":"AT",
    "sg:address":"Industrieweg 1",
    "sg:city":"Gro\u00df Siegharts",
    "sg:classifiers":[
        {
            "category":"Manufacturing",
            "subcategory":"Textiles",
            "type":"Manufacturing & Wholesale Goods"
        }
    ],
    "sg:phone":"+43 4328 472520",
    "sg:postcode":"3812",
    "sg:province":"Nieder\u00f6sterreich",
    "sg:tags":[
        "leather",
        "raw",
        "material",
        "-"
    ],
    "wof:name":"WALDVIERTLER- ETIKETTEN- WEBEREI GES.MBH",
    "wof:placetype":"venue"
},
  "geometry": {"coordinates":[15.4131593704,48.7981796265],"type":"Point"}
}