{
  "type": "Feature",
  "properties": {
    "addr:full":"Hauptstr 56 Rosental an der Kainach Steiermark 8582",
    "addr:housenumber":"56",
    "addr:postcode":"8582",
    "addr:street":"Hauptstr",
    "iso:country":"AT",
    "sg:address":"Hauptstr 56",
    "sg:city":"Rosental an der Kainach",
    "sg:orig_category":"Maler, Anstreicher U Lackierer",
    "sg:phone":"+43 4331 4222739",
    "sg:postcode":"8582",
    "sg:province":"Steiermark",
    "wof:name":"Rajnar Manfred",
    "wof:placetype":"venue"
},
  "geometry": {"coordinates":[15.117351532,47.0545387268],"type":"Point"}
}