{
  "type": "Feature",
  "properties": {
    "addr:full":"Rulmerstr. 48  Attnang-Puchheim Ober\u00f6sterreich 4800",
    "addr:housenumber":"48",
    "addr:postcode":"4800",
    "addr:street":"Rulmerstr.",
    "iso:country":"AT",
    "sg:address":"Rulmerstr. 48 ",
    "sg:city":"Attnang-Puchheim",
    "sg:classifiers":[
        {
            "category":"Building & Trades",
            "subcategory":"Construction",
            "type":"Services"
        }
    ],
    "sg:phone":"+43 4376 74625430",
    "sg:postcode":"4800",
    "sg:province":"Ober\u00f6sterreich",
    "sg:tags":[
        "work",
        "public"
    ],
    "wof:name":"NIEDERNDORFER BAU GESMBH",
    "wof:placetype":"venue"
},
  "geometry": {"coordinates":[13.7204141617,48.0107002258],"type":"Point"}
}