{
  "type": "Feature",
  "properties": {
    "addr:full":"Oberhaus 65 Raggal Vorarlberg 6741",
    "addr:housenumber":"65",
    "addr:postcode":"6741",
    "addr:street":"Oberhaus",
    "iso:country":"AT",
    "sg:address":"Oberhaus 65",
    "sg:city":"Raggal",
    "sg:orig_category":"Appartements / Ferienwohnungen",
    "sg:phone":"+43 5553 263",
    "sg:postcode":"6741",
    "sg:province":"Vorarlberg",
    "wof:name":"Schneider Peter",
    "wof:placetype":"venue"
},
  "geometry": {"coordinates":[9.8354673386,47.2117118835],"type":"Point"}
}