{
  "type": "Feature",
  "properties": {
    "addr:full":"Griegstr 1-3/9 Wien Wien 1200",
    "addr:housenumber":"1-3 / 9",
    "addr:postcode":"1200",
    "addr:street":"Griegstr",
    "iso:country":"AT",
    "sg:address":"Griegstr 1-3/9",
    "sg:city":"Wien",
    "sg:orig_category":"Befestigungstechnik",
    "sg:phone":"+43 4313 304208",
    "sg:postcode":"1200",
    "sg:province":"Wien",
    "wof:name":"Fiala Johann - Inh Bruckl Alice",
    "wof:placetype":"venue"
},
  "geometry": {"coordinates":[16.3734645844,48.2306060791],"type":"Point"}
}