{
  "type": "Feature",
  "properties": {
    "addr:full":"Simmeringer Hauptstr 96A Wien Wien 1110",
    "addr:housenumber":"96a",
    "addr:postcode":"1110",
    "addr:street":"Simmeringer Hauptstr",
    "iso:country":"AT",
    "sg:address":"Simmeringer Hauptstr 96A",
    "sg:city":"Wien",
    "sg:orig_category":"Fotoausarbeitungen",
    "sg:phone":"+43 1 7433090",
    "sg:postcode":"1110",
    "sg:province":"Wien",
    "wof:name":"Bildermacher",
    "wof:placetype":"venue"
},
  "geometry": {"coordinates":[16.4335365295,48.1585578918],"type":"Point"}
}