{
  "type": "Feature",
  "properties": {
    "iso:country":"AT",
    "sg:address":"Kienmayerg 8",
    "sg:city":"Wien",
    "sg:orig_category":"Dentalwaren",
    "sg:phone":"+43 1 9856986",
    "sg:postcode":"1140",
    "sg:province":"Wien",
    "wof:name":"Bauer Wolfgang Dentalwaren-Edelmetalle GesmbH",
    "wof:placetype":"venue"
},
  "geometry": {"coordinates":[16.3163509369,48.199546814],"type":"Point"}
}