{
  "type": "Feature",
  "properties": {
    "addr:full":"Schallmooser Hauptstr 59 Salzburg Salzburg 5020",
    "addr:housenumber":"59",
    "addr:postcode":"5020",
    "addr:street":"Schallmooser Hauptstr;Salzburg",
    "iso:country":"AT",
    "sg:address":"Schallmooser Hauptstr 59",
    "sg:city":"Salzburg",
    "sg:orig_category":"Tischlereien",
    "sg:phone":"+43 4366 2885986",
    "sg:postcode":"5020",
    "sg:province":"Salzburg",
    "wof:name":"Famler Einrichtungen GesmbH",
    "wof:placetype":"venue"
},
  "geometry": {"coordinates":[13.0577840805,47.8072280884],"type":"Point"}
}