{
  "type": "Feature",
  "properties": {
    "addr:full":"Neulerchenfelder Str 2 Wien Wien 1160",
    "addr:housenumber":"2",
    "addr:postcode":"1160",
    "addr:street":"Str",
    "iso:country":"AT",
    "sg:address":"Neulerchenfelder Str 2",
    "sg:city":"Wien",
    "sg:orig_category":"Lederwaren / Einzelhandel",
    "sg:phone":"+43 1 9905730",
    "sg:postcode":"1160",
    "sg:province":"Wien",
    "wof:name":"Leder Mayer Handels GmbH",
    "wof:placetype":"venue"
},
  "geometry": {"coordinates":[16.338394165,48.2109375],"type":"Point"}
}