{
  "type": "Feature",
  "properties": {
    "addr:full":"Dr.-Arthur-Lemisch-Str 16 Feldkirchen in K\u00e4rnten K\u00e4rnten 9560",
    "addr:housenumber":"16",
    "addr:postcode":"9560",
    "addr:street":"Dr.-Arthur-Lemisch-Str;Kaernten",
    "iso:country":"AT",
    "sg:address":"Dr.-Arthur-Lemisch-Str 16",
    "sg:city":"Feldkirchen in K\u00e4rnten",
    "sg:orig_category":"Tankstellen",
    "sg:phone":"+43 4342 762331",
    "sg:postcode":"9560",
    "sg:province":"K\u00e4rnten",
    "wof:name":"Shell Austria GmbH",
    "wof:placetype":"venue"
},
  "geometry": {"coordinates":[14.090180397,46.7263298035],"type":"Point"}
}