{
  "type": "Feature",
  "properties": {
    "iso:country":"AT",
    "sg:address":"Lerchenfelder Str 120",
    "sg:city":"Wien",
    "sg:orig_category":"Ingenieurkonsulenten / Zivilingenieure",
    "sg:phone":"+43 1 4087745",
    "sg:postcode":"1080",
    "sg:province":"Wien",
    "wof:name":"Pulay Franz Prof Dipl-Ing",
    "wof:placetype":"venue"
},
  "geometry": {"coordinates":[16.3428668976,48.2078132629],"type":"Point"}
}