{
  "type": "Feature",
  "properties": {
    "addr:full":"Nr 37 Landeck Tirol 6500",
    "addr:postcode":"6500",
    "addr:street":"Nr 37;Tirol",
    "iso:country":"AT",
    "sg:address":"Nr 37",
    "sg:city":"Landeck",
    "sg:orig_category":"Tischlereien",
    "sg:phone":"+43 4354 4268140",
    "sg:postcode":"6500",
    "sg:province":"Tirol",
    "wof:name":"Ing R u S Tischlerei - Rudig Christine u Stadlwieser Werner",
    "wof:placetype":"venue"
},
  "geometry": {"coordinates":[10.5670547485,47.1368560791],"type":"Point"}
}