{
  "type": "Feature",
  "properties": {
    "iso:country":"AT",
    "sg:address":"Neutorstrasse 46",
    "sg:city":"Salzburg",
    "sg:classifiers":[
        {
            "category":"Real Estate",
            "subcategory":"Real Estate Services",
            "type":"Services"
        }
    ],
    "sg:phone":"+43 662 833787",
    "sg:postcode":"5020",
    "sg:province":"Salzburg",
    "sg:tags":[
        "leather",
        "belt"
    ],
    "wof:name":"Alois Eisl",
    "wof:placetype":"venue"
},
  "geometry": {"coordinates":[13.02775383,47.796459198],"type":"Point"}
}