{
  "type": "Feature",
  "properties": {
    "iso:country":"AT",
    "sg:address":"Elisabethstr 84",
    "sg:city":"Graz",
    "sg:orig_category":"Forschungsinstitute",
    "sg:phone":"+43 316 325776",
    "sg:postcode":"8010",
    "sg:province":"Steiermark",
    "wof:name":"Oridis Biomed Forschungs- und Entwicklungs GmbH",
    "wof:placetype":"venue"
},
  "geometry": {"coordinates":[15.4624967575,47.0777931213],"type":"Point"}
}