{
  "type": "Feature",
  "properties": {
    "addr:full":"Linzer Str 58 Freistadt Ober\u00f6sterreich 4240",
    "addr:housenumber":"58",
    "addr:postcode":"4240",
    "addr:street":"Linzer Str",
    "iso:country":"AT",
    "sg:address":"Linzer Str 58",
    "sg:city":"Freistadt",
    "sg:orig_category":"Baumschulen",
    "sg:phone":"+43 4379 4274592",
    "sg:postcode":"4240",
    "sg:province":"Ober\u00f6sterreich",
    "wof:name":"Baumschule Hennerbichler Klaus GmbH & Co",
    "wof:placetype":"venue"
},
  "geometry": {"coordinates":[14.5027914047,48.4992141724],"type":"Point"}
}