{
  "type": "Feature",
  "properties": {
    "addr:full":"Kranzmayerstr 52 Klagenfurt K\u00e4rnten 9020",
    "addr:housenumber":"52",
    "addr:postcode":"9020",
    "addr:street":"Kranzmayerstr;Kaernten",
    "iso:country":"AT",
    "sg:address":"Kranzmayerstr 52",
    "sg:city":"Klagenfurt",
    "sg:classifiers":[
        {
            "category":"Organizations",
            "subcategory":"Political Organization",
            "type":"Services"
        }
    ],
    "sg:phone":"+43 699 18422171",
    "sg:postcode":"9020",
    "sg:province":"K\u00e4rnten",
    "sg:tags":[
        "mediation"
    ],
    "wof:name":"Mediation Klagenfurt",
    "wof:placetype":"venue"
},
  "geometry": {"coordinates":[14.272813797,46.6130371094],"type":"Point"}
}