{
  "type": "Feature",
  "properties": {
    "iso:country":"AT",
    "sg:address":"Zehetnersdlg 16",
    "sg:city":"Aschach an der Steyr",
    "sg:orig_category":"Maschinenbau",
    "sg:phone":"+43 676 9547932",
    "sg:postcode":"4421",
    "sg:province":"Ober\u00f6sterreich",
    "wof:name":"GTS Glastechnischer Service GesmbH",
    "wof:placetype":"venue"
},
  "geometry": {"coordinates":[14.3353204727,48.0124549866],"type":"Point"}
}