{
  "type": "Feature",
  "properties": {
    "iso:country":"AT",
    "sg:address":"Nr 150",
    "sg:city":"Umhausen",
    "sg:orig_category":"Banken U Sparkassen",
    "sg:phone":"+43 4352 555570",
    "sg:postcode":"6441",
    "sg:province":"Tirol",
    "wof:name":"Raiffeisenbank vorderes \u00f6tztal - Filiale Tumpen",
    "wof:placetype":"venue"
},
  "geometry": {"coordinates":[166.9221496582,-0.5282999873],"type":"Point"}
}