{
  "type": "Feature",
  "properties": {
    "iso:country":"AT",
    "sg:address":"Guritzerstr 27",
    "sg:city":"Salzburg",
    "sg:orig_category":"Garten- U Landschaftsgestaltung",
    "sg:phone":"+43 676 3563035",
    "sg:postcode":"5020",
    "sg:province":"Salzburg",
    "wof:name":"LSD Landscape Design",
    "wof:placetype":"venue"
},
  "geometry": {"coordinates":[13.0016918182,47.8123588562],"type":"Point"}
}