{
  "type": "Feature",
  "properties": {
    "addr:full":"Burgergarten 10 Aurolzm\u00fcnster Ober\u00f6sterreich 4971",
    "addr:housenumber":"10",
    "addr:postcode":"4971",
    "addr:street":"Burgergarten;Oberoesterreich",
    "iso:country":"AT",
    "sg:address":"Burgergarten 10",
    "sg:city":"Aurolzm\u00fcnster",
    "sg:classifiers":[
        {
            "category":"Organizations",
            "subcategory":"Community Association",
            "type":"Services"
        }
    ],
    "sg:phone":"+43 7752 830300",
    "sg:postcode":"4971",
    "sg:province":"Ober\u00f6sterreich",
    "sg:tags":[
        "relation",
        "public"
    ],
    "wof:name":"Ideenkreis - Hujber & Reindl OEG",
    "wof:placetype":"venue"
},
  "geometry": {"coordinates":[13.4526472092,48.2450523376],"type":"Point"}
}