{
  "type": "Feature",
  "properties": {
    "iso:country":"AT",
    "sg:address":"R\u00f6merstr 28",
    "sg:city":"Stra\u00df in Steiermark",
    "sg:orig_category":"Zimmereien",
    "sg:phone":"+43 699 13251224",
    "sg:postcode":"8472",
    "sg:province":"Steiermark",
    "wof:name":"Strassberger Claus GesmbH",
    "wof:placetype":"venue"
},
  "geometry": {"coordinates":[15.6012849808,46.7366752625],"type":"Point"}
}