{
  "type": "Feature",
  "properties": {
    "iso:country":"AT",
    "sg:address":"Nr 29",
    "sg:city":"Kirchbichl",
    "sg:orig_category":"Gemeinden",
    "sg:phone":"+43 5332 56476",
    "sg:postcode":"6322",
    "sg:province":"Tirol",
    "wof:name":"Gemeindeamt Mariastein",
    "wof:placetype":"venue"
},
  "geometry": {"coordinates":[12.0880002975,47.5128707886],"type":"Point"}
}