{
  "type": "Feature",
  "properties": {
    "iso:country":"AT",
    "sg:address":"Giersterg 4",
    "sg:city":"Wien",
    "sg:orig_category":"Altwaren",
    "sg:phone":"+43 1 8154483",
    "sg:postcode":"1120",
    "sg:province":"Wien",
    "wof:name":"Sammelsurium - Nostalgie B\u00fccher",
    "wof:placetype":"venue"
},
  "geometry": {"coordinates":[16.334236145,48.1837654114],"type":"Point"}
}