{
  "type": "Feature",
  "properties": {
    "addr:full":"Mantlerg 47/12 Wien Wien 1130",
    "addr:housenumber":"47 / 12",
    "addr:postcode":"1130",
    "addr:street":"Mantlerg",
    "iso:country":"AT",
    "sg:address":"Mantlerg 47/12",
    "sg:city":"Wien",
    "sg:orig_category":"Psychotherapie",
    "sg:phone":"+43 1 8792701",
    "sg:postcode":"1130",
    "sg:province":"Wien",
    "wof:name":"Dolak Elisabeth Dr",
    "wof:placetype":"venue"
},
  "geometry": {"coordinates":[16.2803344727,48.1910514832],"type":"Point"}
}