{
  "type": "Feature",
  "properties": {
    "iso:country":"AT",
    "sg:address":"Villacher Str. 93-95",
    "sg:city":"Spittal an der Drau",
    "sg:classifiers":[
        {
            "category":"Personal",
            "subcategory":"Shoe Repair & Shine",
            "type":"Services"
        }
    ],
    "sg:phone":"+43 4347 6248110",
    "sg:postcode":"9800",
    "sg:province":"K\u00e4rnten",
    "sg:tags":[
        "leather"
    ],
    "wof:name":"GABOR GES.MBH",
    "wof:placetype":"venue"
},
  "geometry": {"coordinates":[13.486869812,46.8216552734],"type":"Point"}
}