{
  "type": "Feature",
  "properties": {
    "addr:full":"Industriezeile 50A Braunau am Inn Ober\u00f6sterreich 5280",
    "addr:housenumber":"50a",
    "addr:postcode":"5280",
    "addr:street":"Industriezeile",
    "iso:country":"AT",
    "sg:address":"Industriezeile 50A",
    "sg:city":"Braunau am Inn",
    "sg:orig_category":"Metallbe- U -Verarbeitung",
    "sg:phone":"+43 4377 2263749",
    "sg:postcode":"5280",
    "sg:province":"Ober\u00f6sterreich",
    "wof:name":"TEAMwork Holz- u Kunststoffverarbeitung GmbH",
    "wof:placetype":"venue"
},
  "geometry": {"coordinates":[13.0559072495,48.2460975647],"type":"Point"}
}