{
  "type": "Feature",
  "properties": {
    "addr:full":"Kirchenpl Schrems Nieder\u00f6sterreich 3943",
    "addr:postcode":"3943",
    "addr:street":"Niederoesterreich",
    "iso:country":"AT",
    "sg:address":"Kirchenpl",
    "sg:city":"Schrems",
    "sg:orig_category":"Museen / Ausstellungen",
    "sg:phone":"+43 2853 76502",
    "sg:postcode":"3943",
    "sg:province":"Nieder\u00f6sterreich",
    "wof:name":"Museum und B\u00fccherei d Stadtgemeinde",
    "wof:placetype":"venue"
},
  "geometry": {"coordinates":[15.0688295364,48.7935600281],"type":"Point"}
}