{
  "type": "Feature",
  "properties": {
    "addr:full":"Schulweg 17 Ehrwald Tirol 6632",
    "addr:housenumber":"17",
    "addr:postcode":"6632",
    "addr:street":"Schulweg;Tirol",
    "iso:country":"AT",
    "sg:address":"Schulweg 17",
    "sg:city":"Ehrwald",
    "sg:orig_category":"Pensionen / Privatzimmer",
    "sg:phone":"+43 5673 2632",
    "sg:postcode":"6632",
    "sg:province":"Tirol",
    "wof:name":"Schennach Robert",
    "wof:placetype":"venue"
},
  "geometry": {"coordinates":[10.919634819,47.3999290466],"type":"Point"}
}