{
  "type": "Feature",
  "properties": {
    "iso:country":"AT",
    "sg:address":"Winertsham 4",
    "sg:city":"Andorf",
    "sg:orig_category":"Lastkraftwagen",
    "sg:phone":"+43 7766 41230",
    "sg:postcode":"4770",
    "sg:province":"Ober\u00f6sterreich",
    "wof:name":"KLV Rent Nutzfahrzeuge GesmbH",
    "wof:placetype":"venue"
},
  "geometry": {"coordinates":[13.5736274719,48.379863739],"type":"Point"}
}