{
  "type": "Feature",
  "properties": {
    "addr:full":"Favoritenstr 173 Wien Wien 1100",
    "addr:housenumber":"173",
    "addr:postcode":"1100",
    "iso:country":"AT",
    "sg:address":"Favoritenstr 173",
    "sg:city":"Wien",
    "sg:orig_category":"Pizzazustellungen",
    "sg:phone":"+43 1 601380",
    "sg:postcode":"1100",
    "sg:province":"Wien",
    "wof:name":"Pizza Taxi - Da Pina",
    "wof:placetype":"venue"
},
  "geometry": {"coordinates":[16.3814201355,48.1672897339],"type":"Point"}
}