{
  "type": "Feature",
  "properties": {
    "addr:full":"Fasangarteng 103 Wien Wien 1130",
    "addr:housenumber":"103",
    "addr:postcode":"1130",
    "iso:country":"AT",
    "sg:address":"Fasangarteng 103",
    "sg:city":"Wien",
    "sg:classifiers":[
        {
            "category":"Utilities",
            "subcategory":"Refuse",
            "type":"Services"
        }
    ],
    "sg:phone":"+43 4369 914828253",
    "sg:postcode":"1130",
    "sg:province":"Wien",
    "sg:tags":[
        "catering"
    ],
    "sg:website":"catering.co.at",
    "wof:name":"Heidi's Exquisit Catering",
    "wof:placetype":"venue"
},
  "geometry": {"coordinates":[16.2976493835,48.1720542908],"type":"Point"}
}