{
  "type": "Feature",
  "properties": {
    "iso:country":"AT",
    "sg:address":"Tenschertstrasse 8",
    "sg:city":"Wien",
    "sg:classifiers":[
        {
            "category":"Communications",
            "subcategory":"Television Station",
            "type":"Services"
        }
    ],
    "sg:phone":"+43 1 6167871",
    "sg:postcode":"1230",
    "sg:province":"Wien",
    "sg:tags":[
        "machine",
        "answering"
    ],
    "sg:website":"tiptel.at",
    "wof:name":"Tiptel GmbH",
    "wof:placetype":"venue"
},
  "geometry": {"coordinates":[16.3558101654,48.1400947571],"type":"Point"}
}