{
  "type": "Feature",
  "properties": {
    "addr:full":"Gro\u00dfe Zeile 5 Feuersbrunn Nieder\u00f6sterreich 3483",
    "addr:housenumber":"5",
    "addr:postcode":"3483",
    "addr:street":"Grosse Zeile;Niederoesterreich",
    "iso:country":"AT",
    "sg:address":"Gro\u00dfe Zeile 5",
    "sg:city":"Feuersbrunn",
    "sg:orig_category":"Gemeinden",
    "sg:phone":"+43 2738 2214",
    "sg:postcode":"3483",
    "sg:province":"Nieder\u00f6sterreich",
    "wof:name":"Gemeindeamt Feuersbrunn",
    "wof:placetype":"venue"
},
  "geometry": {"coordinates":[15.7867498398,48.4396514893],"type":"Point"}
}