{
  "type": "Feature",
  "properties": {
    "addr:full":"Hasenfeldstr 12a Lustenau Vorarlberg 6890",
    "addr:housenumber":"12a",
    "addr:postcode":"6890",
    "addr:street":"Hasenfeldstr",
    "iso:country":"AT",
    "sg:address":"Hasenfeldstr 12a",
    "sg:city":"Lustenau",
    "sg:orig_category":"Hauptschulen",
    "sg:phone":"+43 5577 886260",
    "sg:postcode":"6890",
    "sg:province":"Vorarlberg",
    "wof:name":"Hauptschule Hasenfeld",
    "wof:placetype":"venue"
},
  "geometry": {"coordinates":[9.6580381393,47.4166183472],"type":"Point"}
}