{
  "type": "Feature",
  "properties": {
    "addr:full":"Uetzg 6b Baden Nieder\u00f6sterreich 2500",
    "addr:housenumber":"6b",
    "addr:postcode":"2500",
    "addr:street":"Uetzg;Niederoesterreich",
    "iso:country":"AT",
    "sg:address":"Uetzg 6b",
    "sg:city":"Baden",
    "sg:orig_category":"Baumeister",
    "sg:phone":"+43 2252 84352",
    "sg:postcode":"2500",
    "sg:province":"Nieder\u00f6sterreich",
    "wof:name":"Beer Gerald Ing",
    "wof:placetype":"venue"
},
  "geometry": {"coordinates":[16.2348117828,48.0019836426],"type":"Point"}
}