{
  "type": "Feature",
  "properties": {
    "addr:full":"Hindenburgstr 11 Poysdorf Nieder\u00f6sterreich 2170",
    "addr:housenumber":"11",
    "addr:postcode":"2170",
    "addr:street":"Hindenburgstr",
    "iso:country":"AT",
    "sg:address":"Hindenburgstr 11",
    "sg:city":"Poysdorf",
    "sg:orig_category":"Speditionen",
    "sg:phone":"+43 4325 5225880",
    "sg:postcode":"2170",
    "sg:province":"Nieder\u00f6sterreich",
    "wof:name":"Gutmayer GesmbH",
    "wof:placetype":"venue"
},
  "geometry": {"coordinates":[16.6295642853,48.6652679443],"type":"Point"}
}