{
  "type": "Feature",
  "properties": {
    "addr:full":"Czeija-Nissl-Gasse 5 Wien Wien 1210",
    "addr:housenumber":"5",
    "addr:postcode":"1210",
    "addr:street":"Czeija-Nissl-Gasse",
    "iso:country":"AT",
    "sg:address":"Czeija-Nissl-Gasse 5",
    "sg:city":"Wien",
    "sg:classifiers":[
        {
            "category":"Banks & Credit Unions",
            "subcategory":"Investment Brokerage",
            "type":"Services"
        }
    ],
    "sg:phone":"+43 1 2707008",
    "sg:postcode":"1210",
    "sg:province":"Wien",
    "sg:tags":[
        "vessel",
        "steel",
        "agitator",
        "stainless"
    ],
    "sg:website":"vana-wien.at",
    "wof:name":"Vana Kupferschmiede und Apparatebau GmbH",
    "wof:placetype":"venue"
},
  "geometry": {"coordinates":[16.374879837,48.2846488953],"type":"Point"}
}