{
  "type": "Feature",
  "properties": {
    "iso:country":"AT",
    "sg:address":"Ghegastr 1",
    "sg:city":"Gunskirchen",
    "sg:orig_category":"Schilder",
    "sg:phone":"+43 7246 7564",
    "sg:postcode":"4623",
    "sg:province":"Ober\u00f6sterreich",
    "wof:name":"Luttinger Robert",
    "wof:placetype":"venue"
},
  "geometry": {"coordinates":[13.9447231293,48.1301040649],"type":"Point"}
}