{
  "type": "Feature",
  "properties": {
    "addr:full":"Ackerg 2 Tribuswinkel Nieder\u00f6sterreich 2512",
    "addr:housenumber":"2",
    "addr:postcode":"2512",
    "addr:street":"Ackerg",
    "iso:country":"AT",
    "sg:address":"Ackerg 2",
    "sg:city":"Tribuswinkel",
    "sg:classifiers":[
        {
            "category":"Internet Cafe",
            "subcategory":"None",
            "type":"Food & Drink"
        }
    ],
    "sg:phone":"+43 2252 209354",
    "sg:postcode":"2512",
    "sg:province":"Nieder\u00f6sterreich",
    "wof:name":"Pc@man Computer & Netzwerk Service Ing Gregor Nowotny",
    "wof:placetype":"venue"
},
  "geometry": {"coordinates":[16.2944698334,47.9887886047],"type":"Point"}
}