{
  "type": "Feature",
  "properties": {
    "iso:country":"AT",
    "sg:address":"Gerhardusg 25",
    "sg:city":"Wien",
    "sg:orig_category":"Offsetdruckereien",
    "sg:phone":"+43 4312 5971210",
    "sg:postcode":"1200",
    "sg:province":"Wien",
    "wof:name":"Mayer & Comp Druck- u VerlagsgesmbH",
    "wof:placetype":"venue"
},
  "geometry": {"coordinates":[16.3734645844,48.2306060791],"type":"Point"}
}