{
  "type": "Feature",
  "properties": {
    "iso:country":"AT",
    "sg:address":"Laxenburger Str 10",
    "sg:city":"Wiener Neudorf",
    "sg:orig_category":"\u00c3\u201enderungsschneidereien",
    "sg:phone":"+43 2236 677733",
    "sg:postcode":"2351",
    "sg:province":"Nieder\u00f6sterreich",
    "wof:name":"\u00c4nderungsatelier Brigitta Gatek",
    "wof:placetype":"venue"
},
  "geometry": {"coordinates":[16.3151893616,48.0825920105],"type":"Point"}
}