{
  "type": "Feature",
  "properties": {
    "addr:full":"Aueng. 11  Ferlach K\u00e4rnten 9170",
    "addr:housenumber":"11",
    "addr:postcode":"9170",
    "addr:street":"Aueng.;Kaernten",
    "iso:country":"AT",
    "sg:address":"Aueng. 11 ",
    "sg:city":"Ferlach",
    "sg:classifiers":[
        {
            "category":"Manufacturing",
            "subcategory":"Metals",
            "type":"Manufacturing & Wholesale Goods"
        }
    ],
    "sg:phone":"+43 4342 2727150",
    "sg:postcode":"9170",
    "sg:province":"K\u00e4rnten",
    "sg:tags":[
        "metallurgy",
        "metalworking"
    ],
    "wof:name":"ALPEN MAY KESTAG GMBH",
    "wof:placetype":"venue"
},
  "geometry": {"coordinates":[14.2950754166,46.5175132751],"type":"Point"}
}