{
  "type": "Feature",
  "properties": {
    "iso:country":"AT",
    "sg:address":"Johann-Nepomuk-Berger-Str 2",
    "sg:city":"Mattersburg",
    "sg:orig_category":"Montagen U Montagetechnik",
    "sg:phone":"+43 4326 2279735",
    "sg:postcode":"7210",
    "sg:province":"Burgenland",
    "wof:name":"M.S.S. Montage-Service-Szabo - Montage v Whirlpools u Duschkabinen",
    "wof:placetype":"venue"
},
  "geometry": {"coordinates":[16.4031429291,47.7357254028],"type":"Point"}
}