{
  "type": "Feature",
  "properties": {
    "addr:full":"Glimpfingerstr 48 Linz Ober\u00f6sterreich 4020",
    "addr:housenumber":"48",
    "addr:postcode":"4020",
    "addr:street":"Glimpfingerstr",
    "iso:country":"AT",
    "sg:address":"Glimpfingerstr 48",
    "sg:city":"Linz",
    "sg:classifiers":[
        {
            "category":"Shopping",
            "subcategory":"Thrift Store",
            "type":"Retail Goods"
        }
    ],
    "sg:phone":"+43 732 3498160",
    "sg:postcode":"4020",
    "sg:province":"Ober\u00f6sterreich",
    "sg:tags":[
        "second-hand-shops"
    ],
    "wof:name":"Basar HandelsgesmbH",
    "wof:placetype":"venue"
},
  "geometry": {"coordinates":[14.3056411743,48.2744026184],"type":"Point"}
}