{
  "type": "Feature",
  "properties": {
    "iso:country":"AT",
    "sg:address":"Trauzlg. 4",
    "sg:city":"Wien",
    "sg:classifiers":[
        {
            "category":"Parking",
            "subcategory":"Lot",
            "type":"Transportation"
        }
    ],
    "sg:phone":"+43 4312 7836110",
    "sg:postcode":"1210",
    "sg:province":"Wien",
    "sg:tags":[
        "transport",
        "road"
    ],
    "wof:name":"OEMAKO LAGERBETRIEB & TRANSPORT GMBH",
    "wof:placetype":"venue"
},
  "geometry": {"coordinates":[16.3690719604,48.2848205566],"type":"Point"}
}