{
  "type": "Feature",
  "properties": {
    "addr:full":"Nr 6 Stanzach Tirol 6642",
    "addr:postcode":"6642",
    "addr:street":"Nr;Stanzach Tirol",
    "iso:country":"AT",
    "sg:address":"Nr 6",
    "sg:city":"Stanzach",
    "sg:orig_category":"Bankomat-Standorte",
    "sg:phone":"+43 5632 231",
    "sg:postcode":"6642",
    "sg:province":"Tirol",
    "wof:name":"Bankomat d Raiffeisenbank Reutte regGenmbH",
    "wof:placetype":"venue"
},
  "geometry": {"coordinates":[10.5403499603,47.3699111938],"type":"Point"}
}