{
  "type": "Feature",
  "properties": {
    "iso:country":"AT",
    "sg:address":"Steing 21a",
    "sg:city":"Linz",
    "sg:orig_category":"Friseure U Frisiersalons",
    "sg:phone":"+43 4373 2777654",
    "sg:postcode":"4020",
    "sg:province":"Ober\u00f6sterreich",
    "sg:website":"mittermeier.at",
    "wof:name":"Salon Gabriele Mittermeier",
    "wof:placetype":"venue"
},
  "geometry": {"coordinates":[14.2835187912,48.3010406494],"type":"Point"}
}