{
  "type": "Feature",
  "properties": {
    "iso:country":"AT",
    "sg:address":"Vogelweider Str 43a",
    "sg:city":"Wels",
    "sg:orig_category":"Banken U Sparkassen",
    "sg:phone":"+43 4372 42681860",
    "sg:postcode":"4600",
    "sg:province":"Ober\u00f6sterreich",
    "wof:name":"Bankomat d Oberbank AG",
    "wof:placetype":"venue"
},
  "geometry": {"coordinates":[14.0117397308,48.1631355286],"type":"Point"}
}