{
  "type": "Feature",
  "properties": {
    "iso:country":"AT",
    "sg:address":"Erbachstr 32",
    "sg:city":"Deutsch Wagram",
    "sg:orig_category":"Bekleidung / Erzeugung U Gro\u00c3\u0178handel",
    "sg:phone":"+43 4322 473318",
    "sg:postcode":"2232",
    "sg:province":"Nieder\u00f6sterreich",
    "wof:name":"Kuchar Agentur",
    "wof:placetype":"venue"
},
  "geometry": {"coordinates":[16.5654125214,48.3015136719],"type":"Point"}
}