{
  "type": "Feature",
  "properties": {
    "addr:full":"Nr 68 Rennweg K\u00e4rnten 9863",
    "addr:postcode":"9863",
    "addr:street":"Nr;Rennweg Kaernten",
    "iso:country":"AT",
    "sg:address":"Nr 68",
    "sg:city":"Rennweg",
    "sg:orig_category":"Appartements / Ferienwohnungen",
    "sg:phone":"+43 4734 3420",
    "sg:postcode":"9863",
    "sg:province":"K\u00e4rnten",
    "wof:name":"Aigner Karl",
    "wof:placetype":"venue"
},
  "geometry": {"coordinates":[13.6159286499,47.058631897],"type":"Point"}
}