{
  "type": "Feature",
  "properties": {
    "addr:full":"Custozzag 3 Wien Wien 1030",
    "addr:housenumber":"3",
    "addr:postcode":"1030",
    "addr:street":"Custozzag",
    "iso:country":"AT",
    "sg:address":"Custozzag 3",
    "sg:city":"Wien",
    "sg:orig_category":"Maler, Anstreicher U Lackierer",
    "sg:phone":"+43 1 7182251",
    "sg:postcode":"1030",
    "sg:province":"Wien",
    "wof:name":"Reitmeier Horst GmbH",
    "wof:placetype":"venue"
},
  "geometry": {"coordinates":[16.3927364349,48.2093734741],"type":"Point"}
}