{
  "type": "Feature",
  "properties": {
    "addr:full":"Nr 100 Taufkirchen an der Pram Ober\u00f6sterreich 4775",
    "addr:postcode":"4775",
    "addr:street":"Nr 100",
    "iso:country":"AT",
    "sg:address":"Nr 100",
    "sg:city":"Taufkirchen an der Pram",
    "sg:orig_category":"Gemeinden",
    "sg:phone":"+43 4377 1972550",
    "sg:postcode":"4775",
    "sg:province":"Ober\u00f6sterreich",
    "wof:name":"Gemeindeamt Taufkirchen a d Pram",
    "wof:placetype":"venue"
},
  "geometry": {"coordinates":[13.5362701416,48.4104499817],"type":"Point"}
}