{
  "type": "Feature",
  "properties": {
    "iso:country":"AT",
    "sg:address":"Umfahrungsstr 1",
    "sg:city":"Hadersdorf am Kamp",
    "sg:orig_category":"Sportanlagen",
    "sg:phone":"+43 2735 3400",
    "sg:postcode":"3493",
    "sg:province":"Nieder\u00f6sterreich",
    "wof:name":"Eislaufplatz Hadersdorf am Kamp",
    "wof:placetype":"venue"
},
  "geometry": {"coordinates":[15.7205963135,48.4622383118],"type":"Point"}
}