{
  "type": "Feature",
  "properties": {
    "iso:country":"AT",
    "sg:address":"Brucker Str 8",
    "sg:city":"Gratkorn",
    "sg:orig_category":"Bekleidung / Erzeugung U Gro\u00c3\u0178handel",
    "sg:phone":"+43 3124 24520",
    "sg:postcode":"8101",
    "sg:province":"Steiermark",
    "wof:name":"Landhaus Mode Kirchmayer",
    "wof:placetype":"venue"
},
  "geometry": {"coordinates":[15.3379688263,47.1337280273],"type":"Point"}
}