{
  "type": "Feature",
  "properties": {
    "addr:full":"Forstbergstr Enns Ober\u00f6sterreich 4470",
    "addr:postcode":"4470",
    "addr:street":"Oberoesterreich",
    "iso:country":"AT",
    "sg:address":"Forstbergstr",
    "sg:city":"Enns",
    "sg:orig_category":"Tankstellen",
    "sg:phone":"+43 7223 82872",
    "sg:postcode":"4470",
    "sg:province":"Ober\u00f6sterreich",
    "wof:name":"Agip Austria GmbH",
    "wof:placetype":"venue"
},
  "geometry": {"coordinates":[14.4770498276,48.2097969055],"type":"Point"}
}