{
  "type": "Feature",
  "properties": {
    "addr:full":"Paschinger Str 53 Leonding Ober\u00f6sterreich 4060",
    "addr:postcode":"4060",
    "addr:street":"Str 53",
    "iso:country":"AT",
    "sg:address":"Paschinger Str 53",
    "sg:city":"Leonding",
    "sg:orig_category":"Fassaden",
    "sg:phone":"+43 4373 26707870",
    "sg:postcode":"4060",
    "sg:province":"Ober\u00f6sterreich",
    "wof:name":"mandl+eckl Stahl- u Metallbau GmbH",
    "wof:placetype":"venue"
},
  "geometry": {"coordinates":[14.2667036057,48.2734489441],"type":"Point"}
}