{
  "type": "Feature",
  "properties": {
    "addr:full":"Schulg 10 Reichenfels K\u00e4rnten 9463",
    "addr:housenumber":"10",
    "addr:postcode":"9463",
    "addr:street":"Schulg;Kaernten",
    "iso:country":"AT",
    "sg:address":"Schulg 10",
    "sg:city":"Reichenfels",
    "sg:orig_category":"Volksschulen",
    "sg:phone":"+43 4359 2213",
    "sg:postcode":"9463",
    "sg:province":"K\u00e4rnten",
    "wof:name":"Volksschule",
    "wof:placetype":"venue"
},
  "geometry": {"coordinates":[14.7415151596,47.0093345642],"type":"Point"}
}