{
  "type": "Feature",
  "properties": {
    "addr:full":"B\u00fcrstadtstr 5 Krieglach Steiermark 8670",
    "addr:housenumber":"5",
    "addr:postcode":"8670",
    "addr:street":"Buerstadtstr",
    "iso:country":"AT",
    "sg:address":"B\u00fcrstadtstr 5",
    "sg:city":"Krieglach",
    "sg:orig_category":"Volksschulen",
    "sg:phone":"+43 3855 23680",
    "sg:postcode":"8670",
    "sg:province":"Steiermark",
    "wof:name":"Volksschule 1",
    "wof:placetype":"venue"
},
  "geometry": {"coordinates":[15.5594148636,47.5454101562],"type":"Point"}
}