{
  "type": "Feature",
  "properties": {
    "iso:country":"AT",
    "sg:address":"Scharnsteiner Str 5",
    "sg:city":"Gmunden",
    "sg:orig_category":"Schlossereien",
    "sg:phone":"+43 761270508",
    "sg:postcode":"4810",
    "sg:province":"Ober\u00f6sterreich",
    "wof:name":"Kramesberger Karl",
    "wof:placetype":"venue"
},
  "geometry": {"coordinates":[13.8191995621,47.9258575439],"type":"Point"}
}