{
  "type": "Feature",
  "properties": {
    "addr:full":"Steyr Ober\u00f6sterreich 4400",
    "addr:postcode":"4400",
    "iso:country":"AT",
    "sg:city":"Steyr",
    "sg:orig_category":"Partnervermittlung",
    "sg:phone":"+43 650 9135499",
    "sg:postcode":"4400",
    "sg:province":"Ober\u00f6sterreich",
    "wof:name":"Agentur Delphinos",
    "wof:placetype":"venue"
},
  "geometry": {"coordinates":[14.4237537384,48.0219917297],"type":"Point"}
}