{
  "type": "Feature",
  "properties": {
    "addr:full":"Ortsstr 14 Furth Nieder\u00f6sterreich 3511",
    "addr:housenumber":"14",
    "addr:postcode":"3511",
    "addr:street":"Ortsstr",
    "iso:country":"AT",
    "sg:address":"Ortsstr 14",
    "sg:city":"Furth",
    "sg:orig_category":"Dekorationsartikel",
    "sg:phone":"+43 4327 392257",
    "sg:postcode":"3511",
    "sg:province":"Nieder\u00f6sterreich",
    "wof:name":"Cosmologisches Weingut Reutter-Gorska",
    "wof:placetype":"venue"
},
  "geometry": {"coordinates":[15.6254730225,48.3793373108],"type":"Point"}
}