{
  "type": "Feature",
  "properties": {
    "addr:full":"Persal 217 Finkenberg Tirol 6292",
    "addr:housenumber":"217",
    "addr:postcode":"6292",
    "addr:street":"Persal",
    "iso:country":"AT",
    "sg:address":"Persal 217",
    "sg:city":"Finkenberg",
    "sg:classifiers":[
        {
            "category":"Travel",
            "subcategory":"Hotels & Motels",
            "type":"Entertainment"
        }
    ],
    "sg:phone":"+43 5285 634530",
    "sg:postcode":"6292",
    "sg:province":"Tirol",
    "wof:name":"Hotel-Pension Margit",
    "wof:placetype":"venue"
},
  "geometry": {"coordinates":[11.819475174,47.1515960693],"type":"Point"}
}