{
  "type": "Feature",
  "properties": {
    "addr:full":"Friedelstr 6 Klagenfurt K\u00e4rnten 9020",
    "addr:housenumber":"6",
    "addr:postcode":"9020",
    "addr:street":"Friedelstr;Kaernten",
    "iso:country":"AT",
    "sg:address":"Friedelstr 6",
    "sg:city":"Klagenfurt",
    "sg:orig_category":"Non-Classified Establishments",
    "sg:phone":"+43 463 24188",
    "sg:postcode":"9020",
    "sg:province":"K\u00e4rnten",
    "wof:name":"EVANGELIKALE GEMEINDE KLAGENFURT",
    "wof:placetype":"venue"
},
  "geometry": {"coordinates":[14.2934188843,46.6214256287],"type":"Point"}
}