{
  "type": "Feature",
  "properties": {
    "addr:full":"Au\u00dferlitzstr 35 Schruns Vorarlberg 6780",
    "addr:housenumber":"35",
    "addr:postcode":"6780",
    "addr:street":"Ausserlitzstr",
    "iso:country":"AT",
    "sg:address":"Au\u00dferlitzstr 35",
    "sg:city":"Schruns",
    "sg:orig_category":"Bestattungsunternehmen",
    "sg:phone":"+43 4355 56724730",
    "sg:postcode":"6780",
    "sg:province":"Vorarlberg",
    "wof:name":"Marent Peter KEG",
    "wof:placetype":"venue"
},
  "geometry": {"coordinates":[9.9074554443,47.0924110413],"type":"Point"}
}