{
  "type": "Feature",
  "properties": {
    "addr:full":"Klosterweg 2 Wernberg K\u00e4rnten 9241",
    "addr:housenumber":"2",
    "addr:postcode":"9241",
    "addr:street":"Klosterweg;Kaernten",
    "iso:country":"AT",
    "sg:address":"Klosterweg 2",
    "sg:city":"Wernberg",
    "sg:orig_category":"Non-Classified Establishments",
    "sg:phone":"+43 4252 22160",
    "sg:postcode":"9241",
    "sg:province":"K\u00e4rnten",
    "wof:name":"Kloster Wernberg",
    "wof:placetype":"venue"
},
  "geometry": {"coordinates":[13.9303503036,46.6211585999],"type":"Point"}
}