{
  "type": "Feature",
  "properties": {
    "addr:full":"Hauptstr 22 Spitz Nieder\u00f6sterreich 3620",
    "addr:housenumber":"22",
    "addr:postcode":"3620",
    "addr:street":"Hauptstr",
    "iso:country":"AT",
    "sg:address":"Hauptstr 22",
    "sg:city":"Spitz",
    "sg:orig_category":"Volksschulen",
    "sg:phone":"+43 2713 2324",
    "sg:postcode":"3620",
    "sg:province":"Nieder\u00f6sterreich",
    "wof:name":"Volksschule und allgemeine Sonderschule",
    "wof:placetype":"venue"
},
  "geometry": {"coordinates":[15.4152297974,48.3630599976],"type":"Point"}
}