{
  "type": "Feature",
  "properties": {
    "iso:country":"AT",
    "sg:address":"Hofgarten 25",
    "sg:city":"Katzelsdorf",
    "sg:orig_category":"Immobilienmakler",
    "sg:phone":"+43 2622 445440",
    "sg:postcode":"2801",
    "sg:province":"Nieder\u00f6sterreich",
    "wof:name":"Die Connect Data Inseratendatenbank GesmbH",
    "wof:placetype":"venue"
},
  "geometry": {"coordinates":[16.2686328888,47.7731704712],"type":"Point"}
}