{
  "type": "Feature",
  "properties": {
    "addr:full":"Freyung 7/3 Wien Wien 1010",
    "addr:housenumber":"7 / 3",
    "addr:postcode":"1010",
    "addr:street":"Freyung",
    "iso:country":"AT",
    "sg:address":"Freyung 7/3",
    "sg:city":"Wien",
    "sg:orig_category":"Immobilienverwaltungen",
    "sg:phone":"+43 1 5359901",
    "sg:postcode":"1010",
    "sg:province":"Wien",
    "wof:name":"VSM SIMON GmbH",
    "wof:placetype":"venue"
},
  "geometry": {"coordinates":[16.3661193848,48.2115783691],"type":"Point"}
}