{
  "type": "Feature",
  "properties": {
    "addr:full":"Fasang 25 Wien Wien 1030",
    "addr:housenumber":"25",
    "addr:postcode":"1030",
    "addr:street":"Fasang",
    "iso:country":"AT",
    "sg:address":"Fasang 25",
    "sg:city":"Wien",
    "sg:orig_category":"Lebensmittel / Einzelhandel",
    "sg:phone":"+43 1 7988125",
    "sg:postcode":"1030",
    "sg:province":"Wien",
    "wof:name":"Hofer KG",
    "wof:placetype":"venue"
},
  "geometry": {"coordinates":[16.3860836029,48.1922721863],"type":"Point"}
}