{
  "type": "Feature",
  "properties": {
    "iso:country":"AT",
    "sg:address":"Diefenbachg 5",
    "sg:city":"Wien",
    "sg:orig_category":"Werbeagenturen",
    "sg:phone":"+43 1 8930373",
    "sg:postcode":"1150",
    "sg:province":"Wien",
    "wof:name":"Message Medien- & VerlagsgmbH",
    "wof:placetype":"venue"
},
  "geometry": {"coordinates":[16.3356285095,48.1865768433],"type":"Point"}
}