{
  "type": "Feature",
  "properties": {
    "addr:full":"Nr 13 Hollersbach im Pinzgau Salzburg 5731",
    "addr:postcode":"5731",
    "addr:street":"Nr 13;Salzburg",
    "iso:country":"AT",
    "sg:address":"Nr 13",
    "sg:city":"Hollersbach im Pinzgau",
    "sg:orig_category":"Tourismusinformation U -Organisationen",
    "sg:phone":"+43 4365 6281050",
    "sg:postcode":"5731",
    "sg:province":"Salzburg",
    "wof:name":"Kolleg Hollersbach Nationalpark Hohe Tauern - Seminarzentrum Klausnerhaus",
    "wof:placetype":"venue"
},
  "geometry": {"coordinates":[12.4197301865,47.2750968933],"type":"Point"}
}