{
  "type": "Feature",
  "properties": {
    "addr:full":"Krugerstr 6 Wien Wien 1010",
    "addr:housenumber":"6",
    "addr:postcode":"1010",
    "addr:street":"Krugerstr",
    "iso:country":"AT",
    "sg:address":"Krugerstr 6",
    "sg:city":"Wien",
    "sg:orig_category":"Nachtclubs-Bars",
    "sg:phone":"+43 1 5122424",
    "sg:postcode":"1010",
    "sg:province":"Wien",
    "wof:name":"Bunnies Club",
    "wof:placetype":"venue"
},
  "geometry": {"coordinates":[16.3713932037,48.2037887573],"type":"Point"}
}