{
  "type": "Feature",
  "properties": {
    "iso:country":"AT",
    "sg:address":"Greith 28",
    "sg:city":"Kitzeck im Sausal",
    "sg:orig_category":"Erdarbeiten",
    "sg:phone":"+43 4334 562384",
    "sg:postcode":"8442",
    "sg:province":"Steiermark",
    "wof:name":"Riffel Alois",
    "wof:placetype":"venue"
},
  "geometry": {"coordinates":[15.4475059509,46.7878723145],"type":"Point"}
}