{
  "type": "Feature",
  "properties": {
    "iso:country":"AT",
    "sg:address":"Herreng 31",
    "sg:city":"Klagenfurt",
    "sg:orig_category":"Friseure U Frisiersalons",
    "sg:phone":"+43 4346 356784",
    "sg:postcode":"9020",
    "sg:province":"K\u00e4rnten",
    "wof:name":"Frisiersalon Helga",
    "wof:placetype":"venue"
},
  "geometry": {"coordinates":[14.3274202347,46.6254196167],"type":"Point"}
}