{
  "type": "Feature",
  "properties": {
    "addr:full":"Stadtpl 22 Pregarten Ober\u00f6sterreich 4230",
    "addr:housenumber":"22",
    "addr:postcode":"4230",
    "addr:street":"Stadtpl",
    "iso:country":"AT",
    "sg:address":"Stadtpl 22",
    "sg:city":"Pregarten",
    "sg:orig_category":"Apotheken",
    "sg:phone":"+43 4372 362226",
    "sg:postcode":"4230",
    "sg:province":"Ober\u00f6sterreich",
    "wof:name":"St Anna Apotheke u Drogerie",
    "wof:placetype":"venue"
},
  "geometry": {"coordinates":[14.5308532715,48.3548355103],"type":"Point"}
}