{
  "type": "Feature",
  "properties": {
    "addr:full":"Dietersdorf am Gnasbach 4 St. Peter am Ottersbach Steiermark 8093",
    "addr:housenumber":"4",
    "addr:postcode":"8093",
    "addr:street":"Dietersdorf Am Gnasbach",
    "iso:country":"AT",
    "sg:address":"Dietersdorf am Gnasbach 4",
    "sg:city":"St. Peter am Ottersbach",
    "sg:orig_category":"Furniture, General",
    "sg:phone":"+43 3477 2650",
    "sg:postcode":"8093",
    "sg:province":"Steiermark",
    "wof:name":"Hannes Radkohl",
    "wof:placetype":"venue"
},
  "geometry": {"coordinates":[15.7936754227,46.8288803101],"type":"Point"}
}