{
  "type": "Feature",
  "properties": {
    "iso:country":"AT",
    "sg:address":"Hauptpl 67",
    "sg:city":"Alland",
    "sg:orig_category":"Friseure U Frisiersalons",
    "sg:phone":"+43 4322 582376",
    "sg:postcode":"2534",
    "sg:province":"Nieder\u00f6sterreich",
    "wof:name":"Friseursalon Eva Loidl",
    "wof:placetype":"venue"
},
  "geometry": {"coordinates":[16.0778408051,48.0587425232],"type":"Point"}
}