{
  "type": "Feature",
  "properties": {
    "iso:country":"AT",
    "sg:address":"Hauptstr 23",
    "sg:city":"Hermagor",
    "sg:orig_category":"Tabaktrafiken",
    "sg:phone":"+43 4282 2342",
    "sg:postcode":"9620",
    "sg:province":"K\u00e4rnten",
    "wof:name":"Wester Roswitha",
    "wof:placetype":"venue"
},
  "geometry": {"coordinates":[13.3679304123,46.6272125244],"type":"Point"}
}