{
  "type": "Feature",
  "properties": {
    "addr:full":"Mayerhofstr 40 Judenau Nieder\u00f6sterreich 3441",
    "addr:housenumber":"40",
    "addr:postcode":"3441",
    "addr:street":"Mayerhofstr",
    "iso:country":"AT",
    "sg:address":"Mayerhofstr 40",
    "sg:city":"Judenau",
    "sg:orig_category":"Heurigen / Buschenschank",
    "sg:phone":"+43 4322 7574737",
    "sg:postcode":"3441",
    "sg:province":"Nieder\u00f6sterreich",
    "wof:name":"Urbanistub'n",
    "wof:placetype":"venue"
},
  "geometry": {"coordinates":[15.9820661545,48.2870674133],"type":"Point"}
}