{
  "type": "Feature",
  "properties": {
    "iso:country":"AT",
    "sg:address":"Hauptpl 6",
    "sg:city":"Leibnitz",
    "sg:orig_category":"Fotoausarbeitungen",
    "sg:phone":"+43 3452 86044",
    "sg:postcode":"8430",
    "sg:province":"Steiermark",
    "wof:name":"Foto-Express-Labor T Koschuh",
    "wof:placetype":"venue"
},
  "geometry": {"coordinates":[15.5397853851,46.7821617126],"type":"Point"}
}