{
  "type": "Feature",
  "properties": {
    "addr:full":"Haager Strasse 54 Steyr Ober\u00f6sterreich 4400",
    "addr:housenumber":"54",
    "addr:postcode":"4400",
    "addr:street":"Haager Strasse;Oberoesterreich",
    "iso:country":"AT",
    "sg:address":"Haager Strasse 54",
    "sg:city":"Steyr",
    "sg:classifiers":[
        {
            "category":"Government",
            "subcategory":"Fire Station",
            "type":"Public Place"
        }
    ],
    "sg:phone":"+43 7252 73148",
    "sg:postcode":"4400",
    "sg:province":"Ober\u00f6sterreich",
    "sg:tags":[
        "bitumen",
        "roof",
        "shingle"
    ],
    "sg:website":"lipfert.at",
    "wof:name":"Gotthard Lipfert Dachdeckerei und Spenglerei Ges.m.b.H. & Co KG",
    "wof:placetype":"venue"
},
  "geometry": {"coordinates":[14.4522800446,48.0596847534],"type":"Point"}
}