{
  "type": "Feature",
  "properties": {
    "addr:full":"Walser Str 57 Riezlern Vorarlberg 6991",
    "addr:postcode":"6991",
    "addr:street":"Str 57",
    "iso:country":"AT",
    "sg:address":"Walser Str 57",
    "sg:city":"Riezlern",
    "sg:orig_category":"Fleischhauereien",
    "sg:phone":"+43 4355 1720011",
    "sg:postcode":"6991",
    "sg:province":"Vorarlberg",
    "wof:name":"Speck Alm GesmbH",
    "wof:placetype":"venue"
},
  "geometry": {"coordinates":[10.1871242523,47.3576545715],"type":"Point"}
}