{
  "type": "Feature",
  "properties": {
    "iso:country":"AT",
    "sg:address":"Walter-Goldschmidt-G 25",
    "sg:city":"St. Peter",
    "sg:classifiers":[
        {
            "category":"Travel",
            "subcategory":"Hotels & Motels",
            "type":"Entertainment"
        }
    ],
    "sg:phone":"+43 4331 6425454",
    "sg:postcode":"8042",
    "sg:province":"Steiermark",
    "wof:name":"Hotel Centercourt",
    "wof:placetype":"venue"
},
  "geometry": {"coordinates":[15.4757108688,47.0508918762],"type":"Point"}
}