{
  "type": "Feature",
  "properties": {
    "iso:country":"AT",
    "sg:address":"Ghegastr 5",
    "sg:city":"Knittelfeld",
    "sg:orig_category":"Steuerberatung",
    "sg:phone":"+43 4335 12828660",
    "sg:postcode":"8720",
    "sg:province":"Steiermark",
    "wof:name":"Domian Alois",
    "wof:placetype":"venue"
},
  "geometry": {"coordinates":[14.8147602081,47.2124671936],"type":"Point"}
}