{
  "type": "Feature",
  "properties": {
    "addr:full":"Nr 77 Gnesau K\u00e4rnten 9563",
    "addr:postcode":"9563",
    "addr:street":"Nr 77 Gnesau Kaernten",
    "iso:country":"AT",
    "sg:address":"Nr 77",
    "sg:city":"Gnesau",
    "sg:orig_category":"Gemeinden",
    "sg:phone":"+43 4278 2710",
    "sg:postcode":"9563",
    "sg:province":"K\u00e4rnten",
    "wof:name":"Gemeindeamt Gnesau",
    "wof:placetype":"venue"
},
  "geometry": {"coordinates":[13.962677002,46.7755317688],"type":"Point"}
}