{
  "type": "Feature",
  "properties": {
    "addr:full":"Kempeleng 8 Wien Wien 1100",
    "addr:housenumber":"8",
    "addr:postcode":"1100",
    "addr:street":"Kempeleng",
    "iso:country":"AT",
    "sg:address":"Kempeleng 8",
    "sg:city":"Wien",
    "sg:orig_category":"Baumeister",
    "sg:phone":"+43 1 60488400",
    "sg:postcode":"1100",
    "sg:province":"Wien",
    "wof:name":"Trimmel Herbert GesmbH",
    "wof:placetype":"venue"
},
  "geometry": {"coordinates":[16.3933849335,48.1742706299],"type":"Point"}
}