{
  "type": "Feature",
  "properties": {
    "iso:country":"AT",
    "sg:address":"Grazer Str 43",
    "sg:city":"Andritz",
    "sg:orig_category":"Restaurants: Chinesisch",
    "sg:phone":"+43 316 692820",
    "sg:postcode":"8045",
    "sg:province":"Steiermark",
    "wof:name":"China-Restaurant Seidenstra\u00dfe",
    "wof:placetype":"venue"
},
  "geometry": {"coordinates":[15.4209985733,47.1032905579],"type":"Point"}
}