{
  "type": "Feature",
  "properties": {
    "iso:country":"AT",
    "sg:address":"Nr 65",
    "sg:city":"Weistrach",
    "sg:orig_category":"Anlagenbau U -Technik",
    "sg:phone":"+43 7477 423450",
    "sg:postcode":"3351",
    "sg:province":"Nieder\u00f6sterreich",
    "wof:name":"DAT Dorfmayr Anlagen Technik GmbH",
    "wof:placetype":"venue"
},
  "geometry": {"coordinates":[14.5837316513,48.0553855896],"type":"Point"}
}