{
  "type": "Feature",
  "properties": {
    "iso:country":"AT",
    "sg:address":"Hammerschmiedstr 6",
    "sg:city":"Kitzb\u00fchel",
    "sg:orig_category":"Friseure U Frisiersalons",
    "sg:phone":"+43 4353 5665023",
    "sg:postcode":"6370",
    "sg:province":"Tirol",
    "wof:name":"Friseursalon Herbert",
    "wof:placetype":"venue"
},
  "geometry": {"coordinates":[12.3942050934,47.4452514648],"type":"Point"}
}