{
  "type": "Feature",
  "properties": {
    "iso:country":"AT",
    "sg:address":"Unterer Schreiberweg 101",
    "sg:city":"Wien",
    "sg:orig_category":"Architekten",
    "sg:phone":"+43 1 3281756",
    "sg:postcode":"1190",
    "sg:province":"Wien",
    "wof:name":"Obermann Werner Arch DI Dr techn",
    "wof:placetype":"venue"
},
  "geometry": {"coordinates":[16.3423252106,48.260181427],"type":"Point"}
}