{
  "type": "Feature",
  "properties": {
    "addr:full":"Hirtenberger Str Parz 1124 Leobersdorf Nieder\u00f6sterreich 2544",
    "addr:postcode":"1124;2544",
    "addr:street":"Str Parz;Niederoesterreich",
    "iso:country":"AT",
    "sg:address":"Hirtenberger Str Parz 1124",
    "sg:city":"Leobersdorf",
    "sg:orig_category":"Lebensmittel / Einzelhandel",
    "sg:phone":"+43 2256 65355",
    "sg:postcode":"2544",
    "sg:province":"Nieder\u00f6sterreich",
    "wof:name":"Hofer KG",
    "wof:placetype":"venue"
},
  "geometry": {"coordinates":[16.2165107727,47.9286613464],"type":"Point"}
}