{
  "type": "Feature",
  "properties": {
    "addr:full":"Wiener Str 48 Langenlois Nieder\u00f6sterreich 3550",
    "addr:postcode":"3550",
    "addr:street":"Niederoesterreich",
    "iso:country":"AT",
    "sg:address":"Wiener Str 48",
    "sg:city":"Langenlois",
    "sg:orig_category":"Installationsunternehmen",
    "sg:phone":"+43 2734 3070",
    "sg:postcode":"3550",
    "sg:province":"Nieder\u00f6sterreich",
    "wof:name":"Kausl GmbH - Energiesysteme & Baddesign",
    "wof:placetype":"venue"
},
  "geometry": {"coordinates":[15.6965236664,48.4755134583],"type":"Point"}
}