{
  "type": "Feature",
  "properties": {
    "addr:full":"Industriepark 4 Trieben Steiermark 8784",
    "addr:housenumber":"4",
    "addr:postcode":"8784",
    "addr:street":"Industriepark",
    "iso:country":"AT",
    "sg:address":"Industriepark 4",
    "sg:city":"Trieben",
    "sg:orig_category":"Fleischhauereien",
    "sg:phone":"+43 3615 28056",
    "sg:postcode":"8784",
    "sg:province":"Steiermark",
    "wof:name":"Schirnhofer-Breisler GesmbH",
    "wof:placetype":"venue"
},
  "geometry": {"coordinates":[14.4830217361,47.4926452637],"type":"Point"}
}