{
  "type": "Feature",
  "properties": {
    "addr:full":"Hoher Pl 19 Wolfsberg K\u00e4rnten 9400",
    "addr:housenumber":"19;kaernten",
    "addr:postcode":"9400",
    "addr:street":"Hoher Pl",
    "iso:country":"AT",
    "sg:address":"Hoher Pl 19",
    "sg:city":"Wolfsberg",
    "sg:orig_category":"Banken U Sparkassen",
    "sg:phone":"+43 4343 5240810",
    "sg:postcode":"9400",
    "sg:province":"K\u00e4rnten",
    "wof:name":"Raiffeisenbank St Andr\u00e4-Wolfsberg regGenmbH",
    "wof:placetype":"venue"
},
  "geometry": {"coordinates":[14.8454113007,46.8391914368],"type":"Point"}
}