{
  "type": "Feature",
  "properties": {
    "addr:full":"Untere Hauptstr 34 Nickelsdorf Burgenland 2425",
    "addr:housenumber":"34",
    "addr:postcode":"2425",
    "addr:street":"Untere Hauptstr",
    "iso:country":"AT",
    "sg:address":"Untere Hauptstr 34",
    "sg:city":"Nickelsdorf",
    "sg:orig_category":"Schlossereien",
    "sg:phone":"+43 2146 20013",
    "sg:postcode":"2425",
    "sg:province":"Burgenland",
    "wof:name":"Pahr Johann",
    "wof:placetype":"venue"
},
  "geometry": {"coordinates":[17.0768737793,47.9376564026],"type":"Point"}
}