{
  "type": "Feature",
  "properties": {
    "iso:country":"AT",
    "sg:address":"Ramingdorf 33",
    "sg:city":"Haidershofen",
    "sg:classifiers":[
        {
            "category":"Home & Garden",
            "subcategory":"Building Materials",
            "type":"Retail Goods"
        }
    ],
    "sg:phone":"+43 7252 800800",
    "sg:postcode":"4431",
    "sg:province":"Nieder\u00f6sterreich",
    "sg:tags":[
        "aluminium",
        "window"
    ],
    "sg:website":"metallbau.federer.at",
    "wof:name":"Metallbau Federer Ges.m.b.H. & Co KG",
    "wof:placetype":"venue"
},
  "geometry": {"coordinates":[14.4630775452,48.0753211975],"type":"Point"}
}