{
  "type": "Feature",
  "properties": {
    "addr:full":"Thalgauberg 94 Thalgau Salzburg 5303",
    "addr:housenumber":"94",
    "addr:postcode":"5303",
    "addr:street":"Thalgauberg;Salzburg",
    "iso:country":"AT",
    "sg:address":"Thalgauberg 94",
    "sg:city":"Thalgau",
    "sg:orig_category":"Grafische Bedarfsartikel",
    "sg:phone":"+43 6235 6467",
    "sg:postcode":"5303",
    "sg:province":"Salzburg",
    "wof:name":"Sterzinger Richard Ing",
    "wof:placetype":"venue"
},
  "geometry": {"coordinates":[13.2530384064,47.8769378662],"type":"Point"}
}