{
  "type": "Feature",
  "properties": {
    "addr:full":"Fabriksstr. 4-6 Judendorf-Stra\u00dfengel Steiermark 8111",
    "addr:housenumber":"4-6",
    "addr:postcode":"8111",
    "addr:street":"Fabriksstr.",
    "iso:country":"AT",
    "sg:address":"Fabriksstr. 4-6",
    "sg:city":"Judendorf-Stra\u00dfengel",
    "sg:classifiers":[
        {
            "category":"Wholesale",
            "subcategory":"Drugs",
            "type":"Manufacturing & Wholesale Goods"
        }
    ],
    "sg:phone":"+43 4331 24517900",
    "sg:postcode":"8111",
    "sg:province":"Steiermark",
    "sg:tags":[
        "chemical",
        "pharmaceutical"
    ],
    "wof:name":"GRAIER GMBH",
    "wof:placetype":"venue"
},
  "geometry": {"coordinates":[15.3490362167,47.1171188354],"type":"Point"}
}