{
  "type": "Feature",
  "properties": {
    "addr:full":"Althauser Str 1 Pregarten Ober\u00f6sterreich 4230",
    "addr:housenumber":"1",
    "addr:postcode":"4230",
    "addr:street":"Str",
    "iso:country":"AT",
    "sg:address":"Althauser Str 1",
    "sg:city":"Pregarten",
    "sg:orig_category":"Kinderbetreuung",
    "sg:phone":"+43 7236 2323",
    "sg:postcode":"4230",
    "sg:province":"Ober\u00f6sterreich",
    "wof:name":"Kindergarten d \u00f6sterr Kinderfreunde",
    "wof:placetype":"venue"
},
  "geometry": {"coordinates":[14.534658432,48.3531723022],"type":"Point"}
}