{
  "type": "Feature",
  "properties": {
    "addr:full":"Klosterstr 12 Amstetten Nieder\u00f6sterreich 3300",
    "addr:housenumber":"12",
    "addr:postcode":"3300",
    "addr:street":"Klosterstr;Niederoesterreich",
    "iso:country":"AT",
    "sg:address":"Klosterstr 12",
    "sg:city":"Amstetten",
    "sg:orig_category":"Personalbereitstellung",
    "sg:phone":"+43 7472 25192",
    "sg:postcode":"3300",
    "sg:province":"Nieder\u00f6sterreich",
    "wof:name":"Trenkwalder Personaldienste AG",
    "wof:placetype":"venue"
},
  "geometry": {"coordinates":[14.8685159683,48.1219329834],"type":"Point"}
}