{
  "type": "Feature",
  "properties": {
    "iso:country":"AT",
    "sg:address":"Brigittenauer Sporn 7",
    "sg:city":"Wien",
    "sg:orig_category":"Ingenieurkonsulenten / Zivilingenieure",
    "sg:phone":"+43 1 3180547",
    "sg:postcode":"1200",
    "sg:province":"Wien",
    "wof:name":"Winkler Kurt Dipl-Ing",
    "wof:placetype":"venue"
},
  "geometry": {"coordinates":[16.3696365356,48.2598686218],"type":"Point"}
}