{
  "type": "Feature",
  "properties": {
    "addr:full":"Hundegger Str 10 F\u00fcrstenfeld Steiermark 8280",
    "addr:postcode":"8280",
    "addr:street":"Str 10 Fuerstenfeld Steiermark",
    "iso:country":"AT",
    "sg:address":"Hundegger Str 10",
    "sg:city":"F\u00fcrstenfeld",
    "sg:orig_category":"Sonderschulen",
    "sg:phone":"+43 3382 53782",
    "sg:postcode":"8280",
    "sg:province":"Steiermark",
    "wof:name":"Allgemeine Sonderschule",
    "wof:placetype":"venue"
},
  "geometry": {"coordinates":[16.079624176,47.0467300415],"type":"Point"}
}