{
  "type": "Feature",
  "properties": {
    "addr:full":"Edelgrund 30 Podersdorf am See Burgenland 7141",
    "addr:housenumber":"30",
    "addr:postcode":"7141",
    "addr:street":"Edelgrund",
    "iso:country":"AT",
    "sg:address":"Edelgrund 30",
    "sg:city":"Podersdorf am See",
    "sg:orig_category":"Elektroinstallationsunternehmen",
    "sg:phone":"+43 2177 27360",
    "sg:postcode":"7141",
    "sg:province":"Burgenland",
    "wof:name":"Elektro Steiner GmbH",
    "wof:placetype":"venue"
},
  "geometry": {"coordinates":[16.8444862366,47.85572052],"type":"Point"}
}