{
  "type": "Feature",
  "properties": {
    "iso:country":"AT",
    "sg:address":"Franzosenweg 14",
    "sg:city":"Wien",
    "sg:orig_category":"Behinderungen / Leben Mit Behinderungen",
    "sg:phone":"+43 4316 884153",
    "sg:postcode":"1100",
    "sg:province":"Wien",
    "wof:name":"Lebenshilfe Wien Verein f Menschen m geistiger u mehrfacher Behinderung",
    "wof:placetype":"venue"
},
  "geometry": {"coordinates":[16.384305954,48.1397743225],"type":"Point"}
}