{
  "type": "Feature",
  "properties": {
    "addr:full":"Bahnstr 8 Wiesen Burgenland 7203",
    "addr:housenumber":"8",
    "addr:postcode":"7203",
    "addr:street":"Bahnstr",
    "iso:country":"AT",
    "sg:address":"Bahnstr 8",
    "sg:city":"Wiesen",
    "sg:orig_category":"Non-Classified Establishments",
    "sg:phone":"+43 2626 81641",
    "sg:postcode":"7203",
    "sg:province":"Burgenland",
    "wof:name":"Pfarramt",
    "wof:placetype":"venue"
},
  "geometry": {"coordinates":[16.3392429352,47.7390823364],"type":"Point"}
}