{
  "type": "Feature",
  "properties": {
    "iso:country":"AT",
    "sg:address":"Schlosserg 3",
    "sg:city":"Innsbruck",
    "sg:orig_category":"Marketingberatung",
    "sg:phone":"+43 512 291141",
    "sg:postcode":"6020",
    "sg:province":"Tirol",
    "wof:name":"IDC Marketing & Consulting GmbH",
    "wof:placetype":"venue"
},
  "geometry": {"coordinates":[11.3927679062,47.2670059204],"type":"Point"}
}