{
  "type": "Feature",
  "properties": {
    "addr:full":"Taglieberstrasse 6 Wien Wien 1230",
    "addr:housenumber":"6",
    "addr:postcode":"1230",
    "addr:street":"Taglieberstrasse",
    "iso:country":"AT",
    "sg:address":"Taglieberstrasse 6",
    "sg:city":"Wien",
    "sg:classifiers":[
        {
            "category":"Building & Trades",
            "subcategory":"Electrical",
            "type":"Services"
        }
    ],
    "sg:phone":"+43 1 8891283",
    "sg:postcode":"1230",
    "sg:province":"Wien",
    "sg:tags":[
        "work",
        "installation"
    ],
    "wof:name":"Friedrich Novak",
    "wof:placetype":"venue"
},
  "geometry": {"coordinates":[16.2876052856,48.1490325928],"type":"Point"}
}