{
  "type": "Feature",
  "properties": {
    "addr:full":"Hauptstr 20 Neumarkt am Wallersee Salzburg 5202",
    "addr:housenumber":"20",
    "addr:postcode":"5202",
    "addr:street":"Hauptstr;Salzburg",
    "iso:country":"AT",
    "sg:address":"Hauptstr 20",
    "sg:city":"Neumarkt am Wallersee",
    "sg:classifiers":[
        {
            "category":"Restaurant",
            "type":"Food & Drink"
        }
    ],
    "sg:phone":"+43 4362 167777",
    "sg:postcode":"5202",
    "sg:province":"Salzburg",
    "sg:tags":[
        "pizzeria"
    ],
    "wof:name":"Pizza-Express-Musti's",
    "wof:placetype":"venue"
},
  "geometry": {"coordinates":[13.2247371674,47.9441604614],"type":"Point"}
}