{
  "type": "Feature",
  "properties": {
    "iso:country":"AT",
    "sg:address":"Am Marienbrunnen 341",
    "sg:city":"Mayrhofen",
    "sg:classifiers":[
        {
            "category":"Travel",
            "subcategory":"Hotels & Motels",
            "type":"Entertainment"
        }
    ],
    "sg:phone":"+43 5285 622650",
    "sg:postcode":"6290",
    "sg:province":"Tirol",
    "wof:name":"Zillertaler Hof",
    "wof:placetype":"venue"
},
  "geometry": {"coordinates":[11.8663682938,47.1672935486],"type":"Point"}
}