{
  "type": "Feature",
  "properties": {
    "addr:full":"Arbeiterstr 16 Steyr Ober\u00f6sterreich 4400",
    "addr:housenumber":"16",
    "addr:postcode":"4400",
    "addr:street":"Arbeiterstr;Oberoesterreich",
    "iso:country":"AT",
    "sg:address":"Arbeiterstr 16",
    "sg:city":"Steyr",
    "sg:orig_category":"Immobilienmakler",
    "sg:phone":"+43 7252 48610",
    "sg:postcode":"4400",
    "sg:province":"Ober\u00f6sterreich",
    "wof:name":"Real Treuhand Immobilien Vertriebs GmbH",
    "wof:placetype":"venue"
},
  "geometry": {"coordinates":[14.4258289337,48.03383255],"type":"Point"}
}