{
  "type": "Feature",
  "properties": {
    "addr:full":"Feldg 4 Sommerein Nieder\u00f6sterreich 2453",
    "addr:housenumber":"4",
    "addr:postcode":"2453",
    "addr:street":"Feldg",
    "iso:country":"AT",
    "sg:address":"Feldg 4",
    "sg:city":"Sommerein",
    "sg:orig_category":"Alternativtherapie",
    "sg:phone":"+43 2168 68377",
    "sg:postcode":"2453",
    "sg:province":"Nieder\u00f6sterreich",
    "wof:name":"Hepner Viktoria Praxis f\u00fcr energetische Ausgeglichenheit",
    "wof:placetype":"venue"
},
  "geometry": {"coordinates":[16.658870697,47.9908905029],"type":"Point"}
}