{
  "type": "Feature",
  "properties": {
    "addr:full":"An Der Sch\u00fctt 40 Krems an der Donau Nieder\u00f6sterreich 3500",
    "addr:housenumber":"40",
    "addr:postcode":"3500",
    "addr:street":"An Der Schuett",
    "iso:country":"AT",
    "sg:address":"An Der Sch\u00fctt 40",
    "sg:city":"Krems an der Donau",
    "sg:classifiers":[
        {
            "category":"Wholesale",
            "subcategory":"Machinery & Supplies",
            "type":"Manufacturing & Wholesale Goods"
        }
    ],
    "sg:phone":"+43 4327 32829670",
    "sg:postcode":"3500",
    "sg:province":"Nieder\u00f6sterreich",
    "sg:tags":[
        "-",
        "agriculture",
        "equipment"
    ],
    "wof:name":"SALIZE GES.MBH",
    "wof:placetype":"venue"
},
  "geometry": {"coordinates":[15.5965108871,48.4088058472],"type":"Point"}
}