{
  "type": "Feature",
  "properties": {
    "addr:full":"Laufnitzdorf 30 Frohnleiten Steiermark 8130",
    "addr:housenumber":"30",
    "addr:postcode":"8130",
    "addr:street":"Laufnitzdorf",
    "iso:country":"AT",
    "sg:address":"Laufnitzdorf 30",
    "sg:city":"Frohnleiten",
    "sg:classifiers":[
        {
            "category":"Professional",
            "subcategory":"Engineering",
            "type":"Services"
        }
    ],
    "sg:phone":"+43 4331 262343",
    "sg:postcode":"8130",
    "sg:province":"Steiermark",
    "sg:tags":[
        "machine",
        "-",
        "mechanical"
    ],
    "wof:name":"KURT WATZL MASCHINEN U. STAHLBAU GES.MBH",
    "wof:placetype":"venue"
},
  "geometry": {"coordinates":[15.3163194656,47.2985916138],"type":"Point"}
}