{
  "type": "Feature",
  "properties": {
    "addr:full":"Reisenbauerring 7/3/32 Wiener Neudorf Nieder\u00f6sterreich 2351",
    "addr:housenumber":"7 / 3 / 32",
    "addr:postcode":"2351",
    "addr:street":"Reisenbauerring",
    "iso:country":"AT",
    "sg:address":"Reisenbauerring 7/3/32",
    "sg:city":"Wiener Neudorf",
    "sg:classifiers":[
        {
            "category":"Professional",
            "subcategory":"Computer Services",
            "type":"Services"
        }
    ],
    "sg:phone":"+43 2236 45412",
    "sg:postcode":"2351",
    "sg:province":"Nieder\u00f6sterreich",
    "sg:tags":[
        "software"
    ],
    "wof:name":"B\u00fccher - EDV Dienstleistungen GesmbH",
    "wof:placetype":"venue"
},
  "geometry": {"coordinates":[16.3183326721,48.0863113403],"type":"Point"}
}