{
  "type": "Feature",
  "properties": {
    "addr:full":"Moosstr 122 Salzburg Salzburg 5020",
    "addr:housenumber":"122",
    "addr:postcode":"5020",
    "addr:street":"Salzburg",
    "iso:country":"AT",
    "sg:address":"Moosstr 122",
    "sg:city":"Salzburg",
    "sg:orig_category":"Friseure U Frisiersalons",
    "sg:phone":"+43 4366 2827718",
    "sg:postcode":"5020",
    "sg:province":"Salzburg",
    "wof:name":"Coiffeur Valentino",
    "wof:placetype":"venue"
},
  "geometry": {"coordinates":[13.0203104019,47.7707366943],"type":"Point"}
}