{
  "type": "Feature",
  "properties": {
    "addr:full":"Nr 38 Haitzendorf Nieder\u00f6sterreich 3485",
    "addr:postcode":"3485",
    "addr:street":"Nr;Haitzendorf",
    "iso:country":"AT",
    "sg:address":"Nr 38",
    "sg:city":"Haitzendorf",
    "sg:orig_category":"Banken U Sparkassen",
    "sg:phone":"+43 4327 3557070",
    "sg:postcode":"3485",
    "sg:province":"Nieder\u00f6sterreich",
    "wof:name":"Raiffeisenbank Langenlois regGenmbH",
    "wof:placetype":"venue"
},
  "geometry": {"coordinates":[15.7485160828,48.4298973083],"type":"Point"}
}