{
  "type": "Feature",
  "properties": {
    "iso:country":"AT",
    "sg:address":"Nr 46",
    "sg:city":"Gries am Brenner",
    "sg:orig_category":"Feuerwehren",
    "sg:phone":"+43 5274 87777",
    "sg:postcode":"6156",
    "sg:province":"Tirol",
    "wof:name":"Freiwillige Feuerwehr Gries a Brenner",
    "wof:placetype":"venue"
},
  "geometry": {"coordinates":[11.478723526,47.0383338928],"type":"Point"}
}