{
  "type": "Feature",
  "properties": {
    "addr:full":"Framrach St. Andr\u00e4 K\u00e4rnten 9433",
    "addr:postcode":"9433",
    "addr:street":"Framrach St.;Kaernten",
    "iso:country":"AT",
    "sg:address":"Framrach",
    "sg:city":"St. Andr\u00e4",
    "sg:orig_category":"Telefonmarketing",
    "sg:phone":"+43 4358 28060300",
    "sg:postcode":"9433",
    "sg:province":"K\u00e4rnten",
    "wof:name":"Mediacalling GmbH",
    "wof:placetype":"venue"
},
  "geometry": {"coordinates":[14.822760582,46.7463035583],"type":"Point"}
}