{
  "type": "Feature",
  "properties": {
    "addr:full":"Fabriksg 1 Markt St. Martin Burgenland 7341",
    "addr:postcode":"7341",
    "addr:street":"Fabriksg;Markt",
    "iso:country":"AT",
    "sg:address":"Fabriksg 1",
    "sg:city":"Markt St. Martin",
    "sg:orig_category":"Strick- U Wirkwaren / Erzeugung U Gro\u00c3\u0178handel",
    "sg:phone":"+43 4326 1822310",
    "sg:postcode":"7341",
    "sg:province":"Burgenland",
    "wof:name":"Pfrommer Strickwarenfabrik GesnbR",
    "wof:placetype":"venue"
},
  "geometry": {"coordinates":[16.4328784943,47.5579376221],"type":"Point"}
}