{
  "type": "Feature",
  "properties": {
    "iso:country":"AT",
    "sg:address":"Gleinker G 15",
    "sg:city":"Steyr",
    "sg:orig_category":"Gastronomie- U Hotelbetriebsgesellschaften",
    "sg:phone":"+43 7252 811780",
    "sg:postcode":"4400",
    "sg:province":"Ober\u00f6sterreich",
    "wof:name":"Holzner GesmbH Gastronomiebetriebs KEG",
    "wof:placetype":"venue"
},
  "geometry": {"coordinates":[14.4183559418,48.0443534851],"type":"Point"}
}