{
  "type": "Feature",
  "properties": {
    "addr:full":"Mehrerauer Str 9 Bregenz Vorarlberg 6900",
    "addr:housenumber":"9",
    "addr:postcode":"6900",
    "addr:street":"Str",
    "iso:country":"AT",
    "sg:address":"Mehrerauer Str 9",
    "sg:city":"Bregenz",
    "sg:orig_category":"Weiterbildungsinstitute M Allg U Berufl Bildungsangebot",
    "sg:phone":"+43 4355 7458014",
    "sg:postcode":"6900",
    "sg:province":"Vorarlberg",
    "wof:name":"Merlin Unternehmensberatung GmbH",
    "wof:placetype":"venue"
},
  "geometry": {"coordinates":[9.7322301865,47.5029602051],"type":"Point"}
}