{
  "type": "Feature",
  "properties": {
    "iso:country":"AT",
    "sg:address":"Arling 11",
    "sg:city":"St. Michael",
    "sg:classifiers":[
        {
            "category":"Manufacturing",
            "subcategory":"Furniture",
            "type":"Manufacturing & Wholesale Goods"
        }
    ],
    "sg:phone":"+43 4352 61762",
    "sg:postcode":"9411",
    "sg:province":"K\u00e4rnten",
    "sg:tags":[
        "bedroom"
    ],
    "wof:name":"Joham K.E.G",
    "wof:placetype":"venue"
},
  "geometry": {"coordinates":[14.8136339188,46.8296051025],"type":"Point"}
}