{
  "type": "Feature",
  "properties": {
    "addr:full":"Klosterstr 18 Linz Ober\u00f6sterreich 4020",
    "addr:housenumber":"18",
    "addr:postcode":"4020",
    "addr:street":"Klosterstr",
    "iso:country":"AT",
    "sg:address":"Klosterstr 18",
    "sg:city":"Linz",
    "sg:orig_category":"\u00c3\u201enderungsschneidereien",
    "sg:phone":"+43 732 795450",
    "sg:postcode":"4020",
    "sg:province":"Ober\u00f6sterreich",
    "wof:name":"\u00e4nderungsschneiderei Monika H\u00f6llhuber",
    "wof:placetype":"venue"
},
  "geometry": {"coordinates":[14.2853517532,48.3044776917],"type":"Point"}
}