{
  "type": "Feature",
  "properties": {
    "addr:full":"Kaiserebersdorfer Str 18 Wien Wien 1110",
    "addr:postcode":"1110",
    "addr:street":"Str 18",
    "iso:country":"AT",
    "sg:address":"Kaiserebersdorfer Str 18",
    "sg:city":"Wien",
    "sg:orig_category":"Friseure U Frisiersalons",
    "sg:phone":"+43 4317 676030",
    "sg:postcode":"1110",
    "sg:province":"Wien",
    "wof:name":"Salon Inge",
    "wof:placetype":"venue"
},
  "geometry": {"coordinates":[16.4239406586,48.1688461304],"type":"Point"}
}