{
  "type": "Feature",
  "properties": {
    "addr:full":"Moosallee 46 Radstadt Salzburg 5550",
    "addr:housenumber":"46",
    "addr:postcode":"5550",
    "addr:street":"Moosallee;Salzburg",
    "iso:country":"AT",
    "sg:address":"Moosallee 46",
    "sg:city":"Radstadt",
    "sg:orig_category":"Postservicestellen",
    "sg:phone":"+43 6452 4588",
    "sg:postcode":"5550",
    "sg:province":"Salzburg",
    "wof:name":"Post-Shop-Partner Margarete Sprung",
    "wof:placetype":"venue"
},
  "geometry": {"coordinates":[13.4694299698,47.3834571838],"type":"Point"}
}