{
  "type": "Feature",
  "properties": {
    "iso:country":"AT",
    "sg:address":"Wiener G 18",
    "sg:city":"Perchtoldsdorf",
    "sg:orig_category":"Drogerien",
    "sg:phone":"+43 1 8651149",
    "sg:postcode":"2380",
    "sg:province":"Nieder\u00f6sterreich",
    "wof:name":"dm drogerie markt GmbH",
    "wof:placetype":"venue"
},
  "geometry": {"coordinates":[16.266784668,48.1207466125],"type":"Point"}
}