{
  "type": "Feature",
  "properties": {
    "addr:full":"Untere Hauptstr 87 Neusiedl am See Burgenland 7100",
    "addr:housenumber":"87",
    "addr:postcode":"7100",
    "addr:street":"Untere Hauptstr",
    "iso:country":"AT",
    "sg:address":"Untere Hauptstr 87",
    "sg:city":"Neusiedl am See",
    "sg:orig_category":"Tankstellen",
    "sg:phone":"+43 2167 2456",
    "sg:postcode":"7100",
    "sg:province":"Burgenland",
    "wof:name":"AVANTI TankstellenbetriebsgesmbH",
    "wof:placetype":"venue"
},
  "geometry": {"coordinates":[16.8502235413,47.9431266785],"type":"Point"}
}