{
  "type": "Feature",
  "properties": {
    "addr:full":"Penzendorf 114 Hartberg Steiermark 8230",
    "addr:housenumber":"114",
    "addr:postcode":"8230",
    "addr:street":"Penzendorf",
    "iso:country":"AT",
    "sg:address":"Penzendorf 114",
    "sg:city":"Hartberg",
    "sg:orig_category":"Tischlereien",
    "sg:phone":"+43 4333 3262853",
    "sg:postcode":"8230",
    "sg:province":"Steiermark",
    "wof:name":"Moser Franz",
    "wof:placetype":"venue"
},
  "geometry": {"coordinates":[15.9814386368,47.3149604797],"type":"Point"}
}