{
  "type": "Feature",
  "properties": {
    "iso:country":"AT",
    "sg:address":"Ardaggerstrasse 28",
    "sg:city":"Amstetten",
    "sg:classifiers":[
        {
            "category":"Structure",
            "subcategory":"Building",
            "type":"Public Place"
        }
    ],
    "sg:phone":"+43 7472 623270",
    "sg:postcode":"3300",
    "sg:province":"Nieder\u00f6sterreich",
    "sg:tags":[
        "apartment"
    ],
    "sg:website":"preiswertwohnen.at",
    "wof:name":"Gemeinn\u00fctzige Wohnungs- und Siedlungsgenossenschaft Amstetten eingetragene Genossenschaft mit besch",
    "wof:placetype":"venue"
},
  "geometry": {"coordinates":[14.8695058823,48.1267051697],"type":"Point"}
}