{
  "type": "Feature",
  "properties": {
    "iso:country":"AT",
    "sg:address":"Stallhofstr 24",
    "sg:city":"Gratwein",
    "sg:orig_category":"Tischlereien",
    "sg:phone":"+43 4331 24519030",
    "sg:postcode":"8112",
    "sg:province":"Steiermark",
    "wof:name":"Polz GesmbH",
    "wof:placetype":"venue"
},
  "geometry": {"coordinates":[15.3191623688,47.1264266968],"type":"Point"}
}