{
  "type": "Feature",
  "properties": {
    "addr:full":"Nr 22 Vorau Steiermark 8250",
    "addr:postcode":"8250",
    "addr:street":"Nr",
    "iso:country":"AT",
    "sg:address":"Nr 22",
    "sg:city":"Vorau",
    "sg:orig_category":"Pensionen / Privatzimmer",
    "sg:phone":"+43 4333 382589",
    "sg:postcode":"8250",
    "sg:province":"Steiermark",
    "wof:name":"H\u00f6ller Josef",
    "wof:placetype":"venue"
},
  "geometry": {"coordinates":[15.8873929977,47.4056854248],"type":"Point"}
}