{
  "type": "Feature",
  "properties": {
    "iso:country":"AT",
    "sg:address":"Marktpl 10",
    "sg:city":"Neuhofen an der Krems",
    "sg:orig_category":"Apotheken",
    "sg:phone":"+43 4372 274218",
    "sg:postcode":"4501",
    "sg:province":"Ober\u00f6sterreich",
    "sg:website":"apotheke-neuhofen.at",
    "wof:name":"Apotheke z hl Dreifaltigkeit KG Mag pharm E Jura",
    "wof:placetype":"venue"
},
  "geometry": {"coordinates":[14.2289171219,48.1381835938],"type":"Point"}
}