{
  "type": "Feature",
  "properties": {
    "addr:full":"Nr 25 \u00d6blarn Steiermark 8960",
    "addr:postcode":"8960",
    "addr:street":"Nr 25 Oeblarn Steiermark",
    "iso:country":"AT",
    "sg:address":"Nr 25",
    "sg:city":"\u00d6blarn",
    "sg:orig_category":"Volksschulen",
    "sg:phone":"+43 4336 842740",
    "sg:postcode":"8960",
    "sg:province":"Steiermark",
    "wof:name":"Volksschule",
    "wof:placetype":"venue"
},
  "geometry": {"coordinates":[166.9221496582,-0.5282999873],"type":"Point"}
}