{
  "type": "Feature",
  "properties": {
    "addr:full":"Bahnstr 3-5 Leopoldsdorf im Marchfelde Nieder\u00f6sterreich 2285",
    "addr:housenumber":"3-5",
    "addr:postcode":"2285",
    "addr:street":"Bahnstr",
    "iso:country":"AT",
    "sg:address":"Bahnstr 3-5",
    "sg:city":"Leopoldsdorf im Marchfelde",
    "sg:orig_category":"Tabaktrafiken",
    "sg:phone":"+43 2216 2248",
    "sg:postcode":"2285",
    "sg:province":"Nieder\u00f6sterreich",
    "wof:name":"Ivanics Regina",
    "wof:placetype":"venue"
},
  "geometry": {"coordinates":[16.6964511871,48.2304191589],"type":"Point"}
}