{
  "type": "Feature",
  "properties": {
    "addr:full":"Sportplatzsiedlung 11 St. Stefan ob Leoben Steiermark 8713",
    "addr:housenumber":"11",
    "addr:postcode":"8713",
    "addr:street":"Sportplatzsiedlung",
    "iso:country":"AT",
    "sg:address":"Sportplatzsiedlung 11",
    "sg:city":"St. Stefan ob Leoben",
    "sg:classifiers":[
        {
            "category":"Professional",
            "subcategory":"Management & Consulting",
            "type":"Services"
        }
    ],
    "sg:phone":"+43 3832 30057",
    "sg:postcode":"8713",
    "sg:province":"Steiermark",
    "sg:tags":[
        "hr",
        "resource",
        "consultancy",
        "human"
    ],
    "sg:website":"heg.at",
    "wof:name":"HEG Transport und Personalmanagement Ges.m.b.H.",
    "wof:placetype":"venue"
},
  "geometry": {"coordinates":[14.976650238,47.3161392212],"type":"Point"}
}