{
  "type": "Feature",
  "properties": {
    "addr:full":"Stephanspl 6/2 Wien Wien 1010",
    "addr:housenumber":"6 / 2",
    "addr:postcode":"1010",
    "addr:street":"Stephanspl",
    "iso:country":"AT",
    "sg:address":"Stephanspl 6/2",
    "sg:city":"Wien",
    "sg:orig_category":"Institute",
    "sg:phone":"+43 1 5137016",
    "sg:postcode":"1010",
    "sg:province":"Wien",
    "wof:name":"Institut d englischen Fr\u00e4ulein",
    "wof:placetype":"venue"
},
  "geometry": {"coordinates":[16.3738803864,48.208820343],"type":"Point"}
}