{
  "type": "Feature",
  "properties": {
    "addr:full":"Schulstr 9 Wallern an der Trattnach Ober\u00f6sterreich 4702",
    "addr:housenumber":"9",
    "addr:postcode":"4702",
    "addr:street":"Schulstr",
    "iso:country":"AT",
    "sg:address":"Schulstr 9",
    "sg:city":"Wallern an der Trattnach",
    "sg:orig_category":"Volksschulen",
    "sg:phone":"+43 4372 49481280",
    "sg:postcode":"4702",
    "sg:province":"Ober\u00f6sterreich",
    "wof:name":"Volksschule",
    "wof:placetype":"venue"
},
  "geometry": {"coordinates":[13.947845459,48.2327041626],"type":"Point"}
}