{
  "type": "Feature",
  "properties": {
    "iso:country":"AT",
    "sg:address":"Kalvarienbergg 66",
    "sg:city":"Wien",
    "sg:orig_category":"Apotheken",
    "sg:phone":"+43 1 40817600",
    "sg:postcode":"1170",
    "sg:province":"Wien",
    "wof:name":"Friedrichs-Apotheke Mag Christoph Siersch",
    "wof:placetype":"venue"
},
  "geometry": {"coordinates":[16.3353977203,48.2225227356],"type":"Point"}
}