{
  "type": "Feature",
  "properties": {
    "addr:full":"D\u00f6rferstr 15 Rum Tirol 6063",
    "addr:housenumber":"15",
    "addr:postcode":"6063",
    "addr:street":"Doerferstr;Tirol",
    "iso:country":"AT",
    "sg:address":"D\u00f6rferstr 15",
    "sg:city":"Rum",
    "sg:orig_category":"Gemeinden",
    "sg:phone":"+43 512 245110",
    "sg:postcode":"6063",
    "sg:province":"Tirol",
    "wof:name":"Marktgemeinde Rum",
    "wof:placetype":"venue"
},
  "geometry": {"coordinates":[11.4584417343,47.2873497009],"type":"Point"}
}