{
  "type": "Feature",
  "properties": {
    "iso:country":"AT",
    "sg:address":"Zugspitzstr 19",
    "sg:city":"Ehrwald",
    "sg:orig_category":"Transportunternehmen",
    "sg:phone":"+43 5673 2901",
    "sg:postcode":"6632",
    "sg:province":"Tirol",
    "wof:name":"Amort-Transporte GesmbH & Co KG",
    "wof:placetype":"venue"
},
  "geometry": {"coordinates":[10.9156742096,47.4104194641],"type":"Point"}
}