{
  "type": "Feature",
  "properties": {
    "iso:country":"AT",
    "sg:address":"G\u00f6riach 117",
    "sg:city":"Mariapfarr",
    "sg:orig_category":"Zimmereien",
    "sg:phone":"+43 6483 218",
    "sg:postcode":"5571",
    "sg:province":"Salzburg",
    "wof:name":"Winkler Johannes",
    "wof:placetype":"venue"
},
  "geometry": {"coordinates":[13.7468299866,47.1498031616],"type":"Point"}
}