{
  "type": "Feature",
  "properties": {
    "addr:full":"Hauptpl 6 Schweiggers Nieder\u00f6sterreich 3931",
    "addr:housenumber":"6",
    "addr:postcode":"3931",
    "addr:street":"Hauptpl",
    "iso:country":"AT",
    "sg:address":"Hauptpl 6",
    "sg:city":"Schweiggers",
    "sg:orig_category":"Banken U Sparkassen",
    "sg:phone":"+43 2829 8431",
    "sg:postcode":"3931",
    "sg:province":"Nieder\u00f6sterreich",
    "wof:name":"Bank und Sparkassen AG Waldviertel-Mitte",
    "wof:placetype":"venue"
},
  "geometry": {"coordinates":[15.0634002686,48.6678962708],"type":"Point"}
}