{
  "type": "Feature",
  "properties": {
    "iso:country":"AT",
    "sg:address":"Paracelsusstr",
    "sg:city":"Salzburg",
    "sg:orig_category":"Biologische Produkte",
    "sg:phone":"+43 662 870788",
    "sg:postcode":"5020",
    "sg:province":"Salzburg",
    "wof:name":"Kr\u00e4uter Paul",
    "wof:placetype":"venue"
},
  "geometry": {"coordinates":[13.0477457047,47.8110198975],"type":"Point"}
}