{
  "type": "Feature",
  "properties": {
    "addr:full":"Hauptpl 12 Trieben Steiermark 8784",
    "addr:housenumber":"12",
    "addr:postcode":"8784",
    "addr:street":"Hauptpl",
    "iso:country":"AT",
    "sg:address":"Hauptpl 12",
    "sg:city":"Trieben",
    "sg:orig_category":"Lebensmittel / Einzelhandel",
    "sg:phone":"+43 4336 152355",
    "sg:postcode":"8784",
    "sg:province":"Steiermark",
    "wof:name":"MONDO Lebensmitteldiskonter",
    "wof:placetype":"venue"
},
  "geometry": {"coordinates":[14.484128952,47.4874267578],"type":"Point"}
}