{
  "type": "Feature",
  "properties": {
    "addr:full":"Kranichbergstr. 16 Gloggnitz Nieder\u00f6sterreich 2640",
    "addr:housenumber":"16",
    "addr:postcode":"2640",
    "addr:street":"Kranichbergstr.",
    "iso:country":"AT",
    "sg:address":"Kranichbergstr. 16",
    "sg:city":"Gloggnitz",
    "sg:classifiers":[
        {
            "category":"Professional",
            "subcategory":"Engineering",
            "type":"Services"
        }
    ],
    "sg:phone":"+43 4326 62401",
    "sg:postcode":"2640",
    "sg:province":"Nieder\u00f6sterreich",
    "sg:tags":[
        "machine",
        "-",
        "mechanical"
    ],
    "wof:name":"EDER STRAHLTECHNIK GES.MBH",
    "wof:placetype":"venue"
},
  "geometry": {"coordinates":[15.953081131,47.6709976196],"type":"Point"}
}