{
  "type": "Feature",
  "properties": {
    "iso:country":"AT",
    "sg:address":"Triester Str 71",
    "sg:city":"Guntramsdorf",
    "sg:orig_category":"Bauunternehmen",
    "sg:phone":"+43 4366 42401852",
    "sg:postcode":"2353",
    "sg:province":"Nieder\u00f6sterreich",
    "wof:name":"B. I. BAU BIGL & JENNEWEIN KEG",
    "wof:placetype":"venue"
},
  "geometry": {"coordinates":[16.307882309,48.0521888733],"type":"Point"}
}