{
  "type": "Feature",
  "properties": {
    "addr:full":"Geschriebensteinstr Rechnitz Burgenland 7471",
    "addr:postcode":"7471",
    "iso:country":"AT",
    "sg:address":"Geschriebensteinstr",
    "sg:city":"Rechnitz",
    "sg:orig_category":"Lebensmittel / Einzelhandel",
    "sg:phone":"+43 3363 77228",
    "sg:postcode":"7471",
    "sg:province":"Burgenland",
    "wof:name":"Billa AG",
    "wof:placetype":"venue"
},
  "geometry": {"coordinates":[16.4113693237,47.347694397],"type":"Point"}
}