{
  "type": "Feature",
  "properties": {
    "addr:full":"Sch\u00f6ckelbachweg 33b Andritz Steiermark 8045",
    "addr:housenumber":"33b",
    "addr:postcode":"8045",
    "addr:street":"Schoeckelbachweg",
    "iso:country":"AT",
    "sg:address":"Sch\u00f6ckelbachweg 33b",
    "sg:city":"Andritz",
    "sg:orig_category":"Baumeister",
    "sg:phone":"+43 316 682263",
    "sg:postcode":"8045",
    "sg:province":"Steiermark",
    "wof:name":"Klug Peter R Ing",
    "wof:placetype":"venue"
},
  "geometry": {"coordinates":[15.4225482941,47.0988006592],"type":"Point"}
}