{
  "type": "Feature",
  "properties": {
    "addr:full":"Bichlfeldstrasse 16 Salzburg Salzburg 5020",
    "addr:housenumber":"16",
    "addr:postcode":"5020",
    "addr:street":"Bichlfeldstrasse;Salzburg",
    "iso:country":"AT",
    "sg:address":"Bichlfeldstrasse 16",
    "sg:city":"Salzburg",
    "sg:classifiers":[
        {
            "category":"Professional",
            "subcategory":"Engineering",
            "type":"Services"
        }
    ],
    "sg:phone":"+43 662 4512370",
    "sg:postcode":"5020",
    "sg:province":"Salzburg",
    "sg:tags":[
        "road",
        "surfacing",
        "asphalt",
        "highway"
    ],
    "wof:name":"Verband der G\u00fcterweggenossenschaften im Bundesland Salzburg",
    "wof:placetype":"venue"
},
  "geometry": {"coordinates":[13.0035743713,47.8284912109],"type":"Point"}
}