{
  "type": "Feature",
  "properties": {
    "addr:full":"Triester Str. 267  Wien Wien 1230",
    "addr:housenumber":"267",
    "addr:postcode":"1230",
    "addr:street":"Str.",
    "iso:country":"AT",
    "sg:address":"Triester Str. 267 ",
    "sg:city":"Wien",
    "sg:classifiers":[
        {
            "category":"Bars & Pubs",
            "subcategory":"Nightclub",
            "type":"Food & Drink"
        }
    ],
    "sg:phone":"+43 4316 650198",
    "sg:postcode":"1230",
    "sg:province":"Wien",
    "sg:tags":[
        "cake",
        "bread"
    ],
    "wof:name":"SCHRAMMEL BROT GES.MBH",
    "wof:placetype":"venue"
},
  "geometry": {"coordinates":[16.3303203583,48.1426048279],"type":"Point"}
}