{
  "type": "Feature",
  "properties": {
    "addr:full":"Binderg 6 Neumarkt im M\u00fchlkreis Ober\u00f6sterreich 4212",
    "addr:housenumber":"6",
    "addr:postcode":"4212",
    "addr:street":"Binderg",
    "iso:country":"AT",
    "sg:address":"Binderg 6",
    "sg:city":"Neumarkt im M\u00fchlkreis",
    "sg:orig_category":"Alternativtherapie",
    "sg:phone":"+43 4379 4120623",
    "sg:postcode":"4212",
    "sg:province":"Ober\u00f6sterreich",
    "wof:name":"W\u00f6ckinger Rosa",
    "wof:placetype":"venue"
},
  "geometry": {"coordinates":[14.4864873886,48.4276924133],"type":"Point"}
}