{
  "type": "Feature",
  "properties": {
    "iso:country":"AT",
    "sg:address":"Eiselsberggang 5",
    "sg:city":"Linz",
    "sg:orig_category":"Steuerberatung",
    "sg:phone":"+43 732 6617210",
    "sg:postcode":"4020",
    "sg:province":"Ober\u00f6sterreich",
    "sg:website":"www.elter.at",
    "wof:name":"Elter Wirtschaftstreuhand GesmbH",
    "wof:placetype":"venue"
},
  "geometry": {"coordinates":[14.2912187576,48.2830924988],"type":"Point"}
}