{
  "type": "Feature",
  "properties": {
    "iso:country":"AT",
    "sg:address":"Franz-Senn-Str 11",
    "sg:city":"Neustift im Stubaital",
    "sg:orig_category":"Appartements / Ferienwohnungen",
    "sg:phone":"+43 4352 263433",
    "sg:postcode":"6167",
    "sg:province":"Tirol",
    "wof:name":"Appartement Ribis",
    "wof:placetype":"venue"
},
  "geometry": {"coordinates":[11.2925424576,47.1050338745],"type":"Point"}
}