{
  "type": "Feature",
  "properties": {
    "addr:full":"Brucker Str 6 Frohnleiten Steiermark 8130",
    "addr:housenumber":"6",
    "addr:postcode":"8130",
    "addr:street":"Str",
    "iso:country":"AT",
    "sg:address":"Brucker Str 6",
    "sg:city":"Frohnleiten",
    "sg:orig_category":"Tankstellen",
    "sg:phone":"+43 4331 2622640",
    "sg:postcode":"8130",
    "sg:province":"Steiermark",
    "wof:name":"BP Tankstelle",
    "wof:placetype":"venue"
},
  "geometry": {"coordinates":[15.3275671005,47.2747955322],"type":"Point"}
}