{
  "type": "Feature",
  "properties": {
    "addr:full":"Nr 4 St. Kanzian am Klopeiner See K\u00e4rnten 9122",
    "addr:housenumber":"4",
    "addr:postcode":"9122",
    "addr:street":"Nr;Kaernten",
    "iso:country":"AT",
    "sg:address":"Nr 4",
    "sg:city":"St. Kanzian am Klopeiner See",
    "sg:orig_category":"Appartements / Ferienwohnungen",
    "sg:phone":"+43 4342 328441",
    "sg:postcode":"9122",
    "sg:province":"K\u00e4rnten",
    "wof:name":"M\u00fcllner Sophie u Willi",
    "wof:placetype":"venue"
},
  "geometry": {"coordinates":[14.5756397247,46.6140594482],"type":"Point"}
}