{
  "type": "Feature",
  "properties": {
    "addr:full":"Kirchenpl 2 Steinerkirchen an der Traun Ober\u00f6sterreich 4652",
    "addr:housenumber":"2",
    "addr:postcode":"4652",
    "addr:street":"Kirchenpl",
    "iso:country":"AT",
    "sg:address":"Kirchenpl 2",
    "sg:city":"Steinerkirchen an der Traun",
    "sg:orig_category":"Non-Classified Establishments",
    "sg:phone":"+43 7241 2206",
    "sg:postcode":"4652",
    "sg:province":"Ober\u00f6sterreich",
    "wof:name":"Pfarramt Steinerkirchen a d Traun",
    "wof:placetype":"venue"
},
  "geometry": {"coordinates":[13.9578104019,48.077331543],"type":"Point"}
}