{
  "type": "Feature",
  "properties": {
    "addr:full":"Untereching/Tischlerstrasse 22-24 St. Georgen Salzburg 5113",
    "addr:housenumber":"22-24",
    "addr:postcode":"5113",
    "addr:street":"Tischlerstrasse",
    "iso:country":"AT",
    "sg:address":"Untereching/Tischlerstrasse 22-24",
    "sg:city":"St. Georgen",
    "sg:classifiers":[
        {
            "category":"Manufacturing",
            "subcategory":"Furniture",
            "type":"Manufacturing & Wholesale Goods"
        }
    ],
    "sg:phone":"+43 6272 8105",
    "sg:postcode":"5113",
    "sg:province":"Salzburg",
    "sg:tags":[
        "bedroom"
    ],
    "sg:website":"tischlerei-spatzenegger.at",
    "wof:name":"Johann Spatzenegger",
    "wof:placetype":"venue"
},
  "geometry": {"coordinates":[12.880112648,47.9934806824],"type":"Point"}
}