{
  "type": "Feature",
  "properties": {
    "addr:full":"Nr 114 F\u00fcgen Tirol 6263",
    "addr:postcode":"6263",
    "addr:street":"Nr 114 Fuegen Tirol",
    "iso:country":"AT",
    "sg:address":"Nr 114",
    "sg:city":"F\u00fcgen",
    "sg:orig_category":"Erdarbeiten",
    "sg:phone":"+43 5288 62548",
    "sg:postcode":"6263",
    "sg:province":"Tirol",
    "wof:name":"Thanner GmbH",
    "wof:placetype":"venue"
},
  "geometry": {"coordinates":[11.8493213654,47.3472557068],"type":"Point"}
}