{
  "type": "Feature",
  "properties": {
    "addr:full":"Lorbersteig 1 Krumpendorf K\u00e4rnten 9201",
    "addr:housenumber":"1",
    "addr:postcode":"9201",
    "addr:street":"Lorbersteig;Kaernten",
    "iso:country":"AT",
    "sg:address":"Lorbersteig 1",
    "sg:city":"Krumpendorf",
    "sg:classifiers":[
        {
            "category":"Retail",
            "subcategory":"Laundry & Dry Cleaning",
            "type":"Services"
        }
    ],
    "sg:phone":"+43 4229 20235",
    "sg:postcode":"9201",
    "sg:province":"K\u00e4rnten",
    "sg:tags":[
        "steel",
        "abrasive",
        "product",
        "stainless"
    ],
    "wof:name":"Handelsagentur J.R. Geisler",
    "wof:placetype":"venue"
},
  "geometry": {"coordinates":[14.2127580643,46.6271743774],"type":"Point"}
}