{
  "type": "Feature",
  "properties": {
    "addr:full":"Wiesfleck 68 Pinkafeld Burgenland 7423",
    "addr:housenumber":"68",
    "addr:postcode":"7423",
    "addr:street":"Wiesfleck",
    "iso:country":"AT",
    "sg:address":"Wiesfleck 68",
    "sg:city":"Pinkafeld",
    "sg:classifiers":[
        {
            "category":"Manufacturing",
            "subcategory":"Wood Products",
            "type":"Manufacturing & Wholesale Goods"
        }
    ],
    "sg:phone":"+43 3357 42215",
    "sg:postcode":"7423",
    "sg:province":"Burgenland",
    "sg:tags":[
        "gate",
        "made",
        "door"
    ],
    "wof:name":"Harald Honigschnabel",
    "wof:placetype":"venue"
},
  "geometry": {"coordinates":[16.1494903564,47.3843421936],"type":"Point"}
}