{
  "type": "Feature",
  "properties": {
    "addr:full":"Belruptstr 44 Bregenz Vorarlberg 6900",
    "addr:housenumber":"44",
    "addr:postcode":"6900",
    "addr:street":"Belruptstr",
    "iso:country":"AT",
    "sg:address":"Belruptstr 44",
    "sg:city":"Bregenz",
    "sg:orig_category":"Elektroinstallationsunternehmen",
    "sg:phone":"+43 5574 427211",
    "sg:postcode":"6900",
    "sg:province":"Vorarlberg",
    "wof:name":"Pircher Elektrotechnik",
    "wof:placetype":"venue"
},
  "geometry": {"coordinates":[9.7534151077,47.5063285828],"type":"Point"}
}