{
  "type": "Feature",
  "properties": {
    "addr:full":"Leobersdorfer Str 43 Hirtenberg Nieder\u00f6sterreich 2552",
    "addr:housenumber":"43",
    "addr:postcode":"2552",
    "addr:street":"Str",
    "iso:country":"AT",
    "sg:address":"Leobersdorfer Str 43",
    "sg:city":"Hirtenberg",
    "sg:orig_category":"Immobilienmakler",
    "sg:phone":"+43 4322 5681962",
    "sg:postcode":"2552",
    "sg:province":"Nieder\u00f6sterreich",
    "wof:name":"Reale Bautr\u00e4ger- u ImmobiliengesmbH",
    "wof:placetype":"venue"
},
  "geometry": {"coordinates":[16.1883087158,47.9315834045],"type":"Point"}
}