{
  "type": "Feature",
  "properties": {
    "iso:country":"AT",
    "sg:address":"Buchauer Bundesstr 605",
    "sg:city":"Admont",
    "sg:orig_category":"Blumeneinzelhandel",
    "sg:phone":"+43 4336 133292",
    "sg:postcode":"8911",
    "sg:province":"Steiermark",
    "sg:website":"ennstaler-gartenland.at",
    "wof:name":"Ennstaler Gartenland u Floristikwerkstatt Sch\u00f6nleitner",
    "wof:placetype":"venue"
},
  "geometry": {"coordinates":[14.4730319977,47.5919876099],"type":"Point"}
}