{
  "type": "Feature",
  "properties": {
    "iso:country":"AT",
    "sg:address":"Brodtischg 21",
    "sg:city":"Wiener Neustadt",
    "sg:orig_category":"Fu\u00c3\u0178pflege U Fu\u00c3\u0178pflegesalons",
    "sg:phone":"+43 4326 2224697",
    "sg:postcode":"2700",
    "sg:province":"Nieder\u00f6sterreich",
    "wof:name":"Fu\u00dfpflegesalon Brigitte",
    "wof:placetype":"venue"
},
  "geometry": {"coordinates":[16.2428398132,47.8110275269],"type":"Point"}
}