{
  "type": "Feature",
  "properties": {
    "iso:country":"AT",
    "sg:address":"Hammerrain 7",
    "sg:city":"Flachau",
    "sg:orig_category":"Pensionen / Privatzimmer",
    "sg:phone":"+43 6457 22180",
    "sg:postcode":"5542",
    "sg:province":"Salzburg",
    "wof:name":"G\u00e4stehaus Rainh\u00e4usl",
    "wof:placetype":"venue"
},
  "geometry": {"coordinates":[13.3949394226,47.3453636169],"type":"Point"}
}