{
  "type": "Feature",
  "properties": {
    "addr:full":"Leiteng 47 Wien Wien 1230",
    "addr:housenumber":"47",
    "addr:postcode":"1230",
    "addr:street":"Leiteng",
    "iso:country":"AT",
    "sg:address":"Leiteng 47",
    "sg:city":"Wien",
    "sg:orig_category":"Ingenieurkonsulenten / Zivilingenieure",
    "sg:phone":"+43 1 8891716",
    "sg:postcode":"1230",
    "sg:province":"Wien",
    "wof:name":"Meyer Fritz Dipl-Ing",
    "wof:placetype":"venue"
},
  "geometry": {"coordinates":[16.2674369812,48.1566429138],"type":"Point"}
}