{
  "type": "Feature",
  "properties": {
    "addr:full":"Unterlinden 24 A  Wolfurt Vorarlberg 6922",
    "addr:housenumber":"24 a",
    "addr:postcode":"6922",
    "addr:street":"Unterlinden",
    "iso:country":"AT",
    "sg:address":"Unterlinden 24 A ",
    "sg:city":"Wolfurt",
    "sg:classifiers":[
        {
            "category":"Shopping",
            "subcategory":"Crafts & Fabrics",
            "type":"Retail Goods"
        }
    ],
    "sg:phone":"+43 4355 7474748",
    "sg:postcode":"6922",
    "sg:province":"Vorarlberg",
    "wof:name":"FEND & EBERLE GMBH",
    "wof:placetype":"venue"
},
  "geometry": {"coordinates":[9.7501468658,47.4715423584],"type":"Point"}
}