{
  "type": "Feature",
  "properties": {
    "addr:full":"Bachg 15 Tulln an der Donau Nieder\u00f6sterreich 3430",
    "addr:housenumber":"15",
    "addr:postcode":"3430",
    "addr:street":"Bachg",
    "iso:country":"AT",
    "sg:address":"Bachg 15",
    "sg:city":"Tulln an der Donau",
    "sg:orig_category":"Architekten",
    "sg:phone":"+43 4322 7282638",
    "sg:postcode":"3430",
    "sg:province":"Nieder\u00f6sterreich",
    "wof:name":"H\u00f6fer Werner Mag arch",
    "wof:placetype":"venue"
},
  "geometry": {"coordinates":[16.0588340759,48.2983360291],"type":"Point"}
}