{
  "type": "Feature",
  "properties": {
    "addr:full":"Rutzenmoos 76 Rutzenmoos Ober\u00f6sterreich 4845",
    "addr:housenumber":"76",
    "addr:postcode":"4845",
    "addr:street":"Rutzenmoos",
    "iso:country":"AT",
    "sg:address":"Rutzenmoos 76",
    "sg:city":"Rutzenmoos",
    "sg:classifiers":[
        {
            "category":"Professional",
            "subcategory":"Advertising",
            "type":"Services"
        }
    ],
    "sg:phone":"+43 767223813",
    "sg:postcode":"4845",
    "sg:province":"Ober\u00f6sterreich",
    "sg:tags":[
        "agency"
    ],
    "wof:name":"Werbe Creation Stadlbauer",
    "wof:placetype":"venue"
},
  "geometry": {"coordinates":[13.7086877823,47.9778518677],"type":"Point"}
}