{
  "type": "Feature",
  "properties": {
    "addr:full":"Metzgerstr. 66 Bergheim Salzburg 5101",
    "addr:housenumber":"66",
    "addr:postcode":"5101",
    "addr:street":"Metzgerstr.;Salzburg",
    "iso:country":"AT",
    "sg:address":"Metzgerstr. 66",
    "sg:city":"Bergheim",
    "sg:classifiers":[
        {
            "category":"Personal",
            "subcategory":"Shoe Repair & Shine",
            "type":"Services"
        }
    ],
    "sg:phone":"+43 4366 24507670",
    "sg:postcode":"5101",
    "sg:province":"Salzburg",
    "sg:tags":[
        "leather"
    ],
    "wof:name":"ZOTH SCHUHANDELS GES.MBH",
    "wof:placetype":"venue"
},
  "geometry": {"coordinates":[13.01521492,47.8474998474],"type":"Point"}
}