{
  "type": "Feature",
  "properties": {
    "addr:full":"Schildbach 51 Hartberg Steiermark 8230",
    "addr:housenumber":"51",
    "addr:postcode":"8230",
    "addr:street":"Schildbach",
    "iso:country":"AT",
    "sg:address":"Schildbach 51",
    "sg:city":"Hartberg",
    "sg:orig_category":"Tankstellen",
    "sg:phone":"+43 4333 32608519",
    "sg:postcode":"8230",
    "sg:province":"Steiermark",
    "wof:name":"Echo Tankstelle",
    "wof:placetype":"venue"
},
  "geometry": {"coordinates":[15.9538917542,47.2759628296],"type":"Point"}
}