{
  "type": "Feature",
  "properties": {
    "addr:full":"Nr 50 Millstatt K\u00e4rnten 9872",
    "addr:postcode":"9872",
    "addr:street":"Nr 50;Kaernten",
    "iso:country":"AT",
    "sg:address":"Nr 50",
    "sg:city":"Millstatt",
    "sg:orig_category":"Pensionen / Privatzimmer",
    "sg:phone":"+43 4766 3627",
    "sg:postcode":"9872",
    "sg:province":"K\u00e4rnten",
    "wof:name":"Haus Alpenblick",
    "wof:placetype":"venue"
},
  "geometry": {"coordinates":[13.5716075897,46.8050041199],"type":"Point"}
}