{
  "type": "Feature",
  "properties": {
    "addr:full":"Obeltsham 29 Gaspoltshofen Ober\u00f6sterreich 4673",
    "addr:housenumber":"29",
    "addr:postcode":"4673",
    "addr:street":"Obeltsham",
    "iso:country":"AT",
    "sg:address":"Obeltsham 29",
    "sg:city":"Gaspoltshofen",
    "sg:classifiers":[
        {
            "category":"Animal Shelter",
            "type":"Public Place"
        }
    ],
    "sg:phone":"+43 7735 6867",
    "sg:postcode":"4673",
    "sg:province":"Ober\u00f6sterreich",
    "sg:tags":[
        "feed",
        "additive"
    ],
    "sg:website":"aspoeck.co.at",
    "wof:name":"Wolfgang Asp\u00f6ck",
    "wof:placetype":"venue"
},
  "geometry": {"coordinates":[13.7259464264,48.131477356],"type":"Point"}
}