{
  "type": "Feature",
  "properties": {
    "addr:full":"Max-Winter-Pl 6 Wien Wien 1020",
    "addr:housenumber":"6",
    "addr:postcode":"1020",
    "addr:street":"Max-Winter-Pl",
    "iso:country":"AT",
    "sg:address":"Max-Winter-Pl 6",
    "sg:city":"Wien",
    "sg:orig_category":"Elektroinstallationsunternehmen",
    "sg:phone":"+43 1 7280265",
    "sg:postcode":"1020",
    "sg:province":"Wien",
    "wof:name":"Schell G & Co",
    "wof:placetype":"venue"
},
  "geometry": {"coordinates":[16.3994960785,48.2209129333],"type":"Point"}
}