{
  "type": "Feature",
  "properties": {
    "addr:full":"Andechsstr 85 Innsbruck Tirol 6020",
    "addr:housenumber":"85",
    "addr:postcode":"6020",
    "addr:street":"Andechsstr;Tirol",
    "iso:country":"AT",
    "sg:address":"Andechsstr 85",
    "sg:city":"Innsbruck",
    "sg:orig_category":"Teppiche / Einzelhandel",
    "sg:phone":"+43 512 393738",
    "sg:postcode":"6020",
    "sg:province":"Tirol",
    "wof:name":"Muigg Teppichparadies",
    "wof:placetype":"venue"
},
  "geometry": {"coordinates":[11.4265737534,47.2647857666],"type":"Point"}
}