{
  "type": "Feature",
  "properties": {
    "iso:country":"AT",
    "sg:address":"Hochhaus 4",
    "sg:city":"Hofkirchen im M\u00fchlkreis",
    "sg:orig_category":"Transportunternehmen",
    "sg:phone":"+43 7285 6414",
    "sg:postcode":"4142",
    "sg:province":"Ober\u00f6sterreich",
    "wof:name":"Neum\u00fcller Friedrich",
    "wof:placetype":"venue"
},
  "geometry": {"coordinates":[13.7852230072,48.5108184814],"type":"Point"}
}