{
  "type": "Feature",
  "properties": {
    "addr:full":"Boder 251 Rottenmann Steiermark 8786",
    "addr:housenumber":"251",
    "addr:postcode":"8786",
    "addr:street":"Boder",
    "iso:country":"AT",
    "sg:address":"Boder 251",
    "sg:city":"Rottenmann",
    "sg:orig_category":"Fotografen",
    "sg:phone":"+43 664 1919182",
    "sg:postcode":"8786",
    "sg:province":"Steiermark",
    "wof:name":"Foto Schnitzer",
    "wof:placetype":"venue"
},
  "geometry": {"coordinates":[14.3770866394,47.5248298645],"type":"Point"}
}