{
  "type": "Feature",
  "properties": {
    "iso:country":"AT",
    "sg:address":"Untere Dorfstr 28",
    "sg:city":"Serfaus",
    "sg:orig_category":"Appartements / Ferienwohnungen",
    "sg:phone":"+43 4354 766298",
    "sg:postcode":"6534",
    "sg:province":"Tirol",
    "wof:name":"Landhaus Schwarz",
    "wof:placetype":"venue"
},
  "geometry": {"coordinates":[10.6055011749,47.038269043],"type":"Point"}
}