{
  "type": "Feature",
  "properties": {
    "addr:full":"Siegespl 5 Wien Wien 1220",
    "addr:housenumber":"5",
    "addr:postcode":"1220",
    "addr:street":"Siegespl",
    "iso:country":"AT",
    "sg:address":"Siegespl 5",
    "sg:city":"Wien",
    "sg:orig_category":"Alternativtherapie",
    "sg:phone":"+43 4312 8054820",
    "sg:postcode":"1220",
    "sg:province":"Wien",
    "sg:website":"hello.to/naturpraxis",
    "wof:name":"Naturpraxis SUS",
    "wof:placetype":"venue"
},
  "geometry": {"coordinates":[16.4854812622,48.2177391052],"type":"Point"}
}