{
  "type": "Feature",
  "properties": {
    "iso:country":"AT",
    "sg:address":"Austr 3",
    "sg:city":"Mautern",
    "sg:orig_category":"Tanzschulen",
    "sg:phone":"+43 2732 75285",
    "sg:postcode":"3512",
    "sg:province":"Nieder\u00f6sterreich",
    "wof:name":"Tanzschule Caterino - Sylvia Caterino",
    "wof:placetype":"venue"
},
  "geometry": {"coordinates":[15.5512466431,48.3772163391],"type":"Point"}
}