{
  "type": "Feature",
  "properties": {
    "iso:country":"AT",
    "sg:address":"Steinacker 4",
    "sg:city":"G\u00f6fis",
    "sg:classifiers":[
        {
            "category":"Communications",
            "subcategory":"Film & Video Production",
            "type":"Services"
        }
    ],
    "sg:phone":"+43 5522 73344",
    "sg:postcode":"6811",
    "sg:province":"Vorarlberg",
    "sg:tags":[
        "photography",
        "digital"
    ],
    "sg:website":"new-media.at",
    "wof:name":"STUDIO WIDNAU Peter Hladky",
    "wof:placetype":"venue"
},
  "geometry": {"coordinates":[-90.2028045654,36.7827301025],"type":"Point"}
}