{
  "type": "Feature",
  "properties": {
    "iso:country":"AT",
    "sg:address":"St Magdalener Str 16A",
    "sg:city":"Villach",
    "sg:orig_category":"Installationsunternehmen",
    "sg:phone":"+43 4242 219237",
    "sg:postcode":"9500",
    "sg:province":"K\u00e4rnten",
    "wof:name":"Rainer GmbH & Co KG",
    "wof:placetype":"venue"
},
  "geometry": {"coordinates":[13.8613700867,46.6148605347],"type":"Point"}
}