{
  "type": "Feature",
  "properties": {
    "addr:full":"Schmiedgrub 1 St. Martin im M\u00fchlkreis Ober\u00f6sterreich 4113",
    "addr:housenumber":"1",
    "addr:postcode":"4113",
    "addr:street":"Schmiedgrub;Im Muehlkreis Oberoesterreich",
    "iso:country":"AT",
    "sg:address":"Schmiedgrub 1",
    "sg:city":"St. Martin im M\u00fchlkreis",
    "sg:orig_category":"Tischlereien",
    "sg:phone":"+43 7232 36480",
    "sg:postcode":"4113",
    "sg:province":"Ober\u00f6sterreich",
    "wof:name":"Kepplinger Siegfried",
    "wof:placetype":"venue"
},
  "geometry": {"coordinates":[14.0460567474,48.4156455994],"type":"Point"}
}