{
  "type": "Feature",
  "properties": {
    "addr:full":"Marktg 7a Feldkirch Vorarlberg 6800",
    "addr:housenumber":"7a",
    "addr:postcode":"6800",
    "addr:street":"Marktg",
    "iso:country":"AT",
    "sg:address":"Marktg 7a",
    "sg:city":"Feldkirch",
    "sg:orig_category":"Baumeister",
    "sg:phone":"+43 5522 73876",
    "sg:postcode":"6800",
    "sg:province":"Vorarlberg",
    "wof:name":"Mahlknecht Josef Bmstr",
    "wof:placetype":"venue"
},
  "geometry": {"coordinates":[9.5967845917,47.2381515503],"type":"Point"}
}