{
  "type": "Feature",
  "properties": {
    "addr:full":"Wildbichler Str 29 Ebbs Tirol 6341",
    "addr:housenumber":"29",
    "addr:postcode":"6341",
    "addr:street":"Str;Tirol",
    "iso:country":"AT",
    "sg:address":"Wildbichler Str 29",
    "sg:city":"Ebbs",
    "sg:orig_category":"Tourismusinformation U -Organisationen",
    "sg:phone":"+43 5373 423260",
    "sg:postcode":"6341",
    "sg:province":"Tirol",
    "wof:name":"Tourismusverband und G\u00e4steinformation",
    "wof:placetype":"venue"
},
  "geometry": {"coordinates":[12.2142438889,47.6295013428],"type":"Point"}
}