{
  "type": "Feature",
  "properties": {
    "addr:full":"Herreng 24 Th\u00fcringen Vorarlberg 6712",
    "addr:housenumber":"24",
    "addr:postcode":"6712",
    "addr:street":"Herreng",
    "iso:country":"AT",
    "sg:address":"Herreng 24",
    "sg:city":"Th\u00fcringen",
    "sg:orig_category":"Raumausstattung",
    "sg:phone":"+43 4355 5022880",
    "sg:postcode":"6712",
    "sg:province":"Vorarlberg",
    "wof:name":"Berle Manfred",
    "wof:placetype":"venue"
},
  "geometry": {"coordinates":[9.7619409561,47.2009315491],"type":"Point"}
}