{
  "type": "Feature",
  "properties": {
    "addr:full":"Ungarg 49 Wien Wien 1030",
    "addr:housenumber":"49",
    "addr:postcode":"1030",
    "addr:street":"Ungarg",
    "iso:country":"AT",
    "sg:address":"Ungarg 49",
    "sg:city":"Wien",
    "sg:orig_category":"Tabaktrafiken",
    "sg:phone":"+43 1 7131856",
    "sg:postcode":"1030",
    "sg:province":"Wien",
    "wof:name":"Stummer Anton",
    "wof:placetype":"venue"
},
  "geometry": {"coordinates":[16.3875961304,48.1992073059],"type":"Point"}
}