{
  "type": "Feature",
  "properties": {
    "addr:full":"Neulingg. 37 Wien Wien 1030",
    "addr:housenumber":"37",
    "addr:postcode":"1030",
    "addr:street":"Neulingg.",
    "iso:country":"AT",
    "sg:address":"Neulingg. 37",
    "sg:city":"Wien",
    "sg:classifiers":[
        {
            "category":"Communications",
            "subcategory":"Newspaper",
            "type":"Services"
        }
    ],
    "sg:phone":"+43 4317 17860",
    "sg:postcode":"1030",
    "sg:province":"Wien",
    "sg:tags":[
        "advertising"
    ],
    "wof:name":"E C C PUBLICO PUBLICRELATIONS GESMBH",
    "wof:placetype":"venue"
},
  "geometry": {"coordinates":[16.4025096893,48.1936683655],"type":"Point"}
}