{
  "type": "Feature",
  "properties": {
    "addr:full":"Gregerstr 13 Fischamend Nieder\u00f6sterreich 2401",
    "addr:housenumber":"13",
    "addr:postcode":"2401",
    "addr:street":"Gregerstr",
    "iso:country":"AT",
    "sg:address":"Gregerstr 13",
    "sg:city":"Fischamend",
    "sg:orig_category":"Elektroinstallationsunternehmen",
    "sg:phone":"+43 664 1317678",
    "sg:postcode":"2401",
    "sg:province":"Nieder\u00f6sterreich",
    "wof:name":"Elsan Elektro & Installations GmbH",
    "wof:placetype":"venue"
},
  "geometry": {"coordinates":[16.6114196777,48.1170883179],"type":"Point"}
}