{
  "type": "Feature",
  "properties": {
    "addr:full":"Grawatschg 4 Wien Wien 1230",
    "addr:housenumber":"4",
    "addr:postcode":"1230",
    "addr:street":"Grawatschg",
    "iso:country":"AT",
    "sg:address":"Grawatschg 4",
    "sg:city":"Wien",
    "sg:classifiers":[
        {
            "category":"Building & Trades",
            "subcategory":"Construction",
            "type":"Services"
        }
    ],
    "sg:phone":"+43 1 66246800",
    "sg:postcode":"1230",
    "sg:province":"Wien",
    "sg:tags":[
        "aggregate"
    ],
    "wof:name":"IMV Invertomatic Victron Energiesysteme HandelsgesmbH",
    "wof:placetype":"venue"
},
  "geometry": {"coordinates":[16.3260269165,48.1382484436],"type":"Point"}
}