{
  "type": "Feature",
  "properties": {
    "addr:full":"Pater-Gratian-Leser-Str 9 G\u00fcssing Burgenland 7540",
    "addr:housenumber":"9",
    "addr:postcode":"7540",
    "addr:street":"Pater-Gratian-Leser-Str",
    "iso:country":"AT",
    "sg:address":"Pater-Gratian-Leser-Str 9",
    "sg:city":"G\u00fcssing",
    "sg:classifiers":[
        {
            "category":"Professional",
            "subcategory":"Computer Services",
            "type":"Services"
        }
    ],
    "sg:phone":"+43 4333 2242363",
    "sg:postcode":"7540",
    "sg:province":"Burgenland",
    "sg:tags":[
        "software"
    ],
    "wof:name":"IT ++ Enterprise Information Services Softwareentwicklungs GmbH",
    "wof:placetype":"venue"
},
  "geometry": {"coordinates":[16.3242702484,47.0595169067],"type":"Point"}
}