{
  "type": "Feature",
  "properties": {
    "addr:full":"Oberhoferstr 41a Mistelbach Nieder\u00f6sterreich 2130",
    "addr:housenumber":"41a",
    "addr:postcode":"2130",
    "addr:street":"Oberhoferstr;Niederoesterreich",
    "iso:country":"AT",
    "sg:address":"Oberhoferstr 41a",
    "sg:city":"Mistelbach",
    "sg:orig_category":"Volksschulen",
    "sg:phone":"+43 2572 32449",
    "sg:postcode":"2130",
    "sg:province":"Nieder\u00f6sterreich",
    "wof:name":"KIM-Schule i d alten Milchkammer",
    "wof:placetype":"venue"
},
  "geometry": {"coordinates":[16.5702724457,48.5745773315],"type":"Point"}
}