{
  "type": "Feature",
  "properties": {
    "addr:full":"Graben 31  Wien Wien 1010",
    "addr:housenumber":"31",
    "addr:postcode":"1010",
    "addr:street":"Graben",
    "iso:country":"AT",
    "sg:address":"Graben 31 ",
    "sg:city":"Wien",
    "sg:classifiers":[
        {
            "category":"Communications",
            "subcategory":"Television Station",
            "type":"Services"
        }
    ],
    "sg:phone":"+43 4315 320102",
    "sg:postcode":"1010",
    "sg:province":"Wien",
    "sg:tags":[
        "electronic",
        "publishing"
    ],
    "wof:name":"GEROLD & CO",
    "wof:placetype":"venue"
},
  "geometry": {"coordinates":[16.3709983826,48.2082557678],"type":"Point"}
}