{
  "type": "Feature",
  "properties": {
    "addr:full":"Wiener Str 1A Hornstein Burgenland 7053",
    "addr:postcode":"7053",
    "addr:street":"Str 1A",
    "iso:country":"AT",
    "sg:address":"Wiener Str 1A",
    "sg:city":"Hornstein",
    "sg:orig_category":"Weine / Einzelhandel",
    "sg:phone":"+43 2689 2084",
    "sg:postcode":"7053",
    "sg:province":"Burgenland",
    "wof:name":"Pinter Helmut und Judith",
    "wof:placetype":"venue"
},
  "geometry": {"coordinates":[16.4397373199,47.8789482117],"type":"Point"}
}