{
  "type": "Feature",
  "properties": {
    "addr:full":"Plattwies 490 Kappl Tirol 6555",
    "addr:housenumber":"490",
    "addr:postcode":"6555",
    "addr:street":"Plattwies;Tirol",
    "iso:country":"AT",
    "sg:address":"Plattwies 490",
    "sg:city":"Kappl",
    "sg:orig_category":"Baumeister",
    "sg:phone":"+43 5445 6616",
    "sg:postcode":"6555",
    "sg:province":"Tirol",
    "wof:name":"Poller Gerhard Ing",
    "wof:placetype":"venue"
},
  "geometry": {"coordinates":[10.3906888962,47.070690155],"type":"Point"}
}