{
  "type": "Feature",
  "properties": {
    "iso:country":"AT",
    "sg:address":"Nr 29",
    "sg:city":"Mautern",
    "sg:orig_category":"Gemeinden",
    "sg:phone":"+43 2714 7220",
    "sg:postcode":"3512",
    "sg:province":"Nieder\u00f6sterreich",
    "wof:name":"Gemeindeamt Bergern im Dunkelsteinerwald",
    "wof:placetype":"venue"
},
  "geometry": {"coordinates":[15.577627182,48.3937988281],"type":"Point"}
}