{
  "type": "Feature",
  "properties": {
    "addr:full":"Marktstr 67 Dornbirn Vorarlberg 6850",
    "addr:housenumber":"67",
    "addr:postcode":"6850",
    "addr:street":"Marktstr",
    "iso:country":"AT",
    "sg:address":"Marktstr 67",
    "sg:city":"Dornbirn",
    "sg:orig_category":"Lebensmittel / Einzelhandel",
    "sg:phone":"+43 5572 25632",
    "sg:postcode":"6850",
    "sg:province":"Vorarlberg",
    "wof:name":"SPAR \u00f6sterr Warenhandels-AG",
    "wof:placetype":"venue"
},
  "geometry": {"coordinates":[9.7420406342,47.4076499939],"type":"Point"}
}