{
  "type": "Feature",
  "properties": {
    "addr:full":"Jupiterstr. 8  Ternberg Ober\u00f6sterreich 4452",
    "addr:housenumber":"8",
    "addr:postcode":"4452",
    "addr:street":"Jupiterstr.",
    "iso:country":"AT",
    "sg:address":"Jupiterstr. 8 ",
    "sg:city":"Ternberg",
    "sg:classifiers":[
        {
            "category":"Manufacturing",
            "subcategory":"Rubber & Plastics",
            "type":"Manufacturing & Wholesale Goods"
        }
    ],
    "sg:phone":"+43 4372 566025",
    "sg:postcode":"4452",
    "sg:province":"Ober\u00f6sterreich",
    "wof:name":"SIBU DESIGN GMBH & CO KG",
    "wof:placetype":"venue"
},
  "geometry": {"coordinates":[14.3536615372,47.956829071],"type":"Point"}
}