{
  "type": "Feature",
  "properties": {
    "addr:full":"Nr 170 G\u00f6stling an der Ybbs Nieder\u00f6sterreich 3345",
    "addr:postcode":"3345",
    "addr:street":"Nr 170 Goestling An Der Ybbs",
    "iso:country":"AT",
    "sg:address":"Nr 170",
    "sg:city":"G\u00f6stling an der Ybbs",
    "sg:orig_category":"Lebensmittel / Einzelhandel",
    "sg:phone":"+43 7484 5008",
    "sg:postcode":"3345",
    "sg:province":"Nieder\u00f6sterreich",
    "wof:name":"Spar-Markt K\u00e4fer-Lengauer Christa",
    "wof:placetype":"venue"
},
  "geometry": {"coordinates":[166.9221496582,-0.5282999873],"type":"Point"}
}