{
  "type": "Feature",
  "properties": {
    "addr:full":"Ernst-Bergmann-G 34-36 Wien Wien 1140",
    "addr:postcode":"34-36;1140",
    "iso:country":"AT",
    "sg:address":"Ernst-Bergmann-G 34-36",
    "sg:city":"Wien",
    "sg:orig_category":"Non-Classified Establishments",
    "sg:phone":"+43 4319 141507",
    "sg:postcode":"1140",
    "sg:province":"Wien",
    "wof:name":"Document Exchange Network GmbH",
    "wof:placetype":"venue"
},
  "geometry": {"coordinates":[16.2721672058,48.2016487122],"type":"Point"}
}