{
  "type": "Feature",
  "properties": {
    "addr:full":"Bahnhofstr 72-74 Saalfelden am Steinernen Meer Salzburg 5760",
    "addr:postcode":"72-74;5760",
    "addr:street":"Bahnhofstr;Salzburg",
    "iso:country":"AT",
    "sg:address":"Bahnhofstr 72-74",
    "sg:city":"Saalfelden am Steinernen Meer",
    "sg:orig_category":"Blumeneinzelhandel",
    "sg:phone":"+43 4365 82725360",
    "sg:postcode":"5760",
    "sg:province":"Salzburg",
    "sg:website":"blumen-steger.at",
    "wof:name":"Steger Christian",
    "wof:placetype":"venue"
},
  "geometry": {"coordinates":[12.8359413147,47.4265899658],"type":"Point"}
}