{
  "type": "Feature",
  "properties": {
    "addr:full":"Breitenfurter Str 118 Wien Wien 1230",
    "addr:housenumber":"118",
    "addr:postcode":"1230",
    "addr:street":"Str",
    "iso:country":"AT",
    "sg:address":"Breitenfurter Str 118",
    "sg:city":"Wien",
    "sg:orig_category":"Schwei\u00c3\u0178- U Schneidetechnik",
    "sg:phone":"+43 4318 047948",
    "sg:postcode":"1230",
    "sg:province":"Wien",
    "wof:name":"LS Orbital Schwei\u00dftechnik GmbH",
    "wof:placetype":"venue"
},
  "geometry": {"coordinates":[16.3072547913,48.1587257385],"type":"Point"}
}