{
  "type": "Feature",
  "properties": {
    "addr:full":"Thurnhofg 5 Horn Nieder\u00f6sterreich 3580",
    "addr:housenumber":"5",
    "addr:postcode":"3580",
    "addr:street":"Thurnhofg;Niederoesterreich",
    "iso:country":"AT",
    "sg:address":"Thurnhofg 5",
    "sg:city":"Horn",
    "sg:orig_category":"Transportunternehmen",
    "sg:phone":"+43 2982 2269",
    "sg:postcode":"3580",
    "sg:province":"Nieder\u00f6sterreich",
    "wof:name":"Langthaler Josef",
    "wof:placetype":"venue"
},
  "geometry": {"coordinates":[15.6574287415,48.6637763977],"type":"Point"}
}