{
  "type": "Feature",
  "properties": {
    "iso:country":"AT",
    "sg:address":"Reichshofstr. 7a",
    "sg:city":"Lustenau",
    "sg:classifiers":[
        {
            "category":"Wholesale",
            "subcategory":"Machinery & Supplies",
            "type":"Manufacturing & Wholesale Goods"
        }
    ],
    "sg:phone":"+43 4355 7783255",
    "sg:postcode":"6890",
    "sg:province":"Vorarlberg",
    "sg:tags":[
        "equipment",
        "-",
        "instrument",
        "measurement"
    ],
    "wof:name":"AFRISO EURO INDEX GES.MBH",
    "wof:placetype":"venue"
},
  "geometry": {"coordinates":[9.651802063,47.4248352051],"type":"Point"}
}