{
  "type": "Feature",
  "properties": {
    "addr:full":"Kaiserstr 80 Wien Wien 1070",
    "addr:housenumber":"80",
    "addr:postcode":"1070",
    "addr:street":"Kaiserstr",
    "iso:country":"AT",
    "sg:address":"Kaiserstr 80",
    "sg:city":"Wien",
    "sg:orig_category":"Transportunternehmen",
    "sg:phone":"+43 1 5245783",
    "sg:postcode":"1070",
    "sg:province":"Wien",
    "wof:name":"Cvetkovic Transport-GmbH",
    "wof:placetype":"venue"
},
  "geometry": {"coordinates":[16.3400630951,48.2052345276],"type":"Point"}
}