{
  "type": "Feature",
  "properties": {
    "addr:full":"Marxerg 10/16 Wien Wien 1030",
    "addr:housenumber":"10 / 16",
    "addr:postcode":"1030",
    "addr:street":"Marxerg",
    "iso:country":"AT",
    "sg:address":"Marxerg 10/16",
    "sg:city":"Wien",
    "sg:classifiers":[
        {
            "category":"Communications",
            "subcategory":"Film & Video Production",
            "type":"Services"
        }
    ],
    "sg:phone":"+43 4367 63229840",
    "sg:postcode":"1030",
    "sg:province":"Wien",
    "sg:tags":[
        "multimedia"
    ],
    "sg:website":"citymedia.at; streettv.at",
    "wof:name":"Citymedia Verkaufsf\u00f6rderungs- u Werbegestaltungssystemeges.m.b.H",
    "wof:placetype":"venue"
},
  "geometry": {"coordinates":[16.3876667023,48.2069320679],"type":"Point"}
}