{
  "type": "Feature",
  "properties": {
    "addr:full":"Wurlitzerg 93 Wien Wien 1170",
    "addr:housenumber":"93",
    "addr:postcode":"1170",
    "addr:street":"Wurlitzerg",
    "iso:country":"AT",
    "sg:address":"Wurlitzerg 93",
    "sg:city":"Wien",
    "sg:orig_category":"Immobilienmakler",
    "sg:phone":"+43 800 908909910",
    "sg:postcode":"1170",
    "sg:province":"Wien",
    "wof:name":"IMMOPERFECT KEG",
    "wof:placetype":"venue"
},
  "geometry": {"coordinates":[16.3201656342,48.2217254639],"type":"Point"}
}