{
  "type": "Feature",
  "properties": {
    "addr:full":"Mechitaristeng 1 Wien Wien 1070",
    "addr:housenumber":"1",
    "addr:postcode":"1070",
    "addr:street":"Mechitaristeng",
    "iso:country":"AT",
    "sg:address":"Mechitaristeng 1",
    "sg:city":"Wien",
    "sg:orig_category":"Unternehmensberatung",
    "sg:phone":"+43 699 19902000",
    "sg:postcode":"1070",
    "sg:province":"Wien",
    "wof:name":"Jirik Christian Ing Dipl-Kfm Dipl-Vw Dr",
    "wof:placetype":"venue"
},
  "geometry": {"coordinates":[16.3539829254,48.2056159973],"type":"Point"}
}