{
  "type": "Feature",
  "properties": {
    "iso:country":"AT",
    "sg:address":"Hohenbrunn 1",
    "sg:city":"St. Florian",
    "sg:orig_category":"Museen / Ausstellungen",
    "sg:phone":"+43 4372 2420083",
    "sg:postcode":"4490",
    "sg:province":"Ober\u00f6sterreich",
    "wof:name":"Jagdmuseum Schlo\u00df Hohenbrunn",
    "wof:placetype":"venue"
},
  "geometry": {"coordinates":[14.3479690552,48.2014808655],"type":"Point"}
}