{
  "type": "Feature",
  "properties": {
    "addr:full":"Franz-Wurm-G 4 Ebenthal in K\u00e4rnten K\u00e4rnten 9065",
    "addr:housenumber":"4",
    "addr:postcode":"9065",
    "addr:street":"Franz-Wurm-G;Kaernten",
    "iso:country":"AT",
    "sg:address":"Franz-Wurm-G 4",
    "sg:city":"Ebenthal in K\u00e4rnten",
    "sg:orig_category":"Metallbau",
    "sg:phone":"+43 4346 3740302",
    "sg:postcode":"9065",
    "sg:province":"K\u00e4rnten",
    "wof:name":"Lesjak J u R Metallbau OEG",
    "wof:placetype":"venue"
},
  "geometry": {"coordinates":[14.3621454239,46.6070404053],"type":"Point"}
}