{
  "type": "Feature",
  "properties": {
    "iso:country":"AT",
    "sg:address":"Schiffsl\u00e4nde 8",
    "sg:city":"Stadl-Paura",
    "sg:orig_category":"Textilreinigung",
    "sg:phone":"+43 7245 28289",
    "sg:postcode":"4651",
    "sg:province":"Ober\u00f6sterreich",
    "wof:name":"M\u00fcller A GesmbH",
    "wof:placetype":"venue"
},
  "geometry": {"coordinates":[13.8596134186,48.0821533203],"type":"Point"}
}