{
  "type": "Feature",
  "properties": {
    "iso:country":"AT",
    "sg:address":"10.-Oktober-Str 20/1",
    "sg:city":"Feldkirchen in K\u00e4rnten",
    "sg:orig_category":"Lebens- U Sozialberatung",
    "sg:phone":"+43 4342 767908",
    "sg:postcode":"9560",
    "sg:province":"K\u00e4rnten",
    "wof:name":"LSB-Netzwerk Jugend- u SozialbetreuungsgmbH",
    "wof:placetype":"venue"
},
  "geometry": {"coordinates":[14.0947132111,46.7240638733],"type":"Point"}
}