{
  "type": "Feature",
  "properties": {
    "iso:country":"AT",
    "sg:address":"Klosterg 14",
    "sg:city":"F\u00fcrstenfeld",
    "sg:orig_category":"Physiotherapie",
    "sg:phone":"+43 4333 8252300",
    "sg:postcode":"8280",
    "sg:province":"Steiermark",
    "wof:name":"APT Pfeilburg Physikalische Therapie GmbH",
    "wof:placetype":"venue"
},
  "geometry": {"coordinates":[9.1809597015,47.6450767517],"type":"Point"}
}