{
  "type": "Feature",
  "properties": {
    "addr:full":"Pirkdorf 11 Sankt Michael ob Bleiburg K\u00e4rnten 9143",
    "addr:housenumber":"11",
    "addr:postcode":"9143",
    "addr:street":"Pirkdorf",
    "iso:country":"AT",
    "sg:address":"Pirkdorf 11",
    "sg:city":"Sankt Michael ob Bleiburg",
    "sg:orig_category":"ChildrenS Mattresses",
    "sg:phone":"+43 4235 2541",
    "sg:postcode":"9143",
    "sg:province":"K\u00e4rnten",
    "sg:website":"elky.at",
    "wof:name":"Elky Unterk\u00e4rntner Matratzenfabrik",
    "wof:placetype":"venue"
},
  "geometry": {"coordinates":[14.7621669769,46.5607833862],"type":"Point"}
}