{
  "type": "Feature",
  "properties": {
    "addr:full":"Am Kehlerpark 5 Dornbirn Vorarlberg 6850",
    "addr:housenumber":"5",
    "addr:postcode":"6850",
    "addr:street":"Am Kehlerpark",
    "iso:country":"AT",
    "sg:address":"Am Kehlerpark 5",
    "sg:city":"Dornbirn",
    "sg:orig_category":"Raucherartikel",
    "sg:phone":"+43 5572 51564",
    "sg:postcode":"6850",
    "sg:province":"Vorarlberg",
    "wof:name":"House of smoke Gunz GmbH",
    "wof:placetype":"venue"
},
  "geometry": {"coordinates":[9.7522382736,47.4166564941],"type":"Point"}
}