{
  "type": "Feature",
  "properties": {
    "addr:full":"Marktstr 68 Rauris Salzburg 5661",
    "addr:housenumber":"68",
    "addr:postcode":"5661",
    "addr:street":"Marktstr;Salzburg",
    "iso:country":"AT",
    "sg:address":"Marktstr 68",
    "sg:city":"Rauris",
    "sg:orig_category":"Pensionen / Privatzimmer",
    "sg:phone":"+43 6544 62310",
    "sg:postcode":"5661",
    "sg:province":"Salzburg",
    "wof:name":"Pension Lohninger Rauris",
    "wof:placetype":"venue"
},
  "geometry": {"coordinates":[12.9940690994,47.2262687683],"type":"Point"}
}