{
  "type": "Feature",
  "properties": {
    "iso:country":"AT",
    "sg:address":"Widmanng 21",
    "sg:city":"Villach",
    "sg:orig_category":"Waren Aller Art",
    "sg:phone":"+43 4242 218668",
    "sg:postcode":"9500",
    "sg:province":"K\u00e4rnten",
    "wof:name":"Welt Laden",
    "wof:placetype":"venue"
},
  "geometry": {"coordinates":[13.8444252014,46.6142082214],"type":"Point"}
}