{
  "type": "Feature",
  "properties": {
    "iso:country":"AT",
    "sg:address":"Stammersdorfer Str 267",
    "sg:city":"Wien",
    "sg:orig_category":"Steinmetzbetriebe",
    "sg:phone":"+43 1 2923651",
    "sg:postcode":"1210",
    "sg:province":"Wien",
    "wof:name":"Melchor Walter GesmbH",
    "wof:placetype":"venue"
},
  "geometry": {"coordinates":[16.4396457672,48.2963562012],"type":"Point"}
}