{
  "type": "Feature",
  "properties": {
    "addr:full":"Martin-Kink-Strasse 11 Lustenau Vorarlberg 6890",
    "addr:housenumber":"11",
    "addr:postcode":"6890",
    "addr:street":"Martin-Kink-Strasse",
    "iso:country":"AT",
    "sg:address":"Martin-Kink-Strasse 11",
    "sg:city":"Lustenau",
    "sg:classifiers":[
        {
            "category":"Transit Center",
            "subcategory":"Freight",
            "type":"Transportation"
        }
    ],
    "sg:phone":"+43 5577 84323",
    "sg:postcode":"6890",
    "sg:province":"Vorarlberg",
    "sg:tags":[
        "forwarding",
        "agency"
    ],
    "wof:name":"Oberti Ges.m.b.H. & Co KG",
    "wof:placetype":"venue"
},
  "geometry": {"coordinates":[9.6710195541,47.4387702942],"type":"Point"}
}