{
  "type": "Feature",
  "properties": {
    "iso:country":"AT",
    "sg:address":"Gro\u00dfklein 55",
    "sg:city":"Gro\u00dfklein",
    "sg:classifiers":[
        {
            "category":"Manufacturing",
            "subcategory":"Wood Products",
            "type":"Manufacturing & Wholesale Goods"
        }
    ],
    "sg:phone":"+43 3456 2214",
    "sg:postcode":"8452",
    "sg:province":"Steiermark",
    "sg:tags":[
        "lumber"
    ],
    "wof:name":"Karl Haring",
    "wof:placetype":"venue"
},
  "geometry": {"coordinates":[-108.55094146730001,46.4105796814],"type":"Point"}
}