{
  "type": "Feature",
  "properties": {
    "iso:country":"AT",
    "sg:address":"Schlo\u00dfgasse 3",
    "sg:city":"Kobersdorf",
    "sg:classifiers":[
        {
            "category":"Education",
            "subcategory":"Dance Studio",
            "type":"Public Place"
        }
    ],
    "sg:phone":"+43 2618 8237",
    "sg:postcode":"7332",
    "sg:province":"Burgenland",
    "sg:tags":[
        "absorbing",
        "spring"
    ],
    "wof:name":"Eduard Scheiber",
    "wof:placetype":"venue"
},
  "geometry": {"coordinates":[16.3912658691,47.596572876],"type":"Point"}
}