{
  "type": "Feature",
  "properties": {
    "iso:country":"AT",
    "sg:address":"Johann Galler-Str 6",
    "sg:city":"Wolkersdorf im Weinviertel",
    "sg:orig_category":"Feuerwehren",
    "sg:phone":"+43 2245 2222",
    "sg:postcode":"2120",
    "sg:province":"Nieder\u00f6sterreich",
    "wof:name":"Freiwillige Feuerwehr Wolkersdorf",
    "wof:placetype":"venue"
},
  "geometry": {"coordinates":[16.5109920502,48.3760223389],"type":"Point"}
}