{
  "type": "Feature",
  "properties": {
    "addr:full":"Alte Poststr. 122  Graz Steiermark 8020",
    "addr:housenumber":"122",
    "addr:postcode":"8020",
    "iso:country":"AT",
    "sg:address":"Alte Poststr. 122 ",
    "sg:city":"Graz",
    "sg:classifiers":[
        {
            "category":"Autos & Motor Vehicles",
            "subcategory":"Automobile Sales",
            "type":"Retail Goods"
        }
    ],
    "sg:phone":"+43 4331 65000",
    "sg:postcode":"8020",
    "sg:province":"Steiermark",
    "sg:tags":[
        "motor-cars"
    ],
    "wof:name":"REISINGER & SOHN AUTOHANDELS- U. INDUSTRIEGES.MBH",
    "wof:placetype":"venue"
},
  "geometry": {"coordinates":[15.4081640244,47.0724983215],"type":"Point"}
}