{
  "type": "Feature",
  "properties": {
    "addr:full":"Unterroith 33 Steinbach am Attersee Ober\u00f6sterreich 4853",
    "addr:housenumber":"33",
    "addr:postcode":"4853",
    "addr:street":"Unterroith",
    "iso:country":"AT",
    "sg:address":"Unterroith 33",
    "sg:city":"Steinbach am Attersee",
    "sg:orig_category":"Appartements / Ferienwohnungen",
    "sg:phone":"+43 4376 63361",
    "sg:postcode":"4853",
    "sg:province":"Ober\u00f6sterreich",
    "wof:name":"Schiemer Elsa & Ferdinand",
    "wof:placetype":"venue"
},
  "geometry": {"coordinates":[13.5476713181,47.840423584],"type":"Point"}
}