{
  "type": "Feature",
  "properties": {
    "addr:full":"Damb\u00f6ckg 4 Wien Wien 1060",
    "addr:housenumber":"4",
    "addr:postcode":"1060",
    "addr:street":"Damboeckg",
    "iso:country":"AT",
    "sg:address":"Damb\u00f6ckg 4",
    "sg:city":"Wien",
    "sg:orig_category":"Volkshochschulen",
    "sg:phone":"+43 1 5865577",
    "sg:postcode":"1060",
    "sg:province":"Wien",
    "wof:name":"Volkshochschule Wien-West",
    "wof:placetype":"venue"
},
  "geometry": {"coordinates":[16.3504657745,48.1947135925],"type":"Point"}
}