{
  "type": "Feature",
  "properties": {
    "addr:full":"Schischulstr 379 Saalbach Salzburg 5753",
    "addr:housenumber":"379",
    "addr:postcode":"5753",
    "addr:street":"Saalbach Salzburg",
    "iso:country":"AT",
    "sg:address":"Schischulstr 379",
    "sg:city":"Saalbach",
    "sg:orig_category":"Pensionen / Privatzimmer",
    "sg:phone":"+43 6541 6509",
    "sg:postcode":"5753",
    "sg:province":"Salzburg",
    "wof:name":"Pension Kohlbr\u00fcndl",
    "wof:placetype":"venue"
},
  "geometry": {"coordinates":[12.6377477646,47.389957428],"type":"Point"}
}