{
  "type": "Feature",
  "properties": {
    "addr:full":"\u00d6lbergstr 20 Niederru\u00dfbach Nieder\u00f6sterreich 3702",
    "addr:housenumber":"20",
    "addr:postcode":"3702",
    "addr:street":"Oelbergstr",
    "iso:country":"AT",
    "sg:address":"\u00d6lbergstr 20",
    "sg:city":"Niederru\u00dfbach",
    "sg:orig_category":"Non-Classified Establishments",
    "sg:phone":"+43 2955 70404",
    "sg:postcode":"3702",
    "sg:province":"Nieder\u00f6sterreich",
    "wof:name":"Pfarramt",
    "wof:placetype":"venue"
},
  "geometry": {"coordinates":[-83.3486022949,43.8284263611],"type":"Point"}
}