{
  "type": "Feature",
  "properties": {
    "addr:full":"Am Markt 23 Orth an der Donau Nieder\u00f6sterreich 2304",
    "addr:housenumber":"23",
    "addr:postcode":"2304",
    "addr:street":"Am Markt",
    "iso:country":"AT",
    "sg:address":"Am Markt 23",
    "sg:city":"Orth an der Donau",
    "sg:orig_category":"Tischlereien",
    "sg:phone":"+43 2212 2663",
    "sg:postcode":"2304",
    "sg:province":"Nieder\u00f6sterreich",
    "wof:name":"Stiller Franz",
    "wof:placetype":"venue"
},
  "geometry": {"coordinates":[16.703371048,48.146648407],"type":"Point"}
}