{
  "type": "Feature",
  "properties": {
    "iso:country":"AT",
    "sg:address":"Landstra\u00dfer Hauptstr 105",
    "sg:city":"Wien",
    "sg:orig_category":"Tabaktrafiken",
    "sg:phone":"+43 1 7122236",
    "sg:postcode":"1030",
    "sg:province":"Wien",
    "wof:name":"Hofmann Reinhard",
    "wof:placetype":"venue"
},
  "geometry": {"coordinates":[16.3954734802,48.1976890564],"type":"Point"}
}