{
  "type": "Feature",
  "properties": {
    "iso:country":"AT",
    "sg:address":"Georgenberg 218",
    "sg:city":"Kuchl",
    "sg:orig_category":"Raumausstattung",
    "sg:phone":"+43 6244 5598",
    "sg:postcode":"5431",
    "sg:province":"Salzburg",
    "wof:name":"Wohnraumausstattung - Christian Reindl",
    "wof:placetype":"venue"
},
  "geometry": {"coordinates":[13.1509180069,47.6254463196],"type":"Point"}
}