{
  "type": "Feature",
  "properties": {
    "addr:full":"Nr 44 M\u00f6llbr\u00fccke K\u00e4rnten 9813",
    "addr:postcode":"9813",
    "addr:street":"Nr 44 Moellbruecke Kaernten",
    "iso:country":"AT",
    "sg:address":"Nr 44",
    "sg:city":"M\u00f6llbr\u00fccke",
    "sg:orig_category":"Massagen",
    "sg:phone":"+43 4347 693873",
    "sg:postcode":"9813",
    "sg:province":"K\u00e4rnten",
    "wof:name":"Fachbetrieb f Massage u Lympfdrainage",
    "wof:placetype":"venue"
},
  "geometry": {"coordinates":[13.3697757721,46.8363571167],"type":"Point"}
}