{
  "type": "Feature",
  "properties": {
    "addr:full":"Nelkeng 31 Gramatneusiedl Nieder\u00f6sterreich 2440",
    "addr:housenumber":"31",
    "addr:postcode":"2440",
    "addr:street":"Nelkeng",
    "iso:country":"AT",
    "sg:address":"Nelkeng 31",
    "sg:city":"Gramatneusiedl",
    "sg:orig_category":"Textilwaren / Einzelhandel",
    "sg:phone":"+43 2234 73559",
    "sg:postcode":"2440",
    "sg:province":"Nieder\u00f6sterreich",
    "wof:name":"Neuberger Ursula",
    "wof:placetype":"venue"
},
  "geometry": {"coordinates":[16.4910297394,48.0298614502],"type":"Point"}
}