{
  "type": "Feature",
  "properties": {
    "addr:full":"Unterdorf 14 Kematen in Tirol Tirol 6175",
    "addr:housenumber":"14",
    "addr:postcode":"6175",
    "addr:street":"Unterdorf;Tirol",
    "iso:country":"AT",
    "sg:address":"Unterdorf 14",
    "sg:city":"Kematen in Tirol",
    "sg:orig_category":"Non-Classified Establishments",
    "sg:phone":"+43 5232 81116",
    "sg:postcode":"6175",
    "sg:province":"Tirol",
    "wof:name":"Pfarramt",
    "wof:placetype":"venue"
},
  "geometry": {"coordinates":[11.2113018036,47.2578582764],"type":"Point"}
}