{
  "type": "Feature",
  "properties": {
    "addr:full":"Oberer Markt 2 Weyer Ober\u00f6sterreich 3335",
    "addr:housenumber":"2",
    "addr:postcode":"3335",
    "addr:street":"Oberer Markt",
    "iso:country":"AT",
    "sg:address":"Oberer Markt 2",
    "sg:city":"Weyer",
    "sg:classifiers":[
        {
            "category":"Travel",
            "subcategory":"Hotels & Motels",
            "type":"Entertainment"
        }
    ],
    "sg:phone":"+43 7355 20068",
    "sg:postcode":"3335",
    "sg:province":"Ober\u00f6sterreich",
    "wof:name":"Hotel-Gasthof Post",
    "wof:placetype":"venue"
},
  "geometry": {"coordinates":[14.6633272171,47.8568153381],"type":"Point"}
}