{
  "type": "Feature",
  "properties": {
    "addr:full":"Diex K\u00e4rnten 9103",
    "addr:postcode":"9103",
    "iso:country":"AT",
    "sg:city":"Diex",
    "sg:orig_category":"Non-Classified Establishments",
    "sg:phone":"+43 4231 8132",
    "sg:postcode":"9103",
    "sg:province":"K\u00e4rnten",
    "wof:name":"Pfarramt",
    "wof:placetype":"venue"
},
  "geometry": {"coordinates":[14.6170005798,46.7444877625],"type":"Point"}
}