{
  "type": "Feature",
  "properties": {
    "iso:country":"AT",
    "sg:address":"Vorstadt 18",
    "sg:city":"Feldkirch",
    "sg:orig_category":"Architekten",
    "sg:phone":"+43 5522 796290",
    "sg:postcode":"6800",
    "sg:province":"Vorarlberg",
    "wof:name":"Schw\u00e4rzler Josef Arch Dipl-Ing",
    "wof:placetype":"venue"
},
  "geometry": {"coordinates":[9.5945444107,47.2367362976],"type":"Point"}
}