{
  "type": "Feature",
  "properties": {
    "iso:country":"AT",
    "sg:address":"Teinfaltstr 8",
    "sg:city":"Wien",
    "sg:orig_category":"Geschenkartikel",
    "sg:phone":"+43 1 5860050",
    "sg:postcode":"1010",
    "sg:province":"Wien",
    "wof:name":"Russ Berri \u00f6sterreich GmbH",
    "wof:placetype":"venue"
},
  "geometry": {"coordinates":[16.3624324799,48.2114868164],"type":"Point"}
}