{
  "type": "Feature",
  "properties": {
    "addr:full":"Lerchenf Hauptpl 18 Krems an der Donau Nieder\u00f6sterreich 3500",
    "addr:housenumber":"18",
    "addr:postcode":"3500",
    "iso:country":"AT",
    "sg:address":"Lerchenf Hauptpl 18",
    "sg:city":"Krems an der Donau",
    "sg:orig_category":"Textilreinigung",
    "sg:phone":"+43 2732 846720",
    "sg:postcode":"3500",
    "sg:province":"Nieder\u00f6sterreich",
    "wof:name":"Regina Textilreinigungs GesmbH",
    "wof:placetype":"venue"
},
  "geometry": {"coordinates":[15.5965108871,48.4088058472],"type":"Point"}
}