{
  "type": "Feature",
  "properties": {
    "addr:full":"Nr 1 Straning Nieder\u00f6sterreich 3722",
    "addr:postcode":"3722",
    "addr:street":"Nr;Straning Niederoesterreich",
    "iso:country":"AT",
    "sg:address":"Nr 1",
    "sg:city":"Straning",
    "sg:orig_category":"Non-Classified Establishments",
    "sg:phone":"+43 2984 7266",
    "sg:postcode":"3722",
    "sg:province":"Nieder\u00f6sterreich",
    "wof:name":"Pfarramt",
    "wof:placetype":"venue"
},
  "geometry": {"coordinates":[15.863940239,48.6107978821],"type":"Point"}
}