{
  "type": "Feature",
  "properties": {
    "addr:full":"Breitenfurter Str 357 Wien Wien 1230",
    "addr:housenumber":"357",
    "addr:postcode":"1230",
    "addr:street":"Str",
    "iso:country":"AT",
    "sg:address":"Breitenfurter Str 357",
    "sg:city":"Wien",
    "sg:orig_category":"Juweliere, Gold- U Silberschmiede",
    "sg:phone":"+43 1 8693369",
    "sg:postcode":"1230",
    "sg:province":"Wien",
    "wof:name":"Moser Josef",
    "wof:placetype":"venue"
},
  "geometry": {"coordinates":[16.2902584076,48.1394195557],"type":"Point"}
}