{
  "type": "Feature",
  "properties": {
    "addr:full":"Gudrunstr 137 Wien Wien 1100",
    "addr:housenumber":"137",
    "addr:postcode":"1100",
    "iso:country":"AT",
    "sg:address":"Gudrunstr 137",
    "sg:city":"Wien",
    "sg:orig_category":"Lebensmittel / Einzelhandel",
    "sg:phone":"+43 4319 612469",
    "sg:postcode":"1100",
    "sg:province":"Wien",
    "wof:name":"Emma Otto GesmbH",
    "wof:placetype":"venue"
},
  "geometry": {"coordinates":[16.3782291412,48.1777992249],"type":"Point"}
}