{
  "type": "Feature",
  "properties": {
    "addr:full":"Autaler Str 25 St. Peter Steiermark 8042",
    "addr:housenumber":"25",
    "addr:postcode":"8042",
    "addr:street":"Str",
    "iso:country":"AT",
    "sg:address":"Autaler Str 25",
    "sg:city":"St. Peter",
    "sg:orig_category":"Bauchtanz",
    "sg:phone":"+43 316 407729",
    "sg:postcode":"8042",
    "sg:province":"Steiermark",
    "sg:website":"www.bauchtanzen.at",
    "wof:name":"Tzimos Nadja",
    "wof:placetype":"venue"
},
  "geometry": {"coordinates":[15.4964923859,47.0369186401],"type":"Point"}
}