{
  "type": "Feature",
  "properties": {
    "addr:full":"Linzer Strasse 2 Windischgarsten Ober\u00f6sterreich 4580",
    "addr:housenumber":"2",
    "addr:postcode":"4580",
    "addr:street":"Linzer Strasse",
    "iso:country":"AT",
    "sg:address":"Linzer Strasse 2",
    "sg:city":"Windischgarsten",
    "sg:classifiers":[
        {
            "category":"Personal",
            "subcategory":"Tanning Parlor",
            "type":"Services"
        }
    ],
    "sg:phone":"+43 7562 5253",
    "sg:postcode":"4580",
    "sg:province":"Ober\u00f6sterreich",
    "sg:tags":[
        "hide"
    ],
    "wof:name":"Wolfgang Max Purgleitner",
    "wof:placetype":"venue"
},
  "geometry": {"coordinates":[14.3216514587,47.7224159241],"type":"Point"}
}