{
  "type": "Feature",
  "properties": {
    "addr:full":"Karl-Zillner-Pl 3 B\u00fcrmoos Salzburg 5111",
    "addr:housenumber":"3",
    "addr:postcode":"5111",
    "addr:street":"Karl-Zillner-Pl;Salzburg",
    "iso:country":"AT",
    "sg:address":"Karl-Zillner-Pl 3",
    "sg:city":"B\u00fcrmoos",
    "sg:orig_category":"Handelsagenturen",
    "sg:phone":"+43 6274 7334",
    "sg:postcode":"5111",
    "sg:province":"Salzburg",
    "wof:name":"Zell Anton",
    "wof:placetype":"venue"
},
  "geometry": {"coordinates":[12.9181785583,47.9851989746],"type":"Point"}
}