{
  "type": "Feature",
  "properties": {
    "iso:country":"AT",
    "sg:address":"Straniakstrasse 34",
    "sg:city":"Salzburg",
    "sg:classifiers":[
        {
            "category":"Manufacturing",
            "subcategory":"Signs",
            "type":"Manufacturing & Wholesale Goods"
        }
    ],
    "sg:phone":"+43 662 451110",
    "sg:postcode":"5020",
    "sg:province":"Salzburg",
    "sg:tags":[
        "engraved"
    ],
    "sg:website":"stubhann.at",
    "wof:name":"Gebr\u00fcder Stubhann KG",
    "wof:placetype":"venue"
},
  "geometry": {"coordinates":[13.0606889725,47.8422966003],"type":"Point"}
}