{
  "type": "Feature",
  "properties": {
    "iso:country":"AT",
    "sg:address":"Nr 21",
    "sg:city":"St. Martin",
    "sg:orig_category":"Appartements / Ferienwohnungen",
    "sg:phone":"+43 4328 572809",
    "sg:postcode":"3971",
    "sg:province":"Nieder\u00f6sterreich",
    "wof:name":"Steinbrunner Herta u Erwin",
    "wof:placetype":"venue"
},
  "geometry": {"coordinates":[14.8395824432,48.662979126],"type":"Point"}
}