{
  "type": "Feature",
  "properties": {
    "addr:full":"Johann-Wolf-Str 13 Salzburg Salzburg 5020",
    "addr:housenumber":"13",
    "addr:postcode":"5020",
    "addr:street":"Johann-Wolf-Str;Salzburg",
    "iso:country":"AT",
    "sg:address":"Johann-Wolf-Str 13",
    "sg:city":"Salzburg",
    "sg:orig_category":"Psychotherapie",
    "sg:phone":"+43 4369 918636871",
    "sg:postcode":"5020",
    "sg:province":"Salzburg",
    "wof:name":"Hofer-Moser Albin Dr",
    "wof:placetype":"venue"
},
  "geometry": {"coordinates":[13.0346794128,47.7967071533],"type":"Point"}
}