{
  "type": "Feature",
  "properties": {
    "addr:full":"Timmersdorfer G 1 Leoben Steiermark 8700",
    "addr:housenumber":"1",
    "addr:postcode":"8700",
    "addr:street":"Timmersdorfer G",
    "iso:country":"AT",
    "sg:address":"Timmersdorfer G 1",
    "sg:city":"Leoben",
    "sg:orig_category":"Schuhreparatur",
    "sg:phone":"+43 4338 4244166",
    "sg:postcode":"8700",
    "sg:province":"Steiermark",
    "wof:name":"Meixner G\u00fcnter",
    "wof:placetype":"venue"
},
  "geometry": {"coordinates":[15.0936412811,47.3809776306],"type":"Point"}
}