{
  "type": "Feature",
  "properties": {
    "addr:full":"Johannespl 1 Leitzersdorf Nieder\u00f6sterreich 2003",
    "addr:housenumber":"1",
    "addr:postcode":"2003",
    "addr:street":"Johannespl;Niederoesterreich",
    "iso:country":"AT",
    "sg:address":"Johannespl 1",
    "sg:city":"Leitzersdorf",
    "sg:orig_category":"Banken U Sparkassen",
    "sg:phone":"+43 2266 63968",
    "sg:postcode":"2003",
    "sg:province":"Nieder\u00f6sterreich",
    "wof:name":"Raiffeisenbank Stockerau regGenmbH",
    "wof:placetype":"venue"
},
  "geometry": {"coordinates":[16.247127533,48.421295166],"type":"Point"}
}