{
  "type": "Feature",
  "properties": {
    "addr:full":"Karl-Loy-Strasse 8 Wels Ober\u00f6sterreich 4600",
    "addr:housenumber":"8",
    "addr:postcode":"4600",
    "addr:street":"Karl-Loy-Strasse;Oberoesterreich",
    "iso:country":"AT",
    "sg:address":"Karl-Loy-Strasse 8",
    "sg:city":"Wels",
    "sg:classifiers":[
        {
            "category":"Home & Garden",
            "subcategory":"Household Appliances",
            "type":"Retail Goods"
        }
    ],
    "sg:phone":"+43 7242 451100",
    "sg:postcode":"4600",
    "sg:province":"Ober\u00f6sterreich",
    "sg:tags":[
        "electric"
    ],
    "wof:name":"Peter KARL GmbH & Co KG",
    "wof:placetype":"venue"
},
  "geometry": {"coordinates":[14.0216293335,48.1598739624],"type":"Point"}
}