{
  "type": "Feature",
  "properties": {
    "addr:full":"Landshaager Str 9 St. Martin im M\u00fchlkreis Ober\u00f6sterreich 4113",
    "addr:housenumber":"9",
    "addr:postcode":"4113",
    "addr:street":"Str;Im Muehlkreis Oberoesterreich",
    "iso:country":"AT",
    "sg:address":"Landshaager Str 9",
    "sg:city":"St. Martin im M\u00fchlkreis",
    "sg:orig_category":"Polizei U Gendarmerie",
    "sg:phone":"+43 4359 1334259",
    "sg:postcode":"4113",
    "sg:province":"Ober\u00f6sterreich",
    "wof:name":"Gendarmerie",
    "wof:placetype":"venue"
},
  "geometry": {"coordinates":[14.040266037,48.4130210876],"type":"Point"}
}