{
  "type": "Feature",
  "properties": {
    "addr:full":"Nr 29 Rennweg K\u00e4rnten 9863",
    "addr:postcode":"9863",
    "addr:street":"Nr;Rennweg Kaernten",
    "iso:country":"AT",
    "sg:address":"Nr 29",
    "sg:city":"Rennweg",
    "sg:orig_category":"Non-Classified Establishments",
    "sg:phone":"+43 5 91332234",
    "sg:postcode":"9863",
    "sg:province":"K\u00e4rnten",
    "wof:name":"Gendarmerieposten Rennweg",
    "wof:placetype":"venue"
},
  "geometry": {"coordinates":[13.6127004623,47.0169067383],"type":"Point"}
}