{
  "type": "Feature",
  "properties": {
    "addr:full":"Maria Theresien-Str 5/48 Wien Wien 1090",
    "addr:housenumber":"5 / 48",
    "addr:postcode":"1090",
    "iso:country":"AT",
    "sg:address":"Maria Theresien-Str 5/48",
    "sg:city":"Wien",
    "sg:orig_category":"Werbegrafik- U Grafik-Design",
    "sg:phone":"+43 1 7293440",
    "sg:postcode":"1090",
    "sg:province":"Wien",
    "wof:name":"MindConnect Digital Media Creation GmbH",
    "wof:placetype":"venue"
},
  "geometry": {"coordinates":[16.3626747131,48.2151031494],"type":"Point"}
}