{
  "type": "Feature",
  "properties": {
    "addr:full":"Zeughauspl 1 Hollabrunn Nieder\u00f6sterreich 2020",
    "addr:housenumber":"1",
    "addr:postcode":"2020",
    "addr:street":"Zeughauspl",
    "iso:country":"AT",
    "sg:address":"Zeughauspl 1",
    "sg:city":"Hollabrunn",
    "sg:orig_category":"Banken U Sparkassen",
    "sg:phone":"+43 2951 2250",
    "sg:postcode":"2020",
    "sg:province":"Nieder\u00f6sterreich",
    "wof:name":"Raiffeisenbank Hollabrunn regGenmbH",
    "wof:placetype":"venue"
},
  "geometry": {"coordinates":[16.0783004761,48.5624580383],"type":"Point"}
}