{
  "type": "Feature",
  "properties": {
    "iso:country":"AT",
    "sg:address":"Umbergstr 72",
    "sg:city":"Gaming",
    "sg:orig_category":"Friseure U Frisiersalons",
    "sg:phone":"+43 4366 41238523",
    "sg:postcode":"3292",
    "sg:province":"Nieder\u00f6sterreich",
    "wof:name":"Hofegger Helga - Mobilfriseur",
    "wof:placetype":"venue"
},
  "geometry": {"coordinates":[15.0910997391,47.9201889038],"type":"Point"}
}