{
  "type": "Feature",
  "properties": {
    "iso:country":"AT",
    "sg:address":"Pleyerg 29",
    "sg:city":"Wiener Neustadt",
    "sg:orig_category":"Baumpflege, -Schutz U -Chirurgie",
    "sg:phone":"+43 4326 22744970",
    "sg:postcode":"2700",
    "sg:province":"Nieder\u00f6sterreich",
    "sg:website":"landschaft.at",
    "wof:name":"Gr\u00fcn + Landschaft Ing Peter Zimmermann",
    "wof:placetype":"venue"
},
  "geometry": {"coordinates":[16.2310886383,47.8095664978],"type":"Point"}
}