{
  "type": "Feature",
  "properties": {
    "addr:full":"Stadtgraben 11 Krems an der Donau Nieder\u00f6sterreich 3500",
    "addr:housenumber":"11",
    "addr:postcode":"3500",
    "addr:street":"Stadtgraben",
    "iso:country":"AT",
    "sg:address":"Stadtgraben 11",
    "sg:city":"Krems an der Donau",
    "sg:classifiers":[
        {
            "category":"Farming",
            "subcategory":"Berry Farm",
            "type":"Manufacturing & Wholesale Goods"
        }
    ],
    "sg:phone":"+43 2732 801441",
    "sg:postcode":"3500",
    "sg:province":"Nieder\u00f6sterreich",
    "sg:tags":[
        "austrian",
        "wine"
    ],
    "sg:website":"weingutstadtkrems.at",
    "wof:name":"Weingut Stadt Krems",
    "wof:placetype":"venue"
},
  "geometry": {"coordinates":[15.5963602066,48.4121246338],"type":"Point"}
}