{
  "type": "Feature",
  "properties": {
    "addr:full":"Paracelsusstr 6 Salzburg Salzburg 5020",
    "addr:housenumber":"6",
    "addr:postcode":"5020",
    "addr:street":"Paracelsusstr;Salzburg",
    "iso:country":"AT",
    "sg:address":"Paracelsusstr 6",
    "sg:city":"Salzburg",
    "sg:orig_category":"Medizintechnik",
    "sg:phone":"+43 662 8776520",
    "sg:postcode":"5020",
    "sg:province":"Salzburg",
    "wof:name":"Plasmacontrol GmbH",
    "wof:placetype":"venue"
},
  "geometry": {"coordinates":[13.0473690033,47.8079299927],"type":"Point"}
}