{
  "type": "Feature",
  "properties": {
    "addr:full":"Hauptpl 12 Sitzendorf an der Schmida Nieder\u00f6sterreich 3714",
    "addr:housenumber":"12",
    "addr:postcode":"3714",
    "addr:street":"Hauptpl",
    "iso:country":"AT",
    "sg:address":"Hauptpl 12",
    "sg:city":"Sitzendorf an der Schmida",
    "sg:orig_category":"Weine / Einzelhandel",
    "sg:phone":"+43 2959 2005",
    "sg:postcode":"3714",
    "sg:province":"Nieder\u00f6sterreich",
    "wof:name":"Autherith Johannes",
    "wof:placetype":"venue"
},
  "geometry": {"coordinates":[15.9419412613,48.5976486206],"type":"Point"}
}