{
  "type": "Feature",
  "properties": {
    "iso:country":"AT",
    "sg:address":"Landesgerichtsstr 10",
    "sg:city":"Wien",
    "sg:orig_category":"Friseure U Frisiersalons",
    "sg:phone":"+43 1 4020734",
    "sg:postcode":"1010",
    "sg:province":"Wien",
    "wof:name":"Hair Galery Exclusive Vienna",
    "wof:placetype":"venue"
},
  "geometry": {"coordinates":[16.3559856415,48.2119941711],"type":"Point"}
}