{
  "type": "Feature",
  "properties": {
    "addr:full":"Pramet 18 Pramet Ober\u00f6sterreich 4925",
    "addr:housenumber":"18",
    "addr:postcode":"4925",
    "addr:street":"Pramet",
    "iso:country":"AT",
    "sg:address":"Pramet 18",
    "sg:city":"Pramet",
    "sg:orig_category":"ChildrenS Furniture",
    "sg:phone":"+43 7754 8438",
    "sg:postcode":"4925",
    "sg:province":"Ober\u00f6sterreich",
    "sg:website":"wohnteam-plus.at",
    "wof:name":"Kurt Feitzinger",
    "wof:placetype":"venue"
},
  "geometry": {"coordinates":[13.4894151688,48.1432876587],"type":"Point"}
}