{
  "type": "Feature",
  "properties": {
    "addr:full":"B\u00fcrgerg 4 Feldbach Steiermark 8330",
    "addr:housenumber":"4",
    "addr:postcode":"8330",
    "addr:street":"Buergerg",
    "iso:country":"AT",
    "sg:address":"B\u00fcrgerg 4",
    "sg:city":"Feldbach",
    "sg:classifiers":[
        {
            "category":"Restaurant",
            "type":"Food & Drink"
        }
    ],
    "sg:phone":"+43 3152 7656",
    "sg:postcode":"8330",
    "sg:province":"Steiermark",
    "sg:tags":[
        "pizzeria"
    ],
    "wof:name":"Pizza Botan",
    "wof:placetype":"venue"
},
  "geometry": {"coordinates":[15.8557338715,46.9628982544],"type":"Point"}
}