{
  "type": "Feature",
  "properties": {
    "iso:country":"AT",
    "sg:address":"Hauptpl 11",
    "sg:city":"Oberwart",
    "sg:orig_category":"Blumeneinzelhandel",
    "sg:phone":"+43 3352 324463",
    "sg:postcode":"7400",
    "sg:province":"Burgenland",
    "wof:name":"Graf Thomas",
    "wof:placetype":"venue"
},
  "geometry": {"coordinates":[16.2139377594,47.2873764038],"type":"Point"}
}