{
  "type": "Feature",
  "properties": {
    "addr:full":"Veltlinerweg 48 Schruns Vorarlberg 6780",
    "addr:housenumber":"48",
    "addr:postcode":"6780",
    "addr:street":"Veltlinerweg",
    "iso:country":"AT",
    "sg:address":"Veltlinerweg 48",
    "sg:city":"Schruns",
    "sg:orig_category":"Appartements / Ferienwohnungen",
    "sg:phone":"+43 4355 5672678",
    "sg:postcode":"6780",
    "sg:province":"Vorarlberg",
    "wof:name":"Landhaus Soldanella",
    "wof:placetype":"venue"
},
  "geometry": {"coordinates":[9.9222345352,47.0760040283],"type":"Point"}
}