{
  "type": "Feature",
  "properties": {
    "addr:full":"Hauptpl 36 Neusiedl am See Burgenland 7100",
    "addr:housenumber":"36",
    "addr:postcode":"7100",
    "addr:street":"Hauptpl",
    "iso:country":"AT",
    "sg:address":"Hauptpl 36",
    "sg:city":"Neusiedl am See",
    "sg:orig_category":"Politische Parteien",
    "sg:phone":"+43 2167 2834",
    "sg:postcode":"7100",
    "sg:province":"Burgenland",
    "wof:name":"\u00f6sterreichische Volkspartei (\u00f6VP)",
    "wof:placetype":"venue"
},
  "geometry": {"coordinates":[16.8411903381,47.9492301941],"type":"Point"}
}