{
  "type": "Feature",
  "properties": {
    "addr:full":"Gewerbezeile 7 Villach K\u00e4rnten 9500",
    "addr:housenumber":"7",
    "addr:postcode":"9500",
    "addr:street":"Gewerbezeile;Kaernten",
    "iso:country":"AT",
    "sg:address":"Gewerbezeile 7",
    "sg:city":"Villach",
    "sg:orig_category":"Bekleidung / Einzelhandel",
    "sg:phone":"+43 4242 319855",
    "sg:postcode":"9500",
    "sg:province":"K\u00e4rnten",
    "wof:name":"adessa Moden GmbH",
    "wof:placetype":"venue"
},
  "geometry": {"coordinates":[13.8677940369,46.6053581238],"type":"Point"}
}