{
  "type": "Feature",
  "properties": {
    "addr:full":"Nr 92 Aigen im Ennstal Steiermark 8943",
    "addr:postcode":"8943",
    "addr:street":"Nr 92",
    "iso:country":"AT",
    "sg:address":"Nr 92",
    "sg:city":"Aigen im Ennstal",
    "sg:orig_category":"Autohandel",
    "sg:phone":"+43 3682 24737",
    "sg:postcode":"8943",
    "sg:province":"Steiermark",
    "wof:name":"Landmarkt KG Autohaus Aigen",
    "wof:placetype":"venue"
},
  "geometry": {"coordinates":[14.1433391571,47.5205230713],"type":"Point"}
}