{
  "type": "Feature",
  "properties": {
    "addr:full":"Michael-Jank-G 2a Ottenschlag Nieder\u00f6sterreich 3631",
    "addr:housenumber":"2a",
    "addr:postcode":"3631",
    "addr:street":"Michael-Jank-G",
    "iso:country":"AT",
    "sg:address":"Michael-Jank-G 2a",
    "sg:city":"Ottenschlag",
    "sg:classifiers":[
        {
            "category":"Personal",
            "subcategory":"Sauna",
            "type":"Services"
        }
    ],
    "sg:phone":"+43 4328 727495",
    "sg:postcode":"3631",
    "sg:province":"Nieder\u00f6sterreich",
    "sg:tags":[
        "u",
        "dampfbad"
    ],
    "wof:name":"Sauna u Freizeitzentrum",
    "wof:placetype":"venue"
},
  "geometry": {"coordinates":[15.2211732864,48.422996521],"type":"Point"}
}