{
  "type": "Feature",
  "properties": {
    "iso:country":"AT",
    "sg:address":"Waagg 20",
    "sg:city":"Freistadt",
    "sg:orig_category":"Installationsunternehmen",
    "sg:phone":"+43 7942 72318",
    "sg:postcode":"4240",
    "sg:province":"Ober\u00f6sterreich",
    "wof:name":"Dolsky Gottfried",
    "wof:placetype":"venue"
},
  "geometry": {"coordinates":[14.5043859482,48.5123634338],"type":"Point"}
}