{
  "type": "Feature",
  "properties": {
    "iso:country":"AT",
    "sg:address":"Hauptplatz 16",
    "sg:city":"Haid",
    "sg:classifiers":[
        {
            "category":"Building & Trades",
            "subcategory":"Locksmith",
            "type":"Services"
        }
    ],
    "sg:phone":"+43 7229 88393",
    "sg:postcode":"4053",
    "sg:province":"Ober\u00f6sterreich",
    "wof:name":"Kessler",
    "wof:placetype":"venue"
},
  "geometry": {"coordinates":[14.2510557175,48.2039833069],"type":"Point"}
}