{
  "type": "Feature",
  "properties": {
    "addr:full":"Egeten 7 Dornbirn Vorarlberg 6850",
    "addr:housenumber":"7",
    "addr:postcode":"6850",
    "addr:street":"Egeten",
    "iso:country":"AT",
    "sg:address":"Egeten 7",
    "sg:city":"Dornbirn",
    "sg:orig_category":"Sonnenschutzanlagen",
    "sg:phone":"+43 5572 22231",
    "sg:postcode":"6850",
    "sg:province":"Vorarlberg",
    "wof:name":"Giesinger & Mayerhofer GmbH & Co KG",
    "wof:placetype":"venue"
},
  "geometry": {"coordinates":[9.7321901321,47.4080429077],"type":"Point"}
}