{
  "type": "Feature",
  "properties": {
    "addr:full":"Ruprechtshofen 5 Naarn im Machlande Ober\u00f6sterreich 4331",
    "addr:housenumber":"5",
    "addr:postcode":"4331",
    "addr:street":"Ruprechtshofen",
    "iso:country":"AT",
    "sg:address":"Ruprechtshofen 5",
    "sg:city":"Naarn im Machlande",
    "sg:orig_category":"Samen U Saatgut",
    "sg:phone":"+43 4372 62586610",
    "sg:postcode":"4331",
    "sg:province":"Ober\u00f6sterreich",
    "wof:name":"Peham Josef",
    "wof:placetype":"venue"
},
  "geometry": {"coordinates":[14.6593856812,48.1819496155],"type":"Point"}
}