{
  "type": "Feature",
  "properties": {
    "addr:full":"Nr 22 St. P\u00f6lten-Traisenpark Nieder\u00f6sterreich 3107",
    "addr:postcode":"3107",
    "addr:street":"Nr 22",
    "iso:country":"AT",
    "sg:address":"Nr 22",
    "sg:city":"St. P\u00f6lten-Traisenpark",
    "sg:orig_category":"Heurigen / Buschenschank",
    "sg:phone":"+43 2742 365941",
    "sg:postcode":"3107",
    "sg:province":"Nieder\u00f6sterreich",
    "wof:name":"Weinschenke Gamsj\u00e4ger Leopold",
    "wof:placetype":"venue"
},
  "geometry": {"coordinates":[15.6436395645,48.2288246155],"type":"Point"}
}