{
  "type": "Feature",
  "properties": {
    "addr:full":"Nr 76 Baumgartenberg Ober\u00f6sterreich 4342",
    "addr:postcode":"4342",
    "addr:street":"Nr;Baumgartenberg Oberoesterreich",
    "iso:country":"AT",
    "sg:address":"Nr 76",
    "sg:city":"Baumgartenberg",
    "sg:orig_category":"Dachdeckereien",
    "sg:phone":"+43 4372 694320",
    "sg:postcode":"4342",
    "sg:province":"Ober\u00f6sterreich",
    "wof:name":"Grillenberger Ernst GesmbH",
    "wof:placetype":"venue"
},
  "geometry": {"coordinates":[14.745724678,48.2092475891],"type":"Point"}
}