{
  "type": "Feature",
  "properties": {
    "addr:full":"Waaggasse 20 Freistadt Ober\u00f6sterreich 4240",
    "addr:housenumber":"20",
    "addr:postcode":"4240",
    "addr:street":"Waaggasse",
    "iso:country":"AT",
    "sg:address":"Waaggasse 20",
    "sg:city":"Freistadt",
    "sg:classifiers":[
        {
            "category":"Home & Garden",
            "subcategory":"Household Appliances",
            "type":"Retail Goods"
        }
    ],
    "sg:phone":"+43 7942 72318",
    "sg:postcode":"4240",
    "sg:province":"Ober\u00f6sterreich",
    "sg:tags":[
        "heater",
        "bathroom"
    ],
    "sg:website":"dolsky.net",
    "wof:name":"Gottfried Dolsky",
    "wof:placetype":"venue"
},
  "geometry": {"coordinates":[14.5043859482,48.5123634338],"type":"Point"}
}