{
  "type": "Feature",
  "properties": {
    "iso:country":"AT",
    "sg:address":"Pischeldorfer Str 107",
    "sg:city":"Klagenfurt",
    "sg:orig_category":"Elektroinstallationsunternehmen",
    "sg:phone":"+43 4346 343266",
    "sg:postcode":"9020",
    "sg:province":"K\u00e4rnten",
    "wof:name":"Elektro Percher",
    "wof:placetype":"venue"
},
  "geometry": {"coordinates":[14.3264942169,46.6361045837],"type":"Point"}
}