{
  "type": "Feature",
  "properties": {
    "iso:country":"AT",
    "sg:address":"Ritter Waldauf-Str 13",
    "sg:city":"Wattens",
    "sg:orig_category":"Dolmetscher",
    "sg:phone":"+43 5224 54201",
    "sg:postcode":"6112",
    "sg:province":"Tirol",
    "wof:name":"Karakas Salih",
    "wof:placetype":"venue"
},
  "geometry": {"coordinates":[11.5852823257,47.2976455688],"type":"Point"}
}