{
  "type": "Feature",
  "properties": {
    "addr:full":"Pichling 39 Wei\u00dfkirchen in Steiermark Steiermark 8741",
    "addr:housenumber":"39",
    "addr:postcode":"8741",
    "addr:street":"Pichling",
    "iso:country":"AT",
    "sg:address":"Pichling 39",
    "sg:city":"Wei\u00dfkirchen in Steiermark",
    "sg:orig_category":"Altbausanierungen",
    "sg:phone":"+43 3577 82546",
    "sg:postcode":"8741",
    "sg:province":"Steiermark",
    "wof:name":"Weithaler Helmut",
    "wof:placetype":"venue"
},
  "geometry": {"coordinates":[14.7391662598,47.1303825378],"type":"Point"}
}