{
  "type": "Feature",
  "properties": {
    "addr:full":"Anton-Bruckner-G 55 Gerasdorf Nieder\u00f6sterreich 2201",
    "addr:housenumber":"55",
    "addr:postcode":"2201",
    "addr:street":"Anton-Bruckner-G",
    "iso:country":"AT",
    "sg:address":"Anton-Bruckner-G 55",
    "sg:city":"Gerasdorf",
    "sg:classifiers":[
        {
            "category":"Shopping",
            "subcategory":"Crafts & Fabrics",
            "type":"Retail Goods"
        }
    ],
    "sg:phone":"+43 4322 462922",
    "sg:postcode":"2201",
    "sg:province":"Nieder\u00f6sterreich",
    "sg:tags":[
        "polyester",
        "u",
        "-verarbeitung"
    ],
    "wof:name":"Meister Franz",
    "wof:placetype":"venue"
},
  "geometry": {"coordinates":[16.4966831207,48.3211326599],"type":"Point"}
}