{
  "type": "Feature",
  "properties": {
    "addr:full":"Maria-Theresien-Str 32 Innsbruck Tirol 6020",
    "addr:housenumber":"32",
    "addr:postcode":"6020",
    "addr:street":"Maria-Theresien-Str;Tirol",
    "iso:country":"AT",
    "sg:address":"Maria-Theresien-Str 32",
    "sg:city":"Innsbruck",
    "sg:orig_category":"Damenmoden",
    "sg:phone":"+43 512 5898580",
    "sg:postcode":"6020",
    "sg:province":"Tirol",
    "wof:name":"Zelger Josef Damenmoden-Exquisit KG",
    "wof:placetype":"venue"
},
  "geometry": {"coordinates":[11.3943033218,47.2651176453],"type":"Point"}
}