{
  "type": "Feature",
  "properties": {
    "iso:country":"AT",
    "sg:address":"7.Haidequerstr 6/Obj A3",
    "sg:city":"Wien",
    "sg:orig_category":"Versuchsanstalten",
    "sg:phone":"+43 1 400437605",
    "sg:postcode":"1110",
    "sg:province":"Wien",
    "wof:name":"WIENSTROM GmbH - Pr\u00fcfstelle Chemisches Laboratorium",
    "wof:placetype":"venue"
},
  "geometry": {"coordinates":[16.4197444916,48.1709709167],"type":"Point"}
}