{
  "type": "Feature",
  "properties": {
    "addr:full":"Nr 88 St. Leonhard im Pitztal Tirol 6481",
    "addr:postcode":"6481",
    "addr:street":"Nr 88;Tirol",
    "iso:country":"AT",
    "sg:address":"Nr 88",
    "sg:city":"St. Leonhard im Pitztal",
    "sg:orig_category":"Appartements / Ferienwohnungen",
    "sg:phone":"+43 5413 86307",
    "sg:postcode":"6481",
    "sg:province":"Tirol",
    "wof:name":"Ferienwohnungen Beim Bergdoktor",
    "wof:placetype":"venue"
},
  "geometry": {"coordinates":[-94.1031036377,34.9474601746],"type":"Point"}
}