{
  "type": "Feature",
  "properties": {
    "addr:full":"Barmherzigeng 3 Wien Wien 1030",
    "addr:housenumber":"3",
    "addr:postcode":"1030",
    "addr:street":"Barmherzigeng",
    "iso:country":"AT",
    "sg:address":"Barmherzigeng 3",
    "sg:city":"Wien",
    "sg:orig_category":"Dolmetscher",
    "sg:phone":"+43 4317 133921",
    "sg:postcode":"1030",
    "sg:province":"Wien",
    "wof:name":"Kalchschmied Gabriele Mag",
    "wof:placetype":"venue"
},
  "geometry": {"coordinates":[16.3937282562,48.197845459],"type":"Point"}
}