{
  "type": "Feature",
  "properties": {
    "iso:country":"AT",
    "sg:address":"Hauptpl 39",
    "sg:city":"Griffen",
    "sg:orig_category":"Polizei U Gendarmerie",
    "sg:phone":"+43 4359 1332149",
    "sg:postcode":"9112",
    "sg:province":"K\u00e4rnten",
    "wof:name":"Gendarmerie",
    "wof:placetype":"venue"
},
  "geometry": {"coordinates":[14.7313051224,46.7036705017],"type":"Point"}
}