{
  "type": "Feature",
  "properties": {
    "addr:full":"Gewerbepark 176 Sinabelkirchen Steiermark 8261",
    "addr:housenumber":"176",
    "addr:postcode":"8261",
    "addr:street":"Gewerbepark",
    "iso:country":"AT",
    "sg:address":"Gewerbepark 176",
    "sg:city":"Sinabelkirchen",
    "sg:orig_category":"Friseure U Frisiersalons",
    "sg:phone":"+43 4331 1820932",
    "sg:postcode":"8261",
    "sg:province":"Steiermark",
    "wof:name":"Friseur Marianne Hasibar - Novak",
    "wof:placetype":"venue"
},
  "geometry": {"coordinates":[15.8282032013,47.1025505066],"type":"Point"}
}