{
  "type": "Feature",
  "properties": {
    "iso:country":"AT",
    "sg:address":"Freist\u00e4dter Str 403a",
    "sg:city":"Linz",
    "sg:orig_category":"Ingenieurkonsulenten / Zivilingenieure",
    "sg:phone":"+43 732 7509830",
    "sg:postcode":"4040",
    "sg:province":"Ober\u00f6sterreich",
    "wof:name":"Wagner & Partner Ziviltechniker GesmbH",
    "wof:placetype":"venue"
},
  "geometry": {"coordinates":[14.3284921646,48.32787323],"type":"Point"}
}