{
  "type": "Feature",
  "properties": {
    "addr:full":"Innsbrucker Str 32 Lermoos Tirol 6631",
    "addr:postcode":"6631",
    "addr:street":"Str 32;Tirol",
    "iso:country":"AT",
    "sg:address":"Innsbrucker Str 32",
    "sg:city":"Lermoos",
    "sg:orig_category":"Appartements / Ferienwohnungen",
    "sg:phone":"+43 4356 733105",
    "sg:postcode":"6631",
    "sg:province":"Tirol",
    "wof:name":"Mott Franz",
    "wof:placetype":"venue"
},
  "geometry": {"coordinates":[10.88788414,47.396697998],"type":"Point"}
}