{
  "type": "Feature",
  "properties": {
    "iso:country":"AT",
    "sg:address":"Talh\u00e4uslweg 3",
    "sg:city":"Hopfgarten im Brixental",
    "sg:orig_category":"Dachdeckereien",
    "sg:phone":"+43 4366 45157170",
    "sg:postcode":"6361",
    "sg:province":"Tirol",
    "wof:name":"Schwarzdeckerei Sesli",
    "wof:placetype":"venue"
},
  "geometry": {"coordinates":[12.1611347198,47.4533653259],"type":"Point"}
}