{
  "type": "Feature",
  "properties": {
    "iso:country":"AT",
    "sg:address":"Holzstr 3",
    "sg:city":"Linz",
    "sg:orig_category":"Diskotheken",
    "sg:phone":"+43 732 784121",
    "sg:postcode":"4020",
    "sg:province":"Ober\u00f6sterreich",
    "wof:name":"Discothek Empire",
    "wof:placetype":"venue"
},
  "geometry": {"coordinates":[14.3005619049,48.3135414124],"type":"Point"}
}