{
  "type": "Feature",
  "properties": {
    "iso:country":"AT",
    "sg:address":"Gunskirchener Str 80",
    "sg:city":"Wels",
    "sg:orig_category":"Gartencenter",
    "sg:phone":"+43 7242 684970",
    "sg:postcode":"4600",
    "sg:province":"Ober\u00f6sterreich",
    "wof:name":"Bellaflora Gartencenter GmbH",
    "wof:placetype":"venue"
},
  "geometry": {"coordinates":[13.9750747681,48.1482620239],"type":"Point"}
}