{
  "type": "Feature",
  "properties": {
    "addr:full":"Ebnerg 2 Spittal an der Drau K\u00e4rnten 9800",
    "addr:housenumber":"2",
    "addr:postcode":"9800",
    "addr:street":"Ebnerg;Kaernten",
    "iso:country":"AT",
    "sg:address":"Ebnerg 2",
    "sg:city":"Spittal an der Drau",
    "sg:orig_category":"Druckereien",
    "sg:phone":"+43 4347 6222450",
    "sg:postcode":"9800",
    "sg:province":"K\u00e4rnten",
    "wof:name":"Kreiner Druck- u VerlagsgesmbH & Co KG",
    "wof:placetype":"venue"
},
  "geometry": {"coordinates":[13.4968490601,46.7980918884],"type":"Point"}
}