{
  "type": "Feature",
  "properties": {
    "iso:country":"AT",
    "sg:address":"Thern 23",
    "sg:city":"St. Georgen im Attergau",
    "sg:orig_category":"Autohandel",
    "sg:phone":"+43 4376 676368",
    "sg:postcode":"4880",
    "sg:province":"Ober\u00f6sterreich",
    "wof:name":"Autohaus Lisko GesmbH & Co KG",
    "wof:placetype":"venue"
},
  "geometry": {"coordinates":[13.5073156357,47.9255943298],"type":"Point"}
}