{
  "type": "Feature",
  "properties": {
    "addr:full":"Schallmooser Hptstr 51/Im AZS Salzburg Salzburg 5020",
    "addr:housenumber":"51",
    "addr:postcode":"5020",
    "addr:street":"Schallmooser;/ Im Azs Salzburg Salzburg",
    "iso:country":"AT",
    "sg:address":"Schallmooser Hptstr 51/Im AZS",
    "sg:city":"Salzburg",
    "sg:orig_category":"Matratzen",
    "sg:phone":"+43 662 8822350",
    "sg:postcode":"5020",
    "sg:province":"Salzburg",
    "wof:name":"Das Gesundheitshaus - Proschlaf",
    "wof:placetype":"venue"
},
  "geometry": {"coordinates":[13.0433769226,47.8006744385],"type":"Point"}
}