{
  "type": "Feature",
  "properties": {
    "addr:full":"Markt 31 Tragwein Ober\u00f6sterreich 4284",
    "addr:housenumber":"31",
    "addr:postcode":"4284",
    "addr:street":"Markt",
    "iso:country":"AT",
    "sg:address":"Markt 31",
    "sg:city":"Tragwein",
    "sg:orig_category":"Tabaktrafiken",
    "sg:phone":"+43 7263 88302",
    "sg:postcode":"4284",
    "sg:province":"Ober\u00f6sterreich",
    "wof:name":"Krapf Wolfgang",
    "wof:placetype":"venue"
},
  "geometry": {"coordinates":[14.6223011017,48.3316497803],"type":"Point"}
}