{
  "type": "Feature",
  "properties": {
    "addr:full":"Lerchenstr 7 Marchtrenk Ober\u00f6sterreich 4614",
    "addr:housenumber":"7",
    "addr:postcode":"4614",
    "addr:street":"Lerchenstr",
    "iso:country":"AT",
    "sg:address":"Lerchenstr 7",
    "sg:city":"Marchtrenk",
    "sg:orig_category":"Transportunternehmen",
    "sg:phone":"+43 7243 583660",
    "sg:postcode":"4614",
    "sg:province":"Ober\u00f6sterreich",
    "wof:name":"Wittberger Johann",
    "wof:placetype":"venue"
},
  "geometry": {"coordinates":[14.141043663,48.1980743408],"type":"Point"}
}