{
  "type": "Feature",
  "properties": {
    "addr:full":"Josef-Lindner-Str 8 Wals Salzburg 5071",
    "addr:housenumber":"8",
    "addr:postcode":"5071",
    "addr:street":"Josef-Lindner-Str;Salzburg",
    "iso:country":"AT",
    "sg:address":"Josef-Lindner-Str 8",
    "sg:city":"Wals",
    "sg:orig_category":"Lebensmittel / Einzelhandel",
    "sg:phone":"+43 662 857051",
    "sg:postcode":"5071",
    "sg:province":"Salzburg",
    "wof:name":"Unimarkt HandelsgesmbH & Co KG",
    "wof:placetype":"venue"
},
  "geometry": {"coordinates":[12.9693145752,47.7897644043],"type":"Point"}
}