{
  "type": "Feature",
  "properties": {
    "iso:country":"AT",
    "sg:address":"Parkstr 33",
    "sg:city":"Bad Tatzmannsdorf",
    "sg:classifiers":[
        {
            "category":"Travel",
            "subcategory":"Hotels & Motels",
            "type":"Entertainment"
        }
    ],
    "sg:phone":"+43 3353 7006",
    "sg:postcode":"7431",
    "sg:province":"Burgenland",
    "wof:name":"Hotel-Pension Sonnenhof",
    "wof:placetype":"venue"
},
  "geometry": {"coordinates":[16.2332458496,47.3379325867],"type":"Point"}
}