{
  "type": "Feature",
  "properties": {
    "iso:country":"AT",
    "sg:address":"Degengasse 20",
    "sg:city":"Wien",
    "sg:orig_category":"Capacity Agencies",
    "sg:phone":"+43 1 92913300",
    "sg:postcode":"1160",
    "sg:province":"Wien",
    "sg:website":"eastunlock.com",
    "wof:name":"EASTunlock",
    "wof:placetype":"venue"
},
  "geometry": {"coordinates":[16.3174304962,48.2151222229],"type":"Point"}
}