{
  "type": "Feature",
  "properties": {
    "addr:full":"Nr 26 Prinzendorf an der Zaya Nieder\u00f6sterreich 2185",
    "addr:housenumber":"2185",
    "addr:street":"Nr 26 Prinzendorf An Der Zaya Niederoesterreich",
    "iso:country":"AT",
    "sg:address":"Nr 26",
    "sg:city":"Prinzendorf an der Zaya",
    "sg:orig_category":"Autohandel",
    "sg:phone":"+43 4325 3389614",
    "sg:postcode":"2185",
    "sg:province":"Nieder\u00f6sterreich",
    "wof:name":"Braun GesmbH",
    "wof:placetype":"venue"
},
  "geometry": {"coordinates":[16.7169094086,48.5999908447],"type":"Point"}
}