{
  "type": "Feature",
  "properties": {
    "iso:country":"AT",
    "sg:address":"Wiener Str 25",
    "sg:city":"Amstetten",
    "sg:orig_category":"Textilwaren / Einzelhandel",
    "sg:phone":"+43 7472 63415",
    "sg:postcode":"3300",
    "sg:province":"Nieder\u00f6sterreich",
    "wof:name":"TPS",
    "wof:placetype":"venue"
},
  "geometry": {"coordinates":[14.8773956299,48.1228942871],"type":"Point"}
}