{
  "type": "Feature",
  "properties": {
    "iso:country":"AT",
    "sg:address":"Kaiserstr 14",
    "sg:city":"Wien",
    "sg:orig_category":"Politische Parteien",
    "sg:phone":"+43 1 5246310",
    "sg:postcode":"1070",
    "sg:province":"Wien",
    "wof:name":"Sozialistische LinksPartei (SLP)",
    "wof:placetype":"venue"
},
  "geometry": {"coordinates":[16.3414154053,48.1981277466],"type":"Point"}
}