{
  "type": "Feature",
  "properties": {
    "addr:full":"Schnerichweg 1 Maria Saal K\u00e4rnten 9063",
    "addr:housenumber":"1",
    "addr:postcode":"9063",
    "addr:street":"Schnerichweg",
    "iso:country":"AT",
    "sg:address":"Schnerichweg 1",
    "sg:city":"Maria Saal",
    "sg:orig_category":"Ingenieurkonsulenten / Zivilingenieure",
    "sg:phone":"+43 4223 2467",
    "sg:postcode":"9063",
    "sg:province":"K\u00e4rnten",
    "wof:name":"Petschnig Andreas Dipl-Ing",
    "wof:placetype":"venue"
},
  "geometry": {"coordinates":[14.3480968475,46.6813583374],"type":"Point"}
}