{
  "type": "Feature",
  "properties": {
    "addr:full":"Schwarzseestr 18 Kitzb\u00fchel Tirol 6370",
    "addr:housenumber":"18",
    "addr:postcode":"6370",
    "addr:street":"Schwarzseestr;Tirol",
    "iso:country":"AT",
    "sg:address":"Schwarzseestr 18",
    "sg:city":"Kitzb\u00fchel",
    "sg:orig_category":"Dolmetscher",
    "sg:phone":"+43 5356 63059",
    "sg:postcode":"6370",
    "sg:province":"Tirol",
    "wof:name":"Poley Anita Mag",
    "wof:placetype":"venue"
},
  "geometry": {"coordinates":[12.3841876984,47.4488868713],"type":"Point"}
}