{
  "type": "Feature",
  "properties": {
    "iso:country":"AT",
    "sg:address":"Kalvarienbergstr 37",
    "sg:city":"Neusiedl am See",
    "sg:orig_category":"Appartements / Ferienwohnungen",
    "sg:phone":"+43 2167 2110",
    "sg:postcode":"7100",
    "sg:province":"Burgenland",
    "wof:name":"K\u00f6nigshofer Maria",
    "wof:placetype":"venue"
},
  "geometry": {"coordinates":[16.8509788513,47.9444046021],"type":"Point"}
}