{
  "type": "Feature",
  "properties": {
    "iso:country":"AT",
    "sg:address":"H\u00f6ferau 59",
    "sg:city":"Kappl",
    "sg:orig_category":"Raumausstattung",
    "sg:phone":"+43 5445 6300",
    "sg:postcode":"6555",
    "sg:province":"Tirol",
    "wof:name":"Ladner Josef",
    "wof:placetype":"venue"
},
  "geometry": {"coordinates":[10.3749132156,47.0630874634],"type":"Point"}
}