{
  "type": "Feature",
  "properties": {
    "addr:full":"K\u00e4rntner Str 49 Wien Wien 1010",
    "addr:postcode":"1010",
    "addr:street":"Str 49",
    "iso:country":"AT",
    "sg:address":"K\u00e4rntner Str 49",
    "sg:city":"Wien",
    "sg:orig_category":"Messen U Ausstellungen",
    "sg:phone":"+43 1 51294900",
    "sg:postcode":"1010",
    "sg:province":"Wien",
    "wof:name":"MMI Messe M\u00fcnchen International Regionalb\u00fcro Mittel/Osteuropa GesmbH",
    "wof:placetype":"venue"
},
  "geometry": {"coordinates":[16.3688049316,48.2025489807],"type":"Point"}
}