{
  "type": "Feature",
  "properties": {
    "iso:country":"AT",
    "sg:address":"Sigmund-Thun-Str 1",
    "sg:city":"Hallein",
    "sg:orig_category":"Freizeit- U Sportbekleidung",
    "sg:phone":"+43 4362 4582726",
    "sg:postcode":"5400",
    "sg:province":"Salzburg",
    "wof:name":"Benetton",
    "wof:placetype":"venue"
},
  "geometry": {"coordinates":[13.0950450897,47.6824150085],"type":"Point"}
}