{
  "type": "Feature",
  "properties": {
    "iso:country":"AT",
    "sg:address":"Transportstr 17",
    "sg:city":"St. Veit an der Glan",
    "sg:orig_category":"Transportunternehmen",
    "sg:phone":"+43 4212 24620",
    "sg:postcode":"9300",
    "sg:province":"K\u00e4rnten",
    "wof:name":"Rabinig GesmbH",
    "wof:placetype":"venue"
},
  "geometry": {"coordinates":[14.3534879684,46.7583732605],"type":"Point"}
}