{
  "type": "Feature",
  "properties": {
    "iso:country":"AT",
    "sg:address":"Arlbergstr 139",
    "sg:city":"Bregenz",
    "sg:orig_category":"Immobilienverwaltungen",
    "sg:phone":"+43 5574 808",
    "sg:postcode":"6900",
    "sg:province":"Vorarlberg",
    "wof:name":"Josef Pircher Immobilienverwaltung GmbH",
    "wof:placetype":"venue"
},
  "geometry": {"coordinates":[9.7330513,47.4868927002],"type":"Point"}
}