{
  "type": "Feature",
  "properties": {
    "addr:full":"Murecker Str 18 St. Stefan im Rosental Steiermark 8083",
    "addr:housenumber":"18",
    "addr:postcode":"8083",
    "addr:street":"Str",
    "iso:country":"AT",
    "sg:address":"Murecker Str 18",
    "sg:city":"St. Stefan im Rosental",
    "sg:orig_category":"Elektroinstallationsunternehmen",
    "sg:phone":"+43 4331 1681450",
    "sg:postcode":"8083",
    "sg:province":"Steiermark",
    "wof:name":"S G S Elektro GmbH",
    "wof:placetype":"venue"
},
  "geometry": {"coordinates":[15.7113962173,46.9027404785],"type":"Point"}
}