{
  "type": "Feature",
  "properties": {
    "iso:country":"AT",
    "sg:address":"Oberhoferstr 145",
    "sg:city":"Mistelbach",
    "sg:orig_category":"Bauunternehmen",
    "sg:phone":"+43 2572 32040",
    "sg:postcode":"2130",
    "sg:province":"Nieder\u00f6sterreich",
    "wof:name":"Zayataler BaugesmbH nunmehr KG",
    "wof:placetype":"venue"
},
  "geometry": {"coordinates":[16.5650405884,48.5797691345],"type":"Point"}
}