{
  "type": "Feature",
  "properties": {
    "addr:full":"Roseggerstr 1 Hohenems Vorarlberg 6845",
    "addr:housenumber":"1",
    "addr:postcode":"6845",
    "addr:street":"Roseggerstr",
    "iso:country":"AT",
    "sg:address":"Roseggerstr 1",
    "sg:city":"Hohenems",
    "sg:orig_category":"Elektroinstallationsunternehmen",
    "sg:phone":"+43 4355 76726800",
    "sg:postcode":"6845",
    "sg:province":"Vorarlberg",
    "wof:name":"Lohs Elektro",
    "wof:placetype":"venue"
},
  "geometry": {"coordinates":[9.6803836823,47.3598251343],"type":"Point"}
}