{
  "type": "Feature",
  "properties": {
    "iso:country":"AT",
    "sg:address":"Radetzkystr 19",
    "sg:city":"Wien",
    "sg:orig_category":"Sonnenstudios",
    "sg:phone":"+43 1 7188999",
    "sg:postcode":"1030",
    "sg:province":"Wien",
    "wof:name":"Power Sun",
    "wof:placetype":"venue"
},
  "geometry": {"coordinates":[16.3902835846,48.2113075256],"type":"Point"}
}