{
  "type": "Feature",
  "properties": {
    "addr:full":"Markt 115 St. Wolfgang im Salzkammergut Ober\u00f6sterreich 5360",
    "addr:housenumber":"115",
    "addr:postcode":"5360",
    "addr:street":"Markt",
    "iso:country":"AT",
    "sg:address":"Markt 115",
    "sg:city":"St. Wolfgang im Salzkammergut",
    "sg:orig_category":"Pensionen / Privatzimmer",
    "sg:phone":"+43 6138 2370",
    "sg:postcode":"5360",
    "sg:province":"Ober\u00f6sterreich",
    "wof:name":"Fr\u00fchst\u00fcckspension Haus Anzengruber",
    "wof:placetype":"venue"
},
  "geometry": {"coordinates":[13.4470758438,47.73878479],"type":"Point"}
}