{
  "type": "Feature",
  "properties": {
    "addr:full":"Kepler Str 5 Attnang-Puchheim Ober\u00f6sterreich 4800",
    "addr:housenumber":"5",
    "addr:postcode":"4800",
    "addr:street":"Str",
    "iso:country":"AT",
    "sg:address":"Kepler Str 5",
    "sg:city":"Attnang-Puchheim",
    "sg:orig_category":"Werbeagenturen",
    "sg:phone":"+43 767462553",
    "sg:postcode":"4800",
    "sg:province":"Ober\u00f6sterreich",
    "wof:name":"Bogner Willi",
    "wof:placetype":"venue"
},
  "geometry": {"coordinates":[13.7268257141,48.0119972229],"type":"Point"}
}