{
  "type": "Feature",
  "properties": {
    "addr:full":"Hietzinger Hauptstr 80 Wien Wien 1130",
    "addr:housenumber":"80",
    "addr:postcode":"1130",
    "addr:street":"Hietzinger Hauptstr",
    "iso:country":"AT",
    "sg:address":"Hietzinger Hauptstr 80",
    "sg:city":"Wien",
    "sg:orig_category":"Werbeagenturen",
    "sg:phone":"+43 4318 793577",
    "sg:postcode":"1130",
    "sg:province":"Wien",
    "wof:name":"Stocker & Partner KEG",
    "wof:placetype":"venue"
},
  "geometry": {"coordinates":[16.2835502625,48.1874542236],"type":"Point"}
}