{
  "type": "Feature",
  "properties": {
    "addr:full":"Hauptstrasse 56 D\u00fcrnkrut Nieder\u00f6sterreich 2263",
    "addr:housenumber":"56",
    "addr:postcode":"2263",
    "addr:street":"Hauptstrasse;Niederoesterreich",
    "iso:country":"AT",
    "sg:address":"Hauptstrasse 56",
    "sg:city":"D\u00fcrnkrut",
    "sg:classifiers":[
        {
            "category":"Government",
            "subcategory":"Fire Station",
            "type":"Public Place"
        }
    ],
    "sg:phone":"+43 2538 80674",
    "sg:postcode":"2263",
    "sg:province":"Nieder\u00f6sterreich",
    "sg:tags":[
        "explosion",
        "coating",
        "surface",
        "equipment",
        "protection",
        "safety",
        "systems",
        "operation"
    ],
    "wof:name":"Walter Stolz",
    "wof:placetype":"venue"
},
  "geometry": {"coordinates":[16.8581809998,48.4686584473],"type":"Point"}
}