{
  "type": "Feature",
  "properties": {
    "addr:full":"Untere Donaul\u00e4nde 9 Linz Ober\u00f6sterreich 4020",
    "addr:housenumber":"9",
    "addr:postcode":"4020",
    "addr:street":"Untere Donaulaende",
    "iso:country":"AT",
    "sg:address":"Untere Donaul\u00e4nde 9",
    "sg:city":"Linz",
    "sg:orig_category":"Bars-Cafes",
    "sg:phone":"+43 732 785555",
    "sg:postcode":"4020",
    "sg:province":"Ober\u00f6sterreich",
    "wof:name":"Beluga Gastro GmbH",
    "wof:placetype":"venue"
},
  "geometry": {"coordinates":[14.2945957184,48.3108139038],"type":"Point"}
}