{
  "type": "Feature",
  "properties": {
    "addr:full":"Sportplatzweg 214 Hirschbach Nieder\u00f6sterreich 3942",
    "addr:housenumber":"214",
    "addr:postcode":"3942",
    "addr:street":"Sportplatzweg",
    "iso:country":"AT",
    "sg:address":"Sportplatzweg 214",
    "sg:city":"Hirschbach",
    "sg:orig_category":"Erdarbeiten",
    "sg:phone":"+43 4328 546542",
    "sg:postcode":"3942",
    "sg:province":"Nieder\u00f6sterreich",
    "wof:name":"Schoderb\u00f6ck Peter",
    "wof:placetype":"venue"
},
  "geometry": {"coordinates":[15.1249046326,48.7473945618],"type":"Point"}
}