{
  "type": "Feature",
  "properties": {
    "iso:country":"AT",
    "sg:address":"Felixdorfer Gasse 4a",
    "sg:city":"Wiener Neustadt",
    "sg:orig_category":"Animal By-Product Plants",
    "sg:phone":"+43 2622 28251",
    "sg:postcode":"2700",
    "sg:province":"Nieder\u00f6sterreich",
    "wof:name":"Friedrich Lassnig",
    "wof:placetype":"venue"
},
  "geometry": {"coordinates":[16.2382469177,47.8401565552],"type":"Point"}
}