{
  "type": "Feature",
  "properties": {
    "addr:full":"Rainerstr 4 Salzburg Salzburg 5020",
    "addr:housenumber":"4",
    "addr:postcode":"5020",
    "addr:street":"Rainerstr;Salzburg",
    "iso:country":"AT",
    "sg:address":"Rainerstr 4",
    "sg:city":"Salzburg",
    "sg:orig_category":"Tabaktrafiken",
    "sg:phone":"+43 662 872212",
    "sg:postcode":"5020",
    "sg:province":"Salzburg",
    "wof:name":"Schiller Barbara",
    "wof:placetype":"venue"
},
  "geometry": {"coordinates":[13.0421390533,47.807182312],"type":"Point"}
}