{
  "type": "Feature",
  "properties": {
    "iso:country":"AT",
    "sg:address":"Meiselstr 77",
    "sg:city":"Wien",
    "sg:orig_category":"Transportunternehmen",
    "sg:phone":"+43 1 9820368",
    "sg:postcode":"1140",
    "sg:province":"Wien",
    "wof:name":"Sladek Theodor",
    "wof:placetype":"venue"
},
  "geometry": {"coordinates":[16.3076953888,48.1982955933],"type":"Point"}
}