{
  "type": "Feature",
  "properties": {
    "iso:country":"AT",
    "sg:address":"Friedrich-Engels-Pl vor 19",
    "sg:city":"Wien",
    "sg:orig_category":"Non-Classified Establishments",
    "sg:phone":"+43 1 3326382",
    "sg:postcode":"1200",
    "sg:province":"Wien",
    "wof:name":"TAXI-TEL Standplatztelefon Betriebs GmbH",
    "wof:placetype":"venue"
},
  "geometry": {"coordinates":[16.3802947998,48.243938446],"type":"Point"}
}