{
  "type": "Feature",
  "properties": {
    "addr:full":"Pernerinsel Hallein Salzburg 5400",
    "addr:postcode":"5400",
    "addr:street":"Pernerinsel;Salzburg",
    "iso:country":"AT",
    "sg:address":"Pernerinsel",
    "sg:city":"Hallein",
    "sg:classifiers":[
        {
            "category":"Building & Trades",
            "subcategory":"Plumbing",
            "type":"Services"
        }
    ],
    "sg:phone":"+43 6245 798300",
    "sg:postcode":"5400",
    "sg:province":"Salzburg",
    "sg:tags":[
        "tyre"
    ],
    "wof:name":"Vulkoplast Reifenges.m.b.H. & Co KG",
    "wof:placetype":"venue"
},
  "geometry": {"coordinates":[13.0917053223,47.6847953796],"type":"Point"}
}