{
  "type": "Feature",
  "properties": {
    "addr:full":"Bahnhofstr 37 Ebensee Ober\u00f6sterreich 4802",
    "addr:housenumber":"37",
    "addr:postcode":"4802",
    "addr:street":"Bahnhofstr",
    "iso:country":"AT",
    "sg:address":"Bahnhofstr 37",
    "sg:city":"Ebensee",
    "sg:orig_category":"Filmproduktionen",
    "sg:phone":"+43 6133 4404",
    "sg:postcode":"4802",
    "sg:province":"Ober\u00f6sterreich",
    "wof:name":"EL-TV",
    "wof:placetype":"venue"
},
  "geometry": {"coordinates":[13.771437645,47.806438446],"type":"Point"}
}