{
  "type": "Feature",
  "properties": {
    "iso:country":"AT",
    "sg:address":"Atterseestr 63",
    "sg:city":"Lenzing",
    "sg:orig_category":"Fotografen",
    "sg:phone":"+43 7672929610",
    "sg:postcode":"4860",
    "sg:province":"Ober\u00f6sterreich",
    "wof:name":"Humer Alois",
    "wof:placetype":"venue"
},
  "geometry": {"coordinates":[13.6099061966,47.9746246338],"type":"Point"}
}