{
  "type": "Feature",
  "properties": {
    "iso:country":"AT",
    "sg:address":"Nr 29",
    "sg:city":"Flie\u00df",
    "sg:orig_category":"Volksschulen",
    "sg:phone":"+43 5449 5173",
    "sg:postcode":"6521",
    "sg:province":"Tirol",
    "wof:name":"Volksschule",
    "wof:placetype":"venue"
},
  "geometry": {"coordinates":[10.6327600479,47.1109886169],"type":"Point"}
}