{
  "type": "Feature",
  "properties": {
    "addr:full":"Framsweg 19 Innsbruck Tirol 6020",
    "addr:housenumber":"19",
    "addr:postcode":"6020",
    "addr:street":"Framsweg;Tirol",
    "iso:country":"AT",
    "sg:address":"Framsweg 19",
    "sg:city":"Innsbruck",
    "sg:orig_category":"Volksschulen",
    "sg:phone":"+43 512 262290",
    "sg:postcode":"6020",
    "sg:province":"Tirol",
    "wof:name":"Volksschule Arzl",
    "wof:placetype":"venue"
},
  "geometry": {"coordinates":[11.4265823364,47.2846336365],"type":"Point"}
}