{
  "type": "Feature",
  "properties": {
    "iso:country":"AT",
    "sg:address":"Seideng 23",
    "sg:city":"Wien",
    "sg:orig_category":"Restaurants: Chinesisch",
    "sg:phone":"+43 1 5231256",
    "sg:postcode":"1070",
    "sg:province":"Wien",
    "wof:name":"China-Restaurant Kanton",
    "wof:placetype":"venue"
},
  "geometry": {"coordinates":[16.3428897858,48.2001495361],"type":"Point"}
}