{
  "type": "Feature",
  "properties": {
    "addr:full":"Loferer Bundesstr 7 Saalfelden am Steinernen Meer Salzburg 5760",
    "addr:housenumber":"7",
    "addr:postcode":"5760",
    "addr:street":"Bundesstr",
    "iso:country":"AT",
    "sg:address":"Loferer Bundesstr 7",
    "sg:city":"Saalfelden am Steinernen Meer",
    "sg:orig_category":"Elektroinstallationsunternehmen",
    "sg:phone":"+43 4365 82741080",
    "sg:postcode":"5760",
    "sg:province":"Salzburg",
    "wof:name":"Elektro Hans St\u00f6ckl GmbH & Co KG",
    "wof:placetype":"venue"
},
  "geometry": {"coordinates":[12.8445281982,47.4316444397],"type":"Point"}
}