{
  "type": "Feature",
  "properties": {
    "addr:full":"Nr 10 Angern Nieder\u00f6sterreich 2261",
    "addr:postcode":"2261",
    "addr:street":"Nr;Angern",
    "iso:country":"AT",
    "sg:address":"Nr 10",
    "sg:city":"Angern",
    "sg:orig_category":"Feuerwehren",
    "sg:phone":"+43 2284 2696",
    "sg:postcode":"2261",
    "sg:province":"Nieder\u00f6sterreich",
    "wof:name":"Freiwillige Feuerwehr Zwerndorf",
    "wof:placetype":"venue"
},
  "geometry": {"coordinates":[16.8282699585,48.3832092285],"type":"Point"}
}