{
  "type": "Feature",
  "properties": {
    "addr:full":"Schubertstrasse 3 Korneuburg Nieder\u00f6sterreich 2100",
    "addr:housenumber":"3",
    "addr:postcode":"2100",
    "addr:street":"Schubertstrasse;Niederoesterreich",
    "iso:country":"AT",
    "sg:address":"Schubertstrasse 3",
    "sg:city":"Korneuburg",
    "sg:classifiers":[
        {
            "category":"Communications",
            "subcategory":"Television Station",
            "type":"Services"
        }
    ],
    "sg:phone":"+43 2262 71117",
    "sg:postcode":"2100",
    "sg:province":"Nieder\u00f6sterreich",
    "sg:tags":[
        "set",
        "radio",
        "cable",
        "antenna"
    ],
    "wof:name":"Bernhard Rainer",
    "wof:placetype":"venue"
},
  "geometry": {"coordinates":[16.3357982635,48.3420410156],"type":"Point"}
}