{
  "type": "Feature",
  "properties": {
    "addr:full":"Grazer Str 7 Pinkafeld Burgenland 7423",
    "addr:housenumber":"7",
    "addr:postcode":"7423",
    "addr:street":"Str",
    "iso:country":"AT",
    "sg:address":"Grazer Str 7",
    "sg:city":"Pinkafeld",
    "sg:classifiers":[
        {
            "category":"Travel",
            "subcategory":"Hotels & Motels",
            "type":"Entertainment"
        }
    ],
    "sg:phone":"+43 3357 42248",
    "sg:postcode":"7423",
    "sg:province":"Burgenland",
    "wof:name":"Portschy Hans",
    "wof:placetype":"venue"
},
  "geometry": {"coordinates":[16.1168327332,47.3704605103],"type":"Point"}
}