{
  "type": "Feature",
  "properties": {
    "addr:full":"Silvrettastr 5 Schruns Vorarlberg 6780",
    "addr:housenumber":"5",
    "addr:postcode":"6780",
    "addr:street":"Silvrettastr",
    "iso:country":"AT",
    "sg:address":"Silvrettastr 5",
    "sg:city":"Schruns",
    "sg:orig_category":"Non-Classified Establishments",
    "sg:phone":"+43 5556 78092",
    "sg:postcode":"6780",
    "sg:province":"Vorarlberg",
    "wof:name":"Kath Jugend und Jungschar Regionalstelle",
    "wof:placetype":"venue"
},
  "geometry": {"coordinates":[9.9206418991,47.0796852112],"type":"Point"}
}