{
  "type": "Feature",
  "properties": {
    "addr:full":"Schillerstr 20 Voitsberg Steiermark 8570",
    "addr:housenumber":"20",
    "addr:postcode":"8570",
    "addr:street":"Schillerstr",
    "iso:country":"AT",
    "sg:address":"Schillerstr 20",
    "sg:city":"Voitsberg",
    "sg:orig_category":"Volksschulen",
    "sg:phone":"+43 3142 22013",
    "sg:postcode":"8570",
    "sg:province":"Steiermark",
    "wof:name":"Volksschule Schillerstr",
    "wof:placetype":"venue"
},
  "geometry": {"coordinates":[15.1474504471,47.0489692688],"type":"Point"}
}