{
  "type": "Feature",
  "properties": {
    "iso:country":"AT",
    "sg:address":"Valentin Zeileis-Str 25",
    "sg:city":"Gallspach",
    "sg:orig_category":"Apotheken",
    "sg:phone":"+43 7248 62604",
    "sg:postcode":"4713",
    "sg:province":"Ober\u00f6sterreich",
    "wof:name":"Apotheke z hl Valentin Magpharm Seidl",
    "wof:placetype":"venue"
},
  "geometry": {"coordinates":[13.8105945587,48.207824707],"type":"Point"}
}