{
  "type": "Feature",
  "properties": {
    "addr:full":"Widumgasse 5 Silz Tirol 6424",
    "addr:housenumber":"5",
    "addr:postcode":"6424",
    "addr:street":"Widumgasse;Tirol",
    "iso:country":"AT",
    "sg:address":"Widumgasse 5",
    "sg:city":"Silz",
    "sg:classifiers":[
        {
            "category":"Home & Garden",
            "subcategory":"Household Appliances",
            "type":"Retail Goods"
        }
    ],
    "sg:phone":"+43 5263 63740",
    "sg:postcode":"6424",
    "sg:province":"Tirol",
    "sg:tags":[
        "electric"
    ],
    "wof:name":"Elektroinstallationen Ing. Dablander GmbH",
    "wof:placetype":"venue"
},
  "geometry": {"coordinates":[10.9269447327,47.266166687],"type":"Point"}
}