{
  "type": "Feature",
  "properties": {
    "addr:full":"Lenaustr 15 Lambach Ober\u00f6sterreich 4650",
    "addr:housenumber":"15",
    "addr:postcode":"4650",
    "addr:street":"Lenaustr",
    "iso:country":"AT",
    "sg:address":"Lenaustr 15",
    "sg:city":"Lambach",
    "sg:orig_category":"Handelsagenturen",
    "sg:phone":"+43 664 2007708",
    "sg:postcode":"4650",
    "sg:province":"Ober\u00f6sterreich",
    "wof:name":"Rampetsreiter Thomas",
    "wof:placetype":"venue"
},
  "geometry": {"coordinates":[13.8608484268,48.0920982361],"type":"Point"}
}