{
  "type": "Feature",
  "properties": {
    "addr:full":"Salzburger Strasse 20b St. Johann in Tirol Tirol 6380",
    "addr:housenumber":"20b",
    "addr:postcode":"6380",
    "addr:street":"Salzburger Strasse;Tirol",
    "iso:country":"AT",
    "sg:address":"Salzburger Strasse 20b",
    "sg:city":"St. Johann in Tirol",
    "sg:classifiers":[
        {
            "category":"Military Area",
            "subcategory":"Air Force Base",
            "type":"Public Place"
        }
    ],
    "sg:phone":"+43 5352 62527",
    "sg:postcode":"6380",
    "sg:province":"Tirol",
    "sg:tags":[
        "curtain",
        "door",
        "doors",
        "gate"
    ],
    "sg:website":"frivent.com",
    "wof:name":"frivent - Josef Friedl GmbH Luft+W\u00e4rme+Klima",
    "wof:placetype":"venue"
},
  "geometry": {"coordinates":[12.4253330231,47.5277442932],"type":"Point"}
}