{
  "type": "Feature",
  "properties": {
    "addr:full":"Manker Strasse 27 Wieselburg an der Erlauf Nieder\u00f6sterreich 3250",
    "addr:housenumber":"27",
    "addr:postcode":"3250",
    "addr:street":"Manker Strasse",
    "iso:country":"AT",
    "sg:address":"Manker Strasse 27",
    "sg:city":"Wieselburg an der Erlauf",
    "sg:classifiers":[
        {
            "category":"Building & Trades",
            "subcategory":"Locksmith",
            "type":"Services"
        }
    ],
    "sg:phone":"+43 7416 59000",
    "sg:postcode":"3250",
    "sg:province":"Nieder\u00f6sterreich",
    "sg:tags":[
        "planting",
        "green",
        "roof"
    ],
    "wof:name":"Wanzmann Ges.m.b.H. & Co KG",
    "wof:placetype":"venue"
},
  "geometry": {"coordinates":[15.143652916,48.1281776428],"type":"Point"}
}