{
  "type": "Feature",
  "properties": {
    "addr:full":"Alte Landstr. 40 5702",
    "addr:housenumber":"40",
    "addr:postcode":"5702",
    "addr:street":"Alte Landstr.",
    "iso:country":"AT",
    "sg:address":"Alte Landstr. 40",
    "sg:classifiers":[
        {
            "category":"Bars & Pubs",
            "subcategory":"Nightclub",
            "type":"Food & Drink"
        }
    ],
    "sg:phone":"+43 4365 4257492",
    "sg:postcode":"5702",
    "sg:tags":[
        "cake",
        "bread"
    ],
    "wof:name":"JOSEF BRANDL",
    "wof:placetype":"venue"
},
  "geometry": {"coordinates":[12.7921161652,47.3035736084],"type":"Point"}
}