{
  "type": "Feature",
  "properties": {
    "addr:full":"Grazer Str 111 Oberwart Burgenland 7400",
    "addr:housenumber":"111",
    "addr:postcode":"7400",
    "iso:country":"AT",
    "sg:address":"Grazer Str 111",
    "sg:city":"Oberwart",
    "sg:orig_category":"Autohandel",
    "sg:phone":"+43 3352 380270",
    "sg:postcode":"7400",
    "sg:province":"Burgenland",
    "wof:name":"Schranz GesmbH",
    "wof:placetype":"venue"
},
  "geometry": {"coordinates":[16.188129425,47.2842178345],"type":"Point"}
}