{
  "type": "Feature",
  "properties": {
    "addr:full":"Quellenstr 138-140 Wien Wien 1100",
    "addr:housenumber":"138-140",
    "addr:postcode":"1100",
    "iso:country":"AT",
    "sg:address":"Quellenstr 138-140",
    "sg:city":"Wien",
    "sg:orig_category":"Druckereien",
    "sg:phone":"+43 1 4797142",
    "sg:postcode":"1100",
    "sg:province":"Wien",
    "wof:name":"K\u00f6NIGSATZ Print GesmbH",
    "wof:placetype":"venue"
},
  "geometry": {"coordinates":[16.3630504608,48.1764717102],"type":"Point"}
}