{
  "type": "Feature",
  "properties": {
    "addr:full":"Wiener Strasse 95 Linz Ober\u00f6sterreich 4020",
    "addr:housenumber":"95",
    "addr:postcode":"4020",
    "addr:street":"Wiener Strasse",
    "iso:country":"AT",
    "sg:address":"Wiener Strasse 95",
    "sg:city":"Linz",
    "sg:classifiers":[
        {
            "category":"Shopping",
            "subcategory":"Clothing, Apparel, & Fashions",
            "type":"Retail Goods"
        }
    ],
    "sg:phone":"+43 732 653250",
    "sg:postcode":"4020",
    "sg:province":"Ober\u00f6sterreich",
    "sg:tags":[
        "garment",
        "fur"
    ],
    "sg:website":"pelzbaumgartner.at",
    "wof:name":"Pelz Baumgartner KG",
    "wof:placetype":"venue"
},
  "geometry": {"coordinates":[14.3050928116,48.2837715149],"type":"Point"}
}