{
  "type": "Feature",
  "properties": {
    "addr:full":"Nr 187 Kaltenbach Tirol 6272",
    "addr:postcode":"6272",
    "addr:street":"Nr 187;Tirol",
    "iso:country":"AT",
    "sg:address":"Nr 187",
    "sg:city":"Kaltenbach",
    "sg:classifiers":[
        {
            "category":"Restaurant",
            "type":"Food & Drink"
        }
    ],
    "sg:phone":"+43 5283 3094",
    "sg:postcode":"6272",
    "sg:province":"Tirol",
    "sg:tags":[
        "pizzeria"
    ],
    "wof:name":"Klocker Katharina",
    "wof:placetype":"venue"
},
  "geometry": {"coordinates":[11.8866147995,47.2910232544],"type":"Point"}
}