{
  "type": "Feature",
  "properties": {
    "iso:country":"AT",
    "sg:address":"Burgstall 346",
    "sg:city":"Mayrhofen",
    "sg:orig_category":"Tischlereien",
    "sg:phone":"+43 5285 63956",
    "sg:postcode":"6290",
    "sg:province":"Tirol",
    "wof:name":"Mauracher Josef",
    "wof:placetype":"venue"
},
  "geometry": {"coordinates":[11.8624277115,47.1670684814],"type":"Point"}
}