{
  "type": "Feature",
  "properties": {
    "addr:full":"Weyrer Str 18 Waidhofen an der Ybbs Nieder\u00f6sterreich 3340",
    "addr:postcode":"3340",
    "addr:street":"Str 18",
    "iso:country":"AT",
    "sg:address":"Weyrer Str 18",
    "sg:city":"Waidhofen an der Ybbs",
    "sg:orig_category":"Bestattungsunternehmen",
    "sg:phone":"+43 4374 42522960",
    "sg:postcode":"3340",
    "sg:province":"Nieder\u00f6sterreich",
    "wof:name":"Aigner A GesmbH",
    "wof:placetype":"venue"
},
  "geometry": {"coordinates":[14.7696933746,47.9574050903],"type":"Point"}
}