{
  "type": "Feature",
  "properties": {
    "iso:country":"AT",
    "sg:address":"Rankeng 28",
    "sg:city":"Graz",
    "sg:orig_category":"Lichtwerbung",
    "sg:phone":"+43 316 7240400",
    "sg:postcode":"8020",
    "sg:province":"Steiermark",
    "wof:name":"Wilfling N Reklamebau GesmbH",
    "wof:placetype":"venue"
},
  "geometry": {"coordinates":[15.4317789078,47.0609054565],"type":"Point"}
}