{
  "type": "Feature",
  "properties": {
    "iso:country":"AT",
    "sg:address":"Nr 17",
    "sg:city":"Fresach",
    "sg:orig_category":"Autoreparatur",
    "sg:phone":"+43 4245 64890",
    "sg:postcode":"9712",
    "sg:province":"K\u00e4rnten",
    "wof:name":"Tschernutter Christoph",
    "wof:placetype":"venue"
},
  "geometry": {"coordinates":[13.6881408691,46.7136497498],"type":"Point"}
}