{
  "type": "Feature",
  "properties": {
    "addr:full":"Floridsdorfer Hauptstr 24 Wien Wien 1210",
    "addr:housenumber":"24",
    "addr:postcode":"1210",
    "addr:street":"Floridsdorfer Hauptstr",
    "iso:country":"AT",
    "sg:address":"Floridsdorfer Hauptstr 24",
    "sg:city":"Wien",
    "sg:orig_category":"Waren Aller Art",
    "sg:phone":"+43 4312 940251",
    "sg:postcode":"1210",
    "sg:province":"Wien",
    "wof:name":"A & G Trading HandelsgesmbH",
    "wof:placetype":"venue"
},
  "geometry": {"coordinates":[16.3957061768,48.2552604675],"type":"Point"}
}