{
  "type": "Feature",
  "properties": {
    "addr:full":"Hafeng 24 Wien Wien 1030",
    "addr:housenumber":"24",
    "addr:postcode":"1030",
    "addr:street":"Hafeng",
    "iso:country":"AT",
    "sg:address":"Hafeng 24",
    "sg:city":"Wien",
    "sg:orig_category":"Innenausbau",
    "sg:phone":"+43 1 7985426",
    "sg:postcode":"1030",
    "sg:province":"Wien",
    "wof:name":"Sturm GmbH",
    "wof:placetype":"venue"
},
  "geometry": {"coordinates":[16.393529892,48.1916847229],"type":"Point"}
}