{
  "type": "Feature",
  "properties": {
    "addr:full":"Nr 43 St. Johann im Saggautal Steiermark 8453",
    "addr:postcode":"8453",
    "addr:street":"Nr 43",
    "iso:country":"AT",
    "sg:address":"Nr 43",
    "sg:city":"St. Johann im Saggautal",
    "sg:orig_category":"Tischlereien",
    "sg:phone":"+43 3455 80480",
    "sg:postcode":"8453",
    "sg:province":"Steiermark",
    "wof:name":"Schmid Karl",
    "wof:placetype":"venue"
},
  "geometry": {"coordinates":[15.4005069733,46.7027244568],"type":"Point"}
}