{
  "type": "Feature",
  "properties": {
    "addr:full":"Huglg 13-15 Wien Wien 1150",
    "addr:postcode":"13-15;1150",
    "iso:country":"AT",
    "sg:address":"Huglg 13-15",
    "sg:city":"Wien",
    "sg:orig_category":"Offsetdruckereien",
    "sg:phone":"+43 1 9854188",
    "sg:postcode":"1150",
    "sg:province":"Wien",
    "wof:name":"Offset-Team",
    "wof:placetype":"venue"
},
  "geometry": {"coordinates":[16.3247299194,48.1983070374],"type":"Point"}
}