{
  "type": "Feature",
  "properties": {
    "addr:full":"Nr 35 Obertraun Ober\u00f6sterreich 4831",
    "addr:postcode":"4831",
    "addr:street":"Nr;Obertraun",
    "iso:country":"AT",
    "sg:address":"Nr 35",
    "sg:city":"Obertraun",
    "sg:orig_category":"Lebensmittel / Einzelhandel",
    "sg:phone":"+43 676 7053236",
    "sg:postcode":"4831",
    "sg:province":"Ober\u00f6sterreich",
    "wof:name":"Stricker Christian",
    "wof:placetype":"venue"
},
  "geometry": {"coordinates":[13.6863412857,47.5574989319],"type":"Point"}
}