{
  "type": "Feature",
  "properties": {
    "addr:full":"Nr 34 Ludmannsdorf K\u00e4rnten 9072",
    "addr:postcode":"9072",
    "addr:street":"Nr 34 Ludmannsdorf Kaernten",
    "iso:country":"AT",
    "sg:address":"Nr 34",
    "sg:city":"Ludmannsdorf",
    "sg:orig_category":"Tischlereien",
    "sg:phone":"+43 4228 2312",
    "sg:postcode":"9072",
    "sg:province":"K\u00e4rnten",
    "wof:name":"Schellander Michael",
    "wof:placetype":"venue"
},
  "geometry": {"coordinates":[14.1361970901,46.5409851074],"type":"Point"}
}