{
  "type": "Feature",
  "properties": {
    "addr:full":"Linzer Strasse 33 Gramastetten Ober\u00f6sterreich 4201",
    "addr:housenumber":"33",
    "addr:postcode":"4201",
    "addr:street":"Linzer Strasse",
    "iso:country":"AT",
    "sg:address":"Linzer Strasse 33",
    "sg:city":"Gramastetten",
    "sg:classifiers":[
        {
            "category":"Structure",
            "subcategory":"Building",
            "type":"Public Place"
        }
    ],
    "sg:phone":"+43 7239 88240",
    "sg:postcode":"4201",
    "sg:province":"Ober\u00f6sterreich",
    "sg:tags":[
        "profiled",
        "aluminium",
        "fence"
    ],
    "sg:website":"metallbaumayr.at",
    "wof:name":"Franz Mayr Schlosserei GmbH",
    "wof:placetype":"venue"
},
  "geometry": {"coordinates":[14.1995439529,48.3777046204],"type":"Point"}
}