{
  "type": "Feature",
  "properties": {
    "addr:full":"Lisztstr 39 Lackendorf Burgenland 7321",
    "addr:housenumber":"39",
    "addr:postcode":"7321",
    "addr:street":"Lisztstr",
    "iso:country":"AT",
    "sg:address":"Lisztstr 39",
    "sg:city":"Lackendorf",
    "sg:orig_category":"Lebensmittel / Einzelhandel",
    "sg:phone":"+43 2619 7455",
    "sg:postcode":"7321",
    "sg:province":"Burgenland",
    "wof:name":"Kientzl Sabine",
    "wof:placetype":"venue"
},
  "geometry": {"coordinates":[16.5304927826,47.5669059753],"type":"Point"}
}