{
  "type": "Feature",
  "properties": {
    "addr:full":"Wiener Str 4 Laxenburg Nieder\u00f6sterreich 2361",
    "addr:postcode":"2361",
    "addr:street":"Niederoesterreich",
    "iso:country":"AT",
    "sg:address":"Wiener Str 4",
    "sg:city":"Laxenburg",
    "sg:orig_category":"Exporteure U Importeure",
    "sg:phone":"+43 2236 716210",
    "sg:postcode":"2361",
    "sg:province":"Nieder\u00f6sterreich",
    "wof:name":"Maximpex Import-Export -Elisabeth Maxim",
    "wof:placetype":"venue"
},
  "geometry": {"coordinates":[16.3579883575,48.069229126],"type":"Point"}
}