{
  "type": "Feature",
  "properties": {
    "addr:full":"Nr 27 Windhaag Ober\u00f6sterreich 4322",
    "addr:postcode":"4322",
    "addr:street":"Nr 27 Windhaag",
    "iso:country":"AT",
    "sg:address":"Nr 27",
    "sg:city":"Windhaag",
    "sg:orig_category":"Gemeinden",
    "sg:phone":"+43 7264 46550",
    "sg:postcode":"4322",
    "sg:province":"Ober\u00f6sterreich",
    "wof:name":"Gemeindeamt Rechberg",
    "wof:placetype":"venue"
},
  "geometry": {"coordinates":[14.6817007065,48.283416748],"type":"Point"}
}