{
  "type": "Feature",
  "properties": {
    "iso:country":"AT",
    "sg:address":"Maistatt 451",
    "sg:city":"Schladming",
    "sg:orig_category":"Fotografen",
    "sg:phone":"+43 4336 8723665",
    "sg:postcode":"8970",
    "sg:province":"Steiermark",
    "wof:name":"Eitzinger Hildegard",
    "wof:placetype":"venue"
},
  "geometry": {"coordinates":[13.6925163269,47.3930587769],"type":"Point"}
}