{
  "type": "Feature",
  "properties": {
    "addr:full":"Nr 6 Hatzendorf Steiermark 8361",
    "addr:postcode":"8361",
    "addr:street":"Nr",
    "iso:country":"AT",
    "sg:address":"Nr 6",
    "sg:city":"Hatzendorf",
    "sg:orig_category":"Bankomat-Standorte",
    "sg:phone":"+43 3155 23420",
    "sg:postcode":"8361",
    "sg:province":"Steiermark",
    "wof:name":"Bankomat d Raiffeisenbank Hatzendorf-Unterlamm",
    "wof:placetype":"venue"
},
  "geometry": {"coordinates":[16.0021743774,46.9774932861],"type":"Point"}
}