{
  "type": "Feature",
  "properties": {
    "addr:full":"Gabelsbergerstr 15 Salzburg Salzburg 5020",
    "addr:housenumber":"15",
    "addr:postcode":"5020",
    "addr:street":"Gabelsbergerstr;Salzburg",
    "iso:country":"AT",
    "sg:address":"Gabelsbergerstr 15",
    "sg:city":"Salzburg",
    "sg:orig_category":"Messerschmiede",
    "sg:phone":"+43 4369 911806866",
    "sg:postcode":"5020",
    "sg:province":"Salzburg",
    "wof:name":"Kappeller Richard",
    "wof:placetype":"venue"
},
  "geometry": {"coordinates":[13.0486021042,47.809173584],"type":"Point"}
}