{
  "type": "Feature",
  "properties": {
    "addr:full":"Rathauspl 1 Gmunden Ober\u00f6sterreich 4810",
    "addr:housenumber":"1",
    "addr:postcode":"4810",
    "addr:street":"Rathauspl;Oberoesterreich",
    "iso:country":"AT",
    "sg:address":"Rathauspl 1",
    "sg:city":"Gmunden",
    "sg:orig_category":"Papier- U Schreibwaren / Einzelhandel",
    "sg:phone":"+43 4376 12641180",
    "sg:postcode":"4810",
    "sg:province":"Ober\u00f6sterreich",
    "wof:name":"B\u00fcroprofi - Meingast Papier GesmbH & Co KG",
    "wof:placetype":"venue"
},
  "geometry": {"coordinates":[13.7995042801,47.9180450439],"type":"Point"}
}