{
  "type": "Feature",
  "properties": {
    "addr:full":"Murbergstr 15-17 Fernitz Steiermark 8072",
    "addr:postcode":"8072",
    "iso:country":"AT",
    "sg:address":"Murbergstr 15-17",
    "sg:city":"Fernitz",
    "sg:orig_category":"Autohandel",
    "sg:phone":"+43 3135 556930",
    "sg:postcode":"8072",
    "sg:province":"Steiermark",
    "wof:name":"Fritz KEG",
    "wof:placetype":"venue"
},
  "geometry": {"coordinates":[15.5000247955,46.9708137512],"type":"Point"}
}