{
  "type": "Feature",
  "properties": {
    "iso:country":"AT",
    "sg:address":"Schillerstr 2",
    "sg:city":"Graz",
    "sg:orig_category":"Restaurants: Chinesisch",
    "sg:phone":"+43 316 381236",
    "sg:postcode":"8010",
    "sg:province":"Steiermark",
    "wof:name":"China-Restaurant Yongle",
    "wof:placetype":"venue"
},
  "geometry": {"coordinates":[15.4506969452,47.07188797],"type":"Point"}
}