{
  "type": "Feature",
  "properties": {
    "iso:country":"AT",
    "sg:address":"Saarpl 17/2",
    "sg:city":"Wien",
    "sg:classifiers":[
        {
            "category":"Home & Garden",
            "subcategory":"Building Materials",
            "type":"Retail Goods"
        }
    ],
    "sg:phone":"+43 4313 691660",
    "sg:postcode":"1190",
    "sg:province":"Wien",
    "sg:tags":[
        "baustoffe",
        "-material",
        "u"
    ],
    "wof:name":"GIG Gangl Internationale Granite Gro\u00dfhandelsgesmbH",
    "wof:placetype":"venue"
},
  "geometry": {"coordinates":[16.3486404419,48.2449798584],"type":"Point"}
}