{
  "type": "Feature",
  "properties": {
    "addr:full":"Turracher Str 24 Feldkirchen in K\u00e4rnten K\u00e4rnten 9560",
    "addr:postcode":"9560",
    "addr:street":"Str 24;Kaernten",
    "iso:country":"AT",
    "sg:address":"Turracher Str 24",
    "sg:city":"Feldkirchen in K\u00e4rnten",
    "sg:classifiers":[
        {
            "category":"Travel",
            "subcategory":"Hotels & Motels",
            "type":"Entertainment"
        }
    ],
    "sg:phone":"+43 4342 762145",
    "sg:postcode":"9560",
    "sg:province":"K\u00e4rnten",
    "wof:name":"Hotel-Restaurant Brandst\u00e4tter",
    "wof:placetype":"venue"
},
  "geometry": {"coordinates":[14.0791110992,46.7320327759],"type":"Point"}
}