{
  "type": "Feature",
  "properties": {
    "addr:full":"Geiselbergstr 49 Wien Wien 1110",
    "addr:housenumber":"49",
    "addr:postcode":"1110",
    "addr:street":"Geiselbergstr",
    "iso:country":"AT",
    "sg:address":"Geiselbergstr 49",
    "sg:city":"Wien",
    "sg:orig_category":"Lebensmittel / Einzelhandel",
    "sg:phone":"+43 4317 492639",
    "sg:postcode":"1110",
    "sg:province":"Wien",
    "wof:name":"Plus Markt",
    "wof:placetype":"venue"
},
  "geometry": {"coordinates":[16.4083271027,48.1747741699],"type":"Point"}
}