{
  "type": "Feature",
  "properties": {
    "iso:country":"AT",
    "sg:address":"Hamburger Str 9",
    "sg:city":"Wien",
    "sg:orig_category":"Ingenieurkonsulenten / Zivilingenieure",
    "sg:phone":"+43 1 589900",
    "sg:postcode":"1050",
    "sg:province":"Wien",
    "wof:name":"P\u00f6rner + Partner Zilviltechniker-GesmbH",
    "wof:placetype":"venue"
},
  "geometry": {"coordinates":[16.3563518524,48.1955528259],"type":"Point"}
}