{
  "type": "Feature",
  "properties": {
    "addr:full":"Baumgartenberg 76 Baumgartenberg Ober\u00f6sterreich 4342",
    "addr:housenumber":"76",
    "addr:postcode":"4342",
    "addr:street":"Baumgartenberg",
    "iso:country":"AT",
    "sg:address":"Baumgartenberg 76",
    "sg:city":"Baumgartenberg",
    "sg:classifiers":[
        {
            "category":"Home & Garden",
            "subcategory":"Building Materials",
            "type":"Retail Goods"
        }
    ],
    "sg:phone":"+43 7269 4320",
    "sg:postcode":"4342",
    "sg:province":"Ober\u00f6sterreich",
    "sg:tags":[
        "plumbing",
        "ceramic",
        "fixture"
    ],
    "sg:website":"grillenberger.com",
    "wof:name":"Ernst Grillenberger GmbH",
    "wof:placetype":"venue"
},
  "geometry": {"coordinates":[14.7457637787,48.2091178894],"type":"Point"}
}