{
  "type": "Feature",
  "properties": {
    "addr:full":"Murauer Str 6a Scheifling Steiermark 8811",
    "addr:postcode":"8811",
    "addr:street":"Str 6A",
    "iso:country":"AT",
    "sg:address":"Murauer Str 6a",
    "sg:city":"Scheifling",
    "sg:orig_category":"Metallbau",
    "sg:phone":"+43 3582 20002",
    "sg:postcode":"8811",
    "sg:province":"Steiermark",
    "wof:name":"Schneider Erich",
    "wof:placetype":"venue"
},
  "geometry": {"coordinates":[14.4099206924,47.1534347534],"type":"Point"}
}