{
  "type": "Feature",
  "properties": {
    "addr:full":"Parkring 6 Lebring Steiermark 8403",
    "addr:housenumber":"6",
    "addr:postcode":"8403",
    "addr:street":"Parkring",
    "iso:country":"AT",
    "sg:address":"Parkring 6",
    "sg:city":"Lebring",
    "sg:orig_category":"Werbeagenturen",
    "sg:phone":"+43 4331 8252050",
    "sg:postcode":"8403",
    "sg:province":"Steiermark",
    "wof:name":"BGD Beschriftung-Grafik-Druck",
    "wof:placetype":"venue"
},
  "geometry": {"coordinates":[15.5279312134,46.8512229919],"type":"Point"}
}