{
  "type": "Feature",
  "properties": {
    "iso:country":"AT",
    "sg:address":"Nr 94",
    "sg:city":"Lavam\u00fcnd",
    "sg:orig_category":"Waschmaschinen / Reparatur",
    "sg:phone":"+43 4356 2834",
    "sg:postcode":"9473",
    "sg:province":"K\u00e4rnten",
    "wof:name":"Grubelnig Hartwig",
    "wof:placetype":"venue"
},
  "geometry": {"coordinates":[14.9413080215,46.6418952942],"type":"Point"}
}