{
  "type": "Feature",
  "properties": {
    "addr:full":"Mariazeller Str 1 Kapfenberg Steiermark 8605",
    "addr:housenumber":"1",
    "addr:postcode":"8605",
    "addr:street":"Str",
    "iso:country":"AT",
    "sg:address":"Mariazeller Str 1",
    "sg:city":"Kapfenberg",
    "sg:orig_category":"Ingenieurkonsulenten / Zivilingenieure",
    "sg:phone":"+43 3862 234560",
    "sg:postcode":"8605",
    "sg:province":"Steiermark",
    "sg:website":"apb-plank.at",
    "wof:name":"Plank-Bachselten Andreas Dipl-Ing Ziviltechniker KEG",
    "wof:placetype":"venue"
},
  "geometry": {"coordinates":[15.2894620895,47.4434967041],"type":"Point"}
}