{
  "type": "Feature",
  "properties": {
    "addr:full":"Hauptpl 26 Gm\u00fcnd K\u00e4rnten 9853",
    "addr:housenumber":"26",
    "addr:postcode":"9853",
    "addr:street":"Hauptpl;Kaernten",
    "iso:country":"AT",
    "sg:address":"Hauptpl 26",
    "sg:city":"Gm\u00fcnd",
    "sg:orig_category":"Textilreinigung",
    "sg:phone":"+43 4732 2130",
    "sg:postcode":"9853",
    "sg:province":"K\u00e4rnten",
    "wof:name":"Florian G\u00fcnter",
    "wof:placetype":"venue"
},
  "geometry": {"coordinates":[13.5356645584,46.9071617126],"type":"Point"}
}