{
  "type": "Feature",
  "properties": {
    "iso:country":"AT",
    "sg:address":"Meravigliag 2",
    "sg:city":"Wien",
    "sg:orig_category":"Elektroinstallationsunternehmen",
    "sg:phone":"+43 1 5961004",
    "sg:postcode":"1060",
    "sg:province":"Wien",
    "wof:name":"Paru ElektroinstallationsgesmbH",
    "wof:placetype":"venue"
},
  "geometry": {"coordinates":[16.3399238586,48.1902656555],"type":"Point"}
}