{
  "type": "Feature",
  "properties": {
    "addr:full":"Bl\u00fctenstr 15 Linz Ober\u00f6sterreich 4040",
    "addr:housenumber":"15",
    "addr:postcode":"4040",
    "addr:street":"Bluetenstr",
    "iso:country":"AT",
    "sg:address":"Bl\u00fctenstr 15",
    "sg:city":"Linz",
    "sg:classifiers":[
        {
            "category":"Restaurant",
            "type":"Food & Drink"
        }
    ],
    "sg:phone":"+43 4373 2732636",
    "sg:postcode":"4040",
    "sg:province":"Ober\u00f6sterreich",
    "wof:name":"GOLD K\u00dcSTE - Snacks u Meeresfr\u00fcchte - Fr\u00f6hlich Franz - Lentia 2000",
    "wof:placetype":"venue"
},
  "geometry": {"coordinates":[14.2578554153,48.3602561951],"type":"Point"}
}