{
  "type": "Feature",
  "properties": {
    "addr:full":"10.Oktober-Str 130 Obervellach K\u00e4rnten 9821",
    "addr:housenumber":"130",
    "addr:postcode":"9821",
    "addr:street":"Obervellach Kaernten",
    "iso:country":"AT",
    "sg:address":"10.Oktober-Str 130",
    "sg:city":"Obervellach",
    "sg:orig_category":"Autohandel",
    "sg:phone":"+43 4347 8220230",
    "sg:postcode":"9821",
    "sg:province":"K\u00e4rnten",
    "wof:name":"Autohaus Wulz Josef",
    "wof:placetype":"venue"
},
  "geometry": {"coordinates":[13.202000618,46.9322319031],"type":"Point"}
}