{
  "type": "Feature",
  "properties": {
    "addr:full":"Leitenstr 17 Lambach Ober\u00f6sterreich 4650",
    "addr:housenumber":"17",
    "addr:postcode":"4650",
    "addr:street":"Leitenstr",
    "iso:country":"AT",
    "sg:address":"Leitenstr 17",
    "sg:city":"Lambach",
    "sg:orig_category":"Fleischhauereien",
    "sg:phone":"+43 7245 288610",
    "sg:postcode":"4650",
    "sg:province":"Ober\u00f6sterreich",
    "wof:name":"Butz Martin",
    "wof:placetype":"venue"
},
  "geometry": {"coordinates":[13.873459816,48.0927314758],"type":"Point"}
}