{
  "type": "Feature",
  "properties": {
    "iso:country":"AT",
    "sg:address":"St Veiter Ring 27",
    "sg:city":"Klagenfurt",
    "sg:orig_category":"Bewachungsunternehmen",
    "sg:phone":"+43 463 54631",
    "sg:postcode":"9020",
    "sg:province":"K\u00e4rnten",
    "sg:website":"www.securitas.at",
    "wof:name":"Securitas Sicherheitsdienstleistungen GmbH",
    "wof:placetype":"venue"
},
  "geometry": {"coordinates":[14.308257103,46.6280403137],"type":"Point"}
}