{
  "type": "Feature",
  "properties": {
    "addr:full":"Rathauspl 43 Vorau Steiermark 8250",
    "addr:housenumber":"43",
    "addr:postcode":"8250",
    "addr:street":"Rathauspl",
    "iso:country":"AT",
    "sg:address":"Rathauspl 43",
    "sg:city":"Vorau",
    "sg:orig_category":"Gemeinden",
    "sg:phone":"+43 3337 22280",
    "sg:postcode":"8250",
    "sg:province":"Steiermark",
    "wof:name":"Marktgemeinde Vorau",
    "wof:placetype":"venue"
},
  "geometry": {"coordinates":[15.8885879517,47.4072494507],"type":"Point"}
}