{
  "type": "Feature",
  "properties": {
    "addr:full":"Dorfbahnstr 30 Serfaus Tirol 6534",
    "addr:housenumber":"30",
    "addr:postcode":"6534",
    "addr:street":"Dorfbahnstr;Tirol",
    "iso:country":"AT",
    "sg:address":"Dorfbahnstr 30",
    "sg:city":"Serfaus",
    "sg:orig_category":"Volksschulen",
    "sg:phone":"+43 5476 6582",
    "sg:postcode":"6534",
    "sg:province":"Tirol",
    "wof:name":"Volksschule",
    "wof:placetype":"venue"
},
  "geometry": {"coordinates":[10.6079416275,47.0384864807],"type":"Point"}
}