{
  "type": "Feature",
  "properties": {
    "iso:country":"AT",
    "sg:address":"Kaiser-Josef-Pl 50",
    "sg:city":"Wels",
    "sg:classifiers":[
        {
            "category":"Travel",
            "subcategory":"Hotels & Motels",
            "type":"Entertainment"
        }
    ],
    "sg:phone":"+43 7242 453610",
    "sg:postcode":"4600",
    "sg:province":"Ober\u00f6sterreich",
    "wof:name":"Hotel Greif Familie Pineker",
    "wof:placetype":"venue"
},
  "geometry": {"coordinates":[14.0240631104,48.1599121094],"type":"Point"}
}