{
  "type": "Feature",
  "properties": {
    "iso:country":"AT",
    "sg:address":"Babenbergerstr 4",
    "sg:city":"Lilienfeld",
    "sg:orig_category":"Psychotherapie",
    "sg:phone":"+43 699 12186481",
    "sg:postcode":"3180",
    "sg:province":"Nieder\u00f6sterreich",
    "wof:name":"Psychotherapeutische Praxis - Dipl-Ing Paul Hemmelmayr",
    "wof:placetype":"venue"
},
  "geometry": {"coordinates":[15.5958795547,48.0140991211],"type":"Point"}
}