{
  "type": "Feature",
  "properties": {
    "addr:full":"B\u00e4ckerg 16 Kritzendorf Nieder\u00f6sterreich 3420",
    "addr:housenumber":"16",
    "addr:postcode":"3420",
    "addr:street":"Baeckerg",
    "iso:country":"AT",
    "sg:address":"B\u00e4ckerg 16",
    "sg:city":"Kritzendorf",
    "sg:orig_category":"Abschleppdienste",
    "sg:phone":"+43 2243 26207",
    "sg:postcode":"3420",
    "sg:province":"Nieder\u00f6sterreich",
    "wof:name":"Vaclavek Helmut",
    "wof:placetype":"venue"
},
  "geometry": {"coordinates":[16.3065757751,48.3242492676],"type":"Point"}
}