{
  "type": "Feature",
  "properties": {
    "iso:country":"AT",
    "sg:address":"Nr 5",
    "sg:city":"Oberdrauburg",
    "sg:orig_category":"Polizei U Gendarmerie",
    "sg:phone":"+43 4359 1332231",
    "sg:postcode":"9781",
    "sg:province":"K\u00e4rnten",
    "wof:name":"Gendarmerie",
    "wof:placetype":"venue"
},
  "geometry": {"coordinates":[12.9699554443,46.7482910156],"type":"Point"}
}