{
  "type": "Feature",
  "properties": {
    "addr:full":"Zieglerg 2 Wien Wien 1070",
    "addr:housenumber":"2",
    "addr:postcode":"1070",
    "addr:street":"Zieglerg",
    "iso:country":"AT",
    "sg:address":"Zieglerg 2",
    "sg:city":"Wien",
    "sg:orig_category":"Tabaktrafiken",
    "sg:phone":"+43 1 5262246",
    "sg:postcode":"1070",
    "sg:province":"Wien",
    "wof:name":"Trisko Paul",
    "wof:placetype":"venue"
},
  "geometry": {"coordinates":[16.3459911346,48.1974334717],"type":"Point"}
}