{
  "type": "Feature",
  "properties": {
    "addr:full":"Priesterbauerweg 24 Hallein Salzburg 5400",
    "addr:housenumber":"24",
    "addr:postcode":"5400",
    "addr:street":"Priesterbauerweg;Salzburg",
    "iso:country":"AT",
    "sg:address":"Priesterbauerweg 24",
    "sg:city":"Hallein",
    "sg:orig_category":"Ergotherapie",
    "sg:phone":"+43 4362 4587550",
    "sg:postcode":"5400",
    "sg:province":"Salzburg",
    "wof:name":"B\u00f6schinger Eva Dipl-ET",
    "wof:placetype":"venue"
},
  "geometry": {"coordinates":[13.0695962906,47.7068634033],"type":"Point"}
}