{
  "type": "Feature",
  "properties": {
    "addr:full":"Hauptstr 97 Oggau Burgenland 7063",
    "addr:housenumber":"97",
    "addr:postcode":"7063",
    "addr:street":"Hauptstr",
    "iso:country":"AT",
    "sg:address":"Hauptstr 97",
    "sg:city":"Oggau",
    "sg:orig_category":"Kinderbetreuung",
    "sg:phone":"+43 2685 7245",
    "sg:postcode":"7063",
    "sg:province":"Burgenland",
    "wof:name":"Kindergarten d r\u00f6misch-katholischen Pfarre Oggau",
    "wof:placetype":"venue"
},
  "geometry": {"coordinates":[16.6610412598,47.8313179016],"type":"Point"}
}