{
  "type": "Feature",
  "properties": {
    "addr:full":"Schl\u00e4gl 1 Aigen im M\u00fchlkreis Ober\u00f6sterreich 4160",
    "addr:housenumber":"1",
    "addr:postcode":"4160",
    "addr:street":"Schlaegl",
    "iso:country":"AT",
    "sg:address":"Schl\u00e4gl 1",
    "sg:city":"Aigen im M\u00fchlkreis",
    "sg:classifiers":[
        {
            "category":"Food & Beverages",
            "subcategory":"Groceries & Convenience Stores",
            "type":"Retail Goods"
        }
    ],
    "sg:phone":"+43 4372 8188010",
    "sg:postcode":"4160",
    "sg:province":"Ober\u00f6sterreich",
    "sg:tags":[
        "drink"
    ],
    "wof:name":"STIFTSBRAUEREI SCHL\u00c4GL",
    "wof:placetype":"venue"
},
  "geometry": {"coordinates":[13.9716520309,48.6466369629],"type":"Point"}
}