{
  "type": "Feature",
  "properties": {
    "addr:full":"Stra\u00df 32 Alkoven Ober\u00f6sterreich 4072",
    "addr:housenumber":"32",
    "addr:postcode":"4072",
    "addr:street":"Strass",
    "iso:country":"AT",
    "sg:address":"Stra\u00df 32",
    "sg:city":"Alkoven",
    "sg:orig_category":"Bolts, Galvanized",
    "sg:phone":"+43 7272 24930",
    "sg:postcode":"4072",
    "sg:province":"Ober\u00f6sterreich",
    "sg:website":"obermoser.com",
    "wof:name":"Obermoser Fendrich GmbH & Co KG",
    "wof:placetype":"venue"
},
  "geometry": {"coordinates":[14.0595092773,48.2893333435],"type":"Point"}
}