{
  "type": "Feature",
  "properties": {
    "addr:full":"K\u00e4rntner Strasse 7 Wien Wien 1010",
    "addr:housenumber":"7",
    "addr:postcode":"1010",
    "addr:street":"Kaerntner Strasse",
    "iso:country":"AT",
    "sg:address":"K\u00e4rntner Strasse 7",
    "sg:city":"Wien",
    "sg:orig_category":"Antimony Trisulphide",
    "sg:phone":"+43 1 51256110",
    "sg:postcode":"1010",
    "sg:province":"Wien",
    "sg:website":"chemetall.at",
    "wof:name":"CHEMETALL Ges.m.b.H.",
    "wof:placetype":"venue"
},
  "geometry": {"coordinates":[16.3718681335,48.2074127197],"type":"Point"}
}