{
  "type": "Feature",
  "properties": {
    "iso:country":"AT",
    "sg:address":"G\u00f6glstr 11",
    "sg:city":"Krems an der Donau",
    "sg:orig_category":"Lederwaren / Einzelhandel",
    "sg:phone":"+43 2732 77316",
    "sg:postcode":"3500",
    "sg:province":"Nieder\u00f6sterreich",
    "wof:name":"Hausmann Georg KG",
    "wof:placetype":"venue"
},
  "geometry": {"coordinates":[15.5965108871,48.4088058472],"type":"Point"}
}