{
  "type": "Feature",
  "properties": {
    "addr:full":"Bergmanngasse 43 Graz Steiermark 8010",
    "addr:housenumber":"43",
    "addr:postcode":"8010",
    "addr:street":"Bergmanngasse",
    "iso:country":"AT",
    "sg:address":"Bergmanngasse 43",
    "sg:city":"Graz",
    "sg:classifiers":[
        {
            "category":"Organizations",
            "subcategory":"Non-profit Organization",
            "type":"Services"
        }
    ],
    "sg:phone":"+43 316 6735350",
    "sg:postcode":"8010",
    "sg:province":"Steiermark",
    "sg:tags":[
        "alarm",
        "system"
    ],
    "sg:website":"slanina.at",
    "wof:name":"Slanina + Partner Elektrotechnik GmbH",
    "wof:placetype":"venue"
},
  "geometry": {"coordinates":[15.4392147064,47.0829238892],"type":"Point"}
}