{
  "type": "Feature",
  "properties": {
    "addr:full":"Nr 7 Tainach K\u00e4rnten 9121",
    "addr:postcode":"9121",
    "addr:street":"Nr;Tainach",
    "iso:country":"AT",
    "sg:address":"Nr 7",
    "sg:city":"Tainach",
    "sg:orig_category":"Maler, Anstreicher U Lackierer",
    "sg:phone":"+43 4224 81352",
    "sg:postcode":"9121",
    "sg:province":"K\u00e4rnten",
    "wof:name":"B\u00fcrger Balthasar",
    "wof:placetype":"venue"
},
  "geometry": {"coordinates":[14.5084590912,46.6561851501],"type":"Point"}
}