{
  "type": "Feature",
  "properties": {
    "addr:full":"Nr 2 St. Michael in Obersteiermark Steiermark 8770",
    "addr:housenumber":"2",
    "addr:postcode":"8770",
    "addr:street":"Nr",
    "iso:country":"AT",
    "sg:address":"Nr 2",
    "sg:city":"St. Michael in Obersteiermark",
    "sg:orig_category":"Autohandel",
    "sg:phone":"+43 3843 3632",
    "sg:postcode":"8770",
    "sg:province":"Steiermark",
    "wof:name":"Jessner Michaela",
    "wof:placetype":"venue"
},
  "geometry": {"coordinates":[15.0202636719,47.3367919922],"type":"Point"}
}