{
  "type": "Feature",
  "properties": {
    "iso:country":"AT",
    "sg:address":"Nr 25",
    "sg:city":"Hirschegg",
    "sg:orig_category":"Banken U Sparkassen",
    "sg:phone":"+43 3141 40040",
    "sg:postcode":"8584",
    "sg:province":"Steiermark",
    "wof:name":"Raiffeisenbank Edelschrott regGenmbH",
    "wof:placetype":"venue"
},
  "geometry": {"coordinates":[14.9580583572,47.0195808411],"type":"Point"}
}