{
  "type": "Feature",
  "properties": {
    "addr:full":"Hugo-Wolf-G 2-4 Graz Steiermark 8010",
    "addr:housenumber":"2-4",
    "addr:postcode":"8010",
    "addr:street":"Hugo-Wolf-G",
    "iso:country":"AT",
    "sg:address":"Hugo-Wolf-G 2-4",
    "sg:city":"Graz",
    "sg:orig_category":"Sanatorien",
    "sg:phone":"+43 316 36320",
    "sg:postcode":"8010",
    "sg:province":"Steiermark",
    "wof:name":"Sanatorium Dr Hoff",
    "wof:placetype":"venue"
},
  "geometry": {"coordinates":[15.4492921829,47.0755310059],"type":"Point"}
}