{
  "type": "Feature",
  "properties": {
    "addr:full":"Mittlere Hauptstr 43 Nickelsdorf Burgenland 2425",
    "addr:housenumber":"43",
    "addr:postcode":"2425",
    "addr:street":"Mittlere Hauptstr",
    "iso:country":"AT",
    "sg:address":"Mittlere Hauptstr 43",
    "sg:city":"Nickelsdorf",
    "sg:orig_category":"Massagen",
    "sg:phone":"+43 2146 3176",
    "sg:postcode":"2425",
    "sg:province":"Burgenland",
    "wof:name":"Pscheiden jun Rudolf",
    "wof:placetype":"venue"
},
  "geometry": {"coordinates":[17.0723075867,47.93957901],"type":"Point"}
}