{
  "type": "Feature",
  "properties": {
    "addr:full":"Erlachg 73 Wien Wien 1100",
    "addr:housenumber":"73",
    "addr:postcode":"1100",
    "addr:street":"Erlachg",
    "iso:country":"AT",
    "sg:address":"Erlachg 73",
    "sg:city":"Wien",
    "sg:orig_category":"Maler, Anstreicher U Lackierer",
    "sg:phone":"+43 1 5973500",
    "sg:postcode":"1100",
    "sg:province":"Wien",
    "wof:name":"St\u00fctzinger Malerei KEG",
    "wof:placetype":"venue"
},
  "geometry": {"coordinates":[16.3810844421,48.1766014099],"type":"Point"}
}