{
  "type": "Feature",
  "properties": {
    "iso:country":"AT",
    "sg:address":"Quellenstr 104",
    "sg:city":"Wien",
    "sg:orig_category":"Telekommunikation",
    "sg:phone":"+43 1 6072300",
    "sg:postcode":"1100",
    "sg:province":"Wien",
    "wof:name":"City Call",
    "wof:placetype":"venue"
},
  "geometry": {"coordinates":[16.3688697815,48.1760749817],"type":"Point"}
}