{
  "type": "Feature",
  "properties": {
    "addr:full":"Waldkirchener Strasse 2-4 Dobersberg Nieder\u00f6sterreich 3843",
    "addr:housenumber":"2-4",
    "addr:postcode":"3843",
    "addr:street":"Waldkirchener Strasse",
    "iso:country":"AT",
    "sg:address":"Waldkirchener Strasse 2-4",
    "sg:city":"Dobersberg",
    "sg:classifiers":[
        {
            "category":"Manufacturing",
            "subcategory":"Furniture",
            "type":"Manufacturing & Wholesale Goods"
        }
    ],
    "sg:phone":"+43 2843 2253",
    "sg:postcode":"3843",
    "sg:province":"Nieder\u00f6sterreich",
    "sg:tags":[
        "beech"
    ],
    "sg:website":"handl.co.at",
    "wof:name":"Lambert Handl",
    "wof:placetype":"venue"
},
  "geometry": {"coordinates":[15.3222408295,48.9154167175],"type":"Point"}
}