{
  "type": "Feature",
  "properties": {
    "addr:full":"Gro\u00dfreith 5 Ohlsdorf Ober\u00f6sterreich 4694",
    "addr:housenumber":"5",
    "addr:postcode":"4694",
    "addr:street":"Grossreith",
    "iso:country":"AT",
    "sg:address":"Gro\u00dfreith 5",
    "sg:city":"Ohlsdorf",
    "sg:orig_category":"Erdarbeiten",
    "sg:phone":"+43 761247703",
    "sg:postcode":"4694",
    "sg:province":"Ober\u00f6sterreich",
    "wof:name":"Preinstorfer Gerhard",
    "wof:placetype":"venue"
},
  "geometry": {"coordinates":[13.757434845,47.9806900024],"type":"Point"}
}