{
  "type": "Feature",
  "properties": {
    "addr:full":"Gaglhamer Weg 50 Bergheim Salzburg 5101",
    "addr:housenumber":"50",
    "addr:postcode":"5101",
    "addr:street":"Gaglhamer Weg;Salzburg",
    "iso:country":"AT",
    "sg:address":"Gaglhamer Weg 50",
    "sg:city":"Bergheim",
    "sg:classifiers":[
        {
            "category":"Building & Trades",
            "subcategory":"Plumbing",
            "type":"Services"
        }
    ],
    "sg:phone":"+43 662 455815",
    "sg:postcode":"5101",
    "sg:province":"Salzburg",
    "sg:tags":[
        "supraregional",
        "gas"
    ],
    "wof:name":"Anim Th\u00f6ni Sanit\u00e4r-, Gas- und Heizungsinstallationen KEG und Personalleasing",
    "wof:placetype":"venue"
},
  "geometry": {"coordinates":[13.0478477478,47.8325767517],"type":"Point"}
}