{
  "type": "Feature",
  "properties": {
    "iso:country":"AT",
    "sg:address":"Industriegel\u00e4nde 1",
    "sg:city":"Wulkaprodersdorf",
    "sg:orig_category":"Transportunternehmen",
    "sg:phone":"+43 2687 62700",
    "sg:postcode":"7041",
    "sg:province":"Burgenland",
    "wof:name":"Tarrody Martin",
    "wof:placetype":"venue"
},
  "geometry": {"coordinates":[16.4992961884,47.806854248],"type":"Point"}
}