{
  "type": "Feature",
  "properties": {
    "addr:full":"Schachenbichlweg 21 Flachau Salzburg 5542",
    "addr:housenumber":"21",
    "addr:postcode":"5542",
    "addr:street":"Schachenbichlweg;Salzburg",
    "iso:country":"AT",
    "sg:address":"Schachenbichlweg 21",
    "sg:city":"Flachau",
    "sg:orig_category":"Appartements / Ferienwohnungen",
    "sg:phone":"+43 4364 572411",
    "sg:postcode":"5542",
    "sg:province":"Salzburg",
    "wof:name":"Steger Franz und Gertrude",
    "wof:placetype":"venue"
},
  "geometry": {"coordinates":[13.3896446228,47.3838882446],"type":"Point"}
}