{
  "type": "Feature",
  "properties": {
    "iso:country":"AT",
    "sg:address":"Bahnhofpl 4",
    "sg:city":"Wolfsberg",
    "sg:orig_category":"Elektroinstallationsunternehmen",
    "sg:phone":"+43 4352 2293",
    "sg:postcode":"9400",
    "sg:province":"K\u00e4rnten",
    "wof:name":"Dohr Walter",
    "wof:placetype":"venue"
},
  "geometry": {"coordinates":[14.8394517899,46.8415641785],"type":"Point"}
}