{
  "type": "Feature",
  "properties": {
    "addr:full":"Mozartstr 6 Perg Ober\u00f6sterreich 4320",
    "addr:housenumber":"6",
    "addr:postcode":"4320",
    "addr:street":"Mozartstr",
    "iso:country":"AT",
    "sg:address":"Mozartstr 6",
    "sg:city":"Perg",
    "sg:orig_category":"Volksschulen",
    "sg:phone":"+43 7262 525321",
    "sg:postcode":"4320",
    "sg:province":"Ober\u00f6sterreich",
    "wof:name":"Volksschule",
    "wof:placetype":"venue"
},
  "geometry": {"coordinates":[14.636967659,48.2472496033],"type":"Point"}
}