{
  "type": "Feature",
  "properties": {
    "iso:country":"AT",
    "sg:address":"Wilhelmstr 30",
    "sg:city":"Tulln an der Donau",
    "sg:orig_category":"Tabaktrafiken",
    "sg:phone":"+43 2272 65575",
    "sg:postcode":"3430",
    "sg:province":"Nieder\u00f6sterreich",
    "wof:name":"Trofeit Karl",
    "wof:placetype":"venue"
},
  "geometry": {"coordinates":[16.0570392609,48.3299293518],"type":"Point"}
}