{
  "type": "Feature",
  "properties": {
    "addr:full":"Mayrhofen Tirol 6290",
    "addr:postcode":"6290",
    "addr:street":"Mayrhofen Tirol",
    "iso:country":"AT",
    "sg:city":"Mayrhofen",
    "sg:orig_category":"Elektroinstallationsunternehmen",
    "sg:phone":"+43 5285 64206",
    "sg:postcode":"6290",
    "sg:province":"Tirol",
    "wof:name":"Sporer Elektrotechnik GesmbH",
    "wof:placetype":"venue"
},
  "geometry": {"coordinates":[11.8624277115,47.1670684814],"type":"Point"}
}