{
  "type": "Feature",
  "properties": {
    "addr:full":"Leopold-Werndl-Str 2 City Point Steyr EG Steyr Ober\u00f6sterreich 4400",
    "addr:housenumber":"2",
    "addr:postcode":"4400",
    "addr:street":"Leopold-Werndl-Str;Point;Oberoesterreich",
    "iso:country":"AT",
    "sg:address":"Leopold-Werndl-Str 2 City Point Steyr EG",
    "sg:city":"Steyr",
    "sg:orig_category":"Damenmoden",
    "sg:phone":"+43 4372 5245217",
    "sg:postcode":"4400",
    "sg:province":"Ober\u00f6sterreich",
    "wof:name":"H & M Hennes & Mauritz GesmbH",
    "wof:placetype":"venue"
},
  "geometry": {"coordinates":[14.4193296432,48.0391807556],"type":"Point"}
}