{
  "type": "Feature",
  "properties": {
    "addr:full":"Grashofg 4 Wien Wien 1010",
    "addr:housenumber":"4",
    "addr:postcode":"1010",
    "addr:street":"Grashofg",
    "iso:country":"AT",
    "sg:address":"Grashofg 4",
    "sg:city":"Wien",
    "sg:classifiers":[
        {
            "category":"Restaurant",
            "type":"Food & Drink"
        }
    ],
    "sg:phone":"+43 1 5138218",
    "sg:postcode":"1010",
    "sg:province":"Wien",
    "wof:name":"Palatschinken-Pfandl",
    "wof:placetype":"venue"
},
  "geometry": {"coordinates":[16.37591362,48.2102012634],"type":"Point"}
}