{
  "type": "Feature",
  "properties": {
    "addr:full":"Heizhausg 12 Bruck an der Leitha Nieder\u00f6sterreich 2460",
    "addr:housenumber":"12",
    "addr:postcode":"2460",
    "addr:street":"Heizhausg",
    "iso:country":"AT",
    "sg:address":"Heizhausg 12",
    "sg:city":"Bruck an der Leitha",
    "sg:orig_category":"Garten- U Landschaftsgestaltung",
    "sg:phone":"+43 664 4156091",
    "sg:postcode":"2460",
    "sg:province":"Nieder\u00f6sterreich",
    "wof:name":"die Landschaftsplaner.at",
    "wof:placetype":"venue"
},
  "geometry": {"coordinates":[16.7836074829,48.0198783875],"type":"Point"}
}