{
  "type": "Feature",
  "properties": {
    "addr:full":"Kagraner Pl 33 Wien Wien 1220",
    "addr:housenumber":"33",
    "addr:postcode":"1220",
    "addr:street":"Kagraner Pl",
    "iso:country":"AT",
    "sg:address":"Kagraner Pl 33",
    "sg:city":"Wien",
    "sg:classifiers":[
        {
            "category":"Restaurant",
            "type":"Food & Drink"
        }
    ],
    "sg:phone":"+43 1 2033400",
    "sg:postcode":"1220",
    "sg:province":"Wien",
    "wof:name":"Restaurant Napoleon",
    "wof:placetype":"venue"
},
  "geometry": {"coordinates":[16.4492797852,48.2483787537],"type":"Point"}
}