{
  "type": "Feature",
  "properties": {
    "iso:country":"AT",
    "sg:address":"Nr 45",
    "sg:city":"Freistadt",
    "sg:orig_category":"Banken U Sparkassen",
    "sg:phone":"+43 7942 82940",
    "sg:postcode":"4240",
    "sg:province":"Ober\u00f6sterreich",
    "wof:name":"Raiffeisenbank Waldburg regGenmbH",
    "wof:placetype":"venue"
},
  "geometry": {"coordinates":[14.5049953461,48.5119857788],"type":"Point"}
}