{
  "type": "Feature",
  "properties": {
    "addr:full":"Terminalstr 100 Wels Ober\u00f6sterreich 4600",
    "addr:housenumber":"100",
    "addr:postcode":"4600",
    "addr:street":"Oberoesterreich",
    "iso:country":"AT",
    "sg:address":"Terminalstr 100",
    "sg:city":"Wels",
    "sg:orig_category":"Paketdienste",
    "sg:phone":"+43 7242 930001351",
    "sg:postcode":"4600",
    "sg:province":"Ober\u00f6sterreich",
    "wof:name":"\u00f6BB-G\u00fcterverkehr - Rail Cargo Austria",
    "wof:placetype":"venue"
},
  "geometry": {"coordinates":[14.0729207993,48.18932724],"type":"Point"}
}