{
  "type": "Feature",
  "properties": {
    "iso:country":"AT",
    "sg:address":"Brucknerstr 8",
    "sg:city":"Perg",
    "sg:orig_category":"Blumeneinzelhandel",
    "sg:phone":"+43 4372 6253864",
    "sg:postcode":"4320",
    "sg:province":"Ober\u00f6sterreich",
    "wof:name":"Gartencenter und Dienstleistungs-GmbH",
    "wof:placetype":"venue"
},
  "geometry": {"coordinates":[14.6303691864,48.2477684021],"type":"Point"}
}