{
  "type": "Feature",
  "properties": {
    "addr:full":"Pulverturmg 4 Bregenz Vorarlberg 6900",
    "addr:housenumber":"4",
    "addr:postcode":"6900",
    "addr:street":"Pulverturmg",
    "iso:country":"AT",
    "sg:address":"Pulverturmg 4",
    "sg:city":"Bregenz",
    "sg:orig_category":"Textilwaren / Einzelhandel",
    "sg:phone":"+43 5574 48157",
    "sg:postcode":"6900",
    "sg:province":"Vorarlberg",
    "wof:name":"Hurrikan - M Bayer KG",
    "wof:placetype":"venue"
},
  "geometry": {"coordinates":[9.7334766388,47.4980239868],"type":"Point"}
}