{
  "type": "Feature",
  "properties": {
    "addr:full":"Handwerkstrasse 1 Berndorf Salzburg 5165",
    "addr:housenumber":"1",
    "addr:postcode":"5165",
    "addr:street":"Handwerkstrasse;Salzburg",
    "iso:country":"AT",
    "sg:address":"Handwerkstrasse 1",
    "sg:city":"Berndorf",
    "sg:classifiers":[
        {
            "category":"Manufacturing",
            "subcategory":"Wood Products",
            "type":"Manufacturing & Wholesale Goods"
        }
    ],
    "sg:phone":"+43 6217 8132",
    "sg:postcode":"5165",
    "sg:province":"Salzburg",
    "sg:tags":[
        "solid",
        "ceiling",
        "made",
        "panel"
    ],
    "wof:name":"Ludwig H\u00f6pflinger & Co KG",
    "wof:placetype":"venue"
},
  "geometry": {"coordinates":[13.0622205734,47.9974784851],"type":"Point"}
}