{
  "type": "Feature",
  "properties": {
    "addr:full":"Scheutz 14 Albrechtsberg an der Gro\u00dfen Krems Nieder\u00f6sterreich 3613",
    "addr:housenumber":"14",
    "addr:postcode":"3613",
    "addr:street":"Scheutz;An Der Grossen;Niederoesterreich",
    "iso:country":"AT",
    "sg:address":"Scheutz 14",
    "sg:city":"Albrechtsberg an der Gro\u00dfen Krems",
    "sg:orig_category":"Holzhandel",
    "sg:phone":"+43 2876 282",
    "sg:postcode":"3613",
    "sg:province":"Nieder\u00f6sterreich",
    "wof:name":"Wendlik Ernst",
    "wof:placetype":"venue"
},
  "geometry": {"coordinates":[15.3861055374,48.4792098999],"type":"Point"}
}