{
  "type": "Feature",
  "properties": {
    "addr:full":"Schottenfeldg 61 Wien Wien 1070",
    "addr:housenumber":"61",
    "addr:postcode":"1070",
    "addr:street":"Schottenfeldg",
    "iso:country":"AT",
    "sg:address":"Schottenfeldg 61",
    "sg:city":"Wien",
    "sg:orig_category":"Fotografen",
    "sg:phone":"+43 1 5226467",
    "sg:postcode":"1070",
    "sg:province":"Wien",
    "wof:name":"Houdek Christian",
    "wof:placetype":"venue"
},
  "geometry": {"coordinates":[16.3429450989,48.2031974792],"type":"Point"}
}