{
  "type": "Feature",
  "properties": {
    "iso:country":"AT",
    "sg:city":"Desselbrunn",
    "sg:orig_category":"Feuerwehren",
    "sg:phone":"+43 76735245",
    "sg:postcode":"4693",
    "sg:province":"Ober\u00f6sterreich",
    "wof:name":"Freiwillige Feuerwehr Windern",
    "wof:placetype":"venue"
},
  "geometry": {"coordinates":[13.791138649,48.0259399414],"type":"Point"}
}