{
  "type": "Feature",
  "properties": {
    "addr:full":"Wallackstr 12 Gunskirchen Ober\u00f6sterreich 4623",
    "addr:housenumber":"12",
    "addr:postcode":"4623",
    "addr:street":"Wallackstr",
    "iso:country":"AT",
    "sg:address":"Wallackstr 12",
    "sg:city":"Gunskirchen",
    "sg:orig_category":"Tischlereien",
    "sg:phone":"+43 7246 7878",
    "sg:postcode":"4623",
    "sg:province":"Ober\u00f6sterreich",
    "wof:name":"Lehner Johann",
    "wof:placetype":"venue"
},
  "geometry": {"coordinates":[13.9608812332,48.1370773315],"type":"Point"}
}