{
  "type": "Feature",
  "properties": {
    "addr:full":"Salmgasse 10 Wien Wien 1030",
    "addr:housenumber":"10",
    "addr:postcode":"1030",
    "addr:street":"Salmgasse",
    "iso:country":"AT",
    "sg:address":"Salmgasse 10",
    "sg:city":"Wien",
    "sg:classifiers":[
        {
            "category":"Professional",
            "subcategory":"Art Services",
            "type":"Services"
        }
    ],
    "sg:phone":"+43 1 7125265",
    "sg:postcode":"1030",
    "sg:province":"Wien",
    "sg:tags":[
        "concept",
        "design"
    ],
    "sg:website":"ploderer.at",
    "wof:name":"Ploderer & Partner",
    "wof:placetype":"venue"
},
  "geometry": {"coordinates":[16.3906478882,48.2040252686],"type":"Point"}
}