{
  "type": "Feature",
  "properties": {
    "addr:full":"Nr 80 Aistersheim Ober\u00f6sterreich 4676",
    "addr:postcode":"4676",
    "addr:street":"Nr;Aistersheim",
    "iso:country":"AT",
    "sg:address":"Nr 80",
    "sg:city":"Aistersheim",
    "sg:orig_category":"Psychotherapie",
    "sg:phone":"+43 7734 4030",
    "sg:postcode":"4676",
    "sg:province":"Ober\u00f6sterreich",
    "wof:name":"Mika Alfred Dr",
    "wof:placetype":"venue"
},
  "geometry": {"coordinates":[13.7416276932,48.1866836548],"type":"Point"}
}