{
  "type": "Feature",
  "properties": {
    "addr:full":"Atterseestr 32 Unterach am Attersee Ober\u00f6sterreich 4866",
    "addr:housenumber":"32",
    "addr:postcode":"4866",
    "addr:street":"Atterseestr",
    "iso:country":"AT",
    "sg:address":"Atterseestr 32",
    "sg:city":"Unterach am Attersee",
    "sg:orig_category":"Appartements / Ferienwohnungen",
    "sg:phone":"+43 76658454",
    "sg:postcode":"4866",
    "sg:province":"Ober\u00f6sterreich",
    "wof:name":"Ferienhof Bucherlhof Fam Stabauer und Strohmayer",
    "wof:placetype":"venue"
},
  "geometry": {"coordinates":[13.4867830276,47.8064651489],"type":"Point"}
}