{
  "type": "Feature",
  "properties": {
    "iso:country":"AT",
    "sg:address":"D\u00f6rnbacher Str 3-5",
    "sg:city":"Pasching",
    "sg:orig_category":"Maschinenbau",
    "sg:phone":"+43 7221 881550",
    "sg:postcode":"4061",
    "sg:province":"Ober\u00f6sterreich",
    "wof:name":"Augl Ernst GesmbH & Co KG",
    "wof:placetype":"venue"
},
  "geometry": {"coordinates":[14.2019853592,48.2585906982],"type":"Point"}
}