{
  "type": "Feature",
  "properties": {
    "iso:country":"AT",
    "sg:address":"Edith-Stein-Weg 5",
    "sg:city":"Innsbruck",
    "sg:orig_category":"Immobilienmakler",
    "sg:phone":"+43 4351 2379191",
    "sg:postcode":"6020",
    "sg:province":"Tirol",
    "wof:name":"Gratzel Johanna",
    "wof:placetype":"venue"
},
  "geometry": {"coordinates":[11.3979997635,47.259929657],"type":"Point"}
}