{
  "type": "Feature",
  "properties": {
    "addr:full":"Markt 220 Abtenau Salzburg 5441",
    "addr:housenumber":"220",
    "addr:postcode":"5441",
    "addr:street":"Markt;Salzburg",
    "iso:country":"AT",
    "sg:address":"Markt 220",
    "sg:city":"Abtenau",
    "sg:classifiers":[
        {
            "category":"Structure",
            "subcategory":"Building",
            "type":"Public Place"
        }
    ],
    "sg:phone":"+43 6243 2436",
    "sg:postcode":"5441",
    "sg:province":"Salzburg",
    "sg:tags":[
        "apartment"
    ],
    "sg:website":"auertech.at",
    "wof:name":"Martin Auer Technik zur Holzbearbeitung",
    "wof:placetype":"venue"
},
  "geometry": {"coordinates":[13.3385505676,47.5679168701],"type":"Point"}
}