{
  "type": "Feature",
  "properties": {
    "addr:full":"Pischeldorf K\u00e4rnten 9064",
    "addr:postcode":"9064",
    "iso:country":"AT",
    "sg:city":"Pischeldorf",
    "sg:orig_category":"Feuerwehren",
    "sg:phone":"+43 4224 2522",
    "sg:postcode":"9064",
    "sg:province":"K\u00e4rnten",
    "wof:name":"Feuerwache Ottmanach",
    "wof:placetype":"venue"
},
  "geometry": {"coordinates":[14.4581594467,46.6882362366],"type":"Point"}
}