{
  "type": "Feature",
  "properties": {
    "iso:country":"AT",
    "sg:address":"Obere Wei\u00dfgerberstr 10-12",
    "sg:city":"Wien",
    "sg:orig_category":"Bierdepots",
    "sg:phone":"+43 1 7135706",
    "sg:postcode":"1030",
    "sg:province":"Wien",
    "wof:name":"Zipfer-Bier Depot Marinits GmbH",
    "wof:placetype":"venue"
},
  "geometry": {"coordinates":[16.3885326385,48.2121772766],"type":"Point"}
}