{
  "type": "Feature",
  "properties": {
    "addr:full":"Wald 52 Faistenau Salzburg 5324",
    "addr:housenumber":"52",
    "addr:postcode":"5324",
    "addr:street":"Wald;Salzburg",
    "iso:country":"AT",
    "sg:address":"Wald 52",
    "sg:city":"Faistenau",
    "sg:orig_category":"Holzhandel",
    "sg:phone":"+43 664 5328179",
    "sg:postcode":"5324",
    "sg:province":"Salzburg",
    "wof:name":"Ebner Gerhard",
    "wof:placetype":"venue"
},
  "geometry": {"coordinates":[13.2332620621,47.7780952454],"type":"Point"}
}