{
  "type": "Feature",
  "properties": {
    "addr:full":"Opernring 16 Graz Steiermark 8010",
    "addr:housenumber":"16",
    "addr:postcode":"8010",
    "addr:street":"Opernring",
    "iso:country":"AT",
    "sg:address":"Opernring 16",
    "sg:city":"Graz",
    "sg:classifiers":[
        {
            "category":"Professional",
            "subcategory":"Computer Services",
            "type":"Services"
        }
    ],
    "sg:phone":"+43 316 820490",
    "sg:postcode":"8010",
    "sg:province":"Steiermark",
    "sg:tags":[
        "software"
    ],
    "wof:name":"Aperture Software GmbH",
    "wof:placetype":"venue"
},
  "geometry": {"coordinates":[15.4438667297,47.069103241],"type":"Point"}
}