{
  "type": "Feature",
  "properties": {
    "addr:full":"Bleichstattgasse 3 Ebensee Ober\u00f6sterreich 4802",
    "addr:housenumber":"3",
    "addr:postcode":"4802",
    "addr:street":"Bleichstattgasse",
    "iso:country":"AT",
    "sg:address":"Bleichstattgasse 3",
    "sg:city":"Ebensee",
    "sg:orig_category":"Biotopes",
    "sg:phone":"+43 6133 8091",
    "sg:postcode":"4802",
    "sg:province":"Ober\u00f6sterreich",
    "wof:name":"Manfred Reininger",
    "wof:placetype":"venue"
},
  "geometry": {"coordinates":[13.7688617706,47.8134918213],"type":"Point"}
}