{
  "type": "Feature",
  "properties": {
    "addr:full":"Greinerg 38 Wien Wien 1190",
    "addr:housenumber":"38",
    "addr:postcode":"1190",
    "addr:street":"Greinerg",
    "iso:country":"AT",
    "sg:address":"Greinerg 38",
    "sg:city":"Wien",
    "sg:orig_category":"Friseure U Frisiersalons",
    "sg:phone":"+43 1 3701255",
    "sg:postcode":"1190",
    "sg:province":"Wien",
    "wof:name":"Hartmaier Renate",
    "wof:placetype":"venue"
},
  "geometry": {"coordinates":[16.364906311,48.2593307495],"type":"Point"}
}