{
  "type": "Feature",
  "properties": {
    "addr:full":"Weinbergg 21 Podersdorf am See Burgenland 7141",
    "addr:housenumber":"21",
    "addr:postcode":"7141",
    "addr:street":"Weinbergg",
    "iso:country":"AT",
    "sg:address":"Weinbergg 21",
    "sg:city":"Podersdorf am See",
    "sg:orig_category":"Pensionen / Privatzimmer",
    "sg:phone":"+43 4321 773120",
    "sg:postcode":"7141",
    "sg:province":"Burgenland",
    "wof:name":"Fr\u00fchst\u00fcckspension Franz u Eleonora Zeisz",
    "wof:placetype":"venue"
},
  "geometry": {"coordinates":[16.8359355927,47.8577194214],"type":"Point"}
}