{
  "type": "Feature",
  "properties": {
    "addr:full":"Arbeiterg 15 Schattendorf Burgenland 7022",
    "addr:housenumber":"15",
    "addr:postcode":"7022",
    "addr:street":"Arbeiterg",
    "iso:country":"AT",
    "sg:address":"Arbeiterg 15",
    "sg:city":"Schattendorf",
    "sg:orig_category":"Gartenpflege",
    "sg:phone":"+43 4366 06563177",
    "sg:postcode":"7022",
    "sg:province":"Burgenland",
    "wof:name":"Gartenservice",
    "wof:placetype":"venue"
},
  "geometry": {"coordinates":[16.5070476532,47.7109451294],"type":"Point"}
}