{
  "type": "Feature",
  "properties": {
    "addr:full":"Peter-Tunner-Str 7 Judenburg Steiermark 8750",
    "addr:housenumber":"7",
    "addr:postcode":"8750",
    "addr:street":"Peter-Tunner-Str",
    "iso:country":"AT",
    "sg:address":"Peter-Tunner-Str 7",
    "sg:city":"Judenburg",
    "sg:orig_category":"Autohandel",
    "sg:phone":"+43 4335 7242142",
    "sg:postcode":"8750",
    "sg:province":"Steiermark",
    "wof:name":"Bauer Markus KFZ-Aufbereitung u Handel",
    "wof:placetype":"venue"
},
  "geometry": {"coordinates":[14.6716251373,47.1859130859],"type":"Point"}
}