{
  "type": "Feature",
  "properties": {
    "addr:full":"Wagingerstr 10 Salzburg Salzburg 5020",
    "addr:housenumber":"10",
    "addr:postcode":"5020",
    "addr:street":"Wagingerstr;Salzburg",
    "iso:country":"AT",
    "sg:address":"Wagingerstr 10",
    "sg:city":"Salzburg",
    "sg:orig_category":"Tabaktrafiken",
    "sg:phone":"+43 662 421466",
    "sg:postcode":"5020",
    "sg:province":"Salzburg",
    "wof:name":"Pamminger Walter",
    "wof:placetype":"venue"
},
  "geometry": {"coordinates":[13.0240364075,47.8222541809],"type":"Point"}
}