{
  "type": "Feature",
  "properties": {
    "iso:country":"AT",
    "sg:address":"Esterhazystr 3",
    "sg:city":"Eisenstadt",
    "sg:orig_category":"Psychotherapie",
    "sg:phone":"+43 4326 8263010",
    "sg:postcode":"7000",
    "sg:province":"Burgenland",
    "wof:name":"BLP - Burgenl\u00e4ndischer Landesverband f Psychotherapie",
    "wof:placetype":"venue"
},
  "geometry": {"coordinates":[16.5177021027,47.8457717896],"type":"Point"}
}