{
  "type": "Feature",
  "properties": {
    "addr:full":"Industriestrasse 2 Perchtoldsdorf Nieder\u00f6sterreich 2380",
    "addr:housenumber":"2",
    "addr:postcode":"2380",
    "addr:street":"Industriestrasse",
    "iso:country":"AT",
    "sg:address":"Industriestrasse 2",
    "sg:city":"Perchtoldsdorf",
    "sg:classifiers":[
        {
            "category":"Banks & Credit Unions",
            "subcategory":"Investment Brokerage",
            "type":"Services"
        }
    ],
    "sg:phone":"+43 1 74935300",
    "sg:postcode":"2380",
    "sg:province":"Nieder\u00f6sterreich",
    "sg:tags":[
        "printing",
        "ink"
    ],
    "sg:website":"basf-drucksysteme.at",
    "wof:name":"BASF Drucksysteme Austria GmbH",
    "wof:placetype":"venue"
},
  "geometry": {"coordinates":[16.2900409698,48.1199913025],"type":"Point"}
}