{
  "type": "Feature",
  "properties": {
    "iso:country":"AT",
    "sg:address":"Nr 34",
    "sg:city":"Heimschuh",
    "sg:orig_category":"Fischerei",
    "sg:phone":"+43 4366 42112821",
    "sg:postcode":"8451",
    "sg:province":"Steiermark",
    "wof:name":"Krasser Sportfischerzentrum",
    "wof:placetype":"venue"
},
  "geometry": {"coordinates":[15.4879951477,46.7589645386],"type":"Point"}
}