{
  "type": "Feature",
  "properties": {
    "addr:full":"Alexander-Putsch-Pl 9 Pinkafeld Burgenland 7423",
    "addr:housenumber":"9",
    "addr:postcode":"7423",
    "addr:street":"Alexander-Putsch-Pl",
    "iso:country":"AT",
    "sg:address":"Alexander-Putsch-Pl 9",
    "sg:city":"Pinkafeld",
    "sg:orig_category":"Lebensmittel / Einzelhandel",
    "sg:phone":"+43 3357 43360",
    "sg:postcode":"7423",
    "sg:province":"Burgenland",
    "wof:name":"Zielpunkt Warenhandel GmbH & Co KG",
    "wof:placetype":"venue"
},
  "geometry": {"coordinates":[16.1204929352,47.3701515198],"type":"Point"}
}