{
  "type": "Feature",
  "properties": {
    "addr:full":"Ungarg 25 Wiener Neustadt Nieder\u00f6sterreich 2700",
    "addr:housenumber":"25",
    "addr:postcode":"2700",
    "addr:street":"Ungarg",
    "iso:country":"AT",
    "sg:address":"Ungarg 25",
    "sg:city":"Wiener Neustadt",
    "sg:orig_category":"Wasserwerke",
    "sg:phone":"+43 4326 22373530",
    "sg:postcode":"2700",
    "sg:province":"Nieder\u00f6sterreich",
    "wof:name":"Wiener Neust\u00e4dter Stadtwerke u Kommunal Service GmbH",
    "wof:placetype":"venue"
},
  "geometry": {"coordinates":[16.2492675781,47.8127326965],"type":"Point"}
}