{
  "type": "Feature",
  "properties": {
    "addr:full":"Rheinstr 17 Feldkirch Vorarlberg 6800",
    "addr:housenumber":"17",
    "addr:postcode":"6800",
    "addr:street":"Rheinstr",
    "iso:country":"AT",
    "sg:address":"Rheinstr 17",
    "sg:city":"Feldkirch",
    "sg:orig_category":"Behinderungen / Leben Mit Behinderungen",
    "sg:phone":"+43 5522 75374",
    "sg:postcode":"6800",
    "sg:province":"Vorarlberg",
    "wof:name":"Lebenshilfe Feldkirch - Werkst\u00e4tte Nofels",
    "wof:placetype":"venue"
},
  "geometry": {"coordinates":[9.5761356354,47.2546730042],"type":"Point"}
}