{
  "type": "Feature",
  "properties": {
    "addr:full":"Nr 83 Zams Tirol 6511",
    "addr:postcode":"6511",
    "addr:street":"Nr 83;Tirol",
    "iso:country":"AT",
    "sg:address":"Nr 83",
    "sg:city":"Zams",
    "sg:orig_category":"Volksschulen",
    "sg:phone":"+43 5442 67748",
    "sg:postcode":"6511",
    "sg:province":"Tirol",
    "wof:name":"Volksschule Falterschein",
    "wof:placetype":"venue"
},
  "geometry": {"coordinates":[10.5895729065,47.157749176],"type":"Point"}
}