{
  "type": "Feature",
  "properties": {
    "addr:full":"M\u00f6nichsreith 12 St. Wolfgang im Salzkammergut Ober\u00f6sterreich 5360",
    "addr:housenumber":"12",
    "addr:postcode":"5360",
    "addr:street":"Moenichsreith",
    "iso:country":"AT",
    "sg:address":"M\u00f6nichsreith 12",
    "sg:city":"St. Wolfgang im Salzkammergut",
    "sg:orig_category":"Bauunternehmen",
    "sg:phone":"+43 4361 388090",
    "sg:postcode":"5360",
    "sg:province":"Ober\u00f6sterreich",
    "wof:name":"Raudaschl Christian",
    "wof:placetype":"venue"
},
  "geometry": {"coordinates":[13.4940757751,47.7322425842],"type":"Point"}
}