{
  "type": "Feature",
  "properties": {
    "addr:full":"Grazer Vorstadt 25 Voitsberg Steiermark 8570",
    "addr:housenumber":"25",
    "addr:postcode":"8570",
    "addr:street":"Grazer Vorstadt",
    "iso:country":"AT",
    "sg:address":"Grazer Vorstadt 25",
    "sg:city":"Voitsberg",
    "sg:orig_category":"Feuerwehren",
    "sg:phone":"+43 3142 222220",
    "sg:postcode":"8570",
    "sg:province":"Steiermark",
    "wof:name":"Feuerwehr d Stadt Voitsberg",
    "wof:placetype":"venue"
},
  "geometry": {"coordinates":[15.157283783,47.0463523865],"type":"Point"}
}