{
  "type": "Feature",
  "properties": {
    "addr:full":"Hof 14 Schwarzenberg Vorarlberg 6867",
    "addr:housenumber":"14",
    "addr:postcode":"6867",
    "addr:street":"Hof",
    "iso:country":"AT",
    "sg:address":"Hof 14",
    "sg:city":"Schwarzenberg",
    "sg:classifiers":[
        {
            "category":"Travel",
            "subcategory":"Hotels & Motels",
            "type":"Entertainment"
        }
    ],
    "sg:phone":"+43 5512 29440",
    "sg:postcode":"6867",
    "sg:province":"Vorarlberg",
    "wof:name":"Romantikhotel Hirschen",
    "wof:placetype":"venue"
},
  "geometry": {"coordinates":[9.8520126343,47.414352417],"type":"Point"}
}