{
  "type": "Feature",
  "properties": {
    "addr:full":"Zeller Bundesstr 7 Saalfelden am Steinernen Meer Salzburg 5760",
    "addr:housenumber":"7",
    "addr:postcode":"5760",
    "addr:street":"Bundesstr",
    "iso:country":"AT",
    "sg:address":"Zeller Bundesstr 7",
    "sg:city":"Saalfelden am Steinernen Meer",
    "sg:orig_category":"Reifen U Reifendienste",
    "sg:phone":"+43 6582 72089",
    "sg:postcode":"5760",
    "sg:province":"Salzburg",
    "wof:name":"Reifen John HandelsgesmbH",
    "wof:placetype":"venue"
},
  "geometry": {"coordinates":[12.8357400894,47.4216308594],"type":"Point"}
}