{
  "type": "Feature",
  "properties": {
    "addr:full":"Hauptpl 22 Weiz Steiermark 8160",
    "addr:housenumber":"22",
    "addr:postcode":"8160",
    "addr:street":"Hauptpl",
    "iso:country":"AT",
    "sg:address":"Hauptpl 22",
    "sg:city":"Weiz",
    "sg:orig_category":"Glasereien",
    "sg:phone":"+43 4331 7223300",
    "sg:postcode":"8160",
    "sg:province":"Steiermark",
    "wof:name":"Raischauer Glaserei +Spenglerei Inh Ludwig Sch\u00fcppel",
    "wof:placetype":"venue"
},
  "geometry": {"coordinates":[15.6209011078,47.2170791626],"type":"Point"}
}