{
  "type": "Feature",
  "properties": {
    "addr:full":"Magnastr 1 Oberwaltersdorf Nieder\u00f6sterreich 2522",
    "addr:housenumber":"1",
    "addr:postcode":"2522",
    "addr:street":"Magnastr",
    "iso:country":"AT",
    "sg:address":"Magnastr 1",
    "sg:city":"Oberwaltersdorf",
    "sg:orig_category":"Immobilienmakler",
    "sg:phone":"+43 2253 6000",
    "sg:postcode":"2522",
    "sg:province":"Nieder\u00f6sterreich",
    "wof:name":"Fontana Beteiligungs AG",
    "wof:placetype":"venue"
},
  "geometry": {"coordinates":[16.3182258606,47.9744796753],"type":"Point"}
}