{
  "type": "Feature",
  "properties": {
    "addr:full":"Herbststr 45 Wien Wien 1160",
    "addr:housenumber":"45",
    "addr:postcode":"1160",
    "addr:street":"Herbststr",
    "iso:country":"AT",
    "sg:address":"Herbststr 45",
    "sg:city":"Wien",
    "sg:orig_category":"Tabaktrafiken",
    "sg:phone":"+43 1 4959400",
    "sg:postcode":"1160",
    "sg:province":"Wien",
    "wof:name":"Bugkel Brigitte",
    "wof:placetype":"venue"
},
  "geometry": {"coordinates":[16.3274745941,48.2061653137],"type":"Point"}
}