{
  "type": "Feature",
  "properties": {
    "addr:full":"Nr 39 Ebbs Tirol 6341",
    "addr:postcode":"6341",
    "addr:street":"Nr 39;Tirol",
    "iso:country":"AT",
    "sg:address":"Nr 39",
    "sg:city":"Ebbs",
    "sg:orig_category":"Tischlereien",
    "sg:phone":"+43 5373 43138",
    "sg:postcode":"6341",
    "sg:province":"Tirol",
    "wof:name":"Buchauer Klaus",
    "wof:placetype":"venue"
},
  "geometry": {"coordinates":[12.2144241333,47.6297264099],"type":"Point"}
}