{
  "type": "Feature",
  "properties": {
    "iso:country":"AT",
    "sg:address":"Marktpl 4",
    "sg:city":"B\u00f6heimkirchen",
    "sg:orig_category":"Textilwaren / Einzelhandel",
    "sg:phone":"+43 2743 2278",
    "sg:postcode":"3071",
    "sg:province":"Nieder\u00f6sterreich",
    "wof:name":"Marga Frei Fashion GesmbH",
    "wof:placetype":"venue"
},
  "geometry": {"coordinates":[7.7521400452,47.9156341553],"type":"Point"}
}