{
  "type": "Feature",
  "properties": {
    "iso:country":"AT",
    "sg:address":"Waagg 12",
    "sg:city":"Klagenfurt",
    "sg:orig_category":"Lebensmittel / Erzeugung U Gro\u00c3\u0178handel",
    "sg:phone":"+43 463 57335",
    "sg:postcode":"9020",
    "sg:province":"K\u00e4rnten",
    "wof:name":"Baum Otto",
    "wof:placetype":"venue"
},
  "geometry": {"coordinates":[14.3099002838,46.626121521],"type":"Point"}
}