{
  "type": "Feature",
  "properties": {
    "iso:country":"AT",
    "sg:address":"Dinstlstr 2",
    "sg:city":"Krems an der Donau",
    "sg:orig_category":"Bekleidung / Einzelhandel",
    "sg:phone":"+43 2732 73522",
    "sg:postcode":"3500",
    "sg:province":"Nieder\u00f6sterreich",
    "wof:name":"CIRCLE TREND",
    "wof:placetype":"venue"
},
  "geometry": {"coordinates":[15.602560997,48.4107093811],"type":"Point"}
}