{
  "type": "Feature",
  "properties": {
    "addr:full":"Nr 20 Lainbach Steiermark 8921",
    "addr:postcode":"8921",
    "addr:street":"Nr 20 Lainbach Steiermark",
    "iso:country":"AT",
    "sg:address":"Nr 20",
    "sg:city":"Lainbach",
    "sg:orig_category":"Friseure U Frisiersalons",
    "sg:phone":"+43 3633 2443",
    "sg:postcode":"8921",
    "sg:province":"Steiermark",
    "wof:name":"Friseur Struwwelpeter",
    "wof:placetype":"venue"
},
  "geometry": {"coordinates":[14.7634248734,47.6528511047],"type":"Point"}
}