{
  "type": "Feature",
  "properties": {
    "iso:country":"AT",
    "sg:address":"Antonig 9",
    "sg:city":"Wien",
    "sg:orig_category":"Restaurants: Indisch",
    "sg:phone":"+43 1 4064116",
    "sg:postcode":"1180",
    "sg:province":"Wien",
    "wof:name":"Tandoor",
    "wof:placetype":"venue"
},
  "geometry": {"coordinates":[16.3405895233,48.221244812],"type":"Point"}
}