{
  "type": "Feature",
  "properties": {
    "addr:full":"Marktpl 1 Bad Zell Ober\u00f6sterreich 4283",
    "addr:housenumber":"1",
    "addr:postcode":"4283",
    "addr:street":"Marktpl",
    "iso:country":"AT",
    "sg:address":"Marktpl 1",
    "sg:city":"Bad Zell",
    "sg:orig_category":"Banken U Sparkassen",
    "sg:phone":"+43 4372 637273",
    "sg:postcode":"4283",
    "sg:province":"Ober\u00f6sterreich",
    "wof:name":"Sparkasse Pregarten-Unterwei\u00dfenbach AG",
    "wof:placetype":"venue"
},
  "geometry": {"coordinates":[14.6696472168,48.3494415283],"type":"Point"}
}