{
  "type": "Feature",
  "properties": {
    "addr:full":"Klosterneuburger Str 127 Wien Wien 1200",
    "addr:housenumber":"127",
    "addr:postcode":"1200",
    "addr:street":"Str",
    "iso:country":"AT",
    "sg:address":"Klosterneuburger Str 127",
    "sg:city":"Wien",
    "sg:orig_category":"Non-Classified Establishments",
    "sg:phone":"+43 1 9422022",
    "sg:postcode":"1200",
    "sg:province":"Wien",
    "wof:name":"Rauchensteiner Andrea",
    "wof:placetype":"venue"
},
  "geometry": {"coordinates":[16.364572525,48.2389945984],"type":"Point"}
}