{
  "type": "Feature",
  "properties": {
    "iso:country":"AT",
    "sg:address":"Birga 1",
    "sg:city":"G\u00f6tzens",
    "sg:classifiers":[
        {
            "category":"Taxi",
            "type":"Transportation"
        }
    ],
    "sg:phone":"+43 4352 3432360",
    "sg:postcode":"6091",
    "sg:province":"Tirol",
    "sg:tags":[
        "personentransporte",
        "u"
    ],
    "wof:name":"Kaltenberger Wolfgang",
    "wof:placetype":"venue"
},
  "geometry": {"coordinates":[11.2967061996,47.2390899658],"type":"Point"}
}