{
  "type": "Feature",
  "properties": {
    "addr:full":"Grabenstr 1a Fohnsdorf Steiermark 8753",
    "addr:housenumber":"1a",
    "addr:postcode":"8753",
    "addr:street":"Grabenstr",
    "iso:country":"AT",
    "sg:address":"Grabenstr 1a",
    "sg:city":"Fohnsdorf",
    "sg:orig_category":"Fleischhauereien",
    "sg:phone":"+43 4335 732149",
    "sg:postcode":"8753",
    "sg:province":"Steiermark",
    "wof:name":"Kienzl Volkart",
    "wof:placetype":"venue"
},
  "geometry": {"coordinates":[14.6776275635,47.2089729309],"type":"Point"}
}