{
  "type": "Feature",
  "properties": {
    "addr:full":"Hans-Sperl-Str 16 Salzburg Salzburg 5020",
    "addr:housenumber":"16",
    "addr:postcode":"5020",
    "addr:street":"Hans-Sperl-Str;Salzburg",
    "iso:country":"AT",
    "sg:address":"Hans-Sperl-Str 16",
    "sg:city":"Salzburg",
    "sg:orig_category":"Psychotherapie",
    "sg:phone":"+43 662 627982",
    "sg:postcode":"5020",
    "sg:province":"Salzburg",
    "wof:name":"Halbleib Heide",
    "wof:placetype":"venue"
},
  "geometry": {"coordinates":[13.0652322769,47.7814903259],"type":"Point"}
}