{
  "type": "Feature",
  "properties": {
    "iso:country":"AT",
    "sg:address":"Schmiedingerstrasse 30",
    "sg:city":"Salzburg",
    "sg:classifiers":[
        {
            "category":"Military Area",
            "subcategory":"Air Force Base",
            "type":"Public Place"
        }
    ],
    "sg:phone":"+43 662 4325140",
    "sg:postcode":"5020",
    "sg:province":"Salzburg",
    "sg:tags":[
        "flag",
        "pole",
        "staff"
    ],
    "sg:website":"lkd.at",
    "wof:name":"LKD Licht-, Klima- und Deckensystem Ges.m.b.H.",
    "wof:placetype":"venue"
},
  "geometry": {"coordinates":[13.0208492279,47.8237876892],"type":"Point"}
}