{
  "type": "Feature",
  "properties": {
    "iso:country":"AT",
    "sg:address":"Koling. 12",
    "sg:city":"Wien",
    "sg:classifiers":[
        {
            "category":"Food & Beverages",
            "subcategory":"Groceries & Convenience Stores",
            "type":"Retail Goods"
        }
    ],
    "sg:phone":"+43 4313 104325",
    "sg:postcode":"1090",
    "sg:province":"Wien",
    "sg:tags":[
        "drink"
    ],
    "wof:name":"KARANTA HANDELS GMBH",
    "wof:placetype":"venue"
},
  "geometry": {"coordinates":[16.3633594513,48.2159614563],"type":"Point"}
}