{
  "type": "Feature",
  "properties": {
    "iso:country":"AT",
    "sg:address":"Oberdorf 71",
    "sg:city":"Stans",
    "sg:orig_category":"Banken U Sparkassen",
    "sg:phone":"+43 4352 42635760",
    "sg:postcode":"6135",
    "sg:province":"Tirol",
    "wof:name":"Bankomat d Raiffeisen-Bezirkskasse Schwaz regGenmbH",
    "wof:placetype":"venue"
},
  "geometry": {"coordinates":[11.7170000076,47.36977005],"type":"Point"}
}