{
  "type": "Feature",
  "properties": {
    "addr:full":"Salzburger Str 381 Linz Ober\u00f6sterreich 4030",
    "addr:housenumber":"381",
    "addr:postcode":"4030",
    "addr:street":"Salzburger Str",
    "iso:country":"AT",
    "sg:address":"Salzburger Str 381",
    "sg:city":"Linz",
    "sg:orig_category":"Autohandel",
    "sg:phone":"+43 732 381857",
    "sg:postcode":"4030",
    "sg:province":"Ober\u00f6sterreich",
    "wof:name":"Auto Karrer",
    "wof:placetype":"venue"
},
  "geometry": {"coordinates":[14.2648801804,48.2476196289],"type":"Point"}
}