{
  "type": "Feature",
  "properties": {
    "iso:country":"AT",
    "sg:address":"Lastenstr 11",
    "sg:city":"Feldkirchen in K\u00e4rnten",
    "sg:orig_category":"Bauunternehmen",
    "sg:phone":"+43 4342 763047",
    "sg:postcode":"9560",
    "sg:province":"K\u00e4rnten",
    "wof:name":"Gailberger & Kristan Baumeister Hoch- u Tiefbau GmbH",
    "wof:placetype":"venue"
},
  "geometry": {"coordinates":[14.1012878418,46.7193756104],"type":"Point"}
}