{
  "type": "Feature",
  "properties": {
    "iso:country":"AT",
    "sg:address":"Landstr 2",
    "sg:city":"Linz",
    "sg:orig_category":"Geschenkartikel",
    "sg:phone":"+43 4373 2786385",
    "sg:postcode":"4020",
    "sg:province":"Ober\u00f6sterreich",
    "wof:name":"Swarovski",
    "wof:placetype":"venue"
},
  "geometry": {"coordinates":[14.2909088135,48.2987327576],"type":"Point"}
}