{
  "type": "Feature",
  "properties": {
    "iso:country":"AT",
    "sg:address":"Nr 16",
    "sg:city":"Feldkirchen",
    "sg:orig_category":"Juweliere, Gold- U Silberschmiede",
    "sg:phone":"+43 4377 486910",
    "sg:postcode":"5143",
    "sg:province":"Ober\u00f6sterreich",
    "wof:name":"Eichberger Johannes",
    "wof:placetype":"venue"
},
  "geometry": {"coordinates":[13.0446195602,48.0679512024],"type":"Point"}
}