{
  "type": "Feature",
  "properties": {
    "iso:country":"AT",
    "sg:address":"Puchberger Str 1-2",
    "sg:city":"St. Egyden am Steinfeld",
    "sg:orig_category":"Non-Classified Establishments",
    "sg:phone":"+43 2638 774310",
    "sg:postcode":"2731",
    "sg:province":"Nieder\u00f6sterreich",
    "wof:name":"Justizanstalt f Jugendliche Gerasdorf",
    "wof:placetype":"venue"
},
  "geometry": {"coordinates":[16.1024875641,47.7818527222],"type":"Point"}
}