{
  "type": "Feature",
  "properties": {
    "addr:full":"Feldg 25 Schattendorf Burgenland 7022",
    "addr:housenumber":"25",
    "addr:postcode":"7022",
    "addr:street":"Feldg",
    "iso:country":"AT",
    "sg:address":"Feldg 25",
    "sg:city":"Schattendorf",
    "sg:orig_category":"Transportunternehmen",
    "sg:phone":"+43 664 1008758",
    "sg:postcode":"7022",
    "sg:province":"Burgenland",
    "wof:name":"Grafl Heinz",
    "wof:placetype":"venue"
},
  "geometry": {"coordinates":[16.510269165,47.7101325989],"type":"Point"}
}