{
  "type": "Feature",
  "properties": {
    "addr:full":"Industriestr 3 Prambachkirchen Ober\u00f6sterreich 4731",
    "addr:housenumber":"3",
    "addr:postcode":"4731",
    "addr:street":"Industriestr",
    "iso:country":"AT",
    "sg:address":"Industriestr 3",
    "sg:city":"Prambachkirchen",
    "sg:orig_category":"Tischlereien",
    "sg:phone":"+43 4372 772688",
    "sg:postcode":"4731",
    "sg:province":"Ober\u00f6sterreich",
    "wof:name":"Egginger Wintergartenbau",
    "wof:placetype":"venue"
},
  "geometry": {"coordinates":[13.9146232605,48.3157157898],"type":"Point"}
}