{
  "type": "Feature",
  "properties": {
    "addr:full":"Wimpassinger Str 76 Wels Ober\u00f6sterreich 4600",
    "addr:housenumber":"76",
    "addr:postcode":"4600",
    "addr:street":"Str;Oberoesterreich",
    "iso:country":"AT",
    "sg:address":"Wimpassinger Str 76",
    "sg:city":"Wels",
    "sg:orig_category":"Physiotherapie",
    "sg:phone":"+43 4369 911081800",
    "sg:postcode":"4600",
    "sg:province":"Ober\u00f6sterreich",
    "wof:name":"Seydl-Schwab Karina",
    "wof:placetype":"venue"
},
  "geometry": {"coordinates":[13.9914426804,48.1636772156],"type":"Point"}
}