{
  "type": "Feature",
  "properties": {
    "addr:full":"Marktpl 9 Pregarten Ober\u00f6sterreich 4230",
    "addr:housenumber":"9",
    "addr:postcode":"4230",
    "addr:street":"Marktpl",
    "iso:country":"AT",
    "sg:address":"Marktpl 9",
    "sg:city":"Pregarten",
    "sg:orig_category":"Massagen",
    "sg:phone":"+43 4372 367858",
    "sg:postcode":"4230",
    "sg:province":"Ober\u00f6sterreich",
    "wof:name":"Massage u R\u00fcckenzentrum Christian Steinmetz",
    "wof:placetype":"venue"
},
  "geometry": {"coordinates":[14.5306072235,48.3553314209],"type":"Point"}
}