{
  "type": "Feature",
  "properties": {
    "iso:country":"AT",
    "sg:address":"Schwefel 73",
    "sg:city":"Dornbirn",
    "sg:orig_category":"Bremsen- U Kupplungsdienste",
    "sg:phone":"+43 5572 250800",
    "sg:postcode":"6850",
    "sg:province":"Vorarlberg",
    "wof:name":"BKT Brems- und Kupplungstechnik GesmbH & Co KG",
    "wof:placetype":"venue"
},
  "geometry": {"coordinates":[9.7392673492,47.4302253723],"type":"Point"}
}