{
  "type": "Feature",
  "properties": {
    "addr:full":"Siebensterngasse 27 Wien Wien 1070",
    "addr:housenumber":"27",
    "addr:postcode":"1070",
    "addr:street":"Siebensterngasse",
    "iso:country":"AT",
    "sg:address":"Siebensterngasse 27",
    "sg:city":"Wien",
    "sg:classifiers":[
        {
            "category":"Professional",
            "type":"Services"
        }
    ],
    "sg:phone":"+43 1 9578985",
    "sg:postcode":"1070",
    "sg:province":"Wien",
    "sg:tags":[
        "catering"
    ],
    "sg:website":"copaloca.at",
    "wof:name":"Copaloca Catering Eventtechnik & Management",
    "wof:placetype":"venue"
},
  "geometry": {"coordinates":[16.3522872925,48.202129364],"type":"Point"}
}