{
  "type": "Feature",
  "properties": {
    "iso:country":"AT",
    "sg:address":"Augartenstr 21",
    "sg:city":"Lustenau",
    "sg:orig_category":"Stickereien",
    "sg:phone":"+43 5577 85713",
    "sg:postcode":"6890",
    "sg:province":"Vorarlberg",
    "wof:name":"Maier Josef",
    "wof:placetype":"venue"
},
  "geometry": {"coordinates":[9.650853157,47.4405517578],"type":"Point"}
}