{
  "type": "Feature",
  "properties": {
    "iso:country":"AT",
    "sg:address":"Templstr 5b",
    "sg:city":"Innsbruck",
    "sg:orig_category":"Immobilienverwaltungen",
    "sg:phone":"+43 512 581010",
    "sg:postcode":"6020",
    "sg:province":"Tirol",
    "wof:name":"ABRIT Immobilien Besitz- und VerwertungsgesmbH",
    "wof:placetype":"venue"
},
  "geometry": {"coordinates":[11.3939342499,47.2603034973],"type":"Point"}
}