{
  "type": "Feature",
  "properties": {
    "addr:full":"Lazarettg 7 Wien Wien 1090",
    "addr:housenumber":"7",
    "addr:postcode":"1090",
    "addr:street":"Lazarettg",
    "iso:country":"AT",
    "sg:address":"Lazarettg 7",
    "sg:city":"Wien",
    "sg:orig_category":"Rauchfangkehrer",
    "sg:phone":"+43 1 7343540",
    "sg:postcode":"1090",
    "sg:province":"Wien",
    "wof:name":"Stern G\u00fcnter",
    "wof:placetype":"venue"
},
  "geometry": {"coordinates":[16.3506202698,48.2179870605],"type":"Point"}
}