{
  "type": "Feature",
  "properties": {
    "addr:full":"Brunner Feldstr 67 Perchtoldsdorf Nieder\u00f6sterreich 2380",
    "addr:housenumber":"67",
    "addr:postcode":"2380",
    "addr:street":"Feldstr",
    "iso:country":"AT",
    "sg:address":"Brunner Feldstr 67",
    "sg:city":"Perchtoldsdorf",
    "sg:orig_category":"Industrieroboterbau",
    "sg:phone":"+43 1 601093721",
    "sg:postcode":"2380",
    "sg:province":"Nieder\u00f6sterreich",
    "wof:name":"ABB AG - Robotics",
    "wof:placetype":"venue"
},
  "geometry": {"coordinates":[16.2905960083,48.1205635071],"type":"Point"}
}