{
  "type": "Feature",
  "properties": {
    "addr:full":"Maurerg 2-4 Bruck an der Mur Steiermark 8600",
    "addr:housenumber":"2-4",
    "addr:postcode":"8600",
    "addr:street":"Maurerg",
    "iso:country":"AT",
    "sg:address":"Maurerg 2-4",
    "sg:city":"Bruck an der Mur",
    "sg:orig_category":"Reifen U Reifendienste",
    "sg:phone":"+43 4338 62511240",
    "sg:postcode":"8600",
    "sg:province":"Steiermark",
    "wof:name":"Edler Reifen GmbH & Co KG",
    "wof:placetype":"venue"
},
  "geometry": {"coordinates":[15.275100708,47.4195175171],"type":"Point"}
}