{
  "type": "Feature",
  "properties": {
    "addr:full":"Froschweg 1 Dornbirn Vorarlberg 6850",
    "addr:housenumber":"1",
    "addr:postcode":"6850",
    "addr:street":"Froschweg",
    "iso:country":"AT",
    "sg:address":"Froschweg 1",
    "sg:city":"Dornbirn",
    "sg:orig_category":"Non-Classified Establishments",
    "sg:phone":"+43 5572 20356",
    "sg:postcode":"6850",
    "sg:province":"Vorarlberg",
    "wof:name":"Pfarramt",
    "wof:placetype":"venue"
},
  "geometry": {"coordinates":[9.7283973694,47.3934288025],"type":"Point"}
}