{
  "type": "Feature",
  "properties": {
    "iso:country":"AT",
    "sg:address":"Anton St\u00f6rck-G 75",
    "sg:city":"Wien",
    "sg:orig_category":"Papier- U Schreibwaren / Einzelhandel",
    "sg:phone":"+43 1 2717454",
    "sg:postcode":"1210",
    "sg:province":"Wien",
    "wof:name":"Schwarz Gertraud",
    "wof:placetype":"venue"
},
  "geometry": {"coordinates":[16.3978404999,48.2579994202],"type":"Point"}
}