{
  "type": "Feature",
  "properties": {
    "iso:country":"AT",
    "sg:address":"Kaserneng 6",
    "sg:city":"St. Magdalen",
    "sg:orig_category":"Gie\u00c3\u0178ereien",
    "sg:phone":"+43 4242 411810",
    "sg:postcode":"9524",
    "sg:province":"K\u00e4rnten",
    "wof:name":"Schmidt Armaturen Zweigniederlassung der Flowserve (Austria) GmbH",
    "wof:placetype":"venue"
},
  "geometry": {"coordinates":[-107.2357559204,34.1140518188],"type":"Point"}
}