{
  "type": "Feature",
  "properties": {
    "addr:full":"Spengergasse 13 Wien Wien 1050",
    "addr:housenumber":"13",
    "addr:postcode":"1050",
    "addr:street":"Spengergasse",
    "iso:country":"AT",
    "sg:address":"Spengergasse 13",
    "sg:city":"Wien",
    "sg:classifiers":[
        {
            "category":"Building & Trades",
            "subcategory":"Plumbing",
            "type":"Services"
        }
    ],
    "sg:phone":"+43 1 5445367",
    "sg:postcode":"1050",
    "sg:province":"Wien",
    "sg:tags":[
        "supraregional",
        "gas"
    ],
    "sg:website":"ingerisch.at",
    "wof:name":"Raimund Ingerisch jun. GesmbH.",
    "wof:placetype":"venue"
},
  "geometry": {"coordinates":[16.3586101532,48.1836395264],"type":"Point"}
}