{
  "type": "Feature",
  "properties": {
    "iso:country":"AT",
    "sg:address":"Sechsschimmelg 17",
    "sg:city":"Wien",
    "sg:orig_category":"Apotheken",
    "sg:phone":"+43 1 3179207",
    "sg:postcode":"1090",
    "sg:province":"Wien",
    "wof:name":"Josefinen-Apotheke Magpharm Reinhard Heinrich",
    "wof:placetype":"venue"
},
  "geometry": {"coordinates":[16.351474762,48.2234115601],"type":"Point"}
}