{
  "type": "Feature",
  "properties": {
    "addr:full":"Reiteregg 25 Hitzendorf Steiermark 8151",
    "addr:housenumber":"25",
    "addr:postcode":"8151",
    "addr:street":"Reiteregg",
    "iso:country":"AT",
    "sg:address":"Reiteregg 25",
    "sg:city":"Hitzendorf",
    "sg:classifiers":[
        {
            "category":"Ice Cream",
            "type":"Food & Drink"
        }
    ],
    "sg:phone":"+43 3123 2717",
    "sg:postcode":"8151",
    "sg:province":"Steiermark",
    "sg:tags":[
        "seed",
        "oil",
        "pumpkin"
    ],
    "wof:name":"Birnstingl Ges.m.b.H.",
    "wof:placetype":"venue"
},
  "geometry": {"coordinates":[15.2762145996,47.0516548157],"type":"Point"}
}