{
  "type": "Feature",
  "properties": {
    "addr:full":"Zellerstr 65 Wels Ober\u00f6sterreich 4600",
    "addr:housenumber":"65",
    "addr:postcode":"4600",
    "addr:street":"Zellerstr;Oberoesterreich",
    "iso:country":"AT",
    "sg:address":"Zellerstr 65",
    "sg:city":"Wels",
    "sg:orig_category":"Maler, Anstreicher U Lackierer",
    "sg:phone":"+43 7242 56632",
    "sg:postcode":"4600",
    "sg:province":"Ober\u00f6sterreich",
    "wof:name":"Pechlof Thomas",
    "wof:placetype":"venue"
},
  "geometry": {"coordinates":[13.9978466034,48.172000885],"type":"Point"}
}