{
  "type": "Feature",
  "properties": {
    "addr:full":"Schikanedergasse 3 Wien Wien 1040",
    "addr:housenumber":"3",
    "addr:postcode":"1040",
    "addr:street":"Schikanedergasse",
    "iso:country":"AT",
    "sg:address":"Schikanedergasse 3",
    "sg:city":"Wien",
    "sg:classifiers":[
        {
            "category":"Home & Garden",
            "subcategory":"Furniture",
            "type":"Retail Goods"
        }
    ],
    "sg:phone":"+43 1 5862806",
    "sg:postcode":"1040",
    "sg:province":"Wien",
    "sg:tags":[
        "designer"
    ],
    "sg:website":"glasart.at",
    "wof:name":"Heinz Knapp Glas-Art ConneXion Kunst & Design",
    "wof:placetype":"venue"
},
  "geometry": {"coordinates":[16.3644695282,48.1966133118],"type":"Point"}
}