{
  "type": "Feature",
  "properties": {
    "addr:full":"Nr 213 Scheffau am Wilden Kaiser Tirol 6351",
    "addr:postcode":"6351",
    "addr:street":"Nr 213;Wilden Kaiser",
    "iso:country":"AT",
    "sg:address":"Nr 213",
    "sg:city":"Scheffau am Wilden Kaiser",
    "sg:orig_category":"Betriebsbeteiligungen",
    "sg:phone":"+43 5358 8155",
    "sg:postcode":"6351",
    "sg:province":"Tirol",
    "wof:name":"Guth BeteiligungsgesmbH",
    "wof:placetype":"venue"
},
  "geometry": {"coordinates":[12.2500114441,47.5286445618],"type":"Point"}
}