{
  "type": "Feature",
  "properties": {
    "addr:full":"Friesacher Str St. Veit an der Glan K\u00e4rnten 9300",
    "addr:postcode":"9300",
    "addr:street":"Str St.;Kaernten",
    "iso:country":"AT",
    "sg:address":"Friesacher Str",
    "sg:city":"St. Veit an der Glan",
    "sg:orig_category":"Garten- U Landschaftsgestaltung",
    "sg:phone":"+43 4342 125580",
    "sg:postcode":"9300",
    "sg:province":"K\u00e4rnten",
    "wof:name":"Gartengestaltung Fleischhacker GesmbH",
    "wof:placetype":"venue"
},
  "geometry": {"coordinates":[14.3500003815,46.769329071],"type":"Point"}
}