{
  "type": "Feature",
  "properties": {
    "addr:full":"Laaber Holzweg 29 Braunau am Inn Ober\u00f6sterreich 5280",
    "addr:housenumber":"29",
    "addr:postcode":"5280",
    "addr:street":"Laaber Holzweg",
    "iso:country":"AT",
    "sg:address":"Laaber Holzweg 29",
    "sg:city":"Braunau am Inn",
    "sg:orig_category":"Autoreparatur",
    "sg:phone":"+43 7722 62580",
    "sg:postcode":"5280",
    "sg:province":"Ober\u00f6sterreich",
    "wof:name":"Autohaus Hofmann GesmbH & Co",
    "wof:placetype":"venue"
},
  "geometry": {"coordinates":[13.0458068848,48.2581329346],"type":"Point"}
}