{
  "type": "Feature",
  "properties": {
    "addr:full":"Dorfstr 27 Hof Salzburg 5322",
    "addr:housenumber":"27",
    "addr:postcode":"5322",
    "addr:street":"Dorfstr;Salzburg",
    "iso:country":"AT",
    "sg:address":"Dorfstr 27",
    "sg:city":"Hof",
    "sg:orig_category":"Autohandel",
    "sg:phone":"+43 4362 2922240",
    "sg:postcode":"5322",
    "sg:province":"Salzburg",
    "wof:name":"IQ- Diskont Tankstelle",
    "wof:placetype":"venue"
},
  "geometry": {"coordinates":[13.2211875916,47.8204193115],"type":"Point"}
}