{
  "type": "Feature",
  "properties": {
    "addr:full":"Erzherzog-Johann-Str 339 Stainach Steiermark 8950",
    "addr:housenumber":"339",
    "addr:postcode":"8950",
    "iso:country":"AT",
    "sg:address":"Erzherzog-Johann-Str 339",
    "sg:city":"Stainach",
    "sg:orig_category":"Hauptschulen",
    "sg:phone":"+43 4336 82220330",
    "sg:postcode":"8950",
    "sg:province":"Steiermark",
    "wof:name":"Hauptschule",
    "wof:placetype":"venue"
},
  "geometry": {"coordinates":[14.1108541489,47.5313873291],"type":"Point"}
}