{
  "type": "Feature",
  "properties": {
    "addr:full":"Brixner Str 10 Kufstein Tirol 6330",
    "addr:housenumber":"10",
    "addr:postcode":"6330",
    "addr:street":"Str;Tirol",
    "iso:country":"AT",
    "sg:address":"Brixner Str 10",
    "sg:city":"Kufstein",
    "sg:orig_category":"Maler, Anstreicher U Lackierer",
    "sg:phone":"+43 4353 7263206",
    "sg:postcode":"6330",
    "sg:province":"Tirol",
    "wof:name":"Praschberger Hans",
    "wof:placetype":"venue"
},
  "geometry": {"coordinates":[12.1766195297,47.5904998779],"type":"Point"}
}