{
  "type": "Feature",
  "properties": {
    "iso:country":"AT",
    "sg:address":"Ruflinger Str 10",
    "sg:city":"Leonding",
    "sg:orig_category":"Musikunterricht",
    "sg:phone":"+43 732 6789680",
    "sg:postcode":"4060",
    "sg:province":"Ober\u00f6sterreich",
    "wof:name":"Landesmusikschule",
    "wof:placetype":"venue"
},
  "geometry": {"coordinates":[14.248790741,48.2811813354],"type":"Point"}
}