{
  "type": "Feature",
  "properties": {
    "addr:full":"Hauptstr 44 Eferding Ober\u00f6sterreich 4070",
    "addr:housenumber":"44",
    "addr:postcode":"4070",
    "addr:street":"Hauptstr",
    "iso:country":"AT",
    "sg:address":"Hauptstr 44",
    "sg:city":"Eferding",
    "sg:orig_category":"Fotografen",
    "sg:phone":"+43 4369 910052695",
    "sg:postcode":"4070",
    "sg:province":"Ober\u00f6sterreich",
    "wof:name":"K\u00f6ck Sabine",
    "wof:placetype":"venue"
},
  "geometry": {"coordinates":[14.0282659531,48.2828330994],"type":"Point"}
}