{
  "type": "Feature",
  "properties": {
    "iso:country":"AT",
    "sg:address":"Burgg 41",
    "sg:city":"Judenburg",
    "sg:orig_category":"Finanz- U Wirtschaftsberatung",
    "sg:phone":"+43 4335 7247583",
    "sg:postcode":"8750",
    "sg:province":"Steiermark",
    "wof:name":"VF-Institut f Verm\u00f6gensplanung u Finanzierungsmanagement GmbH",
    "wof:placetype":"venue"
},
  "geometry": {"coordinates":[14.6557531357,47.1683425903],"type":"Point"}
}