{
  "type": "Feature",
  "properties": {
    "iso:country":"AT",
    "sg:address":"Burgstall 102",
    "sg:city":"St. Andr\u00e4",
    "sg:orig_category":"Lebensmittel / Einzelhandel",
    "sg:phone":"+43 4358 3847",
    "sg:postcode":"9433",
    "sg:province":"K\u00e4rnten",
    "wof:name":"Zielpunkt Warenhandel GmbH & Co KG",
    "wof:placetype":"venue"
},
  "geometry": {"coordinates":[14.8068399429,46.7526512146],"type":"Point"}
}