{
  "type": "Feature",
  "properties": {
    "addr:full":"Adalbert Stifter-Str 64 Pasching Ober\u00f6sterreich 4061",
    "addr:housenumber":"64",
    "addr:postcode":"4061",
    "addr:street":"Adalbert;Oberoesterreich",
    "iso:country":"AT",
    "sg:address":"Adalbert Stifter-Str 64",
    "sg:city":"Pasching",
    "sg:orig_category":"Direktmarketing",
    "sg:phone":"+43 7229 61201",
    "sg:postcode":"4061",
    "sg:province":"Ober\u00f6sterreich",
    "sg:website":"www.lemler.at",
    "wof:name":"Lemler Directmarketing",
    "wof:placetype":"venue"
},
  "geometry": {"coordinates":[14.2412853241,48.2426490784],"type":"Point"}
}