{
  "type": "Feature",
  "properties": {
    "iso:country":"AT",
    "sg:address":"Franz Schubert-Str 5-7",
    "sg:city":"Schwechat",
    "sg:orig_category":"Damenmoden",
    "sg:phone":"+43 1 7065333",
    "sg:postcode":"2320",
    "sg:province":"Nieder\u00f6sterreich",
    "wof:name":"KiK Textilien und Non-Food GesmbH",
    "wof:placetype":"venue"
},
  "geometry": {"coordinates":[16.4782390594,48.1382446289],"type":"Point"}
}