{
  "type": "Feature",
  "properties": {
    "iso:country":"AT",
    "sg:address":"Wagramer Str 119",
    "sg:city":"Wien",
    "sg:orig_category":"Aquarien U Aquarienbedarf",
    "sg:phone":"+43 4312 033774",
    "sg:postcode":"1220",
    "sg:province":"Wien",
    "wof:name":"Paradiese unter Wasser - Traumaquarien",
    "wof:placetype":"venue"
},
  "geometry": {"coordinates":[16.4405117035,48.2472381592],"type":"Point"}
}