{
  "type": "Feature",
  "properties": {
    "iso:country":"AT",
    "sg:address":"Treustr 8",
    "sg:city":"Wien",
    "sg:classifiers":[
        {
            "category":"Retail",
            "subcategory":"Event Space",
            "type":"Services"
        }
    ],
    "sg:phone":"+43 4313 501060",
    "sg:postcode":"1200",
    "sg:province":"Wien",
    "sg:tags":[
        "hand-",
        "u",
        "fu\u00c3\u0178pflege"
    ],
    "wof:name":"Legerer Isabella",
    "wof:placetype":"venue"
},
  "geometry": {"coordinates":[16.3684635162,48.2273330688],"type":"Point"}
}