{
  "type": "Feature",
  "properties": {
    "addr:full":"Laaer Bundesstr. Korneuburg Nieder\u00f6sterreich 2100",
    "addr:postcode":"2100",
    "addr:street":"Niederoesterreich",
    "iso:country":"AT",
    "sg:address":"Laaer Bundesstr.",
    "sg:city":"Korneuburg",
    "sg:classifiers":[
        {
            "category":"Wholesale",
            "subcategory":"Drugs",
            "type":"Manufacturing & Wholesale Goods"
        }
    ],
    "sg:phone":"+43 4322 62735400",
    "sg:postcode":"2100",
    "sg:province":"Nieder\u00f6sterreich",
    "sg:tags":[
        "chemical",
        "pharmaceutical"
    ],
    "wof:name":"F. JOH. KWIZDA GES.MBH",
    "wof:placetype":"venue"
},
  "geometry": {"coordinates":[16.3118495941,48.3599586487],"type":"Point"}
}