{
  "type": "Feature",
  "properties": {
    "addr:full":"Mittelberg 24 Fontanella Vorarlberg 6733",
    "addr:housenumber":"24",
    "addr:postcode":"6733",
    "addr:street":"Mittelberg",
    "iso:country":"AT",
    "sg:address":"Mittelberg 24",
    "sg:city":"Fontanella",
    "sg:orig_category":"Appartements / Ferienwohnungen",
    "sg:phone":"+43 4355 545108",
    "sg:postcode":"6733",
    "sg:province":"Vorarlberg",
    "wof:name":"Ferienhaus Burtscher",
    "wof:placetype":"venue"
},
  "geometry": {"coordinates":[9.8867721558,47.2431488037],"type":"Point"}
}