{
  "type": "Feature",
  "properties": {
    "addr:full":"Sprinzenstein 9 Rohrbach in Ober\u00f6sterreich Ober\u00f6sterreich 4150",
    "addr:housenumber":"9",
    "addr:postcode":"4150",
    "addr:street":"Sprinzenstein",
    "iso:country":"AT",
    "sg:address":"Sprinzenstein 9",
    "sg:city":"Rohrbach in Ober\u00f6sterreich",
    "sg:classifiers":[
        {
            "category":"Shopping",
            "type":"Retail Goods"
        }
    ],
    "sg:phone":"+43 4372 894307",
    "sg:postcode":"4150",
    "sg:province":"Ober\u00f6sterreich",
    "sg:tags":[
        "finished",
        "-",
        "metallic"
    ],
    "wof:name":"FRANZ GRABNER",
    "wof:placetype":"venue"
},
  "geometry": {"coordinates":[13.9905195236,48.5726852417],"type":"Point"}
}