{
  "type": "Feature",
  "properties": {
    "iso:country":"AT",
    "sg:address":"Ferdinandstr 4",
    "sg:city":"Wien",
    "sg:classifiers":[
        {
            "category":"Internet Cafe",
            "subcategory":"None",
            "type":"Food & Drink"
        }
    ],
    "sg:phone":"+43 1 24520",
    "sg:postcode":"1020",
    "sg:province":"Wien",
    "wof:name":"news networld internetservice AG",
    "wof:placetype":"venue"
},
  "geometry": {"coordinates":[16.3816394806,48.2127571106],"type":"Point"}
}