{
  "type": "Feature",
  "properties": {
    "iso:country":"AT",
    "sg:address":"Heinrichstr 91",
    "sg:city":"Graz",
    "sg:orig_category":"Minigolfanlagen U -Bedarf",
    "sg:phone":"+43 4331 6386199",
    "sg:postcode":"8010",
    "sg:province":"Steiermark",
    "wof:name":"Minigolfanlage",
    "wof:placetype":"venue"
},
  "geometry": {"coordinates":[15.4537553787,47.0816726685],"type":"Point"}
}