{
  "type": "Feature",
  "properties": {
    "addr:full":"Industriezone Kematen in Tirol Tirol 6175",
    "addr:postcode":"6175",
    "addr:street":"Industriezone Kematen In Tirol",
    "iso:country":"AT",
    "sg:address":"Industriezone",
    "sg:city":"Kematen in Tirol",
    "sg:orig_category":"Autoreparatur",
    "sg:phone":"+43 5232 2670",
    "sg:postcode":"6175",
    "sg:province":"Tirol",
    "wof:name":"Hofmann Anton",
    "wof:placetype":"venue"
},
  "geometry": {"coordinates":[11.2665309906,47.2622566223],"type":"Point"}
}