{
  "type": "Feature",
  "properties": {
    "iso:country":"AT",
    "sg:address":"M\u00fchlgasse 18",
    "sg:city":"Zirl",
    "sg:classifiers":[
        {
            "category":"Banks & Credit Unions",
            "subcategory":"Bureau De Change",
            "type":"Services"
        }
    ],
    "sg:phone":"+43 5238 53355",
    "sg:postcode":"6170",
    "sg:province":"Tirol",
    "sg:tags":[
        "flat",
        "construction",
        "roof"
    ],
    "sg:website":"spenglerei-hendl.at",
    "wof:name":"Spenglerei Hendl GmbH",
    "wof:placetype":"venue"
},
  "geometry": {"coordinates":[11.2416305542,47.2735519409],"type":"Point"}
}