{
  "type": "Feature",
  "properties": {
    "iso:country":"AT",
    "sg:address":"Nr 87",
    "sg:city":"Obersch\u00fctzen",
    "sg:orig_category":"Elektroinstallationsunternehmen",
    "sg:phone":"+43 4366 41033825",
    "sg:postcode":"7432",
    "sg:province":"Burgenland",
    "wof:name":"Wagner Walter",
    "wof:placetype":"venue"
},
  "geometry": {"coordinates":[16.2074546814,47.3508911133],"type":"Point"}
}