{
  "type": "Feature",
  "properties": {
    "iso:country":"AT",
    "sg:address":"Kirchenpl 3",
    "sg:city":"Wartberg an der Krems",
    "sg:orig_category":"Bibliotheken",
    "sg:phone":"+43 4375 877925",
    "sg:postcode":"4552",
    "sg:province":"Ober\u00f6sterreich",
    "wof:name":"B\u00fccherei Wartberg an der Krems",
    "wof:placetype":"venue"
},
  "geometry": {"coordinates":[14.1171121597,47.9898414612],"type":"Point"}
}