{
  "type": "Feature",
  "properties": {
    "addr:full":"Yppeng 1 Wien Wien 1160",
    "addr:housenumber":"1",
    "addr:postcode":"1160",
    "addr:street":"Yppeng",
    "iso:country":"AT",
    "sg:address":"Yppeng 1",
    "sg:city":"Wien",
    "sg:classifiers":[
        {
            "category":"Restaurant",
            "type":"Food & Drink"
        }
    ],
    "sg:phone":"+43 1 9291364",
    "sg:postcode":"1160",
    "sg:province":"Wien",
    "sg:tags":[
        "pizzeria"
    ],
    "wof:name":"Lisa Pizzeria",
    "wof:placetype":"venue"
},
  "geometry": {"coordinates":[16.3355197906,48.2140235901],"type":"Point"}
}