{
  "type": "Feature",
  "properties": {
    "addr:full":"Hannesgrub 23 Ried im Innkreis Ober\u00f6sterreich 4910",
    "addr:housenumber":"23",
    "addr:postcode":"4910",
    "addr:street":"Hannesgrub",
    "iso:country":"AT",
    "sg:address":"Hannesgrub 23",
    "sg:city":"Ried im Innkreis",
    "sg:classifiers":[
        {
            "category":"Professional",
            "subcategory":"Engineering",
            "type":"Services"
        }
    ],
    "sg:phone":"+43 4377 5283495",
    "sg:postcode":"4910",
    "sg:province":"Ober\u00f6sterreich",
    "sg:tags":[
        "machine",
        "-",
        "mechanical"
    ],
    "wof:name":"THEBERT METALLBAU GMBH",
    "wof:placetype":"venue"
},
  "geometry": {"coordinates":[13.4969873428,48.2161598206],"type":"Point"}
}