{
  "type": "Feature",
  "properties": {
    "addr:full":"Kaiserstr 76 Wien Wien 1070",
    "addr:housenumber":"76",
    "addr:postcode":"1070",
    "addr:street":"Kaiserstr",
    "iso:country":"AT",
    "sg:address":"Kaiserstr 76",
    "sg:city":"Wien",
    "sg:orig_category":"Autohandel",
    "sg:phone":"+43 664 3001816",
    "sg:postcode":"1070",
    "sg:province":"Wien",
    "wof:name":"Hagljan Tihomir",
    "wof:placetype":"venue"
},
  "geometry": {"coordinates":[16.3401241302,48.2049407959],"type":"Point"}
}