{
  "type": "Feature",
  "properties": {
    "iso:country":"AT",
    "sg:address":"Neubauzeile 106",
    "sg:city":"Linz",
    "sg:orig_category":"Staubsauger",
    "sg:phone":"+43 732 3777800",
    "sg:postcode":"4030",
    "sg:province":"Ober\u00f6sterreich",
    "wof:name":"LUX Elektroger\u00e4te VertriebsgesmbH",
    "wof:placetype":"venue"
},
  "geometry": {"coordinates":[14.2784862518,48.2418632507],"type":"Point"}
}