{
  "type": "Feature",
  "properties": {
    "addr:full":"Brucker Bundesstr 57 Zell am See Salzburg 5700",
    "addr:housenumber":"57",
    "addr:postcode":"5700",
    "addr:street":"Salzburg",
    "iso:country":"AT",
    "sg:address":"Brucker Bundesstr 57",
    "sg:city":"Zell am See",
    "sg:orig_category":"Appartements / Ferienwohnungen",
    "sg:phone":"+43 6542 572390",
    "sg:postcode":"5700",
    "sg:province":"Salzburg",
    "wof:name":"Heimhofer Gabriela",
    "wof:placetype":"venue"
},
  "geometry": {"coordinates":[12.7953386307,47.3201522827],"type":"Point"}
}