{
  "type": "Feature",
  "properties": {
    "addr:full":"Hans-Gasser-Pl 7 Villach K\u00e4rnten 9500",
    "addr:housenumber":"7",
    "addr:postcode":"9500",
    "addr:street":"Hans-Gasser-Pl;Kaernten",
    "iso:country":"AT",
    "sg:address":"Hans-Gasser-Pl 7",
    "sg:city":"Villach",
    "sg:orig_category":"Restaurants: Italienisch",
    "sg:phone":"+43 4242 25100",
    "sg:postcode":"9500",
    "sg:province":"K\u00e4rnten",
    "wof:name":"Osteria Sergio",
    "wof:placetype":"venue"
},
  "geometry": {"coordinates":[13.8424005508,46.6126174927],"type":"Point"}
}