{
  "type": "Feature",
  "properties": {
    "iso:country":"AT",
    "sg:address":"Margaretenstr 28",
    "sg:city":"Wien",
    "sg:orig_category":"Tankstellen",
    "sg:phone":"+43 1 5872568",
    "sg:postcode":"1040",
    "sg:province":"Wien",
    "wof:name":"AWI-Diskont",
    "wof:placetype":"venue"
},
  "geometry": {"coordinates":[16.3647060394,48.1961936951],"type":"Point"}
}