{
  "type": "Feature",
  "properties": {
    "addr:full":"Untere Dorfstr 10 Serfaus Tirol 6534",
    "addr:housenumber":"10",
    "addr:postcode":"6534",
    "addr:street":"Untere Dorfstr;Tirol",
    "iso:country":"AT",
    "sg:address":"Untere Dorfstr 10",
    "sg:city":"Serfaus",
    "sg:orig_category":"Banken U Sparkassen",
    "sg:phone":"+43 5476 65050",
    "sg:postcode":"6534",
    "sg:province":"Tirol",
    "wof:name":"Volksbank Landeck regGenmbH",
    "wof:placetype":"venue"
},
  "geometry": {"coordinates":[10.606637001,47.0376586914],"type":"Point"}
}