{
  "type": "Feature",
  "properties": {
    "iso:country":"AT",
    "sg:address":"Negrelliweg 30",
    "sg:city":"Linz",
    "sg:orig_category":"Freizeitangebote U -Einrichtungen",
    "sg:phone":"+43 732 385462",
    "sg:postcode":"4030",
    "sg:province":"Ober\u00f6sterreich",
    "wof:name":"Schorn Ingrid",
    "wof:placetype":"venue"
},
  "geometry": {"coordinates":[14.2855825424,48.2500686646],"type":"Point"}
}