{
  "type": "Feature",
  "properties": {
    "addr:full":"Salzburger Str 2 St. Gilgen Salzburg 5340",
    "addr:housenumber":"2",
    "addr:postcode":"5340",
    "addr:street":"Salzburger Str",
    "iso:country":"AT",
    "sg:address":"Salzburger Str 2",
    "sg:city":"St. Gilgen",
    "sg:orig_category":"Sonnenstudios",
    "sg:phone":"+43 6227 2091",
    "sg:postcode":"5340",
    "sg:province":"Salzburg",
    "wof:name":"Vitalstudio Brigitte",
    "wof:placetype":"venue"
},
  "geometry": {"coordinates":[13.3633069992,47.7674026489],"type":"Point"}
}