{
  "type": "Feature",
  "properties": {
    "addr:full":"Rennweg 86 Wien Wien 1030",
    "addr:housenumber":"86",
    "addr:postcode":"1030",
    "addr:street":"Rennweg",
    "iso:country":"AT",
    "sg:address":"Rennweg 86",
    "sg:city":"Wien",
    "sg:classifiers":[
        {
            "category":"Professional",
            "subcategory":"Computer Services",
            "type":"Services"
        }
    ],
    "sg:phone":"+43 1 7982674",
    "sg:postcode":"1030",
    "sg:province":"Wien",
    "sg:tags":[
        "software"
    ],
    "wof:name":"Heka DatenverarbeitungsgesmbH & Co Betriebs KG",
    "wof:placetype":"venue"
},
  "geometry": {"coordinates":[16.3970355988,48.1904373169],"type":"Point"}
}