{
  "type": "Feature",
  "properties": {
    "addr:full":"Lambrechtg 4 Wien Wien 1040",
    "addr:housenumber":"4",
    "addr:postcode":"1040",
    "addr:street":"Lambrechtg",
    "iso:country":"AT",
    "sg:address":"Lambrechtg 4",
    "sg:city":"Wien",
    "sg:orig_category":"Telekommunikation",
    "sg:phone":"+43 1 92910",
    "sg:postcode":"1040",
    "sg:province":"Wien",
    "wof:name":"NETRING Telekom",
    "wof:placetype":"venue"
},
  "geometry": {"coordinates":[16.3654994965,48.1899642944],"type":"Point"}
}