{
  "type": "Feature",
  "properties": {
    "addr:full":"Herzog-Bernhard-Pl 6 V\u00f6lkermarkt K\u00e4rnten 9100",
    "addr:housenumber":"6",
    "addr:postcode":"9100",
    "addr:street":"Herzog-Bernhard-Pl;Kaernten",
    "iso:country":"AT",
    "sg:address":"Herzog-Bernhard-Pl 6",
    "sg:city":"V\u00f6lkermarkt",
    "sg:orig_category":"Physiotherapie",
    "sg:phone":"+43 4232 51438",
    "sg:postcode":"9100",
    "sg:province":"K\u00e4rnten",
    "wof:name":"Janesch Doris Dipl-PT",
    "wof:placetype":"venue"
},
  "geometry": {"coordinates":[12.9413795471,47.6610603333],"type":"Point"}
}