{
  "type": "Feature",
  "properties": {
    "addr:full":"Seeuferg 12 Podersdorf am See Burgenland 7141",
    "addr:housenumber":"12",
    "addr:postcode":"7141",
    "addr:street":"Seeuferg",
    "iso:country":"AT",
    "sg:address":"Seeuferg 12",
    "sg:city":"Podersdorf am See",
    "sg:orig_category":"Pensionen / Privatzimmer",
    "sg:phone":"+43 4321 772348",
    "sg:postcode":"7141",
    "sg:province":"Burgenland",
    "wof:name":"Arkadenhaus - Helga Steiner",
    "wof:placetype":"venue"
},
  "geometry": {"coordinates":[16.8342761993,47.8618354797],"type":"Point"}
}