{
  "type": "Feature",
  "properties": {
    "addr:full":"Weitersfeld 156 Weitersfeld Nieder\u00f6sterreich 2084",
    "addr:housenumber":"156",
    "addr:postcode":"2084",
    "addr:street":"Weitersfeld",
    "iso:country":"AT",
    "sg:address":"Weitersfeld 156",
    "sg:city":"Weitersfeld",
    "sg:orig_category":"Dienstleistungen, Sonstige Dienstleistungen",
    "sg:postcode":"2084",
    "sg:province":"Nieder\u00f6sterreich",
    "sg:website":"http://www.winter-garten.at/optIndex.htm",
    "wof:name":"Tischlerei H\u00f6rmansdorfer - Winterg\u00e4rten und Wasserbetten",
    "wof:placetype":"venue"
},
  "geometry": {"coordinates":[15.8120307922,48.7801246643],"type":"Point"}
}