{
  "type": "Feature",
  "properties": {
    "addr:full":"Toni-Schruf-Str 2 Mitterdorf im M\u00fcrztal Steiermark 8662",
    "addr:housenumber":"2;im",
    "addr:postcode":"8662",
    "addr:street":"Toni-Schruf-Str;Muerztal Steiermark",
    "iso:country":"AT",
    "sg:address":"Toni-Schruf-Str 2",
    "sg:city":"Mitterdorf im M\u00fcrztal",
    "sg:orig_category":"Maler, Anstreicher U Lackierer",
    "sg:phone":"+43 4338 582248",
    "sg:postcode":"8662",
    "sg:province":"Steiermark",
    "wof:name":"Koudelka Erich",
    "wof:placetype":"venue"
},
  "geometry": {"coordinates":[15.5147237778,47.5355567932],"type":"Point"}
}