{
  "type": "Feature",
  "properties": {
    "iso:country":"AT",
    "sg:address":"Wiener Str 224",
    "sg:city":"G\u00f6sting",
    "sg:orig_category":"Personalbereitstellung",
    "sg:phone":"+43 316 585590",
    "sg:postcode":"8051",
    "sg:province":"Steiermark",
    "wof:name":"KIS Personalservice GmbH",
    "wof:placetype":"venue"
},
  "geometry": {"coordinates":[15.4081268311,47.0913581848],"type":"Point"}
}