{
  "type": "Feature",
  "properties": {
    "addr:full":"Wiener Str 58 Klosterneuburg Nieder\u00f6sterreich 3400",
    "addr:housenumber":"58",
    "addr:postcode":"3400",
    "addr:street":"Niederoesterreich",
    "iso:country":"AT",
    "sg:address":"Wiener Str 58",
    "sg:city":"Klosterneuburg",
    "sg:orig_category":"Glasereien",
    "sg:phone":"+43 2243 26856",
    "sg:postcode":"3400",
    "sg:province":"Nieder\u00f6sterreich",
    "wof:name":"Scharl Johannes",
    "wof:placetype":"venue"
},
  "geometry": {"coordinates":[16.3309001923,48.3028831482],"type":"Point"}
}