{
  "type": "Feature",
  "properties": {
    "iso:country":"AT",
    "sg:address":"Nr 62",
    "sg:city":"Lech",
    "sg:classifiers":[
        {
            "category":"Travel",
            "subcategory":"Hotels & Motels",
            "type":"Entertainment"
        }
    ],
    "sg:phone":"+43 4355 8324070",
    "sg:postcode":"6764",
    "sg:province":"Vorarlberg",
    "wof:name":"Hotel Angela GesmbH",
    "wof:placetype":"venue"
},
  "geometry": {"coordinates":[10.1417798996,47.2082939148],"type":"Point"}
}