{
  "type": "Feature",
  "properties": {
    "iso:country":"AT",
    "sg:address":"Wolfsgraben 54",
    "sg:city":"Klosterneuburg",
    "sg:orig_category":"Psychotherapie",
    "sg:phone":"+43 2243 22325",
    "sg:postcode":"3400",
    "sg:province":"Nieder\u00f6sterreich",
    "wof:name":"Kyomars Hariri Dr med univ",
    "wof:placetype":"venue"
},
  "geometry": {"coordinates":[16.3284492493,48.2849082947],"type":"Point"}
}