{
  "type": "Feature",
  "properties": {
    "iso:country":"AT",
    "sg:address":"Hintersteining 5",
    "sg:city":"Frankenburg am Hausruck",
    "sg:classifiers":[
        {
            "category":"Farming",
            "subcategory":"Livestock Farm",
            "type":"Manufacturing & Wholesale Goods"
        }
    ],
    "sg:phone":"+43 4376 838396",
    "sg:postcode":"4873",
    "sg:province":"Ober\u00f6sterreich",
    "sg:tags":[
        "-handel",
        "viehzucht",
        "u"
    ],
    "wof:name":"Kobleder Johann",
    "wof:placetype":"venue"
},
  "geometry": {"coordinates":[13.4651069641,48.0878677368],"type":"Point"}
}