{
  "type": "Feature",
  "properties": {
    "addr:full":"Albrechtskreithgasse 24 Wien Wien 1160",
    "addr:housenumber":"24",
    "addr:postcode":"1160",
    "addr:street":"Albrechtskreithgasse",
    "iso:country":"AT",
    "sg:address":"Albrechtskreithgasse 24",
    "sg:city":"Wien",
    "sg:classifiers":[
        {
            "category":"Wholesale",
            "subcategory":"Home Furnishings",
            "type":"Manufacturing & Wholesale Goods"
        }
    ],
    "sg:phone":"+43 1 4861428",
    "sg:postcode":"1160",
    "sg:province":"Wien",
    "sg:tags":[
        "chair"
    ],
    "wof:name":"Josef Gerzabek",
    "wof:placetype":"venue"
},
  "geometry": {"coordinates":[16.3173675537,48.220287323],"type":"Point"}
}