{
  "type": "Feature",
  "properties": {
    "addr:full":"Schwefel 40 Dornbirn Vorarlberg 6850",
    "addr:housenumber":"40",
    "addr:postcode":"6850",
    "addr:street":"Schwefel",
    "iso:country":"AT",
    "sg:address":"Schwefel 40",
    "sg:city":"Dornbirn",
    "sg:orig_category":"Tankstellen",
    "sg:phone":"+43 5572 55042",
    "sg:postcode":"6850",
    "sg:province":"Vorarlberg",
    "wof:name":"Shell Austria GmbH",
    "wof:placetype":"venue"
},
  "geometry": {"coordinates":[9.7413682938,47.4254341125],"type":"Point"}
}