{
  "type": "Feature",
  "properties": {
    "addr:full":"Ronachweg 372 Saalbach Salzburg 5753",
    "addr:housenumber":"372",
    "addr:postcode":"5753",
    "addr:street":"Saalbach Salzburg",
    "iso:country":"AT",
    "sg:address":"Ronachweg 372",
    "sg:city":"Saalbach",
    "sg:orig_category":"Appartements / Ferienwohnungen",
    "sg:phone":"+43 6541 6452",
    "sg:postcode":"5753",
    "sg:province":"Salzburg",
    "wof:name":"Appartementhaus Sch\u00f6nblick",
    "wof:placetype":"venue"
},
  "geometry": {"coordinates":[12.6367301941,47.3899307251],"type":"Point"}
}