{
  "type": "Feature",
  "properties": {
    "addr:full":"Eggenwaldweg 60 Innsbruck Tirol 6020",
    "addr:housenumber":"60",
    "addr:postcode":"6020",
    "addr:street":"Eggenwaldweg;Tirol",
    "iso:country":"AT",
    "sg:address":"Eggenwaldweg 60",
    "sg:city":"Innsbruck",
    "sg:orig_category":"Hobbyvereine",
    "sg:phone":"+43 512 262325",
    "sg:postcode":"6020",
    "sg:province":"Tirol",
    "wof:name":"Landeshauptschie\u00dfstand Innsbrucker Hauptsch\u00fctzengesellschaft",
    "wof:placetype":"venue"
},
  "geometry": {"coordinates":[11.4271011353,47.289264679],"type":"Point"}
}