{
  "type": "Feature",
  "properties": {
    "addr:full":"Innsbrucker Bundesstr 79b Salzburg Salzburg 5020",
    "addr:housenumber":"79b",
    "addr:postcode":"5020",
    "addr:street":"Salzburg",
    "iso:country":"AT",
    "sg:address":"Innsbrucker Bundesstr 79b",
    "sg:city":"Salzburg",
    "sg:classifiers":[
        {
            "category":"Shopping",
            "subcategory":"Party Supplies",
            "type":"Retail Goods"
        }
    ],
    "sg:phone":"+43 4366 2828989",
    "sg:postcode":"5020",
    "sg:province":"Salzburg",
    "sg:tags":[
        "u",
        "lichtanlagen",
        "ton-"
    ],
    "wof:name":"Licht Ton Video Markus Schwenter",
    "wof:placetype":"venue"
},
  "geometry": {"coordinates":[13.0107049942,47.799407959],"type":"Point"}
}