{
  "type": "Feature",
  "properties": {
    "addr:full":"Biberstr 15 Wien Wien 1010",
    "addr:housenumber":"15",
    "addr:postcode":"1010",
    "addr:street":"Biberstr",
    "iso:country":"AT",
    "sg:address":"Biberstr 15",
    "sg:city":"Wien",
    "sg:orig_category":"Architekten",
    "sg:phone":"+43 1 5129980",
    "sg:postcode":"1010",
    "sg:province":"Wien",
    "wof:name":"Handgriff Robert Arch Dipl-Ing",
    "wof:placetype":"venue"
},
  "geometry": {"coordinates":[16.3809566498,48.2108612061],"type":"Point"}
}