{
  "type": "Feature",
  "properties": {
    "addr:full":"Nr 155 Abfaltersbach Tirol 9913",
    "addr:postcode":"9913",
    "addr:street":"Nr;Abfaltersbach Tirol",
    "iso:country":"AT",
    "sg:address":"Nr 155",
    "sg:city":"Abfaltersbach",
    "sg:orig_category":"Tischlereien",
    "sg:phone":"+43 4846 62690",
    "sg:postcode":"9913",
    "sg:province":"Tirol",
    "wof:name":"Strasser Franz",
    "wof:placetype":"venue"
},
  "geometry": {"coordinates":[12.5290498734,46.7567977905],"type":"Point"}
}