{
  "type": "Feature",
  "properties": {
    "addr:full":"Au\u00dferrain 42 Neustift im Stubaital Tirol 6167",
    "addr:housenumber":"42",
    "addr:postcode":"6167",
    "addr:street":"Ausserrain;Tirol",
    "iso:country":"AT",
    "sg:address":"Au\u00dferrain 42",
    "sg:city":"Neustift im Stubaital",
    "sg:orig_category":"Erdarbeiten",
    "sg:phone":"+43 4352 262906",
    "sg:postcode":"6167",
    "sg:province":"Tirol",
    "wof:name":"Pfurtscheller Franz",
    "wof:placetype":"venue"
},
  "geometry": {"coordinates":[11.3075504303,47.1104850769],"type":"Point"}
}