{
  "type": "Feature",
  "properties": {
    "iso:country":"AT",
    "sg:address":"P\u00fchretstrasse 15",
    "sg:city":"Roitham",
    "sg:classifiers":[
        {
            "category":"Manufacturing",
            "subcategory":"Tools & Machinery",
            "type":"Manufacturing & Wholesale Goods"
        }
    ],
    "sg:phone":"+43 76135349",
    "sg:postcode":"4661",
    "sg:province":"Ober\u00f6sterreich",
    "sg:tags":[
        "part",
        "turned",
        "cnc"
    ],
    "sg:website":"spitzschuh.at",
    "wof:name":"Spitzschuh Maschinenbau GmbH",
    "wof:placetype":"venue"
},
  "geometry": {"coordinates":[13.8226041794,48.0241851807],"type":"Point"}
}