{
  "type": "Feature",
  "properties": {
    "addr:full":"Nr 32 Deutsch Goritz Steiermark 8483",
    "addr:postcode":"8483",
    "addr:street":"Nr",
    "iso:country":"AT",
    "sg:address":"Nr 32",
    "sg:city":"Deutsch Goritz",
    "sg:orig_category":"Elektroinstallationsunternehmen",
    "sg:phone":"+43 4334 748330",
    "sg:postcode":"8483",
    "sg:province":"Steiermark",
    "wof:name":"Kolar Waltraud",
    "wof:placetype":"venue"
},
  "geometry": {"coordinates":[15.8294000626,46.7518081665],"type":"Point"}
}