{
  "type": "Feature",
  "properties": {
    "addr:full":"Industriezone 3 Nassereith Tirol 6465",
    "addr:housenumber":"3",
    "addr:postcode":"6465",
    "addr:street":"Industriezone;Tirol",
    "iso:country":"AT",
    "sg:address":"Industriezone 3",
    "sg:city":"Nassereith",
    "sg:orig_category":"Autoreparatur",
    "sg:phone":"+43 5265 53270",
    "sg:postcode":"6465",
    "sg:province":"Tirol",
    "wof:name":"Sturm KFZ GmbH",
    "wof:placetype":"venue"
},
  "geometry": {"coordinates":[10.8377714157,47.3145332336],"type":"Point"}
}