{
  "type": "Feature",
  "properties": {
    "addr:full":"Frauenstiftg 12 Wien Wien 1210",
    "addr:housenumber":"12",
    "addr:postcode":"1210",
    "addr:street":"Frauenstiftg",
    "iso:country":"AT",
    "sg:address":"Frauenstiftg 12",
    "sg:city":"Wien",
    "sg:orig_category":"Fotoapparate U -Artikel / Einzelhandel",
    "sg:phone":"+43 4312 923523",
    "sg:postcode":"1210",
    "sg:province":"Wien",
    "wof:name":"Hartlauer HandelsgesmbH",
    "wof:placetype":"venue"
},
  "geometry": {"coordinates":[16.4078063965,48.2766418457],"type":"Point"}
}