{
  "type": "Feature",
  "properties": {
    "addr:full":"K\u00f6nigstetter Str 126 Tulln an der Donau Nieder\u00f6sterreich 3430",
    "addr:housenumber":"126",
    "addr:postcode":"3430",
    "addr:street":"Str",
    "iso:country":"AT",
    "sg:address":"K\u00f6nigstetter Str 126",
    "sg:city":"Tulln an der Donau",
    "sg:orig_category":"Autohandel",
    "sg:phone":"+43 2272 629770",
    "sg:postcode":"3430",
    "sg:province":"Nieder\u00f6sterreich",
    "wof:name":"Hummel R GmbH",
    "wof:placetype":"venue"
},
  "geometry": {"coordinates":[16.0775814056,48.3211898804],"type":"Point"}
}