{
  "type": "Feature",
  "properties": {
    "addr:full":"Dorfstr 37 Westendorf Tirol 6363",
    "addr:housenumber":"37",
    "addr:postcode":"6363",
    "addr:street":"Dorfstr;Tirol",
    "iso:country":"AT",
    "sg:address":"Dorfstr 37",
    "sg:city":"Westendorf",
    "sg:orig_category":"Appartements / Ferienwohnungen",
    "sg:phone":"+43 5334 676515",
    "sg:postcode":"6363",
    "sg:province":"Tirol",
    "wof:name":"Appartements Charlotte",
    "wof:placetype":"venue"
},
  "geometry": {"coordinates":[12.2163496017,47.4355201721],"type":"Point"}
}