{
  "type": "Feature",
  "properties": {
    "addr:full":"Gniebing 325 Feldbach Steiermark 8330",
    "addr:housenumber":"325",
    "addr:postcode":"8330",
    "addr:street":"Gniebing",
    "iso:country":"AT",
    "sg:address":"Gniebing 325",
    "sg:city":"Feldbach",
    "sg:orig_category":"Autohandel",
    "sg:phone":"+43 4331 5239586",
    "sg:postcode":"8330",
    "sg:province":"Steiermark",
    "wof:name":"Autohaus Hiebaum GmbH Ing",
    "wof:placetype":"venue"
},
  "geometry": {"coordinates":[15.8715000153,46.9597816467],"type":"Point"}
}