{
  "type": "Feature",
  "properties": {
    "addr:full":"Rappgasse 7 Wien Wien 1210",
    "addr:housenumber":"7",
    "addr:postcode":"1210",
    "addr:street":"Rappgasse",
    "iso:country":"AT",
    "sg:address":"Rappgasse 7",
    "sg:city":"Wien",
    "sg:classifiers":[
        {
            "category":"Communications",
            "subcategory":"Television Station",
            "type":"Services"
        }
    ],
    "sg:phone":"+43 4312 7175360",
    "sg:postcode":"1210",
    "sg:province":"Wien",
    "sg:tags":[
        "audio-visual"
    ],
    "wof:name":"W RIEDER ELKTROHANDELSGESMBH",
    "wof:placetype":"venue"
},
  "geometry": {"coordinates":[16.3939723969,48.268497467],"type":"Point"}
}