{
  "type": "Feature",
  "properties": {
    "addr:full":"Arthaberpl 18 Wien Wien 1100",
    "addr:housenumber":"18",
    "addr:postcode":"1100",
    "addr:street":"Arthaberpl",
    "iso:country":"AT",
    "sg:address":"Arthaberpl 18",
    "sg:city":"Wien",
    "sg:orig_category":"Volkshochschulen",
    "sg:phone":"+43 1 60340300",
    "sg:postcode":"1100",
    "sg:province":"Wien",
    "wof:name":"Volkshochschule Favoriten",
    "wof:placetype":"venue"
},
  "geometry": {"coordinates":[16.3705101013,48.173084259],"type":"Point"}
}