{
  "type": "Feature",
  "properties": {
    "addr:full":"Am F\u00fcrtherbach 12 Frankenburg am Hausruck Ober\u00f6sterreich 4873",
    "addr:housenumber":"12",
    "addr:postcode":"4873",
    "addr:street":"Am Fuertherbach",
    "iso:country":"AT",
    "sg:address":"Am F\u00fcrtherbach 12",
    "sg:city":"Frankenburg am Hausruck",
    "sg:orig_category":"Anlagenbau U -Technik",
    "sg:phone":"+43 4376 837077",
    "sg:postcode":"4873",
    "sg:province":"Ober\u00f6sterreich",
    "wof:name":"Becon Anlagenbau GmbH",
    "wof:placetype":"venue"
},
  "geometry": {"coordinates":[13.4651069641,48.0878677368],"type":"Point"}
}