{
  "type": "Feature",
  "properties": {
    "iso:country":"AT",
    "sg:address":"Feldweg 277",
    "sg:city":"Scharnitz",
    "sg:classifiers":[
        {
            "category":"Taxi",
            "type":"Transportation"
        }
    ],
    "sg:phone":"+43 5213 5233",
    "sg:postcode":"6108",
    "sg:province":"Tirol",
    "sg:tags":[
        "personentransporte",
        "u"
    ],
    "wof:name":"Taxi Fam Leism\u00fcller",
    "wof:placetype":"venue"
},
  "geometry": {"coordinates":[11.2631502151,47.388168335],"type":"Point"}
}