{
  "type": "Feature",
  "properties": {
    "addr:full":"Haller Str. 121  6025",
    "addr:postcode":"6025",
    "addr:street":"Str. 121",
    "iso:country":"AT",
    "sg:address":"Haller Str. 121 ",
    "sg:classifiers":[
        {
            "category":"Professional",
            "subcategory":"Printing & Photocopies",
            "type":"Services"
        }
    ],
    "sg:phone":"+43 4351 2247200",
    "sg:postcode":"6025",
    "wof:name":"ALPINA DRUCK GMBH & CO. KG",
    "wof:placetype":"venue"
},
  "geometry": {"coordinates":[11.3913040161,47.2679977417],"type":"Point"}
}