{
  "type": "Feature",
  "properties": {
    "addr:full":"Kirchenstr 4 Ertl Nieder\u00f6sterreich 3355",
    "addr:housenumber":"4",
    "addr:postcode":"3355",
    "addr:street":"Kirchenstr",
    "iso:country":"AT",
    "sg:address":"Kirchenstr 4",
    "sg:city":"Ertl",
    "sg:orig_category":"Parkettbodenverlegung",
    "sg:phone":"+43 4374 777100",
    "sg:postcode":"3355",
    "sg:province":"Nieder\u00f6sterreich",
    "wof:name":"Katzensteiner Martin",
    "wof:placetype":"venue"
},
  "geometry": {"coordinates":[14.6302146912,47.977142334],"type":"Point"}
}