{
  "type": "Feature",
  "properties": {
    "addr:full":"Anton-Freunschlag-G 70 Wien Wien 1230",
    "addr:housenumber":"70",
    "addr:postcode":"1230",
    "addr:street":"Anton-Freunschlag-G",
    "iso:country":"AT",
    "sg:address":"Anton-Freunschlag-G 70",
    "sg:city":"Wien",
    "sg:orig_category":"Werbeagenturen",
    "sg:phone":"+43 1 6996347",
    "sg:postcode":"1230",
    "sg:province":"Wien",
    "wof:name":"Czeiner Gabriele - Agentur",
    "wof:placetype":"venue"
},
  "geometry": {"coordinates":[16.3196048737,48.129524231],"type":"Point"}
}