{
  "type": "Feature",
  "properties": {
    "addr:full":"Sch\u00f6nbrunner Str 190 Wien Wien 1120",
    "addr:housenumber":"190",
    "addr:postcode":"1120",
    "addr:street":"Str",
    "iso:country":"AT",
    "sg:address":"Sch\u00f6nbrunner Str 190",
    "sg:city":"Wien",
    "sg:orig_category":"Politische Parteien",
    "sg:phone":"+43 1 8159434",
    "sg:postcode":"1120",
    "sg:province":"Wien",
    "wof:name":"B\u00fcrgerb\u00fcro Meidling",
    "wof:placetype":"venue"
},
  "geometry": {"coordinates":[16.3290939331,48.1824874878],"type":"Point"}
}