{
  "type": "Feature",
  "properties": {
    "iso:country":"AT",
    "sg:address":"Westliche Scheunenstr 33",
    "sg:city":"Gerasdorf",
    "sg:orig_category":"Autoverwertung",
    "sg:phone":"+43 4366 43571141",
    "sg:postcode":"2201",
    "sg:province":"Nieder\u00f6sterreich",
    "sg:website":"autoverwertung-migsch.at",
    "wof:name":"VW & Audi Autoverwertung Gerhard Migsch",
    "wof:placetype":"venue"
},
  "geometry": {"coordinates":[16.4722003937,48.2971687317],"type":"Point"}
}