{
  "type": "Feature",
  "properties": {
    "addr:full":"Obere Hauptstr 14 Wilhelmsburg an der Traisen Nieder\u00f6sterreich 3150",
    "addr:housenumber":"14",
    "addr:postcode":"3150",
    "addr:street":"Obere Hauptstr;An",
    "iso:country":"AT",
    "sg:address":"Obere Hauptstr 14",
    "sg:city":"Wilhelmsburg an der Traisen",
    "sg:orig_category":"Fotografen",
    "sg:phone":"+43 4327 463315",
    "sg:postcode":"3150",
    "sg:province":"Nieder\u00f6sterreich",
    "wof:name":"plus foto",
    "wof:placetype":"venue"
},
  "geometry": {"coordinates":[15.605132103,48.1037063599],"type":"Point"}
}