{
  "type": "Feature",
  "properties": {
    "addr:full":"Nr 16 Neup\u00f6lla Nieder\u00f6sterreich 3593",
    "addr:postcode":"3593",
    "addr:street":"Nr 16 Neupoella",
    "iso:country":"AT",
    "sg:address":"Nr 16",
    "sg:city":"Neup\u00f6lla",
    "sg:orig_category":"Tierpensionen",
    "sg:phone":"+43 2989 8005",
    "sg:postcode":"3593",
    "sg:province":"Nieder\u00f6sterreich",
    "wof:name":"Tierpension El Perro",
    "wof:placetype":"venue"
},
  "geometry": {"coordinates":[15.4494380951,48.6421356201],"type":"Point"}
}