{
  "type": "Feature",
  "properties": {
    "iso:country":"AT",
    "sg:address":"Bahnhofstr 8",
    "sg:city":"Marchtrenk",
    "sg:orig_category":"Banken U Sparkassen",
    "sg:phone":"+43 5 010040102",
    "sg:postcode":"4614",
    "sg:province":"Ober\u00f6sterreich",
    "wof:name":"Allgemeine Sparkasse Ober\u00f6sterreich Bank AG",
    "wof:placetype":"venue"
},
  "geometry": {"coordinates":[14.1112680435,48.1912612915],"type":"Point"}
}