{
  "type": "Feature",
  "properties": {
    "addr:full":"Handelsstr 1 St. Valentin Nieder\u00f6sterreich 4300",
    "addr:housenumber":"1",
    "addr:postcode":"4300",
    "addr:street":"Handelsstr",
    "iso:country":"AT",
    "sg:address":"Handelsstr 1",
    "sg:city":"St. Valentin",
    "sg:orig_category":"Autoreparatur",
    "sg:phone":"+43 7435 523830",
    "sg:postcode":"4300",
    "sg:province":"Nieder\u00f6sterreich",
    "wof:name":"Kammerhuber GmbH",
    "wof:placetype":"venue"
},
  "geometry": {"coordinates":[14.5193910599,48.1937065125],"type":"Point"}
}