{
  "type": "Feature",
  "properties": {
    "addr:full":"Kelsenstr 7 Wien Wien 1030",
    "addr:housenumber":"7",
    "addr:postcode":"1030",
    "addr:street":"Kelsenstr",
    "iso:country":"AT",
    "sg:address":"Kelsenstr 7",
    "sg:city":"Wien",
    "sg:orig_category":"Papier / Erzeugung U Gro\u00c3\u0178handel",
    "sg:phone":"+43 4317 95230",
    "sg:postcode":"1030",
    "sg:province":"Wien",
    "wof:name":"Mondi Packaging Bag Division GmbH",
    "wof:placetype":"venue"
},
  "geometry": {"coordinates":[16.3935279846,48.1864700317],"type":"Point"}
}