{
  "type": "Feature",
  "properties": {
    "addr:full":"Reintal Nieder\u00f6sterreich 2276",
    "addr:housenumber":"2276",
    "addr:street":"Niederoesterreich",
    "iso:country":"AT",
    "sg:city":"Reintal",
    "sg:orig_category":"Forstverwaltungen",
    "sg:phone":"+43 2557 8838",
    "sg:postcode":"2276",
    "sg:province":"Nieder\u00f6sterreich",
    "wof:name":"Liechtenstein Stiftung F\u00fcrst",
    "wof:placetype":"venue"
},
  "geometry": {"coordinates":[16.7840442657,48.6993942261],"type":"Point"}
}