{
  "type": "Feature",
  "properties": {
    "addr:full":"Scheibenbergstr 52 Wien Wien 1180",
    "addr:housenumber":"52",
    "addr:postcode":"1180",
    "addr:street":"Scheibenbergstr",
    "iso:country":"AT",
    "sg:address":"Scheibenbergstr 52",
    "sg:city":"Wien",
    "sg:orig_category":"Werbeagenturen",
    "sg:phone":"+43 1 36957220",
    "sg:postcode":"1180",
    "sg:province":"Wien",
    "wof:name":"Plus Werbeagentur GesmbH & Co KG",
    "wof:placetype":"venue"
},
  "geometry": {"coordinates":[16.3182659149,48.2386016846],"type":"Point"}
}