{
  "type": "Feature",
  "properties": {
    "addr:full":"Salzstr 12 Flaurling Tirol 6403",
    "addr:housenumber":"12",
    "addr:postcode":"6403",
    "addr:street":"Salzstr;Tirol",
    "iso:country":"AT",
    "sg:address":"Salzstr 12",
    "sg:city":"Flaurling",
    "sg:orig_category":"Banken U Sparkassen",
    "sg:phone":"+43 5262 62754",
    "sg:postcode":"6403",
    "sg:province":"Tirol",
    "wof:name":"Raiffeisen-Regionalbank Telfs regGenmbH",
    "wof:placetype":"venue"
},
  "geometry": {"coordinates":[11.1240262985,47.2913665771],"type":"Point"}
}