{
  "type": "Feature",
  "properties": {
    "addr:full":"Vinzenzg 75 Graz Steiermark 8020",
    "addr:housenumber":"75",
    "addr:postcode":"8020",
    "addr:street":"Vinzenzg",
    "iso:country":"AT",
    "sg:address":"Vinzenzg 75",
    "sg:city":"Graz",
    "sg:orig_category":"Transportunternehmen",
    "sg:phone":"+43 316 5812430",
    "sg:postcode":"8020",
    "sg:province":"Steiermark",
    "wof:name":"Walch Franz TransportgesmbH & Co KG",
    "wof:placetype":"venue"
},
  "geometry": {"coordinates":[15.4052820206,47.07862854],"type":"Point"}
}