{
  "type": "Feature",
  "properties": {
    "addr:full":"Rathauspl 7 Pulkau Nieder\u00f6sterreich 3741",
    "addr:housenumber":"7",
    "addr:postcode":"3741",
    "addr:street":"Rathauspl",
    "iso:country":"AT",
    "sg:address":"Rathauspl 7",
    "sg:city":"Pulkau",
    "sg:orig_category":"Elektroinstallationsunternehmen",
    "sg:phone":"+43 2946 27475",
    "sg:postcode":"3741",
    "sg:province":"Nieder\u00f6sterreich",
    "wof:name":"J\u00e4ger & Kronsteiner Elektrotechnik GmbH & Co KG",
    "wof:placetype":"venue"
},
  "geometry": {"coordinates":[15.8590717316,48.7052650452],"type":"Point"}
}