{
  "type": "Feature",
  "properties": {
    "addr:full":"Marktpl 9 Weyer Ober\u00f6sterreich 3335",
    "addr:housenumber":"9",
    "addr:postcode":"3335",
    "addr:street":"Marktpl",
    "iso:country":"AT",
    "sg:address":"Marktpl 9",
    "sg:city":"Weyer",
    "sg:orig_category":"Druckereien",
    "sg:phone":"+43 7355 6279",
    "sg:postcode":"3335",
    "sg:province":"Ober\u00f6sterreich",
    "wof:name":"Ahamer Druckerei GesmbH",
    "wof:placetype":"venue"
},
  "geometry": {"coordinates":[14.6641483307,47.857673645],"type":"Point"}
}