{
  "type": "Feature",
  "properties": {
    "iso:country":"AT",
    "sg:address":"Brunng 38",
    "sg:city":"Poysdorf",
    "sg:orig_category":"Finanz- U Wirtschaftsberatung",
    "sg:phone":"+43 4325 52211213",
    "sg:postcode":"2170",
    "sg:province":"Nieder\u00f6sterreich",
    "wof:name":"AWD Beratungszentrum Poysdorf",
    "wof:placetype":"venue"
},
  "geometry": {"coordinates":[16.6250782013,48.6689186096],"type":"Point"}
}