{
  "type": "Feature",
  "properties": {
    "addr:full":"Uferstrasse 15 Maishofen Salzburg 5751",
    "addr:housenumber":"15",
    "addr:postcode":"5751",
    "addr:street":"Uferstrasse;Salzburg",
    "iso:country":"AT",
    "sg:address":"Uferstrasse 15",
    "sg:city":"Maishofen",
    "sg:classifiers":[
        {
            "category":"Home & Garden",
            "subcategory":"Building Materials",
            "type":"Retail Goods"
        }
    ],
    "sg:phone":"+43 6542 80235",
    "sg:postcode":"5751",
    "sg:province":"Salzburg",
    "sg:tags":[
        "tile",
        "granite"
    ],
    "wof:name":"Holz M. FliesengesmbH",
    "wof:placetype":"venue"
},
  "geometry": {"coordinates":[12.8250045776,47.38048172],"type":"Point"}
}