{
  "type": "Feature",
  "properties": {
    "iso:country":"AT",
    "sg:address":"Bahnhofstr 34",
    "sg:city":"Tulln an der Donau",
    "sg:orig_category":"Friseure U Frisiersalons",
    "sg:phone":"+43 4322 7263387",
    "sg:postcode":"3430",
    "sg:province":"Nieder\u00f6sterreich",
    "wof:name":"Ihr Fris\u00f6r XXL Kamlander",
    "wof:placetype":"venue"
},
  "geometry": {"coordinates":[16.0567512512,48.3278045654],"type":"Point"}
}