{
  "type": "Feature",
  "properties": {
    "addr:full":"Markt 133 Kaumberg Nieder\u00f6sterreich 2572",
    "addr:housenumber":"133",
    "addr:postcode":"2572",
    "addr:street":"Markt",
    "iso:country":"AT",
    "sg:address":"Markt 133",
    "sg:city":"Kaumberg",
    "sg:classifiers":[
        {
            "category":"Manufacturing",
            "subcategory":"Metals",
            "type":"Manufacturing & Wholesale Goods"
        }
    ],
    "sg:phone":"+43 2765 80800",
    "sg:postcode":"2572",
    "sg:province":"Nieder\u00f6sterreich",
    "sg:tags":[
        "processing"
    ],
    "wof:name":"IPA Produktions- & Vertriebs Ges.m.b.H.",
    "wof:placetype":"venue"
},
  "geometry": {"coordinates":[15.8943567276,48.0352554321],"type":"Point"}
}