{
  "type": "Feature",
  "properties": {
    "iso:country":"AT",
    "sg:address":"Altausseer Str 59",
    "sg:city":"Bad Aussee",
    "sg:orig_category":"Schneidereien",
    "sg:phone":"+43 4336 2252260",
    "sg:postcode":"8990",
    "sg:province":"Steiermark",
    "wof:name":"Raich Christian",
    "wof:placetype":"venue"
},
  "geometry": {"coordinates":[13.7786149979,47.6124725342],"type":"Point"}
}