{
  "type": "Feature",
  "properties": {
    "addr:full":"Poscherberg 45 Pregarten Ober\u00f6sterreich 4230",
    "addr:housenumber":"45",
    "addr:postcode":"4230",
    "addr:street":"Poscherberg",
    "iso:country":"AT",
    "sg:address":"Poscherberg 45",
    "sg:city":"Pregarten",
    "sg:orig_category":"\u00c3\u201erzte / F Allgemeinmedizin",
    "sg:phone":"+43 7236 3244",
    "sg:postcode":"4230",
    "sg:province":"Ober\u00f6sterreich",
    "wof:name":"Brandstetter Werner Dr",
    "wof:placetype":"venue"
},
  "geometry": {"coordinates":[14.5364160538,48.3598327637],"type":"Point"}
}