{
  "type": "Feature",
  "properties": {
    "addr:full":"Hagenm\u00fchle 20 Kirchham Ober\u00f6sterreich 4656",
    "addr:housenumber":"20",
    "addr:postcode":"4656",
    "addr:street":"Hagenmuehle",
    "iso:country":"AT",
    "sg:address":"Hagenm\u00fchle 20",
    "sg:city":"Kirchham",
    "sg:orig_category":"Feuerwehren",
    "sg:phone":"+43 76192626",
    "sg:postcode":"4656",
    "sg:province":"Ober\u00f6sterreich",
    "wof:name":"Freiwillige Feuerwehr Feichtenberg",
    "wof:placetype":"venue"
},
  "geometry": {"coordinates":[13.8986949921,47.9711112976],"type":"Point"}
}