{
  "type": "Feature",
  "properties": {
    "addr:full":"Tannenbach 3 Lochau Vorarlberg 6911",
    "addr:housenumber":"3",
    "addr:postcode":"6911",
    "addr:street":"Tannenbach",
    "iso:country":"AT",
    "sg:address":"Tannenbach 3",
    "sg:city":"Lochau",
    "sg:orig_category":"Autohandel",
    "sg:phone":"+43 5574 443100",
    "sg:postcode":"6911",
    "sg:province":"Vorarlberg",
    "wof:name":"Malang VW Audi GmbH",
    "wof:placetype":"venue"
},
  "geometry": {"coordinates":[9.7485046387,47.5290145874],"type":"Point"}
}