{
  "type": "Feature",
  "properties": {
    "addr:full":"Bahnhofstr 6 Waizenkirchen Ober\u00f6sterreich 4730",
    "addr:housenumber":"6",
    "addr:postcode":"4730",
    "addr:street":"Bahnhofstr",
    "iso:country":"AT",
    "sg:address":"Bahnhofstr 6",
    "sg:city":"Waizenkirchen",
    "sg:orig_category":"Farben U Lacke / Einzelhandel",
    "sg:phone":"+43 7277 27750",
    "sg:postcode":"4730",
    "sg:province":"Ober\u00f6sterreich",
    "wof:name":"Sch\u00fctzeneder Norbert",
    "wof:placetype":"venue"
},
  "geometry": {"coordinates":[13.8515577316,48.3297309875],"type":"Point"}
}