{
  "type": "Feature",
  "properties": {
    "iso:country":"AT",
    "sg:address":"Neualmer Strasse 33",
    "sg:city":"Hallein",
    "sg:classifiers":[
        {
            "category":"Social Services",
            "subcategory":"Retirement Home",
            "type":"Services"
        }
    ],
    "sg:phone":"+43 6245 841920",
    "sg:postcode":"5400",
    "sg:province":"Salzburg",
    "sg:tags":[
        "slipper",
        "house"
    ],
    "sg:website":"rohde-schuhe.de",
    "wof:name":"Schuhfabrik Rohde-Schuh Ges.m.b.H.",
    "wof:placetype":"venue"
},
  "geometry": {"coordinates":[13.0868330002,47.6904525757],"type":"Point"}
}