{
  "type": "Feature",
  "properties": {
    "addr:full":"Hauptstr 400 Mayrhofen Tirol 6290",
    "addr:housenumber":"400",
    "addr:postcode":"6290",
    "addr:street":"Hauptstr;Tirol",
    "iso:country":"AT",
    "sg:address":"Hauptstr 400",
    "sg:city":"Mayrhofen",
    "sg:classifiers":[
        {
            "category":"Travel",
            "subcategory":"Hotels & Motels",
            "type":"Entertainment"
        }
    ],
    "sg:phone":"+43 4352 8562131",
    "sg:postcode":"6290",
    "sg:province":"Tirol",
    "wof:name":"Hotel Neue Post",
    "wof:placetype":"venue"
},
  "geometry": {"coordinates":[11.8650941849,47.1691093445],"type":"Point"}
}