{
  "type": "Feature",
  "properties": {
    "addr:full":"Wuhrkopfweg 1 Kennelbach Vorarlberg 6921",
    "addr:housenumber":"1",
    "addr:postcode":"6921",
    "addr:street":"Wuhrkopfweg",
    "iso:country":"AT",
    "sg:address":"Wuhrkopfweg 1",
    "sg:city":"Kennelbach",
    "sg:orig_category":"Gewerbeparks",
    "sg:phone":"+43 5574 714360",
    "sg:postcode":"6921",
    "sg:province":"Vorarlberg",
    "wof:name":"Schindler KG",
    "wof:placetype":"venue"
},
  "geometry": {"coordinates":[9.7636508942,47.4774856567],"type":"Point"}
}