{
  "type": "Feature",
  "properties": {
    "iso:country":"AT",
    "sg:address":"Hauptstr 47",
    "sg:city":"St. Valentin",
    "sg:orig_category":"Blumeneinzelhandel",
    "sg:phone":"+43 4374 3559950",
    "sg:postcode":"4300",
    "sg:province":"Nieder\u00f6sterreich",
    "wof:name":"Naturwerkstatt Nabinger Christine",
    "wof:placetype":"venue"
},
  "geometry": {"coordinates":[14.5260744095,48.1749343872],"type":"Point"}
}