{
  "type": "Feature",
  "properties": {
    "addr:full":"Hauptpl 14a Tulln an der Donau Nieder\u00f6sterreich 3430",
    "addr:housenumber":"14a",
    "addr:postcode":"3430",
    "addr:street":"Hauptpl",
    "iso:country":"AT",
    "sg:address":"Hauptpl 14a",
    "sg:city":"Tulln an der Donau",
    "sg:orig_category":"Appartements / Ferienwohnungen",
    "sg:phone":"+43 4322 7263115",
    "sg:postcode":"3430",
    "sg:province":"Nieder\u00f6sterreich",
    "sg:website":"tenora.at",
    "wof:name":"Pension Springbrunnen F u M Tenora",
    "wof:placetype":"venue"
},
  "geometry": {"coordinates":[16.0500946045,48.3306427002],"type":"Point"}
}