{
  "type": "Feature",
  "properties": {
    "addr:full":"Brunnthalg 22-24 Hollabrunn Nieder\u00f6sterreich 2020",
    "addr:postcode":"22-24;2020",
    "addr:street":"Niederoesterreich",
    "iso:country":"AT",
    "sg:address":"Brunnthalg 22-24",
    "sg:city":"Hollabrunn",
    "sg:orig_category":"Baumeister",
    "sg:phone":"+43 2952 21490",
    "sg:postcode":"2020",
    "sg:province":"Nieder\u00f6sterreich",
    "wof:name":"Schuster Manfred Ing GesmbH",
    "wof:placetype":"venue"
},
  "geometry": {"coordinates":[16.074760437,48.5654716492],"type":"Point"}
}