{
  "type": "Feature",
  "properties": {
    "addr:full":"Dorfpl 1 Fieberbrunn Tirol 6391",
    "addr:housenumber":"1",
    "addr:postcode":"6391",
    "addr:street":"Dorfpl;Tirol",
    "iso:country":"AT",
    "sg:address":"Dorfpl 1",
    "sg:city":"Fieberbrunn",
    "sg:orig_category":"Gemeinden",
    "sg:phone":"+43 5354 562030",
    "sg:postcode":"6391",
    "sg:province":"Tirol",
    "wof:name":"Marktgemeinde Fieberbrunn",
    "wof:placetype":"venue"
},
  "geometry": {"coordinates":[12.5448684692,47.4765357971],"type":"Point"}
}