{
  "type": "Feature",
  "properties": {
    "addr:full":"Schlo\u00dfg 12 Dornbirn Vorarlberg 6850",
    "addr:housenumber":"12",
    "addr:postcode":"6850",
    "addr:street":"Schlossg",
    "iso:country":"AT",
    "sg:address":"Schlo\u00dfg 12",
    "sg:city":"Dornbirn",
    "sg:classifiers":[
        {
            "category":"Taxi",
            "type":"Transportation"
        }
    ],
    "sg:phone":"+43 4355 7225454",
    "sg:postcode":"6850",
    "sg:province":"Vorarlberg",
    "sg:tags":[
        "personentransporte",
        "u"
    ],
    "wof:name":"Kuchling Margit",
    "wof:placetype":"venue"
},
  "geometry": {"coordinates":[9.7527093887,47.4110908508],"type":"Point"}
}