{
  "type": "Feature",
  "properties": {
    "iso:country":"AT",
    "sg:address":"Bahnhofplatz 5",
    "sg:city":"Wolfsberg",
    "sg:classifiers":[
        {
            "category":"Home & Garden",
            "subcategory":"Household Appliances",
            "type":"Retail Goods"
        }
    ],
    "sg:phone":"+43 4352 2293",
    "sg:postcode":"9400",
    "sg:province":"K\u00e4rnten",
    "sg:tags":[
        "electric"
    ],
    "wof:name":"Walter Dohr",
    "wof:placetype":"venue"
},
  "geometry": {"coordinates":[14.8395309448,46.8417778015],"type":"Point"}
}