{
  "type": "Feature",
  "properties": {
    "iso:country":"AT",
    "sg:address":"Schweizer G 1",
    "sg:city":"Lienz",
    "sg:orig_category":"Boutiquen",
    "sg:phone":"+43 4348 5264127",
    "sg:postcode":"9900",
    "sg:province":"Tirol",
    "wof:name":"Basar - Andreas Tagger",
    "wof:placetype":"venue"
},
  "geometry": {"coordinates":[12.7639322281,46.8305740356],"type":"Point"}
}