{
  "type": "Feature",
  "properties": {
    "addr:full":"Lacknergasse 7 Wien Wien 1170",
    "addr:housenumber":"7",
    "addr:postcode":"1170",
    "addr:street":"Lacknergasse",
    "iso:country":"AT",
    "sg:address":"Lacknergasse 7",
    "sg:city":"Wien",
    "sg:classifiers":[
        {
            "category":"Banks & Credit Unions",
            "subcategory":"Investment Brokerage",
            "type":"Services"
        }
    ],
    "sg:phone":"+43 1 4862332",
    "sg:postcode":"1170",
    "sg:province":"Wien",
    "sg:tags":[
        "engraving",
        "hand"
    ],
    "wof:name":"Andreas Schatz",
    "wof:placetype":"venue"
},
  "geometry": {"coordinates":[16.3283233643,48.219417572],"type":"Point"}
}