{
  "type": "Feature",
  "properties": {
    "addr:full":"Matin 45 B\u00fcrserberg Vorarlberg 6707",
    "addr:housenumber":"45;6707",
    "addr:street":"Buerserberg Vorarlberg",
    "iso:country":"AT",
    "sg:address":"Matin 45",
    "sg:city":"B\u00fcrserberg",
    "sg:orig_category":"Volksschulen",
    "sg:phone":"+43 5552 33436",
    "sg:postcode":"6707",
    "sg:province":"Vorarlberg",
    "wof:name":"Volksschule B\u00fcrserberg",
    "wof:placetype":"venue"
},
  "geometry": {"coordinates":[9.777261734,47.1468582153],"type":"Point"}
}