{
  "type": "Feature",
  "properties": {
    "addr:full":"Am Kirchanger 8  Guntramsdorf Nieder\u00f6sterreich 2353",
    "addr:housenumber":"8",
    "addr:postcode":"2353",
    "addr:street":"Am Kirchanger",
    "iso:country":"AT",
    "sg:address":"Am Kirchanger 8 ",
    "sg:city":"Guntramsdorf",
    "sg:classifiers":[
        {
            "category":"Banks & Credit Unions",
            "subcategory":"Bank",
            "type":"Services"
        }
    ],
    "sg:phone":"+43 4322 36532020",
    "sg:postcode":"2353",
    "sg:province":"Nieder\u00f6sterreich",
    "sg:tags":[
        "banking",
        "institution"
    ],
    "wof:name":"RAIFFEISENKASSE GMBH",
    "wof:placetype":"venue"
},
  "geometry": {"coordinates":[16.3121929169,48.0478897095],"type":"Point"}
}