{
  "type": "Feature",
  "properties": {
    "addr:full":"Hugo-von-Hofmannsthal-Str 6 St. P\u00f6lten Nieder\u00f6sterreich 3100",
    "addr:housenumber":"6",
    "addr:postcode":"3100",
    "addr:street":"Hugo-Von-Hofmannsthal-Str",
    "iso:country":"AT",
    "sg:address":"Hugo-von-Hofmannsthal-Str 6",
    "sg:city":"St. P\u00f6lten",
    "sg:orig_category":"Autoersatzteile",
    "sg:phone":"+43 4327 42881096",
    "sg:postcode":"3100",
    "sg:province":"Nieder\u00f6sterreich",
    "wof:name":"Forstinger Handel und Service GmbH",
    "wof:placetype":"venue"
},
  "geometry": {"coordinates":[15.6240940094,48.2076377869],"type":"Point"}
}