{
  "type": "Feature",
  "properties": {
    "iso:country":"AT",
    "sg:address":"Geblergasse 60",
    "sg:city":"Wien",
    "sg:classifiers":[
        {
            "category":"Utilities",
            "subcategory":"Natural Gas",
            "type":"Services"
        }
    ],
    "sg:phone":"+43 1 4081850",
    "sg:postcode":"1170",
    "sg:province":"Wien",
    "sg:tags":[
        "heater",
        "direct",
        "electric"
    ],
    "wof:name":"Helga Kast",
    "wof:placetype":"venue"
},
  "geometry": {"coordinates":[16.3317070007,48.2166099548],"type":"Point"}
}