{
  "type": "Feature",
  "properties": {
    "addr:full":"Nr 143A Sillian Tirol 9920",
    "addr:postcode":"9920",
    "addr:street":"Nr;Sillian Tirol",
    "iso:country":"AT",
    "sg:address":"Nr 143A",
    "sg:city":"Sillian",
    "sg:orig_category":"Hobbyvereine",
    "sg:phone":"+43 4842 20119",
    "sg:postcode":"9920",
    "sg:province":"Tirol",
    "wof:name":"Sch\u00fctzengilde Hochpuster",
    "wof:placetype":"venue"
},
  "geometry": {"coordinates":[12.4398870468,46.7495117188],"type":"Point"}
}