{
  "type": "Feature",
  "properties": {
    "addr:full":"Franz M Felder-Str 2 Hohenems Vorarlberg 6845",
    "addr:housenumber":"2",
    "addr:postcode":"6845",
    "iso:country":"AT",
    "sg:address":"Franz M Felder-Str 2",
    "sg:city":"Hohenems",
    "sg:orig_category":"Blumeneinzelhandel",
    "sg:phone":"+43 5576 763610",
    "sg:postcode":"6845",
    "sg:province":"Vorarlberg",
    "wof:name":"Blumenhof - Blumen & Geschenke HandelsgmbH",
    "wof:placetype":"venue"
},
  "geometry": {"coordinates":[9.6848859787,47.362159729],"type":"Point"}
}