{
  "type": "Feature",
  "properties": {
    "iso:country":"AT",
    "sg:address":"Rauscherstrasse 10",
    "sg:city":"Hausmening",
    "sg:classifiers":[
        {
            "category":"Structure",
            "subcategory":"Bridge",
            "type":"Public Place"
        }
    ],
    "sg:phone":"+43 7475 522210",
    "sg:postcode":"3363",
    "sg:province":"Nieder\u00f6sterreich",
    "sg:tags":[
        "construction"
    ],
    "wof:name":"Leitner-Bau Ges.m.b.H.",
    "wof:placetype":"venue"
},
  "geometry": {"coordinates":[14.816365242,48.0766716003],"type":"Point"}
}