{
  "type": "Feature",
  "properties": {
    "addr:full":"Pischelsdorf Zwentendorf an der Donau Nieder\u00f6sterreich 3435",
    "addr:postcode":"3435",
    "iso:country":"AT",
    "sg:address":"Pischelsdorf",
    "sg:city":"Zwentendorf an der Donau",
    "sg:classifiers":[
        {
            "category":"Home & Garden",
            "subcategory":"Building Materials",
            "type":"Retail Goods"
        }
    ],
    "sg:phone":"+43 2277 20030",
    "sg:postcode":"3435",
    "sg:province":"Nieder\u00f6sterreich",
    "sg:tags":[
        "coating",
        "floor"
    ],
    "sg:website":"latexia.at",
    "wof:name":"Latexia \u00d6sterreich GmbH",
    "wof:placetype":"venue"
},
  "geometry": {"coordinates":[15.9521598816,48.3283996582],"type":"Point"}
}