{
  "type": "Feature",
  "properties": {
    "addr:full":"Bisamberger Str 4 Korneuburg Nieder\u00f6sterreich 2100",
    "addr:housenumber":"4",
    "addr:postcode":"2100",
    "addr:street":"Str;Niederoesterreich",
    "iso:country":"AT",
    "sg:address":"Bisamberger Str 4",
    "sg:city":"Korneuburg",
    "sg:orig_category":"Versicherungsunternehmen",
    "sg:phone":"+43 2262 75134",
    "sg:postcode":"2100",
    "sg:province":"Nieder\u00f6sterreich",
    "wof:name":"Grazer Wechselseitige Versicherung AG",
    "wof:placetype":"venue"
},
  "geometry": {"coordinates":[16.3354320526,48.3431549072],"type":"Point"}
}