{
  "type": "Feature",
  "properties": {
    "iso:country":"AT",
    "sg:address":"Haltestellenweg 23",
    "sg:city":"Bad Hofgastein",
    "sg:classifiers":[
        {
            "category":"Travel",
            "subcategory":"Hotels & Motels",
            "type":"Entertainment"
        }
    ],
    "sg:phone":"+43 6432 64440",
    "sg:postcode":"5630",
    "sg:province":"Salzburg",
    "sg:website":"www.pyrkerhoehe.com",
    "wof:name":"Apparthotel Pyrkerh\u00f6he",
    "wof:placetype":"venue"
},
  "geometry": {"coordinates":[13.094080925,47.1695289612],"type":"Point"}
}