{
  "type": "Feature",
  "properties": {
    "addr:full":"Gregoryg 29 Wien Wien 1230",
    "addr:housenumber":"29",
    "addr:postcode":"1230",
    "addr:street":"Gregoryg",
    "iso:country":"AT",
    "sg:address":"Gregoryg 29",
    "sg:city":"Wien",
    "sg:orig_category":"Non-Classified Establishments",
    "sg:phone":"+43 1 8040169",
    "sg:postcode":"1230",
    "sg:province":"Wien",
    "wof:name":"Kirche Jesu Christi der Heiligen der letzten Tage",
    "wof:placetype":"venue"
},
  "geometry": {"coordinates":[16.3062286377,48.1531677246],"type":"Point"}
}