{
  "type": "Feature",
  "properties": {
    "addr:full":"Marktpl 27 Altheim Ober\u00f6sterreich 4950",
    "addr:housenumber":"27",
    "addr:postcode":"4950",
    "addr:street":"Marktpl",
    "iso:country":"AT",
    "sg:address":"Marktpl 27",
    "sg:city":"Altheim",
    "sg:orig_category":"Non-Classified Establishments",
    "sg:phone":"+43 5 91334202",
    "sg:postcode":"4950",
    "sg:province":"Ober\u00f6sterreich",
    "wof:name":"Gendarmerieposten",
    "wof:placetype":"venue"
},
  "geometry": {"coordinates":[13.2322597504,48.2501029968],"type":"Point"}
}