{
  "type": "Feature",
  "properties": {
    "addr:full":"Radetzkystr 10 Graz Steiermark 8010",
    "addr:housenumber":"10",
    "addr:postcode":"8010",
    "addr:street":"Radetzkystr",
    "iso:country":"AT",
    "sg:address":"Radetzkystr 10",
    "sg:city":"Graz",
    "sg:orig_category":"Marketingberatung",
    "sg:phone":"+43 664 3002573",
    "sg:postcode":"8010",
    "sg:province":"Steiermark",
    "wof:name":"Sassmann Bernhard - ProNet-A Kommunikationsberatung",
    "wof:placetype":"venue"
},
  "geometry": {"coordinates":[15.4396266937,47.0666618347],"type":"Point"}
}