{
  "type": "Feature",
  "properties": {
    "iso:country":"AT",
    "sg:address":"Johann-H\u00f6sl-G 3",
    "sg:city":"Pfaffst\u00e4tten",
    "sg:classifiers":[
        {
            "category":"Professional",
            "subcategory":"Computer Services",
            "type":"Services"
        }
    ],
    "sg:phone":"+43 4322 5280551",
    "sg:postcode":"2511",
    "sg:province":"Nieder\u00f6sterreich",
    "sg:tags":[
        "software"
    ],
    "wof:name":"A & S Software GmbH",
    "wof:placetype":"venue"
},
  "geometry": {"coordinates":[-80.22983551030001,40.6486549377],"type":"Point"}
}