{
  "type": "Feature",
  "properties": {
    "iso:country":"AT",
    "sg:address":"Langobardenstr 189",
    "sg:city":"Wien",
    "sg:orig_category":"Behinderungen / Leben Mit Behinderungen",
    "sg:phone":"+43 4312 802070",
    "sg:postcode":"1220",
    "sg:province":"Wien",
    "wof:name":"Mobile Fr\u00fchf\u00f6rderung d Wiener Sozialdienste Standort Nord",
    "wof:placetype":"venue"
},
  "geometry": {"coordinates":[16.4757061005,48.218132019],"type":"Point"}
}