{
  "type": "Feature",
  "properties": {
    "iso:country":"AT",
    "sg:address":"Am Wierner Neust\u00e4dter Kanal",
    "sg:city":"Eggendorf",
    "sg:classifiers":[
        {
            "category":"Home & Garden",
            "subcategory":"Garden Supply",
            "type":"Retail Goods"
        }
    ],
    "sg:phone":"+43 4326 2862156",
    "sg:postcode":"2492",
    "sg:province":"Nieder\u00f6sterreich",
    "sg:tags":[
        "schotter",
        "sand",
        "u"
    ],
    "wof:name":"Wopfinger Transportbeton GesmbH",
    "wof:placetype":"venue"
},
  "geometry": {"coordinates":[8.1344404221,49.3539199829],"type":"Point"}
}