{
  "type": "Feature",
  "properties": {
    "addr:full":"Grazer Str 24 Langenwang Steiermark 8665",
    "addr:postcode":"8665",
    "addr:street":"Str",
    "iso:country":"AT",
    "sg:address":"Grazer Str 24",
    "sg:city":"Langenwang",
    "sg:orig_category":"Friseure U Frisiersalons",
    "sg:phone":"+43 4338 5461010",
    "sg:postcode":"8665",
    "sg:province":"Steiermark",
    "wof:name":"Stelzer Peter",
    "wof:placetype":"venue"
},
  "geometry": {"coordinates":[15.6192960739,47.5677909851],"type":"Point"}
}