{
  "type": "Feature",
  "properties": {
    "iso:country":"AT",
    "sg:address":"Inzenhof 66",
    "sg:city":"G\u00fcssing",
    "sg:orig_category":"Drinking Fountains, Drinking Water Fountains",
    "sg:phone":"+43 3322 42100",
    "sg:postcode":"7540",
    "sg:province":"Burgenland",
    "wof:name":"Pientsch GmbH",
    "wof:placetype":"venue"
},
  "geometry": {"coordinates":[16.2997722626,47.0242156982],"type":"Point"}
}