{
  "type": "Feature",
  "properties": {
    "addr:full":"Alpenrosenstr 10 Wels Ober\u00f6sterreich 4600",
    "addr:housenumber":"10",
    "addr:postcode":"4600",
    "addr:street":"Alpenrosenstr;Oberoesterreich",
    "iso:country":"AT",
    "sg:address":"Alpenrosenstr 10",
    "sg:city":"Wels",
    "sg:orig_category":"Handelsagenturen",
    "sg:phone":"+43 7242 76451",
    "sg:postcode":"4600",
    "sg:province":"Ober\u00f6sterreich",
    "wof:name":"Strasser Bernd",
    "wof:placetype":"venue"
},
  "geometry": {"coordinates":[13.9857282639,48.1564712524],"type":"Point"}
}