{
  "type": "Feature",
  "properties": {
    "iso:country":"AT",
    "sg:address":"Hauptstr 494",
    "sg:city":"F\u00fcgen",
    "sg:orig_category":"Banken U Sparkassen",
    "sg:phone":"+43 4352 88622040",
    "sg:postcode":"6263",
    "sg:province":"Tirol",
    "wof:name":"Bankomat d Volksbank Innsbruck-Schwaz AG",
    "wof:placetype":"venue"
},
  "geometry": {"coordinates":[11.8505430222,47.3455123901],"type":"Point"}
}