{
  "type": "Feature",
  "properties": {
    "iso:country":"AT",
    "sg:address":"Breitenbruck 71",
    "sg:city":"Katsdorf",
    "sg:orig_category":"Autoreparatur",
    "sg:phone":"+43 4372 3588152",
    "sg:postcode":"4223",
    "sg:province":"Ober\u00f6sterreich",
    "wof:name":"Leonhartsberger Konrad GesmbH",
    "wof:placetype":"venue"
},
  "geometry": {"coordinates":[14.4783906937,48.3273887634],"type":"Point"}
}