{
  "type": "Feature",
  "properties": {
    "addr:full":"Alpendorfstr 19 St. Johann im Pongau Salzburg 5600",
    "addr:housenumber":"19",
    "addr:postcode":"5600",
    "addr:street":"Alpendorfstr;Salzburg",
    "iso:country":"AT",
    "sg:address":"Alpendorfstr 19",
    "sg:city":"St. Johann im Pongau",
    "sg:orig_category":"Automaten",
    "sg:phone":"+43 6412 75010",
    "sg:postcode":"5600",
    "sg:province":"Salzburg",
    "wof:name":"Schwarz Georg",
    "wof:placetype":"venue"
},
  "geometry": {"coordinates":[13.1980543137,47.3315353394],"type":"Point"}
}