{
  "type": "Feature",
  "properties": {
    "addr:full":"Ro\u00dfmarkt 21 Grieskirchen Ober\u00f6sterreich 4710",
    "addr:housenumber":"21",
    "addr:postcode":"4710",
    "addr:street":"Rossmarkt",
    "iso:country":"AT",
    "sg:address":"Ro\u00dfmarkt 21",
    "sg:city":"Grieskirchen",
    "sg:classifiers":[
        {
            "category":"Retail",
            "subcategory":"Event Space",
            "type":"Services"
        }
    ],
    "sg:phone":"+43 4372 4863580",
    "sg:postcode":"4710",
    "sg:province":"Ober\u00f6sterreich",
    "sg:tags":[
        "hand-",
        "u",
        "fu\u00c3\u0178pflege"
    ],
    "wof:name":"Sch\u00f6nheitsstube",
    "wof:placetype":"venue"
},
  "geometry": {"coordinates":[13.8257322311,48.2358856201],"type":"Point"}
}