{
  "type": "Feature",
  "properties": {
    "addr:full":"Lehmanngasse 23 Wien Wien 1230",
    "addr:housenumber":"23",
    "addr:postcode":"1230",
    "addr:street":"Lehmanngasse",
    "iso:country":"AT",
    "sg:address":"Lehmanngasse 23",
    "sg:city":"Wien",
    "sg:classifiers":[
        {
            "category":"Professional",
            "subcategory":"Accounting & Tax Preparation",
            "type":"Services"
        }
    ],
    "sg:phone":"+43 1 8692284",
    "sg:postcode":"1230",
    "sg:province":"Wien",
    "sg:tags":[
        "financial",
        "software"
    ],
    "sg:website":"micro.co.at",
    "wof:name":"MICRO Datenverarbeitung Ges.m.b.H.",
    "wof:placetype":"venue"
},
  "geometry": {"coordinates":[16.2784175873,48.1362991333],"type":"Point"}
}