{
  "type": "Feature",
  "properties": {
    "iso:country":"AT",
    "sg:address":"Erlau 40",
    "sg:city":"Attnang-Puchheim",
    "sg:orig_category":"Psychotherapie",
    "sg:phone":"+43 76736372",
    "sg:postcode":"4800",
    "sg:province":"Ober\u00f6sterreich",
    "wof:name":"Schobesberger Alexandra",
    "wof:placetype":"venue"
},
  "geometry": {"coordinates":[13.7204141617,48.0107002258],"type":"Point"}
}