{
  "type": "Feature",
  "properties": {
    "addr:full":"Schulsdlg 13c Wieselburg an der Erlauf Nieder\u00f6sterreich 3250",
    "addr:housenumber":"13c",
    "addr:postcode":"3250",
    "addr:street":"Schulsdlg;Niederoesterreich",
    "iso:country":"AT",
    "sg:address":"Schulsdlg 13c",
    "sg:city":"Wieselburg an der Erlauf",
    "sg:orig_category":"Pensionen / Privatzimmer",
    "sg:phone":"+43 4374 1653848",
    "sg:postcode":"3250",
    "sg:province":"Nieder\u00f6sterreich",
    "wof:name":"G\u00e4stehaus Elisabeth",
    "wof:placetype":"venue"
},
  "geometry": {"coordinates":[15.1380252838,48.1304283142],"type":"Point"}
}