{
  "type": "Feature",
  "properties": {
    "iso:country":"AT",
    "sg:address":"Wiener Str 255",
    "sg:city":"G\u00f6sting",
    "sg:orig_category":"Erdarbeiten",
    "sg:phone":"+43 316 674874",
    "sg:postcode":"8051",
    "sg:province":"Steiermark",
    "wof:name":"Fr\u00fchwirth Otto",
    "wof:placetype":"venue"
},
  "geometry": {"coordinates":[15.40558815,47.0938110352],"type":"Point"}
}