{
  "type": "Feature",
  "properties": {
    "addr:full":"Gartenstadtstr 20 Linz Ober\u00f6sterreich 4040",
    "addr:housenumber":"20",
    "addr:postcode":"4040",
    "addr:street":"Gartenstadtstr",
    "iso:country":"AT",
    "sg:address":"Gartenstadtstr 20",
    "sg:city":"Linz",
    "sg:orig_category":"Genossenschaften",
    "sg:phone":"+43 732 221072",
    "sg:postcode":"4040",
    "sg:province":"Ober\u00f6sterreich",
    "wof:name":"Neue Heimat Gemeinn Wohnungs- und Siedlungsgenossenschaft in O\u00d6 GesmbH",
    "wof:placetype":"venue"
},
  "geometry": {"coordinates":[14.2348709106,48.3110733032],"type":"Point"}
}