{
  "type": "Feature",
  "properties": {
    "iso:country":"AT",
    "sg:address":"Mariahilfer Str 85-87",
    "sg:city":"Wien",
    "sg:orig_category":"Boutiquen",
    "sg:phone":"+43 4315 876224",
    "sg:postcode":"1060",
    "sg:province":"Wien",
    "wof:name":"Flotten Jeans & Casuals HandelsgesmbH",
    "wof:placetype":"venue"
},
  "geometry": {"coordinates":[16.3484249115,48.1976051331],"type":"Point"}
}