{
  "type": "Feature",
  "properties": {
    "addr:full":"Wattmanng 9 Wien Wien 1130",
    "addr:housenumber":"9",
    "addr:postcode":"1130",
    "addr:street":"Wattmanng",
    "iso:country":"AT",
    "sg:address":"Wattmanng 9",
    "sg:city":"Wien",
    "sg:orig_category":"Transportunternehmen",
    "sg:phone":"+43 1 87712280",
    "sg:postcode":"1130",
    "sg:province":"Wien",
    "wof:name":"Litschauer Franz",
    "wof:placetype":"venue"
},
  "geometry": {"coordinates":[16.2980117798,48.1837806702],"type":"Point"}
}