{
  "type": "Feature",
  "properties": {
    "addr:full":"Hauptstrasse 66 Rottenmann Steiermark 8786",
    "addr:housenumber":"66",
    "addr:postcode":"8786",
    "addr:street":"Hauptstrasse",
    "iso:country":"AT",
    "sg:address":"Hauptstrasse 66",
    "sg:city":"Rottenmann",
    "sg:classifiers":[
        {
            "category":"Building & Trades",
            "subcategory":"Plumbing",
            "type":"Services"
        }
    ],
    "sg:phone":"+43 3614 2396",
    "sg:postcode":"8786",
    "sg:province":"Steiermark",
    "sg:tags":[
        "supraregional",
        "gas"
    ],
    "sg:website":"gretler.cc",
    "wof:name":"Ing. Klaus Gretler GesmbH",
    "wof:placetype":"venue"
},
  "geometry": {"coordinates":[14.3562393188,47.5250091553],"type":"Point"}
}