{
  "type": "Feature",
  "properties": {
    "addr:full":"Untere Donaul\u00e4nde 66 Linz Ober\u00f6sterreich 4020",
    "addr:housenumber":"66",
    "addr:postcode":"4020",
    "addr:street":"Untere Donaulaende",
    "iso:country":"AT",
    "sg:address":"Untere Donaul\u00e4nde 66",
    "sg:city":"Linz",
    "sg:orig_category":"Kinderbetreuung",
    "sg:phone":"+43 732 771218",
    "sg:postcode":"4020",
    "sg:province":"Ober\u00f6sterreich",
    "wof:name":"Kindergarten d Vereins d Lds Bed",
    "wof:placetype":"venue"
},
  "geometry": {"coordinates":[14.2957239151,48.3111076355],"type":"Point"}
}