{
  "type": "Feature",
  "properties": {
    "iso:country":"AT",
    "sg:address":"Traklstrasse 21",
    "sg:city":"Wels",
    "sg:classifiers":[
        {
            "category":"Wholesale",
            "subcategory":"Construction Materials",
            "type":"Manufacturing & Wholesale Goods"
        }
    ],
    "sg:phone":"+43 7242 62916",
    "sg:postcode":"4600",
    "sg:province":"Ober\u00f6sterreich",
    "sg:tags":[
        "sealing",
        "insulating",
        "insulant",
        "moisture"
    ],
    "sg:website":"machacek.at",
    "wof:name":"Bruno Machacek Ges.m.b.H. & Co KG",
    "wof:placetype":"venue"
},
  "geometry": {"coordinates":[14.0768270493,48.1844406128],"type":"Point"}
}