{
  "type": "Feature",
  "properties": {
    "iso:country":"AT",
    "sg:address":"Salzachtalstr 22",
    "sg:city":"Hallein",
    "sg:orig_category":"Tabaktrafiken",
    "sg:phone":"+43 4362 4583050",
    "sg:postcode":"5400",
    "sg:province":"Salzburg",
    "wof:name":"Haslinger Elisabeth",
    "wof:placetype":"venue"
},
  "geometry": {"coordinates":[13.1012935638,47.6819267273],"type":"Point"}
}