{
  "type": "Feature",
  "properties": {
    "addr:full":"Jahnstr. 30 F\u00fcrstenfeld Steiermark 8280",
    "addr:housenumber":"30",
    "addr:postcode":"8280",
    "addr:street":"Jahnstr.",
    "iso:country":"AT",
    "sg:address":"Jahnstr. 30",
    "sg:city":"F\u00fcrstenfeld",
    "sg:classifiers":[
        {
            "category":"Professional",
            "subcategory":"Engineering",
            "type":"Services"
        }
    ],
    "sg:phone":"+43 4333 8250100",
    "sg:postcode":"8280",
    "sg:province":"Steiermark",
    "sg:tags":[
        "machine",
        "-",
        "mechanical"
    ],
    "wof:name":"OE VERDICHTER GESMBH",
    "wof:placetype":"venue"
},
  "geometry": {"coordinates":[16.0881843567,47.0372047424],"type":"Point"}
}