{
  "type": "Feature",
  "properties": {
    "addr:full":"Bad Haller Strasse 23 Kremsm\u00fcnster Ober\u00f6sterreich 4550",
    "addr:housenumber":"23",
    "addr:postcode":"4550",
    "addr:street":"Bad Haller Strasse;Oberoesterreich",
    "iso:country":"AT",
    "sg:address":"Bad Haller Strasse 23",
    "sg:city":"Kremsm\u00fcnster",
    "sg:classifiers":[
        {
            "category":"Home & Garden",
            "subcategory":"Building Materials",
            "type":"Retail Goods"
        }
    ],
    "sg:phone":"+43 7583 7577",
    "sg:postcode":"4550",
    "sg:province":"Ober\u00f6sterreich",
    "sg:tags":[
        "installation",
        "electric"
    ],
    "wof:name":"Leitner GmbH",
    "wof:placetype":"venue"
},
  "geometry": {"coordinates":[7.4943199158,50.8699913025],"type":"Point"}
}