{
  "type": "Feature",
  "properties": {
    "addr:full":"Marksteinerg 7 Wien Wien 1210",
    "addr:housenumber":"7",
    "addr:postcode":"1210",
    "addr:street":"Marksteinerg",
    "iso:country":"AT",
    "sg:address":"Marksteinerg 7",
    "sg:city":"Wien",
    "sg:orig_category":"Fliesen U Platten",
    "sg:phone":"+43 1 2717255",
    "sg:postcode":"1210",
    "sg:province":"Wien",
    "wof:name":"M & G Fliesenhandels und Reinigungs GmbH",
    "wof:placetype":"venue"
},
  "geometry": {"coordinates":[16.3788433075,48.2872657776],"type":"Point"}
}