{
  "type": "Feature",
  "properties": {
    "addr:full":"Waldrasterweg 1 Mieders Tirol 6142",
    "addr:housenumber":"1",
    "addr:postcode":"6142",
    "addr:street":"Waldrasterweg;Tirol",
    "iso:country":"AT",
    "sg:address":"Waldrasterweg 1",
    "sg:city":"Mieders",
    "sg:orig_category":"Bergbahnen",
    "sg:phone":"+43 4352 2562776",
    "sg:postcode":"6142",
    "sg:province":"Tirol",
    "wof:name":"Bergbahnen Mieders-Hochserles GesmbH & Co KG",
    "wof:placetype":"venue"
},
  "geometry": {"coordinates":[11.3800554276,47.163433075],"type":"Point"}
}