{
  "type": "Feature",
  "properties": {
    "addr:full":"Kaplanstr 12a Kirchdorf an der Krems Ober\u00f6sterreich 4560",
    "addr:housenumber":"12a",
    "addr:postcode":"4560",
    "addr:street":"Kaplanstr",
    "iso:country":"AT",
    "sg:address":"Kaplanstr 12a",
    "sg:city":"Kirchdorf an der Krems",
    "sg:orig_category":"Baumschulen",
    "sg:phone":"+43 4375 8264872",
    "sg:postcode":"4560",
    "sg:province":"Ober\u00f6sterreich",
    "wof:name":"Reiter Johannes",
    "wof:placetype":"venue"
},
  "geometry": {"coordinates":[14.112739563,47.905506134],"type":"Point"}
}