{
  "type": "Feature",
  "properties": {
    "iso:country":"AT",
    "sg:address":"Tigerg 30",
    "sg:city":"Wien",
    "sg:orig_category":"Schlossereien",
    "sg:phone":"+43 1 4051273",
    "sg:postcode":"1080",
    "sg:province":"Wien",
    "wof:name":"Beran Josef GesmbH",
    "wof:placetype":"venue"
},
  "geometry": {"coordinates":[16.3450584412,48.2093505859],"type":"Point"}
}