{
  "type": "Feature",
  "properties": {
    "iso:country":"AT",
    "sg:address":"Breitenfelderstrasse 3",
    "sg:city":"Anthering",
    "sg:classifiers":[
        {
            "category":"Manufacturing",
            "subcategory":"Furniture",
            "type":"Manufacturing & Wholesale Goods"
        }
    ],
    "sg:phone":"+43 6223 2220",
    "sg:postcode":"5102",
    "sg:province":"Salzburg",
    "sg:tags":[
        "bedroom"
    ],
    "wof:name":"Franz Jell",
    "wof:placetype":"venue"
},
  "geometry": {"coordinates":[13.008518219,47.8793563843],"type":"Point"}
}