{
  "type": "Feature",
  "properties": {
    "addr:full":"Perfalleckstr 33 Fuschl am See Salzburg 5330",
    "addr:housenumber":"33",
    "addr:postcode":"5330",
    "addr:street":"Perfalleckstr",
    "iso:country":"AT",
    "sg:address":"Perfalleckstr 33",
    "sg:city":"Fuschl am See",
    "sg:orig_category":"Direktmarketing",
    "sg:phone":"+43 6226 8305",
    "sg:postcode":"5330",
    "sg:province":"Salzburg",
    "wof:name":"Werzinger Michaela",
    "wof:placetype":"venue"
},
  "geometry": {"coordinates":[13.2963628769,47.7867927551],"type":"Point"}
}