{
  "type": "Feature",
  "properties": {
    "addr:full":"Br\u00e4unerstr 7 Wien Wien 1010",
    "addr:housenumber":"7",
    "addr:postcode":"1010",
    "addr:street":"Braeunerstr",
    "iso:country":"AT",
    "sg:address":"Br\u00e4unerstr 7",
    "sg:city":"Wien",
    "sg:orig_category":"Lederwaren / Einzelhandel",
    "sg:phone":"+43 1 5138294",
    "sg:postcode":"1010",
    "sg:province":"Wien",
    "wof:name":"R Horn's Wien",
    "wof:placetype":"venue"
},
  "geometry": {"coordinates":[16.3688259125,48.2075576782],"type":"Point"}
}