{
  "type": "Feature",
  "properties": {
    "addr:full":"Lindauerg 30 Wien Wien 1160",
    "addr:housenumber":"30",
    "addr:postcode":"1160",
    "addr:street":"Lindauerg",
    "iso:country":"AT",
    "sg:address":"Lindauerg 30",
    "sg:city":"Wien",
    "sg:orig_category":"\u00c3\u201erzte / F Allgemeinmedizin",
    "sg:phone":"+43 1 4076822",
    "sg:postcode":"1160",
    "sg:province":"Wien",
    "wof:name":"Anlanger-Br\u00fcckler Maria Dr",
    "wof:placetype":"venue"
},
  "geometry": {"coordinates":[16.3301486969,48.2131004333],"type":"Point"}
}