{
  "type": "Feature",
  "properties": {
    "iso:country":"AT",
    "sg:address":"Trattnerhof 1",
    "sg:city":"Wien",
    "sg:orig_category":"Unternehmensberatung",
    "sg:phone":"+43 1 536670",
    "sg:postcode":"1010",
    "sg:province":"Wien",
    "wof:name":"A.T. Kearney GesmbH",
    "wof:placetype":"venue"
},
  "geometry": {"coordinates":[16.370382309,48.2086982727],"type":"Point"}
}