{
  "type": "Feature",
  "properties": {
    "addr:full":"Kircheng 6 Hartberg Steiermark 8230",
    "addr:housenumber":"6",
    "addr:postcode":"8230",
    "addr:street":"Kircheng",
    "iso:country":"AT",
    "sg:address":"Kircheng 6",
    "sg:city":"Hartberg",
    "sg:orig_category":"Tabaktrafiken",
    "sg:phone":"+43 3332 64243",
    "sg:postcode":"8230",
    "sg:province":"Steiermark",
    "wof:name":"Denkmeyr Thomas",
    "wof:placetype":"venue"
},
  "geometry": {"coordinates":[15.9684505463,47.2803535461],"type":"Point"}
}