{
  "type": "Feature",
  "properties": {
    "addr:full":"Hoferstr 17 Ramsau Nieder\u00f6sterreich 3172",
    "addr:housenumber":"17",
    "addr:postcode":"3172",
    "addr:street":"Hoferstr;Niederoesterreich",
    "iso:country":"AT",
    "sg:address":"Hoferstr 17",
    "sg:city":"Ramsau",
    "sg:orig_category":"Handelsagenturen",
    "sg:phone":"+43 2764 8252",
    "sg:postcode":"3172",
    "sg:province":"Nieder\u00f6sterreich",
    "wof:name":"Berger Helmut - Textilagentur",
    "wof:placetype":"venue"
},
  "geometry": {"coordinates":[15.8039188385,48.0056114197],"type":"Point"}
}