{
  "type": "Feature",
  "properties": {
    "iso:country":"AT",
    "sg:address":"Hygna 41a",
    "sg:city":"Reith im Alpbachtal",
    "sg:orig_category":"Feuerwehren",
    "sg:phone":"+43 5337 67333",
    "sg:postcode":"6235",
    "sg:province":"Tirol",
    "wof:name":"Freiwillige Feuerwehr Reith",
    "wof:placetype":"venue"
},
  "geometry": {"coordinates":[11.8906803131,47.4020195007],"type":"Point"}
}