{
  "type": "Feature",
  "properties": {
    "iso:country":"AT",
    "sg:address":"D\u00f6blinger Hauptstr 55",
    "sg:city":"Wien",
    "sg:classifiers":[
        {
            "category":"Travel",
            "subcategory":"Hotels & Motels",
            "type":"Entertainment"
        }
    ],
    "sg:phone":"+43 1 36986730",
    "sg:postcode":"1190",
    "sg:province":"Wien",
    "wof:name":"Hotel Aramis",
    "wof:placetype":"venue"
},
  "geometry": {"coordinates":[16.3546562195,48.2394523621],"type":"Point"}
}