{
  "type": "Feature",
  "properties": {
    "addr:full":"Lannerg 11 Deutsch Wagram Nieder\u00f6sterreich 2232",
    "addr:housenumber":"11",
    "addr:postcode":"2232",
    "addr:street":"Lannerg",
    "iso:country":"AT",
    "sg:address":"Lannerg 11",
    "sg:city":"Deutsch Wagram",
    "sg:orig_category":"Personalberatung",
    "sg:phone":"+43 2247 3986",
    "sg:postcode":"2232",
    "sg:province":"Nieder\u00f6sterreich",
    "wof:name":"H\u00f6dl Consulting",
    "wof:placetype":"venue"
},
  "geometry": {"coordinates":[16.5868453979,48.3168983459],"type":"Point"}
}