{
  "type": "Feature",
  "properties": {
    "iso:country":"AT",
    "sg:address":"Ybbsstr 27",
    "sg:city":"Amstetten",
    "sg:orig_category":"Beteiligungen U Finanzierungen",
    "sg:phone":"+43 7472 61735",
    "sg:postcode":"3300",
    "sg:province":"Nieder\u00f6sterreich",
    "wof:name":"VERSFINANZ Mag Lasch & Partner GesmbH",
    "wof:placetype":"venue"
},
  "geometry": {"coordinates":[14.8469400406,48.1055908203],"type":"Point"}
}