{
  "type": "Feature",
  "properties": {
    "addr:full":"Behambergstr 8 Behamberg Nieder\u00f6sterreich 4441",
    "addr:housenumber":"8",
    "addr:postcode":"4441",
    "addr:street":"Behambergstr;Behamberg Niederoesterreich",
    "iso:country":"AT",
    "sg:address":"Behambergstr 8",
    "sg:city":"Behamberg",
    "sg:orig_category":"Pensionen / Privatzimmer",
    "sg:phone":"+43 7252 30863",
    "sg:postcode":"4441",
    "sg:province":"Nieder\u00f6sterreich",
    "wof:name":"Bl\u00fcmelhuberhof Fam Schweinschwaller",
    "wof:placetype":"venue"
},
  "geometry": {"coordinates":[14.4808130264,48.0405654907],"type":"Point"}
}