{
  "type": "Feature",
  "properties": {
    "addr:full":"Radetzkystr 5 Graz Steiermark 8010",
    "addr:housenumber":"5",
    "addr:postcode":"8010",
    "addr:street":"Radetzkystr",
    "iso:country":"AT",
    "sg:address":"Radetzkystr 5",
    "sg:city":"Graz",
    "sg:orig_category":"Friseure U Frisiersalons",
    "sg:phone":"+43 316 829386",
    "sg:postcode":"8010",
    "sg:province":"Steiermark",
    "wof:name":"Mein Fris\u00f6r",
    "wof:placetype":"venue"
},
  "geometry": {"coordinates":[15.4403839111,47.0664672852],"type":"Point"}
}