{
  "type": "Feature",
  "properties": {
    "addr:full":"Weyrer Str 135 Waidhofen an der Ybbs Nieder\u00f6sterreich 3340",
    "addr:housenumber":"135",
    "addr:postcode":"3340",
    "iso:country":"AT",
    "sg:address":"Weyrer Str 135",
    "sg:city":"Waidhofen an der Ybbs",
    "sg:orig_category":"Autobeschriftungen",
    "sg:phone":"+43 4374 425010",
    "sg:postcode":"3340",
    "sg:province":"Nieder\u00f6sterreich",
    "wof:name":"Forster Verkehrs- u Werbetechnik GmbH",
    "wof:placetype":"venue"
},
  "geometry": {"coordinates":[14.7645168304,47.931312561],"type":"Point"}
}