{
  "type": "Feature",
  "properties": {
    "addr:full":"Knappensteig 8 Heilbad D\u00fcrrnberg Salzburg 5422",
    "addr:housenumber":"8",
    "addr:postcode":"5422",
    "addr:street":"Knappensteig;Duerrnberg Salzburg",
    "iso:country":"AT",
    "sg:address":"Knappensteig 8",
    "sg:city":"Heilbad D\u00fcrrnberg",
    "sg:orig_category":"Autohandel",
    "sg:phone":"+43 664 4000911",
    "sg:postcode":"5422",
    "sg:province":"Salzburg",
    "wof:name":"Sportwagen Handels GmbH",
    "wof:placetype":"venue"
},
  "geometry": {"coordinates":[13.0900039673,47.6706085205],"type":"Point"}
}