{
  "type": "Feature",
  "properties": {
    "addr:full":"Sonnhalb 36+37 H\u00fcttau Salzburg 5511",
    "addr:housenumber":"36 + 37;5511",
    "addr:street":"Sonnhalb;Huettau Salzburg",
    "iso:country":"AT",
    "sg:address":"Sonnhalb 36+37",
    "sg:city":"H\u00fcttau",
    "sg:orig_category":"Tischlereien",
    "sg:phone":"+43 6458 72560",
    "sg:postcode":"5511",
    "sg:province":"Salzburg",
    "wof:name":"Schnitzhofer Josef Peter",
    "wof:placetype":"venue"
},
  "geometry": {"coordinates":[13.2967500687,47.4222412109],"type":"Point"}
}