{
  "type": "Feature",
  "properties": {
    "iso:country":"AT",
    "sg:address":"Hubertusstr 5",
    "sg:city":"St. Veit an der Glan",
    "sg:orig_category":"Erdarbeiten",
    "sg:phone":"+43 4212 4620",
    "sg:postcode":"9300",
    "sg:province":"K\u00e4rnten",
    "wof:name":"Leyfert Christian",
    "wof:placetype":"venue"
},
  "geometry": {"coordinates":[14.3513069153,46.7634239197],"type":"Point"}
}