{
  "type": "Feature",
  "properties": {
    "addr:full":"Villacher Str 1D/3 Klagenfurt K\u00e4rnten 9020",
    "addr:housenumber":"1d / 3",
    "addr:postcode":"9020",
    "addr:street":"Str;Kaernten",
    "iso:country":"AT",
    "sg:address":"Villacher Str 1D/3",
    "sg:city":"Klagenfurt",
    "sg:orig_category":"Galerien",
    "sg:phone":"+43 463 593206",
    "sg:postcode":"9020",
    "sg:province":"K\u00e4rnten",
    "wof:name":"Galerie Carinthia",
    "wof:placetype":"venue"
},
  "geometry": {"coordinates":[14.30356884,46.623336792],"type":"Point"}
}