{
  "type": "Feature",
  "properties": {
    "addr:full":"Marktpl 25 Haag am Hausruck Ober\u00f6sterreich 4680",
    "addr:housenumber":"25",
    "addr:postcode":"4680",
    "addr:street":"Marktpl",
    "iso:country":"AT",
    "sg:address":"Marktpl 25",
    "sg:city":"Haag am Hausruck",
    "sg:orig_category":"Hafnereien",
    "sg:phone":"+43 4377 322601",
    "sg:postcode":"4680",
    "sg:province":"Ober\u00f6sterreich",
    "wof:name":"Schrattenecker Robert",
    "wof:placetype":"venue"
},
  "geometry": {"coordinates":[13.6393823624,48.1848258972],"type":"Point"}
}