{
  "type": "Feature",
  "properties": {
    "addr:full":"Freifeldweg 462 P\u00f6llau Steiermark 8225",
    "addr:housenumber":"462",
    "addr:postcode":"8225",
    "addr:street":"Poellau Steiermark",
    "iso:country":"AT",
    "sg:address":"Freifeldweg 462",
    "sg:city":"P\u00f6llau",
    "sg:orig_category":"Landwirtschaftliche Produkte",
    "sg:phone":"+43 3335 33820",
    "sg:postcode":"8225",
    "sg:province":"Steiermark",
    "wof:name":"Rosenbaum Franz GmbH & Co KG",
    "wof:placetype":"venue"
},
  "geometry": {"coordinates":[15.8337945938,47.301990509],"type":"Point"}
}