{
  "type": "Feature",
  "properties": {
    "addr:full":"P\u00fchretstrasse 3 Roitham Ober\u00f6sterreich 4661",
    "addr:housenumber":"3",
    "addr:postcode":"4661",
    "addr:street":"Puehretstrasse",
    "iso:country":"AT",
    "sg:address":"P\u00fchretstrasse 3",
    "sg:city":"Roitham",
    "sg:classifiers":[
        {
            "category":"Professional",
            "subcategory":"Engineering",
            "type":"Services"
        }
    ],
    "sg:phone":"+43 76135004",
    "sg:postcode":"4661",
    "sg:province":"Ober\u00f6sterreich",
    "sg:tags":[
        "barrel",
        "element",
        "extruder"
    ],
    "sg:website":"3s-gmbh.at",
    "wof:name":"3S Schnecken + Spindeln + Spiralen Bearbeitungsgesellschaft m.b.H.",
    "wof:placetype":"venue"
},
  "geometry": {"coordinates":[13.8226041794,48.0241851807],"type":"Point"}
}