{
  "type": "Feature",
  "properties": {
    "iso:country":"AT",
    "sg:address":"Maria-Theresien-Str 1",
    "sg:city":"Innsbruck",
    "sg:orig_category":"Steuerberatung",
    "sg:phone":"+43 4351 25810400",
    "sg:postcode":"6020",
    "sg:province":"Tirol",
    "wof:name":"Gasser Kurt Mag",
    "wof:placetype":"venue"
},
  "geometry": {"coordinates":[11.393737793,47.2669563293],"type":"Point"}
}