{
  "type": "Feature",
  "properties": {
    "addr:full":"Horner Str 96 Stockerau Nieder\u00f6sterreich 2000",
    "addr:postcode":"2000",
    "addr:street":"Str 96",
    "iso:country":"AT",
    "sg:address":"Horner Str 96",
    "sg:city":"Stockerau",
    "sg:orig_category":"Tankstellen",
    "sg:phone":"+43 2266 65429",
    "sg:postcode":"2000",
    "sg:province":"Nieder\u00f6sterreich",
    "wof:name":"AVANTI TankstellenbetriebsgesmbH",
    "wof:placetype":"venue"
},
  "geometry": {"coordinates":[16.1834526062,48.3883857727],"type":"Point"}
}