{
  "type": "Feature",
  "properties": {
    "addr:full":"Am Agersteg NB Regau Ober\u00f6sterreich 4844",
    "addr:postcode":"4844",
    "addr:street":"Am Agersteg;Oberoesterreich",
    "iso:country":"AT",
    "sg:address":"Am Agersteg NB",
    "sg:city":"Regau",
    "sg:orig_category":"Autohandel",
    "sg:phone":"+43 4376 7221224",
    "sg:postcode":"4844",
    "sg:province":"Ober\u00f6sterreich",
    "wof:name":"Hermanseder GmbH & Co KG",
    "wof:placetype":"venue"
},
  "geometry": {"coordinates":[13.689125061,47.9909744263],"type":"Point"}
}