{
  "type": "Feature",
  "properties": {
    "iso:country":"AT",
    "sg:address":"Hauptpl 5",
    "sg:city":"Bernstein",
    "sg:orig_category":"Edelsteine",
    "sg:phone":"+43 4333 5466200",
    "sg:postcode":"7434",
    "sg:province":"Burgenland",
    "wof:name":"Felsenmuseum",
    "wof:placetype":"venue"
},
  "geometry": {"coordinates":[16.2552394867,47.405670166],"type":"Point"}
}