{
  "type": "Feature",
  "properties": {
    "addr:full":"Homanng 1 Leoben Steiermark 8700",
    "addr:housenumber":"1",
    "addr:postcode":"8700",
    "addr:street":"Homanng",
    "iso:country":"AT",
    "sg:address":"Homanng 1",
    "sg:city":"Leoben",
    "sg:classifiers":[
        {
            "category":"Restaurant",
            "type":"Food & Drink"
        }
    ],
    "sg:phone":"+43 3842 42838",
    "sg:postcode":"8700",
    "sg:province":"Steiermark",
    "wof:name":"Restaurant z Bergmann",
    "wof:placetype":"venue"
},
  "geometry": {"coordinates":[15.0943231583,47.3803634644],"type":"Point"}
}