{
  "type": "Feature",
  "properties": {
    "addr:full":"Schubertstr 62 Graz Steiermark 8010",
    "addr:housenumber":"62",
    "addr:postcode":"8010",
    "addr:street":"Schubertstr",
    "iso:country":"AT",
    "sg:address":"Schubertstr 62",
    "sg:city":"Graz",
    "sg:classifiers":[
        {
            "category":"Professional",
            "subcategory":"Management & Consulting",
            "type":"Services"
        }
    ],
    "sg:phone":"+43 4331 63848620",
    "sg:postcode":"8010",
    "sg:province":"Steiermark",
    "wof:name":"IKM Institut f\u00fcr kommunales Management GmbH",
    "wof:placetype":"venue"
},
  "geometry": {"coordinates":[15.4577980042,47.0816230774],"type":"Point"}
}