{
  "type": "Feature",
  "properties": {
    "addr:full":"Wiener Str 34 Melk Nieder\u00f6sterreich 3390",
    "addr:postcode":"3390",
    "addr:street":"Melk",
    "iso:country":"AT",
    "sg:address":"Wiener Str 34",
    "sg:city":"Melk",
    "sg:orig_category":"Blumeneinzelhandel",
    "sg:phone":"+43 2752 52092",
    "sg:postcode":"3390",
    "sg:province":"Nieder\u00f6sterreich",
    "wof:name":"Lederm\u00fcller Anna & Leopoldine",
    "wof:placetype":"venue"
},
  "geometry": {"coordinates":[15.3354997635,48.2276268005],"type":"Point"}
}