{
  "type": "Feature",
  "properties": {
    "addr:full":"Kircheng 12a Brunn am Gebirge Nieder\u00f6sterreich 2345",
    "addr:housenumber":"12a",
    "addr:postcode":"2345",
    "addr:street":"Kircheng",
    "iso:country":"AT",
    "sg:address":"Kircheng 12a",
    "sg:city":"Brunn am Gebirge",
    "sg:orig_category":"Papier- U Schreibwaren / Einzelhandel",
    "sg:phone":"+43 4322 3631735",
    "sg:postcode":"2345",
    "sg:province":"Nieder\u00f6sterreich",
    "wof:name":"B\u00f6hm Karlheinz",
    "wof:placetype":"venue"
},
  "geometry": {"coordinates":[16.2850894928,48.106880188],"type":"Point"}
}