{
  "type": "Feature",
  "properties": {
    "iso:country":"AT",
    "sg:address":"Oberottnang 25",
    "sg:city":"Ottnang am Hausruck",
    "sg:orig_category":"Tischlereien",
    "sg:phone":"+43 76766505",
    "sg:postcode":"4901",
    "sg:province":"Ober\u00f6sterreich",
    "wof:name":"Mair Franz",
    "wof:placetype":"venue"
},
  "geometry": {"coordinates":[13.6599721909,48.0997428894],"type":"Point"}
}