{
  "type": "Feature",
  "properties": {
    "addr:full":"Warmbad K\u00e4rnten 9504",
    "addr:postcode":"9504",
    "iso:country":"AT",
    "sg:city":"Warmbad",
    "sg:orig_category":"Blumeneinzelhandel",
    "sg:phone":"+43 4242 32139",
    "sg:postcode":"9504",
    "sg:province":"K\u00e4rnten",
    "wof:name":"Winkler Fred",
    "wof:placetype":"venue"
},
  "geometry": {"coordinates":[13.8284034729,46.5899429321],"type":"Point"}
}