{
  "type": "Feature",
  "properties": {
    "addr:full":"Gerbergasse 37 Villach K\u00e4rnten 9500",
    "addr:housenumber":"37",
    "addr:postcode":"9500",
    "addr:street":"Gerbergasse;Kaernten",
    "iso:country":"AT",
    "sg:address":"Gerbergasse 37",
    "sg:city":"Villach",
    "sg:classifiers":[
        {
            "category":"Structure",
            "subcategory":"Building",
            "type":"Public Place"
        }
    ],
    "sg:phone":"+43 4242 24874",
    "sg:postcode":"9500",
    "sg:province":"K\u00e4rnten",
    "sg:tags":[
        "canopy"
    ],
    "sg:website":"smolak.at",
    "wof:name":"Peter Smolak",
    "wof:placetype":"venue"
},
  "geometry": {"coordinates":[13.8498258591,46.6121520996],"type":"Point"}
}