{
  "type": "Feature",
  "properties": {
    "addr:full":"Aberseestr 39 St. Gilgen Salzburg 5340",
    "addr:housenumber":"39",
    "addr:postcode":"5340",
    "addr:street":"Aberseestr",
    "iso:country":"AT",
    "sg:address":"Aberseestr 39",
    "sg:city":"St. Gilgen",
    "sg:classifiers":[
        {
            "category":"Travel",
            "subcategory":"Hotels & Motels",
            "type":"Entertainment"
        }
    ],
    "sg:phone":"+43 6227 25110",
    "sg:postcode":"5340",
    "sg:province":"Salzburg",
    "wof:name":"Hotel Jodlerwirt",
    "wof:placetype":"venue"
},
  "geometry": {"coordinates":[13.3667955399,47.7607917786],"type":"Point"}
}