{
  "type": "Feature",
  "properties": {
    "addr:full":"Wiener Str. 435 Linz Ober\u00f6sterreich 4030",
    "addr:housenumber":"435",
    "addr:postcode":"4030",
    "iso:country":"AT",
    "sg:address":"Wiener Str. 435",
    "sg:city":"Linz",
    "sg:classifiers":[
        {
            "category":"Shopping",
            "subcategory":"Crafts & Fabrics",
            "type":"Retail Goods"
        }
    ],
    "sg:phone":"+43 4373 23996",
    "sg:postcode":"4030",
    "sg:province":"Ober\u00f6sterreich",
    "wof:name":"LINZ TEXTIL GESMBH",
    "wof:placetype":"venue"
},
  "geometry": {"coordinates":[14.3231306076,48.251335144],"type":"Point"}
}