{
  "type": "Feature",
  "properties": {
    "iso:country":"AT",
    "sg:address":"Nr 132",
    "sg:city":"Trins",
    "sg:classifiers":[
        {
            "category":"Travel",
            "subcategory":"Hotels & Motels",
            "type":"Entertainment"
        }
    ],
    "sg:phone":"+43 5275 5208",
    "sg:postcode":"6152",
    "sg:province":"Tirol",
    "wof:name":"Hotel-Cafe Zita",
    "wof:placetype":"venue"
},
  "geometry": {"coordinates":[11.4166841507,47.0829467773],"type":"Point"}
}