{
  "type": "Feature",
  "properties": {
    "addr:full":"August-Jaksch-Str 16 Klagenfurt K\u00e4rnten 9020",
    "addr:housenumber":"16",
    "addr:postcode":"9020",
    "addr:street":"August-Jaksch-Str;Kaernten",
    "iso:country":"AT",
    "sg:address":"August-Jaksch-Str 16",
    "sg:city":"Klagenfurt",
    "sg:classifiers":[
        {
            "category":"Professional",
            "type":"Services"
        }
    ],
    "sg:phone":"+43 4350 10027800",
    "sg:postcode":"9020",
    "sg:province":"K\u00e4rnten",
    "sg:tags":[
        "leasing"
    ],
    "wof:name":"F & S Leasing GmbH",
    "wof:placetype":"venue"
},
  "geometry": {"coordinates":[14.3011760712,46.6208343506],"type":"Point"}
}