{
  "type": "Feature",
  "properties": {
    "addr:full":"Alser Str 57 Wien Wien 1080",
    "addr:postcode":"1080",
    "addr:street":"Str 57",
    "iso:country":"AT",
    "sg:address":"Alser Str 57",
    "sg:city":"Wien",
    "sg:orig_category":"Friseurbedarf",
    "sg:phone":"+43 1 4056822",
    "sg:postcode":"1080",
    "sg:province":"Wien",
    "wof:name":"Wally Susanne",
    "wof:placetype":"venue"
},
  "geometry": {"coordinates":[16.3444728851,48.2151260376],"type":"Point"}
}