{
  "type": "Feature",
  "properties": {
    "iso:country":"AT",
    "sg:address":"Brausewettergasse 8",
    "sg:city":"Wien",
    "sg:classifiers":[
        {
            "category":"Banks & Credit Unions",
            "subcategory":"Financial Services",
            "type":"Services"
        }
    ],
    "sg:phone":"+43 1 28343720",
    "sg:postcode":"1220",
    "sg:province":"Wien",
    "sg:tags":[
        "lens",
        "lens-shades",
        "hood"
    ],
    "sg:website":"sonnenkoenig.at",
    "wof:name":"Lagerholm Finnimport Ges.m.b.H.",
    "wof:placetype":"venue"
},
  "geometry": {"coordinates":[16.4513607025,48.2220497131],"type":"Point"}
}