{
  "type": "Feature",
  "properties": {
    "addr:full":"Feldkirchner Str 114 Klagenfurt K\u00e4rnten 9020",
    "addr:housenumber":"114",
    "addr:postcode":"9020",
    "addr:street":"Str;Kaernten",
    "iso:country":"AT",
    "sg:address":"Feldkirchner Str 114",
    "sg:city":"Klagenfurt",
    "sg:orig_category":"Reiseveranstalter",
    "sg:phone":"+43 463 550800",
    "sg:postcode":"9020",
    "sg:province":"K\u00e4rnten",
    "wof:name":"HMS-H\u00fctten-Miet-Service GmbH",
    "wof:placetype":"venue"
},
  "geometry": {"coordinates":[14.2933597565,46.639251709],"type":"Point"}
}