{
  "type": "Feature",
  "properties": {
    "iso:country":"AT",
    "sg:address":"Taborstr 61",
    "sg:city":"Wien",
    "sg:orig_category":"Raumausstattung",
    "sg:phone":"+43 1 2145576",
    "sg:postcode":"1020",
    "sg:province":"Wien",
    "wof:name":"Staub Gerhard - Tapetencenter",
    "wof:placetype":"venue"
},
  "geometry": {"coordinates":[16.3819446564,48.2217521667],"type":"Point"}
}