{
  "type": "Feature",
  "properties": {
    "addr:full":"Weizer Strasse 13 u. 15 Gleisdorf Steiermark 8200",
    "addr:housenumber":"13 u. 15",
    "addr:postcode":"8200",
    "addr:street":"Weizer Strasse",
    "iso:country":"AT",
    "sg:address":"Weizer Strasse 13 u. 15",
    "sg:city":"Gleisdorf",
    "sg:classifiers":[
        {
            "category":"Autos & Motor Vehicles",
            "subcategory":"Automobile Sales",
            "type":"Retail Goods"
        }
    ],
    "sg:phone":"+43 3112 2145",
    "sg:postcode":"8200",
    "sg:province":"Steiermark",
    "sg:tags":[
        "passenger",
        "car"
    ],
    "sg:website":"mazda.at",
    "wof:name":"Wachtler GesmbH",
    "wof:placetype":"venue"
},
  "geometry": {"coordinates":[15.6912050247,47.103477478],"type":"Point"}
}