{
  "type": "Feature",
  "properties": {
    "iso:country":"AT",
    "sg:address":"Paulustorg 4",
    "sg:city":"Graz",
    "sg:orig_category":"Banken U Sparkassen",
    "sg:phone":"+43 4331 68051851",
    "sg:postcode":"8010",
    "sg:province":"Steiermark",
    "wof:name":"Bankomat d Landes-Hypothekenbank Steiermark",
    "wof:placetype":"venue"
},
  "geometry": {"coordinates":[15.4402532578,47.0743713379],"type":"Point"}
}