{
  "type": "Feature",
  "properties": {
    "addr:full":"Salzburger Str 1a Wattens Tirol 6112",
    "addr:housenumber":"1a",
    "addr:postcode":"6112",
    "addr:street":"Salzburger Str;Tirol",
    "iso:country":"AT",
    "sg:address":"Salzburger Str 1a",
    "sg:city":"Wattens",
    "sg:classifiers":[
        {
            "category":"Utilities",
            "subcategory":"Refuse",
            "type":"Services"
        }
    ],
    "sg:phone":"+43 4352 2451822",
    "sg:postcode":"6112",
    "sg:province":"Tirol",
    "sg:tags":[
        "catering"
    ],
    "wof:name":"Meraner Catering GmbH",
    "wof:placetype":"venue"
},
  "geometry": {"coordinates":[11.5939149857,47.291683197],"type":"Point"}
}