{
  "type": "Feature",
  "properties": {
    "addr:full":"Brandner Str 15 B\u00fcrs Vorarlberg 6706",
    "addr:postcode":"6706",
    "addr:street":"Str 15 Buers",
    "iso:country":"AT",
    "sg:address":"Brandner Str 15",
    "sg:city":"B\u00fcrs",
    "sg:orig_category":"Elektroinstallationsunternehmen",
    "sg:phone":"+43 5552 630330",
    "sg:postcode":"6706",
    "sg:province":"Vorarlberg",
    "wof:name":"Cavada GesmbH",
    "wof:placetype":"venue"
},
  "geometry": {"coordinates":[5.8594698906,49.6493186951],"type":"Point"}
}