{
  "type": "Feature",
  "properties": {
    "addr:full":"Rauhensteing 7/2 Wien Wien 1010",
    "addr:housenumber":"7 / 2",
    "addr:postcode":"1010",
    "addr:street":"Rauhensteing",
    "iso:country":"AT",
    "sg:address":"Rauhensteing 7/2",
    "sg:city":"Wien",
    "sg:classifiers":[
        {
            "category":"Professional",
            "subcategory":"Art Services",
            "type":"Services"
        }
    ],
    "sg:phone":"+43 1 5135381",
    "sg:postcode":"1010",
    "sg:province":"Wien",
    "sg:tags":[
        "designer"
    ],
    "wof:name":"Braunias Ernst",
    "wof:placetype":"venue"
},
  "geometry": {"coordinates":[16.3726139069,48.2059059143],"type":"Point"}
}