{
  "type": "Feature",
  "properties": {
    "addr:full":"Schmiedg Engerwitzdorf Ober\u00f6sterreich 4209",
    "addr:postcode":"4209",
    "addr:street":"Schmiedg",
    "iso:country":"AT",
    "sg:address":"Schmiedg",
    "sg:city":"Engerwitzdorf",
    "sg:orig_category":"Feuerwehren",
    "sg:phone":"+43 7235 64320",
    "sg:postcode":"4209",
    "sg:province":"Ober\u00f6sterreich",
    "wof:name":"Feuerwehrhaus",
    "wof:placetype":"venue"
},
  "geometry": {"coordinates":[14.4257364273,48.3148117065],"type":"Point"}
}