{
  "type": "Feature",
  "properties": {
    "iso:country":"AT",
    "sg:address":"Michael-Jank-G 4",
    "sg:city":"Ottenschlag",
    "sg:orig_category":"Sonderschulen",
    "sg:phone":"+43 2872 6477",
    "sg:postcode":"3631",
    "sg:province":"Nieder\u00f6sterreich",
    "wof:name":"Sonderschule - Sonderp\u00e4dagogisches Zentrum",
    "wof:placetype":"venue"
},
  "geometry": {"coordinates":[15.2212705612,48.4225234985],"type":"Point"}
}