{
  "type": "Feature",
  "properties": {
    "iso:country":"AT",
    "sg:address":"Fuschler Str 11",
    "sg:city":"Thalgau",
    "sg:orig_category":"Maler, Anstreicher U Lackierer",
    "sg:phone":"+43 4362 355181",
    "sg:postcode":"5303",
    "sg:province":"Salzburg",
    "wof:name":"Tomsits Rudolf",
    "wof:placetype":"venue"
},
  "geometry": {"coordinates":[13.2548847198,47.8400993347],"type":"Point"}
}