{
  "type": "Feature",
  "properties": {
    "addr:full":"Perchtoldsdorfer Str 15 Wien Wien 1230",
    "addr:postcode":"1230",
    "addr:street":"Str 15",
    "iso:country":"AT",
    "sg:address":"Perchtoldsdorfer Str 15",
    "sg:city":"Wien",
    "sg:orig_category":"Institute",
    "sg:phone":"+43 1 88980300",
    "sg:postcode":"1230",
    "sg:province":"Wien",
    "sg:website":"www.beika-institut.at",
    "wof:name":"BEIKA - INSTITUT f Legasthenie und ADS-Training",
    "wof:placetype":"venue"
},
  "geometry": {"coordinates":[16.281621933,48.1334609985],"type":"Point"}
}