{
  "type": "Feature",
  "properties": {
    "addr:full":"Schmiedg 5 Brixen im Thale Tirol 6364",
    "addr:housenumber":"5",
    "addr:postcode":"6364",
    "addr:street":"Schmiedg;Tirol",
    "iso:country":"AT",
    "sg:address":"Schmiedg 5",
    "sg:city":"Brixen im Thale",
    "sg:orig_category":"Tischlereien",
    "sg:phone":"+43 4353 342469",
    "sg:postcode":"6364",
    "sg:province":"Tirol",
    "wof:name":"Fuchs Franz Bau- u M\u00f6beltischlerei GmbH",
    "wof:placetype":"venue"
},
  "geometry": {"coordinates":[12.2385759354,47.4459877014],"type":"Point"}
}