{
  "type": "Feature",
  "properties": {
    "addr:full":"Daimlerstr 16 Linz Ober\u00f6sterreich 4030",
    "addr:housenumber":"16",
    "addr:postcode":"4030",
    "addr:street":"Daimlerstr",
    "iso:country":"AT",
    "sg:address":"Daimlerstr 16",
    "sg:city":"Linz",
    "sg:orig_category":"Fahrradreparatur",
    "sg:phone":"+43 676 84938881",
    "sg:postcode":"4030",
    "sg:province":"Ober\u00f6sterreich",
    "wof:name":"SPORT HOME SERVICE",
    "wof:placetype":"venue"
},
  "geometry": {"coordinates":[14.286444664,48.2512435913],"type":"Point"}
}