{
  "type": "Feature",
  "properties": {
    "iso:country":"AT",
    "sg:address":"Wiedner Hauptstr 39/2/11a",
    "sg:city":"Wien",
    "sg:orig_category":"Forschungsinstitute",
    "sg:phone":"+43 1 5224873",
    "sg:postcode":"1040",
    "sg:province":"Wien",
    "wof:name":"abif Analyse - Beratung und interdisziplin\u00e4re Forschung",
    "wof:placetype":"venue"
},
  "geometry": {"coordinates":[16.3671455383,48.1940345764],"type":"Point"}
}