{
  "type": "Feature",
  "properties": {
    "iso:country":"AT",
    "sg:address":"Hernalser Hauptstr 134",
    "sg:city":"Wien",
    "sg:orig_category":"Weinstuben",
    "sg:phone":"+43 4314 864625",
    "sg:postcode":"1170",
    "sg:province":"Wien",
    "wof:name":"Brandstetter Leopold Wein- u Bierhaus Zum Alsegg nunmehr GmbH & Co KG",
    "wof:placetype":"venue"
},
  "geometry": {"coordinates":[16.3220119476,48.2215423584],"type":"Point"}
}