{
  "type": "Feature",
  "properties": {
    "iso:country":"AT",
    "sg:address":"Bahnstr. 29 ",
    "sg:city":"Leibnitz",
    "sg:classifiers":[
        {
            "category":"Manufacturing",
            "subcategory":"Rubber & Plastics",
            "type":"Manufacturing & Wholesale Goods"
        }
    ],
    "sg:phone":"+43 4334 5271660",
    "sg:postcode":"8430",
    "sg:province":"Steiermark",
    "sg:tags":[
        "packaging",
        "material",
        "-"
    ],
    "wof:name":"ELSTAR MOSDORFER GES.MBH",
    "wof:placetype":"venue"
},
  "geometry": {"coordinates":[15.5530967712,46.7950439453],"type":"Point"}
}