{
  "type": "Feature",
  "properties": {
    "iso:country":"AT",
    "sg:address":"Maxingstr 56",
    "sg:city":"Wien",
    "sg:orig_category":"Immobilienmakler",
    "sg:phone":"+43 1 5137317",
    "sg:postcode":"1130",
    "sg:province":"Wien",
    "wof:name":"Urbanz Markus Mag",
    "wof:placetype":"venue"
},
  "geometry": {"coordinates":[16.2980098724,48.1773452759],"type":"Point"}
}