{
  "type": "Feature",
  "properties": {
    "iso:country":"AT",
    "sg:address":"Streininger Str 23",
    "sg:city":"Vorchdorf",
    "sg:orig_category":"Restaurants: Chinesisch",
    "sg:phone":"+43 4376 147483",
    "sg:postcode":"4655",
    "sg:province":"Ober\u00f6sterreich",
    "wof:name":"China Restaurant Yang Tongsheng",
    "wof:placetype":"venue"
},
  "geometry": {"coordinates":[13.9301080704,48.0105056763],"type":"Point"}
}