{
  "type": "Feature",
  "properties": {
    "addr:full":"St. Veiterstr. 4 Klagenfurt K\u00e4rnten 9020",
    "addr:housenumber":"4",
    "addr:postcode":"9020",
    "addr:street":"Kaernten",
    "iso:country":"AT",
    "sg:address":"St. Veiterstr. 4",
    "sg:city":"Klagenfurt",
    "sg:classifiers":[
        {
            "category":"Professional",
            "subcategory":"Computer Services",
            "type":"Services"
        }
    ],
    "sg:phone":"+43 4346 350645",
    "sg:postcode":"9020",
    "sg:province":"K\u00e4rnten",
    "sg:tags":[
        "information",
        "technology"
    ],
    "wof:name":"SER SOLUTION SOFTWARE GMBH",
    "wof:placetype":"venue"
},
  "geometry": {"coordinates":[14.3029489517,46.6278991699],"type":"Point"}
}