{
  "type": "Feature",
  "properties": {
    "addr:full":"Hafendorf 21 Weitensfeld K\u00e4rnten 9344",
    "addr:housenumber":"21",
    "addr:postcode":"9344",
    "addr:street":"Hafendorf;Kaernten",
    "iso:country":"AT",
    "sg:address":"Hafendorf 21",
    "sg:city":"Weitensfeld",
    "sg:classifiers":[
        {
            "category":"Building & Trades",
            "subcategory":"Plumbing",
            "type":"Services"
        }
    ],
    "sg:phone":"+43 4265 434",
    "sg:postcode":"9344",
    "sg:province":"K\u00e4rnten",
    "sg:tags":[
        "tub",
        "bath"
    ],
    "wof:name":"Wintschnig Heizung- Sanit\u00e4rtechnik Ges.m.b.H.",
    "wof:placetype":"venue"
},
  "geometry": {"coordinates":[14.1982526779,46.8504257202],"type":"Point"}
}