{
  "type": "Feature",
  "properties": {
    "addr:full":"Dr.-Breitwieser-Str 16 Wels Ober\u00f6sterreich 4600",
    "addr:housenumber":"16",
    "addr:postcode":"4600",
    "addr:street":"Dr.-Breitwieser-Str;Oberoesterreich",
    "iso:country":"AT",
    "sg:address":"Dr.-Breitwieser-Str 16",
    "sg:city":"Wels",
    "sg:orig_category":"Steuerberatung",
    "sg:phone":"+43 4372 42476690",
    "sg:postcode":"4600",
    "sg:province":"Ober\u00f6sterreich",
    "wof:name":"Humer Herbert",
    "wof:placetype":"venue"
},
  "geometry": {"coordinates":[14.0079813004,48.1631774902],"type":"Point"}
}