{
  "type": "Feature",
  "properties": {
    "iso:country":"AT",
    "sg:address":"Barnabas Fink Str. 11",
    "sg:city":"Hohenems",
    "sg:classifiers":[
        {
            "category":"Wholesale",
            "subcategory":"Drugs",
            "type":"Manufacturing & Wholesale Goods"
        }
    ],
    "sg:phone":"+43 4355 7672330",
    "sg:postcode":"6845",
    "sg:province":"Vorarlberg",
    "sg:tags":[
        "chemical",
        "pharmaceutical"
    ],
    "wof:name":"FARBSCHMID GESMBH",
    "wof:placetype":"venue"
},
  "geometry": {"coordinates":[9.6682291031,47.3657875061],"type":"Point"}
}