{
  "type": "Feature",
  "properties": {
    "addr:full":"P\u00f6tschachg 18 Kapfenberg Steiermark 8605",
    "addr:housenumber":"18",
    "addr:postcode":"8605",
    "addr:street":"Poetschachg",
    "iso:country":"AT",
    "sg:address":"P\u00f6tschachg 18",
    "sg:city":"Kapfenberg",
    "sg:classifiers":[
        {
            "category":"Restaurant",
            "type":"Food & Drink"
        }
    ],
    "sg:phone":"+43 3862 32191",
    "sg:postcode":"8605",
    "sg:province":"Steiermark",
    "wof:name":"Flughafenrestaurant",
    "wof:placetype":"venue"
},
  "geometry": {"coordinates":[15.3359775543,47.4592514038],"type":"Point"}
}