{
  "type": "Feature",
  "properties": {
    "addr:full":"Unterdorf 2a Schoppernau Vorarlberg 6886",
    "addr:housenumber":"2a",
    "addr:postcode":"6886",
    "addr:street":"Unterdorf",
    "iso:country":"AT",
    "sg:address":"Unterdorf 2a",
    "sg:city":"Schoppernau",
    "sg:orig_category":"Banken U Sparkassen",
    "sg:phone":"+43 4355 1521900",
    "sg:postcode":"6886",
    "sg:province":"Vorarlberg",
    "wof:name":"Bankomat d Sparkasse d Gemeinde Egg",
    "wof:placetype":"venue"
},
  "geometry": {"coordinates":[10.0150308609,47.3120536804],"type":"Point"}
}