{
  "type": "Feature",
  "properties": {
    "addr:full":"Wittelsbachstr 5 Wien Wien 1020",
    "addr:housenumber":"5",
    "addr:postcode":"1020",
    "addr:street":"Wittelsbachstr",
    "iso:country":"AT",
    "sg:address":"Wittelsbachstr 5",
    "sg:city":"Wien",
    "sg:orig_category":"Behinderungen / Leben Mit Behinderungen",
    "sg:phone":"+43 4317 294565",
    "sg:postcode":"1020",
    "sg:province":"Wien",
    "wof:name":"CONTRAST - Fr\u00fchf\u00f6rderung f blinde, sehbehinderte u mehrfachbehindert-sehgesch\u00e4digte Kinder",
    "wof:placetype":"venue"
},
  "geometry": {"coordinates":[16.3996963501,48.2063522339],"type":"Point"}
}