{
  "type": "Feature",
  "properties": {
    "iso:country":"AT",
    "sg:address":"Haselbach 27",
    "sg:city":"Altenfelden",
    "sg:orig_category":"Dachdeckereien",
    "sg:phone":"+43 7282 7677",
    "sg:postcode":"4121",
    "sg:province":"Ober\u00f6sterreich",
    "wof:name":"Schmidhofer Rudolf GmbH",
    "wof:placetype":"venue"
},
  "geometry": {"coordinates":[13.9664707184,48.4991416931],"type":"Point"}
}