{
  "type": "Feature",
  "properties": {
    "iso:country":"AT",
    "sg:address":"Fraungruberg 4/5",
    "sg:city":"Wien",
    "sg:classifiers":[
        {
            "category":"Taxi",
            "type":"Transportation"
        }
    ],
    "sg:phone":"+43 1 8155224",
    "sg:postcode":"1120",
    "sg:province":"Wien",
    "sg:tags":[
        "personentransporte",
        "u"
    ],
    "wof:name":"Ruzicka Othmar",
    "wof:placetype":"venue"
},
  "geometry": {"coordinates":[16.3188819885,48.1730308533],"type":"Point"}
}