{
  "type": "Feature",
  "properties": {
    "addr:full":"Nr 64 Dalaas Vorarlberg 6752",
    "addr:postcode":"6752",
    "addr:street":"Nr 64",
    "iso:country":"AT",
    "sg:address":"Nr 64",
    "sg:city":"Dalaas",
    "sg:orig_category":"Telekommunikation",
    "sg:phone":"+43 5585 7223",
    "sg:postcode":"6752",
    "sg:province":"Vorarlberg",
    "wof:name":"Erne Thomas - Elektro Technik - Technische Software",
    "wof:placetype":"venue"
},
  "geometry": {"coordinates":[9.9998960495,47.1229896545],"type":"Point"}
}