{
  "type": "Feature",
  "properties": {
    "iso:country":"AT",
    "sg:address":"Grazer Str 26",
    "sg:city":"Stainz",
    "sg:orig_category":"Beton- U Betonsteinwerke",
    "sg:phone":"+43 3463 23110",
    "sg:postcode":"8510",
    "sg:province":"Steiermark",
    "wof:name":"Winkler Kurt Ing",
    "wof:placetype":"venue"
},
  "geometry": {"coordinates":[15.2678937912,46.8962631226],"type":"Point"}
}