{
  "type": "Feature",
  "properties": {
    "addr:full":"Wollzeile 30 Wien Wien 1010",
    "addr:housenumber":"30",
    "addr:postcode":"1010",
    "addr:street":"Wollzeile",
    "iso:country":"AT",
    "sg:address":"Wollzeile 30",
    "sg:city":"Wien",
    "sg:orig_category":"Feinkost, Partyservice, Vinotheken, Catering",
    "sg:phone":"+43 1 51244750",
    "sg:postcode":"1010",
    "sg:province":"Wien",
    "sg:website":"www.boehle.at",
    "wof:name":"Delikatessen B\u00f6hle",
    "wof:placetype":"venue"
},
  "geometry": {"coordinates":[16.3777389526,48.207775116],"type":"Point"}
}