{
  "type": "Feature",
  "properties": {
    "addr:full":"Laxenburger Str 38 Wien Wien 1100",
    "addr:housenumber":"38",
    "addr:postcode":"1100",
    "addr:street":"Laxenburger Str",
    "iso:country":"AT",
    "sg:address":"Laxenburger Str 38",
    "sg:city":"Wien",
    "sg:orig_category":"Tabaktrafiken",
    "sg:phone":"+43 1 6029728",
    "sg:postcode":"1100",
    "sg:province":"Wien",
    "wof:name":"Renner Inge",
    "wof:placetype":"venue"
},
  "geometry": {"coordinates":[16.3734226227,48.1771240234],"type":"Point"}
}