{
  "type": "Feature",
  "properties": {
    "iso:country":"AT",
    "sg:address":"Dreifaltigkeitsg 7",
    "sg:city":"Zell am See",
    "sg:classifiers":[
        {
            "category":"Travel",
            "subcategory":"Hotels & Motels",
            "type":"Entertainment"
        }
    ],
    "sg:phone":"+43 6542 7760",
    "sg:postcode":"5700",
    "sg:province":"Salzburg",
    "wof:name":"Sporthotel Lebzelter",
    "wof:placetype":"venue"
},
  "geometry": {"coordinates":[12.7975931168,47.3237838745],"type":"Point"}
}