{
  "type": "Feature",
  "properties": {
    "addr:full":"Anton Schwarz-Str 10 Amstetten Nieder\u00f6sterreich 3300",
    "addr:housenumber":"10",
    "addr:postcode":"3300",
    "addr:street":"Niederoesterreich",
    "iso:country":"AT",
    "sg:address":"Anton Schwarz-Str 10",
    "sg:city":"Amstetten",
    "sg:orig_category":"Ambulatorien",
    "sg:phone":"+43 7472 256900",
    "sg:postcode":"3300",
    "sg:province":"Nieder\u00f6sterreich",
    "wof:name":"Ambulatorium f Entwicklungsdiagnostik f k\u00f6rper- und mehrfachbehinderte Kinder und Jugendliche",
    "wof:placetype":"venue"
},
  "geometry": {"coordinates":[14.8683366776,48.1326828003],"type":"Point"}
}