{
  "type": "Feature",
  "properties": {
    "addr:full":"Sommersbergseestr 230 Bad Aussee Steiermark 8990",
    "addr:housenumber":"230",
    "addr:postcode":"8990",
    "iso:country":"AT",
    "sg:address":"Sommersbergseestr 230",
    "sg:city":"Bad Aussee",
    "sg:orig_category":"Non-Classified Establishments",
    "sg:phone":"+43 3622 522440",
    "sg:postcode":"8990",
    "sg:province":"Steiermark",
    "wof:name":"Stra\u00dfenmeisterei Bad Aussee",
    "wof:placetype":"venue"
},
  "geometry": {"coordinates":[13.7453012466,47.6142845154],"type":"Point"}
}