{
  "type": "Feature",
  "properties": {
    "iso:country":"AT",
    "sg:address":"Stoiznerg 3",
    "sg:city":"Bramberg am Wildkogel",
    "sg:orig_category":"Bibliotheken",
    "sg:phone":"+43 4365 66725114",
    "sg:postcode":"5733",
    "sg:province":"Salzburg",
    "wof:name":"B\u00fccherei Felberhaus",
    "wof:placetype":"venue"
},
  "geometry": {"coordinates":[12.3453712463,47.272403717],"type":"Point"}
}