{
  "type": "Feature",
  "properties": {
    "addr:full":"Zemannstr 42 Freistadt Ober\u00f6sterreich 4240",
    "addr:housenumber":"42",
    "addr:postcode":"4240",
    "addr:street":"Zemannstr",
    "iso:country":"AT",
    "sg:address":"Zemannstr 42",
    "sg:city":"Freistadt",
    "sg:orig_category":"Elektroinstallationsunternehmen",
    "sg:phone":"+43 7942 72314",
    "sg:postcode":"4240",
    "sg:province":"Ober\u00f6sterreich",
    "wof:name":"Haghofer Peter",
    "wof:placetype":"venue"
},
  "geometry": {"coordinates":[14.5039844513,48.5053482056],"type":"Point"}
}