{
  "type": "Feature",
  "properties": {
    "iso:country":"AT",
    "sg:address":"Promenadenweg 8",
    "sg:city":"Oberwaltersdorf",
    "sg:orig_category":"Fluggesellschaften",
    "sg:phone":"+43 2253 2160",
    "sg:postcode":"2522",
    "sg:province":"Nieder\u00f6sterreich",
    "wof:name":"AVIA CONSULT FlugbetriebsgesmbH",
    "wof:placetype":"venue"
},
  "geometry": {"coordinates":[16.314157486,47.9755363464],"type":"Point"}
}