{
  "type": "Feature",
  "properties": {
    "addr:full":"Ossiacher Str 32 Landskron K\u00e4rnten 9523",
    "addr:housenumber":"32",
    "addr:postcode":"9523",
    "addr:street":"Str;Kaernten",
    "iso:country":"AT",
    "sg:address":"Ossiacher Str 32",
    "sg:city":"Landskron",
    "sg:orig_category":"Massagen",
    "sg:phone":"+43 650 7840322",
    "sg:postcode":"9523",
    "sg:province":"K\u00e4rnten",
    "wof:name":"Massagefachinstitut Schrottenbach Erika",
    "wof:placetype":"venue"
},
  "geometry": {"coordinates":[13.8834199905,46.635307312],"type":"Point"}
}