{
  "type": "Feature",
  "properties": {
    "addr:full":"Magland 83 Fehring Steiermark 8350",
    "addr:housenumber":"83",
    "addr:postcode":"8350",
    "addr:street":"Magland",
    "iso:country":"AT",
    "sg:address":"Magland 83",
    "sg:city":"Fehring",
    "sg:orig_category":"Tischlereien",
    "sg:phone":"+43 4331 558230",
    "sg:postcode":"8350",
    "sg:province":"Steiermark",
    "wof:name":"Schober Anton",
    "wof:placetype":"venue"
},
  "geometry": {"coordinates":[16.066734314,46.9451332092],"type":"Point"}
}