{
  "type": "Feature",
  "properties": {
    "addr:full":"Mitteleule 40 N\u00fcziders Vorarlberg 6714",
    "addr:housenumber":"40",
    "addr:postcode":"6714",
    "addr:street":"Mitteleule",
    "iso:country":"AT",
    "sg:address":"Mitteleule 40",
    "sg:city":"N\u00fcziders",
    "sg:classifiers":[
        {
            "category":"Personal",
            "subcategory":"Hair Removal",
            "type":"Services"
        }
    ],
    "sg:phone":"+43 5552 65932",
    "sg:postcode":"6714",
    "sg:province":"Vorarlberg",
    "sg:tags":[
        "arbour"
    ],
    "wof:name":"Pfleger Garten- Landschaft GmbH & Co KG",
    "wof:placetype":"venue"
},
  "geometry": {"coordinates":[9.7846670151,47.1739692688],"type":"Point"}
}