{
  "type": "Feature",
  "properties": {
    "addr:full":"Bahnhofstrasse 9 Maria Rain K\u00e4rnten 9161",
    "addr:housenumber":"9",
    "addr:postcode":"9161",
    "addr:street":"Bahnhofstrasse;Kaernten",
    "iso:country":"AT",
    "sg:address":"Bahnhofstrasse 9",
    "sg:city":"Maria Rain",
    "sg:classifiers":[
        {
            "category":"Home & Garden",
            "subcategory":"Carpets & Floor Coverings",
            "type":"Retail Goods"
        }
    ],
    "sg:phone":"+43 4227 84379",
    "sg:postcode":"9161",
    "sg:province":"K\u00e4rnten",
    "sg:tags":[
        "houses",
        "shed"
    ],
    "wof:name":"Holz Schwarzfurtner GesmbH & Co KG",
    "wof:placetype":"venue"
},
  "geometry": {"coordinates":[14.2854681015,46.562286377],"type":"Point"}
}