{
  "type": "Feature",
  "properties": {
    "addr:full":"Hauptpl 21 Deutschlandsberg Steiermark 8530",
    "addr:housenumber":"21",
    "addr:postcode":"8530",
    "addr:street":"Hauptpl",
    "iso:country":"AT",
    "sg:address":"Hauptpl 21",
    "sg:city":"Deutschlandsberg",
    "sg:orig_category":"Feuerwerksartikel U Feuerwerke",
    "sg:phone":"+43 4334 6222020",
    "sg:postcode":"8530",
    "sg:province":"Steiermark",
    "wof:name":"Pieber Gro\u00dfhandelshaus",
    "wof:placetype":"venue"
},
  "geometry": {"coordinates":[15.2138748169,46.814617157],"type":"Point"}
}