{
  "type": "Feature",
  "properties": {
    "addr:full":"Salzburger Str 420 Gro\u00dfgmain Salzburg 5084",
    "addr:housenumber":"420",
    "addr:postcode":"5084",
    "addr:street":"Salzburger Str;Salzburg",
    "iso:country":"AT",
    "sg:address":"Salzburger Str 420",
    "sg:city":"Gro\u00dfgmain",
    "sg:orig_category":"Werbegrafik- U Grafik-Design",
    "sg:phone":"+43 6247 8777",
    "sg:postcode":"5084",
    "sg:province":"Salzburg",
    "wof:name":"Maislinger Albert Mag",
    "wof:placetype":"venue"
},
  "geometry": {"coordinates":[12.0809497833,48.0439414978],"type":"Point"}
}