{
  "type": "Feature",
  "properties": {
    "addr:full":"Heinrich-Gruber-Str 8 Traun Ober\u00f6sterreich 4050",
    "addr:housenumber":"8",
    "addr:postcode":"4050",
    "addr:street":"Heinrich-Gruber-Str",
    "iso:country":"AT",
    "sg:address":"Heinrich-Gruber-Str 8",
    "sg:city":"Traun",
    "sg:orig_category":"Blumeneinzelhandel",
    "sg:phone":"+43 7229 61507",
    "sg:postcode":"4050",
    "sg:province":"Ober\u00f6sterreich",
    "wof:name":"Rubenzucker Walter",
    "wof:placetype":"venue"
},
  "geometry": {"coordinates":[14.2382774353,48.2201118469],"type":"Point"}
}