{
  "type": "Feature",
  "properties": {
    "iso:country":"AT",
    "sg:address":"Schanzstr 3",
    "sg:city":"Wien",
    "sg:orig_category":"Handelsagenturen",
    "sg:phone":"+43 664 1553701",
    "sg:postcode":"1140",
    "sg:province":"Wien",
    "wof:name":"Vorderwinkler Edith",
    "wof:placetype":"venue"
},
  "geometry": {"coordinates":[16.3102684021,48.2028198242],"type":"Point"}
}