{
  "type": "Feature",
  "properties": {
    "iso:country":"AT",
    "sg:address":"Absbergg 25/7",
    "sg:city":"Wien",
    "sg:orig_category":"Tabaktrafiken",
    "sg:phone":"+43 1 6025748",
    "sg:postcode":"1100",
    "sg:province":"Wien",
    "wof:name":"J\u00f6bstl Richard",
    "wof:placetype":"venue"
},
  "geometry": {"coordinates":[16.3896465302,48.1727867126],"type":"Point"}
}