{
  "type": "Feature",
  "properties": {
    "iso:country":"AT",
    "sg:address":"Knappenweg 7",
    "sg:city":"Oberndorf in Tirol",
    "sg:orig_category":"Chemikalien",
    "sg:phone":"+43 5352 64386",
    "sg:postcode":"6372",
    "sg:province":"Tirol",
    "wof:name":"I.B.T. Industrielle Baustoff Technologie GesmbH",
    "wof:placetype":"venue"
},
  "geometry": {"coordinates":[12.3808603287,47.5014839172],"type":"Point"}
}