{
  "type": "Feature",
  "properties": {
    "addr:full":"Stadtpl 28 Steyr Ober\u00f6sterreich 4400",
    "addr:housenumber":"28",
    "addr:postcode":"4400",
    "addr:street":"Stadtpl;Oberoesterreich",
    "iso:country":"AT",
    "sg:address":"Stadtpl 28",
    "sg:city":"Steyr",
    "sg:orig_category":"Restaurants: Chinesisch",
    "sg:phone":"+43 7252 52193",
    "sg:postcode":"4400",
    "sg:province":"Ober\u00f6sterreich",
    "wof:name":"China-Restaurant Pam Pan",
    "wof:placetype":"venue"
},
  "geometry": {"coordinates":[14.419084549,48.0391349792],"type":"Point"}
}