{
  "type": "Feature",
  "properties": {
    "iso:country":"AT",
    "sg:address":"Badener Str 10",
    "sg:city":"Pottendorf",
    "sg:orig_category":"Dachdeckereien",
    "sg:phone":"+43 2623 72343",
    "sg:postcode":"2486",
    "sg:province":"Nieder\u00f6sterreich",
    "wof:name":"Weninger Franz",
    "wof:placetype":"venue"
},
  "geometry": {"coordinates":[16.3824920654,47.9106483459],"type":"Point"}
}