{
  "type": "Feature",
  "properties": {
    "addr:full":"Fieberbrunner Str 14A St. Johann in Tirol Tirol 6380",
    "addr:housenumber":"14a",
    "addr:postcode":"johann;6380",
    "addr:street":"Str;Tirol",
    "iso:country":"AT",
    "sg:address":"Fieberbrunner Str 14A",
    "sg:city":"St. Johann in Tirol",
    "sg:orig_category":"Musikalien",
    "sg:phone":"+43 5352 66886",
    "sg:postcode":"6380",
    "sg:province":"Tirol",
    "wof:name":"X-Large Music",
    "wof:placetype":"venue"
},
  "geometry": {"coordinates":[12.4328718185,47.5209541321],"type":"Point"}
}