{
  "type": "Feature",
  "properties": {
    "addr:full":"Hofmark 23 Zell an der Pram Ober\u00f6sterreich 4755",
    "addr:housenumber":"23",
    "addr:postcode":"4755",
    "addr:street":"Hofmark",
    "iso:country":"AT",
    "sg:address":"Hofmark 23",
    "sg:city":"Zell an der Pram",
    "sg:classifiers":[
        {
            "category":"Manufacturing",
            "subcategory":"Wood Products",
            "type":"Manufacturing & Wholesale Goods"
        }
    ],
    "sg:phone":"+43 7764 83020",
    "sg:postcode":"4755",
    "sg:province":"Ober\u00f6sterreich",
    "sg:tags":[
        "lumber"
    ],
    "wof:name":"Herta Kirchberger",
    "wof:placetype":"venue"
},
  "geometry": {"coordinates":[13.629155159,48.3161315918],"type":"Point"}
}