{
  "type": "Feature",
  "properties": {
    "iso:country":"AT",
    "sg:address":"Katharina-Schratt-Str 4",
    "sg:city":"Bad Ischl",
    "sg:orig_category":"Motorbootfahrschulen",
    "sg:phone":"+43 4361 3224975",
    "sg:postcode":"4820",
    "sg:province":"Ober\u00f6sterreich",
    "wof:name":"Grabner Thomas Wasserschischule Strobl-Motorbootfahrschule",
    "wof:placetype":"venue"
},
  "geometry": {"coordinates":[13.6028699875,47.7187805176],"type":"Point"}
}