{
  "type": "Feature",
  "properties": {
    "addr:full":"St Ulrich 6 Altheim Ober\u00f6sterreich 4950",
    "addr:housenumber":"6",
    "addr:postcode":"4950",
    "addr:street":"St Ulrich",
    "iso:country":"AT",
    "sg:address":"St Ulrich 6",
    "sg:city":"Altheim",
    "sg:orig_category":"Tankstellen",
    "sg:phone":"+43 7723 42552",
    "sg:postcode":"4950",
    "sg:province":"Ober\u00f6sterreich",
    "wof:name":"OMV AG",
    "wof:placetype":"venue"
},
  "geometry": {"coordinates":[13.2365989685,48.2543869019],"type":"Point"}
}