{
  "type": "Feature",
  "properties": {
    "addr:full":"Bruckg 28 Pinkafeld Burgenland 7423",
    "addr:housenumber":"28",
    "addr:postcode":"7423",
    "addr:street":"Bruckg",
    "iso:country":"AT",
    "sg:address":"Bruckg 28",
    "sg:city":"Pinkafeld",
    "sg:orig_category":"Schuhmachereien",
    "sg:phone":"+43 3357 42288",
    "sg:postcode":"7423",
    "sg:province":"Burgenland",
    "wof:name":"W\u00f6lfer Alfred",
    "wof:placetype":"venue"
},
  "geometry": {"coordinates":[16.1197834015,47.3708457947],"type":"Point"}
}