{
  "type": "Feature",
  "properties": {
    "iso:country":"AT",
    "sg:address":"Nr 301",
    "sg:city":"Hinterglemm",
    "sg:orig_category":"Tabaktrafiken",
    "sg:phone":"+43 6541 7120",
    "sg:postcode":"5754",
    "sg:province":"Salzburg",
    "wof:name":"Tabaktrafik",
    "wof:placetype":"venue"
},
  "geometry": {"coordinates":[12.6012058258,47.3800849915],"type":"Point"}
}