{
  "type": "Feature",
  "properties": {
    "addr:full":"Raunaweg 77 Landskron K\u00e4rnten 9523",
    "addr:housenumber":"77",
    "addr:postcode":"9523",
    "addr:street":"Raunaweg;Kaernten",
    "iso:country":"AT",
    "sg:address":"Raunaweg 77",
    "sg:city":"Landskron",
    "sg:classifiers":[
        {
            "category":"Building & Trades",
            "subcategory":"Plumbing",
            "type":"Services"
        }
    ],
    "sg:phone":"+43 4242 41241",
    "sg:postcode":"9523",
    "sg:province":"K\u00e4rnten",
    "sg:tags":[
        "supraregional",
        "gas"
    ],
    "wof:name":"Rupert Gabritsch Ges.m.b.H.",
    "wof:placetype":"venue"
},
  "geometry": {"coordinates":[13.8747816086,46.6348152161],"type":"Point"}
}