{
  "type": "Feature",
  "properties": {
    "iso:country":"AT",
    "sg:address":"Steinamangerer Str 187",
    "sg:city":"Oberwart",
    "sg:orig_category":"Offsetdruckereien",
    "sg:phone":"+43 3352 335930",
    "sg:postcode":"7400",
    "sg:province":"Burgenland",
    "wof:name":"EUROPRINT",
    "wof:placetype":"venue"
},
  "geometry": {"coordinates":[16.2342319489,47.2739067078],"type":"Point"}
}