{
  "type": "Feature",
  "properties": {
    "iso:country":"AT",
    "sg:address":"Hauptstr 8",
    "sg:city":"Ehrwald",
    "sg:orig_category":"Apotheken",
    "sg:phone":"+43 5673 2274",
    "sg:postcode":"6632",
    "sg:province":"Tirol",
    "wof:name":"Zugspitz-Apotheke Mag pharm Wolfgang Lechner",
    "wof:placetype":"venue"
},
  "geometry": {"coordinates":[10.9186067581,47.400062561],"type":"Point"}
}