{
  "type": "Feature",
  "properties": {
    "iso:country":"AT",
    "sg:address":"Nr 158",
    "sg:city":"Haidershofen",
    "sg:orig_category":"Banken U Sparkassen",
    "sg:phone":"+43 4372 52378270",
    "sg:postcode":"4431",
    "sg:province":"Nieder\u00f6sterreich",
    "wof:name":"Raiffeisenkasse Haidershofen regGenmbH",
    "wof:placetype":"venue"
},
  "geometry": {"coordinates":[14.4578227997,48.0766983032],"type":"Point"}
}