{
  "type": "Feature",
  "properties": {
    "addr:full":"M\u00fchlstr 8 Gnigl Salzburg 5023",
    "addr:housenumber":"8",
    "addr:postcode":"5023",
    "addr:street":"Muehlstr",
    "iso:country":"AT",
    "sg:address":"M\u00fchlstr 8",
    "sg:city":"Gnigl",
    "sg:orig_category":"Lebens- U Sozialberatung",
    "sg:phone":"+43 662 640568",
    "sg:postcode":"5023",
    "sg:province":"Salzburg",
    "wof:name":"\u00d6AAP \u00d6sterreichischer Arbeitskreis f Angewandte Psychologie und Psychotherapie",
    "wof:placetype":"venue"
},
  "geometry": {"coordinates":[13.1081838608,47.8200416565],"type":"Point"}
}