{
  "type": "Feature",
  "properties": {
    "addr:full":"Knollg 6 Wien Wien 1170",
    "addr:housenumber":"6",
    "addr:postcode":"1170",
    "addr:street":"Knollg",
    "iso:country":"AT",
    "sg:address":"Knollg 6",
    "sg:city":"Wien",
    "sg:orig_category":"Volksschulen",
    "sg:phone":"+43 1 4863124",
    "sg:postcode":"1170",
    "sg:province":"Wien",
    "wof:name":"Schulen d Stadt Wien",
    "wof:placetype":"venue"
},
  "geometry": {"coordinates":[16.3308048248,48.2193107605],"type":"Point"}
}