{
  "type": "Feature",
  "properties": {
    "addr:full":"Hauptstr 16 Seibersdorf Nieder\u00f6sterreich 2444",
    "addr:housenumber":"16",
    "addr:postcode":"2444",
    "addr:street":"Hauptstr",
    "iso:country":"AT",
    "sg:address":"Hauptstr 16",
    "sg:city":"Seibersdorf",
    "sg:orig_category":"Landwirtschaftliche Hilfsdienste",
    "sg:phone":"+43 4322 557478",
    "sg:postcode":"2444",
    "sg:province":"Nieder\u00f6sterreich",
    "wof:name":"Winter Hermann",
    "wof:placetype":"venue"
},
  "geometry": {"coordinates":[16.518901825,47.958656311],"type":"Point"}
}