{
  "type": "Feature",
  "properties": {
    "addr:full":"Stainerstr 3 Innsbruck Tirol 6020",
    "addr:housenumber":"3",
    "addr:postcode":"6020",
    "addr:street":"Stainerstr;Tirol",
    "iso:country":"AT",
    "sg:address":"Stainerstr 3",
    "sg:city":"Innsbruck",
    "sg:orig_category":"Installationsunternehmen",
    "sg:phone":"+43 512 589825",
    "sg:postcode":"6020",
    "sg:province":"Tirol",
    "wof:name":"Steinlechner Franz",
    "wof:placetype":"venue"
},
  "geometry": {"coordinates":[11.3923635483,47.2667350769],"type":"Point"}
}