{
  "type": "Feature",
  "properties": {
    "addr:full":"Hauptstr 19 St. Lambrecht Steiermark 8813",
    "addr:housenumber":"19",
    "addr:postcode":"8813",
    "addr:street":"Hauptstr",
    "iso:country":"AT",
    "sg:address":"Hauptstr 19",
    "sg:city":"St. Lambrecht",
    "sg:orig_category":"Lebensmittel / Einzelhandel",
    "sg:phone":"+43 3585 22720",
    "sg:postcode":"8813",
    "sg:province":"Steiermark",
    "wof:name":"ADEG Aktiv Markt Thomas Durigon",
    "wof:placetype":"venue"
},
  "geometry": {"coordinates":[14.2986240387,47.0685691833],"type":"Point"}
}