{
  "type": "Feature",
  "properties": {
    "addr:full":"Nr 7 Stuhlfelden Salzburg 5724",
    "addr:postcode":"5724",
    "addr:street":"Nr;Stuhlfelden",
    "iso:country":"AT",
    "sg:address":"Nr 7",
    "sg:city":"Stuhlfelden",
    "sg:orig_category":"Holzhandel",
    "sg:phone":"+43 6562 4145",
    "sg:postcode":"5724",
    "sg:province":"Salzburg",
    "wof:name":"Egger Holz GmbH",
    "wof:placetype":"venue"
},
  "geometry": {"coordinates":[12.5289773941,47.2883834839],"type":"Point"}
}