{
  "type": "Feature",
  "properties": {
    "addr:full":"Freyung 319 Wien Wien 1010",
    "addr:housenumber":"319",
    "addr:postcode":"1010",
    "addr:street":"Freyung",
    "iso:country":"AT",
    "sg:address":"Freyung 319",
    "sg:city":"Wien",
    "sg:orig_category":"Telekommunikation",
    "sg:phone":"+43 4315 354711",
    "sg:postcode":"1010",
    "sg:province":"Wien",
    "wof:name":"Mobilmania Gro\u00dfhandelsgesmbH",
    "wof:placetype":"venue"
},
  "geometry": {"coordinates":[16.3661193848,48.2115783691],"type":"Point"}
}