{
  "type": "Feature",
  "properties": {
    "iso:country":"AT",
    "sg:address":"Hauptpl 2",
    "sg:city":"Jennersdorf",
    "sg:orig_category":"Non-Classified Establishments",
    "sg:phone":"+43 3329 45664",
    "sg:postcode":"8380",
    "sg:province":"Burgenland",
    "wof:name":"Kirchenbeitragsstelle",
    "wof:placetype":"venue"
},
  "geometry": {"coordinates":[16.1409072876,46.9374198914],"type":"Point"}
}