{
  "type": "Feature",
  "properties": {
    "iso:country":"AT",
    "sg:address":"Bahnhofstr 22",
    "sg:city":"Schruns",
    "sg:orig_category":"Textilreinigung",
    "sg:phone":"+43 5556 72612",
    "sg:postcode":"6780",
    "sg:province":"Vorarlberg",
    "wof:name":"Sander Heinrich GesmbH & Co KG",
    "wof:placetype":"venue"
},
  "geometry": {"coordinates":[9.9187145233,47.0795249939],"type":"Point"}
}