{
  "type": "Feature",
  "properties": {
    "addr:full":"Gartenweg 7 Bischofshofen Salzburg 5500",
    "addr:housenumber":"7",
    "addr:postcode":"5500",
    "addr:street":"Gartenweg;Salzburg",
    "iso:country":"AT",
    "sg:address":"Gartenweg 7",
    "sg:city":"Bischofshofen",
    "sg:classifiers":[
        {
            "category":"Banks & Credit Unions",
            "subcategory":"Investment Brokerage",
            "type":"Services"
        }
    ],
    "sg:phone":"+43 6462 2543",
    "sg:postcode":"5500",
    "sg:province":"Salzburg",
    "sg:tags":[
        "development",
        "electronics"
    ],
    "sg:website":"maisl.at",
    "wof:name":"Elektrotechnik Maisl",
    "wof:placetype":"venue"
},
  "geometry": {"coordinates":[13.2163562775,47.4212532043],"type":"Point"}
}