{
  "type": "Feature",
  "properties": {
    "addr:full":"Volkersdorf 8 Enns Ober\u00f6sterreich 4470",
    "addr:housenumber":"8",
    "addr:postcode":"4470",
    "addr:street":"Volkersdorf",
    "iso:country":"AT",
    "sg:address":"Volkersdorf 8",
    "sg:city":"Enns",
    "sg:orig_category":"Blitzableiter U Blitzschutzanlagen",
    "sg:phone":"+43 7223 80356",
    "sg:postcode":"4470",
    "sg:province":"Ober\u00f6sterreich",
    "wof:name":"DEHN AUSTRIA GmbH",
    "wof:placetype":"venue"
},
  "geometry": {"coordinates":[14.4278898239,48.183467865],"type":"Point"}
}