{
  "type": "Feature",
  "properties": {
    "addr:full":"Fadingerstr 23 Waizenkirchen Ober\u00f6sterreich 4730",
    "addr:housenumber":"23",
    "addr:postcode":"4730",
    "addr:street":"Fadingerstr",
    "iso:country":"AT",
    "sg:address":"Fadingerstr 23",
    "sg:city":"Waizenkirchen",
    "sg:orig_category":"Maler, Anstreicher U Lackierer",
    "sg:phone":"+43 7277 2298",
    "sg:postcode":"4730",
    "sg:province":"Ober\u00f6sterreich",
    "wof:name":"Weinzierl Rudolf",
    "wof:placetype":"venue"
},
  "geometry": {"coordinates":[13.8581209183,48.3317871094],"type":"Point"}
}