{
  "type": "Feature",
  "properties": {
    "addr:full":"Villacher Str 74 Feistritz an der Drau K\u00e4rnten 9710",
    "addr:postcode":"9710",
    "addr:street":"Str 74",
    "iso:country":"AT",
    "sg:address":"Villacher Str 74",
    "sg:city":"Feistritz an der Drau",
    "sg:orig_category":"Banken U Sparkassen",
    "sg:phone":"+43 4342 45640000",
    "sg:postcode":"9710",
    "sg:province":"K\u00e4rnten",
    "wof:name":"Raiffeisenbank Drautal regGenmbH",
    "wof:placetype":"venue"
},
  "geometry": {"coordinates":[13.6660671234,46.6996650696],"type":"Point"}
}