{
  "type": "Feature",
  "properties": {
    "addr:full":"Wiener Str 112 Kapfenberg Steiermark 8605",
    "addr:housenumber":"112",
    "addr:postcode":"8605",
    "iso:country":"AT",
    "sg:address":"Wiener Str 112",
    "sg:city":"Kapfenberg",
    "sg:orig_category":"Sonnenstudios",
    "sg:phone":"+43 4338 6226460",
    "sg:postcode":"8605",
    "sg:province":"Steiermark",
    "wof:name":"REGULUS Sonnenstudio",
    "wof:placetype":"venue"
},
  "geometry": {"coordinates":[15.3068237305,47.4486351013],"type":"Point"}
}