{
  "type": "Feature",
  "properties": {
    "iso:country":"AT",
    "sg:address":"Weidenstr 13",
    "sg:city":"Hartberg",
    "sg:orig_category":"Lebensmittel / Einzelhandel",
    "sg:phone":"+43 3332 61050",
    "sg:postcode":"8230",
    "sg:province":"Steiermark",
    "wof:name":"Billa AG",
    "wof:placetype":"venue"
},
  "geometry": {"coordinates":[15.9873380661,47.2842445374],"type":"Point"}
}