{
  "type": "Feature",
  "properties": {
    "iso:country":"AT",
    "sg:address":"Alte Str 20A",
    "sg:city":"Hard",
    "sg:orig_category":"Steinmetzbetriebe",
    "sg:phone":"+43 5574 65930",
    "sg:postcode":"6971",
    "sg:province":"Vorarlberg",
    "wof:name":"Burkhard Fessler GmbH",
    "wof:placetype":"venue"
},
  "geometry": {"coordinates":[9.6927728653,47.4850196838],"type":"Point"}
}