{
  "type": "Feature",
  "properties": {
    "addr:full":"Lainzerbachstr 37 Wien Wien 1130",
    "addr:housenumber":"37",
    "addr:postcode":"1130",
    "addr:street":"Lainzerbachstr",
    "iso:country":"AT",
    "sg:address":"Lainzerbachstr 37",
    "sg:city":"Wien",
    "sg:orig_category":"Ergotherapie",
    "sg:phone":"+43 1 4941398",
    "sg:postcode":"1130",
    "sg:province":"Wien",
    "wof:name":"W\u00fcrth Jochen",
    "wof:placetype":"venue"
},
  "geometry": {"coordinates":[16.2674026489,48.1655578613],"type":"Point"}
}