{
  "type": "Feature",
  "properties": {
    "addr:full":"Marktwald 5 Sch\u00f6rfling am Attersee Ober\u00f6sterreich 4861",
    "addr:housenumber":"5",
    "addr:postcode":"4861",
    "addr:street":"Marktwald;Am",
    "iso:country":"AT",
    "sg:address":"Marktwald 5",
    "sg:city":"Sch\u00f6rfling am Attersee",
    "sg:orig_category":"Automatisierungstechnik",
    "sg:phone":"+43 4376 62362520",
    "sg:postcode":"4861",
    "sg:province":"Ober\u00f6sterreich",
    "sg:website":"softtec.at",
    "wof:name":"SoftTec Austria",
    "wof:placetype":"venue"
},
  "geometry": {"coordinates":[13.6059789658,47.936416626],"type":"Point"}
}