{
  "type": "Feature",
  "properties": {
    "iso:country":"AT",
    "sg:address":"Marktwald 5",
    "sg:city":"Sch\u00f6rfling am Attersee",
    "sg:orig_category":"Automatisierungstechnik",
    "sg:phone":"+43 4376 62362520",
    "sg:postcode":"4861",
    "sg:province":"Ober\u00f6sterreich",
    "sg:website":"softtec.at",
    "wof:name":"SoftTec Austria",
    "wof:placetype":"venue"
},
  "geometry": {"coordinates":[13.6059789658,47.936416626],"type":"Point"}
}