{
  "type": "Feature",
  "properties": {
    "addr:full":"Oidener Str 97 Linz Ober\u00f6sterreich 4030",
    "addr:postcode":"4030",
    "addr:street":"Str 97",
    "iso:country":"AT",
    "sg:address":"Oidener Str 97",
    "sg:city":"Linz",
    "sg:orig_category":"Werbeagenturen",
    "sg:phone":"+43 732 321300",
    "sg:postcode":"4030",
    "sg:province":"Ober\u00f6sterreich",
    "wof:name":"Reichart GmbH",
    "wof:placetype":"venue"
},
  "geometry": {"coordinates":[14.3699932098,48.2470703125],"type":"Point"}
}