{
  "type": "Feature",
  "properties": {
    "addr:full":"Wieselburger Str 26 Gresten Nieder\u00f6sterreich 3264",
    "addr:housenumber":"26",
    "addr:postcode":"3264",
    "addr:street":"Str",
    "iso:country":"AT",
    "sg:address":"Wieselburger Str 26",
    "sg:city":"Gresten",
    "sg:orig_category":"Tischlereien",
    "sg:phone":"+43 7487 2360",
    "sg:postcode":"3264",
    "sg:province":"Nieder\u00f6sterreich",
    "wof:name":"Auer Wolfgang",
    "wof:placetype":"venue"
},
  "geometry": {"coordinates":[15.0219335556,47.9904670715],"type":"Point"}
}