{
  "type": "Feature",
  "properties": {
    "addr:full":"Linzer Str 11 Katsdorf Ober\u00f6sterreich 4223",
    "addr:housenumber":"11",
    "addr:postcode":"4223",
    "addr:street":"Linzer Str",
    "iso:country":"AT",
    "sg:address":"Linzer Str 11",
    "sg:city":"Katsdorf",
    "sg:orig_category":"Immobilienverwaltungen",
    "sg:phone":"+43 4372 35880000",
    "sg:postcode":"4223",
    "sg:province":"Ober\u00f6sterreich",
    "wof:name":"Mader Reisen Vertriebs-GmbH",
    "wof:placetype":"venue"
},
  "geometry": {"coordinates":[14.4703102112,48.3187637329],"type":"Point"}
}