{
  "type": "Feature",
  "properties": {
    "addr:full":"Wendstattg 7/2 Wien Wien 1100",
    "addr:housenumber":"7 / 2",
    "addr:postcode":"1100",
    "addr:street":"Wendstattg",
    "iso:country":"AT",
    "sg:address":"Wendstattg 7/2",
    "sg:city":"Wien",
    "sg:orig_category":"\u00c3\u201erzte / F Allgemeinmedizin",
    "sg:phone":"+43 1 6883568",
    "sg:postcode":"1100",
    "sg:province":"Wien",
    "wof:name":"Klinger Peter MedR Dr",
    "wof:placetype":"venue"
},
  "geometry": {"coordinates":[16.3911018372,48.1483383179],"type":"Point"}
}