{
  "type": "Feature",
  "properties": {
    "iso:country":"AT",
    "sg:address":"Feldkirchner Str 113",
    "sg:city":"Stra\u00dfgang",
    "sg:classifiers":[
        {
            "category":"Organizations",
            "subcategory":"Community Association",
            "type":"Services"
        }
    ],
    "sg:phone":"+43 316 296316",
    "sg:postcode":"8054",
    "sg:province":"Steiermark",
    "sg:tags":[
        "relation",
        "public"
    ],
    "wof:name":"EU-IR Herbert Strau\u00df",
    "wof:placetype":"venue"
},
  "geometry": {"coordinates":[15.4035177231,47.010471344],"type":"Point"}
}