{
  "type": "Feature",
  "properties": {
    "addr:full":"Ferdinand Leihs-Str 14 Hartberg Steiermark 8230",
    "addr:housenumber":"14",
    "addr:postcode":"8230",
    "iso:country":"AT",
    "sg:address":"Ferdinand Leihs-Str 14",
    "sg:city":"Hartberg",
    "sg:orig_category":"Raumausstattung",
    "sg:phone":"+43 3332 61601",
    "sg:postcode":"8230",
    "sg:province":"Steiermark",
    "wof:name":"Schieder W Boden- und Raumstudio",
    "wof:placetype":"venue"
},
  "geometry": {"coordinates":[15.9726915359,47.2797584534],"type":"Point"}
}