{
  "type": "Feature",
  "properties": {
    "addr:full":"Kircheng 12 Neuhofen an der Krems Ober\u00f6sterreich 4501",
    "addr:housenumber":"12",
    "addr:postcode":"4501",
    "addr:street":"Kircheng",
    "iso:country":"AT",
    "sg:address":"Kircheng 12",
    "sg:city":"Neuhofen an der Krems",
    "sg:orig_category":"Dekorationen",
    "sg:phone":"+43 4372 274313",
    "sg:postcode":"4501",
    "sg:province":"Ober\u00f6sterreich",
    "wof:name":"Neubauer Christine",
    "wof:placetype":"venue"
},
  "geometry": {"coordinates":[14.2275772095,48.1370620728],"type":"Point"}
}