{
  "type": "Feature",
  "properties": {
    "addr:full":"Shopping City Seiersberg 7 Puntigam Steiermark 8055",
    "addr:housenumber":"7",
    "addr:postcode":"8055",
    "addr:street":"Shopping City Seiersberg",
    "iso:country":"AT",
    "sg:address":"Shopping City Seiersberg 7",
    "sg:city":"Puntigam",
    "sg:orig_category":"Freizeit- U Sportbekleidung",
    "sg:phone":"+43 4331 6296936",
    "sg:postcode":"8055",
    "sg:province":"Steiermark",
    "wof:name":"BLAUMAX HandelsgmbH",
    "wof:placetype":"venue"
},
  "geometry": {"coordinates":[15.4129114151,47.0127563477],"type":"Point"}
}