{
  "type": "Feature",
  "properties": {
    "addr:full":"Nr 152 St. Peter am Kammersberg Steiermark 8843",
    "addr:postcode":"8843",
    "addr:street":"Nr 152",
    "iso:country":"AT",
    "sg:address":"Nr 152",
    "sg:city":"St. Peter am Kammersberg",
    "sg:orig_category":"Hauptschulen",
    "sg:phone":"+43 4335 368383",
    "sg:postcode":"8843",
    "sg:province":"Steiermark",
    "wof:name":"Hauptschule",
    "wof:placetype":"venue"
},
  "geometry": {"coordinates":[14.1869058609,47.187412262],"type":"Point"}
}