{
  "type": "Feature",
  "properties": {
    "addr:full":"Dragonerstr 44 Wels Ober\u00f6sterreich 4600",
    "addr:housenumber":"44",
    "addr:postcode":"4600",
    "addr:street":"Dragonerstr;Oberoesterreich",
    "iso:country":"AT",
    "sg:address":"Dragonerstr 44",
    "sg:city":"Wels",
    "sg:orig_category":"Botendienste",
    "sg:phone":"+43 664 3558515",
    "sg:postcode":"4600",
    "sg:province":"Ober\u00f6sterreich",
    "wof:name":"Macek G\u00fcnter Zustelldienst - Funktrans Wels",
    "wof:placetype":"venue"
},
  "geometry": {"coordinates":[14.0104637146,48.1558265686],"type":"Point"}
}