{
  "type": "Feature",
  "properties": {
    "addr:full":"Nr 3 Kirchstetten Nieder\u00f6sterreich 3062",
    "addr:postcode":"3062",
    "addr:street":"Nr;Kirchstetten",
    "iso:country":"AT",
    "sg:address":"Nr 3",
    "sg:city":"Kirchstetten",
    "sg:orig_category":"Montagen U Montagetechnik",
    "sg:phone":"+43 4327 4328100",
    "sg:postcode":"3062",
    "sg:province":"Nieder\u00f6sterreich",
    "sg:website":"pmsgmbh.at",
    "wof:name":"P.M.S. Planung Montage & Service GmbH",
    "wof:placetype":"venue"
},
  "geometry": {"coordinates":[15.8185558319,48.1837615967],"type":"Point"}
}