{
  "type": "Feature",
  "properties": {
    "iso:country":"AT",
    "sg:address":"Hauptstr 48",
    "sg:city":"Oberpullendorf",
    "sg:orig_category":"Unterhaltungselektronik / Reparatur",
    "sg:phone":"+43 2612 42265",
    "sg:postcode":"7350",
    "sg:province":"Burgenland",
    "wof:name":"Kneisz Ing",
    "wof:placetype":"venue"
},
  "geometry": {"coordinates":[16.5060977936,47.4988021851],"type":"Point"}
}