{
  "type": "Feature",
  "properties": {
    "iso:country":"AT",
    "sg:address":"Hauptstr 39",
    "sg:city":"St. Valentin",
    "sg:orig_category":"Tabaktrafiken",
    "sg:phone":"+43 7435 52738",
    "sg:postcode":"4300",
    "sg:province":"Nieder\u00f6sterreich",
    "wof:name":"G\u00fctl Christian",
    "wof:placetype":"venue"
},
  "geometry": {"coordinates":[14.5271520615,48.1748352051],"type":"Point"}
}