{
  "type": "Feature",
  "properties": {
    "addr:full":"Exlgasse 20 Innsbruck Tirol 6020",
    "addr:housenumber":"20",
    "addr:postcode":"6020",
    "addr:street":"Exlgasse;Tirol",
    "iso:country":"AT",
    "sg:address":"Exlgasse 20",
    "sg:city":"Innsbruck",
    "sg:classifiers":[
        {
            "category":"Communications",
            "subcategory":"Film & Video Production",
            "type":"Services"
        }
    ],
    "sg:phone":"+43 512 293000",
    "sg:postcode":"6020",
    "sg:province":"Tirol",
    "sg:tags":[
        "photography",
        "digital"
    ],
    "sg:website":"laserpoint.at",
    "wof:name":"Athesia-Laserpoint Digital & Medien Service GmbH",
    "wof:placetype":"venue"
},
  "geometry": {"coordinates":[11.3721590042,47.2597236633],"type":"Point"}
}