{
  "type": "Feature",
  "properties": {
    "iso:country":"AT",
    "sg:address":"Dirmhirng 128",
    "sg:city":"Wien",
    "sg:orig_category":"Handelsagenturen",
    "sg:phone":"+43 1 86991200",
    "sg:postcode":"1230",
    "sg:province":"Wien",
    "wof:name":"KTS Peter Sporrer Handelsagentur f\u00fcr Kabeltechnik GmbH",
    "wof:placetype":"venue"
},
  "geometry": {"coordinates":[16.2833442688,48.137512207],"type":"Point"}
}