{
  "type": "Feature",
  "properties": {
    "addr:full":"Wettersteinstr 29 Ehrwald Tirol 6632",
    "addr:housenumber":"29",
    "addr:postcode":"6632",
    "addr:street":"Wettersteinstr;Tirol",
    "iso:country":"AT",
    "sg:address":"Wettersteinstr 29",
    "sg:city":"Ehrwald",
    "sg:orig_category":"Appartements / Ferienwohnungen",
    "sg:phone":"+43 5673 31510",
    "sg:postcode":"6632",
    "sg:province":"Tirol",
    "wof:name":"Wimmer Johann",
    "wof:placetype":"venue"
},
  "geometry": {"coordinates":[10.9250526428,47.4007835388],"type":"Point"}
}