{
  "type": "Feature",
  "properties": {
    "addr:full":"Nonntaler Hauptstrasse 41 Salzburg Salzburg 5020",
    "addr:housenumber":"41",
    "addr:postcode":"5020",
    "addr:street":"Nonntaler Hauptstrasse;Salzburg",
    "iso:country":"AT",
    "sg:address":"Nonntaler Hauptstrasse 41",
    "sg:city":"Salzburg",
    "sg:classifiers":[
        {
            "category":"Manufacturing",
            "subcategory":"Glass & Minerals",
            "type":"Manufacturing & Wholesale Goods"
        }
    ],
    "sg:phone":"+43 662 829188",
    "sg:postcode":"5020",
    "sg:province":"Salzburg",
    "sg:tags":[
        "wall",
        "partition",
        "accordion"
    ],
    "wof:name":"Glaserei Laurenz D. Jandl",
    "wof:placetype":"venue"
},
  "geometry": {"coordinates":[13.0498809814,47.7904167175],"type":"Point"}
}