{
  "type": "Feature",
  "properties": {
    "iso:country":"AT",
    "sg:address":"Hauptpl 4",
    "sg:city":"Marchegg",
    "sg:orig_category":"Spielwaren U Spiele",
    "sg:phone":"+43 2285 8565",
    "sg:postcode":"2293",
    "sg:province":"Nieder\u00f6sterreich",
    "wof:name":"Schmidt Anna",
    "wof:placetype":"venue"
},
  "geometry": {"coordinates":[16.9103126526,48.2793617249],"type":"Point"}
}