{
  "type": "Feature",
  "properties": {
    "iso:country":"AT",
    "sg:address":"Ossiacher Zeile 46",
    "sg:city":"Villach",
    "sg:classifiers":[
        {
            "category":"Restaurant",
            "type":"Food & Drink"
        }
    ],
    "sg:phone":"+43 4242 37134",
    "sg:postcode":"9500",
    "sg:province":"K\u00e4rnten",
    "wof:name":"Pension - Steak House Rob Roy",
    "wof:placetype":"venue"
},
  "geometry": {"coordinates":[13.8504800797,46.6081695557],"type":"Point"}
}