{
  "type": "Feature",
  "properties": {
    "iso:country":"AT",
    "sg:address":"Gabelhoferstr 8",
    "sg:city":"Fohnsdorf",
    "sg:orig_category":"Transportunternehmen",
    "sg:phone":"+43 3573 3976",
    "sg:postcode":"8753",
    "sg:province":"Steiermark",
    "wof:name":"Zuber Transporte",
    "wof:placetype":"venue"
},
  "geometry": {"coordinates":[14.6683502197,47.1935691833],"type":"Point"}
}