{
  "type": "Feature",
  "properties": {
    "iso:country":"AT",
    "sg:address":"Helenenstr 57-59",
    "sg:city":"Baden",
    "sg:classifiers":[
        {
            "category":"Travel",
            "subcategory":"Hotels & Motels",
            "type":"Entertainment"
        }
    ],
    "sg:phone":"+43 2252 48400",
    "sg:postcode":"2500",
    "sg:province":"Nieder\u00f6sterreich",
    "wof:name":"Hotelappartements Familie Sacher",
    "wof:placetype":"venue"
},
  "geometry": {"coordinates":[16.2036571503,48.01197052],"type":"Point"}
}