{
  "type": "Feature",
  "properties": {
    "addr:full":"Mauermannstr. 8-10  5021",
    "addr:housenumber":"8-10",
    "addr:postcode":"5021",
    "iso:country":"AT",
    "sg:address":"Mauermannstr. 8-10 ",
    "sg:classifiers":[
        {
            "category":"Food & Beverages",
            "subcategory":"Groceries & Convenience Stores",
            "type":"Retail Goods"
        }
    ],
    "sg:phone":"+43 4366 26610460",
    "sg:postcode":"5021",
    "sg:tags":[
        "drink"
    ],
    "wof:name":"NANNERL NAHRUNGSMITTEL SPEZIALT\u00c4TEN GMBH",
    "wof:placetype":"venue"
},
  "geometry": {"coordinates":[13.0611639023,47.8261375427],"type":"Point"}
}