{
  "type": "Feature",
  "properties": {
    "iso:country":"AT",
    "sg:address":"Prechtlg 7",
    "sg:city":"Wien",
    "sg:orig_category":"Juweliere, Gold- U Silberschmiede",
    "sg:phone":"+43 4314 063129",
    "sg:postcode":"1090",
    "sg:province":"Wien",
    "wof:name":"Balaska Swetislaw",
    "wof:placetype":"venue"
},
  "geometry": {"coordinates":[16.3505744934,48.2232513428],"type":"Point"}
}