{
  "type": "Feature",
  "properties": {
    "addr:full":"Nr 44 R\u00f6hrenbach Nieder\u00f6sterreich 3592",
    "addr:postcode":"3592",
    "addr:street":"Nr 44 Roehrenbach",
    "iso:country":"AT",
    "sg:address":"Nr 44",
    "sg:city":"R\u00f6hrenbach",
    "sg:orig_category":"Schmieden U Schmiedeeisenelemente",
    "sg:phone":"+43 4329 8980350",
    "sg:postcode":"3592",
    "sg:province":"Nieder\u00f6sterreich",
    "wof:name":"Suchan Leopold",
    "wof:placetype":"venue"
},
  "geometry": {"coordinates":[15.5094175339,48.6553764343],"type":"Point"}
}