{
  "type": "Feature",
  "properties": {
    "addr:full":"Nr 131 Haidershofen Nieder\u00f6sterreich 4431",
    "addr:housenumber":"4431",
    "addr:street":"Nr;Haidershofen Niederoesterreich",
    "iso:country":"AT",
    "sg:address":"Nr 131",
    "sg:city":"Haidershofen",
    "sg:orig_category":"Lebens- U Sozialberatung",
    "sg:phone":"+43 4367 66127820",
    "sg:postcode":"4431",
    "sg:province":"Nieder\u00f6sterreich",
    "wof:name":"Ruttensteiner Manuela Dipl System Lebensberaterin Ausdrucksp\u00e4dagogin Tanztrainerin",
    "wof:placetype":"venue"
},
  "geometry": {"coordinates":[14.4578227997,48.0766983032],"type":"Point"}
}