{
  "type": "Feature",
  "properties": {
    "iso:country":"AT",
    "sg:address":"Nr 75",
    "sg:city":"Loosdorf",
    "sg:orig_category":"Volksschulen",
    "sg:phone":"+43 4325 248597",
    "sg:postcode":"2133",
    "sg:province":"Nieder\u00f6sterreich",
    "wof:name":"Volksschule",
    "wof:placetype":"venue"
},
  "geometry": {"coordinates":[16.4125576019,48.6558914185],"type":"Point"}
}