{
  "type": "Feature",
  "properties": {
    "iso:country":"AT",
    "sg:address":"Innsbrucker Str 3",
    "sg:city":"Scharnitz",
    "sg:orig_category":"Pensionen / Privatzimmer",
    "sg:phone":"+43 5213 5302",
    "sg:postcode":"6108",
    "sg:province":"Tirol",
    "wof:name":"Brunnerhof",
    "wof:placetype":"venue"
},
  "geometry": {"coordinates":[11.2620210648,47.3881416321],"type":"Point"}
}