{
  "type": "Feature",
  "properties": {
    "iso:country":"AT",
    "sg:address":"Meierhofgasse 1",
    "sg:city":"Hopfgarten im Brixental",
    "sg:classifiers":[
        {
            "category":"Home & Garden",
            "subcategory":"Home Furnishings",
            "type":"Retail Goods"
        }
    ],
    "sg:phone":"+43 5335 3880",
    "sg:postcode":"6361",
    "sg:province":"Tirol",
    "sg:tags":[
        "track",
        "curtain"
    ],
    "wof:name":"Buchmayr vorm. Schwaiger KG",
    "wof:placetype":"venue"
},
  "geometry": {"coordinates":[12.1620168686,47.4474182129],"type":"Point"}
}