{
  "type": "Feature",
  "properties": {
    "addr:full":"Postg 4 Bleiburg K\u00e4rnten 9150",
    "addr:housenumber":"4",
    "addr:postcode":"9150",
    "addr:street":"Postg;Kaernten",
    "iso:country":"AT",
    "sg:address":"Postg 4",
    "sg:city":"Bleiburg",
    "sg:orig_category":"\u00c3\u201erzte / F Allgemeinmedizin",
    "sg:phone":"+43 4342 352700",
    "sg:postcode":"9150",
    "sg:province":"K\u00e4rnten",
    "wof:name":"Kieninger Hans Werner Dr",
    "wof:placetype":"venue"
},
  "geometry": {"coordinates":[14.799115181,46.5901870728],"type":"Point"}
}