{
  "type": "Feature",
  "properties": {
    "addr:full":"Am Reisch 5 Hochfilzen Tirol 6395",
    "addr:housenumber":"5",
    "addr:postcode":"6395",
    "addr:street":"Am Reisch;Tirol",
    "iso:country":"AT",
    "sg:address":"Am Reisch 5",
    "sg:city":"Hochfilzen",
    "sg:orig_category":"Innenarchitekten",
    "sg:phone":"+43 5359 745",
    "sg:postcode":"6395",
    "sg:province":"Tirol",
    "wof:name":"K\u00f6ck & Bachler GmbH",
    "wof:placetype":"venue"
},
  "geometry": {"coordinates":[12.6235866547,47.468547821],"type":"Point"}
}