{
  "type": "Feature",
  "properties": {
    "addr:full":"Kolpingstrasse 12 Wien Wien 1230",
    "addr:housenumber":"12",
    "addr:postcode":"1230",
    "addr:street":"Kolpingstrasse",
    "iso:country":"AT",
    "sg:address":"Kolpingstrasse 12",
    "sg:city":"Wien",
    "sg:classifiers":[
        {
            "category":"Home & Garden",
            "subcategory":"Mobile Homes",
            "type":"Retail Goods"
        }
    ],
    "sg:phone":"+43 1 6167909",
    "sg:postcode":"1230",
    "sg:province":"Wien",
    "sg:tags":[
        "awning",
        "outdoor",
        "marquee"
    ],
    "sg:website":"dolenz-wien.at",
    "wof:name":"Dolenz, Gollner Sonnenschutz Handels GmbH",
    "wof:placetype":"venue"
},
  "geometry": {"coordinates":[16.3437404633,48.1394271851],"type":"Point"}
}