{
  "type": "Feature",
  "properties": {
    "addr:full":"Glanzingg 31 Wien Wien 1190",
    "addr:housenumber":"31",
    "addr:postcode":"1190",
    "addr:street":"Glanzingg",
    "iso:country":"AT",
    "sg:address":"Glanzingg 31",
    "sg:city":"Wien",
    "sg:orig_category":"Immobilienmakler",
    "sg:phone":"+43 1 4794172",
    "sg:postcode":"1190",
    "sg:province":"Wien",
    "wof:name":"Au Rudolf",
    "wof:placetype":"venue"
},
  "geometry": {"coordinates":[16.3157730103,48.2428779602],"type":"Point"}
}