{
  "type": "Feature",
  "properties": {
    "addr:full":"Kircheng 8 Ritzing Burgenland 7323",
    "addr:housenumber":"8",
    "addr:postcode":"7323",
    "addr:street":"Kircheng",
    "iso:country":"AT",
    "sg:address":"Kircheng 8",
    "sg:city":"Ritzing",
    "sg:orig_category":"Non-Classified Establishments",
    "sg:phone":"+43 2619 67340",
    "sg:postcode":"7323",
    "sg:province":"Burgenland",
    "wof:name":"Pfarramt",
    "wof:placetype":"venue"
},
  "geometry": {"coordinates":[16.495552063,47.6056518555],"type":"Point"}
}