{
  "type": "Feature",
  "properties": {
    "addr:full":"Schischulstr 405 Saalbach Salzburg 5753",
    "addr:housenumber":"405",
    "addr:postcode":"5753",
    "addr:street":"Saalbach Salzburg",
    "iso:country":"AT",
    "sg:address":"Schischulstr 405",
    "sg:city":"Saalbach",
    "sg:classifiers":[
        {
            "category":"Park",
            "subcategory":"Provincial",
            "type":"Public Place"
        }
    ],
    "sg:phone":"+43 4365 41668236",
    "sg:postcode":"5753",
    "sg:province":"Salzburg",
    "sg:tags":[
        "u",
        "ski-",
        "snowboardschulen"
    ],
    "wof:name":"Snowacademy Aamadall",
    "wof:placetype":"venue"
},
  "geometry": {"coordinates":[12.6377477646,47.389957428],"type":"Point"}
}