{
  "type": "Feature",
  "properties": {
    "addr:full":"Obertshausener Str 2 Laakirchen Ober\u00f6sterreich 4663",
    "addr:housenumber":"2",
    "addr:postcode":"4663",
    "addr:street":"Str",
    "iso:country":"AT",
    "sg:address":"Obertshausener Str 2",
    "sg:city":"Laakirchen",
    "sg:classifiers":[
        {
            "category":"Restaurant",
            "type":"Food & Drink"
        }
    ],
    "sg:phone":"+43 76138206",
    "sg:postcode":"4663",
    "sg:province":"Ober\u00f6sterreich",
    "wof:name":"Sportland Restaurant",
    "wof:placetype":"venue"
},
  "geometry": {"coordinates":[13.815826416,47.9861373901],"type":"Point"}
}