{
  "type": "Feature",
  "properties": {
    "iso:country":"AT",
    "sg:address":"Pichlmayerg 16",
    "sg:city":"Leoben",
    "sg:orig_category":"Lebensmittel / Einzelhandel",
    "sg:phone":"+43 4338 42215830",
    "sg:postcode":"8700",
    "sg:province":"Steiermark",
    "wof:name":"MERKUR Markt",
    "wof:placetype":"venue"
},
  "geometry": {"coordinates":[15.091509819,47.3702888489],"type":"Point"}
}