{
  "type": "Feature",
  "properties": {
    "addr:full":"Veterin\u00e4rpl 1 Wien Wien 1210",
    "addr:housenumber":"1",
    "addr:postcode":"1210",
    "addr:street":"Veterinaerpl",
    "iso:country":"AT",
    "sg:address":"Veterin\u00e4rpl 1",
    "sg:city":"Wien",
    "sg:orig_category":"Institute",
    "sg:phone":"+43 1 250772201",
    "sg:postcode":"1210",
    "sg:province":"Wien",
    "wof:name":"Institut f Parasitologie und Zoologie d Veterin\u00e4rmed. Universit\u00e4t Wien",
    "wof:placetype":"venue"
},
  "geometry": {"coordinates":[16.4318065643,48.2545318604],"type":"Point"}
}