{
  "type": "Feature",
  "properties": {
    "addr:full":"Drosendorf Altstadt 44 Drosendorf an der Thaya Nieder\u00f6sterreich 2095",
    "addr:housenumber":"44",
    "addr:postcode":"2095",
    "addr:street":"Altstadt;An Der Thaya",
    "iso:country":"AT",
    "sg:address":"Drosendorf Altstadt 44",
    "sg:city":"Drosendorf an der Thaya",
    "sg:classifiers":[
        {
            "category":"Home & Garden",
            "subcategory":"Household Appliances",
            "type":"Retail Goods"
        }
    ],
    "sg:phone":"+43 2915 2272",
    "sg:postcode":"2095",
    "sg:province":"Nieder\u00f6sterreich",
    "sg:tags":[
        "implement",
        "gardening",
        "tool"
    ],
    "wof:name":"Eduard M\u00fcllner",
    "wof:placetype":"venue"
},
  "geometry": {"coordinates":[15.6255941391,48.867061615],"type":"Point"}
}