{
  "type": "Feature",
  "properties": {
    "iso:country":"AT",
    "sg:address":"Nr 1",
    "sg:city":"Kappel am Krappfeld",
    "sg:orig_category":"Massagen",
    "sg:phone":"+43 4342 624416",
    "sg:postcode":"9321",
    "sg:province":"K\u00e4rnten",
    "wof:name":"Akupunktmassage u Massagepraxis Rudolf Weilharter",
    "wof:placetype":"venue"
},
  "geometry": {"coordinates":[166.9221496582,-0.5282999873],"type":"Point"}
}