{
  "type": "Feature",
  "properties": {
    "addr:full":"Hauptstr 37 Gro\u00dfpetersdorf Burgenland 7503",
    "addr:housenumber":"37",
    "addr:postcode":"7503",
    "addr:street":"Hauptstr",
    "iso:country":"AT",
    "sg:address":"Hauptstr 37",
    "sg:city":"Gro\u00dfpetersdorf",
    "sg:orig_category":"\u00c3\u201erzte / F Allgemeinmedizin",
    "sg:phone":"+43 3362 24200",
    "sg:postcode":"7503",
    "sg:province":"Burgenland",
    "wof:name":"Kaitan Wilhelmine Dr",
    "wof:placetype":"venue"
},
  "geometry": {"coordinates":[8.0342617035,53.0030250549],"type":"Point"}
}