{
  "type": "Feature",
  "properties": {
    "iso:country":"AT",
    "sg:address":"Lungendorf 25",
    "sg:city":"Pettenbach",
    "sg:orig_category":"Autoreparatur",
    "sg:phone":"+43 4375 868902",
    "sg:postcode":"4643",
    "sg:province":"Ober\u00f6sterreich",
    "wof:name":"Gruber Andrea u Alois",
    "wof:placetype":"venue"
},
  "geometry": {"coordinates":[13.9603796005,47.9773101807],"type":"Point"}
}