{
  "type": "Feature",
  "properties": {
    "addr:full":"Hauptstr 14 Oberpullendorf Burgenland 7350",
    "addr:housenumber":"14",
    "addr:postcode":"7350",
    "addr:street":"Hauptstr",
    "iso:country":"AT",
    "sg:address":"Hauptstr 14",
    "sg:city":"Oberpullendorf",
    "sg:orig_category":"Fotoapparate U -Artikel / Einzelhandel",
    "sg:phone":"+43 2612 45958",
    "sg:postcode":"7350",
    "sg:province":"Burgenland",
    "wof:name":"Hartlauer HandelsgesmbH",
    "wof:placetype":"venue"
},
  "geometry": {"coordinates":[16.5052375793,47.5008926392],"type":"Point"}
}