{
  "type": "Feature",
  "properties": {
    "iso:country":"AT",
    "sg:address":"Richardsweg 15",
    "sg:city":"Innsbruck",
    "sg:orig_category":"Werbegrafik- U Grafik-Design",
    "sg:phone":"+43 512 2669180",
    "sg:postcode":"6020",
    "sg:province":"Tirol",
    "wof:name":"Bergant Richard",
    "wof:placetype":"venue"
},
  "geometry": {"coordinates":[11.4033794403,47.2814407349],"type":"Point"}
}