{
  "type": "Feature",
  "properties": {
    "addr:full":"Linzer G 41 Salzburg Salzburg 5020",
    "addr:housenumber":"41",
    "addr:postcode":"5020",
    "addr:street":"Linzer G;Salzburg",
    "iso:country":"AT",
    "sg:address":"Linzer G 41",
    "sg:city":"Salzburg",
    "sg:orig_category":"Boutiquen",
    "sg:phone":"+43 662 885784",
    "sg:postcode":"5020",
    "sg:province":"Salzburg",
    "wof:name":"Boutique Mona",
    "wof:placetype":"venue"
},
  "geometry": {"coordinates":[13.0474472046,47.8039779663],"type":"Point"}
}