{
  "type": "Feature",
  "properties": {
    "addr:full":"Mayerlehen 12 Seekirchen am Wallersee Salzburg 5201",
    "addr:housenumber":"12",
    "addr:postcode":"5201",
    "addr:street":"Mayerlehen;Salzburg",
    "iso:country":"AT",
    "sg:address":"Mayerlehen 12",
    "sg:city":"Seekirchen am Wallersee",
    "sg:orig_category":"Personalbereitstellung",
    "sg:phone":"+43 4362 1262590",
    "sg:postcode":"5201",
    "sg:province":"Salzburg",
    "wof:name":"Maschinenring Flachgau",
    "wof:placetype":"venue"
},
  "geometry": {"coordinates":[13.0767621994,47.8971405029],"type":"Point"}
}