{
  "type": "Feature",
  "properties": {
    "addr:full":"Sankt-Paul-Gasse 6 Krems an der Donau Nieder\u00f6sterreich 3500",
    "addr:housenumber":"6",
    "addr:postcode":"3500",
    "addr:street":"Sankt-Paul-Gasse",
    "iso:country":"AT",
    "sg:address":"Sankt-Paul-Gasse 6",
    "sg:city":"Krems an der Donau",
    "sg:orig_category":"CarpenterS Work Supraregional",
    "sg:phone":"+43 2732 74684",
    "sg:postcode":"3500",
    "sg:province":"Nieder\u00f6sterreich",
    "wof:name":"Florian Subosics",
    "wof:placetype":"venue"
},
  "geometry": {"coordinates":[15.6173801422,48.4083824158],"type":"Point"}
}