{
  "type": "Feature",
  "properties": {
    "addr:full":"Patriasdorf 13 Lienz Tirol 9900",
    "addr:housenumber":"13",
    "addr:postcode":"9900",
    "addr:street":"Patriasdorf;Tirol",
    "iso:country":"AT",
    "sg:address":"Patriasdorf 13",
    "sg:city":"Lienz",
    "sg:orig_category":"Tischlereien",
    "sg:phone":"+43 4852 65692",
    "sg:postcode":"9900",
    "sg:province":"Tirol",
    "wof:name":"Fuetsch Walter T\u00fcrenhof-Lienz",
    "wof:placetype":"venue"
},
  "geometry": {"coordinates":[12.7612285614,46.8368263245],"type":"Point"}
}