{
  "type": "Feature",
  "properties": {
    "addr:full":"Wies 29 S\u00f6ll Tirol 6306",
    "addr:housenumber":"29",
    "addr:postcode":"6306",
    "addr:street":"Wies;Tirol",
    "iso:country":"AT",
    "sg:address":"Wies 29",
    "sg:city":"S\u00f6ll",
    "sg:orig_category":"Sonnenschutzanlagen",
    "sg:phone":"+43 5333 202670",
    "sg:postcode":"6306",
    "sg:province":"Tirol",
    "wof:name":"Holm & Holm KEG - Sunstop Sonnenschutzsysteme und Neher Insektenschutz nach Ma\u00df",
    "wof:placetype":"venue"
},
  "geometry": {"coordinates":[-73.28117370610001,42.2773971558],"type":"Point"}
}