{
  "type": "Feature",
  "properties": {
    "addr:full":"Sch\u00f6nauweg 4 Vordernberg Steiermark 8794",
    "addr:housenumber":"4",
    "addr:postcode":"8794",
    "addr:street":"Schoenauweg",
    "iso:country":"AT",
    "sg:address":"Sch\u00f6nauweg 4",
    "sg:city":"Vordernberg",
    "sg:orig_category":"Imkereien",
    "sg:phone":"+43 4338 49866",
    "sg:postcode":"8794",
    "sg:province":"Steiermark",
    "wof:name":"Tratsch Kurt - Imkerei u K\u00f6niginenzucht",
    "wof:placetype":"venue"
},
  "geometry": {"coordinates":[14.9936122894,47.492477417],"type":"Point"}
}