{
  "type": "Feature",
  "properties": {
    "addr:full":"Peerhofstr 3 Innsbruck Tirol 6020",
    "addr:housenumber":"3",
    "addr:postcode":"6020",
    "addr:street":"Peerhofstr;Tirol",
    "iso:country":"AT",
    "sg:address":"Peerhofstr 3",
    "sg:city":"Innsbruck",
    "sg:orig_category":"Beratungsstellen",
    "sg:phone":"+43 512 281396",
    "sg:postcode":"6020",
    "sg:province":"Tirol",
    "wof:name":"Erziehungsberatungsstelle",
    "wof:placetype":"venue"
},
  "geometry": {"coordinates":[11.346364975,47.2687835693],"type":"Point"}
}