{
  "type": "Feature",
  "properties": {
    "addr:full":"Haitzing 6 Laakirchen Ober\u00f6sterreich 4663",
    "addr:housenumber":"6",
    "addr:postcode":"4663",
    "addr:street":"Haitzing",
    "iso:country":"AT",
    "sg:address":"Haitzing 6",
    "sg:city":"Laakirchen",
    "sg:orig_category":"Autobusunternehmen",
    "sg:phone":"+43 76133130",
    "sg:postcode":"4663",
    "sg:province":"Ober\u00f6sterreich",
    "sg:website":"www.stockhammer-reisen.at",
    "wof:name":"Stockhammer Touristik",
    "wof:placetype":"venue"
},
  "geometry": {"coordinates":[13.8415727615,47.9832801819],"type":"Point"}
}