{
  "type": "Feature",
  "properties": {
    "addr:full":"Nr 239 Markt Neuhodis Burgenland 7464",
    "addr:postcode":"7464",
    "addr:street":"Nr",
    "iso:country":"AT",
    "sg:address":"Nr 239",
    "sg:city":"Markt Neuhodis",
    "sg:orig_category":"Putze",
    "sg:phone":"+43 4333 6377660",
    "sg:postcode":"7464",
    "sg:province":"Burgenland",
    "wof:name":"Tallian Heinrich",
    "wof:placetype":"venue"
},
  "geometry": {"coordinates":[16.3952350616,47.2961273193],"type":"Point"}
}