{
  "type": "Feature",
  "properties": {
    "iso:country":"AT",
    "sg:address":"Weiberfelderweg 3",
    "sg:city":"Stra\u00dfgang",
    "sg:orig_category":"Montagen U Montagetechnik",
    "sg:phone":"+43 316 2856650",
    "sg:postcode":"8054",
    "sg:province":"Steiermark",
    "wof:name":"W\u00fcrth HandelsgesmbH - Kundenzentrum Graz",
    "wof:placetype":"venue"
},
  "geometry": {"coordinates":[15.40026474,47.0279045105],"type":"Point"}
}