{
  "type": "Feature",
  "properties": {
    "addr:full":"Seespitzstr 4 Zell am See Salzburg 5700",
    "addr:housenumber":"4",
    "addr:postcode":"5700",
    "addr:street":"Seespitzstr;Salzburg",
    "iso:country":"AT",
    "sg:address":"Seespitzstr 4",
    "sg:city":"Zell am See",
    "sg:orig_category":"Raumausstattung",
    "sg:phone":"+43 6542 572810",
    "sg:postcode":"5700",
    "sg:province":"Salzburg",
    "wof:name":"St\u00f6ckl Egon GesmbH",
    "wof:placetype":"venue"
},
  "geometry": {"coordinates":[12.7946071625,47.3092460632],"type":"Point"}
}