{
  "type": "Feature",
  "properties": {
    "addr:full":"Hauptstr 168 Kalsdorf Steiermark 8401",
    "addr:housenumber":"168",
    "addr:postcode":"8401",
    "addr:street":"Hauptstr",
    "iso:country":"AT",
    "sg:address":"Hauptstr 168",
    "sg:city":"Kalsdorf",
    "sg:orig_category":"Unternehmensberatung",
    "sg:phone":"+43 3135 52247",
    "sg:postcode":"8401",
    "sg:province":"Steiermark",
    "wof:name":"Haider Willibald",
    "wof:placetype":"venue"
},
  "geometry": {"coordinates":[15.4800043106,46.9573516846],"type":"Point"}
}