{
  "type": "Feature",
  "properties": {
    "addr:full":"M\u00fcnchendorfer Str 4 Himberg Nieder\u00f6sterreich 2325",
    "addr:housenumber":"4",
    "addr:postcode":"2325",
    "addr:street":"Str",
    "iso:country":"AT",
    "sg:address":"M\u00fcnchendorfer Str 4",
    "sg:city":"Himberg",
    "sg:orig_category":"Rauchfangkehrer",
    "sg:phone":"+43 4322 35862760",
    "sg:postcode":"2325",
    "sg:province":"Nieder\u00f6sterreich",
    "wof:name":"Fr\u00fcchtl Alexandra",
    "wof:placetype":"venue"
},
  "geometry": {"coordinates":[16.4394855499,48.0822868347],"type":"Point"}
}