{
  "type": "Feature",
  "properties": {
    "iso:country":"AT",
    "sg:address":"Nr 117",
    "sg:city":"Berwang",
    "sg:orig_category":"Tischlereien",
    "sg:phone":"+43 5674 8242",
    "sg:postcode":"6622",
    "sg:province":"Tirol",
    "wof:name":"Lorenz Bautischlerei-M\u00f6beldesign GesmbH",
    "wof:placetype":"venue"
},
  "geometry": {"coordinates":[10.7468204498,47.4090003967],"type":"Point"}
}