{
  "type": "Feature",
  "properties": {
    "iso:country":"AT",
    "sg:address":"Pollheimerstr 15",
    "sg:city":"Wels",
    "sg:orig_category":"Zeitungen U Zeitschriften",
    "sg:phone":"+43 4372 4235106",
    "sg:postcode":"4600",
    "sg:province":"Ober\u00f6sterreich",
    "wof:name":"holl-media GmbH",
    "wof:placetype":"venue"
},
  "geometry": {"coordinates":[14.0220842361,48.1562767029],"type":"Point"}
}