{
  "type": "Feature",
  "properties": {
    "addr:full":"Steigenteschg 22 Wien Wien 1220",
    "addr:housenumber":"22",
    "addr:postcode":"1220",
    "addr:street":"Steigenteschg",
    "iso:country":"AT",
    "sg:address":"Steigenteschg 22",
    "sg:city":"Wien",
    "sg:orig_category":"Juweliere, Gold- U Silberschmiede",
    "sg:phone":"+43 4312 045810",
    "sg:postcode":"1220",
    "sg:province":"Wien",
    "wof:name":"Burker Gabriele",
    "wof:placetype":"venue"
},
  "geometry": {"coordinates":[16.4402561188,48.2451324463],"type":"Point"}
}