{
  "type": "Feature",
  "properties": {
    "addr:full":"Kerpelystr 157 Leoben Steiermark 8700",
    "addr:housenumber":"157",
    "addr:postcode":"8700",
    "iso:country":"AT",
    "sg:address":"Kerpelystr 157",
    "sg:city":"Leoben",
    "sg:orig_category":"Lebensmittel / Einzelhandel",
    "sg:phone":"+43 3842 211150",
    "sg:postcode":"8700",
    "sg:province":"Steiermark",
    "wof:name":"Hornig J GmbH",
    "wof:placetype":"venue"
},
  "geometry": {"coordinates":[15.0657100677,47.3776245117],"type":"Point"}
}