{
  "type": "Feature",
  "properties": {
    "addr:full":"Sparkassenpl 4 Graz Steiermark 8010",
    "addr:housenumber":"4",
    "addr:postcode":"8010",
    "addr:street":"Sparkassenpl",
    "iso:country":"AT",
    "sg:address":"Sparkassenpl 4",
    "sg:city":"Graz",
    "sg:orig_category":"Banken U Sparkassen",
    "sg:phone":"+43 4331 680330",
    "sg:postcode":"8010",
    "sg:province":"Steiermark",
    "wof:name":"Steierm\u00e4rkische Bank u Sparkassen AG",
    "wof:placetype":"venue"
},
  "geometry": {"coordinates":[15.4373569489,47.0694923401],"type":"Point"}
}