{
  "type": "Feature",
  "properties": {
    "addr:full":"Gro\u00dfmengersdorf 17 Sierning Ober\u00f6sterreich 4522",
    "addr:housenumber":"17",
    "addr:postcode":"4522",
    "addr:street":"Grossmengersdorf",
    "iso:country":"AT",
    "sg:address":"Gro\u00dfmengersdorf 17",
    "sg:city":"Sierning",
    "sg:orig_category":"Autoreparatur",
    "sg:phone":"+43 7258 27070",
    "sg:postcode":"4522",
    "sg:province":"Ober\u00f6sterreich",
    "wof:name":"Bachmayr Karl",
    "wof:placetype":"venue"
},
  "geometry": {"coordinates":[14.2583627701,48.0514144897],"type":"Point"}
}