{
  "type": "Feature",
  "properties": {
    "addr:full":"Karl-Morre-Str 15 Graz Steiermark 8020",
    "addr:housenumber":"15",
    "addr:postcode":"8020",
    "addr:street":"Karl-Morre-Str",
    "iso:country":"AT",
    "sg:address":"Karl-Morre-Str 15",
    "sg:city":"Graz",
    "sg:classifiers":[
        {
            "category":"Personal",
            "subcategory":"Sauna",
            "type":"Services"
        }
    ],
    "sg:phone":"+43 4331 6585601",
    "sg:postcode":"8020",
    "sg:province":"Steiermark",
    "sg:tags":[
        "u",
        "dampfbad"
    ],
    "wof:name":"Sauna Insel",
    "wof:placetype":"venue"
},
  "geometry": {"coordinates":[15.4023141861,47.0711097717],"type":"Point"}
}