{
  "type": "Feature",
  "properties": {
    "iso:country":"AT",
    "sg:address":"Ischlerbahnstr 23",
    "sg:city":"Eugendorf",
    "sg:orig_category":"Steuerberatung",
    "sg:phone":"+43 4362 257508",
    "sg:postcode":"5301",
    "sg:province":"Salzburg",
    "wof:name":"Hauser Josef Mag",
    "wof:placetype":"venue"
},
  "geometry": {"coordinates":[13.1278133392,47.8623313904],"type":"Point"}
}