{
  "type": "Feature",
  "properties": {
    "addr:full":"Platz 292 Mellau Vorarlberg 6881",
    "addr:housenumber":"292",
    "addr:postcode":"6881",
    "addr:street":"Platz",
    "iso:country":"AT",
    "sg:address":"Platz 292",
    "sg:city":"Mellau",
    "sg:orig_category":"Rettungsdienste",
    "sg:phone":"+43 5518 220420",
    "sg:postcode":"6881",
    "sg:province":"Vorarlberg",
    "wof:name":"Bergrettung",
    "wof:placetype":"venue"
},
  "geometry": {"coordinates":[9.881570816,47.3503112793],"type":"Point"}
}