{
  "type": "Feature",
  "properties": {
    "addr:full":"Kirchenberg 3 Steinerkirchen an der Traun Ober\u00f6sterreich 4652",
    "addr:housenumber":"3",
    "addr:postcode":"4652",
    "addr:street":"Kirchenberg",
    "iso:country":"AT",
    "sg:address":"Kirchenberg 3",
    "sg:city":"Steinerkirchen an der Traun",
    "sg:orig_category":"Autoreparatur",
    "sg:phone":"+43 7241 5434",
    "sg:postcode":"4652",
    "sg:province":"Ober\u00f6sterreich",
    "wof:name":"Krumphuber GesmbH",
    "wof:placetype":"venue"
},
  "geometry": {"coordinates":[13.9578418732,48.0891494751],"type":"Point"}
}