{
  "type": "Feature",
  "properties": {
    "addr:full":"Hauptpl 9 Treibach-Althofen K\u00e4rnten 9330",
    "addr:housenumber":"9",
    "addr:postcode":"9330",
    "addr:street":"Hauptpl;Kaernten",
    "iso:country":"AT",
    "sg:address":"Hauptpl 9",
    "sg:city":"Treibach-Althofen",
    "sg:orig_category":"Friseure U Frisiersalons",
    "sg:phone":"+43 4262 4626",
    "sg:postcode":"9330",
    "sg:province":"K\u00e4rnten",
    "wof:name":"Friseur DIE HAARSCHNEIDEREI",
    "wof:placetype":"venue"
},
  "geometry": {"coordinates":[14.4701509476,46.8701782227],"type":"Point"}
}