{
  "type": "Feature",
  "properties": {
    "iso:country":"AT",
    "sg:address":"Meidlinger Hauptstr 7-9",
    "sg:city":"Wien",
    "sg:orig_category":"Tabaktrafiken",
    "sg:phone":"+43 1 8122884",
    "sg:postcode":"1120",
    "sg:province":"Wien",
    "wof:name":"Sch\u00f6n Doris",
    "wof:placetype":"venue"
},
  "geometry": {"coordinates":[16.3299598694,48.1824111938],"type":"Point"}
}