{
  "type": "Feature",
  "properties": {
    "addr:full":"Hausruckstr 12 Ampflwang im Hausruckwald Ober\u00f6sterreich 4843",
    "addr:housenumber":"12",
    "addr:postcode":"4843",
    "addr:street":"Hausruckstr",
    "iso:country":"AT",
    "sg:address":"Hausruckstr 12",
    "sg:city":"Ampflwang im Hausruckwald",
    "sg:orig_category":"Gemeinden",
    "sg:phone":"+43 4376 7540100",
    "sg:postcode":"4843",
    "sg:province":"Ober\u00f6sterreich",
    "wof:name":"Marktgemeindeamt Ampflwang im Hausruckwald",
    "wof:placetype":"venue"
},
  "geometry": {"coordinates":[13.5662727356,48.0933799744],"type":"Point"}
}