{
  "type": "Feature",
  "properties": {
    "iso:country":"AT",
    "sg:address":"Hernalser Hauptstr 54",
    "sg:city":"Wien",
    "sg:orig_category":"Installationsunternehmen",
    "sg:phone":"+43 1 4056482",
    "sg:postcode":"1170",
    "sg:province":"Wien",
    "sg:website":"gas-wasser-heizung.at",
    "wof:name":"Simscha Karl",
    "wof:placetype":"venue"
},
  "geometry": {"coordinates":[16.335313797,48.2174453735],"type":"Point"}
}