{
  "type": "Feature",
  "properties": {
    "iso:country":"AT",
    "sg:address":"Hochkuchl 21",
    "sg:city":"Lohnsburg am Kobernau\u00dferwald",
    "sg:orig_category":"Elektroinstallationsunternehmen",
    "sg:phone":"+43 4377 542818",
    "sg:postcode":"4923",
    "sg:province":"Ober\u00f6sterreich",
    "wof:name":"Haslinger Josef",
    "wof:placetype":"venue"
},
  "geometry": {"coordinates":[13.3834466934,48.1379165649],"type":"Point"}
}