{
  "type": "Feature",
  "properties": {
    "iso:country":"AT",
    "sg:address":"Hauptstr 11",
    "sg:city":"Radenthein",
    "sg:classifiers":[
        {
            "category":"Retail",
            "subcategory":"Event Space",
            "type":"Services"
        }
    ],
    "sg:phone":"+43 4246 2090",
    "sg:postcode":"9545",
    "sg:province":"K\u00e4rnten",
    "sg:tags":[
        "hand-",
        "u",
        "fu\u00c3\u0178pflege"
    ],
    "wof:name":"Meixner Reingard Sieghilde",
    "wof:placetype":"venue"
},
  "geometry": {"coordinates":[13.7056455612,46.8016586304],"type":"Point"}
}