{
  "type": "Feature",
  "properties": {
    "addr:full":"Heuberggst\u00e4ttenstr 1 Wien Wien 1100",
    "addr:housenumber":"1",
    "addr:postcode":"1100",
    "addr:street":"Heuberggstaettenstr",
    "iso:country":"AT",
    "sg:address":"Heuberggst\u00e4ttenstr 1",
    "sg:city":"Wien",
    "sg:orig_category":"Sportanlagen",
    "sg:phone":"+43 1 6150356",
    "sg:postcode":"1100",
    "sg:province":"Wien",
    "wof:name":"Sportanlage d Gemeinde Wien - Franz H\u00f6lbl Sportanlage",
    "wof:placetype":"venue"
},
  "geometry": {"coordinates":[16.3679981232,48.1591720581],"type":"Point"}
}