{
  "type": "Feature",
  "properties": {
    "addr:full":"Nr 26 Neudau Steiermark 8292",
    "addr:postcode":"8292",
    "addr:street":"Nr",
    "iso:country":"AT",
    "sg:address":"Nr 26",
    "sg:city":"Neudau",
    "sg:orig_category":"Bekleidung / Einzelhandel",
    "sg:phone":"+43 3383 25397",
    "sg:postcode":"8292",
    "sg:province":"Steiermark",
    "wof:name":"Strobl Anneliese - Landhausmode",
    "wof:placetype":"venue"
},
  "geometry": {"coordinates":[16.1003761292,47.1778526306],"type":"Point"}
}