{
  "type": "Feature",
  "properties": {
    "iso:country":"AT",
    "sg:address":"Nr 7",
    "sg:city":"Gurk",
    "sg:orig_category":"Transportunternehmen",
    "sg:phone":"+43 4266 8271",
    "sg:postcode":"9342",
    "sg:province":"K\u00e4rnten",
    "wof:name":"Feichtinger Max",
    "wof:placetype":"venue"
},
  "geometry": {"coordinates":[12.0683698654,49.400844574],"type":"Point"}
}