{
  "type": "Feature",
  "properties": {
    "addr:full":"Neubaug\u00fcrtel 4 Wien Wien 1070",
    "addr:housenumber":"4",
    "addr:postcode":"1070",
    "addr:street":"Neubauguertel",
    "iso:country":"AT",
    "sg:address":"Neubaug\u00fcrtel 4",
    "sg:city":"Wien",
    "sg:classifiers":[
        {
            "category":"Travel",
            "subcategory":"Hotels & Motels",
            "type":"Entertainment"
        }
    ],
    "sg:phone":"+43 1 52332670",
    "sg:postcode":"1070",
    "sg:province":"Wien",
    "wof:name":"Hotel F\u00fcrstenhof Inh Julius Formanek",
    "wof:placetype":"venue"
},
  "geometry": {"coordinates":[16.3383293152,48.2016792297],"type":"Point"}
}