{
  "type": "Feature",
  "properties": {
    "addr:full":"Pfongauer Strasse 76  Neumarkt am Wallersee Salzburg 5202",
    "addr:housenumber":"76",
    "addr:postcode":"5202",
    "addr:street":"Pfongauer Strasse;Salzburg",
    "iso:country":"AT",
    "sg:address":"Pfongauer Strasse 76 ",
    "sg:city":"Neumarkt am Wallersee",
    "sg:classifiers":[
        {
            "category":"Retail",
            "subcategory":"Driving School",
            "type":"Services"
        }
    ],
    "sg:phone":"+43 6216 40330",
    "sg:postcode":"5202",
    "sg:province":"Salzburg",
    "sg:tags":[
        "wood",
        "logging"
    ],
    "sg:website":"www.henle.at",
    "wof:name":"Kurt Henle Ges.m.b.H.",
    "wof:placetype":"venue"
},
  "geometry": {"coordinates":[13.2476501465,47.9530563354],"type":"Point"}
}