{
  "type": "Feature",
  "properties": {
    "addr:full":"Hetzendorfer Str 163 Wien Wien 1120",
    "addr:housenumber":"163",
    "addr:postcode":"1120",
    "addr:street":"Str",
    "iso:country":"AT",
    "sg:address":"Hetzendorfer Str 163",
    "sg:city":"Wien",
    "sg:orig_category":"Installationsunternehmen",
    "sg:phone":"+43 4318 029762",
    "sg:postcode":"1120",
    "sg:province":"Wien",
    "wof:name":"Steiner Edmund Karl jun",
    "wof:placetype":"venue"
},
  "geometry": {"coordinates":[16.2969799042,48.1703720093],"type":"Point"}
}