{
  "type": "Feature",
  "properties": {
    "addr:full":"Lerchenfelder Str 73 Wien Wien 1070",
    "addr:housenumber":"73",
    "addr:postcode":"1070",
    "addr:street":"Lerchenfelder Str",
    "iso:country":"AT",
    "sg:address":"Lerchenfelder Str 73",
    "sg:city":"Wien",
    "sg:classifiers":[
        {
            "category":"Professional",
            "subcategory":"Computer Services",
            "type":"Services"
        }
    ],
    "sg:phone":"+43 1 5223466",
    "sg:postcode":"1070",
    "sg:province":"Wien",
    "sg:tags":[
        "software"
    ],
    "wof:name":"prevero Handels GmbH",
    "wof:placetype":"venue"
},
  "geometry": {"coordinates":[16.3454742432,48.207069397],"type":"Point"}
}