{
  "type": "Feature",
  "properties": {
    "addr:full":"Graf Maximilian-Str 16 Hohenems Vorarlberg 6845",
    "addr:housenumber":"16",
    "addr:postcode":"6845",
    "iso:country":"AT",
    "sg:address":"Graf Maximilian-Str 16",
    "sg:city":"Hohenems",
    "sg:orig_category":"Banken U Sparkassen",
    "sg:phone":"+43 5 050531260",
    "sg:postcode":"6845",
    "sg:province":"Vorarlberg",
    "wof:name":"Bank Austria Creditanstalt AG",
    "wof:placetype":"venue"
},
  "geometry": {"coordinates":[9.6854753494,47.3642501831],"type":"Point"}
}