{
  "type": "Feature",
  "properties": {
    "addr:full":"Hartberger Str 54 Gleisdorf Steiermark 8200",
    "addr:housenumber":"54",
    "addr:postcode":"8200",
    "addr:street":"Str",
    "iso:country":"AT",
    "sg:address":"Hartberger Str 54",
    "sg:city":"Gleisdorf",
    "sg:orig_category":"Autohandel",
    "sg:phone":"+43 4331 122635",
    "sg:postcode":"8200",
    "sg:province":"Steiermark",
    "wof:name":"Autohaus Jagersberger GmbH",
    "wof:placetype":"venue"
},
  "geometry": {"coordinates":[15.7099456787,47.1139640808],"type":"Point"}
}