{
  "type": "Feature",
  "properties": {
    "addr:full":"Randlstrasse 7 Pasching Ober\u00f6sterreich 4061",
    "addr:housenumber":"7",
    "addr:postcode":"4061",
    "addr:street":"Randlstrasse;Oberoesterreich",
    "iso:country":"AT",
    "sg:address":"Randlstrasse 7",
    "sg:city":"Pasching",
    "sg:classifiers":[
        {
            "category":"Banks & Credit Unions",
            "subcategory":"Bureau De Change",
            "type":"Services"
        }
    ],
    "sg:phone":"+43 7229 69169",
    "sg:postcode":"4061",
    "sg:province":"Ober\u00f6sterreich",
    "sg:tags":[
        "blind",
        "screw",
        "nut",
        "rivet"
    ],
    "sg:website":"boellhoff.de",
    "wof:name":"B\u00f6llhoff GmbH - Verbindungs- und Montagetechnik",
    "wof:placetype":"venue"
},
  "geometry": {"coordinates":[14.2319164276,48.2438659668],"type":"Point"}
}