{
  "type": "Feature",
  "properties": {
    "addr:full":"Untersbergstrasse 24 Anif Salzburg 5081",
    "addr:housenumber":"24",
    "addr:postcode":"5081",
    "addr:street":"Untersbergstrasse;Salzburg",
    "iso:country":"AT",
    "sg:address":"Untersbergstrasse 24",
    "sg:city":"Anif",
    "sg:classifiers":[
        {
            "category":"Professional",
            "subcategory":"Accounting & Tax Preparation",
            "type":"Services"
        }
    ],
    "sg:phone":"+43 6246 762860",
    "sg:postcode":"5081",
    "sg:province":"Salzburg",
    "sg:tags":[
        "data",
        "acquisition"
    ],
    "sg:website":"promomasters.at",
    "wof:name":"PromoMasters Internet Service Michael Kohlf\u00fcrst",
    "wof:placetype":"venue"
},
  "geometry": {"coordinates":[13.0580835342,47.7239379883],"type":"Point"}
}