{
  "type": "Feature",
  "properties": {
    "iso:country":"AT",
    "sg:address":"Wiener Str 69",
    "sg:city":"Linz",
    "sg:orig_category":"Plakatierungsunternehmen",
    "sg:phone":"+43 732 667766",
    "sg:postcode":"4020",
    "sg:province":"Ober\u00f6sterreich",
    "wof:name":"USP WerbegesmbH",
    "wof:placetype":"venue"
},
  "geometry": {"coordinates":[14.3001728058,48.2877464294],"type":"Point"}
}