{
  "type": "Feature",
  "properties": {
    "addr:full":"Wagrainer Str 13 St. Johann im Pongau Salzburg 5600",
    "addr:housenumber":"13",
    "addr:postcode":"5600",
    "addr:street":"Str;Salzburg",
    "iso:country":"AT",
    "sg:address":"Wagrainer Str 13",
    "sg:city":"St. Johann im Pongau",
    "sg:orig_category":"Polytechnische Schulen",
    "sg:phone":"+43 6412 4215",
    "sg:postcode":"5600",
    "sg:province":"Salzburg",
    "wof:name":"Polytechnische Schule",
    "wof:placetype":"venue"
},
  "geometry": {"coordinates":[13.2052707672,47.3477363586],"type":"Point"}
}