{
  "type": "Feature",
  "properties": {
    "iso:country":"AT",
    "sg:address":"Schwenderg 21/1",
    "sg:city":"Wien",
    "sg:classifiers":[
        {
            "category":"Restaurant",
            "type":"Food & Drink"
        }
    ],
    "sg:phone":"+43 1 8939892",
    "sg:postcode":"1150",
    "sg:province":"Wien",
    "wof:name":"Ziegler Josef Mag",
    "wof:placetype":"venue"
},
  "geometry": {"coordinates":[16.3283538818,48.1909828186],"type":"Point"}
}