{
  "type": "Feature",
  "properties": {
    "addr:full":"Franz-Josef-Str 10 Gleisdorf Steiermark 8200",
    "addr:housenumber":"10",
    "addr:postcode":"8200",
    "addr:street":"Franz-Josef-Str",
    "iso:country":"AT",
    "sg:address":"Franz-Josef-Str 10",
    "sg:city":"Gleisdorf",
    "sg:orig_category":"Bars-Cafes",
    "sg:phone":"+43 4366 44622300",
    "sg:postcode":"8200",
    "sg:province":"Steiermark",
    "wof:name":"Twister - Katzbeck & Sailer OEG",
    "wof:placetype":"venue"
},
  "geometry": {"coordinates":[15.7120323181,47.1031799316],"type":"Point"}
}