{
  "type": "Feature",
  "properties": {
    "addr:full":"Josef-Obermaier-Weg 14 Salzburg Salzburg 5020",
    "addr:housenumber":"14",
    "addr:postcode":"5020",
    "addr:street":"Josef-Obermaier-Weg;Salzburg",
    "iso:country":"AT",
    "sg:address":"Josef-Obermaier-Weg 14",
    "sg:city":"Salzburg",
    "sg:orig_category":"Dachdeckereien",
    "sg:phone":"+43 4366 2433296",
    "sg:postcode":"5020",
    "sg:province":"Salzburg",
    "wof:name":"W\u00e4hner Horst",
    "wof:placetype":"venue"
},
  "geometry": {"coordinates":[13.0162506104,47.8184318542],"type":"Point"}
}