{
  "type": "Feature",
  "properties": {
    "addr:full":"Albern 57 Mauthausen Ober\u00f6sterreich 4310",
    "addr:housenumber":"57",
    "addr:postcode":"4310",
    "addr:street":"Albern",
    "iso:country":"AT",
    "sg:address":"Albern 57",
    "sg:city":"Mauthausen",
    "sg:orig_category":"Parkettbodenverlegung",
    "sg:phone":"+43 7238 2862",
    "sg:postcode":"4310",
    "sg:province":"Ober\u00f6sterreich",
    "wof:name":"Friedl Stefan",
    "wof:placetype":"venue"
},
  "geometry": {"coordinates":[14.5436296463,48.2373008728],"type":"Point"}
}