{
  "type": "Feature",
  "properties": {
    "addr:full":"Marktpl 12 Neufelden Ober\u00f6sterreich 4120",
    "addr:housenumber":"12",
    "addr:postcode":"4120",
    "addr:street":"Marktpl",
    "iso:country":"AT",
    "sg:address":"Marktpl 12",
    "sg:city":"Neufelden",
    "sg:orig_category":"Volksschulen",
    "sg:phone":"+43 7282 6397",
    "sg:postcode":"4120",
    "sg:province":"Ober\u00f6sterreich",
    "wof:name":"Volksschule",
    "wof:placetype":"venue"
},
  "geometry": {"coordinates":[14.0005102158,48.4833946228],"type":"Point"}
}