{
  "type": "Feature",
  "properties": {
    "addr:full":"Untere Hauptstr 2 Neusiedl am See Burgenland 7100",
    "addr:housenumber":"2",
    "addr:postcode":"7100",
    "addr:street":"Untere Hauptstr",
    "iso:country":"AT",
    "sg:address":"Untere Hauptstr 2",
    "sg:city":"Neusiedl am See",
    "sg:orig_category":"Banken U Sparkassen",
    "sg:phone":"+43 4321 672537",
    "sg:postcode":"7100",
    "sg:province":"Burgenland",
    "wof:name":"Bankomat d Volksbank Ost regGenmbH",
    "wof:placetype":"venue"
},
  "geometry": {"coordinates":[16.843711853,47.9482078552],"type":"Point"}
}