{
  "type": "Feature",
  "properties": {
    "addr:full":"Flattach 112 Flattach K\u00e4rnten 9831",
    "addr:housenumber":"112",
    "addr:postcode":"9831",
    "addr:street":"Flattach;Kaernten",
    "iso:country":"AT",
    "sg:address":"Flattach 112",
    "sg:city":"Flattach",
    "sg:classifiers":[
        {
            "category":"Banks & Credit Unions",
            "subcategory":"Investment Brokerage",
            "type":"Services"
        }
    ],
    "sg:phone":"+43 4785 318",
    "sg:postcode":"9831",
    "sg:province":"K\u00e4rnten",
    "sg:tags":[
        "absorption",
        "refrigerator"
    ],
    "wof:name":"Helmut Brandst\u00e4tter",
    "wof:placetype":"venue"
},
  "geometry": {"coordinates":[13.1212444305,46.9395179749],"type":"Point"}
}