{
  "type": "Feature",
  "properties": {
    "iso:country":"AT",
    "sg:address":"Lange G 54",
    "sg:city":"Stadtschlaining",
    "sg:orig_category":"Non-Classified Establishments",
    "sg:phone":"+43 3355 2212",
    "sg:postcode":"7461",
    "sg:province":"Burgenland",
    "wof:name":"Evangelisches Pfarramt AB",
    "wof:placetype":"venue"
},
  "geometry": {"coordinates":[16.2768001556,47.3234901428],"type":"Point"}
}