{
  "type": "Feature",
  "properties": {
    "iso:country":"AT",
    "sg:address":"Wiener Str 246",
    "sg:city":"G\u00f6llersdorf",
    "sg:classifiers":[
        {
            "category":"Home & Garden",
            "subcategory":"Garden Supply",
            "type":"Retail Goods"
        }
    ],
    "sg:phone":"+43 2954 22170",
    "sg:postcode":"2013",
    "sg:province":"Nieder\u00f6sterreich",
    "sg:tags":[
        "schotter",
        "sand",
        "u"
    ],
    "wof:name":"Beton- u. Schotterwerke Aichinger Regina GmbH",
    "wof:placetype":"venue"
},
  "geometry": {"coordinates":[16.1194400787,48.4935760498],"type":"Point"}
}