{
  "type": "Feature",
  "properties": {
    "addr:full":"Obere Wiener Str 3 Rohrendorf Nieder\u00f6sterreich 3495",
    "addr:postcode":"3495",
    "addr:street":"Obere;Niederoesterreich",
    "iso:country":"AT",
    "sg:address":"Obere Wiener Str 3",
    "sg:city":"Rohrendorf",
    "sg:orig_category":"Tankstellen",
    "sg:phone":"+43 2732 83895",
    "sg:postcode":"3495",
    "sg:province":"Nieder\u00f6sterreich",
    "wof:name":"AVANTI TankstellenbetriebsgesmbH",
    "wof:placetype":"venue"
},
  "geometry": {"coordinates":[15.6546144485,48.423248291],"type":"Point"}
}