{
  "type": "Feature",
  "properties": {
    "addr:full":"Gm\u00fcnder Str 30 Schrems Nieder\u00f6sterreich 3943",
    "addr:postcode":"3943",
    "addr:street":"Str;Schrems",
    "iso:country":"AT",
    "sg:address":"Gm\u00fcnder Str 30",
    "sg:city":"Schrems",
    "sg:orig_category":"Lebensmittel / Einzelhandel",
    "sg:phone":"+43 2853 72869",
    "sg:postcode":"3943",
    "sg:province":"Nieder\u00f6sterreich",
    "wof:name":"SPAR \u00f6sterreichische Warenhandels-AG",
    "wof:placetype":"venue"
},
  "geometry": {"coordinates":[15.0714254379,48.7929534912],"type":"Point"}
}