{
  "type": "Feature",
  "properties": {
    "addr:full":"Lahnbachg 21a Schwaz Tirol 6130",
    "addr:housenumber":"21a",
    "addr:postcode":"6130",
    "addr:street":"Lahnbachg;Tirol",
    "iso:country":"AT",
    "sg:address":"Lahnbachg 21a",
    "sg:city":"Schwaz",
    "sg:orig_category":"Biologische Produkte",
    "sg:phone":"+43 4352 4261108",
    "sg:postcode":"6130",
    "sg:province":"Tirol",
    "wof:name":"Kugler Helga Aloe-Vera Beratung u Vertrieb",
    "wof:placetype":"venue"
},
  "geometry": {"coordinates":[11.7142715454,47.347026825],"type":"Point"}
}