{
  "type": "Feature",
  "properties": {
    "addr:full":"Industriezentrum N\u00f6 S\u00fcd Stra\u00dfe 7 Obj 58B Wiener Neudorf Nieder\u00f6sterreich 2351",
    "addr:housenumber":"7 obj 58b",
    "addr:postcode":"2351",
    "addr:street":"Industriezentrum Noe Sued Strasse",
    "iso:country":"AT",
    "sg:address":"Industriezentrum N\u00f6 S\u00fcd Stra\u00dfe 7 Obj 58B",
    "sg:city":"Wiener Neudorf",
    "sg:orig_category":"Waren Aller Art",
    "sg:phone":"+43 4322 36677766",
    "sg:postcode":"2351",
    "sg:province":"Nieder\u00f6sterreich",
    "wof:name":"FUTURA WarenhandelsgesmbH",
    "wof:placetype":"venue"
},
  "geometry": {"coordinates":[16.3183326721,48.0863113403],"type":"Point"}
}