{
  "type": "Feature",
  "properties": {
    "iso:country":"AT",
    "sg:address":"Wiener Str 15",
    "sg:city":"Linz",
    "sg:orig_category":"Friseure U Frisiersalons",
    "sg:phone":"+43 4373 2656396",
    "sg:postcode":"4020",
    "sg:province":"Ober\u00f6sterreich",
    "sg:website":"friseur-haslinger.com",
    "wof:name":"Haslinger Haarinnovationen",
    "wof:placetype":"venue"
},
  "geometry": {"coordinates":[14.2961626053,48.2919235229],"type":"Point"}
}