{
  "type": "Feature",
  "properties": {
    "addr:full":"Bergg 6 M\u00fcllendorf Burgenland 7052",
    "addr:housenumber":"6",
    "addr:postcode":"7052",
    "addr:street":"Bergg",
    "iso:country":"AT",
    "sg:address":"Bergg 6",
    "sg:city":"M\u00fcllendorf",
    "sg:classifiers":[
        {
            "category":"Professional",
            "subcategory":"Computer Services",
            "type":"Services"
        }
    ],
    "sg:phone":"+43 2682 75660",
    "sg:postcode":"7052",
    "sg:province":"Burgenland",
    "sg:tags":[
        "software"
    ],
    "wof:name":"Jandl-EDV",
    "wof:placetype":"venue"
},
  "geometry": {"coordinates":[16.4633102417,47.8451919556],"type":"Point"}
}