{
  "type": "Feature",
  "properties": {
    "addr:full":"Zellerndorf 104a Zellerndorf Nieder\u00f6sterreich 2051",
    "addr:housenumber":"104a",
    "addr:postcode":"2051",
    "addr:street":"Zellerndorf",
    "iso:country":"AT",
    "sg:address":"Zellerndorf 104a",
    "sg:city":"Zellerndorf",
    "sg:classifiers":[
        {
            "category":"Farming",
            "subcategory":"Berry Farm",
            "type":"Manufacturing & Wholesale Goods"
        }
    ],
    "sg:phone":"+43 2945 27702",
    "sg:postcode":"2051",
    "sg:province":"Nieder\u00f6sterreich",
    "sg:tags":[
        "austrian",
        "wine"
    ],
    "wof:name":"Weinbau Familie Redl",
    "wof:placetype":"venue"
},
  "geometry": {"coordinates":[15.9596509933,48.6967658997],"type":"Point"}
}