{
  "type": "Feature",
  "properties": {
    "iso:country":"AT",
    "sg:address":"Tiroler Str",
    "sg:city":"Villach",
    "sg:orig_category":"Tankstellen",
    "sg:phone":"+43 4242 588000",
    "sg:postcode":"9500",
    "sg:province":"K\u00e4rnten",
    "wof:name":"BP Austria Marketing GmbH",
    "wof:placetype":"venue"
},
  "geometry": {"coordinates":[13.8242797852,46.616394043],"type":"Point"}
}