{
  "type": "Feature",
  "properties": {
    "addr:full":"Reitschulg 23 Graz Steiermark 8010",
    "addr:housenumber":"23",
    "addr:postcode":"8010",
    "addr:street":"Reitschulg",
    "iso:country":"AT",
    "sg:address":"Reitschulg 23",
    "sg:city":"Graz",
    "sg:orig_category":"Fotoapparate U -Artikel / Reparatur",
    "sg:phone":"+43 4331 6829405",
    "sg:postcode":"8010",
    "sg:province":"Steiermark",
    "sg:website":"fotoriedl.at",
    "wof:name":"Foto Riedl",
    "wof:placetype":"venue"
},
  "geometry": {"coordinates":[15.4457082748,47.0669708252],"type":"Point"}
}