{
  "type": "Feature",
  "properties": {
    "addr:full":"Steinamangerer Str 4/1/3 Oberwart Burgenland 7400",
    "addr:housenumber":"4 / 1 / 3",
    "addr:postcode":"7400",
    "addr:street":"Str",
    "iso:country":"AT",
    "sg:address":"Steinamangerer Str 4/1/3",
    "sg:city":"Oberwart",
    "sg:orig_category":"Ingenieurkonsulenten / Zivilingenieure",
    "sg:phone":"+43 3352 335370",
    "sg:postcode":"7400",
    "sg:province":"Burgenland",
    "wof:name":"H\u00f6henberger Horst Prof Dipl-Ing",
    "wof:placetype":"venue"
},
  "geometry": {"coordinates":[16.2131557465,47.2876167297],"type":"Point"}
}