{
  "type": "Feature",
  "properties": {
    "iso:country":"AT",
    "sg:address":"Florianipl 12",
    "sg:city":"Gleisdorf",
    "sg:orig_category":"Steuerberatung",
    "sg:phone":"+43 4331 1225810",
    "sg:postcode":"8200",
    "sg:province":"Steiermark",
    "sg:website":"pilz-rath.at",
    "wof:name":"PILZ & RATH Wirtschaftstreuhand KG",
    "wof:placetype":"venue"
},
  "geometry": {"coordinates":[15.7117528915,47.1049613953],"type":"Point"}
}