{
  "type": "Feature",
  "properties": {
    "addr:full":"Albert Schweitzer Strasse 6 Marchtrenk Ober\u00f6sterreich 4614",
    "addr:housenumber":"6",
    "addr:postcode":"4614",
    "addr:street":"Albert Schweitzer Strasse",
    "iso:country":"AT",
    "sg:address":"Albert Schweitzer Strasse 6",
    "sg:city":"Marchtrenk",
    "sg:orig_category":"Asynchronous Motors, Controlled",
    "sg:phone":"+43 7243 50996",
    "sg:postcode":"4614",
    "sg:province":"Ober\u00f6sterreich",
    "sg:website":"eibl-hydraulik.at",
    "wof:name":"Eibl",
    "wof:placetype":"venue"
},
  "geometry": {"coordinates":[14.1468391418,48.1985092163],"type":"Point"}
}