{
  "type": "Feature",
  "properties": {
    "addr:full":"Erdbergstr. 57  Wien Wien 1030",
    "addr:housenumber":"57",
    "addr:postcode":"1030",
    "addr:street":"Erdbergstr.",
    "iso:country":"AT",
    "sg:address":"Erdbergstr. 57 ",
    "sg:city":"Wien",
    "sg:classifiers":[
        {
            "category":"Home & Garden",
            "subcategory":"Home Furnishings",
            "type":"Retail Goods"
        }
    ],
    "sg:phone":"+43 4317 127870",
    "sg:postcode":"1030",
    "sg:province":"Wien",
    "sg:tags":[
        "household"
    ],
    "wof:name":"LHD K\u00dcCHENDESIGN GESMBH",
    "wof:placetype":"venue"
},
  "geometry": {"coordinates":[16.399646759,48.199180603],"type":"Point"}
}