{
  "type": "Feature",
  "properties": {
    "addr:full":"Hauptpl 19 Gaweinstal Nieder\u00f6sterreich 2191",
    "addr:housenumber":"19",
    "addr:postcode":"2191",
    "addr:street":"Hauptpl",
    "iso:country":"AT",
    "sg:address":"Hauptpl 19",
    "sg:city":"Gaweinstal",
    "sg:orig_category":"Glasereien",
    "sg:phone":"+43 2574 2258",
    "sg:postcode":"2191",
    "sg:province":"Nieder\u00f6sterreich",
    "wof:name":"Kaufmann Wilhelm",
    "wof:placetype":"venue"
},
  "geometry": {"coordinates":[16.5905361176,48.4775505066],"type":"Point"}
}