{
  "type": "Feature",
  "properties": {
    "addr:full":"Vivenotgasse 38 Wien Wien 1120",
    "addr:housenumber":"38",
    "addr:postcode":"1120",
    "addr:street":"Vivenotgasse",
    "iso:country":"AT",
    "sg:address":"Vivenotgasse 38",
    "sg:city":"Wien",
    "sg:classifiers":[
        {
            "category":"Retail",
            "subcategory":"Auto Repair",
            "type":"Services"
        }
    ],
    "sg:phone":"+43 1 8123474",
    "sg:postcode":"1120",
    "sg:province":"Wien",
    "sg:tags":[
        "window",
        "automatic"
    ],
    "wof:name":"Manfred Fassl",
    "wof:placetype":"venue"
},
  "geometry": {"coordinates":[16.3311519623,48.1778717041],"type":"Point"}
}