{
  "type": "Feature",
  "properties": {
    "addr:full":"Krottendorf 267 Krottendorf-Gaisfeld Steiermark 8564",
    "addr:housenumber":"267",
    "addr:postcode":"krottendorf-gaisfeld;8564",
    "addr:street":"Krottendorf",
    "iso:country":"AT",
    "sg:address":"Krottendorf 267",
    "sg:city":"Krottendorf-Gaisfeld",
    "sg:orig_category":"Fliesen U Platten",
    "sg:phone":"+43 3143 4489",
    "sg:postcode":"8564",
    "sg:province":"Steiermark",
    "wof:name":"Hold Franz",
    "wof:placetype":"venue"
},
  "geometry": {"coordinates":[15.1982555389,47.002872467],"type":"Point"}
}