{
  "type": "Feature",
  "properties": {
    "addr:full":"Ring 111 Hartberg Steiermark 8230",
    "addr:housenumber":"111",
    "addr:postcode":"8230",
    "addr:street":"Ring",
    "iso:country":"AT",
    "sg:address":"Ring 111",
    "sg:city":"Hartberg",
    "sg:orig_category":"Gartenarchitekten",
    "sg:phone":"+43 4333 3266164",
    "sg:postcode":"8230",
    "sg:province":"Steiermark",
    "wof:name":"bella bayer - das Gartenatelier",
    "wof:placetype":"venue"
},
  "geometry": {"coordinates":[15.9597806931,47.2916793823],"type":"Point"}
}