{
  "type": "Feature",
  "properties": {
    "addr:full":"Hauptpl 8 Friesach K\u00e4rnten 9360",
    "addr:housenumber":"8",
    "addr:postcode":"9360",
    "addr:street":"Hauptpl;Kaernten",
    "iso:country":"AT",
    "sg:address":"Hauptpl 8",
    "sg:city":"Friesach",
    "sg:orig_category":"Friseure U Frisiersalons",
    "sg:phone":"+43 4342 682517",
    "sg:postcode":"9360",
    "sg:province":"K\u00e4rnten",
    "wof:name":"Kabon Heimo",
    "wof:placetype":"venue"
},
  "geometry": {"coordinates":[14.4051933289,46.950176239],"type":"Point"}
}