{
  "type": "Feature",
  "properties": {
    "addr:full":"Franziskanerstr 2 Frauenkirchen Burgenland 7132",
    "addr:housenumber":"2",
    "addr:postcode":"7132",
    "addr:street":"Franziskanerstr",
    "iso:country":"AT",
    "sg:address":"Franziskanerstr 2",
    "sg:city":"Frauenkirchen",
    "sg:orig_category":"Geschenkartikel",
    "sg:phone":"+43 2172 3294",
    "sg:postcode":"7132",
    "sg:province":"Burgenland",
    "wof:name":"Hautzinger Erwin",
    "wof:placetype":"venue"
},
  "geometry": {"coordinates":[16.925989151,47.8357086182],"type":"Point"}
}