{
  "type": "Feature",
  "properties": {
    "addr:full":"Nr 23 Texing Nieder\u00f6sterreich 3242",
    "addr:postcode":"3242",
    "addr:street":"Nr;Texing",
    "iso:country":"AT",
    "sg:address":"Nr 23",
    "sg:city":"Texing",
    "sg:orig_category":"Autovermietung",
    "sg:phone":"+43 2755 7480",
    "sg:postcode":"3242",
    "sg:province":"Nieder\u00f6sterreich",
    "wof:name":"Stadler Reinhard",
    "wof:placetype":"venue"
},
  "geometry": {"coordinates":[15.3228321075,48.0478782654],"type":"Point"}
}