{
  "type": "Feature",
  "properties": {
    "addr:full":"Fleischmarkt 1a Wien Wien 1010",
    "addr:housenumber":"1a",
    "addr:postcode":"1010",
    "addr:street":"Fleischmarkt",
    "iso:country":"AT",
    "sg:address":"Fleischmarkt 1a",
    "sg:city":"Wien",
    "sg:classifiers":[
        {
            "category":"Travel",
            "subcategory":"Hotels & Motels",
            "type":"Entertainment"
        }
    ],
    "sg:phone":"+43 1 534600",
    "sg:postcode":"1010",
    "sg:province":"Wien",
    "wof:name":"Hotel Mercure Wien Zentrum - Pannonia HotelbetriebsgmbH",
    "wof:placetype":"venue"
},
  "geometry": {"coordinates":[16.3747196198,48.2113800049],"type":"Point"}
}