{
  "type": "Feature",
  "properties": {
    "iso:country":"AT",
    "sg:address":"Marktpl 18",
    "sg:city":"Heiligenkreuz am Waasen",
    "sg:orig_category":"Banken U Sparkassen",
    "sg:phone":"+43 4331 3420540",
    "sg:postcode":"8081",
    "sg:province":"Steiermark",
    "wof:name":"Bankomat d Steierm\u00e4rkische Bank u Sparkassen AG",
    "wof:placetype":"venue"
},
  "geometry": {"coordinates":[15.5848884583,46.9565734863],"type":"Point"}
}