{
  "type": "Feature",
  "properties": {
    "addr:full":"Grazer Strasse 30 Fohnsdorf Steiermark 8753",
    "addr:housenumber":"30",
    "addr:postcode":"8753",
    "addr:street":"Grazer Strasse",
    "iso:country":"AT",
    "sg:address":"Grazer Strasse 30",
    "sg:city":"Fohnsdorf",
    "sg:classifiers":[
        {
            "category":"Retail",
            "subcategory":"Event Space",
            "type":"Services"
        }
    ],
    "sg:phone":"+43 3573 2640",
    "sg:postcode":"8753",
    "sg:province":"Steiermark",
    "sg:tags":[
        "device",
        "descaling"
    ],
    "sg:website":"aquavital.cc",
    "wof:name":"Aquatec Produktions- und Vertriebs GmbH",
    "wof:placetype":"venue"
},
  "geometry": {"coordinates":[14.6815471649,47.207649231],"type":"Point"}
}