{
  "type": "Feature",
  "properties": {
    "addr:full":"Sieveringer Str 4-10 Wien Wien 1190",
    "addr:housenumber":"4-10",
    "addr:postcode":"1190",
    "addr:street":"Sieveringer Str",
    "iso:country":"AT",
    "sg:address":"Sieveringer Str 4-10",
    "sg:city":"Wien",
    "sg:orig_category":"Drogerien",
    "sg:phone":"+43 1 3201097",
    "sg:postcode":"1190",
    "sg:province":"Wien",
    "wof:name":"dm drogerie markt GmbH",
    "wof:placetype":"venue"
},
  "geometry": {"coordinates":[16.3408355713,48.2460594177],"type":"Point"}
}