{
  "type": "Feature",
  "properties": {
    "addr:full":"Lindhofstr 5 Salzburg Salzburg 5020",
    "addr:housenumber":"5",
    "addr:postcode":"5020",
    "addr:street":"Lindhofstr;Salzburg",
    "iso:country":"AT",
    "sg:address":"Lindhofstr 5",
    "sg:city":"Salzburg",
    "sg:orig_category":"Psychologen",
    "sg:phone":"+43 662 432498",
    "sg:postcode":"5020",
    "sg:province":"Salzburg",
    "wof:name":"Moser Kurt Dr",
    "wof:placetype":"venue"
},
  "geometry": {"coordinates":[13.0328168869,47.8054351807],"type":"Point"}
}