{
  "type": "Feature",
  "properties": {
    "iso:country":"AT",
    "sg:address":"Glemmtaler Landesstr 374",
    "sg:city":"Hinterglemm",
    "sg:orig_category":"Bars-Cafes",
    "sg:phone":"+43 4365 417932",
    "sg:postcode":"5754",
    "sg:province":"Salzburg",
    "wof:name":"Bla Bla - Beate Gensbichler",
    "wof:placetype":"venue"
},
  "geometry": {"coordinates":[12.5967702866,47.3807373047],"type":"Point"}
}