{
  "type": "Feature",
  "properties": {
    "addr:full":"Zieglerg 33 Wien Wien 1070",
    "addr:housenumber":"33",
    "addr:postcode":"1070",
    "addr:street":"Zieglerg",
    "iso:country":"AT",
    "sg:address":"Zieglerg 33",
    "sg:city":"Wien",
    "sg:orig_category":"Modellbahnen",
    "sg:phone":"+43 1 5262629",
    "sg:postcode":"1070",
    "sg:province":"Wien",
    "wof:name":"Ingrid's Second Hand",
    "wof:placetype":"venue"
},
  "geometry": {"coordinates":[16.344865799,48.2015266418],"type":"Point"}
}