{
  "type": "Feature",
  "properties": {
    "addr:full":"Hauptpl 9 Feldbach Steiermark 8330",
    "addr:housenumber":"9",
    "addr:postcode":"8330",
    "addr:street":"Hauptpl",
    "iso:country":"AT",
    "sg:address":"Hauptpl 9",
    "sg:city":"Feldbach",
    "sg:orig_category":"Tabaktrafiken",
    "sg:phone":"+43 3152 2284",
    "sg:postcode":"8330",
    "sg:province":"Steiermark",
    "wof:name":"Frank Herbert",
    "wof:placetype":"venue"
},
  "geometry": {"coordinates":[15.8889045715,46.9529342651],"type":"Point"}
}