{
  "type": "Feature",
  "properties": {
    "addr:full":"Auer-von-Welsbach-Gasse 14 Guntramsdorf Nieder\u00f6sterreich 2353",
    "addr:housenumber":"14",
    "addr:postcode":"2353",
    "addr:street":"Auer-Von-Welsbach-Gasse",
    "iso:country":"AT",
    "sg:address":"Auer-von-Welsbach-Gasse 14",
    "sg:city":"Guntramsdorf",
    "sg:classifiers":[
        {
            "category":"Banks & Credit Unions",
            "subcategory":"Atm",
            "type":"Services"
        }
    ],
    "sg:phone":"+43 2236 53313",
    "sg:postcode":"2353",
    "sg:province":"Nieder\u00f6sterreich",
    "sg:tags":[
        "mill",
        "agitator",
        "ball"
    ],
    "sg:website":"eks-schalk.at",
    "wof:name":"EKS Verfahrenstechnik f\u00fcr Industriemaschinen GmbH",
    "wof:placetype":"venue"
},
  "geometry": {"coordinates":[16.3222904205,48.055644989],"type":"Point"}
}