{
  "type": "Feature",
  "properties": {
    "addr:full":"Siget 47 Hornstein Burgenland 7053",
    "addr:housenumber":"47",
    "addr:postcode":"7053",
    "addr:street":"Siget",
    "iso:country":"AT",
    "sg:address":"Siget 47",
    "sg:city":"Hornstein",
    "sg:orig_category":"Tischlereien",
    "sg:phone":"+43 2689 22550",
    "sg:postcode":"7053",
    "sg:province":"Burgenland",
    "wof:name":"Gerbautz Ferdinand",
    "wof:placetype":"venue"
},
  "geometry": {"coordinates":[16.4419994354,47.8759002686],"type":"Point"}
}