{
  "type": "Feature",
  "properties": {
    "iso:country":"AT",
    "sg:address":"Andreas-Hofer-Str 606",
    "sg:city":"Seefeld in Tirol",
    "sg:orig_category":"Appartements / Ferienwohnungen",
    "sg:phone":"+43 5212 6060",
    "sg:postcode":"6100",
    "sg:province":"Tirol",
    "wof:name":"Appartement-Haus Birkenwald",
    "wof:placetype":"venue"
},
  "geometry": {"coordinates":[11.1889953613,47.3294143677],"type":"Point"}
}