{
  "type": "Feature",
  "properties": {
    "addr:full":"Grazer Strasse 26 Murau Steiermark 8850",
    "addr:housenumber":"26",
    "addr:postcode":"8850",
    "addr:street":"Grazer Strasse",
    "iso:country":"AT",
    "sg:address":"Grazer Strasse 26",
    "sg:city":"Murau",
    "sg:classifiers":[
        {
            "category":"Utilities",
            "subcategory":"Natural Gas",
            "type":"Services"
        }
    ],
    "sg:phone":"+43 3532 2992",
    "sg:postcode":"8850",
    "sg:province":"Steiermark",
    "sg:tags":[
        "flux",
        "magnetic",
        "therapy",
        "equipment"
    ],
    "sg:website":"members.aon.at/magnetfeldtherapie",
    "wof:name":"Willi Trippold",
    "wof:placetype":"venue"
},
  "geometry": {"coordinates":[14.1788816452,47.1111183167],"type":"Point"}
}