{
  "type": "Feature",
  "properties": {
    "iso:country":"AT",
    "sg:address":"Kirchg 22",
    "sg:city":"Kammern im Liesingtal",
    "sg:orig_category":"Friseure U Frisiersalons",
    "sg:phone":"+43 4338 4485640",
    "sg:postcode":"8773",
    "sg:province":"Steiermark",
    "wof:name":"Lerch Anna",
    "wof:placetype":"venue"
},
  "geometry": {"coordinates":[14.9019031525,47.3906669617],"type":"Point"}
}