{
  "type": "Feature",
  "properties": {
    "iso:country":"AT",
    "sg:address":"Ellenbogen 606",
    "sg:city":"Bezau",
    "sg:orig_category":"Musikgruppen",
    "sg:phone":"+43 664 1520896",
    "sg:postcode":"6870",
    "sg:province":"Vorarlberg",
    "wof:name":"Alpenstarkstrom",
    "wof:placetype":"venue"
},
  "geometry": {"coordinates":[9.8968400955,47.3801116943],"type":"Point"}
}