{
  "type": "Feature",
  "properties": {
    "iso:country":"AT",
    "sg:address":"Rathauspl 3",
    "sg:city":"Weitra",
    "sg:orig_category":"Trachtenbekleidung",
    "sg:phone":"+43 2856 3294",
    "sg:postcode":"3970",
    "sg:province":"Nieder\u00f6sterreich",
    "wof:name":"Elfi's Naturstube",
    "wof:placetype":"venue"
},
  "geometry": {"coordinates":[14.8938970566,48.7010917664],"type":"Point"}
}