{
  "type": "Feature",
  "properties": {
    "addr:full":"Wiener Strasse 435 Linz Ober\u00f6sterreich 4030",
    "addr:housenumber":"435",
    "addr:postcode":"4030",
    "addr:street":"Wiener Strasse",
    "iso:country":"AT",
    "sg:address":"Wiener Strasse 435",
    "sg:city":"Linz",
    "sg:classifiers":[
        {
            "category":"Wholesale",
            "subcategory":"Construction Materials",
            "type":"Manufacturing & Wholesale Goods"
        }
    ],
    "sg:phone":"+43 732 39960",
    "sg:postcode":"4030",
    "sg:province":"Ober\u00f6sterreich",
    "sg:tags":[
        "synthetic",
        "fibre",
        "made",
        "natural",
        "backing",
        "mesh"
    ],
    "sg:website":"linz-textil.at",
    "wof:name":"Linz Textil GmbH",
    "wof:placetype":"venue"
},
  "geometry": {"coordinates":[14.3231306076,48.251335144],"type":"Point"}
}