{
  "type": "Feature",
  "properties": {
    "addr:full":"Salzburger Str 2 Wattens Tirol 6112",
    "addr:housenumber":"2",
    "addr:postcode":"6112",
    "addr:street":"Salzburger Str;Tirol",
    "iso:country":"AT",
    "sg:address":"Salzburger Str 2",
    "sg:city":"Wattens",
    "sg:orig_category":"Fleischhauereien",
    "sg:phone":"+43 5224 52318",
    "sg:postcode":"6112",
    "sg:province":"Tirol",
    "wof:name":"Schrott Alois",
    "wof:placetype":"venue"
},
  "geometry": {"coordinates":[11.5936565399,47.29139328],"type":"Point"}
}