{
  "type": "Feature",
  "properties": {
    "addr:full":"Lauterbacher Str 6 Kirchdorf an der Krems Ober\u00f6sterreich 4560",
    "addr:housenumber":"6",
    "addr:postcode":"4560",
    "addr:street":"Lauterbacher Str",
    "iso:country":"AT",
    "sg:address":"Lauterbacher Str 6",
    "sg:city":"Kirchdorf an der Krems",
    "sg:orig_category":"Garten- U Landschaftsgestaltung",
    "sg:phone":"+43 4366 43807401",
    "sg:postcode":"4560",
    "sg:province":"Ober\u00f6sterreich",
    "wof:name":"Geier Robert Haus- u Gartenservice - Reinigungstechnik",
    "wof:placetype":"venue"
},
  "geometry": {"coordinates":[14.1173181534,47.9038009644],"type":"Point"}
}