{
  "type": "Feature",
  "properties": {
    "addr:full":"Lindenpl 4 Judenau Nieder\u00f6sterreich 3441",
    "addr:housenumber":"4",
    "addr:postcode":"3441",
    "addr:street":"Lindenpl",
    "iso:country":"AT",
    "sg:address":"Lindenpl 4",
    "sg:city":"Judenau",
    "sg:orig_category":"Feuerwehren",
    "sg:phone":"+43 2274 7122",
    "sg:postcode":"3441",
    "sg:province":"Nieder\u00f6sterreich",
    "wof:name":"Freiwillige Feuerwehr Freundorf",
    "wof:placetype":"venue"
},
  "geometry": {"coordinates":[16.0334529877,48.2829017639],"type":"Point"}
}