{
  "type": "Feature",
  "properties": {
    "addr:full":"Piaristeng 2-4/12a Wien Wien 1080",
    "addr:housenumber":"2-4 / 12a",
    "addr:postcode":"1080",
    "addr:street":"Piaristeng",
    "iso:country":"AT",
    "sg:address":"Piaristeng 2-4/12a",
    "sg:city":"Wien",
    "sg:orig_category":"Filmproduktionen",
    "sg:phone":"+43 1 4061688",
    "sg:postcode":"1080",
    "sg:province":"Wien",
    "wof:name":"Fochler Rike Dr",
    "wof:placetype":"venue"
},
  "geometry": {"coordinates":[16.3430690765,48.2106552124],"type":"Point"}
}