{
  "type": "Feature",
  "properties": {
    "addr:full":"Nr 80 Maurach Tirol 6212",
    "addr:postcode":"6212",
    "addr:street":"Nr;Maurach Tirol",
    "iso:country":"AT",
    "sg:address":"Nr 80",
    "sg:city":"Maurach",
    "sg:orig_category":"Pensionen / Privatzimmer",
    "sg:phone":"+43 5243 6320",
    "sg:postcode":"6212",
    "sg:province":"Tirol",
    "wof:name":"Fremdenheim Kramerhof",
    "wof:placetype":"venue"
},
  "geometry": {"coordinates":[11.7518672943,47.4225006104],"type":"Point"}
}