{
  "type": "Feature",
  "properties": {
    "iso:country":"AT",
    "sg:address":"Nr 83",
    "sg:city":"Arnfels",
    "sg:orig_category":"Personalbereitstellung",
    "sg:phone":"+43 4366 42865638",
    "sg:postcode":"8454",
    "sg:province":"Steiermark",
    "wof:name":"W.A.P. Winkler Anneliese",
    "wof:placetype":"venue"
},
  "geometry": {"coordinates":[15.4017324448,46.6779937744],"type":"Point"}
}