{
  "type": "Feature",
  "properties": {
    "iso:country":"AT",
    "sg:address":"Favoritenstr 27a",
    "sg:city":"Wien",
    "sg:classifiers":[
        {
            "category":"Restaurant",
            "type":"Food & Drink"
        }
    ],
    "sg:phone":"+43 1 5051545",
    "sg:postcode":"1040",
    "sg:province":"Wien",
    "sg:tags":[
        "pizzeria"
    ],
    "wof:name":"Pizzeria Catania",
    "wof:placetype":"venue"
},
  "geometry": {"coordinates":[16.3725204468,48.1894645691],"type":"Point"}
}