{
  "type": "Feature",
  "properties": {
    "iso:country":"AT",
    "sg:address":"Mesnerg 2",
    "sg:city":"Wattens",
    "sg:orig_category":"Fotografen",
    "sg:phone":"+43 5224 53134",
    "sg:postcode":"6112",
    "sg:province":"Tirol",
    "wof:name":"Lamprechter Walter",
    "wof:placetype":"venue"
},
  "geometry": {"coordinates":[11.5927772522,47.2911605835],"type":"Point"}
}