{
  "type": "Feature",
  "properties": {
    "addr:full":"J\u00e4gerstr 63 Wien Wien 1200",
    "addr:housenumber":"63",
    "addr:postcode":"1200",
    "addr:street":"Jaegerstr",
    "iso:country":"AT",
    "sg:address":"J\u00e4gerstr 63",
    "sg:city":"Wien",
    "sg:orig_category":"Bauunternehmen",
    "sg:phone":"+43 1 9257586",
    "sg:postcode":"1200",
    "sg:province":"Wien",
    "wof:name":"Erfolg Bau GmbH",
    "wof:placetype":"venue"
},
  "geometry": {"coordinates":[16.3699626923,48.234500885],"type":"Point"}
}