{
  "type": "Feature",
  "properties": {
    "addr:full":"Nr 66 Gundersheim K\u00e4rnten 9634",
    "addr:postcode":"9634",
    "addr:street":"Nr",
    "iso:country":"AT",
    "sg:address":"Nr 66",
    "sg:city":"Gundersheim",
    "sg:orig_category":"Banken U Sparkassen",
    "sg:phone":"+43 4347 18350",
    "sg:postcode":"9634",
    "sg:province":"K\u00e4rnten",
    "wof:name":"Raiffeisenbank K\u00f6tschach-Mauthen regGenmbH",
    "wof:placetype":"venue"
},
  "geometry": {"coordinates":[13.117225647,46.6481666565],"type":"Point"}
}