{
  "type": "Feature",
  "properties": {
    "addr:full":"Schulstr 12 Feldkirchen an der Donau Ober\u00f6sterreich 4101",
    "addr:housenumber":"12",
    "addr:postcode":"4101",
    "addr:street":"Schulstr",
    "iso:country":"AT",
    "sg:address":"Schulstr 12",
    "sg:city":"Feldkirchen an der Donau",
    "sg:orig_category":"Hauptschulen",
    "sg:phone":"+43 4372 336372",
    "sg:postcode":"4101",
    "sg:province":"Ober\u00f6sterreich",
    "wof:name":"Hauptschule",
    "wof:placetype":"venue"
},
  "geometry": {"coordinates":[14.0549707413,48.345664978],"type":"Point"}
}