{
  "type": "Feature",
  "properties": {
    "addr:full":"Kirchheimer Weg 8 Bad Kleinkirchheim K\u00e4rnten 9546",
    "addr:housenumber":"8",
    "addr:postcode":"9546",
    "addr:street":"Kirchheimer Weg",
    "iso:country":"AT",
    "sg:address":"Kirchheimer Weg 8",
    "sg:city":"Bad Kleinkirchheim",
    "sg:classifiers":[
        {
            "category":"Restaurant",
            "type":"Food & Drink"
        }
    ],
    "sg:phone":"+43 4240 860050",
    "sg:postcode":"9546",
    "sg:province":"K\u00e4rnten",
    "wof:name":"Restaurant Pizzeria Pr\u00e4gant",
    "wof:placetype":"venue"
},
  "geometry": {"coordinates":[13.7978239059,46.8149337769],"type":"Point"}
}