{
  "type": "Feature",
  "properties": {
    "iso:country":"AT",
    "sg:address":"Industriestrasse 23",
    "sg:city":"St. Johann im Pongau",
    "sg:classifiers":[
        {
            "category":"Government",
            "subcategory":"Department Of Motor Vehicles",
            "type":"Public Place"
        }
    ],
    "sg:phone":"+43 6412 7824",
    "sg:postcode":"5600",
    "sg:province":"Salzburg",
    "sg:tags":[
        "part",
        "bought-in"
    ],
    "wof:name":"Reutter Fabrik f\u00fcr Autoteile Ges.m.b.H.",
    "wof:placetype":"venue"
},
  "geometry": {"coordinates":[13.2005586624,47.3544425964],"type":"Point"}
}