{
  "type": "Feature",
  "properties": {
    "iso:country":"AT",
    "sg:address":"Siemensstr. 160",
    "sg:city":"Wien",
    "sg:classifiers":[
        {
            "category":"Professional",
            "subcategory":"Computer Services",
            "type":"Services"
        }
    ],
    "sg:phone":"+43 4312 77900",
    "sg:postcode":"1210",
    "sg:province":"Wien",
    "sg:tags":[
        "information",
        "technology"
    ],
    "wof:name":"NRG GESTETNER AUSTRIA GESMBH",
    "wof:placetype":"venue"
},
  "geometry": {"coordinates":[16.4315013885,48.2661743164],"type":"Point"}
}