{
  "type": "Feature",
  "properties": {
    "addr:full":"Stephansberg 12 Horn Nieder\u00f6sterreich 3580",
    "addr:housenumber":"12",
    "addr:postcode":"3580",
    "addr:street":"Stephansberg",
    "iso:country":"AT",
    "sg:address":"Stephansberg 12",
    "sg:city":"Horn",
    "sg:orig_category":"Nachhilfe U Lernbetreuung",
    "sg:phone":"+43 2982 30417",
    "sg:postcode":"3580",
    "sg:province":"Nieder\u00f6sterreich",
    "wof:name":"Hilfswerk Horn - Rund ums Lernen",
    "wof:placetype":"venue"
},
  "geometry": {"coordinates":[15.6526679993,48.6626052856],"type":"Point"}
}