{
  "type": "Feature",
  "properties": {
    "addr:full":"Donaustr 5 Korneuburg Nieder\u00f6sterreich 2100",
    "addr:housenumber":"5",
    "addr:postcode":"2100",
    "addr:street":"Donaustr;Niederoesterreich",
    "iso:country":"AT",
    "sg:address":"Donaustr 5",
    "sg:city":"Korneuburg",
    "sg:orig_category":"Personalbereitstellung",
    "sg:phone":"+43 2262 74701",
    "sg:postcode":"2100",
    "sg:province":"Nieder\u00f6sterreich",
    "wof:name":"Spartacus Arbeitskr\u00e4fte\u00fcberlassungsgmbH",
    "wof:placetype":"venue"
},
  "geometry": {"coordinates":[16.3329105377,48.3426094055],"type":"Point"}
}