{
  "type": "Feature",
  "properties": {
    "addr:full":"Praterstr 17 Wien Wien 1020",
    "addr:housenumber":"17",
    "addr:postcode":"1020",
    "addr:street":"Praterstr",
    "iso:country":"AT",
    "sg:address":"Praterstr 17",
    "sg:city":"Wien",
    "sg:orig_category":"Bauunternehmen",
    "sg:phone":"+43 1 2142393",
    "sg:postcode":"1020",
    "sg:province":"Wien",
    "wof:name":"BIRITZ GmbH",
    "wof:placetype":"venue"
},
  "geometry": {"coordinates":[16.3818473816,48.2135391235],"type":"Point"}
}