{
  "type": "Feature",
  "properties": {
    "addr:full":"Khekgasse 19/16 Wien Wien 1230",
    "addr:housenumber":"19 / 16",
    "addr:postcode":"1230",
    "addr:street":"Khekgasse",
    "iso:country":"AT",
    "sg:address":"Khekgasse 19/16",
    "sg:city":"Wien",
    "sg:classifiers":[
        {
            "category":"Real Estate",
            "subcategory":"Real Estate Operator",
            "type":"Services"
        }
    ],
    "sg:phone":"+43 699 11531648",
    "sg:postcode":"1230",
    "sg:province":"Wien",
    "sg:tags":[
        "application",
        "asp",
        "provider"
    ],
    "sg:website":"engagesolution.com",
    "wof:name":"engagesolution Kubitschke KEG",
    "wof:placetype":"venue"
},
  "geometry": {"coordinates":[16.2778949738,48.1331100464],"type":"Point"}
}