{
  "type": "Feature",
  "properties": {
    "iso:country":"AT",
    "sg:address":"Nr 118",
    "sg:city":"St. Johann in der Haide",
    "sg:orig_category":"Pensionen / Privatzimmer",
    "sg:phone":"+43 4333 3263996",
    "sg:postcode":"8295",
    "sg:province":"Steiermark",
    "wof:name":"Pension Fernblick",
    "wof:placetype":"venue"
},
  "geometry": {"coordinates":[16.0245819092,47.2807769775],"type":"Point"}
}