{
  "type": "Feature",
  "properties": {
    "addr:full":"Nr 43 Rohrbach an der Lafnitz Steiermark 8234",
    "addr:postcode":"8234",
    "addr:street":"Nr 43",
    "iso:country":"AT",
    "sg:address":"Nr 43",
    "sg:city":"Rohrbach an der Lafnitz",
    "sg:orig_category":"Kosmetische Produkte / Einzelhandel",
    "sg:phone":"+43 3338 3496",
    "sg:postcode":"8234",
    "sg:province":"Steiermark",
    "wof:name":"Sch\u00fctzenh\u00f6fer Manuela",
    "wof:placetype":"venue"
},
  "geometry": {"coordinates":[15.9732465744,47.3812446594],"type":"Point"}
}