{
  "type": "Feature",
  "properties": {
    "addr:full":"Budapester Str 35 Halbturn Burgenland 7131",
    "addr:housenumber":"35",
    "addr:postcode":"7131",
    "iso:country":"AT",
    "sg:address":"Budapester Str 35",
    "sg:city":"Halbturn",
    "sg:orig_category":"Lebensmittel / Einzelhandel",
    "sg:phone":"+43 2172 8580",
    "sg:postcode":"7131",
    "sg:province":"Burgenland",
    "wof:name":"Spar-Markt Wagersreiter Rudolf",
    "wof:placetype":"venue"
},
  "geometry": {"coordinates":[16.977689743,47.8703613281],"type":"Point"}
}