{
  "type": "Feature",
  "properties": {
    "addr:full":"Gildenweg 4 Ebreichsdorf Nieder\u00f6sterreich 2483",
    "addr:housenumber":"4",
    "addr:postcode":"2483",
    "addr:street":"Gildenweg",
    "iso:country":"AT",
    "sg:address":"Gildenweg 4",
    "sg:city":"Ebreichsdorf",
    "sg:orig_category":"Etiketten",
    "sg:phone":"+43 4322 5472100",
    "sg:postcode":"2483",
    "sg:province":"Nieder\u00f6sterreich",
    "wof:name":"Fischer Alfred & W GesmbH",
    "wof:placetype":"venue"
},
  "geometry": {"coordinates":[16.4127902985,47.9556045532],"type":"Point"}
}