{
  "type": "Feature",
  "properties": {
    "addr:full":"Unterweg 49 Matrei am Brenner Tirol 6143",
    "addr:housenumber":"49",
    "addr:postcode":"6143",
    "addr:street":"Unterweg;Brenner",
    "iso:country":"AT",
    "sg:address":"Unterweg 49",
    "sg:city":"Matrei am Brenner",
    "sg:orig_category":"Banken U Sparkassen",
    "sg:phone":"+43 5278 6208",
    "sg:postcode":"6143",
    "sg:province":"Tirol",
    "wof:name":"Raiffeisenkasse Matrei/Brenner und Umgebung regGenmbH",
    "wof:placetype":"venue"
},
  "geometry": {"coordinates":[11.4936552048,47.124671936],"type":"Point"}
}