{
  "type": "Feature",
  "properties": {
    "iso:country":"AT",
    "sg:address":"Linzer Bundesstrasse 32",
    "sg:city":"Gnigl",
    "sg:classifiers":[
        {
            "category":"Home & Garden",
            "subcategory":"Building Materials",
            "type":"Retail Goods"
        }
    ],
    "sg:phone":"+43 662 640652",
    "sg:postcode":"5023",
    "sg:province":"Salzburg",
    "sg:tags":[
        "installation",
        "electric"
    ],
    "wof:name":"Elektrotechnik Ing. Augeneder KG",
    "wof:placetype":"venue"
},
  "geometry": {"coordinates":[13.0684633255,47.8138465881],"type":"Point"}
}