{
  "type": "Feature",
  "properties": {
    "addr:full":"Hauptstr 36 Kemmelbach Nieder\u00f6sterreich 3373",
    "addr:housenumber":"36",
    "addr:postcode":"3373",
    "addr:street":"Hauptstr",
    "iso:country":"AT",
    "sg:address":"Hauptstr 36",
    "sg:city":"Kemmelbach",
    "sg:orig_category":"Behinderungen / Leben Mit Behinderungen",
    "sg:phone":"+43 7412 520900",
    "sg:postcode":"3373",
    "sg:province":"Nieder\u00f6sterreich",
    "wof:name":"Lebenshilfe N\u00f6 Werkst\u00e4tte i Schlo\u00df Neudenburg",
    "wof:placetype":"venue"
},
  "geometry": {"coordinates":[15.0936956406,48.1543655396],"type":"Point"}
}