{
  "type": "Feature",
  "properties": {
    "addr:full":"Bahnhofstr 39 Attnang-Puchheim Ober\u00f6sterreich 4800",
    "addr:housenumber":"39",
    "addr:postcode":"4800",
    "addr:street":"Bahnhofstr",
    "iso:country":"AT",
    "sg:address":"Bahnhofstr 39",
    "sg:city":"Attnang-Puchheim",
    "sg:classifiers":[
        {
            "category":"Restaurant",
            "type":"Food & Drink"
        }
    ],
    "sg:phone":"+43 767462569",
    "sg:postcode":"4800",
    "sg:province":"Ober\u00f6sterreich",
    "sg:tags":[
        "pizzeria"
    ],
    "wof:name":"Pizzeria Michelangelo",
    "wof:placetype":"venue"
},
  "geometry": {"coordinates":[13.7220096588,48.0131607056],"type":"Point"}
}