{
  "type": "Feature",
  "properties": {
    "iso:country":"AT",
    "sg:address":"Franz-von-Furtenbach-Str 23",
    "sg:city":"Wiener Neustadt",
    "sg:orig_category":"Schaufenstergestaltungen",
    "sg:phone":"+43 4326 22244151",
    "sg:postcode":"2700",
    "sg:province":"Nieder\u00f6sterreich",
    "wof:name":"Platzkammer Helga",
    "wof:placetype":"venue"
},
  "geometry": {"coordinates":[16.2734222412,47.8086204529],"type":"Point"}
}