{
  "type": "Feature",
  "properties": {
    "addr:full":"Lainzer Strasse 16 Wien Wien 1130",
    "addr:housenumber":"16",
    "addr:postcode":"1130",
    "addr:street":"Lainzer Strasse",
    "iso:country":"AT",
    "sg:address":"Lainzer Strasse 16",
    "sg:city":"Wien",
    "sg:classifiers":[
        {
            "category":"Professional",
            "subcategory":"Advertising",
            "type":"Services"
        }
    ],
    "sg:phone":"+43 1 87046",
    "sg:postcode":"1130",
    "sg:province":"Wien",
    "sg:tags":[
        "agency"
    ],
    "sg:website":"unique.at",
    "wof:name":"Unique Werbe Ges.m.b.H.",
    "wof:placetype":"venue"
},
  "geometry": {"coordinates":[16.2957763672,48.185295105],"type":"Point"}
}