{
  "type": "Feature",
  "properties": {
    "iso:country":"AT",
    "sg:address":"Karl-Heinrich-Waggerl-Str 16",
    "sg:city":"Bad Gastein",
    "sg:classifiers":[
        {
            "category":"Travel",
            "subcategory":"Hotels & Motels",
            "type":"Entertainment"
        }
    ],
    "sg:phone":"+43 4364 34207600",
    "sg:postcode":"5640",
    "sg:province":"Salzburg",
    "wof:name":"Hotel Eden",
    "wof:placetype":"venue"
},
  "geometry": {"coordinates":[13.1333007812,47.1137199402],"type":"Point"}
}