{
  "type": "Feature",
  "properties": {
    "addr:full":"Florianig 9 Weiz Steiermark 8160",
    "addr:housenumber":"9",
    "addr:postcode":"8160",
    "addr:street":"Florianig",
    "iso:country":"AT",
    "sg:address":"Florianig 9",
    "sg:city":"Weiz",
    "sg:orig_category":"Energieberatung U -Untersuchung",
    "sg:phone":"+43 4331 72303210",
    "sg:postcode":"8160",
    "sg:province":"Steiermark",
    "wof:name":"Regionalenergie Stmk - Beratungsges f Holzenergiesysteme",
    "wof:placetype":"venue"
},
  "geometry": {"coordinates":[15.6215696335,47.2169532776],"type":"Point"}
}