{
  "type": "Feature",
  "properties": {
    "addr:full":"Seebacher Allee 6 Villach K\u00e4rnten 9500",
    "addr:housenumber":"6",
    "addr:postcode":"9500",
    "addr:street":"Seebacher Allee;Kaernten",
    "iso:country":"AT",
    "sg:address":"Seebacher Allee 6",
    "sg:city":"Villach",
    "sg:orig_category":"Steuerberatung",
    "sg:phone":"+43 4342 4242011",
    "sg:postcode":"9500",
    "sg:province":"K\u00e4rnten",
    "wof:name":"Mairitsch Thomas Mag",
    "wof:placetype":"venue"
},
  "geometry": {"coordinates":[13.8618135452,46.6196289062],"type":"Point"}
}