{
  "type": "Feature",
  "properties": {
    "addr:full":"Egg 15 Eugendorf Salzburg 5301",
    "addr:housenumber":"15",
    "addr:postcode":"5301",
    "addr:street":"Egg;Salzburg",
    "iso:country":"AT",
    "sg:address":"Egg 15",
    "sg:city":"Eugendorf",
    "sg:orig_category":"Waren Aller Art",
    "sg:phone":"+43 6221 83610",
    "sg:postcode":"5301",
    "sg:province":"Salzburg",
    "wof:name":"Shima Handels GmbH",
    "wof:placetype":"venue"
},
  "geometry": {"coordinates":[13.150891304,47.8431358337],"type":"Point"}
}