{
  "type": "Feature",
  "properties": {
    "addr:full":"Ro\u00dfmarkt 21-25 Ried im Innkreis Ober\u00f6sterreich 4910",
    "addr:postcode":"21-25;4910",
    "addr:street":"Rossmarkt",
    "iso:country":"AT",
    "sg:address":"Ro\u00dfmarkt 21-25",
    "sg:city":"Ried im Innkreis",
    "sg:orig_category":"Bekleidung / Einzelhandel",
    "sg:phone":"+43 7752 826570",
    "sg:postcode":"4910",
    "sg:province":"Ober\u00f6sterreich",
    "wof:name":"Mei\u00dfl Mode GmbH & Co",
    "wof:placetype":"venue"
},
  "geometry": {"coordinates":[13.4900550842,48.2098655701],"type":"Point"}
}