{
  "type": "Feature",
  "properties": {
    "addr:full":"St. Peter Str. 25  4021",
    "addr:postcode":"4021",
    "addr:street":"Str. 25",
    "iso:country":"AT",
    "sg:address":"St. Peter Str. 25 ",
    "sg:classifiers":[
        {
            "category":"Wholesale",
            "subcategory":"Drugs",
            "type":"Manufacturing & Wholesale Goods"
        }
    ],
    "sg:phone":"+43 4373 269180",
    "sg:postcode":"4021",
    "sg:tags":[
        "chemical",
        "pharmaceutical"
    ],
    "wof:name":"NUFARM GMBH & CO KG",
    "wof:placetype":"venue"
},
  "geometry": {"coordinates":[14.3216533661,48.2888450623],"type":"Point"}
}