{
  "type": "Feature",
  "properties": {
    "addr:full":"Richard-Mayr-Allee 2 Henndorf am Wallersee Salzburg 5302",
    "addr:housenumber":"2",
    "addr:postcode":"5302",
    "addr:street":"Richard-Mayr-Allee",
    "iso:country":"AT",
    "sg:address":"Richard-Mayr-Allee 2",
    "sg:city":"Henndorf am Wallersee",
    "sg:orig_category":"Lebensmittel / Einzelhandel",
    "sg:phone":"+43 4362 147825",
    "sg:postcode":"5302",
    "sg:province":"Salzburg",
    "wof:name":"Zielpunkt Warenhandel GmbH & Co KG",
    "wof:placetype":"venue"
},
  "geometry": {"coordinates":[13.1892585754,47.8994483948],"type":"Point"}
}