{
  "type": "Feature",
  "properties": {
    "addr:full":"Nr 17 Alland Nieder\u00f6sterreich 2534",
    "addr:postcode":"2534",
    "addr:street":"Nr;Alland",
    "iso:country":"AT",
    "sg:address":"Nr 17",
    "sg:city":"Alland",
    "sg:orig_category":"Autoreparatur",
    "sg:phone":"+43 2258 2551",
    "sg:postcode":"2534",
    "sg:province":"Nieder\u00f6sterreich",
    "wof:name":"The Garage - Umgeher Hannes",
    "wof:placetype":"venue"
},
  "geometry": {"coordinates":[16.0783996582,48.0584259033],"type":"Point"}
}