{
  "type": "Feature",
  "properties": {
    "addr:full":"Nr 99 Jagerberg Steiermark 8091",
    "addr:postcode":"8091",
    "addr:street":"Nr",
    "iso:country":"AT",
    "sg:address":"Nr 99",
    "sg:city":"Jagerberg",
    "sg:orig_category":"Feuerwehren",
    "sg:phone":"+43 3184 8650",
    "sg:postcode":"8091",
    "sg:province":"Steiermark",
    "wof:name":"Freiwillige Feuerwehr Jagerberg",
    "wof:placetype":"venue"
},
  "geometry": {"coordinates":[15.7383260727,46.8539466858],"type":"Point"}
}