{
  "type": "Feature",
  "properties": {
    "addr:full":"Frojach 100 Frojach Steiermark 8841",
    "addr:housenumber":"100",
    "addr:postcode":"8841",
    "addr:street":"Frojach",
    "iso:country":"AT",
    "sg:address":"Frojach 100",
    "sg:city":"Frojach",
    "sg:orig_category":"Volksschulen",
    "sg:phone":"+43 3588 221",
    "sg:postcode":"8841",
    "sg:province":"Steiermark",
    "wof:name":"Volksschule",
    "wof:placetype":"venue"
},
  "geometry": {"coordinates":[14.3013896942,47.1253128052],"type":"Point"}
}