{
  "type": "Feature",
  "properties": {
    "iso:country":"AT",
    "sg:address":"Nr 10",
    "sg:city":"Allhaming",
    "sg:orig_category":"Banken U Sparkassen",
    "sg:phone":"+43 4372 277011",
    "sg:postcode":"4511",
    "sg:province":"Ober\u00f6sterreich",
    "wof:name":"Sparkasse Neuhofen Bank AG",
    "wof:placetype":"venue"
},
  "geometry": {"coordinates":[14.1709213257,48.152923584],"type":"Point"}
}