{
  "type": "Feature",
  "properties": {
    "iso:country":"AT",
    "sg:address":"Burggasse 15 ",
    "sg:city":"Judenburg",
    "sg:classifiers":[
        {
            "category":"Utilities",
            "subcategory":"Electric",
            "type":"Services"
        }
    ],
    "sg:phone":"+43 4335 7283146",
    "sg:postcode":"8750",
    "sg:province":"Steiermark",
    "sg:tags":[
        "electricity"
    ],
    "wof:name":"STADTWERKE JUDENBURG AG",
    "wof:placetype":"venue"
},
  "geometry": {"coordinates":[14.6587848663,47.1678848267],"type":"Point"}
}