{
  "type": "Feature",
  "properties": {
    "addr:full":"Herzog Odilo-Str 46 Mondsee Ober\u00f6sterreich 5310",
    "addr:housenumber":"46",
    "addr:postcode":"5310",
    "addr:street":"Odilo-Str;Oberoesterreich",
    "iso:country":"AT",
    "sg:address":"Herzog Odilo-Str 46",
    "sg:city":"Mondsee",
    "sg:orig_category":"Bestattungsunternehmen",
    "sg:phone":"+43 6232 2386",
    "sg:postcode":"5310",
    "sg:province":"Ober\u00f6sterreich",
    "wof:name":"Bestattung Brandmeier-Schmarl",
    "wof:placetype":"venue"
},
  "geometry": {"coordinates":[13.3474988937,47.8581695557],"type":"Point"}
}