{
  "type": "Feature",
  "properties": {
    "addr:full":"Simmeringer Hauptstr 261 Wien Wien 1110",
    "addr:housenumber":"261",
    "addr:postcode":"1110",
    "addr:street":"Simmeringer Hauptstr",
    "iso:country":"AT",
    "sg:address":"Simmeringer Hauptstr 261",
    "sg:city":"Wien",
    "sg:orig_category":"Autohandel",
    "sg:phone":"+43 4317 60770",
    "sg:postcode":"1110",
    "sg:province":"Wien",
    "wof:name":"FordSimmering",
    "wof:placetype":"venue"
},
  "geometry": {"coordinates":[16.4302082062,48.1611976624],"type":"Point"}
}