{
  "type": "Feature",
  "properties": {
    "iso:country":"AT",
    "sg:address":"Donau-City-Str 1",
    "sg:city":"Wien",
    "sg:orig_category":"Schifffahrt",
    "sg:phone":"+43 4315 954896",
    "sg:postcode":"1220",
    "sg:province":"Wien",
    "wof:name":"via donau - \u00f6sterreichische Wasserstra\u00dfen Gesellschaft mbH",
    "wof:placetype":"venue"
},
  "geometry": {"coordinates":[16.4138431549,48.2321853638],"type":"Point"}
}