{
  "type": "Feature",
  "properties": {
    "iso:country":"AT",
    "sg:address":"Laaer-Berg-Str 12",
    "sg:city":"Wien",
    "sg:orig_category":"Schuhreparatur",
    "sg:phone":"+43 1 6069456",
    "sg:postcode":"1100",
    "sg:province":"Wien",
    "wof:name":"Bagci Isa",
    "wof:placetype":"venue"
},
  "geometry": {"coordinates":[16.3805465698,48.1730117798],"type":"Point"}
}