{
  "type": "Feature",
  "properties": {
    "addr:full":"Marktstr 5 Altm\u00fcnster Ober\u00f6sterreich 4813",
    "addr:housenumber":"5",
    "addr:postcode":"4813",
    "addr:street":"Marktstr;Oberoesterreich",
    "iso:country":"AT",
    "sg:address":"Marktstr 5",
    "sg:city":"Altm\u00fcnster",
    "sg:orig_category":"Friseure U Frisiersalons",
    "sg:phone":"+43 761287365",
    "sg:postcode":"4813",
    "sg:province":"Ober\u00f6sterreich",
    "wof:name":"Reiter Thomas",
    "wof:placetype":"venue"
},
  "geometry": {"coordinates":[13.7663888931,47.901058197],"type":"Point"}
}