{
  "type": "Feature",
  "properties": {
    "iso:country":"AT",
    "sg:address":"Quellenstr 45",
    "sg:city":"Bregenz",
    "sg:orig_category":"Bauunternehmen",
    "sg:phone":"+43 5574 42979",
    "sg:postcode":"6900",
    "sg:province":"Vorarlberg",
    "wof:name":"Zimmermann Bau GesmbH",
    "wof:placetype":"venue"
},
  "geometry": {"coordinates":[9.7341928482,47.4997215271],"type":"Point"}
}