{
  "type": "Feature",
  "properties": {
    "addr:full":"Wiener Str 70 Kapfenberg Steiermark 8605",
    "addr:postcode":"8605",
    "addr:street":"70",
    "iso:country":"AT",
    "sg:address":"Wiener Str 70",
    "sg:city":"Kapfenberg",
    "sg:orig_category":"Tabaktrafiken",
    "sg:phone":"+43 3862 23376",
    "sg:postcode":"8605",
    "sg:province":"Steiermark",
    "wof:name":"Lammer Harald",
    "wof:placetype":"venue"
},
  "geometry": {"coordinates":[15.2987270355,47.4456253052],"type":"Point"}
}