{
  "type": "Feature",
  "properties": {
    "addr:full":"Franz-Throner-G 26 Himberg Nieder\u00f6sterreich 2325",
    "addr:housenumber":"26",
    "addr:postcode":"2325",
    "addr:street":"Franz-Throner-G",
    "iso:country":"AT",
    "sg:address":"Franz-Throner-G 26",
    "sg:city":"Himberg",
    "sg:orig_category":"Tonstudios",
    "sg:phone":"+43 4322 3584365",
    "sg:postcode":"2325",
    "sg:province":"Nieder\u00f6sterreich",
    "wof:name":"Zipp records Tonstudio u Plattenlabel - Collin & Bayer GesnbR",
    "wof:placetype":"venue"
},
  "geometry": {"coordinates":[16.4417667389,48.0806083679],"type":"Point"}
}