{
  "type": "Feature",
  "properties": {
    "addr:full":"Wagnerg 4-6 Gablitz Nieder\u00f6sterreich 3003",
    "addr:housenumber":"4-6",
    "addr:postcode":"3003",
    "addr:street":"Wagnerg",
    "iso:country":"AT",
    "sg:address":"Wagnerg 4-6",
    "sg:city":"Gablitz",
    "sg:classifiers":[
        {
            "category":"Travel",
            "subcategory":"Hotels & Motels",
            "type":"Entertainment"
        }
    ],
    "sg:phone":"+43 2231 66587",
    "sg:postcode":"3003",
    "sg:province":"Nieder\u00f6sterreich",
    "wof:name":"Hotel Restaurant Hohnecker",
    "wof:placetype":"venue"
},
  "geometry": {"coordinates":[16.1601219177,48.2238845825],"type":"Point"}
}