{
  "type": "Feature",
  "properties": {
    "addr:full":"Rudolfstr 37 Graz Steiermark 8010",
    "addr:housenumber":"37",
    "addr:postcode":"8010",
    "addr:street":"Rudolfstr",
    "iso:country":"AT",
    "sg:address":"Rudolfstr 37",
    "sg:city":"Graz",
    "sg:orig_category":"Fotografen",
    "sg:phone":"+43 4331 6381835",
    "sg:postcode":"8010",
    "sg:province":"Steiermark",
    "wof:name":"Pauritsch Franz",
    "wof:placetype":"venue"
},
  "geometry": {"coordinates":[15.4678840637,47.0731697083],"type":"Point"}
}