{
  "type": "Feature",
  "properties": {
    "addr:full":"Zwinzstr 3a Wien Wien 1160",
    "addr:housenumber":"3a",
    "addr:postcode":"1160",
    "addr:street":"Zwinzstr",
    "iso:country":"AT",
    "sg:address":"Zwinzstr 3a",
    "sg:city":"Wien",
    "sg:orig_category":"Dachbodenausbau",
    "sg:phone":"+43 4319 8224330",
    "sg:postcode":"1160",
    "sg:province":"Wien",
    "wof:name":"Holzbau Fr\u00f6stl GesmbH",
    "wof:placetype":"venue"
},
  "geometry": {"coordinates":[16.3077716827,48.206035614],"type":"Point"}
}