{
  "type": "Feature",
  "properties": {
    "addr:full":"Nr 31 Gro\u00dfweikersdorf Nieder\u00f6sterreich 3701",
    "addr:housenumber":"3701",
    "addr:street":"Nr;Grossweikersdorf Niederoesterreich",
    "iso:country":"AT",
    "sg:address":"Nr 31",
    "sg:city":"Gro\u00dfweikersdorf",
    "sg:classifiers":[
        {
            "category":"Professional",
            "subcategory":"Art Services",
            "type":"Services"
        }
    ],
    "sg:phone":"+43 2955 70497",
    "sg:postcode":"3701",
    "sg:province":"Nieder\u00f6sterreich",
    "sg:tags":[
        "designer"
    ],
    "wof:name":"Szurcsik-Wallenta Janos",
    "wof:placetype":"venue"
},
  "geometry": {"coordinates":[15.982219696,48.4726753235],"type":"Point"}
}