{
  "type": "Feature",
  "properties": {
    "addr:full":"Dr.-W-Steing\u00f6tter-Str 23 St. P\u00f6lten-Traisenpark Nieder\u00f6sterreich 3107",
    "addr:housenumber":"23",
    "addr:postcode":"3107",
    "addr:street":"Dr.-W-Steingoetter-Str",
    "iso:country":"AT",
    "sg:address":"Dr.-W-Steing\u00f6tter-Str 23",
    "sg:city":"St. P\u00f6lten-Traisenpark",
    "sg:orig_category":"Autohandel",
    "sg:phone":"+43 2742 3630180",
    "sg:postcode":"3107",
    "sg:province":"Nieder\u00f6sterreich",
    "wof:name":"Mayer F S GesmbH & Co KG",
    "wof:placetype":"venue"
},
  "geometry": {"coordinates":[15.6210651398,48.233089447],"type":"Point"}
}