{
  "type": "Feature",
  "properties": {
    "addr:full":"Hauptstr 17 St. Peter ob Judenburg Steiermark 8755",
    "addr:housenumber":"17",
    "addr:postcode":"8755",
    "addr:street":"Hauptstr",
    "iso:country":"AT",
    "sg:address":"Hauptstr 17",
    "sg:city":"St. Peter ob Judenburg",
    "sg:orig_category":"Gemeinden",
    "sg:phone":"+43 4335 7922870",
    "sg:postcode":"8755",
    "sg:province":"Steiermark",
    "wof:name":"Gemeindeamt St Peter ob Judenburg",
    "wof:placetype":"venue"
},
  "geometry": {"coordinates":[14.5883350372,47.1852760315],"type":"Point"}
}