{
  "type": "Feature",
  "properties": {
    "addr:full":"Innbachtalstr 15 Pichl Ober\u00f6sterreich 4632",
    "addr:housenumber":"15",
    "addr:postcode":"4632",
    "addr:street":"Innbachtalstr",
    "iso:country":"AT",
    "sg:address":"Innbachtalstr 15",
    "sg:city":"Pichl",
    "sg:orig_category":"Banken U Sparkassen",
    "sg:phone":"+43 4350 10040114",
    "sg:postcode":"4632",
    "sg:province":"Ober\u00f6sterreich",
    "wof:name":"Allgemeine Sparkasse Ober\u00f6sterreich Bank AG",
    "wof:placetype":"venue"
},
  "geometry": {"coordinates":[13.8999576569,48.1844367981],"type":"Point"}
}