{
  "type": "Feature",
  "properties": {
    "addr:full":"Emil-Kraft-G 12 Baden Nieder\u00f6sterreich 2500",
    "addr:housenumber":"12",
    "addr:postcode":"2500",
    "addr:street":"Emil-Kraft-G;Niederoesterreich",
    "iso:country":"AT",
    "sg:address":"Emil-Kraft-G 12",
    "sg:city":"Baden",
    "sg:orig_category":"Dolmetscher",
    "sg:phone":"+43 2252 49076",
    "sg:postcode":"2500",
    "sg:province":"Nieder\u00f6sterreich",
    "wof:name":"Neff Ingrid Mag",
    "wof:placetype":"venue"
},
  "geometry": {"coordinates":[16.2532463074,48.0105209351],"type":"Point"}
}