{
  "type": "Feature",
  "properties": {
    "iso:country":"AT",
    "sg:address":"Bahnstr 51a",
    "sg:city":"Parndorf",
    "sg:orig_category":"Holzdecken U Wandverkleidungen",
    "sg:phone":"+43 676 6606001",
    "sg:postcode":"7111",
    "sg:province":"Burgenland",
    "wof:name":"Malzer Franz",
    "wof:placetype":"venue"
},
  "geometry": {"coordinates":[16.866355896,47.9876937866],"type":"Point"}
}