{
  "type": "Feature",
  "properties": {
    "addr:full":"Am Anger 4 Nu\u00dfdorf am Attersee Ober\u00f6sterreich 4865",
    "addr:housenumber":"4",
    "addr:postcode":"4865",
    "addr:street":"Am Anger",
    "iso:country":"AT",
    "sg:address":"Am Anger 4",
    "sg:city":"Nu\u00dfdorf am Attersee",
    "sg:classifiers":[
        {
            "category":"Restaurant",
            "type":"Food & Drink"
        }
    ],
    "sg:phone":"+43 766680000",
    "sg:postcode":"4865",
    "sg:province":"Ober\u00f6sterreich",
    "wof:name":"Einser Beisl im Lexenhof",
    "wof:placetype":"venue"
},
  "geometry": {"coordinates":[13.5220537186,47.8828125],"type":"Point"}
}