{
  "type": "Feature",
  "properties": {
    "addr:full":"Dr.-Karl-Renner-Str 102 Neufeld an der Leitha Burgenland 2491",
    "addr:housenumber":"102",
    "addr:postcode":"2491",
    "iso:country":"AT",
    "sg:address":"Dr.-Karl-Renner-Str 102",
    "sg:city":"Neufeld an der Leitha",
    "sg:classifiers":[
        {
            "category":"Professional",
            "subcategory":"Management & Consulting",
            "type":"Services"
        }
    ],
    "sg:phone":"+43 4326 2454459",
    "sg:postcode":"2491",
    "sg:province":"Burgenland",
    "wof:name":"Jumpzone Productions Event Management GesmbH",
    "wof:placetype":"venue"
},
  "geometry": {"coordinates":[16.379491806,47.8604545593],"type":"Point"}
}