{
  "type": "Feature",
  "properties": {
    "addr:full":"R\u00f6merstr 48/2 Attnang-Puchheim Ober\u00f6sterreich 4800",
    "addr:housenumber":"48 / 2",
    "addr:postcode":"4800",
    "addr:street":"Roemerstr;Attnang-Puchheim Oberoesterreich",
    "iso:country":"AT",
    "sg:address":"R\u00f6merstr 48/2",
    "sg:city":"Attnang-Puchheim",
    "sg:orig_category":"Werbeagenturen",
    "sg:phone":"+43 767463363",
    "sg:postcode":"4800",
    "sg:province":"Ober\u00f6sterreich",
    "wof:name":"PR Anzeigenverwaltung GmbH",
    "wof:placetype":"venue"
},
  "geometry": {"coordinates":[13.7204141617,48.0107002258],"type":"Point"}
}