{
  "type": "Feature",
  "properties": {
    "addr:full":"Englisch Feld-G 4 Wien Wien 1220",
    "addr:housenumber":"4",
    "addr:postcode":"1220",
    "addr:street":"Feld-G",
    "iso:country":"AT",
    "sg:address":"Englisch Feld-G 4",
    "sg:city":"Wien",
    "sg:orig_category":"Non-Classified Establishments",
    "sg:phone":"+43 1 7742680",
    "sg:postcode":"1220",
    "sg:province":"Wien",
    "wof:name":"Evangelikale Gemeinde",
    "wof:placetype":"venue"
},
  "geometry": {"coordinates":[16.5355377197,48.2095985413],"type":"Point"}
}