{
  "type": "Feature",
  "properties": {
    "addr:full":"L\u00e4rcheng 13 Guntramsdorf Nieder\u00f6sterreich 2353",
    "addr:housenumber":"13",
    "addr:postcode":"2353",
    "addr:street":"Laercheng",
    "iso:country":"AT",
    "sg:address":"L\u00e4rcheng 13",
    "sg:city":"Guntramsdorf",
    "sg:orig_category":"Abluftreinigung",
    "sg:phone":"+43 4322 36864247",
    "sg:postcode":"2353",
    "sg:province":"Nieder\u00f6sterreich",
    "wof:name":"Hajek Ludwig Ing",
    "wof:placetype":"venue"
},
  "geometry": {"coordinates":[16.3237991333,48.0635414124],"type":"Point"}
}