{
  "type": "Feature",
  "properties": {
    "addr:full":"Kreuzstr 15 Deutsch Brodersdorf Nieder\u00f6sterreich 2443",
    "addr:housenumber":"15",
    "addr:postcode":"2443",
    "addr:street":"Kreuzstr",
    "iso:country":"AT",
    "sg:address":"Kreuzstr 15",
    "sg:city":"Deutsch Brodersdorf",
    "sg:orig_category":"Architekten",
    "sg:phone":"+43 2255 6390",
    "sg:postcode":"2443",
    "sg:province":"Nieder\u00f6sterreich",
    "wof:name":"Kopinits Rudolf Arch Dipl-Ing",
    "wof:placetype":"venue"
},
  "geometry": {"coordinates":[16.4779834747,47.9344291687],"type":"Point"}
}