{
  "type": "Feature",
  "properties": {
    "addr:full":"Mitterberg 3 Haibach ob der Donau Ober\u00f6sterreich 4083",
    "addr:housenumber":"3",
    "addr:postcode":"4083",
    "addr:street":"Mitterberg",
    "iso:country":"AT",
    "sg:address":"Mitterberg 3",
    "sg:city":"Haibach ob der Donau",
    "sg:orig_category":"Pensionen / Privatzimmer",
    "sg:phone":"+43 4372 798241",
    "sg:postcode":"4083",
    "sg:province":"Ober\u00f6sterreich",
    "wof:name":"Gugler GmbH & Co KG",
    "wof:placetype":"venue"
},
  "geometry": {"coordinates":[13.9162130356,48.4099349976],"type":"Point"}
}