{
  "type": "Feature",
  "properties": {
    "iso:country":"AT",
    "sg:address":"Nr 11",
    "sg:city":"Malta",
    "sg:orig_category":"Pensionen / Privatzimmer",
    "sg:phone":"+43 4347 33318",
    "sg:postcode":"9854",
    "sg:province":"K\u00e4rnten",
    "wof:name":"G\u00e4stehaus Truskaller",
    "wof:placetype":"venue"
},
  "geometry": {"coordinates":[13.5070009232,46.9543418884],"type":"Point"}
}