{
  "type": "Feature",
  "properties": {
    "iso:country":"AT",
    "sg:address":"Quellenstr 211-213",
    "sg:city":"Wien",
    "sg:orig_category":"Baumeister",
    "sg:phone":"+43 1 4082136",
    "sg:postcode":"1100",
    "sg:province":"Wien",
    "wof:name":"BESTA-BAU GmbH",
    "wof:placetype":"venue"
},
  "geometry": {"coordinates":[16.3587036133,48.1769752502],"type":"Point"}
}