{
  "type": "Feature",
  "properties": {
    "addr:full":"Tuchlauben 14 Wien Wien 1010",
    "addr:housenumber":"14",
    "addr:postcode":"1010",
    "addr:street":"Tuchlauben",
    "iso:country":"AT",
    "sg:address":"Tuchlauben 14",
    "sg:city":"Wien",
    "sg:orig_category":"Juweliere, Gold- U Silberschmiede",
    "sg:phone":"+43 4315 3511500",
    "sg:postcode":"1010",
    "sg:province":"Wien",
    "wof:name":"Sillam Henri J.",
    "wof:placetype":"venue"
},
  "geometry": {"coordinates":[16.3711624146,48.210483551],"type":"Point"}
}