{
  "type": "Feature",
  "properties": {
    "addr:full":"Sch\u00fcttaustr 14-18/Stg 13 Wien Wien 1220",
    "addr:housenumber":"14-18 / stg 13",
    "addr:postcode":"1220",
    "iso:country":"AT",
    "sg:address":"Sch\u00fcttaustr 14-18/Stg 13",
    "sg:city":"Wien",
    "sg:orig_category":"Glasereien",
    "sg:phone":"+43 1 2633735",
    "sg:postcode":"1220",
    "sg:province":"Wien",
    "wof:name":"Fisch Helmut",
    "wof:placetype":"venue"
},
  "geometry": {"coordinates":[16.444606781,48.2497138977],"type":"Point"}
}