{
  "type": "Feature",
  "properties": {
    "addr:full":"Nr 44 Feldkirchen in K\u00e4rnten K\u00e4rnten 9560",
    "addr:postcode":"9560",
    "addr:street":"Nr 44;Kaernten",
    "iso:country":"AT",
    "sg:address":"Nr 44",
    "sg:city":"Feldkirchen in K\u00e4rnten",
    "sg:orig_category":"Transportunternehmen",
    "sg:phone":"+43 4276 2381",
    "sg:postcode":"9560",
    "sg:province":"K\u00e4rnten",
    "wof:name":"M\u00fchlbacher Gerhard",
    "wof:placetype":"venue"
},
  "geometry": {"coordinates":[14.0920295715,46.7234268188],"type":"Point"}
}