{
  "type": "Feature",
  "properties": {
    "addr:full":"Europapl 2 Graz Steiermark 8020",
    "addr:housenumber":"2",
    "addr:postcode":"8020",
    "addr:street":"Europapl",
    "iso:country":"AT",
    "sg:address":"Europapl 2",
    "sg:city":"Graz",
    "sg:orig_category":"Ambulatorien",
    "sg:phone":"+43 316 711331",
    "sg:postcode":"8020",
    "sg:province":"Steiermark",
    "wof:name":"Zahnambulatorium d Versicherungsanstalt \u00f6sterr Eisenbahnen",
    "wof:placetype":"venue"
},
  "geometry": {"coordinates":[15.4175891876,47.0712242126],"type":"Point"}
}