{
  "type": "Feature",
  "properties": {
    "addr:full":"Zeppelinstr 1 Linz Ober\u00f6sterreich 4030",
    "addr:housenumber":"1",
    "addr:postcode":"4030",
    "addr:street":"Zeppelinstr",
    "iso:country":"AT",
    "sg:address":"Zeppelinstr 1",
    "sg:city":"Linz",
    "sg:orig_category":"Autovermietung",
    "sg:phone":"+43 732 3055300",
    "sg:postcode":"4030",
    "sg:province":"Ober\u00f6sterreich",
    "wof:name":"Sixt GmbH PKW und LKW Vermietung",
    "wof:placetype":"venue"
},
  "geometry": {"coordinates":[14.3213300705,48.2561721802],"type":"Point"}
}