{
  "type": "Feature",
  "properties": {
    "addr:full":"Erleng 3 Pernitz Nieder\u00f6sterreich 2763",
    "addr:housenumber":"3",
    "addr:postcode":"2763",
    "addr:street":"Erleng",
    "iso:country":"AT",
    "sg:address":"Erleng 3",
    "sg:city":"Pernitz",
    "sg:orig_category":"Handelsagenturen",
    "sg:phone":"+43 2632 73473",
    "sg:postcode":"2763",
    "sg:province":"Nieder\u00f6sterreich",
    "wof:name":"Kunstmann Andreas",
    "wof:placetype":"venue"
},
  "geometry": {"coordinates":[15.9626207352,47.8944244385],"type":"Point"}
}