{
  "type": "Feature",
  "properties": {
    "addr:full":"Kalvarienbergpl 2 Eisenstadt Burgenland 7000",
    "addr:housenumber":"2",
    "addr:postcode":"7000",
    "addr:street":"Kalvarienbergpl",
    "iso:country":"AT",
    "sg:address":"Kalvarienbergpl 2",
    "sg:city":"Eisenstadt",
    "sg:orig_category":"Glasereien",
    "sg:phone":"+43 4366 43560007",
    "sg:postcode":"7000",
    "sg:province":"Burgenland",
    "wof:name":"Sch\u00f6fbeck Walter",
    "wof:placetype":"venue"
},
  "geometry": {"coordinates":[16.5126171112,47.8455123901],"type":"Point"}
}