{
  "type": "Feature",
  "properties": {
    "addr:full":"Wilhelm Greil-Str 19 Innsbruck Tirol 6020",
    "addr:housenumber":"19",
    "addr:postcode":"6020",
    "addr:street":"Tirol",
    "iso:country":"AT",
    "sg:address":"Wilhelm Greil-Str 19",
    "sg:city":"Innsbruck",
    "sg:orig_category":"Autobusunternehmen",
    "sg:phone":"+43 512 581950",
    "sg:postcode":"6020",
    "sg:province":"Tirol",
    "wof:name":"Menardi Heinrich",
    "wof:placetype":"venue"
},
  "geometry": {"coordinates":[11.3968200684,47.2640457153],"type":"Point"}
}