{
  "type": "Feature",
  "properties": {
    "addr:full":"Gmundner Str 21 Stadl-Paura Ober\u00f6sterreich 4651",
    "addr:postcode":"4651",
    "addr:street":"Str 21 Stadl-Paura",
    "iso:country":"AT",
    "sg:address":"Gmundner Str 21",
    "sg:city":"Stadl-Paura",
    "sg:orig_category":"Tankstellen",
    "sg:phone":"+43 7245 32297",
    "sg:postcode":"4651",
    "sg:province":"Ober\u00f6sterreich",
    "wof:name":"BP Austria Marketing GmbH",
    "wof:placetype":"venue"
},
  "geometry": {"coordinates":[13.8738527298,48.0855674744],"type":"Point"}
}