{
  "type": "Feature",
  "properties": {
    "iso:country":"AT",
    "sg:address":"Nr 16",
    "sg:city":"Faistenau",
    "sg:orig_category":"Pensionen / Privatzimmer",
    "sg:phone":"+43 4362 24319",
    "sg:postcode":"5324",
    "sg:province":"Salzburg",
    "wof:name":"Vorderbaernau",
    "wof:placetype":"venue"
},
  "geometry": {"coordinates":[166.9221496582,-0.5282999873],"type":"Point"}
}