{
  "type": "Feature",
  "properties": {
    "addr:full":"Ludwig Walter-Str 56 Villach K\u00e4rnten 9500",
    "addr:housenumber":"56",
    "addr:postcode":"9500",
    "addr:street":"Kaernten",
    "iso:country":"AT",
    "sg:address":"Ludwig Walter-Str 56",
    "sg:city":"Villach",
    "sg:orig_category":"Juwelen, Gold- U Silberwaren / Einzelhandel",
    "sg:phone":"+43 4242 32809",
    "sg:postcode":"9500",
    "sg:province":"K\u00e4rnten",
    "wof:name":"Schweiger Juwelier HandelsgesmbH",
    "wof:placetype":"venue"
},
  "geometry": {"coordinates":[13.8581876755,46.6069297791],"type":"Point"}
}