{
  "type": "Feature",
  "properties": {
    "addr:full":"Wiener Str 55 Amstetten Nieder\u00f6sterreich 3300",
    "addr:postcode":"3300",
    "addr:street":"Niederoesterreich",
    "iso:country":"AT",
    "sg:address":"Wiener Str 55",
    "sg:city":"Amstetten",
    "sg:orig_category":"Weiterbildungsinstitute M Allg U Berufl Bildungsangebot",
    "sg:phone":"+43 4374 7263338",
    "sg:postcode":"3300",
    "sg:province":"Nieder\u00f6sterreich",
    "wof:name":"Berufsf\u00f6rderungsinstitut N\u00f6 Regionalstelle",
    "wof:placetype":"venue"
},
  "geometry": {"coordinates":[14.8810396194,48.1230392456],"type":"Point"}
}