{
  "type": "Feature",
  "properties": {
    "iso:country":"AT",
    "sg:address":"Thimigg 46",
    "sg:city":"Wien",
    "sg:orig_category":"Geschenkartikel",
    "sg:phone":"+43 1 4791388",
    "sg:postcode":"1180",
    "sg:province":"Wien",
    "wof:name":"Becker Richard Dkfm Dr",
    "wof:placetype":"venue"
},
  "geometry": {"coordinates":[16.3235321045,48.2312469482],"type":"Point"}
}