{
  "type": "Feature",
  "properties": {
    "addr:full":"Nr 70 Bad Bleiberg K\u00e4rnten 9530",
    "addr:housenumber":"70",
    "addr:postcode":"9530",
    "addr:street":"Nr",
    "iso:country":"AT",
    "sg:address":"Nr 70",
    "sg:city":"Bad Bleiberg",
    "sg:orig_category":"Pensionen / Privatzimmer",
    "sg:phone":"+43 4244 2520",
    "sg:postcode":"9530",
    "sg:province":"K\u00e4rnten",
    "wof:name":"Mayer Reinhard",
    "wof:placetype":"venue"
},
  "geometry": {"coordinates":[166.9221496582,-0.5282999873],"type":"Point"}
}