{
  "type": "Feature",
  "properties": {
    "addr:full":"Dr.-Rudolf-Schuh-Str 29 Seewalchen am Attersee Ober\u00f6sterreich 4863",
    "addr:housenumber":"29",
    "addr:postcode":"4863",
    "addr:street":"Dr.-Rudolf-Schuh-Str",
    "iso:country":"AT",
    "sg:address":"Dr.-Rudolf-Schuh-Str 29",
    "sg:city":"Seewalchen am Attersee",
    "sg:orig_category":"Hausbetreuung",
    "sg:phone":"+43 4376 623262",
    "sg:postcode":"4863",
    "sg:province":"Ober\u00f6sterreich",
    "wof:name":"SHS Klein & Partner KEG",
    "wof:placetype":"venue"
},
  "geometry": {"coordinates":[13.5768938065,47.9523849487],"type":"Point"}
}