{
  "type": "Feature",
  "properties": {
    "addr:full":"Lahn 47 Wald im Pinzgau Salzburg 5742",
    "addr:housenumber":"47",
    "addr:postcode":"5742",
    "addr:street":"Lahn",
    "iso:country":"AT",
    "sg:address":"Lahn 47",
    "sg:city":"Wald im Pinzgau",
    "sg:orig_category":"Pensionen / Privatzimmer",
    "sg:phone":"+43 6565 8300",
    "sg:postcode":"5742",
    "sg:province":"Salzburg",
    "wof:name":"Pension Kaserer",
    "wof:placetype":"venue"
},
  "geometry": {"coordinates":[12.2023334503,47.2466621399],"type":"Point"}
}