{
  "type": "Feature",
  "properties": {
    "iso:country":"AT",
    "sg:address":"Heiligenst\u00e4dter Str 51",
    "sg:city":"Wien",
    "sg:orig_category":"Wasseraufbereitung U -Reinigung",
    "sg:phone":"+43 1 6986550",
    "sg:postcode":"1190",
    "sg:province":"Wien",
    "wof:name":"Berkefeld-Zuckriegl-Wassertechnik GmbH",
    "wof:placetype":"venue"
},
  "geometry": {"coordinates":[16.3583393097,48.2385749817],"type":"Point"}
}