{
  "type": "Feature",
  "properties": {
    "addr:full":"Wiener Str 176 M\u00fcrzzuschlag Steiermark 8680",
    "addr:housenumber":"176",
    "addr:postcode":"8680",
    "addr:street":"Muerzzuschlag Steiermark",
    "iso:country":"AT",
    "sg:address":"Wiener Str 176",
    "sg:city":"M\u00fcrzzuschlag",
    "sg:orig_category":"Boutiquen",
    "sg:phone":"+43 3852 5227",
    "sg:postcode":"8680",
    "sg:province":"Steiermark",
    "wof:name":"Boutique Susi Inh Susanne Valant",
    "wof:placetype":"venue"
},
  "geometry": {"coordinates":[16.3542709351,48.159198761],"type":"Point"}
}