{
  "type": "Feature",
  "properties": {
    "addr:full":"Industriestr 17 Traiskirchen Nieder\u00f6sterreich 2514",
    "addr:housenumber":"17",
    "addr:postcode":"2514",
    "addr:street":"Industriestr;Niederoesterreich",
    "iso:country":"AT",
    "sg:address":"Industriestr 17",
    "sg:city":"Traiskirchen",
    "sg:orig_category":"Physiotherapie",
    "sg:phone":"+43 2252 53951",
    "sg:postcode":"2514",
    "sg:province":"Nieder\u00f6sterreich",
    "wof:name":"Necker Doris Dipl-PT",
    "wof:placetype":"venue"
},
  "geometry": {"coordinates":[16.2946929932,48.0217933655],"type":"Point"}
}