{
  "type": "Feature",
  "properties": {
    "addr:full":"Stiftstr 1 Aschach an der Donau Ober\u00f6sterreich 4082",
    "addr:housenumber":"1",
    "addr:postcode":"4082",
    "addr:street":"Stiftstr",
    "iso:country":"AT",
    "sg:address":"Stiftstr 1",
    "sg:city":"Aschach an der Donau",
    "sg:classifiers":[
        {
            "category":"Restaurant",
            "type":"Food & Drink"
        }
    ],
    "sg:phone":"+43 7273 7144",
    "sg:postcode":"4082",
    "sg:province":"Ober\u00f6sterreich",
    "sg:tags":[
        "pizzeria"
    ],
    "wof:name":"Pizzeria La Mamma",
    "wof:placetype":"venue"
},
  "geometry": {"coordinates":[14.0231342316,48.3635444641],"type":"Point"}
}