{
  "type": "Feature",
  "properties": {
    "addr:full":"Heldendankstr 5 Bregenz Vorarlberg 6900",
    "addr:housenumber":"5",
    "addr:postcode":"6900",
    "addr:street":"Heldendankstr",
    "iso:country":"AT",
    "sg:address":"Heldendankstr 5",
    "sg:city":"Bregenz",
    "sg:orig_category":"Transportunternehmen",
    "sg:phone":"+43 5574 480300",
    "sg:postcode":"6900",
    "sg:province":"Vorarlberg",
    "wof:name":"Securitas Werttransporte GmbH",
    "wof:placetype":"venue"
},
  "geometry": {"coordinates":[9.7307577133,47.4991264343],"type":"Point"}
}