{
  "type": "Feature",
  "properties": {
    "addr:full":"Gf\u00f6hler Str 53 Sulz im Wienerwald Nieder\u00f6sterreich 2392",
    "addr:housenumber":"53",
    "addr:postcode":"2392",
    "addr:street":"Str",
    "iso:country":"AT",
    "sg:address":"Gf\u00f6hler Str 53",
    "sg:city":"Sulz im Wienerwald",
    "sg:orig_category":"Transportunternehmen",
    "sg:phone":"+43 676 9284465",
    "sg:postcode":"2392",
    "sg:province":"Nieder\u00f6sterreich",
    "wof:name":"Nirschl Norbert KEG",
    "wof:placetype":"venue"
},
  "geometry": {"coordinates":[16.1391887665,48.1020393372],"type":"Point"}
}