{
  "type": "Feature",
  "properties": {
    "addr:full":"Sigmund-Thun-Str 16/6 Hallein Salzburg 5400",
    "addr:housenumber":"16 / 6",
    "addr:postcode":"5400",
    "addr:street":"Sigmund-Thun-Str;Salzburg",
    "iso:country":"AT",
    "sg:address":"Sigmund-Thun-Str 16/6",
    "sg:city":"Hallein",
    "sg:orig_category":"Psychotherapie",
    "sg:phone":"+43 6245 78246",
    "sg:postcode":"5400",
    "sg:province":"Salzburg",
    "wof:name":"Moisl Ulrike Mag",
    "wof:placetype":"venue"
},
  "geometry": {"coordinates":[13.0959501266,47.6826057434],"type":"Point"}
}