{
  "type": "Feature",
  "properties": {
    "addr:full":"Krottendorf 10a Kapfenberg Steiermark 8605",
    "addr:housenumber":"10a",
    "addr:postcode":"8605",
    "addr:street":"Krottendorf",
    "iso:country":"AT",
    "sg:address":"Krottendorf 10a",
    "sg:city":"Kapfenberg",
    "sg:orig_category":"Bauunternehmen",
    "sg:phone":"+43 4350 6260",
    "sg:postcode":"8605",
    "sg:province":"Steiermark",
    "wof:name":"Allgemeine Baugesellschaft A Porr AG",
    "wof:placetype":"venue"
},
  "geometry": {"coordinates":[15.3295631409,47.4527549744],"type":"Point"}
}