{
  "type": "Feature",
  "properties": {
    "addr:full":"Nr 165 Neuhaus am Klausenbach Burgenland 8385",
    "addr:postcode":"8385",
    "addr:street":"Nr 165",
    "iso:country":"AT",
    "sg:address":"Nr 165",
    "sg:city":"Neuhaus am Klausenbach",
    "sg:orig_category":"Gemeinden",
    "sg:phone":"+43 3329 30031",
    "sg:postcode":"8385",
    "sg:province":"Burgenland",
    "wof:name":"Gemeinde M\u00fchlgraben",
    "wof:placetype":"venue"
},
  "geometry": {"coordinates":[16.0319595337,46.8701591492],"type":"Point"}
}