{
  "type": "Feature",
  "properties": {
    "addr:full":"Paulustorg 2 Graz Steiermark 8010",
    "addr:housenumber":"2",
    "addr:postcode":"8010",
    "addr:street":"Paulustorg",
    "iso:country":"AT",
    "sg:address":"Paulustorg 2",
    "sg:city":"Graz",
    "sg:orig_category":"Tabaktrafiken",
    "sg:phone":"+43 316 825616",
    "sg:postcode":"8010",
    "sg:province":"Steiermark",
    "wof:name":"Tautter Mario",
    "wof:placetype":"venue"
},
  "geometry": {"coordinates":[15.4401636124,47.0740852356],"type":"Point"}
}