{
  "type": "Feature",
  "properties": {
    "iso:country":"AT",
    "sg:address":"Bayrhamerpl 8",
    "sg:city":"Hallein",
    "sg:orig_category":"Galerien",
    "sg:phone":"+43 6245 87389",
    "sg:postcode":"5400",
    "sg:province":"Salzburg",
    "wof:name":"1Blick - Minigalerie im Vorhaus",
    "wof:placetype":"venue"
},
  "geometry": {"coordinates":[13.0945444107,47.6821975708],"type":"Point"}
}