{
  "type": "Feature",
  "properties": {
    "addr:full":"Marchfeldstr 19 Wien Wien 1200",
    "addr:housenumber":"19",
    "addr:postcode":"1200",
    "addr:street":"Marchfeldstr",
    "iso:country":"AT",
    "sg:address":"Marchfeldstr 19",
    "sg:city":"Wien",
    "sg:orig_category":"Optiker",
    "sg:phone":"+43 1 3303217",
    "sg:postcode":"1200",
    "sg:province":"Wien",
    "wof:name":"Vrana Rudolf",
    "wof:placetype":"venue"
},
  "geometry": {"coordinates":[16.3782501221,48.2423477173],"type":"Point"}
}