{
  "type": "Feature",
  "properties": {
    "iso:country":"AT",
    "sg:address":"Hauptstr 43",
    "sg:city":"Guntramsdorf",
    "sg:orig_category":"Biologische Produkte",
    "sg:phone":"+43 2236 52009",
    "sg:postcode":"2353",
    "sg:province":"Nieder\u00f6sterreich",
    "wof:name":"Biohof Broschek",
    "wof:placetype":"venue"
},
  "geometry": {"coordinates":[16.3139533997,48.0491867065],"type":"Point"}
}