{
  "type": "Feature",
  "properties": {
    "addr:full":"Bahnhofstr 245 Neulengbach Nieder\u00f6sterreich 3040",
    "addr:housenumber":"245",
    "addr:postcode":"3040",
    "addr:street":"Bahnhofstr",
    "iso:country":"AT",
    "sg:address":"Bahnhofstr 245",
    "sg:city":"Neulengbach",
    "sg:classifiers":[
        {
            "category":"Home & Garden",
            "subcategory":"Building Materials",
            "type":"Retail Goods"
        }
    ],
    "sg:phone":"+43 2772 52524133",
    "sg:postcode":"3040",
    "sg:province":"Nieder\u00f6sterreich",
    "sg:tags":[
        "baustoffe",
        "-material",
        "u"
    ],
    "wof:name":"Raiffeisen-Lagerhaus Tulln-Neulengbach",
    "wof:placetype":"venue"
},
  "geometry": {"coordinates":[15.9079504013,48.1976547241],"type":"Point"}
}