{
  "type": "Feature",
  "properties": {
    "iso:country":"AT",
    "sg:address":"Obere Augartenstr 5",
    "sg:city":"Wien",
    "sg:orig_category":"Lebensmittel / Einzelhandel",
    "sg:phone":"+43 1 2163979",
    "sg:postcode":"1020",
    "sg:province":"Wien",
    "wof:name":"Hofer KG",
    "wof:placetype":"venue"
},
  "geometry": {"coordinates":[16.3805980682,48.2192497253],"type":"Point"}
}