{
  "type": "Feature",
  "properties": {
    "addr:full":"Kalkgruberweg 1 Linz Ober\u00f6sterreich 4040",
    "addr:housenumber":"1",
    "addr:postcode":"4040",
    "addr:street":"Kalkgruberweg",
    "iso:country":"AT",
    "sg:address":"Kalkgruberweg 1",
    "sg:city":"Linz",
    "sg:orig_category":"Betten",
    "sg:phone":"+43 4373 2244848",
    "sg:postcode":"4040",
    "sg:province":"Ober\u00f6sterreich",
    "wof:name":"Das Pflegezimmer Handels- u Service GmbH",
    "wof:placetype":"venue"
},
  "geometry": {"coordinates":[14.3422966003,48.338558197],"type":"Point"}
}