{
  "type": "Feature",
  "properties": {
    "addr:full":"Bundesstrasse 2+4 Koblach Vorarlberg 6842",
    "addr:housenumber":"2 + 4",
    "addr:postcode":"6842",
    "addr:street":"Bundesstrasse",
    "iso:country":"AT",
    "sg:address":"Bundesstrasse 2+4",
    "sg:city":"Koblach",
    "sg:orig_category":"ChildrenS Furniture",
    "sg:phone":"+43 5523 623740",
    "sg:postcode":"6842",
    "sg:province":"Vorarlberg",
    "sg:website":"schwab.at",
    "wof:name":"Schwab GmbH & Co KG",
    "wof:placetype":"venue"
},
  "geometry": {"coordinates":[9.6302700043,47.3260688782],"type":"Point"}
}