{
  "type": "Feature",
  "properties": {
    "addr:full":"Thanner Str 58 Sieding-Stixenstein Nieder\u00f6sterreich 2631",
    "addr:postcode":"2631",
    "addr:street":"Str 58 Sieding-Stixenstein",
    "iso:country":"AT",
    "sg:address":"Thanner Str 58",
    "sg:city":"Sieding-Stixenstein",
    "sg:orig_category":"Immobilienmakler",
    "sg:phone":"+43 2630 33333",
    "sg:postcode":"2631",
    "sg:province":"Nieder\u00f6sterreich",
    "wof:name":"INTERIMMOBILIA - Kurt Egger",
    "wof:placetype":"venue"
},
  "geometry": {"coordinates":[15.975689888,47.7375259399],"type":"Point"}
}