{
  "type": "Feature",
  "properties": {
    "addr:full":"Dorfstr 21 Westendorf Tirol 6363",
    "addr:housenumber":"21",
    "addr:postcode":"6363",
    "addr:street":"Dorfstr;Tirol",
    "iso:country":"AT",
    "sg:address":"Dorfstr 21",
    "sg:city":"Westendorf",
    "sg:orig_category":"\u00c3\u201erzte / F Allgemeinmedizin",
    "sg:phone":"+43 5334 6727",
    "sg:postcode":"6363",
    "sg:province":"Tirol",
    "wof:name":"Graser Ludwig Dr",
    "wof:placetype":"venue"
},
  "geometry": {"coordinates":[12.2162599564,47.4346313477],"type":"Point"}
}