{
  "type": "Feature",
  "properties": {
    "iso:country":"AT",
    "sg:address":"Industriestrasse 2",
    "sg:city":"\u00d6tztal Bahnhof",
    "sg:orig_category":"Expansion Joint Metal Capping Strips",
    "sg:phone":"+43 5266 8911",
    "sg:postcode":"6430",
    "sg:province":"Tirol",
    "wof:name":"Eisen Oberland GmbH & Co KG",
    "wof:placetype":"venue"
},
  "geometry": {"coordinates":[8.3679151535,51.0343704224],"type":"Point"}
}