{
  "type": "Feature",
  "properties": {
    "iso:country":"AT",
    "sg:address":"Bahnhofweg 7",
    "sg:city":"Liezen",
    "sg:orig_category":"Geschenkartikel",
    "sg:phone":"+43 3612 23157",
    "sg:postcode":"8940",
    "sg:province":"Steiermark",
    "wof:name":"STRECANSKY KRISTALLGLAS und PORZELLANWAREN - Export-Import",
    "wof:placetype":"venue"
},
  "geometry": {"coordinates":[14.2428703308,47.5637741089],"type":"Point"}
}