{
  "type": "Feature",
  "properties": {
    "addr:full":"Doblergasse 3 Graz Steiermark 8020",
    "addr:housenumber":"3",
    "addr:postcode":"8020",
    "addr:street":"Doblergasse",
    "iso:country":"AT",
    "sg:address":"Doblergasse 3",
    "sg:city":"Graz",
    "sg:classifiers":[
        {
            "category":"Professional",
            "subcategory":"Art Services",
            "type":"Services"
        }
    ],
    "sg:phone":"+43 316 91923435",
    "sg:postcode":"8020",
    "sg:province":"Steiermark",
    "sg:tags":[
        "product",
        "design"
    ],
    "sg:website":"www.xform.at",
    "wof:name":"xform - Petrus Gartler",
    "wof:placetype":"venue"
},
  "geometry": {"coordinates":[15.4244565964,47.0730514526],"type":"Point"}
}