{
  "type": "Feature",
  "properties": {
    "addr:full":"Nokiaweg 1 Eisenstadt Burgenland 7000",
    "addr:housenumber":"1",
    "addr:postcode":"7000",
    "addr:street":"Nokiaweg",
    "iso:country":"AT",
    "sg:address":"Nokiaweg 1",
    "sg:city":"Eisenstadt",
    "sg:orig_category":"Telekommunikation",
    "sg:phone":"+43 2682 7710",
    "sg:postcode":"7000",
    "sg:province":"Burgenland",
    "wof:name":"Nokia Austria GmbH - Networks",
    "wof:placetype":"venue"
},
  "geometry": {"coordinates":[16.5324954987,47.8301010132],"type":"Point"}
}