{
  "type": "Feature",
  "properties": {
    "addr:full":"Kircheng 22 Wartberg im M\u00fcrztal Steiermark 8661",
    "addr:housenumber":"22",
    "addr:postcode":"8661",
    "addr:street":"Kircheng",
    "iso:country":"AT",
    "sg:address":"Kircheng 22",
    "sg:city":"Wartberg im M\u00fcrztal",
    "sg:orig_category":"Unternehmensberatung",
    "sg:phone":"+43 3858 2395",
    "sg:postcode":"8661",
    "sg:province":"Steiermark",
    "wof:name":"Jurak Dr Consulting GmbH",
    "wof:placetype":"venue"
},
  "geometry": {"coordinates":[15.4888601303,47.5246696472],"type":"Point"}
}