{
  "type": "Feature",
  "properties": {
    "addr:full":"Pfarrgasse 2 Friesach K\u00e4rnten 9360",
    "addr:housenumber":"2",
    "addr:postcode":"9360",
    "addr:street":"Pfarrgasse;Kaernten",
    "iso:country":"AT",
    "sg:address":"Pfarrgasse 2",
    "sg:city":"Friesach",
    "sg:classifiers":[
        {
            "category":"Utilities",
            "subcategory":"Fuel Oil & Lpg",
            "type":"Services"
        }
    ],
    "sg:phone":"+43 4268 2042",
    "sg:postcode":"9360",
    "sg:province":"K\u00e4rnten",
    "sg:tags":[
        "dental",
        "product"
    ],
    "wof:name":"Werner Marcher Zahntechnisches Labor Ges.m.b.H.",
    "wof:placetype":"venue"
},
  "geometry": {"coordinates":[14.4063367844,46.9512672424],"type":"Point"}
}