{
  "type": "Feature",
  "properties": {
    "iso:country":"AT",
    "sg:address":"Innsbrucker Str 36a",
    "sg:city":"Hall in Tirol",
    "sg:orig_category":"Antriebstechnik",
    "sg:phone":"+43 5223 42224",
    "sg:postcode":"6060",
    "sg:province":"Tirol",
    "wof:name":"AFK Maschinenbau",
    "wof:placetype":"venue"
},
  "geometry": {"coordinates":[11.4941167831,47.2781143188],"type":"Point"}
}