{
  "type": "Feature",
  "properties": {
    "addr:full":"Wendling Wendling Ober\u00f6sterreich 4741",
    "addr:postcode":"4741",
    "iso:country":"AT",
    "sg:address":"Wendling",
    "sg:city":"Wendling",
    "sg:orig_category":"Feuerwehren",
    "sg:phone":"+43 7736 6070",
    "sg:postcode":"4741",
    "sg:province":"Ober\u00f6sterreich",
    "wof:name":"Freiwillige Feuerwehr Wendling",
    "wof:placetype":"venue"
},
  "geometry": {"coordinates":[13.6804189682,48.2285614014],"type":"Point"}
}