{
  "type": "Feature",
  "properties": {
    "iso:country":"AT",
    "sg:address":"Rotschernweg 8",
    "sg:city":"Obertrum am See",
    "sg:orig_category":"Datenverarbeitung",
    "sg:phone":"+43 6219 8327",
    "sg:postcode":"5162",
    "sg:province":"Salzburg",
    "wof:name":"Almer Gerhard",
    "wof:placetype":"venue"
},
  "geometry": {"coordinates":[13.0849370956,47.9389305115],"type":"Point"}
}