{
  "type": "Feature",
  "properties": {
    "addr:full":"Zeiselweg 2-6 Tulln an der Donau Nieder\u00f6sterreich 3430",
    "addr:housenumber":"2-6",
    "addr:postcode":"3430",
    "addr:street":"Zeiselweg",
    "iso:country":"AT",
    "sg:address":"Zeiselweg 2-6",
    "sg:city":"Tulln an der Donau",
    "sg:orig_category":"Zahngesundheitsvorsorge",
    "sg:phone":"+43 2272 624832060",
    "sg:postcode":"3430",
    "sg:province":"Nieder\u00f6sterreich",
    "wof:name":"Zahnambulatorium der N\u00f6 Gebietskrankenkasse Tulln",
    "wof:placetype":"venue"
},
  "geometry": {"coordinates":[16.0549068451,48.3263473511],"type":"Point"}
}