{
  "type": "Feature",
  "properties": {
    "addr:full":"Andritzer Reichsstr 58b/17 Andritz Steiermark 8045",
    "addr:housenumber":"58b / 17",
    "addr:postcode":"8045",
    "iso:country":"AT",
    "sg:address":"Andritzer Reichsstr 58b/17",
    "sg:city":"Andritz",
    "sg:orig_category":"Ingenieurkonsulenten / Zivilingenieure",
    "sg:phone":"+43 4331 6695347",
    "sg:postcode":"8045",
    "sg:province":"Steiermark",
    "wof:name":"Diplomingenieure Dieter Depisch u Silvia Kerschbaumer-Depisch Ziviltechniker GmbH",
    "wof:placetype":"venue"
},
  "geometry": {"coordinates":[15.4207439423,47.1056060791],"type":"Point"}
}