{
  "type": "Feature",
  "properties": {
    "addr:full":"Kaiser-Franz-Ring 10 Baden Nieder\u00f6sterreich 2500",
    "addr:housenumber":"10",
    "addr:postcode":"2500",
    "addr:street":"Kaiser-Franz-Ring;Niederoesterreich",
    "iso:country":"AT",
    "sg:address":"Kaiser-Franz-Ring 10",
    "sg:city":"Baden",
    "sg:classifiers":[
        {
            "category":"Travel",
            "subcategory":"Hotels & Motels",
            "type":"Entertainment"
        }
    ],
    "sg:phone":"+43 2252 87297",
    "sg:postcode":"2500",
    "sg:province":"Nieder\u00f6sterreich",
    "wof:name":"Hotel Herzoghof",
    "wof:placetype":"venue"
},
  "geometry": {"coordinates":[16.2333545685,48.0097045898],"type":"Point"}
}