{
  "type": "Feature",
  "properties": {
    "addr:full":"Kreuzg 6 Lienz Tirol 9900",
    "addr:housenumber":"6",
    "addr:postcode":"9900",
    "addr:street":"Kreuzg;Tirol",
    "iso:country":"AT",
    "sg:address":"Kreuzg 6",
    "sg:city":"Lienz",
    "sg:orig_category":"Bergsportartikel",
    "sg:phone":"+43 4852 620502",
    "sg:postcode":"9900",
    "sg:province":"Tirol",
    "wof:name":"Bergsport Gassler",
    "wof:placetype":"venue"
},
  "geometry": {"coordinates":[12.7642650604,46.8295173645],"type":"Point"}
}