{
  "type": "Feature",
  "properties": {
    "iso:country":"AT",
    "sg:address":"Salomong 20A",
    "sg:city":"Wien",
    "sg:orig_category":"Feldenkraismethode",
    "sg:phone":"+43 699 10149448",
    "sg:postcode":"1210",
    "sg:province":"Wien",
    "wof:name":"Schwent Alois",
    "wof:placetype":"venue"
},
  "geometry": {"coordinates":[16.423324585,48.2861442566],"type":"Point"}
}