{
  "type": "Feature",
  "properties": {
    "addr:full":"Theaterpl 3 Friesach K\u00e4rnten 9360",
    "addr:housenumber":"3",
    "addr:postcode":"9360",
    "addr:street":"Theaterpl;Kaernten",
    "iso:country":"AT",
    "sg:address":"Theaterpl 3",
    "sg:city":"Friesach",
    "sg:orig_category":"Glasereien",
    "sg:phone":"+43 4268 2405",
    "sg:postcode":"9360",
    "sg:province":"K\u00e4rnten",
    "wof:name":"Glas Heifler GesmbH & Co KG",
    "wof:placetype":"venue"
},
  "geometry": {"coordinates":[14.4061584473,46.9493865967],"type":"Point"}
}