{
  "type": "Feature",
  "properties": {
    "addr:full":"Landstr 30 Gedersdorf Nieder\u00f6sterreich 3494",
    "addr:housenumber":"30",
    "addr:postcode":"3494",
    "addr:street":"Landstr",
    "iso:country":"AT",
    "sg:address":"Landstr 30",
    "sg:city":"Gedersdorf",
    "sg:orig_category":"Bauunternehmen",
    "sg:phone":"+43 2735 36393",
    "sg:postcode":"3494",
    "sg:province":"Nieder\u00f6sterreich",
    "wof:name":"S-Bau GmbH",
    "wof:placetype":"venue"
},
  "geometry": {"coordinates":[15.6880922318,48.4164237976],"type":"Point"}
}