{
  "type": "Feature",
  "properties": {
    "addr:full":"Herzog-Albrecht-Str 1-3/N07 Mistelbach Nieder\u00f6sterreich 2130",
    "addr:housenumber":"1-3 / n07",
    "addr:postcode":"2130",
    "addr:street":"Herzog-Albrecht-Str;Niederoesterreich",
    "iso:country":"AT",
    "sg:address":"Herzog-Albrecht-Str 1-3/N07",
    "sg:city":"Mistelbach",
    "sg:orig_category":"Bekleidung / Einzelhandel",
    "sg:phone":"+43 4325 7232399",
    "sg:postcode":"2130",
    "sg:province":"Nieder\u00f6sterreich",
    "wof:name":"C & A Mode GesmbH & Co KG - C & A Mode FMZ",
    "wof:placetype":"venue"
},
  "geometry": {"coordinates":[16.5724334717,48.5700798035],"type":"Point"}
}