{
  "type": "Feature",
  "properties": {
    "addr:full":"Nr 86 Patsch Tirol 6082",
    "addr:postcode":"6082",
    "addr:street":"Nr 86;Tirol",
    "iso:country":"AT",
    "sg:address":"Nr 86",
    "sg:city":"Patsch",
    "sg:classifiers":[
        {
            "category":"Taxi",
            "type":"Transportation"
        }
    ],
    "sg:phone":"+43 4366 42435365",
    "sg:postcode":"6082",
    "sg:province":"Tirol",
    "sg:tags":[
        "personentransporte",
        "u"
    ],
    "wof:name":"Mietwagen Klausi",
    "wof:placetype":"venue"
},
  "geometry": {"coordinates":[-103.4913406372,39.2801246643],"type":"Point"}
}