{
  "type": "Feature",
  "properties": {
    "iso:country":"AT",
    "sg:address":"Lagerhausstr 2a",
    "sg:city":"Dobersberg",
    "sg:orig_category":"Autohandel",
    "sg:phone":"+43 2843 2466",
    "sg:postcode":"3843",
    "sg:province":"Nieder\u00f6sterreich",
    "wof:name":"Autohaus Dobersberg - Landrover, MG, Daihatsu",
    "wof:placetype":"venue"
},
  "geometry": {"coordinates":[15.3277301788,48.9145469666],"type":"Point"}
}