{
  "type": "Feature",
  "properties": {
    "iso:country":"AT",
    "sg:address":"Hauptstr 20",
    "sg:city":"Lanzenkirchen",
    "sg:orig_category":"Friseure U Frisiersalons",
    "sg:phone":"+43 2627 45878",
    "sg:postcode":"2821",
    "sg:province":"Nieder\u00f6sterreich",
    "wof:name":"Frieseur Erni",
    "wof:placetype":"venue"
},
  "geometry": {"coordinates":[16.2390842438,47.742805481],"type":"Point"}
}