{
  "type": "Feature",
  "properties": {
    "iso:country":"AT",
    "sg:address":"Industriezeile 33a",
    "sg:city":"Linz",
    "sg:orig_category":"Transportbeton",
    "sg:phone":"+43 732 781123",
    "sg:postcode":"4020",
    "sg:province":"Ober\u00f6sterreich",
    "wof:name":"Lafarge Beton GmbH & Co KG",
    "wof:placetype":"venue"
},
  "geometry": {"coordinates":[14.3133993149,48.3160171509],"type":"Point"}
}