{
  "type": "Feature",
  "properties": {
    "addr:full":"Bundesstr 25 Spital am Semmering Steiermark 8684",
    "addr:housenumber":"25",
    "addr:postcode":"8684",
    "addr:street":"Bundesstr",
    "iso:country":"AT",
    "sg:address":"Bundesstr 25",
    "sg:city":"Spital am Semmering",
    "sg:orig_category":"Transportunternehmen",
    "sg:phone":"+43 3853 660",
    "sg:postcode":"8684",
    "sg:province":"Steiermark",
    "wof:name":"Reiterer Manfred",
    "wof:placetype":"venue"
},
  "geometry": {"coordinates":[15.7516307831,47.615688324],"type":"Point"}
}