{
  "type": "Feature",
  "properties": {
    "addr:full":"Paracelsusstr 11 Salzburg Salzburg 5020",
    "addr:housenumber":"11",
    "addr:postcode":"5020",
    "addr:street":"Paracelsusstr;Salzburg",
    "iso:country":"AT",
    "sg:address":"Paracelsusstr 11",
    "sg:city":"Salzburg",
    "sg:classifiers":[
        {
            "category":"Restaurant",
            "type":"Food & Drink"
        }
    ],
    "sg:phone":"+43 662 877629",
    "sg:postcode":"5020",
    "sg:province":"Salzburg",
    "sg:tags":[
        "pizzeria"
    ],
    "wof:name":"Rest-Pizzeria Intermezzo",
    "wof:placetype":"venue"
},
  "geometry": {"coordinates":[13.047627449,47.8087425232],"type":"Point"}
}