{
  "type": "Feature",
  "properties": {
    "addr:full":"Gewerbestr 10 St. Veit im Pongau Salzburg 5621",
    "addr:housenumber":"10",
    "addr:postcode":"5621",
    "addr:street":"Gewerbestr;Salzburg",
    "iso:country":"AT",
    "sg:address":"Gewerbestr 10",
    "sg:city":"St. Veit im Pongau",
    "sg:orig_category":"Erdarbeiten",
    "sg:phone":"+43 4364 154259",
    "sg:postcode":"5621",
    "sg:province":"Salzburg",
    "wof:name":"K\u00f6ssner GmbH & Co KG",
    "wof:placetype":"venue"
},
  "geometry": {"coordinates":[13.1690740585,47.3226470947],"type":"Point"}
}