{
  "type": "Feature",
  "properties": {
    "addr:full":"Wagramer Strasse 17-19 Wien Wien 1220",
    "addr:postcode":"17-19;1220",
    "addr:street":"Wagramer Strasse",
    "iso:country":"AT",
    "sg:address":"Wagramer Strasse 17-19",
    "sg:city":"Wien",
    "sg:classifiers":[
        {
            "category":"Manufacturing",
            "subcategory":"Soap",
            "type":"Manufacturing & Wholesale Goods"
        }
    ],
    "sg:phone":"+43 1 7188335",
    "sg:postcode":"1220",
    "sg:province":"Wien",
    "sg:tags":[
        "toilet",
        "soaps",
        "fancy"
    ],
    "sg:website":"colgate.at",
    "wof:name":"Colgate - Palmolive Ges.m.b.H.",
    "wof:placetype":"venue"
},
  "geometry": {"coordinates":[16.4672641754,48.2718505859],"type":"Point"}
}