{
  "type": "Feature",
  "properties": {
    "addr:full":"Schulstr 295 Feistritz an der Drau K\u00e4rnten 9710",
    "addr:housenumber":"295",
    "addr:postcode":"9710",
    "iso:country":"AT",
    "sg:address":"Schulstr 295",
    "sg:city":"Feistritz an der Drau",
    "sg:orig_category":"\u00c3\u201erzte / F Allgemeinmedizin",
    "sg:phone":"+43 4342 452360",
    "sg:postcode":"9710",
    "sg:province":"K\u00e4rnten",
    "wof:name":"Gatternig Herbert Dr",
    "wof:placetype":"venue"
},
  "geometry": {"coordinates":[13.6658649445,46.6946182251],"type":"Point"}
}