{
  "type": "Feature",
  "properties": {
    "addr:full":"Sonnberg 12 H\u00fcttau Salzburg 5511",
    "addr:housenumber":"12;5511",
    "addr:street":"Sonnberg",
    "iso:country":"AT",
    "sg:address":"Sonnberg 12",
    "sg:city":"H\u00fcttau",
    "sg:classifiers":[
        {
            "category":"Travel",
            "subcategory":"Hotels & Motels",
            "type":"Entertainment"
        }
    ],
    "sg:phone":"+43 6458 72400",
    "sg:postcode":"5511",
    "sg:province":"Salzburg",
    "wof:name":"Weitgasser & Co KG",
    "wof:placetype":"venue"
},
  "geometry": {"coordinates":[13.3277597427,47.4194602966],"type":"Point"}
}