{
  "type": "Feature",
  "properties": {
    "iso:country":"AT",
    "sg:address":"Hauptpl 3",
    "sg:city":"Liezen",
    "sg:orig_category":"Medizinische Institute",
    "sg:phone":"+43 4336 12251250",
    "sg:postcode":"8940",
    "sg:province":"Steiermark",
    "wof:name":"Computertomographieinstitut Liezen",
    "wof:placetype":"venue"
},
  "geometry": {"coordinates":[14.2422447205,47.5670051575],"type":"Point"}
}