{
  "type": "Feature",
  "properties": {
    "addr:full":"Kletschkag 8 St. Georgen am Steinfelde Nieder\u00f6sterreich 3151",
    "addr:housenumber":"8",
    "addr:postcode":"3151",
    "addr:street":"Kletschkag",
    "iso:country":"AT",
    "sg:address":"Kletschkag 8",
    "sg:city":"St. Georgen am Steinfelde",
    "sg:orig_category":"Biologische Produkte",
    "sg:phone":"+43 2742 884945",
    "sg:postcode":"3151",
    "sg:province":"Nieder\u00f6sterreich",
    "wof:name":"BIO-LADEN Heidemarie Br\u00e4uer",
    "wof:placetype":"venue"
},
  "geometry": {"coordinates":[15.6120681763,48.1405448914],"type":"Point"}
}