{
  "type": "Feature",
  "properties": {
    "addr:full":"Eichenweg 42 Imst Tirol 6460",
    "addr:housenumber":"42",
    "addr:postcode":"6460",
    "addr:street":"Eichenweg;Tirol",
    "iso:country":"AT",
    "sg:address":"Eichenweg 42",
    "sg:city":"Imst",
    "sg:orig_category":"Ingenieurkonsulenten / Zivilingenieure",
    "sg:phone":"+43 5412 62662",
    "sg:postcode":"6460",
    "sg:province":"Tirol",
    "sg:website":"members.aon.at/gstrein",
    "wof:name":"Gstrein Engelbert Dipl-Ing",
    "wof:placetype":"venue"
},
  "geometry": {"coordinates":[10.7440080643,47.2397193909],"type":"Point"}
}