{
  "type": "Feature",
  "properties": {
    "iso:country":"AT",
    "sg:address":"Wenger Str 10",
    "sg:city":"St. Veit im Pongau",
    "sg:orig_category":"Appartements / Ferienwohnungen",
    "sg:phone":"+43 4364 155694",
    "sg:postcode":"5621",
    "sg:province":"Salzburg",
    "wof:name":"Untergrub",
    "wof:placetype":"venue"
},
  "geometry": {"coordinates":[13.1008806229,47.3331336975],"type":"Point"}
}