{
  "type": "Feature",
  "properties": {
    "addr:full":"VOEST-Str 33 Leonding Ober\u00f6sterreich 4060",
    "addr:housenumber":"33",
    "addr:postcode":"4060",
    "addr:street":"Voest-Str",
    "iso:country":"AT",
    "sg:address":"VOEST-Str 33",
    "sg:city":"Leonding",
    "sg:classifiers":[
        {
            "category":"Professional",
            "subcategory":"Computer Services",
            "type":"Services"
        }
    ],
    "sg:phone":"+43 732 676081",
    "sg:postcode":"4060",
    "sg:province":"Ober\u00f6sterreich",
    "sg:tags":[
        "software"
    ],
    "wof:name":"Software Templ OEG",
    "wof:placetype":"venue"
},
  "geometry": {"coordinates":[14.2534122467,48.2443313599],"type":"Point"}
}