{
  "type": "Feature",
  "properties": {
    "addr:full":"L\u00e4rchenwiese 93 Maurach Tirol 6212",
    "addr:housenumber":"93",
    "addr:postcode":"6212",
    "addr:street":"Laerchenwiese",
    "iso:country":"AT",
    "sg:address":"L\u00e4rchenwiese 93",
    "sg:city":"Maurach",
    "sg:orig_category":"Baumeister",
    "sg:phone":"+43 5243 5406",
    "sg:postcode":"6212",
    "sg:province":"Tirol",
    "wof:name":"Kogler Peter Bmstr",
    "wof:placetype":"venue"
},
  "geometry": {"coordinates":[11.749461174,47.4206123352],"type":"Point"}
}