{
  "type": "Feature",
  "properties": {
    "iso:country":"AT",
    "sg:address":"Gumpendorfer Str 101",
    "sg:city":"Wien",
    "sg:orig_category":"Freizeit- U Sportbekleidung",
    "sg:phone":"+43 4315 966703",
    "sg:postcode":"1060",
    "sg:province":"Wien",
    "wof:name":"Sedlacek Norbert on tour GmbH",
    "wof:placetype":"venue"
},
  "geometry": {"coordinates":[16.3483200073,48.1917152405],"type":"Point"}
}