{
  "type": "Feature",
  "properties": {
    "iso:country":"AT",
    "sg:address":"Kreutzerstr 86",
    "sg:city":"Kindberg",
    "sg:classifiers":[
        {
            "category":"Taxi",
            "type":"Transportation"
        }
    ],
    "sg:phone":"+43 3865 36240",
    "sg:postcode":"8650",
    "sg:province":"Steiermark",
    "sg:tags":[
        "personentransporte",
        "u"
    ],
    "wof:name":"Hinterleitner Astrid",
    "wof:placetype":"venue"
},
  "geometry": {"coordinates":[15.434261322,47.5068206787],"type":"Point"}
}