{
  "type": "Feature",
  "properties": {
    "addr:full":"Nr 14 Br\u00fcckl K\u00e4rnten 9371",
    "addr:postcode":"9371",
    "addr:street":"Nr 14 Brueckl Kaernten",
    "iso:country":"AT",
    "sg:address":"Nr 14",
    "sg:city":"Br\u00fcckl",
    "sg:orig_category":"Holzhandel",
    "sg:phone":"+43 4214 2784",
    "sg:postcode":"9371",
    "sg:province":"K\u00e4rnten",
    "wof:name":"Zeiner Erich",
    "wof:placetype":"venue"
},
  "geometry": {"coordinates":[14.5317611694,46.7499198914],"type":"Point"}
}