{
  "type": "Feature",
  "properties": {
    "iso:country":"AT",
    "sg:address":"Kajetan-Sweth-Str 54",
    "sg:city":"Innsbruck",
    "sg:orig_category":"Raumausstattung",
    "sg:phone":"+43 512 266191",
    "sg:postcode":"6020",
    "sg:province":"Tirol",
    "wof:name":"Dibiasi Herbert",
    "wof:placetype":"venue"
},
  "geometry": {"coordinates":[11.4461812973,47.2702407837],"type":"Point"}
}