{
  "type": "Feature",
  "properties": {
    "addr:full":"Nr 44 Th\u00f6rl Steiermark 8621",
    "addr:postcode":"8621",
    "addr:street":"Nr 44 Thoerl Steiermark",
    "iso:country":"AT",
    "sg:address":"Nr 44",
    "sg:city":"Th\u00f6rl",
    "sg:orig_category":"Forstverwaltungen",
    "sg:phone":"+43 3868 8321",
    "sg:postcode":"8621",
    "sg:province":"Steiermark",
    "wof:name":"Forstgut Hubersting",
    "wof:placetype":"venue"
},
  "geometry": {"coordinates":[15.2327127457,47.5226593018],"type":"Point"}
}