{
  "type": "Feature",
  "properties": {
    "addr:full":"Franzosengraben 1 1034",
    "addr:housenumber":"1",
    "addr:postcode":"1034",
    "addr:street":"Franzosengraben",
    "iso:country":"AT",
    "sg:address":"Franzosengraben 1",
    "sg:classifiers":[
        {
            "category":"Utilities",
            "subcategory":"Electric",
            "type":"Services"
        }
    ],
    "sg:phone":"+43 4312 06340",
    "sg:postcode":"1034",
    "sg:tags":[
        "component",
        "electronic"
    ],
    "wof:name":"YOKOGAWA GMBH",
    "wof:placetype":"venue"
},
  "geometry": {"coordinates":[16.4162845612,48.1897354126],"type":"Point"}
}