{
  "type": "Feature",
  "properties": {
    "addr:full":"Laaer-Berg-Str 32 Wien Wien 1100",
    "addr:housenumber":"32",
    "addr:postcode":"1100",
    "addr:street":"Laaer-Berg-Str",
    "iso:country":"AT",
    "sg:address":"Laaer-Berg-Str 32",
    "sg:city":"Wien",
    "sg:orig_category":"Elektroinstallationsunternehmen",
    "sg:phone":"+43 4366 41033825",
    "sg:postcode":"1100",
    "sg:province":"Wien",
    "wof:name":"Wagner Walter",
    "wof:placetype":"venue"
},
  "geometry": {"coordinates":[16.3838920593,48.1691474915],"type":"Point"}
}