{
  "type": "Feature",
  "properties": {
    "iso:country":"AT",
    "sg:address":"Brucknerg 37",
    "sg:city":"Altheim",
    "sg:orig_category":"Blumeneinzelhandel",
    "sg:phone":"+43 4377 2342250",
    "sg:postcode":"4950",
    "sg:province":"Ober\u00f6sterreich",
    "wof:name":"Blumen, Pflanzen,Fleurop, Blumenbinderei - Elisabeth Bodenhofer",
    "wof:placetype":"venue"
},
  "geometry": {"coordinates":[13.2309036255,48.2532234192],"type":"Point"}
}