{
  "type": "Feature",
  "properties": {
    "addr:full":"Haunspergstr 39 Salzburg Salzburg 5020",
    "addr:housenumber":"39",
    "addr:postcode":"5020",
    "addr:street":"Haunspergstr;Salzburg",
    "iso:country":"AT",
    "sg:address":"Haunspergstr 39",
    "sg:city":"Salzburg",
    "sg:orig_category":"Behinderungen / Leben Mit Behinderungen",
    "sg:phone":"+43 662 4510440",
    "sg:postcode":"5020",
    "sg:province":"Salzburg",
    "wof:name":"\u00f6ZIV - \u00f6sterreichischer Zivil-Invalidenverband - Landesverband Salzburg",
    "wof:placetype":"venue"
},
  "geometry": {"coordinates":[13.0389204025,47.8150787354],"type":"Point"}
}