{
  "type": "Feature",
  "properties": {
    "addr:full":"Hofwieselgasse 22 Gerasdorf Nieder\u00f6sterreich 2201",
    "addr:housenumber":"22",
    "addr:postcode":"2201",
    "addr:street":"Hofwieselgasse",
    "iso:country":"AT",
    "sg:address":"Hofwieselgasse 22",
    "sg:city":"Gerasdorf",
    "sg:classifiers":[
        {
            "category":"Retail",
            "subcategory":"Laundry & Dry Cleaning",
            "type":"Services"
        }
    ],
    "sg:phone":"+43 2246 80460",
    "sg:postcode":"2201",
    "sg:province":"Nieder\u00f6sterreich",
    "sg:tags":[
        "neutralization",
        "odour",
        "agent",
        "biological"
    ],
    "sg:website":"bioclean.at",
    "wof:name":"Franz K. Michalek",
    "wof:placetype":"venue"
},
  "geometry": {"coordinates":[16.4795722961,48.3327941895],"type":"Point"}
}