{
  "type": "Feature",
  "properties": {
    "addr:full":"Zieglerg 8 Wien Wien 1070",
    "addr:housenumber":"8",
    "addr:postcode":"1070",
    "addr:street":"Zieglerg",
    "iso:country":"AT",
    "sg:address":"Zieglerg 8",
    "sg:city":"Wien",
    "sg:orig_category":"Wasch- U Reinigungsbedarf",
    "sg:phone":"+43 4315 2325010",
    "sg:postcode":"1070",
    "sg:province":"Wien",
    "wof:name":"Sch\u00fclke & Mayr GesmbH",
    "wof:placetype":"venue"
},
  "geometry": {"coordinates":[16.3456459045,48.1981239319],"type":"Point"}
}