{
  "type": "Feature",
  "properties": {
    "addr:full":"Schulg 11 Dornbirn Vorarlberg 6850",
    "addr:housenumber":"11",
    "addr:postcode":"6850",
    "addr:street":"Schulg",
    "iso:country":"AT",
    "sg:address":"Schulg 11",
    "sg:city":"Dornbirn",
    "sg:orig_category":"Gewerbeparks",
    "sg:phone":"+43 5572 24338",
    "sg:postcode":"6850",
    "sg:province":"Vorarlberg",
    "wof:name":"Stadtmarkt Dornbirn Einkaufszentrum",
    "wof:placetype":"venue"
},
  "geometry": {"coordinates":[9.7409343719,47.4124107361],"type":"Point"}
}