{
  "type": "Feature",
  "properties": {
    "addr:full":"Sportplatzstr 1 Ottensheim Ober\u00f6sterreich 4100",
    "addr:housenumber":"1",
    "addr:postcode":"4100",
    "addr:street":"Sportplatzstr",
    "iso:country":"AT",
    "sg:address":"Sportplatzstr 1",
    "sg:city":"Ottensheim",
    "sg:orig_category":"Restaurants: Chinesisch",
    "sg:phone":"+43 7234 84046",
    "sg:postcode":"4100",
    "sg:province":"Ober\u00f6sterreich",
    "wof:name":"China-Restaurant Lee Garden",
    "wof:placetype":"venue"
},
  "geometry": {"coordinates":[14.1833591461,48.3331565857],"type":"Point"}
}