{
  "type": "Feature",
  "properties": {
    "iso:country":"AT",
    "sg:address":"Wuhrwaldstr 12",
    "sg:city":"Hard",
    "sg:orig_category":"Webdesign",
    "sg:phone":"+43 664 3044786",
    "sg:postcode":"6971",
    "sg:province":"Vorarlberg",
    "wof:name":"PiranhaDesign",
    "wof:placetype":"venue"
},
  "geometry": {"coordinates":[9.7102012634,47.4903411865],"type":"Point"}
}