{
  "type": "Feature",
  "properties": {
    "iso:country":"AT",
    "sg:address":"Gasteiger Str 9",
    "sg:city":"Kirchdorf in Tirol",
    "sg:classifiers":[
        {
            "category":"Restaurant",
            "type":"Food & Drink"
        }
    ],
    "sg:phone":"+43 4353 5263353",
    "sg:postcode":"6382",
    "sg:province":"Tirol",
    "sg:tags":[
        "pizzeria"
    ],
    "wof:name":"Pizzeria Marco",
    "wof:placetype":"venue"
},
  "geometry": {"coordinates":[12.4436101913,47.5571060181],"type":"Point"}
}