{
  "type": "Feature",
  "properties": {
    "addr:full":"Annenstr 31 Graz Steiermark 8020",
    "addr:housenumber":"31",
    "addr:postcode":"8020",
    "addr:street":"Annenstr",
    "iso:country":"AT",
    "sg:address":"Annenstr 31",
    "sg:city":"Graz",
    "sg:orig_category":"Betten",
    "sg:phone":"+43 4331 6713153",
    "sg:postcode":"8020",
    "sg:province":"Steiermark",
    "wof:name":"Staudinger Wilhelm",
    "wof:placetype":"venue"
},
  "geometry": {"coordinates":[15.4269332886,47.0710105896],"type":"Point"}
}