{
  "type": "Feature",
  "properties": {
    "addr:full":"Puchberger Str 59 Wels Ober\u00f6sterreich 4600",
    "addr:housenumber":"59",
    "addr:postcode":"4600",
    "addr:street":"Str;Oberoesterreich",
    "iso:country":"AT",
    "sg:address":"Puchberger Str 59",
    "sg:city":"Wels",
    "sg:orig_category":"Handelsagenturen",
    "sg:phone":"+43 7242 42342",
    "sg:postcode":"4600",
    "sg:province":"Ober\u00f6sterreich",
    "wof:name":"H\u00f6ller Dieter",
    "wof:placetype":"venue"
},
  "geometry": {"coordinates":[14.0227279663,48.1817398071],"type":"Point"}
}