{
  "type": "Feature",
  "properties": {
    "iso:country":"AT",
    "sg:address":"Bahnhofstr 3",
    "sg:city":"Hermagor",
    "sg:orig_category":"Damenmoden",
    "sg:phone":"+43 4342 8225099",
    "sg:postcode":"9620",
    "sg:province":"K\u00e4rnten",
    "wof:name":"KiK Textilien u Non-Food GesmbH",
    "wof:placetype":"venue"
},
  "geometry": {"coordinates":[13.3739156723,46.6273345947],"type":"Point"}
}