{
  "type": "Feature",
  "properties": {
    "iso:country":"AT",
    "sg:address":"Werksgel\u00e4nde 26",
    "sg:orig_category":"Rohrleitungen U Rohrleitungsbau",
    "sg:phone":"+43 4364 628192",
    "sg:postcode":"5503",
    "wof:name":"Viper Tube Systems Rohrsysteme GmbH",
    "wof:placetype":"venue"
},
  "geometry": {"coordinates":[107.0046386719,27.0754508972],"type":"Point"}
}