{
  "type": "Feature",
  "properties": {
    "addr:full":"Ober-Laaer Strasse 222 Wien Wien 1100",
    "addr:housenumber":"222",
    "addr:postcode":"1100",
    "addr:street":"Ober-Laaer Strasse",
    "iso:country":"AT",
    "sg:address":"Ober-Laaer Strasse 222",
    "sg:city":"Wien",
    "sg:classifiers":[
        {
            "category":"Structure",
            "subcategory":"Tunnel",
            "type":"Public Place"
        }
    ],
    "sg:phone":"+43 1 68843320",
    "sg:postcode":"1100",
    "sg:province":"Wien",
    "sg:tags":[
        "catheter"
    ],
    "sg:website":"krainer-medtechnik.at",
    "wof:name":"Krainer Medtechnik HGMBH",
    "wof:placetype":"venue"
},
  "geometry": {"coordinates":[16.3819580078,48.1436347961],"type":"Point"}
}