{
  "type": "Feature",
  "properties": {
    "addr:full":"Klostermanngasse 8 Wien Wien 1230",
    "addr:housenumber":"8",
    "addr:postcode":"1230",
    "addr:street":"Klostermanngasse",
    "iso:country":"AT",
    "sg:address":"Klostermanngasse 8",
    "sg:city":"Wien",
    "sg:classifiers":[
        {
            "category":"Manufacturing",
            "subcategory":"Metals",
            "type":"Manufacturing & Wholesale Goods"
        }
    ],
    "sg:phone":"+43 1 8692350",
    "sg:postcode":"1230",
    "sg:province":"Wien",
    "sg:tags":[
        "hanger",
        "made",
        "clothes"
    ],
    "sg:website":"walter-weiss-wien.at",
    "wof:name":"Walter Weiss Gesch\u00e4ftseinrichtungen GmbH",
    "wof:placetype":"venue"
},
  "geometry": {"coordinates":[16.2957344055,48.1428794861],"type":"Point"}
}