{
  "type": "Feature",
  "properties": {
    "iso:country":"AT",
    "sg:address":"Welser Str 43",
    "sg:city":"Leonding",
    "sg:orig_category":"Restaurants: Japanisch",
    "sg:phone":"+43 732 670800",
    "sg:postcode":"4060",
    "sg:province":"Ober\u00f6sterreich",
    "wof:name":"OSAKA RUNNING SUSHI Restaurant GmbH",
    "wof:placetype":"venue"
},
  "geometry": {"coordinates":[14.2641916275,48.2666854858],"type":"Point"}
}