{
  "type": "Feature",
  "properties": {
    "addr:full":"Hauptstrasse 88 Sigmundsherberg Nieder\u00f6sterreich 3751",
    "addr:housenumber":"88",
    "addr:postcode":"3751",
    "addr:street":"Hauptstrasse",
    "iso:country":"AT",
    "sg:address":"Hauptstrasse 88",
    "sg:city":"Sigmundsherberg",
    "sg:classifiers":[
        {
            "category":"Professional",
            "subcategory":"Advertising",
            "type":"Services"
        }
    ],
    "sg:phone":"+43 2983 23300",
    "sg:postcode":"3751",
    "sg:province":"Nieder\u00f6sterreich",
    "sg:tags":[
        "product-related",
        "article",
        "marzipan",
        "chocolate"
    ],
    "sg:website":"sweetdeco.com",
    "wof:name":"HAB Handelsges.m.b.H.",
    "wof:placetype":"venue"
},
  "geometry": {"coordinates":[15.7347717285,48.6886177063],"type":"Point"}
}