{
  "type": "Feature",
  "properties": {
    "addr:full":"Walser Bundesstr. 273 Wals Salzburg 5071",
    "addr:housenumber":"273",
    "addr:postcode":"5071",
    "addr:street":"Wals Salzburg",
    "iso:country":"AT",
    "sg:address":"Walser Bundesstr. 273",
    "sg:city":"Wals",
    "sg:classifiers":[
        {
            "category":"Shopping",
            "subcategory":"Clothing, Apparel, & Fashions",
            "type":"Retail Goods"
        }
    ],
    "sg:phone":"+43 4366 289640",
    "sg:postcode":"5071",
    "sg:province":"Salzburg",
    "sg:tags":[
        "clothes"
    ],
    "wof:name":"HERVIS SPORT- U. MODE- GES.MBH",
    "wof:placetype":"venue"
},
  "geometry": {"coordinates":[12.975810051,47.7858772278],"type":"Point"}
}