{
  "type": "Feature",
  "properties": {
    "iso:country":"AT",
    "sg:address":"Dorfpl 301",
    "sg:city":"Prutz",
    "sg:orig_category":"Bankomat-Standorte",
    "sg:phone":"+43 5472 63760",
    "sg:postcode":"6522",
    "sg:province":"Tirol",
    "wof:name":"Bankomat d Raiffeisenbank Oberland regGenmbH",
    "wof:placetype":"venue"
},
  "geometry": {"coordinates":[10.6634502411,47.0656585693],"type":"Point"}
}