{
  "type": "Feature",
  "properties": {
    "addr:full":"Hauserg 39 Villach K\u00e4rnten 9500",
    "addr:housenumber":"39",
    "addr:postcode":"9500",
    "addr:street":"Hauserg;Kaernten",
    "iso:country":"AT",
    "sg:address":"Hauserg 39",
    "sg:city":"Villach",
    "sg:orig_category":"Psychotherapie",
    "sg:phone":"+43 4242 264192",
    "sg:postcode":"9500",
    "sg:province":"K\u00e4rnten",
    "wof:name":"Ostermann Barbara Mag phil",
    "wof:placetype":"venue"
},
  "geometry": {"coordinates":[13.848069191,46.6075210571],"type":"Point"}
}