{
  "type": "Feature",
  "properties": {
    "addr:full":"Erlach 163 Steinach am Brenner Tirol 6150",
    "addr:housenumber":"163",
    "addr:postcode":"6150",
    "addr:street":"Erlach;Tirol",
    "iso:country":"AT",
    "sg:address":"Erlach 163",
    "sg:city":"Steinach am Brenner",
    "sg:classifiers":[
        {
            "category":"Home & Garden",
            "subcategory":"Building Materials",
            "type":"Retail Goods"
        }
    ],
    "sg:phone":"+43 5272 6654",
    "sg:postcode":"6150",
    "sg:province":"Tirol",
    "sg:tags":[
        "steel",
        "balcony"
    ],
    "wof:name":"Martin Schliernzauer",
    "wof:placetype":"venue"
},
  "geometry": {"coordinates":[11.3495531082,47.0440292358],"type":"Point"}
}