{
  "type": "Feature",
  "properties": {
    "iso:country":"AT",
    "sg:address":"Sengsschmiedstr 4",
    "sg:city":"Kirchdorf an der Krems",
    "sg:orig_category":"Installationsunternehmen",
    "sg:phone":"+43 4375 82612110",
    "sg:postcode":"4560",
    "sg:province":"Ober\u00f6sterreich",
    "wof:name":"Waser Dietmar Ing GmbH",
    "wof:placetype":"venue"
},
  "geometry": {"coordinates":[14.1213541031,47.9069824219],"type":"Point"}
}