{
  "type": "Feature",
  "properties": {
    "iso:country":"AT",
    "sg:address":"Griffen 161",
    "sg:city":"Griffen",
    "sg:classifiers":[
        {
            "category":"Building & Trades",
            "subcategory":"Construction",
            "type":"Services"
        }
    ],
    "sg:phone":"+43 4233 21070",
    "sg:postcode":"9112",
    "sg:province":"K\u00e4rnten",
    "sg:tags":[
        "binding",
        "road",
        "agent"
    ],
    "wof:name":"Possehl Spezialbau Ges.m.b.H.",
    "wof:placetype":"venue"
},
  "geometry": {"coordinates":[14.7279891968,46.7025146484],"type":"Point"}
}