{
  "type": "Feature",
  "properties": {
    "addr:full":"Schubertg 11 Wien Wien 1090",
    "addr:housenumber":"11",
    "addr:postcode":"1090",
    "addr:street":"Schubertg",
    "iso:country":"AT",
    "sg:address":"Schubertg 11",
    "sg:city":"Wien",
    "sg:orig_category":"Restaurants: Italienisch",
    "sg:phone":"+43 1 3196742",
    "sg:postcode":"1090",
    "sg:province":"Wien",
    "wof:name":"Restaurant Frascati",
    "wof:placetype":"venue"
},
  "geometry": {"coordinates":[16.353313446,48.2272720337],"type":"Point"}
}