{
  "type": "Feature",
  "properties": {
    "iso:country":"AT",
    "sg:address":"Kirchstr 9",
    "sg:city":"Bregenz",
    "sg:orig_category":"Feinkost",
    "sg:phone":"+43 5574 48317",
    "sg:postcode":"6900",
    "sg:province":"Vorarlberg",
    "wof:name":"Chez-Jean Paul",
    "wof:placetype":"venue"
},
  "geometry": {"coordinates":[9.7471618652,47.5017471313],"type":"Point"}
}