{
  "type": "Feature",
  "properties": {
    "addr:full":"Lienfeldergasse 32 Wien Wien 1160",
    "addr:housenumber":"32",
    "addr:postcode":"1160",
    "addr:street":"Lienfeldergasse",
    "iso:country":"AT",
    "sg:address":"Lienfeldergasse 32",
    "sg:city":"Wien",
    "sg:classifiers":[
        {
            "category":"Community Center",
            "subcategory":"Ethnic",
            "type":"Public Place"
        }
    ],
    "sg:phone":"+43 1 48586110",
    "sg:postcode":"1160",
    "sg:province":"Wien",
    "sg:tags":[
        "battery",
        "alkaline"
    ],
    "sg:website":"sauseng.at",
    "wof:name":"Otto Sauseng GmbH",
    "wof:placetype":"venue"
},
  "geometry": {"coordinates":[16.3145160675,48.2158126831],"type":"Point"}
}