{
  "type": "Feature",
  "properties": {
    "iso:country":"AT",
    "sg:address":"Bundesstr 70",
    "sg:city":"Dalaas",
    "sg:orig_category":"Bankomat-Standorte",
    "sg:phone":"+43 5585 7213",
    "sg:postcode":"6752",
    "sg:province":"Vorarlberg",
    "wof:name":"Bankomat d Raiffeisenbank Bludenz regGenmbH",
    "wof:placetype":"venue"
},
  "geometry": {"coordinates":[9.9998960495,47.1229896545],"type":"Point"}
}