{
  "type": "Feature",
  "properties": {
    "addr:full":"Bahnhofstr 3 Kalsdorf Steiermark 8401",
    "addr:housenumber":"3",
    "addr:postcode":"8401",
    "addr:street":"Bahnhofstr",
    "iso:country":"AT",
    "sg:address":"Bahnhofstr 3",
    "sg:city":"Kalsdorf",
    "sg:orig_category":"Friseure U Frisiersalons",
    "sg:phone":"+43 4331 3554235",
    "sg:postcode":"8401",
    "sg:province":"Steiermark",
    "wof:name":"Friseur Irene",
    "wof:placetype":"venue"
},
  "geometry": {"coordinates":[15.4776687622,46.964466095],"type":"Point"}
}