{
  "type": "Feature",
  "properties": {
    "iso:country":"AT",
    "sg:address":"Bahnhofstr 3",
    "sg:city":"Kalsdorf",
    "sg:orig_category":"Friseure U Frisiersalons",
    "sg:phone":"+43 4331 3554235",
    "sg:postcode":"8401",
    "sg:province":"Steiermark",
    "wof:name":"Friseur Irene",
    "wof:placetype":"venue"
},
  "geometry": {"coordinates":[15.4776687622,46.964466095],"type":"Point"}
}