{
  "type": "Feature",
  "properties": {
    "iso:country":"AT",
    "sg:address":"Linzer Str 105",
    "sg:city":"Wien",
    "sg:classifiers":[
        {
            "category":"Travel",
            "subcategory":"Hotels & Motels",
            "type":"Entertainment"
        }
    ],
    "sg:phone":"+43 1 98550950",
    "sg:postcode":"1140",
    "sg:province":"Wien",
    "wof:name":"Hotel Gloriette",
    "wof:placetype":"venue"
},
  "geometry": {"coordinates":[16.3061618805,48.1936378479],"type":"Point"}
}