{
  "type": "Feature",
  "properties": {
    "addr:full":"Falle 6 Koblach Vorarlberg 6842",
    "addr:housenumber":"6",
    "addr:postcode":"6842",
    "addr:street":"Falle",
    "iso:country":"AT",
    "sg:address":"Falle 6",
    "sg:city":"Koblach",
    "sg:orig_category":"Polizei U Gendarmerie",
    "sg:phone":"+43 4359 1338167",
    "sg:postcode":"6842",
    "sg:province":"Vorarlberg",
    "wof:name":"Gendarmerie-Grenzkontrollstelle Koblach",
    "wof:placetype":"venue"
},
  "geometry": {"coordinates":[9.5982999802,47.3323020935],"type":"Point"}
}