{
  "type": "Feature",
  "properties": {
    "addr:full":"Erdbergstr 103/2 Wien Wien 1030",
    "addr:housenumber":"103 / 2",
    "addr:postcode":"1030",
    "iso:country":"AT",
    "sg:address":"Erdbergstr 103/2",
    "sg:city":"Wien",
    "sg:classifiers":[
        {
            "category":"Organizations",
            "subcategory":"Community Association",
            "type":"Services"
        }
    ],
    "sg:phone":"+43 1 71275650",
    "sg:postcode":"1030",
    "sg:province":"Wien",
    "sg:tags":[
        "relation",
        "public"
    ],
    "wof:name":"Sibitz Bernd Dkfm Dr KEG",
    "wof:placetype":"venue"
},
  "geometry": {"coordinates":[16.4054145813,48.1966705322],"type":"Point"}
}