{
  "type": "Feature",
  "properties": {
    "iso:country":"AT",
    "sg:address":"Neue Landstrasse 70",
    "sg:city":"Vorchdorf",
    "sg:classifiers":[
        {
            "category":"Building & Trades",
            "subcategory":"Construction",
            "type":"Services"
        }
    ],
    "sg:phone":"+43 7245 25074",
    "sg:postcode":"4655",
    "sg:province":"Ober\u00f6sterreich",
    "sg:tags":[
        "wall",
        "assembling",
        "roof"
    ],
    "sg:website":"meineseite.i-one.at/seyr",
    "wof:name":"Harald Seyr GmbH",
    "wof:placetype":"venue"
},
  "geometry": {"coordinates":[13.9219017029,48.0079345703],"type":"Point"}
}