{
  "type": "Feature",
  "properties": {
    "addr:full":"Schulweg 3 Seewalchen am Attersee Ober\u00f6sterreich 4863",
    "addr:housenumber":"3",
    "addr:postcode":"4863",
    "addr:street":"Schulweg",
    "iso:country":"AT",
    "sg:address":"Schulweg 3",
    "sg:city":"Seewalchen am Attersee",
    "sg:orig_category":"Musikunterricht",
    "sg:phone":"+43 4376 623738",
    "sg:postcode":"4863",
    "sg:province":"Ober\u00f6sterreich",
    "wof:name":"Landesmusikschule",
    "wof:placetype":"venue"
},
  "geometry": {"coordinates":[13.5842018127,47.9535484314],"type":"Point"}
}