{
  "type": "Feature",
  "properties": {
    "addr:full":"Sporergasse 13 Wolfsberg K\u00e4rnten 9400",
    "addr:housenumber":"13;kaernten",
    "addr:postcode":"9400",
    "addr:street":"Sporergasse",
    "iso:country":"AT",
    "sg:address":"Sporergasse 13",
    "sg:city":"Wolfsberg",
    "sg:classifiers":[
        {
            "category":"Shopping",
            "subcategory":"Jewelry",
            "type":"Retail Goods"
        }
    ],
    "sg:phone":"+43 4352 52020",
    "sg:postcode":"9400",
    "sg:province":"K\u00e4rnten",
    "sg:tags":[
        "amber",
        "jewellery"
    ],
    "wof:name":"Waschier Diadoro Partner",
    "wof:placetype":"venue"
},
  "geometry": {"coordinates":[14.8419752121,46.8413085938],"type":"Point"}
}