{
  "type": "Feature",
  "properties": {
    "iso:country":"AT",
    "sg:address":"Burgpl 4",
    "sg:city":"Ybbs an der Donau",
    "sg:orig_category":"Lebensmittel / Einzelhandel",
    "sg:phone":"+43 4374 1253255",
    "sg:postcode":"3370",
    "sg:province":"Nieder\u00f6sterreich",
    "wof:name":"Kaufhaus H\u00f6ller",
    "wof:placetype":"venue"
},
  "geometry": {"coordinates":[15.0831422806,48.1769180298],"type":"Point"}
}