{
  "type": "Feature",
  "properties": {
    "iso:country":"AT",
    "sg:address":"Nr 157",
    "sg:city":"Hatzendorf",
    "sg:orig_category":"Datenverarbeitung",
    "sg:phone":"+43 3155 3798",
    "sg:postcode":"8361",
    "sg:province":"Steiermark",
    "wof:name":"Thurner KEG",
    "wof:placetype":"venue"
},
  "geometry": {"coordinates":[16.0021743774,46.9774932861],"type":"Point"}
}