{
  "type": "Feature",
  "properties": {
    "addr:full":"Eduard Klinger-Str 3c St. Andr\u00e4-W\u00f6rdern Nieder\u00f6sterreich 3423",
    "addr:housenumber":"3c",
    "addr:postcode":"3423",
    "addr:street":"St. Andrae-Woerdern",
    "iso:country":"AT",
    "sg:address":"Eduard Klinger-Str 3c",
    "sg:city":"St. Andr\u00e4-W\u00f6rdern",
    "sg:orig_category":"Maschinenbau",
    "sg:phone":"+43 2242 33029",
    "sg:postcode":"3423",
    "sg:province":"Nieder\u00f6sterreich",
    "wof:name":"Mischtechnik Hoffmann & Partner KG",
    "wof:placetype":"venue"
},
  "geometry": {"coordinates":[16.2031745911,48.3328895569],"type":"Point"}
}