{
  "type": "Feature",
  "properties": {
    "addr:full":"Hochkogelstr 45 Euratsfeld Nieder\u00f6sterreich 3324",
    "addr:housenumber":"45",
    "addr:postcode":"3324",
    "addr:street":"Hochkogelstr",
    "iso:country":"AT",
    "sg:address":"Hochkogelstr 45",
    "sg:city":"Euratsfeld",
    "sg:orig_category":"Lederbekleidung",
    "sg:phone":"+43 7474 224",
    "sg:postcode":"3324",
    "sg:province":"Nieder\u00f6sterreich",
    "wof:name":"Vanek Engelbert",
    "wof:placetype":"venue"
},
  "geometry": {"coordinates":[14.9316034317,48.0753135681],"type":"Point"}
}