{
  "type": "Feature",
  "properties": {
    "addr:full":"Salzburger Str 6 Mattsee Salzburg 5163",
    "addr:housenumber":"6",
    "addr:postcode":"5163",
    "addr:street":"Salzburger Str;Salzburg",
    "iso:country":"AT",
    "sg:address":"Salzburger Str 6",
    "sg:city":"Mattsee",
    "sg:orig_category":"Installationsunternehmen",
    "sg:phone":"+43 4362 178262",
    "sg:postcode":"5163",
    "sg:province":"Salzburg",
    "wof:name":"Daringer Ernst",
    "wof:placetype":"venue"
},
  "geometry": {"coordinates":[13.083776474,48.0047340393],"type":"Point"}
}