{
  "type": "Feature",
  "properties": {
    "iso:country":"AT",
    "sg:address":"Felberstr. 4 Am Europaplatz",
    "sg:city":"Wien",
    "sg:classifiers":[
        {
            "category":"Travel",
            "subcategory":"Travel Agent",
            "type":"Entertainment"
        }
    ],
    "sg:phone":"+43 4319 8111",
    "sg:postcode":"1150",
    "sg:province":"Wien",
    "sg:tags":[
        "business"
    ],
    "wof:name":"DORINT HOTEL",
    "wof:placetype":"venue"
},
  "geometry": {"coordinates":[16.3320903778,48.2006416321],"type":"Point"}
}