{
  "type": "Feature",
  "properties": {
    "addr:full":"Urzenweg 26 Altenfelden Ober\u00f6sterreich 4121",
    "addr:housenumber":"26",
    "addr:postcode":"4121",
    "addr:street":"Urzenweg",
    "iso:country":"AT",
    "sg:address":"Urzenweg 26",
    "sg:city":"Altenfelden",
    "sg:orig_category":"Isolierungen",
    "sg:phone":"+43 7282 6015",
    "sg:postcode":"4121",
    "sg:province":"Ober\u00f6sterreich",
    "wof:name":"Altenhofer Martin",
    "wof:placetype":"venue"
},
  "geometry": {"coordinates":[13.9672203064,48.4804458618],"type":"Point"}
}