{
  "type": "Feature",
  "properties": {
    "addr:full":"Nr 14 Ludweis Nieder\u00f6sterreich 3762",
    "addr:postcode":"3762",
    "addr:street":"Nr 14 Ludweis",
    "iso:country":"AT",
    "sg:address":"Nr 14",
    "sg:city":"Ludweis",
    "sg:orig_category":"Psychotherapie",
    "sg:phone":"+43 2847 80462",
    "sg:postcode":"3762",
    "sg:province":"Nieder\u00f6sterreich",
    "wof:name":"Schagerl Wolfgang",
    "wof:placetype":"venue"
},
  "geometry": {"coordinates":[15.4908895493,48.769821167],"type":"Point"}
}