{
  "type": "Feature",
  "properties": {
    "iso:country":"AT",
    "sg:address":"Grazer Str 5",
    "sg:city":"Gleisdorf",
    "sg:orig_category":"Steinmetzbetriebe",
    "sg:phone":"+43 4331 122639",
    "sg:postcode":"8200",
    "sg:province":"Steiermark",
    "wof:name":"L\u00f6schnigg Larissa Mag",
    "wof:placetype":"venue"
},
  "geometry": {"coordinates":[15.7037258148,47.104675293],"type":"Point"}
}