{
  "type": "Feature",
  "properties": {
    "addr:full":"Wattmanng 30 Wien Wien 1130",
    "addr:housenumber":"30",
    "addr:postcode":"1130",
    "addr:street":"Wattmanng",
    "iso:country":"AT",
    "sg:address":"Wattmanng 30",
    "sg:city":"Wien",
    "sg:orig_category":"Strick- U Wirkwaren / Erzeugung U Gro\u00c3\u0178handel",
    "sg:phone":"+43 4318 765736",
    "sg:postcode":"1130",
    "sg:province":"Wien",
    "wof:name":"LEA LANEA",
    "wof:placetype":"venue"
},
  "geometry": {"coordinates":[16.2969837189,48.1817855835],"type":"Point"}
}