{
  "type": "Feature",
  "properties": {
    "addr:full":"Kaiser-Josef-Str 3/1 Innsbruck Tirol 6020",
    "addr:housenumber":"3 / 1",
    "addr:postcode":"6020",
    "addr:street":"Kaiser-Josef-Str;Tirol",
    "iso:country":"AT",
    "sg:address":"Kaiser-Josef-Str 3/1",
    "sg:city":"Innsbruck",
    "sg:orig_category":"Architekten",
    "sg:phone":"+43 512 5728570",
    "sg:postcode":"6020",
    "sg:province":"Tirol",
    "wof:name":"Cede Michael Dipl-Ing",
    "wof:placetype":"venue"
},
  "geometry": {"coordinates":[11.3890743256,47.2635383606],"type":"Point"}
}