{
  "type": "Feature",
  "properties": {
    "addr:full":"Kamerlweg 33 Wels Ober\u00f6sterreich 4600",
    "addr:housenumber":"33",
    "addr:postcode":"4600",
    "addr:street":"Kamerlweg;Oberoesterreich",
    "iso:country":"AT",
    "sg:address":"Kamerlweg 33",
    "sg:city":"Wels",
    "sg:orig_category":"Arbeitsschutz U Arbeitsschutzartikel",
    "sg:phone":"+43 4372 4262323",
    "sg:postcode":"4600",
    "sg:province":"Ober\u00f6sterreich",
    "wof:name":"Uvex Austria GesmbH",
    "wof:placetype":"venue"
},
  "geometry": {"coordinates":[14.0508441925,48.1749076843],"type":"Point"}
}