{
  "type": "Feature",
  "properties": {
    "iso:country":"AT",
    "sg:address":"Vorachstr 65b",
    "sg:city":"Lustenau",
    "sg:orig_category":"Ausschneidereien",
    "sg:phone":"+43 5577 870890",
    "sg:postcode":"6890",
    "sg:province":"Vorarlberg",
    "wof:name":"Rauch Kurt",
    "wof:placetype":"venue"
},
  "geometry": {"coordinates":[9.6731967926,47.4254455566],"type":"Point"}
}