{
  "type": "Feature",
  "properties": {
    "addr:full":"Gerstnerstr 2 Linz Ober\u00f6sterreich 4040",
    "addr:housenumber":"2",
    "addr:postcode":"4040",
    "addr:street":"Gerstnerstr",
    "iso:country":"AT",
    "sg:address":"Gerstnerstr 2",
    "sg:city":"Linz",
    "sg:orig_category":"Politische Parteien",
    "sg:phone":"+43 732 7322480",
    "sg:postcode":"4040",
    "sg:province":"Ober\u00f6sterreich",
    "wof:name":"Sozialdemokratische Partei \u00f6sterreichs (SP\u00f6)",
    "wof:placetype":"venue"
},
  "geometry": {"coordinates":[14.2846260071,48.3122406006],"type":"Point"}
}