{
  "type": "Feature",
  "properties": {
    "iso:country":"AT",
    "sg:address":"Anichstr 7",
    "sg:city":"Innsbruck",
    "sg:orig_category":"Friseure U Frisiersalons",
    "sg:phone":"+43 512 58991215",
    "sg:postcode":"6020",
    "sg:province":"Tirol",
    "wof:name":"Ihr dm Friseur Studio",
    "wof:placetype":"venue"
},
  "geometry": {"coordinates":[11.3931798935,47.2648696899],"type":"Point"}
}