{
  "type": "Feature",
  "properties": {
    "addr:full":"Leopoldstr 67 Innsbruck Tirol 6020",
    "addr:housenumber":"67",
    "addr:postcode":"6020",
    "addr:street":"Leopoldstr;Tirol",
    "iso:country":"AT",
    "sg:address":"Leopoldstr 67",
    "sg:city":"Innsbruck",
    "sg:orig_category":"Tankstellen",
    "sg:phone":"+43 512 585958",
    "sg:postcode":"6020",
    "sg:province":"Tirol",
    "wof:name":"Esso Austria GesmbH",
    "wof:placetype":"venue"
},
  "geometry": {"coordinates":[11.3991384506,47.2540092468],"type":"Point"}
}