{
  "type": "Feature",
  "properties": {
    "addr:full":"K Elisabeth-Str 15a Hohenems Vorarlberg 6845",
    "addr:housenumber":"15a",
    "addr:postcode":"6845",
    "addr:street":"Elisabeth-Str",
    "iso:country":"AT",
    "sg:address":"K Elisabeth-Str 15a",
    "sg:city":"Hohenems",
    "sg:orig_category":"Zimmereien",
    "sg:phone":"+43 5576 73720",
    "sg:postcode":"6845",
    "sg:province":"Vorarlberg",
    "wof:name":"Brotzge Manfred",
    "wof:placetype":"venue"
},
  "geometry": {"coordinates":[9.6815233231,47.3613624573],"type":"Point"}
}