{
  "type": "Feature",
  "properties": {
    "addr:full":"D\u00f6blinger Hauptstr 77a Wien Wien 1190",
    "addr:housenumber":"77a",
    "addr:postcode":"1190",
    "addr:street":"Hauptstr",
    "iso:country":"AT",
    "sg:address":"D\u00f6blinger Hauptstr 77a",
    "sg:city":"Wien",
    "sg:orig_category":"Textilreinigung",
    "sg:phone":"+43 1 3683535",
    "sg:postcode":"1190",
    "sg:province":"Wien",
    "wof:name":"Ph\u00f6bus Textilreinigung",
    "wof:placetype":"venue"
},
  "geometry": {"coordinates":[16.3553466797,48.2416610718],"type":"Point"}
}