{
  "type": "Feature",
  "properties": {
    "iso:country":"AT",
    "sg:address":"Altstadt 57",
    "sg:city":"Bruck an der Leitha",
    "sg:classifiers":[
        {
            "category":"Restaurant",
            "type":"Food & Drink"
        }
    ],
    "sg:phone":"+43 2162 63980",
    "sg:postcode":"2460",
    "sg:province":"Nieder\u00f6sterreich",
    "sg:tags":[
        "pizzeria"
    ],
    "wof:name":"Pizzeria-Tavernetta Uomo Fresco",
    "wof:placetype":"venue"
},
  "geometry": {"coordinates":[16.7723999023,48.0216827393],"type":"Point"}
}