{
  "type": "Feature",
  "properties": {
    "addr:full":"Aspangerstrasse 252  Pitten Nieder\u00f6sterreich 2823",
    "addr:housenumber":"252",
    "addr:postcode":"2823",
    "addr:street":"Aspangerstrasse",
    "iso:country":"AT",
    "sg:address":"Aspangerstrasse 252 ",
    "sg:city":"Pitten",
    "sg:classifiers":[
        {
            "category":"Manufacturing",
            "subcategory":"Paper Products",
            "type":"Manufacturing & Wholesale Goods"
        }
    ],
    "sg:phone":"+43 4326 27800",
    "sg:postcode":"2823",
    "sg:province":"Nieder\u00f6sterreich",
    "sg:tags":[
        "cardboard"
    ],
    "wof:name":"HAMBURGER W AG",
    "wof:placetype":"venue"
},
  "geometry": {"coordinates":[16.1872062683,47.7157440186],"type":"Point"}
}