{
  "type": "Feature",
  "properties": {
    "iso:country":"AT",
    "sg:address":"Nr 78",
    "sg:city":"Kitzeck im Sausal",
    "sg:orig_category":"Banken U Sparkassen",
    "sg:phone":"+43 4334 5622220",
    "sg:postcode":"8442",
    "sg:province":"Steiermark",
    "wof:name":"Bankomat d Raiffeisenbank Gleinst\u00e4tten regGenmbH",
    "wof:placetype":"venue"
},
  "geometry": {"coordinates":[15.4540109634,46.7809333801],"type":"Point"}
}