{
  "type": "Feature",
  "properties": {
    "addr:full":"Felber Str 3 Mittersill Salzburg 5730",
    "addr:housenumber":"3",
    "addr:postcode":"5730",
    "addr:street":"Str;Salzburg",
    "iso:country":"AT",
    "sg:address":"Felber Str 3",
    "sg:city":"Mittersill",
    "sg:orig_category":"Hauptschulen",
    "sg:phone":"+43 6562 62770",
    "sg:postcode":"5730",
    "sg:province":"Salzburg",
    "wof:name":"Hauptschule",
    "wof:placetype":"venue"
},
  "geometry": {"coordinates":[12.48458004,47.2808456421],"type":"Point"}
}