{
  "type": "Feature",
  "properties": {
    "addr:full":"Sonnleiten 7 Eschenau an der Traisen Nieder\u00f6sterreich 3153",
    "addr:housenumber":"7",
    "addr:postcode":"3153",
    "addr:street":"Sonnleiten",
    "iso:country":"AT",
    "sg:address":"Sonnleiten 7",
    "sg:city":"Eschenau an der Traisen",
    "sg:classifiers":[
        {
            "category":"Organizations",
            "subcategory":"Community Association",
            "type":"Services"
        }
    ],
    "sg:phone":"+43 2762 67216",
    "sg:postcode":"3153",
    "sg:province":"Nieder\u00f6sterreich",
    "sg:tags":[
        "relation",
        "public"
    ],
    "wof:name":"RYBACEK",
    "wof:placetype":"venue"
},
  "geometry": {"coordinates":[15.5654001236,48.0501098633],"type":"Point"}
}