{
  "type": "Feature",
  "properties": {
    "addr:full":"Nr 106 Globasnitz K\u00e4rnten 9142",
    "addr:postcode":"9142",
    "addr:street":"Nr 106;Kaernten",
    "iso:country":"AT",
    "sg:address":"Nr 106",
    "sg:city":"Globasnitz",
    "sg:orig_category":"Tischlereien",
    "sg:phone":"+43 4230 459",
    "sg:postcode":"9142",
    "sg:province":"K\u00e4rnten",
    "wof:name":"Tschokl Johann",
    "wof:placetype":"venue"
},
  "geometry": {"coordinates":[14.7002391815,46.5574455261],"type":"Point"}
}