{
  "type": "Feature",
  "properties": {
    "iso:country":"AT",
    "sg:address":"Schmiedg 23",
    "sg:city":"Leibnitz",
    "sg:orig_category":"Installationsunternehmen",
    "sg:phone":"+43 3452 829560",
    "sg:postcode":"8430",
    "sg:province":"Steiermark",
    "wof:name":"GWH Gebr\u00fcder Roiko GesmbH",
    "wof:placetype":"venue"
},
  "geometry": {"coordinates":[15.5399017334,46.7799186707],"type":"Point"}
}