{
  "type": "Feature",
  "properties": {
    "addr:full":"Melker Strasse 35 Mautern Nieder\u00f6sterreich 3512",
    "addr:housenumber":"35",
    "addr:postcode":"3512",
    "addr:street":"Melker Strasse",
    "iso:country":"AT",
    "sg:address":"Melker Strasse 35",
    "sg:city":"Mautern",
    "sg:orig_category":"Bathrooms, Exclusive",
    "sg:phone":"+43 2732 70024",
    "sg:postcode":"3512",
    "sg:province":"Nieder\u00f6sterreich",
    "sg:website":"hwg.cc",
    "wof:name":"HWG Stefan Weidinger Installationstechnologie",
    "wof:placetype":"venue"
},
  "geometry": {"coordinates":[15.5512466431,48.3772163391],"type":"Point"}
}