{
  "type": "Feature",
  "properties": {
    "addr:full":"Hauptstr 36 Leibnitz Steiermark 8430",
    "addr:housenumber":"36",
    "addr:postcode":"8430",
    "addr:street":"Hauptstr;Steiermark",
    "iso:country":"AT",
    "sg:address":"Hauptstr 36",
    "sg:city":"Leibnitz",
    "sg:orig_category":"Autoelektrik U -Ersatzteile",
    "sg:phone":"+43 4334 5284308",
    "sg:postcode":"8430",
    "sg:province":"Steiermark",
    "wof:name":"Flucher Helmut u Maria GesnbR",
    "wof:placetype":"venue"
},
  "geometry": {"coordinates":[15.5677719116,46.7756195068],"type":"Point"}
}