{
  "type": "Feature",
  "properties": {
    "addr:full":"Hauptstr 175 Rohrbach Burgenland 7222",
    "addr:housenumber":"175",
    "addr:postcode":"7222",
    "addr:street":"Hauptstr",
    "iso:country":"AT",
    "sg:address":"Hauptstr 175",
    "sg:city":"Rohrbach",
    "sg:orig_category":"Fenster",
    "sg:phone":"+43 2626 62597",
    "sg:postcode":"7222",
    "sg:province":"Burgenland",
    "wof:name":"Kutro Fenster und T\u00fcren GesmbH",
    "wof:placetype":"venue"
},
  "geometry": {"coordinates":[16.4286708832,47.7151908875],"type":"Point"}
}