{
  "type": "Feature",
  "properties": {
    "addr:full":"Gasteinerstrasse 50-52 Bischofshofen Salzburg 5500",
    "addr:postcode":"50-52;5500",
    "addr:street":"Gasteinerstrasse;Salzburg",
    "iso:country":"AT",
    "sg:address":"Gasteinerstrasse 50-52",
    "sg:city":"Bischofshofen",
    "sg:classifiers":[
        {
            "category":"Manufacturing",
            "subcategory":"Wood Products",
            "type":"Manufacturing & Wholesale Goods"
        }
    ],
    "sg:phone":"+43 6462 24380",
    "sg:postcode":"5500",
    "sg:province":"Salzburg",
    "sg:tags":[
        "lumber"
    ],
    "sg:website":"rettenegger.at",
    "wof:name":"Rettenegger S\u00e4ge- und Hobelwerk KG",
    "wof:placetype":"venue"
},
  "geometry": {"coordinates":[13.2166957855,47.4102668762],"type":"Point"}
}