{
  "type": "Feature",
  "properties": {
    "addr:full":"Bucheng 8 Fohnsdorf Steiermark 8753",
    "addr:housenumber":"8",
    "addr:postcode":"8753",
    "addr:street":"Bucheng",
    "iso:country":"AT",
    "sg:address":"Bucheng 8",
    "sg:city":"Fohnsdorf",
    "sg:orig_category":"Tischlereien",
    "sg:phone":"+43 3573 5106",
    "sg:postcode":"8753",
    "sg:province":"Steiermark",
    "wof:name":"Brandner GesmbH",
    "wof:placetype":"venue"
},
  "geometry": {"coordinates":[14.6933135986,47.202293396],"type":"Point"}
}