{
  "type": "Feature",
  "properties": {
    "addr:full":"Oberhausner Strasse 9 Gro\u00df-Enzersdorf Nieder\u00f6sterreich 2301",
    "addr:housenumber":"9",
    "addr:postcode":"2301",
    "addr:street":"Oberhausner Strasse;Niederoesterreich",
    "iso:country":"AT",
    "sg:address":"Oberhausner Strasse 9",
    "sg:city":"Gro\u00df-Enzersdorf",
    "sg:classifiers":[
        {
            "category":"Utilities",
            "subcategory":"Cable",
            "type":"Services"
        }
    ],
    "sg:phone":"+43 2249 74140",
    "sg:postcode":"2301",
    "sg:province":"Nieder\u00f6sterreich",
    "sg:tags":[
        "development"
    ],
    "sg:website":"schrenk-elektronik.at",
    "wof:name":"Schrenk Elektronik Ges.m.b.H.",
    "wof:placetype":"venue"
},
  "geometry": {"coordinates":[16.5793037415,48.1879272461],"type":"Point"}
}