{
  "type": "Feature",
  "properties": {
    "iso:country":"AT",
    "sg:address":"Breitenfurter Str 288",
    "sg:city":"Wien",
    "sg:orig_category":"Unterhaltungselektronik / Reparatur",
    "sg:phone":"+43 1 8657289",
    "sg:postcode":"1230",
    "sg:province":"Wien",
    "wof:name":"Grossbointner Josef Ing",
    "wof:placetype":"venue"
},
  "geometry": {"coordinates":[16.2921638489,48.1429176331],"type":"Point"}
}