{
  "type": "Feature",
  "properties": {
    "addr:full":"Buchbergstr 65 Neukirchen Ober\u00f6sterreich 4814",
    "addr:housenumber":"65",
    "addr:postcode":"4814",
    "addr:street":"Buchbergstr",
    "iso:country":"AT",
    "sg:address":"Buchbergstr 65",
    "sg:city":"Neukirchen",
    "sg:orig_category":"Tischlereien",
    "sg:phone":"+43 4376 188595",
    "sg:postcode":"4814",
    "sg:province":"Ober\u00f6sterreich",
    "wof:name":"Spiessberger Franz",
    "wof:placetype":"venue"
},
  "geometry": {"coordinates":[13.7360639572,47.8695716858],"type":"Point"}
}