{
  "type": "Feature",
  "properties": {
    "addr:full":"Conrad-von-H\u00f6tzendorf-Str 7 Salzburg Salzburg 5020",
    "addr:housenumber":"7",
    "addr:postcode":"5020",
    "addr:street":"Conrad-Von-Hoetzendorf-Str;Salzburg",
    "iso:country":"AT",
    "sg:address":"Conrad-von-H\u00f6tzendorf-Str 7",
    "sg:city":"Salzburg",
    "sg:orig_category":"Tonstudios",
    "sg:phone":"+43 4366 2441648",
    "sg:postcode":"5020",
    "sg:province":"Salzburg",
    "wof:name":"Wavesound M C Diess Audio & Stage Engineering",
    "wof:placetype":"venue"
},
  "geometry": {"coordinates":[13.0251703262,47.8048820496],"type":"Point"}
}