{
  "type": "Feature",
  "properties": {
    "addr:full":"Parkring 2 Lebring Steiermark 8403",
    "addr:housenumber":"2",
    "addr:postcode":"8403",
    "addr:street":"Parkring",
    "iso:country":"AT",
    "sg:address":"Parkring 2",
    "sg:city":"Lebring",
    "sg:classifiers":[
        {
            "category":"Professional",
            "subcategory":"Computer Services",
            "type":"Services"
        }
    ],
    "sg:phone":"+43 3182 49013",
    "sg:postcode":"8403",
    "sg:province":"Steiermark",
    "sg:tags":[
        "software"
    ],
    "wof:name":"AutForce Automations GmbH",
    "wof:placetype":"venue"
},
  "geometry": {"coordinates":[15.5279312134,46.8512229919],"type":"Point"}
}