{
  "type": "Feature",
  "properties": {
    "addr:full":"Copacabana 7 Kalsdorf Steiermark 8401",
    "addr:housenumber":"7",
    "addr:postcode":"8401",
    "addr:street":"Copacabana",
    "iso:country":"AT",
    "sg:address":"Copacabana 7",
    "sg:city":"Kalsdorf",
    "sg:orig_category":"Restaurants: Griechisch",
    "sg:phone":"+43 3135 55738",
    "sg:postcode":"8401",
    "sg:province":"Steiermark",
    "wof:name":"Taverne Der Grieche",
    "wof:placetype":"venue"
},
  "geometry": {"coordinates":[15.4577302933,46.9743423462],"type":"Point"}
}