{
  "type": "Feature",
  "properties": {
    "iso:country":"AT",
    "sg:address":"Bundesstr 4/1",
    "sg:city":"Wals",
    "sg:classifiers":[
        {
            "category":"Professional",
            "type":"Services"
        }
    ],
    "sg:phone":"+43 662 8550800",
    "sg:postcode":"5071",
    "sg:province":"Salzburg",
    "sg:tags":[
        "leasing"
    ],
    "wof:name":"MB Leasing GesmbH",
    "wof:placetype":"venue"
},
  "geometry": {"coordinates":[12.9903039932,47.7917289734],"type":"Point"}
}