{
  "type": "Feature",
  "properties": {
    "iso:country":"AT",
    "sg:address":"B\u00fctzestrasse 39",
    "sg:city":"Wolfurt-Bahnhof",
    "sg:classifiers":[
        {
            "category":"Utilities",
            "subcategory":"Cable",
            "type":"Services"
        }
    ],
    "sg:phone":"+43 5574 71223",
    "sg:postcode":"6960",
    "sg:province":"Vorarlberg",
    "sg:tags":[
        "conduit",
        "made",
        "concrete"
    ],
    "sg:website":"betonwerk-rohner.at",
    "wof:name":"Rochus Rohner Betonwerk",
    "wof:placetype":"venue"
},
  "geometry": {"coordinates":[9.750123024,47.4668045044],"type":"Point"}
}