{
  "type": "Feature",
  "properties": {
    "iso:country":"AT",
    "sg:address":"Nr 86",
    "sg:city":"Telfs",
    "sg:orig_category":"Non-Classified Establishments",
    "sg:phone":"+43 5238 88259",
    "sg:postcode":"6410",
    "sg:province":"Tirol",
    "wof:name":"Pfarramt Leiblfing",
    "wof:placetype":"venue"
},
  "geometry": {"coordinates":[11.072218895,47.3066978455],"type":"Point"}
}