{
  "type": "Feature",
  "properties": {
    "addr:full":"Aufeldg 49a Lichtenw\u00f6rth Nieder\u00f6sterreich 2493",
    "addr:housenumber":"49a",
    "addr:postcode":"2493",
    "addr:street":"Aufeldg;Niederoesterreich",
    "iso:country":"AT",
    "sg:address":"Aufeldg 49a",
    "sg:city":"Lichtenw\u00f6rth",
    "sg:orig_category":"Metallbau",
    "sg:phone":"+43 4326 2275378",
    "sg:postcode":"2493",
    "sg:province":"Nieder\u00f6sterreich",
    "wof:name":"Tasch Julius",
    "wof:placetype":"venue"
},
  "geometry": {"coordinates":[16.2962799072,47.8375015259],"type":"Point"}
}