{
  "type": "Feature",
  "properties": {
    "addr:full":"Unterweidach 39 Ebbs Tirol 6341",
    "addr:housenumber":"39",
    "addr:postcode":"6341",
    "addr:street":"Unterweidach;Tirol",
    "iso:country":"AT",
    "sg:address":"Unterweidach 39",
    "sg:city":"Ebbs",
    "sg:orig_category":"Montagen U Montagetechnik",
    "sg:phone":"+43 5373 43445",
    "sg:postcode":"6341",
    "sg:province":"Tirol",
    "wof:name":"Kitzbichler Helmut",
    "wof:placetype":"venue"
},
  "geometry": {"coordinates":[12.2105035782,47.6364898682],"type":"Point"}
}