{
  "type": "Feature",
  "properties": {
    "addr:full":"Verdiweg 6 Bad Kleinkirchheim K\u00e4rnten 9546",
    "addr:housenumber":"6",
    "addr:postcode":"9546",
    "addr:street":"Verdiweg",
    "iso:country":"AT",
    "sg:address":"Verdiweg 6",
    "sg:city":"Bad Kleinkirchheim",
    "sg:orig_category":"Pensionen / Privatzimmer",
    "sg:phone":"+43 4240 4460",
    "sg:postcode":"9546",
    "sg:province":"K\u00e4rnten",
    "wof:name":"Fr\u00fchst\u00fcckspension Edenhof",
    "wof:placetype":"venue"
},
  "geometry": {"coordinates":[13.8117780685,46.8127861023],"type":"Point"}
}