{
  "type": "Feature",
  "properties": {
    "addr:full":"Nr 49 Neukirchen an der V\u00f6ckla Ober\u00f6sterreich 4872",
    "addr:postcode":"4872",
    "addr:street":"Nr 49;Oberoesterreich",
    "iso:country":"AT",
    "sg:address":"Nr 49",
    "sg:city":"Neukirchen an der V\u00f6ckla",
    "sg:orig_category":"Friseure U Frisiersalons",
    "sg:phone":"+43 4376 827182",
    "sg:postcode":"4872",
    "sg:province":"Ober\u00f6sterreich",
    "wof:name":"Pohn Christine",
    "wof:placetype":"venue"
},
  "geometry": {"coordinates":[13.5377645493,48.0409698486],"type":"Point"}
}