{
  "type": "Feature",
  "properties": {
    "iso:country":"AT",
    "sg:address":"Bahnhofstr 50",
    "sg:city":"Rohrbach in Ober\u00f6sterreich",
    "sg:orig_category":"Bauunternehmen",
    "sg:phone":"+43 4372 8968110",
    "sg:postcode":"4150",
    "sg:province":"Ober\u00f6sterreich",
    "wof:name":"Weber Bau GmbH",
    "wof:placetype":"venue"
},
  "geometry": {"coordinates":[13.9887275696,48.5804862976],"type":"Point"}
}