{
  "type": "Feature",
  "properties": {
    "addr:full":"Steinebach 11 Dornbirn Vorarlberg 6850",
    "addr:housenumber":"11",
    "addr:postcode":"6850",
    "addr:street":"Steinebach",
    "iso:country":"AT",
    "sg:address":"Steinebach 11",
    "sg:city":"Dornbirn",
    "sg:orig_category":"Architekten",
    "sg:phone":"+43 5572 207896",
    "sg:postcode":"6850",
    "sg:province":"Vorarlberg",
    "wof:name":"Frick Bernd Arch Dipl-Ing",
    "wof:placetype":"venue"
},
  "geometry": {"coordinates":[9.759223938,47.4049797058],"type":"Point"}
}