{
  "type": "Feature",
  "properties": {
    "addr:full":"Bahnhofstr 8 Dornbirn Vorarlberg 6850",
    "addr:housenumber":"8",
    "addr:postcode":"6850",
    "addr:street":"Bahnhofstr",
    "iso:country":"AT",
    "sg:address":"Bahnhofstr 8",
    "sg:city":"Dornbirn",
    "sg:orig_category":"Vinotheken",
    "sg:phone":"+43 5572 21269",
    "sg:postcode":"6850",
    "sg:province":"Vorarlberg",
    "wof:name":"Bruvino-Vinothek",
    "wof:placetype":"venue"
},
  "geometry": {"coordinates":[9.7405328751,47.4147529602],"type":"Point"}
}