{
  "type": "Feature",
  "properties": {
    "iso:country":"AT",
    "sg:address":"Arnbach 73",
    "sg:city":"Sillian",
    "sg:orig_category":"Holzbau",
    "sg:phone":"+43 4842 20142",
    "sg:postcode":"9920",
    "sg:province":"Tirol",
    "wof:name":"Holzbau Bachmann GmbH",
    "wof:placetype":"venue"
},
  "geometry": {"coordinates":[12.3908557892,46.7448654175],"type":"Point"}
}