{
  "type": "Feature",
  "properties": {
    "addr:full":"Speisinger Str 154 Wien Wien 1130",
    "addr:housenumber":"154",
    "addr:postcode":"1130",
    "iso:country":"AT",
    "sg:address":"Speisinger Str 154",
    "sg:city":"Wien",
    "sg:orig_category":"Tabaktrafiken",
    "sg:phone":"+43 1 8863675",
    "sg:postcode":"1130",
    "sg:province":"Wien",
    "wof:name":"Windisch Sabine",
    "wof:placetype":"venue"
},
  "geometry": {"coordinates":[16.2766246796,48.1600151062],"type":"Point"}
}