{
  "type": "Feature",
  "properties": {
    "iso:country":"AT",
    "sg:address":"Bahnhofallee 2",
    "sg:city":"Ober-Grafendorf",
    "sg:orig_category":"Bauunternehmen",
    "sg:phone":"+43 2747 22500",
    "sg:postcode":"3200",
    "sg:province":"Nieder\u00f6sterreich",
    "wof:name":"Trepka Alfred GesmbH & Co KG",
    "wof:placetype":"venue"
},
  "geometry": {"coordinates":[15.5442829132,48.1524276733],"type":"Point"}
}