{
  "type": "Feature",
  "properties": {
    "addr:full":"Wiener Str 27 Leopoldsdorf im Marchfelde Nieder\u00f6sterreich 2285",
    "addr:postcode":"2285",
    "iso:country":"AT",
    "sg:address":"Wiener Str 27",
    "sg:city":"Leopoldsdorf im Marchfelde",
    "sg:orig_category":"Metalle U -Halbfabrikate",
    "sg:phone":"+43 4322 162710",
    "sg:postcode":"2285",
    "sg:province":"Nieder\u00f6sterreich",
    "wof:name":"ITC HandelsgesmbH",
    "wof:placetype":"venue"
},
  "geometry": {"coordinates":[16.6851081848,48.218963623],"type":"Point"}
}