{
  "type": "Feature",
  "properties": {
    "addr:full":"Rosenweg 4 Grafenstein K\u00e4rnten 9131",
    "addr:housenumber":"4",
    "addr:postcode":"9131",
    "addr:street":"Rosenweg;Kaernten",
    "iso:country":"AT",
    "sg:address":"Rosenweg 4",
    "sg:city":"Grafenstein",
    "sg:classifiers":[
        {
            "category":"Shopping",
            "subcategory":"Pharmacy",
            "type":"Retail Goods"
        }
    ],
    "sg:phone":"+43 4224 81133",
    "sg:postcode":"9131",
    "sg:province":"K\u00e4rnten",
    "sg:tags":[
        "supplement",
        "dietary"
    ],
    "sg:website":"hafesan.at",
    "wof:name":"Hafesan Handelsges.m.b.H.",
    "wof:placetype":"venue"
},
  "geometry": {"coordinates":[14.432050705,46.646484375],"type":"Point"}
}