{
  "type": "Feature",
  "properties": {
    "addr:full":"Griesg 3 Ferlach K\u00e4rnten 9170",
    "addr:housenumber":"3",
    "addr:postcode":"9170",
    "addr:street":"Griesg;Kaernten",
    "iso:country":"AT",
    "sg:address":"Griesg 3",
    "sg:city":"Ferlach",
    "sg:classifiers":[
        {
            "category":"Shopping",
            "subcategory":"Bicycles & Sporting Goods",
            "type":"Retail Goods"
        }
    ],
    "sg:phone":"+43 4342 272283",
    "sg:postcode":"9170",
    "sg:province":"K\u00e4rnten",
    "sg:tags":[
        "munition",
        "u",
        "waffen"
    ],
    "wof:name":"Fanzoj Jagdwaffen & Ribohunt Sportartikel GmbH",
    "wof:placetype":"venue"
},
  "geometry": {"coordinates":[14.3006019592,46.5291404724],"type":"Point"}
}