{
  "type": "Feature",
  "properties": {
    "iso:country":"AT",
    "sg:address":"Universit\u00e4tspl 3",
    "sg:city":"Graz",
    "sg:orig_category":"Bibliotheken",
    "sg:phone":"+43 316 3803102",
    "sg:postcode":"8010",
    "sg:province":"Steiermark",
    "wof:name":"Universit\u00e4tsbibliothek d Karl Franzens Universit\u00e4t Graz",
    "wof:placetype":"venue"
},
  "geometry": {"coordinates":[15.4490451813,47.0774459839],"type":"Point"}
}