{
  "type": "Feature",
  "properties": {
    "addr:full":"Sankt Margarethen an der Raab 7 St. Margarethen an der Raab Steiermark 8321",
    "addr:housenumber":"7",
    "addr:postcode":"8321",
    "addr:street":"An Der Raab",
    "iso:country":"AT",
    "sg:address":"Sankt Margarethen an der Raab 7",
    "sg:city":"St. Margarethen an der Raab",
    "sg:classifiers":[
        {
            "category":"Community Center",
            "subcategory":"Senior",
            "type":"Public Place"
        }
    ],
    "sg:phone":"+43 3115 2335",
    "sg:postcode":"8321",
    "sg:province":"Steiermark",
    "sg:tags":[
        "front",
        "wood",
        "door"
    ],
    "sg:website":"tischlerei-marksteiner.at",
    "wof:name":"Heimo Marksteiner",
    "wof:placetype":"venue"
},
  "geometry": {"coordinates":[15.7453098297,47.0449333191],"type":"Point"}
}