{
  "type": "Feature",
  "properties": {
    "iso:country":"AT",
    "sg:address":"Akademiestr 25",
    "sg:city":"Salzburg",
    "sg:orig_category":"Volksschulen",
    "sg:phone":"+43 662 62959133",
    "sg:postcode":"5020",
    "sg:province":"Salzburg",
    "wof:name":"\u00dcbungsvolksschule d P\u00e4dagogischen Akademie d Bundes i Salzburg",
    "wof:placetype":"venue"
},
  "geometry": {"coordinates":[13.0549840927,47.791759491],"type":"Point"}
}