{
  "type": "Feature",
  "properties": {
    "iso:country":"AT",
    "sg:address":"Kunigundbergstrasse 35",
    "sg:city":"Perchtoldsdorf",
    "sg:classifiers":[
        {
            "category":"Science Facility",
            "type":"Public Place"
        }
    ],
    "sg:phone":"+43 1 8691050",
    "sg:postcode":"2380",
    "sg:province":"Nieder\u00f6sterreich",
    "sg:tags":[
        "equipment",
        "analysis"
    ],
    "sg:website":"tba-worldwide.com",
    "wof:name":"TBA Instrument Systems Papiermaschinen Service Ges.m.b.H.",
    "wof:placetype":"venue"
},
  "geometry": {"coordinates":[16.2656898499,48.1140937805],"type":"Point"}
}