{
  "type": "Feature",
  "properties": {
    "addr:full":"Firmianstr 42 Salzburg Salzburg 5020",
    "addr:housenumber":"42",
    "addr:postcode":"5020",
    "addr:street":"Firmianstr;Salzburg",
    "iso:country":"AT",
    "sg:address":"Firmianstr 42",
    "sg:city":"Salzburg",
    "sg:orig_category":"Tankstellen",
    "sg:phone":"+43 662 824823",
    "sg:postcode":"5020",
    "sg:province":"Salzburg",
    "wof:name":"OMV AG",
    "wof:placetype":"venue"
},
  "geometry": {"coordinates":[13.02602005,47.7847633362],"type":"Point"}
}