{
  "type": "Feature",
  "properties": {
    "iso:country":"AT",
    "sg:address":"Nr 15",
    "sg:city":"Dorfstetten",
    "sg:orig_category":"Appartements / Ferienwohnungen",
    "sg:phone":"+43 4372 608270",
    "sg:postcode":"4392",
    "sg:province":"Nieder\u00f6sterreich",
    "wof:name":"Wurzer Anna",
    "wof:placetype":"venue"
},
  "geometry": {"coordinates":[14.9821662903,48.32629776],"type":"Point"}
}