{
  "type": "Feature",
  "properties": {
    "addr:full":"Conradpl 9 Rust Burgenland 7071",
    "addr:housenumber":"9",
    "addr:postcode":"7071",
    "addr:street":"Conradpl",
    "iso:country":"AT",
    "sg:address":"Conradpl 9",
    "sg:city":"Rust",
    "sg:orig_category":"Optiker",
    "sg:phone":"+43 2685 6401",
    "sg:postcode":"7071",
    "sg:province":"Burgenland",
    "wof:name":"Ruster Optik Erich Lederer",
    "wof:placetype":"venue"
},
  "geometry": {"coordinates":[16.6731262207,47.8008079529],"type":"Point"}
}