{
  "type": "Feature",
  "properties": {
    "addr:full":"Fridrichallee 6 Bruck an der Mur Steiermark 8600",
    "addr:housenumber":"6",
    "addr:postcode":"8600",
    "addr:street":"Fridrichallee",
    "iso:country":"AT",
    "sg:address":"Fridrichallee 6",
    "sg:city":"Bruck an der Mur",
    "sg:orig_category":"Edelstahl",
    "sg:phone":"+43 3862 550640",
    "sg:postcode":"8600",
    "sg:province":"Steiermark",
    "wof:name":"MURIMPEX EdelstahlhandelsgesmbH",
    "wof:placetype":"venue"
},
  "geometry": {"coordinates":[15.2659196854,47.4109611511],"type":"Point"}
}