{
  "type": "Feature",
  "properties": {
    "addr:full":"Waldeck 3 Kufstein Tirol 6330",
    "addr:housenumber":"3",
    "addr:postcode":"6330",
    "addr:street":"Waldeck;Tirol",
    "iso:country":"AT",
    "sg:address":"Waldeck 3",
    "sg:city":"Kufstein",
    "sg:orig_category":"Bauunternehmen",
    "sg:phone":"+43 5372 638210",
    "sg:postcode":"6330",
    "sg:province":"Tirol",
    "wof:name":"Kofler Hans BaugesmbH & Co KG",
    "wof:placetype":"venue"
},
  "geometry": {"coordinates":[12.1803531647,47.5983276367],"type":"Point"}
}