{
  "type": "Feature",
  "properties": {
    "addr:full":"Dr \u00d6lz-Str 24 Dornbirn Vorarlberg 6850",
    "addr:housenumber":"24",
    "addr:postcode":"6850",
    "iso:country":"AT",
    "sg:address":"Dr \u00d6lz-Str 24",
    "sg:city":"Dornbirn",
    "sg:orig_category":"Friseure U Frisiersalons",
    "sg:phone":"+43 4355 7233419",
    "sg:postcode":"6850",
    "sg:province":"Vorarlberg",
    "wof:name":"Haar Design - Monika Nebel",
    "wof:placetype":"venue"
},
  "geometry": {"coordinates":[9.7501449585,47.4176712036],"type":"Point"}
}