{
  "type": "Feature",
  "properties": {
    "addr:full":"Nr 222 Turnau Steiermark 8625",
    "addr:postcode":"8625",
    "addr:street":"Nr 222",
    "iso:country":"AT",
    "sg:address":"Nr 222",
    "sg:city":"Turnau",
    "sg:orig_category":"Blumeneinzelhandel",
    "sg:phone":"+43 3863 2461",
    "sg:postcode":"8625",
    "sg:province":"Steiermark",
    "wof:name":"Barbara's Blumenladen Stieg und Grammelhofer OEG",
    "wof:placetype":"venue"
},
  "geometry": {"coordinates":[15.3370742798,47.5582237244],"type":"Point"}
}