{
  "type": "Feature",
  "properties": {
    "addr:full":"Stiftg 4 Innsbruck Tirol 6020",
    "addr:housenumber":"4",
    "addr:postcode":"6020",
    "addr:street":"Stiftg;Tirol",
    "iso:country":"AT",
    "sg:address":"Stiftg 4",
    "sg:city":"Innsbruck",
    "sg:orig_category":"Fleischhauereien",
    "sg:phone":"+43 512 588816",
    "sg:postcode":"6020",
    "sg:province":"Tirol",
    "wof:name":"s'Speckladele",
    "wof:placetype":"venue"
},
  "geometry": {"coordinates":[11.3944625854,47.2682914734],"type":"Point"}
}