{
  "type": "Feature",
  "properties": {
    "addr:full":"Ehrenbrunng 1 Schwechat Nieder\u00f6sterreich 2320",
    "addr:housenumber":"1",
    "addr:postcode":"2320",
    "addr:street":"Ehrenbrunng;Niederoesterreich",
    "iso:country":"AT",
    "sg:address":"Ehrenbrunng 1",
    "sg:city":"Schwechat",
    "sg:orig_category":"Installationsunternehmen",
    "sg:phone":"+43 1 7076510",
    "sg:postcode":"2320",
    "sg:province":"Nieder\u00f6sterreich",
    "wof:name":"Ruck Alois",
    "wof:placetype":"venue"
},
  "geometry": {"coordinates":[16.4801883698,48.1403617859],"type":"Point"}
}