{
  "type": "Feature",
  "properties": {
    "iso:country":"AT",
    "sg:address":"Au 149",
    "sg:city":"Abtenau",
    "sg:orig_category":"Bierdepots",
    "sg:phone":"+43 6243 2462",
    "sg:postcode":"5441",
    "sg:province":"Salzburg",
    "wof:name":"Schwaighofer Martina",
    "wof:placetype":"venue"
},
  "geometry": {"coordinates":[13.348446846,47.5548973083],"type":"Point"}
}