{
  "type": "Feature",
  "properties": {
    "addr:full":"Hetzendorfer Str 100-104 Wien Wien 1120",
    "addr:housenumber":"100-104",
    "addr:postcode":"1120",
    "addr:street":"Str",
    "iso:country":"AT",
    "sg:address":"Hetzendorfer Str 100-104",
    "sg:city":"Wien",
    "sg:orig_category":"Lederwaren / Einzelhandel",
    "sg:phone":"+43 1 8023445",
    "sg:postcode":"1120",
    "sg:province":"Wien",
    "wof:name":"Deiml Wolfgang",
    "wof:placetype":"venue"
},
  "geometry": {"coordinates":[16.3069095612,48.1676483154],"type":"Point"}
}