{
  "type": "Feature",
  "properties": {
    "addr:full":"Landstr 3 Linz Ober\u00f6sterreich 4020",
    "addr:housenumber":"3",
    "addr:postcode":"4020",
    "addr:street":"Landstr",
    "iso:country":"AT",
    "sg:address":"Landstr 3",
    "sg:city":"Linz",
    "sg:orig_category":"Restaurants: Amerikanisch",
    "sg:phone":"+43 732 781622",
    "sg:postcode":"4020",
    "sg:province":"Ober\u00f6sterreich",
    "wof:name":"McDonald's Restaurant",
    "wof:placetype":"venue"
},
  "geometry": {"coordinates":[14.2883663177,48.3040275574],"type":"Point"}
}