{
  "type": "Feature",
  "properties": {
    "addr:full":"Zeller Str 18 Mittersill Salzburg 5730",
    "addr:housenumber":"18",
    "addr:postcode":"5730",
    "addr:street":"Zeller Str;Salzburg",
    "iso:country":"AT",
    "sg:address":"Zeller Str 18",
    "sg:city":"Mittersill",
    "sg:orig_category":"Schmieden U Schmiedeeisenelemente",
    "sg:phone":"+43 4365 624091",
    "sg:postcode":"5730",
    "sg:province":"Salzburg",
    "wof:name":"M\u00f6schl Josef",
    "wof:placetype":"venue"
},
  "geometry": {"coordinates":[12.4895820618,47.2850151062],"type":"Point"}
}