{
  "type": "Feature",
  "properties": {
    "iso:country":"AT",
    "sg:address":"Nr 101",
    "sg:city":"Taufkirchen an der Pram",
    "sg:classifiers":[
        {
            "category":"Utilities",
            "subcategory":"Refuse",
            "type":"Services"
        }
    ],
    "sg:phone":"+43 4377 198790",
    "sg:postcode":"4775",
    "sg:province":"Ober\u00f6sterreich",
    "sg:tags":[
        "catering"
    ],
    "wof:name":"Koch & Co",
    "wof:placetype":"venue"
},
  "geometry": {"coordinates":[13.5362701416,48.4104499817],"type":"Point"}
}