{
  "type": "Feature",
  "properties": {
    "addr:full":"Gundertshausen 63 Eggelsberg Ober\u00f6sterreich 5142",
    "addr:housenumber":"63",
    "addr:postcode":"5142",
    "addr:street":"Gundertshausen;Oberoesterreich",
    "iso:country":"AT",
    "sg:address":"Gundertshausen 63",
    "sg:city":"Eggelsberg",
    "sg:classifiers":[
        {
            "category":"Shopping",
            "subcategory":"Department Store",
            "type":"Retail Goods"
        }
    ],
    "sg:phone":"+43 7748 2632",
    "sg:postcode":"5142",
    "sg:province":"Ober\u00f6sterreich",
    "sg:tags":[
        "inside",
        "finishing",
        "storehouse"
    ],
    "wof:name":"Franz Birgmann Tischlerei GesmbH",
    "wof:placetype":"venue"
},
  "geometry": {"coordinates":[12.9934387207,48.0895576477],"type":"Point"}
}