{
  "type": "Feature",
  "properties": {
    "addr:full":"Alexander-Poch-Pl 2 Wien Wien 1020",
    "addr:housenumber":"2",
    "addr:postcode":"1020",
    "addr:street":"Alexander-Poch-Pl",
    "iso:country":"AT",
    "sg:address":"Alexander-Poch-Pl 2",
    "sg:city":"Wien",
    "sg:orig_category":"Ambulatorien",
    "sg:phone":"+43 1 2143821",
    "sg:postcode":"1020",
    "sg:province":"Wien",
    "wof:name":"Ambulatorium Elita Privatkrankenanstalt f nat\u00fcrl Haarchirurgie",
    "wof:placetype":"venue"
},
  "geometry": {"coordinates":[16.3788280487,48.2188415527],"type":"Point"}
}