{
  "type": "Feature",
  "properties": {
    "iso:country":"AT",
    "sg:address":"Theaterg 9",
    "sg:city":"Gmunden",
    "sg:orig_category":"Juweliere, Gold- U Silberschmiede",
    "sg:phone":"+43 4376 1265261",
    "sg:postcode":"4810",
    "sg:province":"Ober\u00f6sterreich",
    "wof:name":"Goldschmiede Eckmann Willy Meisterbetrieb",
    "wof:placetype":"venue"
},
  "geometry": {"coordinates":[13.7982912064,47.9179763794],"type":"Point"}
}