{
  "type": "Feature",
  "properties": {
    "addr:full":"Stift 2 Vorau Steiermark 8250",
    "addr:housenumber":"2",
    "addr:postcode":"8250",
    "addr:street":"Stift",
    "iso:country":"AT",
    "sg:address":"Stift 2",
    "sg:city":"Vorau",
    "sg:orig_category":"Notare",
    "sg:phone":"+43 3337 41140",
    "sg:postcode":"8250",
    "sg:province":"Steiermark",
    "wof:name":"Preihs Michael Mag",
    "wof:placetype":"venue"
},
  "geometry": {"coordinates":[15.8873929977,47.4056854248],"type":"Point"}
}