{
  "type": "Feature",
  "properties": {
    "addr:full":"Erentrudisstr 19/14 Salzburg Salzburg 5020",
    "addr:housenumber":"19 / 14",
    "addr:postcode":"5020",
    "addr:street":"Erentrudisstr;Salzburg",
    "iso:country":"AT",
    "sg:address":"Erentrudisstr 19/14",
    "sg:city":"Salzburg",
    "sg:orig_category":"Architekten",
    "sg:phone":"+43 662 6209910",
    "sg:postcode":"5020",
    "sg:province":"Salzburg",
    "wof:name":"Fally Erich Ekkart BR hc Dipl-Ing",
    "wof:placetype":"venue"
},
  "geometry": {"coordinates":[13.0655794144,47.7831306458],"type":"Point"}
}