{
  "type": "Feature",
  "properties": {
    "addr:full":"Hauptstrasse 16a Seekirchen am Wallersee Salzburg 5201",
    "addr:housenumber":"16a",
    "addr:postcode":"5201",
    "addr:street":"Hauptstrasse;Salzburg",
    "iso:country":"AT",
    "sg:address":"Hauptstrasse 16a",
    "sg:city":"Seekirchen am Wallersee",
    "sg:classifiers":[
        {
            "category":"Manufacturing",
            "subcategory":"Metals",
            "type":"Manufacturing & Wholesale Goods"
        }
    ],
    "sg:phone":"+43 6212 303200",
    "sg:postcode":"5201",
    "sg:province":"Salzburg",
    "sg:tags":[
        "profile",
        "aluminium",
        "working"
    ],
    "sg:website":"lp-trading.com",
    "wof:name":"LP Trading GmbH.",
    "wof:placetype":"venue"
},
  "geometry": {"coordinates":[13.1264982224,47.8926315308],"type":"Point"}
}