{
  "type": "Feature",
  "properties": {
    "addr:full":"Nr 25 Gnigl Salzburg 5023",
    "addr:postcode":"5023",
    "addr:street":"Nr 25",
    "iso:country":"AT",
    "sg:address":"Nr 25",
    "sg:city":"Gnigl",
    "sg:orig_category":"Volksschulen",
    "sg:phone":"+43 662 640357",
    "sg:postcode":"5023",
    "sg:province":"Salzburg",
    "wof:name":"Volksschule",
    "wof:placetype":"venue"
},
  "geometry": {"coordinates":[13.1081838608,47.8200416565],"type":"Point"}
}