{
  "type": "Feature",
  "properties": {
    "addr:full":"Konradsdlg 202 Maria Lankowitz Steiermark 8591",
    "addr:housenumber":"202",
    "addr:postcode":"8591",
    "iso:country":"AT",
    "sg:address":"Konradsdlg 202",
    "sg:city":"Maria Lankowitz",
    "sg:orig_category":"Lebens- U Sozialberatung",
    "sg:phone":"+43 4367 63830316",
    "sg:postcode":"8591",
    "sg:province":"Steiermark",
    "wof:name":"Mayer Johanna",
    "wof:placetype":"venue"
},
  "geometry": {"coordinates":[15.0651445389,47.0628318787],"type":"Point"}
}