{
  "type": "Feature",
  "properties": {
    "addr:full":"Nr 76 St. Ruprecht an der Raab Steiermark 8181",
    "addr:postcode":"8181",
    "addr:street":"Nr 76",
    "iso:country":"AT",
    "sg:address":"Nr 76",
    "sg:city":"St. Ruprecht an der Raab",
    "sg:orig_category":"Autoverwertung",
    "sg:phone":"+43 4331 772470",
    "sg:postcode":"8181",
    "sg:province":"Steiermark",
    "wof:name":"Steiner Helmut",
    "wof:placetype":"venue"
},
  "geometry": {"coordinates":[15.6658182144,47.1803436279],"type":"Point"}
}