{
  "type": "Feature",
  "properties": {
    "addr:full":"Vinzenzg Wien Wien 1180",
    "addr:postcode":"1180",
    "iso:country":"AT",
    "sg:address":"Vinzenzg",
    "sg:city":"Wien",
    "sg:orig_category":"Non-Classified Establishments",
    "sg:phone":"+43 1 4704177",
    "sg:postcode":"1180",
    "sg:province":"Wien",
    "wof:name":"TAXI-TEL Standplatztelefon Betriebs GmbH",
    "wof:placetype":"venue"
},
  "geometry": {"coordinates":[16.3362846375,48.2277259827],"type":"Point"}
}