{
  "type": "Feature",
  "properties": {
    "addr:full":"Girardigasse 5 Wien Wien 1060",
    "addr:housenumber":"5",
    "addr:postcode":"1060",
    "addr:street":"Girardigasse",
    "iso:country":"AT",
    "sg:address":"Girardigasse 5",
    "sg:city":"Wien",
    "sg:classifiers":[
        {
            "category":"Building & Trades",
            "subcategory":"Plumbing",
            "type":"Services"
        }
    ],
    "sg:phone":"+43 1 5874358",
    "sg:postcode":"1060",
    "sg:province":"Wien",
    "sg:tags":[
        "supraregional",
        "gas"
    ],
    "sg:website":"poelzl.com",
    "wof:name":"Christoph P\u00f6lzl GmbH",
    "wof:placetype":"venue"
},
  "geometry": {"coordinates":[16.3618602753,48.1989402771],"type":"Point"}
}