{
  "type": "Feature",
  "properties": {
    "addr:full":"Weignersdorf 7 Hellmons\u00f6dt Ober\u00f6sterreich 4202",
    "addr:housenumber":"7",
    "addr:postcode":"4202",
    "addr:street":"Weignersdorf;Oberoesterreich",
    "iso:country":"AT",
    "sg:address":"Weignersdorf 7",
    "sg:city":"Hellmons\u00f6dt",
    "sg:classifiers":[
        {
            "category":"Taxi",
            "type":"Transportation"
        }
    ],
    "sg:phone":"+43 4372 118700",
    "sg:postcode":"4202",
    "sg:province":"Ober\u00f6sterreich",
    "sg:tags":[
        "personentransporte",
        "u"
    ],
    "wof:name":"Krenn Berta Taxi - Mietwagen",
    "wof:placetype":"venue"
},
  "geometry": {"coordinates":[14.3436765671,48.4187278748],"type":"Point"}
}