{
  "type": "Feature",
  "properties": {
    "addr:full":"Kottulinskystr 17 St. Georgen im Attergau Ober\u00f6sterreich 4880",
    "addr:housenumber":"17",
    "addr:postcode":"4880",
    "addr:street":"Kottulinskystr",
    "iso:country":"AT",
    "sg:address":"Kottulinskystr 17",
    "sg:city":"St. Georgen im Attergau",
    "sg:classifiers":[
        {
            "category":"Travel",
            "subcategory":"Hotels & Motels",
            "type":"Entertainment"
        }
    ],
    "sg:phone":"+43 4376 6787000",
    "sg:postcode":"4880",
    "sg:province":"Ober\u00f6sterreich",
    "wof:name":"Hotel Tirolerhof",
    "wof:placetype":"venue"
},
  "geometry": {"coordinates":[13.4833154678,47.9379806519],"type":"Point"}
}