{
  "type": "Feature",
  "properties": {
    "addr:full":"Ludwig Benedek-G 13 Stra\u00dfgang Steiermark 8054",
    "addr:housenumber":"13",
    "addr:postcode":"8054",
    "iso:country":"AT",
    "sg:address":"Ludwig Benedek-G 13",
    "sg:city":"Stra\u00dfgang",
    "sg:orig_category":"Transportunternehmen",
    "sg:phone":"+43 3135 52051",
    "sg:postcode":"8054",
    "sg:province":"Steiermark",
    "wof:name":"Pfeiffer Werner - Transport- und Express-Service",
    "wof:placetype":"venue"
},
  "geometry": {"coordinates":[15.4018421173,47.0352516174],"type":"Point"}
}