{
  "type": "Feature",
  "properties": {
    "addr:full":"Ortsstr 91 Etsdorf am Kamp Nieder\u00f6sterreich 3492",
    "addr:housenumber":"91",
    "addr:postcode":"3492",
    "addr:street":"Ortsstr;Niederoesterreich",
    "iso:country":"AT",
    "sg:address":"Ortsstr 91",
    "sg:city":"Etsdorf am Kamp",
    "sg:orig_category":"Pensionen / Privatzimmer",
    "sg:phone":"+43 4327 3532550",
    "sg:postcode":"3492",
    "sg:province":"Nieder\u00f6sterreich",
    "wof:name":"Mau\u00df Edith",
    "wof:placetype":"venue"
},
  "geometry": {"coordinates":[15.7310943604,48.449344635],"type":"Point"}
}