{
  "type": "Feature",
  "properties": {
    "addr:full":"Leechg 37/1 Graz Steiermark 8010",
    "addr:housenumber":"37 / 1",
    "addr:postcode":"8010",
    "addr:street":"Leechg",
    "iso:country":"AT",
    "sg:address":"Leechg 37/1",
    "sg:city":"Graz",
    "sg:orig_category":"Ingenieurkonsulenten / Zivilingenieure",
    "sg:phone":"+43 316 381915",
    "sg:postcode":"8010",
    "sg:province":"Steiermark",
    "wof:name":"Garber Ernst Dipl-Ing Dr",
    "wof:placetype":"venue"
},
  "geometry": {"coordinates":[15.4573860168,47.0786857605],"type":"Point"}
}