{
  "type": "Feature",
  "properties": {
    "addr:full":"Michael-Gaismair-Str 9 Innsbruck Tirol 6020",
    "addr:housenumber":"9",
    "addr:postcode":"6020",
    "addr:street":"Michael-Gaismair-Str;Tirol",
    "iso:country":"AT",
    "sg:address":"Michael-Gaismair-Str 9",
    "sg:city":"Innsbruck",
    "sg:orig_category":"Werbegrafik- U Grafik-Design",
    "sg:phone":"+43 4365 02181066",
    "sg:postcode":"6020",
    "sg:province":"Tirol",
    "wof:name":"JANTSCHER Werberaum",
    "wof:placetype":"venue"
},
  "geometry": {"coordinates":[11.3964891434,47.2604026794],"type":"Point"}
}