{
  "type": "Feature",
  "properties": {
    "addr:full":"Marktg 2 Wiener Neustadt Nieder\u00f6sterreich 2700",
    "addr:housenumber":"2",
    "addr:postcode":"2700",
    "addr:street":"Marktg",
    "iso:country":"AT",
    "sg:address":"Marktg 2",
    "sg:city":"Wiener Neustadt",
    "sg:orig_category":"Tankstellen",
    "sg:phone":"+43 2622 21678",
    "sg:postcode":"2700",
    "sg:province":"Nieder\u00f6sterreich",
    "wof:name":"SCHNELL & G\u00dcNSTIG Tankstelle",
    "wof:placetype":"venue"
},
  "geometry": {"coordinates":[16.2455158234,47.8128814697],"type":"Point"}
}