{
  "type": "Feature",
  "properties": {
    "addr:full":"Salzburger Strasse 69 Oberndorf Salzburg 5110",
    "addr:housenumber":"69",
    "addr:postcode":"5110",
    "addr:street":"Salzburger Strasse",
    "iso:country":"AT",
    "sg:address":"Salzburger Strasse 69",
    "sg:city":"Oberndorf",
    "sg:classifiers":[
        {
            "category":"Manufacturing",
            "subcategory":"Metals",
            "type":"Manufacturing & Wholesale Goods"
        }
    ],
    "sg:phone":"+43 6272 42844",
    "sg:postcode":"5110",
    "sg:province":"Salzburg",
    "sg:tags":[
        "aluminium"
    ],
    "wof:name":"Ing. Franz Wimmer Schlosserei Ges.m.b.H. & Co KG",
    "wof:placetype":"venue"
},
  "geometry": {"coordinates":[12.9325675964,47.9608917236],"type":"Point"}
}