{
  "type": "Feature",
  "properties": {
    "addr:full":"Hauptstr. 54 Eisenstadt Burgenland 7000",
    "addr:housenumber":"54",
    "addr:postcode":"7000",
    "addr:street":"Hauptstr.",
    "iso:country":"AT",
    "sg:address":"Hauptstr. 54",
    "sg:city":"Eisenstadt",
    "sg:classifiers":[
        {
            "category":"Shopping",
            "subcategory":"Clothing, Apparel, & Fashions",
            "type":"Retail Goods"
        }
    ],
    "sg:phone":"+43 4326 8262126",
    "sg:postcode":"7000",
    "sg:province":"Burgenland",
    "sg:tags":[
        "clothes"
    ],
    "wof:name":"THURNER KG",
    "wof:placetype":"venue"
},
  "geometry": {"coordinates":[16.5257663727,47.8467330933],"type":"Point"}
}