{
  "type": "Feature",
  "properties": {
    "iso:country":"AT",
    "sg:address":"Wiedner Hauptstr 51",
    "sg:city":"Wien",
    "sg:orig_category":"Personalbereitstellung",
    "sg:phone":"+43 1 5036600",
    "sg:postcode":"1040",
    "sg:province":"Wien",
    "wof:name":"Akademischer G\u00e4stedienst i \u00f6sterreich GesmbH",
    "wof:placetype":"venue"
},
  "geometry": {"coordinates":[16.3672103882,48.1925582886],"type":"Point"}
}