{
  "type": "Feature",
  "properties": {
    "addr:full":"Fichtlg 6 Glaubendorf Nieder\u00f6sterreich 3704",
    "addr:housenumber":"6",
    "addr:postcode":"3704",
    "addr:street":"Fichtlg",
    "iso:country":"AT",
    "sg:address":"Fichtlg 6",
    "sg:city":"Glaubendorf",
    "sg:orig_category":"Kosmetikanwendungsberatung",
    "sg:phone":"+43 2956 81043",
    "sg:postcode":"3704",
    "sg:province":"Nieder\u00f6sterreich",
    "wof:name":"Channoine Kosmetik - Anna Seidl",
    "wof:placetype":"venue"
},
  "geometry": {"coordinates":[11.7665901184,51.0020599365],"type":"Point"}
}