{
  "type": "Feature",
  "properties": {
    "addr:full":"Dorfstr 66 St. Anton am Arlberg Tirol 6580",
    "addr:housenumber":"66",
    "addr:postcode":"6580",
    "addr:street":"Dorfstr",
    "iso:country":"AT",
    "sg:address":"Dorfstr 66",
    "sg:city":"St. Anton am Arlberg",
    "sg:orig_category":"Lebensmittel / Einzelhandel",
    "sg:phone":"+43 5446 2997",
    "sg:postcode":"6580",
    "sg:province":"Tirol",
    "wof:name":"Erster Arlberger Sparmarkt",
    "wof:placetype":"venue"
},
  "geometry": {"coordinates":[10.2675504684,47.13048172],"type":"Point"}
}