{
  "type": "Feature",
  "properties": {
    "addr:full":"Breitenfurter Str 299 Wien Wien 1230",
    "addr:housenumber":"299",
    "addr:postcode":"1230",
    "addr:street":"Str",
    "iso:country":"AT",
    "sg:address":"Breitenfurter Str 299",
    "sg:city":"Wien",
    "sg:orig_category":"Non-Classified Establishments",
    "sg:phone":"+43 1 8693386",
    "sg:postcode":"1230",
    "sg:province":"Wien",
    "wof:name":"TAXI-TEL Standplatztelefon Betriebs GmbH",
    "wof:placetype":"venue"
},
  "geometry": {"coordinates":[16.2941036224,48.1450843811],"type":"Point"}
}