{
  "type": "Feature",
  "properties": {
    "iso:country":"AT",
    "sg:address":"Leo-Mathauser-G 51",
    "sg:city":"Wien",
    "sg:orig_category":"Stahlbau",
    "sg:phone":"+43 1 69933750",
    "sg:postcode":"1230",
    "sg:province":"Wien",
    "wof:name":"Rupp Robert GesmbH",
    "wof:placetype":"venue"
},
  "geometry": {"coordinates":[16.3186416626,48.1290779114],"type":"Point"}
}