{
  "type": "Feature",
  "properties": {
    "addr:full":"Marktpl 3 Neumarkt im Hausruckkreis Ober\u00f6sterreich 4720",
    "addr:housenumber":"3",
    "addr:postcode":"4720",
    "addr:street":"Marktpl",
    "iso:country":"AT",
    "sg:address":"Marktpl 3",
    "sg:city":"Neumarkt im Hausruckkreis",
    "sg:orig_category":"Lebensmittel / Einzelhandel",
    "sg:phone":"+43 7733 5004",
    "sg:postcode":"4720",
    "sg:province":"Ober\u00f6sterreich",
    "wof:name":"Spar-Markt Zauner Reinhard",
    "wof:placetype":"venue"
},
  "geometry": {"coordinates":[13.7265558243,48.2734260559],"type":"Point"}
}