{
  "type": "Feature",
  "properties": {
    "addr:full":"Penzendorf 66 Hartberg Steiermark 8230",
    "addr:housenumber":"66",
    "addr:postcode":"8230",
    "addr:street":"Penzendorf",
    "iso:country":"AT",
    "sg:address":"Penzendorf 66",
    "sg:city":"Hartberg",
    "sg:classifiers":[
        {
            "category":"Professional",
            "subcategory":"Engineering",
            "type":"Services"
        }
    ],
    "sg:phone":"+43 4333 3260210",
    "sg:postcode":"8230",
    "sg:province":"Steiermark",
    "sg:tags":[
        "machine",
        "-",
        "mechanical"
    ],
    "wof:name":"V T TROCKENTECHNIK GMBH",
    "wof:placetype":"venue"
},
  "geometry": {"coordinates":[15.9727478027,47.2819519043],"type":"Point"}
}