{
  "type": "Feature",
  "properties": {
    "addr:full":"Schwertberg Ober\u00f6sterreich 4311",
    "addr:postcode":"4311",
    "iso:country":"AT",
    "sg:city":"Schwertberg",
    "sg:orig_category":"Feuerwehren",
    "sg:phone":"+43 7236 6978",
    "sg:postcode":"4311",
    "sg:province":"Ober\u00f6sterreich",
    "wof:name":"Freiwillige Feuerwehr Hartl",
    "wof:placetype":"venue"
},
  "geometry": {"coordinates":[14.5817127228,48.2739906311],"type":"Point"}
}