{
  "type": "Feature",
  "properties": {
    "addr:full":"Akaziengasse 30 Wien Wien 1230",
    "addr:housenumber":"30",
    "addr:postcode":"1230",
    "addr:street":"Akaziengasse",
    "iso:country":"AT",
    "sg:address":"Akaziengasse 30",
    "sg:city":"Wien",
    "sg:classifiers":[
        {
            "category":"Wholesale",
            "subcategory":"Construction Materials",
            "type":"Manufacturing & Wholesale Goods"
        }
    ],
    "sg:phone":"+43 1 69987170",
    "sg:postcode":"1230",
    "sg:province":"Wien",
    "sg:tags":[
        "textile",
        "dye"
    ],
    "sg:website":"dystar.com",
    "wof:name":"DyStar-Bencolor Farben GmbH",
    "wof:placetype":"venue"
},
  "geometry": {"coordinates":[16.3175888062,48.1346244812],"type":"Point"}
}