{
  "type": "Feature",
  "properties": {
    "addr:full":"Kircheng 22 Wien Wien 1070",
    "addr:housenumber":"22",
    "addr:postcode":"1070",
    "addr:street":"Kircheng",
    "iso:country":"AT",
    "sg:address":"Kircheng 22",
    "sg:city":"Wien",
    "sg:orig_category":"Orientteppiche",
    "sg:phone":"+43 1 4090917",
    "sg:postcode":"1070",
    "sg:province":"Wien",
    "wof:name":"Studio 1001",
    "wof:placetype":"venue"
},
  "geometry": {"coordinates":[16.3522396088,48.201461792],"type":"Point"}
}