{
  "type": "Feature",
  "properties": {
    "iso:country":"AT",
    "sg:address":"H\u00f6schm\u00fchl",
    "sg:city":"Waldzell",
    "sg:orig_category":"Tischlereien",
    "sg:phone":"+43 7754 3216",
    "sg:postcode":"4924",
    "sg:province":"Ober\u00f6sterreich",
    "wof:name":"Emprechtinger Johann",
    "wof:placetype":"venue"
},
  "geometry": {"coordinates":[13.4262657166,48.1358413696],"type":"Point"}
}