{
  "type": "Feature",
  "properties": {
    "iso:country":"AT",
    "sg:address":"Bergzeile 3",
    "sg:city":"Wien",
    "sg:classifiers":[
        {
            "category":"Real Estate",
            "subcategory":"Real Estate Services",
            "type":"Services"
        }
    ],
    "sg:phone":"+43 1 4405480",
    "sg:postcode":"1170",
    "sg:province":"Wien",
    "sg:tags":[
        "development",
        "management"
    ],
    "wof:name":"ESTATE STARKL Liegenschaftsverwertungs KEG",
    "wof:placetype":"venue"
},
  "geometry": {"coordinates":[16.2744865417,48.2523498535],"type":"Point"}
}