{
  "type": "Feature",
  "properties": {
    "addr:full":"Unterh\u00f6rbach 22 Vorchdorf Ober\u00f6sterreich 4655",
    "addr:housenumber":"22",
    "addr:postcode":"4655",
    "addr:street":"Unterhoerbach",
    "iso:country":"AT",
    "sg:address":"Unterh\u00f6rbach 22",
    "sg:city":"Vorchdorf",
    "sg:orig_category":"Installationsunternehmen, Installationsmaterialien",
    "sg:phone":"+43 761473340",
    "sg:postcode":"4655",
    "sg:province":"Ober\u00f6sterreich",
    "wof:name":"Laimer Martin",
    "wof:placetype":"venue"
},
  "geometry": {"coordinates":[13.8990745544,48.0139808655],"type":"Point"}
}