{
  "type": "Feature",
  "properties": {
    "iso:country":"AT",
    "sg:address":"Michlbach 1",
    "sg:city":"Maria Schmolln",
    "sg:orig_category":"Appartements / Ferienwohnungen",
    "sg:phone":"+43 7743 2409",
    "sg:postcode":"5241",
    "sg:province":"Ober\u00f6sterreich",
    "wof:name":"Ferienhof Weber Fam Maierhofer",
    "wof:placetype":"venue"
},
  "geometry": {"coordinates":[13.2479791641,48.1387329102],"type":"Point"}
}