{
  "type": "Feature",
  "properties": {
    "iso:country":"AT",
    "sg:address":"Laudongasse 9",
    "sg:city":"Wien",
    "sg:classifiers":[
        {
            "category":"Health Services",
            "subcategory":"Podiatrist",
            "type":"Services"
        }
    ],
    "sg:phone":"+43 1 4899668",
    "sg:postcode":"1080",
    "sg:province":"Wien",
    "sg:tags":[
        "insole",
        "support",
        "orthopedic",
        "arch"
    ],
    "wof:name":"Alois Novotny Orthop\u00e4disches Institut GesmbH",
    "wof:placetype":"venue"
},
  "geometry": {"coordinates":[16.3520774841,48.2132606506],"type":"Point"}
}