{
  "type": "Feature",
  "properties": {
    "addr:full":"B\u00fchel 106  Hippach Tirol 6283",
    "addr:housenumber":"106",
    "addr:postcode":"6283",
    "addr:street":"Hippach Tirol",
    "iso:country":"AT",
    "sg:address":"B\u00fchel 106 ",
    "sg:city":"Hippach",
    "sg:classifiers":[
        {
            "category":"Building & Trades",
            "subcategory":"Plumbing",
            "type":"Services"
        }
    ],
    "sg:phone":"+43 5282 3381",
    "sg:postcode":"6283",
    "sg:province":"Tirol",
    "sg:tags":[
        "supraregional",
        "gas"
    ],
    "wof:name":"Alfred Winkler",
    "wof:placetype":"venue"
},
  "geometry": {"coordinates":[11.8661670685,47.2039108276],"type":"Point"}
}