{
  "type": "Feature",
  "properties": {
    "iso:country":"AT",
    "sg:address":"Granglerweg 5",
    "sg:city":"Radenthein",
    "sg:orig_category":"Pensionen / Privatzimmer",
    "sg:phone":"+43 4246 2568",
    "sg:postcode":"9545",
    "sg:province":"K\u00e4rnten",
    "wof:name":"Rauter Hans",
    "wof:placetype":"venue"
},
  "geometry": {"coordinates":[13.7309541702,46.7936935425],"type":"Point"}
}