{
  "type": "Feature",
  "properties": {
    "iso:country":"AT",
    "sg:address":"Bahnstr 26",
    "sg:city":"Atzenbrugg",
    "sg:orig_category":"Wasseraufbereitung U -Reinigung",
    "sg:phone":"+43 2275 6105",
    "sg:postcode":"3452",
    "sg:province":"Nieder\u00f6sterreich",
    "wof:name":"Egretzberger Annemarie",
    "wof:placetype":"venue"
},
  "geometry": {"coordinates":[15.9106740952,48.2929153442],"type":"Point"}
}