{
  "type": "Feature",
  "properties": {
    "addr:full":"Bahnstr 26 Atzenbrugg Nieder\u00f6sterreich 3452",
    "addr:housenumber":"26",
    "addr:postcode":"3452",
    "addr:street":"Bahnstr",
    "iso:country":"AT",
    "sg:address":"Bahnstr 26",
    "sg:city":"Atzenbrugg",
    "sg:orig_category":"Wasseraufbereitung U -Reinigung",
    "sg:phone":"+43 2275 6105",
    "sg:postcode":"3452",
    "sg:province":"Nieder\u00f6sterreich",
    "wof:name":"Egretzberger Annemarie",
    "wof:placetype":"venue"
},
  "geometry": {"coordinates":[15.9106740952,48.2929153442],"type":"Point"}
}