{
  "type": "Feature",
  "properties": {
    "iso:country":"AT",
    "sg:address":"Fadingerstr 15",
    "sg:city":"Waizenkirchen",
    "sg:orig_category":"Steuerberatung",
    "sg:phone":"+43 4372 772232",
    "sg:postcode":"4730",
    "sg:province":"Ober\u00f6sterreich",
    "wof:name":"Doppelbauer Norbert Mag",
    "wof:placetype":"venue"
},
  "geometry": {"coordinates":[13.8577327728,48.3310432434],"type":"Point"}
}