{
  "type": "Feature",
  "properties": {
    "iso:country":"AT",
    "sg:address":"Baiernstr 52",
    "sg:city":"Graz",
    "sg:classifiers":[
        {
            "category":"Restaurant",
            "type":"Food & Drink"
        }
    ],
    "sg:phone":"+43 316 576573",
    "sg:postcode":"8020",
    "sg:province":"Steiermark",
    "sg:website":"pharaonentempel.com",
    "wof:name":"Pharaonentempel",
    "wof:placetype":"venue"
},
  "geometry": {"coordinates":[15.3905544281,47.0711898804],"type":"Point"}
}