{
  "type": "Feature",
  "properties": {
    "addr:full":"Vierbatzstr 7 Perchtoldsdorf Nieder\u00f6sterreich 2380",
    "addr:housenumber":"7",
    "addr:postcode":"2380",
    "addr:street":"Vierbatzstr",
    "iso:country":"AT",
    "sg:address":"Vierbatzstr 7",
    "sg:city":"Perchtoldsdorf",
    "sg:orig_category":"Befestigungstechnik",
    "sg:phone":"+43 1 8898461",
    "sg:postcode":"2380",
    "sg:province":"Nieder\u00f6sterreich",
    "wof:name":"Scholly Montagezubeh\u00f6r GmbH",
    "wof:placetype":"venue"
},
  "geometry": {"coordinates":[16.2753696442,48.1137809753],"type":"Point"}
}