{
  "type": "Feature",
  "properties": {
    "addr:full":"Hauptpl 13 Drosendorf an der Thaya Nieder\u00f6sterreich 2095",
    "addr:housenumber":"13",
    "addr:postcode":"2095",
    "addr:street":"Hauptpl;An Der Thaya",
    "iso:country":"AT",
    "sg:address":"Hauptpl 13",
    "sg:city":"Drosendorf an der Thaya",
    "sg:orig_category":"Drogerien",
    "sg:phone":"+43 4329 152530",
    "sg:postcode":"2095",
    "sg:province":"Nieder\u00f6sterreich",
    "wof:name":"Drogerie Kaiser Doris",
    "wof:placetype":"venue"
},
  "geometry": {"coordinates":[15.6200714111,48.8680000305],"type":"Point"}
}