{
  "type": "Feature",
  "properties": {
    "iso:country":"AT",
    "sg:address":"Hauptpl 13",
    "sg:city":"Drosendorf an der Thaya",
    "sg:orig_category":"Drogerien",
    "sg:phone":"+43 4329 152530",
    "sg:postcode":"2095",
    "sg:province":"Nieder\u00f6sterreich",
    "wof:name":"Drogerie Kaiser Doris",
    "wof:placetype":"venue"
},
  "geometry": {"coordinates":[15.6200714111,48.8680000305],"type":"Point"}
}