{
  "type": "Feature",
  "properties": {
    "addr:full":"Nr 12 Lofer Salzburg 5090",
    "addr:postcode":"5090",
    "addr:street":"Nr;Lofer",
    "iso:country":"AT",
    "sg:address":"Nr 12",
    "sg:city":"Lofer",
    "sg:orig_category":"Glasereien",
    "sg:phone":"+43 6588 8273",
    "sg:postcode":"5090",
    "sg:province":"Salzburg",
    "wof:name":"Glas Einwaller - Johann Einwaller",
    "wof:placetype":"venue"
},
  "geometry": {"coordinates":[12.6930541992,47.5873069763],"type":"Point"}
}