{
  "type": "Feature",
  "properties": {
    "addr:full":"Bahnstegg 17-19 Wien Wien 1210",
    "addr:postcode":"17-19;1210",
    "iso:country":"AT",
    "sg:address":"Bahnstegg 17-19",
    "sg:city":"Wien",
    "sg:orig_category":"Telekommunikation",
    "sg:phone":"+43 800 100100",
    "sg:postcode":"1210",
    "sg:province":"Wien",
    "wof:name":"Telekom Shop",
    "wof:placetype":"venue"
},
  "geometry": {"coordinates":[16.3992118835,48.2648086548],"type":"Point"}
}