{
  "type": "Feature",
  "properties": {
    "addr:full":"Marxerg 15 Wien Wien 1030",
    "addr:housenumber":"15",
    "addr:postcode":"1030",
    "addr:street":"Marxerg",
    "iso:country":"AT",
    "sg:address":"Marxerg 15",
    "sg:city":"Wien",
    "sg:orig_category":"Restaurants: Japanisch",
    "sg:phone":"+43 1 7133734",
    "sg:postcode":"1030",
    "sg:province":"Wien",
    "wof:name":"Rikyu Japanisches Restaurant",
    "wof:placetype":"venue"
},
  "geometry": {"coordinates":[16.3905296326,48.206867218],"type":"Point"}
}