{
  "type": "Feature",
  "properties": {
    "iso:country":"AT",
    "sg:address":"Hauptpl 30",
    "sg:city":"Mistelbach",
    "sg:classifiers":[
        {
            "category":"Professional",
            "subcategory":"Advertising",
            "type":"Services"
        }
    ],
    "sg:phone":"+43 4325 722277",
    "sg:postcode":"2130",
    "sg:province":"Nieder\u00f6sterreich",
    "sg:tags":[
        "communication",
        "medium"
    ],
    "wof:name":"PUCHNER FOTOFACHGESCH\u00c4FT ILSE PUCHNER-LAHOFER",
    "wof:placetype":"venue"
},
  "geometry": {"coordinates":[16.5716533661,48.5688056946],"type":"Point"}
}