{
  "type": "Feature",
  "properties": {
    "addr:full":"Mariahilfer Str 48 Wien Wien 1070",
    "addr:postcode":"1070",
    "addr:street":"Str 48",
    "iso:country":"AT",
    "sg:address":"Mariahilfer Str 48",
    "sg:city":"Wien",
    "sg:orig_category":"Tabaktrafiken",
    "sg:phone":"+43 1 5230260",
    "sg:postcode":"1070",
    "sg:province":"Wien",
    "wof:name":"Pelz Wolfgang",
    "wof:placetype":"venue"
},
  "geometry": {"coordinates":[16.3530578613,48.1996459961],"type":"Point"}
}