{
  "type": "Feature",
  "properties": {
    "addr:full":"Mariahilfer Str 107 Wien Wien 1060",
    "addr:housenumber":"107",
    "addr:postcode":"1060",
    "iso:country":"AT",
    "sg:address":"Mariahilfer Str 107",
    "sg:city":"Wien",
    "sg:orig_category":"Notare",
    "sg:phone":"+43 1 59724450",
    "sg:postcode":"1060",
    "sg:province":"Wien",
    "wof:name":"Romstorfer Manfred Dr",
    "wof:placetype":"venue"
},
  "geometry": {"coordinates":[16.3448295593,48.1967315674],"type":"Point"}
}