{
  "type": "Feature",
  "properties": {
    "iso:country":"AT",
    "sg:address":"Sebastian-Frisch-Str 15",
    "sg:city":"Kirchbichl",
    "sg:orig_category":"Volksschulen",
    "sg:phone":"+43 5332 87129",
    "sg:postcode":"6322",
    "sg:province":"Tirol",
    "wof:name":"Volksschule",
    "wof:placetype":"venue"
},
  "geometry": {"coordinates":[12.087264061,47.5130882263],"type":"Point"}
}