{
  "type": "Feature",
  "properties": {
    "iso:country":"AT",
    "sg:address":"Villacher Str 28b/2",
    "sg:city":"Spittal an der Drau",
    "sg:orig_category":"\u00c3\u201erzte / F Allgemeinmedizin",
    "sg:phone":"+43 4762 336600",
    "sg:postcode":"9800",
    "sg:province":"K\u00e4rnten",
    "wof:name":"Kovacic Werner Dr",
    "wof:placetype":"venue"
},
  "geometry": {"coordinates":[13.5045747757,46.7934265137],"type":"Point"}
}