{
  "type": "Feature",
  "properties": {
    "addr:full":"Weinheberstr 126 Neulengbach Nieder\u00f6sterreich 3040",
    "addr:housenumber":"126",
    "addr:postcode":"3040",
    "iso:country":"AT",
    "sg:address":"Weinheberstr 126",
    "sg:city":"Neulengbach",
    "sg:orig_category":"Volksschulen",
    "sg:phone":"+43 2772 523170",
    "sg:postcode":"3040",
    "sg:province":"Nieder\u00f6sterreich",
    "wof:name":"Volksschule",
    "wof:placetype":"venue"
},
  "geometry": {"coordinates":[15.9097547531,48.1972007751],"type":"Point"}
}