{
  "type": "Feature",
  "properties": {
    "addr:full":"Gemeindeweg 6 St. Georgen Salzburg 5113",
    "addr:housenumber":"6",
    "addr:postcode":"5113",
    "addr:street":"Gemeindeweg",
    "iso:country":"AT",
    "sg:address":"Gemeindeweg 6",
    "sg:city":"St. Georgen",
    "sg:orig_category":"Gemeinden",
    "sg:phone":"+43 4362 7229290",
    "sg:postcode":"5113",
    "sg:province":"Salzburg",
    "wof:name":"Gemeindeamt St. Georgen bei Salzburg",
    "wof:placetype":"venue"
},
  "geometry": {"coordinates":[12.8920860291,47.9710693359],"type":"Point"}
}