{
  "type": "Feature",
  "properties": {
    "addr:full":"Heindlkai 9 Mauthausen Ober\u00f6sterreich 4310",
    "addr:housenumber":"9",
    "addr:postcode":"4310",
    "addr:street":"Heindlkai",
    "iso:country":"AT",
    "sg:address":"Heindlkai 9",
    "sg:city":"Mauthausen",
    "sg:orig_category":"Textilreinigung",
    "sg:phone":"+43 7238 2606",
    "sg:postcode":"4310",
    "sg:province":"Ober\u00f6sterreich",
    "wof:name":"Huemer V & Co",
    "wof:placetype":"venue"
},
  "geometry": {"coordinates":[14.5170974731,48.2402305603],"type":"Point"}
}