{
  "type": "Feature",
  "properties": {
    "addr:full":"Holthausstr 2 Engerwitzdorf Ober\u00f6sterreich 4209",
    "addr:housenumber":"2",
    "addr:postcode":"4209",
    "addr:street":"Holthausstr",
    "iso:country":"AT",
    "sg:address":"Holthausstr 2",
    "sg:city":"Engerwitzdorf",
    "sg:orig_category":"Holzbearbeitungsmaschinen U -Werkzeuge",
    "sg:phone":"+43 4372 3550500",
    "sg:postcode":"4209",
    "sg:province":"Ober\u00f6sterreich",
    "wof:name":"HOLTHAUS-Maschinen Nfg. KG",
    "wof:placetype":"venue"
},
  "geometry": {"coordinates":[14.4413757324,48.3437614441],"type":"Point"}
}