{
  "type": "Feature",
  "properties": {
    "addr:full":"Gredlerstr 5 Wien Wien 1020",
    "addr:housenumber":"5",
    "addr:postcode":"1020",
    "addr:street":"Gredlerstr",
    "iso:country":"AT",
    "sg:address":"Gredlerstr 5",
    "sg:city":"Wien",
    "sg:orig_category":"Medizinische Institute",
    "sg:phone":"+43 1 2149721",
    "sg:postcode":"1020",
    "sg:province":"Wien",
    "wof:name":"Medichron GesmbH",
    "wof:placetype":"venue"
},
  "geometry": {"coordinates":[16.3784275055,48.2137374878],"type":"Point"}
}