{
  "type": "Feature",
  "properties": {
    "addr:full":"Rudi Matt-Weg 10 St. Anton am Arlberg Tirol 6580",
    "addr:housenumber":"10",
    "addr:postcode":"6580",
    "addr:street":"Matt-Weg;Tirol",
    "iso:country":"AT",
    "sg:address":"Rudi Matt-Weg 10",
    "sg:city":"St. Anton am Arlberg",
    "sg:orig_category":"Freizeitangebote U -Einrichtungen",
    "sg:phone":"+43 4354 462475",
    "sg:postcode":"6580",
    "sg:province":"Tirol",
    "wof:name":"Ferienpark - Heimatmuseum-Minigolf-Stockschie\u00dfbahn-Fischteich",
    "wof:placetype":"venue"
},
  "geometry": {"coordinates":[10.261759758,47.1275787354],"type":"Point"}
}