{
  "type": "Feature",
  "properties": {
    "addr:full":"Br\u00fcnner Strasse 198 Gerasdorf Nieder\u00f6sterreich 2201",
    "addr:housenumber":"198",
    "addr:postcode":"2201",
    "addr:street":"Bruenner Strasse",
    "iso:country":"AT",
    "sg:address":"Br\u00fcnner Strasse 198",
    "sg:city":"Gerasdorf",
    "sg:classifiers":[
        {
            "category":"Military Area",
            "subcategory":"Air Force Base",
            "type":"Public Place"
        }
    ],
    "sg:phone":"+43 2246 25870",
    "sg:postcode":"2201",
    "sg:province":"Nieder\u00f6sterreich",
    "sg:tags":[
        "assembly",
        "furniture"
    ],
    "sg:website":"weinlandmoebel.at",
    "wof:name":"G\u00f6schelbauer Ma\u00dfm\u00f6bel Vertriebs- und Produktionsges.m.b.H.",
    "wof:placetype":"venue"
},
  "geometry": {"coordinates":[16.4562244415,48.3326835632],"type":"Point"}
}