{
  "type": "Feature",
  "properties": {
    "iso:country":"AT",
    "sg:address":"Marktpl 26",
    "sg:city":"Weyer",
    "sg:orig_category":"Elektroinstallationsunternehmen",
    "sg:phone":"+43 7355 6479",
    "sg:postcode":"3335",
    "sg:province":"Ober\u00f6sterreich",
    "wof:name":"Lumplecker Heinrich",
    "wof:placetype":"venue"
},
  "geometry": {"coordinates":[14.6656455994,47.8583068848],"type":"Point"}
}