{
  "type": "Feature",
  "properties": {
    "iso:country":"AT",
    "sg:address":"Elisabethstr 1",
    "sg:city":"Linz",
    "sg:orig_category":"Medizinische Institute",
    "sg:phone":"+43 732 773070",
    "sg:postcode":"4020",
    "sg:province":"Ober\u00f6sterreich",
    "wof:name":"Institut f Herz- und Gef\u00e4\u00dfdiagnostik",
    "wof:placetype":"venue"
},
  "geometry": {"coordinates":[14.2948513031,48.3056755066],"type":"Point"}
}