{
  "type": "Feature",
  "properties": {
    "addr:full":"Defreggerstrasse 14 Innsbruck Tirol 6020",
    "addr:housenumber":"14",
    "addr:postcode":"6020",
    "addr:street":"Defreggerstrasse;Tirol",
    "iso:country":"AT",
    "sg:address":"Defreggerstrasse 14",
    "sg:city":"Innsbruck",
    "sg:classifiers":[
        {
            "category":"Home & Garden",
            "subcategory":"Carpets & Floor Coverings",
            "type":"Retail Goods"
        }
    ],
    "sg:phone":"+43 512 342171",
    "sg:postcode":"6020",
    "sg:province":"Tirol",
    "sg:tags":[
        "carpeting"
    ],
    "wof:name":"Auernig KG",
    "wof:placetype":"venue"
},
  "geometry": {"coordinates":[11.4078960419,47.2645072937],"type":"Point"}
}