{
  "type": "Feature",
  "properties": {
    "addr:full":"Heidesdlg 28A Parndorf Burgenland 7111",
    "addr:housenumber":"28a",
    "addr:postcode":"7111",
    "addr:street":"Heidesdlg",
    "iso:country":"AT",
    "sg:address":"Heidesdlg 28A",
    "sg:city":"Parndorf",
    "sg:orig_category":"Parkettbodenverlegung",
    "sg:phone":"+43 4321 6620650",
    "sg:postcode":"7111",
    "sg:province":"Burgenland",
    "wof:name":"Parkettdesign Alexander Nossner",
    "wof:placetype":"venue"
},
  "geometry": {"coordinates":[16.8575897217,47.9981613159],"type":"Point"}
}