{
  "type": "Feature",
  "properties": {
    "addr:full":"Hauptpl 2 Obersch\u00fctzen Burgenland 7432",
    "addr:housenumber":"2",
    "addr:postcode":"7432",
    "addr:street":"Hauptpl",
    "iso:country":"AT",
    "sg:address":"Hauptpl 2",
    "sg:city":"Obersch\u00fctzen",
    "sg:orig_category":"Banken U Sparkassen",
    "sg:phone":"+43 3353 75640",
    "sg:postcode":"7432",
    "sg:province":"Burgenland",
    "wof:name":"Raiffeisenbank Obersch\u00fctzen-Bernstein-Mariasdorf-Wiesfleck regGenmbH",
    "wof:placetype":"venue"
},
  "geometry": {"coordinates":[16.2076206207,47.3507995605],"type":"Point"}
}