{
  "type": "Feature",
  "properties": {
    "addr:full":"Ottakringer Str 21/1/Top 18 Wien Wien 1160",
    "addr:housenumber":"21 / 1 / top 18",
    "addr:postcode":"1160",
    "addr:street":"Str",
    "iso:country":"AT",
    "sg:address":"Ottakringer Str 21/1/Top 18",
    "sg:city":"Wien",
    "sg:orig_category":"Maler, Anstreicher U Lackierer",
    "sg:phone":"+43 1 4098820",
    "sg:postcode":"1160",
    "sg:province":"Wien",
    "wof:name":"Baku Maler- und Anstreicher GesmbH",
    "wof:placetype":"venue"
},
  "geometry": {"coordinates":[16.2961292267,48.214931488],"type":"Point"}
}