{
  "type": "Feature",
  "properties": {
    "addr:full":"Wiener Str 35 Wolkersdorf im Weinviertel Nieder\u00f6sterreich 2120",
    "addr:housenumber":"35",
    "addr:postcode":"2120",
    "iso:country":"AT",
    "sg:address":"Wiener Str 35",
    "sg:city":"Wolkersdorf im Weinviertel",
    "sg:orig_category":"Autohandel",
    "sg:phone":"+43 2245 24610",
    "sg:postcode":"2120",
    "sg:province":"Nieder\u00f6sterreich",
    "wof:name":"Fr\u00f6hlich Hans",
    "wof:placetype":"venue"
},
  "geometry": {"coordinates":[16.5102310181,48.3777999878],"type":"Point"}
}