{
  "type": "Feature",
  "properties": {
    "iso:country":"AT",
    "sg:address":"Anton-Rauch-Str 6",
    "sg:city":"Innsbruck",
    "sg:orig_category":"Banken U Sparkassen",
    "sg:phone":"+43 4351 2267422",
    "sg:postcode":"6020",
    "sg:province":"Tirol",
    "wof:name":"Tiroler Sparkasse Bank AG Innsbruck",
    "wof:placetype":"venue"
},
  "geometry": {"coordinates":[11.4111642838,47.2827758789],"type":"Point"}
}