{
  "type": "Feature",
  "properties": {
    "addr:full":"Nr 255 Nauders Tirol 6543",
    "addr:postcode":"6543",
    "addr:street":"Nr 255;Tirol",
    "iso:country":"AT",
    "sg:address":"Nr 255",
    "sg:city":"Nauders",
    "sg:orig_category":"Sportschulen",
    "sg:phone":"+43 5473 87681",
    "sg:postcode":"6543",
    "sg:province":"Tirol",
    "wof:name":"ASPO-Alpine Sport Schule Tiroler Oberland",
    "wof:placetype":"venue"
},
  "geometry": {"coordinates":[10.4996595383,46.8896980286],"type":"Point"}
}