{
  "type": "Feature",
  "properties": {
    "addr:full":"Paulanergasse 13/7 Wien Wien 1040",
    "addr:housenumber":"13 / 7",
    "addr:postcode":"1040",
    "addr:street":"Paulanergasse",
    "iso:country":"AT",
    "sg:address":"Paulanergasse 13/7",
    "sg:city":"Wien",
    "sg:classifiers":[
        {
            "category":"Professional",
            "subcategory":"Accounting & Tax Preparation",
            "type":"Services"
        }
    ],
    "sg:phone":"+43 1 5855939",
    "sg:postcode":"1040",
    "sg:province":"Wien",
    "sg:tags":[
        "book-keeping"
    ],
    "sg:website":"buchhaltung-lv.at",
    "wof:name":"Martina Scheiber",
    "wof:placetype":"venue"
},
  "geometry": {"coordinates":[16.3656635284,48.1959609985],"type":"Point"}
}