{
  "type": "Feature",
  "properties": {
    "addr:full":"Wagnitzstr 22 Feldkirchen Steiermark 8073",
    "addr:housenumber":"22",
    "addr:postcode":"8073",
    "addr:street":"Wagnitzstr",
    "iso:country":"AT",
    "sg:address":"Wagnitzstr 22",
    "sg:city":"Feldkirchen",
    "sg:classifiers":[
        {
            "category":"Taxi",
            "type":"Transportation"
        }
    ],
    "sg:phone":"+43 4331 6242772",
    "sg:postcode":"8073",
    "sg:province":"Steiermark",
    "sg:tags":[
        "personentransporte",
        "u"
    ],
    "wof:name":"Geider Erich",
    "wof:placetype":"venue"
},
  "geometry": {"coordinates":[15.4573955536,46.9947853088],"type":"Point"}
}