{
  "type": "Feature",
  "properties": {
    "addr:full":"Graf-Starhemberg-G. 14  Wien Wien 1040",
    "addr:housenumber":"14",
    "addr:postcode":"1040",
    "addr:street":"Graf-Starhemberg-G.",
    "iso:country":"AT",
    "sg:address":"Graf-Starhemberg-G. 14 ",
    "sg:city":"Wien",
    "sg:classifiers":[
        {
            "category":"Sports & Exercise",
            "subcategory":"Playing Field",
            "type":"Entertainment"
        }
    ],
    "sg:phone":"+43 4315 046651",
    "sg:postcode":"1040",
    "sg:province":"Wien",
    "sg:tags":[
        "game"
    ],
    "wof:name":"L. B\u00d6SENDORFER KLAVIERFABRIK GES. MBH",
    "wof:placetype":"venue"
},
  "geometry": {"coordinates":[16.3692474365,48.190700531],"type":"Point"}
}