{
  "type": "Feature",
  "properties": {
    "iso:country":"AT",
    "sg:address":"Ulrich-Schreier-Str 3",
    "sg:city":"Salzburg",
    "sg:orig_category":"Elektroinstallationsunternehmen",
    "sg:phone":"+43 699 12619090",
    "sg:postcode":"5020",
    "sg:province":"Salzburg",
    "wof:name":"Elektro Kleinsasser - St\u00f6rungsdienst",
    "wof:placetype":"venue"
},
  "geometry": {"coordinates":[13.0643959045,47.7878723145],"type":"Point"}
}