{
  "type": "Feature",
  "properties": {
    "addr:full":"Anton-Baumgartner-Str 44 Wien Wien 1230",
    "addr:housenumber":"44",
    "addr:postcode":"1230",
    "addr:street":"Anton-Baumgartner-Str",
    "iso:country":"AT",
    "sg:address":"Anton-Baumgartner-Str 44",
    "sg:city":"Wien",
    "sg:orig_category":"Yachtcharter",
    "sg:phone":"+43 4316 629960",
    "sg:postcode":"1230",
    "sg:province":"Wien",
    "wof:name":"Barone Yachting Yachttouristik KEG",
    "wof:placetype":"venue"
},
  "geometry": {"coordinates":[16.3137016296,48.1504707336],"type":"Point"}
}