{
  "type": "Feature",
  "properties": {
    "addr:full":"Oberer Stadtpl 19 Waidhofen an der Ybbs Nieder\u00f6sterreich 3340",
    "addr:housenumber":"19",
    "addr:postcode":"3340",
    "addr:street":"Oberer Stadtpl",
    "iso:country":"AT",
    "sg:address":"Oberer Stadtpl 19",
    "sg:city":"Waidhofen an der Ybbs",
    "sg:orig_category":"Damenmoden",
    "sg:phone":"+43 7442 54195",
    "sg:postcode":"3340",
    "sg:province":"Nieder\u00f6sterreich",
    "wof:name":"YES",
    "wof:placetype":"venue"
},
  "geometry": {"coordinates":[14.7754201889,47.9606704712],"type":"Point"}
}