{
  "type": "Feature",
  "properties": {
    "addr:full":"Am Spitz 8 Wien Wien 1210",
    "addr:housenumber":"8",
    "addr:postcode":"1210",
    "addr:street":"Am Spitz",
    "iso:country":"AT",
    "sg:address":"Am Spitz 8",
    "sg:city":"Wien",
    "sg:orig_category":"Damenmoden",
    "sg:phone":"+43 1 2787232",
    "sg:postcode":"1210",
    "sg:province":"Wien",
    "wof:name":"Helly-Moden",
    "wof:placetype":"venue"
},
  "geometry": {"coordinates":[16.3974723816,48.2571792603],"type":"Point"}
}