{
  "type": "Feature",
  "properties": {
    "addr:full":"Mettmach 1 Mettmach Ober\u00f6sterreich 4931",
    "addr:housenumber":"1",
    "addr:postcode":"4931",
    "addr:street":"Mettmach",
    "iso:country":"AT",
    "sg:address":"Mettmach 1",
    "sg:city":"Mettmach",
    "sg:classifiers":[
        {
            "category":"Utilities",
            "subcategory":"Natural Gas",
            "type":"Services"
        }
    ],
    "sg:phone":"+43 7755 7220",
    "sg:postcode":"4931",
    "sg:province":"Ober\u00f6sterreich",
    "sg:tags":[
        "planer"
    ],
    "sg:website":"ago.co.at",
    "wof:name":"Anton Gotthalmseder",
    "wof:placetype":"venue"
},
  "geometry": {"coordinates":[13.3493452072,48.1740264893],"type":"Point"}
}