{
  "type": "Feature",
  "properties": {
    "addr:full":"El\u00dflergasse 25 Wien Wien 1130",
    "addr:housenumber":"25",
    "addr:postcode":"1130",
    "addr:street":"Elsslergasse",
    "iso:country":"AT",
    "sg:address":"El\u00dflergasse 25",
    "sg:city":"Wien",
    "sg:classifiers":[
        {
            "category":"Home & Garden",
            "subcategory":"Garden Supply",
            "type":"Retail Goods"
        }
    ],
    "sg:phone":"+43 1 9619565",
    "sg:postcode":"1130",
    "sg:province":"Wien",
    "sg:tags":[
        "lamp"
    ],
    "sg:website":"livinggarden.at",
    "wof:name":"Living Garden Gartengetstaltung GmbH",
    "wof:placetype":"venue"
},
  "geometry": {"coordinates":[16.3013801575,48.18592453],"type":"Point"}
}