{
  "type": "Feature",
  "properties": {
    "addr:full":"Lamprechtshausen Str 15 B\u00fcrmoos Salzburg 5111",
    "addr:postcode":"5111",
    "addr:street":"Str 15 Buermoos Salzburg",
    "iso:country":"AT",
    "sg:address":"Lamprechtshausen Str 15",
    "sg:city":"B\u00fcrmoos",
    "sg:orig_category":"Bierlokale-Pubs",
    "sg:phone":"+43 6274 623512",
    "sg:postcode":"5111",
    "sg:province":"Salzburg",
    "wof:name":"Planet B\u00fcrmoos",
    "wof:placetype":"venue"
},
  "geometry": {"coordinates":[12.9372987747,47.9899177551],"type":"Point"}
}