{
  "type": "Feature",
  "properties": {
    "addr:full":"Hauptstrasse 13 Weissenbach an der Triesting Nieder\u00f6sterreich 2564",
    "addr:housenumber":"13",
    "addr:postcode":"2564",
    "addr:street":"Hauptstrasse",
    "iso:country":"AT",
    "sg:address":"Hauptstrasse 13",
    "sg:city":"Weissenbach an der Triesting",
    "sg:orig_category":"Non-Classified Establishments",
    "sg:phone":"+43 2674 87259",
    "sg:postcode":"2564",
    "sg:province":"Nieder\u00f6sterreich",
    "wof:name":"Gr\u00f6ss Fleisch- und Wurstwaren GesmbH",
    "wof:placetype":"venue"
},
  "geometry": {"coordinates":[16.0394115448,47.9823188782],"type":"Point"}
}