{
  "type": "Feature",
  "properties": {
    "addr:full":"Erzherzog-Carl-Str 2 Deutsch Wagram Nieder\u00f6sterreich 2232",
    "addr:housenumber":"2",
    "addr:postcode":"2232",
    "addr:street":"Erzherzog-Carl-Str",
    "iso:country":"AT",
    "sg:address":"Erzherzog-Carl-Str 2",
    "sg:city":"Deutsch Wagram",
    "sg:classifiers":[
        {
            "category":"Restaurant",
            "type":"Food & Drink"
        }
    ],
    "sg:phone":"+43 4322 473040",
    "sg:postcode":"2232",
    "sg:province":"Nieder\u00f6sterreich",
    "sg:tags":[
        "pizzeria"
    ],
    "wof:name":"Porto Vino",
    "wof:placetype":"venue"
},
  "geometry": {"coordinates":[16.5580368042,48.2959060669],"type":"Point"}
}