{
  "type": "Feature",
  "properties": {
    "addr:full":"Vivenotg 34 Wien Wien 1120",
    "addr:housenumber":"34",
    "addr:postcode":"1120",
    "addr:street":"Vivenotg",
    "iso:country":"AT",
    "sg:address":"Vivenotg 34",
    "sg:city":"Wien",
    "sg:orig_category":"Cd, Dvd,Musikkassetten U Schallplatten",
    "sg:phone":"+43 4318 135260",
    "sg:postcode":"1120",
    "sg:province":"Wien",
    "wof:name":"CD-Shop Diabolo / Robert Steurer",
    "wof:placetype":"venue"
},
  "geometry": {"coordinates":[16.3311500549,48.1782608032],"type":"Point"}
}