{
  "type": "Feature",
  "properties": {
    "addr:full":"Seecorso 70-72 Velden am W\u00f6rther See K\u00e4rnten 9220",
    "addr:housenumber":"70-72",
    "addr:postcode":"9220",
    "addr:street":"Seecorso;Kaernten",
    "iso:country":"AT",
    "sg:address":"Seecorso 70-72",
    "sg:city":"Velden am W\u00f6rther See",
    "sg:orig_category":"Appartements / Ferienwohnungen",
    "sg:phone":"+43 4342 743947",
    "sg:postcode":"9220",
    "sg:province":"K\u00e4rnten",
    "wof:name":"Truppe-Muschett Anlage",
    "wof:placetype":"venue"
},
  "geometry": {"coordinates":[14.0551242828,46.6093215942],"type":"Point"}
}