{
  "type": "Feature",
  "properties": {
    "addr:full":"Grie\u00dfbachwinkel 26 Maria Alm am Steinernen Meer Salzburg 5761",
    "addr:housenumber":"26",
    "addr:postcode":"5761",
    "addr:street":"Griessbachwinkel",
    "iso:country":"AT",
    "sg:address":"Grie\u00dfbachwinkel 26",
    "sg:city":"Maria Alm am Steinernen Meer",
    "sg:orig_category":"Pensionen / Privatzimmer",
    "sg:phone":"+43 4365 847718",
    "sg:postcode":"5761",
    "sg:province":"Salzburg",
    "wof:name":"Schmuck Anna",
    "wof:placetype":"venue"
},
  "geometry": {"coordinates":[12.903875351,47.4068260193],"type":"Point"}
}