{
  "type": "Feature",
  "properties": {
    "iso:country":"AT",
    "sg:address":"Grie\u00dfbachwinkel 26",
    "sg:city":"Maria Alm am Steinernen Meer",
    "sg:orig_category":"Pensionen / Privatzimmer",
    "sg:phone":"+43 4365 847718",
    "sg:postcode":"5761",
    "sg:province":"Salzburg",
    "wof:name":"Schmuck Anna",
    "wof:placetype":"venue"
},
  "geometry": {"coordinates":[12.903875351,47.4068260193],"type":"Point"}
}