{
  "type": "Feature",
  "properties": {
    "addr:full":"Hauptpl 49 Voitsberg Steiermark 8570",
    "addr:housenumber":"49",
    "addr:postcode":"8570",
    "addr:street":"Hauptpl",
    "iso:country":"AT",
    "sg:address":"Hauptpl 49",
    "sg:city":"Voitsberg",
    "sg:orig_category":"Blumeneinzelhandel",
    "sg:phone":"+43 3142 26556",
    "sg:postcode":"8570",
    "sg:province":"Steiermark",
    "wof:name":"Blumentenne-Sonnleitner",
    "wof:placetype":"venue"
},
  "geometry": {"coordinates":[15.1514987946,47.0484886169],"type":"Point"}
}