{
  "type": "Feature",
  "properties": {
    "addr:full":"Obermarkt 26 Telfs Tirol 6410",
    "addr:housenumber":"26",
    "addr:postcode":"6410",
    "addr:street":"Obermarkt;Tirol",
    "iso:country":"AT",
    "sg:address":"Obermarkt 26",
    "sg:city":"Telfs",
    "sg:orig_category":"Friseure U Frisiersalons",
    "sg:phone":"+43 4352 6262566",
    "sg:postcode":"6410",
    "sg:province":"Tirol",
    "wof:name":"Christiane f Haare",
    "wof:placetype":"venue"
},
  "geometry": {"coordinates":[11.0693044662,47.3065223694],"type":"Point"}
}