{
  "type": "Feature",
  "properties": {
    "addr:full":"Raimund-Walln\u00f6fer-Weg 8 Silz Tirol 6424",
    "addr:housenumber":"8",
    "addr:postcode":"6424",
    "addr:street":"Raimund-Wallnoefer-Weg;Tirol",
    "iso:country":"AT",
    "sg:address":"Raimund-Walln\u00f6fer-Weg 8",
    "sg:city":"Silz",
    "sg:orig_category":"Polytechnische Schulen",
    "sg:phone":"+43 4352 635223",
    "sg:postcode":"6424",
    "sg:province":"Tirol",
    "wof:name":"Polytechnische Schule",
    "wof:placetype":"venue"
},
  "geometry": {"coordinates":[10.9304504395,47.2629928589],"type":"Point"}
}