{
  "type": "Feature",
  "properties": {
    "addr:full":"Stubenring 6/11 Wien Wien 1010",
    "addr:housenumber":"6 / 11",
    "addr:postcode":"1010",
    "addr:street":"Stubenring",
    "iso:country":"AT",
    "sg:address":"Stubenring 6/11",
    "sg:city":"Wien",
    "sg:orig_category":"Werbeagenturen",
    "sg:phone":"+43 1 51238350",
    "sg:postcode":"1010",
    "sg:province":"Wien",
    "wof:name":"GOLDFISH Agentur f Jugendmarketing",
    "wof:placetype":"venue"
},
  "geometry": {"coordinates":[16.3822021484,48.2102394104],"type":"Point"}
}