{
  "type": "Feature",
  "properties": {
    "addr:full":"Fabrikstr. 18 Oberwaltersdorf Nieder\u00f6sterreich 2522",
    "addr:housenumber":"18",
    "addr:postcode":"2522",
    "addr:street":"Fabrikstr.",
    "iso:country":"AT",
    "sg:address":"Fabrikstr. 18",
    "sg:city":"Oberwaltersdorf",
    "sg:classifiers":[
        {
            "category":"Food & Beverages",
            "subcategory":"Groceries & Convenience Stores",
            "type":"Retail Goods"
        }
    ],
    "sg:phone":"+43 4322 53605",
    "sg:postcode":"2522",
    "sg:province":"Nieder\u00f6sterreich",
    "sg:tags":[
        "product",
        "related"
    ],
    "wof:name":"AIBLER PRODUKTIONSGESMBH",
    "wof:placetype":"venue"
},
  "geometry": {"coordinates":[16.3228302002,47.9767494202],"type":"Point"}
}