{
  "type": "Feature",
  "properties": {
    "addr:full":"Viehhauser Str 45 Wals Salzburg 5071",
    "addr:postcode":"5071",
    "addr:street":"Str 45;Salzburg",
    "iso:country":"AT",
    "sg:address":"Viehhauser Str 45",
    "sg:city":"Wals",
    "sg:orig_category":"Farben U Lacke / Erzeugung U Gro\u00c3\u0178handel",
    "sg:phone":"+43 662 8530590",
    "sg:postcode":"5071",
    "sg:province":"Salzburg",
    "wof:name":"Synthesa Chemie Gesellschaft mbH",
    "wof:placetype":"venue"
},
  "geometry": {"coordinates":[12.9858551025,47.7852973938],"type":"Point"}
}