{
  "type": "Feature",
  "properties": {
    "addr:full":"Nr 38 Gastern Nieder\u00f6sterreich 3852",
    "addr:postcode":"3852",
    "addr:street":"Nr;Niederoesterreich",
    "iso:country":"AT",
    "sg:address":"Nr 38",
    "sg:city":"Gastern",
    "sg:orig_category":"Institute",
    "sg:phone":"+43 4328 6426053",
    "sg:postcode":"3852",
    "sg:province":"Nieder\u00f6sterreich",
    "wof:name":"Institut f Medizin-Historische Hilfswissenschaften",
    "wof:placetype":"venue"
},
  "geometry": {"coordinates":[15.2184963226,48.8965377808],"type":"Point"}
}