{
  "type": "Feature",
  "properties": {
    "addr:full":"Fohrafeld 10 Kilb Nieder\u00f6sterreich 3233",
    "addr:housenumber":"10",
    "addr:postcode":"3233",
    "addr:street":"Fohrafeld",
    "iso:country":"AT",
    "sg:address":"Fohrafeld 10",
    "sg:city":"Kilb",
    "sg:classifiers":[
        {
            "category":"Education",
            "subcategory":"Dance Studio",
            "type":"Public Place"
        }
    ],
    "sg:phone":"+43 2748 7286",
    "sg:postcode":"3233",
    "sg:province":"Nieder\u00f6sterreich",
    "sg:tags":[
        "pallet"
    ],
    "wof:name":"Johannes Lampl",
    "wof:placetype":"venue"
},
  "geometry": {"coordinates":[15.4061937332,48.1054801941],"type":"Point"}
}