{
  "type": "Feature",
  "properties": {
    "addr:full":"Baumg 34 Wien Wien 1030",
    "addr:housenumber":"34",
    "addr:postcode":"1030",
    "addr:street":"Baumg",
    "iso:country":"AT",
    "sg:address":"Baumg 34",
    "sg:city":"Wien",
    "sg:orig_category":"Friseure U Frisiersalons",
    "sg:phone":"+43 4317 141530",
    "sg:postcode":"1030",
    "sg:province":"Wien",
    "wof:name":"M\u00e4rz Daniela",
    "wof:placetype":"venue"
},
  "geometry": {"coordinates":[16.4008426666,48.194694519],"type":"Point"}
}