{
  "type": "Feature",
  "properties": {
    "iso:country":"AT",
    "sg:address":"Salzachtal Bundesstr 11",
    "sg:city":"Hallein",
    "sg:orig_category":"Autoersatzteile",
    "sg:phone":"+43 4362 4580398",
    "sg:postcode":"5400",
    "sg:province":"Salzburg",
    "wof:name":"Eisner Auto Vertrieb u Service GmbH",
    "wof:placetype":"venue"
},
  "geometry": {"coordinates":[13.1014728546,47.6821708679],"type":"Point"}
}