{
  "type": "Feature",
  "properties": {
    "iso:country":"AT",
    "sg:address":"Theresieng 1",
    "sg:city":"Baden",
    "sg:orig_category":"Blumeneinzelhandel",
    "sg:phone":"+43 2252 49119",
    "sg:postcode":"2500",
    "sg:province":"Nieder\u00f6sterreich",
    "wof:name":"Blumen Design Michaela Pauer",
    "wof:placetype":"venue"
},
  "geometry": {"coordinates":[16.2337341309,48.0087814331],"type":"Point"}
}