{
  "type": "Feature",
  "properties": {
    "iso:country":"AT",
    "sg:address":"Nr 30",
    "sg:city":"St. Georgen im Gailtal",
    "sg:orig_category":"Waren Aller Art",
    "sg:phone":"+43 4342 562030",
    "sg:postcode":"9612",
    "sg:province":"K\u00e4rnten",
    "wof:name":"Schwenner Klaus",
    "wof:placetype":"venue"
},
  "geometry": {"coordinates":[13.5962772369,46.6046218872],"type":"Point"}
}