{
  "type": "Feature",
  "properties": {
    "addr:full":"Hauptstr 56 Ried im Innkreis Ober\u00f6sterreich 4910",
    "addr:housenumber":"56",
    "addr:postcode":"4910",
    "addr:street":"Hauptstr",
    "iso:country":"AT",
    "sg:address":"Hauptstr 56",
    "sg:city":"Ried im Innkreis",
    "sg:orig_category":"Banken U Sparkassen",
    "sg:phone":"+43 7754 84010",
    "sg:postcode":"4910",
    "sg:province":"Ober\u00f6sterreich",
    "wof:name":"Raiffeisenbank Region Ried regGenmbH",
    "wof:placetype":"venue"
},
  "geometry": {"coordinates":[13.4846172333,48.1565666199],"type":"Point"}
}