{
  "type": "Feature",
  "properties": {
    "addr:full":"Hauptpl 17/Top 14 Traiskirchen Nieder\u00f6sterreich 2514",
    "addr:housenumber":"17 / top 14",
    "addr:postcode":"2514",
    "addr:street":"Hauptpl;Niederoesterreich",
    "iso:country":"AT",
    "sg:address":"Hauptpl 17/Top 14",
    "sg:city":"Traiskirchen",
    "sg:orig_category":"Babyausstattung",
    "sg:phone":"+43 4322 5255255",
    "sg:postcode":"2514",
    "sg:province":"Nieder\u00f6sterreich",
    "wof:name":"Bimini Kinder u Umstandsmoden",
    "wof:placetype":"venue"
},
  "geometry": {"coordinates":[16.2946777344,48.0138092041],"type":"Point"}
}