{
  "type": "Feature",
  "properties": {
    "addr:full":"Elisabethstrasse 59 Graz Steiermark 8010",
    "addr:housenumber":"59",
    "addr:postcode":"8010",
    "addr:street":"Elisabethstrasse",
    "iso:country":"AT",
    "sg:address":"Elisabethstrasse 59",
    "sg:city":"Graz",
    "sg:classifiers":[
        {
            "category":"Home & Garden",
            "subcategory":"Carpets & Floor Coverings",
            "type":"Retail Goods"
        }
    ],
    "sg:phone":"+43 316 3777840",
    "sg:postcode":"8010",
    "sg:province":"Steiermark",
    "sg:tags":[
        "design"
    ],
    "sg:website":"rautnigg.at",
    "wof:name":"Rautnigg & Co",
    "wof:placetype":"venue"
},
  "geometry": {"coordinates":[15.4556627274,47.0761795044],"type":"Point"}
}