{
  "type": "Feature",
  "properties": {
    "addr:full":"Neustadt 10 Feldkirch Vorarlberg 6800",
    "addr:housenumber":"10",
    "addr:postcode":"6800",
    "addr:street":"Neustadt",
    "iso:country":"AT",
    "sg:address":"Neustadt 10",
    "sg:city":"Feldkirch",
    "sg:orig_category":"Bars-Cafes",
    "sg:phone":"+43 5522 71725",
    "sg:postcode":"6800",
    "sg:province":"Vorarlberg",
    "wof:name":"Cafe-Bar Hecht",
    "wof:placetype":"venue"
},
  "geometry": {"coordinates":[9.5981283188,47.2372055054],"type":"Point"}
}