{
  "type": "Feature",
  "properties": {
    "addr:full":"Hausstattstr 3/6 Henndorf am Wallersee Salzburg 5302",
    "addr:housenumber":"3 / 6",
    "addr:postcode":"5302",
    "addr:street":"Hausstattstr",
    "iso:country":"AT",
    "sg:address":"Hausstattstr 3/6",
    "sg:city":"Henndorf am Wallersee",
    "sg:orig_category":"Werbegestalter",
    "sg:phone":"+43 4362 146713",
    "sg:postcode":"5302",
    "sg:province":"Salzburg",
    "wof:name":"Deko 1 Uno Paul Bazzanella",
    "wof:placetype":"venue"
},
  "geometry": {"coordinates":[13.1813716888,47.9000968933],"type":"Point"}
}