{
  "type": "Feature",
  "properties": {
    "addr:full":"Obersdorfer Str 22/1 Wolkersdorf im Weinviertel Nieder\u00f6sterreich 2120",
    "addr:housenumber":"22 / 1",
    "addr:postcode":"2120",
    "addr:street":"Obersdorfer Str",
    "iso:country":"AT",
    "sg:address":"Obersdorfer Str 22/1",
    "sg:city":"Wolkersdorf im Weinviertel",
    "sg:orig_category":"Datenverarbeitung",
    "sg:phone":"+43 2245 20200",
    "sg:postcode":"2120",
    "sg:province":"Nieder\u00f6sterreich",
    "wof:name":"EDSA - Systems Karl Pusch",
    "wof:placetype":"venue"
},
  "geometry": {"coordinates":[16.5148029327,48.380191803],"type":"Point"}
}