{
  "type": "Feature",
  "properties": {
    "addr:full":"Kirchbergg 6-8 Wien Wien 1070",
    "addr:housenumber":"6-8",
    "addr:postcode":"1070",
    "addr:street":"Kirchbergg",
    "iso:country":"AT",
    "sg:address":"Kirchbergg 6-8",
    "sg:city":"Wien",
    "sg:classifiers":[
        {
            "category":"Travel",
            "subcategory":"Hotels & Motels",
            "type":"Entertainment"
        }
    ],
    "sg:phone":"+43 1 521230",
    "sg:postcode":"1070",
    "sg:province":"Wien",
    "wof:name":"K + K Hotel Maria Theresia",
    "wof:placetype":"venue"
},
  "geometry": {"coordinates":[16.3562870026,48.2031555176],"type":"Point"}
}