{
  "type": "Feature",
  "properties": {
    "iso:country":"AT",
    "sg:address":"Quellenstrasse 121",
    "sg:city":"Wien",
    "sg:classifiers":[
        {
            "category":"Government",
            "subcategory":"Fire Station",
            "type":"Public Place"
        }
    ],
    "sg:phone":"+43 1 6026277",
    "sg:postcode":"1100",
    "sg:province":"Wien",
    "sg:tags":[
        "component",
        "watch",
        "clock"
    ],
    "wof:name":"Anton Wallisch",
    "wof:placetype":"venue"
},
  "geometry": {"coordinates":[16.3765659332,48.1752815247],"type":"Point"}
}