{
  "type": "Feature",
  "properties": {
    "addr:full":"Am Steg 13B Ried im Traunkreis Ober\u00f6sterreich 4551",
    "addr:housenumber":"13b",
    "addr:postcode":"4551",
    "addr:street":"Am Steg",
    "iso:country":"AT",
    "sg:address":"Am Steg 13B",
    "sg:city":"Ried im Traunkreis",
    "sg:orig_category":"Apparatebau",
    "sg:phone":"+43 7588 7486",
    "sg:postcode":"4551",
    "sg:province":"Ober\u00f6sterreich",
    "wof:name":"Elektroanlagen Heigl GmbH",
    "wof:placetype":"venue"
},
  "geometry": {"coordinates":[14.062037468,48.020690918],"type":"Point"}
}