{
  "type": "Feature",
  "properties": {
    "addr:full":"Pfarrg 2 Friesach K\u00e4rnten 9360",
    "addr:housenumber":"2",
    "addr:postcode":"9360",
    "addr:street":"Pfarrg;Kaernten",
    "iso:country":"AT",
    "sg:address":"Pfarrg 2",
    "sg:city":"Friesach",
    "sg:orig_category":"Zahntechnische Laboratorien",
    "sg:phone":"+43 4268 2042",
    "sg:postcode":"9360",
    "sg:province":"K\u00e4rnten",
    "wof:name":"Marcher Werner Zahntechnisches Labor GesmbH",
    "wof:placetype":"venue"
},
  "geometry": {"coordinates":[14.4063367844,46.9512672424],"type":"Point"}
}