{
  "type": "Feature",
  "properties": {
    "addr:full":"Fattstra\u00dfe 6 P.O. BOX 40  Wolfurt Vorarlberg 6922",
    "addr:housenumber":"6 p.o. box 40",
    "addr:postcode":"6922",
    "addr:street":"Fattstrasse",
    "iso:country":"AT",
    "sg:address":"Fattstra\u00dfe 6 P.O. BOX 40 ",
    "sg:city":"Wolfurt",
    "sg:classifiers":[
        {
            "category":"Shopping",
            "subcategory":"Crafts & Fabrics",
            "type":"Retail Goods"
        }
    ],
    "sg:phone":"+43 4355 7473618",
    "sg:postcode":"6922",
    "sg:province":"Vorarlberg",
    "wof:name":"AGROFLOR KUNSTSTOFFGES. MBH",
    "wof:placetype":"venue"
},
  "geometry": {"coordinates":[9.7366800308,47.5067596436],"type":"Point"}
}