{
  "type": "Feature",
  "properties": {
    "iso:country":"AT",
    "sg:address":"Stefunstrasse 5",
    "sg:city":"Ebenthal in K\u00e4rnten",
    "sg:classifiers":[
        {
            "category":"Manufacturing",
            "subcategory":"Wood Products",
            "type":"Manufacturing & Wholesale Goods"
        }
    ],
    "sg:phone":"+43 463 73103",
    "sg:postcode":"9065",
    "sg:province":"K\u00e4rnten",
    "sg:tags":[
        "made",
        "balcony"
    ],
    "wof:name":"Holzbau Wolf Inh. Herbert u. Valentin Wolf",
    "wof:placetype":"venue"
},
  "geometry": {"coordinates":[14.3925304413,46.6082191467],"type":"Point"}
}