{
  "type": "Feature",
  "properties": {
    "addr:full":"Flurstr 29/17 Persenbeug Nieder\u00f6sterreich 3680",
    "addr:housenumber":"29 / 17",
    "addr:postcode":"3680",
    "addr:street":"Flurstr",
    "iso:country":"AT",
    "sg:address":"Flurstr 29/17",
    "sg:city":"Persenbeug",
    "sg:orig_category":"Schwimmbecken",
    "sg:phone":"+43 4366 42427335",
    "sg:postcode":"3680",
    "sg:province":"Nieder\u00f6sterreich",
    "sg:website":"polyfaser.com",
    "wof:name":"POLYFASER Andreas Kefer",
    "wof:placetype":"venue"
},
  "geometry": {"coordinates":[15.1025524139,48.1902046204],"type":"Point"}
}