{
  "type": "Feature",
  "properties": {
    "addr:full":"Schlo\u00df Hollenegg 1 Deutschlandsberg Steiermark 8530",
    "addr:housenumber":"1",
    "addr:postcode":"8530",
    "addr:street":"Hollenegg",
    "iso:country":"AT",
    "sg:address":"Schlo\u00df Hollenegg 1",
    "sg:city":"Deutschlandsberg",
    "sg:orig_category":"Forstverwaltungen",
    "sg:phone":"+43 3462 2237",
    "sg:postcode":"8530",
    "sg:province":"Steiermark",
    "wof:name":"Liechtenstein Alfred Prinz Dipl-Ing",
    "wof:placetype":"venue"
},
  "geometry": {"coordinates":[15.2126283646,46.8138923645],"type":"Point"}
}