{
  "type": "Feature",
  "properties": {
    "iso:country":"AT",
    "sg:address":"Badsdlg 28",
    "sg:city":"Hadersdorf am Kamp",
    "sg:orig_category":"Schneidereien",
    "sg:phone":"+43 2735 5864",
    "sg:postcode":"3493",
    "sg:province":"Nieder\u00f6sterreich",
    "wof:name":"Damen-Ma\u00dfschneiderei",
    "wof:placetype":"venue"
},
  "geometry": {"coordinates":[15.7206754684,48.4590759277],"type":"Point"}
}