{
  "type": "Feature",
  "properties": {
    "addr:full":"Lindeng 61/1 Wien Wien 1070",
    "addr:housenumber":"61 / 1",
    "addr:postcode":"1070",
    "addr:street":"Lindeng",
    "iso:country":"AT",
    "sg:address":"Lindeng 61/1",
    "sg:city":"Wien",
    "sg:orig_category":"Weiterbildungsinstitute M Allg U Berufl Bildungsangebot",
    "sg:phone":"+43 4315 231747",
    "sg:postcode":"1070",
    "sg:province":"Wien",
    "wof:name":"Berufsf\u00f6rderungsinstitut Wien - Bildungszentrum",
    "wof:placetype":"venue"
},
  "geometry": {"coordinates":[16.3447055817,48.199092865],"type":"Point"}
}