{
  "type": "Feature",
  "properties": {
    "addr:full":"Duilestr 2-4 Innsbruck Tirol 6020",
    "addr:housenumber":"2-4",
    "addr:postcode":"6020",
    "addr:street":"Duilestr;Tirol",
    "iso:country":"AT",
    "sg:address":"Duilestr 2-4",
    "sg:city":"Innsbruck",
    "sg:orig_category":"Partyservice, Hochzeitsservice, Catering",
    "sg:phone":"+43 512 273786",
    "sg:postcode":"6020",
    "sg:province":"Tirol",
    "sg:website":"esspress.at",
    "wof:name":"Catering Esspress - Ing Michael Dauth KEG",
    "wof:placetype":"venue"
},
  "geometry": {"coordinates":[11.3945741653,47.2547416687],"type":"Point"}
}