{
  "type": "Feature",
  "properties": {
    "iso:country":"AT",
    "sg:address":"Egarterpl 4/p",
    "sg:city":"Spittal an der Drau",
    "sg:orig_category":"Juwelen, Gold- U Silberwaren / Einzelhandel",
    "sg:phone":"+43 4347 6233989",
    "sg:postcode":"9800",
    "sg:province":"K\u00e4rnten",
    "wof:name":"Schweiger Juwelier HandelsgesmbH",
    "wof:placetype":"venue"
},
  "geometry": {"coordinates":[13.4968900681,46.7977409363],"type":"Point"}
}