{
  "type": "Feature",
  "properties": {
    "iso:country":"AT",
    "sg:address":"Groisbacher Str 214",
    "sg:city":"Alland",
    "sg:orig_category":"Baumaschinenverleih",
    "sg:phone":"+43 2258 2410",
    "sg:postcode":"2534",
    "sg:province":"Nieder\u00f6sterreich",
    "wof:name":"Kastner Johann Ing",
    "wof:placetype":"venue"
},
  "geometry": {"coordinates":[16.0696697235,48.0511665344],"type":"Point"}
}