{
  "type": "Feature",
  "properties": {
    "addr:full":"Nr 37 Wolfsegg am Hausruck Ober\u00f6sterreich 4902",
    "addr:postcode":"4902",
    "addr:street":"Nr",
    "iso:country":"AT",
    "sg:address":"Nr 37",
    "sg:city":"Wolfsegg am Hausruck",
    "sg:orig_category":"Holzbearbeitungsmaschinen U -Werkzeuge",
    "sg:phone":"+43 767674600",
    "sg:postcode":"4902",
    "sg:province":"Ober\u00f6sterreich",
    "wof:name":"KNAPP Maschinenbau GmbH",
    "wof:placetype":"venue"
},
  "geometry": {"coordinates":[13.6745090485,48.1071929932],"type":"Point"}
}