{
  "type": "Feature",
  "properties": {
    "addr:full":"Schweizer G 42 Lienz Tirol 9900",
    "addr:housenumber":"42",
    "addr:postcode":"9900",
    "addr:street":"Schweizer G;Tirol",
    "iso:country":"AT",
    "sg:address":"Schweizer G 42",
    "sg:city":"Lienz",
    "sg:orig_category":"Lebens- U Sozialberatung",
    "sg:phone":"+43 4348 5262679",
    "sg:postcode":"9900",
    "sg:province":"Tirol",
    "wof:name":"Psychosozialer Dienst d Gesellschaft f Psychische Gesundheit - Psychohygiene Tirol",
    "wof:placetype":"venue"
},
  "geometry": {"coordinates":[12.7608308792,46.8317985535],"type":"Point"}
}