{
  "type": "Feature",
  "properties": {
    "addr:full":"Schachenwaldstr 11 Feldkirchen Steiermark 8073",
    "addr:housenumber":"11",
    "addr:postcode":"8073",
    "addr:street":"Schachenwaldstr",
    "iso:country":"AT",
    "sg:address":"Schachenwaldstr 11",
    "sg:city":"Feldkirchen",
    "sg:orig_category":"Elektroinstallationsunternehmen",
    "sg:phone":"+43 316 296775",
    "sg:postcode":"8073",
    "sg:province":"Steiermark",
    "wof:name":"Elektro ENA",
    "wof:placetype":"venue"
},
  "geometry": {"coordinates":[15.4276294708,47.0043525696],"type":"Point"}
}