{
  "type": "Feature",
  "properties": {
    "addr:full":"Grazer Str 20/Eurocenter F\u00fcrstenfeld Steiermark 8280",
    "addr:housenumber":"20 /",
    "addr:postcode":"8280",
    "addr:street":"Str",
    "iso:country":"AT",
    "sg:address":"Grazer Str 20/Eurocenter",
    "sg:city":"F\u00fcrstenfeld",
    "sg:orig_category":"Friseure U Frisiersalons",
    "sg:phone":"+43 4333 8254189",
    "sg:postcode":"8280",
    "sg:province":"Steiermark",
    "wof:name":"FRIS\u00f6R KLIER GesmbH",
    "wof:placetype":"venue"
},
  "geometry": {"coordinates":[16.0673484802,47.0585250854],"type":"Point"}
}