{
  "type": "Feature",
  "properties": {
    "iso:country":"AT",
    "sg:address":"Markt 58",
    "sg:city":"Ardagger",
    "sg:orig_category":"Bestattungsunternehmen",
    "sg:phone":"+43 7472 609745",
    "sg:postcode":"3321",
    "sg:province":"Nieder\u00f6sterreich",
    "wof:name":"Bestattung Stadtwerke Amstetten",
    "wof:placetype":"venue"
},
  "geometry": {"coordinates":[14.825838089,48.1811904907],"type":"Point"}
}