{
  "type": "Feature",
  "properties": {
    "iso:country":"AT",
    "sg:address":"Tauernstrasse 29",
    "sg:city":"Radstadt",
    "sg:classifiers":[
        {
            "category":"Retail",
            "subcategory":"Repair Shop",
            "type":"Services"
        }
    ],
    "sg:phone":"+43 6452 4261",
    "sg:postcode":"5550",
    "sg:province":"Salzburg",
    "sg:tags":[
        "agricultural",
        "machinery"
    ],
    "wof:name":"Ing. Harald Neumayer Ges.m.b.H.",
    "wof:placetype":"venue"
},
  "geometry": {"coordinates":[13.4736766815,47.3783950806],"type":"Point"}
}