{
  "type": "Feature",
  "properties": {
    "addr:full":"Heiligenst\u00e4dter Str 144 Wien Wien 1190",
    "addr:housenumber":"144",
    "addr:postcode":"1190",
    "addr:street":"Str",
    "iso:country":"AT",
    "sg:address":"Heiligenst\u00e4dter Str 144",
    "sg:city":"Wien",
    "sg:orig_category":"Restaurants: Chinesisch",
    "sg:phone":"+43 1 3701362",
    "sg:postcode":"1190",
    "sg:province":"Wien",
    "wof:name":"China Restaurant Le Cun",
    "wof:placetype":"venue"
},
  "geometry": {"coordinates":[16.3661766052,48.2557907104],"type":"Point"}
}