{
  "type": "Feature",
  "properties": {
    "addr:full":"Gabesstr 36 Linz Ober\u00f6sterreich 4030",
    "addr:housenumber":"36",
    "addr:postcode":"4030",
    "addr:street":"Gabesstr",
    "iso:country":"AT",
    "sg:address":"Gabesstr 36",
    "sg:city":"Linz",
    "sg:orig_category":"Transportunternehmen",
    "sg:phone":"+43 732 314853",
    "sg:postcode":"4030",
    "sg:province":"Ober\u00f6sterreich",
    "wof:name":"City-Express Inh Gerald G\u00f6ls",
    "wof:placetype":"venue"
},
  "geometry": {"coordinates":[14.3088846207,48.2462921143],"type":"Point"}
}