{
  "type": "Feature",
  "properties": {
    "addr:full":"Gesellenhausstr 13 Linz Ober\u00f6sterreich 4020",
    "addr:housenumber":"13",
    "addr:postcode":"4020",
    "addr:street":"Gesellenhausstr",
    "iso:country":"AT",
    "sg:address":"Gesellenhausstr 13",
    "sg:city":"Linz",
    "sg:orig_category":"Farb-, Stil- U Typberatung",
    "sg:phone":"+43 732 66992114",
    "sg:postcode":"4020",
    "sg:province":"Ober\u00f6sterreich",
    "wof:name":"Uhrmann Ingrid",
    "wof:placetype":"venue"
},
  "geometry": {"coordinates":[14.2894258499,48.2976837158],"type":"Point"}
}