{
  "type": "Feature",
  "properties": {
    "iso:country":"AT",
    "sg:address":"Klappholzstr 2",
    "sg:city":"Innsbruck",
    "sg:orig_category":"Sportanlagen",
    "sg:phone":"+43 512 347668",
    "sg:postcode":"6020",
    "sg:province":"Tirol",
    "wof:name":"Sportanlage Reichenau",
    "wof:placetype":"venue"
},
  "geometry": {"coordinates":[11.4163627625,47.2690010071],"type":"Point"}
}