{
  "type": "Feature",
  "properties": {
    "addr:full":"Maria Grosse Str. 36 Kroisbach Steiermark 8043",
    "addr:housenumber":"36",
    "addr:postcode":"8043",
    "addr:street":"Str.",
    "iso:country":"AT",
    "sg:address":"Maria Grosse Str. 36",
    "sg:city":"Kroisbach",
    "sg:classifiers":[
        {
            "category":"Professional",
            "subcategory":"Business Services",
            "type":"Services"
        }
    ],
    "sg:phone":"+43 4331 6253999",
    "sg:postcode":"8043",
    "sg:province":"Steiermark",
    "sg:tags":[
        "advice"
    ],
    "wof:name":"KHK SOFTWARE GESMBH",
    "wof:placetype":"venue"
},
  "geometry": {"coordinates":[15.4557695389,47.0936889648],"type":"Point"}
}