{
  "type": "Feature",
  "properties": {
    "addr:full":"Bahnhofstr 66 Ried im Innkreis Ober\u00f6sterreich 4910",
    "addr:housenumber":"66",
    "addr:postcode":"4910",
    "addr:street":"Bahnhofstr",
    "iso:country":"AT",
    "sg:address":"Bahnhofstr 66",
    "sg:city":"Ried im Innkreis",
    "sg:orig_category":"Autoersatzteile",
    "sg:phone":"+43 4377 5281007",
    "sg:postcode":"4910",
    "sg:province":"Ober\u00f6sterreich",
    "wof:name":"Weiermann GmbH",
    "wof:placetype":"venue"
},
  "geometry": {"coordinates":[13.4887752533,48.2028388977],"type":"Point"}
}