{
  "type": "Feature",
  "properties": {
    "iso:country":"AT",
    "sg:address":"H\u00f6hnharter Str 33",
    "sg:city":"Aspach",
    "sg:orig_category":"Bildhauer",
    "sg:phone":"+43 7755 5354",
    "sg:postcode":"5252",
    "sg:province":"Ober\u00f6sterreich",
    "wof:name":"Daringer Manfred",
    "wof:placetype":"venue"
},
  "geometry": {"coordinates":[13.3044300079,48.1856651306],"type":"Point"}
}