{
  "type": "Feature",
  "properties": {
    "addr:full":"Ullmannstr 43 Wien Wien 1150",
    "addr:housenumber":"43",
    "addr:postcode":"1150",
    "addr:street":"Ullmannstr",
    "iso:country":"AT",
    "sg:address":"Ullmannstr 43",
    "sg:city":"Wien",
    "sg:orig_category":"Tabaktrafiken",
    "sg:phone":"+43 1 8931394",
    "sg:postcode":"1150",
    "sg:province":"Wien",
    "wof:name":"Furch Gabriele",
    "wof:placetype":"venue"
},
  "geometry": {"coordinates":[16.332239151,48.1871490479],"type":"Point"}
}