{
  "type": "Feature",
  "properties": {
    "addr:full":"Singerstr 14 Wien Wien 1010",
    "addr:housenumber":"14",
    "addr:postcode":"1010",
    "addr:street":"Singerstr",
    "iso:country":"AT",
    "sg:address":"Singerstr 14",
    "sg:city":"Wien",
    "sg:orig_category":"Textilwaren / Erzeugung U Gro\u00c3\u0178handel",
    "sg:phone":"+43 4315 132287",
    "sg:postcode":"1010",
    "sg:province":"Wien",
    "wof:name":"Schellakann",
    "wof:placetype":"venue"
},
  "geometry": {"coordinates":[16.3735599518,48.2072677612],"type":"Point"}
}