{
  "type": "Feature",
  "properties": {
    "addr:full":"Wiener Str 11 Unterwaltersdorf Nieder\u00f6sterreich 2442",
    "addr:postcode":"2442",
    "addr:street":"Niederoesterreich",
    "iso:country":"AT",
    "sg:address":"Wiener Str 11",
    "sg:city":"Unterwaltersdorf",
    "sg:orig_category":"Tankstellen",
    "sg:phone":"+43 2254 72342",
    "sg:postcode":"2442",
    "sg:province":"Nieder\u00f6sterreich",
    "wof:name":"Avia Tankstelle",
    "wof:placetype":"venue"
},
  "geometry": {"coordinates":[16.4298553467,47.9620399475],"type":"Point"}
}