{
  "type": "Feature",
  "properties": {
    "addr:full":"Haydnweg 5 Krumpendorf K\u00e4rnten 9201",
    "addr:housenumber":"5",
    "addr:postcode":"9201",
    "addr:street":"Haydnweg;Kaernten",
    "iso:country":"AT",
    "sg:address":"Haydnweg 5",
    "sg:city":"Krumpendorf",
    "sg:orig_category":"Appartements / Ferienwohnungen",
    "sg:phone":"+43 4229 26950",
    "sg:postcode":"9201",
    "sg:province":"K\u00e4rnten",
    "wof:name":"Appartements Lach",
    "wof:placetype":"venue"
},
  "geometry": {"coordinates":[14.2153511047,46.6228713989],"type":"Point"}
}