{
  "type": "Feature",
  "properties": {
    "iso:country":"AT",
    "sg:address":"Schopperstr 18",
    "sg:city":"Salzburg",
    "sg:orig_category":"Non-Classified Establishments",
    "sg:phone":"+43 662 451336",
    "sg:postcode":"5020",
    "sg:province":"Salzburg",
    "wof:name":"Evangelische Missionsgemeinschaft Salzburg",
    "wof:placetype":"venue"
},
  "geometry": {"coordinates":[13.0477018356,47.8226737976],"type":"Point"}
}