{
  "type": "Feature",
  "properties": {
    "addr:full":"Erleng 10 Kobersdorf Burgenland 7332",
    "addr:housenumber":"10",
    "addr:postcode":"7332",
    "addr:street":"Erleng",
    "iso:country":"AT",
    "sg:address":"Erleng 10",
    "sg:city":"Kobersdorf",
    "sg:orig_category":"Fenster",
    "sg:phone":"+43 2618 8692",
    "sg:postcode":"7332",
    "sg:province":"Burgenland",
    "wof:name":"Gneist Kurt",
    "wof:placetype":"venue"
},
  "geometry": {"coordinates":[16.3847961426,47.6102333069],"type":"Point"}
}