{
  "type": "Feature",
  "properties": {
    "addr:full":"St.-Georgen-G 5 Graz Steiermark 8020",
    "addr:housenumber":"5",
    "addr:postcode":"8020",
    "addr:street":"St.-Georgen-G",
    "iso:country":"AT",
    "sg:address":"St.-Georgen-G 5",
    "sg:city":"Graz",
    "sg:orig_category":"Fotografen",
    "sg:phone":"+43 316 713376",
    "sg:postcode":"8020",
    "sg:province":"Steiermark",
    "wof:name":"Baumgartner Augustin",
    "wof:placetype":"venue"
},
  "geometry": {"coordinates":[15.4303302765,47.0716056824],"type":"Point"}
}