{
  "type": "Feature",
  "properties": {
    "addr:full":"Grazer Str 15 Mureck Steiermark 8480",
    "addr:postcode":"8480",
    "addr:street":"Str",
    "iso:country":"AT",
    "sg:address":"Grazer Str 15",
    "sg:city":"Mureck",
    "sg:orig_category":"Isolierglas",
    "sg:phone":"+43 3472 30407",
    "sg:postcode":"8480",
    "sg:province":"Steiermark",
    "wof:name":"Egger-Glas Isolierglaswerk",
    "wof:placetype":"venue"
},
  "geometry": {"coordinates":[15.7687988281,46.7074813843],"type":"Point"}
}