{
  "type": "Feature",
  "properties": {
    "addr:full":"Sch\u00f6naug 121 Graz Steiermark 8010",
    "addr:housenumber":"121",
    "addr:postcode":"8010",
    "iso:country":"AT",
    "sg:address":"Sch\u00f6naug 121",
    "sg:city":"Graz",
    "sg:orig_category":"Lebensmittel / Einzelhandel",
    "sg:phone":"+43 316 831932",
    "sg:postcode":"8010",
    "sg:province":"Steiermark",
    "wof:name":"Hofer KG",
    "wof:placetype":"venue"
},
  "geometry": {"coordinates":[15.4431800842,47.0685653687],"type":"Point"}
}