{
  "type": "Feature",
  "properties": {
    "iso:country":"AT",
    "sg:address":"Nr 170",
    "sg:city":"Maurach",
    "sg:classifiers":[
        {
            "category":"Restaurant",
            "type":"Food & Drink"
        }
    ],
    "sg:phone":"+43 5243 5384",
    "sg:postcode":"6212",
    "sg:province":"Tirol",
    "wof:name":"Restaurant-Cafe Bergkristall",
    "wof:placetype":"venue"
},
  "geometry": {"coordinates":[11.7334003448,47.4337615967],"type":"Point"}
}