{
  "type": "Feature",
  "properties": {
    "addr:full":"Planerstr 4 Ulrichsberg Ober\u00f6sterreich 4161",
    "addr:housenumber":"4",
    "addr:postcode":"4161",
    "addr:street":"Planerstr",
    "iso:country":"AT",
    "sg:address":"Planerstr 4",
    "sg:city":"Ulrichsberg",
    "sg:orig_category":"Transportunternehmen",
    "sg:phone":"+43 7288 2225",
    "sg:postcode":"4161",
    "sg:province":"Ober\u00f6sterreich",
    "wof:name":"Leibetseder KEG",
    "wof:placetype":"venue"
},
  "geometry": {"coordinates":[13.9074649811,48.6774291992],"type":"Point"}
}