{
  "type": "Feature",
  "properties": {
    "addr:full":"Genotteallee 12 Villach K\u00e4rnten 9500",
    "addr:housenumber":"12",
    "addr:postcode":"9500",
    "addr:street":"Genotteallee;Kaernten",
    "iso:country":"AT",
    "sg:address":"Genotteallee 12",
    "sg:city":"Villach",
    "sg:orig_category":"Nachhilfe U Lernbetreuung",
    "sg:phone":"+43 4342 4224323",
    "sg:postcode":"9500",
    "sg:province":"K\u00e4rnten",
    "wof:name":"Sch\u00fclernachhilfe Lerninstitut Ortner",
    "wof:placetype":"venue"
},
  "geometry": {"coordinates":[13.8430671692,46.6203308105],"type":"Point"}
}