{
  "type": "Feature",
  "properties": {
    "iso:country":"AT",
    "sg:address":"St.-Margarethen-Str 4",
    "sg:city":"Bad Vigaun",
    "sg:classifiers":[
        {
            "category":"Government",
            "subcategory":"Post Office",
            "type":"Public Place"
        }
    ],
    "sg:phone":"+43 4362 4583460",
    "sg:postcode":"5424",
    "sg:province":"Salzburg",
    "sg:tags":[
        "-handel",
        "tierzucht",
        "u"
    ],
    "wof:name":"Frank Josef",
    "wof:placetype":"venue"
},
  "geometry": {"coordinates":[13.1265802383,47.6731987],"type":"Point"}
}