{
  "type": "Feature",
  "properties": {
    "addr:full":"Nikolsdorfer G 10 Wien Wien 1050",
    "addr:housenumber":"10",
    "addr:postcode":"1050",
    "addr:street":"Nikolsdorfer G",
    "iso:country":"AT",
    "sg:address":"Nikolsdorfer G 10",
    "sg:city":"Wien",
    "sg:orig_category":"Tabaktrafiken",
    "sg:phone":"+43 1 5453257",
    "sg:postcode":"1050",
    "sg:province":"Wien",
    "wof:name":"Lugmayr Kurt",
    "wof:placetype":"venue"
},
  "geometry": {"coordinates":[16.3628883362,48.1869544983],"type":"Point"}
}