{
  "type": "Feature",
  "properties": {
    "iso:country":"AT",
    "sg:address":"Adolf Dietel-Weg 3",
    "sg:city":"Linz",
    "sg:orig_category":"Detekteien",
    "sg:phone":"+43 732 376882",
    "sg:postcode":"4030",
    "sg:province":"Ober\u00f6sterreich",
    "wof:name":"Detektivb\u00fcro Walter Spalt",
    "wof:placetype":"venue"
},
  "geometry": {"coordinates":[14.2853879929,48.2448883057],"type":"Point"}
}