{
  "type": "Feature",
  "properties": {
    "iso:country":"AT",
    "sg:address":"Heiligenst\u00e4dter Str 43",
    "sg:city":"Wien",
    "sg:orig_category":"Spirituosen / Erzeugung U Gro\u00c3\u0178handel",
    "sg:phone":"+43 1 36721210",
    "sg:postcode":"1190",
    "sg:province":"Wien",
    "wof:name":"Stock Austria GmbH",
    "wof:placetype":"venue"
},
  "geometry": {"coordinates":[16.3576927185,48.23777771],"type":"Point"}
}