{
  "type": "Feature",
  "properties": {
    "addr:full":"Nr 152 G\u00f6llersdorf Nieder\u00f6sterreich 2013",
    "addr:postcode":"2013",
    "addr:street":"Nr 152 Goellersdorf",
    "iso:country":"AT",
    "sg:address":"Nr 152",
    "sg:city":"G\u00f6llersdorf",
    "sg:orig_category":"Erdarbeiten",
    "sg:phone":"+43 2954 30192",
    "sg:postcode":"2013",
    "sg:province":"Nieder\u00f6sterreich",
    "wof:name":"H\u00f6rmann Franz",
    "wof:placetype":"venue"
},
  "geometry": {"coordinates":[166.9221496582,-0.5282999873],"type":"Point"}
}