{
  "type": "Feature",
  "properties": {
    "iso:country":"AT",
    "sg:address":"Seiserstrasse 10",
    "sg:city":"Kirchschlag in der Buckligen Welt",
    "sg:classifiers":[
        {
            "category":"Banks & Credit Unions",
            "subcategory":"Investment Brokerage",
            "type":"Services"
        }
    ],
    "sg:phone":"+43 2646 2020",
    "sg:postcode":"2860",
    "sg:province":"Nieder\u00f6sterreich",
    "sg:tags":[
        "fence"
    ],
    "wof:name":"Josef Pichler",
    "wof:placetype":"venue"
},
  "geometry": {"coordinates":[16.2750492096,47.4926986694],"type":"Point"}
}