{
  "type": "Feature",
  "properties": {
    "iso:country":"AT",
    "sg:address":"Bahnhofstr. 1a",
    "sg:city":"Asten",
    "sg:classifiers":[
        {
            "category":"Shopping",
            "subcategory":"Stationery & Office Supplies",
            "type":"Retail Goods"
        }
    ],
    "sg:phone":"+43 4372 2466372",
    "sg:postcode":"4481",
    "sg:province":"Ober\u00f6sterreich",
    "sg:tags":[
        "professional"
    ],
    "wof:name":"GRILL GESMBH",
    "wof:placetype":"venue"
},
  "geometry": {"coordinates":[14.4001426697,48.2255210876],"type":"Point"}
}