{
  "type": "Feature",
  "properties": {
    "iso:country":"AT",
    "sg:address":"Pocksteiner Str 22",
    "sg:city":"Waidhofen an der Ybbs",
    "sg:orig_category":"Tischlereien",
    "sg:phone":"+43 7442 90559",
    "sg:postcode":"3340",
    "sg:province":"Nieder\u00f6sterreich",
    "wof:name":"Schrey TischlereigesmbH",
    "wof:placetype":"venue"
},
  "geometry": {"coordinates":[14.7764625549,47.9573707581],"type":"Point"}
}