{
  "type": "Feature",
  "properties": {
    "addr:full":"Hauptpl 9 Hainburg an der Donau Nieder\u00f6sterreich 2410",
    "addr:housenumber":"9",
    "addr:postcode":"2410",
    "addr:street":"Hauptpl",
    "iso:country":"AT",
    "sg:address":"Hauptpl 9",
    "sg:city":"Hainburg an der Donau",
    "sg:orig_category":"Garten- U Landschaftsgestaltung",
    "sg:phone":"+43 4367 65580163",
    "sg:postcode":"2410",
    "sg:province":"Nieder\u00f6sterreich",
    "wof:name":"Manufaktum Verde F. Gerhard Wolf",
    "wof:placetype":"venue"
},
  "geometry": {"coordinates":[16.9424991608,48.1475105286],"type":"Point"}
}