{
  "type": "Feature",
  "properties": {
    "addr:full":"Weiten 71 Weiten Nieder\u00f6sterreich 3653",
    "addr:housenumber":"71",
    "addr:postcode":"3653",
    "addr:street":"Weiten;Niederoesterreich",
    "iso:country":"AT",
    "sg:address":"Weiten 71",
    "sg:city":"Weiten",
    "sg:classifiers":[
        {
            "category":"Home & Garden",
            "subcategory":"Furniture",
            "type":"Retail Goods"
        }
    ],
    "sg:phone":"+43 2758 8221",
    "sg:postcode":"3653",
    "sg:province":"Nieder\u00f6sterreich",
    "sg:tags":[
        "solid",
        "wood",
        "made",
        "childrens"
    ],
    "wof:name":"Ing. Hans Fletzberger",
    "wof:placetype":"venue"
},
  "geometry": {"coordinates":[15.2638158798,48.293258667],"type":"Point"}
}