{
  "type": "Feature",
  "properties": {
    "iso:country":"AT",
    "sg:address":"Grazer Str 71",
    "sg:city":"Oberwart",
    "sg:orig_category":"Partyservice",
    "sg:phone":"+43 4333 52335300",
    "sg:postcode":"7400",
    "sg:province":"Burgenland",
    "sg:website":"hotel-zur-pinka.at",
    "wof:name":"Hotel zur Pinka - Pinkast\u00fcberl",
    "wof:placetype":"venue"
},
  "geometry": {"coordinates":[16.1948719025,47.2875862122],"type":"Point"}
}