{
  "type": "Feature",
  "properties": {
    "addr:full":"Altaussee 22 Altaussee Steiermark 8992",
    "addr:housenumber":"22",
    "addr:postcode":"8992",
    "addr:street":"Altaussee",
    "iso:country":"AT",
    "sg:address":"Altaussee 22",
    "sg:city":"Altaussee",
    "sg:classifiers":[
        {
            "category":"Organizations",
            "subcategory":"Professional Association",
            "type":"Services"
        }
    ],
    "sg:phone":"+43 3622 72300",
    "sg:postcode":"8992",
    "sg:province":"Steiermark",
    "sg:tags":[
        "call"
    ],
    "sg:website":"service24.at",
    "wof:name":"Service 24 Notdienst f\u00fcr den G\u00fcterkraft-und Busreiseverkehr GmbH",
    "wof:placetype":"venue"
},
  "geometry": {"coordinates":[13.7627840042,47.6389808655],"type":"Point"}
}