{
  "type": "Feature",
  "properties": {
    "addr:full":"Hauptpl 15 Lienz Tirol 9900",
    "addr:housenumber":"15",
    "addr:postcode":"9900",
    "addr:street":"Hauptpl;Tirol",
    "iso:country":"AT",
    "sg:address":"Hauptpl 15",
    "sg:city":"Lienz",
    "sg:orig_category":"Raumausstattung",
    "sg:phone":"+43 4348 52621610",
    "sg:postcode":"9900",
    "sg:province":"Tirol",
    "sg:website":"wasserbetten.at",
    "wof:name":"ITW - Wasserbetten - Hassler Josef",
    "wof:placetype":"venue"
},
  "geometry": {"coordinates":[12.7684783936,46.8281173706],"type":"Point"}
}