{
  "type": "Feature",
  "properties": {
    "addr:full":"Nr 208 Rohrbach an der Lafnitz Steiermark 8234",
    "addr:postcode":"8234",
    "addr:street":"Nr 208",
    "iso:country":"AT",
    "sg:address":"Nr 208",
    "sg:city":"Rohrbach an der Lafnitz",
    "sg:orig_category":"Banken U Sparkassen",
    "sg:phone":"+43 4350 10033220",
    "sg:postcode":"8234",
    "sg:province":"Steiermark",
    "wof:name":"Bankomat d Sparkasse Rohrbach",
    "wof:placetype":"venue"
},
  "geometry": {"coordinates":[15.9732465744,47.3812446594],"type":"Point"}
}