{
  "type": "Feature",
  "properties": {
    "addr:full":"Gutendorfer Strasse 38 Klagenfurt K\u00e4rnten 9020",
    "addr:housenumber":"38",
    "addr:postcode":"9020",
    "addr:street":"Gutendorfer Strasse;Kaernten",
    "iso:country":"AT",
    "sg:address":"Gutendorfer Strasse 38",
    "sg:city":"Klagenfurt",
    "sg:orig_category":"Hydrographic Systems",
    "sg:phone":"+43 463 71208",
    "sg:postcode":"9020",
    "sg:province":"K\u00e4rnten",
    "sg:website":"jaeti.at",
    "wof:name":"Kurt J\u00e4ger",
    "wof:placetype":"venue"
},
  "geometry": {"coordinates":[14.3811578751,46.6309089661],"type":"Point"}
}