{
  "type": "Feature",
  "properties": {
    "addr:full":"Himberger Str 11 Schwechat Nieder\u00f6sterreich 2320",
    "addr:postcode":"2320",
    "addr:street":"Str 11 Schwechat Niederoesterreich",
    "iso:country":"AT",
    "sg:address":"Himberger Str 11",
    "sg:city":"Schwechat",
    "sg:orig_category":"Fitnesscenter",
    "sg:phone":"+43 1 7069994",
    "sg:postcode":"2320",
    "sg:province":"Nieder\u00f6sterreich",
    "sg:website":"fitness-center.at/olympia",
    "wof:name":"Olympia Fitness - Belas Artes Handels-GmbH",
    "wof:placetype":"venue"
},
  "geometry": {"coordinates":[16.4756145477,48.1376075745],"type":"Point"}
}