{
  "type": "Feature",
  "properties": {
    "addr:full":"Nr 3a St. Gallenkirch Vorarlberg 6791",
    "addr:postcode":"6791",
    "addr:street":"Nr 3A",
    "iso:country":"AT",
    "sg:address":"Nr 3a",
    "sg:city":"St. Gallenkirch",
    "sg:orig_category":"Banken U Sparkassen",
    "sg:phone":"+43 4355 576228",
    "sg:postcode":"6791",
    "sg:province":"Vorarlberg",
    "wof:name":"Bankomat d Raiffeisenbank Montafon regGenmbH",
    "wof:placetype":"venue"
},
  "geometry": {"coordinates":[9.9691953659,47.0225639343],"type":"Point"}
}