{
  "type": "Feature",
  "properties": {
    "addr:full":"Lindau 15a Fieberbrunn Tirol 6391",
    "addr:housenumber":"15a",
    "addr:postcode":"6391",
    "addr:street":"Lindau;Tirol",
    "iso:country":"AT",
    "sg:address":"Lindau 15a",
    "sg:city":"Fieberbrunn",
    "sg:classifiers":[
        {
            "category":"Park",
            "subcategory":"Provincial",
            "type":"Public Place"
        }
    ],
    "sg:phone":"+43 5354 52540",
    "sg:postcode":"6391",
    "sg:province":"Tirol",
    "sg:tags":[
        "u",
        "ski-",
        "snowboardschulen"
    ],
    "wof:name":"Schischule Fieberbrunn",
    "wof:placetype":"venue"
},
  "geometry": {"coordinates":[12.5507640839,47.4679946899],"type":"Point"}
}