{
  "type": "Feature",
  "properties": {
    "addr:full":"Reznicekgasse 6 Wien Wien 1090",
    "addr:housenumber":"6",
    "addr:postcode":"1090",
    "addr:street":"Reznicekgasse",
    "iso:country":"AT",
    "sg:address":"Reznicekgasse 6",
    "sg:city":"Wien",
    "sg:classifiers":[
        {
            "category":"Building & Trades",
            "subcategory":"Plumbing",
            "type":"Services"
        }
    ],
    "sg:phone":"+43 1 3191162",
    "sg:postcode":"1090",
    "sg:province":"Wien",
    "sg:tags":[
        "supraregional",
        "gas"
    ],
    "wof:name":"Robert Merkstallinger Ges.m.b.H.",
    "wof:placetype":"venue"
},
  "geometry": {"coordinates":[16.3568000793,48.2280845642],"type":"Point"}
}