{
  "type": "Feature",
  "properties": {
    "addr:full":"Lainzer Str 84 Wien Wien 1130",
    "addr:postcode":"1130",
    "addr:street":"Str 84",
    "iso:country":"AT",
    "sg:address":"Lainzer Str 84",
    "sg:city":"Wien",
    "sg:orig_category":"Lebensmittel / Einzelhandel",
    "sg:phone":"+43 1 8773559",
    "sg:postcode":"1130",
    "sg:province":"Wien",
    "wof:name":"Nowotny Ernst",
    "wof:placetype":"venue"
},
  "geometry": {"coordinates":[16.2851772308,48.1812477112],"type":"Point"}
}