{
  "type": "Feature",
  "properties": {
    "addr:full":"Grieskirchner Str 42 Wels Ober\u00f6sterreich 4600",
    "addr:housenumber":"42",
    "addr:postcode":"4600",
    "addr:street":"Str;Oberoesterreich",
    "iso:country":"AT",
    "sg:address":"Grieskirchner Str 42",
    "sg:city":"Wels",
    "sg:orig_category":"Weiterbildungsinstitute M Allg U Berufl Bildungsangebot",
    "sg:phone":"+43 7242 350836",
    "sg:postcode":"4600",
    "sg:province":"Ober\u00f6sterreich",
    "sg:website":"www.die-akademie-wels.at",
    "wof:name":"Akademie f\u00fcr Gesundheit und Bildung d Kreuzschwestern GmbH",
    "wof:placetype":"venue"
},
  "geometry": {"coordinates":[14.0230407715,48.1737976074],"type":"Point"}
}