{
  "type": "Feature",
  "properties": {
    "iso:country":"AT",
    "sg:address":"Nr 129/9",
    "sg:city":"Lend",
    "sg:orig_category":"Astrologie",
    "sg:phone":"+43 676 4771303",
    "sg:postcode":"5651",
    "sg:province":"Salzburg",
    "wof:name":"Brugger Birgit",
    "wof:placetype":"venue"
},
  "geometry": {"coordinates":[13.0434465408,47.299446106],"type":"Point"}
}