{
  "type": "Feature",
  "properties": {
    "iso:country":"AT",
    "sg:address":"Scheibelreiterg 10",
    "sg:city":"Wien",
    "sg:orig_category":"Ingenieurkonsulenten / Zivilingenieure",
    "sg:phone":"+43 1 3695294",
    "sg:postcode":"1190",
    "sg:province":"Wien",
    "wof:name":"Szabo Georg Dipl-Ing",
    "wof:placetype":"venue"
},
  "geometry": {"coordinates":[16.3400745392,48.2544288635],"type":"Point"}
}