{
  "type": "Feature",
  "properties": {
    "addr:full":"Neuberg 134 Filzmoos Salzburg 5532",
    "addr:housenumber":"134",
    "addr:postcode":"5532",
    "addr:street":"Neuberg;Salzburg",
    "iso:country":"AT",
    "sg:address":"Neuberg 134",
    "sg:city":"Filzmoos",
    "sg:orig_category":"Pensionen / Privatzimmer",
    "sg:phone":"+43 6453 8539",
    "sg:postcode":"5532",
    "sg:province":"Salzburg",
    "wof:name":"Landhaus Vierthaler",
    "wof:placetype":"venue"
},
  "geometry": {"coordinates":[13.5203046799,47.4333534241],"type":"Point"}
}