{
  "type": "Feature",
  "properties": {
    "addr:full":"Kleeblattg 43 Sollenau Nieder\u00f6sterreich 2601",
    "addr:housenumber":"43",
    "addr:postcode":"2601",
    "addr:street":"Kleeblattg",
    "iso:country":"AT",
    "sg:address":"Kleeblattg 43",
    "sg:city":"Sollenau",
    "sg:orig_category":"Transportbeton",
    "sg:phone":"+43 2628 67795",
    "sg:postcode":"2601",
    "sg:province":"Nieder\u00f6sterreich",
    "sg:website":"baubeton.at",
    "wof:name":"Bau Beton GmbH",
    "wof:placetype":"venue"
},
  "geometry": {"coordinates":[16.2587566376,47.8883323669],"type":"Point"}
}