{
  "type": "Feature",
  "properties": {
    "addr:full":"Hauptstr 9 Unterach am Attersee Ober\u00f6sterreich 4866",
    "addr:housenumber":"9",
    "addr:postcode":"4866",
    "addr:street":"Hauptstr",
    "iso:country":"AT",
    "sg:address":"Hauptstr 9",
    "sg:city":"Unterach am Attersee",
    "sg:orig_category":"Gemeinden",
    "sg:phone":"+43 766582550",
    "sg:postcode":"4866",
    "sg:province":"Ober\u00f6sterreich",
    "wof:name":"Gemeindeamt Unterach am Attersee",
    "wof:placetype":"venue"
},
  "geometry": {"coordinates":[13.4876689911,47.8040618896],"type":"Point"}
}