{
  "type": "Feature",
  "properties": {
    "addr:full":"Sigmund Haffner-G 14/II Salzburg Salzburg 5020",
    "addr:housenumber":"14 / ii",
    "addr:postcode":"5020",
    "addr:street":"Salzburg",
    "iso:country":"AT",
    "sg:address":"Sigmund Haffner-G 14/II",
    "sg:city":"Salzburg",
    "sg:orig_category":"Weiterbildungsinstitute M Allg U Berufl Bildungsangebot",
    "sg:phone":"+43 4366 28401110",
    "sg:postcode":"5020",
    "sg:province":"Salzburg",
    "wof:name":"Management Akademie a d Universit\u00e4t Salzburg",
    "wof:placetype":"venue"
},
  "geometry": {"coordinates":[13.0433769226,47.8006744385],"type":"Point"}
}