{
  "type": "Feature",
  "properties": {
    "iso:country":"AT",
    "sg:address":"Rengerweg 15",
    "sg:city":"Bad Vigaun",
    "sg:orig_category":"Erdarbeiten",
    "sg:phone":"+43 664 3858169",
    "sg:postcode":"5424",
    "sg:province":"Salzburg",
    "wof:name":"Wallmann Herbert",
    "wof:placetype":"venue"
},
  "geometry": {"coordinates":[13.1731395721,47.6754608154],"type":"Point"}
}