{
  "type": "Feature",
  "properties": {
    "addr:full":"K\u00e4rntner Strasse 10 Wien Wien 1010",
    "addr:housenumber":"10",
    "addr:postcode":"1010",
    "addr:street":"Kaerntner Strasse",
    "iso:country":"AT",
    "sg:address":"K\u00e4rntner Strasse 10",
    "sg:city":"Wien",
    "sg:orig_category":"Forms For Lawyers And Notaries",
    "sg:phone":"+43 1 5121427",
    "sg:postcode":"1010",
    "sg:province":"Wien",
    "sg:website":"advo.at",
    "wof:name":"BOLLER LANGHAMMER SCHUBERT Rechtsanw\u00e4lte OEG",
    "wof:placetype":"venue"
},
  "geometry": {"coordinates":[16.3714313507,48.2070465088],"type":"Point"}
}