{
  "type": "Feature",
  "properties": {
    "addr:full":"Hauptpl 1 St. Leonhard am Forst Nieder\u00f6sterreich 3243",
    "addr:housenumber":"1",
    "addr:postcode":"3243",
    "addr:street":"Hauptpl",
    "iso:country":"AT",
    "sg:address":"Hauptpl 1",
    "sg:city":"St. Leonhard am Forst",
    "sg:orig_category":"Tabaktrafiken",
    "sg:phone":"+43 4327 568955",
    "sg:postcode":"3243",
    "sg:province":"Nieder\u00f6sterreich",
    "wof:name":"Mayer Gabriele",
    "wof:placetype":"venue"
},
  "geometry": {"coordinates":[15.2852468491,48.1427154541],"type":"Point"}
}