{
  "type": "Feature",
  "properties": {
    "addr:full":"Migazzipl 3 Wien Wien 1120",
    "addr:housenumber":"3",
    "addr:postcode":"1120",
    "addr:street":"Migazzipl",
    "iso:country":"AT",
    "sg:address":"Migazzipl 3",
    "sg:city":"Wien",
    "sg:orig_category":"Immobilienverwaltungen",
    "sg:phone":"+43 1 8135324",
    "sg:postcode":"1120",
    "sg:province":"Wien",
    "wof:name":"Weislein & Brauner GesmbH",
    "wof:placetype":"venue"
},
  "geometry": {"coordinates":[16.3357601166,48.1818161011],"type":"Point"}
}