{
  "type": "Feature",
  "properties": {
    "addr:full":"Burgg 2 Klagenfurt K\u00e4rnten 9020",
    "addr:housenumber":"2",
    "addr:postcode":"9020",
    "addr:street":"Burgg;Kaernten",
    "iso:country":"AT",
    "sg:address":"Burgg 2",
    "sg:city":"Klagenfurt",
    "sg:orig_category":"Juwelen, Gold- U Silberwaren / Einzelhandel",
    "sg:phone":"+43 463 511914",
    "sg:postcode":"9020",
    "sg:province":"K\u00e4rnten",
    "wof:name":"Urner Eduard",
    "wof:placetype":"venue"
},
  "geometry": {"coordinates":[14.3087387085,46.6241264343],"type":"Point"}
}