{
  "type": "Feature",
  "properties": {
    "addr:full":"Hauptstr 2 Leobersdorf Nieder\u00f6sterreich 2544",
    "addr:housenumber":"2",
    "addr:postcode":"2544",
    "addr:street":"Hauptstr",
    "iso:country":"AT",
    "sg:address":"Hauptstr 2",
    "sg:city":"Leobersdorf",
    "sg:orig_category":"Fu\u00c3\u0178pflege U Fu\u00c3\u0178pflegesalons",
    "sg:phone":"+43 4366 45577522",
    "sg:postcode":"2544",
    "sg:province":"Nieder\u00f6sterreich",
    "wof:name":"Nails & More Fu\u00dfpflege- u Nagelstudio Portner",
    "wof:placetype":"venue"
},
  "geometry": {"coordinates":[16.2163047791,47.9299125671],"type":"Point"}
}