{
  "type": "Feature",
  "properties": {
    "iso:country":"AT",
    "sg:address":"Nr 28",
    "sg:city":"Gnas",
    "sg:orig_category":"Fotografen",
    "sg:phone":"+43 4331 512204",
    "sg:postcode":"8342",
    "sg:province":"Steiermark",
    "wof:name":"Ettl Franz",
    "wof:placetype":"venue"
},
  "geometry": {"coordinates":[15.8265724182,46.8743095398],"type":"Point"}
}