{
  "type": "Feature",
  "properties": {
    "addr:full":"Postpl 360 Tamsweg Salzburg 5580",
    "addr:housenumber":"360",
    "addr:postcode":"5580",
    "addr:street":"Tamsweg Salzburg",
    "iso:country":"AT",
    "sg:address":"Postpl 360",
    "sg:city":"Tamsweg",
    "sg:orig_category":"Friseure U Frisiersalons",
    "sg:phone":"+43 4364 742362",
    "sg:postcode":"5580",
    "sg:province":"Salzburg",
    "wof:name":"Frisiersalon Erika",
    "wof:placetype":"venue"
},
  "geometry": {"coordinates":[13.8089151382,47.1268844604],"type":"Point"}
}