{
  "type": "Feature",
  "properties": {
    "addr:full":"Dragonerstr 69 Wels Ober\u00f6sterreich 4600",
    "addr:housenumber":"69",
    "addr:postcode":"4600",
    "addr:street":"Dragonerstr;Oberoesterreich",
    "iso:country":"AT",
    "sg:address":"Dragonerstr 69",
    "sg:city":"Wels",
    "sg:orig_category":"Raumausstattung",
    "sg:phone":"+43 4372 42663110",
    "sg:postcode":"4600",
    "sg:province":"Ober\u00f6sterreich",
    "sg:website":"tikal.at",
    "wof:name":"Tikal GmbH & Co KG",
    "wof:placetype":"venue"
},
  "geometry": {"coordinates":[14.0057640076,48.1541519165],"type":"Point"}
}