{
  "type": "Feature",
  "properties": {
    "addr:full":"Italiener Strasse 56 Villach K\u00e4rnten 9500",
    "addr:housenumber":"56",
    "addr:postcode":"9500",
    "addr:street":"Italiener Strasse;Kaernten",
    "iso:country":"AT",
    "sg:address":"Italiener Strasse 56",
    "sg:city":"Villach",
    "sg:classifiers":[
        {
            "category":"Banks & Credit Unions",
            "subcategory":"Investment Brokerage",
            "type":"Services"
        }
    ],
    "sg:phone":"+43 4242 23359",
    "sg:postcode":"9500",
    "sg:province":"K\u00e4rnten",
    "sg:tags":[
        "absorption",
        "refrigerator"
    ],
    "sg:website":"elektro-maschke.at",
    "wof:name":"Elektrounternehmen K. Maschke Ges.m.b.H. & Co KG",
    "wof:placetype":"venue"
},
  "geometry": {"coordinates":[13.840587616,46.6048622131],"type":"Point"}
}