{
  "type": "Feature",
  "properties": {
    "addr:full":"Barmhartstalstr 49 Maria Enzersdorf Nieder\u00f6sterreich 2344",
    "addr:housenumber":"49",
    "addr:postcode":"2344",
    "addr:street":"Barmhartstalstr",
    "iso:country":"AT",
    "sg:address":"Barmhartstalstr 49",
    "sg:city":"Maria Enzersdorf",
    "sg:classifiers":[
        {
            "category":"Wholesale",
            "subcategory":"Stationery",
            "type":"Manufacturing & Wholesale Goods"
        }
    ],
    "sg:phone":"+43 4322 36893221",
    "sg:postcode":"2344",
    "sg:province":"Nieder\u00f6sterreich",
    "sg:tags":[
        "sport-",
        "u",
        "sponsoring-agenturen"
    ],
    "wof:name":"Lobenhofer Robert",
    "wof:placetype":"venue"
},
  "geometry": {"coordinates":[16.263835907,48.1002349854],"type":"Point"}
}