{
  "type": "Feature",
  "properties": {
    "addr:full":"Bachwinkel 89 Saalfelden am Steinernen Meer Salzburg 5760",
    "addr:housenumber":"89",
    "addr:postcode":"5760",
    "addr:street":"Bachwinkel;Salzburg",
    "iso:country":"AT",
    "sg:address":"Bachwinkel 89",
    "sg:city":"Saalfelden am Steinernen Meer",
    "sg:orig_category":"Forstbedarf",
    "sg:phone":"+43 4365 8274638",
    "sg:postcode":"5760",
    "sg:province":"Salzburg",
    "wof:name":"Z\u00f6ggeler Baumaschinen und Nutzfahrzeuge KEG",
    "wof:placetype":"venue"
},
  "geometry": {"coordinates":[12.8623638153,47.4410018921],"type":"Point"}
}