{
  "type": "Feature",
  "properties": {
    "iso:country":"AT",
    "sg:address":"Triester Str 372",
    "sg:city":"Puntigam",
    "sg:orig_category":"Tabaktrafiken",
    "sg:phone":"+43 316 294342",
    "sg:postcode":"8055",
    "sg:province":"Steiermark",
    "wof:name":"Tabakfachgesch\u00e4ft Alois Zacharias",
    "wof:placetype":"venue"
},
  "geometry": {"coordinates":[15.4333057404,47.0277519226],"type":"Point"}
}