{
  "type": "Feature",
  "properties": {
    "iso:country":"AT",
    "sg:address":"Schenkenstr 8",
    "sg:city":"Wien",
    "sg:orig_category":"Politische Parteien",
    "sg:phone":"+43 1 401106698",
    "sg:postcode":"1010",
    "sg:province":"Wien",
    "wof:name":"Gr\u00fcner Klub im Parlament",
    "wof:placetype":"venue"
},
  "geometry": {"coordinates":[16.3629970551,48.2109184265],"type":"Point"}
}