{
  "type": "Feature",
  "properties": {
    "iso:country":"AT",
    "sg:address":"Kaufmannstr 17",
    "sg:city":"Innsbruck",
    "sg:orig_category":"Immobilienmakler",
    "sg:phone":"+43 512 337300",
    "sg:postcode":"6020",
    "sg:province":"Tirol",
    "wof:name":"Tirotel Immobilienverwaltungs- und VermittlungsgesmbH",
    "wof:placetype":"venue"
},
  "geometry": {"coordinates":[11.416639328,47.2578811646],"type":"Point"}
}