{
  "type": "Feature",
  "properties": {
    "addr:full":"Am Kalkberg 7 Mariahof Steiermark 8812",
    "addr:housenumber":"7",
    "addr:postcode":"8812",
    "addr:street":"Am Kalkberg",
    "iso:country":"AT",
    "sg:address":"Am Kalkberg 7",
    "sg:city":"Mariahof",
    "sg:orig_category":"Pensionen / Privatzimmer",
    "sg:phone":"+43 4335 852575",
    "sg:postcode":"8812",
    "sg:province":"Steiermark",
    "wof:name":"Podolerhof L\u00f6cker Klaus u Michaela",
    "wof:placetype":"venue"
},
  "geometry": {"coordinates":[14.347495079,47.106918335],"type":"Point"}
}