{
  "type": "Feature",
  "properties": {
    "addr:full":"Gustav Renker-Weg 2 Bodensdorf K\u00e4rnten 9551",
    "addr:housenumber":"2",
    "addr:postcode":"9551",
    "addr:street":"Gustav Renker-Weg;Kaernten",
    "iso:country":"AT",
    "sg:address":"Gustav Renker-Weg 2",
    "sg:city":"Bodensdorf",
    "sg:orig_category":"Bankomat-Standorte",
    "sg:phone":"+43 4243 87000",
    "sg:postcode":"9551",
    "sg:province":"K\u00e4rnten",
    "wof:name":"Bankomat d Volksbank Feldkirchen regGenmbH",
    "wof:placetype":"venue"
},
  "geometry": {"coordinates":[13.9728527069,46.6842079163],"type":"Point"}
}