{
  "type": "Feature",
  "properties": {
    "addr:full":"Gabrieler Strasse 2-4 Maria Enzersdorf Nieder\u00f6sterreich 2344",
    "addr:housenumber":"2-4",
    "addr:postcode":"2344",
    "addr:street":"Gabrieler Strasse",
    "iso:country":"AT",
    "sg:address":"Gabrieler Strasse 2-4",
    "sg:city":"Maria Enzersdorf",
    "sg:classifiers":[
        {
            "category":"Shopping",
            "subcategory":"Crafts & Fabrics",
            "type":"Retail Goods"
        }
    ],
    "sg:phone":"+43 2236 80900",
    "sg:postcode":"2344",
    "sg:province":"Nieder\u00f6sterreich",
    "sg:tags":[
        "guillotine",
        "graphic",
        "trade"
    ],
    "sg:website":"kba.at",
    "wof:name":"KBA-M\u00f6dling AG",
    "wof:placetype":"venue"
},
  "geometry": {"coordinates":[16.2953701019,48.0956916809],"type":"Point"}
}