{
  "type": "Feature",
  "properties": {
    "iso:country":"AT",
    "sg:address":"Georgenberg 110",
    "sg:city":"Kuchl",
    "sg:orig_category":"Beschriftungen, Autobeschriftungen, Digitaldruck, Textildruckereien",
    "sg:phone":"+43 6244 20229",
    "sg:postcode":"5431",
    "sg:province":"Salzburg",
    "sg:website":"prosim-schilder.at",
    "wof:name":"PRO SIM - Schilder",
    "wof:placetype":"venue"
},
  "geometry": {"coordinates":[13.1509180069,47.6254463196],"type":"Point"}
}