{
  "type": "Feature",
  "properties": {
    "iso:country":"AT",
    "sg:address":"Grazerstrasse 1 ",
    "sg:city":"Wartberg im M\u00fcrztal",
    "sg:classifiers":[
        {
            "category":"Manufacturing",
            "subcategory":"Metals",
            "type":"Manufacturing & Wholesale Goods"
        }
    ],
    "sg:phone":"+43 3858 6000",
    "sg:postcode":"8661",
    "sg:province":"Steiermark",
    "sg:tags":[
        "blanking",
        "dy"
    ],
    "sg:website":"www.vogel-noot.com",
    "wof:name":"Vogel & Noot Technologie GmbH",
    "wof:placetype":"venue"
},
  "geometry": {"coordinates":[15.4847402573,47.5267410278],"type":"Point"}
}