{
  "type": "Feature",
  "properties": {
    "addr:full":"Herzog-Friedrich-Str 21 Innsbruck Tirol 6020",
    "addr:housenumber":"21",
    "addr:postcode":"6020",
    "addr:street":"Herzog-Friedrich-Str;Tirol",
    "iso:country":"AT",
    "sg:address":"Herzog-Friedrich-Str 21",
    "sg:city":"Innsbruck",
    "sg:orig_category":"Galerien",
    "sg:phone":"+43 512 578154",
    "sg:postcode":"6020",
    "sg:province":"Tirol",
    "wof:name":"Stadtturmgalerie",
    "wof:placetype":"venue"
},
  "geometry": {"coordinates":[11.3934059143,47.2682914734],"type":"Point"}
}