{
  "type": "Feature",
  "properties": {
    "iso:country":"AT",
    "sg:address":"Nr 126",
    "sg:city":"Niederw\u00f6lz",
    "sg:orig_category":"Autohandel",
    "sg:phone":"+43 4335 8222690",
    "sg:postcode":"8831",
    "sg:province":"Steiermark",
    "wof:name":"Sapper H GmbH & Co KG",
    "wof:placetype":"venue"
},
  "geometry": {"coordinates":[-97.7764587402,30.0193119049],"type":"Point"}
}