{
  "type": "Feature",
  "properties": {
    "addr:full":"Lederau 26 Vorchdorf Ober\u00f6sterreich 4655",
    "addr:housenumber":"26",
    "addr:postcode":"4655",
    "addr:street":"Lederau",
    "iso:country":"AT",
    "sg:address":"Lederau 26",
    "sg:city":"Vorchdorf",
    "sg:classifiers":[
        {
            "category":"Banks & Credit Unions",
            "subcategory":"Bureau De Change",
            "type":"Services"
        }
    ],
    "sg:phone":"+43 7586 7348",
    "sg:postcode":"4655",
    "sg:province":"Ober\u00f6sterreich",
    "sg:tags":[
        "construction",
        "system",
        "roof"
    ],
    "wof:name":"Aitzetm\u00fcller S\u00e4ge KG",
    "wof:placetype":"venue"
},
  "geometry": {"coordinates":[13.9856624603,47.9626617432],"type":"Point"}
}