{
  "type": "Feature",
  "properties": {
    "addr:full":"Seeb\u00f6ckg 19 Wien Wien 1160",
    "addr:housenumber":"19",
    "addr:postcode":"1160",
    "addr:street":"Seeboeckg",
    "iso:country":"AT",
    "sg:address":"Seeb\u00f6ckg 19",
    "sg:city":"Wien",
    "sg:orig_category":"Bilderrahmen",
    "sg:phone":"+43 4314 8615270",
    "sg:postcode":"1160",
    "sg:province":"Wien",
    "sg:website":"magerglas.at",
    "wof:name":"Mager Glas GesmbH",
    "wof:placetype":"venue"
},
  "geometry": {"coordinates":[16.3163547516,48.2178039551],"type":"Point"}
}