{
  "type": "Feature",
  "properties": {
    "addr:full":"Bahnstr 4a Inzing Tirol 6401",
    "addr:housenumber":"4a",
    "addr:postcode":"6401",
    "addr:street":"Bahnstr;Tirol",
    "iso:country":"AT",
    "sg:address":"Bahnstr 4a",
    "sg:city":"Inzing",
    "sg:orig_category":"Apotheken",
    "sg:phone":"+43 5238 880500",
    "sg:postcode":"6401",
    "sg:province":"Tirol",
    "wof:name":"Christophorus Apotheke Magpharm Silvie Haupt",
    "wof:placetype":"venue"
},
  "geometry": {"coordinates":[11.1977968216,47.2744789124],"type":"Point"}
}