{
  "type": "Feature",
  "properties": {
    "addr:full":"Altenhof Goldegg Salzburg 5622",
    "addr:postcode":"5622",
    "addr:street":"Altenhof;Salzburg",
    "iso:country":"AT",
    "sg:address":"Altenhof",
    "sg:city":"Goldegg",
    "sg:orig_category":"Bergbahnen",
    "sg:phone":"+43 4364 158155",
    "sg:postcode":"5622",
    "sg:province":"Salzburg",
    "wof:name":"Buchberger Goldegger Skilift GesmbH & Co KG",
    "wof:placetype":"venue"
},
  "geometry": {"coordinates":[13.0851945877,47.3159294128],"type":"Point"}
}