{
  "type": "Feature",
  "properties": {
    "addr:full":"Murbodenstrasse 8 Peggau Steiermark 8120",
    "addr:housenumber":"8",
    "addr:postcode":"8120",
    "addr:street":"Murbodenstrasse",
    "iso:country":"AT",
    "sg:address":"Murbodenstrasse 8",
    "sg:city":"Peggau",
    "sg:classifiers":[
        {
            "category":"Manufacturing",
            "subcategory":"Wood Products",
            "type":"Manufacturing & Wholesale Goods"
        }
    ],
    "sg:phone":"+43 3127 28424",
    "sg:postcode":"8120",
    "sg:province":"Steiermark",
    "sg:tags":[
        "solid",
        "ceiling",
        "made",
        "panel"
    ],
    "wof:name":"Andrea Palzer-Felser",
    "wof:placetype":"venue"
},
  "geometry": {"coordinates":[15.3464012146,47.1973571777],"type":"Point"}
}