{
  "type": "Feature",
  "properties": {
    "iso:country":"AT",
    "sg:address":"Wetzelsdorfer Str 154",
    "sg:city":"Wetzelsdorf",
    "sg:orig_category":"Inkassoinstitute",
    "sg:phone":"+43 4331 6586485",
    "sg:postcode":"8052",
    "sg:province":"Steiermark",
    "wof:name":"Inkasso Wottle",
    "wof:placetype":"venue"
},
  "geometry": {"coordinates":[15.3107299805,47.0647239685],"type":"Point"}
}