{
  "type": "Feature",
  "properties": {
    "iso:country":"AT",
    "sg:address":"Kapellenweg 19",
    "sg:city":"Kirchham",
    "sg:orig_category":"Tischlereien",
    "sg:phone":"+43 76192188",
    "sg:postcode":"4656",
    "sg:province":"Ober\u00f6sterreich",
    "wof:name":"Radner Johann - Tischler Montagen",
    "wof:placetype":"venue"
},
  "geometry": {"coordinates":[13.8960809708,47.9734115601],"type":"Point"}
}