{
  "type": "Feature",
  "properties": {
    "addr:full":"Rosenb\u00fchelrotte 59 Frankenfels Nieder\u00f6sterreich 3213",
    "addr:housenumber":"59",
    "addr:postcode":"3213",
    "addr:street":"Rosenbuehelrotte",
    "iso:country":"AT",
    "sg:address":"Rosenb\u00fchelrotte 59",
    "sg:city":"Frankenfels",
    "sg:orig_category":"Autoreparatur",
    "sg:phone":"+43 2725 7280",
    "sg:postcode":"3213",
    "sg:province":"Nieder\u00f6sterreich",
    "wof:name":"H\u00f6sl Gerhard",
    "wof:placetype":"venue"
},
  "geometry": {"coordinates":[15.3225898743,47.9807357788],"type":"Point"}
}