{
  "type": "Feature",
  "properties": {
    "addr:full":"Imolkam 58 Polling im Innkreis Ober\u00f6sterreich 4951",
    "addr:housenumber":"58",
    "addr:postcode":"4951",
    "addr:street":"Imolkam",
    "iso:country":"AT",
    "sg:address":"Imolkam 58",
    "sg:city":"Polling im Innkreis",
    "sg:orig_category":"Offsetdruckereien",
    "sg:phone":"+43 7723 6424",
    "sg:postcode":"4951",
    "sg:province":"Ober\u00f6sterreich",
    "wof:name":"Gierzinger Gerhard",
    "wof:placetype":"venue"
},
  "geometry": {"coordinates":[13.2963237762,48.2259864807],"type":"Point"}
}