{
  "type": "Feature",
  "properties": {
    "addr:full":"Bundesstr 102 Rankweil Vorarlberg 6830",
    "addr:housenumber":"102",
    "addr:postcode":"6830",
    "iso:country":"AT",
    "sg:address":"Bundesstr 102",
    "sg:city":"Rankweil",
    "sg:orig_category":"Alarmanlagen U Sicherheitssysteme",
    "sg:phone":"+43 4355 2232609",
    "sg:postcode":"6830",
    "sg:province":"Vorarlberg",
    "wof:name":"Hartmann Sicherheitstechnik GmbH",
    "wof:placetype":"venue"
},
  "geometry": {"coordinates":[9.6205682755,47.2891731262],"type":"Point"}
}