{
  "type": "Feature",
  "properties": {
    "addr:full":"Steinergasse 8 Wien Wien 1170",
    "addr:housenumber":"8",
    "addr:postcode":"1170",
    "addr:street":"Steinergasse",
    "iso:country":"AT",
    "sg:address":"Steinergasse 8",
    "sg:city":"Wien",
    "sg:classifiers":[
        {
            "category":"Utilities",
            "subcategory":"Natural Gas",
            "type":"Services"
        }
    ],
    "sg:phone":"+43 1 4023300",
    "sg:postcode":"1170",
    "sg:province":"Wien",
    "sg:tags":[
        "fertilizer",
        "biological"
    ],
    "sg:website":"austroschnee.at",
    "wof:name":"Heinz W. Twaroch Ges.m.b.H.",
    "wof:placetype":"venue"
},
  "geometry": {"coordinates":[16.3334293365,48.2153358459],"type":"Point"}
}