{
  "type": "Feature",
  "properties": {
    "addr:full":"Karlg 10 Purkersdorf Nieder\u00f6sterreich 3002",
    "addr:housenumber":"10",
    "addr:postcode":"3002",
    "addr:street":"Karlg",
    "iso:country":"AT",
    "sg:address":"Karlg 10",
    "sg:city":"Purkersdorf",
    "sg:orig_category":"Appartements / Ferienwohnungen",
    "sg:phone":"+43 4322 3161485",
    "sg:postcode":"3002",
    "sg:province":"Nieder\u00f6sterreich",
    "wof:name":"Villa Marie - Fam. Dickmanns",
    "wof:placetype":"venue"
},
  "geometry": {"coordinates":[16.1757965088,48.2075881958],"type":"Point"}
}