{
  "type": "Feature",
  "properties": {
    "addr:full":"Wiener Str 56 Oberwart Burgenland 7400",
    "addr:postcode":"7400",
    "iso:country":"AT",
    "sg:address":"Wiener Str 56",
    "sg:city":"Oberwart",
    "sg:classifiers":[
        {
            "category":"Travel",
            "subcategory":"Hotels & Motels",
            "type":"Entertainment"
        }
    ],
    "sg:phone":"+43 3352 32202",
    "sg:postcode":"7400",
    "sg:province":"Burgenland",
    "wof:name":"Kantor's Ludwig Wwe Juliane Kantor",
    "wof:placetype":"venue"
},
  "geometry": {"coordinates":[16.2065086365,47.2935447693],"type":"Point"}
}