{
  "type": "Feature",
  "properties": {
    "iso:country":"AT",
    "sg:city":"Pertisau",
    "sg:orig_category":"Feuerwehren",
    "sg:phone":"+43 5243 5950",
    "sg:postcode":"6213",
    "sg:province":"Tirol",
    "wof:name":"Freiwillige Feuerwehr Pertisau",
    "wof:placetype":"venue"
},
  "geometry": {"coordinates":[11.6961479187,47.4396896362],"type":"Point"}
}