{
  "type": "Feature",
  "properties": {
    "addr:full":"Fraueng 7 Graz Steiermark 8010",
    "addr:housenumber":"7",
    "addr:postcode":"8010",
    "addr:street":"Fraueng",
    "iso:country":"AT",
    "sg:address":"Fraueng 7",
    "sg:city":"Graz",
    "sg:classifiers":[
        {
            "category":"Professional",
            "subcategory":"Computer Services",
            "type":"Services"
        }
    ],
    "sg:phone":"+43 4331 6811968",
    "sg:postcode":"8010",
    "sg:province":"Steiermark",
    "sg:tags":[
        "software"
    ],
    "wof:name":"DOX.AT Softwareentwicklungs- u Dienstleistungs GmbH",
    "wof:placetype":"venue"
},
  "geometry": {"coordinates":[15.4406833649,47.0687828064],"type":"Point"}
}