{
  "type": "Feature",
  "properties": {
    "addr:full":"Hintere Ortsstr 65 Himberg Nieder\u00f6sterreich 2325",
    "addr:housenumber":"65",
    "addr:postcode":"2325",
    "addr:street":"Hintere Ortsstr",
    "iso:country":"AT",
    "sg:address":"Hintere Ortsstr 65",
    "sg:city":"Himberg",
    "sg:orig_category":"Automatisierungstechnik",
    "sg:phone":"+43 664 1028280",
    "sg:postcode":"2325",
    "sg:province":"Nieder\u00f6sterreich",
    "wof:name":"Aumatec Automatisierungstechnik GesmbH",
    "wof:placetype":"venue"
},
  "geometry": {"coordinates":[16.4411468506,48.0812911987],"type":"Point"}
}