{
  "type": "Feature",
  "properties": {
    "addr:full":"Pradler Str 25/13 Innsbruck Tirol 6020",
    "addr:housenumber":"25 / 13",
    "addr:postcode":"6020",
    "addr:street":"Pradler Str;Tirol",
    "iso:country":"AT",
    "sg:address":"Pradler Str 25/13",
    "sg:city":"Innsbruck",
    "sg:orig_category":"Baumeister",
    "sg:phone":"+43 512 283500",
    "sg:postcode":"6020",
    "sg:province":"Tirol",
    "wof:name":"Wohngef\u00fchl - Immobilien GmbH - Immobilientreuh\u00e4nder-Arch-Baumeister-Baumanagement",
    "wof:placetype":"venue"
},
  "geometry": {"coordinates":[11.4085178375,47.2672729492],"type":"Point"}
}