{
  "type": "Feature",
  "properties": {
    "addr:full":"K\u00f6rmender Str 35-37 F\u00fcrstenfeld Steiermark 8280",
    "addr:housenumber":"35-37",
    "addr:postcode":"8280",
    "addr:street":"Str",
    "iso:country":"AT",
    "sg:address":"K\u00f6rmender Str 35-37",
    "sg:city":"F\u00fcrstenfeld",
    "sg:orig_category":"Autoersatzteile",
    "sg:phone":"+43 3382 558300",
    "sg:postcode":"8280",
    "sg:province":"Steiermark",
    "wof:name":"Forstinger Handel und Service GmbH",
    "wof:placetype":"venue"
},
  "geometry": {"coordinates":[16.0904331207,47.0494041443],"type":"Point"}
}