{
  "type": "Feature",
  "properties": {
    "addr:full":"\u00d6pping 100 Rohrbach in Ober\u00f6sterreich Ober\u00f6sterreich 4150",
    "addr:housenumber":"100",
    "addr:postcode":"4150",
    "iso:country":"AT",
    "sg:address":"\u00d6pping 100",
    "sg:city":"Rohrbach in Ober\u00f6sterreich",
    "sg:classifiers":[
        {
            "category":"Manufacturing",
            "subcategory":"Rubber & Plastics",
            "type":"Manufacturing & Wholesale Goods"
        }
    ],
    "sg:phone":"+43 4372 894611",
    "sg:postcode":"4150",
    "sg:province":"Ober\u00f6sterreich",
    "wof:name":"LERIPA KUNSTSTOFFE GMBH & CO KG",
    "wof:placetype":"venue"
},
  "geometry": {"coordinates":[13.9905195236,48.5726852417],"type":"Point"}
}