{
  "type": "Feature",
  "properties": {
    "addr:full":"Prinz-Eugen-Str 13a Linz Ober\u00f6sterreich 4020",
    "addr:housenumber":"13a",
    "addr:postcode":"4020",
    "addr:street":"Prinz-Eugen-Str",
    "iso:country":"AT",
    "sg:address":"Prinz-Eugen-Str 13a",
    "sg:city":"Linz",
    "sg:orig_category":"Transportunternehmen",
    "sg:phone":"+43 732 786735",
    "sg:postcode":"4020",
    "sg:province":"Ober\u00f6sterreich",
    "wof:name":"\u00dcbersiedlungsprofi GesmbH",
    "wof:placetype":"venue"
},
  "geometry": {"coordinates":[14.3140163422,48.301158905],"type":"Point"}
}