{
  "type": "Feature",
  "properties": {
    "iso:country":"AT",
    "sg:address":"Am Lohningfeld 38",
    "sg:city":"Zell am See",
    "sg:classifiers":[
        {
            "category":"Insurance",
            "subcategory":"Insurance Agent",
            "type":"Services"
        }
    ],
    "sg:phone":"+43 7229 73333",
    "sg:postcode":"5700",
    "sg:province":"Salzburg",
    "sg:tags":[
        "instrument",
        "geophysical",
        "measurement"
    ],
    "wof:name":"Thumersbacher Ger\u00e4teverleih Ges.m.b.H.",
    "wof:placetype":"venue"
},
  "geometry": {"coordinates":[-98.7340621948,44.8969116211],"type":"Point"}
}