{
  "type": "Feature",
  "properties": {
    "addr:full":"Peuerbach Ober\u00f6sterreich 4722",
    "addr:postcode":"4722",
    "iso:country":"AT",
    "sg:city":"Peuerbach",
    "sg:orig_category":"Feuerwehren",
    "sg:phone":"+43 7276 2549",
    "sg:postcode":"4722",
    "sg:province":"Ober\u00f6sterreich",
    "wof:name":"Freiwillige Feuerwehr Oberndorf",
    "wof:placetype":"venue"
},
  "geometry": {"coordinates":[13.7729463577,48.3276634216],"type":"Point"}
}