{
  "type": "Feature",
  "properties": {
    "addr:full":"Hauptstr 10 Stockerau Nieder\u00f6sterreich 2000",
    "addr:housenumber":"10",
    "addr:postcode":"2000",
    "addr:street":"Hauptstr",
    "iso:country":"AT",
    "sg:address":"Hauptstr 10",
    "sg:city":"Stockerau",
    "sg:orig_category":"Fahrschulen",
    "sg:phone":"+43 2266 65771",
    "sg:postcode":"2000",
    "sg:province":"Nieder\u00f6sterreich",
    "wof:name":"Fahrschule Josef Lukas",
    "wof:placetype":"venue"
},
  "geometry": {"coordinates":[16.2094211578,48.3849220276],"type":"Point"}
}