{
  "type": "Feature",
  "properties": {
    "addr:full":"Hinterhof 2 Oberperfuss Tirol 6173",
    "addr:housenumber":"2",
    "addr:postcode":"6173",
    "addr:street":"Hinterhof;Tirol",
    "iso:country":"AT",
    "sg:address":"Hinterhof 2",
    "sg:city":"Oberperfuss",
    "sg:orig_category":"Transportunternehmen",
    "sg:phone":"+43 5232 81361",
    "sg:postcode":"6173",
    "sg:province":"Tirol",
    "wof:name":"Rubatscher Anton",
    "wof:placetype":"venue"
},
  "geometry": {"coordinates":[11.2500524521,47.2472686768],"type":"Point"}
}