{
  "type": "Feature",
  "properties": {
    "addr:full":"Kirchg 2a St. Michael in Obersteiermark Steiermark 8770",
    "addr:housenumber":"2a",
    "addr:postcode":"8770",
    "addr:street":"Kirchg",
    "iso:country":"AT",
    "sg:address":"Kirchg 2a",
    "sg:city":"St. Michael in Obersteiermark",
    "sg:orig_category":"Feuerzeuge",
    "sg:phone":"+43 4338 4351400",
    "sg:postcode":"8770",
    "sg:province":"Steiermark",
    "sg:website":"kamper.cc",
    "wof:name":"Kamper Kurt Vertrieb v Kugelschreibern u Einwegfeuerzeugen",
    "wof:placetype":"venue"
},
  "geometry": {"coordinates":[15.0200557709,47.3372573853],"type":"Point"}
}