{
  "type": "Feature",
  "properties": {
    "iso:country":"AT",
    "sg:address":"Flachenauergutstrasse 4",
    "sg:city":"Linz",
    "sg:classifiers":[
        {
            "category":"Wholesale",
            "subcategory":"Vending Machines",
            "type":"Manufacturing & Wholesale Goods"
        }
    ],
    "sg:phone":"+43 732 784389",
    "sg:postcode":"4020",
    "sg:province":"Ober\u00f6sterreich",
    "sg:tags":[
        "box",
        "container",
        "cleaning",
        "device",
        "washing",
        "machines"
    ],
    "sg:website":"guem-kaercher.com",
    "wof:name":"K\u00c4RCHER - GUEM GMBH falch bis 2000 bar KEW - Service",
    "wof:placetype":"venue"
},
  "geometry": {"coordinates":[14.3207187653,48.3040237427],"type":"Point"}
}