{
  "type": "Feature",
  "properties": {
    "iso:country":"AT",
    "sg:address":"Rupertistr 90",
    "sg:city":"Hart",
    "sg:orig_category":"Feuerwehren",
    "sg:phone":"+43 316 429259",
    "sg:postcode":"8075",
    "sg:province":"Steiermark",
    "wof:name":"Freiwillige Feuerwehr Hart bei Graz",
    "wof:placetype":"venue"
},
  "geometry": {"coordinates":[15.5143547058,47.0669364929],"type":"Point"}
}