{
  "type": "Feature",
  "properties": {
    "addr:full":"Schmidh\u00fcttenstrasse 5  Krems an der Donau Nieder\u00f6sterreich 3500",
    "addr:housenumber":"5",
    "addr:postcode":"3500",
    "addr:street":"Schmidhuettenstrasse",
    "iso:country":"AT",
    "sg:address":"Schmidh\u00fcttenstrasse 5 ",
    "sg:city":"Krems an der Donau",
    "sg:classifiers":[
        {
            "category":"Landmark",
            "subcategory":"City Walls",
            "type":"Public Place"
        }
    ],
    "sg:phone":"+43 2732 8850",
    "sg:postcode":"3500",
    "sg:province":"Nieder\u00f6sterreich",
    "sg:tags":[
        "steel",
        "section",
        "hollow"
    ],
    "sg:website":"www.voestalpine.com/profilform",
    "wof:name":"voestalpine KREMS GmbH",
    "wof:placetype":"venue"
},
  "geometry": {"coordinates":[15.5965108871,48.4088058472],"type":"Point"}
}