{
  "type": "Feature",
  "properties": {
    "iso:country":"AT",
    "sg:address":"Mariahilfer Str 167",
    "sg:city":"Wien",
    "sg:orig_category":"Friseure U Frisiersalons",
    "sg:phone":"+43 1 8975455",
    "sg:postcode":"1150",
    "sg:province":"Wien",
    "wof:name":"Schernhorst Gert",
    "wof:placetype":"venue"
},
  "geometry": {"coordinates":[16.333820343,48.1929168701],"type":"Point"}
}