{
  "type": "Feature",
  "properties": {
    "iso:country":"AT",
    "sg:address":"Karolineng 19/1",
    "sg:city":"Wien",
    "sg:orig_category":"Physiotherapie",
    "sg:phone":"+43 676 7390970",
    "sg:postcode":"1040",
    "sg:province":"Wien",
    "wof:name":"Spanyi-Tupay Katharina Dipl-PT",
    "wof:placetype":"venue"
},
  "geometry": {"coordinates":[16.3764438629,48.1903915405],"type":"Point"}
}