{
  "type": "Feature",
  "properties": {
    "addr:full":"Taxenbach Salzburg 5660",
    "addr:postcode":"5660",
    "iso:country":"AT",
    "sg:city":"Taxenbach",
    "sg:orig_category":"Feuerwehren",
    "sg:phone":"+43 6543 52170",
    "sg:postcode":"5660",
    "sg:province":"Salzburg",
    "wof:name":"Feuerwehr Taxenbach",
    "wof:placetype":"venue"
},
  "geometry": {"coordinates":[12.9626731873,47.2927436829],"type":"Point"}
}