{
  "type": "Feature",
  "properties": {
    "addr:full":"Bahnhofstr 2 Nenzing Vorarlberg 6710",
    "addr:housenumber":"2",
    "addr:postcode":"6710",
    "addr:street":"Bahnhofstr",
    "iso:country":"AT",
    "sg:address":"Bahnhofstr 2",
    "sg:city":"Nenzing",
    "sg:orig_category":"Handelsagenturen",
    "sg:phone":"+43 5525 624080",
    "sg:postcode":"6710",
    "sg:province":"Vorarlberg",
    "wof:name":"AGT Trading & Consulting",
    "wof:placetype":"venue"
},
  "geometry": {"coordinates":[9.7056760788,47.1842155457],"type":"Point"}
}