{
  "type": "Feature",
  "properties": {
    "addr:full":"Kothm\u00fchle 53 Neuhofen an der Ybbs Nieder\u00f6sterreich 3364",
    "addr:housenumber":"53",
    "addr:postcode":"3364",
    "addr:street":"Kothmuehle",
    "iso:country":"AT",
    "sg:address":"Kothm\u00fchle 53",
    "sg:city":"Neuhofen an der Ybbs",
    "sg:classifiers":[
        {
            "category":"Travel",
            "subcategory":"Travel Agent",
            "type":"Entertainment"
        }
    ],
    "sg:phone":"+43 4374 7552112",
    "sg:postcode":"3364",
    "sg:province":"Nieder\u00f6sterreich",
    "sg:tags":[
        "business"
    ],
    "wof:name":"HOTEL KOTHM\u00dcHLE GMBH",
    "wof:placetype":"venue"
},
  "geometry": {"coordinates":[14.8552942276,48.057926178],"type":"Point"}
}