{
  "type": "Feature",
  "properties": {
    "addr:full":"Pa\u00df-Thurn-Str 8 Kitzb\u00fchel Tirol 6370",
    "addr:housenumber":"8",
    "addr:postcode":"6370",
    "addr:street":"Pass-Thurn-Str;Tirol",
    "iso:country":"AT",
    "sg:address":"Pa\u00df-Thurn-Str 8",
    "sg:city":"Kitzb\u00fchel",
    "sg:orig_category":"\u00c3\u201erzte / F Allgemeinmedizin",
    "sg:phone":"+43 4353 5672326",
    "sg:postcode":"6370",
    "sg:province":"Tirol",
    "wof:name":"Schmid Gertrude Dr",
    "wof:placetype":"venue"
},
  "geometry": {"coordinates":[12.41933918,47.419052124],"type":"Point"}
}