{
  "type": "Feature",
  "properties": {
    "iso:country":"AT",
    "sg:address":"Vogelf\u00e4ngerweg 18",
    "sg:city":"Linz",
    "sg:orig_category":"Fleischhauereien",
    "sg:phone":"+43 732 381298",
    "sg:postcode":"4030",
    "sg:province":"Ober\u00f6sterreich",
    "wof:name":"G\u00fcnth\u00f6r Alois",
    "wof:placetype":"venue"
},
  "geometry": {"coordinates":[14.2885503769,48.2512664795],"type":"Point"}
}