{
  "type": "Feature",
  "properties": {
    "addr:full":"Aldranser Str Lans Tirol 6072",
    "addr:postcode":"6072",
    "addr:street":"Str Lans Tirol",
    "iso:country":"AT",
    "sg:address":"Aldranser Str",
    "sg:city":"Lans",
    "sg:orig_category":"Fleischhauereien",
    "sg:phone":"+43 4351 2377866",
    "sg:postcode":"6072",
    "sg:province":"Tirol",
    "wof:name":"Landmetzgerei Piegger KG",
    "wof:placetype":"venue"
},
  "geometry": {"coordinates":[11.4342079163,47.2389907837],"type":"Point"}
}