{
  "type": "Feature",
  "properties": {
    "iso:country":"AT",
    "sg:address":"Berntalerstrasse 10",
    "sg:city":"Vorchdorf",
    "sg:classifiers":[
        {
            "category":"Building & Trades",
            "subcategory":"Landscaping Services",
            "type":"Services"
        }
    ],
    "sg:phone":"+43 76146282",
    "sg:postcode":"4655",
    "sg:province":"Ober\u00f6sterreich",
    "sg:tags":[
        "horticulture",
        "gardening",
        "landscape"
    ],
    "sg:website":"danner-landschaftsbau.at",
    "wof:name":"Danner KG",
    "wof:placetype":"venue"
},
  "geometry": {"coordinates":[13.9174470901,48.0071487427],"type":"Point"}
}