{
  "type": "Feature",
  "properties": {
    "addr:full":"Bismarckg 8 Weiz Steiermark 8160",
    "addr:housenumber":"8",
    "addr:postcode":"8160",
    "addr:street":"Bismarckg",
    "iso:country":"AT",
    "sg:address":"Bismarckg 8",
    "sg:city":"Weiz",
    "sg:orig_category":"Alarmanlagen U Sicherheitssysteme",
    "sg:phone":"+43 4331 7270560",
    "sg:postcode":"8160",
    "sg:province":"Steiermark",
    "wof:name":"Alarm- und Videotechnik Holler KEG",
    "wof:placetype":"venue"
},
  "geometry": {"coordinates":[15.6244068146,47.2179756165],"type":"Point"}
}