{
  "type": "Feature",
  "properties": {
    "iso:country":"AT",
    "sg:address":"Au 6",
    "sg:city":"Gro\u00dfarl",
    "sg:classifiers":[
        {
            "category":"Taxi",
            "type":"Transportation"
        }
    ],
    "sg:phone":"+43 4366 49062850",
    "sg:postcode":"5611",
    "sg:province":"Salzburg",
    "sg:tags":[
        "personentransporte",
        "u"
    ],
    "wof:name":"Taxi Karl Raab KEG",
    "wof:placetype":"venue"
},
  "geometry": {"coordinates":[-114.0853424072,47.1626281738],"type":"Point"}
}