{
  "type": "Feature",
  "properties": {
    "addr:full":"Hofmannsthalstr 40 Maishofen Salzburg 5751",
    "addr:housenumber":"40",
    "addr:postcode":"5751",
    "addr:street":"Hofmannsthalstr;Salzburg",
    "iso:country":"AT",
    "sg:address":"Hofmannsthalstr 40",
    "sg:city":"Maishofen",
    "sg:orig_category":"Schilder",
    "sg:phone":"+43 6542 701060",
    "sg:postcode":"5751",
    "sg:province":"Salzburg",
    "wof:name":"Stainer Schriften und Siebdruck GmbH & Co KG",
    "wof:placetype":"venue"
},
  "geometry": {"coordinates":[12.7989578247,47.3429374695],"type":"Point"}
}