{
  "type": "Feature",
  "properties": {
    "addr:full":"Weiglstr 8 Pottenbrunn Nieder\u00f6sterreich 3140",
    "addr:housenumber":"8",
    "addr:postcode":"3140",
    "addr:street":"Weiglstr;Niederoesterreich",
    "iso:country":"AT",
    "sg:address":"Weiglstr 8",
    "sg:city":"Pottenbrunn",
    "sg:orig_category":"Hauptschulen",
    "sg:phone":"+43 2742 42416",
    "sg:postcode":"3140",
    "sg:province":"Nieder\u00f6sterreich",
    "wof:name":"Hauptschule",
    "wof:placetype":"venue"
},
  "geometry": {"coordinates":[15.6906280518,48.2379837036],"type":"Point"}
}