{
  "type": "Feature",
  "properties": {
    "addr:full":"Gablenzg 54 Wien Wien 1160",
    "addr:housenumber":"54",
    "addr:postcode":"1160",
    "addr:street":"Gablenzg",
    "iso:country":"AT",
    "sg:address":"Gablenzg 54",
    "sg:city":"Wien",
    "sg:orig_category":"Werbeagenturen",
    "sg:phone":"+43 1 8658170",
    "sg:postcode":"1160",
    "sg:province":"Wien",
    "wof:name":"CIP Crossword & Internet Promotions WerbevermittlungsgmbH",
    "wof:placetype":"venue"
},
  "geometry": {"coordinates":[16.3271331787,48.2051887512],"type":"Point"}
}