{
  "type": "Feature",
  "properties": {
    "addr:full":"Viktor-Franz-Hess-Str 4 Innsbruck Tirol 6020",
    "addr:housenumber":"4",
    "addr:postcode":"6020",
    "addr:street":"Viktor-Franz-Hess-Str;Tirol",
    "iso:country":"AT",
    "sg:address":"Viktor-Franz-Hess-Str 4",
    "sg:city":"Innsbruck",
    "sg:orig_category":"Studentenheime",
    "sg:phone":"+43 4351 2228210",
    "sg:postcode":"6020",
    "sg:province":"Tirol",
    "wof:name":"S\u00fcdtiroler Studentenheim",
    "wof:placetype":"venue"
},
  "geometry": {"coordinates":[11.3460159302,47.2655067444],"type":"Point"}
}