{
  "type": "Feature",
  "properties": {
    "iso:country":"AT",
    "sg:address":"G\u00f6ttelsberg 229",
    "sg:city":"Weiz",
    "sg:classifiers":[
        {
            "category":"Professional",
            "subcategory":"Advertising",
            "type":"Services"
        }
    ],
    "sg:phone":"+43 3172 675530",
    "sg:postcode":"8160",
    "sg:province":"Steiermark",
    "sg:tags":[
        "balloon",
        "child"
    ],
    "sg:website":"ballon-prem.at",
    "wof:name":"PREM BALLONS",
    "wof:placetype":"venue"
},
  "geometry": {"coordinates":[15.6215696335,47.2169532776],"type":"Point"}
}