{
  "type": "Feature",
  "properties": {
    "iso:country":"AT",
    "sg:address":"Robert-Stolz-Str 19",
    "sg:city":"Linz",
    "sg:classifiers":[
        {
            "category":"Professional",
            "subcategory":"Computer Services",
            "type":"Services"
        }
    ],
    "sg:phone":"+43 732 612748",
    "sg:postcode":"4020",
    "sg:province":"Ober\u00f6sterreich",
    "sg:tags":[
        "software"
    ],
    "wof:name":"Lenz Werner Ing",
    "wof:placetype":"venue"
},
  "geometry": {"coordinates":[14.2737045288,48.2861709595],"type":"Point"}
}