{
  "type": "Feature",
  "properties": {
    "iso:country":"AT",
    "sg:address":"Thayag 31",
    "sg:city":"Schwarzenau",
    "sg:orig_category":"Hauskrankenpflege / Heimhilfe",
    "sg:phone":"+43 4328 49224717",
    "sg:postcode":"3900",
    "sg:province":"Nieder\u00f6sterreich",
    "wof:name":"Caritas d Di\u00f6zese St P\u00f6lten Hauskrankenpflege u Heimhilfe",
    "wof:placetype":"venue"
},
  "geometry": {"coordinates":[15.2588233948,48.7432861328],"type":"Point"}
}