{
  "type": "Feature",
  "properties": {
    "addr:full":"Obergro\u00dfau 53 Sinabelkirchen Steiermark 8261",
    "addr:housenumber":"53",
    "addr:postcode":"8261",
    "addr:street":"Obergrossau",
    "iso:country":"AT",
    "sg:address":"Obergro\u00dfau 53",
    "sg:city":"Sinabelkirchen",
    "sg:orig_category":"Leuchtschilder U -Schriften",
    "sg:phone":"+43 4331 182134",
    "sg:postcode":"8261",
    "sg:province":"Steiermark",
    "wof:name":"Rauter Lichtwerbung und Metallbau GmbH",
    "wof:placetype":"venue"
},
  "geometry": {"coordinates":[15.7927932739,47.1007003784],"type":"Point"}
}