{
  "type": "Feature",
  "properties": {
    "addr:full":"Liesinger Flurg. 5 Wien Wien 1230",
    "addr:housenumber":"5",
    "addr:postcode":"1230",
    "addr:street":"Flurg.",
    "iso:country":"AT",
    "sg:address":"Liesinger Flurg. 5",
    "sg:city":"Wien",
    "sg:classifiers":[
        {
            "category":"Wholesale",
            "subcategory":"Drugs",
            "type":"Manufacturing & Wholesale Goods"
        }
    ],
    "sg:phone":"+43 4318 694556",
    "sg:postcode":"1230",
    "sg:province":"Wien",
    "sg:tags":[
        "chemical",
        "pharmaceutical"
    ],
    "wof:name":"WILDENHOFER WASSERTECHNIK GMBH",
    "wof:placetype":"venue"
},
  "geometry": {"coordinates":[16.3057136536,48.1353416443],"type":"Point"}
}