{
  "type": "Feature",
  "properties": {
    "addr:full":"Kalvarienbergg 58 Wien Wien 1170",
    "addr:housenumber":"58",
    "addr:postcode":"1170",
    "addr:street":"Kalvarienbergg",
    "iso:country":"AT",
    "sg:address":"Kalvarienbergg 58",
    "sg:city":"Wien",
    "sg:orig_category":"Modellbau",
    "sg:phone":"+43 1 4029859",
    "sg:postcode":"1170",
    "sg:province":"Wien",
    "wof:name":"Modellbau Paul Vienna",
    "wof:placetype":"venue"
},
  "geometry": {"coordinates":[16.3347854614,48.2218818665],"type":"Point"}
}