{
  "type": "Feature",
  "properties": {
    "iso:country":"AT",
    "sg:address":"Lechnerstr 1",
    "sg:city":"Wien",
    "sg:orig_category":"Zauber- U Jonglierartikel",
    "sg:phone":"+43 664 3379018",
    "sg:postcode":"1030",
    "sg:province":"Wien",
    "wof:name":"Jimmys Magic Shop Inh Jimmy Bix",
    "wof:placetype":"venue"
},
  "geometry": {"coordinates":[16.4079971313,48.1981964111],"type":"Point"}
}