{
  "type": "Feature",
  "properties": {
    "addr:full":"Hilmteichstr 79 Graz Steiermark 8010",
    "addr:housenumber":"79",
    "addr:postcode":"8010",
    "addr:street":"Hilmteichstr",
    "iso:country":"AT",
    "sg:address":"Hilmteichstr 79",
    "sg:city":"Graz",
    "sg:orig_category":"Teppichreinigung U -Reparatur",
    "sg:phone":"+43 316 322264",
    "sg:postcode":"8010",
    "sg:province":"Steiermark",
    "wof:name":"Rugani KG",
    "wof:placetype":"venue"
},
  "geometry": {"coordinates":[15.4595451355,47.0846328735],"type":"Point"}
}