{
  "type": "Feature",
  "properties": {
    "addr:full":"An-der-Lan-Str 18/30 Innsbruck Tirol 6020",
    "addr:housenumber":"18 / 30",
    "addr:postcode":"6020",
    "addr:street":"An-Der-Lan-Str;Tirol",
    "iso:country":"AT",
    "sg:address":"An-der-Lan-Str 18/30",
    "sg:city":"Innsbruck",
    "sg:orig_category":"Astrologie",
    "sg:phone":"+43 4351 2202474",
    "sg:postcode":"6020",
    "sg:province":"Tirol",
    "wof:name":"Limmert Hans Peter Michael - Horoskopversand",
    "wof:placetype":"venue"
},
  "geometry": {"coordinates":[11.4358587265,47.2737693787],"type":"Point"}
}