{
  "type": "Feature",
  "properties": {
    "addr:full":"H\u00f6rnlingerstr 5 Rankweil Vorarlberg 6830",
    "addr:housenumber":"5",
    "addr:postcode":"6830",
    "addr:street":"Hoernlingerstr",
    "iso:country":"AT",
    "sg:address":"H\u00f6rnlingerstr 5",
    "sg:city":"Rankweil",
    "sg:orig_category":"Non-Classified Establishments",
    "sg:phone":"+43 5522 41520",
    "sg:postcode":"6830",
    "sg:province":"Vorarlberg",
    "wof:name":"Katholische Jugend und Jungschar",
    "wof:placetype":"venue"
},
  "geometry": {"coordinates":[9.6392297745,47.2731208801],"type":"Point"}
}