{
  "type": "Feature",
  "properties": {
    "addr:full":"Bahnstr 2 Mattersburg Burgenland 7210",
    "addr:housenumber":"2",
    "addr:postcode":"7210",
    "addr:street":"Bahnstr",
    "iso:country":"AT",
    "sg:address":"Bahnstr 2",
    "sg:city":"Mattersburg",
    "sg:orig_category":"Tischlereien",
    "sg:phone":"+43 2626 628110",
    "sg:postcode":"7210",
    "sg:province":"Burgenland",
    "wof:name":"Hausensteiner GmbH",
    "wof:placetype":"venue"
},
  "geometry": {"coordinates":[16.4172401428,47.7370796204],"type":"Point"}
}