{
  "type": "Feature",
  "properties": {
    "addr:full":"Kranebitter Allee 24 Innsbruck Tirol 6020",
    "addr:housenumber":"24",
    "addr:postcode":"6020",
    "addr:street":"Kranebitter Allee;Tirol",
    "iso:country":"AT",
    "sg:address":"Kranebitter Allee 24",
    "sg:city":"Innsbruck",
    "sg:orig_category":"Partnervermittlung",
    "sg:phone":"+43 664 2348159",
    "sg:postcode":"6020",
    "sg:province":"Tirol",
    "wof:name":"Frohnwieser Ingrid",
    "wof:placetype":"venue"
},
  "geometry": {"coordinates":[11.3671007156,47.2645721436],"type":"Point"}
}