{
  "type": "Feature",
  "properties": {
    "iso:country":"AT",
    "sg:address":"Am Krautgarten 21",
    "sg:city":"Wien",
    "sg:orig_category":"Ingenieurkonsulenten / Zivilingenieure",
    "sg:phone":"+43 1 2826760",
    "sg:postcode":"1220",
    "sg:province":"Wien",
    "wof:name":"Schindler J\u00fcrgen Dipl-Ing",
    "wof:placetype":"venue"
},
  "geometry": {"coordinates":[16.4656505585,48.2343521118],"type":"Point"}
}