{
  "type": "Feature",
  "properties": {
    "addr:full":"Urschendorfer Str St. Egyden am Steinfeld Nieder\u00f6sterreich 2731",
    "addr:postcode":"2731",
    "addr:street":"Str St.",
    "iso:country":"AT",
    "sg:address":"Urschendorfer Str",
    "sg:city":"St. Egyden am Steinfeld",
    "sg:orig_category":"Feuerwehren",
    "sg:phone":"+43 2638 77320",
    "sg:postcode":"2731",
    "sg:province":"Nieder\u00f6sterreich",
    "wof:name":"Freiwillige Feuerwehr Willendorf - D\u00f6rfles",
    "wof:placetype":"venue"
},
  "geometry": {"coordinates":[16.1024875641,47.7818527222],"type":"Point"}
}