{
  "type": "Feature",
  "properties": {
    "addr:full":"Kagraner Pl 39 Wien Wien 1220",
    "addr:housenumber":"39",
    "addr:postcode":"1220",
    "addr:street":"Kagraner Pl",
    "iso:country":"AT",
    "sg:address":"Kagraner Pl 39",
    "sg:city":"Wien",
    "sg:orig_category":"Politische Parteien",
    "sg:phone":"+43 1 2044690",
    "sg:postcode":"1220",
    "sg:province":"Wien",
    "wof:name":"FP\u00f6-Die Freiheitlichen",
    "wof:placetype":"venue"
},
  "geometry": {"coordinates":[16.4478321075,48.2485046387],"type":"Point"}
}