{
  "type": "Feature",
  "properties": {
    "iso:country":"AT",
    "sg:address":"Fleischmarkt 9",
    "sg:city":"Klagenfurt",
    "sg:orig_category":"Drogerien",
    "sg:phone":"+43 463 56539",
    "sg:postcode":"9020",
    "sg:province":"K\u00e4rnten",
    "wof:name":"Sch\u00f6nheit-Gesundheit-Polessnig",
    "wof:placetype":"venue"
},
  "geometry": {"coordinates":[14.3104019165,46.6250228882],"type":"Point"}
}