{
  "type": "Feature",
  "properties": {
    "addr:full":"Gangsteig 14 Bergheim Salzburg 5101",
    "addr:housenumber":"14",
    "addr:postcode":"5101",
    "addr:street":"Gangsteig;Salzburg",
    "iso:country":"AT",
    "sg:address":"Gangsteig 14",
    "sg:city":"Bergheim",
    "sg:classifiers":[
        {
            "category":"Taxi",
            "type":"Transportation"
        }
    ],
    "sg:phone":"+43 662 451738",
    "sg:postcode":"5101",
    "sg:province":"Salzburg",
    "sg:tags":[
        "personentransporte",
        "u"
    ],
    "wof:name":"Valenta Heinz",
    "wof:placetype":"venue"
},
  "geometry": {"coordinates":[13.0276556015,47.8447723389],"type":"Point"}
}