{
  "type": "Feature",
  "properties": {
    "iso:country":"AT",
    "sg:address":"St. P\u00f6ltner Str 4",
    "sg:city":"W\u00fcrmla",
    "sg:orig_category":"Tischlereien",
    "sg:phone":"+43 2275 8230",
    "sg:postcode":"3042",
    "sg:province":"Nieder\u00f6sterreich",
    "wof:name":"Wegerer Karl GesmbH",
    "wof:placetype":"venue"
},
  "geometry": {"coordinates":[15.8594493866,48.2568473816],"type":"Point"}
}