{
  "type": "Feature",
  "properties": {
    "addr:full":"Nr 14 S\u00f6lden Tirol 6450",
    "addr:postcode":"6450",
    "addr:street":"Nr 14 Soelden Tirol",
    "iso:country":"AT",
    "sg:address":"Nr 14",
    "sg:city":"S\u00f6lden",
    "sg:orig_category":"Appartements / Ferienwohnungen",
    "sg:phone":"+43 5254 3617",
    "sg:postcode":"6450",
    "sg:province":"Tirol",
    "wof:name":"Ferienwohnung Beim Holzschnitzer",
    "wof:placetype":"venue"
},
  "geometry": {"coordinates":[11.0096664429,46.9695510864],"type":"Point"}
}