{
  "type": "Feature",
  "properties": {
    "iso:country":"AT",
    "sg:address":"Dr.-Waibel-Str 6",
    "sg:city":"Dornbirn",
    "sg:orig_category":"Galerien",
    "sg:phone":"+43 5572 27791",
    "sg:postcode":"6850",
    "sg:province":"Vorarlberg",
    "wof:name":"Art-House Galerie",
    "wof:placetype":"venue"
},
  "geometry": {"coordinates":[9.7451887131,47.4121856689],"type":"Point"}
}