{
  "type": "Feature",
  "properties": {
    "iso:country":"AT",
    "sg:address":"Untere Hauptstrasse 51",
    "sg:city":"Neusiedl am See",
    "sg:orig_category":"Industrie, Sonstige Industrieunternehmungen",
    "sg:phone":"+43 2167 2667",
    "sg:postcode":"7100",
    "sg:province":"Burgenland",
    "sg:website":"http://www.mens-fashion.at",
    "wof:name":"Gstettner Mens Fashion",
    "wof:placetype":"venue"
},
  "geometry": {"coordinates":[16.8475952148,47.9459877014],"type":"Point"}
}