{
  "type": "Feature",
  "properties": {
    "addr:full":"Erdbergstr 202/14c Wien Wien 1030",
    "addr:housenumber":"202 / 14c",
    "addr:postcode":"1030",
    "iso:country":"AT",
    "sg:address":"Erdbergstr 202/14c",
    "sg:city":"Wien",
    "sg:orig_category":"Steuerberatung",
    "sg:phone":"+43 4317 98277030",
    "sg:postcode":"1030",
    "sg:province":"Wien",
    "sg:website":"kavalirek.co.at",
    "wof:name":"Kavalirek Mag & Orbudabi Dr Wirtschafts- u Steuerberatungspartnerschaft",
    "wof:placetype":"venue"
},
  "geometry": {"coordinates":[16.4153442383,48.1901702881],"type":"Point"}
}