{
  "type": "Feature",
  "properties": {
    "addr:full":"Schotteng Pulkau Nieder\u00f6sterreich 3741",
    "addr:postcode":"3741",
    "addr:street":"Niederoesterreich",
    "iso:country":"AT",
    "sg:address":"Schotteng",
    "sg:city":"Pulkau",
    "sg:orig_category":"Vinotheken",
    "sg:phone":"+43 2946 2957",
    "sg:postcode":"3741",
    "sg:province":"Nieder\u00f6sterreich",
    "wof:name":"Pulkauer Weinkeller - Vinothek b d Heiligen Blut Kirche",
    "wof:placetype":"venue"
},
  "geometry": {"coordinates":[15.8594646454,48.7058944702],"type":"Point"}
}