{
  "type": "Feature",
  "properties": {
    "addr:full":"Triester Str 357-359 Puntigam Steiermark 8055",
    "addr:postcode":"8055",
    "addr:street":"Str 357-359",
    "iso:country":"AT",
    "sg:address":"Triester Str 357-359",
    "sg:city":"Puntigam",
    "sg:orig_category":"Immobilienverwaltungen",
    "sg:phone":"+43 4331 65023619",
    "sg:postcode":"8055",
    "sg:province":"Steiermark",
    "wof:name":"Brau Immobilien GmbH",
    "wof:placetype":"venue"
},
  "geometry": {"coordinates":[15.4321594238,47.0301818848],"type":"Point"}
}