{
  "type": "Feature",
  "properties": {
    "iso:country":"AT",
    "sg:address":"Ferdinand-Porsche-Ring 2a",
    "sg:city":"Wiener Neustadt",
    "sg:orig_category":"Bestattungsunternehmen",
    "sg:phone":"+43 4326 22221930",
    "sg:postcode":"2700",
    "sg:province":"Nieder\u00f6sterreich",
    "wof:name":"Bestattungsanstalt",
    "wof:placetype":"venue"
},
  "geometry": {"coordinates":[16.237985611,47.812877655],"type":"Point"}
}