{
  "type": "Feature",
  "properties": {
    "addr:full":"G\u00f6rtschitztalstr 20 Klagenfurt K\u00e4rnten 9020",
    "addr:housenumber":"20",
    "addr:postcode":"9020",
    "addr:street":"Goertschitztalstr;Kaernten",
    "iso:country":"AT",
    "sg:address":"G\u00f6rtschitztalstr 20",
    "sg:city":"Klagenfurt",
    "sg:orig_category":"Tankstellen",
    "sg:phone":"+43 463 723520",
    "sg:postcode":"9020",
    "sg:province":"K\u00e4rnten",
    "wof:name":"JET Tankstelle",
    "wof:placetype":"venue"
},
  "geometry": {"coordinates":[14.3701791763,46.6348762512],"type":"Point"}
}