{
  "type": "Feature",
  "properties": {
    "addr:full":"Nr 61 Altenhof am Hausruck Ober\u00f6sterreich 4674",
    "addr:postcode":"4674",
    "addr:street":"Nr;Altenhof",
    "iso:country":"AT",
    "sg:address":"Nr 61",
    "sg:city":"Altenhof am Hausruck",
    "sg:orig_category":"Volksschulen",
    "sg:phone":"+43 4377 357013",
    "sg:postcode":"4674",
    "sg:province":"Ober\u00f6sterreich",
    "wof:name":"Volksschule",
    "wof:placetype":"venue"
},
  "geometry": {"coordinates":[13.6869459152,48.1363449097],"type":"Point"}
}