{
  "type": "Feature",
  "properties": {
    "iso:country":"AT",
    "sg:address":"Grabnerstr 25",
    "sg:city":"Linz",
    "sg:orig_category":"Architekten",
    "sg:phone":"+43 732 603991",
    "sg:postcode":"4020",
    "sg:province":"Ober\u00f6sterreich",
    "wof:name":"Lepschi Christa Dipl-Ing",
    "wof:placetype":"venue"
},
  "geometry": {"coordinates":[14.2753181458,48.2833900452],"type":"Point"}
}