{
  "type": "Feature",
  "properties": {
    "addr:full":"Landstrasse 13 N\u00fcziders Vorarlberg 6714",
    "addr:housenumber":"13",
    "addr:postcode":"6714",
    "addr:street":"Landstrasse",
    "iso:country":"AT",
    "sg:address":"Landstrasse 13",
    "sg:city":"N\u00fcziders",
    "sg:classifiers":[
        {
            "category":"Home & Garden",
            "subcategory":"Building Materials",
            "type":"Retail Goods"
        }
    ],
    "sg:phone":"+43 5552 63154",
    "sg:postcode":"6714",
    "sg:province":"Vorarlberg",
    "sg:tags":[
        "installation",
        "electric"
    ],
    "wof:name":"Norbert Steiner Elektrounternehmen",
    "wof:placetype":"venue"
},
  "geometry": {"coordinates":[9.7902326584,47.1697921753],"type":"Point"}
}