{
  "type": "Feature",
  "properties": {
    "addr:full":"Wildenstein 9 Gallizien K\u00e4rnten 9132",
    "addr:housenumber":"9",
    "addr:postcode":"9132",
    "addr:street":"Wildenstein;Kaernten",
    "iso:country":"AT",
    "sg:address":"Wildenstein 9",
    "sg:city":"Gallizien",
    "sg:classifiers":[
        {
            "category":"Building & Trades",
            "subcategory":"Landscaping Services",
            "type":"Services"
        }
    ],
    "sg:phone":"+43 4221 2225",
    "sg:postcode":"9132",
    "sg:province":"K\u00e4rnten",
    "sg:tags":[
        "equipment",
        "beekeeping"
    ],
    "sg:website":"sewol.at",
    "wof:name":"Sewol Bienenbeuten Holzindustrie Ges.m.b.H.",
    "wof:placetype":"venue"
},
  "geometry": {"coordinates":[14.5112400055,46.5487709045],"type":"Point"}
}