{
  "type": "Feature",
  "properties": {
    "addr:full":"Gumpendorfer Strasse 56 Wien Wien 1060",
    "addr:housenumber":"56",
    "addr:postcode":"1060",
    "addr:street":"Gumpendorfer Strasse",
    "iso:country":"AT",
    "sg:address":"Gumpendorfer Strasse 56",
    "sg:city":"Wien",
    "sg:classifiers":[
        {
            "category":"Personal",
            "subcategory":"Hair Removal",
            "type":"Services"
        }
    ],
    "sg:phone":"+43 1 5861343",
    "sg:postcode":"1060",
    "sg:province":"Wien",
    "sg:tags":[
        "finishing",
        "fur"
    ],
    "sg:website":"mossboek.at",
    "wof:name":"Ferry Mossboek",
    "wof:placetype":"venue"
},
  "geometry": {"coordinates":[16.3516635895,48.1965675354],"type":"Point"}
}