{
  "type": "Feature",
  "properties": {
    "iso:country":"AT",
    "sg:address":"Zensweg Sonnenrain 16",
    "sg:city":"St. Veit an der Glan",
    "sg:orig_category":"Garten- U Landschaftsgestaltung",
    "sg:phone":"+43 4342 125198",
    "sg:postcode":"9300",
    "sg:province":"K\u00e4rnten",
    "wof:name":"WBZ Gartengestaltung - Dachbegr\u00fcnung - Schwimmteiche",
    "wof:placetype":"venue"
},
  "geometry": {"coordinates":[14.3570547104,46.770778656],"type":"Point"}
}