{
  "type": "Feature",
  "properties": {
    "iso:country":"AT",
    "sg:address":"K\u00e4rntner Ring 1+3",
    "sg:city":"Wien",
    "sg:orig_category":"Banken U Sparkassen",
    "sg:phone":"+43 5 050547150",
    "sg:postcode":"1010",
    "sg:province":"Wien",
    "wof:name":"Bank Austria Creditanstalt AG",
    "wof:placetype":"venue"
},
  "geometry": {"coordinates":[16.3701992035,48.2024230957],"type":"Point"}
}