{
  "type": "Feature",
  "properties": {
    "addr:full":"Jakob-Hannibal-Str 5 Hohenems Vorarlberg 6845",
    "addr:housenumber":"5",
    "addr:postcode":"6845",
    "addr:street":"Jakob-Hannibal-Str",
    "iso:country":"AT",
    "sg:address":"Jakob-Hannibal-Str 5",
    "sg:city":"Hohenems",
    "sg:orig_category":"Transportunternehmen",
    "sg:phone":"+43 4355 7672364",
    "sg:postcode":"6845",
    "sg:province":"Vorarlberg",
    "wof:name":"Marinelli A Transport GesmbH & Co KG",
    "wof:placetype":"venue"
},
  "geometry": {"coordinates":[9.686589241,47.3643112183],"type":"Point"}
}