{
  "type": "Feature",
  "properties": {
    "addr:full":"Satoristr 4 Gmunden Ober\u00f6sterreich 4810",
    "addr:housenumber":"4",
    "addr:postcode":"4810",
    "addr:street":"Satoristr;Oberoesterreich",
    "iso:country":"AT",
    "sg:address":"Satoristr 4",
    "sg:city":"Gmunden",
    "sg:orig_category":"Versicherungsunternehmen",
    "sg:phone":"+43 7612679520",
    "sg:postcode":"4810",
    "sg:province":"Ober\u00f6sterreich",
    "wof:name":"Interunfall Versicherung AG",
    "wof:placetype":"venue"
},
  "geometry": {"coordinates":[13.7981462479,47.918598175],"type":"Point"}
}