{
  "type": "Feature",
  "properties": {
    "addr:full":"Wiener Str 21 M\u00fcrzzuschlag Steiermark 8680",
    "addr:postcode":"8680",
    "addr:street":"21",
    "iso:country":"AT",
    "sg:address":"Wiener Str 21",
    "sg:city":"M\u00fcrzzuschlag",
    "sg:orig_category":"Damenmoden",
    "sg:phone":"+43 4338 5230901",
    "sg:postcode":"8680",
    "sg:province":"Steiermark",
    "wof:name":"KiK Textilien u Non-Food GesmbH",
    "wof:placetype":"venue"
},
  "geometry": {"coordinates":[16.3542709351,48.159198761],"type":"Point"}
}