{
  "type": "Feature",
  "properties": {
    "addr:full":"Atzgersdorfer Str 1 Wien Wien 1120",
    "addr:housenumber":"1",
    "addr:postcode":"1120",
    "addr:street":"Str",
    "iso:country":"AT",
    "sg:address":"Atzgersdorfer Str 1",
    "sg:city":"Wien",
    "sg:orig_category":"Friseure U Frisiersalons",
    "sg:phone":"+43 1 8048817",
    "sg:postcode":"1120",
    "sg:province":"Wien",
    "wof:name":"Jirsa Margarete Monika",
    "wof:placetype":"venue"
},
  "geometry": {"coordinates":[16.2961559296,48.1690979004],"type":"Point"}
}