{
  "type": "Feature",
  "properties": {
    "addr:full":"August-Jaksch-Str 38 Klagenfurt K\u00e4rnten 9020",
    "addr:housenumber":"38",
    "addr:postcode":"9020",
    "addr:street":"August-Jaksch-Str;Kaernten",
    "iso:country":"AT",
    "sg:address":"August-Jaksch-Str 38",
    "sg:city":"Klagenfurt",
    "sg:orig_category":"Innenarchitekten",
    "sg:phone":"+43 463 570670",
    "sg:postcode":"9020",
    "sg:province":"K\u00e4rnten",
    "wof:name":"Semler Hans-Horst Prof Ing Mag",
    "wof:placetype":"venue"
},
  "geometry": {"coordinates":[14.3001775742,46.6207695007],"type":"Point"}
}