{
  "type": "Feature",
  "properties": {
    "addr:full":"Nr 121 Steinach am Brenner Tirol 6150",
    "addr:postcode":"6150",
    "addr:street":"Nr 121;Tirol",
    "iso:country":"AT",
    "sg:address":"Nr 121",
    "sg:city":"Steinach am Brenner",
    "sg:orig_category":"Tischlereien",
    "sg:phone":"+43 4352 7678009",
    "sg:postcode":"6150",
    "sg:province":"Tirol",
    "wof:name":"Salchner Alois",
    "wof:placetype":"venue"
},
  "geometry": {"coordinates":[11.466711998,47.0918159485],"type":"Point"}
}