{
  "type": "Feature",
  "properties": {
    "addr:full":"Schmidtg 24 Wels Ober\u00f6sterreich 4600",
    "addr:housenumber":"24",
    "addr:postcode":"4600",
    "addr:street":"Schmidtg;Oberoesterreich",
    "iso:country":"AT",
    "sg:address":"Schmidtg 24",
    "sg:city":"Wels",
    "sg:orig_category":"Boutiquen",
    "sg:phone":"+43 7242 60622",
    "sg:postcode":"4600",
    "sg:province":"Ober\u00f6sterreich",
    "wof:name":"Marc O' Polo Shop",
    "wof:placetype":"venue"
},
  "geometry": {"coordinates":[14.0249786377,48.1580467224],"type":"Point"}
}