{
  "type": "Feature",
  "properties": {
    "addr:full":"Sternwartestrasse 16 Wien Wien 1180",
    "addr:housenumber":"16",
    "addr:postcode":"1180",
    "addr:street":"Sternwartestrasse",
    "iso:country":"AT",
    "sg:address":"Sternwartestrasse 16",
    "sg:city":"Wien",
    "sg:classifiers":[
        {
            "category":"Bars & Pubs",
            "subcategory":"Nightclub",
            "type":"Food & Drink"
        }
    ],
    "sg:phone":"+43 1 4784373",
    "sg:postcode":"1180",
    "sg:province":"Wien",
    "sg:tags":[
        "fat",
        "deep",
        "fryer"
    ],
    "wof:name":"Dkfm. Paul Hutterer",
    "wof:placetype":"venue"
},
  "geometry": {"coordinates":[16.3472328186,48.2296295166],"type":"Point"}
}