{
  "type": "Feature",
  "properties": {
    "addr:full":"Landstr 31 Linz Ober\u00f6sterreich 4020",
    "addr:housenumber":"31",
    "addr:postcode":"4020",
    "addr:street":"Landstr",
    "iso:country":"AT",
    "sg:address":"Landstr 31",
    "sg:city":"Linz",
    "sg:orig_category":"Eissalons",
    "sg:phone":"+43 732 7716050",
    "sg:postcode":"4020",
    "sg:province":"Ober\u00f6sterreich",
    "wof:name":"Eisk\u00f6nig Landstra\u00dfe",
    "wof:placetype":"venue"
},
  "geometry": {"coordinates":[14.289978981,48.30210495],"type":"Point"}
}