{
  "type": "Feature",
  "properties": {
    "addr:full":"Beethovenstr 9 Amstetten Nieder\u00f6sterreich 3300",
    "addr:housenumber":"9",
    "addr:postcode":"3300",
    "addr:street":"Beethovenstr;Niederoesterreich",
    "iso:country":"AT",
    "sg:address":"Beethovenstr 9",
    "sg:city":"Amstetten",
    "sg:orig_category":"Handelsagenturen",
    "sg:phone":"+43 7472 646040",
    "sg:postcode":"3300",
    "sg:province":"Nieder\u00f6sterreich",
    "wof:name":"Zika Reinhold",
    "wof:placetype":"venue"
},
  "geometry": {"coordinates":[14.8827934265,48.1253051758],"type":"Point"}
}