{
  "type": "Feature",
  "properties": {
    "addr:full":"Seilerst\u00e4tte 5 Wien Wien 1010",
    "addr:housenumber":"5",
    "addr:postcode":"1010",
    "addr:street":"Seilerstaette",
    "iso:country":"AT",
    "sg:address":"Seilerst\u00e4tte 5",
    "sg:city":"Wien",
    "sg:orig_category":"Diskotheken",
    "sg:phone":"+43 1 5122112",
    "sg:postcode":"1010",
    "sg:province":"Wien",
    "wof:name":"Diskothek Big Apple",
    "wof:placetype":"venue"
},
  "geometry": {"coordinates":[16.3759593964,48.2056617737],"type":"Point"}
}