{
  "type": "Feature",
  "properties": {
    "addr:full":"Erzherzog Karl-Str 169 Wien Wien 1220",
    "addr:housenumber":"169",
    "addr:postcode":"1220",
    "iso:country":"AT",
    "sg:address":"Erzherzog Karl-Str 169",
    "sg:city":"Wien",
    "sg:orig_category":"Politische Parteien",
    "sg:phone":"+43 1 2853090",
    "sg:postcode":"1220",
    "sg:province":"Wien",
    "wof:name":"Sozialdemokratische Partei \u00d6sterreichs Sektion 10",
    "wof:placetype":"venue"
},
  "geometry": {"coordinates":[16.4663486481,48.2253723145],"type":"Point"}
}