{
  "type": "Feature",
  "properties": {
    "addr:full":"Hauptpl 9 Jennersdorf Burgenland 8380",
    "addr:housenumber":"9",
    "addr:postcode":"8380",
    "addr:street":"Hauptpl",
    "iso:country":"AT",
    "sg:address":"Hauptpl 9",
    "sg:city":"Jennersdorf",
    "sg:classifiers":[
        {
            "category":"Restaurant",
            "type":"Food & Drink"
        }
    ],
    "sg:phone":"+43 3329 46560",
    "sg:postcode":"8380",
    "sg:province":"Burgenland",
    "sg:tags":[
        "pizzeria"
    ],
    "wof:name":"Pizza Bella Erg\u00fcl",
    "wof:placetype":"venue"
},
  "geometry": {"coordinates":[16.1401119232,46.9370956421],"type":"Point"}
}