{
  "type": "Feature",
  "properties": {
    "addr:full":"Weigelsdorf 12 Kleinzell im M\u00fchlkreis Ober\u00f6sterreich 4115",
    "addr:housenumber":"12",
    "addr:postcode":"4115",
    "addr:street":"Weigelsdorf;Oberoesterreich",
    "iso:country":"AT",
    "sg:address":"Weigelsdorf 12",
    "sg:city":"Kleinzell im M\u00fchlkreis",
    "sg:classifiers":[
        {
            "category":"Manufacturing",
            "subcategory":"Furniture",
            "type":"Manufacturing & Wholesale Goods"
        }
    ],
    "sg:phone":"+43 7282 5302",
    "sg:postcode":"4115",
    "sg:province":"Ober\u00f6sterreich",
    "sg:tags":[
        "design"
    ],
    "wof:name":"Reinhard Pl\u00f6derl",
    "wof:placetype":"venue"
},
  "geometry": {"coordinates":[13.9926204681,48.4571800232],"type":"Point"}
}