{
  "type": "Feature",
  "properties": {
    "addr:full":"Nr 24 Gro\u00dfpesendorf Steiermark 8211",
    "addr:postcode":"8211",
    "addr:street":"Nr",
    "iso:country":"AT",
    "sg:address":"Nr 24",
    "sg:city":"Gro\u00dfpesendorf",
    "sg:orig_category":"Holzhandel",
    "sg:phone":"+43 4331 132236",
    "sg:postcode":"8211",
    "sg:province":"Steiermark",
    "wof:name":"Gruber Holzhandels-KG",
    "wof:placetype":"venue"
},
  "geometry": {"coordinates":[15.7626972198,47.1513366699],"type":"Point"}
}