{
  "type": "Feature",
  "properties": {
    "addr:full":"Gemeindeweg 1 Mattsee Salzburg 5163",
    "addr:housenumber":"1",
    "addr:postcode":"5163",
    "addr:street":"Gemeindeweg;Salzburg",
    "iso:country":"AT",
    "sg:address":"Gemeindeweg 1",
    "sg:city":"Mattsee",
    "sg:orig_category":"Gemeinden",
    "sg:phone":"+43 6217 78850",
    "sg:postcode":"5163",
    "sg:province":"Salzburg",
    "wof:name":"Marktgemeinde Mattsee",
    "wof:placetype":"venue"
},
  "geometry": {"coordinates":[13.1037683487,47.9695281982],"type":"Point"}
}