{
  "type": "Feature",
  "properties": {
    "addr:full":"Hierzenberger Str 32-34 Mondsee Ober\u00f6sterreich 5310",
    "addr:postcode":"32-34;5310",
    "addr:street":"Str;Oberoesterreich",
    "iso:country":"AT",
    "sg:address":"Hierzenberger Str 32-34",
    "sg:city":"Mondsee",
    "sg:orig_category":"Automatendrehereien, Schrauben, Muttern U Nieten, Drehereien",
    "sg:phone":"+43 6232 35630",
    "sg:postcode":"5310",
    "sg:province":"Ober\u00f6sterreich",
    "sg:website":"www.abw-drehteile.at",
    "wof:name":"ABW Automatendreherei Br\u00fcder Wieser GesmbH",
    "wof:placetype":"venue"
},
  "geometry": {"coordinates":[13.3373260498,47.8546562195],"type":"Point"}
}