{
  "type": "Feature",
  "properties": {
    "addr:full":"Gaisbergstr 1 Salzburg Salzburg 5020",
    "addr:housenumber":"1",
    "addr:postcode":"5020",
    "addr:street":"Gaisbergstr;Salzburg",
    "iso:country":"AT",
    "sg:address":"Gaisbergstr 1",
    "sg:city":"Salzburg",
    "sg:orig_category":"Unternehmensberatung",
    "sg:phone":"+43 662 6577",
    "sg:postcode":"5020",
    "sg:province":"Salzburg",
    "wof:name":"DDI Holding Gesellschaft mbH",
    "wof:placetype":"venue"
},
  "geometry": {"coordinates":[13.0635795593,47.7994308472],"type":"Point"}
}