{
  "type": "Feature",
  "properties": {
    "addr:full":"S\u00e4gag 81 Satteins Vorarlberg 6822",
    "addr:housenumber":"81",
    "addr:postcode":"6822",
    "addr:street":"Saegag",
    "iso:country":"AT",
    "sg:address":"S\u00e4gag 81",
    "sg:city":"Satteins",
    "sg:orig_category":"Innenarchitekten",
    "sg:phone":"+43 4355 248519",
    "sg:postcode":"6822",
    "sg:province":"Vorarlberg",
    "wof:name":"Rauch Augustin",
    "wof:placetype":"venue"
},
  "geometry": {"coordinates":[9.6703987122,47.2251396179],"type":"Point"}
}