{
  "type": "Feature",
  "properties": {
    "addr:full":"Freindorfer Str 21 Ansfelden Ober\u00f6sterreich 4052",
    "addr:postcode":"4052",
    "addr:street":"Str 21",
    "iso:country":"AT",
    "sg:address":"Freindorfer Str 21",
    "sg:city":"Ansfelden",
    "sg:orig_category":"Mikroverfilmungen",
    "sg:phone":"+43 732 3125260",
    "sg:postcode":"4052",
    "sg:province":"Ober\u00f6sterreich",
    "sg:website":"www.emd.co.at",
    "wof:name":"EMD Elektronische und Mikrofilm-Dokumentationssysteme GesmbH",
    "wof:placetype":"venue"
},
  "geometry": {"coordinates":[14.2966899872,48.2299804688],"type":"Point"}
}