{
  "type": "Feature",
  "properties": {
    "addr:full":"Pointnerstrasse 28 Gramastetten Ober\u00f6sterreich 4201",
    "addr:housenumber":"28",
    "addr:postcode":"4201",
    "addr:street":"Pointnerstrasse",
    "iso:country":"AT",
    "sg:address":"Pointnerstrasse 28",
    "sg:city":"Gramastetten",
    "sg:orig_category":"Furniture, General",
    "sg:phone":"+43 7239 5017",
    "sg:postcode":"4201",
    "sg:province":"Ober\u00f6sterreich",
    "wof:name":"Robert Vorhemus",
    "wof:placetype":"venue"
},
  "geometry": {"coordinates":[14.2414693832,48.4108848572],"type":"Point"}
}