{
  "type": "Feature",
  "properties": {
    "addr:full":"Rettensteinweg 13 St. Johann im Pongau Salzburg 5600",
    "addr:housenumber":"13",
    "addr:postcode":"5600",
    "addr:street":"Rettensteinweg;Salzburg",
    "iso:country":"AT",
    "sg:address":"Rettensteinweg 13",
    "sg:city":"St. Johann im Pongau",
    "sg:orig_category":"Bergbahnen",
    "sg:phone":"+43 6412 4613",
    "sg:postcode":"5600",
    "sg:province":"Salzburg",
    "wof:name":"Alpendorf Bergbahnen AG",
    "wof:placetype":"venue"
},
  "geometry": {"coordinates":[13.2078790665,47.3553543091],"type":"Point"}
}