{
  "type": "Feature",
  "properties": {
    "addr:full":"Schulg 1A Innsbruck Tirol 6020",
    "addr:housenumber":"1a",
    "addr:postcode":"6020",
    "addr:street":"Schulg;Tirol",
    "iso:country":"AT",
    "sg:address":"Schulg 1A",
    "sg:city":"Innsbruck",
    "sg:orig_category":"\u00c3\u201erzte / F Allgemeinmedizin",
    "sg:phone":"+43 512 2823830",
    "sg:postcode":"6020",
    "sg:province":"Tirol",
    "wof:name":"B\u00f6ser Manuel Peter Dr",
    "wof:placetype":"venue"
},
  "geometry": {"coordinates":[11.3853750229,47.2718238831],"type":"Point"}
}