{
  "type": "Feature",
  "properties": {
    "iso:country":"AT",
    "sg:address":"Grazer Str 66",
    "sg:city":"Gratkorn",
    "sg:orig_category":"Fleischhauereien",
    "sg:phone":"+43 4331 2422304",
    "sg:postcode":"8101",
    "sg:province":"Steiermark",
    "wof:name":"Herzog Georg",
    "wof:placetype":"venue"
},
  "geometry": {"coordinates":[15.3462324142,47.1274986267],"type":"Point"}
}