{
  "type": "Feature",
  "properties": {
    "iso:country":"AT",
    "sg:address":"Bahnweg 1",
    "sg:city":"Hausmening",
    "sg:orig_category":"Landwirtschaftliche Produkte",
    "sg:phone":"+43 7475 523330",
    "sg:postcode":"3363",
    "sg:province":"Nieder\u00f6sterreich",
    "wof:name":"Wagner Gebr\u00fcder",
    "wof:placetype":"venue"
},
  "geometry": {"coordinates":[14.8151359558,48.0742912292],"type":"Point"}
}