{
  "type": "Feature",
  "properties": {
    "addr:full":"Nr 1 Weiten Nieder\u00f6sterreich 3653",
    "addr:postcode":"3653",
    "addr:street":"Nr;Weiten Niederoesterreich",
    "iso:country":"AT",
    "sg:address":"Nr 1",
    "sg:city":"Weiten",
    "sg:orig_category":"Tankstellen",
    "sg:phone":"+43 2758 8247",
    "sg:postcode":"3653",
    "sg:province":"Nieder\u00f6sterreich",
    "wof:name":"AWI-Diskont",
    "wof:placetype":"venue"
},
  "geometry": {"coordinates":[15.2651672363,48.2922363281],"type":"Point"}
}