{
  "type": "Feature",
  "properties": {
    "addr:full":"Haymong 2 Innsbruck Tirol 6020",
    "addr:housenumber":"2",
    "addr:postcode":"6020",
    "addr:street":"Haymong;Tirol",
    "iso:country":"AT",
    "sg:address":"Haymong 2",
    "sg:city":"Innsbruck",
    "sg:classifiers":[
        {
            "category":"Taxi",
            "type":"Transportation"
        }
    ],
    "sg:phone":"+43 4351 2570558",
    "sg:postcode":"6020",
    "sg:province":"Tirol",
    "sg:tags":[
        "personentransporte",
        "u"
    ],
    "wof:name":"Taxiunternehmen Schubert",
    "wof:placetype":"venue"
},
  "geometry": {"coordinates":[11.4071626663,47.2775230408],"type":"Point"}
}