{
  "type": "Feature",
  "properties": {
    "addr:full":"Glasau 2 Hellmons\u00f6dt Ober\u00f6sterreich 4202",
    "addr:housenumber":"2",
    "addr:postcode":"4202",
    "addr:street":"Glasau;Oberoesterreich",
    "iso:country":"AT",
    "sg:address":"Glasau 2",
    "sg:city":"Hellmons\u00f6dt",
    "sg:orig_category":"Fleischhauereien",
    "sg:phone":"+43 7215 24320",
    "sg:postcode":"4202",
    "sg:province":"Ober\u00f6sterreich",
    "wof:name":"Kitzm\u00fcller Wolfgang",
    "wof:placetype":"venue"
},
  "geometry": {"coordinates":[14.2943572998,48.4311447144],"type":"Point"}
}