{
  "type": "Feature",
  "properties": {
    "addr:full":"Morellenfeldg 19 Graz Steiermark 8010",
    "addr:housenumber":"19",
    "addr:postcode":"8010",
    "addr:street":"Morellenfeldg",
    "iso:country":"AT",
    "sg:address":"Morellenfeldg 19",
    "sg:city":"Graz",
    "sg:orig_category":"Steuerberatung",
    "sg:phone":"+43 316 3650000",
    "sg:postcode":"8010",
    "sg:province":"Steiermark",
    "wof:name":"Pailer Sieglinde Mag",
    "wof:placetype":"venue"
},
  "geometry": {"coordinates":[15.453701973,47.0705528259],"type":"Point"}
}