{
  "type": "Feature",
  "properties": {
    "addr:full":"Nr 14 Bischoffeld Steiermark 8731",
    "addr:postcode":"8731",
    "addr:street":"Nr",
    "iso:country":"AT",
    "sg:address":"Nr 14",
    "sg:city":"Bischoffeld",
    "sg:orig_category":"Volksschulen",
    "sg:phone":"+43 4335 132380",
    "sg:postcode":"8731",
    "sg:province":"Steiermark",
    "wof:name":"Volksschule",
    "wof:placetype":"venue"
},
  "geometry": {"coordinates":[14.6728811264,47.2722930908],"type":"Point"}
}