{
  "type": "Feature",
  "properties": {
    "addr:full":"St Julien-Str 8 Salzburg Salzburg 5020",
    "addr:housenumber":"8",
    "addr:postcode":"5020",
    "addr:street":"Salzburg",
    "iso:country":"AT",
    "sg:address":"St Julien-Str 8",
    "sg:city":"Salzburg",
    "sg:orig_category":"Biologische Produkte",
    "sg:phone":"+43 662 873718",
    "sg:postcode":"5020",
    "sg:province":"Salzburg",
    "wof:name":"Hanf in",
    "wof:placetype":"venue"
},
  "geometry": {"coordinates":[13.0397615433,47.8106689453],"type":"Point"}
}