{
  "type": "Feature",
  "properties": {
    "addr:full":"Christian-Laserer-Strasse 6 Gnigl Salzburg 5023",
    "addr:housenumber":"6",
    "addr:postcode":"5023",
    "addr:street":"Christian-Laserer-Strasse",
    "iso:country":"AT",
    "sg:address":"Christian-Laserer-Strasse 6",
    "sg:city":"Gnigl",
    "sg:classifiers":[
        {
            "category":"Professional",
            "subcategory":"Computer Services",
            "type":"Services"
        }
    ],
    "sg:phone":"+43 662 645641",
    "sg:postcode":"5023",
    "sg:province":"Salzburg",
    "sg:tags":[
        "development",
        "software"
    ],
    "sg:website":"hycom-data.at",
    "wof:name":"Hycom Data B\u00e4rbel Maureder",
    "wof:placetype":"venue"
},
  "geometry": {"coordinates":[13.067530632,47.8141403198],"type":"Point"}
}