{
  "type": "Feature",
  "properties": {
    "addr:full":"Merang 48 Graz Steiermark 8010",
    "addr:housenumber":"48",
    "addr:postcode":"8010",
    "addr:street":"Merang",
    "iso:country":"AT",
    "sg:address":"Merang 48",
    "sg:city":"Graz",
    "sg:orig_category":"Weiterbildungsinstitute M Allg U Berufl Bildungsangebot",
    "sg:phone":"+43 316 3712320",
    "sg:postcode":"8010",
    "sg:province":"Steiermark",
    "wof:name":"Akademie f Neue Berufe",
    "wof:placetype":"venue"
},
  "geometry": {"coordinates":[15.455573082,47.0722007751],"type":"Point"}
}