{
  "type": "Feature",
  "properties": {
    "addr:full":"Wiener Str 19 Oberwart Burgenland 7400",
    "addr:postcode":"7400",
    "iso:country":"AT",
    "sg:address":"Wiener Str 19",
    "sg:city":"Oberwart",
    "sg:orig_category":"Fleischhauereien",
    "sg:phone":"+43 3352 32318",
    "sg:postcode":"7400",
    "sg:province":"Burgenland",
    "wof:name":"Hatwagner GmbH",
    "wof:placetype":"venue"
},
  "geometry": {"coordinates":[16.2083492279,47.2901954651],"type":"Point"}
}