{
  "type": "Feature",
  "properties": {
    "addr:full":"Inprugg 49 Neulengbach Nieder\u00f6sterreich 3040",
    "addr:housenumber":"49",
    "addr:postcode":"3040",
    "addr:street":"Inprugg",
    "iso:country":"AT",
    "sg:address":"Inprugg 49",
    "sg:city":"Neulengbach",
    "sg:orig_category":"Maler, Anstreicher U Lackierer",
    "sg:phone":"+43 2772 52372",
    "sg:postcode":"3040",
    "sg:province":"Nieder\u00f6sterreich",
    "wof:name":"Lirsch Ernst",
    "wof:placetype":"venue"
},
  "geometry": {"coordinates":[15.9116754532,48.2122955322],"type":"Point"}
}