{
  "type": "Feature",
  "properties": {
    "addr:full":"Sch\u00fcttererweg 502 Bad St. Leonhard im Lavanttal K\u00e4rnten 9462",
    "addr:housenumber":"502",
    "addr:postcode":"9462",
    "iso:country":"AT",
    "sg:address":"Sch\u00fcttererweg 502",
    "sg:city":"Bad St. Leonhard im Lavanttal",
    "sg:classifiers":[
        {
            "category":"Building & Trades",
            "subcategory":"Construction",
            "type":"Services"
        }
    ],
    "sg:phone":"+43 664 5960075",
    "sg:postcode":"9462",
    "sg:province":"K\u00e4rnten",
    "sg:tags":[
        "installation",
        "air-conditioning",
        "system"
    ],
    "wof:name":"CST Sturmer Catering OEG",
    "wof:placetype":"venue"
},
  "geometry": {"coordinates":[14.7903852463,46.9638404846],"type":"Point"}
}