{
  "type": "Feature",
  "properties": {
    "addr:full":"Waidhofner Str. 144 Amstetten Nieder\u00f6sterreich 3300",
    "addr:housenumber":"144",
    "addr:postcode":"3300",
    "addr:street":"Str.;Niederoesterreich",
    "iso:country":"AT",
    "sg:address":"Waidhofner Str. 144",
    "sg:city":"Amstetten",
    "sg:classifiers":[
        {
            "category":"Shopping",
            "subcategory":"Computers & Home Electronics",
            "type":"Retail Goods"
        }
    ],
    "sg:phone":"+43 4374 7263026",
    "sg:postcode":"3300",
    "sg:province":"Nieder\u00f6sterreich",
    "sg:tags":[
        "electronic",
        "electrical",
        "equipment"
    ],
    "wof:name":"MEGA BAUMAX GMBH",
    "wof:placetype":"venue"
},
  "geometry": {"coordinates":[14.8549604416,48.1189498901],"type":"Point"}
}