{
  "type": "Feature",
  "properties": {
    "addr:full":"Kohlgrub 914 Egg Vorarlberg 6863",
    "addr:housenumber":"914",
    "addr:postcode":"6863",
    "addr:street":"Kohlgrub",
    "iso:country":"AT",
    "sg:address":"Kohlgrub 914",
    "sg:city":"Egg",
    "sg:orig_category":"Dosieranlagen U -Pumpen",
    "sg:phone":"+43 5512 22400",
    "sg:postcode":"6863",
    "sg:province":"Vorarlberg",
    "wof:name":"Dorner Electronic GmbH",
    "wof:placetype":"venue"
},
  "geometry": {"coordinates":[9.8928661346,47.4280052185],"type":"Point"}
}