{
  "type": "Feature",
  "properties": {
    "addr:full":"Bundesstr 93a Lauterach Vorarlberg 6923",
    "addr:housenumber":"93a",
    "addr:postcode":"6923",
    "addr:street":"Bundesstr",
    "iso:country":"AT",
    "sg:address":"Bundesstr 93a",
    "sg:city":"Lauterach",
    "sg:orig_category":"Registrierkassen",
    "sg:phone":"+43 5574 732930",
    "sg:postcode":"6923",
    "sg:province":"Vorarlberg",
    "wof:name":"Lanner S Registrierkassenservice GmbH",
    "wof:placetype":"venue"
},
  "geometry": {"coordinates":[9.7290220261,47.4713554382],"type":"Point"}
}