{
  "type": "Feature",
  "properties": {
    "addr:full":"Am Spitz 9 Neunkirchen Nieder\u00f6sterreich 2620",
    "addr:housenumber":"9",
    "addr:postcode":"2620",
    "addr:street":"Am Spitz",
    "iso:country":"AT",
    "sg:address":"Am Spitz 9",
    "sg:city":"Neunkirchen",
    "sg:classifiers":[
        {
            "category":"Home & Garden",
            "subcategory":"Hardware",
            "type":"Retail Goods"
        }
    ],
    "sg:phone":"+43 2635 65529",
    "sg:postcode":"2620",
    "sg:province":"Nieder\u00f6sterreich",
    "sg:tags":[
        "bellow"
    ],
    "sg:website":"ceratec.at",
    "wof:name":"CERATEC",
    "wof:placetype":"venue"
},
  "geometry": {"coordinates":[16.0704288483,47.7165374756],"type":"Point"}
}