{
  "type": "Feature",
  "properties": {
    "addr:full":"Auhofstr 70 Wien Wien 1130",
    "addr:housenumber":"70",
    "addr:postcode":"1130",
    "addr:street":"Auhofstr",
    "iso:country":"AT",
    "sg:address":"Auhofstr 70",
    "sg:city":"Wien",
    "sg:orig_category":"Filmproduktionen",
    "sg:phone":"+43 1 87687150",
    "sg:postcode":"1130",
    "sg:province":"Wien",
    "wof:name":"Talk TV Produktionsgesellschaft m.b.H.",
    "wof:placetype":"venue"
},
  "geometry": {"coordinates":[16.2869224548,48.1893959045],"type":"Point"}
}