{
  "type": "Feature",
  "properties": {
    "addr:full":"Esternberg 55 Esternberg Ober\u00f6sterreich 4092",
    "addr:housenumber":"55",
    "addr:postcode":"4092",
    "addr:street":"Esternberg",
    "iso:country":"AT",
    "sg:address":"Esternberg 55",
    "sg:city":"Esternberg",
    "sg:classifiers":[
        {
            "category":"Organizations",
            "subcategory":"Non-profit Organization",
            "type":"Services"
        }
    ],
    "sg:phone":"+43 7714 6142",
    "sg:postcode":"4092",
    "sg:province":"Ober\u00f6sterreich",
    "sg:tags":[
        "alarm",
        "system"
    ],
    "wof:name":"Elektro Stemp Inh. Thomas Haberl",
    "wof:placetype":"venue"
},
  "geometry": {"coordinates":[13.5734796524,48.543510437],"type":"Point"}
}