{
  "type": "Feature",
  "properties": {
    "iso:country":"AT",
    "sg:address":"H\u00f6fer Str 8",
    "sg:city":"Wilhering",
    "sg:orig_category":"Polizei U Gendarmerie",
    "sg:phone":"+43 4359 1334143",
    "sg:postcode":"4073",
    "sg:province":"Ober\u00f6sterreich",
    "wof:name":"Gendarmerie",
    "wof:placetype":"venue"
},
  "geometry": {"coordinates":[14.1859989166,48.3231048584],"type":"Point"}
}