{
  "type": "Feature",
  "properties": {
    "addr:full":"Marktm\u00fchlg. 30 4033",
    "addr:housenumber":"30",
    "addr:postcode":"4033",
    "addr:street":"Marktmuehlg.",
    "iso:country":"AT",
    "sg:address":"Marktm\u00fchlg. 30",
    "sg:classifiers":[
        {
            "category":"Food & Beverages",
            "subcategory":"Bakery",
            "type":"Retail Goods"
        }
    ],
    "sg:phone":"+43 4373 2303060",
    "sg:postcode":"4033",
    "sg:tags":[
        "grain",
        "cereal"
    ],
    "wof:name":"CAJ STROBL GESMBH",
    "wof:placetype":"venue"
},
  "geometry": {"coordinates":[14.3332996368,48.2332992554],"type":"Point"}
}