{
  "type": "Feature",
  "properties": {
    "addr:full":"Marktstr 28 Krumbach Nieder\u00f6sterreich 2851",
    "addr:housenumber":"28",
    "addr:postcode":"2851",
    "addr:street":"Marktstr",
    "iso:country":"AT",
    "sg:address":"Marktstr 28",
    "sg:city":"Krumbach",
    "sg:orig_category":"Friseure U Frisiersalons",
    "sg:phone":"+43 4326 4742330",
    "sg:postcode":"2851",
    "sg:province":"Nieder\u00f6sterreich",
    "wof:name":"Simon Brigitta",
    "wof:placetype":"venue"
},
  "geometry": {"coordinates":[16.1930027008,47.5236206055],"type":"Point"}
}