{
  "type": "Feature",
  "properties": {
    "iso:country":"AT",
    "sg:address":"Gewerbestr 10-12",
    "sg:city":"Radstadt",
    "sg:orig_category":"Bierdepots",
    "sg:phone":"+43 6452 7492",
    "sg:postcode":"5550",
    "sg:province":"Salzburg",
    "wof:name":"Radst\u00e4dter Getr\u00e4nkevertrieb GesmbH",
    "wof:placetype":"venue"
},
  "geometry": {"coordinates":[13.4746112823,47.3851203918],"type":"Point"}
}