{
  "type": "Feature",
  "properties": {
    "addr:full":"Pa\u00df-Thurn-Str 66 Kitzb\u00fchel Tirol 6370",
    "addr:housenumber":"66",
    "addr:postcode":"6370",
    "addr:street":"Pass-Thurn-Str;Tirol",
    "iso:country":"AT",
    "sg:address":"Pa\u00df-Thurn-Str 66",
    "sg:city":"Kitzb\u00fchel",
    "sg:orig_category":"Autoreparatur",
    "sg:phone":"+43 5356 66812",
    "sg:postcode":"6370",
    "sg:province":"Tirol",
    "wof:name":"Teufel Hermann",
    "wof:placetype":"venue"
},
  "geometry": {"coordinates":[12.4259262085,47.405632019],"type":"Point"}
}