{
  "type": "Feature",
  "properties": {
    "addr:full":"Gro\u00dfmarktstrasse 8 Wien Wien 1230",
    "addr:housenumber":"8",
    "addr:postcode":"1230",
    "addr:street":"Grossmarktstrasse",
    "iso:country":"AT",
    "sg:address":"Gro\u00dfmarktstrasse 8",
    "sg:city":"Wien",
    "sg:classifiers":[
        {
            "category":"Banks & Credit Unions",
            "subcategory":"Bureau De Change",
            "type":"Services"
        }
    ],
    "sg:phone":"+43 1 610170",
    "sg:postcode":"1230",
    "sg:province":"Wien",
    "sg:tags":[
        "asbestos",
        "abatement"
    ],
    "sg:website":"belfor.at",
    "wof:name":"Belfor Austria GmbH",
    "wof:placetype":"venue"
},
  "geometry": {"coordinates":[16.3644237518,48.1422958374],"type":"Point"}
}