{
  "type": "Feature",
  "properties": {
    "addr:full":"Nr 240 Miesenbach Nieder\u00f6sterreich 2761",
    "addr:postcode":"2761",
    "addr:street":"Nr 240 Miesenbach",
    "iso:country":"AT",
    "sg:address":"Nr 240",
    "sg:city":"Miesenbach",
    "sg:orig_category":"Banken U Sparkassen",
    "sg:phone":"+43 4326 328261",
    "sg:postcode":"2761",
    "sg:province":"Nieder\u00f6sterreich",
    "wof:name":"Raiffeisenbank Piestingtal regGenmbH",
    "wof:placetype":"venue"
},
  "geometry": {"coordinates":[15.9799060822,47.8700790405],"type":"Point"}
}