{
  "type": "Feature",
  "properties": {
    "addr:full":"Kirchfeldstr 29 Windischgarsten Ober\u00f6sterreich 4580",
    "addr:housenumber":"29",
    "addr:postcode":"4580",
    "addr:street":"Kirchfeldstr",
    "iso:country":"AT",
    "sg:address":"Kirchfeldstr 29",
    "sg:city":"Windischgarsten",
    "sg:orig_category":"Zimmereien",
    "sg:phone":"+43 7562 53060",
    "sg:postcode":"4580",
    "sg:province":"Ober\u00f6sterreich",
    "wof:name":"Kretschmer Roland Ing Baumeister und Zimmermeister GmbH",
    "wof:placetype":"venue"
},
  "geometry": {"coordinates":[14.3257761002,47.7185287476],"type":"Point"}
}