{
  "type": "Feature",
  "properties": {
    "addr:full":"Pyrkerstr 67 Bad Hofgastein Salzburg 5630",
    "addr:housenumber":"67",
    "addr:postcode":"5630",
    "addr:street":"Pyrkerstr;Salzburg",
    "iso:country":"AT",
    "sg:address":"Pyrkerstr 67",
    "sg:city":"Bad Hofgastein",
    "sg:orig_category":"Appartements / Ferienwohnungen",
    "sg:phone":"+43 6432 8695",
    "sg:postcode":"5630",
    "sg:province":"Salzburg",
    "wof:name":"Landhaus Elfriede",
    "wof:placetype":"venue"
},
  "geometry": {"coordinates":[13.1075000763,47.1613960266],"type":"Point"}
}