{
  "type": "Feature",
  "properties": {
    "addr:full":"Mauthausener Str 105 St. Georgen an der Gusen Ober\u00f6sterreich 4222",
    "addr:housenumber":"105",
    "addr:postcode":"4222",
    "iso:country":"AT",
    "sg:address":"Mauthausener Str 105",
    "sg:city":"St. Georgen an der Gusen",
    "sg:orig_category":"Stickereien",
    "sg:phone":"+43 4372 373279",
    "sg:postcode":"4222",
    "sg:province":"Ober\u00f6sterreich",
    "wof:name":"B\u00f6s Herwig",
    "wof:placetype":"venue"
},
  "geometry": {"coordinates":[14.4553089142,48.26304245],"type":"Point"}
}