{
  "type": "Feature",
  "properties": {
    "iso:country":"AT",
    "sg:address":"Nr 53",
    "sg:city":"Raxendorf",
    "sg:orig_category":"Feuerwehren",
    "sg:phone":"+43 2758 7350",
    "sg:postcode":"3654",
    "sg:province":"Nieder\u00f6sterreich",
    "wof:name":"Freiwillige Feuerwehr Raxendorf",
    "wof:placetype":"venue"
},
  "geometry": {"coordinates":[15.2746200562,48.3410186768],"type":"Point"}
}