{
  "type": "Feature",
  "properties": {
    "addr:full":"Kirchenpl 1 Bad Leonfelden Ober\u00f6sterreich 4190",
    "addr:housenumber":"1",
    "addr:postcode":"4190",
    "addr:street":"Kirchenpl",
    "iso:country":"AT",
    "sg:address":"Kirchenpl 1",
    "sg:city":"Bad Leonfelden",
    "sg:orig_category":"Bibliotheken",
    "sg:phone":"+43 7213 20637",
    "sg:postcode":"4190",
    "sg:province":"Ober\u00f6sterreich",
    "wof:name":"Bibliothek",
    "wof:placetype":"venue"
},
  "geometry": {"coordinates":[14.2925195694,48.5228881836],"type":"Point"}
}