{
  "type": "Feature",
  "properties": {
    "addr:full":"Hauptstrasse 6 Wiener Neudorf Nieder\u00f6sterreich 2351",
    "addr:housenumber":"6",
    "addr:postcode":"2351",
    "addr:street":"Hauptstrasse",
    "iso:country":"AT",
    "sg:address":"Hauptstrasse 6",
    "sg:city":"Wiener Neudorf",
    "sg:classifiers":[
        {
            "category":"Home & Garden",
            "subcategory":"Building Materials",
            "type":"Retail Goods"
        }
    ],
    "sg:phone":"+43 2236 61746",
    "sg:postcode":"2351",
    "sg:province":"Nieder\u00f6sterreich",
    "sg:tags":[
        "steel",
        "balcony"
    ],
    "wof:name":"Johann HROCH Ges.m.b.H.",
    "wof:placetype":"venue"
},
  "geometry": {"coordinates":[16.3149757385,48.0866088867],"type":"Point"}
}