{
  "type": "Feature",
  "properties": {
    "addr:full":"Unterer Sonnberg 11 Brixen im Thale Tirol 6364",
    "addr:housenumber":"11",
    "addr:postcode":"6364",
    "addr:street":"Unterer Sonnberg;Tirol",
    "iso:country":"AT",
    "sg:address":"Unterer Sonnberg 11",
    "sg:city":"Brixen im Thale",
    "sg:orig_category":"Pensionen / Privatzimmer",
    "sg:phone":"+43 5334 8858",
    "sg:postcode":"6364",
    "sg:province":"Tirol",
    "wof:name":"Haus Alpenheim",
    "wof:placetype":"venue"
},
  "geometry": {"coordinates":[12.2450609207,47.451335907],"type":"Point"}
}