{
  "type": "Feature",
  "properties": {
    "addr:full":"Nr 74 Knittelfeld Steiermark 8720",
    "addr:postcode":"8720",
    "addr:street":"Nr",
    "iso:country":"AT",
    "sg:address":"Nr 74",
    "sg:city":"Knittelfeld",
    "sg:orig_category":"Banken U Sparkassen",
    "sg:phone":"+43 4335 12830750",
    "sg:postcode":"8720",
    "sg:province":"Steiermark",
    "wof:name":"Raiffeisenbank Knittelfeld regGenmbH",
    "wof:placetype":"venue"
},
  "geometry": {"coordinates":[14.7973117828,47.2074241638],"type":"Point"}
}