{
  "type": "Feature",
  "properties": {
    "iso:country":"AT",
    "sg:address":"Kapelleng 16",
    "sg:city":"Kohfidisch",
    "sg:orig_category":"Elektroinstallationsunternehmen",
    "sg:phone":"+43 3366 76657",
    "sg:postcode":"7512",
    "sg:province":"Burgenland",
    "wof:name":"Faulhammer Gerald",
    "wof:placetype":"venue"
},
  "geometry": {"coordinates":[16.3530006409,47.1624107361],"type":"Point"}
}