{
  "type": "Feature",
  "properties": {
    "addr:full":"Leithen 13 Thalgau Salzburg 5303",
    "addr:housenumber":"13",
    "addr:postcode":"5303",
    "addr:street":"Leithen;Salzburg",
    "iso:country":"AT",
    "sg:address":"Leithen 13",
    "sg:city":"Thalgau",
    "sg:orig_category":"Musikgruppen",
    "sg:phone":"+43 4362 355584",
    "sg:postcode":"5303",
    "sg:province":"Salzburg",
    "wof:name":"Die Radauer",
    "wof:placetype":"venue"
},
  "geometry": {"coordinates":[13.2498407364,47.8356246948],"type":"Point"}
}