{
  "type": "Feature",
  "properties": {
    "addr:full":"Fuhrgasse 2 Gerasdorf Nieder\u00f6sterreich 2201",
    "addr:housenumber":"2",
    "addr:postcode":"2201",
    "addr:street":"Fuhrgasse",
    "iso:country":"AT",
    "sg:address":"Fuhrgasse 2",
    "sg:city":"Gerasdorf",
    "sg:classifiers":[
        {
            "category":"Banks & Credit Unions",
            "subcategory":"Atm",
            "type":"Services"
        }
    ],
    "sg:phone":"+43 2246 4897",
    "sg:postcode":"2201",
    "sg:province":"Nieder\u00f6sterreich",
    "sg:tags":[
        "dispersion",
        "cast"
    ],
    "wof:name":"DECO-C.A.P. Coatings HandelsgmbH",
    "wof:placetype":"venue"
},
  "geometry": {"coordinates":[16.4562244415,48.3326835632],"type":"Point"}
}