{
  "type": "Feature",
  "properties": {
    "addr:full":"Fischerg 33 Wels Ober\u00f6sterreich 4600",
    "addr:housenumber":"33",
    "addr:postcode":"4600",
    "addr:street":"Fischerg;Oberoesterreich",
    "iso:country":"AT",
    "sg:address":"Fischerg 33",
    "sg:city":"Wels",
    "sg:orig_category":"Physiotherapie",
    "sg:phone":"+43 7242 76852",
    "sg:postcode":"4600",
    "sg:province":"Ober\u00f6sterreich",
    "wof:name":"Ecker Marcus Dipl-PT",
    "wof:placetype":"venue"
},
  "geometry": {"coordinates":[14.0303401947,48.1584663391],"type":"Point"}
}