{
  "type": "Feature",
  "properties": {
    "iso:country":"AT",
    "sg:address":"Hauptstr 9A",
    "sg:city":"Trofaiach",
    "sg:orig_category":"Tankstellen",
    "sg:phone":"+43 3847 2879",
    "sg:postcode":"8793",
    "sg:province":"Steiermark",
    "wof:name":"BP Austria Marketing GmbH",
    "wof:placetype":"venue"
},
  "geometry": {"coordinates":[15.0150966644,47.4199562073],"type":"Point"}
}