{
  "type": "Feature",
  "properties": {
    "addr:full":"Unteramt 56 Gresten Nieder\u00f6sterreich 3264",
    "addr:housenumber":"56",
    "addr:postcode":"3264",
    "addr:street":"Unteramt",
    "iso:country":"AT",
    "sg:address":"Unteramt 56",
    "sg:city":"Gresten",
    "sg:orig_category":"Pensionen / Privatzimmer",
    "sg:phone":"+43 7487 2818",
    "sg:postcode":"3264",
    "sg:province":"Nieder\u00f6sterreich",
    "wof:name":"Luger Josef",
    "wof:placetype":"venue"
},
  "geometry": {"coordinates":[15.0202932358,47.9927062988],"type":"Point"}
}