{
  "type": "Feature",
  "properties": {
    "addr:full":"K\u00f6r\u00f6sistr 18 Graz Steiermark 8010",
    "addr:housenumber":"18",
    "addr:postcode":"8010",
    "addr:street":"Koeroesistr",
    "iso:country":"AT",
    "sg:address":"K\u00f6r\u00f6sistr 18",
    "sg:city":"Graz",
    "sg:orig_category":"Architekten",
    "sg:phone":"+43 316 674497",
    "sg:postcode":"8010",
    "sg:province":"Steiermark",
    "wof:name":"Supernett Architects",
    "wof:placetype":"venue"
},
  "geometry": {"coordinates":[15.4431800842,47.0685653687],"type":"Point"}
}