{
  "type": "Feature",
  "properties": {
    "addr:full":"Breitenseer Str 86 Wien Wien 1140",
    "addr:postcode":"1140",
    "addr:street":"Str 86",
    "iso:country":"AT",
    "sg:address":"Breitenseer Str 86",
    "sg:city":"Wien",
    "sg:orig_category":"Textilwaren / Einzelhandel",
    "sg:phone":"+43 1 4198237",
    "sg:postcode":"1140",
    "sg:province":"Wien",
    "wof:name":"B & R TextilhandelsgesmbH",
    "wof:placetype":"venue"
},
  "geometry": {"coordinates":[16.3020915985,48.2025337219],"type":"Point"}
}