{
  "type": "Feature",
  "properties": {
    "addr:full":"Wiedner Hauptstr 61 Wien Wien 1040",
    "addr:housenumber":"61",
    "addr:postcode":"1040",
    "addr:street":"Hauptstr",
    "iso:country":"AT",
    "sg:address":"Wiedner Hauptstr 61",
    "sg:city":"Wien",
    "sg:orig_category":"Immobilienmakler",
    "sg:phone":"+43 4315 057070",
    "sg:postcode":"1040",
    "sg:province":"Wien",
    "wof:name":"Altenburg Realit\u00e4ten GmbH & Co KG",
    "wof:placetype":"venue"
},
  "geometry": {"coordinates":[16.3668041229,48.1905174255],"type":"Point"}
}