{
  "type": "Feature",
  "properties": {
    "addr:full":"Meidlinger Hauptstr 1/11 Wien Wien 1120",
    "addr:housenumber":"1 / 11",
    "addr:postcode":"1120",
    "addr:street":"Meidlinger Hauptstr",
    "iso:country":"AT",
    "sg:address":"Meidlinger Hauptstr 1/11",
    "sg:city":"Wien",
    "sg:orig_category":"Fotografen",
    "sg:phone":"+43 1 8178036",
    "sg:postcode":"1120",
    "sg:province":"Wien",
    "wof:name":"Simak Fritz Dr",
    "wof:placetype":"venue"
},
  "geometry": {"coordinates":[16.3297233582,48.1832580566],"type":"Point"}
}