{
  "type": "Feature",
  "properties": {
    "addr:full":"Untere Hauptstr 30 P\u00f6ggstall Nieder\u00f6sterreich 3650",
    "addr:housenumber":"30",
    "addr:postcode":"3650",
    "addr:street":"Untere Hauptstr;Niederoesterreich",
    "iso:country":"AT",
    "sg:address":"Untere Hauptstr 30",
    "sg:city":"P\u00f6ggstall",
    "sg:orig_category":"Tischlereien",
    "sg:phone":"+43 2758 2463",
    "sg:postcode":"3650",
    "sg:province":"Nieder\u00f6sterreich",
    "wof:name":"Ballwein Gerhard",
    "wof:placetype":"venue"
},
  "geometry": {"coordinates":[-80.3472366333,41.0018386841],"type":"Point"}
}