{
  "type": "Feature",
  "properties": {
    "addr:full":"Nr 40 Gro\u00df Sierning Nieder\u00f6sterreich 3384",
    "addr:postcode":"3384",
    "addr:street":"Nr;Gross;Niederoesterreich",
    "iso:country":"AT",
    "sg:address":"Nr 40",
    "sg:city":"Gro\u00df Sierning",
    "sg:orig_category":"Gemeinden",
    "sg:phone":"+43 4327 4922541",
    "sg:postcode":"3384",
    "sg:province":"Nieder\u00f6sterreich",
    "wof:name":"Gemeindeamt Haunoldstein",
    "wof:placetype":"venue"
},
  "geometry": {"coordinates":[15.4538984299,48.19921875],"type":"Point"}
}