{
  "type": "Feature",
  "properties": {
    "addr:full":"Darnautg 13/5 Wien Wien 1120",
    "addr:housenumber":"13 / 5",
    "addr:postcode":"1120",
    "addr:street":"Darnautg",
    "iso:country":"AT",
    "sg:address":"Darnautg 13/5",
    "sg:city":"Wien",
    "sg:orig_category":"Behinderungen / Leben Mit Behinderungen",
    "sg:phone":"+43 4318 101300",
    "sg:postcode":"1120",
    "sg:province":"Wien",
    "wof:name":"CBM Christoffel Blindenmission Verein z weltweiten Hilfe f Blinde u anders Behinderte",
    "wof:placetype":"venue"
},
  "geometry": {"coordinates":[16.3290939331,48.1824874878],"type":"Point"}
}