{
  "type": "Feature",
  "properties": {
    "addr:full":"Grohg 10 Wien Wien 1050",
    "addr:housenumber":"10",
    "addr:postcode":"1050",
    "addr:street":"Grohg",
    "iso:country":"AT",
    "sg:address":"Grohg 10",
    "sg:city":"Wien",
    "sg:orig_category":"Waren Aller Art",
    "sg:phone":"+43 1 5454794",
    "sg:postcode":"1050",
    "sg:province":"Wien",
    "wof:name":"Danich Manfred",
    "wof:placetype":"venue"
},
  "geometry": {"coordinates":[16.3584918976,48.19165802],"type":"Point"}
}