{
  "type": "Feature",
  "properties": {
    "addr:full":"Gradnerstr 56 Puntigam Steiermark 8055",
    "addr:housenumber":"56",
    "addr:postcode":"8055",
    "addr:street":"Gradnerstr",
    "iso:country":"AT",
    "sg:address":"Gradnerstr 56",
    "sg:city":"Puntigam",
    "sg:orig_category":"Tischlereien",
    "sg:phone":"+43 316 295743",
    "sg:postcode":"8055",
    "sg:province":"Steiermark",
    "wof:name":"Tudor Harald",
    "wof:placetype":"venue"
},
  "geometry": {"coordinates":[15.4217433929,47.0216674805],"type":"Point"}
}