{
  "type": "Feature",
  "properties": {
    "addr:full":"B\u00f6hmerg 6 Freistadt Ober\u00f6sterreich 4240",
    "addr:housenumber":"6",
    "addr:postcode":"4240",
    "addr:street":"Boehmerg",
    "iso:country":"AT",
    "sg:address":"B\u00f6hmerg 6",
    "sg:city":"Freistadt",
    "sg:orig_category":"Fleischhauereien",
    "sg:phone":"+43 7942 72324",
    "sg:postcode":"4240",
    "sg:province":"Ober\u00f6sterreich",
    "wof:name":"Haidler Johann",
    "wof:placetype":"venue"
},
  "geometry": {"coordinates":[14.5049953461,48.5119857788],"type":"Point"}
}