{
  "type": "Feature",
  "properties": {
    "addr:full":"Bl\u00fchnbachstrasse 23  Tenneck Salzburg 5451",
    "addr:housenumber":"23",
    "addr:postcode":"5451",
    "addr:street":"Bluehnbachstrasse;Salzburg",
    "iso:country":"AT",
    "sg:address":"Bl\u00fchnbachstrasse 23 ",
    "sg:city":"Tenneck",
    "sg:classifiers":[
        {
            "category":"Government",
            "subcategory":"Fire Station",
            "type":"Public Place"
        }
    ],
    "sg:phone":"+43 6468 8519",
    "sg:postcode":"5451",
    "sg:province":"Salzburg",
    "sg:tags":[
        "supraregional",
        "plant",
        "installation",
        "heating"
    ],
    "wof:name":"Schider GmbH",
    "wof:placetype":"venue"
},
  "geometry": {"coordinates":[13.1755714417,47.4936599731],"type":"Point"}
}