{
  "type": "Feature",
  "properties": {
    "addr:full":"Bahnhofstr 14 Saalfelden am Steinernen Meer Salzburg 5760",
    "addr:housenumber":"14",
    "addr:postcode":"5760",
    "addr:street":"Bahnhofstr;Salzburg",
    "iso:country":"AT",
    "sg:address":"Bahnhofstr 14",
    "sg:city":"Saalfelden am Steinernen Meer",
    "sg:orig_category":"Damenmoden",
    "sg:phone":"+43 4365 82723690",
    "sg:postcode":"5760",
    "sg:province":"Salzburg",
    "wof:name":"Modehaus Candido GesmbH & Co KG",
    "wof:placetype":"venue"
},
  "geometry": {"coordinates":[12.8442831039,47.4267425537],"type":"Point"}
}