{
  "type": "Feature",
  "properties": {
    "addr:full":"Gewerbestrasse 26 Sattledt Ober\u00f6sterreich 4642",
    "addr:housenumber":"26",
    "addr:postcode":"4642",
    "addr:street":"Gewerbestrasse",
    "iso:country":"AT",
    "sg:address":"Gewerbestrasse 26",
    "sg:city":"Sattledt",
    "sg:orig_category":"Apparatus, Containers, Tanks, Boilers Of Sheet Steel",
    "sg:phone":"+43 7244 86110",
    "sg:postcode":"4642",
    "sg:province":"Ober\u00f6sterreich",
    "wof:name":"Ammer Tank GmbH.",
    "wof:placetype":"venue"
},
  "geometry": {"coordinates":[14.0613698959,48.081199646],"type":"Point"}
}