{
  "type": "Feature",
  "properties": {
    "addr:full":"Hauptplatz 7-9 Pottenstein Nieder\u00f6sterreich 2563",
    "addr:housenumber":"7-9",
    "addr:postcode":"2563",
    "addr:street":"Hauptplatz",
    "iso:country":"AT",
    "sg:address":"Hauptplatz 7-9",
    "sg:city":"Pottenstein",
    "sg:classifiers":[
        {
            "category":"Home & Garden",
            "subcategory":"Building Materials",
            "type":"Retail Goods"
        }
    ],
    "sg:phone":"+43 2672 82405",
    "sg:postcode":"2563",
    "sg:province":"Nieder\u00f6sterreich",
    "sg:tags":[
        "aluminium",
        "gutter"
    ],
    "sg:website":"greil-doleschal.at",
    "wof:name":"Greil & Doleschal Ges.m.b.H.",
    "wof:placetype":"venue"
},
  "geometry": {"coordinates":[16.0967159271,47.9588928223],"type":"Point"}
}