{
  "type": "Feature",
  "properties": {
    "iso:country":"AT",
    "sg:city":"Esternberg",
    "sg:orig_category":"Feuerwehren",
    "sg:phone":"+43 7714 6555",
    "sg:postcode":"4092",
    "sg:province":"Ober\u00f6sterreich",
    "wof:name":"Freiwillige Feuerwehr Pyrawang",
    "wof:placetype":"venue"
},
  "geometry": {"coordinates":[13.6066217422,48.563911438],"type":"Point"}
}