{
  "type": "Feature",
  "properties": {
    "addr:full":"Hardtmuthg 53/2 Wien Wien 1100",
    "addr:housenumber":"53 / 2",
    "addr:postcode":"1100",
    "addr:street":"Hardtmuthg",
    "iso:country":"AT",
    "sg:address":"Hardtmuthg 53/2",
    "sg:city":"Wien",
    "sg:orig_category":"Armaturen / Erzeugung U Gro\u00c3\u0178handel",
    "sg:phone":"+43 1 60214450",
    "sg:postcode":"1100",
    "sg:province":"Wien",
    "wof:name":"Gratz & B\u00f6hm GesmbH",
    "wof:placetype":"venue"
},
  "geometry": {"coordinates":[16.3701572418,48.1701660156],"type":"Point"}
}