{
  "type": "Feature",
  "properties": {
    "addr:full":"Kreuzg 15a Innsbruck Tirol 6020",
    "addr:housenumber":"15a",
    "addr:postcode":"6020",
    "addr:street":"Kreuzg;Tirol",
    "iso:country":"AT",
    "sg:address":"Kreuzg 15a",
    "sg:city":"Innsbruck",
    "sg:orig_category":"Gesundheitsvorsorge",
    "sg:phone":"+43 4365 07537085",
    "sg:postcode":"6020",
    "sg:province":"Tirol",
    "wof:name":"Mayr Vertrieb",
    "wof:placetype":"venue"
},
  "geometry": {"coordinates":[11.4249382019,47.2802658081],"type":"Point"}
}