{
  "type": "Feature",
  "properties": {
    "addr:full":"Fernkorng 95 Wien Wien 1100",
    "addr:housenumber":"95",
    "addr:postcode":"1100",
    "addr:street":"Fernkorng",
    "iso:country":"AT",
    "sg:address":"Fernkorng 95",
    "sg:city":"Wien",
    "sg:orig_category":"Autohandel",
    "sg:phone":"+43 1 60671910",
    "sg:postcode":"1100",
    "sg:province":"Wien",
    "wof:name":"Kroisz Johannes GesmbH",
    "wof:placetype":"venue"
},
  "geometry": {"coordinates":[16.3621826172,48.1677818298],"type":"Point"}
}