{
  "type": "Feature",
  "properties": {
    "iso:country":"AT",
    "sg:address":"Claudiusweg 1",
    "sg:city":"Bregenz",
    "sg:orig_category":"Non-Classified Establishments",
    "sg:phone":"+43 5574 43762",
    "sg:postcode":"6900",
    "sg:province":"Vorarlberg",
    "wof:name":"Evangelische Pfarrgemeinde A und HB - Kreuzkirche am \u00d6lrain",
    "wof:placetype":"venue"
},
  "geometry": {"coordinates":[9.7372608185,47.4966659546],"type":"Point"}
}