{
  "type": "Feature",
  "properties": {
    "iso:country":"AT",
    "sg:address":"Landstra\u00dfer Hauptstr 40",
    "sg:city":"Wien",
    "sg:classifiers":[
        {
            "category":"Travel",
            "subcategory":"Hotels & Motels",
            "type":"Entertainment"
        }
    ],
    "sg:phone":"+43 1 71325680",
    "sg:postcode":"1030",
    "sg:province":"Wien",
    "wof:name":"Tourotel Roter Hahn",
    "wof:placetype":"venue"
},
  "geometry": {"coordinates":[16.3896446228,48.2032241821],"type":"Point"}
}