{
  "type": "Feature",
  "properties": {
    "addr:full":"Panholz 33 Grein Ober\u00f6sterreich 4360",
    "addr:housenumber":"33",
    "addr:postcode":"4360",
    "addr:street":"Panholz",
    "iso:country":"AT",
    "sg:address":"Panholz 33",
    "sg:city":"Grein",
    "sg:orig_category":"Maler, Anstreicher U Lackierer",
    "sg:phone":"+43 7268 474",
    "sg:postcode":"4360",
    "sg:province":"Ober\u00f6sterreich",
    "wof:name":"Lindenhofer August",
    "wof:placetype":"venue"
},
  "geometry": {"coordinates":[14.8751535416,48.233253479],"type":"Point"}
}