{
  "type": "Feature",
  "properties": {
    "iso:country":"AT",
    "sg:address":"Dorfstr 3",
    "sg:city":"Mutters",
    "sg:classifiers":[
        {
            "category":"Restaurant",
            "type":"Food & Drink"
        }
    ],
    "sg:phone":"+43 512 548486",
    "sg:postcode":"6162",
    "sg:province":"Tirol",
    "sg:tags":[
        "pizzeria"
    ],
    "wof:name":"Pizzeria Santa Lucia Gastst\u00e4ttenbetriebs-GesmbH",
    "wof:placetype":"venue"
},
  "geometry": {"coordinates":[11.37550354,47.2274093628],"type":"Point"}
}