{
  "type": "Feature",
  "properties": {
    "iso:country":"AT",
    "sg:address":"Bad Haller Str 19",
    "sg:city":"Kremsm\u00fcnster",
    "sg:orig_category":"Autohandel",
    "sg:phone":"+43 7583 6529",
    "sg:postcode":"4550",
    "sg:province":"Ober\u00f6sterreich",
    "wof:name":"Sch\u00f6llhuber Alexander GmbH",
    "wof:placetype":"venue"
},
  "geometry": {"coordinates":[-83.96160888670001,41.5078353882],"type":"Point"}
}