{
  "type": "Feature",
  "properties": {
    "iso:country":"AT",
    "sg:address":"M\u00fchlh\u00e4user 4",
    "sg:city":"Kohfidisch",
    "sg:orig_category":"Transportunternehmen",
    "sg:phone":"+43 3366 77332",
    "sg:postcode":"7512",
    "sg:province":"Burgenland",
    "wof:name":"Oswald & Gober GesmbH",
    "wof:placetype":"venue"
},
  "geometry": {"coordinates":[16.3575592041,47.1757698059],"type":"Point"}
}