{
  "type": "Feature",
  "properties": {
    "addr:full":"Kreuzner Str 47 Grein Ober\u00f6sterreich 4360",
    "addr:housenumber":"47",
    "addr:postcode":"4360",
    "addr:street":"Str",
    "iso:country":"AT",
    "sg:address":"Kreuzner Str 47",
    "sg:city":"Grein",
    "sg:orig_category":"Elektroinstallationsunternehmen",
    "sg:phone":"+43 7268 7020",
    "sg:postcode":"4360",
    "sg:province":"Ober\u00f6sterreich",
    "wof:name":"G\u00f6bl Elektro GesmbH",
    "wof:placetype":"venue"
},
  "geometry": {"coordinates":[14.8541030884,48.2270126343],"type":"Point"}
}