{
  "type": "Feature",
  "properties": {
    "iso:country":"AT",
    "sg:address":"Franz-von-Defregger-Str 12",
    "sg:city":"Lienz",
    "sg:orig_category":"Installationsunternehmen",
    "sg:phone":"+43 4348 52631900",
    "sg:postcode":"9900",
    "sg:province":"Tirol",
    "wof:name":"Flatscher Erwin Ing GmbH",
    "wof:placetype":"venue"
},
  "geometry": {"coordinates":[12.7609148026,46.8288536072],"type":"Point"}
}