{
  "type": "Feature",
  "properties": {
    "iso:country":"AT",
    "sg:address":"K\u00e4rntner Str 18",
    "sg:city":"Wei\u00dfkirchen in Steiermark",
    "sg:orig_category":"Volksschulen",
    "sg:phone":"+43 4335 7781453",
    "sg:postcode":"8741",
    "sg:province":"Steiermark",
    "wof:name":"Volksschule",
    "wof:placetype":"venue"
},
  "geometry": {"coordinates":[14.7382545471,47.1521835327],"type":"Point"}
}