{
  "type": "Feature",
  "properties": {
    "iso:country":"AT",
    "sg:address":"St Peter Hauptstr 80",
    "sg:city":"St. Peter",
    "sg:classifiers":[
        {
            "category":"Restaurant",
            "type":"Food & Drink"
        }
    ],
    "sg:phone":"+43 316 482838",
    "sg:postcode":"8042",
    "sg:province":"Steiermark",
    "wof:name":"China-Restaurant Konfuzius GmbH",
    "wof:placetype":"venue"
},
  "geometry": {"coordinates":[15.4760608673,47.0526580811],"type":"Point"}
}