{
  "type": "Feature",
  "properties": {
    "addr:full":"Kaiserweg 105 Going am Wilden Kaiser Tirol 6353",
    "addr:housenumber":"105",
    "addr:postcode":"6353",
    "addr:street":"Kaiserweg;Tirol",
    "iso:country":"AT",
    "sg:address":"Kaiserweg 105",
    "sg:city":"Going am Wilden Kaiser",
    "sg:orig_category":"Pensionen / Privatzimmer",
    "sg:phone":"+43 5358 2449",
    "sg:postcode":"6353",
    "sg:province":"Tirol",
    "wof:name":"Pension Anika",
    "wof:placetype":"venue"
},
  "geometry": {"coordinates":[-92.58699035639999,38.1396713257],"type":"Point"}
}