{
  "type": "Feature",
  "properties": {
    "addr:full":"Hauptstrasse 56-58 Ehrwald Tirol 6632",
    "addr:postcode":"56-58;6632",
    "addr:street":"Hauptstrasse;Tirol",
    "iso:country":"AT",
    "sg:address":"Hauptstrasse 56-58",
    "sg:city":"Ehrwald",
    "sg:classifiers":[
        {
            "category":"Banks & Credit Unions",
            "subcategory":"Investment Brokerage",
            "type":"Services"
        }
    ],
    "sg:phone":"+43 5673 2132",
    "sg:postcode":"6632",
    "sg:province":"Tirol",
    "sg:tags":[
        "curtain",
        "rod",
        "accessory"
    ],
    "sg:website":"klotz.at",
    "wof:name":"Raummoden Klotz Ges.m.b.H. & Co KG",
    "wof:placetype":"venue"
},
  "geometry": {"coordinates":[10.9197130203,47.4034042358],"type":"Point"}
}