{
  "type": "Feature",
  "properties": {
    "addr:full":"Jahnstr 8 Hollabrunn Nieder\u00f6sterreich 2020",
    "addr:housenumber":"8",
    "addr:postcode":"2020",
    "addr:street":"Jahnstr",
    "iso:country":"AT",
    "sg:address":"Jahnstr 8",
    "sg:city":"Hollabrunn",
    "sg:orig_category":"Direktmarketing",
    "sg:phone":"+43 4329 5256323",
    "sg:postcode":"2020",
    "sg:province":"Nieder\u00f6sterreich",
    "wof:name":"MBC Manfred Breindl Communications",
    "wof:placetype":"venue"
},
  "geometry": {"coordinates":[16.0843296051,48.5562973022],"type":"Point"}
}