{
  "type": "Feature",
  "properties": {
    "addr:full":"Akazieng 36 Wien Wien 1230",
    "addr:housenumber":"36",
    "addr:postcode":"1230",
    "addr:street":"Akazieng",
    "iso:country":"AT",
    "sg:address":"Akazieng 36",
    "sg:city":"Wien",
    "sg:orig_category":"Armaturen / Erzeugung U Gro\u00c3\u0178handel",
    "sg:phone":"+43 4316 9996000",
    "sg:postcode":"1230",
    "sg:province":"Wien",
    "wof:name":"Brunnbauer-Armaturen ProduktionsgesmbH - Industriearmaturen",
    "wof:placetype":"venue"
},
  "geometry": {"coordinates":[16.3169517517,48.1331481934],"type":"Point"}
}