{
  "type": "Feature",
  "properties": {
    "addr:full":"Rosenweg 11 Eugendorf Salzburg 5301",
    "addr:housenumber":"11",
    "addr:postcode":"5301",
    "addr:street":"Rosenweg;Salzburg",
    "iso:country":"AT",
    "sg:address":"Rosenweg 11",
    "sg:city":"Eugendorf",
    "sg:classifiers":[
        {
            "category":"Professional",
            "subcategory":"Detective & Security Services",
            "type":"Services"
        }
    ],
    "sg:phone":"+43 6225 86360",
    "sg:postcode":"5301",
    "sg:province":"Salzburg",
    "sg:tags":[
        "access",
        "control",
        "ac",
        "system"
    ],
    "sg:website":"dorma.com",
    "wof:name":"Dorma AUSTRIA GmbH",
    "wof:placetype":"venue"
},
  "geometry": {"coordinates":[13.1126804352,47.8544692993],"type":"Point"}
}