{
  "type": "Feature",
  "properties": {
    "iso:country":"AT",
    "sg:address":"Untere Viaduktg 9",
    "sg:city":"Wien",
    "sg:orig_category":"Autoersatzteile",
    "sg:phone":"+43 4317 137430",
    "sg:postcode":"1030",
    "sg:province":"Wien",
    "wof:name":"Kronlachner E. Inh Sascha Hauer",
    "wof:placetype":"venue"
},
  "geometry": {"coordinates":[16.3914718628,48.2111473083],"type":"Point"}
}