{
  "type": "Feature",
  "properties": {
    "addr:full":"August-Jaksch-Strasse 53  Klagenfurt K\u00e4rnten 9020",
    "addr:housenumber":"53",
    "addr:postcode":"9020",
    "addr:street":"August-Jaksch-Strasse;Kaernten",
    "iso:country":"AT",
    "sg:address":"August-Jaksch-Strasse 53 ",
    "sg:city":"Klagenfurt",
    "sg:classifiers":[
        {
            "category":"Banks & Credit Unions",
            "subcategory":"Investment Brokerage",
            "type":"Services"
        }
    ],
    "sg:phone":"+43 463 2613720",
    "sg:postcode":"9020",
    "sg:province":"K\u00e4rnten",
    "sg:tags":[
        "dtp",
        "publishing",
        "exposure",
        "desktop"
    ],
    "sg:website":"www.textdesign.com",
    "wof:name":"TextDesign Ges.m.b.H.",
    "wof:placetype":"venue"
},
  "geometry": {"coordinates":[14.2942342758,46.619972229],"type":"Point"}
}