{
  "type": "Feature",
  "properties": {
    "addr:full":"M\u00fchlg 18 Zirl Tirol 6170",
    "addr:housenumber":"18",
    "addr:postcode":"6170",
    "addr:street":"Muehlg;Tirol",
    "iso:country":"AT",
    "sg:address":"M\u00fchlg 18",
    "sg:city":"Zirl",
    "sg:orig_category":"Spenglereien",
    "sg:phone":"+43 4352 3853355",
    "sg:postcode":"6170",
    "sg:province":"Tirol",
    "wof:name":"Hendl Spenglerei GmbH",
    "wof:placetype":"venue"
},
  "geometry": {"coordinates":[11.2416305542,47.2735519409],"type":"Point"}
}