{
  "type": "Feature",
  "properties": {
    "iso:country":"AT",
    "sg:address":"Nr 84",
    "sg:city":"Wettmannst\u00e4tten",
    "sg:orig_category":"Friseure U Frisiersalons",
    "sg:phone":"+43 4331 852353",
    "sg:postcode":"8521",
    "sg:province":"Steiermark",
    "wof:name":"Friseur-Heimservice - Ambros-Guggermaier Karin",
    "wof:placetype":"venue"
},
  "geometry": {"coordinates":[166.9221496582,-0.5282999873],"type":"Point"}
}