{
  "type": "Feature",
  "properties": {
    "addr:full":"Margeritenstr 4 Alkoven Ober\u00f6sterreich 4072",
    "addr:housenumber":"4",
    "addr:postcode":"4072",
    "addr:street":"Margeritenstr",
    "iso:country":"AT",
    "sg:address":"Margeritenstr 4",
    "sg:city":"Alkoven",
    "sg:orig_category":"Rettungsdienste",
    "sg:phone":"+43 7274 6308",
    "sg:postcode":"4072",
    "sg:province":"Ober\u00f6sterreich",
    "wof:name":"Arbeiter Samariter Bund \u00f6sterreichs Rettungsstelle Alkoven",
    "wof:placetype":"venue"
},
  "geometry": {"coordinates":[14.123708725,48.2903175354],"type":"Point"}
}