{
  "type": "Feature",
  "properties": {
    "iso:country":"AT",
    "sg:address":"Nr 74",
    "sg:city":"Eitweg",
    "sg:orig_category":"Transportunternehmen",
    "sg:phone":"+43 4355 2143",
    "sg:postcode":"9421",
    "sg:province":"K\u00e4rnten",
    "wof:name":"Leopold TransportgesmbH",
    "wof:placetype":"venue"
},
  "geometry": {"coordinates":[14.8929834366,46.7751846313],"type":"Point"}
}