{
  "type": "Feature",
  "properties": {
    "addr:full":"Hauptstr 147a Rekawinkel Nieder\u00f6sterreich 3031",
    "addr:housenumber":"147a",
    "addr:postcode":"3031",
    "addr:street":"Hauptstr",
    "iso:country":"AT",
    "sg:address":"Hauptstr 147a",
    "sg:city":"Rekawinkel",
    "sg:orig_category":"Immobilienverwaltungen",
    "sg:phone":"+43 1 4193100",
    "sg:postcode":"3031",
    "sg:province":"Nieder\u00f6sterreich",
    "wof:name":"B\u00fcro- und BetriebsPark Pressbaum",
    "wof:placetype":"venue"
},
  "geometry": {"coordinates":[16.0241127014,48.1794509888],"type":"Point"}
}