{
  "type": "Feature",
  "properties": {
    "addr:full":"Ebentaler Str 24 Klagenfurt K\u00e4rnten 9020",
    "addr:housenumber":"24",
    "addr:postcode":"9020",
    "addr:street":"Str;Kaernten",
    "iso:country":"AT",
    "sg:address":"Ebentaler Str 24",
    "sg:city":"Klagenfurt",
    "sg:orig_category":"Volksschulen",
    "sg:phone":"+43 463 5375734",
    "sg:postcode":"9020",
    "sg:province":"K\u00e4rnten",
    "wof:name":"Volksschule 24 - Rennerschule",
    "wof:placetype":"venue"
},
  "geometry": {"coordinates":[14.3250494003,46.6234817505],"type":"Point"}
}