{
  "type": "Feature",
  "properties": {
    "iso:country":"AT",
    "sg:address":"Hernalser Hauptstr 122",
    "sg:city":"Wien",
    "sg:orig_category":"Installationsunternehmen",
    "sg:phone":"+43 1 48621490",
    "sg:postcode":"1170",
    "sg:province":"Wien",
    "wof:name":"Greger Rudolf",
    "wof:placetype":"venue"
},
  "geometry": {"coordinates":[16.3239154816,48.220790863],"type":"Point"}
}