{
  "type": "Feature",
  "properties": {
    "addr:full":"Johann Klapper-Str St. P\u00f6lten Nieder\u00f6sterreich 3100",
    "addr:postcode":"3100",
    "addr:street":"St.",
    "iso:country":"AT",
    "sg:address":"Johann Klapper-Str",
    "sg:city":"St. P\u00f6lten",
    "sg:orig_category":"Feuerwehren",
    "sg:phone":"+43 2742 251770",
    "sg:postcode":"3100",
    "sg:province":"Nieder\u00f6sterreich",
    "wof:name":"Freiwillige Feuerwehr Stattersdorf",
    "wof:placetype":"venue"
},
  "geometry": {"coordinates":[15.6421861649,48.1836738586],"type":"Point"}
}