{
  "type": "Feature",
  "properties": {
    "addr:full":"Erdbergstr 134 Wien Wien 1030",
    "addr:housenumber":"134",
    "addr:postcode":"1030",
    "iso:country":"AT",
    "sg:address":"Erdbergstr 134",
    "sg:city":"Wien",
    "sg:orig_category":"Boutiquen",
    "sg:phone":"+43 1 7132611",
    "sg:postcode":"1030",
    "sg:province":"Wien",
    "wof:name":"Boutique Tina Inh Martina Kracher-Zugay",
    "wof:placetype":"venue"
},
  "geometry": {"coordinates":[16.4054203033,48.1963882446],"type":"Point"}
}