{
  "type": "Feature",
  "properties": {
    "addr:full":"Hinterbergstr 13 Steyr Ober\u00f6sterreich 4400",
    "addr:housenumber":"13",
    "addr:postcode":"4400",
    "addr:street":"Hinterbergstr;Oberoesterreich",
    "iso:country":"AT",
    "sg:address":"Hinterbergstr 13",
    "sg:city":"Steyr",
    "sg:orig_category":"Telekommunikation",
    "sg:phone":"+43 4372 5271190",
    "sg:postcode":"4400",
    "sg:province":"Ober\u00f6sterreich",
    "wof:name":"ALPINE ENERGIE GmbH & CoKG",
    "wof:placetype":"venue"
},
  "geometry": {"coordinates":[14.4504957199,48.0544815063],"type":"Point"}
}