{
  "type": "Feature",
  "properties": {
    "addr:full":"Rosenauer Str 70 Wels Ober\u00f6sterreich 4600",
    "addr:housenumber":"70",
    "addr:postcode":"4600",
    "addr:street":"Str;Oberoesterreich",
    "iso:country":"AT",
    "sg:address":"Rosenauer Str 70",
    "sg:city":"Wels",
    "sg:orig_category":"Friseure U Frisiersalons",
    "sg:phone":"+43 7242 45152",
    "sg:postcode":"4600",
    "sg:province":"Ober\u00f6sterreich",
    "wof:name":"Humer Walter",
    "wof:placetype":"venue"
},
  "geometry": {"coordinates":[14.0186004639,48.151058197],"type":"Point"}
}