{
  "type": "Feature",
  "properties": {
    "iso:country":"AT",
    "sg:address":"Porzellang 14-16",
    "sg:city":"Wien",
    "sg:orig_category":"Immobilienmakler",
    "sg:phone":"+43 4313 193290",
    "sg:postcode":"1090",
    "sg:province":"Wien",
    "wof:name":"Das Immobilienb\u00fcro Mag Elisabeth Kittl",
    "wof:placetype":"venue"
},
  "geometry": {"coordinates":[16.3618984222,48.2199478149],"type":"Point"}
}