{
  "type": "Feature",
  "properties": {
    "addr:full":"Faschinastr 33 Sonntag Vorarlberg 6731",
    "addr:housenumber":"33",
    "addr:postcode":"6731",
    "addr:street":"Faschinastr",
    "iso:country":"AT",
    "sg:address":"Faschinastr 33",
    "sg:city":"Sonntag",
    "sg:orig_category":"Autohandel",
    "sg:phone":"+43 5554 5266",
    "sg:postcode":"6731",
    "sg:province":"Vorarlberg",
    "wof:name":"Walser-Garage J. Domig",
    "wof:placetype":"venue"
},
  "geometry": {"coordinates":[9.9111471176,47.2455863953],"type":"Point"}
}