{
  "type": "Feature",
  "properties": {
    "addr:full":"Krista 1 Sulz-R\u00f6this Vorarlberg 6832",
    "addr:housenumber":"1",
    "addr:postcode":"6832",
    "addr:street":"Krista",
    "iso:country":"AT",
    "sg:address":"Krista 1",
    "sg:city":"Sulz-R\u00f6this",
    "sg:orig_category":"Handelsagenturen",
    "sg:phone":"+43 5522 43870",
    "sg:postcode":"6832",
    "sg:province":"Vorarlberg",
    "wof:name":"Senkl Franz",
    "wof:placetype":"venue"
},
  "geometry": {"coordinates":[9.6674451828,47.288192749],"type":"Point"}
}