{
  "type": "Feature",
  "properties": {
    "addr:full":"Zieglerg 84 Wien Wien 1070",
    "addr:housenumber":"84",
    "addr:postcode":"1070",
    "addr:street":"Zieglerg",
    "iso:country":"AT",
    "sg:address":"Zieglerg 84",
    "sg:city":"Wien",
    "sg:orig_category":"Holzbearbeitungsmaschinen U -Werkzeuge",
    "sg:phone":"+43 1 5236318",
    "sg:postcode":"1070",
    "sg:province":"Wien",
    "wof:name":"Spindlbauer Josef KG",
    "wof:placetype":"venue"
},
  "geometry": {"coordinates":[16.3450603485,48.2054023743],"type":"Point"}
}