{
  "type": "Feature",
  "properties": {
    "addr:full":"Kirchenring 2 Raggendorf Nieder\u00f6sterreich 2215",
    "addr:housenumber":"2",
    "addr:postcode":"2215",
    "addr:street":"Kirchenring;Niederoesterreich",
    "iso:country":"AT",
    "sg:address":"Kirchenring 2",
    "sg:city":"Raggendorf",
    "sg:orig_category":"Werbeagenturen",
    "sg:phone":"+43 4317 483566",
    "sg:postcode":"2215",
    "sg:province":"Nieder\u00f6sterreich",
    "wof:name":"Kornthal - Werbeagentur David Paul",
    "wof:placetype":"venue"
},
  "geometry": {"coordinates":[16.6556491852,48.3953514099],"type":"Point"}
}