{
  "type": "Feature",
  "properties": {
    "iso:country":"AT",
    "sg:address":"Kirchenring 2",
    "sg:city":"Raggendorf",
    "sg:orig_category":"Werbeagenturen",
    "sg:phone":"+43 4317 483566",
    "sg:postcode":"2215",
    "sg:province":"Nieder\u00f6sterreich",
    "wof:name":"Kornthal - Werbeagentur David Paul",
    "wof:placetype":"venue"
},
  "geometry": {"coordinates":[16.6556491852,48.3953514099],"type":"Point"}
}