{
  "type": "Feature",
  "properties": {
    "addr:full":"Blumauerg 22 Wien Wien 1020",
    "addr:housenumber":"22",
    "addr:postcode":"1020",
    "addr:street":"Blumauerg",
    "iso:country":"AT",
    "sg:address":"Blumauerg 22",
    "sg:city":"Wien",
    "sg:orig_category":"Interessensvertretungen",
    "sg:phone":"+43 1 21652720",
    "sg:postcode":"1020",
    "sg:province":"Wien",
    "wof:name":"KIV Konsequente Interessensvertretung",
    "wof:placetype":"venue"
},
  "geometry": {"coordinates":[16.3852024078,48.2181243896],"type":"Point"}
}