{
  "type": "Feature",
  "properties": {
    "addr:full":"Ludwig-Engel-Strasse 1 Gleink Ober\u00f6sterreich 4407",
    "addr:housenumber":"1",
    "addr:postcode":"4407",
    "addr:street":"Ludwig-Engel-Strasse",
    "iso:country":"AT",
    "sg:address":"Ludwig-Engel-Strasse 1",
    "sg:city":"Gleink",
    "sg:classifiers":[
        {
            "category":"Manufacturing",
            "subcategory":"Tools & Machinery",
            "type":"Manufacturing & Wholesale Goods"
        }
    ],
    "sg:phone":"+43 7262 6200",
    "sg:postcode":"4407",
    "sg:province":"Ober\u00f6sterreich",
    "sg:tags":[
        "device",
        "handling"
    ],
    "sg:website":"engel.info",
    "wof:name":"Engel Austria GmbH, Zweigniederlassung Dietach",
    "wof:placetype":"venue"
},
  "geometry": {"coordinates":[14.4361639023,48.0923080444],"type":"Point"}
}