{
  "type": "Feature",
  "properties": {
    "iso:country":"AT",
    "sg:address":"Tutterstr 411",
    "sg:city":"Schladming",
    "sg:orig_category":"Hauptschulen",
    "sg:phone":"+43 3687 221880",
    "sg:postcode":"8970",
    "sg:province":"Steiermark",
    "wof:name":"Hauptschule 1",
    "wof:placetype":"venue"
},
  "geometry": {"coordinates":[13.6890268326,47.3956336975],"type":"Point"}
}