{
  "type": "Feature",
  "properties": {
    "iso:country":"AT",
    "sg:address":"Wirerquellg 4a",
    "sg:city":"Bad Ischl",
    "sg:orig_category":"Schneidereien",
    "sg:phone":"+43 6132 23359",
    "sg:postcode":"4820",
    "sg:province":"Ober\u00f6sterreich",
    "wof:name":"Hangl Gottlieb",
    "wof:placetype":"venue"
},
  "geometry": {"coordinates":[13.6232786179,47.7094421387],"type":"Point"}
}