{
  "type": "Feature",
  "properties": {
    "addr:full":"Sierninger Str 91A Steyr Ober\u00f6sterreich 4400",
    "addr:postcode":"4400",
    "addr:street":"Str 91A",
    "iso:country":"AT",
    "sg:address":"Sierninger Str 91A",
    "sg:city":"Steyr",
    "sg:orig_category":"Tischlereien",
    "sg:phone":"+43 7252 751580",
    "sg:postcode":"4400",
    "sg:province":"Ober\u00f6sterreich",
    "wof:name":"Siller Herbert",
    "wof:placetype":"venue"
},
  "geometry": {"coordinates":[14.4076442719,48.0440864563],"type":"Point"}
}