{
  "type": "Feature",
  "properties": {
    "addr:full":"Wiener Str 78 Orth an der Donau Nieder\u00f6sterreich 2304",
    "addr:postcode":"2304",
    "iso:country":"AT",
    "sg:address":"Wiener Str 78",
    "sg:city":"Orth an der Donau",
    "sg:classifiers":[
        {
            "category":"Restaurant",
            "type":"Food & Drink"
        }
    ],
    "sg:phone":"+43 2212 2323",
    "sg:postcode":"2304",
    "sg:province":"Nieder\u00f6sterreich",
    "sg:tags":[
        "pizzeria"
    ],
    "wof:name":"Ristorante Pizzeria Treno",
    "wof:placetype":"venue"
},
  "geometry": {"coordinates":[16.7011756897,48.1448936462],"type":"Point"}
}