{
  "type": "Feature",
  "properties": {
    "iso:country":"AT",
    "sg:address":"Lieferinger Hauptstr 102",
    "sg:city":"Salzburg",
    "sg:orig_category":"Fleischhauereien",
    "sg:phone":"+43 4366 2433625",
    "sg:postcode":"5020",
    "sg:province":"Salzburg",
    "wof:name":"KARNERTA GmbH",
    "wof:placetype":"venue"
},
  "geometry": {"coordinates":[13.0093851089,47.8234214783],"type":"Point"}
}