{
  "type": "Feature",
  "properties": {
    "addr:full":"Ing.-August-Kargl-Str 21 Zwentendorf an der Donau Nieder\u00f6sterreich 3435",
    "addr:housenumber":"21",
    "addr:postcode":"3435",
    "addr:street":"Ing.-August-Kargl-Str",
    "iso:country":"AT",
    "sg:address":"Ing.-August-Kargl-Str 21",
    "sg:city":"Zwentendorf an der Donau",
    "sg:orig_category":"Pensionen / Privatzimmer",
    "sg:phone":"+43 4322 772027",
    "sg:postcode":"3435",
    "sg:province":"Nieder\u00f6sterreich",
    "wof:name":"Keiblinger Robert",
    "wof:placetype":"venue"
},
  "geometry": {"coordinates":[15.9081325531,48.3463745117],"type":"Point"}
}