{
  "type": "Feature",
  "properties": {
    "addr:full":"Auhofstr 115/3A Wien Wien 1130",
    "addr:housenumber":"115 / 3a",
    "addr:postcode":"1130",
    "iso:country":"AT",
    "sg:address":"Auhofstr 115/3A",
    "sg:city":"Wien",
    "sg:orig_category":"Lebens- U Sozialberatung",
    "sg:phone":"+43 4318 761615",
    "sg:postcode":"1130",
    "sg:province":"Wien",
    "wof:name":"Suske Eva",
    "wof:placetype":"venue"
},
  "geometry": {"coordinates":[16.2745113373,48.1901855469],"type":"Point"}
}