{
  "type": "Feature",
  "properties": {
    "addr:full":"Rotkreuzg 514 Bernhardsthal Nieder\u00f6sterreich 2275",
    "addr:housenumber":"514",
    "addr:postcode":"2275",
    "addr:street":"Bernhardsthal Niederoesterreich",
    "iso:country":"AT",
    "sg:address":"Rotkreuzg 514",
    "sg:city":"Bernhardsthal",
    "sg:orig_category":"Rettungsdienste",
    "sg:phone":"+43 2557 8844",
    "sg:postcode":"2275",
    "sg:province":"Nieder\u00f6sterreich",
    "wof:name":"Rotes Kreuz \u00f6sterr Ortsstelle Bernhardsthal",
    "wof:placetype":"venue"
},
  "geometry": {"coordinates":[16.8616600037,48.6938667297],"type":"Point"}
}