{
  "type": "Feature",
  "properties": {
    "addr:full":"Josef-Ressel-Str 3 Pasching Ober\u00f6sterreich 4061",
    "addr:housenumber":"3",
    "addr:postcode":"4061",
    "addr:street":"Josef-Ressel-Str;Oberoesterreich",
    "iso:country":"AT",
    "sg:address":"Josef-Ressel-Str 3",
    "sg:city":"Pasching",
    "sg:orig_category":"Tischlereien",
    "sg:phone":"+43 7229 62520",
    "sg:postcode":"4061",
    "sg:province":"Ober\u00f6sterreich",
    "wof:name":"Grimm Manfred",
    "wof:placetype":"venue"
},
  "geometry": {"coordinates":[14.2019853592,48.2585906982],"type":"Point"}
}