{
  "type": "Feature",
  "properties": {
    "iso:country":"AT",
    "sg:address":"Industriestrasse 17",
    "sg:city":"Gro\u00df-Enzersdorf",
    "sg:classifiers":[
        {
            "category":"Manufacturing",
            "subcategory":"Wood Products",
            "type":"Manufacturing & Wholesale Goods"
        }
    ],
    "sg:phone":"+43 2249 7443",
    "sg:postcode":"2301",
    "sg:province":"Nieder\u00f6sterreich",
    "sg:tags":[
        "made",
        "balcony"
    ],
    "wof:name":"Tischlerei A. Gruber GmbH",
    "wof:placetype":"venue"
},
  "geometry": {"coordinates":[16.5734863281,48.191860199],"type":"Point"}
}