{
  "type": "Feature",
  "properties": {
    "addr:full":"Landstr 51 Hard Vorarlberg 6971",
    "addr:housenumber":"51",
    "addr:postcode":"6971",
    "addr:street":"Landstr",
    "iso:country":"AT",
    "sg:address":"Landstr 51",
    "sg:city":"Hard",
    "sg:orig_category":"Geschenkartikel",
    "sg:phone":"+43 4355 7475377",
    "sg:postcode":"6971",
    "sg:province":"Vorarlberg",
    "wof:name":"Bachmann Gro\u00dfhandel",
    "wof:placetype":"venue"
},
  "geometry": {"coordinates":[9.6868057251,47.4840278625],"type":"Point"}
}