{
  "type": "Feature",
  "properties": {
    "addr:full":"Kleinfeld 4 Ebbs Tirol 6341",
    "addr:housenumber":"4",
    "addr:postcode":"6341",
    "addr:street":"Kleinfeld;Tirol",
    "iso:country":"AT",
    "sg:address":"Kleinfeld 4",
    "sg:city":"Ebbs",
    "sg:orig_category":"Installationsunternehmen",
    "sg:phone":"+43 5373 42250",
    "sg:postcode":"6341",
    "sg:province":"Tirol",
    "wof:name":"Anker Josef",
    "wof:placetype":"venue"
},
  "geometry": {"coordinates":[12.2117080688,47.6225662231],"type":"Point"}
}