{
  "type": "Feature",
  "properties": {
    "iso:country":"AT",
    "sg:address":"Gerng 13",
    "sg:city":"Kaltenleutgeben",
    "sg:orig_category":"Unternehmensberatung",
    "sg:phone":"+43 2238 77954",
    "sg:postcode":"2391",
    "sg:province":"Nieder\u00f6sterreich",
    "wof:name":"Karner Helmut Prof",
    "wof:placetype":"venue"
},
  "geometry": {"coordinates":[16.2145824432,48.1225776672],"type":"Point"}
}