{
  "type": "Feature",
  "properties": {
    "iso:country":"AT",
    "sg:address":"Wiener Str. 228",
    "sg:city":"Linz",
    "sg:classifiers":[
        {
            "category":"Professional",
            "subcategory":"Business Services",
            "type":"Services"
        }
    ],
    "sg:phone":"+43 4373 2344023",
    "sg:postcode":"4030",
    "sg:province":"Ober\u00f6sterreich",
    "sg:tags":[
        "advice"
    ],
    "wof:name":"CIV - COMMERZ INDUSTRIEVERTRETUNGEN GESELLSCHAFT M.B.H.",
    "wof:placetype":"venue"
},
  "geometry": {"coordinates":[14.3162403107,48.2685585022],"type":"Point"}
}