{
  "type": "Feature",
  "properties": {
    "iso:country":"AT",
    "sg:address":"Ambros-Rieder-G 23",
    "sg:city":"Perchtoldsdorf",
    "sg:orig_category":"Ingenieurkonsulenten / Zivilingenieure",
    "sg:phone":"+43 4318 654568",
    "sg:postcode":"2380",
    "sg:province":"Nieder\u00f6sterreich",
    "wof:name":"Gayer Franz Dipl-Ing",
    "wof:placetype":"venue"
},
  "geometry": {"coordinates":[16.2670879364,48.1247062683],"type":"Point"}
}