{
  "type": "Feature",
  "properties": {
    "addr:full":"Brixner Str 3/2 Innsbruck Tirol 6020",
    "addr:housenumber":"3 / 2",
    "addr:postcode":"6020",
    "addr:street":"Str;Tirol",
    "iso:country":"AT",
    "sg:address":"Brixner Str 3/2",
    "sg:city":"Innsbruck",
    "sg:orig_category":"Fu\u00c3\u0178pflege U Fu\u00c3\u0178pflegesalons",
    "sg:phone":"+43 4351 2587144",
    "sg:postcode":"6020",
    "sg:province":"Tirol",
    "wof:name":"Scholl Dr Fu\u00dfpflege - Andrea Szendr\u00f6i",
    "wof:placetype":"venue"
},
  "geometry": {"coordinates":[11.3997220993,47.264957428],"type":"Point"}
}