{
  "type": "Feature",
  "properties": {
    "iso:country":"AT",
    "sg:address":"Mitisg 17",
    "sg:city":"Wien",
    "sg:classifiers":[
        {
            "category":"Professional",
            "subcategory":"Computer Services",
            "type":"Services"
        }
    ],
    "sg:phone":"+43 1 5226868",
    "sg:postcode":"1140",
    "sg:province":"Wien",
    "sg:tags":[
        "software"
    ],
    "wof:name":"Neovalis I T Development GmbH",
    "wof:placetype":"venue"
},
  "geometry": {"coordinates":[16.2696990967,48.1994247437],"type":"Point"}
}