{
  "type": "Feature",
  "properties": {
    "iso:country":"AT",
    "sg:address":"Heldendankstr 20",
    "sg:city":"Bregenz",
    "sg:orig_category":"Bodenverlegung",
    "sg:phone":"+43 664 2338435",
    "sg:postcode":"6900",
    "sg:province":"Vorarlberg",
    "wof:name":"Bal GesmbH",
    "wof:placetype":"venue"
},
  "geometry": {"coordinates":[9.7293348312,47.4980735779],"type":"Point"}
}