{
  "type": "Feature",
  "properties": {
    "iso:country":"AT",
    "sg:address":"Marktpl 4",
    "sg:city":"Weyer",
    "sg:orig_category":"Waren Aller Art",
    "sg:phone":"+43 4373 5520583",
    "sg:postcode":"3335",
    "sg:province":"Ober\u00f6sterreich",
    "wof:name":"Weltladen",
    "wof:placetype":"venue"
},
  "geometry": {"coordinates":[14.6641254425,47.8573226929],"type":"Point"}
}