{
  "type": "Feature",
  "properties": {
    "iso:country":"AT",
    "sg:address":"Prager Str 54",
    "sg:city":"Wien",
    "sg:orig_category":"Textilreinigung",
    "sg:phone":"+43 4312 711270",
    "sg:postcode":"1210",
    "sg:province":"Wien",
    "wof:name":"Ihre Textilpflege Klaus",
    "wof:placetype":"venue"
},
  "geometry": {"coordinates":[16.3929138184,48.2671852112],"type":"Point"}
}