{
  "type": "Feature",
  "properties": {
    "iso:country":"AT",
    "sg:address":"Schlaininger Str 4",
    "sg:city":"Oberwart",
    "sg:orig_category":"Umweltschutz",
    "sg:phone":"+43 4333 5235340",
    "sg:postcode":"7400",
    "sg:province":"Burgenland",
    "wof:name":"Putz Karl Dipl Ing Dr - Ziviltechnikerb\u00fcro Dr Putz - ZT KEG - Agrar- u Umwelt\u00f6konomik",
    "wof:placetype":"venue"
},
  "geometry": {"coordinates":[16.2151641846,47.2874908447],"type":"Point"}
}