{
  "type": "Feature",
  "properties": {
    "iso:country":"AT",
    "sg:address":"Landungspl 102",
    "sg:city":"Hallstatt",
    "sg:orig_category":"Friseure U Frisiersalons",
    "sg:phone":"+43 4361 348297",
    "sg:postcode":"4830",
    "sg:province":"Ober\u00f6sterreich",
    "wof:name":"Zauner Ingrid",
    "wof:placetype":"venue"
},
  "geometry": {"coordinates":[13.6492700577,47.5628547668],"type":"Point"}
}