{
  "type": "Feature",
  "properties": {
    "addr:full":"Terassenweg 22 St. Kanzian am Klopeiner See K\u00e4rnten 9122",
    "addr:housenumber":"22",
    "addr:postcode":"9122",
    "addr:street":"Terassenweg;Kaernten",
    "iso:country":"AT",
    "sg:address":"Terassenweg 22",
    "sg:city":"St. Kanzian am Klopeiner See",
    "sg:orig_category":"Pensionen / Privatzimmer",
    "sg:phone":"+43 4342 392410",
    "sg:postcode":"9122",
    "sg:province":"K\u00e4rnten",
    "wof:name":"Pension Puschnig",
    "wof:placetype":"venue"
},
  "geometry": {"coordinates":[14.6016550064,46.6076316833],"type":"Point"}
}