{
  "type": "Feature",
  "properties": {
    "addr:full":"Niederleuthner Str 5 Waidhofen an der Thaya Nieder\u00f6sterreich 3830",
    "addr:housenumber":"5",
    "addr:postcode":"3830",
    "addr:street":"Str",
    "iso:country":"AT",
    "sg:address":"Niederleuthner Str 5",
    "sg:city":"Waidhofen an der Thaya",
    "sg:orig_category":"Optiker",
    "sg:phone":"+43 4328 4252278",
    "sg:postcode":"3830",
    "sg:province":"Nieder\u00f6sterreich",
    "sg:website":"optik-eder.at",
    "wof:name":"Eder Optik",
    "wof:placetype":"venue"
},
  "geometry": {"coordinates":[15.2860746384,48.8143882751],"type":"Point"}
}