{
  "type": "Feature",
  "properties": {
    "addr:full":"Sauerbrunnstr 17 Stainz Steiermark 8510",
    "addr:housenumber":"17",
    "addr:postcode":"8510",
    "addr:street":"Sauerbrunnstr",
    "iso:country":"AT",
    "sg:address":"Sauerbrunnstr 17",
    "sg:city":"Stainz",
    "sg:orig_category":"Werbegestalter",
    "sg:phone":"+43 664 2513525",
    "sg:postcode":"8510",
    "sg:province":"Steiermark",
    "wof:name":"Gestaltung Anita Fuchs Resa Pernthaller OEG",
    "wof:placetype":"venue"
},
  "geometry": {"coordinates":[15.261920929,46.8948402405],"type":"Point"}
}