{
  "type": "Feature",
  "properties": {
    "addr:full":"Daring 1 Ried im Innkreis Ober\u00f6sterreich 4910",
    "addr:housenumber":"1",
    "addr:postcode":"4910",
    "addr:street":"Daring",
    "iso:country":"AT",
    "sg:address":"Daring 1",
    "sg:city":"Ried im Innkreis",
    "sg:classifiers":[
        {
            "category":"Professional",
            "subcategory":"Computer Services",
            "type":"Services"
        }
    ],
    "sg:phone":"+43 7752 85086",
    "sg:postcode":"4910",
    "sg:province":"Ober\u00f6sterreich",
    "sg:tags":[
        "software"
    ],
    "wof:name":"Kohl Thomas Mag",
    "wof:placetype":"venue"
},
  "geometry": {"coordinates":[13.4994344711,48.1676101685],"type":"Point"}
}