{
  "type": "Feature",
  "properties": {
    "addr:full":"Rohrweg 17b Mittelberg Vorarlberg 6993",
    "addr:housenumber":"17b",
    "addr:postcode":"6993",
    "addr:street":"Rohrweg",
    "iso:country":"AT",
    "sg:address":"Rohrweg 17b",
    "sg:city":"Mittelberg",
    "sg:orig_category":"Pensionen / Privatzimmer",
    "sg:phone":"+43 4355 1769910",
    "sg:postcode":"6993",
    "sg:province":"Vorarlberg",
    "wof:name":"Pension Berghaus Mohr",
    "wof:placetype":"venue"
},
  "geometry": {"coordinates":[10.1601552963,47.3371200562],"type":"Point"}
}