{
  "type": "Feature",
  "properties": {
    "addr:full":"Obere Hauptstr 51B Steinberg-D\u00f6rfl Burgenland 7453",
    "addr:housenumber":"51b steinberg-doerfl",
    "addr:postcode":"7453",
    "addr:street":"Obere Hauptstr",
    "iso:country":"AT",
    "sg:address":"Obere Hauptstr 51B",
    "sg:city":"Steinberg-D\u00f6rfl",
    "sg:orig_category":"Werbeagenturen",
    "sg:phone":"+43 2612 42272",
    "sg:postcode":"7453",
    "sg:province":"Burgenland",
    "wof:name":"Werbestudio Oberpullendorf",
    "wof:placetype":"venue"
},
  "geometry": {"coordinates":[16.4869441986,47.4750709534],"type":"Point"}
}