{
  "type": "Feature",
  "properties": {
    "addr:full":"Bahnstr 49a Eisenstadt Burgenland 7000",
    "addr:housenumber":"49a",
    "addr:postcode":"7000",
    "addr:street":"Bahnstr",
    "iso:country":"AT",
    "sg:address":"Bahnstr 49a",
    "sg:city":"Eisenstadt",
    "sg:orig_category":"Hafnereien",
    "sg:phone":"+43 699 12614518",
    "sg:postcode":"7000",
    "sg:province":"Burgenland",
    "wof:name":"Benesch Jan",
    "wof:placetype":"venue"
},
  "geometry": {"coordinates":[16.5280704498,47.8404846191],"type":"Point"}
}