{
  "type": "Feature",
  "properties": {
    "addr:full":"Emsenhuber Str 21 Adlwang Ober\u00f6sterreich 4541",
    "addr:housenumber":"21",
    "addr:postcode":"4541",
    "addr:street":"Str",
    "iso:country":"AT",
    "sg:address":"Emsenhuber Str 21",
    "sg:city":"Adlwang",
    "sg:orig_category":"Tischlereien",
    "sg:phone":"+43 7258 5425",
    "sg:postcode":"4541",
    "sg:province":"Ober\u00f6sterreich",
    "wof:name":"Wieser GesmbH",
    "wof:placetype":"venue"
},
  "geometry": {"coordinates":[14.2390232086,47.9879188538],"type":"Point"}
}