{
  "type": "Feature",
  "properties": {
    "addr:full":"Zentrum 57 Kramsach Tirol 6233",
    "addr:housenumber":"57",
    "addr:postcode":"6233",
    "addr:street":"Zentrum;Tirol",
    "iso:country":"AT",
    "sg:address":"Zentrum 57",
    "sg:city":"Kramsach",
    "sg:orig_category":"Architekten",
    "sg:phone":"+43 5337 62438",
    "sg:postcode":"6233",
    "sg:province":"Tirol",
    "wof:name":"Staic Peter Arch Dipl-Ing",
    "wof:placetype":"venue"
},
  "geometry": {"coordinates":[11.8830766678,47.447479248],"type":"Point"}
}