{
  "type": "Feature",
  "properties": {
    "addr:full":"Gasse 165 Leutasch Tirol 6105",
    "addr:housenumber":"165",
    "addr:postcode":"6105",
    "addr:street":"Gasse;Tirol",
    "iso:country":"AT",
    "sg:address":"Gasse 165",
    "sg:city":"Leutasch",
    "sg:orig_category":"Tabaktrafiken",
    "sg:phone":"+43 5214 6228",
    "sg:postcode":"6105",
    "sg:province":"Tirol",
    "wof:name":"Krug Heidi",
    "wof:placetype":"venue"
},
  "geometry": {"coordinates":[11.1601676941,47.3789863586],"type":"Point"}
}