{
  "type": "Feature",
  "properties": {
    "addr:full":"Wiener Str 255 G\u00f6sting Steiermark 8051",
    "addr:housenumber":"255",
    "addr:postcode":"8051",
    "addr:street":"Goesting Steiermark",
    "iso:country":"AT",
    "sg:address":"Wiener Str 255",
    "sg:city":"G\u00f6sting",
    "sg:orig_category":"Bibliotheken",
    "sg:phone":"+43 316 672330",
    "sg:postcode":"8051",
    "sg:province":"Steiermark",
    "wof:name":"Stadtbibliothek",
    "wof:placetype":"venue"
},
  "geometry": {"coordinates":[-89.5772018433,35.9498329163],"type":"Point"}
}