{
  "type": "Feature",
  "properties": {
    "iso:country":"AT",
    "sg:address":"Gersdorfer Str 2",
    "sg:city":"Stra\u00df in Steiermark",
    "sg:orig_category":"Imkereien",
    "sg:phone":"+43 3453 5452",
    "sg:postcode":"8472",
    "sg:province":"Steiermark",
    "wof:name":"Wagner Otmar",
    "wof:placetype":"venue"
},
  "geometry": {"coordinates":[15.6306190491,46.7250747681],"type":"Point"}
}