{
  "type": "Feature",
  "properties": {
    "iso:country":"AT",
    "sg:address":"Harbach Gewerbegebiet 59",
    "sg:city":"Bad Hofgastein",
    "sg:orig_category":"Elektromotoren / Reparatur U Wicklerei",
    "sg:phone":"+43 4364 322002",
    "sg:postcode":"5630",
    "sg:province":"Salzburg",
    "wof:name":"Elektro Roland Wallner",
    "wof:placetype":"venue"
},
  "geometry": {"coordinates":[13.1028347015,47.1707115173],"type":"Point"}
}