{
  "type": "Feature",
  "properties": {
    "iso:country":"AT",
    "sg:address":"Werk-VI-Str 31",
    "sg:city":"Kapfenberg",
    "sg:orig_category":"Offsetdruckereien",
    "sg:phone":"+43 3862 23862",
    "sg:postcode":"8605",
    "sg:province":"Steiermark",
    "wof:name":"Bachernegg Druckerei GmbH",
    "wof:placetype":"venue"
},
  "geometry": {"coordinates":[15.3177490234,47.4504508972],"type":"Point"}
}