{
  "type": "Feature",
  "properties": {
    "iso:country":"AT",
    "sg:address":"Hauptstr 31",
    "sg:city":"Maria Saal",
    "sg:orig_category":"Landwirtschaftliche Produkte",
    "sg:phone":"+43 4342 232234",
    "sg:postcode":"9063",
    "sg:province":"K\u00e4rnten",
    "wof:name":"Bauernhof Fam Knafl",
    "wof:placetype":"venue"
},
  "geometry": {"coordinates":[14.3435697556,46.6807899475],"type":"Point"}
}