{
  "type": "Feature",
  "properties": {
    "addr:full":"Ponauer Str 17 Spittal an der Drau K\u00e4rnten 9800",
    "addr:housenumber":"17",
    "addr:postcode":"9800",
    "addr:street":"Str;Kaernten",
    "iso:country":"AT",
    "sg:address":"Ponauer Str 17",
    "sg:city":"Spittal an der Drau",
    "sg:orig_category":"Transportunternehmen",
    "sg:phone":"+43 4762 5709",
    "sg:postcode":"9800",
    "sg:province":"K\u00e4rnten",
    "wof:name":"Reiterer Transporte GmbH & Co KG",
    "wof:placetype":"venue"
},
  "geometry": {"coordinates":[13.49913311,46.7894973755],"type":"Point"}
}