{
  "type": "Feature",
  "properties": {
    "iso:country":"AT",
    "sg:address":"Nr 101",
    "sg:city":"Pinkafeld",
    "sg:orig_category":"Tonstudios",
    "sg:phone":"+43 4333 384227",
    "sg:postcode":"7423",
    "sg:province":"Burgenland",
    "wof:name":"Tonstudio Creativ",
    "wof:placetype":"venue"
},
  "geometry": {"coordinates":[16.124250412,47.3718299866],"type":"Point"}
}