{
  "type": "Feature",
  "properties": {
    "addr:full":"Franz-Schalk-Str 3 Salzburg Salzburg 5020",
    "addr:housenumber":"3",
    "addr:postcode":"5020",
    "addr:street":"Franz-Schalk-Str;Salzburg",
    "iso:country":"AT",
    "sg:address":"Franz-Schalk-Str 3",
    "sg:city":"Salzburg",
    "sg:orig_category":"Physiotherapie",
    "sg:phone":"+43 662 835384",
    "sg:postcode":"5020",
    "sg:province":"Salzburg",
    "wof:name":"Sch\u00f6nleitner Eveline Dipl-PT",
    "wof:placetype":"venue"
},
  "geometry": {"coordinates":[13.0477352142,47.7863502502],"type":"Point"}
}