{
  "type": "Feature",
  "properties": {
    "addr:full":"Koaserbauerstrasse 6 Gmunden Ober\u00f6sterreich 4810",
    "addr:housenumber":"6",
    "addr:postcode":"4810",
    "addr:street":"Koaserbauerstrasse;Oberoesterreich",
    "iso:country":"AT",
    "sg:address":"Koaserbauerstrasse 6",
    "sg:city":"Gmunden",
    "sg:classifiers":[
        {
            "category":"Utilities",
            "subcategory":"Electric",
            "type":"Services"
        }
    ],
    "sg:phone":"+43 7612704300",
    "sg:postcode":"4810",
    "sg:province":"Ober\u00f6sterreich",
    "sg:tags":[
        "measuring",
        "device",
        "temperature"
    ],
    "sg:website":"robamat.com",
    "wof:name":"Robamat Automatisierungstechnik Ges.m.b.H.",
    "wof:placetype":"venue"
},
  "geometry": {"coordinates":[13.815527916,47.9263038635],"type":"Point"}
}