{
  "type": "Feature",
  "properties": {
    "iso:country":"AT",
    "sg:address":"Wiener Strasse 89",
    "sg:city":"Baden",
    "sg:orig_category":"Digitizing Services",
    "sg:phone":"+43 2252 457450",
    "sg:postcode":"2500",
    "sg:province":"Nieder\u00f6sterreich",
    "wof:name":"Datagraph Datenverarbeitung Ges.m.b.H.",
    "wof:placetype":"venue"
},
  "geometry": {"coordinates":[16.2517261505,48.0127372742],"type":"Point"}
}