{
  "type": "Feature",
  "properties": {
    "addr:full":"Neue Sdlg 87 Scheifling Steiermark 8811",
    "addr:housenumber":"87",
    "addr:postcode":"8811",
    "iso:country":"AT",
    "sg:address":"Neue Sdlg 87",
    "sg:city":"Scheifling",
    "sg:orig_category":"Zahntechnische Laboratorien",
    "sg:phone":"+43 4335 828439",
    "sg:postcode":"8811",
    "sg:province":"Steiermark",
    "wof:name":"Wieland Blasius Dental-Atelier",
    "wof:placetype":"venue"
},
  "geometry": {"coordinates":[14.4103889465,47.1504631042],"type":"Point"}
}