{
  "type": "Feature",
  "properties": {
    "iso:country":"AT",
    "sg:address":"Wiener Neust\u00e4dter Strasse 22",
    "sg:city":"Mariazell",
    "sg:classifiers":[
        {
            "category":"Shopping",
            "subcategory":"Department Store",
            "type":"Retail Goods"
        }
    ],
    "sg:phone":"+43 3882 2382",
    "sg:postcode":"8630",
    "sg:province":"Steiermark",
    "sg:tags":[
        "linen",
        "bed"
    ],
    "sg:website":"oberrauter.at",
    "wof:name":"Peter Oberrauter GmbH",
    "wof:placetype":"venue"
},
  "geometry": {"coordinates":[15.3215150833,47.7715988159],"type":"Point"}
}