{
  "type": "Feature",
  "properties": {
    "iso:country":"AT",
    "sg:address":"Lehenstr 12",
    "sg:city":"Wien",
    "sg:orig_category":"Werbeagenturen",
    "sg:phone":"+43 1 7748125",
    "sg:postcode":"1220",
    "sg:province":"Wien",
    "wof:name":"D.C.M. Deichgr\u00e4berei-Cech-Martin Werbeagentur und Ank\u00fcndigungsunternehmen",
    "wof:placetype":"venue"
},
  "geometry": {"coordinates":[16.5212154388,48.2265701294],"type":"Point"}
}