{
  "type": "Feature",
  "properties": {
    "iso:country":"AT",
    "sg:address":"Nr 9",
    "sg:city":"Gasen",
    "sg:orig_category":"Musikgruppen",
    "sg:phone":"+43 3171 2210",
    "sg:postcode":"8616",
    "sg:province":"Steiermark",
    "wof:name":"Die Stoakogler - Fritz Willingshofer",
    "wof:placetype":"venue"
},
  "geometry": {"coordinates":[15.5710201263,47.3835105896],"type":"Point"}
}