{
  "type": "Feature",
  "properties": {
    "addr:full":"Maria-Theresien-Str 44 Lustenau Vorarlberg 6890",
    "addr:housenumber":"44",
    "addr:postcode":"6890",
    "addr:street":"Maria-Theresien-Str",
    "iso:country":"AT",
    "sg:address":"Maria-Theresien-Str 44",
    "sg:city":"Lustenau",
    "sg:orig_category":"Farben U Lacke / Einzelhandel",
    "sg:phone":"+43 4355 7785360",
    "sg:postcode":"6890",
    "sg:province":"Vorarlberg",
    "wof:name":"Morscher Farben- u Werkzeug-Handels-GesmbH",
    "wof:placetype":"venue"
},
  "geometry": {"coordinates":[9.6599445343,47.4301490784],"type":"Point"}
}