{
  "type": "Feature",
  "properties": {
    "iso:country":"AT",
    "sg:address":"Akademiestr 2/4",
    "sg:city":"Wien",
    "sg:orig_category":"Beratungsstellen",
    "sg:phone":"+43 1 51265220",
    "sg:postcode":"1010",
    "sg:province":"Wien",
    "wof:name":"Institut zur Berfulichen Integration IBI",
    "wof:placetype":"venue"
},
  "geometry": {"coordinates":[16.3720550537,48.2034683228],"type":"Point"}
}