{
  "type": "Feature",
  "properties": {
    "iso:country":"AT",
    "sg:address":"Industriestrasse 12",
    "sg:city":"Grieskirchen",
    "sg:orig_category":"Apparatus, Containers, Tanks, Vessels, And Boilers Of Stainless Steel",
    "sg:phone":"+43 7248 6060",
    "sg:postcode":"4710",
    "sg:province":"Ober\u00f6sterreich",
    "sg:website":"froeling.com",
    "wof:name":"Fr\u00f6ling Heizkessel- und Beh\u00e4lterbau Ges.m.b.H.",
    "wof:placetype":"venue"
},
  "geometry": {"coordinates":[13.8380966187,48.2301483154],"type":"Point"}
}