{
  "type": "Feature",
  "properties": {
    "addr:full":"Villacher Str 20 Feldkirchen in K\u00e4rnten K\u00e4rnten 9560",
    "addr:postcode":"9560",
    "addr:street":"Str 20;Kaernten",
    "iso:country":"AT",
    "sg:address":"Villacher Str 20",
    "sg:city":"Feldkirchen in K\u00e4rnten",
    "sg:orig_category":"Hallenbau U -Sanierung",
    "sg:phone":"+43 4342 7626510",
    "sg:postcode":"9560",
    "sg:province":"K\u00e4rnten",
    "sg:website":"haslinger.co.at",
    "wof:name":"Haslinger Stahlbau GmbH",
    "wof:placetype":"venue"
},
  "geometry": {"coordinates":[14.0920295715,46.7234268188],"type":"Point"}
}