{
  "type": "Feature",
  "properties": {
    "addr:full":"Nr 20 Schwarzenau Nieder\u00f6sterreich 3900",
    "addr:postcode":"3900",
    "addr:street":"Nr;Schwarzenau",
    "iso:country":"AT",
    "sg:address":"Nr 20",
    "sg:city":"Schwarzenau",
    "sg:orig_category":"Transportunternehmen",
    "sg:phone":"+43 2849 22950",
    "sg:postcode":"3900",
    "sg:province":"Nieder\u00f6sterreich",
    "wof:name":"M\u00fclleder Franz GesmbH & Co KG",
    "wof:placetype":"venue"
},
  "geometry": {"coordinates":[11.1949300766,50.4527397156],"type":"Point"}
}