{
  "type": "Feature",
  "properties": {
    "addr:full":"Linzer Str 412 Wien Wien 1140",
    "addr:housenumber":"412",
    "addr:postcode":"1140",
    "addr:street":"Linzer Str",
    "iso:country":"AT",
    "sg:address":"Linzer Str 412",
    "sg:city":"Wien",
    "sg:orig_category":"Fu\u00c3\u0178pflege U Fu\u00c3\u0178pflegesalons",
    "sg:phone":"+43 4319 149305",
    "sg:postcode":"1140",
    "sg:province":"Wien",
    "wof:name":"Slama Elisabeth",
    "wof:placetype":"venue"
},
  "geometry": {"coordinates":[16.259016037,48.2019386292],"type":"Point"}
}