{
  "type": "Feature",
  "properties": {
    "addr:full":"Schartenweg 5 Bad Kleinkirchheim K\u00e4rnten 9546",
    "addr:housenumber":"5",
    "addr:postcode":"9546",
    "addr:street":"Schartenweg",
    "iso:country":"AT",
    "sg:address":"Schartenweg 5",
    "sg:city":"Bad Kleinkirchheim",
    "sg:classifiers":[
        {
            "category":"Travel",
            "subcategory":"Hotels & Motels",
            "type":"Entertainment"
        }
    ],
    "sg:phone":"+43 4240 5910",
    "sg:postcode":"9546",
    "sg:province":"K\u00e4rnten",
    "wof:name":"Hotel St Oswald",
    "wof:placetype":"venue"
},
  "geometry": {"coordinates":[13.7608537674,46.8356323242],"type":"Point"}
}