{
  "type": "Feature",
  "properties": {
    "addr:full":"Kornpl 2a Langenlois Nieder\u00f6sterreich 3550",
    "addr:housenumber":"2a",
    "addr:postcode":"3550",
    "addr:street":"Kornpl",
    "iso:country":"AT",
    "sg:address":"Kornpl 2a",
    "sg:city":"Langenlois",
    "sg:orig_category":"Banken U Sparkassen",
    "sg:phone":"+43 2734 22910",
    "sg:postcode":"3550",
    "sg:province":"Nieder\u00f6sterreich",
    "wof:name":"Sparkasse Langenlois",
    "wof:placetype":"venue"
},
  "geometry": {"coordinates":[15.6767654419,48.4733161926],"type":"Point"}
}