{
  "type": "Feature",
  "properties": {
    "addr:full":"IZ K\u00e4lberweide 71 Parndorf Burgenland 7111",
    "addr:housenumber":"71",
    "addr:postcode":"7111",
    "iso:country":"AT",
    "sg:address":"IZ K\u00e4lberweide 71",
    "sg:city":"Parndorf",
    "sg:orig_category":"Porzellan U Porzellanwaren",
    "sg:phone":"+43 2166 20836",
    "sg:postcode":"7111",
    "sg:province":"Burgenland",
    "wof:name":"Rosenthal \u00d6sterreich VertriebsgesmbH",
    "wof:placetype":"venue"
},
  "geometry": {"coordinates":[16.8575897217,47.9981613159],"type":"Point"}
}