{
  "type": "Feature",
  "properties": {
    "addr:full":"K\u00f6nigstetter Str 58 Tulln an der Donau Nieder\u00f6sterreich 3430",
    "addr:postcode":"3430",
    "addr:street":"Str 58",
    "iso:country":"AT",
    "sg:address":"K\u00f6nigstetter Str 58",
    "sg:city":"Tulln an der Donau",
    "sg:orig_category":"Bekleidung / Erzeugung U Gro\u00c3\u0178handel",
    "sg:phone":"+43 4322 7264250",
    "sg:postcode":"3430",
    "sg:province":"Nieder\u00f6sterreich",
    "wof:name":"Salem Strickwaren Erzeugung GesmbH",
    "wof:placetype":"venue"
},
  "geometry": {"coordinates":[16.0647926331,48.3250541687],"type":"Point"}
}