{
  "type": "Feature",
  "properties": {
    "addr:full":"E\u00dfreithweg 578A/1 Kaprun Salzburg 5710",
    "addr:housenumber":"578a / 1",
    "addr:postcode":"5710",
    "addr:street":"Essreithweg;Salzburg",
    "iso:country":"AT",
    "sg:address":"E\u00dfreithweg 578A/1",
    "sg:city":"Kaprun",
    "sg:orig_category":"Appartements / Ferienwohnungen",
    "sg:phone":"+43 4365 478451",
    "sg:postcode":"5710",
    "sg:province":"Salzburg",
    "wof:name":"Dettenbeck KEG",
    "wof:placetype":"venue"
},
  "geometry": {"coordinates":[12.7575788498,47.2708206177],"type":"Point"}
}