{
  "type": "Feature",
  "properties": {
    "addr:full":"Schubertstr 23 Kufstein Tirol 6330",
    "addr:housenumber":"23",
    "addr:postcode":"6330",
    "addr:street":"Schubertstr;Tirol",
    "iso:country":"AT",
    "sg:address":"Schubertstr 23",
    "sg:city":"Kufstein",
    "sg:orig_category":"Lesezirkel",
    "sg:phone":"+43 5372 624620",
    "sg:postcode":"6330",
    "sg:province":"Tirol",
    "wof:name":"Alpenland Lesedienst Klemens Dankl GesmbH & Co KG",
    "wof:placetype":"venue"
},
  "geometry": {"coordinates":[12.1624765396,47.5826759338],"type":"Point"}
}