{
  "type": "Feature",
  "properties": {
    "addr:full":"Lebenbergstr 11 Kitzb\u00fchel Tirol 6370",
    "addr:housenumber":"11",
    "addr:postcode":"6370",
    "addr:street":"Lebenbergstr;Tirol",
    "iso:country":"AT",
    "sg:address":"Lebenbergstr 11",
    "sg:city":"Kitzb\u00fchel",
    "sg:orig_category":"Immobilienmakler",
    "sg:phone":"+43 5356 64695",
    "sg:postcode":"6370",
    "sg:province":"Tirol",
    "wof:name":"Lebenberg Immobilien Nikolaus Leitner KEG",
    "wof:placetype":"venue"
},
  "geometry": {"coordinates":[12.3787374496,47.4523200989],"type":"Point"}
}