{
  "type": "Feature",
  "properties": {
    "addr:full":"Gewerbestr 4 Hopfgarten im Brixental Tirol 6361",
    "addr:housenumber":"4",
    "addr:postcode":"6361",
    "addr:street":"Gewerbestr;Tirol",
    "iso:country":"AT",
    "sg:address":"Gewerbestr 4",
    "sg:city":"Hopfgarten im Brixental",
    "sg:orig_category":"Erdbau",
    "sg:phone":"+43 4353 3540138",
    "sg:postcode":"6361",
    "sg:province":"Tirol",
    "wof:name":"Wieser Gerhard Erdbau",
    "wof:placetype":"venue"
},
  "geometry": {"coordinates":[12.1458330154,47.4583282471],"type":"Point"}
}