{
  "type": "Feature",
  "properties": {
    "iso:country":"AT",
    "sg:address":"Nr 3",
    "sg:city":"Heiligenkreuz im Wienerwald",
    "sg:orig_category":"Transportunternehmen",
    "sg:phone":"+43 2258 8582",
    "sg:postcode":"2532",
    "sg:province":"Nieder\u00f6sterreich",
    "wof:name":"Winter Josef",
    "wof:placetype":"venue"
},
  "geometry": {"coordinates":[166.9221496582,-0.5282999873],"type":"Point"}
}