{
  "type": "Feature",
  "properties": {
    "addr:full":"Kammeringstr 14 Guntramsdorf Nieder\u00f6sterreich 2353",
    "addr:housenumber":"14",
    "addr:postcode":"2353",
    "addr:street":"Kammeringstr",
    "iso:country":"AT",
    "sg:address":"Kammeringstr 14",
    "sg:city":"Guntramsdorf",
    "sg:orig_category":"Baumeister",
    "sg:phone":"+43 2236 506088",
    "sg:postcode":"2353",
    "sg:province":"Nieder\u00f6sterreich",
    "sg:website":"www.sogl-bau.at",
    "wof:name":"Sogl Paul Ing Bau GmbH",
    "wof:placetype":"venue"
},
  "geometry": {"coordinates":[16.3064575195,48.0534172058],"type":"Point"}
}