{
  "type": "Feature",
  "properties": {
    "addr:full":"Bahnstr 39 Mistelbach Nieder\u00f6sterreich 2130",
    "addr:housenumber":"39",
    "addr:postcode":"2130",
    "addr:street":"Bahnstr;Niederoesterreich",
    "iso:country":"AT",
    "sg:address":"Bahnstr 39",
    "sg:city":"Mistelbach",
    "sg:orig_category":"Finanz- U Wirtschaftsberatung",
    "sg:phone":"+43 4325 7232412",
    "sg:postcode":"2130",
    "sg:province":"Nieder\u00f6sterreich",
    "wof:name":"P\u00f6schl Claudia Dr",
    "wof:placetype":"venue"
},
  "geometry": {"coordinates":[16.5686302185,48.5663986206],"type":"Point"}
}