{
  "type": "Feature",
  "properties": {
    "addr:full":"Herzog-Albrecht-Str 1 Laxenburg Nieder\u00f6sterreich 2361",
    "addr:housenumber":"1",
    "addr:postcode":"2361",
    "addr:street":"Herzog-Albrecht-Str",
    "iso:country":"AT",
    "sg:address":"Herzog-Albrecht-Str 1",
    "sg:city":"Laxenburg",
    "sg:orig_category":"Tabaktrafiken",
    "sg:phone":"+43 2236 72975",
    "sg:postcode":"2361",
    "sg:province":"Nieder\u00f6sterreich",
    "wof:name":"Riedl Walter",
    "wof:placetype":"venue"
},
  "geometry": {"coordinates":[16.3558387756,48.0685348511],"type":"Point"}
}