{
  "type": "Feature",
  "properties": {
    "addr:full":"Bahnhofstr 28 Retz Nieder\u00f6sterreich 2070",
    "addr:postcode":"2070",
    "addr:street":"Bahnhofstr 28",
    "iso:country":"AT",
    "sg:address":"Bahnhofstr 28",
    "sg:city":"Retz",
    "sg:orig_category":"\u00c3\u201erzte / F Allgemeinmedizin",
    "sg:phone":"+43 2942 20580",
    "sg:postcode":"2070",
    "sg:province":"Nieder\u00f6sterreich",
    "wof:name":"Forsthuber Theresia Dr med",
    "wof:placetype":"venue"
},
  "geometry": {"coordinates":[15.9559659958,48.7547149658],"type":"Point"}
}