{
  "type": "Feature",
  "properties": {
    "iso:country":"AT",
    "sg:address":"Arzberg 147",
    "sg:city":"Reichraming",
    "sg:classifiers":[
        {
            "category":"Home & Garden",
            "subcategory":"Building Materials",
            "type":"Retail Goods"
        }
    ],
    "sg:phone":"+43 7255 8177",
    "sg:postcode":"4462",
    "sg:province":"Ober\u00f6sterreich",
    "sg:tags":[
        "gravel",
        "crushed"
    ],
    "wof:name":"Hermann Oberforster",
    "wof:placetype":"venue"
},
  "geometry": {"coordinates":[14.4813766479,47.8970794678],"type":"Point"}
}