{
  "type": "Feature",
  "properties": {
    "addr:full":"Nr 14 Patsch Tirol 6082",
    "addr:postcode":"6082",
    "addr:street":"Nr 14;Tirol",
    "iso:country":"AT",
    "sg:address":"Nr 14",
    "sg:city":"Patsch",
    "sg:orig_category":"Appartements / Ferienwohnungen",
    "sg:phone":"+43 512 379083",
    "sg:postcode":"6082",
    "sg:province":"Tirol",
    "wof:name":"Ferienhof Sonnentaler",
    "wof:placetype":"venue"
},
  "geometry": {"coordinates":[-103.4913406372,39.2801246643],"type":"Point"}
}