{
  "type": "Feature",
  "properties": {
    "addr:full":"Pluskaufstr 7 Pasching Ober\u00f6sterreich 4061",
    "addr:housenumber":"7",
    "addr:postcode":"4061",
    "addr:street":"Pluskaufstr;Oberoesterreich",
    "iso:country":"AT",
    "sg:address":"Pluskaufstr 7",
    "sg:city":"Pasching",
    "sg:orig_category":"Freizeit- U Sportbekleidung",
    "sg:phone":"+43 4372 2969219",
    "sg:postcode":"4061",
    "sg:province":"Ober\u00f6sterreich",
    "wof:name":"Levis Store",
    "wof:placetype":"venue"
},
  "geometry": {"coordinates":[14.2359104156,48.2444572449],"type":"Point"}
}