{
  "type": "Feature",
  "properties": {
    "addr:full":"Grazer Str 1 Gleisdorf Steiermark 8200",
    "addr:housenumber":"1",
    "addr:postcode":"8200",
    "addr:street":"Str",
    "iso:country":"AT",
    "sg:address":"Grazer Str 1",
    "sg:city":"Gleisdorf",
    "sg:orig_category":"Gerichte",
    "sg:phone":"+43 3112 22360",
    "sg:postcode":"8200",
    "sg:province":"Steiermark",
    "wof:name":"Bezirksgericht Gleisdorf",
    "wof:placetype":"venue"
},
  "geometry": {"coordinates":[15.7045059204,47.1042251587],"type":"Point"}
}