{
  "type": "Feature",
  "properties": {
    "addr:full":"Saarpl 17/5 Wien Wien 1190",
    "addr:housenumber":"17 / 5",
    "addr:postcode":"1190",
    "addr:street":"Saarpl",
    "iso:country":"AT",
    "sg:address":"Saarpl 17/5",
    "sg:city":"Wien",
    "sg:orig_category":"Steuerberatung",
    "sg:phone":"+43 4313 691533",
    "sg:postcode":"1190",
    "sg:province":"Wien",
    "wof:name":"Treuhand-Organisations- u Portfolioberatung Wirtschaftstreuhand GmbH",
    "wof:placetype":"venue"
},
  "geometry": {"coordinates":[16.3486404419,48.2449798584],"type":"Point"}
}