{
  "type": "Feature",
  "properties": {
    "iso:country":"AT",
    "sg:address":"Unterer Markt 18",
    "sg:city":"Wies",
    "sg:classifiers":[
        {
            "category":"Travel",
            "subcategory":"Hotels & Motels",
            "type":"Entertainment"
        }
    ],
    "sg:phone":"+43 3465 23910",
    "sg:postcode":"8551",
    "sg:province":"Steiermark",
    "wof:name":"Hotel Seltenriegel",
    "wof:placetype":"venue"
},
  "geometry": {"coordinates":[15.2726697922,46.7203407288],"type":"Point"}
}