{
  "type": "Feature",
  "properties": {
    "addr:full":"Hermann-Sander-Str 26 Bludenz Vorarlberg 6700",
    "addr:housenumber":"26",
    "addr:postcode":"6700",
    "addr:street":"Hermann-Sander-Str",
    "iso:country":"AT",
    "sg:address":"Hermann-Sander-Str 26",
    "sg:city":"Bludenz",
    "sg:orig_category":"Bergbahnen",
    "sg:phone":"+43 5552 30500",
    "sg:postcode":"6700",
    "sg:province":"Vorarlberg",
    "wof:name":"Ludescher Christoph",
    "wof:placetype":"venue"
},
  "geometry": {"coordinates":[9.8200922012,47.1518974304],"type":"Point"}
}