{
  "type": "Feature",
  "properties": {
    "addr:full":"Innstr 27a Rattenberg Tirol 6240",
    "addr:housenumber":"27a",
    "addr:postcode":"6240",
    "addr:street":"Innstr",
    "iso:country":"AT",
    "sg:address":"Innstr 27a",
    "sg:city":"Rattenberg",
    "sg:orig_category":"Schlossereien",
    "sg:phone":"+43 5337 65154",
    "sg:postcode":"6240",
    "sg:province":"Tirol",
    "wof:name":"H\u00f6lzl G\u00fcnther GesmbH",
    "wof:placetype":"venue"
},
  "geometry": {"coordinates":[11.9093799591,47.4497337341],"type":"Point"}
}