{
  "type": "Feature",
  "properties": {
    "iso:country":"AT",
    "sg:address":"Schwendnerg. 16 ",
    "sg:city":"Klagenfurt",
    "sg:classifiers":[
        {
            "category":"Manufacturing",
            "subcategory":"Glass & Minerals",
            "type":"Manufacturing & Wholesale Goods"
        }
    ],
    "sg:phone":"+43 4346 3382131",
    "sg:postcode":"9020",
    "sg:province":"K\u00e4rnten",
    "wof:name":"ISOLAR ISOLIERGLAS GESMBH",
    "wof:placetype":"venue"
},
  "geometry": {"coordinates":[14.3396263123,46.6069564819],"type":"Point"}
}