{
  "type": "Feature",
  "properties": {
    "addr:full":"Nr 262 Feldbach Steiermark 8330",
    "addr:postcode":"8330",
    "addr:street":"Nr 262",
    "iso:country":"AT",
    "sg:address":"Nr 262",
    "sg:city":"Feldbach",
    "sg:orig_category":"Beton- U Betonsteinwerke",
    "sg:phone":"+43 4331 522587",
    "sg:postcode":"8330",
    "sg:province":"Steiermark",
    "wof:name":"K\u00f6ck Deckensysteme GesmbH & Co KG",
    "wof:placetype":"venue"
},
  "geometry": {"coordinates":[15.888250351,46.9527397156],"type":"Point"}
}