{
  "type": "Feature",
  "properties": {
    "addr:full":"Westbahnstr 56-58 Wien Wien 1070",
    "addr:postcode":"56-58;1070",
    "iso:country":"AT",
    "sg:address":"Westbahnstr 56-58",
    "sg:city":"Wien",
    "sg:orig_category":"Medizintechnik",
    "sg:phone":"+43 1 5228080",
    "sg:postcode":"1070",
    "sg:province":"Wien",
    "wof:name":"Demmer Dr KEG",
    "wof:placetype":"venue"
},
  "geometry": {"coordinates":[16.3396377563,48.2019081116],"type":"Point"}
}