{
  "type": "Feature",
  "properties": {
    "addr:full":"Urreiting 92 St. Johann im Pongau Salzburg 5600",
    "addr:housenumber":"92",
    "addr:postcode":"5600",
    "addr:street":"Urreiting;Salzburg",
    "iso:country":"AT",
    "sg:address":"Urreiting 92",
    "sg:city":"St. Johann im Pongau",
    "sg:orig_category":"Bauunternehmen",
    "sg:phone":"+43 6462 81410",
    "sg:postcode":"5600",
    "sg:province":"Salzburg",
    "wof:name":"STRABAG AG",
    "wof:placetype":"venue"
},
  "geometry": {"coordinates":[13.2228746414,47.3937797546],"type":"Point"}
}