{
  "type": "Feature",
  "properties": {
    "addr:full":"Neustiftgasse 7 Gols Burgenland 7122",
    "addr:housenumber":"7",
    "addr:postcode":"7122",
    "addr:street":"Neustiftgasse",
    "iso:country":"AT",
    "sg:address":"Neustiftgasse 7",
    "sg:city":"Gols",
    "sg:classifiers":[
        {
            "category":"Home & Garden",
            "subcategory":"Household Appliances",
            "type":"Retail Goods"
        }
    ],
    "sg:phone":"+43 2173 2232",
    "sg:postcode":"7122",
    "sg:province":"Burgenland",
    "sg:tags":[
        "electric"
    ],
    "wof:name":"Elektro Taschner GmbH",
    "wof:placetype":"venue"
},
  "geometry": {"coordinates":[16.9086151123,47.8986358643],"type":"Point"}
}