{
  "type": "Feature",
  "properties": {
    "iso:country":"AT",
    "sg:address":"Wagramer Str 12",
    "sg:city":"Grafenw\u00f6rth",
    "sg:orig_category":"Schmieden U Schmiedeeisenelemente",
    "sg:phone":"+43 2738 2289",
    "sg:postcode":"3484",
    "sg:province":"Nieder\u00f6sterreich",
    "wof:name":"Holzinger Werner",
    "wof:placetype":"venue"
},
  "geometry": {"coordinates":[-9.1345300674,52.9185905457],"type":"Point"}
}