{
  "type": "Feature",
  "properties": {
    "addr:full":"Vorgartenstr 111/15 Wien Wien 1020",
    "addr:housenumber":"111 / 15",
    "addr:postcode":"1020",
    "iso:country":"AT",
    "sg:address":"Vorgartenstr 111/15",
    "sg:city":"Wien",
    "sg:orig_category":"Transportunternehmen",
    "sg:phone":"+43 1 2147527",
    "sg:postcode":"1020",
    "sg:province":"Wien",
    "wof:name":"Colic Margarita",
    "wof:placetype":"venue"
},
  "geometry": {"coordinates":[16.3943061829,48.2305984497],"type":"Point"}
}