{
  "type": "Feature",
  "properties": {
    "addr:full":"Wolfholzg 5 Brunn am Gebirge Nieder\u00f6sterreich 2345",
    "addr:housenumber":"5",
    "addr:postcode":"2345",
    "addr:street":"Wolfholzg",
    "iso:country":"AT",
    "sg:address":"Wolfholzg 5",
    "sg:city":"Brunn am Gebirge",
    "sg:orig_category":"Transportunternehmen",
    "sg:phone":"+43 2236 34508",
    "sg:postcode":"2345",
    "sg:province":"Nieder\u00f6sterreich",
    "wof:name":"Hesoun Josef Transport GmbH",
    "wof:placetype":"venue"
},
  "geometry": {"coordinates":[16.2916240692,48.1194419861],"type":"Point"}
}