{
  "type": "Feature",
  "properties": {
    "addr:full":"Weidenstrasse 12 Peuerbach Ober\u00f6sterreich 4722",
    "addr:housenumber":"12",
    "addr:postcode":"4722",
    "addr:street":"Weidenstrasse",
    "iso:country":"AT",
    "sg:address":"Weidenstrasse 12",
    "sg:city":"Peuerbach",
    "sg:classifiers":[
        {
            "category":"Home & Garden",
            "subcategory":"Carpets & Floor Coverings",
            "type":"Retail Goods"
        }
    ],
    "sg:phone":"+43 7276 3373",
    "sg:postcode":"4722",
    "sg:province":"Ober\u00f6sterreich",
    "sg:tags":[
        "design"
    ],
    "wof:name":"Paula's Bodenstudio",
    "wof:placetype":"venue"
},
  "geometry": {"coordinates":[13.7833900452,48.341758728],"type":"Point"}
}