{
  "type": "Feature",
  "properties": {
    "addr:full":"Hetzendorfer Str 65 Wien Wien 1120",
    "addr:postcode":"1120",
    "addr:street":"Str 65",
    "iso:country":"AT",
    "sg:address":"Hetzendorfer Str 65",
    "sg:city":"Wien",
    "sg:orig_category":"Architekten",
    "sg:phone":"+43 1 8020638",
    "sg:postcode":"1120",
    "sg:province":"Wien",
    "wof:name":"Ullreich Gerhard Arch Mag",
    "wof:placetype":"venue"
},
  "geometry": {"coordinates":[16.3128128052,48.1659927368],"type":"Point"}
}