{
  "type": "Feature",
  "properties": {
    "addr:full":"Zillertalstr 43 Salzburg Salzburg 5020",
    "addr:housenumber":"43",
    "addr:postcode":"5020",
    "addr:street":"Zillertalstr;Salzburg",
    "iso:country":"AT",
    "sg:address":"Zillertalstr 43",
    "sg:city":"Salzburg",
    "sg:orig_category":"Elektroinstallationsunternehmen",
    "sg:phone":"+43 662 422090",
    "sg:postcode":"5020",
    "sg:province":"Salzburg",
    "wof:name":"Romagna Gustav",
    "wof:placetype":"venue"
},
  "geometry": {"coordinates":[13.031627655,47.8188209534],"type":"Point"}
}