{
  "type": "Feature",
  "properties": {
    "iso:country":"AT",
    "sg:address":"Zillertalstr 43",
    "sg:city":"Salzburg",
    "sg:orig_category":"Elektroinstallationsunternehmen",
    "sg:phone":"+43 662 422090",
    "sg:postcode":"5020",
    "sg:province":"Salzburg",
    "wof:name":"Romagna Gustav",
    "wof:placetype":"venue"
},
  "geometry": {"coordinates":[13.031627655,47.8188209534],"type":"Point"}
}