{
  "type": "Feature",
  "properties": {
    "iso:country":"AT",
    "sg:address":"Hauptpl 6",
    "sg:city":"Zams",
    "sg:orig_category":"Ingenieurkonsulenten / Zivilingenieure",
    "sg:phone":"+43 5442 645730",
    "sg:postcode":"6511",
    "sg:province":"Tirol",
    "wof:name":"Pfeifer Peter Dipl-Ing",
    "wof:placetype":"venue"
},
  "geometry": {"coordinates":[10.5894384384,47.158164978],"type":"Point"}
}