{
  "type": "Feature",
  "properties": {
    "addr:full":"Nr 30 Gro\u00dfwilfersdorf Steiermark 8263",
    "addr:postcode":"8263",
    "addr:street":"Nr",
    "iso:country":"AT",
    "sg:address":"Nr 30",
    "sg:city":"Gro\u00dfwilfersdorf",
    "sg:orig_category":"Tischlereien",
    "sg:phone":"+43 4333 85326",
    "sg:postcode":"8263",
    "sg:province":"Steiermark",
    "wof:name":"Pfeiffer Bernhard",
    "wof:placetype":"venue"
},
  "geometry": {"coordinates":[15.9948101044,47.0773239136],"type":"Point"}
}