{
  "type": "Feature",
  "properties": {
    "addr:full":"K\u00f6stenberger Str 147 Velden am W\u00f6rther See K\u00e4rnten 9220",
    "addr:housenumber":"147",
    "addr:postcode":"9220",
    "addr:street":"Str;Kaernten",
    "iso:country":"AT",
    "sg:address":"K\u00f6stenberger Str 147",
    "sg:city":"Velden am W\u00f6rther See",
    "sg:orig_category":"Pensionen / Privatzimmer",
    "sg:phone":"+43 4342 7433640",
    "sg:postcode":"9220",
    "sg:province":"K\u00e4rnten",
    "wof:name":"Neff Tanja Mag",
    "wof:placetype":"venue"
},
  "geometry": {"coordinates":[14.0348787308,46.6252365112],"type":"Point"}
}