{
  "type": "Feature",
  "properties": {
    "addr:full":"Stadlauer Str 11 Wien Wien 1220",
    "addr:postcode":"1220",
    "addr:street":"Str 11",
    "iso:country":"AT",
    "sg:address":"Stadlauer Str 11",
    "sg:city":"Wien",
    "sg:orig_category":"Blumeneinzelhandel",
    "sg:phone":"+43 1 2807522",
    "sg:postcode":"1220",
    "sg:province":"Wien",
    "wof:name":"MOON FLOWER",
    "wof:placetype":"venue"
},
  "geometry": {"coordinates":[16.4522514343,48.2254943848],"type":"Point"}
}