{
  "type": "Feature",
  "properties": {
    "addr:full":"Kremstalstrasse 59 Krems an der Donau Nieder\u00f6sterreich 3500",
    "addr:housenumber":"59",
    "addr:postcode":"3500",
    "addr:street":"Kremstalstrasse",
    "iso:country":"AT",
    "sg:address":"Kremstalstrasse 59",
    "sg:city":"Krems an der Donau",
    "sg:classifiers":[
        {
            "category":"Sports & Exercise",
            "subcategory":"Swimming Pool",
            "type":"Entertainment"
        }
    ],
    "sg:phone":"+43 2732 76660",
    "sg:postcode":"3500",
    "sg:province":"Nieder\u00f6sterreich",
    "sg:tags":[
        "balance",
        "tank",
        "plastic"
    ],
    "sg:website":"pastnerit.at",
    "wof:name":"Ing. Erich Pastner Kunststofftechnik",
    "wof:placetype":"venue"
},
  "geometry": {"coordinates":[15.6007146835,48.4185523987],"type":"Point"}
}