{
  "type": "Feature",
  "properties": {
    "addr:full":"Werner-Bader-Strasse 9 B\u00fcrmoos Salzburg 5111",
    "addr:housenumber":"9",
    "addr:postcode":"5111",
    "addr:street":"Werner-Bader-Strasse;Salzburg",
    "iso:country":"AT",
    "sg:address":"Werner-Bader-Strasse 9",
    "sg:city":"B\u00fcrmoos",
    "sg:classifiers":[
        {
            "category":"Home & Garden",
            "subcategory":"Home Furnishings",
            "type":"Retail Goods"
        }
    ],
    "sg:phone":"+43 6274 6588",
    "sg:postcode":"5111",
    "sg:province":"Salzburg",
    "sg:tags":[
        "medicine",
        "bathroom",
        "cupboards",
        "cabinet"
    ],
    "wof:name":"KIFT Handelsges.m.b.H.",
    "wof:placetype":"venue"
},
  "geometry": {"coordinates":[12.9328432083,47.9889717102],"type":"Point"}
}