{
  "type": "Feature",
  "properties": {
    "addr:full":"Dauphinestr 58 Linz Ober\u00f6sterreich 4030",
    "addr:housenumber":"58",
    "addr:postcode":"4030",
    "addr:street":"Dauphinestr",
    "iso:country":"AT",
    "sg:address":"Dauphinestr 58",
    "sg:city":"Linz",
    "sg:orig_category":"Nachhilfe U Lernbetreuung",
    "sg:phone":"+43 4373 2306381",
    "sg:postcode":"4030",
    "sg:province":"Ober\u00f6sterreich",
    "wof:name":"Sch\u00fclerhilfe Institut f Nachhilfe",
    "wof:placetype":"venue"
},
  "geometry": {"coordinates":[14.3116817474,48.2535400391],"type":"Point"}
}