{
  "type": "Feature",
  "properties": {
    "addr:full":"Elisabethstr 39 Salzburg Salzburg 5020",
    "addr:housenumber":"39",
    "addr:postcode":"5020",
    "addr:street":"Elisabethstr;Salzburg",
    "iso:country":"AT",
    "sg:address":"Elisabethstr 39",
    "sg:city":"Salzburg",
    "sg:orig_category":"Kinderbetreuung",
    "sg:phone":"+43 662 454263",
    "sg:postcode":"5020",
    "sg:province":"Salzburg",
    "wof:name":"Kindergarten d Pfarre St Elisabeth",
    "wof:placetype":"venue"
},
  "geometry": {"coordinates":[13.0425643921,47.8156013489],"type":"Point"}
}