{
  "type": "Feature",
  "properties": {
    "addr:full":"Bundesstr 70c Kalwang Steiermark 8775",
    "addr:housenumber":"70c",
    "addr:postcode":"8775",
    "addr:street":"Bundesstr",
    "iso:country":"AT",
    "sg:address":"Bundesstr 70c",
    "sg:city":"Kalwang",
    "sg:orig_category":"Tankstellen",
    "sg:phone":"+43 3846 8372",
    "sg:postcode":"8775",
    "sg:province":"Steiermark",
    "wof:name":"AVANTI TankstellenbetriebsgesmbH",
    "wof:placetype":"venue"
},
  "geometry": {"coordinates":[14.7566070557,47.4275856018],"type":"Point"}
}