{
  "type": "Feature",
  "properties": {
    "addr:full":"Lessingstr 16 Graz Steiermark 8010",
    "addr:housenumber":"16",
    "addr:postcode":"8010",
    "addr:street":"Lessingstr",
    "iso:country":"AT",
    "sg:address":"Lessingstr 16",
    "sg:city":"Graz",
    "sg:orig_category":"Konzertagenturen",
    "sg:phone":"+43 316 378186",
    "sg:postcode":"8010",
    "sg:province":"Steiermark",
    "wof:name":"Fink Jonny",
    "wof:placetype":"venue"
},
  "geometry": {"coordinates":[15.4502401352,47.0708312988],"type":"Point"}
}