{
  "type": "Feature",
  "properties": {
    "iso:country":"AT",
    "sg:address":"Rochelg 19",
    "sg:city":"Graz",
    "sg:orig_category":"Installationsunternehmen",
    "sg:phone":"+43 664 5027209",
    "sg:postcode":"8020",
    "sg:province":"Steiermark",
    "wof:name":"WTW Work-Team-Wolf",
    "wof:placetype":"venue"
},
  "geometry": {"coordinates":[15.4055767059,47.0734558105],"type":"Point"}
}