{
  "type": "Feature",
  "properties": {
    "iso:country":"AT",
    "sg:address":"Leibnitzer Str 25",
    "sg:city":"Lebring",
    "sg:orig_category":"Musikgruppen",
    "sg:phone":"+43 3182 2669",
    "sg:postcode":"8403",
    "sg:province":"Steiermark",
    "wof:name":"Die S\u00fcdwest - Steirer Trummer Karl",
    "wof:placetype":"venue"
},
  "geometry": {"coordinates":[15.5372047424,46.8506813049],"type":"Point"}
}