{
  "type": "Feature",
  "properties": {
    "addr:full":"Dorfstr 3 Wartberg im M\u00fcrztal Steiermark 8661",
    "addr:housenumber":"3",
    "addr:postcode":"8661",
    "addr:street":"Dorfstr",
    "iso:country":"AT",
    "sg:address":"Dorfstr 3",
    "sg:city":"Wartberg im M\u00fcrztal",
    "sg:classifiers":[
        {
            "category":"Restaurant",
            "type":"Food & Drink"
        }
    ],
    "sg:phone":"+43 3858 3614",
    "sg:postcode":"8661",
    "sg:province":"Steiermark",
    "sg:tags":[
        "pizzeria"
    ],
    "wof:name":"Kammerhofer Maria Magdalena",
    "wof:placetype":"venue"
},
  "geometry": {"coordinates":[15.4870481491,47.5263557434],"type":"Point"}
}