{
  "type": "Feature",
  "properties": {
    "iso:country":"AT",
    "sg:address":"Nr 123",
    "sg:city":"St. Konrad",
    "sg:orig_category":"Sondermaschinenbau",
    "sg:phone":"+43 76158390",
    "sg:postcode":"4817",
    "sg:province":"Ober\u00f6sterreich",
    "wof:name":"FRAI Elektromaschinenbau GesmbH",
    "wof:placetype":"venue"
},
  "geometry": {"coordinates":[13.8887310028,47.9127082825],"type":"Point"}
}