{
  "type": "Feature",
  "properties": {
    "addr:full":"Herrenstrasse 8 Perg Ober\u00f6sterreich 4320",
    "addr:housenumber":"8",
    "addr:postcode":"4320",
    "addr:street":"Herrenstrasse",
    "iso:country":"AT",
    "sg:address":"Herrenstrasse 8",
    "sg:city":"Perg",
    "sg:classifiers":[
        {
            "category":"Banks & Credit Unions",
            "subcategory":"Investment Brokerage",
            "type":"Services"
        }
    ],
    "sg:phone":"+43 7262 52445",
    "sg:postcode":"4320",
    "sg:province":"Ober\u00f6sterreich",
    "sg:tags":[
        "curtain",
        "rod",
        "accessory"
    ],
    "sg:website":"perg.at/avantart",
    "wof:name":"AVANT ART Raumdesign Ges.m.b.H.",
    "wof:placetype":"venue"
},
  "geometry": {"coordinates":[14.634970665,48.2496185303],"type":"Point"}
}