{
  "type": "Feature",
  "properties": {
    "addr:full":"Stauwerkstrasse 39 Ybbs an der Donau Nieder\u00f6sterreich 3370",
    "addr:housenumber":"39",
    "addr:postcode":"3370",
    "addr:street":"Stauwerkstrasse",
    "iso:country":"AT",
    "sg:address":"Stauwerkstrasse 39",
    "sg:city":"Ybbs an der Donau",
    "sg:classifiers":[
        {
            "category":"Professional",
            "subcategory":"Advertising",
            "type":"Services"
        }
    ],
    "sg:phone":"+43 7412 550000",
    "sg:postcode":"3370",
    "sg:province":"Nieder\u00f6sterreich",
    "sg:tags":[
        "planning",
        "agency",
        "strategic"
    ],
    "sg:website":"stadtlandzeitung.com",
    "wof:name":"Schmutz Media Ges.m.b.H.",
    "wof:placetype":"venue"
},
  "geometry": {"coordinates":[15.0787506104,48.1808853149],"type":"Point"}
}