{
  "type": "Feature",
  "properties": {
    "addr:full":"Tonwerkstr 1 Fritzens Tirol 6122",
    "addr:housenumber":"1",
    "addr:postcode":"6122",
    "addr:street":"Tonwerkstr;Tirol",
    "iso:country":"AT",
    "sg:address":"Tonwerkstr 1",
    "sg:city":"Fritzens",
    "sg:orig_category":"Reinigungsbedarf U Reinigungsmittel",
    "sg:phone":"+43 5224 57112",
    "sg:postcode":"6122",
    "sg:province":"Tirol",
    "wof:name":"Tronia KEG",
    "wof:placetype":"venue"
},
  "geometry": {"coordinates":[11.587389946,47.301700592],"type":"Point"}
}