{
  "type": "Feature",
  "properties": {
    "addr:full":"Schulweg 2 Leibnitz Steiermark 8430",
    "addr:housenumber":"2",
    "addr:postcode":"8430",
    "addr:street":"Schulweg;Steiermark",
    "iso:country":"AT",
    "sg:address":"Schulweg 2",
    "sg:city":"Leibnitz",
    "sg:orig_category":"Nachhilfe U Lernbetreuung",
    "sg:phone":"+43 3452 75818",
    "sg:postcode":"8430",
    "sg:province":"Steiermark",
    "wof:name":"COOL SCHOOL Lerninstitut Mag Pelzmann",
    "wof:placetype":"venue"
},
  "geometry": {"coordinates":[15.5427417755,46.778553009],"type":"Point"}
}