{
  "type": "Feature",
  "properties": {
    "addr:full":"Gr\u00e4nzing 14 Niederndorf Tirol 6342",
    "addr:housenumber":"14",
    "addr:postcode":"6342",
    "addr:street":"Graenzing",
    "iso:country":"AT",
    "sg:address":"Gr\u00e4nzing 14",
    "sg:city":"Niederndorf",
    "sg:orig_category":"Feuerwehren",
    "sg:phone":"+43 5373 62372",
    "sg:postcode":"6342",
    "sg:province":"Tirol",
    "wof:name":"Feuerwehr Niederndorferberg",
    "wof:placetype":"venue"
},
  "geometry": {"coordinates":[12.2437705994,47.6835289001],"type":"Point"}
}