{
  "type": "Feature",
  "properties": {
    "addr:full":"Nr 69 Grafendorf Steiermark 8232",
    "addr:postcode":"8232",
    "addr:street":"Nr",
    "iso:country":"AT",
    "sg:address":"Nr 69",
    "sg:city":"Grafendorf",
    "sg:orig_category":"\u00c3\u201erzte / F Allgemeinmedizin",
    "sg:phone":"+43 4333 3822670",
    "sg:postcode":"8232",
    "sg:province":"Steiermark",
    "wof:name":"Sch\u00f6ppel Walter MedR Dr",
    "wof:placetype":"venue"
},
  "geometry": {"coordinates":[15.9914007187,47.3399276733],"type":"Point"}
}