{
  "type": "Feature",
  "properties": {
    "addr:full":"Hauptpl 10 Lienz Tirol 9900",
    "addr:housenumber":"10",
    "addr:postcode":"9900",
    "addr:street":"Hauptpl;Tirol",
    "iso:country":"AT",
    "sg:address":"Hauptpl 10",
    "sg:city":"Lienz",
    "sg:orig_category":"Blumeneinzelhandel",
    "sg:phone":"+43 4852 73360",
    "sg:postcode":"9900",
    "sg:province":"Tirol",
    "wof:name":"Blumen Germann - Inh Rettenmoser Hans Peter",
    "wof:placetype":"venue"
},
  "geometry": {"coordinates":[12.7694683075,46.8295135498],"type":"Point"}
}