{
  "type": "Feature",
  "properties": {
    "addr:full":"Schulg 1 Gloggnitz Nieder\u00f6sterreich 2640",
    "addr:housenumber":"1",
    "addr:postcode":"2640",
    "addr:street":"Schulg",
    "iso:country":"AT",
    "sg:address":"Schulg 1",
    "sg:city":"Gloggnitz",
    "sg:orig_category":"Hauptschulen",
    "sg:phone":"+43 4326 62423970",
    "sg:postcode":"2640",
    "sg:province":"Nieder\u00f6sterreich",
    "wof:name":"Hauptschule",
    "wof:placetype":"venue"
},
  "geometry": {"coordinates":[15.9340114594,47.6747894287],"type":"Point"}
}