{
  "type": "Feature",
  "properties": {
    "addr:full":"St. Veiter Str 84 Klagenfurt K\u00e4rnten 9020",
    "addr:housenumber":"84",
    "addr:postcode":"9020",
    "addr:street":"St. Veiter Str;Kaernten",
    "iso:country":"AT",
    "sg:address":"St. Veiter Str 84",
    "sg:city":"Klagenfurt",
    "sg:orig_category":"Gartencenter",
    "sg:phone":"+43 463 513517",
    "sg:postcode":"9020",
    "sg:province":"K\u00e4rnten",
    "wof:name":"Kropfitsch Gartenwelt",
    "wof:placetype":"venue"
},
  "geometry": {"coordinates":[14.3117141724,46.6350784302],"type":"Point"}
}