{
  "type": "Feature",
  "properties": {
    "addr:full":"Raiffeisenpromenade 2/1/6 Waidhofen an der Thaya Nieder\u00f6sterreich 3830",
    "addr:housenumber":"2 / 1 / 6",
    "addr:postcode":"3830",
    "addr:street":"Raiffeisenpromenade",
    "iso:country":"AT",
    "sg:address":"Raiffeisenpromenade 2/1/6",
    "sg:city":"Waidhofen an der Thaya",
    "sg:orig_category":"Steuerberatung",
    "sg:phone":"+43 4328 42534120",
    "sg:postcode":"3830",
    "sg:province":"Nieder\u00f6sterreich",
    "wof:name":"LBG Wirtschaftstreuhand- u BeratungsgesmbH",
    "wof:placetype":"venue"
},
  "geometry": {"coordinates":[15.2838354111,48.8136940002],"type":"Point"}
}