{
  "type": "Feature",
  "properties": {
    "addr:full":"Amesberg 11 Bad Leonfelden Ober\u00f6sterreich 4190",
    "addr:housenumber":"11",
    "addr:postcode":"4190",
    "addr:street":"Amesberg",
    "iso:country":"AT",
    "sg:address":"Amesberg 11",
    "sg:city":"Bad Leonfelden",
    "sg:classifiers":[
        {
            "category":"Professional",
            "subcategory":"Management & Consulting",
            "type":"Services"
        }
    ],
    "sg:phone":"+43 7213 20651",
    "sg:postcode":"4190",
    "sg:province":"Ober\u00f6sterreich",
    "wof:name":"Thurmfart Siegfried - Sitemanagement",
    "wof:placetype":"venue"
},
  "geometry": {"coordinates":[14.2936611176,48.5224494934],"type":"Point"}
}