{
  "type": "Feature",
  "properties": {
    "addr:full":"Galgenul 199 St. Gallenkirch Vorarlberg 6791",
    "addr:housenumber":"199",
    "addr:postcode":"6791",
    "addr:street":"Galgenul",
    "iso:country":"AT",
    "sg:address":"Galgenul 199",
    "sg:city":"St. Gallenkirch",
    "sg:orig_category":"Tonstudios",
    "sg:phone":"+43 5557 665824",
    "sg:postcode":"6791",
    "sg:province":"Vorarlberg",
    "wof:name":"Positiv-Records",
    "wof:placetype":"venue"
},
  "geometry": {"coordinates":[9.9627017975,47.0205802917],"type":"Point"}
}