{
  "type": "Feature",
  "properties": {
    "addr:full":"Mehlpl 1 Graz Steiermark 8010",
    "addr:housenumber":"1",
    "addr:postcode":"8010",
    "addr:street":"Mehlpl",
    "iso:country":"AT",
    "sg:address":"Mehlpl 1",
    "sg:city":"Graz",
    "sg:classifiers":[
        {
            "category":"Restaurant",
            "type":"Food & Drink"
        }
    ],
    "sg:phone":"+43 316 828702",
    "sg:postcode":"8010",
    "sg:province":"Steiermark",
    "wof:name":"Restaurant Maroni",
    "wof:placetype":"venue"
},
  "geometry": {"coordinates":[15.4402179718,47.0712928772],"type":"Point"}
}