{
  "type": "Feature",
  "properties": {
    "addr:full":"Bergg 2 Fischamend Nieder\u00f6sterreich 2401",
    "addr:housenumber":"2",
    "addr:postcode":"2401",
    "addr:street":"Bergg",
    "iso:country":"AT",
    "sg:address":"Bergg 2",
    "sg:city":"Fischamend",
    "sg:orig_category":"Autolackierereien",
    "sg:phone":"+43 2232 76693",
    "sg:postcode":"2401",
    "sg:province":"Nieder\u00f6sterreich",
    "wof:name":"Koch Wilhelm",
    "wof:placetype":"venue"
},
  "geometry": {"coordinates":[16.6206321716,48.1169776917],"type":"Point"}
}