{
  "type": "Feature",
  "properties": {
    "iso:country":"AT",
    "sg:address":"Eschenweg 8",
    "sg:city":"F\u00fcrnitz",
    "sg:orig_category":"Speditionen",
    "sg:phone":"+43 4257 30880",
    "sg:postcode":"9586",
    "sg:province":"K\u00e4rnten",
    "wof:name":"Lex Josef & Co Int Speditions- und Lagerhaus GesmbH",
    "wof:placetype":"venue"
},
  "geometry": {"coordinates":[13.811425209,46.5657997131],"type":"Point"}
}