{
  "type": "Feature",
  "properties": {
    "addr:full":"Dr Alfred Klar-Str 18 Steyr Ober\u00f6sterreich 4400",
    "addr:housenumber":"18",
    "addr:postcode":"4400",
    "addr:street":"Dr;Klar-Str;Oberoesterreich",
    "iso:country":"AT",
    "sg:address":"Dr Alfred Klar-Str 18",
    "sg:city":"Steyr",
    "sg:orig_category":"Physiotherapie",
    "sg:phone":"+43 7252 86858",
    "sg:postcode":"4400",
    "sg:province":"Ober\u00f6sterreich",
    "wof:name":"Landa Karl Dipl-PT",
    "wof:placetype":"venue"
},
  "geometry": {"coordinates":[14.4455223083,48.0523033142],"type":"Point"}
}