{
  "type": "Feature",
  "properties": {
    "addr:full":"Wagramer Str 142 Wien Wien 1220",
    "addr:housenumber":"142",
    "addr:postcode":"1220",
    "iso:country":"AT",
    "sg:address":"Wagramer Str 142",
    "sg:city":"Wien",
    "sg:orig_category":"Tabaktrafiken",
    "sg:phone":"+43 1 2042534",
    "sg:postcode":"1220",
    "sg:province":"Wien",
    "wof:name":"Wogowitsch Herta",
    "wof:placetype":"venue"
},
  "geometry": {"coordinates":[16.4427433014,48.2488059998],"type":"Point"}
}