{
  "type": "Feature",
  "properties": {
    "addr:full":"Nr 39 Neukirchen an der Enknach Ober\u00f6sterreich 5145",
    "addr:postcode":"5145",
    "addr:street":"Nr 39",
    "iso:country":"AT",
    "sg:address":"Nr 39",
    "sg:city":"Neukirchen an der Enknach",
    "sg:orig_category":"Friseure U Frisiersalons",
    "sg:phone":"+43 4377 292960",
    "sg:postcode":"5145",
    "sg:province":"Ober\u00f6sterreich",
    "wof:name":"Haarstudio Andreas Renner",
    "wof:placetype":"venue"
},
  "geometry": {"coordinates":[13.0817890167,48.1556587219],"type":"Point"}
}