{
  "type": "Feature",
  "properties": {
    "addr:full":"Stadlg 8a Enns Ober\u00f6sterreich 4470",
    "addr:housenumber":"8a",
    "addr:postcode":"4470",
    "addr:street":"Stadlg",
    "iso:country":"AT",
    "sg:address":"Stadlg 8a",
    "sg:city":"Enns",
    "sg:orig_category":"Anlagenbau U -Technik",
    "sg:phone":"+43 7223 83620",
    "sg:postcode":"4470",
    "sg:province":"Ober\u00f6sterreich",
    "wof:name":"Cemtec Cement and Mining Technology GmbH",
    "wof:placetype":"venue"
},
  "geometry": {"coordinates":[14.4792346954,48.2137947083],"type":"Point"}
}