{
  "type": "Feature",
  "properties": {
    "addr:full":"Kircheng 14 Neufelden Ober\u00f6sterreich 4120",
    "addr:housenumber":"14",
    "addr:postcode":"4120",
    "addr:street":"Kircheng",
    "iso:country":"AT",
    "sg:address":"Kircheng 14",
    "sg:city":"Neufelden",
    "sg:orig_category":"Massagen",
    "sg:phone":"+43 7282 7670",
    "sg:postcode":"4120",
    "sg:province":"Ober\u00f6sterreich",
    "wof:name":"Massagefachinstitut und Sonnenstudio - Schalek Wolfgang KEG",
    "wof:placetype":"venue"
},
  "geometry": {"coordinates":[14.0007638931,48.4838294983],"type":"Point"}
}