{
  "type": "Feature",
  "properties": {
    "addr:full":"L\u00e4ndb\u00fchel 35 Kramsach Tirol 6233",
    "addr:housenumber":"35",
    "addr:postcode":"6233",
    "addr:street":"Laendbuehel;Tirol",
    "iso:country":"AT",
    "sg:address":"L\u00e4ndb\u00fchel 35",
    "sg:city":"Kramsach",
    "sg:orig_category":"Fliesen U Platten",
    "sg:phone":"+43 5337 62789",
    "sg:postcode":"6233",
    "sg:province":"Tirol",
    "wof:name":"Hechenblaickner KEG",
    "wof:placetype":"venue"
},
  "geometry": {"coordinates":[11.8835477829,47.4473342896],"type":"Point"}
}