{
  "type": "Feature",
  "properties": {
    "addr:full":"Matzneusiedl Gro\u00df-Enzersdorf Nieder\u00f6sterreich 2301",
    "addr:housenumber":"2301",
    "addr:street":"Niederoesterreich",
    "iso:country":"AT",
    "sg:address":"Matzneusiedl",
    "sg:city":"Gro\u00df-Enzersdorf",
    "sg:orig_category":"Gartenanlagen",
    "sg:phone":"+43 4322 1522540",
    "sg:postcode":"2301",
    "sg:province":"Nieder\u00f6sterreich",
    "sg:website":"zehetbauer.at",
    "wof:name":"Zehetbauer Fertigrasen",
    "wof:placetype":"venue"
},
  "geometry": {"coordinates":[16.5502796173,48.2014656067],"type":"Point"}
}