{
  "type": "Feature",
  "properties": {
    "iso:country":"AT",
    "sg:address":"Siemensstr 164",
    "sg:city":"Wien",
    "sg:orig_category":"Farben U Lacke / Erzeugung U Gro\u00c3\u0178handel",
    "sg:phone":"+43 4312 584690",
    "sg:postcode":"1210",
    "sg:province":"Wien",
    "wof:name":"FARBEN WAHL GmbH",
    "wof:placetype":"venue"
},
  "geometry": {"coordinates":[16.4333381653,48.2653236389],"type":"Point"}
}