{
  "type": "Feature",
  "properties": {
    "iso:country":"AT",
    "sg:address":"Werner-Storf-Str 3",
    "sg:city":"Reutte",
    "sg:orig_category":"Metallbe- U -Verarbeitung",
    "sg:phone":"+43 4356 7262886",
    "sg:postcode":"6600",
    "sg:province":"Tirol",
    "wof:name":"Eisen Blasy Reutte GesmbH",
    "wof:placetype":"venue"
},
  "geometry": {"coordinates":[10.7238092422,47.4937858582],"type":"Point"}
}