{
  "type": "Feature",
  "properties": {
    "iso:country":"AT",
    "sg:address":"Nr 234",
    "sg:city":"Stein an der Enns",
    "sg:orig_category":"Volksschulen",
    "sg:phone":"+43 4336 858111",
    "sg:postcode":"8961",
    "sg:province":"Steiermark",
    "wof:name":"Volksschule",
    "wof:placetype":"venue"
},
  "geometry": {"coordinates":[-85.00421142579999,43.8573417664],"type":"Point"}
}