{
  "type": "Feature",
  "properties": {
    "addr:full":"Wichnerg 26 Feldkirch Vorarlberg 6800",
    "addr:housenumber":"26",
    "addr:postcode":"6800",
    "addr:street":"Wichnerg",
    "iso:country":"AT",
    "sg:address":"Wichnerg 26",
    "sg:city":"Feldkirch",
    "sg:orig_category":"Non-Classified Establishments",
    "sg:phone":"+43 5522 77914",
    "sg:postcode":"6800",
    "sg:province":"Vorarlberg",
    "wof:name":"Evangelisches Pfarramt A und HB",
    "wof:placetype":"venue"
},
  "geometry": {"coordinates":[9.6011972427,47.238658905],"type":"Point"}
}