{
  "type": "Feature",
  "properties": {
    "iso:country":"AT",
    "sg:address":"Adolf Kolping-G 10",
    "sg:city":"Klagenfurt",
    "sg:orig_category":"Beratungsstellen",
    "sg:phone":"+43 463 543780",
    "sg:postcode":"9020",
    "sg:province":"K\u00e4rnten",
    "wof:name":"Ausl\u00e4nderberatung",
    "wof:placetype":"venue"
},
  "geometry": {"coordinates":[14.3046655655,46.6222343445],"type":"Point"}
}