{
  "type": "Feature",
  "properties": {
    "iso:country":"AT",
    "sg:address":"Firmianstr 1",
    "sg:city":"Salzburg",
    "sg:orig_category":"\u00c3\u201erzte / F Allgemeinmedizin",
    "sg:phone":"+43 662 829697",
    "sg:postcode":"5020",
    "sg:province":"Salzburg",
    "wof:name":"D\u00f6lzlm\u00fcller Clemens Dr",
    "wof:placetype":"venue"
},
  "geometry": {"coordinates":[13.0345897675,47.7874832153],"type":"Point"}
}