{
  "type": "Feature",
  "properties": {
    "addr:full":"Auerspergstr 1 Wien Wien 1080",
    "addr:housenumber":"1",
    "addr:postcode":"1080",
    "addr:street":"Auerspergstr",
    "iso:country":"AT",
    "sg:address":"Auerspergstr 1",
    "sg:city":"Wien",
    "sg:classifiers":[
        {
            "category":"Manufacturing",
            "subcategory":"Rubber & Plastics",
            "type":"Manufacturing & Wholesale Goods"
        }
    ],
    "sg:phone":"+43 1 4066174",
    "sg:postcode":"1080",
    "sg:province":"Wien",
    "sg:tags":[
        "safe",
        "u",
        "tresore"
    ],
    "wof:name":"Safe WertfachvermietungsgesmbH & Co KG",
    "wof:placetype":"venue"
},
  "geometry": {"coordinates":[16.3552188873,48.2072677612],"type":"Point"}
}