{
  "type": "Feature",
  "properties": {
    "addr:full":"Friedensstr 2 Salzburg Salzburg 5020",
    "addr:housenumber":"2",
    "addr:postcode":"5020",
    "addr:street":"Friedensstr;Salzburg",
    "iso:country":"AT",
    "sg:address":"Friedensstr 2",
    "sg:city":"Salzburg",
    "sg:orig_category":"Friseure U Frisiersalons",
    "sg:phone":"+43 664 2603437",
    "sg:postcode":"5020",
    "sg:province":"Salzburg",
    "wof:name":"K\u00fchleitner Manfred",
    "wof:placetype":"venue"
},
  "geometry": {"coordinates":[13.0661144257,47.7861442566],"type":"Point"}
}