{
  "type": "Feature",
  "properties": {
    "iso:country":"AT",
    "sg:address":"Stadtpl 19",
    "sg:city":"Rohrbach in Ober\u00f6sterreich",
    "sg:orig_category":"Tabaktrafiken",
    "sg:phone":"+43 7289 4317",
    "sg:postcode":"4150",
    "sg:province":"Ober\u00f6sterreich",
    "wof:name":"Kolenc Mathias",
    "wof:placetype":"venue"
},
  "geometry": {"coordinates":[13.9951534271,48.5746955872],"type":"Point"}
}