{
  "type": "Feature",
  "properties": {
    "iso:country":"AT",
    "sg:address":"Nr 132c/4",
    "sg:city":"Leibnitz",
    "sg:orig_category":"Glasdach- U Glaswandbau",
    "sg:phone":"+43 699 13245439",
    "sg:postcode":"8430",
    "sg:province":"Steiermark",
    "sg:website":"www.glasbau.at",
    "wof:name":"GAB Glas-Alu-Bau GesmbH",
    "wof:placetype":"venue"
},
  "geometry": {"coordinates":[15.5377645493,46.7811355591],"type":"Point"}
}