{
  "type": "Feature",
  "properties": {
    "iso:country":"AT",
    "sg:address":"Stadtpl 39",
    "sg:city":"Schwanenstadt",
    "sg:orig_category":"Raumgestaltung",
    "sg:phone":"+43 767375517",
    "sg:postcode":"4690",
    "sg:province":"Ober\u00f6sterreich",
    "wof:name":"Home & Garden - Wohnaccessiores - Inh Andrea Swoboda",
    "wof:placetype":"venue"
},
  "geometry": {"coordinates":[13.7758865356,48.0554962158],"type":"Point"}
}