{
  "type": "Feature",
  "properties": {
    "iso:country":"AT",
    "sg:address":"Am Anger 3",
    "sg:city":"Hirm",
    "sg:orig_category":"Feuerwehren",
    "sg:phone":"+43 2687 47520",
    "sg:postcode":"7024",
    "sg:province":"Burgenland",
    "wof:name":"Freiwillige Feuerwehr Hirm",
    "wof:placetype":"venue"
},
  "geometry": {"coordinates":[16.4579048157,47.7870597839],"type":"Point"}
}