{
  "type": "Feature",
  "properties": {
    "iso:country":"AT",
    "sg:address":"Liebenauer Stra\u00dfe 2-6",
    "sg:city":"Liebenau",
    "sg:orig_category":"Internet, Sonstige Internetdienstleistungen",
    "sg:postcode":"8041",
    "sg:province":"Steiermark",
    "sg:website":"http://www.grazforyou.at",
    "wof:name":"Erster Grazer Stadtserver",
    "wof:placetype":"venue"
},
  "geometry": {"coordinates":[15.4557781219,47.0470581055],"type":"Point"}
}