{
  "type": "Feature",
  "properties": {
    "addr:full":"Reininghausstr 15 Graz Steiermark 8020",
    "addr:housenumber":"15",
    "addr:postcode":"8020",
    "addr:street":"Reininghausstr",
    "iso:country":"AT",
    "sg:address":"Reininghausstr 15",
    "sg:city":"Graz",
    "sg:orig_category":"Lebensmittel / Erzeugung U Gro\u00c3\u0178handel",
    "sg:phone":"+43 4331 6577826",
    "sg:postcode":"8020",
    "sg:province":"Steiermark",
    "wof:name":"STAMAG Stadlauer Malzfabrik GesmbH",
    "wof:placetype":"venue"
},
  "geometry": {"coordinates":[15.4075460434,47.0648651123],"type":"Point"}
}