{
  "type": "Feature",
  "properties": {
    "addr:full":"Gudrunstr 138 Wien Wien 1100",
    "addr:housenumber":"138",
    "addr:postcode":"1100",
    "iso:country":"AT",
    "sg:address":"Gudrunstr 138",
    "sg:city":"Wien",
    "sg:orig_category":"Pensionen / Privatzimmer",
    "sg:phone":"+43 1 6048070",
    "sg:postcode":"1100",
    "sg:province":"Wien",
    "wof:name":"Caroline",
    "wof:placetype":"venue"
},
  "geometry": {"coordinates":[16.3721141815,48.178604126],"type":"Point"}
}