{
  "type": "Feature",
  "properties": {
    "addr:full":"Grazer Strasse 48 Langenwang Steiermark 8665",
    "addr:housenumber":"48",
    "addr:postcode":"8665",
    "addr:street":"Grazer Strasse",
    "iso:country":"AT",
    "sg:address":"Grazer Strasse 48",
    "sg:city":"Langenwang",
    "sg:classifiers":[
        {
            "category":"Home & Garden",
            "subcategory":"Household Appliances",
            "type":"Retail Goods"
        }
    ],
    "sg:phone":"+43 3854 2207",
    "sg:postcode":"8665",
    "sg:province":"Steiermark",
    "sg:tags":[
        "electric"
    ],
    "wof:name":"Heinz Stehrer",
    "wof:placetype":"venue"
},
  "geometry": {"coordinates":[15.61698246,47.5660667419],"type":"Point"}
}