{
  "type": "Feature",
  "properties": {
    "addr:full":"Altes Dorf 24 Raasdorf Nieder\u00f6sterreich 2281",
    "addr:housenumber":"24",
    "addr:postcode":"2281",
    "addr:street":"Altes Dorf",
    "iso:country":"AT",
    "sg:address":"Altes Dorf 24",
    "sg:city":"Raasdorf",
    "sg:orig_category":"Transportunternehmen",
    "sg:phone":"+43 2249 89225",
    "sg:postcode":"2281",
    "sg:province":"Nieder\u00f6sterreich",
    "wof:name":"Peleska OHG",
    "wof:placetype":"venue"
},
  "geometry": {"coordinates":[16.5660991669,48.2460517883],"type":"Point"}
}