{
  "type": "Feature",
  "properties": {
    "addr:full":"Karlspl 2 Wien Wien 1010",
    "addr:housenumber":"2",
    "addr:postcode":"1010",
    "addr:street":"Karlspl",
    "iso:country":"AT",
    "sg:address":"Karlspl 2",
    "sg:city":"Wien",
    "sg:orig_category":"Nachtclubs-Bars",
    "sg:phone":"+43 1 5050487",
    "sg:postcode":"1010",
    "sg:province":"Wien",
    "wof:name":"EAT-IT Bar",
    "wof:placetype":"venue"
},
  "geometry": {"coordinates":[16.3702583313,48.2007713318],"type":"Point"}
}