{
  "type": "Feature",
  "properties": {
    "addr:full":"Greiseneckerg 29 Wien Wien 1200",
    "addr:housenumber":"29",
    "addr:postcode":"1200",
    "addr:street":"Greiseneckerg",
    "iso:country":"AT",
    "sg:address":"Greiseneckerg 29",
    "sg:city":"Wien",
    "sg:orig_category":"Volksschulen",
    "sg:phone":"+43 1 3326340",
    "sg:postcode":"1200",
    "sg:province":"Wien",
    "wof:name":"Schulen d Stadt Wien - VS 2",
    "wof:placetype":"venue"
},
  "geometry": {"coordinates":[16.3739948273,48.2315483093],"type":"Point"}
}