{
  "type": "Feature",
  "properties": {
    "iso:country":"AT",
    "sg:address":"Tiefer Graben 7/9",
    "sg:city":"Wien",
    "sg:classifiers":[
        {
            "category":"Personal",
            "subcategory":"Hair Removal",
            "type":"Services"
        }
    ],
    "sg:phone":"+43 1 7187800",
    "sg:postcode":"1010",
    "sg:province":"Wien",
    "sg:tags":[
        "lotion"
    ],
    "sg:website":"rausch.ch",
    "wof:name":"Rausch Ges.m.b.H.",
    "wof:placetype":"venue"
},
  "geometry": {"coordinates":[16.3668403625,48.2117271423],"type":"Point"}
}