{
  "type": "Feature",
  "properties": {
    "addr:full":"Stelzhamerstrasse 25 Ampflwang im Hausruckwald Ober\u00f6sterreich 4843",
    "addr:housenumber":"25",
    "addr:postcode":"4843",
    "addr:street":"Stelzhamerstrasse",
    "iso:country":"AT",
    "sg:address":"Stelzhamerstrasse 25",
    "sg:city":"Ampflwang im Hausruckwald",
    "sg:classifiers":[
        {
            "category":"Home & Garden",
            "subcategory":"Furniture",
            "type":"Retail Goods"
        }
    ],
    "sg:phone":"+43 767522650",
    "sg:postcode":"4843",
    "sg:province":"Ober\u00f6sterreich",
    "sg:tags":[
        "room",
        "adolescent"
    ],
    "wof:name":"Rudolf Prenneis M\u00f6belwerk Ges.m.b.H. & Co KG",
    "wof:placetype":"venue"
},
  "geometry": {"coordinates":[13.5607681274,48.0945701599],"type":"Point"}
}