{
  "type": "Feature",
  "properties": {
    "iso:country":"AT",
    "sg:address":"Kirchengasse 21",
    "sg:city":"Wien",
    "sg:classifiers":[
        {
            "category":"Banks & Credit Unions",
            "subcategory":"Investment Brokerage",
            "type":"Services"
        }
    ],
    "sg:phone":"+43 1 5238389",
    "sg:postcode":"1070",
    "sg:province":"Wien",
    "sg:tags":[
        "delivery",
        "flower"
    ],
    "sg:website":"flowers.at",
    "wof:name":"FLEUR-BLUMENDIENST-NADERER",
    "wof:placetype":"venue"
},
  "geometry": {"coordinates":[16.3516273499,48.2019271851],"type":"Point"}
}