{
  "type": "Feature",
  "properties": {
    "iso:country":"AT",
    "sg:address":"Rathauspl 1",
    "sg:city":"Hornstein",
    "sg:orig_category":"Polizei U Gendarmerie",
    "sg:phone":"+43 4359 1331104",
    "sg:postcode":"7053",
    "sg:province":"Burgenland",
    "wof:name":"Gendarmerie",
    "wof:placetype":"venue"
},
  "geometry": {"coordinates":[16.4426708221,47.8794975281],"type":"Point"}
}