{
  "type": "Feature",
  "properties": {
    "iso:country":"AT",
    "sg:address":"Dorf 99",
    "sg:city":"Flaurling",
    "sg:orig_category":"Estriche",
    "sg:phone":"+43 4352 3888393",
    "sg:postcode":"6403",
    "sg:province":"Tirol",
    "wof:name":"PHP Fliesenestrich u Innenausbau",
    "wof:placetype":"venue"
},
  "geometry": {"coordinates":[11.1237049103,47.2917556763],"type":"Point"}
}