{
  "type": "Feature",
  "properties": {
    "addr:full":"Wiener Str 36 Pinkafeld Burgenland 7423",
    "addr:postcode":"7423",
    "iso:country":"AT",
    "sg:address":"Wiener Str 36",
    "sg:city":"Pinkafeld",
    "sg:orig_category":"Autohandel",
    "sg:phone":"+43 3357 424470",
    "sg:postcode":"7423",
    "sg:province":"Burgenland",
    "wof:name":"Autohaus Pahr",
    "wof:placetype":"venue"
},
  "geometry": {"coordinates":[16.1235980988,47.3771781921],"type":"Point"}
}