{
  "type": "Feature",
  "properties": {
    "iso:country":"AT",
    "sg:address":"Immervollstr 5-7",
    "sg:city":"Strasshof an der Nordbahn",
    "sg:orig_category":"Bauunternehmen",
    "sg:phone":"+43 4322 874527",
    "sg:postcode":"2231",
    "sg:province":"Nieder\u00f6sterreich",
    "wof:name":"Weidl Rudolf BaugesmbH",
    "wof:placetype":"venue"
},
  "geometry": {"coordinates":[16.6356678009,48.3150482178],"type":"Point"}
}