{
  "type": "Feature",
  "properties": {
    "addr:full":"Leitersdorf 17 Preding Steiermark 8504",
    "addr:housenumber":"17",
    "addr:postcode":"8504",
    "addr:street":"Leitersdorf",
    "iso:country":"AT",
    "sg:address":"Leitersdorf 17",
    "sg:city":"Preding",
    "sg:orig_category":"Transportunternehmen",
    "sg:phone":"+43 4366 43113970",
    "sg:postcode":"8504",
    "sg:province":"Steiermark",
    "wof:name":"Klement Transport KEG",
    "wof:placetype":"venue"
},
  "geometry": {"coordinates":[15.4067401886,46.8597869873],"type":"Point"}
}