{
  "type": "Feature",
  "properties": {
    "iso:country":"AT",
    "sg:address":"Schulstr 8",
    "sg:city":"Niklasdorf",
    "sg:orig_category":"Volksschulen",
    "sg:phone":"+43 3842 81306",
    "sg:postcode":"8712",
    "sg:province":"Steiermark",
    "wof:name":"Volksschule",
    "wof:placetype":"venue"
},
  "geometry": {"coordinates":[15.1616764069,47.3973007202],"type":"Point"}
}