{
  "type": "Feature",
  "properties": {
    "addr:full":"Greifensteiner Str 94 St. Andr\u00e4-W\u00f6rdern Nieder\u00f6sterreich 3423",
    "addr:housenumber":"94",
    "addr:postcode":"3423",
    "addr:street":"Str",
    "iso:country":"AT",
    "sg:address":"Greifensteiner Str 94",
    "sg:city":"St. Andr\u00e4-W\u00f6rdern",
    "sg:orig_category":"Drehereien",
    "sg:phone":"+43 4322 4232268",
    "sg:postcode":"3423",
    "sg:province":"Nieder\u00f6sterreich",
    "wof:name":"Prankl Roman",
    "wof:placetype":"venue"
},
  "geometry": {"coordinates":[16.2173938751,48.3273277283],"type":"Point"}
}