{
  "type": "Feature",
  "properties": {
    "addr:full":"Hauptstr 100-102 Klosterneuburg Nieder\u00f6sterreich 3400",
    "addr:housenumber":"100-102",
    "addr:postcode":"3400",
    "addr:street":"Hauptstr;Niederoesterreich",
    "iso:country":"AT",
    "sg:address":"Hauptstr 100-102",
    "sg:city":"Klosterneuburg",
    "sg:orig_category":"Autobusunternehmen",
    "sg:phone":"+43 2243 83380",
    "sg:postcode":"3400",
    "sg:province":"Nieder\u00f6sterreich",
    "wof:name":"Kolda GesmbH & Dr Richard KG",
    "wof:placetype":"venue"
},
  "geometry": {"coordinates":[16.2812728882,48.3090934753],"type":"Point"}
}