{
  "type": "Feature",
  "properties": {
    "addr:full":"K\u00e4rntner Strasse 2 Neumarkt in Steiermark Steiermark 8820",
    "addr:housenumber":"2",
    "addr:postcode":"8820",
    "addr:street":"Kaerntner Strasse",
    "iso:country":"AT",
    "sg:address":"K\u00e4rntner Strasse 2",
    "sg:city":"Neumarkt in Steiermark",
    "sg:classifiers":[
        {
            "category":"Real Estate",
            "subcategory":"Architect",
            "type":"Services"
        }
    ],
    "sg:phone":"+43 3584 2165",
    "sg:postcode":"8820",
    "sg:province":"Steiermark",
    "sg:tags":[
        "interior",
        "decoration"
    ],
    "wof:name":"Hubert Pobatschnig",
    "wof:placetype":"venue"
},
  "geometry": {"coordinates":[14.4293413162,47.0666313171],"type":"Point"}
}