{
  "type": "Feature",
  "properties": {
    "addr:full":"Viaduktbogen 117 Innsbruck Tirol 6020",
    "addr:housenumber":"117",
    "addr:postcode":"6020",
    "addr:street":"Viaduktbogen;Tirol",
    "iso:country":"AT",
    "sg:address":"Viaduktbogen 117",
    "sg:city":"Innsbruck",
    "sg:orig_category":"Fotoausarbeitungen",
    "sg:phone":"+43 512 586454",
    "sg:postcode":"6020",
    "sg:province":"Tirol",
    "wof:name":"Digital Express Inh Cornelia Schlesinger",
    "wof:placetype":"venue"
},
  "geometry": {"coordinates":[11.4131479263,47.2771835327],"type":"Point"}
}