{
  "type": "Feature",
  "properties": {
    "addr:full":"Porzellangasse 9 Wien Wien 1090",
    "addr:housenumber":"9",
    "addr:postcode":"1090",
    "addr:street":"Porzellangasse",
    "iso:country":"AT",
    "sg:address":"Porzellangasse 9",
    "sg:city":"Wien",
    "sg:classifiers":[
        {
            "category":"Utilities",
            "subcategory":"Natural Gas",
            "type":"Services"
        }
    ],
    "sg:phone":"+43 1 3191382",
    "sg:postcode":"1090",
    "sg:province":"Wien",
    "sg:tags":[
        "ceiling",
        "lamp"
    ],
    "sg:website":"gordis.at",
    "wof:name":"Gordis KG Ley & Co",
    "wof:placetype":"venue"
},
  "geometry": {"coordinates":[16.3624210358,48.2193565369],"type":"Point"}
}