{
  "type": "Feature",
  "properties": {
    "iso:country":"AT",
    "sg:address":"Hernalser Hauptstr 151",
    "sg:city":"Wien",
    "sg:orig_category":"Handelsagenturen",
    "sg:phone":"+43 1 4899374",
    "sg:postcode":"1170",
    "sg:province":"Wien",
    "wof:name":"Formanek Alfred",
    "wof:placetype":"venue"
},
  "geometry": {"coordinates":[16.318819046,48.2221565247],"type":"Point"}
}