{
  "type": "Feature",
  "properties": {
    "addr:full":"W\u00e4hringer Str 64 Wien Wien 1090",
    "addr:postcode":"1090",
    "addr:street":"Str 64",
    "iso:country":"AT",
    "sg:address":"W\u00e4hringer Str 64",
    "sg:city":"Wien",
    "sg:orig_category":"Restaurants: Persisch",
    "sg:phone":"+43 1 3109450",
    "sg:postcode":"1090",
    "sg:province":"Wien",
    "wof:name":"Hatam",
    "wof:placetype":"venue"
},
  "geometry": {"coordinates":[16.3523864746,48.2230148315],"type":"Point"}
}