{
  "type": "Feature",
  "properties": {
    "addr:full":"Siebenbrunnengasse 10 Wien Wien 1050",
    "addr:housenumber":"10",
    "addr:postcode":"1050",
    "addr:street":"Siebenbrunnengasse",
    "iso:country":"AT",
    "sg:address":"Siebenbrunnengasse 10",
    "sg:city":"Wien",
    "sg:classifiers":[
        {
            "category":"Building & Trades",
            "subcategory":"Plumbing",
            "type":"Services"
        }
    ],
    "sg:phone":"+43 1 5444713",
    "sg:postcode":"1050",
    "sg:province":"Wien",
    "sg:tags":[
        "supraregional",
        "gas"
    ],
    "wof:name":"Otto Ullrich",
    "wof:placetype":"venue"
},
  "geometry": {"coordinates":[16.3600826263,48.1882247925],"type":"Point"}
}