{
  "type": "Feature",
  "properties": {
    "addr:full":"St. Zeno 11 Serfaus Tirol 6534",
    "addr:housenumber":"11",
    "addr:postcode":"6534",
    "addr:street":"St. Zeno;Tirol",
    "iso:country":"AT",
    "sg:address":"St. Zeno 11",
    "sg:city":"Serfaus",
    "sg:orig_category":"Pensionen / Privatzimmer",
    "sg:phone":"+43 5476 6376",
    "sg:postcode":"6534",
    "sg:province":"Tirol",
    "wof:name":"Haus Aurora",
    "wof:placetype":"venue"
},
  "geometry": {"coordinates":[10.6006298065,47.0379142761],"type":"Point"}
}