{
  "type": "Feature",
  "properties": {
    "iso:country":"AT",
    "sg:address":"Johann-Wolf-Str 7/7",
    "sg:city":"Salzburg",
    "sg:orig_category":"Psychotherapie",
    "sg:phone":"+43 4366 2844236",
    "sg:postcode":"5020",
    "sg:province":"Salzburg",
    "wof:name":"Sauer Joachim Univ Prof Dr",
    "wof:placetype":"venue"
},
  "geometry": {"coordinates":[13.0360631943,47.7966880798],"type":"Point"}
}