{
  "type": "Feature",
  "properties": {
    "iso:country":"AT",
    "sg:address":"Durchla\u00dfstr 4",
    "sg:city":"Klagenfurt",
    "sg:orig_category":"Bankomat-Standorte",
    "sg:phone":"+43 463 58580",
    "sg:postcode":"9020",
    "sg:province":"K\u00e4rnten",
    "wof:name":"Bankomat d BKS-Bank f K\u00e4rnten und Steiermark",
    "wof:placetype":"venue"
},
  "geometry": {"coordinates":[14.3133525848,46.6361198425],"type":"Point"}
}