{
  "type": "Feature",
  "properties": {
    "addr:full":"Hollerg 51 Wien Wien 1150",
    "addr:housenumber":"51",
    "addr:postcode":"1150",
    "addr:street":"Hollerg",
    "iso:country":"AT",
    "sg:address":"Hollerg 51",
    "sg:city":"Wien",
    "sg:orig_category":"Maler, Anstreicher U Lackierer",
    "sg:phone":"+43 1 8940044",
    "sg:postcode":"1150",
    "sg:province":"Wien",
    "wof:name":"Gierer Leopold",
    "wof:placetype":"venue"
},
  "geometry": {"coordinates":[16.3237724304,48.1898155212],"type":"Point"}
}