{
  "type": "Feature",
  "properties": {
    "addr:full":"Brodtischg 32 Wiener Neustadt Nieder\u00f6sterreich 2700",
    "addr:housenumber":"32",
    "addr:postcode":"2700",
    "addr:street":"Brodtischg",
    "iso:country":"AT",
    "sg:address":"Brodtischg 32",
    "sg:city":"Wiener Neustadt",
    "sg:orig_category":"Sonnenschutzanlagen",
    "sg:phone":"+43 2622 61474",
    "sg:postcode":"2700",
    "sg:province":"Nieder\u00f6sterreich",
    "wof:name":"GRUBER",
    "wof:placetype":"venue"
},
  "geometry": {"coordinates":[16.2424316406,47.8108901978],"type":"Point"}
}