{
  "type": "Feature",
  "properties": {
    "addr:full":"Strandpl 1 Podersdorf am See Burgenland 7141",
    "addr:housenumber":"1",
    "addr:postcode":"7141",
    "addr:street":"Strandpl",
    "iso:country":"AT",
    "sg:address":"Strandpl 1",
    "sg:city":"Podersdorf am See",
    "sg:classifiers":[
        {
            "category":"Travel",
            "subcategory":"Hotels & Motels",
            "type":"Entertainment"
        }
    ],
    "sg:phone":"+43 2177 24150",
    "sg:postcode":"7141",
    "sg:province":"Burgenland",
    "wof:name":"Haus Attila",
    "wof:placetype":"venue"
},
  "geometry": {"coordinates":[16.8301315308,47.8585090637],"type":"Point"}
}