{
  "type": "Feature",
  "properties": {
    "addr:full":"Juns 585 Tux Tirol 6293",
    "addr:housenumber":"585",
    "addr:postcode":"6293",
    "addr:street":"Juns;Tirol",
    "iso:country":"AT",
    "sg:address":"Juns 585",
    "sg:city":"Tux",
    "sg:orig_category":"Appartements / Ferienwohnungen",
    "sg:phone":"+43 4352 8787609",
    "sg:postcode":"6293",
    "sg:province":"Tirol",
    "wof:name":"Haus Angerl",
    "wof:placetype":"venue"
},
  "geometry": {"coordinates":[11.6970243454,47.1270294189],"type":"Point"}
}