{
  "type": "Feature",
  "properties": {
    "addr:full":"Karl-von-Lutterotti-Str 10 Imst Tirol 6460",
    "addr:housenumber":"10",
    "addr:postcode":"6460",
    "addr:street":"Karl-Von-Lutterotti-Str;Tirol",
    "iso:country":"AT",
    "sg:address":"Karl-von-Lutterotti-Str 10",
    "sg:city":"Imst",
    "sg:orig_category":"Ingenieurkonsulenten / Zivilingenieure",
    "sg:phone":"+43 4354 1264227",
    "sg:postcode":"6460",
    "sg:province":"Tirol",
    "wof:name":"Friedle Theodor Erich Dipl-Ing",
    "wof:placetype":"venue"
},
  "geometry": {"coordinates":[10.7383928299,47.2352714539],"type":"Point"}
}