{
  "type": "Feature",
  "properties": {
    "addr:full":"Johann-Weghuber-Str 4 Biedermannsdorf Nieder\u00f6sterreich 2362",
    "addr:housenumber":"4",
    "addr:postcode":"2362",
    "addr:street":"Johann-Weghuber-Str",
    "iso:country":"AT",
    "sg:address":"Johann-Weghuber-Str 4",
    "sg:city":"Biedermannsdorf",
    "sg:orig_category":"Ingenieurkonsulenten / Zivilingenieure",
    "sg:phone":"+43 2236 71265",
    "sg:postcode":"2362",
    "sg:province":"Nieder\u00f6sterreich",
    "wof:name":"Usrael Gerhard DI Dr techn",
    "wof:placetype":"venue"
},
  "geometry": {"coordinates":[16.3508987427,48.0873374939],"type":"Point"}
}