{
  "type": "Feature",
  "properties": {
    "addr:full":"Stephanspl 6 Wien Wien 1010",
    "addr:housenumber":"6",
    "addr:postcode":"1010",
    "addr:street":"Stephanspl",
    "iso:country":"AT",
    "sg:address":"Stephanspl 6",
    "sg:city":"Wien",
    "sg:orig_category":"Handschuhe",
    "sg:phone":"+43 4315 135985",
    "sg:postcode":"1010",
    "sg:province":"Wien",
    "wof:name":"HANDSCHUHE R.J. BOETTNER",
    "wof:placetype":"venue"
},
  "geometry": {"coordinates":[16.3738803864,48.208820343],"type":"Point"}
}