{
  "type": "Feature",
  "properties": {
    "addr:full":"Reumannpl 15 Wien Wien 1100",
    "addr:housenumber":"15",
    "addr:postcode":"1100",
    "addr:street":"Reumannpl",
    "iso:country":"AT",
    "sg:address":"Reumannpl 15",
    "sg:city":"Wien",
    "sg:orig_category":"Friseure U Frisiersalons",
    "sg:phone":"+43 4316 042531",
    "sg:postcode":"1100",
    "sg:province":"Wien",
    "sg:website":"strassl.at",
    "wof:name":"Intercoiffeur Strassl Verwaltung GmbH",
    "wof:placetype":"venue"
},
  "geometry": {"coordinates":[16.3774662018,48.1743621826],"type":"Point"}
}