{
  "type": "Feature",
  "properties": {
    "addr:full":"Mitterfeldstrasse 6 Wels Ober\u00f6sterreich 4600",
    "addr:housenumber":"6",
    "addr:postcode":"4600",
    "addr:street":"Mitterfeldstrasse;Oberoesterreich",
    "iso:country":"AT",
    "sg:address":"Mitterfeldstrasse 6",
    "sg:city":"Wels",
    "sg:classifiers":[
        {
            "category":"Home & Garden",
            "subcategory":"Building Materials",
            "type":"Retail Goods"
        }
    ],
    "sg:phone":"+43 7242 2072820",
    "sg:postcode":"4600",
    "sg:province":"Ober\u00f6sterreich",
    "sg:tags":[
        "tile",
        "ceramic"
    ],
    "sg:website":"ilmaestro.com",
    "wof:name":"MAESTRO Handwerk & Partner Ges.m.b.H.",
    "wof:placetype":"venue"
},
  "geometry": {"coordinates":[14.0262908936,48.1857147217],"type":"Point"}
}