{
  "type": "Feature",
  "properties": {
    "addr:full":"Friedhofstr 4 Linz Ober\u00f6sterreich 4020",
    "addr:housenumber":"4",
    "addr:postcode":"4020",
    "addr:street":"Friedhofstr",
    "iso:country":"AT",
    "sg:address":"Friedhofstr 4",
    "sg:city":"Linz",
    "sg:orig_category":"Solartechnik",
    "sg:phone":"+43 732 6503910",
    "sg:postcode":"4020",
    "sg:province":"Ober\u00f6sterreich",
    "wof:name":"Inocal W\u00e4rmetechnik GesmbH",
    "wof:placetype":"venue"
},
  "geometry": {"coordinates":[14.297170639,48.2949256897],"type":"Point"}
}