{
  "type": "Feature",
  "properties": {
    "addr:full":"Vogelweiderstr 55 Salzburg Salzburg 5020",
    "addr:housenumber":"55",
    "addr:postcode":"5020",
    "addr:street":"Vogelweiderstr;Salzburg",
    "iso:country":"AT",
    "sg:address":"Vogelweiderstr 55",
    "sg:city":"Salzburg",
    "sg:orig_category":"Bankomat-Standorte",
    "sg:phone":"+43 662 8812380",
    "sg:postcode":"5020",
    "sg:province":"Salzburg",
    "wof:name":"Bankomat d Salzburger Landes-Hypothekenbank AG",
    "wof:placetype":"venue"
},
  "geometry": {"coordinates":[13.0539007187,47.8130302429],"type":"Point"}
}