{
  "type": "Feature",
  "properties": {
    "iso:country":"AT",
    "sg:address":"Betriebsstr. 14",
    "sg:classifiers":[
        {
            "category":"Manufacturing",
            "subcategory":"Glass & Minerals",
            "type":"Manufacturing & Wholesale Goods"
        }
    ],
    "sg:phone":"+43 4327 52700800",
    "sg:postcode":"3682",
    "wof:name":"ALFRED WINTER GESMBH",
    "wof:placetype":"venue"
},
  "geometry": {"coordinates":[15.2713851929,48.2396278381],"type":"Point"}
}