{
  "type": "Feature",
  "properties": {
    "addr:full":"Hauptpl 7 F\u00fcrstenfeld Steiermark 8280",
    "addr:housenumber":"7",
    "addr:postcode":"8280",
    "addr:street":"Hauptpl",
    "iso:country":"AT",
    "sg:address":"Hauptpl 7",
    "sg:city":"F\u00fcrstenfeld",
    "sg:orig_category":"Fernsehservice",
    "sg:phone":"+43 3382 54548",
    "sg:postcode":"8280",
    "sg:province":"Steiermark",
    "wof:name":"Stessl Roland",
    "wof:placetype":"venue"
},
  "geometry": {"coordinates":[16.0768013,47.0514183044],"type":"Point"}
}