{
  "type": "Feature",
  "properties": {
    "addr:full":"Praterstr 44-46 Wien Wien 1020",
    "addr:postcode":"44-46;1020",
    "iso:country":"AT",
    "sg:address":"Praterstr 44-46",
    "sg:city":"Wien",
    "sg:orig_category":"Fotoapparate U -Artikel / Einzelhandel",
    "sg:phone":"+43 4312 1655800",
    "sg:postcode":"1020",
    "sg:province":"Wien",
    "wof:name":"Hartlauer HandelsgesmbH",
    "wof:placetype":"venue"
},
  "geometry": {"coordinates":[16.3859386444,48.2153244019],"type":"Point"}
}