{
  "type": "Feature",
  "properties": {
    "addr:full":"Buchenstr. 11  Pregarten Ober\u00f6sterreich 4230",
    "addr:housenumber":"11",
    "addr:postcode":"4230",
    "addr:street":"Buchenstr.",
    "iso:country":"AT",
    "sg:address":"Buchenstr. 11 ",
    "sg:city":"Pregarten",
    "sg:classifiers":[
        {
            "category":"Manufacturing",
            "subcategory":"Metals",
            "type":"Manufacturing & Wholesale Goods"
        }
    ],
    "sg:phone":"+43 4372 363663",
    "sg:postcode":"4230",
    "sg:province":"Ober\u00f6sterreich",
    "sg:tags":[
        "metallurgy",
        "metalworking"
    ],
    "wof:name":"EDEH BAU & M\u00d6BELTISCHLEREI GMBH",
    "wof:placetype":"venue"
},
  "geometry": {"coordinates":[14.5377531052,48.3500137329],"type":"Point"}
}