{
  "type": "Feature",
  "properties": {
    "addr:full":"Schulstrasse 3  Maishofen Salzburg 5751",
    "addr:housenumber":"3",
    "addr:postcode":"5751",
    "addr:street":"Schulstrasse;Salzburg",
    "iso:country":"AT",
    "sg:address":"Schulstrasse 3 ",
    "sg:city":"Maishofen",
    "sg:classifiers":[
        {
            "category":"Government",
            "subcategory":"Fire Station",
            "type":"Public Place"
        }
    ],
    "sg:phone":"+43 6542 68507",
    "sg:postcode":"5751",
    "sg:province":"Salzburg",
    "sg:tags":[
        "supraregional",
        "plant",
        "installation",
        "heating"
    ],
    "wof:name":"Bruno Dick Gas- Wasser- Heizung GesmbH & Co KG",
    "wof:placetype":"venue"
},
  "geometry": {"coordinates":[12.8083095551,47.3621330261],"type":"Point"}
}