{
  "type": "Feature",
  "properties": {
    "addr:full":"Eigenheimstrasse 13 Leonding Ober\u00f6sterreich 4060",
    "addr:housenumber":"13",
    "addr:postcode":"4060",
    "addr:street":"Eigenheimstrasse",
    "iso:country":"AT",
    "sg:address":"Eigenheimstrasse 13",
    "sg:city":"Leonding",
    "sg:classifiers":[
        {
            "category":"Professional",
            "subcategory":"Advertising",
            "type":"Services"
        }
    ],
    "sg:phone":"+43 732 6817340",
    "sg:postcode":"4060",
    "sg:province":"Ober\u00f6sterreich",
    "sg:tags":[
        "agency"
    ],
    "sg:website":"tanczos.at",
    "wof:name":"Tanczos KEG",
    "wof:placetype":"venue"
},
  "geometry": {"coordinates":[14.2569742203,48.2452087402],"type":"Point"}
}