{
  "type": "Feature",
  "properties": {
    "iso:country":"AT",
    "sg:address":"Bahnhofstr 1",
    "sg:city":"Ried im Innkreis",
    "sg:orig_category":"Friseure U Frisiersalons",
    "sg:phone":"+43 4377 5282124",
    "sg:postcode":"4910",
    "sg:province":"Ober\u00f6sterreich",
    "wof:name":"Kopp Dietmar",
    "wof:placetype":"venue"
},
  "geometry": {"coordinates":[13.4874000549,48.2081718445],"type":"Point"}
}