{
  "type": "Feature",
  "properties": {
    "addr:full":"Schmiedkreuzstr 3 Salzburg Salzburg 5020",
    "addr:housenumber":"3",
    "addr:postcode":"5020",
    "addr:street":"Schmiedkreuzstr;Salzburg",
    "iso:country":"AT",
    "sg:address":"Schmiedkreuzstr 3",
    "sg:city":"Salzburg",
    "sg:orig_category":"Schmiermittel",
    "sg:phone":"+43 4366 2442582",
    "sg:postcode":"5020",
    "sg:province":"Salzburg",
    "wof:name":"CIMCOOL - Europe - Milacron",
    "wof:placetype":"venue"
},
  "geometry": {"coordinates":[13.0057039261,47.8269195557],"type":"Point"}
}