{
  "type": "Feature",
  "properties": {
    "addr:full":"Carinthiastr 73 Schwarzau am Steinfeld Nieder\u00f6sterreich 2625",
    "addr:housenumber":"73",
    "addr:postcode":"2625",
    "addr:street":"Carinthiastr",
    "iso:country":"AT",
    "sg:address":"Carinthiastr 73",
    "sg:city":"Schwarzau am Steinfeld",
    "sg:orig_category":"Stahlbau",
    "sg:phone":"+43 4326 2783475",
    "sg:postcode":"2625",
    "sg:province":"Nieder\u00f6sterreich",
    "wof:name":"Stahlbau Jammertzheim",
    "wof:placetype":"venue"
},
  "geometry": {"coordinates":[16.1680202484,47.7320480347],"type":"Point"}
}