{
  "type": "Feature",
  "properties": {
    "addr:full":"Hauptstrasse 22 Gloggnitz Nieder\u00f6sterreich 2640",
    "addr:housenumber":"22",
    "addr:postcode":"2640",
    "addr:street":"Hauptstrasse",
    "iso:country":"AT",
    "sg:address":"Hauptstrasse 22",
    "sg:city":"Gloggnitz",
    "sg:classifiers":[
        {
            "category":"Manufacturing",
            "subcategory":"Glass & Minerals",
            "type":"Manufacturing & Wholesale Goods"
        }
    ],
    "sg:phone":"+43 2662 42275",
    "sg:postcode":"2640",
    "sg:province":"Nieder\u00f6sterreich",
    "sg:tags":[
        "decoration",
        "article",
        "mirror"
    ],
    "sg:website":"glasrigler.at",
    "wof:name":"Helmut Rigler GmbH",
    "wof:placetype":"venue"
},
  "geometry": {"coordinates":[15.9363250732,47.6761932373],"type":"Point"}
}