{
  "type": "Feature",
  "properties": {
    "addr:full":"Moosg 188 Strobl Salzburg 5350",
    "addr:housenumber":"188",
    "addr:postcode":"5350",
    "addr:street":"Strobl Salzburg",
    "iso:country":"AT",
    "sg:address":"Moosg 188",
    "sg:city":"Strobl",
    "sg:orig_category":"Pensionen / Privatzimmer",
    "sg:phone":"+43 6137 7249",
    "sg:postcode":"5350",
    "sg:province":"Salzburg",
    "wof:name":"Kasberger Fr\u00fchst\u00fcckspension",
    "wof:placetype":"venue"
},
  "geometry": {"coordinates":[13.4822740555,47.719165802],"type":"Point"}
}