{
  "type": "Feature",
  "properties": {
    "addr:full":"Fieberbrunner Str 35 St. Johann in Tirol Tirol 6380",
    "addr:housenumber":"35",
    "addr:postcode":"johann;6380",
    "addr:street":"Str;Tirol",
    "iso:country":"AT",
    "sg:address":"Fieberbrunner Str 35",
    "sg:city":"St. Johann in Tirol",
    "sg:orig_category":"Autohandel",
    "sg:phone":"+43 5352 62417",
    "sg:postcode":"6380",
    "sg:province":"Tirol",
    "wof:name":"Reiter Fritz GmbH & Co KG",
    "wof:placetype":"venue"
},
  "geometry": {"coordinates":[12.4371671677,47.5200157166],"type":"Point"}
}