{
  "type": "Feature",
  "properties": {
    "addr:full":"Untere Ortsstr 30 Furth Nieder\u00f6sterreich 3511",
    "addr:housenumber":"30",
    "addr:postcode":"3511",
    "addr:street":"Untere Ortsstr",
    "iso:country":"AT",
    "sg:address":"Untere Ortsstr 30",
    "sg:city":"Furth",
    "sg:orig_category":"Installationsunternehmen",
    "sg:phone":"+43 4327 392595",
    "sg:postcode":"3511",
    "sg:province":"Nieder\u00f6sterreich",
    "sg:website":"heizungsberater.at",
    "wof:name":"SEV Gas-Wasser-Heizungsinstallationen u Solarenergie-Verwertung GesmbH",
    "wof:placetype":"venue"
},
  "geometry": {"coordinates":[15.6125049591,48.374168396],"type":"Point"}
}