{
  "type": "Feature",
  "properties": {
    "addr:full":"Fischlstr 59 Klagenfurt K\u00e4rnten 9020",
    "addr:housenumber":"59",
    "addr:postcode":"9020",
    "addr:street":"Fischlstr;Kaernten",
    "iso:country":"AT",
    "sg:address":"Fischlstr 59",
    "sg:city":"Klagenfurt",
    "sg:orig_category":"Non-Classified Establishments",
    "sg:phone":"+43 463 37005",
    "sg:postcode":"9020",
    "sg:province":"K\u00e4rnten",
    "wof:name":"Pfarramt St Modestus",
    "wof:placetype":"venue"
},
  "geometry": {"coordinates":[14.3331241608,46.6207199097],"type":"Point"}
}