{
  "type": "Feature",
  "properties": {
    "iso:country":"AT",
    "sg:address":"Bethlehemstr 3",
    "sg:city":"Linz",
    "sg:orig_category":"Direktmarketing, Telefonmarketing, Markt- U Meinungsforschung, Marketingberatung, Call Center",
    "sg:phone":"+43 732 7822770",
    "sg:postcode":"4020",
    "sg:province":"Ober\u00f6sterreich",
    "wof:name":"TCS Direkt Marketing GmbH",
    "wof:placetype":"venue"
},
  "geometry": {"coordinates":[14.2899198532,48.3035545349],"type":"Point"}
}