{
  "type": "Feature",
  "properties": {
    "addr:full":"Erdbergstr 46/1 Wien Wien 1030",
    "addr:housenumber":"46 / 1",
    "addr:postcode":"1030",
    "addr:street":"Erdbergstr",
    "iso:country":"AT",
    "sg:address":"Erdbergstr 46/1",
    "sg:city":"Wien",
    "sg:orig_category":"Tauchsportartikel",
    "sg:phone":"+43 1 9132083",
    "sg:postcode":"1030",
    "sg:province":"Wien",
    "wof:name":"UMEX A Gerstl Tauchsportartikel KEG",
    "wof:placetype":"venue"
},
  "geometry": {"coordinates":[16.3966331482,48.2013320923],"type":"Point"}
}