{
  "type": "Feature",
  "properties": {
    "addr:full":"Von-Klenze-Weg 5 Mittelberg Vorarlberg 6993",
    "addr:housenumber":"5",
    "addr:postcode":"6993",
    "addr:street":"Von-Klenze-Weg",
    "iso:country":"AT",
    "sg:address":"Von-Klenze-Weg 5",
    "sg:city":"Mittelberg",
    "sg:classifiers":[
        {
            "category":"Travel",
            "subcategory":"Hotels & Motels",
            "type":"Entertainment"
        }
    ],
    "sg:phone":"+43 4355 1755510",
    "sg:postcode":"6993",
    "sg:province":"Vorarlberg",
    "wof:name":"Happy Austria",
    "wof:placetype":"venue"
},
  "geometry": {"coordinates":[10.162815094,47.3339767456],"type":"Point"}
}