{
  "type": "Feature",
  "properties": {
    "iso:country":"AT",
    "sg:address":"Liechtensteinstr 89",
    "sg:city":"Wien",
    "sg:classifiers":[
        {
            "category":"Travel",
            "subcategory":"Hotels & Motels",
            "type":"Entertainment"
        }
    ],
    "sg:phone":"+43 1 31735080",
    "sg:postcode":"1090",
    "sg:province":"Wien",
    "wof:name":"Austria Trend Hotel Albatros",
    "wof:placetype":"venue"
},
  "geometry": {"coordinates":[16.3563766479,48.2266349792],"type":"Point"}
}