{
  "type": "Feature",
  "properties": {
    "addr:full":"Au 17 Strengberg Nieder\u00f6sterreich 3314",
    "addr:housenumber":"17",
    "addr:postcode":"3314",
    "addr:street":"Au",
    "iso:country":"AT",
    "sg:address":"Au 17",
    "sg:city":"Strengberg",
    "sg:orig_category":"Industrie, Elektronik U Elektrik",
    "sg:phone":"+43 7432",
    "sg:postcode":"3314",
    "sg:province":"Nieder\u00f6sterreich",
    "sg:website":"http://www.igp-generatoren.co.at",
    "wof:name":"IGP Generatoren",
    "wof:placetype":"venue"
},
  "geometry": {"coordinates":[14.6273193359,48.1756401062],"type":"Point"}
}