{
  "type": "Feature",
  "properties": {
    "iso:country":"AT",
    "sg:address":"Eduard-R\u00f6sch-Str 58",
    "sg:city":"Stockerau",
    "sg:orig_category":"Transportunternehmen",
    "sg:phone":"+43 2266 62775",
    "sg:postcode":"2000",
    "sg:province":"Nieder\u00f6sterreich",
    "wof:name":"Seidl Franz - Int Sch\u00fcttguttransporte",
    "wof:placetype":"venue"
},
  "geometry": {"coordinates":[16.2272567749,48.3868560791],"type":"Point"}
}