{
  "type": "Feature",
  "properties": {
    "addr:full":"Authaler Weg 19 Zeltweg Steiermark 8740",
    "addr:housenumber":"19",
    "addr:postcode":"8740",
    "addr:street":"Authaler Weg",
    "iso:country":"AT",
    "sg:address":"Authaler Weg 19",
    "sg:city":"Zeltweg",
    "sg:orig_category":"Transportunternehmen",
    "sg:phone":"+43 3577 81546",
    "sg:postcode":"8740",
    "sg:province":"Steiermark",
    "wof:name":"Steiner Gerhard",
    "wof:placetype":"venue"
},
  "geometry": {"coordinates":[14.751789093,47.1834564209],"type":"Point"}
}