{
  "type": "Feature",
  "properties": {
    "addr:full":"Kirchpl 30 Ehrwald Tirol 6632",
    "addr:housenumber":"30",
    "addr:postcode":"6632",
    "addr:street":"Kirchpl;Tirol",
    "iso:country":"AT",
    "sg:address":"Kirchpl 30",
    "sg:city":"Ehrwald",
    "sg:orig_category":"Non-Classified Establishments",
    "sg:phone":"+43 5673 2360",
    "sg:postcode":"6632",
    "sg:province":"Tirol",
    "wof:name":"Pfarramt",
    "wof:placetype":"venue"
},
  "geometry": {"coordinates":[10.9194555283,47.3988609314],"type":"Point"}
}