{
  "type": "Feature",
  "properties": {
    "addr:full":"Silvrettastr 258 St. Gallenkirch Vorarlberg 6791",
    "addr:housenumber":"258",
    "addr:postcode":"6791",
    "addr:street":"St. Gallenkirch",
    "iso:country":"AT",
    "sg:address":"Silvrettastr 258",
    "sg:city":"St. Gallenkirch",
    "sg:orig_category":"Pensionen / Privatzimmer",
    "sg:phone":"+43 4355 5762610",
    "sg:postcode":"6791",
    "sg:province":"Vorarlberg",
    "wof:name":"Pension Vall\u00fcla",
    "wof:placetype":"venue"
},
  "geometry": {"coordinates":[9.9449863434,47.0390815735],"type":"Point"}
}