{
  "type": "Feature",
  "properties": {
    "iso:country":"AT",
    "sg:address":"Neulinggasse 29/7",
    "sg:city":"Wien",
    "sg:classifiers":[
        {
            "category":"Government",
            "subcategory":"Fire Station",
            "type":"Public Place"
        }
    ],
    "sg:phone":"+43 1 7107633",
    "sg:postcode":"1030",
    "sg:province":"Wien",
    "sg:tags":[
        "steel",
        "made",
        "component",
        "forged"
    ],
    "sg:website":"rswien.at",
    "wof:name":"R & S Rohstoff- und Stahlwarenvertriebsges.m.b.H",
    "wof:placetype":"venue"
},
  "geometry": {"coordinates":[16.3846740723,48.1990470886],"type":"Point"}
}