{
  "type": "Feature",
  "properties": {
    "addr:full":"Hauptstr 109 Etsdorf am Kamp Nieder\u00f6sterreich 3492",
    "addr:housenumber":"109",
    "addr:postcode":"3492",
    "addr:street":"Hauptstr;Kamp",
    "iso:country":"AT",
    "sg:address":"Hauptstr 109",
    "sg:city":"Etsdorf am Kamp",
    "sg:orig_category":"Volksschulen",
    "sg:phone":"+43 2735 2592",
    "sg:postcode":"3492",
    "sg:province":"Nieder\u00f6sterreich",
    "wof:name":"Volksschule",
    "wof:placetype":"venue"
},
  "geometry": {"coordinates":[15.7489948273,48.4521331787],"type":"Point"}
}