{
  "type": "Feature",
  "properties": {
    "addr:full":"Hernalser Hauptstr 91 Wien Wien 1170",
    "addr:housenumber":"91",
    "addr:postcode":"1170",
    "addr:street":"Hernalser Hauptstr",
    "iso:country":"AT",
    "sg:address":"Hernalser Hauptstr 91",
    "sg:city":"Wien",
    "sg:orig_category":"Bekleidung / Einzelhandel",
    "sg:phone":"+43 1 4862565",
    "sg:postcode":"1170",
    "sg:province":"Wien",
    "wof:name":"Sch\u00f6ps Richard & Co AG",
    "wof:placetype":"venue"
},
  "geometry": {"coordinates":[16.3272285461,48.2188606262],"type":"Point"}
}