{
  "type": "Feature",
  "properties": {
    "addr:full":"Fasang 48 Wien Wien 1030",
    "addr:housenumber":"48",
    "addr:postcode":"1030",
    "addr:street":"Fasang",
    "iso:country":"AT",
    "sg:address":"Fasang 48",
    "sg:city":"Wien",
    "sg:orig_category":"Steuerberatung",
    "sg:phone":"+43 1 79872370",
    "sg:postcode":"1030",
    "sg:province":"Wien",
    "wof:name":"Polz Hans Mag",
    "wof:placetype":"venue"
},
  "geometry": {"coordinates":[16.3850688934,48.1891136169],"type":"Point"}
}