{
  "type": "Feature",
  "properties": {
    "addr:full":"Am Tasen 18 Tarrenz Tirol 6464",
    "addr:housenumber":"18",
    "addr:postcode":"6464",
    "addr:street":"Am Tasen;Tirol",
    "iso:country":"AT",
    "sg:address":"Am Tasen 18",
    "sg:city":"Tarrenz",
    "sg:orig_category":"Architekten",
    "sg:phone":"+43 5412 66480",
    "sg:postcode":"6464",
    "sg:province":"Tirol",
    "wof:name":"Gr\u00fcnwald Konrad Dipl-Ing",
    "wof:placetype":"venue"
},
  "geometry": {"coordinates":[10.7579784393,47.2607688904],"type":"Point"}
}