{
  "type": "Feature",
  "properties": {
    "iso:country":"AT",
    "sg:address":"Therme 7",
    "sg:city":"Loipersdorf",
    "sg:classifiers":[
        {
            "category":"Travel",
            "subcategory":"Hotels & Motels",
            "type":"Entertainment"
        }
    ],
    "sg:phone":"+43 4333 8286860",
    "sg:postcode":"8282",
    "sg:province":"Steiermark",
    "wof:name":"Maiers Hotel Thermenblick",
    "wof:placetype":"venue"
},
  "geometry": {"coordinates":[16.1206817627,46.9845046997],"type":"Point"}
}