{
  "type": "Feature",
  "properties": {
    "addr:full":"Prager Strasse 77 Wien Wien 1210",
    "addr:housenumber":"77",
    "addr:postcode":"1210",
    "addr:street":"Prager Strasse",
    "iso:country":"AT",
    "sg:address":"Prager Strasse 77",
    "sg:city":"Wien",
    "sg:classifiers":[
        {
            "category":"Building & Trades",
            "subcategory":"Electrical",
            "type":"Services"
        }
    ],
    "sg:phone":"+43 1 2711145",
    "sg:postcode":"1210",
    "sg:province":"Wien",
    "sg:tags":[
        "work",
        "installation"
    ],
    "wof:name":"Rudolf Kotschar",
    "wof:placetype":"venue"
},
  "geometry": {"coordinates":[16.3922843933,48.2676353455],"type":"Point"}
}