{
  "type": "Feature",
  "properties": {
    "addr:full":"Klammweg 10 Radenthein K\u00e4rnten 9545",
    "addr:housenumber":"10",
    "addr:postcode":"9545",
    "addr:street":"Klammweg;Kaernten",
    "iso:country":"AT",
    "sg:address":"Klammweg 10",
    "sg:city":"Radenthein",
    "sg:orig_category":"Fotografen",
    "sg:phone":"+43 4246 29287",
    "sg:postcode":"9545",
    "sg:province":"K\u00e4rnten",
    "wof:name":"Foto Schober",
    "wof:placetype":"venue"
},
  "geometry": {"coordinates":[13.7051124573,46.8021621704],"type":"Point"}
}