{
  "type": "Feature",
  "properties": {
    "addr:full":"Westsdlg 38 Antiesenhofen Ober\u00f6sterreich 4980",
    "addr:housenumber":"38",
    "addr:postcode":"4980",
    "addr:street":"Westsdlg",
    "iso:country":"AT",
    "sg:address":"Westsdlg 38",
    "sg:city":"Antiesenhofen",
    "sg:orig_category":"Baumschulen",
    "sg:phone":"+43 7759 5128",
    "sg:postcode":"4980",
    "sg:province":"Ober\u00f6sterreich",
    "wof:name":"Auzinger Franz Ing",
    "wof:placetype":"venue"
},
  "geometry": {"coordinates":[13.4010677338,48.346862793],"type":"Point"}
}