{
  "type": "Feature",
  "properties": {
    "addr:full":"Bahnhofstr 28 Schattendorf Burgenland 7022",
    "addr:housenumber":"28",
    "addr:postcode":"7022",
    "addr:street":"Bahnhofstr",
    "iso:country":"AT",
    "sg:address":"Bahnhofstr 28",
    "sg:city":"Schattendorf",
    "sg:orig_category":"Glasereien",
    "sg:phone":"+43 664 4153428",
    "sg:postcode":"7022",
    "sg:province":"Burgenland",
    "wof:name":"Grafl Josef",
    "wof:placetype":"venue"
},
  "geometry": {"coordinates":[16.505903244,47.7072219849],"type":"Point"}
}