{
  "type": "Feature",
  "properties": {
    "addr:full":"Stampferg 437 Altenmarkt im Pongau Salzburg 5541",
    "addr:housenumber":"437",
    "addr:postcode":"5541",
    "addr:street":"Salzburg",
    "iso:country":"AT",
    "sg:address":"Stampferg 437",
    "sg:city":"Altenmarkt im Pongau",
    "sg:orig_category":"Steuerberatung",
    "sg:phone":"+43 4364 5271350",
    "sg:postcode":"5541",
    "sg:province":"Salzburg",
    "wof:name":"Schitter Harald Mag",
    "wof:placetype":"venue"
},
  "geometry": {"coordinates":[13.4183111191,47.3829536438],"type":"Point"}
}