{
  "type": "Feature",
  "properties": {
    "addr:full":"Glocknerweg 4 Bruck an der Gro\u00dfglocknerstra\u00dfe Salzburg 5671",
    "addr:housenumber":"4",
    "addr:postcode":"5671",
    "addr:street":"Glocknerweg;Grossglocknerstrasse Salzburg",
    "iso:country":"AT",
    "sg:address":"Glocknerweg 4",
    "sg:city":"Bruck an der Gro\u00dfglocknerstra\u00dfe",
    "sg:classifiers":[
        {
            "category":"Home & Garden",
            "subcategory":"Kitchen Supply",
            "type":"Retail Goods"
        }
    ],
    "sg:phone":"+43 4365 456078",
    "sg:postcode":"5671",
    "sg:province":"Salzburg",
    "sg:tags":[
        "espresso-",
        "u",
        "kaffeemaschinen"
    ],
    "wof:name":"Leonhartsberger Gro\u00dfk\u00fcchentechnik GesmbH",
    "wof:placetype":"venue"
},
  "geometry": {"coordinates":[12.8262214661,47.2786750793],"type":"Point"}
}