{
  "type": "Feature",
  "properties": {
    "addr:full":"Neulandstr 12 Spittal an der Drau K\u00e4rnten 9800",
    "addr:housenumber":"12",
    "addr:postcode":"9800",
    "addr:street":"Neulandstr;Kaernten",
    "iso:country":"AT",
    "sg:address":"Neulandstr 12",
    "sg:city":"Spittal an der Drau",
    "sg:classifiers":[
        {
            "category":"Taxi",
            "type":"Transportation"
        }
    ],
    "sg:phone":"+43 4347 622111",
    "sg:postcode":"9800",
    "sg:province":"K\u00e4rnten",
    "sg:tags":[
        "personentransporte",
        "u"
    ],
    "wof:name":"Hartlieb Elke",
    "wof:placetype":"venue"
},
  "geometry": {"coordinates":[13.5045566559,46.7872581482],"type":"Point"}
}