{
  "type": "Feature",
  "properties": {
    "addr:full":"Sterneckstr 107 Klagenfurt K\u00e4rnten 9020",
    "addr:housenumber":"107",
    "addr:postcode":"9020",
    "addr:street":"Kaernten",
    "iso:country":"AT",
    "sg:address":"Sterneckstr 107",
    "sg:city":"Klagenfurt",
    "sg:orig_category":"Steuerberatung",
    "sg:phone":"+43 4346 357789",
    "sg:postcode":"9020",
    "sg:province":"K\u00e4rnten",
    "wof:name":"Kohlf\u00fcrst & Partner Wirtschaftspr\u00fcfung u Steuerberatung KEG",
    "wof:placetype":"venue"
},
  "geometry": {"coordinates":[14.2850122452,46.6242790222],"type":"Point"}
}