{
  "type": "Feature",
  "properties": {
    "addr:full":"St Leonharder Str 1 Gutau Ober\u00f6sterreich 4293",
    "addr:housenumber":"1",
    "addr:postcode":"4293",
    "addr:street":"St;Str",
    "iso:country":"AT",
    "sg:address":"St Leonharder Str 1",
    "sg:city":"Gutau",
    "sg:orig_category":"Non-Classified Establishments",
    "sg:phone":"+43 7946 62610",
    "sg:postcode":"4293",
    "sg:province":"Ober\u00f6sterreich",
    "wof:name":"Pfarramt",
    "wof:placetype":"venue"
},
  "geometry": {"coordinates":[14.6138057709,48.4172554016],"type":"Point"}
}