{
  "type": "Feature",
  "properties": {
    "addr:full":"Mauthfeld 14 Kirchdorf in Tirol Tirol 6382",
    "addr:housenumber":"14",
    "addr:postcode":"6382",
    "addr:street":"Mauthfeld;Tirol",
    "iso:country":"AT",
    "sg:address":"Mauthfeld 14",
    "sg:city":"Kirchdorf in Tirol",
    "sg:orig_category":"Appartements / Ferienwohnungen",
    "sg:phone":"+43 5352 66372",
    "sg:postcode":"6382",
    "sg:province":"Tirol",
    "wof:name":"Egger Matthias",
    "wof:placetype":"venue"
},
  "geometry": {"coordinates":[12.4412498474,47.5553398132],"type":"Point"}
}