{
  "type": "Feature",
  "properties": {
    "iso:country":"AT",
    "sg:address":"Widmoosweg 31",
    "sg:city":"Wagrain",
    "sg:orig_category":"Pensionen / Privatzimmer",
    "sg:phone":"+43 4364 14370",
    "sg:postcode":"5602",
    "sg:province":"Salzburg",
    "wof:name":"Zwislegg - Ganschitter",
    "wof:placetype":"venue"
},
  "geometry": {"coordinates":[13.3091096878,47.3340911865],"type":"Point"}
}