{
  "type": "Feature",
  "properties": {
    "addr:full":"Klosterg 7 Irdning Steiermark 8952",
    "addr:housenumber":"7",
    "addr:postcode":"8952",
    "addr:street":"Klosterg",
    "iso:country":"AT",
    "sg:address":"Klosterg 7",
    "sg:city":"Irdning",
    "sg:orig_category":"Betonbohr- U -Schneidedienst",
    "sg:phone":"+43 3682 22636",
    "sg:postcode":"8952",
    "sg:province":"Steiermark",
    "wof:name":"Spreitz Andreas",
    "wof:placetype":"venue"
},
  "geometry": {"coordinates":[14.1033115387,47.5018730164],"type":"Point"}
}