{
  "type": "Feature",
  "properties": {
    "addr:full":"Nr 14 Gleinst\u00e4tten Steiermark 8443",
    "addr:postcode":"8443",
    "addr:street":"Nr 14 Gleinstaetten Steiermark",
    "iso:country":"AT",
    "sg:address":"Nr 14",
    "sg:city":"Gleinst\u00e4tten",
    "sg:orig_category":"Erdarbeiten",
    "sg:phone":"+43 664 5358950",
    "sg:postcode":"8443",
    "sg:province":"Steiermark",
    "wof:name":"Lampl Eduard",
    "wof:placetype":"venue"
},
  "geometry": {"coordinates":[15.3728399277,46.7680854797],"type":"Point"}
}