{
  "type": "Feature",
  "properties": {
    "iso:country":"AT",
    "sg:address":"Eggenberger G\u00fcrtel 34",
    "sg:city":"Graz",
    "sg:classifiers":[
        {
            "category":"Taxi",
            "type":"Transportation"
        }
    ],
    "sg:phone":"+43 4367 684109612",
    "sg:postcode":"8020",
    "sg:province":"Steiermark",
    "sg:tags":[
        "personentransporte",
        "u"
    ],
    "wof:name":"Hamdi Faouzi OEG",
    "wof:placetype":"venue"
},
  "geometry": {"coordinates":[15.4111499786,47.0689201355],"type":"Point"}
}