{
  "type": "Feature",
  "properties": {
    "addr:full":"Tannhofweg 34 Mariatrost Steiermark 8044",
    "addr:housenumber":"34",
    "addr:postcode":"8044",
    "addr:street":"Tannhofweg",
    "iso:country":"AT",
    "sg:address":"Tannhofweg 34",
    "sg:city":"Mariatrost",
    "sg:orig_category":"Architekten",
    "sg:phone":"+43 316 392318",
    "sg:postcode":"8044",
    "sg:province":"Steiermark",
    "wof:name":"Heyszl Roland Arch Dipl-Ing Dr",
    "wof:placetype":"venue"
},
  "geometry": {"coordinates":[15.4858503342,47.1031532288],"type":"Point"}
}