{
  "type": "Feature",
  "properties": {
    "addr:full":"Nr 100 Breitenfeld an der Rittschein Steiermark 8313",
    "addr:postcode":"8313",
    "addr:street":"Nr 100",
    "iso:country":"AT",
    "sg:address":"Nr 100",
    "sg:city":"Breitenfeld an der Rittschein",
    "sg:orig_category":"Volksschulen",
    "sg:phone":"+43 4333 872286",
    "sg:postcode":"8313",
    "sg:province":"Steiermark",
    "wof:name":"Volksschule",
    "wof:placetype":"venue"
},
  "geometry": {"coordinates":[15.9435653687,47.048248291],"type":"Point"}
}