{
  "type": "Feature",
  "properties": {
    "addr:full":"Schie\u00dfstand 3a Inzing Tirol 6401",
    "addr:housenumber":"3a",
    "addr:postcode":"6401",
    "addr:street":"Schiessstand;Tirol",
    "iso:country":"AT",
    "sg:address":"Schie\u00dfstand 3a",
    "sg:city":"Inzing",
    "sg:orig_category":"Fenster",
    "sg:phone":"+43 4352 3853079",
    "sg:postcode":"6401",
    "sg:province":"Tirol",
    "sg:website":"jakubitzka.at",
    "wof:name":"Glaserei Jakubitzka GesmbH & Co KG",
    "wof:placetype":"venue"
},
  "geometry": {"coordinates":[11.2036771774,47.2706336975],"type":"Point"}
}