{
  "type": "Feature",
  "properties": {
    "addr:full":"Brenner Str 9A Steinach am Brenner Tirol 6150",
    "addr:postcode":"6150",
    "addr:street":"Str 9A;Tirol",
    "iso:country":"AT",
    "sg:address":"Brenner Str 9A",
    "sg:city":"Steinach am Brenner",
    "sg:orig_category":"Tischlereien",
    "sg:phone":"+43 5272 2321",
    "sg:postcode":"6150",
    "sg:province":"Tirol",
    "wof:name":"Maffey Stephan",
    "wof:placetype":"venue"
},
  "geometry": {"coordinates":[11.4652500153,47.0965995789],"type":"Point"}
}