{
  "type": "Feature",
  "properties": {
    "addr:full":"Nr 312 Neudorf Nieder\u00f6sterreich 2135",
    "addr:housenumber":"312",
    "addr:postcode":"2135",
    "addr:street":"Nr",
    "iso:country":"AT",
    "sg:address":"Nr 312",
    "sg:city":"Neudorf",
    "sg:orig_category":"Webdesign",
    "sg:phone":"+43 4367 683252222",
    "sg:postcode":"2135",
    "sg:province":"Nieder\u00f6sterreich",
    "wof:name":"Pelzer Lorenz Computer- u Webdesign",
    "wof:placetype":"venue"
},
  "geometry": {"coordinates":[16.4915943146,48.7205314636],"type":"Point"}
}