{
  "type": "Feature",
  "properties": {
    "iso:country":"AT",
    "sg:address":"Hauptstr 42",
    "sg:city":"Mauer-\u00d6hling",
    "sg:orig_category":"Installationsunternehmen",
    "sg:phone":"+43 7475 532540",
    "sg:postcode":"3362",
    "sg:province":"Nieder\u00f6sterreich",
    "wof:name":"Kammleitner GesmbH",
    "wof:placetype":"venue"
},
  "geometry": {"coordinates":[14.7983980179,48.094417572],"type":"Point"}
}