{
  "type": "Feature",
  "properties": {
    "addr:full":"Neulerchenfelder Str 4 Wien Wien 1160",
    "addr:housenumber":"4",
    "addr:postcode":"1160",
    "addr:street":"Str",
    "iso:country":"AT",
    "sg:address":"Neulerchenfelder Str 4",
    "sg:city":"Wien",
    "sg:orig_category":"Apotheken",
    "sg:phone":"+43 1 40624250",
    "sg:postcode":"1160",
    "sg:province":"Wien",
    "wof:name":"Apotheke z Papst Dr Erich Soos KG",
    "wof:placetype":"venue"
},
  "geometry": {"coordinates":[16.3381900787,48.2109603882],"type":"Point"}
}