{
  "type": "Feature",
  "properties": {
    "addr:full":"Gutenbergstr 6 Sattledt Ober\u00f6sterreich 4642",
    "addr:housenumber":"6",
    "addr:postcode":"4642",
    "addr:street":"Gutenbergstr",
    "iso:country":"AT",
    "sg:address":"Gutenbergstr 6",
    "sg:city":"Sattledt",
    "sg:orig_category":"Offsetdruckereien",
    "sg:phone":"+43 7244 8858",
    "sg:postcode":"4642",
    "sg:province":"Ober\u00f6sterreich",
    "wof:name":"M & M-Druck Inh Franz M\u00fchlbauer",
    "wof:placetype":"venue"
},
  "geometry": {"coordinates":[14.0459280014,48.0744628906],"type":"Point"}
}