{
  "type": "Feature",
  "properties": {
    "iso:country":"AT",
    "sg:address":"Enge G 8/1",
    "sg:city":"Steyr",
    "sg:orig_category":"Schneidereien",
    "sg:phone":"+43 7252 41966",
    "sg:postcode":"4400",
    "sg:province":"Ober\u00f6sterreich",
    "wof:name":"Brandst\u00f6tter Karin",
    "wof:placetype":"venue"
},
  "geometry": {"coordinates":[14.4205112457,48.0416412354],"type":"Point"}
}