{
  "type": "Feature",
  "properties": {
    "addr:full":"St Peter-Str 5/123 Klagenfurt K\u00e4rnten 9020",
    "addr:housenumber":"5 / 123",
    "addr:postcode":"9020",
    "addr:street":"Kaernten",
    "iso:country":"AT",
    "sg:address":"St Peter-Str 5/123",
    "sg:city":"Klagenfurt",
    "sg:classifiers":[
        {
            "category":"Internet Cafe",
            "subcategory":"None",
            "type":"Food & Drink"
        }
    ],
    "sg:phone":"+43 463 310744",
    "sg:postcode":"9020",
    "sg:province":"K\u00e4rnten",
    "wof:name":"Lupe.at Ank\u00fcndigungs - GesmbH",
    "wof:placetype":"venue"
},
  "geometry": {"coordinates":[14.3239917755,46.6182861328],"type":"Point"}
}