{
  "type": "Feature",
  "properties": {
    "addr:full":"Ledererstr 5 Eferding Ober\u00f6sterreich 4070",
    "addr:housenumber":"5",
    "addr:postcode":"4070",
    "addr:street":"Ledererstr",
    "iso:country":"AT",
    "sg:address":"Ledererstr 5",
    "sg:city":"Eferding",
    "sg:orig_category":"Fotografen",
    "sg:phone":"+43 664 4233838",
    "sg:postcode":"4070",
    "sg:province":"Ober\u00f6sterreich",
    "wof:name":"Nici Wolf - Photography",
    "wof:placetype":"venue"
},
  "geometry": {"coordinates":[14.0190486908,48.3088111877],"type":"Point"}
}