{
  "type": "Feature",
  "properties": {
    "iso:country":"AT",
    "sg:address":"Kirchenpl 100",
    "sg:city":"Lohnsburg am Kobernau\u00dferwald",
    "sg:orig_category":"Fleischhauereien",
    "sg:phone":"+43 7754 2128",
    "sg:postcode":"4923",
    "sg:province":"Ober\u00f6sterreich",
    "wof:name":"Badegruber GmbH & Co KG",
    "wof:placetype":"venue"
},
  "geometry": {"coordinates":[13.4064073563,48.1435241699],"type":"Point"}
}