{
  "type": "Feature",
  "properties": {
    "addr:full":"Moosstr 156 Salzburg Salzburg 5020",
    "addr:housenumber":"156",
    "addr:postcode":"5020",
    "addr:street":"Salzburg",
    "iso:country":"AT",
    "sg:address":"Moosstr 156",
    "sg:city":"Salzburg",
    "sg:orig_category":"Pensionen / Privatzimmer",
    "sg:phone":"+43 662 826298",
    "sg:postcode":"5020",
    "sg:province":"Salzburg",
    "wof:name":"G\u00f6tzinger Helga",
    "wof:placetype":"venue"
},
  "geometry": {"coordinates":[13.0166978836,47.7614936829],"type":"Point"}
}