{
  "type": "Feature",
  "properties": {
    "addr:full":"Kremser Str 649 Gars am Kamp Nieder\u00f6sterreich 3571",
    "addr:housenumber":"649",
    "addr:postcode":"3571",
    "addr:street":"Str",
    "iso:country":"AT",
    "sg:address":"Kremser Str 649",
    "sg:city":"Gars am Kamp",
    "sg:orig_category":"Banken U Sparkassen",
    "sg:phone":"+43 4329 852305",
    "sg:postcode":"3571",
    "sg:province":"Nieder\u00f6sterreich",
    "wof:name":"Sparkasse Horn-Ravelsbach-Kirchberg AG",
    "wof:placetype":"venue"
},
  "geometry": {"coordinates":[15.6603145599,48.5971336365],"type":"Point"}
}