{
  "type": "Feature",
  "properties": {
    "iso:country":"AT",
    "sg:address":"Seespitz 44",
    "sg:city":"Treffen",
    "sg:orig_category":"Pensionen / Privatzimmer",
    "sg:phone":"+43 4248 3111",
    "sg:postcode":"9521",
    "sg:province":"K\u00e4rnten",
    "wof:name":"Pension Seespitz",
    "wof:placetype":"venue"
},
  "geometry": {"coordinates":[13.8552322388,46.6679840088],"type":"Point"}
}