{
  "type": "Feature",
  "properties": {
    "addr:full":"Gro\u00dfmarktstr 8 Wien Wien 1230",
    "addr:housenumber":"8",
    "addr:postcode":"1230",
    "addr:street":"Grossmarktstr",
    "iso:country":"AT",
    "sg:address":"Gro\u00dfmarktstr 8",
    "sg:city":"Wien",
    "sg:orig_category":"Brandschadensanierung",
    "sg:phone":"+43 4316 10170",
    "sg:postcode":"1230",
    "sg:province":"Wien",
    "wof:name":"BELFOR Austria GmbH",
    "wof:placetype":"venue"
},
  "geometry": {"coordinates":[16.3644237518,48.1422958374],"type":"Point"}
}