{
  "type": "Feature",
  "properties": {
    "addr:full":"Margaretenstrasse 124 Wien Wien 1050",
    "addr:housenumber":"124",
    "addr:postcode":"1050",
    "addr:street":"Margaretenstrasse",
    "iso:country":"AT",
    "sg:address":"Margaretenstrasse 124",
    "sg:city":"Wien",
    "sg:classifiers":[
        {
            "category":"Autos & Motor Vehicles",
            "subcategory":"Automobile Sales",
            "type":"Retail Goods"
        }
    ],
    "sg:phone":"+43 1 5448375",
    "sg:postcode":"1050",
    "sg:province":"Wien",
    "sg:tags":[
        "varnish",
        "lacquers"
    ],
    "wof:name":"Kurt Wolf & Co. OHG",
    "wof:placetype":"venue"
},
  "geometry": {"coordinates":[16.3526611328,48.1881332397],"type":"Point"}
}