{
  "type": "Feature",
  "properties": {
    "addr:full":"Herrgottwiesg. 125 Graz Steiermark 8020",
    "addr:housenumber":"125",
    "addr:postcode":"8020",
    "iso:country":"AT",
    "sg:address":"Herrgottwiesg. 125",
    "sg:city":"Graz",
    "sg:classifiers":[
        {
            "category":"Manufacturing",
            "subcategory":"Metals",
            "type":"Manufacturing & Wholesale Goods"
        }
    ],
    "sg:phone":"+43 4331 62771",
    "sg:postcode":"8020",
    "sg:province":"Steiermark",
    "sg:tags":[
        "metallurgy",
        "metalworking"
    ],
    "wof:name":"OD\u00d6RFER EISENHOF GESMBH",
    "wof:placetype":"venue"
},
  "geometry": {"coordinates":[15.4111499786,47.0689201355],"type":"Point"}
}