{
  "type": "Feature",
  "properties": {
    "addr:full":"Kirchenpl 2 Maissau Nieder\u00f6sterreich 3712",
    "addr:housenumber":"2",
    "addr:postcode":"3712",
    "addr:street":"Kirchenpl",
    "iso:country":"AT",
    "sg:address":"Kirchenpl 2",
    "sg:city":"Maissau",
    "sg:orig_category":"Tischlereien",
    "sg:phone":"+43 2958 822830",
    "sg:postcode":"3712",
    "sg:province":"Nieder\u00f6sterreich",
    "wof:name":"Zellhofer Edmund Ing",
    "wof:placetype":"venue"
},
  "geometry": {"coordinates":[15.8258228302,48.5716705322],"type":"Point"}
}