{
  "type": "Feature",
  "properties": {
    "iso:country":"AT",
    "sg:address":"Dorf 33",
    "sg:city":"Anras",
    "sg:orig_category":"Banken U Sparkassen",
    "sg:phone":"+43 4348 466249",
    "sg:postcode":"9912",
    "sg:province":"Tirol",
    "wof:name":"Raiffeisenbank Sillian regGenmbH",
    "wof:placetype":"venue"
},
  "geometry": {"coordinates":[12.5568389893,46.7720298767],"type":"Point"}
}