{
  "type": "Feature",
  "properties": {
    "addr:full":"Peter-Rosegger-Str 2 Villach K\u00e4rnten 9500",
    "addr:housenumber":"2",
    "addr:postcode":"9500",
    "addr:street":"Peter-Rosegger-Str;Kaernten",
    "iso:country":"AT",
    "sg:address":"Peter-Rosegger-Str 2",
    "sg:city":"Villach",
    "sg:orig_category":"Werbeartikel U -Geschenke",
    "sg:phone":"+43 4342 42257226",
    "sg:postcode":"9500",
    "sg:province":"K\u00e4rnten",
    "wof:name":"Perdacher Werbeartikel",
    "wof:placetype":"venue"
},
  "geometry": {"coordinates":[13.84333992,46.6234817505],"type":"Point"}
}