{
  "type": "Feature",
  "properties": {
    "addr:full":"Schulstr 9/21 Linz Ober\u00f6sterreich 4040",
    "addr:housenumber":"9 / 21",
    "addr:postcode":"4040",
    "addr:street":"Schulstr",
    "iso:country":"AT",
    "sg:address":"Schulstr 9/21",
    "sg:city":"Linz",
    "sg:classifiers":[
        {
            "category":"Professional",
            "subcategory":"Computer Services",
            "type":"Services"
        }
    ],
    "sg:phone":"+43 732 710110",
    "sg:postcode":"4040",
    "sg:province":"Ober\u00f6sterreich",
    "sg:tags":[
        "software"
    ],
    "wof:name":"Ametanet Real Estate Software GmbH",
    "wof:placetype":"venue"
},
  "geometry": {"coordinates":[14.2836370468,48.3113441467],"type":"Point"}
}