{
  "type": "Feature",
  "properties": {
    "addr:full":"Auffach 228 Wildsch\u00f6nau-Auffach Tirol 6313",
    "addr:housenumber":"228",
    "addr:postcode":"6313",
    "addr:street":"Auffach;Tirol",
    "iso:country":"AT",
    "sg:address":"Auffach 228",
    "sg:city":"Wildsch\u00f6nau-Auffach",
    "sg:orig_category":"Pensionen / Privatzimmer",
    "sg:phone":"+43 5339 8883",
    "sg:postcode":"6313",
    "sg:province":"Tirol",
    "wof:name":"Haus am Wildbach",
    "wof:placetype":"venue"
},
  "geometry": {"coordinates":[12.0360631943,47.4098701477],"type":"Point"}
}