{
  "type": "Feature",
  "properties": {
    "addr:full":"Am Brucker Tor 6 Purbach am Neusiedler See Burgenland 7083",
    "addr:housenumber":"6",
    "addr:postcode":"7083",
    "addr:street":"Am Brucker Tor",
    "iso:country":"AT",
    "sg:address":"Am Brucker Tor 6",
    "sg:city":"Purbach am Neusiedler See",
    "sg:orig_category":"Polizei U Gendarmerie",
    "sg:phone":"+43 4359 1331109",
    "sg:postcode":"7083",
    "sg:province":"Burgenland",
    "wof:name":"Gendarmerie",
    "wof:placetype":"venue"
},
  "geometry": {"coordinates":[16.6965637207,47.9152183533],"type":"Point"}
}