{
  "type": "Feature",
  "properties": {
    "iso:country":"AT",
    "sg:address":"Viktor-Hagl-Gasse 2",
    "sg:city":"Wien",
    "sg:classifiers":[
        {
            "category":"Train Station",
            "subcategory":"Rail",
            "type":"Transportation"
        }
    ],
    "sg:phone":"+43 1 97922930",
    "sg:postcode":"1140",
    "sg:province":"Wien",
    "sg:tags":[
        "development",
        "brand",
        "name"
    ],
    "wof:name":"Namework - Agentur f\u00fcr Namensfindung Patrick Seitz",
    "wof:placetype":"venue"
},
  "geometry": {"coordinates":[16.2242088318,48.2158508301],"type":"Point"}
}