{
  "type": "Feature",
  "properties": {
    "addr:full":"Eduard-Meder-Gasse 29 Traiskirchen Nieder\u00f6sterreich 2514",
    "addr:housenumber":"29",
    "addr:postcode":"2514",
    "addr:street":"Eduard-Meder-Gasse;Niederoesterreich",
    "iso:country":"AT",
    "sg:address":"Eduard-Meder-Gasse 29",
    "sg:city":"Traiskirchen",
    "sg:classifiers":[
        {
            "category":"Home & Garden",
            "subcategory":"Furniture",
            "type":"Retail Goods"
        }
    ],
    "sg:phone":"+43 2252 52164",
    "sg:postcode":"2514",
    "sg:province":"Nieder\u00f6sterreich",
    "sg:tags":[
        "bathroom"
    ],
    "wof:name":"Peter S\u00f6lkner",
    "wof:placetype":"venue"
},
  "geometry": {"coordinates":[16.2827262878,48.0116043091],"type":"Point"}
}