{
  "type": "Feature",
  "properties": {
    "addr:full":"Pflanzmannstrasse 4 Salzburg Salzburg 5020",
    "addr:housenumber":"4",
    "addr:postcode":"5020",
    "addr:street":"Pflanzmannstrasse;Salzburg",
    "iso:country":"AT",
    "sg:address":"Pflanzmannstrasse 4",
    "sg:city":"Salzburg",
    "sg:classifiers":[
        {
            "category":"Professional",
            "subcategory":"Advertising",
            "type":"Services"
        }
    ],
    "sg:phone":"+43 662 452665",
    "sg:postcode":"5020",
    "sg:province":"Salzburg",
    "sg:tags":[
        "agency"
    ],
    "wof:name":"Susanne Doblhofer",
    "wof:placetype":"venue"
},
  "geometry": {"coordinates":[13.0506105423,47.8233718872],"type":"Point"}
}