{
  "type": "Feature",
  "properties": {
    "addr:full":"Wienersdorfer Strasse 17 Traiskirchen Nieder\u00f6sterreich 2514",
    "addr:housenumber":"17",
    "addr:postcode":"2514",
    "addr:street":"Wienersdorfer Strasse;Niederoesterreich",
    "iso:country":"AT",
    "sg:address":"Wienersdorfer Strasse 17",
    "sg:city":"Traiskirchen",
    "sg:classifiers":[
        {
            "category":"Government",
            "subcategory":"Fire Station",
            "type":"Public Place"
        }
    ],
    "sg:phone":"+43 664 3166370",
    "sg:postcode":"2514",
    "sg:province":"Nieder\u00f6sterreich",
    "sg:tags":[
        "extinguisher",
        "automatic"
    ],
    "sg:website":"feuerloeschtechnik.at",
    "wof:name":"W. Wienerl Feuerl\u00f6schtechnik",
    "wof:placetype":"venue"
},
  "geometry": {"coordinates":[16.2916984558,48.012008667],"type":"Point"}
}