{
  "type": "Feature",
  "properties": {
    "addr:full":"Reisnerstr 14 Wien Wien 1030",
    "addr:housenumber":"14",
    "addr:postcode":"1030",
    "addr:street":"Reisnerstr",
    "iso:country":"AT",
    "sg:address":"Reisnerstr 14",
    "sg:city":"Wien",
    "sg:orig_category":"Werbegestalter",
    "sg:phone":"+43 1 7154292",
    "sg:postcode":"1030",
    "sg:province":"Wien",
    "wof:name":"Decostil Werbeproduktion",
    "wof:placetype":"venue"
},
  "geometry": {"coordinates":[16.3831615448,48.2013435364],"type":"Point"}
}