{
  "type": "Feature",
  "properties": {
    "iso:country":"AT",
    "sg:address":"Unterer Stadtpl 16",
    "sg:city":"Kufstein",
    "sg:orig_category":"Spirituosen / Erzeugung U Gro\u00c3\u0178handel",
    "sg:phone":"+43 5372 62297",
    "sg:postcode":"6330",
    "sg:province":"Tirol",
    "wof:name":"Osterauer Sepp",
    "wof:placetype":"venue"
},
  "geometry": {"coordinates":[12.1698122025,47.5828475952],"type":"Point"}
}