{
  "type": "Feature",
  "properties": {
    "addr:full":"Hauptpl 3 Leibnitz Steiermark 8430",
    "addr:housenumber":"3",
    "addr:postcode":"8430",
    "addr:street":"Hauptpl;Steiermark",
    "iso:country":"AT",
    "sg:address":"Hauptpl 3",
    "sg:city":"Leibnitz",
    "sg:orig_category":"Bierlokale-Pubs",
    "sg:phone":"+43 3452 82668",
    "sg:postcode":"8430",
    "sg:province":"Steiermark",
    "wof:name":"Hubmann GmbH - Big Ben",
    "wof:placetype":"venue"
},
  "geometry": {"coordinates":[15.5406370163,46.7820739746],"type":"Point"}
}