{
  "type": "Feature",
  "properties": {
    "addr:full":"Traung 25 Wels Ober\u00f6sterreich 4600",
    "addr:housenumber":"25",
    "addr:postcode":"4600",
    "addr:street":"Traung;Oberoesterreich",
    "iso:country":"AT",
    "sg:address":"Traung 25",
    "sg:city":"Wels",
    "sg:orig_category":"Personalbereitstellung",
    "sg:phone":"+43 7242 211612",
    "sg:postcode":"4600",
    "sg:province":"Ober\u00f6sterreich",
    "wof:name":"INTECMA Personaldienste GmbH",
    "wof:placetype":"venue"
},
  "geometry": {"coordinates":[14.02643013,48.1552391052],"type":"Point"}
}