{
  "type": "Feature",
  "properties": {
    "addr:full":"Gmunden Ober\u00f6sterreich 4810",
    "addr:postcode":"4810",
    "addr:street":"Oberoesterreich",
    "iso:country":"AT",
    "sg:city":"Gmunden",
    "sg:classifiers":[
        {
            "category":"Utilities",
            "subcategory":"Cable",
            "type":"Services"
        }
    ],
    "sg:postcode":"4810",
    "sg:province":"Ober\u00f6sterreich",
    "sg:tags":[
        "tv",
        "medien",
        "u",
        "radio"
    ],
    "sg:website":"http://www.traunsee.com/schlosshotel.htm",
    "wof:name":"Schlosshotel Orth",
    "wof:placetype":"venue"
},
  "geometry": {"coordinates":[13.7981462479,47.918598175],"type":"Point"}
}