{
  "type": "Feature",
  "properties": {
    "iso:country":"AT",
    "sg:address":"Hans-Sachs-Str 8",
    "sg:city":"Braunau am Inn",
    "sg:orig_category":"Lebensmittel / Einzelhandel",
    "sg:phone":"+43 7722 63234",
    "sg:postcode":"5280",
    "sg:province":"Ober\u00f6sterreich",
    "wof:name":"Hofer KG",
    "wof:placetype":"venue"
},
  "geometry": {"coordinates":[13.0489263535,48.2598075867],"type":"Point"}
}