{
  "type": "Feature",
  "properties": {
    "addr:full":"Paracelsusstr 20 Oberndorf Salzburg 5110",
    "addr:housenumber":"20",
    "addr:postcode":"5110",
    "addr:street":"Paracelsusstr",
    "iso:country":"AT",
    "sg:address":"Paracelsusstr 20",
    "sg:city":"Oberndorf",
    "sg:orig_category":"Bauunternehmen",
    "sg:phone":"+43 4362 7254430",
    "sg:postcode":"5110",
    "sg:province":"Salzburg",
    "wof:name":"Tiefenthaler Schichtle Hoch- u Tiefbau GesmbH & Co KG",
    "wof:placetype":"venue"
},
  "geometry": {"coordinates":[12.9459609985,47.9383583069],"type":"Point"}
}