{
  "type": "Feature",
  "properties": {
    "addr:full":"Br\u00fcnner Str 243 Gerasdorf Nieder\u00f6sterreich 2201",
    "addr:housenumber":"243",
    "addr:postcode":"2201",
    "addr:street":"Str",
    "iso:country":"AT",
    "sg:address":"Br\u00fcnner Str 243",
    "sg:city":"Gerasdorf",
    "sg:orig_category":"Fenster",
    "sg:phone":"+43 4322 4628080",
    "sg:postcode":"2201",
    "sg:province":"Nieder\u00f6sterreich",
    "wof:name":"M\u00fcller's Fenster- u T\u00fcrenpark GmbH & Co KG",
    "wof:placetype":"venue"
},
  "geometry": {"coordinates":[16.4708862305,48.2990150452],"type":"Point"}
}