{
  "type": "Feature",
  "properties": {
    "addr:full":"Ing Etzel-Str 67 Innsbruck Tirol 6020",
    "addr:housenumber":"67",
    "addr:postcode":"6020",
    "addr:street":"Tirol",
    "iso:country":"AT",
    "sg:address":"Ing Etzel-Str 67",
    "sg:city":"Innsbruck",
    "sg:orig_category":"Behinderungen / Leben Mit Behinderungen",
    "sg:phone":"+43 512 583105",
    "sg:postcode":"6020",
    "sg:province":"Tirol",
    "wof:name":"Geh\u00f6rlosenverein Innsbruck",
    "wof:placetype":"venue"
},
  "geometry": {"coordinates":[11.4128198624,47.2771492004],"type":"Point"}
}