{
  "type": "Feature",
  "properties": {
    "addr:full":"Blankenberg 15 Sierning Ober\u00f6sterreich 4522",
    "addr:housenumber":"15",
    "addr:postcode":"4522",
    "addr:street":"Blankenberg",
    "iso:country":"AT",
    "sg:address":"Blankenberg 15",
    "sg:city":"Sierning",
    "sg:orig_category":"Drechslereien",
    "sg:phone":"+43 7259 5528",
    "sg:postcode":"4522",
    "sg:province":"Ober\u00f6sterreich",
    "wof:name":"Massak Franz",
    "wof:placetype":"venue"
},
  "geometry": {"coordinates":[14.2998399734,48.0387916565],"type":"Point"}
}