{
  "type": "Feature",
  "properties": {
    "addr:full":"Kraut\u00e4ckerg 20 Deutschkreutz Burgenland 7301",
    "addr:housenumber":"20",
    "addr:postcode":"7301",
    "addr:street":"Krautaeckerg",
    "iso:country":"AT",
    "sg:address":"Kraut\u00e4ckerg 20",
    "sg:city":"Deutschkreutz",
    "sg:orig_category":"Schallschutzeinrichtungen",
    "sg:phone":"+43 4326 1389701",
    "sg:postcode":"7301",
    "sg:province":"Burgenland",
    "wof:name":"Kiss Alfred Schlosserei, Isolier- u Schalltechnik",
    "wof:placetype":"venue"
},
  "geometry": {"coordinates":[16.6188468933,47.6017036438],"type":"Point"}
}