{
  "type": "Feature",
  "properties": {
    "addr:full":"M\u00fchlweg 17a Puntigam Steiermark 8055",
    "addr:housenumber":"17a",
    "addr:postcode":"8055",
    "addr:street":"Muehlweg",
    "iso:country":"AT",
    "sg:address":"M\u00fchlweg 17a",
    "sg:city":"Puntigam",
    "sg:orig_category":"Werbeagenturen",
    "sg:phone":"+43 316 243884",
    "sg:postcode":"8055",
    "sg:province":"Steiermark",
    "wof:name":"So. Werbeagentur - Sonnleitner",
    "wof:placetype":"venue"
},
  "geometry": {"coordinates":[15.4245700836,47.0141792297],"type":"Point"}
}