{
  "type": "Feature",
  "properties": {
    "addr:full":"Kaiser-Franz-Ring 48/9 Baden Nieder\u00f6sterreich 2500",
    "addr:housenumber":"48 / 9",
    "addr:postcode":"2500",
    "addr:street":"Kaiser-Franz-Ring;Niederoesterreich",
    "iso:country":"AT",
    "sg:address":"Kaiser-Franz-Ring 48/9",
    "sg:city":"Baden",
    "sg:classifiers":[
        {
            "category":"Internet Cafe",
            "subcategory":"None",
            "type":"Food & Drink"
        }
    ],
    "sg:phone":"+43 2252 86452",
    "sg:postcode":"2500",
    "sg:province":"Nieder\u00f6sterreich",
    "wof:name":"Media Labs Softwarel\u00f6sungen GmbH",
    "wof:placetype":"venue"
},
  "geometry": {"coordinates":[16.2413387299,48.0106925964],"type":"Point"}
}