{
  "type": "Feature",
  "properties": {
    "iso:country":"AT",
    "sg:address":"Reisnerstr 7",
    "sg:city":"Wien",
    "sg:orig_category":"Bankomat-Standorte",
    "sg:phone":"+43 5 010020034",
    "sg:postcode":"1030",
    "sg:province":"Wien",
    "wof:name":"Bankomat d Erste Bank d oesterreichischen Sparkassen AG",
    "wof:placetype":"venue"
},
  "geometry": {"coordinates":[16.3827838898,48.2023658752],"type":"Point"}
}