{
  "type": "Feature",
  "properties": {
    "addr:full":"Vandans Vorarlberg 6773",
    "addr:postcode":"6773",
    "iso:country":"AT",
    "sg:city":"Vandans",
    "sg:orig_category":"Feuerwehren",
    "sg:phone":"+43 5556 720740",
    "sg:postcode":"6773",
    "sg:province":"Vorarlberg",
    "wof:name":"Feuerwehr Vandans",
    "wof:placetype":"venue"
},
  "geometry": {"coordinates":[9.8657302856,47.0953102112],"type":"Point"}
}