{
  "type": "Feature",
  "properties": {
    "iso:country":"AT",
    "sg:address":"Eduard Heinzl-Str 19",
    "sg:city":"Gm\u00fcnd",
    "sg:orig_category":"Installationsunternehmen",
    "sg:phone":"+43 664 2216286",
    "sg:postcode":"3950",
    "sg:province":"Nieder\u00f6sterreich",
    "wof:name":"Simsalik Walter",
    "wof:placetype":"venue"
},
  "geometry": {"coordinates":[14.9809799194,48.7597732544],"type":"Point"}
}