{
  "type": "Feature",
  "properties": {
    "iso:country":"AT",
    "sg:address":"Garteng 1",
    "sg:city":"H\u00fcttenberg",
    "sg:orig_category":"Transportunternehmen",
    "sg:phone":"+43 4263 8106",
    "sg:postcode":"9375",
    "sg:province":"K\u00e4rnten",
    "wof:name":"Trucktrans Albin Schimpl",
    "wof:placetype":"venue"
},
  "geometry": {"coordinates":[14.5484008789,46.9411315918],"type":"Point"}
}