{
  "type": "Feature",
  "properties": {
    "addr:full":"Ludwigg 3-7 Mistelbach Nieder\u00f6sterreich 2130",
    "addr:housenumber":"3-7",
    "addr:postcode":"2130",
    "addr:street":"Ludwigg;Niederoesterreich",
    "iso:country":"AT",
    "sg:address":"Ludwigg 3-7",
    "sg:city":"Mistelbach",
    "sg:orig_category":"Kosmetische Produkte / Einzelhandel",
    "sg:phone":"+43 4325 724584",
    "sg:postcode":"2130",
    "sg:province":"Nieder\u00f6sterreich",
    "wof:name":"Pillgruber GmbH - Channoine & Nobusan - Beauty u Gesundheitscoaching",
    "wof:placetype":"venue"
},
  "geometry": {"coordinates":[16.5655708313,48.5734291077],"type":"Point"}
}