{
  "type": "Feature",
  "properties": {
    "addr:full":"Europastr 8 Villach K\u00e4rnten 9500",
    "addr:housenumber":"8",
    "addr:postcode":"9500",
    "addr:street":"Europastr;Kaernten",
    "iso:country":"AT",
    "sg:address":"Europastr 8",
    "sg:city":"Villach",
    "sg:orig_category":"Umweltschutz",
    "sg:phone":"+43 4242 90033210",
    "sg:postcode":"9500",
    "sg:province":"K\u00e4rnten",
    "wof:name":"Ressourcen Management Agentur",
    "wof:placetype":"venue"
},
  "geometry": {"coordinates":[13.8850021362,46.6103935242],"type":"Point"}
}