{
  "type": "Feature",
  "properties": {
    "addr:full":"Eduard-Keil-G 27a Liebenau Steiermark 8041",
    "addr:housenumber":"27a",
    "addr:postcode":"8041",
    "addr:street":"Eduard-Keil-G",
    "iso:country":"AT",
    "sg:address":"Eduard-Keil-G 27a",
    "sg:city":"Liebenau",
    "sg:orig_category":"Friseure U Frisiersalons",
    "sg:phone":"+43 4331 6424235",
    "sg:postcode":"8041",
    "sg:province":"Steiermark",
    "wof:name":"Koller Helga",
    "wof:placetype":"venue"
},
  "geometry": {"coordinates":[15.449719429,47.0445861816],"type":"Point"}
}