{
  "type": "Feature",
  "properties": {
    "addr:full":"Lagerg 6 Wien Wien 1030",
    "addr:housenumber":"6",
    "addr:postcode":"1030",
    "addr:street":"Lagerg",
    "iso:country":"AT",
    "sg:address":"Lagerg 6",
    "sg:city":"Wien",
    "sg:orig_category":"Medizintechnik",
    "sg:phone":"+43 1 7103165",
    "sg:postcode":"1030",
    "sg:province":"Wien",
    "wof:name":"ad rem team GmbH - Gesellschaft f innovative Medizinprodukte und Dienstleistungen",
    "wof:placetype":"venue"
},
  "geometry": {"coordinates":[16.3800621033,48.2003326416],"type":"Point"}
}