{
  "type": "Feature",
  "properties": {
    "addr:full":"Marktplatz 6 Gr\u00f6dig Salzburg 5082",
    "addr:housenumber":"6",
    "addr:postcode":"5082",
    "addr:street":"Marktplatz;Salzburg",
    "iso:country":"AT",
    "sg:address":"Marktplatz 6",
    "sg:city":"Gr\u00f6dig",
    "sg:classifiers":[
        {
            "category":"Home & Garden",
            "subcategory":"Kitchen Supply",
            "type":"Retail Goods"
        }
    ],
    "sg:phone":"+43 6246 73232",
    "sg:postcode":"5082",
    "sg:province":"Salzburg",
    "sg:tags":[
        "household",
        "electric",
        "cooker"
    ],
    "sg:website":"elektro-kinz.at",
    "wof:name":"Richard Kinz",
    "wof:placetype":"venue"
},
  "geometry": {"coordinates":[-76.2684555054,37.4373283386],"type":"Point"}
}