{
  "type": "Feature",
  "properties": {
    "addr:full":"Stolzenthalerg 26 Wien Wien 1080",
    "addr:housenumber":"26",
    "addr:postcode":"1080",
    "addr:street":"Stolzenthalerg",
    "iso:country":"AT",
    "sg:address":"Stolzenthalerg 26",
    "sg:city":"Wien",
    "sg:orig_category":"Bars-Cafes",
    "sg:phone":"+43 1 4056126",
    "sg:postcode":"1080",
    "sg:province":"Wien",
    "wof:name":"Cafe G-Punkt",
    "wof:placetype":"venue"
},
  "geometry": {"coordinates":[16.3423576355,48.2104988098],"type":"Point"}
}