{
  "type": "Feature",
  "properties": {
    "iso:country":"AT",
    "sg:address":"Nr 1",
    "sg:city":"Dobersberg",
    "sg:classifiers":[
        {
            "category":"Taxi",
            "type":"Transportation"
        }
    ],
    "sg:phone":"+43 4366 46444330",
    "sg:postcode":"3843",
    "sg:province":"Nieder\u00f6sterreich",
    "sg:tags":[
        "personentransporte",
        "u"
    ],
    "wof:name":"Langsteiner Franz",
    "wof:placetype":"venue"
},
  "geometry": {"coordinates":[15.3190174103,48.9154052734],"type":"Point"}
}