{
  "type": "Feature",
  "properties": {
    "addr:full":"Landstr 1 Nenzing Vorarlberg 6710",
    "addr:housenumber":"1",
    "addr:postcode":"6710",
    "addr:street":"Landstr",
    "iso:country":"AT",
    "sg:address":"Landstr 1",
    "sg:city":"Nenzing",
    "sg:orig_category":"Gemeinden",
    "sg:phone":"+43 5525 622150",
    "sg:postcode":"6710",
    "sg:province":"Vorarlberg",
    "wof:name":"Marktgemeinde Nenzing",
    "wof:placetype":"venue"
},
  "geometry": {"coordinates":[9.7052927017,47.184463501],"type":"Point"}
}