{
  "type": "Feature",
  "properties": {
    "addr:full":"Wiesen 20 Koblach Vorarlberg 6842",
    "addr:housenumber":"20",
    "addr:postcode":"6842",
    "addr:street":"Wiesen",
    "iso:country":"AT",
    "sg:address":"Wiesen 20",
    "sg:city":"Koblach",
    "sg:orig_category":"Architekten",
    "sg:phone":"+43 5523 55639",
    "sg:postcode":"6842",
    "sg:province":"Vorarlberg",
    "wof:name":"Amann Kurt",
    "wof:placetype":"venue"
},
  "geometry": {"coordinates":[9.6102485657,47.3287887573],"type":"Point"}
}