{
  "type": "Feature",
  "properties": {
    "addr:full":"Actualstrasse 30 Haid Ober\u00f6sterreich 4053",
    "addr:housenumber":"30",
    "addr:postcode":"4053",
    "addr:street":"Actualstrasse",
    "iso:country":"AT",
    "sg:address":"Actualstrasse 30",
    "sg:city":"Haid",
    "sg:classifiers":[
        {
            "category":"Home & Garden",
            "subcategory":"Building Materials",
            "type":"Retail Goods"
        }
    ],
    "sg:phone":"+43 7229 8660",
    "sg:postcode":"4053",
    "sg:province":"Ober\u00f6sterreich",
    "sg:tags":[
        "aluminium",
        "window"
    ],
    "sg:website":"actual.at",
    "wof:name":"ACTUAL Fenster AG",
    "wof:placetype":"venue"
},
  "geometry": {"coordinates":[14.2489337921,48.2094726562],"type":"Point"}
}