{
  "type": "Feature",
  "properties": {
    "addr:full":"S\u00fcduferstr 115 Reifnitz K\u00e4rnten 9081",
    "addr:housenumber":"115",
    "addr:postcode":"9081",
    "addr:street":"Kaernten",
    "iso:country":"AT",
    "sg:address":"S\u00fcduferstr 115",
    "sg:city":"Reifnitz",
    "sg:orig_category":"Gemeinden",
    "sg:phone":"+43 4273 20500",
    "sg:postcode":"9081",
    "sg:province":"K\u00e4rnten",
    "wof:name":"Gemeindeamt Maria W\u00f6rth",
    "wof:placetype":"venue"
},
  "geometry": {"coordinates":[14.1815433502,46.6068840027],"type":"Point"}
}