{
  "type": "Feature",
  "properties": {
    "iso:country":"AT",
    "sg:address":"Millennium Park 3",
    "sg:city":"Lustenau",
    "sg:orig_category":"Antriebstechnik",
    "sg:phone":"+43 4355 778060",
    "sg:postcode":"6890",
    "sg:province":"Vorarlberg",
    "wof:name":"ZIMM Maschinenelemente GmbH & Co",
    "wof:placetype":"venue"
},
  "geometry": {"coordinates":[9.6708745956,47.4203262329],"type":"Point"}
}