{
  "type": "Feature",
  "properties": {
    "addr:full":"Linzer Str 8 Altenberg Ober\u00f6sterreich 4203",
    "addr:housenumber":"8",
    "addr:postcode":"4203",
    "addr:street":"Linzer Str",
    "iso:country":"AT",
    "sg:address":"Linzer Str 8",
    "sg:city":"Altenberg",
    "sg:orig_category":"Friseure U Frisiersalons",
    "sg:phone":"+43 4372 308699",
    "sg:postcode":"4203",
    "sg:province":"Ober\u00f6sterreich",
    "wof:name":"Schnittzone Haarkunst by Peter Fuchs",
    "wof:placetype":"venue"
},
  "geometry": {"coordinates":[14.3484477997,48.3729553223],"type":"Point"}
}