{
  "type": "Feature",
  "properties": {
    "addr:full":"Gerhardusgasse 25 Wien Wien 1200",
    "addr:housenumber":"25",
    "addr:postcode":"1200",
    "addr:street":"Gerhardusgasse",
    "iso:country":"AT",
    "sg:address":"Gerhardusgasse 25",
    "sg:city":"Wien",
    "sg:classifiers":[
        {
            "category":"Professional",
            "subcategory":"Advertising",
            "type":"Services"
        }
    ],
    "sg:phone":"+43 1 33130300",
    "sg:postcode":"1200",
    "sg:province":"Wien",
    "sg:tags":[
        "job",
        "employment"
    ],
    "sg:website":"bezirksverlag.at",
    "wof:name":"Bezirksinformation Zeitschriftenverlag GmbH Co nfg. KG",
    "wof:placetype":"venue"
},
  "geometry": {"coordinates":[16.3670349121,48.2321090698],"type":"Point"}
}