{
  "type": "Feature",
  "properties": {
    "iso:country":"AT",
    "sg:address":"Hofstadt 20",
    "sg:city":"Ostermiething",
    "sg:orig_category":"Baumschulen",
    "sg:phone":"+43 6278 8446",
    "sg:postcode":"5121",
    "sg:province":"Ober\u00f6sterreich",
    "wof:name":"Forstbaumschule Heimo Feistritzer",
    "wof:placetype":"venue"
},
  "geometry": {"coordinates":[12.8289651871,48.0465812683],"type":"Point"}
}