{
  "type": "Feature",
  "properties": {
    "addr:full":"Fiecht 22 Vomp Tirol 6134",
    "addr:housenumber":"22",
    "addr:postcode":"6134",
    "addr:street":"Fiecht;Tirol",
    "iso:country":"AT",
    "sg:address":"Fiecht 22",
    "sg:city":"Vomp",
    "sg:classifiers":[
        {
            "category":"Building & Trades",
            "subcategory":"Cleaning & Sanitation",
            "type":"Services"
        }
    ],
    "sg:phone":"+43 5242 69030",
    "sg:postcode":"6134",
    "sg:province":"Tirol",
    "sg:tags":[
        "broom"
    ],
    "sg:website":"masta.buersten.com",
    "wof:name":"Masta Produktions- und Vertriebs GmbH",
    "wof:placetype":"venue"
},
  "geometry": {"coordinates":[11.7048397064,47.3587036133],"type":"Point"}
}