{
  "type": "Feature",
  "properties": {
    "iso:country":"AT",
    "sg:address":"St\u00f6cklgras 1c/26",
    "sg:city":"Ried im Innkreis",
    "sg:orig_category":"Werbegrafik- U Grafik-Design",
    "sg:phone":"+43 4366 49147081",
    "sg:postcode":"4910",
    "sg:province":"Ober\u00f6sterreich",
    "wof:name":"MICC-Design",
    "wof:placetype":"venue"
},
  "geometry": {"coordinates":[13.4887552261,48.2188301086],"type":"Point"}
}