{
  "type": "Feature",
  "properties": {
    "iso:country":"AT",
    "sg:address":"Florianipark 12",
    "sg:city":"Judenau",
    "sg:orig_category":"Lebensmittel / Einzelhandel",
    "sg:phone":"+43 4322 7470222",
    "sg:postcode":"3441",
    "sg:province":"Nieder\u00f6sterreich",
    "wof:name":"Spar Markt - BLAHUSCHEK GesmbH",
    "wof:placetype":"venue"
},
  "geometry": {"coordinates":[16.0102977753,48.284702301],"type":"Point"}
}