{
  "type": "Feature",
  "properties": {
    "iso:country":"AT",
    "sg:address":"Franz-Josef-Str 2",
    "sg:city":"Mistelbach",
    "sg:orig_category":"Elektroinstallationsunternehmen",
    "sg:phone":"+43 2572 2571",
    "sg:postcode":"2130",
    "sg:province":"Nieder\u00f6sterreich",
    "wof:name":"Hoffmann Ernst",
    "wof:placetype":"venue"
},
  "geometry": {"coordinates":[16.5714359283,48.5674362183],"type":"Point"}
}