{
  "type": "Feature",
  "properties": {
    "addr:full":"Nr 1 Eisentratten K\u00e4rnten 9861",
    "addr:postcode":"9861",
    "addr:street":"Nr;Eisentratten",
    "iso:country":"AT",
    "sg:address":"Nr 1",
    "sg:city":"Eisentratten",
    "sg:orig_category":"Tierpensionen",
    "sg:phone":"+43 4347 35259",
    "sg:postcode":"9861",
    "sg:province":"K\u00e4rnten",
    "wof:name":"Husky-Ranch",
    "wof:placetype":"venue"
},
  "geometry": {"coordinates":[13.5780506134,46.9226989746],"type":"Point"}
}