{
  "type": "Feature",
  "properties": {
    "iso:country":"AT",
    "sg:address":"Regenhartstr 1",
    "sg:city":"Hinterbr\u00fchl",
    "sg:orig_category":"Biologische Produkte",
    "sg:phone":"+43 4322 3623854",
    "sg:postcode":"2371",
    "sg:province":"Nieder\u00f6sterreich",
    "wof:name":"Nat\u00fcrlich - Nat\u00fcrlich",
    "wof:placetype":"venue"
},
  "geometry": {"coordinates":[16.2486515045,48.0867805481],"type":"Point"}
}