{
  "type": "Feature",
  "properties": {
    "addr:full":"Mariazeller Str 71 Traisen Nieder\u00f6sterreich 3160",
    "addr:postcode":"3160",
    "addr:street":"Str 71",
    "iso:country":"AT",
    "sg:address":"Mariazeller Str 71",
    "sg:city":"Traisen",
    "sg:orig_category":"Banken U Sparkassen",
    "sg:phone":"+43 4327 62623400",
    "sg:postcode":"3160",
    "sg:province":"Nieder\u00f6sterreich",
    "wof:name":"Bankomat d Volksbank Nieder\u00f6sterreich-Mitte regGenmbH",
    "wof:placetype":"venue"
},
  "geometry": {"coordinates":[15.6091413498,48.0401344299],"type":"Point"}
}