{
  "type": "Feature",
  "properties": {
    "addr:full":"Scheibenstr. 2 Lauterach Vorarlberg 6923",
    "addr:housenumber":"2",
    "addr:postcode":"6923",
    "addr:street":"Scheibenstr.",
    "iso:country":"AT",
    "sg:address":"Scheibenstr. 2",
    "sg:city":"Lauterach",
    "sg:classifiers":[
        {
            "category":"Wholesale",
            "subcategory":"Machinery & Supplies",
            "type":"Manufacturing & Wholesale Goods"
        }
    ],
    "sg:phone":"+43 4355 74700600",
    "sg:postcode":"6923",
    "sg:province":"Vorarlberg",
    "sg:tags":[
        "-",
        "agriculture",
        "equipment"
    ],
    "wof:name":"BAYWA VORARLBERG HANDELS GMBH",
    "wof:placetype":"venue"
},
  "geometry": {"coordinates":[9.726023674,47.4633865356],"type":"Point"}
}