{
  "type": "Feature",
  "properties": {
    "iso:country":"AT",
    "sg:address":"Nr 1",
    "sg:city":"Rosenbach",
    "sg:orig_category":"Polizei U Gendarmerie",
    "sg:phone":"+43 4359 1332271",
    "sg:postcode":"9183",
    "sg:province":"K\u00e4rnten",
    "wof:name":"Gendarmerie Grenzkontrollstelle",
    "wof:placetype":"venue"
},
  "geometry": {"coordinates":[14.0542936325,46.539478302],"type":"Point"}
}