{
  "type": "Feature",
  "properties": {
    "addr:full":"Gorskistr. 3 Wien Wien 1230",
    "addr:housenumber":"3",
    "addr:postcode":"1230",
    "addr:street":"Gorskistr.",
    "iso:country":"AT",
    "sg:address":"Gorskistr. 3",
    "sg:city":"Wien",
    "sg:classifiers":[
        {
            "category":"Autos & Motor Vehicles",
            "subcategory":"Automobile Sales",
            "type":"Retail Goods"
        }
    ],
    "sg:phone":"+43 4316 1645800",
    "sg:postcode":"1230",
    "sg:province":"Wien",
    "sg:tags":[
        "motor-cars"
    ],
    "wof:name":"PIONEER HANS LURF GMBH",
    "wof:placetype":"venue"
},
  "geometry": {"coordinates":[16.3569049835,48.1443595886],"type":"Point"}
}