{
  "type": "Feature",
  "properties": {
    "addr:full":"Wirtschaftspark 2 Deutschlandsberg Steiermark 8530",
    "addr:housenumber":"2",
    "addr:postcode":"8530",
    "addr:street":"Wirtschaftspark",
    "iso:country":"AT",
    "sg:address":"Wirtschaftspark 2",
    "sg:city":"Deutschlandsberg",
    "sg:orig_category":"Autoreparatur",
    "sg:phone":"+43 3462 2780",
    "sg:postcode":"8530",
    "sg:province":"Steiermark",
    "wof:name":"KFZ-Technik Christian Ille",
    "wof:placetype":"venue"
},
  "geometry": {"coordinates":[15.2431163788,46.8164558411],"type":"Point"}
}