{
  "type": "Feature",
  "properties": {
    "iso:country":"AT",
    "sg:address":"Kratzmanng 8",
    "sg:city":"Wien",
    "sg:classifiers":[
        {
            "category":"Professional",
            "subcategory":"Computer Services",
            "type":"Services"
        }
    ],
    "sg:phone":"+43 1 7740203",
    "sg:postcode":"1220",
    "sg:province":"Wien",
    "sg:tags":[
        "software"
    ],
    "wof:name":"Kanov Doris - Software Design & Development",
    "wof:placetype":"venue"
},
  "geometry": {"coordinates":[16.5364170074,48.2312698364],"type":"Point"}
}