{
  "type": "Feature",
  "properties": {
    "addr:full":"Moosstr 60 Salzburg Salzburg 5020",
    "addr:housenumber":"60",
    "addr:postcode":"5020",
    "addr:street":"Moosstr;Salzburg",
    "iso:country":"AT",
    "sg:address":"Moosstr 60",
    "sg:city":"Salzburg",
    "sg:classifiers":[
        {
            "category":"Professional",
            "subcategory":"Management & Consulting",
            "type":"Services"
        }
    ],
    "sg:phone":"+43 4366 2890332",
    "sg:postcode":"5020",
    "sg:province":"Salzburg",
    "sg:tags":[
        "supervision"
    ],
    "wof:name":"K\u00f6ppl Richard",
    "wof:placetype":"venue"
},
  "geometry": {"coordinates":[13.0251674652,47.7827682495],"type":"Point"}
}