{
  "type": "Feature",
  "properties": {
    "addr:full":"Robert-Musil-Str 9 Villach K\u00e4rnten 9500",
    "addr:housenumber":"9",
    "addr:postcode":"9500",
    "addr:street":"Robert-Musil-Str;Kaernten",
    "iso:country":"AT",
    "sg:address":"Robert-Musil-Str 9",
    "sg:city":"Villach",
    "sg:orig_category":"Weiterbildungsinstitute M Allg U Berufl Bildungsangebot",
    "sg:phone":"+43 4357 8783100",
    "sg:postcode":"9500",
    "sg:province":"K\u00e4rnten",
    "wof:name":"Berufsf\u00f6rderungsinstitut K\u00e4rnten Ausbildungszentrum",
    "wof:placetype":"venue"
},
  "geometry": {"coordinates":[13.8504905701,46.600643158],"type":"Point"}
}