{
  "type": "Feature",
  "properties": {
    "iso:country":"AT",
    "sg:address":"Neustiftg 98-102",
    "sg:city":"Wien",
    "sg:orig_category":"Hauptschulen",
    "sg:phone":"+43 1 5261978",
    "sg:postcode":"1070",
    "sg:province":"Wien",
    "wof:name":"Europ\u00e4ische Mittelschule",
    "wof:placetype":"venue"
},
  "geometry": {"coordinates":[16.3417434692,48.2060546875],"type":"Point"}
}