{
  "type": "Feature",
  "properties": {
    "addr:full":"Sulb 112 St. Martin im Sulmtal Steiermark 8543",
    "addr:housenumber":"112",
    "addr:postcode":"8543",
    "addr:street":"Sulb",
    "iso:country":"AT",
    "sg:address":"Sulb 112",
    "sg:city":"St. Martin im Sulmtal",
    "sg:orig_category":"\u00c3\u201erzte / F Allgemeinmedizin",
    "sg:phone":"+43 4334 6527000",
    "sg:postcode":"8543",
    "sg:province":"Steiermark",
    "wof:name":"Silly Hans Dr",
    "wof:placetype":"venue"
},
  "geometry": {"coordinates":[15.2959032059,46.7595176697],"type":"Point"}
}