{
  "type": "Feature",
  "properties": {
    "addr:full":"Wasserwerkstrasse 6 Feldkirchen Steiermark 8073",
    "addr:housenumber":"6",
    "addr:postcode":"8073",
    "addr:street":"Wasserwerkstrasse",
    "iso:country":"AT",
    "sg:address":"Wasserwerkstrasse 6",
    "sg:city":"Feldkirchen",
    "sg:classifiers":[
        {
            "category":"Home & Garden",
            "subcategory":"Building Materials",
            "type":"Retail Goods"
        }
    ],
    "sg:phone":"+43 316 296126",
    "sg:postcode":"8073",
    "sg:province":"Steiermark",
    "sg:tags":[
        "glass",
        "enclosures",
        "balcony"
    ],
    "sg:website":"glassajko.at",
    "wof:name":"Harald Sajko",
    "wof:placetype":"venue"
},
  "geometry": {"coordinates":[15.4479799271,47.0042610168],"type":"Point"}
}