{
  "type": "Feature",
  "properties": {
    "addr:full":"Boschstrasse 31 Wels Ober\u00f6sterreich 4600",
    "addr:housenumber":"31",
    "addr:postcode":"4600",
    "addr:street":"Boschstrasse;Oberoesterreich",
    "iso:country":"AT",
    "sg:address":"Boschstrasse 31",
    "sg:city":"Wels",
    "sg:classifiers":[
        {
            "category":"Professional",
            "subcategory":"Advertising",
            "type":"Services"
        }
    ],
    "sg:phone":"+43 7242 2460",
    "sg:postcode":"4600",
    "sg:province":"Ober\u00f6sterreich",
    "sg:tags":[
        "articles"
    ],
    "sg:website":"roidl.at",
    "wof:name":"Roidl Versand GmbH",
    "wof:placetype":"venue"
},
  "geometry": {"coordinates":[14.0513038635,48.1611824036],"type":"Point"}
}