{
  "type": "Feature",
  "properties": {
    "addr:full":"Innrain 100/99 Innsbruck Tirol 6020",
    "addr:housenumber":"100 / 99",
    "addr:postcode":"6020",
    "addr:street":"Innrain;Tirol",
    "iso:country":"AT",
    "sg:address":"Innrain 100/99",
    "sg:city":"Innsbruck",
    "sg:orig_category":"Lebens- U Sozialberatung",
    "sg:phone":"+43 512 562865",
    "sg:postcode":"6020",
    "sg:province":"Tirol",
    "wof:name":"Netzwerk \u00f6sterr Frauen- und M\u00e4dchenberatungsstelle",
    "wof:placetype":"venue"
},
  "geometry": {"coordinates":[11.3793668747,47.2580871582],"type":"Point"}
}