{
  "type": "Feature",
  "properties": {
    "addr:full":"Leopoldstr 26 Innsbruck Tirol 6020",
    "addr:housenumber":"26",
    "addr:postcode":"6020",
    "addr:street":"Leopoldstr;Tirol",
    "iso:country":"AT",
    "sg:address":"Leopoldstr 26",
    "sg:city":"Innsbruck",
    "sg:orig_category":"Psychotherapie",
    "sg:phone":"+43 512 563294",
    "sg:postcode":"6020",
    "sg:province":"Tirol",
    "wof:name":"Edlinger Elisabeth",
    "wof:placetype":"venue"
},
  "geometry": {"coordinates":[11.395983696,47.2598686218],"type":"Point"}
}