{
  "type": "Feature",
  "properties": {
    "addr:full":"Kastellfeldg 43 Graz Steiermark 8010",
    "addr:housenumber":"43",
    "addr:postcode":"8010",
    "addr:street":"Kastellfeldg",
    "iso:country":"AT",
    "sg:address":"Kastellfeldg 43",
    "sg:city":"Graz",
    "sg:orig_category":"Architekten",
    "sg:phone":"+43 316 303856",
    "sg:postcode":"8010",
    "sg:province":"Steiermark",
    "wof:name":"Gabbauer Walter Dipl-Ing",
    "wof:placetype":"venue"
},
  "geometry": {"coordinates":[15.4496536255,47.0615539551],"type":"Point"}
}