{
  "type": "Feature",
  "properties": {
    "iso:country":"AT",
    "sg:address":"Wagramer Str 93/6",
    "sg:city":"Wien",
    "sg:orig_category":"Non-Classified Establishments",
    "sg:phone":"+43 1 20323313",
    "sg:postcode":"1220",
    "sg:province":"Wien",
    "wof:name":"Kirchenbeitragsstelle Kagran",
    "wof:placetype":"venue"
},
  "geometry": {"coordinates":[16.4375171661,48.2443733215],"type":"Point"}
}