{
  "type": "Feature",
  "properties": {
    "addr:full":"Wolf-Dietrich-Str 4a Salzburg Salzburg 5020",
    "addr:housenumber":"4a",
    "addr:postcode":"5020",
    "addr:street":"Wolf-Dietrich-Str;Salzburg",
    "iso:country":"AT",
    "sg:address":"Wolf-Dietrich-Str 4a",
    "sg:city":"Salzburg",
    "sg:orig_category":"Damenmoden",
    "sg:phone":"+43 662 871164",
    "sg:postcode":"5020",
    "sg:province":"Salzburg",
    "wof:name":"Kunsthandwerk Hannelore Jacoby",
    "wof:placetype":"venue"
},
  "geometry": {"coordinates":[13.048415184,47.8047027588],"type":"Point"}
}