{
  "type": "Feature",
  "properties": {
    "iso:country":"AT",
    "sg:address":"Ghegag 12",
    "sg:city":"Wiener Neustadt",
    "sg:orig_category":"Maler, Anstreicher U Lackierer",
    "sg:phone":"+43 4326 2225538",
    "sg:postcode":"2700",
    "sg:province":"Nieder\u00f6sterreich",
    "wof:name":"Reiner Helmut",
    "wof:placetype":"venue"
},
  "geometry": {"coordinates":[16.2405147552,47.8246116638],"type":"Point"}
}