{
  "type": "Feature",
  "properties": {
    "addr:full":"Kirchboden 160 Wagrain Salzburg 5602",
    "addr:housenumber":"160",
    "addr:postcode":"5602",
    "addr:street":"Kirchboden;Salzburg",
    "iso:country":"AT",
    "sg:address":"Kirchboden 160",
    "sg:city":"Wagrain",
    "sg:orig_category":"Appartements / Ferienwohnungen",
    "sg:phone":"+43 6413 86760",
    "sg:postcode":"5602",
    "sg:province":"Salzburg",
    "wof:name":"Appartmenthaus Schaidreiter",
    "wof:placetype":"venue"
},
  "geometry": {"coordinates":[13.3004589081,47.3333244324],"type":"Point"}
}