{
  "type": "Feature",
  "properties": {
    "iso:country":"AT",
    "sg:address":"Kroneplatz 1",
    "sg:city":"Trumau",
    "sg:orig_category":"Cable Fittings",
    "sg:phone":"+43 2253 75210",
    "sg:postcode":"2521",
    "sg:province":"Nieder\u00f6sterreich",
    "sg:website":"krone-gmbh.at",
    "wof:name":"Krone Ges.m.b.H.",
    "wof:placetype":"venue"
},
  "geometry": {"coordinates":[16.3373260498,47.9910049438],"type":"Point"}
}