{
  "type": "Feature",
  "properties": {
    "iso:country":"AT",
    "sg:address":"Wiedner Hauptstr 106",
    "sg:city":"Wien",
    "sg:orig_category":"Medizinische Institute",
    "sg:phone":"+43 1 5455857",
    "sg:postcode":"1050",
    "sg:province":"Wien",
    "wof:name":"Impuls Institut f Gesundheitsberatung Dr Andessner KEG",
    "wof:placetype":"venue"
},
  "geometry": {"coordinates":[16.362651825,48.1856842041],"type":"Point"}
}