{
  "type": "Feature",
  "properties": {
    "addr:full":"Nr 94 Esternberg Ober\u00f6sterreich 4092",
    "addr:postcode":"4092",
    "addr:street":"Nr;Oberoesterreich",
    "iso:country":"AT",
    "sg:address":"Nr 94",
    "sg:city":"Esternberg",
    "sg:orig_category":"Banken U Sparkassen",
    "sg:phone":"+43 7714 66200",
    "sg:postcode":"4092",
    "sg:province":"Ober\u00f6sterreich",
    "wof:name":"Raiffeisenkasse Esternberg und Umgebung regGenmbH",
    "wof:placetype":"venue"
},
  "geometry": {"coordinates":[13.5718803406,48.5439147949],"type":"Point"}
}