{
  "type": "Feature",
  "properties": {
    "addr:full":"Lindenstr 5 St. Valentin Nieder\u00f6sterreich 4300",
    "addr:housenumber":"5",
    "addr:postcode":"4300",
    "addr:street":"Lindenstr",
    "iso:country":"AT",
    "sg:address":"Lindenstr 5",
    "sg:city":"St. Valentin",
    "sg:orig_category":"Autobusunternehmen",
    "sg:phone":"+43 7435 59000",
    "sg:postcode":"4300",
    "sg:province":"Nieder\u00f6sterreich",
    "wof:name":"Widhalm Raimund",
    "wof:placetype":"venue"
},
  "geometry": {"coordinates":[14.5166273117,48.1909217834],"type":"Point"}
}