{
  "type": "Feature",
  "properties": {
    "addr:full":"Wiener Str 27 Tulln an der Donau Nieder\u00f6sterreich 3430",
    "addr:postcode":"3430",
    "iso:country":"AT",
    "sg:address":"Wiener Str 27",
    "sg:city":"Tulln an der Donau",
    "sg:orig_category":"Rettungsdienste",
    "sg:phone":"+43 2272 622440",
    "sg:postcode":"3430",
    "sg:province":"Nieder\u00f6sterreich",
    "wof:name":"Rotes Kreuz \u00d6sterr Bezirksstelle Tulln",
    "wof:placetype":"venue"
},
  "geometry": {"coordinates":[16.0497398376,48.3306999207],"type":"Point"}
}