{
  "type": "Feature",
  "properties": {
    "iso:country":"AT",
    "sg:address":"Maierhofstr 19",
    "sg:city":"Neumarkt am Wallersee",
    "sg:orig_category":"Pensionen / Privatzimmer",
    "sg:phone":"+43 4362 164519",
    "sg:postcode":"5202",
    "sg:province":"Salzburg",
    "wof:name":"Pension Herzog Franz",
    "wof:placetype":"venue"
},
  "geometry": {"coordinates":[13.2191419601,47.9394607544],"type":"Point"}
}