{
  "type": "Feature",
  "properties": {
    "iso:country":"AT",
    "sg:address":"Landstr 7",
    "sg:city":"Hard",
    "sg:orig_category":"Banken U Sparkassen",
    "sg:phone":"+43 5574 784020",
    "sg:postcode":"6971",
    "sg:province":"Vorarlberg",
    "wof:name":"Vorarlberger Landes- und Hypothekenbank AG",
    "wof:placetype":"venue"
},
  "geometry": {"coordinates":[9.6893701553,47.4887237549],"type":"Point"}
}