{
  "type": "Feature",
  "properties": {
    "addr:full":"Laxenburger Str 3/6 Wiener Neudorf Nieder\u00f6sterreich 2351",
    "addr:housenumber":"3 / 6",
    "addr:postcode":"2351",
    "addr:street":"Laxenburger Str",
    "iso:country":"AT",
    "sg:address":"Laxenburger Str 3/6",
    "sg:city":"Wiener Neudorf",
    "sg:orig_category":"Steuerberatung",
    "sg:phone":"+43 4365 03333111",
    "sg:postcode":"2351",
    "sg:province":"Nieder\u00f6sterreich",
    "wof:name":"Bilanzbuchhaltung u Datenverarbeitungen Inh Andrea Flamek",
    "wof:placetype":"venue"
},
  "geometry": {"coordinates":[16.3154907227,48.0828094482],"type":"Point"}
}