{
  "type": "Feature",
  "properties": {
    "iso:country":"AT",
    "sg:address":"Gewerbestr 3",
    "sg:city":"Gols",
    "sg:orig_category":"Autohandel",
    "sg:phone":"+43 4321 732690",
    "sg:postcode":"7122",
    "sg:province":"Burgenland",
    "wof:name":"Beck Manfred",
    "wof:placetype":"venue"
},
  "geometry": {"coordinates":[16.9275074005,47.8893699646],"type":"Point"}
}