{
  "type": "Feature",
  "properties": {
    "addr:full":"Valtau 7 St. Marienkirchen an der Polsenz Ober\u00f6sterreich 4076",
    "addr:housenumber":"7",
    "addr:postcode":"4076",
    "addr:street":"Valtau",
    "iso:country":"AT",
    "sg:address":"Valtau 7",
    "sg:city":"St. Marienkirchen an der Polsenz",
    "sg:orig_category":"Bauunternehmen",
    "sg:phone":"+43 4372 4947116",
    "sg:postcode":"4076",
    "sg:province":"Ober\u00f6sterreich",
    "wof:name":"Haslinger Gerold",
    "wof:placetype":"venue"
},
  "geometry": {"coordinates":[13.9105672836,48.2785148621],"type":"Point"}
}