{
  "type": "Feature",
  "properties": {
    "addr:full":"Stoob S\u00fcd EKZ/Top 35 Oberpullendorf Burgenland 7350",
    "addr:postcode":"7350",
    "iso:country":"AT",
    "sg:address":"Stoob S\u00fcd EKZ/Top 35",
    "sg:city":"Oberpullendorf",
    "sg:orig_category":"Fenster",
    "sg:phone":"+43 2612 43944",
    "sg:postcode":"7350",
    "sg:province":"Burgenland",
    "wof:name":"Femon Hauer Herbert",
    "wof:placetype":"venue"
},
  "geometry": {"coordinates":[16.5069942474,47.4975662231],"type":"Point"}
}