{
  "type": "Feature",
  "properties": {
    "iso:country":"AT",
    "sg:address":"Hauptstr 36",
    "sg:city":"Mattersburg",
    "sg:orig_category":"Beratungsstellen",
    "sg:phone":"+43 2626 67983",
    "sg:postcode":"7210",
    "sg:province":"Burgenland",
    "wof:name":"Evang Frauenarbeit Burgenland - Hackl Susanna",
    "wof:placetype":"venue"
},
  "geometry": {"coordinates":[16.4195785522,47.7405052185],"type":"Point"}
}