{
  "type": "Feature",
  "properties": {
    "addr:full":"Landstr. 57  Tulln an der Donau Nieder\u00f6sterreich 3430",
    "addr:housenumber":"57",
    "addr:postcode":"3430",
    "addr:street":"Landstr.",
    "iso:country":"AT",
    "sg:address":"Landstr. 57 ",
    "sg:city":"Tulln an der Donau",
    "sg:classifiers":[
        {
            "category":"Autos & Motor Vehicles",
            "subcategory":"Automobile Sales",
            "type":"Retail Goods"
        }
    ],
    "sg:phone":"+43 4322 72627850",
    "sg:postcode":"3430",
    "sg:province":"Nieder\u00f6sterreich",
    "sg:tags":[
        "motor-cars"
    ],
    "wof:name":"LEOPOLD LUTZ",
    "wof:placetype":"venue"
},
  "geometry": {"coordinates":[16.0863857269,48.313999176],"type":"Point"}
}