{
  "type": "Feature",
  "properties": {
    "addr:full":"Schwemmbachstr 8 Friedburg Ober\u00f6sterreich 5211",
    "addr:housenumber":"8",
    "addr:postcode":"5211",
    "addr:street":"Schwemmbachstr",
    "iso:country":"AT",
    "sg:address":"Schwemmbachstr 8",
    "sg:city":"Friedburg",
    "sg:classifiers":[
        {
            "category":"Home & Garden",
            "subcategory":"Building Materials",
            "type":"Retail Goods"
        }
    ],
    "sg:phone":"+43 4377 463777",
    "sg:postcode":"5211",
    "sg:province":"Ober\u00f6sterreich",
    "sg:tags":[
        "baustoffe",
        "-material",
        "u"
    ],
    "wof:name":"Erdbau-Baustoffe-Asphaltierungen Schinagl",
    "wof:placetype":"venue"
},
  "geometry": {"coordinates":[13.2410087585,48.0177268982],"type":"Point"}
}