{
  "type": "Feature",
  "properties": {
    "addr:full":"Marktpl 20 Pregarten Ober\u00f6sterreich 4230",
    "addr:housenumber":"20",
    "addr:postcode":"4230",
    "addr:street":"Marktpl",
    "iso:country":"AT",
    "sg:address":"Marktpl 20",
    "sg:city":"Pregarten",
    "sg:orig_category":"Blumeneinzelhandel",
    "sg:phone":"+43 7236 7698",
    "sg:postcode":"4230",
    "sg:province":"Ober\u00f6sterreich",
    "wof:name":"St\u00fcbl's Blumenparadies",
    "wof:placetype":"venue"
},
  "geometry": {"coordinates":[14.5309858322,48.3546714783],"type":"Point"}
}