{
  "type": "Feature",
  "properties": {
    "addr:full":"Hauptstr 11 Jennersdorf Burgenland 8380",
    "addr:housenumber":"11",
    "addr:postcode":"8380",
    "addr:street":"Hauptstr",
    "iso:country":"AT",
    "sg:address":"Hauptstr 11",
    "sg:city":"Jennersdorf",
    "sg:orig_category":"Banken U Sparkassen",
    "sg:phone":"+43 4333 29452200",
    "sg:postcode":"8380",
    "sg:province":"Burgenland",
    "wof:name":"Bankomat d Raiffeisen-Bezirksbank Jennersdorf regGenmbH",
    "wof:placetype":"venue"
},
  "geometry": {"coordinates":[16.1379909515,46.937046051],"type":"Point"}
}