{
  "type": "Feature",
  "properties": {
    "addr:full":"Niederhofen 16 St. Johann in Tirol Tirol 6380",
    "addr:housenumber":"16",
    "addr:postcode":"6380",
    "addr:street":"Niederhofen;Tirol",
    "iso:country":"AT",
    "sg:address":"Niederhofen 16",
    "sg:city":"St. Johann in Tirol",
    "sg:orig_category":"Isolierungen",
    "sg:phone":"+43 5352 62870",
    "sg:postcode":"6380",
    "sg:province":"Tirol",
    "wof:name":"Springinsfeld Hans GesmbH",
    "wof:placetype":"venue"
},
  "geometry": {"coordinates":[12.4393844604,47.5345573425],"type":"Point"}
}