{
  "type": "Feature",
  "properties": {
    "addr:full":"Schelleing 14 Wien Wien 1040",
    "addr:housenumber":"14",
    "addr:postcode":"1040",
    "addr:street":"Schelleing",
    "iso:country":"AT",
    "sg:address":"Schelleing 14",
    "sg:city":"Wien",
    "sg:orig_category":"Filmproduktionen",
    "sg:phone":"+43 1 5037990",
    "sg:postcode":"1040",
    "sg:province":"Wien",
    "sg:website":"closeup.at",
    "wof:name":"Close up FilmgesmbH",
    "wof:placetype":"venue"
},
  "geometry": {"coordinates":[16.3750133514,48.1875686646],"type":"Point"}
}