{
  "type": "Feature",
  "properties": {
    "addr:full":"Dr Georg Prader-Str 13/7 Langenzersdorf Nieder\u00f6sterreich 2103",
    "addr:housenumber":"13 / 7",
    "addr:postcode":"2103",
    "iso:country":"AT",
    "sg:address":"Dr Georg Prader-Str 13/7",
    "sg:city":"Langenzersdorf",
    "sg:orig_category":"Ingenieurkonsulenten / Zivilingenieure",
    "sg:phone":"+43 2244 30942",
    "sg:postcode":"2103",
    "sg:province":"Nieder\u00f6sterreich",
    "wof:name":"Konzept Raumplanung und Projektmanagement GmbH",
    "wof:placetype":"venue"
},
  "geometry": {"coordinates":[16.376411438,48.2982940674],"type":"Point"}
}