{
  "type": "Feature",
  "properties": {
    "addr:full":"Mondseer Bundesstr 1 St. Gilgen Salzburg 5340",
    "addr:housenumber":"1",
    "addr:postcode":"5340",
    "addr:street":"Bundesstr",
    "iso:country":"AT",
    "sg:address":"Mondseer Bundesstr 1",
    "sg:city":"St. Gilgen",
    "sg:orig_category":"Lebensmittel / Einzelhandel",
    "sg:phone":"+43 6227 8903",
    "sg:postcode":"5340",
    "sg:province":"Salzburg",
    "wof:name":"SPAR \u00f6sterreichische Warenhandels-AG",
    "wof:placetype":"venue"
},
  "geometry": {"coordinates":[13.3596963882,47.7693328857],"type":"Point"}
}