{
  "type": "Feature",
  "properties": {
    "addr:full":"Klein Meiseldorfer Str 4 Sigmundsherberg Nieder\u00f6sterreich 3751",
    "addr:housenumber":"4",
    "addr:postcode":"3751",
    "addr:street":"Klein;Str",
    "iso:country":"AT",
    "sg:address":"Klein Meiseldorfer Str 4",
    "sg:city":"Sigmundsherberg",
    "sg:orig_category":"Tischlereien",
    "sg:phone":"+43 4329 832234",
    "sg:postcode":"3751",
    "sg:province":"Nieder\u00f6sterreich",
    "wof:name":"Kreindl G\u00fcnther",
    "wof:placetype":"venue"
},
  "geometry": {"coordinates":[15.7240533829,48.6853027344],"type":"Point"}
}