{
  "type": "Feature",
  "properties": {
    "iso:country":"AT",
    "sg:address":"Nr 1",
    "sg:city":"Mehrnbach",
    "sg:orig_category":"Banken U Sparkassen",
    "sg:phone":"+43 7752 820120",
    "sg:postcode":"4941",
    "sg:province":"Ober\u00f6sterreich",
    "wof:name":"Raiffeisenbank Region Ried regGenmbH",
    "wof:placetype":"venue"
},
  "geometry": {"coordinates":[13.4352054596,48.2079963684],"type":"Point"}
}