{
  "type": "Feature",
  "properties": {
    "addr:full":"Lannesstr 52-54 Wien Wien 1220",
    "addr:postcode":"52-54;1220",
    "iso:country":"AT",
    "sg:address":"Lannesstr 52-54",
    "sg:city":"Wien",
    "sg:orig_category":"Speditionen",
    "sg:phone":"+43 1 7749693",
    "sg:postcode":"1220",
    "sg:province":"Wien",
    "wof:name":"Srsen Viktor Transportberatung & Frachtenreklamation",
    "wof:placetype":"venue"
},
  "geometry": {"coordinates":[16.5102424622,48.2097587585],"type":"Point"}
}