{
  "type": "Feature",
  "properties": {
    "addr:full":"Niedermoos 13 Lassing Steiermark 8903",
    "addr:housenumber":"13",
    "addr:postcode":"8903",
    "addr:street":"Niedermoos",
    "iso:country":"AT",
    "sg:address":"Niedermoos 13",
    "sg:city":"Lassing",
    "sg:orig_category":"Transportunternehmen",
    "sg:phone":"+43 3612 82173",
    "sg:postcode":"8903",
    "sg:province":"Steiermark",
    "wof:name":"Eder Karl",
    "wof:placetype":"venue"
},
  "geometry": {"coordinates":[14.2765655518,47.5320625305],"type":"Point"}
}