{
  "type": "Feature",
  "properties": {
    "addr:full":"Marktstrasse 6 Peilstein im M\u00fchlviertel Ober\u00f6sterreich 4153",
    "addr:housenumber":"6",
    "addr:postcode":"4153",
    "addr:street":"Marktstrasse;Im Muehlviertel Oberoesterreich",
    "iso:country":"AT",
    "sg:address":"Marktstrasse 6",
    "sg:city":"Peilstein im M\u00fchlviertel",
    "sg:classifiers":[
        {
            "category":"Home & Garden",
            "subcategory":"Household Appliances",
            "type":"Retail Goods"
        }
    ],
    "sg:phone":"+43 7287 7247",
    "sg:postcode":"4153",
    "sg:province":"Ober\u00f6sterreich",
    "sg:tags":[
        "electric"
    ],
    "wof:name":"Joachim V\u00f6ltl",
    "wof:placetype":"venue"
},
  "geometry": {"coordinates":[13.8674449921,48.6588592529],"type":"Point"}
}