{
  "type": "Feature",
  "properties": {
    "iso:country":"AT",
    "sg:address":"Degeng 20",
    "sg:city":"Wien",
    "sg:classifiers":[
        {
            "category":"Shopping",
            "subcategory":"Party Supplies",
            "type":"Retail Goods"
        }
    ],
    "sg:phone":"+43 4319 2913300",
    "sg:postcode":"1160",
    "sg:province":"Wien",
    "sg:tags":[
        "u",
        "lichtanlagen",
        "ton-"
    ],
    "wof:name":"Art-Promotion Ton- u Lichtanlagenverleih u Indoor Feuerwerke",
    "wof:placetype":"venue"
},
  "geometry": {"coordinates":[16.3174304962,48.2151222229],"type":"Point"}
}