{
  "type": "Feature",
  "properties": {
    "addr:full":"Nr 86 Bad Blumau Steiermark 8283",
    "addr:housenumber":"86",
    "addr:postcode":"8283",
    "addr:street":"Nr",
    "iso:country":"AT",
    "sg:address":"Nr 86",
    "sg:city":"Bad Blumau",
    "sg:classifiers":[
        {
            "category":"Taxi",
            "type":"Transportation"
        }
    ],
    "sg:phone":"+43 4333 833311",
    "sg:postcode":"8283",
    "sg:province":"Steiermark",
    "sg:tags":[
        "personentransporte",
        "u"
    ],
    "wof:name":"Paar Johannes Ing - Mietwagenunternehmen",
    "wof:placetype":"venue"
},
  "geometry": {"coordinates":[16.0523548126,47.1159667969],"type":"Point"}
}