{
  "type": "Feature",
  "properties": {
    "addr:full":"Industriestra\u00dfe B 12 Brunn am Gebirge Nieder\u00f6sterreich 2345",
    "addr:housenumber":"12",
    "addr:postcode":"2345",
    "addr:street":"Industriestrasse B",
    "iso:country":"AT",
    "sg:address":"Industriestra\u00dfe B 12",
    "sg:city":"Brunn am Gebirge",
    "sg:orig_category":"Speditionen",
    "sg:phone":"+43 4322 36379777",
    "sg:postcode":"2345",
    "sg:province":"Nieder\u00f6sterreich",
    "wof:name":"GEEST - PANTA RHEI Befrachtungs- u Speditions GmbH",
    "wof:placetype":"venue"
},
  "geometry": {"coordinates":[16.2839355469,48.107170105],"type":"Point"}
}