{
  "type": "Feature",
  "properties": {
    "addr:full":"Kreuzfeldh\u00f6he 266 Ilz Steiermark 8262",
    "addr:housenumber":"266",
    "addr:postcode":"8262",
    "iso:country":"AT",
    "sg:address":"Kreuzfeldh\u00f6he 266",
    "sg:city":"Ilz",
    "sg:orig_category":"Baumeister",
    "sg:phone":"+43 3385 7959",
    "sg:postcode":"8262",
    "sg:province":"Steiermark",
    "wof:name":"Puffing Werner Bmstr Ing",
    "wof:placetype":"venue"
},
  "geometry": {"coordinates":[15.9260549545,47.086479187],"type":"Point"}
}