{
  "type": "Feature",
  "properties": {
    "addr:full":"Operng 16 Wien Wien 1010",
    "addr:housenumber":"16",
    "addr:postcode":"1010",
    "addr:street":"Operng",
    "iso:country":"AT",
    "sg:address":"Operng 16",
    "sg:city":"Wien",
    "sg:orig_category":"Apotheken",
    "sg:phone":"+43 1 5877367",
    "sg:postcode":"1010",
    "sg:province":"Wien",
    "wof:name":"Apotheke z heiligen Geist Mag pharm Margarethe Trepka",
    "wof:placetype":"venue"
},
  "geometry": {"coordinates":[16.3671951294,48.2015647888],"type":"Point"}
}