{
  "type": "Feature",
  "properties": {
    "addr:full":"Erhardstr 70 Breitenau am Hochlantsch Steiermark 8614",
    "addr:housenumber":"70",
    "addr:postcode":"8614",
    "addr:street":"Erhardstr",
    "iso:country":"AT",
    "sg:address":"Erhardstr 70",
    "sg:city":"Breitenau am Hochlantsch",
    "sg:orig_category":"Institute",
    "sg:phone":"+43 4338 6627000",
    "sg:postcode":"8614",
    "sg:province":"Steiermark",
    "wof:name":"IUE Institut f\u00fcr Umweltme\u00dftechnik u Emissionsfragen GmbH",
    "wof:placetype":"venue"
},
  "geometry": {"coordinates":[15.464884758,47.3853149414],"type":"Point"}
}