{
  "type": "Feature",
  "properties": {
    "iso:country":"AT",
    "sg:address":"Treietstr 49",
    "sg:city":"Rankweil",
    "sg:orig_category":"Eisenwaren",
    "sg:phone":"+43 5522 319810",
    "sg:postcode":"6830",
    "sg:province":"Vorarlberg",
    "wof:name":"Schachermayer Gro\u00dfhandelsgesmbH",
    "wof:placetype":"venue"
},
  "geometry": {"coordinates":[9.6238899231,47.2891387939],"type":"Point"}
}