{
  "type": "Feature",
  "properties": {
    "iso:country":"AT",
    "sg:address":"Marktpl 13",
    "sg:city":"Perchtoldsdorf",
    "sg:orig_category":"Glasereien",
    "sg:phone":"+43 1 8693586",
    "sg:postcode":"2380",
    "sg:province":"Nieder\u00f6sterreich",
    "wof:name":"H\u00f6ninger Johannes Glasveredelungs- und HandelsgmbH",
    "wof:placetype":"venue"
},
  "geometry": {"coordinates":[16.265619278,48.1189117432],"type":"Point"}
}