{
  "type": "Feature",
  "properties": {
    "addr:full":"Linzer Str 410 Wien Wien 1140",
    "addr:housenumber":"410",
    "addr:postcode":"1140",
    "addr:street":"Linzer Str",
    "iso:country":"AT",
    "sg:address":"Linzer Str 410",
    "sg:city":"Wien",
    "sg:orig_category":"Ingenieurkonsulenten / Zivilingenieure",
    "sg:phone":"+43 1 9143145",
    "sg:postcode":"1140",
    "sg:province":"Wien",
    "wof:name":"Turnovszky Fritz Dipl-Ing",
    "wof:placetype":"venue"
},
  "geometry": {"coordinates":[16.259344101,48.2019348145],"type":"Point"}
}