{
  "type": "Feature",
  "properties": {
    "addr:full":"Wurlitzerg 10 Wien Wien 1160",
    "addr:housenumber":"10",
    "addr:postcode":"1160",
    "addr:street":"Wurlitzerg",
    "iso:country":"AT",
    "sg:address":"Wurlitzerg 10",
    "sg:city":"Wien",
    "sg:orig_category":"Tiertransporte",
    "sg:phone":"+43 1 4861234",
    "sg:postcode":"1160",
    "sg:province":"Wien",
    "wof:name":"Passek GesmbH Sportpferdetransporte und Futtermittelhandel",
    "wof:placetype":"venue"
},
  "geometry": {"coordinates":[16.3170814514,48.2128372192],"type":"Point"}
}