{
  "type": "Feature",
  "properties": {
    "addr:full":"Dresdner Str 80 Wien Wien 1200",
    "addr:postcode":"1200",
    "addr:street":"Str 80",
    "iso:country":"AT",
    "sg:address":"Dresdner Str 80",
    "sg:city":"Wien",
    "sg:classifiers":[
        {
            "category":"Taxi",
            "type":"Transportation"
        }
    ],
    "sg:phone":"+43 699 11001651",
    "sg:postcode":"1200",
    "sg:province":"Wien",
    "sg:tags":[
        "personentransporte",
        "u"
    ],
    "wof:name":"AK-Taxibetriebs GmbH",
    "wof:placetype":"venue"
},
  "geometry": {"coordinates":[16.382270813,48.2343559265],"type":"Point"}
}