{
  "type": "Feature",
  "properties": {
    "addr:full":"Am Steinriegl 18 Hintersdorf Nieder\u00f6sterreich 3413",
    "addr:housenumber":"18",
    "addr:postcode":"3413",
    "addr:street":"Am Steinriegl;Niederoesterreich",
    "iso:country":"AT",
    "sg:address":"Am Steinriegl 18",
    "sg:city":"Hintersdorf",
    "sg:orig_category":"Handelsagenturen",
    "sg:phone":"+43 1 4402187",
    "sg:postcode":"3413",
    "sg:province":"Nieder\u00f6sterreich",
    "wof:name":"Richter Rudolf",
    "wof:placetype":"venue"
},
  "geometry": {"coordinates":[16.2054347992,48.2764625549],"type":"Point"}
}