{
  "type": "Feature",
  "properties": {
    "iso:country":"AT",
    "sg:address":"Hadeldorfstr 43",
    "sg:city":"Rankweil",
    "sg:orig_category":"Speditionen",
    "sg:phone":"+43 5522 4950",
    "sg:postcode":"6830",
    "sg:province":"Vorarlberg",
    "wof:name":"Quehenberger Logistik AG & Co KG",
    "wof:placetype":"venue"
},
  "geometry": {"coordinates":[9.6378202438,47.276550293],"type":"Point"}
}