{
  "type": "Feature",
  "properties": {
    "addr:full":"Bachwinkel 65 Saalfelden am Steinernen Meer Salzburg 5760",
    "addr:housenumber":"65",
    "addr:postcode":"5760",
    "addr:street":"Bachwinkel;Salzburg",
    "iso:country":"AT",
    "sg:address":"Bachwinkel 65",
    "sg:city":"Saalfelden am Steinernen Meer",
    "sg:orig_category":"Sprachschulen U -Unterricht",
    "sg:phone":"+43 4365 8272172",
    "sg:postcode":"5760",
    "sg:province":"Salzburg",
    "sg:website":"sbg.at/sprachferien",
    "wof:name":"Somerset Language School Sprachferien in England",
    "wof:placetype":"venue"
},
  "geometry": {"coordinates":[12.8623638153,47.4410018921],"type":"Point"}
}