{
  "type": "Feature",
  "properties": {
    "addr:full":"Tanzbergweg 2 Bruck an der Mur Steiermark 8600",
    "addr:housenumber":"2",
    "addr:postcode":"8600",
    "addr:street":"Tanzbergweg",
    "iso:country":"AT",
    "sg:address":"Tanzbergweg 2",
    "sg:city":"Bruck an der Mur",
    "sg:classifiers":[
        {
            "category":"Wholesale",
            "subcategory":"Plants",
            "type":"Manufacturing & Wholesale Goods"
        }
    ],
    "sg:phone":"+43 3862 52753",
    "sg:postcode":"8600",
    "sg:province":"Steiermark",
    "sg:tags":[
        "air-conditioning",
        "fresh-air",
        "supply"
    ],
    "wof:name":"Elektro Installation Wartung Ges.m.b.H.",
    "wof:placetype":"venue"
},
  "geometry": {"coordinates":[15.2696752548,47.4059066772],"type":"Point"}
}