{
  "type": "Feature",
  "properties": {
    "addr:full":"Maria-Hilfer-Str. 103  Wien Wien 1060",
    "addr:housenumber":"103",
    "addr:postcode":"1060",
    "iso:country":"AT",
    "sg:address":"Maria-Hilfer-Str. 103 ",
    "sg:city":"Wien",
    "sg:classifiers":[
        {
            "category":"Professional",
            "subcategory":"Advertising",
            "type":"Services"
        }
    ],
    "sg:phone":"+43 4315 967020",
    "sg:postcode":"1060",
    "sg:province":"Wien",
    "sg:tags":[
        "communication",
        "medium"
    ],
    "wof:name":"DR. KARL JURKA POLITIK - & MARKETINGBERATUNG GMBH",
    "wof:placetype":"venue"
},
  "geometry": {"coordinates":[16.3452720642,48.1968421936],"type":"Point"}
}