{
  "type": "Feature",
  "properties": {
    "addr:full":"Hub 1 St. Veit Steiermark 8046",
    "addr:housenumber":"1",
    "addr:postcode":"8046",
    "addr:street":"Hub",
    "iso:country":"AT",
    "sg:address":"Hub 1",
    "sg:city":"St. Veit",
    "sg:orig_category":"Volksschulen",
    "sg:phone":"+43 4331 6693726",
    "sg:postcode":"8046",
    "sg:province":"Steiermark",
    "wof:name":"Volksschule",
    "wof:placetype":"venue"
},
  "geometry": {"coordinates":[15.4166822433,47.1517868042],"type":"Point"}
}