{
  "type": "Feature",
  "properties": {
    "addr:full":"Rainergasse 38 Wien Wien 1050",
    "addr:housenumber":"38",
    "addr:postcode":"1050",
    "addr:street":"Rainergasse",
    "iso:country":"AT",
    "sg:address":"Rainergasse 38",
    "sg:city":"Wien",
    "sg:orig_category":"Internet Studies, Online Studies For Market Research, Online Studies",
    "sg:phone":"+43 1 546700",
    "sg:postcode":"1050",
    "sg:province":"Wien",
    "sg:website":"ifes.at/",
    "wof:name":"Institut f\u00fcr empirische Sozialforschung (IFES) Ges.m.b.H.",
    "wof:placetype":"venue"
},
  "geometry": {"coordinates":[16.3643093109,48.1869926453],"type":"Point"}
}