{
  "type": "Feature",
  "properties": {
    "addr:full":"Unterjahring 19 A St. Nikolai im Sausal Steiermark 8505",
    "addr:housenumber":"19",
    "addr:postcode":"8505",
    "addr:street":"Unterjahring;A St.",
    "iso:country":"AT",
    "sg:address":"Unterjahring 19 A",
    "sg:city":"St. Nikolai im Sausal",
    "sg:classifiers":[
        {
            "category":"Professional",
            "subcategory":"Advertising",
            "type":"Services"
        }
    ],
    "sg:phone":"+43 3185 6177",
    "sg:postcode":"8505",
    "sg:province":"Steiermark",
    "sg:tags":[
        "agency"
    ],
    "sg:website":"ervolk.at",
    "wof:name":"ErVolk Volkmar P\u00f6tsch Werbeagentur",
    "wof:placetype":"venue"
},
  "geometry": {"coordinates":[15.4738378525,46.8103904724],"type":"Point"}
}