{
  "type": "Feature",
  "properties": {
    "addr:full":"F\u00f6hrenwald 17 Leutasch Tirol 6105",
    "addr:housenumber":"17",
    "addr:postcode":"6105",
    "addr:street":"Foehrenwald;Tirol",
    "iso:country":"AT",
    "sg:address":"F\u00f6hrenwald 17",
    "sg:city":"Leutasch",
    "sg:orig_category":"Appartements / Ferienwohnungen",
    "sg:phone":"+43 5214 6477",
    "sg:postcode":"6105",
    "sg:province":"Tirol",
    "wof:name":"Post Margit",
    "wof:placetype":"venue"
},
  "geometry": {"coordinates":[11.1683940887,47.374042511],"type":"Point"}
}