{
  "type": "Feature",
  "properties": {
    "addr:full":"Parsennweg 3 Ludesch Vorarlberg 6713",
    "addr:housenumber":"3",
    "addr:postcode":"6713",
    "addr:street":"Parsennweg",
    "iso:country":"AT",
    "sg:address":"Parsennweg 3",
    "sg:city":"Ludesch",
    "sg:orig_category":"Werbeagenturen",
    "sg:phone":"+43 5550 3991",
    "sg:postcode":"6713",
    "sg:province":"Vorarlberg",
    "wof:name":"TM Hechenberger",
    "wof:placetype":"venue"
},
  "geometry": {"coordinates":[9.7797231674,47.1841316223],"type":"Point"}
}