{
  "type": "Feature",
  "properties": {
    "addr:full":"Treietstr 21b Klaus-Weiler Vorarlberg 6833",
    "addr:housenumber":"21b",
    "addr:postcode":"klaus-weiler;6833",
    "addr:street":"Treietstr",
    "iso:country":"AT",
    "sg:address":"Treietstr 21b",
    "sg:city":"Klaus-Weiler",
    "sg:orig_category":"Massagen",
    "sg:phone":"+43 4355 2354325",
    "sg:postcode":"6833",
    "sg:province":"Vorarlberg",
    "wof:name":"Edlinger Renate Massagepraxis",
    "wof:placetype":"venue"
},
  "geometry": {"coordinates":[9.647190094,47.3041915894],"type":"Point"}
}