{
  "type": "Feature",
  "properties": {
    "addr:full":"Graben 24 Hausmening Nieder\u00f6sterreich 3363",
    "addr:housenumber":"24",
    "addr:postcode":"3363",
    "addr:street":"Graben",
    "iso:country":"AT",
    "sg:address":"Graben 24",
    "sg:city":"Hausmening",
    "sg:classifiers":[
        {
            "category":"Home & Garden",
            "subcategory":"Kitchen Supply",
            "type":"Retail Goods"
        }
    ],
    "sg:phone":"+43 7475 523270",
    "sg:postcode":"3363",
    "sg:province":"Nieder\u00f6sterreich",
    "sg:tags":[
        "household",
        "electric",
        "cooker"
    ],
    "sg:website":"elektro-spreitzer.at",
    "wof:name":"Elektro Spreitzer GmbH",
    "wof:placetype":"venue"
},
  "geometry": {"coordinates":[14.828209877,48.0780105591],"type":"Point"}
}