{
  "type": "Feature",
  "properties": {
    "iso:country":"AT",
    "sg:address":"Fischerg 5",
    "sg:city":"Wels",
    "sg:orig_category":"Maler, Anstreicher U Lackierer",
    "sg:phone":"+43 7242 46002",
    "sg:postcode":"4600",
    "sg:province":"Ober\u00f6sterreich",
    "wof:name":"Oberbauer Adolf KG",
    "wof:placetype":"venue"
},
  "geometry": {"coordinates":[14.0291185379,48.1578521729],"type":"Point"}
}