{
  "type": "Feature",
  "properties": {
    "addr:full":"Rennweg 65 Wien Wien 1030",
    "addr:housenumber":"65",
    "addr:postcode":"1030",
    "addr:street":"Rennweg",
    "iso:country":"AT",
    "sg:address":"Rennweg 65",
    "sg:city":"Wien",
    "sg:orig_category":"Lebensmittel / Einzelhandel",
    "sg:phone":"+43 1 9610356",
    "sg:postcode":"1030",
    "sg:province":"Wien",
    "wof:name":"Billa AG",
    "wof:placetype":"venue"
},
  "geometry": {"coordinates":[16.3916034698,48.1935195923],"type":"Point"}
}