{
  "type": "Feature",
  "properties": {
    "addr:full":"Nr 47 Sankt Michael ob Bleiburg K\u00e4rnten 9143",
    "addr:postcode":"9143",
    "addr:street":"Nr;Sankt;Ob Bleiburg Kaernten",
    "iso:country":"AT",
    "sg:address":"Nr 47",
    "sg:city":"Sankt Michael ob Bleiburg",
    "sg:orig_category":"Schleif- U Poliermittel",
    "sg:phone":"+43 4342 3535500",
    "sg:postcode":"9143",
    "sg:province":"K\u00e4rnten",
    "wof:name":"Cobra Produktions- u HandelsgesmbH",
    "wof:placetype":"venue"
},
  "geometry": {"coordinates":[14.7621669769,46.5607833862],"type":"Point"}
}