{
  "type": "Feature",
  "properties": {
    "iso:country":"AT",
    "sg:address":"Getreideg 11",
    "sg:city":"Salzburg",
    "sg:orig_category":"Exporteure U Importeure",
    "sg:phone":"+43 4366 24313160",
    "sg:postcode":"5020",
    "sg:province":"Salzburg",
    "wof:name":"Balluff Helmuth & Co",
    "wof:placetype":"venue"
},
  "geometry": {"coordinates":[13.0431575775,47.7999458313],"type":"Point"}
}