{
  "type": "Feature",
  "properties": {
    "addr:full":"S\u00f6llingerwald 27 Purgstall an der Erlauf Nieder\u00f6sterreich 3251",
    "addr:housenumber":"27",
    "addr:postcode":"3251",
    "addr:street":"Soellingerwald;Niederoesterreich",
    "iso:country":"AT",
    "sg:address":"S\u00f6llingerwald 27",
    "sg:city":"Purgstall an der Erlauf",
    "sg:classifiers":[
        {
            "category":"Manufacturing",
            "subcategory":"Furniture",
            "type":"Manufacturing & Wholesale Goods"
        }
    ],
    "sg:phone":"+43 7489 2743",
    "sg:postcode":"3251",
    "sg:province":"Nieder\u00f6sterreich",
    "sg:tags":[
        "bedroom"
    ],
    "wof:name":"Ignaz Baierl",
    "wof:placetype":"venue"
},
  "geometry": {"coordinates":[15.1365499496,48.0572319031],"type":"Point"}
}