{
  "type": "Feature",
  "properties": {
    "addr:full":"Krumerweg 9 Thaur Tirol 6065",
    "addr:housenumber":"9",
    "addr:postcode":"6065",
    "addr:street":"Krumerweg;Tirol",
    "iso:country":"AT",
    "sg:address":"Krumerweg 9",
    "sg:city":"Thaur",
    "sg:orig_category":"Fotografen",
    "sg:phone":"+43 5223 492803",
    "sg:postcode":"6065",
    "sg:province":"Tirol",
    "wof:name":"Foto-Studio Dorfstetter Hubert",
    "wof:placetype":"venue"
},
  "geometry": {"coordinates":[11.4742822647,47.2964477539],"type":"Point"}
}