{
  "type": "Feature",
  "properties": {
    "addr:full":"Franz-Josefs-Kai 17/20 Wien Wien 1010",
    "addr:housenumber":"17 / 20",
    "addr:postcode":"1010",
    "addr:street":"Franz-Josefs-Kai",
    "iso:country":"AT",
    "sg:address":"Franz-Josefs-Kai 17/20",
    "sg:city":"Wien",
    "sg:orig_category":"Transportunternehmen",
    "sg:phone":"+43 699 12810635",
    "sg:postcode":"1010",
    "sg:province":"Wien",
    "wof:name":"Milicevic Milenko KEG",
    "wof:placetype":"venue"
},
  "geometry": {"coordinates":[16.3772983551,48.211353302],"type":"Point"}
}