{
  "type": "Feature",
  "properties": {
    "addr:full":"G\u00f6lsentalstr 85 St. Veit an der G\u00f6lsen Nieder\u00f6sterreich 3161",
    "addr:housenumber":"85",
    "addr:postcode":"3161",
    "addr:street":"Goelsentalstr;Niederoesterreich",
    "iso:country":"AT",
    "sg:address":"G\u00f6lsentalstr 85",
    "sg:city":"St. Veit an der G\u00f6lsen",
    "sg:orig_category":"Maler, Anstreicher U Lackierer",
    "sg:phone":"+43 4327 6325001",
    "sg:postcode":"3161",
    "sg:province":"Nieder\u00f6sterreich",
    "wof:name":"Zikoli GmbH",
    "wof:placetype":"venue"
},
  "geometry": {"coordinates":[15.6530990601,48.0464668274],"type":"Point"}
}