{
  "type": "Feature",
  "properties": {
    "addr:full":"Schulg 7 Hainfeld Nieder\u00f6sterreich 3170",
    "addr:housenumber":"7",
    "addr:postcode":"3170",
    "addr:street":"Schulg",
    "iso:country":"AT",
    "sg:address":"Schulg 7",
    "sg:city":"Hainfeld",
    "sg:orig_category":"Musikunterricht",
    "sg:phone":"+43 2764 3670",
    "sg:postcode":"3170",
    "sg:province":"Nieder\u00f6sterreich",
    "wof:name":"Musikschule Hainfeld",
    "wof:placetype":"venue"
},
  "geometry": {"coordinates":[15.7709789276,48.034412384],"type":"Point"}
}