{
  "type": "Feature",
  "properties": {
    "iso:country":"AT",
    "sg:address":"Raiffeisenstr 1",
    "sg:city":"Deutschlandsberg",
    "sg:orig_category":"Bankomat-Standorte",
    "sg:phone":"+43 3462 24010",
    "sg:postcode":"8530",
    "sg:province":"Steiermark",
    "wof:name":"Bankomat d Raiffeisenbank Deutschlandsberg",
    "wof:placetype":"venue"
},
  "geometry": {"coordinates":[15.2260599136,46.8190345764],"type":"Point"}
}