{
  "type": "Feature",
  "properties": {
    "iso:country":"AT",
    "sg:address":"Keplerg 2",
    "sg:city":"Wien",
    "sg:classifiers":[
        {
            "category":"Restaurant",
            "type":"Food & Drink"
        }
    ],
    "sg:phone":"+43 4316 000606",
    "sg:postcode":"1100",
    "sg:province":"Wien",
    "sg:tags":[
        "pizzeria"
    ],
    "wof:name":"Casa Frascati",
    "wof:placetype":"venue"
},
  "geometry": {"coordinates":[16.3792896271,48.1798973083],"type":"Point"}
}