{
  "type": "Feature",
  "properties": {
    "addr:full":"Sackstr 3-5 Graz Steiermark 8010",
    "addr:housenumber":"3-5",
    "addr:postcode":"8010",
    "addr:street":"Sackstr",
    "iso:country":"AT",
    "sg:address":"Sackstr 3-5",
    "sg:city":"Graz",
    "sg:orig_category":"Bars-Cafes",
    "sg:phone":"+43 316 8116160",
    "sg:postcode":"8010",
    "sg:province":"Steiermark",
    "wof:name":"Bar Ernst Fuchs",
    "wof:placetype":"venue"
},
  "geometry": {"coordinates":[15.4373273849,47.0716781616],"type":"Point"}
}