{
  "type": "Feature",
  "properties": {
    "iso:country":"AT",
    "sg:address":"Stifterstr 22",
    "sg:city":"Linz",
    "sg:orig_category":"Genossenschaften",
    "sg:phone":"+43 732 7732740",
    "sg:postcode":"4020",
    "sg:province":"Ober\u00f6sterreich",
    "wof:name":"Gemeinn\u00fctzige Donaul\u00e4ndische Wohnungsgenossenschaft eingetr GenmbH",
    "wof:placetype":"venue"
},
  "geometry": {"coordinates":[14.2838859558,48.29945755],"type":"Point"}
}