{
  "type": "Feature",
  "properties": {
    "addr:full":"Hernalser Hauptstr 158 Wien Wien 1170",
    "addr:housenumber":"158",
    "addr:postcode":"1170",
    "addr:street":"Hernalser Hauptstr",
    "iso:country":"AT",
    "sg:address":"Hernalser Hauptstr 158",
    "sg:city":"Wien",
    "sg:classifiers":[
        {
            "category":"Professional",
            "subcategory":"Computer Services",
            "type":"Services"
        }
    ],
    "sg:phone":"+43 1 47827740",
    "sg:postcode":"1170",
    "sg:province":"Wien",
    "sg:tags":[
        "software"
    ],
    "wof:name":"Bauer Advanced Network Solutions KEG",
    "wof:placetype":"venue"
},
  "geometry": {"coordinates":[16.3188972473,48.2227020264],"type":"Point"}
}