{
  "type": "Feature",
  "properties": {
    "iso:country":"AT",
    "sg:address":"Westbahnstrasse 33",
    "sg:city":"Wien",
    "sg:classifiers":[
        {
            "category":"Professional",
            "subcategory":"Advertising",
            "type":"Services"
        }
    ],
    "sg:phone":"+43 1 5241744",
    "sg:postcode":"1070",
    "sg:province":"Wien",
    "sg:tags":[
        "agency"
    ],
    "wof:name":"DeBerners Wolfgang u. Gabriele Berner GmbH",
    "wof:placetype":"venue"
},
  "geometry": {"coordinates":[16.3413238525,48.2017021179],"type":"Point"}
}