{
  "type": "Feature",
  "properties": {
    "addr:full":"Waltendorfer Hauptstr 27 St. Peter Steiermark 8042",
    "addr:housenumber":"27",
    "addr:postcode":"8042",
    "addr:street":"Waltendorfer Hauptstr",
    "iso:country":"AT",
    "sg:address":"Waltendorfer Hauptstr 27",
    "sg:city":"St. Peter",
    "sg:orig_category":"Werbegrafik- U Grafik-Design",
    "sg:phone":"+43 4331 6426949",
    "sg:postcode":"8042",
    "sg:province":"Steiermark",
    "wof:name":"Mangold - Grafik-Design",
    "wof:placetype":"venue"
},
  "geometry": {"coordinates":[15.4685325623,47.0667991638],"type":"Point"}
}