{
  "type": "Feature",
  "properties": {
    "iso:country":"AT",
    "sg:address":"Mondscheing 16",
    "sg:city":"Wien",
    "sg:orig_category":"Weiterbildungsinstitute M Allg U Berufl Bildungsangebot",
    "sg:phone":"+43 1 71850680",
    "sg:postcode":"1070",
    "sg:province":"Wien",
    "wof:name":"International University",
    "wof:placetype":"venue"
},
  "geometry": {"coordinates":[16.3499450684,48.2011032104],"type":"Point"}
}