{
  "type": "Feature",
  "properties": {
    "addr:full":"Kreuzleitenstr 3/2 Garsten Ober\u00f6sterreich 4451",
    "addr:housenumber":"3 / 2",
    "addr:postcode":"4451",
    "addr:street":"Kreuzleitenstr",
    "iso:country":"AT",
    "sg:address":"Kreuzleitenstr 3/2",
    "sg:city":"Garsten",
    "sg:orig_category":"Massagen",
    "sg:phone":"+43 4372 5243145",
    "sg:postcode":"4451",
    "sg:province":"Ober\u00f6sterreich",
    "wof:name":"Maiw\u00f6ger Dietlinde - Luna Yoga u Shiatsu",
    "wof:placetype":"venue"
},
  "geometry": {"coordinates":[14.4067201614,48.0259666443],"type":"Point"}
}