{
  "type": "Feature",
  "properties": {
    "addr:full":"Nest 5 St. Christophen Nieder\u00f6sterreich 3051",
    "addr:housenumber":"5",
    "addr:postcode":"3051",
    "addr:street":"Nest",
    "iso:country":"AT",
    "sg:address":"Nest 5",
    "sg:city":"St. Christophen",
    "sg:orig_category":"Apparatus, Containers, Tanks, Boilers Of Plastic",
    "sg:phone":"+43 2772 529200",
    "sg:postcode":"3051",
    "sg:province":"Nieder\u00f6sterreich",
    "wof:name":"Josef Peithner Ges.m.b.H.",
    "wof:placetype":"venue"
},
  "geometry": {"coordinates":[15.8867139816,48.1740989685],"type":"Point"}
}