{
  "type": "Feature",
  "properties": {
    "addr:full":"10.-Oktober-Str 12 Feldkirchen in K\u00e4rnten K\u00e4rnten 9560",
    "addr:housenumber":"12",
    "addr:postcode":"9560",
    "addr:street":"10.-Oktober-Str;Kaernten",
    "iso:country":"AT",
    "sg:address":"10.-Oktober-Str 12",
    "sg:city":"Feldkirchen in K\u00e4rnten",
    "sg:orig_category":"Nachhilfe U Lernbetreuung",
    "sg:phone":"+43 4342 7639380",
    "sg:postcode":"9560",
    "sg:province":"K\u00e4rnten",
    "wof:name":"SCH\u00dcLERHILFE FELDKIRCHEN Mag Heidi Bettina Tragl",
    "wof:placetype":"venue"
},
  "geometry": {"coordinates":[14.0943212509,46.7240715027],"type":"Point"}
}