{
  "type": "Feature",
  "properties": {
    "iso:country":"AT",
    "sg:address":"K\u00f6tzing 8",
    "sg:city":"Seeboden",
    "sg:orig_category":"Leder",
    "sg:phone":"+43 4762 811230",
    "sg:postcode":"9871",
    "sg:province":"K\u00e4rnten",
    "wof:name":"Unterlerchner Michael O",
    "wof:placetype":"venue"
},
  "geometry": {"coordinates":[13.5192050934,46.8188858032],"type":"Point"}
}