{
  "type": "Feature",
  "properties": {
    "iso:country":"AT",
    "sg:address":"Schirmerstrasse 6",
    "sg:city":"Leonding",
    "sg:classifiers":[
        {
            "category":"Professional",
            "subcategory":"Advertising",
            "type":"Services"
        }
    ],
    "sg:phone":"+43 732 377300",
    "sg:postcode":"4060",
    "sg:province":"Ober\u00f6sterreich",
    "sg:tags":[
        "article",
        "glass"
    ],
    "sg:website":"work.co.at",
    "wof:name":"Werbe- und Pr\u00e4sentationssysteme at work Die Dienstleistungs GmbH",
    "wof:placetype":"venue"
},
  "geometry": {"coordinates":[14.2730236053,48.2550086975],"type":"Point"}
}