{
  "type": "Feature",
  "properties": {
    "addr:full":"Eggenberger G\u00fcrtel 78 Graz Steiermark 8020",
    "addr:housenumber":"78",
    "addr:postcode":"8020",
    "iso:country":"AT",
    "sg:address":"Eggenberger G\u00fcrtel 78",
    "sg:city":"Graz",
    "sg:orig_category":"Maler, Anstreicher U Lackierer",
    "sg:phone":"+43 664 4605618",
    "sg:postcode":"8020",
    "sg:province":"Steiermark",
    "wof:name":"Malerbetrieb Stefan",
    "wof:placetype":"venue"
},
  "geometry": {"coordinates":[15.4111499786,47.0689201355],"type":"Point"}
}