{
  "type": "Feature",
  "properties": {
    "addr:full":"L\u00f6weng 29A Wien Wien 1030",
    "addr:housenumber":"29a",
    "addr:postcode":"1030",
    "addr:street":"Loeweng",
    "iso:country":"AT",
    "sg:address":"L\u00f6weng 29A",
    "sg:city":"Wien",
    "sg:orig_category":"Zeitungen U Zeitschriften, Antiquariate",
    "sg:phone":"+43 1 7152108",
    "sg:postcode":"1030",
    "sg:province":"Wien",
    "wof:name":"Alte B\u00fccher und Zeitungen f Geburtstage und Jubil\u00e4en Inh Z Zmuda",
    "wof:placetype":"venue"
},
  "geometry": {"coordinates":[16.4025096893,48.1936683655],"type":"Point"}
}