{
  "type": "Feature",
  "properties": {
    "addr:full":"Jakob-Fuchs-G 6 Brunn am Gebirge Nieder\u00f6sterreich 2345",
    "addr:housenumber":"6",
    "addr:postcode":"2345",
    "addr:street":"Jakob-Fuchs-G",
    "iso:country":"AT",
    "sg:address":"Jakob-Fuchs-G 6",
    "sg:city":"Brunn am Gebirge",
    "sg:orig_category":"Dachdeckereien",
    "sg:phone":"+43 2236 31364",
    "sg:postcode":"2345",
    "sg:province":"Nieder\u00f6sterreich",
    "sg:website":"krueckl-dach.at",
    "wof:name":"Kr\u00fcckl Walter GmbH",
    "wof:placetype":"venue"
},
  "geometry": {"coordinates":[16.2967128754,48.1114501953],"type":"Point"}
}