{
  "type": "Feature",
  "properties": {
    "iso:country":"AT",
    "sg:address":"Maria Gailer Str. 59 ",
    "sg:city":"Villach",
    "sg:classifiers":[
        {
            "category":"Sports & Exercise",
            "subcategory":"Playing Field",
            "type":"Entertainment"
        }
    ],
    "sg:phone":"+43 4342 4232540",
    "sg:postcode":"9500",
    "sg:province":"K\u00e4rnten",
    "sg:tags":[
        "game"
    ],
    "wof:name":"FALLE GMBH",
    "wof:placetype":"venue"
},
  "geometry": {"coordinates":[13.8713674545,46.6041564941],"type":"Point"}
}