{
  "type": "Feature",
  "properties": {
    "iso:country":"AT",
    "sg:address":"Hoher Markt 12",
    "sg:city":"Waidhofen an der Ybbs",
    "sg:orig_category":"Biologische Produkte",
    "sg:phone":"+43 4374 4254894",
    "sg:postcode":"3340",
    "sg:province":"Nieder\u00f6sterreich",
    "wof:name":"Bio Bauern Hoflieferanten",
    "wof:placetype":"venue"
},
  "geometry": {"coordinates":[14.7744674683,47.9599304199],"type":"Point"}
}