{
  "type": "Feature",
  "properties": {
    "addr:full":"Hauptstr 247 St. Margarethen im Burgenland Burgenland 7062",
    "addr:housenumber":"247",
    "addr:postcode":"7062",
    "addr:street":"Hauptstr",
    "iso:country":"AT",
    "sg:address":"Hauptstr 247",
    "sg:city":"St. Margarethen im Burgenland",
    "sg:orig_category":"Fleischhauereien",
    "sg:phone":"+43 4326 8021451",
    "sg:postcode":"7062",
    "sg:province":"Burgenland",
    "wof:name":"Schirnhofer-Breisler GesmbH - Shop in Shop",
    "wof:placetype":"venue"
},
  "geometry": {"coordinates":[16.6198577881,47.8021697998],"type":"Point"}
}