{
  "type": "Feature",
  "properties": {
    "addr:full":"Hermann-Gebauer-Str. 3  Wien Wien 1220",
    "addr:housenumber":"3",
    "addr:postcode":"1220",
    "addr:street":"Hermann-Gebauer-Str.",
    "iso:country":"AT",
    "sg:address":"Hermann-Gebauer-Str. 3 ",
    "sg:city":"Wien",
    "sg:classifiers":[
        {
            "category":"Food & Beverages",
            "subcategory":"Groceries & Convenience Stores",
            "type":"Retail Goods"
        }
    ],
    "sg:phone":"+43 4313 3165",
    "sg:postcode":"1220",
    "sg:province":"Wien",
    "sg:tags":[
        "product",
        "related"
    ],
    "wof:name":"TKL TIEFK\u00dcHLLOGISTIK GESMBH",
    "wof:placetype":"venue"
},
  "geometry": {"coordinates":[16.4729785919,48.2646369934],"type":"Point"}
}