{
  "type": "Feature",
  "properties": {
    "addr:full":"Br\u00fchlg 24 Hartberg Steiermark 8230",
    "addr:housenumber":"24",
    "addr:postcode":"8230",
    "addr:street":"Bruehlg",
    "iso:country":"AT",
    "sg:address":"Br\u00fchlg 24",
    "sg:city":"Hartberg",
    "sg:orig_category":"Biologische Produkte",
    "sg:phone":"+43 4333 32626610",
    "sg:postcode":"8230",
    "sg:province":"Steiermark",
    "wof:name":"Roman Posch - Getreidem\u00fchlen",
    "wof:placetype":"venue"
},
  "geometry": {"coordinates":[15.9727478027,47.2819519043],"type":"Point"}
}