{
  "type": "Feature",
  "properties": {
    "addr:full":"Wiedner Hauptstr 116 Wien Wien 1050",
    "addr:housenumber":"116",
    "addr:postcode":"1050",
    "addr:street":"Hauptstr",
    "iso:country":"AT",
    "sg:address":"Wiedner Hauptstr 116",
    "sg:city":"Wien",
    "sg:classifiers":[
        {
            "category":"Restaurant",
            "type":"Food & Drink"
        }
    ],
    "sg:phone":"+43 1 5452333",
    "sg:postcode":"1050",
    "sg:province":"Wien",
    "wof:name":"Restaurant z goldenen L\u00f6wen",
    "wof:placetype":"venue"
},
  "geometry": {"coordinates":[16.3618431091,48.1849708557],"type":"Point"}
}