{
  "type": "Feature",
  "properties": {
    "addr:full":"W\u00f6ranstrasse 13 Gramastetten Ober\u00f6sterreich 4201",
    "addr:housenumber":"13",
    "addr:postcode":"4201",
    "addr:street":"Woeranstrasse",
    "iso:country":"AT",
    "sg:address":"W\u00f6ranstrasse 13",
    "sg:city":"Gramastetten",
    "sg:classifiers":[
        {
            "category":"Building & Trades",
            "subcategory":"Electrical",
            "type":"Services"
        }
    ],
    "sg:phone":"+43 7239 8856",
    "sg:postcode":"4201",
    "sg:province":"Ober\u00f6sterreich",
    "sg:tags":[
        "work",
        "installation"
    ],
    "wof:name":"Alexander F\u00fchrlinger Elektroinstallationen u. Heizungskundendienst",
    "wof:placetype":"venue"
},
  "geometry": {"coordinates":[14.1947412491,48.3803596497],"type":"Point"}
}