{
  "type": "Feature",
  "properties": {
    "addr:full":"Hueb 10-18 Altenhof am Hausruck Ober\u00f6sterreich 4674",
    "addr:postcode":"10-18;4674",
    "addr:street":"Hueb",
    "iso:country":"AT",
    "sg:address":"Hueb 10-18",
    "sg:city":"Altenhof am Hausruck",
    "sg:orig_category":"Banken U Sparkassen",
    "sg:phone":"+43 4377 3570150",
    "sg:postcode":"4674",
    "sg:province":"Ober\u00f6sterreich",
    "wof:name":"Bankomat d Raiffeisenbank Region Hausruck regGenmbH",
    "wof:placetype":"venue"
},
  "geometry": {"coordinates":[13.6841163635,48.130859375],"type":"Point"}
}