{
  "type": "Feature",
  "properties": {
    "addr:full":"Sonnhuberg 7 Leonding Ober\u00f6sterreich 4060",
    "addr:housenumber":"7",
    "addr:postcode":"4060",
    "addr:street":"Sonnhuberg",
    "iso:country":"AT",
    "sg:address":"Sonnhuberg 7",
    "sg:city":"Leonding",
    "sg:classifiers":[
        {
            "category":"Professional",
            "subcategory":"Computer Services",
            "type":"Services"
        }
    ],
    "sg:phone":"+43 732 681111",
    "sg:postcode":"4060",
    "sg:province":"Ober\u00f6sterreich",
    "sg:tags":[
        "software"
    ],
    "wof:name":"perComp IT-Security GmbH",
    "wof:placetype":"venue"
},
  "geometry": {"coordinates":[14.2493629456,48.2761077881],"type":"Point"}
}