{
  "type": "Feature",
  "properties": {
    "addr:full":"Hauptstrasse 50 Zeltweg Steiermark 8740",
    "addr:housenumber":"50",
    "addr:postcode":"8740",
    "addr:street":"Hauptstrasse",
    "iso:country":"AT",
    "sg:address":"Hauptstrasse 50",
    "sg:city":"Zeltweg",
    "sg:classifiers":[
        {
            "category":"Home & Garden",
            "subcategory":"Building Materials",
            "type":"Retail Goods"
        }
    ],
    "sg:phone":"+43 3577 24335",
    "sg:postcode":"8740",
    "sg:province":"Steiermark",
    "sg:tags":[
        "aluminium",
        "gutter"
    ],
    "wof:name":"Wolfgang Kargl",
    "wof:placetype":"venue"
},
  "geometry": {"coordinates":[14.7600374222,47.1931762695],"type":"Point"}
}