{
  "type": "Feature",
  "properties": {
    "addr:full":"Gewerbering 5 Stra\u00dfgang Steiermark 8054",
    "addr:housenumber":"5",
    "addr:postcode":"8054",
    "addr:street":"Gewerbering",
    "iso:country":"AT",
    "sg:address":"Gewerbering 5",
    "sg:city":"Stra\u00dfgang",
    "sg:orig_category":"Bauunternehmen",
    "sg:phone":"+43 4331 68311500",
    "sg:postcode":"8054",
    "sg:province":"Steiermark",
    "wof:name":"Malli BaugesmbH",
    "wof:placetype":"venue"
},
  "geometry": {"coordinates":[15.400270462,46.996219635],"type":"Point"}
}