{
  "type": "Feature",
  "properties": {
    "iso:country":"AT",
    "sg:address":"Bahngasse 16",
    "sg:city":"Gumpoldskirchen",
    "sg:orig_category":"Ambient Media Advertising",
    "sg:phone":"+43 676 5536466",
    "sg:postcode":"2352",
    "sg:province":"Nieder\u00f6sterreich",
    "sg:website":"staytuned.at",
    "wof:name":"stay tuned new media consulting & production",
    "wof:placetype":"venue"
},
  "geometry": {"coordinates":[16.2838573456,48.0409393311],"type":"Point"}
}