{
  "type": "Feature",
  "properties": {
    "iso:country":"AT",
    "sg:address":"Favoritenstr 77",
    "sg:city":"Wien",
    "sg:orig_category":"Friseure U Frisiersalons",
    "sg:phone":"+43 1 6031785",
    "sg:postcode":"1100",
    "sg:province":"Wien",
    "wof:name":"Coiffeur Schauer",
    "wof:placetype":"venue"
},
  "geometry": {"coordinates":[16.375623703,48.1810455322],"type":"Point"}
}