{
  "type": "Feature",
  "properties": {
    "iso:country":"AT",
    "sg:address":"Klebern 561",
    "sg:city":"Egg",
    "sg:orig_category":"Familien / Beratung",
    "sg:phone":"+43 5512 215670",
    "sg:postcode":"6863",
    "sg:province":"Vorarlberg",
    "wof:name":"Ambulanter Familiendienst d Voralrberger Kinderdorf",
    "wof:placetype":"venue"
},
  "geometry": {"coordinates":[9.8979444504,47.4291877747],"type":"Point"}
}