{
  "type": "Feature",
  "properties": {
    "addr:full":"Neulerchenfelder Str 6 Wien Wien 1160",
    "addr:housenumber":"6",
    "addr:postcode":"1160",
    "addr:street":"Str",
    "iso:country":"AT",
    "sg:address":"Neulerchenfelder Str 6",
    "sg:city":"Wien",
    "sg:orig_category":"Optiker",
    "sg:phone":"+43 1 4084013",
    "sg:postcode":"1160",
    "sg:province":"Wien",
    "wof:name":"Walter's Brillenstube Inh Walter Staniek",
    "wof:placetype":"venue"
},
  "geometry": {"coordinates":[16.3379878998,48.2109832764],"type":"Point"}
}