{
  "type": "Feature",
  "properties": {
    "iso:country":"AT",
    "sg:address":"Innrain 12",
    "sg:city":"Innsbruck",
    "sg:orig_category":"Friseure U Frisiersalons",
    "sg:phone":"+43 512 588369",
    "sg:postcode":"6020",
    "sg:province":"Tirol",
    "wof:name":"Salon Helga",
    "wof:placetype":"venue"
},
  "geometry": {"coordinates":[11.39012146,47.2669181824],"type":"Point"}
}