{
  "type": "Feature",
  "properties": {
    "iso:country":"AT",
    "sg:address":"Niederau 115",
    "sg:city":"Wildsch\u00f6nau-Niederau",
    "sg:classifiers":[
        {
            "category":"Manufacturing",
            "subcategory":"Wood Products",
            "type":"Manufacturing & Wholesale Goods"
        }
    ],
    "sg:phone":"+43 5339 2502",
    "sg:postcode":"6314",
    "sg:province":"Tirol",
    "sg:tags":[
        "solid",
        "ceiling",
        "made",
        "panel"
    ],
    "wof:name":"Siegfried Hohlrieder",
    "wof:placetype":"venue"
},
  "geometry": {"coordinates":[12.0885276794,47.4488143921],"type":"Point"}
}