{
  "type": "Feature",
  "properties": {
    "addr:full":"Obersulz Nieder\u00f6sterreich 2224",
    "addr:postcode":"2224",
    "addr:street":"Niederoesterreich",
    "iso:country":"AT",
    "sg:city":"Obersulz",
    "sg:orig_category":"Feuerwehren",
    "sg:phone":"+43 2534 727",
    "sg:postcode":"2224",
    "sg:province":"Nieder\u00f6sterreich",
    "wof:name":"Freiwillige Feuerwehr Niedersulz",
    "wof:placetype":"venue"
},
  "geometry": {"coordinates":[16.6783123016,48.4856414795],"type":"Point"}
}