{
  "type": "Feature",
  "properties": {
    "addr:full":"Unterer Stadtpl 34 Waidhofen an der Ybbs Nieder\u00f6sterreich 3340",
    "addr:housenumber":"34",
    "addr:postcode":"3340",
    "addr:street":"Unterer Stadtpl",
    "iso:country":"AT",
    "sg:address":"Unterer Stadtpl 34",
    "sg:city":"Waidhofen an der Ybbs",
    "sg:orig_category":"Restaurants: Chinesisch",
    "sg:phone":"+43 4374 4254575",
    "sg:postcode":"3340",
    "sg:province":"Nieder\u00f6sterreich",
    "wof:name":"China Restaurant Shang Hai",
    "wof:placetype":"venue"
},
  "geometry": {"coordinates":[14.7733240128,47.9600906372],"type":"Point"}
}