{
  "type": "Feature",
  "properties": {
    "addr:full":"Karl-Plentzner-Str 12a Gmunden Ober\u00f6sterreich 4810",
    "addr:housenumber":"12a",
    "addr:postcode":"4810",
    "addr:street":"Karl-Plentzner-Str;Oberoesterreich",
    "iso:country":"AT",
    "sg:address":"Karl-Plentzner-Str 12a",
    "sg:city":"Gmunden",
    "sg:orig_category":"Steinmetzbetriebe",
    "sg:phone":"+43 7612645670",
    "sg:postcode":"4810",
    "sg:province":"Ober\u00f6sterreich",
    "wof:name":"Paulus Walter",
    "wof:placetype":"venue"
},
  "geometry": {"coordinates":[13.7936592102,47.9230728149],"type":"Point"}
}