{
  "type": "Feature",
  "properties": {
    "iso:country":"AT",
    "sg:address":"Bockg 3A",
    "sg:city":"Linz",
    "sg:orig_category":"Sprachschulen U -Unterricht",
    "sg:phone":"+43 732 662548",
    "sg:postcode":"4020",
    "sg:province":"Ober\u00f6sterreich",
    "wof:name":"EF Education GesmbH",
    "wof:placetype":"venue"
},
  "geometry": {"coordinates":[14.2848186493,48.2928695679],"type":"Point"}
}