{
  "type": "Feature",
  "properties": {
    "iso:country":"AT",
    "sg:address":"Keplerstr 53",
    "sg:city":"Graz",
    "sg:orig_category":"Fenster",
    "sg:phone":"+43 316 720877",
    "sg:postcode":"8020",
    "sg:province":"Steiermark",
    "wof:name":"Fensterpark GmbH",
    "wof:placetype":"venue"
},
  "geometry": {"coordinates":[15.4256849289,47.0749053955],"type":"Point"}
}