{
  "type": "Feature",
  "properties": {
    "addr:full":"Tetmajerg 5 Wien Wien 1210",
    "addr:housenumber":"5",
    "addr:postcode":"1210",
    "addr:street":"Tetmajerg",
    "iso:country":"AT",
    "sg:address":"Tetmajerg 5",
    "sg:city":"Wien",
    "sg:orig_category":"Autoreparatur",
    "sg:phone":"+43 1 2715366",
    "sg:postcode":"1210",
    "sg:province":"Wien",
    "wof:name":"Sklenar Rudolf Franz GesmbH",
    "wof:placetype":"venue"
},
  "geometry": {"coordinates":[16.3906097412,48.2595748901],"type":"Point"}
}