{
  "type": "Feature",
  "properties": {
    "iso:country":"AT",
    "sg:address":"Goldschmiedgasse 3 ",
    "sg:city":"Wien",
    "sg:classifiers":[
        {
            "category":"Banks & Credit Unions",
            "subcategory":"Bank",
            "type":"Services"
        }
    ],
    "sg:phone":"+43 4315 34340",
    "sg:postcode":"1010",
    "sg:province":"Wien",
    "sg:tags":[
        "banking",
        "institution"
    ],
    "wof:name":"BANKHAUS SCHELHAMMER & SCHATTERA AG",
    "wof:placetype":"venue"
},
  "geometry": {"coordinates":[16.3713874817,48.2084732056],"type":"Point"}
}