{
  "type": "Feature",
  "properties": {
    "iso:country":"AT",
    "sg:address":"Baderg 269",
    "sg:city":"Nassereith",
    "sg:orig_category":"Lebensmittel / Einzelhandel",
    "sg:phone":"+43 5265 5358",
    "sg:postcode":"6465",
    "sg:province":"Tirol",
    "wof:name":"Spar-Markt Inh Getraud Kranewitter",
    "wof:placetype":"venue"
},
  "geometry": {"coordinates":[10.8467721939,47.3097229004],"type":"Point"}
}