{
  "type": "Feature",
  "properties": {
    "iso:country":"AT",
    "sg:address":"Inselstr. 5 ",
    "sg:city":"Hard",
    "sg:classifiers":[
        {
            "category":"Home & Garden",
            "subcategory":"Home Furnishings",
            "type":"Retail Goods"
        }
    ],
    "sg:phone":"+43 4355 7472530",
    "sg:postcode":"6971",
    "sg:province":"Vorarlberg",
    "sg:tags":[
        "household"
    ],
    "wof:name":"ALWIN REUMILLER",
    "wof:placetype":"venue"
},
  "geometry": {"coordinates":[9.6929512024,47.4925346375],"type":"Point"}
}