{
  "type": "Feature",
  "properties": {
    "iso:country":"AT",
    "sg:address":"Hafferlstr 12",
    "sg:city":"Linz",
    "sg:orig_category":"Blumeneinzelhandel",
    "sg:phone":"+43 732 783321",
    "sg:postcode":"4020",
    "sg:province":"Ober\u00f6sterreich",
    "wof:name":"Blumen Lisa Inh Lisa Traxler",
    "wof:placetype":"venue"
},
  "geometry": {"coordinates":[14.2896461487,48.2990646362],"type":"Point"}
}