{
  "type": "Feature",
  "properties": {
    "addr:full":"Pfarrg 34-44 Wien Wien 1230",
    "addr:postcode":"34-44;1230",
    "iso:country":"AT",
    "sg:address":"Pfarrg 34-44",
    "sg:city":"Wien",
    "sg:orig_category":"Familien / Beratung",
    "sg:phone":"+43 1 6151102",
    "sg:postcode":"1230",
    "sg:province":"Wien",
    "wof:name":"MAG ELF - Elternberatungsstelle der Stadt Wien",
    "wof:placetype":"venue"
},
  "geometry": {"coordinates":[16.3449020386,48.1450233459],"type":"Point"}
}