{
  "type": "Feature",
  "properties": {
    "addr:full":"K\u00f6glstr 20a Linz Ober\u00f6sterreich 4020",
    "addr:housenumber":"20a",
    "addr:postcode":"4020",
    "addr:street":"Koeglstr",
    "iso:country":"AT",
    "sg:address":"K\u00f6glstr 20a",
    "sg:city":"Linz",
    "sg:orig_category":"Transportunternehmen",
    "sg:phone":"+43 732 7702110",
    "sg:postcode":"4020",
    "sg:province":"Ober\u00f6sterreich",
    "wof:name":"Koblm\u00fcller Kurt",
    "wof:placetype":"venue"
},
  "geometry": {"coordinates":[14.285320282,48.3044815063],"type":"Point"}
}