{
  "type": "Feature",
  "properties": {
    "iso:country":"AT",
    "sg:address":"Stettner Str 50",
    "sg:city":"Eugendorf",
    "sg:orig_category":"Transportunternehmen",
    "sg:phone":"+43 6225 2529",
    "sg:postcode":"5301",
    "sg:province":"Salzburg",
    "wof:name":"M\u00f6sl Johann",
    "wof:placetype":"venue"
},
  "geometry": {"coordinates":[13.1400928497,47.8523178101],"type":"Point"}
}