{
  "type": "Feature",
  "properties": {
    "addr:full":"Martinstrasse 91/9 Wien Wien 1180",
    "addr:housenumber":"91 / 9",
    "addr:postcode":"1180",
    "addr:street":"Martinstrasse",
    "iso:country":"AT",
    "sg:address":"Martinstrasse 91/9",
    "sg:city":"Wien",
    "sg:classifiers":[
        {
            "category":"Health Services",
            "subcategory":"Medical Lab",
            "type":"Services"
        }
    ],
    "sg:phone":"+43 1 4025615",
    "sg:postcode":"1180",
    "sg:province":"Wien",
    "sg:tags":[
        "instrument",
        "surgery",
        "heart"
    ],
    "sg:website":"lagunahealth.com",
    "wof:name":"Laguna Export Ges.m.b.H.",
    "wof:placetype":"venue"
},
  "geometry": {"coordinates":[16.3420009613,48.226398468],"type":"Point"}
}