{
  "type": "Feature",
  "properties": {
    "addr:full":"Feldweg 4A Wolfurt Vorarlberg 6922",
    "addr:housenumber":"4a",
    "addr:postcode":"6922",
    "addr:street":"Feldweg",
    "iso:country":"AT",
    "sg:address":"Feldweg 4A",
    "sg:city":"Wolfurt",
    "sg:orig_category":"Endlosformulare U -Papier",
    "sg:phone":"+43 4366 42134910",
    "sg:postcode":"6922",
    "sg:province":"Vorarlberg",
    "wof:name":"Perfect Print - Peter Huber",
    "wof:placetype":"venue"
},
  "geometry": {"coordinates":[9.7539348602,47.4770812988],"type":"Point"}
}