{
  "type": "Feature",
  "properties": {
    "addr:full":"Bundesstr 73 Nenzing Vorarlberg 6710",
    "addr:housenumber":"73",
    "addr:postcode":"6710",
    "addr:street":"Bundesstr",
    "iso:country":"AT",
    "sg:address":"Bundesstr 73",
    "sg:city":"Nenzing",
    "sg:orig_category":"Restaurants: Chinesisch",
    "sg:phone":"+43 4355 2563125",
    "sg:postcode":"6710",
    "sg:province":"Vorarlberg",
    "wof:name":"China-Restaurant Pracht",
    "wof:placetype":"venue"
},
  "geometry": {"coordinates":[9.7029571533,47.1888084412],"type":"Point"}
}