{
  "type": "Feature",
  "properties": {
    "addr:full":"Weidli 102 Bichlbach Tirol 6621",
    "addr:housenumber":"102",
    "addr:postcode":"6621",
    "addr:street":"Weidli;Tirol",
    "iso:country":"AT",
    "sg:address":"Weidli 102",
    "sg:city":"Bichlbach",
    "sg:orig_category":"Pensionen / Privatzimmer",
    "sg:phone":"+43 4356 745344",
    "sg:postcode":"6621",
    "sg:province":"Tirol",
    "wof:name":"Pension Schander",
    "wof:placetype":"venue"
},
  "geometry": {"coordinates":[10.7882547379,47.4214401245],"type":"Point"}
}