{
  "type": "Feature",
  "properties": {
    "addr:full":"Franz-Walde-Weg 1 Kitzb\u00fchel Tirol 6370",
    "addr:housenumber":"1",
    "addr:postcode":"6370",
    "addr:street":"Franz-Walde-Weg;Tirol",
    "iso:country":"AT",
    "sg:address":"Franz-Walde-Weg 1",
    "sg:city":"Kitzb\u00fchel",
    "sg:classifiers":[
        {
            "category":"Travel",
            "subcategory":"Hotels & Motels",
            "type":"Entertainment"
        }
    ],
    "sg:phone":"+43 5356 66821",
    "sg:postcode":"6370",
    "sg:province":"Tirol",
    "sg:website":"villa-mellon.at",
    "wof:name":"Villa Mellon",
    "wof:placetype":"venue"
},
  "geometry": {"coordinates":[12.3846435547,47.4509010315],"type":"Point"}
}