{
  "type": "Feature",
  "properties": {
    "addr:full":"Schulstr 6 G\u00fcssing Burgenland 7540",
    "addr:housenumber":"6",
    "addr:postcode":"7540",
    "addr:street":"Schulstr",
    "iso:country":"AT",
    "sg:address":"Schulstr 6",
    "sg:city":"G\u00fcssing",
    "sg:orig_category":"Bibliotheken",
    "sg:phone":"+43 3322 42182",
    "sg:postcode":"7540",
    "sg:province":"Burgenland",
    "wof:name":"Stadtb\u00fccherei G\u00fcssing",
    "wof:placetype":"venue"
},
  "geometry": {"coordinates":[16.323223114,47.0624275208],"type":"Point"}
}