{
  "type": "Feature",
  "properties": {
    "addr:full":"Am Berg 4 B\u00f6heimkirchen Nieder\u00f6sterreich 3071",
    "addr:housenumber":"4",
    "addr:postcode":"3071",
    "addr:street":"Am Berg;Niederoesterreich",
    "iso:country":"AT",
    "sg:address":"Am Berg 4",
    "sg:city":"B\u00f6heimkirchen",
    "sg:orig_category":"Musikunterricht",
    "sg:phone":"+43 2743 3280",
    "sg:postcode":"3071",
    "sg:province":"Nieder\u00f6sterreich",
    "wof:name":"Musikschule",
    "wof:placetype":"venue"
},
  "geometry": {"coordinates":[7.7127490044,49.574382782],"type":"Point"}
}