{
  "type": "Feature",
  "properties": {
    "iso:country":"AT",
    "sg:address":"Sallegg 32",
    "sg:city":"Koglhof",
    "sg:orig_category":"Pensionen / Privatzimmer",
    "sg:phone":"+43 3174 3746",
    "sg:postcode":"8191",
    "sg:province":"Steiermark",
    "wof:name":"Tiefengraber Franz",
    "wof:placetype":"venue"
},
  "geometry": {"coordinates":[15.6759395599,47.3340911865],"type":"Point"}
}