{
  "type": "Feature",
  "properties": {
    "addr:full":"Inselgrund 12 Hard Vorarlberg 6971",
    "addr:housenumber":"12",
    "addr:postcode":"6971",
    "addr:street":"Inselgrund",
    "iso:country":"AT",
    "sg:address":"Inselgrund 12",
    "sg:city":"Hard",
    "sg:orig_category":"Handelsagenturen",
    "sg:phone":"+43 5574 71136",
    "sg:postcode":"6971",
    "sg:province":"Vorarlberg",
    "wof:name":"ACW Handelsagentur",
    "wof:placetype":"venue"
},
  "geometry": {"coordinates":[9.6944160461,47.4935073853],"type":"Point"}
}