{
  "type": "Feature",
  "properties": {
    "addr:full":"Paracelsusweg 4 Velden am W\u00f6rther See K\u00e4rnten 9220",
    "addr:housenumber":"4",
    "addr:postcode":"9220",
    "addr:street":"Paracelsusweg;Kaernten",
    "iso:country":"AT",
    "sg:address":"Paracelsusweg 4",
    "sg:city":"Velden am W\u00f6rther See",
    "sg:orig_category":"Pensionen / Privatzimmer",
    "sg:phone":"+43 4342 744394",
    "sg:postcode":"9220",
    "sg:province":"K\u00e4rnten",
    "wof:name":"Pension Solora",
    "wof:placetype":"venue"
},
  "geometry": {"coordinates":[14.0406389236,46.6180267334],"type":"Point"}
}