{
  "type": "Feature",
  "properties": {
    "iso:country":"AT",
    "sg:address":"Laimburgg 15",
    "sg:city":"Graz",
    "sg:classifiers":[
        {
            "category":"Restaurant",
            "type":"Food & Drink"
        }
    ],
    "sg:phone":"+43 316 681095",
    "sg:postcode":"8010",
    "sg:province":"Steiermark",
    "wof:name":"Sapotnik Astrid",
    "wof:placetype":"venue"
},
  "geometry": {"coordinates":[15.4364795685,47.0803909302],"type":"Point"}
}