{
  "type": "Feature",
  "properties": {
    "iso:country":"AT",
    "sg:address":"Kinopl 6",
    "sg:city":"Klagenfurt",
    "sg:orig_category":"Waren Aller Art",
    "sg:phone":"+43 463 3440000",
    "sg:postcode":"9020",
    "sg:province":"K\u00e4rnten",
    "wof:name":"DIFICON VALVES HandelsgesmbH",
    "wof:placetype":"venue"
},
  "geometry": {"coordinates":[14.3086843491,46.6147499084],"type":"Point"}
}