{
  "type": "Feature",
  "properties": {
    "addr:full":"Gugger Nu\u00dfbaum 35a Klaus-Weiler Vorarlberg 6833",
    "addr:housenumber":"35a",
    "addr:postcode":"klaus-weiler;6833",
    "addr:street":"Gugger Nussbaum",
    "iso:country":"AT",
    "sg:address":"Gugger Nu\u00dfbaum 35a",
    "sg:city":"Klaus-Weiler",
    "sg:orig_category":"\u00c3\u201enderungsschneidereien",
    "sg:phone":"+43 5523 55226",
    "sg:postcode":"6833",
    "sg:province":"Vorarlberg",
    "wof:name":"Brucker \u00c4nderungsschneiderei",
    "wof:placetype":"venue"
},
  "geometry": {"coordinates":[9.638841629,47.3074417114],"type":"Point"}
}