{
  "type": "Feature",
  "properties": {
    "addr:full":"Johann K Vogel-Str 2a Linz Ober\u00f6sterreich 4020",
    "addr:housenumber":"2a",
    "addr:postcode":"4020",
    "addr:street":"Johann K Vogel-Str",
    "iso:country":"AT",
    "sg:address":"Johann K Vogel-Str 2a",
    "sg:city":"Linz",
    "sg:orig_category":"Non-Classified Establishments",
    "sg:phone":"+43 732 773260",
    "sg:postcode":"4020",
    "sg:province":"Ober\u00f6sterreich",
    "wof:name":"Evangelische Pfarrgemeinde AB Martin Luther Kirche",
    "wof:placetype":"venue"
},
  "geometry": {"coordinates":[14.2912149429,48.3003387451],"type":"Point"}
}