{
  "type": "Feature",
  "properties": {
    "addr:full":"Albrechtstr 22 Marchtrenk Ober\u00f6sterreich 4614",
    "addr:housenumber":"22",
    "addr:postcode":"4614",
    "addr:street":"Albrechtstr",
    "iso:country":"AT",
    "sg:address":"Albrechtstr 22",
    "sg:city":"Marchtrenk",
    "sg:orig_category":"Tischlereien",
    "sg:phone":"+43 7243 52433",
    "sg:postcode":"4614",
    "sg:province":"Ober\u00f6sterreich",
    "wof:name":"Kn\u00f6gler Anton",
    "wof:placetype":"venue"
},
  "geometry": {"coordinates":[14.1441726685,48.1986618042],"type":"Point"}
}