{
  "type": "Feature",
  "properties": {
    "addr:full":"Pyhrnstr 40 Liezen Steiermark 8940",
    "addr:housenumber":"40",
    "addr:postcode":"8940",
    "addr:street":"Pyhrnstr",
    "iso:country":"AT",
    "sg:address":"Pyhrnstr 40",
    "sg:city":"Liezen",
    "sg:orig_category":"Schneidereien",
    "sg:phone":"+43 3612 231800",
    "sg:postcode":"8940",
    "sg:province":"Steiermark",
    "wof:name":"pro mente steiermark Arbeitstraining Liezen",
    "wof:placetype":"venue"
},
  "geometry": {"coordinates":[14.2526807785,47.5743408203],"type":"Point"}
}