{
  "type": "Feature",
  "properties": {
    "addr:full":"Wenedikterstr 7 Villach K\u00e4rnten 9500",
    "addr:housenumber":"7",
    "addr:postcode":"9500",
    "addr:street":"Wenedikterstr;Kaernten",
    "iso:country":"AT",
    "sg:address":"Wenedikterstr 7",
    "sg:city":"Villach",
    "sg:classifiers":[
        {
            "category":"Professional",
            "subcategory":"Art Services",
            "type":"Services"
        }
    ],
    "sg:phone":"+43 4242 287334",
    "sg:postcode":"9500",
    "sg:province":"K\u00e4rnten",
    "sg:tags":[
        "designer"
    ],
    "wof:name":"SAY YES Design",
    "wof:placetype":"venue"
},
  "geometry": {"coordinates":[13.8434238434,46.6218070984],"type":"Point"}
}