{
  "type": "Feature",
  "properties": {
    "iso:country":"AT",
    "sg:address":"Salzburger Str 199",
    "sg:city":"Wels",
    "sg:orig_category":"Freizeitangebote U -Einrichtungen",
    "sg:phone":"+43 4372 4263245",
    "sg:postcode":"4600",
    "sg:province":"Ober\u00f6sterreich",
    "wof:name":"Bachmaier Georg",
    "wof:placetype":"venue"
},
  "geometry": {"coordinates":[13.9780931473,48.1492958069],"type":"Point"}
}