{
  "type": "Feature",
  "properties": {
    "addr:full":"Josef-Gasser-Str 9 Lienz Tirol 9900",
    "addr:housenumber":"9",
    "addr:postcode":"9900",
    "addr:street":"Josef-Gasser-Str;Tirol",
    "iso:country":"AT",
    "sg:address":"Josef-Gasser-Str 9",
    "sg:city":"Lienz",
    "sg:orig_category":"Tankstellenbau",
    "sg:phone":"+43 4348 5271077",
    "sg:postcode":"9900",
    "sg:province":"Tirol",
    "wof:name":"KSW Elektro- u Industrieanlagenbau GmbH",
    "wof:placetype":"venue"
},
  "geometry": {"coordinates":[12.7683801651,46.831829071],"type":"Point"}
}