{
  "type": "Feature",
  "properties": {
    "iso:country":"AT",
    "sg:address":"Dr.-Salzmann-Str 2",
    "sg:city":"Wels",
    "sg:orig_category":"Druckereien",
    "sg:phone":"+43 4372 4265300",
    "sg:postcode":"4600",
    "sg:province":"Ober\u00f6sterreich",
    "sg:website":"print-service.at",
    "wof:name":"Print & Service Inh Wilhelm Pilsner",
    "wof:placetype":"venue"
},
  "geometry": {"coordinates":[14.0216474533,48.1573486328],"type":"Point"}
}