{
  "type": "Feature",
  "properties": {
    "addr:full":"Rauscherstr 17 Wien Wien 1200",
    "addr:housenumber":"17",
    "addr:postcode":"1200",
    "addr:street":"Rauscherstr",
    "iso:country":"AT",
    "sg:address":"Rauscherstr 17",
    "sg:city":"Wien",
    "sg:orig_category":"Tischlereien",
    "sg:phone":"+43 1 3324662",
    "sg:postcode":"1200",
    "sg:province":"Wien",
    "wof:name":"Tischlerei Jenkner GesmbH",
    "wof:placetype":"venue"
},
  "geometry": {"coordinates":[16.3781871796,48.2295150757],"type":"Point"}
}