{
  "type": "Feature",
  "properties": {
    "addr:full":"Industriestr 7 Korneuburg Nieder\u00f6sterreich 2100",
    "addr:housenumber":"7",
    "addr:postcode":"2100",
    "addr:street":"Industriestr;Niederoesterreich",
    "iso:country":"AT",
    "sg:address":"Industriestr 7",
    "sg:city":"Korneuburg",
    "sg:orig_category":"Fahrzeugeinrichtungen U -Umbauten",
    "sg:phone":"+43 2262 71962",
    "sg:postcode":"2100",
    "sg:province":"Nieder\u00f6sterreich",
    "wof:name":"Syncro Schneider KEG",
    "wof:placetype":"venue"
},
  "geometry": {"coordinates":[16.31873703,48.3578796387],"type":"Point"}
}