{
  "type": "Feature",
  "properties": {
    "addr:full":"Schulg 15 Ebreichsdorf Nieder\u00f6sterreich 2483",
    "addr:housenumber":"15",
    "addr:postcode":"2483",
    "addr:street":"Schulg",
    "iso:country":"AT",
    "sg:address":"Schulg 15",
    "sg:city":"Ebreichsdorf",
    "sg:orig_category":"Rauchfangkehrer",
    "sg:phone":"+43 2254 72391",
    "sg:postcode":"2483",
    "sg:province":"Nieder\u00f6sterreich",
    "wof:name":"Diettrich Karl",
    "wof:placetype":"venue"
},
  "geometry": {"coordinates":[16.4063587189,47.9620475769],"type":"Point"}
}