{
  "type": "Feature",
  "properties": {
    "addr:full":"Alleestrasse 10 Mank Nieder\u00f6sterreich 3240",
    "addr:housenumber":"10",
    "addr:postcode":"3240",
    "addr:street":"Alleestrasse;Niederoesterreich",
    "iso:country":"AT",
    "sg:address":"Alleestrasse 10",
    "sg:city":"Mank",
    "sg:orig_category":"ChildrenS Furniture",
    "sg:phone":"+43 2755 2268",
    "sg:postcode":"3240",
    "sg:province":"Nieder\u00f6sterreich",
    "wof:name":"Ing. Robert Garschall",
    "wof:placetype":"venue"
},
  "geometry": {"coordinates":[15.3371896744,48.1116867065],"type":"Point"}
}