{
  "type": "Feature",
  "properties": {
    "addr:full":"Haiden 47 Bad Ischl Ober\u00f6sterreich 4820",
    "addr:housenumber":"47",
    "addr:postcode":"4820",
    "addr:street":"Haiden",
    "iso:country":"AT",
    "sg:address":"Haiden 47",
    "sg:city":"Bad Ischl",
    "sg:orig_category":"Lebensmittel / Einzelhandel",
    "sg:phone":"+43 6132 26945",
    "sg:postcode":"4820",
    "sg:province":"Ober\u00f6sterreich",
    "wof:name":"Konsumgenossenschaft Salzkammergut reg GenmbH",
    "wof:placetype":"venue"
},
  "geometry": {"coordinates":[13.5800170898,47.7264595032],"type":"Point"}
}