{
  "type": "Feature",
  "properties": {
    "addr:full":"Leebg. 5 Wien Wien 1100",
    "addr:housenumber":"5",
    "addr:postcode":"1100",
    "addr:street":"Leebg.",
    "iso:country":"AT",
    "sg:address":"Leebg. 5",
    "sg:city":"Wien",
    "sg:classifiers":[
        {
            "category":"Professional",
            "subcategory":"Advertising",
            "type":"Services"
        }
    ],
    "sg:phone":"+43 4315 871786",
    "sg:postcode":"1100",
    "sg:province":"Wien",
    "sg:tags":[
        "communication",
        "medium"
    ],
    "wof:name":"VADO TELEKOM GES.MBH",
    "wof:placetype":"venue"
},
  "geometry": {"coordinates":[16.3744049072,48.1782684326],"type":"Point"}
}