{
  "type": "Feature",
  "properties": {
    "addr:full":"Volders Tirol 6111",
    "addr:postcode":"6111",
    "addr:street":"Tirol",
    "iso:country":"AT",
    "sg:city":"Volders",
    "sg:orig_category":"Rettungsdienste",
    "sg:phone":"+43 664 4504294",
    "sg:postcode":"6111",
    "sg:province":"Tirol",
    "wof:name":"Bergrettung Wattens",
    "wof:placetype":"venue"
},
  "geometry": {"coordinates":[11.5665645599,47.2874794006],"type":"Point"}
}