{
  "type": "Feature",
  "properties": {
    "addr:full":"Breitenfurter Strasse 199 Wien Wien 1230",
    "addr:housenumber":"199",
    "addr:postcode":"1230",
    "addr:street":"Breitenfurter Strasse",
    "iso:country":"AT",
    "sg:address":"Breitenfurter Strasse 199",
    "sg:city":"Wien",
    "sg:classifiers":[
        {
            "category":"Military Area",
            "subcategory":"Air Force Base",
            "type":"Public Place"
        }
    ],
    "sg:phone":"+43 1 8023540",
    "sg:postcode":"1230",
    "sg:province":"Wien",
    "sg:tags":[
        "assembly",
        "automation"
    ],
    "sg:website":"fd-engineering.at",
    "wof:name":"FD-Engineering Ing. M. Kronsteiner GmbH",
    "wof:placetype":"venue"
},
  "geometry": {"coordinates":[16.3073406219,48.1583976746],"type":"Point"}
}