{
  "type": "Feature",
  "properties": {
    "addr:full":"Dorf 1 Lochau Vorarlberg 6911",
    "addr:housenumber":"1",
    "addr:postcode":"6911",
    "addr:street":"Dorf",
    "iso:country":"AT",
    "sg:address":"Dorf 1",
    "sg:city":"Lochau",
    "sg:orig_category":"Non-Classified Establishments",
    "sg:phone":"+43 5574 48552",
    "sg:postcode":"6911",
    "sg:province":"Vorarlberg",
    "wof:name":"Pfarramt",
    "wof:placetype":"venue"
},
  "geometry": {"coordinates":[9.7803926468,47.5371360779],"type":"Point"}
}