{
  "type": "Feature",
  "properties": {
    "addr:full":"Himberger Str 69 Wien Wien 1100",
    "addr:postcode":"1100",
    "addr:street":"Str 69",
    "iso:country":"AT",
    "sg:address":"Himberger Str 69",
    "sg:city":"Wien",
    "sg:orig_category":"Autoverwertung",
    "sg:phone":"+43 4316 8821680",
    "sg:postcode":"1100",
    "sg:province":"Wien",
    "sg:website":"kfz-dundler.com",
    "wof:name":"Dundler Reinhard u Ing Hermann",
    "wof:placetype":"venue"
},
  "geometry": {"coordinates":[16.3841629028,48.1360092163],"type":"Point"}
}