{
  "type": "Feature",
  "properties": {
    "addr:full":"Mayerg 6 Wien Wien 1020",
    "addr:housenumber":"6",
    "addr:postcode":"1020",
    "addr:street":"Mayerg",
    "iso:country":"AT",
    "sg:address":"Mayerg 6",
    "sg:city":"Wien",
    "sg:classifiers":[
        {
            "category":"Travel",
            "subcategory":"Hotels & Motels",
            "type":"Entertainment"
        }
    ],
    "sg:phone":"+43 1 21401230",
    "sg:postcode":"1020",
    "sg:province":"Wien",
    "wof:name":"Praterstern-Hotel",
    "wof:placetype":"venue"
},
  "geometry": {"coordinates":[16.3892288208,48.216468811],"type":"Point"}
}