{
  "type": "Feature",
  "properties": {
    "addr:full":"Medrazer Str 24a Fulpmes Tirol 6166",
    "addr:postcode":"6166",
    "addr:street":"Str 24A;Tirol",
    "iso:country":"AT",
    "sg:address":"Medrazer Str 24a",
    "sg:city":"Fulpmes",
    "sg:orig_category":"Elektroinstallationsunternehmen",
    "sg:phone":"+43 5225 64882",
    "sg:postcode":"6166",
    "sg:province":"Tirol",
    "wof:name":"Elektro Johnny",
    "wof:placetype":"venue"
},
  "geometry": {"coordinates":[11.3452959061,47.150718689],"type":"Point"}
}