{
  "type": "Feature",
  "properties": {
    "addr:full":"Archleweg 13 Serfaus Tirol 6534",
    "addr:housenumber":"13",
    "addr:postcode":"6534",
    "addr:street":"Archleweg;Tirol",
    "iso:country":"AT",
    "sg:address":"Archleweg 13",
    "sg:city":"Serfaus",
    "sg:orig_category":"Appartements / Ferienwohnungen",
    "sg:phone":"+43 5476 6668",
    "sg:postcode":"6534",
    "sg:province":"Tirol",
    "wof:name":"Haus Tschiderer",
    "wof:placetype":"venue"
},
  "geometry": {"coordinates":[10.6053972244,47.0375137329],"type":"Point"}
}