{
  "type": "Feature",
  "properties": {
    "addr:full":"Nr 72 Hof Salzburg 5322",
    "addr:postcode":"5322",
    "addr:street":"Nr;Hof",
    "iso:country":"AT",
    "sg:address":"Nr 72",
    "sg:city":"Hof",
    "sg:orig_category":"Transportunternehmen, Erdarbeiten",
    "sg:phone":"+43 6229 2782",
    "sg:postcode":"5322",
    "sg:province":"Salzburg",
    "wof:name":"Gr\u00fcnwald Gerhard",
    "wof:placetype":"venue"
},
  "geometry": {"coordinates":[13.2136449814,47.819229126],"type":"Point"}
}