{
  "type": "Feature",
  "properties": {
    "addr:full":"Waagpl 7 Klagenfurt K\u00e4rnten 9020",
    "addr:housenumber":"7",
    "addr:postcode":"9020",
    "addr:street":"Waagpl;Kaernten",
    "iso:country":"AT",
    "sg:address":"Waagpl 7",
    "sg:city":"Klagenfurt",
    "sg:orig_category":"Internet-Cafes",
    "sg:phone":"+43 463 509777",
    "sg:postcode":"9020",
    "sg:province":"K\u00e4rnten",
    "wof:name":"Internetcafe Gates",
    "wof:placetype":"venue"
},
  "geometry": {"coordinates":[14.311712265,46.6264762878],"type":"Point"}
}