{
  "type": "Feature",
  "properties": {
    "addr:full":"Wallensteinstrasse 27 Wien Wien 1200",
    "addr:housenumber":"27",
    "addr:postcode":"1200",
    "addr:street":"Wallensteinstrasse",
    "iso:country":"AT",
    "sg:address":"Wallensteinstrasse 27",
    "sg:city":"Wien",
    "sg:classifiers":[
        {
            "category":"Manufacturing",
            "subcategory":"Glass & Minerals",
            "type":"Manufacturing & Wholesale Goods"
        }
    ],
    "sg:phone":"+43 1 3300293",
    "sg:postcode":"1200",
    "sg:province":"Wien",
    "sg:tags":[
        "opt",
        "cleaning",
        "agent"
    ],
    "wof:name":"Robert Haberzettl Ges.m.b.H.",
    "wof:placetype":"venue"
},
  "geometry": {"coordinates":[16.3701114655,48.2297096252],"type":"Point"}
}