{
  "type": "Feature",
  "properties": {
    "iso:country":"AT",
    "sg:address":"Kellerg 239",
    "sg:city":"Langenzersdorf",
    "sg:orig_category":"Werbeagenturen",
    "sg:phone":"+43 1 29203440",
    "sg:postcode":"2103",
    "sg:province":"Nieder\u00f6sterreich",
    "wof:name":"Eccomedia Werbeagentur Dr Jestl KEG",
    "wof:placetype":"venue"
},
  "geometry": {"coordinates":[16.3839492798,48.3014373779],"type":"Point"}
}