{
  "type": "Feature",
  "properties": {
    "addr:full":"M\u00fchlberg 13 Sierning Ober\u00f6sterreich 4522",
    "addr:housenumber":"13",
    "addr:postcode":"4522",
    "addr:street":"Muehlberg",
    "iso:country":"AT",
    "sg:address":"M\u00fchlberg 13",
    "sg:city":"Sierning",
    "sg:orig_category":"Maler, Anstreicher U Lackierer",
    "sg:phone":"+43 7259 2529",
    "sg:postcode":"4522",
    "sg:province":"Ober\u00f6sterreich",
    "wof:name":"Gl\u00fcck Walter",
    "wof:placetype":"venue"
},
  "geometry": {"coordinates":[14.3093519211,48.0444831848],"type":"Point"}
}