{
  "type": "Feature",
  "properties": {
    "iso:country":"AT",
    "sg:address":"Kreuzg 4",
    "sg:city":"Mittersill",
    "sg:orig_category":"Installationsunternehmen",
    "sg:phone":"+43 4365 6244660",
    "sg:postcode":"5730",
    "sg:province":"Salzburg",
    "wof:name":"Bergrettung",
    "wof:placetype":"venue"
},
  "geometry": {"coordinates":[12.4773311615,47.2779998779],"type":"Point"}
}