{
  "type": "Feature",
  "properties": {
    "addr:full":"Gallstr 46 Baden Nieder\u00f6sterreich 2500",
    "addr:housenumber":"46",
    "addr:postcode":"2500",
    "addr:street":"Gallstr;Niederoesterreich",
    "iso:country":"AT",
    "sg:address":"Gallstr 46",
    "sg:city":"Baden",
    "sg:orig_category":"Isolierungen",
    "sg:phone":"+43 2252 21787",
    "sg:postcode":"2500",
    "sg:province":"Nieder\u00f6sterreich",
    "wof:name":"wb-akustik - Ing Walter Bartosik",
    "wof:placetype":"venue"
},
  "geometry": {"coordinates":[16.2295646667,47.9965019226],"type":"Point"}
}