{
  "type": "Feature",
  "properties": {
    "iso:country":"AT",
    "sg:address":"Hauptstr 27",
    "sg:city":"Seekirchen am Wallersee",
    "sg:orig_category":"Unterhaltungselektronik / Einzelhandel",
    "sg:phone":"+43 6212 7951",
    "sg:postcode":"5201",
    "sg:province":"Salzburg",
    "wof:name":"Strohbichler Elektronik KG",
    "wof:placetype":"venue"
},
  "geometry": {"coordinates":[13.1253662109,47.8940124512],"type":"Point"}
}