{
  "type": "Feature",
  "properties": {
    "addr:full":"Nr 34 Fiss Tirol 6533",
    "addr:postcode":"6533",
    "addr:street":"Nr 34;Tirol",
    "iso:country":"AT",
    "sg:address":"Nr 34",
    "sg:city":"Fiss",
    "sg:classifiers":[
        {
            "category":"Travel",
            "subcategory":"Hotels & Motels",
            "type":"Entertainment"
        }
    ],
    "sg:phone":"+43 5476 64270",
    "sg:postcode":"6533",
    "sg:province":"Tirol",
    "wof:name":"Hotel-Pension Am R\u00f6merweg",
    "wof:placetype":"venue"
},
  "geometry": {"coordinates":[10.618268013,47.0554733276],"type":"Point"}
}