{
  "type": "Feature",
  "properties": {
    "addr:full":"Franz Josef-Str 7 Zwettl Nieder\u00f6sterreich 3910",
    "addr:housenumber":"7",
    "addr:postcode":"3910",
    "addr:street":"Franz Josef-Str;Niederoesterreich",
    "iso:country":"AT",
    "sg:address":"Franz Josef-Str 7",
    "sg:city":"Zwettl",
    "sg:orig_category":"Non-Classified Establishments",
    "sg:phone":"+43 2822 528120",
    "sg:postcode":"3910",
    "sg:province":"Nieder\u00f6sterreich",
    "wof:name":"BEV-Vermessungsamt",
    "wof:placetype":"venue"
},
  "geometry": {"coordinates":[15.1681003571,48.6041564941],"type":"Point"}
}