{
  "type": "Feature",
  "properties": {
    "iso:country":"AT",
    "sg:address":"Nr 242",
    "sg:city":"Eibiswald",
    "sg:orig_category":"Tankstellen",
    "sg:phone":"+43 4334 6643463",
    "sg:postcode":"8552",
    "sg:province":"Steiermark",
    "wof:name":"Shell Austria GmbH",
    "wof:placetype":"venue"
},
  "geometry": {"coordinates":[15.2274599075,46.6824150085],"type":"Point"}
}