{
  "type": "Feature",
  "properties": {
    "addr:full":"Altenmarkter Str 1 Wies Steiermark 8551",
    "addr:housenumber":"1",
    "addr:postcode":"8551",
    "addr:street":"Str",
    "iso:country":"AT",
    "sg:address":"Altenmarkter Str 1",
    "sg:city":"Wies",
    "sg:orig_category":"Lebensmittel / Einzelhandel",
    "sg:phone":"+43 3465 4830",
    "sg:postcode":"8551",
    "sg:province":"Steiermark",
    "wof:name":"Zielpunkt Warenhandel GmbH & Co KG",
    "wof:placetype":"venue"
},
  "geometry": {"coordinates":[15.2672481537,46.7171325684],"type":"Point"}
}