{
  "type": "Feature",
  "properties": {
    "iso:country":"AT",
    "sg:address":"Marktstr 5",
    "sg:city":"St. Anton am Arlberg",
    "sg:orig_category":"Pensionen / Privatzimmer",
    "sg:phone":"+43 5446 3482",
    "sg:postcode":"6580",
    "sg:province":"Tirol",
    "wof:name":"Margaritenhof",
    "wof:placetype":"venue"
},
  "geometry": {"coordinates":[10.2684078217,47.1308441162],"type":"Point"}
}