{
  "type": "Feature",
  "properties": {
    "addr:full":"In L\u00fcssen 14 Gaweinstal Nieder\u00f6sterreich 2191",
    "addr:housenumber":"14",
    "addr:postcode":"2191",
    "iso:country":"AT",
    "sg:address":"In L\u00fcssen 14",
    "sg:city":"Gaweinstal",
    "sg:orig_category":"Installationsunternehmen",
    "sg:phone":"+43 2574 28104",
    "sg:postcode":"2191",
    "sg:province":"Nieder\u00f6sterreich",
    "wof:name":"Manschein Siegfried Ing GesmbH",
    "wof:placetype":"venue"
},
  "geometry": {"coordinates":[16.5884838104,48.4777412415],"type":"Point"}
}