{
  "type": "Feature",
  "properties": {
    "addr:full":"Beethovenweg 4 Wolfsberg K\u00e4rnten 9400",
    "addr:housenumber":"4;kaernten",
    "addr:postcode":"9400",
    "addr:street":"Beethovenweg",
    "iso:country":"AT",
    "sg:address":"Beethovenweg 4",
    "sg:city":"Wolfsberg",
    "sg:orig_category":"Feng-Shui",
    "sg:phone":"+43 4352 46818",
    "sg:postcode":"9400",
    "sg:province":"K\u00e4rnten",
    "sg:website":"ourvitalworld.de",
    "wof:name":"Pape Edith Qi-Mag Feng Shui Consultant",
    "wof:placetype":"venue"
},
  "geometry": {"coordinates":[14.8565177917,46.8209457397],"type":"Point"}
}