{
  "type": "Feature",
  "properties": {
    "iso:country":"AT",
    "sg:address":"Zur Rastst\u00e4tte",
    "sg:city":"Hohenems",
    "sg:orig_category":"Tankstellen",
    "sg:phone":"+43 5576 42209",
    "sg:postcode":"6845",
    "sg:province":"Vorarlberg",
    "sg:website":"www.rosenberger.cc",
    "wof:name":"Rosenberger Tankstellenbetriebs-GmbH",
    "wof:placetype":"venue"
},
  "geometry": {"coordinates":[9.6581659317,47.3662261963],"type":"Point"}
}