{
  "type": "Feature",
  "properties": {
    "addr:full":"Th\u00fcrnau 26 Thening Ober\u00f6sterreich 4062",
    "addr:housenumber":"26",
    "addr:postcode":"4062",
    "addr:street":"Thuernau;Oberoesterreich",
    "iso:country":"AT",
    "sg:address":"Th\u00fcrnau 26",
    "sg:city":"Thening",
    "sg:classifiers":[
        {
            "category":"Professional",
            "type":"Services"
        }
    ],
    "sg:phone":"+43 7221 641140",
    "sg:postcode":"4062",
    "sg:province":"Ober\u00f6sterreich",
    "sg:tags":[
        "plant",
        "weighing",
        "weigher",
        "hydraulic"
    ],
    "sg:website":"sierzega.com",
    "wof:name":"Sierzega Elektronik GmbH",
    "wof:placetype":"venue"
},
  "geometry": {"coordinates":[14.1671743393,48.2550582886],"type":"Point"}
}