{
  "type": "Feature",
  "properties": {
    "addr:full":"Marktg 22 Hopfgarten im Brixental Tirol 6361",
    "addr:housenumber":"22",
    "addr:postcode":"6361",
    "addr:street":"Marktg;Tirol",
    "iso:country":"AT",
    "sg:address":"Marktg 22",
    "sg:city":"Hopfgarten im Brixental",
    "sg:orig_category":"Sonderschulen",
    "sg:phone":"+43 4353 35228119",
    "sg:postcode":"6361",
    "sg:province":"Tirol",
    "wof:name":"Sonderschule",
    "wof:placetype":"venue"
},
  "geometry": {"coordinates":[12.1574897766,47.4497718811],"type":"Point"}
}