{
  "type": "Feature",
  "properties": {
    "addr:full":"Rainweg 2 Kalsdorf Steiermark 8401",
    "addr:housenumber":"2",
    "addr:postcode":"8401",
    "addr:street":"Rainweg",
    "iso:country":"AT",
    "sg:address":"Rainweg 2",
    "sg:city":"Kalsdorf",
    "sg:orig_category":"Damenmoden",
    "sg:phone":"+43 4331 3552661",
    "sg:postcode":"8401",
    "sg:province":"Steiermark",
    "wof:name":"Zangl Anna",
    "wof:placetype":"venue"
},
  "geometry": {"coordinates":[15.4806699753,46.9527626038],"type":"Point"}
}