{
  "type": "Feature",
  "properties": {
    "iso:country":"AT",
    "sg:address":"TZ Marktstr 3",
    "sg:city":"Eisenstadt",
    "sg:orig_category":"Sicherheitstechnik",
    "sg:phone":"+43 4326 82704380",
    "sg:postcode":"7000",
    "sg:province":"Burgenland",
    "wof:name":"worklab Burgenland arbeitsmedizinisches u sicherheitstechnisches Netzwerk",
    "wof:placetype":"venue"
},
  "geometry": {"coordinates":[16.5189552307,47.8455657959],"type":"Point"}
}