{
  "type": "Feature",
  "properties": {
    "addr:full":"Griesstr 36 Pinggau Steiermark 8243",
    "addr:housenumber":"36",
    "addr:postcode":"8243",
    "addr:street":"Griesstr",
    "iso:country":"AT",
    "sg:address":"Griesstr 36",
    "sg:city":"Pinggau",
    "sg:orig_category":"Holzgro\u00c3\u0178handel",
    "sg:phone":"+43 3339 223260",
    "sg:postcode":"8243",
    "sg:province":"Steiermark",
    "wof:name":"Holzwerk Kern GesmbH & Co KG",
    "wof:placetype":"venue"
},
  "geometry": {"coordinates":[16.0684642792,47.4368515015],"type":"Point"}
}