{
  "type": "Feature",
  "properties": {
    "addr:full":"Schulg 2 Freistadt Ober\u00f6sterreich 4240",
    "addr:housenumber":"2",
    "addr:postcode":"4240",
    "addr:street":"Schulg",
    "iso:country":"AT",
    "sg:address":"Schulg 2",
    "sg:city":"Freistadt",
    "sg:orig_category":"Steuerberatung",
    "sg:phone":"+43 7942 77444",
    "sg:postcode":"4240",
    "sg:province":"Ober\u00f6sterreich",
    "wof:name":"Lumper-Wiesinger Ernestine",
    "wof:placetype":"venue"
},
  "geometry": {"coordinates":[14.5045843124,48.5106544495],"type":"Point"}
}