{
  "type": "Feature",
  "properties": {
    "addr:full":"Nr 88 Utzenaich Ober\u00f6sterreich 4972",
    "addr:postcode":"4972",
    "addr:street":"Nr 88",
    "iso:country":"AT",
    "sg:address":"Nr 88",
    "sg:city":"Utzenaich",
    "sg:orig_category":"Baumeister",
    "sg:phone":"+43 7751 6362",
    "sg:postcode":"4972",
    "sg:province":"Ober\u00f6sterreich",
    "wof:name":"H\u00f6ckner Erwin Ing",
    "wof:placetype":"venue"
},
  "geometry": {"coordinates":[13.459774971,48.2758560181],"type":"Point"}
}