{
  "type": "Feature",
  "properties": {
    "iso:country":"AT",
    "sg:address":"Altstadt 85-87",
    "sg:city":"Bruck an der Leitha",
    "sg:orig_category":"Tankstellen",
    "sg:phone":"+43 2162 62629",
    "sg:postcode":"2460",
    "sg:province":"Nieder\u00f6sterreich",
    "wof:name":"Seewald Walter Ing",
    "wof:placetype":"venue"
},
  "geometry": {"coordinates":[16.7699298859,48.0215797424],"type":"Point"}
}