{
  "type": "Feature",
  "properties": {
    "addr:full":"Brucknerg 16 Altheim Ober\u00f6sterreich 4950",
    "addr:housenumber":"16",
    "addr:postcode":"4950",
    "addr:street":"Brucknerg",
    "iso:country":"AT",
    "sg:address":"Brucknerg 16",
    "sg:city":"Altheim",
    "sg:orig_category":"Holzbearbeitungsmaschinen U -Werkzeuge",
    "sg:phone":"+43 4377 23422650",
    "sg:postcode":"4950",
    "sg:province":"Ober\u00f6sterreich",
    "wof:name":"Mattes Werkzeuge GmbH & Co KG",
    "wof:placetype":"venue"
},
  "geometry": {"coordinates":[13.2320013046,48.2511253357],"type":"Point"}
}