{
  "type": "Feature",
  "properties": {
    "addr:full":"Birkenweg 7 Klagenfurt K\u00e4rnten 9020",
    "addr:housenumber":"7",
    "addr:postcode":"9020",
    "addr:street":"Birkenweg;Kaernten",
    "iso:country":"AT",
    "sg:address":"Birkenweg 7",
    "sg:city":"Klagenfurt",
    "sg:classifiers":[
        {
            "category":"Military Area",
            "subcategory":"Army Base",
            "type":"Public Place"
        }
    ],
    "sg:phone":"+43 4346 3437748",
    "sg:postcode":"9020",
    "sg:province":"K\u00e4rnten",
    "sg:tags":[
        "shiatsu"
    ],
    "wof:name":"Dapra David Mag",
    "wof:placetype":"venue"
},
  "geometry": {"coordinates":[14.3125972748,46.6396789551],"type":"Point"}
}