{
  "type": "Feature",
  "properties": {
    "addr:full":"Marktstr 67 St. Michael im Lungau Salzburg 5582",
    "addr:housenumber":"67",
    "addr:postcode":"5582",
    "addr:street":"Marktstr",
    "iso:country":"AT",
    "sg:address":"Marktstr 67",
    "sg:city":"St. Michael im Lungau",
    "sg:orig_category":"Familien / Beratung",
    "sg:phone":"+43 4364 778213",
    "sg:postcode":"5582",
    "sg:province":"Salzburg",
    "wof:name":"Familien- u Erziehungsberatung d Landes",
    "wof:placetype":"venue"
},
  "geometry": {"coordinates":[13.6381587982,47.0977020264],"type":"Point"}
}