{
  "type": "Feature",
  "properties": {
    "iso:country":"AT",
    "sg:address":"Flugfeldstr 93",
    "sg:city":"Strasshof an der Nordbahn",
    "sg:orig_category":"Tauschvermittler",
    "sg:phone":"+43 4322 873911",
    "sg:postcode":"2231",
    "sg:province":"Nieder\u00f6sterreich",
    "wof:name":"Tauschmarkt R\u00f6ckl",
    "wof:placetype":"venue"
},
  "geometry": {"coordinates":[16.6648159027,48.3152618408],"type":"Point"}
}