{
  "type": "Feature",
  "properties": {
    "addr:full":"Faulmanng 7 Wien Wien 1040",
    "addr:housenumber":"7",
    "addr:postcode":"1040",
    "addr:street":"Faulmanng",
    "iso:country":"AT",
    "sg:address":"Faulmanng 7",
    "sg:city":"Wien",
    "sg:orig_category":"Fotoausarbeitungen",
    "sg:phone":"+43 1 5879406",
    "sg:postcode":"1040",
    "sg:province":"Wien",
    "wof:name":"Foto Shop Naschmarkt",
    "wof:placetype":"venue"
},
  "geometry": {"coordinates":[16.3650245667,48.1989097595],"type":"Point"}
}