{
  "type": "Feature",
  "properties": {
    "addr:full":"Alkovner Str 13 Alkoven Ober\u00f6sterreich 4072",
    "addr:housenumber":"13",
    "addr:postcode":"4072",
    "addr:street":"Str",
    "iso:country":"AT",
    "sg:address":"Alkovner Str 13",
    "sg:city":"Alkoven",
    "sg:orig_category":"Steuerberatung",
    "sg:phone":"+43 7274 61300",
    "sg:postcode":"4072",
    "sg:province":"Ober\u00f6sterreich",
    "wof:name":"Allerstorfer & Hochbold Steuerberatungs-GmbH",
    "wof:placetype":"venue"
},
  "geometry": {"coordinates":[14.1441545486,48.2856445312],"type":"Point"}
}