{
  "type": "Feature",
  "properties": {
    "addr:full":"Hutweideng 36 Wien Wien 1190",
    "addr:housenumber":"36",
    "addr:postcode":"1190",
    "addr:street":"Hutweideng",
    "iso:country":"AT",
    "sg:address":"Hutweideng 36",
    "sg:city":"Wien",
    "sg:orig_category":"Maler, Anstreicher U Lackierer",
    "sg:phone":"+43 1 3284786",
    "sg:postcode":"1190",
    "sg:province":"Wien",
    "wof:name":"Loibl Heinz",
    "wof:placetype":"venue"
},
  "geometry": {"coordinates":[16.3350849152,48.2424621582],"type":"Point"}
}