{
  "type": "Feature",
  "properties": {
    "iso:country":"AT",
    "sg:address":"Frauentaler Str 48",
    "sg:city":"Deutschlandsberg",
    "sg:orig_category":"Sporthallen",
    "sg:phone":"+43 664 2141825",
    "sg:postcode":"8530",
    "sg:province":"Steiermark",
    "wof:name":"Koralmhalle der Stadtgemeinde Deutschlandsberg",
    "wof:placetype":"venue"
},
  "geometry": {"coordinates":[15.2217340469,46.8174819946],"type":"Point"}
}