{
  "type": "Feature",
  "properties": {
    "addr:full":"Uferstr 86a Aigen Salzburg 5026",
    "addr:housenumber":"86a",
    "addr:postcode":"5026",
    "addr:street":"Uferstr;Salzburg",
    "iso:country":"AT",
    "sg:address":"Uferstr 86a",
    "sg:city":"Aigen",
    "sg:orig_category":"Rauchfangkehrer",
    "sg:phone":"+43 662 627728",
    "sg:postcode":"5026",
    "sg:province":"Salzburg",
    "wof:name":"Feichtner Horst",
    "wof:placetype":"venue"
},
  "geometry": {"coordinates":[13.0788917542,47.7731742859],"type":"Point"}
}