{
  "type": "Feature",
  "properties": {
    "addr:full":"Pulverturmweg 3 Kitzb\u00fchel Tirol 6370",
    "addr:housenumber":"3",
    "addr:postcode":"6370",
    "addr:street":"Pulverturmweg;Tirol",
    "iso:country":"AT",
    "sg:address":"Pulverturmweg 3",
    "sg:city":"Kitzb\u00fchel",
    "sg:orig_category":"Pensionen / Privatzimmer",
    "sg:phone":"+43 5356 66469",
    "sg:postcode":"6370",
    "sg:province":"Tirol",
    "wof:name":"Haus Eugenie",
    "wof:placetype":"venue"
},
  "geometry": {"coordinates":[12.3802051544,47.4491233826],"type":"Point"}
}