{
  "type": "Feature",
  "properties": {
    "iso:country":"AT",
    "sg:address":"Pulverturmweg 3",
    "sg:city":"Kitzb\u00fchel",
    "sg:orig_category":"Pensionen / Privatzimmer",
    "sg:phone":"+43 5356 66469",
    "sg:postcode":"6370",
    "sg:province":"Tirol",
    "wof:name":"Haus Eugenie",
    "wof:placetype":"venue"
},
  "geometry": {"coordinates":[12.3802051544,47.4491233826],"type":"Point"}
}