{
  "type": "Feature",
  "properties": {
    "addr:full":"Freifeldweg 541 P\u00f6llau Steiermark 8225",
    "addr:housenumber":"541",
    "addr:postcode":"8225",
    "addr:street":"Poellau Steiermark",
    "iso:country":"AT",
    "sg:address":"Freifeldweg 541",
    "sg:city":"P\u00f6llau",
    "sg:orig_category":"Holzhandel",
    "sg:phone":"+43 3335 2027",
    "sg:postcode":"8225",
    "sg:province":"Steiermark",
    "wof:name":"Schwarz Ernst",
    "wof:placetype":"venue"
},
  "geometry": {"coordinates":[15.8337945938,47.301990509],"type":"Point"}
}