{
  "type": "Feature",
  "properties": {
    "addr:full":"Schulg 6 Bad Ischl Ober\u00f6sterreich 4820",
    "addr:housenumber":"6",
    "addr:postcode":"4820",
    "addr:street":"Schulg",
    "iso:country":"AT",
    "sg:address":"Schulg 6",
    "sg:city":"Bad Ischl",
    "sg:orig_category":"Galerien",
    "sg:phone":"+43 6132 26629",
    "sg:postcode":"4820",
    "sg:province":"Ober\u00f6sterreich",
    "wof:name":"Galerie Sams",
    "wof:placetype":"venue"
},
  "geometry": {"coordinates":[13.622092247,47.7121696472],"type":"Point"}
}