{
  "type": "Feature",
  "properties": {
    "addr:full":"Richard Strau\u00df-Str 4  Wien Wien 1230",
    "addr:housenumber":"4",
    "addr:postcode":"1230",
    "iso:country":"AT",
    "sg:address":"Richard Strau\u00df-Str 4 ",
    "sg:city":"Wien",
    "sg:classifiers":[
        {
            "category":"Autos & Motor Vehicles",
            "subcategory":"Automobile Sales",
            "type":"Retail Goods"
        }
    ],
    "sg:phone":"+43 4316 161646",
    "sg:postcode":"1230",
    "sg:province":"Wien",
    "sg:tags":[
        "industrial"
    ],
    "wof:name":"EBERSP\u00c4CHER GESMBH",
    "wof:placetype":"venue"
},
  "geometry": {"coordinates":[16.3424072266,48.1475868225],"type":"Point"}
}