{
  "type": "Feature",
  "properties": {
    "iso:country":"AT",
    "sg:address":"Schweizer G 3",
    "sg:city":"Lienz",
    "sg:orig_category":"Versicherungsunternehmen",
    "sg:phone":"+43 4852 68949",
    "sg:postcode":"9900",
    "sg:province":"Tirol",
    "wof:name":"D.A.S. \u00f6sterr Allgemeine Rechtsschutz-Versicherungs-AG",
    "wof:placetype":"venue"
},
  "geometry": {"coordinates":[12.7636919022,46.8306350708],"type":"Point"}
}