{
  "type": "Feature",
  "properties": {
    "iso:country":"AT",
    "sg:address":"Franz Peydl-G 5",
    "sg:city":"Untertullnerbach",
    "sg:orig_category":"Werbegrafik- U Grafik-Design",
    "sg:phone":"+43 2233 52404",
    "sg:postcode":"3011",
    "sg:province":"Nieder\u00f6sterreich",
    "wof:name":"Kugler Concept - Grafik Design-Conception-Events",
    "wof:placetype":"venue"
},
  "geometry": {"coordinates":[16.124420166,48.1900024414],"type":"Point"}
}