{
  "type": "Feature",
  "properties": {
    "addr:full":"Wiener Str 31 G\u00fcssing Burgenland 7540",
    "addr:postcode":"7540",
    "addr:street":"31 Guessing",
    "iso:country":"AT",
    "sg:address":"Wiener Str 31",
    "sg:city":"G\u00fcssing",
    "sg:orig_category":"Bauunternehmen",
    "sg:phone":"+43 3322 423860",
    "sg:postcode":"7540",
    "sg:province":"Burgenland",
    "wof:name":"LANG F & K MENHOFER BaugesmbH & Co KG",
    "wof:placetype":"venue"
},
  "geometry": {"coordinates":[16.3218212128,47.0687484741],"type":"Point"}
}