{
  "type": "Feature",
  "properties": {
    "addr:full":"Stra\u00df 146 Lech Vorarlberg 6764",
    "addr:housenumber":"146",
    "addr:postcode":"6764",
    "addr:street":"Strass",
    "iso:country":"AT",
    "sg:address":"Stra\u00df 146",
    "sg:city":"Lech",
    "sg:classifiers":[
        {
            "category":"Travel",
            "subcategory":"Hotels & Motels",
            "type":"Entertainment"
        }
    ],
    "sg:phone":"+43 5583 23490",
    "sg:postcode":"6764",
    "sg:province":"Vorarlberg",
    "wof:name":"Brunnenhof Hotel",
    "wof:placetype":"venue"
},
  "geometry": {"coordinates":[10.1417798996,47.2082939148],"type":"Point"}
}