{
  "type": "Feature",
  "properties": {
    "addr:full":"Bergkammweg 33 Rudersdorf Burgenland 7571",
    "addr:housenumber":"33",
    "addr:postcode":"7571",
    "addr:street":"Bergkammweg",
    "iso:country":"AT",
    "sg:address":"Bergkammweg 33",
    "sg:city":"Rudersdorf",
    "sg:orig_category":"Glasereien",
    "sg:phone":"+43 3382 71736",
    "sg:postcode":"7571",
    "sg:province":"Burgenland",
    "wof:name":"Glaserei Siegfried Bauer",
    "wof:placetype":"venue"
},
  "geometry": {"coordinates":[16.1343631744,47.0502738953],"type":"Point"}
}