{
  "type": "Feature",
  "properties": {
    "addr:full":"Vormarkt 40 Riedau Ober\u00f6sterreich 4752",
    "addr:housenumber":"40",
    "addr:postcode":"4752",
    "addr:street":"Vormarkt",
    "iso:country":"AT",
    "sg:address":"Vormarkt 40",
    "sg:city":"Riedau",
    "sg:orig_category":"Tischlereien",
    "sg:phone":"+43 7764 6611",
    "sg:postcode":"4752",
    "sg:province":"Ober\u00f6sterreich",
    "wof:name":"Meier Reinhard",
    "wof:placetype":"venue"
},
  "geometry": {"coordinates":[13.6297492981,48.303440094],"type":"Point"}
}