{
  "type": "Feature",
  "properties": {
    "addr:full":"Schlo\u00dfstr 4 Baumkirchen Tirol 6121",
    "addr:housenumber":"4",
    "addr:postcode":"6121",
    "addr:street":"Schlossstr;Tirol",
    "iso:country":"AT",
    "sg:address":"Schlo\u00dfstr 4",
    "sg:city":"Baumkirchen",
    "sg:orig_category":"Non-Classified Establishments",
    "sg:phone":"+43 5224 52961",
    "sg:postcode":"6121",
    "sg:province":"Tirol",
    "wof:name":"Don Bosco Schwestern - Bildungshaus",
    "wof:placetype":"venue"
},
  "geometry": {"coordinates":[11.5634288788,47.3009567261],"type":"Point"}
}