{
  "type": "Feature",
  "properties": {
    "addr:full":"Starhembergstr 52 Linz Ober\u00f6sterreich 4020",
    "addr:housenumber":"52",
    "addr:postcode":"4020",
    "addr:street":"Starhembergstr",
    "iso:country":"AT",
    "sg:address":"Starhembergstr 52",
    "sg:city":"Linz",
    "sg:orig_category":"Weine / Einzelhandel",
    "sg:phone":"+43 732 661196",
    "sg:postcode":"4020",
    "sg:province":"Ober\u00f6sterreich",
    "wof:name":"Zellinger Andreas",
    "wof:placetype":"venue"
},
  "geometry": {"coordinates":[14.2994318008,48.2989616394],"type":"Point"}
}