{
  "type": "Feature",
  "properties": {
    "iso:country":"AT",
    "sg:address":"Schulg 10",
    "sg:city":"Fernitz",
    "sg:orig_category":"Non-Classified Establishments",
    "sg:phone":"+43 3135 554000",
    "sg:postcode":"8072",
    "sg:province":"Steiermark",
    "wof:name":"Pfarramt",
    "wof:placetype":"venue"
},
  "geometry": {"coordinates":[15.5014152527,46.9729728699],"type":"Point"}
}