{
  "type": "Feature",
  "properties": {
    "iso:country":"AT",
    "sg:address":"Nr 40",
    "sg:city":"M\u00fcrzsteg",
    "sg:orig_category":"Feuerwehren",
    "sg:phone":"+43 3859 2122",
    "sg:postcode":"8693",
    "sg:province":"Steiermark",
    "wof:name":"Freiwillige Feuerwehr M\u00fcrzsteg",
    "wof:placetype":"venue"
},
  "geometry": {"coordinates":[166.9221496582,-0.5282999873],"type":"Point"}
}