{
  "type": "Feature",
  "properties": {
    "addr:full":"Donaustadtstr 17 Wien Wien 1220",
    "addr:housenumber":"17",
    "addr:postcode":"1220",
    "addr:street":"Donaustadtstr",
    "iso:country":"AT",
    "sg:address":"Donaustadtstr 17",
    "sg:city":"Wien",
    "sg:orig_category":"Autoreparatur",
    "sg:phone":"+43 1 2025767",
    "sg:postcode":"1220",
    "sg:province":"Wien",
    "wof:name":"FASTBOX Autoservice GmbH & Co KG",
    "wof:placetype":"venue"
},
  "geometry": {"coordinates":[16.4436645508,48.2332763672],"type":"Point"}
}