{
  "type": "Feature",
  "properties": {
    "iso:country":"AT",
    "sg:address":"Leobner Str 75a",
    "sg:city":"Bruck an der Mur",
    "sg:orig_category":"Fliesen U Platten",
    "sg:phone":"+43 4338 62556510",
    "sg:postcode":"8600",
    "sg:province":"Steiermark",
    "wof:name":"Mocharitsch Hans-Peter Ing",
    "wof:placetype":"venue"
},
  "geometry": {"coordinates":[15.2539558411,47.4040145874],"type":"Point"}
}