{
  "type": "Feature",
  "properties": {
    "addr:full":"Kardinal-Nagl-Pl 1 Wien Wien 1030",
    "addr:housenumber":"1",
    "addr:postcode":"1030",
    "addr:street":"Kardinal-Nagl-Pl",
    "iso:country":"AT",
    "sg:address":"Kardinal-Nagl-Pl 1",
    "sg:city":"Wien",
    "sg:orig_category":"Damenmoden",
    "sg:phone":"+43 1 7159710",
    "sg:postcode":"1030",
    "sg:province":"Wien",
    "wof:name":"Dany Moden M Eugenie Bydzovsky",
    "wof:placetype":"venue"
},
  "geometry": {"coordinates":[16.4024066925,48.1971931458],"type":"Point"}
}