{
  "type": "Feature",
  "properties": {
    "addr:full":"Grabenweg 72 Innsbruck Tirol 6020",
    "addr:housenumber":"72",
    "addr:postcode":"6020",
    "addr:street":"Grabenweg;Tirol",
    "iso:country":"AT",
    "sg:address":"Grabenweg 72",
    "sg:city":"Innsbruck",
    "sg:classifiers":[
        {
            "category":"Professional",
            "subcategory":"Computer Services",
            "type":"Services"
        }
    ],
    "sg:phone":"+43 512 3428880",
    "sg:postcode":"6020",
    "sg:province":"Tirol",
    "sg:tags":[
        "software"
    ],
    "sg:website":"www.idus.at",
    "wof:name":"IDUS-Software GmbH",
    "wof:placetype":"venue"
},
  "geometry": {"coordinates":[11.4403610229,47.2649726868],"type":"Point"}
}