{
  "type": "Feature",
  "properties": {
    "addr:full":"Oberfeldstr 95 Wels Ober\u00f6sterreich 4600",
    "addr:housenumber":"95",
    "addr:postcode":"4600",
    "addr:street":"Oberfeldstr;Oberoesterreich",
    "iso:country":"AT",
    "sg:address":"Oberfeldstr 95",
    "sg:city":"Wels",
    "sg:orig_category":"Tabaktrafiken",
    "sg:phone":"+43 7242 64004",
    "sg:postcode":"4600",
    "sg:province":"Ober\u00f6sterreich",
    "wof:name":"Sch\u00e4ffer Franz",
    "wof:placetype":"venue"
},
  "geometry": {"coordinates":[14.0166196823,48.1821784973],"type":"Point"}
}