{
  "type": "Feature",
  "properties": {
    "addr:full":"Messingg. 17  Lienz Tirol 9900",
    "addr:housenumber":"17",
    "addr:postcode":"9900",
    "addr:street":"Messingg.;Tirol",
    "iso:country":"AT",
    "sg:address":"Messingg. 17 ",
    "sg:city":"Lienz",
    "sg:classifiers":[
        {
            "category":"Shopping",
            "subcategory":"Clothing, Apparel, & Fashions",
            "type":"Retail Goods"
        }
    ],
    "sg:phone":"+43 4348 52623140",
    "sg:postcode":"9900",
    "sg:province":"Tirol",
    "sg:tags":[
        "clothes"
    ],
    "wof:name":"MANFRED MANFREDA",
    "wof:placetype":"venue"
},
  "geometry": {"coordinates":[12.7304296494,46.8440513611],"type":"Point"}
}