{
  "type": "Feature",
  "properties": {
    "iso:country":"AT",
    "sg:address":"Rauschgraben 31",
    "sg:city":"Mutters",
    "sg:orig_category":"Feuerwerksartikel U Feuerwerke",
    "sg:phone":"+43 4351 2548132",
    "sg:postcode":"6162",
    "sg:province":"Tirol",
    "wof:name":"High Low Boom",
    "wof:placetype":"venue"
},
  "geometry": {"coordinates":[11.3756446838,47.2240447998],"type":"Point"}
}