{
  "type": "Feature",
  "properties": {
    "iso:country":"AT",
    "sg:address":"Siebensterng 29/13",
    "sg:city":"Wien",
    "sg:orig_category":"Weiterbildungsinstitute M Allg U Berufl Bildungsangebot",
    "sg:phone":"+43 4313 679100",
    "sg:postcode":"1070",
    "sg:province":"Wien",
    "wof:name":"Abraham & Abraham OEG",
    "wof:placetype":"venue"
},
  "geometry": {"coordinates":[16.3519458771,48.2019805908],"type":"Point"}
}