{
  "type": "Feature",
  "properties": {
    "iso:country":"AT",
    "sg:address":"Schumanngasse 38",
    "sg:city":"Perchtoldsdorf",
    "sg:classifiers":[
        {
            "category":"Military Area",
            "subcategory":"Air Force Base",
            "type":"Public Place"
        }
    ],
    "sg:phone":"+43 1 86562550",
    "sg:postcode":"2380",
    "sg:province":"Nieder\u00f6sterreich",
    "sg:tags":[
        "water",
        "ceiling",
        "cooling"
    ],
    "wof:name":"Waema W\u00e4rmetechnik und Maschinenbau Ges.m.b.H.",
    "wof:placetype":"venue"
},
  "geometry": {"coordinates":[16.2850265503,48.1166534424],"type":"Point"}
}