{
  "type": "Feature",
  "properties": {
    "addr:full":"Michaelnbach 44 Michaelnbach Ober\u00f6sterreich 4712",
    "addr:housenumber":"44",
    "addr:postcode":"4712",
    "addr:street":"Michaelnbach",
    "iso:country":"AT",
    "sg:address":"Michaelnbach 44",
    "sg:city":"Michaelnbach",
    "sg:classifiers":[
        {
            "category":"Home & Garden",
            "subcategory":"Furniture",
            "type":"Retail Goods"
        }
    ],
    "sg:phone":"+43 7277 25320",
    "sg:postcode":"4712",
    "sg:province":"Ober\u00f6sterreich",
    "sg:tags":[
        "solid",
        "wood",
        "made",
        "childrens"
    ],
    "sg:website":"brunnmair.at",
    "wof:name":"Johann Brunnmair Tischlerei",
    "wof:placetype":"venue"
},
  "geometry": {"coordinates":[13.8315563202,48.2880363464],"type":"Point"}
}