{
  "type": "Feature",
  "properties": {
    "iso:country":"AT",
    "sg:address":"Auenweg 35",
    "sg:city":"Villach",
    "sg:orig_category":"Zeitungen U Zeitschriften / Vertrieb",
    "sg:phone":"+43 4342 42311456",
    "sg:postcode":"9500",
    "sg:province":"K\u00e4rnten",
    "wof:name":"Mediaprint ZeitungsvertriebsgesmbH & Co KG",
    "wof:placetype":"venue"
},
  "geometry": {"coordinates":[13.8364143372,46.5924720764],"type":"Point"}
}