{
  "type": "Feature",
  "properties": {
    "addr:full":"Ebentaler Str 137 Klagenfurt K\u00e4rnten 9020",
    "addr:housenumber":"137",
    "addr:postcode":"9020",
    "addr:street":"Kaernten",
    "iso:country":"AT",
    "sg:address":"Ebentaler Str 137",
    "sg:city":"Klagenfurt",
    "sg:orig_category":"Gie\u00c3\u0178ereien",
    "sg:phone":"+43 4346 3333230",
    "sg:postcode":"9020",
    "sg:province":"K\u00e4rnten",
    "wof:name":"Stiegler Metallwerke GesmbH",
    "wof:placetype":"venue"
},
  "geometry": {"coordinates":[14.3378820419,46.6154747009],"type":"Point"}
}