{
  "type": "Feature",
  "properties": {
    "addr:full":"Opernring 21/12 Wien Wien 1010",
    "addr:housenumber":"21 / 12",
    "addr:postcode":"1010",
    "addr:street":"Opernring",
    "iso:country":"AT",
    "sg:address":"Opernring 21/12",
    "sg:city":"Wien",
    "sg:orig_category":"Galerien",
    "sg:phone":"+43 1 5810252",
    "sg:postcode":"1010",
    "sg:province":"Wien",
    "wof:name":"Galerie Karenina Mag Kirchberger-Egarmina",
    "wof:placetype":"venue"
},
  "geometry": {"coordinates":[16.3647918701,48.2032089233],"type":"Point"}
}