{
  "type": "Feature",
  "properties": {
    "iso:country":"AT",
    "sg:address":"Kreuzweg 1",
    "sg:city":"Rottenegg",
    "sg:orig_category":"Banken U Sparkassen",
    "sg:phone":"+43 4372 3487026",
    "sg:postcode":"4112",
    "sg:province":"Ober\u00f6sterreich",
    "wof:name":"Raiffeisenbank St Gotthard regGenmbH",
    "wof:placetype":"venue"
},
  "geometry": {"coordinates":[14.1323442459,48.3792457581],"type":"Point"}
}