{
  "type": "Feature",
  "properties": {
    "addr:full":"Josef-Pirchl-Str 3 Kitzb\u00fchel Tirol 6370",
    "addr:housenumber":"3",
    "addr:postcode":"6370",
    "addr:street":"Josef-Pirchl-Str;Tirol",
    "iso:country":"AT",
    "sg:address":"Josef-Pirchl-Str 3",
    "sg:city":"Kitzb\u00fchel",
    "sg:classifiers":[
        {
            "category":"Restaurant",
            "type":"Food & Drink"
        }
    ],
    "sg:phone":"+43 4353 5674882",
    "sg:postcode":"6370",
    "sg:province":"Tirol",
    "wof:name":"Restaurant Essen u Trinken",
    "wof:placetype":"venue"
},
  "geometry": {"coordinates":[12.3896560669,47.4480133057],"type":"Point"}
}