{
  "type": "Feature",
  "properties": {
    "addr:full":"Hauptstr 10 St. Radegund Steiermark 8061",
    "addr:housenumber":"10",
    "addr:postcode":"8061",
    "addr:street":"Hauptstr",
    "iso:country":"AT",
    "sg:address":"Hauptstr 10",
    "sg:city":"St. Radegund",
    "sg:orig_category":"Gemeinden",
    "sg:phone":"+43 4331 3223010",
    "sg:postcode":"8061",
    "sg:province":"Steiermark",
    "wof:name":"Gemeinde St Radegund bei Graz",
    "wof:placetype":"venue"
},
  "geometry": {"coordinates":[15.4894170761,47.1812095642],"type":"Point"}
}