{
  "type": "Feature",
  "properties": {
    "addr:full":"Loiblstr 2 Ferlach K\u00e4rnten 9170",
    "addr:housenumber":"2",
    "addr:postcode":"9170",
    "addr:street":"Loiblstr;Kaernten",
    "iso:country":"AT",
    "sg:address":"Loiblstr 2",
    "sg:city":"Ferlach",
    "sg:orig_category":"Fleischhauereien",
    "sg:phone":"+43 4227 2412",
    "sg:postcode":"9170",
    "sg:province":"K\u00e4rnten",
    "wof:name":"Nu\u00dfbaumer Erich",
    "wof:placetype":"venue"
},
  "geometry": {"coordinates":[14.3005723953,46.5243873596],"type":"Point"}
}