{
  "type": "Feature",
  "properties": {
    "iso:country":"AT",
    "sg:address":"Nr 38",
    "sg:city":"Uderns",
    "sg:orig_category":"Tabaktrafiken",
    "sg:phone":"+43 4352 8862575",
    "sg:postcode":"6271",
    "sg:province":"Tirol",
    "wof:name":"Hell Hans",
    "wof:placetype":"venue"
},
  "geometry": {"coordinates":[11.8642072678,47.3266906738],"type":"Point"}
}