{
  "type": "Feature",
  "properties": {
    "addr:full":"Wolfersberg Pramet Ober\u00f6sterreich 4925",
    "addr:postcode":"4925",
    "addr:street":"Oberoesterreich",
    "iso:country":"AT",
    "sg:address":"Wolfersberg",
    "sg:city":"Pramet",
    "sg:orig_category":"Bauunternehmen",
    "sg:phone":"+43 7754 8177",
    "sg:postcode":"4925",
    "sg:province":"Ober\u00f6sterreich",
    "wof:name":"Mayr Bau GmbH & Co KG",
    "wof:placetype":"venue"
},
  "geometry": {"coordinates":[13.4614372253,48.1200447083],"type":"Point"}
}