{
  "type": "Feature",
  "properties": {
    "iso:country":"AT",
    "sg:address":"Thayastr 3a",
    "sg:city":"Waidhofen an der Thaya",
    "sg:orig_category":"Politische Parteien",
    "sg:phone":"+43 4328 42521310",
    "sg:postcode":"3830",
    "sg:province":"Nieder\u00f6sterreich",
    "wof:name":"Sozialdemokratische Partei \u00f6sterreichs",
    "wof:placetype":"venue"
},
  "geometry": {"coordinates":[15.2817554474,48.8158187866],"type":"Point"}
}