{
  "type": "Feature",
  "properties": {
    "addr:full":"Pramwald 8 Haag am Hausruck Ober\u00f6sterreich 4680",
    "addr:housenumber":"8",
    "addr:postcode":"4680",
    "addr:street":"Pramwald",
    "iso:country":"AT",
    "sg:address":"Pramwald 8",
    "sg:city":"Haag am Hausruck",
    "sg:classifiers":[
        {
            "category":"Shopping Center",
            "type":"Public Place"
        }
    ],
    "sg:phone":"+43 7732 4241",
    "sg:postcode":"4680",
    "sg:province":"Ober\u00f6sterreich",
    "sg:tags":[
        "aluminium",
        "section"
    ],
    "sg:website":"abs-austria.com",
    "wof:name":"Brandschutz Systeme Ges.m.b.H.",
    "wof:placetype":"venue"
},
  "geometry": {"coordinates":[13.636885643,48.2029190063],"type":"Point"}
}