{
  "type": "Feature",
  "properties": {
    "addr:full":"Hauptstr 46 Randegg Nieder\u00f6sterreich 3263",
    "addr:housenumber":"46",
    "addr:postcode":"3263",
    "addr:street":"Hauptstr",
    "iso:country":"AT",
    "sg:address":"Hauptstr 46",
    "sg:city":"Randegg",
    "sg:orig_category":"Autoreparatur",
    "sg:phone":"+43 7487 62230",
    "sg:postcode":"3263",
    "sg:province":"Nieder\u00f6sterreich",
    "wof:name":"Br\u00fcder Pruckner GesmbH",
    "wof:placetype":"venue"
},
  "geometry": {"coordinates":[14.9729251862,48.0112915039],"type":"Point"}
}