{
  "type": "Feature",
  "properties": {
    "iso:country":"AT",
    "sg:address":"Wilhelm Kre\u00df-Str 10",
    "sg:city":"Salzburg",
    "sg:classifiers":[
        {
            "category":"Restaurant",
            "type":"Food & Drink"
        }
    ],
    "sg:phone":"+43 662 434272",
    "sg:postcode":"5020",
    "sg:province":"Salzburg",
    "wof:name":"Thaler Friedrich",
    "wof:placetype":"venue"
},
  "geometry": {"coordinates":[13.0002069473,47.8075256348],"type":"Point"}
}