{
  "type": "Feature",
  "properties": {
    "iso:country":"AT",
    "sg:address":"Spie\u00dfhammerg 1",
    "sg:city":"Wien",
    "sg:orig_category":"Beleuchtungsanlagen",
    "sg:phone":"+43 1 81359900",
    "sg:postcode":"1120",
    "sg:province":"Wien",
    "wof:name":"Leman Elektroanlagen Vertriebs- und Service GesmbH",
    "wof:placetype":"venue"
},
  "geometry": {"coordinates":[16.3290939331,48.1824874878],"type":"Point"}
}