{
  "type": "Feature",
  "properties": {
    "iso:country":"AT",
    "sg:address":"Badstr 5",
    "sg:city":"Bad Schallerbach",
    "sg:classifiers":[
        {
            "category":"Utilities",
            "subcategory":"Refuse",
            "type":"Services"
        }
    ],
    "sg:phone":"+43 4372 4942824",
    "sg:postcode":"4701",
    "sg:province":"Ober\u00f6sterreich",
    "sg:tags":[
        "catering"
    ],
    "wof:name":"Fleischerei Strasser Franz",
    "wof:placetype":"venue"
},
  "geometry": {"coordinates":[13.9202814102,48.2306175232],"type":"Point"}
}