{
  "type": "Feature",
  "properties": {
    "addr:full":"Schwechatstrasse 49 Traiskirchen Nieder\u00f6sterreich 2514",
    "addr:housenumber":"49",
    "addr:postcode":"2514",
    "addr:street":"Schwechatstrasse;Niederoesterreich",
    "iso:country":"AT",
    "sg:address":"Schwechatstrasse 49",
    "sg:city":"Traiskirchen",
    "sg:classifiers":[
        {
            "category":"Taxi",
            "type":"Transportation"
        }
    ],
    "sg:phone":"+43 1 5874738",
    "sg:postcode":"2514",
    "sg:province":"Nieder\u00f6sterreich",
    "sg:tags":[
        "furniture"
    ],
    "wof:name":"Peter K\u00f6stinger Trans-Service",
    "wof:placetype":"venue"
},
  "geometry": {"coordinates":[16.2948532104,48.0064926147],"type":"Point"}
}