{
  "type": "Feature",
  "properties": {
    "addr:full":"Eugen-M\u00fcller-Strasse 5 Salzburg Salzburg 5020",
    "addr:housenumber":"5",
    "addr:postcode":"5020",
    "addr:street":"Eugen-Mueller-Strasse;Salzburg",
    "iso:country":"AT",
    "sg:address":"Eugen-M\u00fcller-Strasse 5",
    "sg:city":"Salzburg",
    "sg:classifiers":[
        {
            "category":"Transit Center",
            "subcategory":"Freight",
            "type":"Transportation"
        }
    ],
    "sg:phone":"+43 662 4375160",
    "sg:postcode":"5020",
    "sg:province":"Salzburg",
    "sg:tags":[
        "forwarding",
        "agency"
    ],
    "sg:website":"fernfracht.at",
    "wof:name":"Fernfracht Gimmelsberger Internationale Speditions- und Transportges.m.b.H. & Co. KG",
    "wof:placetype":"venue"
},
  "geometry": {"coordinates":[13.0433769226,47.8006744385],"type":"Point"}
}