{
  "type": "Feature",
  "properties": {
    "addr:full":"Pfarrg 31 Imst Tirol 6460",
    "addr:housenumber":"31",
    "addr:postcode":"6460",
    "addr:street":"Pfarrg;Tirol",
    "iso:country":"AT",
    "sg:address":"Pfarrg 31",
    "sg:city":"Imst",
    "sg:orig_category":"Friseure U Frisiersalons",
    "sg:phone":"+43 4354 1266693",
    "sg:postcode":"6460",
    "sg:province":"Tirol",
    "wof:name":"Frisiersalon Krieglsteiner Irene",
    "wof:placetype":"venue"
},
  "geometry": {"coordinates":[10.7402658463,47.244884491],"type":"Point"}
}