{
  "type": "Feature",
  "properties": {
    "addr:full":"Hauptstr 114 Breitenfurt Nieder\u00f6sterreich 2384",
    "addr:housenumber":"114",
    "addr:postcode":"2384",
    "addr:street":"Hauptstr",
    "iso:country":"AT",
    "sg:address":"Hauptstr 114",
    "sg:city":"Breitenfurt",
    "sg:orig_category":"Tabaktrafiken",
    "sg:phone":"+43 2239 2103",
    "sg:postcode":"2384",
    "sg:province":"Nieder\u00f6sterreich",
    "wof:name":"R\u00fcckesh\u00e4user Anni",
    "wof:placetype":"venue"
},
  "geometry": {"coordinates":[16.2083091736,48.1380805969],"type":"Point"}
}