{
  "type": "Feature",
  "properties": {
    "addr:full":"Hintermarkt 4 Matrei in Osttirol Tirol 9971",
    "addr:housenumber":"4",
    "addr:postcode":"9971",
    "addr:street":"Hintermarkt;Tirol",
    "iso:country":"AT",
    "sg:address":"Hintermarkt 4",
    "sg:city":"Matrei in Osttirol",
    "sg:classifiers":[
        {
            "category":"Travel",
            "subcategory":"Hotels & Motels",
            "type":"Entertainment"
        }
    ],
    "sg:phone":"+43 4875 6587",
    "sg:postcode":"9971",
    "sg:province":"Tirol",
    "wof:name":"Hotel Hinteregger",
    "wof:placetype":"venue"
},
  "geometry": {"coordinates":[12.5383720398,47.0014953613],"type":"Point"}
}