{
  "type": "Feature",
  "properties": {
    "addr:full":"Guglg 8/3/9/40 Wien Wien 1110",
    "addr:housenumber":"8 / 3 / 9 / 40",
    "addr:postcode":"1110",
    "addr:street":"Guglg",
    "iso:country":"AT",
    "sg:address":"Guglg 8/3/9/40",
    "sg:city":"Wien",
    "sg:orig_category":"Werbegrafik- U Grafik-Design",
    "sg:phone":"+43 1 9719968",
    "sg:postcode":"1110",
    "sg:province":"Wien",
    "wof:name":"kreisrot corporate design schiefer widmer oeg",
    "wof:placetype":"venue"
},
  "geometry": {"coordinates":[16.4197444916,48.1709709167],"type":"Point"}
}