{
  "type": "Feature",
  "properties": {
    "iso:country":"AT",
    "sg:address":"Aigner Str 21",
    "sg:city":"Salzburg",
    "sg:orig_category":"\u00c3\u201erzte / F Allgemeinmedizin",
    "sg:phone":"+43 662 645968",
    "sg:postcode":"5020",
    "sg:province":"Salzburg",
    "wof:name":"Seitelberger Gerhard Dr",
    "wof:placetype":"venue"
},
  "geometry": {"coordinates":[13.0703449249,47.7954483032],"type":"Point"}
}