{
  "type": "Feature",
  "properties": {
    "addr:full":"Habichtweg 5 Bad Kleinkirchheim K\u00e4rnten 9546",
    "addr:housenumber":"5",
    "addr:postcode":"9546",
    "addr:street":"Habichtweg",
    "iso:country":"AT",
    "sg:address":"Habichtweg 5",
    "sg:city":"Bad Kleinkirchheim",
    "sg:orig_category":"Appartements / Ferienwohnungen",
    "sg:phone":"+43 4367 65466016",
    "sg:postcode":"9546",
    "sg:province":"K\u00e4rnten",
    "wof:name":"Berghaus Nockalm-Sesselliftn\u00e4he-Panoramablick",
    "wof:placetype":"venue"
},
  "geometry": {"coordinates":[13.7708120346,46.8199768066],"type":"Point"}
}