{
  "type": "Feature",
  "properties": {
    "addr:full":"Scharnsteiner Str 29 Gmunden Ober\u00f6sterreich 4810",
    "addr:postcode":"4810",
    "addr:street":"Str 29",
    "iso:country":"AT",
    "sg:address":"Scharnsteiner Str 29",
    "sg:city":"Gmunden",
    "sg:orig_category":"Autoreparatur",
    "sg:phone":"+43 761263310",
    "sg:postcode":"4810",
    "sg:province":"Ober\u00f6sterreich",
    "wof:name":"Skoda Windischbauer",
    "wof:placetype":"venue"
},
  "geometry": {"coordinates":[13.8191995621,47.9258575439],"type":"Point"}
}