{
  "type": "Feature",
  "properties": {
    "addr:full":"Triester Strasse 66 Wien Wien 1100",
    "addr:housenumber":"66",
    "addr:postcode":"1100",
    "addr:street":"Triester Strasse",
    "iso:country":"AT",
    "sg:address":"Triester Strasse 66",
    "sg:city":"Wien",
    "sg:classifiers":[
        {
            "category":"Communications",
            "subcategory":"Film & Video Production",
            "type":"Services"
        }
    ],
    "sg:phone":"+43 1 605431700",
    "sg:postcode":"1100",
    "sg:province":"Wien",
    "sg:tags":[
        "application",
        "software",
        "cad/cam/cae"
    ],
    "sg:website":"atosorigin.com",
    "wof:name":"Atos Origin Information Technology GmbH",
    "wof:placetype":"venue"
},
  "geometry": {"coordinates":[16.3477363586,48.1669464111],"type":"Point"}
}