{
  "type": "Feature",
  "properties": {
    "addr:full":"Hauptstr 45 Sattledt Ober\u00f6sterreich 4642",
    "addr:housenumber":"45",
    "addr:postcode":"4642",
    "addr:street":"Hauptstr",
    "iso:country":"AT",
    "sg:address":"Hauptstr 45",
    "sg:city":"Sattledt",
    "sg:orig_category":"Molkereien U Molkereiprodukte",
    "sg:phone":"+43 4372 448916",
    "sg:postcode":"4642",
    "sg:province":"Ober\u00f6sterreich",
    "wof:name":"Zentralmolkerei Furtmayr GesmbH & Co KG",
    "wof:placetype":"venue"
},
  "geometry": {"coordinates":[14.0614070892,48.0730934143],"type":"Point"}
}