{
  "type": "Feature",
  "properties": {
    "addr:full":"Steinbergstr 47 Wetzelsdorf Steiermark 8052",
    "addr:housenumber":"47",
    "addr:postcode":"8052",
    "addr:street":"Steinbergstr",
    "iso:country":"AT",
    "sg:address":"Steinbergstr 47",
    "sg:city":"Wetzelsdorf",
    "sg:orig_category":"Friseure U Frisiersalons",
    "sg:phone":"+43 316 381170",
    "sg:postcode":"8052",
    "sg:province":"Steiermark",
    "wof:name":"Frisiersalon und Fingernagelstudio Ilse",
    "wof:placetype":"venue"
},
  "geometry": {"coordinates":[15.3705272675,47.0531425476],"type":"Point"}
}