{
  "type": "Feature",
  "properties": {
    "addr:full":"Dueler Str 65 Velden am W\u00f6rther See K\u00e4rnten 9220",
    "addr:housenumber":"65",
    "addr:postcode":"9220",
    "addr:street":"Dueler Str;Kaernten",
    "iso:country":"AT",
    "sg:address":"Dueler Str 65",
    "sg:city":"Velden am W\u00f6rther See",
    "sg:orig_category":"Sportschulen",
    "sg:phone":"+43 4342 743688",
    "sg:postcode":"9220",
    "sg:province":"K\u00e4rnten",
    "wof:name":"Kajak-Center u Schule Faak-Ossiach",
    "wof:placetype":"venue"
},
  "geometry": {"coordinates":[14.0429868698,46.6151618958],"type":"Point"}
}