{
  "type": "Feature",
  "properties": {
    "addr:full":"Wachaustrasse 12 Ottenschlag Nieder\u00f6sterreich 3631",
    "addr:housenumber":"12",
    "addr:postcode":"3631",
    "addr:street":"Wachaustrasse",
    "iso:country":"AT",
    "sg:address":"Wachaustrasse 12",
    "sg:city":"Ottenschlag",
    "sg:classifiers":[
        {
            "category":"Home & Garden",
            "subcategory":"Household Appliances",
            "type":"Retail Goods"
        }
    ],
    "sg:phone":"+43 2872 72390",
    "sg:postcode":"3631",
    "sg:province":"Nieder\u00f6sterreich",
    "sg:tags":[
        "electric"
    ],
    "wof:name":"Peter Moser GmbH",
    "wof:placetype":"venue"
},
  "geometry": {"coordinates":[15.2233247757,48.4214668274],"type":"Point"}
}