{
  "type": "Feature",
  "properties": {
    "iso:country":"AT",
    "sg:address":"Speckbacherstr 31-33",
    "sg:city":"Innsbruck",
    "sg:orig_category":"Lebensmittel / Einzelhandel",
    "sg:phone":"+43 512 572886",
    "sg:postcode":"6020",
    "sg:province":"Tirol",
    "wof:name":"SPAR \u00f6sterreichische Warenhandels-AG",
    "wof:placetype":"venue"
},
  "geometry": {"coordinates":[11.390124321,47.2592391968],"type":"Point"}
}