{
  "type": "Feature",
  "properties": {
    "addr:full":"Struberg 64 Salzburg Salzburg 5020",
    "addr:housenumber":"64",
    "addr:postcode":"5020",
    "addr:street":"Struberg;Salzburg",
    "iso:country":"AT",
    "sg:address":"Struberg 64",
    "sg:city":"Salzburg",
    "sg:orig_category":"Transportunternehmen",
    "sg:phone":"+43 662 432416",
    "sg:postcode":"5020",
    "sg:province":"Salzburg",
    "wof:name":"Greiner Ferdinand",
    "wof:placetype":"venue"
},
  "geometry": {"coordinates":[13.0271120071,47.8089294434],"type":"Point"}
}