{
  "type": "Feature",
  "properties": {
    "addr:full":"Anningerstr 23 Guntramsdorf Nieder\u00f6sterreich 2353",
    "addr:housenumber":"23",
    "addr:postcode":"2353",
    "addr:street":"Anningerstr",
    "iso:country":"AT",
    "sg:address":"Anningerstr 23",
    "sg:city":"Guntramsdorf",
    "sg:classifiers":[
        {
            "category":"Internet Cafe",
            "subcategory":"None",
            "type":"Food & Drink"
        }
    ],
    "sg:phone":"+43 2236 44699",
    "sg:postcode":"2353",
    "sg:province":"Nieder\u00f6sterreich",
    "wof:name":"IWM Development Austria",
    "wof:placetype":"venue"
},
  "geometry": {"coordinates":[16.304605484,48.04945755],"type":"Point"}
}