{
  "type": "Feature",
  "properties": {
    "addr:full":"Bundesstr 72 Lauterach Vorarlberg 6923",
    "addr:housenumber":"72",
    "addr:postcode":"6923",
    "addr:street":"Bundesstr",
    "iso:country":"AT",
    "sg:address":"Bundesstr 72",
    "sg:city":"Lauterach",
    "sg:orig_category":"Tischlereien",
    "sg:phone":"+43 4355 74713700",
    "sg:postcode":"6923",
    "sg:province":"Vorarlberg",
    "wof:name":"Tischlerei Matt Peter",
    "wof:placetype":"venue"
},
  "geometry": {"coordinates":[9.7305736542,47.4740982056],"type":"Point"}
}