{
  "type": "Feature",
  "properties": {
    "addr:full":"Kirchdorf 19 Doren Vorarlberg 6933",
    "addr:housenumber":"19",
    "addr:postcode":"6933",
    "addr:street":"Kirchdorf",
    "iso:country":"AT",
    "sg:address":"Kirchdorf 19",
    "sg:city":"Doren",
    "sg:orig_category":"Maschinenhandel",
    "sg:phone":"+43 5516 29038",
    "sg:postcode":"6933",
    "sg:province":"Vorarlberg",
    "wof:name":"Barta Wolfgang Maschinen- und Fertigungstechnik",
    "wof:placetype":"venue"
},
  "geometry": {"coordinates":[9.8796796799,47.4928436279],"type":"Point"}
}