{
  "type": "Feature",
  "properties": {
    "iso:country":"AT",
    "sg:address":"Landstr 52",
    "sg:city":"Zwettl",
    "sg:orig_category":"Steuerberatung",
    "sg:phone":"+43 2822 528040",
    "sg:postcode":"3910",
    "sg:province":"Nieder\u00f6sterreich",
    "wof:name":"TPA Treuhand Partner Austria Wirtschaftstreuhand und Steuerberatung GmbH",
    "wof:placetype":"venue"
},
  "geometry": {"coordinates":[15.1657934189,48.6062698364],"type":"Point"}
}