{
  "type": "Feature",
  "properties": {
    "addr:full":"Hartmannweg 4 Hallein Salzburg 5400",
    "addr:housenumber":"4",
    "addr:postcode":"5400",
    "addr:street":"Hartmannweg;Salzburg",
    "iso:country":"AT",
    "sg:address":"Hartmannweg 4",
    "sg:city":"Hallein",
    "sg:orig_category":"Non-Classified Establishments",
    "sg:phone":"+43 6245 86829",
    "sg:postcode":"5400",
    "sg:province":"Salzburg",
    "wof:name":"Bundesheer HLSZ Heeresleitungssportzentrum 8",
    "wof:placetype":"venue"
},
  "geometry": {"coordinates":[13.0701093674,47.7219009399],"type":"Point"}
}