{
  "type": "Feature",
  "properties": {
    "addr:full":"Wilhelm Jentsch Str. 1-5 Peggau Steiermark 8120",
    "addr:housenumber":"1-5",
    "addr:postcode":"8120",
    "addr:street":"Str.",
    "iso:country":"AT",
    "sg:address":"Wilhelm Jentsch Str. 1-5",
    "sg:city":"Peggau",
    "sg:classifiers":[
        {
            "category":"Manufacturing",
            "subcategory":"Tools & Machinery",
            "type":"Manufacturing & Wholesale Goods"
        }
    ],
    "sg:phone":"+43 4331 272191",
    "sg:postcode":"8120",
    "sg:province":"Steiermark",
    "sg:tags":[
        "environment",
        "equipment",
        "-"
    ],
    "wof:name":"ZUSER UMWELTSERVICE GMBH",
    "wof:placetype":"venue"
},
  "geometry": {"coordinates":[15.3394069672,47.2092971802],"type":"Point"}
}