{
  "type": "Feature",
  "properties": {
    "iso:country":"AT",
    "sg:address":"Schlagerg 7",
    "sg:city":"Wien",
    "sg:orig_category":"Tonstudios",
    "sg:phone":"+43 4317 994447",
    "sg:postcode":"1090",
    "sg:province":"Wien",
    "wof:name":"UnartProduktion Bild- u Tontr\u00e4gerproduktion Gauls Kinderlieder",
    "wof:placetype":"venue"
},
  "geometry": {"coordinates":[16.3500175476,48.2236213684],"type":"Point"}
}