{
  "type": "Feature",
  "properties": {
    "addr:full":"Beethovenallee 3 Velden am W\u00f6rther See K\u00e4rnten 9220",
    "addr:housenumber":"3",
    "addr:postcode":"9220",
    "addr:street":"Beethovenallee;Kaernten",
    "iso:country":"AT",
    "sg:address":"Beethovenallee 3",
    "sg:city":"Velden am W\u00f6rther See",
    "sg:orig_category":"Reisen, Sonstige Reisethemen",
    "sg:postcode":"9220",
    "sg:province":"K\u00e4rnten",
    "sg:website":"http://members.aon.at/~holidayb/holiday/",
    "wof:name":"Holiday - Gesundheits- u. Sch\u00f6nheitsfarm",
    "wof:placetype":"venue"
},
  "geometry": {"coordinates":[14.0577516556,46.6189994812],"type":"Point"}
}