{
  "type": "Feature",
  "properties": {
    "iso:country":"AT",
    "sg:address":"Zimmerplatzweg 8",
    "sg:city":"Feldkirchen",
    "sg:classifiers":[
        {
            "category":"Transit Center",
            "subcategory":"Freight",
            "type":"Transportation"
        }
    ],
    "sg:phone":"+43 4331 6293036",
    "sg:postcode":"8073",
    "sg:province":"Steiermark",
    "sg:tags":[
        "import",
        "gro\u00c3\u0178handel",
        "u",
        "tee",
        "/"
    ],
    "wof:name":"Tee-Paradies Nabil El Sharif",
    "wof:placetype":"venue"
},
  "geometry": {"coordinates":[15.4468278885,47.0046882629],"type":"Point"}
}