{
  "type": "Feature",
  "properties": {
    "addr:full":"Hofenederg 4 Wien Wien 1020",
    "addr:housenumber":"4",
    "addr:postcode":"1020",
    "addr:street":"Hofenederg",
    "iso:country":"AT",
    "sg:address":"Hofenederg 4",
    "sg:city":"Wien",
    "sg:classifiers":[
        {
            "category":"Travel",
            "subcategory":"Hotels & Motels",
            "type":"Entertainment"
        }
    ],
    "sg:phone":"+43 4312 1667880",
    "sg:postcode":"1020",
    "sg:province":"Wien",
    "wof:name":"Adlon Hotel Restaurationsbetriebe GesmbH",
    "wof:placetype":"venue"
},
  "geometry": {"coordinates":[16.3903980255,48.2152328491],"type":"Point"}
}