{
  "type": "Feature",
  "properties": {
    "iso:country":"AT",
    "sg:address":"Erzbischofg 22",
    "sg:city":"Wien",
    "sg:orig_category":"Architekten",
    "sg:phone":"+43 1 8776787",
    "sg:postcode":"1130",
    "sg:province":"Wien",
    "wof:name":"Erblich Peter Arch Dipl-Ing",
    "wof:placetype":"venue"
},
  "geometry": {"coordinates":[16.2617263794,48.1916160583],"type":"Point"}
}