{
  "type": "Feature",
  "properties": {
    "iso:country":"AT",
    "sg:address":"Edisonstr 2",
    "sg:city":"Wels",
    "sg:orig_category":"Personalbereitstellung",
    "sg:phone":"+43 7242 210308",
    "sg:postcode":"4600",
    "sg:province":"Ober\u00f6sterreich",
    "wof:name":"PE-LE Anlagenbau Montage und Personalleasing GmbH",
    "wof:placetype":"venue"
},
  "geometry": {"coordinates":[14.0090208054,48.1523284912],"type":"Point"}
}