{
  "type": "Feature",
  "properties": {
    "addr:full":"Schulstr 2 Pinkafeld Burgenland 7423",
    "addr:housenumber":"2",
    "addr:postcode":"7423",
    "addr:street":"Schulstr",
    "iso:country":"AT",
    "sg:address":"Schulstr 2",
    "sg:city":"Pinkafeld",
    "sg:orig_category":"Musikunterricht",
    "sg:phone":"+43 3357 42607",
    "sg:postcode":"7423",
    "sg:province":"Burgenland",
    "wof:name":"Musikschule Pinkafeld",
    "wof:placetype":"venue"
},
  "geometry": {"coordinates":[16.1263332367,47.3676261902],"type":"Point"}
}