{
  "type": "Feature",
  "properties": {
    "iso:country":"AT",
    "sg:address":"Schwamingstr 3",
    "sg:city":"Neuzeug",
    "sg:orig_category":"Hallenbau U -Sanierung",
    "sg:phone":"+43 7259 5191",
    "sg:postcode":"4523",
    "sg:province":"Ober\u00f6sterreich",
    "wof:name":"Concreta HandelsgesmbH",
    "wof:placetype":"venue"
},
  "geometry": {"coordinates":[14.3221750259,48.0261383057],"type":"Point"}
}