{
  "type": "Feature",
  "properties": {
    "addr:full":"Stadtpl 35 Laa an der Thaya Nieder\u00f6sterreich 2136",
    "addr:housenumber":"35",
    "addr:postcode":"2136",
    "addr:street":"Stadtpl",
    "iso:country":"AT",
    "sg:address":"Stadtpl 35",
    "sg:city":"Laa an der Thaya",
    "sg:orig_category":"Maler, Anstreicher U Lackierer",
    "sg:phone":"+43 4325 2284037",
    "sg:postcode":"2136",
    "sg:province":"Nieder\u00f6sterreich",
    "wof:name":"Fenz GmbH",
    "wof:placetype":"venue"
},
  "geometry": {"coordinates":[16.3854408264,48.7216758728],"type":"Point"}
}