{
  "type": "Feature",
  "properties": {
    "iso:country":"AT",
    "sg:address":"W\u00e4lderstrasse 48",
    "sg:city":"Lauterach",
    "sg:classifiers":[
        {
            "category":"Wholesale",
            "subcategory":"Vending Machines",
            "type":"Manufacturing & Wholesale Goods"
        }
    ],
    "sg:phone":"+43 5574 72170",
    "sg:postcode":"6923",
    "sg:province":"Vorarlberg",
    "sg:tags":[
        "filling",
        "aerosol",
        "sealing"
    ],
    "wof:name":"AERCOS Aerosole & Cosmetic GmbH",
    "wof:placetype":"venue"
},
  "geometry": {"coordinates":[9.7377920151,47.4705619812],"type":"Point"}
}