{
  "type": "Feature",
  "properties": {
    "addr:full":"Grillparzerstr 1 Bad Schallerbach Ober\u00f6sterreich 4701",
    "addr:housenumber":"1",
    "addr:postcode":"4701",
    "addr:street":"Grillparzerstr",
    "iso:country":"AT",
    "sg:address":"Grillparzerstr 1",
    "sg:city":"Bad Schallerbach",
    "sg:orig_category":"Pensionen / Privatzimmer",
    "sg:phone":"+43 7249 48227",
    "sg:postcode":"4701",
    "sg:province":"Ober\u00f6sterreich",
    "wof:name":"Mittermayr Heinrich",
    "wof:placetype":"venue"
},
  "geometry": {"coordinates":[13.9172849655,48.2291069031],"type":"Point"}
}