{
  "type": "Feature",
  "properties": {
    "iso:country":"AT",
    "sg:address":"Stegg 15",
    "sg:city":"Wieselburg an der Erlauf",
    "sg:orig_category":"Datenverarbeitung",
    "sg:phone":"+43 4374 1658833",
    "sg:postcode":"3250",
    "sg:province":"Nieder\u00f6sterreich",
    "wof:name":"LGV-Datenverarbeitung Gerlinde Binderlehner",
    "wof:placetype":"venue"
},
  "geometry": {"coordinates":[15.1437187195,48.1299552917],"type":"Point"}
}