{
  "type": "Feature",
  "properties": {
    "iso:country":"AT",
    "sg:address":"Sonnenh\u00f6he 275",
    "sg:city":"Raab",
    "sg:orig_category":"Baumschulen",
    "sg:phone":"+43 7762 2226",
    "sg:postcode":"4760",
    "sg:province":"Ober\u00f6sterreich",
    "wof:name":"Rosenschule Hauer",
    "wof:placetype":"venue"
},
  "geometry": {"coordinates":[13.6459569931,48.3524436951],"type":"Point"}
}