{
  "type": "Feature",
  "properties": {
    "iso:country":"AT",
    "sg:address":"Igler Strasse 16",
    "sg:city":"Innsbruck-Igls",
    "sg:classifiers":[
        {
            "category":"Home & Garden",
            "subcategory":"Furniture",
            "type":"Retail Goods"
        }
    ],
    "sg:phone":"+43 512 370090",
    "sg:postcode":"6080",
    "sg:province":"Tirol",
    "sg:tags":[
        "bathroom"
    ],
    "sg:website":"hero-tischlerei.at",
    "wof:name":"Hero Tischlerei Hermann Rofner",
    "wof:placetype":"venue"
},
  "geometry": {"coordinates":[11.4012298584,47.2370223999],"type":"Point"}
}