{
  "type": "Feature",
  "properties": {
    "addr:full":"H v Hofmannsthal-Str 3 St. P\u00f6lten Nieder\u00f6sterreich 3100",
    "addr:housenumber":"3",
    "addr:postcode":"3100",
    "addr:street":"H;Hofmannsthal-Str",
    "iso:country":"AT",
    "sg:address":"H v Hofmannsthal-Str 3",
    "sg:city":"St. P\u00f6lten",
    "sg:orig_category":"Steuerberatung",
    "sg:phone":"+43 2742 882310",
    "sg:postcode":"3100",
    "sg:province":"Nieder\u00f6sterreich",
    "wof:name":"Mandat Consult Wirtschaftstreuhand GesmbH",
    "wof:placetype":"venue"
},
  "geometry": {"coordinates":[15.6240940094,48.2076377869],"type":"Point"}
}