{
  "type": "Feature",
  "properties": {
    "iso:country":"AT",
    "sg:address":"Auf der Schmelz 62",
    "sg:city":"Pitten",
    "sg:orig_category":"Musikunterricht",
    "sg:phone":"+43 2627 85193",
    "sg:postcode":"2823",
    "sg:province":"Nieder\u00f6sterreich",
    "wof:name":"Musikschule",
    "wof:placetype":"venue"
},
  "geometry": {"coordinates":[16.18658638,47.7162742615],"type":"Point"}
}