{
  "type": "Feature",
  "properties": {
    "iso:country":"AT",
    "sg:address":"Predlitz 15",
    "sg:city":"Predlitz",
    "sg:orig_category":"Pensionen / Privatzimmer",
    "sg:phone":"+43 4335 348266",
    "sg:postcode":"8863",
    "sg:province":"Steiermark",
    "wof:name":"G\u00f6ldner Sepp",
    "wof:placetype":"venue"
},
  "geometry": {"coordinates":[13.9018859863,47.0446052551],"type":"Point"}
}