{
  "type": "Feature",
  "properties": {
    "addr:full":"Wolfholzg 23 Brunn am Gebirge Nieder\u00f6sterreich 2345",
    "addr:housenumber":"23",
    "addr:postcode":"2345",
    "addr:street":"Wolfholzg",
    "iso:country":"AT",
    "sg:address":"Wolfholzg 23",
    "sg:city":"Brunn am Gebirge",
    "sg:orig_category":"Solartechnik",
    "sg:phone":"+43 4322 36377180",
    "sg:postcode":"2345",
    "sg:province":"Nieder\u00f6sterreich",
    "wof:name":"Hinteregger-Estec Ges f Energiespartechnologie GmbH",
    "wof:placetype":"venue"
},
  "geometry": {"coordinates":[16.2839355469,48.107170105],"type":"Point"}
}