{
  "type": "Feature",
  "properties": {
    "addr:full":"Quettensberg 54 Uttendorf Salzburg 5723",
    "addr:housenumber":"54",
    "addr:postcode":"5723",
    "addr:street":"Quettensberg;Salzburg",
    "iso:country":"AT",
    "sg:address":"Quettensberg 54",
    "sg:city":"Uttendorf",
    "sg:classifiers":[
        {
            "category":"Park",
            "subcategory":"Provincial",
            "type":"Public Place"
        }
    ],
    "sg:phone":"+43 4365 6384190",
    "sg:postcode":"5723",
    "sg:province":"Salzburg",
    "sg:tags":[
        "u",
        "ski-",
        "snowboardschulen"
    ],
    "wof:name":"Lederer Anton",
    "wof:placetype":"venue"
},
  "geometry": {"coordinates":[12.6055002213,47.2153511047],"type":"Point"}
}