{
  "type": "Feature",
  "properties": {
    "addr:full":"Laubichl 141 Mayrhofen Tirol 6290",
    "addr:housenumber":"141",
    "addr:postcode":"6290",
    "addr:street":"Laubichl;Tirol",
    "iso:country":"AT",
    "sg:address":"Laubichl 141",
    "sg:city":"Mayrhofen",
    "sg:classifiers":[
        {
            "category":"Travel",
            "subcategory":"Hotels & Motels",
            "type":"Entertainment"
        }
    ],
    "sg:phone":"+43 5285 629320",
    "sg:postcode":"6290",
    "sg:province":"Tirol",
    "wof:name":"Hotel garni Almhof",
    "wof:placetype":"venue"
},
  "geometry": {"coordinates":[11.8669586182,47.1720924377],"type":"Point"}
}