{
  "type": "Feature",
  "properties": {
    "addr:full":"G\u00f6tzstr 4a Bad Ischl Ober\u00f6sterreich 4820",
    "addr:housenumber":"4a",
    "addr:postcode":"4820",
    "addr:street":"Goetzstr",
    "iso:country":"AT",
    "sg:address":"G\u00f6tzstr 4a",
    "sg:city":"Bad Ischl",
    "sg:orig_category":"Lebensmittel / Einzelhandel",
    "sg:phone":"+43 6132 25677",
    "sg:postcode":"4820",
    "sg:province":"Ober\u00f6sterreich",
    "wof:name":"Zielpunkt Warenhandel GmbH & Co KG",
    "wof:placetype":"venue"
},
  "geometry": {"coordinates":[13.6257123947,47.711971283],"type":"Point"}
}