{
  "type": "Feature",
  "properties": {
    "addr:full":"Kapuzinerberg 8 Ried im Innkreis Ober\u00f6sterreich 4910",
    "addr:housenumber":"8",
    "addr:postcode":"4910",
    "addr:street":"Kapuzinerberg",
    "iso:country":"AT",
    "sg:address":"Kapuzinerberg 8",
    "sg:city":"Ried im Innkreis",
    "sg:orig_category":"Orientteppiche",
    "sg:phone":"+43 7752 81862",
    "sg:postcode":"4910",
    "sg:province":"Ober\u00f6sterreich",
    "wof:name":"Schmid Stefan",
    "wof:placetype":"venue"
},
  "geometry": {"coordinates":[13.4918308258,48.211555481],"type":"Point"}
}