{
  "type": "Feature",
  "properties": {
    "addr:full":"Haidhofstr 89 Baden Nieder\u00f6sterreich 2500",
    "addr:housenumber":"89",
    "addr:postcode":"2500",
    "addr:street":"Haidhofstr;Niederoesterreich",
    "iso:country":"AT",
    "sg:address":"Haidhofstr 89",
    "sg:city":"Baden",
    "sg:orig_category":"Metallbau",
    "sg:phone":"+43 2252 88635",
    "sg:postcode":"2500",
    "sg:province":"Nieder\u00f6sterreich",
    "wof:name":"Gemeinb\u00f6ck Ingrid",
    "wof:placetype":"venue"
},
  "geometry": {"coordinates":[16.2605228424,47.986492157],"type":"Point"}
}