{
  "type": "Feature",
  "properties": {
    "addr:full":"Pfalzg 58/40 Wien Wien 1220",
    "addr:housenumber":"58 / 40",
    "addr:postcode":"1220",
    "addr:street":"Pfalzg",
    "iso:country":"AT",
    "sg:address":"Pfalzg 58/40",
    "sg:city":"Wien",
    "sg:orig_category":"Mineralien",
    "sg:phone":"+43 664 4633645",
    "sg:postcode":"1220",
    "sg:province":"Wien",
    "wof:name":"Raza Jaffry",
    "wof:placetype":"venue"
},
  "geometry": {"coordinates":[16.499294281,48.2390937805],"type":"Point"}
}