{
  "type": "Feature",
  "properties": {
    "addr:full":"Markt 159 St. Wolfgang im Salzkammergut Ober\u00f6sterreich 5360",
    "addr:housenumber":"159",
    "addr:postcode":"5360",
    "addr:street":"Markt",
    "iso:country":"AT",
    "sg:address":"Markt 159",
    "sg:city":"St. Wolfgang im Salzkammergut",
    "sg:orig_category":"Volksschulen",
    "sg:phone":"+43 4361 382361",
    "sg:postcode":"5360",
    "sg:province":"Ober\u00f6sterreich",
    "wof:name":"Volksschule",
    "wof:placetype":"venue"
},
  "geometry": {"coordinates":[13.4474153519,47.7377281189],"type":"Point"}
}