{
  "type": "Feature",
  "properties": {
    "addr:full":"Leystr 23 Wien Wien 1200",
    "addr:housenumber":"23",
    "addr:postcode":"1200",
    "addr:street":"Leystr",
    "iso:country":"AT",
    "sg:address":"Leystr 23",
    "sg:city":"Wien",
    "sg:orig_category":"Friseure U Frisiersalons",
    "sg:phone":"+43 4313 348695",
    "sg:postcode":"1200",
    "sg:province":"Wien",
    "wof:name":"Salon Andrea Inh Andrea Vitula",
    "wof:placetype":"venue"
},
  "geometry": {"coordinates":[16.3754711151,48.2457885742],"type":"Point"}
}