{
  "type": "Feature",
  "properties": {
    "addr:full":"Schwarzenbergpl 6 Wien Wien 1030",
    "addr:housenumber":"6",
    "addr:postcode":"1030",
    "addr:street":"Schwarzenbergpl",
    "iso:country":"AT",
    "sg:address":"Schwarzenbergpl 6",
    "sg:city":"Wien",
    "sg:classifiers":[
        {
            "category":"Organizations",
            "subcategory":"Community Association",
            "type":"Services"
        }
    ],
    "sg:phone":"+43 1 71630",
    "sg:postcode":"1030",
    "sg:province":"Wien",
    "sg:tags":[
        "relation",
        "public"
    ],
    "wof:name":"MEDIAHAUS AUSTRIA SP\u00c4TH GesmH",
    "wof:placetype":"venue"
},
  "geometry": {"coordinates":[16.3769416809,48.1987724304],"type":"Point"}
}