{
  "type": "Feature",
  "properties": {
    "iso:country":"AT",
    "sg:address":"Wahringerstr. 36 ",
    "sg:city":"Linz",
    "sg:classifiers":[
        {
            "category":"Professional",
            "subcategory":"Engineering",
            "type":"Services"
        }
    ],
    "sg:phone":"+43 4370 694110",
    "sg:postcode":"4030",
    "sg:province":"Ober\u00f6sterreich",
    "sg:tags":[
        "machine",
        "-",
        "mechanical"
    ],
    "wof:name":"WFL MILLTURN TECHNOLOGIES GMBH & CO KG",
    "wof:placetype":"venue"
},
  "geometry": {"coordinates":[14.3224287033,48.2645149231],"type":"Point"}
}