{
  "type": "Feature",
  "properties": {
    "addr:full":"Schareckstr 8 Bad Gastein Salzburg 5640",
    "addr:housenumber":"8",
    "addr:postcode":"5640",
    "addr:street":"Schareckstr;Salzburg",
    "iso:country":"AT",
    "sg:address":"Schareckstr 8",
    "sg:city":"Bad Gastein",
    "sg:orig_category":"Autobusunternehmen",
    "sg:phone":"+43 6434 28230",
    "sg:postcode":"5640",
    "sg:province":"Salzburg",
    "wof:name":"Lackner Heinrich Gasteiner Verkehrsbetriebe GesmbH",
    "wof:placetype":"venue"
},
  "geometry": {"coordinates":[13.1332197189,47.1065406799],"type":"Point"}
}