{
  "type": "Feature",
  "properties": {
    "iso:country":"AT",
    "sg:address":"Kaltenmarkt 17",
    "sg:city":"Kirchham",
    "sg:orig_category":"Innenausbau",
    "sg:phone":"+43 4365 02825557",
    "sg:postcode":"4656",
    "sg:province":"Ober\u00f6sterreich",
    "wof:name":"Decken AS Alfred Scheuchl",
    "wof:placetype":"venue"
},
  "geometry": {"coordinates":[13.8845300674,47.9486656189],"type":"Point"}
}