{
  "type": "Feature",
  "properties": {
    "iso:country":"AT",
    "sg:address":"Pergerstr 11a",
    "sg:city":"Baden",
    "sg:orig_category":"Lebensmittel / Einzelhandel",
    "sg:phone":"+43 2252 48233",
    "sg:postcode":"2500",
    "sg:province":"Nieder\u00f6sterreich",
    "wof:name":"Schreyer Dorothea",
    "wof:placetype":"venue"
},
  "geometry": {"coordinates":[16.2310256958,48.0066223145],"type":"Point"}
}