{
  "type": "Feature",
  "properties": {
    "addr:full":"Schweizer Strasse 17  Altach Vorarlberg 6844",
    "addr:housenumber":"17",
    "addr:postcode":"6844",
    "addr:street":"Schweizer Strasse",
    "iso:country":"AT",
    "sg:address":"Schweizer Strasse 17 ",
    "sg:city":"Altach",
    "sg:classifiers":[
        {
            "category":"Home & Garden",
            "subcategory":"Kitchen Supply",
            "type":"Retail Goods"
        }
    ],
    "sg:phone":"+43 5576 720900",
    "sg:postcode":"6844",
    "sg:province":"Vorarlberg",
    "sg:tags":[
        "household",
        "electric",
        "cooker"
    ],
    "sg:website":"www.expert.at/scharf",
    "wof:name":"EXPERT Scharf Ges.m.b.H.",
    "wof:placetype":"venue"
},
  "geometry": {"coordinates":[9.6484012604,47.3536148071],"type":"Point"}
}