{
  "type": "Feature",
  "properties": {
    "addr:full":"Ziegelbrennerstr 26 Radstadt Salzburg 5550",
    "addr:housenumber":"26",
    "addr:postcode":"5550",
    "addr:street":"Ziegelbrennerstr;Salzburg",
    "iso:country":"AT",
    "sg:address":"Ziegelbrennerstr 26",
    "sg:city":"Radstadt",
    "sg:orig_category":"Elektroinstallationsunternehmen",
    "sg:phone":"+43 6452 5801",
    "sg:postcode":"5550",
    "sg:province":"Salzburg",
    "wof:name":"Mayer Franz",
    "wof:placetype":"venue"
},
  "geometry": {"coordinates":[13.4771490097,47.3808097839],"type":"Point"}
}