{
  "type": "Feature",
  "properties": {
    "iso:country":"AT",
    "sg:address":"Pichl 24",
    "sg:city":"Ro\u00dfleithen",
    "sg:orig_category":"Autoreparatur",
    "sg:phone":"+43 7562 53630",
    "sg:postcode":"4575",
    "sg:province":"Ober\u00f6sterreich",
    "wof:name":"Ru\u00dfner Hans",
    "wof:placetype":"venue"
},
  "geometry": {"coordinates":[14.3080148697,47.7226333618],"type":"Point"}
}