{
  "type": "Feature",
  "properties": {
    "iso:country":"AT",
    "sg:address":"Stadtpark 3",
    "sg:city":"Wilhelmsburg an der Traisen",
    "sg:orig_category":"Musikunterricht",
    "sg:phone":"+43 2746 8524",
    "sg:postcode":"3150",
    "sg:province":"Nieder\u00f6sterreich",
    "wof:name":"Musikschule",
    "wof:placetype":"venue"
},
  "geometry": {"coordinates":[15.6558494568,48.0672073364],"type":"Point"}
}