{
  "type": "Feature",
  "properties": {
    "addr:full":"Schildbachrotte 15 T\u00fcrnitz Nieder\u00f6sterreich 3184",
    "addr:housenumber":"15",
    "addr:postcode":"3184",
    "addr:street":"Schildbachrotte;Niederoesterreich",
    "iso:country":"AT",
    "sg:address":"Schildbachrotte 15",
    "sg:city":"T\u00fcrnitz",
    "sg:classifiers":[
        {
            "category":"Home & Garden",
            "subcategory":"Building Materials",
            "type":"Retail Goods"
        }
    ],
    "sg:phone":"+43 2769 8393",
    "sg:postcode":"3184",
    "sg:province":"Nieder\u00f6sterreich",
    "sg:tags":[
        "gravel",
        "crushed"
    ],
    "wof:name":"Johann Sieber Ges.m.b.H.",
    "wof:placetype":"venue"
},
  "geometry": {"coordinates":[15.4809703827,47.923740387],"type":"Point"}
}