{
  "type": "Feature",
  "properties": {
    "addr:full":"Freist\u00e4dter Str 145 Linz Ober\u00f6sterreich 4040",
    "addr:housenumber":"145",
    "addr:postcode":"4040",
    "addr:street":"Str",
    "iso:country":"AT",
    "sg:address":"Freist\u00e4dter Str 145",
    "sg:city":"Linz",
    "sg:orig_category":"Non-Classified Establishments",
    "sg:phone":"+43 732 70703335",
    "sg:postcode":"4040",
    "sg:province":"Ober\u00f6sterreich",
    "wof:name":"Stra\u00dfenmeisterei Nord",
    "wof:placetype":"venue"
},
  "geometry": {"coordinates":[14.2938375473,48.3234214783],"type":"Point"}
}