{
  "type": "Feature",
  "properties": {
    "addr:full":"Dorfstr 46 Bad Kleinkirchheim K\u00e4rnten 9546",
    "addr:housenumber":"46",
    "addr:postcode":"9546",
    "addr:street":"Dorfstr",
    "iso:country":"AT",
    "sg:address":"Dorfstr 46",
    "sg:city":"Bad Kleinkirchheim",
    "sg:classifiers":[
        {
            "category":"Restaurant",
            "type":"Food & Drink"
        }
    ],
    "sg:phone":"+43 4240 8217",
    "sg:postcode":"9546",
    "sg:province":"K\u00e4rnten",
    "sg:tags":[
        "pizzeria"
    ],
    "wof:name":"Pizzeria da Capo",
    "wof:placetype":"venue"
},
  "geometry": {"coordinates":[13.7914791107,46.8133506775],"type":"Point"}
}