{
  "type": "Feature",
  "properties": {
    "iso:country":"AT",
    "sg:address":"Florian-Hedorfer-Str 26",
    "sg:city":"Wien",
    "sg:orig_category":"Hauptschulen",
    "sg:phone":"+43 1 7671373",
    "sg:postcode":"1110",
    "sg:province":"Wien",
    "wof:name":"Schulen d Stadt Wien - Mittelschule",
    "wof:placetype":"venue"
},
  "geometry": {"coordinates":[16.4318275452,48.1672134399],"type":"Point"}
}