{
  "type": "Feature",
  "properties": {
    "addr:full":"Siebensterng 31 Wien Wien 1070",
    "addr:housenumber":"31",
    "addr:postcode":"1070",
    "addr:street":"Siebensterng",
    "iso:country":"AT",
    "sg:address":"Siebensterng 31",
    "sg:city":"Wien",
    "sg:orig_category":"Bars-Cafes",
    "sg:phone":"+43 1 5229120",
    "sg:postcode":"1070",
    "sg:province":"Wien",
    "wof:name":"Shultz American Cafe Bar",
    "wof:placetype":"venue"
},
  "geometry": {"coordinates":[16.3514328003,48.2020950317],"type":"Point"}
}