{
  "type": "Feature",
  "properties": {
    "iso:country":"AT",
    "sg:address":"Leo-Mathauser-Gasse 75",
    "sg:city":"Wien",
    "sg:classifiers":[
        {
            "category":"Transit Center",
            "subcategory":"Freight",
            "type":"Transportation"
        }
    ],
    "sg:phone":"+43 1 6994242",
    "sg:postcode":"1230",
    "sg:province":"Wien",
    "sg:tags":[
        "ready",
        "castings",
        "installation"
    ],
    "sg:website":"members.aon.at/k-spring/",
    "wof:name":"Kurt Springer GmbH",
    "wof:placetype":"venue"
},
  "geometry": {"coordinates":[16.3175258636,48.1267967224],"type":"Point"}
}