{
  "type": "Feature",
  "properties": {
    "addr:full":"Stadtpl 15 Steyr Ober\u00f6sterreich 4400",
    "addr:housenumber":"15",
    "addr:postcode":"4400",
    "addr:street":"Stadtpl;Oberoesterreich",
    "iso:country":"AT",
    "sg:address":"Stadtpl 15",
    "sg:city":"Steyr",
    "sg:orig_category":"Steuerberatung",
    "sg:phone":"+43 4372 52539410",
    "sg:postcode":"4400",
    "sg:province":"Ober\u00f6sterreich",
    "wof:name":"Wiesmayr Herfried Dkfm Dr",
    "wof:placetype":"venue"
},
  "geometry": {"coordinates":[14.4196634293,48.0394325256],"type":"Point"}
}