{
  "type": "Feature",
  "properties": {
    "addr:full":"Sparkassenpl 2 Innsbruck Tirol 6020",
    "addr:housenumber":"2",
    "addr:postcode":"6020",
    "addr:street":"Sparkassenpl;Tirol",
    "iso:country":"AT",
    "sg:address":"Sparkassenpl 2",
    "sg:city":"Innsbruck",
    "sg:orig_category":"Boutiquen",
    "sg:phone":"+43 512 580092",
    "sg:postcode":"6020",
    "sg:province":"Tirol",
    "wof:name":"Mode-Studio Ing P Kinzl",
    "wof:placetype":"venue"
},
  "geometry": {"coordinates":[11.3950386047,47.265827179],"type":"Point"}
}