{
  "type": "Feature",
  "properties": {
    "iso:country":"AT",
    "sg:address":"Aub\u00f6ckpl 3",
    "sg:city":"Bad Ischl",
    "sg:orig_category":"Blumeneinzelhandel",
    "sg:phone":"+43 6132 22822",
    "sg:postcode":"4820",
    "sg:province":"Ober\u00f6sterreich",
    "wof:name":"Blumen Eder - Grieshofer OEG",
    "wof:placetype":"venue"
},
  "geometry": {"coordinates":[13.6257123947,47.711971283],"type":"Point"}
}