{
  "type": "Feature",
  "properties": {
    "addr:full":"Amraser Str 25 Innsbruck Tirol 6020",
    "addr:housenumber":"25",
    "addr:postcode":"6020",
    "addr:street":"Amraser Str;Tirol",
    "iso:country":"AT",
    "sg:address":"Amraser Str 25",
    "sg:city":"Innsbruck",
    "sg:orig_category":"Ingenieurkonsulenten / Zivilingenieure",
    "sg:phone":"+43 512 347730",
    "sg:postcode":"6020",
    "sg:province":"Tirol",
    "wof:name":"Inhoven Romed Dipl-Ing",
    "wof:placetype":"venue"
},
  "geometry": {"coordinates":[11.4090976715,47.2633552551],"type":"Point"}
}