{
  "type": "Feature",
  "properties": {
    "addr:full":"Alte Poststr 24 Hainburg an der Donau Nieder\u00f6sterreich 2410",
    "addr:housenumber":"24",
    "addr:postcode":"2410",
    "iso:country":"AT",
    "sg:address":"Alte Poststr 24",
    "sg:city":"Hainburg an der Donau",
    "sg:orig_category":"Volksschulen",
    "sg:phone":"+43 4321 6562547",
    "sg:postcode":"2410",
    "sg:province":"Nieder\u00f6sterreich",
    "wof:name":"Volksschule 1",
    "wof:placetype":"venue"
},
  "geometry": {"coordinates":[16.9423179626,48.1462364197],"type":"Point"}
}