{
  "type": "Feature",
  "properties": {
    "iso:country":"AT",
    "sg:address":"Benediktinerpl 10",
    "sg:city":"Klagenfurt",
    "sg:orig_category":"Freizeitangebote U -Einrichtungen",
    "sg:phone":"+43 4346 3511807",
    "sg:postcode":"9020",
    "sg:province":"K\u00e4rnten",
    "wof:name":"Jugendzentrum POINT",
    "wof:placetype":"venue"
},
  "geometry": {"coordinates":[14.3061237335,46.6223754883],"type":"Point"}
}