{
  "type": "Feature",
  "properties": {
    "addr:full":"Spaunstr 39 Linz Ober\u00f6sterreich 4020",
    "addr:housenumber":"39",
    "addr:postcode":"4020",
    "addr:street":"Spaunstr",
    "iso:country":"AT",
    "sg:address":"Spaunstr 39",
    "sg:city":"Linz",
    "sg:orig_category":"Unternehmensberatung",
    "sg:phone":"+43 4367 684969930",
    "sg:postcode":"4020",
    "sg:province":"Ober\u00f6sterreich",
    "wof:name":"Inticium Brandtner W\u00f6ss OEG",
    "wof:placetype":"venue"
},
  "geometry": {"coordinates":[14.307847023,48.2720832825],"type":"Point"}
}