{
  "type": "Feature",
  "properties": {
    "addr:full":"Roseggerstr 27 Mitterdorf im M\u00fcrztal Steiermark 8662",
    "addr:housenumber":"27;im",
    "addr:postcode":"8662",
    "addr:street":"Roseggerstr;Muerztal Steiermark",
    "iso:country":"AT",
    "sg:address":"Roseggerstr 27",
    "sg:city":"Mitterdorf im M\u00fcrztal",
    "sg:orig_category":"Friseure U Frisiersalons",
    "sg:phone":"+43 4338 582266",
    "sg:postcode":"8662",
    "sg:province":"Steiermark",
    "wof:name":"Fritz Christa",
    "wof:placetype":"venue"
},
  "geometry": {"coordinates":[15.5132570267,47.5354766846],"type":"Point"}
}