{
  "type": "Feature",
  "properties": {
    "addr:full":"Koling 9 Wien Wien 1090",
    "addr:housenumber":"9",
    "addr:postcode":"1090",
    "addr:street":"Koling",
    "iso:country":"AT",
    "sg:address":"Koling 9",
    "sg:city":"Wien",
    "sg:classifiers":[
        {
            "category":"Organizations",
            "subcategory":"Community Association",
            "type":"Services"
        }
    ],
    "sg:phone":"+43 1 31097820",
    "sg:postcode":"1090",
    "sg:province":"Wien",
    "sg:tags":[
        "relation",
        "public"
    ],
    "wof:name":"Active Communications Dr Herbert Braun\u00f6ck",
    "wof:placetype":"venue"
},
  "geometry": {"coordinates":[16.3627338409,48.2161636353],"type":"Point"}
}