{
  "type": "Feature",
  "properties": {
    "iso:country":"AT",
    "sg:address":"Stadtpl 8",
    "sg:city":"Zell am See",
    "sg:orig_category":"Tabaktrafiken",
    "sg:phone":"+43 6542 72508",
    "sg:postcode":"5700",
    "sg:province":"Salzburg",
    "wof:name":"Turmtrafik Burger",
    "wof:placetype":"venue"
},
  "geometry": {"coordinates":[12.7980690002,47.3236198425],"type":"Point"}
}