{
  "type": "Feature",
  "properties": {
    "addr:full":"Nr 79 St. Georgen ob Judenburg Steiermark 8756",
    "addr:postcode":"8756",
    "addr:street":"Nr 79",
    "iso:country":"AT",
    "sg:address":"Nr 79",
    "sg:city":"St. Georgen ob Judenburg",
    "sg:orig_category":"Erdarbeiten",
    "sg:phone":"+43 4335 832017",
    "sg:postcode":"8756",
    "sg:province":"Steiermark",
    "wof:name":"Erdbau Rissner Andreas",
    "wof:placetype":"venue"
},
  "geometry": {"coordinates":[14.4987268448,47.20652771],"type":"Point"}
}