{
  "type": "Feature",
  "properties": {
    "iso:country":"AT",
    "sg:address":"Lindauweg 24",
    "sg:city":"Fieberbrunn",
    "sg:orig_category":"Pensionen / Privatzimmer",
    "sg:phone":"+43 5354 56403",
    "sg:postcode":"6391",
    "sg:province":"Tirol",
    "wof:name":"Fr\u00fchst\u00fcckspension Marie-Lou Habel",
    "wof:placetype":"venue"
},
  "geometry": {"coordinates":[12.5471563339,47.4721794128],"type":"Point"}
}