{
  "type": "Feature",
  "properties": {
    "iso:country":"AT",
    "sg:address":"Hetzendorfer Str 133",
    "sg:city":"Wien",
    "sg:orig_category":"Fleischhauereien",
    "sg:phone":"+43 1 8046692",
    "sg:postcode":"1120",
    "sg:province":"Wien",
    "wof:name":"Ehrenhofer Johann",
    "wof:placetype":"venue"
},
  "geometry": {"coordinates":[16.3014202118,48.1692848206],"type":"Point"}
}