{
  "type": "Feature",
  "properties": {
    "iso:country":"AT",
    "sg:address":"Oberhofstr 29",
    "sg:city":"Bruck an der Gro\u00dfglocknerstra\u00dfe",
    "sg:orig_category":"Baumeister",
    "sg:phone":"+43 4365 4573440",
    "sg:postcode":"5671",
    "sg:province":"Salzburg",
    "wof:name":"Rodler Erich Ing",
    "wof:placetype":"venue"
},
  "geometry": {"coordinates":[12.8371248245,47.2832679749],"type":"Point"}
}