{
  "type": "Feature",
  "properties": {
    "addr:full":"Koflerweg 10 Kaltenbach Tirol 6272",
    "addr:housenumber":"10",
    "addr:postcode":"6272",
    "addr:street":"Koflerweg",
    "iso:country":"AT",
    "sg:address":"Koflerweg 10",
    "sg:city":"Kaltenbach",
    "sg:orig_category":"Dekorationen",
    "sg:phone":"+43 5283 2385",
    "sg:postcode":"6272",
    "sg:province":"Tirol",
    "wof:name":"Braunegger Martin - Kunstgewerbe-Dekoration",
    "wof:placetype":"venue"
},
  "geometry": {"coordinates":[11.8843383789,47.2921791077],"type":"Point"}
}