{
  "type": "Feature",
  "properties": {
    "addr:full":"Seestr 40-42 Neusiedl am See Burgenland 7100",
    "addr:postcode":"40-42;7100",
    "iso:country":"AT",
    "sg:address":"Seestr 40-42",
    "sg:city":"Neusiedl am See",
    "sg:orig_category":"Friseure U Frisiersalons",
    "sg:phone":"+43 4321 678111613",
    "sg:postcode":"7100",
    "sg:province":"Burgenland",
    "wof:name":"Frisiersalon Sylvia im Hotel Wende",
    "wof:placetype":"venue"
},
  "geometry": {"coordinates":[16.8445968628,47.9403877258],"type":"Point"}
}