{
  "type": "Feature",
  "properties": {
    "addr:full":"Georg Sigl-Strasse 14 Breitenfurt Nieder\u00f6sterreich 2384",
    "addr:housenumber":"14",
    "addr:postcode":"2384",
    "addr:street":"Sigl-Strasse",
    "iso:country":"AT",
    "sg:address":"Georg Sigl-Strasse 14",
    "sg:city":"Breitenfurt",
    "sg:classifiers":[
        {
            "category":"Professional",
            "subcategory":"Accounting & Tax Preparation",
            "type":"Services"
        }
    ],
    "sg:phone":"+43 2239 54700",
    "sg:postcode":"2384",
    "sg:province":"Nieder\u00f6sterreich",
    "sg:tags":[
        "financial",
        "software"
    ],
    "sg:website":"multidata.at",
    "wof:name":"MultiData Software Entwicklungsges.m.b.H. & Co KG",
    "wof:placetype":"venue"
},
  "geometry": {"coordinates":[16.1922245026,48.1365089417],"type":"Point"}
}