{
  "type": "Feature",
  "properties": {
    "iso:country":"AT",
    "sg:address":"Norbert-Krebs-G 7",
    "sg:city":"Wien",
    "sg:orig_category":"Raumgestaltung",
    "sg:phone":"+43 664 4445566",
    "sg:postcode":"1210",
    "sg:province":"Wien",
    "wof:name":"Bauer Franz Erwin Ing - Wohnraum- B\u00e4der- K\u00fcchenplanungen + Montagen",
    "wof:placetype":"venue"
},
  "geometry": {"coordinates":[16.4235610962,48.2580528259],"type":"Point"}
}