{
  "type": "Feature",
  "properties": {
    "iso:country":"AT",
    "sg:address":"Schlo\u00dfparkstr 16",
    "sg:city":"Obersiebenbrunn",
    "sg:orig_category":"Gutsverwaltungen",
    "sg:phone":"+43 2286 2248",
    "sg:postcode":"2283",
    "sg:province":"Nieder\u00f6sterreich",
    "wof:name":"Erzbistum Wien - Gutsverwaltung Obersiebenbrunn",
    "wof:placetype":"venue"
},
  "geometry": {"coordinates":[16.7072296143,48.2648887634],"type":"Point"}
}