{
  "type": "Feature",
  "properties": {
    "iso:country":"AT",
    "sg:address":"Mitterg 18",
    "sg:city":"Bruck an der Mur",
    "sg:orig_category":"Immobilienmakler",
    "sg:phone":"+43 4338 6258500",
    "sg:postcode":"8600",
    "sg:province":"Steiermark",
    "wof:name":"Raiffeisen Immobilien Steiermark GesmbH",
    "wof:placetype":"venue"
},
  "geometry": {"coordinates":[15.2717208862,47.41040802],"type":"Point"}
}