{
  "type": "Feature",
  "properties": {
    "iso:country":"AT",
    "sg:address":"Esplanade 11",
    "sg:city":"Bad Ischl",
    "sg:orig_category":"Friseure U Frisiersalons",
    "sg:phone":"+43 4361 3227915",
    "sg:postcode":"4820",
    "sg:province":"Ober\u00f6sterreich",
    "wof:name":"Harmonie Ihr Friseur u Maskenbildner",
    "wof:placetype":"venue"
},
  "geometry": {"coordinates":[13.6257123947,47.711971283],"type":"Point"}
}