{
  "type": "Feature",
  "properties": {
    "addr:full":"Sperrg 12 Wien Wien 1150",
    "addr:housenumber":"12",
    "addr:postcode":"1150",
    "addr:street":"Sperrg",
    "iso:country":"AT",
    "sg:address":"Sperrg 12",
    "sg:city":"Wien",
    "sg:orig_category":"Pensionen / Privatzimmer",
    "sg:phone":"+43 1 8923545",
    "sg:postcode":"1150",
    "sg:province":"Wien",
    "wof:name":"Pension F\u00fcnfhaus Inh Susi Tersch",
    "wof:placetype":"venue"
},
  "geometry": {"coordinates":[16.3314666748,48.1937980652],"type":"Point"}
}