{
  "type": "Feature",
  "properties": {
    "iso:country":"AT",
    "sg:address":"Dorfstr 54c",
    "sg:city":"Rattenberg",
    "sg:orig_category":"Feuerwehren",
    "sg:phone":"+43 5337 64849",
    "sg:postcode":"6240",
    "sg:province":"Tirol",
    "wof:name":"Freiwillige Feuerwehr Radfeld",
    "wof:placetype":"venue"
},
  "geometry": {"coordinates":[11.9041719437,47.4463653564],"type":"Point"}
}