{
  "type": "Feature",
  "properties": {
    "iso:country":"AT",
    "sg:address":"Jahng 2",
    "sg:city":"Gleisdorf",
    "sg:orig_category":"Installationsunternehmen",
    "sg:phone":"+43 3112 50087",
    "sg:postcode":"8200",
    "sg:province":"Steiermark",
    "wof:name":"Sailer Gerhard",
    "wof:placetype":"venue"
},
  "geometry": {"coordinates":[15.7096796036,47.1070671082],"type":"Point"}
}