{
  "type": "Feature",
  "properties": {
    "addr:full":"Georgestr 1 St. Georgen an der Gusen Ober\u00f6sterreich 4222",
    "addr:housenumber":"1",
    "addr:postcode":"4222",
    "addr:street":"Georgestr",
    "iso:country":"AT",
    "sg:address":"Georgestr 1",
    "sg:city":"St. Georgen an der Gusen",
    "sg:orig_category":"Lebensmittel / Einzelhandel",
    "sg:phone":"+43 7237 2256",
    "sg:postcode":"4222",
    "sg:province":"Ober\u00f6sterreich",
    "wof:name":"Sturm Helmut",
    "wof:placetype":"venue"
},
  "geometry": {"coordinates":[14.4713001251,48.2532997131],"type":"Point"}
}