{
  "type": "Feature",
  "properties": {
    "addr:full":"Hollerg 14 Weissenbach an der Triesting Nieder\u00f6sterreich 2564",
    "addr:housenumber":"14",
    "addr:postcode":"2564",
    "addr:street":"Hollerg",
    "iso:country":"AT",
    "sg:address":"Hollerg 14",
    "sg:city":"Weissenbach an der Triesting",
    "sg:classifiers":[
        {
            "category":"Professional",
            "subcategory":"Computer Services",
            "type":"Services"
        }
    ],
    "sg:phone":"+43 4326 7487587",
    "sg:postcode":"2564",
    "sg:province":"Nieder\u00f6sterreich",
    "sg:tags":[
        "software"
    ],
    "wof:name":"RT - Computertechnik Ing Robert Totz",
    "wof:placetype":"venue"
},
  "geometry": {"coordinates":[16.0407123566,47.979057312],"type":"Point"}
}