{
  "type": "Feature",
  "properties": {
    "addr:full":"Dorfstr 2 St. Anton am Arlberg Tirol 6580",
    "addr:housenumber":"2",
    "addr:postcode":"6580",
    "addr:street":"Dorfstr;Tirol",
    "iso:country":"AT",
    "sg:address":"Dorfstr 2",
    "sg:city":"St. Anton am Arlberg",
    "sg:orig_category":"Internet-Cafes",
    "sg:phone":"+43 699 10022001",
    "sg:postcode":"6580",
    "sg:province":"Tirol",
    "wof:name":"New Spirits Kommunikation & Information GmbH",
    "wof:placetype":"venue"
},
  "geometry": {"coordinates":[10.2638940811,47.1268959045],"type":"Point"}
}