{
  "type": "Feature",
  "properties": {
    "addr:full":"Fossenhofstr 40 Freistadt Ober\u00f6sterreich 4240",
    "addr:housenumber":"40",
    "addr:postcode":"4240",
    "addr:street":"Fossenhofstr",
    "iso:country":"AT",
    "sg:address":"Fossenhofstr 40",
    "sg:city":"Freistadt",
    "sg:orig_category":"Werbeagenturen",
    "sg:phone":"+43 4379 4277030",
    "sg:postcode":"4240",
    "sg:province":"Ober\u00f6sterreich",
    "wof:name":"Studio Kapeller KEG",
    "wof:placetype":"venue"
},
  "geometry": {"coordinates":[14.4954395294,48.5088005066],"type":"Point"}
}