{
  "type": "Feature",
  "properties": {
    "addr:full":"Schulzg 15/10 Wien Wien 1210",
    "addr:housenumber":"15 / 10",
    "addr:postcode":"1210",
    "addr:street":"Schulzg",
    "iso:country":"AT",
    "sg:address":"Schulzg 15/10",
    "sg:city":"Wien",
    "sg:classifiers":[
        {
            "category":"Internet Cafe",
            "subcategory":"None",
            "type":"Food & Drink"
        }
    ],
    "sg:phone":"+43 664 4713723",
    "sg:postcode":"1210",
    "sg:province":"Wien",
    "wof:name":"2mComp - Ing Martin Mayrhofer",
    "wof:placetype":"venue"
},
  "geometry": {"coordinates":[16.3844871521,48.26121521],"type":"Point"}
}