{
  "type": "Feature",
  "properties": {
    "addr:full":"Sparkassenpl 1 Ferlach K\u00e4rnten 9170",
    "addr:housenumber":"1",
    "addr:postcode":"9170",
    "addr:street":"Sparkassenpl;Kaernten",
    "iso:country":"AT",
    "sg:address":"Sparkassenpl 1",
    "sg:city":"Ferlach",
    "sg:orig_category":"Banken U Sparkassen",
    "sg:phone":"+43 5 010030817",
    "sg:postcode":"9170",
    "sg:province":"K\u00e4rnten",
    "wof:name":"K\u00e4rntner Sparkasse AG",
    "wof:placetype":"venue"
},
  "geometry": {"coordinates":[14.2990169525,46.5267028809],"type":"Point"}
}