{
  "type": "Feature",
  "properties": {
    "addr:full":"Wiener Str 46 Wiener Neustadt Nieder\u00f6sterreich 2700",
    "addr:postcode":"2700",
    "addr:street":"46",
    "iso:country":"AT",
    "sg:address":"Wiener Str 46",
    "sg:city":"Wiener Neustadt",
    "sg:orig_category":"Steinmetzbetriebe",
    "sg:phone":"+43 2622 227660",
    "sg:postcode":"2700",
    "sg:province":"Nieder\u00f6sterreich",
    "sg:website":"www.steine-hoenig.at",
    "wof:name":"H\u00f6nig Judith - Steine H\u00f6nig",
    "wof:placetype":"venue"
},
  "geometry": {"coordinates":[16.2443904877,47.8158988953],"type":"Point"}
}