{
  "type": "Feature",
  "properties": {
    "iso:country":"AT",
    "sg:address":"Burgg 47",
    "sg:city":"Schwaz",
    "sg:orig_category":"Volkshochschulen",
    "sg:phone":"+43 5242 67209",
    "sg:postcode":"6130",
    "sg:province":"Tirol",
    "wof:name":"Volkshochschule",
    "wof:placetype":"venue"
},
  "geometry": {"coordinates":[11.718123436,47.3453559875],"type":"Point"}
}