{
  "type": "Feature",
  "properties": {
    "iso:country":"AT",
    "sg:address":"Haslingerg 16",
    "sg:city":"Wien",
    "sg:orig_category":"Autohandel",
    "sg:phone":"+43 1 4082036",
    "sg:postcode":"1170",
    "sg:province":"Wien",
    "wof:name":"Osterbauer Kurt GesmbH",
    "wof:placetype":"venue"
},
  "geometry": {"coordinates":[16.330575943,48.2151489258],"type":"Point"}
}