{
  "type": "Feature",
  "properties": {
    "addr:full":"Baumkirchner Str 3 Voitsberg Steiermark 8570",
    "addr:postcode":"8570",
    "iso:country":"AT",
    "sg:address":"Baumkirchner Str 3",
    "sg:city":"Voitsberg",
    "sg:orig_category":"Abfallentsorgung U -Verwertung",
    "sg:phone":"+43 3142 249880",
    "sg:postcode":"8570",
    "sg:province":"Steiermark",
    "wof:name":"Komex - AbfallentsorgungsgesmbH",
    "wof:placetype":"venue"
},
  "geometry": {"coordinates":[15.1351318359,47.0455513],"type":"Point"}
}