{
  "type": "Feature",
  "properties": {
    "iso:country":"AT",
    "sg:address":"Pratsdorf 6",
    "sg:city":"Pettenbach",
    "sg:classifiers":[
        {
            "category":"Professional",
            "subcategory":"Art Services",
            "type":"Services"
        }
    ],
    "sg:phone":"+43 7586 8567",
    "sg:postcode":"4643",
    "sg:province":"Ober\u00f6sterreich",
    "sg:tags":[
        "metalwork"
    ],
    "wof:name":"Ernst Radner",
    "wof:placetype":"venue"
},
  "geometry": {"coordinates":[14.0179386139,47.9592781067],"type":"Point"}
}