{
  "type": "Feature",
  "properties": {
    "iso:country":"AT",
    "sg:address":"Reith 130",
    "sg:city":"Fieberbrunn",
    "sg:classifiers":[
        {
            "category":"Travel",
            "subcategory":"Hotels & Motels",
            "type":"Entertainment"
        }
    ],
    "sg:phone":"+43 4353 54881650",
    "sg:postcode":"6391",
    "sg:province":"Tirol",
    "wof:name":"Ferienhotel Kitz Spitz Fam Nothegger",
    "wof:placetype":"venue"
},
  "geometry": {"coordinates":[12.5685768127,47.5009727478],"type":"Point"}
}