{
  "type": "Feature",
  "properties": {
    "addr:full":"Wiener Str. 52  Langenlois Nieder\u00f6sterreich 3550",
    "addr:postcode":"3550",
    "addr:street":"Str. 52",
    "iso:country":"AT",
    "sg:address":"Wiener Str. 52 ",
    "sg:city":"Langenlois",
    "sg:classifiers":[
        {
            "category":"Manufacturing",
            "subcategory":"Food",
            "type":"Manufacturing & Wholesale Goods"
        }
    ],
    "sg:phone":"+43 4327 342676",
    "sg:postcode":"3550",
    "sg:province":"Nieder\u00f6sterreich",
    "sg:tags":[
        "equipment",
        "processing",
        "-",
        "machinery"
    ],
    "wof:name":"KLINGER MASCHINEN GMBH",
    "wof:placetype":"venue"
},
  "geometry": {"coordinates":[15.6965236664,48.4755134583],"type":"Point"}
}