{
  "type": "Feature",
  "properties": {
    "iso:country":"AT",
    "sg:address":"Kutschkerg 13",
    "sg:city":"Wien",
    "sg:orig_category":"Tischlereien",
    "sg:phone":"+43 1 4026926",
    "sg:postcode":"1180",
    "sg:province":"Wien",
    "wof:name":"Holz-Technik-Design GmbH",
    "wof:placetype":"venue"
},
  "geometry": {"coordinates":[16.3438415527,48.2235870361],"type":"Point"}
}