{
  "type": "Feature",
  "properties": {
    "addr:full":"Sportplatz Gablitz Nieder\u00f6sterreich 3003",
    "addr:postcode":"3003",
    "addr:street":"Sportplatz",
    "iso:country":"AT",
    "sg:address":"Sportplatz",
    "sg:city":"Gablitz",
    "sg:orig_category":"Transportbeton",
    "sg:phone":"+43 2231 65246",
    "sg:postcode":"3003",
    "sg:province":"Nieder\u00f6sterreich",
    "wof:name":"Lieferbeton GesmbH",
    "wof:placetype":"venue"
},
  "geometry": {"coordinates":[16.124830246,48.2415733337],"type":"Point"}
}