{
  "type": "Feature",
  "properties": {
    "addr:full":"Kramer-Gl\u00f6ckner-Str 1 Wien Wien 1130",
    "addr:housenumber":"1",
    "addr:postcode":"1130",
    "addr:street":"Kramer-Gloeckner-Str",
    "iso:country":"AT",
    "sg:address":"Kramer-Gl\u00f6ckner-Str 1",
    "sg:city":"Wien",
    "sg:orig_category":"Maler, Anstreicher U Lackierer",
    "sg:phone":"+43 4318 043927",
    "sg:postcode":"1130",
    "sg:province":"Wien",
    "wof:name":"Hafran Peter",
    "wof:placetype":"venue"
},
  "geometry": {"coordinates":[16.2672386169,48.1684532166],"type":"Point"}
}