{
  "type": "Feature",
  "properties": {
    "addr:full":"Tuttenhofstr Langenzersdorf Nieder\u00f6sterreich 2103",
    "addr:postcode":"2103",
    "addr:street":"Tuttenhofstr",
    "iso:country":"AT",
    "sg:address":"Tuttenhofstr",
    "sg:city":"Langenzersdorf",
    "sg:classifiers":[
        {
            "category":"Restaurant",
            "type":"Food & Drink"
        }
    ],
    "sg:phone":"+43 2244 30735",
    "sg:postcode":"2103",
    "sg:province":"Nieder\u00f6sterreich",
    "wof:name":"Golfrestaurant Peter Dorfner",
    "wof:placetype":"venue"
},
  "geometry": {"coordinates":[16.3421993256,48.3241195679],"type":"Point"}
}