{
  "type": "Feature",
  "properties": {
    "addr:full":"Kapsamerstrasse 3 Offenhausen Ober\u00f6sterreich 4625",
    "addr:housenumber":"3",
    "addr:postcode":"4625",
    "addr:street":"Kapsamerstrasse",
    "iso:country":"AT",
    "sg:address":"Kapsamerstrasse 3",
    "sg:city":"Offenhausen",
    "sg:classifiers":[
        {
            "category":"Sports & Exercise",
            "subcategory":"Playing Field",
            "type":"Entertainment"
        }
    ],
    "sg:phone":"+43 7247 65280",
    "sg:postcode":"4625",
    "sg:province":"Ober\u00f6sterreich",
    "sg:tags":[
        "temporary",
        "employment",
        "software",
        "leasing",
        "staff"
    ],
    "sg:website":"prosoft-edv.at",
    "wof:name":"Prosoft EDV-L\u00f6sungen GmbH & Co KG",
    "wof:placetype":"venue"
},
  "geometry": {"coordinates":[13.8317708969,48.1564750671],"type":"Point"}
}