{
  "type": "Feature",
  "properties": {
    "addr:full":"Thaliastr 159 Wien Wien 1160",
    "addr:housenumber":"159",
    "addr:postcode":"1160",
    "iso:country":"AT",
    "sg:address":"Thaliastr 159",
    "sg:city":"Wien",
    "sg:orig_category":"Blumeneinzelhandel",
    "sg:phone":"+43 1 4931870",
    "sg:postcode":"1160",
    "sg:province":"Wien",
    "wof:name":"Balaika & Co KEG",
    "wof:placetype":"venue"
},
  "geometry": {"coordinates":[16.3030548096,48.2137985229],"type":"Point"}
}