{
  "type": "Feature",
  "properties": {
    "addr:full":"Jauring 31 Aflenz Kurort Steiermark 8623",
    "addr:housenumber":"31",
    "addr:postcode":"8623",
    "addr:street":"Jauring",
    "iso:country":"AT",
    "sg:address":"Jauring 31",
    "sg:city":"Aflenz Kurort",
    "sg:orig_category":"Schmieden U Schmiedeeisenelemente",
    "sg:phone":"+43 4338 612237",
    "sg:postcode":"8623",
    "sg:province":"Steiermark",
    "wof:name":"Plewa Gerald",
    "wof:placetype":"venue"
},
  "geometry": {"coordinates":[15.2517900467,47.5474700928],"type":"Point"}
}