{
  "type": "Feature",
  "properties": {
    "addr:full":"Schladnitzgraben 23 Leoben Steiermark 8700",
    "addr:housenumber":"23",
    "addr:postcode":"8700",
    "addr:street":"Schladnitzgraben",
    "iso:country":"AT",
    "sg:address":"Schladnitzgraben 23",
    "sg:city":"Leoben",
    "sg:orig_category":"Musikgruppen",
    "sg:phone":"+43 664 5269149",
    "sg:postcode":"8700",
    "sg:province":"Steiermark",
    "wof:name":"Die Vier Holterbuam",
    "wof:placetype":"venue"
},
  "geometry": {"coordinates":[15.1065273285,47.3371658325],"type":"Point"}
}