{
  "type": "Feature",
  "properties": {
    "addr:full":"Woissauer Str 13 Linz Ober\u00f6sterreich 4030",
    "addr:postcode":"4030",
    "addr:street":"Str 13",
    "iso:country":"AT",
    "sg:address":"Woissauer Str 13",
    "sg:city":"Linz",
    "sg:classifiers":[
        {
            "category":"Restaurant",
            "type":"Food & Drink"
        }
    ],
    "sg:phone":"+43 732 382228",
    "sg:postcode":"4030",
    "sg:province":"Ober\u00f6sterreich",
    "wof:name":"Gusto Cafe-Restaurant",
    "wof:placetype":"venue"
},
  "geometry": {"coordinates":[14.2894287109,48.2515296936],"type":"Point"}
}