{
  "type": "Feature",
  "properties": {
    "addr:full":"Obervellach 33 Hermagor K\u00e4rnten 9620",
    "addr:housenumber":"33",
    "addr:postcode":"9620",
    "addr:street":"Obervellach;Kaernten",
    "iso:country":"AT",
    "sg:address":"Obervellach 33",
    "sg:city":"Hermagor",
    "sg:orig_category":"Feinkost",
    "sg:phone":"+43 4342 822069",
    "sg:postcode":"9620",
    "sg:province":"K\u00e4rnten",
    "wof:name":"Bachmann's Lachsr\u00e4ucherei",
    "wof:placetype":"venue"
},
  "geometry": {"coordinates":[13.3710899353,46.6263885498],"type":"Point"}
}