{
  "type": "Feature",
  "properties": {
    "addr:full":"Mittler Au 21 und 23 Bad Wimsbach-Neydharting Ober\u00f6sterreich 4654",
    "addr:housenumber":"21 und 23",
    "addr:postcode":"4654",
    "addr:street":"Mittler Au",
    "iso:country":"AT",
    "sg:address":"Mittler Au 21 und 23",
    "sg:city":"Bad Wimsbach-Neydharting",
    "sg:orig_category":"Holzwaren",
    "sg:phone":"+43 7245 25275",
    "sg:postcode":"4654",
    "sg:province":"Ober\u00f6sterreich",
    "wof:name":"Schindlauer Walter",
    "wof:placetype":"venue"
},
  "geometry": {"coordinates":[13.9008865356,48.0625839233],"type":"Point"}
}