{
  "type": "Feature",
  "properties": {
    "addr:full":"Kreitnerg 32 Wien Wien 1160",
    "addr:housenumber":"32",
    "addr:postcode":"1160",
    "addr:street":"Kreitnerg",
    "iso:country":"AT",
    "sg:address":"Kreitnerg 32",
    "sg:city":"Wien",
    "sg:orig_category":"Berufsschulen",
    "sg:phone":"+43 4315 991695940",
    "sg:postcode":"1160",
    "sg:province":"Wien",
    "wof:name":"Berufsschule f Frisur, Maske u Per\u00fccke",
    "wof:placetype":"venue"
},
  "geometry": {"coordinates":[16.3236293793,48.2087364197],"type":"Point"}
}