{
  "type": "Feature",
  "properties": {
    "addr:full":"Stadtpl 17 Rohrbach in Ober\u00f6sterreich Ober\u00f6sterreich 4150",
    "addr:housenumber":"17",
    "addr:postcode":"4150",
    "addr:street":"Stadtpl",
    "iso:country":"AT",
    "sg:address":"Stadtpl 17",
    "sg:city":"Rohrbach in Ober\u00f6sterreich",
    "sg:orig_category":"Optiker",
    "sg:phone":"+43 4372 8940096",
    "sg:postcode":"4150",
    "sg:province":"Ober\u00f6sterreich",
    "wof:name":"Optik Bauer Brillen GmbH",
    "wof:placetype":"venue"
},
  "geometry": {"coordinates":[13.9951534271,48.5746955872],"type":"Point"}
}