{
  "type": "Feature",
  "properties": {
    "iso:country":"AT",
    "sg:address":"Museumstr 18",
    "sg:city":"Innsbruck",
    "sg:orig_category":"Apotheken",
    "sg:phone":"+43 512 72271",
    "sg:postcode":"6020",
    "sg:province":"Tirol",
    "wof:name":"Apotheke Zum Tiroler Adler Inh Mag E Fischer KG",
    "wof:placetype":"venue"
},
  "geometry": {"coordinates":[11.3973608017,47.2668914795],"type":"Point"}
}