{
  "type": "Feature",
  "properties": {
    "addr:full":"Lettenberg 23 Mistelbach Nieder\u00f6sterreich 2130",
    "addr:housenumber":"23",
    "addr:postcode":"2130",
    "addr:street":"Lettenberg;Niederoesterreich",
    "iso:country":"AT",
    "sg:address":"Lettenberg 23",
    "sg:city":"Mistelbach",
    "sg:orig_category":"Tischlereien",
    "sg:phone":"+43 2572 3806",
    "sg:postcode":"2130",
    "sg:province":"Nieder\u00f6sterreich",
    "wof:name":"Ranftler Bernhard",
    "wof:placetype":"venue"
},
  "geometry": {"coordinates":[16.5667705536,48.5556793213],"type":"Point"}
}