{
  "type": "Feature",
  "properties": {
    "iso:country":"AT",
    "sg:address":"St. Veiter Str 7",
    "sg:city":"Feldkirchen in K\u00e4rnten",
    "sg:orig_category":"Entsorgungen",
    "sg:phone":"+43 4342 7620800",
    "sg:postcode":"9560",
    "sg:province":"K\u00e4rnten",
    "wof:name":"Huber Entsorgungs GesmbH Nfg KG",
    "wof:placetype":"venue"
},
  "geometry": {"coordinates":[14.1023893356,46.7223243713],"type":"Point"}
}