{
  "type": "Feature",
  "properties": {
    "addr:full":"Raiffeisenstrasse 1 Trumau Nieder\u00f6sterreich 2521",
    "addr:housenumber":"1",
    "addr:postcode":"2521",
    "addr:street":"Raiffeisenstrasse",
    "iso:country":"AT",
    "sg:address":"Raiffeisenstrasse 1",
    "sg:city":"Trumau",
    "sg:classifiers":[
        {
            "category":"Home & Garden",
            "subcategory":"Household Appliances",
            "type":"Retail Goods"
        }
    ],
    "sg:phone":"+43 2253 6594",
    "sg:postcode":"2521",
    "sg:province":"Nieder\u00f6sterreich",
    "sg:tags":[
        "electric"
    ],
    "wof:name":"Elektro Nigl GesmbH",
    "wof:placetype":"venue"
},
  "geometry": {"coordinates":[16.3418579102,47.9934577942],"type":"Point"}
}