{
  "type": "Feature",
  "properties": {
    "addr:full":"Ziehrerweg 30 Strobl Salzburg 5350",
    "addr:housenumber":"30",
    "addr:postcode":"5350",
    "addr:street":"Ziehrerweg;Salzburg",
    "iso:country":"AT",
    "sg:address":"Ziehrerweg 30",
    "sg:city":"Strobl",
    "sg:orig_category":"Maler, Anstreicher U Lackierer",
    "sg:phone":"+43 6137 5911",
    "sg:postcode":"5350",
    "sg:province":"Salzburg",
    "wof:name":"Flachberger Anton",
    "wof:placetype":"venue"
},
  "geometry": {"coordinates":[13.4822740555,47.719165802],"type":"Point"}
}