{
  "type": "Feature",
  "properties": {
    "addr:full":"Ro\u00dfmarkt 4 Wolfsberg K\u00e4rnten 9400",
    "addr:housenumber":"4;kaernten",
    "addr:postcode":"9400",
    "addr:street":"Rossmarkt",
    "iso:country":"AT",
    "sg:address":"Ro\u00dfmarkt 4",
    "sg:city":"Wolfsberg",
    "sg:orig_category":"Waren Aller Art",
    "sg:phone":"+43 4352 54992",
    "sg:postcode":"9400",
    "sg:province":"K\u00e4rnten",
    "wof:name":"Eine WELT LADEN",
    "wof:placetype":"venue"
},
  "geometry": {"coordinates":[14.8418502808,46.8402099609],"type":"Point"}
}