{
  "type": "Feature",
  "properties": {
    "addr:full":"Bahnhofstrasse 8 Friesach K\u00e4rnten 9360",
    "addr:housenumber":"8",
    "addr:postcode":"9360",
    "addr:street":"Bahnhofstrasse;Kaernten",
    "iso:country":"AT",
    "sg:address":"Bahnhofstrasse 8",
    "sg:city":"Friesach",
    "sg:classifiers":[
        {
            "category":"Home & Garden",
            "subcategory":"Household Appliances",
            "type":"Retail Goods"
        }
    ],
    "sg:phone":"+43 4268 2382",
    "sg:postcode":"9360",
    "sg:province":"K\u00e4rnten",
    "sg:tags":[
        "electric"
    ],
    "wof:name":"Elektrotechnik Wilhelm Feichter",
    "wof:placetype":"venue"
},
  "geometry": {"coordinates":[14.4072303772,46.9507904053],"type":"Point"}
}