{
  "type": "Feature",
  "properties": {
    "addr:full":"Hugo-Meisl-Weg 6 Wien Wien 1100",
    "addr:housenumber":"6",
    "addr:postcode":"1100",
    "addr:street":"Hugo-Meisl-Weg",
    "iso:country":"AT",
    "sg:address":"Hugo-Meisl-Weg 6",
    "sg:city":"Wien",
    "sg:orig_category":"Volksschulen",
    "sg:phone":"+43 1 6156284",
    "sg:postcode":"1100",
    "sg:province":"Wien",
    "wof:name":"Schulen d Stadt Wien",
    "wof:placetype":"venue"
},
  "geometry": {"coordinates":[16.3487071991,48.1560821533],"type":"Point"}
}