{
  "type": "Feature",
  "properties": {
    "addr:full":"Neunkirchner Str 1 Puchberg am Schneeberg Nieder\u00f6sterreich 2734",
    "addr:housenumber":"1",
    "addr:postcode":"2734",
    "addr:street":"Str",
    "iso:country":"AT",
    "sg:address":"Neunkirchner Str 1",
    "sg:city":"Puchberg am Schneeberg",
    "sg:orig_category":"Banken U Sparkassen",
    "sg:phone":"+43 4326 362269",
    "sg:postcode":"2734",
    "sg:province":"Nieder\u00f6sterreich",
    "wof:name":"Volksbank Nieder\u00f6sterreich S\u00fcd regGenmbH",
    "wof:placetype":"venue"
},
  "geometry": {"coordinates":[15.9135246277,47.7872161865],"type":"Point"}
}