{
  "type": "Feature",
  "properties": {
    "iso:country":"AT",
    "sg:address":"Marktpl 1",
    "sg:city":"Knittelfeld",
    "sg:orig_category":"Sauna U Dampfbad / Bau U Ausstattung",
    "sg:phone":"+43 4335 12724660",
    "sg:postcode":"8720",
    "sg:province":"Steiermark",
    "wof:name":"MR VITAL Manfred Reinwald - Infrarot Heilw\u00e4rmekabinen",
    "wof:placetype":"venue"
},
  "geometry": {"coordinates":[14.7965250015,47.2073287964],"type":"Point"}
}