{
  "type": "Feature",
  "properties": {
    "addr:full":"Maximilianstr. 18 Hohenems Vorarlberg 6845",
    "addr:housenumber":"18",
    "addr:postcode":"6845",
    "addr:street":"Maximilianstr.",
    "iso:country":"AT",
    "sg:address":"Maximilianstr. 18",
    "sg:city":"Hohenems",
    "sg:classifiers":[
        {
            "category":"Home & Garden",
            "subcategory":"Home Furnishings",
            "type":"Retail Goods"
        }
    ],
    "sg:phone":"+43 4355 76722240",
    "sg:postcode":"6845",
    "sg:province":"Vorarlberg",
    "sg:tags":[
        "household"
    ],
    "wof:name":"GEBR. DREXEL GES. MBH & CO. KG",
    "wof:placetype":"venue"
},
  "geometry": {"coordinates":[9.6848192215,47.3645744324],"type":"Point"}
}