{
  "type": "Feature",
  "properties": {
    "iso:country":"AT",
    "sg:address":"Pointeng 15/9",
    "sg:city":"Wien",
    "sg:orig_category":"Immobilienmakler",
    "sg:phone":"+43 4314 896871",
    "sg:postcode":"1170",
    "sg:province":"Wien",
    "wof:name":"Bonusreal Immobilien Vermittlungs- u VerwaltungsgesmbH",
    "wof:placetype":"venue"
},
  "geometry": {"coordinates":[16.2925987244,48.226650238],"type":"Point"}
}