{
  "type": "Feature",
  "properties": {
    "addr:full":"Krippeng 4a Hainburg an der Donau Nieder\u00f6sterreich 2410",
    "addr:housenumber":"4a",
    "addr:postcode":"2410",
    "addr:street":"Krippeng",
    "iso:country":"AT",
    "sg:address":"Krippeng 4a",
    "sg:city":"Hainburg an der Donau",
    "sg:orig_category":"Bauunternehmen",
    "sg:phone":"+43 4321 6567425",
    "sg:postcode":"2410",
    "sg:province":"Nieder\u00f6sterreich",
    "wof:name":"OMEGA-BAU Baubedarfshandels GmbH",
    "wof:placetype":"venue"
},
  "geometry": {"coordinates":[16.9400730133,48.1470184326],"type":"Point"}
}