{
  "type": "Feature",
  "properties": {
    "iso:country":"AT",
    "sg:address":"Krippeng 4a",
    "sg:city":"Hainburg an der Donau",
    "sg:orig_category":"Bauunternehmen",
    "sg:phone":"+43 4321 6567425",
    "sg:postcode":"2410",
    "sg:province":"Nieder\u00f6sterreich",
    "wof:name":"OMEGA-BAU Baubedarfshandels GmbH",
    "wof:placetype":"venue"
},
  "geometry": {"coordinates":[16.9400730133,48.1470184326],"type":"Point"}
}