{
  "type": "Feature",
  "properties": {
    "iso:country":"AT",
    "sg:address":"Feldkirchner Strasse 199",
    "sg:city":"Klagenfurt",
    "sg:classifiers":[
        {
            "category":"Home & Garden",
            "subcategory":"Building Materials",
            "type":"Retail Goods"
        }
    ],
    "sg:phone":"+43 463 427100",
    "sg:postcode":"9020",
    "sg:province":"K\u00e4rnten",
    "sg:tags":[
        "gravel",
        "crushed"
    ],
    "wof:name":"Sand-Schotter-Kies Transport- und Erdbewegungs GmbH",
    "wof:placetype":"venue"
},
  "geometry": {"coordinates":[14.2869100571,46.6456871033],"type":"Point"}
}