{
  "type": "Feature",
  "properties": {
    "iso:country":"AT",
    "sg:address":"Erlau 22",
    "sg:city":"Schwanenstadt",
    "sg:orig_category":"Installationsunternehmen",
    "sg:phone":"+43 76732066",
    "sg:postcode":"4690",
    "sg:province":"Ober\u00f6sterreich",
    "wof:name":"Schiermayr Ernst GesmbH & Co KG",
    "wof:placetype":"venue"
},
  "geometry": {"coordinates":[13.7731847763,48.0545158386],"type":"Point"}
}