{
  "type": "Feature",
  "properties": {
    "addr:full":"P\u00f6tschenstr 135 Bad Aussee Steiermark 8990",
    "addr:housenumber":"135",
    "addr:postcode":"8990",
    "iso:country":"AT",
    "sg:address":"P\u00f6tschenstr 135",
    "sg:city":"Bad Aussee",
    "sg:orig_category":"Tischlereien",
    "sg:phone":"+43 4336 22527870",
    "sg:postcode":"8990",
    "sg:province":"Steiermark",
    "wof:name":"Amon Karl",
    "wof:placetype":"venue"
},
  "geometry": {"coordinates":[13.7648000717,47.6135597229],"type":"Point"}
}