{
  "type": "Feature",
  "properties": {
    "addr:full":"Margaretenstr 27 Wien Wien 1040",
    "addr:housenumber":"27",
    "addr:postcode":"1040",
    "addr:street":"Margaretenstr",
    "iso:country":"AT",
    "sg:address":"Margaretenstr 27",
    "sg:city":"Wien",
    "sg:orig_category":"Reproanstalten",
    "sg:phone":"+43 1 58176000",
    "sg:postcode":"1040",
    "sg:province":"Wien",
    "wof:name":"Satz + Bild LohnbelichtungsgmbH",
    "wof:placetype":"venue"
},
  "geometry": {"coordinates":[16.3644142151,48.1956253052],"type":"Point"}
}