{
  "type": "Feature",
  "properties": {
    "iso:country":"AT",
    "sg:address":"Kranzlmarkt 6",
    "sg:city":"Salzburg",
    "sg:orig_category":"Telekommunikation",
    "sg:phone":"+43 676 20800",
    "sg:postcode":"5020",
    "sg:province":"Salzburg",
    "wof:name":"T-Mobile Salzburg-Kranzlmarkt",
    "wof:placetype":"venue"
},
  "geometry": {"coordinates":[13.0449819565,47.7999382019],"type":"Point"}
}