{
  "type": "Feature",
  "properties": {
    "addr:full":"Richard-Gutscher-G 30 Traismauer Nieder\u00f6sterreich 3133",
    "addr:housenumber":"30",
    "addr:postcode":"3133",
    "addr:street":"Richard-Gutscher-G",
    "iso:country":"AT",
    "sg:address":"Richard-Gutscher-G 30",
    "sg:city":"Traismauer",
    "sg:orig_category":"Autobusunternehmen",
    "sg:phone":"+43 2783 44185",
    "sg:postcode":"3133",
    "sg:province":"Nieder\u00f6sterreich",
    "wof:name":"Schipp Karl",
    "wof:placetype":"venue"
},
  "geometry": {"coordinates":[15.7380533218,48.3562736511],"type":"Point"}
}