{
  "type": "Feature",
  "properties": {
    "addr:full":"Wickenburgstr 2 Judenburg Steiermark 8750",
    "addr:housenumber":"2",
    "addr:postcode":"8750",
    "addr:street":"Wickenburgstr",
    "iso:country":"AT",
    "sg:address":"Wickenburgstr 2",
    "sg:city":"Judenburg",
    "sg:classifiers":[
        {
            "category":"Restaurant",
            "type":"Food & Drink"
        }
    ],
    "sg:phone":"+43 3572 46330",
    "sg:postcode":"8750",
    "sg:province":"Steiermark",
    "sg:tags":[
        "pizzeria"
    ],
    "wof:name":"Restaurant-Pizzeria Sandy",
    "wof:placetype":"venue"
},
  "geometry": {"coordinates":[14.6620235443,47.1677742004],"type":"Point"}
}