{
  "type": "Feature",
  "properties": {
    "iso:country":"AT",
    "sg:address":"Rathauspl 53",
    "sg:city":"Neulengbach",
    "sg:orig_category":"Tabaktrafiken",
    "sg:phone":"+43 2772 52180",
    "sg:postcode":"3040",
    "sg:province":"Nieder\u00f6sterreich",
    "wof:name":"Wittmann Renate",
    "wof:placetype":"venue"
},
  "geometry": {"coordinates":[15.9075469971,48.1965484619],"type":"Point"}
}