{
  "type": "Feature",
  "properties": {
    "addr:full":"Felber Str 51 Mittersill Salzburg 5730",
    "addr:postcode":"5730",
    "addr:street":"Str 51;Salzburg",
    "iso:country":"AT",
    "sg:address":"Felber Str 51",
    "sg:city":"Mittersill",
    "sg:classifiers":[
        {
            "category":"Travel",
            "subcategory":"Hotels & Motels",
            "type":"Entertainment"
        }
    ],
    "sg:phone":"+43 6562 44070",
    "sg:postcode":"5730",
    "sg:province":"Salzburg",
    "sg:website":"www.felben.at",
    "wof:name":"Nationalparkhotel Felben",
    "wof:placetype":"venue"
},
  "geometry": {"coordinates":[12.4909706116,47.2770996094],"type":"Point"}
}