{
  "type": "Feature",
  "properties": {
    "iso:country":"AT",
    "sg:address":"Sch\u00f6nbach 19",
    "sg:city":"Schardenberg",
    "sg:orig_category":"Baumschulen",
    "sg:phone":"+43 7713 7047",
    "sg:postcode":"4784",
    "sg:province":"Ober\u00f6sterreich",
    "wof:name":"Kieser Roland",
    "wof:placetype":"venue"
},
  "geometry": {"coordinates":[13.4969301224,48.5200233459],"type":"Point"}
}