{
  "type": "Feature",
  "properties": {
    "iso:country":"AT",
    "sg:address":"Latzendorf 1",
    "sg:city":"Stall",
    "sg:orig_category":"Pensionen / Privatzimmer",
    "sg:phone":"+43 4823 336",
    "sg:postcode":"9832",
    "sg:province":"K\u00e4rnten",
    "wof:name":"Pension Pichlerhof",
    "wof:placetype":"venue"
},
  "geometry": {"coordinates":[13.0180883408,46.8830413818],"type":"Point"}
}