{
  "type": "Feature",
  "properties": {
    "addr:full":"Hauptstr 38 Vorau Steiermark 8250",
    "addr:housenumber":"38",
    "addr:postcode":"8250",
    "addr:street":"Hauptstr",
    "iso:country":"AT",
    "sg:address":"Hauptstr 38",
    "sg:city":"Vorau",
    "sg:orig_category":"Bekleidung / Einzelhandel",
    "sg:phone":"+43 3337 3530",
    "sg:postcode":"8250",
    "sg:province":"Steiermark",
    "wof:name":"H\u00fcbel Gertrude Modeatelier",
    "wof:placetype":"venue"
},
  "geometry": {"coordinates":[15.8881130219,47.4060211182],"type":"Point"}
}