{
  "type": "Feature",
  "properties": {
    "addr:full":"Nr 1 K\u00f6flach Steiermark 8580",
    "addr:postcode":"8580",
    "addr:street":"Nr",
    "iso:country":"AT",
    "sg:address":"Nr 1",
    "sg:city":"K\u00f6flach",
    "sg:classifiers":[
        {
            "category":"Government",
            "subcategory":"Post Office",
            "type":"Public Place"
        }
    ],
    "sg:phone":"+43 4331 443323",
    "sg:postcode":"8580",
    "sg:province":"Steiermark",
    "sg:tags":[
        "-handel",
        "tierzucht",
        "u"
    ],
    "wof:name":"Bundesgest\u00fct Piber - Spanische Hofreitschule",
    "wof:placetype":"venue"
},
  "geometry": {"coordinates":[15.0835552216,47.0640258789],"type":"Point"}
}