{
  "type": "Feature",
  "properties": {
    "addr:full":"Auhofstr 153 Wien Wien 1130",
    "addr:housenumber":"153",
    "addr:postcode":"1130",
    "iso:country":"AT",
    "sg:address":"Auhofstr 153",
    "sg:city":"Wien",
    "sg:orig_category":"Tischlereien",
    "sg:phone":"+43 1 87722130",
    "sg:postcode":"1130",
    "sg:province":"Wien",
    "wof:name":"H&H Wintner GesmbH & Co KG",
    "wof:placetype":"venue"
},
  "geometry": {"coordinates":[16.269153595,48.1912536621],"type":"Point"}
}