{
  "type": "Feature",
  "properties": {
    "addr:full":"Vorderschneeberg 26 Bad Hofgastein Salzburg 5630",
    "addr:housenumber":"26",
    "addr:postcode":"5630",
    "addr:street":"Vorderschneeberg;Salzburg",
    "iso:country":"AT",
    "sg:address":"Vorderschneeberg 26",
    "sg:city":"Bad Hofgastein",
    "sg:orig_category":"Appartements / Ferienwohnungen",
    "sg:phone":"+43 4364 327754",
    "sg:postcode":"5630",
    "sg:province":"Salzburg",
    "wof:name":"Radlachhof",
    "wof:placetype":"venue"
},
  "geometry": {"coordinates":[13.0994386673,47.1438674927],"type":"Point"}
}