{
  "type": "Feature",
  "properties": {
    "addr:full":"Rosa Jochmann-Ring 44 Wien Wien 1110",
    "addr:housenumber":"44",
    "addr:postcode":"1110",
    "iso:country":"AT",
    "sg:address":"Rosa Jochmann-Ring 44",
    "sg:city":"Wien",
    "sg:orig_category":"Behinderungen / Leben Mit Behinderungen",
    "sg:phone":"+43 1 7680224",
    "sg:postcode":"1110",
    "sg:province":"Wien",
    "wof:name":"Lebenshilfe Wien Verein f Menschen m geistiger und mehrfacher Behinderung",
    "wof:placetype":"venue"
},
  "geometry": {"coordinates":[16.4631404877,48.1526260376],"type":"Point"}
}