{
  "type": "Feature",
  "properties": {
    "addr:full":"Wiener G 26 Perchtoldsdorf Nieder\u00f6sterreich 2380",
    "addr:housenumber":"26",
    "addr:postcode":"2380",
    "addr:street":"Wiener G",
    "iso:country":"AT",
    "sg:address":"Wiener G 26",
    "sg:city":"Perchtoldsdorf",
    "sg:orig_category":"Tapezierer U Dekorateure",
    "sg:phone":"+43 4318 693588",
    "sg:postcode":"2380",
    "sg:province":"Nieder\u00f6sterreich",
    "wof:name":"Scheuer Manfred",
    "wof:placetype":"venue"
},
  "geometry": {"coordinates":[16.2673606873,48.1211585999],"type":"Point"}
}