{
  "type": "Feature",
  "properties": {
    "iso:country":"AT",
    "sg:address":"Helmholtzstr. 56 ",
    "sg:city":"Linz",
    "sg:classifiers":[
        {
            "category":"Shopping",
            "subcategory":"Computers & Home Electronics",
            "type":"Retail Goods"
        }
    ],
    "sg:phone":"+43 4373 2381681",
    "sg:postcode":"4020",
    "sg:province":"Ober\u00f6sterreich",
    "sg:tags":[
        "electronic",
        "electrical",
        "equipment"
    ],
    "wof:name":"DIPL. ING. HITZINGER GMBH",
    "wof:placetype":"venue"
},
  "geometry": {"coordinates":[14.2770652771,48.2566184998],"type":"Point"}
}