{
  "type": "Feature",
  "properties": {
    "addr:full":"Schulg 9 Seitenstetten Nieder\u00f6sterreich 3353",
    "addr:housenumber":"9",
    "addr:postcode":"3353",
    "addr:street":"Schulg",
    "iso:country":"AT",
    "sg:address":"Schulg 9",
    "sg:city":"Seitenstetten",
    "sg:orig_category":"Friseure U Frisiersalons",
    "sg:phone":"+43 7477 43505",
    "sg:postcode":"3353",
    "sg:province":"Nieder\u00f6sterreich",
    "wof:name":"PESCHKE KEG",
    "wof:placetype":"venue"
},
  "geometry": {"coordinates":[14.6517572403,48.035533905],"type":"Point"}
}