{
  "type": "Feature",
  "properties": {
    "addr:full":"Nr 11 Linz Ober\u00f6sterreich 4040",
    "addr:postcode":"4040",
    "addr:street":"Nr 11",
    "iso:country":"AT",
    "sg:address":"Nr 11",
    "sg:city":"Linz",
    "sg:orig_category":"Gartenpflege",
    "sg:phone":"+43 732 222577",
    "sg:postcode":"4040",
    "sg:province":"Ober\u00f6sterreich",
    "wof:name":"Burgstaller Bernhard Gartenpflege GmbH",
    "wof:placetype":"venue"
},
  "geometry": {"coordinates":[-88.00114440919999,45.4992752075],"type":"Point"}
}