{
  "type": "Feature",
  "properties": {
    "addr:full":"Wurzbachg 13 Wien Wien 1150",
    "addr:housenumber":"13",
    "addr:postcode":"1150",
    "addr:street":"Wurzbachg",
    "iso:country":"AT",
    "sg:address":"Wurzbachg 13",
    "sg:city":"Wien",
    "sg:orig_category":"Bauunternehmen",
    "sg:phone":"+43 1 7895208",
    "sg:postcode":"1150",
    "sg:province":"Wien",
    "wof:name":"Strasser S BaugesmbH",
    "wof:placetype":"venue"
},
  "geometry": {"coordinates":[16.3356342316,48.2030715942],"type":"Point"}
}