{
  "type": "Feature",
  "properties": {
    "iso:country":"AT",
    "sg:address":"Andreas Hofer-Str 40/2",
    "sg:city":"Innsbruck",
    "sg:orig_category":"Physiotherapie",
    "sg:phone":"+43 699 10587977",
    "sg:postcode":"6020",
    "sg:province":"Tirol",
    "wof:name":"Mair Paul",
    "wof:placetype":"venue"
},
  "geometry": {"coordinates":[11.3917045593,47.2570533752],"type":"Point"}
}