{
  "type": "Feature",
  "properties": {
    "addr:full":"Heinrich Gruber-Str 4 Traun Ober\u00f6sterreich 4050",
    "addr:housenumber":"4",
    "addr:postcode":"4050",
    "iso:country":"AT",
    "sg:address":"Heinrich Gruber-Str 4",
    "sg:city":"Traun",
    "sg:orig_category":"Friseure U Frisiersalons",
    "sg:phone":"+43 4372 297344815",
    "sg:postcode":"4050",
    "sg:province":"Ober\u00f6sterreich",
    "wof:name":"Ihr dm Friseur Studio",
    "wof:placetype":"venue"
},
  "geometry": {"coordinates":[14.2389249802,48.2202644348],"type":"Point"}
}