{
  "type": "Feature",
  "properties": {
    "addr:full":"Mariahilfstr. 45  Bregenz Vorarlberg 6900",
    "addr:housenumber":"45",
    "addr:postcode":"6900",
    "addr:street":"Mariahilfstr.",
    "iso:country":"AT",
    "sg:address":"Mariahilfstr. 45 ",
    "sg:city":"Bregenz",
    "sg:classifiers":[
        {
            "category":"Shopping",
            "subcategory":"Clothing, Apparel, & Fashions",
            "type":"Retail Goods"
        }
    ],
    "sg:phone":"+43 4355 7471792",
    "sg:postcode":"6900",
    "sg:province":"Vorarlberg",
    "sg:tags":[
        "clothes"
    ],
    "wof:name":"LEONHARD BASCHNEGGER OHG",
    "wof:placetype":"venue"
},
  "geometry": {"coordinates":[9.72701931,47.4940719604],"type":"Point"}
}