{
  "type": "Feature",
  "properties": {
    "iso:country":"AT",
    "sg:address":"Marktpl 14",
    "sg:city":"Dornbirn",
    "sg:orig_category":"Architekten",
    "sg:phone":"+43 4355 7223810",
    "sg:postcode":"6850",
    "sg:province":"Vorarlberg",
    "wof:name":"Architektur B\u00fcro Kirchmair",
    "wof:placetype":"venue"
},
  "geometry": {"coordinates":[9.7422103882,47.4135017395],"type":"Point"}
}