{
  "type": "Feature",
  "properties": {
    "iso:country":"AT",
    "sg:address":"Im Dorf",
    "sg:city":"Bregenz",
    "sg:orig_category":"Tabaktrafiken",
    "sg:phone":"+43 5574 47285",
    "sg:postcode":"6900",
    "sg:province":"Vorarlberg",
    "wof:name":"Hehle Veronika - Kiosk",
    "wof:placetype":"venue"
},
  "geometry": {"coordinates":[9.7445011139,47.4972991943],"type":"Point"}
}