{
  "type": "Feature",
  "properties": {
    "iso:country":"AT",
    "sg:address":"Gegend 66",
    "sg:city":"Rohr im Gebirge",
    "sg:orig_category":"Stukkateure U Trockenausbauer",
    "sg:phone":"+43 4326 678524",
    "sg:postcode":"2663",
    "sg:province":"Nieder\u00f6sterreich",
    "wof:name":"Aigner Josef",
    "wof:placetype":"venue"
},
  "geometry": {"coordinates":[15.7186746597,47.8893280029],"type":"Point"}
}