{
  "type": "Feature",
  "properties": {
    "iso:country":"AT",
    "sg:address":"Rinnb\u00f6ckstr 32",
    "sg:city":"Wien",
    "sg:orig_category":"Juweliere, Gold- U Silberschmiede",
    "sg:phone":"+43 4317 493409",
    "sg:postcode":"1110",
    "sg:province":"Wien",
    "wof:name":"Dworak Christian",
    "wof:placetype":"venue"
},
  "geometry": {"coordinates":[16.4197444916,48.1709709167],"type":"Point"}
}