{
  "type": "Feature",
  "properties": {
    "addr:full":"Kiefernweg 17 F\u00fcrnitz K\u00e4rnten 9586",
    "addr:housenumber":"17",
    "addr:postcode":"9586",
    "addr:street":"Kiefernweg;Kaernten",
    "iso:country":"AT",
    "sg:address":"Kiefernweg 17",
    "sg:city":"F\u00fcrnitz",
    "sg:orig_category":"Rauchfangkehrer",
    "sg:phone":"+43 4257 2123",
    "sg:postcode":"9586",
    "sg:province":"K\u00e4rnten",
    "wof:name":"K\u00f6lbl Hannes",
    "wof:placetype":"venue"
},
  "geometry": {"coordinates":[13.7856426239,46.566318512],"type":"Point"}
}