{
  "type": "Feature",
  "properties": {
    "addr:full":"Linke Wienzeile 40/19 Wien Wien 1060",
    "addr:housenumber":"40 / 19",
    "addr:postcode":"1060",
    "addr:street":"Linke Wienzeile",
    "iso:country":"AT",
    "sg:address":"Linke Wienzeile 40/19",
    "sg:city":"Wien",
    "sg:classifiers":[
        {
            "category":"Banks & Credit Unions",
            "subcategory":"Investment Brokerage",
            "type":"Services"
        }
    ],
    "sg:phone":"+43 1 5855757401",
    "sg:postcode":"1060",
    "sg:province":"Wien",
    "sg:tags":[
        "football",
        "gear",
        "accessory"
    ],
    "sg:website":"sportzeitung.at",
    "wof:name":"SPORTZEITUNG Verlags-GmbH",
    "wof:placetype":"venue"
},
  "geometry": {"coordinates":[16.3591861725,48.1974067688],"type":"Point"}
}