{
  "type": "Feature",
  "properties": {
    "addr:full":"Naarner Str 31 Perg Ober\u00f6sterreich 4320",
    "addr:postcode":"4320",
    "addr:street":"Str;Oberoesterreich",
    "iso:country":"AT",
    "sg:address":"Naarner Str 31",
    "sg:city":"Perg",
    "sg:orig_category":"Immobilienverwaltungen",
    "sg:phone":"+43 7262 521920",
    "sg:postcode":"4320",
    "sg:province":"Ober\u00f6sterreich",
    "wof:name":"EHI Immobilien GesmbH & Co KG",
    "wof:placetype":"venue"
},
  "geometry": {"coordinates":[14.6301603317,48.2471427917],"type":"Point"}
}