{
  "type": "Feature",
  "properties": {
    "addr:full":"Rotes Kreuz-G 1 Baden Nieder\u00f6sterreich 2500",
    "addr:housenumber":"1",
    "addr:postcode":"2500",
    "addr:street":"Niederoesterreich",
    "iso:country":"AT",
    "sg:address":"Rotes Kreuz-G 1",
    "sg:city":"Baden",
    "sg:orig_category":"Feuerwehren",
    "sg:phone":"+43 2252 822220",
    "sg:postcode":"2500",
    "sg:province":"Nieder\u00f6sterreich",
    "wof:name":"Freiwillige Feuerwehren d Stadt Baden - Feuerwehrbezirksnachrichtenzentrale",
    "wof:placetype":"venue"
},
  "geometry": {"coordinates":[16.2543983459,48.0018386841],"type":"Point"}
}