{
  "type": "Feature",
  "properties": {
    "addr:full":"Linzer Str 3 Melk Nieder\u00f6sterreich 3390",
    "addr:housenumber":"3",
    "addr:postcode":"3390",
    "addr:street":"Linzer Str",
    "iso:country":"AT",
    "sg:address":"Linzer Str 3",
    "sg:city":"Melk",
    "sg:orig_category":"Gesundheitsvorsorge",
    "sg:phone":"+43 2752 53888",
    "sg:postcode":"3390",
    "sg:province":"Nieder\u00f6sterreich",
    "wof:name":"Norek Dr und Galerie Norek",
    "wof:placetype":"venue"
},
  "geometry": {"coordinates":[15.3289747238,48.226764679],"type":"Point"}
}