{
  "type": "Feature",
  "properties": {
    "addr:full":"Pfarrhofstr 1 Burgkirchen Ober\u00f6sterreich 5274",
    "addr:housenumber":"1",
    "addr:postcode":"5274",
    "addr:street":"Pfarrhofstr",
    "iso:country":"AT",
    "sg:address":"Pfarrhofstr 1",
    "sg:city":"Burgkirchen",
    "sg:orig_category":"Non-Classified Establishments",
    "sg:phone":"+43 7724 22130",
    "sg:postcode":"5274",
    "sg:province":"Ober\u00f6sterreich",
    "wof:name":"Pfarramt",
    "wof:placetype":"venue"
},
  "geometry": {"coordinates":[13.0995197296,48.2032356262],"type":"Point"}
}