{
  "type": "Feature",
  "properties": {
    "addr:full":"Hackherg 22 Graz Steiermark 8020",
    "addr:housenumber":"22",
    "addr:postcode":"8020",
    "addr:street":"Hackherg",
    "iso:country":"AT",
    "sg:address":"Hackherg 22",
    "sg:city":"Graz",
    "sg:orig_category":"Friseure U Frisiersalons",
    "sg:phone":"+43 316 683423",
    "sg:postcode":"8020",
    "sg:province":"Steiermark",
    "wof:name":"Wonisch Evelyn",
    "wof:placetype":"venue"
},
  "geometry": {"coordinates":[15.420665741,47.0826950073],"type":"Point"}
}