{
  "type": "Feature",
  "properties": {
    "iso:country":"AT",
    "sg:address":"Nr 91",
    "sg:city":"Bad Goisern",
    "sg:orig_category":"Musikgruppen",
    "sg:phone":"+43 4366 44220242",
    "sg:postcode":"4822",
    "sg:province":"Ober\u00f6sterreich",
    "wof:name":"Duo Soundmix",
    "wof:placetype":"venue"
},
  "geometry": {"coordinates":[13.6164741516,47.6411628723],"type":"Point"}
}