{
  "type": "Feature",
  "properties": {
    "addr:full":"Hauptstr 9 W\u00fcrmla Nieder\u00f6sterreich 3042",
    "addr:housenumber":"9",
    "addr:postcode":"3042",
    "addr:street":"Hauptstr;Niederoesterreich",
    "iso:country":"AT",
    "sg:address":"Hauptstr 9",
    "sg:city":"W\u00fcrmla",
    "sg:orig_category":"Lebensmittel / Einzelhandel",
    "sg:phone":"+43 2275 8518",
    "sg:postcode":"3042",
    "sg:province":"Nieder\u00f6sterreich",
    "wof:name":"Kratschmar Elisabeth",
    "wof:placetype":"venue"
},
  "geometry": {"coordinates":[4.438521862,51.9283103943],"type":"Point"}
}