{
  "type": "Feature",
  "properties": {
    "addr:full":"Keimweg 3 Wernstein am Inn Ober\u00f6sterreich 4783",
    "addr:housenumber":"3",
    "addr:postcode":"4783",
    "addr:street":"Keimweg",
    "iso:country":"AT",
    "sg:address":"Keimweg 3",
    "sg:city":"Wernstein am Inn",
    "sg:classifiers":[
        {
            "category":"Retail",
            "subcategory":"Animal Services",
            "type":"Services"
        }
    ],
    "sg:phone":"+43 7713 60620",
    "sg:postcode":"4783",
    "sg:province":"Ober\u00f6sterreich",
    "sg:tags":[
        "trap"
    ],
    "sg:website":"keim.cc",
    "wof:name":"Keim GmbH & Co KG",
    "wof:placetype":"venue"
},
  "geometry": {"coordinates":[13.4645051956,48.5049514771],"type":"Point"}
}