{
  "type": "Feature",
  "properties": {
    "addr:full":"B\u00f6rseplatz 6 Wien Wien 1010",
    "addr:housenumber":"6",
    "addr:postcode":"1010",
    "addr:street":"Boerseplatz",
    "iso:country":"AT",
    "sg:address":"B\u00f6rseplatz 6",
    "sg:city":"Wien",
    "sg:classifiers":[
        {
            "category":"Professional",
            "subcategory":"Management & Consulting",
            "type":"Services"
        }
    ],
    "sg:phone":"+43 1 5339302",
    "sg:postcode":"1010",
    "sg:province":"Wien",
    "sg:tags":[
        "hr",
        "resource",
        "consultancy",
        "human"
    ],
    "sg:website":"inter-work.at",
    "wof:name":"Inter-Work B\u00fcrodienstleistung Ges.mb.H. & Co KG",
    "wof:placetype":"venue"
},
  "geometry": {"coordinates":[16.3688049316,48.2025489807],"type":"Point"}
}