{
  "type": "Feature",
  "properties": {
    "addr:full":"Hauptpl 34 Gols Burgenland 7122",
    "addr:housenumber":"34",
    "addr:postcode":"7122",
    "addr:street":"Hauptpl",
    "iso:country":"AT",
    "sg:address":"Hauptpl 34",
    "sg:city":"Gols",
    "sg:orig_category":"Non-Classified Establishments",
    "sg:phone":"+43 2173 2312",
    "sg:postcode":"7122",
    "sg:province":"Burgenland",
    "wof:name":"Pfarramt",
    "wof:placetype":"venue"
},
  "geometry": {"coordinates":[16.9074115753,47.8972663879],"type":"Point"}
}