{
  "type": "Feature",
  "properties": {
    "iso:country":"AT",
    "sg:address":"Forchtenauer Str 99",
    "sg:city":"Mattersburg",
    "sg:orig_category":"Polizei U Gendarmerie",
    "sg:phone":"+43 4359 1331122",
    "sg:postcode":"7210",
    "sg:province":"Burgenland",
    "wof:name":"Autobahngendarmerie Mattersburg",
    "wof:placetype":"venue"
},
  "geometry": {"coordinates":[16.3769569397,47.7198562622],"type":"Point"}
}