{
  "type": "Feature",
  "properties": {
    "iso:country":"AT",
    "sg:address":"Georg Sigl-Str 6",
    "sg:city":"Breitenfurt",
    "sg:orig_category":"Schneidereien",
    "sg:phone":"+43 2239 4114",
    "sg:postcode":"2384",
    "sg:province":"Nieder\u00f6sterreich",
    "wof:name":"Weiser Maria",
    "wof:placetype":"venue"
},
  "geometry": {"coordinates":[16.1939239502,48.1367797852],"type":"Point"}
}