{
  "type": "Feature",
  "properties": {
    "iso:country":"AT",
    "sg:address":"Siehdichf\u00fcrstrasse 23",
    "sg:city":"Strasshof an der Nordbahn",
    "sg:classifiers":[
        {
            "category":"Home & Garden",
            "subcategory":"Building Materials",
            "type":"Retail Goods"
        }
    ],
    "sg:phone":"+43 2287 2345",
    "sg:postcode":"2231",
    "sg:province":"Nieder\u00f6sterreich",
    "sg:tags":[
        "railing",
        "balcony"
    ],
    "wof:name":"Thomas Horzynek",
    "wof:placetype":"venue"
},
  "geometry": {"coordinates":[16.6106395721,48.3223457336],"type":"Point"}
}