{
  "type": "Feature",
  "properties": {
    "addr:full":"Puckinger Str 5 Pucking Ober\u00f6sterreich 4055",
    "addr:housenumber":"5",
    "addr:postcode":"4055",
    "addr:street":"Str",
    "iso:country":"AT",
    "sg:address":"Puckinger Str 5",
    "sg:city":"Pucking",
    "sg:orig_category":"Gemeinden",
    "sg:phone":"+43 7229 889110",
    "sg:postcode":"4055",
    "sg:province":"Ober\u00f6sterreich",
    "wof:name":"Gemeindeamt Pucking",
    "wof:placetype":"venue"
},
  "geometry": {"coordinates":[14.1853437424,48.1889915466],"type":"Point"}
}