{
  "type": "Feature",
  "properties": {
    "iso:country":"AT",
    "sg:address":"Hainfelder Str 22",
    "sg:city":"Berndorf",
    "sg:orig_category":"Bestattungsunternehmen",
    "sg:phone":"+43 2672 82510",
    "sg:postcode":"2560",
    "sg:province":"Nieder\u00f6sterreich",
    "wof:name":"Bestattung Birbamer",
    "wof:placetype":"venue"
},
  "geometry": {"coordinates":[16.1086750031,47.9476699829],"type":"Point"}
}