{
  "type": "Feature",
  "properties": {
    "addr:full":"Neudorfer Str 12 Leoben Steiermark 8700",
    "addr:housenumber":"12",
    "addr:postcode":"8700",
    "addr:street":"Str",
    "iso:country":"AT",
    "sg:address":"Neudorfer Str 12",
    "sg:city":"Leoben",
    "sg:classifiers":[
        {
            "category":"Taxi",
            "type":"Transportation"
        }
    ],
    "sg:phone":"+43 3842 208",
    "sg:postcode":"8700",
    "sg:province":"Steiermark",
    "sg:tags":[
        "personentransporte",
        "u"
    ],
    "wof:name":"Brotbeil Johann",
    "wof:placetype":"venue"
},
  "geometry": {"coordinates":[15.0859260559,47.3809509277],"type":"Point"}
}