{
  "type": "Feature",
  "properties": {
    "addr:full":"Zemannstr 14 Freistadt Ober\u00f6sterreich 4240",
    "addr:housenumber":"14",
    "addr:postcode":"4240",
    "addr:street":"Zemannstr",
    "iso:country":"AT",
    "sg:address":"Zemannstr 14",
    "sg:city":"Freistadt",
    "sg:orig_category":"Volkshochschulen",
    "sg:phone":"+43 7942 749597083",
    "sg:postcode":"4240",
    "sg:province":"Ober\u00f6sterreich",
    "wof:name":"Volkshochschule Freistadt Zweigstelle",
    "wof:placetype":"venue"
},
  "geometry": {"coordinates":[14.5038566589,48.5079116821],"type":"Point"}
}