{
  "type": "Feature",
  "properties": {
    "iso:country":"AT",
    "sg:address":"Thermenstr 34",
    "sg:city":"Geinberg",
    "sg:orig_category":"Volksschulen",
    "sg:phone":"+43 7723 815516",
    "sg:postcode":"4943",
    "sg:province":"Ober\u00f6sterreich",
    "wof:name":"Volksschule Geinberg",
    "wof:placetype":"venue"
},
  "geometry": {"coordinates":[13.2955541611,48.2638969421],"type":"Point"}
}