{
  "type": "Feature",
  "properties": {
    "addr:full":"Schoren 2 Dornbirn Vorarlberg 6850",
    "addr:housenumber":"2",
    "addr:postcode":"6850",
    "addr:street":"Schoren",
    "iso:country":"AT",
    "sg:address":"Schoren 2",
    "sg:city":"Dornbirn",
    "sg:orig_category":"Banken U Sparkassen",
    "sg:phone":"+43 4355 72217270",
    "sg:postcode":"6850",
    "sg:province":"Vorarlberg",
    "wof:name":"Raiffeisenbank Dornbirn regGenmbH",
    "wof:placetype":"venue"
},
  "geometry": {"coordinates":[9.7282943726,47.4091110229],"type":"Point"}
}