{
  "type": "Feature",
  "properties": {
    "iso:country":"AT",
    "sg:address":"Sparbersbachg 56",
    "sg:city":"Graz",
    "sg:orig_category":"Friseure U Frisiersalons",
    "sg:phone":"+43 4331 6848042",
    "sg:postcode":"8010",
    "sg:province":"Steiermark",
    "wof:name":"Haarmode Karin Inh Karin Jeitler",
    "wof:placetype":"venue"
},
  "geometry": {"coordinates":[15.4542551041,47.0694694519],"type":"Point"}
}