{
  "type": "Feature",
  "properties": {
    "iso:country":"AT",
    "sg:address":"Linzer Str 261",
    "sg:city":"Wien",
    "sg:orig_category":"Stoffe / Erzeugung U Gro\u00c3\u0178handel",
    "sg:phone":"+43 4319 125540",
    "sg:postcode":"1140",
    "sg:province":"Wien",
    "wof:name":"Stoffparadies LEO",
    "wof:placetype":"venue"
},
  "geometry": {"coordinates":[16.2824401855,48.1952667236],"type":"Point"}
}