{
  "type": "Feature",
  "properties": {
    "iso:country":"AT",
    "sg:address":"Dorfstr 23",
    "sg:city":"Kolsass",
    "sg:orig_category":"Lebensmittel / Einzelhandel",
    "sg:phone":"+43 5224 68217",
    "sg:postcode":"6114",
    "sg:province":"Tirol",
    "wof:name":"Braunegger KG",
    "wof:placetype":"venue"
},
  "geometry": {"coordinates":[11.6426687241,47.3025016785],"type":"Point"}
}