{
  "type": "Feature",
  "properties": {
    "addr:full":"Hauptstr 48 Eggendorf Nieder\u00f6sterreich 2492",
    "addr:housenumber":"48",
    "addr:postcode":"2492",
    "addr:street":"Hauptstr",
    "iso:country":"AT",
    "sg:address":"Hauptstr 48",
    "sg:city":"Eggendorf",
    "sg:orig_category":"Friseure U Frisiersalons",
    "sg:phone":"+43 4326 2273258",
    "sg:postcode":"2492",
    "sg:province":"Nieder\u00f6sterreich",
    "wof:name":"Frisiersalon Stefan",
    "wof:placetype":"venue"
},
  "geometry": {"coordinates":[8.1344404221,49.3539199829],"type":"Point"}
}