{
  "type": "Feature",
  "properties": {
    "addr:full":"Mitterwei\u00dfenbach 16 Bad Ischl Ober\u00f6sterreich 4820",
    "addr:housenumber":"16",
    "addr:postcode":"4820",
    "addr:street":"Mitterweissenbach",
    "iso:country":"AT",
    "sg:address":"Mitterwei\u00dfenbach 16",
    "sg:city":"Bad Ischl",
    "sg:orig_category":"Tonstudios",
    "sg:phone":"+43 664 4615609",
    "sg:postcode":"4820",
    "sg:province":"Ober\u00f6sterreich",
    "wof:name":"Roland's Tennleuw\u00f6 Licht + Tonanlagen",
    "wof:placetype":"venue"
},
  "geometry": {"coordinates":[13.6257123947,47.711971283],"type":"Point"}
}