{
  "type": "Feature",
  "properties": {
    "addr:full":"Wiedner Hauptstr 75 Wien Wien 1040",
    "addr:housenumber":"75",
    "addr:postcode":"1040",
    "addr:street":"Hauptstr",
    "iso:country":"AT",
    "sg:address":"Wiedner Hauptstr 75",
    "sg:city":"Wien",
    "sg:orig_category":"Weinstuben",
    "sg:phone":"+43 1 5052650",
    "sg:postcode":"1040",
    "sg:province":"Wien",
    "wof:name":"WINZIG",
    "wof:placetype":"venue"
},
  "geometry": {"coordinates":[16.3652114868,48.1885147095],"type":"Point"}
}