{
  "type": "Feature",
  "properties": {
    "iso:country":"AT",
    "sg:address":"Fichtenstr. 7",
    "sg:city":"Linz",
    "sg:classifiers":[
        {
            "category":"Utilities",
            "subcategory":"Electric",
            "type":"Services"
        }
    ],
    "sg:phone":"+43 4373 234000",
    "sg:postcode":"4020",
    "sg:province":"Ober\u00f6sterreich",
    "sg:tags":[
        "electricity"
    ],
    "wof:name":"LINZ AG F\u00dcR ENERGIE TELEKOMMUNIKATION VERKEHR U. KOMMUNALE DIENSTE",
    "wof:placetype":"venue"
},
  "geometry": {"coordinates":[14.3117418289,48.2808685303],"type":"Point"}
}