{
  "type": "Feature",
  "properties": {
    "addr:full":"Fischbach 61 Abtenau Salzburg 5441",
    "addr:housenumber":"61",
    "addr:postcode":"5441",
    "addr:street":"Fischbach;Salzburg",
    "iso:country":"AT",
    "sg:address":"Fischbach 61",
    "sg:city":"Abtenau",
    "sg:orig_category":"Pensionen / Privatzimmer",
    "sg:phone":"+43 6243 24230",
    "sg:postcode":"5441",
    "sg:province":"Salzburg",
    "wof:name":"G\u00e4stehaus Lanzinger",
    "wof:placetype":"venue"
},
  "geometry": {"coordinates":[13.363363266,47.560710907],"type":"Point"}
}