{
  "type": "Feature",
  "properties": {
    "iso:country":"AT",
    "sg:address":"Dr.-Theodor-K\u00f6rner-Str 13",
    "sg:city":"Bruck an der Mur",
    "sg:orig_category":"Telekommunikation",
    "sg:phone":"+43 4338 6281221",
    "sg:postcode":"8600",
    "sg:province":"Steiermark",
    "wof:name":"Beecom.cc Handels-GmbH",
    "wof:placetype":"venue"
},
  "geometry": {"coordinates":[15.2671146393,47.4091110229],"type":"Point"}
}