{
  "type": "Feature",
  "properties": {
    "iso:country":"AT",
    "sg:address":"Nr 47",
    "sg:city":"St. Koloman",
    "sg:orig_category":"Elektroinstallationsunternehmen",
    "sg:phone":"+43 6241 387",
    "sg:postcode":"5423",
    "sg:province":"Salzburg",
    "wof:name":"Rettenbacher Rupert Elektrotechniker Hinterseewald",
    "wof:placetype":"venue"
},
  "geometry": {"coordinates":[13.2037801743,47.6428451538],"type":"Point"}
}