{
  "type": "Feature",
  "properties": {
    "addr:full":"Havannaweg 4 Wien Wien 1220",
    "addr:housenumber":"4",
    "addr:postcode":"1220",
    "addr:street":"Havannaweg",
    "iso:country":"AT",
    "sg:address":"Havannaweg 4",
    "sg:city":"Wien",
    "sg:orig_category":"Solaranlagen",
    "sg:phone":"+43 1 2808477",
    "sg:postcode":"1220",
    "sg:province":"Wien",
    "wof:name":"Chabek Rudolf - Hausstechnik Service",
    "wof:placetype":"venue"
},
  "geometry": {"coordinates":[16.4727611542,48.1980056763],"type":"Point"}
}