{
  "type": "Feature",
  "properties": {
    "addr:full":"Erdbergstr 202/1. OG/P&R U3 Wien Wien 1030",
    "addr:housenumber":"202 / 1 og;p",
    "addr:postcode":"1030",
    "addr:street":"/;U3",
    "iso:country":"AT",
    "sg:address":"Erdbergstr 202/1. OG/P&R U3",
    "sg:city":"Wien",
    "sg:orig_category":"Autovermietung",
    "sg:phone":"+43 1 7996176",
    "sg:postcode":"1030",
    "sg:province":"Wien",
    "wof:name":"DENZELDRIVE Carsharing GmbH - Wien-Stadt",
    "wof:placetype":"venue"
},
  "geometry": {"coordinates":[16.4153747559,48.1902046204],"type":"Point"}
}