{
  "type": "Feature",
  "properties": {
    "addr:full":"Trappelg 11 Wien Wien 1040",
    "addr:housenumber":"11",
    "addr:postcode":"1040",
    "addr:street":"Trappelg",
    "iso:country":"AT",
    "sg:address":"Trappelg 11",
    "sg:city":"Wien",
    "sg:orig_category":"Weiterbildungsinstitute M Allg U Berufl Bildungsangebot",
    "sg:phone":"+43 4315 054234",
    "sg:postcode":"1040",
    "sg:province":"Wien",
    "sg:website":"masteroftraining.com",
    "wof:name":"Institut f Kommunikations- Konfliktp\u00e4dagogik u Coaching, Lenzenweger Hermann, MAS",
    "wof:placetype":"venue"
},
  "geometry": {"coordinates":[16.3671455383,48.1940345764],"type":"Point"}
}