{
  "type": "Feature",
  "properties": {
    "addr:full":"Gegend 2 Schwarzau im Gebirge Nieder\u00f6sterreich 2662",
    "addr:housenumber":"2",
    "addr:postcode":"2662",
    "addr:street":"Gegend",
    "iso:country":"AT",
    "sg:address":"Gegend 2",
    "sg:city":"Schwarzau im Gebirge",
    "sg:orig_category":"Pensionen / Privatzimmer",
    "sg:phone":"+43 2667 240",
    "sg:postcode":"2662",
    "sg:province":"Nieder\u00f6sterreich",
    "wof:name":"Fr\u00fchst\u00fcckspension Gscheiderwirt",
    "wof:placetype":"venue"
},
  "geometry": {"coordinates":[15.7038021088,47.8127593994],"type":"Point"}
}