{
  "type": "Feature",
  "properties": {
    "addr:full":"Kitzb\u00fcheler Str 88 Kirchberg in Tirol Tirol 6365",
    "addr:housenumber":"88",
    "addr:postcode":"6365",
    "addr:street":"Str;Tirol",
    "iso:country":"AT",
    "sg:address":"Kitzb\u00fcheler Str 88",
    "sg:city":"Kirchberg in Tirol",
    "sg:orig_category":"Pensionen / Privatzimmer",
    "sg:phone":"+43 4353 572508",
    "sg:postcode":"6365",
    "sg:province":"Tirol",
    "wof:name":"G\u00e4stehaus Johanna",
    "wof:placetype":"venue"
},
  "geometry": {"coordinates":[12.3149347305,47.4481468201],"type":"Point"}
}