{
  "type": "Feature",
  "properties": {
    "iso:country":"AT",
    "sg:address":"Kapellenweg 1",
    "sg:city":"Au",
    "sg:orig_category":"Volkshochschulen",
    "sg:phone":"+43 4372 6254270",
    "sg:postcode":"4332",
    "sg:province":"Ober\u00f6sterreich",
    "wof:name":"Volkshochschule Naarn/Au",
    "wof:placetype":"venue"
},
  "geometry": {"coordinates":[14.5844583511,48.2259712219],"type":"Point"}
}