{
  "type": "Feature",
  "properties": {
    "addr:full":"Ennstaler Bundesstr Trautenfels Steiermark 8951",
    "addr:postcode":"8951",
    "iso:country":"AT",
    "sg:address":"Ennstaler Bundesstr",
    "sg:city":"Trautenfels",
    "sg:orig_category":"Tankstellen",
    "sg:phone":"+43 3682 22262",
    "sg:postcode":"8951",
    "sg:province":"Steiermark",
    "wof:name":"AVANTI TankstellenbetriebsgesmbH",
    "wof:placetype":"venue"
},
  "geometry": {"coordinates":[14.0831203461,47.5187416077],"type":"Point"}
}