{
  "type": "Feature",
  "properties": {
    "addr:full":"Johannespl 6 Lienz Tirol 9900",
    "addr:housenumber":"6",
    "addr:postcode":"9900",
    "addr:street":"Johannespl;Tirol",
    "iso:country":"AT",
    "sg:address":"Johannespl 6",
    "sg:city":"Lienz",
    "sg:orig_category":"Banken U Sparkassen",
    "sg:phone":"+43 4348 526020",
    "sg:postcode":"9900",
    "sg:province":"Tirol",
    "wof:name":"Bankomat d Lienzer Sparkasse",
    "wof:placetype":"venue"
},
  "geometry": {"coordinates":[12.7666425705,46.8297195435],"type":"Point"}
}