{
  "type": "Feature",
  "properties": {
    "addr:full":"Wiener Str 69 Horn Nieder\u00f6sterreich 3580",
    "addr:housenumber":"69",
    "addr:postcode":"3580",
    "addr:street":"Horn Niederoesterreich",
    "iso:country":"AT",
    "sg:address":"Wiener Str 69",
    "sg:city":"Horn",
    "sg:orig_category":"Bars-Cafes",
    "sg:phone":"+43 2982 2979",
    "sg:postcode":"3580",
    "sg:province":"Nieder\u00f6sterreich",
    "wof:name":"Gleisbar",
    "wof:placetype":"venue"
},
  "geometry": {"coordinates":[15.6669988632,48.6636657715],"type":"Point"}
}