{
  "type": "Feature",
  "properties": {
    "addr:full":"Kaunitzg 33 Wien Wien 1060",
    "addr:housenumber":"33",
    "addr:postcode":"1060",
    "addr:street":"Kaunitzg",
    "iso:country":"AT",
    "sg:address":"Kaunitzg 33",
    "sg:city":"Wien",
    "sg:orig_category":"Ingenieurkonsulenten / Zivilingenieure",
    "sg:phone":"+43 1 5878531",
    "sg:postcode":"1060",
    "sg:province":"Wien",
    "wof:name":"Wiesbauer Heinz Dipl-Ing",
    "wof:placetype":"venue"
},
  "geometry": {"coordinates":[16.3535480499,48.1957206726],"type":"Point"}
}