{
  "type": "Feature",
  "properties": {
    "addr:full":"Grafenwaldweg 12 Klaus-Weiler Vorarlberg 6833",
    "addr:housenumber":"12",
    "addr:postcode":"6833",
    "addr:street":"Grafenwaldweg",
    "iso:country":"AT",
    "sg:address":"Grafenwaldweg 12",
    "sg:city":"Klaus-Weiler",
    "sg:orig_category":"Handelsagenturen",
    "sg:phone":"+43 5523 58933",
    "sg:postcode":"6833",
    "sg:province":"Vorarlberg",
    "wof:name":"CNC-Technik",
    "wof:placetype":"venue"
},
  "geometry": {"coordinates":[9.6248703003,47.3102607727],"type":"Point"}
}