{
  "type": "Feature",
  "properties": {
    "iso:country":"AT",
    "sg:address":"Nr 39",
    "sg:city":"Scheifling",
    "sg:orig_category":"Stahlbau",
    "sg:phone":"+43 3582 22080",
    "sg:postcode":"8811",
    "sg:province":"Steiermark",
    "wof:name":"Zeman & Co GesmbH",
    "wof:placetype":"venue"
},
  "geometry": {"coordinates":[14.4103889465,47.1504631042],"type":"Point"}
}