{
  "type": "Feature",
  "properties": {
    "addr:full":"Steyrtalstr 38 Neuzeug Ober\u00f6sterreich 4523",
    "addr:housenumber":"38",
    "addr:postcode":"4523",
    "addr:street":"Steyrtalstr",
    "iso:country":"AT",
    "sg:address":"Steyrtalstr 38",
    "sg:city":"Neuzeug",
    "sg:orig_category":"Natursteine U -Platten",
    "sg:phone":"+43 7259 32493",
    "sg:postcode":"4523",
    "sg:province":"Ober\u00f6sterreich",
    "wof:name":"P\u00fchringer Gerhard",
    "wof:placetype":"venue"
},
  "geometry": {"coordinates":[14.3318452835,48.0453338623],"type":"Point"}
}