{
  "type": "Feature",
  "properties": {
    "addr:full":"Kramerg 1 Klagenfurt K\u00e4rnten 9020",
    "addr:housenumber":"1",
    "addr:postcode":"9020",
    "addr:street":"Kramerg;Kaernten",
    "iso:country":"AT",
    "sg:address":"Kramerg 1",
    "sg:city":"Klagenfurt",
    "sg:classifiers":[
        {
            "category":"Restaurant",
            "type":"Food & Drink"
        }
    ],
    "sg:phone":"+43 463 511483",
    "sg:postcode":"9020",
    "sg:province":"K\u00e4rnten",
    "wof:name":"Nordsee GesmbH",
    "wof:placetype":"venue"
},
  "geometry": {"coordinates":[14.3072652817,46.6243972778],"type":"Point"}
}