{
  "type": "Feature",
  "properties": {
    "addr:full":"Kirchenpl 1 Feld am See K\u00e4rnten 9544",
    "addr:housenumber":"1",
    "addr:postcode":"9544",
    "addr:street":"Kirchenpl;Kaernten",
    "iso:country":"AT",
    "sg:address":"Kirchenpl 1",
    "sg:city":"Feld am See",
    "sg:classifiers":[
        {
            "category":"Travel",
            "subcategory":"Hotels & Motels",
            "type":"Entertainment"
        }
    ],
    "sg:phone":"+43 4246 22760",
    "sg:postcode":"9544",
    "sg:province":"K\u00e4rnten",
    "wof:name":"Hotel Alte Post",
    "wof:placetype":"venue"
},
  "geometry": {"coordinates":[13.7461795807,46.775894165],"type":"Point"}
}