{
  "type": "Feature",
  "properties": {
    "addr:full":"Torfweg 7 Dornbirn Vorarlberg 6850",
    "addr:housenumber":"7",
    "addr:postcode":"6850",
    "addr:street":"Torfweg",
    "iso:country":"AT",
    "sg:address":"Torfweg 7",
    "sg:city":"Dornbirn",
    "sg:orig_category":"Handelsagenturen",
    "sg:phone":"+43 5572 21734",
    "sg:postcode":"6850",
    "sg:province":"Vorarlberg",
    "wof:name":"Rein Siegfried",
    "wof:placetype":"venue"
},
  "geometry": {"coordinates":[9.7309865952,47.4284095764],"type":"Point"}
}