{
  "type": "Feature",
  "properties": {
    "addr:full":"Grazer Str 85 Wiener Neustadt Nieder\u00f6sterreich 2700",
    "addr:postcode":"2700",
    "addr:street":"Str 85",
    "iso:country":"AT",
    "sg:address":"Grazer Str 85",
    "sg:city":"Wiener Neustadt",
    "sg:orig_category":"Immobilienverwaltungen",
    "sg:phone":"+43 2622 22643",
    "sg:postcode":"2700",
    "sg:province":"Nieder\u00f6sterreich",
    "wof:name":"Amon Gertrude",
    "wof:placetype":"venue"
},
  "geometry": {"coordinates":[16.2457561493,47.8130950928],"type":"Point"}
}