{
  "type": "Feature",
  "properties": {
    "addr:full":"Sonnberg 74 H\u00fcttau Salzburg 5511",
    "addr:housenumber":"74;5511",
    "addr:street":"Sonnberg",
    "iso:country":"AT",
    "sg:address":"Sonnberg 74",
    "sg:city":"H\u00fcttau",
    "sg:orig_category":"\u00c3\u201erzte / F Allgemeinmedizin",
    "sg:phone":"+43 6458 7155",
    "sg:postcode":"5511",
    "sg:province":"Salzburg",
    "wof:name":"Eppenschwandtner Gerhard Dr",
    "wof:placetype":"venue"
},
  "geometry": {"coordinates":[13.3277597427,47.4194602966],"type":"Point"}
}