{
  "type": "Feature",
  "properties": {
    "addr:full":"Hauptpl 7 St. Veit an der Glan K\u00e4rnten 9300",
    "addr:housenumber":"7",
    "addr:postcode":"9300",
    "addr:street":"Hauptpl;Kaernten",
    "iso:country":"AT",
    "sg:address":"Hauptpl 7",
    "sg:city":"St. Veit an der Glan",
    "sg:orig_category":"Juweliere, Gold- U Silberschmiede",
    "sg:phone":"+43 4342 122797",
    "sg:postcode":"9300",
    "sg:province":"K\u00e4rnten",
    "wof:name":"Juwelier Woschank",
    "wof:placetype":"venue"
},
  "geometry": {"coordinates":[14.3585329056,46.7675437927],"type":"Point"}
}