{
  "type": "Feature",
  "properties": {
    "addr:full":"Liechtensteiner Str 94a Feldkirch Vorarlberg 6800",
    "addr:postcode":"6800",
    "addr:street":"Str 94A",
    "iso:country":"AT",
    "sg:address":"Liechtensteiner Str 94a",
    "sg:city":"Feldkirch",
    "sg:orig_category":"Friseure U Frisiersalons",
    "sg:phone":"+43 4355 2274272",
    "sg:postcode":"6800",
    "sg:province":"Vorarlberg",
    "wof:name":"Frisierstudio Hair Radi",
    "wof:placetype":"venue"
},
  "geometry": {"coordinates":[9.5967845917,47.2381515503],"type":"Point"}
}