{
  "type": "Feature",
  "properties": {
    "addr:full":"Hauptstr 64 Neulengbach Nieder\u00f6sterreich 3040",
    "addr:housenumber":"64",
    "addr:postcode":"3040",
    "addr:street":"Hauptstr",
    "iso:country":"AT",
    "sg:address":"Hauptstr 64",
    "sg:city":"Neulengbach",
    "sg:orig_category":"Banken U Sparkassen",
    "sg:phone":"+43 2772 533140",
    "sg:postcode":"3040",
    "sg:province":"Nieder\u00f6sterreich",
    "wof:name":"Volksbank Nieder\u00f6sterreich-Mitte regGenmbH",
    "wof:placetype":"venue"
},
  "geometry": {"coordinates":[15.8699836731,48.1898918152],"type":"Point"}
}