{
  "type": "Feature",
  "properties": {
    "iso:country":"AT",
    "sg:address":"Grazer Str 24",
    "sg:city":"Wolfsberg",
    "sg:orig_category":"Autoreparatur",
    "sg:phone":"+43 4352 23960",
    "sg:postcode":"9400",
    "sg:province":"K\u00e4rnten",
    "wof:name":"Dohr Autohaus GmbH",
    "wof:placetype":"venue"
},
  "geometry": {"coordinates":[14.8433551788,46.8449668884],"type":"Point"}
}