{
  "type": "Feature",
  "properties": {
    "addr:full":"Jubil\u00e4umsstr 76 Gumpoldskirchen Nieder\u00f6sterreich 2352",
    "addr:housenumber":"76",
    "addr:postcode":"2352",
    "addr:street":"Jubilaeumsstr",
    "iso:country":"AT",
    "sg:address":"Jubil\u00e4umsstr 76",
    "sg:city":"Gumpoldskirchen",
    "sg:orig_category":"Werbeagenturen",
    "sg:phone":"+43 2252 63767",
    "sg:postcode":"2352",
    "sg:province":"Nieder\u00f6sterreich",
    "wof:name":"Oh Media Werbeagentur",
    "wof:placetype":"venue"
},
  "geometry": {"coordinates":[16.2826633453,48.0441894531],"type":"Point"}
}