{
  "type": "Feature",
  "properties": {
    "addr:full":"Mildenbergstr 2b Bregenz Vorarlberg 6900",
    "addr:housenumber":"2b",
    "addr:postcode":"6900",
    "addr:street":"Mildenbergstr",
    "iso:country":"AT",
    "sg:address":"Mildenbergstr 2b",
    "sg:city":"Bregenz",
    "sg:orig_category":"Handelsagenturen",
    "sg:phone":"+43 5574 52941",
    "sg:postcode":"6900",
    "sg:province":"Vorarlberg",
    "wof:name":"Machne & Partner Ges f Einrichtungsbedarf mbH",
    "wof:placetype":"venue"
},
  "geometry": {"coordinates":[9.7512741089,47.4995193481],"type":"Point"}
}