{
  "type": "Feature",
  "properties": {
    "addr:full":"Salmg 11 Wien Wien 1030",
    "addr:housenumber":"11",
    "addr:postcode":"1030",
    "addr:street":"Salmg",
    "iso:country":"AT",
    "sg:address":"Salmg 11",
    "sg:city":"Wien",
    "sg:orig_category":"Weiterbildungsinstitute M Allg U Berufl Bildungsangebot",
    "sg:phone":"+43 4317 126749",
    "sg:postcode":"1030",
    "sg:province":"Wien",
    "wof:name":"Schulzentrum der Arbeiteruniversit\u00e4t Neu-Belgrad",
    "wof:placetype":"venue"
},
  "geometry": {"coordinates":[16.3920135498,48.2047080994],"type":"Point"}
}