{
  "type": "Feature",
  "properties": {
    "iso:country":"AT",
    "sg:address":"Leopold-Figl-G 8",
    "sg:city":"Ebergassing",
    "sg:classifiers":[
        {
            "category":"Restaurant",
            "type":"Food & Drink"
        }
    ],
    "sg:phone":"+43 2234 73579",
    "sg:postcode":"2435",
    "sg:province":"Nieder\u00f6sterreich",
    "sg:tags":[
        "pizzeria"
    ],
    "wof:name":"Pizzeria Al Contadino",
    "wof:placetype":"venue"
},
  "geometry": {"coordinates":[16.5189552307,48.0447769165],"type":"Point"}
}