{
  "type": "Feature",
  "properties": {
    "addr:full":"Neu Gablonz 24 Enns Ober\u00f6sterreich 4470",
    "addr:housenumber":"24",
    "addr:postcode":"4470",
    "addr:street":"Neu Gablonz",
    "iso:country":"AT",
    "sg:address":"Neu Gablonz 24",
    "sg:city":"Enns",
    "sg:orig_category":"Dienstleistungen, Sonstige Dienstleistungen",
    "sg:phone":"+43 7223",
    "sg:postcode":"4470",
    "sg:province":"Ober\u00f6sterreich",
    "sg:website":"dienstleistungen.freepage.de/possibility",
    "wof:name":"Jetzinger",
    "wof:placetype":"venue"
},
  "geometry": {"coordinates":[14.4797229767,48.2042160034],"type":"Point"}
}