{
  "type": "Feature",
  "properties": {
    "addr:full":"Nr 49 Malta K\u00e4rnten 9854",
    "addr:postcode":"9854",
    "addr:street":"Nr 49;Kaernten",
    "iso:country":"AT",
    "sg:address":"Nr 49",
    "sg:city":"Malta",
    "sg:orig_category":"Volksschulen",
    "sg:phone":"+43 4347 3322020",
    "sg:postcode":"9854",
    "sg:province":"K\u00e4rnten",
    "wof:name":"Volksschule",
    "wof:placetype":"venue"
},
  "geometry": {"coordinates":[13.5070009232,46.9543418884],"type":"Point"}
}