{
  "type": "Feature",
  "properties": {
    "addr:full":"Mozartg 88 Laa an der Thaya Nieder\u00f6sterreich 2136",
    "addr:housenumber":"88",
    "addr:postcode":"2136",
    "addr:street":"Mozartg",
    "iso:country":"AT",
    "sg:address":"Mozartg 88",
    "sg:city":"Laa an der Thaya",
    "sg:classifiers":[
        {
            "category":"Taxi",
            "type":"Transportation"
        }
    ],
    "sg:phone":"+43 4369 914001410",
    "sg:postcode":"2136",
    "sg:province":"Nieder\u00f6sterreich",
    "sg:tags":[
        "personentransporte",
        "u"
    ],
    "wof:name":"Leitner & Mechtler OEG",
    "wof:placetype":"venue"
},
  "geometry": {"coordinates":[16.3851604462,48.7205963135],"type":"Point"}
}