{
  "type": "Feature",
  "properties": {
    "iso:country":"AT",
    "sg:address":"Nr 342",
    "sg:city":"Piesendorf",
    "sg:orig_category":"\u00c3\u201erzte / F Allgemeinmedizin",
    "sg:phone":"+43 6549 73270",
    "sg:postcode":"5721",
    "sg:province":"Salzburg",
    "wof:name":"Schmid Heinz MedR Dr",
    "wof:placetype":"venue"
},
  "geometry": {"coordinates":[12.7159004211,47.2918968201],"type":"Point"}
}