{
  "type": "Feature",
  "properties": {
    "addr:full":"Obere Hauptstrasse 18 Pama Burgenland 2422",
    "addr:housenumber":"18",
    "addr:postcode":"2422",
    "addr:street":"Obere Hauptstrasse",
    "iso:country":"AT",
    "sg:address":"Obere Hauptstrasse 18",
    "sg:city":"Pama",
    "sg:classifiers":[
        {
            "category":"Home & Garden",
            "subcategory":"Building Materials",
            "type":"Retail Goods"
        }
    ],
    "sg:phone":"+43 2142 6002",
    "sg:postcode":"2422",
    "sg:province":"Burgenland",
    "sg:tags":[
        "steel",
        "balcony"
    ],
    "wof:name":"Wepro Stahlbau",
    "wof:placetype":"venue"
},
  "geometry": {"coordinates":[17.0312404633,48.0499420166],"type":"Point"}
}