{
  "type": "Feature",
  "properties": {
    "addr:full":"Katzianerg 3 Graz Steiermark 8010",
    "addr:housenumber":"3",
    "addr:postcode":"8010",
    "addr:street":"Katzianerg",
    "iso:country":"AT",
    "sg:address":"Katzianerg 3",
    "sg:city":"Graz",
    "sg:orig_category":"Marketingberatung",
    "sg:phone":"+43 316 829513",
    "sg:postcode":"8010",
    "sg:province":"Steiermark",
    "wof:name":"GIL kunst impulse.art infection",
    "wof:placetype":"venue"
},
  "geometry": {"coordinates":[15.4540719986,47.0690879822],"type":"Point"}
}