{
  "type": "Feature",
  "properties": {
    "addr:full":"An der Walk 22 Klagenfurt K\u00e4rnten 9020",
    "addr:housenumber":"22",
    "addr:postcode":"9020",
    "addr:street":"An Der Walk;Kaernten",
    "iso:country":"AT",
    "sg:address":"An der Walk 22",
    "sg:city":"Klagenfurt",
    "sg:orig_category":"Physiotherapie",
    "sg:phone":"+43 650 7700787",
    "sg:postcode":"9020",
    "sg:province":"K\u00e4rnten",
    "wof:name":"Klagenfurt Mobile Physiotherapie - Dipl-PT Andrea Gra\u00dflober und Dipl-PT Nikola Wastl",
    "wof:placetype":"venue"
},
  "geometry": {"coordinates":[14.3252096176,46.6305999756],"type":"Point"}
}