{
  "type": "Feature",
  "properties": {
    "iso:country":"AT",
    "sg:address":"Hauptstrasse 5",
    "sg:city":"Hohenau an der March",
    "sg:classifiers":[
        {
            "category":"Utilities",
            "subcategory":"Natural Gas",
            "type":"Services"
        }
    ],
    "sg:phone":"+43 2535 31130",
    "sg:postcode":"2273",
    "sg:province":"Nieder\u00f6sterreich",
    "sg:tags":[
        "ceiling",
        "lamp"
    ],
    "sg:website":"oms.at",
    "wof:name":"OMS Leuchten GmbH",
    "wof:placetype":"venue"
},
  "geometry": {"coordinates":[16.9099330902,48.6076965332],"type":"Point"}
}