{
  "type": "Feature",
  "properties": {
    "addr:full":"Handelszentrum 1 Bergheim Salzburg 5101",
    "addr:housenumber":"1",
    "addr:postcode":"5101",
    "addr:street":"Handelszentrum;Salzburg",
    "iso:country":"AT",
    "sg:address":"Handelszentrum 1",
    "sg:city":"Bergheim",
    "sg:classifiers":[
        {
            "category":"Government",
            "subcategory":"Post Office",
            "type":"Public Place"
        }
    ],
    "sg:phone":"+43 4366 24520660",
    "sg:postcode":"5101",
    "sg:province":"Salzburg",
    "sg:tags":[
        "u",
        "-material",
        "dachdeckereibedarf"
    ],
    "wof:name":"Austro Dach Handels GmbH & Co KG",
    "wof:placetype":"venue"
},
  "geometry": {"coordinates":[13.0362882614,47.8426780701],"type":"Point"}
}