{
  "type": "Feature",
  "properties": {
    "addr:full":"Michael-Bernhard-G 8 Wien Wien 1120",
    "addr:housenumber":"8",
    "addr:postcode":"1120",
    "addr:street":"Michael-Bernhard-G",
    "iso:country":"AT",
    "sg:address":"Michael-Bernhard-G 8",
    "sg:city":"Wien",
    "sg:orig_category":"Autoreparatur",
    "sg:phone":"+43 1 8139118",
    "sg:postcode":"1120",
    "sg:province":"Wien",
    "wof:name":"Weiser Franz GesmbH",
    "wof:placetype":"venue"
},
  "geometry": {"coordinates":[16.333398819,48.1832237244],"type":"Point"}
}