{
  "type": "Feature",
  "properties": {
    "addr:full":"Predlitz 11 Predlitz Steiermark 8863",
    "addr:housenumber":"11",
    "addr:postcode":"8863",
    "addr:street":"Predlitz",
    "iso:country":"AT",
    "sg:address":"Predlitz 11",
    "sg:city":"Predlitz",
    "sg:orig_category":"Gemeinden",
    "sg:phone":"+43 3534 8021",
    "sg:postcode":"8863",
    "sg:province":"Steiermark",
    "wof:name":"Gemeinde Predlitz-Turrach",
    "wof:placetype":"venue"
},
  "geometry": {"coordinates":[13.9018859863,47.0446052551],"type":"Point"}
}