{
  "type": "Feature",
  "properties": {
    "iso:country":"AT",
    "sg:address":"Nr 14",
    "sg:city":"Gnas",
    "sg:orig_category":"Tabaktrafiken",
    "sg:phone":"+43 3151 30109",
    "sg:postcode":"8342",
    "sg:province":"Steiermark",
    "wof:name":"Roth-Pichler Andrea",
    "wof:placetype":"venue"
},
  "geometry": {"coordinates":[15.8265724182,46.8743095398],"type":"Point"}
}