{
  "type": "Feature",
  "properties": {
    "addr:full":"Linzer Str 404 Wien Wien 1140",
    "addr:housenumber":"404",
    "addr:postcode":"1140",
    "addr:street":"Linzer Str",
    "iso:country":"AT",
    "sg:address":"Linzer Str 404",
    "sg:city":"Wien",
    "sg:orig_category":"Heurigen / Buschenschank",
    "sg:phone":"+43 4319 142397",
    "sg:postcode":"1140",
    "sg:province":"Wien",
    "wof:name":"Dopplinger H KG",
    "wof:placetype":"venue"
},
  "geometry": {"coordinates":[16.2606487274,48.2019462585],"type":"Point"}
}