{
  "type": "Feature",
  "properties": {
    "addr:full":"Riemetschlag 26 Windhaag Ober\u00f6sterreich 4263",
    "addr:housenumber":"26",
    "addr:postcode":"4263",
    "addr:street":"Riemetschlag;Oberoesterreich",
    "iso:country":"AT",
    "sg:address":"Riemetschlag 26",
    "sg:city":"Windhaag",
    "sg:orig_category":"Fenster",
    "sg:phone":"+43 4379 436675",
    "sg:postcode":"4263",
    "sg:province":"Ober\u00f6sterreich",
    "wof:name":"Kampelm\u00fcller Gebhard",
    "wof:placetype":"venue"
},
  "geometry": {"coordinates":[14.5746212006,48.5650787354],"type":"Point"}
}