{
  "type": "Feature",
  "properties": {
    "iso:country":"AT",
    "sg:address":"Zachhuberg 4a",
    "sg:city":"Steyr",
    "sg:orig_category":"Weiterbildungsinstitute M Allg U Berufl Bildungsangebot",
    "sg:phone":"+43 699 12043839",
    "sg:postcode":"4400",
    "sg:province":"Ober\u00f6sterreich",
    "wof:name":"Kletzmayr KEG",
    "wof:placetype":"venue"
},
  "geometry": {"coordinates":[14.4149560928,48.0450553894],"type":"Point"}
}