{
  "type": "Feature",
  "properties": {
    "addr:full":"Hofmark 12 Mining Ober\u00f6sterreich 4962",
    "addr:housenumber":"12",
    "addr:postcode":"4962",
    "addr:street":"Hofmark",
    "iso:country":"AT",
    "sg:address":"Hofmark 12",
    "sg:city":"Mining",
    "sg:orig_category":"Friseure U Frisiersalons",
    "sg:phone":"+43 7723 7443",
    "sg:postcode":"4962",
    "sg:province":"Ober\u00f6sterreich",
    "wof:name":"Frisierstube Evelyn",
    "wof:placetype":"venue"
},
  "geometry": {"coordinates":[13.1616344452,48.2765541077],"type":"Point"}
}