{
  "type": "Feature",
  "properties": {
    "addr:full":"Lindach Dorf 6 Laakirchen Ober\u00f6sterreich 4663",
    "addr:housenumber":"6",
    "addr:postcode":"4663",
    "addr:street":"Lindach Dorf",
    "iso:country":"AT",
    "sg:address":"Lindach Dorf 6",
    "sg:city":"Laakirchen",
    "sg:orig_category":"Autoreparatur",
    "sg:phone":"+43 76135800",
    "sg:postcode":"4663",
    "sg:province":"Ober\u00f6sterreich",
    "wof:name":"Gielesberger Herbert",
    "wof:placetype":"venue"
},
  "geometry": {"coordinates":[13.8235998154,47.9830665588],"type":"Point"}
}