{
  "type": "Feature",
  "properties": {
    "iso:country":"AT",
    "sg:address":"Ysper 33",
    "sg:city":"Yspertal",
    "sg:orig_category":"Arbeitsschutz U Arbeitsschutzartikel",
    "sg:phone":"+43 4374 1574440",
    "sg:postcode":"3683",
    "sg:province":"Nieder\u00f6sterreich",
    "wof:name":"Puschacher Peter",
    "wof:placetype":"venue"
},
  "geometry": {"coordinates":[15.0475206375,48.2543983459],"type":"Point"}
}