{
  "type": "Feature",
  "properties": {
    "addr:full":"G\u00f6tzing 3 Egg K\u00e4rnten 9624",
    "addr:housenumber":"3",
    "addr:postcode":"9624",
    "addr:street":"Goetzing;Kaernten",
    "iso:country":"AT",
    "sg:address":"G\u00f6tzing 3",
    "sg:city":"Egg",
    "sg:classifiers":[
        {
            "category":"Food & Beverages",
            "subcategory":"Cheese",
            "type":"Retail Goods"
        }
    ],
    "sg:phone":"+43 4282 253651",
    "sg:postcode":"9624",
    "sg:province":"K\u00e4rnten",
    "sg:website":"kaeseoase.com",
    "wof:name":"DIE K\u00c4SE OASE",
    "wof:placetype":"venue"
},
  "geometry": {"coordinates":[13.4396696091,46.6203384399],"type":"Point"}
}