{
  "type": "Feature",
  "properties": {
    "iso:country":"AT",
    "sg:address":"Albrechtser Str 1",
    "sg:city":"Gm\u00fcnd",
    "sg:classifiers":[
        {
            "category":"Restaurant",
            "type":"Food & Drink"
        }
    ],
    "sg:phone":"+43 2852 521600",
    "sg:postcode":"3950",
    "sg:province":"Nieder\u00f6sterreich",
    "wof:name":"Restaurant Schachner",
    "wof:placetype":"venue"
},
  "geometry": {"coordinates":[14.9849376678,48.7638626099],"type":"Point"}
}