{
  "type": "Feature",
  "properties": {
    "addr:full":"Westbahnstr 52 St. Valentin Nieder\u00f6sterreich 4300",
    "addr:housenumber":"52",
    "addr:postcode":"4300",
    "addr:street":"Westbahnstr",
    "iso:country":"AT",
    "sg:address":"Westbahnstr 52",
    "sg:city":"St. Valentin",
    "sg:orig_category":"Nagelstudios",
    "sg:phone":"+43 4366 43818113",
    "sg:postcode":"4300",
    "sg:province":"Nieder\u00f6sterreich",
    "wof:name":"Br\u00e4unungsstudio Panhuber Erika",
    "wof:placetype":"venue"
},
  "geometry": {"coordinates":[14.5221118927,48.1804618835],"type":"Point"}
}