{
  "type": "Feature",
  "properties": {
    "addr:full":"Vordernberger Str 41 Eisenerz Steiermark 8790",
    "addr:postcode":"8790",
    "addr:street":"Str 41",
    "iso:country":"AT",
    "sg:address":"Vordernberger Str 41",
    "sg:city":"Eisenerz",
    "sg:classifiers":[
        {
            "category":"Shopping",
            "subcategory":"Gifts & Souvenirs",
            "type":"Retail Goods"
        }
    ],
    "sg:phone":"+43 3848 3327",
    "sg:postcode":"8790",
    "sg:province":"Steiermark",
    "wof:name":"Suchanek Ewald",
    "wof:placetype":"venue"
},
  "geometry": {"coordinates":[14.8965234756,47.5412406921],"type":"Point"}
}