{
  "type": "Feature",
  "properties": {
    "addr:full":"Grafenweg 33 Hard Vorarlberg 6971",
    "addr:housenumber":"33",
    "addr:postcode":"6971",
    "addr:street":"Grafenweg",
    "iso:country":"AT",
    "sg:address":"Grafenweg 33",
    "sg:city":"Hard",
    "sg:classifiers":[
        {
            "category":"Autos & Motor Vehicles",
            "subcategory":"Auto Supplies",
            "type":"Retail Goods"
        }
    ],
    "sg:phone":"+43 5574 82292",
    "sg:postcode":"6971",
    "sg:province":"Vorarlberg",
    "sg:tags":[
        "automobile",
        "accessory"
    ],
    "sg:website":"at-chemie.at",
    "wof:name":"AT Automaterial Ges.m.b.H.",
    "wof:placetype":"venue"
},
  "geometry": {"coordinates":[9.6757488251,47.4717597961],"type":"Point"}
}