{
  "type": "Feature",
  "properties": {
    "iso:country":"AT",
    "sg:address":"Pollheimer Str 13",
    "sg:city":"Timelkam",
    "sg:orig_category":"Politische Parteien",
    "sg:phone":"+43 767296244",
    "sg:postcode":"4850",
    "sg:province":"Ober\u00f6sterreich",
    "wof:name":"Sozialistische Partei \u00f6sterreichs",
    "wof:placetype":"venue"
},
  "geometry": {"coordinates":[13.6143512726,48.002155304],"type":"Point"}
}