{
  "type": "Feature",
  "properties": {
    "iso:country":"AT",
    "sg:address":"Jaiding 11",
    "sg:city":"Ro\u00dfbach",
    "sg:classifiers":[
        {
            "category":"Manufacturing",
            "subcategory":"Furniture",
            "type":"Manufacturing & Wholesale Goods"
        }
    ],
    "sg:phone":"+43 7755 5010",
    "sg:postcode":"5273",
    "sg:province":"Ober\u00f6sterreich",
    "sg:tags":[
        "bedroom"
    ],
    "wof:name":"Johann Gottfried",
    "wof:placetype":"venue"
},
  "geometry": {"coordinates":[13.2750740051,48.2088432312],"type":"Point"}
}