{
  "type": "Feature",
  "properties": {
    "iso:country":"AT",
    "sg:address":"Nr 15",
    "sg:city":"Thening",
    "sg:orig_category":"Spirituosen / Erzeugung U Gro\u00c3\u0178handel",
    "sg:phone":"+43 7221 63690",
    "sg:postcode":"4062",
    "sg:province":"Ober\u00f6sterreich",
    "wof:name":"Reisetbauer Hans",
    "wof:placetype":"venue"
},
  "geometry": {"coordinates":[14.1588783264,48.2645797729],"type":"Point"}
}