{
  "type": "Feature",
  "properties": {
    "addr:full":"Hans-Doppelreiter-Str. 5 Absdorf Nieder\u00f6sterreich 3462",
    "addr:housenumber":"5",
    "addr:postcode":"3462",
    "addr:street":"Hans-Doppelreiter-Str.;Niederoesterreich",
    "iso:country":"AT",
    "sg:address":"Hans-Doppelreiter-Str. 5",
    "sg:city":"Absdorf",
    "sg:classifiers":[
        {
            "category":"Professional",
            "subcategory":"Engineering",
            "type":"Services"
        }
    ],
    "sg:phone":"+43 4322 7822900",
    "sg:postcode":"3462",
    "sg:province":"Nieder\u00f6sterreich",
    "sg:tags":[
        "machine",
        "-",
        "mechanical"
    ],
    "wof:name":"EDWIN WANZENB\u00d6CK",
    "wof:placetype":"venue"
},
  "geometry": {"coordinates":[15.9802322388,48.4034423828],"type":"Point"}
}