{
  "type": "Feature",
  "properties": {
    "addr:full":"Gaullacherg 27 Wien Wien 1160",
    "addr:housenumber":"27",
    "addr:postcode":"1160",
    "addr:street":"Gaullacherg",
    "iso:country":"AT",
    "sg:address":"Gaullacherg 27",
    "sg:city":"Wien",
    "sg:orig_category":"Transportunternehmen",
    "sg:phone":"+43 664 5448670",
    "sg:postcode":"1160",
    "sg:province":"Wien",
    "wof:name":"Topic & Partner OEG",
    "wof:placetype":"venue"
},
  "geometry": {"coordinates":[16.335231781,48.2117576599],"type":"Point"}
}