{
  "type": "Feature",
  "properties": {
    "iso:country":"AT",
    "sg:address":"Ruster Str 24",
    "sg:city":"Eisenstadt",
    "sg:orig_category":"Blumeneinzelhandel",
    "sg:phone":"+43 2682 75758",
    "sg:postcode":"7000",
    "sg:province":"Burgenland",
    "wof:name":"Blumen 2000 Handels GmbH",
    "wof:placetype":"venue"
},
  "geometry": {"coordinates":[16.5224819183,47.842502594],"type":"Point"}
}