{
  "type": "Feature",
  "properties": {
    "addr:full":"Heiligenst\u00e4dter Str 79 Wien Wien 1190",
    "addr:postcode":"1190",
    "addr:street":"Str 79",
    "iso:country":"AT",
    "sg:address":"Heiligenst\u00e4dter Str 79",
    "sg:city":"Wien",
    "sg:orig_category":"Tapezierer U Dekorateure, Raumausstattung",
    "sg:phone":"+43 1 3681612",
    "sg:postcode":"1190",
    "sg:province":"Wien",
    "sg:website":"www.bathelt.at",
    "wof:name":"Bathelt & Co",
    "wof:placetype":"venue"
},
  "geometry": {"coordinates":[16.3614025116,48.2444801331],"type":"Point"}
}