{
  "type": "Feature",
  "properties": {
    "iso:country":"AT",
    "sg:address":"Nr 7",
    "sg:city":"Neumarkt im Hausruckkreis",
    "sg:orig_category":"Reinigungsbedarf U Reinigungsmittel",
    "sg:phone":"+43 4377 3320090",
    "sg:postcode":"4720",
    "sg:province":"Ober\u00f6sterreich",
    "wof:name":"NOVIQUA Handels GmbH",
    "wof:placetype":"venue"
},
  "geometry": {"coordinates":[13.713467598,48.281955719],"type":"Point"}
}