{
  "type": "Feature",
  "properties": {
    "addr:full":"Langauweg 36 Seewalchen am Attersee Ober\u00f6sterreich 4863",
    "addr:housenumber":"36",
    "addr:postcode":"4863",
    "addr:street":"Langauweg",
    "iso:country":"AT",
    "sg:address":"Langauweg 36",
    "sg:city":"Seewalchen am Attersee",
    "sg:orig_category":"Juwelen, Gold- U Silberwaren / Erzeugung U Gro\u00c3\u0178handel",
    "sg:phone":"+43 4376 624955",
    "sg:postcode":"4863",
    "sg:province":"Ober\u00f6sterreich",
    "wof:name":"WOGA",
    "wof:placetype":"venue"
},
  "geometry": {"coordinates":[13.5997495651,47.9576301575],"type":"Point"}
}