{
  "type": "Feature",
  "properties": {
    "addr:full":"Nr 117 Krakaudorf Steiermark 8854",
    "addr:postcode":"8854",
    "addr:street":"Nr",
    "iso:country":"AT",
    "sg:address":"Nr 117",
    "sg:city":"Krakaudorf",
    "sg:orig_category":"Bankomat-Standorte",
    "sg:phone":"+43 3535 8263",
    "sg:postcode":"8854",
    "sg:province":"Steiermark",
    "wof:name":"Bankomat d Raiffeisenbank Murau regGenmbH",
    "wof:placetype":"venue"
},
  "geometry": {"coordinates":[13.9921045303,47.1786117554],"type":"Point"}
}