{
  "type": "Feature",
  "properties": {
    "iso:country":"AT",
    "sg:address":"Gobernitz 5",
    "sg:city":"Knittelfeld",
    "sg:orig_category":"Pensionen / Privatzimmer",
    "sg:phone":"+43 3512 46063",
    "sg:postcode":"8720",
    "sg:province":"Steiermark",
    "wof:name":"Privatzimmer Puster",
    "wof:placetype":"venue"
},
  "geometry": {"coordinates":[14.8478279114,47.215221405],"type":"Point"}
}