{
  "type": "Feature",
  "properties": {
    "iso:country":"AT",
    "sg:address":"Grillg 51",
    "sg:city":"Wien",
    "sg:orig_category":"Abfallentsorgung U -Verwertung",
    "sg:phone":"+43 1 74975150",
    "sg:postcode":"1110",
    "sg:province":"Wien",
    "wof:name":"\u00d6STAB AbfallbeseitigungsgesmbH & Co KG",
    "wof:placetype":"venue"
},
  "geometry": {"coordinates":[16.4197444916,48.1709709167],"type":"Point"}
}