{
  "type": "Feature",
  "properties": {
    "addr:full":"Hundswart 5 Pinkafeld Burgenland 7423",
    "addr:housenumber":"5",
    "addr:postcode":"7423",
    "addr:street":"Hundswart",
    "iso:country":"AT",
    "sg:address":"Hundswart 5",
    "sg:city":"Pinkafeld",
    "sg:orig_category":"Bauunternehmen",
    "sg:phone":"+43 3357 46147",
    "sg:postcode":"7423",
    "sg:province":"Burgenland",
    "wof:name":"GGV Bau & Bautr\u00e4ger GesmbH",
    "wof:placetype":"venue"
},
  "geometry": {"coordinates":[16.1280994415,47.3750762939],"type":"Point"}
}