{
  "type": "Feature",
  "properties": {
    "iso:country":"AT",
    "sg:address":"Schachterlweg 32",
    "sg:city":"Klagenfurt",
    "sg:orig_category":"Psychologen",
    "sg:phone":"+43 676 7068858",
    "sg:postcode":"9020",
    "sg:province":"K\u00e4rnten",
    "wof:name":"Psychologische L\u00f6sungen",
    "wof:placetype":"venue"
},
  "geometry": {"coordinates":[14.3372220993,46.6280403137],"type":"Point"}
}