{
  "type": "Feature",
  "properties": {
    "addr:full":"Mahlerstr 12 Wien Wien 1010",
    "addr:housenumber":"12",
    "addr:postcode":"1010",
    "addr:street":"Mahlerstr",
    "iso:country":"AT",
    "sg:address":"Mahlerstr 12",
    "sg:city":"Wien",
    "sg:orig_category":"Werbeagenturen",
    "sg:phone":"+43 1 5030606",
    "sg:postcode":"1010",
    "sg:province":"Wien",
    "wof:name":"Hundertprozentig Communications PR-Agentur GmbH",
    "wof:placetype":"venue"
},
  "geometry": {"coordinates":[16.3728218079,48.2022819519],"type":"Point"}
}