{
  "type": "Feature",
  "properties": {
    "iso:country":"AT",
    "sg:address":"Elterleinpl 1",
    "sg:city":"Wien",
    "sg:orig_category":"Maschinenhandel",
    "sg:phone":"+43 1 4036166",
    "sg:postcode":"1170",
    "sg:province":"Wien",
    "wof:name":"Liska Nenad Dkfm Industrievertretungen und Handel",
    "wof:placetype":"venue"
},
  "geometry": {"coordinates":[16.3325595856,48.2179145813],"type":"Point"}
}