{
  "type": "Feature",
  "properties": {
    "addr:full":"Waidhofner Str 2-4/4 Amstetten Nieder\u00f6sterreich 3300",
    "addr:housenumber":"2-4 / 4",
    "addr:postcode":"3300",
    "addr:street":"Str;Niederoesterreich",
    "iso:country":"AT",
    "sg:address":"Waidhofner Str 2-4/4",
    "sg:city":"Amstetten",
    "sg:orig_category":"Fahrschulen",
    "sg:phone":"+43 7472 235310",
    "sg:postcode":"3300",
    "sg:province":"Nieder\u00f6sterreich",
    "wof:name":"Easy Drivers Amstetten, Paur",
    "wof:placetype":"venue"
},
  "geometry": {"coordinates":[14.8691329956,48.1217842102],"type":"Point"}
}