{
  "type": "Feature",
  "properties": {
    "iso:country":"AT",
    "sg:address":"Vidmarstr 96",
    "sg:city":"G\u00f6sting",
    "sg:orig_category":"Bauunternehmen",
    "sg:phone":"+43 316 6799780",
    "sg:postcode":"8051",
    "sg:province":"Steiermark",
    "wof:name":"Winkler Reinhard Ing Bau- und HandelsgesmbH",
    "wof:placetype":"venue"
},
  "geometry": {"coordinates":[15.4003400803,47.0909538269],"type":"Point"}
}