{
  "type": "Feature",
  "properties": {
    "addr:full":"Vierhausstr 15 Berndorf Nieder\u00f6sterreich 2560",
    "addr:housenumber":"15",
    "addr:postcode":"2560",
    "addr:street":"Vierhausstr",
    "iso:country":"AT",
    "sg:address":"Vierhausstr 15",
    "sg:city":"Berndorf",
    "sg:orig_category":"Handelsagenturen",
    "sg:phone":"+43 4326 7282868",
    "sg:postcode":"2560",
    "sg:province":"Nieder\u00f6sterreich",
    "wof:name":"Kratohwil Christa",
    "wof:placetype":"venue"
},
  "geometry": {"coordinates":[16.1027374268,47.9459342957],"type":"Point"}
}