{
  "type": "Feature",
  "properties": {
    "iso:country":"AT",
    "sg:address":"Nr 395",
    "sg:city":"Scharnitz",
    "sg:orig_category":"Transportunternehmen",
    "sg:phone":"+43 5213 5500",
    "sg:postcode":"6108",
    "sg:province":"Tirol",
    "wof:name":"Gaugg Manfred",
    "wof:placetype":"venue"
},
  "geometry": {"coordinates":[11.2646799088,47.3903579712],"type":"Point"}
}