{
  "type": "Feature",
  "properties": {
    "addr:full":"Kinskyg 13 Wien Wien 1230",
    "addr:housenumber":"13",
    "addr:postcode":"1230",
    "addr:street":"Kinskyg",
    "iso:country":"AT",
    "sg:address":"Kinskyg 13",
    "sg:city":"Wien",
    "sg:orig_category":"Blitzableiter U Blitzschutzanlagen, Elektroinstallationsunternehmen",
    "sg:phone":"+43 1 6628735",
    "sg:postcode":"1230",
    "sg:province":"Wien",
    "wof:name":"Jamiol Elektro Blitzschutzanlagenbau",
    "wof:placetype":"venue"
},
  "geometry": {"coordinates":[16.3337116241,48.1500740051],"type":"Point"}
}