{
  "type": "Feature",
  "properties": {
    "addr:full":"Bahnhofstr 26 Purkersdorf Nieder\u00f6sterreich 3002",
    "addr:postcode":"3002",
    "addr:street":"Bahnhofstr 26",
    "iso:country":"AT",
    "sg:address":"Bahnhofstr 26",
    "sg:city":"Purkersdorf",
    "sg:orig_category":"Steuerberatung",
    "sg:phone":"+43 2231 636270",
    "sg:postcode":"3002",
    "sg:province":"Nieder\u00f6sterreich",
    "wof:name":"Garantie WirtschaftstreuhandgesmbH",
    "wof:placetype":"venue"
},
  "geometry": {"coordinates":[16.1829605103,48.2080917358],"type":"Point"}
}