{
  "type": "Feature",
  "properties": {
    "iso:country":"AT",
    "sg:address":"Krinbergweg 4",
    "sg:city":"Kirchberg in Tirol",
    "sg:orig_category":"Pensionen / Privatzimmer",
    "sg:phone":"+43 4353 572988",
    "sg:postcode":"6365",
    "sg:province":"Tirol",
    "wof:name":"Eggerhof M\u00f6llinger Angelika u Josef",
    "wof:placetype":"venue"
},
  "geometry": {"coordinates":[12.3160324097,47.4183387756],"type":"Point"}
}