{
  "type": "Feature",
  "properties": {
    "iso:country":"AT",
    "sg:address":"Sch\u00fctzenbichl 15",
    "sg:city":"Bad Ischl",
    "sg:classifiers":[
        {
            "category":"Shopping",
            "subcategory":"Clothing, Apparel, & Fashions",
            "type":"Retail Goods"
        }
    ],
    "sg:phone":"+43 4361 3223367",
    "sg:postcode":"4820",
    "sg:province":"Ober\u00f6sterreich",
    "sg:tags":[
        "clothing",
        "accessory"
    ],
    "wof:name":"FRANZ BITTNER GES.MBH & CO KG",
    "wof:placetype":"venue"
},
  "geometry": {"coordinates":[13.6257123947,47.711971283],"type":"Point"}
}