{
  "type": "Feature",
  "properties": {
    "addr:full":"Breiter Weg 10 Feldkirch Vorarlberg 6800",
    "addr:housenumber":"10",
    "addr:postcode":"6800",
    "addr:street":"Breiter Weg",
    "iso:country":"AT",
    "sg:address":"Breiter Weg 10",
    "sg:city":"Feldkirch",
    "sg:orig_category":"Maler, Anstreicher U Lackierer",
    "sg:phone":"+43 5522 79446",
    "sg:postcode":"6800",
    "sg:province":"Vorarlberg",
    "wof:name":"Lenhart Kurt GesmbH",
    "wof:placetype":"venue"
},
  "geometry": {"coordinates":[9.5617465973,47.2586288452],"type":"Point"}
}