{
  "type": "Feature",
  "properties": {
    "addr:full":"Novaragasse 32 Wien Wien 1020",
    "addr:housenumber":"32",
    "addr:postcode":"1020",
    "addr:street":"Novaragasse",
    "iso:country":"AT",
    "sg:address":"Novaragasse 32",
    "sg:city":"Wien",
    "sg:classifiers":[
        {
            "category":"Building & Trades",
            "subcategory":"Plumbing",
            "type":"Services"
        }
    ],
    "sg:phone":"+43 1 21609370",
    "sg:postcode":"1020",
    "sg:province":"Wien",
    "sg:tags":[
        "tub",
        "bath"
    ],
    "wof:name":"Josef Schenker",
    "wof:placetype":"venue"
},
  "geometry": {"coordinates":[16.38580513,48.218547821],"type":"Point"}
}