{
  "type": "Feature",
  "properties": {
    "addr:full":"Schmiedeg 13 Linz Ober\u00f6sterreich 4040",
    "addr:housenumber":"13",
    "addr:postcode":"4040",
    "addr:street":"Schmiedeg",
    "iso:country":"AT",
    "sg:address":"Schmiedeg 13",
    "sg:city":"Linz",
    "sg:orig_category":"Handelsagenturen",
    "sg:phone":"+43 732 730362",
    "sg:postcode":"4040",
    "sg:province":"Ober\u00f6sterreich",
    "wof:name":"Sadila Rudolf jun",
    "wof:placetype":"venue"
},
  "geometry": {"coordinates":[14.2825241089,48.3152313232],"type":"Point"}
}