{
  "type": "Feature",
  "properties": {
    "addr:full":"Geiselbergstr 53 Wien Wien 1110",
    "addr:housenumber":"53",
    "addr:postcode":"1110",
    "addr:street":"Geiselbergstr",
    "iso:country":"AT",
    "sg:address":"Geiselbergstr 53",
    "sg:city":"Wien",
    "sg:orig_category":"Elektroinstallationsunternehmen",
    "sg:phone":"+43 1 9679000",
    "sg:postcode":"1110",
    "sg:province":"Wien",
    "wof:name":"Lelovich Wolfgang",
    "wof:placetype":"venue"
},
  "geometry": {"coordinates":[16.4092750549,48.174747467],"type":"Point"}
}