{
  "type": "Feature",
  "properties": {
    "addr:full":"Marktpl 10 Neufelden Ober\u00f6sterreich 4120",
    "addr:housenumber":"10",
    "addr:postcode":"4120",
    "addr:street":"Marktpl",
    "iso:country":"AT",
    "sg:address":"Marktpl 10",
    "sg:city":"Neufelden",
    "sg:orig_category":"Banken U Sparkassen",
    "sg:phone":"+43 4372 825645",
    "sg:postcode":"4120",
    "sg:province":"Ober\u00f6sterreich",
    "wof:name":"Sparkasse M\u00fchlviertel-West Bank AG",
    "wof:placetype":"venue"
},
  "geometry": {"coordinates":[14.0002918243,48.4835357666],"type":"Point"}
}