{
  "type": "Feature",
  "properties": {
    "addr:full":"Atterseestr 16 Lenzing Ober\u00f6sterreich 4860",
    "addr:housenumber":"16",
    "addr:postcode":"4860",
    "addr:street":"Atterseestr",
    "iso:country":"AT",
    "sg:address":"Atterseestr 16",
    "sg:city":"Lenzing",
    "sg:orig_category":"Blumeneinzelhandel",
    "sg:phone":"+43 767295848",
    "sg:postcode":"4860",
    "sg:province":"Ober\u00f6sterreich",
    "wof:name":"Blumeneck - Mayer Josef",
    "wof:placetype":"venue"
},
  "geometry": {"coordinates":[13.6119127274,47.9798469543],"type":"Point"}
}