{
  "type": "Feature",
  "properties": {
    "addr:full":"Stadtpl 28 Klosterneuburg Nieder\u00f6sterreich 3400",
    "addr:housenumber":"28",
    "addr:postcode":"3400",
    "addr:street":"Stadtpl;Niederoesterreich",
    "iso:country":"AT",
    "sg:address":"Stadtpl 28",
    "sg:city":"Klosterneuburg",
    "sg:orig_category":"Farben U Lacke / Einzelhandel",
    "sg:phone":"+43 2243 32885",
    "sg:postcode":"3400",
    "sg:province":"Nieder\u00f6sterreich",
    "wof:name":"Weingartner & Maurer Farbenhandels GmbH - ADLER Farbenmeister",
    "wof:placetype":"venue"
},
  "geometry": {"coordinates":[16.3243522644,48.3094673157],"type":"Point"}
}