{
  "type": "Feature",
  "properties": {
    "addr:full":"Illweg 12 N\u00fcziders Vorarlberg 6714",
    "addr:housenumber":"12",
    "addr:postcode":"6714",
    "addr:street":"Illweg",
    "iso:country":"AT",
    "sg:address":"Illweg 12",
    "sg:city":"N\u00fcziders",
    "sg:orig_category":"Schlossereien",
    "sg:phone":"+43 5552 67180",
    "sg:postcode":"6714",
    "sg:province":"Vorarlberg",
    "wof:name":"Bartl Wolfgang",
    "wof:placetype":"venue"
},
  "geometry": {"coordinates":[9.7815084457,47.1724090576],"type":"Point"}
}