{
  "type": "Feature",
  "properties": {
    "iso:country":"AT",
    "sg:address":"Schellingg 4",
    "sg:city":"Wien",
    "sg:orig_category":"Filmproduktionen",
    "sg:phone":"+43 1 51311150",
    "sg:postcode":"1010",
    "sg:province":"Wien",
    "wof:name":"Lisa Film Produktion GmbH",
    "wof:placetype":"venue"
},
  "geometry": {"coordinates":[16.3755245209,48.204875946],"type":"Point"}
}