{
  "type": "Feature",
  "properties": {
    "iso:country":"AT",
    "sg:address":"Nr 39",
    "sg:city":"Ilz",
    "sg:orig_category":"Pensionen / Privatzimmer",
    "sg:phone":"+43 3385 7208",
    "sg:postcode":"8262",
    "sg:province":"Steiermark",
    "wof:name":"Schibich Erika",
    "wof:placetype":"venue"
},
  "geometry": {"coordinates":[15.9260549545,47.086479187],"type":"Point"}
}