{
  "type": "Feature",
  "properties": {
    "addr:full":"Untereitzing 47 Aurolzm\u00fcnster Ober\u00f6sterreich 4971",
    "addr:housenumber":"47",
    "addr:postcode":"4971",
    "addr:street":"Untereitzing;Oberoesterreich",
    "iso:country":"AT",
    "sg:address":"Untereitzing 47",
    "sg:city":"Aurolzm\u00fcnster",
    "sg:orig_category":"Gemeinden",
    "sg:phone":"+43 7752 83037",
    "sg:postcode":"4971",
    "sg:province":"Ober\u00f6sterreich",
    "wof:name":"Gemeindeamt Eitzing",
    "wof:placetype":"venue"
},
  "geometry": {"coordinates":[13.4548149109,48.248500824],"type":"Point"}
}