{
  "type": "Feature",
  "properties": {
    "addr:full":"Dorfstr 24 Schwanenstadt Ober\u00f6sterreich 4690",
    "addr:housenumber":"24",
    "addr:postcode":"4690",
    "addr:street":"Dorfstr",
    "iso:country":"AT",
    "sg:address":"Dorfstr 24",
    "sg:city":"Schwanenstadt",
    "sg:orig_category":"Schneidereien",
    "sg:phone":"+43 4376 733648",
    "sg:postcode":"4690",
    "sg:province":"Ober\u00f6sterreich",
    "wof:name":"Burger Maria",
    "wof:placetype":"venue"
},
  "geometry": {"coordinates":[13.7582616806,48.0563812256],"type":"Point"}
}