{
  "type": "Feature",
  "properties": {
    "addr:full":"M\u00fchlbachweg 9 Saalfelden am Steinernen Meer Salzburg 5760",
    "addr:housenumber":"9",
    "addr:postcode":"5760",
    "addr:street":"Muehlbachweg",
    "iso:country":"AT",
    "sg:address":"M\u00fchlbachweg 9",
    "sg:city":"Saalfelden am Steinernen Meer",
    "sg:orig_category":"Fleischhauereien",
    "sg:phone":"+43 6582 76387",
    "sg:postcode":"5760",
    "sg:province":"Salzburg",
    "wof:name":"Schirnhofer-Breisler GesmbH - Shop in Shop",
    "wof:placetype":"venue"
},
  "geometry": {"coordinates":[12.8474750519,47.426410675],"type":"Point"}
}