{
  "type": "Feature",
  "properties": {
    "addr:full":"Nr 205 Strallegg Steiermark 8192",
    "addr:postcode":"8192",
    "addr:street":"Nr 205",
    "iso:country":"AT",
    "sg:address":"Nr 205",
    "sg:city":"Strallegg",
    "sg:classifiers":[
        {
            "category":"Taxi",
            "type":"Transportation"
        }
    ],
    "sg:phone":"+43 4331 742626",
    "sg:postcode":"8192",
    "sg:province":"Steiermark",
    "sg:tags":[
        "personentransporte",
        "u"
    ],
    "wof:name":"Krogger & Lechner GesmbH",
    "wof:placetype":"venue"
},
  "geometry": {"coordinates":[15.7248001099,47.4109153748],"type":"Point"}
}