{
  "type": "Feature",
  "properties": {
    "iso:country":"AT",
    "sg:address":"Nr 83",
    "sg:city":"Umhausen",
    "sg:orig_category":"Pensionen / Privatzimmer",
    "sg:phone":"+43 5255 5507",
    "sg:postcode":"6441",
    "sg:province":"Tirol",
    "wof:name":"Haus Matthias",
    "wof:placetype":"venue"
},
  "geometry": {"coordinates":[10.9276542664,47.1393241882],"type":"Point"}
}