{
  "type": "Feature",
  "properties": {
    "iso:country":"AT",
    "sg:address":"K\u00e4ferbichlstr 13",
    "sg:city":"Lackenhof",
    "sg:orig_category":"Feuerwehren",
    "sg:phone":"+43 7480 20010",
    "sg:postcode":"3295",
    "sg:province":"Nieder\u00f6sterreich",
    "wof:name":"Freiwillige Feuerwehr",
    "wof:placetype":"venue"
},
  "geometry": {"coordinates":[15.1546726227,47.8706054688],"type":"Point"}
}