{
  "type": "Feature",
  "properties": {
    "addr:full":"Hauptstrasse 29-33 Stockerau Nieder\u00f6sterreich 2000",
    "addr:postcode":"29-33;2000",
    "addr:street":"Hauptstrasse",
    "iso:country":"AT",
    "sg:address":"Hauptstrasse 29-33",
    "sg:city":"Stockerau",
    "sg:classifiers":[
        {
            "category":"Banks & Credit Unions",
            "subcategory":"Investment Brokerage",
            "type":"Services"
        }
    ],
    "sg:phone":"+43 2266 62970",
    "sg:postcode":"2000",
    "sg:province":"Nieder\u00f6sterreich",
    "sg:tags":[
        "case",
        "spectacle"
    ],
    "sg:website":"kelterer.at",
    "wof:name":"Kelterer Ges.m.b.H.",
    "wof:placetype":"venue"
},
  "geometry": {"coordinates":[16.2118721008,48.38539505],"type":"Point"}
}