{
  "type": "Feature",
  "properties": {
    "addr:full":"Ziehrerstr 7 Wels Ober\u00f6sterreich 4600",
    "addr:housenumber":"7",
    "addr:postcode":"4600",
    "addr:street":"Ziehrerstr;Oberoesterreich",
    "iso:country":"AT",
    "sg:address":"Ziehrerstr 7",
    "sg:city":"Wels",
    "sg:orig_category":"Immobilienmakler",
    "sg:phone":"+43 7242 68978",
    "sg:postcode":"4600",
    "sg:province":"Ober\u00f6sterreich",
    "wof:name":"Ranzmeir Immobilien",
    "wof:placetype":"venue"
},
  "geometry": {"coordinates":[14.0046100616,48.171710968],"type":"Point"}
}