{
  "type": "Feature",
  "properties": {
    "iso:country":"AT",
    "sg:address":"Mittersteig 13/5",
    "sg:city":"Wien",
    "sg:classifiers":[
        {
            "category":"Professional",
            "subcategory":"Management & Consulting",
            "type":"Services"
        }
    ],
    "sg:phone":"+43 1 5871010",
    "sg:postcode":"1040",
    "sg:province":"Wien",
    "sg:tags":[
        "consultancy"
    ],
    "wof:name":"MPC Unternehmensberatungsges.m.b.H.",
    "wof:placetype":"venue"
},
  "geometry": {"coordinates":[16.3634128571,48.1911468506],"type":"Point"}
}