{
  "type": "Feature",
  "properties": {
    "addr:full":"Mettmach Ober\u00f6sterreich 4931",
    "addr:postcode":"4931",
    "addr:street":"Oberoesterreich",
    "iso:country":"AT",
    "sg:city":"Mettmach",
    "sg:orig_category":"Feuerwehren",
    "sg:phone":"+43 7755 7254",
    "sg:postcode":"4931",
    "sg:province":"Ober\u00f6sterreich",
    "wof:name":"Freiwillige Feuerwehr Neundling",
    "wof:placetype":"venue"
},
  "geometry": {"coordinates":[13.3672409058,48.1860198975],"type":"Point"}
}