{
  "type": "Feature",
  "properties": {
    "addr:full":"H\u00f6lzelsau 239b Niederndorf Tirol 6342",
    "addr:housenumber":"239b",
    "addr:postcode":"6342",
    "iso:country":"AT",
    "sg:address":"H\u00f6lzelsau 239b",
    "sg:city":"Niederndorf",
    "sg:classifiers":[
        {
            "category":"Home & Garden",
            "subcategory":"Building Materials",
            "type":"Retail Goods"
        }
    ],
    "sg:phone":"+43 5373 61158",
    "sg:postcode":"6342",
    "sg:province":"Tirol",
    "sg:tags":[
        "slab",
        "marble"
    ],
    "wof:name":"Matic Ges.m.b.H.",
    "wof:placetype":"venue"
},
  "geometry": {"coordinates":[12.2130002975,47.6563110352],"type":"Point"}
}