{
  "type": "Feature",
  "properties": {
    "addr:full":"Hauptstr 2 Dr\u00f6sing Nieder\u00f6sterreich 2265",
    "addr:housenumber":"2",
    "addr:postcode":"2265",
    "addr:street":"Hauptstr;Niederoesterreich",
    "iso:country":"AT",
    "sg:address":"Hauptstr 2",
    "sg:city":"Dr\u00f6sing",
    "sg:orig_category":"Fleischhauereien",
    "sg:phone":"+43 2536 7306",
    "sg:postcode":"2265",
    "sg:province":"Nieder\u00f6sterreich",
    "wof:name":"G\u00f6\u00dfl Franz - Partyservice",
    "wof:placetype":"venue"
},
  "geometry": {"coordinates":[-93.4379730225,30.5255451202],"type":"Point"}
}