{
  "type": "Feature",
  "properties": {
    "addr:full":"Johann-Lehner-Str 6 Pasching Ober\u00f6sterreich 4061",
    "addr:housenumber":"6",
    "addr:postcode":"4061",
    "addr:street":"Johann-Lehner-Str;Oberoesterreich",
    "iso:country":"AT",
    "sg:address":"Johann-Lehner-Str 6",
    "sg:city":"Pasching",
    "sg:orig_category":"Unternehmensberatung",
    "sg:phone":"+43 4366 45325633",
    "sg:postcode":"4061",
    "sg:province":"Ober\u00f6sterreich",
    "wof:name":"ConInvest Beratungs- u Beteiligungs GmbH",
    "wof:placetype":"venue"
},
  "geometry": {"coordinates":[14.2030487061,48.2582359314],"type":"Point"}
}