{
  "type": "Feature",
  "properties": {
    "addr:full":"Fattstr 20 Wolfurt Vorarlberg 6922",
    "addr:housenumber":"20",
    "addr:postcode":"6922",
    "addr:street":"Fattstr",
    "iso:country":"AT",
    "sg:address":"Fattstr 20",
    "sg:city":"Wolfurt",
    "sg:orig_category":"Tischlereien",
    "sg:phone":"+43 5574 74911",
    "sg:postcode":"6922",
    "sg:province":"Vorarlberg",
    "wof:name":"Aichholzer Wolfgang",
    "wof:placetype":"venue"
},
  "geometry": {"coordinates":[9.7442407608,47.4737052917],"type":"Point"}
}