{
  "type": "Feature",
  "properties": {
    "iso:country":"AT",
    "sg:address":"Beethoveng 10",
    "sg:city":"Baden",
    "sg:classifiers":[
        {
            "category":"Restaurant",
            "type":"Food & Drink"
        }
    ],
    "sg:phone":"+43 2252 43025",
    "sg:postcode":"2500",
    "sg:province":"Nieder\u00f6sterreich",
    "wof:name":"Pauli's Bar & Restaurant",
    "wof:placetype":"venue"
},
  "geometry": {"coordinates":[16.2326545715,48.0079994202],"type":"Point"}
}