{
  "type": "Feature",
  "properties": {
    "addr:full":"Matzner Str 2 Spannberg Nieder\u00f6sterreich 2244",
    "addr:housenumber":"2",
    "addr:postcode":"2244",
    "addr:street":"Str",
    "iso:country":"AT",
    "sg:address":"Matzner Str 2",
    "sg:city":"Spannberg",
    "sg:orig_category":"Transportunternehmen",
    "sg:phone":"+43 2538 85382",
    "sg:postcode":"2244",
    "sg:province":"Nieder\u00f6sterreich",
    "wof:name":"Westermayr GesmbH",
    "wof:placetype":"venue"
},
  "geometry": {"coordinates":[16.7345714569,48.4638214111],"type":"Point"}
}