{
  "type": "Feature",
  "properties": {
    "addr:full":"Nr 76 Kammersdorf Nieder\u00f6sterreich 2033",
    "addr:postcode":"2033",
    "addr:street":"Nr;Kammersdorf",
    "iso:country":"AT",
    "sg:address":"Nr 76",
    "sg:city":"Kammersdorf",
    "sg:classifiers":[
        {
            "category":"Professional",
            "subcategory":"Computer Services",
            "type":"Services"
        }
    ],
    "sg:phone":"+43 2953 2311",
    "sg:postcode":"2033",
    "sg:province":"Nieder\u00f6sterreich",
    "sg:tags":[
        "software"
    ],
    "wof:name":"B\u00f6ck Reinhard",
    "wof:placetype":"venue"
},
  "geometry": {"coordinates":[16.2387676239,48.6305541992],"type":"Point"}
}