{
  "type": "Feature",
  "properties": {
    "addr:full":"Bahnhofstr 43a Zeltweg Steiermark 8740",
    "addr:housenumber":"43a",
    "addr:postcode":"8740",
    "addr:street":"Bahnhofstr",
    "iso:country":"AT",
    "sg:address":"Bahnhofstr 43a",
    "sg:city":"Zeltweg",
    "sg:orig_category":"Damenmoden",
    "sg:phone":"+43 3577 22838",
    "sg:postcode":"8740",
    "sg:province":"Steiermark",
    "wof:name":"Modella - Mode f d Dame",
    "wof:placetype":"venue"
},
  "geometry": {"coordinates":[14.7539243698,47.1898994446],"type":"Point"}
}