{
  "type": "Feature",
  "properties": {
    "addr:full":"Landstra\u00dfer Hauptstr 72/2 Wien Wien 1030",
    "addr:housenumber":"72 / 2",
    "addr:postcode":"1030",
    "addr:street":"Landstrasser Hauptstr",
    "iso:country":"AT",
    "sg:address":"Landstra\u00dfer Hauptstr 72/2",
    "sg:city":"Wien",
    "sg:orig_category":"Psychotherapie",
    "sg:phone":"+43 1 7109841",
    "sg:postcode":"1030",
    "sg:province":"Wien",
    "wof:name":"Wallisch Karin Mag",
    "wof:placetype":"venue"
},
  "geometry": {"coordinates":[16.392124176,48.2010116577],"type":"Point"}
}