{
  "type": "Feature",
  "properties": {
    "iso:country":"AT",
    "sg:address":"Altmannsdorfer Str 144",
    "sg:city":"Wien",
    "sg:orig_category":"Mikrofilme",
    "sg:phone":"+43 1 80350910",
    "sg:postcode":"1230",
    "sg:province":"Wien",
    "wof:name":"EMD Elektronische- und Mikrofilm-Dokumentationssysteme GesmbH",
    "wof:placetype":"venue"
},
  "geometry": {"coordinates":[16.3190231323,48.1564102173],"type":"Point"}
}