{
  "type": "Feature",
  "properties": {
    "iso:country":"AT",
    "sg:address":"Wiener Strasse 132",
    "sg:city":"Hollabrunn",
    "sg:classifiers":[
        {
            "category":"Home & Garden",
            "subcategory":"Hardware",
            "type":"Retail Goods"
        }
    ],
    "sg:phone":"+43 2952 20221",
    "sg:postcode":"2020",
    "sg:province":"Nieder\u00f6sterreich",
    "sg:tags":[
        "agricultural",
        "implement"
    ],
    "sg:website":"lemken.com",
    "wof:name":"LEMKEN AUSTRIA GmbH",
    "wof:placetype":"venue"
},
  "geometry": {"coordinates":[16.078956604,48.5488471985],"type":"Point"}
}