{
  "type": "Feature",
  "properties": {
    "addr:full":"Lichtersberg 83 Altaussee Steiermark 8992",
    "addr:housenumber":"83",
    "addr:postcode":"8992",
    "addr:street":"Lichtersberg",
    "iso:country":"AT",
    "sg:address":"Lichtersberg 83",
    "sg:city":"Altaussee",
    "sg:classifiers":[
        {
            "category":"Park",
            "subcategory":"Provincial",
            "type":"Public Place"
        }
    ],
    "sg:phone":"+43 4366 43238623",
    "sg:postcode":"8992",
    "sg:province":"Steiermark",
    "sg:tags":[
        "u",
        "ski-",
        "snowboardschulen"
    ],
    "wof:name":"Haim Andreas - Schischule u Schiverleih",
    "wof:placetype":"venue"
},
  "geometry": {"coordinates":[13.7858734131,47.6610450745],"type":"Point"}
}