{
  "type": "Feature",
  "properties": {
    "iso:country":"AT",
    "sg:address":"Pfarrhofstr 5",
    "sg:city":"Roitham",
    "sg:orig_category":"Non-Classified Establishments",
    "sg:phone":"+43 76135108",
    "sg:postcode":"4661",
    "sg:province":"Ober\u00f6sterreich",
    "wof:name":"Pfarramt",
    "wof:placetype":"venue"
},
  "geometry": {"coordinates":[13.8236541748,48.0251121521],"type":"Point"}
}