{
  "type": "Feature",
  "properties": {
    "addr:full":"Grazer Str. 26-28  Wolfsberg K\u00e4rnten 9400",
    "addr:postcode":"26-28;9400",
    "addr:street":"Str.",
    "iso:country":"AT",
    "sg:address":"Grazer Str. 26-28 ",
    "sg:city":"Wolfsberg",
    "sg:classifiers":[
        {
            "category":"Shopping",
            "type":"Retail Goods"
        }
    ],
    "sg:phone":"+43 4343 5221570",
    "sg:postcode":"9400",
    "sg:province":"K\u00e4rnten",
    "sg:tags":[
        "finished",
        "-",
        "metallic"
    ],
    "wof:name":"KOHLBACH GMBH & CO",
    "wof:placetype":"venue"
},
  "geometry": {"coordinates":[14.8433551788,46.8449668884],"type":"Point"}
}