{
  "type": "Feature",
  "properties": {
    "addr:full":"Gruberstrasse 2-6 Linz Ober\u00f6sterreich 4020",
    "addr:housenumber":"2-6",
    "addr:postcode":"4020",
    "addr:street":"Gruberstrasse",
    "iso:country":"AT",
    "sg:address":"Gruberstrasse 2-6",
    "sg:city":"Linz",
    "sg:classifiers":[
        {
            "category":"Professional",
            "subcategory":"Advertising",
            "type":"Services"
        }
    ],
    "sg:phone":"+43 732 7722550",
    "sg:postcode":"4020",
    "sg:province":"Ober\u00f6sterreich",
    "sg:tags":[
        "marketing",
        "direct"
    ],
    "sg:website":"imas-international.com",
    "wof:name":"IMAS International Institut f\u00fcr Markt- und Sozialanalyse Ges.m.b.H.",
    "wof:placetype":"venue"
},
  "geometry": {"coordinates":[14.2965784073,48.3115692139],"type":"Point"}
}