{
  "type": "Feature",
  "properties": {
    "addr:full":"Nr 268 Alpbach Tirol 6236",
    "addr:postcode":"6236",
    "addr:street":"Nr;Alpbach Tirol",
    "iso:country":"AT",
    "sg:address":"Nr 268",
    "sg:city":"Alpbach",
    "sg:orig_category":"Pensionen / Privatzimmer",
    "sg:phone":"+43 4353 365988",
    "sg:postcode":"6236",
    "sg:province":"Tirol",
    "wof:name":"Haus Rosenheim",
    "wof:placetype":"venue"
},
  "geometry": {"coordinates":[11.9435110092,47.3986091614],"type":"Point"}
}