{
  "type": "Feature",
  "properties": {
    "addr:full":"Am Gries 6 Ybbsitz Nieder\u00f6sterreich 3341",
    "addr:housenumber":"6",
    "addr:postcode":"3341",
    "addr:street":"Am Gries",
    "iso:country":"AT",
    "sg:address":"Am Gries 6",
    "sg:city":"Ybbsitz",
    "sg:orig_category":"Metallwaren / Erzeugung U Gro\u00c3\u0178handel",
    "sg:phone":"+43 4374 43865050",
    "sg:postcode":"3341",
    "sg:province":"Nieder\u00f6sterreich",
    "wof:name":"Fuchs Dietrich GesmbH",
    "wof:placetype":"venue"
},
  "geometry": {"coordinates":[14.8740625381,47.9442481995],"type":"Point"}
}