{
  "type": "Feature",
  "properties": {
    "iso:country":"AT",
    "sg:address":"Pichling Lunapl 1",
    "sg:city":"Linz",
    "sg:orig_category":"Banken U Sparkassen",
    "sg:phone":"+43 4373 23200260",
    "sg:postcode":"4030",
    "sg:province":"Ober\u00f6sterreich",
    "wof:name":"HYPO Ober\u00f6sterreich, O\u00f6 Landesbank AG - solarCity",
    "wof:placetype":"venue"
},
  "geometry": {"coordinates":[14.3069601059,48.2325248718],"type":"Point"}
}