{
  "type": "Feature",
  "properties": {
    "addr:full":"Innsbrucker Str 60 Hall in Tirol Tirol 6060",
    "addr:housenumber":"60",
    "addr:postcode":"6060",
    "addr:street":"Str;Tirol",
    "iso:country":"AT",
    "sg:address":"Innsbrucker Str 60",
    "sg:city":"Hall in Tirol",
    "sg:orig_category":"Lebensmittel / Einzelhandel",
    "sg:phone":"+43 5223 42070",
    "sg:postcode":"6060",
    "sg:province":"Tirol",
    "wof:name":"Onay + Ayyildiz -T\u00fcrk Spezialit\u00e4ten",
    "wof:placetype":"venue"
},
  "geometry": {"coordinates":[11.4878969193,47.2773361206],"type":"Point"}
}