{
  "type": "Feature",
  "properties": {
    "iso:country":"AT",
    "sg:address":"Maurach 266c",
    "sg:city":"Jenbach",
    "sg:classifiers":[
        {
            "category":"Professional",
            "subcategory":"Computer Services",
            "type":"Services"
        }
    ],
    "sg:phone":"+43 5244 638780",
    "sg:postcode":"6200",
    "sg:province":"Tirol",
    "sg:tags":[
        "software"
    ],
    "wof:name":"Dialsoft Software GesmbH",
    "wof:placetype":"venue"
},
  "geometry": {"coordinates":[11.7814903259,47.382648468],"type":"Point"}
}