{
  "type": "Feature",
  "properties": {
    "iso:country":"AT",
    "sg:address":"Kirchg 7",
    "sg:city":"Axams",
    "sg:orig_category":"Gemeinden",
    "sg:phone":"+43 5234 68387",
    "sg:postcode":"6094",
    "sg:province":"Tirol",
    "wof:name":"Gemeindeamt Grinzens",
    "wof:placetype":"venue"
},
  "geometry": {"coordinates":[11.2556905746,47.230884552],"type":"Point"}
}