{
  "type": "Feature",
  "properties": {
    "addr:full":"Am Breitenstein 5 Hellmons\u00f6dt Ober\u00f6sterreich 4202",
    "addr:housenumber":"5",
    "addr:postcode":"4202",
    "addr:street":"Am Breitenstein;Oberoesterreich",
    "iso:country":"AT",
    "sg:address":"Am Breitenstein 5",
    "sg:city":"Hellmons\u00f6dt",
    "sg:orig_category":"Garten- U Landschaftsgestaltung",
    "sg:phone":"+43 4372 15344022",
    "sg:postcode":"4202",
    "sg:province":"Ober\u00f6sterreich",
    "wof:name":"Maschinenring- u Betriebshilfering Urfahr",
    "wof:placetype":"venue"
},
  "geometry": {"coordinates":[14.2756567001,48.4133529663],"type":"Point"}
}