{
  "type": "Feature",
  "properties": {
    "addr:full":"Nisselg 16 Wien Wien 1140",
    "addr:housenumber":"16",
    "addr:postcode":"1140",
    "addr:street":"Nisselg",
    "iso:country":"AT",
    "sg:address":"Nisselg 16",
    "sg:city":"Wien",
    "sg:orig_category":"Messerschleifereien",
    "sg:phone":"+43 4318 945587",
    "sg:postcode":"1140",
    "sg:province":"Wien",
    "wof:name":"Messerschleiferei Nagl",
    "wof:placetype":"venue"
},
  "geometry": {"coordinates":[16.3046627045,48.1897125244],"type":"Point"}
}