{
  "type": "Feature",
  "properties": {
    "addr:full":"Franz-Josef-Str 18 Mistelbach Nieder\u00f6sterreich 2130",
    "addr:housenumber":"18",
    "addr:postcode":"2130",
    "addr:street":"Franz-Josef-Str;Niederoesterreich",
    "iso:country":"AT",
    "sg:address":"Franz-Josef-Str 18",
    "sg:city":"Mistelbach",
    "sg:orig_category":"Stoffe / Erzeugung U Gro\u00c3\u0178handel",
    "sg:phone":"+43 4325 722648",
    "sg:postcode":"2130",
    "sg:province":"Nieder\u00f6sterreich",
    "wof:name":"Stofftruhe Degen Waltraud",
    "wof:placetype":"venue"
},
  "geometry": {"coordinates":[16.5707550049,48.568862915],"type":"Point"}
}