{
  "type": "Feature",
  "properties": {
    "addr:full":"GLOR-BERG 10 Kals am Gro\u00dfglockner Tirol 9981",
    "addr:housenumber":"10",
    "addr:postcode":"9981",
    "addr:street":"Glor-Berg;Grossglockner",
    "iso:country":"AT",
    "sg:address":"GLOR-BERG 10",
    "sg:city":"Kals am Gro\u00dfglockner",
    "sg:orig_category":"Freizeit, Sport",
    "sg:phone":"+43 4876",
    "sg:postcode":"9981",
    "sg:province":"Tirol",
    "sg:website":"http://members.1012surfnet.at/mountain-riding/",
    "wof:name":"MOUNTAIN RIDING CENTER AUSTRIA",
    "wof:placetype":"venue"
},
  "geometry": {"coordinates":[12.6881856918,47.0207748413],"type":"Point"}
}