{
  "type": "Feature",
  "properties": {
    "addr:full":"Steyrer Str 32 Sierning Ober\u00f6sterreich 4522",
    "addr:postcode":"4522",
    "addr:street":"Str 32",
    "iso:country":"AT",
    "sg:address":"Steyrer Str 32",
    "sg:city":"Sierning",
    "sg:classifiers":[
        {
            "category":"Home & Garden",
            "subcategory":"Garden Supply",
            "type":"Retail Goods"
        }
    ],
    "sg:phone":"+43 7259 24020",
    "sg:postcode":"4522",
    "sg:province":"Ober\u00f6sterreich",
    "sg:tags":[
        "schotter",
        "sand",
        "u"
    ],
    "wof:name":"Braun GmbH",
    "wof:placetype":"venue"
},
  "geometry": {"coordinates":[14.3128128052,48.0449562073],"type":"Point"}
}