{
  "type": "Feature",
  "properties": {
    "addr:full":"Hauptstr 19 Leopoldsdorf Nieder\u00f6sterreich 2333",
    "addr:housenumber":"19",
    "addr:postcode":"2333",
    "addr:street":"Hauptstr",
    "iso:country":"AT",
    "sg:address":"Hauptstr 19",
    "sg:city":"Leopoldsdorf",
    "sg:orig_category":"Friseure U Frisiersalons",
    "sg:phone":"+43 4322 3542541",
    "sg:postcode":"2333",
    "sg:province":"Nieder\u00f6sterreich",
    "wof:name":"Studio-A Hair & Beauty",
    "wof:placetype":"venue"
},
  "geometry": {"coordinates":[16.3957462311,48.1084632874],"type":"Point"}
}