{
  "type": "Feature",
  "properties": {
    "addr:full":"Salzburger Str 35 Schwarzach im Pongau Salzburg 5620",
    "addr:housenumber":"35",
    "addr:postcode":"5620",
    "addr:street":"Salzburger Str;Salzburg",
    "iso:country":"AT",
    "sg:address":"Salzburger Str 35",
    "sg:city":"Schwarzach im Pongau",
    "sg:orig_category":"Satellitenempfangsanlagen",
    "sg:phone":"+43 6415 7757",
    "sg:postcode":"5620",
    "sg:province":"Salzburg",
    "wof:name":"Hettegger Hannes",
    "wof:placetype":"venue"
},
  "geometry": {"coordinates":[13.1465921402,47.3202705383],"type":"Point"}
}