{
  "type": "Feature",
  "properties": {
    "addr:full":"Nr 87 Kohfidisch Burgenland 7512",
    "addr:postcode":"7512",
    "addr:street":"Nr",
    "iso:country":"AT",
    "sg:address":"Nr 87",
    "sg:city":"Kohfidisch",
    "sg:orig_category":"Autoreparatur",
    "sg:phone":"+43 664 1516339",
    "sg:postcode":"7512",
    "sg:province":"Burgenland",
    "wof:name":"Perfect Autokosmetik",
    "wof:placetype":"venue"
},
  "geometry": {"coordinates":[16.3575592041,47.1757698059],"type":"Point"}
}