{
  "type": "Feature",
  "properties": {
    "iso:country":"AT",
    "sg:address":"Lessingg 3",
    "sg:city":"Wien",
    "sg:orig_category":"\u00c3\u201erzte / F Allgemeinmedizin",
    "sg:phone":"+43 4312 164038",
    "sg:postcode":"1020",
    "sg:province":"Wien",
    "wof:name":"Assadi Mohammad MedR Dr",
    "wof:placetype":"venue"
},
  "geometry": {"coordinates":[16.3802642822,48.2153701782],"type":"Point"}
}