{
  "type": "Feature",
  "properties": {
    "addr:full":"Dorfstr 116 St. Anton am Arlberg Tirol 6580",
    "addr:housenumber":"116",
    "addr:postcode":"6580",
    "addr:street":"Dorfstr",
    "iso:country":"AT",
    "sg:address":"Dorfstr 116",
    "sg:city":"St. Anton am Arlberg",
    "sg:orig_category":"Pensionen / Privatzimmer",
    "sg:phone":"+43 4354 462597",
    "sg:postcode":"6580",
    "sg:province":"Tirol",
    "wof:name":"Haus Monika - Appartement- u Zimmervermietung - Inh Monika Rose",
    "wof:placetype":"venue"
},
  "geometry": {"coordinates":[10.2724113464,47.1333961487],"type":"Point"}
}