{
  "type": "Feature",
  "properties": {
    "addr:full":"Piaristeng 16 Wien Wien 1080",
    "addr:housenumber":"16",
    "addr:postcode":"1080",
    "addr:street":"Piaristeng",
    "iso:country":"AT",
    "sg:address":"Piaristeng 16",
    "sg:city":"Wien",
    "sg:classifiers":[
        {
            "category":"Professional",
            "subcategory":"Computer Services",
            "type":"Services"
        }
    ],
    "sg:phone":"+43 1 40310940",
    "sg:postcode":"1080",
    "sg:province":"Wien",
    "sg:tags":[
        "software"
    ],
    "wof:name":"Hackhofer E Dr EDV-Softwareberatung Gesellschaft mbH",
    "wof:placetype":"venue"
},
  "geometry": {"coordinates":[16.3513069153,48.2073860168],"type":"Point"}
}