{
  "type": "Feature",
  "properties": {
    "iso:country":"AT",
    "sg:address":"Harter Str 157",
    "sg:city":"Stra\u00dfgang",
    "sg:orig_category":"Fotografen",
    "sg:phone":"+43 664 1007892",
    "sg:postcode":"8054",
    "sg:province":"Steiermark",
    "wof:name":"Fineart Roundshot Austria",
    "wof:placetype":"venue"
},
  "geometry": {"coordinates":[15.400885582,47.0396766663],"type":"Point"}
}