{
  "type": "Feature",
  "properties": {
    "addr:full":"Redtenbacherg. 5 Wien Wien 1160",
    "addr:housenumber":"5",
    "addr:postcode":"1160",
    "addr:street":"Redtenbacherg.",
    "iso:country":"AT",
    "sg:address":"Redtenbacherg. 5",
    "sg:city":"Wien",
    "sg:classifiers":[
        {
            "category":"Manufacturing",
            "subcategory":"Tools & Machinery",
            "type":"Manufacturing & Wholesale Goods"
        }
    ],
    "sg:phone":"+43 4314 861159",
    "sg:postcode":"1160",
    "sg:province":"Wien",
    "sg:tags":[
        "environment",
        "equipment",
        "-"
    ],
    "wof:name":"G. WEINER GMBH",
    "wof:placetype":"venue"
},
  "geometry": {"coordinates":[16.314666748,48.2143287659],"type":"Point"}
}