{
  "type": "Feature",
  "properties": {
    "addr:full":"Innweg 15a Zirl Tirol 6170",
    "addr:housenumber":"15a",
    "addr:postcode":"6170",
    "addr:street":"Innweg;Tirol",
    "iso:country":"AT",
    "sg:address":"Innweg 15a",
    "sg:city":"Zirl",
    "sg:orig_category":"Architekten",
    "sg:phone":"+43 5238 53104",
    "sg:postcode":"6170",
    "sg:province":"Tirol",
    "wof:name":"Kirchmair Peter Arch Mag",
    "wof:placetype":"venue"
},
  "geometry": {"coordinates":[11.2525730133,47.2679672241],"type":"Point"}
}