{
  "type": "Feature",
  "properties": {
    "addr:full":"Wiener Str 3 Horn Nieder\u00f6sterreich 3580",
    "addr:housenumber":"3",
    "addr:postcode":"3580",
    "addr:street":"Horn Niederoesterreich",
    "iso:country":"AT",
    "sg:address":"Wiener Str 3",
    "sg:city":"Horn",
    "sg:orig_category":"Autohandel",
    "sg:phone":"+43 2982 30400",
    "sg:postcode":"3580",
    "sg:province":"Nieder\u00f6sterreich",
    "wof:name":"Scheibelhofer Karl",
    "wof:placetype":"venue"
},
  "geometry": {"coordinates":[15.6574287415,48.6637763977],"type":"Point"}
}