{
  "type": "Feature",
  "properties": {
    "addr:full":"Dorfmeisterg 21 Rust Burgenland 7071",
    "addr:housenumber":"21",
    "addr:postcode":"7071",
    "addr:street":"Dorfmeisterg",
    "iso:country":"AT",
    "sg:address":"Dorfmeisterg 21",
    "sg:city":"Rust",
    "sg:orig_category":"Pensionen / Privatzimmer",
    "sg:phone":"+43 2685 3010",
    "sg:postcode":"7071",
    "sg:province":"Burgenland",
    "wof:name":"Pension Alexander",
    "wof:placetype":"venue"
},
  "geometry": {"coordinates":[16.6668243408,47.8048439026],"type":"Point"}
}