{
  "type": "Feature",
  "properties": {
    "iso:country":"AT",
    "sg:address":"Ferdinand-Porsche-Str 7",
    "sg:city":"Salzburg",
    "sg:orig_category":"Internet-Cafes",
    "sg:phone":"+43 4369 917733177",
    "sg:postcode":"5020",
    "sg:province":"Salzburg",
    "wof:name":"Internetcafe Piterfun",
    "wof:placetype":"venue"
},
  "geometry": {"coordinates":[13.0434703827,47.8121757507],"type":"Point"}
}