{
  "type": "Feature",
  "properties": {
    "addr:full":"St Veiter Str 18/2 Klagenfurt K\u00e4rnten 9020",
    "addr:housenumber":"18 / 2",
    "addr:postcode":"9020",
    "addr:street":"St Veiter Str;Kaernten",
    "iso:country":"AT",
    "sg:address":"St Veiter Str 18/2",
    "sg:city":"Klagenfurt",
    "sg:orig_category":"Psychotherapie",
    "sg:phone":"+43 463 508136",
    "sg:postcode":"9020",
    "sg:province":"K\u00e4rnten",
    "wof:name":"Aspernig Andreas A Dr phil",
    "wof:placetype":"venue"
},
  "geometry": {"coordinates":[14.3096809387,46.6288070679],"type":"Point"}
}