{
  "type": "Feature",
  "properties": {
    "addr:full":"Raiffeisenstr 20 Orth an der Donau Nieder\u00f6sterreich 2304",
    "addr:housenumber":"20",
    "addr:postcode":"2304",
    "addr:street":"Raiffeisenstr",
    "iso:country":"AT",
    "sg:address":"Raiffeisenstr 20",
    "sg:city":"Orth an der Donau",
    "sg:orig_category":"Bodenverlegung",
    "sg:phone":"+43 4322 122404",
    "sg:postcode":"2304",
    "sg:province":"Nieder\u00f6sterreich",
    "wof:name":"FUCHS KARL - Malermeister u. Raumdesigner",
    "wof:placetype":"venue"
},
  "geometry": {"coordinates":[16.6972866058,48.1504631042],"type":"Point"}
}