{
  "type": "Feature",
  "properties": {
    "addr:full":"Langenloiser Str 29 Lengenfeld Nieder\u00f6sterreich 3552",
    "addr:housenumber":"29",
    "addr:postcode":"3552",
    "addr:street":"Str",
    "iso:country":"AT",
    "sg:address":"Langenloiser Str 29",
    "sg:city":"Lengenfeld",
    "sg:orig_category":"Feuerwehren",
    "sg:phone":"+43 2719 8455",
    "sg:postcode":"3552",
    "sg:province":"Nieder\u00f6sterreich",
    "wof:name":"Freiwillige Feuerwehr Lengenfeld",
    "wof:placetype":"venue"
},
  "geometry": {"coordinates":[15.5975093842,48.4717712402],"type":"Point"}
}