{
  "type": "Feature",
  "properties": {
    "addr:full":"Markt 25 Weiden am See Burgenland 7121",
    "addr:housenumber":"25",
    "addr:postcode":"7121",
    "addr:street":"Markt",
    "iso:country":"AT",
    "sg:address":"Markt 25",
    "sg:city":"Weiden am See",
    "sg:orig_category":"Appartements / Ferienwohnungen",
    "sg:phone":"+43 2167 7040",
    "sg:postcode":"7121",
    "sg:province":"Burgenland",
    "wof:name":"Hareter Alexander",
    "wof:placetype":"venue"
},
  "geometry": {"coordinates":[16.8662338257,47.9258613586],"type":"Point"}
}