{
  "type": "Feature",
  "properties": {
    "addr:full":"Oberer Markt 1 Birkfeld Steiermark 8190",
    "addr:housenumber":"1",
    "addr:postcode":"8190",
    "addr:street":"Oberer Markt",
    "iso:country":"AT",
    "sg:address":"Oberer Markt 1",
    "sg:city":"Birkfeld",
    "sg:orig_category":"Steuerberatung",
    "sg:phone":"+43 4331 7442440",
    "sg:postcode":"8190",
    "sg:province":"Steiermark",
    "wof:name":"Rein, Rothwangl u Partner Wirtschaftstreuhand GmbH",
    "wof:placetype":"venue"
},
  "geometry": {"coordinates":[15.6930198669,47.3543014526],"type":"Point"}
}