{
  "type": "Feature",
  "properties": {
    "addr:full":"Nr 16 Wildsch\u00f6nau-Auffach Tirol 6313",
    "addr:postcode":"6313",
    "addr:street":"Nr 16 Wildschoenau-Auffach Tirol",
    "iso:country":"AT",
    "sg:address":"Nr 16",
    "sg:city":"Wildsch\u00f6nau-Auffach",
    "sg:orig_category":"Holzbe U -Verarbeitung",
    "sg:phone":"+43 4353 392480",
    "sg:postcode":"6313",
    "sg:province":"Tirol",
    "wof:name":"Weissbacher Johann - Abbruchholz in S\u00e4gerauhschnitt",
    "wof:placetype":"venue"
},
  "geometry": {"coordinates":[12.0360631943,47.4098701477],"type":"Point"}
}