{
  "type": "Feature",
  "properties": {
    "addr:full":"B\u00f6heimg 1 Wiener Neustadt Nieder\u00f6sterreich 2700",
    "addr:housenumber":"1",
    "addr:postcode":"2700",
    "addr:street":"Boeheimg",
    "iso:country":"AT",
    "sg:address":"B\u00f6heimg 1",
    "sg:city":"Wiener Neustadt",
    "sg:orig_category":"Boutiquen",
    "sg:phone":"+43 4326 2266039",
    "sg:postcode":"2700",
    "sg:province":"Nieder\u00f6sterreich",
    "wof:name":"TRASH FASHION - Belinda Mattehs GmbH",
    "wof:placetype":"venue"
},
  "geometry": {"coordinates":[16.2423152924,47.813709259],"type":"Point"}
}