{
  "type": "Feature",
  "properties": {
    "iso:country":"AT",
    "sg:address":"Volkenstorfstrasse 11",
    "sg:city":"Haid",
    "sg:classifiers":[
        {
            "category":"Government",
            "subcategory":"Fire Station",
            "type":"Public Place"
        }
    ],
    "sg:phone":"+43 699 13500360",
    "sg:postcode":"4053",
    "sg:province":"Ober\u00f6sterreich",
    "sg:tags":[
        "engine",
        "generating",
        "set",
        "diesel",
        "emergency"
    ],
    "wof:name":"Erich Andres",
    "wof:placetype":"venue"
},
  "geometry": {"coordinates":[14.2510099411,48.2047348022],"type":"Point"}
}