{
  "type": "Feature",
  "properties": {
    "addr:full":"Reichsstr 5 Bregenz Vorarlberg 6900",
    "addr:housenumber":"5",
    "addr:postcode":"6900",
    "addr:street":"Reichsstr",
    "iso:country":"AT",
    "sg:address":"Reichsstr 5",
    "sg:city":"Bregenz",
    "sg:orig_category":"Architekten",
    "sg:phone":"+43 5574 542420",
    "sg:postcode":"6900",
    "sg:province":"Vorarlberg",
    "wof:name":"Architekturb\u00fcro Wimmer-Armellini",
    "wof:placetype":"venue"
},
  "geometry": {"coordinates":[9.7502746582,47.5069541931],"type":"Point"}
}