{
  "type": "Feature",
  "properties": {
    "addr:full":"Aberg 2 Pichl Steiermark 8973",
    "addr:housenumber":"2",
    "addr:postcode":"8973",
    "addr:street":"Aberg",
    "iso:country":"AT",
    "sg:address":"Aberg 2",
    "sg:city":"Pichl",
    "sg:orig_category":"Pensionen / Privatzimmer",
    "sg:phone":"+43 4364 547354",
    "sg:postcode":"8973",
    "sg:province":"Steiermark",
    "wof:name":"Engelbert u Heidi Walcher",
    "wof:placetype":"venue"
},
  "geometry": {"coordinates":[13.6136493683,47.3911323547],"type":"Point"}
}