{
  "type": "Feature",
  "properties": {
    "addr:full":"Bahnhofstr 1 Raaba Steiermark 8074",
    "addr:housenumber":"1",
    "addr:postcode":"8074",
    "addr:street":"Bahnhofstr",
    "iso:country":"AT",
    "sg:address":"Bahnhofstr 1",
    "sg:city":"Raaba",
    "sg:orig_category":"Flugzeuge",
    "sg:phone":"+43 4331 6244233",
    "sg:postcode":"8074",
    "sg:province":"Steiermark",
    "wof:name":"Brightline Avionics GmbH",
    "wof:placetype":"venue"
},
  "geometry": {"coordinates":[15.4944791794,47.0300064087],"type":"Point"}
}