{
  "type": "Feature",
  "properties": {
    "addr:full":"Regensburger Str 1 Linz Ober\u00f6sterreich 4020",
    "addr:housenumber":"1",
    "addr:postcode":"4020",
    "addr:street":"Str",
    "iso:country":"AT",
    "sg:address":"Regensburger Str 1",
    "sg:city":"Linz",
    "sg:orig_category":"Exporteure U Importeure",
    "sg:phone":"+43 4373 2776208",
    "sg:postcode":"4020",
    "sg:province":"Ober\u00f6sterreich",
    "wof:name":"Blecha Gertrude",
    "wof:placetype":"venue"
},
  "geometry": {"coordinates":[14.3143234253,48.3116760254],"type":"Point"}
}