{
  "type": "Feature",
  "properties": {
    "addr:full":"Eichetstr 11 Salzburg Salzburg 5020",
    "addr:housenumber":"11",
    "addr:postcode":"5020",
    "addr:street":"Eichetstr;Salzburg",
    "iso:country":"AT",
    "sg:address":"Eichetstr 11",
    "sg:city":"Salzburg",
    "sg:orig_category":"Steuerberatung",
    "sg:phone":"+43 662 8231820",
    "sg:postcode":"5020",
    "sg:province":"Salzburg",
    "wof:name":"Wieder Claudia Mag",
    "wof:placetype":"venue"
},
  "geometry": {"coordinates":[13.015294075,47.7959747314],"type":"Point"}
}