{
  "type": "Feature",
  "properties": {
    "addr:full":"Hauptstr 22 Felixdorf Nieder\u00f6sterreich 2603",
    "addr:housenumber":"22",
    "addr:postcode":"2603",
    "addr:street":"Hauptstr",
    "iso:country":"AT",
    "sg:address":"Hauptstr 22",
    "sg:city":"Felixdorf",
    "sg:orig_category":"Installationsunternehmen",
    "sg:phone":"+43 2628 62633",
    "sg:postcode":"2603",
    "sg:province":"Nieder\u00f6sterreich",
    "wof:name":"Kucharik Wolfgang",
    "wof:placetype":"venue"
},
  "geometry": {"coordinates":[16.2428436279,47.8825492859],"type":"Point"}
}