{
  "type": "Feature",
  "properties": {
    "iso:country":"AT",
    "sg:address":"Eichenstrasse 38",
    "sg:city":"Wien",
    "sg:classifiers":[
        {
            "category":"Wholesale",
            "subcategory":"Construction Materials",
            "type":"Manufacturing & Wholesale Goods"
        }
    ],
    "sg:phone":"+43 1 797260",
    "sg:postcode":"1120",
    "sg:province":"Wien",
    "sg:tags":[
        "sealing",
        "insulating",
        "insulant",
        "moisture"
    ],
    "sg:website":"rockwool.at",
    "wof:name":"Rockwool Handelsges.m.b.H.",
    "wof:placetype":"venue"
},
  "geometry": {"coordinates":[16.3368453979,48.1758804321],"type":"Point"}
}