{
  "type": "Feature",
  "properties": {
    "addr:full":"Europastr 69 Wels Ober\u00f6sterreich 4600",
    "addr:housenumber":"69",
    "addr:postcode":"4600",
    "addr:street":"Europastr;Oberoesterreich",
    "iso:country":"AT",
    "sg:address":"Europastr 69",
    "sg:city":"Wels",
    "sg:orig_category":"Gastronomie- U Hoteleinrichtungen",
    "sg:phone":"+43 7242 66490",
    "sg:postcode":"4600",
    "sg:province":"Ober\u00f6sterreich",
    "wof:name":"EVENT CONCEPT GastronomieeinrichtungsgmbH",
    "wof:placetype":"venue"
},
  "geometry": {"coordinates":[13.9873685837,48.147441864],"type":"Point"}
}