{
  "type": "Feature",
  "properties": {
    "iso:country":"AT",
    "sg:address":"Grazer Str. 249 ",
    "sg:city":"Frauental an der La\u00dfnitz",
    "sg:classifiers":[
        {
            "category":"Food & Beverages",
            "subcategory":"Groceries & Convenience Stores",
            "type":"Retail Goods"
        }
    ],
    "sg:phone":"+43 4334 622302",
    "sg:postcode":"8523",
    "sg:province":"Steiermark",
    "sg:tags":[
        "product",
        "related"
    ],
    "wof:name":"FERDINAND SORGER & SOHN GES.MBH",
    "wof:placetype":"venue"
},
  "geometry": {"coordinates":[15.2452449799,46.8533325195],"type":"Point"}
}