{
  "type": "Feature",
  "properties": {
    "addr:full":"Stranach 109 Mariapfarr Salzburg 5571",
    "addr:housenumber":"109",
    "addr:postcode":"5571",
    "addr:street":"Stranach;Salzburg",
    "iso:country":"AT",
    "sg:address":"Stranach 109",
    "sg:city":"Mariapfarr",
    "sg:orig_category":"Brunnen U Brunnenbau",
    "sg:phone":"+43 4364 7320120",
    "sg:postcode":"5571",
    "sg:province":"Salzburg",
    "wof:name":"WH Quell- u Brunnenbau GmbH Wilhelm H\u00f6negger",
    "wof:placetype":"venue"
},
  "geometry": {"coordinates":[13.7428789139,47.1411170959],"type":"Point"}
}