{
  "type": "Feature",
  "properties": {
    "addr:full":"Dreherstr. 5 Wien Wien 1110",
    "addr:housenumber":"5",
    "addr:postcode":"1110",
    "addr:street":"Dreherstr.",
    "iso:country":"AT",
    "sg:address":"Dreherstr. 5",
    "sg:city":"Wien",
    "sg:classifiers":[
        {
            "category":"Shopping",
            "subcategory":"Crafts & Fabrics",
            "type":"Retail Goods"
        }
    ],
    "sg:phone":"+43 4315 875690",
    "sg:postcode":"1110",
    "sg:province":"Wien",
    "wof:name":"MT-TAPETEN SCHOBA SCHOBA GESMBH & CO KG",
    "wof:placetype":"venue"
},
  "geometry": {"coordinates":[16.4740791321,48.156879425],"type":"Point"}
}