{
  "type": "Feature",
  "properties": {
    "addr:full":"Josef-Sablatnig-Str 310 Klagenfurt K\u00e4rnten 9020",
    "addr:housenumber":"310",
    "addr:postcode":"9020",
    "addr:street":"Kaernten",
    "iso:country":"AT",
    "sg:address":"Josef-Sablatnig-Str 310",
    "sg:city":"Klagenfurt",
    "sg:orig_category":"Metallbau",
    "sg:phone":"+43 463 420480",
    "sg:postcode":"9020",
    "sg:province":"K\u00e4rnten",
    "wof:name":"Starmann Metallbau GmbH",
    "wof:placetype":"venue"
},
  "geometry": {"coordinates":[14.3639783859,46.6426353455],"type":"Point"}
}