{
  "type": "Feature",
  "properties": {
    "iso:country":"AT",
    "sg:address":"Waldweg 14",
    "sg:city":"Wien",
    "sg:orig_category":"Filmproduktionen",
    "sg:phone":"+43 4319 791622",
    "sg:postcode":"1140",
    "sg:province":"Wien",
    "wof:name":"wolcon film - Stefan Wolner",
    "wof:placetype":"venue"
},
  "geometry": {"coordinates":[16.2392044067,48.2154045105],"type":"Point"}
}