{
  "type": "Feature",
  "properties": {
    "addr:full":"Kremsm\u00fcnsterer Str 12 Rohr im Kremstal Ober\u00f6sterreich 4532",
    "addr:housenumber":"12",
    "addr:postcode":"4532",
    "addr:street":"Str",
    "iso:country":"AT",
    "sg:address":"Kremsm\u00fcnsterer Str 12",
    "sg:city":"Rohr im Kremstal",
    "sg:orig_category":"Schneidereien",
    "sg:phone":"+43 7258 3295",
    "sg:postcode":"4532",
    "sg:province":"Ober\u00f6sterreich",
    "wof:name":"Breinesberger Walter",
    "wof:placetype":"venue"
},
  "geometry": {"coordinates":[14.1909427643,48.0679512024],"type":"Point"}
}