{
  "type": "Feature",
  "properties": {
    "addr:full":"Hauptstr 92 Reichenau an der Rax Nieder\u00f6sterreich 2651",
    "addr:housenumber":"92",
    "addr:postcode":"2651",
    "addr:street":"Hauptstr",
    "iso:country":"AT",
    "sg:address":"Hauptstr 92",
    "sg:city":"Reichenau an der Rax",
    "sg:orig_category":"Autoreparatur",
    "sg:phone":"+43 4326 6652424",
    "sg:postcode":"2651",
    "sg:province":"Nieder\u00f6sterreich",
    "wof:name":"BP Austria Marketing GmbH",
    "wof:placetype":"venue"
},
  "geometry": {"coordinates":[15.8366861343,47.6981086731],"type":"Point"}
}