{
  "type": "Feature",
  "properties": {
    "addr:full":"Reischenbachweg 18b Hallein Salzburg 5400",
    "addr:housenumber":"18b",
    "addr:postcode":"5400",
    "addr:street":"Reischenbachweg;Salzburg",
    "iso:country":"AT",
    "sg:address":"Reischenbachweg 18b",
    "sg:city":"Hallein",
    "sg:orig_category":"Weiterbildungsinstitute M Allg U Berufl Bildungsangebot",
    "sg:phone":"+43 4369 912773736",
    "sg:postcode":"5400",
    "sg:province":"Salzburg",
    "wof:name":"Easy Life",
    "wof:placetype":"venue"
},
  "geometry": {"coordinates":[13.0781698227,47.7286605835],"type":"Point"}
}