{
  "type": "Feature",
  "properties": {
    "addr:full":"Laaber Holzweg 50 Braunau am Inn Ober\u00f6sterreich 5280",
    "addr:housenumber":"50",
    "addr:postcode":"5280",
    "addr:street":"Laaber Holzweg",
    "iso:country":"AT",
    "sg:address":"Laaber Holzweg 50",
    "sg:city":"Braunau am Inn",
    "sg:orig_category":"Polizei U Gendarmerie",
    "sg:phone":"+43 5 91334200305",
    "sg:postcode":"5280",
    "sg:province":"Ober\u00f6sterreich",
    "wof:name":"Bezirksgendarmeriekommando Braunau am Inn",
    "wof:placetype":"venue"
},
  "geometry": {"coordinates":[13.0454931259,48.2550697327],"type":"Point"}
}