{
  "type": "Feature",
  "properties": {
    "addr:full":"Bahnhof Umgebung 17 Zirl Tirol 6170",
    "addr:housenumber":"17",
    "addr:postcode":"6170",
    "addr:street":"Bahnhof Umgebung;Tirol",
    "iso:country":"AT",
    "sg:address":"Bahnhof Umgebung 17",
    "sg:city":"Zirl",
    "sg:orig_category":"Betonbohr- U -Schneidedienst",
    "sg:phone":"+43 4352 3852126",
    "sg:postcode":"6170",
    "sg:province":"Tirol",
    "wof:name":"BTT Beton-Trenn-Technik Viertler Werner GmbH & Co KEG",
    "wof:placetype":"venue"
},
  "geometry": {"coordinates":[11.2295875549,47.2662582397],"type":"Point"}
}