{
  "type": "Feature",
  "properties": {
    "addr:full":"Dr K Federhofer-Str 21 Knittelfeld Steiermark 8720",
    "addr:housenumber":"21",
    "addr:postcode":"8720",
    "addr:street":"Dr;Federhofer-Str",
    "iso:country":"AT",
    "sg:address":"Dr K Federhofer-Str 21",
    "sg:city":"Knittelfeld",
    "sg:orig_category":"Sportschulen",
    "sg:phone":"+43 664 3926002",
    "sg:postcode":"8720",
    "sg:province":"Steiermark",
    "wof:name":"WingTsun Selbstverteidigungsschulen",
    "wof:placetype":"venue"
},
  "geometry": {"coordinates":[14.8095273972,47.2109489441],"type":"Point"}
}