{
  "type": "Feature",
  "properties": {
    "addr:full":"Friedrich-Schmolka-Str 19 Kottingbrunn Nieder\u00f6sterreich 2542",
    "addr:housenumber":"19",
    "addr:postcode":"2542",
    "addr:street":"Friedrich-Schmolka-Str",
    "iso:country":"AT",
    "sg:address":"Friedrich-Schmolka-Str 19",
    "sg:city":"Kottingbrunn",
    "sg:orig_category":"Innenausbau",
    "sg:phone":"+43 4322 5272796",
    "sg:postcode":"2542",
    "sg:province":"Nieder\u00f6sterreich",
    "wof:name":"Warner Gerhard",
    "wof:placetype":"venue"
},
  "geometry": {"coordinates":[16.2268447876,47.9588012695],"type":"Point"}
}