{
  "type": "Feature",
  "properties": {
    "addr:full":"Nr 87 Pians Tirol 6551",
    "addr:postcode":"6551",
    "addr:street":"Nr;Pians Tirol",
    "iso:country":"AT",
    "sg:address":"Nr 87",
    "sg:city":"Pians",
    "sg:orig_category":"Volksschulen",
    "sg:phone":"+43 4354 4264032",
    "sg:postcode":"6551",
    "sg:province":"Tirol",
    "wof:name":"Volksschule",
    "wof:placetype":"venue"
},
  "geometry": {"coordinates":[10.5105829239,47.1345748901],"type":"Point"}
}