{
  "type": "Feature",
  "properties": {
    "addr:full":"Hauptpl 49 Wildon Steiermark 8410",
    "addr:housenumber":"49",
    "addr:postcode":"8410",
    "addr:street":"Hauptpl;Steiermark",
    "iso:country":"AT",
    "sg:address":"Hauptpl 49",
    "sg:city":"Wildon",
    "sg:orig_category":"Textilreinigung",
    "sg:phone":"+43 3182 2664",
    "sg:postcode":"8410",
    "sg:province":"Steiermark",
    "wof:name":"Konrad Ernst",
    "wof:placetype":"venue"
},
  "geometry": {"coordinates":[15.5127029419,46.8870391846],"type":"Point"}
}