{
  "type": "Feature",
  "properties": {
    "addr:full":"Hauptschulplatz 3 Leobersdorf Nieder\u00f6sterreich 2544",
    "addr:housenumber":"3",
    "addr:postcode":"2544",
    "addr:street":"Hauptschulplatz",
    "iso:country":"AT",
    "sg:address":"Hauptschulplatz 3",
    "sg:city":"Leobersdorf",
    "sg:classifiers":[
        {
            "category":"Building & Trades",
            "subcategory":"Electrical",
            "type":"Services"
        }
    ],
    "sg:phone":"+43 2256 62293",
    "sg:postcode":"2544",
    "sg:province":"Nieder\u00f6sterreich",
    "sg:tags":[
        "work",
        "installation"
    ],
    "wof:name":"Elektro W\u00f6hrer GmbH",
    "wof:placetype":"venue"
},
  "geometry": {"coordinates":[16.2156162262,47.9298858643],"type":"Point"}
}