{
  "type": "Feature",
  "properties": {
    "addr:full":"Hauptpl 8 Ziersdorf Nieder\u00f6sterreich 3710",
    "addr:housenumber":"8",
    "addr:postcode":"3710",
    "addr:street":"Hauptpl",
    "iso:country":"AT",
    "sg:address":"Hauptpl 8",
    "sg:city":"Ziersdorf",
    "sg:orig_category":"Tabaktrafiken",
    "sg:phone":"+43 2956 2425",
    "sg:postcode":"3710",
    "sg:province":"Nieder\u00f6sterreich",
    "wof:name":"Mantler Maria",
    "wof:placetype":"venue"
},
  "geometry": {"coordinates":[15.9268627167,48.5279159546],"type":"Point"}
}