{
  "type": "Feature",
  "properties": {
    "addr:full":"Mesnergut 9 Dornbirn Vorarlberg 6850",
    "addr:housenumber":"9",
    "addr:postcode":"6850",
    "addr:street":"Mesnergut",
    "iso:country":"AT",
    "sg:address":"Mesnergut 9",
    "sg:city":"Dornbirn",
    "sg:classifiers":[
        {
            "category":"Home & Garden",
            "subcategory":"Household Appliances",
            "type":"Retail Goods"
        }
    ],
    "sg:phone":"+43 5572 24626",
    "sg:postcode":"6850",
    "sg:province":"Vorarlberg",
    "sg:tags":[
        "electric"
    ],
    "wof:name":"Elektro Hanno Mair",
    "wof:placetype":"venue"
},
  "geometry": {"coordinates":[9.7492704391,47.4296913147],"type":"Point"}
}