{
  "type": "Feature",
  "properties": {
    "iso:country":"AT",
    "sg:address":"Kollburggasse 15",
    "sg:city":"Wien",
    "sg:classifiers":[
        {
            "category":"Professional",
            "subcategory":"Advertising",
            "type":"Services"
        }
    ],
    "sg:phone":"+43 1 4862621",
    "sg:postcode":"1160",
    "sg:province":"Wien",
    "sg:tags":[
        "agency"
    ],
    "sg:website":"advertiser.at",
    "wof:name":"Advertiser Werbeagentur G.M. Dremsek Ges.m.b.H.",
    "wof:placetype":"venue"
},
  "geometry": {"coordinates":[16.3007297516,48.2170639038],"type":"Point"}
}