{
  "type": "Feature",
  "properties": {
    "addr:full":"Stadtpl 44 Braunau am Inn Ober\u00f6sterreich 5280",
    "addr:housenumber":"44",
    "addr:postcode":"5280",
    "addr:street":"Stadtpl",
    "iso:country":"AT",
    "sg:address":"Stadtpl 44",
    "sg:city":"Braunau am Inn",
    "sg:orig_category":"Lebensmittel / Einzelhandel",
    "sg:phone":"+43 7722 81008",
    "sg:postcode":"5280",
    "sg:province":"Ober\u00f6sterreich",
    "wof:name":"Billa AG Abt Corso",
    "wof:placetype":"venue"
},
  "geometry": {"coordinates":[13.0352535248,48.2584991455],"type":"Point"}
}