{
  "type": "Feature",
  "properties": {
    "addr:full":"Marienpark 64 Admont Steiermark 8911",
    "addr:housenumber":"64",
    "addr:postcode":"8911",
    "addr:street":"Marienpark",
    "iso:country":"AT",
    "sg:address":"Marienpark 64",
    "sg:city":"Admont",
    "sg:orig_category":"Non-Classified Establishments",
    "sg:phone":"+43 5 91336341",
    "sg:postcode":"8911",
    "sg:province":"Steiermark",
    "wof:name":"Gendarmerieposten",
    "wof:placetype":"venue"
},
  "geometry": {"coordinates":[14.4606122971,47.5739822388],"type":"Point"}
}