{
  "type": "Feature",
  "properties": {
    "addr:full":"Kempeleng 20 Wien Wien 1100",
    "addr:housenumber":"20",
    "addr:postcode":"1100",
    "addr:street":"Kempeleng",
    "iso:country":"AT",
    "sg:address":"Kempeleng 20",
    "sg:city":"Wien",
    "sg:orig_category":"Berufsschulen",
    "sg:phone":"+43 1 5991695145",
    "sg:postcode":"1100",
    "sg:province":"Wien",
    "wof:name":"Berufsschule f\u00fcr Einzelhandel IV",
    "wof:placetype":"venue"
},
  "geometry": {"coordinates":[16.3929748535,48.1730270386],"type":"Point"}
}