{
  "type": "Feature",
  "properties": {
    "addr:full":"Igler Str 58a Innsbruck-Igls Tirol 6080",
    "addr:housenumber":"58a",
    "addr:postcode":"6080",
    "addr:street":"Str",
    "iso:country":"AT",
    "sg:address":"Igler Str 58a",
    "sg:city":"Innsbruck-Igls",
    "sg:orig_category":"Feuerwehren",
    "sg:phone":"+43 512 377390",
    "sg:postcode":"6080",
    "sg:province":"Tirol",
    "wof:name":"Freiwillige Feuerwehr Igls",
    "wof:placetype":"venue"
},
  "geometry": {"coordinates":[11.4068813324,47.2302894592],"type":"Point"}
}