{
  "type": "Feature",
  "properties": {
    "addr:full":"Egon-Schiele-G 9 Traiskirchen Nieder\u00f6sterreich 2514",
    "addr:housenumber":"9",
    "addr:postcode":"2514",
    "addr:street":"Egon-Schiele-G;Niederoesterreich",
    "iso:country":"AT",
    "sg:address":"Egon-Schiele-G 9",
    "sg:city":"Traiskirchen",
    "sg:orig_category":"Installationsunternehmen",
    "sg:phone":"+43 4367 67336705",
    "sg:postcode":"2514",
    "sg:province":"Nieder\u00f6sterreich",
    "wof:name":"Heintschel Robert",
    "wof:placetype":"venue"
},
  "geometry": {"coordinates":[16.2863788605,48.0186309814],"type":"Point"}
}