{
  "type": "Feature",
  "properties": {
    "iso:country":"AT",
    "sg:address":"Kreuzgasse 18",
    "sg:city":"Wien",
    "sg:classifiers":[
        {
            "category":"Manufacturing",
            "subcategory":"Glass & Minerals",
            "type":"Manufacturing & Wholesale Goods"
        }
    ],
    "sg:phone":"+43 1 4078136",
    "sg:postcode":"1180",
    "sg:province":"Wien",
    "sg:tags":[
        "industrial",
        "working"
    ],
    "sg:website":"glaserei-hrouda-kurt.at",
    "wof:name":"Kurt Hrouda",
    "wof:placetype":"venue"
},
  "geometry": {"coordinates":[16.341003418,48.2225952148],"type":"Point"}
}