{
  "type": "Feature",
  "properties": {
    "addr:full":"Drautalstr 24 M\u00f6llbr\u00fccke K\u00e4rnten 9813",
    "addr:housenumber":"24",
    "addr:postcode":"9813",
    "addr:street":"Drautalstr;Kaernten",
    "iso:country":"AT",
    "sg:address":"Drautalstr 24",
    "sg:city":"M\u00f6llbr\u00fccke",
    "sg:orig_category":"Abfallentsorgung U -Verwertung",
    "sg:phone":"+43 4347 693500",
    "sg:postcode":"9813",
    "sg:province":"K\u00e4rnten",
    "wof:name":"DE PIERO Schrott GmbH",
    "wof:placetype":"venue"
},
  "geometry": {"coordinates":[13.3657817841,46.8320198059],"type":"Point"}
}