{
  "type": "Feature",
  "properties": {
    "addr:full":"Stiegengasse 5/5 Wien Wien 1060",
    "addr:housenumber":"5 / 5",
    "addr:postcode":"1060",
    "addr:street":"Stiegengasse",
    "iso:country":"AT",
    "sg:address":"Stiegengasse 5/5",
    "sg:city":"Wien",
    "sg:classifiers":[
        {
            "category":"Manufacturing",
            "subcategory":"Wood Products",
            "type":"Manufacturing & Wholesale Goods"
        }
    ],
    "sg:phone":"+43 1 58648000",
    "sg:postcode":"1060",
    "sg:province":"Wien",
    "sg:tags":[
        "lumber"
    ],
    "sg:website":"vesely.at",
    "wof:name":"Alfred Vesely TIMBER-EXPORT",
    "wof:placetype":"venue"
},
  "geometry": {"coordinates":[16.3579807281,48.1976394653],"type":"Point"}
}