{
  "type": "Feature",
  "properties": {
    "addr:full":"Weilhartstr 48 Ostermiething Ober\u00f6sterreich 5121",
    "addr:housenumber":"48",
    "addr:postcode":"5121",
    "addr:street":"Weilhartstr",
    "iso:country":"AT",
    "sg:address":"Weilhartstr 48",
    "sg:city":"Ostermiething",
    "sg:orig_category":"Friseure U Frisiersalons",
    "sg:phone":"+43 4362 787274",
    "sg:postcode":"5121",
    "sg:province":"Ober\u00f6sterreich",
    "wof:name":"Friseur Kreativ",
    "wof:placetype":"venue"
},
  "geometry": {"coordinates":[12.8308019638,48.0447463989],"type":"Point"}
}