{
  "type": "Feature",
  "properties": {
    "addr:full":"Herzog-Albrecht-Str Mistelbach Nieder\u00f6sterreich 2130",
    "addr:postcode":"2130",
    "addr:street":"Niederoesterreich",
    "iso:country":"AT",
    "sg:address":"Herzog-Albrecht-Str",
    "sg:city":"Mistelbach",
    "sg:orig_category":"Lebensmittel / Einzelhandel",
    "sg:phone":"+43 4325 7220323",
    "sg:postcode":"2130",
    "sg:province":"Nieder\u00f6sterreich",
    "wof:name":"Billa AG",
    "wof:placetype":"venue"
},
  "geometry": {"coordinates":[16.5909042358,48.5677909851],"type":"Point"}
}