{
  "type": "Feature",
  "properties": {
    "addr:full":"Untere Klaus 183 Schladming Steiermark 8970",
    "addr:housenumber":"183",
    "addr:postcode":"8970",
    "addr:street":"Untere Klaus",
    "iso:country":"AT",
    "sg:address":"Untere Klaus 183",
    "sg:city":"Schladming",
    "sg:orig_category":"Energietechnik",
    "sg:phone":"+43 3687 23191",
    "sg:postcode":"8970",
    "sg:province":"Steiermark",
    "sg:website":"lackner-bhkw.at",
    "wof:name":"Lackner Energietechnik GmbH",
    "wof:placetype":"venue"
},
  "geometry": {"coordinates":[13.7011709213,47.4016685486],"type":"Point"}
}