{
  "type": "Feature",
  "properties": {
    "addr:full":"Rottenbacher Strasse 23 Haag am Hausruck Ober\u00f6sterreich 4680",
    "addr:housenumber":"23",
    "addr:postcode":"4680",
    "addr:street":"Rottenbacher Strasse",
    "iso:country":"AT",
    "sg:address":"Rottenbacher Strasse 23",
    "sg:city":"Haag am Hausruck",
    "sg:classifiers":[
        {
            "category":"Home & Garden",
            "subcategory":"Home Furnishings",
            "type":"Retail Goods"
        }
    ],
    "sg:phone":"+43 7732 39110",
    "sg:postcode":"4680",
    "sg:province":"Ober\u00f6sterreich",
    "sg:tags":[
        "bathroom",
        "wc",
        "fitting"
    ],
    "sg:website":"schroegenauer.at",
    "wof:name":"Franz Schr\u00f6genauer Ges.m.b.H.",
    "wof:placetype":"venue"
},
  "geometry": {"coordinates":[13.6515769958,48.1863365173],"type":"Point"}
}