{
  "type": "Feature",
  "properties": {
    "iso:country":"AT",
    "sg:address":"Porzellang 44",
    "sg:city":"Wien",
    "sg:orig_category":"Architekten",
    "sg:phone":"+43 676 4148893",
    "sg:postcode":"1090",
    "sg:province":"Wien",
    "wof:name":"Falkner Rupert Mag arch",
    "wof:placetype":"venue"
},
  "geometry": {"coordinates":[16.361656189,48.2232246399],"type":"Point"}
}