{
  "type": "Feature",
  "properties": {
    "iso:country":"AT",
    "sg:address":"Augasse 15",
    "sg:city":"Bad Sauerbrunn",
    "sg:classifiers":[
        {
            "category":"Shopping",
            "subcategory":"Clothing, Apparel, & Fashions",
            "type":"Retail Goods"
        }
    ],
    "sg:phone":"+43 4326 25323080",
    "sg:postcode":"7202",
    "sg:province":"Burgenland",
    "sg:tags":[
        "clothes"
    ],
    "wof:name":"ALTESSA STRICKWARENFABRIK GMBH NFG. KG",
    "wof:placetype":"venue"
},
  "geometry": {"coordinates":[16.3304862976,47.778553009],"type":"Point"}
}