{
  "type": "Feature",
  "properties": {
    "iso:country":"AT",
    "sg:address":"Tegetthoffstr 7",
    "sg:city":"Wien",
    "sg:orig_category":"Werbegestalter",
    "sg:phone":"+43 1 514034193",
    "sg:postcode":"1010",
    "sg:province":"Wien",
    "wof:name":"manaconsult Unternehmensberatungs-GmbH",
    "wof:placetype":"venue"
},
  "geometry": {"coordinates":[16.3694572449,48.2046051025],"type":"Point"}
}