{
  "type": "Feature",
  "properties": {
    "addr:full":"Dr.-Karl-Renner-Str 3 Eisenerz Steiermark 8790",
    "addr:housenumber":"3",
    "addr:postcode":"8790",
    "addr:street":"Dr.-Karl-Renner-Str",
    "iso:country":"AT",
    "sg:address":"Dr.-Karl-Renner-Str 3",
    "sg:city":"Eisenerz",
    "sg:orig_category":"Bekleidung / Einzelhandel",
    "sg:phone":"+43 4338 482227",
    "sg:postcode":"8790",
    "sg:province":"Steiermark",
    "wof:name":"Amberger Moden Inh Karin Hackenauer",
    "wof:placetype":"venue"
},
  "geometry": {"coordinates":[14.8878793716,47.5414733887],"type":"Point"}
}