{
  "type": "Feature",
  "properties": {
    "iso:country":"AT",
    "sg:address":"Autokaderstr. 106",
    "sg:city":"Wien",
    "sg:classifiers":[
        {
            "category":"Sports & Exercise",
            "subcategory":"Playing Field",
            "type":"Entertainment"
        }
    ],
    "sg:phone":"+43 4312 7847120",
    "sg:postcode":"1210",
    "sg:province":"Wien",
    "sg:tags":[
        "game"
    ],
    "wof:name":"DR. SONNE GMBH",
    "wof:placetype":"venue"
},
  "geometry": {"coordinates":[16.3798103333,48.285030365],"type":"Point"}
}