{
  "type": "Feature",
  "properties": {
    "iso:country":"AT",
    "sg:address":"Hornweg 6",
    "sg:city":"St. Johann in Tirol",
    "sg:orig_category":"Pensionen / Privatzimmer",
    "sg:phone":"+43 4353 5262287",
    "sg:postcode":"6380",
    "sg:province":"Tirol",
    "wof:name":"Pension Schwaiger",
    "wof:placetype":"venue"
},
  "geometry": {"coordinates":[12.4244155884,47.518196106],"type":"Point"}
}