{
  "type": "Feature",
  "properties": {
    "addr:full":"Wiesengrund 23 Breitenfurt Nieder\u00f6sterreich 2384",
    "addr:housenumber":"23",
    "addr:postcode":"2384",
    "addr:street":"Wiesengrund",
    "iso:country":"AT",
    "sg:address":"Wiesengrund 23",
    "sg:city":"Breitenfurt",
    "sg:orig_category":"Architekten",
    "sg:phone":"+43 2239 4064",
    "sg:postcode":"2384",
    "sg:province":"Nieder\u00f6sterreich",
    "wof:name":"Fassl Andreas Arch Dipl-Ing",
    "wof:placetype":"venue"
},
  "geometry": {"coordinates":[16.1985988617,48.1394805908],"type":"Point"}
}