{
  "type": "Feature",
  "properties": {
    "addr:full":"Gewerbestr 11 Wiener Neudorf Nieder\u00f6sterreich 2351",
    "addr:housenumber":"11",
    "addr:postcode":"2351",
    "addr:street":"Gewerbestr",
    "iso:country":"AT",
    "sg:address":"Gewerbestr 11",
    "sg:city":"Wiener Neudorf",
    "sg:classifiers":[
        {
            "category":"Government",
            "subcategory":"Post Office",
            "type":"Public Place"
        }
    ],
    "sg:phone":"+43 4322 3661119",
    "sg:postcode":"2351",
    "sg:province":"Nieder\u00f6sterreich",
    "sg:tags":[
        "u",
        "-material",
        "dachdeckereibedarf"
    ],
    "wof:name":"Bitumen- u Baustoffindustrie B\u00e4umler GmbH",
    "wof:placetype":"venue"
},
  "geometry": {"coordinates":[16.3213882446,48.078792572],"type":"Point"}
}