{
  "type": "Feature",
  "properties": {
    "addr:full":"Edenhausen 6 Natters Tirol 6161",
    "addr:housenumber":"6",
    "addr:postcode":"6161",
    "addr:street":"Edenhausen;Tirol",
    "iso:country":"AT",
    "sg:address":"Edenhausen 6",
    "sg:city":"Natters",
    "sg:orig_category":"Pensionen / Privatzimmer",
    "sg:phone":"+43 512 546846",
    "sg:postcode":"6161",
    "sg:province":"Tirol",
    "wof:name":"Edenhauserhof - Johann Mair",
    "wof:placetype":"venue"
},
  "geometry": {"coordinates":[11.3450317383,47.2374382019],"type":"Point"}
}