{
  "type": "Feature",
  "properties": {
    "iso:country":"AT",
    "sg:address":"August-Sigl-Str 2",
    "sg:city":"Wien",
    "sg:orig_category":"Fotografen",
    "sg:phone":"+43 4366 42504741",
    "sg:postcode":"1100",
    "sg:province":"Wien",
    "wof:name":"Maihoff Diether",
    "wof:placetype":"venue"
},
  "geometry": {"coordinates":[16.3487148285,48.1555366516],"type":"Point"}
}