{
  "type": "Feature",
  "properties": {
    "addr:full":"Theresianumg 27 Wien Wien 1040",
    "addr:housenumber":"27",
    "addr:postcode":"1040",
    "addr:street":"Theresianumg",
    "iso:country":"AT",
    "sg:address":"Theresianumg 27",
    "sg:city":"Wien",
    "sg:orig_category":"Institute",
    "sg:phone":"+43 4315 880133001",
    "sg:postcode":"1040",
    "sg:province":"Wien",
    "wof:name":"Institut f Betriebswissenschaft, Arbeitswissenschaft u Betriebswirtschaft d TU Wien",
    "wof:placetype":"venue"
},
  "geometry": {"coordinates":[16.3736991882,48.1915016174],"type":"Point"}
}