{
  "type": "Feature",
  "properties": {
    "addr:full":"Burgstallstr 23 Kitzb\u00fchel Tirol 6370",
    "addr:housenumber":"23",
    "addr:postcode":"6370",
    "addr:street":"Burgstallstr;Tirol",
    "iso:country":"AT",
    "sg:address":"Burgstallstr 23",
    "sg:city":"Kitzb\u00fchel",
    "sg:orig_category":"Lebens- U Sozialberatung",
    "sg:phone":"+43 5356 71951",
    "sg:postcode":"6370",
    "sg:province":"Tirol",
    "wof:name":"Klausner Waltraud",
    "wof:placetype":"venue"
},
  "geometry": {"coordinates":[12.3809957504,47.4491767883],"type":"Point"}
}