{
  "type": "Feature",
  "properties": {
    "addr:full":"Amberg 51 Kufstein Tirol 6330",
    "addr:housenumber":"51",
    "addr:postcode":"6330",
    "addr:street":"Amberg;Tirol",
    "iso:country":"AT",
    "sg:address":"Amberg 51",
    "sg:city":"Kufstein",
    "sg:orig_category":"Speditionen",
    "sg:phone":"+43 5372 57003",
    "sg:postcode":"6330",
    "sg:province":"Tirol",
    "wof:name":"LM-last minute Warenlogistik GmbH",
    "wof:placetype":"venue"
},
  "geometry": {"coordinates":[12.1509380341,47.5363235474],"type":"Point"}
}