{
  "type": "Feature",
  "properties": {
    "addr:full":"Muggendorfer Str 15 Pernitz Nieder\u00f6sterreich 2763",
    "addr:housenumber":"15",
    "addr:postcode":"2763",
    "addr:street":"Str",
    "iso:country":"AT",
    "sg:address":"Muggendorfer Str 15",
    "sg:city":"Pernitz",
    "sg:orig_category":"Musikunterricht",
    "sg:phone":"+43 2632 73170",
    "sg:postcode":"2763",
    "sg:province":"Nieder\u00f6sterreich",
    "wof:name":"Musikschule",
    "wof:placetype":"venue"
},
  "geometry": {"coordinates":[15.9562635422,47.8992805481],"type":"Point"}
}