{
  "type": "Feature",
  "properties": {
    "addr:full":"Holzbauernstr 20 Traun Ober\u00f6sterreich 4050",
    "addr:housenumber":"20",
    "addr:postcode":"4050",
    "addr:street":"Holzbauernstr",
    "iso:country":"AT",
    "sg:address":"Holzbauernstr 20",
    "sg:city":"Traun",
    "sg:orig_category":"Fitnesscenter",
    "sg:phone":"+43 7229 657862",
    "sg:postcode":"4050",
    "sg:province":"Ober\u00f6sterreich",
    "wof:name":"Body Mass In - BMI",
    "wof:placetype":"venue"
},
  "geometry": {"coordinates":[14.2562494278,48.2269554138],"type":"Point"}
}