{
  "type": "Feature",
  "properties": {
    "iso:country":"AT",
    "sg:address":"Schulg 7",
    "sg:city":"Purgstall an der Erlauf",
    "sg:orig_category":"Psychotherapie",
    "sg:phone":"+43 4374 8970903",
    "sg:postcode":"3251",
    "sg:province":"Nieder\u00f6sterreich",
    "wof:name":"Malinowsky-Schnirzer Gerlinde Mag",
    "wof:placetype":"venue"
},
  "geometry": {"coordinates":[15.1348772049,48.0587081909],"type":"Point"}
}