{
  "type": "Feature",
  "properties": {
    "addr:full":"Semmeringstr 1 Neunkirchen Nieder\u00f6sterreich 2620",
    "addr:housenumber":"1",
    "addr:postcode":"2620",
    "addr:street":"Semmeringstr",
    "iso:country":"AT",
    "sg:address":"Semmeringstr 1",
    "sg:city":"Neunkirchen",
    "sg:orig_category":"Autohandel",
    "sg:phone":"+43 2635 69018",
    "sg:postcode":"2620",
    "sg:province":"Nieder\u00f6sterreich",
    "wof:name":"Heinz G\u00fcnther KG",
    "wof:placetype":"venue"
},
  "geometry": {"coordinates":[16.0694084167,47.722530365],"type":"Point"}
}