{
  "type": "Feature",
  "properties": {
    "addr:full":"Matzingthalstr 21 Laakirchen Ober\u00f6sterreich 4663",
    "addr:housenumber":"21",
    "addr:postcode":"4663",
    "addr:street":"Matzingthalstr",
    "iso:country":"AT",
    "sg:address":"Matzingthalstr 21",
    "sg:city":"Laakirchen",
    "sg:orig_category":"Metallbau",
    "sg:phone":"+43 761350310",
    "sg:postcode":"4663",
    "sg:province":"Ober\u00f6sterreich",
    "sg:website":"www.koelblinger.at",
    "wof:name":"K\u00f6lblinger Stahl- und Metallbau GesmbH",
    "wof:placetype":"venue"
},
  "geometry": {"coordinates":[13.8243198395,47.9856147766],"type":"Point"}
}