{
  "type": "Feature",
  "properties": {
    "addr:full":"Klosterstr 13 Zwettl Nieder\u00f6sterreich 3910",
    "addr:housenumber":"13",
    "addr:postcode":"3910",
    "addr:street":"Klosterstr;Niederoesterreich",
    "iso:country":"AT",
    "sg:address":"Klosterstr 13",
    "sg:city":"Zwettl",
    "sg:orig_category":"Bastelbedarf",
    "sg:phone":"+43 2822 52602",
    "sg:postcode":"3910",
    "sg:province":"Nieder\u00f6sterreich",
    "wof:name":"Gr\u00fcbl Brigitta",
    "wof:placetype":"venue"
},
  "geometry": {"coordinates":[15.1681003571,48.6041564941],"type":"Point"}
}