{
  "type": "Feature",
  "properties": {
    "addr:full":"St. Johanner Str 11a Kitzb\u00fchel Tirol 6370",
    "addr:housenumber":"11a",
    "addr:postcode":"6370",
    "addr:street":"St. Johanner Str;Tirol",
    "iso:country":"AT",
    "sg:address":"St. Johanner Str 11a",
    "sg:city":"Kitzb\u00fchel",
    "sg:orig_category":"Transportunternehmen",
    "sg:phone":"+43 5356 62888",
    "sg:postcode":"6370",
    "sg:province":"Tirol",
    "wof:name":"Margreiter Harald",
    "wof:placetype":"venue"
},
  "geometry": {"coordinates":[12.387591362,47.4552078247],"type":"Point"}
}