{
  "type": "Feature",
  "properties": {
    "iso:country":"AT",
    "sg:address":"Liebenstein 45",
    "sg:city":"Liebenau",
    "sg:orig_category":"Galerien",
    "sg:phone":"+43 7953 8724",
    "sg:postcode":"4252",
    "sg:province":"Ober\u00f6sterreich",
    "wof:name":"Atelier & Galerie Wolf-Wolf",
    "wof:placetype":"venue"
},
  "geometry": {"coordinates":[14.7807722092,48.5123023987],"type":"Point"}
}