{
  "type": "Feature",
  "properties": {
    "iso:country":"AT",
    "sg:address":"Hafferlstr 1",
    "sg:city":"Lambach",
    "sg:orig_category":"Familien / Beratung",
    "sg:phone":"+43 7245 32319",
    "sg:postcode":"4650",
    "sg:province":"Ober\u00f6sterreich",
    "wof:name":"Jugendwohlfahrt - Au\u00dfenstelle",
    "wof:placetype":"venue"
},
  "geometry": {"coordinates":[13.8723115921,48.0908164978],"type":"Point"}
}