{
  "type": "Feature",
  "properties": {
    "addr:full":"Swarovskistr 1 Schwaz Tirol 6130",
    "addr:housenumber":"1",
    "addr:postcode":"6130",
    "addr:street":"Swarovskistr;Tirol",
    "iso:country":"AT",
    "sg:address":"Swarovskistr 1",
    "sg:city":"Schwaz",
    "sg:orig_category":"Friseure U Frisiersalons",
    "sg:phone":"+43 5242 73424",
    "sg:postcode":"6130",
    "sg:province":"Tirol",
    "wof:name":"Friseursalon Maria",
    "wof:placetype":"venue"
},
  "geometry": {"coordinates":[11.7048616409,47.3449935913],"type":"Point"}
}