{
  "type": "Feature",
  "properties": {
    "addr:full":"Kircheng 38 Wien Wien 1070",
    "addr:housenumber":"38",
    "addr:postcode":"1070",
    "addr:street":"Kircheng",
    "iso:country":"AT",
    "sg:address":"Kircheng 38",
    "sg:city":"Wien",
    "sg:orig_category":"Boutiquen",
    "sg:phone":"+43 4315 237477",
    "sg:postcode":"1070",
    "sg:province":"Wien",
    "wof:name":"Amba",
    "wof:placetype":"venue"
},
  "geometry": {"coordinates":[16.3517112732,48.2033805847],"type":"Point"}
}