{
  "type": "Feature",
  "properties": {
    "iso:country":"AT",
    "sg:address":"Halleiner Landesstr 31",
    "sg:city":"Oberalm",
    "sg:orig_category":"Musikgruppen",
    "sg:phone":"+43 6245 80146",
    "sg:postcode":"5411",
    "sg:province":"Salzburg",
    "wof:name":"Musikkapelle und Musikheim Oberalm",
    "wof:placetype":"venue"
},
  "geometry": {"coordinates":[13.0998048782,47.697971344],"type":"Point"}
}