{
  "type": "Feature",
  "properties": {
    "addr:full":"Rabensteig 1 Wien Wien 1010",
    "addr:housenumber":"1",
    "addr:postcode":"1010",
    "addr:street":"Rabensteig",
    "iso:country":"AT",
    "sg:address":"Rabensteig 1",
    "sg:city":"Wien",
    "sg:orig_category":"Textilwaren / Einzelhandel",
    "sg:phone":"+43 1 5331487",
    "sg:postcode":"1010",
    "sg:province":"Wien",
    "wof:name":"Zalcotex Handel m Textilien Zahler & Co KG",
    "wof:placetype":"venue"
},
  "geometry": {"coordinates":[16.3749961853,48.2112579346],"type":"Point"}
}