{
  "type": "Feature",
  "properties": {
    "addr:full":"Hauptstr 51 Stockerau Nieder\u00f6sterreich 2000",
    "addr:housenumber":"51",
    "addr:postcode":"2000",
    "addr:street":"Hauptstr",
    "iso:country":"AT",
    "sg:address":"Hauptstr 51",
    "sg:city":"Stockerau",
    "sg:orig_category":"Elektroinstallationsunternehmen",
    "sg:phone":"+43 4322 6662983",
    "sg:postcode":"2000",
    "sg:province":"Nieder\u00f6sterreich",
    "wof:name":"Benold & Pappenscheller OEG",
    "wof:placetype":"venue"
},
  "geometry": {"coordinates":[16.2162322998,48.3862304688],"type":"Point"}
}