{
  "type": "Feature",
  "properties": {
    "addr:full":"Kranzberg 2 St. Georgen am Walde Ober\u00f6sterreich 4372",
    "addr:housenumber":"2",
    "addr:postcode":"4372",
    "addr:street":"Kranzberg",
    "iso:country":"AT",
    "sg:address":"Kranzberg 2",
    "sg:city":"St. Georgen am Walde",
    "sg:orig_category":"Baumeister",
    "sg:phone":"+43 7954 22210",
    "sg:postcode":"4372",
    "sg:province":"Ober\u00f6sterreich",
    "wof:name":"TAWE Buchberger GmbH",
    "wof:placetype":"venue"
},
  "geometry": {"coordinates":[14.8973207474,48.3562927246],"type":"Point"}
}