{
  "type": "Feature",
  "properties": {
    "addr:full":"Nr 11 Ried im Innkreis Ober\u00f6sterreich 4910",
    "addr:postcode":"4910",
    "addr:street":"Nr 11",
    "iso:country":"AT",
    "sg:address":"Nr 11",
    "sg:city":"Ried im Innkreis",
    "sg:orig_category":"Beton- U Betonsteinwerke",
    "sg:phone":"+43 4377 5282809",
    "sg:postcode":"4910",
    "sg:province":"Ober\u00f6sterreich",
    "wof:name":"Niederndorfer Kieswerke-Transportbeton GesmbH",
    "wof:placetype":"venue"
},
  "geometry": {"coordinates":[13.497300148,48.2311439514],"type":"Point"}
}