{
  "type": "Feature",
  "properties": {
    "iso:country":"AT",
    "sg:address":"Marktpl 3",
    "sg:city":"Altheim",
    "sg:orig_category":"Eisenwaren",
    "sg:phone":"+43 7723 42202",
    "sg:postcode":"4950",
    "sg:province":"Ober\u00f6sterreich",
    "wof:name":"Reifeltshammer Hermann",
    "wof:placetype":"venue"
},
  "geometry": {"coordinates":[13.2322597504,48.2501029968],"type":"Point"}
}