{
  "type": "Feature",
  "properties": {
    "iso:country":"AT",
    "sg:address":"Felberstr 104",
    "sg:city":"Wien",
    "sg:orig_category":"Autoersatzteile",
    "sg:phone":"+43 1 9854394",
    "sg:postcode":"1150",
    "sg:province":"Wien",
    "sg:website":"www.abv-wien.at",
    "wof:name":"ABV Handels GesmbH",
    "wof:placetype":"venue"
},
  "geometry": {"coordinates":[16.3205356598,48.1934700012],"type":"Point"}
}