{
  "type": "Feature",
  "properties": {
    "iso:country":"AT",
    "sg:address":"Ketzerg 97",
    "sg:city":"Wien",
    "sg:orig_category":"Apotheken",
    "sg:phone":"+43 4318 694538",
    "sg:postcode":"1230",
    "sg:province":"Wien",
    "wof:name":"Kristall-Apotheke Mag pharm Maria Stefanich KG",
    "wof:placetype":"venue"
},
  "geometry": {"coordinates":[16.3077526093,48.1276473999],"type":"Point"}
}