{
  "type": "Feature",
  "properties": {
    "addr:full":"Wiedner Hauptstr 57 Wien Wien 1040",
    "addr:housenumber":"57",
    "addr:postcode":"1040",
    "addr:street":"Hauptstr",
    "iso:country":"AT",
    "sg:address":"Wiedner Hauptstr 57",
    "sg:city":"Wien",
    "sg:orig_category":"Druckereien, Offsetdruckereien",
    "sg:phone":"+43 1 50588670",
    "sg:postcode":"1040",
    "sg:province":"Wien",
    "wof:name":"DALDRUCK GesmbH",
    "wof:placetype":"venue"
},
  "geometry": {"coordinates":[16.3669433594,48.1909599304],"type":"Point"}
}