{
  "type": "Feature",
  "properties": {
    "addr:full":"Hinterbergstr 23 Leoben Steiermark 8700",
    "addr:housenumber":"23",
    "addr:postcode":"8700",
    "addr:street":"Hinterbergstr",
    "iso:country":"AT",
    "sg:address":"Hinterbergstr 23",
    "sg:city":"Leoben",
    "sg:orig_category":"Non-Classified Establishments",
    "sg:phone":"+43 3842 21453",
    "sg:postcode":"8700",
    "sg:province":"Steiermark",
    "wof:name":"Pfarramt",
    "wof:placetype":"venue"
},
  "geometry": {"coordinates":[15.0705051422,47.3609352112],"type":"Point"}
}