{
  "type": "Feature",
  "properties": {
    "iso:country":"AT",
    "sg:address":"Waldh\u00e4user 45",
    "sg:city":"Helfenberg",
    "sg:orig_category":"Autobusunternehmen",
    "sg:phone":"+43 7216 6310",
    "sg:postcode":"4184",
    "sg:province":"Ober\u00f6sterreich",
    "wof:name":"Kiesl Roland",
    "wof:placetype":"venue"
},
  "geometry": {"coordinates":[14.1459951401,48.5580711365],"type":"Point"}
}