{
  "type": "Feature",
  "properties": {
    "addr:full":"Franz-Fischer-Str 38 Innsbruck Tirol 6020",
    "addr:housenumber":"38",
    "addr:postcode":"6020",
    "addr:street":"Franz-Fischer-Str;Tirol",
    "iso:country":"AT",
    "sg:address":"Franz-Fischer-Str 38",
    "sg:city":"Innsbruck",
    "sg:orig_category":"Volksschulen",
    "sg:phone":"+43 4351 2584153",
    "sg:postcode":"6020",
    "sg:province":"Tirol",
    "wof:name":"Volksschule",
    "wof:placetype":"venue"
},
  "geometry": {"coordinates":[11.389632225,47.2585525513],"type":"Point"}
}