{
  "type": "Feature",
  "properties": {
    "addr:full":"Tallak 58c Rein Steiermark 8103",
    "addr:housenumber":"58c",
    "addr:postcode":"8103",
    "addr:street":"Tallak",
    "iso:country":"AT",
    "sg:address":"Tallak 58c",
    "sg:city":"Rein",
    "sg:orig_category":"Hausbetreuung",
    "sg:phone":"+43 3124 52974",
    "sg:postcode":"8103",
    "sg:province":"Steiermark",
    "wof:name":"Dienstleistungen von A-Z - Hirschler Josef",
    "wof:placetype":"venue"
},
  "geometry": {"coordinates":[15.2872600555,47.1319313049],"type":"Point"}
}