{
  "type": "Feature",
  "properties": {
    "addr:full":"Obertrumer Landesstr 9 Seekirchen am Wallersee Salzburg 5201",
    "addr:housenumber":"9",
    "addr:postcode":"5201",
    "addr:street":"Landesstr;Salzburg",
    "iso:country":"AT",
    "sg:address":"Obertrumer Landesstr 9",
    "sg:city":"Seekirchen am Wallersee",
    "sg:orig_category":"Autoreparatur",
    "sg:phone":"+43 6212 22920",
    "sg:postcode":"5201",
    "sg:province":"Salzburg",
    "wof:name":"Forsterpointner Ernst",
    "wof:placetype":"venue"
},
  "geometry": {"coordinates":[13.1205272675,47.9034118652],"type":"Point"}
}