{
  "type": "Feature",
  "properties": {
    "iso:country":"AT",
    "sg:city":"Satteins",
    "sg:orig_category":"Feuerwehren",
    "sg:phone":"+43 5524 24115",
    "sg:postcode":"6822",
    "sg:province":"Vorarlberg",
    "wof:name":"Feuerwehr D\u00fcnserberg",
    "wof:placetype":"venue"
},
  "geometry": {"coordinates":[8.9956197739,45.9606285095],"type":"Point"}
}