{
  "type": "Feature",
  "properties": {
    "addr:full":"Johannesg 9-13 Wien Wien 1010",
    "addr:housenumber":"9-13",
    "addr:postcode":"1010",
    "iso:country":"AT",
    "sg:address":"Johannesg 9-13",
    "sg:city":"Wien",
    "sg:orig_category":"Galerien",
    "sg:phone":"+43 1 5124569",
    "sg:postcode":"1010",
    "sg:province":"Wien",
    "wof:name":"Kunsthandel Widder OEG",
    "wof:placetype":"venue"
},
  "geometry": {"coordinates":[16.3688049316,48.2025489807],"type":"Point"}
}