{
  "type": "Feature",
  "properties": {
    "addr:full":"Einigkeitsstr 20 Klagenfurt K\u00e4rnten 9020",
    "addr:housenumber":"20",
    "addr:postcode":"9020",
    "addr:street":"Einigkeitsstr;Kaernten",
    "iso:country":"AT",
    "sg:address":"Einigkeitsstr 20",
    "sg:city":"Klagenfurt",
    "sg:orig_category":"Garten- U Landschaftsgestaltung",
    "sg:phone":"+43 4346 344975",
    "sg:postcode":"9020",
    "sg:province":"K\u00e4rnten",
    "wof:name":"Picko Gartenhof -und Steinbau",
    "wof:placetype":"venue"
},
  "geometry": {"coordinates":[14.3254041672,46.6374549866],"type":"Point"}
}