{
  "type": "Feature",
  "properties": {
    "addr:full":"Nr 24 Trautmannsdorf in Oststeiermark Steiermark 8343",
    "addr:postcode":"8343",
    "addr:street":"Nr;Trautmannsdorf",
    "iso:country":"AT",
    "sg:address":"Nr 24",
    "sg:city":"Trautmannsdorf in Oststeiermark",
    "sg:orig_category":"Personalbereitstellung",
    "sg:phone":"+43 3159 2736",
    "sg:postcode":"8343",
    "sg:province":"Steiermark",
    "wof:name":"Fritz Franz - Lohndrusch",
    "wof:placetype":"venue"
},
  "geometry": {"coordinates":[15.8558778763,46.864730835],"type":"Point"}
}