{
  "type": "Feature",
  "properties": {
    "addr:full":"Spittelbergg 9 Wien Wien 1070",
    "addr:housenumber":"9",
    "addr:postcode":"1070",
    "addr:street":"Spittelbergg",
    "iso:country":"AT",
    "sg:address":"Spittelbergg 9",
    "sg:city":"Wien",
    "sg:orig_category":"Juwelen, Gold- U Silberwaren / Einzelhandel",
    "sg:phone":"+43 1 5248041",
    "sg:postcode":"1070",
    "sg:province":"Wien",
    "wof:name":"Schmuckschatulle - Ludmila Kirchmayer",
    "wof:placetype":"venue"
},
  "geometry": {"coordinates":[16.3551120758,48.2031021118],"type":"Point"}
}