{
  "type": "Feature",
  "properties": {
    "addr:full":"Nikolsdorf 91 Nikolsdorf Tirol 9782",
    "addr:housenumber":"91",
    "addr:postcode":"9782",
    "addr:street":"Nikolsdorf",
    "iso:country":"AT",
    "sg:address":"Nikolsdorf 91",
    "sg:city":"Nikolsdorf",
    "sg:classifiers":[
        {
            "category":"Manufacturing",
            "subcategory":"Wood Products",
            "type":"Manufacturing & Wholesale Goods"
        }
    ],
    "sg:phone":"+43 4858 8500",
    "sg:postcode":"9782",
    "sg:province":"Tirol",
    "sg:tags":[
        "case"
    ],
    "sg:website":"ohv.at",
    "wof:name":"Ortner Holzverwertungs-GmbH",
    "wof:placetype":"venue"
},
  "geometry": {"coordinates":[12.9207057953,46.7764434814],"type":"Point"}
}