{
  "type": "Feature",
  "properties": {
    "iso:country":"AT",
    "sg:address":"Liesingbachstr 25",
    "sg:city":"Wien",
    "sg:orig_category":"Heurigen / Buschenschank",
    "sg:phone":"+43 4316 891774",
    "sg:postcode":"1100",
    "sg:province":"Wien",
    "wof:name":"Weinbau Familie Pinther",
    "wof:placetype":"venue"
},
  "geometry": {"coordinates":[16.4044628143,48.135345459],"type":"Point"}
}