{
  "type": "Feature",
  "properties": {
    "addr:full":"Blechturmg 10 Wien Wien 1040",
    "addr:housenumber":"10",
    "addr:postcode":"1040",
    "addr:street":"Blechturmg",
    "iso:country":"AT",
    "sg:address":"Blechturmg 10",
    "sg:city":"Wien",
    "sg:orig_category":"Tonanlagen / Vermietung",
    "sg:phone":"+43 699 10048571",
    "sg:postcode":"1040",
    "sg:province":"Wien",
    "wof:name":"Tontechnik Hinke",
    "wof:placetype":"venue"
},
  "geometry": {"coordinates":[16.3674678802,48.1854438782],"type":"Point"}
}