{
  "type": "Feature",
  "properties": {
    "addr:full":"Hauptstr 80 Ladendorf Nieder\u00f6sterreich 2126",
    "addr:housenumber":"80",
    "addr:postcode":"2126",
    "addr:street":"Hauptstr",
    "iso:country":"AT",
    "sg:address":"Hauptstr 80",
    "sg:city":"Ladendorf",
    "sg:orig_category":"Fleischhauereien",
    "sg:phone":"+43 4325 752257",
    "sg:postcode":"2126",
    "sg:province":"Nieder\u00f6sterreich",
    "wof:name":"Schmid Rudolf",
    "wof:placetype":"venue"
},
  "geometry": {"coordinates":[16.485584259,48.5322265625],"type":"Point"}
}