{
  "type": "Feature",
  "properties": {
    "addr:full":"Bachstr 74 Gnigl Salzburg 5023",
    "addr:housenumber":"74",
    "addr:postcode":"5023",
    "addr:street":"Bachstr",
    "iso:country":"AT",
    "sg:address":"Bachstr 74",
    "sg:city":"Gnigl",
    "sg:orig_category":"Farben U Lacke / Einzelhandel",
    "sg:phone":"+43 4366 26605810",
    "sg:postcode":"5023",
    "sg:province":"Salzburg",
    "wof:name":"SEFRA Farben- u Tapetenvertrieb GesmbH",
    "wof:placetype":"venue"
},
  "geometry": {"coordinates":[13.0641803741,47.8239402771],"type":"Point"}
}