{
  "type": "Feature",
  "properties": {
    "addr:full":"Mommseng 4 Wien Wien 1040",
    "addr:housenumber":"4",
    "addr:postcode":"1040",
    "addr:street":"Mommseng",
    "iso:country":"AT",
    "sg:address":"Mommseng 4",
    "sg:city":"Wien",
    "sg:orig_category":"Satzherstellung",
    "sg:phone":"+43 1 5054376",
    "sg:postcode":"1040",
    "sg:province":"Wien",
    "wof:name":"BuX Verlagsservice",
    "wof:placetype":"venue"
},
  "geometry": {"coordinates":[16.3766117096,48.1918296814],"type":"Point"}
}