{
  "type": "Feature",
  "properties": {
    "addr:full":"Nr 31-32 Ostermiething Ober\u00f6sterreich 5121",
    "addr:postcode":"5121",
    "addr:street":"Nr 31-32",
    "iso:country":"AT",
    "sg:address":"Nr 31-32",
    "sg:city":"Ostermiething",
    "sg:orig_category":"Internet-Cafes",
    "sg:phone":"+43 6278 790013",
    "sg:postcode":"5121",
    "sg:province":"Ober\u00f6sterreich",
    "wof:name":"Cafe Fernweh",
    "wof:placetype":"venue"
},
  "geometry": {"coordinates":[12.8289651871,48.0465812683],"type":"Point"}
}