{
  "type": "Feature",
  "properties": {
    "addr:full":"Nisselweg 48 F\u00fcgen Tirol 6263",
    "addr:housenumber":"48",
    "addr:postcode":"6263",
    "addr:street":"Nisselweg;Tirol",
    "iso:country":"AT",
    "sg:address":"Nisselweg 48",
    "sg:city":"F\u00fcgen",
    "sg:orig_category":"Raumausstattung",
    "sg:phone":"+43 5288 63763",
    "sg:postcode":"6263",
    "sg:province":"Tirol",
    "wof:name":"Wartelsteiner Klaus",
    "wof:placetype":"venue"
},
  "geometry": {"coordinates":[11.8491010666,47.3482284546],"type":"Point"}
}