{
  "type": "Feature",
  "properties": {
    "addr:full":"Herrenstr 8 Linz Ober\u00f6sterreich 4020",
    "addr:housenumber":"8",
    "addr:postcode":"4020",
    "addr:street":"Herrenstr",
    "iso:country":"AT",
    "sg:address":"Herrenstr 8",
    "sg:city":"Linz",
    "sg:orig_category":"Stahlwaren",
    "sg:phone":"+43 732 779167",
    "sg:postcode":"4020",
    "sg:province":"Ober\u00f6sterreich",
    "wof:name":"Pfeffer Angela",
    "wof:placetype":"venue"
},
  "geometry": {"coordinates":[14.2860136032,48.3026733398],"type":"Point"}
}