{
  "type": "Feature",
  "properties": {
    "addr:full":"Lambertg 15 Wien Wien 1160",
    "addr:housenumber":"15",
    "addr:postcode":"1160",
    "addr:street":"Lambertg",
    "iso:country":"AT",
    "sg:address":"Lambertg 15",
    "sg:city":"Wien",
    "sg:orig_category":"Isolierungen",
    "sg:phone":"+43 4314 867068",
    "sg:postcode":"1160",
    "sg:province":"Wien",
    "wof:name":"Dach + Wand Unternehmen z Errichtung u Eindeckung v D\u00e4chern GesmbH",
    "wof:placetype":"venue"
},
  "geometry": {"coordinates":[16.3194847107,48.2130355835],"type":"Point"}
}