{
  "type": "Feature",
  "properties": {
    "addr:full":"Burgg 81 Wien Wien 1070",
    "addr:housenumber":"81",
    "addr:postcode":"1070",
    "addr:street":"Burgg",
    "iso:country":"AT",
    "sg:address":"Burgg 81",
    "sg:city":"Wien",
    "sg:orig_category":"Lederbekleidung",
    "sg:phone":"+43 1 5235136",
    "sg:postcode":"1070",
    "sg:province":"Wien",
    "wof:name":"Poch Heinz",
    "wof:placetype":"venue"
},
  "geometry": {"coordinates":[16.3452262878,48.2042617798],"type":"Point"}
}