{
  "type": "Feature",
  "properties": {
    "iso:country":"AT",
    "sg:address":"Westbahnstrasse 5",
    "sg:city":"Ennsdorf",
    "sg:classifiers":[
        {
            "category":"Autos & Motor Vehicles",
            "subcategory":"Boat Sales",
            "type":"Retail Goods"
        }
    ],
    "sg:phone":"+43 7223 8850",
    "sg:postcode":"4482",
    "sg:province":"Nieder\u00f6sterreich",
    "sg:tags":[
        "die",
        "cutting",
        "printing",
        "automatic",
        "machines"
    ],
    "sg:website":"salvagnini.it",
    "wof:name":"Salvagnini Maschinenbau GmbH",
    "wof:placetype":"venue"
},
  "geometry": {"coordinates":[14.49036026,48.2133216858],"type":"Point"}
}