{
  "type": "Feature",
  "properties": {
    "iso:country":"AT",
    "sg:address":"J\u00e4gerstrasse 6",
    "sg:city":"Wien",
    "sg:classifiers":[
        {
            "category":"Transit Center",
            "subcategory":"Passenger",
            "type":"Transportation"
        }
    ],
    "sg:phone":"+43 1 3509555",
    "sg:postcode":"1200",
    "sg:province":"Wien",
    "sg:tags":[
        "guard",
        "casing",
        "installation"
    ],
    "wof:name":"Elektro-Schneider Inh. Auguste Schneider Nachfolger Hans Peter Pak",
    "wof:placetype":"venue"
},
  "geometry": {"coordinates":[16.370508194,48.2270851135],"type":"Point"}
}