{
  "type": "Feature",
  "properties": {
    "addr:full":"Nr 156 Wildsch\u00f6nau-Oberau Tirol 6311",
    "addr:postcode":"6311",
    "addr:street":"Nr 156 Wildschoenau-Oberau Tirol",
    "iso:country":"AT",
    "sg:address":"Nr 156",
    "sg:city":"Wildsch\u00f6nau-Oberau",
    "sg:orig_category":"Massagen",
    "sg:phone":"+43 4353 3920299",
    "sg:postcode":"6311",
    "sg:province":"Tirol",
    "wof:name":"Schroll Robin Dipl-PT",
    "wof:placetype":"venue"
},
  "geometry": {"coordinates":[12.0532751083,47.4453582764],"type":"Point"}
}