{
  "type": "Feature",
  "properties": {
    "addr:full":"Vor der Au Schwanenstadt Ober\u00f6sterreich 4690",
    "addr:postcode":"4690",
    "addr:street":"Vor Der Au",
    "iso:country":"AT",
    "sg:address":"Vor der Au",
    "sg:city":"Schwanenstadt",
    "sg:classifiers":[
        {
            "category":"Restaurant",
            "type":"Food & Drink"
        }
    ],
    "sg:phone":"+43 76732028",
    "sg:postcode":"4690",
    "sg:province":"Ober\u00f6sterreich",
    "wof:name":"Riener Restaurant",
    "wof:placetype":"venue"
},
  "geometry": {"coordinates":[13.7816085815,48.048324585],"type":"Point"}
}