{
  "type": "Feature",
  "properties": {
    "addr:full":"Unterer Gurhof 4 Ybbsitz Nieder\u00f6sterreich 3341",
    "addr:housenumber":"4",
    "addr:postcode":"3341",
    "addr:street":"Unterer Gurhof",
    "iso:country":"AT",
    "sg:address":"Unterer Gurhof 4",
    "sg:city":"Ybbsitz",
    "sg:orig_category":"Maschinenhandel",
    "sg:phone":"+43 7443 86439",
    "sg:postcode":"3341",
    "sg:province":"Nieder\u00f6sterreich",
    "wof:name":"Kloimwieder Eva Maria",
    "wof:placetype":"venue"
},
  "geometry": {"coordinates":[14.8790073395,47.9448471069],"type":"Point"}
}