{
  "type": "Feature",
  "properties": {
    "addr:full":"Theuerwang 17 Vorchdorf Ober\u00f6sterreich 4655",
    "addr:housenumber":"17",
    "addr:postcode":"4655",
    "addr:street":"Theuerwang",
    "iso:country":"AT",
    "sg:address":"Theuerwang 17",
    "sg:city":"Vorchdorf",
    "sg:orig_category":"Transportunternehmen",
    "sg:phone":"+43 76147072",
    "sg:postcode":"4655",
    "sg:province":"Ober\u00f6sterreich",
    "wof:name":"Schneeberger G\u00fcnter",
    "wof:placetype":"venue"
},
  "geometry": {"coordinates":[13.9667835236,47.9882583618],"type":"Point"}
}