{
  "type": "Feature",
  "properties": {
    "addr:full":"Wiedenstr 3 Mistelbach Nieder\u00f6sterreich 2130",
    "addr:housenumber":"3",
    "addr:postcode":"2130",
    "addr:street":"Wiedenstr;Niederoesterreich",
    "iso:country":"AT",
    "sg:address":"Wiedenstr 3",
    "sg:city":"Mistelbach",
    "sg:orig_category":"Friseure U Frisiersalons",
    "sg:phone":"+43 4325 7234400",
    "sg:postcode":"2130",
    "sg:province":"Nieder\u00f6sterreich",
    "wof:name":"Friseur Haarschneiderei",
    "wof:placetype":"venue"
},
  "geometry": {"coordinates":[16.5733947754,48.5679206848],"type":"Point"}
}