{
  "type": "Feature",
  "properties": {
    "addr:full":"Rennhammerg 21 Schwaz Tirol 6130",
    "addr:housenumber":"21",
    "addr:postcode":"6130",
    "addr:street":"Rennhammerg;Tirol",
    "iso:country":"AT",
    "sg:address":"Rennhammerg 21",
    "sg:city":"Schwaz",
    "sg:orig_category":"Unternehmensberatung",
    "sg:phone":"+43 664 4538538",
    "sg:postcode":"6130",
    "sg:province":"Tirol",
    "wof:name":"Burkia Christian Dipl Som World of Wine-Slow Food International Austria-Tirol",
    "wof:placetype":"venue"
},
  "geometry": {"coordinates":[11.7170715332,47.3463478088],"type":"Point"}
}