{
  "type": "Feature",
  "properties": {
    "addr:full":"Weichstettener Str 7 Sierning Ober\u00f6sterreich 4522",
    "addr:housenumber":"7",
    "addr:postcode":"4522",
    "addr:street":"Str",
    "iso:country":"AT",
    "sg:address":"Weichstettener Str 7",
    "sg:city":"Sierning",
    "sg:orig_category":"Lebensmittel / Einzelhandel",
    "sg:phone":"+43 7259 3576",
    "sg:postcode":"4522",
    "sg:province":"Ober\u00f6sterreich",
    "wof:name":"Zielpunkt Warenhandel GmbH & Co KG",
    "wof:placetype":"venue"
},
  "geometry": {"coordinates":[14.3146762848,48.049030304],"type":"Point"}
}