{
  "type": "Feature",
  "properties": {
    "addr:full":"Friedhofstr 11 Herrnbaumgarten Nieder\u00f6sterreich 2171",
    "addr:housenumber":"11",
    "addr:postcode":"2171",
    "addr:street":"Friedhofstr",
    "iso:country":"AT",
    "sg:address":"Friedhofstr 11",
    "sg:city":"Herrnbaumgarten",
    "sg:orig_category":"Tischlereien",
    "sg:phone":"+43 2555 2263",
    "sg:postcode":"2171",
    "sg:province":"Nieder\u00f6sterreich",
    "wof:name":"Rabl Josef GesmbH",
    "wof:placetype":"venue"
},
  "geometry": {"coordinates":[16.6786575317,48.698299408],"type":"Point"}
}