{
  "type": "Feature",
  "properties": {
    "addr:full":"Ingen-Housz-G 2 Wien Wien 1090",
    "addr:housenumber":"2",
    "addr:postcode":"1090",
    "addr:street":"Ingen-Housz-G",
    "iso:country":"AT",
    "sg:address":"Ingen-Housz-G 2",
    "sg:city":"Wien",
    "sg:orig_category":"Baumeister",
    "sg:phone":"+43 664 2405252",
    "sg:postcode":"1090",
    "sg:province":"Wien",
    "wof:name":"Buczak Josef Dipl-Ing",
    "wof:placetype":"venue"
},
  "geometry": {"coordinates":[16.3629436493,48.2270545959],"type":"Point"}
}