{
  "type": "Feature",
  "properties": {
    "addr:full":"Nr 5 Gnas Steiermark 8342",
    "addr:postcode":"8342",
    "addr:street":"Nr",
    "iso:country":"AT",
    "sg:address":"Nr 5",
    "sg:city":"Gnas",
    "sg:orig_category":"Brunnen U Brunnenbau",
    "sg:phone":"+43 4331 512427",
    "sg:postcode":"8342",
    "sg:province":"Steiermark",
    "wof:name":"Payer Johannes",
    "wof:placetype":"venue"
},
  "geometry": {"coordinates":[15.8265724182,46.8743095398],"type":"Point"}
}