{
  "type": "Feature",
  "properties": {
    "iso:country":"AT",
    "sg:address":"Hauptstr 91",
    "sg:city":"Nikitsch",
    "sg:orig_category":"Ingenieurkonsulenten / Zivilingenieure",
    "sg:phone":"+43 2614 8616",
    "sg:postcode":"7302",
    "sg:province":"Burgenland",
    "wof:name":"Krizmanich Johann Dipl-Ing",
    "wof:placetype":"venue"
},
  "geometry": {"coordinates":[16.6420841217,47.522567749],"type":"Point"}
}