{
  "type": "Feature",
  "properties": {
    "addr:full":"Triester Str 7 Neunkirchen Nieder\u00f6sterreich 2620",
    "addr:housenumber":"7",
    "addr:postcode":"2620",
    "addr:street":"Str",
    "iso:country":"AT",
    "sg:address":"Triester Str 7",
    "sg:city":"Neunkirchen",
    "sg:orig_category":"Installationsunternehmen",
    "sg:phone":"+43 2635 66666",
    "sg:postcode":"2620",
    "sg:province":"Nieder\u00f6sterreich",
    "wof:name":"B\u00fcrger Rudolf",
    "wof:placetype":"venue"
},
  "geometry": {"coordinates":[16.080827713,47.7202377319],"type":"Point"}
}