{
  "type": "Feature",
  "properties": {
    "iso:country":"AT",
    "sg:address":"Hanuschg 6",
    "sg:city":"Graz",
    "sg:classifiers":[
        {
            "category":"Home & Garden",
            "subcategory":"Building Materials",
            "type":"Retail Goods"
        }
    ],
    "sg:phone":"+43 4331 6714974",
    "sg:postcode":"8020",
    "sg:province":"Steiermark",
    "sg:tags":[
        "baustoffe",
        "-material",
        "u"
    ],
    "wof:name":"Trocal-Kunststoffenster",
    "wof:placetype":"venue"
},
  "geometry": {"coordinates":[15.4257564545,47.0718841553],"type":"Point"}
}