{
  "type": "Feature",
  "properties": {
    "addr:full":"Rinn Tirol 6074",
    "addr:postcode":"6074",
    "addr:street":"Rinn Tirol",
    "iso:country":"AT",
    "sg:city":"Rinn",
    "sg:orig_category":"Freizeit, Musik",
    "sg:phone":"+43 4352 2378886",
    "sg:postcode":"6074",
    "sg:province":"Tirol",
    "sg:website":"http://www.korn-media.com",
    "wof:name":"Korn-Media",
    "wof:placetype":"venue"
},
  "geometry": {"coordinates":[11.5041694641,47.2501792908],"type":"Point"}
}