{
  "type": "Feature",
  "properties": {
    "addr:full":"Geroldsegg 586 Schwarzenberg Vorarlberg 6867",
    "addr:housenumber":"586",
    "addr:postcode":"6867",
    "iso:country":"AT",
    "sg:address":"Geroldsegg 586",
    "sg:city":"Schwarzenberg",
    "sg:orig_category":"Appartements / Ferienwohnungen",
    "sg:phone":"+43 4355 122968",
    "sg:postcode":"6867",
    "sg:province":"Vorarlberg",
    "wof:name":"G\u00e4stehaus Viktoria - Metzler Germana",
    "wof:placetype":"venue"
},
  "geometry": {"coordinates":[9.8363351822,47.4056930542],"type":"Point"}
}