{
  "type": "Feature",
  "properties": {
    "addr:full":"Eberschwanger Str 50 Ried im Innkreis Ober\u00f6sterreich 4910",
    "addr:postcode":"4910",
    "addr:street":"Str 50",
    "iso:country":"AT",
    "sg:address":"Eberschwanger Str 50",
    "sg:city":"Ried im Innkreis",
    "sg:orig_category":"Lederbekleidung",
    "sg:phone":"+43 7752 87062",
    "sg:postcode":"4910",
    "sg:province":"Ober\u00f6sterreich",
    "wof:name":"Hainzl Maria",
    "wof:placetype":"venue"
},
  "geometry": {"coordinates":[13.4942750931,48.1966133118],"type":"Point"}
}