{
  "type": "Feature",
  "properties": {
    "iso:country":"AT",
    "sg:address":"Hainburger Strasse 36",
    "sg:city":"Wien",
    "sg:classifiers":[
        {
            "category":"Professional",
            "subcategory":"Management & Consulting",
            "type":"Services"
        }
    ],
    "sg:phone":"+43 1 7132811",
    "sg:postcode":"1030",
    "sg:province":"Wien",
    "sg:tags":[
        "hr",
        "resource",
        "consultancy",
        "human"
    ],
    "sg:website":"dbm.com",
    "wof:name":"DBM Karriereberatung Ges.m.b.H.",
    "wof:placetype":"venue"
},
  "geometry": {"coordinates":[16.3959522247,48.1997566223],"type":"Point"}
}