{
  "type": "Feature",
  "properties": {
    "addr:full":"Hanriederstr 31 Peilstein im M\u00fchlviertel Ober\u00f6sterreich 4153",
    "addr:housenumber":"31",
    "addr:postcode":"4153",
    "addr:street":"Hanriederstr;Im Muehlviertel Oberoesterreich",
    "iso:country":"AT",
    "sg:address":"Hanriederstr 31",
    "sg:city":"Peilstein im M\u00fchlviertel",
    "sg:orig_category":"Tischlereien",
    "sg:phone":"+43 4372 8772190",
    "sg:postcode":"4153",
    "sg:province":"Ober\u00f6sterreich",
    "wof:name":"M\u00e4rzinger Tischlerei GmbH",
    "wof:placetype":"venue"
},
  "geometry": {"coordinates":[13.8917808533,48.6182098389],"type":"Point"}
}