{
  "type": "Feature",
  "properties": {
    "addr:full":"Hagenauertalstr. 40 Gie\u00dfh\u00fcbl Nieder\u00f6sterreich 2372",
    "addr:housenumber":"40",
    "addr:postcode":"2372",
    "addr:street":"Hagenauertalstr.;Niederoesterreich",
    "iso:country":"AT",
    "sg:address":"Hagenauertalstr. 40",
    "sg:city":"Gie\u00dfh\u00fcbl",
    "sg:classifiers":[
        {
            "category":"Manufacturing",
            "subcategory":"Printing",
            "type":"Manufacturing & Wholesale Goods"
        }
    ],
    "sg:phone":"+43 4322 36425280",
    "sg:postcode":"2372",
    "sg:province":"Nieder\u00f6sterreich",
    "sg:tags":[
        "publishing"
    ],
    "wof:name":"A3 WIRTSCHAFTSVERLAG GES.MBH",
    "wof:placetype":"venue"
},
  "geometry": {"coordinates":[16.3687992096,48.2025413513],"type":"Point"}
}