{
  "type": "Feature",
  "properties": {
    "addr:full":"Oserstr 12 Mistelbach Nieder\u00f6sterreich 2130",
    "addr:housenumber":"12",
    "addr:postcode":"2130",
    "addr:street":"Oserstr;Niederoesterreich",
    "iso:country":"AT",
    "sg:address":"Oserstr 12",
    "sg:city":"Mistelbach",
    "sg:orig_category":"Volkshochschulen",
    "sg:phone":"+43 2572 5200",
    "sg:postcode":"2130",
    "sg:province":"Nieder\u00f6sterreich",
    "wof:name":"Volkshochschule Mistelbach",
    "wof:placetype":"venue"
},
  "geometry": {"coordinates":[16.5728130341,48.5665512085],"type":"Point"}
}