{
  "type": "Feature",
  "properties": {
    "iso:country":"AT",
    "sg:address":"Kremser Str 28",
    "sg:city":"Retz",
    "sg:orig_category":"Fleischhauereien",
    "sg:phone":"+43 2942 20224",
    "sg:postcode":"2070",
    "sg:province":"Nieder\u00f6sterreich",
    "wof:name":"Schirnhofer-Breisler GesmbH - Shop in Shop",
    "wof:placetype":"venue"
},
  "geometry": {"coordinates":[15.9520797729,48.753200531],"type":"Point"}
}