{
  "type": "Feature",
  "properties": {
    "addr:full":"Weiherweg 18 Seeham Salzburg 5164",
    "addr:housenumber":"18",
    "addr:postcode":"5164",
    "addr:street":"Weiherweg;Salzburg",
    "iso:country":"AT",
    "sg:address":"Weiherweg 18",
    "sg:city":"Seeham",
    "sg:orig_category":"Abdichtungen",
    "sg:phone":"+43 6217 20386",
    "sg:postcode":"5164",
    "sg:province":"Salzburg",
    "wof:name":"Sp\u00e4th Thomas - Abdichtungen",
    "wof:placetype":"venue"
},
  "geometry": {"coordinates":[13.0767621994,47.9780197144],"type":"Point"}
}