{
  "type": "Feature",
  "properties": {
    "addr:full":"Laaer Berg-Str 66 Wien Wien 1100",
    "addr:housenumber":"66",
    "addr:postcode":"1100",
    "addr:street":"Berg-Str",
    "iso:country":"AT",
    "sg:address":"Laaer Berg-Str 66",
    "sg:city":"Wien",
    "sg:classifiers":[
        {
            "category":"Professional",
            "type":"Services"
        }
    ],
    "sg:phone":"+43 1 680300",
    "sg:postcode":"1100",
    "sg:province":"Wien",
    "sg:tags":[
        "leasing"
    ],
    "wof:name":"RCI Bank AG",
    "wof:placetype":"venue"
},
  "geometry": {"coordinates":[16.3888111115,48.1658706665],"type":"Point"}
}