{
  "type": "Feature",
  "properties": {
    "addr:full":"Bruckg 9 Pinkafeld Burgenland 7423",
    "addr:housenumber":"9",
    "addr:postcode":"7423",
    "addr:street":"Bruckg",
    "iso:country":"AT",
    "sg:address":"Bruckg 9",
    "sg:city":"Pinkafeld",
    "sg:orig_category":"Lebensmittel / Einzelhandel",
    "sg:phone":"+43 3357 42229",
    "sg:postcode":"7423",
    "sg:province":"Burgenland",
    "wof:name":"Lamprecht Anneliese",
    "wof:placetype":"venue"
},
  "geometry": {"coordinates":[16.1212768555,47.3710746765],"type":"Point"}
}