{
  "type": "Feature",
  "properties": {
    "addr:full":"Spanheimerstr 28 Wolfsberg K\u00e4rnten 9400",
    "addr:housenumber":"28;kaernten",
    "addr:postcode":"9400",
    "addr:street":"Spanheimerstr",
    "iso:country":"AT",
    "sg:address":"Spanheimerstr 28",
    "sg:city":"Wolfsberg",
    "sg:orig_category":"Sonnenstudios",
    "sg:phone":"+43 4352 36161",
    "sg:postcode":"9400",
    "sg:province":"K\u00e4rnten",
    "wof:name":"Sonnenstudio Sun Factory",
    "wof:placetype":"venue"
},
  "geometry": {"coordinates":[14.8396100998,46.8391036987],"type":"Point"}
}