{
  "type": "Feature",
  "properties": {
    "addr:full":"Kaiser-Franz-Josef-Str 2 Innsbruck Tirol 6020",
    "addr:housenumber":"2",
    "addr:postcode":"6020",
    "addr:street":"Kaiser-Franz-Josef-Str;Tirol",
    "iso:country":"AT",
    "sg:address":"Kaiser-Franz-Josef-Str 2",
    "sg:city":"Innsbruck",
    "sg:orig_category":"Psychotherapie",
    "sg:phone":"+43 4351 2563343",
    "sg:postcode":"6020",
    "sg:province":"Tirol",
    "wof:name":"Sporschill Eva Dr phil",
    "wof:placetype":"venue"
},
  "geometry": {"coordinates":[11.4059391022,47.2758598328],"type":"Point"}
}