{
  "type": "Feature",
  "properties": {
    "addr:full":"Wattg 12 Wiener Neustadt Nieder\u00f6sterreich 2700",
    "addr:housenumber":"12",
    "addr:postcode":"2700",
    "addr:street":"Wattg",
    "iso:country":"AT",
    "sg:address":"Wattg 12",
    "sg:city":"Wiener Neustadt",
    "sg:orig_category":"Elektromotoren U -Maschinen",
    "sg:phone":"+43 4326 22228460",
    "sg:postcode":"2700",
    "sg:province":"Nieder\u00f6sterreich",
    "sg:website":"transformatoren.at",
    "wof:name":"ELMA-BARTH GmbH",
    "wof:placetype":"venue"
},
  "geometry": {"coordinates":[16.2455158234,47.8128814697],"type":"Point"}
}