{
  "type": "Feature",
  "properties": {
    "addr:full":"Viktor-Schumacher-Weg 2 Hall in Tirol Tirol 6060",
    "addr:housenumber":"2",
    "addr:postcode":"6060",
    "addr:street":"Viktor-Schumacher-Weg;Tirol",
    "iso:country":"AT",
    "sg:address":"Viktor-Schumacher-Weg 2",
    "sg:city":"Hall in Tirol",
    "sg:orig_category":"Cd, Dvd,Musikkassetten U Schallplatten",
    "sg:phone":"+43 4352 2357969",
    "sg:postcode":"6060",
    "sg:province":"Tirol",
    "wof:name":"Musikpark Lackmaier",
    "wof:placetype":"venue"
},
  "geometry": {"coordinates":[11.5075674057,47.2834892273],"type":"Point"}
}