{
  "type": "Feature",
  "properties": {
    "iso:country":"AT",
    "sg:address":"Hauptstr 47",
    "sg:city":"Neumarkt am Wallersee",
    "sg:orig_category":"Handelsagenturen",
    "sg:phone":"+43 4362 1620348",
    "sg:postcode":"5202",
    "sg:province":"Salzburg",
    "wof:name":"Seer Gottfried",
    "wof:placetype":"venue"
},
  "geometry": {"coordinates":[13.2246198654,47.9454803467],"type":"Point"}
}