{
  "type": "Feature",
  "properties": {
    "addr:full":"Kirchenpl 1 Pillichsdorf Nieder\u00f6sterreich 2211",
    "addr:housenumber":"1",
    "addr:postcode":"2211",
    "addr:street":"Kirchenpl",
    "iso:country":"AT",
    "sg:address":"Kirchenpl 1",
    "sg:city":"Pillichsdorf",
    "sg:orig_category":"Non-Classified Establishments",
    "sg:phone":"+43 2245 2382",
    "sg:postcode":"2211",
    "sg:province":"Nieder\u00f6sterreich",
    "wof:name":"Pfarramt",
    "wof:placetype":"venue"
},
  "geometry": {"coordinates":[16.5397071838,48.362197876],"type":"Point"}
}