{
  "type": "Feature",
  "properties": {
    "addr:full":"Graf-Starhemberg-G 29 Wien Wien 1040",
    "addr:housenumber":"29",
    "addr:postcode":"1040",
    "addr:street":"Graf-Starhemberg-G",
    "iso:country":"AT",
    "sg:address":"Graf-Starhemberg-G 29",
    "sg:city":"Wien",
    "sg:orig_category":"Gerichtsdolmetscher",
    "sg:phone":"+43 1 5051066",
    "sg:postcode":"1040",
    "sg:province":"Wien",
    "wof:name":"Pfaffinger Ingeborg",
    "wof:placetype":"venue"
},
  "geometry": {"coordinates":[16.3713741302,48.1887054443],"type":"Point"}
}