{
  "type": "Feature",
  "properties": {
    "addr:full":"Hauptstr 75 Himberg Nieder\u00f6sterreich 2325",
    "addr:housenumber":"75",
    "addr:postcode":"2325",
    "addr:street":"Hauptstr",
    "iso:country":"AT",
    "sg:address":"Hauptstr 75",
    "sg:city":"Himberg",
    "sg:orig_category":"Eissalons",
    "sg:phone":"+43 2235 84636",
    "sg:postcode":"2325",
    "sg:province":"Nieder\u00f6sterreich",
    "wof:name":"El Sendiony Ibrahim",
    "wof:placetype":"venue"
},
  "geometry": {"coordinates":[16.4404582977,48.080329895],"type":"Point"}
}