{
  "type": "Feature",
  "properties": {
    "addr:full":"Hofmark 17 Zell an der Pram Ober\u00f6sterreich 4755",
    "addr:housenumber":"17",
    "addr:postcode":"4755",
    "addr:street":"Hofmark",
    "iso:country":"AT",
    "sg:address":"Hofmark 17",
    "sg:city":"Zell an der Pram",
    "sg:orig_category":"Banken U Sparkassen",
    "sg:phone":"+43 4377 6483760",
    "sg:postcode":"4755",
    "sg:province":"Ober\u00f6sterreich",
    "wof:name":"Raiffeisenbank Zell a d Pram regGenmb",
    "wof:placetype":"venue"
},
  "geometry": {"coordinates":[13.6287441254,48.3155097961],"type":"Point"}
}