{
  "type": "Feature",
  "properties": {
    "addr:full":"Markstein 7 Lunz am See Nieder\u00f6sterreich 3293",
    "addr:housenumber":"7",
    "addr:postcode":"3293",
    "addr:street":"Markstein;Niederoesterreich",
    "iso:country":"AT",
    "sg:address":"Markstein 7",
    "sg:city":"Lunz am See",
    "sg:orig_category":"Zimmereien",
    "sg:phone":"+43 4366 41819616",
    "sg:postcode":"3293",
    "sg:province":"Nieder\u00f6sterreich",
    "wof:name":"B\u00f6ckl Wolfgang",
    "wof:placetype":"venue"
},
  "geometry": {"coordinates":[15.072136879,47.8736953735],"type":"Point"}
}