{
  "type": "Feature",
  "properties": {
    "addr:full":"Stubenbergg 4 Graz Steiermark 8010",
    "addr:housenumber":"4",
    "addr:postcode":"8010",
    "addr:street":"Stubenbergg",
    "iso:country":"AT",
    "sg:address":"Stubenbergg 4",
    "sg:city":"Graz",
    "sg:orig_category":"Pelze U Pelzwaren",
    "sg:phone":"+43 316 8256140",
    "sg:postcode":"8010",
    "sg:province":"Steiermark",
    "wof:name":"Pelzhaus Mangold",
    "wof:placetype":"venue"
},
  "geometry": {"coordinates":[15.4404249191,47.0686264038],"type":"Point"}
}