{
  "type": "Feature",
  "properties": {
    "iso:country":"AT",
    "sg:address":"Gumpendorfer Str 48",
    "sg:city":"Wien",
    "sg:classifiers":[
        {
            "category":"Restaurant",
            "type":"Food & Drink"
        }
    ],
    "sg:phone":"+43 1 5879210",
    "sg:postcode":"1060",
    "sg:province":"Wien",
    "wof:name":"Hungerk\u00fcnstler",
    "wof:placetype":"venue"
},
  "geometry": {"coordinates":[16.3551292419,48.1980743408],"type":"Point"}
}