{
  "type": "Feature",
  "properties": {
    "iso:country":"AT",
    "sg:address":"Danratherstr 64",
    "sg:city":"M\u00fcnzkirchen",
    "sg:orig_category":"Rauchfangkehrer",
    "sg:phone":"+43 7716 7235",
    "sg:postcode":"4792",
    "sg:province":"Ober\u00f6sterreich",
    "wof:name":"Schiller Veronika",
    "wof:placetype":"venue"
},
  "geometry": {"coordinates":[13.5767612457,48.4760284424],"type":"Point"}
}