{
  "type": "Feature",
  "properties": {
    "iso:country":"AT",
    "sg:address":"Obere Hauptstr 27/1",
    "sg:city":"Neusiedl am See",
    "sg:orig_category":"Steuerberatung",
    "sg:phone":"+43 2167 23160",
    "sg:postcode":"7100",
    "sg:province":"Burgenland",
    "wof:name":"Weinzetl Johann Mag Wirtschaftstreuhand GesmbH",
    "wof:placetype":"venue"
},
  "geometry": {"coordinates":[16.8389549255,47.9506111145],"type":"Point"}
}