{
  "type": "Feature",
  "properties": {
    "addr:full":"Kreuzstr 19 Treibach-Althofen K\u00e4rnten 9330",
    "addr:housenumber":"19",
    "addr:postcode":"9330",
    "addr:street":"Kreuzstr;Kaernten",
    "iso:country":"AT",
    "sg:address":"Kreuzstr 19",
    "sg:city":"Treibach-Althofen",
    "sg:orig_category":"Textilwaren / Einzelhandel",
    "sg:phone":"+43 4262 2324",
    "sg:postcode":"9330",
    "sg:province":"K\u00e4rnten",
    "wof:name":"Mautz Hubert GesmbH",
    "wof:placetype":"venue"
},
  "geometry": {"coordinates":[14.4684400558,46.8706512451],"type":"Point"}
}