{
  "type": "Feature",
  "properties": {
    "addr:full":"Finkenweg 3 Hard Vorarlberg 6971",
    "addr:housenumber":"3",
    "addr:postcode":"6971",
    "addr:street":"Finkenweg",
    "iso:country":"AT",
    "sg:address":"Finkenweg 3",
    "sg:city":"Hard",
    "sg:orig_category":"Orientteppiche",
    "sg:phone":"+43 5574 63611",
    "sg:postcode":"6971",
    "sg:province":"Vorarlberg",
    "wof:name":"Orientteppiche Memu",
    "wof:placetype":"venue"
},
  "geometry": {"coordinates":[9.6859579086,47.4775123596],"type":"Point"}
}