{
  "type": "Feature",
  "properties": {
    "addr:full":"Birneckerg 31 Wien Wien 1210",
    "addr:housenumber":"31",
    "addr:postcode":"1210",
    "addr:street":"Birneckerg",
    "iso:country":"AT",
    "sg:address":"Birneckerg 31",
    "sg:city":"Wien",
    "sg:orig_category":"Elektronik",
    "sg:phone":"+43 1 26368680",
    "sg:postcode":"1210",
    "sg:province":"Wien",
    "wof:name":"Gwiss Power Electronics GmbH",
    "wof:placetype":"venue"
},
  "geometry": {"coordinates":[16.4051799774,48.2440223694],"type":"Point"}
}