{
  "type": "Feature",
  "properties": {
    "addr:full":"Bahnstr 52/2/25 Brunn am Gebirge Nieder\u00f6sterreich 2345",
    "addr:housenumber":"52 / 2 / 25",
    "addr:postcode":"2345",
    "addr:street":"Bahnstr",
    "iso:country":"AT",
    "sg:address":"Bahnstr 52/2/25",
    "sg:city":"Brunn am Gebirge",
    "sg:orig_category":"Bauunternehmen",
    "sg:phone":"+43 2236 34338",
    "sg:postcode":"2345",
    "sg:province":"Nieder\u00f6sterreich",
    "sg:website":"www.safrian.at",
    "wof:name":"SAFRIAN Bau GmbH",
    "wof:placetype":"venue"
},
  "geometry": {"coordinates":[16.2839355469,48.107170105],"type":"Point"}
}