{
  "type": "Feature",
  "properties": {
    "addr:full":"Loys-Auffanger-Weg 4 Braunau am Inn Ober\u00f6sterreich 5280",
    "addr:housenumber":"4",
    "addr:postcode":"5280",
    "addr:street":"Loys-Auffanger-Weg",
    "iso:country":"AT",
    "sg:address":"Loys-Auffanger-Weg 4",
    "sg:city":"Braunau am Inn",
    "sg:orig_category":"Fahrschulen",
    "sg:phone":"+43 4377 2262782",
    "sg:postcode":"5280",
    "sg:province":"Ober\u00f6sterreich",
    "wof:name":"Fahrschule Burgstaller Kurt Ing",
    "wof:placetype":"venue"
},
  "geometry": {"coordinates":[13.0376243591,48.2541007996],"type":"Point"}
}