{
  "type": "Feature",
  "properties": {
    "addr:full":"Leopold-Ernst-G 12 Wien Wien 1170",
    "addr:housenumber":"12",
    "addr:postcode":"1170",
    "addr:street":"Leopold-Ernst-G",
    "iso:country":"AT",
    "sg:address":"Leopold-Ernst-G 12",
    "sg:city":"Wien",
    "sg:orig_category":"Reinigungsservice",
    "sg:phone":"+43 1 4085669",
    "sg:postcode":"1170",
    "sg:province":"Wien",
    "wof:name":"DCS Geb\u00e4udereinigung GmbH",
    "wof:placetype":"venue"
},
  "geometry": {"coordinates":[16.3352985382,48.2214355469],"type":"Point"}
}