{
  "type": "Feature",
  "properties": {
    "addr:full":"Altenberger Str 40 Linz Ober\u00f6sterreich 4040",
    "addr:postcode":"4040",
    "addr:street":"Str 40",
    "iso:country":"AT",
    "sg:address":"Altenberger Str 40",
    "sg:city":"Linz",
    "sg:orig_category":"Apotheken",
    "sg:phone":"+43 732 757017",
    "sg:postcode":"4040",
    "sg:province":"Ober\u00f6sterreich",
    "wof:name":"Apotheke Auhof",
    "wof:placetype":"venue"
},
  "geometry": {"coordinates":[14.318362236,48.33335495],"type":"Point"}
}