{
  "type": "Feature",
  "properties": {
    "iso:country":"AT",
    "sg:address":"Anton-Schneider-Str 1",
    "sg:city":"Bregenz",
    "sg:orig_category":"Bierlokale-Pubs",
    "sg:phone":"+43 5574 4246776",
    "sg:postcode":"6900",
    "sg:province":"Vorarlberg",
    "wof:name":"rap-sak Bar",
    "wof:placetype":"venue"
},
  "geometry": {"coordinates":[9.7470188141,47.5031738281],"type":"Point"}
}