{
  "type": "Feature",
  "properties": {
    "addr:full":"Walterstr 2 Langenlois Nieder\u00f6sterreich 3550",
    "addr:housenumber":"2",
    "addr:postcode":"3550",
    "addr:street":"Walterstr",
    "iso:country":"AT",
    "sg:address":"Walterstr 2",
    "sg:city":"Langenlois",
    "sg:orig_category":"Friseure U Frisiersalons",
    "sg:phone":"+43 2734 2822",
    "sg:postcode":"3550",
    "sg:province":"Nieder\u00f6sterreich",
    "wof:name":"Maurer Robert",
    "wof:placetype":"venue"
},
  "geometry": {"coordinates":[15.6766672134,48.4738616943],"type":"Point"}
}