{
  "type": "Feature",
  "properties": {
    "iso:country":"AT",
    "sg:address":"Barnabiteng 8",
    "sg:city":"Wien",
    "sg:orig_category":"Telekommunikation",
    "sg:phone":"+43 1 58631240",
    "sg:postcode":"1060",
    "sg:province":"Wien",
    "wof:name":"Vetro Ing Alexander Glas KEG",
    "wof:placetype":"venue"
},
  "geometry": {"coordinates":[16.3541679382,48.1984825134],"type":"Point"}
}