{
  "type": "Feature",
  "properties": {
    "addr:full":"Marktstr 103 Neukirchen am Gro\u00dfvenediger Salzburg 5741",
    "addr:housenumber":"103",
    "addr:postcode":"5741",
    "addr:street":"Salzburg",
    "iso:country":"AT",
    "sg:address":"Marktstr 103",
    "sg:city":"Neukirchen am Gro\u00dfvenediger",
    "sg:orig_category":"Hauptschulen",
    "sg:phone":"+43 6565 6330",
    "sg:postcode":"5741",
    "sg:province":"Salzburg",
    "wof:name":"Hauptschule",
    "wof:placetype":"venue"
},
  "geometry": {"coordinates":[12.3227596283,47.261390686],"type":"Point"}
}