{
  "type": "Feature",
  "properties": {
    "addr:full":"Uraniastr 2 Wien Wien 1010",
    "addr:housenumber":"2",
    "addr:postcode":"1010",
    "addr:street":"Uraniastr",
    "iso:country":"AT",
    "sg:address":"Uraniastr 2",
    "sg:city":"Wien",
    "sg:orig_category":"Versicherungsunternehmen",
    "sg:phone":"+43 1 711500",
    "sg:postcode":"1010",
    "sg:province":"Wien",
    "wof:name":"AXA Versicherungs AG - Maklerzentrum-Wien",
    "wof:placetype":"venue"
},
  "geometry": {"coordinates":[16.383764267,48.21118927],"type":"Point"}
}