{
  "type": "Feature",
  "properties": {
    "iso:country":"AT",
    "sg:address":"Esterhazygasse 22",
    "sg:city":"Wien",
    "sg:classifiers":[
        {
            "category":"Farming",
            "subcategory":"Fish & Marine Products",
            "type":"Manufacturing & Wholesale Goods"
        }
    ],
    "sg:phone":"+43 1 5860578",
    "sg:postcode":"1060",
    "sg:province":"Wien",
    "sg:tags":[
        "hotel",
        "dishwashing",
        "cleaning",
        "restaurant"
    ],
    "sg:website":"bigfive.at",
    "wof:name":"Vienna-Hygieneservice",
    "wof:placetype":"venue"
},
  "geometry": {"coordinates":[16.3502502441,48.1963691711],"type":"Point"}
}