{
  "type": "Feature",
  "properties": {
    "iso:country":"AT",
    "sg:city":"Prutz",
    "sg:orig_category":"Genossenschaften",
    "sg:phone":"+43 5472 6261",
    "sg:postcode":"6522",
    "sg:province":"Tirol",
    "wof:name":"Landwirtschaftliche Genossenschaft",
    "wof:placetype":"venue"
},
  "geometry": {"coordinates":[10.6638202667,47.0765533447],"type":"Point"}
}