{
  "type": "Feature",
  "properties": {
    "iso:country":"AT",
    "sg:address":"Nr 4",
    "sg:city":"Gm\u00fcnd",
    "sg:orig_category":"Non-Classified Establishments",
    "sg:phone":"+43 4732 2085",
    "sg:postcode":"9853",
    "sg:province":"K\u00e4rnten",
    "wof:name":"Evangelisches Pfarramt Dornbach",
    "wof:placetype":"venue"
},
  "geometry": {"coordinates":[13.5357999802,46.906955719],"type":"Point"}
}