{
  "type": "Feature",
  "properties": {
    "addr:full":"Bahnhofstr 43 St. Veit an der Glan K\u00e4rnten 9300",
    "addr:housenumber":"43",
    "addr:postcode":"9300",
    "addr:street":"Bahnhofstr;Kaernten",
    "iso:country":"AT",
    "sg:address":"Bahnhofstr 43",
    "sg:city":"St. Veit an der Glan",
    "sg:orig_category":"Lebensmittel / Einzelhandel",
    "sg:phone":"+43 4212 6512",
    "sg:postcode":"9300",
    "sg:province":"K\u00e4rnten",
    "wof:name":"Billa AG",
    "wof:placetype":"venue"
},
  "geometry": {"coordinates":[14.3656606674,46.7706565857],"type":"Point"}
}