{
  "type": "Feature",
  "properties": {
    "addr:full":"Venediger Au Wien Wien 1020",
    "addr:postcode":"1020",
    "addr:street":"Venediger Au",
    "iso:country":"AT",
    "sg:address":"Venediger Au",
    "sg:city":"Wien",
    "sg:orig_category":"Sportanlagen",
    "sg:phone":"+43 4317 295428",
    "sg:postcode":"1020",
    "sg:province":"Wien",
    "wof:name":"Sportanlage d Stadt Wien (MA 51) - Venediger Au/Spielplatz",
    "wof:placetype":"venue"
},
  "geometry": {"coordinates":[16.3952503204,48.2193412781],"type":"Point"}
}