{
  "type": "Feature",
  "properties": {
    "addr:full":"Belruptstr 27 Bregenz Vorarlberg 6900",
    "addr:housenumber":"27",
    "addr:postcode":"6900",
    "addr:street":"Belruptstr",
    "iso:country":"AT",
    "sg:address":"Belruptstr 27",
    "sg:city":"Bregenz",
    "sg:orig_category":"Immobilienmakler",
    "sg:phone":"+43 5574 484000",
    "sg:postcode":"6900",
    "sg:province":"Vorarlberg",
    "wof:name":"Mistura Markus",
    "wof:placetype":"venue"
},
  "geometry": {"coordinates":[9.7511463165,47.504360199],"type":"Point"}
}