{
  "type": "Feature",
  "properties": {
    "iso:country":"AT",
    "sg:address":"Nr 15",
    "sg:city":"N\u00f6tsch im Gailtal",
    "sg:orig_category":"Erdarbeiten",
    "sg:phone":"+43 4256 2314",
    "sg:postcode":"9611",
    "sg:province":"K\u00e4rnten",
    "wof:name":"Lussnig Johann",
    "wof:placetype":"venue"
},
  "geometry": {"coordinates":[13.6230163574,46.5904045105],"type":"Point"}
}