{
  "type": "Feature",
  "properties": {
    "addr:full":"Friedhofweg 277 M\u00fcnzkirchen Ober\u00f6sterreich 4792",
    "addr:housenumber":"277",
    "addr:postcode":"4792",
    "addr:street":"Friedhofweg;Oberoesterreich",
    "iso:country":"AT",
    "sg:address":"Friedhofweg 277",
    "sg:city":"M\u00fcnzkirchen",
    "sg:classifiers":[
        {
            "category":"Home & Garden",
            "subcategory":"Carpets & Floor Coverings",
            "type":"Retail Goods"
        }
    ],
    "sg:phone":"+43 7716 7475",
    "sg:postcode":"4792",
    "sg:province":"Ober\u00f6sterreich",
    "sg:tags":[
        "carpeting"
    ],
    "wof:name":"Franz Stadler",
    "wof:placetype":"venue"
},
  "geometry": {"coordinates":[13.568572998,48.4859848022],"type":"Point"}
}