{
  "type": "Feature",
  "properties": {
    "addr:full":"Jochen-Rindt-Strasse 19 Wien Wien 1230",
    "addr:housenumber":"19",
    "addr:postcode":"1230",
    "addr:street":"Jochen-Rindt-Strasse",
    "iso:country":"AT",
    "sg:address":"Jochen-Rindt-Strasse 19",
    "sg:city":"Wien",
    "sg:classifiers":[
        {
            "category":"Communications",
            "subcategory":"Film & Video Production",
            "type":"Services"
        }
    ],
    "sg:phone":"+43 1 61697770",
    "sg:postcode":"1230",
    "sg:province":"Wien",
    "sg:tags":[
        "engraving",
        "industry",
        "graphic",
        "foils",
        "foil"
    ],
    "sg:website":"folex.at",
    "wof:name":"Folex Technische Folien Ges.m.b.H.",
    "wof:placetype":"venue"
},
  "geometry": {"coordinates":[16.3526763916,48.1402778625],"type":"Point"}
}