{
  "type": "Feature",
  "properties": {
    "addr:full":"Wiesenfeld St. Veit an der G\u00f6lsen Nieder\u00f6sterreich 3161",
    "addr:postcode":"3161",
    "addr:street":"Wiesenfeld;Niederoesterreich",
    "iso:country":"AT",
    "sg:address":"Wiesenfeld",
    "sg:city":"St. Veit an der G\u00f6lsen",
    "sg:orig_category":"Feuerwehren",
    "sg:phone":"+43 2763 2021",
    "sg:postcode":"3161",
    "sg:province":"Nieder\u00f6sterreich",
    "wof:name":"Freiwillige Feuerwehr Wiesenfeld",
    "wof:placetype":"venue"
},
  "geometry": {"coordinates":[15.6399087906,48.0431251526],"type":"Point"}
}