{
  "type": "Feature",
  "properties": {
    "addr:full":"Lindenstr 36 Wels Ober\u00f6sterreich 4600",
    "addr:housenumber":"36",
    "addr:postcode":"4600",
    "addr:street":"Lindenstr;Oberoesterreich",
    "iso:country":"AT",
    "sg:address":"Lindenstr 36",
    "sg:city":"Wels",
    "sg:orig_category":"Unternehmensberatung",
    "sg:phone":"+43 7242 433320",
    "sg:postcode":"4600",
    "sg:province":"Ober\u00f6sterreich",
    "wof:name":"HOTEC Unternehmensberatung Kurt Hofst\u00e4tter",
    "wof:placetype":"venue"
},
  "geometry": {"coordinates":[13.9975805283,48.1534767151],"type":"Point"}
}