{
  "type": "Feature",
  "properties": {
    "addr:full":"Hauptpl 20 Eggenburg Nieder\u00f6sterreich 3730",
    "addr:housenumber":"20",
    "addr:postcode":"3730",
    "addr:street":"Hauptpl",
    "iso:country":"AT",
    "sg:address":"Hauptpl 20",
    "sg:city":"Eggenburg",
    "sg:orig_category":"Fleischhauereien",
    "sg:phone":"+43 2984 3013",
    "sg:postcode":"3730",
    "sg:province":"Nieder\u00f6sterreich",
    "wof:name":"Fischer Harald",
    "wof:placetype":"venue"
},
  "geometry": {"coordinates":[15.8165102005,48.6435203552],"type":"Point"}
}