{
  "type": "Feature",
  "properties": {
    "iso:country":"AT",
    "sg:address":"Hauptpl 20",
    "sg:city":"Eggenburg",
    "sg:orig_category":"Fleischhauereien",
    "sg:phone":"+43 2984 3013",
    "sg:postcode":"3730",
    "sg:province":"Nieder\u00f6sterreich",
    "wof:name":"Fischer Harald",
    "wof:placetype":"venue"
},
  "geometry": {"coordinates":[15.8165102005,48.6435203552],"type":"Point"}
}