{
  "type": "Feature",
  "properties": {
    "addr:full":"Bahnhofstr 12 Schwarzach Vorarlberg 6858",
    "addr:housenumber":"12",
    "addr:postcode":"6858",
    "addr:street":"Bahnhofstr",
    "iso:country":"AT",
    "sg:address":"Bahnhofstr 12",
    "sg:city":"Schwarzach",
    "sg:orig_category":"Bestattungsunternehmen",
    "sg:phone":"+43 4355 72206300",
    "sg:postcode":"6858",
    "sg:province":"Vorarlberg",
    "wof:name":"Bestattung Oberhauser GesmbH",
    "wof:placetype":"venue"
},
  "geometry": {"coordinates":[9.7608013153,47.4448051453],"type":"Point"}
}