{
  "type": "Feature",
  "properties": {
    "addr:full":"Hauptstr 143 Langegg Nieder\u00f6sterreich 3872",
    "addr:housenumber":"143",
    "addr:postcode":"3872",
    "addr:street":"Hauptstr;Langegg Niederoesterreich",
    "iso:country":"AT",
    "sg:address":"Hauptstr 143",
    "sg:city":"Langegg",
    "sg:orig_category":"Glasereien",
    "sg:phone":"+43 2862 525080",
    "sg:postcode":"3872",
    "sg:province":"Nieder\u00f6sterreich",
    "wof:name":"Bartl Werner",
    "wof:placetype":"venue"
},
  "geometry": {"coordinates":[15.0698003769,48.8389282227],"type":"Point"}
}