{
  "type": "Feature",
  "properties": {
    "addr:full":"Schwefel 88 Dornbirn Vorarlberg 6850",
    "addr:housenumber":"88",
    "addr:postcode":"6850",
    "addr:street":"Schwefel",
    "iso:country":"AT",
    "sg:address":"Schwefel 88",
    "sg:city":"Dornbirn",
    "sg:classifiers":[
        {
            "category":"Health Services",
            "subcategory":"Nursing And Care Facility",
            "type":"Services"
        }
    ],
    "sg:phone":"+43 5572 22525",
    "sg:postcode":"6850",
    "sg:province":"Vorarlberg",
    "sg:tags":[
        "restoration",
        "gold-plating",
        "cross",
        "grave"
    ],
    "wof:name":"STEIN Vetter Ges.m.b.H.",
    "wof:placetype":"venue"
},
  "geometry": {"coordinates":[9.7390117645,47.4320793152],"type":"Point"}
}