{
  "type": "Feature",
  "properties": {
    "addr:full":"Kirchg 2 Kitzb\u00fchel Tirol 6370",
    "addr:housenumber":"2",
    "addr:postcode":"6370",
    "addr:street":"Kirchg;Tirol",
    "iso:country":"AT",
    "sg:address":"Kirchg 2",
    "sg:city":"Kitzb\u00fchel",
    "sg:classifiers":[
        {
            "category":"Retail",
            "subcategory":"Storage",
            "type":"Services"
        }
    ],
    "sg:phone":"+43 5356 64588",
    "sg:postcode":"6370",
    "sg:province":"Tirol",
    "sg:tags":[
        "archive"
    ],
    "wof:name":"Stadtarchiv Kitzb\u00fchel",
    "wof:placetype":"venue"
},
  "geometry": {"coordinates":[12.389705658,47.4473953247],"type":"Point"}
}