{
  "type": "Feature",
  "properties": {
    "addr:full":"D\u00f6llerhof 88 Abtenau Salzburg 5441",
    "addr:housenumber":"88",
    "addr:postcode":"5441",
    "addr:street":"Doellerhof;Salzburg",
    "iso:country":"AT",
    "sg:address":"D\u00f6llerhof 88",
    "sg:city":"Abtenau",
    "sg:orig_category":"Appartements / Ferienwohnungen",
    "sg:phone":"+43 6243 20610",
    "sg:postcode":"5441",
    "sg:province":"Salzburg",
    "wof:name":"Webinger Helmut",
    "wof:placetype":"venue"
},
  "geometry": {"coordinates":[13.3463459015,47.5636177063],"type":"Point"}
}