{
  "type": "Feature",
  "properties": {
    "addr:full":"Neusiedler Strasse 21 Purbach am Neusiedler See Burgenland 7083",
    "addr:housenumber":"21",
    "addr:postcode":"7083",
    "addr:street":"Neusiedler Strasse",
    "iso:country":"AT",
    "sg:address":"Neusiedler Strasse 21",
    "sg:city":"Purbach am Neusiedler See",
    "sg:orig_category":"Greenhouse Mats, Reed Matting",
    "sg:phone":"+43 2683 5503",
    "sg:postcode":"7083",
    "sg:province":"Burgenland",
    "wof:name":"Martin Knoll Ges.m.b.H. Schilfrohrverarbeitung",
    "wof:placetype":"venue"
},
  "geometry": {"coordinates":[16.6985149384,47.9176101685],"type":"Point"}
}