{
  "type": "Feature",
  "properties": {
    "iso:country":"AT",
    "sg:address":"Hofwiese 21",
    "sg:city":"Kirchschlag in der Buckligen Welt",
    "sg:orig_category":"Feuerwehren",
    "sg:phone":"+43 2646 2222",
    "sg:postcode":"2860",
    "sg:province":"Nieder\u00f6sterreich",
    "wof:name":"Freiwillige Feuerwehr Kirchschlag i d Buckligen Welt",
    "wof:placetype":"venue"
},
  "geometry": {"coordinates":[16.2783737183,47.4930343628],"type":"Point"}
}