{
  "type": "Feature",
  "properties": {
    "iso:country":"AT",
    "sg:address":"Hauptpl 11",
    "sg:city":"Liebenfels",
    "sg:orig_category":"Friseure U Frisiersalons",
    "sg:phone":"+43 4342 152352",
    "sg:postcode":"9556",
    "sg:province":"K\u00e4rnten",
    "wof:name":"Frisuren Schmied",
    "wof:placetype":"venue"
},
  "geometry": {"coordinates":[14.289484024,46.7376213074],"type":"Point"}
}