{
  "type": "Feature",
  "properties": {
    "addr:full":"Engerwitzdorf Ober\u00f6sterreich 4209",
    "addr:postcode":"4209",
    "iso:country":"AT",
    "sg:city":"Engerwitzdorf",
    "sg:orig_category":"Feuerwehren",
    "sg:phone":"+43 4372 3564320",
    "sg:postcode":"4209",
    "sg:province":"Ober\u00f6sterreich",
    "wof:name":"Feuerwehrhaus",
    "wof:placetype":"venue"
},
  "geometry": {"coordinates":[14.4413757324,48.3437614441],"type":"Point"}
}