{
  "type": "Feature",
  "properties": {
    "addr:full":"Alban-Berg-Weg 8 Wien Wien 1130",
    "addr:housenumber":"8",
    "addr:postcode":"1130",
    "addr:street":"Alban-Berg-Weg",
    "iso:country":"AT",
    "sg:address":"Alban-Berg-Weg 8",
    "sg:city":"Wien",
    "sg:classifiers":[
        {
            "category":"Retail",
            "subcategory":"Event Space",
            "type":"Services"
        }
    ],
    "sg:phone":"+43 1 8048382",
    "sg:postcode":"1130",
    "sg:province":"Wien",
    "wof:name":"Dian-Film und Theater Anneliese Wiesler",
    "wof:placetype":"venue"
},
  "geometry": {"coordinates":[16.2936038971,48.1759643555],"type":"Point"}
}