{
  "type": "Feature",
  "properties": {
    "addr:full":"Lienfelderg 68 Wien Wien 1160",
    "addr:housenumber":"68",
    "addr:postcode":"1160",
    "addr:street":"Lienfelderg",
    "iso:country":"AT",
    "sg:address":"Lienfelderg 68",
    "sg:city":"Wien",
    "sg:orig_category":"Physiotherapie",
    "sg:phone":"+43 1 4856977",
    "sg:postcode":"1160",
    "sg:province":"Wien",
    "wof:name":"Viktorin Friederike Dipl-PT",
    "wof:placetype":"venue"
},
  "geometry": {"coordinates":[16.316400528,48.2198753357],"type":"Point"}
}