{
  "type": "Feature",
  "properties": {
    "iso:country":"AT",
    "sg:address":"Ossiacher Zeile 7",
    "sg:city":"Villach",
    "sg:orig_category":"Architekten",
    "sg:phone":"+43 4342 42223660",
    "sg:postcode":"9500",
    "sg:province":"K\u00e4rnten",
    "wof:name":"Kataplan Vermietung GmbH & Co KEG",
    "wof:placetype":"venue"
},
  "geometry": {"coordinates":[13.8424701691,46.6038665771],"type":"Point"}
}