{
  "type": "Feature",
  "properties": {
    "addr:full":"Steinamangerer Str 4 Oberwart Burgenland 7400",
    "addr:housenumber":"4",
    "addr:postcode":"7400",
    "addr:street":"Str",
    "iso:country":"AT",
    "sg:address":"Steinamangerer Str 4",
    "sg:city":"Oberwart",
    "sg:orig_category":"Psychologen",
    "sg:phone":"+43 4333 5234359",
    "sg:postcode":"7400",
    "sg:province":"Burgenland",
    "wof:name":"Psychotherapeutische & Psychologische Praxis Mag Edith Struckl-Voglj\u00e4ger u Ulrike Zigner",
    "wof:placetype":"venue"
},
  "geometry": {"coordinates":[16.2143440247,47.2869377136],"type":"Point"}
}