{
  "type": "Feature",
  "properties": {
    "addr:full":"Schulweg 1 Feldkirch Vorarlberg 6800",
    "addr:housenumber":"1",
    "addr:postcode":"6800",
    "addr:street":"Schulweg",
    "iso:country":"AT",
    "sg:address":"Schulweg 1",
    "sg:city":"Feldkirch",
    "sg:orig_category":"Schwangerenberatung / Geburtsvorbereitung",
    "sg:phone":"+43 4355 2236583",
    "sg:postcode":"6800",
    "sg:province":"Vorarlberg",
    "wof:name":"S\u00e4uglingsf\u00fcrsorge u M\u00fctterberatung der Stadt",
    "wof:placetype":"venue"
},
  "geometry": {"coordinates":[9.5967845917,47.2381515503],"type":"Point"}
}