{
  "type": "Feature",
  "properties": {
    "addr:full":"Pa\u00df-Thurn-Str 17 St. Johann in Tirol Tirol 6380",
    "addr:housenumber":"17",
    "addr:postcode":"6380",
    "addr:street":"Pass-Thurn-Str;Tirol",
    "iso:country":"AT",
    "sg:address":"Pa\u00df-Thurn-Str 17",
    "sg:city":"St. Johann in Tirol",
    "sg:orig_category":"Telekommunikation",
    "sg:phone":"+43 4353 5264200",
    "sg:postcode":"6380",
    "sg:province":"Tirol",
    "wof:name":"goingsoft Softwarevertriebs- u Beratungs GmbH",
    "wof:placetype":"venue"
},
  "geometry": {"coordinates":[12.4155836105,47.518901825],"type":"Point"}
}