{
  "type": "Feature",
  "properties": {
    "iso:country":"AT",
    "sg:address":"Veltlinerstr 4-6",
    "sg:city":"Guntramsdorf",
    "sg:orig_category":"Videotheken",
    "sg:phone":"+43 2236 506150",
    "sg:postcode":"2353",
    "sg:province":"Nieder\u00f6sterreich",
    "wof:name":"VIDEO & MEDIATHEK",
    "wof:placetype":"venue"
},
  "geometry": {"coordinates":[16.3178043365,48.0596961975],"type":"Point"}
}