{
  "type": "Feature",
  "properties": {
    "iso:country":"AT",
    "sg:address":"Hagenbuchstr 9",
    "sg:city":"Stra\u00dfgang",
    "sg:orig_category":"\u00c3\u201erzte / F Allgemeinmedizin",
    "sg:phone":"+43 316 285863",
    "sg:postcode":"8054",
    "sg:province":"Steiermark",
    "wof:name":"Kain Franz Dr",
    "wof:placetype":"venue"
},
  "geometry": {"coordinates":[15.3881778717,47.0013999939],"type":"Point"}
}