{
  "type": "Feature",
  "properties": {
    "iso:country":"AT",
    "sg:address":"Heinestr 43",
    "sg:city":"Wien",
    "sg:orig_category":"Beratungsstellen",
    "sg:phone":"+43 4312 127664",
    "sg:postcode":"1020",
    "sg:province":"Wien",
    "wof:name":"FIBEL Frauen Initiative Bikulturelle Ehen u Lebensgemeinschaften",
    "wof:placetype":"venue"
},
  "geometry": {"coordinates":[16.3891181946,48.2189025879],"type":"Point"}
}