{
  "type": "Feature",
  "properties": {
    "addr:full":"Platz 28 Bezau Vorarlberg 6870",
    "addr:housenumber":"28",
    "addr:postcode":"6870",
    "addr:street":"Platz",
    "iso:country":"AT",
    "sg:address":"Platz 28",
    "sg:city":"Bezau",
    "sg:orig_category":"Bodenverlegung",
    "sg:phone":"+43 664 2525205",
    "sg:postcode":"6870",
    "sg:province":"Vorarlberg",
    "wof:name":"Greussing Christian",
    "wof:placetype":"venue"
},
  "geometry": {"coordinates":[9.9028358459,47.3854217529],"type":"Point"}
}