{
  "type": "Feature",
  "properties": {
    "addr:full":"Perger Str 2 Naarn im Machlande Ober\u00f6sterreich 4331",
    "addr:housenumber":"2",
    "addr:postcode":"4331",
    "addr:street":"Str",
    "iso:country":"AT",
    "sg:address":"Perger Str 2",
    "sg:city":"Naarn im Machlande",
    "sg:orig_category":"Tourismusinformation U -Organisationen",
    "sg:phone":"+43 4372 6258255",
    "sg:postcode":"4331",
    "sg:province":"Ober\u00f6sterreich",
    "wof:name":"Tourismusverband",
    "wof:placetype":"venue"
},
  "geometry": {"coordinates":[14.6085929871,48.225227356],"type":"Point"}
}