{
  "type": "Feature",
  "properties": {
    "addr:full":"Weiherstr 3/1 Bregenz Vorarlberg 6900",
    "addr:housenumber":"3 / 1",
    "addr:postcode":"6900",
    "addr:street":"Weiherstr",
    "iso:country":"AT",
    "sg:address":"Weiherstr 3/1",
    "sg:city":"Bregenz",
    "sg:orig_category":"Weiterbildungsinstitute M Allg U Berufl Bildungsangebot",
    "sg:phone":"+43 4355 74522690",
    "sg:postcode":"6900",
    "sg:province":"Vorarlberg",
    "wof:name":"IBIS acam - Professionelle Weiterbildung. In Europa. F\u00fcr Europa",
    "wof:placetype":"venue"
},
  "geometry": {"coordinates":[9.7437648773,47.5024757385],"type":"Point"}
}