{
  "type": "Feature",
  "properties": {
    "addr:full":"Steinamangerer Str 7 Oberwart Burgenland 7400",
    "addr:housenumber":"7",
    "addr:postcode":"7400",
    "addr:street":"Str",
    "iso:country":"AT",
    "sg:address":"Steinamangerer Str 7",
    "sg:city":"Oberwart",
    "sg:classifiers":[
        {
            "category":"Shopping",
            "subcategory":"Bicycles & Sporting Goods",
            "type":"Retail Goods"
        }
    ],
    "sg:phone":"+43 4333 5238399",
    "sg:postcode":"7400",
    "sg:province":"Burgenland",
    "sg:tags":[
        "munition",
        "u",
        "waffen"
    ],
    "wof:name":"Waffen Rudolf GesmbH & Co KG",
    "wof:placetype":"venue"
},
  "geometry": {"coordinates":[16.2150020599,47.286781311],"type":"Point"}
}