{
  "type": "Feature",
  "properties": {
    "addr:full":"Hauptstr 31 Stockerau Nieder\u00f6sterreich 2000",
    "addr:housenumber":"31",
    "addr:postcode":"2000",
    "addr:street":"Hauptstr",
    "iso:country":"AT",
    "sg:address":"Hauptstr 31",
    "sg:city":"Stockerau",
    "sg:orig_category":"Tabaktrafiken",
    "sg:phone":"+43 2266 62788503",
    "sg:postcode":"2000",
    "sg:province":"Nieder\u00f6sterreich",
    "wof:name":"Hopfeld Peter",
    "wof:placetype":"venue"
},
  "geometry": {"coordinates":[16.2120819092,48.3853797913],"type":"Point"}
}