{
  "type": "Feature",
  "properties": {
    "addr:full":"Raimundstr 3 Linz Ober\u00f6sterreich 4020",
    "addr:housenumber":"3",
    "addr:postcode":"4020",
    "addr:street":"Raimundstr",
    "iso:country":"AT",
    "sg:address":"Raimundstr 3",
    "sg:city":"Linz",
    "sg:orig_category":"Weiterbildungsinstitute M Allg U Berufl Bildungsangebot",
    "sg:phone":"+43 4373 269220",
    "sg:postcode":"4020",
    "sg:province":"Ober\u00f6sterreich",
    "sg:website":"bfi-ooe.at",
    "wof:name":"Berufsf\u00f6rderungsinstitut Ober\u00f6sterreich - BFI O\u00f6 - Berufliche Erwachsenenbildung",
    "wof:placetype":"venue"
},
  "geometry": {"coordinates":[14.2989587784,48.2893600464],"type":"Point"}
}