{
  "type": "Feature",
  "properties": {
    "addr:full":"Schulg 19 Wien Wien 1180",
    "addr:housenumber":"19",
    "addr:postcode":"1180",
    "addr:street":"Schulg",
    "iso:country":"AT",
    "sg:address":"Schulg 19",
    "sg:city":"Wien",
    "sg:orig_category":"Gesundheit / Allgemeine Informationsstellen",
    "sg:phone":"+43 1 4763418800",
    "sg:postcode":"1180",
    "sg:province":"Wien",
    "wof:name":"Gesundheits- und Sozialzentrum f\u00fcr den 9. 18. und 19. Bezirk",
    "wof:placetype":"venue"
},
  "geometry": {"coordinates":[16.3454303741,48.2247390747],"type":"Point"}
}