{
  "type": "Feature",
  "properties": {
    "iso:country":"AT",
    "sg:address":"Waidach 8",
    "sg:city":"Schwaz",
    "sg:orig_category":"Polytechnische Schulen",
    "sg:phone":"+43 5242 63344",
    "sg:postcode":"6130",
    "sg:province":"Tirol",
    "wof:name":"Polytechnische Schule",
    "wof:placetype":"venue"
},
  "geometry": {"coordinates":[11.7084636688,47.3497009277],"type":"Point"}
}