{
  "type": "Feature",
  "properties": {
    "addr:full":"Seidengasse 32 Wien Wien 1070",
    "addr:housenumber":"32",
    "addr:postcode":"1070",
    "addr:street":"Seidengasse",
    "iso:country":"AT",
    "sg:address":"Seidengasse 32",
    "sg:city":"Wien",
    "sg:classifiers":[
        {
            "category":"Real Estate",
            "subcategory":"Real Estate Agent",
            "type":"Services"
        }
    ],
    "sg:phone":"+43 1 5220824",
    "sg:postcode":"1070",
    "sg:province":"Wien",
    "sg:tags":[
        "oil",
        "natural",
        "cosmetic",
        "essential"
    ],
    "sg:website":"mani.at",
    "wof:name":"Ing. Manfred Bl\u00e4uel",
    "wof:placetype":"venue"
},
  "geometry": {"coordinates":[16.3414077759,48.200553894],"type":"Point"}
}