{
  "type": "Feature",
  "properties": {
    "iso:country":"AT",
    "sg:address":"Abelstr 12",
    "sg:city":"Aschach an der Donau",
    "sg:orig_category":"Steuerungstechnik",
    "sg:phone":"+43 7273 6313",
    "sg:postcode":"4082",
    "sg:province":"Ober\u00f6sterreich",
    "wof:name":"Affenzeller GesmbH",
    "wof:placetype":"venue"
},
  "geometry": {"coordinates":[14.023399353,48.3643226624],"type":"Point"}
}