{
  "type": "Feature",
  "properties": {
    "addr:full":"Barnabiteng 8 Wien Wien 1060",
    "addr:housenumber":"8",
    "addr:postcode":"1060",
    "addr:street":"Barnabiteng",
    "iso:country":"AT",
    "sg:address":"Barnabiteng 8",
    "sg:city":"Wien",
    "sg:orig_category":"Ingenieurkonsulenten / Zivilingenieure",
    "sg:phone":"+43 1 5123635",
    "sg:postcode":"1060",
    "sg:province":"Wien",
    "wof:name":"Tecton Consult Bauwesen-ZT-GesmbH",
    "wof:placetype":"venue"
},
  "geometry": {"coordinates":[16.3541679382,48.1984825134],"type":"Point"}
}