{
  "type": "Feature",
  "properties": {
    "iso:country":"AT",
    "sg:address":"Dorfstr 14",
    "sg:city":"Fuschl am See",
    "sg:classifiers":[
        {
            "category":"Travel",
            "subcategory":"Hotels & Motels",
            "type":"Entertainment"
        }
    ],
    "sg:phone":"+43 6226 82080",
    "sg:postcode":"5330",
    "sg:province":"Salzburg",
    "wof:name":"Sch\u00fctzenhof",
    "wof:placetype":"venue"
},
  "geometry": {"coordinates":[13.2998332977,47.7969779968],"type":"Point"}
}