{
  "type": "Feature",
  "properties": {
    "iso:country":"AT",
    "sg:address":"Kirchstr 13",
    "sg:city":"Bregenz",
    "sg:orig_category":"Schlankheitsinstitute",
    "sg:phone":"+43 676 87837800",
    "sg:postcode":"6900",
    "sg:province":"Vorarlberg",
    "wof:name":"Assmann Manuela",
    "wof:placetype":"venue"
},
  "geometry": {"coordinates":[9.7472066879,47.5016326904],"type":"Point"}
}