{
  "type": "Feature",
  "properties": {
    "iso:country":"AT",
    "sg:address":"Seebach 3",
    "sg:city":"St. Magdalen",
    "sg:orig_category":"Decanter Centrifuges",
    "sg:phone":"+43 4242 42763",
    "sg:postcode":"9524",
    "sg:province":"K\u00e4rnten",
    "sg:website":"hechlglas.com",
    "wof:name":"Alois Hechl",
    "wof:placetype":"venue"
},
  "geometry": {"coordinates":[13.8908548355,46.6142501831],"type":"Point"}
}