{
  "type": "Feature",
  "properties": {
    "addr:full":"Nr 97 Kirchberg an der Raab Steiermark 8324",
    "addr:postcode":"8324",
    "addr:street":"Nr 97",
    "iso:country":"AT",
    "sg:address":"Nr 97",
    "sg:city":"Kirchberg an der Raab",
    "sg:orig_category":"\u00c3\u201erzte / F Allgemeinmedizin",
    "sg:phone":"+43 4331 1523200",
    "sg:postcode":"8324",
    "sg:province":"Steiermark",
    "wof:name":"Gungl Christiana Dr",
    "wof:placetype":"venue"
},
  "geometry": {"coordinates":[15.7642307281,46.9871444702],"type":"Point"}
}