{
  "type": "Feature",
  "properties": {
    "iso:country":"AT",
    "sg:address":"Waltersdorfer Str 55",
    "sg:city":"Baden",
    "sg:orig_category":"Fleischhauereien",
    "sg:phone":"+43 2252 802980",
    "sg:postcode":"2500",
    "sg:province":"Nieder\u00f6sterreich",
    "wof:name":"Willixhofer Albert",
    "wof:placetype":"venue"
},
  "geometry": {"coordinates":[16.2515277863,47.9996414185],"type":"Point"}
}