{
  "type": "Feature",
  "properties": {
    "addr:full":"Wallstr 45 Hard Vorarlberg 6971",
    "addr:housenumber":"45",
    "addr:postcode":"6971",
    "addr:street":"Wallstr",
    "iso:country":"AT",
    "sg:address":"Wallstr 45",
    "sg:city":"Hard",
    "sg:orig_category":"Schlossereien",
    "sg:phone":"+43 5574 89685",
    "sg:postcode":"6971",
    "sg:province":"Vorarlberg",
    "wof:name":"K\u00f6hlmeier Martin",
    "wof:placetype":"venue"
},
  "geometry": {"coordinates":[9.7017822266,47.4910202026],"type":"Point"}
}