{
  "type": "Feature",
  "properties": {
    "iso:country":"AT",
    "sg:address":"Aub\u00f6ckplatz 10",
    "sg:city":"Bad Ischl",
    "sg:classifiers":[
        {
            "category":"Building & Trades",
            "subcategory":"Electrical",
            "type":"Services"
        }
    ],
    "sg:phone":"+43 6132 23125",
    "sg:postcode":"4820",
    "sg:province":"Ober\u00f6sterreich",
    "sg:tags":[
        "work",
        "installation"
    ],
    "sg:website":"promberger.at",
    "wof:name":"Promberger Elektrotechnik",
    "wof:placetype":"venue"
},
  "geometry": {"coordinates":[13.6232833862,47.7108306885],"type":"Point"}
}