{
  "type": "Feature",
  "properties": {
    "iso:country":"AT",
    "sg:address":"Freudenauer Hafenstrasse 12",
    "sg:city":"Wien",
    "sg:orig_category":"Customs Agencies, Declarants",
    "sg:phone":"+43 1 7277220",
    "sg:postcode":"1020",
    "sg:province":"Wien",
    "wof:name":"TERMINALSPED Speditionsges.m.b.H.",
    "wof:placetype":"venue"
},
  "geometry": {"coordinates":[16.4644355774,48.183883667],"type":"Point"}
}