{
  "type": "Feature",
  "properties": {
    "iso:country":"AT",
    "sg:address":"Dietenberg 140",
    "sg:city":"Ligist",
    "sg:orig_category":"Maler, Anstreicher U Lackierer",
    "sg:phone":"+43 4331 433511",
    "sg:postcode":"8563",
    "sg:province":"Steiermark",
    "wof:name":"Schober Johann",
    "wof:placetype":"venue"
},
  "geometry": {"coordinates":[15.2158975601,46.9934234619],"type":"Point"}
}