{
  "type": "Feature",
  "properties": {
    "iso:country":"AT",
    "sg:address":"Bauern 17A",
    "sg:city":"Altach",
    "sg:classifiers":[
        {
            "category":"Military Area",
            "subcategory":"Air Force Base",
            "type":"Public Place"
        }
    ],
    "sg:phone":"+43 5576 42766",
    "sg:postcode":"6844",
    "sg:province":"Vorarlberg",
    "sg:tags":[
        "component",
        "elevator"
    ],
    "sg:website":"sst-engineering.com",
    "wof:name":"SST System Sicherheits- Technik GmbH",
    "wof:placetype":"venue"
},
  "geometry": {"coordinates":[9.6617231369,47.353969574],"type":"Point"}
}