{
  "type": "Feature",
  "properties": {
    "addr:full":"Frau-Hitt-Str 8 Innsbruck Tirol 6020",
    "addr:housenumber":"8",
    "addr:postcode":"6020",
    "addr:street":"Frau-Hitt-Str;Tirol",
    "iso:country":"AT",
    "sg:address":"Frau-Hitt-Str 8",
    "sg:city":"Innsbruck",
    "sg:orig_category":"Ingenieurkonsulenten / Zivilingenieure",
    "sg:phone":"+43 512 281397",
    "sg:postcode":"6020",
    "sg:province":"Tirol",
    "wof:name":"Straninger Walter Dipl-Ing",
    "wof:placetype":"venue"
},
  "geometry": {"coordinates":[11.3839387894,47.2700042725],"type":"Point"}
}