{
  "type": "Feature",
  "properties": {
    "iso:country":"AT",
    "sg:address":"Andritzer Reichsstr 35",
    "sg:city":"Andritz",
    "sg:orig_category":"Beratungsstellen, Mediation",
    "sg:phone":"+43 699 17511175",
    "sg:postcode":"8045",
    "sg:province":"Steiermark",
    "wof:name":"Hrozny Stefan Mag iur",
    "wof:placetype":"venue"
},
  "geometry": {"coordinates":[15.4216337204,47.1033554077],"type":"Point"}
}