{
  "type": "Feature",
  "properties": {
    "addr:full":"Manglburg 17 Grieskirchen Ober\u00f6sterreich 4710",
    "addr:housenumber":"17",
    "addr:postcode":"4710",
    "addr:street":"Manglburg",
    "iso:country":"AT",
    "sg:address":"Manglburg 17",
    "sg:city":"Grieskirchen",
    "sg:orig_category":"Non-Classified Establishments",
    "sg:phone":"+43 5 91334230",
    "sg:postcode":"4710",
    "sg:province":"Ober\u00f6sterreich",
    "wof:name":"Gendarmerieposten Grieskirchen",
    "wof:placetype":"venue"
},
  "geometry": {"coordinates":[13.8269844055,48.2337112427],"type":"Point"}
}