{
  "type": "Feature",
  "properties": {
    "addr:full":"Lacknergasse 57 Wien Wien 1170",
    "addr:housenumber":"57",
    "addr:postcode":"1170",
    "addr:street":"Lacknergasse",
    "iso:country":"AT",
    "sg:address":"Lacknergasse 57",
    "sg:city":"Wien",
    "sg:classifiers":[
        {
            "category":"Home & Garden",
            "subcategory":"Hardware",
            "type":"Retail Goods"
        }
    ],
    "sg:phone":"+43 1 4858156",
    "sg:postcode":"1170",
    "sg:province":"Wien",
    "sg:tags":[
        "steel",
        "stainless",
        "banister"
    ],
    "wof:name":"Josef Klimes Metallwarenerzeugung GmbH",
    "wof:placetype":"venue"
},
  "geometry": {"coordinates":[16.331697464,48.2248420715],"type":"Point"}
}