{
  "type": "Feature",
  "properties": {
    "iso:country":"AT",
    "sg:address":"Vorderer Trojer 8",
    "sg:city":"Thiersee",
    "sg:classifiers":[
        {
            "category":"Building & Trades",
            "subcategory":"Plumbing",
            "type":"Services"
        }
    ],
    "sg:phone":"+43 5376 5271",
    "sg:postcode":"6335",
    "sg:province":"Tirol",
    "sg:tags":[
        "tub",
        "bath"
    ],
    "wof:name":"Josef Juffinger",
    "wof:placetype":"venue"
},
  "geometry": {"coordinates":[12.0962142944,47.5979804993],"type":"Point"}
}