{
  "type": "Feature",
  "properties": {
    "iso:country":"AT",
    "sg:address":"Industriezeile 28",
    "sg:city":"Linz",
    "sg:orig_category":"Metallbe- U -Verarbeitung",
    "sg:phone":"+43 4373 2749880",
    "sg:postcode":"4020",
    "sg:province":"Ober\u00f6sterreich",
    "wof:name":"VOEST-Alpine Stahl Service Center GmbH",
    "wof:placetype":"venue"
},
  "geometry": {"coordinates":[14.3114213943,48.3157272339],"type":"Point"}
}