{
  "type": "Feature",
  "properties": {
    "iso:country":"AT",
    "sg:address":"Haratzm\u00fcllerstr 5",
    "sg:city":"Steyr",
    "sg:orig_category":"Finanz- U Wirtschaftsberatung",
    "sg:phone":"+43 4372 52771250",
    "sg:postcode":"4400",
    "sg:province":"Ober\u00f6sterreich",
    "wof:name":"ACUS Wirtschaftsberatungskanzlei GmbH",
    "wof:placetype":"venue"
},
  "geometry": {"coordinates":[14.4193296432,48.0391807556],"type":"Point"}
}