{
  "type": "Feature",
  "properties": {
    "addr:full":"Nordwestbahnstr 2 Wien Wien 1200",
    "addr:housenumber":"2",
    "addr:postcode":"1200",
    "addr:street":"Nordwestbahnstr",
    "iso:country":"AT",
    "sg:address":"Nordwestbahnstr 2",
    "sg:city":"Wien",
    "sg:orig_category":"Tankstellen",
    "sg:phone":"+43 1 3324796",
    "sg:postcode":"1200",
    "sg:province":"Wien",
    "wof:name":"BP Austria Marketing GmbH",
    "wof:placetype":"venue"
},
  "geometry": {"coordinates":[16.3806800842,48.2288208008],"type":"Point"}
}