{
  "type": "Feature",
  "properties": {
    "iso:country":"AT",
    "sg:address":"Nr 72",
    "sg:city":"Ro\u00dfleithen",
    "sg:orig_category":"Sensen",
    "sg:phone":"+43 7562 61110",
    "sg:postcode":"4575",
    "sg:province":"Ober\u00f6sterreich",
    "wof:name":"Schr\u00f6ckenfux Franz de Paul GesmbH",
    "wof:placetype":"venue"
},
  "geometry": {"coordinates":[14.2730884552,47.7020835876],"type":"Point"}
}