{
  "type": "Feature",
  "properties": {
    "addr:full":"Neulingg 52 Wien Wien 1030",
    "addr:housenumber":"52",
    "addr:postcode":"1030",
    "addr:street":"Neulingg",
    "iso:country":"AT",
    "sg:address":"Neulingg 52",
    "sg:city":"Wien",
    "sg:orig_category":"Institute",
    "sg:phone":"+43 1 7139980",
    "sg:postcode":"1030",
    "sg:province":"Wien",
    "wof:name":"Institut DAS",
    "wof:placetype":"venue"
},
  "geometry": {"coordinates":[16.4025096893,48.1936683655],"type":"Point"}
}