{
  "type": "Feature",
  "properties": {
    "addr:full":"Katzmoosstr 26 Elixhausen Salzburg 5161",
    "addr:housenumber":"26",
    "addr:postcode":"5161",
    "addr:street":"Katzmoosstr;Salzburg",
    "iso:country":"AT",
    "sg:address":"Katzmoosstr 26",
    "sg:city":"Elixhausen",
    "sg:orig_category":"Reinigungsbedarf U Reinigungsmittel",
    "sg:phone":"+43 4366 2453856",
    "sg:postcode":"5161",
    "sg:province":"Salzburg",
    "sg:website":"ihr-wintersteller.at",
    "wof:name":"IHR Roland Wintersteller",
    "wof:placetype":"venue"
},
  "geometry": {"coordinates":[13.0648288727,47.8607063293],"type":"Point"}
}