{
  "type": "Feature",
  "properties": {
    "addr:full":"Nr 35 Maishofen Salzburg 5751",
    "addr:postcode":"5751",
    "addr:street":"Nr 35;Salzburg",
    "iso:country":"AT",
    "sg:address":"Nr 35",
    "sg:city":"Maishofen",
    "sg:orig_category":"Pensionen / Privatzimmer",
    "sg:phone":"+43 6542 68757",
    "sg:postcode":"5751",
    "sg:province":"Salzburg",
    "wof:name":"Fr\u00fchst\u00fcckspension Hettlerhof",
    "wof:placetype":"venue"
},
  "geometry": {"coordinates":[12.8060150146,47.3612213135],"type":"Point"}
}