{
  "type": "Feature",
  "properties": {
    "addr:full":"St. Bartlm\u00e4 5 Innsbruck Tirol 6020",
    "addr:housenumber":"5",
    "addr:postcode":"6020",
    "addr:street":"Tirol",
    "iso:country":"AT",
    "sg:address":"St. Bartlm\u00e4 5",
    "sg:city":"Innsbruck",
    "sg:orig_category":"Hobbyvereine",
    "sg:phone":"+43 512 588595",
    "sg:postcode":"6020",
    "sg:province":"Tirol",
    "wof:name":"Sch\u00fctzenheim Wilten Sch\u00fctzengilde",
    "wof:placetype":"venue"
},
  "geometry": {"coordinates":[11.4026737213,47.2536964417],"type":"Point"}
}