{
  "type": "Feature",
  "properties": {
    "addr:full":"Austr 219 Strobl Salzburg 5350",
    "addr:housenumber":"219",
    "addr:postcode":"5350",
    "addr:street":"Strobl Salzburg",
    "iso:country":"AT",
    "sg:address":"Austr 219",
    "sg:city":"Strobl",
    "sg:orig_category":"Transportunternehmen",
    "sg:phone":"+43 6137 5396",
    "sg:postcode":"5350",
    "sg:province":"Salzburg",
    "wof:name":"Sch\u00f6ndorfer Josef",
    "wof:placetype":"venue"
},
  "geometry": {"coordinates":[13.4830083847,47.7162399292],"type":"Point"}
}