{
  "type": "Feature",
  "properties": {
    "iso:country":"AT",
    "sg:address":"Hammerschmiede 5",
    "sg:city":"Linz",
    "sg:orig_category":"Autoreparatur",
    "sg:phone":"+43 732 221051",
    "sg:postcode":"4040",
    "sg:province":"Ober\u00f6sterreich",
    "wof:name":"Danklmayer GesmbH",
    "wof:placetype":"venue"
},
  "geometry": {"coordinates":[14.2411441803,48.3129653931],"type":"Point"}
}