{
  "type": "Feature",
  "properties": {
    "addr:full":"Heiz Felderstr. 88 Neulengbach Nieder\u00f6sterreich 3040",
    "addr:housenumber":"88",
    "addr:postcode":"3040",
    "iso:country":"AT",
    "sg:address":"Heiz Felderstr. 88",
    "sg:city":"Neulengbach",
    "sg:classifiers":[
        {
            "category":"Home & Garden",
            "subcategory":"Home Furnishings",
            "type":"Retail Goods"
        }
    ],
    "sg:phone":"+43 4327 7252348",
    "sg:postcode":"3040",
    "sg:province":"Nieder\u00f6sterreich",
    "sg:tags":[
        "household"
    ],
    "wof:name":"ALBIN KUCHER",
    "wof:placetype":"venue"
},
  "geometry": {"coordinates":[15.9079504013,48.1976547241],"type":"Point"}
}