{
  "type": "Feature",
  "properties": {
    "addr:full":"Blankenbergerstr 30 Bad Hall Ober\u00f6sterreich 4540",
    "addr:housenumber":"30",
    "addr:postcode":"4540",
    "addr:street":"Blankenbergerstr",
    "iso:country":"AT",
    "sg:address":"Blankenbergerstr 30",
    "sg:city":"Bad Hall",
    "sg:classifiers":[
        {
            "category":"Restaurant",
            "type":"Food & Drink"
        }
    ],
    "sg:phone":"+43 7258 548013",
    "sg:postcode":"4540",
    "sg:province":"Ober\u00f6sterreich",
    "wof:name":"Golfrestaurant Herzog Tassilo",
    "wof:placetype":"venue"
},
  "geometry": {"coordinates":[14.1916313171,48.0372238159],"type":"Point"}
}