{
  "type": "Feature",
  "properties": {
    "addr:full":"Imling 10 Wolfsegg am Hausruck Ober\u00f6sterreich 4902",
    "addr:housenumber":"10",
    "addr:postcode":"4902",
    "addr:street":"Imling",
    "iso:country":"AT",
    "sg:address":"Imling 10",
    "sg:city":"Wolfsegg am Hausruck",
    "sg:classifiers":[
        {
            "category":"Government",
            "subcategory":"Fire Station",
            "type":"Public Place"
        }
    ],
    "sg:phone":"+43 767660600",
    "sg:postcode":"4902",
    "sg:province":"Ober\u00f6sterreich",
    "sg:tags":[
        "door"
    ],
    "sg:website":"tortec.at",
    "wof:name":"TORTEC Brandschutztor Ges.m.b.H.",
    "wof:placetype":"venue"
},
  "geometry": {"coordinates":[13.7124147415,48.1149787903],"type":"Point"}
}