{
  "type": "Feature",
  "properties": {
    "iso:country":"AT",
    "sg:address":"Stelzerstr 7",
    "sg:city":"Linz",
    "sg:orig_category":"Werbeagenturen",
    "sg:phone":"+43 732 604040",
    "sg:postcode":"4020",
    "sg:province":"Ober\u00f6sterreich",
    "wof:name":"AD design Haselgr\u00fcbler Werbe- und Medien KEG",
    "wof:placetype":"venue"
},
  "geometry": {"coordinates":[14.300198555,48.3086853027],"type":"Point"}
}