{
  "type": "Feature",
  "properties": {
    "addr:full":"Deisenham 12 Wolfsegg am Hausruck Ober\u00f6sterreich 4902",
    "addr:housenumber":"12",
    "addr:postcode":"4902",
    "addr:street":"Deisenham",
    "iso:country":"AT",
    "sg:address":"Deisenham 12",
    "sg:city":"Wolfsegg am Hausruck",
    "sg:orig_category":"Transportunternehmen",
    "sg:phone":"+43 767673830",
    "sg:postcode":"4902",
    "sg:province":"Ober\u00f6sterreich",
    "wof:name":"Hittmair Karl",
    "wof:placetype":"venue"
},
  "geometry": {"coordinates":[13.6670951843,48.1075782776],"type":"Point"}
}