{
  "type": "Feature",
  "properties": {
    "addr:full":"Nr 119 Artstetten Nieder\u00f6sterreich 3661",
    "addr:postcode":"3661",
    "addr:street":"Nr 119",
    "iso:country":"AT",
    "sg:address":"Nr 119",
    "sg:city":"Artstetten",
    "sg:orig_category":"Botendienste",
    "sg:phone":"+43 7413 80540",
    "sg:postcode":"3661",
    "sg:province":"Nieder\u00f6sterreich",
    "wof:name":"B\u00dcRO + BOTEN DIENST",
    "wof:placetype":"venue"
},
  "geometry": {"coordinates":[15.2035694122,48.243057251],"type":"Point"}
}