{
  "type": "Feature",
  "properties": {
    "iso:country":"AT",
    "sg:address":"Hackendorf 15",
    "sg:city":"St. Aegidi",
    "sg:classifiers":[
        {
            "category":"Home & Garden",
            "subcategory":"Furniture",
            "type":"Retail Goods"
        }
    ],
    "sg:phone":"+43 7717 7410",
    "sg:postcode":"4725",
    "sg:province":"Ober\u00f6sterreich",
    "sg:tags":[
        "solid",
        "wood",
        "made",
        "childrens"
    ],
    "sg:website":"tischlerei-glas.at",
    "wof:name":"Franz Glas",
    "wof:placetype":"venue"
},
  "geometry": {"coordinates":[13.7089395523,48.4694442749],"type":"Point"}
}