{
  "type": "Feature",
  "properties": {
    "addr:full":"Wienerbergstrasse 11 Wien Wien 1100",
    "addr:housenumber":"11",
    "addr:postcode":"1100",
    "addr:street":"Wienerbergstrasse",
    "iso:country":"AT",
    "sg:address":"Wienerbergstrasse 11",
    "sg:city":"Wien",
    "sg:classifiers":[
        {
            "category":"Home & Garden",
            "subcategory":"Building Materials",
            "type":"Retail Goods"
        }
    ],
    "sg:phone":"+43 1 502130",
    "sg:postcode":"1100",
    "sg:province":"Wien",
    "sg:tags":[
        "brick",
        "fire-proof"
    ],
    "sg:website":"rhi-ag.com",
    "wof:name":"Veitsch-Radex GmbH &. Co",
    "wof:placetype":"venue"
},
  "geometry": {"coordinates":[16.344953537,48.168094635],"type":"Point"}
}