{
  "type": "Feature",
  "properties": {
    "addr:full":"Drechslerg 38 Wien Wien 1140",
    "addr:housenumber":"38",
    "addr:postcode":"1140",
    "addr:street":"Drechslerg",
    "iso:country":"AT",
    "sg:address":"Drechslerg 38",
    "sg:city":"Wien",
    "sg:orig_category":"Handelsagenturen",
    "sg:phone":"+43 1 9901065",
    "sg:postcode":"1140",
    "sg:province":"Wien",
    "wof:name":"Vogt Harald",
    "wof:placetype":"venue"
},
  "geometry": {"coordinates":[16.3072910309,48.197555542],"type":"Point"}
}