{
  "type": "Feature",
  "properties": {
    "addr:full":"Landstr 50 Velm-G\u00f6tzendorf Nieder\u00f6sterreich 2245",
    "addr:housenumber":"50",
    "addr:postcode":"2245",
    "addr:street":"Landstr;Niederoesterreich",
    "iso:country":"AT",
    "sg:address":"Landstr 50",
    "sg:city":"Velm-G\u00f6tzendorf",
    "sg:orig_category":"Feuerwehren",
    "sg:phone":"+43 2538 85310",
    "sg:postcode":"2245",
    "sg:province":"Nieder\u00f6sterreich",
    "wof:name":"Freiwillige Feuerwehr Velm-G\u00f6tzendorf",
    "wof:placetype":"venue"
},
  "geometry": {"coordinates":[16.7887802124,48.4687385559],"type":"Point"}
}