{
  "type": "Feature",
  "properties": {
    "addr:full":"Negrellistr 61 Wels Ober\u00f6sterreich 4600",
    "addr:housenumber":"61",
    "addr:postcode":"4600",
    "addr:street":"Negrellistr;Oberoesterreich",
    "iso:country":"AT",
    "sg:address":"Negrellistr 61",
    "sg:city":"Wels",
    "sg:orig_category":"Traktoren",
    "sg:phone":"+43 7242 61041",
    "sg:postcode":"4600",
    "sg:province":"Ober\u00f6sterreich",
    "wof:name":"Mat-Import GmbH",
    "wof:placetype":"venue"
},
  "geometry": {"coordinates":[14.0584487915,48.1649208069],"type":"Point"}
}