{
  "type": "Feature",
  "properties": {
    "addr:full":"Kircheng 11 Apetlon Burgenland 7143",
    "addr:housenumber":"11",
    "addr:postcode":"7143",
    "addr:street":"Kircheng",
    "iso:country":"AT",
    "sg:address":"Kircheng 11",
    "sg:city":"Apetlon",
    "sg:orig_category":"Elektroinstallationsunternehmen",
    "sg:phone":"+43 2175 3625",
    "sg:postcode":"7143",
    "sg:province":"Burgenland",
    "wof:name":"Pitzl Mario",
    "wof:placetype":"venue"
},
  "geometry": {"coordinates":[16.8309898376,47.7431602478],"type":"Point"}
}