{
  "type": "Feature",
  "properties": {
    "iso:country":"AT",
    "sg:address":"Nr 179",
    "sg:city":"Berg im Drautal",
    "sg:orig_category":"Montagen U Montagetechnik",
    "sg:phone":"+43 4367 64109026",
    "sg:postcode":"9771",
    "sg:province":"K\u00e4rnten",
    "wof:name":"Mellitzer-Taurer Tischlermontagen OEG",
    "wof:placetype":"venue"
},
  "geometry": {"coordinates":[13.1351499557,46.7480010986],"type":"Point"}
}