{
  "type": "Feature",
  "properties": {
    "iso:country":"AT",
    "sg:address":"Jesserniggstr 4",
    "sg:city":"Klagenfurt",
    "sg:orig_category":"Psychologen",
    "sg:phone":"+43 4346 3914538",
    "sg:postcode":"9020",
    "sg:province":"K\u00e4rnten",
    "wof:name":"Vogls Bernd Dipl Ing. Mag. Mag.",
    "wof:placetype":"venue"
},
  "geometry": {"coordinates":[14.3177204132,46.6200027466],"type":"Point"}
}