{
  "type": "Feature",
  "properties": {
    "addr:full":"Wiener Str 9 Hartberg Steiermark 8230",
    "addr:postcode":"8230",
    "iso:country":"AT",
    "sg:address":"Wiener Str 9",
    "sg:city":"Hartberg",
    "sg:classifiers":[
        {
            "category":"Restaurant",
            "type":"Food & Drink"
        }
    ],
    "sg:phone":"+43 3332 63161",
    "sg:postcode":"8230",
    "sg:province":"Steiermark",
    "sg:tags":[
        "pizzeria"
    ],
    "wof:name":"Pizzeria David",
    "wof:placetype":"venue"
},
  "geometry": {"coordinates":[15.970369339,47.2815208435],"type":"Point"}
}