{
  "type": "Feature",
  "properties": {
    "addr:full":"Kohlmarkt 11/4 Wien Wien 1010",
    "addr:housenumber":"11 / 4",
    "addr:postcode":"1010",
    "addr:street":"Kohlmarkt",
    "iso:country":"AT",
    "sg:address":"Kohlmarkt 11/4",
    "sg:city":"Wien",
    "sg:orig_category":"Juweliere, Gold- U Silberschmiede",
    "sg:phone":"+43 4369 910881033",
    "sg:postcode":"1010",
    "sg:province":"Wien",
    "wof:name":"Radanovic Eduard",
    "wof:placetype":"venue"
},
  "geometry": {"coordinates":[16.3672180176,48.2082901001],"type":"Point"}
}