{
  "type": "Feature",
  "properties": {
    "addr:full":"Hafnerstrasse 193 Stra\u00dfgang Steiermark 8054",
    "addr:housenumber":"193",
    "addr:postcode":"8054",
    "addr:street":"Hafnerstrasse",
    "iso:country":"AT",
    "sg:address":"Hafnerstrasse 193",
    "sg:city":"Stra\u00dfgang",
    "sg:classifiers":[
        {
            "category":"Structure",
            "subcategory":"Tower",
            "type":"Public Place"
        }
    ],
    "sg:phone":"+43 316 28070",
    "sg:postcode":"8054",
    "sg:province":"Steiermark",
    "sg:tags":[
        "awning",
        "marquee"
    ],
    "sg:website":"woundwo.at",
    "wof:name":"Wo & Wo Gr\u00fcn GmbH",
    "wof:placetype":"venue"
},
  "geometry": {"coordinates":[15.4080724716,47.0248718262],"type":"Point"}
}