{
  "type": "Feature",
  "properties": {
    "addr:full":"Kulm 179 Ramsau am Dachstein Steiermark 8972",
    "addr:housenumber":"179",
    "addr:postcode":"8972",
    "addr:street":"Kulm",
    "iso:country":"AT",
    "sg:address":"Kulm 179",
    "sg:city":"Ramsau am Dachstein",
    "sg:classifiers":[
        {
            "category":"Travel",
            "subcategory":"Hotels & Motels",
            "type":"Entertainment"
        }
    ],
    "sg:phone":"+43 4336 87817080",
    "sg:postcode":"8972",
    "sg:province":"Steiermark",
    "wof:name":"Hotel Post",
    "wof:placetype":"venue"
},
  "geometry": {"coordinates":[13.6525297165,47.4214515686],"type":"Point"}
}