{
  "type": "Feature",
  "properties": {
    "addr:full":"Schuhmeierstr 1 Wilhelmsburg an der Traisen Nieder\u00f6sterreich 3150",
    "addr:housenumber":"1",
    "addr:postcode":"3150",
    "addr:street":"Schuhmeierstr",
    "iso:country":"AT",
    "sg:address":"Schuhmeierstr 1",
    "sg:city":"Wilhelmsburg an der Traisen",
    "sg:orig_category":"Massagen",
    "sg:phone":"+43 664 2264283",
    "sg:postcode":"3150",
    "sg:province":"Nieder\u00f6sterreich",
    "wof:name":"Pils Erich",
    "wof:placetype":"venue"
},
  "geometry": {"coordinates":[15.6558494568,48.0672073364],"type":"Point"}
}