{
  "type": "Feature",
  "properties": {
    "addr:full":"Stadtpl 9-10 Imst Tirol 6460",
    "addr:housenumber":"9-10",
    "addr:postcode":"6460",
    "addr:street":"Imst Tirol",
    "iso:country":"AT",
    "sg:address":"Stadtpl 9-10",
    "sg:city":"Imst",
    "sg:orig_category":"Banken U Sparkassen",
    "sg:phone":"+43 4354 1269200",
    "sg:postcode":"6460",
    "sg:province":"Tirol",
    "wof:name":"Raiffeisen-Landesbank Tirol AG",
    "wof:placetype":"venue"
},
  "geometry": {"coordinates":[10.7423028946,47.2384643555],"type":"Point"}
}