{
  "type": "Feature",
  "properties": {
    "iso:country":"AT",
    "sg:address":"Parkstr 3",
    "sg:city":"Leoben",
    "sg:orig_category":"Psychotherapie",
    "sg:phone":"+43 3842 47646",
    "sg:postcode":"8700",
    "sg:province":"Steiermark",
    "wof:name":"Schmidt Christine",
    "wof:placetype":"venue"
},
  "geometry": {"coordinates":[15.0947008133,47.382434845],"type":"Point"}
}