{
  "type": "Feature",
  "properties": {
    "addr:full":"Stifterstr 6 Gallspach Ober\u00f6sterreich 4713",
    "addr:housenumber":"6",
    "addr:postcode":"4713",
    "addr:street":"Stifterstr",
    "iso:country":"AT",
    "sg:address":"Stifterstr 6",
    "sg:city":"Gallspach",
    "sg:orig_category":"Autohandel",
    "sg:phone":"+43 7248 68244",
    "sg:postcode":"4713",
    "sg:province":"Ober\u00f6sterreich",
    "wof:name":"Lang Dieter",
    "wof:placetype":"venue"
},
  "geometry": {"coordinates":[13.8127784729,48.2094917297],"type":"Point"}
}