{
  "type": "Feature",
  "properties": {
    "addr:full":"Kirchenpl 3 Gro\u00dfwarasdorf Burgenland 7304",
    "addr:housenumber":"3",
    "addr:postcode":"7304",
    "addr:street":"Kirchenpl",
    "iso:country":"AT",
    "sg:address":"Kirchenpl 3",
    "sg:city":"Gro\u00dfwarasdorf",
    "sg:orig_category":"Non-Classified Establishments",
    "sg:phone":"+43 2614 2201",
    "sg:postcode":"7304",
    "sg:province":"Burgenland",
    "wof:name":"Pfarramt",
    "wof:placetype":"venue"
},
  "geometry": {"coordinates":[16.5840377808,47.5424156189],"type":"Point"}
}