{
  "type": "Feature",
  "properties": {
    "iso:country":"AT",
    "sg:address":"Gewerbegebiet P.O.Box 160",
    "sg:city":"St. Florian am Inn",
    "sg:orig_category":"Elektronische Bauelemente U Bauteile",
    "sg:phone":"+43 4377 1253110",
    "sg:postcode":"4782",
    "sg:province":"Ober\u00f6sterreich",
    "wof:name":"EV-Group E Thallner GmbH",
    "wof:placetype":"venue"
},
  "geometry": {"coordinates":[13.4422712326,48.4417228699],"type":"Point"}
}