{
  "type": "Feature",
  "properties": {
    "iso:country":"AT",
    "sg:address":"Ruflinger Str 185",
    "sg:city":"Leonding",
    "sg:orig_category":"Steinmetzbetriebe",
    "sg:phone":"+43 732 683459",
    "sg:postcode":"4060",
    "sg:province":"Ober\u00f6sterreich",
    "sg:website":"natursteinzentrum.at",
    "wof:name":"Natursteinzentrum Roitner - Schneider OEG",
    "wof:placetype":"venue"
},
  "geometry": {"coordinates":[14.2104940414,48.2761764526],"type":"Point"}
}