{
  "type": "Feature",
  "properties": {
    "iso:country":"AT",
    "sg:address":"Linzer Str 56",
    "sg:city":"Kematen an der Krems",
    "sg:orig_category":"Autohandel",
    "sg:phone":"+43 4372 2864360",
    "sg:postcode":"4531",
    "sg:province":"Ober\u00f6sterreich",
    "wof:name":"Autohaus Schmidberger GmbH",
    "wof:placetype":"venue"
},
  "geometry": {"coordinates":[14.1893339157,48.1054573059],"type":"Point"}
}