{
  "type": "Feature",
  "properties": {
    "addr:full":"Hauptpl 1 Bad Radkersburg Steiermark 8490",
    "addr:housenumber":"1",
    "addr:postcode":"8490",
    "addr:street":"Hauptpl",
    "iso:country":"AT",
    "sg:address":"Hauptpl 1",
    "sg:city":"Bad Radkersburg",
    "sg:orig_category":"Gemeinden",
    "sg:phone":"+43 3476 25090",
    "sg:postcode":"8490",
    "sg:province":"Steiermark",
    "wof:name":"Stadtgemeinde Bad Radkersburg",
    "wof:placetype":"venue"
},
  "geometry": {"coordinates":[15.9865398407,46.6875534058],"type":"Point"}
}