{
  "type": "Feature",
  "properties": {
    "addr:full":"Eberstalzell Ober\u00f6sterreich 4653",
    "addr:postcode":"4653",
    "iso:country":"AT",
    "sg:city":"Eberstalzell",
    "sg:orig_category":"Feuerwehren",
    "sg:phone":"+43 7241 5690",
    "sg:postcode":"4653",
    "sg:province":"Ober\u00f6sterreich",
    "wof:name":"Freiwillige Feuerwehr Eberstalzell",
    "wof:placetype":"venue"
},
  "geometry": {"coordinates":[13.9801950455,48.0445671082],"type":"Point"}
}