{
  "type": "Feature",
  "properties": {
    "addr:full":"Riccabonastr 6 Absam Tirol 6067",
    "addr:housenumber":"6",
    "addr:postcode":"6067",
    "addr:street":"Riccabonastr;Tirol",
    "iso:country":"AT",
    "sg:address":"Riccabonastr 6",
    "sg:city":"Absam",
    "sg:orig_category":"Mess-, Steuer- U Regeltechnik",
    "sg:phone":"+43 4352 2357017",
    "sg:postcode":"6067",
    "sg:province":"Tirol",
    "wof:name":"Alge Sports-Timing Werner Unterfrauner",
    "wof:placetype":"venue"
},
  "geometry": {"coordinates":[11.5137233734,47.2957344055],"type":"Point"}
}