{
  "type": "Feature",
  "properties": {
    "addr:full":"Agathenhofstr 24 Micheldorf K\u00e4rnten 9322",
    "addr:housenumber":"24",
    "addr:postcode":"9322",
    "addr:street":"Agathenhofstr;Kaernten",
    "iso:country":"AT",
    "sg:address":"Agathenhofstr 24",
    "sg:city":"Micheldorf",
    "sg:classifiers":[
        {
            "category":"Travel",
            "subcategory":"Hotels & Motels",
            "type":"Entertainment"
        }
    ],
    "sg:phone":"+43 4268 50170",
    "sg:postcode":"9322",
    "sg:province":"K\u00e4rnten",
    "wof:name":"Agathenhof Vitalhotel",
    "wof:placetype":"venue"
},
  "geometry": {"coordinates":[14.421090126,46.9170837402],"type":"Point"}
}