{
  "type": "Feature",
  "properties": {
    "addr:full":"W\u00e4hringer Str 155 Wien Wien 1180",
    "addr:housenumber":"155",
    "addr:postcode":"1180",
    "addr:street":"Str",
    "iso:country":"AT",
    "sg:address":"W\u00e4hringer Str 155",
    "sg:city":"Wien",
    "sg:orig_category":"Juweliere, Gold- U Silberschmiede",
    "sg:phone":"+43 4315 874146",
    "sg:postcode":"1180",
    "sg:province":"Wien",
    "wof:name":"Hittinger - vorm Konrad - alter Schmuck",
    "wof:placetype":"venue"
},
  "geometry": {"coordinates":[16.3343715668,48.2282943726],"type":"Point"}
}