{
  "type": "Feature",
  "properties": {
    "addr:full":"Laaer Strasse 58a R\u00fcckersdorf-Harmannsdorf Nieder\u00f6sterreich 2111",
    "addr:housenumber":"58a",
    "addr:postcode":"2111",
    "addr:street":"Laaer Strasse;Niederoesterreich",
    "iso:country":"AT",
    "sg:address":"Laaer Strasse 58a",
    "sg:city":"R\u00fcckersdorf-Harmannsdorf",
    "sg:orig_category":"Brushes, Special, For Technical Purposes",
    "sg:phone":"+43 2264 6425",
    "sg:postcode":"2111",
    "sg:province":"Nieder\u00f6sterreich",
    "sg:website":"h-koller.at",
    "wof:name":"Helmut Koller",
    "wof:placetype":"venue"
},
  "geometry": {"coordinates":[16.3712005615,48.3930053711],"type":"Point"}
}