{
  "type": "Feature",
  "properties": {
    "addr:full":"Nr 34 Eisentratten K\u00e4rnten 9861",
    "addr:postcode":"9861",
    "addr:street":"Nr 34 Eisentratten Kaernten",
    "iso:country":"AT",
    "sg:address":"Nr 34",
    "sg:city":"Eisentratten",
    "sg:orig_category":"Schmieden U Schmiedeeisenelemente",
    "sg:phone":"+43 4347 3227640",
    "sg:postcode":"9861",
    "sg:province":"K\u00e4rnten",
    "wof:name":"Pichorner Peter",
    "wof:placetype":"venue"
},
  "geometry": {"coordinates":[13.5780506134,46.9226989746],"type":"Point"}
}