{
  "type": "Feature",
  "properties": {
    "addr:full":"Unterlinden 35 Wolfurt Vorarlberg 6922",
    "addr:housenumber":"35",
    "addr:postcode":"6922",
    "addr:street":"Unterlinden",
    "iso:country":"AT",
    "sg:address":"Unterlinden 35",
    "sg:city":"Wolfurt",
    "sg:orig_category":"Stiegen U Treppen",
    "sg:phone":"+43 5574 71490",
    "sg:postcode":"6922",
    "sg:province":"Vorarlberg",
    "wof:name":"Rupp Holztreppen- und Holzgel\u00e4nderbau",
    "wof:placetype":"venue"
},
  "geometry": {"coordinates":[9.7501811981,47.4733352661],"type":"Point"}
}