{
  "type": "Feature",
  "properties": {
    "addr:full":"Gentzg 64 Wien Wien 1180",
    "addr:housenumber":"64",
    "addr:postcode":"1180",
    "addr:street":"Gentzg",
    "iso:country":"AT",
    "sg:address":"Gentzg 64",
    "sg:city":"Wien",
    "sg:orig_category":"Fitnesscenter",
    "sg:phone":"+43 1 4706609",
    "sg:postcode":"1180",
    "sg:province":"Wien",
    "wof:name":"Body Quest",
    "wof:placetype":"venue"
},
  "geometry": {"coordinates":[16.3402194977,48.2276992798],"type":"Point"}
}