{
  "type": "Feature",
  "properties": {
    "iso:country":"AT",
    "sg:address":"Weiher 2",
    "sg:city":"Bramberg am Wildkogel",
    "sg:classifiers":[
        {
            "category":"Home & Garden",
            "subcategory":"Home Furnishings",
            "type":"Retail Goods"
        }
    ],
    "sg:phone":"+43 4365 6684080",
    "sg:postcode":"5733",
    "sg:province":"Salzburg",
    "sg:tags":[
        "household"
    ],
    "wof:name":"HOLZSPECHT URIG UND ECHT NOTHDURFTER UND SCH\u00dcPPL KG",
    "wof:placetype":"venue"
},
  "geometry": {"coordinates":[12.3472557068,47.2725601196],"type":"Point"}
}