{
  "type": "Feature",
  "properties": {
    "addr:full":"Rathauspl 2 Stockerau Nieder\u00f6sterreich 2000",
    "addr:housenumber":"2",
    "addr:postcode":"2000",
    "addr:street":"Rathauspl",
    "iso:country":"AT",
    "sg:address":"Rathauspl 2",
    "sg:city":"Stockerau",
    "sg:orig_category":"Banken U Sparkassen",
    "sg:phone":"+43 2266 625010",
    "sg:postcode":"2000",
    "sg:province":"Nieder\u00f6sterreich",
    "wof:name":"Raiffeisenbank Stockerau regGenmbH",
    "wof:placetype":"venue"
},
  "geometry": {"coordinates":[16.207239151,48.3848495483],"type":"Point"}
}