{
  "type": "Feature",
  "properties": {
    "addr:full":"Schottenfeldg 51 Wien Wien 1070",
    "addr:housenumber":"51",
    "addr:postcode":"1070",
    "addr:street":"Schottenfeldg",
    "iso:country":"AT",
    "sg:address":"Schottenfeldg 51",
    "sg:city":"Wien",
    "sg:classifiers":[
        {
            "category":"Park",
            "subcategory":"Provincial",
            "type":"Public Place"
        }
    ],
    "sg:phone":"+43 4315 21190",
    "sg:postcode":"1070",
    "sg:province":"Wien",
    "sg:tags":[
        "u",
        "-archive",
        "bildagenturen"
    ],
    "sg:website":"contrastphoto.com",
    "wof:name":"Contrast Photo GmbH",
    "wof:placetype":"venue"
},
  "geometry": {"coordinates":[16.3429851532,48.2021522522],"type":"Point"}
}