{
  "type": "Feature",
  "properties": {
    "addr:full":"Schmitteng 10 Frastanz Vorarlberg 6820",
    "addr:housenumber":"10",
    "addr:postcode":"6820",
    "addr:street":"Schmitteng",
    "iso:country":"AT",
    "sg:address":"Schmitteng 10",
    "sg:city":"Frastanz",
    "sg:orig_category":"Rettungsdienste",
    "sg:phone":"+43 5522 54144",
    "sg:postcode":"6820",
    "sg:province":"Vorarlberg",
    "wof:name":"Rotes Kreuz \u00f6sterr Ortsstelle Frastanz",
    "wof:placetype":"venue"
},
  "geometry": {"coordinates":[9.6307477951,47.2188911438],"type":"Point"}
}