{
  "type": "Feature",
  "properties": {
    "iso:country":"AT",
    "sg:address":"Spitalg 1",
    "sg:city":"Mariazell",
    "sg:classifiers":[
        {
            "category":"Park",
            "subcategory":"Provincial",
            "type":"Public Place"
        }
    ],
    "sg:phone":"+43 4338 822720",
    "sg:postcode":"8630",
    "sg:province":"Steiermark",
    "sg:tags":[
        "u",
        "ski-",
        "snowboardschulen"
    ],
    "wof:name":"Gornik Ferdinand",
    "wof:placetype":"venue"
},
  "geometry": {"coordinates":[15.3180360794,47.7734832764],"type":"Point"}
}