{
  "type": "Feature",
  "properties": {
    "addr:full":"Nordstrasse 6 Eugendorf Salzburg 5301",
    "addr:housenumber":"6",
    "addr:postcode":"5301",
    "addr:street":"Nordstrasse;Salzburg",
    "iso:country":"AT",
    "sg:address":"Nordstrasse 6",
    "sg:city":"Eugendorf",
    "sg:classifiers":[
        {
            "category":"Science Facility",
            "type":"Public Place"
        }
    ],
    "sg:phone":"+43 6225 7160",
    "sg:postcode":"5301",
    "sg:province":"Salzburg",
    "sg:tags":[
        "installation",
        "brewery"
    ],
    "sg:website":"keg-gruber.at",
    "wof:name":"Alfred Gruber Ges.m.b.H. & Co KG",
    "wof:placetype":"venue"
},
  "geometry": {"coordinates":[13.1257448196,47.8696899414],"type":"Point"}
}