{
  "type": "Feature",
  "properties": {
    "addr:full":"Wipplingerstr 29 Wien Wien 1010",
    "addr:housenumber":"29",
    "addr:postcode":"1010",
    "addr:street":"Wipplingerstr",
    "iso:country":"AT",
    "sg:address":"Wipplingerstr 29",
    "sg:city":"Wien",
    "sg:classifiers":[
        {
            "category":"Restaurant",
            "type":"Food & Drink"
        }
    ],
    "sg:phone":"+43 1 5326847",
    "sg:postcode":"1010",
    "sg:province":"Wien",
    "wof:name":"Buffy's Toasteria",
    "wof:placetype":"venue"
},
  "geometry": {"coordinates":[16.3670768738,48.2134590149],"type":"Point"}
}