{
  "type": "Feature",
  "properties": {
    "addr:full":"Nr 57 W\u00f6rgl Tirol 6300",
    "addr:postcode":"6300",
    "addr:street":"Nr 57 Woergl Tirol",
    "iso:country":"AT",
    "sg:address":"Nr 57",
    "sg:city":"W\u00f6rgl",
    "sg:orig_category":"Fleischhauereien",
    "sg:phone":"+43 5332 74307",
    "sg:postcode":"6300",
    "sg:province":"Tirol",
    "wof:name":"Wimpissinger Andreas",
    "wof:placetype":"venue"
},
  "geometry": {"coordinates":[12.0642328262,47.506893158],"type":"Point"}
}