{
  "type": "Feature",
  "properties": {
    "iso:country":"AT",
    "sg:address":"Krankenhausg 1",
    "sg:city":"Kufstein",
    "sg:orig_category":"Apotheken",
    "sg:phone":"+43 4353 7264548",
    "sg:postcode":"6330",
    "sg:province":"Tirol",
    "wof:name":"Obere Stadt-Apotheke Magpharm Wolfgang Glicha",
    "wof:placetype":"venue"
},
  "geometry": {"coordinates":[12.1719703674,47.5836448669],"type":"Point"}
}