{
  "type": "Feature",
  "properties": {
    "iso:country":"AT",
    "sg:address":"Rosenb\u00fchelrotte 35",
    "sg:city":"Frankenfels",
    "sg:orig_category":"Elektroinstallationsunternehmen",
    "sg:phone":"+43 2725 7208",
    "sg:postcode":"3213",
    "sg:province":"Nieder\u00f6sterreich",
    "wof:name":"Winter Marco",
    "wof:placetype":"venue"
},
  "geometry": {"coordinates":[15.3225898743,47.9807357788],"type":"Point"}
}