{
  "type": "Feature",
  "properties": {
    "addr:full":"Maierhof 12 Aurolzm\u00fcnster Ober\u00f6sterreich 4971",
    "addr:housenumber":"12",
    "addr:postcode":"4971",
    "addr:street":"Maierhof;Oberoesterreich",
    "iso:country":"AT",
    "sg:address":"Maierhof 12",
    "sg:city":"Aurolzm\u00fcnster",
    "sg:orig_category":"Steuerungstechnik",
    "sg:phone":"+43 7752 875310",
    "sg:postcode":"4971",
    "sg:province":"Ober\u00f6sterreich",
    "wof:name":"Knauseder Ing Mechatronik GmbH",
    "wof:placetype":"venue"
},
  "geometry": {"coordinates":[13.4719295502,48.2443809509],"type":"Point"}
}