{
  "type": "Feature",
  "properties": {
    "addr:full":"Kaiserstr 6 Bregenz Vorarlberg 6900",
    "addr:housenumber":"6",
    "addr:postcode":"6900",
    "addr:street":"Kaiserstr",
    "iso:country":"AT",
    "sg:address":"Kaiserstr 6",
    "sg:city":"Bregenz",
    "sg:orig_category":"Optiker",
    "sg:phone":"+43 4355 7445161",
    "sg:postcode":"6900",
    "sg:province":"Vorarlberg",
    "wof:name":"Praeg Augenoptik",
    "wof:placetype":"venue"
},
  "geometry": {"coordinates":[9.7467765808,47.5027160645],"type":"Point"}
}