{
  "type": "Feature",
  "properties": {
    "addr:full":"M\u00fchlstr 23 Podersdorf am See Burgenland 7141",
    "addr:housenumber":"23",
    "addr:postcode":"7141",
    "addr:street":"Muehlstr",
    "iso:country":"AT",
    "sg:address":"M\u00fchlstr 23",
    "sg:city":"Podersdorf am See",
    "sg:orig_category":"Heurigen / Buschenschank",
    "sg:phone":"+43 2177 2300",
    "sg:postcode":"7141",
    "sg:province":"Burgenland",
    "wof:name":"Weinschenke Zigeunergrube",
    "wof:placetype":"venue"
},
  "geometry": {"coordinates":[16.8368549347,47.8544998169],"type":"Point"}
}