{
  "type": "Feature",
  "properties": {
    "iso:country":"AT",
    "sg:address":"Lilienthalg 6-10",
    "sg:city":"Wien",
    "sg:orig_category":"Versicherungsunternehmen",
    "sg:phone":"+43 4317 984069",
    "sg:postcode":"1030",
    "sg:province":"Wien",
    "wof:name":"Donau Allg Vers AG - KFZ-Zulassungsstelle",
    "wof:placetype":"venue"
},
  "geometry": {"coordinates":[16.3920841217,48.1790313721],"type":"Point"}
}