{
  "type": "Feature",
  "properties": {
    "iso:country":"AT",
    "sg:address":"Burggraben 5",
    "sg:city":"Innsbruck",
    "sg:orig_category":"Blumeneinzelhandel",
    "sg:phone":"+43 512 585075",
    "sg:postcode":"6020",
    "sg:province":"Tirol",
    "wof:name":"Hajny Brigitte",
    "wof:placetype":"venue"
},
  "geometry": {"coordinates":[11.4197340012,47.2605209351],"type":"Point"}
}