{
  "type": "Feature",
  "properties": {
    "addr:full":"Johann-Teufel-G 81 Wien Wien 1230",
    "addr:housenumber":"81",
    "addr:postcode":"1230",
    "addr:street":"Johann-Teufel-G",
    "iso:country":"AT",
    "sg:address":"Johann-Teufel-G 81",
    "sg:city":"Wien",
    "sg:orig_category":"Steuerberatung",
    "sg:phone":"+43 4318 887688",
    "sg:postcode":"1230",
    "sg:province":"Wien",
    "wof:name":"Breinl Hans Gert Dkfm Dr",
    "wof:placetype":"venue"
},
  "geometry": {"coordinates":[16.2738933563,48.1406021118],"type":"Point"}
}