{
  "type": "Feature",
  "properties": {
    "addr:full":"Judeng 15 Salzburg Salzburg 5020",
    "addr:housenumber":"15",
    "addr:postcode":"5020",
    "addr:street":"Judeng;Salzburg",
    "iso:country":"AT",
    "sg:address":"Judeng 15",
    "sg:city":"Salzburg",
    "sg:orig_category":"Geschenkartikel",
    "sg:phone":"+43 662 840231",
    "sg:postcode":"5020",
    "sg:province":"Salzburg",
    "wof:name":"Geschenke aus dem Orient - Kahled Abd Altaher Ahmed Said",
    "wof:placetype":"venue"
},
  "geometry": {"coordinates":[13.0827417374,47.8034362793],"type":"Point"}
}