{
  "type": "Feature",
  "properties": {
    "addr:full":"Bahnhofstr 3 Zell am Ziller Tirol 6280",
    "addr:housenumber":"3",
    "addr:postcode":"6280",
    "addr:street":"Bahnhofstr;Tirol",
    "iso:country":"AT",
    "sg:address":"Bahnhofstr 3",
    "sg:city":"Zell am Ziller",
    "sg:classifiers":[
        {
            "category":"Travel",
            "subcategory":"Hotels & Motels",
            "type":"Entertainment"
        }
    ],
    "sg:phone":"+43 4352 8226120",
    "sg:postcode":"6280",
    "sg:province":"Tirol",
    "wof:name":"Alpenhotel Zellerhof - Schul u Lehrhotel",
    "wof:placetype":"venue"
},
  "geometry": {"coordinates":[11.8815040588,47.2326049805],"type":"Point"}
}