{
  "type": "Feature",
  "properties": {
    "iso:country":"AT",
    "sg:address":"Vinzenzg 22",
    "sg:city":"Graz",
    "sg:orig_category":"Blumeneinzelhandel",
    "sg:phone":"+43 316 582118",
    "sg:postcode":"8020",
    "sg:province":"Steiermark",
    "wof:name":"G\u00fcnther Renate",
    "wof:placetype":"venue"
},
  "geometry": {"coordinates":[15.4048042297,47.072807312],"type":"Point"}
}