{
  "type": "Feature",
  "properties": {
    "iso:country":"AT",
    "sg:address":"Friedhofallee 8",
    "sg:city":"Deutsch Wagram",
    "sg:orig_category":"Hauptschulen",
    "sg:phone":"+43 2247 2491",
    "sg:postcode":"2232",
    "sg:province":"Nieder\u00f6sterreich",
    "wof:name":"Hauptschule",
    "wof:placetype":"venue"
},
  "geometry": {"coordinates":[16.5589962006,48.2978248596],"type":"Point"}
}