{
  "type": "Feature",
  "properties": {
    "addr:full":"Vogelweiderstr 44a/4 Salzburg Salzburg 5020",
    "addr:housenumber":"44a / 4",
    "addr:postcode":"5020",
    "addr:street":"Vogelweiderstr;Salzburg",
    "iso:country":"AT",
    "sg:address":"Vogelweiderstr 44a/4",
    "sg:city":"Salzburg",
    "sg:orig_category":"Schaltanlagen U -Systeme",
    "sg:phone":"+43 662 8822670",
    "sg:postcode":"5020",
    "sg:province":"Salzburg",
    "wof:name":"MOELLER Geb\u00e4udeautomation KG",
    "wof:placetype":"venue"
},
  "geometry": {"coordinates":[13.0544376373,47.812461853],"type":"Point"}
}