{
  "type": "Feature",
  "properties": {
    "iso:country":"AT",
    "sg:address":"Nr 10",
    "sg:city":"Gro\u00dfsteinbach",
    "sg:orig_category":"Friseure U Frisiersalons",
    "sg:phone":"+43 4333 8623307",
    "sg:postcode":"8265",
    "sg:province":"Steiermark",
    "wof:name":"Frisiersalon Monika",
    "wof:placetype":"venue"
},
  "geometry": {"coordinates":[13.1806230545,51.1235580444],"type":"Point"}
}