{
  "type": "Feature",
  "properties": {
    "addr:full":"Karmeliterg 5 Wien Wien 1020",
    "addr:housenumber":"5",
    "addr:postcode":"1020",
    "addr:street":"Karmeliterg",
    "iso:country":"AT",
    "sg:address":"Karmeliterg 5",
    "sg:city":"Wien",
    "sg:orig_category":"Psychotherapie",
    "sg:phone":"+43 1 2164399",
    "sg:postcode":"1020",
    "sg:province":"Wien",
    "wof:name":"Werdigier Ruth",
    "wof:placetype":"venue"
},
  "geometry": {"coordinates":[16.3789997101,48.2166557312],"type":"Point"}
}