{
  "type": "Feature",
  "properties": {
    "iso:country":"AT",
    "sg:address":"Landstra\u00dfer Hauptstrasse 75-77/21",
    "sg:city":"Wien",
    "sg:classifiers":[
        {
            "category":"Professional",
            "subcategory":"Business Services",
            "type":"Services"
        }
    ],
    "sg:phone":"+43 1 7159808",
    "sg:postcode":"1030",
    "sg:province":"Wien",
    "sg:tags":[
        "consulting",
        "sap"
    ],
    "sg:website":"epoconsulting.com",
    "wof:name":"EPO Consulting GmbH",
    "wof:placetype":"venue"
},
  "geometry": {"coordinates":[16.4025096893,48.1936683655],"type":"Point"}
}