{
  "type": "Feature",
  "properties": {
    "addr:full":"Nr 439 Feldbach Steiermark 8330",
    "addr:postcode":"8330",
    "addr:street":"Nr 439",
    "iso:country":"AT",
    "sg:address":"Nr 439",
    "sg:city":"Feldbach",
    "sg:classifiers":[
        {
            "category":"Home & Garden",
            "subcategory":"Building Materials",
            "type":"Retail Goods"
        }
    ],
    "sg:phone":"+43 4331 5262080",
    "sg:postcode":"8330",
    "sg:province":"Steiermark",
    "sg:tags":[
        "baustoffe",
        "-material",
        "u"
    ],
    "wof:name":"FMA Asphaltwerk GmbH & Co KG",
    "wof:placetype":"venue"
},
  "geometry": {"coordinates":[15.888250351,46.9527397156],"type":"Point"}
}