{
  "type": "Feature",
  "properties": {
    "addr:full":"Nr 62 Spielfeld Steiermark 8471",
    "addr:postcode":"8471",
    "addr:street":"Nr",
    "iso:country":"AT",
    "sg:address":"Nr 62",
    "sg:city":"Spielfeld",
    "sg:orig_category":"Lastkraftwagen",
    "sg:phone":"+43 4334 5320546",
    "sg:postcode":"8471",
    "sg:province":"Steiermark",
    "wof:name":"Temmel Erich - LKW Nutzfahrzeuge",
    "wof:placetype":"venue"
},
  "geometry": {"coordinates":[15.6304121017,46.7054443359],"type":"Point"}
}