{
  "type": "Feature",
  "properties": {
    "addr:full":"Hummelgasse 50 Wien Wien 1130",
    "addr:housenumber":"50",
    "addr:postcode":"1130",
    "addr:street":"Hummelgasse",
    "iso:country":"AT",
    "sg:address":"Hummelgasse 50",
    "sg:city":"Wien",
    "sg:classifiers":[
        {
            "category":"Social Services",
            "subcategory":"Job Training",
            "type":"Services"
        }
    ],
    "sg:phone":"+43 1 8791252",
    "sg:postcode":"1130",
    "sg:province":"Wien",
    "sg:tags":[
        "antistatic",
        "cleaner"
    ],
    "wof:name":"Richard Koffmahn",
    "wof:placetype":"venue"
},
  "geometry": {"coordinates":[16.2816696167,48.1848106384],"type":"Point"}
}