{
  "type": "Feature",
  "properties": {
    "addr:full":"Leebg 30-32 Wien Wien 1100",
    "addr:postcode":"30-32;1100",
    "iso:country":"AT",
    "sg:address":"Leebg 30-32",
    "sg:city":"Wien",
    "sg:classifiers":[
        {
            "category":"Professional",
            "subcategory":"Art Services",
            "type":"Services"
        }
    ],
    "sg:phone":"+43 1 7986275",
    "sg:postcode":"1100",
    "sg:province":"Wien",
    "sg:tags":[
        "designer"
    ],
    "wof:name":"Magnes Christian - Design",
    "wof:placetype":"venue"
},
  "geometry": {"coordinates":[16.3744049072,48.1782684326],"type":"Point"}
}