{
  "type": "Feature",
  "properties": {
    "addr:full":"Gr\u00fcnau Gr\u00fcnau im Almtal Ober\u00f6sterreich 4645",
    "addr:postcode":"4645",
    "addr:street":"Im Almtal",
    "iso:country":"AT",
    "sg:address":"Gr\u00fcnau",
    "sg:city":"Gr\u00fcnau im Almtal",
    "sg:orig_category":"ChildrenS Furniture",
    "sg:phone":"+43 761660060",
    "sg:postcode":"4645",
    "sg:province":"Ober\u00f6sterreich",
    "sg:website":"members.nextra.at/grabner",
    "wof:name":"Tischlerei Grabner GmbH",
    "wof:placetype":"venue"
},
  "geometry": {"coordinates":[173.85847473140001,-39.453868866],"type":"Point"}
}