{
  "type": "Feature",
  "properties": {
    "addr:full":"Steinbockallee 31 Rum Tirol 6063",
    "addr:housenumber":"31",
    "addr:postcode":"6063",
    "addr:street":"Steinbockallee;Tirol",
    "iso:country":"AT",
    "sg:address":"Steinbockallee 31",
    "sg:city":"Rum",
    "sg:orig_category":"Damenmoden",
    "sg:phone":"+43 4351 2206260",
    "sg:postcode":"6063",
    "sg:province":"Tirol",
    "wof:name":"KiK Textilien u Non-Food GesmbH",
    "wof:placetype":"venue"
},
  "geometry": {"coordinates":[11.4515810013,47.2712059021],"type":"Point"}
}