{
  "type": "Feature",
  "properties": {
    "addr:full":"Favoritenstr 213 Wien Wien 1100",
    "addr:housenumber":"213",
    "addr:postcode":"1100",
    "iso:country":"AT",
    "sg:address":"Favoritenstr 213",
    "sg:city":"Wien",
    "sg:orig_category":"Gastronomie- U Hotelbetriebsgesellschaften",
    "sg:phone":"+43 1 60760310",
    "sg:postcode":"1100",
    "sg:province":"Wien",
    "wof:name":"RETAS HandelsgesmbH",
    "wof:placetype":"venue"
},
  "geometry": {"coordinates":[16.3830013275,48.1635246277],"type":"Point"}
}