{
  "type": "Feature",
  "properties": {
    "addr:full":"Trautenfels Steiermark 8951",
    "addr:postcode":"8951",
    "iso:country":"AT",
    "sg:city":"Trautenfels",
    "sg:classifiers":[
        {
            "category":"Restaurant",
            "type":"Food & Drink"
        }
    ],
    "sg:phone":"+43 4336 8224767",
    "sg:postcode":"8951",
    "sg:province":"Steiermark",
    "wof:name":"Fischrestaurant K u V Rieger GesmbH",
    "wof:placetype":"venue"
},
  "geometry": {"coordinates":[14.0831203461,47.5187416077],"type":"Point"}
}