{
  "type": "Feature",
  "properties": {
    "addr:full":"Dr.-Karl-Renner-Pl 5 Attnang-Puchheim Ober\u00f6sterreich 4800",
    "addr:housenumber":"5",
    "addr:postcode":"4800",
    "addr:street":"Dr.-Karl-Renner-Pl",
    "iso:country":"AT",
    "sg:address":"Dr.-Karl-Renner-Pl 5",
    "sg:city":"Attnang-Puchheim",
    "sg:orig_category":"Eisenwaren",
    "sg:phone":"+43 767467193",
    "sg:postcode":"4800",
    "sg:province":"Ober\u00f6sterreich",
    "wof:name":"Langthaler & Wetzlmayr OEG Werkstatt-Hobby-Garten",
    "wof:placetype":"venue"
},
  "geometry": {"coordinates":[13.7217588425,48.0112419128],"type":"Point"}
}