{
  "type": "Feature",
  "properties": {
    "iso:country":"AT",
    "sg:address":"Triester Str 17-25",
    "sg:city":"Guntramsdorf",
    "sg:orig_category":"Tankstellen",
    "sg:phone":"+43 2236 506532",
    "sg:postcode":"2353",
    "sg:province":"Nieder\u00f6sterreich",
    "wof:name":"JET Tankstelle",
    "wof:placetype":"venue"
},
  "geometry": {"coordinates":[16.3060626984,48.0464782715],"type":"Point"}
}