{
  "type": "Feature",
  "properties": {
    "addr:full":"Loferer Bundesstr 10 Zell am See Salzburg 5700",
    "addr:housenumber":"10",
    "addr:postcode":"5700",
    "addr:street":"Salzburg",
    "iso:country":"AT",
    "sg:address":"Loferer Bundesstr 10",
    "sg:city":"Zell am See",
    "sg:orig_category":"Bausparkassen",
    "sg:phone":"+43 5 7070204",
    "sg:postcode":"5700",
    "sg:province":"Salzburg",
    "wof:name":"Bausparkasse W\u00fcstenrot AG",
    "wof:placetype":"venue"
},
  "geometry": {"coordinates":[12.7967386246,47.3248748779],"type":"Point"}
}