{
  "type": "Feature",
  "properties": {
    "addr:full":"Walser Str 43 Riezlern Vorarlberg 6991",
    "addr:postcode":"6991",
    "addr:street":"Str 43",
    "iso:country":"AT",
    "sg:address":"Walser Str 43",
    "sg:city":"Riezlern",
    "sg:orig_category":"Banken U Sparkassen",
    "sg:phone":"+43 4355 1720203",
    "sg:postcode":"6991",
    "sg:province":"Vorarlberg",
    "wof:name":"Raiffeisenbank Kleinwalsertal AG",
    "wof:placetype":"venue"
},
  "geometry": {"coordinates":[10.1890096664,47.3582992554],"type":"Point"}
}