{
  "type": "Feature",
  "properties": {
    "addr:full":"Andreas-Hofer-Str 480 Seefeld in Tirol Tirol 6100",
    "addr:housenumber":"480",
    "addr:postcode":"6100",
    "addr:street":"Seefeld;Tirol",
    "iso:country":"AT",
    "sg:address":"Andreas-Hofer-Str 480",
    "sg:city":"Seefeld in Tirol",
    "sg:orig_category":"Pensionen / Privatzimmer",
    "sg:phone":"+43 5212 2677",
    "sg:postcode":"6100",
    "sg:province":"Tirol",
    "wof:name":"Haus Orplid",
    "wof:placetype":"venue"
},
  "geometry": {"coordinates":[11.1889953613,47.3294143677],"type":"Point"}
}