{
  "type": "Feature",
  "properties": {
    "addr:full":"Leonfeldner Str 276b Linz Ober\u00f6sterreich 4040",
    "addr:postcode":"4040",
    "addr:street":"Str 276B",
    "iso:country":"AT",
    "sg:address":"Leonfeldner Str 276b",
    "sg:city":"Linz",
    "sg:orig_category":"\u00c3\u201erzte / F Allgemeinmedizin",
    "sg:phone":"+43 732 251600",
    "sg:postcode":"4040",
    "sg:province":"Ober\u00f6sterreich",
    "wof:name":"Hausleitner Heinz Dr",
    "wof:placetype":"venue"
},
  "geometry": {"coordinates":[14.2941770554,48.3454666138],"type":"Point"}
}