{
  "type": "Feature",
  "properties": {
    "addr:full":"Wr Neust\u00e4dter Str 53 Steinbrunn Burgenland 7035",
    "addr:postcode":"7035",
    "addr:street":"Str",
    "iso:country":"AT",
    "sg:address":"Wr Neust\u00e4dter Str 53",
    "sg:city":"Steinbrunn",
    "sg:orig_category":"Solartechnik",
    "sg:phone":"+43 4326 8872018",
    "sg:postcode":"7035",
    "sg:province":"Burgenland",
    "wof:name":"Mezgolits Herbert",
    "wof:placetype":"venue"
},
  "geometry": {"coordinates":[16.4131641388,47.8366889954],"type":"Point"}
}