{
  "type": "Feature",
  "properties": {
    "addr:full":"Westbahnstr 15 Wien Wien 1070",
    "addr:housenumber":"15",
    "addr:postcode":"1070",
    "addr:street":"Westbahnstr",
    "iso:country":"AT",
    "sg:address":"Westbahnstr 15",
    "sg:city":"Wien",
    "sg:orig_category":"Lebensmittel / Einzelhandel",
    "sg:phone":"+43 1 5233223",
    "sg:postcode":"1070",
    "sg:province":"Wien",
    "wof:name":"Billa AG",
    "wof:placetype":"venue"
},
  "geometry": {"coordinates":[16.3452205658,48.2016944885],"type":"Point"}
}