{
  "type": "Feature",
  "properties": {
    "addr:full":"Salzburger Str 24 Bischofshofen Salzburg 5500",
    "addr:housenumber":"24",
    "addr:postcode":"5500",
    "addr:street":"Salzburger Str;Salzburg",
    "iso:country":"AT",
    "sg:address":"Salzburger Str 24",
    "sg:city":"Bischofshofen",
    "sg:orig_category":"Damenmoden",
    "sg:phone":"+43 6462 2332",
    "sg:postcode":"5500",
    "sg:province":"Salzburg",
    "wof:name":"Hedegger-Moden Ellmauthaler Hertha",
    "wof:placetype":"venue"
},
  "geometry": {"coordinates":[13.2189769745,47.4197883606],"type":"Point"}
}