{
  "type": "Feature",
  "properties": {
    "iso:country":"AT",
    "sg:address":"Salzburger Str 24",
    "sg:city":"Bischofshofen",
    "sg:orig_category":"Damenmoden",
    "sg:phone":"+43 6462 2332",
    "sg:postcode":"5500",
    "sg:province":"Salzburg",
    "wof:name":"Hedegger-Moden Ellmauthaler Hertha",
    "wof:placetype":"venue"
},
  "geometry": {"coordinates":[13.2189769745,47.4197883606],"type":"Point"}
}