{
  "type": "Feature",
  "properties": {
    "addr:full":"Schlosserg\u00e4\u00dfchen 1 Baden Nieder\u00f6sterreich 2500",
    "addr:housenumber":"1",
    "addr:postcode":"2500",
    "addr:street":"Schlossergaesschen;Niederoesterreich",
    "iso:country":"AT",
    "sg:address":"Schlosserg\u00e4\u00dfchen 1",
    "sg:city":"Baden",
    "sg:orig_category":"Versicherungsunternehmen",
    "sg:phone":"+43 2252 48571",
    "sg:postcode":"2500",
    "sg:province":"Nieder\u00f6sterreich",
    "wof:name":"Grazer Wechselseitige Versicherung AG",
    "wof:placetype":"venue"
},
  "geometry": {"coordinates":[16.2145595551,47.9845733643],"type":"Point"}
}