{
  "type": "Feature",
  "properties": {
    "iso:country":"AT",
    "sg:address":"Bahnhofstrasse 21",
    "sg:city":"Velden am W\u00f6rther See",
    "sg:classifiers":[
        {
            "category":"Professional",
            "subcategory":"Art Services",
            "type":"Services"
        }
    ],
    "sg:phone":"+43 4274 2422",
    "sg:postcode":"9220",
    "sg:province":"K\u00e4rnten",
    "sg:tags":[
        "graphic",
        "designer"
    ],
    "sg:website":"thaler-design.com",
    "wof:name":"THALER DESIGN GmbH",
    "wof:placetype":"venue"
},
  "geometry": {"coordinates":[14.0438718796,46.6191291809],"type":"Point"}
}