{
  "type": "Feature",
  "properties": {
    "addr:full":"Karl Zanger-Str 13 Absam Tirol 6067",
    "addr:housenumber":"13",
    "addr:postcode":"6067",
    "addr:street":"Absam Tirol",
    "iso:country":"AT",
    "sg:address":"Karl Zanger-Str 13",
    "sg:city":"Absam",
    "sg:orig_category":"Holdinggesellschaften",
    "sg:phone":"+43 5223 53331",
    "sg:postcode":"6067",
    "sg:province":"Tirol",
    "wof:name":"Absamer L\u00e4uteanlagen GmbH",
    "wof:placetype":"venue"
},
  "geometry": {"coordinates":[11.5050792694,47.2934150696],"type":"Point"}
}