{
  "type": "Feature",
  "properties": {
    "iso:country":"AT",
    "sg:address":"Prehauserpl 1",
    "sg:city":"Radstadt",
    "sg:orig_category":"Non-Classified Establishments",
    "sg:phone":"+43 6452 42460",
    "sg:postcode":"5550",
    "sg:province":"Salzburg",
    "wof:name":"Pfarramt r\u00f6m kath",
    "wof:placetype":"venue"
},
  "geometry": {"coordinates":[13.4655704498,47.3853416443],"type":"Point"}
}