{
  "type": "Feature",
  "properties": {
    "addr:full":"Waidhofner Str 2-4/Top 3/9/1.OG Amstetten Nieder\u00f6sterreich 3300",
    "addr:housenumber":"2-4 / top 3 / 9 / 1.og",
    "addr:postcode":"3300",
    "addr:street":"Str;Niederoesterreich",
    "iso:country":"AT",
    "sg:address":"Waidhofner Str 2-4/Top 3/9/1.OG",
    "sg:city":"Amstetten",
    "sg:orig_category":"Telekommunikation",
    "sg:phone":"+43 800 664300",
    "sg:postcode":"3300",
    "sg:province":"Nieder\u00f6sterreich",
    "wof:name":"A1-Shop Amstetten",
    "wof:placetype":"venue"
},
  "geometry": {"coordinates":[14.8706607819,48.1244812012],"type":"Point"}
}