{
  "type": "Feature",
  "properties": {
    "iso:country":"AT",
    "sg:address":"Klagenfurter Str 5",
    "sg:city":"Moosburg",
    "sg:orig_category":"Banken U Sparkassen",
    "sg:phone":"+43 4272 832080",
    "sg:postcode":"9062",
    "sg:province":"K\u00e4rnten",
    "wof:name":"Raiffeisenbank Moosburg-Tigring regGenmbH",
    "wof:placetype":"venue"
},
  "geometry": {"coordinates":[14.1748075485,46.6581726074],"type":"Point"}
}