{
  "type": "Feature",
  "properties": {
    "iso:country":"AT",
    "sg:address":"Landstrasse 51 ",
    "sg:city":"Schlins",
    "sg:classifiers":[
        {
            "category":"Science Facility",
            "type":"Public Place"
        }
    ],
    "sg:phone":"+43 5524 2863",
    "sg:postcode":"6824",
    "sg:province":"Vorarlberg",
    "sg:tags":[
        "cnc",
        "flamecutting",
        "installation",
        "combined",
        "drilling"
    ],
    "sg:website":"www.bruno-matt.at",
    "wof:name":"Bruno Matt",
    "wof:placetype":"venue"
},
  "geometry": {"coordinates":[9.703245163,47.2000427246],"type":"Point"}
}