{
  "type": "Feature",
  "properties": {
    "iso:country":"AT",
    "sg:address":"Industriestr 4",
    "sg:city":"Weiz",
    "sg:classifiers":[
        {
            "category":"Autos & Motor Vehicles",
            "subcategory":"Automobile Sales",
            "type":"Retail Goods"
        }
    ],
    "sg:phone":"+43 4331 725900",
    "sg:postcode":"8160",
    "sg:province":"Steiermark",
    "sg:tags":[
        "motor-cars"
    ],
    "wof:name":"AUTOMOBILTECHNIK BLAU ZWGNDL. D. TESMA MOTOREN & GETRIEBETECHNIK GMBH",
    "wof:placetype":"venue"
},
  "geometry": {"coordinates":[15.6215696335,47.2169532776],"type":"Point"}
}