{
  "type": "Feature",
  "properties": {
    "addr:full":"Josef-Pirchl-Str 17 Kitzb\u00fchel Tirol 6370",
    "addr:housenumber":"17",
    "addr:postcode":"6370",
    "addr:street":"Josef-Pirchl-Str;Tirol",
    "iso:country":"AT",
    "sg:address":"Josef-Pirchl-Str 17",
    "sg:city":"Kitzb\u00fchel",
    "sg:classifiers":[
        {
            "category":"Restaurant",
            "type":"Food & Drink"
        }
    ],
    "sg:phone":"+43 5356 62729",
    "sg:postcode":"6370",
    "sg:province":"Tirol",
    "sg:tags":[
        "pizzeria"
    ],
    "wof:name":"Pizzeria Adria GesmbH",
    "wof:placetype":"venue"
},
  "geometry": {"coordinates":[12.3898220062,47.4501075745],"type":"Point"}
}