{
  "type": "Feature",
  "properties": {
    "addr:full":"Grabenweg 67 Innsbruck Tirol 6020",
    "addr:housenumber":"67",
    "addr:postcode":"6020",
    "addr:street":"Grabenweg;Tirol",
    "iso:country":"AT",
    "sg:address":"Grabenweg 67",
    "sg:city":"Innsbruck",
    "sg:classifiers":[
        {
            "category":"Communications",
            "subcategory":"Television Station",
            "type":"Services"
        }
    ],
    "sg:phone":"+43 512 393950",
    "sg:postcode":"6020",
    "sg:province":"Tirol",
    "sg:tags":[
        "entry",
        "phone"
    ],
    "sg:website":"elvox.at",
    "wof:name":"Trowa - Elektronik Dietmar Asen KG",
    "wof:placetype":"venue"
},
  "geometry": {"coordinates":[11.4383325577,47.2650718689],"type":"Point"}
}