{
  "type": "Feature",
  "properties": {
    "iso:country":"AT",
    "sg:address":"Nr 145",
    "sg:city":"Neudau",
    "sg:classifiers":[
        {
            "category":"Home & Garden",
            "subcategory":"Building Materials",
            "type":"Retail Goods"
        }
    ],
    "sg:phone":"+43 4333 8322170",
    "sg:postcode":"8292",
    "sg:province":"Steiermark",
    "sg:tags":[
        "baustoffe",
        "-material",
        "u"
    ],
    "wof:name":"Glaser Werner GesmbH",
    "wof:placetype":"venue"
},
  "geometry": {"coordinates":[16.1003761292,47.1778526306],"type":"Point"}
}