{
  "type": "Feature",
  "properties": {
    "addr:full":"Villacher Str 29 Spittal an der Drau K\u00e4rnten 9800",
    "addr:housenumber":"29",
    "addr:postcode":"9800",
    "addr:street":"Str;Kaernten",
    "iso:country":"AT",
    "sg:address":"Villacher Str 29",
    "sg:city":"Spittal an der Drau",
    "sg:orig_category":"Papier- U Schreibwaren / Einzelhandel",
    "sg:phone":"+43 4347 623943",
    "sg:postcode":"9800",
    "sg:province":"K\u00e4rnten",
    "wof:name":"Brandst\u00e4tter Theresia",
    "wof:placetype":"venue"
},
  "geometry": {"coordinates":[13.5061988831,46.7927703857],"type":"Point"}
}