{
  "type": "Feature",
  "properties": {
    "addr:full":"Hauserdorfstr 451 Kaprun Salzburg 5710",
    "addr:housenumber":"451",
    "addr:postcode":"5710",
    "addr:street":"Kaprun Salzburg",
    "iso:country":"AT",
    "sg:address":"Hauserdorfstr 451",
    "sg:city":"Kaprun",
    "sg:orig_category":"Installationsunternehmen",
    "sg:phone":"+43 6547 83380",
    "sg:postcode":"5710",
    "sg:province":"Salzburg",
    "wof:name":"Haslauer Installationen GesmbH",
    "wof:placetype":"venue"
},
  "geometry": {"coordinates":[12.7577257156,47.2704467773],"type":"Point"}
}