{
  "type": "Feature",
  "properties": {
    "iso:country":"AT",
    "sg:address":"Merang 56",
    "sg:city":"Graz",
    "sg:classifiers":[
        {
            "category":"Professional",
            "subcategory":"Computer Services",
            "type":"Services"
        }
    ],
    "sg:phone":"+43 316 673630",
    "sg:postcode":"8010",
    "sg:province":"Steiermark",
    "sg:tags":[
        "software"
    ],
    "wof:name":"Adhoc Hard- und Software GesmbH Nfg KG",
    "wof:placetype":"venue"
},
  "geometry": {"coordinates":[15.4561882019,47.0717811584],"type":"Point"}
}