{
  "type": "Feature",
  "properties": {
    "addr:full":"Am Sonnenrain 21 Hallwang Salzburg 5300",
    "addr:housenumber":"21",
    "addr:postcode":"5300",
    "addr:street":"Am Sonnenrain;Salzburg",
    "iso:country":"AT",
    "sg:address":"Am Sonnenrain 21",
    "sg:city":"Hallwang",
    "sg:classifiers":[
        {
            "category":"Shopping",
            "subcategory":"Computers & Home Electronics",
            "type":"Retail Goods"
        }
    ],
    "sg:phone":"+43 662 665600",
    "sg:postcode":"5300",
    "sg:province":"Salzburg",
    "sg:tags":[
        "individual",
        "software"
    ],
    "sg:website":"rieger.at",
    "wof:name":"Rieger Software GmbH",
    "wof:placetype":"venue"
},
  "geometry": {"coordinates":[13.1020746231,47.8451080322],"type":"Point"}
}