{
  "type": "Feature",
  "properties": {
    "addr:full":"Linzer Str 54 Wien Wien 1140",
    "addr:housenumber":"54",
    "addr:postcode":"1140",
    "addr:street":"Linzer Str",
    "iso:country":"AT",
    "sg:address":"Linzer Str 54",
    "sg:city":"Wien",
    "sg:orig_category":"Drogerien",
    "sg:phone":"+43 1 9821354",
    "sg:postcode":"1140",
    "sg:province":"Wien",
    "wof:name":"Havel Michael Dr",
    "wof:placetype":"venue"
},
  "geometry": {"coordinates":[16.2696990967,48.1994247437],"type":"Point"}
}