{
  "type": "Feature",
  "properties": {
    "addr:full":"Wr Neust\u00e4dter Str 20 Zemendorf Burgenland 7023",
    "addr:postcode":"7023",
    "addr:street":"Str 20 Zemendorf",
    "iso:country":"AT",
    "sg:address":"Wr Neust\u00e4dter Str 20",
    "sg:city":"Zemendorf",
    "sg:orig_category":"Werbeagenturen",
    "sg:phone":"+43 4326 265858",
    "sg:postcode":"7023",
    "sg:province":"Burgenland",
    "sg:website":"kornfehl.com",
    "wof:name":"WK Werbeagentur Kornfehl",
    "wof:placetype":"venue"
},
  "geometry": {"coordinates":[16.4522590637,47.761844635],"type":"Point"}
}