{
  "type": "Feature",
  "properties": {
    "addr:full":"Siedlerg 6 Felixdorf Nieder\u00f6sterreich 2603",
    "addr:housenumber":"6",
    "addr:postcode":"2603",
    "addr:street":"Siedlerg",
    "iso:country":"AT",
    "sg:address":"Siedlerg 6",
    "sg:city":"Felixdorf",
    "sg:orig_category":"Volksschulen",
    "sg:phone":"+43 2628 626660",
    "sg:postcode":"2603",
    "sg:province":"Nieder\u00f6sterreich",
    "wof:name":"Volksschule",
    "wof:placetype":"venue"
},
  "geometry": {"coordinates":[16.2415294647,47.8815612793],"type":"Point"}
}