{
  "type": "Feature",
  "properties": {
    "iso:country":"AT",
    "sg:address":"Hauptpl 7",
    "sg:city":"Gars am Kamp",
    "sg:orig_category":"Lebensmittel / Einzelhandel",
    "sg:phone":"+43 2985 23410",
    "sg:postcode":"3571",
    "sg:province":"Nieder\u00f6sterreich",
    "wof:name":"Kiennast Julius Einzelhandels-GmbH & Co KG",
    "wof:placetype":"venue"
},
  "geometry": {"coordinates":[15.6587266922,48.5969390869],"type":"Point"}
}