{
  "type": "Feature",
  "properties": {
    "addr:full":"Dorfstr 95 Rattenberg Tirol 6240",
    "addr:housenumber":"95",
    "addr:postcode":"6240",
    "addr:street":"Dorfstr;Tirol",
    "iso:country":"AT",
    "sg:address":"Dorfstr 95",
    "sg:city":"Rattenberg",
    "sg:orig_category":"Pensionen / Privatzimmer",
    "sg:phone":"+43 5337 64574",
    "sg:postcode":"6240",
    "sg:province":"Tirol",
    "wof:name":"Michaelerhof",
    "wof:placetype":"venue"
},
  "geometry": {"coordinates":[11.9041719437,47.4463653564],"type":"Point"}
}