{
  "type": "Feature",
  "properties": {
    "iso:country":"AT",
    "sg:address":"Himmelpfortg 13",
    "sg:city":"Wien",
    "sg:orig_category":"\u00c3\u201erzte / F Allgemeinmedizin",
    "sg:phone":"+43 664 3122661",
    "sg:postcode":"1010",
    "sg:province":"Wien",
    "wof:name":"Fykatas-Guth Birgit Dr",
    "wof:placetype":"venue"
},
  "geometry": {"coordinates":[16.3733406067,48.2056808472],"type":"Point"}
}