{
  "type": "Feature",
  "properties": {
    "addr:full":"Pasettistr 103 Wien Wien 1200",
    "addr:housenumber":"103",
    "addr:postcode":"1200",
    "iso:country":"AT",
    "sg:address":"Pasettistr 103",
    "sg:city":"Wien",
    "sg:orig_category":"Bauunternehmen",
    "sg:phone":"+43 1 3746365",
    "sg:postcode":"1200",
    "sg:province":"Wien",
    "wof:name":"AVIA Planungs- und BaugesmbH",
    "wof:placetype":"venue"
},
  "geometry": {"coordinates":[16.388048172,48.2321853638],"type":"Point"}
}