{
  "type": "Feature",
  "properties": {
    "addr:full":"Lahntalweg 6/19 Innsbruck Tirol 6020",
    "addr:housenumber":"6 / 19",
    "addr:postcode":"6020",
    "addr:street":"Lahntalweg;Tirol",
    "iso:country":"AT",
    "sg:address":"Lahntalweg 6/19",
    "sg:city":"Innsbruck",
    "sg:orig_category":"Massagen",
    "sg:phone":"+43 664 1509679",
    "sg:postcode":"6020",
    "sg:province":"Tirol",
    "wof:name":"Eckbauer Luise - Akupunkturmassage n Penzel",
    "wof:placetype":"venue"
},
  "geometry": {"coordinates":[11.3507013321,47.2676773071],"type":"Point"}
}