{
  "type": "Feature",
  "properties": {
    "iso:country":"AT",
    "sg:address":"Industriegel\u00e4nde 1",
    "sg:city":"Donnerskirchen",
    "sg:orig_category":"Druckereien",
    "sg:phone":"+43 2683 71051",
    "sg:postcode":"7082",
    "sg:province":"Burgenland",
    "wof:name":"Druckerei Mayer GmbH",
    "wof:placetype":"venue"
},
  "geometry": {"coordinates":[16.6494483948,47.8743286133],"type":"Point"}
}