{
  "type": "Feature",
  "properties": {
    "iso:country":"AT",
    "sg:address":"Hammerweg 29",
    "sg:city":"Micheldorf in Ober\u00f6sterreich",
    "sg:orig_category":"Maschinenhandel",
    "sg:phone":"+43 7582 63886",
    "sg:postcode":"4563",
    "sg:province":"Ober\u00f6sterreich",
    "wof:name":"Agie \u00f6sterreich - Rudolf Schmidt",
    "wof:placetype":"venue"
},
  "geometry": {"coordinates":[14.1309604645,47.8810310364],"type":"Point"}
}