{
  "type": "Feature",
  "properties": {
    "iso:country":"AT",
    "sg:address":"Untere Hauptstr 1",
    "sg:city":"Bad Pirawarth",
    "sg:orig_category":"Lebensmittel / Einzelhandel",
    "sg:phone":"+43 2574 22050",
    "sg:postcode":"2222",
    "sg:province":"Nieder\u00f6sterreich",
    "wof:name":"Kaufhaus Plach",
    "wof:placetype":"venue"
},
  "geometry": {"coordinates":[16.6007480621,48.4515113831],"type":"Point"}
}