{
  "type": "Feature",
  "properties": {
    "addr:full":"Kirchenstr 11 Maria Enzersdorf Nieder\u00f6sterreich 2344",
    "addr:housenumber":"11",
    "addr:postcode":"2344",
    "addr:street":"Kirchenstr",
    "iso:country":"AT",
    "sg:address":"Kirchenstr 11",
    "sg:city":"Maria Enzersdorf",
    "sg:orig_category":"Werbeagenturen",
    "sg:phone":"+43 2236 29924",
    "sg:postcode":"2344",
    "sg:province":"Nieder\u00f6sterreich",
    "wof:name":"Xtratour Communication, Werbeagentur Mag Elli Schlintl",
    "wof:placetype":"venue"
},
  "geometry": {"coordinates":[16.2823543549,48.1010856628],"type":"Point"}
}