{
  "type": "Feature",
  "properties": {
    "addr:full":"Steinebach 9  Dornbirn Vorarlberg 6850",
    "addr:housenumber":"9",
    "addr:postcode":"6850",
    "addr:street":"Steinebach",
    "iso:country":"AT",
    "sg:address":"Steinebach 9 ",
    "sg:city":"Dornbirn",
    "sg:classifiers":[
        {
            "category":"Professional",
            "subcategory":"Business Services",
            "type":"Services"
        }
    ],
    "sg:phone":"+43 4355 723990",
    "sg:postcode":"6850",
    "sg:province":"Vorarlberg",
    "sg:tags":[
        "advice"
    ],
    "wof:name":"F.M. H\u00c4MMERLE TEXTILWERKE GES.MBH",
    "wof:placetype":"venue"
},
  "geometry": {"coordinates":[9.7589826584,47.4050827026],"type":"Point"}
}