{
  "type": "Feature",
  "properties": {
    "iso:country":"AT",
    "sg:address":"Rathauspl 62",
    "sg:city":"Weitra",
    "sg:orig_category":"Apotheken",
    "sg:phone":"+43 4328 562350",
    "sg:postcode":"3970",
    "sg:province":"Nieder\u00f6sterreich",
    "wof:name":"Apotheke Zum schwarzen Adler Mag pharm F Armanios KG",
    "wof:placetype":"venue"
},
  "geometry": {"coordinates":[14.8933191299,48.7010574341],"type":"Point"}
}