{
  "type": "Feature",
  "properties": {
    "iso:country":"AT",
    "sg:address":"Siedlerstr 2",
    "sg:city":"Hainburg an der Donau",
    "sg:orig_category":"Transportunternehmen",
    "sg:phone":"+43 4321 6563378",
    "sg:postcode":"2410",
    "sg:province":"Nieder\u00f6sterreich",
    "wof:name":"Kratky Peter",
    "wof:placetype":"venue"
},
  "geometry": {"coordinates":[16.9454936981,48.138923645],"type":"Point"}
}