{
  "type": "Feature",
  "properties": {
    "addr:full":"Siedlerstr 2 Hainburg an der Donau Nieder\u00f6sterreich 2410",
    "addr:housenumber":"2",
    "addr:postcode":"2410",
    "addr:street":"Siedlerstr",
    "iso:country":"AT",
    "sg:address":"Siedlerstr 2",
    "sg:city":"Hainburg an der Donau",
    "sg:orig_category":"Transportunternehmen",
    "sg:phone":"+43 4321 6563378",
    "sg:postcode":"2410",
    "sg:province":"Nieder\u00f6sterreich",
    "wof:name":"Kratky Peter",
    "wof:placetype":"venue"
},
  "geometry": {"coordinates":[16.9454936981,48.138923645],"type":"Point"}
}