{
  "type": "Feature",
  "properties": {
    "addr:full":"Hauptstr 2 Kirchberg in Tirol Tirol 6365",
    "addr:housenumber":"2",
    "addr:postcode":"6365",
    "addr:street":"Hauptstr;Tirol",
    "iso:country":"AT",
    "sg:address":"Hauptstr 2",
    "sg:city":"Kirchberg in Tirol",
    "sg:classifiers":[
        {
            "category":"Restaurant",
            "type":"Food & Drink"
        }
    ],
    "sg:phone":"+43 5357 3612",
    "sg:postcode":"6365",
    "sg:province":"Tirol",
    "sg:tags":[
        "pizzeria"
    ],
    "wof:name":"Daxer Pizzeria-Gasthof",
    "wof:placetype":"venue"
},
  "geometry": {"coordinates":[12.3152656555,47.4475326538],"type":"Point"}
}