{
  "type": "Feature",
  "properties": {
    "addr:full":"Gudrunstr 184 Wien Wien 1100",
    "addr:housenumber":"184",
    "addr:postcode":"1100",
    "iso:country":"AT",
    "sg:address":"Gudrunstr 184",
    "sg:city":"Wien",
    "sg:orig_category":"Weiterbildungsinstitute M Allg U Berufl Bildungsangebot",
    "sg:phone":"+43 4316 078809",
    "sg:postcode":"1100",
    "sg:province":"Wien",
    "wof:name":"Bildungszentrum Gudrunstra\u00dfe",
    "wof:placetype":"venue"
},
  "geometry": {"coordinates":[16.3628425598,48.1790924072],"type":"Point"}
}