{
  "type": "Feature",
  "properties": {
    "addr:full":"Weinzierlbruck 24 Prambachkirchen Ober\u00f6sterreich 4731",
    "addr:housenumber":"24",
    "addr:postcode":"4731",
    "addr:street":"Weinzierlbruck",
    "iso:country":"AT",
    "sg:address":"Weinzierlbruck 24",
    "sg:city":"Prambachkirchen",
    "sg:classifiers":[
        {
            "category":"Banks & Credit Unions",
            "subcategory":"Investment Brokerage",
            "type":"Services"
        }
    ],
    "sg:phone":"+43 7277 2136",
    "sg:postcode":"4731",
    "sg:province":"Ober\u00f6sterreich",
    "sg:tags":[
        "stairway",
        "disabled",
        "lift",
        "elevator",
        "persons"
    ],
    "wof:name":"LEHNER LIFTTECHNIK Ges.m.b.H.",
    "wof:placetype":"venue"
},
  "geometry": {"coordinates":[13.8937654495,48.3191146851],"type":"Point"}
}