{
  "type": "Feature",
  "properties": {
    "addr:full":"Kapuzinerstr 40 Linz Ober\u00f6sterreich 4020",
    "addr:housenumber":"40",
    "addr:postcode":"4020",
    "addr:street":"Kapuzinerstr",
    "iso:country":"AT",
    "sg:address":"Kapuzinerstr 40",
    "sg:city":"Linz",
    "sg:orig_category":"Behinderungen / Leben Mit Behinderungen",
    "sg:phone":"+43 4373 27713660",
    "sg:postcode":"4020",
    "sg:province":"Ober\u00f6sterreich",
    "wof:name":"Institut f H\u00f6r- u Sehbildung - Caritas f Menschen m Behinderung",
    "wof:placetype":"venue"
},
  "geometry": {"coordinates":[14.2809686661,48.2992134094],"type":"Point"}
}