{
  "type": "Feature",
  "properties": {
    "addr:full":"Breitenau 109 Molln Ober\u00f6sterreich 4591",
    "addr:housenumber":"109",
    "addr:postcode":"4591",
    "addr:street":"Breitenau",
    "iso:country":"AT",
    "sg:address":"Breitenau 109",
    "sg:city":"Molln",
    "sg:orig_category":"Fische U Fischwaren / Erzeugung U Gro\u00c3\u0178handel",
    "sg:phone":"+43 4375 8430900",
    "sg:postcode":"4591",
    "sg:province":"Ober\u00f6sterreich",
    "wof:name":"Eisvogel Hubert Bernegger GmbH & Co KG",
    "wof:placetype":"venue"
},
  "geometry": {"coordinates":[14.3490400314,47.8487854004],"type":"Point"}
}