{
  "type": "Feature",
  "properties": {
    "addr:full":"Elisabethstr 57 Salzburg Salzburg 5020",
    "addr:housenumber":"57",
    "addr:postcode":"5020",
    "addr:street":"Elisabethstr;Salzburg",
    "iso:country":"AT",
    "sg:address":"Elisabethstr 57",
    "sg:city":"Salzburg",
    "sg:orig_category":"Textilreinigung",
    "sg:phone":"+43 662 452917",
    "sg:postcode":"5020",
    "sg:province":"Salzburg",
    "wof:name":"Textilpflege - Erich Lercher",
    "wof:placetype":"venue"
},
  "geometry": {"coordinates":[13.0441923141,47.8180046082],"type":"Point"}
}