{
  "type": "Feature",
  "properties": {
    "iso:country":"AT",
    "sg:address":"Trostg 4a",
    "sg:city":"Wiener Neustadt",
    "sg:orig_category":"Autohandel",
    "sg:phone":"+43 4326 22232400",
    "sg:postcode":"2700",
    "sg:province":"Nieder\u00f6sterreich",
    "wof:name":"Autohaus Kusebauch Sternecker GesmbH",
    "wof:placetype":"venue"
},
  "geometry": {"coordinates":[16.2330150604,47.8130531311],"type":"Point"}
}