{
  "type": "Feature",
  "properties": {
    "iso:country":"AT",
    "sg:address":"Konstanziag 36-40",
    "sg:city":"Wien",
    "sg:orig_category":"Lebensmittel / Einzelhandel",
    "sg:phone":"+43 1 2857101",
    "sg:postcode":"1220",
    "sg:province":"Wien",
    "wof:name":"Kaufmannsladen Stadlau",
    "wof:placetype":"venue"
},
  "geometry": {"coordinates":[16.4550361633,48.2245864868],"type":"Point"}
}