{
  "type": "Feature",
  "properties": {
    "addr:full":"Hauptstr 71 Mieming Tirol 6414",
    "addr:housenumber":"71",
    "addr:postcode":"6414",
    "addr:street":"Hauptstr;Tirol",
    "iso:country":"AT",
    "sg:address":"Hauptstr 71",
    "sg:city":"Mieming",
    "sg:orig_category":"Tankstellen",
    "sg:phone":"+43 5264 5364",
    "sg:postcode":"6414",
    "sg:province":"Tirol",
    "wof:name":"AVANTI TankstellenbetriebsgesmbH",
    "wof:placetype":"venue"
},
  "geometry": {"coordinates":[10.9781799316,47.3059082031],"type":"Point"}
}