{
  "type": "Feature",
  "properties": {
    "addr:full":"Sautergasse 62 Wien Wien 1170",
    "addr:housenumber":"62",
    "addr:postcode":"1170",
    "addr:street":"Sautergasse",
    "iso:country":"AT",
    "sg:address":"Sautergasse 62",
    "sg:city":"Wien",
    "sg:classifiers":[
        {
            "category":"Bars & Pubs",
            "subcategory":"Lounge",
            "type":"Food & Drink"
        }
    ],
    "sg:phone":"+43 699 19714735",
    "sg:postcode":"1170",
    "sg:province":"Wien",
    "sg:tags":[
        "shelf",
        "all-purpose"
    ],
    "sg:website":"metallregal.at",
    "wof:name":"HPS Handelsagentur Inh. Hanns-Peter Schreiber",
    "wof:placetype":"venue"
},
  "geometry": {"coordinates":[16.3152637482,48.2226638794],"type":"Point"}
}