{
  "type": "Feature",
  "properties": {
    "addr:full":"Hirnbachstr 5 Kirchbichl Tirol 6322",
    "addr:housenumber":"5",
    "addr:postcode":"6322",
    "addr:street":"Hirnbachstr;Tirol",
    "iso:country":"AT",
    "sg:address":"Hirnbachstr 5",
    "sg:city":"Kirchbichl",
    "sg:orig_category":"Futtermittel",
    "sg:phone":"+43 5332 816530",
    "sg:postcode":"6322",
    "sg:province":"Tirol",
    "wof:name":"Serotech-N\u00e4hrmittel HandelsgesmbH",
    "wof:placetype":"venue"
},
  "geometry": {"coordinates":[12.1196537018,47.5394287109],"type":"Point"}
}