{
  "type": "Feature",
  "properties": {
    "iso:country":"AT",
    "sg:address":"Fabrikstr 6",
    "sg:city":"Schwarzach",
    "sg:orig_category":"Maschinenbau",
    "sg:phone":"+43 5572 581770",
    "sg:postcode":"6858",
    "sg:province":"Vorarlberg",
    "wof:name":"MBM Maschinenbau GesmbH",
    "wof:placetype":"venue"
},
  "geometry": {"coordinates":[9.7614002228,47.4455604553],"type":"Point"}
}