{
  "type": "Feature",
  "properties": {
    "iso:country":"AT",
    "sg:address":"Krautbergstr 2a",
    "sg:city":"Amstetten",
    "sg:orig_category":"Friseure U Frisiersalons",
    "sg:phone":"+43 7472 62574",
    "sg:postcode":"3300",
    "sg:province":"Nieder\u00f6sterreich",
    "wof:name":"Le Figaro",
    "wof:placetype":"venue"
},
  "geometry": {"coordinates":[14.8601455688,48.123210907],"type":"Point"}
}