{
  "type": "Feature",
  "properties": {
    "addr:full":"Hans Gasser-Pl 8 Villach K\u00e4rnten 9500",
    "addr:housenumber":"8",
    "addr:postcode":"9500",
    "addr:street":"Gasser-Pl;Kaernten",
    "iso:country":"AT",
    "sg:address":"Hans Gasser-Pl 8",
    "sg:city":"Villach",
    "sg:orig_category":"Banken U Sparkassen",
    "sg:phone":"+43 4350 50594202",
    "sg:postcode":"9500",
    "sg:province":"K\u00e4rnten",
    "wof:name":"Bank Austria Creditanstalt AG - Regionaldirektion Privat- u Gesch\u00e4ftskunden",
    "wof:placetype":"venue"
},
  "geometry": {"coordinates":[13.8429841995,46.6125907898],"type":"Point"}
}