{
  "type": "Feature",
  "properties": {
    "iso:country":"AT",
    "sg:address":"Hauptpl 18",
    "sg:city":"Stegersbach",
    "sg:orig_category":"Landwirtschaftliche Produkte",
    "sg:phone":"+43 3326 54894",
    "sg:postcode":"7551",
    "sg:province":"Burgenland",
    "wof:name":"Bauernhof Stegersbach",
    "wof:placetype":"venue"
},
  "geometry": {"coordinates":[16.1666297913,47.1591377258],"type":"Point"}
}