{
  "type": "Feature",
  "properties": {
    "addr:full":"Salurner Str 4a Kufstein Tirol 6330",
    "addr:postcode":"6330",
    "addr:street":"Str 4A;Tirol",
    "iso:country":"AT",
    "sg:address":"Salurner Str 4a",
    "sg:city":"Kufstein",
    "sg:orig_category":"Autohandel",
    "sg:phone":"+43 5372 63702",
    "sg:postcode":"6330",
    "sg:province":"Tirol",
    "wof:name":"Fuchs Gebr\u00fcder Autohaus GesmbH",
    "wof:placetype":"venue"
},
  "geometry": {"coordinates":[12.1672296524,47.5791015625],"type":"Point"}
}