{
  "type": "Feature",
  "properties": {
    "addr:full":"Leopoldg 102 Maria Anzbach Nieder\u00f6sterreich 3034",
    "addr:housenumber":"102",
    "addr:postcode":"3034",
    "iso:country":"AT",
    "sg:address":"Leopoldg 102",
    "sg:city":"Maria Anzbach",
    "sg:orig_category":"Geschenkartikel",
    "sg:phone":"+43 4327 7256319",
    "sg:postcode":"3034",
    "sg:province":"Nieder\u00f6sterreich",
    "wof:name":"Extra Presents",
    "wof:placetype":"venue"
},
  "geometry": {"coordinates":[15.9219617844,48.191696167],"type":"Point"}
}