{
  "type": "Feature",
  "properties": {
    "iso:country":"AT",
    "sg:address":"Hauptstr 37",
    "sg:city":"Gurk",
    "sg:orig_category":"Feuerwehren",
    "sg:phone":"+43 4266 8478",
    "sg:postcode":"9342",
    "sg:province":"K\u00e4rnten",
    "wof:name":"Feuerwache Gurk - R\u00fcsthaus",
    "wof:placetype":"venue"
},
  "geometry": {"coordinates":[14.2866697311,46.8726768494],"type":"Point"}
}