{
  "type": "Feature",
  "properties": {
    "addr:full":"Untere Bahng 22 Purbach am Neusiedler See Burgenland 7083",
    "addr:housenumber":"22",
    "addr:postcode":"7083",
    "addr:street":"Untere Bahng",
    "iso:country":"AT",
    "sg:address":"Untere Bahng 22",
    "sg:city":"Purbach am Neusiedler See",
    "sg:orig_category":"Non-Classified Establishments",
    "sg:phone":"+43 4369 912676319",
    "sg:postcode":"7083",
    "sg:province":"Burgenland",
    "wof:name":"GREBIC Verkauf & Montage",
    "wof:placetype":"venue"
},
  "geometry": {"coordinates":[16.6971511841,47.909866333],"type":"Point"}
}