{
  "type": "Feature",
  "properties": {
    "addr:full":"Flughafen 5035",
    "addr:postcode":"5035",
    "iso:country":"AT",
    "sg:address":"Flughafen",
    "sg:orig_category":"Juweliere, Gold- U Silberschmiede",
    "sg:phone":"+43 4366 2852230",
    "sg:postcode":"5035",
    "wof:name":"Kemmetinger Christine",
    "wof:placetype":"venue"
},
  "geometry": {"coordinates":[13.0433702469,47.8006706238],"type":"Point"}
}