{
  "type": "Feature",
  "properties": {
    "iso:country":"AT",
    "sg:address":"Ullach 6",
    "sg:city":"Leogang",
    "sg:orig_category":"Pensionen / Privatzimmer",
    "sg:phone":"+43 6583 70850",
    "sg:postcode":"5771",
    "sg:province":"Salzburg",
    "wof:name":"Feriengut Stoffenhof",
    "wof:placetype":"venue"
},
  "geometry": {"coordinates":[12.7580242157,47.4512863159],"type":"Point"}
}