{
  "type": "Feature",
  "properties": {
    "iso:country":"AT",
    "sg:address":"Marktstr 19",
    "sg:city":"Taxenbach",
    "sg:orig_category":"Abschleppdienste",
    "sg:phone":"+43 6543 52260",
    "sg:postcode":"5660",
    "sg:province":"Salzburg",
    "wof:name":"Lehrsperger Albert",
    "wof:placetype":"venue"
},
  "geometry": {"coordinates":[12.9661598206,47.2931671143],"type":"Point"}
}