{
  "type": "Feature",
  "properties": {
    "addr:full":"Viktor-Adler-Pl 10 Wien Wien 1100",
    "addr:housenumber":"10",
    "addr:postcode":"1100",
    "addr:street":"Viktor-Adler-Pl",
    "iso:country":"AT",
    "sg:address":"Viktor-Adler-Pl 10",
    "sg:city":"Wien",
    "sg:orig_category":"Damenmoden",
    "sg:phone":"+43 1 6040779",
    "sg:postcode":"1100",
    "sg:province":"Wien",
    "wof:name":"Modepoint 21 Handel GmbH",
    "wof:placetype":"venue"
},
  "geometry": {"coordinates":[16.3765449524,48.1771659851],"type":"Point"}
}