{
  "type": "Feature",
  "properties": {
    "addr:full":"Scharitzerstr 23 Linz Ober\u00f6sterreich 4020",
    "addr:housenumber":"23",
    "addr:postcode":"4020",
    "addr:street":"Scharitzerstr",
    "iso:country":"AT",
    "sg:address":"Scharitzerstr 23",
    "sg:city":"Linz",
    "sg:orig_category":"Telekommunikation",
    "sg:phone":"+43 732 663538",
    "sg:postcode":"4020",
    "sg:province":"Ober\u00f6sterreich",
    "wof:name":"Nil-Phonecenter Othm KEG",
    "wof:placetype":"venue"
},
  "geometry": {"coordinates":[14.2965192795,48.2966842651],"type":"Point"}
}