{
  "type": "Feature",
  "properties": {
    "iso:country":"AT",
    "sg:address":"Breitenfurterstrasse 394",
    "sg:city":"Wien",
    "sg:orig_category":"Project Management For Software Development",
    "sg:phone":"+43 1 88903890",
    "sg:postcode":"1230",
    "sg:province":"Wien",
    "sg:website":"pms-projektmanagement.at",
    "wof:name":"PMS Software Beratungs- u. Vertriebsges.m.b.H.",
    "wof:placetype":"venue"
},
  "geometry": {"coordinates":[16.269701004,48.1393470764],"type":"Point"}
}