{
  "type": "Feature",
  "properties": {
    "iso:country":"AT",
    "sg:address":"Ungenacher Str 15",
    "sg:city":"Timelkam",
    "sg:orig_category":"Solaranlagen",
    "sg:phone":"+43 4376 7295589",
    "sg:postcode":"4850",
    "sg:province":"Ober\u00f6sterreich",
    "wof:name":"H\u00f6fl Alois",
    "wof:placetype":"venue"
},
  "geometry": {"coordinates":[13.6073532104,48.0041694641],"type":"Point"}
}