{
  "type": "Feature",
  "properties": {
    "addr:full":"M\u00fchlefeldstr 43 Lustenau Vorarlberg 6890",
    "addr:housenumber":"43",
    "addr:postcode":"6890",
    "addr:street":"Muehlefeldstr",
    "iso:country":"AT",
    "sg:address":"M\u00fchlefeldstr 43",
    "sg:city":"Lustenau",
    "sg:orig_category":"Blumengro\u00c3\u0178handel",
    "sg:phone":"+43 5577 84990",
    "sg:postcode":"6890",
    "sg:province":"Vorarlberg",
    "wof:name":"REWEFA Blumen Gro\u00dfhandel Nfg KG",
    "wof:placetype":"venue"
},
  "geometry": {"coordinates":[9.6590452194,47.4262237549],"type":"Point"}
}