{
  "type": "Feature",
  "properties": {
    "addr:full":"Rohrmoos 208 Rohrmoos-Untertal Steiermark 8971",
    "addr:housenumber":"208",
    "addr:postcode":"rohrmoos-untertal;8971",
    "addr:street":"Rohrmoos",
    "iso:country":"AT",
    "sg:address":"Rohrmoos 208",
    "sg:city":"Rohrmoos-Untertal",
    "sg:classifiers":[
        {
            "category":"Restaurant",
            "type":"Food & Drink"
        }
    ],
    "sg:phone":"+43 3687 616720",
    "sg:postcode":"8971",
    "sg:province":"Steiermark",
    "sg:website":"tauernalm.com",
    "wof:name":"Restaurant Tauernalm",
    "wof:placetype":"venue"
},
  "geometry": {"coordinates":[13.632891655,47.3760528564],"type":"Point"}
}