{
  "type": "Feature",
  "properties": {
    "addr:full":"Pfarrg 13 Enns Ober\u00f6sterreich 4470",
    "addr:housenumber":"13",
    "addr:postcode":"4470",
    "addr:street":"Pfarrg",
    "iso:country":"AT",
    "sg:address":"Pfarrg 13",
    "sg:city":"Enns",
    "sg:classifiers":[
        {
            "category":"Landmark",
            "subcategory":"Square",
            "type":"Public Place"
        }
    ],
    "sg:phone":"+43 4372 2382609",
    "sg:postcode":"4470",
    "sg:province":"Ober\u00f6sterreich",
    "sg:tags":[
        "geometer"
    ],
    "wof:name":"Ferge Alfred Dipl-Ing",
    "wof:placetype":"venue"
},
  "geometry": {"coordinates":[14.4772968292,48.212852478],"type":"Point"}
}