{
  "type": "Feature",
  "properties": {
    "addr:full":"Karlauer Str 33 Graz Steiermark 8020",
    "addr:housenumber":"33",
    "addr:postcode":"8020",
    "addr:street":"Str",
    "iso:country":"AT",
    "sg:address":"Karlauer Str 33",
    "sg:city":"Graz",
    "sg:orig_category":"Dachdeckereien",
    "sg:phone":"+43 316 714432",
    "sg:postcode":"8020",
    "sg:province":"Steiermark",
    "wof:name":"Koch Anton GesmbH",
    "wof:placetype":"venue"
},
  "geometry": {"coordinates":[15.4309949875,47.0618515015],"type":"Point"}
}