{
  "type": "Feature",
  "properties": {
    "addr:full":"Schulg 4 Mutters Tirol 6162",
    "addr:housenumber":"4",
    "addr:postcode":"6162",
    "addr:street":"Schulg;Tirol",
    "iso:country":"AT",
    "sg:address":"Schulg 4",
    "sg:city":"Mutters",
    "sg:orig_category":"Gemeinden",
    "sg:phone":"+43 512 5484000",
    "sg:postcode":"6162",
    "sg:province":"Tirol",
    "wof:name":"Gemeindeamt Mutters",
    "wof:placetype":"venue"
},
  "geometry": {"coordinates":[11.3760061264,47.2271842957],"type":"Point"}
}