{
  "type": "Feature",
  "properties": {
    "addr:full":"Seidengasse 33-35 Wien Wien 1070",
    "addr:postcode":"33-35;1070",
    "addr:street":"Seidengasse",
    "iso:country":"AT",
    "sg:address":"Seidengasse 33-35",
    "sg:city":"Wien",
    "sg:classifiers":[
        {
            "category":"Health Services",
            "subcategory":"Nursing And Care Facility",
            "type":"Services"
        }
    ],
    "sg:phone":"+43 1 521150",
    "sg:postcode":"1070",
    "sg:province":"Wien",
    "sg:tags":[
        "circulatory",
        "cardiac",
        "complaint",
        "remedy",
        "stimulant"
    ],
    "sg:website":"pfizer.com",
    "wof:name":"Pfizer Corporation Austria Ges.m.b.H.",
    "wof:placetype":"venue"
},
  "geometry": {"coordinates":[16.3416538239,48.2001495361],"type":"Point"}
}