{
  "type": "Feature",
  "properties": {
    "addr:full":"Alfred Wegener-G 10-12 Wien Wien 1190",
    "addr:postcode":"10-12;1190",
    "iso:country":"AT",
    "sg:address":"Alfred Wegener-G 10-12",
    "sg:city":"Wien",
    "sg:orig_category":"Volksschulen",
    "sg:phone":"+43 1 32021070",
    "sg:postcode":"1190",
    "sg:province":"Wien",
    "wof:name":"Neulandschulen",
    "wof:placetype":"venue"
},
  "geometry": {"coordinates":[16.3389968872,48.2513542175],"type":"Point"}
}