{
  "type": "Feature",
  "properties": {
    "iso:country":"AT",
    "sg:address":"Bundesstr 2",
    "sg:city":"Wals",
    "sg:orig_category":"Restaurants: Griechisch",
    "sg:phone":"+43 662 852178",
    "sg:postcode":"5071",
    "sg:province":"Salzburg",
    "wof:name":"Restaurant Athen",
    "wof:placetype":"venue"
},
  "geometry": {"coordinates":[12.9906549454,47.7918701172],"type":"Point"}
}