{
  "type": "Feature",
  "properties": {
    "addr:full":"Feldkirchner Str 175 Puntigam Steiermark 8055",
    "addr:housenumber":"175",
    "addr:postcode":"8055",
    "addr:street":"Str",
    "iso:country":"AT",
    "sg:address":"Feldkirchner Str 175",
    "sg:city":"Puntigam",
    "sg:orig_category":"Personalbereitstellung",
    "sg:phone":"+43 316 242604",
    "sg:postcode":"8055",
    "sg:province":"Steiermark",
    "sg:website":"www.aldrian-personal.at",
    "wof:name":"Aldrian Personal GesmbH",
    "wof:placetype":"venue"
},
  "geometry": {"coordinates":[15.4303798676,47.0127792358],"type":"Point"}
}