{
  "type": "Feature",
  "properties": {
    "iso:country":"AT",
    "sg:address":"Krankenhausg 19/18",
    "sg:city":"Kufstein",
    "sg:orig_category":"Werbeagenturen",
    "sg:phone":"+43 5372 65963",
    "sg:postcode":"6330",
    "sg:province":"Tirol",
    "wof:name":"SKYWALK Design und Kommunikation Werner Neulinger",
    "wof:placetype":"venue"
},
  "geometry": {"coordinates":[12.1743993759,47.5829925537],"type":"Point"}
}