{
  "type": "Feature",
  "properties": {
    "addr:full":"Hauptstr 42 Wartberg an der Krems Ober\u00f6sterreich 4552",
    "addr:housenumber":"42",
    "addr:postcode":"4552",
    "addr:street":"Hauptstr",
    "iso:country":"AT",
    "sg:address":"Hauptstr 42",
    "sg:city":"Wartberg an der Krems",
    "sg:orig_category":"Fenster",
    "sg:phone":"+43 4375 8772110",
    "sg:postcode":"4552",
    "sg:province":"Ober\u00f6sterreich",
    "wof:name":"Fensterbau P\u00fcrstinger GesmbH",
    "wof:placetype":"venue"
},
  "geometry": {"coordinates":[14.1261196136,47.9890403748],"type":"Point"}
}