{
  "type": "Feature",
  "properties": {
    "addr:full":"Nr 31 Fornach Ober\u00f6sterreich 4892",
    "addr:postcode":"4892",
    "addr:street":"Nr;Oberoesterreich",
    "iso:country":"AT",
    "sg:address":"Nr 31",
    "sg:city":"Fornach",
    "sg:orig_category":"Banken U Sparkassen",
    "sg:phone":"+43 76825004",
    "sg:postcode":"4892",
    "sg:province":"Ober\u00f6sterreich",
    "wof:name":"Raiffeisenbank P\u00f6ndorf-Frankenmarkt regGenmbH",
    "wof:placetype":"venue"
},
  "geometry": {"coordinates":[13.4300832748,48.0231781006],"type":"Point"}
}