{
  "type": "Feature",
  "properties": {
    "addr:full":"Schillerstr 15 Graz Steiermark 8010",
    "addr:housenumber":"15",
    "addr:postcode":"8010",
    "addr:street":"Schillerstr",
    "iso:country":"AT",
    "sg:address":"Schillerstr 15",
    "sg:city":"Graz",
    "sg:orig_category":"Architekten",
    "sg:phone":"+43 4331 63279630",
    "sg:postcode":"8010",
    "sg:province":"Steiermark",
    "wof:name":"Hoffmann & Partner Arch Dipl-Ing",
    "wof:placetype":"venue"
},
  "geometry": {"coordinates":[15.4529447556,47.0714073181],"type":"Point"}
}