{
  "type": "Feature",
  "properties": {
    "addr:full":"Sch\u00f6nbrunner Str 263 Wien Wien 1120",
    "addr:housenumber":"263",
    "addr:postcode":"1120",
    "addr:street":"Str",
    "iso:country":"AT",
    "sg:address":"Sch\u00f6nbrunner Str 263",
    "sg:city":"Wien",
    "sg:orig_category":"Banken U Sparkassen",
    "sg:phone":"+43 5 050531580",
    "sg:postcode":"1120",
    "sg:province":"Wien",
    "wof:name":"Bank Austria Creditanstalt AG",
    "wof:placetype":"venue"
},
  "geometry": {"coordinates":[16.3290939331,48.1824874878],"type":"Point"}
}