{
  "type": "Feature",
  "properties": {
    "addr:full":"Freibach 41 Ferlach K\u00e4rnten 9170",
    "addr:housenumber":"41",
    "addr:postcode":"9170",
    "addr:street":"Freibach;Kaernten",
    "iso:country":"AT",
    "sg:address":"Freibach 41",
    "sg:city":"Ferlach",
    "sg:orig_category":"Lebensmittel / Einzelhandel",
    "sg:phone":"+43 4227 7170",
    "sg:postcode":"9170",
    "sg:province":"K\u00e4rnten",
    "wof:name":"Spar-Markt Inh Walter Rakuschek",
    "wof:placetype":"venue"
},
  "geometry": {"coordinates":[14.2995548248,46.5264358521],"type":"Point"}
}