{
  "type": "Feature",
  "properties": {
    "iso:country":"AT",
    "sg:address":"Babenbergerstr 26",
    "sg:city":"Lilienfeld",
    "sg:orig_category":"Friseure U Frisiersalons",
    "sg:phone":"+43 2762 52344",
    "sg:postcode":"3180",
    "sg:province":"Nieder\u00f6sterreich",
    "wof:name":"Sch\u00e4dl Karin",
    "wof:placetype":"venue"
},
  "geometry": {"coordinates":[15.5969419479,48.0169334412],"type":"Point"}
}