{
  "type": "Feature",
  "properties": {
    "iso:country":"AT",
    "sg:address":"Pettenbacher Str 1",
    "sg:city":"Vorchdorf",
    "sg:orig_category":"Cd, Dvd,Musikkassetten U Schallplatten",
    "sg:phone":"+43 76146267",
    "sg:postcode":"4655",
    "sg:province":"Ober\u00f6sterreich",
    "wof:name":"Adrigan Franz",
    "wof:placetype":"venue"
},
  "geometry": {"coordinates":[13.9236984253,48.0031471252],"type":"Point"}
}