{
  "type": "Feature",
  "properties": {
    "addr:full":"Bahnhofstr 70 Greifenburg K\u00e4rnten 9761",
    "addr:housenumber":"70",
    "addr:postcode":"9761",
    "addr:street":"Bahnhofstr;Kaernten",
    "iso:country":"AT",
    "sg:address":"Bahnhofstr 70",
    "sg:city":"Greifenburg",
    "sg:classifiers":[
        {
            "category":"Taxi",
            "type":"Transportation"
        }
    ],
    "sg:phone":"+43 4712 339",
    "sg:postcode":"9761",
    "sg:province":"K\u00e4rnten",
    "sg:tags":[
        "personentransporte",
        "u"
    ],
    "wof:name":"Baumgartner Johann",
    "wof:placetype":"venue"
},
  "geometry": {"coordinates":[13.1846418381,46.7443618774],"type":"Point"}
}