{
  "type": "Feature",
  "properties": {
    "addr:full":"Langenlebarner Str 92 Tulln an der Donau Nieder\u00f6sterreich 3430",
    "addr:postcode":"3430",
    "addr:street":"Str 92",
    "iso:country":"AT",
    "sg:address":"Langenlebarner Str 92",
    "sg:city":"Tulln an der Donau",
    "sg:orig_category":"Pensionen / Privatzimmer",
    "sg:phone":"+43 2272 65077",
    "sg:postcode":"3430",
    "sg:province":"Nieder\u00f6sterreich",
    "wof:name":"Pension Renate",
    "wof:placetype":"venue"
},
  "geometry": {"coordinates":[16.0751399994,48.3290328979],"type":"Point"}
}