{
  "type": "Feature",
  "properties": {
    "addr:full":"Nr 175 Gro\u00dfmeiseldorf Nieder\u00f6sterreich 3711",
    "addr:postcode":"3711",
    "addr:street":"Nr 175 Grossmeiseldorf",
    "iso:country":"AT",
    "sg:address":"Nr 175",
    "sg:city":"Gro\u00dfmeiseldorf",
    "sg:orig_category":"Nachtclubs-Bars",
    "sg:phone":"+43 2956 81030",
    "sg:postcode":"3711",
    "sg:province":"Nieder\u00f6sterreich",
    "wof:name":"Beninger & Plessl GesmbH",
    "wof:placetype":"venue"
},
  "geometry": {"coordinates":[15.8752231598,48.5312347412],"type":"Point"}
}