{
  "type": "Feature",
  "properties": {
    "addr:full":"Roseng 1 Pamhagen Burgenland 7152",
    "addr:housenumber":"1",
    "addr:postcode":"7152",
    "addr:street":"Roseng",
    "iso:country":"AT",
    "sg:address":"Roseng 1",
    "sg:city":"Pamhagen",
    "sg:orig_category":"Fleischhauereien",
    "sg:phone":"+43 2174 21260",
    "sg:postcode":"7152",
    "sg:province":"Burgenland",
    "wof:name":"Karlo Martin",
    "wof:placetype":"venue"
},
  "geometry": {"coordinates":[16.9086685181,47.7017440796],"type":"Point"}
}