{
  "type": "Feature",
  "properties": {
    "addr:full":"Parkstrasse 12 Saalfelden am Steinernen Meer Salzburg 5760",
    "addr:housenumber":"12",
    "addr:postcode":"5760",
    "addr:street":"Parkstrasse;Salzburg",
    "iso:country":"AT",
    "sg:address":"Parkstrasse 12",
    "sg:city":"Saalfelden am Steinernen Meer",
    "sg:classifiers":[
        {
            "category":"Professional",
            "subcategory":"Art Services",
            "type":"Services"
        }
    ],
    "sg:phone":"+43 6582 74056",
    "sg:postcode":"5760",
    "sg:province":"Salzburg",
    "sg:tags":[
        "glass",
        "article"
    ],
    "sg:website":"creativ-glas.at",
    "wof:name":"Herbert Katstaller",
    "wof:placetype":"venue"
},
  "geometry": {"coordinates":[12.8440666199,47.4282035828],"type":"Point"}
}