{
  "type": "Feature",
  "properties": {
    "addr:full":"Kochg 28 Wien Wien 1080",
    "addr:housenumber":"28",
    "addr:postcode":"1080",
    "addr:street":"Kochg",
    "iso:country":"AT",
    "sg:address":"Kochg 28",
    "sg:city":"Wien",
    "sg:orig_category":"Rauchfangkehrer",
    "sg:phone":"+43 1 3190025",
    "sg:postcode":"1080",
    "sg:province":"Wien",
    "wof:name":"Tomicich Rudolf jun",
    "wof:placetype":"venue"
},
  "geometry": {"coordinates":[16.3496456146,48.2139396667],"type":"Point"}
}