{
  "type": "Feature",
  "properties": {
    "iso:country":"AT",
    "sg:address":"Sch\u00fcrerpl 6",
    "sg:city":"Krems an der Donau",
    "sg:classifiers":[
        {
            "category":"Travel",
            "subcategory":"Hotels & Motels",
            "type":"Entertainment"
        }
    ],
    "sg:phone":"+43 2732 83001",
    "sg:postcode":"3500",
    "sg:province":"Nieder\u00f6sterreich",
    "wof:name":"Hotel Zur goldenen Sonne",
    "wof:placetype":"venue"
},
  "geometry": {"coordinates":[15.5816602707,48.4014434814],"type":"Point"}
}