{
  "type": "Feature",
  "properties": {
    "addr:full":"Nr 27 Markt Allhau Burgenland 7411",
    "addr:postcode":"7411",
    "addr:street":"Nr",
    "iso:country":"AT",
    "sg:address":"Nr 27",
    "sg:city":"Markt Allhau",
    "sg:orig_category":"Feuerwehren",
    "sg:phone":"+43 3359 2222",
    "sg:postcode":"7411",
    "sg:province":"Burgenland",
    "wof:name":"Freiwillige Feuerwehr Loipersdorf",
    "wof:placetype":"venue"
},
  "geometry": {"coordinates":[16.0806007385,47.2934417725],"type":"Point"}
}