{
  "type": "Feature",
  "properties": {
    "iso:country":"AT",
    "sg:address":"EKZ Eurospar Riedauer Str 37",
    "sg:city":"Ried im Innkreis",
    "sg:orig_category":"Freizeit- U Sportbekleidung",
    "sg:phone":"+43 4377 52819940",
    "sg:postcode":"4910",
    "sg:province":"Ober\u00f6sterreich",
    "wof:name":"HERVIS Sport- u ModegesmbH",
    "wof:placetype":"venue"
},
  "geometry": {"coordinates":[13.4900550842,48.2098655701],"type":"Point"}
}