{
  "type": "Feature",
  "properties": {
    "addr:full":"Herrenstr 22 Perg Ober\u00f6sterreich 4320",
    "addr:housenumber":"22",
    "addr:postcode":"4320",
    "addr:street":"Herrenstr",
    "iso:country":"AT",
    "sg:address":"Herrenstr 22",
    "sg:city":"Perg",
    "sg:orig_category":"Politische Parteien",
    "sg:phone":"+43 7262 57104",
    "sg:postcode":"4320",
    "sg:province":"Ober\u00f6sterreich",
    "wof:name":"Freiheitliche Partei \u00f6sterreichs (FP\u00f6)",
    "wof:placetype":"venue"
},
  "geometry": {"coordinates":[14.635925293,48.2493438721],"type":"Point"}
}