{
  "type": "Feature",
  "properties": {
    "addr:full":"Gepringweg 10 Stra\u00dfgang Steiermark 8054",
    "addr:housenumber":"10",
    "addr:postcode":"8054",
    "addr:street":"Gepringweg",
    "iso:country":"AT",
    "sg:address":"Gepringweg 10",
    "sg:city":"Stra\u00dfgang",
    "sg:orig_category":"Baumeister",
    "sg:phone":"+43 316 287928",
    "sg:postcode":"8054",
    "sg:province":"Steiermark",
    "wof:name":"Pobitzer Rudolf Dipl-Ing",
    "wof:placetype":"venue"
},
  "geometry": {"coordinates":[15.3792915344,46.9934005737],"type":"Point"}
}