{
  "type": "Feature",
  "properties": {
    "addr:full":"Pfarrweg 2 Elixhausen Salzburg 5161",
    "addr:housenumber":"2",
    "addr:postcode":"5161",
    "addr:street":"Pfarrweg;Salzburg",
    "iso:country":"AT",
    "sg:address":"Pfarrweg 2",
    "sg:city":"Elixhausen",
    "sg:orig_category":"Baumeister",
    "sg:phone":"+43 662 4805030",
    "sg:postcode":"5161",
    "sg:province":"Salzburg",
    "wof:name":"Brandst\u00e4tter Hermann",
    "wof:placetype":"venue"
},
  "geometry": {"coordinates":[13.0671920776,47.8674087524],"type":"Point"}
}