{
  "type": "Feature",
  "properties": {
    "addr:full":"Nr 103 Pinkafeld Burgenland 7423",
    "addr:postcode":"7423",
    "addr:street":"Nr",
    "iso:country":"AT",
    "sg:address":"Nr 103",
    "sg:city":"Pinkafeld",
    "sg:orig_category":"Tischlereien",
    "sg:phone":"+43 3359 2344",
    "sg:postcode":"7423",
    "sg:province":"Burgenland",
    "wof:name":"Faustmann Erwin",
    "wof:placetype":"venue"
},
  "geometry": {"coordinates":[16.124250412,47.3718299866],"type":"Point"}
}