{
  "type": "Feature",
  "properties": {
    "iso:country":"AT",
    "sg:address":"Hackinger Kai 11",
    "sg:city":"Wien",
    "sg:orig_category":"Fliesen U Platten",
    "sg:phone":"+43 1 8796435",
    "sg:postcode":"1130",
    "sg:province":"Wien",
    "wof:name":"Lukowski KEG",
    "wof:placetype":"venue"
},
  "geometry": {"coordinates":[16.2623252869,48.1952323914],"type":"Point"}
}