{
  "type": "Feature",
  "properties": {
    "addr:full":"Herreng 7 Rechnitz Burgenland 7471",
    "addr:housenumber":"7",
    "addr:postcode":"7471",
    "addr:street":"Herreng",
    "iso:country":"AT",
    "sg:address":"Herreng 7",
    "sg:city":"Rechnitz",
    "sg:orig_category":"Bankomat-Standorte",
    "sg:phone":"+43 3363 79289",
    "sg:postcode":"7471",
    "sg:province":"Burgenland",
    "wof:name":"Bankomat d Burgenl\u00e4ndische Anlage & Kredit Bank AG",
    "wof:placetype":"venue"
},
  "geometry": {"coordinates":[16.439573288,47.3043479919],"type":"Point"}
}