{
  "type": "Feature",
  "properties": {
    "addr:full":"Hammerschmidtweg 2 Hallwang Salzburg 5300",
    "addr:housenumber":"2",
    "addr:postcode":"5300",
    "addr:street":"Hammerschmidtweg;Salzburg",
    "iso:country":"AT",
    "sg:address":"Hammerschmidtweg 2",
    "sg:city":"Hallwang",
    "sg:orig_category":"Autohandel",
    "sg:phone":"+43 662 661959",
    "sg:postcode":"5300",
    "sg:province":"Salzburg",
    "wof:name":"AK Wohnmobil und Kfz Handel K J Kruft",
    "wof:placetype":"venue"
},
  "geometry": {"coordinates":[13.0870800018,47.8418884277],"type":"Point"}
}