{
  "type": "Feature",
  "properties": {
    "iso:country":"AT",
    "sg:address":"Harter Str 5",
    "sg:city":"Neuhart",
    "sg:orig_category":"Autoreparatur",
    "sg:phone":"+43 316 272339",
    "sg:postcode":"8053",
    "sg:province":"Steiermark",
    "wof:name":"Karner Ernst und Josef K\u00f6ck",
    "wof:placetype":"venue"
},
  "geometry": {"coordinates":[15.3952732086,47.0450782776],"type":"Point"}
}