{
  "type": "Feature",
  "properties": {
    "iso:country":"AT",
    "sg:address":"Eulenstrasse 14",
    "sg:city":"Neuzeug",
    "sg:orig_category":"Software For Contracting",
    "sg:phone":"+43 7259 56350",
    "sg:postcode":"4523",
    "sg:province":"Ober\u00f6sterreich",
    "sg:website":"contractmanager.at",
    "wof:name":"R&B Consulting GmbH",
    "wof:placetype":"venue"
},
  "geometry": {"coordinates":[14.3221750259,48.0261383057],"type":"Point"}
}