{
  "type": "Feature",
  "properties": {
    "addr:full":"Neubaustr.34 Ansfelden Ober\u00f6sterreich 4052",
    "addr:postcode":"4052",
    "addr:street":"Neubaustr.34",
    "iso:country":"AT",
    "sg:address":"Neubaustr.34",
    "sg:city":"Ansfelden",
    "sg:orig_category":"Freizeit, Partnerschaft",
    "sg:postcode":"4052",
    "sg:province":"Ober\u00f6sterreich",
    "sg:website":"http://www.ukrainegirls.at",
    "wof:name":"ukrainegirls",
    "wof:placetype":"venue"
},
  "geometry": {"coordinates":[14.3021240234,48.2256774902],"type":"Point"}
}