{
  "type": "Feature",
  "properties": {
    "addr:full":"Welser Str 34 Leonding Ober\u00f6sterreich 4060",
    "addr:postcode":"4060",
    "addr:street":"Str 34",
    "iso:country":"AT",
    "sg:address":"Welser Str 34",
    "sg:city":"Leonding",
    "sg:orig_category":"Maler, Anstreicher U Lackierer",
    "sg:phone":"+43 732 6831800",
    "sg:postcode":"4060",
    "sg:province":"Ober\u00f6sterreich",
    "wof:name":"Hirsch Otto GesmbH",
    "wof:placetype":"venue"
},
  "geometry": {"coordinates":[14.2644672394,48.2677574158],"type":"Point"}
}