{
  "type": "Feature",
  "properties": {
    "addr:full":"Krichbaumg 31 Wien Wien 1120",
    "addr:housenumber":"31",
    "addr:postcode":"1120",
    "addr:street":"Krichbaumg",
    "iso:country":"AT",
    "sg:address":"Krichbaumg 31",
    "sg:city":"Wien",
    "sg:orig_category":"Werbeagenturen",
    "sg:phone":"+43 1 8120303",
    "sg:postcode":"1120",
    "sg:province":"Wien",
    "wof:name":"Opus Marketing Erik R Kastner KG",
    "wof:placetype":"venue"
},
  "geometry": {"coordinates":[16.3307971954,48.1786651611],"type":"Point"}
}