{
  "type": "Feature",
  "properties": {
    "iso:country":"AT",
    "sg:address":"Kalvarienbergg 54",
    "sg:city":"Wien",
    "sg:orig_category":"Fleischhauereien",
    "sg:phone":"+43 1 4081146",
    "sg:postcode":"1170",
    "sg:province":"Wien",
    "wof:name":"Zederbauer Karl",
    "wof:placetype":"venue"
},
  "geometry": {"coordinates":[16.3336296082,48.2207145691],"type":"Point"}
}