{
  "type": "Feature",
  "properties": {
    "addr:full":"Theodor-Storm-Weg 7 Wien Wien 1160",
    "addr:housenumber":"7",
    "addr:postcode":"1160",
    "addr:street":"Theodor-Storm-Weg",
    "iso:country":"AT",
    "sg:address":"Theodor-Storm-Weg 7",
    "sg:city":"Wien",
    "sg:orig_category":"Werbegrafik- U Grafik-Design",
    "sg:phone":"+43 4314 165141",
    "sg:postcode":"1160",
    "sg:province":"Wien",
    "wof:name":"Kreativ Atelier Iko-Art",
    "wof:placetype":"venue"
},
  "geometry": {"coordinates":[16.2909889221,48.2148246765],"type":"Point"}
}