{
  "type": "Feature",
  "properties": {
    "addr:full":"Wagendorf 138 St. Veit am Vogau Steiermark 8423",
    "addr:housenumber":"138",
    "addr:postcode":"8423",
    "addr:street":"Wagendorf",
    "iso:country":"AT",
    "sg:address":"Wagendorf 138",
    "sg:city":"St. Veit am Vogau",
    "sg:orig_category":"Bildhauer",
    "sg:phone":"+43 3453 4271",
    "sg:postcode":"8423",
    "sg:province":"Steiermark",
    "wof:name":"Gert Richard",
    "wof:placetype":"venue"
},
  "geometry": {"coordinates":[15.6051454544,46.7559776306],"type":"Point"}
}