{
  "type": "Feature",
  "properties": {
    "addr:full":"Hauptplatz 22 Retz Nieder\u00f6sterreich 2070",
    "addr:housenumber":"22",
    "addr:postcode":"2070",
    "addr:street":"Hauptplatz",
    "iso:country":"AT",
    "sg:address":"Hauptplatz 22",
    "sg:city":"Retz",
    "sg:classifiers":[
        {
            "category":"Food & Beverages",
            "subcategory":"Chocolate",
            "type":"Retail Goods"
        }
    ],
    "sg:phone":"+43 2942 22530",
    "sg:postcode":"2070",
    "sg:province":"Nieder\u00f6sterreich",
    "sg:tags":[
        "crumb",
        "bread"
    ],
    "sg:website":"baeckerei-blei.at",
    "wof:name":"Cyrill Blei Ges.m.b.H.",
    "wof:placetype":"venue"
},
  "geometry": {"coordinates":[15.950340271,48.7568092346],"type":"Point"}
}