{
  "type": "Feature",
  "properties": {
    "addr:full":"Hauptstr 24 Oberndorf an der Melk Nieder\u00f6sterreich 3281",
    "addr:housenumber":"24",
    "addr:postcode":"3281",
    "addr:street":"Hauptstr;Niederoesterreich",
    "iso:country":"AT",
    "sg:address":"Hauptstr 24",
    "sg:city":"Oberndorf an der Melk",
    "sg:orig_category":"Fleischhauereien",
    "sg:phone":"+43 4374 837590",
    "sg:postcode":"3281",
    "sg:province":"Nieder\u00f6sterreich",
    "wof:name":"Buchmayer Matthias",
    "wof:placetype":"venue"
},
  "geometry": {"coordinates":[15.2193222046,48.0651893616],"type":"Point"}
}