{
  "type": "Feature",
  "properties": {
    "iso:country":"AT",
    "sg:address":"Grindelstr 17A",
    "sg:city":"Lustenau",
    "sg:orig_category":"Apotheken",
    "sg:phone":"+43 5577 880800",
    "sg:postcode":"6890",
    "sg:province":"Vorarlberg",
    "wof:name":"Engel-Apotheke",
    "wof:placetype":"venue"
},
  "geometry": {"coordinates":[9.659661293,47.4188194275],"type":"Point"}
}