{
  "type": "Feature",
  "properties": {
    "addr:full":"Gumpendorfer Str 20 Wien Wien 1060",
    "addr:postcode":"1060",
    "addr:street":"Str 20",
    "iso:country":"AT",
    "sg:address":"Gumpendorfer Str 20",
    "sg:city":"Wien",
    "sg:orig_category":"Altwaren",
    "sg:phone":"+43 1 5868564",
    "sg:postcode":"1060",
    "sg:province":"Wien",
    "wof:name":"Heinzl Helmut",
    "wof:placetype":"venue"
},
  "geometry": {"coordinates":[16.3600387573,48.1996688843],"type":"Point"}
}