{
  "type": "Feature",
  "properties": {
    "iso:country":"AT",
    "sg:address":"Goldg 13",
    "sg:city":"Salzburg",
    "sg:orig_category":"Restaurants: Chinesisch",
    "sg:phone":"+43 662 841779",
    "sg:postcode":"5020",
    "sg:province":"Salzburg",
    "wof:name":"China-Restaurant An Bing",
    "wof:placetype":"venue"
},
  "geometry": {"coordinates":[13.0433769226,47.8006744385],"type":"Point"}
}