{
  "type": "Feature",
  "properties": {
    "addr:full":"Franz-Josef-Str. 15 Salzburg Salzburg 5020",
    "addr:housenumber":"15",
    "addr:postcode":"5020",
    "addr:street":"Franz-Josef-Str.;Salzburg",
    "iso:country":"AT",
    "sg:address":"Franz-Josef-Str. 15",
    "sg:city":"Salzburg",
    "sg:classifiers":[
        {
            "category":"Professional",
            "subcategory":"Advertising",
            "type":"Services"
        }
    ],
    "sg:phone":"+43 4366 29309090",
    "sg:postcode":"5020",
    "sg:province":"Salzburg",
    "sg:tags":[
        "communication",
        "medium"
    ],
    "wof:name":"CLIENTLOGIC HANDELSGES.MBH",
    "wof:placetype":"venue"
},
  "geometry": {"coordinates":[13.0451221466,47.8073883057],"type":"Point"}
}