{
  "type": "Feature",
  "properties": {
    "iso:country":"AT",
    "sg:address":"Marktstr 59",
    "sg:city":"Dornbirn",
    "sg:orig_category":"Unternehmensberatung",
    "sg:phone":"+43 5572 386581",
    "sg:postcode":"6850",
    "sg:province":"Vorarlberg",
    "wof:name":"Futura Consulting GmbH",
    "wof:placetype":"venue"
},
  "geometry": {"coordinates":[9.7422113419,47.4084815979],"type":"Point"}
}