{
  "type": "Feature",
  "properties": {
    "addr:full":"Weinbergstr 62 Ohlsdorf Ober\u00f6sterreich 4694",
    "addr:housenumber":"62",
    "addr:postcode":"4694",
    "addr:street":"Weinbergstr",
    "iso:country":"AT",
    "sg:address":"Weinbergstr 62",
    "sg:city":"Ohlsdorf",
    "sg:orig_category":"Unterhaltungselektronik / Einzelhandel",
    "sg:phone":"+43 761247033",
    "sg:postcode":"4694",
    "sg:province":"Ober\u00f6sterreich",
    "wof:name":"Mayerhofer Alfred",
    "wof:placetype":"venue"
},
  "geometry": {"coordinates":[13.7944097519,47.9768409729],"type":"Point"}
}