{
  "type": "Feature",
  "properties": {
    "iso:country":"AT",
    "sg:address":"Wurlitzerg 59",
    "sg:city":"Wien",
    "sg:orig_category":"Behinderungen / Leben Mit Behinderungen",
    "sg:phone":"+43 1 4864283",
    "sg:postcode":"1160",
    "sg:province":"Wien",
    "wof:name":"Jugend am Werk",
    "wof:placetype":"venue"
},
  "geometry": {"coordinates":[16.3179664612,48.2179298401],"type":"Point"}
}