{
  "type": "Feature",
  "properties": {
    "addr:full":"Parz 4/8 Getzersdorf Nieder\u00f6sterreich 3131",
    "addr:housenumber":"4 / 8",
    "addr:postcode":"3131",
    "addr:street":"Parz",
    "iso:country":"AT",
    "sg:address":"Parz 4/8",
    "sg:city":"Getzersdorf",
    "sg:orig_category":"Feuerwehren",
    "sg:phone":"+43 2783 8745",
    "sg:postcode":"3131",
    "sg:province":"Nieder\u00f6sterreich",
    "wof:name":"Freiwillige Feuerwehr Reichersdorf",
    "wof:placetype":"venue"
},
  "geometry": {"coordinates":[15.6760120392,48.3197212219],"type":"Point"}
}