{
  "type": "Feature",
  "properties": {
    "iso:country":"AT",
    "sg:address":"Richtstr 45",
    "sg:city":"Villach",
    "sg:orig_category":"Reifen U Reifendienste",
    "sg:phone":"+43 4242 343980",
    "sg:postcode":"9500",
    "sg:province":"K\u00e4rnten",
    "wof:name":"Reifenhaus Thomas Plankenauer GesmbH",
    "wof:placetype":"venue"
},
  "geometry": {"coordinates":[13.8449983597,46.5957946777],"type":"Point"}
}