{
  "type": "Feature",
  "properties": {
    "addr:full":"Wiener Str 37 Kapfenberg Steiermark 8605",
    "addr:postcode":"8605",
    "addr:street":"37",
    "iso:country":"AT",
    "sg:address":"Wiener Str 37",
    "sg:city":"Kapfenberg",
    "sg:orig_category":"Eisenwaren",
    "sg:phone":"+43 4338 62221450",
    "sg:postcode":"8605",
    "sg:province":"Steiermark",
    "wof:name":"Heimlich Alfred HandelsgesmbH",
    "wof:placetype":"venue"
},
  "geometry": {"coordinates":[15.2924928665,47.4444236755],"type":"Point"}
}