{
  "type": "Feature",
  "properties": {
    "addr:full":"Herzog Odilo-Str 100 Mondsee Ober\u00f6sterreich 5310",
    "addr:housenumber":"100",
    "addr:postcode":"5310",
    "addr:street":"Mondsee Oberoesterreich",
    "iso:country":"AT",
    "sg:address":"Herzog Odilo-Str 100",
    "sg:city":"Mondsee",
    "sg:classifiers":[
        {
            "category":"Home & Garden",
            "subcategory":"Garden Supply",
            "type":"Retail Goods"
        }
    ],
    "sg:phone":"+43 6232 2597",
    "sg:postcode":"5310",
    "sg:province":"Ober\u00f6sterreich",
    "sg:tags":[
        "schotter",
        "sand",
        "u"
    ],
    "wof:name":"Buchschartner Fritz Kieswerk GmbH",
    "wof:placetype":"venue"
},
  "geometry": {"coordinates":[13.3344545364,47.8657302856],"type":"Point"}
}