{
  "type": "Feature",
  "properties": {
    "addr:full":"Kufsteiner Str. 4 Langkampfen Tirol 6336",
    "addr:housenumber":"4",
    "addr:postcode":"6336",
    "addr:street":"Str.;Tirol",
    "iso:country":"AT",
    "sg:address":"Kufsteiner Str. 4",
    "sg:city":"Langkampfen",
    "sg:classifiers":[
        {
            "category":"Professional",
            "subcategory":"Engineering",
            "type":"Services"
        }
    ],
    "sg:phone":"+43 4353 726993",
    "sg:postcode":"6336",
    "sg:province":"Tirol",
    "sg:tags":[
        "machine",
        "-",
        "mechanical"
    ],
    "wof:name":"SCHABLONENTECHNIK KUFSTEIN AG",
    "wof:placetype":"venue"
},
  "geometry": {"coordinates":[12.1131038666,47.5539741516],"type":"Point"}
}