{
  "type": "Feature",
  "properties": {
    "addr:full":"Feuerwehrstr 2 Blumau-Neuri\u00dfhof Nieder\u00f6sterreich 2602",
    "addr:housenumber":"2;2602",
    "addr:street":"Feuerwehrstr;Niederoesterreich",
    "iso:country":"AT",
    "sg:address":"Feuerwehrstr 2",
    "sg:city":"Blumau-Neuri\u00dfhof",
    "sg:orig_category":"Seifen",
    "sg:phone":"+43 4326 2848030",
    "sg:postcode":"2602",
    "sg:province":"Nieder\u00f6sterreich",
    "wof:name":"Freyberger Barbara",
    "wof:placetype":"venue"
},
  "geometry": {"coordinates":[16.301738739,47.9267921448],"type":"Point"}
}