{
  "type": "Feature",
  "properties": {
    "iso:country":"AT",
    "sg:address":"Favoritenstrasse 38 ",
    "sg:city":"Wien",
    "sg:classifiers":[
        {
            "category":"Health Services",
            "subcategory":"Podiatrist",
            "type":"Services"
        }
    ],
    "sg:phone":"+43 1 50506780",
    "sg:postcode":"1040",
    "sg:province":"Wien",
    "sg:tags":[
        "insole",
        "support",
        "orthopedic",
        "arch"
    ],
    "sg:website":"www.mass-schuh.at",
    "wof:name":"Walter Wist Ges.m.b.H.",
    "wof:placetype":"venue"
},
  "geometry": {"coordinates":[16.3710803986,48.1912689209],"type":"Point"}
}