{
  "type": "Feature",
  "properties": {
    "iso:country":"AT",
    "sg:address":"Stadtpl 11",
    "sg:city":"Klosterneuburg",
    "sg:orig_category":"Banken U Sparkassen",
    "sg:phone":"+43 4322 43321160",
    "sg:postcode":"3400",
    "sg:province":"Nieder\u00f6sterreich",
    "wof:name":"Bankomat d Volksbank Wien AG",
    "wof:placetype":"venue"
},
  "geometry": {"coordinates":[16.323425293,48.309299469],"type":"Point"}
}