{
  "type": "Feature",
  "properties": {
    "addr:full":"Wiener Str 9 Wiener Neudorf Nieder\u00f6sterreich 2351",
    "addr:postcode":"2351",
    "iso:country":"AT",
    "sg:address":"Wiener Str 9",
    "sg:city":"Wiener Neudorf",
    "sg:orig_category":"Transportunternehmen",
    "sg:phone":"+43 2236 235160",
    "sg:postcode":"2351",
    "sg:province":"Nieder\u00f6sterreich",
    "wof:name":"Freylinger Ludwig",
    "wof:placetype":"venue"
},
  "geometry": {"coordinates":[16.3134841919,48.0850448608],"type":"Point"}
}