{
  "type": "Feature",
  "properties": {
    "addr:full":"Ennser Str 16 Steyr Ober\u00f6sterreich 4400",
    "addr:postcode":"4400",
    "addr:street":"Str 16",
    "iso:country":"AT",
    "sg:address":"Ennser Str 16",
    "sg:city":"Steyr",
    "sg:orig_category":"Tankstellen",
    "sg:phone":"+43 7252 80790",
    "sg:postcode":"4400",
    "sg:province":"Ober\u00f6sterreich",
    "wof:name":"AVANTI TankstellenbetriebsgesmbH",
    "wof:placetype":"venue"
},
  "geometry": {"coordinates":[14.4206933975,48.0573196411],"type":"Point"}
}