{
  "type": "Feature",
  "properties": {
    "addr:full":"Josef Jessernig-Str 19 Stockerau Nieder\u00f6sterreich 2000",
    "addr:housenumber":"19",
    "addr:postcode":"2000",
    "iso:country":"AT",
    "sg:address":"Josef Jessernig-Str 19",
    "sg:city":"Stockerau",
    "sg:orig_category":"Logistik",
    "sg:phone":"+43 2266 72020",
    "sg:postcode":"2000",
    "sg:province":"Nieder\u00f6sterreich",
    "wof:name":"P.P.Pharma Logistik GmbH",
    "wof:placetype":"venue"
},
  "geometry": {"coordinates":[16.237701416,48.3875579834],"type":"Point"}
}