{
  "type": "Feature",
  "properties": {
    "iso:country":"AT",
    "sg:address":"Edlastr 4",
    "sg:city":"Weissenbach an der Triesting",
    "sg:orig_category":"Tischlereien",
    "sg:phone":"+43 4326 7486191",
    "sg:postcode":"2564",
    "sg:province":"Nieder\u00f6sterreich",
    "wof:name":"Schweiger Karl",
    "wof:placetype":"venue"
},
  "geometry": {"coordinates":[16.0329914093,47.9860610962],"type":"Point"}
}