{
  "type": "Feature",
  "properties": {
    "iso:country":"AT",
    "sg:address":"Steinerg 22",
    "sg:city":"Wien",
    "sg:orig_category":"Sportanlagen",
    "sg:phone":"+43 4318 659209",
    "sg:postcode":"1230",
    "sg:province":"Wien",
    "wof:name":"Sportanlage d Stadt Wien (MA 51) - Atzgersdorf",
    "wof:placetype":"venue"
},
  "geometry": {"coordinates":[16.2900714874,48.1450576782],"type":"Point"}
}