{
  "type": "Feature",
  "properties": {
    "addr:full":"Nr 96 Wulzeshofen Nieder\u00f6sterreich 2064",
    "addr:postcode":"2064",
    "addr:street":"Nr;Wulzeshofen",
    "iso:country":"AT",
    "sg:address":"Nr 96",
    "sg:city":"Wulzeshofen",
    "sg:orig_category":"Gemeinden",
    "sg:phone":"+43 2527 204",
    "sg:postcode":"2064",
    "sg:province":"Nieder\u00f6sterreich",
    "wof:name":"Gemeindeamt Wulzeshofen",
    "wof:placetype":"venue"
},
  "geometry": {"coordinates":[16.3042545319,48.7180900574],"type":"Point"}
}