{
  "type": "Feature",
  "properties": {
    "iso:country":"AT",
    "sg:address":"Jedleseer Str 71",
    "sg:city":"Wien",
    "sg:orig_category":"Blumeneinzelhandel",
    "sg:phone":"+43 4312 702583",
    "sg:postcode":"1210",
    "sg:province":"Wien",
    "wof:name":"Blumen Ingrid",
    "wof:placetype":"venue"
},
  "geometry": {"coordinates":[16.3873176575,48.2617263794],"type":"Point"}
}