{
  "type": "Feature",
  "properties": {
    "addr:full":"Volksfeststrasse 13 Linz Ober\u00f6sterreich 4020",
    "addr:housenumber":"13",
    "addr:postcode":"4020",
    "addr:street":"Volksfeststrasse",
    "iso:country":"AT",
    "sg:address":"Volksfeststrasse 13",
    "sg:city":"Linz",
    "sg:classifiers":[
        {
            "category":"Health Services",
            "subcategory":"Dentist",
            "type":"Services"
        }
    ],
    "sg:phone":"+43 732 779842",
    "sg:postcode":"4020",
    "sg:province":"Ober\u00f6sterreich",
    "sg:tags":[
        "dental",
        "implant"
    ],
    "sg:website":"kroeswang-dental.at",
    "wof:name":"Thomas Kr\u00f6swang",
    "wof:placetype":"venue"
},
  "geometry": {"coordinates":[14.2966451645,48.3018226624],"type":"Point"}
}