{
  "type": "Feature",
  "properties": {
    "addr:full":"G\u00fcnser Strasse 13 Horitschon Burgenland 7312",
    "addr:housenumber":"13",
    "addr:postcode":"7312",
    "addr:street":"Guenser Strasse",
    "iso:country":"AT",
    "sg:address":"G\u00fcnser Strasse 13",
    "sg:city":"Horitschon",
    "sg:classifiers":[
        {
            "category":"Banks & Credit Unions",
            "subcategory":"Investment Brokerage",
            "type":"Services"
        }
    ],
    "sg:phone":"+43 2610 42151",
    "sg:postcode":"7312",
    "sg:province":"Burgenland",
    "sg:tags":[
        "absorption",
        "refrigerator"
    ],
    "sg:website":"elektro-lehrner.at",
    "wof:name":"Lehrner Elektro GesmbH",
    "wof:placetype":"venue"
},
  "geometry": {"coordinates":[16.5498600006,47.5862045288],"type":"Point"}
}