{
  "type": "Feature",
  "properties": {
    "addr:full":"Horner Str 20 Eggenburg Nieder\u00f6sterreich 3730",
    "addr:postcode":"3730",
    "addr:street":"Str;Niederoesterreich",
    "iso:country":"AT",
    "sg:address":"Horner Str 20",
    "sg:city":"Eggenburg",
    "sg:orig_category":"Steinmetzbetriebe",
    "sg:phone":"+43 2984 35670",
    "sg:postcode":"3730",
    "sg:province":"Nieder\u00f6sterreich",
    "wof:name":"Worek Karl",
    "wof:placetype":"venue"
},
  "geometry": {"coordinates":[15.8143186569,48.6419944763],"type":"Point"}
}