{
  "type": "Feature",
  "properties": {
    "addr:full":"Fischauer G 209/Top 1 Wiener Neustadt Nieder\u00f6sterreich 2700",
    "addr:housenumber":"209 / top 1",
    "addr:postcode":"2700",
    "addr:street":"Fischauer G",
    "iso:country":"AT",
    "sg:address":"Fischauer G 209/Top 1",
    "sg:city":"Wiener Neustadt",
    "sg:orig_category":"Tauchsportartikel",
    "sg:phone":"+43 4326 2272040",
    "sg:postcode":"2700",
    "sg:province":"Nieder\u00f6sterreich",
    "sg:website":"scubadiving.at",
    "wof:name":"5 Star Dive Center & IDC - SCUBADIVING",
    "wof:placetype":"venue"
},
  "geometry": {"coordinates":[16.2455158234,47.8128814697],"type":"Point"}
}