{
  "type": "Feature",
  "properties": {
    "addr:full":"Nr 24 St. Nikola an der Donau Ober\u00f6sterreich 4381",
    "addr:postcode":"4381",
    "addr:street":"Nr 24;An Der Donau",
    "iso:country":"AT",
    "sg:address":"Nr 24",
    "sg:city":"St. Nikola an der Donau",
    "sg:orig_category":"Bierdepots",
    "sg:phone":"+43 4372 6881060",
    "sg:postcode":"4381",
    "sg:province":"Ober\u00f6sterreich",
    "wof:name":"Seyr Christian",
    "wof:placetype":"venue"
},
  "geometry": {"coordinates":[14.9039363861,48.2318992615],"type":"Point"}
}