{
  "type": "Feature",
  "properties": {
    "addr:full":"Sulzengasse 1 Wien Wien 1230",
    "addr:housenumber":"1",
    "addr:postcode":"1230",
    "addr:street":"Sulzengasse",
    "iso:country":"AT",
    "sg:address":"Sulzengasse 1",
    "sg:city":"Wien",
    "sg:orig_category":"Miscellaneous Products",
    "sg:phone":"+43 4316 8875570",
    "sg:postcode":"1230",
    "sg:province":"Wien",
    "wof:name":"BAUSCHUTZ GES.MBH & CO KG",
    "wof:placetype":"venue"
},
  "geometry": {"coordinates":[16.375667572,48.1460533142],"type":"Point"}
}