{
  "type": "Feature",
  "properties": {
    "addr:full":"Unterdorf 26 Lermoos Tirol 6631",
    "addr:housenumber":"26",
    "addr:postcode":"6631",
    "addr:street":"Unterdorf;Tirol",
    "iso:country":"AT",
    "sg:address":"Unterdorf 26",
    "sg:city":"Lermoos",
    "sg:orig_category":"Matratzen",
    "sg:phone":"+43 5673 3750",
    "sg:postcode":"6631",
    "sg:province":"Tirol",
    "wof:name":"Matratzen Tirol",
    "wof:placetype":"venue"
},
  "geometry": {"coordinates":[10.8809080124,47.4020805359],"type":"Point"}
}