{
  "type": "Feature",
  "properties": {
    "iso:country":"AT",
    "sg:address":"Babenbergerring 9a",
    "sg:city":"Wiener Neustadt",
    "sg:orig_category":"Fu\u00c3\u0178pflege U Fu\u00c3\u0178pflegesalons",
    "sg:phone":"+43 4326 2222232",
    "sg:postcode":"2700",
    "sg:province":"Nieder\u00f6sterreich",
    "wof:name":"Fu\u00dfpflege Regina",
    "wof:placetype":"venue"
},
  "geometry": {"coordinates":[16.2395191193,47.8160591125],"type":"Point"}
}