{
  "type": "Feature",
  "properties": {
    "addr:full":"Markt 3 Abtenau Salzburg 5441",
    "addr:housenumber":"3",
    "addr:postcode":"5441",
    "addr:street":"Markt;Salzburg",
    "iso:country":"AT",
    "sg:address":"Markt 3",
    "sg:city":"Abtenau",
    "sg:classifiers":[
        {
            "category":"Shopping",
            "subcategory":"Gifts & Souvenirs",
            "type":"Retail Goods"
        }
    ],
    "sg:phone":"+43 6243 2296",
    "sg:postcode":"5441",
    "sg:province":"Salzburg",
    "sg:tags":[
        "item"
    ],
    "wof:name":"Glaserei Schmid Inh. Brigitte Wass",
    "wof:placetype":"venue"
},
  "geometry": {"coordinates":[13.3462638855,47.563495636],"type":"Point"}
}