{
  "type": "Feature",
  "properties": {
    "iso:country":"AT",
    "sg:address":"Neidlinger Str 6",
    "sg:city":"Karlstetten",
    "sg:orig_category":"Volksschulen",
    "sg:phone":"+43 2741 8329",
    "sg:postcode":"3121",
    "sg:province":"Nieder\u00f6sterreich",
    "wof:name":"Volksschule",
    "wof:placetype":"venue"
},
  "geometry": {"coordinates":[15.5653095245,48.256439209],"type":"Point"}
}