{
  "type": "Feature",
  "properties": {
    "addr:full":"Nr 80 Obertilliach Tirol 9942",
    "addr:postcode":"9942",
    "addr:street":"Nr 80;Tirol",
    "iso:country":"AT",
    "sg:address":"Nr 80",
    "sg:city":"Obertilliach",
    "sg:orig_category":"Erdarbeiten",
    "sg:phone":"+43 664 3003867",
    "sg:postcode":"9942",
    "sg:province":"Tirol",
    "wof:name":"Scherer Josef",
    "wof:placetype":"venue"
},
  "geometry": {"coordinates":[12.6160793304,46.7085914612],"type":"Point"}
}