{
  "type": "Feature",
  "properties": {
    "iso:country":"AT",
    "sg:address":"Gottscheerstrasse 6",
    "sg:city":"Spittal an der Drau",
    "sg:classifiers":[
        {
            "category":"Home & Garden",
            "subcategory":"Household Appliances",
            "type":"Retail Goods"
        }
    ],
    "sg:phone":"+43 4762 2192",
    "sg:postcode":"9800",
    "sg:province":"K\u00e4rnten",
    "sg:tags":[
        "electric"
    ],
    "wof:name":"Werner Gigler",
    "wof:placetype":"venue"
},
  "geometry": {"coordinates":[13.486869812,46.8216552734],"type":"Point"}
}