{
  "type": "Feature",
  "properties": {
    "addr:full":"Preising 24 Regau Ober\u00f6sterreich 4844",
    "addr:housenumber":"24",
    "addr:postcode":"4844",
    "addr:street":"Preising;Oberoesterreich",
    "iso:country":"AT",
    "sg:address":"Preising 24",
    "sg:city":"Regau",
    "sg:orig_category":"Furniture, General",
    "sg:phone":"+43 767462314",
    "sg:postcode":"4844",
    "sg:province":"Ober\u00f6sterreich",
    "wof:name":"Tischlerei Hessenberger KEG",
    "wof:placetype":"venue"
},
  "geometry": {"coordinates":[13.708562851,47.9954376221],"type":"Point"}
}