{
  "type": "Feature",
  "properties": {
    "addr:full":"Donaul\u00e4nde 54 Krems an der Donau Nieder\u00f6sterreich 3500",
    "addr:housenumber":"54",
    "addr:postcode":"3500",
    "addr:street":"Donaulaende",
    "iso:country":"AT",
    "sg:address":"Donaul\u00e4nde 54",
    "sg:city":"Krems an der Donau",
    "sg:orig_category":"Reinigungsservice",
    "sg:phone":"+43 2732 857510",
    "sg:postcode":"3500",
    "sg:province":"Nieder\u00f6sterreich",
    "wof:name":"ISS Servisystem GesmbH",
    "wof:placetype":"venue"
},
  "geometry": {"coordinates":[15.5834093094,48.402217865],"type":"Point"}
}