{
  "type": "Feature",
  "properties": {
    "addr:full":"Anton-Bosch-G 20 Wien Wien 1210",
    "addr:housenumber":"20",
    "addr:postcode":"1210",
    "addr:street":"Anton-Bosch-G",
    "iso:country":"AT",
    "sg:address":"Anton-Bosch-G 20",
    "sg:city":"Wien",
    "sg:orig_category":"Autoreparatur",
    "sg:phone":"+43 4312 711138",
    "sg:postcode":"1210",
    "sg:province":"Wien",
    "sg:website":"kfz-racek.at",
    "wof:name":"Racek R GmbH",
    "wof:placetype":"venue"
},
  "geometry": {"coordinates":[16.3894748688,48.2696037292],"type":"Point"}
}