{
  "type": "Feature",
  "properties": {
    "iso:country":"AT",
    "sg:address":"Franz-Liszt-G 21",
    "sg:city":"Neusiedl am See",
    "sg:classifiers":[
        {
            "category":"Organizations",
            "subcategory":"Political Organization",
            "type":"Services"
        }
    ],
    "sg:phone":"+43 4321 6740216",
    "sg:postcode":"7100",
    "sg:province":"Burgenland",
    "sg:tags":[
        "mediation"
    ],
    "wof:name":"co medio - Institut f\u00fcr Konfliktregelung & Mediation",
    "wof:placetype":"venue"
},
  "geometry": {"coordinates":[16.8482284546,47.9471588135],"type":"Point"}
}