{
  "type": "Feature",
  "properties": {
    "iso:country":"AT",
    "sg:address":"Brixentaler Str 6",
    "sg:city":"Kirchberg in Tirol",
    "sg:classifiers":[
        {
            "category":"Professional",
            "subcategory":"Computer Services",
            "type":"Services"
        }
    ],
    "sg:phone":"+43 5357 7110",
    "sg:postcode":"6365",
    "sg:province":"Tirol",
    "sg:tags":[
        "software"
    ],
    "wof:name":"UBM Handels GmbH",
    "wof:placetype":"venue"
},
  "geometry": {"coordinates":[12.3132390976,47.4490776062],"type":"Point"}
}