{
  "type": "Feature",
  "properties": {
    "addr:full":"Brauhausgasse 8 Ried im Innkreis Ober\u00f6sterreich 4910",
    "addr:housenumber":"8",
    "addr:postcode":"4910",
    "addr:street":"Brauhausgasse",
    "iso:country":"AT",
    "sg:address":"Brauhausgasse 8",
    "sg:city":"Ried im Innkreis",
    "sg:classifiers":[
        {
            "category":"Professional",
            "subcategory":"Engineering",
            "type":"Services"
        }
    ],
    "sg:phone":"+43 7752 860370",
    "sg:postcode":"4910",
    "sg:province":"Ober\u00f6sterreich",
    "sg:tags":[
        "environmental",
        "protection"
    ],
    "wof:name":"Ing. Wolfgang Taus Technisches B\u00fcro",
    "wof:placetype":"venue"
},
  "geometry": {"coordinates":[13.4876651764,48.2116012573],"type":"Point"}
}