{
  "type": "Feature",
  "properties": {
    "addr:full":"Nr 70 Gr\u00f6bming Steiermark 8962",
    "addr:postcode":"8962",
    "addr:street":"Nr 70 Groebming Steiermark",
    "iso:country":"AT",
    "sg:address":"Nr 70",
    "sg:city":"Gr\u00f6bming",
    "sg:orig_category":"Gemeinden",
    "sg:phone":"+43 3685 223190",
    "sg:postcode":"8962",
    "sg:province":"Steiermark",
    "wof:name":"Gemeindeamt Mitterberg",
    "wof:placetype":"venue"
},
  "geometry": {"coordinates":[13.9440145493,47.4527168274],"type":"Point"}
}