{
  "type": "Feature",
  "properties": {
    "addr:full":"Brunn an der Wild 3  Brunn an der Wild Nieder\u00f6sterreich 3595",
    "addr:housenumber":"3",
    "addr:postcode":"3595",
    "addr:street":"Brunn An Der Wild",
    "iso:country":"AT",
    "sg:address":"Brunn an der Wild 3 ",
    "sg:city":"Brunn an der Wild",
    "sg:classifiers":[
        {
            "category":"Building & Trades",
            "subcategory":"Plumbing",
            "type":"Services"
        }
    ],
    "sg:phone":"+43 2989 2231",
    "sg:postcode":"3595",
    "sg:province":"Nieder\u00f6sterreich",
    "sg:tags":[
        "supraregional",
        "gas"
    ],
    "wof:name":"Schachtner Ges.m.b.H.",
    "wof:placetype":"venue"
},
  "geometry": {"coordinates":[15.5209503174,48.6939620972],"type":"Point"}
}