{
  "type": "Feature",
  "properties": {
    "iso:country":"AT",
    "sg:address":"Mahlerstr 4",
    "sg:city":"Wien",
    "sg:orig_category":"Vinotheken",
    "sg:phone":"+43 1 5125150",
    "sg:postcode":"1010",
    "sg:province":"Wien",
    "wof:name":"ROSSO E NERO Gastst\u00e4ttenbetriebsgmbH",
    "wof:placetype":"venue"
},
  "geometry": {"coordinates":[16.3704948425,48.2027893066],"type":"Point"}
}