{
  "type": "Feature",
  "properties": {
    "addr:full":"Bahnhofstr 7 St. Johann in Tirol Tirol 6380",
    "addr:housenumber":"7",
    "addr:postcode":"6380",
    "addr:street":"Bahnhofstr;Tirol",
    "iso:country":"AT",
    "sg:address":"Bahnhofstr 7",
    "sg:city":"St. Johann in Tirol",
    "sg:orig_category":"Beratungsstellen",
    "sg:phone":"+43 4353 526764241",
    "sg:postcode":"6380",
    "sg:province":"Tirol",
    "wof:name":"BIT - Drogenberatung",
    "wof:placetype":"venue"
},
  "geometry": {"coordinates":[12.4309940338,47.5213317871],"type":"Point"}
}