{
  "type": "Feature",
  "properties": {
    "addr:full":"Marktstr 39 Taxenbach Salzburg 5660",
    "addr:housenumber":"39",
    "addr:postcode":"5660",
    "addr:street":"Marktstr;Salzburg",
    "iso:country":"AT",
    "sg:address":"Marktstr 39",
    "sg:city":"Taxenbach",
    "sg:orig_category":"Tabaktrafiken",
    "sg:phone":"+43 6543 5412",
    "sg:postcode":"5660",
    "sg:province":"Salzburg",
    "wof:name":"Hotter Maximilian",
    "wof:placetype":"venue"
},
  "geometry": {"coordinates":[12.962937355,47.292640686],"type":"Point"}
}