{
  "type": "Feature",
  "properties": {
    "iso:country":"AT",
    "sg:address":"Krottendorf 44",
    "sg:city":"Krottendorf-Gaisfeld",
    "sg:classifiers":[
        {
            "category":"Home & Garden",
            "subcategory":"Building Materials",
            "type":"Retail Goods"
        }
    ],
    "sg:phone":"+43 3143 2231",
    "sg:postcode":"8564",
    "sg:province":"Steiermark",
    "sg:tags":[
        "steel",
        "balcony"
    ],
    "wof:name":"Johann Jocham",
    "wof:placetype":"venue"
},
  "geometry": {"coordinates":[15.1982555389,47.002872467],"type":"Point"}
}