{
  "type": "Feature",
  "properties": {
    "iso:country":"AT",
    "sg:address":"L\u00e4rchenweg 14",
    "sg:city":"St. Marien",
    "sg:orig_category":"Handelsagenturen",
    "sg:phone":"+43 7227 21100",
    "sg:postcode":"4502",
    "sg:province":"Ober\u00f6sterreich",
    "wof:name":"E&M VITAL Orgon Austria - Ensfellner Bernardette",
    "wof:placetype":"venue"
},
  "geometry": {"coordinates":[14.2783632278,48.1462554932],"type":"Point"}
}