{
  "type": "Feature",
  "properties": {
    "addr:full":"Pa\u00df-Thurn-Str 40 Kitzb\u00fchel Tirol 6370",
    "addr:housenumber":"40",
    "addr:postcode":"6370",
    "addr:street":"Pass-Thurn-Str;Tirol",
    "iso:country":"AT",
    "sg:address":"Pa\u00df-Thurn-Str 40",
    "sg:city":"Kitzb\u00fchel",
    "sg:orig_category":"Zimmereien",
    "sg:phone":"+43 5356 65606",
    "sg:postcode":"6370",
    "sg:province":"Tirol",
    "wof:name":"Kreidl Schindeln GesmbH",
    "wof:placetype":"venue"
},
  "geometry": {"coordinates":[12.4274311066,47.4102973938],"type":"Point"}
}