{
  "type": "Feature",
  "properties": {
    "addr:full":"Rattener Str 9 Birkfeld Steiermark 8190",
    "addr:housenumber":"9",
    "addr:postcode":"8190",
    "addr:street":"Str",
    "iso:country":"AT",
    "sg:address":"Rattener Str 9",
    "sg:city":"Birkfeld",
    "sg:orig_category":"Autohandel",
    "sg:phone":"+43 3174 30550",
    "sg:postcode":"8190",
    "sg:province":"Steiermark",
    "wof:name":"Friesenbichler Peter - Peugeot-Autohaus",
    "wof:placetype":"venue"
},
  "geometry": {"coordinates":[15.697681427,47.3575401306],"type":"Point"}
}