{
  "type": "Feature",
  "properties": {
    "addr:full":"Markt 14 Bad Wimsbach-Neydharting Ober\u00f6sterreich 4654",
    "addr:housenumber":"14",
    "addr:postcode":"4654",
    "addr:street":"Markt",
    "iso:country":"AT",
    "sg:address":"Markt 14",
    "sg:city":"Bad Wimsbach-Neydharting",
    "sg:orig_category":"Personalbereitstellung",
    "sg:phone":"+43 4372 4525945",
    "sg:postcode":"4654",
    "sg:province":"Ober\u00f6sterreich",
    "wof:name":"Octopus Reinigung- & Personalbereitstellung GesmbH",
    "wof:placetype":"venue"
},
  "geometry": {"coordinates":[13.9008951187,48.0621871948],"type":"Point"}
}