{
  "type": "Feature",
  "properties": {
    "addr:full":"Haid 25 V\u00f6cklamarkt Ober\u00f6sterreich 4870",
    "addr:housenumber":"25",
    "addr:postcode":"4870",
    "addr:street":"Haid;Oberoesterreich",
    "iso:country":"AT",
    "sg:address":"Haid 25",
    "sg:city":"V\u00f6cklamarkt",
    "sg:classifiers":[
        {
            "category":"Professional",
            "subcategory":"Engineering",
            "type":"Services"
        }
    ],
    "sg:phone":"+43 4376 822245",
    "sg:postcode":"4870",
    "sg:province":"Ober\u00f6sterreich",
    "sg:tags":[
        "machine",
        "-",
        "mechanical"
    ],
    "wof:name":"WIBA GMBH",
    "wof:placetype":"venue"
},
  "geometry": {"coordinates":[13.5049724579,47.9973335266],"type":"Point"}
}