{
  "type": "Feature",
  "properties": {
    "iso:country":"AT",
    "sg:address":"Richard-Strauss-Str 28",
    "sg:city":"Wien",
    "sg:orig_category":"Autoersatzteile",
    "sg:phone":"+43 1 610110",
    "sg:postcode":"1230",
    "sg:province":"Wien",
    "wof:name":"Forstinger Handel und Service GmbH",
    "wof:placetype":"venue"
},
  "geometry": {"coordinates":[16.3363323212,48.139541626],"type":"Point"}
}