{
  "type": "Feature",
  "properties": {
    "iso:country":"AT",
    "sg:city":"Lohnsburg am Kobernau\u00dferwald",
    "sg:orig_category":"Feuerwehren",
    "sg:phone":"+43 7754 3311",
    "sg:postcode":"4923",
    "sg:province":"Ober\u00f6sterreich",
    "wof:name":"Freiwillige Feuerwehr Lohnsburg",
    "wof:placetype":"venue"
},
  "geometry": {"coordinates":[13.4055995941,48.1439590454],"type":"Point"}
}