{
  "type": "Feature",
  "properties": {
    "addr:full":"Kollingweg 324 Hinterglemm Salzburg 5754",
    "addr:housenumber":"324",
    "addr:postcode":"5754",
    "addr:street":"Hinterglemm Salzburg",
    "iso:country":"AT",
    "sg:address":"Kollingweg 324",
    "sg:city":"Hinterglemm",
    "sg:orig_category":"Pensionen / Privatzimmer",
    "sg:phone":"+43 6541 71940",
    "sg:postcode":"5754",
    "sg:province":"Salzburg",
    "wof:name":"Pension Spieleck Johann Baumann",
    "wof:placetype":"venue"
},
  "geometry": {"coordinates":[12.6012058258,47.3800849915],"type":"Point"}
}