{
  "type": "Feature",
  "properties": {
    "addr:full":"Beethovenstrasse 8 Lustenau Vorarlberg 6890",
    "addr:housenumber":"8",
    "addr:postcode":"6890",
    "addr:street":"Beethovenstrasse",
    "iso:country":"AT",
    "sg:address":"Beethovenstrasse 8",
    "sg:city":"Lustenau",
    "sg:classifiers":[
        {
            "category":"Banks & Credit Unions",
            "subcategory":"Bureau De Change",
            "type":"Services"
        }
    ],
    "sg:phone":"+43 5577 84006",
    "sg:postcode":"6890",
    "sg:province":"Vorarlberg",
    "sg:tags":[
        "shielded",
        "equipment",
        "gas",
        "welding"
    ],
    "wof:name":"Peter Roblek-Ortner Technik & Vertrieb f\u00fcr innovative Schweissysteme",
    "wof:placetype":"venue"
},
  "geometry": {"coordinates":[9.6718082428,47.4363136292],"type":"Point"}
}