{
  "type": "Feature",
  "properties": {
    "addr:full":"Hohe Warte 3 Wien Wien 1190",
    "addr:housenumber":"3",
    "addr:postcode":"1190",
    "addr:street":"Hohe Warte",
    "iso:country":"AT",
    "sg:address":"Hohe Warte 3",
    "sg:city":"Wien",
    "sg:orig_category":"Sonderschulen",
    "sg:phone":"+43 1 3685385",
    "sg:postcode":"1190",
    "sg:province":"Wien",
    "wof:name":"Sonderp\u00e4dagogisches Zentrum f verhaltensauff\u00e4llige Kinder d Stadt Wien",
    "wof:placetype":"venue"
},
  "geometry": {"coordinates":[16.3556118011,48.2448272705],"type":"Point"}
}