{
  "type": "Feature",
  "properties": {
    "addr:full":"Walchen 317 Piesendorf Salzburg 5721",
    "addr:housenumber":"317",
    "addr:postcode":"5721",
    "addr:street":"Walchen;Salzburg",
    "iso:country":"AT",
    "sg:address":"Walchen 317",
    "sg:city":"Piesendorf",
    "sg:orig_category":"Holzhandel",
    "sg:phone":"+43 6549 7915",
    "sg:postcode":"5721",
    "sg:province":"Salzburg",
    "wof:name":"Winkler Peter",
    "wof:placetype":"venue"
},
  "geometry": {"coordinates":[12.6913766861,47.2882194519],"type":"Point"}
}