{
  "type": "Feature",
  "properties": {
    "iso:country":"AT",
    "sg:address":"Jedlham 17",
    "sg:city":"St. Georgen im Attergau",
    "sg:orig_category":"Massagen",
    "sg:phone":"+43 76678082",
    "sg:postcode":"4880",
    "sg:province":"Ober\u00f6sterreich",
    "wof:name":"Moser Gerhard",
    "wof:placetype":"venue"
},
  "geometry": {"coordinates":[13.5116796494,47.9487838745],"type":"Point"}
}