{
  "type": "Feature",
  "properties": {
    "addr:full":"Nr 43 Going am Wilden Kaiser Tirol 6353",
    "addr:postcode":"6353",
    "addr:street":"Nr;Going;Tirol",
    "iso:country":"AT",
    "sg:address":"Nr 43",
    "sg:city":"Going am Wilden Kaiser",
    "sg:orig_category":"Pensionen / Privatzimmer",
    "sg:phone":"+43 4353 582440",
    "sg:postcode":"6353",
    "sg:province":"Tirol",
    "wof:name":"Pension Haus Norbert",
    "wof:placetype":"venue"
},
  "geometry": {"coordinates":[12.3282499313,47.5145301819],"type":"Point"}
}