{
  "type": "Feature",
  "properties": {
    "iso:country":"AT",
    "sg:address":"Burgstrasse 27",
    "sg:city":"Vorchdorf",
    "sg:classifiers":[
        {
            "category":"Banks & Credit Unions",
            "subcategory":"Investment Brokerage",
            "type":"Services"
        }
    ],
    "sg:phone":"+43 76148284",
    "sg:postcode":"4655",
    "sg:province":"Ober\u00f6sterreich",
    "sg:tags":[
        "audio",
        "accessory"
    ],
    "sg:website":"koflertv.at",
    "wof:name":"Herbert Kofler",
    "wof:placetype":"venue"
},
  "geometry": {"coordinates":[13.9132957458,47.9972953796],"type":"Point"}
}