{
  "type": "Feature",
  "properties": {
    "addr:full":"stegleiten 94 - pf27 3402",
    "addr:housenumber":"94 pf27",
    "addr:postcode":"3402",
    "addr:street":"Stegleiten",
    "iso:country":"AT",
    "sg:address":"stegleiten 94 - pf27",
    "sg:orig_category":"Finanzen, Finanzberatung",
    "sg:phone":"+43 4366 42221686",
    "sg:postcode":"3402",
    "sg:website":"http://www.amazon.at/riding",
    "wof:name":"KAISA-Grafik",
    "wof:placetype":"venue"
},
  "geometry": {"coordinates":[16.3252258301,48.3049087524],"type":"Point"}
}