{
  "type": "Feature",
  "properties": {
    "addr:full":"Wiener Str 38 Stockerau Nieder\u00f6sterreich 2000",
    "addr:postcode":"2000",
    "addr:street":"38",
    "iso:country":"AT",
    "sg:address":"Wiener Str 38",
    "sg:city":"Stockerau",
    "sg:orig_category":"Lebensmittel / Einzelhandel",
    "sg:phone":"+43 2266 64527",
    "sg:postcode":"2000",
    "sg:province":"Nieder\u00f6sterreich",
    "wof:name":"MERKUR Markt",
    "wof:placetype":"venue"
},
  "geometry": {"coordinates":[16.2367019653,48.3850822449],"type":"Point"}
}