{
  "type": "Feature",
  "properties": {
    "iso:country":"AT",
    "sg:address":"Galvanistr 2",
    "sg:city":"Linz",
    "sg:orig_category":"Unternehmensberatung",
    "sg:phone":"+43 732 750557",
    "sg:postcode":"4040",
    "sg:province":"Ober\u00f6sterreich",
    "wof:name":"andreas christian prag - prag keg team- & organisationsberatung",
    "wof:placetype":"venue"
},
  "geometry": {"coordinates":[14.3022670746,48.332649231],"type":"Point"}
}