{
  "type": "Feature",
  "properties": {
    "addr:full":"Nr 137 Stetteldorf am Wagram Nieder\u00f6sterreich 3463",
    "addr:postcode":"3463",
    "addr:street":"Nr;Niederoesterreich",
    "iso:country":"AT",
    "sg:address":"Nr 137",
    "sg:city":"Stetteldorf am Wagram",
    "sg:orig_category":"Baumschulen",
    "sg:phone":"+43 4322 782705",
    "sg:postcode":"3463",
    "sg:province":"Nieder\u00f6sterreich",
    "wof:name":"Ziegelmaier Leopold",
    "wof:placetype":"venue"
},
  "geometry": {"coordinates":[16.0162162781,48.4079933167],"type":"Point"}
}