{
  "type": "Feature",
  "properties": {
    "addr:full":"Franzensthalstr 25 Ebergassing Nieder\u00f6sterreich 2435",
    "addr:housenumber":"25",
    "addr:postcode":"2435",
    "addr:street":"Franzensthalstr",
    "iso:country":"AT",
    "sg:address":"Franzensthalstr 25",
    "sg:city":"Ebergassing",
    "sg:orig_category":"Futtermittel",
    "sg:phone":"+43 2234 72231",
    "sg:postcode":"2435",
    "sg:province":"Nieder\u00f6sterreich",
    "wof:name":"K\u00f6nigshofer Futtermittel GmbH",
    "wof:placetype":"venue"
},
  "geometry": {"coordinates":[16.5153083801,48.0412826538],"type":"Point"}
}