{
  "type": "Feature",
  "properties": {
    "addr:full":"Markt 85 Golling an der Salzach Salzburg 5440",
    "addr:housenumber":"85",
    "addr:postcode":"5440",
    "addr:street":"Markt",
    "iso:country":"AT",
    "sg:address":"Markt 85",
    "sg:city":"Golling an der Salzach",
    "sg:orig_category":"Banken U Sparkassen",
    "sg:phone":"+43 4362 4477550",
    "sg:postcode":"5440",
    "sg:province":"Salzburg",
    "wof:name":"Bankomat d Volksbank Salzburg regGenmbH",
    "wof:placetype":"venue"
},
  "geometry": {"coordinates":[13.1674156189,47.5967559814],"type":"Point"}
}