{
  "type": "Feature",
  "properties": {
    "iso:country":"AT",
    "sg:address":"Obere Landstr 29",
    "sg:city":"Krems an der Donau",
    "sg:orig_category":"Banken U Sparkassen",
    "sg:phone":"+43 4327 32735960",
    "sg:postcode":"3500",
    "sg:province":"Nieder\u00f6sterreich",
    "wof:name":"Bankomat der Oberbank AG",
    "wof:placetype":"venue"
},
  "geometry": {"coordinates":[15.5972585678,48.410068512],"type":"Point"}
}