{
  "type": "Feature",
  "properties": {
    "addr:full":"Obere Landstr 29 Krems an der Donau Nieder\u00f6sterreich 3500",
    "addr:housenumber":"29",
    "addr:postcode":"3500",
    "addr:street":"Obere Landstr",
    "iso:country":"AT",
    "sg:address":"Obere Landstr 29",
    "sg:city":"Krems an der Donau",
    "sg:orig_category":"Banken U Sparkassen",
    "sg:phone":"+43 4327 32735960",
    "sg:postcode":"3500",
    "sg:province":"Nieder\u00f6sterreich",
    "wof:name":"Bankomat der Oberbank AG",
    "wof:placetype":"venue"
},
  "geometry": {"coordinates":[15.5972585678,48.410068512],"type":"Point"}
}