{
  "type": "Feature",
  "properties": {
    "iso:country":"AT",
    "sg:address":"Wei\u00dfenbach 2",
    "sg:city":"Kuchl",
    "sg:orig_category":"Tischlereien",
    "sg:phone":"+43 6244 5380",
    "sg:postcode":"5431",
    "sg:province":"Salzburg",
    "wof:name":"Seidl Johann",
    "wof:placetype":"venue"
},
  "geometry": {"coordinates":[13.1438808441,47.625667572],"type":"Point"}
}