{
  "type": "Feature",
  "properties": {
    "addr:full":"Brenjurweg 1 Tarrenz Tirol 6464",
    "addr:housenumber":"1",
    "addr:postcode":"6464",
    "addr:street":"Brenjurweg;Tirol",
    "iso:country":"AT",
    "sg:address":"Brenjurweg 1",
    "sg:city":"Tarrenz",
    "sg:orig_category":"Feuerwehren",
    "sg:phone":"+43 5412 62724",
    "sg:postcode":"6464",
    "sg:province":"Tirol",
    "wof:name":"Freiwillige Feuerwehr",
    "wof:placetype":"venue"
},
  "geometry": {"coordinates":[10.7595796585,47.260055542],"type":"Point"}
}