{
  "type": "Feature",
  "properties": {
    "addr:full":"Denglerg 7/7 Wien Wien 1150",
    "addr:housenumber":"7 / 7",
    "addr:postcode":"1150",
    "addr:street":"Denglerg",
    "iso:country":"AT",
    "sg:address":"Denglerg 7/7",
    "sg:city":"Wien",
    "sg:orig_category":"Bauunternehmen",
    "sg:phone":"+43 1 9610703",
    "sg:postcode":"1150",
    "sg:province":"Wien",
    "wof:name":"MIBERO BaugesmbH",
    "wof:placetype":"venue"
},
  "geometry": {"coordinates":[16.3284492493,48.192401886],"type":"Point"}
}