{
  "type": "Feature",
  "properties": {
    "addr:full":"Voitshofen 30 Weilbach Ober\u00f6sterreich 4984",
    "addr:housenumber":"30",
    "addr:postcode":"4984",
    "addr:street":"Voitshofen",
    "iso:country":"AT",
    "sg:address":"Voitshofen 30",
    "sg:city":"Weilbach",
    "sg:orig_category":"Appartements / Ferienwohnungen",
    "sg:phone":"+43 4377 576288",
    "sg:postcode":"4984",
    "sg:province":"Ober\u00f6sterreich",
    "wof:name":"Appartementhaus Innviertel",
    "wof:placetype":"venue"
},
  "geometry": {"coordinates":[13.3607063293,48.2757110596],"type":"Point"}
}