{
  "type": "Feature",
  "properties": {
    "iso:country":"AT",
    "sg:address":"Untere Carnuntumstr 6",
    "sg:city":"Regelsbrunn",
    "sg:orig_category":"Tankstellen",
    "sg:phone":"+43 2163 2349",
    "sg:postcode":"2403",
    "sg:province":"Nieder\u00f6sterreich",
    "wof:name":"OMV AG",
    "wof:placetype":"venue"
},
  "geometry": {"coordinates":[16.809135437,48.1077575684],"type":"Point"}
}