{
  "type": "Feature",
  "properties": {
    "iso:country":"AT",
    "sg:address":"Nr 26",
    "sg:city":"Obernberg am Inn",
    "sg:orig_category":"Pensionen / Privatzimmer",
    "sg:phone":"+43 7758 2414",
    "sg:postcode":"4982",
    "sg:province":"Ober\u00f6sterreich",
    "wof:name":"Ferienhof Fam Schie\u00dfl",
    "wof:placetype":"venue"
},
  "geometry": {"coordinates":[13.3341207504,48.2915267944],"type":"Point"}
}