{
  "type": "Feature",
  "properties": {
    "addr:full":"Fischer-von-Erlach-Gasse 23 Leibnitz Steiermark 8430",
    "addr:housenumber":"23",
    "addr:postcode":"8430",
    "addr:street":"Fischer-Von-Erlach-Gasse;Steiermark",
    "iso:country":"AT",
    "sg:address":"Fischer-von-Erlach-Gasse 23",
    "sg:city":"Leibnitz",
    "sg:classifiers":[
        {
            "category":"Organizations",
            "subcategory":"Labor Organization",
            "type":"Services"
        }
    ],
    "sg:phone":"+43 3452 733340",
    "sg:postcode":"8430",
    "sg:province":"Steiermark",
    "sg:tags":[
        "work",
        "assembling",
        "assembly",
        "contract"
    ],
    "sg:website":"globus-bau.at",
    "wof:name":"Globus-Bau GmbH",
    "wof:placetype":"venue"
},
  "geometry": {"coordinates":[15.5505876541,46.7889595032],"type":"Point"}
}