{
  "type": "Feature",
  "properties": {
    "addr:full":"Biberhaufenweg 78 Wien Wien 1220",
    "addr:housenumber":"78",
    "addr:postcode":"1220",
    "addr:street":"Biberhaufenweg",
    "iso:country":"AT",
    "sg:address":"Biberhaufenweg 78",
    "sg:city":"Wien",
    "sg:orig_category":"Lebensmittel / Einzelhandel",
    "sg:phone":"+43 1 2821377",
    "sg:postcode":"1220",
    "sg:province":"Wien",
    "wof:name":"ADEG Aktiv Markt",
    "wof:placetype":"venue"
},
  "geometry": {"coordinates":[16.4786376953,48.2114486694],"type":"Point"}
}