{
  "type": "Feature",
  "properties": {
    "addr:full":"Am \u00f6KOPARK 4 Hartberg Steiermark 8230",
    "addr:housenumber":"4",
    "addr:postcode":"8230",
    "addr:street":"Am Oekopark",
    "iso:country":"AT",
    "sg:address":"Am \u00f6KOPARK 4",
    "sg:city":"Hartberg",
    "sg:orig_category":"Umweltschutz",
    "sg:phone":"+43 4333 3266639",
    "sg:postcode":"8230",
    "sg:province":"Steiermark",
    "wof:name":"Haslauer & Partner GmbH",
    "wof:placetype":"venue"
},
  "geometry": {"coordinates":[15.9727478027,47.2819519043],"type":"Point"}
}