{
  "type": "Feature",
  "properties": {
    "addr:full":"Gumpendorfer Str 93 Wien Wien 1060",
    "addr:postcode":"1060",
    "addr:street":"Str 93",
    "iso:country":"AT",
    "sg:address":"Gumpendorfer Str 93",
    "sg:city":"Wien",
    "sg:orig_category":"Lebensmittel / Einzelhandel",
    "sg:phone":"+43 1 9612620",
    "sg:postcode":"1060",
    "sg:province":"Wien",
    "wof:name":"EMMA Otto",
    "wof:placetype":"venue"
},
  "geometry": {"coordinates":[16.3490085602,48.1927032471],"type":"Point"}
}