{
  "type": "Feature",
  "properties": {
    "addr:full":"Bahnhofstr 16 Amstetten Nieder\u00f6sterreich 3300",
    "addr:housenumber":"16",
    "addr:postcode":"3300",
    "addr:street":"Bahnhofstr;Niederoesterreich",
    "iso:country":"AT",
    "sg:address":"Bahnhofstr 16",
    "sg:city":"Amstetten",
    "sg:orig_category":"Reitsportartikel",
    "sg:phone":"+43 4374 72623250",
    "sg:postcode":"3300",
    "sg:province":"Nieder\u00f6sterreich",
    "wof:name":"Prokop Reitsport",
    "wof:placetype":"venue"
},
  "geometry": {"coordinates":[14.8782320023,48.123588562],"type":"Point"}
}