{
  "type": "Feature",
  "properties": {
    "iso:country":"AT",
    "sg:address":"Donaufelder Str 2",
    "sg:city":"Wien",
    "sg:orig_category":"Tabaktrafiken",
    "sg:phone":"+43 1 2706723",
    "sg:postcode":"1210",
    "sg:province":"Wien",
    "wof:name":"Steininger Gabriele",
    "wof:placetype":"venue"
},
  "geometry": {"coordinates":[16.408618927,48.2547302246],"type":"Point"}
}