{
  "type": "Feature",
  "properties": {
    "addr:full":"Nr 4 Gosdorf Steiermark 8482",
    "addr:postcode":"8482",
    "addr:street":"Nr;Gosdorf",
    "iso:country":"AT",
    "sg:address":"Nr 4",
    "sg:city":"Gosdorf",
    "sg:orig_category":"Installationsunternehmen",
    "sg:phone":"+43 4334 7238610",
    "sg:postcode":"8482",
    "sg:province":"Steiermark",
    "wof:name":"Agrarunion S\u00fcdost regGenmbH Lagerhaus KG",
    "wof:placetype":"venue"
},
  "geometry": {"coordinates":[15.7965946198,46.7270584106],"type":"Point"}
}