{
  "type": "Feature",
  "properties": {
    "addr:full":"Mariahilfer Str 51 Wien Wien 1060",
    "addr:postcode":"1060",
    "addr:street":"Str 51",
    "iso:country":"AT",
    "sg:address":"Mariahilfer Str 51",
    "sg:city":"Wien",
    "sg:orig_category":"Fotoapparate U -Artikel / Einzelhandel",
    "sg:phone":"+43 4315 879575",
    "sg:postcode":"1060",
    "sg:province":"Wien",
    "wof:name":"Niedermeyer GmbH",
    "wof:placetype":"venue"
},
  "geometry": {"coordinates":[16.3539848328,48.1996459961],"type":"Point"}
}