{
  "type": "Feature",
  "properties": {
    "addr:full":"Stadionstr 7 Judenburg Steiermark 8750",
    "addr:housenumber":"7",
    "addr:postcode":"8750",
    "addr:street":"Stadionstr",
    "iso:country":"AT",
    "sg:address":"Stadionstr 7",
    "sg:city":"Judenburg",
    "sg:orig_category":"Sportanlagen",
    "sg:phone":"+43 3572 82750",
    "sg:postcode":"8750",
    "sg:province":"Steiermark",
    "wof:name":"Stadion Judenburg",
    "wof:placetype":"venue"
},
  "geometry": {"coordinates":[14.6768932343,47.1782112122],"type":"Point"}
}