{
  "type": "Feature",
  "properties": {
    "addr:full":"Wiener Str 23 Wiener Neustadt Nieder\u00f6sterreich 2700",
    "addr:postcode":"2700",
    "addr:street":"23",
    "iso:country":"AT",
    "sg:address":"Wiener Str 23",
    "sg:city":"Wiener Neustadt",
    "sg:orig_category":"Boutiquen",
    "sg:phone":"+43 2622 20895",
    "sg:postcode":"2700",
    "sg:province":"Nieder\u00f6sterreich",
    "wof:name":"B & A Jeansstore",
    "wof:placetype":"venue"
},
  "geometry": {"coordinates":[16.2440242767,47.8155555725],"type":"Point"}
}