{
  "type": "Feature",
  "properties": {
    "addr:full":"Trattnerring 2 Ebergassing Nieder\u00f6sterreich 2435",
    "addr:housenumber":"2",
    "addr:postcode":"2435",
    "addr:street":"Trattnerring",
    "iso:country":"AT",
    "sg:address":"Trattnerring 2",
    "sg:city":"Ebergassing",
    "sg:classifiers":[
        {
            "category":"Autos & Motor Vehicles",
            "subcategory":"Fuel & Gas Station",
            "type":"Retail Goods"
        }
    ],
    "sg:phone":"+43 2230 30010",
    "sg:postcode":"2435",
    "sg:province":"Nieder\u00f6sterreich",
    "sg:tags":[
        "engine",
        "set",
        "diesel"
    ],
    "wof:name":"Ehardt Maschinenbau GmbH",
    "wof:placetype":"venue"
},
  "geometry": {"coordinates":[16.5202293396,48.0465164185],"type":"Point"}
}