{
  "type": "Feature",
  "properties": {
    "addr:full":"Stolzenthalerg 20/7 Wien Wien 1080",
    "addr:housenumber":"20 / 7",
    "addr:postcode":"1080",
    "addr:street":"Stolzenthalerg",
    "iso:country":"AT",
    "sg:address":"Stolzenthalerg 20/7",
    "sg:city":"Wien",
    "sg:orig_category":"\u00c3\u201erzte / F Allgemeinmedizin",
    "sg:phone":"+43 664 1848732",
    "sg:postcode":"1080",
    "sg:province":"Wien",
    "wof:name":"Schmid Marcus Dr",
    "wof:placetype":"venue"
},
  "geometry": {"coordinates":[16.3422641754,48.2099876404],"type":"Point"}
}