{
  "type": "Feature",
  "properties": {
    "iso:country":"AT",
    "sg:address":"Jahnstrasse 12",
    "sg:city":"Tulln an der Donau",
    "sg:classifiers":[
        {
            "category":"Manufacturing",
            "subcategory":"Petroleum Products",
            "type":"Manufacturing & Wholesale Goods"
        }
    ],
    "sg:phone":"+43 2272 63391",
    "sg:postcode":"3430",
    "sg:province":"Nieder\u00f6sterreich",
    "sg:tags":[
        "air-conditioned",
        "raw",
        "plant",
        "sausage",
        "smoking"
    ],
    "sg:website":"thermotrans.at",
    "wof:name":"Thermo Trans K\u00e4ltetechnik GmbH",
    "wof:placetype":"venue"
},
  "geometry": {"coordinates":[16.0478000641,48.3286933899],"type":"Point"}
}