{
  "type": "Feature",
  "properties": {
    "iso:country":"AT",
    "sg:address":"Hirscheng 3",
    "sg:city":"Wien",
    "sg:orig_category":"Friseure U Frisiersalons",
    "sg:phone":"+43 4315 971513",
    "sg:postcode":"1060",
    "sg:province":"Wien",
    "wof:name":"Handb\u00fcchler Barbara",
    "wof:placetype":"venue"
},
  "geometry": {"coordinates":[16.3486709595,48.1933403015],"type":"Point"}
}