{
  "type": "Feature",
  "properties": {
    "addr:full":"Zieglerg 13 Wien Wien 1070",
    "addr:housenumber":"13",
    "addr:postcode":"1070",
    "addr:street":"Zieglerg",
    "iso:country":"AT",
    "sg:address":"Zieglerg 13",
    "sg:city":"Wien",
    "sg:orig_category":"Montagen U Montagetechnik",
    "sg:phone":"+43 4366 44652067",
    "sg:postcode":"1070",
    "sg:province":"Wien",
    "wof:name":"Yalcin Yasemin GesmbH",
    "wof:placetype":"venue"
},
  "geometry": {"coordinates":[16.3449573517,48.19871521],"type":"Point"}
}