{
  "type": "Feature",
  "properties": {
    "addr:full":"Paracelsusg 6 Villach K\u00e4rnten 9500",
    "addr:housenumber":"6",
    "addr:postcode":"9500",
    "addr:street":"Paracelsusg;Kaernten",
    "iso:country":"AT",
    "sg:address":"Paracelsusg 6",
    "sg:city":"Villach",
    "sg:orig_category":"Juweliere, Gold- U Silberschmiede",
    "sg:phone":"+43 4242 238739",
    "sg:postcode":"9500",
    "sg:province":"K\u00e4rnten",
    "wof:name":"Girardi Schmuck Design",
    "wof:placetype":"venue"
},
  "geometry": {"coordinates":[13.8451061249,46.6141967773],"type":"Point"}
}