{
  "type": "Feature",
  "properties": {
    "addr:full":"Stadionstr 42 Wiener Neustadt Nieder\u00f6sterreich 2700",
    "addr:housenumber":"42",
    "addr:postcode":"2700",
    "addr:street":"Stadionstr",
    "iso:country":"AT",
    "sg:address":"Stadionstr 42",
    "sg:city":"Wiener Neustadt",
    "sg:orig_category":"Spielwaren U Spiele",
    "sg:phone":"+43 4326 2229442",
    "sg:postcode":"2700",
    "sg:province":"Nieder\u00f6sterreich",
    "wof:name":"VEDES FAMILY STORE Wr Neustadt",
    "wof:placetype":"venue"
},
  "geometry": {"coordinates":[16.2471618652,47.8297348022],"type":"Point"}
}