{
  "type": "Feature",
  "properties": {
    "iso:country":"AT",
    "sg:address":"Zeller Bundesstr 4/1. Stock",
    "sg:city":"Saalfelden am Steinernen Meer",
    "sg:orig_category":"Physiotherapie",
    "sg:phone":"+43 4365 8273779",
    "sg:postcode":"5760",
    "sg:province":"Salzburg",
    "wof:name":"Gemeinschaftspraxis f\u00fcr Physiotherapie Leonhardt",
    "wof:placetype":"venue"
},
  "geometry": {"coordinates":[12.8474750519,47.426410675],"type":"Point"}
}