{
  "type": "Feature",
  "properties": {
    "addr:full":"Markt 38 Ulrichsberg Ober\u00f6sterreich 4161",
    "addr:housenumber":"38",
    "addr:postcode":"4161",
    "addr:street":"Markt",
    "iso:country":"AT",
    "sg:address":"Markt 38",
    "sg:city":"Ulrichsberg",
    "sg:orig_category":"Transportunternehmen",
    "sg:phone":"+43 7288 22020",
    "sg:postcode":"4161",
    "sg:province":"Ober\u00f6sterreich",
    "wof:name":"M\u00fcller Josef",
    "wof:placetype":"venue"
},
  "geometry": {"coordinates":[13.9110097885,48.6748313904],"type":"Point"}
}