{
  "type": "Feature",
  "properties": {
    "addr:full":"Ramingstein Salzburg 5591",
    "addr:postcode":"5591",
    "iso:country":"AT",
    "sg:city":"Ramingstein",
    "sg:orig_category":"Feuerwehren",
    "sg:phone":"+43 6475 80212",
    "sg:postcode":"5591",
    "sg:province":"Salzburg",
    "wof:name":"Feuerwehr Ramingstein",
    "wof:placetype":"venue"
},
  "geometry": {"coordinates":[13.8369922638,47.0755195618],"type":"Point"}
}