{
  "type": "Feature",
  "properties": {
    "iso:country":"AT",
    "sg:address":"Nottendorfer G 2",
    "sg:city":"Wien",
    "sg:classifiers":[
        {
            "category":"Retail",
            "subcategory":"Storage",
            "type":"Services"
        }
    ],
    "sg:phone":"+43 1 795400",
    "sg:postcode":"1030",
    "sg:province":"Wien",
    "sg:tags":[
        "archive"
    ],
    "wof:name":"\u00f6sterreichisches Staatsarchiv - Generaldirektion",
    "wof:placetype":"venue"
},
  "geometry": {"coordinates":[16.4113368988,48.1910591125],"type":"Point"}
}