{
  "type": "Feature",
  "properties": {
    "iso:country":"AT",
    "sg:address":"Nr 153",
    "sg:city":"Loipersdorf",
    "sg:orig_category":"Massagen",
    "sg:phone":"+43 4333 828212718",
    "sg:postcode":"8282",
    "sg:province":"Steiermark",
    "wof:name":"Massagefachinstitut Meusburger Reinhard",
    "wof:placetype":"venue"
},
  "geometry": {"coordinates":[16.1014595032,47.012878418],"type":"Point"}
}