{
  "type": "Feature",
  "properties": {
    "addr:full":"Schiedstr 555 Kaprun Salzburg 5710",
    "addr:housenumber":"555",
    "addr:postcode":"5710",
    "addr:street":"Kaprun Salzburg",
    "iso:country":"AT",
    "sg:address":"Schiedstr 555",
    "sg:city":"Kaprun",
    "sg:orig_category":"Elektroinstallationsunternehmen",
    "sg:phone":"+43 6547 73060",
    "sg:postcode":"5710",
    "sg:province":"Salzburg",
    "wof:name":"Lackner Erwin",
    "wof:placetype":"venue"
},
  "geometry": {"coordinates":[12.7624454498,47.2706108093],"type":"Point"}
}