{
  "type": "Feature",
  "properties": {
    "addr:full":"Lustenauerstr 110 Hohenems Vorarlberg 6845",
    "addr:housenumber":"110",
    "addr:postcode":"6845",
    "iso:country":"AT",
    "sg:address":"Lustenauerstr 110",
    "sg:city":"Hohenems",
    "sg:classifiers":[
        {
            "category":"Shopping",
            "subcategory":"Clothing, Apparel, & Fashions",
            "type":"Retail Goods"
        }
    ],
    "sg:phone":"+43 4355 7672384",
    "sg:postcode":"6845",
    "sg:province":"Vorarlberg",
    "sg:tags":[
        "clothes"
    ],
    "wof:name":"L KOMMERELL & CO",
    "wof:placetype":"venue"
},
  "geometry": {"coordinates":[9.6761226654,47.3723487854],"type":"Point"}
}