{
  "type": "Feature",
  "properties": {
    "iso:country":"AT",
    "sg:address":"Anton-Schneider-Str 2",
    "sg:city":"Bregenz",
    "sg:orig_category":"Steuerberatung",
    "sg:phone":"+43 5574 52741",
    "sg:postcode":"6900",
    "sg:province":"Vorarlberg",
    "wof:name":"Schrottenbaum Nikolaus Mag",
    "wof:placetype":"venue"
},
  "geometry": {"coordinates":[9.7472848892,47.5030097961],"type":"Point"}
}