{
  "type": "Feature",
  "properties": {
    "addr:full":"Frax 281 M\u00fcnster Tirol 6232",
    "addr:housenumber":"281",
    "addr:postcode":"6232",
    "addr:street":"Frax;Tirol",
    "iso:country":"AT",
    "sg:address":"Frax 281",
    "sg:city":"M\u00fcnster",
    "sg:orig_category":"Friseure U Frisiersalons",
    "sg:phone":"+43 4353 378370",
    "sg:postcode":"6232",
    "sg:province":"Tirol",
    "wof:name":"Frisiersalon Tamara",
    "wof:placetype":"venue"
},
  "geometry": {"coordinates":[11.8125801086,47.4356613159],"type":"Point"}
}