{
  "type": "Feature",
  "properties": {
    "addr:full":"Beda-Weber-G 29 Innsbruck Tirol 6020",
    "addr:housenumber":"29",
    "addr:postcode":"6020",
    "addr:street":"Beda-Weber-G;Tirol",
    "iso:country":"AT",
    "sg:address":"Beda-Weber-G 29",
    "sg:city":"Innsbruck",
    "sg:orig_category":"Pensionen / Privatzimmer",
    "sg:phone":"+43 512 3412430",
    "sg:postcode":"6020",
    "sg:province":"Tirol",
    "wof:name":"Pension Menghini",
    "wof:placetype":"venue"
},
  "geometry": {"coordinates":[11.4141979218,47.2563667297],"type":"Point"}
}