{
  "type": "Feature",
  "properties": {
    "iso:country":"AT",
    "sg:address":"Rankg 8",
    "sg:city":"Wien",
    "sg:orig_category":"Immobilienmakler",
    "sg:phone":"+43 4319 249727",
    "sg:postcode":"1160",
    "sg:province":"Wien",
    "wof:name":"Wolf Paul Ing",
    "wof:placetype":"venue"
},
  "geometry": {"coordinates":[16.3089694977,48.2105178833],"type":"Point"}
}