{
  "type": "Feature",
  "properties": {
    "addr:full":"Inselstr 19 Wolfurt Vorarlberg 6922",
    "addr:housenumber":"19",
    "addr:postcode":"6922",
    "addr:street":"Inselstr",
    "iso:country":"AT",
    "sg:address":"Inselstr 19",
    "sg:city":"Wolfurt",
    "sg:orig_category":"Dachdeckereien",
    "sg:phone":"+43 4355 74759270",
    "sg:postcode":"6922",
    "sg:province":"Vorarlberg",
    "wof:name":"Schwendinger & Fink Spengler- u Dachdecker GesmbH",
    "wof:placetype":"venue"
},
  "geometry": {"coordinates":[9.7496061325,47.4794654846],"type":"Point"}
}