{
  "type": "Feature",
  "properties": {
    "addr:full":"Kremsm\u00fcnsterer Str 42B Linz Ober\u00f6sterreich 4030",
    "addr:postcode":"4030",
    "addr:street":"Str 42B",
    "iso:country":"AT",
    "sg:address":"Kremsm\u00fcnsterer Str 42B",
    "sg:city":"Linz",
    "sg:classifiers":[
        {
            "category":"Taxi",
            "type":"Transportation"
        }
    ],
    "sg:phone":"+43 732 309036",
    "sg:postcode":"4030",
    "sg:province":"Ober\u00f6sterreich",
    "sg:tags":[
        "personentransporte",
        "u"
    ],
    "wof:name":"Gruber Silvia",
    "wof:placetype":"venue"
},
  "geometry": {"coordinates":[14.3069601059,48.2325248718],"type":"Point"}
}