{
  "type": "Feature",
  "properties": {
    "iso:country":"AT",
    "sg:address":"Nr 12",
    "sg:city":"Aich-Assach",
    "sg:orig_category":"Tischlereien",
    "sg:phone":"+43 3686 4785",
    "sg:postcode":"8966",
    "sg:province":"Steiermark",
    "wof:name":"Vrece & Pichler OHG",
    "wof:placetype":"venue"
},
  "geometry": {"coordinates":[13.8196287155,47.4196052551],"type":"Point"}
}