{
  "type": "Feature",
  "properties": {
    "addr:full":"Mayerbeerweg 3 Bad Gastein Salzburg 5640",
    "addr:housenumber":"3",
    "addr:postcode":"5640",
    "addr:street":"Mayerbeerweg;Salzburg",
    "iso:country":"AT",
    "sg:address":"Mayerbeerweg 3",
    "sg:city":"Bad Gastein",
    "sg:classifiers":[
        {
            "category":"Travel",
            "subcategory":"Hotels & Motels",
            "type":"Entertainment"
        }
    ],
    "sg:phone":"+43 6434 22530",
    "sg:postcode":"5640",
    "sg:province":"Salzburg",
    "wof:name":"Hotel Gisela",
    "wof:placetype":"venue"
},
  "geometry": {"coordinates":[13.1331090927,47.1131210327],"type":"Point"}
}