{
  "type": "Feature",
  "properties": {
    "iso:country":"AT",
    "sg:address":"Bahnhofstrasse 5",
    "sg:city":"Waizenkirchen",
    "sg:classifiers":[
        {
            "category":"Home & Garden",
            "subcategory":"Hardware",
            "type":"Retail Goods"
        }
    ],
    "sg:phone":"+43 7277 2434",
    "sg:postcode":"4730",
    "sg:province":"Ober\u00f6sterreich",
    "sg:tags":[
        "agricultural",
        "implement"
    ],
    "wof:name":"Herbert Fleischanderl",
    "wof:placetype":"venue"
},
  "geometry": {"coordinates":[13.8518733978,48.3295631409],"type":"Point"}
}