{
  "type": "Feature",
  "properties": {
    "addr:full":"Josef-Fuhs-Strasse 5 Bisamberg Nieder\u00f6sterreich 2102",
    "addr:housenumber":"5",
    "addr:postcode":"2102",
    "addr:street":"Josef-Fuhs-Strasse",
    "iso:country":"AT",
    "sg:address":"Josef-Fuhs-Strasse 5",
    "sg:city":"Bisamberg",
    "sg:classifiers":[
        {
            "category":"Parking",
            "subcategory":"Bicycle",
            "type":"Transportation"
        }
    ],
    "sg:phone":"+43 2262 75090",
    "sg:postcode":"2102",
    "sg:province":"Nieder\u00f6sterreich",
    "sg:tags":[
        "wheel",
        "cutting-off",
        "diamond"
    ],
    "sg:website":"troester.at",
    "wof:name":"Markus Tr\u00f6ster",
    "wof:placetype":"venue"
},
  "geometry": {"coordinates":[16.368927002,48.3457107544],"type":"Point"}
}