{
  "type": "Feature",
  "properties": {
    "iso:country":"AT",
    "sg:address":"Schubertpl 19",
    "sg:city":"Gm\u00fcnd",
    "sg:orig_category":"Steinmetzbetriebe",
    "sg:phone":"+43 2852 51352",
    "sg:postcode":"3950",
    "sg:province":"Nieder\u00f6sterreich",
    "wof:name":"Stein Center Gr\u00fcnsteidl",
    "wof:placetype":"venue"
},
  "geometry": {"coordinates":[14.972281456,48.7615432739],"type":"Point"}
}