{
  "type": "Feature",
  "properties": {
    "addr:full":"Untere Hauptstrasse 53 Trausdorf an der Wulka Burgenland 7061",
    "addr:housenumber":"53",
    "addr:postcode":"7061",
    "addr:street":"Untere Hauptstrasse",
    "iso:country":"AT",
    "sg:address":"Untere Hauptstrasse 53",
    "sg:city":"Trausdorf an der Wulka",
    "sg:classifiers":[
        {
            "category":"Building & Trades",
            "subcategory":"Plumbing",
            "type":"Services"
        }
    ],
    "sg:phone":"+43 2682 62026",
    "sg:postcode":"7061",
    "sg:province":"Burgenland",
    "sg:tags":[
        "supraregional",
        "gas"
    ],
    "sg:website":"karlich.at",
    "wof:name":"Karlich GmbH",
    "wof:placetype":"venue"
},
  "geometry": {"coordinates":[16.5624198914,47.8144683838],"type":"Point"}
}