{
  "type": "Feature",
  "properties": {
    "iso:country":"AT",
    "sg:address":"Lagerstr 9",
    "sg:city":"Bruck an der Leitha",
    "sg:orig_category":"Blumeneinzelhandel",
    "sg:phone":"+43 2162 647420",
    "sg:postcode":"2460",
    "sg:province":"Nieder\u00f6sterreich",
    "wof:name":"Kosak Blumen Nfg OHG",
    "wof:placetype":"venue"
},
  "geometry": {"coordinates":[16.7776203156,48.020740509],"type":"Point"}
}