{
  "type": "Feature",
  "properties": {
    "addr:full":"Richard-Strauss-Str 32 Wien Wien 1230",
    "addr:housenumber":"32",
    "addr:postcode":"1230",
    "addr:street":"Richard-Strauss-Str",
    "iso:country":"AT",
    "sg:address":"Richard-Strauss-Str 32",
    "sg:city":"Wien",
    "sg:orig_category":"Autobusunternehmen",
    "sg:phone":"+43 1 6152521",
    "sg:postcode":"1230",
    "sg:province":"Wien",
    "wof:name":"Neue Panorama Busreisen GmbH",
    "wof:placetype":"venue"
},
  "geometry": {"coordinates":[16.336101532,48.1384773254],"type":"Point"}
}