{
  "type": "Feature",
  "properties": {
    "iso:country":"AT",
    "sg:address":"Dauphinestr 89",
    "sg:city":"Linz",
    "sg:orig_category":"Wasseraufbereitung U -Reinigung",
    "sg:phone":"+43 4373 23052330",
    "sg:postcode":"4030",
    "sg:province":"Ober\u00f6sterreich",
    "wof:name":"Pecho Hans",
    "wof:placetype":"venue"
},
  "geometry": {"coordinates":[14.3013820648,48.2526779175],"type":"Point"}
}