{
  "type": "Feature",
  "properties": {
    "iso:country":"AT",
    "sg:city":"Ostermiething",
    "sg:orig_category":"Feuerwehren",
    "sg:phone":"+43 6278 6325",
    "sg:postcode":"5121",
    "sg:province":"Ober\u00f6sterreich",
    "wof:name":"Freiwillige Feuerwehr Ernsting",
    "wof:placetype":"venue"
},
  "geometry": {"coordinates":[12.8510437012,48.050743103],"type":"Point"}
}