{
  "type": "Feature",
  "properties": {
    "iso:country":"AT",
    "sg:address":"Haid\u00e4ckerstr 6",
    "sg:city":"Gerasdorf",
    "sg:orig_category":"Transportunternehmen",
    "sg:phone":"+43 2246 3097",
    "sg:postcode":"2201",
    "sg:province":"Nieder\u00f6sterreich",
    "wof:name":"Zettl Transport GmbH",
    "wof:placetype":"venue"
},
  "geometry": {"coordinates":[16.4488983154,48.3327713013],"type":"Point"}
}