{
  "type": "Feature",
  "properties": {
    "addr:full":"Weiserhofstr 18 Salzburg Salzburg 5020",
    "addr:housenumber":"18",
    "addr:postcode":"5020",
    "addr:street":"Weiserhofstr;Salzburg",
    "iso:country":"AT",
    "sg:address":"Weiserhofstr 18",
    "sg:city":"Salzburg",
    "sg:classifiers":[
        {
            "category":"Professional",
            "subcategory":"Computer Services",
            "type":"Services"
        }
    ],
    "sg:phone":"+43 4366 2871033",
    "sg:postcode":"5020",
    "sg:province":"Salzburg",
    "sg:tags":[
        "software"
    ],
    "wof:name":"SBS Software GesmbH",
    "wof:placetype":"venue"
},
  "geometry": {"coordinates":[13.0485515594,47.8140296936],"type":"Point"}
}