{
  "type": "Feature",
  "properties": {
    "addr:full":"Lurnfelder Str 54 Lieserbr\u00fccke K\u00e4rnten 9851",
    "addr:postcode":"9851",
    "addr:street":"Str 54 Lieserbruecke Kaernten",
    "iso:country":"AT",
    "sg:address":"Lurnfelder Str 54",
    "sg:city":"Lieserbr\u00fccke",
    "sg:orig_category":"Entsorgungen",
    "sg:phone":"+43 4762 42341",
    "sg:postcode":"9851",
    "sg:province":"K\u00e4rnten",
    "wof:name":"Staudacher Heinz Entsorgung",
    "wof:placetype":"venue"
},
  "geometry": {"coordinates":[13.4812335968,46.8264923096],"type":"Point"}
}