{
  "type": "Feature",
  "properties": {
    "addr:full":"Nr 61 Piesendorf Salzburg 5721",
    "addr:postcode":"5721",
    "addr:street":"Nr;Salzburg",
    "iso:country":"AT",
    "sg:address":"Nr 61",
    "sg:city":"Piesendorf",
    "sg:orig_category":"Maler, Anstreicher U Lackierer",
    "sg:phone":"+43 4365 497414",
    "sg:postcode":"5721",
    "sg:province":"Salzburg",
    "wof:name":"Hetz Rudolf",
    "wof:placetype":"venue"
},
  "geometry": {"coordinates":[6.2247400284,49.5246315002],"type":"Point"}
}