{
  "type": "Feature",
  "properties": {
    "addr:full":"Toni-Schruf-Str 40 Mitterdorf im M\u00fcrztal Steiermark 8662",
    "addr:housenumber":"40;im",
    "addr:postcode":"8662",
    "addr:street":"Toni-Schruf-Str;Muerztal Steiermark",
    "iso:country":"AT",
    "sg:address":"Toni-Schruf-Str 40",
    "sg:city":"Mitterdorf im M\u00fcrztal",
    "sg:orig_category":"Maschinenhandel",
    "sg:phone":"+43 4338 583774",
    "sg:postcode":"8662",
    "sg:province":"Steiermark",
    "wof:name":"Scheikl Maschinenhandel GmbH",
    "wof:placetype":"venue"
},
  "geometry": {"coordinates":[15.5187158585,47.5370330811],"type":"Point"}
}