{
  "type": "Feature",
  "properties": {
    "iso:country":"AT",
    "sg:address":"Dr Salzmann-Str 12",
    "sg:city":"Wels",
    "sg:orig_category":"Non-Classified Establishments",
    "sg:phone":"+43 7242 448250",
    "sg:postcode":"4600",
    "sg:province":"Ober\u00f6sterreich",
    "wof:name":"BEV-Vermessungsamt",
    "wof:placetype":"venue"
},
  "geometry": {"coordinates":[14.0208902359,48.158203125],"type":"Point"}
}