{
  "type": "Feature",
  "properties": {
    "addr:full":"S\u00fcdlandstr 1 Amstetten Nieder\u00f6sterreich 3300",
    "addr:housenumber":"1",
    "addr:postcode":"3300",
    "addr:street":"Suedlandstr;Niederoesterreich",
    "iso:country":"AT",
    "sg:address":"S\u00fcdlandstr 1",
    "sg:city":"Amstetten",
    "sg:orig_category":"Beton- U Betonsteinwerke, Transportbeton",
    "sg:phone":"+43 7472 6030",
    "sg:postcode":"3300",
    "sg:province":"Nieder\u00f6sterreich",
    "wof:name":"Lehner Josef Bmstr",
    "wof:placetype":"venue"
},
  "geometry": {"coordinates":[14.8706607819,48.1244812012],"type":"Point"}
}