{
  "type": "Feature",
  "properties": {
    "iso:country":"AT",
    "sg:address":"Schlo\u00df 1",
    "sg:city":"Herzogenburg",
    "sg:classifiers":[
        {
            "category":"Restaurant",
            "type":"Food & Drink"
        }
    ],
    "sg:phone":"+43 4327 8285827",
    "sg:postcode":"3130",
    "sg:province":"Nieder\u00f6sterreich",
    "wof:name":"Atelier f Restaurierungen J Jan Michalik",
    "wof:placetype":"venue"
},
  "geometry": {"coordinates":[15.6948232651,48.2849159241],"type":"Point"}
}