{
  "type": "Feature",
  "properties": {
    "addr:full":"Nr 217 Gleisdorf Steiermark 8200",
    "addr:postcode":"8200",
    "addr:street":"Nr 217",
    "iso:country":"AT",
    "sg:address":"Nr 217",
    "sg:city":"Gleisdorf",
    "sg:orig_category":"Elektronik",
    "sg:phone":"+43 3133 2038",
    "sg:postcode":"8200",
    "sg:province":"Steiermark",
    "wof:name":"Watzl Manfred Elektronik & Design",
    "wof:placetype":"venue"
},
  "geometry": {"coordinates":[166.9221496582,-0.5282999873],"type":"Point"}
}