{
  "type": "Feature",
  "properties": {
    "addr:full":"Roseggerstr 13b Hohenems Vorarlberg 6845",
    "addr:housenumber":"13b",
    "addr:postcode":"6845",
    "addr:street":"Roseggerstr",
    "iso:country":"AT",
    "sg:address":"Roseggerstr 13b",
    "sg:city":"Hohenems",
    "sg:orig_category":"Industrievertretungen",
    "sg:phone":"+43 5576 74941",
    "sg:postcode":"6845",
    "sg:province":"Vorarlberg",
    "wof:name":"Mathis Werner H GesmbH & Co KG",
    "wof:placetype":"venue"
},
  "geometry": {"coordinates":[9.6789321899,47.3590965271],"type":"Point"}
}