{
  "type": "Feature",
  "properties": {
    "iso:country":"AT",
    "sg:address":"R\u00f6cklbrunnstr. 41 ",
    "sg:city":"Salzburg",
    "sg:classifiers":[
        {
            "category":"Manufacturing",
            "subcategory":"Tools & Machinery",
            "type":"Manufacturing & Wholesale Goods"
        }
    ],
    "sg:phone":"+43 4366 28724250",
    "sg:postcode":"5020",
    "sg:province":"Salzburg",
    "sg:tags":[
        "environment",
        "equipment",
        "-"
    ],
    "wof:name":"WASSERTECHNIK GES.MBH & CO.KG",
    "wof:placetype":"venue"
},
  "geometry": {"coordinates":[13.0564908981,47.8129577637],"type":"Point"}
}