{
  "type": "Feature",
  "properties": {
    "addr:full":"Walfischg 6/2  Wien Wien 1010",
    "addr:housenumber":"6 / 2",
    "addr:postcode":"1010",
    "addr:street":"Walfischg",
    "iso:country":"AT",
    "sg:address":"Walfischg 6/2 ",
    "sg:city":"Wien",
    "sg:classifiers":[
        {
            "category":"Shopping",
            "type":"Retail Goods"
        }
    ],
    "sg:phone":"+43 4342 42418110",
    "sg:postcode":"1010",
    "sg:province":"Wien",
    "sg:tags":[
        "finished",
        "-",
        "metallic"
    ],
    "wof:name":"RAPPOLD SCHLEIFMITTEL INDUSTRIE GMBH",
    "wof:placetype":"venue"
},
  "geometry": {"coordinates":[16.3711128235,48.2032775879],"type":"Point"}
}