{
  "type": "Feature",
  "properties": {
    "addr:full":"Nr 71 Preitenegg K\u00e4rnten 9451",
    "addr:postcode":"9451",
    "addr:street":"Nr;Kaernten",
    "iso:country":"AT",
    "sg:address":"Nr 71",
    "sg:city":"Preitenegg",
    "sg:orig_category":"Feuerwehren",
    "sg:phone":"+43 4354 2122",
    "sg:postcode":"9451",
    "sg:province":"K\u00e4rnten",
    "wof:name":"Freiwillige Feuerwehr Preitenegg",
    "wof:placetype":"venue"
},
  "geometry": {"coordinates":[14.9251499176,46.9387931824],"type":"Point"}
}