{
  "type": "Feature",
  "properties": {
    "addr:full":"Nr 70 Wies Steiermark 8551",
    "addr:postcode":"8551",
    "addr:street":"Nr",
    "iso:country":"AT",
    "sg:address":"Nr 70",
    "sg:city":"Wies",
    "sg:orig_category":"Gemeinden",
    "sg:phone":"+43 4334 66423630",
    "sg:postcode":"8551",
    "sg:province":"Steiermark",
    "wof:name":"Gemeindeamt Wernersdorf",
    "wof:placetype":"venue"
},
  "geometry": {"coordinates":[15.2706108093,46.7187728882],"type":"Point"}
}