{
  "type": "Feature",
  "properties": {
    "addr:full":"Franz-Hochedlinger-Gasse 4 Wien Wien 1020",
    "addr:housenumber":"4",
    "addr:postcode":"1020",
    "addr:street":"Franz-Hochedlinger-Gasse",
    "iso:country":"AT",
    "sg:address":"Franz-Hochedlinger-Gasse 4",
    "sg:city":"Wien",
    "sg:classifiers":[
        {
            "category":"Manufacturing",
            "subcategory":"Furniture",
            "type":"Manufacturing & Wholesale Goods"
        }
    ],
    "sg:phone":"+43 1 2146752",
    "sg:postcode":"1020",
    "sg:province":"Wien",
    "sg:tags":[
        "design"
    ],
    "wof:name":"Herbert Koukal",
    "wof:placetype":"venue"
},
  "geometry": {"coordinates":[16.3723201752,48.2197494507],"type":"Point"}
}