{
  "type": "Feature",
  "properties": {
    "iso:country":"AT",
    "sg:address":"Wiener G 118",
    "sg:city":"Perchtoldsdorf",
    "sg:orig_category":"Autohandel",
    "sg:phone":"+43 1 86904150",
    "sg:postcode":"2380",
    "sg:province":"Nieder\u00f6sterreich",
    "wof:name":"Rabl GesmbH",
    "wof:placetype":"venue"
},
  "geometry": {"coordinates":[16.2760353088,48.1271705627],"type":"Point"}
}