{
  "type": "Feature",
  "properties": {
    "addr:full":"W\u00f6gersdorf 3 Pregarten Ober\u00f6sterreich 4230",
    "addr:housenumber":"3",
    "addr:postcode":"4230",
    "addr:street":"Woegersdorf",
    "iso:country":"AT",
    "sg:address":"W\u00f6gersdorf 3",
    "sg:city":"Pregarten",
    "sg:orig_category":"Appartements / Ferienwohnungen",
    "sg:phone":"+43 7236 3820",
    "sg:postcode":"4230",
    "sg:province":"Ober\u00f6sterreich",
    "wof:name":"Ferienhof Prangl",
    "wof:placetype":"venue"
},
  "geometry": {"coordinates":[14.5308532715,48.3548355103],"type":"Point"}
}