{
  "type": "Feature",
  "properties": {
    "addr:full":"Ungarnstr 15 Fehring Steiermark 8350",
    "addr:housenumber":"15",
    "addr:postcode":"8350",
    "addr:street":"Ungarnstr",
    "iso:country":"AT",
    "sg:address":"Ungarnstr 15",
    "sg:city":"Fehring",
    "sg:orig_category":"Zahntechnische Laboratorien",
    "sg:phone":"+43 3155 3344",
    "sg:postcode":"8350",
    "sg:province":"Steiermark",
    "wof:name":"Luckmann Dental OEG",
    "wof:placetype":"venue"
},
  "geometry": {"coordinates":[16.0139408112,46.9352607727],"type":"Point"}
}