{
  "type": "Feature",
  "properties": {
    "addr:full":"Pestalozzistr 59 Graz Steiermark 8010",
    "addr:housenumber":"59",
    "addr:postcode":"8010",
    "addr:street":"Pestalozzistr",
    "iso:country":"AT",
    "sg:address":"Pestalozzistr 59",
    "sg:city":"Graz",
    "sg:orig_category":"Familien / Beratung",
    "sg:phone":"+43 4331 68724650",
    "sg:postcode":"8010",
    "sg:province":"Steiermark",
    "wof:name":"Familienberatungs- u Mediationsstelle",
    "wof:placetype":"venue"
},
  "geometry": {"coordinates":[15.4381666183,47.0607452393],"type":"Point"}
}