{
  "type": "Feature",
  "properties": {
    "addr:full":"Leitnerstrasse 580 Puch Salzburg 5412",
    "addr:housenumber":"580",
    "addr:postcode":"5412",
    "addr:street":"Leitnerstrasse;Salzburg",
    "iso:country":"AT",
    "sg:address":"Leitnerstrasse 580",
    "sg:city":"Puch",
    "sg:classifiers":[
        {
            "category":"Government",
            "subcategory":"Department Of Motor Vehicles",
            "type":"Public Place"
        }
    ],
    "sg:phone":"+43 6245 807680",
    "sg:postcode":"5412",
    "sg:province":"Salzburg",
    "sg:tags":[
        "truck",
        "purpose"
    ],
    "wof:name":"Martin Wiesinger Internationale Transporte GmbH",
    "wof:placetype":"venue"
},
  "geometry": {"coordinates":[13.0951023102,47.7187614441],"type":"Point"}
}