{
  "type": "Feature",
  "properties": {
    "addr:full":"Nr 46 Wendling Ober\u00f6sterreich 4741",
    "addr:postcode":"4741",
    "addr:street":"Nr;Wendling",
    "iso:country":"AT",
    "sg:address":"Nr 46",
    "sg:city":"Wendling",
    "sg:orig_category":"Volksschulen",
    "sg:phone":"+43 4377 366101",
    "sg:postcode":"4741",
    "sg:province":"Ober\u00f6sterreich",
    "wof:name":"Volksschule",
    "wof:placetype":"venue"
},
  "geometry": {"coordinates":[13.6804189682,48.2285614014],"type":"Point"}
}