{
  "type": "Feature",
  "properties": {
    "addr:full":"Linzer Str 30 Bad Leonfelden Ober\u00f6sterreich 4190",
    "addr:housenumber":"30",
    "addr:postcode":"4190",
    "addr:street":"Linzer Str",
    "iso:country":"AT",
    "sg:address":"Linzer Str 30",
    "sg:city":"Bad Leonfelden",
    "sg:classifiers":[
        {
            "category":"Taxi",
            "type":"Transportation"
        }
    ],
    "sg:phone":"+43 4372 1387870",
    "sg:postcode":"4190",
    "sg:province":"Ober\u00f6sterreich",
    "sg:tags":[
        "personentransporte",
        "u"
    ],
    "wof:name":"Hochreither Alfred",
    "wof:placetype":"venue"
},
  "geometry": {"coordinates":[14.2947149277,48.5182113647],"type":"Point"}
}