{
  "type": "Feature",
  "properties": {
    "addr:full":"R\u00f6merstr 4 Hall in Tirol Tirol 6060",
    "addr:housenumber":"4",
    "addr:postcode":"6060",
    "addr:street":"Roemerstr;Tirol",
    "iso:country":"AT",
    "sg:address":"R\u00f6merstr 4",
    "sg:city":"Hall in Tirol",
    "sg:orig_category":"Tischlereien",
    "sg:phone":"+43 664 4001292",
    "sg:postcode":"6060",
    "sg:province":"Tirol",
    "wof:name":"Kaltenhauser Peter",
    "wof:placetype":"venue"
},
  "geometry": {"coordinates":[11.4692420959,47.2642745972],"type":"Point"}
}