{
  "type": "Feature",
  "properties": {
    "addr:full":"Dr.-Karl-Renner-Str 39 Neufeld an der Leitha Burgenland 2491",
    "addr:housenumber":"39",
    "addr:postcode":"2491",
    "addr:street":"Dr.-Karl-Renner-Str",
    "iso:country":"AT",
    "sg:address":"Dr.-Karl-Renner-Str 39",
    "sg:city":"Neufeld an der Leitha",
    "sg:orig_category":"Metallbau",
    "sg:phone":"+43 4326 24523480",
    "sg:postcode":"2491",
    "sg:province":"Burgenland",
    "wof:name":"Zeiler Ing Metallbau GmbH & Co KG Ing",
    "wof:placetype":"venue"
},
  "geometry": {"coordinates":[16.3784618378,47.8665618896],"type":"Point"}
}