{
  "type": "Feature",
  "properties": {
    "addr:full":"Graf-Starhemberg-G 43/5 Wien Wien 1040",
    "addr:housenumber":"43 / 5",
    "addr:postcode":"1040",
    "addr:street":"Graf-Starhemberg-G",
    "iso:country":"AT",
    "sg:address":"Graf-Starhemberg-G 43/5",
    "sg:city":"Wien",
    "sg:orig_category":"Ingenieurkonsulenten / Zivilingenieure",
    "sg:phone":"+43 1 5045333",
    "sg:postcode":"1040",
    "sg:province":"Wien",
    "wof:name":"Luggin Wilhelm Dipl-Ing",
    "wof:placetype":"venue"
},
  "geometry": {"coordinates":[16.3724899292,48.1874046326],"type":"Point"}
}