{
  "type": "Feature",
  "properties": {
    "iso:country":"AT",
    "sg:address":"Thanhoferstr. 8 ",
    "sg:city":"Linz",
    "sg:classifiers":[
        {
            "category":"Manufacturing",
            "subcategory":"Metals",
            "type":"Manufacturing & Wholesale Goods"
        }
    ],
    "sg:phone":"+43 4373 2370008",
    "sg:postcode":"4030",
    "sg:province":"Ober\u00f6sterreich",
    "sg:tags":[
        "metallurgy",
        "metalworking"
    ],
    "wof:name":"BRIX-ALU VERTRIEBSGES.MBH",
    "wof:placetype":"venue"
},
  "geometry": {"coordinates":[-82.9872589111,36.5964202881],"type":"Point"}
}