{
  "type": "Feature",
  "properties": {
    "iso:country":"AT",
    "sg:address":"Pergerstr 15",
    "sg:city":"Baden",
    "sg:orig_category":"Hauskrankenpflege / Heimhilfe",
    "sg:phone":"+43 2252 86260",
    "sg:postcode":"2500",
    "sg:province":"Nieder\u00f6sterreich",
    "wof:name":"Hilfswerk Baden - Hilfe und Pflege daheim",
    "wof:placetype":"venue"
},
  "geometry": {"coordinates":[16.2307739258,48.0065956116],"type":"Point"}
}