{
  "type": "Feature",
  "properties": {
    "addr:full":"Dominikanerbastei 19 Wien Wien 1010",
    "addr:housenumber":"19",
    "addr:postcode":"1010",
    "addr:street":"Dominikanerbastei",
    "iso:country":"AT",
    "sg:address":"Dominikanerbastei 19",
    "sg:city":"Wien",
    "sg:orig_category":"Psychotherapie",
    "sg:phone":"+43 1 5358413",
    "sg:postcode":"1010",
    "sg:province":"Wien",
    "wof:name":"Altzinger Fatma Mag",
    "wof:placetype":"venue"
},
  "geometry": {"coordinates":[16.3797626495,48.2110214233],"type":"Point"}
}