{
  "type": "Feature",
  "properties": {
    "addr:full":"Kircheng 2 Aigen im M\u00fchlkreis Ober\u00f6sterreich 4160",
    "addr:housenumber":"2",
    "addr:postcode":"4160",
    "addr:street":"Kircheng",
    "iso:country":"AT",
    "sg:address":"Kircheng 2",
    "sg:city":"Aigen im M\u00fchlkreis",
    "sg:classifiers":[
        {
            "category":"Professional",
            "subcategory":"Computer Services",
            "type":"Services"
        }
    ],
    "sg:phone":"+43 4372 816793",
    "sg:postcode":"4160",
    "sg:province":"Ober\u00f6sterreich",
    "sg:tags":[
        "software"
    ],
    "wof:name":"Information Engineering GmbH - Erik M. Pillinger",
    "wof:placetype":"venue"
},
  "geometry": {"coordinates":[13.970659256,48.6457290649],"type":"Point"}
}