{
  "type": "Feature",
  "properties": {
    "addr:full":"H\u00f6henstr 6 Telfs Tirol 6410",
    "addr:housenumber":"6",
    "addr:postcode":"6410",
    "addr:street":"Hoehenstr;Tirol",
    "iso:country":"AT",
    "sg:address":"H\u00f6henstr 6",
    "sg:city":"Telfs",
    "sg:orig_category":"Estriche",
    "sg:phone":"+43 5262 63560",
    "sg:postcode":"6410",
    "sg:province":"Tirol",
    "wof:name":"Wiedemann GesmbH & Co KG",
    "wof:placetype":"venue"
},
  "geometry": {"coordinates":[11.0755491257,47.3199424744],"type":"Point"}
}