{
  "type": "Feature",
  "properties": {
    "addr:full":"Leitenhaus 42 Annaberg Salzburg 5524",
    "addr:housenumber":"42",
    "addr:postcode":"5524",
    "addr:street":"Leitenhaus;Salzburg",
    "iso:country":"AT",
    "sg:address":"Leitenhaus 42",
    "sg:city":"Annaberg",
    "sg:orig_category":"Non-Classified Establishments",
    "sg:phone":"+43 6243 22270",
    "sg:postcode":"5524",
    "sg:province":"Salzburg",
    "wof:name":"Stra\u00dfenmeisterei Tennengau - St\u00fctzpunkt Tuftholz",
    "wof:placetype":"venue"
},
  "geometry": {"coordinates":[13.4122552872,47.5409889221],"type":"Point"}
}