{
  "type": "Feature",
  "properties": {
    "addr:full":"Brunecker Strasse 6 Innsbruck Tirol 6020",
    "addr:housenumber":"6",
    "addr:postcode":"6020",
    "addr:street":"Brunecker Strasse;Tirol",
    "iso:country":"AT",
    "sg:address":"Brunecker Strasse 6",
    "sg:city":"Innsbruck",
    "sg:classifiers":[
        {
            "category":"Manufacturing",
            "subcategory":"Paper Products",
            "type":"Manufacturing & Wholesale Goods"
        }
    ],
    "sg:phone":"+43 664 1840015",
    "sg:postcode":"6020",
    "sg:province":"Tirol",
    "sg:tags":[
        "painting",
        "art"
    ],
    "wof:name":"Alfred Lotter",
    "wof:placetype":"venue"
},
  "geometry": {"coordinates":[11.4007253647,47.2657623291],"type":"Point"}
}