{
  "type": "Feature",
  "properties": {
    "addr:full":"Anichstr.4  Innsbruck Tirol 6020",
    "addr:postcode":"6020",
    "addr:street":"Anichstr.4;Tirol",
    "iso:country":"AT",
    "sg:address":"Anichstr.4 ",
    "sg:city":"Innsbruck",
    "sg:classifiers":[
        {
            "category":"Shopping",
            "subcategory":"Clothing, Apparel, & Fashions",
            "type":"Retail Goods"
        }
    ],
    "sg:phone":"+43 4351 2588404",
    "sg:postcode":"6020",
    "sg:province":"Tirol",
    "sg:tags":[
        "clothes"
    ],
    "wof:name":"SCHMITT & LAIR GMBH",
    "wof:placetype":"venue"
},
  "geometry": {"coordinates":[11.3935508728,47.2652397156],"type":"Point"}
}