{
  "type": "Feature",
  "properties": {
    "iso:country":"AT",
    "sg:address":"Hauptstr 11",
    "sg:city":"Pressbaum",
    "sg:classifiers":[
        {
            "category":"Restaurant",
            "type":"Food & Drink"
        }
    ],
    "sg:phone":"+43 2233 56469",
    "sg:postcode":"3021",
    "sg:province":"Nieder\u00f6sterreich",
    "sg:tags":[
        "pizzeria"
    ],
    "wof:name":"Pizzeria-Ristorante Danijele",
    "wof:placetype":"venue"
},
  "geometry": {"coordinates":[16.090057373,48.1829147339],"type":"Point"}
}