{
  "type": "Feature",
  "properties": {
    "addr:full":"Marokkanerg 3 Wien Wien 1030",
    "addr:housenumber":"3",
    "addr:postcode":"1030",
    "addr:street":"Marokkanerg",
    "iso:country":"AT",
    "sg:address":"Marokkanerg 3",
    "sg:city":"Wien",
    "sg:orig_category":"\u00c3\u201erzte / F Allgemeinmedizin",
    "sg:phone":"+43 4314 069293",
    "sg:postcode":"1030",
    "sg:province":"Wien",
    "wof:name":"Frenzel Ingrid Dr",
    "wof:placetype":"venue"
},
  "geometry": {"coordinates":[16.3793640137,48.1999168396],"type":"Point"}
}