{
  "type": "Feature",
  "properties": {
    "addr:full":"Hauptstr 49 D\u00f6briach K\u00e4rnten 9873",
    "addr:housenumber":"49",
    "addr:postcode":"9873",
    "addr:street":"Hauptstr;Kaernten",
    "iso:country":"AT",
    "sg:address":"Hauptstr 49",
    "sg:city":"D\u00f6briach",
    "sg:orig_category":"Autoreparatur",
    "sg:phone":"+43 4246 7736",
    "sg:postcode":"9873",
    "sg:province":"K\u00e4rnten",
    "wof:name":"Tschernutter Wolfgang",
    "wof:placetype":"venue"
},
  "geometry": {"coordinates":[7.6419029236,48.0125808716],"type":"Point"}
}