{
  "type": "Feature",
  "properties": {
    "iso:country":"AT",
    "sg:address":"Taubergasse 23",
    "sg:city":"Wien",
    "sg:orig_category":"Bottle Brushes",
    "sg:phone":"+43 1 4864603",
    "sg:postcode":"1170",
    "sg:province":"Wien",
    "wof:name":"Norbert Meier",
    "wof:placetype":"venue"
},
  "geometry": {"coordinates":[16.3268051147,48.2168655396],"type":"Point"}
}