{
  "type": "Feature",
  "properties": {
    "iso:country":"AT",
    "sg:address":"Gumppstr 4",
    "sg:city":"Innsbruck",
    "sg:orig_category":"Detekteien",
    "sg:phone":"+43 4351 2272705",
    "sg:postcode":"6020",
    "sg:province":"Tirol",
    "sg:website":"leitner-gmbh.at",
    "wof:name":"Leitner Sicherheits- u \u00dcberwachungstechnik",
    "wof:placetype":"venue"
},
  "geometry": {"coordinates":[11.4090108871,47.2639465332],"type":"Point"}
}