{
  "type": "Feature",
  "properties": {
    "addr:full":"Reinprechtsdorfer Strasse 46 Wien Wien 1050",
    "addr:housenumber":"46",
    "addr:postcode":"1050",
    "addr:street":"Reinprechtsdorfer Strasse",
    "iso:country":"AT",
    "sg:address":"Reinprechtsdorfer Strasse 46",
    "sg:city":"Wien",
    "sg:classifiers":[
        {
            "category":"Utilities",
            "subcategory":"Mobile Phone",
            "type":"Services"
        }
    ],
    "sg:phone":"+43 1 546470",
    "sg:postcode":"1050",
    "sg:province":"Wien",
    "sg:tags":[
        "battery",
        "operated",
        "clock"
    ],
    "wof:name":"Ostersetzer & Co Ges.m.b.H.",
    "wof:placetype":"venue"
},
  "geometry": {"coordinates":[16.3536624908,48.1863021851],"type":"Point"}
}