{
  "type": "Feature",
  "properties": {
    "addr:full":"Pegasusweg 13 Linz Ober\u00f6sterreich 4030",
    "addr:housenumber":"13",
    "addr:postcode":"4030",
    "addr:street":"Pegasusweg",
    "iso:country":"AT",
    "sg:address":"Pegasusweg 13",
    "sg:city":"Linz",
    "sg:orig_category":"Psychologen",
    "sg:phone":"+43 732 943372",
    "sg:postcode":"4030",
    "sg:province":"Ober\u00f6sterreich",
    "wof:name":"Winkler Otto Mag",
    "wof:placetype":"venue"
},
  "geometry": {"coordinates":[14.3581848145,48.257938385],"type":"Point"}
}