{
  "type": "Feature",
  "properties": {
    "iso:country":"AT",
    "sg:address":"Triester Str 162",
    "sg:city":"Feldkirchen",
    "sg:orig_category":"Autohandel",
    "sg:phone":"+43 316 295260",
    "sg:postcode":"8073",
    "sg:province":"Steiermark",
    "wof:name":"Zeschko Werner",
    "wof:placetype":"venue"
},
  "geometry": {"coordinates":[15.4506883621,46.9999847412],"type":"Point"}
}