{
  "type": "Feature",
  "properties": {
    "addr:full":"Obere Landstr 79 Furth Nieder\u00f6sterreich 3511",
    "addr:housenumber":"79",
    "addr:postcode":"3511",
    "addr:street":"Obere Landstr",
    "iso:country":"AT",
    "sg:address":"Obere Landstr 79",
    "sg:city":"Furth",
    "sg:orig_category":"Unternehmensberatung",
    "sg:phone":"+43 2732 795160",
    "sg:postcode":"3511",
    "sg:province":"Nieder\u00f6sterreich",
    "wof:name":"HL-Sportmanagement & Consulting GmbH",
    "wof:placetype":"venue"
},
  "geometry": {"coordinates":[15.6125049591,48.374168396],"type":"Point"}
}