{
  "type": "Feature",
  "properties": {
    "iso:country":"AT",
    "sg:address":"Steinm\u00fcllergasse 46c",
    "sg:city":"Wien",
    "sg:classifiers":[
        {
            "category":"Utilities",
            "subcategory":"Fuel Oil & Lpg",
            "type":"Services"
        }
    ],
    "sg:phone":"+43 1 4858788",
    "sg:postcode":"1160",
    "sg:province":"Wien",
    "sg:tags":[
        "dental",
        "product"
    ],
    "wof:name":"Ralph Fibinger",
    "wof:placetype":"venue"
},
  "geometry": {"coordinates":[16.2961292267,48.214931488],"type":"Point"}
}