{
  "type": "Feature",
  "properties": {
    "addr:full":"Weidach 374b Leutasch Tirol 6105",
    "addr:housenumber":"374b",
    "addr:postcode":"6105",
    "addr:street":"Weidach;Tirol",
    "iso:country":"AT",
    "sg:address":"Weidach 374b",
    "sg:city":"Leutasch",
    "sg:orig_category":"Appartements / Ferienwohnungen",
    "sg:phone":"+43 5214 6621",
    "sg:postcode":"6105",
    "sg:province":"Tirol",
    "wof:name":"Haus Bergfreund",
    "wof:placetype":"venue"
},
  "geometry": {"coordinates":[11.1513023376,47.3726921082],"type":"Point"}
}