{
  "type": "Feature",
  "properties": {
    "iso:country":"AT",
    "sg:address":"Mexikopl 20",
    "sg:city":"Wien",
    "sg:orig_category":"Damenmoden",
    "sg:phone":"+43 1 7280486",
    "sg:postcode":"1020",
    "sg:province":"Wien",
    "wof:name":"Silberberg & Co - Markus Spiegel",
    "wof:placetype":"venue"
},
  "geometry": {"coordinates":[16.4038639069,48.2237625122],"type":"Point"}
}