{
  "type": "Feature",
  "properties": {
    "iso:country":"AT",
    "sg:address":"Badweg 1",
    "sg:city":"Frankenmarkt",
    "sg:classifiers":[
        {
            "category":"Manufacturing",
            "subcategory":"Metals",
            "type":"Manufacturing & Wholesale Goods"
        }
    ],
    "sg:phone":"+43 4376 8463380",
    "sg:postcode":"4890",
    "sg:province":"Ober\u00f6sterreich",
    "sg:tags":[
        "metallurgy",
        "metalworking"
    ],
    "wof:name":"LACHER MASCHINENBAU GMBH & CO. KG",
    "wof:placetype":"venue"
},
  "geometry": {"coordinates":[13.4109392166,47.9832572937],"type":"Point"}
}