{
  "type": "Feature",
  "properties": {
    "iso:country":"AT",
    "sg:address":"Hauptpl 13",
    "sg:city":"Wiener Neustadt",
    "sg:orig_category":"Damenmoden",
    "sg:phone":"+43 2622 86021",
    "sg:postcode":"2700",
    "sg:province":"Nieder\u00f6sterreich",
    "wof:name":"Esprit - Sisley",
    "wof:placetype":"venue"
},
  "geometry": {"coordinates":[16.2434978485,47.8135528564],"type":"Point"}
}