{
  "type": "Feature",
  "properties": {
    "iso:country":"AT",
    "sg:address":"Lana 3",
    "sg:city":"Kals am Gro\u00dfglockner",
    "sg:orig_category":"Pensionen / Privatzimmer",
    "sg:phone":"+43 4876 8282",
    "sg:postcode":"9981",
    "sg:province":"Tirol",
    "wof:name":"Fremdenheim Lanahof",
    "wof:placetype":"venue"
},
  "geometry": {"coordinates":[12.6364002228,46.9959259033],"type":"Point"}
}