{
  "type": "Feature",
  "properties": {
    "addr:full":"Ginzldorf 13 St. Roman Ober\u00f6sterreich 4793",
    "addr:housenumber":"13",
    "addr:postcode":"4793",
    "addr:street":"Ginzldorf;St. Roman Oberoesterreich",
    "iso:country":"AT",
    "sg:address":"Ginzldorf 13",
    "sg:city":"St. Roman",
    "sg:orig_category":"Behinderungen / Leben Mit Behinderungen",
    "sg:phone":"+43 4377 166261",
    "sg:postcode":"4793",
    "sg:province":"Ober\u00f6sterreich",
    "wof:name":"\u00f6ZIV - \u00f6sterreichischer Zivil-Invalidenverband",
    "wof:placetype":"venue"
},
  "geometry": {"coordinates":[13.6531324387,48.5000305176],"type":"Point"}
}