{
  "type": "Feature",
  "properties": {
    "iso:country":"AT",
    "sg:address":"Platzl 11",
    "sg:city":"Rietz",
    "sg:orig_category":"Lebensmittel / Einzelhandel",
    "sg:phone":"+43 5262 62613",
    "sg:postcode":"6421",
    "sg:province":"Tirol",
    "wof:name":"Spar-Markt Inh Martin Walch",
    "wof:placetype":"venue"
},
  "geometry": {"coordinates":[11.0290136337,47.2858314514],"type":"Point"}
}