{
  "type": "Feature",
  "properties": {
    "addr:full":"Bergmanng 10 Wallern im Burgenland Burgenland 7151",
    "addr:housenumber":"10",
    "addr:postcode":"7151",
    "addr:street":"Bergmanng",
    "iso:country":"AT",
    "sg:address":"Bergmanng 10",
    "sg:city":"Wallern im Burgenland",
    "sg:orig_category":"Baumeister",
    "sg:phone":"+43 4321 7422350",
    "sg:postcode":"7151",
    "sg:province":"Burgenland",
    "sg:website":"altenthaler.at",
    "wof:name":"Altenthaler Bau GmbH",
    "wof:placetype":"venue"
},
  "geometry": {"coordinates":[16.9429359436,47.730556488],"type":"Point"}
}