{
  "type": "Feature",
  "properties": {
    "iso:country":"AT",
    "sg:address":"Hauptstr 2",
    "sg:city":"Blumau-Neuri\u00dfhof",
    "sg:orig_category":"Gemeinden",
    "sg:phone":"+43 2628 482900",
    "sg:postcode":"2602",
    "sg:province":"Nieder\u00f6sterreich",
    "wof:name":"Gemeinde Blumau-Neuri\u00dfhof",
    "wof:placetype":"venue"
},
  "geometry": {"coordinates":[16.3020076752,47.9262695312],"type":"Point"}
}