{
  "type": "Feature",
  "properties": {
    "addr:full":"Bahnhofstr 37 Ried im Innkreis Ober\u00f6sterreich 4910",
    "addr:housenumber":"37",
    "addr:postcode":"4910",
    "addr:street":"Bahnhofstr",
    "iso:country":"AT",
    "sg:address":"Bahnhofstr 37",
    "sg:city":"Ried im Innkreis",
    "sg:orig_category":"Zahntechnische Laboratorien",
    "sg:phone":"+43 7752 84392",
    "sg:postcode":"4910",
    "sg:province":"Ober\u00f6sterreich",
    "wof:name":"Raminger Norbert - Zahntechnikermeister",
    "wof:placetype":"venue"
},
  "geometry": {"coordinates":[13.4892997742,48.2045822144],"type":"Point"}
}