{
  "type": "Feature",
  "properties": {
    "iso:country":"AT",
    "sg:address":"Zaimweg 5",
    "sg:city":"Radstadt",
    "sg:orig_category":"Beton- U Betonsteinwerke",
    "sg:phone":"+43 6452 7198",
    "sg:postcode":"5550",
    "sg:province":"Salzburg",
    "wof:name":"Deisl Tauernbeton GesmbH",
    "wof:placetype":"venue"
},
  "geometry": {"coordinates":[13.5093603134,47.391910553],"type":"Point"}
}