{
  "type": "Feature",
  "properties": {
    "addr:full":"Leberstr 96 Wien Wien 1110",
    "addr:housenumber":"96",
    "addr:postcode":"1110",
    "addr:street":"Leberstr",
    "iso:country":"AT",
    "sg:address":"Leberstr 96",
    "sg:city":"Wien",
    "sg:orig_category":"Bauunternehmen",
    "sg:phone":"+43 1 4802606",
    "sg:postcode":"1110",
    "sg:province":"Wien",
    "wof:name":"STRELA Bau GesmbH",
    "wof:placetype":"venue"
},
  "geometry": {"coordinates":[16.4081668854,48.1716690063],"type":"Point"}
}