{
  "type": "Feature",
  "properties": {
    "addr:full":"Wiener Str 47 Petzenkirchen Nieder\u00f6sterreich 3252",
    "addr:postcode":"3252",
    "addr:street":"Niederoesterreich",
    "iso:country":"AT",
    "sg:address":"Wiener Str 47",
    "sg:city":"Petzenkirchen",
    "sg:orig_category":"Lebensmittel / Einzelhandel",
    "sg:phone":"+43 4374 1652146",
    "sg:postcode":"3252",
    "sg:province":"Nieder\u00f6sterreich",
    "wof:name":"Postservicestelle Petzenkirchen",
    "wof:placetype":"venue"
},
  "geometry": {"coordinates":[15.1571063995,48.1467971802],"type":"Point"}
}