{
  "type": "Feature",
  "properties": {
    "iso:country":"AT",
    "sg:address":"Valierg 14",
    "sg:city":"Innsbruck",
    "sg:orig_category":"Putze",
    "sg:phone":"+43 512 3428800",
    "sg:postcode":"6020",
    "sg:province":"Tirol",
    "wof:name":"STO GesmbH",
    "wof:placetype":"venue"
},
  "geometry": {"coordinates":[11.4295949936,47.2682533264],"type":"Point"}
}