{
  "type": "Feature",
  "properties": {
    "addr:full":"Klagenfurter Str 10 Villach K\u00e4rnten 9500",
    "addr:housenumber":"10",
    "addr:postcode":"9500",
    "addr:street":"Str;Kaernten",
    "iso:country":"AT",
    "sg:address":"Klagenfurter Str 10",
    "sg:city":"Villach",
    "sg:orig_category":"Bandagen U Bandagisten",
    "sg:phone":"+43 4342 4224154",
    "sg:postcode":"9500",
    "sg:province":"K\u00e4rnten",
    "wof:name":"SEPIN ORTHOP\u00e4DIETECHNIK SANIT\u00e4TSHAUS GesmbH",
    "wof:placetype":"venue"
},
  "geometry": {"coordinates":[13.8503303528,46.6170196533],"type":"Point"}
}