{
  "type": "Feature",
  "properties": {
    "iso:country":"AT",
    "sg:address":"Reikersdorf 14",
    "sg:city":"St. Peter am Hart",
    "sg:orig_category":"Steuerungstechnik",
    "sg:phone":"+43 7722 631900",
    "sg:postcode":"4963",
    "sg:province":"Ober\u00f6sterreich",
    "wof:name":"Lutz Volkmar Dipl-Ing Dr",
    "wof:placetype":"venue"
},
  "geometry": {"coordinates":[13.0719852448,48.2608642578],"type":"Point"}
}