{
  "type": "Feature",
  "properties": {
    "iso:country":"AT",
    "sg:address":"H\u00f6flerweg 13",
    "sg:city":"Mittelberg",
    "sg:orig_category":"Bergbahnen",
    "sg:phone":"+43 5517 6430",
    "sg:postcode":"6993",
    "sg:province":"Vorarlberg",
    "wof:name":"Ahornlift",
    "wof:placetype":"venue"
},
  "geometry": {"coordinates":[10.1620397568,47.3287506104],"type":"Point"}
}