{
  "type": "Feature",
  "properties": {
    "iso:country":"AT",
    "sg:address":"Oberg\u00e4u 177",
    "sg:city":"Golling an der Salzach",
    "sg:orig_category":"Wasserschadensanierung, Abdichtungen, Mauertrockenlegungen, Entfeuchtungen",
    "sg:phone":"+43 6244 75410",
    "sg:postcode":"5440",
    "sg:province":"Salzburg",
    "sg:website":"mitterbauer.com",
    "wof:name":"Mitterbauer GmbH",
    "wof:placetype":"venue"
},
  "geometry": {"coordinates":[13.2115449905,47.5899581909],"type":"Point"}
}