{
  "type": "Feature",
  "properties": {
    "iso:country":"AT",
    "sg:address":"Schiffsl\u00e4nde 3",
    "sg:city":"Gmunden",
    "sg:orig_category":"Steuerberatung",
    "sg:phone":"+43 4376 1263837",
    "sg:postcode":"4810",
    "sg:province":"Ober\u00f6sterreich",
    "sg:website":"derfler-wt.at",
    "wof:name":"Derfler Rudolf Mag",
    "wof:placetype":"venue"
},
  "geometry": {"coordinates":[13.802611351,47.9176559448],"type":"Point"}
}