{
  "type": "Feature",
  "properties": {
    "addr:full":"Walgaustr 81 Th\u00fcringen Vorarlberg 6712",
    "addr:housenumber":"81",
    "addr:postcode":"6712",
    "addr:street":"Walgaustr",
    "iso:country":"AT",
    "sg:address":"Walgaustr 81",
    "sg:city":"Th\u00fcringen",
    "sg:orig_category":"Bodenverlegung",
    "sg:phone":"+43 4355 503157",
    "sg:postcode":"6712",
    "sg:province":"Vorarlberg",
    "wof:name":"Tschann Belagsverleger u Heimtextilien GesmbH",
    "wof:placetype":"venue"
},
  "geometry": {"coordinates":[9.7572822571,47.1986465454],"type":"Point"}
}