{
  "type": "Feature",
  "properties": {
    "iso:country":"AT",
    "sg:address":"Johann-Steinb\u00f6ck-Str. 2",
    "sg:city":"Brunn am Gebirge",
    "sg:classifiers":[
        {
            "category":"Autos & Motor Vehicles",
            "subcategory":"Automobile Sales",
            "type":"Retail Goods"
        }
    ],
    "sg:phone":"+43 4322 3635501",
    "sg:postcode":"2345",
    "sg:province":"Nieder\u00f6sterreich",
    "sg:tags":[
        "industrial"
    ],
    "wof:name":"KLEPP FAHRERSITZE GMBH",
    "wof:placetype":"venue"
},
  "geometry": {"coordinates":[16.3078613281,48.1109657288],"type":"Point"}
}