{
  "type": "Feature",
  "properties": {
    "addr:full":"Botanikerstr 9/1 Innsbruck Tirol 6020",
    "addr:housenumber":"9 / 1",
    "addr:postcode":"6020",
    "addr:street":"Botanikerstr;Tirol",
    "iso:country":"AT",
    "sg:address":"Botanikerstr 9/1",
    "sg:city":"Innsbruck",
    "sg:orig_category":"Ingenieurkonsulenten / Zivilingenieure",
    "sg:phone":"+43 512 2953000",
    "sg:postcode":"6020",
    "sg:province":"Tirol",
    "wof:name":"Schwaninger Dieter Dipl-Ing",
    "wof:placetype":"venue"
},
  "geometry": {"coordinates":[11.3816242218,47.2678031921],"type":"Point"}
}