{
  "type": "Feature",
  "properties": {
    "addr:full":"Riegersburg 202 Riegersburg Steiermark 8333",
    "addr:housenumber":"202",
    "addr:postcode":"8333",
    "addr:street":"Riegersburg",
    "iso:country":"AT",
    "sg:address":"Riegersburg 202",
    "sg:city":"Riegersburg",
    "sg:classifiers":[
        {
            "category":"Manufacturing",
            "subcategory":"Motor Vehicles & Parts",
            "type":"Manufacturing & Wholesale Goods"
        }
    ],
    "sg:phone":"+43 3153 7463",
    "sg:postcode":"8333",
    "sg:province":"Steiermark",
    "sg:tags":[
        "component",
        "banister"
    ],
    "sg:website":"ortauf.at",
    "wof:name":"Johann Ortauf",
    "wof:placetype":"venue"
},
  "geometry": {"coordinates":[15.9359741211,47.0009155273],"type":"Point"}
}