{
  "type": "Feature",
  "properties": {
    "iso:country":"AT",
    "sg:address":"Neue G 11",
    "sg:city":"Rust",
    "sg:orig_category":"Appartements / Ferienwohnungen",
    "sg:phone":"+43 2685 6550",
    "sg:postcode":"7071",
    "sg:province":"Burgenland",
    "wof:name":"Wiedenhofer Hedwig",
    "wof:placetype":"venue"
},
  "geometry": {"coordinates":[16.6686382294,47.8017959595],"type":"Point"}
}