{
  "type": "Feature",
  "properties": {
    "iso:country":"AT",
    "sg:address":"Franz Herndl-Weg 3",
    "sg:city":"Grein",
    "sg:orig_category":"Telefonmarketing",
    "sg:phone":"+43 7268 75550",
    "sg:postcode":"4360",
    "sg:province":"Ober\u00f6sterreich",
    "wof:name":"Audio Sattler professionelle Ansagen",
    "wof:placetype":"venue"
},
  "geometry": {"coordinates":[14.8566379547,48.2299842834],"type":"Point"}
}