{
  "type": "Feature",
  "properties": {
    "addr:full":"Naglerg 2 Wien Wien 1010",
    "addr:housenumber":"2",
    "addr:postcode":"1010",
    "addr:street":"Naglerg",
    "iso:country":"AT",
    "sg:address":"Naglerg 2",
    "sg:city":"Wien",
    "sg:orig_category":"Botschaften",
    "sg:phone":"+43 1 5332771",
    "sg:postcode":"1010",
    "sg:province":"Wien",
    "wof:name":"Botschaft der Republik Island",
    "wof:placetype":"venue"
},
  "geometry": {"coordinates":[16.3686141968,48.2097702026],"type":"Point"}
}