{
  "type": "Feature",
  "properties": {
    "addr:full":"Hobelweg 20  Pucking Ober\u00f6sterreich 4055",
    "addr:housenumber":"20",
    "addr:postcode":"4055",
    "addr:street":"Hobelweg",
    "iso:country":"AT",
    "sg:address":"Hobelweg 20 ",
    "sg:city":"Pucking",
    "sg:classifiers":[
        {
            "category":"Bus Stop",
            "subcategory":"None",
            "type":"Transportation"
        }
    ],
    "sg:phone":"+43 7229 661770",
    "sg:postcode":"4055",
    "sg:province":"Ober\u00f6sterreich",
    "sg:tags":[
        "absorbing",
        "litter",
        "granule",
        "cat"
    ],
    "wof:name":"CONCEPT Trading Handelsges.m.b.H.",
    "wof:placetype":"venue"
},
  "geometry": {"coordinates":[14.2089576721,48.1935653687],"type":"Point"}
}