{
  "type": "Feature",
  "properties": {
    "addr:full":"Sechsschimmelg 7/45 Wien Wien 1090",
    "addr:housenumber":"7 / 45",
    "addr:postcode":"1090",
    "addr:street":"Sechsschimmelg",
    "iso:country":"AT",
    "sg:address":"Sechsschimmelg 7/45",
    "sg:city":"Wien",
    "sg:orig_category":"Rauchfangsanierungen U -Ausschleifungen, Kaminsanierungen U -Ausschleifereien",
    "sg:phone":"+43 1 31900250",
    "sg:postcode":"1090",
    "sg:province":"Wien",
    "wof:name":"Tomicich Spirale",
    "wof:placetype":"venue"
},
  "geometry": {"coordinates":[16.351474762,48.2234115601],"type":"Point"}
}