{
  "type": "Feature",
  "properties": {
    "addr:full":"Alszeile 74/20 Wien Wien 1170",
    "addr:housenumber":"74 / 20",
    "addr:postcode":"1170",
    "addr:street":"Alszeile",
    "iso:country":"AT",
    "sg:address":"Alszeile 74/20",
    "sg:city":"Wien",
    "sg:orig_category":"Waren Aller Art",
    "sg:phone":"+43 1 4898555",
    "sg:postcode":"1170",
    "sg:province":"Wien",
    "wof:name":"Mampfi Mampfi Imbi\u00dfstuben BetriebsgesmbH",
    "wof:placetype":"venue"
},
  "geometry": {"coordinates":[16.30377388,48.2294960022],"type":"Point"}
}