{
  "type": "Feature",
  "properties": {
    "iso:country":"AT",
    "sg:address":"Herreng 3",
    "sg:city":"Retz",
    "sg:orig_category":"Elektroinstallationsunternehmen",
    "sg:phone":"+43 2942 23300",
    "sg:postcode":"2070",
    "sg:province":"Nieder\u00f6sterreich",
    "wof:name":"J\u00e4ger Reinhard",
    "wof:placetype":"venue"
},
  "geometry": {"coordinates":[15.9526758194,48.7570152283],"type":"Point"}
}