{
  "type": "Feature",
  "properties": {
    "addr:full":"Michelndorf 11 Atzenbrugg Nieder\u00f6sterreich 3452",
    "addr:housenumber":"11",
    "addr:postcode":"3452",
    "addr:street":"Michelndorf",
    "iso:country":"AT",
    "sg:address":"Michelndorf 11",
    "sg:city":"Atzenbrugg",
    "sg:classifiers":[
        {
            "category":"Home & Garden",
            "subcategory":"Hardware",
            "type":"Retail Goods"
        }
    ],
    "sg:phone":"+43 2275 5566",
    "sg:postcode":"3452",
    "sg:province":"Nieder\u00f6sterreich",
    "sg:tags":[
        "agricultural",
        "implement"
    ],
    "sg:website":"agrifarm-maschinen.com",
    "wof:name":"AGRI FARM Maschinenbauges.m.b.H.",
    "wof:placetype":"venue"
},
  "geometry": {"coordinates":[15.9042654037,48.2924804688],"type":"Point"}
}