{
  "type": "Feature",
  "properties": {
    "iso:country":"AT",
    "sg:address":"Wiesenweg 140",
    "sg:city":"Rohrmoos-Untertal",
    "sg:classifiers":[
        {
            "category":"Travel",
            "subcategory":"Hotels & Motels",
            "type":"Entertainment"
        }
    ],
    "sg:phone":"+43 4336 87612050",
    "sg:postcode":"8971",
    "sg:province":"Steiermark",
    "wof:name":"Hotel Sch\u00fctterhof",
    "wof:placetype":"venue"
},
  "geometry": {"coordinates":[13.6753616333,47.3862915039],"type":"Point"}
}