{
  "type": "Feature",
  "properties": {
    "addr:full":"Theaterplatz 1 Klagenfurt K\u00e4rnten 9020",
    "addr:housenumber":"1",
    "addr:postcode":"9020",
    "addr:street":"Theaterplatz;Kaernten",
    "iso:country":"AT",
    "sg:address":"Theaterplatz 1",
    "sg:city":"Klagenfurt",
    "sg:orig_category":"Observation Systems",
    "sg:phone":"+43 463 5093000",
    "sg:postcode":"9020",
    "sg:province":"K\u00e4rnten",
    "sg:website":"detektiv.at",
    "wof:name":"BLUE MOON Detektiv- und Sicherheitsagentur",
    "wof:placetype":"venue"
},
  "geometry": {"coordinates":[14.304517746,46.6264343262],"type":"Point"}
}