{
  "type": "Feature",
  "properties": {
    "addr:full":"Fr\u00f6sau 84 Sinabelkirchen Steiermark 8261",
    "addr:housenumber":"84",
    "addr:postcode":"8261",
    "addr:street":"Froesau",
    "iso:country":"AT",
    "sg:address":"Fr\u00f6sau 84",
    "sg:city":"Sinabelkirchen",
    "sg:classifiers":[
        {
            "category":"Home & Garden",
            "subcategory":"Carpets & Floor Coverings",
            "type":"Retail Goods"
        }
    ],
    "sg:phone":"+43 3118 2155",
    "sg:postcode":"8261",
    "sg:province":"Steiermark",
    "sg:tags":[
        "screed",
        "floating"
    ],
    "wof:name":"Bierbauer Bau KEG",
    "wof:placetype":"venue"
},
  "geometry": {"coordinates":[15.8282032013,47.1025505066],"type":"Point"}
}