{
  "type": "Feature",
  "properties": {
    "addr:full":"Haller Str 202 Innsbruck Tirol 6020",
    "addr:housenumber":"202",
    "addr:postcode":"6020",
    "addr:street":"Str;Tirol",
    "iso:country":"AT",
    "sg:address":"Haller Str 202",
    "sg:city":"Innsbruck",
    "sg:orig_category":"Raumausstattung",
    "sg:phone":"+43 512 246430",
    "sg:postcode":"6020",
    "sg:province":"Tirol",
    "wof:name":"Perle Textil GesmbH",
    "wof:placetype":"venue"
},
  "geometry": {"coordinates":[11.4415769577,47.2767562866],"type":"Point"}
}