{
  "type": "Feature",
  "properties": {
    "iso:country":"AT",
    "sg:address":"Wiener Str 4",
    "sg:city":"Horn",
    "sg:orig_category":"Museen / Ausstellungen",
    "sg:phone":"+43 2982 2372",
    "sg:postcode":"3580",
    "sg:province":"Nieder\u00f6sterreich",
    "wof:name":"H\u00f6barth- und Madermuseum",
    "wof:placetype":"venue"
},
  "geometry": {"coordinates":[15.6612663269,48.6646766663],"type":"Point"}
}