{
  "type": "Feature",
  "properties": {
    "iso:country":"AT",
    "sg:address":"Bundesstr 29",
    "sg:city":"Schwarzenau",
    "sg:orig_category":"Tischlereien",
    "sg:phone":"+43 2849 2245",
    "sg:postcode":"3900",
    "sg:province":"Nieder\u00f6sterreich",
    "wof:name":"Steinhauser Brigitta",
    "wof:placetype":"venue"
},
  "geometry": {"coordinates":[15.2566289902,48.743724823],"type":"Point"}
}