{
  "type": "Feature",
  "properties": {
    "addr:full":"Ringg 31 St. Peter-Freienstein Steiermark 8792",
    "addr:housenumber":"31",
    "addr:postcode":"8792",
    "addr:street":"Ringg",
    "iso:country":"AT",
    "sg:address":"Ringg 31",
    "sg:city":"St. Peter-Freienstein",
    "sg:orig_category":"Elektrotechnik",
    "sg:phone":"+43 4338 4224502",
    "sg:postcode":"8792",
    "sg:province":"Steiermark",
    "wof:name":"ETEKLA - Klammer Johann Handelsagentur",
    "wof:placetype":"venue"
},
  "geometry": {"coordinates":[15.0324897766,47.3988990784],"type":"Point"}
}