{
  "type": "Feature",
  "properties": {
    "addr:full":"Schulstr 25 Felixdorf Nieder\u00f6sterreich 2603",
    "addr:housenumber":"25",
    "addr:postcode":"2603",
    "addr:street":"Schulstr",
    "iso:country":"AT",
    "sg:address":"Schulstr 25",
    "sg:city":"Felixdorf",
    "sg:orig_category":"Installationsunternehmen",
    "sg:phone":"+43 4326 2863776",
    "sg:postcode":"2603",
    "sg:province":"Nieder\u00f6sterreich",
    "wof:name":"Weninger G\u00fcnter",
    "wof:placetype":"venue"
},
  "geometry": {"coordinates":[16.2446689606,47.8789405823],"type":"Point"}
}