{
  "type": "Feature",
  "properties": {
    "iso:country":"AT",
    "sg:city":"Gurk",
    "sg:orig_category":"Non-Classified Establishments",
    "sg:phone":"+43 4266 8148",
    "sg:postcode":"9342",
    "sg:province":"K\u00e4rnten",
    "wof:name":"Pfarramt",
    "wof:placetype":"venue"
},
  "geometry": {"coordinates":[14.2860603333,46.8486061096],"type":"Point"}
}