{
  "type": "Feature",
  "properties": {
    "addr:full":"Rainerstr 3 Mondsee Ober\u00f6sterreich 5310",
    "addr:housenumber":"3",
    "addr:postcode":"5310",
    "addr:street":"Rainerstr;Oberoesterreich",
    "iso:country":"AT",
    "sg:address":"Rainerstr 3",
    "sg:city":"Mondsee",
    "sg:orig_category":"Friseure U Frisiersalons",
    "sg:phone":"+43 4362 322406",
    "sg:postcode":"5310",
    "sg:province":"Ober\u00f6sterreich",
    "sg:website":"hairlounge.co.at",
    "wof:name":"Hairlounge",
    "wof:placetype":"venue"
},
  "geometry": {"coordinates":[13.3498182297,47.8551826477],"type":"Point"}
}