{
  "type": "Feature",
  "properties": {
    "addr:full":"Nr 60 Raabs an der Thaya Nieder\u00f6sterreich 3820",
    "addr:postcode":"3820",
    "addr:street":"Nr",
    "iso:country":"AT",
    "sg:address":"Nr 60",
    "sg:city":"Raabs an der Thaya",
    "sg:orig_category":"Non-Classified Establishments",
    "sg:phone":"+43 2846 265",
    "sg:postcode":"3820",
    "sg:province":"Nieder\u00f6sterreich",
    "wof:name":"Pfarramt",
    "wof:placetype":"venue"
},
  "geometry": {"coordinates":[15.4923467636,48.8486366272],"type":"Point"}
}