{
  "type": "Feature",
  "properties": {
    "iso:country":"AT",
    "sg:address":"Burgfriedweg 13a",
    "sg:city":"Graz",
    "sg:orig_category":"Architekten",
    "sg:phone":"+43 316 3817930",
    "sg:postcode":"8010",
    "sg:province":"Steiermark",
    "wof:name":"Kiesel Martin Dipl-Ing",
    "wof:placetype":"venue"
},
  "geometry": {"coordinates":[15.4737930298,47.075920105],"type":"Point"}
}