{
  "type": "Feature",
  "properties": {
    "addr:full":"Weizer Str 1 Gleisdorf Steiermark 8200",
    "addr:housenumber":"1",
    "addr:postcode":"8200",
    "addr:street":"Str",
    "iso:country":"AT",
    "sg:address":"Weizer Str 1",
    "sg:city":"Gleisdorf",
    "sg:orig_category":"Boutiquen",
    "sg:phone":"+43 4331 127869",
    "sg:postcode":"8200",
    "sg:province":"Steiermark",
    "wof:name":"COCUNI",
    "wof:placetype":"venue"
},
  "geometry": {"coordinates":[15.7066783905,47.109172821],"type":"Point"}
}