{
  "type": "Feature",
  "properties": {
    "addr:full":"Nr 41 Herzogsdorf Ober\u00f6sterreich 4175",
    "addr:postcode":"4175",
    "addr:street":"Nr;Oberoesterreich",
    "iso:country":"AT",
    "sg:address":"Nr 41",
    "sg:city":"Herzogsdorf",
    "sg:classifiers":[
        {
            "category":"Home & Garden",
            "subcategory":"Building Materials",
            "type":"Retail Goods"
        }
    ],
    "sg:phone":"+43 7231 22270",
    "sg:postcode":"4175",
    "sg:province":"Ober\u00f6sterreich",
    "sg:tags":[
        "baustoffe",
        "-material",
        "u"
    ],
    "wof:name":"Hamberger-Inh P\u00f6senb\u00e4ck Friedrich",
    "wof:placetype":"venue"
},
  "geometry": {"coordinates":[14.1121921539,48.4299697876],"type":"Point"}
}