{
  "type": "Feature",
  "properties": {
    "addr:full":"Wildpretstr 27 Wien Wien 1110",
    "addr:housenumber":"27",
    "addr:postcode":"1110",
    "addr:street":"Wildpretstr",
    "iso:country":"AT",
    "sg:address":"Wildpretstr 27",
    "sg:city":"Wien",
    "sg:orig_category":"Transportunternehmen",
    "sg:phone":"+43 1 7673153",
    "sg:postcode":"1110",
    "sg:province":"Wien",
    "wof:name":"Leutl Christian GesmbH",
    "wof:placetype":"venue"
},
  "geometry": {"coordinates":[16.4562492371,48.1764144897],"type":"Point"}
}