{
  "type": "Feature",
  "properties": {
    "iso:country":"AT",
    "sg:address":"Hauptstr 25",
    "sg:city":"Obdach",
    "sg:orig_category":"Textilwaren / Einzelhandel",
    "sg:phone":"+43 3578 4033",
    "sg:postcode":"8742",
    "sg:province":"Steiermark",
    "wof:name":"TPS",
    "wof:placetype":"venue"
},
  "geometry": {"coordinates":[14.6948900223,47.0688552856],"type":"Point"}
}