{
  "type": "Feature",
  "properties": {
    "addr:full":"Fliederstrasse 13 Tulln an der Donau Nieder\u00f6sterreich 3430",
    "addr:housenumber":"13",
    "addr:postcode":"3430",
    "addr:street":"Fliederstrasse",
    "iso:country":"AT",
    "sg:address":"Fliederstrasse 13",
    "sg:city":"Tulln an der Donau",
    "sg:classifiers":[
        {
            "category":"Professional",
            "subcategory":"Art Services",
            "type":"Services"
        }
    ],
    "sg:phone":"+43 2272 68492",
    "sg:postcode":"3430",
    "sg:province":"Nieder\u00f6sterreich",
    "sg:tags":[
        "concept",
        "design"
    ],
    "sg:website":"members.aon.at/k.r.i.",
    "wof:name":"Technisches B\u00fcro Ralph Kruta",
    "wof:placetype":"venue"
},
  "geometry": {"coordinates":[16.0497398376,48.3306999207],"type":"Point"}
}