{
  "type": "Feature",
  "properties": {
    "addr:full":"De-La-Tour-Str 11 Treffen K\u00e4rnten 9521",
    "addr:housenumber":"11",
    "addr:postcode":"9521",
    "addr:street":"De-La-Tour-Str;Kaernten",
    "iso:country":"AT",
    "sg:address":"De-La-Tour-Str 11",
    "sg:city":"Treffen",
    "sg:orig_category":"Behinderungen / Leben Mit Behinderungen",
    "sg:phone":"+43 4248 28160",
    "sg:postcode":"9521",
    "sg:province":"K\u00e4rnten",
    "wof:name":"Behindertenheim f\u00fcr M\u00e4nner Evangelische Stiftung de La Tour",
    "wof:placetype":"venue"
},
  "geometry": {"coordinates":[13.8435745239,46.6789627075],"type":"Point"}
}