{
  "type": "Feature",
  "properties": {
    "addr:full":"Bahnhofstr 53 Vorchdorf Ober\u00f6sterreich 4655",
    "addr:postcode":"4655",
    "addr:street":"Bahnhofstr 53",
    "iso:country":"AT",
    "sg:address":"Bahnhofstr 53",
    "sg:city":"Vorchdorf",
    "sg:orig_category":"Notstromaggregate",
    "sg:phone":"+43 761479640",
    "sg:postcode":"4655",
    "sg:province":"Ober\u00f6sterreich",
    "wof:name":"Hartner Erich",
    "wof:placetype":"venue"
},
  "geometry": {"coordinates":[13.9218273163,47.996181488],"type":"Point"}
}