{
  "type": "Feature",
  "properties": {
    "addr:full":"Nr 24 Trebesing K\u00e4rnten 9852",
    "addr:postcode":"9852",
    "addr:street":"Nr;Trebesing Kaernten",
    "iso:country":"AT",
    "sg:address":"Nr 24",
    "sg:city":"Trebesing",
    "sg:orig_category":"Transportunternehmen",
    "sg:phone":"+43 4732 2854",
    "sg:postcode":"9852",
    "sg:province":"K\u00e4rnten",
    "wof:name":"Kr\u00e4mmer Karl",
    "wof:placetype":"venue"
},
  "geometry": {"coordinates":[13.514292717,46.8835754395],"type":"Point"}
}