{
  "type": "Feature",
  "properties": {
    "addr:full":"Braunauer Str 2 Mattighofen Ober\u00f6sterreich 5230",
    "addr:housenumber":"2",
    "addr:postcode":"5230",
    "addr:street":"Str",
    "iso:country":"AT",
    "sg:address":"Braunauer Str 2",
    "sg:city":"Mattighofen",
    "sg:orig_category":"Steuerberatung",
    "sg:phone":"+43 4377 4221810",
    "sg:postcode":"5230",
    "sg:province":"Ober\u00f6sterreich",
    "wof:name":"Simson & Partner Wirtschaftstreuhand GesmbH",
    "wof:placetype":"venue"
},
  "geometry": {"coordinates":[13.1498003006,48.1069450378],"type":"Point"}
}