{
  "type": "Feature",
  "properties": {
    "addr:full":"Achsengraben 8 Pregarten Ober\u00f6sterreich 4230",
    "addr:housenumber":"8",
    "addr:postcode":"4230",
    "addr:street":"Achsengraben",
    "iso:country":"AT",
    "sg:address":"Achsengraben 8",
    "sg:city":"Pregarten",
    "sg:orig_category":"Rauchfangkehrer",
    "sg:phone":"+43 7236 2225",
    "sg:postcode":"4230",
    "sg:province":"Ober\u00f6sterreich",
    "wof:name":"Mayer Herbert",
    "wof:placetype":"venue"
},
  "geometry": {"coordinates":[14.5321073532,48.35181427],"type":"Point"}
}