{
  "type": "Feature",
  "properties": {
    "addr:full":"Reith 61 St. Pantaleon Ober\u00f6sterreich 5120",
    "addr:housenumber":"61",
    "addr:postcode":"5120",
    "addr:street":"Reith;Pantaleon Oberoesterreich",
    "iso:country":"AT",
    "sg:address":"Reith 61",
    "sg:city":"St. Pantaleon",
    "sg:classifiers":[
        {
            "category":"Ice Cream",
            "type":"Food & Drink"
        }
    ],
    "sg:phone":"+43 6277 76810",
    "sg:postcode":"5120",
    "sg:province":"Ober\u00f6sterreich",
    "sg:tags":[
        "freezers",
        "chest",
        "deep",
        "freezer"
    ],
    "sg:website":"turbo.co.at",
    "wof:name":"TURBO Professional Equipment GmbH",
    "wof:placetype":"venue"
},
  "geometry": {"coordinates":[12.8775920868,47.9970474243],"type":"Point"}
}