{
  "type": "Feature",
  "properties": {
    "addr:full":"Grazer Str 97 Leibnitz Steiermark 8430",
    "addr:postcode":"8430",
    "addr:street":"Str 97;Steiermark",
    "iso:country":"AT",
    "sg:address":"Grazer Str 97",
    "sg:city":"Leibnitz",
    "sg:orig_category":"Gemeinden",
    "sg:phone":"+43 4334 52828510",
    "sg:postcode":"8430",
    "sg:province":"Steiermark",
    "wof:name":"Marktgemeindeamt Kaindorf an der Sulm",
    "wof:placetype":"venue"
},
  "geometry": {"coordinates":[15.5381326675,46.7900047302],"type":"Point"}
}