{
  "type": "Feature",
  "properties": {
    "iso:country":"AT",
    "sg:address":"Gumpendorfer Str 85",
    "sg:city":"Wien",
    "sg:orig_category":"Edelmetalle U -Verarbeitung",
    "sg:phone":"+43 1 599610",
    "sg:postcode":"1060",
    "sg:province":"Wien",
    "wof:name":"\u00d6gussa \u00d6sterreichische Gold- und Silber Scheideanstalt GesmbH",
    "wof:placetype":"venue"
},
  "geometry": {"coordinates":[16.3496360779,48.1934928894],"type":"Point"}
}