{
  "type": "Feature",
  "properties": {
    "addr:full":"Adi-Dassler-Gasse 2 Klagenfurt-Viktring K\u00e4rnten 9073",
    "addr:housenumber":"2",
    "addr:postcode":"9073",
    "addr:street":"Adi-Dassler-Gasse;Kaernten",
    "iso:country":"AT",
    "sg:address":"Adi-Dassler-Gasse 2",
    "sg:city":"Klagenfurt-Viktring",
    "sg:classifiers":[
        {
            "category":"Professional",
            "subcategory":"Advertising",
            "type":"Services"
        }
    ],
    "sg:phone":"+43 463 292144",
    "sg:postcode":"9073",
    "sg:province":"K\u00e4rnten",
    "sg:tags":[
        "articles"
    ],
    "sg:website":"werbemittel.at",
    "wof:name":"Camp Werbedruck u. Werbemittel",
    "wof:placetype":"venue"
},
  "geometry": {"coordinates":[14.2813844681,46.5803871155],"type":"Point"}
}