{
  "type": "Feature",
  "properties": {
    "iso:country":"AT",
    "sg:address":"Hauptstr 43",
    "sg:city":"Stixneusiedl",
    "sg:orig_category":"Architekten",
    "sg:phone":"+43 2169 2276",
    "sg:postcode":"2463",
    "sg:province":"Nieder\u00f6sterreich",
    "wof:name":"Putz Monika Dipl-Ing",
    "wof:placetype":"venue"
},
  "geometry": {"coordinates":[16.6735801697,48.0411987305],"type":"Point"}
}