{
  "type": "Feature",
  "properties": {
    "addr:full":"Nr 142 Ried im Oberinntal Tirol 6531",
    "addr:postcode":"6531",
    "addr:street":"Nr 142;Tirol",
    "iso:country":"AT",
    "sg:address":"Nr 142",
    "sg:city":"Ried im Oberinntal",
    "sg:orig_category":"Appartements / Ferienwohnungen",
    "sg:phone":"+43 664 3803273",
    "sg:postcode":"6531",
    "sg:province":"Tirol",
    "wof:name":"Ferienwohnungen Eiterer",
    "wof:placetype":"venue"
},
  "geometry": {"coordinates":[10.654545784,47.0553817749],"type":"Point"}
}