{
  "type": "Feature",
  "properties": {
    "iso:country":"AT",
    "sg:address":"Arlbergstr 135",
    "sg:city":"Bregenz",
    "sg:orig_category":"Tankstellen",
    "sg:phone":"+43 5574 71115",
    "sg:postcode":"6900",
    "sg:province":"Vorarlberg",
    "wof:name":"OMV AG",
    "wof:placetype":"venue"
},
  "geometry": {"coordinates":[9.7331314087,47.4878044128],"type":"Point"}
}