{
  "type": "Feature",
  "properties": {
    "addr:full":"Ziegeleistrasse 18 Salzburg Salzburg 5020",
    "addr:housenumber":"18",
    "addr:postcode":"5020",
    "addr:street":"Ziegeleistrasse;Salzburg",
    "iso:country":"AT",
    "sg:address":"Ziegeleistrasse 18",
    "sg:city":"Salzburg",
    "sg:classifiers":[
        {
            "category":"Shopping",
            "subcategory":"Books",
            "type":"Retail Goods"
        }
    ],
    "sg:phone":"+43 662 8742110",
    "sg:postcode":"5020",
    "sg:province":"Salzburg",
    "wof:name":"Reiter Offsetdruck Ernst Hanisch Ges.m.b.H.",
    "wof:placetype":"venue"
},
  "geometry": {"coordinates":[13.0582342148,47.8251953125],"type":"Point"}
}