{
  "type": "Feature",
  "properties": {
    "addr:full":"Schlo\u00dfstr 450 Kaprun Salzburg 5710",
    "addr:housenumber":"450",
    "addr:postcode":"5710",
    "addr:street":"Schlossstr;Salzburg",
    "iso:country":"AT",
    "sg:address":"Schlo\u00dfstr 450",
    "sg:city":"Kaprun",
    "sg:orig_category":"Pensionen / Privatzimmer",
    "sg:phone":"+43 6547 8477",
    "sg:postcode":"5710",
    "sg:province":"Salzburg",
    "wof:name":"Fr\u00fchst\u00fcckspension Alpenblick",
    "wof:placetype":"venue"
},
  "geometry": {"coordinates":[12.7664232254,47.2727508545],"type":"Point"}
}