{
  "type": "Feature",
  "properties": {
    "addr:full":"Marktpl 2 Neufelden Ober\u00f6sterreich 4120",
    "addr:housenumber":"2",
    "addr:postcode":"4120",
    "addr:street":"Marktpl",
    "iso:country":"AT",
    "sg:address":"Marktpl 2",
    "sg:city":"Neufelden",
    "sg:orig_category":"Appartements / Ferienwohnungen",
    "sg:phone":"+43 7282 6253",
    "sg:postcode":"4120",
    "sg:province":"Ober\u00f6sterreich",
    "wof:name":"Ferienhaus Scherrer",
    "wof:placetype":"venue"
},
  "geometry": {"coordinates":[14.0016126633,48.4851341248],"type":"Point"}
}