{
  "type": "Feature",
  "properties": {
    "addr:full":"Schlachthammerstr 76 Wien Wien 1220",
    "addr:housenumber":"76",
    "addr:postcode":"1220",
    "addr:street":"Schlachthammerstr",
    "iso:country":"AT",
    "sg:address":"Schlachthammerstr 76",
    "sg:city":"Wien",
    "sg:orig_category":"Blumeneinzelhandel",
    "sg:phone":"+43 1 7742758",
    "sg:postcode":"1220",
    "sg:province":"Wien",
    "wof:name":"Blumen Gaderer KEG",
    "wof:placetype":"venue"
},
  "geometry": {"coordinates":[16.5219669342,48.2120895386],"type":"Point"}
}