{
  "type": "Feature",
  "properties": {
    "addr:full":"Linzer Str 120 Wels Ober\u00f6sterreich 4600",
    "addr:housenumber":"120",
    "addr:postcode":"4600",
    "addr:street":"Linzer Str;Oberoesterreich",
    "iso:country":"AT",
    "sg:address":"Linzer Str 120",
    "sg:city":"Wels",
    "sg:orig_category":"Elektroinstallationsunternehmen",
    "sg:phone":"+43 7242 61312",
    "sg:postcode":"4600",
    "sg:province":"Ober\u00f6sterreich",
    "wof:name":"Edlbauer Erich",
    "wof:placetype":"venue"
},
  "geometry": {"coordinates":[14.0460910797,48.1671676636],"type":"Point"}
}