{
  "type": "Feature",
  "properties": {
    "iso:country":"AT",
    "sg:address":"Bahnhofweg 5",
    "sg:city":"St. Johann in Tirol",
    "sg:orig_category":"Pensionen / Privatzimmer",
    "sg:phone":"+43 5352 62637",
    "sg:postcode":"6380",
    "sg:province":"Tirol",
    "wof:name":"Fr\u00fchst\u00fcckspension Pletzer",
    "wof:placetype":"venue"
},
  "geometry": {"coordinates":[12.4294900894,47.5204734802],"type":"Point"}
}