{
  "type": "Feature",
  "properties": {
    "addr:full":"Troststr 53/13 Wien Wien 1100",
    "addr:housenumber":"53 / 13",
    "addr:postcode":"1100",
    "addr:street":"Troststr",
    "iso:country":"AT",
    "sg:address":"Troststr 53/13",
    "sg:city":"Wien",
    "sg:orig_category":"Physiotherapie",
    "sg:phone":"+43 1 6031037",
    "sg:postcode":"1100",
    "sg:province":"Wien",
    "wof:name":"Piwonka Doris Dipl-PT",
    "wof:placetype":"venue"
},
  "geometry": {"coordinates":[16.3668060303,48.1694984436],"type":"Point"}
}