{
  "type": "Feature",
  "properties": {
    "addr:full":"Rechenau 332 S\u00f6lden Tirol 6450",
    "addr:housenumber":"332",
    "addr:postcode":"6450",
    "addr:street":"Rechenau;Tirol",
    "iso:country":"AT",
    "sg:address":"Rechenau 332",
    "sg:city":"S\u00f6lden",
    "sg:orig_category":"Appartements / Ferienwohnungen",
    "sg:phone":"+43 5254 2372",
    "sg:postcode":"6450",
    "sg:province":"Tirol",
    "wof:name":"Haus Wiesenrand",
    "wof:placetype":"venue"
},
  "geometry": {"coordinates":[11.0118169785,46.9741744995],"type":"Point"}
}