{
  "type": "Feature",
  "properties": {
    "iso:country":"AT",
    "sg:address":"Rechenau 332",
    "sg:city":"S\u00f6lden",
    "sg:orig_category":"Appartements / Ferienwohnungen",
    "sg:phone":"+43 5254 2372",
    "sg:postcode":"6450",
    "sg:province":"Tirol",
    "wof:name":"Haus Wiesenrand",
    "wof:placetype":"venue"
},
  "geometry": {"coordinates":[11.0118169785,46.9741744995],"type":"Point"}
}