{
  "type": "Feature",
  "properties": {
    "addr:full":"Kirchpl 24 Schruns Vorarlberg 6780",
    "addr:housenumber":"24",
    "addr:postcode":"6780",
    "addr:street":"Kirchpl",
    "iso:country":"AT",
    "sg:address":"Kirchpl 24",
    "sg:city":"Schruns",
    "sg:orig_category":"Apotheken",
    "sg:phone":"+43 4355 5672362",
    "sg:postcode":"6780",
    "sg:province":"Vorarlberg",
    "wof:name":"Kur-Apotheke Magpharm Walter van Dellen KG",
    "wof:placetype":"venue"
},
  "geometry": {"coordinates":[9.9189195633,47.0809402466],"type":"Point"}
}