{
  "type": "Feature",
  "properties": {
    "addr:full":"Oldenburgg 13/9 Wien Wien 1230",
    "addr:housenumber":"13 / 9",
    "addr:postcode":"1230",
    "addr:street":"Oldenburgg",
    "iso:country":"AT",
    "sg:address":"Oldenburgg 13/9",
    "sg:city":"Wien",
    "sg:orig_category":"Tonstudios",
    "sg:phone":"+43 1 6652764",
    "sg:postcode":"1230",
    "sg:province":"Wien",
    "wof:name":"KLANGGALERIE Franz & Robotka OEG",
    "wof:placetype":"venue"
},
  "geometry": {"coordinates":[16.3313331604,48.1502151489],"type":"Point"}
}