{
  "type": "Feature",
  "properties": {
    "addr:full":"Reutte Tirol 6600",
    "addr:postcode":"6600",
    "addr:street":"Tirol",
    "iso:country":"AT",
    "sg:city":"Reutte",
    "sg:orig_category":"Finanzen, Banken",
    "sg:postcode":"6600",
    "sg:province":"Tirol",
    "sg:website":"http://www.sparkasse-reutte.at",
    "wof:name":"Sparkasse Reutte",
    "wof:placetype":"venue"
},
  "geometry": {"coordinates":[10.7185935974,47.4889183044],"type":"Point"}
}