{
  "type": "Feature",
  "properties": {
    "iso:country":"AT",
    "sg:address":"Hinsenkamppl 3",
    "sg:city":"Linz",
    "sg:orig_category":"Polytechnische Schulen",
    "sg:phone":"+43 732 700901",
    "sg:postcode":"4040",
    "sg:province":"Ober\u00f6sterreich",
    "wof:name":"Polytechnische Schule Urfahr",
    "wof:placetype":"venue"
},
  "geometry": {"coordinates":[14.2832241058,48.3116531372],"type":"Point"}
}