{
  "type": "Feature",
  "properties": {
    "addr:full":"Tuchlauben 8/3 Wien Wien 1010",
    "addr:housenumber":"8 / 3",
    "addr:postcode":"1010",
    "addr:street":"Tuchlauben",
    "iso:country":"AT",
    "sg:address":"Tuchlauben 8/3",
    "sg:city":"Wien",
    "sg:classifiers":[
        {
            "category":"Professional",
            "subcategory":"Management & Consulting",
            "type":"Services"
        }
    ],
    "sg:phone":"+43 1 5335188",
    "sg:postcode":"1010",
    "sg:province":"Wien",
    "sg:tags":[
        "hr",
        "resource",
        "consultancy",
        "human"
    ],
    "sg:website":"kienbaum.at",
    "wof:name":"Kienbaum Beratungen Ges.m.b.H.",
    "wof:placetype":"venue"
},
  "geometry": {"coordinates":[16.3703765869,48.2100753784],"type":"Point"}
}