{
  "type": "Feature",
  "properties": {
    "addr:full":"Grestenwaldstr 23 Ertl Nieder\u00f6sterreich 3355",
    "addr:housenumber":"23",
    "addr:postcode":"3355",
    "addr:street":"Grestenwaldstr",
    "iso:country":"AT",
    "sg:address":"Grestenwaldstr 23",
    "sg:city":"Ertl",
    "sg:orig_category":"Tischlereien",
    "sg:phone":"+43 7477 72200",
    "sg:postcode":"3355",
    "sg:province":"Nieder\u00f6sterreich",
    "wof:name":"M\u00f6bel Scharnreitner",
    "wof:placetype":"venue"
},
  "geometry": {"coordinates":[14.6237878799,47.9690475464],"type":"Point"}
}