{
  "type": "Feature",
  "properties": {
    "addr:full":"Bahnhofstr 18 W\u00f6rgl Tirol 6300",
    "addr:housenumber":"18",
    "addr:postcode":"6300",
    "addr:street":"Bahnhofstr;Tirol",
    "iso:country":"AT",
    "sg:address":"Bahnhofstr 18",
    "sg:city":"W\u00f6rgl",
    "sg:orig_category":"Banken U Sparkassen",
    "sg:phone":"+43 5 05333",
    "sg:postcode":"6300",
    "sg:province":"Tirol",
    "wof:name":"BTV - Bank f Tirol und Vorarlberg AG",
    "wof:placetype":"venue"
},
  "geometry": {"coordinates":[-69.3131027222,-51.6091995239],"type":"Point"}
}