{
  "type": "Feature",
  "properties": {
    "addr:full":"Kranzmayerstr 35 Klagenfurt K\u00e4rnten 9020",
    "addr:housenumber":"35",
    "addr:postcode":"9020",
    "addr:street":"Kranzmayerstr;Kaernten",
    "iso:country":"AT",
    "sg:address":"Kranzmayerstr 35",
    "sg:city":"Klagenfurt",
    "sg:orig_category":"Psychotherapie",
    "sg:phone":"+43 463 242024",
    "sg:postcode":"9020",
    "sg:province":"K\u00e4rnten",
    "wof:name":"Baumann Wolfhart Dr",
    "wof:placetype":"venue"
},
  "geometry": {"coordinates":[14.2752933502,46.6119766235],"type":"Point"}
}