{
  "type": "Feature",
  "properties": {
    "addr:full":"Bahnhofstr 20a W\u00f6rgl Tirol 6300",
    "addr:housenumber":"20a",
    "addr:postcode":"6300",
    "addr:street":"Bahnhofstr;Tirol",
    "iso:country":"AT",
    "sg:address":"Bahnhofstr 20a",
    "sg:city":"W\u00f6rgl",
    "sg:orig_category":"Freizeit- U Sportbekleidung",
    "sg:phone":"+43 5332 75309",
    "sg:postcode":"6300",
    "sg:province":"Tirol",
    "wof:name":"Western Store Mode GmbH",
    "wof:placetype":"venue"
},
  "geometry": {"coordinates":[-69.3131027222,-51.6091995239],"type":"Point"}
}