{
  "type": "Feature",
  "properties": {
    "addr:full":"Bahnhofstr 75 Ludesch Vorarlberg 6713",
    "addr:housenumber":"75",
    "addr:postcode":"6713",
    "addr:street":"Bahnhofstr",
    "iso:country":"AT",
    "sg:address":"Bahnhofstr 75",
    "sg:city":"Ludesch",
    "sg:orig_category":"Preisagenturen",
    "sg:phone":"+43 5550 3803",
    "sg:postcode":"6713",
    "sg:province":"Vorarlberg",
    "wof:name":"Ammann Kurt",
    "wof:placetype":"venue"
},
  "geometry": {"coordinates":[9.7727174759,47.1815109253],"type":"Point"}
}