{
  "type": "Feature",
  "properties": {
    "addr:full":"Friedrich-Wilhelm-Raiffeisen-Pl 1 Hausleiten Nieder\u00f6sterreich 3464",
    "addr:housenumber":"1",
    "addr:postcode":"3464",
    "addr:street":"Friedrich-Wilhelm-Raiffeisen-Pl",
    "iso:country":"AT",
    "sg:address":"Friedrich-Wilhelm-Raiffeisen-Pl 1",
    "sg:city":"Hausleiten",
    "sg:orig_category":"Dachdeckereien",
    "sg:phone":"+43 4322 657531",
    "sg:postcode":"3464",
    "sg:province":"Nieder\u00f6sterreich",
    "wof:name":"Posch Friedrich",
    "wof:placetype":"venue"
},
  "geometry": {"coordinates":[16.1026268005,48.394203186],"type":"Point"}
}