{
  "type": "Feature",
  "properties": {
    "addr:full":"Nr 15a Krakaudorf Steiermark 8854",
    "addr:housenumber":"15a",
    "addr:postcode":"8854",
    "addr:street":"Nr",
    "iso:country":"AT",
    "sg:address":"Nr 15a",
    "sg:city":"Krakaudorf",
    "sg:orig_category":"Pensionen / Privatzimmer",
    "sg:phone":"+43 3535 8672",
    "sg:postcode":"8854",
    "sg:province":"Steiermark",
    "wof:name":"Kendlbacher Peter und Gertrude",
    "wof:placetype":"venue"
},
  "geometry": {"coordinates":[13.9921045303,47.1786117554],"type":"Point"}
}