{
  "type": "Feature",
  "properties": {
    "iso:country":"AT",
    "sg:address":"St. Ruprechter Str 19",
    "sg:city":"Klagenfurt",
    "sg:orig_category":"Musikunterricht",
    "sg:phone":"+43 664 8279068",
    "sg:postcode":"9020",
    "sg:province":"K\u00e4rnten",
    "wof:name":"Musikschule Fr\u00f6hlich Klagenfurt",
    "wof:placetype":"venue"
},
  "geometry": {"coordinates":[14.3083696365,46.6168441772],"type":"Point"}
}