{
  "type": "Feature",
  "properties": {
    "iso:country":"AT",
    "sg:address":"Bayerhamerstr 12a",
    "sg:city":"Salzburg",
    "sg:orig_category":"Farben U Lacke / Einzelhandel",
    "sg:phone":"+43 662 875604",
    "sg:postcode":"5020",
    "sg:province":"Salzburg",
    "wof:name":"Wildschek Egon Ing & Co",
    "wof:placetype":"venue"
},
  "geometry": {"coordinates":[13.0511255264,47.8080825806],"type":"Point"}
}