{
  "type": "Feature",
  "properties": {
    "addr:full":"Viktor-Adler-Sdlg 44 Neusiedl an der Zaya Nieder\u00f6sterreich 2183",
    "addr:housenumber":"44",
    "addr:postcode":"2183",
    "addr:street":"Viktor-Adler-Sdlg",
    "iso:country":"AT",
    "sg:address":"Viktor-Adler-Sdlg 44",
    "sg:city":"Neusiedl an der Zaya",
    "sg:orig_category":"Transportunternehmen",
    "sg:phone":"+43 664 1001332",
    "sg:postcode":"2183",
    "sg:province":"Nieder\u00f6sterreich",
    "wof:name":"Schweng Helmut",
    "wof:placetype":"venue"
},
  "geometry": {"coordinates":[16.7960529327,48.5966262817],"type":"Point"}
}