{
  "type": "Feature",
  "properties": {
    "addr:full":"Horngach 23 Ellmau Tirol 6352",
    "addr:housenumber":"23",
    "addr:postcode":"6352",
    "addr:street":"Horngach;Tirol",
    "iso:country":"AT",
    "sg:address":"Horngach 23",
    "sg:city":"Ellmau",
    "sg:orig_category":"Pensionen / Privatzimmer",
    "sg:phone":"+43 5358 3776",
    "sg:postcode":"6352",
    "sg:province":"Tirol",
    "wof:name":"Sonnhof Ratzenbauer",
    "wof:placetype":"venue"
},
  "geometry": {"coordinates":[12.2718362808,47.5255317688],"type":"Point"}
}