{
  "type": "Feature",
  "properties": {
    "addr:full":"Bahnhofstr 15a Schruns Vorarlberg 6780",
    "addr:housenumber":"15a",
    "addr:postcode":"6780",
    "addr:street":"Bahnhofstr",
    "iso:country":"AT",
    "sg:address":"Bahnhofstr 15a",
    "sg:city":"Schruns",
    "sg:orig_category":"Elektroinstallationsunternehmen",
    "sg:phone":"+43 4355 569000",
    "sg:postcode":"6780",
    "sg:province":"Vorarlberg",
    "wof:name":"Montafonerbahn AG",
    "wof:placetype":"venue"
},
  "geometry": {"coordinates":[9.9190063477,47.0791168213],"type":"Point"}
}