{
  "type": "Feature",
  "properties": {
    "addr:full":"Untere Hauptstr 30 Jois Burgenland 7093",
    "addr:housenumber":"30",
    "addr:postcode":"7093",
    "addr:street":"Untere Hauptstr",
    "iso:country":"AT",
    "sg:address":"Untere Hauptstr 30",
    "sg:city":"Jois",
    "sg:orig_category":"Pensionen / Privatzimmer",
    "sg:phone":"+43 4321 607385",
    "sg:postcode":"7093",
    "sg:province":"Burgenland",
    "wof:name":"Pension-Weingut Pasler",
    "wof:placetype":"venue"
},
  "geometry": {"coordinates":[16.7938423157,47.9597663879],"type":"Point"}
}