{
  "type": "Feature",
  "properties": {
    "addr:full":"Schottenfeldg 56/23 Wien Wien 1070",
    "addr:housenumber":"56 / 23",
    "addr:postcode":"1070",
    "addr:street":"Schottenfeldg",
    "iso:country":"AT",
    "sg:address":"Schottenfeldg 56/23",
    "sg:city":"Wien",
    "sg:orig_category":"Filmproduktionen",
    "sg:phone":"+43 4315 222588",
    "sg:postcode":"1070",
    "sg:province":"Wien",
    "wof:name":"Orbrock Filmproduktion GmbH",
    "wof:placetype":"venue"
},
  "geometry": {"coordinates":[16.3433494568,48.2032012939],"type":"Point"}
}