{
  "type": "Feature",
  "properties": {
    "addr:full":"Hofsteigstr 118 Hard Vorarlberg 6971",
    "addr:housenumber":"118",
    "addr:postcode":"6971",
    "addr:street":"Hard Vorarlberg",
    "iso:country":"AT",
    "sg:address":"Hofsteigstr 118",
    "sg:city":"Hard",
    "sg:orig_category":"Autohandel",
    "sg:phone":"+43 4355 74732880",
    "sg:postcode":"6971",
    "sg:province":"Vorarlberg",
    "sg:website":"unterberger.cc",
    "wof:name":"Unterberger Automobile GmbH & Co KG",
    "wof:placetype":"venue"
},
  "geometry": {"coordinates":[9.7087574005,47.4874267578],"type":"Point"}
}