{
  "type": "Feature",
  "properties": {
    "addr:full":"Wiedner Hauptstr 76 Wien Wien 1040",
    "addr:housenumber":"76",
    "addr:postcode":"1040",
    "addr:street":"Hauptstr",
    "iso:country":"AT",
    "sg:address":"Wiedner Hauptstr 76",
    "sg:city":"Wien",
    "sg:orig_category":"Molkereien U Molkereiprodukte",
    "sg:phone":"+43 1 58603510",
    "sg:postcode":"1040",
    "sg:province":"Wien",
    "wof:name":"Bongrain GesmbH",
    "wof:placetype":"venue"
},
  "geometry": {"coordinates":[16.365114212,48.1893043518],"type":"Point"}
}