{
  "type": "Feature",
  "properties": {
    "iso:country":"AT",
    "sg:address":"Sparbersbachg 40",
    "sg:city":"Graz",
    "sg:orig_category":"Bibliotheken",
    "sg:phone":"+43 316 830639",
    "sg:postcode":"8010",
    "sg:province":"Steiermark",
    "wof:name":"Stadtbibliothek d Magistrates",
    "wof:placetype":"venue"
},
  "geometry": {"coordinates":[15.4520053864,47.068271637],"type":"Point"}
}