{
  "type": "Feature",
  "properties": {
    "addr:full":"Nr 77 Neumarkt an der Ybbs Nieder\u00f6sterreich 3371",
    "addr:housenumber":"3371",
    "addr:street":"Nr 77;Niederoesterreich",
    "iso:country":"AT",
    "sg:address":"Nr 77",
    "sg:city":"Neumarkt an der Ybbs",
    "sg:orig_category":"Volksschulen",
    "sg:phone":"+43 4374 1258901",
    "sg:postcode":"3371",
    "sg:province":"Nieder\u00f6sterreich",
    "wof:name":"Volksschule",
    "wof:placetype":"venue"
},
  "geometry": {"coordinates":[15.0592651367,48.1405639648],"type":"Point"}
}