{
  "type": "Feature",
  "properties": {
    "iso:country":"AT",
    "sg:address":"Fachschulg 14",
    "sg:city":"Fulpmes",
    "sg:orig_category":"Metallbe- U -Verarbeitung",
    "sg:phone":"+43 4352 25696061",
    "sg:postcode":"6166",
    "sg:province":"Tirol",
    "wof:name":"Schmid Karl OEG",
    "wof:placetype":"venue"
},
  "geometry": {"coordinates":[11.3472709656,47.1571388245],"type":"Point"}
}