{
  "type": "Feature",
  "properties": {
    "addr:full":"Hainfelder Str 3A Weissenbach an der Triesting Nieder\u00f6sterreich 2564",
    "addr:postcode":"2564",
    "addr:street":"Str 3A",
    "iso:country":"AT",
    "sg:address":"Hainfelder Str 3A",
    "sg:city":"Weissenbach an der Triesting",
    "sg:orig_category":"Transportunternehmen",
    "sg:phone":"+43 2672 882720",
    "sg:postcode":"2564",
    "sg:province":"Nieder\u00f6sterreich",
    "wof:name":"Steyrer Friedrich GesmbH & Co KG",
    "wof:placetype":"venue"
},
  "geometry": {"coordinates":[16.0735168457,47.9719619751],"type":"Point"}
}