{
  "type": "Feature",
  "properties": {
    "addr:full":"Laxenburger Str 123-125 Wien Wien 1100",
    "addr:postcode":"123-125;1100",
    "addr:street":"Laxenburger Str",
    "iso:country":"AT",
    "sg:address":"Laxenburger Str 123-125",
    "sg:city":"Wien",
    "sg:orig_category":"Rauchfangkehrer",
    "sg:phone":"+43 1 6046565",
    "sg:postcode":"1100",
    "sg:province":"Wien",
    "wof:name":"Wilde Susanne",
    "wof:placetype":"venue"
},
  "geometry": {"coordinates":[16.370721817,48.1687774658],"type":"Point"}
}