{
  "type": "Feature",
  "properties": {
    "addr:full":"Auf der Ertlh\u00f6he 37/3 Seeboden K\u00e4rnten 9871",
    "addr:housenumber":"37 / 3",
    "addr:postcode":"9871",
    "addr:street":"Auf Der Ertlhoehe;Kaernten",
    "iso:country":"AT",
    "sg:address":"Auf der Ertlh\u00f6he 37/3",
    "sg:city":"Seeboden",
    "sg:orig_category":"Banken U Sparkassen",
    "sg:phone":"+43 4762 82404",
    "sg:postcode":"9871",
    "sg:province":"K\u00e4rnten",
    "wof:name":"Sparkasse Rottal-Inn",
    "wof:placetype":"venue"
},
  "geometry": {"coordinates":[13.5196332932,46.8233795166],"type":"Point"}
}