{
  "type": "Feature",
  "properties": {
    "addr:full":"Untere Bahngasse 90 Purbach am Neusiedler See Burgenland 7083",
    "addr:housenumber":"90",
    "addr:postcode":"7083",
    "addr:street":"Untere Bahngasse",
    "iso:country":"AT",
    "sg:address":"Untere Bahngasse 90",
    "sg:city":"Purbach am Neusiedler See",
    "sg:classifiers":[
        {
            "category":"Manufacturing",
            "subcategory":"Furniture",
            "type":"Manufacturing & Wholesale Goods"
        }
    ],
    "sg:phone":"+43 2683 5176",
    "sg:postcode":"7083",
    "sg:province":"Burgenland",
    "sg:tags":[
        "beech"
    ],
    "wof:name":"Ing. Richard Hermann",
    "wof:placetype":"venue"
},
  "geometry": {"coordinates":[16.6976337433,47.9060592651],"type":"Point"}
}