{
  "type": "Feature",
  "properties": {
    "addr:full":"Hauptstr 28 Gerasdorf Nieder\u00f6sterreich 2201",
    "addr:housenumber":"28",
    "addr:postcode":"2201",
    "addr:street":"Hauptstr",
    "iso:country":"AT",
    "sg:address":"Hauptstr 28",
    "sg:city":"Gerasdorf",
    "sg:orig_category":"Feuerwehren",
    "sg:phone":"+43 2246 22220",
    "sg:postcode":"2201",
    "sg:province":"Nieder\u00f6sterreich",
    "wof:name":"Freiwillige Feuerwehr Gerasdorf",
    "wof:placetype":"venue"
},
  "geometry": {"coordinates":[16.4701557159,48.297996521],"type":"Point"}
}