{
  "type": "Feature",
  "properties": {
    "addr:full":"Hauptstr 446 Mayrhofen Tirol 6290",
    "addr:housenumber":"446",
    "addr:postcode":"6290",
    "addr:street":"Hauptstr;Tirol",
    "iso:country":"AT",
    "sg:address":"Hauptstr 446",
    "sg:city":"Mayrhofen",
    "sg:orig_category":"Molkereien U Molkereiprodukte",
    "sg:phone":"+43 5285 64926",
    "sg:postcode":"6290",
    "sg:province":"Tirol",
    "wof:name":"Sennerei G'sch\u00e4ftl Mayrhofen",
    "wof:placetype":"venue"
},
  "geometry": {"coordinates":[11.8623189926,47.1658782959],"type":"Point"}
}