{
  "type": "Feature",
  "properties": {
    "addr:full":"Marburger Str 41-43 Weiz Steiermark 8160",
    "addr:postcode":"41-43;8160",
    "addr:street":"Str",
    "iso:country":"AT",
    "sg:address":"Marburger Str 41-43",
    "sg:city":"Weiz",
    "sg:orig_category":"Raumausstattung",
    "sg:phone":"+43 3172 4840",
    "sg:postcode":"8160",
    "sg:province":"Steiermark",
    "wof:name":"Strametz Erhard",
    "wof:placetype":"venue"
},
  "geometry": {"coordinates":[15.6252756119,47.2136421204],"type":"Point"}
}