{
  "type": "Feature",
  "properties": {
    "addr:full":"Gr\u00fcnlandweg 2 Neidling Nieder\u00f6sterreich 3110",
    "addr:housenumber":"2",
    "addr:postcode":"3110",
    "addr:street":"Gruenlandweg;Niederoesterreich",
    "iso:country":"AT",
    "sg:address":"Gr\u00fcnlandweg 2",
    "sg:city":"Neidling",
    "sg:orig_category":"Markisen",
    "sg:phone":"+43 2741 7350",
    "sg:postcode":"3110",
    "sg:province":"Nieder\u00f6sterreich",
    "sg:website":"sonnenschutz-kern.at",
    "wof:name":"Kern Sonnenschutz",
    "wof:placetype":"venue"
},
  "geometry": {"coordinates":[15.5568723679,48.2376899719],"type":"Point"}
}