{
  "type": "Feature",
  "properties": {
    "addr:full":"Blasius-Hueber-Str 16 Innsbruck Tirol 6020",
    "addr:housenumber":"16",
    "addr:postcode":"6020",
    "addr:street":"Blasius-Hueber-Str;Tirol",
    "iso:country":"AT",
    "sg:address":"Blasius-Hueber-Str 16",
    "sg:city":"Innsbruck",
    "sg:orig_category":"Friseure U Frisiersalons",
    "sg:phone":"+43 4351 2287187",
    "sg:postcode":"6020",
    "sg:province":"Tirol",
    "wof:name":"Friseursalon Monika Falger - Haar + Haut",
    "wof:placetype":"venue"
},
  "geometry": {"coordinates":[11.3840017319,47.2659111023],"type":"Point"}
}