{
  "type": "Feature",
  "properties": {
    "iso:country":"AT",
    "sg:address":"Nr 13",
    "sg:city":"Saalfelden am Steinernen Meer",
    "sg:orig_category":"Imkereien",
    "sg:phone":"+43 6582 72433",
    "sg:postcode":"5760",
    "sg:province":"Salzburg",
    "wof:name":"Unterberger Peter",
    "wof:placetype":"venue"
},
  "geometry": {"coordinates":[12.8474750519,47.426410675],"type":"Point"}
}