{
  "type": "Feature",
  "properties": {
    "addr:full":"Fleischmanng 8 Wien Wien 1040",
    "addr:housenumber":"8",
    "addr:postcode":"1040",
    "addr:street":"Fleischmanng",
    "iso:country":"AT",
    "sg:address":"Fleischmanng 8",
    "sg:city":"Wien",
    "sg:orig_category":"Blitzableiter U Blitzschutzanlagen, Elektroinstallationsunternehmen",
    "sg:phone":"+43 1 58621650",
    "sg:postcode":"1040",
    "sg:province":"Wien",
    "wof:name":"Tr\u00f6tzm\u00fcller Blitzschutzbau GesmbH",
    "wof:placetype":"venue"
},
  "geometry": {"coordinates":[16.365819931,48.1937179565],"type":"Point"}
}