{
  "type": "Feature",
  "properties": {
    "iso:country":"AT",
    "sg:address":"Nr 32",
    "sg:city":"St. Paul im Lavanttal",
    "sg:orig_category":"Transportunternehmen",
    "sg:phone":"+43 4357 3602",
    "sg:postcode":"9470",
    "sg:province":"K\u00e4rnten",
    "wof:name":"Mohl Werner KEG",
    "wof:placetype":"venue"
},
  "geometry": {"coordinates":[14.8693141937,46.7011146545],"type":"Point"}
}