{
  "type": "Feature",
  "properties": {
    "addr:full":"R\u00f6merweg 48 Krumpendorf K\u00e4rnten 9201",
    "addr:housenumber":"48",
    "addr:postcode":"9201",
    "addr:street":"Roemerweg;Kaernten",
    "iso:country":"AT",
    "sg:address":"R\u00f6merweg 48",
    "sg:city":"Krumpendorf",
    "sg:orig_category":"Steuerberatung",
    "sg:phone":"+43 4229 2428",
    "sg:postcode":"9201",
    "sg:province":"K\u00e4rnten",
    "wof:name":"Haselmayer Erika",
    "wof:placetype":"venue"
},
  "geometry": {"coordinates":[14.2104196548,46.6270256042],"type":"Point"}
}