{
  "type": "Feature",
  "properties": {
    "addr:full":"Wendstattg 5 Wien Wien 1100",
    "addr:housenumber":"5",
    "addr:postcode":"1100",
    "addr:street":"Wendstattg",
    "iso:country":"AT",
    "sg:address":"Wendstattg 5",
    "sg:city":"Wien",
    "sg:orig_category":"Hauptschulen",
    "sg:phone":"+43 1 6883564",
    "sg:postcode":"1100",
    "sg:province":"Wien",
    "wof:name":"Schulen d Stadt Wien - HS 2 Sporthauptschule",
    "wof:placetype":"venue"
},
  "geometry": {"coordinates":[16.392824173,48.1478118896],"type":"Point"}
}