{
  "type": "Feature",
  "properties": {
    "iso:country":"AT",
    "sg:address":"Dr.-Otto-Neurath-G 1",
    "sg:city":"Wien",
    "sg:orig_category":"Mess-, Steuer- U Regeltechnik",
    "sg:phone":"+43 4312 8216270",
    "sg:postcode":"1220",
    "sg:province":"Wien",
    "wof:name":"Grabner Instruments Me\u00dftechnik Nfg GesmbH & Co KG",
    "wof:placetype":"venue"
},
  "geometry": {"coordinates":[16.4550800323,48.2312774658],"type":"Point"}
}