{
  "type": "Feature",
  "properties": {
    "iso:country":"AT",
    "sg:address":"Henzingweg 1",
    "sg:city":"W\u00fcrmla",
    "sg:orig_category":"Elektroinstallationsunternehmen",
    "sg:phone":"+43 2275 8762",
    "sg:postcode":"3042",
    "sg:province":"Nieder\u00f6sterreich",
    "wof:name":"Schmidt Christoph",
    "wof:placetype":"venue"
},
  "geometry": {"coordinates":[15.8556470871,48.2478675842],"type":"Point"}
}