{
  "type": "Feature",
  "properties": {
    "iso:country":"AT",
    "sg:address":"Fricken 14",
    "sg:city":"Schattwald",
    "sg:orig_category":"Transportunternehmen",
    "sg:phone":"+43 5675 6717",
    "sg:postcode":"6677",
    "sg:province":"Tirol",
    "wof:name":"Tannheimer Wolfgang",
    "wof:placetype":"venue"
},
  "geometry": {"coordinates":[10.4649200439,47.5142822266],"type":"Point"}
}