{
  "type": "Feature",
  "properties": {
    "addr:full":"Hauptpl. 25  Villach K\u00e4rnten 9500",
    "addr:housenumber":"25",
    "addr:postcode":"9500",
    "addr:street":"Hauptpl.;Kaernten",
    "iso:country":"AT",
    "sg:address":"Hauptpl. 25 ",
    "sg:city":"Villach",
    "sg:classifiers":[
        {
            "category":"Professional",
            "subcategory":"Computer Services",
            "type":"Services"
        }
    ],
    "sg:phone":"+43 4342 4224126",
    "sg:postcode":"9500",
    "sg:province":"K\u00e4rnten",
    "sg:tags":[
        "information",
        "technology"
    ],
    "wof:name":"CASPAR & POLTNIG",
    "wof:placetype":"venue"
},
  "geometry": {"coordinates":[13.8464508057,46.6135177612],"type":"Point"}
}