{
  "type": "Feature",
  "properties": {
    "addr:full":"Hauptstr 223 Kalsdorf Steiermark 8401",
    "addr:housenumber":"223",
    "addr:postcode":"8401",
    "addr:street":"Hauptstr",
    "iso:country":"AT",
    "sg:address":"Hauptstr 223",
    "sg:city":"Kalsdorf",
    "sg:orig_category":"Autohandel",
    "sg:phone":"+43 4331 3554520",
    "sg:postcode":"8401",
    "sg:province":"Steiermark",
    "wof:name":"Lenhardt - Nutzfahrzeuge",
    "wof:placetype":"venue"
},
  "geometry": {"coordinates":[15.4822349548,46.9519348145],"type":"Point"}
}