{
  "type": "Feature",
  "properties": {
    "iso:country":"AT",
    "sg:address":"Fischabachg 29",
    "sg:city":"Wiener Neustadt",
    "sg:orig_category":"Massagen",
    "sg:phone":"+43 2622 84752",
    "sg:postcode":"2700",
    "sg:province":"Nieder\u00f6sterreich",
    "sg:website":"studiobieber.at",
    "wof:name":"Bieber Gabriele & Norbert",
    "wof:placetype":"venue"
},
  "geometry": {"coordinates":[16.2296142578,47.8192138672],"type":"Point"}
}