{
  "type": "Feature",
  "properties": {
    "addr:full":"Gorintschach 45 St. Jakob im Rosental K\u00e4rnten 9184",
    "addr:housenumber":"45",
    "addr:postcode":"9184",
    "addr:street":"Gorintschach",
    "iso:country":"AT",
    "sg:address":"Gorintschach 45",
    "sg:city":"St. Jakob im Rosental",
    "sg:orig_category":"Battery Packaging Services",
    "sg:phone":"+43 4253 31061",
    "sg:postcode":"9184",
    "sg:province":"K\u00e4rnten",
    "wof:name":"BKB Bernd-Joachim Sack",
    "wof:placetype":"venue"
},
  "geometry": {"coordinates":[14.0255775452,46.5568161011],"type":"Point"}
}