{
  "type": "Feature",
  "properties": {
    "iso:country":"AT",
    "sg:address":"10.-Oktober-Str 20",
    "sg:city":"Feldkirchen in K\u00e4rnten",
    "sg:classifiers":[
        {
            "category":"Restaurant",
            "type":"Food & Drink"
        }
    ],
    "sg:phone":"+43 4342 7648142",
    "sg:postcode":"9560",
    "sg:province":"K\u00e4rnten",
    "wof:name":"Restaurant Reblaus Inh Margarete Piber",
    "wof:placetype":"venue"
},
  "geometry": {"coordinates":[14.0947132111,46.7240638733],"type":"Point"}
}