{
  "type": "Feature",
  "properties": {
    "addr:full":"Kempfstr 16 Klagenfurt K\u00e4rnten 9020",
    "addr:housenumber":"16",
    "addr:postcode":"9020",
    "addr:street":"Kempfstr;Kaernten",
    "iso:country":"AT",
    "sg:address":"Kempfstr 16",
    "sg:city":"Klagenfurt",
    "sg:orig_category":"Psychologen",
    "sg:phone":"+43 463 515503",
    "sg:postcode":"9020",
    "sg:province":"K\u00e4rnten",
    "wof:name":"Sankl Isabella Dr",
    "wof:placetype":"venue"
},
  "geometry": {"coordinates":[14.3089876175,46.6177978516],"type":"Point"}
}