{
  "type": "Feature",
  "properties": {
    "iso:country":"AT",
    "sg:address":"Waldemar-Hering-Str 5",
    "sg:city":"Oberndorf",
    "sg:orig_category":"Elektronik",
    "sg:phone":"+43 4362 727634",
    "sg:postcode":"5110",
    "sg:province":"Salzburg",
    "wof:name":"Strametz-Industrie-Electronic",
    "wof:placetype":"venue"
},
  "geometry": {"coordinates":[12.9393901825,47.9540481567],"type":"Point"}
}