{
  "type": "Feature",
  "properties": {
    "addr:full":"Karl-Wurmb-Str. 8 Wels Ober\u00f6sterreich 4600",
    "addr:housenumber":"8",
    "addr:postcode":"4600",
    "addr:street":"Karl-Wurmb-Str.;Oberoesterreich",
    "iso:country":"AT",
    "sg:address":"Karl-Wurmb-Str. 8",
    "sg:city":"Wels",
    "sg:classifiers":[
        {
            "category":"Manufacturing",
            "subcategory":"Metals",
            "type":"Manufacturing & Wholesale Goods"
        }
    ],
    "sg:phone":"+43 4372 4242141",
    "sg:postcode":"4600",
    "sg:province":"Ober\u00f6sterreich",
    "sg:tags":[
        "metallurgy",
        "metalworking"
    ],
    "wof:name":"MOLIN INDUSTRIE INBETRIEBNAHME MONTAGE GMBH & CO KG",
    "wof:placetype":"venue"
},
  "geometry": {"coordinates":[14.0611972809,48.1609687805],"type":"Point"}
}