{
  "type": "Feature",
  "properties": {
    "addr:full":"Hochtennstr 26d Zell am See Salzburg 5700",
    "addr:housenumber":"26d",
    "addr:postcode":"5700",
    "addr:street":"Hochtennstr;Salzburg",
    "iso:country":"AT",
    "sg:address":"Hochtennstr 26d",
    "sg:city":"Zell am See",
    "sg:orig_category":"Freizeit- U Sportbekleidung",
    "sg:phone":"+43 4366 44239498",
    "sg:postcode":"5700",
    "sg:province":"Salzburg",
    "wof:name":"Sporty Teubner G\u00fcnther",
    "wof:placetype":"venue"
},
  "geometry": {"coordinates":[12.7980804443,47.2976493835],"type":"Point"}
}