{
  "type": "Feature",
  "properties": {
    "iso:country":"AT",
    "sg:address":"Hauptpl 22",
    "sg:city":"Freistadt",
    "sg:orig_category":"Werbeagenturen",
    "sg:phone":"+43 664 5200213",
    "sg:postcode":"4240",
    "sg:province":"Ober\u00f6sterreich",
    "wof:name":"sense/ad - Sinnvoll Werbung",
    "wof:placetype":"venue"
},
  "geometry": {"coordinates":[14.5053253174,48.5109596252],"type":"Point"}
}