{
  "type": "Feature",
  "properties": {
    "addr:full":"Frank-Stronach-Strasse 3 Gleisdorf Steiermark 8200",
    "addr:housenumber":"3",
    "addr:postcode":"8200",
    "addr:street":"Frank-Stronach-Strasse",
    "iso:country":"AT",
    "sg:address":"Frank-Stronach-Strasse 3",
    "sg:city":"Gleisdorf",
    "sg:classifiers":[
        {
            "category":"Shopping",
            "subcategory":"Computers & Home Electronics",
            "type":"Retail Goods"
        }
    ],
    "sg:phone":"+43 3112 90000",
    "sg:postcode":"8200",
    "sg:province":"Steiermark",
    "sg:tags":[
        "system",
        "automation"
    ],
    "sg:website":"magna-systemtechnik.com",
    "wof:name":"MAGNA Systemtechnik AG",
    "wof:placetype":"venue"
},
  "geometry": {"coordinates":[15.6994400024,47.1150970459],"type":"Point"}
}