{
  "type": "Feature",
  "properties": {
    "addr:full":"Hauptstr 30 Neumarkt am Wallersee Salzburg 5202",
    "addr:housenumber":"30",
    "addr:postcode":"5202",
    "addr:street":"Hauptstr;Salzburg",
    "iso:country":"AT",
    "sg:address":"Hauptstr 30",
    "sg:city":"Neumarkt am Wallersee",
    "sg:orig_category":"Tourismusinformation U -Organisationen",
    "sg:phone":"+43 4362 166907",
    "sg:postcode":"5202",
    "sg:province":"Salzburg",
    "wof:name":"Fremdenverkehrsverband Neumarkt am Wallersee",
    "wof:placetype":"venue"
},
  "geometry": {"coordinates":[13.2247152328,47.9452896118],"type":"Point"}
}