{
  "type": "Feature",
  "properties": {
    "iso:country":"AT",
    "sg:address":"Nr 38",
    "sg:city":"Aigen-Voglhub",
    "sg:orig_category":"Forstverwaltungen",
    "sg:phone":"+43 4361 3721773",
    "sg:postcode":"5351",
    "sg:province":"Salzburg",
    "wof:name":"\u00f6sterreichische Bundesforste AG",
    "wof:placetype":"venue"
},
  "geometry": {"coordinates":[-83.3486022949,43.8284263611],"type":"Point"}
}