{
  "type": "Feature",
  "properties": {
    "iso:country":"AT",
    "sg:address":"Veldner Str NB",
    "sg:city":"Neufelden",
    "sg:orig_category":"Reifen U Reifendienste",
    "sg:phone":"+43 4372 827680",
    "sg:postcode":"4120",
    "sg:province":"Ober\u00f6sterreich",
    "wof:name":"Krenn GesmbH",
    "wof:placetype":"venue"
},
  "geometry": {"coordinates":[13.9883146286,48.4849128723],"type":"Point"}
}