{
  "type": "Feature",
  "properties": {
    "addr:full":"Nr 86 Neumarkt in Steiermark Steiermark 8820",
    "addr:postcode":"8820",
    "addr:street":"Nr 86",
    "iso:country":"AT",
    "sg:address":"Nr 86",
    "sg:city":"Neumarkt in Steiermark",
    "sg:orig_category":"Datenverarbeitung",
    "sg:phone":"+43 4335 84400251",
    "sg:postcode":"8820",
    "sg:province":"Steiermark",
    "wof:name":"Informationstechnologie Ing Peter Hasler",
    "wof:placetype":"venue"
},
  "geometry": {"coordinates":[14.4293413162,47.0666313171],"type":"Point"}
}