{
  "type": "Feature",
  "properties": {
    "addr:full":"Bahnstr 9 Neunkirchen Nieder\u00f6sterreich 2620",
    "addr:housenumber":"9",
    "addr:postcode":"2620",
    "addr:street":"Bahnstr",
    "iso:country":"AT",
    "sg:address":"Bahnstr 9",
    "sg:city":"Neunkirchen",
    "sg:orig_category":"Friseure U Frisiersalons",
    "sg:phone":"+43 4326 3562018",
    "sg:postcode":"2620",
    "sg:province":"Nieder\u00f6sterreich",
    "wof:name":"Schlager Gottfried",
    "wof:placetype":"venue"
},
  "geometry": {"coordinates":[16.0813827515,47.7276992798],"type":"Point"}
}