{
  "type": "Feature",
  "properties": {
    "addr:full":"Payer Weyprecht-Str 33-35 Graz Steiermark 8020",
    "addr:postcode":"33-35;8020",
    "iso:country":"AT",
    "sg:address":"Payer Weyprecht-Str 33-35",
    "sg:city":"Graz",
    "sg:orig_category":"Zeitungen U Zeitschriften",
    "sg:phone":"+43 316 674045",
    "sg:postcode":"8020",
    "sg:province":"Steiermark",
    "wof:name":"Thema - plus Zeitung",
    "wof:placetype":"venue"
},
  "geometry": {"coordinates":[15.4220943451,47.0511054993],"type":"Point"}
}