{
  "type": "Feature",
  "properties": {
    "addr:full":"Kanalpl 2 Wolfsberg K\u00e4rnten 9400",
    "addr:housenumber":"2;kaernten",
    "addr:postcode":"9400",
    "addr:street":"Kanalpl",
    "iso:country":"AT",
    "sg:address":"Kanalpl 2",
    "sg:city":"Wolfsberg",
    "sg:orig_category":"Schlossereien",
    "sg:phone":"+43 4352 2176",
    "sg:postcode":"9400",
    "sg:province":"K\u00e4rnten",
    "wof:name":"Hornof Franz",
    "wof:placetype":"venue"
},
  "geometry": {"coordinates":[14.8438968658,46.8389091492],"type":"Point"}
}