{
  "type": "Feature",
  "properties": {
    "addr:full":"Fillgradergasse 7 Wien Wien 1060",
    "addr:housenumber":"7",
    "addr:postcode":"1060",
    "addr:street":"Fillgradergasse",
    "iso:country":"AT",
    "sg:address":"Fillgradergasse 7",
    "sg:city":"Wien",
    "sg:classifiers":[
        {
            "category":"Government",
            "subcategory":"Office",
            "type":"Public Place"
        }
    ],
    "sg:phone":"+43 1 588100",
    "sg:postcode":"1060",
    "sg:province":"Wien",
    "sg:tags":[
        "broking",
        "brand",
        "agency",
        "product"
    ],
    "sg:website":"gertnergroup.de",
    "wof:name":"M. & D. Gertner GmbH",
    "wof:placetype":"venue"
},
  "geometry": {"coordinates":[16.358751297,48.1997146606],"type":"Point"}
}