{
  "type": "Feature",
  "properties": {
    "addr:full":"Zirknitzberg 2 Mooskirchen Steiermark 8562",
    "addr:housenumber":"2",
    "addr:postcode":"8562",
    "addr:street":"Zirknitzberg",
    "iso:country":"AT",
    "sg:address":"Zirknitzberg 2",
    "sg:city":"Mooskirchen",
    "sg:orig_category":"Transportunternehmen",
    "sg:phone":"+43 3463 81583",
    "sg:postcode":"8562",
    "sg:province":"Steiermark",
    "wof:name":"Spari & Gr\u00fcnwald Transporte KEG",
    "wof:placetype":"venue"
},
  "geometry": {"coordinates":[15.2464008331,46.9670372009],"type":"Point"}
}