{
  "type": "Feature",
  "properties": {
    "addr:full":"Gewerbestra\u00dfe Ost 7 Niedernsill Salzburg 5722",
    "addr:housenumber":"7",
    "addr:postcode":"5722",
    "addr:street":"Gewerbestrasse Ost;Salzburg",
    "iso:country":"AT",
    "sg:address":"Gewerbestra\u00dfe Ost 7",
    "sg:city":"Niedernsill",
    "sg:orig_category":"Autoreparatur",
    "sg:phone":"+43 4365 4881420",
    "sg:postcode":"5722",
    "sg:province":"Salzburg",
    "wof:name":"Egger Alfred GmbH",
    "wof:placetype":"venue"
},
  "geometry": {"coordinates":[12.6475505829,47.280960083],"type":"Point"}
}