{
  "type": "Feature",
  "properties": {
    "addr:full":"Mill\u00f6ckerg 35 Dornbirn Vorarlberg 6850",
    "addr:housenumber":"35",
    "addr:postcode":"6850",
    "addr:street":"Milloeckerg",
    "iso:country":"AT",
    "sg:address":"Mill\u00f6ckerg 35",
    "sg:city":"Dornbirn",
    "sg:orig_category":"Werbegrafik- U Grafik-Design",
    "sg:phone":"+43 4355 7223515",
    "sg:postcode":"6850",
    "sg:province":"Vorarlberg",
    "wof:name":"Aries Werbegrafik-Design Witzemann",
    "wof:placetype":"venue"
},
  "geometry": {"coordinates":[9.7437801361,47.4131889343],"type":"Point"}
}