{
  "type": "Feature",
  "properties": {
    "addr:full":"Bahnhofstr 10 Windischgarsten Ober\u00f6sterreich 4580",
    "addr:housenumber":"10",
    "addr:postcode":"4580",
    "addr:street":"Bahnhofstr",
    "iso:country":"AT",
    "sg:address":"Bahnhofstr 10",
    "sg:city":"Windischgarsten",
    "sg:orig_category":"Banken U Sparkassen",
    "sg:phone":"+43 4375 6252310",
    "sg:postcode":"4580",
    "sg:province":"Ober\u00f6sterreich",
    "wof:name":"Bankomat d Sparkasse Kremstal-Pyhrn AG",
    "wof:placetype":"venue"
},
  "geometry": {"coordinates":[14.3279800415,47.7206039429],"type":"Point"}
}