{
  "type": "Feature",
  "properties": {
    "iso:country":"AT",
    "sg:address":"Schulg 36",
    "sg:city":"Wien",
    "sg:orig_category":"Architekten",
    "sg:phone":"+43 1 40387570",
    "sg:postcode":"1180",
    "sg:province":"Wien",
    "wof:name":"BUS ARCHITEKTUR - Mag Laura Spinadel - Mag Rainer Lalics",
    "wof:placetype":"venue"
},
  "geometry": {"coordinates":[16.3429069519,48.2252044678],"type":"Point"}
}