{
  "type": "Feature",
  "properties": {
    "iso:country":"AT",
    "sg:address":"Bichlstr 18",
    "sg:city":"Kitzb\u00fchel",
    "sg:orig_category":"Ingenieurkonsulenten / Zivilingenieure",
    "sg:phone":"+43 5356 753050",
    "sg:postcode":"6370",
    "sg:province":"Tirol",
    "wof:name":"Klingler Josef Dipl-Ing",
    "wof:placetype":"venue"
},
  "geometry": {"coordinates":[12.3924150467,47.4448547363],"type":"Point"}
}