{
  "type": "Feature",
  "properties": {
    "iso:country":"AT",
    "sg:address":"Schulstr 31",
    "sg:city":"Obergr\u00fcnburg",
    "sg:orig_category":"Non-Classified Establishments",
    "sg:phone":"+43 7257 8205",
    "sg:postcode":"4593",
    "sg:province":"Ober\u00f6sterreich",
    "wof:name":"Pfarramt",
    "wof:placetype":"venue"
},
  "geometry": {"coordinates":[14.2545108795,47.9541397095],"type":"Point"}
}