{
  "type": "Feature",
  "properties": {
    "addr:full":"Pfarrg 2 Schladming Steiermark 8970",
    "addr:housenumber":"2",
    "addr:postcode":"8970",
    "addr:street":"Pfarrg",
    "iso:country":"AT",
    "sg:address":"Pfarrg 2",
    "sg:city":"Schladming",
    "sg:orig_category":"Innenarchitekten",
    "sg:phone":"+43 3687 22545",
    "sg:postcode":"8970",
    "sg:province":"Steiermark",
    "wof:name":"Schrempf August",
    "wof:placetype":"venue"
},
  "geometry": {"coordinates":[13.6869354248,47.3917236328],"type":"Point"}
}