{
  "type": "Feature",
  "properties": {
    "iso:country":"AT",
    "sg:address":"Wohnpark 7",
    "sg:city":"St. Georgen an der Gusen",
    "sg:orig_category":"Farb-, Stil- U Typberatung",
    "sg:phone":"+43 4366 44545466",
    "sg:postcode":"4222",
    "sg:province":"Ober\u00f6sterreich",
    "wof:name":"Hanl Carmen",
    "wof:placetype":"venue"
},
  "geometry": {"coordinates":[14.4460496902,48.2764205933],"type":"Point"}
}