{
  "type": "Feature",
  "properties": {
    "iso:country":"AT",
    "sg:address":"Dr.-Hubert-Kravcar-Pl 1",
    "sg:city":"Voitsberg",
    "sg:orig_category":"Werbegrafik- U Grafik-Design",
    "sg:phone":"+43 4331 4222510",
    "sg:postcode":"8570",
    "sg:province":"Steiermark",
    "wof:name":"CPS-Copy Print Studio",
    "wof:placetype":"venue"
},
  "geometry": {"coordinates":[15.149353981,47.0477218628],"type":"Point"}
}