{
  "type": "Feature",
  "properties": {
    "iso:country":"AT",
    "sg:address":"Nr 255",
    "sg:city":"Selzthal",
    "sg:orig_category":"Lebensmittel / Einzelhandel",
    "sg:phone":"+43 3616 229",
    "sg:postcode":"8900",
    "sg:province":"Steiermark",
    "wof:name":"Stieg Alfred",
    "wof:placetype":"venue"
},
  "geometry": {"coordinates":[14.3138341904,47.5491828918],"type":"Point"}
}