{
  "type": "Feature",
  "properties": {
    "addr:full":"Zementwerkstr. 25  Ludesch Vorarlberg 6713",
    "addr:housenumber":"25",
    "addr:postcode":"6713",
    "addr:street":"Zementwerkstr.",
    "iso:country":"AT",
    "sg:address":"Zementwerkstr. 25 ",
    "sg:city":"Ludesch",
    "sg:classifiers":[
        {
            "category":"Home & Garden",
            "subcategory":"Home Furnishings",
            "type":"Retail Goods"
        }
    ],
    "sg:phone":"+43 4355 502441",
    "sg:postcode":"6713",
    "sg:province":"Vorarlberg",
    "sg:tags":[
        "household"
    ],
    "wof:name":"WUCHER HOLZBAU GMBH & CO KG",
    "wof:placetype":"venue"
},
  "geometry": {"coordinates":[9.7755002975,47.1797294617],"type":"Point"}
}