{
  "type": "Feature",
  "properties": {
    "addr:full":"Plankengasse 6 Wien Wien 1010",
    "addr:housenumber":"6",
    "addr:postcode":"1010",
    "addr:street":"Plankengasse",
    "iso:country":"AT",
    "sg:address":"Plankengasse 6",
    "sg:city":"Wien",
    "sg:classifiers":[
        {
            "category":"Shopping",
            "subcategory":"Antiques",
            "type":"Retail Goods"
        }
    ],
    "sg:phone":"+43 1 51258850",
    "sg:postcode":"1010",
    "sg:province":"Wien",
    "sg:website":"ds-antiques.com",
    "wof:name":"Discogast - Diskotheken und Gastronomie Betriebsges.m.b.H.",
    "wof:placetype":"venue"
},
  "geometry": {"coordinates":[16.3693504333,48.2068099976],"type":"Point"}
}