{
  "type": "Feature",
  "properties": {
    "addr:full":"Ringstr 35 Krems an der Donau Nieder\u00f6sterreich 3500",
    "addr:housenumber":"35",
    "addr:postcode":"3500",
    "addr:street":"Ringstr",
    "iso:country":"AT",
    "sg:address":"Ringstr 35",
    "sg:city":"Krems an der Donau",
    "sg:orig_category":"Nachhilfe U Lernbetreuung",
    "sg:phone":"+43 4327 3275991",
    "sg:postcode":"3500",
    "sg:province":"Nieder\u00f6sterreich",
    "sg:website":"rampitsch.at",
    "wof:name":"IFL - Institut f Lernhilfe",
    "wof:placetype":"venue"
},
  "geometry": {"coordinates":[15.5990056992,48.4081420898],"type":"Point"}
}