{
  "type": "Feature",
  "properties": {
    "addr:full":"Marktpl. 12 Mooskirchen Steiermark 8562",
    "addr:housenumber":"12",
    "addr:postcode":"8562",
    "addr:street":"Marktpl.",
    "iso:country":"AT",
    "sg:address":"Marktpl. 12",
    "sg:city":"Mooskirchen",
    "sg:classifiers":[
        {
            "category":"Food & Beverages",
            "subcategory":"Groceries & Convenience Stores",
            "type":"Retail Goods"
        }
    ],
    "sg:phone":"+43 4331 372232",
    "sg:postcode":"8562",
    "sg:province":"Steiermark",
    "sg:tags":[
        "drink"
    ],
    "wof:name":"HOCHSTRASSER MOOSKIRCHNER FEINDESTILLERIE FA HOCHSTRASSER",
    "wof:placetype":"venue"
},
  "geometry": {"coordinates":[15.2824201584,46.9843139648],"type":"Point"}
}