{
  "type": "Feature",
  "properties": {
    "addr:full":"Hardtmuthg 34 Wien Wien 1100",
    "addr:housenumber":"34",
    "addr:postcode":"1100",
    "addr:street":"Hardtmuthg",
    "iso:country":"AT",
    "sg:address":"Hardtmuthg 34",
    "sg:city":"Wien",
    "sg:orig_category":"Handelsagenturen",
    "sg:phone":"+43 1 6025132",
    "sg:postcode":"1100",
    "sg:province":"Wien",
    "wof:name":"Aringer H V",
    "wof:placetype":"venue"
},
  "geometry": {"coordinates":[16.3746051788,48.1695632935],"type":"Point"}
}