{
  "type": "Feature",
  "properties": {
    "iso:country":"AT",
    "sg:address":"Thaliastr 16",
    "sg:city":"Wien",
    "sg:orig_category":"Psychotherapie",
    "sg:phone":"+43 1 4081042",
    "sg:postcode":"1160",
    "sg:province":"Wien",
    "wof:name":"Andritsch-Kretz Irmgard Dr",
    "wof:placetype":"venue"
},
  "geometry": {"coordinates":[16.3361167908,48.2090911865],"type":"Point"}
}