{
  "type": "Feature",
  "properties": {
    "iso:country":"AT",
    "sg:address":"Untere Ortsstr 82",
    "sg:city":"Winzendorf",
    "sg:orig_category":"Transportunternehmen",
    "sg:phone":"+43 2638 22077",
    "sg:postcode":"2722",
    "sg:province":"Nieder\u00f6sterreich",
    "wof:name":"Dinhobel GesmbH",
    "wof:placetype":"venue"
},
  "geometry": {"coordinates":[16.1118373871,47.8077926636],"type":"Point"}
}