{
  "type": "Feature",
  "properties": {
    "addr:full":"M Bayrhammer-Str 1 Seekirchen am Wallersee Salzburg 5201",
    "addr:housenumber":"1",
    "addr:postcode":"5201",
    "addr:street":"Salzburg",
    "iso:country":"AT",
    "sg:address":"M Bayrhammer-Str 1",
    "sg:city":"Seekirchen am Wallersee",
    "sg:orig_category":"Stahlbau",
    "sg:phone":"+43 6212 22640",
    "sg:postcode":"5201",
    "sg:province":"Salzburg",
    "wof:name":"Asen Franz KG",
    "wof:placetype":"venue"
},
  "geometry": {"coordinates":[13.1259384155,47.8936538696],"type":"Point"}
}