{
  "type": "Feature",
  "properties": {
    "addr:full":"Atzlergasse 2 Wien Wien 1230",
    "addr:housenumber":"2",
    "addr:postcode":"1230",
    "addr:street":"Atzlergasse",
    "iso:country":"AT",
    "sg:address":"Atzlergasse 2",
    "sg:city":"Wien",
    "sg:classifiers":[
        {
            "category":"Banks & Credit Unions",
            "subcategory":"Investment Brokerage",
            "type":"Services"
        }
    ],
    "sg:phone":"+43 1 6091255",
    "sg:postcode":"1230",
    "sg:province":"Wien",
    "sg:tags":[
        "shop",
        "plants",
        "technical",
        "factory",
        "machine",
        "cleaning"
    ],
    "wof:name":"EVW Geb\u00e4udereinigungs GmbH",
    "wof:placetype":"venue"
},
  "geometry": {"coordinates":[16.3206386566,48.1290054321],"type":"Point"}
}