{
  "type": "Feature",
  "properties": {
    "addr:full":"Unken 33  Unken Salzburg 5091",
    "addr:housenumber":"33",
    "addr:postcode":"5091",
    "addr:street":"Unken;Salzburg",
    "iso:country":"AT",
    "sg:address":"Unken 33 ",
    "sg:city":"Unken",
    "sg:orig_category":"CarpenterS Work Supraregional",
    "sg:phone":"+43 6589 42720",
    "sg:postcode":"5091",
    "sg:province":"Salzburg",
    "wof:name":"Holzbau Herbst Ges.m.b.H. & Co KG",
    "wof:placetype":"venue"
},
  "geometry": {"coordinates":[12.727481842,47.6388397217],"type":"Point"}
}