{
  "type": "Feature",
  "properties": {
    "addr:full":"Lichtenbergstr 3 Linz Ober\u00f6sterreich 4040",
    "addr:housenumber":"3",
    "addr:postcode":"4040",
    "addr:street":"Lichtenbergstr",
    "iso:country":"AT",
    "sg:address":"Lichtenbergstr 3",
    "sg:city":"Linz",
    "sg:orig_category":"Bibliotheken",
    "sg:phone":"+43 7239 20321",
    "sg:postcode":"4040",
    "sg:province":"Ober\u00f6sterreich",
    "wof:name":"B\u00fccherei d Gemeinde Lichtenberg",
    "wof:placetype":"venue"
},
  "geometry": {"coordinates":[14.3393220901,48.3345298767],"type":"Point"}
}