{
  "type": "Feature",
  "properties": {
    "iso:country":"AT",
    "sg:address":"Hammerpl 25a",
    "sg:city":"Eisenerz",
    "sg:orig_category":"Damenmoden",
    "sg:phone":"+43 4338 4860097",
    "sg:postcode":"8790",
    "sg:province":"Steiermark",
    "wof:name":"KiK Textilien u Non-Food GesmbH",
    "wof:placetype":"venue"
},
  "geometry": {"coordinates":[14.8800897598,47.5464706421],"type":"Point"}
}