{
  "type": "Feature",
  "properties": {
    "addr:full":"Maurer Lange Gasse 11 Wien Wien 1230",
    "addr:housenumber":"11",
    "addr:postcode":"1230",
    "addr:street":"Maurer Lange Gasse",
    "iso:country":"AT",
    "sg:address":"Maurer Lange Gasse 11",
    "sg:city":"Wien",
    "sg:orig_category":"Trade In Classic, Veteran, And Vintage Cars",
    "sg:phone":"+43 1 48152240",
    "sg:postcode":"1230",
    "sg:province":"Wien",
    "sg:website":"niemehrsockenwaschen.at",
    "wof:name":"VIDEOMATIC Handelsges.m.b.H.",
    "wof:placetype":"venue"
},
  "geometry": {"coordinates":[16.2753353119,48.1479911804],"type":"Point"}
}