{
  "type": "Feature",
  "properties": {
    "addr:full":"Untere Hauptstr 48 Neusiedl am See Burgenland 7100",
    "addr:housenumber":"48",
    "addr:postcode":"7100",
    "addr:street":"Untere Hauptstr",
    "iso:country":"AT",
    "sg:address":"Untere Hauptstr 48",
    "sg:city":"Neusiedl am See",
    "sg:orig_category":"Restaurants: Chinesisch",
    "sg:phone":"+43 2167 40295",
    "sg:postcode":"7100",
    "sg:province":"Burgenland",
    "wof:name":"Chinarestaurant YING",
    "wof:placetype":"venue"
},
  "geometry": {"coordinates":[16.8466968536,47.9462547302],"type":"Point"}
}