{
  "type": "Feature",
  "properties": {
    "addr:full":"Gewerbezone 4 Flaurling Tirol 6403",
    "addr:housenumber":"4",
    "addr:postcode":"6403",
    "addr:street":"Gewerbezone;Tirol",
    "iso:country":"AT",
    "sg:address":"Gewerbezone 4",
    "sg:city":"Flaurling",
    "sg:classifiers":[
        {
            "category":"Building & Trades",
            "subcategory":"Pest Control",
            "type":"Services"
        }
    ],
    "sg:phone":"+43 5262 646260",
    "sg:postcode":"6403",
    "sg:province":"Tirol",
    "sg:tags":[
        "pneumatic",
        "logic",
        "devices",
        "fluidic"
    ],
    "sg:website":"sfs-fluidsysteme.com",
    "wof:name":"SFS-Fluidtechnische Systeme GmbH Hersteller von Sonderl\u00f6sungen",
    "wof:placetype":"venue"
},
  "geometry": {"coordinates":[11.1503076553,47.281337738],"type":"Point"}
}