{
  "type": "Feature",
  "properties": {
    "addr:full":"Stremayrg 11 Graz Steiermark 8010",
    "addr:housenumber":"11",
    "addr:postcode":"8010",
    "addr:street":"Stremayrg",
    "iso:country":"AT",
    "sg:address":"Stremayrg 11",
    "sg:city":"Graz",
    "sg:orig_category":"Institute",
    "sg:phone":"+43 4331 68737151",
    "sg:postcode":"8010",
    "sg:province":"Steiermark",
    "wof:name":"Inst f Materialpr\u00fcfung u Baustofftechnologie",
    "wof:placetype":"venue"
},
  "geometry": {"coordinates":[15.4511508942,47.0643615723],"type":"Point"}
}