{
  "type": "Feature",
  "properties": {
    "addr:full":"Gersthofer Str 6 Wien Wien 1180",
    "addr:housenumber":"6",
    "addr:postcode":"1180",
    "addr:street":"Str",
    "iso:country":"AT",
    "sg:address":"Gersthofer Str 6",
    "sg:city":"Wien",
    "sg:orig_category":"Installationsunternehmen",
    "sg:phone":"+43 4319 135277",
    "sg:postcode":"1180",
    "sg:province":"Wien",
    "sg:website":"installationen-kouba.at.tt",
    "wof:name":"Kouba Gerhard",
    "wof:placetype":"venue"
},
  "geometry": {"coordinates":[16.3285331726,48.2323532104],"type":"Point"}
}