{
  "type": "Feature",
  "properties": {
    "iso:country":"AT",
    "sg:address":"Hauptstr 102",
    "sg:city":"Hollenburg",
    "sg:orig_category":"Maschinenhandel",
    "sg:phone":"+43 2739 2284",
    "sg:postcode":"3506",
    "sg:province":"Nieder\u00f6sterreich",
    "wof:name":"Mei\u00dfner Lutz",
    "wof:placetype":"venue"
},
  "geometry": {"coordinates":[15.6919670105,48.3797721863],"type":"Point"}
}