{
  "type": "Feature",
  "properties": {
    "iso:country":"AT",
    "sg:address":"Benediktinerpl. 10",
    "sg:city":"Klagenfurt",
    "sg:classifiers":[
        {
            "category":"Travel",
            "subcategory":"Travel Agent",
            "type":"Entertainment"
        }
    ],
    "sg:phone":"+43 4346 3508707",
    "sg:postcode":"9020",
    "sg:province":"K\u00e4rnten",
    "sg:tags":[
        "business"
    ],
    "wof:name":"MUSIL BETRIEBS GMBH",
    "wof:placetype":"venue"
},
  "geometry": {"coordinates":[14.3061237335,46.6223754883],"type":"Point"}
}