{
  "type": "Feature",
  "properties": {
    "addr:full":"Conrad-von-H\u00f6tzendorf-Str 91 Graz Steiermark 8010",
    "addr:housenumber":"91",
    "addr:postcode":"8010",
    "addr:street":"Conrad-Von-Hoetzendorf-Str",
    "iso:country":"AT",
    "sg:address":"Conrad-von-H\u00f6tzendorf-Str 91",
    "sg:city":"Graz",
    "sg:orig_category":"Restaurants: Amerikanisch",
    "sg:phone":"+43 4331 64719090",
    "sg:postcode":"8010",
    "sg:province":"Steiermark",
    "wof:name":"McDonald's Restaurant - McDrive",
    "wof:placetype":"venue"
},
  "geometry": {"coordinates":[15.4477729797,47.0556488037],"type":"Point"}
}