{
  "type": "Feature",
  "properties": {
    "addr:full":"Dorfring 16 Frauental an der La\u00dfnitz Steiermark 8523",
    "addr:housenumber":"16",
    "addr:postcode":"8523",
    "addr:street":"Dorfring",
    "iso:country":"AT",
    "sg:address":"Dorfring 16",
    "sg:city":"Frauental an der La\u00dfnitz",
    "sg:orig_category":"Feuerwehren",
    "sg:phone":"+43 3462 2744",
    "sg:postcode":"8523",
    "sg:province":"Steiermark",
    "wof:name":"Freiwillige Feuerwehr Freidorf",
    "wof:placetype":"venue"
},
  "geometry": {"coordinates":[15.2559175491,46.8265342712],"type":"Point"}
}