{
  "type": "Feature",
  "properties": {
    "iso:country":"AT",
    "sg:address":"Billrothstr 29/7",
    "sg:city":"Wien",
    "sg:orig_category":"Architekten",
    "sg:phone":"+43 1 3690203",
    "sg:postcode":"1190",
    "sg:province":"Wien",
    "wof:name":"M\u00fcck Wolfgang",
    "wof:placetype":"venue"
},
  "geometry": {"coordinates":[16.3493824005,48.2360038757],"type":"Point"}
}