{
  "type": "Feature",
  "properties": {
    "addr:full":"Nestroypl 1 Wien Wien 1020",
    "addr:housenumber":"1",
    "addr:postcode":"1020",
    "addr:street":"Nestroypl",
    "iso:country":"AT",
    "sg:address":"Nestroypl 1",
    "sg:city":"Wien",
    "sg:orig_category":"Finanz- U Wirtschaftsberatung",
    "sg:phone":"+43 4312 188155",
    "sg:postcode":"1020",
    "sg:province":"Wien",
    "wof:name":"heller & pfennig KG",
    "wof:placetype":"venue"
},
  "geometry": {"coordinates":[16.3848514557,48.2143974304],"type":"Point"}
}