{
  "type": "Feature",
  "properties": {
    "iso:country":"AT",
    "sg:address":"Nikolaipl 1",
    "sg:city":"Mureck",
    "sg:orig_category":"Textilwaren / Einzelhandel",
    "sg:phone":"+43 3472 3269",
    "sg:postcode":"8480",
    "sg:province":"Steiermark",
    "wof:name":"Kolletnigg Textil",
    "wof:placetype":"venue"
},
  "geometry": {"coordinates":[15.7761068344,46.7082366943],"type":"Point"}
}