{
  "type": "Feature",
  "properties": {
    "iso:country":"AT",
    "sg:address":"Dorf 12a",
    "sg:city":"Niederndorf",
    "sg:orig_category":"Fu\u00c3\u0178pflege U Fu\u00c3\u0178pflegesalons",
    "sg:phone":"+43 4353 7362137",
    "sg:postcode":"6342",
    "sg:province":"Tirol",
    "wof:name":"Go\u00dfner Andrea",
    "wof:placetype":"venue"
},
  "geometry": {"coordinates":[12.2139883041,47.65102005],"type":"Point"}
}