{
  "type": "Feature",
  "properties": {
    "addr:full":"Reinprechtsdorf Str 1c Wien Wien 1050",
    "addr:housenumber":"1c",
    "addr:postcode":"1050",
    "addr:street":"Reinprechtsdorf Str",
    "iso:country":"AT",
    "sg:address":"Reinprechtsdorf Str 1c",
    "sg:city":"Wien",
    "sg:orig_category":"Friseure U Frisiersalons",
    "sg:phone":"+43 1 5446325",
    "sg:postcode":"1050",
    "sg:province":"Wien",
    "sg:website":"www.rothen.co.at",
    "wof:name":"Haarstudio Rothen",
    "wof:placetype":"venue"
},
  "geometry": {"coordinates":[16.3578910828,48.1816368103],"type":"Point"}
}