{
  "type": "Feature",
  "properties": {
    "iso:country":"AT",
    "sg:address":"Ringstr 96",
    "sg:city":"Wilfersdorf",
    "sg:orig_category":"Feuerwehren",
    "sg:phone":"+43 4325 7325544",
    "sg:postcode":"2193",
    "sg:province":"Nieder\u00f6sterreich",
    "wof:name":"Freiwillige Feuerwehr",
    "wof:placetype":"venue"
},
  "geometry": {"coordinates":[16.6676063538,48.595500946],"type":"Point"}
}