{
  "type": "Feature",
  "properties": {
    "addr:full":"Haidfeldstr 33 Leonding Ober\u00f6sterreich 4060",
    "addr:housenumber":"33",
    "addr:postcode":"4060",
    "addr:street":"Haidfeldstr",
    "iso:country":"AT",
    "sg:address":"Haidfeldstr 33",
    "sg:city":"Leonding",
    "sg:orig_category":"Fahrschulen",
    "sg:phone":"+43 4373 2677756",
    "sg:postcode":"4060",
    "sg:province":"Ober\u00f6sterreich",
    "wof:name":"Fahrschule Snopek Ing",
    "wof:placetype":"venue"
},
  "geometry": {"coordinates":[14.2599143982,48.2564353943],"type":"Point"}
}