{
  "type": "Feature",
  "properties": {
    "addr:full":"Bahnhofstrasse 10 Paternion K\u00e4rnten 9711",
    "addr:housenumber":"10",
    "addr:postcode":"9711",
    "addr:street":"Bahnhofstrasse;Kaernten",
    "iso:country":"AT",
    "sg:address":"Bahnhofstrasse 10",
    "sg:city":"Paternion",
    "sg:classifiers":[
        {
            "category":"Government",
            "subcategory":"Fire Station",
            "type":"Public Place"
        }
    ],
    "sg:phone":"+43 4245 24190",
    "sg:postcode":"9711",
    "sg:province":"K\u00e4rnten",
    "sg:tags":[
        "thermal",
        "power",
        "block-type"
    ],
    "sg:website":"oberdorfer.at",
    "wof:name":"Oberdorfer Kraft-W\u00e4rme-Kopplung GmbH",
    "wof:placetype":"venue"
},
  "geometry": {"coordinates":[13.6415052414,46.7165794373],"type":"Point"}
}