{
  "type": "Feature",
  "properties": {
    "addr:full":"Puchberger Str 105 Winzendorf Nieder\u00f6sterreich 2722",
    "addr:housenumber":"105",
    "addr:postcode":"2722",
    "addr:street":"Str",
    "iso:country":"AT",
    "sg:address":"Puchberger Str 105",
    "sg:city":"Winzendorf",
    "sg:orig_category":"Tischlereien",
    "sg:phone":"+43 4326 3822255",
    "sg:postcode":"2722",
    "sg:province":"Nieder\u00f6sterreich",
    "wof:name":"Senftl Herbert",
    "wof:placetype":"venue"
},
  "geometry": {"coordinates":[16.1118373871,47.8077926636],"type":"Point"}
}