{
  "type": "Feature",
  "properties": {
    "addr:full":"Neunkirchner Str 119 Wiener Neustadt Nieder\u00f6sterreich 2700",
    "addr:postcode":"2700",
    "iso:country":"AT",
    "sg:address":"Neunkirchner Str 119",
    "sg:city":"Wiener Neustadt",
    "sg:orig_category":"Abfallentsorgung U -Verwertung",
    "sg:phone":"+43 4326 2287215",
    "sg:postcode":"2700",
    "sg:province":"Nieder\u00f6sterreich",
    "wof:name":"A S A Abfallservice AG",
    "wof:placetype":"venue"
},
  "geometry": {"coordinates":[16.224647522,47.7981147766],"type":"Point"}
}