{
  "type": "Feature",
  "properties": {
    "addr:full":"Lindfeldg 9 Judenburg Steiermark 8750",
    "addr:housenumber":"9",
    "addr:postcode":"8750",
    "addr:street":"Lindfeldg",
    "iso:country":"AT",
    "sg:address":"Lindfeldg 9",
    "sg:city":"Judenburg",
    "sg:orig_category":"Hauptschulen",
    "sg:phone":"+43 3572 83888",
    "sg:postcode":"8750",
    "sg:province":"Steiermark",
    "wof:name":"Hauptschule 1 Dr Karl Renner",
    "wof:placetype":"venue"
},
  "geometry": {"coordinates":[14.6697015762,47.1683654785],"type":"Point"}
}