{
  "type": "Feature",
  "properties": {
    "addr:full":"Waidhofner Str 2-4 Amstetten Nieder\u00f6sterreich 3300",
    "addr:housenumber":"2-4",
    "addr:postcode":"3300",
    "addr:street":"Str;Niederoesterreich",
    "iso:country":"AT",
    "sg:address":"Waidhofner Str 2-4",
    "sg:city":"Amstetten",
    "sg:orig_category":"Telekommunikation",
    "sg:phone":"+43 800 699889",
    "sg:postcode":"3300",
    "sg:province":"Nieder\u00f6sterreich",
    "wof:name":"ONE World Amstetten",
    "wof:placetype":"venue"
},
  "geometry": {"coordinates":[14.8694534302,48.1217918396],"type":"Point"}
}