{
  "type": "Feature",
  "properties": {
    "addr:full":"Ronachweg 303 Saalbach Salzburg 5753",
    "addr:housenumber":"303",
    "addr:postcode":"5753",
    "addr:street":"Saalbach Salzburg",
    "iso:country":"AT",
    "sg:address":"Ronachweg 303",
    "sg:city":"Saalbach",
    "sg:orig_category":"Pensionen / Privatzimmer",
    "sg:phone":"+43 6541 6454",
    "sg:postcode":"5753",
    "sg:province":"Salzburg",
    "wof:name":"Pension Vier Jahreszeiten",
    "wof:placetype":"venue"
},
  "geometry": {"coordinates":[12.6459789276,47.3916625977],"type":"Point"}
}