{
  "type": "Feature",
  "properties": {
    "addr:full":"M\u00fchlg 1 Hollabrunn Nieder\u00f6sterreich 2020",
    "addr:housenumber":"1",
    "addr:postcode":"2020",
    "addr:street":"Muehlg",
    "iso:country":"AT",
    "sg:address":"M\u00fchlg 1",
    "sg:city":"Hollabrunn",
    "sg:classifiers":[
        {
            "category":"Shopping",
            "subcategory":"Thrift Store",
            "type":"Retail Goods"
        }
    ],
    "sg:phone":"+43 4329 5230520",
    "sg:postcode":"2020",
    "sg:province":"Nieder\u00f6sterreich",
    "sg:tags":[
        "second-hand-shops"
    ],
    "wof:name":"Luna Textiles Frauenbesch\u00e4ftigungsprojekt Hollabrunn",
    "wof:placetype":"venue"
},
  "geometry": {"coordinates":[16.0783004761,48.5624580383],"type":"Point"}
}