{
  "type": "Feature",
  "properties": {
    "addr:full":"Nr 63 Geistthal Steiermark 8153",
    "addr:postcode":"8153",
    "addr:street":"Nr",
    "iso:country":"AT",
    "sg:address":"Nr 63",
    "sg:city":"Geistthal",
    "sg:orig_category":"Tischlereien",
    "sg:phone":"+43 4331 492209",
    "sg:postcode":"8153",
    "sg:province":"Steiermark",
    "wof:name":"Koller Rudolf",
    "wof:placetype":"venue"
},
  "geometry": {"coordinates":[15.1865959167,47.1377792358],"type":"Point"}
}