{
  "type": "Feature",
  "properties": {
    "addr:full":"G\u00f6sser Str 46 Leoben Steiermark 8700",
    "addr:housenumber":"46",
    "addr:postcode":"8700",
    "addr:street":"Str",
    "iso:country":"AT",
    "sg:address":"G\u00f6sser Str 46",
    "sg:city":"Leoben",
    "sg:orig_category":"Schneidereien",
    "sg:phone":"+43 4338 4222128",
    "sg:postcode":"8700",
    "sg:province":"Steiermark",
    "wof:name":"Heidenreich Johann",
    "wof:placetype":"venue"
},
  "geometry": {"coordinates":[15.0981445312,47.3659515381],"type":"Point"}
}