{
  "type": "Feature",
  "properties": {
    "addr:full":"Hatting 1 St. Marienkirchen am Hausruck Ober\u00f6sterreich 4926",
    "addr:housenumber":"1",
    "addr:postcode":"4926",
    "addr:street":"Hatting",
    "iso:country":"AT",
    "sg:address":"Hatting 1",
    "sg:city":"St. Marienkirchen am Hausruck",
    "sg:orig_category":"Psychotherapie",
    "sg:phone":"+43 4377 533094",
    "sg:postcode":"4926",
    "sg:province":"Ober\u00f6sterreich",
    "wof:name":"Weimann Michael Mag - Da Moarhof",
    "wof:placetype":"venue"
},
  "geometry": {"coordinates":[13.5849199295,48.1851196289],"type":"Point"}
}