{
  "type": "Feature",
  "properties": {
    "addr:full":"Bahnhofg\u00fcrtel 85/Top GE01 Graz Steiermark 8020",
    "addr:housenumber":"85 / top",
    "addr:postcode":"8020",
    "addr:street":"Bahnhofguertel;Ge01",
    "iso:country":"AT",
    "sg:address":"Bahnhofg\u00fcrtel 85/Top GE01",
    "sg:city":"Graz",
    "sg:orig_category":"Telekommunikation",
    "sg:phone":"+43 800 664300",
    "sg:postcode":"8020",
    "sg:province":"Steiermark",
    "wof:name":"A1-Shop Annenpassage Graz",
    "wof:placetype":"venue"
},
  "geometry": {"coordinates":[15.4111499786,47.0689201355],"type":"Point"}
}