{
  "type": "Feature",
  "properties": {
    "addr:full":"Ronthal 3 M\u00fchlbach am Manhartsberg Nieder\u00f6sterreich 3473",
    "addr:housenumber":"3",
    "addr:postcode":"3473",
    "addr:street":"Ronthal;Niederoesterreich",
    "iso:country":"AT",
    "sg:address":"Ronthal 3",
    "sg:city":"M\u00fchlbach am Manhartsberg",
    "sg:classifiers":[
        {
            "category":"Shopping",
            "subcategory":"Gifts & Souvenirs",
            "type":"Retail Goods"
        }
    ],
    "sg:phone":"+43 2957 68820",
    "sg:postcode":"3473",
    "sg:province":"Nieder\u00f6sterreich",
    "sg:tags":[
        "item",
        "ceramic"
    ],
    "sg:website":"ronthal-keramik.at",
    "wof:name":"Ronthal Keramik Haas & Hober OEG",
    "wof:placetype":"venue"
},
  "geometry": {"coordinates":[15.7929344177,48.5032615662],"type":"Point"}
}