{
  "type": "Feature",
  "properties": {
    "iso:country":"AT",
    "sg:address":"Liebhartsg 31",
    "sg:city":"Wien",
    "sg:orig_category":"Psychotherapie",
    "sg:phone":"+43 1 4931858",
    "sg:postcode":"1160",
    "sg:province":"Wien",
    "wof:name":"Herceg-Eichler Susanne F Mag",
    "wof:placetype":"venue"
},
  "geometry": {"coordinates":[16.2879619598,48.2168388367],"type":"Point"}
}