{
  "type": "Feature",
  "properties": {
    "addr:full":"Schulg 8 Krumbach Nieder\u00f6sterreich 2851",
    "addr:housenumber":"8",
    "addr:postcode":"2851",
    "addr:street":"Schulg",
    "iso:country":"AT",
    "sg:address":"Schulg 8",
    "sg:city":"Krumbach",
    "sg:orig_category":"Freizeitangebote U -Einrichtungen",
    "sg:phone":"+43 4326 4742940",
    "sg:postcode":"2851",
    "sg:province":"Nieder\u00f6sterreich",
    "wof:name":"Kultur- u Sportzentrum Krumbach",
    "wof:placetype":"venue"
},
  "geometry": {"coordinates":[16.191701889,47.5226211548],"type":"Point"}
}