{
  "type": "Feature",
  "properties": {
    "addr:full":"Franz-Mair-Str 47 Deutsch Wagram Nieder\u00f6sterreich 2232",
    "addr:housenumber":"47",
    "addr:postcode":"2232",
    "addr:street":"Franz-Mair-Str",
    "iso:country":"AT",
    "sg:address":"Franz-Mair-Str 47",
    "sg:city":"Deutsch Wagram",
    "sg:orig_category":"Wassertechnik",
    "sg:phone":"+43 2247 45700",
    "sg:postcode":"2232",
    "sg:province":"Nieder\u00f6sterreich",
    "wof:name":"Betriebsgesellschaft Marchfeldkanal",
    "wof:placetype":"venue"
},
  "geometry": {"coordinates":[16.5526504517,48.2997817993],"type":"Point"}
}