{
  "type": "Feature",
  "properties": {
    "addr:full":"Augarteng 11 Oberwart Burgenland 7400",
    "addr:housenumber":"11",
    "addr:postcode":"7400",
    "addr:street":"Augarteng",
    "iso:country":"AT",
    "sg:address":"Augarteng 11",
    "sg:city":"Oberwart",
    "sg:orig_category":"Architekten",
    "sg:phone":"+43 3352 34445",
    "sg:postcode":"7400",
    "sg:province":"Burgenland",
    "wof:name":"Fandl Barbara Dipl-Ing Arch - staatl bef und beeid Ziviltechn",
    "wof:placetype":"venue"
},
  "geometry": {"coordinates":[16.2010993958,47.2859420776],"type":"Point"}
}