{
  "type": "Feature",
  "properties": {
    "addr:full":"Anton-Wildgans-G 5 Perchtoldsdorf Nieder\u00f6sterreich 2380",
    "addr:housenumber":"5",
    "addr:postcode":"2380",
    "addr:street":"Anton-Wildgans-G",
    "iso:country":"AT",
    "sg:address":"Anton-Wildgans-G 5",
    "sg:city":"Perchtoldsdorf",
    "sg:orig_category":"Immobilienmakler",
    "sg:phone":"+43 1 8653293",
    "sg:postcode":"2380",
    "sg:province":"Nieder\u00f6sterreich",
    "wof:name":"RED Real Estate Development GmbH",
    "wof:placetype":"venue"
},
  "geometry": {"coordinates":[16.2896842957,48.1256141663],"type":"Point"}
}