{
  "type": "Feature",
  "properties": {
    "iso:country":"AT",
    "sg:address":"Heidenreichsteiner Str 38",
    "sg:city":"Schrems",
    "sg:orig_category":"Berufsschulen",
    "sg:phone":"+43 4328 5377329",
    "sg:postcode":"3943",
    "sg:province":"Nieder\u00f6sterreich",
    "wof:name":"Berufsschule f Steinmetze",
    "wof:placetype":"venue"
},
  "geometry": {"coordinates":[15.0648298264,48.7986755371],"type":"Point"}
}