{
  "type": "Feature",
  "properties": {
    "iso:country":"AT",
    "sg:address":"Schubertstr 11",
    "sg:city":"Innsbruck",
    "sg:orig_category":"Fleischhauereien",
    "sg:phone":"+43 512 588442",
    "sg:postcode":"6020",
    "sg:province":"Tirol",
    "wof:name":"Zach Josef Fleischhauerei & Co",
    "wof:placetype":"venue"
},
  "geometry": {"coordinates":[11.4072999954,47.2759208679],"type":"Point"}
}