{
  "type": "Feature",
  "properties": {
    "addr:full":"Wiener Str 3 Stockerau Nieder\u00f6sterreich 2000",
    "addr:housenumber":"3",
    "addr:postcode":"2000",
    "iso:country":"AT",
    "sg:address":"Wiener Str 3",
    "sg:city":"Stockerau",
    "sg:orig_category":"Handelsagenturen",
    "sg:phone":"+43 2266 62730",
    "sg:postcode":"2000",
    "sg:province":"Nieder\u00f6sterreich",
    "wof:name":"Stockhammer Friedrich",
    "wof:placetype":"venue"
},
  "geometry": {"coordinates":[16.229757309,48.3869171143],"type":"Point"}
}