{
  "type": "Feature",
  "properties": {
    "addr:full":"Talschlu\u00dfweg 1 Hinterglemm Salzburg 5754",
    "addr:housenumber":"1",
    "addr:postcode":"5754",
    "addr:street":"Talschlussweg;Salzburg",
    "iso:country":"AT",
    "sg:address":"Talschlu\u00dfweg 1",
    "sg:city":"Hinterglemm",
    "sg:classifiers":[
        {
            "category":"Park",
            "subcategory":"Provincial",
            "type":"Public Place"
        }
    ],
    "sg:phone":"+43 6541 72550",
    "sg:postcode":"5754",
    "sg:province":"Salzburg",
    "sg:tags":[
        "u",
        "ski-",
        "snowboardschulen"
    ],
    "wof:name":"Skischule Mitterlengau",
    "wof:placetype":"venue"
},
  "geometry": {"coordinates":[12.6012058258,47.3800849915],"type":"Point"}
}