{
  "type": "Feature",
  "properties": {
    "addr:full":"Ferdinand-Raimund-Str 4a Amstetten Nieder\u00f6sterreich 3300",
    "addr:housenumber":"4a",
    "addr:postcode":"3300",
    "addr:street":"Ferdinand-Raimund-Str;Niederoesterreich",
    "iso:country":"AT",
    "sg:address":"Ferdinand-Raimund-Str 4a",
    "sg:city":"Amstetten",
    "sg:orig_category":"Lebensmittel / Einzelhandel",
    "sg:phone":"+43 4374 72625670",
    "sg:postcode":"3300",
    "sg:province":"Nieder\u00f6sterreich",
    "wof:name":"Nah und Frisch - Fritz Rafetseder",
    "wof:placetype":"venue"
},
  "geometry": {"coordinates":[14.8600769043,48.1247138977],"type":"Point"}
}