{
  "type": "Feature",
  "properties": {
    "addr:full":"Gumpendorfer Str 63b Wien Wien 1060",
    "addr:housenumber":"63b",
    "addr:postcode":"1060",
    "addr:street":"Str",
    "iso:country":"AT",
    "sg:address":"Gumpendorfer Str 63b",
    "sg:city":"Wien",
    "sg:orig_category":"Erdarbeiten",
    "sg:phone":"+43 4315 862323",
    "sg:postcode":"1060",
    "sg:province":"Wien",
    "wof:name":"Schmutzer Gottfried",
    "wof:placetype":"venue"
},
  "geometry": {"coordinates":[16.3533363342,48.1972198486],"type":"Point"}
}