{
  "type": "Feature",
  "properties": {
    "iso:country":"AT",
    "sg:address":"Nr 202",
    "sg:city":"Laussa",
    "sg:orig_category":"Postservicestellen",
    "sg:phone":"+43 7255 7236",
    "sg:postcode":"4461",
    "sg:province":"Ober\u00f6sterreich",
    "wof:name":"Postservicestelle Laussa",
    "wof:placetype":"venue"
},
  "geometry": {"coordinates":[14.4546041489,47.9519042969],"type":"Point"}
}