{
  "type": "Feature",
  "properties": {
    "addr:full":"N Pfeifauf-Str 33 Jenbach Tirol 6200",
    "addr:housenumber":"33",
    "addr:postcode":"6200",
    "addr:street":"N;Jenbach Tirol",
    "iso:country":"AT",
    "sg:address":"N Pfeifauf-Str 33",
    "sg:city":"Jenbach",
    "sg:orig_category":"Energiespartechnik",
    "sg:phone":"+43 5244 63482",
    "sg:postcode":"6200",
    "sg:province":"Tirol",
    "wof:name":"Wasserspartechnik Alfred Brachmaier",
    "wof:placetype":"venue"
},
  "geometry": {"coordinates":[11.7624607086,47.3902282715],"type":"Point"}
}