{
  "type": "Feature",
  "properties": {
    "addr:full":"Bankmannring 5 Korneuburg Nieder\u00f6sterreich 2100",
    "addr:housenumber":"5",
    "addr:postcode":"2100",
    "addr:street":"Bankmannring;Niederoesterreich",
    "iso:country":"AT",
    "sg:address":"Bankmannring 5",
    "sg:city":"Korneuburg",
    "sg:orig_category":"Bezirkshauptmannschaften",
    "sg:phone":"+43 2262 90250",
    "sg:postcode":"2100",
    "sg:province":"Nieder\u00f6sterreich",
    "wof:name":"Bezirkshauptmannschaft Korneuburg",
    "wof:placetype":"venue"
},
  "geometry": {"coordinates":[16.3339748383,48.347278595],"type":"Point"}
}