{
  "type": "Feature",
  "properties": {
    "addr:full":"Bahnstr 2 Zell an der Pram Ober\u00f6sterreich 4755",
    "addr:housenumber":"2",
    "addr:postcode":"4755",
    "addr:street":"Bahnstr;Oberoesterreich",
    "iso:country":"AT",
    "sg:address":"Bahnstr 2",
    "sg:city":"Zell an der Pram",
    "sg:orig_category":"Friseure U Frisiersalons",
    "sg:phone":"+43 4377 648327",
    "sg:postcode":"4755",
    "sg:province":"Ober\u00f6sterreich",
    "wof:name":"Friseursalon Murauer",
    "wof:placetype":"venue"
},
  "geometry": {"coordinates":[13.6288232803,48.3170051575],"type":"Point"}
}