{
  "type": "Feature",
  "properties": {
    "addr:full":"Freiling 72 Oftering Ober\u00f6sterreich 4064",
    "addr:housenumber":"72",
    "addr:postcode":"4064",
    "addr:street":"Freiling",
    "iso:country":"AT",
    "sg:address":"Freiling 72",
    "sg:city":"Oftering",
    "sg:orig_category":"Installationsunternehmen",
    "sg:phone":"+43 7221 63193",
    "sg:postcode":"4064",
    "sg:province":"Ober\u00f6sterreich",
    "wof:name":"Humer Herbert Ing",
    "wof:placetype":"venue"
},
  "geometry": {"coordinates":[14.1267137527,48.2428512573],"type":"Point"}
}