{
  "type": "Feature",
  "properties": {
    "addr:full":"Schmerlingpl 8 Wien Wien 1010",
    "addr:housenumber":"8",
    "addr:postcode":"1010",
    "addr:street":"Schmerlingpl",
    "iso:country":"AT",
    "sg:address":"Schmerlingpl 8",
    "sg:city":"Wien",
    "sg:orig_category":"Filmproduktionen",
    "sg:phone":"+43 1 52611480",
    "sg:postcode":"1010",
    "sg:province":"Wien",
    "wof:name":"Praun Locations",
    "wof:placetype":"venue"
},
  "geometry": {"coordinates":[16.3588066101,48.2074203491],"type":"Point"}
}