{
  "type": "Feature",
  "properties": {
    "iso:country":"AT",
    "sg:address":"Anton-Regner-Str 27",
    "sg:city":"Knittelfeld",
    "sg:orig_category":"Behinderungen / Leben Mit Behinderungen",
    "sg:phone":"+43 3512 861580",
    "sg:postcode":"8720",
    "sg:province":"Steiermark",
    "wof:name":"Jugend am Werk Steiermark GmbH - Werkst\u00e4tten",
    "wof:placetype":"venue"
},
  "geometry": {"coordinates":[14.8211297989,47.2169265747],"type":"Point"}
}