{
  "type": "Feature",
  "properties": {
    "addr:full":"Nr 3 Gm\u00fcnd Nieder\u00f6sterreich 3950",
    "addr:postcode":"3950",
    "addr:street":"Nr;Gmuend Niederoesterreich",
    "iso:country":"AT",
    "sg:address":"Nr 3",
    "sg:city":"Gm\u00fcnd",
    "sg:orig_category":"Landwirtschaftliche Produkte",
    "sg:phone":"+43 2852 8469",
    "sg:postcode":"3950",
    "sg:province":"Nieder\u00f6sterreich",
    "wof:name":"Schwingenschl\u00f6gl Johann Landesprodukte - Baumbrennstoffe",
    "wof:placetype":"venue"
},
  "geometry": {"coordinates":[14.9872903824,48.7729454041],"type":"Point"}
}