{
  "type": "Feature",
  "properties": {
    "addr:full":"Neufeldweg 66 Graz Steiermark 8010",
    "addr:housenumber":"66",
    "addr:postcode":"8010",
    "addr:street":"Neufeldweg",
    "iso:country":"AT",
    "sg:address":"Neufeldweg 66",
    "sg:city":"Graz",
    "sg:orig_category":"Werbegrafik- U Grafik-Design",
    "sg:phone":"+43 316 6840392",
    "sg:postcode":"8010",
    "sg:province":"Steiermark",
    "wof:name":"Lazarus Grafikdesign",
    "wof:placetype":"venue"
},
  "geometry": {"coordinates":[15.458729744,47.051399231],"type":"Point"}
}