{
  "type": "Feature",
  "properties": {
    "addr:full":"Rosenkranzg 41a Bad Ischl Ober\u00f6sterreich 4820",
    "addr:housenumber":"41a",
    "addr:postcode":"4820",
    "addr:street":"Rosenkranzg",
    "iso:country":"AT",
    "sg:address":"Rosenkranzg 41a",
    "sg:city":"Bad Ischl",
    "sg:orig_category":"Webdesign",
    "sg:phone":"+43 6132 23100",
    "sg:postcode":"4820",
    "sg:province":"Ober\u00f6sterreich",
    "wof:name":"Blue-point Webdesign & Kassensysteme",
    "wof:placetype":"venue"
},
  "geometry": {"coordinates":[13.6341218948,47.7061691284],"type":"Point"}
}