{
  "type": "Feature",
  "properties": {
    "addr:full":"Liechtensteinstr 68 Wien Wien 1090",
    "addr:housenumber":"68",
    "addr:postcode":"1090",
    "addr:street":"Liechtensteinstr",
    "iso:country":"AT",
    "sg:address":"Liechtensteinstr 68",
    "sg:city":"Wien",
    "sg:orig_category":"Tabaktrafiken",
    "sg:phone":"+43 1 3106829",
    "sg:postcode":"1090",
    "sg:province":"Wien",
    "wof:name":"Wannamacher Kurt",
    "wof:placetype":"venue"
},
  "geometry": {"coordinates":[16.3567886353,48.2266578674],"type":"Point"}
}