{
  "type": "Feature",
  "properties": {
    "addr:full":"Kirchpl 3 Wattens Tirol 6112",
    "addr:housenumber":"3",
    "addr:postcode":"6112",
    "addr:street":"Kirchpl;Tirol",
    "iso:country":"AT",
    "sg:address":"Kirchpl 3",
    "sg:city":"Wattens",
    "sg:orig_category":"Juweliere, Gold- U Silberschmiede",
    "sg:phone":"+43 4352 2452535",
    "sg:postcode":"6112",
    "sg:province":"Tirol",
    "wof:name":"Schmuck Schipflinger GesmbH",
    "wof:placetype":"venue"
},
  "geometry": {"coordinates":[11.5925683975,47.2920913696],"type":"Point"}
}