{
  "type": "Feature",
  "properties": {
    "addr:full":"Schiffg 19 Bruck an der Mur Steiermark 8600",
    "addr:housenumber":"19",
    "addr:postcode":"8600",
    "addr:street":"Schiffg",
    "iso:country":"AT",
    "sg:address":"Schiffg 19",
    "sg:city":"Bruck an der Mur",
    "sg:orig_category":"Installationsunternehmen",
    "sg:phone":"+43 3862 526280",
    "sg:postcode":"8600",
    "sg:province":"Steiermark",
    "wof:name":"Merl Gas Wasser Heizung Klimatechnik GesmbH",
    "wof:placetype":"venue"
},
  "geometry": {"coordinates":[15.2685451508,47.4100990295],"type":"Point"}
}