{
  "type": "Feature",
  "properties": {
    "iso:country":"AT",
    "sg:address":"Therese-Riggle-Str 12",
    "sg:city":"Obernberg am Inn",
    "sg:orig_category":"Elektroinstallationsunternehmen",
    "sg:phone":"+43 7758 4018",
    "sg:postcode":"4982",
    "sg:province":"Ober\u00f6sterreich",
    "wof:name":"Gurtner Josef",
    "wof:placetype":"venue"
},
  "geometry": {"coordinates":[13.3300437927,48.3202438354],"type":"Point"}
}