{
  "type": "Feature",
  "properties": {
    "addr:full":"Hauptplatz 7 Deutschlandsberg Steiermark 8530",
    "addr:housenumber":"7",
    "addr:postcode":"8530",
    "addr:street":"Hauptplatz",
    "iso:country":"AT",
    "sg:address":"Hauptplatz 7",
    "sg:city":"Deutschlandsberg",
    "sg:classifiers":[
        {
            "category":"Home & Garden",
            "subcategory":"Building Materials",
            "type":"Retail Goods"
        }
    ],
    "sg:phone":"+43 3462 2512",
    "sg:postcode":"8530",
    "sg:province":"Steiermark",
    "sg:tags":[
        "glass",
        "enclosures",
        "balcony"
    ],
    "wof:name":"Josef Topolnik",
    "wof:placetype":"venue"
},
  "geometry": {"coordinates":[15.2155704498,46.8150482178],"type":"Point"}
}