{
  "type": "Feature",
  "properties": {
    "addr:full":"Zentrum 36 Kramsach Tirol 6233",
    "addr:housenumber":"36",
    "addr:postcode":"6233",
    "addr:street":"Zentrum;Tirol",
    "iso:country":"AT",
    "sg:address":"Zentrum 36",
    "sg:city":"Kramsach",
    "sg:orig_category":"Motoreninstandsetzung",
    "sg:phone":"+43 5337 653750",
    "sg:postcode":"6233",
    "sg:province":"Tirol",
    "wof:name":"M+M Motor-Service GmbH",
    "wof:placetype":"venue"
},
  "geometry": {"coordinates":[11.8838882446,47.4470901489],"type":"Point"}
}