{
  "type": "Feature",
  "properties": {
    "addr:full":"Hauptstr 30 Spitz Nieder\u00f6sterreich 3620",
    "addr:housenumber":"30",
    "addr:postcode":"3620",
    "addr:street":"Hauptstr",
    "iso:country":"AT",
    "sg:address":"Hauptstr 30",
    "sg:city":"Spitz",
    "sg:orig_category":"Hafnereien",
    "sg:phone":"+43 2713 2818",
    "sg:postcode":"3620",
    "sg:province":"Nieder\u00f6sterreich",
    "wof:name":"Erlinger Johann",
    "wof:placetype":"venue"
},
  "geometry": {"coordinates":[15.4142923355,48.3622436523],"type":"Point"}
}