{
  "type": "Feature",
  "properties": {
    "iso:country":"AT",
    "sg:address":"Schlachthausg 3/1",
    "sg:city":"Wien",
    "sg:orig_category":"Lebens- U Sozialberatung",
    "sg:phone":"+43 4317 980891",
    "sg:postcode":"1030",
    "sg:province":"Wien",
    "wof:name":"Ederer Gerty LIMA Ged\u00e4chtnistrainerin",
    "wof:placetype":"venue"
},
  "geometry": {"coordinates":[16.4094028473,48.1958885193],"type":"Point"}
}