{
  "type": "Feature",
  "properties": {
    "addr:full":"Hollandstr 14 Wien Wien 1020",
    "addr:housenumber":"14",
    "addr:postcode":"1020",
    "addr:street":"Hollandstr",
    "iso:country":"AT",
    "sg:address":"Hollandstr 14",
    "sg:city":"Wien",
    "sg:orig_category":"Psychotherapie",
    "sg:phone":"+43 1 2162833",
    "sg:postcode":"1020",
    "sg:province":"Wien",
    "wof:name":"Zidek Brigitte Dr",
    "wof:placetype":"venue"
},
  "geometry": {"coordinates":[16.3772678375,48.2159156799],"type":"Point"}
}