{
  "type": "Feature",
  "properties": {
    "addr:full":"Am Bahnhof 7 Kefermarkt Ober\u00f6sterreich 4292",
    "addr:housenumber":"7",
    "addr:postcode":"4292",
    "addr:street":"Am Bahnhof",
    "iso:country":"AT",
    "sg:address":"Am Bahnhof 7",
    "sg:city":"Kefermarkt",
    "sg:orig_category":"Blechbe- U -Verarbeitung",
    "sg:phone":"+43 4379 4720590",
    "sg:postcode":"4292",
    "sg:province":"Ober\u00f6sterreich",
    "wof:name":"BGtech GmbH",
    "wof:placetype":"venue"
},
  "geometry": {"coordinates":[14.5385417938,48.4386558533],"type":"Point"}
}