{
  "type": "Feature",
  "properties": {
    "iso:country":"AT",
    "sg:address":"Bahnhofpl 9",
    "sg:city":"Stockerau",
    "sg:orig_category":"Politische Parteien",
    "sg:phone":"+43 2266 62748",
    "sg:postcode":"2000",
    "sg:province":"Nieder\u00f6sterreich",
    "wof:name":"Sozialdemokratische Partei \u00f6sterreichs",
    "wof:placetype":"venue"
},
  "geometry": {"coordinates":[16.2116508484,48.3831443787],"type":"Point"}
}