{
  "type": "Feature",
  "properties": {
    "iso:country":"AT",
    "sg:address":"Hauptpl 1",
    "sg:city":"Irdning",
    "sg:orig_category":"Non-Classified Establishments",
    "sg:phone":"+43 3682 224180",
    "sg:postcode":"8952",
    "sg:province":"Steiermark",
    "wof:name":"Pfarramt",
    "wof:placetype":"venue"
},
  "geometry": {"coordinates":[14.1046161652,47.5055541992],"type":"Point"}
}