{
  "type": "Feature",
  "properties": {
    "addr:full":"March 1 Ellmau Tirol 6352",
    "addr:housenumber":"1",
    "addr:postcode":"6352",
    "addr:street":"March;Tirol",
    "iso:country":"AT",
    "sg:address":"March 1",
    "sg:city":"Ellmau",
    "sg:orig_category":"Pensionen / Privatzimmer",
    "sg:phone":"+43 5358 2743",
    "sg:postcode":"6352",
    "sg:province":"Tirol",
    "wof:name":"Pension Aufschnaiter",
    "wof:placetype":"venue"
},
  "geometry": {"coordinates":[12.3138628006,47.5080566406],"type":"Point"}
}