{
  "type": "Feature",
  "properties": {
    "addr:full":"Neutorstr 14 Salzburg Salzburg 5020",
    "addr:housenumber":"14",
    "addr:postcode":"5020",
    "addr:street":"Neutorstr;Salzburg",
    "iso:country":"AT",
    "sg:address":"Neutorstr 14",
    "sg:city":"Salzburg",
    "sg:orig_category":"Sonnenschutzanlagen",
    "sg:phone":"+43 662 820830",
    "sg:postcode":"5020",
    "sg:province":"Salzburg",
    "wof:name":"Arquati GesmbH",
    "wof:placetype":"venue"
},
  "geometry": {"coordinates":[13.0360841751,47.7976875305],"type":"Point"}
}