{
  "type": "Feature",
  "properties": {
    "addr:full":"Goldbergstr 38 Bad Hofgastein Salzburg 5630",
    "addr:housenumber":"38",
    "addr:postcode":"5630",
    "addr:street":"Goldbergstr;Salzburg",
    "iso:country":"AT",
    "sg:address":"Goldbergstr 38",
    "sg:city":"Bad Hofgastein",
    "sg:orig_category":"Ingenieurkonsulenten / Zivilingenieure",
    "sg:phone":"+43 6432 75170",
    "sg:postcode":"5630",
    "sg:province":"Salzburg",
    "wof:name":"Wimmer & Partner Ingenieurb\u00fcro ZT GmbH",
    "wof:placetype":"venue"
},
  "geometry": {"coordinates":[13.1030578613,47.1783676147],"type":"Point"}
}