{
  "type": "Feature",
  "properties": {
    "addr:full":"Steing 65 Salzburg Salzburg 5020",
    "addr:housenumber":"65",
    "addr:postcode":"5020",
    "addr:street":"Steing;Salzburg",
    "iso:country":"AT",
    "sg:address":"Steing 65",
    "sg:city":"Salzburg",
    "sg:orig_category":"Weinstuben",
    "sg:phone":"+43 662 872769",
    "sg:postcode":"5020",
    "sg:province":"Salzburg",
    "wof:name":"Stadtalm Gruber & Esterer OEG",
    "wof:placetype":"venue"
},
  "geometry": {"coordinates":[13.0518541336,47.8005027771],"type":"Point"}
}