{
  "type": "Feature",
  "properties": {
    "iso:country":"AT",
    "sg:address":"Dr.-Gschmeidler-Str 43",
    "sg:city":"Krems an der Donau",
    "sg:orig_category":"Banken U Sparkassen",
    "sg:phone":"+43 4350 10025589",
    "sg:postcode":"3500",
    "sg:province":"Nieder\u00f6sterreich",
    "wof:name":"Kremser Bank u Sparkassen AG",
    "wof:placetype":"venue"
},
  "geometry": {"coordinates":[15.6159772873,48.4094696045],"type":"Point"}
}