{
  "type": "Feature",
  "properties": {
    "addr:full":"Salzburger Str 224 Wels Ober\u00f6sterreich 4600",
    "addr:housenumber":"224",
    "addr:postcode":"4600",
    "addr:street":"Salzburger Str;Oberoesterreich",
    "iso:country":"AT",
    "sg:address":"Salzburger Str 224",
    "sg:city":"Wels",
    "sg:orig_category":"Restaurants: Amerikanisch",
    "sg:phone":"+43 7242 44115",
    "sg:postcode":"4600",
    "sg:province":"Ober\u00f6sterreich",
    "wof:name":"McDonald's Restaurant - McDrive",
    "wof:placetype":"venue"
},
  "geometry": {"coordinates":[13.9877490997,48.1531944275],"type":"Point"}
}