{
  "type": "Feature",
  "properties": {
    "iso:country":"AT",
    "sg:address":"Salzburger Str 224",
    "sg:city":"Wels",
    "sg:orig_category":"Restaurants: Amerikanisch",
    "sg:phone":"+43 7242 44115",
    "sg:postcode":"4600",
    "sg:province":"Ober\u00f6sterreich",
    "wof:name":"McDonald's Restaurant - McDrive",
    "wof:placetype":"venue"
},
  "geometry": {"coordinates":[13.9877490997,48.1531944275],"type":"Point"}
}