{
  "type": "Feature",
  "properties": {
    "iso:country":"AT",
    "sg:address":"Wiener Strasse 56",
    "sg:city":"Wilfersdorf",
    "sg:orig_category":"CarpenterS Work Supraregional",
    "sg:phone":"+43 2573 22290",
    "sg:postcode":"2193",
    "sg:province":"Nieder\u00f6sterreich",
    "sg:website":"ing-hofer.at",
    "wof:name":"Ing. Hofer Dachdecker Spengler Zimmerer Isolierungen Ges.m.b.H.",
    "wof:placetype":"venue"
},
  "geometry": {"coordinates":[16.6399097443,48.5764503479],"type":"Point"}
}