{
  "type": "Feature",
  "properties": {
    "addr:full":"Pottenbrunner Hptstr 102 Pottenbrunn Nieder\u00f6sterreich 3140",
    "addr:housenumber":"102",
    "addr:postcode":"3140",
    "addr:street":"Niederoesterreich",
    "iso:country":"AT",
    "sg:address":"Pottenbrunner Hptstr 102",
    "sg:city":"Pottenbrunn",
    "sg:orig_category":"Hauskrankenpflege / Heimhilfe",
    "sg:phone":"+43 2742 43806",
    "sg:postcode":"3140",
    "sg:province":"Nieder\u00f6sterreich",
    "wof:name":"Caritas d Di\u00f6zese St P\u00f6lten Hauskrankenhilfe und Heimhilfe Pottenbrunn",
    "wof:placetype":"venue"
},
  "geometry": {"coordinates":[15.6984500885,48.2392196655],"type":"Point"}
}