{
  "type": "Feature",
  "properties": {
    "addr:full":"Hartberger Str 9 Buchkirchen Ober\u00f6sterreich 4611",
    "addr:housenumber":"9",
    "addr:postcode":"4611",
    "addr:street":"Str",
    "iso:country":"AT",
    "sg:address":"Hartberger Str 9",
    "sg:city":"Buchkirchen",
    "sg:classifiers":[
        {
            "category":"Home & Garden",
            "subcategory":"Garden Supply",
            "type":"Retail Goods"
        }
    ],
    "sg:phone":"+43 4372 4228070",
    "sg:postcode":"4611",
    "sg:province":"Ober\u00f6sterreich",
    "sg:tags":[
        "schotter",
        "sand",
        "u"
    ],
    "wof:name":"Jandl Transport GesmbH",
    "wof:placetype":"venue"
},
  "geometry": {"coordinates":[13.9993219376,48.2324943542],"type":"Point"}
}