{
  "type": "Feature",
  "properties": {
    "addr:full":"Traunwang. 8  Desselbrunn Ober\u00f6sterreich 4693",
    "addr:housenumber":"8",
    "addr:postcode":"4693",
    "addr:street":"Traunwang.",
    "iso:country":"AT",
    "sg:address":"Traunwang. 8 ",
    "sg:city":"Desselbrunn",
    "sg:classifiers":[
        {
            "category":"Parking",
            "subcategory":"Lot",
            "type":"Transportation"
        }
    ],
    "sg:phone":"+43 4376 734675",
    "sg:postcode":"4693",
    "sg:province":"Ober\u00f6sterreich",
    "sg:tags":[
        "transport",
        "road"
    ],
    "wof:name":"FRANZ SCHOBESBERGER TRANSPORT-GMBH",
    "wof:placetype":"venue"
},
  "geometry": {"coordinates":[13.8005132675,48.0282249451],"type":"Point"}
}