{
  "type": "Feature",
  "properties": {
    "iso:country":"AT",
    "sg:address":"Dornbirner Str 34",
    "sg:city":"Wolfurt",
    "sg:classifiers":[
        {
            "category":"Home & Garden",
            "subcategory":"Building Materials",
            "type":"Retail Goods"
        }
    ],
    "sg:phone":"+43 5574 70492",
    "sg:postcode":"6922",
    "sg:province":"Vorarlberg",
    "sg:tags":[
        "baustoffe",
        "-material",
        "u"
    ],
    "wof:name":"Feuerstein Baustoffhandels GmbH",
    "wof:placetype":"venue"
},
  "geometry": {"coordinates":[9.7568883896,47.4528236389],"type":"Point"}
}