{
  "type": "Feature",
  "properties": {
    "addr:full":"IZ K\u00e4lberweide 36/Outlet Cen. Parndorf Burgenland 7111",
    "addr:housenumber":"36",
    "addr:postcode":"7111",
    "iso:country":"AT",
    "sg:address":"IZ K\u00e4lberweide 36/Outlet Cen.",
    "sg:city":"Parndorf",
    "sg:orig_category":"Freizeit- U Sportbekleidung",
    "sg:phone":"+43 2166 3109",
    "sg:postcode":"7111",
    "sg:province":"Burgenland",
    "wof:name":"Red Green HandelsgesmbH",
    "wof:placetype":"venue"
},
  "geometry": {"coordinates":[16.8575897217,47.9981613159],"type":"Point"}
}