{
  "type": "Feature",
  "properties": {
    "addr:full":"Hauptstr 3 Laab im Walde Nieder\u00f6sterreich 2381",
    "addr:housenumber":"3",
    "addr:postcode":"2381",
    "addr:street":"Hauptstr",
    "iso:country":"AT",
    "sg:address":"Hauptstr 3",
    "sg:city":"Laab im Walde",
    "sg:orig_category":"\u00c3\u201erzte / F Allgemeinmedizin",
    "sg:phone":"+43 699 15236294",
    "sg:postcode":"2381",
    "sg:province":"Nieder\u00f6sterreich",
    "wof:name":"Flick Reinhard Dr",
    "wof:placetype":"venue"
},
  "geometry": {"coordinates":[16.1808509827,48.1537818909],"type":"Point"}
}