{
  "type": "Feature",
  "properties": {
    "iso:country":"AT",
    "sg:address":"Klagenfurter Str 72",
    "sg:city":"Bad St. Leonhard im Lavanttal",
    "sg:orig_category":"Immobilienmakler",
    "sg:phone":"+43 4343 5038001",
    "sg:postcode":"9462",
    "sg:province":"K\u00e4rnten",
    "wof:name":"Bischof Immobilientreuh\u00e4nder GesmbH",
    "wof:placetype":"venue"
},
  "geometry": {"coordinates":[14.7947130203,46.9622306824],"type":"Point"}
}