{
  "type": "Feature",
  "properties": {
    "addr:full":"Nr 13 Lavam\u00fcnd K\u00e4rnten 9473",
    "addr:postcode":"9473",
    "addr:street":"Nr 13 Lavamuend Kaernten",
    "iso:country":"AT",
    "sg:address":"Nr 13",
    "sg:city":"Lavam\u00fcnd",
    "sg:orig_category":"Non-Classified Establishments",
    "sg:phone":"+43 4356 2046",
    "sg:postcode":"9473",
    "sg:province":"K\u00e4rnten",
    "wof:name":"Pfarramt",
    "wof:placetype":"venue"
},
  "geometry": {"coordinates":[14.9413080215,46.6418952942],"type":"Point"}
}