{
  "type": "Feature",
  "properties": {
    "addr:full":"Grindelstr 11 Lustenau Vorarlberg 6890",
    "addr:housenumber":"11",
    "addr:postcode":"6890",
    "addr:street":"Grindelstr",
    "iso:country":"AT",
    "sg:address":"Grindelstr 11",
    "sg:city":"Lustenau",
    "sg:orig_category":"Autoreparatur",
    "sg:phone":"+43 4355 7783229",
    "sg:postcode":"6890",
    "sg:province":"Vorarlberg",
    "wof:name":"Scandella Wilhelm GesmbH & Co",
    "wof:placetype":"venue"
},
  "geometry": {"coordinates":[9.6579523087,47.4209442139],"type":"Point"}
}