{
  "type": "Feature",
  "properties": {
    "addr:full":"Josef-Fuhs-Str 1A Bisamberg Nieder\u00f6sterreich 2102",
    "addr:housenumber":"1a",
    "addr:postcode":"2102",
    "addr:street":"Josef-Fuhs-Str",
    "iso:country":"AT",
    "sg:address":"Josef-Fuhs-Str 1A",
    "sg:city":"Bisamberg",
    "sg:orig_category":"Handelsagenturen",
    "sg:phone":"+43 2262 755750",
    "sg:postcode":"2102",
    "sg:province":"Nieder\u00f6sterreich",
    "wof:name":"Cosmet HandelsgesmbH",
    "wof:placetype":"venue"
},
  "geometry": {"coordinates":[16.3696956635,48.3458938599],"type":"Point"}
}