{
  "type": "Feature",
  "properties": {
    "iso:country":"AT",
    "sg:address":"Josef-Fuhs-Str 1A",
    "sg:city":"Bisamberg",
    "sg:orig_category":"Handelsagenturen",
    "sg:phone":"+43 2262 755750",
    "sg:postcode":"2102",
    "sg:province":"Nieder\u00f6sterreich",
    "wof:name":"Cosmet HandelsgesmbH",
    "wof:placetype":"venue"
},
  "geometry": {"coordinates":[16.3696956635,48.3458938599],"type":"Point"}
}