{
  "type": "Feature",
  "properties": {
    "addr:full":"Raiffeisenstrasse 23 Waidhofen an der Thaya Nieder\u00f6sterreich 3830",
    "addr:housenumber":"23",
    "addr:postcode":"3830",
    "addr:street":"Raiffeisenstrasse",
    "iso:country":"AT",
    "sg:address":"Raiffeisenstrasse 23",
    "sg:city":"Waidhofen an der Thaya",
    "sg:classifiers":[
        {
            "category":"Food & Beverages",
            "subcategory":"Cheese",
            "type":"Retail Goods"
        }
    ],
    "sg:phone":"+43 2842 512150",
    "sg:postcode":"3830",
    "sg:province":"Nieder\u00f6sterreich",
    "sg:website":"kaesemacher.at",
    "wof:name":"Die K\u00e4semacher K\u00e4seproduktions- und Vertriebs GmbH",
    "wof:placetype":"venue"
},
  "geometry": {"coordinates":[15.2517976761,48.7931785583],"type":"Point"}
}