{
  "type": "Feature",
  "properties": {
    "addr:full":"Nr 297 Bad Gleichenberg Steiermark 8344",
    "addr:postcode":"8344",
    "addr:street":"Nr",
    "iso:country":"AT",
    "sg:address":"Nr 297",
    "sg:city":"Bad Gleichenberg",
    "sg:orig_category":"Banken U Sparkassen",
    "sg:phone":"+43 4331 5937500",
    "sg:postcode":"8344",
    "sg:province":"Steiermark",
    "wof:name":"Bankomat d Volksbank S\u00fcd-Oststeiermark",
    "wof:placetype":"venue"
},
  "geometry": {"coordinates":[15.9038906097,46.8549499512],"type":"Point"}
}