{
  "type": "Feature",
  "properties": {
    "iso:country":"AT",
    "sg:address":"Sankt Lorenz 298",
    "sg:city":"Mondsee",
    "sg:classifiers":[
        {
            "category":"Manufacturing",
            "subcategory":"Furniture",
            "type":"Manufacturing & Wholesale Goods"
        }
    ],
    "sg:phone":"+43 6232 4553",
    "sg:postcode":"5310",
    "sg:province":"Ober\u00f6sterreich",
    "sg:tags":[
        "bedroom"
    ],
    "wof:name":"Johann Stabauer",
    "wof:placetype":"venue"
},
  "geometry": {"coordinates":[13.349562645,47.855255127],"type":"Point"}
}