{
  "type": "Feature",
  "properties": {
    "addr:full":"Am Auwald 1 Elixhausen Salzburg 5161",
    "addr:housenumber":"1",
    "addr:postcode":"5161",
    "addr:street":"Am Auwald;Salzburg",
    "iso:country":"AT",
    "sg:address":"Am Auwald 1",
    "sg:city":"Elixhausen",
    "sg:orig_category":"Massagen",
    "sg:phone":"+43 662 481416",
    "sg:postcode":"5161",
    "sg:province":"Salzburg",
    "wof:name":"Winkler Waltraud",
    "wof:placetype":"venue"
},
  "geometry": {"coordinates":[13.0608472824,47.8604354858],"type":"Point"}
}