{
  "type": "Feature",
  "properties": {
    "addr:full":"Ennser Strasse 113 Gleink Ober\u00f6sterreich 4407",
    "addr:housenumber":"113",
    "addr:postcode":"4407",
    "addr:street":"Ennser Strasse",
    "iso:country":"AT",
    "sg:address":"Ennser Strasse 113",
    "sg:city":"Gleink",
    "sg:classifiers":[
        {
            "category":"Manufacturing",
            "subcategory":"Rubber & Plastics",
            "type":"Manufacturing & Wholesale Goods"
        }
    ],
    "sg:phone":"+43 7252 38180",
    "sg:postcode":"4407",
    "sg:province":"Ober\u00f6sterreich",
    "sg:tags":[
        "balcony"
    ],
    "sg:website":"tauschfenster.at",
    "wof:name":"H. Winkler Tauschfenster GmbH",
    "wof:placetype":"venue"
},
  "geometry": {"coordinates":[14.424200058,48.0736694336],"type":"Point"}
}