{
  "type": "Feature",
  "properties": {
    "iso:country":"AT",
    "sg:address":"Stiglingen 63",
    "sg:city":"Dornbirn",
    "sg:classifiers":[
        {
            "category":"Home & Garden",
            "subcategory":"Building Materials",
            "type":"Retail Goods"
        }
    ],
    "sg:phone":"+43 4355 72224750",
    "sg:postcode":"6850",
    "sg:province":"Vorarlberg",
    "sg:tags":[
        "baustoffe",
        "-material",
        "u"
    ],
    "wof:name":"Spiegel Otto GesmbH",
    "wof:placetype":"venue"
},
  "geometry": {"coordinates":[9.7419099808,47.4339904785],"type":"Point"}
}