{
  "type": "Feature",
  "properties": {
    "addr:full":"M\u00fcnichreiterstr 14  Wien Wien 1130",
    "addr:housenumber":"14",
    "addr:postcode":"1130",
    "addr:street":"Muenichreiterstr",
    "iso:country":"AT",
    "sg:address":"M\u00fcnichreiterstr 14 ",
    "sg:city":"Wien",
    "sg:classifiers":[
        {
            "category":"Professional",
            "subcategory":"Business Services",
            "type":"Services"
        }
    ],
    "sg:phone":"+43 4318 773724",
    "sg:postcode":"1130",
    "sg:province":"Wien",
    "sg:tags":[
        "advice"
    ],
    "wof:name":"HEINRICH-INTERNATIONAL TRADE-HANDELSGESMBH",
    "wof:placetype":"venue"
},
  "geometry": {"coordinates":[16.3013801575,48.18592453],"type":"Point"}
}