{
  "type": "Feature",
  "properties": {
    "addr:full":"Pottschacher Str 113 Ternitz Nieder\u00f6sterreich 2630",
    "addr:housenumber":"113",
    "addr:postcode":"2630",
    "addr:street":"Str",
    "iso:country":"AT",
    "sg:address":"Pottschacher Str 113",
    "sg:city":"Ternitz",
    "sg:orig_category":"Spenglereien",
    "sg:phone":"+43 2630 36788",
    "sg:postcode":"2630",
    "sg:province":"Nieder\u00f6sterreich",
    "wof:name":"Pichler Friedrich",
    "wof:placetype":"venue"
},
  "geometry": {"coordinates":[15.9937200546,47.7060623169],"type":"Point"}
}