{
  "type": "Feature",
  "properties": {
    "addr:full":"Eicherweg 5 St. Margarethen an der Raab Steiermark 8321",
    "addr:housenumber":"5",
    "addr:postcode":"8321",
    "addr:street":"Eicherweg",
    "iso:country":"AT",
    "sg:address":"Eicherweg 5",
    "sg:city":"St. Margarethen an der Raab",
    "sg:orig_category":"Abfallentsorgung U -Verwertung",
    "sg:phone":"+43 4331 1236033",
    "sg:postcode":"8321",
    "sg:province":"Steiermark",
    "wof:name":"M\u00fcllex Umwelt-S\u00e4uberung GesmbH",
    "wof:placetype":"venue"
},
  "geometry": {"coordinates":[15.7453098297,47.0449333191],"type":"Point"}
}