{
  "type": "Feature",
  "properties": {
    "addr:full":"Nesselthaler G 36 Salzburg Salzburg 5020",
    "addr:housenumber":"36",
    "addr:postcode":"5020",
    "addr:street":"Nesselthaler G;Salzburg",
    "iso:country":"AT",
    "sg:address":"Nesselthaler G 36",
    "sg:city":"Salzburg",
    "sg:orig_category":"Architekten",
    "sg:phone":"+43 662 6306130",
    "sg:postcode":"5020",
    "sg:province":"Salzburg",
    "sg:website":"www.arching.at/hofer-hekl",
    "wof:name":"Hofer + Hekl Architekten",
    "wof:placetype":"venue"
},
  "geometry": {"coordinates":[13.0696249008,47.7933197021],"type":"Point"}
}