{
  "type": "Feature",
  "properties": {
    "addr:full":"Salurner Str 28 Kufstein Tirol 6330",
    "addr:housenumber":"28",
    "addr:postcode":"6330",
    "addr:street":"Str;Tirol",
    "iso:country":"AT",
    "sg:address":"Salurner Str 28",
    "sg:city":"Kufstein",
    "sg:orig_category":"Tankstellen",
    "sg:phone":"+43 5372 62665",
    "sg:postcode":"6330",
    "sg:province":"Tirol",
    "wof:name":"Esso Austria GmbH",
    "wof:placetype":"venue"
},
  "geometry": {"coordinates":[12.1607046127,47.5765914917],"type":"Point"}
}