{
  "type": "Feature",
  "properties": {
    "addr:full":"Kohlpl 4 Reutte Tirol 6600",
    "addr:housenumber":"4",
    "addr:postcode":"6600",
    "addr:street":"Kohlpl;Tirol",
    "iso:country":"AT",
    "sg:address":"Kohlpl 4",
    "sg:city":"Reutte",
    "sg:orig_category":"Installationsunternehmen",
    "sg:phone":"+43 5672 646530",
    "sg:postcode":"6600",
    "sg:province":"Tirol",
    "wof:name":"Bouvier Erwin GesmbH & Co KG",
    "wof:placetype":"venue"
},
  "geometry": {"coordinates":[10.7172956467,47.5081291199],"type":"Point"}
}