{
  "type": "Feature",
  "properties": {
    "addr:full":"Matth\u00e4us Jiszda-Str 3 Wien Wien 1210",
    "addr:housenumber":"3",
    "addr:postcode":"1210",
    "addr:street":"Jiszda-Str",
    "iso:country":"AT",
    "sg:address":"Matth\u00e4us Jiszda-Str 3",
    "sg:city":"Wien",
    "sg:orig_category":"Physiotherapie",
    "sg:phone":"+43 4313 6922170",
    "sg:postcode":"1210",
    "sg:province":"Wien",
    "wof:name":"Sportmed Ges f sportmedizinische Leistungserfassung u Trainingsberatung GesmbH",
    "wof:placetype":"venue"
},
  "geometry": {"coordinates":[16.3953456879,48.2539787292],"type":"Point"}
}