{
  "type": "Feature",
  "properties": {
    "iso:country":"AT",
    "sg:address":"Urichstrasse 100",
    "sg:city":"Landeck",
    "sg:orig_category":"Furniture, General",
    "sg:phone":"+43 5442 62310",
    "sg:postcode":"6500",
    "sg:province":"Tirol",
    "wof:name":"Wolfgang Kr\u00f6pfl",
    "wof:placetype":"venue"
},
  "geometry": {"coordinates":[10.5814657211,47.1487388611],"type":"Point"}
}