{
  "type": "Feature",
  "properties": {
    "addr:full":"Nr 8 Steinhaus Ober\u00f6sterreich 4641",
    "addr:housenumber":"8",
    "addr:postcode":"4641",
    "addr:street":"Nr;Oberoesterreich",
    "iso:country":"AT",
    "sg:address":"Nr 8",
    "sg:city":"Steinhaus",
    "sg:orig_category":"Friseure U Frisiersalons",
    "sg:phone":"+43 7242 27029",
    "sg:postcode":"4641",
    "sg:province":"Ober\u00f6sterreich",
    "wof:name":"Krenslehner Gabriele",
    "wof:placetype":"venue"
},
  "geometry": {"coordinates":[14.0203199387,48.1157035828],"type":"Point"}
}