{
  "type": "Feature",
  "properties": {
    "addr:full":"Unterbergen 1 Treibach-Althofen K\u00e4rnten 9330",
    "addr:housenumber":"1",
    "addr:postcode":"9330",
    "addr:street":"Unterbergen;Kaernten",
    "iso:country":"AT",
    "sg:address":"Unterbergen 1",
    "sg:city":"Treibach-Althofen",
    "sg:orig_category":"Autoreparatur",
    "sg:phone":"+43 4262 2166",
    "sg:postcode":"9330",
    "sg:province":"K\u00e4rnten",
    "wof:name":"H\u00f6lbling Johann",
    "wof:placetype":"venue"
},
  "geometry": {"coordinates":[14.4729986191,46.8705062866],"type":"Point"}
}