{
  "type": "Feature",
  "properties": {
    "iso:country":"AT",
    "sg:address":"Egerdachstr 26",
    "sg:city":"Innsbruck",
    "sg:orig_category":"Fliesen U Platten",
    "sg:phone":"+43 512 394675",
    "sg:postcode":"6020",
    "sg:province":"Tirol",
    "sg:website":"www.abfliesen.at",
    "wof:name":"Berchtold Alfred",
    "wof:placetype":"venue"
},
  "geometry": {"coordinates":[11.4121131897,47.2684326172],"type":"Point"}
}