{
  "type": "Feature",
  "properties": {
    "addr:full":"Tauplitzalm 26 Tauplitz Steiermark 8982",
    "addr:housenumber":"26",
    "addr:postcode":"8982",
    "addr:street":"Tauplitzalm",
    "iso:country":"AT",
    "sg:address":"Tauplitzalm 26",
    "sg:city":"Tauplitz",
    "sg:classifiers":[
        {
            "category":"Travel",
            "subcategory":"Hotels & Motels",
            "type":"Entertainment"
        }
    ],
    "sg:phone":"+43 3688 23060",
    "sg:postcode":"8982",
    "sg:province":"Steiermark",
    "wof:name":"Sporthotel Tauplitzalm GesmbH",
    "wof:placetype":"venue"
},
  "geometry": {"coordinates":[13.9870586395,47.5930328369],"type":"Point"}
}