{
  "type": "Feature",
  "properties": {
    "addr:full":"Reschgasse 21 Wien Wien 1120",
    "addr:housenumber":"21",
    "addr:postcode":"1120",
    "addr:street":"Reschgasse",
    "iso:country":"AT",
    "sg:address":"Reschgasse 21",
    "sg:city":"Wien",
    "sg:classifiers":[
        {
            "category":"Home & Garden",
            "subcategory":"Building Materials",
            "type":"Retail Goods"
        }
    ],
    "sg:phone":"+43 1 9662421",
    "sg:postcode":"1120",
    "sg:province":"Wien",
    "sg:tags":[
        "installation",
        "electric"
    ],
    "sg:website":"nake.at",
    "wof:name":"NAKE Bau Installations- und Handels-KEG",
    "wof:placetype":"venue"
},
  "geometry": {"coordinates":[16.3308868408,48.1800537109],"type":"Point"}
}