{
  "type": "Feature",
  "properties": {
    "iso:country":"AT",
    "sg:address":"Zeughausg 6",
    "sg:city":"Feldkirch",
    "sg:orig_category":"Grafische Maschinen U Reparaturen",
    "sg:phone":"+43 4355 2290809",
    "sg:postcode":"6800",
    "sg:province":"Vorarlberg",
    "wof:name":"Graph & Print",
    "wof:placetype":"venue"
},
  "geometry": {"coordinates":[9.5955286026,47.236831665],"type":"Point"}
}