{
  "type": "Feature",
  "properties": {
    "addr:full":"Tiergartenstr 131 Innsbruck Tirol 6020",
    "addr:housenumber":"131",
    "addr:postcode":"6020",
    "addr:street":"Tirol",
    "iso:country":"AT",
    "sg:address":"Tiergartenstr 131",
    "sg:city":"Innsbruck",
    "sg:orig_category":"Immobilienverwaltungen",
    "sg:phone":"+43 512 2855800",
    "sg:postcode":"6020",
    "sg:province":"Tirol",
    "wof:name":"Praxmarer Josef GmbH",
    "wof:placetype":"venue"
},
  "geometry": {"coordinates":[11.360660553,47.256652832],"type":"Point"}
}