{
  "type": "Feature",
  "properties": {
    "addr:full":"Sonnenhang 2 Trofaiach Steiermark 8793",
    "addr:housenumber":"2",
    "addr:postcode":"8793",
    "addr:street":"Sonnenhang",
    "iso:country":"AT",
    "sg:address":"Sonnenhang 2",
    "sg:city":"Trofaiach",
    "sg:orig_category":"Non-Classified Establishments",
    "sg:phone":"+43 4338 4775026",
    "sg:postcode":"8793",
    "sg:province":"Steiermark",
    "wof:name":"HILD Tortechnik GmbH",
    "wof:placetype":"venue"
},
  "geometry": {"coordinates":[15.0303897858,47.4209594727],"type":"Point"}
}