{
  "type": "Feature",
  "properties": {
    "addr:full":"Hofkreuzsdlg 16 Atzenbrugg Nieder\u00f6sterreich 3452",
    "addr:housenumber":"16",
    "addr:postcode":"3452",
    "addr:street":"Hofkreuzsdlg",
    "iso:country":"AT",
    "sg:address":"Hofkreuzsdlg 16",
    "sg:city":"Atzenbrugg",
    "sg:classifiers":[
        {
            "category":"Internet Cafe",
            "subcategory":"None",
            "type":"Food & Drink"
        }
    ],
    "sg:phone":"+43 4322 7540128",
    "sg:postcode":"3452",
    "sg:province":"Nieder\u00f6sterreich",
    "sg:tags":[
        "internet-provider"
    ],
    "wof:name":"Faix Rudolf Funkinternet KEG",
    "wof:placetype":"venue"
},
  "geometry": {"coordinates":[15.9042654037,48.2924804688],"type":"Point"}
}