{
  "type": "Feature",
  "properties": {
    "addr:full":"Gudrunstr 187/2 Wien Wien 1100",
    "addr:housenumber":"187 / 2",
    "addr:postcode":"1100",
    "iso:country":"AT",
    "sg:address":"Gudrunstr 187/2",
    "sg:city":"Wien",
    "sg:classifiers":[
        {
            "category":"Manufacturing",
            "subcategory":"Rubber & Plastics",
            "type":"Manufacturing & Wholesale Goods"
        }
    ],
    "sg:phone":"+43 1 6070130",
    "sg:postcode":"1100",
    "sg:province":"Wien",
    "sg:tags":[
        "safe",
        "u",
        "tresore"
    ],
    "sg:website":"www.fortknox.at",
    "wof:name":"Fort Knox Sicherheitsges.m.b.H.",
    "wof:placetype":"venue"
},
  "geometry": {"coordinates":[16.3634757996,48.178817749],"type":"Point"}
}