{
  "type": "Feature",
  "properties": {
    "addr:full":"St. P\u00f6ltner Str 26 Herzogenburg Nieder\u00f6sterreich 3130",
    "addr:postcode":"3130",
    "addr:street":"Str 26",
    "iso:country":"AT",
    "sg:address":"St. P\u00f6ltner Str 26",
    "sg:city":"Herzogenburg",
    "sg:orig_category":"Versicherungsunternehmen",
    "sg:phone":"+43 2782 83427",
    "sg:postcode":"3130",
    "sg:province":"Nieder\u00f6sterreich",
    "wof:name":"Wiener St\u00e4dtische Allgemeine Versicherung AG",
    "wof:placetype":"venue"
},
  "geometry": {"coordinates":[15.6955575943,48.2830123901],"type":"Point"}
}