{
  "type": "Feature",
  "properties": {
    "addr:full":"Lothringerstr 44 Klosterneuburg Nieder\u00f6sterreich 3400",
    "addr:housenumber":"44",
    "addr:postcode":"3400",
    "addr:street":"Lothringerstr;Niederoesterreich",
    "iso:country":"AT",
    "sg:address":"Lothringerstr 44",
    "sg:city":"Klosterneuburg",
    "sg:orig_category":"Handelsagenturen",
    "sg:phone":"+43 4366 44114936",
    "sg:postcode":"3400",
    "sg:province":"Nieder\u00f6sterreich",
    "wof:name":"Kreuzinger Isabella",
    "wof:placetype":"venue"
},
  "geometry": {"coordinates":[16.3358860016,48.2922592163],"type":"Point"}
}