{
  "type": "Feature",
  "properties": {
    "addr:full":"Linzer Str 3 Haag Nieder\u00f6sterreich 3350",
    "addr:housenumber":"3",
    "addr:postcode":"3350",
    "addr:street":"Linzer Str",
    "iso:country":"AT",
    "sg:address":"Linzer Str 3",
    "sg:city":"Haag",
    "sg:orig_category":"Eisenwaren",
    "sg:phone":"+43 7434 422170",
    "sg:postcode":"3350",
    "sg:province":"Nieder\u00f6sterreich",
    "wof:name":"B\u00f6ckle Harald GmbH",
    "wof:placetype":"venue"
},
  "geometry": {"coordinates":[14.5670642853,48.1107978821],"type":"Point"}
}