{
  "type": "Feature",
  "properties": {
    "addr:full":"Kornsteinpl 12 Hallein Salzburg 5400",
    "addr:housenumber":"12",
    "addr:postcode":"5400",
    "addr:street":"Kornsteinpl;Salzburg",
    "iso:country":"AT",
    "sg:address":"Kornsteinpl 12",
    "sg:city":"Hallein",
    "sg:orig_category":"Zeitungen U Zeitschriften",
    "sg:phone":"+43 4362 4570001",
    "sg:postcode":"5400",
    "sg:province":"Salzburg",
    "wof:name":"Print Zeitungsverlag GesmbH - Bezirksbl\u00e4tter-Bezirksblatt Tennengau",
    "wof:placetype":"venue"
},
  "geometry": {"coordinates":[13.0931158066,47.682472229],"type":"Point"}
}