{
  "type": "Feature",
  "properties": {
    "iso:country":"AT",
    "sg:address":"Schulg 20b",
    "sg:city":"Deutschlandsberg",
    "sg:orig_category":"Elektroinstallationsunternehmen",
    "sg:phone":"+43 4334 628256",
    "sg:postcode":"8530",
    "sg:province":"Steiermark",
    "wof:name":"Elektrotechnik u Werbung",
    "wof:placetype":"venue"
},
  "geometry": {"coordinates":[15.2118997574,46.8156318665],"type":"Point"}
}