{
  "type": "Feature",
  "properties": {
    "iso:country":"AT",
    "sg:address":"Atzbacher Strasse 17",
    "sg:city":"Schwanenstadt",
    "sg:classifiers":[
        {
            "category":"Manufacturing",
            "subcategory":"Furniture",
            "type":"Manufacturing & Wholesale Goods"
        }
    ],
    "sg:phone":"+43 767374510",
    "sg:postcode":"4690",
    "sg:province":"Ober\u00f6sterreich",
    "sg:tags":[
        "upholstered",
        "designing"
    ],
    "sg:website":"joka.at",
    "wof:name":"Joka-Werke Johann Kapsamer GmbH & Co KG",
    "wof:placetype":"venue"
},
  "geometry": {"coordinates":[13.7709331512,48.0529937744],"type":"Point"}
}