{
  "type": "Feature",
  "properties": {
    "addr:full":"M\u00fchlg 2 St. Michael in Obersteiermark Steiermark 8770",
    "addr:housenumber":"2",
    "addr:postcode":"8770",
    "addr:street":"Muehlg",
    "iso:country":"AT",
    "sg:address":"M\u00fchlg 2",
    "sg:city":"St. Michael in Obersteiermark",
    "sg:orig_category":"Musikunterricht",
    "sg:phone":"+43 4338 433122",
    "sg:postcode":"8770",
    "sg:province":"Steiermark",
    "wof:name":"Musikschule",
    "wof:placetype":"venue"
},
  "geometry": {"coordinates":[15.0202636719,47.3367919922],"type":"Point"}
}