{
  "type": "Feature",
  "properties": {
    "addr:full":"Nr 81 Neudorf Nieder\u00f6sterreich 2135",
    "addr:postcode":"2135",
    "addr:street":"Nr",
    "iso:country":"AT",
    "sg:address":"Nr 81",
    "sg:city":"Neudorf",
    "sg:orig_category":"Feuerwehren",
    "sg:phone":"+43 4325 2320098",
    "sg:postcode":"2135",
    "sg:province":"Nieder\u00f6sterreich",
    "wof:name":"Freiwillige Feuerwehr Zlabern",
    "wof:placetype":"venue"
},
  "geometry": {"coordinates":[16.4915943146,48.7205314636],"type":"Point"}
}