{
  "type": "Feature",
  "properties": {
    "iso:country":"AT",
    "sg:address":"St. Jakob 33",
    "sg:city":"St. Andr\u00e4",
    "sg:orig_category":"Maler, Anstreicher U Lackierer",
    "sg:phone":"+43 4343 583723",
    "sg:postcode":"9433",
    "sg:province":"K\u00e4rnten",
    "wof:name":"Seifried Siegfried",
    "wof:placetype":"venue"
},
  "geometry": {"coordinates":[14.8301897049,46.737739563],"type":"Point"}
}