{
  "type": "Feature",
  "properties": {
    "addr:full":"Nr 34 Gro\u00dfklein Steiermark 8452",
    "addr:postcode":"8452",
    "addr:street":"Nr;Grossklein",
    "iso:country":"AT",
    "sg:address":"Nr 34",
    "sg:city":"Gro\u00dfklein",
    "sg:orig_category":"Transportunternehmen",
    "sg:phone":"+43 3456 2206",
    "sg:postcode":"8452",
    "sg:province":"Steiermark",
    "wof:name":"Maier Josef",
    "wof:placetype":"venue"
},
  "geometry": {"coordinates":[15.4416875839,46.7364997864],"type":"Point"}
}