{
  "type": "Feature",
  "properties": {
    "addr:full":"Hintergasse 23 Rudersdorf Burgenland 7571",
    "addr:housenumber":"23",
    "addr:postcode":"7571",
    "addr:street":"Hintergasse",
    "iso:country":"AT",
    "sg:address":"Hintergasse 23",
    "sg:city":"Rudersdorf",
    "sg:classifiers":[
        {
            "category":"Home & Garden",
            "subcategory":"Furniture",
            "type":"Retail Goods"
        }
    ],
    "sg:phone":"+43 3382 71600",
    "sg:postcode":"7571",
    "sg:province":"Burgenland",
    "sg:tags":[
        "bathroom"
    ],
    "wof:name":"Johann Fuchs",
    "wof:placetype":"venue"
},
  "geometry": {"coordinates":[16.1216831207,47.050327301],"type":"Point"}
}