{
  "type": "Feature",
  "properties": {
    "iso:country":"AT",
    "sg:address":"Flurstr 12",
    "sg:city":"Lustenau",
    "sg:orig_category":"Handelsagenturen",
    "sg:phone":"+43 5577 87002",
    "sg:postcode":"6890",
    "sg:province":"Vorarlberg",
    "wof:name":"Scheffknecht J\u00fcrgen",
    "wof:placetype":"venue"
},
  "geometry": {"coordinates":[9.6601057053,47.4161758423],"type":"Point"}
}