{
  "type": "Feature",
  "properties": {
    "addr:full":"Reitberg 315 Eugendorf Salzburg 5301",
    "addr:housenumber":"315",
    "addr:postcode":"5301",
    "addr:street":"Reitberg;Salzburg",
    "iso:country":"AT",
    "sg:address":"Reitberg 315",
    "sg:city":"Eugendorf",
    "sg:orig_category":"Spielwaren U Spiele",
    "sg:phone":"+43 4362 257150",
    "sg:postcode":"5301",
    "sg:province":"Salzburg",
    "wof:name":"Feichtinger Harald",
    "wof:placetype":"venue"
},
  "geometry": {"coordinates":[13.1481981277,47.862033844],"type":"Point"}
}