{
  "type": "Feature",
  "properties": {
    "addr:full":"Dobler Str 37 Lieboch Steiermark 8501",
    "addr:postcode":"8501",
    "addr:street":"Str",
    "iso:country":"AT",
    "sg:address":"Dobler Str 37",
    "sg:city":"Lieboch",
    "sg:orig_category":"Tierpensionen",
    "sg:phone":"+43 3136 62739",
    "sg:postcode":"8501",
    "sg:province":"Steiermark",
    "wof:name":"Tierbetreuung Regine Schineis",
    "wof:placetype":"venue"
},
  "geometry": {"coordinates":[15.3556118011,46.9608001709],"type":"Point"}
}