{
  "type": "Feature",
  "properties": {
    "iso:country":"AT",
    "sg:address":"Maximilianstr 8",
    "sg:city":"Innsbruck",
    "sg:orig_category":"Institute",
    "sg:phone":"+43 512 574772",
    "sg:postcode":"6020",
    "sg:province":"Tirol",
    "wof:name":"Grenzgebiete der Wissenschaft",
    "wof:placetype":"venue"
},
  "geometry": {"coordinates":[11.3898172379,47.2623405457],"type":"Point"}
}