{
  "type": "Feature",
  "properties": {
    "addr:full":"Tarviser Str 2 Klagenfurt K\u00e4rnten 9020",
    "addr:housenumber":"2",
    "addr:postcode":"9020",
    "addr:street":"Str;Kaernten",
    "iso:country":"AT",
    "sg:address":"Tarviser Str 2",
    "sg:city":"Klagenfurt",
    "sg:orig_category":"Alternativtherapie",
    "sg:phone":"+43 463 504756",
    "sg:postcode":"9020",
    "sg:province":"K\u00e4rnten",
    "wof:name":"Suchanek Gilbert - Shiatsu Praxis",
    "wof:placetype":"venue"
},
  "geometry": {"coordinates":[14.3017473221,46.6239967346],"type":"Point"}
}