{
  "type": "Feature",
  "properties": {
    "addr:full":"Berglehen 13a St. Johann in Tirol Tirol 6380",
    "addr:housenumber":"13a",
    "addr:postcode":"johann;6380",
    "addr:street":"Berglehen;Tirol",
    "iso:country":"AT",
    "sg:address":"Berglehen 13a",
    "sg:city":"St. Johann in Tirol",
    "sg:classifiers":[
        {
            "category":"Restaurant",
            "type":"Food & Drink"
        }
    ],
    "sg:phone":"+43 5352 63940",
    "sg:postcode":"6380",
    "sg:province":"Tirol",
    "wof:name":"Restaurant Koasaburg",
    "wof:placetype":"venue"
},
  "geometry": {"coordinates":[12.4251117706,47.5076828003],"type":"Point"}
}