{
  "type": "Feature",
  "properties": {
    "addr:full":"Hauptstr 46 Gr\u00f6dig Salzburg 5082",
    "addr:housenumber":"46",
    "addr:postcode":"5082",
    "addr:street":"Hauptstr",
    "iso:country":"AT",
    "sg:address":"Hauptstr 46",
    "sg:city":"Gr\u00f6dig",
    "sg:orig_category":"Fliesen U Platten",
    "sg:phone":"+43 4362 4673714",
    "sg:postcode":"5082",
    "sg:province":"Salzburg",
    "wof:name":"Baukeramik HandelsgesmbH",
    "wof:placetype":"venue"
},
  "geometry": {"coordinates":[-76.2684555054,37.4373283386],"type":"Point"}
}