{
  "type": "Feature",
  "properties": {
    "addr:full":"Terrassenweg 7 St. Kanzian am Klopeiner See K\u00e4rnten 9122",
    "addr:housenumber":"7",
    "addr:postcode":"9122",
    "addr:street":"Terrassenweg;Kaernten",
    "iso:country":"AT",
    "sg:address":"Terrassenweg 7",
    "sg:city":"St. Kanzian am Klopeiner See",
    "sg:classifiers":[
        {
            "category":"Shopping",
            "subcategory":"Computers & Home Electronics",
            "type":"Retail Goods"
        }
    ],
    "sg:phone":"+43 664 3376998",
    "sg:postcode":"9122",
    "sg:province":"K\u00e4rnten",
    "sg:tags":[
        "system",
        "automation"
    ],
    "wof:name":"Diex E-Technik Automation",
    "wof:placetype":"venue"
},
  "geometry": {"coordinates":[14.5990886688,46.6082992554],"type":"Point"}
}