{
  "type": "Feature",
  "properties": {
    "iso:country":"AT",
    "sg:address":"Siemensstrasse 15",
    "sg:classifiers":[
        {
            "category":"Banks & Credit Unions",
            "subcategory":"Investment Brokerage",
            "type":"Services"
        }
    ],
    "sg:phone":"+43 512 2659880",
    "sg:postcode":"6023",
    "sg:tags":[
        "axial",
        "fan"
    ],
    "sg:website":"heliosventilatoren.at",
    "wof:name":"Helios Ventilatoren Ges.m.b.H.",
    "wof:placetype":"venue"
},
  "geometry": {"coordinates":[11.3913040161,47.2679977417],"type":"Point"}
}