{
  "type": "Feature",
  "properties": {
    "iso:country":"AT",
    "sg:address":"Lorenz-Mandl-G 50",
    "sg:city":"Wien",
    "sg:orig_category":"Babyausstattung",
    "sg:phone":"+43 1 491410",
    "sg:postcode":"1160",
    "sg:province":"Wien",
    "sg:website":"mambaby.com",
    "wof:name":"MAM Babyartikel GesmbH",
    "wof:placetype":"venue"
},
  "geometry": {"coordinates":[16.3073558807,48.2115821838],"type":"Point"}
}