{
  "type": "Feature",
  "properties": {
    "addr:full":"Tullner Str 7 Traismauer Nieder\u00f6sterreich 3133",
    "addr:housenumber":"7",
    "addr:postcode":"3133",
    "addr:street":"Str",
    "iso:country":"AT",
    "sg:address":"Tullner Str 7",
    "sg:city":"Traismauer",
    "sg:orig_category":"Banken U Sparkassen",
    "sg:phone":"+43 4359 50053300",
    "sg:postcode":"3133",
    "sg:province":"Nieder\u00f6sterreich",
    "wof:name":"Raiffeisenbank Region St. P\u00f6lten regGenmbH - Bankstelle Gemeinlebarn",
    "wof:placetype":"venue"
},
  "geometry": {"coordinates":[15.8030691147,48.3374099731],"type":"Point"}
}