{
  "type": "Feature",
  "properties": {
    "iso:country":"AT",
    "sg:address":"Hermann-Fischer-Str 1",
    "sg:city":"Wolfsberg",
    "sg:orig_category":"Fotografen",
    "sg:phone":"+43 4343 5262456",
    "sg:postcode":"9400",
    "sg:province":"K\u00e4rnten",
    "wof:name":"Zimmermann Elisabeth - Forever Digital",
    "wof:placetype":"venue"
},
  "geometry": {"coordinates":[14.8409872055,46.8416252136],"type":"Point"}
}