{
  "type": "Feature",
  "properties": {
    "iso:country":"AT",
    "sg:address":"Thalgaustr 32",
    "sg:city":"Mondsee",
    "sg:orig_category":"Pensionen / Privatzimmer",
    "sg:phone":"+43 6232 2115",
    "sg:postcode":"5310",
    "sg:province":"Ober\u00f6sterreich",
    "wof:name":"Schwaighofer Marianne",
    "wof:placetype":"venue"
},
  "geometry": {"coordinates":[13.349562645,47.855255127],"type":"Point"}
}