{
  "type": "Feature",
  "properties": {
    "iso:country":"AT",
    "sg:address":"Bauernmarkt 12",
    "sg:city":"Wien",
    "sg:orig_category":"Boutiquen",
    "sg:phone":"+43 4315 354936",
    "sg:postcode":"1010",
    "sg:province":"Wien",
    "wof:name":"Viva Vienna",
    "wof:placetype":"venue"
},
  "geometry": {"coordinates":[16.3726959229,48.2098655701],"type":"Point"}
}