{
  "type": "Feature",
  "properties": {
    "addr:full":"Herrengschwendt 111 Steinach am Brenner Tirol 6150",
    "addr:housenumber":"111",
    "addr:postcode":"6150",
    "addr:street":"Herrengschwendt;Tirol",
    "iso:country":"AT",
    "sg:address":"Herrengschwendt 111",
    "sg:city":"Steinach am Brenner",
    "sg:orig_category":"Suchtberatung / Alkohol, Drogen, Zigaretten",
    "sg:phone":"+43 5272 6647",
    "sg:postcode":"6150",
    "sg:province":"Tirol",
    "wof:name":"Verein KIT Kontakt-Information-Therapie Rehabilitationszentrum",
    "wof:placetype":"venue"
},
  "geometry": {"coordinates":[11.4600229263,47.0865783691],"type":"Point"}
}