{
  "type": "Feature",
  "properties": {
    "addr:full":"Anton-Wildgans-G 1 Leobersdorf Nieder\u00f6sterreich 2544",
    "addr:housenumber":"1",
    "addr:postcode":"2544",
    "addr:street":"Anton-Wildgans-G",
    "iso:country":"AT",
    "sg:address":"Anton-Wildgans-G 1",
    "sg:city":"Leobersdorf",
    "sg:orig_category":"Friseure U Frisiersalons",
    "sg:phone":"+43 4322 5663191",
    "sg:postcode":"2544",
    "sg:province":"Nieder\u00f6sterreich",
    "wof:name":"Schreiber Monika",
    "wof:placetype":"venue"
},
  "geometry": {"coordinates":[16.2252025604,47.9327011108],"type":"Point"}
}