{
  "type": "Feature",
  "properties": {
    "addr:full":"Keltenstr 13 Lochen Ober\u00f6sterreich 5221",
    "addr:housenumber":"13",
    "addr:postcode":"5221",
    "addr:street":"Keltenstr",
    "iso:country":"AT",
    "sg:address":"Keltenstr 13",
    "sg:city":"Lochen",
    "sg:orig_category":"Maler, Anstreicher U Lackierer",
    "sg:phone":"+43 4377 458400",
    "sg:postcode":"5221",
    "sg:province":"Ober\u00f6sterreich",
    "wof:name":"Vitzthum Mario",
    "wof:placetype":"venue"
},
  "geometry": {"coordinates":[13.1818666458,48.0078582764],"type":"Point"}
}