{
  "type": "Feature",
  "properties": {
    "iso:country":"AT",
    "sg:address":"Bahnhofstr 23",
    "sg:city":"Rattersdorf-Liebing",
    "sg:orig_category":"Fenster",
    "sg:phone":"+43 2611 2956",
    "sg:postcode":"7443",
    "sg:province":"Burgenland",
    "wof:name":"Schl\u00f6gl Stefan",
    "wof:placetype":"venue"
},
  "geometry": {"coordinates":[16.4945831299,47.4136657715],"type":"Point"}
}