{
  "type": "Feature",
  "properties": {
    "addr:full":"Hauptpl 31 Villach K\u00e4rnten 9500",
    "addr:housenumber":"31",
    "addr:postcode":"9500",
    "addr:street":"Hauptpl;Kaernten",
    "iso:country":"AT",
    "sg:address":"Hauptpl 31",
    "sg:city":"Villach",
    "sg:orig_category":"Steuerberatung",
    "sg:phone":"+43 4242 23532",
    "sg:postcode":"9500",
    "sg:province":"K\u00e4rnten",
    "wof:name":"Schmidt Roland Wirtschaftstreuhand GesmbH",
    "wof:placetype":"venue"
},
  "geometry": {"coordinates":[13.8462018967,46.6131439209],"type":"Point"}
}