{
  "type": "Feature",
  "properties": {
    "iso:country":"AT",
    "sg:address":"Alxingergasse 19",
    "sg:city":"Wien",
    "sg:orig_category":"Chain Suspension Tackle",
    "sg:phone":"+43 1 60257230",
    "sg:postcode":"1100",
    "sg:province":"Wien",
    "wof:name":"Michael Heinz Krane-Ketten-Hebezeuge",
    "wof:placetype":"venue"
},
  "geometry": {"coordinates":[16.3686580658,48.1791381836],"type":"Point"}
}