{
  "type": "Feature",
  "properties": {
    "addr:full":"Kircheng 33 Bad Goisern Ober\u00f6sterreich 4822",
    "addr:housenumber":"33",
    "addr:postcode":"4822",
    "addr:street":"Kircheng",
    "iso:country":"AT",
    "sg:address":"Kircheng 33",
    "sg:city":"Bad Goisern",
    "sg:classifiers":[
        {
            "category":"Restaurant",
            "type":"Food & Drink"
        }
    ],
    "sg:phone":"+43 6135 8252",
    "sg:postcode":"4822",
    "sg:province":"Ober\u00f6sterreich",
    "sg:tags":[
        "pizzeria"
    ],
    "wof:name":"Pizzeria Romana",
    "wof:placetype":"venue"
},
  "geometry": {"coordinates":[13.6166954041,47.6421012878],"type":"Point"}
}