{
  "type": "Feature",
  "properties": {
    "addr:full":"Senefelderg 25 Wien Wien 1100",
    "addr:housenumber":"25",
    "addr:postcode":"1100",
    "addr:street":"Senefelderg",
    "iso:country":"AT",
    "sg:address":"Senefelderg 25",
    "sg:city":"Wien",
    "sg:classifiers":[
        {
            "category":"Restaurant",
            "type":"Food & Drink"
        }
    ],
    "sg:phone":"+43 1 6020267",
    "sg:postcode":"1100",
    "sg:province":"Wien",
    "wof:name":"Steirerhof",
    "wof:placetype":"venue"
},
  "geometry": {"coordinates":[16.3756408691,48.1749763489],"type":"Point"}
}