{
  "type": "Feature",
  "properties": {
    "iso:country":"AT",
    "sg:address":"Nr 125",
    "sg:city":"Eltendorf",
    "sg:orig_category":"Steinmetzbetriebe",
    "sg:phone":"+43 3325 2387",
    "sg:postcode":"7562",
    "sg:province":"Burgenland",
    "wof:name":"Horvath Johann",
    "wof:placetype":"venue"
},
  "geometry": {"coordinates":[16.1975917816,47.0079803467],"type":"Point"}
}