{
  "type": "Feature",
  "properties": {
    "addr:full":"Maria Lanzendorfer Str 16 Leopoldsdorf Nieder\u00f6sterreich 2333",
    "addr:housenumber":"16",
    "addr:postcode":"2333",
    "addr:street":"Maria Lanzendorfer Str",
    "iso:country":"AT",
    "sg:address":"Maria Lanzendorfer Str 16",
    "sg:city":"Leopoldsdorf",
    "sg:orig_category":"Transportunternehmen",
    "sg:phone":"+43 4322 3544170",
    "sg:postcode":"2333",
    "sg:province":"Nieder\u00f6sterreich",
    "wof:name":"Varga Transporte",
    "wof:placetype":"venue"
},
  "geometry": {"coordinates":[16.3975696564,48.1078414917],"type":"Point"}
}