{
  "type": "Feature",
  "properties": {
    "addr:full":"Dorfstetten Nieder\u00f6sterreich 4392",
    "addr:housenumber":"4392",
    "addr:street":"Niederoesterreich",
    "iso:country":"AT",
    "sg:city":"Dorfstetten",
    "sg:orig_category":"Non-Classified Establishments",
    "sg:phone":"+43 7260 8204",
    "sg:postcode":"4392",
    "sg:province":"Nieder\u00f6sterreich",
    "wof:name":"Pfarramt",
    "wof:placetype":"venue"
},
  "geometry": {"coordinates":[14.9821662903,48.32629776],"type":"Point"}
}