{
  "type": "Feature",
  "properties": {
    "addr:full":"Halleiner Landesstrasse 252 Puch Salzburg 5412",
    "addr:housenumber":"252",
    "addr:postcode":"5412",
    "addr:street":"Halleiner Landesstrasse;Salzburg",
    "iso:country":"AT",
    "sg:address":"Halleiner Landesstrasse 252",
    "sg:city":"Puch",
    "sg:classifiers":[
        {
            "category":"Home & Garden",
            "subcategory":"Building Materials",
            "type":"Retail Goods"
        }
    ],
    "sg:phone":"+43 6245 80231",
    "sg:postcode":"5412",
    "sg:province":"Salzburg",
    "sg:tags":[
        "gravel",
        "crushed"
    ],
    "wof:name":"Anton Rieger Steinbruch Schotterwerk",
    "wof:placetype":"venue"
},
  "geometry": {"coordinates":[13.091504097,47.7125434875],"type":"Point"}
}