{
  "type": "Feature",
  "properties": {
    "addr:full":"Schlosserg 1 Innsbruck Tirol 6020",
    "addr:housenumber":"1",
    "addr:postcode":"6020",
    "addr:street":"Schlosserg;Tirol",
    "iso:country":"AT",
    "sg:address":"Schlosserg 1",
    "sg:city":"Innsbruck",
    "sg:orig_category":"Versicherungsunternehmen",
    "sg:phone":"+43 512 59543",
    "sg:postcode":"6020",
    "sg:province":"Tirol",
    "wof:name":"Donau Versicherung - Landesdirektion Tirol",
    "wof:placetype":"venue"
},
  "geometry": {"coordinates":[11.3933925629,47.2670974731],"type":"Point"}
}