{
  "type": "Feature",
  "properties": {
    "iso:country":"AT",
    "sg:address":"Grazer Str 6",
    "sg:city":"Gratkorn",
    "sg:orig_category":"Textilwaren / Einzelhandel",
    "sg:phone":"+43 4331 2429045",
    "sg:postcode":"8101",
    "sg:province":"Steiermark",
    "wof:name":"NKD",
    "wof:placetype":"venue"
},
  "geometry": {"coordinates":[15.339392662,47.1321411133],"type":"Point"}
}