{
  "type": "Feature",
  "properties": {
    "addr:full":"Panoramastr 31 Neumarkt in Steiermark Steiermark 8820",
    "addr:housenumber":"31",
    "addr:postcode":"8820",
    "addr:street":"Panoramastr",
    "iso:country":"AT",
    "sg:address":"Panoramastr 31",
    "sg:city":"Neumarkt in Steiermark",
    "sg:classifiers":[
        {
            "category":"Retail",
            "subcategory":"Event Space",
            "type":"Services"
        }
    ],
    "sg:phone":"+43 4335 843757",
    "sg:postcode":"8820",
    "sg:province":"Steiermark",
    "sg:tags":[
        "hand-",
        "u",
        "fu\u00c3\u0178pflege"
    ],
    "wof:name":"Massar Gertraud",
    "wof:placetype":"venue"
},
  "geometry": {"coordinates":[14.4334497452,47.0722923279],"type":"Point"}
}