{
  "type": "Feature",
  "properties": {
    "addr:full":"Lindenweg 8b/43 W\u00f6rgl Tirol 6300",
    "addr:housenumber":"8b / 43",
    "addr:postcode":"6300",
    "addr:street":"Lindenweg;Woergl Tirol",
    "iso:country":"AT",
    "sg:address":"Lindenweg 8b/43",
    "sg:city":"W\u00f6rgl",
    "sg:orig_category":"Webdesign",
    "sg:phone":"+43 4365 04412444",
    "sg:postcode":"6300",
    "sg:province":"Tirol",
    "wof:name":"Sumo Media Werbung & Multimedia",
    "wof:placetype":"venue"
},
  "geometry": {"coordinates":[-69.3131027222,-51.6091995239],"type":"Point"}
}