{
  "type": "Feature",
  "properties": {
    "addr:full":"Reiner Str 60 Gratwein Steiermark 8112",
    "addr:postcode":"8112",
    "iso:country":"AT",
    "sg:address":"Reiner Str 60",
    "sg:city":"Gratwein",
    "sg:orig_category":"Stahlbau",
    "sg:phone":"+43 4331 24514040",
    "sg:postcode":"8112",
    "sg:province":"Steiermark",
    "wof:name":"Marchl Stahlbau GesmbH",
    "wof:placetype":"venue"
},
  "geometry": {"coordinates":[15.3115463257,47.1307373047],"type":"Point"}
}