{
  "type": "Feature",
  "properties": {
    "addr:full":"Schlo\u00dfm\u00fchlstr 7a Schwechat Nieder\u00f6sterreich 2320",
    "addr:housenumber":"7a",
    "addr:postcode":"2320",
    "addr:street":"Schlossmuehlstr;Niederoesterreich",
    "iso:country":"AT",
    "sg:address":"Schlo\u00dfm\u00fchlstr 7a",
    "sg:city":"Schwechat",
    "sg:orig_category":"Speditionen",
    "sg:phone":"+43 4317 986111",
    "sg:postcode":"2320",
    "sg:province":"Nieder\u00f6sterreich",
    "wof:name":"Hnat Karl & Co Int Spedition",
    "wof:placetype":"venue"
},
  "geometry": {"coordinates":[16.4771652222,48.1398735046],"type":"Point"}
}