{
  "type": "Feature",
  "properties": {
    "addr:full":"Gro\u00dfsch\u00f6rgern 34 Andorf Ober\u00f6sterreich 4770",
    "addr:housenumber":"34",
    "addr:postcode":"4770",
    "addr:street":"Grossschoergern",
    "iso:country":"AT",
    "sg:address":"Gro\u00dfsch\u00f6rgern 34",
    "sg:city":"Andorf",
    "sg:classifiers":[
        {
            "category":"Retail",
            "subcategory":"Repair Shop",
            "type":"Services"
        }
    ],
    "sg:phone":"+43 7766 2811",
    "sg:postcode":"4770",
    "sg:province":"Ober\u00f6sterreich",
    "sg:tags":[
        "agricultural",
        "machinery"
    ],
    "wof:name":"Josef Eder",
    "wof:placetype":"venue"
},
  "geometry": {"coordinates":[13.5776348114,48.371761322],"type":"Point"}
}