{
  "type": "Feature",
  "properties": {
    "addr:full":"Schulerstr 18 Wien Wien 1010",
    "addr:housenumber":"18",
    "addr:postcode":"1010",
    "addr:street":"Schulerstr",
    "iso:country":"AT",
    "sg:address":"Schulerstr 18",
    "sg:city":"Wien",
    "sg:orig_category":"Restaurants: Italienisch",
    "sg:phone":"+43 1 51244910",
    "sg:postcode":"1010",
    "sg:province":"Wien",
    "wof:name":"Da Capo Ristorante",
    "wof:placetype":"venue"
},
  "geometry": {"coordinates":[16.3763885498,48.2078170776],"type":"Point"}
}