{
  "type": "Feature",
  "properties": {
    "addr:full":"Lebinger Str 6 Perg Ober\u00f6sterreich 4320",
    "addr:housenumber":"6",
    "addr:postcode":"4320",
    "addr:street":"Str",
    "iso:country":"AT",
    "sg:address":"Lebinger Str 6",
    "sg:city":"Perg",
    "sg:orig_category":"Fotoapparate U -Artikel / Einzelhandel",
    "sg:phone":"+43 7262 52331",
    "sg:postcode":"4320",
    "sg:province":"Ober\u00f6sterreich",
    "wof:name":"Photo Schmidmayr",
    "wof:placetype":"venue"
},
  "geometry": {"coordinates":[14.6232347488,48.2587242126],"type":"Point"}
}