{
  "type": "Feature",
  "properties": {
    "iso:country":"AT",
    "sg:address":"Hosnedlg 13",
    "sg:city":"Wien",
    "sg:orig_category":"Maschinenreparatur",
    "sg:phone":"+43 1 2597517",
    "sg:postcode":"1220",
    "sg:province":"Wien",
    "wof:name":"Sulzer Christian",
    "wof:placetype":"venue"
},
  "geometry": {"coordinates":[16.4623355865,48.256111145],"type":"Point"}
}