{
  "type": "Feature",
  "properties": {
    "addr:full":"Ludwig-Binder-Str 26 Gleisdorf Steiermark 8200",
    "addr:housenumber":"26",
    "addr:postcode":"8200",
    "addr:street":"Ludwig-Binder-Str",
    "iso:country":"AT",
    "sg:address":"Ludwig-Binder-Str 26",
    "sg:city":"Gleisdorf",
    "sg:classifiers":[
        {
            "category":"Restaurant",
            "type":"Food & Drink"
        }
    ],
    "sg:phone":"+43 4331 1237001",
    "sg:postcode":"8200",
    "sg:province":"Steiermark",
    "wof:name":"Schnitzel & Co",
    "wof:placetype":"venue"
},
  "geometry": {"coordinates":[15.7051534653,47.1056213379],"type":"Point"}
}