{
  "type": "Feature",
  "properties": {
    "iso:country":"AT",
    "sg:address":"Klammstr 6",
    "sg:city":"Weiz",
    "sg:orig_category":"Friseure U Frisiersalons",
    "sg:phone":"+43 4331 722314",
    "sg:postcode":"8160",
    "sg:province":"Steiermark",
    "wof:name":"Creativ Fris\u00f6r Ewald",
    "wof:placetype":"venue"
},
  "geometry": {"coordinates":[15.6223592758,47.2183074951],"type":"Point"}
}