{
  "type": "Feature",
  "properties": {
    "addr:full":"Porzellang 22 Wien Wien 1090",
    "addr:housenumber":"22",
    "addr:postcode":"1090",
    "addr:street":"Porzellang",
    "iso:country":"AT",
    "sg:address":"Porzellang 22",
    "sg:city":"Wien",
    "sg:orig_category":"Behinderungen / Leben Mit Behinderungen",
    "sg:phone":"+43 1 3156818",
    "sg:postcode":"1090",
    "sg:province":"Wien",
    "wof:name":"Mobile Fr\u00fchf\u00f6rderung d Wiener Sozialdienste Standort S\u00fcd",
    "wof:placetype":"venue"
},
  "geometry": {"coordinates":[16.3610229492,48.2207107544],"type":"Point"}
}