{
  "type": "Feature",
  "properties": {
    "addr:full":"Handelskai 130 Wien Wien 1020",
    "addr:housenumber":"130",
    "addr:postcode":"1020",
    "addr:street":"Handelskai",
    "iso:country":"AT",
    "sg:address":"Handelskai 130",
    "sg:city":"Wien",
    "sg:orig_category":"Restaurants: Amerikanisch",
    "sg:phone":"+43 1 2185337",
    "sg:postcode":"1020",
    "sg:province":"Wien",
    "wof:name":"McDonald's Restaurant - McDrive",
    "wof:placetype":"venue"
},
  "geometry": {"coordinates":[16.3942203522,48.2341117859],"type":"Point"}
}