{
  "type": "Feature",
  "properties": {
    "iso:country":"AT",
    "sg:address":"Anzengruberstr 19",
    "sg:city":"Klagenfurt",
    "sg:orig_category":"Installationsunternehmen",
    "sg:phone":"+43 4346 321271",
    "sg:postcode":"9020",
    "sg:province":"K\u00e4rnten",
    "wof:name":"K\u00f6chl Wolfgang",
    "wof:placetype":"venue"
},
  "geometry": {"coordinates":[14.2807188034,46.6208381653],"type":"Point"}
}