{
  "type": "Feature",
  "properties": {
    "addr:full":"Waltersdorfer Str 43 Baden Nieder\u00f6sterreich 2500",
    "addr:housenumber":"43",
    "addr:postcode":"2500",
    "addr:street":"Waltersdorfer Str;Niederoesterreich",
    "iso:country":"AT",
    "sg:address":"Waltersdorfer Str 43",
    "sg:city":"Baden",
    "sg:orig_category":"Friseure U Frisiersalons",
    "sg:phone":"+43 4322 5249351",
    "sg:postcode":"2500",
    "sg:province":"Nieder\u00f6sterreich",
    "wof:name":"Berger Susanne",
    "wof:placetype":"venue"
},
  "geometry": {"coordinates":[16.2496948242,48.0004272461],"type":"Point"}
}