{
  "type": "Feature",
  "properties": {
    "iso:country":"AT",
    "sg:address":"Loferer Str 2",
    "sg:city":"Saalfelden am Steinernen Meer",
    "sg:orig_category":"Immobilienverwaltungen",
    "sg:phone":"+43 4365 8272463",
    "sg:postcode":"5760",
    "sg:province":"Salzburg",
    "wof:name":"Unterganschnigg Wilfried Vermietung & Verpachtung KEG",
    "wof:placetype":"venue"
},
  "geometry": {"coordinates":[12.8484992981,47.4254264832],"type":"Point"}
}