{
  "type": "Feature",
  "properties": {
    "iso:country":"AT",
    "sg:address":"Valenting 9-11",
    "sg:city":"Wien",
    "sg:orig_category":"Architekten",
    "sg:phone":"+43 1 8886954",
    "sg:postcode":"1230",
    "sg:province":"Wien",
    "wof:name":"Steinbichler Elisabeth Arch Dipl-Ing",
    "wof:placetype":"venue"
},
  "geometry": {"coordinates":[16.265039444,48.1495780945],"type":"Point"}
}