{
  "type": "Feature",
  "properties": {
    "addr:full":"Vorachstr 150 Lustenau Vorarlberg 6890",
    "addr:housenumber":"150",
    "addr:postcode":"6890",
    "iso:country":"AT",
    "sg:address":"Vorachstr 150",
    "sg:city":"Lustenau",
    "sg:orig_category":"Landwirtschaftliche Produkte",
    "sg:phone":"+43 5577 84740",
    "sg:postcode":"6890",
    "sg:province":"Vorarlberg",
    "wof:name":"Hofer Hermann",
    "wof:placetype":"venue"
},
  "geometry": {"coordinates":[9.6742868423,47.424823761],"type":"Point"}
}