{
  "type": "Feature",
  "properties": {
    "addr:full":"Puchg 8 Wien Wien 1220",
    "addr:housenumber":"8",
    "addr:postcode":"1220",
    "addr:street":"Puchg",
    "iso:country":"AT",
    "sg:address":"Puchg 8",
    "sg:city":"Wien",
    "sg:orig_category":"Transportunternehmen",
    "sg:phone":"+43 1 2593031",
    "sg:postcode":"1220",
    "sg:province":"Wien",
    "wof:name":"Kandler Josef",
    "wof:placetype":"venue"
},
  "geometry": {"coordinates":[16.4567012787,48.2622642517],"type":"Point"}
}