{
  "type": "Feature",
  "properties": {
    "addr:full":"Schallmooser Hauptstr 16 Salzburg Salzburg 5020",
    "addr:housenumber":"16",
    "addr:postcode":"5020",
    "addr:street":"Schallmooser Hauptstr;Salzburg",
    "iso:country":"AT",
    "sg:address":"Schallmooser Hauptstr 16",
    "sg:city":"Salzburg",
    "sg:classifiers":[
        {
            "category":"Retail",
            "subcategory":"Event Space",
            "type":"Services"
        }
    ],
    "sg:phone":"+43 4366 2876208",
    "sg:postcode":"5020",
    "sg:province":"Salzburg",
    "sg:tags":[
        "hand-",
        "u",
        "fu\u00c3\u0178pflege"
    ],
    "wof:name":"Kosmetik-Fu\u00dfpflege Ricki",
    "wof:placetype":"venue"
},
  "geometry": {"coordinates":[13.0523548126,47.8055763245],"type":"Point"}
}