{
  "type": "Feature",
  "properties": {
    "iso:country":"AT",
    "sg:address":"Lassallestr 11",
    "sg:city":"Wien",
    "sg:orig_category":"Tabaktrafiken",
    "sg:phone":"+43 1 2148879",
    "sg:postcode":"1020",
    "sg:province":"Wien",
    "wof:name":"Pekarek Brigitte",
    "wof:placetype":"venue"
},
  "geometry": {"coordinates":[16.4003639221,48.2235221863],"type":"Point"}
}