{
  "type": "Feature",
  "properties": {
    "addr:full":"Bogeng 14 Spittal an der Drau K\u00e4rnten 9800",
    "addr:housenumber":"14",
    "addr:postcode":"9800",
    "addr:street":"Bogeng;Kaernten",
    "iso:country":"AT",
    "sg:address":"Bogeng 14",
    "sg:city":"Spittal an der Drau",
    "sg:orig_category":"Immobilienmakler",
    "sg:phone":"+43 4762 37400",
    "sg:postcode":"9800",
    "sg:province":"K\u00e4rnten",
    "wof:name":"Realit\u00e4tenkanzlei Christine Rabl",
    "wof:placetype":"venue"
},
  "geometry": {"coordinates":[13.4995422363,46.7970199585],"type":"Point"}
}