{
  "type": "Feature",
  "properties": {
    "addr:full":"Nr 170 St. Johann in der Haide Steiermark 8295",
    "addr:postcode":"8295",
    "addr:street":"Nr 170;Der Haide Steiermark",
    "iso:country":"AT",
    "sg:address":"Nr 170",
    "sg:city":"St. Johann in der Haide",
    "sg:orig_category":"Abfallentsorgung U -Verwertung",
    "sg:phone":"+43 4333 32654560",
    "sg:postcode":"8295",
    "sg:province":"Steiermark",
    "wof:name":"Abfallwirtschaftsverband Hartberg (AWV-H)",
    "wof:placetype":"venue"
},
  "geometry": {"coordinates":[16.0245819092,47.2807769775],"type":"Point"}
}