{
  "type": "Feature",
  "properties": {
    "addr:full":"J v Eichendorff-Str 20 Salzburg Salzburg 5020",
    "addr:housenumber":"20",
    "addr:postcode":"5020",
    "addr:street":"J;Eichendorff-Str;Salzburg",
    "iso:country":"AT",
    "sg:address":"J v Eichendorff-Str 20",
    "sg:city":"Salzburg",
    "sg:orig_category":"Musikagenturen",
    "sg:phone":"+43 662 823788",
    "sg:postcode":"5020",
    "sg:province":"Salzburg",
    "wof:name":"Gesellschaft Musica Sacra Salzburg",
    "wof:placetype":"venue"
},
  "geometry": {"coordinates":[13.0433769226,47.8006744385],"type":"Point"}
}