{
  "type": "Feature",
  "properties": {
    "iso:country":"AT",
    "sg:address":"Leisingstrasse 2",
    "sg:city":"Kraubath an der Mur",
    "sg:classifiers":[
        {
            "category":"Home & Garden",
            "subcategory":"Carpets & Floor Coverings",
            "type":"Retail Goods"
        }
    ],
    "sg:phone":"+43 3832 2373",
    "sg:postcode":"8714",
    "sg:province":"Steiermark",
    "sg:tags":[
        "carpeting"
    ],
    "wof:name":"Matthias Saiger",
    "wof:placetype":"venue"
},
  "geometry": {"coordinates":[14.9665708542,47.3080711365],"type":"Point"}
}