{
  "type": "Feature",
  "properties": {
    "addr:full":"Rathausstr 19 Amstetten Nieder\u00f6sterreich 3300",
    "addr:housenumber":"19",
    "addr:postcode":"3300",
    "addr:street":"Rathausstr;Niederoesterreich",
    "iso:country":"AT",
    "sg:address":"Rathausstr 19",
    "sg:city":"Amstetten",
    "sg:orig_category":"Non-Classified Establishments",
    "sg:phone":"+43 7472 627540",
    "sg:postcode":"3300",
    "sg:province":"Nieder\u00f6sterreich",
    "wof:name":"Kirchenbeitragsstelle",
    "wof:placetype":"venue"
},
  "geometry": {"coordinates":[14.86906147,48.1223258972],"type":"Point"}
}