{
  "type": "Feature",
  "properties": {
    "addr:full":"Raiffeisenstr 1 Elsbethen-Glasenbach Salzburg 5061",
    "addr:housenumber":"1",
    "addr:postcode":"5061",
    "addr:street":"Raiffeisenstr;Salzburg",
    "iso:country":"AT",
    "sg:address":"Raiffeisenstr 1",
    "sg:city":"Elsbethen-Glasenbach",
    "sg:orig_category":"Telekommunikation",
    "sg:phone":"+43 4366 2621357",
    "sg:postcode":"5061",
    "sg:province":"Salzburg",
    "wof:name":"SCI-Telekommunikations GmbH",
    "wof:placetype":"venue"
},
  "geometry": {"coordinates":[13.0922317505,47.769405365],"type":"Point"}
}