{
  "type": "Feature",
  "properties": {
    "addr:full":"Ramperstorfferg 66 Wien Wien 1050",
    "addr:housenumber":"66",
    "addr:postcode":"1050",
    "addr:street":"Ramperstorfferg",
    "iso:country":"AT",
    "sg:address":"Ramperstorfferg 66",
    "sg:city":"Wien",
    "sg:orig_category":"Bierlokale-Pubs",
    "sg:phone":"+43 1 5442690",
    "sg:postcode":"1050",
    "sg:province":"Wien",
    "wof:name":"Little Stage",
    "wof:placetype":"venue"
},
  "geometry": {"coordinates":[16.3554058075,48.1901092529],"type":"Point"}
}