{
  "type": "Feature",
  "properties": {
    "iso:country":"AT",
    "sg:address":"Schlo\u00dfpl 4",
    "sg:city":"Karlstetten",
    "sg:orig_category":"Hauptschulen",
    "sg:phone":"+43 4327 418650",
    "sg:postcode":"3121",
    "sg:province":"Nieder\u00f6sterreich",
    "wof:name":"Hauptschule",
    "wof:placetype":"venue"
},
  "geometry": {"coordinates":[15.5651483536,48.2585983276],"type":"Point"}
}