{
  "type": "Feature",
  "properties": {
    "iso:country":"AT",
    "sg:address":"Gaswerkg 14",
    "sg:city":"Salzburg",
    "sg:orig_category":"Nachhilfe U Lernbetreuung",
    "sg:phone":"+43 4366 2433745",
    "sg:postcode":"5020",
    "sg:province":"Salzburg",
    "wof:name":"Schistek Ulrike",
    "wof:placetype":"venue"
},
  "geometry": {"coordinates":[13.033156395,47.8098106384],"type":"Point"}
}