{
  "type": "Feature",
  "properties": {
    "iso:country":"AT",
    "sg:address":"Grazer Str 5",
    "sg:city":"Rudersdorf",
    "sg:orig_category":"Innenausbau",
    "sg:phone":"+43 664 1527947",
    "sg:postcode":"7571",
    "sg:province":"Burgenland",
    "wof:name":"Thonhofer Willibald",
    "wof:placetype":"venue"
},
  "geometry": {"coordinates":[16.1186504364,47.0530738831],"type":"Point"}
}