{
  "type": "Feature",
  "properties": {
    "iso:country":"AT",
    "sg:address":"Sportplatzstrasse 53",
    "sg:city":"Enns",
    "sg:classifiers":[
        {
            "category":"Shopping",
            "subcategory":"Jewelry",
            "type":"Retail Goods"
        }
    ],
    "sg:phone":"+43 7223 849010",
    "sg:postcode":"4470",
    "sg:province":"Ober\u00f6sterreich",
    "sg:tags":[
        "fashion",
        "jewellery"
    ],
    "wof:name":"Sabine Kaiserseder Modeschmuck Inh. Birgit Freudenthaler",
    "wof:placetype":"venue"
},
  "geometry": {"coordinates":[14.4712438583,48.2063484192],"type":"Point"}
}