{
  "type": "Feature",
  "properties": {
    "addr:full":"Heiligenst\u00e4dter Str. 43  Wien Wien 1190",
    "addr:postcode":"1190",
    "addr:street":"Str. 43",
    "iso:country":"AT",
    "sg:address":"Heiligenst\u00e4dter Str. 43 ",
    "sg:city":"Wien",
    "sg:classifiers":[
        {
            "category":"Food & Beverages",
            "subcategory":"Groceries & Convenience Stores",
            "type":"Retail Goods"
        }
    ],
    "sg:phone":"+43 4313 6860380",
    "sg:postcode":"1190",
    "sg:province":"Wien",
    "sg:tags":[
        "drink"
    ],
    "wof:name":"SCHLUMBERGER WEIN- UND SEKTKELLEREI AG",
    "wof:placetype":"venue"
},
  "geometry": {"coordinates":[16.3576927185,48.23777771],"type":"Point"}
}