{
  "type": "Feature",
  "properties": {
    "addr:full":"Nr 1 Mariahof Steiermark 8812",
    "addr:postcode":"8812",
    "addr:street":"Nr;Mariahof",
    "iso:country":"AT",
    "sg:address":"Nr 1",
    "sg:city":"Mariahof",
    "sg:orig_category":"Non-Classified Establishments",
    "sg:phone":"+43 3584 2680",
    "sg:postcode":"8812",
    "sg:province":"Steiermark",
    "wof:name":"Pfarramt",
    "wof:placetype":"venue"
},
  "geometry": {"coordinates":[14.3994102478,47.0992660522],"type":"Point"}
}