{
  "type": "Feature",
  "properties": {
    "addr:full":"Stutterheimstr 16-18 Wien Wien 1150",
    "addr:postcode":"16-18;1150",
    "iso:country":"AT",
    "sg:address":"Stutterheimstr 16-18",
    "sg:city":"Wien",
    "sg:classifiers":[
        {
            "category":"Professional",
            "subcategory":"Computer Services",
            "type":"Services"
        }
    ],
    "sg:phone":"+43 1 98383980",
    "sg:postcode":"1150",
    "sg:province":"Wien",
    "sg:tags":[
        "software"
    ],
    "wof:name":"Kreml & Co GesmbH",
    "wof:placetype":"venue"
},
  "geometry": {"coordinates":[16.3255786896,48.2027435303],"type":"Point"}
}