{
  "type": "Feature",
  "properties": {
    "iso:country":"AT",
    "sg:address":"Josefst\u00e4dter Str 5",
    "sg:city":"Wien",
    "sg:orig_category":"Tai Chi, Tai Chi Chuan U Qi Gong",
    "sg:phone":"+43 1 40847860",
    "sg:postcode":"1080",
    "sg:province":"Wien",
    "sg:website":"www.shambhala.at",
    "wof:name":"Tai Chi Verein Shambhala",
    "wof:placetype":"venue"
},
  "geometry": {"coordinates":[16.3430690765,48.2106552124],"type":"Point"}
}