{
  "type": "Feature",
  "properties": {
    "iso:country":"AT",
    "sg:address":"Dompl 5",
    "sg:city":"Innsbruck",
    "sg:orig_category":"Non-Classified Establishments",
    "sg:phone":"+43 512 583123",
    "sg:postcode":"6020",
    "sg:province":"Tirol",
    "wof:name":"Bischofskanzlei",
    "wof:placetype":"venue"
},
  "geometry": {"coordinates":[11.3931331635,47.2695426941],"type":"Point"}
}