{
  "type": "Feature",
  "properties": {
    "addr:full":"IZ N\u00d6-S\u00fcd Strasse 2d, Obj. M44 2355",
    "addr:housenumber":"2d;m44",
    "addr:postcode":"2355",
    "addr:street":"Noe-Sued Strasse",
    "iso:country":"AT",
    "sg:address":"IZ N\u00d6-S\u00fcd Strasse 2d, Obj. M44",
    "sg:classifiers":[
        {
            "category":"Communications",
            "subcategory":"Film & Video Production",
            "type":"Services"
        }
    ],
    "sg:phone":"+43 2236 23422",
    "sg:postcode":"2355",
    "sg:tags":[
        "machine",
        "wrapping"
    ],
    "sg:website":"saropack.at",
    "wof:name":"Saropack Handels GmbH",
    "wof:placetype":"venue"
},
  "geometry": {"coordinates":[16.3183326721,48.0863113403],"type":"Point"}
}