{
  "type": "Feature",
  "properties": {
    "addr:full":"Pollheimerstrasse 17 Timelkam Ober\u00f6sterreich 4850",
    "addr:housenumber":"17",
    "addr:postcode":"4850",
    "addr:street":"Pollheimerstrasse",
    "iso:country":"AT",
    "sg:address":"Pollheimerstrasse 17",
    "sg:city":"Timelkam",
    "sg:classifiers":[
        {
            "category":"Utilities",
            "subcategory":"Cable",
            "type":"Services"
        }
    ],
    "sg:phone":"+43 7672941710",
    "sg:postcode":"4850",
    "sg:province":"Ober\u00f6sterreich",
    "sg:tags":[
        "cookers",
        "miscellaneous",
        "electric"
    ],
    "wof:name":"Elektro Fuchs Ges.m.b.H. & Co KG",
    "wof:placetype":"venue"
},
  "geometry": {"coordinates":[13.615281105,48.0023651123],"type":"Point"}
}