{
  "type": "Feature",
  "properties": {
    "addr:full":"Trentinig 12 Wien Wien 1230",
    "addr:housenumber":"12",
    "addr:postcode":"1230",
    "addr:street":"Trentinig",
    "iso:country":"AT",
    "sg:address":"Trentinig 12",
    "sg:city":"Wien",
    "sg:orig_category":"Immobilienmakler",
    "sg:phone":"+43 4313 289136",
    "sg:postcode":"1230",
    "sg:province":"Wien",
    "wof:name":"OPTIMAL REAL",
    "wof:placetype":"venue"
},
  "geometry": {"coordinates":[16.3216285706,48.1555633545],"type":"Point"}
}