{
  "type": "Feature",
  "properties": {
    "addr:full":"Landstr 12 Linz Ober\u00f6sterreich 4020",
    "addr:housenumber":"12",
    "addr:postcode":"4020",
    "addr:street":"Landstr",
    "iso:country":"AT",
    "sg:address":"Landstr 12",
    "sg:city":"Linz",
    "sg:orig_category":"Textilwaren / Einzelhandel",
    "sg:phone":"+43 732 794692",
    "sg:postcode":"4020",
    "sg:province":"Ober\u00f6sterreich",
    "wof:name":"GLENFIELD",
    "wof:placetype":"venue"
},
  "geometry": {"coordinates":[14.2885293961,48.303352356],"type":"Point"}
}