{
  "type": "Feature",
  "properties": {
    "iso:country":"AT",
    "sg:address":"Walfischg 5",
    "sg:city":"Wien",
    "sg:orig_category":"Friseure U Frisiersalons",
    "sg:phone":"+43 1 5127215",
    "sg:postcode":"1010",
    "sg:province":"Wien",
    "sg:website":"www.friseur-irene.at",
    "wof:name":"Chaos Hairconcept",
    "wof:placetype":"venue"
},
  "geometry": {"coordinates":[16.3710460663,48.203578949],"type":"Point"}
}