{
  "type": "Feature",
  "properties": {
    "addr:full":"Zahl\u00e4ckerweg 32 Stra\u00dfgang Steiermark 8054",
    "addr:housenumber":"32",
    "addr:postcode":"8054",
    "addr:street":"Zahlaeckerweg",
    "iso:country":"AT",
    "sg:address":"Zahl\u00e4ckerweg 32",
    "sg:city":"Stra\u00dfgang",
    "sg:orig_category":"Lichtkuppeln",
    "sg:phone":"+43 316 2529840",
    "sg:postcode":"8054",
    "sg:province":"Steiermark",
    "wof:name":"aTmos L\u00fcftungs- und Tageslichtsysteme GesmbH",
    "wof:placetype":"venue"
},
  "geometry": {"coordinates":[15.4109048843,47.0297889709],"type":"Point"}
}