{
  "type": "Feature",
  "properties": {
    "addr:full":"Stadtplatz 30 Gm\u00fcnd Nieder\u00f6sterreich 3950",
    "addr:housenumber":"30",
    "addr:postcode":"3950",
    "addr:street":"Stadtplatz;Niederoesterreich",
    "iso:country":"AT",
    "sg:address":"Stadtplatz 30",
    "sg:city":"Gm\u00fcnd",
    "sg:orig_category":"Non-Classified Establishments",
    "sg:phone":"+43 2852 524770",
    "sg:postcode":"3950",
    "sg:province":"Nieder\u00f6sterreich",
    "wof:name":"Friedrich Wandl Ges.m.b.H.",
    "wof:placetype":"venue"
},
  "geometry": {"coordinates":[14.985959053,48.7729225159],"type":"Point"}
}