{
  "type": "Feature",
  "properties": {
    "addr:full":"Savenauweg 24a St. Peter Steiermark 8042",
    "addr:housenumber":"24a",
    "addr:postcode":"8042",
    "addr:street":"Savenauweg",
    "iso:country":"AT",
    "sg:address":"Savenauweg 24a",
    "sg:city":"St. Peter",
    "sg:orig_category":"Rauchfangkehrer",
    "sg:phone":"+43 316 465095",
    "sg:postcode":"8042",
    "sg:province":"Steiermark",
    "wof:name":"Konrad Dieter",
    "wof:placetype":"venue"
},
  "geometry": {"coordinates":[15.5047063828,47.0674209595],"type":"Point"}
}