{
  "type": "Feature",
  "properties": {
    "iso:country":"AT",
    "sg:address":"Hochweg 4",
    "sg:city":"Velden am W\u00f6rther See",
    "sg:orig_category":"Pensionen / Privatzimmer",
    "sg:phone":"+43 676 6253400",
    "sg:postcode":"9220",
    "sg:province":"K\u00e4rnten",
    "wof:name":"G\u00e4stehaus Renate",
    "wof:placetype":"venue"
},
  "geometry": {"coordinates":[14.0336580276,46.6090927124],"type":"Point"}
}