{
  "type": "Feature",
  "properties": {
    "addr:full":"Porzellang 12 Wien Wien 1090",
    "addr:housenumber":"12",
    "addr:postcode":"1090",
    "addr:street":"Porzellang",
    "iso:country":"AT",
    "sg:address":"Porzellang 12",
    "sg:city":"Wien",
    "sg:orig_category":"Optiker",
    "sg:phone":"+43 1 3191971",
    "sg:postcode":"1090",
    "sg:province":"Wien",
    "wof:name":"Waluna Brillenstudio",
    "wof:placetype":"venue"
},
  "geometry": {"coordinates":[16.3623580933,48.2196807861],"type":"Point"}
}