{
  "type": "Feature",
  "properties": {
    "iso:country":"AT",
    "sg:address":"Berg 10",
    "sg:city":"St. Martin im Innkreis",
    "sg:orig_category":"Volksschulen",
    "sg:phone":"+43 7751 6100",
    "sg:postcode":"4973",
    "sg:province":"Ober\u00f6sterreich",
    "wof:name":"Volksschule Senftenbach",
    "wof:placetype":"venue"
},
  "geometry": {"coordinates":[13.4162845612,48.2599983215],"type":"Point"}
}