{
  "type": "Feature",
  "properties": {
    "addr:full":"Treustr 49/17 Wien Wien 1200",
    "addr:housenumber":"49 / 17",
    "addr:postcode":"1200",
    "addr:street":"Treustr",
    "iso:country":"AT",
    "sg:address":"Treustr 49/17",
    "sg:city":"Wien",
    "sg:orig_category":"Hausbetreuung",
    "sg:phone":"+43 650 3019331",
    "sg:postcode":"1200",
    "sg:province":"Wien",
    "wof:name":"Korecki Lukasz",
    "wof:placetype":"venue"
},
  "geometry": {"coordinates":[16.3643360138,48.230884552],"type":"Point"}
}