{
  "type": "Feature",
  "properties": {
    "addr:full":"Meierhofg 25 Hopfgarten im Brixental Tirol 6361",
    "addr:housenumber":"25",
    "addr:postcode":"6361",
    "addr:street":"Meierhofg;Tirol",
    "iso:country":"AT",
    "sg:address":"Meierhofg 25",
    "sg:city":"Hopfgarten im Brixental",
    "sg:orig_category":"Tischlereien",
    "sg:phone":"+43 5335 2294",
    "sg:postcode":"6361",
    "sg:province":"Tirol",
    "wof:name":"Biembacher Max",
    "wof:placetype":"venue"
},
  "geometry": {"coordinates":[12.1574897766,47.4497718811],"type":"Point"}
}