{
  "type": "Feature",
  "properties": {
    "addr:full":"Landstrasse 1 Lochau Vorarlberg 6911",
    "addr:housenumber":"1",
    "addr:postcode":"6911",
    "addr:street":"Landstrasse",
    "iso:country":"AT",
    "sg:address":"Landstrasse 1",
    "sg:city":"Lochau",
    "sg:classifiers":[
        {
            "category":"Farming",
            "subcategory":"Berry Farm",
            "type":"Manufacturing & Wholesale Goods"
        }
    ],
    "sg:phone":"+43 5574 422050",
    "sg:postcode":"6911",
    "sg:province":"Vorarlberg",
    "sg:tags":[
        "preserve"
    ],
    "sg:website":"vol.at/breganzia",
    "wof:name":"BREGANZIA Konserven GmbH & Co KG",
    "wof:placetype":"venue"
},
  "geometry": {"coordinates":[9.7517232895,47.5308685303],"type":"Point"}
}