{
  "type": "Feature",
  "properties": {
    "iso:country":"AT",
    "sg:address":"Quellenstr 154",
    "sg:city":"Wien",
    "sg:orig_category":"Alarmanlagen U Sicherheitssysteme",
    "sg:phone":"+43 1 69999620",
    "sg:postcode":"1100",
    "sg:province":"Wien",
    "wof:name":"DASATEC Sicherheitstechnik GmbH",
    "wof:placetype":"venue"
},
  "geometry": {"coordinates":[16.3590431213,48.1771507263],"type":"Point"}
}