{
  "type": "Feature",
  "properties": {
    "addr:full":"Harterfeldstr 7a Leonding Ober\u00f6sterreich 4060",
    "addr:housenumber":"7a",
    "addr:postcode":"4060",
    "addr:street":"Harterfeldstr",
    "iso:country":"AT",
    "sg:address":"Harterfeldstr 7a",
    "sg:city":"Leonding",
    "sg:orig_category":"Lebensmittel / Einzelhandel",
    "sg:phone":"+43 732 674443",
    "sg:postcode":"4060",
    "sg:province":"Ober\u00f6sterreich",
    "wof:name":"SPAR \u00f6sterreichische Warenhandels-AG",
    "wof:placetype":"venue"
},
  "geometry": {"coordinates":[14.258357048,48.2645111084],"type":"Point"}
}