{
  "type": "Feature",
  "properties": {
    "iso:country":"AT",
    "sg:address":"Hauptstr 53",
    "sg:city":"Stockerau",
    "sg:orig_category":"Fitnesscenter",
    "sg:phone":"+43 2266 61131",
    "sg:postcode":"2000",
    "sg:province":"Nieder\u00f6sterreich",
    "wof:name":"Fitnessinsel Otto Pfennig GesmbH",
    "wof:placetype":"venue"
},
  "geometry": {"coordinates":[16.2165603638,48.3862686157],"type":"Point"}
}