{
  "type": "Feature",
  "properties": {
    "addr:full":"Gerberg 1 Hall in Tirol Tirol 6060",
    "addr:housenumber":"1",
    "addr:postcode":"6060",
    "addr:street":"Gerberg;Tirol",
    "iso:country":"AT",
    "sg:address":"Gerberg 1",
    "sg:city":"Hall in Tirol",
    "sg:orig_category":"Fliesen U Platten",
    "sg:phone":"+43 4352 2356736",
    "sg:postcode":"6060",
    "sg:province":"Tirol",
    "wof:name":"Otto's Fliesen & Kachelstube",
    "wof:placetype":"venue"
},
  "geometry": {"coordinates":[11.50440979,47.2799415588],"type":"Point"}
}