{
  "type": "Feature",
  "properties": {
    "iso:country":"AT",
    "sg:address":"Obern 29a",
    "sg:city":"Leutasch",
    "sg:orig_category":"Appartements / Ferienwohnungen",
    "sg:phone":"+43 4352 146469",
    "sg:postcode":"6105",
    "sg:province":"Tirol",
    "wof:name":"Chalet Cristall - Rosenberger",
    "wof:placetype":"venue"
},
  "geometry": {"coordinates":[11.1253614426,47.3580665588],"type":"Point"}
}