{
  "type": "Feature",
  "properties": {
    "iso:country":"AT",
    "sg:address":"Industriestr 5",
    "sg:city":"Wolfern",
    "sg:orig_category":"Nachhilfe U Lernbetreuung",
    "sg:phone":"+43 7253 7250",
    "sg:postcode":"4493",
    "sg:province":"Ober\u00f6sterreich",
    "wof:name":"Eckelt Gabriela",
    "wof:placetype":"venue"
},
  "geometry": {"coordinates":[14.3772583008,48.0868988037],"type":"Point"}
}