{
  "type": "Feature",
  "properties": {
    "iso:country":"AT",
    "sg:address":"Gaisbacher Strasse 15",
    "sg:city":"Gallneukirchen",
    "sg:classifiers":[
        {
            "category":"Real Estate",
            "subcategory":"Architect",
            "type":"Services"
        }
    ],
    "sg:phone":"+43 7235 62240",
    "sg:postcode":"4210",
    "sg:province":"Ober\u00f6sterreich",
    "sg:tags":[
        "interior",
        "decoration"
    ],
    "sg:website":"1-deutsch.at",
    "wof:name":"Ludwig Deutsch",
    "wof:placetype":"venue"
},
  "geometry": {"coordinates":[14.4168729782,48.3506088257],"type":"Point"}
}