{
  "type": "Feature",
  "properties": {
    "addr:full":"Hans Sachs-G 10 Wiener Neustadt Nieder\u00f6sterreich 2700",
    "addr:housenumber":"10",
    "addr:postcode":"2700",
    "iso:country":"AT",
    "sg:address":"Hans Sachs-G 10",
    "sg:city":"Wiener Neustadt",
    "sg:classifiers":[
        {
            "category":"Professional",
            "subcategory":"Computer Services",
            "type":"Services"
        }
    ],
    "sg:phone":"+43 2622 218190",
    "sg:postcode":"2700",
    "sg:province":"Nieder\u00f6sterreich",
    "sg:tags":[
        "software"
    ],
    "wof:name":"DR Software GmbH",
    "wof:placetype":"venue"
},
  "geometry": {"coordinates":[16.2186508179,47.8123321533],"type":"Point"}
}