{
  "type": "Feature",
  "properties": {
    "addr:full":"Ramsauer Str 129 Schladming Steiermark 8970",
    "addr:housenumber":"129",
    "addr:postcode":"8970",
    "iso:country":"AT",
    "sg:address":"Ramsauer Str 129",
    "sg:city":"Schladming",
    "sg:orig_category":"Ingenieurkonsulenten / Zivilingenieure",
    "sg:phone":"+43 3687 226800",
    "sg:postcode":"8970",
    "sg:province":"Steiermark",
    "wof:name":"Badura Heinz Dipl-Ing",
    "wof:placetype":"venue"
},
  "geometry": {"coordinates":[13.6850805283,47.3915252686],"type":"Point"}
}