{
  "type": "Feature",
  "properties": {
    "addr:full":"Untere Hauptstr 99 Wulkaprodersdorf Burgenland 7041",
    "addr:housenumber":"99",
    "addr:postcode":"7041",
    "addr:street":"Untere Hauptstr",
    "iso:country":"AT",
    "sg:address":"Untere Hauptstr 99",
    "sg:city":"Wulkaprodersdorf",
    "sg:orig_category":"Fleischhauereien",
    "sg:phone":"+43 2687 62244",
    "sg:postcode":"7041",
    "sg:province":"Burgenland",
    "wof:name":"Krojer Willibald",
    "wof:placetype":"venue"
},
  "geometry": {"coordinates":[16.5077877045,47.7967414856],"type":"Point"}
}