{
  "type": "Feature",
  "properties": {
    "addr:full":"Schubertpl 1 Feldkirch Vorarlberg 6800",
    "addr:housenumber":"1",
    "addr:postcode":"6800",
    "addr:street":"Schubertpl",
    "iso:country":"AT",
    "sg:address":"Schubertpl 1",
    "sg:city":"Feldkirch",
    "sg:orig_category":"Nachhilfe U Lernbetreuung",
    "sg:phone":"+43 5522 82315",
    "sg:postcode":"6800",
    "sg:province":"Vorarlberg",
    "wof:name":"Studientreff Feldkirch",
    "wof:placetype":"venue"
},
  "geometry": {"coordinates":[9.5986003876,47.2341575623],"type":"Point"}
}