{
  "type": "Feature",
  "properties": {
    "addr:full":"St.-Nikolaus-G 10 Innsbruck Tirol 6020",
    "addr:housenumber":"10",
    "addr:postcode":"6020",
    "addr:street":"St.-Nikolaus-G;Tirol",
    "iso:country":"AT",
    "sg:address":"St.-Nikolaus-G 10",
    "sg:city":"Innsbruck",
    "sg:orig_category":"Non-Classified Establishments",
    "sg:phone":"+43 512 274826",
    "sg:postcode":"6020",
    "sg:province":"Tirol",
    "wof:name":"Viktoria Bau GmbH",
    "wof:placetype":"venue"
},
  "geometry": {"coordinates":[11.3925170898,47.2725143433],"type":"Point"}
}