{
  "type": "Feature",
  "properties": {
    "iso:country":"AT",
    "sg:address":"Stadtpl 16",
    "sg:city":"Radstadt",
    "sg:orig_category":"Psychotherapie",
    "sg:phone":"+43 664 5911359",
    "sg:postcode":"5550",
    "sg:province":"Salzburg",
    "wof:name":"Kiefer Eva B Mag",
    "wof:placetype":"venue"
},
  "geometry": {"coordinates":[13.4625864029,47.3844833374],"type":"Point"}
}