{
  "type": "Feature",
  "properties": {
    "iso:country":"AT",
    "sg:address":"Neug 4/Stg1",
    "sg:city":"Hinterbr\u00fchl",
    "sg:classifiers":[
        {
            "category":"Professional",
            "subcategory":"Computer Services",
            "type":"Services"
        }
    ],
    "sg:phone":"+43 2236 45087",
    "sg:postcode":"2371",
    "sg:province":"Nieder\u00f6sterreich",
    "sg:tags":[
        "software"
    ],
    "wof:name":"K\u00f6bu Data GesmbH",
    "wof:placetype":"venue"
},
  "geometry": {"coordinates":[16.2608547211,48.0851364136],"type":"Point"}
}