{
  "type": "Feature",
  "properties": {
    "addr:full":"Bahnhofstrasse 31 Kematen in Tirol Tirol 6175",
    "addr:housenumber":"31",
    "addr:postcode":"6175",
    "addr:street":"Bahnhofstrasse;Tirol",
    "iso:country":"AT",
    "sg:address":"Bahnhofstrasse 31",
    "sg:city":"Kematen in Tirol",
    "sg:classifiers":[
        {
            "category":"Sports & Exercise",
            "subcategory":"Gym",
            "type":"Entertainment"
        }
    ],
    "sg:phone":"+43 5232 24860",
    "sg:postcode":"6175",
    "sg:province":"Tirol",
    "sg:tags":[
        "athletic",
        "equipment",
        "gymnastic"
    ],
    "sg:website":"team-sport-kematen.at",
    "wof:name":"Team - Sport Ges.m.b.H. & Co KG",
    "wof:placetype":"venue"
},
  "geometry": {"coordinates":[11.258890152,47.2597961426],"type":"Point"}
}