{
  "type": "Feature",
  "properties": {
    "addr:full":"Am Vormarkt 9 Frohnleiten Steiermark 8130",
    "addr:housenumber":"9",
    "addr:postcode":"8130",
    "addr:street":"Am Vormarkt",
    "iso:country":"AT",
    "sg:address":"Am Vormarkt 9",
    "sg:city":"Frohnleiten",
    "sg:orig_category":"Fahrschulen",
    "sg:phone":"+43 3126 3747",
    "sg:postcode":"8130",
    "sg:province":"Steiermark",
    "wof:name":"Fahrschule Waitzl",
    "wof:placetype":"venue"
},
  "geometry": {"coordinates":[15.3229179382,47.2684593201],"type":"Point"}
}