{
  "type": "Feature",
  "properties": {
    "addr:full":"Niederottnang 149 Ottnang am Hausruck Ober\u00f6sterreich 4901",
    "addr:housenumber":"149",
    "addr:postcode":"4901",
    "addr:street":"Niederottnang",
    "iso:country":"AT",
    "sg:address":"Niederottnang 149",
    "sg:city":"Ottnang am Hausruck",
    "sg:orig_category":"Musikunterricht",
    "sg:phone":"+43 76766140",
    "sg:postcode":"4901",
    "sg:province":"Ober\u00f6sterreich",
    "wof:name":"Landesmusikschule Ottnang",
    "wof:placetype":"venue"
},
  "geometry": {"coordinates":[13.6627902985,48.0965843201],"type":"Point"}
}