{
  "type": "Feature",
  "properties": {
    "addr:full":"Bobletten 32 Dornbirn Vorarlberg 6850",
    "addr:housenumber":"32",
    "addr:postcode":"6850",
    "addr:street":"Bobletten",
    "iso:country":"AT",
    "sg:address":"Bobletten 32",
    "sg:city":"Dornbirn",
    "sg:classifiers":[
        {
            "category":"Manufacturing",
            "subcategory":"Wood Products",
            "type":"Manufacturing & Wholesale Goods"
        }
    ],
    "sg:phone":"+43 5572 34096",
    "sg:postcode":"6850",
    "sg:province":"Vorarlberg",
    "sg:tags":[
        "lumber"
    ],
    "wof:name":"Hilbe S\u00e4gewerk KG",
    "wof:placetype":"venue"
},
  "geometry": {"coordinates":[9.7119674683,47.3875541687],"type":"Point"}
}