{
  "type": "Feature",
  "properties": {
    "addr:full":"Zapfendorfer Str 11 Grafenstein K\u00e4rnten 9131",
    "addr:housenumber":"11",
    "addr:postcode":"9131",
    "addr:street":"Str;Kaernten",
    "iso:country":"AT",
    "sg:address":"Zapfendorfer Str 11",
    "sg:city":"Grafenstein",
    "sg:orig_category":"Tischlereien",
    "sg:phone":"+43 4225 2118",
    "sg:postcode":"9131",
    "sg:province":"K\u00e4rnten",
    "wof:name":"Prasenc Gottfried",
    "wof:placetype":"venue"
},
  "geometry": {"coordinates":[14.4707555771,46.6106987],"type":"Point"}
}