{
  "type": "Feature",
  "properties": {
    "addr:full":"Schmiedstr 28 Eferding Ober\u00f6sterreich 4070",
    "addr:housenumber":"28",
    "addr:postcode":"4070",
    "addr:street":"Schmiedstr",
    "iso:country":"AT",
    "sg:address":"Schmiedstr 28",
    "sg:city":"Eferding",
    "sg:orig_category":"Lebensmittel / Einzelhandel",
    "sg:phone":"+43 4372 723132",
    "sg:postcode":"4070",
    "sg:province":"Ober\u00f6sterreich",
    "wof:name":"Penny Markt",
    "wof:placetype":"venue"
},
  "geometry": {"coordinates":[14.020485878,48.3088912964],"type":"Point"}
}