{
  "type": "Feature",
  "properties": {
    "addr:full":"Dieselg 1-3 Wien Wien 1100",
    "addr:housenumber":"1-3",
    "addr:postcode":"1100",
    "addr:street":"Dieselg",
    "iso:country":"AT",
    "sg:address":"Dieselg 1-3",
    "sg:city":"Wien",
    "sg:orig_category":"Lebensmittel / Einzelhandel",
    "sg:phone":"+43 1 6002814",
    "sg:postcode":"1100",
    "sg:province":"Wien",
    "wof:name":"ADEG Contra Markt",
    "wof:placetype":"venue"
},
  "geometry": {"coordinates":[16.3724899292,48.1672019958],"type":"Point"}
}