{
  "type": "Feature",
  "properties": {
    "addr:full":"Walkerg 12 Wien Wien 1210",
    "addr:housenumber":"12",
    "addr:postcode":"1210",
    "addr:street":"Walkerg",
    "iso:country":"AT",
    "sg:address":"Walkerg 12",
    "sg:city":"Wien",
    "sg:orig_category":"Werbeagenturen",
    "sg:phone":"+43 1 6627980",
    "sg:postcode":"1210",
    "sg:province":"Wien",
    "wof:name":"CREATIVE ORANGE - SCHINDLER & SCHMIDT OEG",
    "wof:placetype":"venue"
},
  "geometry": {"coordinates":[16.4032821655,48.2430305481],"type":"Point"}
}