{
  "type": "Feature",
  "properties": {
    "addr:full":"Neulinggasse 29 Wien Wien 1030",
    "addr:housenumber":"29",
    "addr:postcode":"1030",
    "addr:street":"Neulinggasse",
    "iso:country":"AT",
    "sg:address":"Neulinggasse 29",
    "sg:city":"Wien",
    "sg:classifiers":[
        {
            "category":"Travel",
            "subcategory":"Travel Agent",
            "type":"Entertainment"
        }
    ],
    "sg:phone":"+43 4317 124621",
    "sg:postcode":"1030",
    "sg:province":"Wien",
    "sg:tags":[
        "business"
    ],
    "wof:name":"EUREST RESTAURATIONSBETRIEBSGES.MBH",
    "wof:placetype":"venue"
},
  "geometry": {"coordinates":[16.3846740723,48.1990470886],"type":"Point"}
}