{
  "type": "Feature",
  "properties": {
    "addr:full":"Karl-Zanger-Str 6 Absam Tirol 6067",
    "addr:housenumber":"6",
    "addr:postcode":"6067",
    "addr:street":"Karl-Zanger-Str;Tirol",
    "iso:country":"AT",
    "sg:address":"Karl-Zanger-Str 6",
    "sg:city":"Absam",
    "sg:orig_category":"Friseure U Frisiersalons",
    "sg:phone":"+43 4352 2356574",
    "sg:postcode":"6067",
    "sg:province":"Tirol",
    "wof:name":"Zanger Anna",
    "wof:placetype":"venue"
},
  "geometry": {"coordinates":[11.505109787,47.292766571],"type":"Point"}
}