{
  "type": "Feature",
  "properties": {
    "addr:full":"Elisabethstr 27 Baden Nieder\u00f6sterreich 2500",
    "addr:housenumber":"27",
    "addr:postcode":"2500",
    "addr:street":"Elisabethstr;Niederoesterreich",
    "iso:country":"AT",
    "sg:address":"Elisabethstr 27",
    "sg:city":"Baden",
    "sg:orig_category":"\u00c3\u201erzte / F Allgemeinmedizin",
    "sg:phone":"+43 2252 48854",
    "sg:postcode":"2500",
    "sg:province":"Nieder\u00f6sterreich",
    "wof:name":"Sedlacek Gabriele Angelika Dr",
    "wof:placetype":"venue"
},
  "geometry": {"coordinates":[16.2323741913,48.002571106],"type":"Point"}
}