{
  "type": "Feature",
  "properties": {
    "iso:country":"AT",
    "sg:address":"Am Nordrain 9",
    "sg:city":"St. Marien",
    "sg:orig_category":"Zoologiebedarf",
    "sg:phone":"+43 7227 4008",
    "sg:postcode":"4502",
    "sg:province":"Ober\u00f6sterreich",
    "wof:name":"Kleintierzuchtbedarf - Sturmberger Manfred",
    "wof:placetype":"venue"
},
  "geometry": {"coordinates":[14.2549276352,48.1687393188],"type":"Point"}
}