{
  "type": "Feature",
  "properties": {
    "iso:country":"AT",
    "sg:address":"Parkstr 26",
    "sg:city":"Bad Hofgastein",
    "sg:orig_category":"Appartements / Ferienwohnungen",
    "sg:phone":"+43 6432 67140",
    "sg:postcode":"5630",
    "sg:province":"Salzburg",
    "wof:name":"Appartementhaus Alpina Gorscheg-Czerny Gabriela",
    "wof:placetype":"venue"
},
  "geometry": {"coordinates":[13.0985736847,47.1736869812],"type":"Point"}
}