{
  "type": "Feature",
  "properties": {
    "addr:full":"Nr 155 W\u00f6rgl Tirol 6300",
    "addr:postcode":"6300",
    "addr:street":"Nr 155 Woergl Tirol",
    "iso:country":"AT",
    "sg:address":"Nr 155",
    "sg:city":"W\u00f6rgl",
    "sg:orig_category":"Transportunternehmen",
    "sg:phone":"+43 699 18416045",
    "sg:postcode":"6300",
    "sg:province":"Tirol",
    "wof:name":"Freund Werner",
    "wof:placetype":"venue"
},
  "geometry": {"coordinates":[12.0642328262,47.506893158],"type":"Point"}
}