{
  "type": "Feature",
  "properties": {
    "iso:country":"AT",
    "sg:address":"Salzstra\u00dfe 3",
    "sg:city":"Flaurling",
    "sg:orig_category":"Freizeit, Musik",
    "sg:phone":"+43 5262 67320",
    "sg:postcode":"6403",
    "sg:province":"Tirol",
    "sg:website":"http://www.ennemoser.com",
    "wof:name":"C37 Acoustics Dieter ENNEMOSER",
    "wof:placetype":"venue"
},
  "geometry": {"coordinates":[11.1237049103,47.2917556763],"type":"Point"}
}