{
  "type": "Feature",
  "properties": {
    "addr:full":"Obermillst\u00e4tter Str 169 Millstatt K\u00e4rnten 9872",
    "addr:housenumber":"169",
    "addr:postcode":"9872",
    "addr:street":"Str;Kaernten",
    "iso:country":"AT",
    "sg:address":"Obermillst\u00e4tter Str 169",
    "sg:city":"Millstatt",
    "sg:orig_category":"Pensionen / Privatzimmer",
    "sg:phone":"+43 4766 2044",
    "sg:postcode":"9872",
    "sg:province":"K\u00e4rnten",
    "wof:name":"Haus Franz",
    "wof:placetype":"venue"
},
  "geometry": {"coordinates":[13.5759601593,46.8054580688],"type":"Point"}
}