{
  "type": "Feature",
  "properties": {
    "addr:full":"Nr 209 Mieming Tirol 6414",
    "addr:postcode":"6414",
    "addr:street":"Nr 209;Tirol",
    "iso:country":"AT",
    "sg:address":"Nr 209",
    "sg:city":"Mieming",
    "sg:orig_category":"Estriche",
    "sg:phone":"+43 5264 20268",
    "sg:postcode":"6414",
    "sg:province":"Tirol",
    "wof:name":"P\u00f6schl Winfried",
    "wof:placetype":"venue"
},
  "geometry": {"coordinates":[11.0065221786,47.3184700012],"type":"Point"}
}