{
  "type": "Feature",
  "properties": {
    "addr:full":"Dorfstr 22 K\u00f6ssen Tirol 6345",
    "addr:housenumber":"22",
    "addr:postcode":"6345",
    "addr:street":"Dorfstr;Tirol",
    "iso:country":"AT",
    "sg:address":"Dorfstr 22",
    "sg:city":"K\u00f6ssen",
    "sg:orig_category":"Tourismusinformation U -Organisationen",
    "sg:phone":"+43 5375 6816",
    "sg:postcode":"6345",
    "sg:province":"Tirol",
    "wof:name":"Tourismusverband Schwendt",
    "wof:placetype":"venue"
},
  "geometry": {"coordinates":[12.394115448,47.6410293579],"type":"Point"}
}