{
  "type": "Feature",
  "properties": {
    "iso:country":"AT",
    "sg:address":"Zeller Str 9",
    "sg:city":"Mittersill",
    "sg:orig_category":"Optiker",
    "sg:phone":"+43 4365 6247810",
    "sg:postcode":"5730",
    "sg:province":"Salzburg",
    "wof:name":"Sehen & H\u00f6ren Maurer GmbH",
    "wof:placetype":"venue"
},
  "geometry": {"coordinates":[12.4825763702,47.28332901],"type":"Point"}
}