{
  "type": "Feature",
  "properties": {
    "iso:country":"AT",
    "sg:address":"Nr 68",
    "sg:city":"Hohentauern",
    "sg:orig_category":"Pensionen / Privatzimmer",
    "sg:phone":"+43 4336 18307",
    "sg:postcode":"8785",
    "sg:province":"Steiermark",
    "wof:name":"Ritzinger - Privatzimmer",
    "wof:placetype":"venue"
},
  "geometry": {"coordinates":[14.4843893051,47.4336090088],"type":"Point"}
}