{
  "type": "Feature",
  "properties": {
    "iso:country":"AT",
    "sg:address":"Franz-Martin-Str 2",
    "sg:city":"Salzburg",
    "sg:orig_category":"Physiotherapie",
    "sg:phone":"+43 4366 41554458",
    "sg:postcode":"5020",
    "sg:province":"Salzburg",
    "wof:name":"Huber Angelika Dipl-PT",
    "wof:placetype":"venue"
},
  "geometry": {"coordinates":[13.0349321365,47.8163948059],"type":"Point"}
}