{
  "type": "Feature",
  "properties": {
    "addr:full":"Ursulinenpl 8 Salzburg Salzburg 5020",
    "addr:housenumber":"8",
    "addr:postcode":"5020",
    "addr:street":"Ursulinenpl;Salzburg",
    "iso:country":"AT",
    "sg:address":"Ursulinenpl 8",
    "sg:city":"Salzburg",
    "sg:orig_category":"Spielwaren U Spiele",
    "sg:phone":"+43 4366 2849919",
    "sg:postcode":"5020",
    "sg:province":"Salzburg",
    "wof:name":"Spiel Raum",
    "wof:placetype":"venue"
},
  "geometry": {"coordinates":[13.0380249023,47.8024139404],"type":"Point"}
}