{
  "type": "Feature",
  "properties": {
    "iso:country":"AT",
    "sg:address":"Freindorfer Str 13",
    "sg:city":"Ansfelden",
    "sg:orig_category":"Bauunternehmen",
    "sg:phone":"+43 4367 65571285",
    "sg:postcode":"4052",
    "sg:province":"Ober\u00f6sterreich",
    "wof:name":"1 A-Bau",
    "wof:placetype":"venue"
},
  "geometry": {"coordinates":[14.2966899872,48.2299804688],"type":"Point"}
}