{
  "type": "Feature",
  "properties": {
    "addr:full":"Hermann Sander-Str 3/1 Bludenz Vorarlberg 6700",
    "addr:housenumber":"3 / 1",
    "addr:postcode":"6700",
    "iso:country":"AT",
    "sg:address":"Hermann Sander-Str 3/1",
    "sg:city":"Bludenz",
    "sg:orig_category":"Medizinische Beratung",
    "sg:phone":"+43 5552 65035",
    "sg:postcode":"6700",
    "sg:province":"Vorarlberg",
    "wof:name":"aks Arbeitskreis f Vorsorge- und Sozialmedizin gemeinn\u00fctzige Betriebs GmbH",
    "wof:placetype":"venue"
},
  "geometry": {"coordinates":[9.8172082901,47.1539154053],"type":"Point"}
}