{
  "type": "Feature",
  "properties": {
    "iso:country":"AT",
    "sg:address":"Landstr 28",
    "sg:city":"Hard",
    "sg:orig_category":"Bestattungsunternehmen",
    "sg:phone":"+43 4355 7482080",
    "sg:postcode":"6971",
    "sg:province":"Vorarlberg",
    "wof:name":"NUCK Bestattungs GmbH - G\u00fcnther Nuck",
    "wof:placetype":"venue"
},
  "geometry": {"coordinates":[9.6876916885,47.4867668152],"type":"Point"}
}