{
  "type": "Feature",
  "properties": {
    "addr:full":"Gerling 3 Herzogsdorf Ober\u00f6sterreich 4175",
    "addr:housenumber":"3",
    "addr:postcode":"4175",
    "addr:street":"Gerling",
    "iso:country":"AT",
    "sg:address":"Gerling 3",
    "sg:city":"Herzogsdorf",
    "sg:classifiers":[
        {
            "category":"Home & Garden",
            "subcategory":"Building Materials",
            "type":"Retail Goods"
        }
    ],
    "sg:phone":"+43 7232 2818",
    "sg:postcode":"4175",
    "sg:province":"Ober\u00f6sterreich",
    "sg:tags":[
        "steel",
        "balcony"
    ],
    "sg:website":"koegl.co.at",
    "wof:name":"Manfred K\u00f6gl",
    "wof:placetype":"venue"
},
  "geometry": {"coordinates":[14.0855636597,48.4026184082],"type":"Point"}
}