{
  "type": "Feature",
  "properties": {
    "addr:full":"Uhlandstr 39 Wels Ober\u00f6sterreich 4600",
    "addr:housenumber":"39",
    "addr:postcode":"4600",
    "addr:street":"Uhlandstr;Oberoesterreich",
    "iso:country":"AT",
    "sg:address":"Uhlandstr 39",
    "sg:city":"Wels",
    "sg:orig_category":"Metallbau",
    "sg:phone":"+43 7242 211415",
    "sg:postcode":"4600",
    "sg:province":"Ober\u00f6sterreich",
    "wof:name":"Wittberger Gerald",
    "wof:placetype":"venue"
},
  "geometry": {"coordinates":[14.0764055252,48.1793670654],"type":"Point"}
}