{
  "type": "Feature",
  "properties": {
    "addr:full":"Turnerstr 10 Gnigl Salzburg 5023",
    "addr:housenumber":"10",
    "addr:postcode":"5023",
    "addr:street":"Turnerstr",
    "iso:country":"AT",
    "sg:address":"Turnerstr 10",
    "sg:city":"Gnigl",
    "sg:orig_category":"Bauunternehmen",
    "sg:phone":"+43 662 640427",
    "sg:postcode":"5023",
    "sg:province":"Salzburg",
    "wof:name":"PLAN KO BAU GmbH - Baumeister Dumfort",
    "wof:placetype":"venue"
},
  "geometry": {"coordinates":[13.0691614151,47.8166236877],"type":"Point"}
}