{
  "type": "Feature",
  "properties": {
    "iso:country":"AT",
    "sg:address":"Erberpromenade 29",
    "sg:city":"Himberg",
    "sg:orig_category":"Polytechnische Schulen",
    "sg:phone":"+43 2235 87914",
    "sg:postcode":"2325",
    "sg:province":"Nieder\u00f6sterreich",
    "wof:name":"Polytechnische Schule",
    "wof:placetype":"venue"
},
  "geometry": {"coordinates":[16.4394855499,48.0822868347],"type":"Point"}
}