{
  "type": "Feature",
  "properties": {
    "iso:country":"AT",
    "sg:address":"Kahlenberger Str 46",
    "sg:city":"Wien",
    "sg:orig_category":"Sektkellereien",
    "sg:phone":"+43 1 3187080",
    "sg:postcode":"1190",
    "sg:province":"Wien",
    "wof:name":"Inf\u00fchr Karl KG",
    "wof:placetype":"venue"
},
  "geometry": {"coordinates":[16.3589172363,48.2578392029],"type":"Point"}
}