{
  "type": "Feature",
  "properties": {
    "addr:full":"Meidlinger Hauptstr 30 Wien Wien 1120",
    "addr:housenumber":"30",
    "addr:postcode":"1120",
    "addr:street":"Meidlinger Hauptstr",
    "iso:country":"AT",
    "sg:address":"Meidlinger Hauptstr 30",
    "sg:city":"Wien",
    "sg:orig_category":"Friseure U Frisiersalons",
    "sg:phone":"+43 4318 139571",
    "sg:postcode":"1120",
    "sg:province":"Wien",
    "wof:name":"Salon Viktor Inh Christian Lehner",
    "wof:placetype":"venue"
},
  "geometry": {"coordinates":[16.3295459747,48.1803092957],"type":"Point"}
}