{
  "type": "Feature",
  "properties": {
    "addr:full":"Waldgasse 54-58 Gerasdorf Nieder\u00f6sterreich 2201",
    "addr:postcode":"54-58;2201",
    "addr:street":"Waldgasse;Niederoesterreich",
    "iso:country":"AT",
    "sg:address":"Waldgasse 54-58",
    "sg:city":"Gerasdorf",
    "sg:orig_category":"Software For Glaziers",
    "sg:phone":"+43 2246 4546",
    "sg:postcode":"2201",
    "sg:province":"Nieder\u00f6sterreich",
    "sg:website":"dataflex.at",
    "wof:name":"Dataflex Handelsges.m.b.H.",
    "wof:placetype":"venue"
},
  "geometry": {"coordinates":[16.4931221008,48.3155555725],"type":"Point"}
}