{
  "type": "Feature",
  "properties": {
    "addr:full":"Nr 150 Ardning Steiermark 8904",
    "addr:postcode":"8904",
    "addr:street":"Nr;Ardning",
    "iso:country":"AT",
    "sg:address":"Nr 150",
    "sg:city":"Ardning",
    "sg:orig_category":"Volksschulen",
    "sg:phone":"+43 3612 7277",
    "sg:postcode":"8904",
    "sg:province":"Steiermark",
    "wof:name":"Volksschule",
    "wof:placetype":"venue"
},
  "geometry": {"coordinates":[14.3644237518,47.5910682678],"type":"Point"}
}