{
  "type": "Feature",
  "properties": {
    "addr:full":"Erdbrustg 52 Wien Wien 1160",
    "addr:housenumber":"52",
    "addr:postcode":"1160",
    "addr:street":"Erdbrustg",
    "iso:country":"AT",
    "sg:address":"Erdbrustg 52",
    "sg:city":"Wien",
    "sg:orig_category":"Psychotherapie",
    "sg:phone":"+43 1 4859158",
    "sg:postcode":"1160",
    "sg:province":"Wien",
    "wof:name":"Huber Bettina Mag",
    "wof:placetype":"venue"
},
  "geometry": {"coordinates":[16.2999744415,48.2159805298],"type":"Point"}
}