{
  "type": "Feature",
  "properties": {
    "addr:full":"Veluxstrasse 3 Wolkersdorf im Weinviertel Nieder\u00f6sterreich 2120",
    "addr:housenumber":"3",
    "addr:postcode":"2120",
    "addr:street":"Veluxstrasse",
    "iso:country":"AT",
    "sg:address":"Veluxstrasse 3",
    "sg:city":"Wolkersdorf im Weinviertel",
    "sg:classifiers":[
        {
            "category":"Home & Garden",
            "subcategory":"Building Materials",
            "type":"Retail Goods"
        }
    ],
    "sg:phone":"+43 2245 32350",
    "sg:postcode":"2120",
    "sg:province":"Nieder\u00f6sterreich",
    "sg:tags":[
        "antiglare",
        "blind",
        "roller"
    ],
    "sg:website":"velux.at",
    "wof:name":"VELUX \u00d6sterreich GmbH",
    "wof:placetype":"venue"
},
  "geometry": {"coordinates":[16.5088787079,48.381061554],"type":"Point"}
}