{
  "type": "Feature",
  "properties": {
    "addr:full":"Quellenstrasse 50 Wien Wien 1100",
    "addr:housenumber":"50",
    "addr:postcode":"1100",
    "addr:street":"Quellenstrasse",
    "iso:country":"AT",
    "sg:address":"Quellenstrasse 50",
    "sg:city":"Wien",
    "sg:classifiers":[
        {
            "category":"Home & Garden",
            "subcategory":"Household Appliances",
            "type":"Retail Goods"
        }
    ],
    "sg:phone":"+43 1 6042480",
    "sg:postcode":"1100",
    "sg:province":"Wien",
    "sg:tags":[
        "electric"
    ],
    "wof:name":"Wilhelm Blaschka",
    "wof:placetype":"venue"
},
  "geometry": {"coordinates":[16.3798160553,48.1753234863],"type":"Point"}
}