{
  "type": "Feature",
  "properties": {
    "addr:full":"Nr 101 P\u00f6lfing-Brunn Steiermark 8544",
    "addr:postcode":"8544",
    "addr:street":"Nr 101",
    "iso:country":"AT",
    "sg:address":"Nr 101",
    "sg:city":"P\u00f6lfing-Brunn",
    "sg:orig_category":"Raumausstattung",
    "sg:phone":"+43 3465 2537",
    "sg:postcode":"8544",
    "sg:province":"Steiermark",
    "wof:name":"Krainer Alfred",
    "wof:placetype":"venue"
},
  "geometry": {"coordinates":[15.2966852188,46.7287216187],"type":"Point"}
}