{
  "type": "Feature",
  "properties": {
    "iso:country":"AT",
    "sg:address":"Hirmstr",
    "sg:city":"Zemendorf",
    "sg:orig_category":"Fahrsicherheitszentren",
    "sg:phone":"+43 4326 2662596",
    "sg:postcode":"7023",
    "sg:province":"Burgenland",
    "wof:name":"FTZ Fahrtechnik-Zentrum Ost GesmbH",
    "wof:placetype":"venue"
},
  "geometry": {"coordinates":[16.4522590637,47.761844635],"type":"Point"}
}