{
  "type": "Feature",
  "properties": {
    "addr:full":"Gumpendorfer Str 6 Wien Wien 1060",
    "addr:housenumber":"6",
    "addr:postcode":"1060",
    "addr:street":"Str",
    "iso:country":"AT",
    "sg:address":"Gumpendorfer Str 6",
    "sg:city":"Wien",
    "sg:orig_category":"Abfallentsorgung U -Verwertung",
    "sg:phone":"+43 1 58135000",
    "sg:postcode":"1060",
    "sg:province":"Wien",
    "sg:website":"www.aro.at",
    "wof:name":"Altpapier Recycling OrganisationsgesmbH",
    "wof:placetype":"venue"
},
  "geometry": {"coordinates":[16.3617534637,48.2009277344],"type":"Point"}
}