{
  "type": "Feature",
  "properties": {
    "addr:full":"Schulg Dra\u00dfmarkt Burgenland 7372",
    "addr:postcode":"7372",
    "iso:country":"AT",
    "sg:address":"Schulg",
    "sg:city":"Dra\u00dfmarkt",
    "sg:orig_category":"Volksschulen",
    "sg:phone":"+43 2617 2332",
    "sg:postcode":"7372",
    "sg:province":"Burgenland",
    "wof:name":"Volksschule",
    "wof:placetype":"venue"
},
  "geometry": {"coordinates":[-79.06452178959999,41.010345459],"type":"Point"}
}