{
  "type": "Feature",
  "properties": {
    "addr:full":"Landstr 101 Linz Ober\u00f6sterreich 4020",
    "addr:housenumber":"101",
    "addr:postcode":"4020",
    "addr:street":"Landstr",
    "iso:country":"AT",
    "sg:address":"Landstr 101",
    "sg:city":"Linz",
    "sg:orig_category":"Fotoapparate U -Artikel / Einzelhandel",
    "sg:phone":"+43 4373 2663222",
    "sg:postcode":"4020",
    "sg:province":"Ober\u00f6sterreich",
    "wof:name":"Hartlauer HandelsgesmbH",
    "wof:placetype":"venue"
},
  "geometry": {"coordinates":[14.2919616699,48.2968292236],"type":"Point"}
}