{
  "type": "Feature",
  "properties": {
    "iso:country":"AT",
    "sg:address":"Kupferschmiedg 21-23/Halle 7",
    "sg:city":"Gerasdorf",
    "sg:classifiers":[
        {
            "category":"Professional",
            "subcategory":"Art Services",
            "type":"Services"
        }
    ],
    "sg:phone":"+43 4322 4620737",
    "sg:postcode":"2201",
    "sg:province":"Nieder\u00f6sterreich",
    "sg:tags":[
        "designer"
    ],
    "wof:name":"Vitovec Alfred AV-Design",
    "wof:placetype":"venue"
},
  "geometry": {"coordinates":[16.4708862305,48.2990150452],"type":"Point"}
}