{
  "type": "Feature",
  "properties": {
    "addr:full":"Unterreith 31 P\u00f6ndorf Ober\u00f6sterreich 4891",
    "addr:housenumber":"31",
    "addr:postcode":"4891",
    "addr:street":"Unterreith;Oberoesterreich",
    "iso:country":"AT",
    "sg:address":"Unterreith 31",
    "sg:city":"P\u00f6ndorf",
    "sg:orig_category":"Finanz- U Wirtschaftsberatung",
    "sg:phone":"+43 76847608",
    "sg:postcode":"4891",
    "sg:province":"Ober\u00f6sterreich",
    "wof:name":"Gruber Johann",
    "wof:placetype":"venue"
},
  "geometry": {"coordinates":[13.3326320648,47.9923782349],"type":"Point"}
}