{
  "type": "Feature",
  "properties": {
    "addr:full":"Obere Donaul\u00e4nde 105 Linz Ober\u00f6sterreich 4020",
    "addr:housenumber":"105",
    "addr:postcode":"4020",
    "addr:street":"Obere Donaulaende",
    "iso:country":"AT",
    "sg:address":"Obere Donaul\u00e4nde 105",
    "sg:city":"Linz",
    "sg:classifiers":[
        {
            "category":"Travel",
            "subcategory":"Hotels & Motels",
            "type":"Entertainment"
        }
    ],
    "sg:phone":"+43 732 7955660",
    "sg:postcode":"4020",
    "sg:province":"Ober\u00f6sterreich",
    "wof:name":"Donautal Hotel-Restaurant",
    "wof:placetype":"venue"
},
  "geometry": {"coordinates":[14.2667732239,48.3048744202],"type":"Point"}
}