{
  "type": "Feature",
  "properties": {
    "addr:full":"Nr 46 Kottes Nieder\u00f6sterreich 3623",
    "addr:postcode":"3623",
    "addr:street":"Nr;Kottes Niederoesterreich",
    "iso:country":"AT",
    "sg:address":"Nr 46",
    "sg:city":"Kottes",
    "sg:orig_category":"Orgel- U Harmoniumbau",
    "sg:phone":"+43 2873 63520",
    "sg:postcode":"3623",
    "sg:province":"Nieder\u00f6sterreich",
    "wof:name":"Pemmer Josef Diethard",
    "wof:placetype":"venue"
},
  "geometry": {"coordinates":[15.3013572693,48.4425735474],"type":"Point"}
}