{
  "type": "Feature",
  "properties": {
    "addr:full":"Amtshausg 1 Frauenkirchen Burgenland 7132",
    "addr:housenumber":"1",
    "addr:postcode":"7132",
    "addr:street":"Amtshausg",
    "iso:country":"AT",
    "sg:address":"Amtshausg 1",
    "sg:city":"Frauenkirchen",
    "sg:orig_category":"Textilwaren / Einzelhandel",
    "sg:phone":"+43 2172 7170",
    "sg:postcode":"7132",
    "sg:province":"Burgenland",
    "wof:name":"TPS",
    "wof:placetype":"venue"
},
  "geometry": {"coordinates":[16.9262104034,47.8370018005],"type":"Point"}
}