{
  "type": "Feature",
  "properties": {
    "iso:country":"AT",
    "sg:address":"Wolf-Dietrich-G 6",
    "sg:city":"Radstadt",
    "sg:orig_category":"Physiotherapie",
    "sg:phone":"+43 6452 6527",
    "sg:postcode":"5550",
    "sg:province":"Salzburg",
    "wof:name":"Prehal Elfi Dipl-Ass",
    "wof:placetype":"venue"
},
  "geometry": {"coordinates":[13.4622926712,47.3844833374],"type":"Point"}
}