{
  "type": "Feature",
  "properties": {
    "addr:full":"Lindenpl 5 Zwentendorf an der Donau Nieder\u00f6sterreich 3435",
    "addr:housenumber":"5",
    "addr:postcode":"3435",
    "addr:street":"Lindenpl",
    "iso:country":"AT",
    "sg:address":"Lindenpl 5",
    "sg:city":"Zwentendorf an der Donau",
    "sg:orig_category":"Feuerwehren",
    "sg:phone":"+43 2277 2922",
    "sg:postcode":"3435",
    "sg:province":"Nieder\u00f6sterreich",
    "wof:name":"Freiwillige Feuerwehr Zwentendorf a d Donau",
    "wof:placetype":"venue"
},
  "geometry": {"coordinates":[15.9072790146,48.3459434509],"type":"Point"}
}