{
  "type": "Feature",
  "properties": {
    "addr:full":"Bahnhofstr 6a Feldkirch Vorarlberg 6800",
    "addr:housenumber":"6a",
    "addr:postcode":"6800",
    "addr:street":"Bahnhofstr",
    "iso:country":"AT",
    "sg:address":"Bahnhofstr 6a",
    "sg:city":"Feldkirch",
    "sg:orig_category":"Autohandel",
    "sg:phone":"+43 5522 37032",
    "sg:postcode":"6800",
    "sg:province":"Vorarlberg",
    "wof:name":"AUTO IN KFZ Handel GmbH",
    "wof:placetype":"venue"
},
  "geometry": {"coordinates":[9.599609375,47.2396354675],"type":"Point"}
}