{
  "type": "Feature",
  "properties": {
    "iso:country":"AT",
    "sg:address":"Klingerstr 4a",
    "sg:city":"Wien",
    "sg:orig_category":"Fliesen U Platten",
    "sg:phone":"+43 4318 934305",
    "sg:postcode":"1230",
    "sg:province":"Wien",
    "wof:name":"Ofenwelt-Senger",
    "wof:placetype":"venue"
},
  "geometry": {"coordinates":[16.3389530182,48.1486587524],"type":"Point"}
}