{
  "type": "Feature",
  "properties": {
    "addr:full":"Nr 167 Paldau Steiermark 8341",
    "addr:postcode":"8341",
    "addr:street":"Nr",
    "iso:country":"AT",
    "sg:address":"Nr 167",
    "sg:city":"Paldau",
    "sg:orig_category":"Lebensmittel / Einzelhandel",
    "sg:phone":"+43 3150 2233",
    "sg:postcode":"8341",
    "sg:province":"Steiermark",
    "wof:name":"Kaufhaus Renz",
    "wof:placetype":"venue"
},
  "geometry": {"coordinates":[15.7963991165,46.9407424927],"type":"Point"}
}