{
  "type": "Feature",
  "properties": {
    "iso:country":"AT",
    "sg:address":"Liechtensteinstr 101",
    "sg:city":"Wien",
    "sg:orig_category":"Pelze U Pelzwaren",
    "sg:phone":"+43 4313 196958",
    "sg:postcode":"1090",
    "sg:province":"Wien",
    "wof:name":"Pelze Konecky",
    "wof:placetype":"venue"
},
  "geometry": {"coordinates":[16.3560466766,48.2275848389],"type":"Point"}
}