{
  "type": "Feature",
  "properties": {
    "addr:full":"Tiroler Str 17 A-C Lienz Tirol 9900",
    "addr:housenumber":"17 a-c",
    "addr:postcode":"9900",
    "addr:street":"Str;Tirol",
    "iso:country":"AT",
    "sg:address":"Tiroler Str 17 A-C",
    "sg:city":"Lienz",
    "sg:orig_category":"Damenmoden",
    "sg:phone":"+43 4852 71403",
    "sg:postcode":"9900",
    "sg:province":"Tirol",
    "wof:name":"Charles V\u00f6gele (Austria) AG",
    "wof:placetype":"venue"
},
  "geometry": {"coordinates":[12.7684783936,46.8281173706],"type":"Point"}
}