{
  "type": "Feature",
  "properties": {
    "addr:full":"Krankenhausstr 3 Wolfsberg K\u00e4rnten 9400",
    "addr:housenumber":"3;kaernten",
    "addr:postcode":"9400",
    "addr:street":"Krankenhausstr",
    "iso:country":"AT",
    "sg:address":"Krankenhausstr 3",
    "sg:city":"Wolfsberg",
    "sg:orig_category":"Rettungsdienste",
    "sg:phone":"+43 4352 21000",
    "sg:postcode":"9400",
    "sg:province":"K\u00e4rnten",
    "wof:name":"Rotes Kreuz \u00f6sterr Bezirksstelle Wolfsberg",
    "wof:placetype":"venue"
},
  "geometry": {"coordinates":[14.8466672897,46.8321800232],"type":"Point"}
}