{
  "type": "Feature",
  "properties": {
    "iso:country":"AT",
    "sg:address":"Haselbach 23",
    "sg:city":"Altenfelden",
    "sg:orig_category":"Lastkraftwagen",
    "sg:phone":"+43 7282 64950",
    "sg:postcode":"4121",
    "sg:province":"Ober\u00f6sterreich",
    "wof:name":"Truck-Center L Katzinger GmbH",
    "wof:placetype":"venue"
},
  "geometry": {"coordinates":[13.9682264328,48.4974021912],"type":"Point"}
}