{
  "type": "Feature",
  "properties": {
    "iso:country":"AT",
    "sg:address":"Flughafen Wien Schwechat Obj 610/Personal/Shop",
    "sg:city":"Wien",
    "sg:orig_category":"Waren Aller Art",
    "sg:phone":"+43 4317 00762513",
    "sg:postcode":"1300",
    "sg:province":"Wien",
    "wof:name":"TVW Travel Value Wien Betriebs GmbH & Co KG",
    "wof:placetype":"venue"
},
  "geometry": {"coordinates":[16.5561008453,48.1137504578],"type":"Point"}
}