{
  "type": "Feature",
  "properties": {
    "iso:country":"AT",
    "sg:address":"Rittingerstr 7",
    "sg:city":"Bad Ischl",
    "sg:orig_category":"Volkshochschulen",
    "sg:phone":"+43 650 4821939",
    "sg:postcode":"4820",
    "sg:province":"Ober\u00f6sterreich",
    "wof:name":"Volkshochschule Ober\u00f6sterreich gemeinn\u00fctzige Bildungs-GmbH d AK f O\u00d6",
    "wof:placetype":"venue"
},
  "geometry": {"coordinates":[13.6326179504,47.7019767761],"type":"Point"}
}