{
  "type": "Feature",
  "properties": {
    "addr:full":"Sagl 2A Telfs Tirol 6410",
    "addr:housenumber":"2a",
    "addr:postcode":"6410",
    "addr:street":"Sagl;Tirol",
    "iso:country":"AT",
    "sg:address":"Sagl 2A",
    "sg:city":"Telfs",
    "sg:orig_category":"Geschenkartikel",
    "sg:phone":"+43 5262 61480",
    "sg:postcode":"6410",
    "sg:province":"Tirol",
    "wof:name":"Geschenke i Trend - Fa Pflug",
    "wof:placetype":"venue"
},
  "geometry": {"coordinates":[11.0752620697,47.3088188171],"type":"Point"}
}