{
  "type": "Feature",
  "properties": {
    "addr:full":"Wiesenstr 6 Eberstalzell Ober\u00f6sterreich 4653",
    "addr:housenumber":"6",
    "addr:postcode":"4653",
    "addr:street":"Wiesenstr",
    "iso:country":"AT",
    "sg:address":"Wiesenstr 6",
    "sg:city":"Eberstalzell",
    "sg:orig_category":"Musikgruppen",
    "sg:phone":"+43 699 10501000",
    "sg:postcode":"4653",
    "sg:province":"Ober\u00f6sterreich",
    "wof:name":"Mickla Gabriele - Musical & More",
    "wof:placetype":"venue"
},
  "geometry": {"coordinates":[13.9871768951,48.0428619385],"type":"Point"}
}