{
  "type": "Feature",
  "properties": {
    "addr:full":"Hormayrg 39 Wien Wien 1170",
    "addr:housenumber":"39",
    "addr:postcode":"1170",
    "addr:street":"Hormayrg",
    "iso:country":"AT",
    "sg:address":"Hormayrg 39",
    "sg:city":"Wien",
    "sg:orig_category":"Lebensmittel / Einzelhandel",
    "sg:phone":"+43 1 4807759",
    "sg:postcode":"1170",
    "sg:province":"Wien",
    "wof:name":"Guirguis Jadwiga OEG",
    "wof:placetype":"venue"
},
  "geometry": {"coordinates":[16.33203125,48.2224388123],"type":"Point"}
}