{
  "type": "Feature",
  "properties": {
    "iso:country":"AT",
    "sg:address":"Hauptstr 47",
    "sg:city":"Oberpullendorf",
    "sg:orig_category":"Textilwaren / Einzelhandel",
    "sg:phone":"+43 4326 1242292",
    "sg:postcode":"7350",
    "sg:province":"Burgenland",
    "wof:name":"NKD",
    "wof:placetype":"venue"
},
  "geometry": {"coordinates":[16.5063457489,47.4991226196],"type":"Point"}
}