{
  "type": "Feature",
  "properties": {
    "addr:full":"Plenerg 1 Wien Wien 1180",
    "addr:housenumber":"1",
    "addr:postcode":"1180",
    "addr:street":"Plenerg",
    "iso:country":"AT",
    "sg:address":"Plenerg 1",
    "sg:city":"Wien",
    "sg:orig_category":"Lebensmittel / Einzelhandel",
    "sg:phone":"+43 1 9291834",
    "sg:postcode":"1180",
    "sg:province":"Wien",
    "wof:name":"EMMA Otto",
    "wof:placetype":"venue"
},
  "geometry": {"coordinates":[16.3381385803,48.2265281677],"type":"Point"}
}