{
  "type": "Feature",
  "properties": {
    "addr:full":"Schulweg 1 Frohnleiten Steiermark 8130",
    "addr:housenumber":"1",
    "addr:postcode":"8130",
    "addr:street":"Schulweg",
    "iso:country":"AT",
    "sg:address":"Schulweg 1",
    "sg:city":"Frohnleiten",
    "sg:orig_category":"Volksschulen",
    "sg:phone":"+43 3126 2444",
    "sg:postcode":"8130",
    "sg:province":"Steiermark",
    "wof:name":"Volksschule 1",
    "wof:placetype":"venue"
},
  "geometry": {"coordinates":[15.3195409775,47.2691650391],"type":"Point"}
}