{
  "type": "Feature",
  "properties": {
    "addr:full":"Wilhelmstr 50 Wien Wien 1120",
    "addr:housenumber":"50",
    "addr:postcode":"1120",
    "addr:street":"Wilhelmstr",
    "iso:country":"AT",
    "sg:address":"Wilhelmstr 50",
    "sg:city":"Wien",
    "sg:orig_category":"Friseure U Frisiersalons",
    "sg:phone":"+43 1 8150236",
    "sg:postcode":"1120",
    "sg:province":"Wien",
    "wof:name":"Wiche Christa",
    "wof:placetype":"venue"
},
  "geometry": {"coordinates":[16.3328285217,48.1759262085],"type":"Point"}
}