{
  "type": "Feature",
  "properties": {
    "addr:full":"Kugelfangweg 36 Innsbruck Tirol 6020",
    "addr:housenumber":"36",
    "addr:postcode":"6020",
    "addr:street":"Kugelfangweg;Tirol",
    "iso:country":"AT",
    "sg:address":"Kugelfangweg 36",
    "sg:city":"Innsbruck",
    "sg:orig_category":"Handelsagenturen",
    "sg:phone":"+43 512 2065330",
    "sg:postcode":"6020",
    "sg:province":"Tirol",
    "wof:name":"Medwed Georg",
    "wof:placetype":"venue"
},
  "geometry": {"coordinates":[11.4466695786,47.271156311],"type":"Point"}
}