{
  "type": "Feature",
  "properties": {
    "addr:full":"Favoritner Gewerbering 5 Wien Wien 1100",
    "addr:housenumber":"5",
    "addr:postcode":"1100",
    "addr:street":"Favoritner Gewerbering",
    "iso:country":"AT",
    "sg:address":"Favoritner Gewerbering 5",
    "sg:city":"Wien",
    "sg:classifiers":[
        {
            "category":"Industrial Area",
            "type":"Public Place"
        }
    ],
    "sg:phone":"+43 1 6021507",
    "sg:postcode":"1100",
    "sg:province":"Wien",
    "sg:tags":[
        "orbital",
        "welding"
    ],
    "sg:website":"nowotny.co.at",
    "wof:name":"Wolfgang Nowotny Sondermaschinenbau",
    "wof:placetype":"venue"
},
  "geometry": {"coordinates":[16.3772277832,48.165222168],"type":"Point"}
}