{
  "type": "Feature",
  "properties": {
    "addr:full":"Brixentaler Strasse 59 W\u00f6rgl Tirol 6300",
    "addr:housenumber":"59",
    "addr:postcode":"6300",
    "addr:street":"Brixentaler Strasse;Tirol",
    "iso:country":"AT",
    "sg:address":"Brixentaler Strasse 59",
    "sg:city":"W\u00f6rgl",
    "sg:classifiers":[
        {
            "category":"Professional",
            "subcategory":"Art Services",
            "type":"Services"
        }
    ],
    "sg:phone":"+43 5332 732230",
    "sg:postcode":"6300",
    "sg:province":"Tirol",
    "sg:tags":[
        "metalwork"
    ],
    "sg:website":"farthofergmbh.com",
    "wof:name":"Farthofer Schmiede- u. Stahlbauges.m.b.H.",
    "wof:placetype":"venue"
},
  "geometry": {"coordinates":[-69.3131027222,-51.6091995239],"type":"Point"}
}