{
  "type": "Feature",
  "properties": {
    "addr:full":"Emil-Kraft-G 17/7 Baden Nieder\u00f6sterreich 2500",
    "addr:housenumber":"17 / 7",
    "addr:postcode":"2500",
    "addr:street":"Emil-Kraft-G;Niederoesterreich",
    "iso:country":"AT",
    "sg:address":"Emil-Kraft-G 17/7",
    "sg:city":"Baden",
    "sg:orig_category":"Psychotherapie",
    "sg:phone":"+43 2252 81621",
    "sg:postcode":"2500",
    "sg:province":"Nieder\u00f6sterreich",
    "wof:name":"Rodlauer Rosita",
    "wof:placetype":"venue"
},
  "geometry": {"coordinates":[16.2544326782,48.010345459],"type":"Point"}
}