{
  "type": "Feature",
  "properties": {
    "addr:full":"Breinleiten 1 Gm\u00fcnd Nieder\u00f6sterreich 3950",
    "addr:housenumber":"1",
    "addr:postcode":"3950",
    "addr:street":"Breinleiten;Niederoesterreich",
    "iso:country":"AT",
    "sg:address":"Breinleiten 1",
    "sg:city":"Gm\u00fcnd",
    "sg:classifiers":[
        {
            "category":"Building & Trades",
            "subcategory":"Construction",
            "type":"Services"
        }
    ],
    "sg:phone":"+43 2852 52712",
    "sg:postcode":"3950",
    "sg:province":"Nieder\u00f6sterreich",
    "sg:tags":[
        "roofing"
    ],
    "wof:name":"Gerhard Reitter",
    "wof:placetype":"venue"
},
  "geometry": {"coordinates":[14.989279747,48.7849502563],"type":"Point"}
}