{
  "type": "Feature",
  "properties": {
    "addr:full":"Gewerbepark 9 Gramastetten Ober\u00f6sterreich 4201",
    "addr:housenumber":"9",
    "addr:postcode":"4201",
    "addr:street":"Gewerbepark",
    "iso:country":"AT",
    "sg:address":"Gewerbepark 9",
    "sg:city":"Gramastetten",
    "sg:orig_category":"Elektronik",
    "sg:phone":"+43 4372 3975500",
    "sg:postcode":"4201",
    "sg:province":"Ober\u00f6sterreich",
    "wof:name":"REGATRONIC Regel- u Antriebs-Electronic GmbH",
    "wof:placetype":"venue"
},
  "geometry": {"coordinates":[14.2138977051,48.3723068237],"type":"Point"}
}