{
  "type": "Feature",
  "properties": {
    "iso:country":"AT",
    "sg:city":"Eferding",
    "sg:orig_category":"Feuerwehren",
    "sg:phone":"+43 7272 2251",
    "sg:postcode":"4070",
    "sg:province":"Ober\u00f6sterreich",
    "wof:name":"Freiwillige Feuerwehr Hinzenbach",
    "wof:placetype":"venue"
},
  "geometry": {"coordinates":[14.0049600601,48.310344696],"type":"Point"}
}