{
  "type": "Feature",
  "properties": {
    "addr:full":"Nestroystr 46 Ansfelden Ober\u00f6sterreich 4052",
    "addr:housenumber":"46",
    "addr:postcode":"4052",
    "addr:street":"Nestroystr",
    "iso:country":"AT",
    "sg:address":"Nestroystr 46",
    "sg:city":"Ansfelden",
    "sg:orig_category":"Autobusunternehmen",
    "sg:phone":"+43 7229 88438",
    "sg:postcode":"4052",
    "sg:province":"Ober\u00f6sterreich",
    "wof:name":"Welser Wilhelm",
    "wof:placetype":"venue"
},
  "geometry": {"coordinates":[14.290804863,48.2099838257],"type":"Point"}
}