{
  "type": "Feature",
  "properties": {
    "addr:full":"Betriebsstr 7 Wolfsthal Nieder\u00f6sterreich 2412",
    "addr:housenumber":"7",
    "addr:postcode":"2412",
    "addr:street":"Betriebsstr",
    "iso:country":"AT",
    "sg:address":"Betriebsstr 7",
    "sg:city":"Wolfsthal",
    "sg:orig_category":"Autoersatzteile",
    "sg:phone":"+43 2165 633900",
    "sg:postcode":"2412",
    "sg:province":"Nieder\u00f6sterreich",
    "wof:name":"Forstinger Handel und Service GmbH",
    "wof:placetype":"venue"
},
  "geometry": {"coordinates":[17.0261726379,48.1273384094],"type":"Point"}
}