{
  "type": "Feature",
  "properties": {
    "addr:full":"Brandjochstr 3 Innsbruck Tirol 6020",
    "addr:housenumber":"3",
    "addr:postcode":"6020",
    "addr:street":"Brandjochstr;Tirol",
    "iso:country":"AT",
    "sg:address":"Brandjochstr 3",
    "sg:city":"Innsbruck",
    "sg:orig_category":"Unternehmensberatung",
    "sg:phone":"+43 512 285333",
    "sg:postcode":"6020",
    "sg:province":"Tirol",
    "wof:name":"J.A.G. Sportmarketing",
    "wof:placetype":"venue"
},
  "geometry": {"coordinates":[11.3820743561,47.2699394226],"type":"Point"}
}