{
  "type": "Feature",
  "properties": {
    "addr:full":"Au 27 Kremsm\u00fcnster Ober\u00f6sterreich 4550",
    "addr:housenumber":"27",
    "addr:postcode":"4550",
    "addr:street":"Au;Oberoesterreich",
    "iso:country":"AT",
    "sg:address":"Au 27",
    "sg:city":"Kremsm\u00fcnster",
    "sg:orig_category":"Erdarbeiten",
    "sg:phone":"+43 7583 6906",
    "sg:postcode":"4550",
    "sg:province":"Ober\u00f6sterreich",
    "wof:name":"Gnadlinger Christa",
    "wof:placetype":"venue"
},
  "geometry": {"coordinates":[14.1575660706,48.0666236877],"type":"Point"}
}