{
  "type": "Feature",
  "properties": {
    "addr:full":"Gewerbestr 550 Alland Nieder\u00f6sterreich 2534",
    "addr:housenumber":"550;2534",
    "addr:street":"Alland Niederoesterreich",
    "iso:country":"AT",
    "sg:address":"Gewerbestr 550",
    "sg:city":"Alland",
    "sg:orig_category":"Tankstellen",
    "sg:phone":"+43 2258 8912",
    "sg:postcode":"2534",
    "sg:province":"Nieder\u00f6sterreich",
    "wof:name":"OMV Tankstelle",
    "wof:placetype":"venue"
},
  "geometry": {"coordinates":[16.0628623962,48.0671081543],"type":"Point"}
}