{
  "type": "Feature",
  "properties": {
    "addr:full":"Pfeiferg 6 Salzburg Salzburg 5020",
    "addr:housenumber":"6",
    "addr:postcode":"5020",
    "addr:street":"Pfeiferg;Salzburg",
    "iso:country":"AT",
    "sg:address":"Pfeiferg 6",
    "sg:city":"Salzburg",
    "sg:orig_category":"Bauunternehmen",
    "sg:phone":"+43 662 840379",
    "sg:postcode":"5020",
    "sg:province":"Salzburg",
    "wof:name":"Altmann Baugesellschaft mbH",
    "wof:placetype":"venue"
},
  "geometry": {"coordinates":[13.048784256,47.798374176],"type":"Point"}
}