{
  "type": "Feature",
  "properties": {
    "iso:country":"AT",
    "sg:address":"Kesselstr 11",
    "sg:city":"Wolfurt",
    "sg:orig_category":"Installationsunternehmen",
    "sg:phone":"+43 4355 74864860",
    "sg:postcode":"6922",
    "sg:province":"Vorarlberg",
    "wof:name":"Lukas Ing GmbH",
    "wof:placetype":"venue"
},
  "geometry": {"coordinates":[9.745349884,47.4537887573],"type":"Point"}
}