{
  "type": "Feature",
  "properties": {
    "iso:country":"AT",
    "sg:address":"Arthur-Krupp-Str 1",
    "sg:city":"Amstetten",
    "sg:orig_category":"Unternehmensberatung",
    "sg:phone":"+43 4374 7268468",
    "sg:postcode":"3300",
    "sg:province":"Nieder\u00f6sterreich",
    "wof:name":"Feldhofer & Partner Wirtschaftstreuhand GmbH",
    "wof:placetype":"venue"
},
  "geometry": {"coordinates":[14.8950948715,48.1190376282],"type":"Point"}
}