{
  "type": "Feature",
  "properties": {
    "addr:full":"Frauentaler Str 8 Deutschlandsberg Steiermark 8530",
    "addr:housenumber":"8",
    "addr:postcode":"8530",
    "addr:street":"Str",
    "iso:country":"AT",
    "sg:address":"Frauentaler Str 8",
    "sg:city":"Deutschlandsberg",
    "sg:orig_category":"Optiker",
    "sg:phone":"+43 4334 623134",
    "sg:postcode":"8530",
    "sg:province":"Steiermark",
    "wof:name":"Optik Scala GesmbH",
    "wof:placetype":"venue"
},
  "geometry": {"coordinates":[15.2167139053,46.816532135],"type":"Point"}
}