{
  "type": "Feature",
  "properties": {
    "addr:full":"Rudolfstrasse 6 Lustenau Vorarlberg 6890",
    "addr:housenumber":"6",
    "addr:postcode":"6890",
    "addr:street":"Rudolfstrasse",
    "iso:country":"AT",
    "sg:address":"Rudolfstrasse 6",
    "sg:city":"Lustenau",
    "sg:classifiers":[
        {
            "category":"Professional",
            "subcategory":"Advertising",
            "type":"Services"
        }
    ],
    "sg:phone":"+43 5577 85379",
    "sg:postcode":"6890",
    "sg:province":"Vorarlberg",
    "sg:tags":[
        "agency"
    ],
    "sg:website":"hk-werbung.com",
    "wof:name":"H\u00e4mmerle & Kathan Werbeagentur Ges.m.b.H. & Co KG",
    "wof:placetype":"venue"
},
  "geometry": {"coordinates":[9.6511554718,47.4306488037],"type":"Point"}
}