{
  "type": "Feature",
  "properties": {
    "iso:country":"AT",
    "sg:address":"Universit\u00e4tsstr 10/1/7",
    "sg:city":"Wien",
    "sg:classifiers":[
        {
            "category":"Internet Cafe",
            "subcategory":"None",
            "type":"Food & Drink"
        }
    ],
    "sg:phone":"+43 1 4015961",
    "sg:postcode":"1090",
    "sg:province":"Wien",
    "wof:name":"Streams Telecommunicationsservices GesmbH",
    "wof:placetype":"venue"
},
  "geometry": {"coordinates":[16.351474762,48.2234115601],"type":"Point"}
}