{
  "type": "Feature",
  "properties": {
    "iso:country":"AT",
    "sg:address":"Bahnspitz 1",
    "sg:city":"Teesdorf",
    "sg:orig_category":"Hochdruckreinigung",
    "sg:phone":"+43 4322 5381228",
    "sg:postcode":"2524",
    "sg:province":"Nieder\u00f6sterreich",
    "sg:website":"hametner.net",
    "wof:name":"Hametner Gerda",
    "wof:placetype":"venue"
},
  "geometry": {"coordinates":[16.289352417,47.9410057068],"type":"Point"}
}