{
  "type": "Feature",
  "properties": {
    "addr:full":"Wattgasse 31 Wien Wien 1160",
    "addr:housenumber":"31",
    "addr:postcode":"1160",
    "addr:street":"Wattgasse",
    "iso:country":"AT",
    "sg:address":"Wattgasse 31",
    "sg:city":"Wien",
    "sg:orig_category":"Garages, Pre-Fabricated Garages",
    "sg:phone":"+43 1 48533520",
    "sg:postcode":"1160",
    "sg:province":"Wien",
    "sg:website":"kawe.at",
    "wof:name":"KAWE-GARAGE Carl F. Weinberger GmbH",
    "wof:placetype":"venue"
},
  "geometry": {"coordinates":[16.3194141388,48.2165603638],"type":"Point"}
}