{
  "type": "Feature",
  "properties": {
    "addr:full":"Rennweg 23 Innsbruck Tirol 6020",
    "addr:housenumber":"23",
    "addr:postcode":"6020",
    "addr:street":"Rennweg;Tirol",
    "iso:country":"AT",
    "sg:address":"Rennweg 23",
    "sg:city":"Innsbruck",
    "sg:orig_category":"Unternehmensberatung",
    "sg:phone":"+43 512 580010",
    "sg:postcode":"6020",
    "sg:province":"Tirol",
    "wof:name":"IMP-Innovative Management Partner",
    "wof:placetype":"venue"
},
  "geometry": {"coordinates":[11.4007129669,47.2777862549],"type":"Point"}
}