{
  "type": "Feature",
  "properties": {
    "addr:full":"Griesauweg 35  Innsbruck Tirol 6020",
    "addr:housenumber":"35",
    "addr:postcode":"6020",
    "addr:street":"Griesauweg;Tirol",
    "iso:country":"AT",
    "sg:address":"Griesauweg 35 ",
    "sg:city":"Innsbruck",
    "sg:classifiers":[
        {
            "category":"Shopping",
            "subcategory":"Crafts & Fabrics",
            "type":"Retail Goods"
        }
    ],
    "sg:phone":"+43 4351 2334020",
    "sg:postcode":"6020",
    "sg:province":"Tirol",
    "sg:tags":[
        "ceramic"
    ],
    "wof:name":"STEKA WERKE TECHNISCHEKERAMIK GMBH & CO KG",
    "wof:placetype":"venue"
},
  "geometry": {"coordinates":[11.4394741058,47.2687416077],"type":"Point"}
}