{
  "type": "Feature",
  "properties": {
    "iso:country":"AT",
    "sg:address":"Salzburger Str 26",
    "sg:city":"St. Johann in Tirol",
    "sg:orig_category":"Installationsmaterialien",
    "sg:phone":"+43 4353 52647070",
    "sg:postcode":"6380",
    "sg:province":"Tirol",
    "wof:name":"Wolseley Austria AG",
    "wof:placetype":"venue"
},
  "geometry": {"coordinates":[12.4345541,47.5307044983],"type":"Point"}
}