{
  "type": "Feature",
  "properties": {
    "iso:country":"AT",
    "sg:address":"Grazer Str 101",
    "sg:city":"Fernitz",
    "sg:orig_category":"Zelte / Vermietung",
    "sg:phone":"+43 4366 41540115",
    "sg:postcode":"8072",
    "sg:province":"Steiermark",
    "sg:website":"vip-zelte.at",
    "wof:name":"Brunold Philipp",
    "wof:placetype":"venue"
},
  "geometry": {"coordinates":[15.4959154129,46.9819297791],"type":"Point"}
}