{
  "type": "Feature",
  "properties": {
    "addr:full":"Hauptstr 38 Kremsm\u00fcnster Ober\u00f6sterreich 4550",
    "addr:housenumber":"38",
    "addr:postcode":"4550",
    "addr:street":"Hauptstr;Oberoesterreich",
    "iso:country":"AT",
    "sg:address":"Hauptstr 38",
    "sg:city":"Kremsm\u00fcnster",
    "sg:orig_category":"Waren Aller Art",
    "sg:phone":"+43 7583 7919",
    "sg:postcode":"4550",
    "sg:province":"Ober\u00f6sterreich",
    "wof:name":"India Centre",
    "wof:placetype":"venue"
},
  "geometry": {"coordinates":[14.1252908707,48.0516853333],"type":"Point"}
}