{
  "type": "Feature",
  "properties": {
    "addr:full":"Lustenauer Str 125 Hohenems Vorarlberg 6845",
    "addr:housenumber":"125",
    "addr:postcode":"6845",
    "iso:country":"AT",
    "sg:address":"Lustenauer Str 125",
    "sg:city":"Hohenems",
    "sg:orig_category":"Bankomat-Standorte",
    "sg:phone":"+43 5576 766880",
    "sg:postcode":"6845",
    "sg:province":"Vorarlberg",
    "wof:name":"Bankomat d Raiffeisenbank Hohenems",
    "wof:placetype":"venue"
},
  "geometry": {"coordinates":[9.6773166656,47.3741188049],"type":"Point"}
}