{
  "type": "Feature",
  "properties": {
    "addr:full":"Paulanerg 6 Wien Wien 1040",
    "addr:housenumber":"6",
    "addr:postcode":"1040",
    "addr:street":"Paulanerg",
    "iso:country":"AT",
    "sg:address":"Paulanerg 6",
    "sg:city":"Wien",
    "sg:orig_category":"Non-Classified Establishments",
    "sg:phone":"+43 1 50521710",
    "sg:postcode":"1040",
    "sg:province":"Wien",
    "wof:name":"Pfarramt Wieden zu den hl Schutzengeln",
    "wof:placetype":"venue"
},
  "geometry": {"coordinates":[16.3675098419,48.1959762573],"type":"Point"}
}