{
  "type": "Feature",
  "properties": {
    "addr:full":"Afritschg 55 Wien Wien 1220",
    "addr:housenumber":"55",
    "addr:postcode":"1220",
    "addr:street":"Afritschg",
    "iso:country":"AT",
    "sg:address":"Afritschg 55",
    "sg:city":"Wien",
    "sg:orig_category":"Ballettschulen",
    "sg:phone":"+43 664 3246847",
    "sg:postcode":"1220",
    "sg:province":"Wien",
    "wof:name":"Fantasia Kindertanzstudio",
    "wof:placetype":"venue"
},
  "geometry": {"coordinates":[16.4500999451,48.2454948425],"type":"Point"}
}