{
  "type": "Feature",
  "properties": {
    "iso:country":"AT",
    "sg:address":"Bahnhofstr 5",
    "sg:city":"Haag",
    "sg:orig_category":"Damenmoden",
    "sg:phone":"+43 7434 43957",
    "sg:postcode":"3350",
    "sg:province":"Nieder\u00f6sterreich",
    "wof:name":"Sch\u00f6llhammer Peter",
    "wof:placetype":"venue"
},
  "geometry": {"coordinates":[14.5746603012,48.1028213501],"type":"Point"}
}