{
  "type": "Feature",
  "properties": {
    "addr:full":"Piaristeng 1/13 Wien Wien 1080",
    "addr:housenumber":"1 / 13",
    "addr:postcode":"1080",
    "addr:street":"Piaristeng",
    "iso:country":"AT",
    "sg:address":"Piaristeng 1/13",
    "sg:city":"Wien",
    "sg:orig_category":"Architekten",
    "sg:phone":"+43 4314 099283",
    "sg:postcode":"1080",
    "sg:province":"Wien",
    "wof:name":"Fornezzi Ronald Dipl-Ing",
    "wof:placetype":"venue"
},
  "geometry": {"coordinates":[16.3511352539,48.2064743042],"type":"Point"}
}