{
  "type": "Feature",
  "properties": {
    "addr:full":"Wiener Str 1 Ebreichsdorf Nieder\u00f6sterreich 2483",
    "addr:housenumber":"1",
    "addr:postcode":"2483",
    "iso:country":"AT",
    "sg:address":"Wiener Str 1",
    "sg:city":"Ebreichsdorf",
    "sg:orig_category":"Elektroinstallationsunternehmen",
    "sg:phone":"+43 2254 72249",
    "sg:postcode":"2483",
    "sg:province":"Nieder\u00f6sterreich",
    "wof:name":"Vlasta W Ing GesmbH",
    "wof:placetype":"venue"
},
  "geometry": {"coordinates":[16.4022502899,47.9636497498],"type":"Point"}
}