{
  "type": "Feature",
  "properties": {
    "addr:full":"Belruptstr 17 Bregenz Vorarlberg 6900",
    "addr:housenumber":"17",
    "addr:postcode":"6900",
    "addr:street":"Belruptstr",
    "iso:country":"AT",
    "sg:address":"Belruptstr 17",
    "sg:city":"Bregenz",
    "sg:orig_category":"Bestattungsunternehmen",
    "sg:phone":"+43 5574 42784",
    "sg:postcode":"6900",
    "sg:province":"Vorarlberg",
    "wof:name":"H\u00e4mmerle N GesmbH",
    "wof:placetype":"venue"
},
  "geometry": {"coordinates":[9.7503728867,47.5036582947],"type":"Point"}
}