{
  "type": "Feature",
  "properties": {
    "addr:full":"Naglerg 60 Graz Steiermark 8010",
    "addr:housenumber":"60",
    "addr:postcode":"8010",
    "addr:street":"Naglerg",
    "iso:country":"AT",
    "sg:address":"Naglerg 60",
    "sg:city":"Graz",
    "sg:classifiers":[
        {
            "category":"Restaurant",
            "type":"Food & Drink"
        }
    ],
    "sg:phone":"+43 4331 6846281",
    "sg:postcode":"8010",
    "sg:province":"Steiermark",
    "wof:name":"Konservierung u Restaurierung von Wandmalereien Hubert Schwarz",
    "wof:placetype":"venue"
},
  "geometry": {"coordinates":[15.4566926956,47.067653656],"type":"Point"}
}