{
  "type": "Feature",
  "properties": {
    "addr:full":"Harrachg 21 Graz Steiermark 8010",
    "addr:housenumber":"21",
    "addr:postcode":"8010",
    "addr:street":"Harrachg",
    "iso:country":"AT",
    "sg:address":"Harrachg 21",
    "sg:city":"Graz",
    "sg:orig_category":"Institute",
    "sg:phone":"+43 316 3804200",
    "sg:postcode":"8010",
    "sg:province":"Steiermark",
    "wof:name":"Inst f Medizinische Biochemie Karl Franzens Universit\u00e4t",
    "wof:placetype":"venue"
},
  "geometry": {"coordinates":[15.4475736618,47.0770988464],"type":"Point"}
}