{
  "type": "Feature",
  "properties": {
    "addr:full":"Am Damm 4 Haid Ober\u00f6sterreich 4053",
    "addr:housenumber":"4",
    "addr:postcode":"4053",
    "addr:street":"Am Damm",
    "iso:country":"AT",
    "sg:address":"Am Damm 4",
    "sg:city":"Haid",
    "sg:classifiers":[
        {
            "category":"Professional",
            "subcategory":"Engineering",
            "type":"Services"
        }
    ],
    "sg:phone":"+43 4372 29875860",
    "sg:postcode":"4053",
    "sg:province":"Ober\u00f6sterreich",
    "sg:tags":[
        "machine",
        "-",
        "mechanical"
    ],
    "wof:name":"K\u00d6LLER & LUSENBERGER GES.MBH",
    "wof:placetype":"venue"
},
  "geometry": {"coordinates":[14.2373685837,48.1676254272],"type":"Point"}
}