{
  "type": "Feature",
  "properties": {
    "addr:full":"Stappitz 120 Mallnitz K\u00e4rnten 9822",
    "addr:housenumber":"120",
    "addr:postcode":"9822",
    "addr:street":"Stappitz;Kaernten",
    "iso:country":"AT",
    "sg:address":"Stappitz 120",
    "sg:city":"Mallnitz",
    "sg:orig_category":"Pensionen / Privatzimmer",
    "sg:phone":"+43 4784 3700",
    "sg:postcode":"9822",
    "sg:province":"K\u00e4rnten",
    "wof:name":"Pension J\u00e4gerhof",
    "wof:placetype":"venue"
},
  "geometry": {"coordinates":[13.1797780991,46.9743995667],"type":"Point"}
}