{
  "type": "Feature",
  "properties": {
    "iso:country":"AT",
    "sg:address":"Dr A Sch\u00e4rf-Str 8-10",
    "sg:city":"Wiener Neustadt",
    "sg:orig_category":"Maschinenbau",
    "sg:phone":"+43 2622 223810",
    "sg:postcode":"2700",
    "sg:province":"Nieder\u00f6sterreich",
    "wof:name":"Nemetz Gebr\u00fcder Maschinenbau GesmbH",
    "wof:placetype":"venue"
},
  "geometry": {"coordinates":[16.2420711517,47.8385238647],"type":"Point"}
}