{
  "type": "Feature",
  "properties": {
    "iso:country":"AT",
    "sg:address":"Mariatroster Str 41",
    "sg:city":"Kroisbach",
    "sg:orig_category":"Immobilienverwaltungen",
    "sg:phone":"+43 316 3225670",
    "sg:postcode":"8043",
    "sg:province":"Steiermark",
    "wof:name":"Grach Dieter",
    "wof:placetype":"venue"
},
  "geometry": {"coordinates":[15.4598073959,47.090927124],"type":"Point"}
}