{
  "type": "Feature",
  "properties": {
    "iso:country":"AT",
    "sg:address":"Hauptstr 45",
    "sg:city":"Radenthein",
    "sg:orig_category":"Kontaktlinsenoptiker",
    "sg:phone":"+43 4246 2168",
    "sg:postcode":"9545",
    "sg:province":"K\u00e4rnten",
    "wof:name":"Kontaktlinsenstudio K\u00f6le",
    "wof:placetype":"venue"
},
  "geometry": {"coordinates":[13.7032775879,46.8004341125],"type":"Point"}
}