{
  "type": "Feature",
  "properties": {
    "addr:full":"Leutascher Str 485 Seefeld in Tirol Tirol 6100",
    "addr:housenumber":"485",
    "addr:postcode":"6100",
    "addr:street":"Seefeld;Tirol",
    "iso:country":"AT",
    "sg:address":"Leutascher Str 485",
    "sg:city":"Seefeld in Tirol",
    "sg:classifiers":[
        {
            "category":"Travel",
            "subcategory":"Hotels & Motels",
            "type":"Entertainment"
        }
    ],
    "sg:phone":"+43 5212 30300",
    "sg:postcode":"6100",
    "sg:province":"Tirol",
    "wof:name":"Hotel Metropol",
    "wof:placetype":"venue"
},
  "geometry": {"coordinates":[11.1787643433,47.3372306824],"type":"Point"}
}