{
  "type": "Feature",
  "properties": {
    "addr:full":"Tausing 29 Liezen Steiermark 8940",
    "addr:housenumber":"29",
    "addr:postcode":"8940",
    "addr:street":"Tausing",
    "iso:country":"AT",
    "sg:address":"Tausing 29",
    "sg:city":"Liezen",
    "sg:orig_category":"Gie\u00c3\u0178ereieinrichtungen U -Bedarf",
    "sg:phone":"+43 3612 25724",
    "sg:postcode":"8940",
    "sg:province":"Steiermark",
    "wof:name":"WAS Trading und HandelsgesmbH",
    "wof:placetype":"venue"
},
  "geometry": {"coordinates":[14.2303247452,47.570728302],"type":"Point"}
}