{
  "type": "Feature",
  "properties": {
    "addr:full":"Treitlstr 3 Wien Wien 1040",
    "addr:housenumber":"3",
    "addr:postcode":"1040",
    "addr:street":"Treitlstr",
    "iso:country":"AT",
    "sg:address":"Treitlstr 3",
    "sg:city":"Wien",
    "sg:orig_category":"Forschungsinstitute",
    "sg:phone":"+43 1 5852300",
    "sg:postcode":"1040",
    "sg:province":"Wien",
    "wof:name":"Forschungsgesellschaft f Informatik FGI",
    "wof:placetype":"venue"
},
  "geometry": {"coordinates":[16.3671875,48.1997146606],"type":"Point"}
}