{
  "type": "Feature",
  "properties": {
    "addr:full":"Hauptstr 42A Gloggnitz Nieder\u00f6sterreich 2640",
    "addr:housenumber":"42a",
    "addr:postcode":"2640",
    "addr:street":"Hauptstr",
    "iso:country":"AT",
    "sg:address":"Hauptstr 42A",
    "sg:city":"Gloggnitz",
    "sg:orig_category":"Fu\u00c3\u0178pflege U Fu\u00c3\u0178pflegesalons",
    "sg:phone":"+43 4326 6242333",
    "sg:postcode":"2640",
    "sg:province":"Nieder\u00f6sterreich",
    "wof:name":"Fu\u00dfpflege & Kosmetik Studio Karin",
    "wof:placetype":"venue"
},
  "geometry": {"coordinates":[15.9330682755,47.675163269],"type":"Point"}
}