{
  "type": "Feature",
  "properties": {
    "addr:full":"Nr 183 Reichersberg Ober\u00f6sterreich 4981",
    "addr:postcode":"4981",
    "addr:street":"Nr 183",
    "iso:country":"AT",
    "sg:address":"Nr 183",
    "sg:city":"Reichersberg",
    "sg:orig_category":"Tischlereien",
    "sg:phone":"+43 4377 583644",
    "sg:postcode":"4981",
    "sg:province":"Ober\u00f6sterreich",
    "wof:name":"Lechner Walter Bau- u M\u00f6beltischlerei",
    "wof:placetype":"venue"
},
  "geometry": {"coordinates":[13.3593406677,48.3358459473],"type":"Point"}
}