{
  "type": "Feature",
  "properties": {
    "addr:full":"Robert-Fuchs-G 6 Wien Wien 1140",
    "addr:housenumber":"6",
    "addr:postcode":"1140",
    "addr:street":"Robert-Fuchs-G",
    "iso:country":"AT",
    "sg:address":"Robert-Fuchs-G 6",
    "sg:city":"Wien",
    "sg:orig_category":"Physiotherapie",
    "sg:phone":"+43 1 9798841",
    "sg:postcode":"1140",
    "sg:province":"Wien",
    "wof:name":"Kie\u00dfling Helga Dipl PT - Hausbesuche",
    "wof:placetype":"venue"
},
  "geometry": {"coordinates":[16.2428417206,48.2111206055],"type":"Point"}
}