{
  "type": "Feature",
  "properties": {
    "iso:country":"AT",
    "sg:address":"Hauptstr 11",
    "sg:city":"M\u00f6llbr\u00fccke",
    "sg:orig_category":"Installationsunternehmen",
    "sg:phone":"+43 4769 33289",
    "sg:postcode":"9813",
    "sg:province":"K\u00e4rnten",
    "wof:name":"Rothleitner Walter",
    "wof:placetype":"venue"
},
  "geometry": {"coordinates":[13.3698091507,46.8365135193],"type":"Point"}
}