{
  "type": "Feature",
  "properties": {
    "addr:full":"Radegunder Str 23 Kumberg Steiermark 8062",
    "addr:housenumber":"23",
    "addr:postcode":"8062",
    "addr:street":"Str",
    "iso:country":"AT",
    "sg:address":"Radegunder Str 23",
    "sg:city":"Kumberg",
    "sg:orig_category":"Parkettbodenverlegung",
    "sg:phone":"+43 3132 3960",
    "sg:postcode":"8062",
    "sg:province":"Steiermark",
    "wof:name":"Pfeifer Erich",
    "wof:placetype":"venue"
},
  "geometry": {"coordinates":[15.5345201492,47.1602363586],"type":"Point"}
}