{
  "type": "Feature",
  "properties": {
    "addr:full":"Gr\u00fcnental 7 Kleinzell im M\u00fchlkreis Ober\u00f6sterreich 4115",
    "addr:housenumber":"7",
    "addr:postcode":"4115",
    "addr:street":"Gruenental;Oberoesterreich",
    "iso:country":"AT",
    "sg:address":"Gr\u00fcnental 7",
    "sg:city":"Kleinzell im M\u00fchlkreis",
    "sg:classifiers":[
        {
            "category":"Taxi",
            "type":"Transportation"
        }
    ],
    "sg:phone":"+43 4372 825156",
    "sg:postcode":"4115",
    "sg:province":"Ober\u00f6sterreich",
    "sg:tags":[
        "personentransporte",
        "u"
    ],
    "wof:name":"Wolfmeir Josef",
    "wof:placetype":"venue"
},
  "geometry": {"coordinates":[13.9926204681,48.4571800232],"type":"Point"}
}