{
  "type": "Feature",
  "properties": {
    "addr:full":"Lugendorf 31 Sallingberg Nieder\u00f6sterreich 3525",
    "addr:housenumber":"31",
    "addr:postcode":"3525",
    "addr:street":"Lugendorf;Niederoesterreich",
    "iso:country":"AT",
    "sg:address":"Lugendorf 31",
    "sg:city":"Sallingberg",
    "sg:classifiers":[
        {
            "category":"Manufacturing",
            "subcategory":"Wood Products",
            "type":"Manufacturing & Wholesale Goods"
        }
    ],
    "sg:phone":"+43 2875 8265",
    "sg:postcode":"3525",
    "sg:province":"Nieder\u00f6sterreich",
    "sg:tags":[
        "lumber"
    ],
    "wof:name":"S\u00e4gewerk Bernhard GmbH",
    "wof:placetype":"venue"
},
  "geometry": {"coordinates":[15.2004852295,48.4672851562],"type":"Point"}
}