{
  "type": "Feature",
  "properties": {
    "addr:full":"Endach 30 Kufstein Tirol 6330",
    "addr:housenumber":"30",
    "addr:postcode":"6330",
    "addr:street":"Endach;Tirol",
    "iso:country":"AT",
    "sg:address":"Endach 30",
    "sg:city":"Kufstein",
    "sg:orig_category":"Transportunternehmen",
    "sg:phone":"+43 5372 63626",
    "sg:postcode":"6330",
    "sg:province":"Tirol",
    "wof:name":"CST Transport GmbH",
    "wof:placetype":"venue"
},
  "geometry": {"coordinates":[12.1515321732,47.5662307739],"type":"Point"}
}