{
  "type": "Feature",
  "properties": {
    "iso:country":"AT",
    "sg:address":"Utzeneck 5",
    "sg:city":"Maria Schmolln",
    "sg:orig_category":"Betriebseinrichtungen",
    "sg:phone":"+43 4377 4320050",
    "sg:postcode":"5241",
    "sg:province":"Ober\u00f6sterreich",
    "wof:name":"Kind-Ladenbau-GesmbH - Betriebs- und B\u00fcroeinrichtungen",
    "wof:placetype":"venue"
},
  "geometry": {"coordinates":[13.2180109024,48.1389541626],"type":"Point"}
}