{
  "type": "Feature",
  "properties": {
    "addr:full":"Siebenbrunneng 21 Wien Wien 1050",
    "addr:housenumber":"21",
    "addr:postcode":"1050",
    "addr:street":"Siebenbrunneng",
    "iso:country":"AT",
    "sg:address":"Siebenbrunneng 21",
    "sg:city":"Wien",
    "sg:orig_category":"Architekten",
    "sg:phone":"+43 1 54446180",
    "sg:postcode":"1050",
    "sg:province":"Wien",
    "wof:name":"Zehethofer Gerhard Arch Dipl-Ing",
    "wof:placetype":"venue"
},
  "geometry": {"coordinates":[16.3586845398,48.1871795654],"type":"Point"}
}