{
  "type": "Feature",
  "properties": {
    "addr:full":"Gentzg 122/Top 12 Wien Wien 1180",
    "addr:housenumber":"122 / top 12",
    "addr:postcode":"1180",
    "iso:country":"AT",
    "sg:address":"Gentzg 122/Top 12",
    "sg:city":"Wien",
    "sg:orig_category":"Institute",
    "sg:phone":"+43 1 9575258",
    "sg:postcode":"1180",
    "sg:province":"Wien",
    "wof:name":"Pesendorfer Bernhard Dr - Institut f angewandte Philosophie",
    "wof:placetype":"venue"
},
  "geometry": {"coordinates":[16.3445625305,48.2262420654],"type":"Point"}
}