{
  "type": "Feature",
  "properties": {
    "addr:full":"Baumannstr 4 Wien Wien 1030",
    "addr:housenumber":"4",
    "addr:postcode":"1030",
    "addr:street":"Baumannstr",
    "iso:country":"AT",
    "sg:address":"Baumannstr 4",
    "sg:city":"Wien",
    "sg:orig_category":"Internationale Organisationen",
    "sg:phone":"+43 1 7130751",
    "sg:postcode":"1030",
    "sg:province":"Wien",
    "wof:name":"Jaeri Wien Office",
    "wof:placetype":"venue"
},
  "geometry": {"coordinates":[16.3868141174,48.2040977478],"type":"Point"}
}