{
  "type": "Feature",
  "properties": {
    "addr:full":"Waagner-Biro-Strasse 11 Graz Steiermark 8020",
    "addr:housenumber":"11",
    "addr:postcode":"8020",
    "addr:street":"Waagner-Biro-Strasse",
    "iso:country":"AT",
    "sg:address":"Waagner-Biro-Strasse 11",
    "sg:city":"Graz",
    "sg:classifiers":[
        {
            "category":"Education",
            "subcategory":"Special Training",
            "type":"Public Place"
        }
    ],
    "sg:phone":"+43 316 5815040",
    "sg:postcode":"8020",
    "sg:province":"Steiermark",
    "sg:tags":[
        "steel",
        "aluminium",
        "stainless",
        "material",
        "part",
        "cnc",
        "milled"
    ],
    "sg:website":"ferrotechnik.co.at",
    "wof:name":"Ferrotechnik G.m.b.H.",
    "wof:placetype":"venue"
},
  "geometry": {"coordinates":[15.4142408371,47.071937561],"type":"Point"}
}