{
  "type": "Feature",
  "properties": {
    "addr:full":"Loferer Bundesstr 20 Zell am See Salzburg 5700",
    "addr:housenumber":"20",
    "addr:postcode":"5700",
    "addr:street":"Salzburg",
    "iso:country":"AT",
    "sg:address":"Loferer Bundesstr 20",
    "sg:city":"Zell am See",
    "sg:orig_category":"Installationsunternehmen",
    "sg:phone":"+43 6542 723350",
    "sg:postcode":"5700",
    "sg:province":"Salzburg",
    "wof:name":"Vogl Hermann GesmbH & Co KG",
    "wof:placetype":"venue"
},
  "geometry": {"coordinates":[12.7967529297,47.3260383606],"type":"Point"}
}