{
  "type": "Feature",
  "properties": {
    "iso:country":"AT",
    "sg:address":"Grazer Str 28",
    "sg:city":"Murau",
    "sg:orig_category":"Unterhaltungselektronik / Einzelhandel",
    "sg:phone":"+43 4335 322531",
    "sg:postcode":"8850",
    "sg:province":"Steiermark",
    "wof:name":"Expert Karner Inh Matthias Degold",
    "wof:placetype":"venue"
},
  "geometry": {"coordinates":[14.1789684296,47.1118927002],"type":"Point"}
}