{
  "type": "Feature",
  "properties": {
    "addr:full":"Markt 39 Werfen Salzburg 5450",
    "addr:housenumber":"39",
    "addr:postcode":"5450",
    "addr:street":"Markt;Salzburg",
    "iso:country":"AT",
    "sg:address":"Markt 39",
    "sg:city":"Werfen",
    "sg:classifiers":[
        {
            "category":"Restaurant",
            "type":"Food & Drink"
        }
    ],
    "sg:phone":"+43 6468 7607",
    "sg:postcode":"5450",
    "sg:province":"Salzburg",
    "sg:tags":[
        "pizzeria"
    ],
    "wof:name":"Bella Grotta Pizzeria Ristorante",
    "wof:placetype":"venue"
},
  "geometry": {"coordinates":[13.1898126602,47.4761009216],"type":"Point"}
}