{
  "type": "Feature",
  "properties": {
    "iso:country":"AT",
    "sg:address":"Alte Bundesstr 14",
    "sg:city":"Haiming",
    "sg:orig_category":"Bars-Cafes",
    "sg:phone":"+43 5266 88329",
    "sg:postcode":"6425",
    "sg:province":"Tirol",
    "wof:name":"Cafe Alt-Haiming",
    "wof:placetype":"venue"
},
  "geometry": {"coordinates":[10.8843755722,47.2577514648],"type":"Point"}
}