{
  "type": "Feature",
  "properties": {
    "addr:full":"Dammstr 4 G\u00fcssing Burgenland 7540",
    "addr:housenumber":"4",
    "addr:postcode":"7540",
    "addr:street":"Dammstr",
    "iso:country":"AT",
    "sg:address":"Dammstr 4",
    "sg:city":"G\u00fcssing",
    "sg:orig_category":"Raumausstattung",
    "sg:phone":"+43 3322 42281",
    "sg:postcode":"7540",
    "sg:province":"Burgenland",
    "wof:name":"Weinhofer Raumausstattung",
    "wof:placetype":"venue"
},
  "geometry": {"coordinates":[16.3264312744,47.0602149963],"type":"Point"}
}