{
  "type": "Feature",
  "properties": {
    "addr:full":"Halleiner Landesstr 3 Hallein Salzburg 5400",
    "addr:housenumber":"3",
    "addr:postcode":"5400",
    "addr:street":"Landesstr;Salzburg",
    "iso:country":"AT",
    "sg:address":"Halleiner Landesstr 3",
    "sg:city":"Hallein",
    "sg:orig_category":"Autohandel",
    "sg:phone":"+43 6245 81139",
    "sg:postcode":"5400",
    "sg:province":"Salzburg",
    "wof:name":"Wei\u00dfenbacher Manuela",
    "wof:placetype":"venue"
},
  "geometry": {"coordinates":[13.101143837,47.6853942871],"type":"Point"}
}