{
  "type": "Feature",
  "properties": {
    "addr:full":"Herbert-B\u00f6ckl-G 20 Liebenau Steiermark 8041",
    "addr:housenumber":"20",
    "addr:postcode":"8041",
    "addr:street":"Herbert-Boeckl-G",
    "iso:country":"AT",
    "sg:address":"Herbert-B\u00f6ckl-G 20",
    "sg:city":"Liebenau",
    "sg:orig_category":"Handelsagenturen",
    "sg:phone":"+43 316 426828",
    "sg:postcode":"8041",
    "sg:province":"Steiermark",
    "wof:name":"Koroschetz Erich",
    "wof:placetype":"venue"
},
  "geometry": {"coordinates":[15.4671764374,47.0340538025],"type":"Point"}
}