{
  "type": "Feature",
  "properties": {
    "addr:full":"Annenstr 57 Graz Steiermark 8020",
    "addr:housenumber":"57",
    "addr:postcode":"8020",
    "addr:street":"Annenstr",
    "iso:country":"AT",
    "sg:address":"Annenstr 57",
    "sg:city":"Graz",
    "sg:orig_category":"Personalbereitstellung",
    "sg:phone":"+43 316 723546",
    "sg:postcode":"8020",
    "sg:province":"Steiermark",
    "wof:name":"TTI Personaldienstleistung GmbH",
    "wof:placetype":"venue"
},
  "geometry": {"coordinates":[15.4220018387,47.0712165833],"type":"Point"}
}