{
  "type": "Feature",
  "properties": {
    "addr:full":"Nr 40 Unterpremst\u00e4tten Steiermark 8141",
    "addr:postcode":"8141",
    "addr:street":"Nr 40 Unterpremstaetten Steiermark",
    "iso:country":"AT",
    "sg:address":"Nr 40",
    "sg:city":"Unterpremst\u00e4tten",
    "sg:orig_category":"Pensionen / Privatzimmer",
    "sg:phone":"+43 4331 35537540",
    "sg:postcode":"8141",
    "sg:province":"Steiermark",
    "wof:name":"Pension Am Schachenwald GesmbH",
    "wof:placetype":"venue"
},
  "geometry": {"coordinates":[166.9221496582,-0.5282999873],"type":"Point"}
}