{
  "type": "Feature",
  "properties": {
    "addr:full":"Andreas-Hofer-Str 11 Innsbruck Tirol 6020",
    "addr:housenumber":"11",
    "addr:postcode":"6020",
    "addr:street":"Andreas-Hofer-Str;Tirol",
    "iso:country":"AT",
    "sg:address":"Andreas-Hofer-Str 11",
    "sg:city":"Innsbruck",
    "sg:orig_category":"Spirituosen / Erzeugung U Gro\u00c3\u0178handel",
    "sg:phone":"+43 4351 25883116",
    "sg:postcode":"6020",
    "sg:province":"Tirol",
    "wof:name":"Lauda A Destillerie u Getr\u00e4nkehandel GesmbH & Co KG",
    "wof:placetype":"venue"
},
  "geometry": {"coordinates":[11.391784668,47.2610855103],"type":"Point"}
}