{
  "type": "Feature",
  "properties": {
    "addr:full":"Platz 45 Bezau Vorarlberg 6870",
    "addr:housenumber":"45",
    "addr:postcode":"6870",
    "addr:street":"Platz",
    "iso:country":"AT",
    "sg:address":"Platz 45",
    "sg:city":"Bezau",
    "sg:orig_category":"Volksschulen",
    "sg:phone":"+43 5514 2379",
    "sg:postcode":"6870",
    "sg:province":"Vorarlberg",
    "wof:name":"Volksschule",
    "wof:placetype":"venue"
},
  "geometry": {"coordinates":[9.9022083282,47.3848991394],"type":"Point"}
}