{
  "type": "Feature",
  "properties": {
    "addr:full":"H\u00f6henstr 2 Bischofstetten Nieder\u00f6sterreich 3232",
    "addr:housenumber":"2",
    "addr:postcode":"3232",
    "addr:street":"Hoehenstr;Niederoesterreich",
    "iso:country":"AT",
    "sg:address":"H\u00f6henstr 2",
    "sg:city":"Bischofstetten",
    "sg:orig_category":"Schlossereien",
    "sg:phone":"+43 4327 4882580",
    "sg:postcode":"3232",
    "sg:province":"Nieder\u00f6sterreich",
    "wof:name":"S-&-W Schlosserei u Pulverbeschichtungs GmbH",
    "wof:placetype":"venue"
},
  "geometry": {"coordinates":[15.4644804001,48.1201400757],"type":"Point"}
}