{
  "type": "Feature",
  "properties": {
    "iso:country":"AT",
    "sg:address":"Dorfstr 91",
    "sg:city":"St. Anton am Arlberg",
    "sg:classifiers":[
        {
            "category":"Travel",
            "subcategory":"Hotels & Motels",
            "type":"Entertainment"
        }
    ],
    "sg:phone":"+43 5446 3601",
    "sg:postcode":"6580",
    "sg:province":"Tirol",
    "wof:name":"Hotel Senn garni",
    "wof:placetype":"venue"
},
  "geometry": {"coordinates":[10.2720327377,47.1335334778],"type":"Point"}
}