{
  "type": "Feature",
  "properties": {
    "iso:country":"AT",
    "sg:address":"Sch\u00f6nauer Str. 5",
    "sg:city":"Steyr",
    "sg:classifiers":[
        {
            "category":"Autos & Motor Vehicles",
            "subcategory":"Automobile Sales",
            "type":"Retail Goods"
        }
    ],
    "sg:phone":"+43 4372 5258500",
    "sg:postcode":"4400",
    "sg:province":"Ober\u00f6sterreich",
    "sg:tags":[
        "industrial"
    ],
    "wof:name":"MAN STEYR AG",
    "wof:placetype":"venue"
},
  "geometry": {"coordinates":[14.4279384613,48.0398521423],"type":"Point"}
}