{
  "type": "Feature",
  "properties": {
    "addr:full":"Industriestr 39 Lannach Steiermark 8502",
    "addr:housenumber":"39",
    "addr:postcode":"8502",
    "addr:street":"Industriestr",
    "iso:country":"AT",
    "sg:address":"Industriestr 39",
    "sg:city":"Lannach",
    "sg:orig_category":"Schrott",
    "sg:phone":"+43 3136 81640",
    "sg:postcode":"8502",
    "sg:province":"Steiermark",
    "wof:name":"Schweiger Helmut GmbH",
    "wof:placetype":"venue"
},
  "geometry": {"coordinates":[15.3352937698,46.9621315002],"type":"Point"}
}