{
  "type": "Feature",
  "properties": {
    "iso:country":"AT",
    "sg:address":"Hauptstr 87",
    "sg:city":"Stixneusiedl",
    "sg:classifiers":[
        {
            "category":"Travel",
            "subcategory":"Hotels & Motels",
            "type":"Entertainment"
        }
    ],
    "sg:phone":"+43 2230 28580",
    "sg:postcode":"2463",
    "sg:province":"Nieder\u00f6sterreich",
    "wof:name":"Hotel-Restaurant Muhr",
    "wof:placetype":"venue"
},
  "geometry": {"coordinates":[16.6462974548,48.053150177],"type":"Point"}
}