{
  "type": "Feature",
  "properties": {
    "addr:full":"L\u00e4rchenstr 46 Wels Ober\u00f6sterreich 4600",
    "addr:housenumber":"46",
    "addr:postcode":"4600",
    "addr:street":"Laerchenstr;Oberoesterreich",
    "iso:country":"AT",
    "sg:address":"L\u00e4rchenstr 46",
    "sg:city":"Wels",
    "sg:orig_category":"Bauleitung U -Betreuung",
    "sg:phone":"+43 4372 4246978",
    "sg:postcode":"4600",
    "sg:province":"Ober\u00f6sterreich",
    "wof:name":"Randacher Andreas - Dienstleistung im Baugewerbe",
    "wof:placetype":"venue"
},
  "geometry": {"coordinates":[14.0007953644,48.1447372437],"type":"Point"}
}