{
  "type": "Feature",
  "properties": {
    "addr:full":"Moosbachrotte 6 Freiland Nieder\u00f6sterreich 3183",
    "addr:housenumber":"6",
    "addr:postcode":"3183",
    "addr:street":"Moosbachrotte;Niederoesterreich",
    "iso:country":"AT",
    "sg:address":"Moosbachrotte 6",
    "sg:city":"Freiland",
    "sg:orig_category":"Lumber For Packaging Purposes",
    "sg:phone":"+43 2762 52122",
    "sg:postcode":"3183",
    "sg:province":"Nieder\u00f6sterreich",
    "wof:name":"Ing. Franz Lampl",
    "wof:placetype":"venue"
},
  "geometry": {"coordinates":[15.5521612167,47.9612503052],"type":"Point"}
}