{
  "type": "Feature",
  "properties": {
    "addr:full":"Krankenhausg 7 Kufstein Tirol 6330",
    "addr:housenumber":"7",
    "addr:postcode":"6330",
    "addr:street":"Krankenhausg;Tirol",
    "iso:country":"AT",
    "sg:address":"Krankenhausg 7",
    "sg:city":"Kufstein",
    "sg:orig_category":"Bibliotheken",
    "sg:phone":"+43 5372 602505",
    "sg:postcode":"6330",
    "sg:province":"Tirol",
    "wof:name":"Stadtb\u00fccherei",
    "wof:placetype":"venue"
},
  "geometry": {"coordinates":[12.173157692,47.5833091736],"type":"Point"}
}