{
  "type": "Feature",
  "properties": {
    "addr:full":"Neunkirchner Str 14/4 Wiener Neustadt Nieder\u00f6sterreich 2700",
    "addr:housenumber":"14 / 4",
    "addr:postcode":"2700",
    "addr:street":"Str",
    "iso:country":"AT",
    "sg:address":"Neunkirchner Str 14/4",
    "sg:city":"Wiener Neustadt",
    "sg:orig_category":"Ergotherapie",
    "sg:phone":"+43 699 19235951",
    "sg:postcode":"2700",
    "sg:province":"Nieder\u00f6sterreich",
    "wof:name":"Ergotherapeutische Praxis f\u00fcr Kinder und Erwachsene - Schaffer Karin Mag",
    "wof:placetype":"venue"
},
  "geometry": {"coordinates":[16.2435646057,47.8116264343],"type":"Point"}
}