{
  "type": "Feature",
  "properties": {
    "addr:full":"Neudorfer Str 7 Staatz-Kautendorf Nieder\u00f6sterreich 2134",
    "addr:housenumber":"7",
    "addr:postcode":"2134",
    "addr:street":"Str;Niederoesterreich",
    "iso:country":"AT",
    "sg:address":"Neudorfer Str 7",
    "sg:city":"Staatz-Kautendorf",
    "sg:orig_category":"Gemeinden",
    "sg:phone":"+43 2524 22120",
    "sg:postcode":"2134",
    "sg:province":"Nieder\u00f6sterreich",
    "wof:name":"Gemeindeamt Staatz",
    "wof:placetype":"venue"
},
  "geometry": {"coordinates":[16.4860973358,48.6758804321],"type":"Point"}
}