{
  "type": "Feature",
  "properties": {
    "addr:full":"Wr Neust\u00e4dter Str 2 Bad Sauerbrunn Burgenland 7202",
    "addr:housenumber":"2",
    "addr:postcode":"7202",
    "addr:street":"Str",
    "iso:country":"AT",
    "sg:address":"Wr Neust\u00e4dter Str 2",
    "sg:city":"Bad Sauerbrunn",
    "sg:orig_category":"Banken U Sparkassen",
    "sg:phone":"+43 4350 50537550",
    "sg:postcode":"7202",
    "sg:province":"Burgenland",
    "wof:name":"Bank Austria Creditanstalt AG",
    "wof:placetype":"venue"
},
  "geometry": {"coordinates":[16.3250465393,47.7747840881],"type":"Point"}
}