{
  "type": "Feature",
  "properties": {
    "addr:full":"Gartenstr 11 Aigen im M\u00fchlkreis Ober\u00f6sterreich 4160",
    "addr:housenumber":"11",
    "addr:postcode":"4160",
    "addr:street":"Gartenstr",
    "iso:country":"AT",
    "sg:address":"Gartenstr 11",
    "sg:city":"Aigen im M\u00fchlkreis",
    "sg:orig_category":"Maler, Anstreicher U Lackierer",
    "sg:phone":"+43 4372 8163780",
    "sg:postcode":"4160",
    "sg:province":"Ober\u00f6sterreich",
    "wof:name":"Pernauer Werner",
    "wof:placetype":"venue"
},
  "geometry": {"coordinates":[13.9704666138,48.6473655701],"type":"Point"}
}