{
  "type": "Feature",
  "properties": {
    "iso:country":"AT",
    "sg:address":"Maria Saaler Bergweg 1",
    "sg:city":"Maria Saal",
    "sg:orig_category":"Lebensmittel / Einzelhandel",
    "sg:phone":"+43 4223 22260",
    "sg:postcode":"9063",
    "sg:province":"K\u00e4rnten",
    "wof:name":"ADEG Wilhelm Wohlgemuth",
    "wof:placetype":"venue"
},
  "geometry": {"coordinates":[14.3474750519,46.680065155],"type":"Point"}
}