{
  "type": "Feature",
  "properties": {
    "addr:full":"Obermarkt 2 Reutte Tirol 6600",
    "addr:housenumber":"2",
    "addr:postcode":"6600",
    "addr:street":"Obermarkt;Tirol",
    "iso:country":"AT",
    "sg:address":"Obermarkt 2",
    "sg:city":"Reutte",
    "sg:orig_category":"Polizei U Gendarmerie",
    "sg:phone":"+43 4359 1337150",
    "sg:postcode":"6600",
    "sg:province":"Tirol",
    "wof:name":"Gendarmerie",
    "wof:placetype":"venue"
},
  "geometry": {"coordinates":[10.7184438705,47.4888305664],"type":"Point"}
}