{
  "type": "Feature",
  "properties": {
    "addr:full":"Kraims 1 Seewalchen am Attersee Ober\u00f6sterreich 4863",
    "addr:housenumber":"1",
    "addr:postcode":"4863",
    "addr:street":"Kraims",
    "iso:country":"AT",
    "sg:address":"Kraims 1",
    "sg:city":"Seewalchen am Attersee",
    "sg:orig_category":"Autohandel",
    "sg:phone":"+43 4369 911681110",
    "sg:postcode":"4863",
    "sg:province":"Ober\u00f6sterreich",
    "wof:name":"NEUTRON Handels-GmbH",
    "wof:placetype":"venue"
},
  "geometry": {"coordinates":[13.5828876495,47.9701271057],"type":"Point"}
}