{
  "type": "Feature",
  "properties": {
    "addr:full":"Hostauerstr 56 Ottensheim Ober\u00f6sterreich 4100",
    "addr:housenumber":"56",
    "addr:postcode":"4100",
    "addr:street":"Hostauerstr",
    "iso:country":"AT",
    "sg:address":"Hostauerstr 56",
    "sg:city":"Ottensheim",
    "sg:orig_category":"Schlossereien",
    "sg:phone":"+43 7234 826500",
    "sg:postcode":"4100",
    "sg:province":"Ober\u00f6sterreich",
    "wof:name":"Sch\u00f6ppl KEG",
    "wof:placetype":"venue"
},
  "geometry": {"coordinates":[14.1684818268,48.3385848999],"type":"Point"}
}