{
  "type": "Feature",
  "properties": {
    "addr:full":"Hauptstr 129 Marz Burgenland 7221",
    "addr:housenumber":"129",
    "addr:postcode":"7221",
    "addr:street":"Hauptstr",
    "iso:country":"AT",
    "sg:address":"Hauptstr 129",
    "sg:city":"Marz",
    "sg:orig_category":"Autoreparatur",
    "sg:phone":"+43 2626 64955",
    "sg:postcode":"7221",
    "sg:province":"Burgenland",
    "wof:name":"Sauerzapf Manfred",
    "wof:placetype":"venue"
},
  "geometry": {"coordinates":[16.4052639008,47.713809967],"type":"Point"}
}