{
  "type": "Feature",
  "properties": {
    "addr:full":"Bahnhofstr 1 Reutte Tirol 6600",
    "addr:housenumber":"1",
    "addr:postcode":"6600",
    "addr:street":"Bahnhofstr;Tirol",
    "iso:country":"AT",
    "sg:address":"Bahnhofstr 1",
    "sg:city":"Reutte",
    "sg:orig_category":"Bandagen U Bandagisten",
    "sg:phone":"+43 5672 63336",
    "sg:postcode":"6600",
    "sg:province":"Tirol",
    "wof:name":"Danner Sanit\u00e4tshaus",
    "wof:placetype":"venue"
},
  "geometry": {"coordinates":[10.7182025909,47.4930038452],"type":"Point"}
}