{
  "type": "Feature",
  "properties": {
    "addr:full":"Olivierstr 25 Aigen Salzburg 5026",
    "addr:housenumber":"25",
    "addr:postcode":"5026",
    "addr:street":"Olivierstr;Salzburg",
    "iso:country":"AT",
    "sg:address":"Olivierstr 25",
    "sg:city":"Aigen",
    "sg:orig_category":"Bilder",
    "sg:phone":"+43 4366 26335000",
    "sg:postcode":"5026",
    "sg:province":"Salzburg",
    "sg:website":"artworkshop.at",
    "wof:name":"ARTworkshop Werbeagentur Inh Walter Puchmayr-Angerer",
    "wof:placetype":"venue"
},
  "geometry": {"coordinates":[13.0770225525,47.7857208252],"type":"Point"}
}