{
  "type": "Feature",
  "properties": {
    "addr:full":"Nr 36 Lofer Salzburg 5090",
    "addr:postcode":"5090",
    "addr:street":"Nr;Lofer",
    "iso:country":"AT",
    "sg:address":"Nr 36",
    "sg:city":"Lofer",
    "sg:orig_category":"Transportunternehmen",
    "sg:phone":"+43 6588 8217",
    "sg:postcode":"5090",
    "sg:province":"Salzburg",
    "wof:name":"Leitinger KEG & Co KEG",
    "wof:placetype":"venue"
},
  "geometry": {"coordinates":[12.6930541992,47.5873069763],"type":"Point"}
}