{
  "type": "Feature",
  "properties": {
    "addr:full":"Franziskanerstr 59 Frauenkirchen Burgenland 7132",
    "addr:housenumber":"59",
    "addr:postcode":"7132",
    "addr:street":"Franziskanerstr",
    "iso:country":"AT",
    "sg:address":"Franziskanerstr 59",
    "sg:city":"Frauenkirchen",
    "sg:orig_category":"Autoreparatur",
    "sg:phone":"+43 2172 25880",
    "sg:postcode":"7132",
    "sg:province":"Burgenland",
    "wof:name":"Lamster Peter",
    "wof:placetype":"venue"
},
  "geometry": {"coordinates":[16.9216690063,47.8345375061],"type":"Point"}
}