{
  "type": "Feature",
  "properties": {
    "addr:full":"Boznerplatz, 2 -  Innsbruck Tirol 6020",
    "addr:housenumber":"2",
    "addr:postcode":"6020",
    "addr:street":"Boznerplatz;Tirol",
    "iso:country":"AT",
    "sg:address":"Boznerplatz, 2 - ",
    "sg:city":"Innsbruck",
    "sg:classifiers":[
        {
            "category":"Professional",
            "subcategory":"Art Services",
            "type":"Services"
        }
    ],
    "sg:phone":"+43 512 580461",
    "sg:postcode":"6020",
    "sg:province":"Tirol",
    "sg:tags":[
        "export-import"
    ],
    "wof:name":"Royal Thai Consulate",
    "wof:placetype":"venue"
},
  "geometry": {"coordinates":[11.3975543976,47.2652626038],"type":"Point"}
}