{
  "type": "Feature",
  "properties": {
    "addr:full":"Hauptpl 29 Hadersdorf am Kamp Nieder\u00f6sterreich 3493",
    "addr:housenumber":"29",
    "addr:postcode":"3493",
    "addr:street":"Hauptpl;Niederoesterreich",
    "iso:country":"AT",
    "sg:address":"Hauptpl 29",
    "sg:city":"Hadersdorf am Kamp",
    "sg:orig_category":"Friseure U Frisiersalons",
    "sg:phone":"+43 4327 352485",
    "sg:postcode":"3493",
    "sg:province":"Nieder\u00f6sterreich",
    "wof:name":"Kisela Gabriele",
    "wof:placetype":"venue"
},
  "geometry": {"coordinates":[15.7206497192,48.4578361511],"type":"Point"}
}