{
  "type": "Feature",
  "properties": {
    "iso:country":"AT",
    "sg:address":"Daffingerstr. 10",
    "sg:city":"Wels",
    "sg:classifiers":[
        {
            "category":"Professional",
            "subcategory":"Engineering",
            "type":"Services"
        }
    ],
    "sg:phone":"+43 4372 4244540",
    "sg:postcode":"4600",
    "sg:province":"Ober\u00f6sterreich",
    "sg:tags":[
        "machine",
        "-",
        "mechanical"
    ],
    "wof:name":"ANGLEITNER GMBH",
    "wof:placetype":"venue"
},
  "geometry": {"coordinates":[14.0565433502,48.1843757629],"type":"Point"}
}