{
  "type": "Feature",
  "properties": {
    "addr:full":"Krehbachg 5b Telfs Tirol 6410",
    "addr:housenumber":"5b",
    "addr:postcode":"6410",
    "addr:street":"Krehbachg;Tirol",
    "iso:country":"AT",
    "sg:address":"Krehbachg 5b",
    "sg:city":"Telfs",
    "sg:orig_category":"Autoreparatur",
    "sg:phone":"+43 5262 64235",
    "sg:postcode":"6410",
    "sg:province":"Tirol",
    "wof:name":"Kapferer Klaus",
    "wof:placetype":"venue"
},
  "geometry": {"coordinates":[11.0629739761,47.3111686707],"type":"Point"}
}