{
  "type": "Feature",
  "properties": {
    "addr:full":"Stadtfeldg 5 Laa an der Thaya Nieder\u00f6sterreich 2136",
    "addr:housenumber":"5",
    "addr:postcode":"2136",
    "addr:street":"Stadtfeldg",
    "iso:country":"AT",
    "sg:address":"Stadtfeldg 5",
    "sg:city":"Laa an der Thaya",
    "sg:orig_category":"Bars-Cafes",
    "sg:phone":"+43 2522 7713",
    "sg:postcode":"2136",
    "sg:province":"Nieder\u00f6sterreich",
    "wof:name":"Paddock-Bar",
    "wof:placetype":"venue"
},
  "geometry": {"coordinates":[16.3890666962,48.7181167603],"type":"Point"}
}