{
  "type": "Feature",
  "properties": {
    "addr:full":"Rotenhofg. 43 Wien Wien 1100",
    "addr:housenumber":"43",
    "addr:postcode":"1100",
    "addr:street":"Rotenhofg.",
    "iso:country":"AT",
    "sg:address":"Rotenhofg. 43",
    "sg:city":"Wien",
    "sg:classifiers":[
        {
            "category":"Wholesale",
            "subcategory":"Drugs",
            "type":"Manufacturing & Wholesale Goods"
        }
    ],
    "sg:phone":"+43 4316 043431",
    "sg:postcode":"1100",
    "sg:province":"Wien",
    "sg:tags":[
        "chemical",
        "pharmaceutical"
    ],
    "wof:name":"HASLINGER SEIFEN UND KOSMETIK GMBH",
    "wof:placetype":"venue"
},
  "geometry": {"coordinates":[16.3693771362,48.1742591858],"type":"Point"}
}