{
  "type": "Feature",
  "properties": {
    "addr:full":"Klausenweg 19 Linz Ober\u00f6sterreich 4040",
    "addr:housenumber":"19",
    "addr:postcode":"4040",
    "addr:street":"Klausenweg",
    "iso:country":"AT",
    "sg:address":"Klausenweg 19",
    "sg:city":"Linz",
    "sg:orig_category":"Weiterbildungsinstitute M Allg U Berufl Bildungsangebot",
    "sg:phone":"+43 4373 2246375",
    "sg:postcode":"4040",
    "sg:province":"Ober\u00f6sterreich",
    "wof:name":"Cue-Train Thon & Partner OEG",
    "wof:placetype":"venue"
},
  "geometry": {"coordinates":[14.2907943726,48.3428421021],"type":"Point"}
}