{
  "type": "Feature",
  "properties": {
    "iso:country":"AT",
    "sg:address":"Salzburger Str 37",
    "sg:city":"Schwanenstadt",
    "sg:orig_category":"Autoreparatur",
    "sg:phone":"+43 767322190",
    "sg:postcode":"4690",
    "sg:province":"Ober\u00f6sterreich",
    "wof:name":"Willeit GesmbH & Co KG",
    "wof:placetype":"venue"
},
  "geometry": {"coordinates":[13.7634983063,48.04870224],"type":"Point"}
}