{
  "type": "Feature",
  "properties": {
    "addr:full":"Wiener Str 51 Tulbing Nieder\u00f6sterreich 3434",
    "addr:postcode":"3434",
    "addr:street":"Niederoesterreich",
    "iso:country":"AT",
    "sg:address":"Wiener Str 51",
    "sg:city":"Tulbing",
    "sg:classifiers":[
        {
            "category":"Professional",
            "subcategory":"Computer Services",
            "type":"Services"
        }
    ],
    "sg:phone":"+43 4322 7370122",
    "sg:postcode":"3434",
    "sg:province":"Nieder\u00f6sterreich",
    "sg:tags":[
        "software"
    ],
    "wof:name":"Kerth Softwarehaus",
    "wof:placetype":"venue"
},
  "geometry": {"coordinates":[16.113401413,48.278793335],"type":"Point"}
}