{
  "type": "Feature",
  "properties": {
    "addr:full":"Eichenstr 74 Wien Wien 1120",
    "addr:housenumber":"74",
    "addr:postcode":"1120",
    "addr:street":"Eichenstr",
    "iso:country":"AT",
    "sg:address":"Eichenstr 74",
    "sg:city":"Wien",
    "sg:orig_category":"Lebensmittel / Einzelhandel",
    "sg:phone":"+43 699 11648325",
    "sg:postcode":"1120",
    "sg:province":"Wien",
    "wof:name":"Nedumthottiyil & Pereira OEG",
    "wof:placetype":"venue"
},
  "geometry": {"coordinates":[16.3323917389,48.1749649048],"type":"Point"}
}