{
  "type": "Feature",
  "properties": {
    "addr:full":"Stern 41 Altheim Ober\u00f6sterreich 4950",
    "addr:housenumber":"41",
    "addr:postcode":"4950",
    "addr:street":"Stern",
    "iso:country":"AT",
    "sg:address":"Stern 41",
    "sg:city":"Altheim",
    "sg:orig_category":"Fenster",
    "sg:phone":"+43 7723 44420",
    "sg:postcode":"4950",
    "sg:province":"Ober\u00f6sterreich",
    "wof:name":"KOBE",
    "wof:placetype":"venue"
},
  "geometry": {"coordinates":[13.2211990356,48.2296447754],"type":"Point"}
}