{
  "type": "Feature",
  "properties": {
    "addr:full":"Rathausstr 33 Bregenz Vorarlberg 6900",
    "addr:housenumber":"33",
    "addr:postcode":"6900",
    "addr:street":"Rathausstr",
    "iso:country":"AT",
    "sg:address":"Rathausstr 33",
    "sg:city":"Bregenz",
    "sg:orig_category":"Friseure U Frisiersalons",
    "sg:phone":"+43 4355 7452555",
    "sg:postcode":"6900",
    "sg:province":"Vorarlberg",
    "wof:name":"\u00f6lz Intercoiffeur",
    "wof:placetype":"venue"
},
  "geometry": {"coordinates":[9.7461738586,47.5041503906],"type":"Point"}
}