{
  "type": "Feature",
  "properties": {
    "addr:full":"Herrgottwiesg 160c-162a Puntigam Steiermark 8055",
    "addr:postcode":"8055",
    "addr:street":"160C-162A",
    "iso:country":"AT",
    "sg:address":"Herrgottwiesg 160c-162a",
    "sg:city":"Puntigam",
    "sg:orig_category":"Polytechnische Schulen",
    "sg:phone":"+43 316 273484",
    "sg:postcode":"8055",
    "sg:province":"Steiermark",
    "wof:name":"Polytechnische Schule",
    "wof:placetype":"venue"
},
  "geometry": {"coordinates":[15.4314804077,47.0309486389],"type":"Point"}
}