{
  "type": "Feature",
  "properties": {
    "addr:full":"Rain 323 Mellau Vorarlberg 6881",
    "addr:housenumber":"323",
    "addr:postcode":"6881",
    "addr:street":"Rain",
    "iso:country":"AT",
    "sg:address":"Rain 323",
    "sg:city":"Mellau",
    "sg:orig_category":"Bergbahnen",
    "sg:phone":"+43 5518 2744",
    "sg:postcode":"6881",
    "sg:province":"Vorarlberg",
    "wof:name":"Kohler Seilbahnen GmbH - Seil- und Hebetechnik",
    "wof:placetype":"venue"
},
  "geometry": {"coordinates":[9.8822097778,47.3512458801],"type":"Point"}
}