{
  "type": "Feature",
  "properties": {
    "addr:full":"Dieselstr 1 Mauthausen Ober\u00f6sterreich 4310",
    "addr:housenumber":"1",
    "addr:postcode":"4310",
    "addr:street":"Dieselstr",
    "iso:country":"AT",
    "sg:address":"Dieselstr 1",
    "sg:city":"Mauthausen",
    "sg:orig_category":"Tankstellen",
    "sg:phone":"+43 7238 33200",
    "sg:postcode":"4310",
    "sg:province":"Ober\u00f6sterreich",
    "wof:name":"Shell Austria GmbH",
    "wof:placetype":"venue"
},
  "geometry": {"coordinates":[14.5450143814,48.2419776917],"type":"Point"}
}