{
  "type": "Feature",
  "properties": {
    "addr:full":"Mitisgasse 17/6 Wien Wien 1140",
    "addr:housenumber":"17 / 6",
    "addr:postcode":"1140",
    "addr:street":"Mitisgasse",
    "iso:country":"AT",
    "sg:address":"Mitisgasse 17/6",
    "sg:city":"Wien",
    "sg:classifiers":[
        {
            "category":"Social Services",
            "subcategory":"Job Training",
            "type":"Services"
        }
    ],
    "sg:phone":"+43 1 5226868",
    "sg:postcode":"1140",
    "sg:province":"Wien",
    "sg:tags":[
        "software",
        "database"
    ],
    "sg:website":"neovalis.com",
    "wof:name":"Neovalis IT Development GmbH",
    "wof:placetype":"venue"
},
  "geometry": {"coordinates":[16.2931995392,48.1967773438],"type":"Point"}
}