{
  "type": "Feature",
  "properties": {
    "addr:full":"Mozartpl 9 St. Gilgen Salzburg 5340",
    "addr:housenumber":"9",
    "addr:postcode":"5340",
    "addr:street":"Mozartpl",
    "iso:country":"AT",
    "sg:address":"Mozartpl 9",
    "sg:city":"St. Gilgen",
    "sg:orig_category":"Freizeit- U Sportbekleidung",
    "sg:phone":"+43 4362 272416",
    "sg:postcode":"5340",
    "sg:province":"Salzburg",
    "wof:name":"Noppi Sport und Mode HandelsgmbH",
    "wof:placetype":"venue"
},
  "geometry": {"coordinates":[13.3641786575,47.7671394348],"type":"Point"}
}