{
  "type": "Feature",
  "properties": {
    "iso:country":"AT",
    "sg:address":"Platzl 103",
    "sg:city":"Leutasch",
    "sg:classifiers":[
        {
            "category":"Travel",
            "subcategory":"Hotels & Motels",
            "type":"Entertainment"
        }
    ],
    "sg:phone":"+43 5214 62010",
    "sg:postcode":"6105",
    "sg:province":"Tirol",
    "wof:name":"Hotel Gasthof Zugspitze",
    "wof:placetype":"venue"
},
  "geometry": {"coordinates":[11.1340169907,47.3612556458],"type":"Point"}
}