{
  "type": "Feature",
  "properties": {
    "iso:country":"AT",
    "sg:address":"Hauptstr 41",
    "sg:city":"Trautmannsdorf an der Leitha",
    "sg:orig_category":"Gemeinden",
    "sg:phone":"+43 2169 2235",
    "sg:postcode":"2454",
    "sg:province":"Nieder\u00f6sterreich",
    "wof:name":"Gemeindeamt d Marktgemeinde Trautmannsdorf a d Leitha",
    "wof:placetype":"venue"
},
  "geometry": {"coordinates":[16.6775856018,48.0202789307],"type":"Point"}
}