{
  "type": "Feature",
  "properties": {
    "iso:country":"AT",
    "sg:address":"Innstr 45",
    "sg:city":"Innsbruck",
    "sg:orig_category":"Baumeister",
    "sg:phone":"+43 512 295607",
    "sg:postcode":"6020",
    "sg:province":"Tirol",
    "wof:name":"Wechselberger Roland Ing GesmbH",
    "wof:placetype":"venue"
},
  "geometry": {"coordinates":[11.3915166855,47.2708587646],"type":"Point"}
}