{
  "type": "Feature",
  "properties": {
    "addr:full":"W\u00e4hringer Str 86 Wien Wien 1180",
    "addr:postcode":"1180",
    "addr:street":"Str 86",
    "iso:country":"AT",
    "sg:address":"W\u00e4hringer Str 86",
    "sg:city":"Wien",
    "sg:orig_category":"Lebensmittel / Einzelhandel",
    "sg:phone":"+43 1 4796838",
    "sg:postcode":"1180",
    "sg:province":"Wien",
    "wof:name":"Zielpunkt Warenhandel GmbH & Co KG",
    "wof:placetype":"venue"
},
  "geometry": {"coordinates":[16.3479175568,48.2254562378],"type":"Point"}
}