{
  "type": "Feature",
  "properties": {
    "iso:country":"AT",
    "sg:address":"Bahnhofstr 57",
    "sg:city":"Hausmening",
    "sg:orig_category":"Holzhandel",
    "sg:phone":"+43 7475 52276",
    "sg:postcode":"3363",
    "sg:province":"Nieder\u00f6sterreich",
    "wof:name":"Dorner Walter Ing",
    "wof:placetype":"venue"
},
  "geometry": {"coordinates":[14.8148822784,48.0708312988],"type":"Point"}
}