{
  "type": "Feature",
  "properties": {
    "addr:full":"Kapr Generator-Str 34 Weiz Steiermark 8160",
    "addr:housenumber":"34",
    "addr:postcode":"8160",
    "iso:country":"AT",
    "sg:address":"Kapr Generator-Str 34",
    "sg:city":"Weiz",
    "sg:orig_category":"Werbeagenturen",
    "sg:phone":"+43 3172 30150",
    "sg:postcode":"8160",
    "sg:province":"Steiermark",
    "wof:name":"Digitiv Koller-Mauritsch-Most\u00f6gl OEG",
    "wof:placetype":"venue"
},
  "geometry": {"coordinates":[15.6215696335,47.2169532776],"type":"Point"}
}