{
  "type": "Feature",
  "properties": {
    "addr:full":"Arbeiterg 41 Wien Wien 1050",
    "addr:housenumber":"41",
    "addr:postcode":"1050",
    "addr:street":"Arbeiterg",
    "iso:country":"AT",
    "sg:address":"Arbeiterg 41",
    "sg:city":"Wien",
    "sg:orig_category":"Galerien",
    "sg:phone":"+43 1 5446819",
    "sg:postcode":"1050",
    "sg:province":"Wien",
    "wof:name":"galelrie aRtelier Peter Meier KEG",
    "wof:placetype":"venue"
},
  "geometry": {"coordinates":[16.347951889,48.1846008301],"type":"Point"}
}