{
  "type": "Feature",
  "properties": {
    "addr:full":"Josef-Leitgeb-Str 1 Bischofshofen Salzburg 5500",
    "addr:housenumber":"1",
    "addr:postcode":"5500",
    "addr:street":"Josef-Leitgeb-Str;Salzburg",
    "iso:country":"AT",
    "sg:address":"Josef-Leitgeb-Str 1",
    "sg:city":"Bischofshofen",
    "sg:orig_category":"Banken U Sparkassen",
    "sg:phone":"+43 4364 622353",
    "sg:postcode":"5500",
    "sg:province":"Salzburg",
    "wof:name":"Bankomat d Sparda-Bank Linz regGenmbH",
    "wof:placetype":"venue"
},
  "geometry": {"coordinates":[13.2192382812,47.4182472229],"type":"Point"}
}