{
  "type": "Feature",
  "properties": {
    "iso:country":"AT",
    "sg:address":"Salzburger Str 70",
    "sg:city":"Bad Hofgastein",
    "sg:orig_category":"Psychologen",
    "sg:phone":"+43 4364 3226070",
    "sg:postcode":"5630",
    "sg:province":"Salzburg",
    "wof:name":"Klinische u Gesundheits-Psychologin Mag Sigrid Hamberg",
    "wof:placetype":"venue"
},
  "geometry": {"coordinates":[13.1020784378,47.1807250977],"type":"Point"}
}