{
  "type": "Feature",
  "properties": {
    "addr:full":"Kirchfeldgasse 69 Wien Wien 1230",
    "addr:housenumber":"69",
    "addr:postcode":"1230",
    "addr:street":"Kirchfeldgasse",
    "iso:country":"AT",
    "sg:address":"Kirchfeldgasse 69",
    "sg:city":"Wien",
    "sg:classifiers":[
        {
            "category":"Government",
            "subcategory":"Post Office",
            "type":"Public Place"
        }
    ],
    "sg:phone":"+43 1 80486260",
    "sg:postcode":"1230",
    "sg:province":"Wien",
    "sg:tags":[
        "technical",
        "injection",
        "parts",
        "moulded"
    ],
    "sg:website":"rejlek.at",
    "wof:name":"Viennaplex Fabrik f\u00fcr Kunststofferzeugnisse Ernst Pless KG",
    "wof:placetype":"venue"
},
  "geometry": {"coordinates":[16.3051757812,48.1599311829],"type":"Point"}
}