{
  "type": "Feature",
  "properties": {
    "iso:country":"AT",
    "sg:address":"Sewerstr 4",
    "sg:city":"Hall in Tirol",
    "sg:orig_category":"Architekten",
    "sg:phone":"+43 5223 57995",
    "sg:postcode":"6060",
    "sg:province":"Tirol",
    "wof:name":"Holzmann Karl Arch Dipl-Ing",
    "wof:placetype":"venue"
},
  "geometry": {"coordinates":[11.5025568008,47.2838592529],"type":"Point"}
}