{
  "type": "Feature",
  "properties": {
    "addr:full":"Sewerstr 4 Hall in Tirol Tirol 6060",
    "addr:housenumber":"4",
    "addr:postcode":"6060",
    "addr:street":"Sewerstr;Tirol",
    "iso:country":"AT",
    "sg:address":"Sewerstr 4",
    "sg:city":"Hall in Tirol",
    "sg:orig_category":"Architekten",
    "sg:phone":"+43 5223 57995",
    "sg:postcode":"6060",
    "sg:province":"Tirol",
    "wof:name":"Holzmann Karl Arch Dipl-Ing",
    "wof:placetype":"venue"
},
  "geometry": {"coordinates":[11.5025568008,47.2838592529],"type":"Point"}
}