{
  "type": "Feature",
  "properties": {
    "addr:full":"Schwarzenbach 2 Metnitz K\u00e4rnten 9363",
    "addr:housenumber":"2",
    "addr:postcode":"9363",
    "addr:street":"Schwarzenbach;Kaernten",
    "iso:country":"AT",
    "sg:address":"Schwarzenbach 2",
    "sg:city":"Metnitz",
    "sg:orig_category":"Immobilienverwaltungen",
    "sg:phone":"+43 4267 564",
    "sg:postcode":"9363",
    "sg:province":"K\u00e4rnten",
    "wof:name":"Ha\u00dfhold Herbert",
    "wof:placetype":"venue"
},
  "geometry": {"coordinates":[14.1217441559,46.9840812683],"type":"Point"}
}