{
  "type": "Feature",
  "properties": {
    "addr:full":"Fischerweg 7 Bodensdorf K\u00e4rnten 9551",
    "addr:housenumber":"7",
    "addr:postcode":"9551",
    "addr:street":"Fischerweg;Kaernten",
    "iso:country":"AT",
    "sg:address":"Fischerweg 7",
    "sg:city":"Bodensdorf",
    "sg:classifiers":[
        {
            "category":"Travel",
            "subcategory":"Hotels & Motels",
            "type":"Entertainment"
        }
    ],
    "sg:phone":"+43 4243 25140",
    "sg:postcode":"9551",
    "sg:province":"K\u00e4rnten",
    "sg:website":"seerose.info",
    "wof:name":"Familienhotel Seerose-P\u00f6lzl KG",
    "wof:placetype":"venue"
},
  "geometry": {"coordinates":[13.9701690674,46.6783409119],"type":"Point"}
}