{
  "type": "Feature",
  "properties": {
    "iso:country":"AT",
    "sg:address":"Schulg 7",
    "sg:city":"Wiener Neustadt",
    "sg:orig_category":"Freizeit- U Sportbekleidung",
    "sg:phone":"+43 4326 2226089",
    "sg:postcode":"2700",
    "sg:province":"Nieder\u00f6sterreich",
    "wof:name":"Duo Jeans Company",
    "wof:placetype":"venue"
},
  "geometry": {"coordinates":[16.2444705963,47.8124237061],"type":"Point"}
}