{
  "type": "Feature",
  "properties": {
    "addr:full":"Waschpoint 16 Eferding Ober\u00f6sterreich 4070",
    "addr:housenumber":"16",
    "addr:postcode":"4070",
    "addr:street":"Waschpoint",
    "iso:country":"AT",
    "sg:address":"Waschpoint 16",
    "sg:city":"Eferding",
    "sg:orig_category":"Massagen",
    "sg:phone":"+43 7272 6190",
    "sg:postcode":"4070",
    "sg:province":"Ober\u00f6sterreich",
    "wof:name":"Massage-Bernhard",
    "wof:placetype":"venue"
},
  "geometry": {"coordinates":[14.0234451294,48.3086395264],"type":"Point"}
}