{
  "type": "Feature",
  "properties": {
    "iso:country":"AT",
    "sg:address":"Thurnfeldg 4a",
    "sg:city":"Hall in Tirol",
    "sg:orig_category":"\u00c3\u201erzte / F Allgemeinmedizin",
    "sg:phone":"+43 5223 56711",
    "sg:postcode":"6060",
    "sg:province":"Tirol",
    "wof:name":"Dengg Christian Dr",
    "wof:placetype":"venue"
},
  "geometry": {"coordinates":[11.5099096298,47.2834091187],"type":"Point"}
}