{
  "type": "Feature",
  "properties": {
    "addr:full":"Steinfeldg 63a Graz Steiermark 8020",
    "addr:housenumber":"63a",
    "addr:postcode":"8020",
    "addr:street":"Steinfeldg",
    "iso:country":"AT",
    "sg:address":"Steinfeldg 63a",
    "sg:city":"Graz",
    "sg:orig_category":"Immobilienmakler",
    "sg:phone":"+43 316 714865",
    "sg:postcode":"8020",
    "sg:province":"Steiermark",
    "wof:name":"Immobilien B\u00f6ss",
    "wof:placetype":"venue"
},
  "geometry": {"coordinates":[15.4197692871,47.0644989014],"type":"Point"}
}