{
  "type": "Feature",
  "properties": {
    "iso:country":"AT",
    "sg:address":"Daimlerg 13",
    "sg:city":"Steinabr\u00fcckl",
    "sg:orig_category":"Elektroinstallationsunternehmen",
    "sg:phone":"+43 2622 43387",
    "sg:postcode":"2751",
    "sg:province":"Nieder\u00f6sterreich",
    "wof:name":"Elektro Peter Dezsi Ing Peter Dezsi-Szene",
    "wof:placetype":"venue"
},
  "geometry": {"coordinates":[16.2142677307,47.8700141907],"type":"Point"}
}