{
  "type": "Feature",
  "properties": {
    "addr:full":"Westbahnstr 9 Wien Wien 1070",
    "addr:housenumber":"9",
    "addr:postcode":"1070",
    "addr:street":"Westbahnstr",
    "iso:country":"AT",
    "sg:address":"Westbahnstr 9",
    "sg:city":"Wien",
    "sg:orig_category":"Architekten",
    "sg:phone":"+43 1 9249446",
    "sg:postcode":"1070",
    "sg:province":"Wien",
    "wof:name":"F\u00fcrst Willi Dipl-Ing",
    "wof:placetype":"venue"
},
  "geometry": {"coordinates":[16.3462677002,48.2015991211],"type":"Point"}
}