{
  "type": "Feature",
  "properties": {
    "addr:full":"Prinz-Eugen-Str 35 Linz Ober\u00f6sterreich 4020",
    "addr:housenumber":"35",
    "addr:postcode":"4020",
    "addr:street":"Prinz-Eugen-Str",
    "iso:country":"AT",
    "sg:address":"Prinz-Eugen-Str 35",
    "sg:city":"Linz",
    "sg:orig_category":"Wasseraufbereitung U -Reinigung",
    "sg:phone":"+43 4373 2776677",
    "sg:postcode":"4020",
    "sg:province":"Ober\u00f6sterreich",
    "sg:website":"culligan.at",
    "wof:name":"Culligan O\u00f6 - Wassertechnik GmbH",
    "wof:placetype":"venue"
},
  "geometry": {"coordinates":[14.3288297653,48.3042297363],"type":"Point"}
}