{
  "type": "Feature",
  "properties": {
    "addr:full":"Nr 90 Kaltenbach Tirol 6272",
    "addr:postcode":"6272",
    "addr:street":"Nr 90 Kaltenbach",
    "iso:country":"AT",
    "sg:address":"Nr 90",
    "sg:city":"Kaltenbach",
    "sg:classifiers":[
        {
            "category":"Restaurant",
            "type":"Food & Drink"
        }
    ],
    "sg:phone":"+43 4352 833343",
    "sg:postcode":"6272",
    "sg:province":"Tirol",
    "sg:tags":[
        "pizzeria"
    ],
    "wof:name":"Pizza & Pasta 12 Apostel",
    "wof:placetype":"venue"
},
  "geometry": {"coordinates":[11.8866147995,47.2910232544],"type":"Point"}
}