{
  "type": "Feature",
  "properties": {
    "iso:country":"AT",
    "sg:address":"Brenner Str 78",
    "sg:city":"Steinach am Brenner",
    "sg:orig_category":"Partyservice",
    "sg:phone":"+43 4352 2453534",
    "sg:postcode":"6150",
    "sg:province":"Tirol",
    "sg:website":"tyrocate.at",
    "wof:name":"Tyro Cate Event-Culinarium GmbH",
    "wof:placetype":"venue"
},
  "geometry": {"coordinates":[11.4682626724,47.0876655579],"type":"Point"}
}