{
  "type": "Feature",
  "properties": {
    "iso:country":"AT",
    "sg:address":"Flachauer Landesstr 157",
    "sg:city":"Flachau",
    "sg:classifiers":[
        {
            "category":"Travel",
            "subcategory":"Hotels & Motels",
            "type":"Entertainment"
        }
    ],
    "sg:phone":"+43 6457 22250",
    "sg:postcode":"5542",
    "sg:province":"Salzburg",
    "wof:name":"Flachauerhof Hotel",
    "wof:placetype":"venue"
},
  "geometry": {"coordinates":[13.3956289291,47.3000259399],"type":"Point"}
}