{
  "type": "Feature",
  "properties": {
    "iso:country":"AT",
    "sg:address":"Rohrbach 46",
    "sg:city":"Dornbirn",
    "sg:orig_category":"Textiltechnik",
    "sg:phone":"+43 5572 29000",
    "sg:postcode":"6850",
    "sg:province":"Vorarlberg",
    "wof:name":"Telser Herbert Ing",
    "wof:placetype":"venue"
},
  "geometry": {"coordinates":[9.7305402756,47.4235458374],"type":"Point"}
}