{
  "type": "Feature",
  "properties": {
    "addr:full":"Nr 78 Roppen Tirol 6426",
    "addr:postcode":"6426",
    "addr:street":"Nr 78;Tirol",
    "iso:country":"AT",
    "sg:address":"Nr 78",
    "sg:city":"Roppen",
    "sg:orig_category":"Tourismusinformation U -Organisationen",
    "sg:phone":"+43 4354 175217",
    "sg:postcode":"6426",
    "sg:province":"Tirol",
    "wof:name":"Tourismusverband Roppen",
    "wof:placetype":"venue"
},
  "geometry": {"coordinates":[10.8198480606,47.2171440125],"type":"Point"}
}