{
  "type": "Feature",
  "properties": {
    "addr:full":"Nr 50 Freiland Nieder\u00f6sterreich 3183",
    "addr:postcode":"3183",
    "addr:street":"Nr;Freiland",
    "iso:country":"AT",
    "sg:address":"Nr 50",
    "sg:city":"Freiland",
    "sg:orig_category":"Pensionen / Privatzimmer",
    "sg:phone":"+43 2762 53110",
    "sg:postcode":"3183",
    "sg:province":"Nieder\u00f6sterreich",
    "wof:name":"Sch\u00f6nhofer Johann",
    "wof:placetype":"venue"
},
  "geometry": {"coordinates":[15.5521612167,47.9612503052],"type":"Point"}
}