{
  "type": "Feature",
  "properties": {
    "addr:full":"Kegelg 37-39 Wien Wien 1030",
    "addr:postcode":"37-39;1030",
    "iso:country":"AT",
    "sg:address":"Kegelg 37-39",
    "sg:city":"Wien",
    "sg:classifiers":[
        {
            "category":"Shopping",
            "subcategory":"Gifts & Souvenirs",
            "type":"Retail Goods"
        }
    ],
    "sg:phone":"+43 1 21608000",
    "sg:postcode":"1030",
    "sg:province":"Wien",
    "wof:name":"Hofbauer Michael HandelsgesmbH",
    "wof:placetype":"venue"
},
  "geometry": {"coordinates":[16.3941745758,48.2077865601],"type":"Point"}
}