{
  "type": "Feature",
  "properties": {
    "iso:country":"AT",
    "sg:address":"Ketzerg 191",
    "sg:city":"Perchtoldsdorf",
    "sg:orig_category":"Tankstellen",
    "sg:phone":"+43 1 8694352",
    "sg:postcode":"2380",
    "sg:province":"Nieder\u00f6sterreich",
    "wof:name":"BP Austria Marketing GmbH",
    "wof:placetype":"venue"
},
  "geometry": {"coordinates":[16.292339325,48.1301116943],"type":"Point"}
}