{
  "type": "Feature",
  "properties": {
    "iso:country":"AT",
    "sg:address":"Untere Hauptstr NB",
    "sg:city":"Potzneusiedl",
    "sg:orig_category":"Feuerwehren",
    "sg:phone":"+43 2145 2966",
    "sg:postcode":"2473",
    "sg:province":"Burgenland",
    "wof:name":"Freiwillige Feuerwehr Potzneusiedl",
    "wof:placetype":"venue"
},
  "geometry": {"coordinates":[16.9518222809,48.0437278748],"type":"Point"}
}