{
  "type": "Feature",
  "properties": {
    "addr:full":"Josef-K\u00f6lbl-Weg 8 Stra\u00dfgang Steiermark 8054",
    "addr:housenumber":"8",
    "addr:postcode":"8054",
    "addr:street":"Josef-Koelbl-Weg",
    "iso:country":"AT",
    "sg:address":"Josef-K\u00f6lbl-Weg 8",
    "sg:city":"Stra\u00dfgang",
    "sg:orig_category":"Handelsagenturen",
    "sg:phone":"+43 316 285073",
    "sg:postcode":"8054",
    "sg:province":"Steiermark",
    "wof:name":"Schweiger Siegfried Josef",
    "wof:placetype":"venue"
},
  "geometry": {"coordinates":[15.4008283615,47.0090484619],"type":"Point"}
}