{
  "type": "Feature",
  "properties": {
    "addr:full":"Innerschwand 370 Loibichl Ober\u00f6sterreich 5311",
    "addr:housenumber":"370",
    "addr:postcode":"5311",
    "addr:street":"Innerschwand;Oberoesterreich",
    "iso:country":"AT",
    "sg:address":"Innerschwand 370",
    "sg:city":"Loibichl",
    "sg:orig_category":"Dachdeckereien",
    "sg:phone":"+43 4362 3379988",
    "sg:postcode":"5311",
    "sg:province":"Ober\u00f6sterreich",
    "wof:name":"Speer GesmbH",
    "wof:placetype":"venue"
},
  "geometry": {"coordinates":[13.3961286545,47.831577301],"type":"Point"}
}