{
  "type": "Feature",
  "properties": {
    "addr:full":"Dorfstr 5 Walchsee Tirol 6344",
    "addr:housenumber":"5",
    "addr:postcode":"6344",
    "addr:street":"Dorfstr;Tirol",
    "iso:country":"AT",
    "sg:address":"Dorfstr 5",
    "sg:city":"Walchsee",
    "sg:orig_category":"Pensionen / Privatzimmer",
    "sg:phone":"+43 5374 5292",
    "sg:postcode":"6344",
    "sg:province":"Tirol",
    "wof:name":"Pramel Johann",
    "wof:placetype":"venue"
},
  "geometry": {"coordinates":[12.3120832443,47.6492080688],"type":"Point"}
}