{
  "type": "Feature",
  "properties": {
    "addr:full":"Bahnhofstr 13 Blumau-Neuri\u00dfhof Nieder\u00f6sterreich 2602",
    "addr:housenumber":"13;2602",
    "addr:street":"Bahnhofstr;Niederoesterreich",
    "iso:country":"AT",
    "sg:address":"Bahnhofstr 13",
    "sg:city":"Blumau-Neuri\u00dfhof",
    "sg:orig_category":"Alteisen U Altmetalle",
    "sg:phone":"+43 2628 48200",
    "sg:postcode":"2602",
    "sg:province":"Nieder\u00f6sterreich",
    "wof:name":"Erhardt Hans",
    "wof:placetype":"venue"
},
  "geometry": {"coordinates":[16.2932682037,47.9151916504],"type":"Point"}
}