{
  "type": "Feature",
  "properties": {
    "addr:full":"Fleischmarkt 26 Wien Wien 1010",
    "addr:housenumber":"26",
    "addr:postcode":"1010",
    "addr:street":"Fleischmarkt",
    "iso:country":"AT",
    "sg:address":"Fleischmarkt 26",
    "sg:city":"Wien",
    "sg:orig_category":"Schwangerenberatung / Geburtsvorbereitung, Ambulatorien",
    "sg:phone":"+43 1 51296310",
    "sg:postcode":"1010",
    "sg:province":"Wien",
    "sg:website":"asfleischmarkt.at",
    "wof:name":"Ambulatorium f Schwangerenhilfe am Fleischmarkt",
    "wof:placetype":"venue"
},
  "geometry": {"coordinates":[16.3783931732,48.2100601196],"type":"Point"}
}