{
  "type": "Feature",
  "properties": {
    "addr:full":"Gasteiner Str 29 Bischofshofen Salzburg 5500",
    "addr:housenumber":"29",
    "addr:postcode":"5500",
    "addr:street":"Gasteiner Str;Salzburg",
    "iso:country":"AT",
    "sg:address":"Gasteiner Str 29",
    "sg:city":"Bischofshofen",
    "sg:orig_category":"Zahngesundheitsvorsorge",
    "sg:phone":"+43 6462 251216",
    "sg:postcode":"5500",
    "sg:province":"Salzburg",
    "wof:name":"Zahnambulatorium d Salzburger Gebietskrankenkasse",
    "wof:placetype":"venue"
},
  "geometry": {"coordinates":[13.216588974,47.4123840332],"type":"Point"}
}