{
  "type": "Feature",
  "properties": {
    "addr:full":"Gartenstr 197 Wals Salzburg 5071",
    "addr:housenumber":"197",
    "addr:postcode":"5071",
    "addr:street":"Wals Salzburg",
    "iso:country":"AT",
    "sg:address":"Gartenstr 197",
    "sg:city":"Wals",
    "sg:orig_category":"Tischlereien",
    "sg:phone":"+43 662 850060",
    "sg:postcode":"5071",
    "sg:province":"Salzburg",
    "wof:name":"Tacer M\u00f6beltischlerei",
    "wof:placetype":"venue"
},
  "geometry": {"coordinates":[12.9826545715,47.8063964844],"type":"Point"}
}