{
  "type": "Feature",
  "properties": {
    "iso:country":"AT",
    "sg:address":"Haidweg",
    "sg:city":"Hinterglemm",
    "sg:orig_category":"Pensionen / Privatzimmer",
    "sg:phone":"+43 6541 66280",
    "sg:postcode":"5754",
    "sg:province":"Salzburg",
    "wof:name":"Haus Jakober",
    "wof:placetype":"venue"
},
  "geometry": {"coordinates":[12.5976638794,47.3775405884],"type":"Point"}
}