{
  "type": "Feature",
  "properties": {
    "addr:full":"Treustr 15/23 Wien Wien 1200",
    "addr:housenumber":"15 / 23",
    "addr:postcode":"1200",
    "addr:street":"Treustr",
    "iso:country":"AT",
    "sg:address":"Treustr 15/23",
    "sg:city":"Wien",
    "sg:orig_category":"Nachhilfe U Lernbetreuung",
    "sg:phone":"+43 1 9429681",
    "sg:postcode":"1200",
    "sg:province":"Wien",
    "wof:name":"Deutsch Lernen bei Mag Marcel Richter",
    "wof:placetype":"venue"
},
  "geometry": {"coordinates":[16.3673667908,48.2278060913],"type":"Point"}
}