{
  "type": "Feature",
  "properties": {
    "iso:country":"AT",
    "sg:address":"Nr 22",
    "sg:city":"Grieskirchen",
    "sg:orig_category":"Volkshochschulen",
    "sg:phone":"+43 7248 624764513",
    "sg:postcode":"4710",
    "sg:province":"Ober\u00f6sterreich",
    "wof:name":"Volkshochschule Ober\u00f6sterreich gemeinn\u00fctzige Bildungs-GmbH d AK f O\u00d6",
    "wof:placetype":"venue"
},
  "geometry": {"coordinates":[166.9221496582,-0.5282999873],"type":"Point"}
}