{
  "type": "Feature",
  "properties": {
    "addr:full":"Johann-Tikal-Str 11 Gallneukirchen Ober\u00f6sterreich 4210",
    "addr:housenumber":"11",
    "addr:postcode":"4210",
    "addr:street":"Johann-Tikal-Str;Oberoesterreich",
    "iso:country":"AT",
    "sg:address":"Johann-Tikal-Str 11",
    "sg:city":"Gallneukirchen",
    "sg:orig_category":"Innenarchitekten",
    "sg:phone":"+43 7235 620730",
    "sg:postcode":"4210",
    "sg:province":"Ober\u00f6sterreich",
    "wof:name":"P3 Plan Architektur Innenarchitektur Einrichtungsdesign Erwin Pinsker",
    "wof:placetype":"venue"
},
  "geometry": {"coordinates":[14.4270486832,48.3602256775],"type":"Point"}
}