{
  "type": "Feature",
  "properties": {
    "addr:full":"Herzog Friedrich-Str 7 Innsbruck Tirol 6020",
    "addr:housenumber":"7",
    "addr:postcode":"6020",
    "addr:street":"Friedrich-Str;Tirol",
    "iso:country":"AT",
    "sg:address":"Herzog Friedrich-Str 7",
    "sg:city":"Innsbruck",
    "sg:orig_category":"Bankomat-Standorte",
    "sg:phone":"+43 5 05333",
    "sg:postcode":"6020",
    "sg:province":"Tirol",
    "wof:name":"Bankomat d BTV Bank f Tirol und Vorarlberg AG",
    "wof:placetype":"venue"
},
  "geometry": {"coordinates":[11.3926267624,47.2686347961],"type":"Point"}
}