{
  "type": "Feature",
  "properties": {
    "addr:full":"GIP 1/4 Gro\u00dfpetersdorf Burgenland 7503",
    "addr:housenumber":"1 / 4",
    "addr:postcode":"7503",
    "addr:street":"Gip;Grosspetersdorf",
    "iso:country":"AT",
    "sg:address":"GIP 1/4",
    "sg:city":"Gro\u00dfpetersdorf",
    "sg:orig_category":"Fitnesscenter",
    "sg:phone":"+43 664 1536737",
    "sg:postcode":"7503",
    "sg:province":"Burgenland",
    "wof:name":"Wellness-Studio Easyfit",
    "wof:placetype":"venue"
},
  "geometry": {"coordinates":[12.1167001724,54.1500015259],"type":"Point"}
}