{
  "type": "Feature",
  "properties": {
    "addr:full":"Salzmannstr 13 Zell am See Salzburg 5700",
    "addr:housenumber":"13",
    "addr:postcode":"5700",
    "addr:street":"Salzmannstr;Salzburg",
    "iso:country":"AT",
    "sg:address":"Salzmannstr 13",
    "sg:city":"Zell am See",
    "sg:orig_category":"Optiker",
    "sg:phone":"+43 6542 73713",
    "sg:postcode":"5700",
    "sg:province":"Salzburg",
    "wof:name":"Kabiersch Sylvia",
    "wof:placetype":"venue"
},
  "geometry": {"coordinates":[12.7995882034,47.323841095],"type":"Point"}
}