{
  "type": "Feature",
  "properties": {
    "iso:country":"AT",
    "sg:address":"Sch\u00f6naug 17",
    "sg:city":"Graz",
    "sg:orig_category":"Exporteure U Importeure",
    "sg:phone":"+43 4331 6715890",
    "sg:postcode":"8010",
    "sg:province":"Steiermark",
    "wof:name":"Imex Import-Export",
    "wof:placetype":"venue"
},
  "geometry": {"coordinates":[15.4431800842,47.0685653687],"type":"Point"}
}