{
  "type": "Feature",
  "properties": {
    "addr:full":"Nonntaler Hauptstr 49 Salzburg Salzburg 5020",
    "addr:housenumber":"49",
    "addr:postcode":"5020",
    "addr:street":"Nonntaler Hauptstr;Salzburg",
    "iso:country":"AT",
    "sg:address":"Nonntaler Hauptstr 49",
    "sg:city":"Salzburg",
    "sg:orig_category":"Steuerberatung",
    "sg:phone":"+43 4366 26201850",
    "sg:postcode":"5020",
    "sg:province":"Salzburg",
    "sg:website":"dr-lohberger.at",
    "wof:name":"Lohberger Gerd Dr",
    "wof:placetype":"venue"
},
  "geometry": {"coordinates":[13.0509290695,47.7886047363],"type":"Point"}
}