{
  "type": "Feature",
  "properties": {
    "iso:country":"AT",
    "sg:address":"Emmerich-Berger-Str 9",
    "sg:city":"Gm\u00fcnd",
    "sg:orig_category":"Damenmoden",
    "sg:phone":"+43 2852 54509",
    "sg:postcode":"3950",
    "sg:province":"Nieder\u00f6sterreich",
    "wof:name":"Charles V\u00f6gele (Austria) AG",
    "wof:placetype":"venue"
},
  "geometry": {"coordinates":[14.9795694351,48.7656745911],"type":"Point"}
}