{
  "type": "Feature",
  "properties": {
    "addr:full":"Nachts\u00f6llberg 12 Westendorf Tirol 6363",
    "addr:housenumber":"12",
    "addr:postcode":"6363",
    "addr:street":"Nachtsoellberg;Tirol",
    "iso:country":"AT",
    "sg:address":"Nachts\u00f6llberg 12",
    "sg:city":"Westendorf",
    "sg:classifiers":[
        {
            "category":"Travel",
            "subcategory":"Hotels & Motels",
            "type":"Entertainment"
        }
    ],
    "sg:phone":"+43 5334 6495",
    "sg:postcode":"6363",
    "sg:province":"Tirol",
    "wof:name":"Hotel-Gasthof Sportalm & Schwaigeralm",
    "wof:placetype":"venue"
},
  "geometry": {"coordinates":[12.2147397995,47.4321594238],"type":"Point"}
}