{
  "type": "Feature",
  "properties": {
    "addr:full":"Freist\u00e4dter Str 328A Linz Ober\u00f6sterreich 4040",
    "addr:postcode":"4040",
    "addr:street":"Str 328A",
    "iso:country":"AT",
    "sg:address":"Freist\u00e4dter Str 328A",
    "sg:city":"Linz",
    "sg:orig_category":"Lebensmittel / Einzelhandel",
    "sg:phone":"+43 732 247730",
    "sg:postcode":"4040",
    "sg:province":"Ober\u00f6sterreich",
    "wof:name":"Zielpunkt Warenhandel GmbH & Co KG",
    "wof:placetype":"venue"
},
  "geometry": {"coordinates":[14.3163194656,48.3294563293],"type":"Point"}
}