{
  "type": "Feature",
  "properties": {
    "addr:full":"St. Georgener Hauptstr 181 St. Georgen am Steinfelde Nieder\u00f6sterreich 3151",
    "addr:housenumber":"181",
    "addr:postcode":"3151",
    "addr:street":"St. Georgener Hauptstr",
    "iso:country":"AT",
    "sg:address":"St. Georgener Hauptstr 181",
    "sg:city":"St. Georgen am Steinfelde",
    "sg:classifiers":[
        {
            "category":"Home & Garden",
            "subcategory":"Building Materials",
            "type":"Retail Goods"
        }
    ],
    "sg:phone":"+43 4327 42884046",
    "sg:postcode":"3151",
    "sg:province":"Nieder\u00f6sterreich",
    "sg:tags":[
        "baustoffe",
        "-material",
        "u"
    ],
    "wof:name":"Gererstorfer GesmbH",
    "wof:placetype":"venue"
},
  "geometry": {"coordinates":[15.6130447388,48.1324958801],"type":"Point"}
}