{
  "type": "Feature",
  "properties": {
    "iso:country":"AT",
    "sg:address":"Industriestr. 2",
    "sg:city":"St. Veit an der Glan",
    "sg:classifiers":[
        {
            "category":"Professional",
            "subcategory":"Engineering",
            "type":"Services"
        }
    ],
    "sg:phone":"+43 4342 1220260",
    "sg:postcode":"9300",
    "sg:province":"K\u00e4rnten",
    "sg:tags":[
        "machine",
        "-",
        "mechanical"
    ],
    "wof:name":"ALU-STAHL-GLAS GES.MBH ING. A. SAURITSCHNIG",
    "wof:placetype":"venue"
},
  "geometry": {"coordinates":[14.3577518463,46.7791061401],"type":"Point"}
}