{
  "type": "Feature",
  "properties": {
    "iso:country":"AT",
    "sg:address":"Alte Wiener Str 57",
    "sg:city":"Bruck an der Leitha",
    "sg:orig_category":"Tankstellen",
    "sg:phone":"+43 2162 62547",
    "sg:postcode":"2460",
    "sg:province":"Nieder\u00f6sterreich",
    "wof:name":"AVANTI TankstellenbetriebsgesmbH",
    "wof:placetype":"venue"
},
  "geometry": {"coordinates":[16.7667770386,48.0214271545],"type":"Point"}
}