{
  "type": "Feature",
  "properties": {
    "addr:full":"SIG Geb.2, Simmeringer Hauptstrasse 24 Wien Wien 1110",
    "addr:housenumber":"24",
    "addr:postcode":"1110",
    "addr:street":"Simmeringer Hauptstrasse",
    "iso:country":"AT",
    "sg:address":"SIG Geb.2, Simmeringer Hauptstrasse 24",
    "sg:city":"Wien",
    "sg:classifiers":[
        {
            "category":"Shopping",
            "subcategory":"Stationery & Office Supplies",
            "type":"Retail Goods"
        }
    ],
    "sg:phone":"+43 1 74040344",
    "sg:postcode":"1110",
    "sg:province":"Wien",
    "sg:tags":[
        "chemical",
        "plant",
        "planning"
    ],
    "sg:website":"vtu.com",
    "wof:name":"VTU-Engineering GmbH",
    "wof:placetype":"venue"
},
  "geometry": {"coordinates":[16.4197444916,48.1709709167],"type":"Point"}
}