{
  "type": "Feature",
  "properties": {
    "addr:full":"Wiener Str 1 Brunn am Gebirge Nieder\u00f6sterreich 2345",
    "addr:postcode":"2345",
    "iso:country":"AT",
    "sg:address":"Wiener Str 1",
    "sg:city":"Brunn am Gebirge",
    "sg:orig_category":"Banken U Sparkassen",
    "sg:phone":"+43 4350 50534720",
    "sg:postcode":"2345",
    "sg:province":"Nieder\u00f6sterreich",
    "wof:name":"Bank Austria Creditanstalt AG",
    "wof:placetype":"venue"
},
  "geometry": {"coordinates":[16.2853851318,48.1055603027],"type":"Point"}
}