{
  "type": "Feature",
  "properties": {
    "addr:full":"Hammerweg 27 Micheldorf in Ober\u00f6sterreich Ober\u00f6sterreich 4563",
    "addr:housenumber":"27",
    "addr:postcode":"4563",
    "addr:street":"Hammerweg",
    "iso:country":"AT",
    "sg:address":"Hammerweg 27",
    "sg:city":"Micheldorf in Ober\u00f6sterreich",
    "sg:orig_category":"Bestattungsunternehmen",
    "sg:phone":"+43 7582 62522",
    "sg:postcode":"4563",
    "sg:province":"Ober\u00f6sterreich",
    "wof:name":"Schwarzbauer Johann",
    "wof:placetype":"venue"
},
  "geometry": {"coordinates":[14.1328620911,47.8772888184],"type":"Point"}
}