{
  "type": "Feature",
  "properties": {
    "addr:full":"Siedlungsgasse 2a Wiesen Burgenland 7203",
    "addr:housenumber":"2a",
    "addr:postcode":"7203",
    "addr:street":"Siedlungsgasse",
    "iso:country":"AT",
    "sg:address":"Siedlungsgasse 2a",
    "sg:city":"Wiesen",
    "sg:orig_category":"Furniture, General",
    "sg:phone":"+43 2626 83250",
    "sg:postcode":"7203",
    "sg:province":"Burgenland",
    "sg:website":"pauschenwein.at",
    "wof:name":"Pauschenwein Creatives Wohnen KG",
    "wof:placetype":"venue"
},
  "geometry": {"coordinates":[16.3454971313,47.7396469116],"type":"Point"}
}