{
  "type": "Feature",
  "properties": {
    "iso:country":"AT",
    "sg:address":"Dornacher Str 35",
    "sg:city":"Linz",
    "sg:orig_category":"Hauptschulen",
    "sg:phone":"+43 732 750829",
    "sg:postcode":"4040",
    "sg:province":"Ober\u00f6sterreich",
    "wof:name":"Hauptschule 27 Bertha v Suttner Schule",
    "wof:placetype":"venue"
},
  "geometry": {"coordinates":[14.3040571213,48.3335075378],"type":"Point"}
}