{
  "type": "Feature",
  "properties": {
    "addr:full":"K\u00e4rntner Str 300 Leoben Steiermark 8700",
    "addr:housenumber":"300",
    "addr:postcode":"8700",
    "addr:street":"Str",
    "iso:country":"AT",
    "sg:address":"K\u00e4rntner Str 300",
    "sg:city":"Leoben",
    "sg:orig_category":"Autoersatzteile",
    "sg:phone":"+43 3842 247870",
    "sg:postcode":"8700",
    "sg:province":"Steiermark",
    "wof:name":"Forstinger Handel und Service GmbH",
    "wof:placetype":"venue"
},
  "geometry": {"coordinates":[15.0898256302,47.3745040894],"type":"Point"}
}