{
  "type": "Feature",
  "properties": {
    "iso:country":"AT",
    "sg:address":"Pasnatsch 270",
    "sg:city":"Ischgl",
    "sg:classifiers":[
        {
            "category":"Travel",
            "subcategory":"Hotels & Motels",
            "type":"Entertainment"
        }
    ],
    "sg:phone":"+43 5444 5609",
    "sg:postcode":"6561",
    "sg:province":"Tirol",
    "wof:name":"Lamtana",
    "wof:placetype":"venue"
},
  "geometry": {"coordinates":[10.28358078,47.0069656372],"type":"Point"}
}