{
  "type": "Feature",
  "properties": {
    "addr:full":"Heiligenkreuzer Gasse 3-5 Baden Nieder\u00f6sterreich 2500",
    "addr:housenumber":"3-5",
    "addr:postcode":"2500",
    "addr:street":"Heiligenkreuzer Gasse;Niederoesterreich",
    "iso:country":"AT",
    "sg:address":"Heiligenkreuzer Gasse 3-5",
    "sg:city":"Baden",
    "sg:classifiers":[
        {
            "category":"Bakery",
            "type":"Food & Drink"
        }
    ],
    "sg:phone":"+43 2252 435000",
    "sg:postcode":"2500",
    "sg:province":"Nieder\u00f6sterreich",
    "sg:tags":[
        "fresh",
        "pastry",
        "bread"
    ],
    "sg:website":"backhaus-annamuehle.at",
    "wof:name":"Backhaus Annam\u00fchle GmbH & Co KG",
    "wof:placetype":"venue"
},
  "geometry": {"coordinates":[16.2316741943,48.0070953369],"type":"Point"}
}