{
  "type": "Feature",
  "properties": {
    "addr:full":"D\u00f6lach 2 Hopfgarten in Defereggen Tirol 9961",
    "addr:housenumber":"2",
    "addr:postcode":"9961",
    "addr:street":"Doelach;Tirol",
    "iso:country":"AT",
    "sg:address":"D\u00f6lach 2",
    "sg:city":"Hopfgarten in Defereggen",
    "sg:classifiers":[
        {
            "category":"Manufacturing",
            "subcategory":"Wood Products",
            "type":"Manufacturing & Wholesale Goods"
        }
    ],
    "sg:phone":"+43 4872 5243",
    "sg:postcode":"9961",
    "sg:province":"Tirol",
    "sg:tags":[
        "gate",
        "made",
        "door"
    ],
    "wof:name":"Albert Patterer",
    "wof:placetype":"venue"
},
  "geometry": {"coordinates":[12.5194997787,46.9212799072],"type":"Point"}
}