{
  "type": "Feature",
  "properties": {
    "addr:full":"Nebersdorfer Hauptstr 89 Gro\u00dfwarasdorf Burgenland 7304",
    "addr:housenumber":"89",
    "addr:postcode":"7304",
    "addr:street":"Nebersdorfer Hauptstr",
    "iso:country":"AT",
    "sg:address":"Nebersdorfer Hauptstr 89",
    "sg:city":"Gro\u00dfwarasdorf",
    "sg:orig_category":"Banken U Sparkassen",
    "sg:phone":"+43 4326 142359",
    "sg:postcode":"7304",
    "sg:province":"Burgenland",
    "wof:name":"Raiffeisenbank Horitschon u Umgebung regGenmbH",
    "wof:placetype":"venue"
},
  "geometry": {"coordinates":[16.5700626373,47.5131149292],"type":"Point"}
}