{
  "type": "Feature",
  "properties": {
    "addr:full":"Nr 30 Hermagor K\u00e4rnten 9620",
    "addr:postcode":"9620",
    "addr:street":"Nr 30;Kaernten",
    "iso:country":"AT",
    "sg:address":"Nr 30",
    "sg:city":"Hermagor",
    "sg:orig_category":"Pensionen / Privatzimmer",
    "sg:phone":"+43 4282 2665",
    "sg:postcode":"9620",
    "sg:province":"K\u00e4rnten",
    "wof:name":"Kraker Heinrich",
    "wof:placetype":"venue"
},
  "geometry": {"coordinates":[13.3051300049,46.6695404053],"type":"Point"}
}