{
  "type": "Feature",
  "properties": {
    "addr:full":"Limmersdorfer Str 59 Klagenfurt K\u00e4rnten 9020",
    "addr:housenumber":"59",
    "addr:postcode":"9020",
    "addr:street":"Str;Kaernten",
    "iso:country":"AT",
    "sg:address":"Limmersdorfer Str 59",
    "sg:city":"Klagenfurt",
    "sg:orig_category":"Hundeabrichtung U -Schulen",
    "sg:phone":"+43 4346 371631",
    "sg:postcode":"9020",
    "sg:province":"K\u00e4rnten",
    "wof:name":"Hundeschule",
    "wof:placetype":"venue"
},
  "geometry": {"coordinates":[14.3881044388,46.6277542114],"type":"Point"}
}