{
  "type": "Feature",
  "properties": {
    "addr:full":"Altmannsdorfer Anger 3 Wien Wien 1120",
    "addr:housenumber":"3",
    "addr:postcode":"1120",
    "addr:street":"Altmannsdorfer Anger",
    "iso:country":"AT",
    "sg:address":"Altmannsdorfer Anger 3",
    "sg:city":"Wien",
    "sg:orig_category":"Psychologen",
    "sg:phone":"+43 1 8048274",
    "sg:postcode":"1120",
    "sg:province":"Wien",
    "wof:name":"Haiden Margit Dr",
    "wof:placetype":"venue"
},
  "geometry": {"coordinates":[16.3145809174,48.1737556458],"type":"Point"}
}