{
  "type": "Feature",
  "properties": {
    "addr:full":"Bahnhofstr 16 Vorchdorf Ober\u00f6sterreich 4655",
    "addr:postcode":"4655",
    "addr:street":"Bahnhofstr 16",
    "iso:country":"AT",
    "sg:address":"Bahnhofstr 16",
    "sg:city":"Vorchdorf",
    "sg:orig_category":"Textilwaren / Einzelhandel",
    "sg:phone":"+43 4376 1451538",
    "sg:postcode":"4655",
    "sg:province":"Ober\u00f6sterreich",
    "wof:name":"NKD",
    "wof:placetype":"venue"
},
  "geometry": {"coordinates":[13.9210653305,48.0011367798],"type":"Point"}
}