{
  "type": "Feature",
  "properties": {
    "iso:country":"AT",
    "sg:address":"Dorfstr 60",
    "sg:city":"St. Anton am Arlberg",
    "sg:classifiers":[
        {
            "category":"Travel",
            "subcategory":"Hotels & Motels",
            "type":"Entertainment"
        }
    ],
    "sg:phone":"+43 5446 2848",
    "sg:postcode":"6580",
    "sg:province":"Tirol",
    "wof:name":"Hotel Kristall",
    "wof:placetype":"venue"
},
  "geometry": {"coordinates":[10.266576767,47.1296043396],"type":"Point"}
}