{
  "type": "Feature",
  "properties": {
    "iso:country":"AT",
    "sg:address":"Nr 97",
    "sg:city":"St. Egyden",
    "sg:orig_category":"Lebensmittel / Einzelhandel",
    "sg:phone":"+43 4274 8214",
    "sg:postcode":"9536",
    "sg:province":"K\u00e4rnten",
    "wof:name":"Schwarcz Norbert",
    "wof:placetype":"venue"
},
  "geometry": {"coordinates":[14.0653963089,46.5760765076],"type":"Point"}
}