{
  "type": "Feature",
  "properties": {
    "addr:full":"Ketzerg 191/3/8 Perchtoldsdorf Nieder\u00f6sterreich 2380",
    "addr:housenumber":"191 / 3 / 8",
    "addr:postcode":"2380",
    "iso:country":"AT",
    "sg:address":"Ketzerg 191/3/8",
    "sg:city":"Perchtoldsdorf",
    "sg:orig_category":"Massagen",
    "sg:phone":"+43 664 3015656",
    "sg:postcode":"2380",
    "sg:province":"Nieder\u00f6sterreich",
    "wof:name":"Bruckner Wolfgang",
    "wof:placetype":"venue"
},
  "geometry": {"coordinates":[16.2652320862,48.1192970276],"type":"Point"}
}