{
  "type": "Feature",
  "properties": {
    "iso:country":"AT",
    "sg:address":"Nr 186",
    "sg:city":"Schwarzenberg am B\u00f6hmerwald",
    "sg:orig_category":"Elektroinstallationsunternehmen",
    "sg:phone":"+43 4372 80544",
    "sg:postcode":"4164",
    "sg:province":"Ober\u00f6sterreich",
    "wof:name":"Zinn\u00f6cker Albert",
    "wof:placetype":"venue"
},
  "geometry": {"coordinates":[9.5621795654,51.1460418701],"type":"Point"}
}