{
  "type": "Feature",
  "properties": {
    "addr:full":"Ringstr 50 Krems an der Donau Nieder\u00f6sterreich 3500",
    "addr:housenumber":"50",
    "addr:postcode":"3500",
    "addr:street":"Ringstr",
    "iso:country":"AT",
    "sg:address":"Ringstr 50",
    "sg:city":"Krems an der Donau",
    "sg:orig_category":"Nachhilfe U Lernbetreuung",
    "sg:phone":"+43 4327 3276104",
    "sg:postcode":"3500",
    "sg:province":"Nieder\u00f6sterreich",
    "wof:name":"Sch\u00fclerhilfe",
    "wof:placetype":"venue"
},
  "geometry": {"coordinates":[15.5979757309,48.4080924988],"type":"Point"}
}