{
  "type": "Feature",
  "properties": {
    "addr:full":"Bahnhofweg 5 Liezen Steiermark 8940",
    "addr:housenumber":"5",
    "addr:postcode":"8940",
    "addr:street":"Bahnhofweg",
    "iso:country":"AT",
    "sg:address":"Bahnhofweg 5",
    "sg:city":"Liezen",
    "sg:orig_category":"Telekommunikation",
    "sg:phone":"+43 800 699889",
    "sg:postcode":"8940",
    "sg:province":"Steiermark",
    "wof:name":"ONE World Liezen",
    "wof:placetype":"venue"
},
  "geometry": {"coordinates":[14.2428979874,47.5642127991],"type":"Point"}
}