{
  "type": "Feature",
  "properties": {
    "addr:full":"Schiffmeisterpl 6 Ybbs an der Donau Nieder\u00f6sterreich 3370",
    "addr:housenumber":"6",
    "addr:postcode":"3370",
    "addr:street":"Schiffmeisterpl",
    "iso:country":"AT",
    "sg:address":"Schiffmeisterpl 6",
    "sg:city":"Ybbs an der Donau",
    "sg:classifiers":[
        {
            "category":"Restaurant",
            "type":"Food & Drink"
        }
    ],
    "sg:phone":"+43 7412 56980",
    "sg:postcode":"3370",
    "sg:province":"Nieder\u00f6sterreich",
    "wof:name":"Giovanni Restaurant Betriebs GesmbH",
    "wof:placetype":"venue"
},
  "geometry": {"coordinates":[15.0857715607,48.176990509],"type":"Point"}
}