{
  "type": "Feature",
  "properties": {
    "addr:full":"M\u00fchlenstrasse 3 Amstetten Nieder\u00f6sterreich 3300",
    "addr:housenumber":"3",
    "addr:postcode":"3300",
    "addr:street":"Muehlenstrasse;Niederoesterreich",
    "iso:country":"AT",
    "sg:address":"M\u00fchlenstrasse 3",
    "sg:city":"Amstetten",
    "sg:classifiers":[
        {
            "category":"Health Services",
            "subcategory":"Nursing And Care Facility",
            "type":"Services"
        }
    ],
    "sg:phone":"+43 7472 63085",
    "sg:postcode":"3300",
    "sg:province":"Nieder\u00f6sterreich",
    "sg:tags":[
        "battery",
        "aid",
        "hearing"
    ],
    "sg:website":"schmidradler.at",
    "wof:name":"Optik Schmidradler G.m.b.H.",
    "wof:placetype":"venue"
},
  "geometry": {"coordinates":[14.8706607819,48.1244812012],"type":"Point"}
}