{
  "type": "Feature",
  "properties": {
    "addr:full":"Wiener Str 3/Top/OG/4 Wieselburg an der Erlauf Nieder\u00f6sterreich 3250",
    "addr:housenumber":"3 / top",
    "addr:postcode":"3250",
    "iso:country":"AT",
    "sg:address":"Wiener Str 3/Top/OG/4",
    "sg:city":"Wieselburg an der Erlauf",
    "sg:orig_category":"Fahrschulen",
    "sg:phone":"+43 4374 1655585",
    "sg:postcode":"3250",
    "sg:province":"Nieder\u00f6sterreich",
    "wof:name":"Easy Drivers Wieselburg - Au\u00dfenkursstelle von Ybbs, Fichtinger",
    "wof:placetype":"venue"
},
  "geometry": {"coordinates":[15.1380252838,48.1304283142],"type":"Point"}
}