{
  "type": "Feature",
  "properties": {
    "iso:country":"AT",
    "sg:address":"Pfarrg 61",
    "sg:city":"Wien",
    "sg:orig_category":"\u00c3\u201erzte / F Allgemeinmedizin",
    "sg:phone":"+43 1 6174603",
    "sg:postcode":"1230",
    "sg:province":"Wien",
    "wof:name":"Hoffmann Herbert Dr",
    "wof:placetype":"venue"
},
  "geometry": {"coordinates":[16.3451213837,48.1445960999],"type":"Point"}
}