{
  "type": "Feature",
  "properties": {
    "iso:country":"AT",
    "sg:address":"Platzl 1",
    "sg:city":"Lilienfeld",
    "sg:orig_category":"Non-Classified Establishments",
    "sg:phone":"+43 2762 526090",
    "sg:postcode":"3180",
    "sg:province":"Nieder\u00f6sterreich",
    "wof:name":"Kirchenbeitragsstelle",
    "wof:placetype":"venue"
},
  "geometry": {"coordinates":[15.59623909,48.0134506226],"type":"Point"}
}