{
  "type": "Feature",
  "properties": {
    "iso:country":"AT",
    "sg:address":"Nr 9a",
    "sg:city":"Seefeld in Tirol",
    "sg:classifiers":[
        {
            "category":"Travel",
            "subcategory":"Hotels & Motels",
            "type":"Entertainment"
        }
    ],
    "sg:phone":"+43 5212 4755",
    "sg:postcode":"6100",
    "sg:province":"Tirol",
    "wof:name":"Hotel garni Berghof",
    "wof:placetype":"venue"
},
  "geometry": {"coordinates":[166.9221496582,-0.5282999873],"type":"Point"}
}