{
  "type": "Feature",
  "properties": {
    "addr:full":"Sechshauser Str. 15  Wien Wien 1150",
    "addr:postcode":"1150",
    "addr:street":"Str. 15",
    "iso:country":"AT",
    "sg:address":"Sechshauser Str. 15 ",
    "sg:city":"Wien",
    "sg:classifiers":[
        {
            "category":"Home & Garden",
            "subcategory":"Home Furnishings",
            "type":"Retail Goods"
        }
    ],
    "sg:phone":"+43 4318 936514",
    "sg:postcode":"1150",
    "sg:province":"Wien",
    "sg:tags":[
        "household"
    ],
    "wof:name":"RUDOLF GEISELHART GES.MBH",
    "wof:placetype":"venue"
},
  "geometry": {"coordinates":[16.3349609375,48.1885757446],"type":"Point"}
}