{
  "type": "Feature",
  "properties": {
    "addr:full":"Hofsteigstr 49a Wolfurt Vorarlberg 6922",
    "addr:housenumber":"49a",
    "addr:postcode":"6922",
    "addr:street":"Hofsteigstr",
    "iso:country":"AT",
    "sg:address":"Hofsteigstr 49a",
    "sg:city":"Wolfurt",
    "sg:orig_category":"Transportunternehmen",
    "sg:phone":"+43 5574 64650",
    "sg:postcode":"6922",
    "sg:province":"Vorarlberg",
    "wof:name":"Gunz Alois",
    "wof:placetype":"venue"
},
  "geometry": {"coordinates":[9.7517337799,47.4592285156],"type":"Point"}
}