{
  "type": "Feature",
  "properties": {
    "iso:country":"AT",
    "sg:address":"Sagl 4",
    "sg:city":"K\u00f6ssen",
    "sg:orig_category":"Holzhandel",
    "sg:phone":"+43 5375 6793",
    "sg:postcode":"6345",
    "sg:province":"Tirol",
    "wof:name":"Haunholter Sebastian",
    "wof:placetype":"venue"
},
  "geometry": {"coordinates":[12.3894271851,47.6354904175],"type":"Point"}
}