{
  "type": "Feature",
  "properties": {
    "addr:full":"Nr 66 Kirchschlag in der Buckligen Welt Nieder\u00f6sterreich 2860",
    "addr:postcode":"2860",
    "addr:street":"Nr 66",
    "iso:country":"AT",
    "sg:address":"Nr 66",
    "sg:city":"Kirchschlag in der Buckligen Welt",
    "sg:orig_category":"Hufschmiede",
    "sg:phone":"+43 4366 44304933",
    "sg:postcode":"2860",
    "sg:province":"Nieder\u00f6sterreich",
    "wof:name":"Heitler Herbert",
    "wof:placetype":"venue"
},
  "geometry": {"coordinates":[16.2951545715,47.501991272],"type":"Point"}
}