{
  "type": "Feature",
  "properties": {
    "addr:full":"Lustenauer Str 53 Hohenems Vorarlberg 6845",
    "addr:postcode":"6845",
    "addr:street":"Str 53",
    "iso:country":"AT",
    "sg:address":"Lustenauer Str 53",
    "sg:city":"Hohenems",
    "sg:orig_category":"Werbeagenturen",
    "sg:phone":"+43 5576 4302010",
    "sg:postcode":"6845",
    "sg:province":"Vorarlberg",
    "wof:name":"WnM Lenzi KEG Werbeagentur",
    "wof:placetype":"venue"
},
  "geometry": {"coordinates":[9.6684446335,47.3635215759],"type":"Point"}
}