{
  "type": "Feature",
  "properties": {
    "iso:country":"AT",
    "sg:address":"Stuben 30",
    "sg:city":"Pfunds",
    "sg:classifiers":[
        {
            "category":"Park",
            "subcategory":"Provincial",
            "type":"Public Place"
        }
    ],
    "sg:phone":"+43 5474 5602",
    "sg:postcode":"6542",
    "sg:province":"Tirol",
    "sg:tags":[
        "u",
        "ski-",
        "snowboardschulen"
    ],
    "wof:name":"Schischule-Sport Monz",
    "wof:placetype":"venue"
},
  "geometry": {"coordinates":[10.535697937,46.968536377],"type":"Point"}
}