{
  "type": "Feature",
  "properties": {
    "addr:full":"Poschacherstr 35 Linz Ober\u00f6sterreich 4020",
    "addr:housenumber":"35",
    "addr:postcode":"4020",
    "addr:street":"Poschacherstr",
    "iso:country":"AT",
    "sg:address":"Poschacherstr 35",
    "sg:city":"Linz",
    "sg:orig_category":"Immobilienverwaltungen",
    "sg:phone":"+43 4373 26979",
    "sg:postcode":"4020",
    "sg:province":"Ober\u00f6sterreich",
    "wof:name":"Schwechater Hof Verm\u00f6gens- verwaltungsgesellschaft mbH",
    "wof:placetype":"venue"
},
  "geometry": {"coordinates":[14.3092384338,48.2861099243],"type":"Point"}
}