{
  "type": "Feature",
  "properties": {
    "iso:country":"AT",
    "sg:address":"Schr\u00f6pferpl 4",
    "sg:city":"Bad Ischl",
    "sg:orig_category":"Optiker",
    "sg:phone":"+43 6132 23617",
    "sg:postcode":"4820",
    "sg:province":"Ober\u00f6sterreich",
    "wof:name":"Optik Hahn GesmbH",
    "wof:placetype":"venue"
},
  "geometry": {"coordinates":[13.6257123947,47.711971283],"type":"Point"}
}