{
  "type": "Feature",
  "properties": {
    "addr:full":"Sandgasse 18 Herzogenburg Nieder\u00f6sterreich 3130",
    "addr:housenumber":"18",
    "addr:postcode":"3130",
    "addr:street":"Sandgasse",
    "iso:country":"AT",
    "sg:address":"Sandgasse 18",
    "sg:city":"Herzogenburg",
    "sg:classifiers":[
        {
            "category":"Manufacturing",
            "subcategory":"Glass & Minerals",
            "type":"Manufacturing & Wholesale Goods"
        }
    ],
    "sg:phone":"+43 2782 823480",
    "sg:postcode":"3130",
    "sg:province":"Nieder\u00f6sterreich",
    "sg:tags":[
        "flat",
        "processed"
    ],
    "wof:name":"Kurt Mayer KG",
    "wof:placetype":"venue"
},
  "geometry": {"coordinates":[15.7190732956,48.2794494629],"type":"Point"}
}