{
  "type": "Feature",
  "properties": {
    "addr:full":"M\u00fchlg 41 Gols Burgenland 7122",
    "addr:housenumber":"41",
    "addr:postcode":"7122",
    "addr:street":"Muehlg",
    "iso:country":"AT",
    "sg:address":"M\u00fchlg 41",
    "sg:city":"Gols",
    "sg:orig_category":"Weine / Einzelhandel",
    "sg:phone":"+43 2173 2544",
    "sg:postcode":"7122",
    "sg:province":"Burgenland",
    "wof:name":"Leitner Helmut",
    "wof:placetype":"venue"
},
  "geometry": {"coordinates":[16.9098987579,47.8975830078],"type":"Point"}
}