{
  "type": "Feature",
  "properties": {
    "addr:full":"Untere Landstr 10 Krems an der Donau Nieder\u00f6sterreich 3500",
    "addr:housenumber":"10",
    "addr:postcode":"3500",
    "addr:street":"Untere Landstr",
    "iso:country":"AT",
    "sg:address":"Untere Landstr 10",
    "sg:city":"Krems an der Donau",
    "sg:orig_category":"Telekommunikation",
    "sg:phone":"+43 676 20800",
    "sg:postcode":"3500",
    "sg:province":"Nieder\u00f6sterreich",
    "wof:name":"T-Mobile Krems",
    "wof:placetype":"venue"
},
  "geometry": {"coordinates":[15.5987434387,48.410900116],"type":"Point"}
}