{
  "type": "Feature",
  "properties": {
    "addr:full":"Gewerbeparkstr 105/15 Theresienfeld Nieder\u00f6sterreich 2604",
    "addr:housenumber":"105 / 15",
    "addr:postcode":"2604",
    "iso:country":"AT",
    "sg:address":"Gewerbeparkstr 105/15",
    "sg:city":"Theresienfeld",
    "sg:orig_category":"Gitterroste",
    "sg:phone":"+43 2622 71912",
    "sg:postcode":"2604",
    "sg:province":"Nieder\u00f6sterreich",
    "wof:name":"Lichtgitter Service Center OTW GmbH",
    "wof:placetype":"venue"
},
  "geometry": {"coordinates":[16.2305793762,47.8641586304],"type":"Point"}
}