{
  "type": "Feature",
  "properties": {
    "iso:country":"AT",
    "sg:address":"Weinschenk 15",
    "sg:city":"Waldhausen im Strudengau",
    "sg:classifiers":[
        {
            "category":"Home & Garden",
            "subcategory":"Household Appliances",
            "type":"Retail Goods"
        }
    ],
    "sg:phone":"+43 7260 4445",
    "sg:postcode":"4391",
    "sg:province":"Ober\u00f6sterreich",
    "sg:tags":[
        "electric"
    ],
    "sg:website":"brennerdienst.at",
    "wof:name":"Berthold Furtlehner",
    "wof:placetype":"venue"
},
  "geometry": {"coordinates":[14.9481801987,48.2729988098],"type":"Point"}
}