{
  "type": "Feature",
  "properties": {
    "addr:full":"Michelbeuerng 3 Wien Wien 1090",
    "addr:housenumber":"3",
    "addr:postcode":"1090",
    "addr:street":"Michelbeuerng",
    "iso:country":"AT",
    "sg:address":"Michelbeuerng 3",
    "sg:city":"Wien",
    "sg:orig_category":"Ingenieurkonsulenten / Zivilingenieure",
    "sg:phone":"+43 1 4081794",
    "sg:postcode":"1090",
    "sg:province":"Wien",
    "wof:name":"Schmid Christa Dipl-Ing",
    "wof:placetype":"venue"
},
  "geometry": {"coordinates":[16.3521175385,48.2215003967],"type":"Point"}
}