{
  "type": "Feature",
  "properties": {
    "iso:country":"AT",
    "sg:address":"Weyerstr. 350",
    "sg:city":"Bramberg am Wildkogel",
    "sg:classifiers":[
        {
            "category":"Shopping",
            "type":"Retail Goods"
        }
    ],
    "sg:phone":"+43 4365 667366",
    "sg:postcode":"5733",
    "sg:province":"Salzburg",
    "sg:tags":[
        "finished",
        "-",
        "metallic"
    ],
    "wof:name":"ANTON EDER GMBH",
    "wof:placetype":"venue"
},
  "geometry": {"coordinates":[12.3337306976,47.2665176392],"type":"Point"}
}