{
  "type": "Feature",
  "properties": {
    "addr:full":"H\u00f6henstr 4 Henndorf am Wallersee Salzburg 5302",
    "addr:housenumber":"4",
    "addr:postcode":"5302",
    "addr:street":"Hoehenstr",
    "iso:country":"AT",
    "sg:address":"H\u00f6henstr 4",
    "sg:city":"Henndorf am Wallersee",
    "sg:orig_category":"Autoersatzteile",
    "sg:phone":"+43 4362 1420003",
    "sg:postcode":"5302",
    "sg:province":"Salzburg",
    "wof:name":"Hella Handel Austria GmbH",
    "wof:placetype":"venue"
},
  "geometry": {"coordinates":[13.1823301315,47.8969497681],"type":"Point"}
}