{
  "type": "Feature",
  "properties": {
    "addr:full":"Klagenfurter Str 68 Villach K\u00e4rnten 9500",
    "addr:housenumber":"68",
    "addr:postcode":"9500",
    "addr:street":"Str;Kaernten",
    "iso:country":"AT",
    "sg:address":"Klagenfurter Str 68",
    "sg:city":"Villach",
    "sg:orig_category":"Offsetdruckereien",
    "sg:phone":"+43 4342 4289041",
    "sg:postcode":"9500",
    "sg:province":"K\u00e4rnten",
    "wof:name":"Kreiner Druck- u VerlagsgesmbH",
    "wof:placetype":"venue"
},
  "geometry": {"coordinates":[13.8582601547,46.6188926697],"type":"Point"}
}