{
  "type": "Feature",
  "properties": {
    "addr:full":"M\u00fcnchner Bundesstrasse 121 Salzburg Salzburg 5020",
    "addr:housenumber":"121",
    "addr:postcode":"5020",
    "addr:street":"Bundesstrasse;Salzburg",
    "iso:country":"AT",
    "sg:address":"M\u00fcnchner Bundesstrasse 121",
    "sg:city":"Salzburg",
    "sg:orig_category":"Chemico-Technical Articles",
    "sg:phone":"+43 662 4315410",
    "sg:postcode":"5020",
    "sg:province":"Salzburg",
    "sg:website":"poro.at",
    "wof:name":"Pointner & Rothsch\u00e4dl Chemikalien Produktions- und Handelsges.m.b.H.",
    "wof:placetype":"venue"
},
  "geometry": {"coordinates":[13.0433769226,47.8006744385],"type":"Point"}
}