{
  "type": "Feature",
  "properties": {
    "iso:country":"AT",
    "sg:address":"Nr 5",
    "sg:city":"Treglwang",
    "sg:orig_category":"Schneidereien",
    "sg:phone":"+43 676 6175620",
    "sg:postcode":"8782",
    "sg:province":"Steiermark",
    "wof:name":"Schneiderei Sprung",
    "wof:placetype":"venue"
},
  "geometry": {"coordinates":[14.5917663574,47.4753799438],"type":"Point"}
}