{
  "type": "Feature",
  "properties": {
    "addr:full":"Ritter-Waldauf-Str 32 Wattens Tirol 6112",
    "addr:housenumber":"32",
    "addr:postcode":"6112",
    "addr:street":"Ritter-Waldauf-Str;Tirol",
    "iso:country":"AT",
    "sg:address":"Ritter-Waldauf-Str 32",
    "sg:city":"Wattens",
    "sg:orig_category":"Immobilienverwaltungen",
    "sg:phone":"+43 4352 2457855",
    "sg:postcode":"6112",
    "sg:province":"Tirol",
    "wof:name":"Immorealit\u00e4ten GmbH",
    "wof:placetype":"venue"
},
  "geometry": {"coordinates":[11.5824804306,47.2971191406],"type":"Point"}
}