{
  "type": "Feature",
  "properties": {
    "addr:full":"Fraueng 1 Knittelfeld Steiermark 8720",
    "addr:housenumber":"1",
    "addr:postcode":"8720",
    "addr:street":"Fraueng",
    "iso:country":"AT",
    "sg:address":"Fraueng 1",
    "sg:city":"Knittelfeld",
    "sg:orig_category":"Immobilienmakler",
    "sg:phone":"+43 3512 73400",
    "sg:postcode":"8720",
    "sg:province":"Steiermark",
    "wof:name":"ZeSch Immobilienb\u00fcro GmbH - Immobilienmakler und Investmentberatung",
    "wof:placetype":"venue"
},
  "geometry": {"coordinates":[14.8292417526,47.2151145935],"type":"Point"}
}