{
  "type": "Feature",
  "properties": {
    "addr:full":"D\u00f6blinger Hauptstr 34 Wien Wien 1190",
    "addr:housenumber":"34",
    "addr:postcode":"1190",
    "addr:street":"Hauptstr",
    "iso:country":"AT",
    "sg:address":"D\u00f6blinger Hauptstr 34",
    "sg:city":"Wien",
    "sg:classifiers":[
        {
            "category":"Restaurant",
            "type":"Food & Drink"
        }
    ],
    "sg:phone":"+43 4313 684468",
    "sg:postcode":"1190",
    "sg:province":"Wien",
    "sg:tags":[
        "pizzeria"
    ],
    "wof:name":"MONTE CHRISTO",
    "wof:placetype":"venue"
},
  "geometry": {"coordinates":[16.3533306122,48.2354621887],"type":"Point"}
}