{
  "type": "Feature",
  "properties": {
    "addr:full":"Birkachweg 13 Knittelfeld Steiermark 8720",
    "addr:housenumber":"13",
    "addr:postcode":"8720",
    "addr:street":"Birkachweg",
    "iso:country":"AT",
    "sg:address":"Birkachweg 13",
    "sg:city":"Knittelfeld",
    "sg:orig_category":"Pensionen / Privatzimmer",
    "sg:phone":"+43 4335 1284583",
    "sg:postcode":"8720",
    "sg:province":"Steiermark",
    "wof:name":"Schindelbacher Theresia",
    "wof:placetype":"venue"
},
  "geometry": {"coordinates":[14.7786560059,47.2220993042],"type":"Point"}
}