{
  "type": "Feature",
  "properties": {
    "iso:country":"AT",
    "sg:address":"Gro\u00df Weikersdorfer Strasse 29",
    "sg:city":"Niederru\u00dfbach",
    "sg:classifiers":[
        {
            "category":"Professional",
            "subcategory":"Computer Services",
            "type":"Services"
        }
    ],
    "sg:phone":"+43 664 1416935",
    "sg:postcode":"3702",
    "sg:province":"Nieder\u00f6sterreich",
    "sg:tags":[
        "services",
        "consulting",
        "internet"
    ],
    "sg:website":"evos.at",
    "wof:name":"Edv EVOS",
    "wof:placetype":"venue"
},
  "geometry": {"coordinates":[-83.3486022949,43.8284263611],"type":"Point"}
}