{
  "type": "Feature",
  "properties": {
    "addr:full":"Bahnhofg\u00fcrtel 65 Graz Steiermark 8020",
    "addr:housenumber":"65",
    "addr:postcode":"8020",
    "addr:street":"Bahnhofguertel",
    "iso:country":"AT",
    "sg:address":"Bahnhofg\u00fcrtel 65",
    "sg:city":"Graz",
    "sg:classifiers":[
        {
            "category":"Transit Center",
            "subcategory":"Freight",
            "type":"Transportation"
        }
    ],
    "sg:phone":"+43 316 711762",
    "sg:postcode":"8020",
    "sg:province":"Steiermark",
    "sg:tags":[
        "forwarding",
        "agency"
    ],
    "wof:name":"Spedition, Lagerei und Bef\u00f6rderung von G\u00fctern mit Kraftfahrzeugen Alois Herbst",
    "wof:placetype":"venue"
},
  "geometry": {"coordinates":[15.4111499786,47.0689201355],"type":"Point"}
}