{
  "type": "Feature",
  "properties": {
    "addr:full":"Swarovskistr 22 Schwaz Tirol 6130",
    "addr:housenumber":"22",
    "addr:postcode":"6130",
    "addr:street":"Swarovskistr;Tirol",
    "iso:country":"AT",
    "sg:address":"Swarovskistr 22",
    "sg:city":"Schwaz",
    "sg:orig_category":"Bildungsservice / Allgemeine Informationsstellen",
    "sg:phone":"+43 4351 259660",
    "sg:postcode":"6130",
    "sg:province":"Tirol",
    "wof:name":"Berufsinformationszentrum Schwaz",
    "wof:placetype":"venue"
},
  "geometry": {"coordinates":[11.7019805908,47.3465003967],"type":"Point"}
}