{
  "type": "Feature",
  "properties": {
    "iso:country":"AT",
    "sg:address":"Baumgarten 39",
    "sg:city":"W\u00f6rgl",
    "sg:orig_category":"Isolierungen",
    "sg:phone":"+43 5332 56767",
    "sg:postcode":"6300",
    "sg:province":"Tirol",
    "wof:name":"Sulzenbacher Ernst",
    "wof:placetype":"venue"
},
  "geometry": {"coordinates":[12.0463237762,47.5093421936],"type":"Point"}
}