{
  "type": "Feature",
  "properties": {
    "addr:full":"Steinbergstr 50 Niederhollabrunn Nieder\u00f6sterreich 2004",
    "addr:housenumber":"50",
    "addr:postcode":"2004",
    "addr:street":"Steinbergstr;Niederoesterreich",
    "iso:country":"AT",
    "sg:address":"Steinbergstr 50",
    "sg:city":"Niederhollabrunn",
    "sg:orig_category":"Werbeagenturen",
    "sg:phone":"+43 2269 24048",
    "sg:postcode":"2004",
    "sg:province":"Nieder\u00f6sterreich",
    "wof:name":"Wareka Eveline",
    "wof:placetype":"venue"
},
  "geometry": {"coordinates":[16.3055706024,48.4473991394],"type":"Point"}
}