{
  "type": "Feature",
  "properties": {
    "iso:country":"AT",
    "sg:address":"Obermarktstr 74a",
    "sg:city":"Telfs",
    "sg:orig_category":"Zahntechnische Laboratorien",
    "sg:phone":"+43 4352 6267725",
    "sg:postcode":"6410",
    "sg:province":"Tirol",
    "wof:name":"Zahntechnik K\u00f6ll",
    "wof:placetype":"venue"
},
  "geometry": {"coordinates":[11.0657596588,47.3096694946],"type":"Point"}
}