{
  "type": "Feature",
  "properties": {
    "addr:full":"Salzbergstr 8 Absam Tirol 6067",
    "addr:housenumber":"8",
    "addr:postcode":"6067",
    "addr:street":"Salzbergstr;Tirol",
    "iso:country":"AT",
    "sg:address":"Salzbergstr 8",
    "sg:city":"Absam",
    "sg:orig_category":"Dachdeckereien",
    "sg:phone":"+43 4352 2356168",
    "sg:postcode":"6067",
    "sg:province":"Tirol",
    "wof:name":"Wagner Michael",
    "wof:placetype":"venue"
},
  "geometry": {"coordinates":[11.5132856369,47.2909393311],"type":"Point"}
}