{
  "type": "Feature",
  "properties": {
    "addr:full":"Enzersberg 98 Thalgau Salzburg 5303",
    "addr:housenumber":"98",
    "addr:postcode":"5303",
    "addr:street":"Enzersberg;Salzburg",
    "iso:country":"AT",
    "sg:address":"Enzersberg 98",
    "sg:city":"Thalgau",
    "sg:orig_category":"Geologie",
    "sg:phone":"+43 6235 6230",
    "sg:postcode":"5303",
    "sg:province":"Salzburg",
    "wof:name":"Winkler Heinrich Dr GEO Win",
    "wof:placetype":"venue"
},
  "geometry": {"coordinates":[13.1954441071,47.8485679626],"type":"Point"}
}