{
  "type": "Feature",
  "properties": {
    "addr:full":"Langenstegstr 14 Hard Vorarlberg 6971",
    "addr:housenumber":"14",
    "addr:postcode":"6971",
    "addr:street":"Langenstegstr",
    "iso:country":"AT",
    "sg:address":"Langenstegstr 14",
    "sg:city":"Hard",
    "sg:orig_category":"Marketingberatung",
    "sg:phone":"+43 5574 859430",
    "sg:postcode":"6971",
    "sg:province":"Vorarlberg",
    "wof:name":"Mediawerkstatt Consulting GmbH",
    "wof:placetype":"venue"
},
  "geometry": {"coordinates":[9.7105302811,47.4837112427],"type":"Point"}
}