{
  "type": "Feature",
  "properties": {
    "iso:country":"AT",
    "sg:address":"Nr 41",
    "sg:city":"Aich-Assach",
    "sg:orig_category":"Imkereien",
    "sg:phone":"+43 4336 864430",
    "sg:postcode":"8966",
    "sg:province":"Steiermark",
    "wof:name":"Posch Erich",
    "wof:placetype":"venue"
},
  "geometry": {"coordinates":[13.8196287155,47.4196052551],"type":"Point"}
}