{
  "type": "Feature",
  "properties": {
    "addr:full":"Hauptstr 17 Pulkau Nieder\u00f6sterreich 3741",
    "addr:housenumber":"17",
    "addr:postcode":"3741",
    "addr:street":"Hauptstr",
    "iso:country":"AT",
    "sg:address":"Hauptstr 17",
    "sg:city":"Pulkau",
    "sg:orig_category":"Massagen",
    "sg:phone":"+43 2946 2852",
    "sg:postcode":"3741",
    "sg:province":"Nieder\u00f6sterreich",
    "wof:name":"Massagestudio",
    "wof:placetype":"venue"
},
  "geometry": {"coordinates":[15.8637609482,48.7041549683],"type":"Point"}
}