{
  "type": "Feature",
  "properties": {
    "addr:full":"Innrain 42a Innsbruck Tirol 6020",
    "addr:housenumber":"42a",
    "addr:postcode":"6020",
    "addr:street":"Innrain;Tirol",
    "iso:country":"AT",
    "sg:address":"Innrain 42a",
    "sg:city":"Innsbruck",
    "sg:classifiers":[
        {
            "category":"Restaurant",
            "type":"Food & Drink"
        }
    ],
    "sg:phone":"+43 512 589432",
    "sg:postcode":"6020",
    "sg:province":"Tirol",
    "wof:name":"Cafe-Restaurant Johannesst\u00fcberl",
    "wof:placetype":"venue"
},
  "geometry": {"coordinates":[11.3876886368,47.264831543],"type":"Point"}
}