{
  "type": "Feature",
  "properties": {
    "addr:full":"Ludwig-Bieringer-Pl 1 Wals Salzburg 5071",
    "addr:housenumber":"1",
    "addr:postcode":"5071",
    "addr:street":"Ludwig-Bieringer-Pl;Salzburg",
    "iso:country":"AT",
    "sg:address":"Ludwig-Bieringer-Pl 1",
    "sg:city":"Wals",
    "sg:classifiers":[
        {
            "category":"Organizations",
            "subcategory":"Community Association",
            "type":"Services"
        }
    ],
    "sg:phone":"+43 4366 28550820",
    "sg:postcode":"5071",
    "sg:province":"Salzburg",
    "sg:tags":[
        "relation",
        "public"
    ],
    "wof:name":"Salcon Public Relations u Werbeproduktions- u BeratungsgesmbH",
    "wof:placetype":"venue"
},
  "geometry": {"coordinates":[12.9867248535,47.7939758301],"type":"Point"}
}