{
  "type": "Feature",
  "properties": {
    "iso:country":"AT",
    "sg:address":"Siccardsburgg 56",
    "sg:city":"Wien",
    "sg:orig_category":"Eisenwaren",
    "sg:phone":"+43 1 6040167",
    "sg:postcode":"1100",
    "sg:province":"Wien",
    "wof:name":"Thaler Stefan",
    "wof:placetype":"venue"
},
  "geometry": {"coordinates":[16.3699626923,48.1721191406],"type":"Point"}
}