{
  "type": "Feature",
  "properties": {
    "addr:full":"Morzing 5 Mariazell Steiermark 8630",
    "addr:housenumber":"5",
    "addr:postcode":"8630",
    "addr:street":"Morzing",
    "iso:country":"AT",
    "sg:address":"Morzing 5",
    "sg:city":"Mariazell",
    "sg:orig_category":"Volksschulen",
    "sg:phone":"+43 3882 2167",
    "sg:postcode":"8630",
    "sg:province":"Steiermark",
    "wof:name":"Volksschule",
    "wof:placetype":"venue"
},
  "geometry": {"coordinates":[15.3173656464,47.7719841003],"type":"Point"}
}