{
  "type": "Feature",
  "properties": {
    "addr:full":"Zillingtaler Str 1 Steinbrunn Burgenland 7035",
    "addr:housenumber":"1",
    "addr:postcode":"7035",
    "addr:street":"Str",
    "iso:country":"AT",
    "sg:address":"Zillingtaler Str 1",
    "sg:city":"Steinbrunn",
    "sg:orig_category":"Autoreparatur",
    "sg:phone":"+43 4326 88722620",
    "sg:postcode":"7035",
    "sg:province":"Burgenland",
    "wof:name":"Ullrich Peter u Robert OHG",
    "wof:placetype":"venue"
},
  "geometry": {"coordinates":[16.4168739319,47.8321418762],"type":"Point"}
}