{
  "type": "Feature",
  "properties": {
    "addr:full":"Bahnhofstr 4 Ottensheim Ober\u00f6sterreich 4100",
    "addr:housenumber":"4",
    "addr:postcode":"4100",
    "addr:street":"Bahnhofstr",
    "iso:country":"AT",
    "sg:address":"Bahnhofstr 4",
    "sg:city":"Ottensheim",
    "sg:orig_category":"Feldenkraismethode",
    "sg:phone":"+43 4367 682161807",
    "sg:postcode":"4100",
    "sg:province":"Ober\u00f6sterreich",
    "wof:name":"Weinberger Stefan",
    "wof:placetype":"venue"
},
  "geometry": {"coordinates":[14.1760292053,48.3325157166],"type":"Point"}
}