{
  "type": "Feature",
  "properties": {
    "iso:country":"AT",
    "sg:address":"Sonnenburgstr 3",
    "sg:city":"Innsbruck",
    "sg:orig_category":"Werbeagenturen",
    "sg:phone":"+43 512 561900",
    "sg:postcode":"6020",
    "sg:province":"Tirol",
    "wof:name":"Mediacontact Dr Bernhard Platzer",
    "wof:placetype":"venue"
},
  "geometry": {"coordinates":[11.3932657242,47.258266449],"type":"Point"}
}