{
  "type": "Feature",
  "properties": {
    "addr:full":"Walser Str 80 Mittelberg Vorarlberg 6993",
    "addr:housenumber":"80",
    "addr:postcode":"6993",
    "addr:street":"Str",
    "iso:country":"AT",
    "sg:address":"Walser Str 80",
    "sg:city":"Mittelberg",
    "sg:orig_category":"Pensionen / Privatzimmer",
    "sg:phone":"+43 4355 175719",
    "sg:postcode":"6993",
    "sg:province":"Vorarlberg",
    "wof:name":"G\u00e4stehaus Neue Post",
    "wof:placetype":"venue"
},
  "geometry": {"coordinates":[10.1651554108,47.3385772705],"type":"Point"}
}