{
  "type": "Feature",
  "properties": {
    "iso:country":"AT",
    "sg:address":"K\u00e4rntner Str 149",
    "sg:city":"Leoben",
    "sg:orig_category":"Tankstellen",
    "sg:phone":"+43 4338 4244101",
    "sg:postcode":"8700",
    "sg:province":"Steiermark",
    "wof:name":"OMV AG",
    "wof:placetype":"venue"
},
  "geometry": {"coordinates":[15.1019496918,47.3780937195],"type":"Point"}
}