{
  "type": "Feature",
  "properties": {
    "addr:full":"Mastalierg 21 Bad Ischl Ober\u00f6sterreich 4820",
    "addr:housenumber":"21",
    "addr:postcode":"4820",
    "addr:street":"Mastalierg",
    "iso:country":"AT",
    "sg:address":"Mastalierg 21",
    "sg:city":"Bad Ischl",
    "sg:orig_category":"Pensionen / Privatzimmer",
    "sg:phone":"+43 6132 23104",
    "sg:postcode":"4820",
    "sg:province":"Ober\u00f6sterreich",
    "wof:name":"Stadlmann Josefa",
    "wof:placetype":"venue"
},
  "geometry": {"coordinates":[13.6058673859,47.7087478638],"type":"Point"}
}