{
  "type": "Feature",
  "properties": {
    "iso:country":"AT",
    "sg:address":"Nr 33",
    "sg:city":"Gr\u00fcnbach",
    "sg:orig_category":"Appartements / Ferienwohnungen",
    "sg:phone":"+43 4379 4272888",
    "sg:postcode":"4264",
    "sg:province":"Ober\u00f6sterreich",
    "wof:name":"Nadelbauer Familie Jezek",
    "wof:placetype":"venue"
},
  "geometry": {"coordinates":[14.5361270905,48.5379142761],"type":"Point"}
}