{
  "type": "Feature",
  "properties": {
    "iso:country":"AT",
    "sg:address":"Taborstr 52A/10",
    "sg:city":"Wien",
    "sg:classifiers":[
        {
            "category":"Communications",
            "subcategory":"Film & Video Production",
            "type":"Services"
        }
    ],
    "sg:phone":"+43 1 2143230",
    "sg:postcode":"1020",
    "sg:province":"Wien",
    "sg:tags":[
        "multimedia"
    ],
    "wof:name":"Electronic Team - Ing Stefan Rozporka",
    "wof:placetype":"venue"
},
  "geometry": {"coordinates":[16.3818721771,48.2206993103],"type":"Point"}
}