{
  "type": "Feature",
  "properties": {
    "addr:full":"Hauptstr 66 Petronell Nieder\u00f6sterreich 2404",
    "addr:housenumber":"66",
    "addr:postcode":"2404",
    "addr:street":"Hauptstr;Niederoesterreich",
    "iso:country":"AT",
    "sg:address":"Hauptstr 66",
    "sg:city":"Petronell",
    "sg:orig_category":"Tankstellen",
    "sg:phone":"+43 2163 2281",
    "sg:postcode":"2404",
    "sg:province":"Nieder\u00f6sterreich",
    "wof:name":"Diskont Tankstelle",
    "wof:placetype":"venue"
},
  "geometry": {"coordinates":[16.8722610474,48.1139945984],"type":"Point"}
}