{
  "type": "Feature",
  "properties": {
    "addr:full":"Staudenstr 32 Altach Vorarlberg 6844",
    "addr:housenumber":"32",
    "addr:postcode":"6844",
    "addr:street":"Staudenstr",
    "iso:country":"AT",
    "sg:address":"Staudenstr 32",
    "sg:city":"Altach",
    "sg:orig_category":"Garderobeeinrichtungen",
    "sg:phone":"+43 5576 732060",
    "sg:postcode":"6844",
    "sg:province":"Vorarlberg",
    "wof:name":"V\u00f6gel Anton GesmbH & Co KG",
    "wof:placetype":"venue"
},
  "geometry": {"coordinates":[9.656378746,47.3621940613],"type":"Point"}
}