{
  "type": "Feature",
  "properties": {
    "addr:full":"Mariahilfer Str 192 Wien Wien 1150",
    "addr:housenumber":"192",
    "addr:postcode":"1150",
    "iso:country":"AT",
    "sg:address":"Mariahilfer Str 192",
    "sg:city":"Wien",
    "sg:orig_category":"Tabaktrafiken",
    "sg:phone":"+43 1 8932661",
    "sg:postcode":"1150",
    "sg:province":"Wien",
    "wof:name":"Goldberg Hermann",
    "wof:placetype":"venue"
},
  "geometry": {"coordinates":[16.3268451691,48.1915245056],"type":"Point"}
}