{
  "type": "Feature",
  "properties": {
    "addr:full":"Am Kirchwald 522 Seefeld in Tirol Tirol 6100",
    "addr:housenumber":"522",
    "addr:postcode":"6100",
    "addr:street":"Am Kirchwald;Tirol",
    "iso:country":"AT",
    "sg:address":"Am Kirchwald 522",
    "sg:city":"Seefeld in Tirol",
    "sg:orig_category":"Appartements / Ferienwohnungen",
    "sg:phone":"+43 5212 2748",
    "sg:postcode":"6100",
    "sg:province":"Tirol",
    "wof:name":"Haus St Sigmund",
    "wof:placetype":"venue"
},
  "geometry": {"coordinates":[11.1796703339,47.3292961121],"type":"Point"}
}