{
  "type": "Feature",
  "properties": {
    "iso:country":"AT",
    "sg:address":"Nr 70",
    "sg:city":"P\u00f6llau",
    "sg:orig_category":"Gemeinden",
    "sg:phone":"+43 3335 33600",
    "sg:postcode":"8225",
    "sg:province":"Steiermark",
    "wof:name":"Gemeindeamt Sonnhofen",
    "wof:placetype":"venue"
},
  "geometry": {"coordinates":[166.9221496582,-0.5282999873],"type":"Point"}
}