{
  "type": "Feature",
  "properties": {
    "iso:country":"AT",
    "sg:address":"Bahnhofstrasse 12-13",
    "sg:city":"Vandans",
    "sg:classifiers":[
        {
            "category":"Home & Garden",
            "subcategory":"Home Furnishings",
            "type":"Retail Goods"
        }
    ],
    "sg:phone":"+43 5556 73701",
    "sg:postcode":"6773",
    "sg:province":"Vorarlberg",
    "sg:tags":[
        "bathroom",
        "wc",
        "fitting"
    ],
    "wof:name":"Franz Egele",
    "wof:placetype":"venue"
},
  "geometry": {"coordinates":[9.8648281097,47.096496582],"type":"Point"}
}