{
  "type": "Feature",
  "properties": {
    "addr:full":"Ruckerg 26 Wien Wien 1120",
    "addr:housenumber":"26",
    "addr:postcode":"1120",
    "addr:street":"Ruckerg",
    "iso:country":"AT",
    "sg:address":"Ruckerg 26",
    "sg:city":"Wien",
    "sg:orig_category":"Finanz- U Wirtschaftsberatung",
    "sg:phone":"+43 4318 158008",
    "sg:postcode":"1120",
    "sg:province":"Wien",
    "sg:website":"pfs.at",
    "wof:name":"PFS Immobilien Management GmbH",
    "wof:placetype":"venue"
},
  "geometry": {"coordinates":[16.3267593384,48.1802177429],"type":"Point"}
}