{
  "type": "Feature",
  "properties": {
    "addr:full":"Im Forst 29 Scharnstein Ober\u00f6sterreich 4644",
    "addr:housenumber":"29",
    "addr:postcode":"4644",
    "addr:street":"Im Forst",
    "iso:country":"AT",
    "sg:address":"Im Forst 29",
    "sg:city":"Scharnstein",
    "sg:orig_category":"Reinigungsbedarf U Reinigungsmittel",
    "sg:phone":"+43 76157478",
    "sg:postcode":"4644",
    "sg:province":"Ober\u00f6sterreich",
    "wof:name":"Ha-Ra - Holl",
    "wof:placetype":"venue"
},
  "geometry": {"coordinates":[13.9247169495,47.8898582458],"type":"Point"}
}