{
  "type": "Feature",
  "properties": {
    "iso:country":"AT",
    "sg:address":"Herburg 201",
    "sg:city":"Bezau",
    "sg:orig_category":"Holzbau",
    "sg:phone":"+43 5514 2693",
    "sg:postcode":"6870",
    "sg:province":"Vorarlberg",
    "wof:name":"Kaufmann Anton Ing - Holzbauservice",
    "wof:placetype":"venue"
},
  "geometry": {"coordinates":[9.9022083282,47.3848991394],"type":"Point"}
}