{
  "type": "Feature",
  "properties": {
    "iso:country":"AT",
    "sg:address":"Schweigers 62",
    "sg:city":"Schweiggers",
    "sg:classifiers":[
        {
            "category":"Building & Trades",
            "subcategory":"Plumbing",
            "type":"Services"
        }
    ],
    "sg:phone":"+43 2829 7075",
    "sg:postcode":"3931",
    "sg:province":"Nieder\u00f6sterreich",
    "sg:tags":[
        "supraregional",
        "gas"
    ],
    "wof:name":"Alfred Pistracher GesmbH",
    "wof:placetype":"venue"
},
  "geometry": {"coordinates":[15.0622196198,48.6683349609],"type":"Point"}
}