{
  "type": "Feature",
  "properties": {
    "iso:country":"AT",
    "sg:address":"Hof 16",
    "sg:city":"Ried im Innkreis",
    "sg:orig_category":"Installationsunternehmen",
    "sg:phone":"+43 7752 829280",
    "sg:postcode":"4910",
    "sg:province":"Ober\u00f6sterreich",
    "wof:name":"Mayer Karl Dipl-Ing",
    "wof:placetype":"venue"
},
  "geometry": {"coordinates":[13.483080864,48.1678390503],"type":"Point"}
}