{
  "type": "Feature",
  "properties": {
    "addr:full":"Johann-Gerlitz-G 13 Hartberg Steiermark 8230",
    "addr:housenumber":"13",
    "addr:postcode":"8230",
    "addr:street":"Johann-Gerlitz-G",
    "iso:country":"AT",
    "sg:address":"Johann-Gerlitz-G 13",
    "sg:city":"Hartberg",
    "sg:orig_category":"Immobilienverwaltungen",
    "sg:phone":"+43 3332 62232",
    "sg:postcode":"8230",
    "sg:province":"Steiermark",
    "wof:name":"Freiberger Franz GesmbH",
    "wof:placetype":"venue"
},
  "geometry": {"coordinates":[15.9716501236,47.2843284607],"type":"Point"}
}