{
  "type": "Feature",
  "properties": {
    "addr:full":"Sonnenberger Str 31 Frastanz Vorarlberg 6820",
    "addr:postcode":"6820",
    "addr:street":"Str 31",
    "iso:country":"AT",
    "sg:address":"Sonnenberger Str 31",
    "sg:city":"Frastanz",
    "sg:orig_category":"Textildruckereien",
    "sg:phone":"+43 4355 22517850",
    "sg:postcode":"6820",
    "sg:province":"Vorarlberg",
    "wof:name":"Nitschmann trading company",
    "wof:placetype":"venue"
},
  "geometry": {"coordinates":[9.6437664032,47.216960907],"type":"Point"}
}