{
  "type": "Feature",
  "properties": {
    "addr:full":"Feldkirchen in K\u00e4rnten K\u00e4rnten 9560",
    "addr:postcode":"9560",
    "addr:street":"Kaernten",
    "iso:country":"AT",
    "sg:city":"Feldkirchen in K\u00e4rnten",
    "sg:orig_category":"Feuerwehren",
    "sg:phone":"+43 4276 8005",
    "sg:postcode":"9560",
    "sg:province":"K\u00e4rnten",
    "wof:name":"Feuerwehr Glanhofen",
    "wof:placetype":"venue"
},
  "geometry": {"coordinates":[14.0898571014,46.6891746521],"type":"Point"}
}