{
  "type": "Feature",
  "properties": {
    "addr:full":"Adolf-Wimmer-Str 5 Ober-Grafendorf Nieder\u00f6sterreich 3200",
    "addr:housenumber":"5",
    "addr:postcode":"3200",
    "addr:street":"Adolf-Wimmer-Str",
    "iso:country":"AT",
    "sg:address":"Adolf-Wimmer-Str 5",
    "sg:city":"Ober-Grafendorf",
    "sg:orig_category":"Hafnereien",
    "sg:phone":"+43 2747 8500",
    "sg:postcode":"3200",
    "sg:province":"Nieder\u00f6sterreich",
    "wof:name":"Staudinger Franz GesmbH",
    "wof:placetype":"venue"
},
  "geometry": {"coordinates":[15.548781395,48.1509132385],"type":"Point"}
}