{
  "type": "Feature",
  "properties": {
    "addr:full":"Sandg 17 Linz Ober\u00f6sterreich 4020",
    "addr:housenumber":"17",
    "addr:postcode":"4020",
    "addr:street":"Sandg",
    "iso:country":"AT",
    "sg:address":"Sandg 17",
    "sg:city":"Linz",
    "sg:orig_category":"Ingenieurkonsulenten / Zivilingenieure",
    "sg:phone":"+43 732 664455",
    "sg:postcode":"4020",
    "sg:province":"Ober\u00f6sterreich",
    "wof:name":"Klo\u00df Max Dipl-Ing",
    "wof:placetype":"venue"
},
  "geometry": {"coordinates":[14.2451400757,48.3018455505],"type":"Point"}
}