{
  "type": "Feature",
  "properties": {
    "addr:full":"S\u00fcdtiroler Pl 7 Lienz Tirol 9900",
    "addr:housenumber":"7",
    "addr:postcode":"9900",
    "addr:street":"Suedtiroler Pl;Tirol",
    "iso:country":"AT",
    "sg:address":"S\u00fcdtiroler Pl 7",
    "sg:city":"Lienz",
    "sg:classifiers":[
        {
            "category":"Travel",
            "subcategory":"Hotels & Motels",
            "type":"Entertainment"
        }
    ],
    "sg:phone":"+43 4852 625050",
    "sg:postcode":"9900",
    "sg:province":"Tirol",
    "wof:name":"Hotel Post",
    "wof:placetype":"venue"
},
  "geometry": {"coordinates":[12.7684783936,46.8281173706],"type":"Point"}
}