{
  "type": "Feature",
  "properties": {
    "addr:full":"Schererstr 18 Linz Ober\u00f6sterreich 4020",
    "addr:housenumber":"18",
    "addr:postcode":"4020",
    "addr:street":"Schererstr",
    "iso:country":"AT",
    "sg:address":"Schererstr 18",
    "sg:city":"Linz",
    "sg:orig_category":"Weiterbildungsinstitute M Allg U Berufl Bildungsangebot",
    "sg:phone":"+43 4373 23701520",
    "sg:postcode":"4020",
    "sg:province":"Ober\u00f6sterreich",
    "sg:website":"mentor.at",
    "wof:name":"MENTOR Management-Entwicklung-Organisation GmbH & Co",
    "wof:placetype":"venue"
},
  "geometry": {"coordinates":[14.2781400681,48.2577781677],"type":"Point"}
}