{
  "type": "Feature",
  "properties": {
    "iso:country":"AT",
    "sg:address":"Hauptpl 27",
    "sg:city":"Deutschlandsberg",
    "sg:orig_category":"Blumeneinzelhandel",
    "sg:phone":"+43 3462 290714",
    "sg:postcode":"8530",
    "sg:province":"Steiermark",
    "wof:name":"Pinter GesmbH",
    "wof:placetype":"venue"
},
  "geometry": {"coordinates":[15.2133216858,46.8144836426],"type":"Point"}
}