{
  "type": "Feature",
  "properties": {
    "addr:full":"Kemating 35 Nu\u00dfdorf am Haunsberg Salzburg 5151",
    "addr:housenumber":"35",
    "addr:postcode":"5151",
    "addr:street":"Kemating;Salzburg",
    "iso:country":"AT",
    "sg:address":"Kemating 35",
    "sg:city":"Nu\u00dfdorf am Haunsberg",
    "sg:orig_category":"Etiketten",
    "sg:phone":"+43 6276 520",
    "sg:postcode":"5151",
    "sg:province":"Salzburg",
    "wof:name":"All Sale HandelsgesmbH",
    "wof:placetype":"venue"
},
  "geometry": {"coordinates":[13.0084629059,47.9599075317],"type":"Point"}
}