{
  "type": "Feature",
  "properties": {
    "iso:country":"AT",
    "sg:address":"Nr 10",
    "sg:city":"Nestelbach",
    "sg:orig_category":"Tabaktrafiken",
    "sg:phone":"+43 3133 2454",
    "sg:postcode":"8302",
    "sg:province":"Steiermark",
    "wof:name":"Schmidt Johann",
    "wof:placetype":"venue"
},
  "geometry": {"coordinates":[15.6095781326,47.0327033997],"type":"Point"}
}