{
  "type": "Feature",
  "properties": {
    "addr:full":"Stinyg 9/R1 Wien Wien 1100",
    "addr:housenumber":"9 / r1",
    "addr:postcode":"1100",
    "addr:street":"Stinyg",
    "iso:country":"AT",
    "sg:address":"Stinyg 9/R1",
    "sg:city":"Wien",
    "sg:classifiers":[
        {
            "category":"Banks & Credit Unions",
            "subcategory":"Investment Brokerage",
            "type":"Services"
        }
    ],
    "sg:phone":"+43 1 6892411",
    "sg:postcode":"1100",
    "sg:province":"Wien",
    "sg:tags":[
        "management",
        "facility"
    ],
    "wof:name":"REVITALIS Bauplanung GmbH",
    "wof:placetype":"venue"
},
  "geometry": {"coordinates":[16.3744049072,48.1782684326],"type":"Point"}
}