{
  "type": "Feature",
  "properties": {
    "addr:full":"Ferlach K\u00e4rnten 9170",
    "addr:postcode":"9170",
    "iso:country":"AT",
    "sg:city":"Ferlach",
    "sg:orig_category":"Non-Classified Establishments",
    "sg:phone":"+43 4227 2290",
    "sg:postcode":"9170",
    "sg:province":"K\u00e4rnten",
    "wof:name":"Pfarramt",
    "wof:placetype":"venue"
},
  "geometry": {"coordinates":[14.2995548248,46.5264358521],"type":"Point"}
}