{
  "type": "Feature",
  "properties": {
    "addr:full":"Sonnleiten 13 Hinterbr\u00fchl Nieder\u00f6sterreich 2371",
    "addr:housenumber":"13",
    "addr:postcode":"2371",
    "addr:street":"Sonnleiten;Niederoesterreich",
    "iso:country":"AT",
    "sg:address":"Sonnleiten 13",
    "sg:city":"Hinterbr\u00fchl",
    "sg:orig_category":"Ingenieurkonsulenten / Zivilingenieure",
    "sg:phone":"+43 2236 46848",
    "sg:postcode":"2371",
    "sg:province":"Nieder\u00f6sterreich",
    "wof:name":"Krisch Helmut Dipl-Ing",
    "wof:placetype":"venue"
},
  "geometry": {"coordinates":[15.7279596329,47.3482704163],"type":"Point"}
}