{
  "type": "Feature",
  "properties": {
    "addr:full":"Endach 32 Kufstein Tirol 6330",
    "addr:housenumber":"32",
    "addr:postcode":"6330",
    "addr:street":"Endach;Tirol",
    "iso:country":"AT",
    "sg:address":"Endach 32",
    "sg:city":"Kufstein",
    "sg:orig_category":"Autohandel",
    "sg:phone":"+43 4353 7269450",
    "sg:postcode":"6330",
    "sg:province":"Tirol",
    "sg:website":"unterberger.cc",
    "wof:name":"Unterberger Automobile GmbH & Co KG",
    "wof:placetype":"venue"
},
  "geometry": {"coordinates":[12.1519317627,47.5657463074],"type":"Point"}
}