{
  "type": "Feature",
  "properties": {
    "addr:full":"Hauptstr 35 St. Stefan im Lavanttal K\u00e4rnten 9431",
    "addr:housenumber":"35",
    "addr:postcode":"9431",
    "addr:street":"Hauptstr",
    "iso:country":"AT",
    "sg:address":"Hauptstr 35",
    "sg:city":"St. Stefan im Lavanttal",
    "sg:orig_category":"Tabaktrafiken",
    "sg:phone":"+43 4343 522668",
    "sg:postcode":"9431",
    "sg:province":"K\u00e4rnten",
    "wof:name":"Scharf Daniel",
    "wof:placetype":"venue"
},
  "geometry": {"coordinates":[14.832036972,46.8094558716],"type":"Point"}
}