{
  "type": "Feature",
  "properties": {
    "addr:full":"Murweg 3 Fohnsdorf Steiermark 8753",
    "addr:housenumber":"3",
    "addr:postcode":"8753",
    "addr:street":"Murweg",
    "iso:country":"AT",
    "sg:address":"Murweg 3",
    "sg:city":"Fohnsdorf",
    "sg:orig_category":"Tankstellen",
    "sg:phone":"+43 3572 42193",
    "sg:postcode":"8753",
    "sg:province":"Steiermark",
    "wof:name":"JET Tankstelle",
    "wof:placetype":"venue"
},
  "geometry": {"coordinates":[14.6780195236,47.2084732056],"type":"Point"}
}