{
  "type": "Feature",
  "properties": {
    "iso:country":"AT",
    "sg:address":"Niederottnang 145",
    "sg:city":"Ottnang am Hausruck",
    "sg:classifiers":[
        {
            "category":"Building & Trades",
            "subcategory":"Construction",
            "type":"Services"
        }
    ],
    "sg:phone":"+43 76767350",
    "sg:postcode":"4901",
    "sg:province":"Ober\u00f6sterreich",
    "sg:tags":[
        "installation",
        "air-conditioning",
        "system"
    ],
    "wof:name":"Franz H\u00f6dlmoser Ges.m.b.H. & Co KG",
    "wof:placetype":"venue"
},
  "geometry": {"coordinates":[13.665930748,48.0873031616],"type":"Point"}
}