{
  "type": "Feature",
  "properties": {
    "iso:country":"AT",
    "sg:address":"Dorfstr 23",
    "sg:city":"Kundl",
    "sg:orig_category":"Feuerwehren",
    "sg:phone":"+43 5338 8800",
    "sg:postcode":"6250",
    "sg:province":"Tirol",
    "wof:name":"Freiwillige Feuerwehr Kundl",
    "wof:placetype":"venue"
},
  "geometry": {"coordinates":[11.9864416122,47.4700927734],"type":"Point"}
}