{
  "type": "Feature",
  "properties": {
    "addr:full":"Schrammlstr 8 Traun Ober\u00f6sterreich 4050",
    "addr:housenumber":"8",
    "addr:postcode":"4050",
    "addr:street":"Schrammlstr",
    "iso:country":"AT",
    "sg:address":"Schrammlstr 8",
    "sg:city":"Traun",
    "sg:orig_category":"Maler, Anstreicher U Lackierer",
    "sg:phone":"+43 4372 2951201",
    "sg:postcode":"4050",
    "sg:province":"Ober\u00f6sterreich",
    "wof:name":"Art & Design Tischer GmbH",
    "wof:placetype":"venue"
},
  "geometry": {"coordinates":[14.2671947479,48.2398872375],"type":"Point"}
}