{
  "type": "Feature",
  "properties": {
    "addr:full":"Wiener Str 83 Neunkirchen Nieder\u00f6sterreich 2620",
    "addr:housenumber":"83",
    "addr:postcode":"2620",
    "iso:country":"AT",
    "sg:address":"Wiener Str 83",
    "sg:city":"Neunkirchen",
    "sg:orig_category":"Steinmetzbetriebe",
    "sg:phone":"+43 2635 62756",
    "sg:postcode":"2620",
    "sg:province":"Nieder\u00f6sterreich",
    "wof:name":"Hofer Roman",
    "wof:placetype":"venue"
},
  "geometry": {"coordinates":[16.0980548859,47.7119560242],"type":"Point"}
}