{
  "type": "Feature",
  "properties": {
    "addr:full":"Ing.-Etzel-Str 16d Innsbruck Tirol 6020",
    "addr:housenumber":"16d",
    "addr:postcode":"6020",
    "addr:street":"Ing.-Etzel-Str;Tirol",
    "iso:country":"AT",
    "sg:address":"Ing.-Etzel-Str 16d",
    "sg:city":"Innsbruck",
    "sg:orig_category":"Rauchfangkehrer",
    "sg:phone":"+43 512 579892",
    "sg:postcode":"6020",
    "sg:province":"Tirol",
    "wof:name":"Windbichler Martin",
    "wof:placetype":"venue"
},
  "geometry": {"coordinates":[11.4097480774,47.274356842],"type":"Point"}
}