{
  "type": "Feature",
  "properties": {
    "iso:country":"AT",
    "sg:address":"Sonnenstrasse 1",
    "sg:city":"Satteins",
    "sg:orig_category":"Fastening Systems For Solar And Photovoltaic Modules",
    "sg:phone":"+43 5524 8666",
    "sg:postcode":"6822",
    "sg:province":"Vorarlberg",
    "sg:website":"stromaufwaerts.at",
    "wof:name":"stromaufw\u00e4rts Photovoltaik GmbH",
    "wof:placetype":"venue"
},
  "geometry": {"coordinates":[9.6628293991,47.219203949],"type":"Point"}
}