{
  "type": "Feature",
  "properties": {
    "addr:full":"Tschamlerstr 7 Innsbruck Tirol 6020",
    "addr:housenumber":"7",
    "addr:postcode":"6020",
    "addr:street":"Tschamlerstr;Tirol",
    "iso:country":"AT",
    "sg:address":"Tschamlerstr 7",
    "sg:city":"Innsbruck",
    "sg:classifiers":[
        {
            "category":"Restaurant",
            "type":"Food & Drink"
        }
    ],
    "sg:phone":"+43 512 560709",
    "sg:postcode":"6020",
    "sg:province":"Tirol",
    "sg:tags":[
        "pizzeria"
    ],
    "wof:name":"Pizzeria Il Campo",
    "wof:placetype":"venue"
},
  "geometry": {"coordinates":[11.3963098526,47.2568397522],"type":"Point"}
}