{
  "type": "Feature",
  "properties": {
    "addr:full":"Am Platz 2 Wien Wien 1130",
    "addr:housenumber":"2",
    "addr:postcode":"1130",
    "addr:street":"Am Platz",
    "iso:country":"AT",
    "sg:address":"Am Platz 2",
    "sg:city":"Wien",
    "sg:orig_category":"Volksschulen",
    "sg:phone":"+43 1 8777368",
    "sg:postcode":"1130",
    "sg:province":"Wien",
    "wof:name":"Schulen d Stadt Wien",
    "wof:placetype":"venue"
},
  "geometry": {"coordinates":[16.3013801575,48.18592453],"type":"Point"}
}