{
  "type": "Feature",
  "properties": {
    "iso:country":"AT",
    "sg:address":"Rathauspl 1",
    "sg:city":"Kirchdorf an der Krems",
    "sg:orig_category":"Gemeinden",
    "sg:phone":"+43 4375 82622380",
    "sg:postcode":"4560",
    "sg:province":"Ober\u00f6sterreich",
    "wof:name":"Stadtamt Kirchdorf an der Krems",
    "wof:placetype":"venue"
},
  "geometry": {"coordinates":[14.1226596832,47.9057617188],"type":"Point"}
}