{
  "type": "Feature",
  "properties": {
    "iso:country":"AT",
    "sg:address":"Linzer Str 25",
    "sg:city":"Gallneukirchen",
    "sg:orig_category":"Baumschulen",
    "sg:phone":"+43 7235 63229",
    "sg:postcode":"4210",
    "sg:province":"Ober\u00f6sterreich",
    "wof:name":"St\u00fctz Norbert Andreas",
    "wof:placetype":"venue"
},
  "geometry": {"coordinates":[14.4120206833,48.3504104614],"type":"Point"}
}