{
  "type": "Feature",
  "properties": {
    "addr:full":"Ludwig-Benedek-G 19 Stra\u00dfgang Steiermark 8054",
    "addr:housenumber":"19",
    "addr:postcode":"8054",
    "addr:street":"Ludwig-Benedek-G",
    "iso:country":"AT",
    "sg:address":"Ludwig-Benedek-G 19",
    "sg:city":"Stra\u00dfgang",
    "sg:orig_category":"Tonstudios",
    "sg:phone":"+43 316 285244",
    "sg:postcode":"8054",
    "sg:province":"Steiermark",
    "wof:name":"Jauk Werner Dr",
    "wof:placetype":"venue"
},
  "geometry": {"coordinates":[15.4028863907,47.0352897644],"type":"Point"}
}