{
  "type": "Feature",
  "properties": {
    "iso:country":"AT",
    "sg:address":"Wilhelm-Exner-G 30",
    "sg:city":"Wien",
    "sg:orig_category":"Psychotherapie",
    "sg:phone":"+43 1 3197819",
    "sg:postcode":"1090",
    "sg:province":"Wien",
    "wof:name":"Zimprich Vera Dr phil",
    "wof:placetype":"venue"
},
  "geometry": {"coordinates":[16.352640152,48.2244338989],"type":"Point"}
}