{
  "type": "Feature",
  "properties": {
    "addr:full":"Unterdorf 22 Pusarnitz K\u00e4rnten 9812",
    "addr:housenumber":"22",
    "addr:postcode":"9812",
    "addr:street":"Unterdorf;Kaernten",
    "iso:country":"AT",
    "sg:address":"Unterdorf 22",
    "sg:city":"Pusarnitz",
    "sg:orig_category":"Elektroinstallationsunternehmen",
    "sg:phone":"+43 664 1817605",
    "sg:postcode":"9812",
    "sg:province":"K\u00e4rnten",
    "wof:name":"Pichler Helmut Elektrotechnik",
    "wof:placetype":"venue"
},
  "geometry": {"coordinates":[13.3967895508,46.8407173157],"type":"Point"}
}