{
  "type": "Feature",
  "properties": {
    "addr:full":"Borrom\u00e4umstr 17/20 Salzburg Salzburg 5020",
    "addr:housenumber":"17 / 20",
    "addr:postcode":"5020",
    "addr:street":"Borromaeumstr;Salzburg",
    "iso:country":"AT",
    "sg:address":"Borrom\u00e4umstr 17/20",
    "sg:city":"Salzburg",
    "sg:orig_category":"Non-Classified Establishments",
    "sg:phone":"+43 662 641025",
    "sg:postcode":"5020",
    "sg:province":"Salzburg",
    "wof:name":"Katholische Pfarr\u00e4mter - Ukrainische Gemeinde gr-kath Seelsorgeamt f West\u00f6sterreich",
    "wof:placetype":"venue"
},
  "geometry": {"coordinates":[13.0630025864,47.8014373779],"type":"Point"}
}