{
  "type": "Feature",
  "properties": {
    "addr:full":"Kugelhofstr 8 Salzburg Salzburg 5020",
    "addr:housenumber":"8",
    "addr:postcode":"5020",
    "addr:street":"Kugelhofstr;Salzburg",
    "iso:country":"AT",
    "sg:address":"Kugelhofstr 8",
    "sg:city":"Salzburg",
    "sg:orig_category":"Tonstudios",
    "sg:phone":"+43 4369 912195842",
    "sg:postcode":"5020",
    "sg:province":"Salzburg",
    "wof:name":"wacht production",
    "wof:placetype":"venue"
},
  "geometry": {"coordinates":[13.016450882,47.7937431335],"type":"Point"}
}