{
  "type": "Feature",
  "properties": {
    "iso:country":"AT",
    "sg:address":"Gr\u00fcnburgerstrasse 38",
    "sg:city":"Waldneukirchen",
    "sg:classifiers":[
        {
            "category":"Manufacturing",
            "subcategory":"Signs",
            "type":"Manufacturing & Wholesale Goods"
        }
    ],
    "sg:phone":"+43 7257 7782",
    "sg:postcode":"4595",
    "sg:province":"Ober\u00f6sterreich",
    "sg:tags":[
        "car",
        "lettering"
    ],
    "wof:name":"Johann Holzer",
    "wof:placetype":"venue"
},
  "geometry": {"coordinates":[14.2606515884,47.9965286255],"type":"Point"}
}