{
  "type": "Feature",
  "properties": {
    "iso:country":"AT",
    "sg:address":"Tr\u00f6ssing 59",
    "sg:city":"Gnas",
    "sg:classifiers":[
        {
            "category":"Manufacturing",
            "subcategory":"Furniture",
            "type":"Manufacturing & Wholesale Goods"
        }
    ],
    "sg:phone":"+43 3477 2590",
    "sg:postcode":"8342",
    "sg:province":"Steiermark",
    "sg:tags":[
        "bedroom"
    ],
    "wof:name":"Tischlerei Tuscher OEG",
    "wof:placetype":"venue"
},
  "geometry": {"coordinates":[15.8265724182,46.8743095398],"type":"Point"}
}