{
  "type": "Feature",
  "properties": {
    "addr:full":"Ungarstr 16 F\u00fcrstenfeld Steiermark 8280",
    "addr:housenumber":"16",
    "addr:postcode":"8280",
    "addr:street":"Ungarstr",
    "iso:country":"AT",
    "sg:address":"Ungarstr 16",
    "sg:city":"F\u00fcrstenfeld",
    "sg:orig_category":"Nachhilfe U Lernbetreuung",
    "sg:phone":"+43 4333 8253845",
    "sg:postcode":"8280",
    "sg:province":"Steiermark",
    "wof:name":"Lern und Sprachzentrum Derler",
    "wof:placetype":"venue"
},
  "geometry": {"coordinates":[16.078792572,47.0487365723],"type":"Point"}
}