{
  "type": "Feature",
  "properties": {
    "addr:full":"Linzer Str 2A Wien Wien 1150",
    "addr:housenumber":"2a",
    "addr:postcode":"1150",
    "addr:street":"Linzer Str",
    "iso:country":"AT",
    "sg:address":"Linzer Str 2A",
    "sg:city":"Wien",
    "sg:orig_category":"Tankstellen",
    "sg:phone":"+43 1 8928077",
    "sg:postcode":"1150",
    "sg:province":"Wien",
    "wof:name":"Shell Austria GmbH",
    "wof:placetype":"venue"
},
  "geometry": {"coordinates":[16.3217754364,48.1906929016],"type":"Point"}
}