{
  "type": "Feature",
  "properties": {
    "iso:country":"AT",
    "sg:address":"Hasenleitengasse 73",
    "sg:city":"Wien",
    "sg:orig_category":"Non-Classified Establishments",
    "sg:phone":"+43 1 86500540",
    "sg:postcode":"1110",
    "sg:province":"Wien",
    "wof:name":"Delta Werbeges.m.b.H.",
    "wof:placetype":"venue"
},
  "geometry": {"coordinates":[16.4176521301,48.1599159241],"type":"Point"}
}