{
  "type": "Feature",
  "properties": {
    "iso:country":"AT",
    "sg:address":"Nr 21",
    "sg:city":"Krakaudorf",
    "sg:orig_category":"Tischlereien",
    "sg:phone":"+43 3535 8213",
    "sg:postcode":"8854",
    "sg:province":"Steiermark",
    "wof:name":"Etz Arnold",
    "wof:placetype":"venue"
},
  "geometry": {"coordinates":[13.9921045303,47.1786117554],"type":"Point"}
}