{
  "type": "Feature",
  "properties": {
    "addr:full":"Triester Bundesstr 60 Gloggnitz Nieder\u00f6sterreich 2640",
    "addr:housenumber":"60",
    "addr:postcode":"2640",
    "addr:street":"Niederoesterreich",
    "iso:country":"AT",
    "sg:address":"Triester Bundesstr 60",
    "sg:city":"Gloggnitz",
    "sg:orig_category":"Autohandel",
    "sg:phone":"+43 2662 42409",
    "sg:postcode":"2640",
    "sg:province":"Nieder\u00f6sterreich",
    "wof:name":"Griessner Ferdinand Ing",
    "wof:placetype":"venue"
},
  "geometry": {"coordinates":[15.94622612,47.6675071716],"type":"Point"}
}