{
  "type": "Feature",
  "properties": {
    "addr:full":"Mauermannstrasse 6 Gnigl Salzburg 5023",
    "addr:housenumber":"6",
    "addr:postcode":"5023",
    "addr:street":"Mauermannstrasse",
    "iso:country":"AT",
    "sg:address":"Mauermannstrasse 6",
    "sg:city":"Gnigl",
    "sg:classifiers":[
        {
            "category":"Retail",
            "subcategory":"Laundry & Dry Cleaning",
            "type":"Services"
        }
    ],
    "sg:phone":"+43 662 6617710",
    "sg:postcode":"5023",
    "sg:province":"Salzburg",
    "sg:tags":[
        "product",
        "system",
        "carpet"
    ],
    "sg:website":"www.zezi.at",
    "wof:name":"Chemische Fabrik - Jos. Ant. Zezi Ges.m.b.H.",
    "wof:placetype":"venue"
},
  "geometry": {"coordinates":[13.0612916946,47.8261528015],"type":"Point"}
}