{
  "type": "Feature",
  "properties": {
    "addr:full":"Deuchendorf 22 Kapfenberg Steiermark 8605",
    "addr:housenumber":"22",
    "addr:postcode":"8605",
    "addr:street":"Deuchendorf",
    "iso:country":"AT",
    "sg:address":"Deuchendorf 22",
    "sg:city":"Kapfenberg",
    "sg:orig_category":"Transportunternehmen",
    "sg:phone":"+43 676 4175404",
    "sg:postcode":"8605",
    "sg:province":"Steiermark",
    "wof:name":"Fuchs Transport Vermittlung und Beratungs GesmbH",
    "wof:placetype":"venue"
},
  "geometry": {"coordinates":[15.317735672,47.4638557434],"type":"Point"}
}