{
  "type": "Feature",
  "properties": {
    "iso:country":"AT",
    "sg:address":"Deuchendorf 22",
    "sg:city":"Kapfenberg",
    "sg:orig_category":"Transportunternehmen",
    "sg:phone":"+43 676 4175404",
    "sg:postcode":"8605",
    "sg:province":"Steiermark",
    "wof:name":"Fuchs Transport Vermittlung und Beratungs GesmbH",
    "wof:placetype":"venue"
},
  "geometry": {"coordinates":[15.317735672,47.4638557434],"type":"Point"}
}