{
  "type": "Feature",
  "properties": {
    "iso:country":"AT",
    "sg:address":"Hauptstr 55",
    "sg:city":"H\u00f6flein an der Donau",
    "sg:orig_category":"Feuerwehren",
    "sg:phone":"+43 2243 80122",
    "sg:postcode":"3421",
    "sg:province":"Nieder\u00f6sterreich",
    "wof:name":"Freiwillige Feuerwehr Klosterneuburg-H\u00f6flein",
    "wof:placetype":"venue"
},
  "geometry": {"coordinates":[20.6613903046,47.8595314026],"type":"Point"}
}