{
  "type": "Feature",
  "properties": {
    "addr:full":"P\u00f6llnstr 13 St. Johann im Pongau Salzburg 5600",
    "addr:housenumber":"13",
    "addr:postcode":"5600",
    "addr:street":"Poellnstr;Salzburg",
    "iso:country":"AT",
    "sg:address":"P\u00f6llnstr 13",
    "sg:city":"St. Johann im Pongau",
    "sg:orig_category":"Lebensmittel / Einzelhandel",
    "sg:phone":"+43 4364 128410",
    "sg:postcode":"5600",
    "sg:province":"Salzburg",
    "wof:name":"Penny Markt",
    "wof:placetype":"venue"
},
  "geometry": {"coordinates":[13.1995849609,47.3472366333],"type":"Point"}
}