{
  "type": "Feature",
  "properties": {
    "addr:full":"Neuhauser Str 7 Innsbruck Tirol 6020",
    "addr:housenumber":"7",
    "addr:postcode":"6020",
    "addr:street":"Str;Tirol",
    "iso:country":"AT",
    "sg:address":"Neuhauser Str 7",
    "sg:city":"Innsbruck",
    "sg:orig_category":"Steuerberatung",
    "sg:phone":"+43 4351 25881160",
    "sg:postcode":"6020",
    "sg:province":"Tirol",
    "wof:name":"Reitschuler Wolfgang Mag",
    "wof:placetype":"venue"
},
  "geometry": {"coordinates":[11.3948154449,47.2566375732],"type":"Point"}
}