{
  "type": "Feature",
  "properties": {
    "addr:full":"Nr 4 Litschau Nieder\u00f6sterreich 3874",
    "addr:postcode":"3874",
    "addr:street":"Nr;Niederoesterreich",
    "iso:country":"AT",
    "sg:address":"Nr 4",
    "sg:city":"Litschau",
    "sg:orig_category":"Landwirtschaftliche Produkte",
    "sg:phone":"+43 4328 65314",
    "sg:postcode":"3874",
    "sg:province":"Nieder\u00f6sterreich",
    "wof:name":"Bauernmarktprodukte Otto Schierer-Poindl",
    "wof:placetype":"venue"
},
  "geometry": {"coordinates":[15.0453643799,48.9441757202],"type":"Point"}
}