{
  "type": "Feature",
  "properties": {
    "addr:full":"D\u00f6pplingerstr Ternitz Nieder\u00f6sterreich 2630",
    "addr:postcode":"2630",
    "addr:street":"Doepplingerstr;Niederoesterreich",
    "iso:country":"AT",
    "sg:address":"D\u00f6pplingerstr",
    "sg:city":"Ternitz",
    "sg:orig_category":"Feuerwehren",
    "sg:phone":"+43 2630 39650",
    "sg:postcode":"2630",
    "sg:province":"Nieder\u00f6sterreich",
    "wof:name":"Freiwillige Feuerwehr Ternitz-D\u00f6ppling",
    "wof:placetype":"venue"
},
  "geometry": {"coordinates":[16.0391273499,47.7222175598],"type":"Point"}
}