{
  "type": "Feature",
  "properties": {
    "addr:full":"Nr 11 Riegersdorf K\u00e4rnten 9587",
    "addr:postcode":"9587",
    "addr:street":"Nr;Riegersdorf Kaernten",
    "iso:country":"AT",
    "sg:address":"Nr 11",
    "sg:city":"Riegersdorf",
    "sg:orig_category":"Volksschulen",
    "sg:phone":"+43 4342 572464",
    "sg:postcode":"9587",
    "sg:province":"K\u00e4rnten",
    "wof:name":"Volksschule",
    "wof:placetype":"venue"
},
  "geometry": {"coordinates":[13.7944297791,46.5479393005],"type":"Point"}
}