{
  "type": "Feature",
  "properties": {
    "iso:country":"AT",
    "sg:address":"St. Oswalder Str 2",
    "sg:city":"Gutau",
    "sg:orig_category":"Gemeinden",
    "sg:phone":"+43 4379 4662550",
    "sg:postcode":"4293",
    "sg:province":"Ober\u00f6sterreich",
    "wof:name":"Marktgemeindeamt Gutau",
    "wof:placetype":"venue"
},
  "geometry": {"coordinates":[14.6139183044,48.4179496765],"type":"Point"}
}