{
  "type": "Feature",
  "properties": {
    "addr:full":"Kirchenring 16 Raggendorf Nieder\u00f6sterreich 2215",
    "addr:housenumber":"16",
    "addr:postcode":"2215",
    "addr:street":"Kirchenring;Niederoesterreich",
    "iso:country":"AT",
    "sg:address":"Kirchenring 16",
    "sg:city":"Raggendorf",
    "sg:orig_category":"Behinderungen / Leben Mit Behinderungen",
    "sg:phone":"+43 2289 2659",
    "sg:postcode":"2215",
    "sg:province":"Nieder\u00f6sterreich",
    "wof:name":"Lebenshilfe N\u00d6 Werkst\u00e4tte Raggendorf",
    "wof:placetype":"venue"
},
  "geometry": {"coordinates":[16.6550102234,48.3945007324],"type":"Point"}
}