{
  "type": "Feature",
  "properties": {
    "iso:country":"AT",
    "sg:address":"Steinleiten 25",
    "sg:city":"Frankenmarkt",
    "sg:orig_category":"Autohandel",
    "sg:phone":"+43 768460210",
    "sg:postcode":"4890",
    "sg:province":"Ober\u00f6sterreich",
    "wof:name":"Autohaus Fink",
    "wof:placetype":"venue"
},
  "geometry": {"coordinates":[13.4358196259,47.9853286743],"type":"Point"}
}