{
  "type": "Feature",
  "properties": {
    "iso:country":"AT",
    "sg:address":"Trabeniger Str 1",
    "sg:city":"Wernberg",
    "sg:orig_category":"Lebensmittel / Einzelhandel",
    "sg:phone":"+43 4252 3322",
    "sg:postcode":"9241",
    "sg:province":"K\u00e4rnten",
    "wof:name":"Spar-Markt Inh Zluga-Wurmitzer KEG",
    "wof:placetype":"venue"
},
  "geometry": {"coordinates":[13.9407958984,46.6229705811],"type":"Point"}
}