{
  "type": "Feature",
  "properties": {
    "iso:country":"AT",
    "sg:address":"Lichtenw\u00f6rther Str 2",
    "sg:city":"Theresienfeld",
    "sg:orig_category":"Nachtclubs-Bars",
    "sg:phone":"+43 2622 72285",
    "sg:postcode":"2604",
    "sg:province":"Nieder\u00f6sterreich",
    "wof:name":"Cat Club Bar",
    "wof:placetype":"venue"
},
  "geometry": {"coordinates":[16.2477703094,47.8601417542],"type":"Point"}
}