{
  "type": "Feature",
  "properties": {
    "addr:full":"Obere Bahng 20 Wien Wien 1030",
    "addr:housenumber":"20",
    "addr:postcode":"1030",
    "addr:street":"Obere Bahng",
    "iso:country":"AT",
    "sg:address":"Obere Bahng 20",
    "sg:city":"Wien",
    "sg:orig_category":"Dekorationsartikel",
    "sg:phone":"+43 1 7986142",
    "sg:postcode":"1030",
    "sg:province":"Wien",
    "wof:name":"Seda Viktor",
    "wof:placetype":"venue"
},
  "geometry": {"coordinates":[16.3903694153,48.191986084],"type":"Point"}
}