{
  "type": "Feature",
  "properties": {
    "iso:country":"AT",
    "sg:address":"Sportplatzstrasse 6",
    "sg:city":"Spillern",
    "sg:classifiers":[
        {
            "category":"Science Facility",
            "type":"Public Place"
        }
    ],
    "sg:phone":"+43 2266 808720",
    "sg:postcode":"2104",
    "sg:province":"Nieder\u00f6sterreich",
    "sg:tags":[
        "equipment",
        "analysis"
    ],
    "sg:website":"betavertrieb.at",
    "wof:name":"BETA Vertriebsges.m.b.H.",
    "wof:placetype":"venue"
},
  "geometry": {"coordinates":[16.2651100159,48.3777084351],"type":"Point"}
}