{
  "type": "Feature",
  "properties": {
    "addr:full":"Nr 20 Stronsdorf Nieder\u00f6sterreich 2153",
    "addr:postcode":"2153",
    "addr:street":"Nr 20 Stronsdorf",
    "iso:country":"AT",
    "sg:address":"Nr 20",
    "sg:city":"Stronsdorf",
    "sg:orig_category":"Non-Classified Establishments",
    "sg:phone":"+43 5 91333276",
    "sg:postcode":"2153",
    "sg:province":"Nieder\u00f6sterreich",
    "wof:name":"Gendarmerie",
    "wof:placetype":"venue"
},
  "geometry": {"coordinates":[16.2972221375,48.6530685425],"type":"Point"}
}