{
  "type": "Feature",
  "properties": {
    "addr:full":"Hietzinger Hauptstr 36 Wien Wien 1130",
    "addr:housenumber":"36",
    "addr:postcode":"1130",
    "addr:street":"Hietzinger Hauptstr",
    "iso:country":"AT",
    "sg:address":"Hietzinger Hauptstr 36",
    "sg:city":"Wien",
    "sg:orig_category":"Nagelstudios",
    "sg:phone":"+43 1 8764346",
    "sg:postcode":"1130",
    "sg:province":"Wien",
    "sg:website":"classic-nail-design.com",
    "wof:name":"Veith Claudia",
    "wof:placetype":"venue"
},
  "geometry": {"coordinates":[16.2967414856,48.1869125366],"type":"Point"}
}