{
  "type": "Feature",
  "properties": {
    "addr:full":"Bergsteigg 48 Wien Wien 1170",
    "addr:housenumber":"48",
    "addr:postcode":"1170",
    "addr:street":"Bergsteigg",
    "iso:country":"AT",
    "sg:address":"Bergsteigg 48",
    "sg:city":"Wien",
    "sg:orig_category":"Autospenglereien",
    "sg:phone":"+43 4319 825271",
    "sg:postcode":"1170",
    "sg:province":"Wien",
    "wof:name":"DOGAN Arif KEG",
    "wof:placetype":"venue"
},
  "geometry": {"coordinates":[16.3361110687,48.2194328308],"type":"Point"}
}