{
  "type": "Feature",
  "properties": {
    "addr:full":"Zaillachweg 12 Kammern im Liesingtal Steiermark 8773",
    "addr:housenumber":"12",
    "addr:postcode":"8773",
    "addr:street":"Zaillachweg",
    "iso:country":"AT",
    "sg:address":"Zaillachweg 12",
    "sg:city":"Kammern im Liesingtal",
    "sg:orig_category":"Maschinenhandel",
    "sg:phone":"+43 4338 4480380",
    "sg:postcode":"8773",
    "sg:province":"Steiermark",
    "wof:name":"HMT Technologie u Handel GmbH",
    "wof:placetype":"venue"
},
  "geometry": {"coordinates":[14.8905639648,47.392742157],"type":"Point"}
}