{
  "type": "Feature",
  "properties": {
    "iso:country":"AT",
    "sg:address":"M\u00fcnchner Bundesstr 92",
    "sg:city":"Salzburg",
    "sg:classifiers":[
        {
            "category":"Professional",
            "subcategory":"Computer Services",
            "type":"Services"
        }
    ],
    "sg:phone":"+43 662 459158",
    "sg:postcode":"5020",
    "sg:province":"Salzburg",
    "sg:tags":[
        "software"
    ],
    "wof:name":"Sunrise Software M\u00fchlbacher Nussbaumer OEG",
    "wof:placetype":"venue"
},
  "geometry": {"coordinates":[13.0433769226,47.8006744385],"type":"Point"}
}