{
  "type": "Feature",
  "properties": {
    "addr:full":"Eisenstr 2 Kronstorf Ober\u00f6sterreich 4484",
    "addr:housenumber":"2",
    "addr:postcode":"4484",
    "addr:street":"Eisenstr",
    "iso:country":"AT",
    "sg:address":"Eisenstr 2",
    "sg:city":"Kronstorf",
    "sg:classifiers":[
        {
            "category":"Restaurant",
            "type":"Food & Drink"
        }
    ],
    "sg:phone":"+43 7223 82691",
    "sg:postcode":"4484",
    "sg:province":"Ober\u00f6sterreich",
    "sg:tags":[
        "pizzeria"
    ],
    "wof:name":"Pizzeria Sorrento",
    "wof:placetype":"venue"
},
  "geometry": {"coordinates":[14.4767417908,48.1742019653],"type":"Point"}
}