{
  "type": "Feature",
  "properties": {
    "addr:full":"St. Jakober Str 32 Ebenthal in K\u00e4rnten K\u00e4rnten 9065",
    "addr:housenumber":"32",
    "addr:postcode":"9065",
    "addr:street":"St. Jakober Str;Kaernten",
    "iso:country":"AT",
    "sg:address":"St. Jakober Str 32",
    "sg:city":"Ebenthal in K\u00e4rnten",
    "sg:orig_category":"Tischlereien",
    "sg:phone":"+43 463 332190",
    "sg:postcode":"9065",
    "sg:province":"K\u00e4rnten",
    "wof:name":"Wrie\u00dfnegger Ulrich",
    "wof:placetype":"venue"
},
  "geometry": {"coordinates":[14.3602151871,46.6170578003],"type":"Point"}
}