{
  "type": "Feature",
  "properties": {
    "iso:country":"AT",
    "sg:address":"Hauptstr 13",
    "sg:city":"Bisamberg",
    "sg:orig_category":"Banken U Sparkassen",
    "sg:phone":"+43 2262 626500",
    "sg:postcode":"2102",
    "sg:province":"Nieder\u00f6sterreich",
    "wof:name":"Raiffeisenbank Korneuburg regGenmbH",
    "wof:placetype":"venue"
},
  "geometry": {"coordinates":[16.3606014252,48.3306236267],"type":"Point"}
}