{
  "type": "Feature",
  "properties": {
    "addr:full":"Welser Str 17 Micheldorf in Ober\u00f6sterreich Ober\u00f6sterreich 4563",
    "addr:postcode":"4563",
    "addr:street":"Str 17",
    "iso:country":"AT",
    "sg:address":"Welser Str 17",
    "sg:city":"Micheldorf in Ober\u00f6sterreich",
    "sg:orig_category":"Friseure U Frisiersalons",
    "sg:phone":"+43 4375 8251478",
    "sg:postcode":"4563",
    "sg:province":"Ober\u00f6sterreich",
    "wof:name":"Irmi - Ihr pers\u00f6nlicher Friseur",
    "wof:placetype":"venue"
},
  "geometry": {"coordinates":[14.1324977875,47.881942749],"type":"Point"}
}