{
  "type": "Feature",
  "properties": {
    "addr:full":"Wagnerstr 2 Hinterbr\u00fchl Nieder\u00f6sterreich 2371",
    "addr:housenumber":"2",
    "addr:postcode":"2371",
    "addr:street":"Wagnerstr;Niederoesterreich",
    "iso:country":"AT",
    "sg:address":"Wagnerstr 2",
    "sg:city":"Hinterbr\u00fchl",
    "sg:orig_category":"\u00c3\u201erzte- U Spitalsbedarf",
    "sg:phone":"+43 2236 869021",
    "sg:postcode":"2371",
    "sg:province":"Nieder\u00f6sterreich",
    "wof:name":"CONSPRAX Beratungs- und Handels GmbH",
    "wof:placetype":"venue"
},
  "geometry": {"coordinates":[16.2634468079,48.0839576721],"type":"Point"}
}