{
  "type": "Feature",
  "properties": {
    "addr:full":"Fischhof 1a Wien Wien 1010",
    "addr:housenumber":"1a",
    "addr:postcode":"1010",
    "addr:street":"Fischhof",
    "iso:country":"AT",
    "sg:address":"Fischhof 1a",
    "sg:city":"Wien",
    "sg:orig_category":"Immobilienverwaltungen",
    "sg:phone":"+43 1 53474379",
    "sg:postcode":"1010",
    "sg:province":"Wien",
    "wof:name":"R\u00f6mertor Immobilien- und BaugesmbH",
    "wof:placetype":"venue"
},
  "geometry": {"coordinates":[16.3738937378,48.2107124329],"type":"Point"}
}