{
  "type": "Feature",
  "properties": {
    "iso:country":"AT",
    "sg:address":"Obere Hauptstr 47",
    "sg:city":"Lassee",
    "sg:orig_category":"Hunde- U Katzensalons",
    "sg:phone":"+43 4366 48289056",
    "sg:postcode":"2291",
    "sg:province":"Nieder\u00f6sterreich",
    "wof:name":"Susi und Strolchi",
    "wof:placetype":"venue"
},
  "geometry": {"coordinates":[-76.4168395996,37.452419281],"type":"Point"}
}