{
  "type": "Feature",
  "properties": {
    "addr:full":"Elis 218 See Tirol 6553",
    "addr:housenumber":"218",
    "addr:postcode":"6553",
    "addr:street":"Elis;Tirol",
    "iso:country":"AT",
    "sg:address":"Elis 218",
    "sg:city":"See",
    "sg:orig_category":"Pensionen / Privatzimmer",
    "sg:phone":"+43 5441 8590",
    "sg:postcode":"6553",
    "sg:province":"Tirol",
    "wof:name":"Ehrenberger Erich",
    "wof:placetype":"venue"
},
  "geometry": {"coordinates":[10.4631299973,47.0825309753],"type":"Point"}
}