{
  "type": "Feature",
  "properties": {
    "addr:full":"Josef-Kremslehner-G 1 Pressbaum Nieder\u00f6sterreich 3021",
    "addr:housenumber":"1",
    "addr:postcode":"3021",
    "addr:street":"Josef-Kremslehner-G;Niederoesterreich",
    "iso:country":"AT",
    "sg:address":"Josef-Kremslehner-G 1",
    "sg:city":"Pressbaum",
    "sg:orig_category":"\u00c3\u201erzte / F Allgemeinmedizin",
    "sg:phone":"+43 2233 53049",
    "sg:postcode":"3021",
    "sg:province":"Nieder\u00f6sterreich",
    "wof:name":"Barfu\u00df Karin Dr",
    "wof:placetype":"venue"
},
  "geometry": {"coordinates":[16.0873165131,48.1844520569],"type":"Point"}
}