{
  "type": "Feature",
  "properties": {
    "iso:country":"AT",
    "sg:address":"Zum wei\u00dfen Kreuz 9",
    "sg:city":"Wien",
    "sg:classifiers":[
        {
            "category":"Organizations",
            "subcategory":"Community Association",
            "type":"Services"
        }
    ],
    "sg:phone":"+43 676 3603471",
    "sg:postcode":"1190",
    "sg:province":"Wien",
    "sg:tags":[
        "relation",
        "public"
    ],
    "wof:name":"Holzer Medien Content",
    "wof:placetype":"venue"
},
  "geometry": {"coordinates":[16.3589725494,48.2612724304],"type":"Point"}
}