{
  "type": "Feature",
  "properties": {
    "iso:country":"AT",
    "sg:address":"Anger 64",
    "sg:city":"Faistenau",
    "sg:orig_category":"Transportunternehmen",
    "sg:phone":"+43 6228 7286",
    "sg:postcode":"5324",
    "sg:province":"Salzburg",
    "wof:name":"Resch Transporte",
    "wof:placetype":"venue"
},
  "geometry": {"coordinates":[13.2292079926,47.7754478455],"type":"Point"}
}