{
  "type": "Feature",
  "properties": {
    "addr:full":"Wolfgang K\u00f6pfle-Weg 7 Vils Tirol 6682",
    "addr:housenumber":"7",
    "addr:postcode":"6682",
    "addr:street":"Tirol",
    "iso:country":"AT",
    "sg:address":"Wolfgang K\u00f6pfle-Weg 7",
    "sg:city":"Vils",
    "sg:orig_category":"Friseure U Frisiersalons",
    "sg:phone":"+43 4356 7753016",
    "sg:postcode":"6682",
    "sg:province":"Tirol",
    "wof:name":"Petra's kleines Haarstudio",
    "wof:placetype":"venue"
},
  "geometry": {"coordinates":[10.6301765442,47.5495033264],"type":"Point"}
}