{
  "type": "Feature",
  "properties": {
    "addr:full":"Europastr 3 St. Magdalen K\u00e4rnten 9524",
    "addr:housenumber":"3",
    "addr:postcode":"9524",
    "addr:street":"Europastr;Kaernten",
    "iso:country":"AT",
    "sg:address":"Europastr 3",
    "sg:city":"St. Magdalen",
    "sg:orig_category":"Solartechnik",
    "sg:phone":"+43 4242 4187330",
    "sg:postcode":"9524",
    "sg:province":"K\u00e4rnten",
    "wof:name":"GEO-TEC Solartechnik GmbH",
    "wof:placetype":"venue"
},
  "geometry": {"coordinates":[13.9121189117,46.6102218628],"type":"Point"}
}