{
  "type": "Feature",
  "properties": {
    "addr:full":"Kapuzinerg 10 Dornbirn Vorarlberg 6850",
    "addr:housenumber":"10",
    "addr:postcode":"6850",
    "addr:street":"Kapuzinerg",
    "iso:country":"AT",
    "sg:address":"Kapuzinerg 10",
    "sg:city":"Dornbirn",
    "sg:orig_category":"Non-Classified Establishments",
    "sg:phone":"+43 5572 23146",
    "sg:postcode":"6850",
    "sg:province":"Vorarlberg",
    "wof:name":"Justizanstalt Feldkirch - Aussenstelle Dornbirn",
    "wof:placetype":"venue"
},
  "geometry": {"coordinates":[9.7441940308,47.4089927673],"type":"Point"}
}