{
  "type": "Feature",
  "properties": {
    "addr:full":"Hammersdorf 82 Pettenbach Ober\u00f6sterreich 4643",
    "addr:housenumber":"82",
    "addr:postcode":"4643",
    "addr:street":"Hammersdorf",
    "iso:country":"AT",
    "sg:address":"Hammersdorf 82",
    "sg:city":"Pettenbach",
    "sg:orig_category":"Schneidereien",
    "sg:phone":"+43 7586 20502",
    "sg:postcode":"4643",
    "sg:province":"Ober\u00f6sterreich",
    "wof:name":"M\u00f6rtenhumer Michaela",
    "wof:placetype":"venue"
},
  "geometry": {"coordinates":[14.0650529861,47.9619407654],"type":"Point"}
}