{
  "type": "Feature",
  "properties": {
    "addr:full":"Andreas-Hofer-Str 14 Innsbruck Tirol 6020",
    "addr:housenumber":"14",
    "addr:postcode":"6020",
    "addr:street":"Andreas-Hofer-Str;Tirol",
    "iso:country":"AT",
    "sg:address":"Andreas-Hofer-Str 14",
    "sg:city":"Innsbruck",
    "sg:classifiers":[
        {
            "category":"Communications",
            "subcategory":"Film & Video Production",
            "type":"Services"
        }
    ],
    "sg:phone":"+43 512 572344",
    "sg:postcode":"6020",
    "sg:province":"Tirol",
    "sg:tags":[
        "multimedia"
    ],
    "wof:name":"AltNeuland Bildschirmwerkstatt - Hofinger Niko",
    "wof:placetype":"venue"
},
  "geometry": {"coordinates":[11.3914842606,47.2607307434],"type":"Point"}
}