{
  "type": "Feature",
  "properties": {
    "iso:country":"AT",
    "sg:address":"Siemensstr 58",
    "sg:city":"Linz",
    "sg:orig_category":"Volksschulen",
    "sg:phone":"+43 732 380638",
    "sg:postcode":"4030",
    "sg:province":"Ober\u00f6sterreich",
    "wof:name":"Volksschule 35 Wegscheid",
    "wof:placetype":"venue"
},
  "geometry": {"coordinates":[14.2841567993,48.2480392456],"type":"Point"}
}