{
  "type": "Feature",
  "properties": {
    "iso:country":"AT",
    "sg:address":"Badergrabenweg 21 ",
    "sg:city":"Litschau",
    "sg:orig_category":"CarpenterS Work Supraregional",
    "sg:phone":"+43 2865 5955",
    "sg:postcode":"3874",
    "sg:province":"Nieder\u00f6sterreich",
    "sg:website":"www.meisterdach.at",
    "wof:name":"Herbert Eschelm\u00fcller Ges.m.b.H.",
    "wof:placetype":"venue"
},
  "geometry": {"coordinates":[15.048374176,48.9431724548],"type":"Point"}
}