{
  "type": "Feature",
  "properties": {
    "addr:full":"Marktstr 9 Dornbirn Vorarlberg 6850",
    "addr:housenumber":"9",
    "addr:postcode":"6850",
    "addr:street":"Marktstr",
    "iso:country":"AT",
    "sg:address":"Marktstr 9",
    "sg:city":"Dornbirn",
    "sg:orig_category":"Bekleidung / Einzelhandel",
    "sg:phone":"+43 5572 23648",
    "sg:postcode":"6850",
    "sg:province":"Vorarlberg",
    "wof:name":"La Donna Fashion L' Uomo Men's Fashion Inh Ambros Mayer",
    "wof:placetype":"venue"
},
  "geometry": {"coordinates":[9.7426214218,47.413143158],"type":"Point"}
}