{
  "type": "Feature",
  "properties": {
    "addr:full":"Sonnhalberweg 2 Wolfsberg K\u00e4rnten 9400",
    "addr:housenumber":"2;kaernten",
    "addr:postcode":"9400",
    "addr:street":"Sonnhalberweg",
    "iso:country":"AT",
    "sg:address":"Sonnhalberweg 2",
    "sg:city":"Wolfsberg",
    "sg:orig_category":"Bekleidung / Einzelhandel",
    "sg:phone":"+43 4352 36086",
    "sg:postcode":"9400",
    "sg:province":"K\u00e4rnten",
    "wof:name":"Takko ModeMarkt GmbH",
    "wof:placetype":"venue"
},
  "geometry": {"coordinates":[14.8397903442,46.8174552917],"type":"Point"}
}