{
  "type": "Feature",
  "properties": {
    "iso:country":"AT",
    "sg:address":"\u00dcberlendnerstr 24a",
    "sg:city":"Walding",
    "sg:orig_category":"Bootsvermietung",
    "sg:phone":"+43 7234 84545",
    "sg:postcode":"4111",
    "sg:province":"Ober\u00f6sterreich",
    "wof:name":"Yachting 2000 Limberger OEG",
    "wof:placetype":"venue"
},
  "geometry": {"coordinates":[14.1589193344,48.3504638672],"type":"Point"}
}