{
  "type": "Feature",
  "properties": {
    "addr:full":"Am Gamauf 23 Ulrichskirchen Nieder\u00f6sterreich 2122",
    "addr:housenumber":"23",
    "addr:postcode":"2122",
    "addr:street":"Am Gamauf",
    "iso:country":"AT",
    "sg:address":"Am Gamauf 23",
    "sg:city":"Ulrichskirchen",
    "sg:orig_category":"Personalberatung",
    "sg:phone":"+43 2245 20120",
    "sg:postcode":"2122",
    "sg:province":"Nieder\u00f6sterreich",
    "wof:name":"Stifter et partner",
    "wof:placetype":"venue"
},
  "geometry": {"coordinates":[-64.9468917847,-3.7910699844],"type":"Point"}
}