{
  "type": "Feature",
  "properties": {
    "addr:full":"Ausseer Str 21 Liezen Steiermark 8940",
    "addr:postcode":"8940",
    "addr:street":"Str 21",
    "iso:country":"AT",
    "sg:address":"Ausseer Str 21",
    "sg:city":"Liezen",
    "sg:orig_category":"Elektroinstallationsunternehmen",
    "sg:phone":"+43 3612 222830",
    "sg:postcode":"8940",
    "sg:province":"Steiermark",
    "wof:name":"Sch\u00f6ppel Ing Nfg Alfred Lemmerer",
    "wof:placetype":"venue"
},
  "geometry": {"coordinates":[14.2406311035,47.5689697266],"type":"Point"}
}