{
  "type": "Feature",
  "properties": {
    "addr:full":"Deutsch Minihof 54 Mogersdorf Burgenland 8382",
    "addr:housenumber":"54",
    "addr:postcode":"8382",
    "addr:street":"Minihof",
    "iso:country":"AT",
    "sg:address":"Deutsch Minihof 54",
    "sg:city":"Mogersdorf",
    "sg:classifiers":[
        {
            "category":"Industrial Area",
            "type":"Public Place"
        }
    ],
    "sg:phone":"+43 3325 20282",
    "sg:postcode":"8382",
    "sg:province":"Burgenland",
    "sg:tags":[
        "ovens",
        "heated",
        "furnace",
        "electrically"
    ],
    "sg:website":"david-baader.de",
    "wof:name":"SIT Scheibreithner Industrie Technik KEG Generalvertretung f\u00fcr David + Baader Ofensysteme",
    "wof:placetype":"venue"
},
  "geometry": {"coordinates":[16.2483253479,46.9605865479],"type":"Point"}
}