{
  "type": "Feature",
  "properties": {
    "addr:full":"Kremstal Bundesstr 5 Pasching Ober\u00f6sterreich 4061",
    "addr:housenumber":"5",
    "addr:postcode":"4061",
    "addr:street":"Oberoesterreich",
    "iso:country":"AT",
    "sg:address":"Kremstal Bundesstr 5",
    "sg:city":"Pasching",
    "sg:orig_category":"Waren Aller Art",
    "sg:phone":"+43 7229 61121",
    "sg:postcode":"4061",
    "sg:province":"Ober\u00f6sterreich",
    "wof:name":"SERIL GmbH",
    "wof:placetype":"venue"
},
  "geometry": {"coordinates":[14.2353391647,48.2410049438],"type":"Point"}
}