{
  "type": "Feature",
  "properties": {
    "addr:full":"Ruster Str 86-104 EZE Eisenstadt Top 24 Eisenstadt Burgenland 7000",
    "addr:postcode":"86-104;7000",
    "addr:street":"Str;Top",
    "iso:country":"AT",
    "sg:address":"Ruster Str 86-104 EZE Eisenstadt Top 24",
    "sg:city":"Eisenstadt",
    "sg:orig_category":"Papier- U Schreibwaren / Einzelhandel",
    "sg:phone":"+43 4326 8261536",
    "sg:postcode":"7000",
    "sg:province":"Burgenland",
    "wof:name":"SKRIBO",
    "wof:placetype":"venue"
},
  "geometry": {"coordinates":[16.5189552307,47.8455657959],"type":"Point"}
}