{
  "type": "Feature",
  "properties": {
    "addr:full":"Eisenst\u00e4dter Str 72 Breitenbrunn Burgenland 7091",
    "addr:postcode":"7091",
    "addr:street":"Str 72",
    "iso:country":"AT",
    "sg:address":"Eisenst\u00e4dter Str 72",
    "sg:city":"Breitenbrunn",
    "sg:orig_category":"Elektroinstallationsunternehmen",
    "sg:phone":"+43 2683 5279",
    "sg:postcode":"7091",
    "sg:province":"Burgenland",
    "wof:name":"Moser Gerhard GesmbH",
    "wof:placetype":"venue"
},
  "geometry": {"coordinates":[16.728055954,47.9406051636],"type":"Point"}
}