{
  "type": "Feature",
  "properties": {
    "addr:full":"Hainfelder Str 19 Pottenstein Nieder\u00f6sterreich 2563",
    "addr:postcode":"2563",
    "addr:street":"Str 19",
    "iso:country":"AT",
    "sg:address":"Hainfelder Str 19",
    "sg:city":"Pottenstein",
    "sg:orig_category":"Garten- U Landschaftsgestaltung",
    "sg:phone":"+43 4326 7283979",
    "sg:postcode":"2563",
    "sg:province":"Nieder\u00f6sterreich",
    "wof:name":"Blazek Christian",
    "wof:placetype":"venue"
},
  "geometry": {"coordinates":[16.0937576294,47.9605140686],"type":"Point"}
}