{
  "type": "Feature",
  "properties": {
    "iso:country":"AT",
    "sg:address":"M\u00fchlein 44",
    "sg:city":"Weyer",
    "sg:orig_category":"Pensionen / Privatzimmer",
    "sg:phone":"+43 7355 6537",
    "sg:postcode":"3335",
    "sg:province":"Ober\u00f6sterreich",
    "wof:name":"Krenn Rosa",
    "wof:placetype":"venue"
},
  "geometry": {"coordinates":[14.6647500992,47.8578910828],"type":"Point"}
}