{
  "type": "Feature",
  "properties": {
    "addr:full":"Dichterstr 1 Allhaming Ober\u00f6sterreich 4511",
    "addr:housenumber":"1",
    "addr:postcode":"4511",
    "addr:street":"Dichterstr",
    "iso:country":"AT",
    "sg:address":"Dichterstr 1",
    "sg:city":"Allhaming",
    "sg:orig_category":"Gemeinden",
    "sg:phone":"+43 4372 277155",
    "sg:postcode":"4511",
    "sg:province":"Ober\u00f6sterreich",
    "wof:name":"Gemeindeamt Allhaming",
    "wof:placetype":"venue"
},
  "geometry": {"coordinates":[14.172580719,48.1534843445],"type":"Point"}
}