{
  "type": "Feature",
  "properties": {
    "addr:full":"Ganglbauerstr 9 Wolfern Ober\u00f6sterreich 4493",
    "addr:housenumber":"9",
    "addr:postcode":"4493",
    "addr:street":"Ganglbauerstr",
    "iso:country":"AT",
    "sg:address":"Ganglbauerstr 9",
    "sg:city":"Wolfern",
    "sg:orig_category":"Ingenieurkonsulenten / Zivilingenieure",
    "sg:phone":"+43 7253 83120",
    "sg:postcode":"4493",
    "sg:province":"Ober\u00f6sterreich",
    "wof:name":"Forstenlehner Ludwig Dipl-Ing",
    "wof:placetype":"venue"
},
  "geometry": {"coordinates":[14.3743438721,48.0698928833],"type":"Point"}
}