{
  "type": "Feature",
  "properties": {
    "addr:full":"Gustav-Tschermak-G 4 Wien Wien 1180",
    "addr:housenumber":"4",
    "addr:postcode":"1180",
    "addr:street":"Gustav-Tschermak-G",
    "iso:country":"AT",
    "sg:address":"Gustav-Tschermak-G 4",
    "sg:city":"Wien",
    "sg:classifiers":[
        {
            "category":"Professional",
            "subcategory":"Art Services",
            "type":"Services"
        }
    ],
    "sg:phone":"+43 4314 7001900",
    "sg:postcode":"1180",
    "sg:province":"Wien",
    "sg:tags":[
        "designer"
    ],
    "wof:name":"Wurm Design",
    "wof:placetype":"venue"
},
  "geometry": {"coordinates":[16.3395957947,48.2317848206],"type":"Point"}
}