{
  "type": "Feature",
  "properties": {
    "iso:country":"AT",
    "sg:address":"Schlo\u00dfbergstr 11",
    "sg:city":"Gro\u00dfru\u00dfbach",
    "sg:orig_category":"Non-Classified Establishments",
    "sg:phone":"+43 2263 6695",
    "sg:postcode":"2114",
    "sg:province":"Nieder\u00f6sterreich",
    "wof:name":"Pfarramt",
    "wof:placetype":"venue"
},
  "geometry": {"coordinates":[-95.7533187866,34.9332122803],"type":"Point"}
}