{
  "type": "Feature",
  "properties": {
    "addr:full":"Rohrmoosstr 60 Rohrmoos-Untertal Steiermark 8971",
    "addr:housenumber":"60",
    "addr:postcode":"8971",
    "addr:street":"Rohrmoosstr",
    "iso:country":"AT",
    "sg:address":"Rohrmoosstr 60",
    "sg:city":"Rohrmoos-Untertal",
    "sg:orig_category":"Unternehmensberatung",
    "sg:phone":"+43 3687 616800",
    "sg:postcode":"8971",
    "sg:province":"Steiermark",
    "wof:name":"DATA-connect Verrechnungs- und Beratungs GmbH",
    "wof:placetype":"venue"
},
  "geometry": {"coordinates":[13.6315746307,47.3756942749],"type":"Point"}
}