{
  "type": "Feature",
  "properties": {
    "addr:full":"Fuhrmannsg 20 St. P\u00f6lten Nieder\u00f6sterreich 3100",
    "addr:housenumber":"20",
    "addr:postcode":"3100",
    "addr:street":"Fuhrmannsg",
    "iso:country":"AT",
    "sg:address":"Fuhrmannsg 20",
    "sg:city":"St. P\u00f6lten",
    "sg:orig_category":"Werbegrafik- U Grafik-Design",
    "sg:phone":"+43 4327 4231991",
    "sg:postcode":"3100",
    "sg:province":"Nieder\u00f6sterreich",
    "wof:name":"Atelier Wurm",
    "wof:placetype":"venue"
},
  "geometry": {"coordinates":[-76.07303619379999,41.7845001221],"type":"Point"}
}