{
  "type": "Feature",
  "properties": {
    "addr:full":"Attergaustr 1 St. Georgen im Attergau Ober\u00f6sterreich 4880",
    "addr:housenumber":"1",
    "addr:postcode":"4880",
    "addr:street":"Attergaustr",
    "iso:country":"AT",
    "sg:address":"Attergaustr 1",
    "sg:city":"St. Georgen im Attergau",
    "sg:orig_category":"Lebensmittel / Einzelhandel",
    "sg:phone":"+43 4376 675112",
    "sg:postcode":"4880",
    "sg:province":"Ober\u00f6sterreich",
    "wof:name":"Billa AG",
    "wof:placetype":"venue"
},
  "geometry": {"coordinates":[13.4934415817,47.932220459],"type":"Point"}
}