{
  "type": "Feature",
  "properties": {
    "iso:country":"AT",
    "sg:address":"Salzburger Str 531",
    "sg:city":"Gro\u00dfgmain",
    "sg:orig_category":"Erdarbeiten",
    "sg:phone":"+43 4362 477328",
    "sg:postcode":"5084",
    "sg:province":"Salzburg",
    "wof:name":"Eder Johann Erdbwewegungs- u Transport GesmbH & Co KG",
    "wof:placetype":"venue"
},
  "geometry": {"coordinates":[12.0809497833,48.0439414978],"type":"Point"}
}