{
  "type": "Feature",
  "properties": {
    "iso:country":"AT",
    "sg:address":"Matthias-Schmid-Str 12",
    "sg:city":"Innsbruck",
    "sg:orig_category":"Offsetdruckereien",
    "sg:phone":"+43 512 59140",
    "sg:postcode":"6020",
    "sg:province":"Tirol",
    "wof:name":"WUB Wagner'sche Universit\u00e4tsdruckerei GmbH",
    "wof:placetype":"venue"
},
  "geometry": {"coordinates":[11.413476944,47.2756347656],"type":"Point"}
}