{
  "type": "Feature",
  "properties": {
    "addr:full":"Westbahnstrasse 62 Marchtrenk Ober\u00f6sterreich 4614",
    "addr:housenumber":"62",
    "addr:postcode":"4614",
    "addr:street":"Westbahnstrasse",
    "iso:country":"AT",
    "sg:address":"Westbahnstrasse 62",
    "sg:city":"Marchtrenk",
    "sg:classifiers":[
        {
            "category":"Retail",
            "subcategory":"Repair Shop",
            "type":"Services"
        }
    ],
    "sg:phone":"+43 7243 521410",
    "sg:postcode":"4614",
    "sg:province":"Ober\u00f6sterreich",
    "sg:tags":[
        "agricultural",
        "machinery"
    ],
    "sg:website":"bauholding.at",
    "wof:name":"BMTI-Baumaschinentechnik International GmbH",
    "wof:placetype":"venue"
},
  "geometry": {"coordinates":[14.0904598236,48.1971511841],"type":"Point"}
}