{
  "type": "Feature",
  "properties": {
    "addr:full":"Lindrainweg 59 Hopfgarten im Brixental Tirol 6361",
    "addr:housenumber":"59",
    "addr:postcode":"6361",
    "addr:street":"Lindrainweg;Tirol",
    "iso:country":"AT",
    "sg:address":"Lindrainweg 59",
    "sg:city":"Hopfgarten im Brixental",
    "sg:orig_category":"Appartements / Ferienwohnungen",
    "sg:phone":"+43 5335 2704",
    "sg:postcode":"6361",
    "sg:province":"Tirol",
    "wof:name":"Erbhof Hinting",
    "wof:placetype":"venue"
},
  "geometry": {"coordinates":[12.172082901,47.4483566284],"type":"Point"}
}