{
  "type": "Feature",
  "properties": {
    "addr:full":"Halbgasse 9 Spannberg Nieder\u00f6sterreich 2244",
    "addr:housenumber":"9",
    "addr:postcode":"2244",
    "addr:street":"Halbgasse",
    "iso:country":"AT",
    "sg:address":"Halbgasse 9",
    "sg:city":"Spannberg",
    "sg:classifiers":[
        {
            "category":"Shopping",
            "subcategory":"Crafts & Fabrics",
            "type":"Retail Goods"
        }
    ],
    "sg:phone":"+43 2538 8989",
    "sg:postcode":"2244",
    "sg:province":"Nieder\u00f6sterreich",
    "sg:tags":[
        "decorative"
    ],
    "wof:name":"Rainer Wengraf",
    "wof:placetype":"venue"
},
  "geometry": {"coordinates":[16.7371940613,48.4660186768],"type":"Point"}
}