{
  "type": "Feature",
  "properties": {
    "addr:full":"Reinholzg 7 Kapfenberg Steiermark 8605",
    "addr:housenumber":"7",
    "addr:postcode":"8605",
    "addr:street":"Reinholzg",
    "iso:country":"AT",
    "sg:address":"Reinholzg 7",
    "sg:city":"Kapfenberg",
    "sg:orig_category":"Lebensmittel / Einzelhandel",
    "sg:phone":"+43 3862 21053",
    "sg:postcode":"8605",
    "sg:province":"Steiermark",
    "wof:name":"A & O Nahversorger pro mente Steiermark",
    "wof:placetype":"venue"
},
  "geometry": {"coordinates":[15.2995328903,47.4497718811],"type":"Point"}
}