{
  "type": "Feature",
  "properties": {
    "iso:country":"AT",
    "sg:address":"Judendorfer Str 46a",
    "sg:city":"Villach",
    "sg:orig_category":"Pensionen / Privatzimmer",
    "sg:phone":"+43 4242 317977",
    "sg:postcode":"9500",
    "sg:province":"K\u00e4rnten",
    "wof:name":"Hopfgartner",
    "wof:placetype":"venue"
},
  "geometry": {"coordinates":[13.8238372803,46.5984153748],"type":"Point"}
}