{
  "type": "Feature",
  "properties": {
    "addr:full":"Nr 19 Krakaudorf Steiermark 8854",
    "addr:postcode":"8854",
    "addr:street":"Nr",
    "iso:country":"AT",
    "sg:address":"Nr 19",
    "sg:city":"Krakaudorf",
    "sg:orig_category":"Pensionen / Privatzimmer",
    "sg:phone":"+43 3535 8295",
    "sg:postcode":"8854",
    "sg:province":"Steiermark",
    "wof:name":"Spreitzer Aloisia",
    "wof:placetype":"venue"
},
  "geometry": {"coordinates":[13.9921045303,47.1786117554],"type":"Point"}
}