{
  "type": "Feature",
  "properties": {
    "addr:full":"Nr 285 M\u00f6nichkirchen Nieder\u00f6sterreich 2872",
    "addr:housenumber":"2872",
    "addr:street":"Nr;Moenichkirchen Niederoesterreich",
    "iso:country":"AT",
    "sg:address":"Nr 285",
    "sg:city":"M\u00f6nichkirchen",
    "sg:orig_category":"Ingenieurkonsulenten / Zivilingenieure",
    "sg:phone":"+43 2649 278",
    "sg:postcode":"2872",
    "sg:province":"Nieder\u00f6sterreich",
    "wof:name":"Buschina Felix Dipl-Ing",
    "wof:placetype":"venue"
},
  "geometry": {"coordinates":[166.9221496582,-0.5282999873],"type":"Point"}
}