{
  "type": "Feature",
  "properties": {
    "addr:full":"Sonnleitnerg 1 Wiener Neustadt Nieder\u00f6sterreich 2700",
    "addr:housenumber":"1",
    "addr:postcode":"2700",
    "addr:street":"Sonnleitnerg",
    "iso:country":"AT",
    "sg:address":"Sonnleitnerg 1",
    "sg:city":"Wiener Neustadt",
    "sg:orig_category":"Sonderschulen",
    "sg:phone":"+43 2622 373360",
    "sg:postcode":"2700",
    "sg:province":"Nieder\u00f6sterreich",
    "wof:name":"Allgemeine Sonderschule",
    "wof:placetype":"venue"
},
  "geometry": {"coordinates":[16.2407817841,47.825176239],"type":"Point"}
}