{
  "type": "Feature",
  "properties": {
    "addr:full":"Lend 25 Lend Salzburg 5651",
    "addr:housenumber":"25",
    "addr:postcode":"5651",
    "addr:street":"Lend;Salzburg",
    "iso:country":"AT",
    "sg:address":"Lend 25",
    "sg:city":"Lend",
    "sg:classifiers":[
        {
            "category":"Manufacturing",
            "subcategory":"Motor Vehicles & Parts",
            "type":"Manufacturing & Wholesale Goods"
        }
    ],
    "sg:phone":"+43 7722 8870",
    "sg:postcode":"5651",
    "sg:province":"Salzburg",
    "sg:tags":[
        "product",
        "automotive",
        "aluminium",
        "finished",
        "industry"
    ],
    "sg:website":"sag.at",
    "wof:name":"Euromotive Ges.m.b.H. & Co KG",
    "wof:placetype":"venue"
},
  "geometry": {"coordinates":[13.051864624,47.2966117859],"type":"Point"}
}