{
  "type": "Feature",
  "properties": {
    "addr:full":"Eichetstr 7 Wals Salzburg 5071",
    "addr:housenumber":"7",
    "addr:postcode":"5071",
    "addr:street":"Eichetstr;Salzburg",
    "iso:country":"AT",
    "sg:address":"Eichetstr 7",
    "sg:city":"Wals",
    "sg:orig_category":"Appartements / Ferienwohnungen",
    "sg:phone":"+43 662 853591",
    "sg:postcode":"5071",
    "sg:province":"Salzburg",
    "wof:name":"Ferienwohnungen Fam Zemanek",
    "wof:placetype":"venue"
},
  "geometry": {"coordinates":[12.998550415,47.7844924927],"type":"Point"}
}