{
  "type": "Feature",
  "properties": {
    "addr:full":"Enderstr 15a Altach Vorarlberg 6844",
    "addr:housenumber":"15a",
    "addr:postcode":"6844",
    "addr:street":"Enderstr",
    "iso:country":"AT",
    "sg:address":"Enderstr 15a",
    "sg:city":"Altach",
    "sg:orig_category":"Volksschulen",
    "sg:phone":"+43 5576 74949",
    "sg:postcode":"6844",
    "sg:province":"Vorarlberg",
    "wof:name":"Private Volksschule Altach m \u00d6ffentlichkeitsrecht",
    "wof:placetype":"venue"
},
  "geometry": {"coordinates":[9.6554803848,47.3553237915],"type":"Point"}
}