{
  "type": "Feature",
  "properties": {
    "iso:country":"AT",
    "sg:address":"Karfreitstr 24/4",
    "sg:city":"Klagenfurt",
    "sg:orig_category":"Personalbereitstellung",
    "sg:phone":"+43 463 590421",
    "sg:postcode":"9020",
    "sg:province":"K\u00e4rnten",
    "wof:name":"Proworks Personal- und Montageservice GmbH & Co KEG",
    "wof:placetype":"venue"
},
  "geometry": {"coordinates":[14.3085947037,46.6215133667],"type":"Point"}
}