{
  "type": "Feature",
  "properties": {
    "iso:country":"AT",
    "sg:city":"Schalchen",
    "sg:orig_category":"Feuerwehren",
    "sg:phone":"+43 7742 4932",
    "sg:postcode":"5231",
    "sg:province":"Ober\u00f6sterreich",
    "wof:name":"Freiwillige Feuerwehr Stallhofen",
    "wof:placetype":"venue"
},
  "geometry": {"coordinates":[13.1769418716,48.0978012085],"type":"Point"}
}