{
  "type": "Feature",
  "properties": {
    "addr:full":"Resselstr 3 St. Valentin Nieder\u00f6sterreich 4300",
    "addr:housenumber":"3",
    "addr:postcode":"4300",
    "addr:street":"Resselstr",
    "iso:country":"AT",
    "sg:address":"Resselstr 3",
    "sg:city":"St. Valentin",
    "sg:orig_category":"Zimmereien",
    "sg:phone":"+43 4374 3554576",
    "sg:postcode":"4300",
    "sg:province":"Nieder\u00f6sterreich",
    "wof:name":"AUER I.H.G. Handels GmbH",
    "wof:placetype":"venue"
},
  "geometry": {"coordinates":[14.5330696106,48.174621582],"type":"Point"}
}