{
  "type": "Feature",
  "properties": {
    "addr:full":"Hochsteing 11 Graz Steiermark 8010",
    "addr:housenumber":"11",
    "addr:postcode":"8010",
    "addr:street":"Hochsteing",
    "iso:country":"AT",
    "sg:address":"Hochsteing 11",
    "sg:city":"Graz",
    "sg:orig_category":"Behinderungen / Leben Mit Behinderungen",
    "sg:phone":"+43 316 681369",
    "sg:postcode":"8010",
    "sg:province":"Steiermark",
    "wof:name":"Caritas MOHI Familienentlastung und mobile Hilfe",
    "wof:placetype":"venue"
},
  "geometry": {"coordinates":[15.4369935989,47.0882644653],"type":"Point"}
}