{
  "type": "Feature",
  "properties": {
    "addr:full":"Neunkirchner Strasse 119 Wiener Neustadt Nieder\u00f6sterreich 2700",
    "addr:housenumber":"119",
    "addr:postcode":"2700",
    "addr:street":"Neunkirchner Strasse",
    "iso:country":"AT",
    "sg:address":"Neunkirchner Strasse 119",
    "sg:city":"Wiener Neustadt",
    "sg:classifiers":[
        {
            "category":"Building & Trades",
            "subcategory":"Cleaning & Sanitation",
            "type":"Services"
        }
    ],
    "sg:phone":"+43 2622 872150",
    "sg:postcode":"2700",
    "sg:province":"Nieder\u00f6sterreich",
    "sg:tags":[
        "technical",
        "services"
    ],
    "sg:website":"asa-group.com",
    "wof:name":".A.S.A. Abfallservice Wiener Neustadt Gesellschaft m.b.H.",
    "wof:placetype":"venue"
},
  "geometry": {"coordinates":[16.224647522,47.7981147766],"type":"Point"}
}