{
  "type": "Feature",
  "properties": {
    "addr:full":"Breiteneicher Str 3 Horn Nieder\u00f6sterreich 3580",
    "addr:housenumber":"3",
    "addr:postcode":"3580",
    "addr:street":"Str;Niederoesterreich",
    "iso:country":"AT",
    "sg:address":"Breiteneicher Str 3",
    "sg:city":"Horn",
    "sg:orig_category":"Lebensmittel / Erzeugung U Gro\u00c3\u0178handel",
    "sg:phone":"+43 4329 8220870",
    "sg:postcode":"3580",
    "sg:province":"Nieder\u00f6sterreich",
    "wof:name":"Schuberts K\u00f6stlichkeiten HandelsgesmbH",
    "wof:placetype":"venue"
},
  "geometry": {"coordinates":[15.6712665558,48.6668701172],"type":"Point"}
}