{
  "type": "Feature",
  "properties": {
    "addr:full":"Gartenfeldstr 2-4 Tulln an der Donau Nieder\u00f6sterreich 3430",
    "addr:housenumber":"2-4",
    "addr:postcode":"3430",
    "addr:street":"Gartenfeldstr",
    "iso:country":"AT",
    "sg:address":"Gartenfeldstr 2-4",
    "sg:city":"Tulln an der Donau",
    "sg:orig_category":"Sonnenstudios",
    "sg:phone":"+43 2272 81225",
    "sg:postcode":"3430",
    "sg:province":"Nieder\u00f6sterreich",
    "wof:name":"Sunplexx The Ultimate Sunstudio",
    "wof:placetype":"venue"
},
  "geometry": {"coordinates":[16.048910141,48.3249053955],"type":"Point"}
}