{
  "type": "Feature",
  "properties": {
    "iso:country":"AT",
    "sg:address":"Nr 246",
    "sg:city":"Breitenbach am Inn",
    "sg:orig_category":"Friseure U Frisiersalons",
    "sg:phone":"+43 4353 387604",
    "sg:postcode":"6252",
    "sg:province":"Tirol",
    "wof:name":"Zimmermann Erwin",
    "wof:placetype":"venue"
},
  "geometry": {"coordinates":[11.973446846,47.4788246155],"type":"Point"}
}