{
  "type": "Feature",
  "properties": {
    "addr:full":"Europapl 12/10 Graz Steiermark 8020",
    "addr:housenumber":"12 / 10",
    "addr:postcode":"8020",
    "addr:street":"Europapl",
    "iso:country":"AT",
    "sg:address":"Europapl 12/10",
    "sg:city":"Graz",
    "sg:orig_category":"Personalbereitstellung",
    "sg:phone":"+43 4331 6717274",
    "sg:postcode":"8020",
    "sg:province":"Steiermark",
    "sg:website":"rex-dienstleistungen.com",
    "wof:name":"Rex HandelsgesmbH & Co KG",
    "wof:placetype":"venue"
},
  "geometry": {"coordinates":[15.4170770645,47.0742988586],"type":"Point"}
}