{
  "type": "Feature",
  "properties": {
    "iso:country":"AT",
    "sg:address":"Swarovskistrasse 33",
    "sg:city":"Schwaz",
    "sg:classifiers":[
        {
            "category":"Manufacturing",
            "subcategory":"Tools & Machinery",
            "type":"Manufacturing & Wholesale Goods"
        }
    ],
    "sg:phone":"+43 5242 6060",
    "sg:postcode":"6130",
    "sg:province":"Tirol",
    "sg:tags":[
        "abrasive"
    ],
    "sg:website":"tyrolit.com",
    "wof:name":"Tyrolit Schleifmittelwerke Swarovski KG",
    "wof:placetype":"venue"
},
  "geometry": {"coordinates":[11.7007713318,47.3464927673],"type":"Point"}
}