{
  "type": "Feature",
  "properties": {
    "addr:full":"Villacher Str 22 Spittal an der Drau K\u00e4rnten 9800",
    "addr:housenumber":"22",
    "addr:postcode":"9800",
    "addr:street":"Str;Kaernten",
    "iso:country":"AT",
    "sg:address":"Villacher Str 22",
    "sg:city":"Spittal an der Drau",
    "sg:orig_category":"Fleischhauereien",
    "sg:phone":"+43 4762 37662",
    "sg:postcode":"9800",
    "sg:province":"K\u00e4rnten",
    "wof:name":"Schirnhofer-Breisler GesmbH - Shop in Shop",
    "wof:placetype":"venue"
},
  "geometry": {"coordinates":[13.5030298233,46.7950553894],"type":"Point"}
}