{
  "type": "Feature",
  "properties": {
    "addr:full":"Vogelau 28-30 Hohenruppersdorf Nieder\u00f6sterreich 2223",
    "addr:housenumber":"28-30",
    "addr:postcode":"2223",
    "addr:street":"Vogelau",
    "iso:country":"AT",
    "sg:address":"Vogelau 28-30",
    "sg:city":"Hohenruppersdorf",
    "sg:orig_category":"Tischlereien",
    "sg:phone":"+43 2574 82010",
    "sg:postcode":"2223",
    "sg:province":"Nieder\u00f6sterreich",
    "sg:website":"www.schreitl.at",
    "wof:name":"Tischlerei Schreitl",
    "wof:placetype":"venue"
},
  "geometry": {"coordinates":[16.6568565369,48.4597930908],"type":"Point"}
}