{
  "type": "Feature",
  "properties": {
    "addr:full":"Stahlm\u00fchle 3-4 Haslach an der M\u00fchl Ober\u00f6sterreich 4170",
    "addr:housenumber":"3-4",
    "addr:postcode":"4170",
    "addr:street":"Stahlmuehle;Oberoesterreich",
    "iso:country":"AT",
    "sg:address":"Stahlm\u00fchle 3-4",
    "sg:city":"Haslach an der M\u00fchl",
    "sg:orig_category":"Felt Slippers",
    "sg:phone":"+43 7289 72180",
    "sg:postcode":"4170",
    "sg:province":"Ober\u00f6sterreich",
    "sg:website":"alom.at/twh",
    "wof:name":"ALOM Manufaktur",
    "wof:placetype":"venue"
},
  "geometry": {"coordinates":[14.1033849716,48.5675315857],"type":"Point"}
}