{
  "type": "Feature",
  "properties": {
    "addr:full":"Dinghoferstr 60 Linz Ober\u00f6sterreich 4020",
    "addr:housenumber":"60",
    "addr:postcode":"4020",
    "addr:street":"Dinghoferstr",
    "iso:country":"AT",
    "sg:address":"Dinghoferstr 60",
    "sg:city":"Linz",
    "sg:orig_category":"Friseure U Frisiersalons",
    "sg:phone":"+43 4373 2663633",
    "sg:postcode":"4020",
    "sg:province":"Ober\u00f6sterreich",
    "wof:name":"Strau\u00df Brigitte",
    "wof:placetype":"venue"
},
  "geometry": {"coordinates":[14.2988243103,48.2968101501],"type":"Point"}
}