{
  "type": "Feature",
  "properties": {
    "addr:full":"Rofansiedlung 490h Jenbach Tirol 6200",
    "addr:housenumber":"490h",
    "addr:postcode":"6200",
    "addr:street":"Rofansiedlung;Tirol",
    "iso:country":"AT",
    "sg:address":"Rofansiedlung 490h",
    "sg:city":"Jenbach",
    "sg:classifiers":[
        {
            "category":"Professional",
            "subcategory":"Credit Reporting & Collection",
            "type":"Services"
        }
    ],
    "sg:phone":"+43 5244 64077",
    "sg:postcode":"6200",
    "sg:province":"Tirol",
    "sg:tags":[
        "processing",
        "data"
    ],
    "sg:website":"alpha-edv.at",
    "wof:name":"Alpha EDV-Consulting GmbH & Co KEG",
    "wof:placetype":"venue"
},
  "geometry": {"coordinates":[11.7709331512,47.3917541504],"type":"Point"}
}