{
  "type": "Feature",
  "properties": {
    "iso:country":"AT",
    "sg:address":"Fuchsgraben 17",
    "sg:city":"Oberneukirchen",
    "sg:orig_category":"Schmieden U Schmiedeeisenelemente",
    "sg:phone":"+43 4372 1270610",
    "sg:postcode":"4181",
    "sg:province":"Ober\u00f6sterreich",
    "wof:name":"Kollros Johann",
    "wof:placetype":"venue"
},
  "geometry": {"coordinates":[14.2180013657,48.4743995667],"type":"Point"}
}