{
  "type": "Feature",
  "properties": {
    "addr:full":"Eckhlg 7 Enzesfeld-Lindabrunn Nieder\u00f6sterreich 2551",
    "addr:housenumber":"7",
    "addr:postcode":"2551",
    "addr:street":"Eckhlg;Niederoesterreich",
    "iso:country":"AT",
    "sg:address":"Eckhlg 7",
    "sg:city":"Enzesfeld-Lindabrunn",
    "sg:orig_category":"Weiterbildungsinstitute M Allg U Berufl Bildungsangebot",
    "sg:phone":"+43 650 2022444",
    "sg:postcode":"2551",
    "sg:province":"Nieder\u00f6sterreich",
    "wof:name":"A & A Business Support - Inh Andrea Pucher",
    "wof:placetype":"venue"
},
  "geometry": {"coordinates":[16.1836013794,47.9182281494],"type":"Point"}
}