{
  "type": "Feature",
  "properties": {
    "addr:full":"Stadtpl 7 Steyregg Ober\u00f6sterreich 4221",
    "addr:housenumber":"7",
    "addr:postcode":"4221",
    "addr:street":"Stadtpl",
    "iso:country":"AT",
    "sg:address":"Stadtpl 7",
    "sg:city":"Steyregg",
    "sg:orig_category":"Textilwaren / Einzelhandel",
    "sg:phone":"+43 732 641163",
    "sg:postcode":"4221",
    "sg:province":"Ober\u00f6sterreich",
    "wof:name":"TPS",
    "wof:placetype":"venue"
},
  "geometry": {"coordinates":[14.372215271,48.285949707],"type":"Point"}
}