{
  "type": "Feature",
  "properties": {
    "addr:full":"Uferweg 24 Stockerau Nieder\u00f6sterreich 2000",
    "addr:housenumber":"24",
    "addr:postcode":"2000",
    "addr:street":"Uferweg",
    "iso:country":"AT",
    "sg:address":"Uferweg 24",
    "sg:city":"Stockerau",
    "sg:orig_category":"Blumenbinder",
    "sg:phone":"+43 2266 63288",
    "sg:postcode":"2000",
    "sg:province":"Nieder\u00f6sterreich",
    "wof:name":"Reichl Karl",
    "wof:placetype":"venue"
},
  "geometry": {"coordinates":[16.2074947357,48.3848304749],"type":"Point"}
}