{
  "type": "Feature",
  "properties": {
    "addr:full":"Wohlmutstr 12/4 Wien Wien 1020",
    "addr:housenumber":"12 / 4",
    "addr:postcode":"1020",
    "addr:street":"Wohlmutstr",
    "iso:country":"AT",
    "sg:address":"Wohlmutstr 12/4",
    "sg:city":"Wien",
    "sg:classifiers":[
        {
            "category":"Professional",
            "subcategory":"Computer Services",
            "type":"Services"
        }
    ],
    "sg:phone":"+43 4369 912546850",
    "sg:postcode":"1020",
    "sg:province":"Wien",
    "sg:tags":[
        "software"
    ],
    "wof:name":"digital-invent.com",
    "wof:placetype":"venue"
},
  "geometry": {"coordinates":[16.4023246765,48.2203788757],"type":"Point"}
}