{
  "type": "Feature",
  "properties": {
    "iso:country":"AT",
    "sg:address":"Industriestra\u00dfe II 3",
    "sg:city":"Neunkirchen",
    "sg:orig_category":"Autohandel",
    "sg:phone":"+43 4326 3562187",
    "sg:postcode":"2620",
    "sg:province":"Nieder\u00f6sterreich",
    "wof:name":"Citroen-Autohaus K\u00f6hler GesmbH",
    "wof:placetype":"venue"
},
  "geometry": {"coordinates":[16.0825557709,47.7204246521],"type":"Point"}
}