{
  "type": "Feature",
  "properties": {
    "addr:full":"Sporg 21a Graz Steiermark 8010",
    "addr:housenumber":"21a",
    "addr:postcode":"8010",
    "addr:street":"Sporg",
    "iso:country":"AT",
    "sg:address":"Sporg 21a",
    "sg:city":"Graz",
    "sg:orig_category":"Non-Classified Establishments",
    "sg:phone":"+43 316 829318",
    "sg:postcode":"8010",
    "sg:province":"Steiermark",
    "wof:name":"Pfarre Stiegenkirche",
    "wof:placetype":"venue"
},
  "geometry": {"coordinates":[15.4389448166,47.0725288391],"type":"Point"}
}