{
  "type": "Feature",
  "properties": {
    "addr:full":"Hofsteigstr 124 B Hard Vorarlberg 6971",
    "addr:housenumber":"124 b",
    "addr:postcode":"6971",
    "iso:country":"AT",
    "sg:address":"Hofsteigstr 124 B",
    "sg:city":"Hard",
    "sg:orig_category":"Tanzschulen",
    "sg:phone":"+43 5574 44367",
    "sg:postcode":"6971",
    "sg:province":"Vorarlberg",
    "wof:name":"Tango Argentino Unterricht + Show",
    "wof:placetype":"venue"
},
  "geometry": {"coordinates":[9.7092113495,47.4865570068],"type":"Point"}
}