{
  "type": "Feature",
  "properties": {
    "addr:full":"Josef-Wilberger-Str 29 Innsbruck Tirol 6020",
    "addr:housenumber":"29",
    "addr:postcode":"6020",
    "addr:street":"Josef-Wilberger-Str;Tirol",
    "iso:country":"AT",
    "sg:address":"Josef-Wilberger-Str 29",
    "sg:city":"Innsbruck",
    "sg:orig_category":"Installationsunternehmen",
    "sg:phone":"+43 512 260201",
    "sg:postcode":"6020",
    "sg:province":"Tirol",
    "wof:name":"AUSSERER Haustechnik - Ing Gerhard Lacher",
    "wof:placetype":"venue"
},
  "geometry": {"coordinates":[11.4371585846,47.2776298523],"type":"Point"}
}