{
  "type": "Feature",
  "properties": {
    "addr:full":"Enzersberg 174 Thalgau Salzburg 5303",
    "addr:housenumber":"174",
    "addr:postcode":"5303",
    "addr:street":"Enzersberg;Salzburg",
    "iso:country":"AT",
    "sg:address":"Enzersberg 174",
    "sg:city":"Thalgau",
    "sg:orig_category":"Transportunternehmen",
    "sg:phone":"+43 6235 65870",
    "sg:postcode":"5303",
    "sg:province":"Salzburg",
    "wof:name":"Ebner A Internationale Transporte GmbH",
    "wof:placetype":"venue"
},
  "geometry": {"coordinates":[13.1954441071,47.8485679626],"type":"Point"}
}