{
  "type": "Feature",
  "properties": {
    "iso:country":"AT",
    "sg:address":"Nr 4",
    "sg:city":"Bad Waltersdorf",
    "sg:orig_category":"Landwirtschaftliche Produkte",
    "sg:phone":"+43 3333 2271",
    "sg:postcode":"8271",
    "sg:province":"Steiermark",
    "wof:name":"PIWETZ - M\u00dcHLE Inh Ing Peter B\u00f6hm",
    "wof:placetype":"venue"
},
  "geometry": {"coordinates":[15.9916791916,47.1863212585],"type":"Point"}
}