{
  "type": "Feature",
  "properties": {
    "addr:full":"Raiffeisenpl 3 St. Gilgen Salzburg 5340",
    "addr:housenumber":"3",
    "addr:postcode":"5340",
    "addr:street":"Raiffeisenpl",
    "iso:country":"AT",
    "sg:address":"Raiffeisenpl 3",
    "sg:city":"St. Gilgen",
    "sg:orig_category":"Bergbahnen",
    "sg:phone":"+43 6227 2350",
    "sg:postcode":"5340",
    "sg:province":"Salzburg",
    "wof:name":"Zw\u00f6lferhornseilbahn GesmbH",
    "wof:placetype":"venue"
},
  "geometry": {"coordinates":[13.364030838,47.7656326294],"type":"Point"}
}