{
  "type": "Feature",
  "properties": {
    "iso:country":"AT",
    "sg:address":"Obere Hauptstr 15",
    "sg:city":"Hohenberg",
    "sg:orig_category":"Elektroinstallationsunternehmen",
    "sg:phone":"+43 664 5268500",
    "sg:postcode":"3192",
    "sg:province":"Nieder\u00f6sterreich",
    "wof:name":"Wagner Leo",
    "wof:placetype":"venue"
},
  "geometry": {"coordinates":[15.6198654175,47.9034423828],"type":"Point"}
}