{
  "type": "Feature",
  "properties": {
    "iso:country":"AT",
    "sg:address":"Wilhelm-Jentsch-Str 2",
    "sg:city":"Peggau",
    "sg:orig_category":"Hufschmiede",
    "sg:phone":"+43 4331 272229",
    "sg:postcode":"8120",
    "sg:province":"Steiermark",
    "wof:name":"Hufkonzept Mag Peter u Franz Kramberger",
    "wof:placetype":"venue"
},
  "geometry": {"coordinates":[15.3418970108,47.2034454346],"type":"Point"}
}