{
  "type": "Feature",
  "properties": {
    "addr:full":"Peretseck 20 St. Johann am Walde Ober\u00f6sterreich 5242",
    "addr:housenumber":"20",
    "addr:postcode":"5242",
    "addr:street":"Peretseck",
    "iso:country":"AT",
    "sg:address":"Peretseck 20",
    "sg:city":"St. Johann am Walde",
    "sg:orig_category":"Handelsagenturen",
    "sg:phone":"+43 7743 8316",
    "sg:postcode":"5242",
    "sg:province":"Ober\u00f6sterreich",
    "wof:name":"Berer Hans",
    "wof:placetype":"venue"
},
  "geometry": {"coordinates":[13.2888126373,48.114490509],"type":"Point"}
}