{
  "type": "Feature",
  "properties": {
    "addr:full":"St Ruprechter Str 117 Klagenfurt K\u00e4rnten 9020",
    "addr:housenumber":"117",
    "addr:postcode":"9020",
    "addr:street":"St;Str;Kaernten",
    "iso:country":"AT",
    "sg:address":"St Ruprechter Str 117",
    "sg:city":"Klagenfurt",
    "sg:orig_category":"Flaschen",
    "sg:phone":"+43 463 31113",
    "sg:postcode":"9020",
    "sg:province":"K\u00e4rnten",
    "wof:name":"Plastikwerk Expan GesmbH",
    "wof:placetype":"venue"
},
  "geometry": {"coordinates":[14.3121023178,46.6016159058],"type":"Point"}
}