{
  "type": "Feature",
  "properties": {
    "iso:country":"AT",
    "sg:address":"Imbergstr 39",
    "sg:city":"Salzburg",
    "sg:orig_category":"Lebensmittel / Einzelhandel",
    "sg:phone":"+43 662 642938",
    "sg:postcode":"5020",
    "sg:province":"Salzburg",
    "wof:name":"Stoll Manfred",
    "wof:placetype":"venue"
},
  "geometry": {"coordinates":[13.0534925461,47.7999382019],"type":"Point"}
}