{
  "type": "Feature",
  "properties": {
    "addr:full":"Lindeng. 48-52 Wien Wien 1070",
    "addr:postcode":"48-52;1070",
    "iso:country":"AT",
    "sg:address":"Lindeng. 48-52",
    "sg:city":"Wien",
    "sg:classifiers":[
        {
            "category":"Manufacturing",
            "subcategory":"Printing",
            "type":"Manufacturing & Wholesale Goods"
        }
    ],
    "sg:phone":"+43 4315 2130",
    "sg:postcode":"1070",
    "sg:province":"Wien",
    "sg:tags":[
        "publishing"
    ],
    "wof:name":"MEDIAPRINT ZEITUNGSVERTRIEBSGESMBH & CO KG",
    "wof:placetype":"venue"
},
  "geometry": {"coordinates":[16.3473720551,48.1997947693],"type":"Point"}
}