{
  "type": "Feature",
  "properties": {
    "iso:country":"AT",
    "sg:address":"Nr 16",
    "sg:city":"Stronsdorf",
    "sg:orig_category":"Partyservice",
    "sg:phone":"+43 2526 7343",
    "sg:postcode":"2153",
    "sg:province":"Nieder\u00f6sterreich",
    "wof:name":"Futschik Josef",
    "wof:placetype":"venue"
},
  "geometry": {"coordinates":[16.2972221375,48.6530685425],"type":"Point"}
}