{
  "type": "Feature",
  "properties": {
    "addr:full":"Nr 51b St. Oswald Steiermark 8113",
    "addr:postcode":"8113",
    "addr:street":"Nr 51B",
    "iso:country":"AT",
    "sg:address":"Nr 51b",
    "sg:city":"St. Oswald",
    "sg:classifiers":[
        {
            "category":"Government",
            "subcategory":"Post Office",
            "type":"Public Place"
        }
    ],
    "sg:phone":"+43 4331 232560",
    "sg:postcode":"8113",
    "sg:province":"Steiermark",
    "sg:tags":[
        "yoga"
    ],
    "wof:name":"Bosch Johanna",
    "wof:placetype":"venue"
},
  "geometry": {"coordinates":[15.2193155289,47.1025161743],"type":"Point"}
}