{
  "type": "Feature",
  "properties": {
    "addr:full":"Kirchg 19 Feldkirchen in K\u00e4rnten K\u00e4rnten 9560",
    "addr:housenumber":"19",
    "addr:postcode":"9560",
    "addr:street":"Kirchg;Kaernten",
    "iso:country":"AT",
    "sg:address":"Kirchg 19",
    "sg:city":"Feldkirchen in K\u00e4rnten",
    "sg:classifiers":[
        {
            "category":"Internet Cafe",
            "subcategory":"None",
            "type":"Food & Drink"
        }
    ],
    "sg:phone":"+43 4342 7637235",
    "sg:postcode":"9560",
    "sg:province":"K\u00e4rnten",
    "wof:name":"c-works-design edv & internet gmbh",
    "wof:placetype":"venue"
},
  "geometry": {"coordinates":[14.0940999985,46.7261657715],"type":"Point"}
}