{
  "type": "Feature",
  "properties": {
    "addr:full":"Brenner Str 42 Steinach am Brenner Tirol 6150",
    "addr:postcode":"6150",
    "addr:street":"Str 42;Tirol",
    "iso:country":"AT",
    "sg:address":"Brenner Str 42",
    "sg:city":"Steinach am Brenner",
    "sg:orig_category":"Lebensmittel / Einzelhandel",
    "sg:phone":"+43 5272 6233",
    "sg:postcode":"6150",
    "sg:province":"Tirol",
    "wof:name":"Spar-Markt Inh Hans-Peter Stockhammer",
    "wof:placetype":"venue"
},
  "geometry": {"coordinates":[11.4665327072,47.0918884277],"type":"Point"}
}