{
  "type": "Feature",
  "properties": {
    "addr:full":"Nr 12 St. Georgen ob Judenburg Steiermark 8756",
    "addr:postcode":"8756",
    "addr:street":"Nr 12",
    "iso:country":"AT",
    "sg:address":"Nr 12",
    "sg:city":"St. Georgen ob Judenburg",
    "sg:orig_category":"Gemeinden",
    "sg:phone":"+43 4335 832376",
    "sg:postcode":"8756",
    "sg:province":"Steiermark",
    "wof:name":"Gemeindeamt St Georgen ob Judenburg",
    "wof:placetype":"venue"
},
  "geometry": {"coordinates":[14.4987268448,47.20652771],"type":"Point"}
}