{
  "type": "Feature",
  "properties": {
    "addr:full":"Ecksteinerweg 12 Gramastetten Ober\u00f6sterreich 4201",
    "addr:housenumber":"12",
    "addr:postcode":"4201",
    "addr:street":"Ecksteinerweg",
    "iso:country":"AT",
    "sg:address":"Ecksteinerweg 12",
    "sg:city":"Gramastetten",
    "sg:orig_category":"Perlen",
    "sg:phone":"+43 7212 6454",
    "sg:postcode":"4201",
    "sg:province":"Ober\u00f6sterreich",
    "wof:name":"Scherb & Freiseder OEG",
    "wof:placetype":"venue"
},
  "geometry": {"coordinates":[14.249420166,48.4175491333],"type":"Point"}
}