{
  "type": "Feature",
  "properties": {
    "addr:full":"Gmundner Str 23 Schwanenstadt Ober\u00f6sterreich 4690",
    "addr:postcode":"4690",
    "addr:street":"Str;Oberoesterreich",
    "iso:country":"AT",
    "sg:address":"Gmundner Str 23",
    "sg:city":"Schwanenstadt",
    "sg:orig_category":"Schwimmbecken",
    "sg:phone":"+43 76734369",
    "sg:postcode":"4690",
    "sg:province":"Ober\u00f6sterreich",
    "wof:name":"Poolservice",
    "wof:placetype":"venue"
},
  "geometry": {"coordinates":[13.7773780823,48.0511474609],"type":"Point"}
}