{
  "type": "Feature",
  "properties": {
    "addr:full":"O Kernstock-Str 18 Feldbach Steiermark 8330",
    "addr:housenumber":"18",
    "addr:postcode":"8330",
    "iso:country":"AT",
    "sg:address":"O Kernstock-Str 18",
    "sg:city":"Feldbach",
    "sg:orig_category":"Blumeneinzelhandel",
    "sg:phone":"+43 3152 4108",
    "sg:postcode":"8330",
    "sg:province":"Steiermark",
    "wof:name":"Koch Eveline",
    "wof:placetype":"venue"
},
  "geometry": {"coordinates":[15.8825540543,46.9503250122],"type":"Point"}
}