{
  "type": "Feature",
  "properties": {
    "addr:full":"Montafoner Str 29 Schruns Vorarlberg 6780",
    "addr:housenumber":"29",
    "addr:postcode":"6780",
    "addr:street":"Str",
    "iso:country":"AT",
    "sg:address":"Montafoner Str 29",
    "sg:city":"Schruns",
    "sg:orig_category":"Hubschrauberflugdienste",
    "sg:phone":"+43 5556 74000160",
    "sg:postcode":"6780",
    "sg:province":"Vorarlberg",
    "wof:name":"Schenk Air GmbH",
    "wof:placetype":"venue"
},
  "geometry": {"coordinates":[9.9145812988,47.0727539062],"type":"Point"}
}