{
  "type": "Feature",
  "properties": {
    "addr:full":"Nr 218 Markt Neuhodis Burgenland 7464",
    "addr:postcode":"7464",
    "addr:street":"Nr",
    "iso:country":"AT",
    "sg:address":"Nr 218",
    "sg:city":"Markt Neuhodis",
    "sg:orig_category":"Transportunternehmen",
    "sg:phone":"+43 3363 77626",
    "sg:postcode":"7464",
    "sg:province":"Burgenland",
    "wof:name":"AGT Allgemeine G\u00fctertransporte OEG",
    "wof:placetype":"venue"
},
  "geometry": {"coordinates":[16.3952350616,47.2961273193],"type":"Point"}
}