{
  "type": "Feature",
  "properties": {
    "addr:full":"Nibelungengasse 3/2/7 Wien Wien 1010",
    "addr:housenumber":"3 / 2 / 7",
    "addr:postcode":"1010",
    "addr:street":"Nibelungengasse",
    "iso:country":"AT",
    "sg:address":"Nibelungengasse 3/2/7",
    "sg:city":"Wien",
    "sg:classifiers":[
        {
            "category":"Building & Trades",
            "subcategory":"Electrical",
            "type":"Services"
        }
    ],
    "sg:phone":"+43 1 58764600",
    "sg:postcode":"1010",
    "sg:province":"Wien",
    "sg:tags":[
        "engineering",
        "construction",
        "architectural",
        "software"
    ],
    "sg:website":"cadstudio.at",
    "wof:name":"Dipl.-Ing. Michael Sanytr GesmbH",
    "wof:placetype":"venue"
},
  "geometry": {"coordinates":[16.3688049316,48.2025489807],"type":"Point"}
}