{
  "type": "Feature",
  "properties": {
    "addr:full":"Hoher Pl 21 Wolfsberg K\u00e4rnten 9400",
    "addr:housenumber":"21;kaernten",
    "addr:postcode":"9400",
    "addr:street":"Hoher Pl",
    "iso:country":"AT",
    "sg:address":"Hoher Pl 21",
    "sg:city":"Wolfsberg",
    "sg:orig_category":"Juwelen, Gold- U Silberwaren / Einzelhandel",
    "sg:phone":"+43 4343 5230103",
    "sg:postcode":"9400",
    "sg:province":"K\u00e4rnten",
    "wof:name":"Uhren-Raup",
    "wof:placetype":"venue"
},
  "geometry": {"coordinates":[14.8454751968,46.8391189575],"type":"Point"}
}