{
  "type": "Feature",
  "properties": {
    "iso:country":"AT",
    "sg:address":"Eigelg 11",
    "sg:city":"Wien",
    "sg:classifiers":[
        {
            "category":"Arts & Performance",
            "subcategory":"Theater",
            "type":"Entertainment"
        }
    ],
    "sg:phone":"+43 1 6994550",
    "sg:postcode":"1230",
    "sg:province":"Wien",
    "wof:name":"Rothstein Christine - Puppentheater Arlequin-Habakuk",
    "wof:placetype":"venue"
},
  "geometry": {"coordinates":[16.321685791,48.1348228455],"type":"Point"}
}