{
  "type": "Feature",
  "properties": {
    "addr:full":"Nr 39 Hollabrunn Nieder\u00f6sterreich 2020",
    "addr:postcode":"2020",
    "addr:street":"Nr;Niederoesterreich",
    "iso:country":"AT",
    "sg:address":"Nr 39",
    "sg:city":"Hollabrunn",
    "sg:orig_category":"Psychotherapie",
    "sg:phone":"+43 2959 2298",
    "sg:postcode":"2020",
    "sg:province":"Nieder\u00f6sterreich",
    "wof:name":"Lambauer Monika Mag",
    "wof:placetype":"venue"
},
  "geometry": {"coordinates":[166.9221496582,-0.5282999873],"type":"Point"}
}