{
  "type": "Feature",
  "properties": {
    "iso:country":"AT",
    "sg:address":"Rathausg 4",
    "sg:city":"Pulkau",
    "sg:orig_category":"Blumeneinzelhandel",
    "sg:phone":"+43 2946 2264",
    "sg:postcode":"3741",
    "sg:province":"Nieder\u00f6sterreich",
    "wof:name":"Frank Christine",
    "wof:placetype":"venue"
},
  "geometry": {"coordinates":[15.8591041565,48.7055625916],"type":"Point"}
}