{
  "type": "Feature",
  "properties": {
    "addr:full":"Grazer Str 6 Lebring Steiermark 8403",
    "addr:housenumber":"6",
    "addr:postcode":"8403",
    "addr:street":"Str",
    "iso:country":"AT",
    "sg:address":"Grazer Str 6",
    "sg:city":"Lebring",
    "sg:orig_category":"Bankomat-Standorte",
    "sg:phone":"+43 4331 822580",
    "sg:postcode":"8403",
    "sg:province":"Steiermark",
    "wof:name":"Bankomat d Raiffeisenbank Lebring",
    "wof:placetype":"venue"
},
  "geometry": {"coordinates":[15.5350522995,46.8587608337],"type":"Point"}
}