{
  "type": "Feature",
  "properties": {
    "iso:country":"AT",
    "sg:address":"Braunhirscheng 52",
    "sg:city":"Wien",
    "sg:orig_category":"Metallbau",
    "sg:phone":"+43 1 8921247",
    "sg:postcode":"1150",
    "sg:province":"Wien",
    "wof:name":"Fill Metallbau GesmbH",
    "wof:placetype":"venue"
},
  "geometry": {"coordinates":[16.3264446259,48.1904983521],"type":"Point"}
}