{
  "type": "Feature",
  "properties": {
    "addr:full":"Samhaberweg 4 Kirchdorf an der Krems Ober\u00f6sterreich 4560",
    "addr:housenumber":"4",
    "addr:postcode":"4560",
    "addr:street":"Samhaberweg",
    "iso:country":"AT",
    "sg:address":"Samhaberweg 4",
    "sg:city":"Kirchdorf an der Krems",
    "sg:orig_category":"Steuerberatung",
    "sg:phone":"+43 4375 82605500",
    "sg:postcode":"4560",
    "sg:province":"Ober\u00f6sterreich",
    "sg:website":"ganglbauer.co.at",
    "wof:name":"Ganglbauer Friedrich",
    "wof:placetype":"venue"
},
  "geometry": {"coordinates":[14.1187143326,47.9055747986],"type":"Point"}
}