{
  "type": "Feature",
  "properties": {
    "addr:full":"W\u00f6rgl Tirol 6300",
    "addr:postcode":"6300",
    "addr:street":"Tirol",
    "iso:country":"AT",
    "sg:city":"W\u00f6rgl",
    "sg:orig_category":"Freizeitangebote U -Einrichtungen",
    "sg:phone":"+43 4353 3272529",
    "sg:postcode":"6300",
    "sg:province":"Tirol",
    "wof:name":"Volkshaus W\u00f6rgl",
    "wof:placetype":"venue"
},
  "geometry": {"coordinates":[-69.3131027222,-51.6091995239],"type":"Point"}
}