{
  "type": "Feature",
  "properties": {
    "addr:full":"Lothringerstr 20 Wien Wien 1030",
    "addr:housenumber":"20",
    "addr:postcode":"1030",
    "addr:street":"Lothringerstr",
    "iso:country":"AT",
    "sg:address":"Lothringerstr 20",
    "sg:city":"Wien",
    "sg:orig_category":"Bankomat-Standorte",
    "sg:phone":"+43 800 204880",
    "sg:postcode":"1030",
    "sg:province":"Wien",
    "wof:name":"Bankomat d Bank f Arbeit und Wirtschaft AG",
    "wof:placetype":"venue"
},
  "geometry": {"coordinates":[16.3772964478,48.2008705139],"type":"Point"}
}