{
  "type": "Feature",
  "properties": {
    "iso:country":"AT",
    "sg:address":"Bahnstr 246",
    "sg:city":"Wullersdorf",
    "sg:orig_category":"Zimmereien",
    "sg:phone":"+43 2951 84390",
    "sg:postcode":"2041",
    "sg:province":"Nieder\u00f6sterreich",
    "wof:name":"Gr\u00e4tzhofer Josef",
    "wof:placetype":"venue"
},
  "geometry": {"coordinates":[16.1008262634,48.6280441284],"type":"Point"}
}