{
  "type": "Feature",
  "properties": {
    "addr:full":"Innsbrucker Str 15 Reutte Tirol 6600",
    "addr:postcode":"6600",
    "addr:street":"Str 15;Tirol",
    "iso:country":"AT",
    "sg:address":"Innsbrucker Str 15",
    "sg:city":"Reutte",
    "sg:orig_category":"Lebensmittel / Einzelhandel",
    "sg:phone":"+43 5672 728440",
    "sg:postcode":"6600",
    "sg:province":"Tirol",
    "wof:name":"SPAR \u00d6sterreichische Warenhandels-AG",
    "wof:placetype":"venue"
},
  "geometry": {"coordinates":[10.7245349884,47.4824256897],"type":"Point"}
}