{
  "type": "Feature",
  "properties": {
    "addr:full":"Franz Josef-Str 34 Perchtoldsdorf Nieder\u00f6sterreich 2380",
    "addr:housenumber":"34",
    "addr:postcode":"2380",
    "addr:street":"Franz Josef-Str",
    "iso:country":"AT",
    "sg:address":"Franz Josef-Str 34",
    "sg:city":"Perchtoldsdorf",
    "sg:orig_category":"Ballettschulen",
    "sg:phone":"+43 1 7898895",
    "sg:postcode":"2380",
    "sg:province":"Nieder\u00f6sterreich",
    "wof:name":"Studio Susanna Fuchs",
    "wof:placetype":"venue"
},
  "geometry": {"coordinates":[16.2682418823,48.1186943054],"type":"Point"}
}