{
  "type": "Feature",
  "properties": {
    "addr:full":"Kurgartenstr 40 Bad Hofgastein Salzburg 5630",
    "addr:housenumber":"40",
    "addr:postcode":"5630",
    "addr:street":"Kurgartenstr;Salzburg",
    "iso:country":"AT",
    "sg:address":"Kurgartenstr 40",
    "sg:city":"Bad Hofgastein",
    "sg:orig_category":"Rauchfangkehrer",
    "sg:phone":"+43 6432 6381",
    "sg:postcode":"5630",
    "sg:province":"Salzburg",
    "wof:name":"Lackner Alexander",
    "wof:placetype":"venue"
},
  "geometry": {"coordinates":[13.09786129,47.1702156067],"type":"Point"}
}