{
  "type": "Feature",
  "properties": {
    "addr:full":"Mitteldorf 269 Schoppernau Vorarlberg 6886",
    "addr:housenumber":"269",
    "addr:postcode":"6886",
    "addr:street":"Mitteldorf",
    "iso:country":"AT",
    "sg:address":"Mitteldorf 269",
    "sg:city":"Schoppernau",
    "sg:orig_category":"Pensionen / Privatzimmer",
    "sg:phone":"+43 4355 152417",
    "sg:postcode":"6886",
    "sg:province":"Vorarlberg",
    "wof:name":"Simma Maria",
    "wof:placetype":"venue"
},
  "geometry": {"coordinates":[10.0196466446,47.3102760315],"type":"Point"}
}