{
  "type": "Feature",
  "properties": {
    "addr:full":"Seebadstr 1 Mondsee Ober\u00f6sterreich 5310",
    "addr:housenumber":"1",
    "addr:postcode":"5310",
    "addr:street":"Seebadstr;Oberoesterreich",
    "iso:country":"AT",
    "sg:address":"Seebadstr 1",
    "sg:city":"Mondsee",
    "sg:orig_category":"Schifffahrt",
    "sg:phone":"+43 6232 4934",
    "sg:postcode":"5310",
    "sg:province":"Ober\u00f6sterreich",
    "sg:website":"mondseeschiffahrt.at; mondseeschiffahrt.com",
    "wof:name":"Schiffahrt - Hemetsberger",
    "wof:placetype":"venue"
},
  "geometry": {"coordinates":[13.3498382568,47.8510131836],"type":"Point"}
}