{
  "type": "Feature",
  "properties": {
    "addr:full":"Oberndorfer Strasse 14-16 Purgstall an der Erlauf Nieder\u00f6sterreich 3251",
    "addr:postcode":"14-16;3251",
    "addr:street":"Oberndorfer Strasse;Niederoesterreich",
    "iso:country":"AT",
    "sg:address":"Oberndorfer Strasse 14-16",
    "sg:city":"Purgstall an der Erlauf",
    "sg:classifiers":[
        {
            "category":"Home & Garden",
            "subcategory":"Building Materials",
            "type":"Retail Goods"
        }
    ],
    "sg:phone":"+43 7489 24230",
    "sg:postcode":"3251",
    "sg:province":"Nieder\u00f6sterreich",
    "sg:tags":[
        "adhesive",
        "tape",
        "trade"
    ],
    "sg:website":"uebellacker.at",
    "wof:name":"Leopold \u00dcbellacker",
    "wof:placetype":"venue"
},
  "geometry": {"coordinates":[15.1427164078,48.0586891174],"type":"Point"}
}