{
  "type": "Feature",
  "properties": {
    "addr:full":"Braunschweigg 12 Wien Wien 1130",
    "addr:housenumber":"12",
    "addr:postcode":"1130",
    "addr:street":"Braunschweigg",
    "iso:country":"AT",
    "sg:address":"Braunschweigg 12",
    "sg:city":"Wien",
    "sg:orig_category":"Galerien",
    "sg:phone":"+43 1 87754870",
    "sg:postcode":"1130",
    "sg:province":"Wien",
    "wof:name":"Reisser M und D Kunstverlag KG - Hochwertige Kunstdrucke - Galerie",
    "wof:placetype":"venue"
},
  "geometry": {"coordinates":[16.2949104309,48.1881484985],"type":"Point"}
}