{
  "type": "Feature",
  "properties": {
    "addr:full":"Gonzagag 15 Wien Wien 1010",
    "addr:housenumber":"15",
    "addr:postcode":"1010",
    "addr:street":"Gonzagag",
    "iso:country":"AT",
    "sg:address":"Gonzagag 15",
    "sg:city":"Wien",
    "sg:orig_category":"Damenmoden",
    "sg:phone":"+43 1 53372540",
    "sg:postcode":"1010",
    "sg:province":"Wien",
    "wof:name":"Rieger Herbert",
    "wof:placetype":"venue"
},
  "geometry": {"coordinates":[16.3699436188,48.2155227661],"type":"Point"}
}