{
  "type": "Feature",
  "properties": {
    "addr:full":"Rathausg 4 Deutschlandsberg Steiermark 8530",
    "addr:housenumber":"4",
    "addr:postcode":"8530",
    "addr:street":"Rathausg",
    "iso:country":"AT",
    "sg:address":"Rathausg 4",
    "sg:city":"Deutschlandsberg",
    "sg:orig_category":"Bildungsservice / Allgemeine Informationsstellen",
    "sg:phone":"+43 3462 2947210",
    "sg:postcode":"8530",
    "sg:province":"Steiermark",
    "wof:name":"Berufsinformationszentrum Deutschlandsberg",
    "wof:placetype":"venue"
},
  "geometry": {"coordinates":[15.2126283646,46.8138923645],"type":"Point"}
}