{
  "type": "Feature",
  "properties": {
    "addr:full":"Grieselstein Therme 99 Jennersdorf Burgenland 8380",
    "addr:housenumber":"99",
    "addr:postcode":"8380",
    "iso:country":"AT",
    "sg:address":"Grieselstein Therme 99",
    "sg:city":"Jennersdorf",
    "sg:classifiers":[
        {
            "category":"Travel",
            "subcategory":"Hotels & Motels",
            "type":"Entertainment"
        }
    ],
    "sg:phone":"+43 3329 485020",
    "sg:postcode":"8380",
    "sg:province":"Burgenland",
    "wof:name":"Villa Kunterbunt Familienhotel",
    "wof:placetype":"venue"
},
  "geometry": {"coordinates":[16.1297111511,46.9432792664],"type":"Point"}
}