{
  "type": "Feature",
  "properties": {
    "addr:full":"Schlachthofg 2 Innsbruck Tirol 6020",
    "addr:housenumber":"2",
    "addr:postcode":"6020",
    "addr:street":"Schlachthofg;Tirol",
    "iso:country":"AT",
    "sg:address":"Schlachthofg 2",
    "sg:city":"Innsbruck",
    "sg:orig_category":"Kosmetische Produkte / Einzelhandel",
    "sg:phone":"+43 512 583738",
    "sg:postcode":"6020",
    "sg:province":"Tirol",
    "wof:name":"Tyromar WarenhandelsgesmbH & Co KG",
    "wof:placetype":"venue"
},
  "geometry": {"coordinates":[11.4112873077,47.2753143311],"type":"Point"}
}