{
  "type": "Feature",
  "properties": {
    "addr:full":"Nr 15 Thiersee Tirol 6335",
    "addr:postcode":"6335",
    "addr:street":"Nr 15;Tirol",
    "iso:country":"AT",
    "sg:address":"Nr 15",
    "sg:city":"Thiersee",
    "sg:orig_category":"Pensionen / Privatzimmer",
    "sg:phone":"+43 5376 5544",
    "sg:postcode":"6335",
    "sg:province":"Tirol",
    "wof:name":"Wanishof",
    "wof:placetype":"venue"
},
  "geometry": {"coordinates":[12.0649995804,47.584148407],"type":"Point"}
}