{
  "type": "Feature",
  "properties": {
    "addr:full":"Marburgg 48 Wien Wien 1220",
    "addr:housenumber":"48",
    "addr:postcode":"1220",
    "addr:street":"Marburgg",
    "iso:country":"AT",
    "sg:address":"Marburgg 48",
    "sg:city":"Wien",
    "sg:orig_category":"Baumeister, Bauunternehmen",
    "sg:phone":"+43 1 7743801",
    "sg:postcode":"1220",
    "sg:province":"Wien",
    "wof:name":"Lehner Johann BaugesmbH",
    "wof:placetype":"venue"
},
  "geometry": {"coordinates":[16.5236167908,48.2047386169],"type":"Point"}
}