{
  "type": "Feature",
  "properties": {
    "addr:full":"Ischler Strasse 71 Bad Aussee Steiermark 8990",
    "addr:housenumber":"71",
    "addr:postcode":"8990",
    "addr:street":"Ischler Strasse",
    "iso:country":"AT",
    "sg:address":"Ischler Strasse 71",
    "sg:city":"Bad Aussee",
    "sg:classifiers":[
        {
            "category":"Building & Trades",
            "subcategory":"Construction",
            "type":"Services"
        }
    ],
    "sg:phone":"+43 3622 53745",
    "sg:postcode":"8990",
    "sg:province":"Steiermark",
    "sg:tags":[
        "residential",
        "masonry"
    ],
    "sg:website":"salzkammergut-immobilien.at",
    "wof:name":"GBG Bau- und Betriebsges.m.b.H.",
    "wof:placetype":"venue"
},
  "geometry": {"coordinates":[13.7821416855,47.609336853],"type":"Point"}
}