{
  "type": "Feature",
  "properties": {
    "addr:full":"Enghagner Str 3 Enns Ober\u00f6sterreich 4470",
    "addr:housenumber":"3",
    "addr:postcode":"4470",
    "addr:street":"Str",
    "iso:country":"AT",
    "sg:address":"Enghagner Str 3",
    "sg:city":"Enns",
    "sg:orig_category":"Tischlereien",
    "sg:phone":"+43 7223 83476",
    "sg:postcode":"4470",
    "sg:province":"Ober\u00f6sterreich",
    "wof:name":"Thanner Heribert",
    "wof:placetype":"venue"
},
  "geometry": {"coordinates":[14.4873943329,48.225605011],"type":"Point"}
}