{
  "type": "Feature",
  "properties": {
    "addr:full":"Czeija-Nissl-Gasse 11 Wien Wien 1210",
    "addr:housenumber":"11",
    "addr:postcode":"1210",
    "addr:street":"Czeija-Nissl-Gasse",
    "iso:country":"AT",
    "sg:address":"Czeija-Nissl-Gasse 11",
    "sg:city":"Wien",
    "sg:orig_category":"Cashiers Bags",
    "sg:phone":"+43 1 2701620",
    "sg:postcode":"1210",
    "sg:province":"Wien",
    "wof:name":"Josef Unterweger OHG",
    "wof:placetype":"venue"
},
  "geometry": {"coordinates":[16.3744716644,48.2853279114],"type":"Point"}
}