{
  "type": "Feature",
  "properties": {
    "iso:country":"AT",
    "sg:address":"Pittermann 18",
    "sg:city":"Wenigzell",
    "sg:orig_category":"Tankstellen",
    "sg:phone":"+43 3336 2686",
    "sg:postcode":"8254",
    "sg:province":"Steiermark",
    "wof:name":"Bauer Hans J\u00fcrgen",
    "wof:placetype":"venue"
},
  "geometry": {"coordinates":[15.7876119614,47.431552887],"type":"Point"}
}