{
  "type": "Feature",
  "properties": {
    "iso:country":"AT",
    "sg:address":"Herreng 16",
    "sg:city":"Wien",
    "sg:orig_category":"Immobilienmakler",
    "sg:phone":"+43 4315 334080",
    "sg:postcode":"1010",
    "sg:province":"Wien",
    "wof:name":"CB Richard Ellis GesmbH",
    "wof:placetype":"venue"
},
  "geometry": {"coordinates":[16.3648815155,48.2112503052],"type":"Point"}
}