{
  "type": "Feature",
  "properties": {
    "addr:full":"Rappetsederweg 28 Linz Ober\u00f6sterreich 4040",
    "addr:housenumber":"28",
    "addr:postcode":"4040",
    "addr:street":"Rappetsederweg",
    "iso:country":"AT",
    "sg:address":"Rappetsederweg 28",
    "sg:city":"Linz",
    "sg:orig_category":"Elektronik",
    "sg:phone":"+43 4373 2254611",
    "sg:postcode":"4040",
    "sg:province":"Ober\u00f6sterreich",
    "wof:name":"contec Elektronik GmbH",
    "wof:placetype":"venue"
},
  "geometry": {"coordinates":[14.3446187973,48.3265266418],"type":"Point"}
}