{
  "type": "Feature",
  "properties": {
    "addr:full":"Mucharg 5 Lienz Tirol 9900",
    "addr:housenumber":"5",
    "addr:postcode":"9900",
    "addr:street":"Mucharg;Tirol",
    "iso:country":"AT",
    "sg:address":"Mucharg 5",
    "sg:city":"Lienz",
    "sg:orig_category":"Boutiquen",
    "sg:phone":"+43 4348 5272287",
    "sg:postcode":"9900",
    "sg:province":"Tirol",
    "wof:name":"Close up Fashion Company",
    "wof:placetype":"venue"
},
  "geometry": {"coordinates":[12.7661514282,46.8300895691],"type":"Point"}
}