{
  "type": "Feature",
  "properties": {
    "iso:country":"AT",
    "sg:address":"Salzlegerg 2",
    "sg:city":"Stadl-Paura",
    "sg:orig_category":"Damenmoden",
    "sg:phone":"+43 7245 28528",
    "sg:postcode":"4651",
    "sg:province":"Ober\u00f6sterreich",
    "wof:name":"Schneberger GesmbH",
    "wof:placetype":"venue"
},
  "geometry": {"coordinates":[13.8613376617,48.0800590515],"type":"Point"}
}