{
  "type": "Feature",
  "properties": {
    "addr:full":"Fadingerstr 1 Waizenkirchen Ober\u00f6sterreich 4730",
    "addr:housenumber":"1",
    "addr:postcode":"4730",
    "addr:street":"Fadingerstr",
    "iso:country":"AT",
    "sg:address":"Fadingerstr 1",
    "sg:city":"Waizenkirchen",
    "sg:orig_category":"Spenglereien",
    "sg:phone":"+43 7277 2261",
    "sg:postcode":"4730",
    "sg:province":"Ober\u00f6sterreich",
    "wof:name":"Beisl GesmbH",
    "wof:placetype":"venue"
},
  "geometry": {"coordinates":[13.8570108414,48.3302612305],"type":"Point"}
}