{
  "type": "Feature",
  "properties": {
    "addr:full":"Seideng 26 Wien Wien 1070",
    "addr:housenumber":"26",
    "addr:postcode":"1070",
    "addr:street":"Seideng",
    "iso:country":"AT",
    "sg:address":"Seideng 26",
    "sg:city":"Wien",
    "sg:orig_category":"Architekten",
    "sg:phone":"+43 1 52351210",
    "sg:postcode":"1070",
    "sg:province":"Wien",
    "wof:name":"Neu Horst Klaus Arch Dipl-Ing",
    "wof:placetype":"venue"
},
  "geometry": {"coordinates":[16.3421497345,48.200553894],"type":"Point"}
}