{
  "type": "Feature",
  "properties": {
    "iso:country":"AT",
    "sg:address":"Bahnstr 25",
    "sg:city":"Leopoldsdorf im Marchfelde",
    "sg:orig_category":"Hunde- U Katzensalons",
    "sg:phone":"+43 4322 163168",
    "sg:postcode":"2285",
    "sg:province":"Nieder\u00f6sterreich",
    "wof:name":"Hundesalon - Schnipp & Schnapp",
    "wof:placetype":"venue"
},
  "geometry": {"coordinates":[16.6970539093,48.2312850952],"type":"Point"}
}