{
  "type": "Feature",
  "properties": {
    "addr:full":"Oberradin 14 Braz Vorarlberg 6751",
    "addr:housenumber":"14",
    "addr:postcode":"6751",
    "addr:street":"Oberradin",
    "iso:country":"AT",
    "sg:address":"Oberradin 14",
    "sg:city":"Braz",
    "sg:orig_category":"Pensionen / Privatzimmer",
    "sg:phone":"+43 5552 67861",
    "sg:postcode":"6751",
    "sg:province":"Vorarlberg",
    "wof:name":"Bitschnau Rita",
    "wof:placetype":"venue"
},
  "geometry": {"coordinates":[9.9180688858,47.144695282],"type":"Point"}
}