{
  "type": "Feature",
  "properties": {
    "iso:country":"AT",
    "sg:address":"G\u00e4rtnerg 2",
    "sg:city":"Wien",
    "sg:orig_category":"Physikalische Institute",
    "sg:phone":"+43 4317 132650",
    "sg:postcode":"1030",
    "sg:province":"Wien",
    "wof:name":"Physika Institut f physikalisch-medizinische Therapie GesmbH",
    "wof:placetype":"venue"
},
  "geometry": {"coordinates":[16.3883666992,48.2067070007],"type":"Point"}
}