{
  "type": "Feature",
  "properties": {
    "iso:country":"AT",
    "sg:address":"Nr 70",
    "sg:city":"Gampern",
    "sg:orig_category":"Banken U Sparkassen",
    "sg:phone":"+43 768280140",
    "sg:postcode":"4851",
    "sg:province":"Ober\u00f6sterreich",
    "wof:name":"Raiffeisenbank Gampern regGenmbH",
    "wof:placetype":"venue"
},
  "geometry": {"coordinates":[13.5552349091,47.989364624],"type":"Point"}
}