{
  "type": "Feature",
  "properties": {
    "iso:country":"AT",
    "sg:address":"Obere Donaustr 53",
    "sg:city":"Wien",
    "sg:orig_category":"Versicherungsunternehmen",
    "sg:phone":"+43 1 211290",
    "sg:postcode":"1020",
    "sg:province":"Wien",
    "wof:name":"Wiener St\u00e4dtische Allgemeine Versicherung AG",
    "wof:placetype":"venue"
},
  "geometry": {"coordinates":[16.3722839355,48.2187423706],"type":"Point"}
}