{
  "type": "Feature",
  "properties": {
    "iso:country":"AT",
    "sg:address":"Molkereistr 4",
    "sg:city":"Ried im Innkreis",
    "sg:orig_category":"Metalle U -Halbfabrikate",
    "sg:phone":"+43 4377 5288086",
    "sg:postcode":"4910",
    "sg:province":"Ober\u00f6sterreich",
    "sg:website":"leichtmetalltechnik.at",
    "wof:name":"Leicht Metall Technik GmbH",
    "wof:placetype":"venue"
},
  "geometry": {"coordinates":[13.4849100113,48.2022781372],"type":"Point"}
}