{
  "type": "Feature",
  "properties": {
    "addr:full":"H\u00f6tzendorfstr 114 Brunn am Gebirge Nieder\u00f6sterreich 2345",
    "addr:housenumber":"114",
    "addr:postcode":"2345",
    "iso:country":"AT",
    "sg:address":"H\u00f6tzendorfstr 114",
    "sg:city":"Brunn am Gebirge",
    "sg:orig_category":"Restaurants: Chinesisch",
    "sg:phone":"+43 2236 35634",
    "sg:postcode":"2345",
    "sg:province":"Nieder\u00f6sterreich",
    "wof:name":"China-Restaurant Lin-House",
    "wof:placetype":"venue"
},
  "geometry": {"coordinates":[16.3010997772,48.1210784912],"type":"Point"}
}