{
  "type": "Feature",
  "properties": {
    "addr:full":"Brucknerstr 20/2 Linz Ober\u00f6sterreich 4020",
    "addr:housenumber":"20 / 2",
    "addr:postcode":"4020",
    "addr:street":"Brucknerstr",
    "iso:country":"AT",
    "sg:address":"Brucknerstr 20/2",
    "sg:city":"Linz",
    "sg:orig_category":"Physiotherapie",
    "sg:phone":"+43 664 1616767",
    "sg:postcode":"4020",
    "sg:province":"Ober\u00f6sterreich",
    "wof:name":"Klingesberger Marlies",
    "wof:placetype":"venue"
},
  "geometry": {"coordinates":[14.2961997986,48.2871246338],"type":"Point"}
}