{
  "type": "Feature",
  "properties": {
    "addr:full":"Perchtoldsdorfer Str 17 Wien Wien 1230",
    "addr:postcode":"1230",
    "addr:street":"Str 17",
    "iso:country":"AT",
    "sg:address":"Perchtoldsdorfer Str 17",
    "sg:city":"Wien",
    "sg:orig_category":"Bauunternehmen",
    "sg:phone":"+43 1 86742620",
    "sg:postcode":"1230",
    "sg:province":"Wien",
    "wof:name":"vision contractors BaugesmbH",
    "wof:placetype":"venue"
},
  "geometry": {"coordinates":[16.2816333771,48.1333084106],"type":"Point"}
}