{
  "type": "Feature",
  "properties": {
    "addr:full":"Montfortstr 34 Sulz-R\u00f6this Vorarlberg 6832",
    "addr:housenumber":"34",
    "addr:postcode":"6832",
    "addr:street":"Montfortstr",
    "iso:country":"AT",
    "sg:address":"Montfortstr 34",
    "sg:city":"Sulz-R\u00f6this",
    "sg:orig_category":"Bauunternehmen",
    "sg:phone":"+43 4355 22415260",
    "sg:postcode":"6832",
    "sg:province":"Vorarlberg",
    "sg:website":"naegelebau.at",
    "wof:name":"N\u00e4gelebau GmbH",
    "wof:placetype":"venue"
},
  "geometry": {"coordinates":[9.6577978134,47.2859764099],"type":"Point"}
}