{
  "type": "Feature",
  "properties": {
    "addr:full":"Edelhof 5 St. Stefan im Rosental Steiermark 8083",
    "addr:housenumber":"5",
    "addr:postcode":"8083",
    "addr:street":"Edelhof",
    "iso:country":"AT",
    "sg:address":"Edelhof 5",
    "sg:city":"St. Stefan im Rosental",
    "sg:orig_category":"Pensionen / Privatzimmer",
    "sg:phone":"+43 4331 168443",
    "sg:postcode":"8083",
    "sg:province":"Steiermark",
    "wof:name":"Schl\u00f6gl Erwin u Herta",
    "wof:placetype":"venue"
},
  "geometry": {"coordinates":[15.7101650238,46.909324646],"type":"Point"}
}