{
  "type": "Feature",
  "properties": {
    "iso:country":"AT",
    "sg:address":"Weng 57",
    "sg:city":"Werfenweng",
    "sg:orig_category":"Pensionen / Privatzimmer",
    "sg:phone":"+43 4364 66514",
    "sg:postcode":"5453",
    "sg:province":"Salzburg",
    "wof:name":"G\u00e4stehaus GAMSBLICK Fam Krahbichler",
    "wof:placetype":"venue"
},
  "geometry": {"coordinates":[13.2566633224,47.4615287781],"type":"Point"}
}