{
  "type": "Feature",
  "properties": {
    "iso:country":"AT",
    "sg:address":"Dorf 53",
    "sg:city":"Going am Wilden Kaiser",
    "sg:orig_category":"Lebensmittel / Einzelhandel",
    "sg:phone":"+43 4353 582407",
    "sg:postcode":"6353",
    "sg:province":"Tirol",
    "wof:name":"Adeg Markt GmbH",
    "wof:placetype":"venue"
},
  "geometry": {"coordinates":[12.3330402374,47.5138702393],"type":"Point"}
}