{
  "type": "Feature",
  "properties": {
    "addr:full":"Wildpretmarkt 10 Wien Wien 1010",
    "addr:housenumber":"10",
    "addr:postcode":"1010",
    "addr:street":"Wildpretmarkt",
    "iso:country":"AT",
    "sg:address":"Wildpretmarkt 10",
    "sg:city":"Wien",
    "sg:orig_category":"Boutiquen",
    "sg:phone":"+43 1 5359921",
    "sg:postcode":"1010",
    "sg:province":"Wien",
    "wof:name":"Boutique Papillon",
    "wof:placetype":"venue"
},
  "geometry": {"coordinates":[16.3720417023,48.2104377747],"type":"Point"}
}