{
  "type": "Feature",
  "properties": {
    "addr:full":"Nr 5 Oberm\u00fchl Ober\u00f6sterreich 4131",
    "addr:postcode":"4131",
    "addr:street":"Nr;Obermuehl Oberoesterreich",
    "iso:country":"AT",
    "sg:address":"Nr 5",
    "sg:city":"Oberm\u00fchl",
    "sg:orig_category":"Gemeinden",
    "sg:phone":"+43 4372 824601",
    "sg:postcode":"4131",
    "sg:province":"Ober\u00f6sterreich",
    "wof:name":"Gemeinde Kirchberg ob der Donau",
    "wof:placetype":"venue"
},
  "geometry": {"coordinates":[13.9352884293,48.4440193176],"type":"Point"}
}