{
  "type": "Feature",
  "properties": {
    "addr:full":"Fleischmarkt 16/37 Wien Wien 1010",
    "addr:housenumber":"16 / 37",
    "addr:postcode":"1010",
    "addr:street":"Fleischmarkt",
    "iso:country":"AT",
    "sg:address":"Fleischmarkt 16/37",
    "sg:city":"Wien",
    "sg:orig_category":"Bauunternehmen",
    "sg:phone":"+43 4315 12714621",
    "sg:postcode":"1010",
    "sg:province":"Wien",
    "wof:name":"KRONIKA & PUHR Bau - Management KEG",
    "wof:placetype":"venue"
},
  "geometry": {"coordinates":[16.3768444061,48.2105445862],"type":"Point"}
}