{
  "type": "Feature",
  "properties": {
    "addr:full":"Marktpl 8 Dornbirn Vorarlberg 6850",
    "addr:housenumber":"8",
    "addr:postcode":"6850",
    "addr:street":"Marktpl",
    "iso:country":"AT",
    "sg:address":"Marktpl 8",
    "sg:city":"Dornbirn",
    "sg:orig_category":"Trachtenbekleidung",
    "sg:phone":"+43 5572 22619",
    "sg:postcode":"6850",
    "sg:province":"Vorarlberg",
    "wof:name":"Feurstein Raimund",
    "wof:placetype":"venue"
},
  "geometry": {"coordinates":[9.742647171,47.4139328003],"type":"Point"}
}