{
  "type": "Feature",
  "properties": {
    "addr:full":"Nr 1 Jenig K\u00e4rnten 9631",
    "addr:postcode":"9631",
    "addr:street":"Nr;Jenig",
    "iso:country":"AT",
    "sg:address":"Nr 1",
    "sg:city":"Jenig",
    "sg:orig_category":"Filmproduktionen",
    "sg:phone":"+43 4285 605",
    "sg:postcode":"9631",
    "sg:province":"K\u00e4rnten",
    "wof:name":"Zappe Wilhelm",
    "wof:placetype":"venue"
},
  "geometry": {"coordinates":[13.2537050247,46.6278686523],"type":"Point"}
}