{
  "type": "Feature",
  "properties": {
    "iso:country":"AT",
    "sg:address":"Siemensstr 17",
    "sg:city":"Wien",
    "sg:orig_category":"Politische Parteien",
    "sg:phone":"+43 1 2921037",
    "sg:postcode":"1210",
    "sg:province":"Wien",
    "wof:name":"Sozialdemokratische Partei \u00d6sterreichs Sektion 11",
    "wof:placetype":"venue"
},
  "geometry": {"coordinates":[16.4117584229,48.2752532959],"type":"Point"}
}