{
  "type": "Feature",
  "properties": {
    "iso:country":"AT",
    "sg:address":"Anbass-Strasse 2",
    "sg:city":"Weyregg am Attersee",
    "sg:classifiers":[
        {
            "category":"Professional",
            "subcategory":"Art Services",
            "type":"Services"
        }
    ],
    "sg:phone":"+43 766422480",
    "sg:postcode":"4852",
    "sg:province":"Ober\u00f6sterreich",
    "sg:tags":[
        "metalwork"
    ],
    "sg:website":"kunstschmied-oberwanger.at",
    "wof:name":"Kurt Oberwanger",
    "wof:placetype":"venue"
},
  "geometry": {"coordinates":[13.5697803497,47.901260376],"type":"Point"}
}