{
  "type": "Feature",
  "properties": {
    "iso:country":"AT",
    "sg:address":"Unterpurkla 74",
    "sg:city":"Unterpurkla",
    "sg:classifiers":[
        {
            "category":"Structure",
            "subcategory":"Building",
            "type":"Public Place"
        }
    ],
    "sg:phone":"+43 3475 2369",
    "sg:postcode":"8484",
    "sg:province":"Steiermark",
    "sg:tags":[
        "apartment"
    ],
    "wof:name":"Moder Bauunternehmen GesmbH",
    "wof:placetype":"venue"
},
  "geometry": {"coordinates":[15.90346241,46.7319793701],"type":"Point"}
}