{
  "type": "Feature",
  "properties": {
    "addr:full":"Dieselstr 13 Wels Ober\u00f6sterreich 4600",
    "addr:housenumber":"13",
    "addr:postcode":"4600",
    "addr:street":"Dieselstr;Oberoesterreich",
    "iso:country":"AT",
    "sg:address":"Dieselstr 13",
    "sg:city":"Wels",
    "sg:orig_category":"Galvanisieranstalten",
    "sg:phone":"+43 7242 460190",
    "sg:postcode":"4600",
    "sg:province":"Ober\u00f6sterreich",
    "sg:website":"holbe.at",
    "wof:name":"Holbe Julius GesmbH",
    "wof:placetype":"venue"
},
  "geometry": {"coordinates":[14.0508298874,48.1581993103],"type":"Point"}
}