{
  "type": "Feature",
  "properties": {
    "addr:full":"Hauptstr 40 St. Marein im M\u00fcrztal Steiermark 8641",
    "addr:housenumber":"40",
    "addr:postcode":"8641",
    "addr:street":"Hauptstr",
    "iso:country":"AT",
    "sg:address":"Hauptstr 40",
    "sg:city":"St. Marein im M\u00fcrztal",
    "sg:orig_category":"Webdesign",
    "sg:phone":"+43 4338 6420085",
    "sg:postcode":"8641",
    "sg:province":"Steiermark",
    "wof:name":"Web 2000 Unternehmens- u Systemberatungs-GmbH",
    "wof:placetype":"venue"
},
  "geometry": {"coordinates":[15.3676948547,47.473236084],"type":"Point"}
}