{
  "type": "Feature",
  "properties": {
    "iso:country":"AT",
    "sg:address":"Planitzer Weg 4",
    "sg:city":"Niedernsill",
    "sg:orig_category":"Maler, Anstreicher U Lackierer",
    "sg:phone":"+43 4365 4820137",
    "sg:postcode":"5722",
    "sg:province":"Salzburg",
    "wof:name":"Bayer Gerhard",
    "wof:placetype":"venue"
},
  "geometry": {"coordinates":[12.6527881622,47.2818946838],"type":"Point"}
}