{
  "type": "Feature",
  "properties": {
    "iso:country":"AT",
    "sg:address":"Stiglingen 5",
    "sg:city":"Dornbirn",
    "sg:orig_category":"Torantriebe",
    "sg:phone":"+43 5572 25282",
    "sg:postcode":"6850",
    "sg:province":"Vorarlberg",
    "wof:name":"Fohgrub Herbert",
    "wof:placetype":"venue"
},
  "geometry": {"coordinates":[9.7547168732,47.4309539795],"type":"Point"}
}