{
  "type": "Feature",
  "properties": {
    "addr:full":"Nr 58 M\u00fchlbach am Manhartsberg Nieder\u00f6sterreich 3473",
    "addr:postcode":"3473",
    "addr:street":"Nr;Muehlbach Am Manhartsberg",
    "iso:country":"AT",
    "sg:address":"Nr 58",
    "sg:city":"M\u00fchlbach am Manhartsberg",
    "sg:orig_category":"Lebensmittel / Einzelhandel",
    "sg:phone":"+43 4329 57303",
    "sg:postcode":"3473",
    "sg:province":"Nieder\u00f6sterreich",
    "wof:name":"Spar Markt - Amon Helmut",
    "wof:placetype":"venue"
},
  "geometry": {"coordinates":[15.748749733,48.5439605713],"type":"Point"}
}