{
  "type": "Feature",
  "properties": {
    "addr:full":"Obere Hauptstr 1 Steinbrunn Burgenland 7035",
    "addr:housenumber":"1",
    "addr:postcode":"7035",
    "addr:street":"Obere Hauptstr",
    "iso:country":"AT",
    "sg:address":"Obere Hauptstr 1",
    "sg:city":"Steinbrunn",
    "sg:orig_category":"Gemeinden",
    "sg:phone":"+43 2688 72212",
    "sg:postcode":"7035",
    "sg:province":"Burgenland",
    "wof:name":"Gemeindeamt Steinbrunn",
    "wof:placetype":"venue"
},
  "geometry": {"coordinates":[16.4138755798,47.8369750977],"type":"Point"}
}