{
  "type": "Feature",
  "properties": {
    "iso:country":"AT",
    "sg:address":"Kirchenpl 2",
    "sg:city":"Frauenkirchen",
    "sg:orig_category":"Non-Classified Establishments",
    "sg:phone":"+43 2172 2224",
    "sg:postcode":"7132",
    "sg:province":"Burgenland",
    "wof:name":"Pfarramt",
    "wof:placetype":"venue"
},
  "geometry": {"coordinates":[16.9269733429,47.8360214233],"type":"Point"}
}