{
  "type": "Feature",
  "properties": {
    "addr:full":"Nr 140 Guntersdorf Nieder\u00f6sterreich 2042",
    "addr:postcode":"2042",
    "addr:street":"Nr 140",
    "iso:country":"AT",
    "sg:address":"Nr 140",
    "sg:city":"Guntersdorf",
    "sg:orig_category":"Banken U Sparkassen",
    "sg:phone":"+43 4329 512471",
    "sg:postcode":"2042",
    "sg:province":"Nieder\u00f6sterreich",
    "wof:name":"Raiffeisenbank Hollabrunn regGenmbH",
    "wof:placetype":"venue"
},
  "geometry": {"coordinates":[16.0462493896,48.648059845],"type":"Point"}
}