{
  "type": "Feature",
  "properties": {
    "addr:full":"Hofwaldweg 35 Innsbruck Tirol 6020",
    "addr:housenumber":"35",
    "addr:postcode":"6020",
    "addr:street":"Hofwaldweg;Tirol",
    "iso:country":"AT",
    "sg:address":"Hofwaldweg 35",
    "sg:city":"Innsbruck",
    "sg:orig_category":"Innenarchitekten",
    "sg:phone":"+43 512 288340",
    "sg:postcode":"6020",
    "sg:province":"Tirol",
    "wof:name":"Sachs Adi Einrichtungsberatung",
    "wof:placetype":"venue"
},
  "geometry": {"coordinates":[11.3679237366,47.2701339722],"type":"Point"}
}