{
  "type": "Feature",
  "properties": {
    "addr:full":"Mayrweg 3b Hagenberg im M\u00fchlkreis Ober\u00f6sterreich 4232",
    "addr:housenumber":"3b",
    "addr:postcode":"4232",
    "addr:street":"Mayrweg;Im Muehlkreis Oberoesterreich",
    "iso:country":"AT",
    "sg:address":"Mayrweg 3b",
    "sg:city":"Hagenberg im M\u00fchlkreis",
    "sg:orig_category":"Geschenkartikel",
    "sg:phone":"+43 4372 363963",
    "sg:postcode":"4232",
    "sg:province":"Ober\u00f6sterreich",
    "wof:name":"Schwarzgruber GmbH",
    "wof:placetype":"venue"
},
  "geometry": {"coordinates":[14.5253400803,48.3588981628],"type":"Point"}
}