{
  "type": "Feature",
  "properties": {
    "addr:full":"Andreas-Hofer-Str 615 Seefeld in Tirol Tirol 6100",
    "addr:housenumber":"615",
    "addr:postcode":"6100",
    "addr:street":"Seefeld;Tirol",
    "iso:country":"AT",
    "sg:address":"Andreas-Hofer-Str 615",
    "sg:city":"Seefeld in Tirol",
    "sg:orig_category":"Psychologen",
    "sg:phone":"+43 676 7083051",
    "sg:postcode":"6100",
    "sg:province":"Tirol",
    "wof:name":"Zeller Carolin Mag Dr",
    "wof:placetype":"venue"
},
  "geometry": {"coordinates":[11.1886711121,47.3300094604],"type":"Point"}
}