{
  "type": "Feature",
  "properties": {
    "iso:country":"AT",
    "sg:address":"Getreideg 48",
    "sg:city":"Salzburg",
    "sg:orig_category":"Telekommunikation",
    "sg:phone":"+43 800 664300",
    "sg:postcode":"5020",
    "sg:province":"Salzburg",
    "wof:name":"A1-Shop Salzburg",
    "wof:placetype":"venue"
},
  "geometry": {"coordinates":[13.0404777527,47.8001060486],"type":"Point"}
}