{
  "type": "Feature",
  "properties": {
    "addr:full":"Wiener G 71 Perchtoldsdorf Nieder\u00f6sterreich 2380",
    "addr:housenumber":"71",
    "addr:postcode":"2380",
    "addr:street":"Wiener G",
    "iso:country":"AT",
    "sg:address":"Wiener G 71",
    "sg:city":"Perchtoldsdorf",
    "sg:classifiers":[
        {
            "category":"Restaurant",
            "type":"Food & Drink"
        }
    ],
    "sg:phone":"+43 1 86389200",
    "sg:postcode":"2380",
    "sg:province":"Nieder\u00f6sterreich",
    "wof:name":"PETER'SDORF",
    "wof:placetype":"venue"
},
  "geometry": {"coordinates":[16.2768306732,48.1281433105],"type":"Point"}
}