{
  "type": "Feature",
  "properties": {
    "addr:full":"Hauptstrasse 13 St. Lorenzen im M\u00fcrztal Steiermark 8642",
    "addr:housenumber":"13",
    "addr:postcode":"8642",
    "addr:street":"Hauptstrasse",
    "iso:country":"AT",
    "sg:address":"Hauptstrasse 13",
    "sg:city":"St. Lorenzen im M\u00fcrztal",
    "sg:classifiers":[
        {
            "category":"Community Center",
            "subcategory":"Youth",
            "type":"Public Place"
        }
    ],
    "sg:phone":"+43 3864 22430",
    "sg:postcode":"8642",
    "sg:province":"Steiermark",
    "sg:tags":[
        "plant",
        "flower",
        "artificial"
    ],
    "sg:website":"blumen-nagl.at",
    "wof:name":"Blumen Nagl",
    "wof:placetype":"venue"
},
  "geometry": {"coordinates":[15.3711433411,47.4781761169],"type":"Point"}
}