{
  "type": "Feature",
  "properties": {
    "addr:full":"H\u00f6rsdorf 35 Mank Nieder\u00f6sterreich 3240",
    "addr:housenumber":"35",
    "addr:postcode":"3240",
    "addr:street":"Hoersdorf;Niederoesterreich",
    "iso:country":"AT",
    "sg:address":"H\u00f6rsdorf 35",
    "sg:city":"Mank",
    "sg:orig_category":"Bauunternehmen",
    "sg:phone":"+43 2755 8900",
    "sg:postcode":"3240",
    "sg:province":"Nieder\u00f6sterreich",
    "wof:name":"Z\u00f6FA Baub\u00fcro GmbH",
    "wof:placetype":"venue"
},
  "geometry": {"coordinates":[15.3406190872,48.1110343933],"type":"Point"}
}