{
  "type": "Feature",
  "properties": {
    "addr:full":"Tenschertstrasse 3 Wien Wien 1230",
    "addr:housenumber":"3",
    "addr:postcode":"1230",
    "addr:street":"Tenschertstrasse",
    "iso:country":"AT",
    "sg:address":"Tenschertstrasse 3",
    "sg:city":"Wien",
    "sg:classifiers":[
        {
            "category":"Banks & Credit Unions",
            "subcategory":"Investment Brokerage",
            "type":"Services"
        }
    ],
    "sg:phone":"+43 1 6166812",
    "sg:postcode":"1230",
    "sg:province":"Wien",
    "sg:tags":[
        "cnc",
        "milling"
    ],
    "sg:website":"cnc-metall.at",
    "wof:name":"CNC-Metallproduktion-GmbH",
    "wof:placetype":"venue"
},
  "geometry": {"coordinates":[16.3565406799,48.1402282715],"type":"Point"}
}