{
  "type": "Feature",
  "properties": {
    "addr:full":"Linzer Str 76 Wien Wien 1140",
    "addr:housenumber":"76",
    "addr:postcode":"1140",
    "addr:street":"Linzer Str",
    "iso:country":"AT",
    "sg:address":"Linzer Str 76",
    "sg:city":"Wien",
    "sg:orig_category":"Arbeitsschutz U Arbeitsschutzartikel",
    "sg:phone":"+43 4317 8988000",
    "sg:postcode":"1140",
    "sg:province":"Wien",
    "sg:website":"asa-arbeitsschutz.at",
    "wof:name":"ASA Arbeitsschutzartikel- Direkt & Sicherheitsschuhe VertriebsgmbH",
    "wof:placetype":"venue"
},
  "geometry": {"coordinates":[16.3057136536,48.1939125061],"type":"Point"}
}