{
  "type": "Feature",
  "properties": {
    "addr:full":"Theresienfelder Gasse 51 Wiener Neustadt Nieder\u00f6sterreich 2700",
    "addr:housenumber":"51",
    "addr:postcode":"2700",
    "addr:street":"Gasse",
    "iso:country":"AT",
    "sg:address":"Theresienfelder Gasse 51",
    "sg:city":"Wiener Neustadt",
    "sg:orig_category":"Granite Pavers",
    "sg:phone":"+43 2622 27812",
    "sg:postcode":"2700",
    "sg:province":"Nieder\u00f6sterreich",
    "wof:name":"Josef Kampichler GesmbH",
    "wof:placetype":"venue"
},
  "geometry": {"coordinates":[16.2402610779,47.8444328308],"type":"Point"}
}