{
  "type": "Feature",
  "properties": {
    "iso:country":"AT",
    "sg:city":"Hochneukirchen",
    "sg:orig_category":"Feuerwehren",
    "sg:phone":"+43 2648 4611",
    "sg:postcode":"2852",
    "sg:province":"Nieder\u00f6sterreich",
    "wof:name":"Freiwillige Feuerwehr Gschaidt",
    "wof:placetype":"venue"
},
  "geometry": {"coordinates":[16.1997680664,47.4575958252],"type":"Point"}
}