{
  "type": "Feature",
  "properties": {
    "addr:full":"Seiterndorf 18 Weiten Nieder\u00f6sterreich 3653",
    "addr:housenumber":"18",
    "addr:postcode":"3653",
    "addr:street":"Seiterndorf;Niederoesterreich",
    "iso:country":"AT",
    "sg:address":"Seiterndorf 18",
    "sg:city":"Weiten",
    "sg:classifiers":[
        {
            "category":"Organizations",
            "subcategory":"Professional Association",
            "type":"Services"
        }
    ],
    "sg:phone":"+43 2758 8321",
    "sg:postcode":"3653",
    "sg:province":"Nieder\u00f6sterreich",
    "sg:tags":[
        "car",
        "full-service",
        "pool"
    ],
    "wof:name":"Werner Weissensteiner",
    "wof:placetype":"venue"
},
  "geometry": {"coordinates":[15.2340507507,48.2785758972],"type":"Point"}
}