{
  "type": "Feature",
  "properties": {
    "addr:full":"Austr 6 Wels Ober\u00f6sterreich 4600",
    "addr:housenumber":"6",
    "addr:postcode":"4600",
    "addr:street":"Austr;Oberoesterreich",
    "iso:country":"AT",
    "sg:address":"Austr 6",
    "sg:city":"Wels",
    "sg:orig_category":"Abdichtungen",
    "sg:phone":"+43 7242 70034",
    "sg:postcode":"4600",
    "sg:province":"Ober\u00f6sterreich",
    "wof:name":"Brandlmair G. KEG",
    "wof:placetype":"venue"
},
  "geometry": {"coordinates":[14.041261673,48.1549682617],"type":"Point"}
}