{
  "type": "Feature",
  "properties": {
    "iso:country":"AT",
    "sg:address":"Oberklammer Str 70",
    "sg:city":"Altenberg",
    "sg:orig_category":"Unternehmensberatung",
    "sg:phone":"+43 7230 20531",
    "sg:postcode":"4203",
    "sg:province":"Ober\u00f6sterreich",
    "wof:name":"Heilbrunner Christina Mag",
    "wof:placetype":"venue"
},
  "geometry": {"coordinates":[14.353228569,48.3494796753],"type":"Point"}
}