{
  "type": "Feature",
  "properties": {
    "addr:full":"Nr 16 Riegersburg Steiermark 8333",
    "addr:postcode":"8333",
    "addr:street":"Nr",
    "iso:country":"AT",
    "sg:address":"Nr 16",
    "sg:city":"Riegersburg",
    "sg:orig_category":"Tabaktrafiken",
    "sg:phone":"+43 3153 20071",
    "sg:postcode":"8333",
    "sg:province":"Steiermark",
    "wof:name":"Gumhold Waltraud",
    "wof:placetype":"venue"
},
  "geometry": {"coordinates":[15.9359292984,47.0007858276],"type":"Point"}
}