{
  "type": "Feature",
  "properties": {
    "addr:full":"D\u00f6blinger Hauptstr 11 Wien Wien 1190",
    "addr:housenumber":"11",
    "addr:postcode":"1190",
    "addr:street":"Hauptstr",
    "iso:country":"AT",
    "sg:address":"D\u00f6blinger Hauptstr 11",
    "sg:city":"Wien",
    "sg:orig_category":"Tapezierer U Dekorateure",
    "sg:phone":"+43 4313 690311",
    "sg:postcode":"1190",
    "sg:province":"Wien",
    "wof:name":"Eschelm\u00fcller Werner",
    "wof:placetype":"venue"
},
  "geometry": {"coordinates":[16.3526191711,48.2344284058],"type":"Point"}
}