{
  "type": "Feature",
  "properties": {
    "addr:full":"Muhreng 57/12 Wien Wien 1100",
    "addr:housenumber":"57 / 12",
    "addr:postcode":"1100",
    "addr:street":"Muhreng",
    "iso:country":"AT",
    "sg:address":"Muhreng 57/12",
    "sg:city":"Wien",
    "sg:orig_category":"Lichtwerbung, Displays",
    "sg:phone":"+43 1 6007582",
    "sg:postcode":"1100",
    "sg:province":"Wien",
    "sg:website":"display-technik.at",
    "wof:name":"Disp & Tech",
    "wof:placetype":"venue"
},
  "geometry": {"coordinates":[16.3721027374,48.169216156],"type":"Point"}
}