{
  "type": "Feature",
  "properties": {
    "addr:full":"Gampweg 28 Nenzing Vorarlberg 6710",
    "addr:housenumber":"28",
    "addr:postcode":"6710",
    "addr:street":"Gampweg",
    "iso:country":"AT",
    "sg:address":"Gampweg 28",
    "sg:city":"Nenzing",
    "sg:orig_category":"Genossenschaften",
    "sg:phone":"+43 5525 63280",
    "sg:postcode":"6710",
    "sg:province":"Vorarlberg",
    "wof:name":"Agrargemeinschaft Beschling-Latz",
    "wof:placetype":"venue"
},
  "geometry": {"coordinates":[9.6813621521,47.1902618408],"type":"Point"}
}