{
  "type": "Feature",
  "properties": {
    "iso:country":"AT",
    "sg:address":"Bismarckstr 16",
    "sg:city":"Feldbach",
    "sg:orig_category":"Versicherungsunternehmen",
    "sg:phone":"+43 3152 23050",
    "sg:postcode":"8330",
    "sg:province":"Steiermark",
    "wof:name":"Wiener St\u00e4dtische Allgemeine Versicherung AG",
    "wof:placetype":"venue"
},
  "geometry": {"coordinates":[15.8872900009,46.9505996704],"type":"Point"}
}