{
  "type": "Feature",
  "properties": {
    "addr:full":"Bahnzeile 1 Wilfersdorf Nieder\u00f6sterreich 2193",
    "addr:housenumber":"1",
    "addr:postcode":"2193",
    "addr:street":"Bahnzeile",
    "iso:country":"AT",
    "sg:address":"Bahnzeile 1",
    "sg:city":"Wilfersdorf",
    "sg:orig_category":"Reifen U Reifendienste",
    "sg:phone":"+43 664 2776510",
    "sg:postcode":"2193",
    "sg:province":"Nieder\u00f6sterreich",
    "wof:name":"Geyer Friedrich KFZ-Technik Reparatur Service & Verkauf von Druckluftbremssystemen",
    "wof:placetype":"venue"
},
  "geometry": {"coordinates":[16.6445789337,48.5837173462],"type":"Point"}
}