{
  "type": "Feature",
  "properties": {
    "addr:full":"Aigenstr 39 Wels Ober\u00f6sterreich 4600",
    "addr:housenumber":"39",
    "addr:postcode":"4600",
    "addr:street":"Aigenstr;Oberoesterreich",
    "iso:country":"AT",
    "sg:address":"Aigenstr 39",
    "sg:city":"Wels",
    "sg:orig_category":"Autoreparatur",
    "sg:phone":"+43 7242 41847",
    "sg:postcode":"4600",
    "sg:province":"Ober\u00f6sterreich",
    "wof:name":"Radner Karl",
    "wof:placetype":"venue"
},
  "geometry": {"coordinates":[14.0344133377,48.1495742798],"type":"Point"}
}