{
  "type": "Feature",
  "properties": {
    "iso:country":"AT",
    "sg:address":"Hauptstr 27",
    "sg:city":"Gro\u00df-Enzersdorf",
    "sg:orig_category":"Hufschmiede",
    "sg:phone":"+43 2215 2990",
    "sg:postcode":"2301",
    "sg:province":"Nieder\u00f6sterreich",
    "wof:name":"Langer Johann",
    "wof:placetype":"venue"
},
  "geometry": {"coordinates":[16.5967845917,48.1816558838],"type":"Point"}
}