{
  "type": "Feature",
  "properties": {
    "addr:full":"Zeiller Pl 1/I Reutte Tirol 6600",
    "addr:housenumber":"1 / i",
    "addr:postcode":"6600",
    "addr:street":"Zeiller Pl;Tirol",
    "iso:country":"AT",
    "sg:address":"Zeiller Pl 1/I",
    "sg:city":"Reutte",
    "sg:orig_category":"Fotografen",
    "sg:phone":"+43 664 1327673",
    "sg:postcode":"6600",
    "sg:province":"Tirol",
    "wof:name":"Foto Studio Sylvy",
    "wof:placetype":"venue"
},
  "geometry": {"coordinates":[10.7185935974,47.4889183044],"type":"Point"}
}