{
  "type": "Feature",
  "properties": {
    "addr:full":"Nu\u00dfdorfer Strasse 63 Wien Wien 1090",
    "addr:housenumber":"63",
    "addr:postcode":"1090",
    "addr:street":"Nussdorfer Strasse",
    "iso:country":"AT",
    "sg:address":"Nu\u00dfdorfer Strasse 63",
    "sg:city":"Wien",
    "sg:classifiers":[
        {
            "category":"Autos & Motor Vehicles",
            "subcategory":"Fuel & Gas Station",
            "type":"Retail Goods"
        }
    ],
    "sg:phone":"+43 1 3172145",
    "sg:postcode":"1090",
    "sg:province":"Wien",
    "sg:tags":[
        "appliance",
        "heating"
    ],
    "wof:name":"Ing. Brodicky Ges.m.b.H.",
    "wof:placetype":"venue"
},
  "geometry": {"coordinates":[16.3543071747,48.2295455933],"type":"Point"}
}