{
  "type": "Feature",
  "properties": {
    "addr:full":"Mozartweg 25 St. Johann in Tirol Tirol 6380",
    "addr:housenumber":"25",
    "addr:postcode":"6380",
    "addr:street":"Mozartweg;Tirol",
    "iso:country":"AT",
    "sg:address":"Mozartweg 25",
    "sg:city":"St. Johann in Tirol",
    "sg:orig_category":"Pensionen / Privatzimmer",
    "sg:phone":"+43 5352 62456",
    "sg:postcode":"6380",
    "sg:province":"Tirol",
    "wof:name":"Haus Isenburg",
    "wof:placetype":"venue"
},
  "geometry": {"coordinates":[12.4173593521,47.5203933716],"type":"Point"}
}