{
  "type": "Feature",
  "properties": {
    "addr:full":"Harterfeldstr 14d Leonding Ober\u00f6sterreich 4060",
    "addr:housenumber":"14d",
    "addr:postcode":"4060",
    "addr:street":"Harterfeldstr",
    "iso:country":"AT",
    "sg:address":"Harterfeldstr 14d",
    "sg:city":"Leonding",
    "sg:orig_category":"Detekteien",
    "sg:phone":"+43 732 676440",
    "sg:postcode":"4060",
    "sg:province":"Ober\u00f6sterreich",
    "wof:name":"Atlantis Detektivb\u00fcro Peter Hager-Roiser",
    "wof:placetype":"venue"
},
  "geometry": {"coordinates":[14.2558383942,48.263874054],"type":"Point"}
}