{
  "type": "Feature",
  "properties": {
    "addr:full":"Birkfelder Str 84 Weiz Steiermark 8160",
    "addr:housenumber":"84",
    "addr:postcode":"8160",
    "addr:street":"Str",
    "iso:country":"AT",
    "sg:address":"Birkfelder Str 84",
    "sg:city":"Weiz",
    "sg:orig_category":"Steinmetzbetriebe",
    "sg:phone":"+43 4331 7223320",
    "sg:postcode":"8160",
    "sg:province":"Steiermark",
    "sg:website":"stein-wiedenhofer.at",
    "wof:name":"L Wiedenhofer Steinmetzmeister-GesmbH & Co KG",
    "wof:placetype":"venue"
},
  "geometry": {"coordinates":[15.6378068924,47.2199134827],"type":"Point"}
}