{
  "type": "Feature",
  "properties": {
    "iso:country":"AT",
    "sg:address":"Nr 36",
    "sg:city":"Terfens",
    "sg:orig_category":"Autobusunternehmen",
    "sg:phone":"+43 5224 68426",
    "sg:postcode":"6123",
    "sg:province":"Tirol",
    "wof:name":"Karwendelbusreisen Tausch KEG",
    "wof:placetype":"venue"
},
  "geometry": {"coordinates":[11.6419610977,47.3217391968],"type":"Point"}
}