{
  "type": "Feature",
  "properties": {
    "addr:full":"Falkenstr 5 Prinzersdorf Nieder\u00f6sterreich 3385",
    "addr:housenumber":"5",
    "addr:postcode":"3385",
    "addr:street":"Falkenstr",
    "iso:country":"AT",
    "sg:address":"Falkenstr 5",
    "sg:city":"Prinzersdorf",
    "sg:orig_category":"Autoreparatur",
    "sg:phone":"+43 4327 492501",
    "sg:postcode":"3385",
    "sg:province":"Nieder\u00f6sterreich",
    "wof:name":"Ratzinger Franz",
    "wof:placetype":"venue"
},
  "geometry": {"coordinates":[15.5544900894,48.1992416382],"type":"Point"}
}