{
  "type": "Feature",
  "properties": {
    "addr:full":"Hanuschstr 25 Enns Ober\u00f6sterreich 4470",
    "addr:housenumber":"25",
    "addr:postcode":"4470",
    "addr:street":"Hanuschstr",
    "iso:country":"AT",
    "sg:address":"Hanuschstr 25",
    "sg:city":"Enns",
    "sg:orig_category":"Polytechnische Schulen",
    "sg:phone":"+43 7223 81515",
    "sg:postcode":"4470",
    "sg:province":"Ober\u00f6sterreich",
    "wof:name":"Polytechnische Schule",
    "wof:placetype":"venue"
},
  "geometry": {"coordinates":[14.4777212143,48.2181854248],"type":"Point"}
}