{
  "type": "Feature",
  "properties": {
    "addr:full":"Vorberg 12 Ramsau am Dachstein Steiermark 8972",
    "addr:housenumber":"12",
    "addr:postcode":"8972",
    "addr:street":"Vorberg",
    "iso:country":"AT",
    "sg:address":"Vorberg 12",
    "sg:city":"Ramsau am Dachstein",
    "sg:orig_category":"Pensionen / Privatzimmer",
    "sg:phone":"+43 4364 547363",
    "sg:postcode":"8972",
    "sg:province":"Steiermark",
    "wof:name":"Pension Astlhof",
    "wof:placetype":"venue"
},
  "geometry": {"coordinates":[13.6386823654,47.4179039001],"type":"Point"}
}