{
  "type": "Feature",
  "properties": {
    "iso:country":"AT",
    "sg:address":"Lehmanng 23",
    "sg:city":"Wien",
    "sg:orig_category":"Friseure U Frisiersalons",
    "sg:phone":"+43 1 8658910",
    "sg:postcode":"1230",
    "sg:province":"Wien",
    "wof:name":"Trost Martina",
    "wof:placetype":"venue"
},
  "geometry": {"coordinates":[16.2784175873,48.1362991333],"type":"Point"}
}