{
  "type": "Feature",
  "properties": {
    "addr:full":"Gewerbepark 8 Hall in Tirol Tirol 6060",
    "addr:housenumber":"8",
    "addr:postcode":"6060",
    "addr:street":"Gewerbepark;Tirol",
    "iso:country":"AT",
    "sg:address":"Gewerbepark 8",
    "sg:city":"Hall in Tirol",
    "sg:orig_category":"Ecg Electrodes",
    "sg:phone":"+43 5223 46087",
    "sg:postcode":"6060",
    "sg:province":"Tirol",
    "wof:name":"Metec Medizinhandel und Technologie GmbH",
    "wof:placetype":"venue"
},
  "geometry": {"coordinates":[11.5024385452,47.2797927856],"type":"Point"}
}