{
  "type": "Feature",
  "properties": {
    "iso:country":"AT",
    "sg:address":"Musilplatz 4",
    "sg:city":"Wien",
    "sg:classifiers":[
        {
            "category":"Banks & Credit Unions",
            "subcategory":"Bureau De Change",
            "type":"Services"
        }
    ],
    "sg:phone":"+43 1 4862585",
    "sg:postcode":"1160",
    "sg:province":"Wien",
    "sg:tags":[
        "housing",
        "plastic"
    ],
    "wof:name":"Ingeborg Weilguni Ges.m.b.H.",
    "wof:placetype":"venue"
},
  "geometry": {"coordinates":[16.3079090118,48.215713501],"type":"Point"}
}