{
  "type": "Feature",
  "properties": {
    "addr:full":"Am Freihof 39 Wien Wien 1220",
    "addr:housenumber":"39",
    "addr:postcode":"1220",
    "addr:street":"Am Freihof",
    "iso:country":"AT",
    "sg:address":"Am Freihof 39",
    "sg:city":"Wien",
    "sg:orig_category":"Werbeagenturen",
    "sg:phone":"+43 1 2036403",
    "sg:postcode":"1220",
    "sg:province":"Wien",
    "wof:name":"Moto-Consulting Christian Molzer",
    "wof:placetype":"venue"
},
  "geometry": {"coordinates":[16.4496612549,48.2473335266],"type":"Point"}
}