{
  "type": "Feature",
  "properties": {
    "iso:country":"AT",
    "sg:address":"Leibnitzer Str 4",
    "sg:city":"Lebring",
    "sg:orig_category":"Reinigungsservice",
    "sg:phone":"+43 3182 3660",
    "sg:postcode":"8403",
    "sg:province":"Steiermark",
    "wof:name":"Kleiderreinigung Zirngast",
    "wof:placetype":"venue"
},
  "geometry": {"coordinates":[15.5358381271,46.857006073],"type":"Point"}
}