{
  "type": "Feature",
  "properties": {
    "iso:country":"AT",
    "sg:address":"Hadeldorfstr 17",
    "sg:city":"Rankweil",
    "sg:orig_category":"Autoreparatur",
    "sg:phone":"+43 5522 43727",
    "sg:postcode":"6830",
    "sg:province":"Vorarlberg",
    "wof:name":"Flash Autotechnik GmbH",
    "wof:placetype":"venue"
},
  "geometry": {"coordinates":[9.6403989792,47.2740821838],"type":"Point"}
}