{
  "type": "Feature",
  "properties": {
    "iso:country":"AT",
    "sg:address":"Nr 9",
    "sg:city":"Offenhausen",
    "sg:orig_category":"Elektroinstallationsunternehmen",
    "sg:phone":"+43 7247 62350",
    "sg:postcode":"4625",
    "sg:province":"Ober\u00f6sterreich",
    "wof:name":"Buder Walter",
    "wof:placetype":"venue"
},
  "geometry": {"coordinates":[18.5431098938,47.2171516418],"type":"Point"}
}