{
  "type": "Feature",
  "properties": {
    "addr:full":"Austr 24 Rum Tirol 6063",
    "addr:housenumber":"24",
    "addr:postcode":"6063",
    "addr:street":"Austr;Tirol",
    "iso:country":"AT",
    "sg:address":"Austr 24",
    "sg:city":"Rum",
    "sg:orig_category":"Installationsunternehmen",
    "sg:phone":"+43 512 2619160",
    "sg:postcode":"6063",
    "sg:province":"Tirol",
    "wof:name":"Hotter & Fobeaux",
    "wof:placetype":"venue"
},
  "geometry": {"coordinates":[11.449048996,47.276966095],"type":"Point"}
}