{
  "type": "Feature",
  "properties": {
    "iso:country":"AT",
    "sg:address":"Donaustr 47",
    "sg:city":"Regelsbrunn",
    "sg:orig_category":"Schneidereien",
    "sg:phone":"+43 2163 2289",
    "sg:postcode":"2403",
    "sg:province":"Nieder\u00f6sterreich",
    "wof:name":"Gesperger Karl",
    "wof:placetype":"venue"
},
  "geometry": {"coordinates":[16.8051109314,48.1122741699],"type":"Point"}
}