{
  "type": "Feature",
  "properties": {
    "addr:full":"Simmeringer Hauptstr 281 Wien Wien 1110",
    "addr:housenumber":"281",
    "addr:postcode":"1110",
    "addr:street":"Simmeringer Hauptstr",
    "iso:country":"AT",
    "sg:address":"Simmeringer Hauptstr 281",
    "sg:city":"Wien",
    "sg:orig_category":"Blumeneinzelhandel",
    "sg:phone":"+43 1 76025",
    "sg:postcode":"1110",
    "sg:province":"Wien",
    "wof:name":"F\u00f6tschl Martin",
    "wof:placetype":"venue"
},
  "geometry": {"coordinates":[16.4342575073,48.1587982178],"type":"Point"}
}