{
  "type": "Feature",
  "properties": {
    "addr:full":"Freisinger Berg 2 Waidhofen an der Ybbs Nieder\u00f6sterreich 3340",
    "addr:housenumber":"2",
    "addr:postcode":"3340",
    "addr:street":"Freisinger Berg",
    "iso:country":"AT",
    "sg:address":"Freisinger Berg 2",
    "sg:city":"Waidhofen an der Ybbs",
    "sg:orig_category":"Tourismusinformation U -Organisationen",
    "sg:phone":"+43 4374 42511255",
    "sg:postcode":"3340",
    "sg:province":"Nieder\u00f6sterreich",
    "wof:name":"Tourismusb\u00fcro",
    "wof:placetype":"venue"
},
  "geometry": {"coordinates":[14.7744684219,47.9610939026],"type":"Point"}
}