{
  "type": "Feature",
  "properties": {
    "addr:full":"Maria Theresien-Str 91 Lustenau Vorarlberg 6890",
    "addr:housenumber":"91",
    "addr:postcode":"6890",
    "iso:country":"AT",
    "sg:address":"Maria Theresien-Str 91",
    "sg:city":"Lustenau",
    "sg:orig_category":"Tanzschulen",
    "sg:phone":"+43 5577 85259",
    "sg:postcode":"6890",
    "sg:province":"Vorarlberg",
    "wof:name":"Flamenco - Studio",
    "wof:placetype":"venue"
},
  "geometry": {"coordinates":[9.6565599442,47.436290741],"type":"Point"}
}