{
  "type": "Feature",
  "properties": {
    "iso:country":"AT",
    "sg:address":"Schulstr 1",
    "sg:city":"Berndorf",
    "sg:orig_category":"Volksschulen",
    "sg:phone":"+43 4362 1720477",
    "sg:postcode":"5165",
    "sg:province":"Salzburg",
    "wof:name":"Volksschule Matthias Laireiter",
    "wof:placetype":"venue"
},
  "geometry": {"coordinates":[13.0583229065,47.9952964783],"type":"Point"}
}