{
  "type": "Feature",
  "properties": {
    "addr:full":"Jochberger Str 67 Kitzb\u00fchel Tirol 6370",
    "addr:postcode":"6370",
    "addr:street":"Str 67 Kitzbuehel Tirol",
    "iso:country":"AT",
    "sg:address":"Jochberger Str 67",
    "sg:city":"Kitzb\u00fchel",
    "sg:orig_category":"Volkshochschulen",
    "sg:phone":"+43 5356 74159",
    "sg:postcode":"6370",
    "sg:province":"Tirol",
    "wof:name":"Volkshochschule",
    "wof:placetype":"venue"
},
  "geometry": {"coordinates":[12.4003305435,47.4394569397],"type":"Point"}
}