{
  "type": "Feature",
  "properties": {
    "addr:full":"Danreiterg 8 Salzburg Salzburg 5020",
    "addr:housenumber":"8",
    "addr:postcode":"5020",
    "addr:street":"Danreiterg;Salzburg",
    "iso:country":"AT",
    "sg:address":"Danreiterg 8",
    "sg:city":"Salzburg",
    "sg:orig_category":"Hauskrankenpflege / Heimhilfe",
    "sg:phone":"+43 662 6210100",
    "sg:postcode":"5020",
    "sg:province":"Salzburg",
    "wof:name":"Salzburger Krankenhilfe",
    "wof:placetype":"venue"
},
  "geometry": {"coordinates":[13.0653448105,47.7964706421],"type":"Point"}
}