{
  "type": "Feature",
  "properties": {
    "addr:full":"Kircheng 13 Knittelfeld Steiermark 8720",
    "addr:housenumber":"13",
    "addr:postcode":"8720",
    "addr:street":"Kircheng",
    "iso:country":"AT",
    "sg:address":"Kircheng 13",
    "sg:city":"Knittelfeld",
    "sg:orig_category":"Fleischhauereien",
    "sg:phone":"+43 4335 1282340",
    "sg:postcode":"8720",
    "sg:province":"Steiermark",
    "wof:name":"Klampfer Dieter",
    "wof:placetype":"venue"
},
  "geometry": {"coordinates":[14.8306856155,47.213634491],"type":"Point"}
}