{
  "type": "Feature",
  "properties": {
    "addr:full":"Triester Str 290 Wien Wien 1230",
    "addr:housenumber":"290",
    "addr:postcode":"1230",
    "iso:country":"AT",
    "sg:address":"Triester Str 290",
    "sg:city":"Wien",
    "sg:orig_category":"Autohandel",
    "sg:phone":"+43 1 6985531",
    "sg:postcode":"1230",
    "sg:province":"Wien",
    "wof:name":"Autozentrum",
    "wof:placetype":"venue"
},
  "geometry": {"coordinates":[16.3221740723,48.1317901611],"type":"Point"}
}