{
  "type": "Feature",
  "properties": {
    "addr:full":"Groi\u00dfgraben 2 Grein Ober\u00f6sterreich 4360",
    "addr:housenumber":"2",
    "addr:postcode":"4360",
    "addr:street":"Groissgraben",
    "iso:country":"AT",
    "sg:address":"Groi\u00dfgraben 2",
    "sg:city":"Grein",
    "sg:orig_category":"Hauptschulen",
    "sg:phone":"+43 7268 70460",
    "sg:postcode":"4360",
    "sg:province":"Ober\u00f6sterreich",
    "wof:name":"Hauptschule",
    "wof:placetype":"venue"
},
  "geometry": {"coordinates":[14.8253002167,48.2162208557],"type":"Point"}
}