{
  "type": "Feature",
  "properties": {
    "addr:full":"Weinzierler Br\u00fccke 23 Kirchdorf an der Krems Ober\u00f6sterreich 4560",
    "addr:housenumber":"23",
    "addr:postcode":"4560",
    "iso:country":"AT",
    "sg:address":"Weinzierler Br\u00fccke 23",
    "sg:city":"Kirchdorf an der Krems",
    "sg:classifiers":[
        {
            "category":"Taxi",
            "type":"Transportation"
        }
    ],
    "sg:phone":"+43 4375 8261711",
    "sg:postcode":"4560",
    "sg:province":"Ober\u00f6sterreich",
    "sg:tags":[
        "personentransporte",
        "u"
    ],
    "wof:name":"Kirchdorfer Taxi Riedler & Co KEG",
    "wof:placetype":"venue"
},
  "geometry": {"coordinates":[14.1225223541,47.9058189392],"type":"Point"}
}