{
  "type": "Feature",
  "properties": {
    "addr:full":"Auer-von-Welsbach-Str 4 Salzburg Salzburg 5020",
    "addr:housenumber":"4",
    "addr:postcode":"5020",
    "addr:street":"Auer-Von-Welsbach-Str;Salzburg",
    "iso:country":"AT",
    "sg:address":"Auer-von-Welsbach-Str 4",
    "sg:city":"Salzburg",
    "sg:orig_category":"Polizei U Gendarmerie",
    "sg:phone":"+43 4366 263835841",
    "sg:postcode":"5020",
    "sg:province":"Salzburg",
    "wof:name":"Polizei Taxham",
    "wof:placetype":"venue"
},
  "geometry": {"coordinates":[13.0046596527,47.8126373291],"type":"Point"}
}