{
  "type": "Feature",
  "properties": {
    "addr:full":"Einfahrt Mitte 432 Mayrhofen Tirol 6290",
    "addr:housenumber":"432",
    "addr:postcode":"6290",
    "addr:street":"Einfahrt Mitte;Tirol",
    "iso:country":"AT",
    "sg:address":"Einfahrt Mitte 432",
    "sg:city":"Mayrhofen",
    "sg:classifiers":[
        {
            "category":"Travel",
            "subcategory":"Hotels & Motels",
            "type":"Entertainment"
        }
    ],
    "sg:phone":"+43 5285 67670",
    "sg:postcode":"6290",
    "sg:province":"Tirol",
    "wof:name":"Hotel Elisabeth",
    "wof:placetype":"venue"
},
  "geometry": {"coordinates":[11.8611059189,47.1675071716],"type":"Point"}
}