{
  "type": "Feature",
  "properties": {
    "addr:full":"Sonnberg 59 Leogang Salzburg 5771",
    "addr:housenumber":"59",
    "addr:postcode":"5771",
    "addr:street":"Sonnberg;Salzburg",
    "iso:country":"AT",
    "sg:address":"Sonnberg 59",
    "sg:city":"Leogang",
    "sg:orig_category":"Erdarbeiten",
    "sg:phone":"+43 664 2316628",
    "sg:postcode":"5771",
    "sg:province":"Salzburg",
    "wof:name":"Hasenauer Erdbau & Transporte GmbH",
    "wof:placetype":"venue"
},
  "geometry": {"coordinates":[12.7476482391,47.4409828186],"type":"Point"}
}