{
  "type": "Feature",
  "properties": {
    "addr:full":"Donaufelder Str 255 Wien Wien 1220",
    "addr:housenumber":"255",
    "addr:postcode":"1220",
    "iso:country":"AT",
    "sg:address":"Donaufelder Str 255",
    "sg:city":"Wien",
    "sg:orig_category":"Autohandel",
    "sg:phone":"+43 1 2033133",
    "sg:postcode":"1220",
    "sg:province":"Wien",
    "wof:name":"Lock Alois",
    "wof:placetype":"venue"
},
  "geometry": {"coordinates":[16.4417572021,48.2502098083],"type":"Point"}
}