{
  "type": "Feature",
  "properties": {
    "addr:full":"Donaul\u00e4nde 8A Krems an der Donau Nieder\u00f6sterreich 3500",
    "addr:housenumber":"8a",
    "addr:postcode":"3500",
    "addr:street":"Donaulaende",
    "iso:country":"AT",
    "sg:address":"Donaul\u00e4nde 8A",
    "sg:city":"Krems an der Donau",
    "sg:orig_category":"Versicherungsunternehmen",
    "sg:phone":"+43 4327 3282271",
    "sg:postcode":"3500",
    "sg:province":"Nieder\u00f6sterreich",
    "wof:name":"Basler Versicherungs AG in \u00f6sterreich - Dienstleistungszentrum",
    "wof:placetype":"venue"
},
  "geometry": {"coordinates":[15.5965108871,48.4088058472],"type":"Point"}
}