{
  "type": "Feature",
  "properties": {
    "iso:country":"AT",
    "sg:address":"Tschavollstr 7",
    "sg:city":"Feldkirch",
    "sg:orig_category":"Tischlereien",
    "sg:phone":"+43 664 5365706",
    "sg:postcode":"6800",
    "sg:province":"Vorarlberg",
    "wof:name":"Graf Werner",
    "wof:placetype":"venue"
},
  "geometry": {"coordinates":[9.5878705978,47.2317962646],"type":"Point"}
}