{
  "type": "Feature",
  "properties": {
    "iso:country":"AT",
    "sg:address":"Raiffeisenstr 4",
    "sg:city":"Neunkirchen",
    "sg:orig_category":"Lebensmittel / Einzelhandel",
    "sg:phone":"+43 2635 64996",
    "sg:postcode":"2620",
    "sg:province":"Nieder\u00f6sterreich",
    "wof:name":"Billa AG",
    "wof:placetype":"venue"
},
  "geometry": {"coordinates":[16.0842857361,47.7199897766],"type":"Point"}
}