{
  "type": "Feature",
  "properties": {
    "addr:full":"Hans-Czettel-Str 10 Gm\u00fcnd Nieder\u00f6sterreich 3950",
    "addr:housenumber":"10",
    "addr:postcode":"3950",
    "addr:street":"Hans-Czettel-Str;Niederoesterreich",
    "iso:country":"AT",
    "sg:address":"Hans-Czettel-Str 10",
    "sg:city":"Gm\u00fcnd",
    "sg:orig_category":"Zimmereien",
    "sg:phone":"+43 4328 52521620",
    "sg:postcode":"3950",
    "sg:province":"Nieder\u00f6sterreich",
    "wof:name":"Mokesch Bau- u Zimmermeister GesmbH",
    "wof:placetype":"venue"
},
  "geometry": {"coordinates":[14.9977283478,48.7587776184],"type":"Point"}
}