{
  "type": "Feature",
  "properties": {
    "addr:full":"Gaismairallee 45 Radstadt Salzburg 5550",
    "addr:housenumber":"45",
    "addr:postcode":"5550",
    "addr:street":"Gaismairallee;Salzburg",
    "iso:country":"AT",
    "sg:address":"Gaismairallee 45",
    "sg:city":"Radstadt",
    "sg:classifiers":[
        {
            "category":"Home & Garden",
            "subcategory":"Building Materials",
            "type":"Retail Goods"
        }
    ],
    "sg:phone":"+43 6452 5970",
    "sg:postcode":"5550",
    "sg:province":"Salzburg",
    "sg:tags":[
        "tile",
        "marble"
    ],
    "wof:name":"Fliesen-Fliesco Fliesenverlegung GmbH",
    "wof:placetype":"venue"
},
  "geometry": {"coordinates":[13.4495201111,47.3831367493],"type":"Point"}
}