{
  "type": "Feature",
  "properties": {
    "addr:full":"Moos 24 9953",
    "addr:housenumber":"24",
    "addr:postcode":"9953",
    "addr:street":"Moos",
    "iso:country":"AT",
    "sg:address":"Moos 24",
    "sg:orig_category":"Tischlereien",
    "sg:phone":"+43 4872 5630",
    "sg:postcode":"9953",
    "sg:website":"www.coop-holz.at",
    "wof:name":"Rainer Gerhard",
    "wof:placetype":"venue"
},
  "geometry": {"coordinates":[12.573764801,46.9368247986],"type":"Point"}
}