{
  "type": "Feature",
  "properties": {
    "iso:country":"AT",
    "sg:address":"Hannoverg 16",
    "sg:city":"Wien",
    "sg:orig_category":"Lebensmittel / Einzelhandel",
    "sg:phone":"+43 4312 763942",
    "sg:postcode":"1200",
    "sg:province":"Wien",
    "wof:name":"AN-DATA HandelsgesmbH",
    "wof:placetype":"venue"
},
  "geometry": {"coordinates":[16.3691997528,48.2307434082],"type":"Point"}
}