{
  "type": "Feature",
  "properties": {
    "addr:full":"Industriestr 18-20 Gerasdorf Nieder\u00f6sterreich 2201",
    "addr:postcode":"18-20;2201",
    "addr:street":"Niederoesterreich",
    "iso:country":"AT",
    "sg:address":"Industriestr 18-20",
    "sg:city":"Gerasdorf",
    "sg:orig_category":"Fleischereimaschinen U -Einrichtungen",
    "sg:phone":"+43 4322 4631180",
    "sg:postcode":"2201",
    "sg:province":"Nieder\u00f6sterreich",
    "wof:name":"Inject Star P\u00f6kelmaschinen GesmbH",
    "wof:placetype":"venue"
},
  "geometry": {"coordinates":[16.459569931,48.3357772827],"type":"Point"}
}