{
  "type": "Feature",
  "properties": {
    "addr:full":"Stadtpl 44 Wels Ober\u00f6sterreich 4600",
    "addr:housenumber":"44",
    "addr:postcode":"4600",
    "addr:street":"Stadtpl;Oberoesterreich",
    "iso:country":"AT",
    "sg:address":"Stadtpl 44",
    "sg:city":"Wels",
    "sg:orig_category":"Personalbereitstellung",
    "sg:phone":"+43 7242 207676",
    "sg:postcode":"4600",
    "sg:province":"Ober\u00f6sterreich",
    "wof:name":"EUROJOBS GesmbH",
    "wof:placetype":"venue"
},
  "geometry": {"coordinates":[14.0247087479,48.1568717957],"type":"Point"}
}