{
  "type": "Feature",
  "properties": {
    "addr:full":"Gasteiner Str 46 Bischofshofen Salzburg 5500",
    "addr:housenumber":"46",
    "addr:postcode":"5500",
    "addr:street":"Gasteiner Str;Salzburg",
    "iso:country":"AT",
    "sg:address":"Gasteiner Str 46",
    "sg:city":"Bischofshofen",
    "sg:orig_category":"Lebensmittel / Einzelhandel",
    "sg:phone":"+43 6462 22655",
    "sg:postcode":"5500",
    "sg:province":"Salzburg",
    "wof:name":"Hofer KG",
    "wof:placetype":"venue"
},
  "geometry": {"coordinates":[13.2165966034,47.4106483459],"type":"Point"}
}