{
  "type": "Feature",
  "properties": {
    "addr:full":"Wei\u00dfkirchner Strasse 84 Gro\u00dflobming Steiermark 8734",
    "addr:housenumber":"84",
    "addr:postcode":"8734",
    "addr:street":"Weisskirchner Strasse",
    "iso:country":"AT",
    "sg:address":"Wei\u00dfkirchner Strasse 84",
    "sg:city":"Gro\u00dflobming",
    "sg:classifiers":[
        {
            "category":"Manufacturing",
            "subcategory":"Wood Products",
            "type":"Manufacturing & Wholesale Goods"
        }
    ],
    "sg:phone":"+43 3512 829100",
    "sg:postcode":"8734",
    "sg:province":"Steiermark",
    "sg:tags":[
        "lumber"
    ],
    "wof:name":"Gebr\u00fcder Egger Ges.m.b.H. & Co",
    "wof:placetype":"venue"
},
  "geometry": {"coordinates":[14.7951402664,47.1815071106],"type":"Point"}
}