{
  "type": "Feature",
  "properties": {
    "addr:full":"Steinamangerer Str 19 Oberwart Burgenland 7400",
    "addr:housenumber":"19",
    "addr:postcode":"7400",
    "addr:street":"Str",
    "iso:country":"AT",
    "sg:address":"Steinamangerer Str 19",
    "sg:city":"Oberwart",
    "sg:orig_category":"Bettfedernreinigung",
    "sg:phone":"+43 3352 38539",
    "sg:postcode":"7400",
    "sg:province":"Burgenland",
    "wof:name":"Bettfedern-Reinigung Gerlinde Tschida",
    "wof:placetype":"venue"
},
  "geometry": {"coordinates":[16.2160511017,47.2857666016],"type":"Point"}
}