{
  "type": "Feature",
  "properties": {
    "addr:full":"Ranser Feld 4 Aldrans Tirol 6071",
    "addr:housenumber":"4",
    "addr:postcode":"6071",
    "addr:street":"Ranser Feld;Tirol",
    "iso:country":"AT",
    "sg:address":"Ranser Feld 4",
    "sg:city":"Aldrans",
    "sg:orig_category":"Gesundheit / Allgemeine Informationsstellen",
    "sg:phone":"+43 512 394233",
    "sg:postcode":"6071",
    "sg:province":"Tirol",
    "wof:name":"Feldenkrais Methode - Mag Helga Jenewein",
    "wof:placetype":"venue"
},
  "geometry": {"coordinates":[11.4444284439,47.245300293],"type":"Point"}
}