{
  "type": "Feature",
  "properties": {
    "addr:full":"Z\u00f6chg 30 Bisamberg Nieder\u00f6sterreich 2102",
    "addr:housenumber":"30",
    "addr:postcode":"2102",
    "addr:street":"Zoechg",
    "iso:country":"AT",
    "sg:address":"Z\u00f6chg 30",
    "sg:city":"Bisamberg",
    "sg:orig_category":"Transportunternehmen",
    "sg:phone":"+43 2262 62676",
    "sg:postcode":"2102",
    "sg:province":"Nieder\u00f6sterreich",
    "wof:name":"Kisela Martin",
    "wof:placetype":"venue"
},
  "geometry": {"coordinates":[16.3610553741,48.3311195374],"type":"Point"}
}