{
  "type": "Feature",
  "properties": {
    "iso:country":"AT",
    "sg:address":"Argentinierstr 8/265",
    "sg:city":"Wien",
    "sg:orig_category":"Institute",
    "sg:phone":"+43 4315 880126501",
    "sg:postcode":"1040",
    "sg:province":"Wien",
    "wof:name":"Institut f Rechtswissenschaften d TU Wien",
    "wof:placetype":"venue"
},
  "geometry": {"coordinates":[16.3714141846,48.1976242065],"type":"Point"}
}