{
  "type": "Feature",
  "properties": {
    "addr:full":"Sebastian-St\u00f6llner-Str 17a Salzburg Salzburg 5020",
    "addr:housenumber":"17a",
    "addr:postcode":"5020",
    "addr:street":"Sebastian-Stoellner-Str;Salzburg",
    "iso:country":"AT",
    "sg:address":"Sebastian-St\u00f6llner-Str 17a",
    "sg:city":"Salzburg",
    "sg:orig_category":"Fotografen",
    "sg:phone":"+43 4366 2831965",
    "sg:postcode":"5020",
    "sg:province":"Salzburg",
    "wof:name":"Lindenbauer Ursula - Photo Design",
    "wof:placetype":"venue"
},
  "geometry": {"coordinates":[13.0224313736,47.7990036011],"type":"Point"}
}