{
  "type": "Feature",
  "properties": {
    "iso:country":"AT",
    "sg:address":"Josefsthaler Str 32",
    "sg:city":"Tribuswinkel",
    "sg:orig_category":"Speditionen",
    "sg:phone":"+43 2252 45701",
    "sg:postcode":"2512",
    "sg:province":"Nieder\u00f6sterreich",
    "wof:name":"Toplica Kuzmanovic GesmbH",
    "wof:placetype":"venue"
},
  "geometry": {"coordinates":[16.2946853638,47.9884490967],"type":"Point"}
}