{
  "type": "Feature",
  "properties": {
    "iso:country":"AT",
    "sg:address":"Pfarrg 4",
    "sg:city":"Steyr",
    "sg:orig_category":"Geschenkartikel",
    "sg:phone":"+43 7252 46378",
    "sg:postcode":"4400",
    "sg:province":"Ober\u00f6sterreich",
    "wof:name":"Sunk Mathilde Geschenkstube",
    "wof:placetype":"venue"
},
  "geometry": {"coordinates":[14.4175357819,48.0371551514],"type":"Point"}
}