{
  "type": "Feature",
  "properties": {
    "iso:country":"AT",
    "sg:address":"Nr 20",
    "sg:city":"Theras",
    "sg:orig_category":"Landwirtschaftliche Produkte",
    "sg:phone":"+43 4329 47393",
    "sg:postcode":"3742",
    "sg:province":"Nieder\u00f6sterreich",
    "wof:name":"Meierhofer Norbert u Hilda",
    "wof:placetype":"venue"
},
  "geometry": {"coordinates":[15.7620153427,48.7446746826],"type":"Point"}
}