{
  "type": "Feature",
  "properties": {
    "addr:full":"Bachstrasse 57 Gnigl Salzburg 5023",
    "addr:housenumber":"57",
    "addr:postcode":"5023",
    "addr:street":"Bachstrasse",
    "iso:country":"AT",
    "sg:address":"Bachstrasse 57",
    "sg:city":"Gnigl",
    "sg:classifiers":[
        {
            "category":"Government",
            "subcategory":"Jail",
            "type":"Public Place"
        }
    ],
    "sg:phone":"+43 662 6444240",
    "sg:postcode":"5023",
    "sg:province":"Salzburg",
    "sg:tags":[
        "planning",
        "designing"
    ],
    "sg:website":"is-online.at",
    "wof:name":"is Industrial Services GmbH",
    "wof:placetype":"venue"
},
  "geometry": {"coordinates":[13.0661363602,47.82188797],"type":"Point"}
}