{
  "type": "Feature",
  "properties": {
    "addr:full":"Lagerstr 2 Wolfsberg K\u00e4rnten 9400",
    "addr:housenumber":"2;kaernten",
    "addr:postcode":"9400",
    "addr:street":"Lagerstr",
    "iso:country":"AT",
    "sg:address":"Lagerstr 2",
    "sg:city":"Wolfsberg",
    "sg:orig_category":"Fa\u00c3\u0178bindereien",
    "sg:phone":"+43 4352 2042",
    "sg:postcode":"9400",
    "sg:province":"K\u00e4rnten",
    "wof:name":"Pauscha Klaus Fa\u00dfbinderei GesmbH",
    "wof:placetype":"venue"
},
  "geometry": {"coordinates":[14.8381156921,46.8289413452],"type":"Point"}
}