{
  "type": "Feature",
  "properties": {
    "iso:country":"AT",
    "sg:address":"Porzellang 8",
    "sg:city":"Wien",
    "sg:orig_category":"Werbeagenturen",
    "sg:phone":"+43 1 3190840",
    "sg:postcode":"1090",
    "sg:province":"Wien",
    "wof:name":"DIE VIVIENNA - the art of promotion",
    "wof:placetype":"venue"
},
  "geometry": {"coordinates":[16.3630237579,48.2193946838],"type":"Point"}
}