{
  "type": "Feature",
  "properties": {
    "addr:full":"Grabeng 28-30 Baden Nieder\u00f6sterreich 2500",
    "addr:postcode":"28-30;2500",
    "addr:street":"Niederoesterreich",
    "iso:country":"AT",
    "sg:address":"Grabeng 28-30",
    "sg:city":"Baden",
    "sg:orig_category":"Zeitungen U Zeitschriften",
    "sg:phone":"+43 4322 52444920",
    "sg:postcode":"2500",
    "sg:province":"Nieder\u00f6sterreich",
    "wof:name":"Badener Rundschau",
    "wof:placetype":"venue"
},
  "geometry": {"coordinates":[16.2364406586,48.0086708069],"type":"Point"}
}