{
  "type": "Feature",
  "properties": {
    "addr:full":"Hohe Warte 43 Wien Wien 1190",
    "addr:housenumber":"43",
    "addr:postcode":"1190",
    "addr:street":"Hohe Warte",
    "iso:country":"AT",
    "sg:address":"Hohe Warte 43",
    "sg:city":"Wien",
    "sg:orig_category":"Handelsagenturen",
    "sg:phone":"+43 1 3702288",
    "sg:postcode":"1190",
    "sg:province":"Wien",
    "wof:name":"Knapp Peter",
    "wof:placetype":"venue"
},
  "geometry": {"coordinates":[16.3547897339,48.2534599304],"type":"Point"}
}