{
  "type": "Feature",
  "properties": {
    "addr:full":"Industriestr 13 Zwettl Nieder\u00f6sterreich 3910",
    "addr:housenumber":"13",
    "addr:postcode":"3910",
    "addr:street":"Industriestr;Niederoesterreich",
    "iso:country":"AT",
    "sg:address":"Industriestr 13",
    "sg:city":"Zwettl",
    "sg:orig_category":"Autohandel",
    "sg:phone":"+43 2822 524400",
    "sg:postcode":"3910",
    "sg:province":"Nieder\u00f6sterreich",
    "sg:website":"opel-erhart.at",
    "wof:name":"OPEL Erhart",
    "wof:placetype":"venue"
},
  "geometry": {"coordinates":[15.190779686,48.6002082825],"type":"Point"}
}