{
  "type": "Feature",
  "properties": {
    "iso:country":"AT",
    "sg:address":"Nr 21",
    "sg:city":"W\u00f6rgl",
    "sg:orig_category":"Bibliotheken",
    "sg:phone":"+43 5332 23159",
    "sg:postcode":"6300",
    "sg:province":"Tirol",
    "wof:name":"B\u00fccherei d Gemeinde Angath",
    "wof:placetype":"venue"
},
  "geometry": {"coordinates":[12.0642328262,47.506893158],"type":"Point"}
}