{
  "type": "Feature",
  "properties": {
    "iso:country":"AT",
    "sg:address":"Hauptpl 32",
    "sg:city":"Tulln an der Donau",
    "sg:orig_category":"Geschenkartikel",
    "sg:phone":"+43 2272 65796",
    "sg:postcode":"3430",
    "sg:province":"Nieder\u00f6sterreich",
    "wof:name":"Smile On",
    "wof:placetype":"venue"
},
  "geometry": {"coordinates":[16.0519638062,48.3314743042],"type":"Point"}
}