{
  "type": "Feature",
  "properties": {
    "addr:full":"W\u00e4hringer Str 168 Wien Wien 1180",
    "addr:housenumber":"168",
    "addr:postcode":"1180",
    "addr:street":"Str",
    "iso:country":"AT",
    "sg:address":"W\u00e4hringer Str 168",
    "sg:city":"Wien",
    "sg:orig_category":"Tischlereien",
    "sg:phone":"+43 1 4781313",
    "sg:postcode":"1180",
    "sg:province":"Wien",
    "wof:name":"Wagner Friedrich",
    "wof:placetype":"venue"
},
  "geometry": {"coordinates":[16.3344173431,48.2285652161],"type":"Point"}
}