{
  "type": "Feature",
  "properties": {
    "addr:full":"Riefelg 2 Maria Enzersdorf Nieder\u00f6sterreich 2344",
    "addr:housenumber":"2",
    "addr:postcode":"2344",
    "addr:street":"Riefelg",
    "iso:country":"AT",
    "sg:address":"Riefelg 2",
    "sg:city":"Maria Enzersdorf",
    "sg:orig_category":"Politische Parteien",
    "sg:phone":"+43 2236 27251",
    "sg:postcode":"2344",
    "sg:province":"Nieder\u00f6sterreich",
    "wof:name":"Sozialdemokratische Partei \u00f6sterreichs",
    "wof:placetype":"venue"
},
  "geometry": {"coordinates":[16.2838249207,48.0979003906],"type":"Point"}
}