{
  "type": "Feature",
  "properties": {
    "iso:country":"AT",
    "sg:address":"Wiener Str 2",
    "sg:city":"Gaweinstal",
    "sg:orig_category":"Friseure U Frisiersalons",
    "sg:phone":"+43 2574 29030",
    "sg:postcode":"2191",
    "sg:province":"Nieder\u00f6sterreich",
    "wof:name":"Steiner Elfi Frisiersalon",
    "wof:placetype":"venue"
},
  "geometry": {"coordinates":[16.5889453888,48.4754638672],"type":"Point"}
}