{
  "type": "Feature",
  "properties": {
    "iso:country":"AT",
    "sg:address":"Burgring 1",
    "sg:city":"Wien",
    "sg:orig_category":"Antiquariate",
    "sg:phone":"+43 1 5877311",
    "sg:postcode":"1010",
    "sg:province":"Wien",
    "sg:website":"burgverlag.com",
    "wof:name":"Antiquariat Burgverlag BuchhandelsgesmbH",
    "wof:placetype":"venue"
},
  "geometry": {"coordinates":[16.3638896942,48.2035217285],"type":"Point"}
}