{
  "type": "Feature",
  "properties": {
    "addr:full":"Reut Nicolussi-Str 11/6 Innsbruck Tirol 6020",
    "addr:housenumber":"11 / 6",
    "addr:postcode":"6020",
    "addr:street":"Tirol",
    "iso:country":"AT",
    "sg:address":"Reut Nicolussi-Str 11/6",
    "sg:city":"Innsbruck",
    "sg:orig_category":"Fenster",
    "sg:phone":"+43 512 933552",
    "sg:postcode":"6020",
    "sg:province":"Tirol",
    "wof:name":"Glaser Johann",
    "wof:placetype":"venue"
},
  "geometry": {"coordinates":[11.4216403961,47.2707443237],"type":"Point"}
}