{
  "type": "Feature",
  "properties": {
    "addr:full":"General-Feurstein-Str 29 Innsbruck Tirol 6020",
    "addr:housenumber":"29",
    "addr:postcode":"6020",
    "addr:street":"General-Feurstein-Str;Tirol",
    "iso:country":"AT",
    "sg:address":"General-Feurstein-Str 29",
    "sg:city":"Innsbruck",
    "sg:orig_category":"Zahntechnische Laboratorien",
    "sg:phone":"+43 4351 2267575",
    "sg:postcode":"6020",
    "sg:province":"Tirol",
    "wof:name":"Rangger Dentaltechnik KEG",
    "wof:placetype":"venue"
},
  "geometry": {"coordinates":[11.4316387177,47.286529541],"type":"Point"}
}