{
  "type": "Feature",
  "properties": {
    "iso:country":"AT",
    "sg:address":"Plabutscher Str 79",
    "sg:city":"G\u00f6sting",
    "sg:orig_category":"Aluminiumbe- U -Verarbeitung",
    "sg:phone":"+43 4331 6679464",
    "sg:postcode":"8051",
    "sg:province":"Steiermark",
    "wof:name":"Alutech GmbH",
    "wof:placetype":"venue"
},
  "geometry": {"coordinates":[15.4026927948,47.0899200439],"type":"Point"}
}