{
  "type": "Feature",
  "properties": {
    "addr:full":"Wagmeisterstr 11 Amstetten Nieder\u00f6sterreich 3300",
    "addr:housenumber":"11",
    "addr:postcode":"3300",
    "addr:street":"Wagmeisterstr;Niederoesterreich",
    "iso:country":"AT",
    "sg:address":"Wagmeisterstr 11",
    "sg:city":"Amstetten",
    "sg:orig_category":"Tischlereien",
    "sg:phone":"+43 7472 63630",
    "sg:postcode":"3300",
    "sg:province":"Nieder\u00f6sterreich",
    "wof:name":"Hirsch Heribert",
    "wof:placetype":"venue"
},
  "geometry": {"coordinates":[14.8830518723,48.1238594055],"type":"Point"}
}