{
  "type": "Feature",
  "properties": {
    "addr:full":"Nr 26 Weikendorf Nieder\u00f6sterreich 2253",
    "addr:postcode":"2253",
    "addr:street":"Nr;Weikendorf",
    "iso:country":"AT",
    "sg:address":"Nr 26",
    "sg:city":"Weikendorf",
    "sg:orig_category":"Fenster",
    "sg:phone":"+43 2283 2504",
    "sg:postcode":"2253",
    "sg:province":"Nieder\u00f6sterreich",
    "wof:name":"Gruber Erich",
    "wof:placetype":"venue"
},
  "geometry": {"coordinates":[16.7665348053,48.3444709778],"type":"Point"}
}