{
  "type": "Feature",
  "properties": {
    "addr:full":"Lerchenfelder Str 128 Wien Wien 1080",
    "addr:housenumber":"128",
    "addr:postcode":"1080",
    "addr:street":"Lerchenfelder Str",
    "iso:country":"AT",
    "sg:address":"Lerchenfelder Str 128",
    "sg:city":"Wien",
    "sg:orig_category":"Geigen",
    "sg:phone":"+43 4314 068350",
    "sg:postcode":"1080",
    "sg:province":"Wien",
    "wof:name":"Geigenbau B\u00f6lli & Partner",
    "wof:placetype":"venue"
},
  "geometry": {"coordinates":[16.3420982361,48.2078971863],"type":"Point"}
}