{
  "type": "Feature",
  "properties": {
    "addr:full":"Bleichestr 1 Bludenz Vorarlberg 6700",
    "addr:housenumber":"1",
    "addr:postcode":"6700",
    "addr:street":"Bleichestr",
    "iso:country":"AT",
    "sg:address":"Bleichestr 1",
    "sg:city":"Bludenz",
    "sg:orig_category":"Textilwaren / Erzeugung U Gro\u00c3\u0178handel",
    "sg:phone":"+43 5552 6010",
    "sg:postcode":"6700",
    "sg:province":"Vorarlberg",
    "wof:name":"Getzner Textil AG",
    "wof:placetype":"venue"
},
  "geometry": {"coordinates":[9.8235645294,47.1516532898],"type":"Point"}
}