{
  "type": "Feature",
  "properties": {
    "addr:full":"Millenniumspark 3 Lustenau Vorarlberg 6890",
    "addr:housenumber":"3",
    "addr:postcode":"6890",
    "addr:street":"Millenniumspark",
    "iso:country":"AT",
    "sg:address":"Millenniumspark 3",
    "sg:city":"Lustenau",
    "sg:orig_category":"Antriebstechnik",
    "sg:phone":"+43 5577 8060",
    "sg:postcode":"6890",
    "sg:province":"Vorarlberg",
    "wof:name":"ZIMM Maschinenelemente GmbH & Co",
    "wof:placetype":"venue"
},
  "geometry": {"coordinates":[9.6708745956,47.4203262329],"type":"Point"}
}