{
  "type": "Feature",
  "properties": {
    "iso:country":"AT",
    "sg:address":"Rosenegg 57",
    "sg:city":"Fieberbrunn",
    "sg:orig_category":"Pensionen / Privatzimmer",
    "sg:phone":"+43 5354 56213",
    "sg:postcode":"6391",
    "sg:province":"Tirol",
    "wof:name":"H\u00f6rfarter Micheal KG",
    "wof:placetype":"venue"
},
  "geometry": {"coordinates":[12.5307331085,47.4876556396],"type":"Point"}
}