{
  "type": "Feature",
  "properties": {
    "iso:country":"AT",
    "sg:address":"Skiliftstr 281",
    "sg:city":"Saalbach",
    "sg:orig_category":"Pensionen / Privatzimmer",
    "sg:phone":"+43 6541 7470",
    "sg:postcode":"5753",
    "sg:province":"Salzburg",
    "wof:name":"Haus Wien",
    "wof:placetype":"venue"
},
  "geometry": {"coordinates":[12.6385402679,47.3914794922],"type":"Point"}
}