{
  "type": "Feature",
  "properties": {
    "addr:full":"Franz-Schubert-Str 8 Tulln an der Donau Nieder\u00f6sterreich 3430",
    "addr:housenumber":"8",
    "addr:postcode":"3430",
    "addr:street":"Franz-Schubert-Str",
    "iso:country":"AT",
    "sg:address":"Franz-Schubert-Str 8",
    "sg:city":"Tulln an der Donau",
    "sg:orig_category":"Massagen",
    "sg:phone":"+43 2272 66423",
    "sg:postcode":"3430",
    "sg:province":"Nieder\u00f6sterreich",
    "wof:name":"Karas Johannes",
    "wof:placetype":"venue"
},
  "geometry": {"coordinates":[16.0493526459,48.3291053772],"type":"Point"}
}