{
  "type": "Feature",
  "properties": {
    "iso:country":"AT",
    "sg:address":"Steinh\u00fcblstr 1",
    "sg:city":"Attnang-Puchheim",
    "sg:orig_category":"Anlagenbau U -Technik",
    "sg:phone":"+43 7674630330",
    "sg:postcode":"4800",
    "sg:province":"Ober\u00f6sterreich",
    "wof:name":"GIG Apparate- und Anlagenbau GmbH",
    "wof:placetype":"venue"
},
  "geometry": {"coordinates":[13.7204141617,48.0107002258],"type":"Point"}
}