{
  "type": "Feature",
  "properties": {
    "addr:full":"Pfarriweg 17 St. Anton am Arlberg Tirol 6580",
    "addr:housenumber":"17",
    "addr:postcode":"6580",
    "addr:street":"Pfarriweg;Tirol",
    "iso:country":"AT",
    "sg:address":"Pfarriweg 17",
    "sg:city":"St. Anton am Arlberg",
    "sg:orig_category":"Appartements / Ferienwohnungen",
    "sg:phone":"+43 5446 35570",
    "sg:postcode":"6580",
    "sg:province":"Tirol",
    "wof:name":"Landhaus Raffl",
    "wof:placetype":"venue"
},
  "geometry": {"coordinates":[10.2725353241,47.1377067566],"type":"Point"}
}