{
  "type": "Feature",
  "properties": {
    "addr:full":"Osterwitzg 12 Klagenfurt K\u00e4rnten 9020",
    "addr:housenumber":"12",
    "addr:postcode":"9020",
    "addr:street":"Osterwitzg;Kaernten",
    "iso:country":"AT",
    "sg:address":"Osterwitzg 12",
    "sg:city":"Klagenfurt",
    "sg:classifiers":[
        {
            "category":"Restaurant",
            "type":"Food & Drink"
        }
    ],
    "sg:phone":"+43 463 55339",
    "sg:postcode":"9020",
    "sg:province":"K\u00e4rnten",
    "wof:name":"Restaurant 7. Himmel",
    "wof:placetype":"venue"
},
  "geometry": {"coordinates":[14.3100166321,46.6257972717],"type":"Point"}
}