{
  "type": "Feature",
  "properties": {
    "addr:full":"Griesstr 12 Pinggau Steiermark 8243",
    "addr:housenumber":"12",
    "addr:postcode":"8243",
    "addr:street":"Griesstr",
    "iso:country":"AT",
    "sg:address":"Griesstr 12",
    "sg:city":"Pinggau",
    "sg:orig_category":"Tischlereien",
    "sg:phone":"+43 3339 22155",
    "sg:postcode":"8243",
    "sg:province":"Steiermark",
    "wof:name":"Oswald Josef",
    "wof:placetype":"venue"
},
  "geometry": {"coordinates":[16.0664710999,47.4400291443],"type":"Point"}
}