{
  "type": "Feature",
  "properties": {
    "iso:country":"AT",
    "sg:address":"Franz-Jonas-Pl",
    "sg:city":"Wien",
    "sg:orig_category":"Banken U Sparkassen",
    "sg:phone":"+43 4312 788709",
    "sg:postcode":"1210",
    "sg:province":"Wien",
    "wof:name":"\u00f6sterreichische Verkehrskreditbank AG - Western Union Floridsdorfer Bahnhof",
    "wof:placetype":"venue"
},
  "geometry": {"coordinates":[16.3990402222,48.2570152283],"type":"Point"}
}