{
  "type": "Feature",
  "properties": {
    "addr:full":"Kainachtalstr 83 Wildon Steiermark 8410",
    "addr:housenumber":"83",
    "addr:postcode":"8410",
    "addr:street":"Kainachtalstr;Steiermark",
    "iso:country":"AT",
    "sg:address":"Kainachtalstr 83",
    "sg:city":"Wildon",
    "sg:orig_category":"Fenster",
    "sg:phone":"+43 3182 35460",
    "sg:postcode":"8410",
    "sg:province":"Steiermark",
    "wof:name":"Maitz W Dr GesmbH",
    "wof:placetype":"venue"
},
  "geometry": {"coordinates":[15.4750499725,46.8929100037],"type":"Point"}
}