{
  "type": "Feature",
  "properties": {
    "addr:full":"Herrgottwiesg 192 Puntigam Steiermark 8055",
    "addr:housenumber":"192",
    "addr:postcode":"8055",
    "iso:country":"AT",
    "sg:address":"Herrgottwiesg 192",
    "sg:city":"Puntigam",
    "sg:orig_category":"Automatisierungstechnik",
    "sg:phone":"+43 316 263484",
    "sg:postcode":"8055",
    "sg:province":"Steiermark",
    "wof:name":"CEGELEC GmbH Zweigniederl Graz",
    "wof:placetype":"venue"
},
  "geometry": {"coordinates":[15.4314804077,47.0309486389],"type":"Point"}
}