{
  "type": "Feature",
  "properties": {
    "iso:country":"AT",
    "sg:address":"Arlbergstr 41",
    "sg:city":"St. Anton am Arlberg",
    "sg:classifiers":[
        {
            "category":"Travel",
            "subcategory":"Hotels & Motels",
            "type":"Entertainment"
        }
    ],
    "sg:phone":"+43 4354 4630108",
    "sg:postcode":"6580",
    "sg:province":"Tirol",
    "wof:name":"Lux Alpinae Hotel",
    "wof:placetype":"venue"
},
  "geometry": {"coordinates":[10.254784584,47.124382019],"type":"Point"}
}