{
  "type": "Feature",
  "properties": {
    "iso:country":"AT",
    "sg:address":"Reindlstr 6",
    "sg:city":"Linz",
    "sg:orig_category":"Installationsunternehmen",
    "sg:phone":"+43 732 734046",
    "sg:postcode":"4040",
    "sg:province":"Ober\u00f6sterreich",
    "wof:name":"Royer GmbH",
    "wof:placetype":"venue"
},
  "geometry": {"coordinates":[14.2826318741,48.3129920959],"type":"Point"}
}