{
  "type": "Feature",
  "properties": {
    "iso:country":"AT",
    "sg:address":"W\u00e4hringer Str 67",
    "sg:city":"Wien",
    "sg:orig_category":"Sonnenstudios",
    "sg:phone":"+43 1 4052080",
    "sg:postcode":"1090",
    "sg:province":"Wien",
    "wof:name":"Sun Company Br\u00e4unungsstudio",
    "wof:placetype":"venue"
},
  "geometry": {"coordinates":[16.3497924805,48.2242927551],"type":"Point"}
}