{
  "type": "Feature",
  "properties": {
    "addr:full":"Nr 226/EG Achenkirch Tirol 6215",
    "addr:postcode":"6215",
    "addr:street":"Nr 226 /;Achenkirch Tirol",
    "iso:country":"AT",
    "sg:address":"Nr 226/EG",
    "sg:city":"Achenkirch",
    "sg:orig_category":"Transportunternehmen",
    "sg:phone":"+43 5246 6482",
    "sg:postcode":"6215",
    "sg:province":"Tirol",
    "wof:name":"Egger Ludwig",
    "wof:placetype":"venue"
},
  "geometry": {"coordinates":[11.7065629959,47.5290184021],"type":"Point"}
}