{
  "type": "Feature",
  "properties": {
    "iso:country":"AT",
    "sg:address":"Eichetstr. 9-11",
    "sg:city":"Salzburg",
    "sg:classifiers":[
        {
            "category":"Sports & Exercise",
            "subcategory":"Playing Field",
            "type":"Entertainment"
        }
    ],
    "sg:phone":"+43 4366 28323570",
    "sg:postcode":"5020",
    "sg:province":"Salzburg",
    "sg:tags":[
        "game"
    ],
    "wof:name":"SALZBURGER BLUMENSCHL\u00d6SSL GES.MBH",
    "wof:placetype":"venue"
},
  "geometry": {"coordinates":[13.0158233643,47.7964630127],"type":"Point"}
}