{
  "type": "Feature",
  "properties": {
    "addr:full":"Sankt Margarethen im Lungau 171 St. Michael im Lungau Salzburg 5582",
    "addr:housenumber":"171",
    "addr:postcode":"5582",
    "addr:street":"Sankt Margarethen;Lungau;Salzburg",
    "iso:country":"AT",
    "sg:address":"Sankt Margarethen im Lungau 171",
    "sg:city":"St. Michael im Lungau",
    "sg:classifiers":[
        {
            "category":"Shopping",
            "subcategory":"Books",
            "type":"Retail Goods"
        }
    ],
    "sg:phone":"+43 6476 833",
    "sg:postcode":"5582",
    "sg:province":"Salzburg",
    "sg:website":"samsondruck.at",
    "wof:name":"Samson Druck GmbH",
    "wof:placetype":"venue"
},
  "geometry": {"coordinates":[13.6378936768,47.0988998413],"type":"Point"}
}