{
  "type": "Feature",
  "properties": {
    "addr:full":"Stahlstr 31 4031",
    "addr:housenumber":"31",
    "addr:postcode":"4031",
    "addr:street":"Stahlstr",
    "iso:country":"AT",
    "sg:address":"Stahlstr 31",
    "sg:orig_category":"Personalbereitstellung",
    "sg:phone":"+43 732 65852500",
    "sg:postcode":"4031",
    "wof:name":"voestalpine Personalservice GmbH",
    "wof:placetype":"venue"
},
  "geometry": {"coordinates":[14.3218727112,48.275226593],"type":"Point"}
}