{
  "type": "Feature",
  "properties": {
    "addr:full":"M\u00fchlbachg 21 Grieskirchen Ober\u00f6sterreich 4710",
    "addr:housenumber":"21",
    "addr:postcode":"4710",
    "addr:street":"Muehlbachg",
    "iso:country":"AT",
    "sg:address":"M\u00fchlbachg 21",
    "sg:city":"Grieskirchen",
    "sg:classifiers":[
        {
            "category":"Taxi",
            "type":"Transportation"
        }
    ],
    "sg:phone":"+43 4372 4861700",
    "sg:postcode":"4710",
    "sg:province":"Ober\u00f6sterreich",
    "sg:tags":[
        "personentransporte",
        "u"
    ],
    "sg:website":"taxi-reiterrobert.at",
    "wof:name":"Reiter Robert",
    "wof:placetype":"venue"
},
  "geometry": {"coordinates":[13.8257322311,48.2358856201],"type":"Point"}
}