{
  "type": "Feature",
  "properties": {
    "iso:country":"AT",
    "sg:address":"Marktpl 6",
    "sg:city":"Haag am Hausruck",
    "sg:orig_category":"Banken U Sparkassen",
    "sg:phone":"+43 4377 3233110",
    "sg:postcode":"4680",
    "sg:province":"Ober\u00f6sterreich",
    "wof:name":"Bankomat d Raiffeisenbank Region Hausruck regGenmbH",
    "wof:placetype":"venue"
},
  "geometry": {"coordinates":[13.6406202316,48.1851654053],"type":"Point"}
}