{
  "type": "Feature",
  "properties": {
    "addr:full":"Teiritzstr 3 Korneuburg Nieder\u00f6sterreich 2100",
    "addr:housenumber":"3",
    "addr:postcode":"2100",
    "addr:street":"Teiritzstr;Niederoesterreich",
    "iso:country":"AT",
    "sg:address":"Teiritzstr 3",
    "sg:city":"Korneuburg",
    "sg:orig_category":"Automatisierungstechnik",
    "sg:phone":"+43 4322 62608",
    "sg:postcode":"2100",
    "sg:province":"Nieder\u00f6sterreich",
    "sg:website":"rath-co.at",
    "wof:name":"Rath & Co GesmbH",
    "wof:placetype":"venue"
},
  "geometry": {"coordinates":[16.3408164978,48.3516731262],"type":"Point"}
}