{
  "type": "Feature",
  "properties": {
    "iso:country":"AT",
    "sg:address":"Nr 1",
    "sg:city":"Gloggnitz",
    "sg:orig_category":"Galerien",
    "sg:phone":"+43 2662 45633",
    "sg:postcode":"2640",
    "sg:province":"Nieder\u00f6sterreich",
    "wof:name":"Seidl Johannes",
    "wof:placetype":"venue"
},
  "geometry": {"coordinates":[15.9365577698,47.6758956909],"type":"Point"}
}