{
  "type": "Feature",
  "properties": {
    "addr:full":"Dammstr 16 Wimpassing im Schwarzatale Nieder\u00f6sterreich 2632",
    "addr:housenumber":"16",
    "addr:postcode":"2632",
    "addr:street":"Dammstr",
    "iso:country":"AT",
    "sg:address":"Dammstr 16",
    "sg:city":"Wimpassing im Schwarzatale",
    "sg:orig_category":"\u00c3\u201erzte / F Allgemeinmedizin",
    "sg:phone":"+43 4326 3038361",
    "sg:postcode":"2632",
    "sg:province":"Nieder\u00f6sterreich",
    "wof:name":"K\u00f6nig Christine Dr",
    "wof:placetype":"venue"
},
  "geometry": {"coordinates":[16.0219936371,47.7010650635],"type":"Point"}
}