{
  "type": "Feature",
  "properties": {
    "addr:full":"Bischofstrasse 3a Linz Ober\u00f6sterreich 4020",
    "addr:housenumber":"3a",
    "addr:postcode":"4020",
    "addr:street":"Bischofstrasse",
    "iso:country":"AT",
    "sg:address":"Bischofstrasse 3a",
    "sg:city":"Linz",
    "sg:classifiers":[
        {
            "category":"Shopping",
            "subcategory":"Clothing, Apparel, & Fashions",
            "type":"Retail Goods"
        }
    ],
    "sg:phone":"+43 732 797710",
    "sg:postcode":"4020",
    "sg:province":"Ober\u00f6sterreich",
    "sg:tags":[
        "fastener",
        "clothing"
    ],
    "wof:name":"Karina Leitner",
    "wof:placetype":"venue"
},
  "geometry": {"coordinates":[14.2891597748,48.3018455505],"type":"Point"}
}