{
  "type": "Feature",
  "properties": {
    "addr:full":"Nr 107 Kleinzell im M\u00fchlkreis Ober\u00f6sterreich 4115",
    "addr:postcode":"4115",
    "addr:street":"Nr 107 Kleinzell Im Muehlkreis Oberoesterreich",
    "iso:country":"AT",
    "sg:address":"Nr 107",
    "sg:city":"Kleinzell im M\u00fchlkreis",
    "sg:orig_category":"Offsetdruckereien",
    "sg:phone":"+43 4372 82566630",
    "sg:postcode":"4115",
    "sg:province":"Ober\u00f6sterreich",
    "wof:name":"Studio M - Mayrhofer & Partner GmbH",
    "wof:placetype":"venue"
},
  "geometry": {"coordinates":[13.9926204681,48.4571800232],"type":"Point"}
}