{
  "type": "Feature",
  "properties": {
    "addr:full":"Neufeldweg 146 Liebenau Steiermark 8041",
    "addr:housenumber":"146",
    "addr:postcode":"8041",
    "addr:street":"Neufeldweg",
    "iso:country":"AT",
    "sg:address":"Neufeldweg 146",
    "sg:city":"Liebenau",
    "sg:orig_category":"Waren Aller Art",
    "sg:phone":"+43 316 4753150",
    "sg:postcode":"8041",
    "sg:province":"Steiermark",
    "wof:name":"ACTIV Project Management GmbH",
    "wof:placetype":"venue"
},
  "geometry": {"coordinates":[15.4649610519,47.0443267822],"type":"Point"}
}