{
  "type": "Feature",
  "properties": {
    "addr:full":"Fritz-Stachel-Pl 3 Hartberg Steiermark 8230",
    "addr:housenumber":"3",
    "addr:postcode":"8230",
    "addr:street":"Fritz-Stachel-Pl",
    "iso:country":"AT",
    "sg:address":"Fritz-Stachel-Pl 3",
    "sg:city":"Hartberg",
    "sg:classifiers":[
        {
            "category":"Restaurant",
            "type":"Food & Drink"
        }
    ],
    "sg:phone":"+43 3332 64133",
    "sg:postcode":"8230",
    "sg:province":"Steiermark",
    "sg:tags":[
        "pizzeria"
    ],
    "wof:name":"Cafe Pizzeria Polo",
    "wof:placetype":"venue"
},
  "geometry": {"coordinates":[15.9737224579,47.2835197449],"type":"Point"}
}