{
  "type": "Feature",
  "properties": {
    "addr:full":"Wiener Strasse 47 Hornstein Burgenland 7053",
    "addr:housenumber":"47",
    "addr:postcode":"7053",
    "addr:street":"Wiener Strasse",
    "iso:country":"AT",
    "sg:address":"Wiener Strasse 47",
    "sg:city":"Hornstein",
    "sg:classifiers":[
        {
            "category":"Home & Garden",
            "subcategory":"Building Materials",
            "type":"Retail Goods"
        }
    ],
    "sg:phone":"+43 2689 2240",
    "sg:postcode":"7053",
    "sg:province":"Burgenland",
    "sg:tags":[
        "tile",
        "ceramic"
    ],
    "sg:website":"fliesen-plattig.at",
    "wof:name":"Fliesen Plattig Verlegungs- und Handelsges.m.b.H.",
    "wof:placetype":"venue"
},
  "geometry": {"coordinates":[16.4390220642,47.8855514526],"type":"Point"}
}