{
  "type": "Feature",
  "properties": {
    "addr:full":"Kaltenbachstr 6 Bad Ischl Ober\u00f6sterreich 4820",
    "addr:housenumber":"6",
    "addr:postcode":"4820",
    "addr:street":"Kaltenbachstr",
    "iso:country":"AT",
    "sg:address":"Kaltenbachstr 6",
    "sg:city":"Bad Ischl",
    "sg:orig_category":"Maler, Anstreicher U Lackierer",
    "sg:phone":"+43 4361 3223462",
    "sg:postcode":"4820",
    "sg:province":"Ober\u00f6sterreich",
    "wof:name":"Harmonie der Farben Eva Roth",
    "wof:placetype":"venue"
},
  "geometry": {"coordinates":[13.6178798676,47.7095222473],"type":"Point"}
}