{
  "type": "Feature",
  "properties": {
    "iso:country":"AT",
    "sg:address":"Meinhardstr 3",
    "sg:city":"Innsbruck",
    "sg:orig_category":"Unternehmensberatung",
    "sg:phone":"+43 512 583676",
    "sg:postcode":"6020",
    "sg:province":"Tirol",
    "wof:name":"Grubhofer Consulting Group - Christian Grubhofer",
    "wof:placetype":"venue"
},
  "geometry": {"coordinates":[11.3992490768,47.2662391663],"type":"Point"}
}