{
  "type": "Feature",
  "properties": {
    "iso:country":"AT",
    "sg:address":"Am Steinenbach 8",
    "sg:city":"Bregenz",
    "sg:orig_category":"Friseure U Frisiersalons",
    "sg:phone":"+43 5574 43167",
    "sg:postcode":"6900",
    "sg:province":"Vorarlberg",
    "wof:name":"Salon Magda Neurauter",
    "wof:placetype":"venue"
},
  "geometry": {"coordinates":[9.7512140274,47.5063095093],"type":"Point"}
}