{
  "type": "Feature",
  "properties": {
    "iso:country":"AT",
    "sg:address":"Nr.",
    "sg:city":"Weiden am See",
    "sg:orig_category":"Baumschulen",
    "sg:phone":"+43 2167 7218",
    "sg:postcode":"7121",
    "sg:province":"Burgenland",
    "wof:name":"Landesforstgarten Weiden",
    "wof:placetype":"venue"
},
  "geometry": {"coordinates":[16.8681316376,47.926235199],"type":"Point"}
}