{
  "type": "Feature",
  "properties": {
    "iso:country":"AT",
    "sg:address":"Nr 98",
    "sg:city":"Altenmarkt-Thenneberg",
    "sg:orig_category":"Erdarbeiten",
    "sg:phone":"+43 4326 732298",
    "sg:postcode":"2571",
    "sg:province":"Nieder\u00f6sterreich",
    "wof:name":"Kullar Herbert",
    "wof:placetype":"venue"
},
  "geometry": {"coordinates":[15.9934597015,48.0158500671],"type":"Point"}
}