{
  "type": "Feature",
  "properties": {
    "addr:full":"Wiener Str 19 Graz Steiermark 8020",
    "addr:housenumber":"19",
    "addr:postcode":"8020",
    "iso:country":"AT",
    "sg:address":"Wiener Str 19",
    "sg:city":"Graz",
    "sg:orig_category":"\u00c3\u201erzte / F Allgemeinmedizin",
    "sg:phone":"+43 316 714669",
    "sg:postcode":"8020",
    "sg:province":"Steiermark",
    "wof:name":"Kubin Bertho Dr",
    "wof:placetype":"venue"
},
  "geometry": {"coordinates":[15.4273900986,47.0785484314],"type":"Point"}
}