{
  "type": "Feature",
  "properties": {
    "addr:full":"Gabelsbergerstr 7-9 Salzburg Salzburg 5020",
    "addr:housenumber":"7-9",
    "addr:postcode":"5020",
    "addr:street":"Gabelsbergerstr;Salzburg",
    "iso:country":"AT",
    "sg:address":"Gabelsbergerstr 7-9",
    "sg:city":"Salzburg",
    "sg:orig_category":"Apotheken",
    "sg:phone":"+43 662 882413",
    "sg:postcode":"5020",
    "sg:province":"Salzburg",
    "wof:name":"Virgil Apotheke",
    "wof:placetype":"venue"
},
  "geometry": {"coordinates":[13.0473527908,47.8096847534],"type":"Point"}
}