{
  "type": "Feature",
  "properties": {
    "iso:country":"AT",
    "sg:address":"Operng 2",
    "sg:city":"Wien",
    "sg:classifiers":[
        {
            "category":"Retail",
            "subcategory":"Event Space",
            "type":"Services"
        }
    ],
    "sg:phone":"+43 4315 123469",
    "sg:postcode":"1010",
    "sg:province":"Wien",
    "sg:tags":[
        "hand-",
        "u",
        "fu\u00c3\u0178pflege"
    ],
    "wof:name":"Fu\u00df - Sachs Fu\u00dfpflege",
    "wof:placetype":"venue"
},
  "geometry": {"coordinates":[16.3683223724,48.2037849426],"type":"Point"}
}