{
  "type": "Feature",
  "properties": {
    "addr:full":"Neubau 9 Stockerau Nieder\u00f6sterreich 2000",
    "addr:housenumber":"9",
    "addr:postcode":"2000",
    "addr:street":"Neubau",
    "iso:country":"AT",
    "sg:address":"Neubau 9",
    "sg:city":"Stockerau",
    "sg:orig_category":"Non-Classified Establishments",
    "sg:phone":"+43 2266 62854",
    "sg:postcode":"2000",
    "sg:province":"Nieder\u00f6sterreich",
    "wof:name":"Evangelikal-freikirchliche Gemeinde",
    "wof:placetype":"venue"
},
  "geometry": {"coordinates":[16.2135810852,48.3836555481],"type":"Point"}
}