{
  "type": "Feature",
  "properties": {
    "addr:full":"Eindlgrundweg 30 Kindberg Steiermark 8650",
    "addr:housenumber":"30",
    "addr:postcode":"8650",
    "addr:street":"Eindlgrundweg",
    "iso:country":"AT",
    "sg:address":"Eindlgrundweg 30",
    "sg:city":"Kindberg",
    "sg:classifiers":[
        {
            "category":"Restaurant",
            "type":"Food & Drink"
        }
    ],
    "sg:phone":"+43 3865 44888",
    "sg:postcode":"8650",
    "sg:province":"Steiermark",
    "wof:name":"Volkshausst\u00fcberl",
    "wof:placetype":"venue"
},
  "geometry": {"coordinates":[15.440826416,47.4988937378],"type":"Point"}
}