{
  "type": "Feature",
  "properties": {
    "addr:full":"Langauerg 1 Wien Wien 1150",
    "addr:housenumber":"1",
    "addr:postcode":"1150",
    "addr:street":"Langauerg",
    "iso:country":"AT",
    "sg:address":"Langauerg 1",
    "sg:city":"Wien",
    "sg:orig_category":"Autovermietung",
    "sg:phone":"+43 4318 975528",
    "sg:postcode":"1150",
    "sg:province":"Wien",
    "wof:name":"DENZELDRIVE Carsharing GmbH - Wien-West",
    "wof:placetype":"venue"
},
  "geometry": {"coordinates":[16.3372440338,48.1959381104],"type":"Point"}
}