{
  "type": "Feature",
  "properties": {
    "iso:country":"AT",
    "sg:address":"Weidach 275",
    "sg:city":"Leutasch",
    "sg:orig_category":"Friseure U Frisiersalons",
    "sg:phone":"+43 5214 6490",
    "sg:postcode":"6105",
    "sg:province":"Tirol",
    "wof:name":"Friseursalon Beauty Hair im Alpenbad",
    "wof:placetype":"venue"
},
  "geometry": {"coordinates":[11.1522283554,47.3719978333],"type":"Point"}
}