{
  "type": "Feature",
  "properties": {
    "iso:country":"AT",
    "sg:address":"Annaberg 6",
    "sg:city":"Grieskirchen",
    "sg:orig_category":"Handelsagenturen",
    "sg:phone":"+43 7248 62975",
    "sg:postcode":"4710",
    "sg:province":"Ober\u00f6sterreich",
    "wof:name":"Walzer Agentur GmbH",
    "wof:placetype":"venue"
},
  "geometry": {"coordinates":[13.8442487717,48.2302780151],"type":"Point"}
}