{
  "type": "Feature",
  "properties": {
    "addr:full":"Johannesg 13 Bad V\u00f6slau Nieder\u00f6sterreich 2540",
    "addr:housenumber":"13",
    "addr:postcode":"2540",
    "addr:street":"Johannesg",
    "iso:country":"AT",
    "sg:address":"Johannesg 13",
    "sg:city":"Bad V\u00f6slau",
    "sg:orig_category":"Filmproduktionen",
    "sg:phone":"+43 2252 251287",
    "sg:postcode":"2540",
    "sg:province":"Nieder\u00f6sterreich",
    "wof:name":"TV Rental Professional TV Equipment GesmbH",
    "wof:placetype":"venue"
},
  "geometry": {"coordinates":[16.2141895294,47.9654006958],"type":"Point"}
}