{
  "type": "Feature",
  "properties": {
    "addr:full":"Frau-Hitt-Str 3 Innsbruck Tirol 6020",
    "addr:housenumber":"3",
    "addr:postcode":"6020",
    "addr:street":"Frau-Hitt-Str;Tirol",
    "iso:country":"AT",
    "sg:address":"Frau-Hitt-Str 3",
    "sg:city":"Innsbruck",
    "sg:orig_category":"Psychologen",
    "sg:phone":"+43 512 286487",
    "sg:postcode":"6020",
    "sg:province":"Tirol",
    "wof:name":"Sebanz Ingrid Dr",
    "wof:placetype":"venue"
},
  "geometry": {"coordinates":[11.3846502304,47.269985199],"type":"Point"}
}