{
  "type": "Feature",
  "properties": {
    "addr:full":"Seenstr 27 Reifnitz K\u00e4rnten 9081",
    "addr:housenumber":"27",
    "addr:postcode":"9081",
    "addr:street":"Seenstr;Kaernten",
    "iso:country":"AT",
    "sg:address":"Seenstr 27",
    "sg:city":"Reifnitz",
    "sg:classifiers":[
        {
            "category":"Travel",
            "subcategory":"Hotels & Motels",
            "type":"Entertainment"
        }
    ],
    "sg:phone":"+43 4273 22560",
    "sg:postcode":"9081",
    "sg:province":"K\u00e4rnten",
    "wof:name":"Hotel-Restaurant Siegfried",
    "wof:placetype":"venue"
},
  "geometry": {"coordinates":[14.1786909103,46.604927063],"type":"Point"}
}