{
  "type": "Feature",
  "properties": {
    "addr:full":"Brestelg 6 Wien Wien 1160",
    "addr:housenumber":"6",
    "addr:postcode":"1160",
    "addr:street":"Brestelg",
    "iso:country":"AT",
    "sg:address":"Brestelg 6",
    "sg:city":"Wien",
    "sg:orig_category":"Abbruchunternehmen",
    "sg:phone":"+43 664 1036451",
    "sg:postcode":"1160",
    "sg:province":"Wien",
    "wof:name":"Prajo und Co OEG",
    "wof:placetype":"venue"
},
  "geometry": {"coordinates":[16.3307819366,48.2128105164],"type":"Point"}
}