{
  "type": "Feature",
  "properties": {
    "iso:country":"AT",
    "sg:address":"Leopoldauer Str 19",
    "sg:city":"Wien",
    "sg:orig_category":"Sonnenstudios",
    "sg:phone":"+43 1 2724440",
    "sg:postcode":"1210",
    "sg:province":"Wien",
    "wof:name":"Sun Factory",
    "wof:placetype":"venue"
},
  "geometry": {"coordinates":[16.4065990448,48.2582588196],"type":"Point"}
}