{
  "type": "Feature",
  "properties": {
    "addr:full":"Bahnhofstr 5 Velden am W\u00f6rther See K\u00e4rnten 9220",
    "addr:housenumber":"5",
    "addr:postcode":"9220",
    "addr:street":"Bahnhofstr;Kaernten",
    "iso:country":"AT",
    "sg:address":"Bahnhofstr 5",
    "sg:city":"Velden am W\u00f6rther See",
    "sg:classifiers":[
        {
            "category":"Restaurant",
            "type":"Food & Drink"
        }
    ],
    "sg:phone":"+43 4342 7451266",
    "sg:postcode":"9220",
    "sg:province":"K\u00e4rnten",
    "wof:name":"Cafe Restaurant Dominici",
    "wof:placetype":"venue"
},
  "geometry": {"coordinates":[14.045627594,46.6171264648],"type":"Point"}
}