{
  "type": "Feature",
  "properties": {
    "addr:full":"Maierh\u00f6fenstrasse 14 Krumbach Nieder\u00f6sterreich 2851",
    "addr:housenumber":"14",
    "addr:postcode":"2851",
    "addr:street":"Maierhoefenstrasse",
    "iso:country":"AT",
    "sg:address":"Maierh\u00f6fenstrasse 14",
    "sg:city":"Krumbach",
    "sg:classifiers":[
        {
            "category":"Professional",
            "subcategory":"Detective & Security Services",
            "type":"Services"
        }
    ],
    "sg:phone":"+43 2647 42873",
    "sg:postcode":"2851",
    "sg:province":"Nieder\u00f6sterreich",
    "sg:tags":[
        "access",
        "control",
        "ac",
        "system"
    ],
    "wof:name":"Komm Tech Ing. Johann Schwarz",
    "wof:placetype":"venue"
},
  "geometry": {"coordinates":[16.1943454742,47.5257606506],"type":"Point"}
}