{
  "type": "Feature",
  "properties": {
    "addr:full":"Semperitstr 8 Traiskirchen Nieder\u00f6sterreich 2514",
    "addr:housenumber":"8",
    "addr:postcode":"2514",
    "addr:street":"Semperitstr;Niederoesterreich",
    "iso:country":"AT",
    "sg:address":"Semperitstr 8",
    "sg:city":"Traiskirchen",
    "sg:orig_category":"Installationsunternehmen",
    "sg:phone":"+43 2252 53725",
    "sg:postcode":"2514",
    "sg:province":"Nieder\u00f6sterreich",
    "wof:name":"Kopsa Gerald Ing GmbH",
    "wof:placetype":"venue"
},
  "geometry": {"coordinates":[16.2901611328,48.0137252808],"type":"Point"}
}