{
  "type": "Feature",
  "properties": {
    "iso:country":"AT",
    "sg:address":"Nr 363",
    "sg:city":"Markgrafneusiedl",
    "sg:classifiers":[
        {
            "category":"Home & Garden",
            "subcategory":"Building Materials",
            "type":"Retail Goods"
        }
    ],
    "sg:phone":"+43 2248 2134",
    "sg:postcode":"2282",
    "sg:province":"Nieder\u00f6sterreich",
    "sg:tags":[
        "baustoffe",
        "-material",
        "u"
    ],
    "wof:name":"AMB Asphalt-Mischanlagen Betriebs GesmbH & Co KG",
    "wof:placetype":"venue"
},
  "geometry": {"coordinates":[16.6323261261,48.2674369812],"type":"Point"}
}