{
  "type": "Feature",
  "properties": {
    "iso:country":"AT",
    "sg:address":"Bahnstr 3",
    "sg:city":"Hohenau an der March",
    "sg:orig_category":"Spielwaren U Spiele",
    "sg:phone":"+43 4325 3531101",
    "sg:postcode":"2273",
    "sg:province":"Nieder\u00f6sterreich",
    "wof:name":"B\u00f6hm Horst",
    "wof:placetype":"venue"
},
  "geometry": {"coordinates":[16.9045505524,48.6054725647],"type":"Point"}
}