{
  "type": "Feature",
  "properties": {
    "addr:full":"Wolfholzg 28 Brunn am Gebirge Nieder\u00f6sterreich 2345",
    "addr:housenumber":"28",
    "addr:postcode":"2345",
    "addr:street":"Wolfholzg",
    "iso:country":"AT",
    "sg:address":"Wolfholzg 28",
    "sg:city":"Brunn am Gebirge",
    "sg:orig_category":"Medizintechnik",
    "sg:phone":"+43 2236 379600",
    "sg:postcode":"2345",
    "sg:province":"Nieder\u00f6sterreich",
    "wof:name":"INO Therapeutics GmbH",
    "wof:placetype":"venue"
},
  "geometry": {"coordinates":[16.2946739197,48.1187057495],"type":"Point"}
}