{
  "type": "Feature",
  "properties": {
    "iso:country":"AT",
    "sg:address":"Stadlweg 40",
    "sg:city":"Innsbruck",
    "sg:orig_category":"Eisenwaren",
    "sg:phone":"+43 512 345164",
    "sg:postcode":"6020",
    "sg:province":"Tirol",
    "wof:name":"Ortner & Stanger",
    "wof:placetype":"venue"
},
  "geometry": {"coordinates":[11.4309425354,47.2669487],"type":"Point"}
}