{
  "type": "Feature",
  "properties": {
    "iso:country":"AT",
    "sg:address":"Hauptstr 71",
    "sg:city":"Zams",
    "sg:orig_category":"Fleischhauereien",
    "sg:phone":"+43 4354 4262619",
    "sg:postcode":"6511",
    "sg:province":"Tirol",
    "wof:name":"Schmid Alois",
    "wof:placetype":"venue"
},
  "geometry": {"coordinates":[10.5871667862,47.1599197388],"type":"Point"}
}