{
  "type": "Feature",
  "properties": {
    "iso:country":"AT",
    "sg:address":"Kopfstetten 58",
    "sg:city":"Eckartsau",
    "sg:classifiers":[
        {
            "category":"Manufacturing",
            "subcategory":"Wood Products",
            "type":"Manufacturing & Wholesale Goods"
        }
    ],
    "sg:phone":"+43 2214 70010",
    "sg:postcode":"2305",
    "sg:province":"Nieder\u00f6sterreich",
    "sg:tags":[
        "gate",
        "made",
        "door"
    ],
    "sg:website":"proeglhoef.at",
    "wof:name":"Alfred Pr\u00f6glh\u00f6f GmbH",
    "wof:placetype":"venue"
},
  "geometry": {"coordinates":[16.8109073639,48.1695823669],"type":"Point"}
}