{
  "type": "Feature",
  "properties": {
    "addr:full":"Rasmusseng 2 Wien Wien 1210",
    "addr:housenumber":"2",
    "addr:postcode":"1210",
    "addr:street":"Rasmusseng",
    "iso:country":"AT",
    "sg:address":"Rasmusseng 2",
    "sg:city":"Wien",
    "sg:orig_category":"Grafische Bedarfsartikel",
    "sg:phone":"+43 1 47970140",
    "sg:postcode":"1210",
    "sg:province":"Wien",
    "wof:name":"Japico Feinpapier VertriebsgesmbH",
    "wof:placetype":"venue"
},
  "geometry": {"coordinates":[16.3878059387,48.2750740051],"type":"Point"}
}