{
  "type": "Feature",
  "properties": {
    "iso:country":"AT",
    "sg:address":"Hauptschulpl 2",
    "sg:city":"Leobersdorf",
    "sg:orig_category":"Freizeit- U Sportbekleidung",
    "sg:phone":"+43 664 1833445",
    "sg:postcode":"2544",
    "sg:province":"Nieder\u00f6sterreich",
    "wof:name":"Happy Jeans",
    "wof:placetype":"venue"
},
  "geometry": {"coordinates":[16.2162818909,47.9301567078],"type":"Point"}
}