{
  "type": "Feature",
  "properties": {
    "addr:full":"Grazer Str 62 Kapfenberg Steiermark 8605",
    "addr:postcode":"8605",
    "addr:street":"Str 62",
    "iso:country":"AT",
    "sg:address":"Grazer Str 62",
    "sg:city":"Kapfenberg",
    "sg:orig_category":"Fleischhauereien",
    "sg:phone":"+43 3862 222350",
    "sg:postcode":"8605",
    "sg:province":"Steiermark",
    "wof:name":"Harger Hans Sohn & Co GesmbH",
    "wof:placetype":"venue"
},
  "geometry": {"coordinates":[15.2817077637,47.4372253418],"type":"Point"}
}