{
  "type": "Feature",
  "properties": {
    "addr:full":"Nr 21 Kollerschlag Ober\u00f6sterreich 4154",
    "addr:postcode":"4154",
    "addr:street":"Nr 21",
    "iso:country":"AT",
    "sg:address":"Nr 21",
    "sg:city":"Kollerschlag",
    "sg:orig_category":"Volksschulen",
    "sg:phone":"+43 4372 878197",
    "sg:postcode":"4154",
    "sg:province":"Ober\u00f6sterreich",
    "wof:name":"Volksschule",
    "wof:placetype":"venue"
},
  "geometry": {"coordinates":[13.8414564133,48.6052284241],"type":"Point"}
}