{
  "type": "Feature",
  "properties": {
    "iso:country":"AT",
    "sg:address":"Ort am Mondsee 30",
    "sg:city":"Unterach am Attersee",
    "sg:orig_category":"Pensionen / Privatzimmer",
    "sg:phone":"+43 76658457",
    "sg:postcode":"4866",
    "sg:province":"Ober\u00f6sterreich",
    "wof:name":"Pension Seeruhe",
    "wof:placetype":"venue"
},
  "geometry": {"coordinates":[13.4285640717,47.8061065674],"type":"Point"}
}