{
  "type": "Feature",
  "properties": {
    "iso:country":"AT",
    "sg:address":"Nr 113",
    "sg:city":"Eisgarn",
    "sg:orig_category":"Autoreparatur",
    "sg:phone":"+43 2863 265",
    "sg:postcode":"3862",
    "sg:province":"Nieder\u00f6sterreich",
    "wof:name":"Schandl Franz",
    "wof:placetype":"venue"
},
  "geometry": {"coordinates":[15.0980672836,48.9167289734],"type":"Point"}
}