{
  "type": "Feature",
  "properties": {
    "addr:full":"Stafflach 40 Steinach am Brenner Tirol 6150",
    "addr:housenumber":"40",
    "addr:postcode":"6150",
    "addr:street":"Stafflach;Tirol",
    "iso:country":"AT",
    "sg:address":"Stafflach 40",
    "sg:city":"Steinach am Brenner",
    "sg:classifiers":[
        {
            "category":"Utilities",
            "subcategory":"Recycling",
            "type":"Services"
        }
    ],
    "sg:phone":"+43 4352 795225",
    "sg:postcode":"6150",
    "sg:province":"Tirol",
    "wof:name":"Huter Recycling u Transport GmbH",
    "wof:placetype":"venue"
},
  "geometry": {"coordinates":[11.4865369797,47.0662155151],"type":"Point"}
}