{
  "type": "Feature",
  "properties": {
    "addr:full":"Nr 332 Eibiswald Steiermark 8552",
    "addr:postcode":"8552",
    "addr:street":"Nr 332",
    "iso:country":"AT",
    "sg:address":"Nr 332",
    "sg:city":"Eibiswald",
    "sg:orig_category":"Genossenschaften",
    "sg:phone":"+43 3466 42417",
    "sg:postcode":"8552",
    "sg:province":"Steiermark",
    "wof:name":"Steirische Beerenobstgenossenschaft regGenmbH",
    "wof:placetype":"venue"
},
  "geometry": {"coordinates":[15.2274599075,46.6824150085],"type":"Point"}
}