{
  "type": "Feature",
  "properties": {
    "addr:full":"Thaliastr 35 Wien Wien 1160",
    "addr:housenumber":"35",
    "addr:postcode":"1160",
    "addr:street":"Thaliastr",
    "iso:country":"AT",
    "sg:address":"Thaliastr 35",
    "sg:city":"Wien",
    "sg:orig_category":"Boutiquen",
    "sg:phone":"+43 4314 958974",
    "sg:postcode":"1160",
    "sg:province":"Wien",
    "wof:name":"MILANO Pernar KEG",
    "wof:placetype":"venue"
},
  "geometry": {"coordinates":[16.3315067291,48.2095375061],"type":"Point"}
}