{
  "type": "Feature",
  "properties": {
    "iso:country":"AT",
    "sg:address":"Ascheter Str 29",
    "sg:city":"Wels",
    "sg:orig_category":"Hydrokulturen",
    "sg:phone":"+43 664 3000581",
    "sg:postcode":"4600",
    "sg:province":"Ober\u00f6sterreich",
    "wof:name":"Pesl Reinhard",
    "wof:placetype":"venue"
},
  "geometry": {"coordinates":[14.0169782639,48.1463851929],"type":"Point"}
}