{
  "type": "Feature",
  "properties": {
    "addr:full":"Lamingfeldsdlg D4 Bruck an der Mur Steiermark 8600",
    "addr:postcode":"8600",
    "iso:country":"AT",
    "sg:address":"Lamingfeldsdlg D4",
    "sg:city":"Bruck an der Mur",
    "sg:classifiers":[
        {
            "category":"Internet Cafe",
            "subcategory":"None",
            "type":"Food & Drink"
        }
    ],
    "sg:phone":"+43 676 6238844",
    "sg:postcode":"8600",
    "sg:province":"Steiermark",
    "wof:name":"mytimewill.com Mag Robert Steigberger",
    "wof:placetype":"venue"
},
  "geometry": {"coordinates":[15.2685451508,47.4100990295],"type":"Point"}
}