{
  "type": "Feature",
  "properties": {
    "iso:country":"AT",
    "sg:address":"Bundesstr 3",
    "sg:city":"N\u00fcziders",
    "sg:orig_category":"Tankstellen",
    "sg:phone":"+43 5552 63211",
    "sg:postcode":"6714",
    "sg:province":"Vorarlberg",
    "wof:name":"Shell Austria GmbH",
    "wof:placetype":"venue"
},
  "geometry": {"coordinates":[9.7949848175,47.1653327942],"type":"Point"}
}