{
  "type": "Feature",
  "properties": {
    "addr:full":"Kaiser-Josef-Pl 8 Wels Ober\u00f6sterreich 4600",
    "addr:housenumber":"8",
    "addr:postcode":"4600",
    "addr:street":"Kaiser-Josef-Pl;Oberoesterreich",
    "iso:country":"AT",
    "sg:address":"Kaiser-Josef-Pl 8",
    "sg:city":"Wels",
    "sg:orig_category":"Porzellan U Porzellanwaren",
    "sg:phone":"+43 4372 42543980",
    "sg:postcode":"4600",
    "sg:province":"Ober\u00f6sterreich",
    "wof:name":"Willinger",
    "wof:placetype":"venue"
},
  "geometry": {"coordinates":[14.0246763229,48.1599464417],"type":"Point"}
}