{
  "type": "Feature",
  "properties": {
    "addr:full":"Breitenfelder G 11/8 Wien Wien 1080",
    "addr:housenumber":"11 / 8",
    "addr:postcode":"1080",
    "addr:street":"Breitenfelder G",
    "iso:country":"AT",
    "sg:address":"Breitenfelder G 11/8",
    "sg:city":"Wien",
    "sg:orig_category":"Immobilienmakler",
    "sg:phone":"+43 1 40745010",
    "sg:postcode":"1080",
    "sg:province":"Wien",
    "wof:name":"Top Real Liegenschaftsverwertung GmbH",
    "wof:placetype":"venue"
},
  "geometry": {"coordinates":[16.3431110382,48.2140159607],"type":"Point"}
}