{
  "type": "Feature",
  "properties": {
    "iso:country":"AT",
    "sg:address":"Postg 1",
    "sg:city":"Neunkirchen",
    "sg:orig_category":"Politische Parteien",
    "sg:phone":"+43 2635 65589",
    "sg:postcode":"2620",
    "sg:province":"Nieder\u00f6sterreich",
    "wof:name":"Freiheitliche Partei \u00f6sterreichs",
    "wof:placetype":"venue"
},
  "geometry": {"coordinates":[16.0980548859,47.7119560242],"type":"Point"}
}