{
  "type": "Feature",
  "properties": {
    "addr:full":"Pfarrg 22 Oberwaltersdorf Nieder\u00f6sterreich 2522",
    "addr:housenumber":"22",
    "addr:postcode":"2522",
    "addr:street":"Pfarrg",
    "iso:country":"AT",
    "sg:address":"Pfarrg 22",
    "sg:city":"Oberwaltersdorf",
    "sg:orig_category":"Non-Classified Establishments",
    "sg:phone":"+43 2253 6506",
    "sg:postcode":"2522",
    "sg:province":"Nieder\u00f6sterreich",
    "wof:name":"Pfarramt",
    "wof:placetype":"venue"
},
  "geometry": {"coordinates":[16.3201808929,47.9745254517],"type":"Point"}
}