{
  "type": "Feature",
  "properties": {
    "addr:full":"Speisinger Str 260 Wien Wien 1230",
    "addr:housenumber":"260",
    "addr:postcode":"1230",
    "iso:country":"AT",
    "sg:address":"Speisinger Str 260",
    "sg:city":"Wien",
    "sg:orig_category":"Transportunternehmen",
    "sg:phone":"+43 4319 904038",
    "sg:postcode":"1230",
    "sg:province":"Wien",
    "wof:name":"CISAR Martin Transporte KEG",
    "wof:placetype":"venue"
},
  "geometry": {"coordinates":[16.2689285278,48.1512451172],"type":"Point"}
}