{
  "type": "Feature",
  "properties": {
    "addr:full":"Marienpl 1 Mistelbach Nieder\u00f6sterreich 2130",
    "addr:housenumber":"1",
    "addr:postcode":"2130",
    "addr:street":"Marienpl;Niederoesterreich",
    "iso:country":"AT",
    "sg:address":"Marienpl 1",
    "sg:city":"Mistelbach",
    "sg:orig_category":"Beratungsstellen",
    "sg:phone":"+43 4325 722118",
    "sg:postcode":"2130",
    "sg:province":"Nieder\u00f6sterreich",
    "wof:name":"Sucht- u Lebensfragen Beratungsstelle",
    "wof:placetype":"venue"
},
  "geometry": {"coordinates":[16.5753707886,48.5682792664],"type":"Point"}
}