{
  "type": "Feature",
  "properties": {
    "iso:country":"AT",
    "sg:address":"Nr 30",
    "sg:city":"Oberrohrbach",
    "sg:orig_category":"Weine / Gro\u00c3\u0178handel",
    "sg:phone":"+43 4322 66639260",
    "sg:postcode":"2105",
    "sg:province":"Nieder\u00f6sterreich",
    "wof:name":"Grams & Co KG",
    "wof:placetype":"venue"
},
  "geometry": {"coordinates":[16.2794837952,48.3863220215],"type":"Point"}
}