{
  "type": "Feature",
  "properties": {
    "addr:full":"Rohrbacher Str 7 Helfenberg Ober\u00f6sterreich 4184",
    "addr:housenumber":"7",
    "addr:postcode":"4184",
    "addr:street":"Str",
    "iso:country":"AT",
    "sg:address":"Rohrbacher Str 7",
    "sg:city":"Helfenberg",
    "sg:orig_category":"Textilwaren / Erzeugung U Gro\u00c3\u0178handel",
    "sg:phone":"+43 7216 6206",
    "sg:postcode":"4184",
    "sg:province":"Ober\u00f6sterreich",
    "wof:name":"Helfenberger Frottier & K\u00fcchenw\u00e4sche GmbH",
    "wof:placetype":"venue"
},
  "geometry": {"coordinates":[14.1407299042,48.5421676636],"type":"Point"}
}