{
  "type": "Feature",
  "properties": {
    "addr:full":"Winzerweg 3 Feldkirch Vorarlberg 6800",
    "addr:housenumber":"3",
    "addr:postcode":"6800",
    "addr:street":"Winzerweg",
    "iso:country":"AT",
    "sg:address":"Winzerweg 3",
    "sg:city":"Feldkirch",
    "sg:orig_category":"Unternehmensberatung",
    "sg:phone":"+43 4355 2231387",
    "sg:postcode":"6800",
    "sg:province":"Vorarlberg",
    "sg:website":"unternehmenskultur.at",
    "wof:name":"Gruber Kommunikationsberatung Mag Wolfgang Gruber",
    "wof:placetype":"venue"
},
  "geometry": {"coordinates":[9.5996952057,47.2426643372],"type":"Point"}
}