{
  "type": "Feature",
  "properties": {
    "addr:full":"Langenlebarn Nieder\u00f6sterreich 3425",
    "addr:postcode":"3425",
    "iso:country":"AT",
    "sg:city":"Langenlebarn",
    "sg:orig_category":"Non-Classified Establishments",
    "sg:phone":"+43 2272 6960",
    "sg:postcode":"3425",
    "sg:province":"Nieder\u00f6sterreich",
    "wof:name":"Fliegerhorst Brumowski",
    "wof:placetype":"venue"
},
  "geometry": {"coordinates":[16.1178627014,48.3325881958],"type":"Point"}
}