{
  "type": "Feature",
  "properties": {
    "addr:full":"Untere Schmiedg 13 Deutschlandsberg Steiermark 8530",
    "addr:housenumber":"13",
    "addr:postcode":"8530",
    "addr:street":"Untere Schmiedg",
    "iso:country":"AT",
    "sg:address":"Untere Schmiedg 13",
    "sg:city":"Deutschlandsberg",
    "sg:orig_category":"Transportunternehmen",
    "sg:phone":"+43 4334 6230383",
    "sg:postcode":"8530",
    "sg:province":"Steiermark",
    "wof:name":"Kl\u00f6sch Anton Handel- u Transport KEG",
    "wof:placetype":"venue"
},
  "geometry": {"coordinates":[15.2168626785,46.8145523071],"type":"Point"}
}