{
  "type": "Feature",
  "properties": {
    "addr:full":"Alxingergasse 55 Wien Wien 1100",
    "addr:housenumber":"55",
    "addr:postcode":"1100",
    "addr:street":"Alxingergasse",
    "iso:country":"AT",
    "sg:address":"Alxingergasse 55",
    "sg:city":"Wien",
    "sg:classifiers":[
        {
            "category":"Home & Garden",
            "subcategory":"Building Materials",
            "type":"Retail Goods"
        }
    ],
    "sg:phone":"+43 1 6049695",
    "sg:postcode":"1100",
    "sg:province":"Wien",
    "sg:tags":[
        "installation",
        "electric"
    ],
    "wof:name":"Elektro Ponbauer Ges.m.b.H.",
    "wof:placetype":"venue"
},
  "geometry": {"coordinates":[16.3678531647,48.1734352112],"type":"Point"}
}