{
  "type": "Feature",
  "properties": {
    "iso:country":"AT",
    "sg:address":"St. Oswalder Str 5",
    "sg:city":"Bad Kleinkirchheim",
    "sg:orig_category":"Appartements / Ferienwohnungen",
    "sg:phone":"+43 4240 3510",
    "sg:postcode":"9546",
    "sg:province":"K\u00e4rnten",
    "wof:name":"Haus Katholnig",
    "wof:placetype":"venue"
},
  "geometry": {"coordinates":[13.7923994064,46.8139839172],"type":"Point"}
}