{
  "type": "Feature",
  "properties": {
    "addr:full":"Almhausstr 9b Ebensee Ober\u00f6sterreich 4802",
    "addr:housenumber":"9b",
    "addr:postcode":"4802",
    "addr:street":"Almhausstr",
    "iso:country":"AT",
    "sg:address":"Almhausstr 9b",
    "sg:city":"Ebensee",
    "sg:orig_category":"Fische U Fischwaren / Erzeugung U Gro\u00c3\u0178handel",
    "sg:phone":"+43 6133 8587",
    "sg:postcode":"4802",
    "sg:province":"Ober\u00f6sterreich",
    "wof:name":"Walter Franz - Fischgro\u00dfhandel",
    "wof:placetype":"venue"
},
  "geometry": {"coordinates":[13.774058342,47.8055801392],"type":"Point"}
}