{
  "type": "Feature",
  "properties": {
    "addr:full":"Wimmer Str 10 Seekirchen am Wallersee Salzburg 5201",
    "addr:postcode":"5201",
    "addr:street":"Str 10;Salzburg",
    "iso:country":"AT",
    "sg:address":"Wimmer Str 10",
    "sg:city":"Seekirchen am Wallersee",
    "sg:orig_category":"Gastronomie- U Hotelbedarf",
    "sg:phone":"+43 4362 12301000",
    "sg:postcode":"5201",
    "sg:province":"Salzburg",
    "wof:name":"Roider Richard",
    "wof:placetype":"venue"
},
  "geometry": {"coordinates":[13.1076021194,47.8983192444],"type":"Point"}
}