{
  "type": "Feature",
  "properties": {
    "addr:full":"Magtstrasse 4a Innsbruck Tirol 6020",
    "addr:housenumber":"4a",
    "addr:postcode":"6020",
    "addr:street":"Magtstrasse;Tirol",
    "iso:country":"AT",
    "sg:address":"Magtstrasse 4a",
    "sg:city":"Innsbruck",
    "sg:classifiers":[
        {
            "category":"Banks & Credit Unions",
            "subcategory":"Investment Brokerage",
            "type":"Services"
        }
    ],
    "sg:phone":"+43 512 225600",
    "sg:postcode":"6020",
    "sg:province":"Tirol",
    "sg:tags":[
        "size",
        "cut",
        "chipboard"
    ],
    "sg:website":"schuster-holz.at",
    "wof:name":"Schuster Holzgro\u00dfhandlung Holzexport Ges.m.b.H. & CO KG",
    "wof:placetype":"venue"
},
  "geometry": {"coordinates":[11.3948793411,47.2757110596],"type":"Point"}
}