{
  "type": "Feature",
  "properties": {
    "addr:full":"Beethovenstr. 4 Wieselburg an der Erlauf Nieder\u00f6sterreich 3250",
    "addr:housenumber":"4",
    "addr:postcode":"3250",
    "addr:street":"Beethovenstr.",
    "iso:country":"AT",
    "sg:address":"Beethovenstr. 4",
    "sg:city":"Wieselburg an der Erlauf",
    "sg:classifiers":[
        {
            "category":"Wholesale",
            "subcategory":"Machinery & Supplies",
            "type":"Manufacturing & Wholesale Goods"
        }
    ],
    "sg:phone":"+43 4374 16524720",
    "sg:postcode":"3250",
    "sg:province":"Nieder\u00f6sterreich",
    "sg:tags":[
        "-",
        "agriculture",
        "equipment"
    ],
    "wof:name":"ANTON ROHER GMBH",
    "wof:placetype":"venue"
},
  "geometry": {"coordinates":[15.1409931183,48.1324920654],"type":"Point"}
}