{
  "type": "Feature",
  "properties": {
    "addr:full":"Immeng 21 Wien Wien 1210",
    "addr:housenumber":"21",
    "addr:postcode":"1210",
    "addr:street":"Immeng",
    "iso:country":"AT",
    "sg:address":"Immeng 21",
    "sg:city":"Wien",
    "sg:orig_category":"Dachdeckereien",
    "sg:phone":"+43 1 27862540",
    "sg:postcode":"1210",
    "sg:province":"Wien",
    "wof:name":"Herbich R GesmbH",
    "wof:placetype":"venue"
},
  "geometry": {"coordinates":[16.3999195099,48.2635726929],"type":"Point"}
}