{
  "type": "Feature",
  "properties": {
    "addr:full":"Eggerweg 301 Kappl Tirol 6555",
    "addr:housenumber":"301",
    "addr:postcode":"6555",
    "addr:street":"Eggerweg;Tirol",
    "iso:country":"AT",
    "sg:address":"Eggerweg 301",
    "sg:city":"Kappl",
    "sg:orig_category":"Appartements / Ferienwohnungen",
    "sg:phone":"+43 5445 6264",
    "sg:postcode":"6555",
    "sg:province":"Tirol",
    "wof:name":"Haus Bergkristall",
    "wof:placetype":"venue"
},
  "geometry": {"coordinates":[10.3702163696,47.0637741089],"type":"Point"}
}