{
  "type": "Feature",
  "properties": {
    "iso:country":"AT",
    "sg:address":"Nr 1",
    "sg:city":"Unterlamm",
    "sg:orig_category":"Schlossereien",
    "sg:phone":"+43 4331 558308",
    "sg:postcode":"8352",
    "sg:province":"Steiermark",
    "wof:name":"Lang Franz",
    "wof:placetype":"venue"
},
  "geometry": {"coordinates":[16.0573005676,46.9795761108],"type":"Point"}
}