{
  "type": "Feature",
  "properties": {
    "addr:full":"Nr 18 Irschen K\u00e4rnten 9773",
    "addr:postcode":"9773",
    "addr:street":"Nr 18 Irschen Kaernten",
    "iso:country":"AT",
    "sg:address":"Nr 18",
    "sg:city":"Irschen",
    "sg:orig_category":"Volksschulen",
    "sg:phone":"+43 4347 102511",
    "sg:postcode":"9773",
    "sg:province":"K\u00e4rnten",
    "wof:name":"Volksschule",
    "wof:placetype":"venue"
},
  "geometry": {"coordinates":[13.025015831,46.755897522],"type":"Point"}
}