{
  "type": "Feature",
  "properties": {
    "addr:full":"Steinbrecherg 20 Wien Wien 1220",
    "addr:housenumber":"20",
    "addr:postcode":"1220",
    "addr:street":"Steinbrecherg",
    "iso:country":"AT",
    "sg:address":"Steinbrecherg 20",
    "sg:city":"Wien",
    "sg:orig_category":"Installationsunternehmen",
    "sg:phone":"+43 1 7741482",
    "sg:postcode":"1220",
    "sg:province":"Wien",
    "wof:name":"Steiner Berndt",
    "wof:placetype":"venue"
},
  "geometry": {"coordinates":[16.4406452179,48.2339248657],"type":"Point"}
}