{
  "type": "Feature",
  "properties": {
    "addr:full":"Hadres 26 Hadres Nieder\u00f6sterreich 2061",
    "addr:housenumber":"26;2061",
    "addr:street":"Hadres;Niederoesterreich",
    "iso:country":"AT",
    "sg:address":"Hadres 26",
    "sg:city":"Hadres",
    "sg:classifiers":[
        {
            "category":"Structure",
            "subcategory":"Tunnel",
            "type":"Public Place"
        }
    ],
    "sg:phone":"+43 2943 2308",
    "sg:postcode":"2061",
    "sg:province":"Nieder\u00f6sterreich",
    "sg:tags":[
        "assembly",
        "system",
        "antenna"
    ],
    "wof:name":"Harald Sponner",
    "wof:placetype":"venue"
},
  "geometry": {"coordinates":[16.1345539093,48.7085876465],"type":"Point"}
}