{
  "type": "Feature",
  "properties": {
    "addr:full":"Ungarg 47 Wien Wien 1030",
    "addr:housenumber":"47",
    "addr:postcode":"1030",
    "addr:street":"Ungarg",
    "iso:country":"AT",
    "sg:address":"Ungarg 47",
    "sg:city":"Wien",
    "sg:orig_category":"Baumeister",
    "sg:phone":"+43 1 7137252",
    "sg:postcode":"1030",
    "sg:province":"Wien",
    "wof:name":"Pichelmann & Co GesmbH",
    "wof:placetype":"venue"
},
  "geometry": {"coordinates":[16.3876132965,48.1993751526],"type":"Point"}
}