{
  "type": "Feature",
  "properties": {
    "addr:full":"Gaullacherg 55 Wien Wien 1160",
    "addr:housenumber":"55",
    "addr:postcode":"1160",
    "addr:street":"Gaullacherg",
    "iso:country":"AT",
    "sg:address":"Gaullacherg 55",
    "sg:city":"Wien",
    "sg:orig_category":"Non-Classified Establishments",
    "sg:phone":"+43 1 4073141",
    "sg:postcode":"1160",
    "sg:province":"Wien",
    "wof:name":"Pfingstkirche der Koreaner in Wien",
    "wof:placetype":"venue"
},
  "geometry": {"coordinates":[16.3324317932,48.2120513916],"type":"Point"}
}