{
  "type": "Feature",
  "properties": {
    "iso:country":"AT",
    "sg:address":"Gratweiner Str 17",
    "sg:city":"Judendorf-Stra\u00dfengel",
    "sg:orig_category":"Friseure U Frisiersalons",
    "sg:phone":"+43 4331 2454062",
    "sg:postcode":"8111",
    "sg:province":"Steiermark",
    "wof:name":"Frisiersalon Haardesign",
    "wof:placetype":"venue"
},
  "geometry": {"coordinates":[15.342956543,47.1167564392],"type":"Point"}
}