{
  "type": "Feature",
  "properties": {
    "addr:full":"Windhagm\u00fchl 25 Liebenau Ober\u00f6sterreich 4252",
    "addr:housenumber":"25",
    "addr:postcode":"4252",
    "addr:street":"Windhagmuehl",
    "iso:country":"AT",
    "sg:address":"Windhagm\u00fchl 25",
    "sg:city":"Liebenau",
    "sg:orig_category":"Maler, Anstreicher U Lackierer",
    "sg:phone":"+43 7953 673",
    "sg:postcode":"4252",
    "sg:province":"Ober\u00f6sterreich",
    "wof:name":"Kastl Franz",
    "wof:placetype":"venue"
},
  "geometry": {"coordinates":[14.8076267242,48.531665802],"type":"Point"}
}