{
  "type": "Feature",
  "properties": {
    "addr:full":"Hauptpl 10 Lassee Nieder\u00f6sterreich 2291",
    "addr:housenumber":"10",
    "addr:postcode":"2291",
    "addr:street":"Hauptpl;Niederoesterreich",
    "iso:country":"AT",
    "sg:address":"Hauptpl 10",
    "sg:city":"Lassee",
    "sg:orig_category":"Banken U Sparkassen",
    "sg:phone":"+43 4322 1324410",
    "sg:postcode":"2291",
    "sg:province":"Nieder\u00f6sterreich",
    "wof:name":"Marchfelder Volksbank regGenmbH",
    "wof:placetype":"venue"
},
  "geometry": {"coordinates":[-94.2693786621,47.8095817566],"type":"Point"}
}