{
  "type": "Feature",
  "properties": {
    "addr:full":"Umseer Str 19 Neulengbach Nieder\u00f6sterreich 3040",
    "addr:housenumber":"19",
    "addr:postcode":"3040",
    "addr:street":"Str",
    "iso:country":"AT",
    "sg:address":"Umseer Str 19",
    "sg:city":"Neulengbach",
    "sg:orig_category":"Partyservice",
    "sg:phone":"+43 2772 52457",
    "sg:postcode":"3040",
    "sg:province":"Nieder\u00f6sterreich",
    "wof:name":"R & M Reither und Messerer Ihr Partyservice",
    "wof:placetype":"venue"
},
  "geometry": {"coordinates":[15.8680639267,48.2038764954],"type":"Point"}
}