{
  "type": "Feature",
  "properties": {
    "addr:full":"Schmiede 21 Ehrwald Tirol 6632",
    "addr:housenumber":"21",
    "addr:postcode":"6632",
    "addr:street":"Schmiede;Tirol",
    "iso:country":"AT",
    "sg:address":"Schmiede 21",
    "sg:city":"Ehrwald",
    "sg:orig_category":"Appartements / Ferienwohnungen",
    "sg:phone":"+43 4356 7320001",
    "sg:postcode":"6632",
    "sg:province":"Tirol",
    "wof:name":"Blue Sky Appartements Hornikel Margit",
    "wof:placetype":"venue"
},
  "geometry": {"coordinates":[10.9153862,47.412399292],"type":"Point"}
}