{
  "type": "Feature",
  "properties": {
    "iso:country":"AT",
    "sg:address":"Hauptstr 28",
    "sg:city":"Lackendorf",
    "sg:orig_category":"Gemeinden",
    "sg:phone":"+43 2619 7213",
    "sg:postcode":"7321",
    "sg:province":"Burgenland",
    "wof:name":"Gemeindeamt Unterfrauenhaid",
    "wof:placetype":"venue"
},
  "geometry": {"coordinates":[16.5012645721,47.5733566284],"type":"Point"}
}