{
  "type": "Feature",
  "properties": {
    "iso:country":"AT",
    "sg:address":"Traung 4",
    "sg:city":"Wien",
    "sg:orig_category":"Steuerberatung",
    "sg:phone":"+43 4317 1225550",
    "sg:postcode":"1030",
    "sg:province":"Wien",
    "wof:name":"Schwarzinger Prof Dr Wirtschaftstreuhand GmbH Mag Dr",
    "wof:placetype":"venue"
},
  "geometry": {"coordinates":[16.3802642822,48.200088501],"type":"Point"}
}