{
  "type": "Feature",
  "properties": {
    "iso:country":"AT",
    "sg:address":"Spanheimerstr 32",
    "sg:city":"Wolfsberg",
    "sg:orig_category":"Bekleidung / Einzelhandel",
    "sg:phone":"+43 4367 67899116",
    "sg:postcode":"9400",
    "sg:province":"K\u00e4rnten",
    "wof:name":"Esprit Store Partnership",
    "wof:placetype":"venue"
},
  "geometry": {"coordinates":[14.8399982452,46.8375701904],"type":"Point"}
}