{
  "type": "Feature",
  "properties": {
    "addr:full":"Zenog 9/1a Wien Wien 1120",
    "addr:housenumber":"9 / 1a",
    "addr:postcode":"1120",
    "addr:street":"Zenog",
    "iso:country":"AT",
    "sg:address":"Zenog 9/1a",
    "sg:city":"Wien",
    "sg:orig_category":"Alternativtherapie",
    "sg:phone":"+43 4319 436376",
    "sg:postcode":"1120",
    "sg:province":"Wien",
    "wof:name":"Praxis f\u00fcr Energietherapie - G\u00fcnther Viertl",
    "wof:placetype":"venue"
},
  "geometry": {"coordinates":[16.3290939331,48.1824874878],"type":"Point"}
}