{
  "type": "Feature",
  "properties": {
    "addr:full":"Vordertambergau 21 Vorderstoder Ober\u00f6sterreich 4574",
    "addr:housenumber":"21",
    "addr:postcode":"4574",
    "addr:street":"Vordertambergau",
    "iso:country":"AT",
    "sg:address":"Vordertambergau 21",
    "sg:city":"Vorderstoder",
    "sg:orig_category":"Musikgruppen",
    "sg:phone":"+43 664 3141551",
    "sg:postcode":"4574",
    "sg:province":"Ober\u00f6sterreich",
    "wof:name":"Stodertaler Gaudi-Express",
    "wof:placetype":"venue"
},
  "geometry": {"coordinates":[14.2474517822,47.7175483704],"type":"Point"}
}