{
  "type": "Feature",
  "properties": {
    "addr:full":"Kirchenb\u00fchl 375 Hittisau Vorarlberg 6952",
    "addr:housenumber":"375",
    "addr:postcode":"6952",
    "iso:country":"AT",
    "sg:address":"Kirchenb\u00fchl 375",
    "sg:city":"Hittisau",
    "sg:orig_category":"\u00c3\u201erzte / F Allgemeinmedizin",
    "sg:phone":"+43 5513 30001",
    "sg:postcode":"6952",
    "sg:province":"Vorarlberg",
    "wof:name":"Bilgeri Stefan Dr",
    "wof:placetype":"venue"
},
  "geometry": {"coordinates":[9.956700325,47.4603385925],"type":"Point"}
}