{
  "type": "Feature",
  "properties": {
    "addr:full":"Zelfenstr 3A Tschagguns Vorarlberg 6774",
    "addr:housenumber":"3a",
    "addr:postcode":"6774",
    "addr:street":"Zelfenstr",
    "iso:country":"AT",
    "sg:address":"Zelfenstr 3A",
    "sg:city":"Tschagguns",
    "sg:orig_category":"Tabaktrafiken",
    "sg:phone":"+43 5556 77566",
    "sg:postcode":"6774",
    "sg:province":"Vorarlberg",
    "wof:name":"Harry's Eck - Fam Loretz",
    "wof:placetype":"venue"
},
  "geometry": {"coordinates":[9.9024362564,47.0772476196],"type":"Point"}
}