{
  "type": "Feature",
  "properties": {
    "iso:country":"AT",
    "sg:address":"Am Anger 42",
    "sg:city":"Stockerau",
    "sg:orig_category":"Lebensmittel / Einzelhandel",
    "sg:phone":"+43 2267 2537",
    "sg:postcode":"2000",
    "sg:province":"Nieder\u00f6sterreich",
    "wof:name":"Muck Gottfried - Einkaufen am Bauernhof",
    "wof:placetype":"venue"
},
  "geometry": {"coordinates":[16.1622982025,48.4096794128],"type":"Point"}
}