{
  "type": "Feature",
  "properties": {
    "iso:country":"AT",
    "sg:address":"Am Eisbach 28",
    "sg:city":"Puntigam",
    "sg:orig_category":"Dachdeckereien",
    "sg:phone":"+43 4331 62943380",
    "sg:postcode":"8055",
    "sg:province":"Steiermark",
    "wof:name":"Balk Dach GmbH",
    "wof:placetype":"venue"
},
  "geometry": {"coordinates":[15.4512224197,47.0193214417],"type":"Point"}
}