{
  "type": "Feature",
  "properties": {
    "addr:full":"Obermarkt 51 Reutte Tirol 6600",
    "addr:housenumber":"51",
    "addr:postcode":"6600",
    "addr:street":"Obermarkt;Tirol",
    "iso:country":"AT",
    "sg:address":"Obermarkt 51",
    "sg:city":"Reutte",
    "sg:orig_category":"Banken U Sparkassen",
    "sg:phone":"+43 4356 7269690",
    "sg:postcode":"6600",
    "sg:province":"Tirol",
    "wof:name":"Sparkasse Reutte",
    "wof:placetype":"venue"
},
  "geometry": {"coordinates":[10.7198190689,47.4867362976],"type":"Point"}
}