{
  "type": "Feature",
  "properties": {
    "addr:full":"Bahnstr 10 Wieselburg an der Erlauf Nieder\u00f6sterreich 3250",
    "addr:housenumber":"10",
    "addr:postcode":"3250",
    "addr:street":"Bahnstr",
    "iso:country":"AT",
    "sg:address":"Bahnstr 10",
    "sg:city":"Wieselburg an der Erlauf",
    "sg:orig_category":"Kosmetikanwendungsberatung",
    "sg:phone":"+43 7416 53356",
    "sg:postcode":"3250",
    "sg:province":"Nieder\u00f6sterreich",
    "wof:name":"Scharner Margit - Kosmetikberatung",
    "wof:placetype":"venue"
},
  "geometry": {"coordinates":[15.135219574,48.1061210632],"type":"Point"}
}