{
  "type": "Feature",
  "properties": {
    "iso:country":"AT",
    "sg:address":"Wiener Str 287",
    "sg:city":"G\u00f6sting",
    "sg:orig_category":"Ballettschulen",
    "sg:phone":"+43 316 683568",
    "sg:postcode":"8051",
    "sg:province":"Steiermark",
    "sg:website":"www.ballettschule-graz.at",
    "wof:name":"ON STAGE - Tanz 287",
    "wof:placetype":"venue"
},
  "geometry": {"coordinates":[15.4038715363,47.0969390869],"type":"Point"}
}