{
  "type": "Feature",
  "properties": {
    "iso:country":"AT",
    "sg:address":"Troststr 48",
    "sg:city":"Wien",
    "sg:orig_category":"Immobilienmakler",
    "sg:phone":"+43 1 6418376",
    "sg:postcode":"1100",
    "sg:province":"Wien",
    "wof:name":"Kukowitsch Otmar Dkfm",
    "wof:placetype":"venue"
},
  "geometry": {"coordinates":[16.3713378906,48.1690711975],"type":"Point"}
}