{
  "type": "Feature",
  "properties": {
    "iso:country":"AT",
    "sg:address":"D\u00fcrndorf 142",
    "sg:city":"Pettenbach",
    "sg:orig_category":"Baumeister",
    "sg:phone":"+43 7586 72740",
    "sg:postcode":"4643",
    "sg:province":"Ober\u00f6sterreich",
    "sg:website":"bm-staudinger.at",
    "wof:name":"Staudinger Franz Baumeister GesmbH",
    "wof:placetype":"venue"
},
  "geometry": {"coordinates":[14.0165214539,47.9612464905],"type":"Point"}
}