{
  "type": "Feature",
  "properties": {
    "addr:full":"Kleingartenweg 7 Bruck an der Gro\u00dfglocknerstra\u00dfe Salzburg 5671",
    "addr:housenumber":"7",
    "addr:postcode":"5671",
    "addr:street":"Kleingartenweg;Grossglocknerstrasse Salzburg",
    "iso:country":"AT",
    "sg:address":"Kleingartenweg 7",
    "sg:city":"Bruck an der Gro\u00dfglocknerstra\u00dfe",
    "sg:orig_category":"Fliesen- U Plattenverlegungen",
    "sg:phone":"+43 4365 457155",
    "sg:postcode":"5671",
    "sg:province":"Salzburg",
    "wof:name":"Leixnering Herbert - Fliesenlegermeisterbetrieb",
    "wof:placetype":"venue"
},
  "geometry": {"coordinates":[12.8397130966,47.2818870544],"type":"Point"}
}