{
  "type": "Feature",
  "properties": {
    "addr:full":"Burgenlandstrasse 4 Bruck an der Leitha Nieder\u00f6sterreich 2460",
    "addr:housenumber":"4",
    "addr:postcode":"2460",
    "addr:street":"Burgenlandstrasse",
    "iso:country":"AT",
    "sg:address":"Burgenlandstrasse 4",
    "sg:city":"Bruck an der Leitha",
    "sg:classifiers":[
        {
            "category":"Home & Garden",
            "subcategory":"Household Appliances",
            "type":"Retail Goods"
        }
    ],
    "sg:phone":"+43 2162 624640",
    "sg:postcode":"2460",
    "sg:province":"Nieder\u00f6sterreich",
    "sg:tags":[
        "electric"
    ],
    "wof:name":"Elektro Huber Ges.m.b.H.",
    "wof:placetype":"venue"
},
  "geometry": {"coordinates":[16.7790088654,48.0245628357],"type":"Point"}
}