{
  "type": "Feature",
  "properties": {
    "addr:full":"Getreideg 34 Salzburg Salzburg 5020",
    "addr:housenumber":"34",
    "addr:postcode":"5020",
    "addr:street":"Getreideg;Salzburg",
    "iso:country":"AT",
    "sg:address":"Getreideg 34",
    "sg:city":"Salzburg",
    "sg:orig_category":"Juweliere, Gold- U Silberschmiede",
    "sg:phone":"+43 662 840402",
    "sg:postcode":"5020",
    "sg:province":"Salzburg",
    "wof:name":"Goldschmied Steiner",
    "wof:placetype":"venue"
},
  "geometry": {"coordinates":[13.041724205,47.8001327515],"type":"Point"}
}