{
  "type": "Feature",
  "properties": {
    "iso:country":"AT",
    "sg:address":"W\u00fcrnsdorf 1",
    "sg:city":"P\u00f6ggstall",
    "sg:classifiers":[
        {
            "category":"Retail",
            "subcategory":"Repair Shop",
            "type":"Services"
        }
    ],
    "sg:phone":"+43 2758 2251",
    "sg:postcode":"3650",
    "sg:province":"Nieder\u00f6sterreich",
    "sg:tags":[
        "agricultural",
        "machinery"
    ],
    "sg:website":"alois-jungwirth.at",
    "wof:name":"Alois Jungwirth",
    "wof:placetype":"venue"
},
  "geometry": {"coordinates":[-80.3472366333,41.0018386841],"type":"Point"}
}