{
  "type": "Feature",
  "properties": {
    "addr:full":"Traung 21 Wels Ober\u00f6sterreich 4600",
    "addr:housenumber":"21",
    "addr:postcode":"4600",
    "addr:street":"Traung;Oberoesterreich",
    "iso:country":"AT",
    "sg:address":"Traung 21",
    "sg:city":"Wels",
    "sg:orig_category":"Juweliere, Gold- U Silberschmiede",
    "sg:phone":"+43 4372 4268765",
    "sg:postcode":"4600",
    "sg:province":"Ober\u00f6sterreich",
    "wof:name":"Kemptner Franz Josef",
    "wof:placetype":"venue"
},
  "geometry": {"coordinates":[14.0263175964,48.1556663513],"type":"Point"}
}