{
  "type": "Feature",
  "properties": {
    "addr:full":"Wilhelm Erben-Str 17 Salzburg Salzburg 5020",
    "addr:housenumber":"17",
    "addr:postcode":"5020",
    "addr:street":"Salzburg",
    "iso:country":"AT",
    "sg:address":"Wilhelm Erben-Str 17",
    "sg:city":"Salzburg",
    "sg:orig_category":"Bekleidung / Erzeugung U Gro\u00c3\u0178handel",
    "sg:phone":"+43 4366 2432979",
    "sg:postcode":"5020",
    "sg:province":"Salzburg",
    "wof:name":"Ballnik Eduard",
    "wof:placetype":"venue"
},
  "geometry": {"coordinates":[13.0233316422,47.8070220947],"type":"Point"}
}