{
  "type": "Feature",
  "properties": {
    "addr:full":"Kirchenpl 5 Zistersdorf Nieder\u00f6sterreich 2225",
    "addr:housenumber":"5",
    "addr:postcode":"2225",
    "addr:street":"Kirchenpl;Niederoesterreich",
    "iso:country":"AT",
    "sg:address":"Kirchenpl 5",
    "sg:city":"Zistersdorf",
    "sg:classifiers":[
        {
            "category":"Shopping",
            "subcategory":"Bicycles & Sporting Goods",
            "type":"Retail Goods"
        }
    ],
    "sg:phone":"+43 2532 22710",
    "sg:postcode":"2225",
    "sg:province":"Nieder\u00f6sterreich",
    "sg:tags":[
        "munition",
        "u",
        "waffen"
    ],
    "sg:website":"www.waffen.at",
    "wof:name":"Frohner Robert",
    "wof:placetype":"venue"
},
  "geometry": {"coordinates":[16.761177063,48.5449905396],"type":"Point"}
}