{
  "type": "Feature",
  "properties": {
    "iso:country":"AT",
    "sg:address":"Valiergasse 40",
    "sg:city":"Innsbruck",
    "sg:classifiers":[
        {
            "category":"Professional",
            "subcategory":"Art Services",
            "type":"Services"
        }
    ],
    "sg:phone":"+43 512 33404",
    "sg:postcode":"6020",
    "sg:province":"Tirol",
    "sg:tags":[
        "catalogue"
    ],
    "sg:website":"tiroler-repro-druck.co.at",
    "wof:name":"Tiroler Repro Druck GesmbH",
    "wof:placetype":"venue"
},
  "geometry": {"coordinates":[11.4368476868,47.2668800354],"type":"Point"}
}