{
  "type": "Feature",
  "properties": {
    "iso:country":"AT",
    "sg:address":"Klosterstr 23",
    "sg:city":"Gaspoltshofen",
    "sg:orig_category":"Transportunternehmen",
    "sg:phone":"+43 7735 7193",
    "sg:postcode":"4673",
    "sg:province":"Ober\u00f6sterreich",
    "wof:name":"Klinger Wolfgang Ing",
    "wof:placetype":"venue"
},
  "geometry": {"coordinates":[13.7299776077,48.1410980225],"type":"Point"}
}