{
  "type": "Feature",
  "properties": {
    "iso:country":"AT",
    "sg:address":"Nr 25",
    "sg:city":"Glanegg",
    "sg:orig_category":"Schlossereien",
    "sg:phone":"+43 4277 3229",
    "sg:postcode":"9555",
    "sg:province":"K\u00e4rnten",
    "wof:name":"Lesjak J und R Metallbau OEG",
    "wof:placetype":"venue"
},
  "geometry": {"coordinates":[14.2108659744,46.7163887024],"type":"Point"}
}