{
  "type": "Feature",
  "properties": {
    "addr:full":"Ferdinand Waldm\u00fcller-Gasse 6 Gaaden Nieder\u00f6sterreich 2531",
    "addr:housenumber":"6",
    "addr:postcode":"2531",
    "addr:street":"Waldmueller-Gasse",
    "iso:country":"AT",
    "sg:address":"Ferdinand Waldm\u00fcller-Gasse 6",
    "sg:city":"Gaaden",
    "sg:classifiers":[
        {
            "category":"Banks & Credit Unions",
            "subcategory":"Bank",
            "type":"Services"
        }
    ],
    "sg:phone":"+43 2237 8117",
    "sg:postcode":"2531",
    "sg:province":"Nieder\u00f6sterreich",
    "sg:tags":[
        "detector",
        "banknote",
        "reader"
    ],
    "sg:website":"phyma-colourvision.com",
    "wof:name":"Phyma Computerme\u00dftechnik Spektrometersysteme Ges.m.b.H.",
    "wof:placetype":"venue"
},
  "geometry": {"coordinates":[16.2028598785,48.0539512634],"type":"Point"}
}