{
  "type": "Feature",
  "properties": {
    "iso:country":"AT",
    "sg:city":"Mutters",
    "sg:orig_category":"Feuerwehren",
    "sg:phone":"+43 512 548409",
    "sg:postcode":"6162",
    "sg:province":"Tirol",
    "wof:name":"Freiwillige Feuerwehr Mutters",
    "wof:placetype":"venue"
},
  "geometry": {"coordinates":[11.376742363,47.227558136],"type":"Point"}
}