{
  "type": "Feature",
  "properties": {
    "iso:country":"AT",
    "sg:address":"Porschestr 39",
    "sg:city":"St. P\u00f6lten",
    "sg:classifiers":[
        {
            "category":"Home & Garden",
            "subcategory":"Building Materials",
            "type":"Retail Goods"
        }
    ],
    "sg:phone":"+43 2742 8825200",
    "sg:postcode":"3100",
    "sg:province":"Nieder\u00f6sterreich",
    "sg:tags":[
        "baustoffe",
        "-material",
        "u"
    ],
    "wof:name":"Quester Baustoffhandel GmbH & Co KG",
    "wof:placetype":"venue"
},
  "geometry": {"coordinates":[15.6240940094,48.2076377869],"type":"Point"}
}