{
  "type": "Feature",
  "properties": {
    "iso:country":"AT",
    "sg:address":"Hauptstr 6",
    "sg:city":"St. Leonhard",
    "sg:orig_category":"Tischlereien",
    "sg:phone":"+43 4379 5282020",
    "sg:postcode":"4294",
    "sg:province":"Ober\u00f6sterreich",
    "wof:name":"Kiesenhofer Robert",
    "wof:placetype":"venue"
},
  "geometry": {"coordinates":[14.6746883392,48.4413414001],"type":"Point"}
}