{
  "type": "Feature",
  "properties": {
    "addr:full":"Schulstr 299 Feistritz im Rosental K\u00e4rnten 9181",
    "addr:housenumber":"299",
    "addr:postcode":"9181",
    "iso:country":"AT",
    "sg:address":"Schulstr 299",
    "sg:city":"Feistritz im Rosental",
    "sg:orig_category":"Tabaktrafiken",
    "sg:phone":"+43 4342 282039",
    "sg:postcode":"9181",
    "sg:province":"K\u00e4rnten",
    "wof:name":"Tamegger Erwin",
    "wof:placetype":"venue"
},
  "geometry": {"coordinates":[14.1680231094,46.5231285095],"type":"Point"}
}