{
  "type": "Feature",
  "properties": {
    "addr:full":"Nr 124 St. Leonhard am Hornerwald Nieder\u00f6sterreich 3572",
    "addr:postcode":"3572",
    "addr:street":"Nr 124",
    "iso:country":"AT",
    "sg:address":"Nr 124",
    "sg:city":"St. Leonhard am Hornerwald",
    "sg:orig_category":"Friseure U Frisiersalons",
    "sg:phone":"+43 4329 8724145",
    "sg:postcode":"3572",
    "sg:province":"Nieder\u00f6sterreich",
    "wof:name":"FRISEUR HAIR-WELL Alexandra Mrlik",
    "wof:placetype":"venue"
},
  "geometry": {"coordinates":[15.5459947586,48.598236084],"type":"Point"}
}