{
  "type": "Feature",
  "properties": {
    "addr:full":"Dambergg 8b Steyr Ober\u00f6sterreich 4400",
    "addr:housenumber":"8b",
    "addr:postcode":"4400",
    "addr:street":"Dambergg;Oberoesterreich",
    "iso:country":"AT",
    "sg:address":"Dambergg 8b",
    "sg:city":"Steyr",
    "sg:orig_category":"Tabaktrafiken",
    "sg:phone":"+43 7252 46330",
    "sg:postcode":"4400",
    "sg:province":"Ober\u00f6sterreich",
    "wof:name":"Novak Karl-Heinz",
    "wof:placetype":"venue"
},
  "geometry": {"coordinates":[14.4254550934,48.0383453369],"type":"Point"}
}