{
  "type": "Feature",
  "properties": {
    "addr:full":"Bergmanng 249 Neulengbach Nieder\u00f6sterreich 3040",
    "addr:housenumber":"249",
    "addr:postcode":"3040",
    "iso:country":"AT",
    "sg:address":"Bergmanng 249",
    "sg:city":"Neulengbach",
    "sg:orig_category":"Massagen",
    "sg:phone":"+43 2772 55215",
    "sg:postcode":"3040",
    "sg:province":"Nieder\u00f6sterreich",
    "wof:name":"Kravogel Helmut",
    "wof:placetype":"venue"
},
  "geometry": {"coordinates":[15.9042549133,48.193321228],"type":"Point"}
}