{
  "type": "Feature",
  "properties": {
    "iso:country":"AT",
    "sg:address":"Bundesstr 41b",
    "sg:city":"Kl\u00f6sterle",
    "sg:orig_category":"Transportunternehmen",
    "sg:phone":"+43 4355 82279",
    "sg:postcode":"6754",
    "sg:province":"Vorarlberg",
    "wof:name":"Kessler GesmbH",
    "wof:placetype":"venue"
},
  "geometry": {"coordinates":[-101.40701293950001,34.2146606445],"type":"Point"}
}