{
  "type": "Feature",
  "properties": {
    "addr:full":"Schumanngasse 56/2 Wien Wien 1170",
    "addr:housenumber":"56 / 2",
    "addr:postcode":"1170",
    "addr:street":"Schumanngasse",
    "iso:country":"AT",
    "sg:address":"Schumanngasse 56/2",
    "sg:city":"Wien",
    "sg:classifiers":[
        {
            "category":"Building & Trades",
            "subcategory":"Electrical",
            "type":"Services"
        }
    ],
    "sg:phone":"+43 1 3694724",
    "sg:postcode":"1170",
    "sg:province":"Wien",
    "sg:tags":[
        "work",
        "installation"
    ],
    "sg:website":"koepf.at",
    "wof:name":"Alois K\u00f6pf GmbH",
    "wof:placetype":"venue"
},
  "geometry": {"coordinates":[16.3359279633,48.2221794128],"type":"Point"}
}