{
  "type": "Feature",
  "properties": {
    "iso:country":"AT",
    "sg:address":"Linke Br\u00fcckenstr 11",
    "sg:city":"Linz",
    "sg:orig_category":"Boutiquen",
    "sg:phone":"+43 732 732639",
    "sg:postcode":"4040",
    "sg:province":"Ober\u00f6sterreich",
    "wof:name":"Obersteiner Monika",
    "wof:placetype":"venue"
},
  "geometry": {"coordinates":[14.2578554153,48.3602561951],"type":"Point"}
}