{
  "type": "Feature",
  "properties": {
    "addr:full":"Tuxer Str 700 Mayrhofen Tirol 6290",
    "addr:housenumber":"700",
    "addr:postcode":"6290",
    "addr:street":"Str;Tirol",
    "iso:country":"AT",
    "sg:address":"Tuxer Str 700",
    "sg:city":"Mayrhofen",
    "sg:orig_category":"Friseure U Frisiersalons",
    "sg:phone":"+43 5285 62326",
    "sg:postcode":"6290",
    "sg:province":"Tirol",
    "wof:name":"Wechselberger Paul",
    "wof:placetype":"venue"
},
  "geometry": {"coordinates":[11.860203743,47.1618690491],"type":"Point"}
}