{
  "type": "Feature",
  "properties": {
    "iso:country":"AT",
    "sg:address":"Italiener Str 27",
    "sg:city":"Villach",
    "sg:orig_category":"Sonnenstudios",
    "sg:phone":"+43 4242 287130",
    "sg:postcode":"9500",
    "sg:province":"K\u00e4rnten",
    "wof:name":"City Sun Br\u00e4ungsstudio",
    "wof:placetype":"venue"
},
  "geometry": {"coordinates":[13.8431978226,46.6093482971],"type":"Point"}
}