{
  "type": "Feature",
  "properties": {
    "iso:country":"AT",
    "sg:address":"Schl\u00f6glstr 36",
    "sg:city":"Hall in Tirol",
    "sg:orig_category":"Technische Bedarfsartikel",
    "sg:phone":"+43 5223 418880",
    "sg:postcode":"6060",
    "sg:province":"Tirol",
    "wof:name":"HB-Technik Huber & B\u00fcchele GesmbH & Co KG",
    "wof:placetype":"venue"
},
  "geometry": {"coordinates":[11.4808206558,47.2741012573],"type":"Point"}
}