{
  "type": "Feature",
  "properties": {
    "addr:full":"Innsbrucker Strasse 49 Reutte Tirol 6600",
    "addr:housenumber":"49",
    "addr:postcode":"6600",
    "addr:street":"Innsbrucker Strasse;Tirol",
    "iso:country":"AT",
    "sg:address":"Innsbrucker Strasse 49",
    "sg:city":"Reutte",
    "sg:classifiers":[
        {
            "category":"Manufacturing",
            "subcategory":"Wood Products",
            "type":"Manufacturing & Wholesale Goods"
        }
    ],
    "sg:phone":"+43 5672 622220",
    "sg:postcode":"6600",
    "sg:province":"Tirol",
    "sg:tags":[
        "gate",
        "made",
        "door"
    ],
    "sg:website":"nessler-tirol.at",
    "wof:name":"Nessler Fenster T\u00fcren Produktions- und Vertriebsgesellschaft m.b.H. & Co KG",
    "wof:placetype":"venue"
},
  "geometry": {"coordinates":[10.7293739319,47.480014801],"type":"Point"}
}