{
  "type": "Feature",
  "properties": {
    "iso:country":"AT",
    "sg:address":"Erlauftalstrasse 42",
    "sg:city":"Gaming",
    "sg:classifiers":[
        {
            "category":"Shopping",
            "subcategory":"Bicycles & Sporting Goods",
            "type":"Retail Goods"
        }
    ],
    "sg:phone":"+43 7485 97566",
    "sg:postcode":"3292",
    "sg:province":"Nieder\u00f6sterreich",
    "wof:name":"Franz Krendl",
    "wof:placetype":"venue"
},
  "geometry": {"coordinates":[15.0963602066,47.9360847473],"type":"Point"}
}