{
  "type": "Feature",
  "properties": {
    "addr:full":"Herzog-Friedrich-Str 11 Innsbruck Tirol 6020",
    "addr:housenumber":"11",
    "addr:postcode":"6020",
    "addr:street":"Herzog-Friedrich-Str;Tirol",
    "iso:country":"AT",
    "sg:address":"Herzog-Friedrich-Str 11",
    "sg:city":"Innsbruck",
    "sg:classifiers":[
        {
            "category":"Restaurant",
            "type":"Food & Drink"
        }
    ],
    "sg:phone":"+43 512 582875",
    "sg:postcode":"6020",
    "sg:province":"Tirol",
    "wof:name":"Restaurant Elferhaus",
    "wof:placetype":"venue"
},
  "geometry": {"coordinates":[11.3928718567,47.2686538696],"type":"Point"}
}