{
  "type": "Feature",
  "properties": {
    "iso:country":"AT",
    "sg:address":"Sepp-Amschl-Str 21",
    "sg:city":"Mureck",
    "sg:orig_category":"Versicherungsunternehmen",
    "sg:phone":"+43 3472 2000",
    "sg:postcode":"8480",
    "sg:province":"Steiermark",
    "wof:name":"\u00f6sterr Beamtenversicherung Gesch\u00e4ftsstelle",
    "wof:placetype":"venue"
},
  "geometry": {"coordinates":[15.7793512344,46.709903717],"type":"Point"}
}