{
  "type": "Feature",
  "properties": {
    "addr:full":"Wolfgang-Pauli-Str 2 Wiener Neustadt Nieder\u00f6sterreich 2700",
    "addr:housenumber":"2",
    "addr:postcode":"2700",
    "addr:street":"Wolfgang-Pauli-Str",
    "iso:country":"AT",
    "sg:address":"Wolfgang-Pauli-Str 2",
    "sg:city":"Wiener Neustadt",
    "sg:orig_category":"Elektronische Bauelemente U Bauteile",
    "sg:phone":"+43 4326 2222700",
    "sg:postcode":"2700",
    "sg:province":"Nieder\u00f6sterreich",
    "wof:name":"J S T Oesterreich GmbH",
    "wof:placetype":"venue"
},
  "geometry": {"coordinates":[16.250333786,47.8405265808],"type":"Point"}
}