{
  "type": "Feature",
  "properties": {
    "addr:full":"Hauptplatz 7  Knittelfeld Steiermark 8720",
    "addr:housenumber":"7",
    "addr:postcode":"8720",
    "addr:street":"Hauptplatz",
    "iso:country":"AT",
    "sg:address":"Hauptplatz 7 ",
    "sg:city":"Knittelfeld",
    "sg:classifiers":[
        {
            "category":"Banks & Credit Unions",
            "subcategory":"Bank",
            "type":"Services"
        }
    ],
    "sg:phone":"+43 4335 12853000",
    "sg:postcode":"8720",
    "sg:province":"Steiermark",
    "sg:tags":[
        "banking",
        "institution"
    ],
    "wof:name":"SPARKASSE DER STADT KNITTELFELD AG",
    "wof:placetype":"venue"
},
  "geometry": {"coordinates":[14.8295631409,47.2139663696],"type":"Point"}
}