{
  "type": "Feature",
  "properties": {
    "iso:country":"AT",
    "sg:address":"Brandm\u00fchlestr. 2",
    "sg:city":"Adlwang",
    "sg:classifiers":[
        {
            "category":"Home & Garden",
            "subcategory":"Home Furnishings",
            "type":"Retail Goods"
        }
    ],
    "sg:phone":"+43 4372 5839080",
    "sg:postcode":"4541",
    "sg:province":"Ober\u00f6sterreich",
    "sg:tags":[
        "household"
    ],
    "wof:name":"HALE HANDEL & DIENSTLEISTUNG GMBH",
    "wof:placetype":"venue"
},
  "geometry": {"coordinates":[14.2176198959,47.9920692444],"type":"Point"}
}