{
  "type": "Feature",
  "properties": {
    "addr:full":"Nr 105 Maria Lankowitz Steiermark 8591",
    "addr:postcode":"8591",
    "addr:street":"Nr 105",
    "iso:country":"AT",
    "sg:address":"Nr 105",
    "sg:city":"Maria Lankowitz",
    "sg:orig_category":"Erdarbeiten",
    "sg:phone":"+43 4331 444942",
    "sg:postcode":"8591",
    "sg:province":"Steiermark",
    "wof:name":"Erdbewegungen Fink",
    "wof:placetype":"venue"
},
  "geometry": {"coordinates":[15.0651445389,47.0628318787],"type":"Point"}
}