{
  "type": "Feature",
  "properties": {
    "addr:full":"Obere Viaduktg 20 Wien Wien 1030",
    "addr:housenumber":"20",
    "addr:postcode":"1030",
    "addr:street":"Obere Viaduktg",
    "iso:country":"AT",
    "sg:address":"Obere Viaduktg 20",
    "sg:city":"Wien",
    "sg:orig_category":"Unternehmensberatung",
    "sg:phone":"+43 4366 43428442",
    "sg:postcode":"1030",
    "sg:province":"Wien",
    "wof:name":"Beakon Consulting - Erik Schnabl",
    "wof:placetype":"venue"
},
  "geometry": {"coordinates":[16.3897094727,48.2105522156],"type":"Point"}
}