{
  "type": "Feature",
  "properties": {
    "addr:full":"Bauhofgasse 14 Judenburg Steiermark 8750",
    "addr:housenumber":"14",
    "addr:postcode":"8750",
    "addr:street":"Bauhofgasse",
    "iso:country":"AT",
    "sg:address":"Bauhofgasse 14",
    "sg:city":"Judenburg",
    "sg:classifiers":[
        {
            "category":"Home & Garden",
            "subcategory":"Building Materials",
            "type":"Retail Goods"
        }
    ],
    "sg:phone":"+43 3572 83421",
    "sg:postcode":"8750",
    "sg:province":"Steiermark",
    "sg:tags":[
        "scraps",
        "scrap",
        "metal",
        "iron"
    ],
    "sg:website":"truegler-recycling.at",
    "wof:name":"Tr\u00fcgler Recycling und Transport GmbH",
    "wof:placetype":"venue"
},
  "geometry": {"coordinates":[14.6756277084,47.1691207886],"type":"Point"}
}