{
  "type": "Feature",
  "properties": {
    "addr:full":"Bahnhofstr 8 St. Johann in Tirol Tirol 6380",
    "addr:housenumber":"8",
    "addr:postcode":"6380",
    "addr:street":"Bahnhofstr;Tirol",
    "iso:country":"AT",
    "sg:address":"Bahnhofstr 8",
    "sg:city":"St. Johann in Tirol",
    "sg:orig_category":"Museen / Ausstellungen",
    "sg:phone":"+43 4353 52690013",
    "sg:postcode":"6380",
    "sg:province":"Tirol",
    "wof:name":"St. Johann Museum",
    "wof:placetype":"venue"
},
  "geometry": {"coordinates":[12.4289827347,47.5218658447],"type":"Point"}
}