{
  "type": "Feature",
  "properties": {
    "addr:full":"Puntigamer Str 127 Puntigam Steiermark 8055",
    "addr:housenumber":"127",
    "addr:postcode":"8055",
    "iso:country":"AT",
    "sg:address":"Puntigamer Str 127",
    "sg:city":"Puntigam",
    "sg:orig_category":"Adressen- U Telefonbuchverlage",
    "sg:phone":"+43 4331 6242411",
    "sg:postcode":"8055",
    "sg:province":"Steiermark",
    "sg:website":"herold.at",
    "wof:name":"HEROLD Business Data GmbH & Co. KG - Anzeigenverkauf",
    "wof:placetype":"venue"
},
  "geometry": {"coordinates":[15.4434785843,47.0333900452],"type":"Point"}
}