{
  "type": "Feature",
  "properties": {
    "addr:full":"Minorgasse 63 Wien Wien 1140",
    "addr:housenumber":"63",
    "addr:postcode":"1140",
    "addr:street":"Minorgasse",
    "iso:country":"AT",
    "sg:address":"Minorgasse 63",
    "sg:city":"Wien",
    "sg:classifiers":[
        {
            "category":"Utilities",
            "subcategory":"Telephone",
            "type":"Services"
        }
    ],
    "sg:phone":"+43 1 4164164",
    "sg:postcode":"1140",
    "sg:province":"Wien",
    "sg:tags":[
        "telecommunication",
        "expert"
    ],
    "sg:website":"0800vanity.com; blutegel.org",
    "wof:name":"0800VAMITY.com Neue Medien GmbH",
    "wof:placetype":"venue"
},
  "geometry": {"coordinates":[16.2705020905,48.2011947632],"type":"Point"}
}