{
  "type": "Feature",
  "properties": {
    "addr:full":"Josefsdorf 2 Gro\u00df Gerungs Nieder\u00f6sterreich 3920",
    "addr:housenumber":"2",
    "addr:postcode":"3920",
    "addr:street":"Josefsdorf",
    "iso:country":"AT",
    "sg:address":"Josefsdorf 2",
    "sg:city":"Gro\u00df Gerungs",
    "sg:classifiers":[
        {
            "category":"Building & Trades",
            "subcategory":"Pest Control",
            "type":"Services"
        }
    ],
    "sg:phone":"+43 664 4002225",
    "sg:postcode":"3920",
    "sg:province":"Nieder\u00f6sterreich",
    "sg:tags":[
        "uninterruptible",
        "power",
        "supply",
        "accumulator",
        "ups",
        "unit"
    ],
    "sg:website":"servicetech.at",
    "wof:name":"Servicetech",
    "wof:placetype":"venue"
},
  "geometry": {"coordinates":[20.0779304504,45.3694000244],"type":"Point"}
}