{
  "type": "Feature",
  "properties": {
    "iso:country":"AT",
    "sg:address":"Schweningerg 10/1",
    "sg:city":"Schwechat",
    "sg:classifiers":[
        {
            "category":"Taxi",
            "type":"Transportation"
        }
    ],
    "sg:phone":"+43 4317 076565",
    "sg:postcode":"2320",
    "sg:province":"Nieder\u00f6sterreich",
    "sg:tags":[
        "personentransporte",
        "u"
    ],
    "wof:name":"GO Trans - Taxi u Mietauto",
    "wof:placetype":"venue"
},
  "geometry": {"coordinates":[16.477684021,48.1335144043],"type":"Point"}
}