{
  "type": "Feature",
  "properties": {
    "iso:country":"AT",
    "sg:address":"Eybnerstrasse 22",
    "sg:city":"St. P\u00f6lten",
    "sg:classifiers":[
        {
            "category":"Communications",
            "subcategory":"Television Station",
            "type":"Services"
        }
    ],
    "sg:phone":"+43 2742 366403",
    "sg:postcode":"3100",
    "sg:province":"Nieder\u00f6sterreich",
    "sg:tags":[
        "set",
        "radio",
        "cable",
        "antenna"
    ],
    "wof:name":"Karl-Heinz Enigl",
    "wof:placetype":"venue"
},
  "geometry": {"coordinates":[-76.07303619379999,41.7845001221],"type":"Point"}
}