{
  "type": "Feature",
  "properties": {
    "addr:full":"Bahng 46/5 Wiener Neustadt Nieder\u00f6sterreich 2700",
    "addr:housenumber":"46 / 5",
    "addr:postcode":"2700",
    "addr:street":"Bahng",
    "iso:country":"AT",
    "sg:address":"Bahng 46/5",
    "sg:city":"Wiener Neustadt",
    "sg:orig_category":"Yachtcharter",
    "sg:phone":"+43 4326 2228074",
    "sg:postcode":"2700",
    "sg:province":"Nieder\u00f6sterreich",
    "wof:name":"Hanakamp Andreas Yachting- u Segelwelt.at",
    "wof:placetype":"venue"
},
  "geometry": {"coordinates":[16.2366409302,47.8116416931],"type":"Point"}
}