{
  "type": "Feature",
  "properties": {
    "iso:country":"AT",
    "sg:address":"St Margarethen 156",
    "sg:city":"Jenbach",
    "sg:orig_category":"Musikgruppen",
    "sg:phone":"+43 5244 62432",
    "sg:postcode":"6200",
    "sg:province":"Tirol",
    "wof:name":"Almrauschklang",
    "wof:placetype":"venue"
},
  "geometry": {"coordinates":[11.7708826065,47.3827819824],"type":"Point"}
}