{
  "type": "Feature",
  "properties": {
    "addr:full":"Lammg 12 Wien Wien 1080",
    "addr:housenumber":"12",
    "addr:postcode":"1080",
    "addr:street":"Lammg",
    "iso:country":"AT",
    "sg:address":"Lammg 12",
    "sg:city":"Wien",
    "sg:orig_category":"Forschungsinstitute",
    "sg:phone":"+43 1 4028952",
    "sg:postcode":"1080",
    "sg:province":"Wien",
    "wof:name":"Forschungsgruppe Psychoanalyse",
    "wof:placetype":"venue"
},
  "geometry": {"coordinates":[16.3520755768,48.2131652832],"type":"Point"}
}