{
  "type": "Feature",
  "properties": {
    "addr:full":"Sternwaldstrasse 60 Haslach an der M\u00fchl Ober\u00f6sterreich 4170",
    "addr:housenumber":"60",
    "addr:postcode":"4170",
    "addr:street":"Sternwaldstrasse;Oberoesterreich",
    "iso:country":"AT",
    "sg:address":"Sternwaldstrasse 60",
    "sg:city":"Haslach an der M\u00fchl",
    "sg:classifiers":[
        {
            "category":"Home & Garden",
            "subcategory":"Home Furnishings",
            "type":"Retail Goods"
        }
    ],
    "sg:phone":"+43 7289 718880",
    "sg:postcode":"4170",
    "sg:province":"Ober\u00f6sterreich",
    "sg:tags":[
        "premise"
    ],
    "sg:website":"andex.at",
    "wof:name":"Tischlerei Andexlinger Ges.m.b.H.",
    "wof:placetype":"venue"
},
  "geometry": {"coordinates":[14.1033849716,48.5675315857],"type":"Point"}
}