{
  "type": "Feature",
  "properties": {
    "iso:country":"AT",
    "sg:address":"Stiftg 23",
    "sg:city":"Innsbruck",
    "sg:orig_category":"Tabaktrafiken",
    "sg:phone":"+43 512 575350",
    "sg:postcode":"6020",
    "sg:province":"Tirol",
    "wof:name":"Reinstadler Sonja",
    "wof:placetype":"venue"
},
  "geometry": {"coordinates":[11.3935604095,47.2672386169],"type":"Point"}
}