{
  "type": "Feature",
  "properties": {
    "addr:full":"Nr 122 Halbenrain Steiermark 8492",
    "addr:postcode":"8492",
    "addr:street":"Nr",
    "iso:country":"AT",
    "sg:address":"Nr 122",
    "sg:city":"Halbenrain",
    "sg:orig_category":"Autohandel",
    "sg:phone":"+43 4334 7621410",
    "sg:postcode":"8492",
    "sg:province":"Steiermark",
    "sg:website":"autoschaffer.at",
    "wof:name":"Autohaus Schaffer GmbH & Co KG",
    "wof:placetype":"venue"
},
  "geometry": {"coordinates":[15.9466428757,46.7218742371],"type":"Point"}
}