{
  "type": "Feature",
  "properties": {
    "addr:full":"Figulystr 30 Linz Ober\u00f6sterreich 4020",
    "addr:housenumber":"30",
    "addr:postcode":"4020",
    "addr:street":"Figulystr",
    "iso:country":"AT",
    "sg:address":"Figulystr 30",
    "sg:city":"Linz",
    "sg:orig_category":"Familien / Beratung",
    "sg:phone":"+43 732 669611",
    "sg:postcode":"4020",
    "sg:province":"Ober\u00f6sterreich",
    "wof:name":"Eltern-Kind-Zentrum Linz",
    "wof:placetype":"venue"
},
  "geometry": {"coordinates":[14.2870912552,48.2926712036],"type":"Point"}
}