{
  "type": "Feature",
  "properties": {
    "addr:full":"K\u00e4ferheimer Strasse 36 Wals Salzburg 5071",
    "addr:housenumber":"36",
    "addr:postcode":"5071",
    "addr:street":"Kaeferheimer Strasse;Salzburg",
    "iso:country":"AT",
    "sg:address":"K\u00e4ferheimer Strasse 36",
    "sg:city":"Wals",
    "sg:orig_category":"CarpenterS Work Supraregional",
    "sg:phone":"+43 662 850461",
    "sg:postcode":"5071",
    "sg:province":"Salzburg",
    "wof:name":"Josef Koch Zimmerei Ges.m.b.H. & Co KG",
    "wof:placetype":"venue"
},
  "geometry": {"coordinates":[12.9650602341,47.7890663147],"type":"Point"}
}