{
  "type": "Feature",
  "properties": {
    "iso:country":"AT",
    "sg:address":"Kulturhausstr 7",
    "sg:city":"Latschach ober dem Faaker See",
    "sg:orig_category":"Elektroinstallationsunternehmen",
    "sg:phone":"+43 4342 542651",
    "sg:postcode":"9582",
    "sg:province":"K\u00e4rnten",
    "wof:name":"Hassler Walter",
    "wof:placetype":"venue"
},
  "geometry": {"coordinates":[13.9216537476,46.5588226318],"type":"Point"}
}