{
  "type": "Feature",
  "properties": {
    "addr:full":"Otto Probst-Str 3 Wien Wien 1100",
    "addr:housenumber":"3",
    "addr:postcode":"1100",
    "addr:street":"Probst-Str",
    "iso:country":"AT",
    "sg:address":"Otto Probst-Str 3",
    "sg:city":"Wien",
    "sg:orig_category":"Friseure U Frisiersalons",
    "sg:phone":"+43 1 6161884",
    "sg:postcode":"1100",
    "sg:province":"Wien",
    "wof:name":"Hair & Style",
    "wof:placetype":"venue"
},
  "geometry": {"coordinates":[16.3550052643,48.1560668945],"type":"Point"}
}