{
  "type": "Feature",
  "properties": {
    "addr:full":"Nr 18 S\u00e4usenstein Nieder\u00f6sterreich 3374",
    "addr:postcode":"3374",
    "addr:street":"Nr 18 Saeusenstein",
    "iso:country":"AT",
    "sg:address":"Nr 18",
    "sg:city":"S\u00e4usenstein",
    "sg:classifiers":[
        {
            "category":"Home & Garden",
            "subcategory":"Garden Supply",
            "type":"Retail Goods"
        }
    ],
    "sg:phone":"+43 4374 1254650",
    "sg:postcode":"3374",
    "sg:province":"Nieder\u00f6sterreich",
    "sg:tags":[
        "schotter",
        "sand",
        "u"
    ],
    "wof:name":"Steurer Franz",
    "wof:placetype":"venue"
},
  "geometry": {"coordinates":[15.1166582108,48.1923294067],"type":"Point"}
}