{
  "type": "Feature",
  "properties": {
    "iso:country":"AT",
    "sg:address":"Vorstadt 33",
    "sg:city":"Hardegg",
    "sg:orig_category":"Polizei U Gendarmerie",
    "sg:phone":"+43 4359 1333413",
    "sg:postcode":"2082",
    "sg:province":"Nieder\u00f6sterreich",
    "wof:name":"Gendarmerie",
    "wof:placetype":"venue"
},
  "geometry": {"coordinates":[15.8594007492,48.8545608521],"type":"Point"}
}