{
  "type": "Feature",
  "properties": {
    "addr:full":"Schr\u00e4ndlg 50 Illmitz Burgenland 7142",
    "addr:housenumber":"50",
    "addr:postcode":"7142",
    "addr:street":"Schraendlg",
    "iso:country":"AT",
    "sg:address":"Schr\u00e4ndlg 50",
    "sg:city":"Illmitz",
    "sg:orig_category":"Rebschulen",
    "sg:phone":"+43 2175 3207",
    "sg:postcode":"7142",
    "sg:province":"Burgenland",
    "wof:name":"Gangl Josef",
    "wof:placetype":"venue"
},
  "geometry": {"coordinates":[16.7927932739,47.7554588318],"type":"Point"}
}