{
  "type": "Feature",
  "properties": {
    "addr:full":"Obergurgl Tirol 6456",
    "addr:postcode":"6456",
    "iso:country":"AT",
    "sg:city":"Obergurgl",
    "sg:classifiers":[
        {
            "category":"Taxi",
            "type":"Transportation"
        }
    ],
    "sg:phone":"+43 5256 22900",
    "sg:postcode":"6456",
    "sg:province":"Tirol",
    "sg:tags":[
        "personentransporte",
        "u"
    ],
    "wof:name":"Taxi Lenz",
    "wof:placetype":"venue"
},
  "geometry": {"coordinates":[11.0323400497,46.875579834],"type":"Point"}
}