{
  "type": "Feature",
  "properties": {
    "iso:country":"AT",
    "sg:address":"Wienerstrasse 101",
    "sg:city":"Linz",
    "sg:orig_category":"Shoe Polish And Care Agents",
    "sg:phone":"+43 732 657307",
    "sg:postcode":"4020",
    "sg:province":"Ober\u00f6sterreich",
    "wof:name":"Hans Socher",
    "wof:placetype":"venue"
},
  "geometry": {"coordinates":[14.3054838181,48.283531189],"type":"Point"}
}