{
  "type": "Feature",
  "properties": {
    "iso:country":"AT",
    "sg:address":"Hainbach 5",
    "sg:city":"Nu\u00dfdorf am Haunsberg",
    "sg:orig_category":"Tischlereien",
    "sg:phone":"+43 6276 22166",
    "sg:postcode":"5151",
    "sg:province":"Salzburg",
    "wof:name":"P\u00f6tzelsberger & Huber GmbH",
    "wof:placetype":"venue"
},
  "geometry": {"coordinates":[12.9873800278,47.9691810608],"type":"Point"}
}