{
  "type": "Feature",
  "properties": {
    "iso:country":"AT",
    "sg:address":"Sechshauser Str 122/16",
    "sg:city":"Wien",
    "sg:orig_category":"Installationsunternehmen",
    "sg:phone":"+43 4366 43001703",
    "sg:postcode":"1150",
    "sg:province":"Wien",
    "wof:name":"Macho Installationen",
    "wof:placetype":"venue"
},
  "geometry": {"coordinates":[16.3216266632,48.1862182617],"type":"Point"}
}