{
  "type": "Feature",
  "properties": {
    "iso:country":"AT",
    "sg:address":"Loeweg 8",
    "sg:city":"Wetzelsdorf",
    "sg:orig_category":"Volksschulen",
    "sg:phone":"+43 316 582224",
    "sg:postcode":"8052",
    "sg:province":"Steiermark",
    "wof:name":"Volksschule Peter Rosegger",
    "wof:placetype":"venue"
},
  "geometry": {"coordinates":[15.3939123154,47.0531616211],"type":"Point"}
}