{
  "type": "Feature",
  "properties": {
    "addr:full":"Konrad-Lorenz-Weg 3 Bad Tatzmannsdorf Burgenland 7431",
    "addr:housenumber":"3",
    "addr:postcode":"7431",
    "addr:street":"Konrad-Lorenz-Weg",
    "iso:country":"AT",
    "sg:address":"Konrad-Lorenz-Weg 3",
    "sg:city":"Bad Tatzmannsdorf",
    "sg:orig_category":"Appartements / Ferienwohnungen",
    "sg:phone":"+43 4333 538962",
    "sg:postcode":"7431",
    "sg:province":"Burgenland",
    "wof:name":"Kur- u Ferienbungalows Arkadenhof",
    "wof:placetype":"venue"
},
  "geometry": {"coordinates":[16.2292537689,47.3407669067],"type":"Point"}
}