{
  "type": "Feature",
  "properties": {
    "addr:full":"Hauptstr 18 Neudorf Nieder\u00f6sterreich 2135",
    "addr:housenumber":"18",
    "addr:postcode":"2135",
    "addr:street":"Hauptstr",
    "iso:country":"AT",
    "sg:address":"Hauptstr 18",
    "sg:city":"Neudorf",
    "sg:orig_category":"Lebensmittel / Einzelhandel",
    "sg:phone":"+43 2523 8203",
    "sg:postcode":"2135",
    "sg:province":"Nieder\u00f6sterreich",
    "wof:name":"Spar-Markt Schuster Herta",
    "wof:placetype":"venue"
},
  "geometry": {"coordinates":[16.4915943146,48.7205314636],"type":"Point"}
}