{
  "type": "Feature",
  "properties": {
    "iso:country":"AT",
    "sg:address":"Hauptpl 17",
    "sg:city":"Waidhofen an der Thaya",
    "sg:orig_category":"Blumeneinzelhandel",
    "sg:phone":"+43 4328 4220207",
    "sg:postcode":"3830",
    "sg:province":"Nieder\u00f6sterreich",
    "wof:name":"ROSENK\u00f6NIG Aichhorn Walter",
    "wof:placetype":"venue"
},
  "geometry": {"coordinates":[15.2860021591,48.8149909973],"type":"Point"}
}