{
  "type": "Feature",
  "properties": {
    "addr:full":"Hartwig Balzen-G 7/21 Wien Wien 1210",
    "addr:housenumber":"7 / 21",
    "addr:postcode":"1210",
    "addr:street":"Balzen-G",
    "iso:country":"AT",
    "sg:address":"Hartwig Balzen-G 7/21",
    "sg:city":"Wien",
    "sg:orig_category":"Schlossereien",
    "sg:phone":"+43 1 7865003",
    "sg:postcode":"1210",
    "sg:province":"Wien",
    "wof:name":"Express Montageschlosser - Sonak Christian",
    "wof:placetype":"venue"
},
  "geometry": {"coordinates":[16.4429721832,48.2837715149],"type":"Point"}
}