{
  "type": "Feature",
  "properties": {
    "addr:full":"Hauptpl 34 Deutschlandsberg Steiermark 8530",
    "addr:housenumber":"34",
    "addr:postcode":"8530",
    "addr:street":"Hauptpl",
    "iso:country":"AT",
    "sg:address":"Hauptpl 34",
    "sg:city":"Deutschlandsberg",
    "sg:orig_category":"Tourismusinformation U -Organisationen",
    "sg:phone":"+43 4334 627520",
    "sg:postcode":"8530",
    "sg:province":"Steiermark",
    "wof:name":"Tourismusverband Deutschlandsberg - Ferienregion Schilcherheimat",
    "wof:placetype":"venue"
},
  "geometry": {"coordinates":[15.2119274139,46.8143844604],"type":"Point"}
}