{
  "type": "Feature",
  "properties": {
    "iso:country":"AT",
    "sg:address":"Trattfelderstr 7",
    "sg:city":"Stra\u00dfgang",
    "sg:orig_category":"Ingenieurkonsulenten / Zivilingenieure",
    "sg:phone":"+43 316 281642",
    "sg:postcode":"8054",
    "sg:province":"Steiermark",
    "wof:name":"Ahmadi Fakhrad-din Dipl-Ing",
    "wof:placetype":"venue"
},
  "geometry": {"coordinates":[15.4088945389,47.03540802],"type":"Point"}
}