{
  "type": "Feature",
  "properties": {
    "addr:full":"Nr 128 Filzmoos Salzburg 5532",
    "addr:postcode":"5532",
    "addr:street":"Nr;Filzmoos",
    "iso:country":"AT",
    "sg:address":"Nr 128",
    "sg:city":"Filzmoos",
    "sg:orig_category":"Tischlereien",
    "sg:phone":"+43 6453 82830",
    "sg:postcode":"5532",
    "sg:province":"Salzburg",
    "wof:name":"Kirchgasser & S\u00f6hne Tischlerei GesmbH",
    "wof:placetype":"venue"
},
  "geometry": {"coordinates":[13.5202980042,47.4332199097],"type":"Point"}
}