{
  "type": "Feature",
  "properties": {
    "addr:full":"Fl\u00f6tzerweg 156 Linz Ober\u00f6sterreich 4030",
    "addr:housenumber":"156",
    "addr:postcode":"4030",
    "iso:country":"AT",
    "sg:address":"Fl\u00f6tzerweg 156",
    "sg:city":"Linz",
    "sg:orig_category":"Maler, Anstreicher U Lackierer",
    "sg:phone":"+43 4373 2374450",
    "sg:postcode":"4030",
    "sg:province":"Ober\u00f6sterreich",
    "wof:name":"Weilguni Gerhard",
    "wof:placetype":"venue"
},
  "geometry": {"coordinates":[14.2792186737,48.2480010986],"type":"Point"}
}