{
  "type": "Feature",
  "properties": {
    "addr:full":"Jedleseer Str 73 Wien Wien 1210",
    "addr:postcode":"1210",
    "addr:street":"Str 73",
    "iso:country":"AT",
    "sg:address":"Jedleseer Str 73",
    "sg:city":"Wien",
    "sg:classifiers":[
        {
            "category":"Restaurant",
            "type":"Food & Drink"
        }
    ],
    "sg:phone":"+43 1 2787754",
    "sg:postcode":"1210",
    "sg:province":"Wien",
    "sg:tags":[
        "pizzeria"
    ],
    "wof:name":"La Cinar",
    "wof:placetype":"venue"
},
  "geometry": {"coordinates":[16.3872013092,48.2618675232],"type":"Point"}
}