{
  "type": "Feature",
  "properties": {
    "iso:country":"AT",
    "sg:address":"Kreuzg 9",
    "sg:city":"Zell am See",
    "sg:orig_category":"Rauchfangkehrer",
    "sg:phone":"+43 6542 728080",
    "sg:postcode":"5700",
    "sg:province":"Salzburg",
    "wof:name":"Gadenst\u00e4tter Werner",
    "wof:placetype":"venue"
},
  "geometry": {"coordinates":[12.7991123199,47.3238182068],"type":"Point"}
}