{
  "type": "Feature",
  "properties": {
    "addr:full":"Troststr 83 Wien Wien 1100",
    "addr:housenumber":"83",
    "addr:postcode":"1100",
    "addr:street":"Troststr",
    "iso:country":"AT",
    "sg:address":"Troststr 83",
    "sg:city":"Wien",
    "sg:orig_category":"Friseure U Frisiersalons",
    "sg:phone":"+43 1 6076019",
    "sg:postcode":"1100",
    "sg:province":"Wien",
    "wof:name":"Schmerda KG Alleininhaber Dipl-Ing Stefan Sauerwein",
    "wof:placetype":"venue"
},
  "geometry": {"coordinates":[16.3617897034,48.170337677],"type":"Point"}
}