{
  "type": "Feature",
  "properties": {
    "addr:full":"Gutheil-Schoder-G Wien Wien 1100",
    "addr:postcode":"1100",
    "iso:country":"AT",
    "sg:address":"Gutheil-Schoder-G",
    "sg:city":"Wien",
    "sg:orig_category":"Lebensmittel / Einzelhandel",
    "sg:phone":"+43 1 6656900",
    "sg:postcode":"1100",
    "sg:province":"Wien",
    "wof:name":"Hofer KG",
    "wof:placetype":"venue"
},
  "geometry": {"coordinates":[16.339471817,48.1631202698],"type":"Point"}
}