{
  "type": "Feature",
  "properties": {
    "addr:full":"Radlach 6 Steinfeld K\u00e4rnten 9754",
    "addr:housenumber":"6",
    "addr:postcode":"9754",
    "addr:street":"Radlach",
    "iso:country":"AT",
    "sg:address":"Radlach 6",
    "sg:city":"Steinfeld",
    "sg:orig_category":"Pensionen / Privatzimmer",
    "sg:phone":"+43 4717 345",
    "sg:postcode":"9754",
    "sg:province":"K\u00e4rnten",
    "wof:name":"Haus Sagmeister",
    "wof:placetype":"venue"
},
  "geometry": {"coordinates":[13.2206459045,46.7519187927],"type":"Point"}
}