{
  "type": "Feature",
  "properties": {
    "addr:full":"Stelzen 61 Lohnsburg am Kobernau\u00dferwald Ober\u00f6sterreich 4923",
    "addr:housenumber":"61",
    "addr:postcode":"4923",
    "addr:street":"Stelzen",
    "iso:country":"AT",
    "sg:address":"Stelzen 61",
    "sg:city":"Lohnsburg am Kobernau\u00dferwald",
    "sg:orig_category":"Fenster",
    "sg:phone":"+43 4377 542404",
    "sg:postcode":"4923",
    "sg:province":"Ober\u00f6sterreich",
    "wof:name":"Krautgartner Leopold",
    "wof:placetype":"venue"
},
  "geometry": {"coordinates":[13.3577833176,48.110824585],"type":"Point"}
}