{
  "type": "Feature",
  "properties": {
    "addr:full":"Zanklstr 24 G\u00f6sting Steiermark 8051",
    "addr:housenumber":"24",
    "addr:postcode":"8051",
    "addr:street":"Zanklstr",
    "iso:country":"AT",
    "sg:address":"Zanklstr 24",
    "sg:city":"G\u00f6sting",
    "sg:orig_category":"Feinkost",
    "sg:phone":"+43 316 684140",
    "sg:postcode":"8051",
    "sg:province":"Steiermark",
    "wof:name":"Ranftl Herbert",
    "wof:placetype":"venue"
},
  "geometry": {"coordinates":[15.4089813232,47.0949172974],"type":"Point"}
}