{
  "type": "Feature",
  "properties": {
    "addr:full":"Cumberlandstr 25/4 Wien Wien 1140",
    "addr:housenumber":"25 / 4",
    "addr:postcode":"1140",
    "addr:street":"Cumberlandstr",
    "iso:country":"AT",
    "sg:address":"Cumberlandstr 25/4",
    "sg:city":"Wien",
    "sg:orig_category":"Werbegestalter",
    "sg:phone":"+43 664 1855833",
    "sg:postcode":"1140",
    "sg:province":"Wien",
    "wof:name":"Sch\u00f6nfelder Silvia",
    "wof:placetype":"venue"
},
  "geometry": {"coordinates":[16.3082141876,48.1916847229],"type":"Point"}
}