{
  "type": "Feature",
  "properties": {
    "addr:full":"Hauptstr 87 Frankenmarkt Ober\u00f6sterreich 4890",
    "addr:housenumber":"87",
    "addr:postcode":"4890",
    "addr:street":"Hauptstr;Oberoesterreich",
    "iso:country":"AT",
    "sg:address":"Hauptstr 87",
    "sg:city":"Frankenmarkt",
    "sg:orig_category":"Dachdeckereien",
    "sg:phone":"+43 76846377",
    "sg:postcode":"4890",
    "sg:province":"Ober\u00f6sterreich",
    "wof:name":"Walbergs & Lechner OHG",
    "wof:placetype":"venue"
},
  "geometry": {"coordinates":[13.4175386429,47.9851417542],"type":"Point"}
}