{
  "type": "Feature",
  "properties": {
    "addr:full":"Allendepl 2 Linz Ober\u00f6sterreich 4030",
    "addr:housenumber":"2",
    "addr:postcode":"4030",
    "addr:street":"Allendepl",
    "iso:country":"AT",
    "sg:address":"Allendepl 2",
    "sg:city":"Linz",
    "sg:orig_category":"Kinderbetreuung",
    "sg:phone":"+43 732 311743",
    "sg:postcode":"4030",
    "sg:province":"Ober\u00f6sterreich",
    "wof:name":"Hort d Stadt Linz",
    "wof:placetype":"venue"
},
  "geometry": {"coordinates":[14.3101329803,48.2500991821],"type":"Point"}
}