{
  "type": "Feature",
  "properties": {
    "addr:full":"Nr 7 Bischofstetten Nieder\u00f6sterreich 3232",
    "addr:postcode":"3232",
    "addr:street":"Nr;Niederoesterreich",
    "iso:country":"AT",
    "sg:address":"Nr 7",
    "sg:city":"Bischofstetten",
    "sg:orig_category":"Tischlereien",
    "sg:phone":"+43 2748 8003",
    "sg:postcode":"3232",
    "sg:province":"Nieder\u00f6sterreich",
    "wof:name":"Hellmer Johann",
    "wof:placetype":"venue"
},
  "geometry": {"coordinates":[15.4687490463,48.1223945618],"type":"Point"}
}