{
  "type": "Feature",
  "properties": {
    "addr:full":"Feldkirchner Str 93 Klagenfurt K\u00e4rnten 9020",
    "addr:housenumber":"93",
    "addr:postcode":"9020",
    "addr:street":"Str;Kaernten",
    "iso:country":"AT",
    "sg:address":"Feldkirchner Str 93",
    "sg:city":"Klagenfurt",
    "sg:orig_category":"Tabaktrafiken",
    "sg:phone":"+43 4346 3418673",
    "sg:postcode":"9020",
    "sg:province":"K\u00e4rnten",
    "wof:name":"Pachernig Andrea",
    "wof:placetype":"venue"
},
  "geometry": {"coordinates":[14.294383049,46.636554718],"type":"Point"}
}