{
  "type": "Feature",
  "properties": {
    "addr:full":"Hauptstr 16 Lackendorf Burgenland 7321",
    "addr:housenumber":"16",
    "addr:postcode":"7321",
    "addr:street":"Hauptstr",
    "iso:country":"AT",
    "sg:address":"Hauptstr 16",
    "sg:city":"Lackendorf",
    "sg:orig_category":"Volksschulen",
    "sg:phone":"+43 4326 197539",
    "sg:postcode":"7321",
    "sg:province":"Burgenland",
    "wof:name":"Volksschule",
    "wof:placetype":"venue"
},
  "geometry": {"coordinates":[16.5020332336,47.5739212036],"type":"Point"}
}