{
  "type": "Feature",
  "properties": {
    "addr:full":"Burgenlandstr 15 Innsbruck Tirol 6020",
    "addr:housenumber":"15",
    "addr:postcode":"6020",
    "addr:street":"Burgenlandstr;Tirol",
    "iso:country":"AT",
    "sg:address":"Burgenlandstr 15",
    "sg:city":"Innsbruck",
    "sg:orig_category":"Wach- U Sicherheitsunternehmen",
    "sg:phone":"+43 4351 2396464",
    "sg:postcode":"6020",
    "sg:province":"Tirol",
    "wof:name":"Dietrich-St\u00e4rz Transportbegleitung",
    "wof:placetype":"venue"
},
  "geometry": {"coordinates":[11.4181909561,47.2600898743],"type":"Point"}
}