{
  "type": "Feature",
  "properties": {
    "addr:full":"Untere Dorfstr 28 Serfaus Tirol 6534",
    "addr:housenumber":"28",
    "addr:postcode":"6534",
    "addr:street":"Untere Dorfstr;Tirol",
    "iso:country":"AT",
    "sg:address":"Untere Dorfstr 28",
    "sg:city":"Serfaus",
    "sg:orig_category":"Restaurants: Griechisch",
    "sg:phone":"+43 5476 20128",
    "sg:postcode":"6534",
    "sg:province":"Tirol",
    "wof:name":"Restaurant Elgi",
    "wof:placetype":"venue"
},
  "geometry": {"coordinates":[10.6055011749,47.038269043],"type":"Point"}
}