{
  "type": "Feature",
  "properties": {
    "addr:full":"Badner Str 3 Baden Nieder\u00f6sterreich 2500",
    "addr:housenumber":"3",
    "addr:postcode":"2500",
    "addr:street":"Str;Niederoesterreich",
    "iso:country":"AT",
    "sg:address":"Badner Str 3",
    "sg:city":"Baden",
    "sg:orig_category":"Werbegrafik- U Grafik-Design",
    "sg:phone":"+43 4322 5224495",
    "sg:postcode":"2500",
    "sg:province":"Nieder\u00f6sterreich",
    "wof:name":"Moravec Robert",
    "wof:placetype":"venue"
},
  "geometry": {"coordinates":[16.1735877991,48.0373687744],"type":"Point"}
}