{
  "type": "Feature",
  "properties": {
    "addr:full":"Marktstr 3 Grimmenstein Nieder\u00f6sterreich 2840",
    "addr:housenumber":"3",
    "addr:postcode":"2840",
    "addr:street":"Marktstr",
    "iso:country":"AT",
    "sg:address":"Marktstr 3",
    "sg:city":"Grimmenstein",
    "sg:orig_category":"Baumeister",
    "sg:phone":"+43 2644 7258",
    "sg:postcode":"2840",
    "sg:province":"Nieder\u00f6sterreich",
    "wof:name":"Schwarz Emma",
    "wof:placetype":"venue"
},
  "geometry": {"coordinates":[16.1247596741,47.6146087646],"type":"Point"}
}