{
  "type": "Feature",
  "properties": {
    "iso:country":"AT",
    "sg:address":"Nr 278",
    "sg:city":"Neukirchen am Gro\u00dfvenediger",
    "sg:classifiers":[
        {
            "category":"Travel",
            "subcategory":"Hotels & Motels",
            "type":"Entertainment"
        }
    ],
    "sg:phone":"+43 6565 64800",
    "sg:postcode":"5741",
    "sg:province":"Salzburg",
    "wof:name":"Hotel Hubertus",
    "wof:placetype":"venue"
},
  "geometry": {"coordinates":[12.3227596283,47.261390686],"type":"Point"}
}