{
  "type": "Feature",
  "properties": {
    "addr:full":"Seestr 6 Seekirchen am Wallersee Salzburg 5201",
    "addr:housenumber":"6",
    "addr:postcode":"5201",
    "addr:street":"Seestr;Salzburg",
    "iso:country":"AT",
    "sg:address":"Seestr 6",
    "sg:city":"Seekirchen am Wallersee",
    "sg:orig_category":"Segel- U Seefahrtschulen",
    "sg:phone":"+43 650 3000731",
    "sg:postcode":"5201",
    "sg:province":"Salzburg",
    "wof:name":"Segelschule Wallersee M\u00fcller Wolfgang",
    "wof:placetype":"venue"
},
  "geometry": {"coordinates":[13.1428194046,47.9023323059],"type":"Point"}
}