{
  "type": "Feature",
  "properties": {
    "addr:full":"Riedg 10b Dornbirn Vorarlberg 6850",
    "addr:housenumber":"10b",
    "addr:postcode":"6850",
    "addr:street":"Riedg",
    "iso:country":"AT",
    "sg:address":"Riedg 10b",
    "sg:city":"Dornbirn",
    "sg:orig_category":"Behinderungen / Leben Mit Behinderungen",
    "sg:phone":"+43 5572 39475911",
    "sg:postcode":"6850",
    "sg:province":"Vorarlberg",
    "wof:name":"Lebenshilfe Dornbirn - Werkst\u00e4tten",
    "wof:placetype":"venue"
},
  "geometry": {"coordinates":[9.7437801361,47.4131889343],"type":"Point"}
}