{
  "type": "Feature",
  "properties": {
    "addr:full":"Badner Str 49 Eichgraben Nieder\u00f6sterreich 3032",
    "addr:housenumber":"49",
    "addr:postcode":"3032",
    "addr:street":"Str",
    "iso:country":"AT",
    "sg:address":"Badner Str 49",
    "sg:city":"Eichgraben",
    "sg:orig_category":"Massagen",
    "sg:phone":"+43 2773 42475",
    "sg:postcode":"3032",
    "sg:province":"Nieder\u00f6sterreich",
    "wof:name":"Gaisbauer Peter",
    "wof:placetype":"venue"
},
  "geometry": {"coordinates":[15.976061821,48.1822891235],"type":"Point"}
}