{
  "type": "Feature",
  "properties": {
    "addr:full":"Schmittenstr 16 Zell am See Salzburg 5700",
    "addr:housenumber":"16",
    "addr:postcode":"5700",
    "addr:street":"Schmittenstr;Salzburg",
    "iso:country":"AT",
    "sg:address":"Schmittenstr 16",
    "sg:city":"Zell am See",
    "sg:orig_category":"Bauunternehmen",
    "sg:phone":"+43 4365 42723780",
    "sg:postcode":"5700",
    "sg:province":"Salzburg",
    "wof:name":"Wildbach- u Lawinenverbauung",
    "wof:placetype":"venue"
},
  "geometry": {"coordinates":[12.7930459976,47.3242835999],"type":"Point"}
}