{
  "type": "Feature",
  "properties": {
    "addr:full":"Nr 13 Rosegg K\u00e4rnten 9232",
    "addr:postcode":"9232",
    "addr:street":"Nr 13;Kaernten",
    "iso:country":"AT",
    "sg:address":"Nr 13",
    "sg:city":"Rosegg",
    "sg:orig_category":"Tischlereien",
    "sg:phone":"+43 4274 45060",
    "sg:postcode":"9232",
    "sg:province":"K\u00e4rnten",
    "wof:name":"Heregger Manfred",
    "wof:placetype":"venue"
},
  "geometry": {"coordinates":[14.0191602707,46.5909347534],"type":"Point"}
}