{
  "type": "Feature",
  "properties": {
    "addr:full":"Braunauer Str 1 Ried im Innkreis Ober\u00f6sterreich 4910",
    "addr:housenumber":"1",
    "addr:postcode":"4910",
    "addr:street":"Str",
    "iso:country":"AT",
    "sg:address":"Braunauer Str 1",
    "sg:city":"Ried im Innkreis",
    "sg:orig_category":"Textilreinigung",
    "sg:phone":"+43 7752 820640",
    "sg:postcode":"4910",
    "sg:province":"Ober\u00f6sterreich",
    "wof:name":"Leitgeb Gerhard Ing",
    "wof:placetype":"venue"
},
  "geometry": {"coordinates":[13.4836702347,48.2060279846],"type":"Point"}
}