{
  "type": "Feature",
  "properties": {
    "iso:country":"AT",
    "sg:address":"Dr.-Sommer-Weg 9",
    "sg:city":"Bad Deutsch Altenburg",
    "sg:orig_category":"Rettungsdienste",
    "sg:phone":"+43 4317 678899",
    "sg:postcode":"2405",
    "sg:province":"Nieder\u00f6sterreich",
    "wof:name":"Gr\u00fcnes Kreuz Rettungs- u Krankentransporte - Rettungsstelle Bad Deutsch Altenburg",
    "wof:placetype":"venue"
},
  "geometry": {"coordinates":[16.9099235535,48.1350021362],"type":"Point"}
}