{
  "type": "Feature",
  "properties": {
    "addr:full":"Linzer Str 5 Amstetten Nieder\u00f6sterreich 3300",
    "addr:housenumber":"5",
    "addr:postcode":"3300",
    "addr:street":"Linzer Str;Niederoesterreich",
    "iso:country":"AT",
    "sg:address":"Linzer Str 5",
    "sg:city":"Amstetten",
    "sg:orig_category":"Versicherungsunternehmen",
    "sg:phone":"+43 7472 620610",
    "sg:postcode":"3300",
    "sg:province":"Nieder\u00f6sterreich",
    "wof:name":"Allianz Elementar Versicherungs-AG",
    "wof:placetype":"venue"
},
  "geometry": {"coordinates":[14.8706989288,48.1242179871],"type":"Point"}
}