{
  "type": "Feature",
  "properties": {
    "addr:full":"Alte Landstr 29 Bludenz Vorarlberg 6700",
    "addr:housenumber":"29",
    "addr:postcode":"6700",
    "addr:street":"Alte Landstr",
    "iso:country":"AT",
    "sg:address":"Alte Landstr 29",
    "sg:city":"Bludenz",
    "sg:orig_category":"Unternehmensberatung",
    "sg:phone":"+43 4355 526568910",
    "sg:postcode":"6700",
    "sg:province":"Vorarlberg",
    "wof:name":"CS Consulting and Trading GmbH",
    "wof:placetype":"venue"
},
  "geometry": {"coordinates":[9.8145132065,47.1606941223],"type":"Point"}
}