{
  "type": "Feature",
  "properties": {
    "addr:full":"Bienensteinstr. 13 Bruck an der Mur Steiermark 8600",
    "addr:housenumber":"13",
    "addr:postcode":"8600",
    "addr:street":"Bienensteinstr.",
    "iso:country":"AT",
    "sg:address":"Bienensteinstr. 13",
    "sg:city":"Bruck an der Mur",
    "sg:classifiers":[
        {
            "category":"Food & Beverages",
            "subcategory":"Groceries & Convenience Stores",
            "type":"Retail Goods"
        }
    ],
    "sg:phone":"+43 4338 62519650",
    "sg:postcode":"8600",
    "sg:province":"Steiermark",
    "sg:tags":[
        "drink"
    ],
    "wof:name":"A HAUSMANN",
    "wof:placetype":"venue"
},
  "geometry": {"coordinates":[15.2787847519,47.4078712463],"type":"Point"}
}