{
  "type": "Feature",
  "properties": {
    "addr:full":"Wr Neust\u00e4dter Str 120 Lanzenkirchen Nieder\u00f6sterreich 2821",
    "addr:housenumber":"120",
    "addr:postcode":"2821",
    "addr:street":"Str;Niederoesterreich",
    "iso:country":"AT",
    "sg:address":"Wr Neust\u00e4dter Str 120",
    "sg:city":"Lanzenkirchen",
    "sg:orig_category":"Tankstellen",
    "sg:phone":"+43 2627 45290",
    "sg:postcode":"2821",
    "sg:province":"Nieder\u00f6sterreich",
    "wof:name":"BP Austria Marketing GmbH",
    "wof:placetype":"venue"
},
  "geometry": {"coordinates":[16.2391223907,47.7426261902],"type":"Point"}
}