{
  "type": "Feature",
  "properties": {
    "addr:full":"Wiener Str 62 Neusiedl am See Burgenland 7100",
    "addr:housenumber":"62",
    "addr:postcode":"7100",
    "iso:country":"AT",
    "sg:address":"Wiener Str 62",
    "sg:city":"Neusiedl am See",
    "sg:orig_category":"Reitsportartikel",
    "sg:phone":"+43 4321 678806",
    "sg:postcode":"7100",
    "sg:province":"Burgenland",
    "wof:name":"Jagd + Reitsport Wasserscheid",
    "wof:placetype":"venue"
},
  "geometry": {"coordinates":[16.8365936279,47.9559860229],"type":"Point"}
}