{
  "type": "Feature",
  "properties": {
    "addr:full":"Neufahrerg 130 Linz Ober\u00f6sterreich 4040",
    "addr:housenumber":"130",
    "addr:postcode":"4040",
    "iso:country":"AT",
    "sg:address":"Neufahrerg 130",
    "sg:city":"Linz",
    "sg:orig_category":"Friseure U Frisiersalons",
    "sg:phone":"+43 664 3454326",
    "sg:postcode":"4040",
    "sg:province":"Ober\u00f6sterreich",
    "wof:name":"Buraletti Alexandra - Mobilfriseur",
    "wof:placetype":"venue"
},
  "geometry": {"coordinates":[14.293422699,48.3442573547],"type":"Point"}
}