{
  "type": "Feature",
  "properties": {
    "addr:full":"Technikerstr 44 Innsbruck Tirol 6020",
    "addr:housenumber":"44",
    "addr:postcode":"6020",
    "addr:street":"Technikerstr;Tirol",
    "iso:country":"AT",
    "sg:address":"Technikerstr 44",
    "sg:city":"Innsbruck",
    "sg:orig_category":"Tabaktrafiken",
    "sg:phone":"+43 512 294423",
    "sg:postcode":"6020",
    "sg:province":"Tirol",
    "wof:name":"Schaffer B & Co KG",
    "wof:placetype":"venue"
},
  "geometry": {"coordinates":[11.3449497223,47.2653808594],"type":"Point"}
}