{
  "type": "Feature",
  "properties": {
    "addr:full":"Obere Hauptstr 4/Rathaus Kohfidisch Burgenland 7512",
    "addr:housenumber":"4 / rathaus",
    "addr:postcode":"7512",
    "addr:street":"Obere Hauptstr",
    "iso:country":"AT",
    "sg:address":"Obere Hauptstr 4/Rathaus",
    "sg:city":"Kohfidisch",
    "sg:orig_category":"Banken U Sparkassen",
    "sg:phone":"+43 5 050537640",
    "sg:postcode":"7512",
    "sg:province":"Burgenland",
    "wof:name":"Bank Austria Creditanstalt AG",
    "wof:placetype":"venue"
},
  "geometry": {"coordinates":[16.3575592041,47.1757698059],"type":"Point"}
}