{
  "type": "Feature",
  "properties": {
    "addr:full":"Tiroler Str 25 Kirchbichl Tirol 6322",
    "addr:postcode":"6322",
    "addr:street":"Str 25;Tirol",
    "iso:country":"AT",
    "sg:address":"Tiroler Str 25",
    "sg:city":"Kirchbichl",
    "sg:orig_category":"Banken U Sparkassen",
    "sg:phone":"+43 5332 87406",
    "sg:postcode":"6322",
    "sg:province":"Tirol",
    "wof:name":"Sparkasse Kufstein Tiroler Sparkasse von 1877",
    "wof:placetype":"venue"
},
  "geometry": {"coordinates":[12.0855712891,47.5112304688],"type":"Point"}
}