{
  "type": "Feature",
  "properties": {
    "addr:full":"Meraner Str. 9 Innsbruck Tirol 6020",
    "addr:housenumber":"9",
    "addr:postcode":"6020",
    "addr:street":"Str.;Tirol",
    "iso:country":"AT",
    "sg:address":"Meraner Str. 9",
    "sg:city":"Innsbruck",
    "sg:classifiers":[
        {
            "category":"Shopping",
            "subcategory":"Clothing, Apparel, & Fashions",
            "type":"Retail Goods"
        }
    ],
    "sg:phone":"+43 4351 2581443",
    "sg:postcode":"6020",
    "sg:province":"Tirol",
    "sg:tags":[
        "clothes"
    ],
    "wof:name":"HAIDEGGER GESMBH & CO KG",
    "wof:placetype":"venue"
},
  "geometry": {"coordinates":[11.3967351913,47.2652015686],"type":"Point"}
}