{
  "type": "Feature",
  "properties": {
    "addr:full":"Nr 51 Klagenfurt-Viktring K\u00e4rnten 9073",
    "addr:postcode":"9073",
    "addr:street":"Nr 51 Klagenfurt-Viktring Kaernten",
    "iso:country":"AT",
    "sg:address":"Nr 51",
    "sg:city":"Klagenfurt-Viktring",
    "sg:orig_category":"Werbeagenturen",
    "sg:phone":"+43 4220 51000",
    "sg:postcode":"9073",
    "sg:province":"K\u00e4rnten",
    "wof:name":"Werbeagentur Hitzenhammer KEG",
    "wof:placetype":"venue"
},
  "geometry": {"coordinates":[14.2700395584,46.5941810608],"type":"Point"}
}