{
  "type": "Feature",
  "properties": {
    "addr:full":"Gumppstr 71 Innsbruck Tirol 6020",
    "addr:housenumber":"71",
    "addr:postcode":"6020",
    "addr:street":"Gumppstr;Tirol",
    "iso:country":"AT",
    "sg:address":"Gumppstr 71",
    "sg:city":"Innsbruck",
    "sg:orig_category":"Lebens- U Sozialberatung",
    "sg:phone":"+43 4369 910587413",
    "sg:postcode":"6020",
    "sg:province":"Tirol",
    "wof:name":"Steixner Andr\u00e4 Dr",
    "wof:placetype":"venue"
},
  "geometry": {"coordinates":[11.4187908173,47.266620636],"type":"Point"}
}