{
  "type": "Feature",
  "properties": {
    "addr:full":"Achenweg 102 Kirchberg in Tirol Tirol 6365",
    "addr:housenumber":"102",
    "addr:postcode":"6365",
    "addr:street":"Achenweg;Tirol",
    "iso:country":"AT",
    "sg:address":"Achenweg 102",
    "sg:city":"Kirchberg in Tirol",
    "sg:orig_category":"Massagen",
    "sg:phone":"+43 664 1001005",
    "sg:postcode":"6365",
    "sg:province":"Tirol",
    "wof:name":"Wimmer Thomas",
    "wof:placetype":"venue"
},
  "geometry": {"coordinates":[12.3149614334,47.4314346313],"type":"Point"}
}