{
  "type": "Feature",
  "properties": {
    "addr:full":"Josef-Pock-Str 3 G\u00f6sting Steiermark 8051",
    "addr:housenumber":"3",
    "addr:postcode":"8051",
    "addr:street":"Josef-Pock-Str",
    "iso:country":"AT",
    "sg:address":"Josef-Pock-Str 3",
    "sg:city":"G\u00f6sting",
    "sg:orig_category":"Autoreparatur",
    "sg:phone":"+43 316 570256",
    "sg:postcode":"8051",
    "sg:province":"Steiermark",
    "wof:name":"Auto Achatz OEG",
    "wof:placetype":"venue"
},
  "geometry": {"coordinates":[15.4102888107,47.0884742737],"type":"Point"}
}