{
  "type": "Feature",
  "properties": {
    "iso:country":"AT",
    "sg:address":"Lambachstr 4",
    "sg:city":"Kindberg",
    "sg:orig_category":"Feuerwehren",
    "sg:phone":"+43 3865 3011",
    "sg:postcode":"8652",
    "sg:province":"Steiermark",
    "wof:name":"Freiwillige Feuerwehr Hadersdorf",
    "wof:placetype":"venue"
},
  "geometry": {"coordinates":[15.4102191925,47.4949645996],"type":"Point"}
}