{
  "type": "Feature",
  "properties": {
    "iso:country":"AT",
    "sg:address":"Wohlmutstr 22",
    "sg:city":"Wien",
    "sg:orig_category":"Behinderungen / Leben Mit Behinderungen",
    "sg:phone":"+43 1 7208317",
    "sg:postcode":"1020",
    "sg:province":"Wien",
    "wof:name":"Jugend am Werk",
    "wof:placetype":"venue"
},
  "geometry": {"coordinates":[16.4033622742,48.2191505432],"type":"Point"}
}