{
  "type": "Feature",
  "properties": {
    "addr:full":"Nr 5 Obdach Steiermark 8742",
    "addr:postcode":"8742",
    "addr:street":"Nr",
    "iso:country":"AT",
    "sg:address":"Nr 5",
    "sg:city":"Obdach",
    "sg:orig_category":"Holzhandel",
    "sg:phone":"+43 4335 7836536",
    "sg:postcode":"8742",
    "sg:province":"Steiermark",
    "sg:website":"holzmarktpabst.at",
    "wof:name":"Pabst Holzmarkt HolzhandelsgesmbH",
    "wof:placetype":"venue"
},
  "geometry": {"coordinates":[14.6953725815,47.0679969788],"type":"Point"}
}