{
  "type": "Feature",
  "properties": {
    "iso:country":"AT",
    "sg:address":"Franz-Samwald-Strasse 11",
    "sg:city":"Ternitz",
    "sg:classifiers":[
        {
            "category":"Utilities",
            "subcategory":"Natural Gas",
            "type":"Services"
        }
    ],
    "sg:phone":"+43 2630 38682",
    "sg:postcode":"2630",
    "sg:province":"Nieder\u00f6sterreich",
    "sg:tags":[
        "bathroom",
        "cock",
        "fitting"
    ],
    "wof:name":"Max Sprinschitz",
    "wof:placetype":"venue"
},
  "geometry": {"coordinates":[16.0149402618,47.7022285461],"type":"Point"}
}