{
  "type": "Feature",
  "properties": {
    "addr:full":"Liftstr 1 Reichenfels K\u00e4rnten 9463",
    "addr:housenumber":"1",
    "addr:postcode":"9463",
    "addr:street":"Liftstr;Kaernten",
    "iso:country":"AT",
    "sg:address":"Liftstr 1",
    "sg:city":"Reichenfels",
    "sg:orig_category":"Gemeinden",
    "sg:phone":"+43 4359 22210",
    "sg:postcode":"9463",
    "sg:province":"K\u00e4rnten",
    "wof:name":"Gemeindeamt Reichenfels",
    "wof:placetype":"venue"
},
  "geometry": {"coordinates":[14.7450275421,47.0070495605],"type":"Point"}
}