{
  "type": "Feature",
  "properties": {
    "addr:full":"Vollerer Str 30 St. Georgen Salzburg 5113",
    "addr:housenumber":"30",
    "addr:postcode":"5113",
    "addr:street":"Str",
    "iso:country":"AT",
    "sg:address":"Vollerer Str 30",
    "sg:city":"St. Georgen",
    "sg:orig_category":"Handelsagenturen",
    "sg:phone":"+43 4362 725867",
    "sg:postcode":"5113",
    "sg:province":"Salzburg",
    "wof:name":"Erlacher Friedrich",
    "wof:placetype":"venue"
},
  "geometry": {"coordinates":[12.9125099182,47.9605484009],"type":"Point"}
}