{
  "type": "Feature",
  "properties": {
    "addr:full":"Ressavarstr 4 Hartberg Steiermark 8230",
    "addr:housenumber":"4",
    "addr:postcode":"8230",
    "addr:street":"Ressavarstr",
    "iso:country":"AT",
    "sg:address":"Ressavarstr 4",
    "sg:city":"Hartberg",
    "sg:orig_category":"Tankstellen",
    "sg:phone":"+43 4333 3262571",
    "sg:postcode":"8230",
    "sg:province":"Steiermark",
    "wof:name":"Agip Austria GmbH",
    "wof:placetype":"venue"
},
  "geometry": {"coordinates":[15.9662446976,47.2753868103],"type":"Point"}
}