{
  "type": "Feature",
  "properties": {
    "addr:full":"Burgg 86 Wien Wien 1070",
    "addr:housenumber":"86",
    "addr:postcode":"1070",
    "addr:street":"Burgg",
    "iso:country":"AT",
    "sg:address":"Burgg 86",
    "sg:city":"Wien",
    "sg:orig_category":"Briefmarken Philatelie",
    "sg:phone":"+43 1 5244074",
    "sg:postcode":"1070",
    "sg:province":"Wien",
    "wof:name":"Hinkelmann Erich",
    "wof:placetype":"venue"
},
  "geometry": {"coordinates":[16.3456287384,48.2045288086],"type":"Point"}
}