{
  "type": "Feature",
  "properties": {
    "iso:country":"AT",
    "sg:address":"Gnigler Str 3B",
    "sg:city":"Salzburg",
    "sg:orig_category":"Filmproduktionen",
    "sg:phone":"+43 4366 2871615",
    "sg:postcode":"5020",
    "sg:province":"Salzburg",
    "sg:website":"angermuellermedia.com",
    "wof:name":"ANGERM\u00dcLLER MEDIA GmbH",
    "wof:placetype":"venue"
},
  "geometry": {"coordinates":[13.0496377945,47.8157653809],"type":"Point"}
}