{
  "type": "Feature",
  "properties": {
    "addr:full":"Dr Karl Renner-Ring 1b Gro\u00df-Enzersdorf Nieder\u00f6sterreich 2301",
    "addr:housenumber":"1b",
    "addr:postcode":"2301",
    "addr:street":"Dr;Renner-Ring;Niederoesterreich",
    "iso:country":"AT",
    "sg:address":"Dr Karl Renner-Ring 1b",
    "sg:city":"Gro\u00df-Enzersdorf",
    "sg:orig_category":"Lebensmittel / Einzelhandel",
    "sg:phone":"+43 2249 28466",
    "sg:postcode":"2301",
    "sg:province":"Nieder\u00f6sterreich",
    "wof:name":"Hofer KG",
    "wof:placetype":"venue"
},
  "geometry": {"coordinates":[16.5508308411,48.2053031921],"type":"Point"}
}