{
  "type": "Feature",
  "properties": {
    "addr:full":"Hauptstr 14 Seekirchen am Wallersee Salzburg 5201",
    "addr:housenumber":"14",
    "addr:postcode":"5201",
    "addr:street":"Hauptstr;Salzburg",
    "iso:country":"AT",
    "sg:address":"Hauptstr 14",
    "sg:city":"Seekirchen am Wallersee",
    "sg:orig_category":"Autohandel",
    "sg:phone":"+43 6212 22350",
    "sg:postcode":"5201",
    "sg:province":"Salzburg",
    "wof:name":"Heiss & Hutticher GmbH",
    "wof:placetype":"venue"
},
  "geometry": {"coordinates":[13.1264839172,47.892375946],"type":"Point"}
}