{
  "type": "Feature",
  "properties": {
    "addr:full":"Pamesberg 17 Altm\u00fcnster Ober\u00f6sterreich 4813",
    "addr:housenumber":"17",
    "addr:postcode":"4813",
    "addr:street":"Pamesberg;Oberoesterreich",
    "iso:country":"AT",
    "sg:address":"Pamesberg 17",
    "sg:city":"Altm\u00fcnster",
    "sg:orig_category":"Installationsunternehmen",
    "sg:phone":"+43 76172741",
    "sg:postcode":"4813",
    "sg:province":"Ober\u00f6sterreich",
    "wof:name":"Hofer Alois",
    "wof:placetype":"venue"
},
  "geometry": {"coordinates":[13.7685117722,47.8718528748],"type":"Point"}
}