{
  "type": "Feature",
  "properties": {
    "addr:full":"Flachau Salzburg 5542",
    "addr:postcode":"5542",
    "addr:street":"Flachau",
    "iso:country":"AT",
    "sg:city":"Flachau",
    "sg:orig_category":"Bergbahnen",
    "sg:phone":"+43 6457 25740",
    "sg:postcode":"5542",
    "sg:province":"Salzburg",
    "wof:name":"Kleinarler Bergbahnen GesmbH & Co KG",
    "wof:placetype":"venue"
},
  "geometry": {"coordinates":[13.3921222687,47.3435821533],"type":"Point"}
}