{
  "type": "Feature",
  "properties": {
    "addr:full":"Esplanade 24 Gmunden Ober\u00f6sterreich 4810",
    "addr:housenumber":"24",
    "addr:postcode":"4810",
    "addr:street":"Esplanade;Oberoesterreich",
    "iso:country":"AT",
    "sg:address":"Esplanade 24",
    "sg:city":"Gmunden",
    "sg:orig_category":"Banken U Sparkassen",
    "sg:phone":"+43 7612628710",
    "sg:postcode":"4810",
    "sg:province":"Ober\u00f6sterreich",
    "wof:name":"Oberbank AG",
    "wof:placetype":"venue"
},
  "geometry": {"coordinates":[13.7908658981,47.9147720337],"type":"Point"}
}