{
  "type": "Feature",
  "properties": {
    "addr:full":"Obermarkt 26 Reutte Tirol 6600",
    "addr:housenumber":"26",
    "addr:postcode":"6600",
    "addr:street":"Obermarkt;Tirol",
    "iso:country":"AT",
    "sg:address":"Obermarkt 26",
    "sg:city":"Reutte",
    "sg:orig_category":"Lebensmittel / Einzelhandel",
    "sg:phone":"+43 5672 622500",
    "sg:postcode":"6600",
    "sg:province":"Tirol",
    "wof:name":"Spar-Markt Inh Erwin Sigl",
    "wof:placetype":"venue"
},
  "geometry": {"coordinates":[10.7197170258,47.4861907959],"type":"Point"}
}