{
  "type": "Feature",
  "properties": {
    "addr:full":"Alleestr 26 Lienz Tirol 9900",
    "addr:housenumber":"26",
    "addr:postcode":"9900",
    "addr:street":"Alleestr;Tirol",
    "iso:country":"AT",
    "sg:address":"Alleestr 26",
    "sg:city":"Lienz",
    "sg:orig_category":"Unterhaltungselektronik / Einzelhandel",
    "sg:phone":"+43 4852 73110",
    "sg:postcode":"9900",
    "sg:province":"Tirol",
    "wof:name":"Stotter Rudolf",
    "wof:placetype":"venue"
},
  "geometry": {"coordinates":[12.7570104599,46.8304595947],"type":"Point"}
}