{
  "type": "Feature",
  "properties": {
    "addr:full":"Nr 47 Pettenbach Ober\u00f6sterreich 4643",
    "addr:postcode":"4643",
    "addr:street":"Nr;Oberoesterreich",
    "iso:country":"AT",
    "sg:address":"Nr 47",
    "sg:city":"Pettenbach",
    "sg:orig_category":"Bars-Cafes",
    "sg:phone":"+43 699 12003623",
    "sg:postcode":"4643",
    "sg:province":"Ober\u00f6sterreich",
    "wof:name":"Austaller & Holzinger Gastro OEG",
    "wof:placetype":"venue"
},
  "geometry": {"coordinates":[14.0165214539,47.9612464905],"type":"Point"}
}