{
  "type": "Feature",
  "properties": {
    "addr:full":"Josef Weislein-Str Hollabrunn Nieder\u00f6sterreich 2020",
    "addr:postcode":"2020",
    "addr:street":"Niederoesterreich",
    "iso:country":"AT",
    "sg:address":"Josef Weislein-Str",
    "sg:city":"Hollabrunn",
    "sg:orig_category":"Feuerwehren",
    "sg:phone":"+43 2952 222270",
    "sg:postcode":"2020",
    "sg:province":"Nieder\u00f6sterreich",
    "wof:name":"Freiwillige Feuerwehr Hollabrunn",
    "wof:placetype":"venue"
},
  "geometry": {"coordinates":[16.0745620728,48.5592308044],"type":"Point"}
}