{
  "type": "Feature",
  "properties": {
    "addr:full":"Helblingg 7 Wien Wien 1170",
    "addr:housenumber":"7",
    "addr:postcode":"1170",
    "addr:street":"Helblingg",
    "iso:country":"AT",
    "sg:address":"Helblingg 7",
    "sg:city":"Wien",
    "sg:orig_category":"Appartements / Ferienwohnungen",
    "sg:phone":"+43 1 4088295",
    "sg:postcode":"1170",
    "sg:province":"Wien",
    "wof:name":"Johann Strauss AppartementsvermietungsgesmbH",
    "wof:placetype":"venue"
},
  "geometry": {"coordinates":[16.3354873657,48.2154159546],"type":"Point"}
}