{
  "type": "Feature",
  "properties": {
    "addr:full":"Leonhardstrasse 30 Graz Steiermark 8010",
    "addr:housenumber":"30",
    "addr:postcode":"8010",
    "addr:street":"Leonhardstrasse",
    "iso:country":"AT",
    "sg:address":"Leonhardstrasse 30",
    "sg:city":"Graz",
    "sg:orig_category":"Dienstleistungen, Umwelt",
    "sg:postcode":"8010",
    "sg:province":"Steiermark",
    "sg:website":"http://www.societas.at",
    "wof:name":"SOCIETAS VERM\u00d6GENSBERATUNG AKTIEN OPTIONEN WERTPAPIERE FONDS",
    "wof:placetype":"venue"
},
  "geometry": {"coordinates":[15.4521694183,47.0722541809],"type":"Point"}
}