{
  "type": "Feature",
  "properties": {
    "iso:country":"AT",
    "sg:address":"Wallenmahd 23",
    "sg:city":"Dornbirn",
    "sg:orig_category":"Freizeit- U Sportbekleidung",
    "sg:phone":"+43 5572 9083030",
    "sg:postcode":"6850",
    "sg:province":"Vorarlberg",
    "wof:name":"Promonta Textil GmbH",
    "wof:placetype":"venue"
},
  "geometry": {"coordinates":[9.7264003754,47.3903808594],"type":"Point"}
}