{
  "type": "Feature",
  "properties": {
    "addr:full":"Austr 35 Ellmau Tirol 6352",
    "addr:housenumber":"35",
    "addr:postcode":"6352",
    "addr:street":"Austr;Tirol",
    "iso:country":"AT",
    "sg:address":"Austr 35",
    "sg:city":"Ellmau",
    "sg:orig_category":"Pensionen / Privatzimmer",
    "sg:phone":"+43 5358 2808",
    "sg:postcode":"6352",
    "sg:province":"Tirol",
    "wof:name":"Pension Mirabelle",
    "wof:placetype":"venue"
},
  "geometry": {"coordinates":[12.2941970825,47.5108299255],"type":"Point"}
}