{
  "type": "Feature",
  "properties": {
    "addr:full":"Dreisesselbergstr 34 Aigen im M\u00fchlkreis Ober\u00f6sterreich 4160",
    "addr:housenumber":"34",
    "addr:postcode":"4160",
    "addr:street":"Dreisesselbergstr",
    "iso:country":"AT",
    "sg:address":"Dreisesselbergstr 34",
    "sg:city":"Aigen im M\u00fchlkreis",
    "sg:orig_category":"Tischlereien",
    "sg:phone":"+43 7281 6279",
    "sg:postcode":"4160",
    "sg:province":"Ober\u00f6sterreich",
    "wof:name":"M\u00f6beltischlerei Resch GesmbH",
    "wof:placetype":"venue"
},
  "geometry": {"coordinates":[13.9645586014,48.6501197815],"type":"Point"}
}