{
  "type": "Feature",
  "properties": {
    "addr:full":"Kirchenberg 27 Losenstein Ober\u00f6sterreich 4460",
    "addr:housenumber":"27",
    "addr:postcode":"4460",
    "addr:street":"Kirchenberg",
    "iso:country":"AT",
    "sg:address":"Kirchenberg 27",
    "sg:city":"Losenstein",
    "sg:classifiers":[
        {
            "category":"Home & Garden",
            "subcategory":"Furniture",
            "type":"Retail Goods"
        }
    ],
    "sg:phone":"+43 7255 6252",
    "sg:postcode":"4460",
    "sg:province":"Ober\u00f6sterreich",
    "sg:tags":[
        "bathroom"
    ],
    "wof:name":"Zeilermayr OEG",
    "wof:placetype":"venue"
},
  "geometry": {"coordinates":[14.4308271408,47.9289512634],"type":"Point"}
}