{
  "type": "Feature",
  "properties": {
    "addr:full":"Modecenterstr 7 Wien Wien 1030",
    "addr:housenumber":"7",
    "addr:postcode":"1030",
    "addr:street":"Modecenterstr",
    "iso:country":"AT",
    "sg:address":"Modecenterstr 7",
    "sg:city":"Wien",
    "sg:orig_category":"Hydraulik",
    "sg:phone":"+43 1 7431030",
    "sg:postcode":"1030",
    "sg:province":"Wien",
    "wof:name":"Haberkorn S GmbH",
    "wof:placetype":"venue"
},
  "geometry": {"coordinates":[16.4165687561,48.1867446899],"type":"Point"}
}