{
  "type": "Feature",
  "properties": {
    "addr:full":"Hauptpl 9 Unterwaltersdorf Nieder\u00f6sterreich 2442",
    "addr:housenumber":"9",
    "addr:postcode":"2442",
    "addr:street":"Hauptpl",
    "iso:country":"AT",
    "sg:address":"Hauptpl 9",
    "sg:city":"Unterwaltersdorf",
    "sg:classifiers":[
        {
            "category":"Travel",
            "subcategory":"Hotels & Motels",
            "type":"Entertainment"
        }
    ],
    "sg:phone":"+43 2254 72405",
    "sg:postcode":"2442",
    "sg:province":"Nieder\u00f6sterreich",
    "wof:name":"Waitz Gerhard GesmbH",
    "wof:placetype":"venue"
},
  "geometry": {"coordinates":[16.4311714172,47.9602775574],"type":"Point"}
}