{
  "type": "Feature",
  "properties": {
    "iso:country":"AT",
    "sg:address":"Nr 113",
    "sg:city":"Finkenberg",
    "sg:orig_category":"Pensionen / Privatzimmer",
    "sg:phone":"+43 5285 63501",
    "sg:postcode":"6292",
    "sg:province":"Tirol",
    "wof:name":"Finkenberghof Eberl",
    "wof:placetype":"venue"
},
  "geometry": {"coordinates":[11.8239097595,47.153465271],"type":"Point"}
}