{
  "type": "Feature",
  "properties": {
    "addr:full":"Nr 47 Birkfeld Steiermark 8190",
    "addr:postcode":"8190",
    "addr:street":"Nr 47",
    "iso:country":"AT",
    "sg:address":"Nr 47",
    "sg:city":"Birkfeld",
    "sg:orig_category":"Bestattungsunternehmen",
    "sg:phone":"+43 4331 744720",
    "sg:postcode":"8190",
    "sg:province":"Steiermark",
    "wof:name":"P\u00f6tz-Allmer Irmgard",
    "wof:placetype":"venue"
},
  "geometry": {"coordinates":[15.7014284134,47.3529853821],"type":"Point"}
}