{
  "type": "Feature",
  "properties": {
    "addr:full":"Dorf 43 Obertilliach Tirol 9942",
    "addr:housenumber":"43",
    "addr:postcode":"9942",
    "addr:street":"Dorf;Tirol",
    "iso:country":"AT",
    "sg:address":"Dorf 43",
    "sg:city":"Obertilliach",
    "sg:orig_category":"Pensionen / Privatzimmer",
    "sg:phone":"+43 4348 475248",
    "sg:postcode":"9942",
    "sg:province":"Tirol",
    "wof:name":"Bucherhof Peter Bucher",
    "wof:placetype":"venue"
},
  "geometry": {"coordinates":[12.6132011414,46.7110023499],"type":"Point"}
}