{
  "type": "Feature",
  "properties": {
    "addr:full":"Handelsweg 6 Kottingbrunn Nieder\u00f6sterreich 2542",
    "addr:housenumber":"6",
    "addr:postcode":"2542",
    "addr:street":"Handelsweg",
    "iso:country":"AT",
    "sg:address":"Handelsweg 6",
    "sg:city":"Kottingbrunn",
    "sg:orig_category":"Mess-, Steuer- U Regeltechnik",
    "sg:phone":"+43 4322 5270704",
    "sg:postcode":"2542",
    "sg:province":"Nieder\u00f6sterreich",
    "wof:name":"Utner GesmbH",
    "wof:placetype":"venue"
},
  "geometry": {"coordinates":[16.2194881439,47.9481544495],"type":"Point"}
}