{
  "type": "Feature",
  "properties": {
    "addr:full":"Bergmannpl 1 Traun Ober\u00f6sterreich 4050",
    "addr:housenumber":"1",
    "addr:postcode":"4050",
    "addr:street":"Bergmannpl",
    "iso:country":"AT",
    "sg:address":"Bergmannpl 1",
    "sg:city":"Traun",
    "sg:classifiers":[
        {
            "category":"Home & Garden",
            "subcategory":"Building Materials",
            "type":"Retail Goods"
        }
    ],
    "sg:phone":"+43 732 37330",
    "sg:postcode":"4050",
    "sg:province":"Ober\u00f6sterreich",
    "sg:tags":[
        "baustoffe",
        "-material",
        "u"
    ],
    "wof:name":"Bergmann C Baustoffe",
    "wof:placetype":"venue"
},
  "geometry": {"coordinates":[14.2668514252,48.2453804016],"type":"Point"}
}