{
  "type": "Feature",
  "properties": {
    "iso:country":"AT",
    "sg:address":"Marktstr 1",
    "sg:city":"Ried in der Riedmark",
    "sg:orig_category":"Lebensmittel / Einzelhandel",
    "sg:phone":"+43 7238 2383",
    "sg:postcode":"4312",
    "sg:province":"Ober\u00f6sterreich",
    "wof:name":"ADEG Aktiv Markt Klaus Wall",
    "wof:placetype":"venue"
},
  "geometry": {"coordinates":[14.5266218185,48.2710266113],"type":"Point"}
}