{
  "type": "Feature",
  "properties": {
    "addr:full":"Treustr 68 Wien Wien 1200",
    "addr:housenumber":"68",
    "addr:postcode":"1200",
    "addr:street":"Treustr",
    "iso:country":"AT",
    "sg:address":"Treustr 68",
    "sg:city":"Wien",
    "sg:orig_category":"Siebdruckereien",
    "sg:phone":"+43 1 33282100",
    "sg:postcode":"1200",
    "sg:province":"Wien",
    "wof:name":"Impresa DruckereigesmbH",
    "wof:placetype":"venue"
},
  "geometry": {"coordinates":[16.3640556335,48.2324447632],"type":"Point"}
}