{
  "type": "Feature",
  "properties": {
    "iso:country":"AT",
    "sg:address":"Hauptpl 34a",
    "sg:city":"Arnfels",
    "sg:orig_category":"Elektroinstallationsunternehmen",
    "sg:phone":"+43 4334 558044",
    "sg:postcode":"8454",
    "sg:province":"Steiermark",
    "wof:name":"Elektro Lang GmbH & Co KG",
    "wof:placetype":"venue"
},
  "geometry": {"coordinates":[15.4015378952,46.6779785156],"type":"Point"}
}