{
  "type": "Feature",
  "properties": {
    "addr:full":"Herbststr 86 Wien Wien 1160",
    "addr:housenumber":"86",
    "addr:postcode":"1160",
    "addr:street":"Herbststr",
    "iso:country":"AT",
    "sg:address":"Herbststr 86",
    "sg:city":"Wien",
    "sg:orig_category":"Volksschulen",
    "sg:phone":"+43 1 4924323",
    "sg:postcode":"1160",
    "sg:province":"Wien",
    "wof:name":"Schulen d Stadt Wien",
    "wof:placetype":"venue"
},
  "geometry": {"coordinates":[16.3213329315,48.2073669434],"type":"Point"}
}