{
  "type": "Feature",
  "properties": {
    "addr:full":"P\u00f6llach 10 St. Gilgen Salzburg 5340",
    "addr:housenumber":"10",
    "addr:postcode":"5340",
    "addr:street":"Poellach",
    "iso:country":"AT",
    "sg:address":"P\u00f6llach 10",
    "sg:city":"St. Gilgen",
    "sg:classifiers":[
        {
            "category":"Banks & Credit Unions",
            "subcategory":"Bureau De Change",
            "type":"Services"
        }
    ],
    "sg:phone":"+43 6227 23410",
    "sg:postcode":"5340",
    "sg:province":"Salzburg",
    "sg:tags":[
        "demolition"
    ],
    "sg:website":"boeckl.at",
    "wof:name":"B\u00f6ckl Erdbau und Abbruch GmbH",
    "wof:placetype":"venue"
},
  "geometry": {"coordinates":[13.3638296127,47.7669639587],"type":"Point"}
}