{
  "type": "Feature",
  "properties": {
    "addr:full":"Palfenweg 123 Piesendorf Salzburg 5721",
    "addr:housenumber":"123",
    "addr:postcode":"5721",
    "addr:street":"Palfenweg;Salzburg",
    "iso:country":"AT",
    "sg:address":"Palfenweg 123",
    "sg:city":"Piesendorf",
    "sg:orig_category":"Pensionen / Privatzimmer",
    "sg:phone":"+43 6549 81720",
    "sg:postcode":"5721",
    "sg:province":"Salzburg",
    "wof:name":"Pension Kitzblick",
    "wof:placetype":"venue"
},
  "geometry": {"coordinates":[12.7474546432,47.2952232361],"type":"Point"}
}