{
  "type": "Feature",
  "properties": {
    "iso:country":"AT",
    "sg:address":"Uraniastr 4",
    "sg:city":"Wien",
    "sg:orig_category":"Interessensvertretungen",
    "sg:phone":"+43 1 71204740",
    "sg:postcode":"1010",
    "sg:province":"Wien",
    "wof:name":"ARGE PROHOLZ Austria",
    "wof:placetype":"venue"
},
  "geometry": {"coordinates":[16.3840770721,48.2111701965],"type":"Point"}
}