{
  "type": "Feature",
  "properties": {
    "addr:full":"Lobkowitzpl 1 Wien Wien 1010",
    "addr:housenumber":"1",
    "addr:postcode":"1010",
    "addr:street":"Lobkowitzpl",
    "iso:country":"AT",
    "sg:address":"Lobkowitzpl 1",
    "sg:city":"Wien",
    "sg:orig_category":"Versicherungsunternehmen",
    "sg:phone":"+43 1 515470",
    "sg:postcode":"1010",
    "sg:province":"Wien",
    "wof:name":"Grazer Wechselseitige Versicherung AG LdsDion f Wien und N\u00f6",
    "wof:placetype":"venue"
},
  "geometry": {"coordinates":[16.3687057495,48.2054138184],"type":"Point"}
}