{
  "type": "Feature",
  "properties": {
    "iso:country":"AT",
    "sg:address":"Annag 5",
    "sg:city":"Wien",
    "sg:orig_category":"Antiquariate",
    "sg:phone":"+43 1 5127344",
    "sg:postcode":"1010",
    "sg:province":"Wien",
    "sg:website":"loecker.at",
    "wof:name":"Antiquariat L\u00f6cker",
    "wof:placetype":"venue"
},
  "geometry": {"coordinates":[16.3688049316,48.2025489807],"type":"Point"}
}