{
  "type": "Feature",
  "properties": {
    "iso:country":"AT",
    "sg:address":"Spengerg 1",
    "sg:city":"Wien",
    "sg:orig_category":"Steuerberatung",
    "sg:phone":"+43 4315 443169",
    "sg:postcode":"1050",
    "sg:province":"Wien",
    "wof:name":"Panhans Vinzenz",
    "wof:placetype":"venue"
},
  "geometry": {"coordinates":[16.3594875336,48.1828651428],"type":"Point"}
}