{
  "type": "Feature",
  "properties": {
    "iso:country":"AT",
    "sg:address":"Sparkassenpl 4",
    "sg:city":"Bludenz",
    "sg:orig_category":"Gerichte",
    "sg:phone":"+43 5552 630810",
    "sg:postcode":"6700",
    "sg:province":"Vorarlberg",
    "wof:name":"Bezirksgericht Bludenz",
    "wof:placetype":"venue"
},
  "geometry": {"coordinates":[9.8210258484,47.1556396484],"type":"Point"}
}