{
  "type": "Feature",
  "properties": {
    "iso:country":"AT",
    "sg:address":"Peischinger Str 5",
    "sg:city":"Neunkirchen",
    "sg:orig_category":"Versicherungsunternehmen",
    "sg:phone":"+43 2635 628520",
    "sg:postcode":"2620",
    "sg:province":"Nieder\u00f6sterreich",
    "wof:name":"Der Anker Allgemeine Versicherung AG",
    "wof:placetype":"venue"
},
  "geometry": {"coordinates":[16.0818023682,47.7259178162],"type":"Point"}
}