{
  "type": "Feature",
  "properties": {
    "addr:full":"Tiroler Str 9 St. P\u00f6lten-Radlberg Nieder\u00f6sterreich 3105",
    "addr:housenumber":"9",
    "addr:postcode":"3105",
    "addr:street":"Str",
    "iso:country":"AT",
    "sg:address":"Tiroler Str 9",
    "sg:city":"St. P\u00f6lten-Radlberg",
    "sg:orig_category":"Staubsauger",
    "sg:phone":"+43 4327 4221472",
    "sg:postcode":"3105",
    "sg:province":"Nieder\u00f6sterreich",
    "wof:name":"SRK Zauner Heinrich",
    "wof:placetype":"venue"
},
  "geometry": {"coordinates":[15.6872873306,48.2614517212],"type":"Point"}
}