{
  "type": "Feature",
  "properties": {
    "addr:full":"Nr 40 Lendorf K\u00e4rnten 9811",
    "addr:postcode":"9811",
    "addr:street":"Nr;Lendorf",
    "iso:country":"AT",
    "sg:address":"Nr 40",
    "sg:city":"Lendorf",
    "sg:orig_category":"Installationsunternehmen",
    "sg:phone":"+43 4347 6235900",
    "sg:postcode":"9811",
    "sg:province":"K\u00e4rnten",
    "wof:name":"Energiesparinstallateur Kloss Thomas Ing",
    "wof:placetype":"venue"
},
  "geometry": {"coordinates":[166.9221496582,-0.5282999873],"type":"Point"}
}