{
  "type": "Feature",
  "properties": {
    "addr:full":"Nr 4 Moosdorf Ober\u00f6sterreich 5141",
    "addr:postcode":"5141",
    "addr:street":"Nr;Moosdorf",
    "iso:country":"AT",
    "sg:address":"Nr 4",
    "sg:city":"Moosdorf",
    "sg:orig_category":"Teigwaren",
    "sg:phone":"+43 7748 2134",
    "sg:postcode":"5141",
    "sg:province":"Ober\u00f6sterreich",
    "wof:name":"Wallner's Nudelei",
    "wof:placetype":"venue"
},
  "geometry": {"coordinates":[12.9887685776,48.046245575],"type":"Point"}
}