{
  "type": "Feature",
  "properties": {
    "addr:full":"8.-Mai-Str 31 Klagenfurt K\u00e4rnten 9020",
    "addr:housenumber":"31",
    "addr:postcode":"9020",
    "addr:street":"8.-Mai-Str;Kaernten",
    "iso:country":"AT",
    "sg:address":"8.-Mai-Str 31",
    "sg:city":"Klagenfurt",
    "sg:orig_category":"Bausparkassen",
    "sg:phone":"+43 4357 070260",
    "sg:postcode":"9020",
    "sg:province":"K\u00e4rnten",
    "sg:website":"wuestenrot.at",
    "wof:name":"Bausparkasse W\u00fcstenrot AG LdsDion f Ktn u OT",
    "wof:placetype":"venue"
},
  "geometry": {"coordinates":[14.310915947,46.6232566833],"type":"Point"}
}