{
  "type": "Feature",
  "properties": {
    "addr:full":"Millerg 40/9 Wien Wien 1060",
    "addr:housenumber":"40 / 9",
    "addr:postcode":"1060",
    "addr:street":"Millerg",
    "iso:country":"AT",
    "sg:address":"Millerg 40/9",
    "sg:city":"Wien",
    "sg:orig_category":"Psychotherapie",
    "sg:phone":"+43 4369 912075221",
    "sg:postcode":"1060",
    "sg:province":"Wien",
    "wof:name":"Psychotherapeutische Praxis - Mag Christian Schweiger - Psychotherapeut i.A.u.S.",
    "wof:placetype":"venue"
},
  "geometry": {"coordinates":[16.3424263,48.194480896],"type":"Point"}
}