{
  "type": "Feature",
  "properties": {
    "iso:country":"AT",
    "sg:address":"Hauptstr 60",
    "sg:city":"Oberpullendorf",
    "sg:orig_category":"Optiker",
    "sg:phone":"+43 2612 42737",
    "sg:postcode":"7350",
    "sg:province":"Burgenland",
    "wof:name":"Pearle \u00f6sterreich GmbH",
    "wof:placetype":"venue"
},
  "geometry": {"coordinates":[16.5068073273,47.4975204468],"type":"Point"}
}