{
  "type": "Feature",
  "properties": {
    "iso:country":"AT",
    "sg:address":"St. Marienkirchen/Hausruck 16",
    "sg:city":"Geiersberg",
    "sg:classifiers":[
        {
            "category":"Home & Garden",
            "subcategory":"Building Materials",
            "type":"Retail Goods"
        }
    ],
    "sg:phone":"+43 7753 3141",
    "sg:postcode":"4922",
    "sg:province":"Ober\u00f6sterreich",
    "sg:tags":[
        "steel",
        "metal",
        "made",
        "door",
        "gate"
    ],
    "wof:name":"Alois Raschhofer",
    "wof:placetype":"venue"
},
  "geometry": {"coordinates":[13.5825490952,48.1999702454],"type":"Point"}
}