{
  "type": "Feature",
  "properties": {
    "addr:full":"Linzer Strasse 359 Wien Wien 1140",
    "addr:housenumber":"359",
    "addr:postcode":"1140",
    "addr:street":"Linzer Strasse",
    "iso:country":"AT",
    "sg:address":"Linzer Strasse 359",
    "sg:city":"Wien",
    "sg:classifiers":[
        {
            "category":"Parking",
            "subcategory":"Garage",
            "type":"Transportation"
        }
    ],
    "sg:phone":"+43 1 9146119",
    "sg:postcode":"1140",
    "sg:province":"Wien",
    "sg:tags":[
        "carport"
    ],
    "sg:website":"mach-holzbau.at",
    "wof:name":"Karl Mach Ges.m.b.H.",
    "wof:placetype":"venue"
},
  "geometry": {"coordinates":[16.2667255402,48.2000579834],"type":"Point"}
}