{
  "type": "Feature",
  "properties": {
    "addr:full":"Untere Hofmark 4 Braunau am Inn-Ranshofen Ober\u00f6sterreich 5282",
    "addr:housenumber":"4",
    "addr:postcode":"5282",
    "addr:street":"Untere Hofmark",
    "iso:country":"AT",
    "sg:address":"Untere Hofmark 4",
    "sg:city":"Braunau am Inn-Ranshofen",
    "sg:orig_category":"Autohandel",
    "sg:phone":"+43 7722 63404",
    "sg:postcode":"5282",
    "sg:province":"Ober\u00f6sterreich",
    "wof:name":"Autohaus Forster GmbH",
    "wof:placetype":"venue"
},
  "geometry": {"coordinates":[13.0156641006,48.2334823608],"type":"Point"}
}