{
  "type": "Feature",
  "properties": {
    "addr:full":"Pfongau 8 Neumarkt am Wallersee Salzburg 5202",
    "addr:housenumber":"8",
    "addr:postcode":"5202",
    "addr:street":"Pfongau;Salzburg",
    "iso:country":"AT",
    "sg:address":"Pfongau 8",
    "sg:city":"Neumarkt am Wallersee",
    "sg:classifiers":[
        {
            "category":"Professional",
            "subcategory":"Art Services",
            "type":"Services"
        }
    ],
    "sg:phone":"+43 6216 6990",
    "sg:postcode":"5202",
    "sg:province":"Salzburg",
    "sg:tags":[
        "picture",
        "frame"
    ],
    "sg:website":"multicolours.at",
    "wof:name":"Multi Colours K. + S. Hagn Bilder-Rahmen-Kunstdrucke",
    "wof:placetype":"venue"
},
  "geometry": {"coordinates":[13.2246103287,47.9449386597],"type":"Point"}
}