{
  "type": "Feature",
  "properties": {
    "addr:full":"Wienerfeldstr 6 Wolkersdorf im Weinviertel Nieder\u00f6sterreich 2120",
    "addr:housenumber":"6",
    "addr:postcode":"2120",
    "addr:street":"Wienerfeldstr",
    "iso:country":"AT",
    "sg:address":"Wienerfeldstr 6",
    "sg:city":"Wolkersdorf im Weinviertel",
    "sg:orig_category":"Drehereien",
    "sg:phone":"+43 4322 4531810",
    "sg:postcode":"2120",
    "sg:province":"Nieder\u00f6sterreich",
    "wof:name":"Dvorak Johann GesmbH",
    "wof:placetype":"venue"
},
  "geometry": {"coordinates":[16.5105857849,48.3817024231],"type":"Point"}
}