{
  "type": "Feature",
  "properties": {
    "addr:full":"Favoritenstr 58 Wien Wien 1040",
    "addr:housenumber":"58",
    "addr:postcode":"1040",
    "addr:street":"Favoritenstr",
    "iso:country":"AT",
    "sg:address":"Favoritenstr 58",
    "sg:city":"Wien",
    "sg:orig_category":"Restaurants: Mexikanisch",
    "sg:phone":"+43 1 2165830",
    "sg:postcode":"1040",
    "sg:province":"Wien",
    "wof:name":"JALISCO",
    "wof:placetype":"venue"
},
  "geometry": {"coordinates":[16.3724784851,48.1887741089],"type":"Point"}
}