{
  "type": "Feature",
  "properties": {
    "addr:full":"Gewerbestr 6 Gr\u00f6dig Salzburg 5082",
    "addr:housenumber":"6",
    "addr:postcode":"5082",
    "addr:street":"Gewerbestr;Salzburg",
    "iso:country":"AT",
    "sg:address":"Gewerbestr 6",
    "sg:city":"Gr\u00f6dig",
    "sg:orig_category":"Werbegrafik- U Grafik-Design",
    "sg:phone":"+43 6246 75949",
    "sg:postcode":"5082",
    "sg:province":"Salzburg",
    "wof:name":"M\u00fchlbacher Werbegrafik",
    "wof:placetype":"venue"
},
  "geometry": {"coordinates":[-76.2684555054,37.4373283386],"type":"Point"}
}