{
  "type": "Feature",
  "properties": {
    "iso:country":"AT",
    "sg:address":"Favoritenstr 111",
    "sg:city":"Wien",
    "sg:orig_category":"Notare",
    "sg:phone":"+43 1 60432150",
    "sg:postcode":"1100",
    "sg:province":"Wien",
    "wof:name":"Hofer Karl Dr",
    "wof:placetype":"venue"
},
  "geometry": {"coordinates":[16.3778591156,48.1755599976],"type":"Point"}
}