{
  "type": "Feature",
  "properties": {
    "addr:full":"Scheffelgasse 8 Villach K\u00e4rnten 9500",
    "addr:housenumber":"8",
    "addr:postcode":"9500",
    "addr:street":"Scheffelgasse;Kaernten",
    "iso:country":"AT",
    "sg:address":"Scheffelgasse 8",
    "sg:city":"Villach",
    "sg:classifiers":[
        {
            "category":"Manufacturing",
            "subcategory":"Metals",
            "type":"Manufacturing & Wholesale Goods"
        }
    ],
    "sg:phone":"+43 4242 214200",
    "sg:postcode":"9500",
    "sg:province":"K\u00e4rnten",
    "sg:tags":[
        "die",
        "aluminium",
        "casting"
    ],
    "sg:website":"technical-solutions.at",
    "wof:name":"G\u00e4rtner & Krucker Technical- Solutions G\u00e4rtner Handels Ges.m.b.H. & Co KEG",
    "wof:placetype":"venue"
},
  "geometry": {"coordinates":[13.8512973785,46.622795105],"type":"Point"}
}