{
  "type": "Feature",
  "properties": {
    "addr:full":"Dr Hild-G 2-8/5 Purkersdorf Nieder\u00f6sterreich 3002",
    "addr:housenumber":"2-8 / 5",
    "addr:postcode":"3002",
    "iso:country":"AT",
    "sg:address":"Dr Hild-G 2-8/5",
    "sg:city":"Purkersdorf",
    "sg:orig_category":"Physiotherapie",
    "sg:phone":"+43 2231 63502",
    "sg:postcode":"3002",
    "sg:province":"Nieder\u00f6sterreich",
    "wof:name":"Physiotherapiepraxis Peschta - Cerny",
    "wof:placetype":"venue"
},
  "geometry": {"coordinates":[16.1757965088,48.2075881958],"type":"Point"}
}