{
  "type": "Feature",
  "properties": {
    "iso:country":"AT",
    "sg:address":"Achamerg 4/11",
    "sg:city":"Wien",
    "sg:orig_category":"Psychotherapie",
    "sg:phone":"+43 699 11650799",
    "sg:postcode":"1090",
    "sg:province":"Wien",
    "wof:name":"Lasar Sabine Mag - Psychotherapie und Coaching",
    "wof:placetype":"venue"
},
  "geometry": {"coordinates":[16.350435257,48.2256011963],"type":"Point"}
}