{
  "type": "Feature",
  "properties": {
    "addr:full":"Pantzerg 21 Wien Wien 1190",
    "addr:housenumber":"21",
    "addr:postcode":"1190",
    "addr:street":"Pantzerg",
    "iso:country":"AT",
    "sg:address":"Pantzerg 21",
    "sg:city":"Wien",
    "sg:orig_category":"Rauchfangkehrer",
    "sg:phone":"+43 1 4862509",
    "sg:postcode":"1190",
    "sg:province":"Wien",
    "wof:name":"Hahn Kurt",
    "wof:placetype":"venue"
},
  "geometry": {"coordinates":[16.3540592194,48.2355155945],"type":"Point"}
}