{
  "type": "Feature",
  "properties": {
    "iso:country":"AT",
    "sg:address":"Friedhofg 1",
    "sg:city":"Grieskirchen",
    "sg:orig_category":"Steuerberatung",
    "sg:phone":"+43 7248 68552",
    "sg:postcode":"4710",
    "sg:province":"Ober\u00f6sterreich",
    "wof:name":"Leimer Elisabeth",
    "wof:placetype":"venue"
},
  "geometry": {"coordinates":[13.832780838,48.2335662842],"type":"Point"}
}