{
  "type": "Feature",
  "properties": {
    "iso:country":"AT",
    "sg:address":"Melisau 1039",
    "sg:city":"Egg",
    "sg:orig_category":"Farben U Lacke / Einzelhandel",
    "sg:phone":"+43 5512 2054",
    "sg:postcode":"6863",
    "sg:province":"Vorarlberg",
    "wof:name":"Morscher Farben- und Werkzeug-Handels-GesmbH",
    "wof:placetype":"venue"
},
  "geometry": {"coordinates":[9.897102356,47.4310417175],"type":"Point"}
}