{
  "type": "Feature",
  "properties": {
    "addr:full":"Bahnhofstr 4 Aschach an der Donau Ober\u00f6sterreich 4082",
    "addr:housenumber":"4",
    "addr:postcode":"4082",
    "addr:street":"Bahnhofstr",
    "iso:country":"AT",
    "sg:address":"Bahnhofstr 4",
    "sg:city":"Aschach an der Donau",
    "sg:orig_category":"Volksschulen",
    "sg:phone":"+43 4372 738837",
    "sg:postcode":"4082",
    "sg:province":"Ober\u00f6sterreich",
    "wof:name":"Volksschule",
    "wof:placetype":"venue"
},
  "geometry": {"coordinates":[14.018198967,48.3644752502],"type":"Point"}
}