{
  "type": "Feature",
  "properties": {
    "addr:full":"Am Dechantriegel 16 Voitsberg Steiermark 8570",
    "addr:housenumber":"16",
    "addr:postcode":"8570",
    "addr:street":"Am Dechantriegel",
    "iso:country":"AT",
    "sg:address":"Am Dechantriegel 16",
    "sg:city":"Voitsberg",
    "sg:orig_category":"Werbegestalter",
    "sg:phone":"+43 3142 28378",
    "sg:postcode":"8570",
    "sg:province":"Steiermark",
    "wof:name":"Deko Design Inh Emanuela Vadlau",
    "wof:placetype":"venue"
},
  "geometry": {"coordinates":[15.1525030136,47.0387535095],"type":"Point"}
}