{
  "type": "Feature",
  "properties": {
    "addr:full":"Weizer Str 7 Birkfeld Steiermark 8190",
    "addr:housenumber":"7",
    "addr:postcode":"8190",
    "addr:street":"Str",
    "iso:country":"AT",
    "sg:address":"Weizer Str 7",
    "sg:city":"Birkfeld",
    "sg:orig_category":"Schneidereien",
    "sg:phone":"+43 4331 744579",
    "sg:postcode":"8190",
    "sg:province":"Steiermark",
    "wof:name":"Schoberer Johanna",
    "wof:placetype":"venue"
},
  "geometry": {"coordinates":[15.6950502396,47.3526611328],"type":"Point"}
}