{
  "type": "Feature",
  "properties": {
    "addr:full":"Mitterweg 60 Innsbruck Tirol 6020",
    "addr:housenumber":"60",
    "addr:postcode":"6020",
    "addr:street":"Mitterweg;Tirol",
    "iso:country":"AT",
    "sg:address":"Mitterweg 60",
    "sg:city":"Innsbruck",
    "sg:orig_category":"Steuerberatung",
    "sg:phone":"+43 4351 2295292",
    "sg:postcode":"6020",
    "sg:province":"Tirol",
    "sg:website":"dorn-consult.at",
    "wof:name":"Dorn Rainer",
    "wof:placetype":"venue"
},
  "geometry": {"coordinates":[11.3695268631,47.2578926086],"type":"Point"}
}