{
  "type": "Feature",
  "properties": {
    "addr:full":"Wiener Strasse 9 Kindberg Steiermark 8650",
    "addr:housenumber":"9",
    "addr:postcode":"8650",
    "addr:street":"Wiener Strasse",
    "iso:country":"AT",
    "sg:address":"Wiener Strasse 9",
    "sg:city":"Kindberg",
    "sg:classifiers":[
        {
            "category":"Home & Garden",
            "subcategory":"Building Materials",
            "type":"Retail Goods"
        }
    ],
    "sg:phone":"+43 3865 3570",
    "sg:postcode":"8650",
    "sg:province":"Steiermark",
    "sg:tags":[
        "tile",
        "granite"
    ],
    "wof:name":"Heidemarie Janger",
    "wof:placetype":"venue"
},
  "geometry": {"coordinates":[15.449215889,47.5087585449],"type":"Point"}
}