{
  "type": "Feature",
  "properties": {
    "addr:full":"Gunoldstr 14 Wien Wien 1190",
    "addr:housenumber":"14",
    "addr:postcode":"1190",
    "addr:street":"Gunoldstr",
    "iso:country":"AT",
    "sg:address":"Gunoldstr 14",
    "sg:city":"Wien",
    "sg:classifiers":[
        {
            "category":"Organizations",
            "subcategory":"Community Association",
            "type":"Services"
        }
    ],
    "sg:phone":"+43 1 360605310",
    "sg:postcode":"1190",
    "sg:province":"Wien",
    "sg:tags":[
        "relation",
        "public"
    ],
    "wof:name":"APA OTS Originaltext-Service GmbH",
    "wof:placetype":"venue"
},
  "geometry": {"coordinates":[16.3654174805,48.2450714111],"type":"Point"}
}