{
  "type": "Feature",
  "properties": {
    "addr:full":"Maiffredyg 4/4 Graz Steiermark 8010",
    "addr:housenumber":"4 / 4",
    "addr:postcode":"8010",
    "addr:street":"Maiffredyg",
    "iso:country":"AT",
    "sg:address":"Maiffredyg 4/4",
    "sg:city":"Graz",
    "sg:orig_category":"Institute",
    "sg:phone":"+43 4331 6323900",
    "sg:postcode":"8010",
    "sg:province":"Steiermark",
    "wof:name":"Institut f Ettikete u Gesellschaft",
    "wof:placetype":"venue"
},
  "geometry": {"coordinates":[15.4482889175,47.0708503723],"type":"Point"}
}