{
  "type": "Feature",
  "properties": {
    "addr:full":"Kirchenstr 11 Bad Hall Ober\u00f6sterreich 4540",
    "addr:housenumber":"11",
    "addr:postcode":"4540",
    "addr:street":"Kirchenstr",
    "iso:country":"AT",
    "sg:address":"Kirchenstr 11",
    "sg:city":"Bad Hall",
    "sg:orig_category":"\u00c3\u201erzte / F Allgemeinmedizin",
    "sg:phone":"+43 7258 5454",
    "sg:postcode":"4540",
    "sg:province":"Ober\u00f6sterreich",
    "wof:name":"Huemer Kurt Dr",
    "wof:placetype":"venue"
},
  "geometry": {"coordinates":[14.207072258,48.0355949402],"type":"Point"}
}