{
  "type": "Feature",
  "properties": {
    "addr:full":"Maria-Theresien-Str 31 Innsbruck Tirol 6020",
    "addr:housenumber":"31",
    "addr:postcode":"6020",
    "addr:street":"Maria-Theresien-Str;Tirol",
    "iso:country":"AT",
    "sg:address":"Maria-Theresien-Str 31",
    "sg:city":"Innsbruck",
    "sg:orig_category":"Lederwaren / Einzelhandel",
    "sg:phone":"+43 512 564910",
    "sg:postcode":"6020",
    "sg:province":"Tirol",
    "wof:name":"Samsonite GesmbH",
    "wof:placetype":"venue"
},
  "geometry": {"coordinates":[11.3944892883,47.265411377],"type":"Point"}
}