{
  "type": "Feature",
  "properties": {
    "addr:full":"Innsbrucker Str 11 Brixlegg Tirol 6230",
    "addr:postcode":"6230",
    "addr:street":"Str 11;Tirol",
    "iso:country":"AT",
    "sg:address":"Innsbrucker Str 11",
    "sg:city":"Brixlegg",
    "sg:orig_category":"Blumeneinzelhandel",
    "sg:phone":"+43 5337 62316",
    "sg:postcode":"6230",
    "sg:province":"Tirol",
    "wof:name":"Blumenhaus Schie\u00dfling",
    "wof:placetype":"venue"
},
  "geometry": {"coordinates":[11.8756532669,47.427532196],"type":"Point"}
}