{
  "type": "Feature",
  "properties": {
    "addr:full":"Dr.-Theodor-Pfeiffer-Str 40 Puntigam Steiermark 8055",
    "addr:housenumber":"40",
    "addr:postcode":"8055",
    "addr:street":"Dr.-Theodor-Pfeiffer-Str",
    "iso:country":"AT",
    "sg:address":"Dr.-Theodor-Pfeiffer-Str 40",
    "sg:city":"Puntigam",
    "sg:orig_category":"Autobeschriftungen",
    "sg:phone":"+43 4331 6294252",
    "sg:postcode":"8055",
    "sg:province":"Steiermark",
    "wof:name":"Schriften Binder GesmbH",
    "wof:placetype":"venue"
},
  "geometry": {"coordinates":[15.4300384521,47.042011261],"type":"Point"}
}