{
  "type": "Feature",
  "properties": {
    "iso:country":"AT",
    "sg:address":"Kreuzstr 9",
    "sg:city":"St. Lorenzen im M\u00fcrztal",
    "sg:orig_category":"Friseure U Frisiersalons",
    "sg:phone":"+43 4338 642159",
    "sg:postcode":"8642",
    "sg:province":"Steiermark",
    "wof:name":"Schmidt Josef jr",
    "wof:placetype":"venue"
},
  "geometry": {"coordinates":[15.3727340698,47.4814071655],"type":"Point"}
}