{
  "type": "Feature",
  "properties": {
    "addr:full":"Gr\u00fcnburger Str 5 Bad Hall Ober\u00f6sterreich 4540",
    "addr:housenumber":"5",
    "addr:postcode":"4540",
    "addr:street":"Str",
    "iso:country":"AT",
    "sg:address":"Gr\u00fcnburger Str 5",
    "sg:city":"Bad Hall",
    "sg:orig_category":"Transportunternehmen",
    "sg:phone":"+43 7258 30220",
    "sg:postcode":"4540",
    "sg:province":"Ober\u00f6sterreich",
    "wof:name":"Kaiblinger Gerhard Transport GesmbH",
    "wof:placetype":"venue"
},
  "geometry": {"coordinates":[14.2057199478,48.0356216431],"type":"Point"}
}