{
  "type": "Feature",
  "properties": {
    "iso:country":"AT",
    "sg:address":"Bahnhofstr 11",
    "sg:city":"Steyr",
    "sg:orig_category":"Friseure U Frisiersalons",
    "sg:phone":"+43 7252 46251",
    "sg:postcode":"4400",
    "sg:province":"Ober\u00f6sterreich",
    "wof:name":"Intercoiffeur Studio G Inh Gabriele Wild-R\u00f6hrich",
    "wof:placetype":"venue"
},
  "geometry": {"coordinates":[14.4240531921,48.0405807495],"type":"Point"}
}