{
  "type": "Feature",
  "properties": {
    "addr:full":"Rohr1  Fu\u00dfach Vorarlberg 6972",
    "addr:postcode":"6972",
    "iso:country":"AT",
    "sg:address":"Rohr1 ",
    "sg:city":"Fu\u00dfach",
    "sg:classifiers":[
        {
            "category":"Travel",
            "subcategory":"Travel Agent",
            "type":"Entertainment"
        }
    ],
    "sg:phone":"+43 4355 7875708",
    "sg:postcode":"6972",
    "sg:province":"Vorarlberg",
    "sg:tags":[
        "business"
    ],
    "wof:name":"ROHR SPITZ YACHTING SALZMANN GMBH",
    "wof:placetype":"venue"
},
  "geometry": {"coordinates":[-79.8480834961,39.8919715881],"type":"Point"}
}