{
  "type": "Feature",
  "properties": {
    "addr:full":"Ziegelstr 19W Andritz Steiermark 8045",
    "addr:housenumber":"19w",
    "addr:postcode":"8045",
    "addr:street":"Ziegelstr",
    "iso:country":"AT",
    "sg:address":"Ziegelstr 19W",
    "sg:city":"Andritz",
    "sg:orig_category":"Sicherheitstechnik",
    "sg:phone":"+43 4331 6425722",
    "sg:postcode":"8045",
    "sg:province":"Steiermark",
    "wof:name":"Funda Walter",
    "wof:placetype":"venue"
},
  "geometry": {"coordinates":[15.429898262,47.1020126343],"type":"Point"}
}