{
  "type": "Feature",
  "properties": {
    "addr:full":"Kaiserj\u00e4gerstr. 9 Innsbruck Tirol 6020",
    "addr:housenumber":"9",
    "addr:postcode":"6020",
    "addr:street":"Kaiserjaegerstr.;Tirol",
    "iso:country":"AT",
    "sg:address":"Kaiserj\u00e4gerstr. 9",
    "sg:city":"Innsbruck",
    "sg:classifiers":[
        {
            "category":"Banks & Credit Unions",
            "subcategory":"Bank",
            "type":"Services"
        }
    ],
    "sg:phone":"+43 4351 259977",
    "sg:postcode":"6020",
    "sg:province":"Tirol",
    "sg:tags":[
        "banking",
        "institution"
    ],
    "wof:name":"ALPENBANK AG",
    "wof:placetype":"venue"
},
  "geometry": {"coordinates":[11.4004821777,47.2747192383],"type":"Point"}
}