{
  "type": "Feature",
  "properties": {
    "iso:country":"AT",
    "sg:address":"Untere Hauptstr 20",
    "sg:city":"Steinbrunn",
    "sg:orig_category":"Banken U Sparkassen",
    "sg:phone":"+43 2688 722490",
    "sg:postcode":"7035",
    "sg:province":"Burgenland",
    "wof:name":"Raiffeisenbank Steinbrunn",
    "wof:placetype":"venue"
},
  "geometry": {"coordinates":[16.4160919189,47.8346672058],"type":"Point"}
}