{
  "type": "Feature",
  "properties": {
    "iso:country":"AT",
    "sg:address":"Erdbergstr 81",
    "sg:city":"Wien",
    "sg:orig_category":"Friseure U Frisiersalons",
    "sg:phone":"+43 1 7989548",
    "sg:postcode":"1030",
    "sg:province":"Wien",
    "wof:name":"O Haara Scheitz & Nagler KEG",
    "wof:placetype":"venue"
},
  "geometry": {"coordinates":[16.4027996063,48.1974411011],"type":"Point"}
}