{
  "type": "Feature",
  "properties": {
    "iso:country":"AT",
    "sg:address":"Zentrum 54",
    "sg:city":"Kramsach",
    "sg:orig_category":"Friseure U Frisiersalons",
    "sg:phone":"+43 4353 3762702",
    "sg:postcode":"6233",
    "sg:province":"Tirol",
    "wof:name":"M\u00fcck Dietmar",
    "wof:placetype":"venue"
},
  "geometry": {"coordinates":[11.8836288452,47.4468917847],"type":"Point"}
}