{
  "type": "Feature",
  "properties": {
    "addr:full":"M\u00fcnster 403 Brixlegg Tirol 6230",
    "addr:housenumber":"403",
    "addr:postcode":"6230",
    "addr:street":"Muenster;Tirol",
    "iso:country":"AT",
    "sg:address":"M\u00fcnster 403",
    "sg:city":"Brixlegg",
    "sg:orig_category":"Medicinal Spring Waters",
    "sg:phone":"+43 5337 61500",
    "sg:postcode":"6230",
    "sg:province":"Tirol",
    "sg:website":"alpquell.com",
    "wof:name":"Rieders Quellenbetriebe GmbH",
    "wof:placetype":"venue"
},
  "geometry": {"coordinates":[11.8779993057,47.4296073914],"type":"Point"}
}