{
  "type": "Feature",
  "properties": {
    "addr:full":"Anglerstr 10 Klagenfurt K\u00e4rnten 9020",
    "addr:housenumber":"10",
    "addr:postcode":"9020",
    "addr:street":"Anglerstr;Kaernten",
    "iso:country":"AT",
    "sg:address":"Anglerstr 10",
    "sg:city":"Klagenfurt",
    "sg:orig_category":"Inkassoinstitute",
    "sg:phone":"+43 4346 355916",
    "sg:postcode":"9020",
    "sg:province":"K\u00e4rnten",
    "wof:name":"Austria Kreditorengesellschaft OHG Dr Wrulich & Co Nachf",
    "wof:placetype":"venue"
},
  "geometry": {"coordinates":[14.4098052979,46.6275367737],"type":"Point"}
}