{
  "type": "Feature",
  "properties": {
    "addr:full":"Nr 1 Thening Ober\u00f6sterreich 4062",
    "addr:postcode":"4062",
    "addr:street":"Nr;Thening Oberoesterreich",
    "iso:country":"AT",
    "sg:address":"Nr 1",
    "sg:city":"Thening",
    "sg:orig_category":"Feng-Shui",
    "sg:phone":"+43 664 4120408",
    "sg:postcode":"4062",
    "sg:province":"Ober\u00f6sterreich",
    "wof:name":"Kollinger Birgit Mag",
    "wof:placetype":"venue"
},
  "geometry": {"coordinates":[14.1671743393,48.2550582886],"type":"Point"}
}