{
  "type": "Feature",
  "properties": {
    "iso:country":"AT",
    "sg:address":"Georg-Bucher-Str 1",
    "sg:city":"Axams",
    "sg:orig_category":"Sauna U Dampfbad / Bau U Ausstattung",
    "sg:phone":"+43 4365 04437736",
    "sg:postcode":"6094",
    "sg:province":"Tirol",
    "sg:website":"londa.at",
    "wof:name":"L'onda - Wellnessanlagen f\u00fcr Gro\u00df u Klein",
    "wof:placetype":"venue"
},
  "geometry": {"coordinates":[11.2788934708,47.230342865],"type":"Point"}
}