{
  "type": "Feature",
  "properties": {
    "addr:full":"Wedekindg 1 Mattersburg Burgenland 7210",
    "addr:housenumber":"1",
    "addr:postcode":"7210",
    "addr:street":"Wedekindg",
    "iso:country":"AT",
    "sg:address":"Wedekindg 1",
    "sg:city":"Mattersburg",
    "sg:orig_category":"Schlossereien",
    "sg:phone":"+43 2626 63829",
    "sg:postcode":"7210",
    "sg:province":"Burgenland",
    "wof:name":"Irlweg Rudolf",
    "wof:placetype":"venue"
},
  "geometry": {"coordinates":[16.4034061432,47.7390289307],"type":"Point"}
}