{
  "type": "Feature",
  "properties": {
    "iso:country":"AT",
    "sg:address":"Zur Autobahn 9",
    "sg:city":"Wieselburg an der Erlauf",
    "sg:orig_category":"Hafnereien",
    "sg:phone":"+43 4374 1655140",
    "sg:postcode":"3250",
    "sg:province":"Nieder\u00f6sterreich",
    "wof:name":"Nemecek Ofenbau GmbH",
    "wof:placetype":"venue"
},
  "geometry": {"coordinates":[15.1386299133,48.1382598877],"type":"Point"}
}