{
  "type": "Feature",
  "properties": {
    "iso:country":"AT",
    "sg:address":"Frojach 108",
    "sg:city":"Frojach",
    "sg:classifiers":[
        {
            "category":"Home & Garden",
            "subcategory":"Carpets & Floor Coverings",
            "type":"Retail Goods"
        }
    ],
    "sg:phone":"+43 3588 349",
    "sg:postcode":"8841",
    "sg:province":"Steiermark",
    "sg:tags":[
        "grout",
        "adhesive",
        "tiles"
    ],
    "sg:website":"som.at",
    "wof:name":"Erich Kaiser",
    "wof:placetype":"venue"
},
  "geometry": {"coordinates":[14.3118448257,47.1327972412],"type":"Point"}
}