{
  "type": "Feature",
  "properties": {
    "iso:country":"AT",
    "sg:address":"Schumacherstr 4",
    "sg:city":"Salzburg",
    "sg:orig_category":"Textilreinigung",
    "sg:phone":"+43 662 433893",
    "sg:postcode":"5020",
    "sg:province":"Salzburg",
    "wof:name":"Exclusiv Spezialreinigung",
    "wof:placetype":"venue"
},
  "geometry": {"coordinates":[13.0266275406,47.8119812012],"type":"Point"}
}