{
  "type": "Feature",
  "properties": {
    "addr:full":"Anton Karg-Str 2 Kufstein Tirol 6330",
    "addr:housenumber":"2",
    "addr:postcode":"6330",
    "addr:street":"Tirol",
    "iso:country":"AT",
    "sg:address":"Anton Karg-Str 2",
    "sg:city":"Kufstein",
    "sg:orig_category":"Lebensmittel / Erzeugung U Gro\u00c3\u0178handel",
    "sg:phone":"+43 5372 636630",
    "sg:postcode":"6330",
    "sg:province":"Tirol",
    "wof:name":"Weinbaur GmbH",
    "wof:placetype":"venue"
},
  "geometry": {"coordinates":[12.1726503372,47.5861358643],"type":"Point"}
}