{
  "type": "Feature",
  "properties": {
    "iso:country":"AT",
    "sg:address":"Hasnerstr 4",
    "sg:city":"Linz",
    "sg:orig_category":"Steuerberatung",
    "sg:phone":"+43 732 661717",
    "sg:postcode":"4020",
    "sg:province":"Ober\u00f6sterreich",
    "wof:name":"Mc Tax Steuerberatung GmbH",
    "wof:placetype":"venue"
},
  "geometry": {"coordinates":[14.3000869751,48.286365509],"type":"Point"}
}