{
  "type": "Feature",
  "properties": {
    "addr:full":"Im Schaumboden 17 St. Veit an der Glan K\u00e4rnten 9300",
    "addr:housenumber":"17",
    "addr:postcode":"9300",
    "addr:street":"Im Schaumboden;Kaernten",
    "iso:country":"AT",
    "sg:address":"Im Schaumboden 17",
    "sg:city":"St. Veit an der Glan",
    "sg:orig_category":"Appartements / Ferienwohnungen",
    "sg:phone":"+43 4212 8174",
    "sg:postcode":"9300",
    "sg:province":"K\u00e4rnten",
    "wof:name":"Pemberger Hannelore",
    "wof:placetype":"venue"
},
  "geometry": {"coordinates":[14.3591928482,46.7664413452],"type":"Point"}
}