{
  "type": "Feature",
  "properties": {
    "addr:full":"Wolfsbach Nieder\u00f6sterreich 3354",
    "addr:postcode":"3354",
    "iso:country":"AT",
    "sg:city":"Wolfsbach",
    "sg:orig_category":"Medizin, Zahnmedizin",
    "sg:postcode":"3354",
    "sg:province":"Nieder\u00f6sterreich",
    "sg:website":"http://www.zahntechnik-dens-lab.at",
    "wof:name":"Dens Lab Gugler",
    "wof:placetype":"venue"
},
  "geometry": {"coordinates":[14.6686410904,48.0791740417],"type":"Point"}
}