{
  "type": "Feature",
  "properties": {
    "addr:full":"Nr 8 Ilz Steiermark 8262",
    "addr:postcode":"8262",
    "addr:street":"Nr",
    "iso:country":"AT",
    "sg:address":"Nr 8",
    "sg:city":"Ilz",
    "sg:orig_category":"Non-Classified Establishments",
    "sg:phone":"+43 3385 8438",
    "sg:postcode":"8262",
    "sg:province":"Steiermark",
    "wof:name":"Kober Josef",
    "wof:placetype":"venue"
},
  "geometry": {"coordinates":[15.9260549545,47.086479187],"type":"Point"}
}