{
  "type": "Feature",
  "properties": {
    "addr:full":"Klosterneuburger Str 25 Langenzersdorf Nieder\u00f6sterreich 2103",
    "addr:postcode":"2103",
    "addr:street":"Str 25",
    "iso:country":"AT",
    "sg:address":"Klosterneuburger Str 25",
    "sg:city":"Langenzersdorf",
    "sg:orig_category":"Lebensmittel / Einzelhandel",
    "sg:phone":"+43 2244 30333",
    "sg:postcode":"2103",
    "sg:province":"Nieder\u00f6sterreich",
    "wof:name":"Feinkost Br\u00fcnner",
    "wof:placetype":"venue"
},
  "geometry": {"coordinates":[16.3527336121,48.3048858643],"type":"Point"}
}