{
  "type": "Feature",
  "properties": {
    "addr:full":"Mattersburger Str 7 Eisenstadt Burgenland 7000",
    "addr:housenumber":"7",
    "addr:postcode":"7000",
    "addr:street":"Str",
    "iso:country":"AT",
    "sg:address":"Mattersburger Str 7",
    "sg:city":"Eisenstadt",
    "sg:orig_category":"Installationsunternehmen",
    "sg:phone":"+43 2682 651890",
    "sg:postcode":"7000",
    "sg:province":"Burgenland",
    "wof:name":"Palatin Liegenschaftsverwaltungs-GesmbH",
    "wof:placetype":"venue"
},
  "geometry": {"coordinates":[16.5243759155,47.8352203369],"type":"Point"}
}