{
  "type": "Feature",
  "properties": {
    "addr:full":"Hauptstr 16 St. Veit an der G\u00f6lsen Nieder\u00f6sterreich 3161",
    "addr:housenumber":"16",
    "addr:postcode":"3161",
    "addr:street":"Hauptstr;Niederoesterreich",
    "iso:country":"AT",
    "sg:address":"Hauptstr 16",
    "sg:city":"St. Veit an der G\u00f6lsen",
    "sg:orig_category":"Friseure U Frisiersalons",
    "sg:phone":"+43 4327 632038",
    "sg:postcode":"3161",
    "sg:province":"Nieder\u00f6sterreich",
    "wof:name":"Salon Elli",
    "wof:placetype":"venue"
},
  "geometry": {"coordinates":[15.6704187393,48.0430030823],"type":"Point"}
}