{
  "type": "Feature",
  "properties": {
    "addr:full":"Br\u00fcckenweg 4 Bad Wimsbach-Neydharting Ober\u00f6sterreich 4654",
    "addr:housenumber":"4",
    "addr:postcode":"4654",
    "addr:street":"Brueckenweg",
    "iso:country":"AT",
    "sg:address":"Br\u00fcckenweg 4",
    "sg:city":"Bad Wimsbach-Neydharting",
    "sg:classifiers":[
        {
            "category":"Wholesale",
            "subcategory":"Music Publishers",
            "type":"Manufacturing & Wholesale Goods"
        }
    ],
    "sg:phone":"+43 7245 25050",
    "sg:postcode":"4654",
    "sg:province":"Ober\u00f6sterreich",
    "sg:tags":[
        "button",
        "horn",
        "bovine"
    ],
    "wof:name":"Knopffabrik Hofmaninger Gesellschaftsm.b.H.",
    "wof:placetype":"venue"
},
  "geometry": {"coordinates":[13.9008865356,48.0625839233],"type":"Point"}
}