{
  "type": "Feature",
  "properties": {
    "addr:full":"Arndtstr 67 Wien Wien 1120",
    "addr:housenumber":"67",
    "addr:postcode":"1120",
    "addr:street":"Arndtstr",
    "iso:country":"AT",
    "sg:address":"Arndtstr 67",
    "sg:city":"Wien",
    "sg:orig_category":"Gesundheit / Allgemeine Informationsstellen",
    "sg:phone":"+43 1 8113412800",
    "sg:postcode":"1120",
    "sg:province":"Wien",
    "wof:name":"Gesundheits- und Sozialzentrum f\u00fcr den 12. 13. und 23. Bezirk",
    "wof:placetype":"venue"
},
  "geometry": {"coordinates":[16.3290939331,48.1824874878],"type":"Point"}
}