{
  "type": "Feature",
  "properties": {
    "addr:full":"Schikanederg 13 Wien Wien 1040",
    "addr:housenumber":"13",
    "addr:postcode":"1040",
    "addr:street":"Schikanederg",
    "iso:country":"AT",
    "sg:address":"Schikanederg 13",
    "sg:city":"Wien",
    "sg:orig_category":"Exporteure U Importeure",
    "sg:phone":"+43 1 5855510",
    "sg:postcode":"1040",
    "sg:province":"Wien",
    "wof:name":"Vetrimex HandelsgmbH",
    "wof:placetype":"venue"
},
  "geometry": {"coordinates":[16.3631286621,48.1976089478],"type":"Point"}
}