{
  "type": "Feature",
  "properties": {
    "addr:full":"H\u00e4uslhofstr 655 Kaprun Salzburg 5710",
    "addr:housenumber":"655",
    "addr:postcode":"5710",
    "addr:street":"Kaprun Salzburg",
    "iso:country":"AT",
    "sg:address":"H\u00e4uslhofstr 655",
    "sg:city":"Kaprun",
    "sg:orig_category":"Pensionen / Privatzimmer",
    "sg:phone":"+43 6547 8405",
    "sg:postcode":"5710",
    "sg:province":"Salzburg",
    "wof:name":"Klein Christine",
    "wof:placetype":"venue"
},
  "geometry": {"coordinates":[12.7654352188,47.2751808167],"type":"Point"}
}