{
  "type": "Feature",
  "properties": {
    "addr:full":"Albrechtg 1 Graz Steiermark 8010",
    "addr:housenumber":"1",
    "addr:postcode":"8010",
    "addr:street":"Albrechtg",
    "iso:country":"AT",
    "sg:address":"Albrechtg 1",
    "sg:city":"Graz",
    "sg:orig_category":"Museen / Ausstellungen",
    "sg:phone":"+43 316 851500",
    "sg:postcode":"8010",
    "sg:province":"Steiermark",
    "wof:name":"\u00f6sterreichischer Skulpturenpark Privatstiftung",
    "wof:placetype":"venue"
},
  "geometry": {"coordinates":[15.437702179,47.0701332092],"type":"Point"}
}