{
  "type": "Feature",
  "properties": {
    "addr:full":"Hauptstrasse 91 Strasshof an der Nordbahn Nieder\u00f6sterreich 2231",
    "addr:housenumber":"91",
    "addr:postcode":"2231",
    "addr:street":"Hauptstrasse",
    "iso:country":"AT",
    "sg:address":"Hauptstrasse 91",
    "sg:city":"Strasshof an der Nordbahn",
    "sg:classifiers":[
        {
            "category":"Wholesale",
            "subcategory":"Home Furnishings",
            "type":"Manufacturing & Wholesale Goods"
        }
    ],
    "sg:phone":"+43 2287 4696",
    "sg:postcode":"2231",
    "sg:province":"Nieder\u00f6sterreich",
    "sg:tags":[
        "dh",
        "heating",
        "district",
        "system"
    ],
    "sg:website":"farthofer.cc",
    "wof:name":"Herbert Farthofer",
    "wof:placetype":"venue"
},
  "geometry": {"coordinates":[16.6106395721,48.3223457336],"type":"Point"}
}