{
  "type": "Feature",
  "properties": {
    "addr:full":"Tivolig 70 Wien Wien 1120",
    "addr:housenumber":"70",
    "addr:postcode":"1120",
    "addr:street":"Tivolig",
    "iso:country":"AT",
    "sg:address":"Tivolig 70",
    "sg:city":"Wien",
    "sg:orig_category":"Unternehmensberatung",
    "sg:phone":"+43 4318 174020",
    "sg:postcode":"1120",
    "sg:province":"Wien",
    "wof:name":"EUCUSA Gesellschaft f\u00fcr Mitarbeiter- u Kundenorientierung-GmbH",
    "wof:placetype":"venue"
},
  "geometry": {"coordinates":[16.3290939331,48.1824874878],"type":"Point"}
}