{
  "type": "Feature",
  "properties": {
    "addr:full":"R\u00f6merstr 58 Wels Ober\u00f6sterreich 4600",
    "addr:housenumber":"58",
    "addr:postcode":"4600",
    "addr:street":"Roemerstr;Oberoesterreich",
    "iso:country":"AT",
    "sg:address":"R\u00f6merstr 58",
    "sg:city":"Wels",
    "sg:orig_category":"Bauunternehmen",
    "sg:phone":"+43 7242 460350",
    "sg:postcode":"4600",
    "sg:province":"Ober\u00f6sterreich",
    "wof:name":"Kaltenb\u00f6ck & Haller BaugesmbH",
    "wof:placetype":"venue"
},
  "geometry": {"coordinates":[14.018986702,48.1732673645],"type":"Point"}
}