{
  "type": "Feature",
  "properties": {
    "addr:full":"Daniel-Swarovski-Str 4 Absam Tirol 6067",
    "addr:housenumber":"4",
    "addr:postcode":"6067",
    "addr:street":"Daniel-Swarovski-Str;Tirol",
    "iso:country":"AT",
    "sg:address":"Daniel-Swarovski-Str 4",
    "sg:city":"Absam",
    "sg:orig_category":"Alarmanlagen U Sicherheitssysteme",
    "sg:phone":"+43 4352 2352752",
    "sg:postcode":"6067",
    "sg:province":"Tirol",
    "wof:name":"Total Walther Feuerschutz und Sicherheit GmbH",
    "wof:placetype":"venue"
},
  "geometry": {"coordinates":[11.5159873962,47.2935943604],"type":"Point"}
}