{
  "type": "Feature",
  "properties": {
    "iso:country":"AT",
    "sg:address":"Nr 603",
    "sg:city":"Olbendorf",
    "sg:orig_category":"Innenausbau",
    "sg:phone":"+43 3326 54406",
    "sg:postcode":"7534",
    "sg:province":"Burgenland",
    "wof:name":"Heschl Erich",
    "wof:placetype":"venue"
},
  "geometry": {"coordinates":[16.2039165497,47.1885948181],"type":"Point"}
}