{
  "type": "Feature",
  "properties": {
    "iso:country":"AT",
    "sg:address":"Langer Graben 10",
    "sg:city":"Rum",
    "sg:orig_category":"Pensionen / Privatzimmer",
    "sg:phone":"+43 4351 2261404",
    "sg:postcode":"6063",
    "sg:province":"Tirol",
    "wof:name":"Haus H\u00f6lzl",
    "wof:placetype":"venue"
},
  "geometry": {"coordinates":[11.4573917389,47.2849655151],"type":"Point"}
}