{
  "type": "Feature",
  "properties": {
    "addr:full":"Ottakringer Str 91 Wien Wien 1160",
    "addr:postcode":"1160",
    "addr:street":"Str 91",
    "iso:country":"AT",
    "sg:address":"Ottakringer Str 91",
    "sg:city":"Wien",
    "sg:orig_category":"Holdinggesellschaften",
    "sg:phone":"+43 1 49100251",
    "sg:postcode":"1160",
    "sg:province":"Wien",
    "wof:name":"Getr\u00e4nkeindustrie Holding AG",
    "wof:placetype":"venue"
},
  "geometry": {"coordinates":[16.3238945007,48.21326828],"type":"Point"}
}