{
  "type": "Feature",
  "properties": {
    "addr:full":"Mitterg 19 Bruck an der Mur Steiermark 8600",
    "addr:housenumber":"19",
    "addr:postcode":"8600",
    "addr:street":"Mitterg",
    "iso:country":"AT",
    "sg:address":"Mitterg 19",
    "sg:city":"Bruck an der Mur",
    "sg:orig_category":"Friseure U Frisiersalons",
    "sg:phone":"+43 4338 625675515",
    "sg:postcode":"8600",
    "sg:province":"Steiermark",
    "wof:name":"Ihr dm Friseur Studio",
    "wof:placetype":"venue"
},
  "geometry": {"coordinates":[15.272233963,47.4107818604],"type":"Point"}
}