{
  "type": "Feature",
  "properties": {
    "addr:full":"Schumanng 100 Wien Wien 1170",
    "addr:housenumber":"100",
    "addr:postcode":"1170",
    "iso:country":"AT",
    "sg:address":"Schumanng 100",
    "sg:city":"Wien",
    "sg:orig_category":"Ergotherapie",
    "sg:phone":"+43 1 4802580",
    "sg:postcode":"1170",
    "sg:province":"Wien",
    "wof:name":"Roschnik-Wolkenberg Gabriele Dipl-ET",
    "wof:placetype":"venue"
},
  "geometry": {"coordinates":[16.3311157227,48.2245445251],"type":"Point"}
}