{
  "type": "Feature",
  "properties": {
    "addr:full":"Nr 53 Oberwart Burgenland 7400",
    "addr:postcode":"7400",
    "addr:street":"Nr",
    "iso:country":"AT",
    "sg:address":"Nr 53",
    "sg:city":"Oberwart",
    "sg:orig_category":"Autoverwertung",
    "sg:phone":"+43 3352 34127",
    "sg:postcode":"7400",
    "sg:province":"Burgenland",
    "wof:name":"Weber Hans",
    "wof:placetype":"venue"
},
  "geometry": {"coordinates":[172.59916687009999,-43.3058509827],"type":"Point"}
}