{
  "type": "Feature",
  "properties": {
    "iso:country":"AT",
    "sg:address":"Hof 712",
    "sg:city":"Alberschwende",
    "sg:orig_category":"Bibliotheken",
    "sg:phone":"+43 5579 20044",
    "sg:postcode":"6861",
    "sg:province":"Vorarlberg",
    "wof:name":"B\u00fccherei",
    "wof:placetype":"venue"
},
  "geometry": {"coordinates":[9.8315839767,47.4503974915],"type":"Point"}
}