{
  "type": "Feature",
  "properties": {
    "iso:country":"AT",
    "sg:address":"Lachhofweg 4a",
    "sg:city":"Volders",
    "sg:orig_category":"Tischlereien",
    "sg:phone":"+43 664 1102787",
    "sg:postcode":"6111",
    "sg:province":"Tirol",
    "wof:name":"Tischlerei Lechner und Arnold OEG",
    "wof:placetype":"venue"
},
  "geometry": {"coordinates":[11.5531187057,47.2772026062],"type":"Point"}
}