{
  "type": "Feature",
  "properties": {
    "addr:full":"Berthold-Schwarz-Str 33 Klagenfurt K\u00e4rnten 9020",
    "addr:housenumber":"33",
    "addr:postcode":"9020",
    "addr:street":"Berthold-Schwarz-Str;Kaernten",
    "iso:country":"AT",
    "sg:address":"Berthold-Schwarz-Str 33",
    "sg:city":"Klagenfurt",
    "sg:orig_category":"Schlossereien",
    "sg:phone":"+43 463 43268",
    "sg:postcode":"9020",
    "sg:province":"K\u00e4rnten",
    "wof:name":"Kra\u00dfnig Josef",
    "wof:placetype":"venue"
},
  "geometry": {"coordinates":[14.3115177155,46.6644248962],"type":"Point"}
}