{
  "type": "Feature",
  "properties": {
    "addr:full":"Universit\u00e4tspl 4 Graz Steiermark 8010",
    "addr:housenumber":"4",
    "addr:postcode":"8010",
    "addr:street":"Universitaetspl",
    "iso:country":"AT",
    "sg:address":"Universit\u00e4tspl 4",
    "sg:city":"Graz",
    "sg:orig_category":"Institute",
    "sg:phone":"+43 316 3805525",
    "sg:postcode":"8010",
    "sg:province":"Steiermark",
    "wof:name":"Inst f Pharmakognosie Karl Franzens Universit\u00e4t",
    "wof:placetype":"venue"
},
  "geometry": {"coordinates":[15.4492797852,47.0795097351],"type":"Point"}
}