{
  "type": "Feature",
  "properties": {
    "addr:full":"Kirchstetterng 5/3 Wien Wien 1160",
    "addr:housenumber":"5 / 3",
    "addr:postcode":"1160",
    "addr:street":"Kirchstetterng",
    "iso:country":"AT",
    "sg:address":"Kirchstetterng 5/3",
    "sg:city":"Wien",
    "sg:orig_category":"Glockengie\u00c3\u0178ereien",
    "sg:phone":"+43 1 48641320",
    "sg:postcode":"1160",
    "sg:province":"Wien",
    "wof:name":"Grassmayr Johann GesmbH & Co KG",
    "wof:placetype":"venue"
},
  "geometry": {"coordinates":[16.3312911987,48.2050170898],"type":"Point"}
}