{
  "type": "Feature",
  "properties": {
    "addr:full":"Hauptpl 2/2 Spittal an der Drau K\u00e4rnten 9800",
    "addr:housenumber":"2 / 2",
    "addr:postcode":"9800",
    "addr:street":"Hauptpl;Kaernten",
    "iso:country":"AT",
    "sg:address":"Hauptpl 2/2",
    "sg:city":"Spittal an der Drau",
    "sg:orig_category":"Familien / Beratung",
    "sg:phone":"+43 4347 6235994",
    "sg:postcode":"9800",
    "sg:province":"K\u00e4rnten",
    "wof:name":"Verein f Familienmediation u Frauenfragen, berufl Frauenberatung",
    "wof:placetype":"venue"
},
  "geometry": {"coordinates":[13.4965848923,46.7979812622],"type":"Point"}
}