{
  "type": "Feature",
  "properties": {
    "addr:full":"Neukommweg 7 Wien Wien 1130",
    "addr:housenumber":"7",
    "addr:postcode":"1130",
    "addr:street":"Neukommweg",
    "iso:country":"AT",
    "sg:address":"Neukommweg 7",
    "sg:city":"Wien",
    "sg:orig_category":"Transportunternehmen",
    "sg:phone":"+43 1 8046109",
    "sg:postcode":"1130",
    "sg:province":"Wien",
    "wof:name":"Dober Heinrich",
    "wof:placetype":"venue"
},
  "geometry": {"coordinates":[16.2795028687,48.1649665833],"type":"Point"}
}