{
  "type": "Feature",
  "properties": {
    "iso:country":"AT",
    "sg:address":"Goethestr 1a",
    "sg:city":"Linz",
    "sg:orig_category":"Banken U Sparkassen",
    "sg:phone":"+43 4373 269650",
    "sg:postcode":"4020",
    "sg:province":"Ober\u00f6sterreich",
    "wof:name":"PARTNER BANK AG",
    "wof:placetype":"venue"
},
  "geometry": {"coordinates":[14.2921199799,48.2963905334],"type":"Point"}
}