{
  "type": "Feature",
  "properties": {
    "addr:full":"Schellg 2c Illmitz Burgenland 7142",
    "addr:housenumber":"2c",
    "addr:postcode":"7142",
    "addr:street":"Schellg",
    "iso:country":"AT",
    "sg:address":"Schellg 2c",
    "sg:city":"Illmitz",
    "sg:orig_category":"Fotografen",
    "sg:phone":"+43 4321 755002",
    "sg:postcode":"7142",
    "sg:province":"Burgenland",
    "wof:name":"Huber Peter",
    "wof:placetype":"venue"
},
  "geometry": {"coordinates":[16.7985877991,47.7559051514],"type":"Point"}
}