{
  "type": "Feature",
  "properties": {
    "addr:full":"Steyrtalstr 3 Gr\u00fcnburg Ober\u00f6sterreich 4594",
    "addr:housenumber":"3",
    "addr:postcode":"4594",
    "addr:street":"Steyrtalstr;Oberoesterreich",
    "iso:country":"AT",
    "sg:address":"Steyrtalstr 3",
    "sg:city":"Gr\u00fcnburg",
    "sg:orig_category":"Drechslereien",
    "sg:phone":"+43 4372 5772830",
    "sg:postcode":"4594",
    "sg:province":"Ober\u00f6sterreich",
    "wof:name":"Gasplmayr Johann u Roberta GmbH",
    "wof:placetype":"venue"
},
  "geometry": {"coordinates":[14.2564191818,47.9651489258],"type":"Point"}
}