{
  "type": "Feature",
  "properties": {
    "iso:country":"AT",
    "sg:address":"Hauptstr 20",
    "sg:city":"Obertrum am See",
    "sg:orig_category":"Umweltschutz",
    "sg:phone":"+43 6219 20446",
    "sg:postcode":"5162",
    "sg:province":"Salzburg",
    "wof:name":"\u00f6sterreichische Umweltschutzhilfe",
    "wof:placetype":"venue"
},
  "geometry": {"coordinates":[13.0798997879,47.9363517761],"type":"Point"}
}