{
  "type": "Feature",
  "properties": {
    "addr:full":"Ruckerg 40 Wien Wien 1120",
    "addr:housenumber":"40",
    "addr:postcode":"1120",
    "addr:street":"Ruckerg",
    "iso:country":"AT",
    "sg:address":"Ruckerg 40",
    "sg:city":"Wien",
    "sg:orig_category":"Politische Parteien",
    "sg:phone":"+43 1 53427112",
    "sg:postcode":"1120",
    "sg:province":"Wien",
    "wof:name":"Sozialdemokratische Partei \u00f6sterreichs BezOrg Meidling",
    "wof:placetype":"venue"
},
  "geometry": {"coordinates":[16.3264007568,48.1781806946],"type":"Point"}
}