{
  "type": "Feature",
  "properties": {
    "addr:full":"Pfarrweg 15 M\u00f6llbr\u00fccke K\u00e4rnten 9813",
    "addr:housenumber":"15",
    "addr:postcode":"9813",
    "addr:street":"Pfarrweg;Kaernten",
    "iso:country":"AT",
    "sg:address":"Pfarrweg 15",
    "sg:city":"M\u00f6llbr\u00fccke",
    "sg:orig_category":"Anti-Mould Coatings",
    "sg:phone":"+43 4769 35890",
    "sg:postcode":"9813",
    "sg:province":"K\u00e4rnten",
    "wof:name":"Fina GmbH",
    "wof:placetype":"venue"
},
  "geometry": {"coordinates":[13.3749885559,46.831653595],"type":"Point"}
}