{
  "type": "Feature",
  "properties": {
    "addr:full":"Kastnerg 18 Wien Wien 1170",
    "addr:housenumber":"18",
    "addr:postcode":"1170",
    "addr:street":"Kastnerg",
    "iso:country":"AT",
    "sg:address":"Kastnerg 18",
    "sg:city":"Wien",
    "sg:orig_category":"Transportunternehmen",
    "sg:phone":"+43 1 4862555",
    "sg:postcode":"1170",
    "sg:province":"Wien",
    "wof:name":"K\u00f6stler Karl",
    "wof:placetype":"venue"
},
  "geometry": {"coordinates":[16.3310832977,48.2215385437],"type":"Point"}
}