{
  "type": "Feature",
  "properties": {
    "iso:country":"AT",
    "sg:address":"Stiftg 12",
    "sg:city":"Wien",
    "sg:classifiers":[
        {
            "category":"Professional",
            "subcategory":"Computer Services",
            "type":"Services"
        }
    ],
    "sg:phone":"+43 4366 44351584",
    "sg:postcode":"1070",
    "sg:province":"Wien",
    "sg:tags":[
        "software"
    ],
    "wof:name":"ATCOM Data Consulting GmbH",
    "wof:placetype":"venue"
},
  "geometry": {"coordinates":[16.3544235229,48.2034797668],"type":"Point"}
}