{
  "type": "Feature",
  "properties": {
    "addr:full":"Hauptstr 12 Deutsch Wagram Nieder\u00f6sterreich 2232",
    "addr:housenumber":"12",
    "addr:postcode":"2232",
    "addr:street":"Hauptstr",
    "iso:country":"AT",
    "sg:address":"Hauptstr 12",
    "sg:city":"Deutsch Wagram",
    "sg:orig_category":"Banken U Sparkassen",
    "sg:phone":"+43 4322 4770000",
    "sg:postcode":"2232",
    "sg:province":"Nieder\u00f6sterreich",
    "wof:name":"Bankomat der Raiffeisen-Regionalbank G\u00e4nserndorf regGenmbH",
    "wof:placetype":"venue"
},
  "geometry": {"coordinates":[16.5632457733,48.2980728149],"type":"Point"}
}