{
  "type": "Feature",
  "properties": {
    "iso:country":"AT",
    "sg:address":"Poschacherstr 5",
    "sg:city":"Mauthausen",
    "sg:orig_category":"Friseure U Frisiersalons",
    "sg:phone":"+43 7238 3929",
    "sg:postcode":"4310",
    "sg:province":"Ober\u00f6sterreich",
    "wof:name":"Struwelliese - Frisiersalon und Pedik\u00fcrestudio",
    "wof:placetype":"venue"
},
  "geometry": {"coordinates":[14.5266342163,48.2399368286],"type":"Point"}
}