{
  "type": "Feature",
  "properties": {
    "addr:full":"Wei\u00dfkirchner Str 51 Zeltweg Steiermark 8740",
    "addr:housenumber":"51",
    "addr:postcode":"8740",
    "addr:street":"Str",
    "iso:country":"AT",
    "sg:address":"Wei\u00dfkirchner Str 51",
    "sg:city":"Zeltweg",
    "sg:orig_category":"Transportunternehmen",
    "sg:phone":"+43 3577 81207",
    "sg:postcode":"8740",
    "sg:province":"Steiermark",
    "wof:name":"Schmied Alois",
    "wof:placetype":"venue"
},
  "geometry": {"coordinates":[14.7546157837,47.1828765869],"type":"Point"}
}