{
  "type": "Feature",
  "properties": {
    "iso:country":"AT",
    "sg:address":"Sch\u00fctzenweg 34",
    "sg:city":"Vomp",
    "sg:orig_category":"Psychotherapie",
    "sg:phone":"+43 4352 4220042",
    "sg:postcode":"6134",
    "sg:province":"Tirol",
    "wof:name":"Sch\u00f6pf Maria",
    "wof:placetype":"venue"
},
  "geometry": {"coordinates":[11.683139801,47.3420982361],"type":"Point"}
}