{
  "type": "Feature",
  "properties": {
    "addr:full":"Vorberg 8 Ramsau am Dachstein Steiermark 8972",
    "addr:housenumber":"8",
    "addr:postcode":"8972",
    "addr:street":"Vorberg",
    "iso:country":"AT",
    "sg:address":"Vorberg 8",
    "sg:city":"Ramsau am Dachstein",
    "sg:orig_category":"Pensionen / Privatzimmer",
    "sg:phone":"+43 4336 87812890",
    "sg:postcode":"8972",
    "sg:province":"Steiermark",
    "wof:name":"Deutschmann Walpurga Pension Tischlberger",
    "wof:placetype":"venue"
},
  "geometry": {"coordinates":[13.6386823654,47.4179039001],"type":"Point"}
}