{
  "type": "Feature",
  "properties": {
    "addr:full":"Hauptstr 72 Wien Wien 1140",
    "addr:housenumber":"72",
    "addr:postcode":"1140",
    "addr:street":"Hauptstr",
    "iso:country":"AT",
    "sg:address":"Hauptstr 72",
    "sg:city":"Wien",
    "sg:orig_category":"Sonderschulen",
    "sg:phone":"+43 1 9794203",
    "sg:postcode":"1140",
    "sg:province":"Wien",
    "wof:name":"Sonderp\u00e4dagogisches Zentrum f verhaltensauff\u00e4llige Kinder d Stadt Wien",
    "wof:placetype":"venue"
},
  "geometry": {"coordinates":[16.2230644226,48.2094345093],"type":"Point"}
}