{
  "type": "Feature",
  "properties": {
    "iso:country":"AT",
    "sg:address":"Villacher Str 32",
    "sg:city":"Feistritz an der Drau",
    "sg:orig_category":"Bestattungsunternehmen",
    "sg:phone":"+43 4342 4565111",
    "sg:postcode":"9710",
    "sg:province":"K\u00e4rnten",
    "wof:name":"PAX Bestattungs- und Grabst\u00e4ttenfachbetrieb GesmbH",
    "wof:placetype":"venue"
},
  "geometry": {"coordinates":[13.6660671234,46.6996650696],"type":"Point"}
}