{
  "type": "Feature",
  "properties": {
    "iso:country":"AT",
    "sg:address":"Nr 9",
    "sg:city":"Gr\u00e4n",
    "sg:orig_category":"Pensionen / Privatzimmer",
    "sg:phone":"+43 5675 6376",
    "sg:postcode":"6673",
    "sg:province":"Tirol",
    "wof:name":"Scheidle Gabriele - G\u00e4stehaus Zitt",
    "wof:placetype":"venue"
},
  "geometry": {"coordinates":[166.9221496582,-0.5282999873],"type":"Point"}
}