{
  "type": "Feature",
  "properties": {
    "iso:country":"AT",
    "sg:address":"Nikolaus-August-Otto-Str 8",
    "sg:city":"Wiener Neustadt",
    "sg:orig_category":"Beschriftungen",
    "sg:phone":"+43 4326 2261500",
    "sg:postcode":"2700",
    "sg:province":"Nieder\u00f6sterreich",
    "wof:name":"Austroschrift Michael Klapper & Partner Werbetechnik GmbH",
    "wof:placetype":"venue"
},
  "geometry": {"coordinates":[16.2487316132,47.8423614502],"type":"Point"}
}