{
  "type": "Feature",
  "properties": {
    "addr:full":"Auf Arzill 11 Imst Tirol 6460",
    "addr:housenumber":"11",
    "addr:postcode":"6460",
    "addr:street":"Auf Arzill;Tirol",
    "iso:country":"AT",
    "sg:address":"Auf Arzill 11",
    "sg:city":"Imst",
    "sg:orig_category":"Maler, Anstreicher U Lackierer",
    "sg:phone":"+43 4354 1263013",
    "sg:postcode":"6460",
    "sg:province":"Tirol",
    "wof:name":"Neuner Bruno",
    "wof:placetype":"venue"
},
  "geometry": {"coordinates":[10.744562149,47.237033844],"type":"Point"}
}