{
  "type": "Feature",
  "properties": {
    "iso:country":"AT",
    "sg:address":"Zennerstr 14",
    "sg:city":"Wien",
    "sg:orig_category":"Psychotherapie",
    "sg:phone":"+43 664 1833984",
    "sg:postcode":"1140",
    "sg:province":"Wien",
    "wof:name":"Pointner Susanne Mag",
    "wof:placetype":"venue"
},
  "geometry": {"coordinates":[16.3058738708,48.2016716003],"type":"Point"}
}