{
  "type": "Feature",
  "properties": {
    "addr:full":"St. Veiter Str 107 Klagenfurt K\u00e4rnten 9020",
    "addr:housenumber":"107",
    "addr:postcode":"9020",
    "addr:street":"St. Veiter Str;Kaernten",
    "iso:country":"AT",
    "sg:address":"St. Veiter Str 107",
    "sg:city":"Klagenfurt",
    "sg:orig_category":"Apotheken",
    "sg:phone":"+43 463 41771",
    "sg:postcode":"9020",
    "sg:province":"K\u00e4rnten",
    "wof:name":"Nord-Apotheke",
    "wof:placetype":"venue"
},
  "geometry": {"coordinates":[14.3145866394,46.6412849426],"type":"Point"}
}