{
  "type": "Feature",
  "properties": {
    "iso:country":"AT",
    "sg:address":"Erzherzog-Rainer-Ring 2",
    "sg:city":"Baden",
    "sg:orig_category":"Architekten",
    "sg:phone":"+43 4322 5246994",
    "sg:postcode":"2500",
    "sg:province":"Nieder\u00f6sterreich",
    "wof:name":"Hudritsch Peter Dipl-Ing",
    "wof:placetype":"venue"
},
  "geometry": {"coordinates":[16.2327537537,48.0067443848],"type":"Point"}
}