{
  "type": "Feature",
  "properties": {
    "addr:full":"R\u00f6merstr 10 Anif Salzburg 5081",
    "addr:housenumber":"10",
    "addr:postcode":"5081",
    "addr:street":"Roemerstr;Salzburg",
    "iso:country":"AT",
    "sg:address":"R\u00f6merstr 10",
    "sg:city":"Anif",
    "sg:orig_category":"Non-Classified Establishments",
    "sg:phone":"+43 6246 72375",
    "sg:postcode":"5081",
    "sg:province":"Salzburg",
    "wof:name":"Pfarramt r\u00f6m-kath",
    "wof:placetype":"venue"
},
  "geometry": {"coordinates":[13.0645360947,47.7482452393],"type":"Point"}
}