{
  "type": "Feature",
  "properties": {
    "addr:full":"Albertg 57/5 Wien Wien 1080",
    "addr:housenumber":"57 / 5",
    "addr:postcode":"1080",
    "addr:street":"Albertg",
    "iso:country":"AT",
    "sg:address":"Albertg 57/5",
    "sg:city":"Wien",
    "sg:orig_category":"Mediation, Steuerberatung",
    "sg:phone":"+43 1 40885880",
    "sg:postcode":"1080",
    "sg:province":"Wien",
    "sg:website":"www.atp-krejca.at",
    "wof:name":"ATP Andreas Krejca Wirtschaftstreuhand GmbH",
    "wof:placetype":"venue"
},
  "geometry": {"coordinates":[16.3430690765,48.2106552124],"type":"Point"}
}