{
  "type": "Feature",
  "properties": {
    "iso:country":"AT",
    "sg:address":"Nr 89",
    "sg:city":"Eibiswald",
    "sg:orig_category":"Unterhaltungselektronik / Erzeugung U Gro\u00c3\u0178handel",
    "sg:phone":"+43 3466 42328",
    "sg:postcode":"8552",
    "sg:province":"Steiermark",
    "wof:name":"Wallis Universal Maria Kanatschnig - Spezialist f Plattennadeln und Fernbedienungen",
    "wof:placetype":"venue"
},
  "geometry": {"coordinates":[15.2274599075,46.6824150085],"type":"Point"}
}