{
  "type": "Feature",
  "properties": {
    "addr:full":"Friedrich-Torberg-Weg 140 Altaussee Steiermark 8992",
    "addr:housenumber":"140",
    "addr:postcode":"8992",
    "iso:country":"AT",
    "sg:address":"Friedrich-Torberg-Weg 140",
    "sg:city":"Altaussee",
    "sg:orig_category":"Bauunternehmen",
    "sg:phone":"+43 4336 2271322",
    "sg:postcode":"8992",
    "sg:province":"Steiermark",
    "wof:name":"Zeppetzauer - Bau- u Zimmerei GesmbH",
    "wof:placetype":"venue"
},
  "geometry": {"coordinates":[13.764960289,47.6403694153],"type":"Point"}
}