{
  "type": "Feature",
  "properties": {
    "addr:full":"Au 21 Sch\u00f6nwies Tirol 6491",
    "addr:housenumber":"21",
    "addr:postcode":"6491",
    "addr:street":"Au;Tirol",
    "iso:country":"AT",
    "sg:address":"Au 21",
    "sg:city":"Sch\u00f6nwies",
    "sg:orig_category":"Tischlereien",
    "sg:phone":"+43 5412 64195",
    "sg:postcode":"6491",
    "sg:province":"Tirol",
    "wof:name":"Schnegg Thomas",
    "wof:placetype":"venue"
},
  "geometry": {"coordinates":[10.7206449509,47.2138404846],"type":"Point"}
}