{
  "type": "Feature",
  "properties": {
    "iso:country":"AT",
    "sg:address":"Kirchenstrasse 10-14",
    "sg:city":"Amstetten",
    "sg:classifiers":[
        {
            "category":"Education",
            "subcategory":"Special Training",
            "type":"Public Place"
        }
    ],
    "sg:phone":"+43 7472 626750",
    "sg:postcode":"3300",
    "sg:province":"Nieder\u00f6sterreich",
    "sg:tags":[
        "bread"
    ],
    "sg:website":"fleischerei-huerner.at",
    "wof:name":"Karl H\u00fcrner Ges.m.b.H.",
    "wof:placetype":"venue"
},
  "geometry": {"coordinates":[14.8699760437,48.1236763],"type":"Point"}
}