{
  "type": "Feature",
  "properties": {
    "addr:full":"Reiner Strasse 60 Gratwein Steiermark 8112",
    "addr:housenumber":"60",
    "addr:postcode":"8112",
    "addr:street":"Reiner Strasse",
    "iso:country":"AT",
    "sg:address":"Reiner Strasse 60",
    "sg:city":"Gratwein",
    "sg:classifiers":[
        {
            "category":"Home & Garden",
            "subcategory":"Building Materials",
            "type":"Retail Goods"
        }
    ],
    "sg:phone":"+43 3124 51404",
    "sg:postcode":"8112",
    "sg:province":"Steiermark",
    "sg:tags":[
        "steel",
        "metal",
        "made",
        "door",
        "gate"
    ],
    "sg:website":"marchl-stahlbau.at",
    "wof:name":"Marchl Stahlbau Ges.m.b.H.",
    "wof:placetype":"venue"
},
  "geometry": {"coordinates":[15.3115463257,47.1307373047],"type":"Point"}
}