{
  "type": "Feature",
  "properties": {
    "addr:full":"Au\u00dferhalbach 35 Rohrbach an der G\u00f6lsen Nieder\u00f6sterreich 3163",
    "addr:housenumber":"35",
    "addr:postcode":"3163",
    "addr:street":"Ausserhalbach;Niederoesterreich",
    "iso:country":"AT",
    "sg:address":"Au\u00dferhalbach 35",
    "sg:city":"Rohrbach an der G\u00f6lsen",
    "sg:classifiers":[
        {
            "category":"Home & Garden",
            "subcategory":"Building Materials",
            "type":"Retail Goods"
        }
    ],
    "sg:phone":"+43 2763 2613",
    "sg:postcode":"3163",
    "sg:province":"Nieder\u00f6sterreich",
    "sg:tags":[
        "gravel",
        "crushed"
    ],
    "wof:name":"Wilhelm Bachner GesmbH & Co KG",
    "wof:placetype":"venue"
},
  "geometry": {"coordinates":[15.7436361313,48.0416183472],"type":"Point"}
}