{
  "type": "Feature",
  "properties": {
    "iso:country":"AT",
    "sg:address":"Dr.-Theodor-K\u00f6rner-Str 5",
    "sg:city":"Bruck an der Mur",
    "sg:orig_category":"Friseure U Frisiersalons",
    "sg:phone":"+43 4338 6257166",
    "sg:postcode":"8600",
    "sg:province":"Steiermark",
    "wof:name":"haar scharf - Martina Lenhard",
    "wof:placetype":"venue"
},
  "geometry": {"coordinates":[15.2681493759,47.4096832275],"type":"Point"}
}