{
  "type": "Feature",
  "properties": {
    "addr:full":"Moosbachsdlg 154 Uderns Tirol 6271",
    "addr:housenumber":"154",
    "addr:postcode":"6271",
    "addr:street":"Uderns Tirol",
    "iso:country":"AT",
    "sg:address":"Moosbachsdlg 154",
    "sg:city":"Uderns",
    "sg:classifiers":[
        {
            "category":"Taxi",
            "type":"Transportation"
        }
    ],
    "sg:phone":"+43 664 2000157",
    "sg:postcode":"6271",
    "sg:province":"Tirol",
    "sg:tags":[
        "personentransporte",
        "u"
    ],
    "wof:name":"Taxi Peter",
    "wof:placetype":"venue"
},
  "geometry": {"coordinates":[11.8642072678,47.3266906738],"type":"Point"}
}