{
  "type": "Feature",
  "properties": {
    "addr:full":"Sommerhaidenweg 39 Wien Wien 1180",
    "addr:housenumber":"39",
    "addr:postcode":"1180",
    "addr:street":"Sommerhaidenweg",
    "iso:country":"AT",
    "sg:address":"Sommerhaidenweg 39",
    "sg:city":"Wien",
    "sg:orig_category":"Finanz- U Wirtschaftsberatung",
    "sg:phone":"+43 1 44039630",
    "sg:postcode":"1180",
    "sg:province":"Wien",
    "wof:name":"Merit UnternehmensberatungsgesmbH",
    "wof:placetype":"venue"
},
  "geometry": {"coordinates":[16.288022995,48.2507476807],"type":"Point"}
}