{
  "type": "Feature",
  "properties": {
    "iso:country":"AT",
    "sg:address":"Wittelsbachstr 6",
    "sg:city":"Wien",
    "sg:orig_category":"Hauptschulen",
    "sg:phone":"+43 1 7281060",
    "sg:postcode":"1020",
    "sg:province":"Wien",
    "wof:name":"Schulen d Stadt Wien",
    "wof:placetype":"venue"
},
  "geometry": {"coordinates":[16.3997421265,48.2060852051],"type":"Point"}
}