{
  "type": "Feature",
  "properties": {
    "addr:full":"Kaserng 9 Judenburg Steiermark 8750",
    "addr:housenumber":"9",
    "addr:postcode":"8750",
    "addr:street":"Kaserng",
    "iso:country":"AT",
    "sg:address":"Kaserng 9",
    "sg:city":"Judenburg",
    "sg:orig_category":"Fahrschulen",
    "sg:phone":"+43 4335 7282682",
    "sg:postcode":"8750",
    "sg:province":"Steiermark",
    "wof:name":"Blauensteiner Uwe Ing",
    "wof:placetype":"venue"
},
  "geometry": {"coordinates":[14.6621141434,47.169303894],"type":"Point"}
}