{
  "type": "Feature",
  "properties": {
    "iso:country":"AT",
    "sg:address":"Kainachstr 55",
    "sg:city":"Lieboch",
    "sg:orig_category":"Fleischhauereien",
    "sg:phone":"+43 3136 62219",
    "sg:postcode":"8501",
    "sg:province":"Steiermark",
    "wof:name":"Konrad Gabriele",
    "wof:placetype":"venue"
},
  "geometry": {"coordinates":[15.3060483932,46.980430603],"type":"Point"}
}