{
  "type": "Feature",
  "properties": {
    "iso:country":"AT",
    "sg:address":"Automeile 1",
    "sg:city":"Amstetten",
    "sg:orig_category":"Autolackierereien",
    "sg:phone":"+43 7472 6674440",
    "sg:postcode":"3300",
    "sg:province":"Nieder\u00f6sterreich",
    "wof:name":"Chips Away",
    "wof:placetype":"venue"
},
  "geometry": {"coordinates":[14.8706607819,48.1244812012],"type":"Point"}
}