{
  "type": "Feature",
  "properties": {
    "iso:country":"AT",
    "sg:address":"Dietrichsteinpl 2",
    "sg:city":"Graz",
    "sg:classifiers":[
        {
            "category":"Restaurant",
            "type":"Food & Drink"
        }
    ],
    "sg:phone":"+43 316 829584",
    "sg:postcode":"8010",
    "sg:province":"Steiermark",
    "wof:name":"Restaurant Alt Wien",
    "wof:placetype":"venue"
},
  "geometry": {"coordinates":[15.4467792511,47.0666122437],"type":"Point"}
}