{
  "type": "Feature",
  "properties": {
    "addr:full":"Garteng 2 Ollersdorf im Burgenland Burgenland 7533",
    "addr:housenumber":"2",
    "addr:postcode":"7533",
    "addr:street":"Garteng",
    "iso:country":"AT",
    "sg:address":"Garteng 2",
    "sg:city":"Ollersdorf im Burgenland",
    "sg:orig_category":"Schneidereien",
    "sg:phone":"+43 3326 52442",
    "sg:postcode":"7533",
    "sg:province":"Burgenland",
    "wof:name":"Strobl Regina",
    "wof:placetype":"venue"
},
  "geometry": {"coordinates":[16.1646461487,47.1866493225],"type":"Point"}
}