{
  "type": "Feature",
  "properties": {
    "addr:full":"Lawieser Str 126 Tullnerbach Nieder\u00f6sterreich 3013",
    "addr:housenumber":"126",
    "addr:postcode":"3013",
    "addr:street":"Str",
    "iso:country":"AT",
    "sg:address":"Lawieser Str 126",
    "sg:city":"Tullnerbach",
    "sg:orig_category":"Garten- U Landschaftsgestaltung",
    "sg:phone":"+43 4322 3355588",
    "sg:postcode":"3013",
    "sg:province":"Nieder\u00f6sterreich",
    "wof:name":"Pischinger Marcus u Michael OEG",
    "wof:placetype":"venue"
},
  "geometry": {"coordinates":[16.0981845856,48.1843643188],"type":"Point"}
}