{
  "type": "Feature",
  "properties": {
    "addr:full":"Hauptpl 16 Wilhelmsburg an der Traisen Nieder\u00f6sterreich 3150",
    "addr:housenumber":"16",
    "addr:postcode":"3150",
    "addr:street":"Hauptpl;An",
    "iso:country":"AT",
    "sg:address":"Hauptpl 16",
    "sg:city":"Wilhelmsburg an der Traisen",
    "sg:orig_category":"Tabaktrafiken",
    "sg:phone":"+43 4327 468280",
    "sg:postcode":"3150",
    "sg:province":"Nieder\u00f6sterreich",
    "wof:name":"Lind Johann",
    "wof:placetype":"venue"
},
  "geometry": {"coordinates":[15.6061897278,48.1053657532],"type":"Point"}
}