{
  "type": "Feature",
  "properties": {
    "addr:full":"Kasernenstrasse 3b 5073",
    "addr:housenumber":"3b",
    "addr:postcode":"5073",
    "addr:street":"Kasernenstrasse",
    "iso:country":"AT",
    "sg:address":"Kasernenstrasse 3b",
    "sg:classifiers":[
        {
            "category":"Professional",
            "subcategory":"Detective & Security Services",
            "type":"Services"
        }
    ],
    "sg:phone":"+43 662 852830",
    "sg:postcode":"5073",
    "sg:tags":[
        "access",
        "control",
        "ac",
        "system"
    ],
    "sg:website":"dr-weiss.at",
    "wof:name":"Alarmanlagen Dr. Weiss Sicherheitssysteme",
    "wof:placetype":"venue"
},
  "geometry": {"coordinates":[12.9862499237,47.7898788452],"type":"Point"}
}