{
  "type": "Feature",
  "properties": {
    "addr:full":"Ri\u00dfberg 27 Oberndorf in Tirol Tirol 6372",
    "addr:housenumber":"27",
    "addr:postcode":"6372",
    "addr:street":"Rissberg;Tirol",
    "iso:country":"AT",
    "sg:address":"Ri\u00dfberg 27",
    "sg:city":"Oberndorf in Tirol",
    "sg:orig_category":"Pensionen / Privatzimmer",
    "sg:phone":"+43 5356 64201",
    "sg:postcode":"6372",
    "sg:province":"Tirol",
    "wof:name":"Haus Alpenblick",
    "wof:placetype":"venue"
},
  "geometry": {"coordinates":[12.3853178024,47.4997444153],"type":"Point"}
}