{
  "type": "Feature",
  "properties": {
    "addr:full":"Ligusterstr 6 Wels Ober\u00f6sterreich 4600",
    "addr:housenumber":"6",
    "addr:postcode":"4600",
    "addr:street":"Ligusterstr;Oberoesterreich",
    "iso:country":"AT",
    "sg:address":"Ligusterstr 6",
    "sg:city":"Wels",
    "sg:orig_category":"Metallbau",
    "sg:phone":"+43 7242 45003",
    "sg:postcode":"4600",
    "sg:province":"Ober\u00f6sterreich",
    "wof:name":"Pfeiffer Metallbau GmbH",
    "wof:placetype":"venue"
},
  "geometry": {"coordinates":[13.9701919556,48.1419944763],"type":"Point"}
}