{
  "type": "Feature",
  "properties": {
    "addr:full":"Otto Hauberger-Str 24a Kapfenberg Steiermark 8605",
    "addr:housenumber":"24a",
    "addr:postcode":"8605",
    "iso:country":"AT",
    "sg:address":"Otto Hauberger-Str 24a",
    "sg:city":"Kapfenberg",
    "sg:orig_category":"Behinderungen / Leben Mit Behinderungen",
    "sg:phone":"+43 3862 21038",
    "sg:postcode":"8605",
    "sg:province":"Steiermark",
    "wof:name":"Jugend am Werk Steiermark GmbH - Wohnhaus",
    "wof:placetype":"venue"
},
  "geometry": {"coordinates":[15.3043117523,47.4508705139],"type":"Point"}
}