{
  "type": "Feature",
  "properties": {
    "addr:full":"Siemensstr 88 Wien Wien 1210",
    "addr:housenumber":"88",
    "addr:postcode":"1210",
    "addr:street":"Siemensstr",
    "iso:country":"AT",
    "sg:address":"Siemensstr 88",
    "sg:city":"Wien",
    "sg:orig_category":"Banken U Sparkassen",
    "sg:phone":"+43 4350 50539900",
    "sg:postcode":"1210",
    "sg:province":"Wien",
    "wof:name":"Bank Austria Creditanstalt AG",
    "wof:placetype":"venue"
},
  "geometry": {"coordinates":[16.4222049713,48.2699432373],"type":"Point"}
}