{
  "type": "Feature",
  "properties": {
    "addr:full":"Gutenbergstrasse 8 Hohenems Vorarlberg 6845",
    "addr:housenumber":"8",
    "addr:postcode":"6845",
    "addr:street":"Gutenbergstrasse",
    "iso:country":"AT",
    "sg:address":"Gutenbergstrasse 8",
    "sg:city":"Hohenems",
    "sg:orig_category":"ChildrenS Furniture",
    "sg:phone":"+43 5576 77718",
    "sg:postcode":"6845",
    "sg:province":"Vorarlberg",
    "wof:name":"Karl-Heinz Fu\u00dfenegger",
    "wof:placetype":"venue"
},
  "geometry": {"coordinates":[9.6844673157,47.3725776672],"type":"Point"}
}