{
  "type": "Feature",
  "properties": {
    "addr:full":"Neubaug 38 Weiden am See Burgenland 7121",
    "addr:housenumber":"38",
    "addr:postcode":"7121",
    "addr:street":"Neubaug",
    "iso:country":"AT",
    "sg:address":"Neubaug 38",
    "sg:city":"Weiden am See",
    "sg:orig_category":"Pensionen / Privatzimmer",
    "sg:phone":"+43 2167 7341",
    "sg:postcode":"7121",
    "sg:province":"Burgenland",
    "wof:name":"Pension Rose",
    "wof:placetype":"venue"
},
  "geometry": {"coordinates":[16.8681316376,47.926235199],"type":"Point"}
}