{
  "type": "Feature",
  "properties": {
    "addr:full":"Kircheng 31 Eisenstadt Burgenland 7000",
    "addr:housenumber":"31",
    "addr:postcode":"7000",
    "addr:street":"Kircheng",
    "iso:country":"AT",
    "sg:address":"Kircheng 31",
    "sg:city":"Eisenstadt",
    "sg:orig_category":"Bestattungsunternehmen",
    "sg:phone":"+43 4326 8268048",
    "sg:postcode":"7000",
    "sg:province":"Burgenland",
    "wof:name":"Rumpler Maria",
    "wof:placetype":"venue"
},
  "geometry": {"coordinates":[16.5112743378,47.844039917],"type":"Point"}
}