{
  "type": "Feature",
  "properties": {
    "iso:country":"AT",
    "sg:address":"Coburgstr 168",
    "sg:city":"Schladming",
    "sg:orig_category":"Appartements / Ferienwohnungen",
    "sg:phone":"+43 4336 87227850",
    "sg:postcode":"8970",
    "sg:province":"Steiermark",
    "wof:name":"Bio Apparthaus Rosenheim Inh Danklmaier",
    "wof:placetype":"venue"
},
  "geometry": {"coordinates":[13.6916103363,47.3928985596],"type":"Point"}
}