{
  "type": "Feature",
  "properties": {
    "addr:full":"Sch\u00f6ffelstr 9 Waidhofen an der Ybbs Nieder\u00f6sterreich 3340",
    "addr:housenumber":"9",
    "addr:postcode":"3340",
    "addr:street":"Schoeffelstr",
    "iso:country":"AT",
    "sg:address":"Sch\u00f6ffelstr 9",
    "sg:city":"Waidhofen an der Ybbs",
    "sg:orig_category":"\u00c3\u201erzte / F Allgemeinmedizin",
    "sg:phone":"+43 4367 67086992",
    "sg:postcode":"3340",
    "sg:province":"Nieder\u00f6sterreich",
    "wof:name":"Schweiger Kurt Dr",
    "wof:placetype":"venue"
},
  "geometry": {"coordinates":[14.7754945755,47.9575500488],"type":"Point"}
}