{
  "type": "Feature",
  "properties": {
    "addr:full":"Weinzierl 24 Velden am W\u00f6rther See K\u00e4rnten 9220",
    "addr:housenumber":"24",
    "addr:postcode":"9220",
    "addr:street":"Weinzierl;Kaernten",
    "iso:country":"AT",
    "sg:address":"Weinzierl 24",
    "sg:city":"Velden am W\u00f6rther See",
    "sg:orig_category":"Psychologen",
    "sg:phone":"+43 4342 744013",
    "sg:postcode":"9220",
    "sg:province":"K\u00e4rnten",
    "wof:name":"Steger Elisabeth Dr",
    "wof:placetype":"venue"
},
  "geometry": {"coordinates":[14.003370285,46.6165618896],"type":"Point"}
}