{
  "type": "Feature",
  "properties": {
    "iso:country":"AT",
    "sg:address":"Drautalstr 9",
    "sg:city":"M\u00f6llbr\u00fccke",
    "sg:orig_category":"Autohandel",
    "sg:phone":"+43 4769 2363",
    "sg:postcode":"9813",
    "sg:province":"K\u00e4rnten",
    "wof:name":"Pacher Dietmar",
    "wof:placetype":"venue"
},
  "geometry": {"coordinates":[13.3735342026,46.8305854797],"type":"Point"}
}