{
  "type": "Feature",
  "properties": {
    "addr:full":"Innrain 26 Innsbruck Tirol 6020",
    "addr:housenumber":"26",
    "addr:postcode":"6020",
    "addr:street":"Innrain;Tirol",
    "iso:country":"AT",
    "sg:address":"Innrain 26",
    "sg:city":"Innsbruck",
    "sg:orig_category":"Glaswaren",
    "sg:phone":"+43 512 588221",
    "sg:postcode":"6020",
    "sg:province":"Tirol",
    "wof:name":"Kontor Tollinger & Granbichler OEG",
    "wof:placetype":"venue"
},
  "geometry": {"coordinates":[11.3892784119,47.2663421631],"type":"Point"}
}