{
  "type": "Feature",
  "properties": {
    "addr:full":"Wilhelm-Traeger-Str 12 Ried im Innkreis Ober\u00f6sterreich 4910",
    "addr:housenumber":"12",
    "addr:postcode":"4910",
    "addr:street":"Wilhelm-Traeger-Str",
    "iso:country":"AT",
    "sg:address":"Wilhelm-Traeger-Str 12",
    "sg:city":"Ried im Innkreis",
    "sg:orig_category":"Tiertransporte",
    "sg:phone":"+43 664 2867534",
    "sg:postcode":"4910",
    "sg:province":"Ober\u00f6sterreich",
    "wof:name":"Rabenberger Johann GesmbH",
    "wof:placetype":"venue"
},
  "geometry": {"coordinates":[13.4833812714,48.2093849182],"type":"Point"}
}