{
  "type": "Feature",
  "properties": {
    "addr:full":"Reinhartsdorfg 7 Schwechat Nieder\u00f6sterreich 2320",
    "addr:housenumber":"7",
    "addr:postcode":"2320",
    "addr:street":"Reinhartsdorfg;Niederoesterreich",
    "iso:country":"AT",
    "sg:address":"Reinhartsdorfg 7",
    "sg:city":"Schwechat",
    "sg:orig_category":"Stukkateure U Trockenausbauer",
    "sg:phone":"+43 1 70764360",
    "sg:postcode":"2320",
    "sg:province":"Nieder\u00f6sterreich",
    "sg:website":"www.stuck-wimmer.at",
    "wof:name":"Wimmer Josef",
    "wof:placetype":"venue"
},
  "geometry": {"coordinates":[16.4567546844,48.118183136],"type":"Point"}
}