{
  "type": "Feature",
  "properties": {
    "addr:full":"Marianumstr 14 Freistadt Ober\u00f6sterreich 4240",
    "addr:housenumber":"14",
    "addr:postcode":"4240",
    "addr:street":"Marianumstr",
    "iso:country":"AT",
    "sg:address":"Marianumstr 14",
    "sg:city":"Freistadt",
    "sg:classifiers":[
        {
            "category":"Taxi",
            "type":"Transportation"
        }
    ],
    "sg:phone":"+43 4379 4276777",
    "sg:postcode":"4240",
    "sg:province":"Ober\u00f6sterreich",
    "sg:tags":[
        "personentransporte",
        "u"
    ],
    "wof:name":"Funk Taxi - Taxi Mietwagen u Krankentransporte Tag u Nacht",
    "wof:placetype":"venue"
},
  "geometry": {"coordinates":[14.4995632172,48.5128288269],"type":"Point"}
}