{
  "type": "Feature",
  "properties": {
    "addr:full":"\u00c4uleweg 3  Meiningen Vorarlberg 6812",
    "addr:housenumber":"3",
    "addr:postcode":"6812",
    "addr:street":"Aeuleweg",
    "iso:country":"AT",
    "sg:address":"\u00c4uleweg 3 ",
    "sg:city":"Meiningen",
    "sg:classifiers":[
        {
            "category":"Wholesale",
            "subcategory":"Drugs",
            "type":"Manufacturing & Wholesale Goods"
        }
    ],
    "sg:phone":"+43 4355 2231223",
    "sg:postcode":"6812",
    "sg:province":"Vorarlberg",
    "sg:tags":[
        "chemical",
        "pharmaceutical"
    ],
    "wof:name":"CHT AUSTRIA R. BEITLICH GMBH",
    "wof:placetype":"venue"
},
  "geometry": {"coordinates":[9.574877739,47.3040847778],"type":"Point"}
}