{
  "type": "Feature",
  "properties": {
    "iso:country":"AT",
    "sg:address":"Neutorg 22",
    "sg:city":"Graz",
    "sg:orig_category":"Friseure U Frisiersalons",
    "sg:phone":"+43 316 833500",
    "sg:postcode":"8010",
    "sg:province":"Steiermark",
    "wof:name":"Ulli Haarscharf Frisiersalon",
    "wof:placetype":"venue"
},
  "geometry": {"coordinates":[15.4358825684,47.0701599121],"type":"Point"}
}