{
  "type": "Feature",
  "properties": {
    "addr:full":"Bundesstr 9 St. Michael in Obersteiermark Steiermark 8770",
    "addr:housenumber":"9",
    "addr:postcode":"8770",
    "addr:street":"Bundesstr",
    "iso:country":"AT",
    "sg:address":"Bundesstr 9",
    "sg:city":"St. Michael in Obersteiermark",
    "sg:orig_category":"Transportunternehmen",
    "sg:phone":"+43 4338 433272",
    "sg:postcode":"8770",
    "sg:province":"Steiermark",
    "wof:name":"Stiglechner Julius GmbH & Co KG",
    "wof:placetype":"venue"
},
  "geometry": {"coordinates":[15.0290679932,47.3365516663],"type":"Point"}
}