{
  "type": "Feature",
  "properties": {
    "addr:full":"Jakob-Redtenbacher-G 6 Graz Steiermark 8010",
    "addr:housenumber":"6",
    "addr:postcode":"8010",
    "addr:street":"Jakob-Redtenbacher-G",
    "iso:country":"AT",
    "sg:address":"Jakob-Redtenbacher-G 6",
    "sg:city":"Graz",
    "sg:orig_category":"Maler, Anstreicher U Lackierer",
    "sg:phone":"+43 4331 6827697",
    "sg:postcode":"8010",
    "sg:province":"Steiermark",
    "wof:name":"Aflenzer Alfred",
    "wof:placetype":"venue"
},
  "geometry": {"coordinates":[15.4409980774,47.0637626648],"type":"Point"}
}