{
  "type": "Feature",
  "properties": {
    "iso:country":"AT",
    "sg:address":"M\u00fchltal 11",
    "sg:city":"Westendorf",
    "sg:orig_category":"Schlossereien, Maschinenreparatur",
    "sg:phone":"+43 5334 23700",
    "sg:postcode":"6363",
    "sg:province":"Tirol",
    "wof:name":"Steixner Johann",
    "wof:placetype":"venue"
},
  "geometry": {"coordinates":[12.2147397995,47.4321594238],"type":"Point"}
}