{
  "type": "Feature",
  "properties": {
    "addr:full":"Aldranser Str 214 Lans Tirol 6072",
    "addr:housenumber":"214",
    "addr:postcode":"6072",
    "addr:street":"Lans Tirol",
    "iso:country":"AT",
    "sg:address":"Aldranser Str 214",
    "sg:city":"Lans",
    "sg:orig_category":"Polizei U Gendarmerie",
    "sg:phone":"+43 4359 1337116",
    "sg:postcode":"6072",
    "sg:province":"Tirol",
    "wof:name":"Gendarmerie",
    "wof:placetype":"venue"
},
  "geometry": {"coordinates":[11.4354534149,47.2407341003],"type":"Point"}
}