{
  "type": "Feature",
  "properties": {
    "addr:full":"Eichbichlweg 8 Villach K\u00e4rnten 9500",
    "addr:housenumber":"8",
    "addr:postcode":"9500",
    "addr:street":"Eichbichlweg;Kaernten",
    "iso:country":"AT",
    "sg:address":"Eichbichlweg 8",
    "sg:city":"Villach",
    "sg:orig_category":"Finanz- U Wirtschaftsberatung",
    "sg:phone":"+43 4342 4227180",
    "sg:postcode":"9500",
    "sg:province":"K\u00e4rnten",
    "wof:name":"Tscheitschonig Dr Management u WirtschaftsberatungsgesmbH",
    "wof:placetype":"venue"
},
  "geometry": {"coordinates":[13.8530063629,46.6312942505],"type":"Point"}
}