{
  "type": "Feature",
  "properties": {
    "addr:full":"Schlo\u00dfberg 5 Arbing Ober\u00f6sterreich 4341",
    "addr:housenumber":"5",
    "addr:postcode":"4341",
    "addr:street":"Schlossberg",
    "iso:country":"AT",
    "sg:address":"Schlo\u00dfberg 5",
    "sg:city":"Arbing",
    "sg:orig_category":"Non-Classified Establishments",
    "sg:phone":"+43 7269 387",
    "sg:postcode":"4341",
    "sg:province":"Ober\u00f6sterreich",
    "wof:name":"Pfarramt",
    "wof:placetype":"venue"
},
  "geometry": {"coordinates":[14.7062034607,48.2240180969],"type":"Point"}
}