{
  "type": "Feature",
  "properties": {
    "iso:country":"AT",
    "sg:address":"Hardtmuthg 42",
    "sg:city":"Wien",
    "sg:orig_category":"Non-Classified Establishments",
    "sg:phone":"+43 1 601210",
    "sg:postcode":"1100",
    "sg:province":"Wien",
    "wof:name":"Justizanstalt Wien-Favoriten",
    "wof:placetype":"venue"
},
  "geometry": {"coordinates":[16.37251091,48.1699981689],"type":"Point"}
}