{
  "type": "Feature",
  "properties": {
    "addr:full":"Unternberg 102 Tamsweg Salzburg 5580",
    "addr:housenumber":"102",
    "addr:postcode":"5580",
    "addr:street":"Unternberg;Salzburg",
    "iso:country":"AT",
    "sg:address":"Unternberg 102",
    "sg:city":"Tamsweg",
    "sg:classifiers":[
        {
            "category":"Community Center",
            "subcategory":"Senior",
            "type":"Public Place"
        }
    ],
    "sg:phone":"+43 6474 6202",
    "sg:postcode":"5580",
    "sg:province":"Salzburg",
    "sg:tags":[
        "front",
        "wood",
        "door"
    ],
    "wof:name":"Tischlerei Doppler Inh. Maria Sampl",
    "wof:placetype":"venue"
},
  "geometry": {"coordinates":[13.8101902008,47.1263389587],"type":"Point"}
}