{
  "type": "Feature",
  "properties": {
    "iso:country":"AT",
    "sg:address":"Marxerg 19",
    "sg:city":"Wien",
    "sg:orig_category":"Webdesign",
    "sg:phone":"+43 1 5243859",
    "sg:postcode":"1030",
    "sg:province":"Wien",
    "wof:name":"Iwaniewicz-Eberle Karin GmbH",
    "wof:placetype":"venue"
},
  "geometry": {"coordinates":[16.3916225433,48.2064628601],"type":"Point"}
}