{
  "type": "Feature",
  "properties": {
    "iso:country":"AT",
    "sg:address":"Nr 78",
    "sg:city":"Liebenau",
    "sg:orig_category":"Hauptschulen",
    "sg:phone":"+43 4379 538112",
    "sg:postcode":"4252",
    "sg:province":"Ober\u00f6sterreich",
    "wof:name":"Hauptschule",
    "wof:placetype":"venue"
},
  "geometry": {"coordinates":[14.8076267242,48.531665802],"type":"Point"}
}