{
  "type": "Feature",
  "properties": {
    "addr:full":"Tummelpl 3 Graz Steiermark 8010",
    "addr:housenumber":"3",
    "addr:postcode":"8010",
    "addr:street":"Tummelpl",
    "iso:country":"AT",
    "sg:address":"Tummelpl 3",
    "sg:city":"Graz",
    "sg:classifiers":[
        {
            "category":"Home & Garden",
            "subcategory":"Kitchen Supply",
            "type":"Retail Goods"
        }
    ],
    "sg:phone":"+43 4331 6819572",
    "sg:postcode":"8010",
    "sg:province":"Steiermark",
    "sg:tags":[
        "espresso-",
        "u",
        "kaffeemaschinen"
    ],
    "wof:name":"eVino HandelsgmbH",
    "wof:placetype":"venue"
},
  "geometry": {"coordinates":[15.4435930252,47.069984436],"type":"Point"}
}