{
  "type": "Feature",
  "properties": {
    "addr:full":"Tennispointstr 1 Pasching Ober\u00f6sterreich 4061",
    "addr:housenumber":"1",
    "addr:postcode":"4061",
    "addr:street":"Tennispointstr;Oberoesterreich",
    "iso:country":"AT",
    "sg:address":"Tennispointstr 1",
    "sg:city":"Pasching",
    "sg:classifiers":[
        {
            "category":"Restaurant",
            "type":"Food & Drink"
        }
    ],
    "sg:phone":"+43 7229 648810",
    "sg:postcode":"4061",
    "sg:province":"Ober\u00f6sterreich",
    "wof:name":"Restaurant Matchpoint",
    "wof:placetype":"venue"
},
  "geometry": {"coordinates":[14.235077858,48.2456588745],"type":"Point"}
}