{
  "type": "Feature",
  "properties": {
    "iso:country":"AT",
    "sg:address":"Dorf 46",
    "sg:city":"Vomp",
    "sg:orig_category":"Handelsagenturen",
    "sg:phone":"+43 4352 4262219",
    "sg:postcode":"6134",
    "sg:province":"Tirol",
    "wof:name":"Haim Hansj\u00f6rg",
    "wof:placetype":"venue"
},
  "geometry": {"coordinates":[11.6835241318,47.3423919678],"type":"Point"}
}