{
  "type": "Feature",
  "properties": {
    "addr:full":"Wangerstr 2 Adlwang Ober\u00f6sterreich 4541",
    "addr:housenumber":"2",
    "addr:postcode":"4541",
    "addr:street":"Wangerstr",
    "iso:country":"AT",
    "sg:address":"Wangerstr 2",
    "sg:city":"Adlwang",
    "sg:orig_category":"Maschinenbau",
    "sg:phone":"+43 4372 583917",
    "sg:postcode":"4541",
    "sg:province":"Ober\u00f6sterreich",
    "wof:name":"STRASSMAYR Maschinenbau GmbH & Co KG",
    "wof:placetype":"venue"
},
  "geometry": {"coordinates":[14.2218875885,48.0015563965],"type":"Point"}
}