{
  "type": "Feature",
  "properties": {
    "addr:full":"Brodingberg, Brodersdorf 83 Gleisdorf Steiermark 8200",
    "addr:housenumber":"83",
    "addr:postcode":"8200",
    "addr:street":"Brodersdorf",
    "iso:country":"AT",
    "sg:address":"Brodingberg, Brodersdorf 83",
    "sg:city":"Gleisdorf",
    "sg:classifiers":[
        {
            "category":"Home & Garden",
            "subcategory":"Carpets & Floor Coverings",
            "type":"Retail Goods"
        }
    ],
    "sg:phone":"+43 3117 22890",
    "sg:postcode":"8200",
    "sg:province":"Steiermark",
    "sg:tags":[
        "screed",
        "renovation"
    ],
    "wof:name":"Estrich und Industriebodenverlegung Alter Ges.m.b.H.",
    "wof:placetype":"venue"
},
  "geometry": {"coordinates":[15.6912050247,47.103477478],"type":"Point"}
}