{
  "type": "Feature",
  "properties": {
    "addr:full":"Salzburger Str 88 Bischofshofen Salzburg 5500",
    "addr:housenumber":"88",
    "addr:postcode":"5500",
    "addr:street":"Salzburger Str;Salzburg",
    "iso:country":"AT",
    "sg:address":"Salzburger Str 88",
    "sg:city":"Bischofshofen",
    "sg:classifiers":[
        {
            "category":"Taxi",
            "type":"Transportation"
        }
    ],
    "sg:phone":"+43 6462 2200",
    "sg:postcode":"5500",
    "sg:province":"Salzburg",
    "sg:tags":[
        "personentransporte",
        "u"
    ],
    "wof:name":"Bischofshofner Funktaxi",
    "wof:placetype":"venue"
},
  "geometry": {"coordinates":[13.2146368027,47.4243202209],"type":"Point"}
}