{
  "type": "Feature",
  "properties": {
    "addr:full":"Landstr 14/3 Linz Ober\u00f6sterreich 4020",
    "addr:housenumber":"14 / 3",
    "addr:postcode":"4020",
    "addr:street":"Landstr",
    "iso:country":"AT",
    "sg:address":"Landstr 14/3",
    "sg:city":"Linz",
    "sg:orig_category":"Werbeagenturen",
    "sg:phone":"+43 732 9188510",
    "sg:postcode":"4020",
    "sg:province":"Ober\u00f6sterreich",
    "wof:name":"Pill Harald Dr",
    "wof:placetype":"venue"
},
  "geometry": {"coordinates":[14.2884273529,48.3034591675],"type":"Point"}
}