{
  "type": "Feature",
  "properties": {
    "iso:country":"AT",
    "sg:address":"Hobelweg 2",
    "sg:city":"Pucking",
    "sg:orig_category":"Folien",
    "sg:phone":"+43 7229 896960",
    "sg:postcode":"4055",
    "sg:province":"Ober\u00f6sterreich",
    "wof:name":"Eigbrecht Folientechnik GmbH",
    "wof:placetype":"venue"
},
  "geometry": {"coordinates":[14.2137517929,48.1953392029],"type":"Point"}
}