{
  "type": "Feature",
  "properties": {
    "addr:full":"Loquaipl 9 Wien Wien 1060",
    "addr:housenumber":"9",
    "addr:postcode":"1060",
    "addr:street":"Loquaipl",
    "iso:country":"AT",
    "sg:address":"Loquaipl 9",
    "sg:city":"Wien",
    "sg:orig_category":"Reinigungsservice",
    "sg:phone":"+43 1 5979366",
    "sg:postcode":"1060",
    "sg:province":"Wien",
    "wof:name":"Degner Franz",
    "wof:placetype":"venue"
},
  "geometry": {"coordinates":[16.3488235474,48.1952438354],"type":"Point"}
}