{
  "type": "Feature",
  "properties": {
    "iso:country":"AT",
    "sg:address":"Attergaustr 15",
    "sg:city":"St. Georgen im Attergau",
    "sg:classifiers":[
        {
            "category":"Restaurant",
            "type":"Food & Drink"
        }
    ],
    "sg:phone":"+43 76678800",
    "sg:postcode":"4880",
    "sg:province":"Ober\u00f6sterreich",
    "wof:name":"s'Georgerl Pizzeria & Schmankerlstubn",
    "wof:placetype":"venue"
},
  "geometry": {"coordinates":[13.4915714264,47.9329528809],"type":"Point"}
}