{
  "type": "Feature",
  "properties": {
    "iso:country":"AT",
    "sg:address":"Sackstr 7-13",
    "sg:city":"Graz",
    "sg:orig_category":"Lebensmittel / Einzelhandel",
    "sg:phone":"+43 316 827910",
    "sg:postcode":"8010",
    "sg:province":"Steiermark",
    "wof:name":"SPAR \u00f6sterreichische Warenhandels-AG",
    "wof:placetype":"venue"
},
  "geometry": {"coordinates":[15.4370765686,47.0718727112],"type":"Point"}
}