{
  "type": "Feature",
  "properties": {
    "addr:full":"Domgasse 4/3/1/26 Wien Wien 1010",
    "addr:housenumber":"4 / 3 / 1 / 26",
    "addr:postcode":"1010",
    "addr:street":"Domgasse",
    "iso:country":"AT",
    "sg:address":"Domgasse 4/3/1/26",
    "sg:city":"Wien",
    "sg:classifiers":[
        {
            "category":"Structure",
            "subcategory":"Office Building",
            "type":"Public Place"
        }
    ],
    "sg:phone":"+43 1 5127661",
    "sg:postcode":"1010",
    "sg:province":"Wien",
    "sg:tags":[
        "steel",
        "stainless",
        "chimney",
        "element"
    ],
    "sg:website":"rauchfang-quester.at",
    "wof:name":"Rudolf Quester Ges.m.b.H.",
    "wof:placetype":"venue"
},
  "geometry": {"coordinates":[16.3688049316,48.2025489807],"type":"Point"}
}