{
  "type": "Feature",
  "properties": {
    "addr:full":"Weyer 8 Bramberg am Wildkogel Salzburg 5733",
    "addr:housenumber":"8",
    "addr:postcode":"5733",
    "addr:street":"Weyer",
    "iso:country":"AT",
    "sg:address":"Weyer 8",
    "sg:city":"Bramberg am Wildkogel",
    "sg:classifiers":[
        {
            "category":"Building & Trades",
            "subcategory":"Construction",
            "type":"Services"
        }
    ],
    "sg:phone":"+43 4365 667664",
    "sg:postcode":"5733",
    "sg:province":"Salzburg",
    "sg:tags":[
        "aggregate"
    ],
    "wof:name":"Meilinger E-Werk GesmbH",
    "wof:placetype":"venue"
},
  "geometry": {"coordinates":[12.3337306976,47.2665176392],"type":"Point"}
}