{
  "type": "Feature",
  "properties": {
    "addr:full":"Au 95 See Tirol 6553",
    "addr:housenumber":"95",
    "addr:postcode":"6553",
    "addr:street":"Au;Tirol",
    "iso:country":"AT",
    "sg:address":"Au 95",
    "sg:city":"See",
    "sg:orig_category":"Tischlereien",
    "sg:phone":"+43 5441 8210",
    "sg:postcode":"6553",
    "sg:province":"Tirol",
    "wof:name":"Konrad Daniel",
    "wof:placetype":"venue"
},
  "geometry": {"coordinates":[10.4631299973,47.0825309753],"type":"Point"}
}