{
  "type": "Feature",
  "properties": {
    "addr:full":"Engerthstr 52 Wien Wien 1200",
    "addr:housenumber":"52",
    "addr:postcode":"1200",
    "addr:street":"Engerthstr",
    "iso:country":"AT",
    "sg:address":"Engerthstr 52",
    "sg:city":"Wien",
    "sg:orig_category":"Marketingberatung",
    "sg:phone":"+43 4313 3200810",
    "sg:postcode":"1200",
    "sg:province":"Wien",
    "wof:name":"Bilic Milan Dipl-Ing",
    "wof:placetype":"venue"
},
  "geometry": {"coordinates":[16.3807315826,48.2438392639],"type":"Point"}
}