{
  "type": "Feature",
  "properties": {
    "iso:country":"AT",
    "sg:address":"Bahnstr. 3-5 ",
    "sg:city":"P\u00f6chlarn",
    "sg:classifiers":[
        {
            "category":"Food & Beverages",
            "subcategory":"Bakery",
            "type":"Retail Goods"
        }
    ],
    "sg:phone":"+43 4327 5722010",
    "sg:postcode":"3380",
    "sg:province":"Nieder\u00f6sterreich",
    "sg:tags":[
        "grain",
        "cereal"
    ],
    "wof:name":"RAIFFEISEN- LAGERHAUS MOSTVIERTEL MITTE REG. GEN.MBH.",
    "wof:placetype":"venue"
},
  "geometry": {"coordinates":[-79.38526153559999,41.2145881653],"type":"Point"}
}