{
  "type": "Feature",
  "properties": {
    "addr:full":"Prinzersdorfer Str 1 Prinzersdorf Nieder\u00f6sterreich 3385",
    "addr:housenumber":"1",
    "addr:postcode":"3385",
    "addr:street":"Str",
    "iso:country":"AT",
    "sg:address":"Prinzersdorfer Str 1",
    "sg:city":"Prinzersdorf",
    "sg:orig_category":"Non-Classified Establishments",
    "sg:phone":"+43 2749 2372",
    "sg:postcode":"3385",
    "sg:province":"Nieder\u00f6sterreich",
    "wof:name":"Pfarramt",
    "wof:placetype":"venue"
},
  "geometry": {"coordinates":[15.5544900894,48.1992416382],"type":"Point"}
}