{
  "type": "Feature",
  "properties": {
    "addr:full":"Sigmundsg 7 Wien Wien 1070",
    "addr:housenumber":"7",
    "addr:postcode":"1070",
    "addr:street":"Sigmundsg",
    "iso:country":"AT",
    "sg:address":"Sigmundsg 7",
    "sg:city":"Wien",
    "sg:classifiers":[
        {
            "category":"Professional",
            "subcategory":"Art Services",
            "type":"Services"
        }
    ],
    "sg:phone":"+43 1 9671675",
    "sg:postcode":"1070",
    "sg:province":"Wien",
    "sg:tags":[
        "designer"
    ],
    "wof:name":"B\u00fcro Exner Interior & Produkt Design",
    "wof:placetype":"venue"
},
  "geometry": {"coordinates":[16.3532943726,48.2031478882],"type":"Point"}
}