{
  "type": "Feature",
  "properties": {
    "addr:full":"Mirabellpl 6 Salzburg Salzburg 5020",
    "addr:housenumber":"6",
    "addr:postcode":"5020",
    "addr:street":"Mirabellpl;Salzburg",
    "iso:country":"AT",
    "sg:address":"Mirabellpl 6",
    "sg:city":"Salzburg",
    "sg:orig_category":"Friseure U Frisiersalons",
    "sg:phone":"+43 4366 2874960",
    "sg:postcode":"5020",
    "sg:province":"Salzburg",
    "wof:name":"Top Man Haarstudio",
    "wof:placetype":"venue"
},
  "geometry": {"coordinates":[13.0436229706,47.8050193787],"type":"Point"}
}