{
  "type": "Feature",
  "properties": {
    "addr:full":"Wildpretmarkt 7 Wien Wien 1010",
    "addr:housenumber":"7",
    "addr:postcode":"1010",
    "addr:street":"Wildpretmarkt",
    "iso:country":"AT",
    "sg:address":"Wildpretmarkt 7",
    "sg:city":"Wien",
    "sg:orig_category":"Edelsteine",
    "sg:phone":"+43 1 7891045",
    "sg:postcode":"1010",
    "sg:province":"Wien",
    "wof:name":"FACETTE WIEN - Thomas Pfneisl",
    "wof:placetype":"venue"
},
  "geometry": {"coordinates":[16.37159729,48.210521698],"type":"Point"}
}