{
  "type": "Feature",
  "properties": {
    "addr:full":"Nr 27 Stroheim Ober\u00f6sterreich 4074",
    "addr:postcode":"4074",
    "addr:street":"Nr;Stroheim",
    "iso:country":"AT",
    "sg:address":"Nr 27",
    "sg:city":"Stroheim",
    "sg:orig_category":"Non-Classified Establishments",
    "sg:phone":"+43 7272 6231",
    "sg:postcode":"4074",
    "sg:province":"Ober\u00f6sterreich",
    "wof:name":"Pfarramt Stroheim",
    "wof:placetype":"venue"
},
  "geometry": {"coordinates":[13.956949234,48.3375434875],"type":"Point"}
}