{
  "type": "Feature",
  "properties": {
    "addr:full":"Pfeifferstrasse 22 Linz Ober\u00f6sterreich 4040",
    "addr:housenumber":"22",
    "addr:postcode":"4040",
    "addr:street":"Pfeifferstrasse",
    "iso:country":"AT",
    "sg:address":"Pfeifferstrasse 22",
    "sg:city":"Linz",
    "sg:classifiers":[
        {
            "category":"Home & Garden",
            "subcategory":"Furniture",
            "type":"Retail Goods"
        }
    ],
    "sg:phone":"+43 699 11770252",
    "sg:postcode":"4040",
    "sg:province":"Ober\u00f6sterreich",
    "sg:tags":[
        "bathroom"
    ],
    "sg:website":"bau-und-moebel.liwest.at",
    "wof:name":"Telser Thomas (Bau und M\u00f6bel)",
    "wof:placetype":"venue"
},
  "geometry": {"coordinates":[14.2730674744,48.3130760193],"type":"Point"}
}