{
  "type": "Feature",
  "properties": {
    "addr:full":"Karl-Innerebner-Str 49a Innsbruck Tirol 6020",
    "addr:housenumber":"49a",
    "addr:postcode":"6020",
    "addr:street":"Karl-Innerebner-Str;Tirol",
    "iso:country":"AT",
    "sg:address":"Karl-Innerebner-Str 49a",
    "sg:city":"Innsbruck",
    "sg:orig_category":"Zimmereien",
    "sg:phone":"+43 664 1625642",
    "sg:postcode":"6020",
    "sg:province":"Tirol",
    "wof:name":"Pl\u00f6rer Klaus",
    "wof:placetype":"venue"
},
  "geometry": {"coordinates":[11.3632297516,47.2666816711],"type":"Point"}
}