{
  "type": "Feature",
  "properties": {
    "addr:full":"Scheibe 442 Nauders Tirol 6543",
    "addr:housenumber":"442",
    "addr:postcode":"6543",
    "addr:street":"Scheibe;Tirol",
    "iso:country":"AT",
    "sg:address":"Scheibe 442",
    "sg:city":"Nauders",
    "sg:orig_category":"Transportunternehmen",
    "sg:phone":"+43 4367 67446230",
    "sg:postcode":"6543",
    "sg:province":"Tirol",
    "wof:name":"Zegg Andreas",
    "wof:placetype":"venue"
},
  "geometry": {"coordinates":[10.5038547516,46.8894767761],"type":"Point"}
}