{
  "type": "Feature",
  "properties": {
    "addr:full":"Hauptstr 12 Enzesfeld-Lindabrunn Nieder\u00f6sterreich 2551",
    "addr:housenumber":"12",
    "addr:postcode":"2551",
    "addr:street":"Hauptstr;Niederoesterreich",
    "iso:country":"AT",
    "sg:address":"Hauptstr 12",
    "sg:city":"Enzesfeld-Lindabrunn",
    "sg:orig_category":"Gemeinden",
    "sg:phone":"+43 2256 812510",
    "sg:postcode":"2551",
    "sg:province":"Nieder\u00f6sterreich",
    "wof:name":"Marktgemeinde Enzesfeld-Lindabrunn",
    "wof:placetype":"venue"
},
  "geometry": {"coordinates":[16.1868247986,47.9209899902],"type":"Point"}
}