{
  "type": "Feature",
  "properties": {
    "iso:country":"AT",
    "sg:address":"Lasserstr 11",
    "sg:city":"Salzburg",
    "sg:orig_category":"Immobilienmakler",
    "sg:phone":"+43 662 88554613",
    "sg:postcode":"5020",
    "sg:province":"Salzburg",
    "wof:name":"Immobilien K\u00e4fer GesmbH",
    "wof:placetype":"venue"
},
  "geometry": {"coordinates":[13.0498895645,47.8073959351],"type":"Point"}
}