{
  "type": "Feature",
  "properties": {
    "addr:full":"Kirchpl 6 Mittelberg Vorarlberg 6993",
    "addr:housenumber":"6",
    "addr:postcode":"6993",
    "addr:street":"Kirchpl",
    "iso:country":"AT",
    "sg:address":"Kirchpl 6",
    "sg:city":"Mittelberg",
    "sg:orig_category":"Volksschulen",
    "sg:phone":"+43 5517 5546",
    "sg:postcode":"6993",
    "sg:province":"Vorarlberg",
    "wof:name":"Volksschule",
    "wof:placetype":"venue"
},
  "geometry": {"coordinates":[10.1530122757,47.3230361938],"type":"Point"}
}