{
  "type": "Feature",
  "properties": {
    "addr:full":"Schulg 3 Schiltern Nieder\u00f6sterreich 3553",
    "addr:housenumber":"3",
    "addr:postcode":"3553",
    "addr:street":"Schulg;Niederoesterreich",
    "iso:country":"AT",
    "sg:address":"Schulg 3",
    "sg:city":"Schiltern",
    "sg:orig_category":"Volksschulen",
    "sg:phone":"+43 2734 8240",
    "sg:postcode":"3553",
    "sg:province":"Nieder\u00f6sterreich",
    "wof:name":"Volksschule",
    "wof:placetype":"venue"
},
  "geometry": {"coordinates":[15.6203260422,48.5167884827],"type":"Point"}
}