{
  "type": "Feature",
  "properties": {
    "iso:country":"AT",
    "sg:address":"Hauptstr 34",
    "sg:city":"Micheldorf",
    "sg:orig_category":"Lebensmittel / Einzelhandel",
    "sg:phone":"+43 4268 2008",
    "sg:postcode":"9322",
    "sg:province":"K\u00e4rnten",
    "wof:name":"Zamernik Rupert",
    "wof:placetype":"venue"
},
  "geometry": {"coordinates":[14.426697731,46.9158592224],"type":"Point"}
}