{
  "type": "Feature",
  "properties": {
    "addr:full":"Schulgasse 12 Thaur Tirol 6065",
    "addr:housenumber":"12",
    "addr:postcode":"6065",
    "addr:street":"Schulgasse;Tirol",
    "iso:country":"AT",
    "sg:address":"Schulgasse 12",
    "sg:city":"Thaur",
    "sg:classifiers":[
        {
            "category":"Communications",
            "subcategory":"Television Station",
            "type":"Services"
        }
    ],
    "sg:phone":"+43 5223 492604",
    "sg:postcode":"6065",
    "sg:province":"Tirol",
    "sg:tags":[
        "light",
        "therapy",
        "equipment"
    ],
    "sg:website":"sambax.com",
    "wof:name":"SAMBAX GmbH",
    "wof:placetype":"venue"
},
  "geometry": {"coordinates":[11.4741029739,47.2922744751],"type":"Point"}
}