{
  "type": "Feature",
  "properties": {
    "addr:full":"Finsing 47 Uderns Tirol 6271",
    "addr:housenumber":"47",
    "addr:postcode":"6271",
    "addr:street":"Finsing;Tirol",
    "iso:country":"AT",
    "sg:address":"Finsing 47",
    "sg:city":"Uderns",
    "sg:orig_category":"Tischlereien",
    "sg:phone":"+43 5288 63524",
    "sg:postcode":"6271",
    "sg:province":"Tirol",
    "wof:name":"Moser Andreas",
    "wof:placetype":"venue"
},
  "geometry": {"coordinates":[11.8629217148,47.3257598877],"type":"Point"}
}