{
  "type": "Feature",
  "properties": {
    "addr:full":"Kreuzberg 71 Bischofshofen Salzburg 5500",
    "addr:housenumber":"71",
    "addr:postcode":"5500",
    "addr:street":"Kreuzberg;Salzburg",
    "iso:country":"AT",
    "sg:address":"Kreuzberg 71",
    "sg:city":"Bischofshofen",
    "sg:orig_category":"Architekten",
    "sg:phone":"+43 6462 45020",
    "sg:postcode":"5500",
    "sg:province":"Salzburg",
    "wof:name":"Maier Gerhard Dipl-Ing",
    "wof:placetype":"venue"
},
  "geometry": {"coordinates":[13.2250528336,47.4293746948],"type":"Point"}
}