{
  "type": "Feature",
  "properties": {
    "addr:full":"Bergsdlg 5 Prinzersdorf Nieder\u00f6sterreich 3385",
    "addr:housenumber":"5",
    "addr:postcode":"3385",
    "addr:street":"Bergsdlg",
    "iso:country":"AT",
    "sg:address":"Bergsdlg 5",
    "sg:city":"Prinzersdorf",
    "sg:classifiers":[
        {
            "category":"Shopping",
            "subcategory":"Thrift Store",
            "type":"Retail Goods"
        }
    ],
    "sg:phone":"+43 4367 67335741",
    "sg:postcode":"3385",
    "sg:province":"Nieder\u00f6sterreich",
    "sg:tags":[
        "second-hand-shops"
    ],
    "wof:name":"Schn\u00e4ppchen Jagd - An u Verkauf v Neu- u Gebrauchtwaren",
    "wof:placetype":"venue"
},
  "geometry": {"coordinates":[15.5011911392,48.1929016113],"type":"Point"}
}