{
  "type": "Feature",
  "properties": {
    "addr:full":"Dorf 138 Lech Vorarlberg 6764",
    "addr:housenumber":"138",
    "addr:postcode":"6764",
    "addr:street":"Dorf",
    "iso:country":"AT",
    "sg:address":"Dorf 138",
    "sg:city":"Lech",
    "sg:classifiers":[
        {
            "category":"Travel",
            "subcategory":"Hotels & Motels",
            "type":"Entertainment"
        }
    ],
    "sg:phone":"+43 5583 25250",
    "sg:postcode":"6764",
    "sg:province":"Vorarlberg",
    "wof:name":"Pfefferkorn's Hotel",
    "wof:placetype":"venue"
},
  "geometry": {"coordinates":[10.1417798996,47.2082939148],"type":"Point"}
}