{
  "type": "Feature",
  "properties": {
    "iso:country":"AT",
    "sg:address":"Templstr 2",
    "sg:city":"Innsbruck",
    "sg:orig_category":"Steuerberatung",
    "sg:phone":"+43 512 575750",
    "sg:postcode":"6020",
    "sg:province":"Tirol",
    "wof:name":"Andersag Kurt Mag",
    "wof:placetype":"venue"
},
  "geometry": {"coordinates":[11.3933353424,47.2613067627],"type":"Point"}
}