{
  "type": "Feature",
  "properties": {
    "addr:full":"Moosstr Salzburg Salzburg 5020",
    "addr:postcode":"5020",
    "iso:country":"AT",
    "sg:address":"Moosstr",
    "sg:city":"Salzburg",
    "sg:orig_category":"Partyservice",
    "sg:phone":"+43 4366 2625410",
    "sg:postcode":"5020",
    "sg:province":"Salzburg",
    "wof:name":"Partyservice Unterreiner",
    "wof:placetype":"venue"
},
  "geometry": {"coordinates":[13.0301828384,47.7959518433],"type":"Point"}
}