{
  "type": "Feature",
  "properties": {
    "addr:full":"Bierh\u00e4uselbergg 90 Wien Wien 1140",
    "addr:housenumber":"90",
    "addr:postcode":"1140",
    "addr:street":"Bierhaeuselbergg",
    "iso:country":"AT",
    "sg:address":"Bierh\u00e4uselbergg 90",
    "sg:city":"Wien",
    "sg:orig_category":"Werbegrafik- U Grafik-Design",
    "sg:phone":"+43 4314 812566",
    "sg:postcode":"1140",
    "sg:province":"Wien",
    "wof:name":"Concept Design",
    "wof:placetype":"venue"
},
  "geometry": {"coordinates":[16.242143631,48.2063064575],"type":"Point"}
}