{
  "type": "Feature",
  "properties": {
    "iso:country":"AT",
    "sg:address":"F\u00fcrstenstr 47/4",
    "sg:city":"Maria Enzersdorf",
    "sg:orig_category":"Feldenkraismethode",
    "sg:phone":"+43 4322 3643368",
    "sg:postcode":"2344",
    "sg:province":"Nieder\u00f6sterreich",
    "wof:name":"Hartmann Ursula Mag",
    "wof:placetype":"venue"
},
  "geometry": {"coordinates":[16.2838249207,48.0979003906],"type":"Point"}
}