{
  "type": "Feature",
  "properties": {
    "iso:country":"AT",
    "sg:address":"Wiener Str 16",
    "sg:city":"Neusiedl am See",
    "sg:orig_category":"Versicherungsunternehmen",
    "sg:phone":"+43 2167 2696",
    "sg:postcode":"7100",
    "sg:province":"Burgenland",
    "wof:name":"Donau Versicherung",
    "wof:placetype":"venue"
},
  "geometry": {"coordinates":[16.8368854523,47.9525375366],"type":"Point"}
}