{
  "type": "Feature",
  "properties": {
    "addr:full":"Hauptstr 20 Oberwaltersdorf Nieder\u00f6sterreich 2522",
    "addr:housenumber":"20",
    "addr:postcode":"2522",
    "addr:street":"Hauptstr",
    "iso:country":"AT",
    "sg:address":"Hauptstr 20",
    "sg:city":"Oberwaltersdorf",
    "sg:orig_category":"Bankomat-Standorte",
    "sg:phone":"+43 2253 6212",
    "sg:postcode":"2522",
    "sg:province":"Nieder\u00f6sterreich",
    "wof:name":"Bankomat der Vereinigte Volksbanken Baden-M\u00f6dling-Liesing regGenmbH",
    "wof:placetype":"venue"
},
  "geometry": {"coordinates":[16.3225288391,47.9765586853],"type":"Point"}
}