{
  "type": "Feature",
  "properties": {
    "addr:full":"Frauentaler Strasse 14 Deutschlandsberg Steiermark 8530",
    "addr:housenumber":"14",
    "addr:postcode":"8530",
    "addr:street":"Frauentaler Strasse",
    "iso:country":"AT",
    "sg:address":"Frauentaler Strasse 14",
    "sg:city":"Deutschlandsberg",
    "sg:classifiers":[
        {
            "category":"Military Area",
            "subcategory":"Air Force Base",
            "type":"Public Place"
        }
    ],
    "sg:phone":"+43 3462 2667",
    "sg:postcode":"8530",
    "sg:province":"Steiermark",
    "sg:tags":[
        "arrester",
        "system",
        "lightning"
    ],
    "wof:name":"Rudolf Kaup",
    "wof:placetype":"venue"
},
  "geometry": {"coordinates":[15.2173118591,46.8167228699],"type":"Point"}
}