{
  "type": "Feature",
  "properties": {
    "iso:country":"AT",
    "sg:address":"Gro\u00dfmarktstrasse 10-12",
    "sg:city":"Wien",
    "sg:classifiers":[
        {
            "category":"Autos & Motor Vehicles",
            "subcategory":"Auto Supplies",
            "type":"Retail Goods"
        }
    ],
    "sg:phone":"+43 1 610080",
    "sg:postcode":"1230",
    "sg:province":"Wien",
    "sg:tags":[
        "test",
        "automobile",
        "brake",
        "stand"
    ],
    "sg:website":"siems-klein.at",
    "wof:name":"Siems & Klein Autowerkstatt- Technik Vertriebs GmbH",
    "wof:placetype":"venue"
},
  "geometry": {"coordinates":[16.36419487,48.1419410706],"type":"Point"}
}