{
  "type": "Feature",
  "properties": {
    "addr:full":"Lech Vorarlberg 6764",
    "addr:postcode":"6764",
    "iso:country":"AT",
    "sg:city":"Lech",
    "sg:orig_category":"Gemeinden",
    "sg:phone":"+43 4355 8322130",
    "sg:postcode":"6764",
    "sg:province":"Vorarlberg",
    "wof:name":"Gemeindeamt Lech",
    "wof:placetype":"venue"
},
  "geometry": {"coordinates":[10.1417798996,47.2082939148],"type":"Point"}
}