{
  "type": "Feature",
  "properties": {
    "addr:full":"Triflweg 174 Fiss Tirol 6533",
    "addr:housenumber":"174",
    "addr:postcode":"6533",
    "addr:street":"Triflweg;Tirol",
    "iso:country":"AT",
    "sg:address":"Triflweg 174",
    "sg:city":"Fiss",
    "sg:classifiers":[
        {
            "category":"Travel",
            "subcategory":"Hotels & Motels",
            "type":"Entertainment"
        }
    ],
    "sg:phone":"+43 5476 65150",
    "sg:postcode":"6533",
    "sg:province":"Tirol",
    "wof:name":"Dreisonnenhof",
    "wof:placetype":"venue"
},
  "geometry": {"coordinates":[10.6246204376,47.0540885925],"type":"Point"}
}