{
  "type": "Feature",
  "properties": {
    "addr:full":"Obere Hauptstr 19 Maria Lanzendorf Nieder\u00f6sterreich 2326",
    "addr:housenumber":"19",
    "addr:postcode":"2326",
    "addr:street":"Obere Hauptstr",
    "iso:country":"AT",
    "sg:address":"Obere Hauptstr 19",
    "sg:city":"Maria Lanzendorf",
    "sg:orig_category":"Blumeneinzelhandel",
    "sg:phone":"+43 4322 3547116",
    "sg:postcode":"2326",
    "sg:province":"Nieder\u00f6sterreich",
    "wof:name":"G\u00e4rtnerei Nagy Markus",
    "wof:placetype":"venue"
},
  "geometry": {"coordinates":[16.4458179474,48.1117210388],"type":"Point"}
}