{
  "type": "Feature",
  "properties": {
    "addr:full":"Riesstr 16 Graz Steiermark 8010",
    "addr:housenumber":"16",
    "addr:postcode":"8010",
    "addr:street":"Riesstr",
    "iso:country":"AT",
    "sg:address":"Riesstr 16",
    "sg:city":"Graz",
    "sg:orig_category":"Schuhreparatur",
    "sg:phone":"+43 4331 6338406",
    "sg:postcode":"8010",
    "sg:province":"Steiermark",
    "wof:name":"Sommerhuber Franz",
    "wof:placetype":"venue"
},
  "geometry": {"coordinates":[15.4675369263,47.0790405273],"type":"Point"}
}