{
  "type": "Feature",
  "properties": {
    "iso:country":"AT",
    "sg:address":"Bergg 5",
    "sg:city":"Fischamend",
    "sg:orig_category":"Fenster",
    "sg:phone":"+43 2232 775130",
    "sg:postcode":"2401",
    "sg:province":"Nieder\u00f6sterreich",
    "wof:name":"actual Fenstertechnik GmbH",
    "wof:placetype":"venue"
},
  "geometry": {"coordinates":[16.6214694977,48.1171951294],"type":"Point"}
}