{
  "type": "Feature",
  "properties": {
    "addr:full":"Bahnstr 6b Altach Vorarlberg 6844",
    "addr:housenumber":"6b",
    "addr:postcode":"6844",
    "addr:street":"Bahnstr",
    "iso:country":"AT",
    "sg:address":"Bahnstr 6b",
    "sg:city":"Altach",
    "sg:orig_category":"\u00c3\u201erzte / F Allgemeinmedizin",
    "sg:phone":"+43 5576 76829",
    "sg:postcode":"6844",
    "sg:province":"Vorarlberg",
    "wof:name":"Ender Edith Dr",
    "wof:placetype":"venue"
},
  "geometry": {"coordinates":[9.6500692368,47.352809906],"type":"Point"}
}