{
  "type": "Feature",
  "properties": {
    "addr:full":"Heinrich-Gruber-Str 4 Traun Ober\u00f6sterreich 4050",
    "addr:housenumber":"4",
    "addr:postcode":"4050",
    "addr:street":"Heinrich-Gruber-Str",
    "iso:country":"AT",
    "sg:address":"Heinrich-Gruber-Str 4",
    "sg:city":"Traun",
    "sg:orig_category":"Drogerien",
    "sg:phone":"+43 7229 73448",
    "sg:postcode":"4050",
    "sg:province":"Ober\u00f6sterreich",
    "wof:name":"dm drogerie markt GmbH",
    "wof:placetype":"venue"
},
  "geometry": {"coordinates":[14.2389249802,48.2202644348],"type":"Point"}
}