{
  "type": "Feature",
  "properties": {
    "addr:full":"Wlassakstrasse 76  Wien Wien 1130",
    "addr:housenumber":"76",
    "addr:postcode":"1130",
    "addr:street":"Wlassakstrasse",
    "iso:country":"AT",
    "sg:address":"Wlassakstrasse 76 ",
    "sg:city":"Wien",
    "sg:classifiers":[
        {
            "category":"Professional",
            "subcategory":"Detective & Security Services",
            "type":"Services"
        }
    ],
    "sg:phone":"+43 1 87621810",
    "sg:postcode":"1130",
    "sg:province":"Wien",
    "sg:tags":[
        "access",
        "control",
        "ac",
        "system"
    ],
    "sg:website":"www.tt-netcom.com",
    "wof:name":"Telematic & Telemetry Netcom Dataservice u. Vertriebs-GmbH",
    "wof:placetype":"venue"
},
  "geometry": {"coordinates":[16.2633018494,48.1768341064],"type":"Point"}
}