{
  "type": "Feature",
  "properties": {
    "addr:full":"Wiener Strasse 6 Herzogenburg Nieder\u00f6sterreich 3130",
    "addr:housenumber":"6",
    "addr:postcode":"3130",
    "addr:street":"Wiener Strasse",
    "iso:country":"AT",
    "sg:address":"Wiener Strasse 6",
    "sg:city":"Herzogenburg",
    "sg:classifiers":[
        {
            "category":"Arts & Performance",
            "subcategory":"Arts Center",
            "type":"Entertainment"
        }
    ],
    "sg:phone":"+43 2782 82293",
    "sg:postcode":"3130",
    "sg:province":"Nieder\u00f6sterreich",
    "sg:tags":[
        "object",
        "appraisal",
        "structure"
    ],
    "wof:name":"Dipl.-Ing. Rudolf S\u00fc\u00df",
    "wof:placetype":"venue"
},
  "geometry": {"coordinates":[15.6966333389,48.2841491699],"type":"Point"}
}