{
  "type": "Feature",
  "properties": {
    "iso:country":"AT",
    "sg:address":"Wiener Strasse 2",
    "sg:city":"Mariazell",
    "sg:classifiers":[
        {
            "category":"Food & Beverages",
            "subcategory":"Cheese",
            "type":"Retail Goods"
        }
    ],
    "sg:phone":"+43 3882 26110",
    "sg:postcode":"8630",
    "sg:province":"Steiermark",
    "wof:name":"Caj. Arzberger's Nachfolger, Arzberger Ges.m.b.H. & Co KG",
    "wof:placetype":"venue"
},
  "geometry": {"coordinates":[15.3181524277,47.7740249634],"type":"Point"}
}