{
  "type": "Feature",
  "properties": {
    "addr:full":"Untere Hauptstr 15 Jois Burgenland 7093",
    "addr:housenumber":"15",
    "addr:postcode":"7093",
    "addr:street":"Untere Hauptstr",
    "iso:country":"AT",
    "sg:address":"Untere Hauptstr 15",
    "sg:city":"Jois",
    "sg:orig_category":"Pensionen / Privatzimmer",
    "sg:phone":"+43 2160 8220",
    "sg:postcode":"7093",
    "sg:province":"Burgenland",
    "wof:name":"Agerlhof Fam Wetschka",
    "wof:placetype":"venue"
},
  "geometry": {"coordinates":[16.791677475,47.9596214294],"type":"Point"}
}