{
  "type": "Feature",
  "properties": {
    "addr:full":"Aubrunner Weg 1a Linz Ober\u00f6sterreich 4040",
    "addr:housenumber":"1a",
    "addr:postcode":"4040",
    "addr:street":"Aubrunner Weg",
    "iso:country":"AT",
    "sg:address":"Aubrunner Weg 1a",
    "sg:city":"Linz",
    "sg:classifiers":[
        {
            "category":"Restaurant",
            "type":"Food & Drink"
        }
    ],
    "sg:phone":"+43 4373 2245646",
    "sg:postcode":"4040",
    "sg:province":"Ober\u00f6sterreich",
    "sg:tags":[
        "pizzeria"
    ],
    "wof:name":"Pizzeria Bella-Casa",
    "wof:placetype":"venue"
},
  "geometry": {"coordinates":[14.3210134506,48.3348731995],"type":"Point"}
}