{
  "type": "Feature",
  "properties": {
    "iso:country":"AT",
    "sg:address":"Schwarzindien 17",
    "sg:city":"Mondsee",
    "sg:orig_category":"Pensionen / Privatzimmer",
    "sg:phone":"+43 4362 324254",
    "sg:postcode":"5310",
    "sg:province":"Ober\u00f6sterreich",
    "wof:name":"Pension Geier",
    "wof:placetype":"venue"
},
  "geometry": {"coordinates":[13.349562645,47.855255127],"type":"Point"}
}