{
  "type": "Feature",
  "properties": {
    "addr:full":"Nr 25 Strengberg Nieder\u00f6sterreich 3314",
    "addr:postcode":"3314",
    "addr:street":"Nr;Niederoesterreich",
    "iso:country":"AT",
    "sg:address":"Nr 25",
    "sg:city":"Strengberg",
    "sg:orig_category":"Banken U Sparkassen",
    "sg:phone":"+43 4374 3222500",
    "sg:postcode":"3314",
    "sg:province":"Nieder\u00f6sterreich",
    "wof:name":"Raiffeisenbank im Mostviertel Aschbach regGenmbH",
    "wof:placetype":"venue"
},
  "geometry": {"coordinates":[14.6513147354,48.1428489685],"type":"Point"}
}