{
  "type": "Feature",
  "properties": {
    "iso:country":"AT",
    "sg:address":"Rauth 102",
    "sg:city":"Keutschach",
    "sg:orig_category":"Metalle U -Halbfabrikate",
    "sg:phone":"+43 4342 7337700",
    "sg:postcode":"9074",
    "sg:province":"K\u00e4rnten",
    "sg:website":"ivb-gmbh.at",
    "wof:name":"IVB Industrievertretungen GmbH",
    "wof:placetype":"venue"
},
  "geometry": {"coordinates":[14.1858158112,46.5947608948],"type":"Point"}
}