{
  "type": "Feature",
  "properties": {
    "addr:full":"Antoniusstr 6 Strasshof an der Nordbahn Nieder\u00f6sterreich 2231",
    "addr:housenumber":"6",
    "addr:postcode":"2231",
    "addr:street":"Antoniusstr",
    "iso:country":"AT",
    "sg:address":"Antoniusstr 6",
    "sg:city":"Strasshof an der Nordbahn",
    "sg:orig_category":"Glasereien",
    "sg:phone":"+43 4322 872294",
    "sg:postcode":"2231",
    "sg:province":"Nieder\u00f6sterreich",
    "sg:website":"wienglas.at",
    "wof:name":"Glaserei Mislik",
    "wof:placetype":"venue"
},
  "geometry": {"coordinates":[16.6429767609,48.3166770935],"type":"Point"}
}