{
  "type": "Feature",
  "properties": {
    "addr:full":"Ossiacher Zeile 56b Villach K\u00e4rnten 9500",
    "addr:housenumber":"56b",
    "addr:postcode":"9500",
    "addr:street":"Ossiacher Zeile;Kaernten",
    "iso:country":"AT",
    "sg:address":"Ossiacher Zeile 56b",
    "sg:city":"Villach",
    "sg:orig_category":"Lebensmittel / Einzelhandel",
    "sg:phone":"+43 4242 218727",
    "sg:postcode":"9500",
    "sg:province":"K\u00e4rnten",
    "wof:name":"Hofer KG",
    "wof:placetype":"venue"
},
  "geometry": {"coordinates":[13.8586559296,46.6142311096],"type":"Point"}
}