{
  "type": "Feature",
  "properties": {
    "addr:full":"Schnalla 63 Ried im Innkreis Ober\u00f6sterreich 4910",
    "addr:housenumber":"63",
    "addr:postcode":"4910",
    "addr:street":"Schnalla",
    "iso:country":"AT",
    "sg:address":"Schnalla 63",
    "sg:city":"Ried im Innkreis",
    "sg:classifiers":[
        {
            "category":"Autos & Motor Vehicles",
            "subcategory":"Boat Sales",
            "type":"Retail Goods"
        }
    ],
    "sg:phone":"+43 4377 52879740",
    "sg:postcode":"4910",
    "sg:province":"Ober\u00f6sterreich",
    "wof:name":"ECKER YACHT & FLUG GMBH",
    "wof:placetype":"venue"
},
  "geometry": {"coordinates":[13.4873600006,48.2222366333],"type":"Point"}
}