{
  "type": "Feature",
  "properties": {
    "addr:full":"Kaiser-Josef-Pl 19 Wels Ober\u00f6sterreich 4600",
    "addr:housenumber":"19",
    "addr:postcode":"4600",
    "addr:street":"Kaiser-Josef-Pl;Oberoesterreich",
    "iso:country":"AT",
    "sg:address":"Kaiser-Josef-Pl 19",
    "sg:city":"Wels",
    "sg:orig_category":"Textilwaren / Einzelhandel",
    "sg:phone":"+43 7242 211699",
    "sg:postcode":"4600",
    "sg:province":"Ober\u00f6sterreich",
    "wof:name":"Gerald's Strumpfgruben HandelsgesmbH",
    "wof:placetype":"venue"
},
  "geometry": {"coordinates":[14.0228595734,48.1591835022],"type":"Point"}
}