{
  "type": "Feature",
  "properties": {
    "iso:country":"AT",
    "sg:address":"Weidlinger Str. 9 ",
    "sg:city":"Klosterneuburg",
    "sg:classifiers":[
        {
            "category":"Bars & Pubs",
            "subcategory":"Nightclub",
            "type":"Food & Drink"
        }
    ],
    "sg:phone":"+43 4322 4332394",
    "sg:postcode":"3400",
    "sg:province":"Nieder\u00f6sterreich",
    "sg:tags":[
        "cake",
        "bread"
    ],
    "wof:name":"THOMAS BAUMEISTER",
    "wof:placetype":"venue"
},
  "geometry": {"coordinates":[16.3323497772,48.2961502075],"type":"Point"}
}