{
  "type": "Feature",
  "properties": {
    "iso:country":"AT",
    "sg:address":"Gartenstr 48",
    "sg:city":"Wilhering",
    "sg:orig_category":"Tonstudios",
    "sg:phone":"+43 664 1024100",
    "sg:postcode":"4073",
    "sg:province":"Ober\u00f6sterreich",
    "wof:name":"evision",
    "wof:placetype":"venue"
},
  "geometry": {"coordinates":[14.1671791077,48.2996826172],"type":"Point"}
}