{
  "type": "Feature",
  "properties": {
    "addr:full":"Ybbsstr 76 Mauer-\u00d6hling Nieder\u00f6sterreich 3362",
    "addr:housenumber":"76",
    "addr:postcode":"3362",
    "addr:street":"Ybbsstr;Niederoesterreich",
    "iso:country":"AT",
    "sg:address":"Ybbsstr 76",
    "sg:city":"Mauer-\u00d6hling",
    "sg:orig_category":"Werbeartikel U -Geschenke",
    "sg:phone":"+43 4374 7261881",
    "sg:postcode":"3362",
    "sg:province":"Nieder\u00f6sterreich",
    "wof:name":"RIWE-Werbedruck",
    "wof:placetype":"venue"
},
  "geometry": {"coordinates":[14.7985095978,48.1009559631],"type":"Point"}
}