{
  "type": "Feature",
  "properties": {
    "iso:country":"AT",
    "sg:address":"Nr 15",
    "sg:city":"Traunstein",
    "sg:orig_category":"Autobusunternehmen",
    "sg:phone":"+43 2878 6242",
    "sg:postcode":"3632",
    "sg:province":"Nieder\u00f6sterreich",
    "wof:name":"Mayerhofer Maria",
    "wof:placetype":"venue"
},
  "geometry": {"coordinates":[15.1159744263,48.4355010986],"type":"Point"}
}