{
  "type": "Feature",
  "properties": {
    "iso:country":"AT",
    "sg:address":"H\u00fctteldorfer Str 68",
    "sg:city":"Wien",
    "sg:orig_category":"Juwelen, Gold- U Silberwaren / Einzelhandel",
    "sg:phone":"+43 4317 862937",
    "sg:postcode":"1150",
    "sg:province":"Wien",
    "sg:website":"neuwirth.co.at",
    "wof:name":"Neuwirth Ursula",
    "wof:placetype":"venue"
},
  "geometry": {"coordinates":[16.3320903778,48.2006416321],"type":"Point"}
}