{
  "type": "Feature",
  "properties": {
    "iso:country":"AT",
    "sg:address":"Stefanieg 1",
    "sg:city":"Bruck an der Leitha",
    "sg:orig_category":"Politische Parteien",
    "sg:phone":"+43 2162 624260",
    "sg:postcode":"2460",
    "sg:province":"Nieder\u00f6sterreich",
    "wof:name":"Sozialdemokratische Partei \u00f6sterreichs",
    "wof:placetype":"venue"
},
  "geometry": {"coordinates":[16.7797031403,48.0261116028],"type":"Point"}
}