{
  "type": "Feature",
  "properties": {
    "iso:country":"AT",
    "sg:address":"Ahamerweg 4",
    "sg:city":"Ried im Innkreis",
    "sg:orig_category":"Juweliere, Gold- U Silberschmiede",
    "sg:phone":"+43 4377 5282365",
    "sg:postcode":"4910",
    "sg:province":"Ober\u00f6sterreich",
    "wof:name":"Muck Christa",
    "wof:placetype":"venue"
},
  "geometry": {"coordinates":[13.49995327,48.2119216919],"type":"Point"}
}