{
  "type": "Feature",
  "properties": {
    "addr:full":"Bruggerstr 13 Kirchbichl Tirol 6322",
    "addr:housenumber":"13",
    "addr:postcode":"6322",
    "addr:street":"Bruggerstr;Tirol",
    "iso:country":"AT",
    "sg:address":"Bruggerstr 13",
    "sg:city":"Kirchbichl",
    "sg:orig_category":"Fotografen",
    "sg:phone":"+43 4353 3288822",
    "sg:postcode":"6322",
    "sg:province":"Tirol",
    "wof:name":"M\u00fchlanger Roland Mag",
    "wof:placetype":"venue"
},
  "geometry": {"coordinates":[12.0866203308,47.5028686523],"type":"Point"}
}