{
  "type": "Feature",
  "properties": {
    "addr:full":"Paul Ernst-Weg 10 Leibnitz Steiermark 8430",
    "addr:housenumber":"10",
    "addr:postcode":"8430",
    "addr:street":"Ernst-Weg;Steiermark",
    "iso:country":"AT",
    "sg:address":"Paul Ernst-Weg 10",
    "sg:city":"Leibnitz",
    "sg:orig_category":"Gastronomie- U Hotelbedarf",
    "sg:phone":"+43 4334 5286771",
    "sg:postcode":"8430",
    "sg:province":"Steiermark",
    "wof:name":"Allinger Kurt",
    "wof:placetype":"venue"
},
  "geometry": {"coordinates":[15.5498723984,46.7779045105],"type":"Point"}
}