{
  "type": "Feature",
  "properties": {
    "addr:full":"Nr 286 K\u00f6tschach-Mauthen K\u00e4rnten 9640",
    "addr:postcode":"9640",
    "addr:street":"Nr;Koetschach-Mauthen",
    "iso:country":"AT",
    "sg:address":"Nr 286",
    "sg:city":"K\u00f6tschach-Mauthen",
    "sg:orig_category":"Fleischhauereien",
    "sg:phone":"+43 4715 323",
    "sg:postcode":"9640",
    "sg:province":"K\u00e4rnten",
    "wof:name":"Kastner Gottfried",
    "wof:placetype":"venue"
},
  "geometry": {"coordinates":[12.9984302521,46.6670227051],"type":"Point"}
}