{
  "type": "Feature",
  "properties": {
    "addr:full":"Innsbrucker Str 34a/5 Schwaz Tirol 6130",
    "addr:housenumber":"34a / 5",
    "addr:postcode":"6130",
    "addr:street":"Str;Tirol",
    "iso:country":"AT",
    "sg:address":"Innsbrucker Str 34a/5",
    "sg:city":"Schwaz",
    "sg:orig_category":"Werbeagenturen",
    "sg:phone":"+43 5242 72525",
    "sg:postcode":"6130",
    "sg:province":"Tirol",
    "wof:name":"Creativ-Design Mariacher & Friends",
    "wof:placetype":"venue"
},
  "geometry": {"coordinates":[11.7072658539,47.3423805237],"type":"Point"}
}