{
  "type": "Feature",
  "properties": {
    "addr:full":"Wiedner Hauptstr 78 Wien Wien 1040",
    "addr:housenumber":"78",
    "addr:postcode":"1040",
    "addr:street":"Hauptstr",
    "iso:country":"AT",
    "sg:address":"Wiedner Hauptstr 78",
    "sg:city":"Wien",
    "sg:orig_category":"Bekleidung / Einzelhandel",
    "sg:phone":"+43 1 5876623",
    "sg:postcode":"1040",
    "sg:province":"Wien",
    "wof:name":"Sch\u00f6ps Richard & Co AG",
    "wof:placetype":"venue"
},
  "geometry": {"coordinates":[16.364906311,48.1891098022],"type":"Point"}
}