{
  "type": "Feature",
  "properties": {
    "iso:country":"AT",
    "sg:address":"Europapl 7",
    "sg:city":"Knittelfeld",
    "sg:orig_category":"Transportunternehmen",
    "sg:phone":"+43 4335 1273876",
    "sg:postcode":"8720",
    "sg:province":"Steiermark",
    "wof:name":"Diethard Josef",
    "wof:placetype":"venue"
},
  "geometry": {"coordinates":[14.8034410477,47.2082366943],"type":"Point"}
}