{
  "type": "Feature",
  "properties": {
    "addr:full":"Birkenstr 2 Hallwang Salzburg 5300",
    "addr:housenumber":"2",
    "addr:postcode":"5300",
    "addr:street":"Birkenstr;Salzburg",
    "iso:country":"AT",
    "sg:address":"Birkenstr 2",
    "sg:city":"Hallwang",
    "sg:orig_category":"Offsetdruckereien",
    "sg:phone":"+43 662 6686330",
    "sg:postcode":"5300",
    "sg:province":"Salzburg",
    "wof:name":"Druck & digitale Medien Harald Magenschab KEG",
    "wof:placetype":"venue"
},
  "geometry": {"coordinates":[13.0838956833,47.8324584961],"type":"Point"}
}