{
  "type": "Feature",
  "properties": {
    "addr:full":"Johnstr 5-7/Stg 1 Wien Wien 1140",
    "addr:housenumber":"5-7 / stg 1",
    "addr:postcode":"1140",
    "addr:street":"Johnstr",
    "iso:country":"AT",
    "sg:address":"Johnstr 5-7/Stg 1",
    "sg:city":"Wien",
    "sg:orig_category":"\u00c3\u201enderungsschneidereien",
    "sg:phone":"+43 1 9825000",
    "sg:postcode":"1140",
    "sg:province":"Wien",
    "wof:name":"Kacavenda GesmbH",
    "wof:placetype":"venue"
},
  "geometry": {"coordinates":[16.2696990967,48.1994247437],"type":"Point"}
}