{
  "type": "Feature",
  "properties": {
    "addr:full":"K\u00e4rntner Ring 5-7 Wien Wien 1010",
    "addr:housenumber":"5-7",
    "addr:postcode":"1010",
    "addr:street":"Kaerntner Ring",
    "iso:country":"AT",
    "sg:address":"K\u00e4rntner Ring 5-7",
    "sg:city":"Wien",
    "sg:classifiers":[
        {
            "category":"Personal",
            "subcategory":"Shoe Repair & Shine",
            "type":"Services"
        }
    ],
    "sg:phone":"+43 4315 125160",
    "sg:postcode":"1010",
    "sg:province":"Wien",
    "sg:tags":[
        "leather"
    ],
    "wof:name":"LUDWIG G\u00d6RTZ GESMBH",
    "wof:placetype":"venue"
},
  "geometry": {"coordinates":[16.3708763123,48.2022705078],"type":"Point"}
}