{
  "type": "Feature",
  "properties": {
    "iso:country":"AT",
    "sg:address":"Erzherzog-Johann-Str 586",
    "sg:city":"Schladming",
    "sg:orig_category":"Lebensmittel / Erzeugung U Gro\u00c3\u0178handel",
    "sg:phone":"+43 4336 87226290",
    "sg:postcode":"8970",
    "sg:province":"Steiermark",
    "wof:name":"Landmarkt KG Eurogast Schladming",
    "wof:placetype":"venue"
},
  "geometry": {"coordinates":[13.6907081604,47.3944816589],"type":"Point"}
}