{
  "type": "Feature",
  "properties": {
    "addr:full":"Harrachg 23 Graz Steiermark 8010",
    "addr:housenumber":"23",
    "addr:postcode":"8010",
    "addr:street":"Harrachg",
    "iso:country":"AT",
    "sg:address":"Harrachg 23",
    "sg:city":"Graz",
    "sg:orig_category":"Banken U Sparkassen",
    "sg:phone":"+43 5 050536110",
    "sg:postcode":"8010",
    "sg:province":"Steiermark",
    "wof:name":"Bank Austria Creditanstalt AG",
    "wof:placetype":"venue"
},
  "geometry": {"coordinates":[15.4480695724,47.0773162842],"type":"Point"}
}