{
  "type": "Feature",
  "properties": {
    "addr:full":"Michael Haydn-Weg 2 Lamprechtshausen Salzburg 5112",
    "addr:housenumber":"2",
    "addr:postcode":"5112",
    "addr:street":"Haydn-Weg;Salzburg",
    "iso:country":"AT",
    "sg:address":"Michael Haydn-Weg 2",
    "sg:city":"Lamprechtshausen",
    "sg:orig_category":"Direktmarketing",
    "sg:phone":"+43 6274 20348",
    "sg:postcode":"5112",
    "sg:province":"Salzburg",
    "wof:name":"KUBEOS GmbH - Direktmarketingsysteme und Services-Lettershop",
    "wof:placetype":"venue"
},
  "geometry": {"coordinates":[12.9538221359,47.9852485657],"type":"Point"}
}