{
  "type": "Feature",
  "properties": {
    "iso:country":"AT",
    "sg:address":"Percostrasse 18",
    "sg:city":"Wien",
    "sg:classifiers":[
        {
            "category":"Professional",
            "subcategory":"Credit Reporting & Collection",
            "type":"Services"
        }
    ],
    "sg:phone":"+43 1 250800",
    "sg:postcode":"1220",
    "sg:province":"Wien",
    "sg:tags":[
        "processing",
        "data"
    ],
    "sg:website":"piu-printex.at",
    "wof:name":"PIU-PRINTEX Ges. f\u00fcr programmierte Instruktion im Unterricht GmbH",
    "wof:placetype":"venue"
},
  "geometry": {"coordinates":[16.466999054,48.2674980164],"type":"Point"}
}