{
  "type": "Feature",
  "properties": {
    "addr:full":"Hauptpl 8 Mariazell Steiermark 8630",
    "addr:housenumber":"8",
    "addr:postcode":"8630",
    "addr:street":"Hauptpl",
    "iso:country":"AT",
    "sg:address":"Hauptpl 8",
    "sg:city":"Mariazell",
    "sg:orig_category":"Unterhaltungselektronik / Einzelhandel",
    "sg:phone":"+43 3882 6033",
    "sg:postcode":"8630",
    "sg:province":"Steiermark",
    "wof:name":"Margreiter Werner GmbH",
    "wof:placetype":"venue"
},
  "geometry": {"coordinates":[15.3187952042,47.773639679],"type":"Point"}
}