{
  "type": "Feature",
  "properties": {
    "addr:full":"Seeham Salzburg 5164",
    "addr:postcode":"5164",
    "iso:country":"AT",
    "sg:city":"Seeham",
    "sg:orig_category":"Feuerwehren",
    "sg:phone":"+43 6217 5897",
    "sg:postcode":"5164",
    "sg:province":"Salzburg",
    "wof:name":"Feuerwehr Seeham",
    "wof:placetype":"venue"
},
  "geometry": {"coordinates":[13.078578949,47.9681854248],"type":"Point"}
}