{
  "type": "Feature",
  "properties": {
    "addr:full":"Wiener Str Parz 1693 Himberg Nieder\u00f6sterreich 2325",
    "addr:postcode":"1693;2325",
    "addr:street":"Parz;Niederoesterreich",
    "iso:country":"AT",
    "sg:address":"Wiener Str Parz 1693",
    "sg:city":"Himberg",
    "sg:orig_category":"Bauunternehmen",
    "sg:phone":"+43 2235 87514",
    "sg:postcode":"2325",
    "sg:province":"Nieder\u00f6sterreich",
    "wof:name":"Jovanovic Bau KEG",
    "wof:placetype":"venue"
},
  "geometry": {"coordinates":[16.4394855499,48.0822868347],"type":"Point"}
}