{
  "type": "Feature",
  "properties": {
    "addr:full":"Salcherstr 108 St. P\u00f6lten-Harland Nieder\u00f6sterreich 3104",
    "addr:housenumber":"108",
    "addr:postcode":"3104",
    "addr:street":"St. Poelten-Harland",
    "iso:country":"AT",
    "sg:address":"Salcherstr 108",
    "sg:city":"St. P\u00f6lten-Harland",
    "sg:orig_category":"Tischlereien",
    "sg:phone":"+43 2742 881197",
    "sg:postcode":"3104",
    "sg:province":"Nieder\u00f6sterreich",
    "wof:name":"Masopust Thomas",
    "wof:placetype":"venue"
},
  "geometry": {"coordinates":[15.6398267746,48.1571121216],"type":"Point"}
}