{
  "type": "Feature",
  "properties": {
    "iso:country":"AT",
    "sg:address":"Treustr 29",
    "sg:city":"Wien",
    "sg:orig_category":"Waren Aller Art",
    "sg:phone":"+43 1 33052440",
    "sg:postcode":"1200",
    "sg:province":"Wien",
    "wof:name":"Eximpol Industriewaren HandelsgesmbH",
    "wof:placetype":"venue"
},
  "geometry": {"coordinates":[16.3657684326,48.2292404175],"type":"Point"}
}