{
  "type": "Feature",
  "properties": {
    "iso:country":"AT",
    "sg:address":"Hackhoferg 18",
    "sg:city":"Wien",
    "sg:orig_category":"Museen / Ausstellungen",
    "sg:phone":"+43 1 3185416",
    "sg:postcode":"1190",
    "sg:province":"Wien",
    "wof:name":"Lehar-Schikaneder-Schl\u00f6ssl",
    "wof:placetype":"venue"
},
  "geometry": {"coordinates":[16.3656387329,48.2618331909],"type":"Point"}
}