{
  "type": "Feature",
  "properties": {
    "iso:country":"AT",
    "sg:address":"Georg-Grinninger-Str 81",
    "sg:city":"Traun",
    "sg:orig_category":"Friseure U Frisiersalons",
    "sg:phone":"+43 4372 2975086",
    "sg:postcode":"4050",
    "sg:province":"Ober\u00f6sterreich",
    "wof:name":"Salon Sabine",
    "wof:placetype":"venue"
},
  "geometry": {"coordinates":[14.2307128906,48.2289581299],"type":"Point"}
}