{
  "type": "Feature",
  "properties": {
    "iso:country":"AT",
    "sg:address":"Hauptpl 35",
    "sg:city":"St. Ruprecht an der Raab",
    "sg:orig_category":"Blumeneinzelhandel",
    "sg:phone":"+43 4331 782492",
    "sg:postcode":"8181",
    "sg:province":"Steiermark",
    "wof:name":"Hasenh\u00fctl Blumen-Kr\u00e4nze",
    "wof:placetype":"venue"
},
  "geometry": {"coordinates":[15.6622104645,47.1534233093],"type":"Point"}
}