{
  "type": "Feature",
  "properties": {
    "iso:country":"AT",
    "sg:address":"Burgg 9/1",
    "sg:city":"Graz",
    "sg:orig_category":"Energieberatung U -Untersuchung",
    "sg:phone":"+43 316 8773413",
    "sg:postcode":"8010",
    "sg:province":"Steiermark",
    "wof:name":"Energieberatungsstelle Land Steiermark",
    "wof:placetype":"venue"
},
  "geometry": {"coordinates":[15.4439067841,47.0710601807],"type":"Point"}
}