{
  "type": "Feature",
  "properties": {
    "addr:full":"Porschestr 1 Enns Ober\u00f6sterreich 4470",
    "addr:housenumber":"1",
    "addr:postcode":"4470",
    "addr:street":"Porschestr",
    "iso:country":"AT",
    "sg:address":"Porschestr 1",
    "sg:city":"Enns",
    "sg:orig_category":"Fenster",
    "sg:phone":"+43 800 0234456",
    "sg:postcode":"4470",
    "sg:province":"Ober\u00f6sterreich",
    "sg:website":"optima-fenster.at, www.optima.at",
    "wof:name":"OPTIMA Fenster GmbH",
    "wof:placetype":"venue"
},
  "geometry": {"coordinates":[14.4792346954,48.2137947083],"type":"Point"}
}