{
  "type": "Feature",
  "properties": {
    "addr:full":"St. P\u00f6ltner Str 1 Kilb Nieder\u00f6sterreich 3233",
    "addr:housenumber":"1",
    "addr:postcode":"3233",
    "addr:street":"Str",
    "iso:country":"AT",
    "sg:address":"St. P\u00f6ltner Str 1",
    "sg:city":"Kilb",
    "sg:orig_category":"Elektroinstallationsunternehmen",
    "sg:phone":"+43 2748 73510",
    "sg:postcode":"3233",
    "sg:province":"Nieder\u00f6sterreich",
    "wof:name":"Schadner Leopold",
    "wof:placetype":"venue"
},
  "geometry": {"coordinates":[15.4123630524,48.1020851135],"type":"Point"}
}