{
  "type": "Feature",
  "properties": {
    "addr:full":"Stadl 6 Moosdorf Ober\u00f6sterreich 5141",
    "addr:housenumber":"6",
    "addr:postcode":"5141",
    "addr:street":"Stadl",
    "iso:country":"AT",
    "sg:address":"Stadl 6",
    "sg:city":"Moosdorf",
    "sg:classifiers":[
        {
            "category":"Communications",
            "subcategory":"Film & Video Production",
            "type":"Services"
        }
    ],
    "sg:phone":"+43 7748 26500",
    "sg:postcode":"5141",
    "sg:province":"Ober\u00f6sterreich",
    "sg:tags":[
        "multimedia"
    ],
    "wof:name":"Writer's Company Media GmbH",
    "wof:placetype":"venue"
},
  "geometry": {"coordinates":[12.999997139,48.0469894409],"type":"Point"}
}