{
  "type": "Feature",
  "properties": {
    "addr:full":"Gumpendorfer Str 124 Wien Wien 1060",
    "addr:housenumber":"124",
    "addr:postcode":"1060",
    "iso:country":"AT",
    "sg:address":"Gumpendorfer Str 124",
    "sg:city":"Wien",
    "sg:orig_category":"Friseure U Frisiersalons",
    "sg:phone":"+43 4315 968957",
    "sg:postcode":"1060",
    "sg:province":"Wien",
    "wof:name":"Cerkez Nevenka - Frisiersalon NANCY",
    "wof:placetype":"venue"
},
  "geometry": {"coordinates":[16.3420124054,48.190776825],"type":"Point"}
}