{
  "type": "Feature",
  "properties": {
    "addr:full":"Gymnasiumstr 58 Wien Wien 1190",
    "addr:housenumber":"58",
    "addr:postcode":"1190",
    "addr:street":"Gymnasiumstr",
    "iso:country":"AT",
    "sg:address":"Gymnasiumstr 58",
    "sg:city":"Wien",
    "sg:classifiers":[
        {
            "category":"Restaurant",
            "type":"Food & Drink"
        }
    ],
    "sg:phone":"+43 1 9690471",
    "sg:postcode":"1190",
    "sg:province":"Wien",
    "wof:name":"Nuhro Gastronomie- und HandelsgesmbH",
    "wof:placetype":"venue"
},
  "geometry": {"coordinates":[16.3485374451,48.2346763611],"type":"Point"}
}