{
  "type": "Feature",
  "properties": {
    "iso:country":"AT",
    "sg:address":"Wiener Str 34",
    "sg:city":"Kirchstetten",
    "sg:orig_category":"Banken U Sparkassen",
    "sg:phone":"+43 2743 86800",
    "sg:postcode":"3062",
    "sg:province":"Nieder\u00f6sterreich",
    "wof:name":"Volksbank Nieder\u00f6sterreich-Mitte regGenmbH",
    "wof:placetype":"venue"
},
  "geometry": {"coordinates":[15.8206634521,48.1898384094],"type":"Point"}
}