{
  "type": "Feature",
  "properties": {
    "iso:country":"AT",
    "sg:address":"Bahnhofstr 1-3",
    "sg:city":"Steyr",
    "sg:orig_category":"Nachhilfe U Lernbetreuung",
    "sg:phone":"+43 4372 5250722",
    "sg:postcode":"4400",
    "sg:province":"Ober\u00f6sterreich",
    "wof:name":"Learn Up - Lern u Trainingszentrum Grafendorfer",
    "wof:placetype":"venue"
},
  "geometry": {"coordinates":[14.4230184555,48.0415763855],"type":"Point"}
}