{
  "type": "Feature",
  "properties": {
    "addr:full":"Anzengruberstrasse 20 Traun Ober\u00f6sterreich 4050",
    "addr:housenumber":"20",
    "addr:postcode":"4050",
    "addr:street":"Anzengruberstrasse",
    "iso:country":"AT",
    "sg:address":"Anzengruberstrasse 20",
    "sg:city":"Traun",
    "sg:orig_category":"Anti-Mould Coatings",
    "sg:phone":"+43 7229 62902",
    "sg:postcode":"4050",
    "sg:province":"Ober\u00f6sterreich",
    "wof:name":"Strecker Malereibetriebsges.m.b.H.",
    "wof:placetype":"venue"
},
  "geometry": {"coordinates":[14.259147644,48.2426185608],"type":"Point"}
}