{
  "type": "Feature",
  "properties": {
    "addr:full":"Ansch\u00fctzgasse 1 Wien Wien 1150",
    "addr:housenumber":"1",
    "addr:postcode":"1150",
    "addr:street":"Anschuetzgasse",
    "iso:country":"AT",
    "sg:address":"Ansch\u00fctzgasse 1",
    "sg:city":"Wien",
    "sg:classifiers":[
        {
            "category":"Building & Trades",
            "subcategory":"Construction",
            "type":"Services"
        }
    ],
    "sg:phone":"+43 1 89191451",
    "sg:postcode":"1150",
    "sg:province":"Wien",
    "sg:tags":[
        "duct",
        "cable"
    ],
    "wof:name":"Franz B\u00f6ck's Nachf. Ing. Eva & Karl Schindler Ges.m.b.H .",
    "wof:placetype":"venue"
},
  "geometry": {"coordinates":[16.3320903778,48.2006416321],"type":"Point"}
}