{
  "type": "Feature",
  "properties": {
    "addr:full":"Lengbachlstr 19 Altlengbach Nieder\u00f6sterreich 3033",
    "addr:housenumber":"19",
    "addr:postcode":"3033",
    "addr:street":"Lengbachlstr",
    "iso:country":"AT",
    "sg:address":"Lengbachlstr 19",
    "sg:city":"Altlengbach",
    "sg:orig_category":"Drechslereien",
    "sg:phone":"+43 2774 6279",
    "sg:postcode":"3033",
    "sg:province":"Nieder\u00f6sterreich",
    "wof:name":"Gutscher Josef",
    "wof:placetype":"venue"
},
  "geometry": {"coordinates":[15.9633178711,48.148979187],"type":"Point"}
}