{
  "type": "Feature",
  "properties": {
    "iso:country":"AT",
    "sg:address":"Jechtenham 16",
    "sg:city":"Taufkirchen an der Pram",
    "sg:classifiers":[
        {
            "category":"Science Facility",
            "type":"Public Place"
        }
    ],
    "sg:phone":"+43 7719 85850",
    "sg:postcode":"4775",
    "sg:province":"Ober\u00f6sterreich",
    "sg:tags":[
        "sanitary",
        "internal",
        "partition"
    ],
    "sg:website":"palme-dusch.com",
    "wof:name":"Palme Dusch-Abtrennungen Ges.m.b.H. & Co",
    "wof:placetype":"venue"
},
  "geometry": {"coordinates":[13.515794754,48.4124298096],"type":"Point"}
}