{
  "type": "Feature",
  "properties": {
    "addr:full":"Wiener Str 1 Langenlois Nieder\u00f6sterreich 3550",
    "addr:postcode":"3550",
    "addr:street":"Niederoesterreich",
    "iso:country":"AT",
    "sg:address":"Wiener Str 1",
    "sg:city":"Langenlois",
    "sg:orig_category":"Papier- U Schreibwaren / Einzelhandel",
    "sg:phone":"+43 2734 2238",
    "sg:postcode":"3550",
    "sg:province":"Nieder\u00f6sterreich",
    "wof:name":"Murth - Inh Poscharnig KEG",
    "wof:placetype":"venue"
},
  "geometry": {"coordinates":[15.6776828766,48.4720153809],"type":"Point"}
}