{
  "type": "Feature",
  "properties": {
    "addr:full":"Bruck 55 St. Martin im Innkreis Ober\u00f6sterreich 4973",
    "addr:housenumber":"55",
    "addr:postcode":"4973",
    "addr:street":"Bruck",
    "iso:country":"AT",
    "sg:address":"Bruck 55",
    "sg:city":"St. Martin im Innkreis",
    "sg:orig_category":"Musikgruppen",
    "sg:phone":"+43 7751 20230",
    "sg:postcode":"4973",
    "sg:province":"Ober\u00f6sterreich",
    "wof:name":"Musikverein Senftenbach",
    "wof:placetype":"venue"
},
  "geometry": {"coordinates":[13.4221353531,48.2661743164],"type":"Point"}
}