{
  "type": "Feature",
  "properties": {
    "iso:country":"AT",
    "sg:address":"Erlerstr 13",
    "sg:city":"Innsbruck",
    "sg:orig_category":"Non-Classified Establishments",
    "sg:phone":"+43 512 582140",
    "sg:postcode":"6020",
    "sg:province":"Tirol",
    "wof:name":"dekor-shop KEG",
    "wof:placetype":"venue"
},
  "geometry": {"coordinates":[11.3961858749,47.2657356262],"type":"Point"}
}