{
  "type": "Feature",
  "properties": {
    "addr:full":"Hauptpl 26 Ried im Innkreis Ober\u00f6sterreich 4910",
    "addr:housenumber":"26",
    "addr:postcode":"4910",
    "addr:street":"Hauptpl",
    "iso:country":"AT",
    "sg:address":"Hauptpl 26",
    "sg:city":"Ried im Innkreis",
    "sg:orig_category":"Damenmoden",
    "sg:phone":"+43 7752 80008",
    "sg:postcode":"4910",
    "sg:province":"Ober\u00f6sterreich",
    "wof:name":"Mairinger Haus",
    "wof:placetype":"venue"
},
  "geometry": {"coordinates":[13.4895401001,48.2102851868],"type":"Point"}
}