{
  "type": "Feature",
  "properties": {
    "addr:full":"Obere Hauptstr 61 Wulkaprodersdorf Burgenland 7041",
    "addr:housenumber":"61",
    "addr:postcode":"7041",
    "addr:street":"Obere Hauptstr",
    "iso:country":"AT",
    "sg:address":"Obere Hauptstr 61",
    "sg:city":"Wulkaprodersdorf",
    "sg:orig_category":"Non-Classified Establishments",
    "sg:phone":"+43 2687 62303",
    "sg:postcode":"7041",
    "sg:province":"Burgenland",
    "wof:name":"Pfarramt",
    "wof:placetype":"venue"
},
  "geometry": {"coordinates":[16.4942722321,47.7937088013],"type":"Point"}
}