{
  "type": "Feature",
  "properties": {
    "addr:full":"Nr 9 Piesendorf Salzburg 5721",
    "addr:postcode":"5721",
    "addr:street":"Nr;Salzburg",
    "iso:country":"AT",
    "sg:address":"Nr 9",
    "sg:city":"Piesendorf",
    "sg:classifiers":[
        {
            "category":"Travel",
            "subcategory":"Hotels & Motels",
            "type":"Entertainment"
        }
    ],
    "sg:phone":"+43 6549 81700",
    "sg:postcode":"5721",
    "sg:province":"Salzburg",
    "wof:name":"Golf- & Sporthotel Select GmbH",
    "wof:placetype":"venue"
},
  "geometry": {"coordinates":[6.2247400284,49.5246315002],"type":"Point"}
}