{
  "type": "Feature",
  "properties": {
    "iso:country":"AT",
    "sg:address":"Nr 147",
    "sg:city":"Kirchbach",
    "sg:orig_category":"Tischlereien",
    "sg:phone":"+43 4284 254",
    "sg:postcode":"9632",
    "sg:province":"K\u00e4rnten",
    "wof:name":"Telesklav Hubert",
    "wof:placetype":"venue"
},
  "geometry": {"coordinates":[13.1851024628,46.6416473389],"type":"Point"}
}