{
  "type": "Feature",
  "properties": {
    "addr:full":"Ottakringer Str 144 Wien Wien 1160",
    "addr:housenumber":"144",
    "addr:postcode":"1160",
    "iso:country":"AT",
    "sg:address":"Ottakringer Str 144",
    "sg:city":"Wien",
    "sg:orig_category":"Blumeneinzelhandel",
    "sg:phone":"+43 1 4869954",
    "sg:postcode":"1160",
    "sg:province":"Wien",
    "sg:website":"blumenclaudia.at",
    "wof:name":"Blumen Claudia",
    "wof:placetype":"venue"
},
  "geometry": {"coordinates":[16.3197975159,48.2135810852],"type":"Point"}
}