{
  "type": "Feature",
  "properties": {
    "addr:full":"Ignaz-Glaser-Str 59 B\u00fcrmoos Salzburg 5111",
    "addr:housenumber":"59",
    "addr:postcode":"5111",
    "addr:street":"Ignaz-Glaser-Str",
    "iso:country":"AT",
    "sg:address":"Ignaz-Glaser-Str 59",
    "sg:city":"B\u00fcrmoos",
    "sg:orig_category":"Gemeinden",
    "sg:phone":"+43 6274 42050",
    "sg:postcode":"5111",
    "sg:province":"Salzburg",
    "wof:name":"Gemeinde B\u00fcrmoos",
    "wof:placetype":"venue"
},
  "geometry": {"coordinates":[12.9197635651,47.9836006165],"type":"Point"}
}