{
  "type": "Feature",
  "properties": {
    "iso:country":"AT",
    "sg:address":"Kirchenpl 211",
    "sg:city":"Sulz im Wienerwald",
    "sg:orig_category":"Feuerwehren",
    "sg:phone":"+43 2258 78090",
    "sg:postcode":"2392",
    "sg:province":"Nieder\u00f6sterreich",
    "wof:name":"Freiwillige Feuerwehr Grub",
    "wof:placetype":"venue"
},
  "geometry": {"coordinates":[16.139629364,48.101978302],"type":"Point"}
}