{
  "type": "Feature",
  "properties": {
    "iso:country":"AT",
    "sg:address":"Jedleseer Str 63",
    "sg:city":"Wien",
    "sg:orig_category":"Fitnesscenter",
    "sg:phone":"+43 1 2720102",
    "sg:postcode":"1210",
    "sg:province":"Wien",
    "wof:name":"Slender You - Claudia G\u00f6bel",
    "wof:placetype":"venue"
},
  "geometry": {"coordinates":[16.3879108429,48.2609977722],"type":"Point"}
}