{
  "type": "Feature",
  "properties": {
    "addr:full":"Winkl 31 Galt\u00fcr Tirol 6563",
    "addr:housenumber":"31",
    "addr:postcode":"6563",
    "addr:street":"Winkl;Tirol",
    "iso:country":"AT",
    "sg:address":"Winkl 31",
    "sg:city":"Galt\u00fcr",
    "sg:orig_category":"Pensionen / Privatzimmer",
    "sg:phone":"+43 5443 82080",
    "sg:postcode":"6563",
    "sg:province":"Tirol",
    "wof:name":"Pension Bergfried",
    "wof:placetype":"venue"
},
  "geometry": {"coordinates":[10.1840963364,46.9681587219],"type":"Point"}
}