{
  "type": "Feature",
  "properties": {
    "iso:country":"AT",
    "sg:address":"Michaelerpl 8",
    "sg:city":"Steyr",
    "sg:orig_category":"Autosattlereien",
    "sg:phone":"+43 7252 76115",
    "sg:postcode":"4400",
    "sg:province":"Ober\u00f6sterreich",
    "wof:name":"Bilweis & Zehethofer OEG",
    "wof:placetype":"venue"
},
  "geometry": {"coordinates":[14.4217367172,48.0433044434],"type":"Point"}
}