{
  "type": "Feature",
  "properties": {
    "iso:country":"AT",
    "sg:address":"Schleinbacher Str 65",
    "sg:city":"Ulrichskirchen",
    "sg:orig_category":"Ergotherapie",
    "sg:phone":"+43 4322 455929",
    "sg:postcode":"2122",
    "sg:province":"Nieder\u00f6sterreich",
    "wof:name":"Riepl Elisabeth Dipl-ET",
    "wof:placetype":"venue"
},
  "geometry": {"coordinates":[16.4911766052,48.4071350098],"type":"Point"}
}