{
  "type": "Feature",
  "properties": {
    "addr:full":"Linzer Str 359 Wien Wien 1140",
    "addr:housenumber":"359",
    "addr:postcode":"1140",
    "addr:street":"Linzer Str",
    "iso:country":"AT",
    "sg:address":"Linzer Str 359",
    "sg:city":"Wien",
    "sg:orig_category":"Zimmereien, Holzbau",
    "sg:phone":"+43 1 91461190",
    "sg:postcode":"1140",
    "sg:province":"Wien",
    "sg:website":"www.mach-holzbau.at",
    "wof:name":"MACH-HOLZBAU Karl Mach GesmbH",
    "wof:placetype":"venue"
},
  "geometry": {"coordinates":[16.2667255402,48.2000579834],"type":"Point"}
}