{
  "type": "Feature",
  "properties": {
    "iso:country":"AT",
    "sg:address":"Hubertusg. 10",
    "sg:city":"Gerasdorf",
    "sg:classifiers":[
        {
            "category":"Manufacturing",
            "subcategory":"Tools & Machinery",
            "type":"Manufacturing & Wholesale Goods"
        }
    ],
    "sg:phone":"+43 4322 4627702",
    "sg:postcode":"2201",
    "sg:province":"Nieder\u00f6sterreich",
    "sg:tags":[
        "environment",
        "equipment",
        "-"
    ],
    "wof:name":"FREYLIT UMWELTTECHNIK GMBH",
    "wof:placetype":"venue"
},
  "geometry": {"coordinates":[16.4708862305,48.2990150452],"type":"Point"}
}