{
  "type": "Feature",
  "properties": {
    "addr:full":"Gasteig 6 Neustift im Stubaital Tirol 6167",
    "addr:housenumber":"6",
    "addr:postcode":"6167",
    "addr:street":"Gasteig;Tirol",
    "iso:country":"AT",
    "sg:address":"Gasteig 6",
    "sg:city":"Neustift im Stubaital",
    "sg:orig_category":"Pensionen / Privatzimmer",
    "sg:phone":"+43 4352 262285",
    "sg:postcode":"6167",
    "sg:province":"Tirol",
    "wof:name":"Fr\u00fchst\u00fcckspension Haus am Wasserfall",
    "wof:placetype":"venue"
},
  "geometry": {"coordinates":[11.2597112656,47.072769165],"type":"Point"}
}