{
  "type": "Feature",
  "properties": {
    "addr:full":"Schulstr 11 Pasching Ober\u00f6sterreich 4061",
    "addr:housenumber":"11",
    "addr:postcode":"4061",
    "addr:street":"Schulstr;Oberoesterreich",
    "iso:country":"AT",
    "sg:address":"Schulstr 11",
    "sg:city":"Pasching",
    "sg:orig_category":"Volksschulen",
    "sg:phone":"+43 7221 880410",
    "sg:postcode":"4061",
    "sg:province":"Ober\u00f6sterreich",
    "wof:name":"Volksschule",
    "wof:placetype":"venue"
},
  "geometry": {"coordinates":[14.2002134323,48.2579727173],"type":"Point"}
}