{
  "type": "Feature",
  "properties": {
    "addr:full":"Haidhofstrasse 146 Baden Nieder\u00f6sterreich 2500",
    "addr:housenumber":"146",
    "addr:postcode":"2500",
    "addr:street":"Haidhofstrasse;Niederoesterreich",
    "iso:country":"AT",
    "sg:address":"Haidhofstrasse 146",
    "sg:city":"Baden",
    "sg:classifiers":[
        {
            "category":"Home & Garden",
            "subcategory":"Furniture",
            "type":"Retail Goods"
        }
    ],
    "sg:phone":"+43 2252 89518",
    "sg:postcode":"2500",
    "sg:province":"Nieder\u00f6sterreich",
    "sg:website":"kayu.at",
    "wof:name":"KAYU Handels GmbH",
    "wof:placetype":"venue"
},
  "geometry": {"coordinates":[16.2697257996,47.9810791016],"type":"Point"}
}