{
  "type": "Feature",
  "properties": {
    "addr:full":"Nr 70 Sandl Ober\u00f6sterreich 4251",
    "addr:postcode":"4251",
    "addr:street":"Nr 70",
    "iso:country":"AT",
    "sg:address":"Nr 70",
    "sg:city":"Sandl",
    "sg:orig_category":"Polizei U Gendarmerie",
    "sg:phone":"+43 4359 1334308",
    "sg:postcode":"4251",
    "sg:province":"Ober\u00f6sterreich",
    "wof:name":"Gendarmerie",
    "wof:placetype":"venue"
},
  "geometry": {"coordinates":[14.6452903748,48.5599403381],"type":"Point"}
}