{
  "type": "Feature",
  "properties": {
    "addr:full":"Zettersfeldstr 38 Lienz Tirol 9900",
    "addr:housenumber":"38",
    "addr:postcode":"9900",
    "addr:street":"Zettersfeldstr;Tirol",
    "iso:country":"AT",
    "sg:address":"Zettersfeldstr 38",
    "sg:city":"Lienz",
    "sg:orig_category":"Immobilienverwaltungen",
    "sg:phone":"+43 4852 697880",
    "sg:postcode":"9900",
    "sg:province":"Tirol",
    "wof:name":"CUP Touristic GesmbH",
    "wof:placetype":"venue"
},
  "geometry": {"coordinates":[12.778547287,46.8325424194],"type":"Point"}
}