{
  "type": "Feature",
  "properties": {
    "addr:full":"Kahlenberger Str 210 Wien Wien 1190",
    "addr:housenumber":"210",
    "addr:postcode":"1190",
    "iso:country":"AT",
    "sg:address":"Kahlenberger Str 210",
    "sg:city":"Wien",
    "sg:orig_category":"Heurigen / Buschenschank",
    "sg:phone":"+43 1 3205928",
    "sg:postcode":"1190",
    "sg:province":"Wien",
    "wof:name":"Sirbu Johann",
    "wof:placetype":"venue"
},
  "geometry": {"coordinates":[16.3415317535,48.2700614929],"type":"Point"}
}