{
  "type": "Feature",
  "properties": {
    "iso:country":"AT",
    "sg:address":"Waldstrasse 23",
    "sg:city":"Timelkam",
    "sg:classifiers":[
        {
            "category":"Home & Garden",
            "subcategory":"Building Materials",
            "type":"Retail Goods"
        }
    ],
    "sg:phone":"+43 767295172",
    "sg:postcode":"4850",
    "sg:province":"Ober\u00f6sterreich",
    "sg:tags":[
        "central",
        "heating",
        "boiler"
    ],
    "wof:name":"Hermann Pillichshammer",
    "wof:placetype":"venue"
},
  "geometry": {"coordinates":[13.587392807,47.9975662231],"type":"Point"}
}