{
  "type": "Feature",
  "properties": {
    "addr:full":"Wehrgasse 6 Pottenstein Nieder\u00f6sterreich 2563",
    "addr:housenumber":"6",
    "addr:postcode":"2563",
    "addr:street":"Wehrgasse",
    "iso:country":"AT",
    "sg:address":"Wehrgasse 6",
    "sg:city":"Pottenstein",
    "sg:classifiers":[
        {
            "category":"Brewery",
            "type":"Food & Drink"
        }
    ],
    "sg:phone":"+43 2672 824190",
    "sg:postcode":"2563",
    "sg:province":"Nieder\u00f6sterreich",
    "sg:tags":[
        "equipment"
    ],
    "sg:website":"dreher.at",
    "wof:name":"Ing. Leopold Schl\u00f6gl Ges.m.b.H.",
    "wof:placetype":"venue"
},
  "geometry": {"coordinates":[16.0881919861,47.967010498],"type":"Point"}
}