{
  "type": "Feature",
  "properties": {
    "addr:full":"Nr 39 Leogang Salzburg 5771",
    "addr:postcode":"5771",
    "addr:street":"Nr;Leogang",
    "iso:country":"AT",
    "sg:address":"Nr 39",
    "sg:city":"Leogang",
    "sg:orig_category":"Bergbahnen",
    "sg:phone":"+43 6583 82190",
    "sg:postcode":"5771",
    "sg:province":"Salzburg",
    "wof:name":"Leogang'er Bergbahnen GesmbH",
    "wof:placetype":"venue"
},
  "geometry": {"coordinates":[175.35493469240001,-41.1709899902],"type":"Point"}
}