{
  "type": "Feature",
  "properties": {
    "iso:country":"AT",
    "sg:address":"Im G\u00e4\u00dfle 4",
    "sg:city":"Bludesch",
    "sg:orig_category":"Autobusunternehmen",
    "sg:phone":"+43 5550 2941",
    "sg:postcode":"6719",
    "sg:province":"Vorarlberg",
    "wof:name":"Krajisnik GmbH",
    "wof:placetype":"venue"
},
  "geometry": {"coordinates":[9.7409362793,47.1968688965],"type":"Point"}
}