{
  "type": "Feature",
  "properties": {
    "addr:full":"9. Str 4 Kematen an der Ybbs Nieder\u00f6sterreich 3331",
    "addr:housenumber":"4",
    "addr:postcode":"3331",
    "addr:street":"Str",
    "iso:country":"AT",
    "sg:address":"9. Str 4",
    "sg:city":"Kematen an der Ybbs",
    "sg:classifiers":[
        {
            "category":"Shopping",
            "subcategory":"Crafts & Fabrics",
            "type":"Retail Goods"
        }
    ],
    "sg:phone":"+43 4374 483319",
    "sg:postcode":"3331",
    "sg:province":"Nieder\u00f6sterreich",
    "sg:tags":[
        "polyester",
        "u",
        "-verarbeitung"
    ],
    "wof:name":"Pils Herbert",
    "wof:placetype":"venue"
},
  "geometry": {"coordinates":[14.7814750671,48.0463294983],"type":"Point"}
}