{
  "type": "Feature",
  "properties": {
    "addr:full":"Promenade 39 Linz Ober\u00f6sterreich 4020",
    "addr:housenumber":"39",
    "addr:postcode":"4020",
    "addr:street":"Promenade",
    "iso:country":"AT",
    "sg:address":"Promenade 39",
    "sg:city":"Linz",
    "sg:orig_category":"Musikgruppen",
    "sg:phone":"+43 732 782263",
    "sg:postcode":"4020",
    "sg:province":"Ober\u00f6sterreich",
    "wof:name":"Brucknerorchester - Tonbanddienst",
    "wof:placetype":"venue"
},
  "geometry": {"coordinates":[14.2833871841,48.3039894104],"type":"Point"}
}