{
  "type": "Feature",
  "properties": {
    "addr:full":"Wiesenstr 37 Lustenau Vorarlberg 6890",
    "addr:housenumber":"37",
    "addr:postcode":"6890",
    "addr:street":"Wiesenstr",
    "iso:country":"AT",
    "sg:address":"Wiesenstr 37",
    "sg:city":"Lustenau",
    "sg:orig_category":"Textilwaren / Erzeugung U Gro\u00c3\u0178handel",
    "sg:phone":"+43 4355 7786000",
    "sg:postcode":"6890",
    "sg:province":"Vorarlberg",
    "wof:name":"Real-Textil Handel KG",
    "wof:placetype":"venue"
},
  "geometry": {"coordinates":[9.6643877029,47.4378166199],"type":"Point"}
}