{
  "type": "Feature",
  "properties": {
    "addr:full":"Thaliastr 10 Wien Wien 1160",
    "addr:housenumber":"10",
    "addr:postcode":"1160",
    "addr:street":"Thaliastr",
    "iso:country":"AT",
    "sg:address":"Thaliastr 10",
    "sg:city":"Wien",
    "sg:orig_category":"Fotoapparate U -Artikel / Einzelhandel",
    "sg:phone":"+43 1 49207420",
    "sg:postcode":"1160",
    "sg:province":"Wien",
    "wof:name":"Hartlauer HandelsgesmbH",
    "wof:placetype":"venue"
},
  "geometry": {"coordinates":[16.3369941711,48.2089576721],"type":"Point"}
}