{
  "type": "Feature",
  "properties": {
    "addr:full":"Greisseneggerstrasse 27 Voitsberg Steiermark 8570",
    "addr:housenumber":"27",
    "addr:postcode":"8570",
    "addr:street":"Greisseneggerstrasse",
    "iso:country":"AT",
    "sg:address":"Greisseneggerstrasse 27",
    "sg:city":"Voitsberg",
    "sg:classifiers":[
        {
            "category":"Professional",
            "subcategory":"Advertising",
            "type":"Services"
        }
    ],
    "sg:phone":"+43 3142 25111",
    "sg:postcode":"8570",
    "sg:province":"Steiermark",
    "sg:tags":[
        "column",
        "made",
        "plastic"
    ],
    "sg:website":"faku.at",
    "wof:name":"FAKU-Faserverbund-Kunststoffe Ges.m.b.H.",
    "wof:placetype":"venue"
},
  "geometry": {"coordinates":[15.1369409561,47.0467987061],"type":"Point"}
}