{
  "type": "Feature",
  "properties": {
    "addr:full":"Auwerk 23 Imst Tirol 6460",
    "addr:housenumber":"23",
    "addr:postcode":"6460",
    "addr:street":"Auwerk;Tirol",
    "iso:country":"AT",
    "sg:address":"Auwerk 23",
    "sg:city":"Imst",
    "sg:orig_category":"Fertigteilbau",
    "sg:phone":"+43 5412 63392",
    "sg:postcode":"6460",
    "sg:province":"Tirol",
    "wof:name":"Canal Othmar Betonwerk Imst KG",
    "wof:placetype":"venue"
},
  "geometry": {"coordinates":[10.737487793,47.2392234802],"type":"Point"}
}