{
  "type": "Feature",
  "properties": {
    "addr:full":"Steinbichl 21 Gschwandt Ober\u00f6sterreich 4816",
    "addr:housenumber":"21",
    "addr:postcode":"4816",
    "addr:street":"Steinbichl",
    "iso:country":"AT",
    "sg:address":"Steinbichl 21",
    "sg:city":"Gschwandt",
    "sg:orig_category":"Erdarbeiten",
    "sg:phone":"+43 761271874",
    "sg:postcode":"4816",
    "sg:province":"Ober\u00f6sterreich",
    "wof:name":"Bergthaller Josef",
    "wof:placetype":"venue"
},
  "geometry": {"coordinates":[13.8354120255,47.9379005432],"type":"Point"}
}