{
  "type": "Feature",
  "properties": {
    "addr:full":"Nr 199 Ischgl Tirol 6561",
    "addr:postcode":"6561",
    "addr:street":"Nr 199;Tirol",
    "iso:country":"AT",
    "sg:address":"Nr 199",
    "sg:city":"Ischgl",
    "sg:orig_category":"Pensionen / Privatzimmer",
    "sg:phone":"+43 5444 5704",
    "sg:postcode":"6561",
    "sg:province":"Tirol",
    "wof:name":"Haus Heidi",
    "wof:placetype":"venue"
},
  "geometry": {"coordinates":[10.2881736755,47.0111351013],"type":"Point"}
}