{
  "type": "Feature",
  "properties": {
    "iso:country":"AT",
    "sg:address":"Dorotheerg 10",
    "sg:city":"Wien",
    "sg:orig_category":"Musikalien",
    "sg:phone":"+43 1 515030",
    "sg:postcode":"1010",
    "sg:province":"Wien",
    "sg:website":"doblinger.at",
    "wof:name":"Doblinger Musikhaus-Musikverlag",
    "wof:placetype":"venue"
},
  "geometry": {"coordinates":[16.3692684174,48.2075767517],"type":"Point"}
}