{
  "type": "Feature",
  "properties": {
    "iso:country":"AT",
    "sg:address":"Herrenstr 30",
    "sg:city":"Perg",
    "sg:orig_category":"Sonnenstudios",
    "sg:phone":"+43 7262 57733",
    "sg:postcode":"4320",
    "sg:province":"Ober\u00f6sterreich",
    "wof:name":"Br\u00e4unungsstudio Happy Sunshine",
    "wof:placetype":"venue"
},
  "geometry": {"coordinates":[14.6374721527,48.2490501404],"type":"Point"}
}