{
  "type": "Feature",
  "properties": {
    "addr:full":"Tiroler Str 19 Villach K\u00e4rnten 9500",
    "addr:housenumber":"19",
    "addr:postcode":"9500",
    "addr:street":"Str;Kaernten",
    "iso:country":"AT",
    "sg:address":"Tiroler Str 19",
    "sg:city":"Villach",
    "sg:orig_category":"Lebensmittel / Einzelhandel",
    "sg:phone":"+43 4242 582710",
    "sg:postcode":"9500",
    "sg:province":"K\u00e4rnten",
    "wof:name":"Zielpunkt Warenhandel GmbH & Co KG",
    "wof:placetype":"venue"
},
  "geometry": {"coordinates":[13.8358316422,46.6131362915],"type":"Point"}
}