{
  "type": "Feature",
  "properties": {
    "iso:country":"AT",
    "sg:address":"Neuhausfeld 7",
    "sg:city":"Jochberg",
    "sg:orig_category":"Innenausbau",
    "sg:phone":"+43 676 5400239",
    "sg:postcode":"6373",
    "sg:province":"Tirol",
    "wof:name":"Gromala KEG",
    "wof:placetype":"venue"
},
  "geometry": {"coordinates":[12.4180698395,47.3754234314],"type":"Point"}
}