{
  "type": "Feature",
  "properties": {
    "addr:full":"Arzberg 39 Waldbach Steiermark 8253",
    "addr:housenumber":"39",
    "addr:postcode":"8253",
    "addr:street":"Arzberg",
    "iso:country":"AT",
    "sg:address":"Arzberg 39",
    "sg:city":"Waldbach",
    "sg:orig_category":"Volksschulen",
    "sg:phone":"+43 3336 4506",
    "sg:postcode":"8253",
    "sg:province":"Steiermark",
    "wof:name":"Volksschule",
    "wof:placetype":"venue"
},
  "geometry": {"coordinates":[15.8458461761,47.4498291016],"type":"Point"}
}