{
  "type": "Feature",
  "properties": {
    "addr:full":"Aue 117b Leutasch Tirol 6105",
    "addr:housenumber":"117b",
    "addr:postcode":"6105",
    "addr:street":"Aue;Tirol",
    "iso:country":"AT",
    "sg:address":"Aue 117b",
    "sg:city":"Leutasch",
    "sg:orig_category":"Appartements / Ferienwohnungen",
    "sg:phone":"+43 5214 6172",
    "sg:postcode":"6105",
    "sg:province":"Tirol",
    "wof:name":"Landhaus Leutaschtal Fam Gertrud Krug",
    "wof:placetype":"venue"
},
  "geometry": {"coordinates":[11.1416893005,47.3639831543],"type":"Point"}
}