{
  "type": "Feature",
  "properties": {
    "addr:full":"Schildbach 58 Hartberg Steiermark 8230",
    "addr:housenumber":"58",
    "addr:postcode":"8230",
    "addr:street":"Schildbach",
    "iso:country":"AT",
    "sg:address":"Schildbach 58",
    "sg:city":"Hartberg",
    "sg:orig_category":"Autohandel",
    "sg:phone":"+43 4333 32628110",
    "sg:postcode":"8230",
    "sg:province":"Steiermark",
    "wof:name":"K\u00f6nig Autotechnik",
    "wof:placetype":"venue"
},
  "geometry": {"coordinates":[15.9557476044,47.2710113525],"type":"Point"}
}