{
  "type": "Feature",
  "properties": {
    "iso:country":"AT",
    "sg:address":"Kremser Str 7-9",
    "sg:city":"Krems an der Donau",
    "sg:classifiers":[
        {
            "category":"Community Center",
            "subcategory":"Social",
            "type":"Public Place"
        }
    ],
    "sg:phone":"+43 2732 855370",
    "sg:postcode":"3500",
    "sg:province":"Nieder\u00f6sterreich",
    "sg:tags":[
        "profile"
    ],
    "wof:name":"PENN Sch\u00e4lwerk GmbH",
    "wof:placetype":"venue"
},
  "geometry": {"coordinates":[15.5965108871,48.4088058472],"type":"Point"}
}