{
  "type": "Feature",
  "properties": {
    "addr:full":"Ackeraustrasse 35 Weiz Steiermark 8160",
    "addr:housenumber":"35",
    "addr:postcode":"8160",
    "addr:street":"Ackeraustrasse",
    "iso:country":"AT",
    "sg:address":"Ackeraustrasse 35",
    "sg:city":"Weiz",
    "sg:classifiers":[
        {
            "category":"Bars & Pubs",
            "subcategory":"Lounge",
            "type":"Food & Drink"
        }
    ],
    "sg:phone":"+43 664 1632104",
    "sg:postcode":"8160",
    "sg:province":"Steiermark",
    "sg:tags":[
        "aluminium",
        "railing"
    ],
    "sg:website":"preissler.at",
    "wof:name":"Josef Prei\u00dfler, Schlosserei",
    "wof:placetype":"venue"
},
  "geometry": {"coordinates":[15.6329698563,47.2122993469],"type":"Point"}
}