{
  "type": "Feature",
  "properties": {
    "iso:country":"AT",
    "sg:address":"Auf der Gugl 3",
    "sg:city":"Linz",
    "sg:classifiers":[
        {
            "category":"Travel",
            "subcategory":"Hotels & Motels",
            "type":"Entertainment"
        }
    ],
    "sg:phone":"+43 4373 269021470",
    "sg:postcode":"4020",
    "sg:province":"Ober\u00f6sterreich",
    "sg:website":"hotel.lfi.at",
    "wof:name":"LFI Hotel - Landwirtschaftskammer G\u00e4stehaus GmbH",
    "wof:placetype":"venue"
},
  "geometry": {"coordinates":[14.282746315,48.2920875549],"type":"Point"}
}