{
  "type": "Feature",
  "properties": {
    "addr:full":"Marie-Louisen-Str 4 Bad Ischl Ober\u00f6sterreich 4820",
    "addr:housenumber":"4",
    "addr:postcode":"4820",
    "addr:street":"Marie-Louisen-Str",
    "iso:country":"AT",
    "sg:address":"Marie-Louisen-Str 4",
    "sg:city":"Bad Ischl",
    "sg:orig_category":"Hygieneartikel / Erzeugung U Gro\u00c3\u0178handel",
    "sg:phone":"+43 4361 32264550",
    "sg:postcode":"4820",
    "sg:province":"Ober\u00f6sterreich",
    "sg:website":"1a-anzenberger.com",
    "wof:name":"Anzenberger Produktions- u HandelsgesmbH",
    "wof:placetype":"venue"
},
  "geometry": {"coordinates":[13.592915535,47.7179641724],"type":"Point"}
}