{
  "type": "Feature",
  "properties": {
    "addr:full":"Erlerstr 19 Innsbruck Tirol 6020",
    "addr:housenumber":"19",
    "addr:postcode":"6020",
    "addr:street":"Erlerstr;Tirol",
    "iso:country":"AT",
    "sg:address":"Erlerstr 19",
    "sg:city":"Innsbruck",
    "sg:orig_category":"Boutiquen",
    "sg:phone":"+43 512 575317",
    "sg:postcode":"6020",
    "sg:province":"Tirol",
    "wof:name":"Boutique Fulli Belli",
    "wof:placetype":"venue"
},
  "geometry": {"coordinates":[11.3962602615,47.2651863098],"type":"Point"}
}