{
  "type": "Feature",
  "properties": {
    "addr:full":"Nr 174 Thalgau Salzburg 5303",
    "addr:postcode":"5303",
    "addr:street":"Nr 174;Salzburg",
    "iso:country":"AT",
    "sg:address":"Nr 174",
    "sg:city":"Thalgau",
    "sg:orig_category":"Transportunternehmen",
    "sg:phone":"+43 6235 7280",
    "sg:postcode":"5303",
    "sg:province":"Salzburg",
    "wof:name":"Knoblechner Franz & Sohn GmbH & Co KG",
    "wof:placetype":"venue"
},
  "geometry": {"coordinates":[13.2537765503,47.8417167664],"type":"Point"}
}