{
  "type": "Feature",
  "properties": {
    "addr:full":"Funkenstrasse 6 Lauterach Vorarlberg 6923",
    "addr:housenumber":"6",
    "addr:postcode":"6923",
    "addr:street":"Funkenstrasse",
    "iso:country":"AT",
    "sg:address":"Funkenstrasse 6",
    "sg:city":"Lauterach",
    "sg:orig_category":"Cheese Packages Of Cardboard And Wood",
    "sg:phone":"+43 5574 71290",
    "sg:postcode":"6923",
    "sg:province":"Vorarlberg",
    "sg:website":"flatz.com",
    "wof:name":"Flatz Verpackungen - Styropor Ges.m.b.H.",
    "wof:placetype":"venue"
},
  "geometry": {"coordinates":[9.722820282,47.467250824],"type":"Point"}
}