{
  "type": "Feature",
  "properties": {
    "addr:full":"Stollgasse 7 Wien Wien 1070",
    "addr:housenumber":"7",
    "addr:postcode":"1070",
    "addr:street":"Stollgasse",
    "iso:country":"AT",
    "sg:address":"Stollgasse 7",
    "sg:city":"Wien",
    "sg:classifiers":[
        {
            "category":"Organizations",
            "subcategory":"Non-profit Organization",
            "type":"Services"
        }
    ],
    "sg:phone":"+43 1 5239688",
    "sg:postcode":"1070",
    "sg:province":"Wien",
    "sg:tags":[
        "alarm",
        "system"
    ],
    "wof:name":"Rudolf Schwarz KG",
    "wof:placetype":"venue"
},
  "geometry": {"coordinates":[16.3408870697,48.1985397339],"type":"Point"}
}