{
  "type": "Feature",
  "properties": {
    "addr:full":"Walser Str 52 Hirschegg Vorarlberg 6992",
    "addr:housenumber":"52",
    "addr:postcode":"6992",
    "addr:street":"Str",
    "iso:country":"AT",
    "sg:address":"Walser Str 52",
    "sg:city":"Hirschegg",
    "sg:orig_category":"Friseure U Frisiersalons",
    "sg:phone":"+43 4355 176102",
    "sg:postcode":"6992",
    "sg:province":"Vorarlberg",
    "wof:name":"Der kleine Friseur",
    "wof:placetype":"venue"
},
  "geometry": {"coordinates":[10.1668701172,47.3438453674],"type":"Point"}
}