{
  "type": "Feature",
  "properties": {
    "addr:full":"Poststr 5 St. Johann in Tirol Tirol 6380",
    "addr:housenumber":"5",
    "addr:postcode":"6380",
    "addr:street":"Poststr;Tirol",
    "iso:country":"AT",
    "sg:address":"Poststr 5",
    "sg:city":"St. Johann in Tirol",
    "sg:orig_category":"Blumeneinzelhandel",
    "sg:phone":"+43 5352 62366",
    "sg:postcode":"6380",
    "sg:province":"Tirol",
    "wof:name":"Stocker Christine",
    "wof:placetype":"venue"
},
  "geometry": {"coordinates":[12.426571846,47.5219345093],"type":"Point"}
}