{
  "type": "Feature",
  "properties": {
    "addr:full":"Werkstr 5 Liezen Steiermark 8940",
    "addr:housenumber":"5",
    "addr:postcode":"8940",
    "addr:street":"Werkstr",
    "iso:country":"AT",
    "sg:address":"Werkstr 5",
    "sg:city":"Liezen",
    "sg:orig_category":"Maschinenbau",
    "sg:phone":"+43 3612 270",
    "sg:postcode":"8940",
    "sg:province":"Steiermark",
    "wof:name":"Mali GesmbH",
    "wof:placetype":"venue"
},
  "geometry": {"coordinates":[14.2486343384,47.5633544922],"type":"Point"}
}