{
  "type": "Feature",
  "properties": {
    "addr:full":"Unterwaldschlag 4 Traberg Ober\u00f6sterreich 4183",
    "addr:housenumber":"4",
    "addr:postcode":"4183",
    "addr:street":"Unterwaldschlag;Oberoesterreich",
    "iso:country":"AT",
    "sg:address":"Unterwaldschlag 4",
    "sg:city":"Traberg",
    "sg:classifiers":[
        {
            "category":"Shopping",
            "subcategory":"Crafts & Fabrics",
            "type":"Retail Goods"
        }
    ],
    "sg:phone":"+43 7218 2660",
    "sg:postcode":"4183",
    "sg:province":"Ober\u00f6sterreich",
    "sg:tags":[
        "cloth"
    ],
    "wof:name":"Weberei Tumfart Ges.m.b.H.",
    "wof:placetype":"venue"
},
  "geometry": {"coordinates":[14.2014760971,48.5139007568],"type":"Point"}
}