{
  "type": "Feature",
  "properties": {
    "iso:country":"AT",
    "sg:address":"Johann-Sackl-G 65-67",
    "sg:city":"Leoben",
    "sg:orig_category":"Umwelttechnik",
    "sg:phone":"+43 3842 265480",
    "sg:postcode":"8700",
    "sg:province":"Steiermark",
    "wof:name":"MONTEX Montan-Bureau f Brand- und Umweltsch\u00e4den GmbH & Co KG",
    "wof:placetype":"venue"
},
  "geometry": {"coordinates":[15.0608673096,47.378112793],"type":"Point"}
}