{
  "type": "Feature",
  "properties": {
    "iso:country":"AT",
    "sg:address":"Werkstrasse 3",
    "sg:city":"Garsten",
    "sg:classifiers":[
        {
            "category":"Autos & Motor Vehicles",
            "subcategory":"Auto Supplies",
            "type":"Retail Goods"
        }
    ],
    "sg:phone":"+43 7252 52671",
    "sg:postcode":"4451",
    "sg:province":"Ober\u00f6sterreich",
    "sg:tags":[
        "body",
        "car",
        "truck",
        "trailer",
        "superstructure"
    ],
    "wof:name":"Fahrzeugbau Obermayr Ges.m.b.H.",
    "wof:placetype":"venue"
},
  "geometry": {"coordinates":[14.4075651169,48.0228309631],"type":"Point"}
}