{
  "type": "Feature",
  "properties": {
    "addr:full":"Eichenstrasse 6 Marchtrenk Ober\u00f6sterreich 4614",
    "addr:housenumber":"6",
    "addr:postcode":"4614",
    "addr:street":"Eichenstrasse",
    "iso:country":"AT",
    "sg:address":"Eichenstrasse 6",
    "sg:city":"Marchtrenk",
    "sg:orig_category":"Block Bottom Bags And Cross-Bottom Bags",
    "sg:phone":"+43 7243 5530",
    "sg:postcode":"4614",
    "sg:province":"Ober\u00f6sterreich",
    "sg:website":"wipf.ch",
    "wof:name":"Wipf Austria GmbH",
    "wof:placetype":"venue"
},
  "geometry": {"coordinates":[14.1176290512,48.1930503845],"type":"Point"}
}