{
  "type": "Feature",
  "properties": {
    "addr:full":"Wiener G 4 Klagenfurt K\u00e4rnten 9020",
    "addr:housenumber":"4",
    "addr:postcode":"9020",
    "addr:street":"Wiener G;Kaernten",
    "iso:country":"AT",
    "sg:address":"Wiener G 4",
    "sg:city":"Klagenfurt",
    "sg:orig_category":"Boutiquen",
    "sg:phone":"+43 463 596523",
    "sg:postcode":"9020",
    "sg:province":"K\u00e4rnten",
    "wof:name":"Moustache",
    "wof:placetype":"venue"
},
  "geometry": {"coordinates":[14.3082265854,46.6255111694],"type":"Point"}
}