{
  "type": "Feature",
  "properties": {
    "addr:full":"R\u00f6merstr 1 Aschbach Markt Nieder\u00f6sterreich 3361",
    "addr:housenumber":"1",
    "addr:postcode":"3361",
    "addr:street":"Roemerstr",
    "iso:country":"AT",
    "sg:address":"R\u00f6merstr 1",
    "sg:city":"Aschbach Markt",
    "sg:orig_category":"Friseure U Frisiersalons",
    "sg:phone":"+43 4374 76772720",
    "sg:postcode":"3361",
    "sg:province":"Nieder\u00f6sterreich",
    "wof:name":"Weinfurter Thomas",
    "wof:placetype":"venue"
},
  "geometry": {"coordinates":[14.7550191879,48.0736503601],"type":"Point"}
}