{
  "type": "Feature",
  "properties": {
    "addr:full":"Fraueng 15 Knittelfeld Steiermark 8720",
    "addr:housenumber":"15",
    "addr:postcode":"8720",
    "addr:street":"Fraueng",
    "iso:country":"AT",
    "sg:address":"Fraueng 15",
    "sg:city":"Knittelfeld",
    "sg:orig_category":"Detekteien",
    "sg:phone":"+43 664 2420252",
    "sg:postcode":"8720",
    "sg:province":"Steiermark",
    "sg:website":"detektei-rettenegger.at",
    "wof:name":"A.D.R Detektivb\u00fcro Rettenegger",
    "wof:placetype":"venue"
},
  "geometry": {"coordinates":[14.8278369904,47.2151031494],"type":"Point"}
}