{
  "type": "Feature",
  "properties": {
    "iso:country":"AT",
    "sg:address":"Villacher Str 14",
    "sg:city":"Spittal an der Drau",
    "sg:orig_category":"Restaurants: Chinesisch",
    "sg:phone":"+43 4762 33286",
    "sg:postcode":"9800",
    "sg:province":"K\u00e4rnten",
    "wof:name":"China-Restaurant Shanghai",
    "wof:placetype":"venue"
},
  "geometry": {"coordinates":[13.5020370483,46.7959709167],"type":"Point"}
}