{
  "type": "Feature",
  "properties": {
    "addr:full":"Sparkassenpl 1 Hartberg Steiermark 8230",
    "addr:housenumber":"1",
    "addr:postcode":"8230",
    "addr:street":"Sparkassenpl",
    "iso:country":"AT",
    "sg:address":"Sparkassenpl 1",
    "sg:city":"Hartberg",
    "sg:orig_category":"Immobilienmakler",
    "sg:phone":"+43 4333 3264144",
    "sg:postcode":"8230",
    "sg:province":"Steiermark",
    "wof:name":"S REAL - Real-Service f steirische Sparkassen Realit\u00e4tenvermittlungsgesmbH",
    "wof:placetype":"venue"
},
  "geometry": {"coordinates":[15.9718570709,47.2822914124],"type":"Point"}
}