{
  "type": "Feature",
  "properties": {
    "iso:country":"AT",
    "sg:address":"Hackengasse 16",
    "sg:city":"Wien",
    "sg:classifiers":[
        {
            "category":"Building & Trades",
            "subcategory":"Plumbing",
            "type":"Services"
        }
    ],
    "sg:phone":"+43 1 4921299",
    "sg:postcode":"1150",
    "sg:province":"Wien",
    "sg:tags":[
        "supraregional",
        "gas"
    ],
    "sg:website":"koehler-wien.at",
    "wof:name":"Rudolf K\u00f6hler Gas-, Wasser- und Heizungsinstallationen Ges.m.b.H.",
    "wof:placetype":"venue"
},
  "geometry": {"coordinates":[16.333984375,48.1988945007],"type":"Point"}
}