{
  "type": "Feature",
  "properties": {
    "addr:full":"Maria-Theresia-Str 19 Wels Ober\u00f6sterreich 4600",
    "addr:housenumber":"19",
    "addr:postcode":"4600",
    "addr:street":"Maria-Theresia-Str;Oberoesterreich",
    "iso:country":"AT",
    "sg:address":"Maria-Theresia-Str 19",
    "sg:city":"Wels",
    "sg:orig_category":"Architekten",
    "sg:phone":"+43 7242 47955",
    "sg:postcode":"4600",
    "sg:province":"Ober\u00f6sterreich",
    "wof:name":"Hiptmair Martin Dipl-Ing",
    "wof:placetype":"venue"
},
  "geometry": {"coordinates":[13.9685125351,48.1398696899],"type":"Point"}
}