{
  "type": "Feature",
  "properties": {
    "iso:country":"AT",
    "sg:address":"Anderg 50",
    "sg:city":"Wien",
    "sg:orig_category":"Rohstoffe",
    "sg:phone":"+43 1 4841616",
    "sg:postcode":"1170",
    "sg:province":"Wien",
    "wof:name":"Realmin Industriemineralien GmbH",
    "wof:placetype":"venue"
},
  "geometry": {"coordinates":[16.2886257172,48.2249565125],"type":"Point"}
}