{
  "type": "Feature",
  "properties": {
    "iso:country":"AT",
    "sg:address":"Herreng 1",
    "sg:city":"Unterretzbach",
    "sg:orig_category":"Pensionen / Privatzimmer",
    "sg:phone":"+43 4329 4220802",
    "sg:postcode":"2074",
    "sg:province":"Nieder\u00f6sterreich",
    "wof:name":"R\u00fccker Edmund",
    "wof:placetype":"venue"
},
  "geometry": {"coordinates":[16.0019378662,48.7649917603],"type":"Point"}
}