{
  "type": "Feature",
  "properties": {
    "addr:full":"Dietrichsteinplatz 13 Graz Steiermark 8010",
    "addr:housenumber":"13",
    "addr:postcode":"8010",
    "addr:street":"Dietrichsteinplatz",
    "iso:country":"AT",
    "sg:address":"Dietrichsteinplatz 13",
    "sg:city":"Graz",
    "sg:classifiers":[
        {
            "category":"Education",
            "subcategory":"Special Training",
            "type":"Public Place"
        }
    ],
    "sg:phone":"+43 316 80400",
    "sg:postcode":"8010",
    "sg:province":"Steiermark",
    "sg:tags":[
        "bread"
    ],
    "wof:name":"Auer Brot Ges.m.b.H.",
    "wof:placetype":"venue"
},
  "geometry": {"coordinates":[15.4466381073,47.066280365],"type":"Point"}
}