{
  "type": "Feature",
  "properties": {
    "addr:full":"Traunwang 3 Desselbrunn Ober\u00f6sterreich 4693",
    "addr:housenumber":"3",
    "addr:postcode":"4693",
    "addr:street":"Traunwang",
    "iso:country":"AT",
    "sg:address":"Traunwang 3",
    "sg:city":"Desselbrunn",
    "sg:orig_category":"Autobusunternehmen",
    "sg:phone":"+43 767337010",
    "sg:postcode":"4693",
    "sg:province":"Ober\u00f6sterreich",
    "wof:name":"Tassilo Reisen GesmbH",
    "wof:placetype":"venue"
},
  "geometry": {"coordinates":[13.8005132675,48.0282249451],"type":"Point"}
}