{
  "type": "Feature",
  "properties": {
    "iso:country":"AT",
    "sg:address":"Wimmerstr 26",
    "sg:city":"Eggersdorf",
    "sg:orig_category":"Bergbahnen",
    "sg:phone":"+43 4331 172190",
    "sg:postcode":"8063",
    "sg:province":"Steiermark",
    "wof:name":"Wimmer Roman",
    "wof:placetype":"venue"
},
  "geometry": {"coordinates":[15.58066082,47.1230239868],"type":"Point"}
}