{
  "type": "Feature",
  "properties": {
    "addr:full":"D\u00f6rfl 19 Kasten Nieder\u00f6sterreich 3072",
    "addr:housenumber":"19",
    "addr:postcode":"3072",
    "addr:street":"Doerfl",
    "iso:country":"AT",
    "sg:address":"D\u00f6rfl 19",
    "sg:city":"Kasten",
    "sg:classifiers":[
        {
            "category":"Travel",
            "subcategory":"Hotels & Motels",
            "type":"Entertainment"
        }
    ],
    "sg:phone":"+43 4327 4473870",
    "sg:postcode":"3072",
    "sg:province":"Nieder\u00f6sterreich",
    "wof:name":"Pedros Landhaus",
    "wof:placetype":"venue"
},
  "geometry": {"coordinates":[7.7127399445,49.5743789673],"type":"Point"}
}