{
  "type": "Feature",
  "properties": {
    "iso:country":"AT",
    "sg:address":"Nr 73",
    "sg:city":"Ossiach",
    "sg:orig_category":"Pensionen / Privatzimmer",
    "sg:phone":"+43 4243 438",
    "sg:postcode":"9570",
    "sg:province":"K\u00e4rnten",
    "wof:name":"Pension Rosenheim - Fauler Traude",
    "wof:placetype":"venue"
},
  "geometry": {"coordinates":[13.9840993881,46.6746025085],"type":"Point"}
}