{
  "type": "Feature",
  "properties": {
    "addr:full":"Trefflinger Strasse 15  Seeboden K\u00e4rnten 9871",
    "addr:housenumber":"15",
    "addr:postcode":"9871",
    "addr:street":"Trefflinger Strasse;Kaernten",
    "iso:country":"AT",
    "sg:address":"Trefflinger Strasse 15 ",
    "sg:city":"Seeboden",
    "sg:classifiers":[
        {
            "category":"Building & Trades",
            "subcategory":"Plumbing",
            "type":"Services"
        }
    ],
    "sg:phone":"+43 4762 81918",
    "sg:postcode":"9871",
    "sg:province":"K\u00e4rnten",
    "sg:tags":[
        "supraregional",
        "gas"
    ],
    "sg:website":"www.pritz.at",
    "wof:name":"Pritz Ges.m.b.H",
    "wof:placetype":"venue"
},
  "geometry": {"coordinates":[13.5155391693,46.8188323975],"type":"Point"}
}