{
  "type": "Feature",
  "properties": {
    "addr:full":"Thaliastr 98-100 Wien Wien 1160",
    "addr:housenumber":"98-100",
    "addr:postcode":"1160",
    "addr:street":"Thaliastr",
    "iso:country":"AT",
    "sg:address":"Thaliastr 98-100",
    "sg:city":"Wien",
    "sg:orig_category":"Elektronik",
    "sg:phone":"+43 1 4851162",
    "sg:postcode":"1160",
    "sg:province":"Wien",
    "wof:name":"Segadat Elekronische Anlagen GesmbH",
    "wof:placetype":"venue"
},
  "geometry": {"coordinates":[16.318353653,48.2117996216],"type":"Point"}
}