{
  "type": "Feature",
  "properties": {
    "addr:full":"Nr 7 Braunau am Inn Ober\u00f6sterreich 5280",
    "addr:postcode":"5280",
    "addr:street":"Nr",
    "iso:country":"AT",
    "sg:address":"Nr 7",
    "sg:city":"Braunau am Inn",
    "sg:orig_category":"Non-Classified Establishments",
    "sg:phone":"+43 5 91334200",
    "sg:postcode":"5280",
    "sg:province":"Ober\u00f6sterreich",
    "wof:name":"Gendarmerieposten - Schie\u00dfplatz Lachforst",
    "wof:placetype":"venue"
},
  "geometry": {"coordinates":[13.0349302292,48.2589187622],"type":"Point"}
}