{
  "type": "Feature",
  "properties": {
    "iso:country":"AT",
    "sg:address":"Siemensstr. 11 ",
    "sg:city":"Pinkafeld",
    "sg:classifiers":[
        {
            "category":"Professional",
            "subcategory":"Printing & Photocopies",
            "type":"Services"
        }
    ],
    "sg:phone":"+43 4333 57424600",
    "sg:postcode":"7423",
    "sg:province":"Burgenland",
    "wof:name":"SIGNALE MEDIENTECHNIK GES.MBH",
    "wof:placetype":"venue"
},
  "geometry": {"coordinates":[16.1183547974,47.3652305603],"type":"Point"}
}