{
  "type": "Feature",
  "properties": {
    "addr:full":"Leopoldauer Str 3 Gerasdorf Nieder\u00f6sterreich 2201",
    "addr:housenumber":"3",
    "addr:postcode":"2201",
    "addr:street":"Leopoldauer Str",
    "iso:country":"AT",
    "sg:address":"Leopoldauer Str 3",
    "sg:city":"Gerasdorf",
    "sg:orig_category":"Fleischhauereien",
    "sg:phone":"+43 2246 20977",
    "sg:postcode":"2201",
    "sg:province":"Nieder\u00f6sterreich",
    "wof:name":"Schirnhofer-Breisler GesmbH - Shop in Shop",
    "wof:placetype":"venue"
},
  "geometry": {"coordinates":[16.4675960541,48.2940406799],"type":"Point"}
}