{
  "type": "Feature",
  "properties": {
    "addr:full":"Hauptstr 52d Obdach Steiermark 8742",
    "addr:housenumber":"52d",
    "addr:postcode":"8742",
    "addr:street":"Hauptstr",
    "iso:country":"AT",
    "sg:address":"Hauptstr 52d",
    "sg:city":"Obdach",
    "sg:orig_category":"Autohandel",
    "sg:phone":"+43 4335 782385",
    "sg:postcode":"8742",
    "sg:province":"Steiermark",
    "wof:name":"Knoll Heinrich Fahrzeuginstandsetzungs- u HandelsgesmbH",
    "wof:placetype":"venue"
},
  "geometry": {"coordinates":[14.6973085403,47.0659828186],"type":"Point"}
}