{
  "type": "Feature",
  "properties": {
    "addr:full":"Heidenfeldstr 31 Villach K\u00e4rnten 9500",
    "addr:housenumber":"31",
    "addr:postcode":"9500",
    "addr:street":"Heidenfeldstr;Kaernten",
    "iso:country":"AT",
    "sg:address":"Heidenfeldstr 31",
    "sg:city":"Villach",
    "sg:orig_category":"Lebensmittel / Einzelhandel",
    "sg:phone":"+43 4242 34914",
    "sg:postcode":"9500",
    "sg:province":"K\u00e4rnten",
    "wof:name":"Billa AG",
    "wof:placetype":"venue"
},
  "geometry": {"coordinates":[13.8470230103,46.6000022888],"type":"Point"}
}