{
  "type": "Feature",
  "properties": {
    "addr:full":"Am Hartmayrgut 12 Linz Ober\u00f6sterreich 4040",
    "addr:housenumber":"12",
    "addr:postcode":"4040",
    "addr:street":"Am Hartmayrgut",
    "iso:country":"AT",
    "sg:address":"Am Hartmayrgut 12",
    "sg:city":"Linz",
    "sg:orig_category":"Kinderbetreuung",
    "sg:phone":"+43 732 731080",
    "sg:postcode":"4040",
    "sg:province":"Ober\u00f6sterreich",
    "wof:name":"Hort d Stadt Linz",
    "wof:placetype":"venue"
},
  "geometry": {"coordinates":[14.2894630432,48.3186836243],"type":"Point"}
}