{
  "type": "Feature",
  "properties": {
    "addr:full":"Peintnerstr 6A Leonding Ober\u00f6sterreich 4060",
    "addr:housenumber":"6a",
    "addr:postcode":"4060",
    "addr:street":"Peintnerstr",
    "iso:country":"AT",
    "sg:address":"Peintnerstr 6A",
    "sg:city":"Leonding",
    "sg:orig_category":"Schaltanlagen U -Systeme",
    "sg:phone":"+43 4373 26774800",
    "sg:postcode":"4060",
    "sg:province":"Ober\u00f6sterreich",
    "wof:name":"MOELLER Geb\u00e4udeautomation KG",
    "wof:placetype":"venue"
},
  "geometry": {"coordinates":[14.238656044,48.2474517822],"type":"Point"}
}