{
  "type": "Feature",
  "properties": {
    "addr:full":"Industriestr 9 Top 1 Guntramsdorf Nieder\u00f6sterreich 2353",
    "addr:housenumber":"9 top 1",
    "addr:postcode":"2353",
    "addr:street":"Industriestr",
    "iso:country":"AT",
    "sg:address":"Industriestr 9 Top 1",
    "sg:city":"Guntramsdorf",
    "sg:orig_category":"Speditionen",
    "sg:phone":"+43 2236 893989",
    "sg:postcode":"2353",
    "sg:province":"Nieder\u00f6sterreich",
    "wof:name":"International Logistic Gateway GmbH",
    "wof:placetype":"venue"
},
  "geometry": {"coordinates":[16.3131484985,48.0491676331],"type":"Point"}
}