{
  "type": "Feature",
  "properties": {
    "addr:full":"Breiteng 12 Schrems Nieder\u00f6sterreich 3943",
    "addr:housenumber":"12",
    "addr:postcode":"3943",
    "addr:street":"Breiteng",
    "iso:country":"AT",
    "sg:address":"Breiteng 12",
    "sg:city":"Schrems",
    "sg:orig_category":"Aluminiumhalbfabrikate",
    "sg:phone":"+43 2853 76262",
    "sg:postcode":"3943",
    "sg:province":"Nieder\u00f6sterreich",
    "wof:name":"Alu-System FertigungsgmbH",
    "wof:placetype":"venue"
},
  "geometry": {"coordinates":[15.0589942932,48.7934074402],"type":"Point"}
}