{
  "type": "Feature",
  "properties": {
    "addr:full":"Wiener Str 4 Hartberg Steiermark 8230",
    "addr:postcode":"8230",
    "iso:country":"AT",
    "sg:address":"Wiener Str 4",
    "sg:city":"Hartberg",
    "sg:orig_category":"Bekleidung / Einzelhandel",
    "sg:phone":"+43 4333 3263064",
    "sg:postcode":"8230",
    "sg:province":"Steiermark",
    "wof:name":"Sch\u00f6ps Richard & Co AG",
    "wof:placetype":"venue"
},
  "geometry": {"coordinates":[15.97016716,47.2812957764],"type":"Point"}
}