{
  "type": "Feature",
  "properties": {
    "iso:country":"AT",
    "sg:address":"Vogelfeldstr 4",
    "sg:city":"Anthering",
    "sg:orig_category":"Solartechnik",
    "sg:phone":"+43 6223 2249",
    "sg:postcode":"5102",
    "sg:province":"Salzburg",
    "wof:name":"Frischluftpartner GmbH - Ing Stefan K\u00f6pfelsberger",
    "wof:placetype":"venue"
},
  "geometry": {"coordinates":[13.0160999298,47.8822402954],"type":"Point"}
}