{
  "type": "Feature",
  "properties": {
    "addr:full":"Florianipl 1 Gleisdorf Steiermark 8200",
    "addr:housenumber":"1",
    "addr:postcode":"8200",
    "addr:street":"Florianipl",
    "iso:country":"AT",
    "sg:address":"Florianipl 1",
    "sg:city":"Gleisdorf",
    "sg:orig_category":"Banken U Sparkassen",
    "sg:phone":"+43 4331 1223090",
    "sg:postcode":"8200",
    "sg:province":"Steiermark",
    "wof:name":"Bankomat d Volksbank f d Bez Weiz",
    "wof:placetype":"venue"
},
  "geometry": {"coordinates":[15.7112607956,47.1053771973],"type":"Point"}
}