{
  "type": "Feature",
  "properties": {
    "addr:full":"Ignaz-Harrer-Strasse 74 Salzburg Salzburg 5020",
    "addr:housenumber":"74",
    "addr:postcode":"5020",
    "addr:street":"Ignaz-Harrer-Strasse;Salzburg",
    "iso:country":"AT",
    "sg:address":"Ignaz-Harrer-Strasse 74",
    "sg:city":"Salzburg",
    "sg:classifiers":[
        {
            "category":"Food & Beverages",
            "subcategory":"Bakery",
            "type":"Retail Goods"
        }
    ],
    "sg:phone":"+43 662 4313160",
    "sg:postcode":"5020",
    "sg:province":"Salzburg",
    "sg:tags":[
        "biscuit"
    ],
    "wof:name":"Helmuth Balluff & Co",
    "wof:placetype":"venue"
},
  "geometry": {"coordinates":[13.0244789124,47.8119506836],"type":"Point"}
}