{
  "type": "Feature",
  "properties": {
    "addr:full":"Pichelmayerg 2 Wien Wien 1100",
    "addr:housenumber":"2",
    "addr:postcode":"1100",
    "addr:street":"Pichelmayerg",
    "iso:country":"AT",
    "sg:address":"Pichelmayerg 2",
    "sg:city":"Wien",
    "sg:orig_category":"Non-Classified Establishments",
    "sg:phone":"+43 1 6897040",
    "sg:postcode":"1100",
    "sg:province":"Wien",
    "wof:name":"Evangelisches Pfarramt AB",
    "wof:placetype":"venue"
},
  "geometry": {"coordinates":[16.3774223328,48.1547927856],"type":"Point"}
}