{
  "type": "Feature",
  "properties": {
    "addr:full":"Noplerstr 10 Stoob Burgenland 7344",
    "addr:housenumber":"10",
    "addr:postcode":"stoob;7344",
    "addr:street":"Noplerstr",
    "iso:country":"AT",
    "sg:address":"Noplerstr 10",
    "sg:city":"Stoob",
    "sg:orig_category":"Internet-Cafes",
    "sg:phone":"+43 2612 42738",
    "sg:postcode":"7344",
    "sg:province":"Burgenland",
    "wof:name":"Krug Barbara KEG",
    "wof:placetype":"venue"
},
  "geometry": {"coordinates":[16.4682445526,47.5301017761],"type":"Point"}
}