{
  "type": "Feature",
  "properties": {
    "iso:country":"AT",
    "sg:address":"Raiffeisenpl 2",
    "sg:city":"Walding",
    "sg:orig_category":"Banken U Sparkassen",
    "sg:phone":"+43 7234 822940",
    "sg:postcode":"4111",
    "sg:province":"Ober\u00f6sterreich",
    "wof:name":"Raiffeisenbank Walding-Ottensheim regGenmbH",
    "wof:placetype":"venue"
},
  "geometry": {"coordinates":[14.1602058411,48.3505973816],"type":"Point"}
}