{
  "type": "Feature",
  "properties": {
    "iso:country":"AT",
    "sg:address":"Wiedner Hauptstr 113",
    "sg:city":"Wien",
    "sg:orig_category":"Reinigungsbedarf U Reinigungsmittel",
    "sg:phone":"+43 4315 444310",
    "sg:postcode":"1050",
    "sg:province":"Wien",
    "wof:name":"Obrecht F Inh Robert Doll",
    "wof:placetype":"venue"
},
  "geometry": {"coordinates":[16.3619098663,48.1845626831],"type":"Point"}
}