{
  "type": "Feature",
  "properties": {
    "addr:full":"Traunstr 61 Aigen Salzburg 5026",
    "addr:housenumber":"61",
    "addr:postcode":"5026",
    "addr:street":"Traunstr;Salzburg",
    "iso:country":"AT",
    "sg:address":"Traunstr 61",
    "sg:city":"Aigen",
    "sg:orig_category":"Lebensmittel / Einzelhandel",
    "sg:phone":"+43 662 628900",
    "sg:postcode":"5026",
    "sg:province":"Salzburg",
    "wof:name":"Spar-Markt - Haas",
    "wof:placetype":"venue"
},
  "geometry": {"coordinates":[13.0831050873,47.7883033752],"type":"Point"}
}