{
  "type": "Feature",
  "properties": {
    "iso:country":"AT",
    "sg:address":"Bundesstr 1",
    "sg:city":"Hohenems",
    "sg:orig_category":"Steinmetzbetriebe",
    "sg:phone":"+43 4355 7672079",
    "sg:postcode":"6845",
    "sg:province":"Vorarlberg",
    "wof:name":"Prenn Granit- u Marmorwerk GmbH",
    "wof:placetype":"venue"
},
  "geometry": {"coordinates":[9.6887483597,47.3621101379],"type":"Point"}
}