{
  "type": "Feature",
  "properties": {
    "addr:full":"Lerchenfelder Str 70 Wien Wien 1080",
    "addr:housenumber":"70",
    "addr:postcode":"1080",
    "addr:street":"Lerchenfelder Str",
    "iso:country":"AT",
    "sg:address":"Lerchenfelder Str 70",
    "sg:city":"Wien",
    "sg:orig_category":"Optiker",
    "sg:phone":"+43 1 4051013",
    "sg:postcode":"1080",
    "sg:province":"Wien",
    "wof:name":"Optik Ulrich Contact Optique GesmbH",
    "wof:placetype":"venue"
},
  "geometry": {"coordinates":[16.3466720581,48.2070236206],"type":"Point"}
}