{
  "type": "Feature",
  "properties": {
    "iso:country":"AT",
    "sg:address":"Herbersteinstr 73",
    "sg:city":"Wetzelsdorf",
    "sg:orig_category":"Personalbereitstellung",
    "sg:phone":"+43 4331 6912473",
    "sg:postcode":"8052",
    "sg:province":"Steiermark",
    "wof:name":"LKF-Weinberger",
    "wof:placetype":"venue"
},
  "geometry": {"coordinates":[15.3937797546,47.0597686768],"type":"Point"}
}