{
  "type": "Feature",
  "properties": {
    "iso:country":"AT",
    "sg:address":"Erdbergstr 184",
    "sg:city":"Wien",
    "sg:orig_category":"Tankstellen",
    "sg:phone":"+43 1 79872020",
    "sg:postcode":"1030",
    "sg:province":"Wien",
    "wof:name":"BP Austria Marketing GmbH",
    "wof:placetype":"venue"
},
  "geometry": {"coordinates":[16.410785675,48.1929969788],"type":"Point"}
}