{
  "type": "Feature",
  "properties": {
    "addr:full":"Rathstr 50 Wien Wien 1190",
    "addr:housenumber":"50",
    "addr:postcode":"1190",
    "addr:street":"Rathstr",
    "iso:country":"AT",
    "sg:address":"Rathstr 50",
    "sg:city":"Wien",
    "sg:orig_category":"Heurigen / Buschenschank",
    "sg:phone":"+43 1 4403727",
    "sg:postcode":"1190",
    "sg:province":"Wien",
    "wof:name":"Wolff Heuriger-Weingut",
    "wof:placetype":"venue"
},
  "geometry": {"coordinates":[16.3025150299,48.2511177063],"type":"Point"}
}