{
  "type": "Feature",
  "properties": {
    "addr:full":"Mozartpl. 5-7 Salzburg Salzburg 5020",
    "addr:housenumber":"5-7",
    "addr:postcode":"5020",
    "addr:street":"Mozartpl.;Salzburg",
    "iso:country":"AT",
    "sg:address":"Mozartpl. 5-7",
    "sg:city":"Salzburg",
    "sg:classifiers":[
        {
            "category":"Banks & Credit Unions",
            "subcategory":"Bank",
            "type":"Services"
        }
    ],
    "sg:phone":"+43 4366 28080",
    "sg:postcode":"5020",
    "sg:province":"Salzburg",
    "sg:tags":[
        "banking",
        "institution"
    ],
    "wof:name":"AMERICAN EXPRESS BANK LTD.",
    "wof:placetype":"venue"
},
  "geometry": {"coordinates":[13.0481777191,47.7990913391],"type":"Point"}
}