{
  "type": "Feature",
  "properties": {
    "addr:full":"Neunkirchner Strasse 46-52 Wiener Neustadt Nieder\u00f6sterreich 2700",
    "addr:postcode":"46-52;2700",
    "addr:street":"Neunkirchner Strasse;Niederoesterreich",
    "iso:country":"AT",
    "sg:address":"Neunkirchner Strasse 46-52",
    "sg:city":"Wiener Neustadt",
    "sg:classifiers":[
        {
            "category":"Retail",
            "subcategory":"Auto Repair",
            "type":"Services"
        }
    ],
    "sg:phone":"+43 2622 23134",
    "sg:postcode":"2700",
    "sg:province":"Nieder\u00f6sterreich",
    "sg:tags":[
        "tyre"
    ],
    "wof:name":"Alfons Sipser Ges.m.b.H.",
    "wof:placetype":"venue"
},
  "geometry": {"coordinates":[16.2410907745,47.8071174622],"type":"Point"}
}