{
  "type": "Feature",
  "properties": {
    "addr:full":"Nr 24 Weitersfelden Ober\u00f6sterreich 4272",
    "addr:postcode":"4272",
    "addr:street":"Nr;Weitersfelden Oberoesterreich",
    "iso:country":"AT",
    "sg:address":"Nr 24",
    "sg:city":"Weitersfelden",
    "sg:orig_category":"Biologische Produkte",
    "sg:phone":"+43 4379 526234",
    "sg:postcode":"4272",
    "sg:province":"Ober\u00f6sterreich",
    "wof:name":"Bio Frischdienst - Renate N\u00f6tstaller",
    "wof:placetype":"venue"
},
  "geometry": {"coordinates":[14.7282371521,48.4773292542],"type":"Point"}
}