{
  "type": "Feature",
  "properties": {
    "iso:country":"AT",
    "sg:address":"H\u00f6henweg 17",
    "sg:city":"Mariatrost",
    "sg:orig_category":"Elektroinstallationsunternehmen",
    "sg:phone":"+43 3132 2620",
    "sg:postcode":"8044",
    "sg:province":"Steiermark",
    "wof:name":"Kratzer Johann",
    "wof:placetype":"venue"
},
  "geometry": {"coordinates":[15.4900388718,47.1405334473],"type":"Point"}
}