{
  "type": "Feature",
  "properties": {
    "addr:full":"Simmeringer Hauptstr 39 Wien Wien 1110",
    "addr:housenumber":"39",
    "addr:postcode":"1110",
    "addr:street":"Simmeringer Hauptstr",
    "iso:country":"AT",
    "sg:address":"Simmeringer Hauptstr 39",
    "sg:city":"Wien",
    "sg:orig_category":"Matratzen",
    "sg:phone":"+43 1 7436885",
    "sg:postcode":"1110",
    "sg:province":"Wien",
    "wof:name":"Matratzen Concord GesmbH",
    "wof:placetype":"venue"
},
  "geometry": {"coordinates":[16.4093704224,48.1809577942],"type":"Point"}
}