{
  "type": "Feature",
  "properties": {
    "addr:full":"Ungarg. 37 Wien Wien 1030",
    "addr:housenumber":"37",
    "addr:postcode":"1030",
    "addr:street":"Ungarg.",
    "iso:country":"AT",
    "sg:address":"Ungarg. 37",
    "sg:city":"Wien",
    "sg:classifiers":[
        {
            "category":"Professional",
            "subcategory":"Advertising",
            "type":"Services"
        }
    ],
    "sg:phone":"+43 4317 17100",
    "sg:postcode":"1030",
    "sg:province":"Wien",
    "sg:tags":[
        "communication",
        "medium"
    ],
    "wof:name":"FESSEL-GFK INSTITUT F. MARKTFORSCHUNG GES.MBH",
    "wof:placetype":"venue"
},
  "geometry": {"coordinates":[16.38763237,48.200504303],"type":"Point"}
}