{
  "type": "Feature",
  "properties": {
    "addr:full":"Hauptpl 7 Haugsdorf Nieder\u00f6sterreich 2054",
    "addr:housenumber":"7",
    "addr:postcode":"2054",
    "addr:street":"Hauptpl",
    "iso:country":"AT",
    "sg:address":"Hauptpl 7",
    "sg:city":"Haugsdorf",
    "sg:orig_category":"Banken U Sparkassen",
    "sg:phone":"+43 2944 22610",
    "sg:postcode":"2054",
    "sg:province":"Nieder\u00f6sterreich",
    "wof:name":"Raiffeisenkasse Retz-Pulkautal regGenmbH",
    "wof:placetype":"venue"
},
  "geometry": {"coordinates":[16.0777797699,48.7081794739],"type":"Point"}
}