{
  "type": "Feature",
  "properties": {
    "addr:full":"/Pf\u00e4nder Bregenz Vorarlberg 6900",
    "addr:postcode":"6900",
    "iso:country":"AT",
    "sg:address":"/Pf\u00e4nder",
    "sg:city":"Bregenz",
    "sg:classifiers":[
        {
            "category":"Restaurant",
            "type":"Food & Drink"
        }
    ],
    "sg:phone":"+43 5574 42184",
    "sg:postcode":"6900",
    "sg:province":"Vorarlberg",
    "wof:name":"Pf\u00e4nder-Berghaus",
    "wof:placetype":"venue"
},
  "geometry": {"coordinates":[9.7464256287,47.4882698059],"type":"Point"}
}