{
  "type": "Feature",
  "properties": {
    "addr:full":"Nr 345 Krottendorf-Gaisfeld Steiermark 8564",
    "addr:postcode":"8564",
    "addr:street":"Nr",
    "iso:country":"AT",
    "sg:address":"Nr 345",
    "sg:city":"Krottendorf-Gaisfeld",
    "sg:orig_category":"\u00c3\u201erzte / F Allgemeinmedizin",
    "sg:phone":"+43 3143 2235",
    "sg:postcode":"8564",
    "sg:province":"Steiermark",
    "wof:name":"Heidinger Peter Dr",
    "wof:placetype":"venue"
},
  "geometry": {"coordinates":[15.1990747452,47.0217704773],"type":"Point"}
}