{
  "type": "Feature",
  "properties": {
    "addr:full":"Heustadelg 1/1 Wien Wien 1220",
    "addr:housenumber":"1 / 1",
    "addr:postcode":"1220",
    "addr:street":"Heustadelg",
    "iso:country":"AT",
    "sg:address":"Heustadelg 1/1",
    "sg:city":"Wien",
    "sg:orig_category":"Gastronomie- U Hoteleinrichtungen",
    "sg:phone":"+43 4366 44538644",
    "sg:postcode":"1220",
    "sg:province":"Wien",
    "sg:website":"gastroteufel.at",
    "wof:name":"Gastroteufel Norbert Schwitzer",
    "wof:placetype":"venue"
},
  "geometry": {"coordinates":[16.444606781,48.2497138977],"type":"Point"}
}