{
  "type": "Feature",
  "properties": {
    "iso:country":"AT",
    "sg:address":"Hochstr 32a",
    "sg:city":"Perchtoldsdorf",
    "sg:orig_category":"Installationsunternehmen",
    "sg:phone":"+43 1 8673666",
    "sg:postcode":"2380",
    "sg:province":"Nieder\u00f6sterreich",
    "sg:website":"absolut-haustechnik.at",
    "wof:name":"ABSOLUT Martin Schmidt",
    "wof:placetype":"venue"
},
  "geometry": {"coordinates":[16.2627696991,48.1238555908],"type":"Point"}
}