{
  "type": "Feature",
  "properties": {
    "iso:country":"AT",
    "sg:address":"Erkerg 10",
    "sg:city":"Klagenfurt",
    "sg:orig_category":"Botendienste",
    "sg:phone":"+43 664 5036291",
    "sg:postcode":"9020",
    "sg:province":"K\u00e4rnten",
    "wof:name":"Maier Franz",
    "wof:placetype":"venue"
},
  "geometry": {"coordinates":[14.2908792496,46.6122817993],"type":"Point"}
}