{
  "type": "Feature",
  "properties": {
    "iso:country":"AT",
    "sg:address":"Kirchgasse 28",
    "sg:city":"Feldkirchen in K\u00e4rnten",
    "sg:classifiers":[
        {
            "category":"Social Services",
            "subcategory":"Adult Care",
            "type":"Services"
        }
    ],
    "sg:phone":"+43 4276 4306",
    "sg:postcode":"9560",
    "sg:province":"K\u00e4rnten",
    "sg:tags":[
        "limb",
        "artificial"
    ],
    "wof:name":"Orthop\u00e4dietechnik-u. Sanit\u00e4tsfachhandel GesmbH",
    "wof:placetype":"venue"
},
  "geometry": {"coordinates":[14.0944223404,46.7263641357],"type":"Point"}
}