{
  "type": "Feature",
  "properties": {
    "addr:full":"Ledererg 20 Wien Wien 1080",
    "addr:housenumber":"20",
    "addr:postcode":"1080",
    "addr:street":"Ledererg",
    "iso:country":"AT",
    "sg:address":"Ledererg 20",
    "sg:city":"Wien",
    "sg:orig_category":"Feinkost",
    "sg:phone":"+43 1 4058858",
    "sg:postcode":"1080",
    "sg:province":"Wien",
    "wof:name":"Drazan Brigitte",
    "wof:placetype":"venue"
},
  "geometry": {"coordinates":[16.3487606049,48.2127914429],"type":"Point"}
}