{
  "type": "Feature",
  "properties": {
    "addr:full":"Mittelstr 40 Wolkersdorf im Weinviertel Nieder\u00f6sterreich 2120",
    "addr:housenumber":"40",
    "addr:postcode":"2120",
    "addr:street":"Mittelstr",
    "iso:country":"AT",
    "sg:address":"Mittelstr 40",
    "sg:city":"Wolkersdorf im Weinviertel",
    "sg:orig_category":"Lebens- U Sozialberatung",
    "sg:phone":"+43 2245 2258",
    "sg:postcode":"2120",
    "sg:province":"Nieder\u00f6sterreich",
    "wof:name":"Ehe- Familien- und Lebensberatungsstelle",
    "wof:placetype":"venue"
},
  "geometry": {"coordinates":[16.5196666718,48.3830986023],"type":"Point"}
}