{
  "type": "Feature",
  "properties": {
    "addr:full":"Nr 37 Studenzen Steiermark 8322",
    "addr:postcode":"8322",
    "addr:street":"Nr",
    "iso:country":"AT",
    "sg:address":"Nr 37",
    "sg:city":"Studenzen",
    "sg:classifiers":[
        {
            "category":"Farming",
            "subcategory":"Livestock Farm",
            "type":"Manufacturing & Wholesale Goods"
        }
    ],
    "sg:phone":"+43 4331 152201",
    "sg:postcode":"8322",
    "sg:province":"Steiermark",
    "sg:tags":[
        "agriculture"
    ],
    "wof:name":"OBST LEOPOLD HANDELS GMBH",
    "wof:placetype":"venue"
},
  "geometry": {"coordinates":[15.7906103134,47.0232505798],"type":"Point"}
}