{
  "type": "Feature",
  "properties": {
    "iso:country":"AT",
    "sg:address":"S\u00e4gestrasse 210",
    "sg:city":"St. Michael im Lungau",
    "sg:orig_category":"Wedge Plants For Bonding Of Lengthening Joints",
    "sg:phone":"+43 6477 7558",
    "sg:postcode":"5582",
    "sg:province":"Salzburg",
    "sg:website":"hutter-holz.at",
    "wof:name":"Hutter - Holzindustrie Ges.m.b.H.",
    "wof:placetype":"venue"
},
  "geometry": {"coordinates":[13.6378936768,47.0988998413],"type":"Point"}
}