{
  "type": "Feature",
  "properties": {
    "addr:full":"Quellenweg 14 Wildon Steiermark 8410",
    "addr:housenumber":"14",
    "addr:postcode":"8410",
    "addr:street":"Quellenweg;Steiermark",
    "iso:country":"AT",
    "sg:address":"Quellenweg 14",
    "sg:city":"Wildon",
    "sg:orig_category":"Lichttechnik",
    "sg:phone":"+43 3182 44870",
    "sg:postcode":"8410",
    "sg:province":"Steiermark",
    "wof:name":"IVAP Trading - Notbeleuchtung",
    "wof:placetype":"venue"
},
  "geometry": {"coordinates":[15.51658535,46.8796081543],"type":"Point"}
}