{
  "type": "Feature",
  "properties": {
    "iso:country":"AT",
    "sg:address":"Schlo\u00dfstr 17",
    "sg:city":"Saalfelden am Steinernen Meer",
    "sg:orig_category":"Ingenieurkonsulenten / Zivilingenieure",
    "sg:phone":"+43 6582 72066",
    "sg:postcode":"5760",
    "sg:province":"Salzburg",
    "wof:name":"Kienberger Helmut Dipl-Ing Dr",
    "wof:placetype":"venue"
},
  "geometry": {"coordinates":[12.8474750519,47.426410675],"type":"Point"}
}