{
  "type": "Feature",
  "properties": {
    "addr:full":"Hildmannpl 6 Salzburg Salzburg 5020",
    "addr:housenumber":"6",
    "addr:postcode":"5020",
    "addr:street":"Hildmannpl;Salzburg",
    "iso:country":"AT",
    "sg:address":"Hildmannpl 6",
    "sg:city":"Salzburg",
    "sg:classifiers":[
        {
            "category":"Travel",
            "subcategory":"Hotels & Motels",
            "type":"Entertainment"
        }
    ],
    "sg:phone":"+43 662 874760",
    "sg:postcode":"5020",
    "sg:province":"Salzburg",
    "wof:name":"Schw\u00e4rzler Hotels Sales Office GmbH",
    "wof:placetype":"venue"
},
  "geometry": {"coordinates":[13.0376777649,47.7977752686],"type":"Point"}
}