{
  "type": "Feature",
  "properties": {
    "iso:country":"AT",
    "sg:city":"Bregenz",
    "sg:orig_category":"Finanzen, Investment",
    "sg:postcode":"6900",
    "sg:province":"Vorarlberg",
    "sg:website":"http://www.vbankdirekt.at",
    "wof:name":"vbankdirekt.at - Full-Service-Discount-Broker",
    "wof:placetype":"venue"
},
  "geometry": {"coordinates":[9.7436752319,47.5037956238],"type":"Point"}
}