{
  "type": "Feature",
  "properties": {
    "addr:full":"Waldeggstr 59/1 Linz Ober\u00f6sterreich 4020",
    "addr:housenumber":"59 / 1",
    "addr:postcode":"4020",
    "addr:street":"Waldeggstr",
    "iso:country":"AT",
    "sg:address":"Waldeggstr 59/1",
    "sg:city":"Linz",
    "sg:orig_category":"Orientteppiche",
    "sg:phone":"+43 732 664666",
    "sg:postcode":"4020",
    "sg:province":"Ober\u00f6sterreich",
    "wof:name":"Reyhani Abbas KmzlR",
    "wof:placetype":"venue"
},
  "geometry": {"coordinates":[14.2875528336,48.2873191833],"type":"Point"}
}