{
  "type": "Feature",
  "properties": {
    "iso:country":"AT",
    "sg:address":"Conte-Corti-Str 18",
    "sg:city":"Pressbaum",
    "sg:orig_category":"\u00c3\u201erzte / F Allgemeinmedizin",
    "sg:phone":"+43 2233 55550",
    "sg:postcode":"3021",
    "sg:province":"Nieder\u00f6sterreich",
    "wof:name":"Kunyik-Szlezak Franz Dr",
    "wof:placetype":"venue"
},
  "geometry": {"coordinates":[16.0742015839,48.1640129089],"type":"Point"}
}