{
  "type": "Feature",
  "properties": {
    "addr:full":"Dorf 5 Seeham Salzburg 5164",
    "addr:housenumber":"5",
    "addr:postcode":"5164",
    "addr:street":"Dorf;Salzburg",
    "iso:country":"AT",
    "sg:address":"Dorf 5",
    "sg:city":"Seeham",
    "sg:orig_category":"Tourismusinformation U -Organisationen",
    "sg:phone":"+43 4362 175493",
    "sg:postcode":"5164",
    "sg:province":"Salzburg",
    "wof:name":"Fremdenverkehrsverband Seeham",
    "wof:placetype":"venue"
},
  "geometry": {"coordinates":[13.0786962509,47.9679107666],"type":"Point"}
}