{
  "type": "Feature",
  "properties": {
    "iso:country":"AT",
    "sg:address":"Kart\u00e4userg 3",
    "sg:city":"Scheibbs",
    "sg:orig_category":"Notare",
    "sg:phone":"+43 7482 42306",
    "sg:postcode":"3270",
    "sg:province":"Nieder\u00f6sterreich",
    "wof:name":"Holzinger Gottfried Mag",
    "wof:placetype":"venue"
},
  "geometry": {"coordinates":[15.167216301,48.0050201416],"type":"Point"}
}