{
  "type": "Feature",
  "properties": {
    "addr:full":"Mitterweg 176 Innsbruck Tirol 6020",
    "addr:housenumber":"176",
    "addr:postcode":"6020",
    "addr:street":"Mitterweg;Tirol",
    "iso:country":"AT",
    "sg:address":"Mitterweg 176",
    "sg:city":"Innsbruck",
    "sg:orig_category":"Architekten",
    "sg:phone":"+43 512 285380",
    "sg:postcode":"6020",
    "sg:province":"Tirol",
    "wof:name":"Schweiger Harald Arch Dipl-Ing",
    "wof:placetype":"venue"
},
  "geometry": {"coordinates":[11.360912323,47.25598526],"type":"Point"}
}