{
  "type": "Feature",
  "properties": {
    "iso:country":"AT",
    "sg:address":"Rosbachstr 534",
    "sg:city":"Kaprun",
    "sg:orig_category":"Pensionen / Privatzimmer",
    "sg:phone":"+43 6547 8538",
    "sg:postcode":"5710",
    "sg:province":"Salzburg",
    "wof:name":"Ripper Pension",
    "wof:placetype":"venue"
},
  "geometry": {"coordinates":[12.7681894302,47.2716789246],"type":"Point"}
}