{
  "type": "Feature",
  "properties": {
    "addr:full":"Wiener Str B 16 Ebreichsdorf Nieder\u00f6sterreich 2483",
    "addr:housenumber":"16",
    "addr:postcode":"2483",
    "addr:street":"B",
    "iso:country":"AT",
    "sg:address":"Wiener Str B 16",
    "sg:city":"Ebreichsdorf",
    "sg:orig_category":"Gartencenter",
    "sg:phone":"+43 4322 54726890",
    "sg:postcode":"2483",
    "sg:province":"Nieder\u00f6sterreich",
    "sg:website":"gartenparkgeringer.at",
    "wof:name":"Geringer Ing Gartenpark GmbH",
    "wof:placetype":"venue"
},
  "geometry": {"coordinates":[16.3995132446,47.9585876465],"type":"Point"}
}