{
  "type": "Feature",
  "properties": {
    "addr:full":"Manker Str 37 Wieselburg an der Erlauf Nieder\u00f6sterreich 3250",
    "addr:postcode":"3250",
    "addr:street":"Str 37",
    "iso:country":"AT",
    "sg:address":"Manker Str 37",
    "sg:city":"Wieselburg an der Erlauf",
    "sg:orig_category":"Videotheken",
    "sg:phone":"+43 4374 1654810",
    "sg:postcode":"3250",
    "sg:province":"Nieder\u00f6sterreich",
    "wof:name":"Video Royal",
    "wof:placetype":"venue"
},
  "geometry": {"coordinates":[15.1446237564,48.1286621094],"type":"Point"}
}