{
  "type": "Feature",
  "properties": {
    "iso:country":"AT",
    "sg:address":"Heupl 8",
    "sg:city":"Klagenfurt",
    "sg:classifiers":[
        {
            "category":"Restaurant",
            "type":"Food & Drink"
        }
    ],
    "sg:phone":"+43 463 500255",
    "sg:postcode":"9020",
    "sg:province":"K\u00e4rnten",
    "wof:name":"Wieser Harald",
    "wof:placetype":"venue"
},
  "geometry": {"coordinates":[14.3084411621,46.6266136169],"type":"Point"}
}