{
  "type": "Feature",
  "properties": {
    "addr:full":"Brehmstr 9 Wien Wien 1110",
    "addr:housenumber":"9",
    "addr:postcode":"1110",
    "addr:street":"Brehmstr",
    "iso:country":"AT",
    "sg:address":"Brehmstr 9",
    "sg:city":"Wien",
    "sg:orig_category":"Volksschulen",
    "sg:phone":"+43 1 7491446",
    "sg:postcode":"1110",
    "sg:province":"Wien",
    "wof:name":"Schulen d Stadt Wien",
    "wof:placetype":"venue"
},
  "geometry": {"coordinates":[16.4055538177,48.1755867004],"type":"Point"}
}