{
  "type": "Feature",
  "properties": {
    "addr:full":"Seitenbergg 61 Wien Wien 1160",
    "addr:housenumber":"61",
    "addr:postcode":"1160",
    "addr:street":"Seitenbergg",
    "iso:country":"AT",
    "sg:address":"Seitenbergg 61",
    "sg:city":"Wien",
    "sg:orig_category":"Psychotherapie",
    "sg:phone":"+43 664 2611536",
    "sg:postcode":"1160",
    "sg:province":"Wien",
    "wof:name":"Leimer Helmut",
    "wof:placetype":"venue"
},
  "geometry": {"coordinates":[16.3143463135,48.220741272],"type":"Point"}
}