{
  "type": "Feature",
  "properties": {
    "addr:full":"Gesellenhausstr 7 Linz Ober\u00f6sterreich 4020",
    "addr:housenumber":"7",
    "addr:postcode":"4020",
    "addr:street":"Gesellenhausstr",
    "iso:country":"AT",
    "sg:address":"Gesellenhausstr 7",
    "sg:city":"Linz",
    "sg:orig_category":"Ballettschulen",
    "sg:phone":"+43 4373 2777705",
    "sg:postcode":"4020",
    "sg:province":"Ober\u00f6sterreich",
    "sg:website":"yorkstudios.at",
    "wof:name":"B\u00fchnentanzschule York Studios",
    "wof:placetype":"venue"
},
  "geometry": {"coordinates":[14.2893724442,48.2981071472],"type":"Point"}
}