{
  "type": "Feature",
  "properties": {
    "addr:full":"Langg 25 Bad Radkersburg Steiermark 8490",
    "addr:housenumber":"25",
    "addr:postcode":"8490",
    "addr:street":"Langg",
    "iso:country":"AT",
    "sg:address":"Langg 25",
    "sg:city":"Bad Radkersburg",
    "sg:orig_category":"Papier- U Schreibwaren / Einzelhandel",
    "sg:phone":"+43 4334 762375",
    "sg:postcode":"8490",
    "sg:province":"Steiermark",
    "wof:name":"Weitzinger - Inh Sedlak Irmgard",
    "wof:placetype":"venue"
},
  "geometry": {"coordinates":[15.9888820648,46.6908340454],"type":"Point"}
}