{
  "type": "Feature",
  "properties": {
    "addr:full":"Karl-Aschenbrenner-G 3 Wien Wien 1210",
    "addr:housenumber":"3",
    "addr:postcode":"1210",
    "addr:street":"Karl-Aschenbrenner-G",
    "iso:country":"AT",
    "sg:address":"Karl-Aschenbrenner-G 3",
    "sg:city":"Wien",
    "sg:orig_category":"Ambulatorien",
    "sg:phone":"+43 1 6012240224",
    "sg:postcode":"1210",
    "sg:province":"Wien",
    "wof:name":"Wiener Gebietskrankenkasse Gesundheitszentrum f Kinder",
    "wof:placetype":"venue"
},
  "geometry": {"coordinates":[16.3975124359,48.2536010742],"type":"Point"}
}