{
  "type": "Feature",
  "properties": {
    "addr:full":"Nr 2a Mogersdorf Burgenland 8382",
    "addr:housenumber":"2a",
    "addr:postcode":"8382",
    "addr:street":"Nr",
    "iso:country":"AT",
    "sg:address":"Nr 2a",
    "sg:city":"Mogersdorf",
    "sg:orig_category":"Gemeinden",
    "sg:phone":"+43 3329 48798",
    "sg:postcode":"8382",
    "sg:province":"Burgenland",
    "wof:name":"Gemeindeamt Weichselbaum",
    "wof:placetype":"venue"
},
  "geometry": {"coordinates":[16.2301654816,46.9476585388],"type":"Point"}
}