{
  "type": "Feature",
  "properties": {
    "addr:full":"Reinprechtsdorfer Strasse 7 Wien Wien 1050",
    "addr:housenumber":"7",
    "addr:postcode":"1050",
    "addr:street":"Reinprechtsdorfer Strasse",
    "iso:country":"AT",
    "sg:address":"Reinprechtsdorfer Strasse 7",
    "sg:city":"Wien",
    "sg:classifiers":[
        {
            "category":"Structure",
            "subcategory":"Tunnel",
            "type":"Public Place"
        }
    ],
    "sg:phone":"+43 1 2569200",
    "sg:postcode":"1050",
    "sg:province":"Wien",
    "sg:tags":[
        "aluminium",
        "fence"
    ],
    "sg:website":"alusol.at",
    "wof:name":"ALUSOL Handel und Produktion Ges.m.b.H.",
    "wof:placetype":"venue"
},
  "geometry": {"coordinates":[16.3560085297,48.1835594177],"type":"Point"}
}