{
  "type": "Feature",
  "properties": {
    "iso:country":"AT",
    "sg:address":"Nr 64",
    "sg:city":"St. Willibald",
    "sg:orig_category":"Friseure U Frisiersalons",
    "sg:phone":"+43 4377 622827",
    "sg:postcode":"4762",
    "sg:province":"Ober\u00f6sterreich",
    "wof:name":"Life Style",
    "wof:placetype":"venue"
},
  "geometry": {"coordinates":[13.6854219437,48.3610458374],"type":"Point"}
}