{
  "type": "Feature",
  "properties": {
    "iso:country":"AT",
    "sg:address":"Faulmanng 4/4",
    "sg:city":"Wien",
    "sg:orig_category":"Ingenieurkonsulenten / Zivilingenieure",
    "sg:phone":"+43 1 5861516",
    "sg:postcode":"1040",
    "sg:province":"Wien",
    "wof:name":"Spiegelfeld Markus Dipl-Ing",
    "wof:placetype":"venue"
},
  "geometry": {"coordinates":[16.3658390045,48.1987228394],"type":"Point"}
}