{
  "type": "Feature",
  "properties": {
    "addr:full":"Stadtpl 14/2 Gm\u00fcnd Nieder\u00f6sterreich 3950",
    "addr:housenumber":"14 / 2",
    "addr:postcode":"3950",
    "addr:street":"Stadtpl;Niederoesterreich",
    "iso:country":"AT",
    "sg:address":"Stadtpl 14/2",
    "sg:city":"Gm\u00fcnd",
    "sg:orig_category":"Architekten",
    "sg:phone":"+43 2852 54925",
    "sg:postcode":"3950",
    "sg:province":"Nieder\u00f6sterreich",
    "wof:name":"Macho Gerhard Arch Dipl-Ing",
    "wof:placetype":"venue"
},
  "geometry": {"coordinates":[14.9847583771,48.7727203369],"type":"Point"}
}