{
  "type": "Feature",
  "properties": {
    "addr:full":"Raschleweg 8 Fiss Tirol 6533",
    "addr:housenumber":"8",
    "addr:postcode":"6533",
    "addr:street":"Raschleweg;Tirol",
    "iso:country":"AT",
    "sg:address":"Raschleweg 8",
    "sg:city":"Fiss",
    "sg:orig_category":"Elektroinstallationsunternehmen",
    "sg:phone":"+43 5476 6060",
    "sg:postcode":"6533",
    "sg:province":"Tirol",
    "wof:name":"Elektrotechnik Plangger GmbH Ing",
    "wof:placetype":"venue"
},
  "geometry": {"coordinates":[10.6198368073,47.0544128418],"type":"Point"}
}