{
  "type": "Feature",
  "properties": {
    "iso:country":"AT",
    "sg:address":"Wagramer Str 111",
    "sg:city":"Wien",
    "sg:classifiers":[
        {
            "category":"Restaurant",
            "type":"Food & Drink"
        }
    ],
    "sg:phone":"+43 1 2032352",
    "sg:postcode":"1220",
    "sg:province":"Wien",
    "wof:name":"Fischer Walter",
    "wof:placetype":"venue"
},
  "geometry": {"coordinates":[16.4396743774,48.2463989258],"type":"Point"}
}