{
  "type": "Feature",
  "properties": {
    "addr:full":"Otto-Bauer-G 9 Wien Wien 1060",
    "addr:housenumber":"9",
    "addr:postcode":"1060",
    "addr:street":"Otto-Bauer-G",
    "iso:country":"AT",
    "sg:address":"Otto-Bauer-G 9",
    "sg:city":"Wien",
    "sg:orig_category":"Politische Parteien",
    "sg:phone":"+43 1 53427106",
    "sg:postcode":"1060",
    "sg:province":"Wien",
    "wof:name":"Sozialdemokratische Partei \u00f6sterreichs BezOrg Mariahilf",
    "wof:placetype":"venue"
},
  "geometry": {"coordinates":[16.3488769531,48.1955566406],"type":"Point"}
}