{
  "type": "Feature",
  "properties": {
    "addr:full":"Bahnhofpl 2a Bad Gastein Salzburg 5640",
    "addr:housenumber":"2a",
    "addr:postcode":"5640",
    "addr:street":"Bahnhofpl;Salzburg",
    "iso:country":"AT",
    "sg:address":"Bahnhofpl 2a",
    "sg:city":"Bad Gastein",
    "sg:classifiers":[
        {
            "category":"Travel",
            "subcategory":"Hotels & Motels",
            "type":"Entertainment"
        }
    ],
    "sg:phone":"+43 6434 27170",
    "sg:postcode":"5640",
    "sg:province":"Salzburg",
    "wof:name":"Kurhotel Goethehof",
    "wof:placetype":"venue"
},
  "geometry": {"coordinates":[13.1325101852,47.1122550964],"type":"Point"}
}