{
  "type": "Feature",
  "properties": {
    "addr:full":"Robert-Stolz-Strasse 7 Linz Ober\u00f6sterreich 4020",
    "addr:housenumber":"7",
    "addr:postcode":"4020",
    "addr:street":"Robert-Stolz-Strasse",
    "iso:country":"AT",
    "sg:address":"Robert-Stolz-Strasse 7",
    "sg:city":"Linz",
    "sg:classifiers":[
        {
            "category":"Professional",
            "subcategory":"Advertising",
            "type":"Services"
        }
    ],
    "sg:phone":"+43 732 6658830",
    "sg:postcode":"4020",
    "sg:province":"Ober\u00f6sterreich",
    "sg:tags":[
        "agency"
    ],
    "sg:website":"como.at",
    "wof:name":"COMO Werbe & Public Relations Ges.m.b.H.",
    "wof:placetype":"venue"
},
  "geometry": {"coordinates":[14.2764625549,48.285610199],"type":"Point"}
}