{
  "type": "Feature",
  "properties": {
    "iso:country":"AT",
    "sg:address":"Harter Str 167",
    "sg:city":"Stra\u00dfgang",
    "sg:orig_category":"Restaurants: Chinesisch",
    "sg:phone":"+43 316 285432",
    "sg:postcode":"8054",
    "sg:province":"Steiermark",
    "wof:name":"China-Restaurant Neuer Stern",
    "wof:placetype":"venue"
},
  "geometry": {"coordinates":[15.4005756378,47.0386276245],"type":"Point"}
}