{
  "type": "Feature",
  "properties": {
    "addr:full":"Widnau 12 Feldkirch Vorarlberg 6800",
    "addr:housenumber":"12",
    "addr:postcode":"6800",
    "addr:street":"Widnau",
    "iso:country":"AT",
    "sg:address":"Widnau 12",
    "sg:city":"Feldkirch",
    "sg:orig_category":"Immobilienverwaltungen",
    "sg:phone":"+43 5522 33346024",
    "sg:postcode":"6800",
    "sg:province":"Vorarlberg",
    "wof:name":"IMB Immobilienmanagementgesellschaft des Bundes mbH",
    "wof:placetype":"venue"
},
  "geometry": {"coordinates":[9.5983686447,47.239692688],"type":"Point"}
}