{
  "type": "Feature",
  "properties": {
    "addr:full":"Sollingergasse 13 Wien Wien 1190",
    "addr:housenumber":"13",
    "addr:postcode":"1190",
    "addr:street":"Sollingergasse",
    "iso:country":"AT",
    "sg:address":"Sollingergasse 13",
    "sg:city":"Wien",
    "sg:classifiers":[
        {
            "category":"Government",
            "subcategory":"Office",
            "type":"Public Place"
        }
    ],
    "sg:phone":"+43 1 4819059",
    "sg:postcode":"1190",
    "sg:province":"Wien",
    "sg:tags":[
        "cd-rom",
        "network",
        "integration"
    ],
    "sg:website":"digimedia.co.at",
    "wof:name":"DigiMedia - Peter Ungvari",
    "wof:placetype":"venue"
},
  "geometry": {"coordinates":[16.3350849152,48.2421226501],"type":"Point"}
}