{
  "type": "Feature",
  "properties": {
    "iso:country":"AT",
    "sg:address":"Gudrunstr 168",
    "sg:city":"Wien",
    "sg:orig_category":"Fenster",
    "sg:phone":"+43 1 60328880",
    "sg:postcode":"1100",
    "sg:province":"Wien",
    "wof:name":"Actual Hartlieb & Partner GmbH",
    "wof:placetype":"venue"
},
  "geometry": {"coordinates":[16.365737915,48.1789627075],"type":"Point"}
}