{
  "type": "Feature",
  "properties": {
    "addr:full":"Unterdorf 101 Wenns Tirol 6473",
    "addr:housenumber":"101",
    "addr:postcode":"6473",
    "addr:street":"Unterdorf;Tirol",
    "iso:country":"AT",
    "sg:address":"Unterdorf 101",
    "sg:city":"Wenns",
    "sg:orig_category":"Autoreparatur",
    "sg:phone":"+43 5414 86338",
    "sg:postcode":"6473",
    "sg:province":"Tirol",
    "wof:name":"KFZ-MIKE Weber Michael",
    "wof:placetype":"venue"
},
  "geometry": {"coordinates":[10.7312002182,47.1684265137],"type":"Point"}
}