{
  "type": "Feature",
  "properties": {
    "iso:country":"AT",
    "sg:address":"Ziedlergasse 11",
    "sg:city":"Wien",
    "sg:classifiers":[
        {
            "category":"Home & Garden",
            "subcategory":"Building Materials",
            "type":"Retail Goods"
        }
    ],
    "sg:phone":"+43 1 8652344",
    "sg:postcode":"1230",
    "sg:province":"Wien",
    "sg:tags":[
        "antiglare",
        "blind",
        "roller"
    ],
    "sg:website":"alucolor.at",
    "wof:name":"Alucolor GmbH Jalousien- Markisen-Rolladen Erzeugung",
    "wof:placetype":"venue"
},
  "geometry": {"coordinates":[16.2951717377,48.1486778259],"type":"Point"}
}