{
  "type": "Feature",
  "properties": {
    "iso:country":"AT",
    "sg:address":"Attendorf 58 ",
    "sg:city":"Hitzendorf",
    "sg:orig_category":"CarpenterS Work Supraregional",
    "sg:phone":"+43 3137 2665",
    "sg:postcode":"8151",
    "sg:province":"Steiermark",
    "wof:name":"Willibald Marek",
    "wof:placetype":"venue"
},
  "geometry": {"coordinates":[15.3353347778,47.0280914307],"type":"Point"}
}