{
  "type": "Feature",
  "properties": {
    "iso:country":"AT",
    "sg:address":"Nr 6",
    "sg:city":"Hermagor",
    "sg:orig_category":"Holzhandel",
    "sg:phone":"+43 4282 3274",
    "sg:postcode":"9620",
    "sg:province":"K\u00e4rnten",
    "wof:name":"PAHOLZ HandelsgesmbH",
    "wof:placetype":"venue"
},
  "geometry": {"coordinates":[167.6717224121,-46.1283493042],"type":"Point"}
}