{
  "type": "Feature",
  "properties": {
    "addr:full":"Simmeringer Hauptstr 33 Wien Wien 1110",
    "addr:housenumber":"33",
    "addr:postcode":"1110",
    "addr:street":"Simmeringer Hauptstr",
    "iso:country":"AT",
    "sg:address":"Simmeringer Hauptstr 33",
    "sg:city":"Wien",
    "sg:orig_category":"Transportunternehmen",
    "sg:phone":"+43 4367 63558223",
    "sg:postcode":"1110",
    "sg:province":"Wien",
    "wof:name":"Bolzer Werner",
    "wof:placetype":"venue"
},
  "geometry": {"coordinates":[16.4085197449,48.1816978455],"type":"Point"}
}