{
  "type": "Feature",
  "properties": {
    "addr:full":"Kunzg 4 Wien Wien 1200",
    "addr:housenumber":"4",
    "addr:postcode":"1200",
    "addr:street":"Kunzg",
    "iso:country":"AT",
    "sg:address":"Kunzg 4",
    "sg:city":"Wien",
    "sg:orig_category":"Elektroinstallationsunternehmen",
    "sg:phone":"+43 1 3304242",
    "sg:postcode":"1200",
    "sg:province":"Wien",
    "wof:name":"Zauner Wilhelm GesmbH & Co KG",
    "wof:placetype":"venue"
},
  "geometry": {"coordinates":[16.3789558411,48.2293548584],"type":"Point"}
}