{
  "type": "Feature",
  "properties": {
    "addr:full":"Hof\u00e4ckerg 4a Gleisdorf Steiermark 8200",
    "addr:housenumber":"4a",
    "addr:postcode":"8200",
    "addr:street":"Hofaeckerg",
    "iso:country":"AT",
    "sg:address":"Hof\u00e4ckerg 4a",
    "sg:city":"Gleisdorf",
    "sg:orig_category":"Weiterbildungsinstitute M Allg U Berufl Bildungsangebot",
    "sg:phone":"+43 3112 4050",
    "sg:postcode":"8200",
    "sg:province":"Steiermark",
    "wof:name":"Top Training",
    "wof:placetype":"venue"
},
  "geometry": {"coordinates":[15.7174444199,47.1069984436],"type":"Point"}
}