{
  "type": "Feature",
  "properties": {
    "iso:country":"AT",
    "sg:address":"Neubaustr 36",
    "sg:city":"Steyr",
    "sg:orig_category":"Filmproduktionen",
    "sg:phone":"+43 4366 42111143",
    "sg:postcode":"4400",
    "sg:province":"Ober\u00f6sterreich",
    "wof:name":"YouSee Television - Gerald Egelseer Film- u Fernsehproduktion",
    "wof:placetype":"venue"
},
  "geometry": {"coordinates":[14.4172153473,48.0288581848],"type":"Point"}
}