{
  "type": "Feature",
  "properties": {
    "addr:full":"Mitterfeldstr 1 Amstetten Nieder\u00f6sterreich 3300",
    "addr:housenumber":"1",
    "addr:postcode":"3300",
    "addr:street":"Mitterfeldstr;Niederoesterreich",
    "iso:country":"AT",
    "sg:address":"Mitterfeldstr 1",
    "sg:city":"Amstetten",
    "sg:orig_category":"Autoersatzteile",
    "sg:phone":"+43 4374 72222",
    "sg:postcode":"3300",
    "sg:province":"Nieder\u00f6sterreich",
    "sg:website":"kugellager-leitner.at",
    "wof:name":"Leitner Franz Kfz- u Industriebedarf",
    "wof:placetype":"venue"
},
  "geometry": {"coordinates":[14.8903989792,48.1234207153],"type":"Point"}
}