{
  "type": "Feature",
  "properties": {
    "iso:country":"AT",
    "sg:address":"Roseng 88-90",
    "sg:city":"Gerasdorf",
    "sg:orig_category":"Non-Classified Establishments",
    "sg:phone":"+43 2246 2989",
    "sg:postcode":"2201",
    "sg:province":"Nieder\u00f6sterreich",
    "wof:name":"Pfarramt Kapellerfeld",
    "wof:placetype":"venue"
},
  "geometry": {"coordinates":[16.4987201691,48.3167991638],"type":"Point"}
}