{
  "type": "Feature",
  "properties": {
    "addr:full":"Grazer Str 69 St. Radegund Steiermark 8061",
    "addr:housenumber":"69",
    "addr:postcode":"8061",
    "addr:street":"Str",
    "iso:country":"AT",
    "sg:address":"Grazer Str 69",
    "sg:city":"St. Radegund",
    "sg:orig_category":"Spielwaren U Spiele",
    "sg:phone":"+43 4331 323243",
    "sg:postcode":"8061",
    "sg:province":"Steiermark",
    "wof:name":"Wernitznig & Kohlwei\u00df OEG",
    "wof:placetype":"venue"
},
  "geometry": {"coordinates":[15.5092000961,47.1628417969],"type":"Point"}
}