{
  "type": "Feature",
  "properties": {
    "addr:full":"Turmplatz 1 Lieboch Steiermark 8501",
    "addr:housenumber":"1",
    "addr:postcode":"8501",
    "addr:street":"Turmplatz",
    "iso:country":"AT",
    "sg:address":"Turmplatz 1",
    "sg:city":"Lieboch",
    "sg:classifiers":[
        {
            "category":"Utilities",
            "subcategory":"Water",
            "type":"Services"
        }
    ],
    "sg:phone":"+43 3136 62188",
    "sg:postcode":"8501",
    "sg:province":"Steiermark",
    "sg:tags":[
        "feed",
        "plant",
        "boiler",
        "treatment"
    ],
    "sg:website":"tepro.at",
    "wof:name":"Tepro Project Engineering Wassertechnik GesmbH",
    "wof:placetype":"venue"
},
  "geometry": {"coordinates":[15.3384017944,46.9725074768],"type":"Point"}
}