{
  "type": "Feature",
  "properties": {
    "addr:full":"Franz Leitner-Str 21-23 Knittelfeld Steiermark 8720",
    "addr:housenumber":"21-23",
    "addr:postcode":"8720",
    "iso:country":"AT",
    "sg:address":"Franz Leitner-Str 21-23",
    "sg:city":"Knittelfeld",
    "sg:orig_category":"Polytechnische Schulen",
    "sg:phone":"+43 3512 826970",
    "sg:postcode":"8720",
    "sg:province":"Steiermark",
    "wof:name":"Polytechnische Schule",
    "wof:placetype":"venue"
},
  "geometry": {"coordinates":[14.8308773041,47.2183876038],"type":"Point"}
}