{
  "type": "Feature",
  "properties": {
    "addr:full":"Rosenweg 5 Wartberg im M\u00fcrztal Steiermark 8661",
    "addr:housenumber":"5",
    "addr:postcode":"8661",
    "addr:street":"Rosenweg",
    "iso:country":"AT",
    "sg:address":"Rosenweg 5",
    "sg:city":"Wartberg im M\u00fcrztal",
    "sg:orig_category":"Elektroinstallationsunternehmen",
    "sg:phone":"+43 3858 32910",
    "sg:postcode":"8661",
    "sg:province":"Steiermark",
    "wof:name":"LBG GmbH Schnabl",
    "wof:placetype":"venue"
},
  "geometry": {"coordinates":[15.49746418,47.5296516418],"type":"Point"}
}