{
  "type": "Feature",
  "properties": {
    "addr:full":"Markt 11 Tragwein Ober\u00f6sterreich 4284",
    "addr:housenumber":"11",
    "addr:postcode":"4284",
    "addr:street":"Markt",
    "iso:country":"AT",
    "sg:address":"Markt 11",
    "sg:city":"Tragwein",
    "sg:orig_category":"Non-Classified Establishments",
    "sg:phone":"+43 7263 883150",
    "sg:postcode":"4284",
    "sg:province":"Ober\u00f6sterreich",
    "wof:name":"Pfarramt",
    "wof:placetype":"venue"
},
  "geometry": {"coordinates":[14.62150383,48.3318748474],"type":"Point"}
}