{
  "type": "Feature",
  "properties": {
    "addr:full":"Pestalozzistr 4 Moosburg K\u00e4rnten 9062",
    "addr:housenumber":"4",
    "addr:postcode":"9062",
    "addr:street":"Pestalozzistr;Kaernten",
    "iso:country":"AT",
    "sg:address":"Pestalozzistr 4",
    "sg:city":"Moosburg",
    "sg:orig_category":"Volksschulen",
    "sg:phone":"+43 4342 7283413",
    "sg:postcode":"9062",
    "sg:province":"K\u00e4rnten",
    "wof:name":"Volksschule 1 u Allgemeine Sonderschule",
    "wof:placetype":"venue"
},
  "geometry": {"coordinates":[14.1743040085,46.6548156738],"type":"Point"}
}