{
  "type": "Feature",
  "properties": {
    "addr:full":"Am Pfarrfeld 16 Niederwaldkirchen Ober\u00f6sterreich 4174",
    "addr:housenumber":"16",
    "addr:postcode":"4174",
    "addr:street":"Am Pfarrfeld",
    "iso:country":"AT",
    "sg:address":"Am Pfarrfeld 16",
    "sg:city":"Niederwaldkirchen",
    "sg:orig_category":"Torantriebe",
    "sg:phone":"+43 4372 313269",
    "sg:postcode":"4174",
    "sg:province":"Ober\u00f6sterreich",
    "wof:name":"Normstahl Au\u00dfendienst",
    "wof:placetype":"venue"
},
  "geometry": {"coordinates":[14.0809497833,48.4493484497],"type":"Point"}
}