{
  "type": "Feature",
  "properties": {
    "addr:full":"Hauptstrasse 17 Launsdorf K\u00e4rnten 9314",
    "addr:housenumber":"17",
    "addr:postcode":"9314",
    "addr:street":"Hauptstrasse;Kaernten",
    "iso:country":"AT",
    "sg:address":"Hauptstrasse 17",
    "sg:city":"Launsdorf",
    "sg:classifiers":[
        {
            "category":"Manufacturing",
            "subcategory":"Tools & Machinery",
            "type":"Manufacturing & Wholesale Goods"
        }
    ],
    "sg:phone":"+43 4213 4120",
    "sg:postcode":"9314",
    "sg:province":"K\u00e4rnten",
    "sg:tags":[
        "abrasive"
    ],
    "sg:website":"molemab.at",
    "wof:name":"molemab inotech Schleifmittelindustrie Ges.m.b.H.",
    "wof:placetype":"venue"
},
  "geometry": {"coordinates":[14.4615783691,46.7702331543],"type":"Point"}
}