{
  "type": "Feature",
  "properties": {
    "addr:full":"Preishartlweg 4 Salzburg Salzburg 5020",
    "addr:housenumber":"4",
    "addr:postcode":"5020",
    "addr:street":"Preishartlweg;Salzburg",
    "iso:country":"AT",
    "sg:address":"Preishartlweg 4",
    "sg:city":"Salzburg",
    "sg:orig_category":"Ingenieurkonsulenten / Zivilingenieure",
    "sg:phone":"+43 662 4307030",
    "sg:postcode":"5020",
    "sg:province":"Salzburg",
    "wof:name":"IL - Ingenieurb\u00fcro Laabmayr & Partner ZT GesmbH",
    "wof:placetype":"venue"
},
  "geometry": {"coordinates":[13.0156745911,47.819606781],"type":"Point"}
}