{
  "type": "Feature",
  "properties": {
    "iso:country":"AT",
    "sg:address":"Millennium Park 4",
    "sg:city":"Lustenau",
    "sg:orig_category":"Architekten",
    "sg:phone":"+43 4355 77626540",
    "sg:postcode":"6890",
    "sg:province":"Vorarlberg",
    "wof:name":"Aicher Architeken",
    "wof:placetype":"venue"
},
  "geometry": {"coordinates":[9.6712684631,47.4202842712],"type":"Point"}
}