{
  "type": "Feature",
  "properties": {
    "addr:full":"Hauptstr 24 Blindenmarkt Nieder\u00f6sterreich 3372",
    "addr:housenumber":"24",
    "addr:postcode":"3372",
    "addr:street":"Hauptstr",
    "iso:country":"AT",
    "sg:address":"Hauptstr 24",
    "sg:city":"Blindenmarkt",
    "sg:orig_category":"Tischlereien",
    "sg:phone":"+43 7473 2358",
    "sg:postcode":"3372",
    "sg:province":"Nieder\u00f6sterreich",
    "wof:name":"Kautsch Karl",
    "wof:placetype":"venue"
},
  "geometry": {"coordinates":[14.9896326065,48.1288795471],"type":"Point"}
}