{
  "type": "Feature",
  "properties": {
    "iso:country":"AT",
    "sg:address":"Am D\u00fcrrgraben 18a",
    "sg:city":"Andritz",
    "sg:orig_category":"Handelsagenturen",
    "sg:phone":"+43 316 694316",
    "sg:postcode":"8045",
    "sg:province":"Steiermark",
    "wof:name":"LKW-Beleuchtung - Pro Plast Progress Kunststoff GmbH",
    "wof:placetype":"venue"
},
  "geometry": {"coordinates":[15.4198312759,47.1376914978],"type":"Point"}
}