{
  "type": "Feature",
  "properties": {
    "addr:full":"Korneuburger Str 14 Langenzersdorf Nieder\u00f6sterreich 2103",
    "addr:postcode":"2103",
    "addr:street":"Str 14",
    "iso:country":"AT",
    "sg:address":"Korneuburger Str 14",
    "sg:city":"Langenzersdorf",
    "sg:orig_category":"Architekten",
    "sg:phone":"+43 2244 42700",
    "sg:postcode":"2103",
    "sg:province":"Nieder\u00f6sterreich",
    "wof:name":"Zita Werner Arch Dipl-Ing",
    "wof:placetype":"venue"
},
  "geometry": {"coordinates":[16.3540210724,48.3222122192],"type":"Point"}
}