{
  "type": "Feature",
  "properties": {
    "addr:full":"Gschwendter Str 43 Kumberg Steiermark 8062",
    "addr:housenumber":"43",
    "addr:postcode":"8062",
    "addr:street":"Str",
    "iso:country":"AT",
    "sg:address":"Gschwendter Str 43",
    "sg:city":"Kumberg",
    "sg:orig_category":"Friseure U Frisiersalons",
    "sg:phone":"+43 4331 324545",
    "sg:postcode":"8062",
    "sg:province":"Steiermark",
    "wof:name":"Friseursalon Stelzer",
    "wof:placetype":"venue"
},
  "geometry": {"coordinates":[15.5573501587,47.172958374],"type":"Point"}
}