{
  "type": "Feature",
  "properties": {
    "addr:full":"Maxstr 32 Salzburg Salzburg 5020",
    "addr:housenumber":"32",
    "addr:postcode":"5020",
    "addr:street":"Maxstr;Salzburg",
    "iso:country":"AT",
    "sg:address":"Maxstr 32",
    "sg:city":"Salzburg",
    "sg:orig_category":"Psychologen",
    "sg:phone":"+43 662 874659",
    "sg:postcode":"5020",
    "sg:province":"Salzburg",
    "wof:name":"Zott Herwig Dr",
    "wof:placetype":"venue"
},
  "geometry": {"coordinates":[13.0593042374,47.8287162781],"type":"Point"}
}