{
  "type": "Feature",
  "properties": {
    "iso:country":"AT",
    "sg:address":"Liechtensteinstr 2",
    "sg:city":"Niederabsdorf",
    "sg:orig_category":"Non-Classified Establishments",
    "sg:phone":"+43 2536 7942",
    "sg:postcode":"2272",
    "sg:province":"Nieder\u00f6sterreich",
    "wof:name":"Pfarramt",
    "wof:placetype":"venue"
},
  "geometry": {"coordinates":[16.855178833,48.5644378662],"type":"Point"}
}