{
  "type": "Feature",
  "properties": {
    "addr:full":"Glanfeldstr 46 A Salzburg Salzburg 5020",
    "addr:housenumber":"46 a",
    "addr:postcode":"5020",
    "addr:street":"Glanfeldstr;Salzburg",
    "iso:country":"AT",
    "sg:address":"Glanfeldstr 46 A",
    "sg:city":"Salzburg",
    "sg:orig_category":"Handelsagenturen",
    "sg:phone":"+43 4366 2826445",
    "sg:postcode":"5020",
    "sg:province":"Salzburg",
    "wof:name":"Pro.Fi.S Vertrieb und Regalservice - Stephan Zurkuhlen",
    "wof:placetype":"venue"
},
  "geometry": {"coordinates":[13.0047883987,47.7775840759],"type":"Point"}
}