{
  "type": "Feature",
  "properties": {
    "addr:full":"Kirchenpl 4 Horn Nieder\u00f6sterreich 3580",
    "addr:housenumber":"4",
    "addr:postcode":"3580",
    "addr:street":"Kirchenpl;Niederoesterreich",
    "iso:country":"AT",
    "sg:address":"Kirchenpl 4",
    "sg:city":"Horn",
    "sg:orig_category":"Banken U Sparkassen",
    "sg:phone":"+43 2982 22360",
    "sg:postcode":"3580",
    "sg:province":"Nieder\u00f6sterreich",
    "wof:name":"Raiffeisenbank Horn regGenmbH",
    "wof:placetype":"venue"
},
  "geometry": {"coordinates":[15.657585144,48.6636734009],"type":"Point"}
}