{
  "type": "Feature",
  "properties": {
    "iso:country":"AT",
    "sg:address":"F\u00f6hreng 4",
    "sg:city":"Petzenkirchen",
    "sg:orig_category":"Handelsagenturen",
    "sg:phone":"+43 7416 53864",
    "sg:postcode":"3252",
    "sg:province":"Nieder\u00f6sterreich",
    "wof:name":"Trinkl Josef",
    "wof:placetype":"venue"
},
  "geometry": {"coordinates":[15.152964592,48.1433868408],"type":"Point"}
}