{
  "type": "Feature",
  "properties": {
    "addr:full":"Hauptpl 6 Tulln an der Donau Nieder\u00f6sterreich 3430",
    "addr:housenumber":"6",
    "addr:postcode":"3430",
    "addr:street":"Hauptpl",
    "iso:country":"AT",
    "sg:address":"Hauptpl 6",
    "sg:city":"Tulln an der Donau",
    "sg:orig_category":"Waren Aller Art",
    "sg:phone":"+43 2272 82689",
    "sg:postcode":"3430",
    "sg:province":"Nieder\u00f6sterreich",
    "wof:name":"TACK HandelsgesmbH",
    "wof:placetype":"venue"
},
  "geometry": {"coordinates":[16.0517444611,48.3308944702],"type":"Point"}
}