{
  "type": "Feature",
  "properties": {
    "addr:full":"H\u00f6chster Str 25 Fu\u00dfach Vorarlberg 6972",
    "addr:postcode":"6972",
    "addr:street":"Str 25",
    "iso:country":"AT",
    "sg:address":"H\u00f6chster Str 25",
    "sg:city":"Fu\u00dfach",
    "sg:orig_category":"Wasseraufbereitung U -Reinigung",
    "sg:phone":"+43 5578 75622",
    "sg:postcode":"6972",
    "sg:province":"Vorarlberg",
    "wof:name":"\u00d6sterle Alfred & Co",
    "wof:placetype":"venue"
},
  "geometry": {"coordinates":[-79.8480834961,39.8919715881],"type":"Point"}
}