{
  "type": "Feature",
  "properties": {
    "iso:country":"AT",
    "sg:address":"Eisteichstr. 16",
    "sg:city":"Schwechat",
    "sg:classifiers":[
        {
            "category":"Parking",
            "subcategory":"Lot",
            "type":"Transportation"
        }
    ],
    "sg:phone":"+43 4317 0774750",
    "sg:postcode":"2320",
    "sg:province":"Nieder\u00f6sterreich",
    "sg:tags":[
        "transport",
        "road"
    ],
    "wof:name":"AUER INTERNATIONALE SPEDTION GMBH",
    "wof:placetype":"venue"
},
  "geometry": {"coordinates":[16.4856834412,48.1450538635],"type":"Point"}
}