{
  "type": "Feature",
  "properties": {
    "addr:full":"Puchegger Str 5 Regau Ober\u00f6sterreich 4844",
    "addr:housenumber":"5",
    "addr:postcode":"4844",
    "addr:street":"Str;Oberoesterreich",
    "iso:country":"AT",
    "sg:address":"Puchegger Str 5",
    "sg:city":"Regau",
    "sg:orig_category":"Autohandel",
    "sg:phone":"+43 4376 7228050",
    "sg:postcode":"4844",
    "sg:province":"Ober\u00f6sterreich",
    "wof:name":"Scheinecker Manfred GesmbH & Co KG",
    "wof:placetype":"venue"
},
  "geometry": {"coordinates":[13.6663551331,47.9996376038],"type":"Point"}
}