{
  "type": "Feature",
  "properties": {
    "addr:full":"Freimoosstr 22 Neumarkt in Steiermark Steiermark 8820",
    "addr:housenumber":"22",
    "addr:postcode":"8820",
    "addr:street":"Freimoosstr",
    "iso:country":"AT",
    "sg:address":"Freimoosstr 22",
    "sg:city":"Neumarkt in Steiermark",
    "sg:orig_category":"Rettungsdienste",
    "sg:phone":"+43 4335 8421440",
    "sg:postcode":"8820",
    "sg:province":"Steiermark",
    "wof:name":"Rotes Kreuz \u00f6sterreich Ortsstelle Neumarkt",
    "wof:placetype":"venue"
},
  "geometry": {"coordinates":[14.4307231903,47.0690078735],"type":"Point"}
}