{
  "type": "Feature",
  "properties": {
    "iso:country":"AT",
    "sg:address":"Pinnisweg 23",
    "sg:city":"Neustift im Stubaital",
    "sg:orig_category":"Pensionen / Privatzimmer",
    "sg:phone":"+43 4352 262382",
    "sg:postcode":"6167",
    "sg:province":"Tirol",
    "wof:name":"Gleirscher Ida",
    "wof:placetype":"venue"
},
  "geometry": {"coordinates":[11.3264970779,47.120262146],"type":"Point"}
}