{
  "type": "Feature",
  "properties": {
    "addr:full":"Loipersdorfer Str 7 F\u00fcrstenfeld Steiermark 8280",
    "addr:housenumber":"7",
    "addr:postcode":"8280",
    "addr:street":"Str",
    "iso:country":"AT",
    "sg:address":"Loipersdorfer Str 7",
    "sg:city":"F\u00fcrstenfeld",
    "sg:orig_category":"Autolackierereien",
    "sg:phone":"+43 4333 82528090",
    "sg:postcode":"8280",
    "sg:province":"Steiermark",
    "wof:name":"Mayer Philipp Mag GmbH & Co KG",
    "wof:placetype":"venue"
},
  "geometry": {"coordinates":[16.085319519,47.0341339111],"type":"Point"}
}