{
  "type": "Feature",
  "properties": {
    "iso:country":"AT",
    "sg:address":"Wei\u00dfenbachg 6",
    "sg:city":"Telfs",
    "sg:orig_category":"Einkaufszentren",
    "sg:phone":"+43 5262 63077",
    "sg:postcode":"6410",
    "sg:province":"Tirol",
    "wof:name":"Einkaufszentrum Telfs GmbH & Co KG - Inntalcenter Telfs",
    "wof:placetype":"venue"
},
  "geometry": {"coordinates":[11.072218895,47.3066978455],"type":"Point"}
}