{
  "type": "Feature",
  "properties": {
    "addr:full":"Oberregauer Str 25 Regau Ober\u00f6sterreich 4844",
    "addr:postcode":"4844",
    "addr:street":"Str 25",
    "iso:country":"AT",
    "sg:address":"Oberregauer Str 25",
    "sg:city":"Regau",
    "sg:orig_category":"Lohnfertigung",
    "sg:phone":"+43 767226252",
    "sg:postcode":"4844",
    "sg:province":"Ober\u00f6sterreich",
    "wof:name":"BBRZ - Berufliches Bildungs- und Rehabilitationszentrum Linz",
    "wof:placetype":"venue"
},
  "geometry": {"coordinates":[13.6557826996,47.9877510071],"type":"Point"}
}