{
  "type": "Feature",
  "properties": {
    "addr:full":"Sparkassenpl 1 Innsbruck Tirol 6020",
    "addr:housenumber":"1",
    "addr:postcode":"6020",
    "addr:street":"Sparkassenpl;Tirol",
    "iso:country":"AT",
    "sg:address":"Sparkassenpl 1",
    "sg:city":"Innsbruck",
    "sg:orig_category":"Immobilienverwaltungen",
    "sg:phone":"+43 512 59104214",
    "sg:postcode":"6020",
    "sg:province":"Tirol",
    "wof:name":"Sparkassen-Liegenschafts-Verwaltung GesmbH",
    "wof:placetype":"venue"
},
  "geometry": {"coordinates":[11.3950386047,47.2662124634],"type":"Point"}
}