{
  "type": "Feature",
  "properties": {
    "addr:full":"Dr M Sager-Str 4 Peggau Steiermark 8120",
    "addr:housenumber":"4",
    "addr:postcode":"8120",
    "iso:country":"AT",
    "sg:address":"Dr M Sager-Str 4",
    "sg:city":"Peggau",
    "sg:orig_category":"Fliesen U Platten",
    "sg:phone":"+43 3127 2389",
    "sg:postcode":"8120",
    "sg:province":"Steiermark",
    "wof:name":"M\u00fcller Andreas - REFIN Keramik",
    "wof:placetype":"venue"
},
  "geometry": {"coordinates":[15.3470640182,47.1988716125],"type":"Point"}
}