{
  "type": "Feature",
  "properties": {
    "addr:full":"Lehenweg 2 Rankweil Vorarlberg 6830",
    "addr:housenumber":"2",
    "addr:postcode":"6830",
    "addr:street":"Lehenweg",
    "iso:country":"AT",
    "sg:address":"Lehenweg 2",
    "sg:city":"Rankweil",
    "sg:orig_category":"Zahntechnische Laboratorien",
    "sg:phone":"+43 5522 42826",
    "sg:postcode":"6830",
    "sg:province":"Vorarlberg",
    "wof:name":"Crystal Art K\u00f6nig",
    "wof:placetype":"venue"
},
  "geometry": {"coordinates":[9.6237602234,47.2723121643],"type":"Point"}
}