{
  "type": "Feature",
  "properties": {
    "addr:full":"H\u00f6pflinger Weg 2-4 Mattighofen Ober\u00f6sterreich 5230",
    "addr:housenumber":"2-4",
    "addr:postcode":"5230",
    "addr:street":"Hoepflinger Weg",
    "iso:country":"AT",
    "sg:address":"H\u00f6pflinger Weg 2-4",
    "sg:city":"Mattighofen",
    "sg:classifiers":[
        {
            "category":"Recreation",
            "subcategory":"Fishing",
            "type":"Entertainment"
        }
    ],
    "sg:phone":"+43 7742 3450",
    "sg:postcode":"5230",
    "sg:province":"Ober\u00f6sterreich",
    "sg:tags":[
        "fish-breeding"
    ],
    "sg:website":"bachfischerei.at",
    "wof:name":"Mattigtaler Forellen & Seiblinge Bachfischerei Baumgartner",
    "wof:placetype":"venue"
},
  "geometry": {"coordinates":[13.1493988037,48.0945510864],"type":"Point"}
}