{
  "type": "Feature",
  "properties": {
    "iso:country":"AT",
    "sg:address":"Eduard-Klinger-Strasse 12",
    "sg:city":"St. Andr\u00e4-W\u00f6rdern",
    "sg:classifiers":[
        {
            "category":"Building & Trades",
            "subcategory":"Construction",
            "type":"Services"
        }
    ],
    "sg:phone":"+43 2242 333880",
    "sg:postcode":"3423",
    "sg:province":"Nieder\u00f6sterreich",
    "sg:tags":[
        "screw",
        "ball"
    ],
    "sg:website":"bibus-austria.com",
    "wof:name":"BIBUS Austria GmbH",
    "wof:placetype":"venue"
},
  "geometry": {"coordinates":[16.2101764679,48.3275222778],"type":"Point"}
}