{
  "type": "Feature",
  "properties": {
    "addr:full":"Laab 2 Andorf Ober\u00f6sterreich 4770",
    "addr:housenumber":"2",
    "addr:postcode":"4770",
    "addr:street":"Laab",
    "iso:country":"AT",
    "sg:address":"Laab 2",
    "sg:city":"Andorf",
    "sg:orig_category":"Autoreparatur",
    "sg:phone":"+43 7766 2961",
    "sg:postcode":"4770",
    "sg:province":"Ober\u00f6sterreich",
    "wof:name":"Leithner Felix",
    "wof:placetype":"venue"
},
  "geometry": {"coordinates":[13.5587377548,48.3526268005],"type":"Point"}
}