{
  "type": "Feature",
  "properties": {
    "iso:country":"AT",
    "sg:address":"Amberg",
    "sg:city":"Mining",
    "sg:orig_category":"Transportbeton",
    "sg:phone":"+43 7723 7213",
    "sg:postcode":"4962",
    "sg:province":"Ober\u00f6sterreich",
    "wof:name":"NIED Fertigbeton GesmbH",
    "wof:placetype":"venue"
},
  "geometry": {"coordinates":[13.1658706665,48.2673835754],"type":"Point"}
}