{
  "type": "Feature",
  "properties": {
    "addr:full":"Harrachg 30 Graz Steiermark 8010",
    "addr:housenumber":"30",
    "addr:postcode":"8010",
    "addr:street":"Harrachg",
    "iso:country":"AT",
    "sg:address":"Harrachg 30",
    "sg:city":"Graz",
    "sg:orig_category":"Ambulatorien",
    "sg:phone":"+43 316 321602",
    "sg:postcode":"8010",
    "sg:province":"Steiermark",
    "wof:name":"Ambulatorium f Langzeit - EKG und Blutdruckspeichermessung",
    "wof:placetype":"venue"
},
  "geometry": {"coordinates":[15.4480381012,47.0769805908],"type":"Point"}
}