{
  "type": "Feature",
  "properties": {
    "addr:full":"Weinheimerg 11 Wien Wien 1160",
    "addr:housenumber":"11",
    "addr:postcode":"1160",
    "addr:street":"Weinheimerg",
    "iso:country":"AT",
    "sg:address":"Weinheimerg 11",
    "sg:city":"Wien",
    "sg:orig_category":"Non-Classified Establishments",
    "sg:phone":"+43 1 4865194",
    "sg:postcode":"1160",
    "sg:province":"Wien",
    "wof:name":"TAXI-TEL Standplatztelefon Betriebs GmbH",
    "wof:placetype":"venue"
},
  "geometry": {"coordinates":[16.3100261688,48.2145385742],"type":"Point"}
}