{
  "type": "Feature",
  "properties": {
    "addr:full":"Bahnhofstr 2 Peuerbach Ober\u00f6sterreich 4722",
    "addr:housenumber":"2",
    "addr:postcode":"4722",
    "addr:street":"Bahnhofstr",
    "iso:country":"AT",
    "sg:address":"Bahnhofstr 2",
    "sg:city":"Peuerbach",
    "sg:orig_category":"Tabaktrafiken",
    "sg:phone":"+43 7276 3916",
    "sg:postcode":"4722",
    "sg:province":"Ober\u00f6sterreich",
    "wof:name":"Steininger Christine",
    "wof:placetype":"venue"
},
  "geometry": {"coordinates":[13.7723112106,48.3429527283],"type":"Point"}
}