{
  "type": "Feature",
  "properties": {
    "addr:full":"Haidinger Str 20 Buchkirchen Ober\u00f6sterreich 4611",
    "addr:postcode":"4611",
    "addr:street":"Str 20",
    "iso:country":"AT",
    "sg:address":"Haidinger Str 20",
    "sg:city":"Buchkirchen",
    "sg:orig_category":"Spirituosen / Erzeugung U Gro\u00c3\u0178handel",
    "sg:phone":"+43 4372 4228026",
    "sg:postcode":"4611",
    "sg:province":"Ober\u00f6sterreich",
    "wof:name":"Schosser Heidelbeergarten Destillerie",
    "wof:placetype":"venue"
},
  "geometry": {"coordinates":[14.0031795502,48.2100257874],"type":"Point"}
}