{
  "type": "Feature",
  "properties": {
    "addr:full":"Nr 81 Zederhaus Salzburg 5584",
    "addr:postcode":"5584",
    "addr:street":"Nr;Zederhaus",
    "iso:country":"AT",
    "sg:address":"Nr 81",
    "sg:city":"Zederhaus",
    "sg:orig_category":"Bankomat-Standorte",
    "sg:phone":"+43 6478 2080",
    "sg:postcode":"5584",
    "sg:province":"Salzburg",
    "wof:name":"Bankomat d Raiffeisenbank Zederhaus regGenmbH",
    "wof:placetype":"venue"
},
  "geometry": {"coordinates":[13.5075616837,47.1524772644],"type":"Point"}
}