{
  "type": "Feature",
  "properties": {
    "iso:country":"AT",
    "sg:address":"Am Berg 3",
    "sg:city":"Hirschegg",
    "sg:orig_category":"Appartements / Ferienwohnungen",
    "sg:phone":"+43 4355 175682",
    "sg:postcode":"6992",
    "sg:province":"Vorarlberg",
    "wof:name":"Ferienwohnung H\u00f6rmann",
    "wof:placetype":"venue"
},
  "geometry": {"coordinates":[10.1663284302,47.3434524536],"type":"Point"}
}