{
  "type": "Feature",
  "properties": {
    "iso:country":"AT",
    "sg:address":"Industriegel\u00e4nde 5 ",
    "sg:city":"Steinbrunn",
    "sg:classifiers":[
        {
            "category":"Shopping",
            "subcategory":"Clothing, Apparel, & Fashions",
            "type":"Retail Goods"
        }
    ],
    "sg:phone":"+43 4326 24523450",
    "sg:postcode":"7035",
    "sg:province":"Burgenland",
    "sg:tags":[
        "clothes"
    ],
    "wof:name":"BURG BEKLEIDUNGSGESMBH",
    "wof:placetype":"venue"
},
  "geometry": {"coordinates":[16.4131641388,47.8366889954],"type":"Point"}
}