{
  "type": "Feature",
  "properties": {
    "addr:full":"Industriestrasse 6 Kottingbrunn Nieder\u00f6sterreich 2542",
    "addr:housenumber":"6",
    "addr:postcode":"2542",
    "addr:street":"Industriestrasse",
    "iso:country":"AT",
    "sg:address":"Industriestrasse 6",
    "sg:city":"Kottingbrunn",
    "sg:classifiers":[
        {
            "category":"Structure",
            "subcategory":"Office Building",
            "type":"Public Place"
        }
    ],
    "sg:phone":"+43 2252 71585",
    "sg:postcode":"2542",
    "sg:province":"Nieder\u00f6sterreich",
    "sg:tags":[
        "plant",
        "window",
        "door",
        "aluminium",
        "manufacturing"
    ],
    "sg:website":"goeschl-metallbau.at",
    "wof:name":"G\u00f6schl Ges.m.b.H.",
    "wof:placetype":"venue"
},
  "geometry": {"coordinates":[16.220495224,47.9493904114],"type":"Point"}
}