{
  "type": "Feature",
  "properties": {
    "addr:full":"Thalgaustr 42 Mondsee Ober\u00f6sterreich 5310",
    "addr:housenumber":"42",
    "addr:postcode":"5310",
    "addr:street":"Thalgaustr;Oberoesterreich",
    "iso:country":"AT",
    "sg:address":"Thalgaustr 42",
    "sg:city":"Mondsee",
    "sg:orig_category":"Appartements / Ferienwohnungen",
    "sg:phone":"+43 6232 5108",
    "sg:postcode":"5310",
    "sg:province":"Ober\u00f6sterreich",
    "wof:name":"Ferienhof Hinterstrasser Fam Putz",
    "wof:placetype":"venue"
},
  "geometry": {"coordinates":[13.3248157501,47.8470726013],"type":"Point"}
}