{
  "type": "Feature",
  "properties": {
    "addr:full":"Langbathstr 30 Ebensee Ober\u00f6sterreich 4802",
    "addr:housenumber":"30",
    "addr:postcode":"4802",
    "addr:street":"Langbathstr",
    "iso:country":"AT",
    "sg:address":"Langbathstr 30",
    "sg:city":"Ebensee",
    "sg:orig_category":"Messe- U Ausstellungsbau U -Gestaltung",
    "sg:phone":"+43 4361 334329",
    "sg:postcode":"4802",
    "sg:province":"Ober\u00f6sterreich",
    "wof:name":"Lahnsteiner Michael Ing Event Systems",
    "wof:placetype":"venue"
},
  "geometry": {"coordinates":[13.6744604111,47.8341178894],"type":"Point"}
}