{
  "type": "Feature",
  "properties": {
    "iso:country":"AT",
    "sg:address":"Rauth 136",
    "sg:city":"Stanzach",
    "sg:orig_category":"Holzhandel",
    "sg:phone":"+43 5632 201",
    "sg:postcode":"6642",
    "sg:province":"Tirol",
    "wof:name":"Fuchs Helmut",
    "wof:placetype":"venue"
},
  "geometry": {"coordinates":[10.5403499603,47.3699111938],"type":"Point"}
}