{
  "type": "Feature",
  "properties": {
    "addr:full":"Jahnstr 5 Herzogenburg Nieder\u00f6sterreich 3130",
    "addr:housenumber":"5",
    "addr:postcode":"3130",
    "addr:street":"Jahnstr",
    "iso:country":"AT",
    "sg:address":"Jahnstr 5",
    "sg:city":"Herzogenburg",
    "sg:orig_category":"Maler, Anstreicher U Lackierer",
    "sg:phone":"+43 4327 8285772",
    "sg:postcode":"3130",
    "sg:province":"Nieder\u00f6sterreich",
    "wof:name":"Haselmann Friedrich",
    "wof:placetype":"venue"
},
  "geometry": {"coordinates":[15.6915512085,48.2884368896],"type":"Point"}
}