{
  "type": "Feature",
  "properties": {
    "iso:country":"AT",
    "sg:address":"Hauptstr 77",
    "sg:city":"Oberpullendorf",
    "sg:orig_category":"Autoersatzteile",
    "sg:phone":"+43 2612 45808",
    "sg:postcode":"7350",
    "sg:province":"Burgenland",
    "wof:name":"Edelschmiede - Schl\u00f6gl Eduard KEG",
    "wof:placetype":"venue"
},
  "geometry": {"coordinates":[16.507434845,47.4969863892],"type":"Point"}
}