{
  "type": "Feature",
  "properties": {
    "iso:country":"AT",
    "sg:address":"Waidhofner Str 43",
    "sg:city":"Rosenau",
    "sg:orig_category":"Apotheken",
    "sg:phone":"+43 4374 4825250",
    "sg:postcode":"3332",
    "sg:province":"Nieder\u00f6sterreich",
    "wof:name":"Apotheke u Drogerie Rosenau Mag pharm Rapatz OHG",
    "wof:placetype":"venue"
},
  "geometry": {"coordinates":[14.732260704,48.0170059204],"type":"Point"}
}