{
  "type": "Feature",
  "properties": {
    "addr:full":"Dr.-Karl-Lueger-Pl 2 Wien Wien 1010",
    "addr:housenumber":"2",
    "addr:postcode":"1010",
    "addr:street":"Dr.-Karl-Lueger-Pl",
    "iso:country":"AT",
    "sg:address":"Dr.-Karl-Lueger-Pl 2",
    "sg:city":"Wien",
    "sg:orig_category":"Eissalons",
    "sg:phone":"+43 1 5132145",
    "sg:postcode":"1010",
    "sg:province":"Wien",
    "wof:name":"Perrella",
    "wof:placetype":"venue"
},
  "geometry": {"coordinates":[16.3609142303,48.2103614807],"type":"Point"}
}