{
  "type": "Feature",
  "properties": {
    "addr:full":"Nr 35 St. Nikolai ob Dra\u00dfling Steiermark 8422",
    "addr:postcode":"8422",
    "addr:street":"Nr 35",
    "iso:country":"AT",
    "sg:address":"Nr 35",
    "sg:city":"St. Nikolai ob Dra\u00dfling",
    "sg:orig_category":"Pensionen / Privatzimmer",
    "sg:phone":"+43 4331 842789",
    "sg:postcode":"8422",
    "sg:province":"Steiermark",
    "wof:name":"Neuhold Anna u Josef",
    "wof:placetype":"venue"
},
  "geometry": {"coordinates":[15.6606082916,46.8158721924],"type":"Point"}
}