{
  "type": "Feature",
  "properties": {
    "iso:country":"AT",
    "sg:address":"Andergasse 12a",
    "sg:city":"Wien",
    "sg:classifiers":[
        {
            "category":"Professional",
            "subcategory":"Credit Reporting & Collection",
            "type":"Services"
        }
    ],
    "sg:phone":"+43 1 4844964",
    "sg:postcode":"1170",
    "sg:province":"Wien",
    "sg:tags":[
        "processing",
        "data"
    ],
    "sg:website":"vienna.co",
    "wof:name":"Internet - Dienstleistungs Ges.m.b.H.",
    "wof:placetype":"venue"
},
  "geometry": {"coordinates":[16.2967529297,48.2278251648],"type":"Point"}
}