{
  "type": "Feature",
  "properties": {
    "iso:country":"AT",
    "sg:address":"Hauptstr 30",
    "sg:city":"Ebensee",
    "sg:orig_category":"Fahrradreparatur",
    "sg:phone":"+43 6133 6187",
    "sg:postcode":"4802",
    "sg:province":"Ober\u00f6sterreich",
    "wof:name":"Drahteselklinik - Fahrrad-Reparatur und Fachhandel",
    "wof:placetype":"venue"
},
  "geometry": {"coordinates":[13.7732582092,47.8116798401],"type":"Point"}
}