{
  "type": "Feature",
  "properties": {
    "iso:country":"AT",
    "sg:address":"Unterer Markt 13",
    "sg:city":"Gresten",
    "sg:orig_category":"Holzgro\u00c3\u0178handel",
    "sg:phone":"+43 7487 4000",
    "sg:postcode":"3264",
    "sg:province":"Nieder\u00f6sterreich",
    "wof:name":"Hubegger Leopold GesmbH",
    "wof:placetype":"venue"
},
  "geometry": {"coordinates":[15.0261077881,47.9835243225],"type":"Point"}
}