{
  "type": "Feature",
  "properties": {
    "addr:full":"Wienerbergstr 11 Wien Wien 1100",
    "addr:housenumber":"11",
    "addr:postcode":"1100",
    "addr:street":"Wienerbergstr",
    "iso:country":"AT",
    "sg:address":"Wienerbergstr 11",
    "sg:city":"Wien",
    "sg:classifiers":[
        {
            "category":"Restaurant",
            "type":"Food & Drink"
        }
    ],
    "sg:phone":"+43 4319 181717",
    "sg:postcode":"1100",
    "sg:province":"Wien",
    "wof:name":"M\u00fcller Br\u00e4u im Twinpark - Bierlokal",
    "wof:placetype":"venue"
},
  "geometry": {"coordinates":[16.344953537,48.168094635],"type":"Point"}
}