{
  "type": "Feature",
  "properties": {
    "addr:full":"Hans-Scheiber-Str 4 Wolfsberg K\u00e4rnten 9400",
    "addr:housenumber":"4;kaernten",
    "addr:postcode":"9400",
    "addr:street":"Hans-Scheiber-Str",
    "iso:country":"AT",
    "sg:address":"Hans-Scheiber-Str 4",
    "sg:city":"Wolfsberg",
    "sg:orig_category":"Sonderschulen",
    "sg:phone":"+43 4352 30464450",
    "sg:postcode":"9400",
    "sg:province":"K\u00e4rnten",
    "wof:name":"Allgemeine Sonderschule",
    "wof:placetype":"venue"
},
  "geometry": {"coordinates":[14.8420124054,46.8340644836],"type":"Point"}
}