{
  "type": "Feature",
  "properties": {
    "addr:full":"Speckbacherstr 33a St. Johann in Tirol Tirol 6380",
    "addr:housenumber":"33a",
    "addr:postcode":"johann;6380",
    "addr:street":"Speckbacherstr;Tirol",
    "iso:country":"AT",
    "sg:address":"Speckbacherstr 33a",
    "sg:city":"St. Johann in Tirol",
    "sg:orig_category":"Ballonfahrten",
    "sg:phone":"+43 4353 5265666",
    "sg:postcode":"6380",
    "sg:province":"Tirol",
    "sg:website":"ballooningtyrol.com",
    "wof:name":"Ballooning Tyrol Ballonfahrten u Freizeitaktivit\u00e4ten GesmbH",
    "wof:placetype":"venue"
},
  "geometry": {"coordinates":[12.4256362915,47.5201187134],"type":"Point"}
}