{
  "type": "Feature",
  "properties": {
    "iso:country":"AT",
    "sg:address":"Linzer Strasse 145",
    "sg:city":"Wels",
    "sg:orig_category":"Bathing Gratings",
    "sg:phone":"+43 7242 61729",
    "sg:postcode":"4600",
    "sg:province":"Ober\u00f6sterreich",
    "wof:name":"Ruth Moser GmbH & Co KG",
    "wof:placetype":"venue"
},
  "geometry": {"coordinates":[14.0475282669,48.1676864624],"type":"Point"}
}