{
  "type": "Feature",
  "properties": {
    "addr:full":"Gentzg 36 Wien Wien 1180",
    "addr:housenumber":"36",
    "addr:postcode":"1180",
    "addr:street":"Gentzg",
    "iso:country":"AT",
    "sg:address":"Gentzg 36",
    "sg:city":"Wien",
    "sg:orig_category":"Farben U Lacke / Einzelhandel",
    "sg:phone":"+43 1 4796656",
    "sg:postcode":"1180",
    "sg:province":"Wien",
    "wof:name":"Kreiter-Trampitsch Gabriele Gabriele",
    "wof:placetype":"venue"
},
  "geometry": {"coordinates":[16.3435096741,48.2270698547],"type":"Point"}
}