{
  "type": "Feature",
  "properties": {
    "iso:country":"AT",
    "sg:address":"Wildentalstr 3",
    "sg:city":"Mittelberg",
    "sg:classifiers":[
        {
            "category":"Travel",
            "subcategory":"Hotels & Motels",
            "type":"Entertainment"
        }
    ],
    "sg:phone":"+43 4355 1765110",
    "sg:postcode":"6993",
    "sg:province":"Vorarlberg",
    "wof:name":"Aparthotel Kleinwalsertal",
    "wof:placetype":"venue"
},
  "geometry": {"coordinates":[10.152089119,47.318145752],"type":"Point"}
}