{
  "type": "Feature",
  "properties": {
    "addr:full":"Villacher Bundesstr 100 Radenthein K\u00e4rnten 9545",
    "addr:housenumber":"100",
    "addr:postcode":"9545",
    "addr:street":"Radenthein Kaernten",
    "iso:country":"AT",
    "sg:address":"Villacher Bundesstr 100",
    "sg:city":"Radenthein",
    "sg:orig_category":"Autohandel",
    "sg:phone":"+43 4246 2094",
    "sg:postcode":"9545",
    "sg:province":"K\u00e4rnten",
    "wof:name":"Staber Autohaus GesmbH & Co KG",
    "wof:placetype":"venue"
},
  "geometry": {"coordinates":[13.7050790787,46.8011779785],"type":"Point"}
}