{
  "type": "Feature",
  "properties": {
    "addr:full":"Leobner Str 44 Bruck an der Mur Steiermark 8600",
    "addr:postcode":"8600",
    "addr:street":"Str 44",
    "iso:country":"AT",
    "sg:address":"Leobner Str 44",
    "sg:city":"Bruck an der Mur",
    "sg:orig_category":"Tankstellen",
    "sg:phone":"+43 3862 52781",
    "sg:postcode":"8600",
    "sg:province":"Steiermark",
    "wof:name":"Shell Austria GmbH",
    "wof:placetype":"venue"
},
  "geometry": {"coordinates":[15.2528610229,47.4040908813],"type":"Point"}
}