{
  "type": "Feature",
  "properties": {
    "iso:country":"AT",
    "sg:address":"Kirchenpl 11",
    "sg:city":"Markt St. Martin",
    "sg:orig_category":"Volksschulen",
    "sg:phone":"+43 2618 2440",
    "sg:postcode":"7341",
    "sg:province":"Burgenland",
    "wof:name":"Volksschule",
    "wof:placetype":"venue"
},
  "geometry": {"coordinates":[16.4277458191,47.5640830994],"type":"Point"}
}