{
  "type": "Feature",
  "properties": {
    "addr:full":"Jochberger Str 21 Kitzb\u00fchel Tirol 6370",
    "addr:postcode":"6370",
    "addr:street":"Str 21 Kitzbuehel Tirol",
    "iso:country":"AT",
    "sg:address":"Jochberger Str 21",
    "sg:city":"Kitzb\u00fchel",
    "sg:orig_category":"Werbeagenturen",
    "sg:phone":"+43 5356 71333",
    "sg:postcode":"6370",
    "sg:province":"Tirol",
    "wof:name":"GCA-Agentur f Markenwerbung GesmbH",
    "wof:placetype":"venue"
},
  "geometry": {"coordinates":[12.3973169327,47.4440879822],"type":"Point"}
}