{
  "type": "Feature",
  "properties": {
    "addr:full":"Schottenfeldg 3/26 Wien Wien 1070",
    "addr:housenumber":"3 / 26",
    "addr:postcode":"1070",
    "addr:street":"Schottenfeldg",
    "iso:country":"AT",
    "sg:address":"Schottenfeldg 3/26",
    "sg:city":"Wien",
    "sg:classifiers":[
        {
            "category":"Professional",
            "subcategory":"Computer Services",
            "type":"Services"
        }
    ],
    "sg:phone":"+43 1 27490400",
    "sg:postcode":"1070",
    "sg:province":"Wien",
    "sg:tags":[
        "software"
    ],
    "wof:name":"Frango GmbH",
    "wof:placetype":"venue"
},
  "geometry": {"coordinates":[16.3438873291,48.1970787048],"type":"Point"}
}