{
  "type": "Feature",
  "properties": {
    "addr:full":"Thayagraben 58 St. Lambrecht Steiermark 8813",
    "addr:housenumber":"58",
    "addr:postcode":"8813",
    "addr:street":"Thayagraben",
    "iso:country":"AT",
    "sg:address":"Thayagraben 58",
    "sg:city":"St. Lambrecht",
    "sg:orig_category":"Fenster",
    "sg:phone":"+43 3585 56797",
    "sg:postcode":"8813",
    "sg:province":"Steiermark",
    "wof:name":"ECE Holz/Alu-Fenstersysteme GmbH",
    "wof:placetype":"venue"
},
  "geometry": {"coordinates":[14.3215875626,47.0944747925],"type":"Point"}
}