{
  "type": "Feature",
  "properties": {
    "addr:full":"Rechte Ennsau 403 Schladming Steiermark 8970",
    "addr:housenumber":"403",
    "addr:postcode":"8970",
    "iso:country":"AT",
    "sg:address":"Rechte Ennsau 403",
    "sg:city":"Schladming",
    "sg:classifiers":[
        {
            "category":"Home & Garden",
            "subcategory":"Carpets & Floor Coverings",
            "type":"Retail Goods"
        }
    ],
    "sg:phone":"+43 3687 23236",
    "sg:postcode":"8970",
    "sg:province":"Steiermark",
    "sg:tags":[
        "screed",
        "floating"
    ],
    "sg:website":"kreativ-estrich.at",
    "wof:name":"Schrempf Estrichverlegung KEG",
    "wof:placetype":"venue"
},
  "geometry": {"coordinates":[13.6958904266,47.3978500366],"type":"Point"}
}