{
  "type": "Feature",
  "properties": {
    "addr:full":"Bahnhofstr 22 Bischofshofen Salzburg 5500",
    "addr:housenumber":"22",
    "addr:postcode":"5500",
    "addr:street":"Bahnhofstr;Salzburg",
    "iso:country":"AT",
    "sg:address":"Bahnhofstr 22",
    "sg:city":"Bischofshofen",
    "sg:orig_category":"Immobilienverwaltungen",
    "sg:phone":"+43 6462 33170",
    "sg:postcode":"5500",
    "sg:province":"Salzburg",
    "wof:name":"Arzb\u00f6ck Immobilien-Treuh\u00e4nder, Hausverwaltung",
    "wof:placetype":"venue"
},
  "geometry": {"coordinates":[13.218791008,47.4167861938],"type":"Point"}
}