{
  "type": "Feature",
  "properties": {
    "addr:full":"Olsaring 18 Friesach K\u00e4rnten 9360",
    "addr:housenumber":"18",
    "addr:postcode":"9360",
    "addr:street":"Olsaring;Kaernten",
    "iso:country":"AT",
    "sg:address":"Olsaring 18",
    "sg:city":"Friesach",
    "sg:orig_category":"Dekorationen",
    "sg:phone":"+43 4268 4129",
    "sg:postcode":"9360",
    "sg:province":"K\u00e4rnten",
    "wof:name":"Lehnert Rudolf",
    "wof:placetype":"venue"
},
  "geometry": {"coordinates":[14.4214954376,46.9509162903],"type":"Point"}
}