{
  "type": "Feature",
  "properties": {
    "iso:country":"AT",
    "sg:address":"Venusweg 21",
    "sg:city":"Wien",
    "sg:orig_category":"Gerichtsdolmetscher",
    "sg:phone":"+43 1 9795610",
    "sg:postcode":"1140",
    "sg:province":"Wien",
    "wof:name":"St\u00f6ckl\u00f6cker Silvia Dipl-Dolm",
    "wof:placetype":"venue"
},
  "geometry": {"coordinates":[16.2505073547,48.2088851929],"type":"Point"}
}