{
  "type": "Feature",
  "properties": {
    "addr:full":"Lonstorfer Weg 9 Linz Ober\u00f6sterreich 4020",
    "addr:housenumber":"9",
    "addr:postcode":"4020",
    "addr:street":"Lonstorfer Weg",
    "iso:country":"AT",
    "sg:address":"Lonstorfer Weg 9",
    "sg:city":"Linz",
    "sg:orig_category":"Pensionen / Privatzimmer, Hotels",
    "sg:phone":"+43 732 675490",
    "sg:postcode":"4020",
    "sg:province":"Ober\u00f6sterreich",
    "wof:name":"G\u00e4stehaus Alexandra",
    "wof:placetype":"venue"
},
  "geometry": {"coordinates":[14.3149499893,48.294757843],"type":"Point"}
}