{
  "type": "Feature",
  "properties": {
    "addr:full":"Wiener Strasse 23 Neunkirchen Nieder\u00f6sterreich 2620",
    "addr:housenumber":"23",
    "addr:postcode":"2620",
    "addr:street":"Wiener Strasse",
    "iso:country":"AT",
    "sg:address":"Wiener Strasse 23",
    "sg:city":"Neunkirchen",
    "sg:classifiers":[
        {
            "category":"Building & Trades",
            "subcategory":"Electrical",
            "type":"Services"
        }
    ],
    "sg:phone":"+43 2635 62482",
    "sg:postcode":"2620",
    "sg:province":"Nieder\u00f6sterreich",
    "sg:tags":[
        "installation"
    ],
    "sg:website":"elektrohaus.neunkirchen.at",
    "wof:name":"Elektroinstallationsbetrieb der Stadtgemeinde Neunkirchen",
    "wof:placetype":"venue"
},
  "geometry": {"coordinates":[16.0805854797,47.7246780396],"type":"Point"}
}