{
  "type": "Feature",
  "properties": {
    "addr:full":"null Postfach/136 1071",
    "addr:postcode":"1071",
    "iso:country":"AT",
    "sg:address":"null Postfach/136",
    "sg:classifiers":[
        {
            "category":"Professional",
            "subcategory":"Management & Consulting",
            "type":"Services"
        }
    ],
    "sg:phone":"+43 4315 2676590",
    "sg:postcode":"1071",
    "wof:name":"Management Forum",
    "wof:placetype":"venue"
},
  "geometry": {"coordinates":[16.3489398956,48.2022285461],"type":"Point"}
}