{
  "type": "Feature",
  "properties": {
    "addr:full":"Seestr 4 und 6 Seeboden K\u00e4rnten 9871",
    "addr:housenumber":"4 und 6",
    "addr:postcode":"9871",
    "addr:street":"Seestr;Kaernten",
    "iso:country":"AT",
    "sg:address":"Seestr 4 und 6",
    "sg:city":"Seeboden",
    "sg:orig_category":"Appartements / Ferienwohnungen",
    "sg:phone":"+43 4762 816720",
    "sg:postcode":"9871",
    "sg:province":"K\u00e4rnten",
    "wof:name":"Haus Kampitsch",
    "wof:placetype":"venue"
},
  "geometry": {"coordinates":[13.5192050934,46.8188858032],"type":"Point"}
}