{
  "type": "Feature",
  "properties": {
    "iso:country":"AT",
    "sg:address":"Globasnitz 36",
    "sg:city":"Globasnitz",
    "sg:classifiers":[
        {
            "category":"Manufacturing",
            "subcategory":"Wood Products",
            "type":"Manufacturing & Wholesale Goods"
        }
    ],
    "sg:phone":"+43 4230 633",
    "sg:postcode":"9142",
    "sg:province":"K\u00e4rnten",
    "sg:tags":[
        "made",
        "balcony"
    ],
    "wof:name":"Holzbau Smretschnig GmbH",
    "wof:placetype":"venue"
},
  "geometry": {"coordinates":[14.7004308701,46.5574684143],"type":"Point"}
}