{
  "type": "Feature",
  "properties": {
    "addr:full":"Am Rofen 43 Imst Tirol 6460",
    "addr:housenumber":"43",
    "addr:postcode":"6460",
    "addr:street":"Am Rofen;Tirol",
    "iso:country":"AT",
    "sg:address":"Am Rofen 43",
    "sg:city":"Imst",
    "sg:orig_category":"Landwirtschaftliche Produkte",
    "sg:phone":"+43 5412 66642",
    "sg:postcode":"6460",
    "sg:province":"Tirol",
    "wof:name":"Neururer Roswitha",
    "wof:placetype":"venue"
},
  "geometry": {"coordinates":[10.7501926422,47.2380943298],"type":"Point"}
}