{
  "type": "Feature",
  "properties": {
    "addr:full":"Grabeng 4 Hermagor K\u00e4rnten 9620",
    "addr:housenumber":"4",
    "addr:postcode":"9620",
    "addr:street":"Grabeng;Kaernten",
    "iso:country":"AT",
    "sg:address":"Grabeng 4",
    "sg:city":"Hermagor",
    "sg:orig_category":"Arbeitsvermittlung",
    "sg:phone":"+43 4282 20610",
    "sg:postcode":"9620",
    "sg:province":"K\u00e4rnten",
    "wof:name":"Arbeitsmarktservice Hermagor",
    "wof:placetype":"venue"
},
  "geometry": {"coordinates":[13.3657979965,46.6281585693],"type":"Point"}
}