{
  "type": "Feature",
  "properties": {
    "addr:full":"Elisabethstr 52 Graz Steiermark 8010",
    "addr:housenumber":"52",
    "addr:postcode":"8010",
    "addr:street":"Elisabethstr",
    "iso:country":"AT",
    "sg:address":"Elisabethstr 52",
    "sg:city":"Graz",
    "sg:orig_category":"Architekten",
    "sg:phone":"+43 316 3275750",
    "sg:postcode":"8010",
    "sg:province":"Steiermark",
    "wof:name":"Architekturb\u00fcro Szyszkowitz + Kowalski",
    "wof:placetype":"venue"
},
  "geometry": {"coordinates":[15.4557228088,47.0759048462],"type":"Point"}
}