{
  "type": "Feature",
  "properties": {
    "iso:country":"AT",
    "sg:address":"Florianig 40",
    "sg:city":"Wien",
    "sg:orig_category":"Maler, Anstreicher U Lackierer",
    "sg:phone":"+43 1 5977777",
    "sg:postcode":"1080",
    "sg:province":"Wien",
    "wof:name":"Krinninger Erich",
    "wof:placetype":"venue"
},
  "geometry": {"coordinates":[16.3476657867,48.2122039795],"type":"Point"}
}