{
  "type": "Feature",
  "properties": {
    "addr:full":"Klagenfurter Str 17 Wolfsberg K\u00e4rnten 9400",
    "addr:housenumber":"17;kaernten",
    "addr:postcode":"9400",
    "addr:street":"Str",
    "iso:country":"AT",
    "sg:address":"Klagenfurter Str 17",
    "sg:city":"Wolfsberg",
    "sg:orig_category":"Schneidereien",
    "sg:phone":"+43 4352 46806",
    "sg:postcode":"9400",
    "sg:province":"K\u00e4rnten",
    "wof:name":"Kurz Bettina",
    "wof:placetype":"venue"
},
  "geometry": {"coordinates":[14.8395729065,46.827911377],"type":"Point"}
}