{
  "type": "Feature",
  "properties": {
    "addr:full":"Deimledt 3 Pischelsdorf am Engelbach Ober\u00f6sterreich 5233",
    "addr:housenumber":"3",
    "addr:postcode":"5233",
    "addr:street":"Deimledt",
    "iso:country":"AT",
    "sg:address":"Deimledt 3",
    "sg:city":"Pischelsdorf am Engelbach",
    "sg:orig_category":"Autovermietung",
    "sg:phone":"+43 7742 7100",
    "sg:postcode":"5233",
    "sg:province":"Ober\u00f6sterreich",
    "wof:name":"K\u00fccher Josef",
    "wof:placetype":"venue"
},
  "geometry": {"coordinates":[13.0910606384,48.1376647949],"type":"Point"}
}