{
  "type": "Feature",
  "properties": {
    "addr:full":"Garteng 5 Feldbach Steiermark 8330",
    "addr:housenumber":"5",
    "addr:postcode":"8330",
    "addr:street":"Garteng",
    "iso:country":"AT",
    "sg:address":"Garteng 5",
    "sg:city":"Feldbach",
    "sg:orig_category":"Massagen",
    "sg:phone":"+43 3152 5140",
    "sg:postcode":"8330",
    "sg:province":"Steiermark",
    "wof:name":"Massageinstitut Maria",
    "wof:placetype":"venue"
},
  "geometry": {"coordinates":[15.8557338715,46.9628982544],"type":"Point"}
}