{
  "type": "Feature",
  "properties": {
    "iso:country":"AT",
    "sg:address":"Bahnstr 24A",
    "sg:city":"Mistelbach",
    "sg:orig_category":"Bauunternehmen",
    "sg:phone":"+43 2572 32454",
    "sg:postcode":"2130",
    "sg:province":"Nieder\u00f6sterreich",
    "wof:name":"VFS bau CRNOVRSANIN KEG",
    "wof:placetype":"venue"
},
  "geometry": {"coordinates":[16.5690994263,48.5722084045],"type":"Point"}
}