{
  "type": "Feature",
  "properties": {
    "iso:country":"AT",
    "sg:address":"Andritzer Reichsstr 18",
    "sg:city":"Andritz",
    "sg:orig_category":"Werbeagenturen",
    "sg:phone":"+43 316 6826960",
    "sg:postcode":"8045",
    "sg:province":"Steiermark",
    "sg:website":"www.design-q.at",
    "wof:name":"Design Q - Werbeagentur GmbH",
    "wof:placetype":"venue"
},
  "geometry": {"coordinates":[15.4249839783,47.1002540588],"type":"Point"}
}