{
  "type": "Feature",
  "properties": {
    "addr:full":"Lehargasse 7 Graz Steiermark 8010",
    "addr:housenumber":"7",
    "addr:postcode":"8010",
    "addr:street":"Lehargasse",
    "iso:country":"AT",
    "sg:address":"Lehargasse 7",
    "sg:city":"Graz",
    "sg:classifiers":[
        {
            "category":"Organizations",
            "subcategory":"Labor Organization",
            "type":"Services"
        }
    ],
    "sg:phone":"+43 316 677904",
    "sg:postcode":"8010",
    "sg:province":"Steiermark",
    "sg:tags":[
        "on-site",
        "waste-water",
        "treatment",
        "system"
    ],
    "sg:website":"galle-abwasser.at",
    "wof:name":"Baumeister Ing. Klaus Gall\u00e9 GmbH & Co KG",
    "wof:placetype":"venue"
},
  "geometry": {"coordinates":[15.430439949,47.0896606445],"type":"Point"}
}