{
  "type": "Feature",
  "properties": {
    "iso:country":"AT",
    "sg:address":"Stadlwg. 13 ",
    "sg:city":"Innsbruck",
    "sg:classifiers":[
        {
            "category":"Shopping",
            "subcategory":"Crafts & Fabrics",
            "type":"Retail Goods"
        }
    ],
    "sg:phone":"+43 4351 2364444",
    "sg:postcode":"6020",
    "sg:province":"Tirol",
    "sg:tags":[
        "ceramic"
    ],
    "wof:name":"FLIESEN CENTER TIROL GMBH & CO. KG",
    "wof:placetype":"venue"
},
  "geometry": {"coordinates":[11.4287605286,47.2674751282],"type":"Point"}
}