{
  "type": "Feature",
  "properties": {
    "addr:full":"Hauptstr 39 G\u00f6ttlesbrunn Nieder\u00f6sterreich 2464",
    "addr:housenumber":"39;2464",
    "addr:street":"Hauptstr;Niederoesterreich",
    "iso:country":"AT",
    "sg:address":"Hauptstr 39",
    "sg:city":"G\u00f6ttlesbrunn",
    "sg:orig_category":"Pensionen / Privatzimmer",
    "sg:phone":"+43 4321 628822",
    "sg:postcode":"2464",
    "sg:province":"Nieder\u00f6sterreich",
    "wof:name":"G\u00e4stehaus Rosenhof",
    "wof:placetype":"venue"
},
  "geometry": {"coordinates":[16.705783844,48.0668106079],"type":"Point"}
}