{
  "type": "Feature",
  "properties": {
    "addr:full":"Bichlstr 14 Kitzb\u00fchel Tirol 6370",
    "addr:housenumber":"14",
    "addr:postcode":"6370",
    "addr:street":"Bichlstr;Tirol",
    "iso:country":"AT",
    "sg:address":"Bichlstr 14",
    "sg:city":"Kitzb\u00fchel",
    "sg:orig_category":"Fleischhauereien",
    "sg:phone":"+43 5356 624800",
    "sg:postcode":"6370",
    "sg:province":"Tirol",
    "sg:website":"www.tirolspeck.com",
    "wof:name":"Huber Josef",
    "wof:placetype":"venue"
},
  "geometry": {"coordinates":[12.3923492432,47.4449234009],"type":"Point"}
}