{
  "type": "Feature",
  "properties": {
    "addr:full":"Quellenstr 36 Wien Wien 1100",
    "addr:housenumber":"36",
    "addr:postcode":"1100",
    "addr:street":"Quellenstr",
    "iso:country":"AT",
    "sg:address":"Quellenstr 36",
    "sg:city":"Wien",
    "sg:orig_category":"Tabaktrafiken",
    "sg:phone":"+43 1 6046522",
    "sg:postcode":"1100",
    "sg:province":"Wien",
    "wof:name":"Hora Gerlinde",
    "wof:placetype":"venue"
},
  "geometry": {"coordinates":[16.3818302155,48.1752052307],"type":"Point"}
}