{
  "type": "Feature",
  "properties": {
    "addr:full":"Nr 123 Wolfsbach Nieder\u00f6sterreich 3354",
    "addr:postcode":"3354",
    "addr:street":"Nr 123",
    "iso:country":"AT",
    "sg:address":"Nr 123",
    "sg:city":"Wolfsbach",
    "sg:orig_category":"Zahntechnische Laboratorien",
    "sg:phone":"+43 7477 82510",
    "sg:postcode":"3354",
    "sg:province":"Nieder\u00f6sterreich",
    "wof:name":"Dens-Lab Inh Franz Gugler",
    "wof:placetype":"venue"
},
  "geometry": {"coordinates":[14.6686410904,48.0791740417],"type":"Point"}
}