{
  "type": "Feature",
  "properties": {
    "iso:country":"AT",
    "sg:address":"J\u00e4gerstr 6",
    "sg:city":"Wien",
    "sg:orig_category":"Elektroinstallationsunternehmen",
    "sg:phone":"+43 1 3509555",
    "sg:postcode":"1200",
    "sg:province":"Wien",
    "wof:name":"Elektro Schneider Inh Auguste Schneider Nfg Hans Peter Pak",
    "wof:placetype":"venue"
},
  "geometry": {"coordinates":[16.370508194,48.2270851135],"type":"Point"}
}