{
  "type": "Feature",
  "properties": {
    "iso:country":"AT",
    "sg:address":"Wiener Str 17a",
    "sg:city":"Wulkaprodersdorf",
    "sg:orig_category":"Bestattungsunternehmen",
    "sg:phone":"+43 2687 62257",
    "sg:postcode":"7041",
    "sg:province":"Burgenland",
    "wof:name":"Ivancsits Rudolf",
    "wof:placetype":"venue"
},
  "geometry": {"coordinates":[16.5063362122,47.7987747192],"type":"Point"}
}