{
  "type": "Feature",
  "properties": {
    "addr:full":"Niederhart 111 F\u00fcgen Tirol 6263",
    "addr:housenumber":"111",
    "addr:postcode":"6263",
    "addr:street":"Niederhart;Tirol",
    "iso:country":"AT",
    "sg:address":"Niederhart 111",
    "sg:city":"F\u00fcgen",
    "sg:orig_category":"Installationsunternehmen",
    "sg:phone":"+43 5288 63931",
    "sg:postcode":"6263",
    "sg:province":"Tirol",
    "wof:name":"Installationstechnik Falkner & Eberharter OEG",
    "wof:placetype":"venue"
},
  "geometry": {"coordinates":[11.8686199188,47.3540496826],"type":"Point"}
}