{
  "type": "Feature",
  "properties": {
    "addr:full":"Pasettistrasse 78 Wien Wien 1200",
    "addr:housenumber":"78",
    "addr:postcode":"1200",
    "addr:street":"Pasettistrasse",
    "iso:country":"AT",
    "sg:address":"Pasettistrasse 78",
    "sg:city":"Wien",
    "sg:classifiers":[
        {
            "category":"Utilities",
            "subcategory":"Cable",
            "type":"Services"
        }
    ],
    "sg:phone":"+43 1 33068270",
    "sg:postcode":"1200",
    "sg:province":"Wien",
    "sg:tags":[
        "ready",
        "use",
        "cables",
        "finished"
    ],
    "sg:website":"fastech.at",
    "wof:name":"FASTECH Kommunikationseinrichtungen GmbH",
    "wof:placetype":"venue"
},
  "geometry": {"coordinates":[16.386636734,48.2329788208],"type":"Point"}
}