{
  "type": "Feature",
  "properties": {
    "addr:full":"O Kernstock-Str 10 St. Lorenzen im M\u00fcrztal Steiermark 8642",
    "addr:housenumber":"10",
    "addr:postcode":"8642",
    "iso:country":"AT",
    "sg:address":"O Kernstock-Str 10",
    "sg:city":"St. Lorenzen im M\u00fcrztal",
    "sg:orig_category":"Tischlereien",
    "sg:phone":"+43 3864 22230",
    "sg:postcode":"8642",
    "sg:province":"Steiermark",
    "wof:name":"Holz + Wohnen Bruno K\u00f6ck KG",
    "wof:placetype":"venue"
},
  "geometry": {"coordinates":[15.3703804016,47.4826202393],"type":"Point"}
}