{
  "type": "Feature",
  "properties": {
    "addr:full":"Grieskirchner Str 87 Wels Ober\u00f6sterreich 4600",
    "addr:housenumber":"87",
    "addr:postcode":"4600",
    "addr:street":"Str;Oberoesterreich",
    "iso:country":"AT",
    "sg:address":"Grieskirchner Str 87",
    "sg:city":"Wels",
    "sg:orig_category":"Physiotherapie",
    "sg:phone":"+43 676 5384887",
    "sg:postcode":"4600",
    "sg:province":"Ober\u00f6sterreich",
    "wof:name":"Schwandl Thomas Dipl-PT",
    "wof:placetype":"venue"
},
  "geometry": {"coordinates":[14.0213546753,48.1769714355],"type":"Point"}
}