{
  "type": "Feature",
  "properties": {
    "addr:full":"M\u00f6dringer Str 17 Horn Nieder\u00f6sterreich 3580",
    "addr:housenumber":"17",
    "addr:postcode":"3580",
    "addr:street":"Str",
    "iso:country":"AT",
    "sg:address":"M\u00f6dringer Str 17",
    "sg:city":"Horn",
    "sg:orig_category":"Genossenschaften",
    "sg:phone":"+43 2982 5232",
    "sg:postcode":"3580",
    "sg:province":"Nieder\u00f6sterreich",
    "wof:name":"Allgemeine gemeinn\u00fctzige Wohnungsgen in St. P\u00f6lten - eingetr GenmbH",
    "wof:placetype":"venue"
},
  "geometry": {"coordinates":[15.6574287415,48.6637763977],"type":"Point"}
}