{
  "type": "Feature",
  "properties": {
    "addr:full":"Adalbert-Stifter-Str 20 Ansfelden Ober\u00f6sterreich 4052",
    "addr:housenumber":"20",
    "addr:postcode":"4052",
    "addr:street":"Adalbert-Stifter-Str",
    "iso:country":"AT",
    "sg:address":"Adalbert-Stifter-Str 20",
    "sg:city":"Ansfelden",
    "sg:orig_category":"Blumeneinzelhandel",
    "sg:phone":"+43 7229 89727",
    "sg:postcode":"4052",
    "sg:province":"Ober\u00f6sterreich",
    "wof:name":"Mayer Hildegard",
    "wof:placetype":"venue"
},
  "geometry": {"coordinates":[14.290804863,48.2099838257],"type":"Point"}
}