{
  "type": "Feature",
  "properties": {
    "addr:full":"Alte Landstr 19 Frastanz Vorarlberg 6820",
    "addr:housenumber":"19",
    "addr:postcode":"6820",
    "addr:street":"Alte Landstr",
    "iso:country":"AT",
    "sg:address":"Alte Landstr 19",
    "sg:city":"Frastanz",
    "sg:orig_category":"Raumausstattung",
    "sg:phone":"+43 4355 2251540",
    "sg:postcode":"6820",
    "sg:province":"Vorarlberg",
    "wof:name":"Lins Gerold",
    "wof:placetype":"venue"
},
  "geometry": {"coordinates":[9.6273736954,47.2189025879],"type":"Point"}
}