{
  "type": "Feature",
  "properties": {
    "addr:full":"Kalsdorfer Str 45 Feldkirchen Steiermark 8073",
    "addr:postcode":"8073",
    "addr:street":"Str 45",
    "iso:country":"AT",
    "sg:address":"Kalsdorfer Str 45",
    "sg:city":"Feldkirchen",
    "sg:orig_category":"Betonbohr- U -Schneidedienst",
    "sg:phone":"+43 4331 62962180",
    "sg:postcode":"8073",
    "sg:province":"Steiermark",
    "wof:name":"DIMAS Bohr- u S\u00e4ge GesmbH",
    "wof:placetype":"venue"
},
  "geometry": {"coordinates":[15.4514112473,46.9865150452],"type":"Point"}
}