{
  "type": "Feature",
  "properties": {
    "addr:full":"Bahnstr 18 Aspang-Markt Nieder\u00f6sterreich 2870",
    "addr:housenumber":"18",
    "addr:postcode":"2870",
    "addr:street":"Bahnstr;Niederoesterreich",
    "iso:country":"AT",
    "sg:address":"Bahnstr 18",
    "sg:city":"Aspang-Markt",
    "sg:orig_category":"Hafnereien",
    "sg:phone":"+43 2642 525030",
    "sg:postcode":"2870",
    "sg:province":"Nieder\u00f6sterreich",
    "wof:name":"Feldwebel Franz",
    "wof:placetype":"venue"
},
  "geometry": {"coordinates":[16.0942897797,47.5588607788],"type":"Point"}
}