{
  "type": "Feature",
  "properties": {
    "addr:full":"Nr. 173  Achenkirch Tirol 6215",
    "addr:postcode":"6215",
    "addr:street":"Nr.;Achenkirch Tirol",
    "iso:country":"AT",
    "sg:address":"Nr. 173 ",
    "sg:city":"Achenkirch",
    "sg:classifiers":[
        {
            "category":"Travel",
            "subcategory":"Travel Agent",
            "type":"Entertainment"
        }
    ],
    "sg:phone":"+43 4352 4666440",
    "sg:postcode":"6215",
    "sg:province":"Tirol",
    "sg:tags":[
        "business"
    ],
    "wof:name":"CORDIAL FAMILIEN & VITAL HOTEL ACHENKIRCH",
    "wof:placetype":"venue"
},
  "geometry": {"coordinates":[11.7065629959,47.5290184021],"type":"Point"}
}