{
  "type": "Feature",
  "properties": {
    "iso:country":"AT",
    "sg:address":"Ambrosig 7",
    "sg:city":"Oberwart",
    "sg:orig_category":"Blumeneinzelhandel",
    "sg:phone":"+43 3352 31466",
    "sg:postcode":"7400",
    "sg:province":"Burgenland",
    "wof:name":"Blumen 4 Jahreszeiten Michaela Grandits",
    "wof:placetype":"venue"
},
  "geometry": {"coordinates":[16.210603714,47.2877311707],"type":"Point"}
}