{
  "type": "Feature",
  "properties": {
    "iso:country":"AT",
    "sg:address":"Nr 12",
    "sg:city":"Kl\u00f6ch",
    "sg:orig_category":"Spenglereien",
    "sg:phone":"+43 3475 2754",
    "sg:postcode":"8493",
    "sg:province":"Steiermark",
    "wof:name":"Schilli Anton",
    "wof:placetype":"venue"
},
  "geometry": {"coordinates":[8.8541097641,47.3906326294],"type":"Point"}
}