{
  "type": "Feature",
  "properties": {
    "addr:full":"Wolfgang-Amadeus-Mozart-G 29 Wiener Neustadt Nieder\u00f6sterreich 2700",
    "addr:housenumber":"29",
    "addr:postcode":"2700",
    "addr:street":"Wolfgang-Amadeus-Mozart-G",
    "iso:country":"AT",
    "sg:address":"Wolfgang-Amadeus-Mozart-G 29",
    "sg:city":"Wiener Neustadt",
    "sg:orig_category":"Ingenieurkonsulenten / Zivilingenieure",
    "sg:phone":"+43 4326 2225452",
    "sg:postcode":"2700",
    "sg:province":"Nieder\u00f6sterreich",
    "wof:name":"Kraus Eduard Dipl-Ing",
    "wof:placetype":"venue"
},
  "geometry": {"coordinates":[16.26313591,47.8159599304],"type":"Point"}
}