{
  "type": "Feature",
  "properties": {
    "addr:full":"Schweglerstrasse 37  Wien Wien 1150",
    "addr:housenumber":"37",
    "addr:postcode":"1150",
    "addr:street":"Schweglerstrasse",
    "iso:country":"AT",
    "sg:address":"Schweglerstrasse 37 ",
    "sg:city":"Wien",
    "sg:classifiers":[
        {
            "category":"Banks & Credit Unions",
            "subcategory":"Financial Services",
            "type":"Services"
        }
    ],
    "sg:phone":"+43 1 98285290",
    "sg:postcode":"1150",
    "sg:province":"Wien",
    "sg:tags":[
        "control",
        "inventory",
        "software"
    ],
    "sg:website":"www.additive.at",
    "wof:name":"ADDITIVE Hard- und Software f\u00fcr Technik und Wirtschaft GmbH & Co KG",
    "wof:placetype":"venue"
},
  "geometry": {"coordinates":[16.3271617889,48.1996803284],"type":"Point"}
}