{
  "type": "Feature",
  "properties": {
    "iso:country":"AT",
    "sg:address":"Anton-Reichel-Str 14",
    "sg:city":"St. Veit an der Glan",
    "sg:orig_category":"Dachdeckereien",
    "sg:phone":"+43 4212 71386",
    "sg:postcode":"9300",
    "sg:province":"K\u00e4rnten",
    "wof:name":"Sch\u00f6ffmann Dachdeckerei Spenglerei GesmbH",
    "wof:placetype":"venue"
},
  "geometry": {"coordinates":[14.3652324677,46.764125824],"type":"Point"}
}