{
  "type": "Feature",
  "properties": {
    "iso:country":"AT",
    "sg:address":"B\u00fctzenweg 10",
    "sg:city":"Hohenems",
    "sg:orig_category":"Tapezierer U Dekorateure",
    "sg:phone":"+43 5576 75350",
    "sg:postcode":"6845",
    "sg:province":"Vorarlberg",
    "wof:name":"Watzdorf Peter",
    "wof:placetype":"venue"
},
  "geometry": {"coordinates":[9.6887483597,47.3621101379],"type":"Point"}
}