{
  "type": "Feature",
  "properties": {
    "iso:country":"AT",
    "sg:address":"Vivenotg 39",
    "sg:city":"Wien",
    "sg:classifiers":[
        {
            "category":"Restaurant",
            "type":"Food & Drink"
        }
    ],
    "sg:phone":"+43 1 8177975",
    "sg:postcode":"1120",
    "sg:province":"Wien",
    "sg:tags":[
        "pizzeria"
    ],
    "wof:name":"Pizzeria Ragusa",
    "wof:placetype":"venue"
},
  "geometry": {"coordinates":[16.3315734863,48.1776924133],"type":"Point"}
}