{
  "type": "Feature",
  "properties": {
    "addr:full":"Nr 46a Niederndorf Tirol 6342",
    "addr:postcode":"6342",
    "addr:street":"Nr 46A",
    "iso:country":"AT",
    "sg:address":"Nr 46a",
    "sg:city":"Niederndorf",
    "sg:orig_category":"Volksschulen",
    "sg:phone":"+43 5373 61387",
    "sg:postcode":"6342",
    "sg:province":"Tirol",
    "wof:name":"Volksschule",
    "wof:placetype":"venue"
},
  "geometry": {"coordinates":[12.2141237259,47.6500205994],"type":"Point"}
}