{
  "type": "Feature",
  "properties": {
    "iso:country":"AT",
    "sg:address":"Burgg 6",
    "sg:city":"Judenburg",
    "sg:orig_category":"Friseure U Frisiersalons",
    "sg:phone":"+43 3572 8520715",
    "sg:postcode":"8750",
    "sg:province":"Steiermark",
    "wof:name":"Ihr dm Friseur Studio",
    "wof:placetype":"venue"
},
  "geometry": {"coordinates":[14.6603031158,47.1678390503],"type":"Point"}
}