{
  "type": "Feature",
  "properties": {
    "addr:full":"Hackhoferg 17 Neuhart Steiermark 8053",
    "addr:housenumber":"17",
    "addr:postcode":"8053",
    "addr:street":"Hackhoferg",
    "iso:country":"AT",
    "sg:address":"Hackhoferg 17",
    "sg:city":"Neuhart",
    "sg:orig_category":"Raumausstattung",
    "sg:phone":"+43 316 272486",
    "sg:postcode":"8053",
    "sg:province":"Steiermark",
    "wof:name":"Vallant Eduard",
    "wof:placetype":"venue"
},
  "geometry": {"coordinates":[15.4088497162,47.0416946411],"type":"Point"}
}