{
  "type": "Feature",
  "properties": {
    "addr:full":"Weinbergweg 12 Zirl Tirol 6170",
    "addr:housenumber":"12",
    "addr:postcode":"6170",
    "addr:street":"Weinbergweg;Tirol",
    "iso:country":"AT",
    "sg:address":"Weinbergweg 12",
    "sg:city":"Zirl",
    "sg:orig_category":"Pensionen / Privatzimmer",
    "sg:phone":"+43 5238 52079",
    "sg:postcode":"6170",
    "sg:province":"Tirol",
    "wof:name":"G\u00e4stehaus Karl Stranner",
    "wof:placetype":"venue"
},
  "geometry": {"coordinates":[11.2520103455,47.2736701965],"type":"Point"}
}