{
  "type": "Feature",
  "properties": {
    "addr:full":"Grillparzerstr 7 Kirchdorf an der Krems Ober\u00f6sterreich 4560",
    "addr:housenumber":"7",
    "addr:postcode":"4560",
    "addr:street":"Grillparzerstr",
    "iso:country":"AT",
    "sg:address":"Grillparzerstr 7",
    "sg:city":"Kirchdorf an der Krems",
    "sg:orig_category":"Webdesign",
    "sg:phone":"+43 4375 8261193",
    "sg:postcode":"4560",
    "sg:province":"Ober\u00f6sterreich",
    "wof:name":"HOX WEB & GRAFIK DESIGN",
    "wof:placetype":"venue"
},
  "geometry": {"coordinates":[14.1204719543,47.9034309387],"type":"Point"}
}