{
  "type": "Feature",
  "properties": {
    "addr:full":"Reiner Str 60a Gratwein Steiermark 8112",
    "addr:housenumber":"60a",
    "addr:postcode":"8112",
    "addr:street":"Str",
    "iso:country":"AT",
    "sg:address":"Reiner Str 60a",
    "sg:city":"Gratwein",
    "sg:orig_category":"Metallbau",
    "sg:phone":"+43 3124 536350",
    "sg:postcode":"8112",
    "sg:province":"Steiermark",
    "wof:name":"Sint Franz Ing",
    "wof:placetype":"venue"
},
  "geometry": {"coordinates":[15.3115463257,47.1307373047],"type":"Point"}
}