{
  "type": "Feature",
  "properties": {
    "addr:full":"R\u00f6merstr 51 Linz Ober\u00f6sterreich 4020",
    "addr:housenumber":"51",
    "addr:postcode":"4020",
    "addr:street":"Roemerstr",
    "iso:country":"AT",
    "sg:address":"R\u00f6merstr 51",
    "sg:city":"Linz",
    "sg:orig_category":"Steuerberatung",
    "sg:phone":"+43 4373 27857850",
    "sg:postcode":"4020",
    "sg:province":"Ober\u00f6sterreich",
    "wof:name":"TREUGES Wirtschaftspr\u00fcfungs- u SteuerberatungsgesmbH",
    "wof:placetype":"venue"
},
  "geometry": {"coordinates":[14.2883615494,48.2739562988],"type":"Point"}
}