{
  "type": "Feature",
  "properties": {
    "addr:full":"Alleeg 3 M\u00fcrzzuschlag Steiermark 8680",
    "addr:housenumber":"3",
    "addr:postcode":"8680",
    "addr:street":"Alleeg",
    "iso:country":"AT",
    "sg:address":"Alleeg 3",
    "sg:city":"M\u00fcrzzuschlag",
    "sg:orig_category":"Bierdepots",
    "sg:phone":"+43 4338 5221210",
    "sg:postcode":"8680",
    "sg:province":"Steiermark",
    "wof:name":"Brau Union \u00f6sterreich AG",
    "wof:placetype":"venue"
},
  "geometry": {"coordinates":[15.6785535812,47.6071090698],"type":"Point"}
}