{
  "type": "Feature",
  "properties": {
    "iso:country":"AT",
    "sg:address":"Buchbergweg 15",
    "sg:city":"Mattsee",
    "sg:orig_category":"Holzgro\u00c3\u0178handel",
    "sg:phone":"+43 6217 5286",
    "sg:postcode":"5163",
    "sg:province":"Salzburg",
    "wof:name":"Wiesner Sepp KG",
    "wof:placetype":"venue"
},
  "geometry": {"coordinates":[13.1066503525,47.9658889771],"type":"Point"}
}