{
  "type": "Feature",
  "properties": {
    "iso:country":"AT",
    "sg:address":"Burenstr 31",
    "sg:city":"Graz",
    "sg:orig_category":"Nachhilfe U Lernbetreuung",
    "sg:phone":"+43 4366 43464992",
    "sg:postcode":"8020",
    "sg:province":"Steiermark",
    "wof:name":"FLEISS Sprachschule",
    "wof:placetype":"venue"
},
  "geometry": {"coordinates":[15.3929834366,47.0605659485],"type":"Point"}
}