{
  "type": "Feature",
  "properties": {
    "addr:full":"Kurze G 2 Mannersdorf an der Rabnitz Burgenland 7444",
    "addr:housenumber":"2",
    "addr:postcode":"7444",
    "addr:street":"Kurze G",
    "iso:country":"AT",
    "sg:address":"Kurze G 2",
    "sg:city":"Mannersdorf an der Rabnitz",
    "sg:orig_category":"Maschinenreparatur",
    "sg:phone":"+43 2611 2651",
    "sg:postcode":"7444",
    "sg:province":"Burgenland",
    "wof:name":"Wutschek Stefan",
    "wof:placetype":"venue"
},
  "geometry": {"coordinates":[16.5280208588,47.428894043],"type":"Point"}
}