{
  "type": "Feature",
  "properties": {
    "addr:full":"Nr 168 Obervellach K\u00e4rnten 9821",
    "addr:postcode":"9821",
    "addr:street":"Nr 168;Kaernten",
    "iso:country":"AT",
    "sg:address":"Nr 168",
    "sg:city":"Obervellach",
    "sg:orig_category":"Maschinenhandel",
    "sg:phone":"+43 4782 26550",
    "sg:postcode":"9821",
    "sg:province":"K\u00e4rnten",
    "wof:name":"Plantrans Handels- und Projekt GmbH",
    "wof:placetype":"venue"
},
  "geometry": {"coordinates":[13.202000618,46.9322319031],"type":"Point"}
}