{
  "type": "Feature",
  "properties": {
    "iso:country":"AT",
    "sg:address":"Kirchg 2",
    "sg:city":"Bludenz",
    "sg:orig_category":"Architekten",
    "sg:phone":"+43 5552 33611",
    "sg:postcode":"6700",
    "sg:province":"Vorarlberg",
    "wof:name":"Mitiska Markus Dipl-Ing",
    "wof:placetype":"venue"
},
  "geometry": {"coordinates":[9.8195838928,47.1566047668],"type":"Point"}
}