{
  "type": "Feature",
  "properties": {
    "addr:full":"Gewerbeparkstrasse 7 Anif Salzburg 5081",
    "addr:housenumber":"7",
    "addr:postcode":"5081",
    "addr:street":"Gewerbeparkstrasse;Salzburg",
    "iso:country":"AT",
    "sg:address":"Gewerbeparkstrasse 7",
    "sg:city":"Anif",
    "sg:orig_category":"Filling And Test Adapters For Fire Extinguishers",
    "sg:phone":"+43 6246 769250",
    "sg:postcode":"5081",
    "sg:province":"Salzburg",
    "sg:website":"tankschutztechnik.com",
    "wof:name":"tank-schutz-technik Dohnalek-Lebesm\u00fchlbacher OEG",
    "wof:placetype":"venue"
},
  "geometry": {"coordinates":[13.0639257431,47.7499694824],"type":"Point"}
}