{
  "type": "Feature",
  "properties": {
    "iso:country":"AT",
    "sg:address":"Postfeld 10",
    "sg:city":"Dalaas",
    "sg:orig_category":"Behinderungen / Leben Mit Behinderungen",
    "sg:phone":"+43 5585 20055",
    "sg:postcode":"6752",
    "sg:province":"Vorarlberg",
    "wof:name":"WG Lea d Caritas f Menschen mit Behinderung",
    "wof:placetype":"venue"
},
  "geometry": {"coordinates":[9.9998960495,47.1229896545],"type":"Point"}
}