{
  "type": "Feature",
  "properties": {
    "addr:full":"Hauptstrasse 103 Grafenstein K\u00e4rnten 9131",
    "addr:housenumber":"103",
    "addr:postcode":"9131",
    "addr:street":"Hauptstrasse;Kaernten",
    "iso:country":"AT",
    "sg:address":"Hauptstrasse 103",
    "sg:city":"Grafenstein",
    "sg:classifiers":[
        {
            "category":"Shopping",
            "subcategory":"Department Store",
            "type":"Retail Goods"
        }
    ],
    "sg:phone":"+43 4225 2774",
    "sg:postcode":"9131",
    "sg:province":"K\u00e4rnten",
    "sg:tags":[
        "linen",
        "bed"
    ],
    "wof:name":"Josef Rautz",
    "wof:placetype":"venue"
},
  "geometry": {"coordinates":[14.4680223465,46.6107711792],"type":"Point"}
}