{
  "type": "Feature",
  "properties": {
    "addr:full":"Nr 79 Michaelbeuern Salzburg 5152",
    "addr:postcode":"5152",
    "addr:street":"Nr;Michaelbeuern",
    "iso:country":"AT",
    "sg:address":"Nr 79",
    "sg:city":"Michaelbeuern",
    "sg:orig_category":"Friseure U Frisiersalons",
    "sg:phone":"+43 6274 8191",
    "sg:postcode":"5152",
    "sg:province":"Salzburg",
    "wof:name":"Jungwirth Friedrich",
    "wof:placetype":"venue"
},
  "geometry": {"coordinates":[13.0150594711,48.0233306885],"type":"Point"}
}