{
  "type": "Feature",
  "properties": {
    "addr:full":"Passauer Strasse 13 Bad Leonfelden Ober\u00f6sterreich 4190",
    "addr:housenumber":"13",
    "addr:postcode":"4190",
    "addr:street":"Passauer Strasse",
    "iso:country":"AT",
    "sg:address":"Passauer Strasse 13",
    "sg:city":"Bad Leonfelden",
    "sg:classifiers":[
        {
            "category":"Home & Garden",
            "subcategory":"Hardware",
            "type":"Retail Goods"
        }
    ],
    "sg:phone":"+43 7213 6249",
    "sg:postcode":"4190",
    "sg:province":"Ober\u00f6sterreich",
    "sg:tags":[
        "polystyrene",
        "bath-tub",
        "frame",
        "expanded",
        "eps",
        "shower",
        "base"
    ],
    "sg:website":"weichselbaumer.com",
    "wof:name":"Weichselbaumer GmbH & Co KG",
    "wof:placetype":"venue"
},
  "geometry": {"coordinates":[14.2907142639,48.5246734619],"type":"Point"}
}