{
  "type": "Feature",
  "properties": {
    "addr:full":"Claudiastr 610 Seefeld in Tirol Tirol 6100",
    "addr:housenumber":"610",
    "addr:postcode":"6100",
    "addr:street":"Seefeld;Tirol",
    "iso:country":"AT",
    "sg:address":"Claudiastr 610",
    "sg:city":"Seefeld in Tirol",
    "sg:classifiers":[
        {
            "category":"Park",
            "subcategory":"Provincial",
            "type":"Public Place"
        }
    ],
    "sg:phone":"+43 4367 63009859",
    "sg:postcode":"6100",
    "sg:province":"Tirol",
    "sg:tags":[
        "u",
        "ski-",
        "snowboardschulen"
    ],
    "wof:name":"SKI-Guiding Seefeld Keplinger Benno",
    "wof:placetype":"venue"
},
  "geometry": {"coordinates":[11.192278862,47.3305969238],"type":"Point"}
}