{
  "type": "Feature",
  "properties": {
    "addr:full":"Nr 38 Anif Salzburg 5081",
    "addr:postcode":"5081",
    "addr:street":"Nr;Anif",
    "iso:country":"AT",
    "sg:address":"Nr 38",
    "sg:city":"Anif",
    "sg:orig_category":"Exporteure U Importeure",
    "sg:phone":"+43 6246 724910",
    "sg:postcode":"5081",
    "sg:province":"Salzburg",
    "wof:name":"Sixtus-Import - Inh Becker Josef",
    "wof:placetype":"venue"
},
  "geometry": {"coordinates":[13.0639257431,47.7499694824],"type":"Point"}
}