{
  "type": "Feature",
  "properties": {
    "iso:country":"AT",
    "sg:address":"Wiener Strasse 266",
    "sg:city":"G\u00f6sting",
    "sg:classifiers":[
        {
            "category":"Shopping",
            "subcategory":"Department Store",
            "type":"Retail Goods"
        }
    ],
    "sg:phone":"+43 316 6822830",
    "sg:postcode":"8051",
    "sg:province":"Steiermark",
    "sg:tags":[
        "linen",
        "bed"
    ],
    "sg:website":"langer-leinen.at",
    "wof:name":"Norbert Langer & S\u00f6hne Ges.m.b.H.",
    "wof:placetype":"venue"
},
  "geometry": {"coordinates":[15.4065475464,47.0950546265],"type":"Point"}
}