{
  "type": "Feature",
  "properties": {
    "addr:full":"Nr 25 St. P\u00f6lten Nieder\u00f6sterreich 3100",
    "addr:postcode":"3100",
    "addr:street":"Nr 25 St.",
    "iso:country":"AT",
    "sg:address":"Nr 25",
    "sg:city":"St. P\u00f6lten",
    "sg:orig_category":"Hobbyvereine",
    "sg:phone":"+43 2742 74804",
    "sg:postcode":"3100",
    "sg:province":"Nieder\u00f6sterreich",
    "wof:name":"\u00f6sterreichischer Preis-Schnapser Verein",
    "wof:placetype":"venue"
},
  "geometry": {"coordinates":[15.6240940094,48.2076377869],"type":"Point"}
}