{
  "type": "Feature",
  "properties": {
    "iso:country":"AT",
    "sg:address":"H\u00f6henstr 18",
    "sg:city":"Henndorf am Wallersee",
    "sg:classifiers":[
        {
            "category":"Home & Garden",
            "subcategory":"Building Materials",
            "type":"Retail Goods"
        }
    ],
    "sg:phone":"+43 4362 148412",
    "sg:postcode":"5302",
    "sg:province":"Salzburg",
    "sg:tags":[
        "baustoffe",
        "-material",
        "u"
    ],
    "wof:name":"Bosek Adolf Eisen Armierungsdienst GesmbH",
    "wof:placetype":"venue"
},
  "geometry": {"coordinates":[13.1802921295,47.8964118958],"type":"Point"}
}