{
  "type": "Feature",
  "properties": {
    "addr:full":"Dielstr 20 Vandans Vorarlberg 6773",
    "addr:housenumber":"20",
    "addr:postcode":"6773",
    "addr:street":"Dielstr",
    "iso:country":"AT",
    "sg:address":"Dielstr 20",
    "sg:city":"Vandans",
    "sg:orig_category":"Behinderungen / Leben Mit Behinderungen",
    "sg:phone":"+43 5556 75405",
    "sg:postcode":"6773",
    "sg:province":"Vorarlberg",
    "wof:name":"WG Benjamin d. Caritas f. Menschen mit Behinderung",
    "wof:placetype":"venue"
},
  "geometry": {"coordinates":[9.856672287,47.0917282104],"type":"Point"}
}