{
  "type": "Feature",
  "properties": {
    "addr:full":"Hauptstr 83 Gie\u00dfh\u00fcbl Nieder\u00f6sterreich 2372",
    "addr:housenumber":"83",
    "addr:postcode":"2372",
    "addr:street":"Hauptstr;Niederoesterreich",
    "iso:country":"AT",
    "sg:address":"Hauptstr 83",
    "sg:city":"Gie\u00dfh\u00fcbl",
    "sg:orig_category":"Chemisch-Technische Produkte",
    "sg:phone":"+43 2236 26460",
    "sg:postcode":"2372",
    "sg:province":"Nieder\u00f6sterreich",
    "wof:name":"Pingitzer Karl",
    "wof:placetype":"venue"
},
  "geometry": {"coordinates":[16.3687992096,48.2025413513],"type":"Point"}
}