{
  "type": "Feature",
  "properties": {
    "addr:full":"Mayerhoferstr 12 Maishofen Salzburg 5751",
    "addr:housenumber":"12",
    "addr:postcode":"5751",
    "addr:street":"Mayerhoferstr;Salzburg",
    "iso:country":"AT",
    "sg:address":"Mayerhoferstr 12",
    "sg:city":"Maishofen",
    "sg:classifiers":[
        {
            "category":"Government",
            "subcategory":"Post Office",
            "type":"Public Place"
        }
    ],
    "sg:phone":"+43 4365 42682290",
    "sg:postcode":"5751",
    "sg:province":"Salzburg",
    "sg:tags":[
        "-handel",
        "tierzucht",
        "u"
    ],
    "sg:website":"rinderzuchtverband.at",
    "wof:name":"Arbeitsgemeinschaft d Pinzgauer Rinderzuchtverb\u00e4nde",
    "wof:placetype":"venue"
},
  "geometry": {"coordinates":[12.8077926636,47.3584022522],"type":"Point"}
}