{
  "type": "Feature",
  "properties": {
    "addr:full":"Rot-Kreuz-Str 1 Wels Ober\u00f6sterreich 4600",
    "addr:housenumber":"1",
    "addr:postcode":"4600",
    "addr:street":"Rot-Kreuz-Str;Oberoesterreich",
    "iso:country":"AT",
    "sg:address":"Rot-Kreuz-Str 1",
    "sg:city":"Wels",
    "sg:orig_category":"Rettungsdienste",
    "sg:phone":"+43 7242 46400",
    "sg:postcode":"4600",
    "sg:province":"Ober\u00f6sterreich",
    "wof:name":"\u00e4rzte-Notdienst",
    "wof:placetype":"venue"
},
  "geometry": {"coordinates":[14.021944046,48.1726875305],"type":"Point"}
}