{
  "type": "Feature",
  "properties": {
    "addr:full":"Nr 6 Pr\u00e4graten Tirol 9974",
    "addr:postcode":"9974",
    "addr:street":"Nr;Praegraten Tirol",
    "iso:country":"AT",
    "sg:address":"Nr 6",
    "sg:city":"Pr\u00e4graten",
    "sg:orig_category":"Appartements / Ferienwohnungen",
    "sg:phone":"+43 4348 775377",
    "sg:postcode":"9974",
    "sg:province":"Tirol",
    "wof:name":"Bstieler Irma",
    "wof:placetype":"venue"
},
  "geometry": {"coordinates":[12.3755149841,47.0161705017],"type":"Point"}
}