{
  "type": "Feature",
  "properties": {
    "addr:full":"Templstr 32/2 Innsbruck Tirol 6020",
    "addr:housenumber":"32 / 2",
    "addr:postcode":"6020",
    "addr:street":"Templstr;Tirol",
    "iso:country":"AT",
    "sg:address":"Templstr 32/2",
    "sg:city":"Innsbruck",
    "sg:orig_category":"Lebens- U Sozialberatung",
    "sg:phone":"+43 650 5540026",
    "sg:postcode":"6020",
    "sg:province":"Tirol",
    "wof:name":"Institut f Neuropsychologische Rehab -Mag Mario und Mag Christina Draxl",
    "wof:placetype":"venue"
},
  "geometry": {"coordinates":[11.3940086365,47.2584915161],"type":"Point"}
}