{
  "type": "Feature",
  "properties": {
    "addr:full":"Meilersdorf 140 Wolfsbach Nieder\u00f6sterreich 3354",
    "addr:housenumber":"140",
    "addr:postcode":"3354",
    "addr:street":"Meilersdorf",
    "iso:country":"AT",
    "sg:address":"Meilersdorf 140",
    "sg:city":"Wolfsbach",
    "sg:classifiers":[
        {
            "category":"Building & Trades",
            "subcategory":"Electrical",
            "type":"Services"
        }
    ],
    "sg:phone":"+43 7477 20022",
    "sg:postcode":"3354",
    "sg:province":"Nieder\u00f6sterreich",
    "sg:tags":[
        "work",
        "installation"
    ],
    "wof:name":"1AA Personalbereitstellung Halmayr",
    "wof:placetype":"venue"
},
  "geometry": {"coordinates":[14.6686410904,48.0791740417],"type":"Point"}
}