{
  "type": "Feature",
  "properties": {
    "addr:full":"Breitenfurter Str 59 Wien Wien 1120",
    "addr:postcode":"1120",
    "addr:street":"Str 59",
    "iso:country":"AT",
    "sg:address":"Breitenfurter Str 59",
    "sg:city":"Wien",
    "sg:orig_category":"Autohandel",
    "sg:phone":"+43 1 8033445",
    "sg:postcode":"1120",
    "sg:province":"Wien",
    "wof:name":"Autohaus Sascha - Inh Petrovic Zoran KEG",
    "wof:placetype":"venue"
},
  "geometry": {"coordinates":[16.3207950592,48.1691436768],"type":"Point"}
}