{
  "type": "Feature",
  "properties": {
    "addr:full":"Hauptstrasse 145 Mauerbach Nieder\u00f6sterreich 3001",
    "addr:housenumber":"145",
    "addr:postcode":"3001",
    "addr:street":"Hauptstrasse",
    "iso:country":"AT",
    "sg:address":"Hauptstrasse 145",
    "sg:city":"Mauerbach",
    "sg:classifiers":[
        {
            "category":"Military Area",
            "subcategory":"Air Force Base",
            "type":"Public Place"
        }
    ],
    "sg:phone":"+43 1 9792279",
    "sg:postcode":"3001",
    "sg:province":"Nieder\u00f6sterreich",
    "sg:tags":[
        "appliance",
        "assembly",
        "electric"
    ],
    "sg:website":"homeelectronics.at",
    "wof:name":"Walter Kendl Ges.m.b.H.",
    "wof:placetype":"venue"
},
  "geometry": {"coordinates":[16.1664276123,48.2465782166],"type":"Point"}
}