{
  "type": "Feature",
  "properties": {
    "addr:full":"Markt 24 Gutenstein Nieder\u00f6sterreich 2770",
    "addr:housenumber":"24",
    "addr:postcode":"2770",
    "addr:street":"Markt",
    "iso:country":"AT",
    "sg:address":"Markt 24",
    "sg:city":"Gutenstein",
    "sg:orig_category":"Feinkost",
    "sg:phone":"+43 2634 7226",
    "sg:postcode":"2770",
    "sg:province":"Nieder\u00f6sterreich",
    "wof:name":"Rotheneder Alexander",
    "wof:placetype":"venue"
},
  "geometry": {"coordinates":[15.889538765,47.875629425],"type":"Point"}
}