{
  "type": "Feature",
  "properties": {
    "addr:full":"Speisinger Str. 42  Wien Wien 1130",
    "addr:postcode":"1130",
    "addr:street":"Str. 42",
    "iso:country":"AT",
    "sg:address":"Speisinger Str. 42 ",
    "sg:city":"Wien",
    "sg:classifiers":[
        {
            "category":"Banks & Credit Unions",
            "subcategory":"Bank",
            "type":"Services"
        }
    ],
    "sg:phone":"+43 4318 0455280",
    "sg:postcode":"1130",
    "sg:province":"Wien",
    "sg:tags":[
        "banking",
        "institution"
    ],
    "wof:name":"BANK AUSTRIA AG",
    "wof:placetype":"venue"
},
  "geometry": {"coordinates":[16.2853984833,48.1697769165],"type":"Point"}
}