{
  "type": "Feature",
  "properties": {
    "addr:full":"Jochlg 12 Jenbach Tirol 6200",
    "addr:housenumber":"12",
    "addr:postcode":"6200",
    "addr:street":"Jochlg;Tirol",
    "iso:country":"AT",
    "sg:address":"Jochlg 12",
    "sg:city":"Jenbach",
    "sg:orig_category":"Ingenieurkonsulenten / Zivilingenieure",
    "sg:phone":"+43 5244 65491",
    "sg:postcode":"6200",
    "sg:province":"Tirol",
    "wof:name":"P\u00fcllbeck Gottfried Dipl-Ing",
    "wof:placetype":"venue"
},
  "geometry": {"coordinates":[11.7709331512,47.3917541504],"type":"Point"}
}