{
  "type": "Feature",
  "properties": {
    "addr:full":"Hauptstr 38 Seekirchen am Wallersee Salzburg 5201",
    "addr:housenumber":"38",
    "addr:postcode":"5201",
    "addr:street":"Hauptstr;Salzburg",
    "iso:country":"AT",
    "sg:address":"Hauptstr 38",
    "sg:city":"Seekirchen am Wallersee",
    "sg:orig_category":"Friseure U Frisiersalons",
    "sg:phone":"+43 6212 2444",
    "sg:postcode":"5201",
    "sg:province":"Salzburg",
    "wof:name":"Friseur Irina",
    "wof:placetype":"venue"
},
  "geometry": {"coordinates":[13.1251440048,47.8945503235],"type":"Point"}
}