{
  "type": "Feature",
  "properties": {
    "addr:full":"Tratten 10  Kolbnitz K\u00e4rnten 9815",
    "addr:housenumber":"10",
    "addr:postcode":"9815",
    "addr:street":"Tratten;Kaernten",
    "iso:country":"AT",
    "sg:address":"Tratten 10 ",
    "sg:city":"Kolbnitz",
    "sg:classifiers":[
        {
            "category":"Shopping",
            "subcategory":"Stationery & Office Supplies",
            "type":"Retail Goods"
        }
    ],
    "sg:phone":"+43 4347 832575",
    "sg:postcode":"9815",
    "sg:province":"K\u00e4rnten",
    "sg:tags":[
        "professional"
    ],
    "wof:name":"SIEGFRIED EGGER",
    "wof:placetype":"venue"
},
  "geometry": {"coordinates":[13.3048963547,46.8765449524],"type":"Point"}
}