{
  "type": "Feature",
  "properties": {
    "addr:full":"Nr 10 St. Egyden K\u00e4rnten 9536",
    "addr:postcode":"9536",
    "addr:street":"Nr 10",
    "iso:country":"AT",
    "sg:address":"Nr 10",
    "sg:city":"St. Egyden",
    "sg:orig_category":"Pensionen / Privatzimmer",
    "sg:phone":"+43 664 4031895",
    "sg:postcode":"9536",
    "sg:province":"K\u00e4rnten",
    "wof:name":"Pension Santa Lucia",
    "wof:placetype":"venue"
},
  "geometry": {"coordinates":[14.0653963089,46.5760765076],"type":"Point"}
}