{
  "type": "Feature",
  "properties": {
    "addr:full":"Brandberg 164 Mayrhofen Tirol 6290",
    "addr:housenumber":"164",
    "addr:postcode":"6290",
    "addr:street":"Brandberg;Tirol",
    "iso:country":"AT",
    "sg:address":"Brandberg 164",
    "sg:city":"Mayrhofen",
    "sg:orig_category":"Appartements / Ferienwohnungen",
    "sg:phone":"+43 4352 8563911",
    "sg:postcode":"6290",
    "sg:province":"Tirol",
    "wof:name":"Haus Bergland",
    "wof:placetype":"venue"
},
  "geometry": {"coordinates":[11.8654098511,47.1671714783],"type":"Point"}
}