{
  "type": "Feature",
  "properties": {
    "iso:country":"AT",
    "sg:address":"Bahnstr 16A",
    "sg:city":"Aspang-Markt",
    "sg:orig_category":"Bekleidung / Einzelhandel",
    "sg:phone":"+43 2642 51330",
    "sg:postcode":"2870",
    "sg:province":"Nieder\u00f6sterreich",
    "wof:name":"adessa Moden GmbH",
    "wof:placetype":"venue"
},
  "geometry": {"coordinates":[16.0923805237,47.5573196411],"type":"Point"}
}