{
  "type": "Feature",
  "properties": {
    "addr:full":"Fockygasse 39-41 Wien Wien 1120",
    "addr:postcode":"39-41;1120",
    "addr:street":"Fockygasse",
    "iso:country":"AT",
    "sg:address":"Fockygasse 39-41",
    "sg:city":"Wien",
    "sg:classifiers":[
        {
            "category":"Home & Garden",
            "subcategory":"Building Materials",
            "type":"Retail Goods"
        }
    ],
    "sg:phone":"+43 1 8152107",
    "sg:postcode":"1120",
    "sg:province":"Wien",
    "sg:tags":[
        "tile",
        "granite"
    ],
    "wof:name":"Dipl.-Ing. Foltin Bau Ges.m.b.H.",
    "wof:placetype":"venue"
},
  "geometry": {"coordinates":[16.3424816132,48.1814460754],"type":"Point"}
}