{
  "type": "Feature",
  "properties": {
    "addr:full":"Horner Str 42 Ziersdorf Nieder\u00f6sterreich 3710",
    "addr:housenumber":"42",
    "addr:postcode":"3710",
    "addr:street":"Str",
    "iso:country":"AT",
    "sg:address":"Horner Str 42",
    "sg:city":"Ziersdorf",
    "sg:orig_category":"Volkshochschulen",
    "sg:phone":"+43 2956 2495",
    "sg:postcode":"3710",
    "sg:province":"Nieder\u00f6sterreich",
    "wof:name":"Volkshochschule Ziersdorf",
    "wof:placetype":"venue"
},
  "geometry": {"coordinates":[15.9232559204,48.5291481018],"type":"Point"}
}