{
  "type": "Feature",
  "properties": {
    "addr:full":"Dechantskirchen 7 Dechantskirchen Steiermark 8241",
    "addr:housenumber":"7",
    "addr:postcode":"8241",
    "addr:street":"Dechantskirchen",
    "iso:country":"AT",
    "sg:address":"Dechantskirchen 7",
    "sg:city":"Dechantskirchen",
    "sg:classifiers":[
        {
            "category":"Home & Garden",
            "subcategory":"Carpets & Floor Coverings",
            "type":"Retail Goods"
        }
    ],
    "sg:phone":"+43 3339 23341",
    "sg:postcode":"8241",
    "sg:province":"Steiermark",
    "sg:tags":[
        "carpeting"
    ],
    "wof:name":"Manfred Kaltenbacher",
    "wof:placetype":"venue"
},
  "geometry": {"coordinates":[16.0170688629,47.4166946411],"type":"Point"}
}