{
  "type": "Feature",
  "properties": {
    "addr:full":"Scherenbrandtnerhfst 6 Salzburg Salzburg 5020",
    "addr:housenumber":"6",
    "addr:postcode":"5020",
    "addr:street":"Scherenbrandtnerhfst;Salzburg",
    "iso:country":"AT",
    "sg:address":"Scherenbrandtnerhfst 6",
    "sg:city":"Salzburg",
    "sg:classifiers":[
        {
            "category":"Professional",
            "subcategory":"Computer Services",
            "type":"Services"
        }
    ],
    "sg:phone":"+43 662 873792",
    "sg:postcode":"5020",
    "sg:province":"Salzburg",
    "sg:tags":[
        "software"
    ],
    "wof:name":"INTERACTIVE DATA SOLUTIONS K\u00d6LTRINGER & STREILI OEG",
    "wof:placetype":"venue"
},
  "geometry": {"coordinates":[13.0592317581,47.8237113953],"type":"Point"}
}