{
  "type": "Feature",
  "properties": {
    "addr:full":"Landstra\u00dfer Hauptstr 26 Wien Wien 1030",
    "addr:housenumber":"26",
    "addr:postcode":"1030",
    "addr:street":"Landstrasser Hauptstr",
    "iso:country":"AT",
    "sg:address":"Landstra\u00dfer Hauptstr 26",
    "sg:city":"Wien",
    "sg:orig_category":"Finanz- U Wirtschaftsberatung",
    "sg:phone":"+43 4317 137073",
    "sg:postcode":"1030",
    "sg:province":"Wien",
    "wof:name":"actuaria benefits consulting GmbH",
    "wof:placetype":"venue"
},
  "geometry": {"coordinates":[16.3886451721,48.2040252686],"type":"Point"}
}