{
  "type": "Feature",
  "properties": {
    "iso:country":"AT",
    "sg:address":"Bahnhofpl 3",
    "sg:city":"Linz",
    "sg:classifiers":[
        {
            "category":"Restaurant",
            "type":"Food & Drink"
        }
    ],
    "sg:phone":"+43 732 654502",
    "sg:postcode":"4020",
    "sg:province":"Ober\u00f6sterreich",
    "wof:name":"Restaurant Drehscheibe",
    "wof:placetype":"venue"
},
  "geometry": {"coordinates":[14.2926950455,48.293762207],"type":"Point"}
}