{
  "type": "Feature",
  "properties": {
    "addr:full":"Gutenbergg 13 Wien Wien 1070",
    "addr:housenumber":"13",
    "addr:postcode":"1070",
    "addr:street":"Gutenbergg",
    "iso:country":"AT",
    "sg:address":"Gutenbergg 13",
    "sg:city":"Wien",
    "sg:classifiers":[
        {
            "category":"Restaurant",
            "type":"Food & Drink"
        }
    ],
    "sg:phone":"+43 1 5231450",
    "sg:postcode":"1070",
    "sg:province":"Wien",
    "wof:name":"Witwe Bolte",
    "wof:placetype":"venue"
},
  "geometry": {"coordinates":[16.3555793762,48.2032470703],"type":"Point"}
}