{
  "type": "Feature",
  "properties": {
    "iso:country":"AT",
    "sg:address":"Nr 44",
    "sg:city":"Breitenbach am Inn",
    "sg:orig_category":"Pensionen / Privatzimmer",
    "sg:phone":"+43 5338 7571",
    "sg:postcode":"6252",
    "sg:province":"Tirol",
    "wof:name":"Pension-Edelwei\u00df",
    "wof:placetype":"venue"
},
  "geometry": {"coordinates":[11.973446846,47.4788246155],"type":"Point"}
}