{
  "type": "Feature",
  "properties": {
    "addr:full":"Gemeindestr 46 Hausmannst\u00e4tten Steiermark 8071",
    "addr:housenumber":"46",
    "addr:postcode":"8071",
    "addr:street":"Gemeindestr",
    "iso:country":"AT",
    "sg:address":"Gemeindestr 46",
    "sg:city":"Hausmannst\u00e4tten",
    "sg:orig_category":"Transportunternehmen",
    "sg:phone":"+43 4331 3548413",
    "sg:postcode":"8071",
    "sg:province":"Steiermark",
    "wof:name":"Prangl Gerhard",
    "wof:placetype":"venue"
},
  "geometry": {"coordinates":[15.5667476654,47.0226325989],"type":"Point"}
}