{
  "type": "Feature",
  "properties": {
    "addr:full":"Rot-Kreuz-G 40 Neusiedl am See Burgenland 7100",
    "addr:housenumber":"40",
    "addr:postcode":"7100",
    "addr:street":"Rot-Kreuz-G",
    "iso:country":"AT",
    "sg:address":"Rot-Kreuz-G 40",
    "sg:city":"Neusiedl am See",
    "sg:orig_category":"Installationsunternehmen",
    "sg:phone":"+43 2167 8666",
    "sg:postcode":"7100",
    "sg:province":"Burgenland",
    "sg:website":"thienel-installationen.at",
    "wof:name":"Thienel Wolfgang",
    "wof:placetype":"venue"
},
  "geometry": {"coordinates":[16.841884613,47.9491081238],"type":"Point"}
}