{
  "type": "Feature",
  "properties": {
    "addr:full":"Hauptstr 11a Neufeld an der Leitha Burgenland 2491",
    "addr:housenumber":"11a",
    "addr:postcode":"2491",
    "addr:street":"Hauptstr",
    "iso:country":"AT",
    "sg:address":"Hauptstr 11a",
    "sg:city":"Neufeld an der Leitha",
    "sg:orig_category":"Elektroinstallationsunternehmen",
    "sg:phone":"+43 4326 2452315",
    "sg:postcode":"2491",
    "sg:province":"Burgenland",
    "wof:name":"Jungbauer Gerhard Ing",
    "wof:placetype":"venue"
},
  "geometry": {"coordinates":[16.3767986298,47.8690719604],"type":"Point"}
}