{
  "type": "Feature",
  "properties": {
    "iso:country":"AT",
    "sg:address":"Ramsauer Str 12",
    "sg:city":"Linz",
    "sg:orig_category":"Friseure U Frisiersalons",
    "sg:phone":"+43 4373 2346292",
    "sg:postcode":"4020",
    "sg:province":"Ober\u00f6sterreich",
    "wof:name":"Svatek Karl-Heinz",
    "wof:placetype":"venue"
},
  "geometry": {"coordinates":[14.2905950546,48.2755203247],"type":"Point"}
}