{
  "type": "Feature",
  "properties": {
    "iso:country":"AT",
    "sg:address":"Resthofstrasse 2",
    "sg:city":"Steyr",
    "sg:classifiers":[
        {
            "category":"Bus Stop",
            "subcategory":"None",
            "type":"Transportation"
        }
    ],
    "sg:phone":"+43 7252 81122",
    "sg:postcode":"4400",
    "sg:province":"Ober\u00f6sterreich",
    "sg:tags":[
        "current",
        "direct",
        "generator"
    ],
    "sg:website":"ennskraft.at",
    "wof:name":"Ennskraftwerke AG",
    "wof:placetype":"venue"
},
  "geometry": {"coordinates":[14.4232616425,48.0497245789],"type":"Point"}
}