{
  "type": "Feature",
  "properties": {
    "addr:full":"Gschwandnerg 29 Wien Wien 1170",
    "addr:housenumber":"29",
    "addr:postcode":"1170",
    "addr:street":"Gschwandnerg",
    "iso:country":"AT",
    "sg:address":"Gschwandnerg 29",
    "sg:city":"Wien",
    "sg:orig_category":"Bronzewaren",
    "sg:phone":"+43 1 48625830",
    "sg:postcode":"1170",
    "sg:province":"Wien",
    "wof:name":"Zellmetall VertriebsgesmbH",
    "wof:placetype":"venue"
},
  "geometry": {"coordinates":[16.3244934082,48.2181243896],"type":"Point"}
}