{
  "type": "Feature",
  "properties": {
    "iso:country":"AT",
    "sg:address":"Reichsstr 26",
    "sg:city":"Lustenau",
    "sg:classifiers":[
        {
            "category":"Restaurant",
            "type":"Food & Drink"
        }
    ],
    "sg:phone":"+43 5577 89992",
    "sg:postcode":"6890",
    "sg:province":"Vorarlberg",
    "sg:tags":[
        "pizzeria"
    ],
    "wof:name":"Pizzeria Roni",
    "wof:placetype":"venue"
},
  "geometry": {"coordinates":[9.6526107788,47.4233894348],"type":"Point"}
}