{
  "type": "Feature",
  "properties": {
    "addr:full":"Linker Iselweg 20 Lienz Tirol 9900",
    "addr:housenumber":"20",
    "addr:postcode":"9900",
    "addr:street":"Linker Iselweg;Tirol",
    "iso:country":"AT",
    "sg:address":"Linker Iselweg 20",
    "sg:city":"Lienz",
    "sg:orig_category":"Berufsschulen",
    "sg:phone":"+43 4852 627260",
    "sg:postcode":"9900",
    "sg:province":"Tirol",
    "wof:name":"Tiroler Fachberufsschule Lienz",
    "wof:placetype":"venue"
},
  "geometry": {"coordinates":[12.760184288,46.8329658508],"type":"Point"}
}