{
  "type": "Feature",
  "properties": {
    "addr:full":"Hauptpl 14 Liezen Steiermark 8940",
    "addr:housenumber":"14",
    "addr:postcode":"8940",
    "addr:street":"Hauptpl",
    "iso:country":"AT",
    "sg:address":"Hauptpl 14",
    "sg:city":"Liezen",
    "sg:orig_category":"Bankomat-Standorte",
    "sg:phone":"+43 3612 227450",
    "sg:postcode":"8940",
    "sg:province":"Steiermark",
    "wof:name":"Bankomat d Volksbank Liezen, Gesch\u00e4ftsst d Volksbank Enns-u Paltental",
    "wof:placetype":"venue"
},
  "geometry": {"coordinates":[14.2412004471,47.5673294067],"type":"Point"}
}