{
  "type": "Feature",
  "properties": {
    "addr:full":"Alte Arlbergstr 9 St. Anton am Arlberg Tirol 6580",
    "addr:housenumber":"9",
    "addr:postcode":"6580",
    "addr:street":"Tirol",
    "iso:country":"AT",
    "sg:address":"Alte Arlbergstr 9",
    "sg:city":"St. Anton am Arlberg",
    "sg:orig_category":"Pensionen / Privatzimmer",
    "sg:phone":"+43 5446 3272",
    "sg:postcode":"6580",
    "sg:province":"Tirol",
    "wof:name":"Fremdenzimmer Fam Schwendinger",
    "wof:placetype":"venue"
},
  "geometry": {"coordinates":[10.2621707916,47.1267166138],"type":"Point"}
}