{
  "type": "Feature",
  "properties": {
    "addr:full":"Prinz-Eugen-Strasse 30 Wien Wien 1040",
    "addr:housenumber":"30",
    "addr:postcode":"1040",
    "addr:street":"Prinz-Eugen-Strasse",
    "iso:country":"AT",
    "sg:address":"Prinz-Eugen-Strasse 30",
    "sg:city":"Wien",
    "sg:classifiers":[
        {
            "category":"Shopping",
            "subcategory":"Books",
            "type":"Retail Goods"
        }
    ],
    "sg:phone":"+43 1 50576610",
    "sg:postcode":"1040",
    "sg:province":"Wien",
    "sg:tags":[
        "astronomy"
    ],
    "sg:website":"www.zsolnay.at",
    "wof:name":"Paul Zsolnay Verlag GesmbH.",
    "wof:placetype":"venue"
},
  "geometry": {"coordinates":[16.3775062561,48.1938056946],"type":"Point"}
}