{
  "type": "Feature",
  "properties": {
    "addr:full":"Nr 249 Ischgl Tirol 6561",
    "addr:postcode":"6561",
    "addr:street":"Nr 249;Tirol",
    "iso:country":"AT",
    "sg:address":"Nr 249",
    "sg:city":"Ischgl",
    "sg:orig_category":"Appartements / Ferienwohnungen",
    "sg:phone":"+43 5444 5464",
    "sg:postcode":"6561",
    "sg:province":"Tirol",
    "wof:name":"Chalet Schmitta",
    "wof:placetype":"venue"
},
  "geometry": {"coordinates":[10.2881736755,47.0111351013],"type":"Point"}
}