{
  "type": "Feature",
  "properties": {
    "addr:full":"Laabstr 72 Braunau am Inn Ober\u00f6sterreich 5280",
    "addr:housenumber":"72",
    "addr:postcode":"5280",
    "addr:street":"Laabstr",
    "iso:country":"AT",
    "sg:address":"Laabstr 72",
    "sg:city":"Braunau am Inn",
    "sg:orig_category":"Waagen / Erzeugung U Gro\u00c3\u0178handel",
    "sg:phone":"+43 4377 22623870",
    "sg:postcode":"5280",
    "sg:province":"Ober\u00f6sterreich",
    "sg:website":"schenck.at",
    "wof:name":"Schenck GesmbH",
    "wof:placetype":"venue"
},
  "geometry": {"coordinates":[13.0535516739,48.2594108582],"type":"Point"}
}