{
  "type": "Feature",
  "properties": {
    "addr:full":"Stadtpl 40/42 Gm\u00fcnd Nieder\u00f6sterreich 3950",
    "addr:housenumber":"40 / 42",
    "addr:postcode":"3950",
    "addr:street":"Stadtpl;Niederoesterreich",
    "iso:country":"AT",
    "sg:address":"Stadtpl 40/42",
    "sg:city":"Gm\u00fcnd",
    "sg:orig_category":"Damenmoden",
    "sg:phone":"+43 2852 52636",
    "sg:postcode":"3950",
    "sg:province":"Nieder\u00f6sterreich",
    "wof:name":"Zimm Mode",
    "wof:placetype":"venue"
},
  "geometry": {"coordinates":[14.9868993759,48.772731781],"type":"Point"}
}