{
  "type": "Feature",
  "properties": {
    "iso:country":"AT",
    "sg:address":"Bahnhofstr 27",
    "sg:city":"Altheim",
    "sg:orig_category":"\u00c3\u201erzte / F Allgemeinmedizin",
    "sg:phone":"+43 7723 423220",
    "sg:postcode":"4950",
    "sg:province":"Ober\u00f6sterreich",
    "wof:name":"Kr\u00f6sslhuber Michael Dr",
    "wof:placetype":"venue"
},
  "geometry": {"coordinates":[13.2342281342,48.251991272],"type":"Point"}
}