{
  "type": "Feature",
  "properties": {
    "addr:full":"Gramartstr 25 Innsbruck Tirol 6020",
    "addr:housenumber":"25",
    "addr:postcode":"6020",
    "addr:street":"Gramartstr;Tirol",
    "iso:country":"AT",
    "sg:address":"Gramartstr 25",
    "sg:city":"Innsbruck",
    "sg:orig_category":"Preisagenturen",
    "sg:phone":"+43 512 933358",
    "sg:postcode":"6020",
    "sg:province":"Tirol",
    "wof:name":"Andre Gerhard",
    "wof:placetype":"venue"
},
  "geometry": {"coordinates":[11.3931846619,47.284702301],"type":"Point"}
}