{
  "type": "Feature",
  "properties": {
    "addr:full":"Steinebach 18 Dornbirn Vorarlberg 6850",
    "addr:housenumber":"18",
    "addr:postcode":"6850",
    "addr:street":"Steinebach",
    "iso:country":"AT",
    "sg:address":"Steinebach 18",
    "sg:city":"Dornbirn",
    "sg:orig_category":"Werbegrafik- U Grafik-Design",
    "sg:phone":"+43 4355 72386300",
    "sg:postcode":"6850",
    "sg:province":"Vorarlberg",
    "wof:name":"Haun Design+",
    "wof:placetype":"venue"
},
  "geometry": {"coordinates":[9.7585306168,47.4049568176],"type":"Point"}
}