{
  "type": "Feature",
  "properties": {
    "addr:full":"Nr 75 Baldramsdorf K\u00e4rnten 9805",
    "addr:postcode":"9805",
    "addr:street":"Nr 75;Kaernten",
    "iso:country":"AT",
    "sg:address":"Nr 75",
    "sg:city":"Baldramsdorf",
    "sg:orig_category":"Futtermittel",
    "sg:phone":"+43 4762 7178",
    "sg:postcode":"9805",
    "sg:province":"K\u00e4rnten",
    "wof:name":"Volpini De Maestri Paul Sixtus",
    "wof:placetype":"venue"
},
  "geometry": {"coordinates":[13.4519433975,46.801574707],"type":"Point"}
}