{
  "type": "Feature",
  "properties": {
    "iso:country":"AT",
    "sg:address":"Broschg 9",
    "sg:city":"Linz",
    "sg:orig_category":"Feinkost",
    "sg:phone":"+43 732 7311110",
    "sg:postcode":"4040",
    "sg:province":"Ober\u00f6sterreich",
    "wof:name":"Erste Linzer Feinkost Riemenschneider GesmbH",
    "wof:placetype":"venue"
},
  "geometry": {"coordinates":[14.2928495407,48.3224029541],"type":"Point"}
}