{
  "type": "Feature",
  "properties": {
    "iso:country":"AT",
    "sg:address":"Kienzlstr 13/1",
    "sg:city":"Wels",
    "sg:orig_category":"Psychotherapie",
    "sg:phone":"+43 7242 66595",
    "sg:postcode":"4600",
    "sg:province":"Ober\u00f6sterreich",
    "wof:name":"Fussenegger Ingrid Dr",
    "wof:placetype":"venue"
},
  "geometry": {"coordinates":[14.0140399933,48.155872345],"type":"Point"}
}