{
  "type": "Feature",
  "properties": {
    "addr:full":"Stadtpl 49 Schwanenstadt Ober\u00f6sterreich 4690",
    "addr:housenumber":"49",
    "addr:postcode":"4690",
    "addr:street":"Stadtpl",
    "iso:country":"AT",
    "sg:address":"Stadtpl 49",
    "sg:city":"Schwanenstadt",
    "sg:orig_category":"Installationsunternehmen",
    "sg:phone":"+43 76732349",
    "sg:postcode":"4690",
    "sg:province":"Ober\u00f6sterreich",
    "wof:name":"Langer Stephan",
    "wof:placetype":"venue"
},
  "geometry": {"coordinates":[13.7744998932,48.0548400879],"type":"Point"}
}