{
  "type": "Feature",
  "properties": {
    "addr:full":"Wiener G 44 Perchtoldsdorf Nieder\u00f6sterreich 2380",
    "addr:housenumber":"44",
    "addr:postcode":"2380",
    "addr:street":"Wiener G",
    "iso:country":"AT",
    "sg:address":"Wiener G 44",
    "sg:city":"Perchtoldsdorf",
    "sg:orig_category":"Juweliere, Gold- U Silberschmiede",
    "sg:phone":"+43 1 8673535",
    "sg:postcode":"2380",
    "sg:province":"Nieder\u00f6sterreich",
    "wof:name":"NADJA'S by Nadja Zweigler",
    "wof:placetype":"venue"
},
  "geometry": {"coordinates":[16.268819809,48.122303009],"type":"Point"}
}