{
  "type": "Feature",
  "properties": {
    "addr:full":"Br\u00e4um\u00fchlweg 3 Bergheim Salzburg 5101",
    "addr:housenumber":"3",
    "addr:postcode":"5101",
    "addr:street":"Braeumuehlweg;Salzburg",
    "iso:country":"AT",
    "sg:address":"Br\u00e4um\u00fchlweg 3",
    "sg:city":"Bergheim",
    "sg:orig_category":"Warensicherungssysteme",
    "sg:phone":"+43 662 455353",
    "sg:postcode":"5101",
    "sg:province":"Salzburg",
    "wof:name":"Intersafe GesmbH",
    "wof:placetype":"venue"
},
  "geometry": {"coordinates":[13.0230998993,47.8411369324],"type":"Point"}
}