{
  "type": "Feature",
  "properties": {
    "iso:country":"AT",
    "sg:address":"Tauernstr 27",
    "sg:city":"Radstadt",
    "sg:orig_category":"Autoreparatur",
    "sg:phone":"+43 6452 55630",
    "sg:postcode":"5550",
    "sg:province":"Salzburg",
    "wof:name":"Neumayer GesmbH",
    "wof:placetype":"venue"
},
  "geometry": {"coordinates":[13.4735078812,47.3789138794],"type":"Point"}
}