{
  "type": "Feature",
  "properties": {
    "iso:country":"AT",
    "sg:address":"Diefenbachg 35/1",
    "sg:city":"Wien",
    "sg:orig_category":"Auskunfteien",
    "sg:phone":"+43 1 8974244",
    "sg:postcode":"1150",
    "sg:province":"Wien",
    "wof:name":"Deltavista GesmbH",
    "wof:placetype":"venue"
},
  "geometry": {"coordinates":[16.3324775696,48.1852989197],"type":"Point"}
}