{
  "type": "Feature",
  "properties": {
    "addr:full":"Wannemacherg 4/7 Wien Wien 1210",
    "addr:housenumber":"4 / 7",
    "addr:postcode":"1210",
    "addr:street":"Wannemacherg",
    "iso:country":"AT",
    "sg:address":"Wannemacherg 4/7",
    "sg:city":"Wien",
    "sg:classifiers":[
        {
            "category":"Professional",
            "subcategory":"Computer Services",
            "type":"Services"
        }
    ],
    "sg:phone":"+43 1 2940200",
    "sg:postcode":"1210",
    "sg:province":"Wien",
    "sg:tags":[
        "software"
    ],
    "wof:name":"GoToWeb Software Vertriebs GmbH",
    "wof:placetype":"venue"
},
  "geometry": {"coordinates":[16.4098377228,48.2798728943],"type":"Point"}
}