{
  "type": "Feature",
  "properties": {
    "iso:country":"AT",
    "sg:address":"Strandg 33",
    "sg:city":"Podersdorf am See",
    "sg:orig_category":"Pensionen / Privatzimmer",
    "sg:phone":"+43 2177 2162",
    "sg:postcode":"7141",
    "sg:province":"Burgenland",
    "wof:name":"Schreier Ingrid",
    "wof:placetype":"venue"
},
  "geometry": {"coordinates":[16.8282814026,47.8544578552],"type":"Point"}
}