{
  "type": "Feature",
  "properties": {
    "addr:full":"Puchg. 6 Wien Wien 1220",
    "addr:housenumber":"6",
    "addr:postcode":"1220",
    "addr:street":"Puchg.",
    "iso:country":"AT",
    "sg:address":"Puchg. 6",
    "sg:city":"Wien",
    "sg:classifiers":[
        {
            "category":"Professional",
            "subcategory":"Engineering",
            "type":"Services"
        }
    ],
    "sg:phone":"+43 4312 583511",
    "sg:postcode":"1220",
    "sg:province":"Wien",
    "sg:tags":[
        "machine",
        "-",
        "mechanical"
    ],
    "wof:name":"K\u00dcHLER FISCHER AUSTRIA GMBH",
    "wof:placetype":"venue"
},
  "geometry": {"coordinates":[16.4565162659,48.2620162964],"type":"Point"}
}