{
  "type": "Feature",
  "properties": {
    "iso:country":"AT",
    "sg:address":"Bahnhofstr 8",
    "sg:city":"Lustenau",
    "sg:orig_category":"Tankstellen",
    "sg:phone":"+43 4355 7782312",
    "sg:postcode":"6890",
    "sg:province":"Vorarlberg",
    "wof:name":"AVANTI TankstellenbetriebsgesmbH",
    "wof:placetype":"venue"
},
  "geometry": {"coordinates":[9.6567964554,47.4391746521],"type":"Point"}
}