{
  "type": "Feature",
  "properties": {
    "addr:full":"Gutenbergg 1 Wien Wien 1070",
    "addr:housenumber":"1",
    "addr:postcode":"1070",
    "addr:street":"Gutenbergg",
    "iso:country":"AT",
    "sg:address":"Gutenbergg 1",
    "sg:city":"Wien",
    "sg:orig_category":"Architekten",
    "sg:phone":"+43 1 52391940",
    "sg:postcode":"1070",
    "sg:province":"Wien",
    "wof:name":"Fuchs Reinhard Arch Dipl-Ing",
    "wof:placetype":"venue"
},
  "geometry": {"coordinates":[16.3557109833,48.2027397156],"type":"Point"}
}