{
  "type": "Feature",
  "properties": {
    "addr:full":"Rosenstr 15 Linz Ober\u00f6sterreich 4040",
    "addr:housenumber":"15",
    "addr:postcode":"4040",
    "addr:street":"Rosenstr",
    "iso:country":"AT",
    "sg:address":"Rosenstr 15",
    "sg:city":"Linz",
    "sg:orig_category":"Waren Aller Art",
    "sg:phone":"+43 732 776922",
    "sg:postcode":"4040",
    "sg:province":"Ober\u00f6sterreich",
    "wof:name":"P.L.U.S. Marketing GesmbH",
    "wof:placetype":"venue"
},
  "geometry": {"coordinates":[14.2789535522,48.3095245361],"type":"Point"}
}