{
  "type": "Feature",
  "properties": {
    "iso:country":"AT",
    "sg:address":"Laichbergweg 64",
    "sg:city":"Steyr",
    "sg:classifiers":[
        {
            "category":"Organizations",
            "subcategory":"Community Association",
            "type":"Services"
        }
    ],
    "sg:phone":"+43 7252 48212",
    "sg:postcode":"4400",
    "sg:province":"Ober\u00f6sterreich",
    "sg:tags":[
        "relation",
        "public"
    ],
    "wof:name":"Obst Harald Public Relations KEG",
    "wof:placetype":"venue"
},
  "geometry": {"coordinates":[14.4021396637,48.032119751],"type":"Point"}
}