{
  "type": "Feature",
  "properties": {
    "iso:country":"AT",
    "sg:address":"Am S\u00fcssenberg 6",
    "sg:city":"Steinerkirchen an der Traun",
    "sg:orig_category":"Zahntechnische Laboratorien",
    "sg:phone":"+43 664 4508478",
    "sg:postcode":"4652",
    "sg:province":"Ober\u00f6sterreich",
    "wof:name":"Dentallabor Wurm",
    "wof:placetype":"venue"
},
  "geometry": {"coordinates":[13.957324028,48.0788803101],"type":"Point"}
}