{
  "type": "Feature",
  "properties": {
    "addr:full":"Moosfeldstr 24/1 Bergheim Salzburg 5101",
    "addr:housenumber":"24 / 1",
    "addr:postcode":"5101",
    "addr:street":"Moosfeldstr;Salzburg",
    "iso:country":"AT",
    "sg:address":"Moosfeldstr 24/1",
    "sg:city":"Bergheim",
    "sg:orig_category":"Werbeagenturen",
    "sg:phone":"+43 662 4599950",
    "sg:postcode":"5101",
    "sg:province":"Salzburg",
    "wof:name":"Prossinger Werbeagentur",
    "wof:placetype":"venue"
},
  "geometry": {"coordinates":[13.0589427948,47.8414916992],"type":"Point"}
}