{
  "type": "Feature",
  "properties": {
    "addr:full":"Franziskanerpl 1 Wien Wien 1010",
    "addr:housenumber":"1",
    "addr:postcode":"1010",
    "addr:street":"Franziskanerpl",
    "iso:country":"AT",
    "sg:address":"Franziskanerpl 1",
    "sg:city":"Wien",
    "sg:orig_category":"Waren Aller Art",
    "sg:phone":"+43 1 5125178",
    "sg:postcode":"1010",
    "sg:province":"Wien",
    "wof:name":"Anatevka Handelsgesellschaft m.b.H.",
    "wof:placetype":"venue"
},
  "geometry": {"coordinates":[16.3740577698,48.206577301],"type":"Point"}
}