{
  "type": "Feature",
  "properties": {
    "addr:full":"Rudolf-von-Alt-Pl 6 Wien Wien 1030",
    "addr:housenumber":"6",
    "addr:postcode":"1030",
    "addr:street":"Rudolf-Von-Alt-Pl",
    "iso:country":"AT",
    "sg:address":"Rudolf-von-Alt-Pl 6",
    "sg:city":"Wien",
    "sg:orig_category":"Psychotherapie",
    "sg:phone":"+43 4317 136677",
    "sg:postcode":"1030",
    "sg:province":"Wien",
    "wof:name":"Bischof Maria",
    "wof:placetype":"venue"
},
  "geometry": {"coordinates":[16.393404007,48.2069778442],"type":"Point"}
}