{
  "type": "Feature",
  "properties": {
    "iso:country":"AT",
    "sg:address":"Neunkirchner Str 129",
    "sg:city":"Wiener Neustadt",
    "sg:orig_category":"Autohandel",
    "sg:phone":"+43 2622 282550",
    "sg:postcode":"2700",
    "sg:province":"Nieder\u00f6sterreich",
    "wof:name":"DENZEL Kundencenter Wiener Neustadt",
    "wof:placetype":"venue"
},
  "geometry": {"coordinates":[16.2212734222,47.7963409424],"type":"Point"}
}