{
  "type": "Feature",
  "properties": {
    "iso:country":"AT",
    "sg:address":"Wandstr 7",
    "sg:city":"Gr\u00fcnbach am Schneeberg",
    "sg:orig_category":"Raumausstattung",
    "sg:phone":"+43 4326 372297",
    "sg:postcode":"2733",
    "sg:province":"Nieder\u00f6sterreich",
    "wof:name":"Scherz GesmbH",
    "wof:placetype":"venue"
},
  "geometry": {"coordinates":[12.6405601501,50.5948791504],"type":"Point"}
}