{
  "type": "Feature",
  "properties": {
    "addr:full":"Hochofenstr. 3 Eisenerz Steiermark 8790",
    "addr:housenumber":"3",
    "addr:postcode":"8790",
    "addr:street":"Hochofenstr.",
    "iso:country":"AT",
    "sg:address":"Hochofenstr. 3",
    "sg:city":"Eisenerz",
    "sg:classifiers":[
        {
            "category":"Manufacturing",
            "subcategory":"Glass & Minerals",
            "type":"Manufacturing & Wholesale Goods"
        }
    ],
    "sg:phone":"+43 4338 482280",
    "sg:postcode":"8790",
    "sg:province":"Steiermark",
    "wof:name":"PILKINGTON AUTOMOTIVE AUSTRIA GESMBH",
    "wof:placetype":"venue"
},
  "geometry": {"coordinates":[14.8730783463,47.551109314],"type":"Point"}
}