{
  "type": "Feature",
  "properties": {
    "addr:full":"Unterdorf 13 Wenns Tirol 6473",
    "addr:housenumber":"13",
    "addr:postcode":"6473",
    "addr:street":"Unterdorf;Tirol",
    "iso:country":"AT",
    "sg:address":"Unterdorf 13",
    "sg:city":"Wenns",
    "sg:orig_category":"Appartements / Ferienwohnungen",
    "sg:phone":"+43 5414 86172",
    "sg:postcode":"6473",
    "sg:province":"Tirol",
    "wof:name":"R\u00f6ck Werner - Appartements Wildkar und Landhaus Julia",
    "wof:placetype":"venue"
},
  "geometry": {"coordinates":[10.7312002182,47.1684265137],"type":"Point"}
}