{
  "type": "Feature",
  "properties": {
    "addr:full":"Percostr 8 Wien Wien 1220",
    "addr:housenumber":"8",
    "addr:postcode":"1220",
    "addr:street":"Percostr",
    "iso:country":"AT",
    "sg:address":"Percostr 8",
    "sg:city":"Wien",
    "sg:orig_category":"Gie\u00c3\u0178ereien",
    "sg:phone":"+43 1 25744160",
    "sg:postcode":"1220",
    "sg:province":"Wien",
    "wof:name":"GUSS Fertigungs-GesmbH",
    "wof:placetype":"venue"
},
  "geometry": {"coordinates":[16.4665298462,48.2646217346],"type":"Point"}
}