{
  "type": "Feature",
  "properties": {
    "iso:country":"AT",
    "sg:address":"Monte-Piano-Str 9",
    "sg:city":"Innsbruck",
    "sg:orig_category":"Friseure U Frisiersalons",
    "sg:phone":"+43 4351 2204664",
    "sg:postcode":"6020",
    "sg:province":"Tirol",
    "wof:name":"Frisiersalon Gitti",
    "wof:placetype":"venue"
},
  "geometry": {"coordinates":[11.4396734238,47.2754478455],"type":"Point"}
}