{
  "type": "Feature",
  "properties": {
    "addr:full":"Machstr 7 Wels Ober\u00f6sterreich 4600",
    "addr:housenumber":"7",
    "addr:postcode":"4600",
    "addr:street":"Machstr;Oberoesterreich",
    "iso:country":"AT",
    "sg:address":"Machstr 7",
    "sg:city":"Wels",
    "sg:orig_category":"Bauunternehmen",
    "sg:phone":"+43 7242 6950",
    "sg:postcode":"4600",
    "sg:province":"Ober\u00f6sterreich",
    "wof:name":"Felbermayr Bau GmbH & Co KG",
    "wof:placetype":"venue"
},
  "geometry": {"coordinates":[14.0529623032,48.1633720398],"type":"Point"}
}