{
  "type": "Feature",
  "properties": {
    "addr:full":"Lainzer Str 1 Wien Wien 1130",
    "addr:housenumber":"1",
    "addr:postcode":"1130",
    "addr:street":"Str",
    "iso:country":"AT",
    "sg:address":"Lainzer Str 1",
    "sg:city":"Wien",
    "sg:orig_category":"Molkereien U Molkereiprodukte",
    "sg:phone":"+43 4318 764749",
    "sg:postcode":"1130",
    "sg:province":"Wien",
    "wof:name":"Alles K\u00e4se Teigwarenerzeugung u K\u00e4sehandel GesmbH",
    "wof:placetype":"venue"
},
  "geometry": {"coordinates":[16.2983551025,48.1860466003],"type":"Point"}
}