{
  "type": "Feature",
  "properties": {
    "iso:country":"AT",
    "sg:address":"Sch\u00f6nbrunng 73",
    "sg:city":"Graz",
    "sg:orig_category":"Architekten",
    "sg:phone":"+43 316 3230770",
    "sg:postcode":"8010",
    "sg:province":"Steiermark",
    "wof:name":"Giencke Volker Univ Prof Dipl-Ing",
    "wof:placetype":"venue"
},
  "geometry": {"coordinates":[15.4485778809,47.0934791565],"type":"Point"}
}