{
  "type": "Feature",
  "properties": {
    "iso:country":"AT",
    "sg:address":"Hausberg 4",
    "sg:city":"Waidring",
    "sg:orig_category":"Appartements / Ferienwohnungen",
    "sg:phone":"+43 4353 535339",
    "sg:postcode":"6384",
    "sg:province":"Tirol",
    "wof:name":"Albrecht Oliver",
    "wof:placetype":"venue"
},
  "geometry": {"coordinates":[12.5678377151,47.5823822021],"type":"Point"}
}