{
  "type": "Feature",
  "properties": {
    "iso:country":"AT",
    "sg:address":"Nr 90c",
    "sg:city":"Innervillgraten",
    "sg:orig_category":"Energietechnik",
    "sg:phone":"+43 664 1207867",
    "sg:postcode":"9932",
    "sg:province":"Tirol",
    "wof:name":"Steidl - Innovationen mit Energie",
    "wof:placetype":"venue"
},
  "geometry": {"coordinates":[12.3711109161,46.8079109192],"type":"Point"}
}