{
  "type": "Feature",
  "properties": {
    "iso:country":"AT",
    "sg:address":"Hausbergstr 15",
    "sg:city":"Walchsee",
    "sg:orig_category":"Volksschulen",
    "sg:phone":"+43 5374 521020",
    "sg:postcode":"6344",
    "sg:province":"Tirol",
    "wof:name":"Volksschule",
    "wof:placetype":"venue"
},
  "geometry": {"coordinates":[12.3191843033,47.6572875977],"type":"Point"}
}