{
  "type": "Feature",
  "properties": {
    "iso:country":"AT",
    "sg:address":"Hammerpark 4-8",
    "sg:city":"M\u00fcrzzuschlag",
    "sg:orig_category":"Fleischhauereien",
    "sg:phone":"+43 3852 30038",
    "sg:postcode":"8680",
    "sg:province":"Steiermark",
    "wof:name":"Schirnhofer-Breisler GesmbH",
    "wof:placetype":"venue"
},
  "geometry": {"coordinates":[15.672908783,47.6063156128],"type":"Point"}
}