{
  "type": "Feature",
  "properties": {
    "addr:full":"Kurrentg 10 Wien Wien 1010",
    "addr:housenumber":"10",
    "addr:postcode":"1010",
    "addr:street":"Kurrentg",
    "iso:country":"AT",
    "sg:address":"Kurrentg 10",
    "sg:city":"Wien",
    "sg:orig_category":"Tapezierer U Dekorateure",
    "sg:phone":"+43 1 5337468",
    "sg:postcode":"1010",
    "sg:province":"Wien",
    "wof:name":"Stary Josef",
    "wof:placetype":"venue"
},
  "geometry": {"coordinates":[16.3700313568,48.2110824585],"type":"Point"}
}