{
  "type": "Feature",
  "properties": {
    "iso:country":"AT",
    "sg:address":"Inselstr 5",
    "sg:city":"Hard",
    "sg:orig_category":"Bestattungsunternehmen",
    "sg:phone":"+43 4355 74725300",
    "sg:postcode":"6971",
    "sg:province":"Vorarlberg",
    "wof:name":"Reumiller Alwin",
    "wof:placetype":"venue"
},
  "geometry": {"coordinates":[9.6929512024,47.4925346375],"type":"Point"}
}