{
  "type": "Feature",
  "properties": {
    "addr:full":"F Hanusch-Str 1 Leoben Steiermark 8700",
    "addr:housenumber":"1",
    "addr:postcode":"8700",
    "addr:street":"Hanusch-Str",
    "iso:country":"AT",
    "sg:address":"F Hanusch-Str 1",
    "sg:city":"Leoben",
    "sg:orig_category":"Damenmoden",
    "sg:phone":"+43 3842 29517",
    "sg:postcode":"8700",
    "sg:province":"Steiermark",
    "wof:name":"NEW YORKER - NYer Hansen & Knapp KG",
    "wof:placetype":"venue"
},
  "geometry": {"coordinates":[15.0868330002,47.3728065491],"type":"Point"}
}