{
  "type": "Feature",
  "properties": {
    "iso:country":"AT",
    "sg:address":"Nr 56",
    "sg:city":"Waldhausen",
    "sg:orig_category":"Lebensmittel / Einzelhandel",
    "sg:phone":"+43 2877 8271",
    "sg:postcode":"3914",
    "sg:province":"Nieder\u00f6sterreich",
    "wof:name":"Spar Markt - Engelbert Glatzl",
    "wof:placetype":"venue"
},
  "geometry": {"coordinates":[15.2610387802,48.5218048096],"type":"Point"}
}