{
  "type": "Feature",
  "properties": {
    "addr:full":"Wiener Ring 26 Korneuburg Nieder\u00f6sterreich 2100",
    "addr:housenumber":"26",
    "addr:postcode":"2100",
    "addr:street":"Wiener Ring;Niederoesterreich",
    "iso:country":"AT",
    "sg:address":"Wiener Ring 26",
    "sg:city":"Korneuburg",
    "sg:orig_category":"Baumeister",
    "sg:phone":"+43 2262 725950",
    "sg:postcode":"2100",
    "sg:province":"Nieder\u00f6sterreich",
    "wof:name":"Garo Marius Dipl-Ing GmbH & Co KG",
    "wof:placetype":"venue"
},
  "geometry": {"coordinates":[16.3356647491,48.3413085938],"type":"Point"}
}