{
  "type": "Feature",
  "properties": {
    "addr:full":"Am Bahnhof 10 Haringsee Nieder\u00f6sterreich 2286",
    "addr:housenumber":"10",
    "addr:postcode":"2286",
    "addr:street":"Am Bahnhof",
    "iso:country":"AT",
    "sg:address":"Am Bahnhof 10",
    "sg:city":"Haringsee",
    "sg:orig_category":"Fleischhauereien",
    "sg:phone":"+43 2214 84089",
    "sg:postcode":"2286",
    "sg:province":"Nieder\u00f6sterreich",
    "wof:name":"Selinger Anton",
    "wof:placetype":"venue"
},
  "geometry": {"coordinates":[16.7825450897,48.1914291382],"type":"Point"}
}