{
  "type": "Feature",
  "properties": {
    "iso:country":"AT",
    "sg:address":"Bergg 6",
    "sg:city":"Wien",
    "sg:orig_category":"Restaurants: Italienisch",
    "sg:phone":"+43 1 3194262",
    "sg:postcode":"1090",
    "sg:province":"Wien",
    "wof:name":"Pizzeria Valentino",
    "wof:placetype":"venue"
},
  "geometry": {"coordinates":[16.3603286743,48.2174301147],"type":"Point"}
}