{
  "type": "Feature",
  "properties": {
    "addr:full":"Favoritenstrasse 50/10 Wien Wien 1040",
    "addr:housenumber":"50 / 10",
    "addr:postcode":"1040",
    "addr:street":"Favoritenstrasse",
    "iso:country":"AT",
    "sg:address":"Favoritenstrasse 50/10",
    "sg:city":"Wien",
    "sg:classifiers":[
        {
            "category":"Building & Trades",
            "subcategory":"Electrical",
            "type":"Services"
        }
    ],
    "sg:phone":"+43 1 50447110",
    "sg:postcode":"1040",
    "sg:province":"Wien",
    "sg:tags":[
        "engineering",
        "construction",
        "architectural",
        "software"
    ],
    "sg:website":"fm-solutions.com",
    "wof:name":"Complott Facility Management",
    "wof:placetype":"venue"
},
  "geometry": {"coordinates":[16.3721389771,48.1893768311],"type":"Point"}
}