{
  "type": "Feature",
  "properties": {
    "addr:full":"Tschapina 10 Bludenz Vorarlberg 6700",
    "addr:housenumber":"10",
    "addr:postcode":"6700",
    "addr:street":"Tschapina",
    "iso:country":"AT",
    "sg:address":"Tschapina 10",
    "sg:city":"Bludenz",
    "sg:classifiers":[
        {
            "category":"Manufacturing",
            "subcategory":"Wood Products",
            "type":"Manufacturing & Wholesale Goods"
        }
    ],
    "sg:phone":"+43 664 2663666",
    "sg:postcode":"6700",
    "sg:province":"Vorarlberg",
    "sg:tags":[
        "lumber"
    ],
    "sg:website":"alles-holz.at",
    "wof:name":"S\u00e4gewerk Andreas Fritsche",
    "wof:placetype":"venue"
},
  "geometry": {"coordinates":[5.7947201729,49.6745986938],"type":"Point"}
}