{
  "type": "Feature",
  "properties": {
    "addr:full":"Fettingerg 13 Leibnitz Steiermark 8430",
    "addr:housenumber":"13",
    "addr:postcode":"8430",
    "addr:street":"Fettingerg;Steiermark",
    "iso:country":"AT",
    "sg:address":"Fettingerg 13",
    "sg:city":"Leibnitz",
    "sg:orig_category":"Installationsunternehmen",
    "sg:phone":"+43 4334 5282047",
    "sg:postcode":"8430",
    "sg:province":"Steiermark",
    "wof:name":"Haas Walter GesmbH",
    "wof:placetype":"venue"
},
  "geometry": {"coordinates":[15.5429363251,46.7768745422],"type":"Point"}
}