{
  "type": "Feature",
  "properties": {
    "iso:country":"AT",
    "sg:address":"Mandarfen 78",
    "sg:city":"St. Leonhard im Pitztal",
    "sg:classifiers":[
        {
            "category":"Travel",
            "subcategory":"Hotels & Motels",
            "type":"Entertainment"
        }
    ],
    "sg:phone":"+43 4354 1386365",
    "sg:postcode":"6481",
    "sg:province":"Tirol",
    "sg:website":"piz-hotel.at",
    "wof:name":"Pizhotel",
    "wof:placetype":"venue"
},
  "geometry": {"coordinates":[10.8690948486,46.9701805115],"type":"Point"}
}