{
  "type": "Feature",
  "properties": {
    "addr:full":"R\u00f6merstrasse 48  Attnang-Puchheim Ober\u00f6sterreich 4800",
    "addr:housenumber":"48",
    "addr:postcode":"4800",
    "addr:street":"Roemerstrasse",
    "iso:country":"AT",
    "sg:address":"R\u00f6merstrasse 48 ",
    "sg:city":"Attnang-Puchheim",
    "sg:classifiers":[
        {
            "category":"Home & Garden",
            "subcategory":"Building Materials",
            "type":"Retail Goods"
        }
    ],
    "sg:phone":"+43 7674625430",
    "sg:postcode":"4800",
    "sg:province":"Ober\u00f6sterreich",
    "sg:tags":[
        "gravel",
        "crushed"
    ],
    "wof:name":"Niederndorfer Kieswerke - Transportbeton Ges.m.b.H.",
    "wof:placetype":"venue"
},
  "geometry": {"coordinates":[13.7204141617,48.0107002258],"type":"Point"}
}