{
  "type": "Feature",
  "properties": {
    "addr:full":"Margaretenstrasse 98 Wien Wien 1050",
    "addr:housenumber":"98",
    "addr:postcode":"1050",
    "addr:street":"Margaretenstrasse",
    "iso:country":"AT",
    "sg:address":"Margaretenstrasse 98",
    "sg:city":"Wien",
    "sg:classifiers":[
        {
            "category":"Banks & Credit Unions",
            "subcategory":"Investment Brokerage",
            "type":"Services"
        }
    ],
    "sg:phone":"+43 1 5448580",
    "sg:postcode":"1050",
    "sg:province":"Wien",
    "sg:tags":[
        "audio",
        "accessory"
    ],
    "wof:name":"Heinrich Lichtenegger Audiotuning",
    "wof:placetype":"venue"
},
  "geometry": {"coordinates":[16.3562927246,48.1895637512],"type":"Point"}
}