{
  "type": "Feature",
  "properties": {
    "addr:full":"Marktstr 4 St. Anton am Arlberg Tirol 6580",
    "addr:housenumber":"4",
    "addr:postcode":"6580",
    "addr:street":"Marktstr;Tirol",
    "iso:country":"AT",
    "sg:address":"Marktstr 4",
    "sg:city":"St. Anton am Arlberg",
    "sg:orig_category":"Unterhaltungselektronik / Einzelhandel",
    "sg:phone":"+43 5446 2307",
    "sg:postcode":"6580",
    "sg:province":"Tirol",
    "wof:name":"Audio-TV- Video-Technik Johannes Traxl",
    "wof:placetype":"venue"
},
  "geometry": {"coordinates":[10.268321991,47.130443573],"type":"Point"}
}