{
  "type": "Feature",
  "properties": {
    "addr:full":"Hauptpl 21a Schwechat Nieder\u00f6sterreich 2320",
    "addr:housenumber":"21a",
    "addr:postcode":"2320",
    "addr:street":"Hauptpl;Niederoesterreich",
    "iso:country":"AT",
    "sg:address":"Hauptpl 21a",
    "sg:city":"Schwechat",
    "sg:orig_category":"Lebensmittel / Einzelhandel",
    "sg:phone":"+43 1 7077246",
    "sg:postcode":"2320",
    "sg:province":"Nieder\u00f6sterreich",
    "wof:name":"Billa AG",
    "wof:placetype":"venue"
},
  "geometry": {"coordinates":[16.4770183563,48.1403045654],"type":"Point"}
}