{
  "type": "Feature",
  "properties": {
    "iso:country":"AT",
    "sg:address":"Steinberg 237",
    "sg:city":"Ligist",
    "sg:orig_category":"Blumeneinzelhandel",
    "sg:phone":"+43 3143 4395",
    "sg:postcode":"8563",
    "sg:province":"Steiermark",
    "wof:name":"Petra's Blumenkiosk",
    "wof:placetype":"venue"
},
  "geometry": {"coordinates":[15.2113437653,46.9924087524],"type":"Point"}
}