{
  "type": "Feature",
  "properties": {
    "addr:full":"Steyrer G 137 Graz Steiermark 8010",
    "addr:housenumber":"137",
    "addr:postcode":"8010",
    "addr:street":"Steyrer G",
    "iso:country":"AT",
    "sg:address":"Steyrer G 137",
    "sg:city":"Graz",
    "sg:orig_category":"Psychotherapie",
    "sg:phone":"+43 664 4983152",
    "sg:postcode":"8010",
    "sg:province":"Steiermark",
    "wof:name":"Palt Monika Dr",
    "wof:placetype":"venue"
},
  "geometry": {"coordinates":[15.4408960342,47.0602111816],"type":"Point"}
}