{
  "type": "Feature",
  "properties": {
    "addr:full":"Reinprechtsdorf Str 52 Wien Wien 1050",
    "addr:housenumber":"52",
    "addr:postcode":"1050",
    "addr:street":"Reinprechtsdorf Str",
    "iso:country":"AT",
    "sg:address":"Reinprechtsdorf Str 52",
    "sg:city":"Wien",
    "sg:orig_category":"Banken U Sparkassen",
    "sg:phone":"+43 5 010020051",
    "sg:postcode":"1050",
    "sg:province":"Wien",
    "wof:name":"Erste Bank d oesterreichischen Sparkassen AG",
    "wof:placetype":"venue"
},
  "geometry": {"coordinates":[16.3530273438,48.1869125366],"type":"Point"}
}