{
  "type": "Feature",
  "properties": {
    "addr:full":"Markt 65 Kirchberg am Wechsel Nieder\u00f6sterreich 2880",
    "addr:housenumber":"65",
    "addr:postcode":"2880",
    "addr:street":"Markt",
    "iso:country":"AT",
    "sg:address":"Markt 65",
    "sg:city":"Kirchberg am Wechsel",
    "sg:orig_category":"Solartechnik",
    "sg:phone":"+43 4326 4122380",
    "sg:postcode":"2880",
    "sg:province":"Nieder\u00f6sterreich",
    "wof:name":"Mitter Michael Ing",
    "wof:placetype":"venue"
},
  "geometry": {"coordinates":[15.9898548126,47.6096954346],"type":"Point"}
}