{
  "type": "Feature",
  "properties": {
    "addr:full":"Tyroliaplatz 1 Schwechat Nieder\u00f6sterreich 2320",
    "addr:housenumber":"1",
    "addr:postcode":"2320",
    "addr:street":"Tyroliaplatz;Niederoesterreich",
    "iso:country":"AT",
    "sg:address":"Tyroliaplatz 1",
    "sg:city":"Schwechat",
    "sg:orig_category":"Miscellaneous Products",
    "sg:phone":"+43 4317 01790",
    "sg:postcode":"2320",
    "sg:province":"Nieder\u00f6sterreich",
    "wof:name":"HTM SPORT- UND FREIZEIT- GER\u00c4TE AG",
    "wof:placetype":"venue"
},
  "geometry": {"coordinates":[16.48138237,48.1498756409],"type":"Point"}
}