{
  "type": "Feature",
  "properties": {
    "addr:full":"Sinnhub 39 Altenmarkt im Pongau Salzburg 5541",
    "addr:housenumber":"39",
    "addr:postcode":"5541",
    "addr:street":"Sinnhub;Salzburg",
    "iso:country":"AT",
    "sg:address":"Sinnhub 39",
    "sg:city":"Altenmarkt im Pongau",
    "sg:orig_category":"Steinmetzbetriebe",
    "sg:phone":"+43 6452 7322",
    "sg:postcode":"5541",
    "sg:province":"Salzburg",
    "wof:name":"Herzgsell Marmor Stein & Form",
    "wof:placetype":"venue"
},
  "geometry": {"coordinates":[13.4277963638,47.3848495483],"type":"Point"}
}