{
  "type": "Feature",
  "properties": {
    "iso:country":"AT",
    "sg:address":"Eisenbahnerstr 2",
    "sg:city":"St. P\u00f6lten",
    "sg:orig_category":"Non-Classified Establishments",
    "sg:phone":"+43 2742 881217",
    "sg:postcode":"3100",
    "sg:province":"Nieder\u00f6sterreich",
    "wof:name":"Pfarramt Spratzern",
    "wof:placetype":"venue"
},
  "geometry": {"coordinates":[15.6203861237,48.1700668335],"type":"Point"}
}