{
  "type": "Feature",
  "properties": {
    "iso:country":"AT",
    "sg:address":"Itzlinger Hauptstr 23",
    "sg:city":"Salzburg",
    "sg:orig_category":"Tabaktrafiken",
    "sg:phone":"+43 662 450157",
    "sg:postcode":"5020",
    "sg:province":"Salzburg",
    "wof:name":"Schmidhuber Georg",
    "wof:placetype":"venue"
},
  "geometry": {"coordinates":[13.044172287,47.8212394714],"type":"Point"}
}