{
  "type": "Feature",
  "properties": {
    "addr:full":"Neug 19 Mattersburg Burgenland 7210",
    "addr:housenumber":"19",
    "addr:postcode":"7210",
    "addr:street":"Neug",
    "iso:country":"AT",
    "sg:address":"Neug 19",
    "sg:city":"Mattersburg",
    "sg:orig_category":"Baumaschinenverleih",
    "sg:phone":"+43 664 1218312",
    "sg:postcode":"7210",
    "sg:province":"Burgenland",
    "wof:name":"Mamo Baumaschinenverleih-Deichgr\u00e4berei",
    "wof:placetype":"venue"
},
  "geometry": {"coordinates":[16.4006614685,47.7379341125],"type":"Point"}
}