{
  "type": "Feature",
  "properties": {
    "addr:full":"Eugen-Markus-Pl 5 Hollabrunn Nieder\u00f6sterreich 2020",
    "addr:housenumber":"5",
    "addr:postcode":"2020",
    "addr:street":"Eugen-Markus-Pl",
    "iso:country":"AT",
    "sg:address":"Eugen-Markus-Pl 5",
    "sg:city":"Hollabrunn",
    "sg:orig_category":"Lebensmittel / Einzelhandel",
    "sg:phone":"+43 4329 5220114",
    "sg:postcode":"2020",
    "sg:province":"Nieder\u00f6sterreich",
    "wof:name":"Bauernladen Gruberhof",
    "wof:placetype":"venue"
},
  "geometry": {"coordinates":[16.0793933868,48.565486908],"type":"Point"}
}