{
  "type": "Feature",
  "properties": {
    "iso:country":"AT",
    "sg:address":"Kaiser-Josef-Pl 23",
    "sg:city":"Wels",
    "sg:orig_category":"Banken U Sparkassen",
    "sg:phone":"+43 4372 42628810",
    "sg:postcode":"4600",
    "sg:province":"Ober\u00f6sterreich",
    "wof:name":"HYPO Ober\u00f6sterreich, O\u00f6 Landesbank AG",
    "wof:placetype":"venue"
},
  "geometry": {"coordinates":[14.0218639374,48.1587295532],"type":"Point"}
}