{
  "type": "Feature",
  "properties": {
    "addr:full":"Schrickg 1 Wien Wien 1220",
    "addr:housenumber":"1",
    "addr:postcode":"1220",
    "addr:street":"Schrickg",
    "iso:country":"AT",
    "sg:address":"Schrickg 1",
    "sg:city":"Wien",
    "sg:orig_category":"Werbeagenturen",
    "sg:phone":"+43 1 3199086",
    "sg:postcode":"1220",
    "sg:province":"Wien",
    "wof:name":"media.sales Werbe- & VertriebsgesmbH",
    "wof:placetype":"venue"
},
  "geometry": {"coordinates":[16.4382858276,48.2497787476],"type":"Point"}
}