{
  "type": "Feature",
  "properties": {
    "iso:country":"AT",
    "sg:address":"Bleiburger Str 9",
    "sg:city":"Eberndorf",
    "sg:orig_category":"Physiotherapie",
    "sg:phone":"+43 664 1817719",
    "sg:postcode":"9141",
    "sg:province":"K\u00e4rnten",
    "wof:name":"Hribar-Marko Sonja Dipl-PT",
    "wof:placetype":"venue"
},
  "geometry": {"coordinates":[14.6405639648,46.5906181335],"type":"Point"}
}