{
  "type": "Feature",
  "properties": {
    "iso:country":"AT",
    "sg:address":"Baiernstr 122a",
    "sg:city":"Graz",
    "sg:orig_category":"Ingenieurkonsulenten / Zivilingenieure",
    "sg:phone":"+43 316 59951071",
    "sg:postcode":"8020",
    "sg:province":"Steiermark",
    "wof:name":"Rossegger Wolfram Dipl-Ing Dr",
    "wof:placetype":"venue"
},
  "geometry": {"coordinates":[15.3886051178,47.061870575],"type":"Point"}
}