{
  "type": "Feature",
  "properties": {
    "addr:full":"Erzherzog-Wilhelm-Ring 50 Baden Nieder\u00f6sterreich 2500",
    "addr:housenumber":"50",
    "addr:postcode":"2500",
    "addr:street":"Erzherzog-Wilhelm-Ring;Niederoesterreich",
    "iso:country":"AT",
    "sg:address":"Erzherzog-Wilhelm-Ring 50",
    "sg:city":"Baden",
    "sg:orig_category":"Blumeneinzelhandel",
    "sg:phone":"+43 4322 5241067",
    "sg:postcode":"2500",
    "sg:province":"Nieder\u00f6sterreich",
    "wof:name":"Blumenecke Walter Oswald",
    "wof:placetype":"venue"
},
  "geometry": {"coordinates":[16.243768692,48.0111465454],"type":"Point"}
}