{
  "type": "Feature",
  "properties": {
    "iso:country":"AT",
    "sg:address":"Hauptpl 1",
    "sg:city":"Ziersdorf",
    "sg:orig_category":"Politische Parteien",
    "sg:phone":"+43 2956 3403",
    "sg:postcode":"3710",
    "sg:province":"Nieder\u00f6sterreich",
    "wof:name":"\u00d6sterreichische Volkspartei (\u00d6VP)",
    "wof:placetype":"venue"
},
  "geometry": {"coordinates":[15.9278860092,48.5275230408],"type":"Point"}
}