{
  "type": "Feature",
  "properties": {
    "iso:country":"AT",
    "sg:address":"Franzosenhausweg 49a",
    "sg:city":"Linz",
    "sg:classifiers":[
        {
            "category":"Home & Garden",
            "subcategory":"Building Materials",
            "type":"Retail Goods"
        }
    ],
    "sg:phone":"+43 4373 2773098",
    "sg:postcode":"4030",
    "sg:province":"Ober\u00f6sterreich",
    "sg:tags":[
        "baustoffe",
        "-material",
        "u"
    ],
    "wof:name":"Murexin AG Bauprodukte - Durlin Farben & Lacke",
    "wof:placetype":"venue"
},
  "geometry": {"coordinates":[14.2944555283,48.2439231873],"type":"Point"}
}