{
  "type": "Feature",
  "properties": {
    "iso:country":"AT",
    "sg:address":"Steinbergstr 47",
    "sg:city":"Wetzelsdorf",
    "sg:orig_category":"Tabaktrafiken",
    "sg:phone":"+43 316 576450",
    "sg:postcode":"8052",
    "sg:province":"Steiermark",
    "wof:name":"H\u00f6dl Markus",
    "wof:placetype":"venue"
},
  "geometry": {"coordinates":[15.3705272675,47.0531425476],"type":"Point"}
}