{
  "type": "Feature",
  "properties": {
    "iso:country":"AT",
    "sg:address":"Weixelbaum 99",
    "sg:city":"Unterpurkla",
    "sg:classifiers":[
        {
            "category":"Organizations",
            "subcategory":"Labor Organization",
            "type":"Services"
        }
    ],
    "sg:phone":"+43 3475 300500",
    "sg:postcode":"8484",
    "sg:province":"Steiermark",
    "sg:tags":[
        "aluminium",
        "door",
        "entrance",
        "system"
    ],
    "wof:name":"Mazuheli - Metalltechnik GmbH",
    "wof:placetype":"venue"
},
  "geometry": {"coordinates":[15.8910417557,46.7629318237],"type":"Point"}
}