{
  "type": "Feature",
  "properties": {
    "iso:country":"AT",
    "sg:address":"Franz Koci-Str 2/4",
    "sg:city":"Wien",
    "sg:classifiers":[
        {
            "category":"Taxi",
            "type":"Transportation"
        }
    ],
    "sg:phone":"+43 1 6893712",
    "sg:postcode":"1100",
    "sg:province":"Wien",
    "sg:tags":[
        "personentransporte",
        "u"
    ],
    "wof:name":"Walter Roland",
    "wof:placetype":"venue"
},
  "geometry": {"coordinates":[16.3968486786,48.1454124451],"type":"Point"}
}