{
  "type": "Feature",
  "properties": {
    "iso:country":"AT",
    "sg:address":"Winterburgerg 1/3",
    "sg:city":"Wien",
    "sg:orig_category":"\u00c3\u201erzte / F Allgemeinmedizin",
    "sg:phone":"+43 1 4861456",
    "sg:postcode":"1160",
    "sg:province":"Wien",
    "wof:name":"Grabner Hugo SanR Dr",
    "wof:placetype":"venue"
},
  "geometry": {"coordinates":[16.3039073944,48.2193641663],"type":"Point"}
}