{
  "type": "Feature",
  "properties": {
    "addr:full":"Vollerer Str 11 St. Georgen Salzburg 5113",
    "addr:housenumber":"11",
    "addr:postcode":"5113",
    "addr:street":"Str",
    "iso:country":"AT",
    "sg:address":"Vollerer Str 11",
    "sg:city":"St. Georgen",
    "sg:orig_category":"Transportunternehmen",
    "sg:phone":"+43 4362 727617",
    "sg:postcode":"5113",
    "sg:province":"Salzburg",
    "wof:name":"Zauner Adolf",
    "wof:placetype":"venue"
},
  "geometry": {"coordinates":[12.9121379852,47.9604072571],"type":"Point"}
}