{
  "type": "Feature",
  "properties": {
    "iso:country":"AT",
    "sg:address":"Vollerer Str 11",
    "sg:city":"St. Georgen",
    "sg:orig_category":"Transportunternehmen",
    "sg:phone":"+43 4362 727617",
    "sg:postcode":"5113",
    "sg:province":"Salzburg",
    "wof:name":"Zauner Adolf",
    "wof:placetype":"venue"
},
  "geometry": {"coordinates":[12.9121379852,47.9604072571],"type":"Point"}
}