{
  "type": "Feature",
  "properties": {
    "iso:country":"AT",
    "sg:address":"Triester Str 95",
    "sg:city":"Tribuswinkel",
    "sg:orig_category":"Autoersatzteile",
    "sg:phone":"+43 2252 46219",
    "sg:postcode":"2512",
    "sg:province":"Nieder\u00f6sterreich",
    "wof:name":"Auto-Pikard",
    "wof:placetype":"venue"
},
  "geometry": {"coordinates":[16.2891998291,47.9824180603],"type":"Point"}
}