{
  "type": "Feature",
  "properties": {
    "addr:full":"Nr 13 Arnreit Ober\u00f6sterreich 4122",
    "addr:postcode":"4122",
    "addr:street":"Nr 13",
    "iso:country":"AT",
    "sg:address":"Nr 13",
    "sg:city":"Arnreit",
    "sg:orig_category":"Institute",
    "sg:phone":"+43 7282 7711",
    "sg:postcode":"4122",
    "sg:province":"Ober\u00f6sterreich",
    "wof:name":"Lacon-Privatinst f Qualit\u00e4tssicherung und Zertifizierung GmbH",
    "wof:placetype":"venue"
},
  "geometry": {"coordinates":[13.9950246811,48.5253715515],"type":"Point"}
}