{
  "type": "Feature",
  "properties": {
    "addr:full":"R\u00f6sselm\u00fchlg 12/3 Graz Steiermark 8020",
    "addr:housenumber":"12 / 3",
    "addr:postcode":"8020",
    "addr:street":"Roesselmuehlg",
    "iso:country":"AT",
    "sg:address":"R\u00f6sselm\u00fchlg 12/3",
    "sg:city":"Graz",
    "sg:orig_category":"Behinderungen / Leben Mit Behinderungen",
    "sg:phone":"+43 316 760966",
    "sg:postcode":"8020",
    "sg:province":"Steiermark",
    "wof:name":"Jugend am Werk Steirmark GmbH Arbeitsassistenz f Menschen mit Behinderung und H\u00f6rbehinderte",
    "wof:placetype":"venue"
},
  "geometry": {"coordinates":[15.4111499786,47.0689201355],"type":"Point"}
}