{
  "type": "Feature",
  "properties": {
    "iso:country":"AT",
    "sg:address":"Marktstr 53A",
    "sg:city":"Dornbirn",
    "sg:orig_category":"Tankstellen",
    "sg:phone":"+43 4355 7224323",
    "sg:postcode":"6850",
    "sg:province":"Vorarlberg",
    "wof:name":"Esso Austria GmbH",
    "wof:placetype":"venue"
},
  "geometry": {"coordinates":[9.7424325943,47.4094848633],"type":"Point"}
}