{
  "type": "Feature",
  "properties": {
    "addr:full":"Wiener Str 7 Poysdorf Nieder\u00f6sterreich 2170",
    "addr:postcode":"2170",
    "addr:street":"Niederoesterreich",
    "iso:country":"AT",
    "sg:address":"Wiener Str 7",
    "sg:city":"Poysdorf",
    "sg:orig_category":"Glasereien",
    "sg:phone":"+43 2552 2127",
    "sg:postcode":"2170",
    "sg:province":"Nieder\u00f6sterreich",
    "wof:name":"Spiehs-Glas",
    "wof:placetype":"venue"
},
  "geometry": {"coordinates":[16.6285438538,48.6659812927],"type":"Point"}
}