{
  "type": "Feature",
  "properties": {
    "iso:country":"AT",
    "sg:address":"Ignaz-Harrer-Str 55",
    "sg:city":"Salzburg",
    "sg:orig_category":"Architekturmodellbau",
    "sg:phone":"+43 662 439111",
    "sg:postcode":"5020",
    "sg:province":"Salzburg",
    "wof:name":"modellbau kreipl d helmut",
    "wof:placetype":"venue"
},
  "geometry": {"coordinates":[13.0258264542,47.8115196228],"type":"Point"}
}