{
  "type": "Feature",
  "properties": {
    "addr:full":"Auenweg 14 Fulpmes Tirol 6166",
    "addr:housenumber":"14",
    "addr:postcode":"6166",
    "addr:street":"Auenweg;Tirol",
    "iso:country":"AT",
    "sg:address":"Auenweg 14",
    "sg:city":"Fulpmes",
    "sg:classifiers":[
        {
            "category":"Travel",
            "subcategory":"Hotels & Motels",
            "type":"Entertainment"
        }
    ],
    "sg:phone":"+43 5225 62763",
    "sg:postcode":"6166",
    "sg:province":"Tirol",
    "wof:name":"Familien- & Vitalhotel Auenhof",
    "wof:placetype":"venue"
},
  "geometry": {"coordinates":[11.3444442749,47.1432685852],"type":"Point"}
}