{
  "type": "Feature",
  "properties": {
    "addr:full":"Nr 107 Reisach K\u00e4rnten 9633",
    "addr:postcode":"9633",
    "addr:street":"Nr 107;Kaernten",
    "iso:country":"AT",
    "sg:address":"Nr 107",
    "sg:city":"Reisach",
    "sg:orig_category":"Lebensmittel / Einzelhandel",
    "sg:phone":"+43 4284 263",
    "sg:postcode":"9633",
    "sg:province":"K\u00e4rnten",
    "wof:name":"Spar Markt Inh Hans Stampfl",
    "wof:placetype":"venue"
},
  "geometry": {"coordinates":[13.154958725,46.6491584778],"type":"Point"}
}