{
  "type": "Feature",
  "properties": {
    "iso:country":"AT",
    "sg:address":"Kirchstr 35",
    "sg:city":"Fulpmes",
    "sg:orig_category":"Handelsagenturen",
    "sg:phone":"+43 5225 63687",
    "sg:postcode":"6166",
    "sg:province":"Tirol",
    "wof:name":"Busch Erich",
    "wof:placetype":"venue"
},
  "geometry": {"coordinates":[11.3502988815,47.1513786316],"type":"Point"}
}