{
  "type": "Feature",
  "properties": {
    "addr:full":"Hauptstr 12 Gloggnitz Nieder\u00f6sterreich 2640",
    "addr:housenumber":"12",
    "addr:postcode":"2640",
    "addr:street":"Hauptstr",
    "iso:country":"AT",
    "sg:address":"Hauptstr 12",
    "sg:city":"Gloggnitz",
    "sg:orig_category":"Banken U Sparkassen",
    "sg:phone":"+43 4326 62422650",
    "sg:postcode":"2640",
    "sg:province":"Nieder\u00f6sterreich",
    "wof:name":"Bankomat d Raiffeisenbank N\u00f6-S\u00fcd Alpin regGenmbH",
    "wof:placetype":"venue"
},
  "geometry": {"coordinates":[15.9380893707,47.6761360168],"type":"Point"}
}