{
  "type": "Feature",
  "properties": {
    "addr:full":"Obweg 18 Vils Tirol 6682",
    "addr:housenumber":"18",
    "addr:postcode":"6682",
    "addr:street":"Obweg;Tirol",
    "iso:country":"AT",
    "sg:address":"Obweg 18",
    "sg:city":"Vils",
    "sg:orig_category":"Rettungsdienste",
    "sg:phone":"+43 5677 8635",
    "sg:postcode":"6682",
    "sg:province":"Tirol",
    "wof:name":"Bergrettung Vils",
    "wof:placetype":"venue"
},
  "geometry": {"coordinates":[10.63285923,47.5451698303],"type":"Point"}
}