{
  "type": "Feature",
  "properties": {
    "iso:country":"AT",
    "sg:address":"Naarner Str 51",
    "sg:city":"Perg",
    "sg:orig_category":"Massagen",
    "sg:phone":"+43 676 4913504",
    "sg:postcode":"4320",
    "sg:province":"Ober\u00f6sterreich",
    "wof:name":"Six Manuela - Shiatsu",
    "wof:placetype":"venue"
},
  "geometry": {"coordinates":[14.6280288696,48.243522644],"type":"Point"}
}