{
  "type": "Feature",
  "properties": {
    "addr:full":"Alfred-Schedewy-Str 10 Teesdorf Nieder\u00f6sterreich 2524",
    "addr:housenumber":"10",
    "addr:postcode":"2524",
    "addr:street":"Alfred-Schedewy-Str",
    "iso:country":"AT",
    "sg:address":"Alfred-Schedewy-Str 10",
    "sg:city":"Teesdorf",
    "sg:orig_category":"Volksschulen",
    "sg:phone":"+43 4322 5381660",
    "sg:postcode":"2524",
    "sg:province":"Nieder\u00f6sterreich",
    "wof:name":"Volksschule f Knaben u M\u00e4dchen",
    "wof:placetype":"venue"
},
  "geometry": {"coordinates":[16.2783222198,47.9487686157],"type":"Point"}
}