{
  "type": "Feature",
  "properties": {
    "addr:full":"Waldburgstr 43 N\u00fcziders Vorarlberg 6714",
    "addr:housenumber":"43",
    "addr:postcode":"6714",
    "addr:street":"Waldburgstr",
    "iso:country":"AT",
    "sg:address":"Waldburgstr 43",
    "sg:city":"N\u00fcziders",
    "sg:orig_category":"Mess-, Steuer- U Regeltechnik",
    "sg:phone":"+43 4355 5265661",
    "sg:postcode":"6714",
    "sg:province":"Vorarlberg",
    "wof:name":"EFW-Elektronik Heinz Wolf",
    "wof:placetype":"venue"
},
  "geometry": {"coordinates":[9.807636261,47.1671142578],"type":"Point"}
}