{
  "type": "Feature",
  "properties": {
    "addr:full":"Jadorf 16 Kuchl Salzburg 5431",
    "addr:housenumber":"16",
    "addr:postcode":"5431",
    "addr:street":"Jadorf;Salzburg",
    "iso:country":"AT",
    "sg:address":"Jadorf 16",
    "sg:city":"Kuchl",
    "sg:orig_category":"Schlossereien",
    "sg:phone":"+43 6244 63770",
    "sg:postcode":"5431",
    "sg:province":"Salzburg",
    "wof:name":"Schmid Josef",
    "wof:placetype":"venue"
},
  "geometry": {"coordinates":[13.1488933563,47.6385154724],"type":"Point"}
}