{
  "type": "Feature",
  "properties": {
    "addr:full":"Rindbachstrasse 38 Ebensee Ober\u00f6sterreich 4802",
    "addr:housenumber":"38",
    "addr:postcode":"4802",
    "addr:street":"Rindbachstrasse",
    "iso:country":"AT",
    "sg:address":"Rindbachstrasse 38",
    "sg:city":"Ebensee",
    "sg:classifiers":[
        {
            "category":"Building & Trades",
            "subcategory":"Plumbing",
            "type":"Services"
        }
    ],
    "sg:phone":"+43 6133 5337",
    "sg:postcode":"4802",
    "sg:province":"Ober\u00f6sterreich",
    "sg:tags":[
        "supraregional",
        "gas"
    ],
    "wof:name":"Kienesberger Ges.m.b.H.",
    "wof:placetype":"venue"
},
  "geometry": {"coordinates":[13.7761297226,47.8093299866],"type":"Point"}
}