{
  "type": "Feature",
  "properties": {
    "addr:full":"Dr.-Theodor-K\u00f6rner-Str 22 Bruck an der Mur Steiermark 8600",
    "addr:housenumber":"22",
    "addr:postcode":"8600",
    "addr:street":"Dr.-Theodor-Koerner-Str",
    "iso:country":"AT",
    "sg:address":"Dr.-Theodor-K\u00f6rner-Str 22",
    "sg:city":"Bruck an der Mur",
    "sg:orig_category":"Blumeneinzelhandel",
    "sg:phone":"+43 4338 6281257",
    "sg:postcode":"8600",
    "sg:province":"Steiermark",
    "wof:name":"BLUMENOASE FLEUROP",
    "wof:placetype":"venue"
},
  "geometry": {"coordinates":[15.2665863037,47.409160614],"type":"Point"}
}