{
  "type": "Feature",
  "properties": {
    "addr:full":"null Logistk/Center Nr 3 Trofaiach Steiermark 8793",
    "addr:postcode":"8793",
    "iso:country":"AT",
    "sg:address":"null Logistk/Center Nr 3",
    "sg:city":"Trofaiach",
    "sg:classifiers":[
        {
            "category":"Professional",
            "subcategory":"Management & Consulting",
            "type":"Services"
        }
    ],
    "sg:phone":"+43 4367 69360421",
    "sg:postcode":"8793",
    "sg:province":"Steiermark",
    "wof:name":"LMS Logistik-Management-Service-Dr Herbert B\u00e4ck",
    "wof:placetype":"venue"
},
  "geometry": {"coordinates":[14.969628334,47.4129219055],"type":"Point"}
}