{
  "type": "Feature",
  "properties": {
    "addr:full":"Schwadorfer Str 9 Ebergassing Nieder\u00f6sterreich 2435",
    "addr:housenumber":"9",
    "addr:postcode":"2435",
    "addr:street":"Str",
    "iso:country":"AT",
    "sg:address":"Schwadorfer Str 9",
    "sg:city":"Ebergassing",
    "sg:orig_category":"Friseure U Frisiersalons",
    "sg:phone":"+43 4322 3478959",
    "sg:postcode":"2435",
    "sg:province":"Nieder\u00f6sterreich",
    "wof:name":"Haarstudio Renate Inh Sykora Renate",
    "wof:placetype":"venue"
},
  "geometry": {"coordinates":[16.520198822,48.0466804504],"type":"Point"}
}