{
  "type": "Feature",
  "properties": {
    "addr:full":"Nr 68 Vomp Tirol 6134",
    "addr:postcode":"6134",
    "addr:street":"Nr 68;Tirol",
    "iso:country":"AT",
    "sg:address":"Nr 68",
    "sg:city":"Vomp",
    "sg:orig_category":"Physiotherapie",
    "sg:phone":"+43 5242 728702",
    "sg:postcode":"6134",
    "sg:province":"Tirol",
    "wof:name":"Vital Kurinstitut Fiecht",
    "wof:placetype":"venue"
},
  "geometry": {"coordinates":[11.683139801,47.3420982361],"type":"Point"}
}