{
  "type": "Feature",
  "properties": {
    "addr:full":"Nr 51 Piesendorf Salzburg 5721",
    "addr:postcode":"5721",
    "addr:street":"Nr;Salzburg",
    "iso:country":"AT",
    "sg:address":"Nr 51",
    "sg:city":"Piesendorf",
    "sg:orig_category":"Appartements / Ferienwohnungen",
    "sg:phone":"+43 6549 74710",
    "sg:postcode":"5721",
    "sg:province":"Salzburg",
    "wof:name":"Pension Hochb\u00fcrgl",
    "wof:placetype":"venue"
},
  "geometry": {"coordinates":[12.7159004211,47.2918968201],"type":"Point"}
}