{
  "type": "Feature",
  "properties": {
    "addr:full":"Lobisserweg 9 St. Kanzian am Klopeiner See K\u00e4rnten 9122",
    "addr:housenumber":"9",
    "addr:postcode":"9122",
    "addr:street":"Lobisserweg;Kaernten",
    "iso:country":"AT",
    "sg:address":"Lobisserweg 9",
    "sg:city":"St. Kanzian am Klopeiner See",
    "sg:classifiers":[
        {
            "category":"Professional",
            "subcategory":"Advertising",
            "type":"Services"
        }
    ],
    "sg:phone":"+43 4239 2525",
    "sg:postcode":"9122",
    "sg:province":"K\u00e4rnten",
    "sg:tags":[
        "poster"
    ],
    "sg:website":"mitschedruck.at",
    "wof:name":"Druckerei Mitsche",
    "wof:placetype":"venue"
},
  "geometry": {"coordinates":[14.5374526978,46.6072502136],"type":"Point"}
}