{
  "type": "Feature",
  "properties": {
    "iso:country":"AT",
    "sg:address":"Quellenstr 1",
    "sg:city":"St. Radegund",
    "sg:classifiers":[
        {
            "category":"Health Services",
            "subcategory":"Nursing And Care Facility",
            "type":"Services"
        }
    ],
    "sg:phone":"+43 4331 3223510",
    "sg:postcode":"8061",
    "sg:province":"Steiermark",
    "sg:tags":[
        "rehabilitation"
    ],
    "wof:name":"Pensionsversicherungsanstalt - Sonderkrankenanstalt RZ St. Radegund",
    "wof:placetype":"venue"
},
  "geometry": {"coordinates":[15.4844493866,47.1812705994],"type":"Point"}
}