{
  "type": "Feature",
  "properties": {
    "addr:full":"Klostermanngasse 4 Wien Wien 1230",
    "addr:housenumber":"4",
    "addr:postcode":"1230",
    "addr:street":"Klostermanngasse",
    "iso:country":"AT",
    "sg:address":"Klostermanngasse 4",
    "sg:city":"Wien",
    "sg:classifiers":[
        {
            "category":"Building & Trades",
            "subcategory":"Construction",
            "type":"Services"
        }
    ],
    "sg:phone":"+43 1 8698759",
    "sg:postcode":"1230",
    "sg:province":"Wien",
    "sg:tags":[
        "mural"
    ],
    "wof:name":"Friedrich Wyhlidal",
    "wof:placetype":"venue"
},
  "geometry": {"coordinates":[16.2957344055,48.1432228088],"type":"Point"}
}