{
  "type": "Feature",
  "properties": {
    "addr:full":"St. Martiner Str 1 Deutschlandsberg Steiermark 8530",
    "addr:housenumber":"1",
    "addr:postcode":"8530",
    "addr:street":"St.;Str",
    "iso:country":"AT",
    "sg:address":"St. Martiner Str 1",
    "sg:city":"Deutschlandsberg",
    "sg:orig_category":"Autohandel",
    "sg:phone":"+43 3462 4760",
    "sg:postcode":"8530",
    "sg:province":"Steiermark",
    "wof:name":"Cebular Wolfgang",
    "wof:placetype":"venue"
},
  "geometry": {"coordinates":[15.222117424,46.7999038696],"type":"Point"}
}