{
  "type": "Feature",
  "properties": {
    "addr:full":"Nr 50 Semriach Steiermark 8102",
    "addr:postcode":"8102",
    "addr:street":"Nr 50",
    "iso:country":"AT",
    "sg:address":"Nr 50",
    "sg:city":"Semriach",
    "sg:orig_category":"Gemeinden",
    "sg:phone":"+43 3127 80980",
    "sg:postcode":"8102",
    "sg:province":"Steiermark",
    "wof:name":"Marktgemeinde Semriach",
    "wof:placetype":"venue"
},
  "geometry": {"coordinates":[15.4031257629,47.217502594],"type":"Point"}
}