{
  "type": "Feature",
  "properties": {
    "addr:full":"Kohlenplatzstr 12 St. Valentin Nieder\u00f6sterreich 4300",
    "addr:housenumber":"12",
    "addr:postcode":"4300",
    "addr:street":"Kohlenplatzstr",
    "iso:country":"AT",
    "sg:address":"Kohlenplatzstr 12",
    "sg:city":"St. Valentin",
    "sg:orig_category":"Unterhaltungselektronik / Reparatur",
    "sg:phone":"+43 7435 54661",
    "sg:postcode":"4300",
    "sg:province":"Nieder\u00f6sterreich",
    "wof:name":"Hausleitner Kurt",
    "wof:placetype":"venue"
},
  "geometry": {"coordinates":[14.5162611008,48.1868057251],"type":"Point"}
}