{
  "type": "Feature",
  "properties": {
    "iso:country":"AT",
    "sg:address":"Graben 28",
    "sg:city":"Linz",
    "sg:orig_category":"Friseure U Frisiersalons",
    "sg:phone":"+43 664 3778999",
    "sg:postcode":"4020",
    "sg:province":"Ober\u00f6sterreich",
    "wof:name":"InMann Goes Ahead - Marco Inmann - H-KLINIK",
    "wof:placetype":"venue"
},
  "geometry": {"coordinates":[14.2889308929,48.3049125671],"type":"Point"}
}