{
  "type": "Feature",
  "properties": {
    "addr:full":"Oberarnsdorf 46 Lamprechtshausen Salzburg 5112",
    "addr:housenumber":"46",
    "addr:postcode":"5112",
    "addr:street":"Oberarnsdorf;Salzburg",
    "iso:country":"AT",
    "sg:address":"Oberarnsdorf 46",
    "sg:city":"Lamprechtshausen",
    "sg:classifiers":[
        {
            "category":"Professional",
            "subcategory":"Printing & Photocopies",
            "type":"Services"
        }
    ],
    "sg:phone":"+43 6274 73310",
    "sg:postcode":"5112",
    "sg:province":"Salzburg",
    "sg:tags":[
        "menu",
        "folder"
    ],
    "sg:website":"reischl.at",
    "wof:name":"Reischl & Sohn Ges.m.b.H.",
    "wof:placetype":"venue"
},
  "geometry": {"coordinates":[12.9633302689,47.9721908569],"type":"Point"}
}