{
  "type": "Feature",
  "properties": {
    "iso:country":"AT",
    "sg:address":"Oberer Kirchenweg 1",
    "sg:city":"Weyer",
    "sg:orig_category":"Non-Classified Establishments",
    "sg:phone":"+43 7355 6274",
    "sg:postcode":"3335",
    "sg:province":"Ober\u00f6sterreich",
    "wof:name":"Pfarramt Weyer",
    "wof:placetype":"venue"
},
  "geometry": {"coordinates":[14.6630449295,47.8563842773],"type":"Point"}
}