{
  "type": "Feature",
  "properties": {
    "addr:full":"Wildbichler Str 33 Ebbs Tirol 6341",
    "addr:housenumber":"33",
    "addr:postcode":"6341",
    "addr:street":"Str;Tirol",
    "iso:country":"AT",
    "sg:address":"Wildbichler Str 33",
    "sg:city":"Ebbs",
    "sg:orig_category":"Freizeit- U Sportbekleidung",
    "sg:phone":"+43 4366 43426367",
    "sg:postcode":"6341",
    "sg:province":"Tirol",
    "wof:name":"Silberjack HandelsgesmbH",
    "wof:placetype":"venue"
},
  "geometry": {"coordinates":[12.2141838074,47.6299133301],"type":"Point"}
}