{
  "type": "Feature",
  "properties": {
    "iso:country":"AT",
    "sg:address":"A Schweitzer-Str 7",
    "sg:city":"Knittelfeld",
    "sg:orig_category":"Friseure U Frisiersalons",
    "sg:phone":"+43 4335 1286659",
    "sg:postcode":"8720",
    "sg:province":"Steiermark",
    "wof:name":"Hair-Studio-Helga",
    "wof:placetype":"venue"
},
  "geometry": {"coordinates":[14.8188810349,47.2075881958],"type":"Point"}
}