{
  "type": "Feature",
  "properties": {
    "iso:country":"AT",
    "sg:address":"Seilerg 6",
    "sg:city":"Innsbruck",
    "sg:orig_category":"Studentenheime",
    "sg:phone":"+43 512 59906",
    "sg:postcode":"6020",
    "sg:province":"Tirol",
    "wof:name":"Studentenheim d WIST Innsbruck - Roter Adler",
    "wof:placetype":"venue"
},
  "geometry": {"coordinates":[11.3925151825,47.2681045532],"type":"Point"}
}