{
  "type": "Feature",
  "properties": {
    "iso:country":"AT",
    "sg:address":"Bernhard-H\u00f6fel-Str 11",
    "sg:city":"Innsbruck",
    "sg:orig_category":"Bauunternehmen",
    "sg:phone":"+43 4351 233110",
    "sg:postcode":"6020",
    "sg:province":"Tirol",
    "wof:name":"Beton- u Monierbau GesmbH",
    "wof:placetype":"venue"
},
  "geometry": {"coordinates":[11.4291696548,47.2653198242],"type":"Point"}
}