{
  "type": "Feature",
  "properties": {
    "addr:full":"Nr 12 V\u00f6lkermarkt K\u00e4rnten 9100",
    "addr:postcode":"9100",
    "addr:street":"Nr 12 Voelkermarkt Kaernten",
    "iso:country":"AT",
    "sg:address":"Nr 12",
    "sg:city":"V\u00f6lkermarkt",
    "sg:orig_category":"Dachdeckereien",
    "sg:phone":"+43 4232 2918",
    "sg:postcode":"9100",
    "sg:province":"K\u00e4rnten",
    "wof:name":"Golob & Oeser Dachsysteme GesmbH",
    "wof:placetype":"venue"
},
  "geometry": {"coordinates":[14.6339902878,46.6604690552],"type":"Point"}
}