{
  "type": "Feature",
  "properties": {
    "addr:full":"Rochusmarkt 33 Wien Wien 1030",
    "addr:housenumber":"33",
    "addr:postcode":"1030",
    "addr:street":"Rochusmarkt",
    "iso:country":"AT",
    "sg:address":"Rochusmarkt 33",
    "sg:city":"Wien",
    "sg:orig_category":"Lebensmittel / Einzelhandel",
    "sg:phone":"+43 4317 107880",
    "sg:postcode":"1030",
    "sg:province":"Wien",
    "wof:name":"Arrigo - Feine Kost u Vinothek",
    "wof:placetype":"venue"
},
  "geometry": {"coordinates":[16.3874092102,48.2009086609],"type":"Point"}
}