{
  "type": "Feature",
  "properties": {
    "addr:full":"Marktpl 8 Sachsenburg K\u00e4rnten 9751",
    "addr:housenumber":"8",
    "addr:postcode":"9751",
    "addr:street":"Marktpl;Kaernten",
    "iso:country":"AT",
    "sg:address":"Marktpl 8",
    "sg:city":"Sachsenburg",
    "sg:orig_category":"Pensionen / Privatzimmer",
    "sg:phone":"+43 4769 2577",
    "sg:postcode":"9751",
    "sg:province":"K\u00e4rnten",
    "wof:name":"Lampersberger Wiltraud",
    "wof:placetype":"venue"
},
  "geometry": {"coordinates":[13.3495893478,46.8276672363],"type":"Point"}
}