{
  "type": "Feature",
  "properties": {
    "addr:full":"Hauptstr 74 Seeham Salzburg 5164",
    "addr:housenumber":"74",
    "addr:postcode":"5164",
    "addr:street":"Hauptstr;Salzburg",
    "iso:country":"AT",
    "sg:address":"Hauptstr 74",
    "sg:city":"Seeham",
    "sg:classifiers":[
        {
            "category":"Travel",
            "subcategory":"Hotels & Motels",
            "type":"Entertainment"
        }
    ],
    "sg:phone":"+43 6217 7297",
    "sg:postcode":"5164",
    "sg:province":"Salzburg",
    "wof:name":"Sporthof Wimmer",
    "wof:placetype":"venue"
},
  "geometry": {"coordinates":[13.0783433914,47.9714508057],"type":"Point"}
}