{
  "type": "Feature",
  "properties": {
    "addr:full":"Bahnhofstr 45 St. Veit an der Glan K\u00e4rnten 9300",
    "addr:housenumber":"45",
    "addr:postcode":"9300",
    "addr:street":"Bahnhofstr;Kaernten",
    "iso:country":"AT",
    "sg:address":"Bahnhofstr 45",
    "sg:city":"St. Veit an der Glan",
    "sg:orig_category":"Versicherungsunternehmen",
    "sg:phone":"+43 4212 55290",
    "sg:postcode":"9300",
    "sg:province":"K\u00e4rnten",
    "wof:name":"Generali Interunfall Versicherung AG",
    "wof:placetype":"venue"
},
  "geometry": {"coordinates":[-90.4969863892,31.8169898987],"type":"Point"}
}