{
  "type": "Feature",
  "properties": {
    "addr:full":"Maistatt 300 Schladming Steiermark 8970",
    "addr:housenumber":"300",
    "addr:postcode":"8970",
    "addr:street":"Maistatt",
    "iso:country":"AT",
    "sg:address":"Maistatt 300",
    "sg:city":"Schladming",
    "sg:orig_category":"Waren Aller Art",
    "sg:phone":"+43 4336 87234770",
    "sg:postcode":"8970",
    "sg:province":"Steiermark",
    "wof:name":"Stachlhof Gerhardter Franz",
    "wof:placetype":"venue"
},
  "geometry": {"coordinates":[13.6925163269,47.3930587769],"type":"Point"}
}