{
  "type": "Feature",
  "properties": {
    "iso:country":"AT",
    "sg:address":"Oberwang 51",
    "sg:city":"Oberwang",
    "sg:classifiers":[
        {
            "category":"Manufacturing",
            "subcategory":"Wood Products",
            "type":"Manufacturing & Wholesale Goods"
        }
    ],
    "sg:phone":"+43 6233 8514",
    "sg:postcode":"4882",
    "sg:province":"Ober\u00f6sterreich",
    "sg:tags":[
        "solid",
        "ceiling",
        "made",
        "panel"
    ],
    "wof:name":"Siegfried Hausleitner",
    "wof:placetype":"venue"
},
  "geometry": {"coordinates":[13.4359827042,47.8685035706],"type":"Point"}
}