{
  "type": "Feature",
  "properties": {
    "addr:full":"Hans-Sachs-Str 80 Wels Ober\u00f6sterreich 4600",
    "addr:housenumber":"80",
    "addr:postcode":"4600",
    "addr:street":"Hans-Sachs-Str;Oberoesterreich",
    "iso:country":"AT",
    "sg:address":"Hans-Sachs-Str 80",
    "sg:city":"Wels",
    "sg:orig_category":"Apotheken",
    "sg:phone":"+43 7242 474040",
    "sg:postcode":"4600",
    "sg:province":"Ober\u00f6sterreich",
    "wof:name":"Steinbock Apotheke",
    "wof:placetype":"venue"
},
  "geometry": {"coordinates":[14.0414400101,48.1674194336],"type":"Point"}
}