{
  "type": "Feature",
  "properties": {
    "iso:country":"AT",
    "sg:address":"Hof 437",
    "sg:city":"Alberschwende",
    "sg:orig_category":"Architekturvisualisierungen",
    "sg:phone":"+43 4355 7985738",
    "sg:postcode":"6861",
    "sg:province":"Vorarlberg",
    "sg:website":"knapp2.com",
    "wof:name":"Knapp Visualisierung Innenarchitektur",
    "wof:placetype":"venue"
},
  "geometry": {"coordinates":[9.8311910629,47.4506950378],"type":"Point"}
}