{
  "type": "Feature",
  "properties": {
    "addr:full":"Brunneng 39 Wien Wien 1160",
    "addr:housenumber":"39",
    "addr:postcode":"1160",
    "addr:street":"Brunneng",
    "iso:country":"AT",
    "sg:address":"Brunneng 39",
    "sg:city":"Wien",
    "sg:orig_category":"Fleischhauereien",
    "sg:phone":"+43 1 4088815",
    "sg:postcode":"1160",
    "sg:province":"Wien",
    "wof:name":"Feinkost am Markt",
    "wof:placetype":"venue"
},
  "geometry": {"coordinates":[16.335313797,48.2094421387],"type":"Point"}
}