{
  "type": "Feature",
  "properties": {
    "addr:full":"Guglgasse 12 Gasometer C Top 474 Wien Wien 1110",
    "addr:housenumber":"12;c;474",
    "addr:postcode":"1110",
    "addr:street":"Guglgasse;Top",
    "iso:country":"AT",
    "sg:address":"Guglgasse 12 Gasometer C Top 474",
    "sg:city":"Wien",
    "sg:orig_category":"Lebens- U Sozialberatung",
    "sg:phone":"+43 4319 202116",
    "sg:postcode":"1110",
    "sg:province":"Wien",
    "wof:name":"Tr\u00f6stl-B\u00f6hm Edith Mag - Psychoanalytisch-P\u00e4dagogische Erziehungsberaterin",
    "wof:placetype":"venue"
},
  "geometry": {"coordinates":[16.4197444916,48.1709709167],"type":"Point"}
}