{
  "type": "Feature",
  "properties": {
    "addr:full":"Kollerweg 10a Mariatrost Steiermark 8044",
    "addr:housenumber":"10a",
    "addr:postcode":"8044",
    "addr:street":"Kollerweg",
    "iso:country":"AT",
    "sg:address":"Kollerweg 10a",
    "sg:city":"Mariatrost",
    "sg:orig_category":"Finanz- U Wirtschaftsberatung",
    "sg:phone":"+43 4331 3221541",
    "sg:postcode":"8044",
    "sg:province":"Steiermark",
    "wof:name":"Ferder Rudolf",
    "wof:placetype":"venue"
},
  "geometry": {"coordinates":[15.5193653107,47.1305961609],"type":"Point"}
}