{
  "type": "Feature",
  "properties": {
    "addr:full":"E\u00dflinger Hauptstrasse 81-87 Wien Wien 1220",
    "addr:postcode":"81-87;1220",
    "addr:street":"Esslinger Hauptstrasse",
    "iso:country":"AT",
    "sg:address":"E\u00dflinger Hauptstrasse 81-87",
    "sg:city":"Wien",
    "sg:orig_category":"Cad/Cam Software",
    "sg:phone":"+43 1 77466550",
    "sg:postcode":"1220",
    "sg:province":"Wien",
    "sg:website":"comdata.at",
    "wof:name":"Comdata Systemhaus",
    "wof:placetype":"venue"
},
  "geometry": {"coordinates":[16.5228500366,48.2147521973],"type":"Point"}
}