{
  "type": "Feature",
  "properties": {
    "addr:full":"Andreas-Hofer-Str 4 Grein Ober\u00f6sterreich 4360",
    "addr:housenumber":"4",
    "addr:postcode":"4360",
    "addr:street":"Andreas-Hofer-Str",
    "iso:country":"AT",
    "sg:address":"Andreas-Hofer-Str 4",
    "sg:city":"Grein",
    "sg:orig_category":"Volkshochschulen",
    "sg:phone":"+43 4372 687527",
    "sg:postcode":"4360",
    "sg:province":"Ober\u00f6sterreich",
    "wof:name":"Volkshochschule Grein",
    "wof:placetype":"venue"
},
  "geometry": {"coordinates":[14.8636846542,48.2310752869],"type":"Point"}
}