{
  "type": "Feature",
  "properties": {
    "iso:country":"AT",
    "sg:address":"Pfongau 73",
    "sg:city":"Neumarkt am Wallersee",
    "sg:orig_category":"Speditionen",
    "sg:phone":"+43 6216 5511",
    "sg:postcode":"5202",
    "sg:province":"Salzburg",
    "wof:name":"MHM Internationale SpeditionsgesmbH",
    "wof:placetype":"venue"
},
  "geometry": {"coordinates":[13.247300148,47.9533157349],"type":"Point"}
}