{
  "type": "Feature",
  "properties": {
    "addr:full":"Julius-Hann-Str 2 St. Georgen am Steinfelde Nieder\u00f6sterreich 3151",
    "addr:housenumber":"2",
    "addr:postcode":"3151",
    "addr:street":"Julius-Hann-Str",
    "iso:country":"AT",
    "sg:address":"Julius-Hann-Str 2",
    "sg:city":"St. Georgen am Steinfelde",
    "sg:orig_category":"Fenster",
    "sg:phone":"+43 4327 42882624",
    "sg:postcode":"3151",
    "sg:province":"Nieder\u00f6sterreich",
    "wof:name":"Scherz Hubert",
    "wof:placetype":"venue"
},
  "geometry": {"coordinates":[15.6137161255,48.1494407654],"type":"Point"}
}