{
  "type": "Feature",
  "properties": {
    "iso:country":"AT",
    "sg:address":"Nr 33",
    "sg:city":"St. Georgen an der Leys",
    "sg:orig_category":"Bauunternehmen",
    "sg:phone":"+43 4374 82462440",
    "sg:postcode":"3282",
    "sg:province":"Nieder\u00f6sterreich",
    "wof:name":"Schweighofer Karl GesmbH",
    "wof:placetype":"venue"
},
  "geometry": {"coordinates":[15.2251644135,48.0312957764],"type":"Point"}
}