{
  "type": "Feature",
  "properties": {
    "iso:country":"AT",
    "sg:address":"Tigerg 14",
    "sg:city":"Wien",
    "sg:orig_category":"Forschungsinstitute",
    "sg:phone":"+43 1 4087184",
    "sg:postcode":"1080",
    "sg:province":"Wien",
    "wof:name":"Institut f Sozialanalyse",
    "wof:placetype":"venue"
},
  "geometry": {"coordinates":[16.345117569,48.2084159851],"type":"Point"}
}