{
  "type": "Feature",
  "properties": {
    "iso:country":"AT",
    "sg:address":"St. Peter Hauptstr 55",
    "sg:city":"St. Peter",
    "sg:orig_category":"Bankomat-Standorte",
    "sg:phone":"+43 316 46990",
    "sg:postcode":"8042",
    "sg:province":"Steiermark",
    "wof:name":"Bankomat d Raiffeisenbank Graz-St Peter",
    "wof:placetype":"venue"
},
  "geometry": {"coordinates":[15.4717903137,47.0571784973],"type":"Point"}
}