{
  "type": "Feature",
  "properties": {
    "iso:country":"AT",
    "sg:address":"Hauptstr 54",
    "sg:city":"Zams",
    "sg:orig_category":"Steuerberatung",
    "sg:phone":"+43 4354 4262818",
    "sg:postcode":"6511",
    "sg:province":"Tirol",
    "wof:name":"Antretter Nikolaus Mag",
    "wof:placetype":"venue"
},
  "geometry": {"coordinates":[10.5853290558,47.1552238464],"type":"Point"}
}