{
  "type": "Feature",
  "properties": {
    "addr:full":"Wiedner Hauptstr 113 Wien Wien 1050",
    "addr:housenumber":"113",
    "addr:postcode":"1050",
    "addr:street":"Hauptstr",
    "iso:country":"AT",
    "sg:address":"Wiedner Hauptstr 113",
    "sg:city":"Wien",
    "sg:orig_category":"Drucker",
    "sg:phone":"+43 1 9581933",
    "sg:postcode":"1050",
    "sg:province":"Wien",
    "wof:name":"REFILL 24 GmbH",
    "wof:placetype":"venue"
},
  "geometry": {"coordinates":[16.3619098663,48.1845626831],"type":"Point"}
}