{
  "type": "Feature",
  "properties": {
    "addr:full":"Hauptpl 18 Leoben Steiermark 8700",
    "addr:housenumber":"18",
    "addr:postcode":"8700",
    "addr:street":"Hauptpl",
    "iso:country":"AT",
    "sg:address":"Hauptpl 18",
    "sg:city":"Leoben",
    "sg:orig_category":"Bankomat-Standorte",
    "sg:phone":"+43 3842 45515",
    "sg:postcode":"8700",
    "sg:province":"Steiermark",
    "wof:name":"Bankomat d Bank f Arbeit und Wirtschaft AG",
    "wof:placetype":"venue"
},
  "geometry": {"coordinates":[15.0944347382,47.3814239502],"type":"Point"}
}