{
  "type": "Feature",
  "properties": {
    "addr:full":"Niederuntersberg 36 Schwarzach im Pongau Salzburg 5620",
    "addr:housenumber":"36",
    "addr:postcode":"5620",
    "addr:street":"Niederuntersberg;Salzburg",
    "iso:country":"AT",
    "sg:address":"Niederuntersberg 36",
    "sg:city":"Schwarzach im Pongau",
    "sg:orig_category":"Beteiligungen U Finanzierungen",
    "sg:phone":"+43 4366 43365393",
    "sg:postcode":"5620",
    "sg:province":"Salzburg",
    "wof:name":"The Win-Win Connection",
    "wof:placetype":"venue"
},
  "geometry": {"coordinates":[13.1821050644,47.3175201416],"type":"Point"}
}