{
  "type": "Feature",
  "properties": {
    "iso:country":"AT",
    "sg:address":"Hetmanekg 18",
    "sg:city":"Wien",
    "sg:orig_category":"Holzbearbeitungsmaschinen U -Werkzeuge",
    "sg:phone":"+43 1 69997630",
    "sg:postcode":"1230",
    "sg:province":"Wien",
    "wof:name":"Leitz GmbH & Co KG",
    "wof:placetype":"venue"
},
  "geometry": {"coordinates":[16.3149852753,48.132648468],"type":"Point"}
}