{
  "type": "Feature",
  "properties": {
    "addr:full":"Wiener Strasse 53 Schwechat Nieder\u00f6sterreich 2320",
    "addr:housenumber":"53",
    "addr:postcode":"2320",
    "addr:street":"Wiener Strasse;Niederoesterreich",
    "iso:country":"AT",
    "sg:address":"Wiener Strasse 53",
    "sg:city":"Schwechat",
    "sg:classifiers":[
        {
            "category":"Wholesale",
            "subcategory":"Auto Parts",
            "type":"Manufacturing & Wholesale Goods"
        }
    ],
    "sg:phone":"+43 1 7073304",
    "sg:postcode":"2320",
    "sg:province":"Nieder\u00f6sterreich",
    "sg:tags":[
        "automobile",
        "lamp",
        "illuminant"
    ],
    "wof:name":"Eduard Kucera",
    "wof:placetype":"venue"
},
  "geometry": {"coordinates":[16.4697494507,48.1451301575],"type":"Point"}
}