{
  "type": "Feature",
  "properties": {
    "iso:country":"AT",
    "sg:address":"Aug 7",
    "sg:city":"Oberpullendorf",
    "sg:orig_category":"Fenster",
    "sg:phone":"+43 4326 1243012",
    "sg:postcode":"7350",
    "sg:province":"Burgenland",
    "wof:name":"Altdorffer GesmbH",
    "wof:placetype":"venue"
},
  "geometry": {"coordinates":[16.5082492828,47.50233078],"type":"Point"}
}