{
  "type": "Feature",
  "properties": {
    "iso:country":"AT",
    "sg:address":"Wiener Str 28",
    "sg:city":"Gloggnitz",
    "sg:orig_category":"Friseure U Frisiersalons",
    "sg:phone":"+43 4326 6242290",
    "sg:postcode":"2640",
    "sg:province":"Nieder\u00f6sterreich",
    "wof:name":"Riegler Liselotte",
    "wof:placetype":"venue"
},
  "geometry": {"coordinates":[15.9438323975,47.6737213135],"type":"Point"}
}