{
  "type": "Feature",
  "properties": {
    "addr:full":"Alois Edlinger-G 17a Leoben Steiermark 8700",
    "addr:housenumber":"17a",
    "addr:postcode":"8700",
    "iso:country":"AT",
    "sg:address":"Alois Edlinger-G 17a",
    "sg:city":"Leoben",
    "sg:orig_category":"Konzertagenturen",
    "sg:phone":"+43 3842 46929",
    "sg:postcode":"8700",
    "sg:province":"Steiermark",
    "wof:name":"Katzianka Klaus Konzert- und K\u00fcnstleragentur HOTLINE",
    "wof:placetype":"venue"
},
  "geometry": {"coordinates":[15.0934648514,47.3684997559],"type":"Point"}
}