{
  "type": "Feature",
  "properties": {
    "addr:full":"Neutorg 49 Graz Steiermark 8010",
    "addr:housenumber":"49",
    "addr:postcode":"8010",
    "addr:street":"Neutorg",
    "iso:country":"AT",
    "sg:address":"Neutorg 49",
    "sg:city":"Graz",
    "sg:orig_category":"Friseure U Frisiersalons",
    "sg:phone":"+43 4366 48495206",
    "sg:postcode":"8010",
    "sg:province":"Steiermark",
    "wof:name":"Figaro Salon d Haarschneidekunst Inh Manninger Christine",
    "wof:placetype":"venue"
},
  "geometry": {"coordinates":[15.4377784729,47.0676651001],"type":"Point"}
}