{
  "type": "Feature",
  "properties": {
    "iso:country":"AT",
    "sg:address":"Ramsaustr 9",
    "sg:city":"Hof",
    "sg:orig_category":"Tischlereien",
    "sg:phone":"+43 6229 2647",
    "sg:postcode":"5322",
    "sg:province":"Salzburg",
    "wof:name":"Kanzler Wilhelm KEG",
    "wof:placetype":"venue"
},
  "geometry": {"coordinates":[13.1942806244,47.8190612793],"type":"Point"}
}