{
  "type": "Feature",
  "properties": {
    "addr:full":"Langauweg 33a Seewalchen am Attersee Ober\u00f6sterreich 4863",
    "addr:housenumber":"33a",
    "addr:postcode":"4863",
    "addr:street":"Langauweg",
    "iso:country":"AT",
    "sg:address":"Langauweg 33a",
    "sg:city":"Seewalchen am Attersee",
    "sg:classifiers":[
        {
            "category":"Structure",
            "subcategory":"Restrooms",
            "type":"Public Place"
        }
    ],
    "sg:phone":"+43 664 9267019",
    "sg:postcode":"4863",
    "sg:province":"Ober\u00f6sterreich",
    "sg:tags":[
        "equipment",
        "bath"
    ],
    "wof:name":"Fritz Schornsteiner",
    "wof:placetype":"venue"
},
  "geometry": {"coordinates":[13.5966100693,47.9562225342],"type":"Point"}
}