{
  "type": "Feature",
  "properties": {
    "iso:country":"AT",
    "sg:address":"Eichenweg 9/Grass-Haus",
    "sg:city":"Fu\u00dfach",
    "sg:orig_category":"Datenverarbeitung",
    "sg:phone":"+43 5578 770010",
    "sg:postcode":"6972",
    "sg:province":"Vorarlberg",
    "wof:name":"Adlon Datenverarbeitung GmbH",
    "wof:placetype":"venue"
},
  "geometry": {"coordinates":[-79.8480834961,39.8919715881],"type":"Point"}
}