{
  "type": "Feature",
  "properties": {
    "addr:full":"Burgtorg 122 Rottenmann Steiermark 8786",
    "addr:housenumber":"122",
    "addr:postcode":"8786",
    "addr:street":"Burgtorg",
    "iso:country":"AT",
    "sg:address":"Burgtorg 122",
    "sg:city":"Rottenmann",
    "sg:orig_category":"Non-Classified Establishments",
    "sg:phone":"+43 3614 23030",
    "sg:postcode":"8786",
    "sg:province":"Steiermark",
    "wof:name":"Pfarramt",
    "wof:placetype":"venue"
},
  "geometry": {"coordinates":[14.3583297729,47.5211982727],"type":"Point"}
}