{
  "type": "Feature",
  "properties": {
    "addr:full":"Lederergasse 23 Wien Wien 1080",
    "addr:housenumber":"23",
    "addr:postcode":"1080",
    "addr:street":"Lederergasse",
    "iso:country":"AT",
    "sg:address":"Lederergasse 23",
    "sg:city":"Wien",
    "sg:classifiers":[
        {
            "category":"Professional",
            "subcategory":"Printing & Photocopies",
            "type":"Services"
        }
    ],
    "sg:phone":"+43 4314 0210050",
    "sg:postcode":"1080",
    "sg:province":"Wien",
    "wof:name":"HERMANN BECKER",
    "wof:placetype":"venue"
},
  "geometry": {"coordinates":[16.3484039307,48.212387085],"type":"Point"}
}