{
  "type": "Feature",
  "properties": {
    "addr:full":"Postfach 39 Braunau am Inn-Ranshofen Ober\u00f6sterreich 5282",
    "addr:housenumber":"39",
    "addr:postcode":"5282",
    "addr:street":"Postfach",
    "iso:country":"AT",
    "sg:address":"Postfach 39",
    "sg:city":"Braunau am Inn-Ranshofen",
    "sg:orig_category":"Aluminiumbe- U -Verarbeitung",
    "sg:phone":"+43 7722 8012590",
    "sg:postcode":"5282",
    "sg:province":"Ober\u00f6sterreich",
    "wof:name":"AMAG service GmbH",
    "wof:placetype":"venue"
},
  "geometry": {"coordinates":[13.0155496597,48.2334632874],"type":"Point"}
}