{
  "type": "Feature",
  "properties": {
    "addr:full":"Enzing 26 Henndorf am Wallersee Salzburg 5302",
    "addr:housenumber":"26",
    "addr:postcode":"5302",
    "addr:street":"Enzing",
    "iso:country":"AT",
    "sg:address":"Enzing 26",
    "sg:city":"Henndorf am Wallersee",
    "sg:classifiers":[
        {
            "category":"Food & Beverages",
            "subcategory":"Dairy",
            "type":"Retail Goods"
        }
    ],
    "sg:phone":"+43 4362 1466310",
    "sg:postcode":"5302",
    "sg:province":"Salzburg",
    "sg:tags":[
        "product"
    ],
    "wof:name":"GEBR\u00dcDER WOERLE GES.MBH",
    "wof:placetype":"venue"
},
  "geometry": {"coordinates":[13.1848621368,47.9117012024],"type":"Point"}
}