{
  "type": "Feature",
  "properties": {
    "addr:full":"Nr 42b Mieming Tirol 6414",
    "addr:housenumber":"42b",
    "addr:postcode":"6414",
    "addr:street":"Nr;Tirol",
    "iso:country":"AT",
    "sg:address":"Nr 42b",
    "sg:city":"Mieming",
    "sg:classifiers":[
        {
            "category":"Restaurant",
            "type":"Food & Drink"
        }
    ],
    "sg:phone":"+43 4352 646227",
    "sg:postcode":"6414",
    "sg:province":"Tirol",
    "wof:name":"Atelier f Maler Bildhauer u Restauratoren",
    "wof:placetype":"venue"
},
  "geometry": {"coordinates":[11.0065221786,47.3184700012],"type":"Point"}
}