{
  "type": "Feature",
  "properties": {
    "addr:full":"Abelstr 44 Aschach an der Donau Ober\u00f6sterreich 4082",
    "addr:housenumber":"44",
    "addr:postcode":"4082",
    "addr:street":"Abelstr",
    "iso:country":"AT",
    "sg:address":"Abelstr 44",
    "sg:city":"Aschach an der Donau",
    "sg:orig_category":"Gemeinden",
    "sg:phone":"+43 7273 63550",
    "sg:postcode":"4082",
    "sg:province":"Ober\u00f6sterreich",
    "wof:name":"Gemeindeamt des Marktes Aschach a d Donau",
    "wof:placetype":"venue"
},
  "geometry": {"coordinates":[14.0248203278,48.3664169312],"type":"Point"}
}