{
  "type": "Feature",
  "properties": {
    "iso:country":"AT",
    "sg:address":"Sponheimerstr 1",
    "sg:city":"St. Veit an der Glan",
    "sg:orig_category":"Ingenieurkonsulenten / Zivilingenieure",
    "sg:phone":"+43 4212 2789",
    "sg:postcode":"9300",
    "sg:province":"K\u00e4rnten",
    "wof:name":"Ebner G\u00fcnter Dipl-Ing",
    "wof:placetype":"venue"
},
  "geometry": {"coordinates":[14.3570985794,46.76902771],"type":"Point"}
}