{
  "type": "Feature",
  "properties": {
    "addr:full":"Dorf 30 Erpfendorf Tirol 6383",
    "addr:housenumber":"30",
    "addr:postcode":"6383",
    "addr:street":"Dorf",
    "iso:country":"AT",
    "sg:address":"Dorf 30",
    "sg:city":"Erpfendorf",
    "sg:orig_category":"Tourismusinformation U -Organisationen",
    "sg:phone":"+43 4353 528150",
    "sg:postcode":"6383",
    "sg:province":"Tirol",
    "wof:name":"Tourismusverband Erpfendorf",
    "wof:placetype":"venue"
},
  "geometry": {"coordinates":[12.4777803421,47.5757026672],"type":"Point"}
}