{
  "type": "Feature",
  "properties": {
    "addr:full":"Sechshauser Str 41 Wien Wien 1150",
    "addr:postcode":"1150",
    "addr:street":"41",
    "iso:country":"AT",
    "sg:address":"Sechshauser Str 41",
    "sg:city":"Wien",
    "sg:orig_category":"Aufsperrdienste",
    "sg:phone":"+43 1 8931113",
    "sg:postcode":"1150",
    "sg:province":"Wien",
    "wof:name":"Alon's Aufsperrdienst Markus Todic",
    "wof:placetype":"venue"
},
  "geometry": {"coordinates":[16.3306522369,48.18724823],"type":"Point"}
}