{
  "type": "Feature",
  "properties": {
    "addr:full":"Loferer Str 8 Saalfelden am Steinernen Meer Salzburg 5760",
    "addr:housenumber":"8",
    "addr:postcode":"5760",
    "addr:street":"Str",
    "iso:country":"AT",
    "sg:address":"Loferer Str 8",
    "sg:city":"Saalfelden am Steinernen Meer",
    "sg:orig_category":"Schlankheitsinstitute",
    "sg:phone":"+43 6582 74333",
    "sg:postcode":"5760",
    "sg:province":"Salzburg",
    "wof:name":"Beauty Body Schlankheitsstudio Winkler Hertha",
    "wof:placetype":"venue"
},
  "geometry": {"coordinates":[12.8489990234,47.4258270264],"type":"Point"}
}