{
  "type": "Feature",
  "properties": {
    "addr:full":"Parkstr 6 Schwertberg Ober\u00f6sterreich 4311",
    "addr:housenumber":"6",
    "addr:postcode":"4311",
    "addr:street":"Parkstr",
    "iso:country":"AT",
    "sg:address":"Parkstr 6",
    "sg:city":"Schwertberg",
    "sg:orig_category":"Tabaktrafiken",
    "sg:phone":"+43 7262 62206",
    "sg:postcode":"4311",
    "sg:province":"Ober\u00f6sterreich",
    "wof:name":"Starzer Gerda",
    "wof:placetype":"venue"
},
  "geometry": {"coordinates":[14.5802516937,48.2745552063],"type":"Point"}
}