{
  "type": "Feature",
  "properties": {
    "addr:full":"Talh\u00e4uslweg 10 Hopfgarten im Brixental Tirol 6361",
    "addr:housenumber":"10",
    "addr:postcode":"6361",
    "addr:street":"Talhaeuslweg;Tirol",
    "iso:country":"AT",
    "sg:address":"Talh\u00e4uslweg 10",
    "sg:city":"Hopfgarten im Brixental",
    "sg:orig_category":"Pensionen / Privatzimmer",
    "sg:phone":"+43 5335 4143",
    "sg:postcode":"6361",
    "sg:province":"Tirol",
    "wof:name":"Farbmacher Karin und Reinhard",
    "wof:placetype":"venue"
},
  "geometry": {"coordinates":[12.1574897766,47.4497718811],"type":"Point"}
}