{
  "type": "Feature",
  "properties": {
    "addr:full":"Lassallestr 26 Wien Wien 1020",
    "addr:housenumber":"26",
    "addr:postcode":"1020",
    "addr:street":"Lassallestr",
    "iso:country":"AT",
    "sg:address":"Lassallestr 26",
    "sg:city":"Wien",
    "sg:orig_category":"Immobilienmakler",
    "sg:phone":"+43 4317 298545",
    "sg:postcode":"1020",
    "sg:province":"Wien",
    "wof:name":"DSI Dr Stange International GesmbH",
    "wof:placetype":"venue"
},
  "geometry": {"coordinates":[16.3992023468,48.2223701477],"type":"Point"}
}