{
  "type": "Feature",
  "properties": {
    "iso:country":"AT",
    "sg:address":"Kaiserstr 7",
    "sg:city":"Wien",
    "sg:orig_category":"Non-Classified Establishments",
    "sg:phone":"+43 1 52312550",
    "sg:postcode":"1070",
    "sg:province":"Wien",
    "wof:name":"Pfarramt Lazaristen Unbefleckte Empf\u00e4ngnis",
    "wof:placetype":"venue"
},
  "geometry": {"coordinates":[16.3411750793,48.1973381042],"type":"Point"}
}