{
  "type": "Feature",
  "properties": {
    "addr:full":"Sch\u00f6pfstr 41 Innsbruck Tirol 6020",
    "addr:housenumber":"41",
    "addr:postcode":"6020",
    "addr:street":"Schoepfstr;Tirol",
    "iso:country":"AT",
    "sg:address":"Sch\u00f6pfstr 41",
    "sg:city":"Innsbruck",
    "sg:orig_category":"Institute",
    "sg:phone":"+43 512 5073200",
    "sg:postcode":"6020",
    "sg:province":"Tirol",
    "wof:name":"Institut f Biostatistik d Universit\u00e4t Innsbruck",
    "wof:placetype":"venue"
},
  "geometry": {"coordinates":[11.3873643875,47.2601470947],"type":"Point"}
}