{
  "type": "Feature",
  "properties": {
    "addr:full":"Stegen 5 Vils Tirol 6682",
    "addr:housenumber":"5",
    "addr:postcode":"6682",
    "addr:street":"Stegen;Tirol",
    "iso:country":"AT",
    "sg:address":"Stegen 5",
    "sg:city":"Vils",
    "sg:orig_category":"Autospenglereien",
    "sg:phone":"+43 5677 53040",
    "sg:postcode":"6682",
    "sg:province":"Tirol",
    "wof:name":"Ausbeultechnik Christian Rofner",
    "wof:placetype":"venue"
},
  "geometry": {"coordinates":[10.6575965881,47.5494155884],"type":"Point"}
}