{
  "type": "Feature",
  "properties": {
    "iso:country":"AT",
    "sg:address":"Dorfbahnstr 62",
    "sg:city":"Serfaus",
    "sg:orig_category":"Appartements / Ferienwohnungen",
    "sg:phone":"+43 5476 62840",
    "sg:postcode":"6534",
    "sg:province":"Tirol",
    "wof:name":"Appartementhaus Pezid",
    "wof:placetype":"venue"
},
  "geometry": {"coordinates":[10.6012544632,47.0396957397],"type":"Point"}
}