{
  "type": "Feature",
  "properties": {
    "iso:country":"AT",
    "sg:address":"Sportplatzg 31",
    "sg:city":"Apetlon",
    "sg:orig_category":"Friseure U Frisiersalons",
    "sg:phone":"+43 2175 2942",
    "sg:postcode":"7143",
    "sg:province":"Burgenland",
    "wof:name":"Grieman Elfriede",
    "wof:placetype":"venue"
},
  "geometry": {"coordinates":[16.833360672,47.7409553528],"type":"Point"}
}