{
  "type": "Feature",
  "properties": {
    "addr:full":"Talstation Aspang-Markt Nieder\u00f6sterreich 2870",
    "addr:postcode":"2870",
    "addr:street":"Niederoesterreich",
    "iso:country":"AT",
    "sg:address":"Talstation",
    "sg:city":"Aspang-Markt",
    "sg:orig_category":"Bergbahnen",
    "sg:phone":"+43 4326 412383",
    "sg:postcode":"2870",
    "sg:province":"Nieder\u00f6sterreich",
    "wof:name":"St Corona Sessellift GesmbH",
    "wof:placetype":"venue"
},
  "geometry": {"coordinates":[16.090839386,47.554725647],"type":"Point"}
}