{
  "type": "Feature",
  "properties": {
    "addr:full":"Melkfeldstr 2 Matzleinsdorf Nieder\u00f6sterreich 3393",
    "addr:housenumber":"2",
    "addr:postcode":"3393",
    "addr:street":"Melkfeldstr;Niederoesterreich",
    "iso:country":"AT",
    "sg:address":"Melkfeldstr 2",
    "sg:city":"Matzleinsdorf",
    "sg:orig_category":"Spenglereien",
    "sg:phone":"+43 4327 5252420",
    "sg:postcode":"3393",
    "sg:province":"Nieder\u00f6sterreich",
    "wof:name":"P\u00f6lzl Friedrich",
    "wof:placetype":"venue"
},
  "geometry": {"coordinates":[15.2786569595,48.2035293579],"type":"Point"}
}