{
  "type": "Feature",
  "properties": {
    "iso:country":"AT",
    "sg:address":"Burgstall 12",
    "sg:city":"Mutters",
    "sg:classifiers":[
        {
            "category":"Travel",
            "subcategory":"Hotels & Motels",
            "type":"Entertainment"
        }
    ],
    "sg:phone":"+43 512 548470",
    "sg:postcode":"6162",
    "sg:province":"Tirol",
    "wof:name":"Hotel Sonnhof",
    "wof:placetype":"venue"
},
  "geometry": {"coordinates":[11.3795814514,47.2270812988],"type":"Point"}
}