{
  "type": "Feature",
  "properties": {
    "iso:country":"AT",
    "sg:address":"Bahnhofstr 53",
    "sg:city":"Gm\u00fcnd",
    "sg:orig_category":"Friseure U Frisiersalons",
    "sg:phone":"+43 2852 52461",
    "sg:postcode":"3950",
    "sg:province":"Nieder\u00f6sterreich",
    "wof:name":"Knapp Christa",
    "wof:placetype":"venue"
},
  "geometry": {"coordinates":[14.9856405258,48.7665290833],"type":"Point"}
}