{
  "type": "Feature",
  "properties": {
    "addr:full":"Lindaustr 3 Bad Ischl Ober\u00f6sterreich 4820",
    "addr:housenumber":"3",
    "addr:postcode":"4820",
    "addr:street":"Lindaustr",
    "iso:country":"AT",
    "sg:address":"Lindaustr 3",
    "sg:city":"Bad Ischl",
    "sg:classifiers":[
        {
            "category":"Professional",
            "subcategory":"Computer Services",
            "type":"Services"
        }
    ],
    "sg:phone":"+43 6132 267210",
    "sg:postcode":"4820",
    "sg:province":"Ober\u00f6sterreich",
    "sg:tags":[
        "software"
    ],
    "wof:name":"S.E.G. Informationstechnik GesmbH",
    "wof:placetype":"venue"
},
  "geometry": {"coordinates":[13.6090240479,47.7080574036],"type":"Point"}
}