{
  "type": "Feature",
  "properties": {
    "addr:full":"Enzersdorf 136 Staatz-Kautendorf Nieder\u00f6sterreich 2134",
    "addr:housenumber":"136",
    "addr:postcode":"2134",
    "addr:street":"Enzersdorf;Niederoesterreich",
    "iso:country":"AT",
    "sg:address":"Enzersdorf 136",
    "sg:city":"Staatz-Kautendorf",
    "sg:classifiers":[
        {
            "category":"Shopping",
            "subcategory":"Party Supplies",
            "type":"Retail Goods"
        }
    ],
    "sg:phone":"+43 664 1209992",
    "sg:postcode":"2134",
    "sg:province":"Nieder\u00f6sterreich",
    "sg:tags":[
        "u",
        "lichtanlagen",
        "ton-"
    ],
    "wof:name":"Stockhammer Roman",
    "wof:placetype":"venue"
},
  "geometry": {"coordinates":[16.486240387,48.6759986877],"type":"Point"}
}