{
  "type": "Feature",
  "properties": {
    "iso:country":"AT",
    "sg:address":"Universit\u00e4tsstr 13",
    "sg:city":"Innsbruck",
    "sg:orig_category":"Restaurants: Italienisch",
    "sg:phone":"+43 512 565410",
    "sg:postcode":"6020",
    "sg:province":"Tirol",
    "wof:name":"Restaurant BLAUES SCHIFF",
    "wof:placetype":"venue"
},
  "geometry": {"coordinates":[11.3979463577,47.2689781189],"type":"Point"}
}