{
  "type": "Feature",
  "properties": {
    "iso:country":"AT",
    "sg:address":"Jenseng 4",
    "sg:city":"Graz",
    "sg:orig_category":"Ingenieurkonsulenten / Zivilingenieure",
    "sg:phone":"+43 316 382820",
    "sg:postcode":"8010",
    "sg:province":"Steiermark",
    "wof:name":"Z\u00fcckert Werner Dipl-Ing",
    "wof:placetype":"venue"
},
  "geometry": {"coordinates":[15.4591426849,47.0717544556],"type":"Point"}
}