{
  "type": "Feature",
  "properties": {
    "addr:full":"Stieglh\u00f6fen 8a Eferding Ober\u00f6sterreich 4070",
    "addr:housenumber":"8a",
    "addr:postcode":"4070",
    "addr:street":"Stieglhoefen",
    "iso:country":"AT",
    "sg:address":"Stieglh\u00f6fen 8a",
    "sg:city":"Eferding",
    "sg:orig_category":"Massagen",
    "sg:phone":"+43 4372 723883",
    "sg:postcode":"4070",
    "sg:province":"Ober\u00f6sterreich",
    "wof:name":"Massage-Fachinstitut Gruber Karin",
    "wof:placetype":"venue"
},
  "geometry": {"coordinates":[14.0143060684,48.3058738708],"type":"Point"}
}