{
  "type": "Feature",
  "properties": {
    "addr:full":"Am Nordsaum 83 Traun Ober\u00f6sterreich 4050",
    "addr:housenumber":"83",
    "addr:postcode":"4050",
    "addr:street":"Am Nordsaum",
    "iso:country":"AT",
    "sg:address":"Am Nordsaum 83",
    "sg:city":"Traun",
    "sg:orig_category":"Abfallentsorgung U -Verwertung",
    "sg:phone":"+43 7229 71245",
    "sg:postcode":"4050",
    "sg:province":"Ober\u00f6sterreich",
    "wof:name":"Altstoffsammelzentrum Traun",
    "wof:placetype":"venue"
},
  "geometry": {"coordinates":[14.2417984009,48.2325172424],"type":"Point"}
}