{
  "type": "Feature",
  "properties": {
    "addr:full":"Dienerg 12 Gallneukirchen Ober\u00f6sterreich 4210",
    "addr:housenumber":"12",
    "addr:postcode":"4210",
    "addr:street":"Dienerg;Oberoesterreich",
    "iso:country":"AT",
    "sg:address":"Dienerg 12",
    "sg:city":"Gallneukirchen",
    "sg:orig_category":"Friseure U Frisiersalons",
    "sg:phone":"+43 7235 62733",
    "sg:postcode":"4210",
    "sg:province":"Ober\u00f6sterreich",
    "wof:name":"Wolfgang's Frisurenstube",
    "wof:placetype":"venue"
},
  "geometry": {"coordinates":[14.4157953262,48.3520927429],"type":"Point"}
}