{
  "type": "Feature",
  "properties": {
    "addr:full":"Dr.-Breitwieser-Str 12 Wels Ober\u00f6sterreich 4600",
    "addr:housenumber":"12",
    "addr:postcode":"4600",
    "addr:street":"Dr.-Breitwieser-Str;Oberoesterreich",
    "iso:country":"AT",
    "sg:address":"Dr.-Breitwieser-Str 12",
    "sg:city":"Wels",
    "sg:orig_category":"Tabaktrafiken",
    "sg:phone":"+43 7242 78021",
    "sg:postcode":"4600",
    "sg:province":"Ober\u00f6sterreich",
    "wof:name":"Piesl Wolfgang",
    "wof:placetype":"venue"
},
  "geometry": {"coordinates":[14.0084123611,48.1626663208],"type":"Point"}
}