{
  "type": "Feature",
  "properties": {
    "iso:country":"AT",
    "sg:address":"Gewerbestr 20",
    "sg:city":"Langenlois",
    "sg:orig_category":"Glaswaren",
    "sg:phone":"+43 2734 2267",
    "sg:postcode":"3550",
    "sg:province":"Nieder\u00f6sterreich",
    "wof:name":"Sauberer GesmbH",
    "wof:placetype":"venue"
},
  "geometry": {"coordinates":[15.6897792816,48.4700012207],"type":"Point"}
}