{
  "type": "Feature",
  "properties": {
    "addr:full":"Rosentaler Str 168 Klagenfurt K\u00e4rnten 9020",
    "addr:housenumber":"168",
    "addr:postcode":"9020",
    "addr:street":"Kaernten",
    "iso:country":"AT",
    "sg:address":"Rosentaler Str 168",
    "sg:city":"Klagenfurt",
    "sg:orig_category":"Tankstellen",
    "sg:phone":"+43 463 21463",
    "sg:postcode":"9020",
    "sg:province":"K\u00e4rnten",
    "wof:name":"Agip Austria GmbH",
    "wof:placetype":"venue"
},
  "geometry": {"coordinates":[14.2978906631,46.6056098938],"type":"Point"}
}