{
  "type": "Feature",
  "properties": {
    "addr:full":"Dr.-Stumpf-Str 2 Innsbruck Tirol 6020",
    "addr:housenumber":"2",
    "addr:postcode":"6020",
    "addr:street":"Dr.-Stumpf-Str;Tirol",
    "iso:country":"AT",
    "sg:address":"Dr.-Stumpf-Str 2",
    "sg:city":"Innsbruck",
    "sg:orig_category":"Installationsunternehmen",
    "sg:phone":"+43 512 224910",
    "sg:postcode":"6020",
    "sg:province":"Tirol",
    "wof:name":"Ortner GesmbH",
    "wof:placetype":"venue"
},
  "geometry": {"coordinates":[11.3754844666,47.2571220398],"type":"Point"}
}