{
  "type": "Feature",
  "properties": {
    "addr:full":"Torren 162 Golling an der Salzach Salzburg 5440",
    "addr:housenumber":"162",
    "addr:postcode":"5440",
    "addr:street":"Torren",
    "iso:country":"AT",
    "sg:address":"Torren 162",
    "sg:city":"Golling an der Salzach",
    "sg:classifiers":[
        {
            "category":"Shopping",
            "subcategory":"Gifts & Souvenirs",
            "type":"Retail Goods"
        }
    ],
    "sg:phone":"+43 4362 447550",
    "sg:postcode":"5440",
    "sg:province":"Salzburg",
    "wof:name":"Pliem Rainer",
    "wof:placetype":"venue"
},
  "geometry": {"coordinates":[13.1678924561,47.5982322693],"type":"Point"}
}