{
  "type": "Feature",
  "properties": {
    "addr:full":"Maisdorf 16 Wartberg an der Krems Ober\u00f6sterreich 4552",
    "addr:housenumber":"16",
    "addr:postcode":"4552",
    "addr:street":"Maisdorf",
    "iso:country":"AT",
    "sg:address":"Maisdorf 16",
    "sg:city":"Wartberg an der Krems",
    "sg:orig_category":"Geschenkartikel",
    "sg:phone":"+43 4375 8281568",
    "sg:postcode":"4552",
    "sg:province":"Ober\u00f6sterreich",
    "wof:name":"Geschenkstube am Bauernhof",
    "wof:placetype":"venue"
},
  "geometry": {"coordinates":[14.0942153931,47.9690742493],"type":"Point"}
}