{
  "type": "Feature",
  "properties": {
    "addr:full":"Berchtesgadner Str 69 Salzburg Salzburg 5020",
    "addr:housenumber":"69",
    "addr:postcode":"5020",
    "addr:street":"Str;Salzburg",
    "iso:country":"AT",
    "sg:address":"Berchtesgadner Str 69",
    "sg:city":"Salzburg",
    "sg:classifiers":[
        {
            "category":"Taxi",
            "type":"Transportation"
        }
    ],
    "sg:phone":"+43 676 4292290",
    "sg:postcode":"5020",
    "sg:province":"Salzburg",
    "sg:tags":[
        "personentransporte",
        "u"
    ],
    "wof:name":"Randorf Peter",
    "wof:placetype":"venue"
},
  "geometry": {"coordinates":[13.0413789749,47.7729301453],"type":"Point"}
}