{
  "type": "Feature",
  "properties": {
    "addr:full":"Ramsau 70 Hippach Tirol 6283",
    "addr:housenumber":"70",
    "addr:postcode":"6283",
    "addr:street":"Ramsau;Tirol",
    "iso:country":"AT",
    "sg:address":"Ramsau 70",
    "sg:city":"Hippach",
    "sg:classifiers":[
        {
            "category":"Manufacturing",
            "subcategory":"Wood Products",
            "type":"Manufacturing & Wholesale Goods"
        }
    ],
    "sg:phone":"+43 5282 4566",
    "sg:postcode":"6283",
    "sg:province":"Tirol",
    "sg:tags":[
        "made",
        "balcony"
    ],
    "sg:website":"www.zimmerei-eberl.com",
    "wof:name":"Eberl Zimmerei",
    "wof:placetype":"venue"
},
  "geometry": {"coordinates":[11.8661670685,47.2039108276],"type":"Point"}
}