{
  "type": "Feature",
  "properties": {
    "addr:full":"Pfarrpl 5 Krems an der Donau Nieder\u00f6sterreich 3500",
    "addr:housenumber":"5",
    "addr:postcode":"3500",
    "addr:street":"Pfarrpl",
    "iso:country":"AT",
    "sg:address":"Pfarrpl 5",
    "sg:city":"Krems an der Donau",
    "sg:orig_category":"Schlossereien",
    "sg:phone":"+43 2732 83931",
    "sg:postcode":"3500",
    "sg:province":"Nieder\u00f6sterreich",
    "wof:name":"Braun Josef NfG Inh Christian Braun - 1. Mobiler Aufsperrdienst",
    "wof:placetype":"venue"
},
  "geometry": {"coordinates":[15.5990724564,48.411781311],"type":"Point"}
}