{
  "type": "Feature",
  "properties": {
    "iso:country":"AT",
    "sg:address":"Vorderstadt 13",
    "sg:city":"Kitzb\u00fchel",
    "sg:orig_category":"Lederwaren / Einzelhandel",
    "sg:phone":"+43 5356 73560",
    "sg:postcode":"6370",
    "sg:province":"Tirol",
    "wof:name":"Louis Vuitton \u00f6sterreich GesmbH",
    "wof:placetype":"venue"
},
  "geometry": {"coordinates":[12.3910007477,47.4468803406],"type":"Point"}
}