{
  "type": "Feature",
  "properties": {
    "addr:full":"Villacher Str 78 St. Veit an der Glan K\u00e4rnten 9300",
    "addr:housenumber":"78",
    "addr:postcode":"9300",
    "addr:street":"Str;Kaernten",
    "iso:country":"AT",
    "sg:address":"Villacher Str 78",
    "sg:city":"St. Veit an der Glan",
    "sg:orig_category":"Pensionen / Privatzimmer",
    "sg:phone":"+43 4342 1233335",
    "sg:postcode":"9300",
    "sg:province":"K\u00e4rnten",
    "wof:name":"Steindorfer Irene",
    "wof:placetype":"venue"
},
  "geometry": {"coordinates":[14.3476028442,46.7606277466],"type":"Point"}
}