{
  "type": "Feature",
  "properties": {
    "iso:country":"AT",
    "sg:address":"Wagendorf 150a",
    "sg:city":"St. Veit am Vogau",
    "sg:orig_category":"Bauunternehmen",
    "sg:phone":"+43 4334 5324040",
    "sg:postcode":"8423",
    "sg:province":"Steiermark",
    "wof:name":"S\u00fcd-Bau Hoch- u Tiefbau GmbH",
    "wof:placetype":"venue"
},
  "geometry": {"coordinates":[15.6070804596,46.7576293945],"type":"Point"}
}