{
  "type": "Feature",
  "properties": {
    "addr:full":"Rheinstrasse 3 Feldkirch Vorarlberg 6800",
    "addr:housenumber":"3",
    "addr:postcode":"6800",
    "addr:street":"Rheinstrasse",
    "iso:country":"AT",
    "sg:address":"Rheinstrasse 3",
    "sg:city":"Feldkirch",
    "sg:classifiers":[
        {
            "category":"Building & Trades",
            "subcategory":"Electrical",
            "type":"Services"
        }
    ],
    "sg:phone":"+43 5522 713120",
    "sg:postcode":"6800",
    "sg:province":"Vorarlberg",
    "sg:tags":[
        "work",
        "installation"
    ],
    "wof:name":"Elektro Beck GmbH & Co KG",
    "wof:placetype":"venue"
},
  "geometry": {"coordinates":[9.5807008743,47.2540740967],"type":"Point"}
}