{
  "type": "Feature",
  "properties": {
    "iso:country":"AT",
    "sg:address":"Hofsteigstr 1",
    "sg:city":"Lustenau",
    "sg:orig_category":"Apotheken",
    "sg:phone":"+43 4355 77833440",
    "sg:postcode":"6890",
    "sg:province":"Vorarlberg",
    "wof:name":"Rheintal-Apotheke Magpharm Andrea-Claudia Haider",
    "wof:placetype":"venue"
},
  "geometry": {"coordinates":[9.6567173004,47.437538147],"type":"Point"}
}