{
  "type": "Feature",
  "properties": {
    "iso:country":"AT",
    "sg:address":"Praterstr 62-64",
    "sg:city":"Wien",
    "sg:orig_category":"Immobilienverwaltungen",
    "sg:phone":"+43 1 2183732",
    "sg:postcode":"1020",
    "sg:province":"Wien",
    "wof:name":"REAL ESTATE PARTNER Realit\u00e4ten & Immobilien Consulting Services GmbH",
    "wof:placetype":"venue"
},
  "geometry": {"coordinates":[16.3882236481,48.2164840698],"type":"Point"}
}