{
  "type": "Feature",
  "properties": {
    "addr:full":"Nr 192b F\u00fcrstenfeld Steiermark 8280",
    "addr:housenumber":"192b",
    "addr:postcode":"8280",
    "addr:street":"Nr",
    "iso:country":"AT",
    "sg:address":"Nr 192b",
    "sg:city":"F\u00fcrstenfeld",
    "sg:orig_category":"Bekleidung / Einzelhandel",
    "sg:phone":"+43 3382 55845",
    "sg:postcode":"8280",
    "sg:province":"Steiermark",
    "wof:name":"adessa Moden GmbH",
    "wof:placetype":"venue"
},
  "geometry": {"coordinates":[16.0748786926,47.0515441895],"type":"Point"}
}