{
  "type": "Feature",
  "properties": {
    "addr:full":"Salzburger Str 26 Haid Ober\u00f6sterreich 4053",
    "addr:housenumber":"26",
    "addr:postcode":"4053",
    "addr:street":"Salzburger Str",
    "iso:country":"AT",
    "sg:address":"Salzburger Str 26",
    "sg:city":"Haid",
    "sg:orig_category":"Kinderbetreuung",
    "sg:phone":"+43 7229 79455",
    "sg:postcode":"4053",
    "sg:province":"Ober\u00f6sterreich",
    "wof:name":"Hort der O\u00f6 Kinderfreunde",
    "wof:placetype":"venue"
},
  "geometry": {"coordinates":[14.2507419586,48.2004013062],"type":"Point"}
}