{
  "type": "Feature",
  "properties": {
    "addr:full":"Pfarrgarteng 1 Zistersdorf Nieder\u00f6sterreich 2225",
    "addr:housenumber":"1",
    "addr:postcode":"2225",
    "addr:street":"Pfarrgarteng;Niederoesterreich",
    "iso:country":"AT",
    "sg:address":"Pfarrgarteng 1",
    "sg:city":"Zistersdorf",
    "sg:orig_category":"Installationsunternehmen",
    "sg:phone":"+43 2532 2347",
    "sg:postcode":"2225",
    "sg:province":"Nieder\u00f6sterreich",
    "wof:name":"Semmler Alfred",
    "wof:placetype":"venue"
},
  "geometry": {"coordinates":[16.7601394653,48.5484619141],"type":"Point"}
}