{
  "type": "Feature",
  "properties": {
    "iso:country":"AT",
    "sg:address":"Unterradin 15",
    "sg:city":"Bludenz",
    "sg:orig_category":"Installationsunternehmen",
    "sg:phone":"+43 5552 31641",
    "sg:postcode":"6700",
    "sg:province":"Vorarlberg",
    "wof:name":"Horner Services - Manfred Horner",
    "wof:placetype":"venue"
},
  "geometry": {"coordinates":[9.8793878555,47.1443862915],"type":"Point"}
}