{
  "type": "Feature",
  "properties": {
    "iso:country":"AT",
    "sg:address":"Moosstr 9",
    "sg:city":"Mattighofen",
    "sg:classifiers":[
        {
            "category":"Restaurant",
            "type":"Food & Drink"
        }
    ],
    "sg:phone":"+43 4377 4231531",
    "sg:postcode":"5230",
    "sg:province":"Ober\u00f6sterreich",
    "sg:tags":[
        "pizzeria"
    ],
    "wof:name":"Pizzeria PORTOFINO",
    "wof:placetype":"venue"
},
  "geometry": {"coordinates":[13.1457948685,48.102481842],"type":"Point"}
}