{
  "type": "Feature",
  "properties": {
    "iso:country":"AT",
    "sg:address":"Walfischg 6/1",
    "sg:city":"Wien",
    "sg:orig_category":"Digitaldruck",
    "sg:phone":"+43 4315 128855",
    "sg:postcode":"1010",
    "sg:province":"Wien",
    "sg:website":"mbe.at",
    "wof:name":"Mail Boxes ETC",
    "wof:placetype":"venue"
},
  "geometry": {"coordinates":[16.3711128235,48.2032775879],"type":"Point"}
}