{
  "type": "Feature",
  "properties": {
    "iso:country":"AT",
    "sg:address":"Sallingberg 35",
    "sg:city":"Sallingberg",
    "sg:classifiers":[
        {
            "category":"Arts & Performance",
            "subcategory":"Art Gallery",
            "type":"Entertainment"
        }
    ],
    "sg:phone":"+43 2877 7117",
    "sg:postcode":"3525",
    "sg:province":"Nieder\u00f6sterreich",
    "sg:tags":[
        "painting"
    ],
    "wof:name":"Franz Maierhofer",
    "wof:placetype":"venue"
},
  "geometry": {"coordinates":[15.2366504669,48.4642105103],"type":"Point"}
}