{
  "type": "Feature",
  "properties": {
    "iso:country":"AT",
    "sg:address":"Landstrasser Hauptstr. 71",
    "sg:city":"Wien",
    "sg:classifiers":[
        {
            "category":"Professional",
            "subcategory":"Computer Services",
            "type":"Services"
        }
    ],
    "sg:phone":"+43 4317 11820",
    "sg:postcode":"1030",
    "sg:province":"Wien",
    "sg:tags":[
        "information",
        "technology"
    ],
    "wof:name":"APPLE COMPUTER GMBH",
    "wof:placetype":"venue"
},
  "geometry": {"coordinates":[16.3928337097,48.2008285522],"type":"Point"}
}