{
  "type": "Feature",
  "properties": {
    "addr:full":"Siedlung 1 Haugsdorf Nieder\u00f6sterreich 2054",
    "addr:housenumber":"1",
    "addr:postcode":"2054",
    "addr:street":"Siedlung",
    "iso:country":"AT",
    "sg:address":"Siedlung 1",
    "sg:city":"Haugsdorf",
    "sg:orig_category":"Rettungsdienste",
    "sg:phone":"+43 2944 2544",
    "sg:postcode":"2054",
    "sg:province":"Nieder\u00f6sterreich",
    "wof:name":"Rotes Kreuz \u00f6sterr Ortsstelle Haugsdorf",
    "wof:placetype":"venue"
},
  "geometry": {"coordinates":[16.0809173584,48.7063293457],"type":"Point"}
}