{
  "type": "Feature",
  "properties": {
    "addr:full":"Mariahilfer Str 127 Wien Wien 1060",
    "addr:housenumber":"127",
    "addr:postcode":"1060",
    "iso:country":"AT",
    "sg:address":"Mariahilfer Str 127",
    "sg:city":"Wien",
    "sg:classifiers":[
        {
            "category":"Restaurant",
            "type":"Food & Drink"
        }
    ],
    "sg:phone":"+43 1 5951155",
    "sg:postcode":"1060",
    "sg:province":"Wien",
    "wof:name":"Yellow",
    "wof:placetype":"venue"
},
  "geometry": {"coordinates":[16.340385437,48.1958007812],"type":"Point"}
}