{
  "type": "Feature",
  "properties": {
    "iso:country":"AT",
    "sg:address":"Dr.-Auner-Str 8",
    "sg:city":"Raaba",
    "sg:classifiers":[
        {
            "category":"Professional",
            "type":"Services"
        }
    ],
    "sg:phone":"+43 4331 640024184",
    "sg:postcode":"8074",
    "sg:province":"Steiermark",
    "sg:tags":[
        "leasing"
    ],
    "wof:name":"Raiffeisen-Leasing GmbH Landesgesch\u00e4ftsstelle Steiermark",
    "wof:placetype":"venue"
},
  "geometry": {"coordinates":[15.4922428131,47.0282249451],"type":"Point"}
}