{
  "type": "Feature",
  "properties": {
    "iso:country":"AT",
    "sg:address":"Favoritenstr 93",
    "sg:city":"Wien",
    "sg:orig_category":"Marketingberatung",
    "sg:phone":"+43 1 6068040",
    "sg:postcode":"1100",
    "sg:province":"Wien",
    "wof:name":"Human Media Marketing und Verlag GmbH",
    "wof:placetype":"venue"
},
  "geometry": {"coordinates":[16.3762798309,48.1794090271],"type":"Point"}
}