{
  "type": "Feature",
  "properties": {
    "addr:full":"Carl-Michael-Ziehrer-G 4 Felixdorf Nieder\u00f6sterreich 2603",
    "addr:housenumber":"4",
    "addr:postcode":"2603",
    "addr:street":"Carl-Michael-Ziehrer-G",
    "iso:country":"AT",
    "sg:address":"Carl-Michael-Ziehrer-G 4",
    "sg:city":"Felixdorf",
    "sg:orig_category":"Glasereien",
    "sg:phone":"+43 4326 2861449",
    "sg:postcode":"2603",
    "sg:province":"Nieder\u00f6sterreich",
    "wof:name":"G\u00fcney KEG",
    "wof:placetype":"venue"
},
  "geometry": {"coordinates":[16.232257843,47.8748703003],"type":"Point"}
}