{
  "type": "Feature",
  "properties": {
    "addr:full":"Max-Kleinoscheg-G 11 M\u00fcrzzuschlag Steiermark 8680",
    "addr:housenumber":"11",
    "addr:postcode":"8680",
    "addr:street":"Max-Kleinoscheg-G",
    "iso:country":"AT",
    "sg:address":"Max-Kleinoscheg-G 11",
    "sg:city":"M\u00fcrzzuschlag",
    "sg:orig_category":"Restaurants: Chinesisch",
    "sg:phone":"+43 3852 5133",
    "sg:postcode":"8680",
    "sg:province":"Steiermark",
    "wof:name":"China-Restaurant",
    "wof:placetype":"venue"
},
  "geometry": {"coordinates":[15.6756210327,47.6069297791],"type":"Point"}
}