{
  "type": "Feature",
  "properties": {
    "addr:full":"Hippgasse 6 Wien Wien 1160",
    "addr:housenumber":"6",
    "addr:postcode":"1160",
    "addr:street":"Hippgasse",
    "iso:country":"AT",
    "sg:address":"Hippgasse 6",
    "sg:city":"Wien",
    "sg:classifiers":[
        {
            "category":"Building & Trades",
            "subcategory":"Construction",
            "type":"Services"
        }
    ],
    "sg:phone":"+43 1 4920022",
    "sg:postcode":"1160",
    "sg:province":"Wien",
    "sg:tags":[
        "interior",
        "work"
    ],
    "wof:name":"Boguslaw Slemp Ges.m.b.H.",
    "wof:placetype":"venue"
},
  "geometry": {"coordinates":[16.3358783722,48.2047271729],"type":"Point"}
}