{
  "type": "Feature",
  "properties": {
    "addr:full":"Zitternberg 29 Gars am Kamp Nieder\u00f6sterreich 3571",
    "addr:housenumber":"29",
    "addr:postcode":"3571",
    "addr:street":"Zitternberg",
    "iso:country":"AT",
    "sg:address":"Zitternberg 29",
    "sg:city":"Gars am Kamp",
    "sg:orig_category":"Altwaren",
    "sg:phone":"+43 2985 30533",
    "sg:postcode":"3571",
    "sg:province":"Nieder\u00f6sterreich",
    "wof:name":"Ohrfandl Stefanie",
    "wof:placetype":"venue"
},
  "geometry": {"coordinates":[15.6673746109,48.5854759216],"type":"Point"}
}