{
  "type": "Feature",
  "properties": {
    "addr:full":"Nr 98 Dalaas Vorarlberg 6752",
    "addr:postcode":"6752",
    "addr:street":"Nr 98",
    "iso:country":"AT",
    "sg:address":"Nr 98",
    "sg:city":"Dalaas",
    "sg:orig_category":"Tischlereien",
    "sg:phone":"+43 5585 7258",
    "sg:postcode":"6752",
    "sg:province":"Vorarlberg",
    "sg:website":"www.tischlerei-duenser.at",
    "wof:name":"D\u00fcnser Martin",
    "wof:placetype":"venue"
},
  "geometry": {"coordinates":[9.9998960495,47.1229896545],"type":"Point"}
}