{
  "type": "Feature",
  "properties": {
    "addr:full":"Moosmahdstr 19b Dornbirn Vorarlberg 6850",
    "addr:housenumber":"19b",
    "addr:postcode":"6850",
    "addr:street":"Moosmahdstr",
    "iso:country":"AT",
    "sg:address":"Moosmahdstr 19b",
    "sg:city":"Dornbirn",
    "sg:orig_category":"Installationsunternehmen",
    "sg:phone":"+43 4355 72228730",
    "sg:postcode":"6850",
    "sg:province":"Vorarlberg",
    "wof:name":"Thurnher Installationen GesmbH",
    "wof:placetype":"venue"
},
  "geometry": {"coordinates":[9.7354640961,47.4120330811],"type":"Point"}
}