{
  "type": "Feature",
  "properties": {
    "iso:country":"AT",
    "sg:address":"Nr 75",
    "sg:city":"St. Michael",
    "sg:orig_category":"Installationsunternehmen",
    "sg:phone":"+43 4343 5261950",
    "sg:postcode":"9411",
    "sg:province":"K\u00e4rnten",
    "wof:name":"Hartl u Melcher GmbH & Co KG",
    "wof:placetype":"venue"
},
  "geometry": {"coordinates":[14.8000583649,46.8348121643],"type":"Point"}
}