{
  "type": "Feature",
  "properties": {
    "addr:full":"Nr 24a St. Veit am Vogau Steiermark 8423",
    "addr:postcode":"8423",
    "addr:street":"Nr 24A",
    "iso:country":"AT",
    "sg:address":"Nr 24a",
    "sg:city":"St. Veit am Vogau",
    "sg:orig_category":"Banken U Sparkassen",
    "sg:phone":"+43 4334 5324320",
    "sg:postcode":"8423",
    "sg:province":"Steiermark",
    "wof:name":"Bankomat d Raiffeisenbank Spielfeld-Stra\u00df regGenmbH",
    "wof:placetype":"venue"
},
  "geometry": {"coordinates":[15.6265096664,46.7477264404],"type":"Point"}
}