{
  "type": "Feature",
  "properties": {
    "addr:full":"Feldg 10 Oberwaltersdorf Nieder\u00f6sterreich 2522",
    "addr:housenumber":"10",
    "addr:postcode":"2522",
    "addr:street":"Feldg",
    "iso:country":"AT",
    "sg:address":"Feldg 10",
    "sg:city":"Oberwaltersdorf",
    "sg:orig_category":"Tischlereien",
    "sg:phone":"+43 2253 6509",
    "sg:postcode":"2522",
    "sg:province":"Nieder\u00f6sterreich",
    "wof:name":"Kethelyi Karl",
    "wof:placetype":"venue"
},
  "geometry": {"coordinates":[16.3228302002,47.9767494202],"type":"Point"}
}