{
  "type": "Feature",
  "properties": {
    "iso:country":"AT",
    "sg:address":"Nr 26",
    "sg:city":"Breitenau am Hochlantsch",
    "sg:orig_category":"Lebensmittel / Einzelhandel",
    "sg:phone":"+43 3866 51150",
    "sg:postcode":"8614",
    "sg:province":"Steiermark",
    "wof:name":"Kopatsch Gerhard",
    "wof:placetype":"venue"
},
  "geometry": {"coordinates":[15.428899765,47.3905715942],"type":"Point"}
}