{
  "type": "Feature",
  "properties": {
    "addr:full":"Hauptstrasse 30 Stixneusiedl Nieder\u00f6sterreich 2463",
    "addr:housenumber":"30",
    "addr:postcode":"2463",
    "addr:street":"Hauptstrasse;Niederoesterreich",
    "iso:country":"AT",
    "sg:address":"Hauptstrasse 30",
    "sg:city":"Stixneusiedl",
    "sg:classifiers":[
        {
            "category":"Home & Garden",
            "subcategory":"Furniture",
            "type":"Retail Goods"
        }
    ],
    "sg:phone":"+43 2169 2271",
    "sg:postcode":"2463",
    "sg:province":"Nieder\u00f6sterreich",
    "sg:tags":[
        "solid",
        "wood",
        "made",
        "childrens"
    ],
    "wof:name":"Hubert Umprecht GmbH",
    "wof:placetype":"venue"
},
  "geometry": {"coordinates":[16.6741123199,48.0423812866],"type":"Point"}
}