{
  "type": "Feature",
  "properties": {
    "addr:full":"Am Buchenhain 11 Bodensdorf K\u00e4rnten 9551",
    "addr:housenumber":"11",
    "addr:postcode":"9551",
    "addr:street":"Am Buchenhain;Kaernten",
    "iso:country":"AT",
    "sg:address":"Am Buchenhain 11",
    "sg:city":"Bodensdorf",
    "sg:orig_category":"Appartements / Ferienwohnungen",
    "sg:phone":"+43 4243 488",
    "sg:postcode":"9551",
    "sg:province":"K\u00e4rnten",
    "wof:name":"Reichmann Ewald",
    "wof:placetype":"venue"
},
  "geometry": {"coordinates":[13.9706993103,46.6813430786],"type":"Point"}
}