{
  "type": "Feature",
  "properties": {
    "iso:country":"AT",
    "sg:address":"Bahnhofstr",
    "sg:city":"Seefeld in Tirol",
    "sg:orig_category":"Bars-Cafes",
    "sg:phone":"+43 5212 22580",
    "sg:postcode":"6100",
    "sg:province":"Tirol",
    "wof:name":"Cafe-Bar Fledermaus",
    "wof:placetype":"venue"
},
  "geometry": {"coordinates":[11.1881904602,47.3288803101],"type":"Point"}
}