{
  "type": "Feature",
  "properties": {
    "addr:full":"Sonnleithengasse 5 Schleinbach Nieder\u00f6sterreich 2123",
    "addr:housenumber":"5",
    "addr:postcode":"2123",
    "addr:street":"Sonnleithengasse",
    "iso:country":"AT",
    "sg:address":"Sonnleithengasse 5",
    "sg:city":"Schleinbach",
    "sg:classifiers":[
        {
            "category":"Arts & Performance",
            "subcategory":"Music",
            "type":"Entertainment"
        }
    ],
    "sg:phone":"+43 2245 6319",
    "sg:postcode":"2123",
    "sg:province":"Nieder\u00f6sterreich",
    "sg:tags":[
        "sound",
        "studios",
        "production"
    ],
    "sg:website":"otahal.at",
    "wof:name":"Herbert OTAHAL KEG",
    "wof:placetype":"venue"
},
  "geometry": {"coordinates":[16.4741096497,48.4203834534],"type":"Point"}
}