{
  "type": "Feature",
  "properties": {
    "iso:country":"AT",
    "sg:address":"Nr 4",
    "sg:city":"Trebesing",
    "sg:orig_category":"Appartements / Ferienwohnungen",
    "sg:phone":"+43 4732 4055",
    "sg:postcode":"9852",
    "sg:province":"K\u00e4rnten",
    "wof:name":"Simonbauer",
    "wof:placetype":"venue"
},
  "geometry": {"coordinates":[13.5098352432,46.8834381104],"type":"Point"}
}