{
  "type": "Feature",
  "properties": {
    "iso:country":"AT",
    "sg:address":"Hannoverg 7",
    "sg:city":"Wien",
    "sg:orig_category":"Friseurbedarf",
    "sg:phone":"+43 4313 338503",
    "sg:postcode":"1200",
    "sg:province":"Wien",
    "wof:name":"Roma Friseurbedarf",
    "wof:placetype":"venue"
},
  "geometry": {"coordinates":[16.3692054749,48.2298812866],"type":"Point"}
}