{
  "type": "Feature",
  "properties": {
    "addr:full":"Nr 40 Mischendorf Burgenland 7511",
    "addr:postcode":"7511",
    "addr:street":"Nr;Mischendorf",
    "iso:country":"AT",
    "sg:address":"Nr 40",
    "sg:city":"Mischendorf",
    "sg:orig_category":"Non-Classified Establishments",
    "sg:phone":"+43 3366 78246",
    "sg:postcode":"7511",
    "sg:province":"Burgenland",
    "wof:name":"Pfarramt r\u00f6m kath",
    "wof:placetype":"venue"
},
  "geometry": {"coordinates":[16.313615799,47.1943016052],"type":"Point"}
}