{
  "type": "Feature",
  "properties": {
    "addr:full":"Atzmanning 3 Wernstein am Inn Ober\u00f6sterreich 4783",
    "addr:housenumber":"3",
    "addr:postcode":"4783",
    "addr:street":"Atzmanning",
    "iso:country":"AT",
    "sg:address":"Atzmanning 3",
    "sg:city":"Wernstein am Inn",
    "sg:classifiers":[
        {
            "category":"Banks & Credit Unions",
            "subcategory":"Investment Brokerage",
            "type":"Services"
        }
    ],
    "sg:phone":"+43 7712 29580",
    "sg:postcode":"4783",
    "sg:province":"Ober\u00f6sterreich",
    "sg:tags":[
        "machine",
        "plant",
        "manufacturing",
        "brick",
        "clinker"
    ],
    "sg:website":"www.zsm.at",
    "wof:name":"Z-S-M Maschinen- & Metallbau GmbH",
    "wof:placetype":"venue"
},
  "geometry": {"coordinates":[13.460269928,48.5087356567],"type":"Point"}
}