{
  "type": "Feature",
  "properties": {
    "addr:full":"Albenedt 14 Vorchdorf Ober\u00f6sterreich 4655",
    "addr:housenumber":"14",
    "addr:postcode":"4655",
    "addr:street":"Albenedt",
    "iso:country":"AT",
    "sg:address":"Albenedt 14",
    "sg:city":"Vorchdorf",
    "sg:orig_category":"Gartenpflege",
    "sg:phone":"+43 76146587",
    "sg:postcode":"4655",
    "sg:province":"Ober\u00f6sterreich",
    "wof:name":"Preinsdorfer Karl",
    "wof:placetype":"venue"
},
  "geometry": {"coordinates":[13.978058815,47.9972572327],"type":"Point"}
}