{
  "type": "Feature",
  "properties": {
    "addr:full":"Bozener Str 18 Graz Steiermark 8020",
    "addr:housenumber":"18",
    "addr:postcode":"8020",
    "addr:street":"Str",
    "iso:country":"AT",
    "sg:address":"Bozener Str 18",
    "sg:city":"Graz",
    "sg:orig_category":"Gesundheit / Allgemeine Informationsstellen",
    "sg:phone":"+43 316 262278",
    "sg:postcode":"8020",
    "sg:province":"Steiermark",
    "wof:name":"Hypoxi Studio Graz",
    "wof:placetype":"venue"
},
  "geometry": {"coordinates":[15.4255123138,47.0503616333],"type":"Point"}
}