{
  "type": "Feature",
  "properties": {
    "addr:full":"Wagramer Strasse 55-61  Wien Wien 1220",
    "addr:postcode":"55-61;1220",
    "addr:street":"Wagramer Strasse",
    "iso:country":"AT",
    "sg:address":"Wagramer Strasse 55-61 ",
    "sg:city":"Wien",
    "sg:classifiers":[
        {
            "category":"Government",
            "subcategory":"Fire Station",
            "type":"Public Place"
        }
    ],
    "sg:phone":"+43 1 20418190",
    "sg:postcode":"1220",
    "sg:province":"Wien",
    "sg:tags":[
        "supraregional",
        "plant",
        "installation",
        "heating"
    ],
    "sg:website":"www.uhrmann.at",
    "wof:name":"H. Uhrmann Ges.m.b.H.",
    "wof:placetype":"venue"
},
  "geometry": {"coordinates":[16.4672641754,48.2718505859],"type":"Point"}
}