{
  "type": "Feature",
  "properties": {
    "addr:full":"Siggerwiesen 69 Bergheim Salzburg 5101",
    "addr:housenumber":"69",
    "addr:postcode":"5101",
    "addr:street":"Siggerwiesen;Salzburg",
    "iso:country":"AT",
    "sg:address":"Siggerwiesen 69",
    "sg:city":"Bergheim",
    "sg:orig_category":"Gartenbaubedarf",
    "sg:phone":"+43 662 4521910",
    "sg:postcode":"5101",
    "sg:province":"Salzburg",
    "sg:website":"kardeis.at",
    "wof:name":"Kardeis Rudolf Ing",
    "wof:placetype":"venue"
},
  "geometry": {"coordinates":[13.0071077347,47.8597640991],"type":"Point"}
}