{
  "type": "Feature",
  "properties": {
    "addr:full":"Bachfeldg 23 Lieboch Steiermark 8501",
    "addr:housenumber":"23",
    "addr:postcode":"8501",
    "addr:street":"Bachfeldg",
    "iso:country":"AT",
    "sg:address":"Bachfeldg 23",
    "sg:city":"Lieboch",
    "sg:orig_category":"Fenster",
    "sg:phone":"+43 4366 41448525",
    "sg:postcode":"8501",
    "sg:province":"Steiermark",
    "sg:website":"persch-lieboch.at",
    "wof:name":"Persch KEG",
    "wof:placetype":"venue"
},
  "geometry": {"coordinates":[15.333234787,46.9810523987],"type":"Point"}
}