{
  "type": "Feature",
  "properties": {
    "addr:full":"Wiener Str 3 Stegersbach Burgenland 7551",
    "addr:postcode":"7551",
    "iso:country":"AT",
    "sg:address":"Wiener Str 3",
    "sg:city":"Stegersbach",
    "sg:orig_category":"Autoreparatur",
    "sg:phone":"+43 3326 523720",
    "sg:postcode":"7551",
    "sg:province":"Burgenland",
    "wof:name":"Mandler Franz",
    "wof:placetype":"venue"
},
  "geometry": {"coordinates":[16.1650180817,47.1610336304],"type":"Point"}
}