{
  "type": "Feature",
  "properties": {
    "addr:full":"Lacknerstr 23 Wels Ober\u00f6sterreich 4600",
    "addr:housenumber":"23",
    "addr:postcode":"4600",
    "addr:street":"Lacknerstr;Oberoesterreich",
    "iso:country":"AT",
    "sg:address":"Lacknerstr 23",
    "sg:city":"Wels",
    "sg:orig_category":"Ingenieurkonsulenten / Zivilingenieure",
    "sg:phone":"+43 7242 423000",
    "sg:postcode":"4600",
    "sg:province":"Ober\u00f6sterreich",
    "wof:name":"Verkehrsplanung Kleiner Dipl-Ing Joachim Kleiner",
    "wof:placetype":"venue"
},
  "geometry": {"coordinates":[13.9797306061,48.1792755127],"type":"Point"}
}