{
  "type": "Feature",
  "properties": {
    "addr:full":"G\u00fcnser Str 3 Mannersdorf an der Rabnitz Burgenland 7444",
    "addr:housenumber":"3",
    "addr:postcode":"7444",
    "addr:street":"Str",
    "iso:country":"AT",
    "sg:address":"G\u00fcnser Str 3",
    "sg:city":"Mannersdorf an der Rabnitz",
    "sg:orig_category":"Maler, Anstreicher U Lackierer",
    "sg:phone":"+43 4326 112344",
    "sg:postcode":"7444",
    "sg:province":"Burgenland",
    "wof:name":"Kollerits Johann",
    "wof:placetype":"venue"
},
  "geometry": {"coordinates":[16.5280208588,47.428894043],"type":"Point"}
}