{
  "type": "Feature",
  "properties": {
    "iso:country":"AT",
    "sg:address":"Donaustrasse 60",
    "sg:city":"Maria Enzersdorf",
    "sg:classifiers":[
        {
            "category":"Professional",
            "subcategory":"Testing Lab",
            "type":"Services"
        }
    ],
    "sg:phone":"+43 2236 864073",
    "sg:postcode":"2344",
    "sg:province":"Nieder\u00f6sterreich",
    "sg:tags":[
        "test",
        "leak",
        "stand"
    ],
    "wof:name":"Wiehsb\u00f6ck KG",
    "wof:placetype":"venue"
},
  "geometry": {"coordinates":[16.3056716919,48.0987281799],"type":"Point"}
}