{
  "type": "Feature",
  "properties": {
    "iso:country":"AT",
    "sg:address":"Moosmahdstr 19a",
    "sg:city":"Dornbirn",
    "sg:orig_category":"Videotheken",
    "sg:phone":"+43 5572 21924",
    "sg:postcode":"6850",
    "sg:province":"Vorarlberg",
    "sg:website":"vhz.at",
    "wof:name":"VHZ Video & Hifi Z Medien + Hifi Fachgesch\u00e4ft",
    "wof:placetype":"venue"
},
  "geometry": {"coordinates":[9.7354640961,47.4120330811],"type":"Point"}
}