{
  "type": "Feature",
  "properties": {
    "addr:full":"Fl\u00f6tzerweg 150 Linz Ober\u00f6sterreich 4030",
    "addr:housenumber":"150",
    "addr:postcode":"4030",
    "iso:country":"AT",
    "sg:address":"Fl\u00f6tzerweg 150",
    "sg:city":"Linz",
    "sg:classifiers":[
        {
            "category":"Internet Cafe",
            "subcategory":"None",
            "type":"Food & Drink"
        }
    ],
    "sg:phone":"+43 732 370700",
    "sg:postcode":"4030",
    "sg:province":"Ober\u00f6sterreich",
    "wof:name":"LinzNet Internet Service Provider GmbH",
    "wof:placetype":"venue"
},
  "geometry": {"coordinates":[14.2798404694,48.248085022],"type":"Point"}
}