{
  "type": "Feature",
  "properties": {
    "addr:full":"Am Reitweg 5 Wiener Neustadt Nieder\u00f6sterreich 2700",
    "addr:housenumber":"5",
    "addr:postcode":"2700",
    "addr:street":"Am Reitweg",
    "iso:country":"AT",
    "sg:address":"Am Reitweg 5",
    "sg:city":"Wiener Neustadt",
    "sg:orig_category":"Restaurants: Chinesisch",
    "sg:phone":"+43 4326 2288289",
    "sg:postcode":"2700",
    "sg:province":"Nieder\u00f6sterreich",
    "wof:name":"Asia Restaurant WANG PAI",
    "wof:placetype":"venue"
},
  "geometry": {"coordinates":[16.2249107361,47.8156280518],"type":"Point"}
}