{
  "type": "Feature",
  "properties": {
    "addr:full":"Eisenfeldstrasse 27 Wels Ober\u00f6sterreich 4600",
    "addr:housenumber":"27",
    "addr:postcode":"4600",
    "addr:street":"Eisenfeldstrasse;Oberoesterreich",
    "iso:country":"AT",
    "sg:address":"Eisenfeldstrasse 27",
    "sg:city":"Wels",
    "sg:classifiers":[
        {
            "category":"Wholesale",
            "subcategory":"Metals & Minerals",
            "type":"Manufacturing & Wholesale Goods"
        }
    ],
    "sg:phone":"+43 7242 628070",
    "sg:postcode":"4600",
    "sg:province":"Ober\u00f6sterreich",
    "sg:tags":[
        "band",
        "blade",
        "saw",
        "machining"
    ],
    "sg:website":"scheinecker-wels.at",
    "wof:name":"Scheinecker Ges.m.b.H.",
    "wof:placetype":"venue"
},
  "geometry": {"coordinates":[14.0374126434,48.1661949158],"type":"Point"}
}