{
  "type": "Feature",
  "properties": {
    "iso:country":"AT",
    "sg:address":"Ramsau 71c",
    "sg:city":"Hippach",
    "sg:orig_category":"Appartements / Ferienwohnungen",
    "sg:phone":"+43 4352 822952",
    "sg:postcode":"6283",
    "sg:province":"Tirol",
    "wof:name":"Ferienwohnung Kr\u00f6ll",
    "wof:placetype":"venue"
},
  "geometry": {"coordinates":[11.8692798615,47.2042808533],"type":"Point"}
}