{
  "type": "Feature",
  "properties": {
    "addr:full":"Landstra\u00dfer Hauptstr Wien Wien 1030",
    "addr:postcode":"1030",
    "addr:street":"Landstrasser Hauptstr",
    "iso:country":"AT",
    "sg:address":"Landstra\u00dfer Hauptstr",
    "sg:city":"Wien",
    "sg:orig_category":"Garagen Parkgaragen",
    "sg:phone":"+43 1 7136983",
    "sg:postcode":"1030",
    "sg:province":"Wien",
    "wof:name":"Garage Landstra\u00dfer Hauptstra\u00dfe",
    "wof:placetype":"venue"
},
  "geometry": {"coordinates":[16.3859596252,48.2056808472],"type":"Point"}
}