{
  "type": "Feature",
  "properties": {
    "addr:full":"Loferer Str 54a Saalfelden am Steinernen Meer Salzburg 5760",
    "addr:housenumber":"54a",
    "addr:postcode":"5760",
    "addr:street":"Str",
    "iso:country":"AT",
    "sg:address":"Loferer Str 54a",
    "sg:city":"Saalfelden am Steinernen Meer",
    "sg:orig_category":"Bestattungsunternehmen",
    "sg:phone":"+43 6582 723550",
    "sg:postcode":"5760",
    "sg:province":"Salzburg",
    "wof:name":"Gadenst\u00e4tter GmbH & Co KG",
    "wof:placetype":"venue"
},
  "geometry": {"coordinates":[12.8463172913,47.4291687012],"type":"Point"}
}