{
  "type": "Feature",
  "properties": {
    "addr:full":"Gerasdorfer Stra\u00dfe 153/308 Wien Wien 1210",
    "addr:housenumber":"153 / 308",
    "addr:postcode":"1210",
    "addr:street":"Gerasdorfer Strasse",
    "iso:country":"AT",
    "sg:address":"Gerasdorfer Stra\u00dfe 153/308",
    "sg:city":"Wien",
    "sg:orig_category":"Bildung And Forschung, Museen",
    "sg:postcode":"1210",
    "sg:province":"Wien",
    "sg:website":"http://www.voodoo.at",
    "wof:name":"Bisarias Voodoo und Magieseiten",
    "wof:placetype":"venue"
},
  "geometry": {"coordinates":[16.4356060028,48.2860107422],"type":"Point"}
}