{
  "type": "Feature",
  "properties": {
    "addr:full":"Matth\u00e4usg 9 Wien Wien 1030",
    "addr:housenumber":"9",
    "addr:postcode":"1030",
    "addr:street":"Matthaeusg",
    "iso:country":"AT",
    "sg:address":"Matth\u00e4usg 9",
    "sg:city":"Wien",
    "sg:orig_category":"Installationsunternehmen",
    "sg:phone":"+43 4317 146765",
    "sg:postcode":"1030",
    "sg:province":"Wien",
    "wof:name":"Tibor Peter GesmbH",
    "wof:placetype":"venue"
},
  "geometry": {"coordinates":[16.3883914948,48.2100334167],"type":"Point"}
}