{
  "type": "Feature",
  "properties": {
    "addr:full":"Linzer Str 79 Wien Wien 1140",
    "addr:housenumber":"79",
    "addr:postcode":"1140",
    "addr:street":"Linzer Str",
    "iso:country":"AT",
    "sg:address":"Linzer Str 79",
    "sg:city":"Wien",
    "sg:orig_category":"Friseure U Frisiersalons",
    "sg:phone":"+43 4319 827023",
    "sg:postcode":"1140",
    "sg:province":"Wien",
    "wof:name":"Stylinghouse",
    "wof:placetype":"venue"
},
  "geometry": {"coordinates":[16.3097057343,48.1933250427],"type":"Point"}
}