{
  "type": "Feature",
  "properties": {
    "iso:country":"AT",
    "sg:address":"Kaiserebersdorferstr 187",
    "sg:city":"Wien",
    "sg:orig_category":"Blumengro\u00c3\u0178handel",
    "sg:phone":"+43 1 7684240",
    "sg:postcode":"1110",
    "sg:province":"Wien",
    "wof:name":"Schwarz Johann",
    "wof:placetype":"venue"
},
  "geometry": {"coordinates":[16.4528141022,48.1607055664],"type":"Point"}
}