{
  "type": "Feature",
  "properties": {
    "addr:full":"J Mayr Nusser-Weg 2 Innsbruck Tirol 6020",
    "addr:housenumber":"2",
    "addr:postcode":"6020",
    "addr:street":"Tirol",
    "iso:country":"AT",
    "sg:address":"J Mayr Nusser-Weg 2",
    "sg:city":"Innsbruck",
    "sg:orig_category":"Transportbeton",
    "sg:phone":"+43 512 336330",
    "sg:postcode":"6020",
    "sg:province":"Tirol",
    "wof:name":"Fr\u00f6schl Bau AG & Co KG",
    "wof:placetype":"venue"
},
  "geometry": {"coordinates":[11.4414920807,47.2677001953],"type":"Point"}
}