{
  "type": "Feature",
  "properties": {
    "iso:country":"AT",
    "sg:address":"Gemeindeheide",
    "sg:city":"Lutzmannsburg",
    "sg:orig_category":"Sonnenstudios",
    "sg:phone":"+43 2615 87388",
    "sg:postcode":"7361",
    "sg:province":"Burgenland",
    "wof:name":"Br\u00e4unungsstudio Inge",
    "wof:placetype":"venue"
},
  "geometry": {"coordinates":[16.6097984314,47.4495391846],"type":"Point"}
}