{
  "type": "Feature",
  "properties": {
    "iso:country":"AT",
    "sg:address":"Lindauweg 2",
    "sg:city":"Fieberbrunn",
    "sg:orig_category":"Pensionen / Privatzimmer",
    "sg:phone":"+43 5354 56807",
    "sg:postcode":"6391",
    "sg:province":"Tirol",
    "wof:name":"St\u00f6ckl Anneliese",
    "wof:placetype":"venue"
},
  "geometry": {"coordinates":[12.5452785492,47.4750175476],"type":"Point"}
}