{
  "type": "Feature",
  "properties": {
    "iso:country":"AT",
    "sg:address":"Lastenstr 34",
    "sg:city":"St. Veit an der Glan",
    "sg:orig_category":"Eisenwaren",
    "sg:phone":"+43 4212 21480",
    "sg:postcode":"9300",
    "sg:province":"K\u00e4rnten",
    "wof:name":"Geiger Franz & S\u00f6hne",
    "wof:placetype":"venue"
},
  "geometry": {"coordinates":[14.3652448654,46.7657432556],"type":"Point"}
}