{
  "type": "Feature",
  "properties": {
    "addr:full":"Hauptstr 47 Gallneukirchen Ober\u00f6sterreich 4210",
    "addr:housenumber":"47",
    "addr:postcode":"4210",
    "addr:street":"Hauptstr;Oberoesterreich",
    "iso:country":"AT",
    "sg:address":"Hauptstr 47",
    "sg:city":"Gallneukirchen",
    "sg:classifiers":[
        {
            "category":"Restaurant",
            "type":"Food & Drink"
        }
    ],
    "sg:phone":"+43 7235 20090",
    "sg:postcode":"4210",
    "sg:province":"Ober\u00f6sterreich",
    "sg:tags":[
        "pizzeria"
    ],
    "wof:name":"Pizzeria Pella",
    "wof:placetype":"venue"
},
  "geometry": {"coordinates":[14.4184045792,48.3552284241],"type":"Point"}
}