{
  "type": "Feature",
  "properties": {
    "addr:full":"Alpineweg 142 Rohrmoos-Untertal Steiermark 8971",
    "addr:housenumber":"142",
    "addr:postcode":"8971",
    "addr:street":"Rohrmoos-Untertal Steiermark",
    "iso:country":"AT",
    "sg:address":"Alpineweg 142",
    "sg:city":"Rohrmoos-Untertal",
    "sg:classifiers":[
        {
            "category":"Travel",
            "subcategory":"Hotels & Motels",
            "type":"Entertainment"
        }
    ],
    "sg:phone":"+43 3687 61215",
    "sg:postcode":"8971",
    "sg:province":"Steiermark",
    "wof:name":"Alpine Apartment Hotel",
    "wof:placetype":"venue"
},
  "geometry": {"coordinates":[13.6795110703,47.3872146606],"type":"Point"}
}