{
  "type": "Feature",
  "properties": {
    "addr:full":"Kitzb\u00fcheler Str 30 Kirchberg in Tirol Tirol 6365",
    "addr:housenumber":"30",
    "addr:postcode":"6365",
    "addr:street":"Str;Tirol",
    "iso:country":"AT",
    "sg:address":"Kitzb\u00fcheler Str 30",
    "sg:city":"Kirchberg in Tirol",
    "sg:orig_category":"Garten- U Landschaftsgestaltung",
    "sg:phone":"+43 4353 572503",
    "sg:postcode":"6365",
    "sg:province":"Tirol",
    "wof:name":"Schranzhofer Toni",
    "wof:placetype":"venue"
},
  "geometry": {"coordinates":[12.3149347305,47.4481468201],"type":"Point"}
}