{
  "type": "Feature",
  "properties": {
    "iso:country":"AT",
    "sg:address":"Gumpendorfer Str. 132",
    "sg:city":"Wien",
    "sg:classifiers":[
        {
            "category":"Professional",
            "subcategory":"Advertising",
            "type":"Services"
        }
    ],
    "sg:phone":"+43 4315 961515",
    "sg:postcode":"1060",
    "sg:province":"Wien",
    "sg:tags":[
        "communication",
        "medium"
    ],
    "wof:name":"LISTO VIDIOFILM GMBH & CO KG",
    "wof:placetype":"venue"
},
  "geometry": {"coordinates":[16.3404197693,48.1906661987],"type":"Point"}
}