{
  "type": "Feature",
  "properties": {
    "iso:country":"AT",
    "sg:address":"Gutenbergstr 10",
    "sg:city":"Innsbruck",
    "sg:orig_category":"Tanzschulen",
    "sg:phone":"+43 512 584095",
    "sg:postcode":"6020",
    "sg:province":"Tirol",
    "wof:name":"Tanzschule Helga Sch\u00fccker",
    "wof:placetype":"venue"
},
  "geometry": {"coordinates":[11.4057884216,47.27709198],"type":"Point"}
}