{
  "type": "Feature",
  "properties": {
    "addr:full":"Mittere G 9 Felixdorf Nieder\u00f6sterreich 2603",
    "addr:housenumber":"9",
    "addr:postcode":"2603",
    "addr:street":"Mittere G",
    "iso:country":"AT",
    "sg:address":"Mittere G 9",
    "sg:city":"Felixdorf",
    "sg:orig_category":"Spenglereien",
    "sg:phone":"+43 2633 43187",
    "sg:postcode":"2603",
    "sg:province":"Nieder\u00f6sterreich",
    "wof:name":"Krennert Ernst Ing",
    "wof:placetype":"venue"
},
  "geometry": {"coordinates":[16.2418251038,47.8797912598],"type":"Point"}
}