{
  "type": "Feature",
  "properties": {
    "iso:country":"AT",
    "sg:address":"Mautner Markhof-G 45",
    "sg:city":"Wien",
    "sg:orig_category":"Musikunterricht",
    "sg:phone":"+43 1 7434000",
    "sg:postcode":"1110",
    "sg:province":"Wien",
    "wof:name":"Mahler Gustav Konservatorium f Musik und darstellende Kunst",
    "wof:placetype":"venue"
},
  "geometry": {"coordinates":[16.4207038879,48.1756477356],"type":"Point"}
}