{
  "type": "Feature",
  "properties": {
    "addr:full":"Breitenfurter Strasse 314 Wien Wien 1230",
    "addr:housenumber":"314",
    "addr:postcode":"1230",
    "addr:street":"Breitenfurter Strasse",
    "iso:country":"AT",
    "sg:address":"Breitenfurter Strasse 314",
    "sg:city":"Wien",
    "sg:classifiers":[
        {
            "category":"Community Center",
            "subcategory":"Senior",
            "type":"Public Place"
        }
    ],
    "sg:phone":"+43 1 8691213",
    "sg:postcode":"1230",
    "sg:province":"Wien",
    "sg:tags":[
        "front",
        "wood",
        "door"
    ],
    "wof:name":"Herbert Fahrecker",
    "wof:placetype":"venue"
},
  "geometry": {"coordinates":[16.2901287079,48.1397247314],"type":"Point"}
}