{
  "type": "Feature",
  "properties": {
    "iso:country":"AT",
    "sg:address":"Marchfeldg 34",
    "sg:city":"Kitzb\u00fchel",
    "sg:orig_category":"\u00c3\u201erzte / F Allgemeinmedizin",
    "sg:phone":"+43 5356 63009",
    "sg:postcode":"6370",
    "sg:province":"Tirol",
    "wof:name":"Bartl Eva Dr",
    "wof:placetype":"venue"
},
  "geometry": {"coordinates":[12.38991642,47.4377555847],"type":"Point"}
}