{
  "type": "Feature",
  "properties": {
    "addr:full":"Josef-Weiland-Str 3 Gaweinstal Nieder\u00f6sterreich 2191",
    "addr:housenumber":"3",
    "addr:postcode":"2191",
    "addr:street":"Josef-Weiland-Str",
    "iso:country":"AT",
    "sg:address":"Josef-Weiland-Str 3",
    "sg:city":"Gaweinstal",
    "sg:orig_category":"Volksschulen",
    "sg:phone":"+43 2574 29410",
    "sg:postcode":"2191",
    "sg:province":"Nieder\u00f6sterreich",
    "wof:name":"Volksschule Schrick",
    "wof:placetype":"venue"
},
  "geometry": {"coordinates":[16.6201286316,48.5121498108],"type":"Point"}
}