{
  "type": "Feature",
  "properties": {
    "addr:full":"Maurach 222 Jenbach Tirol 6200",
    "addr:housenumber":"222",
    "addr:postcode":"6200",
    "addr:street":"Maurach;Tirol",
    "iso:country":"AT",
    "sg:address":"Maurach 222",
    "sg:city":"Jenbach",
    "sg:orig_category":"Autoersatzteile",
    "sg:phone":"+43 4367 65605484",
    "sg:postcode":"6200",
    "sg:province":"Tirol",
    "wof:name":"Moser Christine",
    "wof:placetype":"venue"
},
  "geometry": {"coordinates":[11.7804536819,47.3818092346],"type":"Point"}
}