{
  "type": "Feature",
  "properties": {
    "addr:full":"Stiftstr 5 St. Florian Ober\u00f6sterreich 4490",
    "addr:housenumber":"5",
    "addr:postcode":"4490",
    "addr:street":"Stiftstr",
    "iso:country":"AT",
    "sg:address":"Stiftstr 5",
    "sg:city":"St. Florian",
    "sg:orig_category":"Orgel- U Harmoniumbau",
    "sg:phone":"+43 4372 244247",
    "sg:postcode":"4490",
    "sg:province":"Ober\u00f6sterreich",
    "wof:name":"O\u00f6 Orgelbau K\u00f6gler GmbH",
    "wof:placetype":"venue"
},
  "geometry": {"coordinates":[14.374341011,48.2053451538],"type":"Point"}
}