{
  "type": "Feature",
  "properties": {
    "addr:full":"Kapellenweg 54 Going am Wilden Kaiser Tirol 6353",
    "addr:housenumber":"54",
    "addr:postcode":"6353",
    "addr:street":"Kapellenweg;Tirol",
    "iso:country":"AT",
    "sg:address":"Kapellenweg 54",
    "sg:city":"Going am Wilden Kaiser",
    "sg:orig_category":"Elektroinstallationsunternehmen",
    "sg:phone":"+43 4353 582487",
    "sg:postcode":"6353",
    "sg:province":"Tirol",
    "wof:name":"Grottenthaler Horst",
    "wof:placetype":"venue"
},
  "geometry": {"coordinates":[12.3440504074,47.5208282471],"type":"Point"}
}