{
  "type": "Feature",
  "properties": {
    "iso:country":"AT",
    "sg:address":"Kapellenweg 54",
    "sg:city":"Going am Wilden Kaiser",
    "sg:orig_category":"Elektroinstallationsunternehmen",
    "sg:phone":"+43 4353 582487",
    "sg:postcode":"6353",
    "sg:province":"Tirol",
    "wof:name":"Grottenthaler Horst",
    "wof:placetype":"venue"
},
  "geometry": {"coordinates":[12.3440504074,47.5208282471],"type":"Point"}
}