{
  "type": "Feature",
  "properties": {
    "iso:country":"AT",
    "sg:address":"Schullernstrasse 11",
    "sg:city":"Innsbruck",
    "sg:classifiers":[
        {
            "category":"Shopping",
            "subcategory":"Musical Instruments",
            "type":"Retail Goods"
        }
    ],
    "sg:phone":"+43 512 391391",
    "sg:postcode":"6020",
    "sg:province":"Tirol",
    "sg:tags":[
        "brass"
    ],
    "sg:website":"tutz.at",
    "wof:name":"Musikhaus Tutz GmbH",
    "wof:placetype":"venue"
},
  "geometry": {"coordinates":[11.4179754257,47.259147644],"type":"Point"}
}