{
  "type": "Feature",
  "properties": {
    "addr:full":"Hof 16 Saalfelden am Steinernen Meer Salzburg 5760",
    "addr:housenumber":"16",
    "addr:postcode":"5760",
    "addr:street":"Hof;Salzburg",
    "iso:country":"AT",
    "sg:address":"Hof 16",
    "sg:city":"Saalfelden am Steinernen Meer",
    "sg:orig_category":"Maler, Anstreicher U Lackierer",
    "sg:phone":"+43 6582 74575",
    "sg:postcode":"5760",
    "sg:province":"Salzburg",
    "wof:name":"Rohrmoser Christian",
    "wof:placetype":"venue"
},
  "geometry": {"coordinates":[12.8600797653,47.4025154114],"type":"Point"}
}