{
  "type": "Feature",
  "properties": {
    "addr:full":"Dorfweg 3 Latschach ober dem Faaker See K\u00e4rnten 9582",
    "addr:housenumber":"3",
    "addr:postcode":"9582",
    "addr:street":"Dorfweg",
    "iso:country":"AT",
    "sg:address":"Dorfweg 3",
    "sg:city":"Latschach ober dem Faaker See",
    "sg:orig_category":"Pensionen / Privatzimmer",
    "sg:phone":"+43 4342 5427630",
    "sg:postcode":"9582",
    "sg:province":"K\u00e4rnten",
    "wof:name":"Fr\u00fchst\u00fcckspension Hubertushof",
    "wof:placetype":"venue"
},
  "geometry": {"coordinates":[13.924949646,46.5571289062],"type":"Point"}
}