{
  "type": "Feature",
  "properties": {
    "iso:country":"AT",
    "sg:address":"Nr 25",
    "sg:city":"Uderns",
    "sg:classifiers":[
        {
            "category":"Travel",
            "subcategory":"Hotels & Motels",
            "type":"Entertainment"
        }
    ],
    "sg:phone":"+43 4352 88625210",
    "sg:postcode":"6271",
    "sg:province":"Tirol",
    "wof:name":"Hotel Pachmair",
    "wof:placetype":"venue"
},
  "geometry": {"coordinates":[11.8642072678,47.3266906738],"type":"Point"}
}