{
  "type": "Feature",
  "properties": {
    "iso:country":"AT",
    "sg:address":"Dorf 11",
    "sg:city":"Umhausen",
    "sg:orig_category":"Banken U Sparkassen",
    "sg:phone":"+43 4352 555867",
    "sg:postcode":"6441",
    "sg:province":"Tirol",
    "wof:name":"Sparkasse Imst",
    "wof:placetype":"venue"
},
  "geometry": {"coordinates":[10.9266080856,47.1400985718],"type":"Point"}
}