{
  "type": "Feature",
  "properties": {
    "addr:full":"Prof F Spath-Ring 34 St. Peter Steiermark 8042",
    "addr:housenumber":"34",
    "addr:postcode":"8042",
    "addr:street":"Prof F Spath-Ring",
    "iso:country":"AT",
    "sg:address":"Prof F Spath-Ring 34",
    "sg:city":"St. Peter",
    "sg:orig_category":"Alternativtherapie",
    "sg:phone":"+43 316 465052",
    "sg:postcode":"8042",
    "sg:province":"Steiermark",
    "wof:name":"Sudi Claudia",
    "wof:placetype":"venue"
},
  "geometry": {"coordinates":[15.4814271927,47.0514221191],"type":"Point"}
}