{
  "type": "Feature",
  "properties": {
    "addr:full":"Klosterstr 608 Seefeld in Tirol Tirol 6100",
    "addr:housenumber":"608",
    "addr:postcode":"6100",
    "addr:street":"Seefeld;Tirol",
    "iso:country":"AT",
    "sg:address":"Klosterstr 608",
    "sg:city":"Seefeld in Tirol",
    "sg:orig_category":"Boutiquen",
    "sg:phone":"+43 5212 2032",
    "sg:postcode":"6100",
    "sg:province":"Tirol",
    "wof:name":"Boutique Jacqueline",
    "wof:placetype":"venue"
},
  "geometry": {"coordinates":[11.1828870773,47.3278808594],"type":"Point"}
}