{
  "type": "Feature",
  "properties": {
    "addr:full":"Dr.-Ammann-Str 26 Frohnleiten Steiermark 8130",
    "addr:housenumber":"26",
    "addr:postcode":"8130",
    "addr:street":"Dr.-Ammann-Str",
    "iso:country":"AT",
    "sg:address":"Dr.-Ammann-Str 26",
    "sg:city":"Frohnleiten",
    "sg:orig_category":"Dolmetscher",
    "sg:phone":"+43 4366 44235984",
    "sg:postcode":"8130",
    "sg:province":"Steiermark",
    "wof:name":"Bernard Svetlana",
    "wof:placetype":"venue"
},
  "geometry": {"coordinates":[15.3155536652,47.2708396912],"type":"Point"}
}