{
  "type": "Feature",
  "properties": {
    "addr:full":"Hauptpl Schrems Nieder\u00f6sterreich 3943",
    "addr:postcode":"3943",
    "addr:street":"Niederoesterreich",
    "iso:country":"AT",
    "sg:address":"Hauptpl",
    "sg:city":"Schrems",
    "sg:orig_category":"Tabaktrafiken",
    "sg:phone":"+43 2853 77462",
    "sg:postcode":"3943",
    "sg:province":"Nieder\u00f6sterreich",
    "wof:name":"Rubicko Franz",
    "wof:placetype":"venue"
},
  "geometry": {"coordinates":[15.072634697,48.7927818298],"type":"Point"}
}