{
  "type": "Feature",
  "properties": {
    "iso:country":"AT",
    "sg:address":"Gschwandtkopf 702",
    "sg:city":"Seefeld in Tirol",
    "sg:orig_category":"Rope Clips",
    "sg:phone":"+43 5212 2490",
    "sg:postcode":"6100",
    "sg:province":"Tirol",
    "wof:name":"Schneider Ges.m.b.H. & Co KG",
    "wof:placetype":"venue"
},
  "geometry": {"coordinates":[11.1465129852,47.3113555908],"type":"Point"}
}