{
  "type": "Feature",
  "properties": {
    "iso:country":"AT",
    "sg:address":"Unterm Burgstall 4",
    "sg:city":"Spittal an der Drau",
    "sg:orig_category":"Webdesign",
    "sg:phone":"+43 4762 33539",
    "sg:postcode":"9800",
    "sg:province":"K\u00e4rnten",
    "wof:name":"Creative Service Austria- Internetdesign Schwitzer",
    "wof:placetype":"venue"
},
  "geometry": {"coordinates":[13.5080213547,46.7955093384],"type":"Point"}
}