{
  "type": "Feature",
  "properties": {
    "addr:full":"B 182 Brennerstrasse Gries am Brenner Tirol 6156",
    "addr:postcode":"6156",
    "addr:street":"Brennerstrasse;Tirol",
    "iso:country":"AT",
    "sg:address":"B 182 Brennerstrasse",
    "sg:city":"Gries am Brenner",
    "sg:orig_category":"Reisen, Tourismusinfo",
    "sg:phone":"+43 4352 7487201",
    "sg:postcode":"6156",
    "sg:province":"Tirol",
    "sg:website":"http://www.wipptal.net",
    "wof:name":"GASTHOF ROSE",
    "wof:placetype":"venue"
},
  "geometry": {"coordinates":[11.4193086624,47.0162277222],"type":"Point"}
}