{
  "type": "Feature",
  "properties": {
    "addr:full":"Johann-Panzl-Str 3 Matrei in Osttirol Tirol 9971",
    "addr:housenumber":"3",
    "addr:postcode":"9971",
    "addr:street":"Johann-Panzl-Str;Tirol",
    "iso:country":"AT",
    "sg:address":"Johann-Panzl-Str 3",
    "sg:city":"Matrei in Osttirol",
    "sg:orig_category":"Zimmereien",
    "sg:phone":"+43 4875 6521",
    "sg:postcode":"9971",
    "sg:province":"Tirol",
    "wof:name":"K\u00f6ll Andreas Ing",
    "wof:placetype":"venue"
},
  "geometry": {"coordinates":[12.5399284363,47.0024528503],"type":"Point"}
}