{
  "type": "Feature",
  "properties": {
    "addr:full":"W\u00e4hringer Str 123 Wien Wien 1180",
    "addr:housenumber":"123",
    "addr:postcode":"1180",
    "addr:street":"Str",
    "iso:country":"AT",
    "sg:address":"W\u00e4hringer Str 123",
    "sg:city":"Wien",
    "sg:orig_category":"Trachtenbekleidung",
    "sg:phone":"+43 1 4060863",
    "sg:postcode":"1180",
    "sg:province":"Wien",
    "wof:name":"Felsinger Monika",
    "wof:placetype":"venue"
},
  "geometry": {"coordinates":[16.3399753571,48.2269248962],"type":"Point"}
}