{
  "type": "Feature",
  "properties": {
    "addr:full":"St. Georgener Hauptstrasse 22 St. Georgen am Steinfelde Nieder\u00f6sterreich 3151",
    "addr:housenumber":"22",
    "addr:postcode":"3151",
    "addr:street":"St. Georgener Hauptstrasse",
    "iso:country":"AT",
    "sg:address":"St. Georgener Hauptstrasse 22",
    "sg:city":"St. Georgen am Steinfelde",
    "sg:classifiers":[
        {
            "category":"Manufacturing",
            "subcategory":"Wood Products",
            "type":"Manufacturing & Wholesale Goods"
        }
    ],
    "sg:phone":"+43 2742 884611",
    "sg:postcode":"3151",
    "sg:province":"Nieder\u00f6sterreich",
    "sg:tags":[
        "made",
        "castor",
        "furniture"
    ],
    "wof:name":"Heribert Mailer GmbH",
    "wof:placetype":"venue"
},
  "geometry": {"coordinates":[15.6142187119,48.1519203186],"type":"Point"}
}