{
  "type": "Feature",
  "properties": {
    "addr:full":"Nr 403 Alpbach Tirol 6236",
    "addr:postcode":"6236",
    "addr:street":"Nr;Alpbach Tirol",
    "iso:country":"AT",
    "sg:address":"Nr 403",
    "sg:city":"Alpbach",
    "sg:orig_category":"Appartements / Ferienwohnungen",
    "sg:phone":"+43 5336 5503",
    "sg:postcode":"6236",
    "sg:province":"Tirol",
    "wof:name":"Moser Annemarie",
    "wof:placetype":"venue"
},
  "geometry": {"coordinates":[11.9435110092,47.3986091614],"type":"Point"}
}