{
  "type": "Feature",
  "properties": {
    "addr:full":"Meilersdorf 31 Wolfsbach Nieder\u00f6sterreich 3354",
    "addr:housenumber":"31",
    "addr:postcode":"3354",
    "addr:street":"Meilersdorf",
    "iso:country":"AT",
    "sg:address":"Meilersdorf 31",
    "sg:city":"Wolfsbach",
    "sg:orig_category":"Webdesign",
    "sg:phone":"+43 4366 05203171",
    "sg:postcode":"3354",
    "sg:province":"Nieder\u00f6sterreich",
    "wof:name":"Webrevolution - Internetagentur",
    "wof:placetype":"venue"
},
  "geometry": {"coordinates":[14.655295372,48.1046409607],"type":"Point"}
}