{
  "type": "Feature",
  "properties": {
    "iso:country":"AT",
    "sg:address":"Rosasg 6",
    "sg:city":"Wien",
    "sg:orig_category":"\u00c3\u201erzte / F Allgemeinmedizin",
    "sg:phone":"+43 1 8131416",
    "sg:postcode":"1120",
    "sg:province":"Wien",
    "wof:name":"Haiden Rudolf Dr",
    "wof:placetype":"venue"
},
  "geometry": {"coordinates":[16.3261032104,48.1817436218],"type":"Point"}
}