{
  "type": "Feature",
  "properties": {
    "addr:full":"St Jakober Dorfstr 37 St. Anton am Arlberg Tirol 6580",
    "addr:housenumber":"37",
    "addr:postcode":"6580",
    "addr:street":"St Jakober Dorfstr",
    "iso:country":"AT",
    "sg:address":"St Jakober Dorfstr 37",
    "sg:city":"St. Anton am Arlberg",
    "sg:orig_category":"Pensionen / Privatzimmer",
    "sg:phone":"+43 5446 3137",
    "sg:postcode":"6580",
    "sg:province":"Tirol",
    "wof:name":"G\u00e4stehaus Bellamonte",
    "wof:placetype":"venue"
},
  "geometry": {"coordinates":[10.2977342606,47.1429519653],"type":"Point"}
}