{
  "type": "Feature",
  "properties": {
    "iso:country":"AT",
    "sg:address":"B\u00e4ckerg 4",
    "sg:city":"Wels",
    "sg:orig_category":"Damenmoden",
    "sg:phone":"+43 7242 26998",
    "sg:postcode":"4600",
    "sg:province":"Ober\u00f6sterreich",
    "wof:name":"Orsay-Ordia HandelsgesmbH",
    "wof:placetype":"venue"
},
  "geometry": {"coordinates":[14.024805069,48.1587791443],"type":"Point"}
}