{
  "type": "Feature",
  "properties": {
    "addr:full":"Hauptstr 22 St. Valentin Nieder\u00f6sterreich 4300",
    "addr:housenumber":"22",
    "addr:postcode":"4300",
    "addr:street":"Hauptstr",
    "iso:country":"AT",
    "sg:address":"Hauptstr 22",
    "sg:city":"St. Valentin",
    "sg:orig_category":"Apotheken",
    "sg:phone":"+43 7435 524130",
    "sg:postcode":"4300",
    "sg:province":"Nieder\u00f6sterreich",
    "wof:name":"St Valentinus Apotheke Mag pharm Hoyer KG",
    "wof:placetype":"venue"
},
  "geometry": {"coordinates":[14.5291233063,48.175163269],"type":"Point"}
}