{
  "type": "Feature",
  "properties": {
    "addr:full":"Innern\u00f6ring Eisentratten K\u00e4rnten 9861",
    "addr:postcode":"9861",
    "addr:street":"Kaernten",
    "iso:country":"AT",
    "sg:address":"Innern\u00f6ring",
    "sg:city":"Eisentratten",
    "sg:orig_category":"Fischzucht",
    "sg:phone":"+43 4732 3039",
    "sg:postcode":"9861",
    "sg:province":"K\u00e4rnten",
    "wof:name":"Liesertaler Gebirgsforelle",
    "wof:placetype":"venue"
},
  "geometry": {"coordinates":[13.5780506134,46.9226989746],"type":"Point"}
}