{
  "type": "Feature",
  "properties": {
    "addr:full":"Altaussee Steiermark 8992",
    "addr:postcode":"8992",
    "iso:country":"AT",
    "sg:city":"Altaussee",
    "sg:orig_category":"Reisen, Tourismusinfo",
    "sg:phone":"+43 3622 71315",
    "sg:postcode":"8992",
    "sg:province":"Steiermark",
    "sg:website":"http://www.loser.at",
    "wof:name":"Der Loser - Panoramastrasse, Wanderparadies, Bergrestaurant",
    "wof:placetype":"venue"
},
  "geometry": {"coordinates":[13.764960289,47.6403694153],"type":"Point"}
}