{
  "type": "Feature",
  "properties": {
    "iso:country":"AT",
    "sg:address":"Glang 2",
    "sg:city":"Salzburg",
    "sg:orig_category":"Balkon-, Loggien- U Terrassenverbauten",
    "sg:phone":"+43 4366 2835057",
    "sg:postcode":"5020",
    "sg:province":"Salzburg",
    "wof:name":"WIGALUX Produktions- u VertriebsgesmbH",
    "wof:placetype":"venue"
},
  "geometry": {"coordinates":[13.0204162598,47.7973976135],"type":"Point"}
}