{
  "type": "Feature",
  "properties": {
    "iso:country":"AT",
    "sg:address":"Eferdinger Str 13",
    "sg:city":"Wallern an der Trattnach",
    "sg:orig_category":"Erdarbeiten, Baustoffe U -Material",
    "sg:phone":"+43 4372 4948228",
    "sg:postcode":"4702",
    "sg:province":"Ober\u00f6sterreich",
    "sg:website":"web.utanet.at/situkwyy",
    "wof:name":"Situk Wilfried",
    "wof:placetype":"venue"
},
  "geometry": {"coordinates":[13.9460506439,48.2335624695],"type":"Point"}
}