{
  "type": "Feature",
  "properties": {
    "addr:full":"Eferdinger Str 13 Wallern an der Trattnach Ober\u00f6sterreich 4702",
    "addr:postcode":"4702",
    "addr:street":"Str 13",
    "iso:country":"AT",
    "sg:address":"Eferdinger Str 13",
    "sg:city":"Wallern an der Trattnach",
    "sg:orig_category":"Erdarbeiten, Baustoffe U -Material",
    "sg:phone":"+43 4372 4948228",
    "sg:postcode":"4702",
    "sg:province":"Ober\u00f6sterreich",
    "sg:website":"web.utanet.at/situkwyy",
    "wof:name":"Situk Wilfried",
    "wof:placetype":"venue"
},
  "geometry": {"coordinates":[13.9460506439,48.2335624695],"type":"Point"}
}