{
  "type": "Feature",
  "properties": {
    "addr:full":"Untere Rentmeisterg 2 Hainfeld Nieder\u00f6sterreich 3170",
    "addr:housenumber":"2",
    "addr:postcode":"3170",
    "addr:street":"Untere Rentmeisterg",
    "iso:country":"AT",
    "sg:address":"Untere Rentmeisterg 2",
    "sg:city":"Hainfeld",
    "sg:orig_category":"Fenster",
    "sg:phone":"+43 2764 7688",
    "sg:postcode":"3170",
    "sg:province":"Nieder\u00f6sterreich",
    "wof:name":"Guttmann Fenster - Inh Walter Scheuher",
    "wof:placetype":"venue"
},
  "geometry": {"coordinates":[15.7765483856,48.0360145569],"type":"Point"}
}