{
  "type": "Feature",
  "properties": {
    "addr:full":"L Gattringer-Str 49 Brunn am Gebirge Nieder\u00f6sterreich 2345",
    "addr:housenumber":"49",
    "addr:postcode":"2345",
    "iso:country":"AT",
    "sg:address":"L Gattringer-Str 49",
    "sg:city":"Brunn am Gebirge",
    "sg:orig_category":"Lebensmittel / Einzelhandel",
    "sg:phone":"+43 2236 31683",
    "sg:postcode":"2345",
    "sg:province":"Nieder\u00f6sterreich",
    "wof:name":"Billa AG",
    "wof:placetype":"venue"
},
  "geometry": {"coordinates":[16.2810993195,48.1080703735],"type":"Point"}
}