{
  "type": "Feature",
  "properties": {
    "iso:country":"AT",
    "sg:address":"Wallerer Strasse 97",
    "sg:city":"Wels",
    "sg:classifiers":[
        {
            "category":"Manufacturing",
            "subcategory":"Wood Products",
            "type":"Manufacturing & Wholesale Goods"
        }
    ],
    "sg:phone":"+43 7242 60567",
    "sg:postcode":"4600",
    "sg:province":"Ober\u00f6sterreich",
    "sg:tags":[
        "gate",
        "made",
        "door"
    ],
    "wof:name":"G\u00fcnter P\u00fchringer",
    "wof:placetype":"venue"
},
  "geometry": {"coordinates":[14.0159416199,48.1754570007],"type":"Point"}
}