{
  "type": "Feature",
  "properties": {
    "addr:full":"Hardtmuthg 62 Wien Wien 1100",
    "addr:housenumber":"62",
    "addr:postcode":"1100",
    "addr:street":"Hardtmuthg",
    "iso:country":"AT",
    "sg:address":"Hardtmuthg 62",
    "sg:city":"Wien",
    "sg:orig_category":"Lederwaren / Einzelhandel",
    "sg:phone":"+43 1 60241870",
    "sg:postcode":"1100",
    "sg:province":"Wien",
    "sg:website":"koffer-kraus.at",
    "wof:name":"Koffer Kraus Lederwarenhandel Kraus & Co KG",
    "wof:placetype":"venue"
},
  "geometry": {"coordinates":[16.3690929413,48.1706008911],"type":"Point"}
}