{
  "type": "Feature",
  "properties": {
    "addr:full":"Austr 12 Kottingbrunn Nieder\u00f6sterreich 2542",
    "addr:housenumber":"12",
    "addr:postcode":"2542",
    "addr:street":"Austr",
    "iso:country":"AT",
    "sg:address":"Austr 12",
    "sg:city":"Kottingbrunn",
    "sg:orig_category":"Elektronik",
    "sg:phone":"+43 2252 71204",
    "sg:postcode":"2542",
    "sg:province":"Nieder\u00f6sterreich",
    "wof:name":"Nossek Heinrich",
    "wof:placetype":"venue"
},
  "geometry": {"coordinates":[16.2379722595,47.9460372925],"type":"Point"}
}