{
  "type": "Feature",
  "properties": {
    "iso:country":"AT",
    "sg:address":"Dominikanerpl 1",
    "sg:city":"Krems an der Donau",
    "sg:orig_category":"Lebensmittel / Einzelhandel",
    "sg:phone":"+43 2732 84938",
    "sg:postcode":"3500",
    "sg:province":"Nieder\u00f6sterreich",
    "wof:name":"Billa AG",
    "wof:placetype":"venue"
},
  "geometry": {"coordinates":[15.5983982086,48.4110603333],"type":"Point"}
}