{
  "type": "Feature",
  "properties": {
    "iso:country":"AT",
    "sg:address":"Dieselstr 1A",
    "sg:city":"Mauer-\u00d6hling",
    "sg:classifiers":[
        {
            "category":"Home & Garden",
            "subcategory":"Building Materials",
            "type":"Retail Goods"
        }
    ],
    "sg:phone":"+43 4374 72280700",
    "sg:postcode":"3362",
    "sg:province":"Nieder\u00f6sterreich",
    "sg:tags":[
        "baustoffe",
        "-material",
        "u"
    ],
    "wof:name":"Fuchsberger GmbH",
    "wof:placetype":"venue"
},
  "geometry": {"coordinates":[14.7985095978,48.1009559631],"type":"Point"}
}