{
  "type": "Feature",
  "properties": {
    "addr:full":"Breite G 5 Laa an der Thaya Nieder\u00f6sterreich 2136",
    "addr:housenumber":"5",
    "addr:postcode":"2136",
    "addr:street":"Breite G",
    "iso:country":"AT",
    "sg:address":"Breite G 5",
    "sg:city":"Laa an der Thaya",
    "sg:orig_category":"Reifen U Reifendienste",
    "sg:phone":"+43 4325 2223340",
    "sg:postcode":"2136",
    "sg:province":"Nieder\u00f6sterreich",
    "wof:name":"Winkler Karl",
    "wof:placetype":"venue"
},
  "geometry": {"coordinates":[16.3857116699,48.7234954834],"type":"Point"}
}