{
  "type": "Feature",
  "properties": {
    "iso:country":"AT",
    "sg:address":"Erndtg 7",
    "sg:city":"Wien",
    "sg:orig_category":"Restaurants: Italienisch",
    "sg:phone":"+43 4314 792954",
    "sg:postcode":"1180",
    "sg:province":"Wien",
    "wof:name":"Monte Rosa",
    "wof:placetype":"venue"
},
  "geometry": {"coordinates":[16.3445625305,48.2262420654],"type":"Point"}
}