{
  "type": "Feature",
  "properties": {
    "iso:country":"AT",
    "sg:address":"Wachaustr 1",
    "sg:city":"Karlstetten",
    "sg:orig_category":"Lebensmittel / Einzelhandel",
    "sg:phone":"+43 2741 80050",
    "sg:postcode":"3121",
    "sg:province":"Nieder\u00f6sterreich",
    "wof:name":"ADEG-Aktiv Othmar Ratzinger",
    "wof:placetype":"venue"
},
  "geometry": {"coordinates":[15.5661640167,48.259098053],"type":"Point"}
}