{
  "type": "Feature",
  "properties": {
    "iso:country":"AT",
    "sg:address":"Kircheng 131",
    "sg:city":"Tamsweg",
    "sg:orig_category":"Lebensmittel / Einzelhandel",
    "sg:phone":"+43 6474 21390",
    "sg:postcode":"5580",
    "sg:province":"Salzburg",
    "wof:name":"ADEG Aktiv Markt",
    "wof:placetype":"venue"
},
  "geometry": {"coordinates":[13.8102960587,47.1271438599],"type":"Point"}
}