{
  "type": "Feature",
  "properties": {
    "iso:country":"AT",
    "sg:address":"Nr 43",
    "sg:city":"Kirchdorf an der Krems",
    "sg:orig_category":"Autoverwertung",
    "sg:phone":"+43 7582 63830",
    "sg:postcode":"4560",
    "sg:province":"Ober\u00f6sterreich",
    "wof:name":"Auto Sperrer",
    "wof:placetype":"venue"
},
  "geometry": {"coordinates":[14.1225223541,47.9058189392],"type":"Point"}
}