{
  "type": "Feature",
  "properties": {
    "iso:country":"AT",
    "sg:address":"Rohrbach 7",
    "sg:city":"Pischelsdorf in Steiermark",
    "sg:orig_category":"Pensionen / Privatzimmer",
    "sg:phone":"+43 3113 8007",
    "sg:postcode":"8212",
    "sg:province":"Steiermark",
    "wof:name":"Gesundheitsbauernhof Wachmann",
    "wof:placetype":"venue"
},
  "geometry": {"coordinates":[15.7832288742,47.1852493286],"type":"Point"}
}