{
  "type": "Feature",
  "properties": {
    "addr:full":"Studenzen 12 Studenzen Steiermark 8322",
    "addr:housenumber":"12",
    "addr:postcode":"8322",
    "addr:street":"Studenzen",
    "iso:country":"AT",
    "sg:address":"Studenzen 12",
    "sg:city":"Studenzen",
    "sg:classifiers":[
        {
            "category":"Manufacturing",
            "subcategory":"Furniture",
            "type":"Manufacturing & Wholesale Goods"
        }
    ],
    "sg:phone":"+43 3115 2232",
    "sg:postcode":"8322",
    "sg:province":"Steiermark",
    "sg:tags":[
        "bedroom"
    ],
    "wof:name":"Tischlerei Dirnbauer Inh. Anna Fritz",
    "wof:placetype":"venue"
},
  "geometry": {"coordinates":[15.7906103134,47.0232505798],"type":"Point"}
}