{
  "type": "Feature",
  "properties": {
    "addr:full":"Sankt-Rochus-Strasse 25 Eisenstadt Burgenland 7000",
    "addr:housenumber":"25",
    "addr:postcode":"7000",
    "addr:street":"Sankt-Rochus-Strasse",
    "iso:country":"AT",
    "sg:address":"Sankt-Rochus-Strasse 25",
    "sg:city":"Eisenstadt",
    "sg:classifiers":[
        {
            "category":"Shopping",
            "subcategory":"Books",
            "type":"Retail Goods"
        }
    ],
    "sg:phone":"+43 2682 62473",
    "sg:postcode":"7000",
    "sg:province":"Burgenland",
    "wof:name":"E. Weber Verlag GmbH",
    "wof:placetype":"venue"
},
  "geometry": {"coordinates":[16.5251846313,47.8447151184],"type":"Point"}
}