{
  "type": "Feature",
  "properties": {
    "addr:full":"Schmiedg 11 Apetlon Burgenland 7143",
    "addr:housenumber":"11",
    "addr:postcode":"7143",
    "addr:street":"Schmiedg",
    "iso:country":"AT",
    "sg:address":"Schmiedg 11",
    "sg:city":"Apetlon",
    "sg:orig_category":"Lebensmittel / Einzelhandel",
    "sg:phone":"+43 2175 23610",
    "sg:postcode":"7143",
    "sg:province":"Burgenland",
    "wof:name":"Reinprecht Gregor",
    "wof:placetype":"venue"
},
  "geometry": {"coordinates":[16.838312149,47.7437133789],"type":"Point"}
}