{
  "type": "Feature",
  "properties": {
    "addr:full":"Hauptstr 14 Seewalchen am Attersee Ober\u00f6sterreich 4863",
    "addr:housenumber":"14",
    "addr:postcode":"4863",
    "addr:street":"Hauptstr",
    "iso:country":"AT",
    "sg:address":"Hauptstr 14",
    "sg:city":"Seewalchen am Attersee",
    "sg:orig_category":"Tabaktrafiken",
    "sg:phone":"+43 4376 623089",
    "sg:postcode":"4863",
    "sg:province":"Ober\u00f6sterreich",
    "wof:name":"Powischer Mario",
    "wof:placetype":"venue"
},
  "geometry": {"coordinates":[13.5877199173,47.9528846741],"type":"Point"}
}