{
  "type": "Feature",
  "properties": {
    "iso:country":"AT",
    "sg:address":"Obdacher Str 153a",
    "sg:city":"Bad St. Leonhard im Lavanttal",
    "sg:orig_category":"Autoreparatur",
    "sg:phone":"+43 4343 502336",
    "sg:postcode":"9462",
    "sg:province":"K\u00e4rnten",
    "wof:name":"Maggale Hubert",
    "wof:placetype":"venue"
},
  "geometry": {"coordinates":[14.7846679688,46.9694633484],"type":"Point"}
}