{
  "type": "Feature",
  "properties": {
    "iso:country":"AT",
    "sg:address":"Handelskai 214/15",
    "sg:city":"Wien",
    "sg:orig_category":"Transportunternehmen",
    "sg:phone":"+43 4317 281690",
    "sg:postcode":"1020",
    "sg:province":"Wien",
    "wof:name":"Hasieber Otto",
    "wof:placetype":"venue"
},
  "geometry": {"coordinates":[16.4112224579,48.2208023071],"type":"Point"}
}