{
  "type": "Feature",
  "properties": {
    "iso:country":"AT",
    "sg:address":"Nr 4",
    "sg:city":"Ferlach",
    "sg:orig_category":"Nachhilfe U Lernbetreuung",
    "sg:phone":"+43 4366 44873888",
    "sg:postcode":"9170",
    "sg:province":"K\u00e4rnten",
    "wof:name":"P\u00e4dagogische Praxis - Legasthenietherapie/Lernberatung",
    "wof:placetype":"venue"
},
  "geometry": {"coordinates":[14.3864421844,46.4714927673],"type":"Point"}
}