{
  "type": "Feature",
  "properties": {
    "iso:country":"AT",
    "sg:address":"Alpenstra\u00dfe 61",
    "sg:orig_category":"Finanzen, Versicherungen",
    "sg:phone":"+43 662 63860",
    "sg:postcode":"5033",
    "sg:website":"http://www.wuestenrot.co.at",
    "wof:name":"W\u00fcstenrot Versicherungs-AG",
    "wof:placetype":"venue"
},
  "geometry": {"coordinates":[13.0433702469,47.8006706238],"type":"Point"}
}