{
  "type": "Feature",
  "properties": {
    "addr:full":"Shuttleworthstr 6-8 Wien Wien 1210",
    "addr:housenumber":"6-8",
    "addr:postcode":"1210",
    "addr:street":"Shuttleworthstr",
    "iso:country":"AT",
    "sg:address":"Shuttleworthstr 6-8",
    "sg:city":"Wien",
    "sg:orig_category":"Behinderungen / Leben Mit Behinderungen",
    "sg:phone":"+43 1 291003470",
    "sg:postcode":"1210",
    "sg:province":"Wien",
    "wof:name":"Jugend am Werk",
    "wof:placetype":"venue"
},
  "geometry": {"coordinates":[16.4108753204,48.2707481384],"type":"Point"}
}