{
  "type": "Feature",
  "properties": {
    "addr:full":"Sonnseite 9 Schwaz Tirol 6130",
    "addr:housenumber":"9",
    "addr:postcode":"6130",
    "addr:street":"Sonnseite;Tirol",
    "iso:country":"AT",
    "sg:address":"Sonnseite 9",
    "sg:city":"Schwaz",
    "sg:orig_category":"Strick- U Wirkwaren / Erzeugung U Gro\u00c3\u0178handel",
    "sg:phone":"+43 5242 62224",
    "sg:postcode":"6130",
    "sg:province":"Tirol",
    "wof:name":"Kr\u00e4mer Franz",
    "wof:placetype":"venue"
},
  "geometry": {"coordinates":[11.7019290924,47.3427276611],"type":"Point"}
}