{
  "type": "Feature",
  "properties": {
    "addr:full":"Sonnenstr 12a Innsbruck Tirol 6020",
    "addr:housenumber":"12a",
    "addr:postcode":"6020",
    "addr:street":"Sonnenstr;Tirol",
    "iso:country":"AT",
    "sg:address":"Sonnenstr 12a",
    "sg:city":"Innsbruck",
    "sg:orig_category":"Filmproduktionen",
    "sg:phone":"+43 650 5531985",
    "sg:postcode":"6020",
    "sg:province":"Tirol",
    "wof:name":"art2rent",
    "wof:placetype":"venue"
},
  "geometry": {"coordinates":[11.381696701,47.2666511536],"type":"Point"}
}