{
  "type": "Feature",
  "properties": {
    "addr:full":"Leoganger Str 18a Saalfelden am Steinernen Meer Salzburg 5760",
    "addr:housenumber":"18a",
    "addr:postcode":"5760",
    "addr:street":"Str",
    "iso:country":"AT",
    "sg:address":"Leoganger Str 18a",
    "sg:city":"Saalfelden am Steinernen Meer",
    "sg:orig_category":"Tankstellen",
    "sg:phone":"+43 4365 8272376",
    "sg:postcode":"5760",
    "sg:province":"Salzburg",
    "wof:name":"JET Tankstelle",
    "wof:placetype":"venue"
},
  "geometry": {"coordinates":[12.8424301147,47.4294281006],"type":"Point"}
}