{
  "type": "Feature",
  "properties": {
    "addr:full":"Baumgartnerstr 2 Kufstein Tirol 6330",
    "addr:housenumber":"2",
    "addr:postcode":"6330",
    "addr:street":"Baumgartnerstr;Tirol",
    "iso:country":"AT",
    "sg:address":"Baumgartnerstr 2",
    "sg:city":"Kufstein",
    "sg:orig_category":"Friseure U Frisiersalons",
    "sg:phone":"+43 4353 7262291",
    "sg:postcode":"6330",
    "sg:province":"Tirol",
    "wof:name":"Outfit Friseursalon",
    "wof:placetype":"venue"
},
  "geometry": {"coordinates":[12.1699304581,47.5799865723],"type":"Point"}
}