{
  "type": "Feature",
  "properties": {
    "addr:full":"Mitterweg 4 Putzleinsdorf Ober\u00f6sterreich 4134",
    "addr:housenumber":"4",
    "addr:postcode":"4134",
    "addr:street":"Mitterweg",
    "iso:country":"AT",
    "sg:address":"Mitterweg 4",
    "sg:city":"Putzleinsdorf",
    "sg:orig_category":"Bierlokale-Pubs",
    "sg:phone":"+43 7286 7137",
    "sg:postcode":"4134",
    "sg:province":"Ober\u00f6sterreich",
    "wof:name":"Cafe-Pub Winkler",
    "wof:placetype":"venue"
},
  "geometry": {"coordinates":[13.8721313477,48.5135116577],"type":"Point"}
}