{
  "type": "Feature",
  "properties": {
    "addr:full":"S\u00f6dingbergstr 2 S\u00f6ding Steiermark 8561",
    "addr:housenumber":"2",
    "addr:postcode":"8561",
    "addr:street":"Soedingbergstr",
    "iso:country":"AT",
    "sg:address":"S\u00f6dingbergstr 2",
    "sg:city":"S\u00f6ding",
    "sg:orig_category":"Friseure U Frisiersalons",
    "sg:phone":"+43 4331 3750468",
    "sg:postcode":"8561",
    "sg:province":"Steiermark",
    "wof:name":"Haarstudio Simone",
    "wof:placetype":"venue"
},
  "geometry": {"coordinates":[-83.223487854,38.0187950134],"type":"Point"}
}