{
  "type": "Feature",
  "properties": {
    "addr:full":"G\u00fcpferlingstr 7 Wien Wien 1170",
    "addr:housenumber":"7",
    "addr:postcode":"1170",
    "addr:street":"Guepferlingstr",
    "iso:country":"AT",
    "sg:address":"G\u00fcpferlingstr 7",
    "sg:city":"Wien",
    "sg:classifiers":[
        {
            "category":"Restaurant",
            "type":"Food & Drink"
        }
    ],
    "sg:phone":"+43 1 4894314",
    "sg:postcode":"1170",
    "sg:province":"Wien",
    "sg:tags":[
        "pizzeria"
    ],
    "wof:name":"Ristorante Caorle Pizzeria",
    "wof:placetype":"venue"
},
  "geometry": {"coordinates":[16.3308048248,48.2193107605],"type":"Point"}
}