{
  "type": "Feature",
  "properties": {
    "addr:full":"Wulkal\u00e4nde 4 Mattersburg Burgenland 7210",
    "addr:housenumber":"4",
    "addr:postcode":"7210",
    "addr:street":"Wulkalaende",
    "iso:country":"AT",
    "sg:address":"Wulkal\u00e4nde 4",
    "sg:city":"Mattersburg",
    "sg:orig_category":"Hauptschulen",
    "sg:phone":"+43 2626 62802",
    "sg:postcode":"7210",
    "sg:province":"Burgenland",
    "wof:name":"Hauptschule",
    "wof:placetype":"venue"
},
  "geometry": {"coordinates":[16.4093818665,47.7377662659],"type":"Point"}
}