{
  "type": "Feature",
  "properties": {
    "addr:full":"Unternalb 25 Retz Nieder\u00f6sterreich 2070",
    "addr:housenumber":"25",
    "addr:postcode":"2070",
    "addr:street":"Unternalb",
    "iso:country":"AT",
    "sg:address":"Unternalb 25",
    "sg:city":"Retz",
    "sg:orig_category":"Behinderungen / Leben Mit Behinderungen",
    "sg:phone":"+43 2942 32700",
    "sg:postcode":"2070",
    "sg:province":"Nieder\u00f6sterreich",
    "wof:name":"Caritas d Erzdi\u00f6zese Wien - Behindertenheim Unternalb",
    "wof:placetype":"venue"
},
  "geometry": {"coordinates":[15.9532260895,48.7432937622],"type":"Point"}
}