{
  "type": "Feature",
  "properties": {
    "addr:full":"Rosenegg 32 Fieberbrunn Tirol 6391",
    "addr:housenumber":"32",
    "addr:postcode":"6391",
    "addr:street":"Rosenegg;Tirol",
    "iso:country":"AT",
    "sg:address":"Rosenegg 32",
    "sg:city":"Fieberbrunn",
    "sg:orig_category":"Damenmoden",
    "sg:phone":"+43 4353 5452767",
    "sg:postcode":"6391",
    "sg:province":"Tirol",
    "wof:name":"KiK Textilien u Non-Food GesmbH",
    "wof:placetype":"venue"
},
  "geometry": {"coordinates":[12.5290489197,47.488193512],"type":"Point"}
}