{
  "type": "Feature",
  "properties": {
    "iso:country":"AT",
    "sg:address":"Falterweg 19b",
    "sg:city":"Linz",
    "sg:orig_category":"Tabaktrafiken",
    "sg:phone":"+43 732 320190",
    "sg:postcode":"4030",
    "sg:province":"Ober\u00f6sterreich",
    "wof:name":"Hagendorf Fritz",
    "wof:placetype":"venue"
},
  "geometry": {"coordinates":[14.3615999222,48.2523727417],"type":"Point"}
}