{
  "type": "Feature",
  "properties": {
    "addr:full":"Sylvester-Wagner-Str 5 Salzburg Salzburg 5020",
    "addr:housenumber":"5",
    "addr:postcode":"5020",
    "addr:street":"Sylvester-Wagner-Str;Salzburg",
    "iso:country":"AT",
    "sg:address":"Sylvester-Wagner-Str 5",
    "sg:city":"Salzburg",
    "sg:orig_category":"Schmiermittel",
    "sg:phone":"+43 4366 2872498",
    "sg:postcode":"5020",
    "sg:province":"Salzburg",
    "wof:name":"Konitzer R Ing GesmbH",
    "wof:placetype":"venue"
},
  "geometry": {"coordinates":[13.0529460907,47.8180923462],"type":"Point"}
}