{
  "type": "Feature",
  "properties": {
    "addr:full":"B\u00e4rnstetten 5a St. Johann in Tirol Tirol 6380",
    "addr:housenumber":"5a",
    "addr:postcode":"johann;6380",
    "addr:street":"Baernstetten;Tirol",
    "iso:country":"AT",
    "sg:address":"B\u00e4rnstetten 5a",
    "sg:city":"St. Johann in Tirol",
    "sg:classifiers":[
        {
            "category":"Manufacturing",
            "subcategory":"Paper Products",
            "type":"Manufacturing & Wholesale Goods"
        }
    ],
    "sg:phone":"+43 5352 633440",
    "sg:postcode":"6380",
    "sg:province":"Tirol",
    "sg:tags":[
        "brochure",
        "production"
    ],
    "sg:website":"staffner.at",
    "wof:name":"Druckerei Staffner Ges.m.b.H.",
    "wof:placetype":"venue"
},
  "geometry": {"coordinates":[12.4263467789,47.5309791565],"type":"Point"}
}