{
  "type": "Feature",
  "properties": {
    "addr:full":"Zinzendorfg 14 Graz Steiermark 8010",
    "addr:housenumber":"14",
    "addr:postcode":"8010",
    "addr:street":"Zinzendorfg",
    "iso:country":"AT",
    "sg:address":"Zinzendorfg 14",
    "sg:city":"Graz",
    "sg:orig_category":"Fleischhauereien",
    "sg:phone":"+43 316 319195",
    "sg:postcode":"8010",
    "sg:province":"Steiermark",
    "wof:name":"Mosshammer & Partner OEG",
    "wof:placetype":"venue"
},
  "geometry": {"coordinates":[15.4477977753,47.075302124],"type":"Point"}
}