{
  "type": "Feature",
  "properties": {
    "addr:full":"Schulstr 2 St. Georgen Salzburg 5113",
    "addr:housenumber":"2",
    "addr:postcode":"5113",
    "addr:street":"Schulstr",
    "iso:country":"AT",
    "sg:address":"Schulstr 2",
    "sg:city":"St. Georgen",
    "sg:orig_category":"Tischlereien",
    "sg:phone":"+43 4362 728106",
    "sg:postcode":"5113",
    "sg:province":"Salzburg",
    "wof:name":"Lepperdinger Hermann",
    "wof:placetype":"venue"
},
  "geometry": {"coordinates":[12.8907194138,47.9691848755],"type":"Point"}
}