{
  "type": "Feature",
  "properties": {
    "iso:country":"AT",
    "sg:address":"Nr 9",
    "sg:city":"Maria Rojach",
    "sg:orig_category":"Transportunternehmen",
    "sg:phone":"+43 4355 2022",
    "sg:postcode":"9422",
    "sg:province":"K\u00e4rnten",
    "wof:name":"Pachoinig Erwin",
    "wof:placetype":"venue"
},
  "geometry": {"coordinates":[14.9049329758,46.7435035706],"type":"Point"}
}