{
  "type": "Feature",
  "properties": {
    "addr:full":"Arlbergstr 69 St. Anton am Arlberg Tirol 6580",
    "addr:housenumber":"69",
    "addr:postcode":"6580",
    "addr:street":"Arlbergstr",
    "iso:country":"AT",
    "sg:address":"Arlbergstr 69",
    "sg:city":"St. Anton am Arlberg",
    "sg:classifiers":[
        {
            "category":"Travel",
            "subcategory":"Hotels & Motels",
            "type":"Entertainment"
        }
    ],
    "sg:phone":"+43 5446 29100",
    "sg:postcode":"6580",
    "sg:province":"Tirol",
    "wof:name":"St Antoner Hof",
    "wof:placetype":"venue"
},
  "geometry": {"coordinates":[10.2684497833,47.1296081543],"type":"Point"}
}