{
  "type": "Feature",
  "properties": {
    "addr:full":"Nr 38 Trofaiach Steiermark 8793",
    "addr:postcode":"8793",
    "addr:street":"Nr 38",
    "iso:country":"AT",
    "sg:address":"Nr 38",
    "sg:city":"Trofaiach",
    "sg:orig_category":"Personalbereitstellung",
    "sg:phone":"+43 3847 34053",
    "sg:postcode":"8793",
    "sg:province":"Steiermark",
    "wof:name":"IRONMAN P.C. Personalleasing GmbH",
    "wof:placetype":"venue"
},
  "geometry": {"coordinates":[14.969628334,47.4129219055],"type":"Point"}
}