{
  "type": "Feature",
  "properties": {
    "addr:full":"Deuringstr 5 Bregenz Vorarlberg 6900",
    "addr:housenumber":"5",
    "addr:postcode":"6900",
    "addr:street":"Deuringstr",
    "iso:country":"AT",
    "sg:address":"Deuringstr 5",
    "sg:city":"Bregenz",
    "sg:orig_category":"Restaurants: Griechisch",
    "sg:phone":"+43 5574 52954",
    "sg:postcode":"6900",
    "sg:province":"Vorarlberg",
    "wof:name":"Gasthof Ikaros",
    "wof:placetype":"venue"
},
  "geometry": {"coordinates":[9.7476406097,47.5026435852],"type":"Point"}
}