{
  "type": "Feature",
  "properties": {
    "addr:full":"Grazer Str 10 Mariazell Steiermark 8630",
    "addr:postcode":"8630",
    "addr:street":"Str 10",
    "iso:country":"AT",
    "sg:address":"Grazer Str 10",
    "sg:city":"Mariazell",
    "sg:classifiers":[
        {
            "category":"Travel",
            "subcategory":"Hotels & Motels",
            "type":"Entertainment"
        }
    ],
    "sg:phone":"+43 3882 21790",
    "sg:postcode":"8630",
    "sg:province":"Steiermark",
    "sg:website":"mariazell.at/wirtschaft/pirker",
    "wof:name":"Hotel Mariazellerhof Konditorei-Cafe-Lebzelterei",
    "wof:placetype":"venue"
},
  "geometry": {"coordinates":[15.3162250519,47.7723388672],"type":"Point"}
}