{
  "type": "Feature",
  "properties": {
    "addr:full":"G\u00e4rtnerweg 2A Spitz Nieder\u00f6sterreich 3620",
    "addr:housenumber":"2a",
    "addr:postcode":"3620",
    "addr:street":"Gaertnerweg",
    "iso:country":"AT",
    "sg:address":"G\u00e4rtnerweg 2A",
    "sg:city":"Spitz",
    "sg:orig_category":"Transportunternehmen",
    "sg:phone":"+43 2713 2094",
    "sg:postcode":"3620",
    "sg:province":"Nieder\u00f6sterreich",
    "wof:name":"Rehberger Josef",
    "wof:placetype":"venue"
},
  "geometry": {"coordinates":[15.4193649292,48.3656196594],"type":"Point"}
}