{
  "type": "Feature",
  "properties": {
    "addr:full":"Haidenstr Parz 380/8 Ottenschlag Nieder\u00f6sterreich 3631",
    "addr:housenumber":"380 / 8;3631",
    "addr:street":"Parz;Ottenschlag Niederoesterreich",
    "iso:country":"AT",
    "sg:address":"Haidenstr Parz 380/8",
    "sg:city":"Ottenschlag",
    "sg:orig_category":"Hobbyvereine",
    "sg:phone":"+43 2872 6615",
    "sg:postcode":"3631",
    "sg:province":"Nieder\u00f6sterreich",
    "wof:name":"Country & Western Club Fort Swanee Hunt",
    "wof:placetype":"venue"
},
  "geometry": {"coordinates":[15.222495079,48.3943595886],"type":"Point"}
}