{
  "type": "Feature",
  "properties": {
    "iso:country":"AT",
    "sg:address":"Passauer Pl 6",
    "sg:city":"Wien",
    "sg:orig_category":"Gutsverwaltungen",
    "sg:phone":"+43 1 5338161",
    "sg:postcode":"1010",
    "sg:province":"Wien",
    "wof:name":"Czell'sche Gutsverwaltung - Inh Vivian Czell",
    "wof:placetype":"venue"
},
  "geometry": {"coordinates":[16.3702964783,48.2130813599],"type":"Point"}
}