{
  "type": "Feature",
  "properties": {
    "iso:country":"AT",
    "sg:address":"Sennereistr 10",
    "sg:city":"Schlins",
    "sg:orig_category":"Genossenschaften",
    "sg:phone":"+43 5524 2340",
    "sg:postcode":"6824",
    "sg:province":"Vorarlberg",
    "wof:name":"Sennereigenossenschaft Schlins-R\u00f6ns und Umgebung regGenmbH",
    "wof:placetype":"venue"
},
  "geometry": {"coordinates":[9.6990251541,47.2049789429],"type":"Point"}
}