{
  "type": "Feature",
  "properties": {
    "iso:country":"AT",
    "sg:address":"Hohe Munde-Str 589",
    "sg:city":"Seefeld in Tirol",
    "sg:orig_category":"Tourismusinformation U -Organisationen",
    "sg:phone":"+43 4352 1248800",
    "sg:postcode":"6100",
    "sg:province":"Tirol",
    "wof:name":"A-VITA Veranstaltungs-GmbH",
    "wof:placetype":"venue"
},
  "geometry": {"coordinates":[11.1834783554,47.3304214478],"type":"Point"}
}