{
  "type": "Feature",
  "properties": {
    "addr:full":"Garbergasse 12 Wien Wien 1060",
    "addr:housenumber":"12",
    "addr:postcode":"1060",
    "addr:street":"Garbergasse",
    "iso:country":"AT",
    "sg:address":"Garbergasse 12",
    "sg:city":"Wien",
    "sg:orig_category":"Crowd Barriers",
    "sg:phone":"+43 1 5964754",
    "sg:postcode":"1060",
    "sg:province":"Wien",
    "sg:website":"kleinlercher.net",
    "wof:name":"Bernhard Kleinlercher Betriebsausstattung & Pr\u00e4sentationstechnik",
    "wof:placetype":"venue"
},
  "geometry": {"coordinates":[16.3441524506,48.1932868958],"type":"Point"}
}