{
  "type": "Feature",
  "properties": {
    "addr:full":"Klosterstr 276 Seefeld in Tirol Tirol 6100",
    "addr:housenumber":"276",
    "addr:postcode":"6100",
    "addr:street":"Seefeld;Tirol",
    "iso:country":"AT",
    "sg:address":"Klosterstr 276",
    "sg:city":"Seefeld in Tirol",
    "sg:orig_category":"Lebensmittel / Einzelhandel",
    "sg:phone":"+43 5212 62620",
    "sg:postcode":"6100",
    "sg:province":"Tirol",
    "wof:name":"MPREIS WarenvertriebsgesmbH",
    "wof:placetype":"venue"
},
  "geometry": {"coordinates":[11.1857070923,47.3290481567],"type":"Point"}
}