{
  "type": "Feature",
  "properties": {
    "addr:full":"Hermannstr 11 Klosterneuburg Nieder\u00f6sterreich 3400",
    "addr:housenumber":"11",
    "addr:postcode":"3400",
    "addr:street":"Hermannstr;Niederoesterreich",
    "iso:country":"AT",
    "sg:address":"Hermannstr 11",
    "sg:city":"Klosterneuburg",
    "sg:orig_category":"Hauptschulen",
    "sg:phone":"+43 2243 444323",
    "sg:postcode":"3400",
    "sg:province":"Nieder\u00f6sterreich",
    "wof:name":"Hauptschule",
    "wof:placetype":"venue"
},
  "geometry": {"coordinates":[16.3233451843,48.3033981323],"type":"Point"}
}