{
  "type": "Feature",
  "properties": {
    "iso:country":"AT",
    "sg:address":"Wildpretstr 7",
    "sg:city":"Wien",
    "sg:orig_category":"Stra\u00c3\u0178enbau",
    "sg:phone":"+43 5 06262053",
    "sg:postcode":"1110",
    "sg:province":"Wien",
    "wof:name":"ALLBAU - Allgemeine Stra\u00dfenbau GmbH",
    "wof:placetype":"venue"
},
  "geometry": {"coordinates":[16.4464263916,48.1785812378],"type":"Point"}
}