{
  "type": "Feature",
  "properties": {
    "addr:full":"Oberdorf 50 Ardning Steiermark 8904",
    "addr:housenumber":"50",
    "addr:postcode":"8904",
    "addr:street":"Oberdorf",
    "iso:country":"AT",
    "sg:address":"Oberdorf 50",
    "sg:city":"Ardning",
    "sg:orig_category":"Psychologen",
    "sg:phone":"+43 3612 76663",
    "sg:postcode":"8904",
    "sg:province":"Steiermark",
    "wof:name":"Joast Martina Mag",
    "wof:placetype":"venue"
},
  "geometry": {"coordinates":[14.3644237518,47.5910682678],"type":"Point"}
}