{
  "type": "Feature",
  "properties": {
    "addr:full":"Wagramer Str 124 Wien Wien 1220",
    "addr:housenumber":"124",
    "addr:postcode":"1220",
    "iso:country":"AT",
    "sg:address":"Wagramer Str 124",
    "sg:city":"Wien",
    "sg:orig_category":"Autovermietung",
    "sg:phone":"+43 1 2036978",
    "sg:postcode":"1220",
    "sg:province":"Wien",
    "wof:name":"DENZELDRIVE Carsharing GmbH - Wien-Nord",
    "wof:placetype":"venue"
},
  "geometry": {"coordinates":[16.4411373138,48.2471885681],"type":"Point"}
}