{
  "type": "Feature",
  "properties": {
    "addr:full":"Rudolf-Hausner-G 12 Wien Wien 1220",
    "addr:housenumber":"12",
    "addr:postcode":"1220",
    "addr:street":"Rudolf-Hausner-G",
    "iso:country":"AT",
    "sg:address":"Rudolf-Hausner-G 12",
    "sg:city":"Wien",
    "sg:orig_category":"Elektrische Heizungen",
    "sg:phone":"+43 1 73427470",
    "sg:postcode":"1220",
    "sg:province":"Wien",
    "wof:name":"Elitec Elektrotechnik HandelsgesmbH",
    "wof:placetype":"venue"
},
  "geometry": {"coordinates":[16.4751167297,48.2644882202],"type":"Point"}
}