{
  "type": "Feature",
  "properties": {
    "addr:full":"Bergsteigg 26 Wien Wien 1170",
    "addr:housenumber":"26",
    "addr:postcode":"1170",
    "addr:street":"Bergsteigg",
    "iso:country":"AT",
    "sg:address":"Bergsteigg 26",
    "sg:city":"Wien",
    "sg:orig_category":"Armaturen / Erzeugung U Gro\u00c3\u0178handel",
    "sg:phone":"+43 4314 024951",
    "sg:postcode":"1170",
    "sg:province":"Wien",
    "wof:name":"SAM Schulte Armaturen u Metallwaren HandelsgesmbH",
    "wof:placetype":"venue"
},
  "geometry": {"coordinates":[16.3350086212,48.2171821594],"type":"Point"}
}