{
  "type": "Feature",
  "properties": {
    "addr:full":"Ballg 5 Wien Wien 1010",
    "addr:housenumber":"5",
    "addr:postcode":"1010",
    "addr:street":"Ballg",
    "iso:country":"AT",
    "sg:address":"Ballg 5",
    "sg:city":"Wien",
    "sg:classifiers":[
        {
            "category":"Restaurant",
            "type":"Food & Drink"
        }
    ],
    "sg:phone":"+43 4315 129982",
    "sg:postcode":"1010",
    "sg:province":"Wien",
    "sg:website":"zimolo.at",
    "wof:name":"Zimolo Ristorante - Inh Renato Zimolo",
    "wof:placetype":"venue"
},
  "geometry": {"coordinates":[16.3688049316,48.2025489807],"type":"Point"}
}