{
  "type": "Feature",
  "properties": {
    "addr:full":"Bad Aussee Steiermark 8990",
    "addr:postcode":"8990",
    "iso:country":"AT",
    "sg:city":"Bad Aussee",
    "sg:orig_category":"Feuerwehren",
    "sg:phone":"+43 3622 52510",
    "sg:postcode":"8990",
    "sg:province":"Steiermark",
    "wof:name":"Feuerwehr Obertressen",
    "wof:placetype":"venue"
},
  "geometry": {"coordinates":[13.783372879,47.6095199585],"type":"Point"}
}