{
  "type": "Feature",
  "properties": {
    "addr:full":"Weidenweg 338 Friedberg Steiermark 8240",
    "addr:housenumber":"338",
    "addr:postcode":"8240",
    "addr:street":"Weidenweg",
    "iso:country":"AT",
    "sg:address":"Weidenweg 338",
    "sg:city":"Friedberg",
    "sg:orig_category":"Baumeister",
    "sg:phone":"+43 3339 25195",
    "sg:postcode":"8240",
    "sg:province":"Steiermark",
    "wof:name":"Mitterm\u00fcller GmbH",
    "wof:placetype":"venue"
},
  "geometry": {"coordinates":[16.0531902313,47.4329833984],"type":"Point"}
}