{
  "type": "Feature",
  "properties": {
    "addr:full":"Seenstr 12 K\u00fchnsdorf K\u00e4rnten 9125",
    "addr:housenumber":"12",
    "addr:postcode":"9125",
    "addr:street":"Seenstr;Kaernten",
    "iso:country":"AT",
    "sg:address":"Seenstr 12",
    "sg:city":"K\u00fchnsdorf",
    "sg:orig_category":"Tonstudios",
    "sg:phone":"+43 4232 27583",
    "sg:postcode":"9125",
    "sg:province":"K\u00e4rnten",
    "wof:name":"Quetschnmusi Musikproduktionen",
    "wof:placetype":"venue"
},
  "geometry": {"coordinates":[14.615363121,46.6193237305],"type":"Point"}
}