{
  "type": "Feature",
  "properties": {
    "addr:full":"Marktpl 1 Oberdrauburg K\u00e4rnten 9781",
    "addr:housenumber":"1",
    "addr:postcode":"9781",
    "addr:street":"Marktpl;Kaernten",
    "iso:country":"AT",
    "sg:address":"Marktpl 1",
    "sg:city":"Oberdrauburg",
    "sg:orig_category":"Gemeinden",
    "sg:phone":"+43 4710 22480",
    "sg:postcode":"9781",
    "sg:province":"K\u00e4rnten",
    "wof:name":"Marktgemeinde Oberdrauburg",
    "wof:placetype":"venue"
},
  "geometry": {"coordinates":[12.9699077606,46.7482032776],"type":"Point"}
}