{
  "type": "Feature",
  "properties": {
    "addr:full":"Forststr 14 Kirchbichl Tirol 6322",
    "addr:housenumber":"14",
    "addr:postcode":"6322",
    "addr:street":"Forststr;Tirol",
    "iso:country":"AT",
    "sg:address":"Forststr 14",
    "sg:city":"Kirchbichl",
    "sg:orig_category":"Transportunternehmen",
    "sg:phone":"+43 5332 85010",
    "sg:postcode":"6322",
    "sg:province":"Tirol",
    "wof:name":"Tschenet Herbert",
    "wof:placetype":"venue"
},
  "geometry": {"coordinates":[12.0915117264,47.5092048645],"type":"Point"}
}