{
  "type": "Feature",
  "properties": {
    "iso:country":"AT",
    "sg:address":"Wolfernstr 17",
    "sg:city":"Steyr",
    "sg:orig_category":"Befestigungstechnik",
    "sg:phone":"+43 800 818100",
    "sg:postcode":"4400",
    "sg:province":"Ober\u00f6sterreich",
    "wof:name":"Hilti ProShop Steyr",
    "wof:placetype":"venue"
},
  "geometry": {"coordinates":[14.4078083038,48.0476875305],"type":"Point"}
}