{
  "type": "Feature",
  "properties": {
    "addr:full":"Eisenharting 4 Seeham Salzburg 5164",
    "addr:housenumber":"4",
    "addr:postcode":"5164",
    "addr:street":"Eisenharting;Salzburg",
    "iso:country":"AT",
    "sg:address":"Eisenharting 4",
    "sg:city":"Seeham",
    "sg:classifiers":[
        {
            "category":"Travel",
            "subcategory":"Hotels & Motels",
            "type":"Entertainment"
        }
    ],
    "sg:phone":"+43 6217 55500",
    "sg:postcode":"5164",
    "sg:province":"Salzburg",
    "wof:name":"Hotel-Walkner",
    "wof:placetype":"venue"
},
  "geometry": {"coordinates":[13.0741119385,47.9748954773],"type":"Point"}
}