{
  "type": "Feature",
  "properties": {
    "addr:full":"Untergasse 20 Serfaus Tirol 6534",
    "addr:housenumber":"20",
    "addr:postcode":"6534",
    "addr:street":"Untergasse;Tirol",
    "iso:country":"AT",
    "sg:address":"Untergasse 20",
    "sg:city":"Serfaus",
    "sg:orig_category":"Reisen, Tourismusinfo",
    "sg:postcode":"6534",
    "sg:province":"Tirol",
    "sg:website":"http://www.serfausfissladis.at",
    "wof:name":"Serfaus Fiss Ladis",
    "wof:placetype":"venue"
},
  "geometry": {"coordinates":[10.6094837189,47.0364761353],"type":"Point"}
}