{
  "type": "Feature",
  "properties": {
    "addr:full":"Egg 68 5503",
    "addr:housenumber":"68",
    "addr:postcode":"5503",
    "addr:street":"Egg",
    "iso:country":"AT",
    "sg:address":"Egg 68",
    "sg:orig_category":"Medizin, Medizinische Beratung",
    "sg:phone":"+43 4306 2355729",
    "sg:postcode":"5503",
    "sg:website":"http://www.alpenhof.com/skin/",
    "wof:name":"Dr. Schm\u00f6lzer",
    "wof:placetype":"venue"
},
  "geometry": {"coordinates":[13.2784490585,47.8214645386],"type":"Point"}
}