{
  "type": "Feature",
  "properties": {
    "addr:full":"Klagenfurter Str 60 St. Stefan im Lavanttal K\u00e4rnten 9431",
    "addr:housenumber":"60",
    "addr:postcode":"9431",
    "addr:street":"Str",
    "iso:country":"AT",
    "sg:address":"Klagenfurter Str 60",
    "sg:city":"St. Stefan im Lavanttal",
    "sg:orig_category":"Autoreparatur",
    "sg:phone":"+43 4343 5281230",
    "sg:postcode":"9431",
    "sg:province":"K\u00e4rnten",
    "wof:name":"Welwich KEG",
    "wof:placetype":"venue"
},
  "geometry": {"coordinates":[14.832036972,46.8094558716],"type":"Point"}
}