{
  "type": "Feature",
  "properties": {
    "addr:full":"Marktstr 6 Rauris Salzburg 5661",
    "addr:housenumber":"6",
    "addr:postcode":"5661",
    "addr:street":"Marktstr;Salzburg",
    "iso:country":"AT",
    "sg:address":"Marktstr 6",
    "sg:city":"Rauris",
    "sg:classifiers":[
        {
            "category":"Travel",
            "subcategory":"Hotels & Motels",
            "type":"Entertainment"
        }
    ],
    "sg:phone":"+43 6544 62130",
    "sg:postcode":"5661",
    "sg:province":"Salzburg",
    "wof:name":"Rauriserhof",
    "wof:placetype":"venue"
},
  "geometry": {"coordinates":[12.9931602478,47.2326774597],"type":"Point"}
}