{
  "type": "Feature",
  "properties": {
    "addr:full":"Burgfrieden 12 Hall in Tirol Tirol 6060",
    "addr:housenumber":"12",
    "addr:postcode":"6060",
    "addr:street":"Burgfrieden;Tirol",
    "iso:country":"AT",
    "sg:address":"Burgfrieden 12",
    "sg:city":"Hall in Tirol",
    "sg:classifiers":[
        {
            "category":"Taxi",
            "type":"Transportation"
        }
    ],
    "sg:phone":"+43 4352 2356474",
    "sg:postcode":"6060",
    "sg:province":"Tirol",
    "sg:tags":[
        "personentransporte",
        "u"
    ],
    "wof:name":"Nicolodi & Ehrensperger OEG",
    "wof:placetype":"venue"
},
  "geometry": {"coordinates":[11.4864282608,47.278301239],"type":"Point"}
}