{
  "type": "Feature",
  "properties": {
    "addr:full":"Nibelungeng 3 Wien Wien 1010",
    "addr:housenumber":"3",
    "addr:postcode":"1010",
    "addr:street":"Nibelungeng",
    "iso:country":"AT",
    "sg:address":"Nibelungeng 3",
    "sg:city":"Wien",
    "sg:orig_category":"Montagen U Montagetechnik",
    "sg:phone":"+43 4315 855802",
    "sg:postcode":"1010",
    "sg:province":"Wien",
    "wof:name":"Montech Montage Technik GmbH",
    "wof:placetype":"venue"
},
  "geometry": {"coordinates":[16.3663978577,48.201374054],"type":"Point"}
}