{
  "type": "Feature",
  "properties": {
    "addr:full":"Nr 8a Ischgl Tirol 6561",
    "addr:postcode":"6561",
    "addr:street":"Nr 8A;Tirol",
    "iso:country":"AT",
    "sg:address":"Nr 8a",
    "sg:city":"Ischgl",
    "sg:orig_category":"Pensionen / Privatzimmer",
    "sg:phone":"+43 5444 53390",
    "sg:postcode":"6561",
    "sg:province":"Tirol",
    "wof:name":"Sportpension Persura",
    "wof:placetype":"venue"
},
  "geometry": {"coordinates":[10.2881736755,47.0111351013],"type":"Point"}
}