{
  "type": "Feature",
  "properties": {
    "iso:country":"AT",
    "sg:address":"Nonntaler Hauptstr 120",
    "sg:city":"Salzburg",
    "sg:orig_category":"Steinmetzbetriebe",
    "sg:phone":"+43 662 8352130",
    "sg:postcode":"5020",
    "sg:province":"Salzburg",
    "wof:name":"M!D!M! HandelsgesmbH",
    "wof:placetype":"venue"
},
  "geometry": {"coordinates":[13.0487499237,47.7816734314],"type":"Point"}
}