{
  "type": "Feature",
  "properties": {
    "addr:full":"Walgaustr 26 Klaus-Weiler Vorarlberg 6833",
    "addr:housenumber":"26",
    "addr:postcode":"6833",
    "addr:street":"Walgaustr",
    "iso:country":"AT",
    "sg:address":"Walgaustr 26",
    "sg:city":"Klaus-Weiler",
    "sg:orig_category":"Apotheken",
    "sg:phone":"+43 5523 626060",
    "sg:postcode":"6833",
    "sg:province":"Vorarlberg",
    "wof:name":"St Arbogast-Apotheke Magpharm Doris Moshuber",
    "wof:placetype":"venue"
},
  "geometry": {"coordinates":[9.6512317657,47.2992362976],"type":"Point"}
}