{
  "type": "Feature",
  "properties": {
    "addr:full":"Schl\u00f6gelg 9a Graz Steiermark 8010",
    "addr:housenumber":"9a",
    "addr:postcode":"8010",
    "addr:street":"Schloegelg",
    "iso:country":"AT",
    "sg:address":"Schl\u00f6gelg 9a",
    "sg:city":"Graz",
    "sg:orig_category":"Massagen",
    "sg:phone":"+43 676 3077198",
    "sg:postcode":"8010",
    "sg:province":"Steiermark",
    "wof:name":"Lewin Kevin",
    "wof:placetype":"venue"
},
  "geometry": {"coordinates":[15.44647789,47.0669441223],"type":"Point"}
}