{
  "type": "Feature",
  "properties": {
    "iso:country":"AT",
    "sg:address":"Dr.-Theodor-K\u00f6rner-Pl 4",
    "sg:city":"Eisenerz",
    "sg:orig_category":"Textilreinigung",
    "sg:phone":"+43 4338 482586",
    "sg:postcode":"8790",
    "sg:province":"Steiermark",
    "wof:name":"Koschnik Nicole",
    "wof:placetype":"venue"
},
  "geometry": {"coordinates":[14.8849449158,47.5429267883],"type":"Point"}
}