{
  "type": "Feature",
  "properties": {
    "addr:full":"Nr 67 St. Egyden am Steinfeld Nieder\u00f6sterreich 2731",
    "addr:postcode":"2731",
    "addr:street":"Nr 67",
    "iso:country":"AT",
    "sg:address":"Nr 67",
    "sg:city":"St. Egyden am Steinfeld",
    "sg:orig_category":"Bauunternehmen",
    "sg:phone":"+43 2638 77445",
    "sg:postcode":"2731",
    "sg:province":"Nieder\u00f6sterreich",
    "wof:name":"Hochegger Matthias Ing",
    "wof:placetype":"venue"
},
  "geometry": {"coordinates":[16.1024875641,47.7818527222],"type":"Point"}
}