{
  "type": "Feature",
  "properties": {
    "iso:country":"AT",
    "sg:address":"Br\u00fchl 4",
    "sg:city":"M\u00e4der",
    "sg:orig_category":"Volksschulen",
    "sg:phone":"+43 5523 6400750",
    "sg:postcode":"6841",
    "sg:province":"Vorarlberg",
    "wof:name":"Volksschule",
    "wof:placetype":"venue"
},
  "geometry": {"coordinates":[-92.94867706300001,31.5349597931],"type":"Point"}
}