{
  "type": "Feature",
  "properties": {
    "addr:full":"Linke Wienzeile 42/3 Wien Wien 1060",
    "addr:housenumber":"42 / 3",
    "addr:postcode":"1060",
    "addr:street":"Linke Wienzeile",
    "iso:country":"AT",
    "sg:address":"Linke Wienzeile 42/3",
    "sg:city":"Wien",
    "sg:orig_category":"Modellagenturen",
    "sg:phone":"+43 1 5858249",
    "sg:postcode":"1060",
    "sg:province":"Wien",
    "sg:website":"www.modelrepublic.at",
    "wof:name":"model republic",
    "wof:placetype":"venue"
},
  "geometry": {"coordinates":[16.3589172363,48.1973075867],"type":"Point"}
}