{
  "type": "Feature",
  "properties": {
    "addr:full":"Schreiberweg 55 Wien Wien 1190",
    "addr:housenumber":"55",
    "addr:postcode":"1190",
    "addr:street":"Schreiberweg",
    "iso:country":"AT",
    "sg:address":"Schreiberweg 55",
    "sg:city":"Wien",
    "sg:orig_category":"Betriebsbeteiligungen",
    "sg:phone":"+43 4315 864230",
    "sg:postcode":"1190",
    "sg:province":"Wien",
    "wof:name":"Drapal GesmbH",
    "wof:placetype":"venue"
},
  "geometry": {"coordinates":[16.342924118,48.2581672668],"type":"Point"}
}