{
  "type": "Feature",
  "properties": {
    "addr:full":"Hauptstr 56 Yspertal Nieder\u00f6sterreich 3683",
    "addr:housenumber":"56",
    "addr:postcode":"3683",
    "addr:street":"Hauptstr",
    "iso:country":"AT",
    "sg:address":"Hauptstr 56",
    "sg:city":"Yspertal",
    "sg:orig_category":"Tischlereien",
    "sg:phone":"+43 4374 1565260",
    "sg:postcode":"3683",
    "sg:province":"Nieder\u00f6sterreich",
    "wof:name":"Sch\u00f6n M GesmbH",
    "wof:placetype":"venue"
},
  "geometry": {"coordinates":[15.0681600571,48.2892379761],"type":"Point"}
}