{
  "type": "Feature",
  "properties": {
    "addr:full":"Hauptstrasse 76 Bernstein Burgenland 7434",
    "addr:housenumber":"76",
    "addr:postcode":"7434",
    "addr:street":"Hauptstrasse",
    "iso:country":"AT",
    "sg:address":"Hauptstrasse 76",
    "sg:city":"Bernstein",
    "sg:classifiers":[
        {
            "category":"Manufacturing",
            "subcategory":"Furniture",
            "type":"Manufacturing & Wholesale Goods"
        }
    ],
    "sg:phone":"+43 3354 6589",
    "sg:postcode":"7434",
    "sg:province":"Burgenland",
    "sg:tags":[
        "beech"
    ],
    "wof:name":"Josef Wallner",
    "wof:placetype":"venue"
},
  "geometry": {"coordinates":[16.2638816833,47.408657074],"type":"Point"}
}