{
  "type": "Feature",
  "properties": {
    "addr:full":"Hauptstr 36 Stra\u00dfburg K\u00e4rnten 9341",
    "addr:housenumber":"36",
    "addr:postcode":"9341",
    "addr:street":"Hauptstr;Kaernten",
    "iso:country":"AT",
    "sg:address":"Hauptstr 36",
    "sg:city":"Stra\u00dfburg",
    "sg:orig_category":"Feuerwehren",
    "sg:phone":"+43 4266 2333",
    "sg:postcode":"9341",
    "sg:province":"K\u00e4rnten",
    "wof:name":"Freiwillige Feuerwehr Stra\u00dfburg",
    "wof:placetype":"venue"
},
  "geometry": {"coordinates":[-94.07168579099999,34.2320823669],"type":"Point"}
}