{
  "type": "Feature",
  "properties": {
    "addr:full":"Schmieding 5 Kronstorf Ober\u00f6sterreich 4484",
    "addr:housenumber":"5",
    "addr:postcode":"4484",
    "addr:street":"Schmieding",
    "iso:country":"AT",
    "sg:address":"Schmieding 5",
    "sg:city":"Kronstorf",
    "sg:orig_category":"Spenglereien",
    "sg:phone":"+43 4366 41404426",
    "sg:postcode":"4484",
    "sg:province":"Ober\u00f6sterreich",
    "wof:name":"M\u00fchleder Wolfgang",
    "wof:placetype":"venue"
},
  "geometry": {"coordinates":[14.4590215683,48.1520957947],"type":"Point"}
}