{
  "type": "Feature",
  "properties": {
    "iso:country":"AT",
    "sg:address":"Dornauberg 19",
    "sg:city":"Ginzling",
    "sg:orig_category":"Maschinenreparatur",
    "sg:phone":"+43 5286 5258",
    "sg:postcode":"6295",
    "sg:province":"Tirol",
    "wof:name":"Klausner Franz",
    "wof:placetype":"venue"
},
  "geometry": {"coordinates":[11.8085803986,47.1002845764],"type":"Point"}
}