{
  "type": "Feature",
  "properties": {
    "iso:country":"AT",
    "sg:address":"Felbigerg 97",
    "sg:city":"Wien",
    "sg:orig_category":"Volksschulen",
    "sg:phone":"+43 1 9148584",
    "sg:postcode":"1140",
    "sg:province":"Wien",
    "wof:name":"Schulen d Stadt Wien",
    "wof:placetype":"venue"
},
  "geometry": {"coordinates":[16.2830448151,48.1962013245],"type":"Point"}
}