{
  "type": "Feature",
  "properties": {
    "addr:full":"W\u00f6ranstr 5 Gramastetten Ober\u00f6sterreich 4201",
    "addr:housenumber":"5",
    "addr:postcode":"4201",
    "addr:street":"Woeranstr",
    "iso:country":"AT",
    "sg:address":"W\u00f6ranstr 5",
    "sg:city":"Gramastetten",
    "sg:orig_category":"Blumeneinzelhandel",
    "sg:phone":"+43 7239 8153",
    "sg:postcode":"4201",
    "sg:province":"Ober\u00f6sterreich",
    "wof:name":"Handlbauer Sylvia",
    "wof:placetype":"venue"
},
  "geometry": {"coordinates":[14.1936101913,48.3802757263],"type":"Point"}
}