{
  "type": "Feature",
  "properties": {
    "addr:full":"Karmeliterg 10 Wien Wien 1020",
    "addr:housenumber":"10",
    "addr:postcode":"1020",
    "addr:street":"Karmeliterg",
    "iso:country":"AT",
    "sg:address":"Karmeliterg 10",
    "sg:city":"Wien",
    "sg:orig_category":"Non-Classified Establishments",
    "sg:phone":"+43 1 2128042",
    "sg:postcode":"1020",
    "sg:province":"Wien",
    "wof:name":"Kleine Br\u00fcder v Lamm",
    "wof:placetype":"venue"
},
  "geometry": {"coordinates":[16.3800163269,48.2162513733],"type":"Point"}
}