{
  "type": "Feature",
  "properties": {
    "iso:country":"AT",
    "sg:address":"Viktringer Ring 23",
    "sg:city":"Klagenfurt",
    "sg:orig_category":"Architekten",
    "sg:phone":"+43 463 554300",
    "sg:postcode":"9020",
    "sg:province":"K\u00e4rnten",
    "wof:name":"Rubin Eva Mag arch",
    "wof:placetype":"venue"
},
  "geometry": {"coordinates":[14.3096609116,46.6202049255],"type":"Point"}
}