{
  "type": "Feature",
  "properties": {
    "iso:country":"AT",
    "sg:address":"Oberndorfer Str 9",
    "sg:city":"Purgstall an der Erlauf",
    "sg:orig_category":"Maler, Anstreicher U Lackierer",
    "sg:phone":"+43 4374 898075",
    "sg:postcode":"3251",
    "sg:province":"Nieder\u00f6sterreich",
    "wof:name":"Maler Max GesmbH",
    "wof:placetype":"venue"
},
  "geometry": {"coordinates":[15.1415119171,48.0587997437],"type":"Point"}
}