{
  "type": "Feature",
  "properties": {
    "addr:full":"Herzog-Otto-Str 8 Innsbruck Tirol 6020",
    "addr:housenumber":"8",
    "addr:postcode":"6020",
    "addr:street":"Herzog-Otto-Str;Tirol",
    "iso:country":"AT",
    "sg:address":"Herzog-Otto-Str 8",
    "sg:city":"Innsbruck",
    "sg:orig_category":"Restaurants: Japanisch",
    "sg:phone":"+43 512 560813",
    "sg:postcode":"6020",
    "sg:province":"Tirol",
    "wof:name":"Kenzi-Restaurant",
    "wof:placetype":"venue"
},
  "geometry": {"coordinates":[11.3922252655,47.2687606812],"type":"Point"}
}