{
  "type": "Feature",
  "properties": {
    "addr:full":"Innstr 7 Innsbruck Tirol 6020",
    "addr:housenumber":"7",
    "addr:postcode":"6020",
    "addr:street":"Innstr;Tirol",
    "iso:country":"AT",
    "sg:address":"Innstr 7",
    "sg:city":"Innsbruck",
    "sg:orig_category":"Banken U Sparkassen",
    "sg:phone":"+43 512 22730",
    "sg:postcode":"6020",
    "sg:province":"Tirol",
    "wof:name":"Raiffeisen-Landesbank Tirol AG",
    "wof:placetype":"venue"
},
  "geometry": {"coordinates":[11.3906497955,47.2695884705],"type":"Point"}
}