{
  "type": "Feature",
  "properties": {
    "addr:full":"Hofsteigstr 18a Schwarzach Vorarlberg 6858",
    "addr:housenumber":"18a",
    "addr:postcode":"6858",
    "addr:street":"Hofsteigstr",
    "iso:country":"AT",
    "sg:address":"Hofsteigstr 18a",
    "sg:city":"Schwarzach",
    "sg:orig_category":"Betriebs- U Fernverpflegung",
    "sg:phone":"+43 5572 58420",
    "sg:postcode":"6858",
    "sg:province":"Vorarlberg",
    "wof:name":"Pipan Betriebsverpflegung",
    "wof:placetype":"venue"
},
  "geometry": {"coordinates":[9.7610797882,47.4509277344],"type":"Point"}
}