{
  "type": "Feature",
  "properties": {
    "addr:full":"Mozartstr 14 Amstetten Nieder\u00f6sterreich 3300",
    "addr:housenumber":"14",
    "addr:postcode":"3300",
    "addr:street":"Mozartstr;Niederoesterreich",
    "iso:country":"AT",
    "sg:address":"Mozartstr 14",
    "sg:city":"Amstetten",
    "sg:orig_category":"Autovermietung",
    "sg:phone":"+43 7472 617180",
    "sg:postcode":"3300",
    "sg:province":"Nieder\u00f6sterreich",
    "wof:name":"Autoverleih Buchbinder",
    "wof:placetype":"venue"
},
  "geometry": {"coordinates":[14.880320549,48.1240577698],"type":"Point"}
}