{
  "type": "Feature",
  "properties": {
    "iso:country":"AT",
    "sg:address":"Untere Klaus 14",
    "sg:city":"Schladming",
    "sg:orig_category":"Massagen",
    "sg:phone":"+43 664 4306688",
    "sg:postcode":"8970",
    "sg:province":"Steiermark",
    "wof:name":"Sieder Petra",
    "wof:placetype":"venue"
},
  "geometry": {"coordinates":[13.7011709213,47.4016685486],"type":"Point"}
}