{
  "type": "Feature",
  "properties": {
    "addr:full":"Hans-Reither-G 2 Gm\u00fcnd Nieder\u00f6sterreich 3950",
    "addr:housenumber":"2",
    "addr:postcode":"3950",
    "addr:street":"Hans-Reither-G;Niederoesterreich",
    "iso:country":"AT",
    "sg:address":"Hans-Reither-G 2",
    "sg:city":"Gm\u00fcnd",
    "sg:orig_category":"Fleischhauereien",
    "sg:phone":"+43 2852 52676",
    "sg:postcode":"3950",
    "sg:province":"Nieder\u00f6sterreich",
    "wof:name":"Hirsch Johann",
    "wof:placetype":"venue"
},
  "geometry": {"coordinates":[14.9686613083,48.7587432861],"type":"Point"}
}