{
  "type": "Feature",
  "properties": {
    "addr:full":"Birkenweg 1 Seeboden K\u00e4rnten 9871",
    "addr:housenumber":"1",
    "addr:postcode":"9871",
    "addr:street":"Birkenweg;Kaernten",
    "iso:country":"AT",
    "sg:address":"Birkenweg 1",
    "sg:city":"Seeboden",
    "sg:orig_category":"Pensionen / Privatzimmer",
    "sg:phone":"+43 4762 81369",
    "sg:postcode":"9871",
    "sg:province":"K\u00e4rnten",
    "wof:name":"G\u00e4stehaus Rechner - Egarter",
    "wof:placetype":"venue"
},
  "geometry": {"coordinates":[13.5256271362,46.8203735352],"type":"Point"}
}