{
  "type": "Feature",
  "properties": {
    "addr:full":"Starhembergstr 33 Linz Ober\u00f6sterreich 4020",
    "addr:housenumber":"33",
    "addr:postcode":"4020",
    "addr:street":"Starhembergstr",
    "iso:country":"AT",
    "sg:address":"Starhembergstr 33",
    "sg:city":"Linz",
    "sg:orig_category":"Industrievertretungen",
    "sg:phone":"+43 732 774064",
    "sg:postcode":"4020",
    "sg:province":"Ober\u00f6sterreich",
    "wof:name":"Zastera Wilhelm",
    "wof:placetype":"venue"
},
  "geometry": {"coordinates":[14.298989296,48.3004760742],"type":"Point"}
}