{
  "type": "Feature",
  "properties": {
    "iso:country":"AT",
    "sg:address":"Unterer Pl 14",
    "sg:city":"St. Veit an der Glan",
    "sg:orig_category":"Textildruckereien",
    "sg:phone":"+43 4212 305130",
    "sg:postcode":"9300",
    "sg:province":"K\u00e4rnten",
    "wof:name":"Point Druckservice H Glock",
    "wof:placetype":"venue"
},
  "geometry": {"coordinates":[-90.4969863892,31.8169898987],"type":"Point"}
}