{
  "type": "Feature",
  "properties": {
    "addr:full":"Bodenst\u00e4tt 11 Mattsee Salzburg 5163",
    "addr:housenumber":"11",
    "addr:postcode":"5163",
    "addr:street":"Bodenstaett;Salzburg",
    "iso:country":"AT",
    "sg:address":"Bodenst\u00e4tt 11",
    "sg:city":"Mattsee",
    "sg:orig_category":"Feng-Shui, Wohnraumberatung",
    "sg:phone":"+43 6217 592070",
    "sg:postcode":"5163",
    "sg:province":"Salzburg",
    "sg:website":"sator.at",
    "wof:name":"Sator G\u00fcnther GmbH",
    "wof:placetype":"venue"
},
  "geometry": {"coordinates":[13.09907341,47.9456520081],"type":"Point"}
}