{
  "type": "Feature",
  "properties": {
    "addr:full":"Sch\u00e4rdinger Str. 38 Ried im Innkreis Ober\u00f6sterreich 4910",
    "addr:postcode":"4910",
    "addr:street":"Str. 38",
    "iso:country":"AT",
    "sg:address":"Sch\u00e4rdinger Str. 38",
    "sg:city":"Ried im Innkreis",
    "sg:classifiers":[
        {
            "category":"Food & Beverages",
            "subcategory":"Groceries & Convenience Stores",
            "type":"Retail Goods"
        }
    ],
    "sg:phone":"+43 4377 52844760",
    "sg:postcode":"4910",
    "sg:province":"Ober\u00f6sterreich",
    "sg:tags":[
        "product",
        "related"
    ],
    "wof:name":"MAXIMARKT HANDELSGES.MBH",
    "wof:placetype":"venue"
},
  "geometry": {"coordinates":[13.4900550842,48.2098655701],"type":"Point"}
}