{
  "type": "Feature",
  "properties": {
    "addr:full":"Lilienweg 28 Zell am See Salzburg 5700",
    "addr:housenumber":"28",
    "addr:postcode":"5700",
    "addr:street":"Lilienweg;Salzburg",
    "iso:country":"AT",
    "sg:address":"Lilienweg 28",
    "sg:city":"Zell am See",
    "sg:classifiers":[
        {
            "category":"Travel",
            "subcategory":"Hotels & Motels",
            "type":"Entertainment"
        }
    ],
    "sg:phone":"+43 6542 53690",
    "sg:postcode":"5700",
    "sg:province":"Salzburg",
    "wof:name":"Berghotel Schmittenh\u00f6he BetriebsgesmbH",
    "wof:placetype":"venue"
},
  "geometry": {"coordinates":[12.7813663483,47.294670105],"type":"Point"}
}