{
  "type": "Feature",
  "properties": {
    "addr:full":"Tannenbergg 2 Schwaz Tirol 6130",
    "addr:housenumber":"2",
    "addr:postcode":"6130",
    "addr:street":"Tannenbergg;Tirol",
    "iso:country":"AT",
    "sg:address":"Tannenbergg 2",
    "sg:city":"Schwaz",
    "sg:orig_category":"Fernseh- U Radiogesellschaften",
    "sg:phone":"+43 5242 61030",
    "sg:postcode":"6130",
    "sg:province":"Tirol",
    "wof:name":"Radio Unterland U1",
    "wof:placetype":"venue"
},
  "geometry": {"coordinates":[11.7081594467,47.347442627],"type":"Point"}
}