{
  "type": "Feature",
  "properties": {
    "addr:full":"Bundesstr 4 Wals Salzburg 5071",
    "addr:housenumber":"4",
    "addr:postcode":"5071",
    "addr:street":"Bundesstr;Salzburg",
    "iso:country":"AT",
    "sg:address":"Bundesstr 4",
    "sg:city":"Wals",
    "sg:classifiers":[
        {
            "category":"Restaurant",
            "type":"Food & Drink"
        }
    ],
    "sg:phone":"+43 662 85814160",
    "sg:postcode":"5071",
    "sg:province":"Salzburg",
    "wof:name":"Globetrotter Restaurant & Bar & Catering",
    "wof:placetype":"venue"
},
  "geometry": {"coordinates":[12.9903039932,47.7917289734],"type":"Point"}
}