{
  "type": "Feature",
  "properties": {
    "iso:country":"AT",
    "sg:address":"Hauptpl 300",
    "sg:city":"St. Michael im Burgenland",
    "sg:orig_category":"Banken U Sparkassen",
    "sg:phone":"+43 4350 10020262",
    "sg:postcode":"7535",
    "sg:province":"Burgenland",
    "wof:name":"Erste Bank d oesterreichischen Sparkassen AG",
    "wof:placetype":"venue"
},
  "geometry": {"coordinates":[16.2694511414,47.127117157],"type":"Point"}
}