{
  "type": "Feature",
  "properties": {
    "addr:full":"Reither Anger 28 Reith im Alpbachtal Tirol 6235",
    "addr:housenumber":"28",
    "addr:postcode":"6235",
    "addr:street":"Reither Anger;Alpbachtal Tirol",
    "iso:country":"AT",
    "sg:address":"Reither Anger 28",
    "sg:city":"Reith im Alpbachtal",
    "sg:orig_category":"Baumeister",
    "sg:phone":"+43 5337 623630",
    "sg:postcode":"6235",
    "sg:province":"Tirol",
    "wof:name":"Vorhofer & Lintner KG",
    "wof:placetype":"venue"
},
  "geometry": {"coordinates":[11.8783016205,47.4169235229],"type":"Point"}
}