{
  "type": "Feature",
  "properties": {
    "addr:full":"Herreng 10 Klagenfurt K\u00e4rnten 9020",
    "addr:housenumber":"10",
    "addr:postcode":"9020",
    "addr:street":"Herreng;Kaernten",
    "iso:country":"AT",
    "sg:address":"Herreng 10",
    "sg:city":"Klagenfurt",
    "sg:orig_category":"Beratungsstellen",
    "sg:phone":"+43 4366 41838868",
    "sg:postcode":"9020",
    "sg:province":"K\u00e4rnten",
    "wof:name":"The Mental Meeting Place",
    "wof:placetype":"venue"
},
  "geometry": {"coordinates":[14.306063652,46.625667572],"type":"Point"}
}