{
  "type": "Feature",
  "properties": {
    "addr:full":"Ruthnerg 18 Wien Wien 1210",
    "addr:housenumber":"18",
    "addr:postcode":"1210",
    "addr:street":"Ruthnerg",
    "iso:country":"AT",
    "sg:address":"Ruthnerg 18",
    "sg:city":"Wien",
    "sg:orig_category":"Bauunternehmen",
    "sg:phone":"+43 1 2922450",
    "sg:postcode":"1210",
    "sg:province":"Wien",
    "wof:name":"Sanierprofi BaugesmbH",
    "wof:placetype":"venue"
},
  "geometry": {"coordinates":[16.4160022736,48.2697105408],"type":"Point"}
}