{
  "type": "Feature",
  "properties": {
    "addr:full":"Pfeiferg 3 Salzburg Salzburg 5020",
    "addr:housenumber":"3",
    "addr:postcode":"5020",
    "addr:street":"Pfeiferg;Salzburg",
    "iso:country":"AT",
    "sg:address":"Pfeiferg 3",
    "sg:city":"Salzburg",
    "sg:orig_category":"Partyservice",
    "sg:phone":"+43 662 844774",
    "sg:postcode":"5020",
    "sg:province":"Salzburg",
    "wof:name":"Fasties finest catering Gerhard Starzer",
    "wof:placetype":"venue"
},
  "geometry": {"coordinates":[13.0489416122,47.7986221313],"type":"Point"}
}