{
  "type": "Feature",
  "properties": {
    "addr:full":"Brenner Str 43 Steinach am Brenner Tirol 6150",
    "addr:postcode":"6150",
    "addr:street":"Str 43;Tirol",
    "iso:country":"AT",
    "sg:address":"Brenner Str 43",
    "sg:city":"Steinach am Brenner",
    "sg:orig_category":"Fotografen",
    "sg:phone":"+43 5272 20150",
    "sg:postcode":"6150",
    "sg:province":"Tirol",
    "wof:name":"das fotoatelier Barbara Gschliesser & Carmen Leitner OEG",
    "wof:placetype":"venue"
},
  "geometry": {"coordinates":[11.4669160843,47.0920257568],"type":"Point"}
}