{
  "type": "Feature",
  "properties": {
    "addr:full":"Nr 32 Mathon Tirol 6562",
    "addr:postcode":"6562",
    "addr:street":"Nr;Mathon Tirol",
    "iso:country":"AT",
    "sg:address":"Nr 32",
    "sg:city":"Mathon",
    "sg:orig_category":"Volksschulen",
    "sg:phone":"+43 4354 445540",
    "sg:postcode":"6562",
    "sg:province":"Tirol",
    "wof:name":"Volksschule",
    "wof:placetype":"venue"
},
  "geometry": {"coordinates":[10.2449302673,46.9883995056],"type":"Point"}
}