{
  "type": "Feature",
  "properties": {
    "addr:full":"Nr 61 Ernstbrunn Nieder\u00f6sterreich 2115",
    "addr:postcode":"2115",
    "addr:street":"Nr;Niederoesterreich",
    "iso:country":"AT",
    "sg:address":"Nr 61",
    "sg:city":"Ernstbrunn",
    "sg:orig_category":"Fleischhauereien",
    "sg:phone":"+43 2576 29030",
    "sg:postcode":"2115",
    "sg:province":"Nieder\u00f6sterreich",
    "wof:name":"Steininger Franz",
    "wof:placetype":"venue"
},
  "geometry": {"coordinates":[16.361114502,48.5277061462],"type":"Point"}
}