{
  "type": "Feature",
  "properties": {
    "addr:full":"K\u00fcnstlerg 11/3 Wien Wien 1150",
    "addr:housenumber":"11 / 3",
    "addr:postcode":"1150",
    "addr:street":"Kuenstlerg",
    "iso:country":"AT",
    "sg:address":"K\u00fcnstlerg 11/3",
    "sg:city":"Wien",
    "sg:orig_category":"Drucker, Computersysteme",
    "sg:phone":"+43 1 891540",
    "sg:postcode":"1150",
    "sg:province":"Wien",
    "sg:website":"edvw.com",
    "wof:name":"EDV-Werkstatt GesmbH",
    "wof:placetype":"venue"
},
  "geometry": {"coordinates":[16.3320903778,48.2006416321],"type":"Point"}
}