{
  "type": "Feature",
  "properties": {
    "addr:full":"Brauhausstr 27-29 Schwechat Nieder\u00f6sterreich 2320",
    "addr:postcode":"27-29;2320",
    "addr:street":"Niederoesterreich",
    "iso:country":"AT",
    "sg:address":"Brauhausstr 27-29",
    "sg:city":"Schwechat",
    "sg:orig_category":"Transportunternehmen",
    "sg:phone":"+43 1 7077837",
    "sg:postcode":"2320",
    "sg:province":"Nieder\u00f6sterreich",
    "wof:name":"Cadilek W KEG",
    "wof:placetype":"venue"
},
  "geometry": {"coordinates":[16.4673652649,48.1319198608],"type":"Point"}
}