{
  "type": "Feature",
  "properties": {
    "iso:country":"AT",
    "sg:address":"Klosterpl 7",
    "sg:city":"Traunkirchen",
    "sg:orig_category":"Friseure U Frisiersalons",
    "sg:phone":"+43 76172268",
    "sg:postcode":"4801",
    "sg:province":"Ober\u00f6sterreich",
    "wof:name":"Friseur Putz",
    "wof:placetype":"venue"
},
  "geometry": {"coordinates":[13.7908592224,47.8452377319],"type":"Point"}
}