{
  "type": "Feature",
  "properties": {
    "iso:country":"AT",
    "sg:address":"Uhlpl 5",
    "sg:city":"Wien",
    "sg:orig_category":"Waren Aller Art",
    "sg:phone":"+43 1 4054968",
    "sg:postcode":"1080",
    "sg:province":"Wien",
    "wof:name":"Ponom Handelsgewerbe",
    "wof:placetype":"venue"
},
  "geometry": {"coordinates":[16.3406429291,48.2125701904],"type":"Point"}
}