{
  "type": "Feature",
  "properties": {
    "addr:full":"Hornweg 15 St. Johann in Tirol Tirol 6380",
    "addr:housenumber":"15",
    "addr:postcode":"6380",
    "addr:street":"Hornweg;Tirol",
    "iso:country":"AT",
    "sg:address":"Hornweg 15",
    "sg:city":"St. Johann in Tirol",
    "sg:classifiers":[
        {
            "category":"Park",
            "subcategory":"Provincial",
            "type":"Public Place"
        }
    ],
    "sg:phone":"+43 4353 5264777",
    "sg:postcode":"6380",
    "sg:province":"Tirol",
    "sg:tags":[
        "u",
        "ski-",
        "snowboardschulen"
    ],
    "wof:name":"Skischule St Johann i Tirol - Inh Ballweber Ulrich",
    "wof:placetype":"venue"
},
  "geometry": {"coordinates":[12.4262933731,47.5172309875],"type":"Point"}
}