{
  "type": "Feature",
  "properties": {
    "iso:country":"AT",
    "sg:address":"Austr 33",
    "sg:city":"Krems an der Donau",
    "sg:orig_category":"Feuerwehren",
    "sg:phone":"+43 2732 855220",
    "sg:postcode":"3500",
    "sg:province":"Nieder\u00f6sterreich",
    "wof:name":"Freiwillige Feuerwehr Krems",
    "wof:placetype":"venue"
},
  "geometry": {"coordinates":[15.6095781326,48.4056358337],"type":"Point"}
}