{
  "type": "Feature",
  "properties": {
    "addr:full":"L v Keutschach-Str 6 Salzburg Salzburg 5020",
    "addr:housenumber":"6",
    "addr:postcode":"5020",
    "addr:street":"L;Keutschach-Str;Salzburg",
    "iso:country":"AT",
    "sg:address":"L v Keutschach-Str 6",
    "sg:city":"Salzburg",
    "sg:orig_category":"Notare",
    "sg:phone":"+43 662 4375480",
    "sg:postcode":"5020",
    "sg:province":"Salzburg",
    "wof:name":"Sonnleitner Ernst Dr",
    "wof:placetype":"venue"
},
  "geometry": {"coordinates":[13.0433769226,47.8006744385],"type":"Point"}
}