{
  "type": "Feature",
  "properties": {
    "addr:full":"Mariahilfer Str 54 Wien Wien 1070",
    "addr:postcode":"1070",
    "addr:street":"Str 54",
    "iso:country":"AT",
    "sg:address":"Mariahilfer Str 54",
    "sg:city":"Wien",
    "sg:orig_category":"Waren Aller Art",
    "sg:phone":"+43 4315 265962",
    "sg:postcode":"1070",
    "sg:province":"Wien",
    "wof:name":"Allerlei - D\u00f6rrbecker Wien HandelsgmbH",
    "wof:placetype":"venue"
},
  "geometry": {"coordinates":[16.3520927429,48.1992874146],"type":"Point"}
}