{
  "type": "Feature",
  "properties": {
    "addr:full":"St. P\u00f6ltner Str 22 Herzogenburg Nieder\u00f6sterreich 3130",
    "addr:postcode":"3130",
    "addr:street":"Str 22",
    "iso:country":"AT",
    "sg:address":"St. P\u00f6ltner Str 22",
    "sg:city":"Herzogenburg",
    "sg:orig_category":"Juweliere, Gold- U Silberschmiede",
    "sg:phone":"+43 4327 8283190",
    "sg:postcode":"3130",
    "sg:province":"Nieder\u00f6sterreich",
    "wof:name":"Hasenzagl OEG",
    "wof:placetype":"venue"
},
  "geometry": {"coordinates":[15.6953983307,48.2832336426],"type":"Point"}
}