{
  "type": "Feature",
  "properties": {
    "iso:country":"AT",
    "sg:address":"Kolschitzkyg 6",
    "sg:city":"Wien",
    "sg:orig_category":"Fleischhauereien",
    "sg:phone":"+43 1 5040143",
    "sg:postcode":"1040",
    "sg:province":"Wien",
    "wof:name":"Klausberger GesmbH",
    "wof:placetype":"venue"
},
  "geometry": {"coordinates":[16.3722724915,48.188079834],"type":"Point"}
}