{
  "type": "Feature",
  "properties": {
    "addr:full":"Wiener Str 28-30 Lockenhaus Burgenland 7442",
    "addr:postcode":"7442",
    "iso:country":"AT",
    "sg:address":"Wiener Str 28-30",
    "sg:city":"Lockenhaus",
    "sg:orig_category":"Tankstellen",
    "sg:phone":"+43 2616 2253",
    "sg:postcode":"7442",
    "sg:province":"Burgenland",
    "wof:name":"Schmall Josef - ESSO Station",
    "wof:placetype":"venue"
},
  "geometry": {"coordinates":[16.4153556824,47.4104309082],"type":"Point"}
}