{
  "type": "Feature",
  "properties": {
    "iso:country":"AT",
    "sg:address":"Michael Ruppe-Str 4",
    "sg:city":"Elsbethen-Glasenbach",
    "sg:orig_category":"Tapezierer U Dekorateure",
    "sg:phone":"+43 662 633941",
    "sg:postcode":"5061",
    "sg:province":"Salzburg",
    "wof:name":"Demelbauer Friedrich",
    "wof:placetype":"venue"
},
  "geometry": {"coordinates":[13.0884561539,47.7744903564],"type":"Point"}
}