{
  "type": "Feature",
  "properties": {
    "addr:full":"Neubauerstr 58 Traun Ober\u00f6sterreich 4050",
    "addr:housenumber":"58",
    "addr:postcode":"4050",
    "addr:street":"Neubauerstr",
    "iso:country":"AT",
    "sg:address":"Neubauerstr 58",
    "sg:city":"Traun",
    "sg:orig_category":"Farben U Lacke / Einzelhandel",
    "sg:phone":"+43 699 12695900",
    "sg:postcode":"4050",
    "sg:province":"Ober\u00f6sterreich",
    "wof:name":"Reixenartner Werner - Farbenzentrum",
    "wof:placetype":"venue"
},
  "geometry": {"coordinates":[14.2292976379,48.219291687],"type":"Point"}
}