{
  "type": "Feature",
  "properties": {
    "iso:country":"AT",
    "sg:address":"Prandtauerring 1",
    "sg:city":"Herzogenburg",
    "sg:classifiers":[
        {
            "category":"Home & Garden",
            "subcategory":"Building Materials",
            "type":"Retail Goods"
        }
    ],
    "sg:phone":"+43 2782 85952",
    "sg:postcode":"3130",
    "sg:province":"Nieder\u00f6sterreich",
    "sg:tags":[
        "steel",
        "metal",
        "made",
        "door",
        "gate"
    ],
    "wof:name":"Metallbau Herzogenburg Pehofer",
    "wof:placetype":"venue"
},
  "geometry": {"coordinates":[15.6982030869,48.288772583],"type":"Point"}
}