{
  "type": "Feature",
  "properties": {
    "addr:full":"Kaiser-Ebersdorfer Strasse 78 Wien Wien 1110",
    "addr:housenumber":"78",
    "addr:postcode":"1110",
    "addr:street":"Kaiser-Ebersdorfer Strasse",
    "iso:country":"AT",
    "sg:address":"Kaiser-Ebersdorfer Strasse 78",
    "sg:city":"Wien",
    "sg:classifiers":[
        {
            "category":"Manufacturing",
            "subcategory":"Motor Vehicles & Parts",
            "type":"Manufacturing & Wholesale Goods"
        }
    ],
    "sg:phone":"+43 1 7676518",
    "sg:postcode":"1110",
    "sg:province":"Wien",
    "sg:tags":[
        "body",
        "car"
    ],
    "wof:name":"Adolf Kail Ges.m.b.H.",
    "wof:placetype":"venue"
},
  "geometry": {"coordinates":[16.4299087524,48.1658248901],"type":"Point"}
}