{
  "type": "Feature",
  "properties": {
    "iso:country":"AT",
    "sg:address":"Hauptstrasse 75",
    "sg:city":"Pernitz",
    "sg:classifiers":[
        {
            "category":"Banks & Credit Unions",
            "subcategory":"Investment Brokerage",
            "type":"Services"
        }
    ],
    "sg:phone":"+43 2632 74080",
    "sg:postcode":"2763",
    "sg:province":"Nieder\u00f6sterreich",
    "sg:tags":[
        "audio",
        "accessory"
    ],
    "sg:website":"hms.co.at",
    "wof:name":"HMS - Elektroinstallations GmbH",
    "wof:placetype":"venue"
},
  "geometry": {"coordinates":[15.9622535706,47.8977775574],"type":"Point"}
}