{
  "type": "Feature",
  "properties": {
    "addr:full":"Roseggerstr 10 Wels Ober\u00f6sterreich 4600",
    "addr:housenumber":"10",
    "addr:postcode":"4600",
    "addr:street":"Roseggerstr;Oberoesterreich",
    "iso:country":"AT",
    "sg:address":"Roseggerstr 10",
    "sg:city":"Wels",
    "sg:orig_category":"Gewerkschaften",
    "sg:phone":"+43 7242 47109",
    "sg:postcode":"4600",
    "sg:province":"Ober\u00f6sterreich",
    "wof:name":"\u00f6sterreichischer Gewerkschaftsbund-Bezirkssekretariat Wels",
    "wof:placetype":"venue"
},
  "geometry": {"coordinates":[14.0274152756,48.1603469849],"type":"Point"}
}