{
  "type": "Feature",
  "properties": {
    "iso:country":"AT",
    "sg:address":"Kreuzpl 16",
    "sg:city":"Bad Ischl",
    "sg:classifiers":[
        {
            "category":"Arts & Performance",
            "subcategory":"Theater",
            "type":"Entertainment"
        }
    ],
    "sg:phone":"+43 664 2415655",
    "sg:postcode":"4820",
    "sg:province":"Ober\u00f6sterreich",
    "wof:name":"Lehartheater",
    "wof:placetype":"venue"
},
  "geometry": {"coordinates":[13.6225070953,47.7130050659],"type":"Point"}
}