{
  "type": "Feature",
  "properties": {
    "addr:full":"Stabauerg 5 Salzburg Salzburg 5020",
    "addr:housenumber":"5",
    "addr:postcode":"5020",
    "addr:street":"Stabauerg;Salzburg",
    "iso:country":"AT",
    "sg:address":"Stabauerg 5",
    "sg:city":"Salzburg",
    "sg:orig_category":"Satzherstellung",
    "sg:phone":"+43 662 8746740",
    "sg:postcode":"5020",
    "sg:province":"Salzburg",
    "wof:name":"MEDIA DESIGN: RIZNER.AT GesmbH",
    "wof:placetype":"venue"
},
  "geometry": {"coordinates":[13.0496416092,47.8148536682],"type":"Point"}
}