{
  "type": "Feature",
  "properties": {
    "addr:full":"Lindenstr 31 Reutte Tirol 6600",
    "addr:housenumber":"31",
    "addr:postcode":"6600",
    "addr:street":"Lindenstr;Tirol",
    "iso:country":"AT",
    "sg:address":"Lindenstr 31",
    "sg:city":"Reutte",
    "sg:orig_category":"Installationsunternehmen",
    "sg:phone":"+43 5672 64090",
    "sg:postcode":"6600",
    "sg:province":"Tirol",
    "wof:name":"Scheucher Raimund",
    "wof:placetype":"venue"
},
  "geometry": {"coordinates":[10.7125492096,47.4879608154],"type":"Point"}
}