{
  "type": "Feature",
  "properties": {
    "addr:full":"Nonntaler Hauptstr 59 Salzburg Salzburg 5020",
    "addr:housenumber":"59",
    "addr:postcode":"5020",
    "addr:street":"Nonntaler Hauptstr;Salzburg",
    "iso:country":"AT",
    "sg:address":"Nonntaler Hauptstr 59",
    "sg:city":"Salzburg",
    "sg:orig_category":"Fotoapparate U -Artikel / Einzelhandel",
    "sg:phone":"+43 662 825875",
    "sg:postcode":"5020",
    "sg:province":"Salzburg",
    "wof:name":"Foto Veigl FotografengesmbH",
    "wof:placetype":"venue"
},
  "geometry": {"coordinates":[13.0524082184,47.7855873108],"type":"Point"}
}