{
  "type": "Feature",
  "properties": {
    "addr:full":"H\u00f6henstr 6 Innsbruck Tirol 6020",
    "addr:housenumber":"6",
    "addr:postcode":"6020",
    "addr:street":"Hoehenstr;Tirol",
    "iso:country":"AT",
    "sg:address":"H\u00f6henstr 6",
    "sg:city":"Innsbruck",
    "sg:orig_category":"Fliesen- U Plattenverlegungen",
    "sg:phone":"+43 512 273882",
    "sg:postcode":"6020",
    "sg:province":"Tirol",
    "wof:name":"Berchtold Hansj\u00f6rg",
    "wof:placetype":"venue"
},
  "geometry": {"coordinates":[11.364616394,47.2611160278],"type":"Point"}
}