{
  "type": "Feature",
  "properties": {
    "addr:full":"Holzmanng 5 Wien Wien 1210",
    "addr:housenumber":"5",
    "addr:postcode":"1210",
    "addr:street":"Holzmanng",
    "iso:country":"AT",
    "sg:address":"Holzmanng 5",
    "sg:city":"Wien",
    "sg:orig_category":"Gastronomie- U Hotelbedarf",
    "sg:phone":"+43 1 250480",
    "sg:postcode":"1210",
    "sg:province":"Wien",
    "sg:website":"www.holzmann.at",
    "wof:name":"Holzmann Rudolf OHG - Gastro",
    "wof:placetype":"venue"
},
  "geometry": {"coordinates":[16.4511241913,48.2639427185],"type":"Point"}
}