{
  "type": "Feature",
  "properties": {
    "iso:country":"AT",
    "sg:address":"Walser Str 60",
    "sg:city":"Mittelberg",
    "sg:orig_category":"Bars-Cafes",
    "sg:phone":"+43 5517 6803",
    "sg:postcode":"6993",
    "sg:province":"Vorarlberg",
    "wof:name":"Pils und Weinstube s'\u00c4lpele",
    "wof:placetype":"venue"
},
  "geometry": {"coordinates":[10.1576881409,47.3269004822],"type":"Point"}
}