{
  "type": "Feature",
  "properties": {
    "addr:full":"Malser Strasse 14 Landeck Tirol 6500",
    "addr:housenumber":"14",
    "addr:postcode":"6500",
    "addr:street":"Malser Strasse;Tirol",
    "iso:country":"AT",
    "sg:address":"Malser Strasse 14",
    "sg:city":"Landeck",
    "sg:classifiers":[
        {
            "category":"Shopping",
            "subcategory":"Computers & Home Electronics",
            "type":"Retail Goods"
        }
    ],
    "sg:phone":"+43 5442 633110",
    "sg:postcode":"6500",
    "sg:province":"Tirol",
    "sg:tags":[
        "binoculars",
        "prism"
    ],
    "wof:name":"Simperl-Pellosch GmbH",
    "wof:placetype":"venue"
},
  "geometry": {"coordinates":[10.5672206879,47.1369667053],"type":"Point"}
}