{
  "type": "Feature",
  "properties": {
    "addr:full":"Maistatt 724 Schladming Steiermark 8970",
    "addr:housenumber":"724",
    "addr:postcode":"8970",
    "addr:street":"Maistatt",
    "iso:country":"AT",
    "sg:address":"Maistatt 724",
    "sg:city":"Schladming",
    "sg:classifiers":[
        {
            "category":"Park",
            "subcategory":"Provincial",
            "type":"Public Place"
        }
    ],
    "sg:phone":"+43 3687 23444",
    "sg:postcode":"8970",
    "sg:province":"Steiermark",
    "sg:tags":[
        "u",
        "ski-",
        "snowboardschulen"
    ],
    "wof:name":"Tritscher Franz GesmbH",
    "wof:placetype":"venue"
},
  "geometry": {"coordinates":[13.6925163269,47.3930587769],"type":"Point"}
}