{
  "type": "Feature",
  "properties": {
    "iso:country":"AT",
    "sg:address":"Hauptstr 333",
    "sg:city":"Eben im Pongau",
    "sg:orig_category":"Appartements / Ferienwohnungen",
    "sg:phone":"+43 4364 588412",
    "sg:postcode":"5531",
    "sg:province":"Salzburg",
    "wof:name":"Appartements Passrugger",
    "wof:placetype":"venue"
},
  "geometry": {"coordinates":[13.3952989578,47.4079742432],"type":"Point"}
}