{
  "type": "Feature",
  "properties": {
    "addr:full":"Austinstr 7 St. P\u00f6lten-Traisenpark Nieder\u00f6sterreich 3107",
    "addr:housenumber":"7",
    "addr:postcode":"3107",
    "addr:street":"Austinstr",
    "iso:country":"AT",
    "sg:address":"Austinstr 7",
    "sg:city":"St. P\u00f6lten-Traisenpark",
    "sg:orig_category":"Architekten",
    "sg:phone":"+43 2742 3619530",
    "sg:postcode":"3107",
    "sg:province":"Nieder\u00f6sterreich",
    "wof:name":"Pfaffenbichler Paul Dipl-Ing",
    "wof:placetype":"venue"
},
  "geometry": {"coordinates":[15.6369466782,48.2259407043],"type":"Point"}
}