{
  "type": "Feature",
  "properties": {
    "addr:full":"Reumannpl 17 Wien Wien 1100",
    "addr:housenumber":"17",
    "addr:postcode":"1100",
    "addr:street":"Reumannpl",
    "iso:country":"AT",
    "sg:address":"Reumannpl 17",
    "sg:city":"Wien",
    "sg:orig_category":"Ambulatorien",
    "sg:phone":"+43 1 6042470",
    "sg:postcode":"1100",
    "sg:province":"Wien",
    "sg:website":"www.allamb.at",
    "wof:name":"Ambulatorium f Allergie klin Immunologie und Histopathologie d Haut",
    "wof:placetype":"venue"
},
  "geometry": {"coordinates":[16.3782196045,48.1747932434],"type":"Point"}
}