{
  "type": "Feature",
  "properties": {
    "iso:country":"AT",
    "sg:address":"Franz-Fischer-Str 51",
    "sg:city":"Innsbruck",
    "sg:orig_category":"Datenverarbeitung",
    "sg:phone":"+43 664 3940707",
    "sg:postcode":"6020",
    "sg:province":"Tirol",
    "wof:name":"Lackner Wolfgang",
    "wof:placetype":"venue"
},
  "geometry": {"coordinates":[11.3880748749,47.2580604553],"type":"Point"}
}