{
  "type": "Feature",
  "properties": {
    "iso:country":"AT",
    "sg:address":"Radlpa\u00dfstr 15",
    "sg:city":"Deutschlandsberg",
    "sg:orig_category":"Lebensmittel / Einzelhandel",
    "sg:phone":"+43 3462 30937",
    "sg:postcode":"8530",
    "sg:province":"Steiermark",
    "wof:name":"Billa AG",
    "wof:placetype":"venue"
},
  "geometry": {"coordinates":[15.2354717255,46.8159065247],"type":"Point"}
}