{
  "type": "Feature",
  "properties": {
    "addr:full":"Werkstr 274 Deutschfeistritz Steiermark 8121",
    "addr:housenumber":"274",
    "addr:postcode":"8121",
    "iso:country":"AT",
    "sg:address":"Werkstr 274",
    "sg:city":"Deutschfeistritz",
    "sg:orig_category":"Lastkraftwagen",
    "sg:phone":"+43 3127 28609",
    "sg:postcode":"8121",
    "sg:province":"Steiermark",
    "wof:name":"Schaffer Muhammed Naim",
    "wof:placetype":"venue"
},
  "geometry": {"coordinates":[15.3360729218,47.2085838318],"type":"Point"}
}