{
  "type": "Feature",
  "properties": {
    "iso:country":"AT",
    "sg:address":"Promenade 2",
    "sg:city":"Steyr",
    "sg:orig_category":"Musikgruppen",
    "sg:phone":"+43 7252 48205",
    "sg:postcode":"4400",
    "sg:province":"Ober\u00f6sterreich",
    "wof:name":"Bruckner S\u00e4ngerknaben",
    "wof:placetype":"venue"
},
  "geometry": {"coordinates":[14.4176874161,48.04063797],"type":"Point"}
}