{
  "type": "Feature",
  "properties": {
    "addr:full":"Landstra\u00dfer Hauptstr 1/U4/Bahnsteig Wien Wien 1030",
    "addr:housenumber":"1 / u4",
    "addr:postcode":"1030",
    "addr:street":"Landstrasser Hauptstr;/ Bahnsteig",
    "iso:country":"AT",
    "sg:address":"Landstra\u00dfer Hauptstr 1/U4/Bahnsteig",
    "sg:city":"Wien",
    "sg:orig_category":"Tabaktrafiken",
    "sg:phone":"+43 1 7123302",
    "sg:postcode":"1030",
    "sg:province":"Wien",
    "wof:name":"Lesjak Josef",
    "wof:placetype":"venue"
},
  "geometry": {"coordinates":[16.4025096893,48.1936683655],"type":"Point"}
}