{
  "type": "Feature",
  "properties": {
    "iso:country":"AT",
    "sg:address":"Eisenstr 52",
    "sg:city":"Losenstein",
    "sg:orig_category":"Non-Classified Establishments",
    "sg:phone":"+43 7255 62270",
    "sg:postcode":"4460",
    "sg:province":"Ober\u00f6sterreich",
    "wof:name":"Pfarramt",
    "wof:placetype":"venue"
},
  "geometry": {"coordinates":[14.4324502945,47.9255828857],"type":"Point"}
}