{
  "type": "Feature",
  "properties": {
    "addr:full":"Weitra Nieder\u00f6sterreich 3970",
    "addr:postcode":"3970",
    "addr:street":"Niederoesterreich",
    "iso:country":"AT",
    "sg:city":"Weitra",
    "sg:orig_category":"Non-Classified Establishments",
    "sg:phone":"+43 2856 24110",
    "sg:postcode":"3970",
    "sg:province":"Nieder\u00f6sterreich",
    "wof:name":"Kuenringer Kaserne",
    "wof:placetype":"venue"
},
  "geometry": {"coordinates":[14.905380249,48.7212104797],"type":"Point"}
}