{
  "type": "Feature",
  "properties": {
    "addr:full":"Alte Reichsstr 6 Wildon Steiermark 8410",
    "addr:housenumber":"6",
    "addr:postcode":"8410",
    "addr:street":"Steiermark",
    "iso:country":"AT",
    "sg:address":"Alte Reichsstr 6",
    "sg:city":"Wildon",
    "sg:orig_category":"Hauptschulen",
    "sg:phone":"+43 3182 3274",
    "sg:postcode":"8410",
    "sg:province":"Steiermark",
    "wof:name":"Hauptschule",
    "wof:placetype":"venue"
},
  "geometry": {"coordinates":[15.5174160004,46.8815879822],"type":"Point"}
}