{
  "type": "Feature",
  "properties": {
    "addr:full":"J\u00f6rgmayrstr 6 Walding Ober\u00f6sterreich 4111",
    "addr:housenumber":"6",
    "addr:postcode":"4111",
    "addr:street":"Joergmayrstr",
    "iso:country":"AT",
    "sg:address":"J\u00f6rgmayrstr 6",
    "sg:city":"Walding",
    "sg:orig_category":"Transportunternehmen",
    "sg:phone":"+43 7234 82562",
    "sg:postcode":"4111",
    "sg:province":"Ober\u00f6sterreich",
    "wof:name":"Kaiser Erich",
    "wof:placetype":"venue"
},
  "geometry": {"coordinates":[14.1564540863,48.3510055542],"type":"Point"}
}