{
  "type": "Feature",
  "properties": {
    "iso:country":"AT",
    "sg:address":"Klagenfurter Str 32",
    "sg:city":"St. Veit an der Glan",
    "sg:orig_category":"Wasseraufbereitung U -Reinigung",
    "sg:phone":"+43 4342 1271220",
    "sg:postcode":"9300",
    "sg:province":"K\u00e4rnten",
    "wof:name":"AQUAMAG-Umwelttechnik GesmbH",
    "wof:placetype":"venue"
},
  "geometry": {"coordinates":[-90.4969863892,31.8169898987],"type":"Point"}
}