{
  "type": "Feature",
  "properties": {
    "addr:full":"Lindhofstr 13 Wolfsberg K\u00e4rnten 9400",
    "addr:housenumber":"13;kaernten",
    "addr:postcode":"9400",
    "addr:street":"Lindhofstr",
    "iso:country":"AT",
    "sg:address":"Lindhofstr 13",
    "sg:city":"Wolfsberg",
    "sg:orig_category":"Fahrschulen",
    "sg:phone":"+43 4352 3148",
    "sg:postcode":"9400",
    "sg:province":"K\u00e4rnten",
    "wof:name":"Haider Peter Ing",
    "wof:placetype":"venue"
},
  "geometry": {"coordinates":[14.8447561264,46.8332328796],"type":"Point"}
}