{
  "type": "Feature",
  "properties": {
    "iso:country":"AT",
    "sg:address":"Angerg 43",
    "sg:city":"Rotenturm an der Pinka",
    "sg:orig_category":"Markisen",
    "sg:phone":"+43 4333 52313300",
    "sg:postcode":"7501",
    "sg:province":"Burgenland",
    "wof:name":"Halvax GesmbH",
    "wof:placetype":"venue"
},
  "geometry": {"coordinates":[16.2457733154,47.2590179443],"type":"Point"}
}