{
  "type": "Feature",
  "properties": {
    "addr:full":"Jara-Benes-G 16 Wien Wien 1210",
    "addr:housenumber":"16",
    "addr:postcode":"1210",
    "addr:street":"Jara-Benes-G",
    "iso:country":"AT",
    "sg:address":"Jara-Benes-G 16",
    "sg:city":"Wien",
    "sg:orig_category":"Ambulatorien",
    "sg:phone":"+43 4312 9214770",
    "sg:postcode":"1210",
    "sg:province":"Wien",
    "wof:name":"Ambulatorium f Entwicklungsdiagnostik f k\u00f6rper- u mehrfachbehinderte Kinder u Jugendliche",
    "wof:placetype":"venue"
},
  "geometry": {"coordinates":[16.3874454498,48.2905693054],"type":"Point"}
}