{
  "type": "Feature",
  "properties": {
    "addr:full":"Hauptstr 24 Wolkersdorf im Weinviertel Nieder\u00f6sterreich 2120",
    "addr:housenumber":"24",
    "addr:postcode":"2120",
    "addr:street":"Hauptstr",
    "iso:country":"AT",
    "sg:address":"Hauptstr 24",
    "sg:city":"Wolkersdorf im Weinviertel",
    "sg:orig_category":"Apotheken",
    "sg:phone":"+43 2245 2354",
    "sg:postcode":"2120",
    "sg:province":"Nieder\u00f6sterreich",
    "wof:name":"Apotheke Zur heiligen Dreifaltigkeit Mag Eberhard Lux KG",
    "wof:placetype":"venue"
},
  "geometry": {"coordinates":[16.5253124237,48.3683013916],"type":"Point"}
}