{
  "type": "Feature",
  "properties": {
    "addr:full":"Weissenbachweg 3 Absam Tirol 6067",
    "addr:housenumber":"3",
    "addr:postcode":"6067",
    "addr:street":"Weissenbachweg;Tirol",
    "iso:country":"AT",
    "sg:address":"Weissenbachweg 3",
    "sg:city":"Absam",
    "sg:orig_category":"Freizeit, Sport",
    "sg:phone":"+43 4305 22353653",
    "sg:postcode":"6067",
    "sg:province":"Tirol",
    "sg:website":"http://www.tirol.com/divers-paradise/Shop.htm",
    "wof:name":"Tauchschule - Tauchshop Diver\u00b4s Paradise",
    "wof:placetype":"venue"
},
  "geometry": {"coordinates":[11.5155000687,47.2947425842],"type":"Point"}
}