{
  "type": "Feature",
  "properties": {
    "addr:full":"Attergaustr 99 St. Georgen im Attergau Ober\u00f6sterreich 4880",
    "addr:housenumber":"99",
    "addr:postcode":"4880",
    "addr:street":"Attergaustr",
    "iso:country":"AT",
    "sg:address":"Attergaustr 99",
    "sg:city":"St. Georgen im Attergau",
    "sg:orig_category":"Autoreparatur",
    "sg:phone":"+43 4376 676216",
    "sg:postcode":"4880",
    "sg:province":"Ober\u00f6sterreich",
    "wof:name":"Baumann Auto KG",
    "wof:placetype":"venue"
},
  "geometry": {"coordinates":[13.4807357788,47.93516922],"type":"Point"}
}