{
  "type": "Feature",
  "properties": {
    "iso:country":"AT",
    "sg:address":"Leopold-Figl-Str 4",
    "sg:city":"Markt Piesting",
    "sg:orig_category":"Fenster",
    "sg:phone":"+43 4366 48223314",
    "sg:postcode":"2753",
    "sg:province":"Nieder\u00f6sterreich",
    "wof:name":"Scheibenreif Roman KEG",
    "wof:placetype":"venue"
},
  "geometry": {"coordinates":[16.1341876984,47.874912262],"type":"Point"}
}