{
  "type": "Feature",
  "properties": {
    "addr:full":"Tivoligasse 24 Wien Wien 1120",
    "addr:housenumber":"24",
    "addr:postcode":"1120",
    "addr:street":"Tivoligasse",
    "iso:country":"AT",
    "sg:address":"Tivoligasse 24",
    "sg:city":"Wien",
    "sg:classifiers":[
        {
            "category":"Food & Beverages",
            "subcategory":"Chocolate",
            "type":"Retail Goods"
        }
    ],
    "sg:phone":"+43 1 8132129",
    "sg:postcode":"1120",
    "sg:province":"Wien",
    "wof:name":"Jonny Schokoladen Ges.m.b.H.",
    "wof:placetype":"venue"
},
  "geometry": {"coordinates":[16.3259220123,48.1803245544],"type":"Point"}
}