{
  "type": "Feature",
  "properties": {
    "addr:full":"R\u00f6merweg 750 Seefeld in Tirol Tirol 6100",
    "addr:housenumber":"750",
    "addr:postcode":"6100",
    "addr:street":"Seefeld;Tirol",
    "iso:country":"AT",
    "sg:address":"R\u00f6merweg 750",
    "sg:city":"Seefeld in Tirol",
    "sg:orig_category":"Pensionen / Privatzimmer",
    "sg:phone":"+43 5212 2990",
    "sg:postcode":"6100",
    "sg:province":"Tirol",
    "wof:name":"Haus Bergwelt",
    "wof:placetype":"venue"
},
  "geometry": {"coordinates":[11.1889953613,47.3294143677],"type":"Point"}
}