{
  "type": "Feature",
  "properties": {
    "addr:full":"Altstadt 2A Bruck an der Leitha Nieder\u00f6sterreich 2460",
    "addr:housenumber":"2a",
    "addr:postcode":"2460",
    "addr:street":"Altstadt",
    "iso:country":"AT",
    "sg:address":"Altstadt 2A",
    "sg:city":"Bruck an der Leitha",
    "sg:orig_category":"Damenmoden",
    "sg:phone":"+43 2162 64822",
    "sg:postcode":"2460",
    "sg:province":"Nieder\u00f6sterreich",
    "wof:name":"Heissenberger Otto - Sport und Mode",
    "wof:placetype":"venue"
},
  "geometry": {"coordinates":[16.7770729065,48.0221099854],"type":"Point"}
}