{
  "type": "Feature",
  "properties": {
    "addr:full":"Bergstr 2 Sulz-R\u00f6this Vorarlberg 6832",
    "addr:housenumber":"2",
    "addr:postcode":"6832",
    "addr:street":"Bergstr",
    "iso:country":"AT",
    "sg:address":"Bergstr 2",
    "sg:city":"Sulz-R\u00f6this",
    "sg:orig_category":"Lebensmittel / Einzelhandel",
    "sg:phone":"+43 4355 2241257",
    "sg:postcode":"6832",
    "sg:province":"Vorarlberg",
    "wof:name":"Matt Stephanie",
    "wof:placetype":"venue"
},
  "geometry": {"coordinates":[9.6628751755,47.2872886658],"type":"Point"}
}