{
  "type": "Feature",
  "properties": {
    "iso:country":"AT",
    "sg:address":"Wernhartsgrub 3",
    "sg:city":"Eggerding",
    "sg:orig_category":"Installationsunternehmen",
    "sg:phone":"+43 7767 379",
    "sg:postcode":"4773",
    "sg:province":"Ober\u00f6sterreich",
    "wof:name":"Muckenhumer Rudolf - Solar-Biomasseheizungen",
    "wof:placetype":"venue"
},
  "geometry": {"coordinates":[13.4591608047,48.3581390381],"type":"Point"}
}