{
  "type": "Feature",
  "properties": {
    "addr:full":"Eggerdinger Str 10 Antiesenhofen Ober\u00f6sterreich 4980",
    "addr:housenumber":"10",
    "addr:postcode":"4980",
    "addr:street":"Str",
    "iso:country":"AT",
    "sg:address":"Eggerdinger Str 10",
    "sg:city":"Antiesenhofen",
    "sg:orig_category":"Maler, Anstreicher U Lackierer",
    "sg:phone":"+43 4377 595445",
    "sg:postcode":"4980",
    "sg:province":"Ober\u00f6sterreich",
    "wof:name":"Huber Hannes",
    "wof:placetype":"venue"
},
  "geometry": {"coordinates":[13.4021348953,48.345451355],"type":"Point"}
}