{
  "type": "Feature",
  "properties": {
    "iso:country":"AT",
    "sg:address":"Kirchst\u00e4ttstr 50",
    "sg:city":"Obertrum am See",
    "sg:orig_category":"Elektroinstallationsunternehmen",
    "sg:phone":"+43 6219 64450",
    "sg:postcode":"5162",
    "sg:province":"Salzburg",
    "wof:name":"Elektro Schweiger KEG",
    "wof:placetype":"venue"
},
  "geometry": {"coordinates":[13.070933342,47.9385147095],"type":"Point"}
}