{
  "type": "Feature",
  "properties": {
    "addr:full":"Hetzendorfer Str 63 Wien Wien 1120",
    "addr:postcode":"1120",
    "addr:street":"Str 63",
    "iso:country":"AT",
    "sg:address":"Hetzendorfer Str 63",
    "sg:city":"Wien",
    "sg:orig_category":"Unternehmensberatung",
    "sg:phone":"+43 1 8049519",
    "sg:postcode":"1120",
    "sg:province":"Wien",
    "wof:name":"IQM.eureka Unternehmensberatung GmbH Nfg OEG",
    "wof:placetype":"venue"
},
  "geometry": {"coordinates":[16.3132305145,48.1658782959],"type":"Point"}
}