{
  "type": "Feature",
  "properties": {
    "iso:country":"AT",
    "sg:address":"Gemeindeg 6",
    "sg:city":"Obdach",
    "sg:orig_category":"Feuerwehren",
    "sg:phone":"+43 3578 4058",
    "sg:postcode":"8742",
    "sg:province":"Steiermark",
    "wof:name":"Freiwillige Feuerwehr Obdach",
    "wof:placetype":"venue"
},
  "geometry": {"coordinates":[14.6953725815,47.0679969788],"type":"Point"}
}