{
  "type": "Feature",
  "properties": {
    "addr:full":"Peterskirchen 28 Peterskirchen Ober\u00f6sterreich 4743",
    "addr:housenumber":"28",
    "addr:postcode":"4743",
    "addr:street":"Peterskirchen",
    "iso:country":"AT",
    "sg:address":"Peterskirchen 28",
    "sg:city":"Peterskirchen",
    "sg:classifiers":[
        {
            "category":"Communications",
            "subcategory":"Radio Station",
            "type":"Services"
        }
    ],
    "sg:phone":"+43 7750 3402",
    "sg:postcode":"4743",
    "sg:province":"Ober\u00f6sterreich",
    "sg:tags":[
        "economic",
        "expert"
    ],
    "wof:name":"Wilfried-August Manhartsgruber",
    "wof:placetype":"venue"
},
  "geometry": {"coordinates":[13.5475358963,48.238117218],"type":"Point"}
}