{
  "type": "Feature",
  "properties": {
    "iso:country":"AT",
    "sg:address":"Elisabethstr 93",
    "sg:city":"Graz",
    "sg:classifiers":[
        {
            "category":"Travel",
            "subcategory":"Hotels & Motels",
            "type":"Entertainment"
        }
    ],
    "sg:phone":"+43 4331 63221580",
    "sg:postcode":"8010",
    "sg:province":"Steiermark",
    "wof:name":"Akademikerhilfe - Studentenheime",
    "wof:placetype":"venue"
},
  "geometry": {"coordinates":[15.4623527527,47.0780448914],"type":"Point"}
}