{
  "type": "Feature",
  "properties": {
    "addr:full":"Albrechtstr 88/II/2 Klosterneuburg Nieder\u00f6sterreich 3400",
    "addr:housenumber":"88 / ii / 2",
    "addr:postcode":"3400",
    "addr:street":"Albrechtstr;Niederoesterreich",
    "iso:country":"AT",
    "sg:address":"Albrechtstr 88/II/2",
    "sg:city":"Klosterneuburg",
    "sg:orig_category":"Steuerberatung",
    "sg:phone":"+43 2243 21980",
    "sg:postcode":"3400",
    "sg:province":"Nieder\u00f6sterreich",
    "wof:name":"Fritsch Wolfgang Dr",
    "wof:placetype":"venue"
},
  "geometry": {"coordinates":[16.3252258301,48.3049087524],"type":"Point"}
}