{
  "type": "Feature",
  "properties": {
    "addr:full":"Glaserstr 34 Linz Ober\u00f6sterreich 4040",
    "addr:housenumber":"34",
    "addr:postcode":"4040",
    "addr:street":"Glaserstr",
    "iso:country":"AT",
    "sg:address":"Glaserstr 34",
    "sg:city":"Linz",
    "sg:orig_category":"Ingenieurkonsulenten / Zivilingenieure",
    "sg:phone":"+43 732 243855",
    "sg:postcode":"4040",
    "sg:province":"Ober\u00f6sterreich",
    "wof:name":"PSQC Dipl-Ing Peter Steinbach Quality Consulting",
    "wof:placetype":"venue"
},
  "geometry": {"coordinates":[14.3092031479,48.334980011],"type":"Point"}
}