{
  "type": "Feature",
  "properties": {
    "addr:full":"Hauptstr 22 Breitenfurt Nieder\u00f6sterreich 2384",
    "addr:housenumber":"22",
    "addr:postcode":"2384",
    "addr:street":"Hauptstr",
    "iso:country":"AT",
    "sg:address":"Hauptstr 22",
    "sg:city":"Breitenfurt",
    "sg:classifiers":[
        {
            "category":"Restaurant",
            "type":"Food & Drink"
        }
    ],
    "sg:phone":"+43 664 4236076",
    "sg:postcode":"2384",
    "sg:province":"Nieder\u00f6sterreich",
    "wof:name":"Niewiadomski - Blaas",
    "wof:placetype":"venue"
},
  "geometry": {"coordinates":[16.1783370972,48.1339530945],"type":"Point"}
}