{
  "type": "Feature",
  "properties": {
    "addr:full":"Klosterneuburger Str 12 Langenzersdorf Nieder\u00f6sterreich 2103",
    "addr:postcode":"2103",
    "addr:street":"Str 12",
    "iso:country":"AT",
    "sg:address":"Klosterneuburger Str 12",
    "sg:city":"Langenzersdorf",
    "sg:orig_category":"Hauptschulen",
    "sg:phone":"+43 2244 2312",
    "sg:postcode":"2103",
    "sg:province":"Nieder\u00f6sterreich",
    "wof:name":"Hauptschule",
    "wof:placetype":"venue"
},
  "geometry": {"coordinates":[16.3554000854,48.3081665039],"type":"Point"}
}