{
  "type": "Feature",
  "properties": {
    "addr:full":"Gewerbestrasse 224 Bramberg am Wildkogel Salzburg 5733",
    "addr:housenumber":"224",
    "addr:postcode":"5733",
    "addr:street":"Gewerbestrasse;Salzburg",
    "iso:country":"AT",
    "sg:address":"Gewerbestrasse 224",
    "sg:city":"Bramberg am Wildkogel",
    "sg:orig_category":"LocksmithS Shops",
    "sg:phone":"+43 6566 7441",
    "sg:postcode":"5733",
    "sg:province":"Salzburg",
    "wof:name":"Alois Freiberger Portal- u. Anlagenbau GesmbH",
    "wof:placetype":"venue"
},
  "geometry": {"coordinates":[12.3472499847,47.2725601196],"type":"Point"}
}