{
  "type": "Feature",
  "properties": {
    "iso:country":"AT",
    "sg:address":"Wiener Strasse 53",
    "sg:city":"Purkersdorf",
    "sg:classifiers":[
        {
            "category":"Health Services",
            "subcategory":"Clinic",
            "type":"Services"
        }
    ],
    "sg:phone":"+43 2231 65512",
    "sg:postcode":"3002",
    "sg:province":"Nieder\u00f6sterreich",
    "sg:tags":[
        "dental",
        "chair"
    ],
    "sg:website":"kavo.at",
    "wof:name":"KaVo Austria Dentalwarenhandelsges.m.b.H.",
    "wof:placetype":"venue"
},
  "geometry": {"coordinates":[16.197013855,48.2054176331],"type":"Point"}
}