{
  "type": "Feature",
  "properties": {
    "iso:country":"AT",
    "sg:address":"Markt 17",
    "sg:city":"Werfen",
    "sg:orig_category":"Elektroinstallationsunternehmen",
    "sg:phone":"+43 4366 43413225",
    "sg:postcode":"5450",
    "sg:province":"Salzburg",
    "wof:name":"Elektrohandel RS - Roman Sighel",
    "wof:placetype":"venue"
},
  "geometry": {"coordinates":[13.1883554459,47.478099823],"type":"Point"}
}