{
  "type": "Feature",
  "properties": {
    "iso:country":"AT",
    "sg:address":"Hofhaymer Allee 22/3",
    "sg:city":"Salzburg",
    "sg:orig_category":"Fotografen",
    "sg:phone":"+43 676 4948470",
    "sg:postcode":"5020",
    "sg:province":"Salzburg",
    "wof:name":"Kolarik Andreas",
    "wof:placetype":"venue"
},
  "geometry": {"coordinates":[13.0538187027,47.7860946655],"type":"Point"}
}