{
  "type": "Feature",
  "properties": {
    "iso:country":"AT",
    "sg:address":"Attergaustr 50",
    "sg:city":"St. Georgen im Attergau",
    "sg:orig_category":"Elektroinstallationsunternehmen",
    "sg:phone":"+43 4376 676330",
    "sg:postcode":"4880",
    "sg:province":"Ober\u00f6sterreich",
    "wof:name":"Buchinger Elektro GmbH",
    "wof:placetype":"venue"
},
  "geometry": {"coordinates":[13.4864864349,47.9358596802],"type":"Point"}
}