{
  "type": "Feature",
  "properties": {
    "addr:full":"Bergwerkstrasse 331 Schladming Steiermark 8970",
    "addr:housenumber":"331",
    "addr:postcode":"8970",
    "addr:street":"Bergwerkstrasse",
    "iso:country":"AT",
    "sg:address":"Bergwerkstrasse 331",
    "sg:city":"Schladming",
    "sg:classifiers":[
        {
            "category":"Military Area",
            "subcategory":"Air Force Base",
            "type":"Public Place"
        }
    ],
    "sg:phone":"+43 3687 23204",
    "sg:postcode":"8970",
    "sg:province":"Steiermark",
    "sg:tags":[
        "attic",
        "stair"
    ],
    "wof:name":"Ferdinand Pachernegg",
    "wof:placetype":"venue"
},
  "geometry": {"coordinates":[13.6749048233,47.3936538696],"type":"Point"}
}