{
  "type": "Feature",
  "properties": {
    "addr:full":"Ettenreichg 9 Wien Wien 1100",
    "addr:housenumber":"9",
    "addr:postcode":"1100",
    "addr:street":"Ettenreichg",
    "iso:country":"AT",
    "sg:address":"Ettenreichg 9",
    "sg:city":"Wien",
    "sg:classifiers":[
        {
            "category":"Restaurant",
            "type":"Food & Drink"
        }
    ],
    "sg:phone":"+43 1 6072634",
    "sg:postcode":"1100",
    "sg:province":"Wien",
    "sg:tags":[
        "pizzeria"
    ],
    "wof:name":"Pizzeria Alexandra",
    "wof:placetype":"venue"
},
  "geometry": {"coordinates":[16.3768787384,48.1723060608],"type":"Point"}
}