{
  "type": "Feature",
  "properties": {
    "addr:full":"Nr 136 Feichten Tirol 6524",
    "addr:postcode":"6524",
    "addr:street":"Nr;Feichten Tirol",
    "iso:country":"AT",
    "sg:address":"Nr 136",
    "sg:city":"Feichten",
    "sg:orig_category":"Lebensmittel / Einzelhandel",
    "sg:phone":"+43 4354 75423",
    "sg:postcode":"6524",
    "sg:province":"Tirol",
    "wof:name":"Nah & Frisch Plankensteiner",
    "wof:placetype":"venue"
},
  "geometry": {"coordinates":[10.7479600906,47.0302619934],"type":"Point"}
}