{
  "type": "Feature",
  "properties": {
    "addr:full":"Mallestiger Pl 6 Finkenstein K\u00e4rnten 9584",
    "addr:housenumber":"6",
    "addr:postcode":"9584",
    "addr:street":"Mallestiger Pl;Kaernten",
    "iso:country":"AT",
    "sg:address":"Mallestiger Pl 6",
    "sg:city":"Finkenstein",
    "sg:orig_category":"Installationsunternehmen",
    "sg:phone":"+43 4254 2055",
    "sg:postcode":"9584",
    "sg:province":"K\u00e4rnten",
    "wof:name":"Wurzer Johannes",
    "wof:placetype":"venue"
},
  "geometry": {"coordinates":[13.8711080551,46.5611763],"type":"Point"}
}