{
  "type": "Feature",
  "properties": {
    "addr:full":"Neug 14 Weissenbach an der Triesting Nieder\u00f6sterreich 2564",
    "addr:housenumber":"14",
    "addr:postcode":"2564",
    "addr:street":"Neug",
    "iso:country":"AT",
    "sg:address":"Neug 14",
    "sg:city":"Weissenbach an der Triesting",
    "sg:orig_category":"Autobusunternehmen",
    "sg:phone":"+43 2674 87224",
    "sg:postcode":"2564",
    "sg:province":"Nieder\u00f6sterreich",
    "wof:name":"Grill Hans",
    "wof:placetype":"venue"
},
  "geometry": {"coordinates":[15.9736728668,47.9732284546],"type":"Point"}
}