{
  "type": "Feature",
  "properties": {
    "iso:country":"AT",
    "sg:address":"\u00dcberh\u00fclling 2",
    "sg:city":"Laakirchen",
    "sg:orig_category":"Partyservice",
    "sg:phone":"+43 76133122",
    "sg:postcode":"4663",
    "sg:province":"Ober\u00f6sterreich",
    "wof:name":"Sch\u00f6nberger KEG",
    "wof:placetype":"venue"
},
  "geometry": {"coordinates":[13.8235998154,47.9830665588],"type":"Point"}
}