{
  "type": "Feature",
  "properties": {
    "addr:full":"Gewerbepark 5 P\u00f6lfing-Brunn Steiermark 8544",
    "addr:housenumber":"5",
    "addr:postcode":"8544",
    "addr:street":"Gewerbepark",
    "iso:country":"AT",
    "sg:address":"Gewerbepark 5",
    "sg:city":"P\u00f6lfing-Brunn",
    "sg:orig_category":"Isolierungen",
    "sg:phone":"+43 4366 41137384",
    "sg:postcode":"8544",
    "sg:province":"Steiermark",
    "wof:name":"Vidally-Krainer GmbH",
    "wof:placetype":"venue"
},
  "geometry": {"coordinates":[15.292427063,46.7258605957],"type":"Point"}
}