{
  "type": "Feature",
  "properties": {
    "addr:full":"Wildpretstrasse 18 Wien Wien 1110",
    "addr:housenumber":"18",
    "addr:postcode":"1110",
    "addr:street":"Wildpretstrasse",
    "iso:country":"AT",
    "sg:address":"Wildpretstrasse 18",
    "sg:city":"Wien",
    "sg:classifiers":[
        {
            "category":"Structure",
            "subcategory":"Bridge",
            "type":"Public Place"
        }
    ],
    "sg:phone":"+43 1 7697762",
    "sg:postcode":"1110",
    "sg:province":"Wien",
    "sg:tags":[
        "construction"
    ],
    "sg:website":"ruck.at",
    "wof:name":"Bauunternehmen W. Ruck Ges.m.b.H.",
    "wof:placetype":"venue"
},
  "geometry": {"coordinates":[16.4545898438,48.1769638062],"type":"Point"}
}