{
  "type": "Feature",
  "properties": {
    "iso:country":"AT",
    "sg:address":"Am Hof 126",
    "sg:city":"Hallstatt",
    "sg:orig_category":"Schifffahrt",
    "sg:phone":"+43 6134 8228",
    "sg:postcode":"4830",
    "sg:province":"Ober\u00f6sterreich",
    "wof:name":"Hallst\u00e4ttersee-Schiffahrt Hemetsberger KEG",
    "wof:placetype":"venue"
},
  "geometry": {"coordinates":[13.6491317749,47.5612754822],"type":"Point"}
}