{
  "type": "Feature",
  "properties": {
    "addr:full":"Neutorstr 52 Salzburg Salzburg 5020",
    "addr:housenumber":"52",
    "addr:postcode":"5020",
    "addr:street":"Neutorstr;Salzburg",
    "iso:country":"AT",
    "sg:address":"Neutorstr 52",
    "sg:city":"Salzburg",
    "sg:orig_category":"\u00c3\u201erzte / F Allgemeinmedizin",
    "sg:phone":"+43 4366 2823512",
    "sg:postcode":"5020",
    "sg:province":"Salzburg",
    "wof:name":"Sieber Ullrich Dr",
    "wof:placetype":"venue"
},
  "geometry": {"coordinates":[13.0268125534,47.7961921692],"type":"Point"}
}