{
  "type": "Feature",
  "properties": {
    "addr:full":"Hauptpl 3 Schwechat Nieder\u00f6sterreich 2320",
    "addr:housenumber":"3",
    "addr:postcode":"2320",
    "addr:street":"Hauptpl;Niederoesterreich",
    "iso:country":"AT",
    "sg:address":"Hauptpl 3",
    "sg:city":"Schwechat",
    "sg:orig_category":"Versicherungsunternehmen",
    "sg:phone":"+43 1 7071064",
    "sg:postcode":"2320",
    "sg:province":"Nieder\u00f6sterreich",
    "wof:name":"Donau Allgemeine Versicherungs AG",
    "wof:placetype":"venue"
},
  "geometry": {"coordinates":[16.4774055481,48.1407051086],"type":"Point"}
}