{
  "type": "Feature",
  "properties": {
    "addr:full":"Joanneumring 5 Graz Steiermark 8010",
    "addr:housenumber":"5",
    "addr:postcode":"8010",
    "addr:street":"Joanneumring",
    "iso:country":"AT",
    "sg:address":"Joanneumring 5",
    "sg:city":"Graz",
    "sg:orig_category":"Zahntechnische Laboratorien",
    "sg:phone":"+43 316 840902",
    "sg:postcode":"8010",
    "sg:province":"Steiermark",
    "wof:name":"Dentalia Zahntechnisches Labor GesmbH",
    "wof:placetype":"venue"
},
  "geometry": {"coordinates":[15.4409646988,47.0674095154],"type":"Point"}
}