{
  "type": "Feature",
  "properties": {
    "addr:full":"M\u00fcnchnerstr. 114  Seefeld in Tirol Tirol 6100",
    "addr:housenumber":"114",
    "addr:postcode":"6100",
    "addr:street":"Seefeld;Tirol",
    "iso:country":"AT",
    "sg:address":"M\u00fcnchnerstr. 114 ",
    "sg:city":"Seefeld in Tirol",
    "sg:classifiers":[
        {
            "category":"Travel",
            "subcategory":"Travel Agent",
            "type":"Entertainment"
        }
    ],
    "sg:phone":"+43 4352 122221",
    "sg:postcode":"6100",
    "sg:province":"Tirol",
    "sg:tags":[
        "business"
    ],
    "wof:name":"HOTEL TYROL SEEFELD GMBH",
    "wof:placetype":"venue"
},
  "geometry": {"coordinates":[11.1465129852,47.3113555908],"type":"Point"}
}