{
  "type": "Feature",
  "properties": {
    "addr:full":"Nr 25 Mettersdorf am Sa\u00dfbach Steiermark 8092",
    "addr:postcode":"8092",
    "addr:street":"Nr",
    "iso:country":"AT",
    "sg:address":"Nr 25",
    "sg:city":"Mettersdorf am Sa\u00dfbach",
    "sg:orig_category":"Unternehmensberatung",
    "sg:phone":"+43 664 1819377",
    "sg:postcode":"8092",
    "sg:province":"Steiermark",
    "wof:name":"Jost August \u00f6kRat B\u00e4uerliche Unternehmensberatung",
    "wof:placetype":"venue"
},
  "geometry": {"coordinates":[15.7108011246,46.8041954041],"type":"Point"}
}