{
  "type": "Feature",
  "properties": {
    "addr:full":"Badstr 32 Metnitz K\u00e4rnten 9363",
    "addr:housenumber":"32",
    "addr:postcode":"9363",
    "addr:street":"Badstr;Kaernten",
    "iso:country":"AT",
    "sg:address":"Badstr 32",
    "sg:city":"Metnitz",
    "sg:orig_category":"Zimmereien",
    "sg:phone":"+43 4267 2060",
    "sg:postcode":"9363",
    "sg:province":"K\u00e4rnten",
    "wof:name":"Leitner Lambert",
    "wof:placetype":"venue"
},
  "geometry": {"coordinates":[14.1992406845,46.9811286926],"type":"Point"}
}