{
  "type": "Feature",
  "properties": {
    "iso:country":"AT",
    "sg:address":"Bahnhofstr 19",
    "sg:city":"Reutte",
    "sg:orig_category":"Gewerkschaften",
    "sg:phone":"+43 4356 7273222",
    "sg:postcode":"6600",
    "sg:province":"Tirol",
    "wof:name":"\u00f6sterreichischer Gewerkschaftsbund",
    "wof:placetype":"venue"
},
  "geometry": {"coordinates":[10.7207403183,47.4937171936],"type":"Point"}
}