{
  "type": "Feature",
  "properties": {
    "iso:country":"AT",
    "sg:address":"Bleiberger Str 67",
    "sg:city":"Villach",
    "sg:orig_category":"Fenster",
    "sg:phone":"+43 4242 574470",
    "sg:postcode":"9500",
    "sg:province":"K\u00e4rnten",
    "wof:name":"Opitz-ideal Kunststoff-Fenstererzeugung GesmbH",
    "wof:placetype":"venue"
},
  "geometry": {"coordinates":[13.7610635757,46.6230926514],"type":"Point"}
}