{
  "type": "Feature",
  "properties": {
    "addr:full":"Flie\u00dferau 393 Flie\u00df Tirol 6521",
    "addr:housenumber":"393",
    "addr:postcode":"6521",
    "addr:street":"Fliesserau;Tirol",
    "iso:country":"AT",
    "sg:address":"Flie\u00dferau 393",
    "sg:city":"Flie\u00df",
    "sg:orig_category":"Garten- U Landschaftsgestaltung",
    "sg:phone":"+43 5442 627100",
    "sg:postcode":"6521",
    "sg:province":"Tirol",
    "wof:name":"Grasberger Landschaftsbau",
    "wof:placetype":"venue"
},
  "geometry": {"coordinates":[10.6277103424,47.1199989319],"type":"Point"}
}