{
  "type": "Feature",
  "properties": {
    "addr:full":"Haydnstr 51 Leopoldsdorf Nieder\u00f6sterreich 2333",
    "addr:housenumber":"51",
    "addr:postcode":"2333",
    "addr:street":"Haydnstr",
    "iso:country":"AT",
    "sg:address":"Haydnstr 51",
    "sg:city":"Leopoldsdorf",
    "sg:orig_category":"Exporteure U Importeure",
    "sg:phone":"+43 4322 35422370",
    "sg:postcode":"2333",
    "sg:province":"Nieder\u00f6sterreich",
    "wof:name":"L\u00f6ffler Werner Ing",
    "wof:placetype":"venue"
},
  "geometry": {"coordinates":[16.3877086639,48.1168937683],"type":"Point"}
}