{
  "type": "Feature",
  "properties": {
    "addr:full":"Ziegelofeng 6a Wien Wien 1040",
    "addr:housenumber":"6a",
    "addr:postcode":"1040",
    "addr:street":"Ziegelofeng",
    "iso:country":"AT",
    "sg:address":"Ziegelofeng 6a",
    "sg:city":"Wien",
    "sg:orig_category":"Friseure U Frisiersalons",
    "sg:phone":"+43 1 5872119",
    "sg:postcode":"1040",
    "sg:province":"Wien",
    "wof:name":"L\u00f6scher Marion",
    "wof:placetype":"venue"
},
  "geometry": {"coordinates":[16.3634376526,48.1891899109],"type":"Point"}
}