{
  "type": "Feature",
  "properties": {
    "addr:full":"Brunnenweg 4 Lienz Tirol 9900",
    "addr:housenumber":"4",
    "addr:postcode":"9900",
    "addr:street":"Brunnenweg;Tirol",
    "iso:country":"AT",
    "sg:address":"Brunnenweg 4",
    "sg:city":"Lienz",
    "sg:orig_category":"Architekten",
    "sg:phone":"+43 4852 64533",
    "sg:postcode":"9900",
    "sg:province":"Tirol",
    "wof:name":"Eck Werner Dipl-Ing",
    "wof:placetype":"venue"
},
  "geometry": {"coordinates":[12.777589798,46.8299827576],"type":"Point"}
}