{
  "type": "Feature",
  "properties": {
    "addr:full":"Unterfahrenbach 57 Heimschuh Steiermark 8451",
    "addr:housenumber":"57",
    "addr:postcode":"8451",
    "addr:street":"Unterfahrenbach",
    "iso:country":"AT",
    "sg:address":"Unterfahrenbach 57",
    "sg:city":"Heimschuh",
    "sg:classifiers":[
        {
            "category":"Home & Garden",
            "subcategory":"Building Materials",
            "type":"Retail Goods"
        }
    ],
    "sg:phone":"+43 3452 72778",
    "sg:postcode":"8451",
    "sg:province":"Steiermark",
    "sg:tags":[
        "aluminium",
        "gutter"
    ],
    "wof:name":"Schwinger-Dach Ges.m.b.H.",
    "wof:placetype":"venue"
},
  "geometry": {"coordinates":[15.4880180359,46.7347259521],"type":"Point"}
}