{
  "type": "Feature",
  "properties": {
    "addr:full":"Jetzing 5 Leonding Ober\u00f6sterreich 4060",
    "addr:housenumber":"5",
    "addr:postcode":"4060",
    "addr:street":"Jetzing",
    "iso:country":"AT",
    "sg:address":"Jetzing 5",
    "sg:city":"Leonding",
    "sg:orig_category":"Berufsbekleidung / Erzeugung U Gro\u00c3\u0178handel",
    "sg:phone":"+43 4373 26806620",
    "sg:postcode":"4060",
    "sg:province":"Ober\u00f6sterreich",
    "sg:website":"khan.at",
    "wof:name":"KHAN Berufsbekleidung GmbH",
    "wof:placetype":"venue"
},
  "geometry": {"coordinates":[14.2295026779,48.2632064819],"type":"Point"}
}