{
  "type": "Feature",
  "properties": {
    "addr:full":"Nr 164 Ramsau am Dachstein Steiermark 8972",
    "addr:postcode":"8972",
    "addr:street":"Nr 164",
    "iso:country":"AT",
    "sg:address":"Nr 164",
    "sg:city":"Ramsau am Dachstein",
    "sg:orig_category":"Pensionen / Privatzimmer",
    "sg:phone":"+43 4336 87818020",
    "sg:postcode":"8972",
    "sg:province":"Steiermark",
    "wof:name":"Pension Alpenhof Inh Maria Simonlehner",
    "wof:placetype":"venue"
},
  "geometry": {"coordinates":[13.6525297165,47.4214515686],"type":"Point"}
}