{
  "type": "Feature",
  "properties": {
    "iso:country":"AT",
    "sg:address":"Schwarzviertler Str 27",
    "sg:city":"St. Paul im Lavanttal",
    "sg:orig_category":"Weine / Einzelhandel",
    "sg:phone":"+43 4357 2403",
    "sg:postcode":"9470",
    "sg:province":"K\u00e4rnten",
    "wof:name":"Pl\u00f6sch Aloisia",
    "wof:placetype":"venue"
},
  "geometry": {"coordinates":[14.8674278259,46.6966362],"type":"Point"}
}