{
  "type": "Feature",
  "properties": {
    "addr:full":"Hauptstr 17 Deutschkreutz Burgenland 7301",
    "addr:housenumber":"17",
    "addr:postcode":"7301",
    "addr:street":"Hauptstr",
    "iso:country":"AT",
    "sg:address":"Hauptstr 17",
    "sg:city":"Deutschkreutz",
    "sg:orig_category":"Spielwaren U Spiele",
    "sg:phone":"+43 2613 89263",
    "sg:postcode":"7301",
    "sg:province":"Burgenland",
    "wof:name":"Aminger Martha",
    "wof:placetype":"venue"
},
  "geometry": {"coordinates":[16.6237831116,47.6025123596],"type":"Point"}
}