{
  "type": "Feature",
  "properties": {
    "addr:full":"Gaisbergstr 13 Salzburg Salzburg 5020",
    "addr:housenumber":"13",
    "addr:postcode":"5020",
    "addr:street":"Gaisbergstr;Salzburg",
    "iso:country":"AT",
    "sg:address":"Gaisbergstr 13",
    "sg:city":"Salzburg",
    "sg:orig_category":"Isolierungen",
    "sg:phone":"+43 662 641852",
    "sg:postcode":"5020",
    "sg:province":"Salzburg",
    "wof:name":"Mosmonder Paul",
    "wof:placetype":"venue"
},
  "geometry": {"coordinates":[13.0680971146,47.8024902344],"type":"Point"}
}