{
  "type": "Feature",
  "properties": {
    "iso:country":"AT",
    "sg:address":"Schulweg 18",
    "sg:city":"Reifnitz",
    "sg:orig_category":"Pensionen / Privatzimmer",
    "sg:phone":"+43 4273 2027",
    "sg:postcode":"9081",
    "sg:province":"K\u00e4rnten",
    "wof:name":"Haus Sch\u00f6nblick",
    "wof:placetype":"venue"
},
  "geometry": {"coordinates":[14.1756668091,46.6063995361],"type":"Point"}
}