{
  "type": "Feature",
  "properties": {
    "addr:full":"Sonnenstr 8 Kirchbichl Tirol 6322",
    "addr:housenumber":"8",
    "addr:postcode":"6322",
    "addr:street":"Sonnenstr;Tirol",
    "iso:country":"AT",
    "sg:address":"Sonnenstr 8",
    "sg:city":"Kirchbichl",
    "sg:orig_category":"Physiotherapie",
    "sg:phone":"+43 5332 87656",
    "sg:postcode":"6322",
    "sg:province":"Tirol",
    "wof:name":"Physiotherapie Rauscher & Nagele & Scheider",
    "wof:placetype":"venue"
},
  "geometry": {"coordinates":[12.081612587,47.5069885254],"type":"Point"}
}