{
  "type": "Feature",
  "properties": {
    "iso:country":"AT",
    "sg:address":"Roseggerstr 102",
    "sg:city":"Marchtrenk",
    "sg:orig_category":"Technische Bedarfsartikel",
    "sg:phone":"+43 7243 585310",
    "sg:postcode":"4614",
    "sg:province":"Ober\u00f6sterreich",
    "wof:name":"Sturm W GesmbH",
    "wof:placetype":"venue"
},
  "geometry": {"coordinates":[14.1349458694,48.2016487122],"type":"Point"}
}