{
  "type": "Feature",
  "properties": {
    "addr:full":"Hainfelder Str 72 Weissenbach an der Triesting Nieder\u00f6sterreich 2564",
    "addr:postcode":"2564",
    "addr:street":"Str 72",
    "iso:country":"AT",
    "sg:address":"Hainfelder Str 72",
    "sg:city":"Weissenbach an der Triesting",
    "sg:orig_category":"Fenster",
    "sg:phone":"+43 4326 7281301",
    "sg:postcode":"2564",
    "sg:province":"Nieder\u00f6sterreich",
    "wof:name":"FTS Johannes Fichtinger",
    "wof:placetype":"venue"
},
  "geometry": {"coordinates":[16.0648403168,47.9814300537],"type":"Point"}
}