{
  "type": "Feature",
  "properties": {
    "addr:full":"Feldgasse 75 Bruck an der Leitha Nieder\u00f6sterreich 2460",
    "addr:housenumber":"75",
    "addr:postcode":"2460",
    "addr:street":"Feldgasse",
    "iso:country":"AT",
    "sg:address":"Feldgasse 75",
    "sg:city":"Bruck an der Leitha",
    "sg:classifiers":[
        {
            "category":"Banks & Credit Unions",
            "subcategory":"Investment Brokerage",
            "type":"Services"
        }
    ],
    "sg:phone":"+43 2162 639390",
    "sg:postcode":"2460",
    "sg:province":"Nieder\u00f6sterreich",
    "sg:tags":[
        "mobile",
        "toilet"
    ],
    "sg:website":"juely.at",
    "wof:name":"Annemarie J\u00fcly",
    "wof:placetype":"venue"
},
  "geometry": {"coordinates":[16.7641124725,48.0262947083],"type":"Point"}
}