{
  "type": "Feature",
  "properties": {
    "addr:full":"Schillerstr 9 F\u00fcrstenfeld Steiermark 8280",
    "addr:housenumber":"9",
    "addr:postcode":"8280",
    "addr:street":"Schillerstr",
    "iso:country":"AT",
    "sg:address":"Schillerstr 9",
    "sg:city":"F\u00fcrstenfeld",
    "sg:orig_category":"Gerichte",
    "sg:phone":"+43 3382 524430",
    "sg:postcode":"8280",
    "sg:province":"Steiermark",
    "wof:name":"Bezirksgericht F\u00fcrstenfeld",
    "wof:placetype":"venue"
},
  "geometry": {"coordinates":[16.0816669464,47.0458030701],"type":"Point"}
}