{
  "type": "Feature",
  "properties": {
    "addr:full":"Prielstr 8 Sattledt Ober\u00f6sterreich 4642",
    "addr:housenumber":"8",
    "addr:postcode":"4642",
    "addr:street":"Prielstr",
    "iso:country":"AT",
    "sg:address":"Prielstr 8",
    "sg:city":"Sattledt",
    "sg:orig_category":"Massagen",
    "sg:phone":"+43 7244 81230",
    "sg:postcode":"4642",
    "sg:province":"Ober\u00f6sterreich",
    "wof:name":"Reindl KEG Inst. f. Harmonisierung u. Regenerierung",
    "wof:placetype":"venue"
},
  "geometry": {"coordinates":[14.0552158356,48.0652275085],"type":"Point"}
}