{
  "type": "Feature",
  "properties": {
    "iso:country":"AT",
    "sg:address":"Nr 40",
    "sg:city":"Rastenfeld",
    "sg:orig_category":"Lebensmittel / Einzelhandel",
    "sg:phone":"+43 2826 7630",
    "sg:postcode":"3532",
    "sg:province":"Nieder\u00f6sterreich",
    "wof:name":"Hohenegger Erika",
    "wof:placetype":"venue"
},
  "geometry": {"coordinates":[117.87354278559999,26.9144191742],"type":"Point"}
}