{
  "type": "Feature",
  "properties": {
    "addr:full":"Nr 82 Feichten Tirol 6524",
    "addr:postcode":"6524",
    "addr:street":"Nr;Feichten Tirol",
    "iso:country":"AT",
    "sg:address":"Nr 82",
    "sg:city":"Feichten",
    "sg:classifiers":[
        {
            "category":"Travel",
            "subcategory":"Hotels & Motels",
            "type":"Entertainment"
        }
    ],
    "sg:phone":"+43 4354 75202",
    "sg:postcode":"6524",
    "sg:province":"Tirol",
    "wof:name":"Hotel J\u00e4gerhof",
    "wof:placetype":"venue"
},
  "geometry": {"coordinates":[10.7479600906,47.0302619934],"type":"Point"}
}