{
  "type": "Feature",
  "properties": {
    "iso:country":"AT",
    "sg:address":"Au 2",
    "sg:city":"Sch\u00f6nwies",
    "sg:orig_category":"Reifen U Reifendienste",
    "sg:phone":"+43 5412 69330",
    "sg:postcode":"6491",
    "sg:province":"Tirol",
    "wof:name":"G\u00e4chter GesmbH",
    "wof:placetype":"venue"
},
  "geometry": {"coordinates":[10.7206449509,47.2138404846],"type":"Point"}
}