{
  "type": "Feature",
  "properties": {
    "addr:full":"Stockholmer Pl 4 Wien Wien 1100",
    "addr:housenumber":"4",
    "addr:postcode":"1100",
    "addr:street":"Stockholmer Pl",
    "iso:country":"AT",
    "sg:address":"Stockholmer Pl 4",
    "sg:city":"Wien",
    "sg:orig_category":"Papier- U Schreibwaren / Einzelhandel",
    "sg:phone":"+43 4367 66903630",
    "sg:postcode":"1100",
    "sg:province":"Wien",
    "wof:name":"Lese Zeit Christoph Eckl",
    "wof:placetype":"venue"
},
  "geometry": {"coordinates":[16.3813686371,48.1496505737],"type":"Point"}
}