{
  "type": "Feature",
  "properties": {
    "addr:full":"Formanekgasse 45/5 Wien Wien 1190",
    "addr:housenumber":"45 / 5",
    "addr:postcode":"1190",
    "addr:street":"Formanekgasse",
    "iso:country":"AT",
    "sg:address":"Formanekgasse 45/5",
    "sg:city":"Wien",
    "sg:classifiers":[
        {
            "category":"Social Services",
            "subcategory":"Job Training",
            "type":"Services"
        }
    ],
    "sg:phone":"+43 1 3686065",
    "sg:postcode":"1190",
    "sg:province":"Wien",
    "sg:tags":[
        "mental"
    ],
    "sg:website":"selfmanagement.at",
    "wof:name":"Selfmanagment",
    "wof:placetype":"venue"
},
  "geometry": {"coordinates":[16.350736618,48.2490615845],"type":"Point"}
}