{
  "type": "Feature",
  "properties": {
    "addr:full":"Robert Schumann-G 38A/Stg 1 Perchtoldsdorf Nieder\u00f6sterreich 2380",
    "addr:housenumber":"38a / stg 1",
    "addr:postcode":"2380",
    "iso:country":"AT",
    "sg:address":"Robert Schumann-G 38A/Stg 1",
    "sg:city":"Perchtoldsdorf",
    "sg:orig_category":"Me\u00c3\u0178-, Steuer- U Regeltechnik",
    "sg:phone":"+43 1 86962000",
    "sg:postcode":"2380",
    "sg:province":"Nieder\u00f6sterreich",
    "wof:name":"Kuhnke Automation GesmbH",
    "wof:placetype":"venue"
},
  "geometry": {"coordinates":[16.2652320862,48.1192970276],"type":"Point"}
}