{
  "type": "Feature",
  "properties": {
    "addr:full":"Ehregutapl 8 Bregenz Vorarlberg 6900",
    "addr:housenumber":"8",
    "addr:postcode":"6900",
    "addr:street":"Ehregutapl",
    "iso:country":"AT",
    "sg:address":"Ehregutapl 8",
    "sg:city":"Bregenz",
    "sg:orig_category":"Architekten",
    "sg:phone":"+43 5574 428450",
    "sg:postcode":"6900",
    "sg:province":"Vorarlberg",
    "wof:name":"Kuess Helmut Arch Dipl-Ing",
    "wof:placetype":"venue"
},
  "geometry": {"coordinates":[9.7488527298,47.5001564026],"type":"Point"}
}