{
  "type": "Feature",
  "properties": {
    "addr:full":"Ober Roden-Str 2 Saalfelden am Steinernen Meer Salzburg 5760",
    "addr:housenumber":"2",
    "addr:postcode":"5760",
    "addr:street":"Ober Roden-Str",
    "iso:country":"AT",
    "sg:address":"Ober Roden-Str 2",
    "sg:city":"Saalfelden am Steinernen Meer",
    "sg:orig_category":"Installationsunternehmen",
    "sg:phone":"+43 4365 8276196",
    "sg:postcode":"5760",
    "sg:province":"Salzburg",
    "wof:name":"Mitteregger Josef Sanit\u00e4re Gas- u Heizungsinstallationen",
    "wof:placetype":"venue"
},
  "geometry": {"coordinates":[12.8454303741,47.4340133667],"type":"Point"}
}