{
  "type": "Feature",
  "properties": {
    "addr:full":"Bahnhofstr Kiosk Pitten Nieder\u00f6sterreich 2823",
    "addr:postcode":"2823",
    "addr:street":"Niederoesterreich",
    "iso:country":"AT",
    "sg:address":"Bahnhofstr Kiosk",
    "sg:city":"Pitten",
    "sg:orig_category":"Tabaktrafiken",
    "sg:phone":"+43 2627 82504",
    "sg:postcode":"2823",
    "sg:province":"Nieder\u00f6sterreich",
    "wof:name":"H\u00f6ne Renate",
    "wof:placetype":"venue"
},
  "geometry": {"coordinates":[16.18658638,47.7162742615],"type":"Point"}
}