{
  "type": "Feature",
  "properties": {
    "addr:full":"Auf der Huben 3b Jenbach Tirol 6200",
    "addr:housenumber":"3b",
    "addr:postcode":"6200",
    "addr:street":"Auf Der Huben;Tirol",
    "iso:country":"AT",
    "sg:address":"Auf der Huben 3b",
    "sg:city":"Jenbach",
    "sg:classifiers":[
        {
            "category":"Personal",
            "subcategory":"Sauna",
            "type":"Services"
        }
    ],
    "sg:phone":"+43 4352 4461018",
    "sg:postcode":"6200",
    "sg:province":"Tirol",
    "sg:tags":[
        "u",
        "dampfbad"
    ],
    "wof:name":"Sauna Jenbach",
    "wof:placetype":"venue"
},
  "geometry": {"coordinates":[11.7721509933,47.3900299072],"type":"Point"}
}