{
  "type": "Feature",
  "properties": {
    "iso:country":"AT",
    "sg:address":"Seybelg. 24 ",
    "sg:classifiers":[
        {
            "category":"Parking",
            "subcategory":"Lot",
            "type":"Transportation"
        }
    ],
    "sg:phone":"+43 4318 691394",
    "sg:postcode":"1235",
    "sg:tags":[
        "transport",
        "road"
    ],
    "wof:name":"KEMETER GESMBH",
    "wof:placetype":"venue"
},
  "geometry": {"coordinates":[16.2934799194,48.1539306641],"type":"Point"}
}