{
  "type": "Feature",
  "properties": {
    "addr:full":"Erlerstr 6 Innsbruck Tirol 6020",
    "addr:housenumber":"6",
    "addr:postcode":"6020",
    "addr:street":"Erlerstr;Tirol",
    "iso:country":"AT",
    "sg:address":"Erlerstr 6",
    "sg:city":"Innsbruck",
    "sg:classifiers":[
        {
            "category":"Travel",
            "subcategory":"Hotels & Motels",
            "type":"Entertainment"
        }
    ],
    "sg:phone":"+43 512 5870540",
    "sg:postcode":"6020",
    "sg:province":"Tirol",
    "wof:name":"Delevo Hotel",
    "wof:placetype":"venue"
},
  "geometry": {"coordinates":[11.3958864212,47.2666473389],"type":"Point"}
}