{
  "type": "Feature",
  "properties": {
    "iso:country":"AT",
    "sg:address":"Unterer Markt 34",
    "sg:city":"Wildon",
    "sg:orig_category":"Friseure U Frisiersalons",
    "sg:phone":"+43 4331 823234",
    "sg:postcode":"8410",
    "sg:province":"Steiermark",
    "wof:name":"Schulter Charlotte",
    "wof:placetype":"venue"
},
  "geometry": {"coordinates":[15.5159187317,46.8868598938],"type":"Point"}
}