{
  "type": "Feature",
  "properties": {
    "addr:full":"Greuth 14 Tainach K\u00e4rnten 9121",
    "addr:housenumber":"14",
    "addr:postcode":"9121",
    "addr:street":"Greuth;Kaernten",
    "iso:country":"AT",
    "sg:address":"Greuth 14",
    "sg:city":"Tainach",
    "sg:orig_category":"Tankstellen",
    "sg:phone":"+43 4232 3628",
    "sg:postcode":"9121",
    "sg:province":"K\u00e4rnten",
    "wof:name":"Shell Austria GmbH",
    "wof:placetype":"venue"
},
  "geometry": {"coordinates":[14.5084590912,46.6561851501],"type":"Point"}
}