{
  "type": "Feature",
  "properties": {
    "iso:country":"AT",
    "sg:address":"Liesinger Pl 1",
    "sg:city":"Wien",
    "sg:orig_category":"Tabaktrafiken",
    "sg:phone":"+43 1 8694165",
    "sg:postcode":"1230",
    "sg:province":"Wien",
    "wof:name":"Haasl Rudolf",
    "wof:placetype":"venue"
},
  "geometry": {"coordinates":[16.2832775116,48.1353530884],"type":"Point"}
}