{
  "type": "Feature",
  "properties": {
    "addr:full":"Hermagor K\u00e4rnten 9620",
    "addr:postcode":"9620",
    "iso:country":"AT",
    "sg:city":"Hermagor",
    "sg:orig_category":"Medien, Zeitungen And Zeitschriften",
    "sg:postcode":"9620",
    "sg:province":"K\u00e4rnten",
    "sg:website":"http://www.spittaler-monat.at/reg-zeitung.html",
    "wof:name":"Spittaler Monatsmagazin - Alles aus einer Hand",
    "wof:placetype":"venue"
},
  "geometry": {"coordinates":[13.3710899353,46.6263885498],"type":"Point"}
}