{
  "type": "Feature",
  "properties": {
    "addr:full":"Nr 98 Kottes Nieder\u00f6sterreich 3623",
    "addr:postcode":"3623",
    "addr:street":"Nr;Kottes Niederoesterreich",
    "iso:country":"AT",
    "sg:address":"Nr 98",
    "sg:city":"Kottes",
    "sg:orig_category":"Friseure U Frisiersalons",
    "sg:phone":"+43 2873 7372",
    "sg:postcode":"3623",
    "sg:province":"Nieder\u00f6sterreich",
    "wof:name":"B\u00f6hm Lydia",
    "wof:placetype":"venue"
},
  "geometry": {"coordinates":[15.3025751114,48.4154853821],"type":"Point"}
}