{
  "type": "Feature",
  "properties": {
    "addr:full":"Oberdorfstr 12 Fuschl am See Salzburg 5330",
    "addr:housenumber":"12",
    "addr:postcode":"5330",
    "addr:street":"Oberdorfstr",
    "iso:country":"AT",
    "sg:address":"Oberdorfstr 12",
    "sg:city":"Fuschl am See",
    "sg:orig_category":"Tonstudios",
    "sg:phone":"+43 6226 883434",
    "sg:postcode":"5330",
    "sg:province":"Salzburg",
    "wof:name":"CREATIV ARENA AUDIODESIGN - SPEZIALAGENTUR F AUDIOPRODUKTIONEN ALLER ART",
    "wof:placetype":"venue"
},
  "geometry": {"coordinates":[13.3055944443,47.7967796326],"type":"Point"}
}