{
  "type": "Feature",
  "properties": {
    "addr:full":"Nr 58 Braunau am Inn Ober\u00f6sterreich 5280",
    "addr:postcode":"5280",
    "addr:street":"Nr 58",
    "iso:country":"AT",
    "sg:address":"Nr 58",
    "sg:city":"Braunau am Inn",
    "sg:orig_category":"Filmproduktionen",
    "sg:phone":"+43 7722 62247",
    "sg:postcode":"5280",
    "sg:province":"Ober\u00f6sterreich",
    "wof:name":"Videostudio Braunauer Fenster",
    "wof:placetype":"venue"
},
  "geometry": {"coordinates":[9.1401977539,48.0772857666],"type":"Point"}
}