{
  "type": "Feature",
  "properties": {
    "addr:full":"Marktpassage 3 Knittelfeld Steiermark 8720",
    "addr:housenumber":"3",
    "addr:postcode":"8720",
    "addr:street":"Marktpassage",
    "iso:country":"AT",
    "sg:address":"Marktpassage 3",
    "sg:city":"Knittelfeld",
    "sg:orig_category":"Tabaktrafiken",
    "sg:phone":"+43 4335 1273371",
    "sg:postcode":"8720",
    "sg:province":"Steiermark",
    "wof:name":"Knaus Dieter",
    "wof:placetype":"venue"
},
  "geometry": {"coordinates":[14.7966070175,47.2082443237],"type":"Point"}
}