{
  "type": "Feature",
  "properties": {
    "addr:full":"Kurbadstr 16 Wien Wien 1100",
    "addr:housenumber":"16",
    "addr:postcode":"1100",
    "addr:street":"Kurbadstr",
    "iso:country":"AT",
    "sg:address":"Kurbadstr 16",
    "sg:city":"Wien",
    "sg:orig_category":"Sportmedizin",
    "sg:phone":"+43 676 3308358",
    "sg:postcode":"1100",
    "sg:province":"Wien",
    "wof:name":"Wahler Guido Dr - allg beeid gerichtl zertif Sachverst\u00e4ndiger - Wellness Park Oberlaa",
    "wof:placetype":"venue"
},
  "geometry": {"coordinates":[16.4066123962,48.1416854858],"type":"Point"}
}