{
  "type": "Feature",
  "properties": {
    "addr:full":"Westbahnstr 30 St. Valentin Nieder\u00f6sterreich 4300",
    "addr:housenumber":"30",
    "addr:postcode":"4300",
    "addr:street":"Westbahnstr",
    "iso:country":"AT",
    "sg:address":"Westbahnstr 30",
    "sg:city":"St. Valentin",
    "sg:orig_category":"Fotoapparate U -Artikel / Einzelhandel",
    "sg:phone":"+43 4374 3552291",
    "sg:postcode":"4300",
    "sg:province":"Nieder\u00f6sterreich",
    "wof:name":"Hartlauer HandelsgesmbH",
    "wof:placetype":"venue"
},
  "geometry": {"coordinates":[14.5232305527,48.1783447266],"type":"Point"}
}