{
  "type": "Feature",
  "properties": {
    "iso:country":"AT",
    "sg:address":"Ziegelstr 3",
    "sg:city":"Andritz",
    "sg:orig_category":"Non-Classified Establishments",
    "sg:phone":"+43 4331 6684265",
    "sg:postcode":"8045",
    "sg:province":"Steiermark",
    "wof:name":"Haller Ursula",
    "wof:placetype":"venue"
},
  "geometry": {"coordinates":[15.4271564484,47.1012077332],"type":"Point"}
}