{
  "type": "Feature",
  "properties": {
    "addr:full":"Herzog-Ernst-G 20 Bruck an der Mur Steiermark 8600",
    "addr:housenumber":"20",
    "addr:postcode":"8600",
    "addr:street":"Herzog-Ernst-G",
    "iso:country":"AT",
    "sg:address":"Herzog-Ernst-G 20",
    "sg:city":"Bruck an der Mur",
    "sg:orig_category":"Fotografen",
    "sg:phone":"+43 3862 53512",
    "sg:postcode":"8600",
    "sg:province":"Steiermark",
    "wof:name":"Fotofrosch J\u00fcrgen Dieter Wesiak",
    "wof:placetype":"venue"
},
  "geometry": {"coordinates":[15.2717628479,47.4112510681],"type":"Point"}
}