{
  "type": "Feature",
  "properties": {
    "iso:country":"AT",
    "sg:address":"Salzburger Str 12",
    "sg:city":"Haid",
    "sg:orig_category":"Tankstellen",
    "sg:phone":"+43 7229 82917",
    "sg:postcode":"4053",
    "sg:province":"Ober\u00f6sterreich",
    "wof:name":"A1 Tankstelle",
    "wof:placetype":"venue"
},
  "geometry": {"coordinates":[14.249663353,48.2031822205],"type":"Point"}
}