{
  "type": "Feature",
  "properties": {
    "addr:full":"Gumpenberg 2 Haus Steiermark 8967",
    "addr:housenumber":"2",
    "addr:postcode":"8967",
    "addr:street":"Gumpenberg",
    "iso:country":"AT",
    "sg:address":"Gumpenberg 2",
    "sg:city":"Haus",
    "sg:orig_category":"Reisen, Tourismusinfo",
    "sg:phone":"+43 433686",
    "sg:postcode":"8967",
    "sg:province":"Steiermark",
    "sg:website":"http://www.knapplhof.at",
    "wof:name":"Gasthof Knapplhof - Familie H\u00f6flehner",
    "wof:placetype":"venue"
},
  "geometry": {"coordinates":[13.7913379669,47.4065933228],"type":"Point"}
}