{
  "type": "Feature",
  "properties": {
    "addr:full":"Nr 12 Arzl im Pitztal Tirol 6471",
    "addr:postcode":"6471",
    "addr:street":"Nr 12;Tirol",
    "iso:country":"AT",
    "sg:address":"Nr 12",
    "sg:city":"Arzl im Pitztal",
    "sg:orig_category":"Pensionen / Privatzimmer",
    "sg:phone":"+43 5412 63110",
    "sg:postcode":"6471",
    "sg:province":"Tirol",
    "wof:name":"Pension Sch\u00f6pf",
    "wof:placetype":"venue"
},
  "geometry": {"coordinates":[10.7617301941,47.2069854736],"type":"Point"}
}