{
  "type": "Feature",
  "properties": {
    "addr:full":"Braunhuberg 20 Wien Wien 1110",
    "addr:housenumber":"20",
    "addr:postcode":"1110",
    "addr:street":"Braunhuberg",
    "iso:country":"AT",
    "sg:address":"Braunhuberg 20",
    "sg:city":"Wien",
    "sg:orig_category":"Non-Classified Establishments",
    "sg:phone":"+43 1 749120411",
    "sg:postcode":"1110",
    "sg:province":"Wien",
    "wof:name":"Evangelische Pfarre - Simmering",
    "wof:placetype":"venue"
},
  "geometry": {"coordinates":[16.4143409729,48.1700630188],"type":"Point"}
}