{
  "type": "Feature",
  "properties": {
    "addr:full":"Technikerstr 13 Innsbruck Tirol 6020",
    "addr:housenumber":"13",
    "addr:postcode":"6020",
    "addr:street":"Technikerstr;Tirol",
    "iso:country":"AT",
    "sg:address":"Technikerstr 13",
    "sg:city":"Innsbruck",
    "sg:orig_category":"Institute",
    "sg:phone":"+43 4351 25076671",
    "sg:postcode":"6020",
    "sg:province":"Tirol",
    "wof:name":"Institut f Geotechnik u Tunnelbau d Universit\u00e4t Innsbruck",
    "wof:placetype":"venue"
},
  "geometry": {"coordinates":[11.345870018,47.2635688782],"type":"Point"}
}