{
  "type": "Feature",
  "properties": {
    "addr:full":"Dr.-A.-Wei\u00dfgatterer-Str 48/10 Schwaz Tirol 6130",
    "addr:housenumber":"48 / 10",
    "addr:postcode":"6130",
    "addr:street":"Dr.-A.-Weissgatterer-Str;Tirol",
    "iso:country":"AT",
    "sg:address":"Dr.-A.-Wei\u00dfgatterer-Str 48/10",
    "sg:city":"Schwaz",
    "sg:classifiers":[
        {
            "category":"Organizations",
            "subcategory":"Community Association",
            "type":"Services"
        }
    ],
    "sg:phone":"+43 4352 4263636",
    "sg:postcode":"6130",
    "sg:province":"Tirol",
    "sg:tags":[
        "relation",
        "public"
    ],
    "wof:name":"PR-Agentur Oberhollenzer",
    "wof:placetype":"venue"
},
  "geometry": {"coordinates":[11.7021903992,47.3387680054],"type":"Point"}
}