{
  "type": "Feature",
  "properties": {
    "iso:country":"AT",
    "sg:address":"Nr 100",
    "sg:city":"Puch",
    "sg:orig_category":"Gemeinden",
    "sg:phone":"+43 3177 22220",
    "sg:postcode":"8182",
    "sg:province":"Steiermark",
    "wof:name":"Gemeindeamt Puch bei Weiz",
    "wof:placetype":"venue"
},
  "geometry": {"coordinates":[15.72590065,47.2250213623],"type":"Point"}
}