{
  "type": "Feature",
  "properties": {
    "addr:full":"Nestroystr 2 Wiener Neustadt Nieder\u00f6sterreich 2700",
    "addr:housenumber":"2",
    "addr:postcode":"2700",
    "addr:street":"Nestroystr",
    "iso:country":"AT",
    "sg:address":"Nestroystr 2",
    "sg:city":"Wiener Neustadt",
    "sg:orig_category":"Tabaktrafiken",
    "sg:phone":"+43 2622 66347",
    "sg:postcode":"2700",
    "sg:province":"Nieder\u00f6sterreich",
    "wof:name":"Ployer Christine",
    "wof:placetype":"venue"
},
  "geometry": {"coordinates":[16.2590579987,47.8138122559],"type":"Point"}
}