{
  "type": "Feature",
  "properties": {
    "addr:full":"Nr 29 Altenmarkt Steiermark 8934",
    "addr:postcode":"8934",
    "addr:street":"Nr 29",
    "iso:country":"AT",
    "sg:address":"Nr 29",
    "sg:city":"Altenmarkt",
    "sg:orig_category":"Forstverwaltungen",
    "sg:phone":"+43 3631 40075",
    "sg:postcode":"8934",
    "sg:province":"Steiermark",
    "wof:name":"Paumann Roman - Nationalpark Forstverwaltung O\u00f6 Kalkalpen d \u00f6sterr Bundesforste AG",
    "wof:placetype":"venue"
},
  "geometry": {"coordinates":[14.6499977112,47.722366333],"type":"Point"}
}