{
  "type": "Feature",
  "properties": {
    "addr:full":"Breiter Weg 2a Feldkirch Vorarlberg 6800",
    "addr:housenumber":"2a",
    "addr:postcode":"6800",
    "addr:street":"Breiter Weg",
    "iso:country":"AT",
    "sg:address":"Breiter Weg 2a",
    "sg:city":"Feldkirch",
    "sg:orig_category":"Messe- U Ausstellungsbau U -Gestaltung",
    "sg:phone":"+43 5522 74847",
    "sg:postcode":"6800",
    "sg:province":"Vorarlberg",
    "wof:name":"CI Marketing - Presse Messe Events",
    "wof:placetype":"venue"
},
  "geometry": {"coordinates":[9.5610589981,47.2578392029],"type":"Point"}
}