{
  "type": "Feature",
  "properties": {
    "addr:full":"Gewerbepark 10 Aschbach Markt Nieder\u00f6sterreich 3361",
    "addr:housenumber":"10",
    "addr:postcode":"3361",
    "addr:street":"Gewerbepark",
    "iso:country":"AT",
    "sg:address":"Gewerbepark 10",
    "sg:city":"Aschbach Markt",
    "sg:orig_category":"CarpenterS Work Supraregional",
    "sg:phone":"+43 7476 777770",
    "sg:postcode":"3361",
    "sg:province":"Nieder\u00f6sterreich",
    "wof:name":"Pabst Holzverarbeitungsges.m.b.H.",
    "wof:placetype":"venue"
},
  "geometry": {"coordinates":[14.7393102646,48.0738182068],"type":"Point"}
}