{
  "type": "Feature",
  "properties": {
    "addr:full":"Feldg 2 St. Leonhard am Hornerwald Nieder\u00f6sterreich 3572",
    "addr:housenumber":"2",
    "addr:postcode":"3572",
    "addr:street":"Feldg",
    "iso:country":"AT",
    "sg:address":"Feldg 2",
    "sg:city":"St. Leonhard am Hornerwald",
    "sg:orig_category":"Autoreparatur",
    "sg:phone":"+43 4329 8724324",
    "sg:postcode":"3572",
    "sg:province":"Nieder\u00f6sterreich",
    "wof:name":"Leopold Franz",
    "wof:placetype":"venue"
},
  "geometry": {"coordinates":[15.5459947586,48.598236084],"type":"Point"}
}