{
  "type": "Feature",
  "properties": {
    "addr:full":"Kaiserstr 45 Wien Wien 1070",
    "addr:housenumber":"45",
    "addr:postcode":"1070",
    "addr:street":"Kaiserstr",
    "iso:country":"AT",
    "sg:address":"Kaiserstr 45",
    "sg:city":"Wien",
    "sg:classifiers":[
        {
            "category":"Travel",
            "subcategory":"Hotels & Motels",
            "type":"Entertainment"
        }
    ],
    "sg:phone":"+43 1 52386880",
    "sg:postcode":"1070",
    "sg:province":"Wien",
    "wof:name":"Hotel Pension Kaffeem\u00fchle",
    "wof:placetype":"venue"
},
  "geometry": {"coordinates":[16.340423584,48.2012481689],"type":"Point"}
}