{
  "type": "Feature",
  "properties": {
    "addr:full":"Stattegger Str 31B Andritz Steiermark 8045",
    "addr:housenumber":"31b",
    "addr:postcode":"8045",
    "addr:street":"Str",
    "iso:country":"AT",
    "sg:address":"Stattegger Str 31B",
    "sg:city":"Andritz",
    "sg:orig_category":"Medizintechnik",
    "sg:phone":"+43 4331 6698069",
    "sg:postcode":"8045",
    "sg:province":"Steiermark",
    "wof:name":"AMP Medizintechnik Handels GmbH",
    "wof:placetype":"venue"
},
  "geometry": {"coordinates":[15.4221591949,47.111114502],"type":"Point"}
}