{
  "type": "Feature",
  "properties": {
    "addr:full":"Otto-Probst-Strasse 22-24 Wien Wien 1100",
    "addr:postcode":"22-24;1100",
    "addr:street":"Otto-Probst-Strasse",
    "iso:country":"AT",
    "sg:address":"Otto-Probst-Strasse 22-24",
    "sg:city":"Wien",
    "sg:classifiers":[
        {
            "category":"Utilities",
            "subcategory":"Natural Gas",
            "type":"Services"
        }
    ],
    "sg:phone":"+43 1 6174480",
    "sg:postcode":"1100",
    "sg:province":"Wien",
    "sg:tags":[
        "lamp",
        "accent",
        "luminaires"
    ],
    "sg:website":"sylvania.at",
    "wof:name":"SLI Lichtsysteme Ges.m.b.H.",
    "wof:placetype":"venue"
},
  "geometry": {"coordinates":[16.3479537964,48.1545944214],"type":"Point"}
}