{
  "type": "Feature",
  "properties": {
    "iso:country":"AT",
    "sg:address":"Reitherspitzstr 410",
    "sg:city":"Seefeld in Tirol",
    "sg:orig_category":"Pensionen / Privatzimmer",
    "sg:phone":"+43 5212 25510",
    "sg:postcode":"6100",
    "sg:province":"Tirol",
    "wof:name":"Haus Harmeler Inh Elfriede Blumthaler",
    "wof:placetype":"venue"
},
  "geometry": {"coordinates":[11.1961679459,47.3264656067],"type":"Point"}
}