{
  "type": "Feature",
  "properties": {
    "addr:full":"Hauptplatz 1 Bruck an der Leitha Nieder\u00f6sterreich 2460",
    "addr:housenumber":"1",
    "addr:postcode":"2460",
    "addr:street":"Hauptplatz",
    "iso:country":"AT",
    "sg:address":"Hauptplatz 1",
    "sg:city":"Bruck an der Leitha",
    "sg:classifiers":[
        {
            "category":"Banks & Credit Unions",
            "subcategory":"Investment Brokerage",
            "type":"Services"
        }
    ],
    "sg:phone":"+43 2162 65063",
    "sg:postcode":"2460",
    "sg:province":"Nieder\u00f6sterreich",
    "sg:tags":[
        "case",
        "spectacle"
    ],
    "sg:website":"optik-bastel.at",
    "wof:name":"Optik Bastel Ges.m.b.H.",
    "wof:placetype":"venue"
},
  "geometry": {"coordinates":[16.7785186768,48.0247802734],"type":"Point"}
}