{
  "type": "Feature",
  "properties": {
    "addr:full":"Roseggerstr 74 Velden am W\u00f6rther See K\u00e4rnten 9220",
    "addr:housenumber":"74",
    "addr:postcode":"9220",
    "addr:street":"Roseggerstr;Kaernten",
    "iso:country":"AT",
    "sg:address":"Roseggerstr 74",
    "sg:city":"Velden am W\u00f6rther See",
    "sg:orig_category":"Lebensmittel / Einzelhandel",
    "sg:phone":"+43 4274 38299",
    "sg:postcode":"9220",
    "sg:province":"K\u00e4rnten",
    "wof:name":"SPAR \u00f6sterreichische Warenhandels AG",
    "wof:placetype":"venue"
},
  "geometry": {"coordinates":[14.0229578018,46.6019210815],"type":"Point"}
}