{
  "type": "Feature",
  "properties": {
    "addr:full":"Stadtpl 29 Steyr Ober\u00f6sterreich 4400",
    "addr:housenumber":"29",
    "addr:postcode":"4400",
    "addr:street":"Stadtpl;Oberoesterreich",
    "iso:country":"AT",
    "sg:address":"Stadtpl 29",
    "sg:city":"Steyr",
    "sg:orig_category":"Ingenieurkonsulenten / Zivilingenieure",
    "sg:phone":"+43 7252 42484",
    "sg:postcode":"4400",
    "sg:province":"Ober\u00f6sterreich",
    "wof:name":"Gunz Christof Dipl-Ing",
    "wof:placetype":"venue"
},
  "geometry": {"coordinates":[14.4192991257,48.0388450623],"type":"Point"}
}