{
  "type": "Feature",
  "properties": {
    "iso:country":"AT",
    "sg:address":"Raiffeisenstr 2",
    "sg:city":"Blindenmarkt",
    "sg:orig_category":"Gefahrguttransporte",
    "sg:phone":"+43 7473 25000",
    "sg:postcode":"3372",
    "sg:province":"Nieder\u00f6sterreich",
    "wof:name":"Kralowetz GesmbH",
    "wof:placetype":"venue"
},
  "geometry": {"coordinates":[14.9872093201,48.1288032532],"type":"Point"}
}