{
  "type": "Feature",
  "properties": {
    "addr:full":"Industriestr 17 Gro\u00df-Enzersdorf Nieder\u00f6sterreich 2301",
    "addr:housenumber":"17",
    "addr:postcode":"2301",
    "addr:street":"Industriestr;Niederoesterreich",
    "iso:country":"AT",
    "sg:address":"Industriestr 17",
    "sg:city":"Gro\u00df-Enzersdorf",
    "sg:orig_category":"Tischlereien",
    "sg:phone":"+43 2249 7443",
    "sg:postcode":"2301",
    "sg:province":"Nieder\u00f6sterreich",
    "wof:name":"Gruber Adolf GesmbH",
    "wof:placetype":"venue"
},
  "geometry": {"coordinates":[16.5734863281,48.191860199],"type":"Point"}
}