{
  "type": "Feature",
  "properties": {
    "addr:full":"Breitenfurter Str 236 Wien Wien 1230",
    "addr:housenumber":"236",
    "addr:postcode":"1230",
    "addr:street":"Str",
    "iso:country":"AT",
    "sg:address":"Breitenfurter Str 236",
    "sg:city":"Wien",
    "sg:orig_category":"Friseure U Frisiersalons",
    "sg:phone":"+43 4318 698708",
    "sg:postcode":"1230",
    "sg:province":"Wien",
    "wof:name":"Loth Regina",
    "wof:placetype":"venue"
},
  "geometry": {"coordinates":[16.2965431213,48.1469573975],"type":"Point"}
}