{
  "type": "Feature",
  "properties": {
    "addr:full":"M\u00fchlbachstr 31 Garsten Ober\u00f6sterreich 4451",
    "addr:housenumber":"31",
    "addr:postcode":"4451",
    "addr:street":"Muehlbachstr",
    "iso:country":"AT",
    "sg:address":"M\u00fchlbachstr 31",
    "sg:city":"Garsten",
    "sg:orig_category":"Volksschulen",
    "sg:phone":"+43 7252 46618",
    "sg:postcode":"4451",
    "sg:province":"Ober\u00f6sterreich",
    "wof:name":"Volksschule M\u00fchlbach",
    "wof:placetype":"venue"
},
  "geometry": {"coordinates":[14.4075651169,48.0228309631],"type":"Point"}
}