{
  "type": "Feature",
  "properties": {
    "addr:full":"Rosalieng 9 Mannersdorf an der Rabnitz Burgenland 7444",
    "addr:housenumber":"9",
    "addr:postcode":"7444",
    "addr:street":"Rosalieng",
    "iso:country":"AT",
    "sg:address":"Rosalieng 9",
    "sg:city":"Mannersdorf an der Rabnitz",
    "sg:orig_category":"Tischlereien",
    "sg:phone":"+43 2611 2258",
    "sg:postcode":"7444",
    "sg:province":"Burgenland",
    "wof:name":"Schlegl Josef",
    "wof:placetype":"venue"
},
  "geometry": {"coordinates":[16.5283622742,47.4267272949],"type":"Point"}
}