{
  "type": "Feature",
  "properties": {
    "addr:full":"Gonzagag 1/36 Wien Wien 1010",
    "addr:housenumber":"1 / 36",
    "addr:postcode":"1010",
    "addr:street":"Gonzagag",
    "iso:country":"AT",
    "sg:address":"Gonzagag 1/36",
    "sg:city":"Wien",
    "sg:orig_category":"Beteiligungen U Finanzierungen",
    "sg:phone":"+43 4312 2888080",
    "sg:postcode":"1010",
    "sg:province":"Wien",
    "wof:name":"AFA AG finance services",
    "wof:placetype":"venue"
},
  "geometry": {"coordinates":[16.3737068176,48.2129898071],"type":"Point"}
}