{
  "type": "Feature",
  "properties": {
    "addr:full":"Egger-Lienz-Str 1 Innsbruck Tirol 6020",
    "addr:housenumber":"1",
    "addr:postcode":"6020",
    "addr:street":"Egger-Lienz-Str;Tirol",
    "iso:country":"AT",
    "sg:address":"Egger-Lienz-Str 1",
    "sg:city":"Innsbruck",
    "sg:orig_category":"Speditionen",
    "sg:phone":"+43 4351 294033",
    "sg:postcode":"6020",
    "sg:province":"Tirol",
    "sg:website":"afs-austria.at",
    "wof:name":"AFS All Freight Systems SpeditonsgmbH & Co KG",
    "wof:placetype":"venue"
},
  "geometry": {"coordinates":[11.3889913559,47.2562942505],"type":"Point"}
}