{
  "type": "Feature",
  "properties": {
    "addr:full":"Sattledter Strasse 16 Steinerkirchen an der Traun Ober\u00f6sterreich 4652",
    "addr:housenumber":"16",
    "addr:postcode":"4652",
    "addr:street":"Sattledter Strasse",
    "iso:country":"AT",
    "sg:address":"Sattledter Strasse 16",
    "sg:city":"Steinerkirchen an der Traun",
    "sg:classifiers":[
        {
            "category":"Manufacturing",
            "subcategory":"Lumber",
            "type":"Manufacturing & Wholesale Goods"
        }
    ],
    "sg:phone":"+43 7241 2270",
    "sg:postcode":"4652",
    "sg:province":"Ober\u00f6sterreich",
    "sg:tags":[
        "chipping"
    ],
    "wof:name":"PLANA Kieserzeugungs- und Vertriebsges.m.b.H.",
    "wof:placetype":"venue"
},
  "geometry": {"coordinates":[13.934431076,48.0916862488],"type":"Point"}
}