{
  "type": "Feature",
  "properties": {
    "addr:full":"Johann Roithner-Str 92 Traun Ober\u00f6sterreich 4050",
    "addr:housenumber":"92",
    "addr:postcode":"4050",
    "iso:country":"AT",
    "sg:address":"Johann Roithner-Str 92",
    "sg:city":"Traun",
    "sg:orig_category":"Feuerwehren",
    "sg:phone":"+43 7229 61122",
    "sg:postcode":"4050",
    "sg:province":"Ober\u00f6sterreich",
    "wof:name":"Freiwillige Feuerwehr Traun",
    "wof:placetype":"venue"
},
  "geometry": {"coordinates":[14.2465696335,48.2243995667],"type":"Point"}
}