{
  "type": "Feature",
  "properties": {
    "addr:full":"Bahnhofstr 1 Schwanenstadt Ober\u00f6sterreich 4690",
    "addr:housenumber":"1",
    "addr:postcode":"4690",
    "addr:street":"Bahnhofstr",
    "iso:country":"AT",
    "sg:address":"Bahnhofstr 1",
    "sg:city":"Schwanenstadt",
    "sg:classifiers":[
        {
            "category":"Taxi",
            "type":"Transportation"
        }
    ],
    "sg:phone":"+43 4376 7375175",
    "sg:postcode":"4690",
    "sg:province":"Ober\u00f6sterreich",
    "sg:tags":[
        "personentransporte",
        "u"
    ],
    "wof:name":"Enser Herbert Auto-Funk Taxi GembH",
    "wof:placetype":"venue"
},
  "geometry": {"coordinates":[13.7717962265,48.0547409058],"type":"Point"}
}