{
  "type": "Feature",
  "properties": {
    "addr:full":"10.Oktober-Str 4 Hermagor K\u00e4rnten 9620",
    "addr:housenumber":"4",
    "addr:postcode":"9620",
    "addr:street":"10.Oktober-Str;Kaernten",
    "iso:country":"AT",
    "sg:address":"10.Oktober-Str 4",
    "sg:city":"Hermagor",
    "sg:orig_category":"Elektroinstallationsunternehmen",
    "sg:phone":"+43 4342 8220670",
    "sg:postcode":"9620",
    "sg:province":"K\u00e4rnten",
    "wof:name":"Elektro SCHULLER GmbH",
    "wof:placetype":"venue"
},
  "geometry": {"coordinates":[13.3708848953,46.6267433167],"type":"Point"}
}