{
  "type": "Feature",
  "properties": {
    "iso:country":"AT",
    "sg:address":"Hauptstr. 28",
    "sg:city":"Frauenkirchen",
    "sg:classifiers":[
        {
            "category":"Parking",
            "subcategory":"Lot",
            "type":"Transportation"
        }
    ],
    "sg:phone":"+43 4321 7222790",
    "sg:postcode":"7132",
    "sg:province":"Burgenland",
    "sg:tags":[
        "transport",
        "road"
    ],
    "wof:name":"ROBERT FRANK GESMBH",
    "wof:placetype":"venue"
},
  "geometry": {"coordinates":[16.9251003265,47.8372306824],"type":"Point"}
}