{
  "type": "Feature",
  "properties": {
    "addr:full":"Hohe-Munde-Str 772 Seefeld in Tirol Tirol 6100",
    "addr:housenumber":"772",
    "addr:postcode":"6100",
    "addr:street":"Seefeld;Tirol",
    "iso:country":"AT",
    "sg:address":"Hohe-Munde-Str 772",
    "sg:city":"Seefeld in Tirol",
    "sg:orig_category":"Appartements / Ferienwohnungen",
    "sg:phone":"+43 5212 2357",
    "sg:postcode":"6100",
    "sg:province":"Tirol",
    "wof:name":"Sackl Christine",
    "wof:placetype":"venue"
},
  "geometry": {"coordinates":[11.1889953613,47.3294143677],"type":"Point"}
}