{
  "type": "Feature",
  "properties": {
    "addr:full":"Hintere Lendstr 5 Mittersill Salzburg 5730",
    "addr:housenumber":"5",
    "addr:postcode":"5730",
    "addr:street":"Hintere Lendstr;Salzburg",
    "iso:country":"AT",
    "sg:address":"Hintere Lendstr 5",
    "sg:city":"Mittersill",
    "sg:orig_category":"Rauchfangkehrer",
    "sg:phone":"+43 6562 41870",
    "sg:postcode":"5730",
    "sg:province":"Salzburg",
    "wof:name":"Rainer Peter Christian",
    "wof:placetype":"venue"
},
  "geometry": {"coordinates":[12.4793243408,47.2823944092],"type":"Point"}
}