{
  "type": "Feature",
  "properties": {
    "addr:full":"Plattnerstr 12 Salzburg Salzburg 5020",
    "addr:housenumber":"12",
    "addr:postcode":"5020",
    "addr:street":"Plattnerstr;Salzburg",
    "iso:country":"AT",
    "sg:address":"Plattnerstr 12",
    "sg:city":"Salzburg",
    "sg:orig_category":"\u00c3\u201erzte / F Allgemeinmedizin",
    "sg:phone":"+43 662 454454",
    "sg:postcode":"5020",
    "sg:province":"Salzburg",
    "wof:name":"Biedrawa Rupert Dr",
    "wof:placetype":"venue"
},
  "geometry": {"coordinates":[13.0450162888,47.826915741],"type":"Point"}
}