{
  "type": "Feature",
  "properties": {
    "addr:full":"Resselstr 18/1 Innsbruck Tirol 6020",
    "addr:housenumber":"18 / 1",
    "addr:postcode":"6020",
    "addr:street":"Resselstr;Tirol",
    "iso:country":"AT",
    "sg:address":"Resselstr 18/1",
    "sg:city":"Innsbruck",
    "sg:classifiers":[
        {
            "category":"Military Area",
            "subcategory":"Army Base",
            "type":"Public Place"
        }
    ],
    "sg:phone":"+43 4351 2344266",
    "sg:postcode":"6020",
    "sg:province":"Tirol",
    "sg:tags":[
        "shiatsu"
    ],
    "wof:name":"Bewusstseinsquelle Therapie u Shiatsu GesmbH",
    "wof:placetype":"venue"
},
  "geometry": {"coordinates":[11.409989357,47.2610931396],"type":"Point"}
}