{
  "type": "Feature",
  "properties": {
    "addr:full":"Triester Strasse 222a Puntigam Steiermark 8055",
    "addr:housenumber":"222a",
    "addr:postcode":"8055",
    "addr:street":"Triester Strasse",
    "iso:country":"AT",
    "sg:address":"Triester Strasse 222a",
    "sg:city":"Puntigam",
    "sg:classifiers":[
        {
            "category":"Manufacturing",
            "subcategory":"Tobacco Products",
            "type":"Manufacturing & Wholesale Goods"
        }
    ],
    "sg:phone":"+43 316 294224",
    "sg:postcode":"8055",
    "sg:province":"Steiermark",
    "sg:tags":[
        "case",
        "cigarette",
        "cigar"
    ],
    "wof:name":"Walter Sabukoschek",
    "wof:placetype":"venue"
},
  "geometry": {"coordinates":[15.4294528961,47.040435791],"type":"Point"}
}