{
  "type": "Feature",
  "properties": {
    "addr:full":"Salzburger Str 29 Schwanenstadt Ober\u00f6sterreich 4690",
    "addr:housenumber":"29",
    "addr:postcode":"4690",
    "addr:street":"Salzburger Str",
    "iso:country":"AT",
    "sg:address":"Salzburger Str 29",
    "sg:city":"Schwanenstadt",
    "sg:orig_category":"Lebensmittel / Einzelhandel",
    "sg:phone":"+43 76734660",
    "sg:postcode":"4690",
    "sg:province":"Ober\u00f6sterreich",
    "wof:name":"Hofer KG",
    "wof:placetype":"venue"
},
  "geometry": {"coordinates":[13.7660083771,48.0501785278],"type":"Point"}
}