{
  "type": "Feature",
  "properties": {
    "addr:full":"Neutorstr. 10  Salzburg Salzburg 5020",
    "addr:housenumber":"10",
    "addr:postcode":"5020",
    "addr:street":"Neutorstr.;Salzburg",
    "iso:country":"AT",
    "sg:address":"Neutorstr. 10 ",
    "sg:city":"Salzburg",
    "sg:classifiers":[
        {
            "category":"Shopping",
            "subcategory":"Clothing, Apparel, & Fashions",
            "type":"Retail Goods"
        }
    ],
    "sg:phone":"+43 4366 2845735",
    "sg:postcode":"5020",
    "sg:province":"Salzburg",
    "sg:tags":[
        "clothes"
    ],
    "wof:name":"DANTENDORFER GMBH & CO. KG",
    "wof:placetype":"venue"
},
  "geometry": {"coordinates":[13.0368108749,47.797668457],"type":"Point"}
}