{
  "type": "Feature",
  "properties": {
    "iso:country":"AT",
    "sg:address":"Dr.-Hans-Lechner-Str 510",
    "sg:city":"Wals",
    "sg:orig_category":"Abwassertechnik",
    "sg:phone":"+43 4366 2855110",
    "sg:postcode":"5071",
    "sg:province":"Salzburg",
    "wof:name":"Dauser Industrieanlagen u Abwassertechnik GmbH",
    "wof:placetype":"venue"
},
  "geometry": {"coordinates":[12.9693145752,47.7897644043],"type":"Point"}
}