{
  "type": "Feature",
  "properties": {
    "addr:full":"Hochschartenstr 4 Buchkirchen Ober\u00f6sterreich 4611",
    "addr:housenumber":"4",
    "addr:postcode":"4611",
    "addr:street":"Hochschartenstr",
    "iso:country":"AT",
    "sg:address":"Hochschartenstr 4",
    "sg:city":"Buchkirchen",
    "sg:orig_category":"Unternehmensberatung",
    "sg:phone":"+43 7272 5266",
    "sg:postcode":"4611",
    "sg:province":"Ober\u00f6sterreich",
    "wof:name":"Gr\u00fcnwald Johannes KEG",
    "wof:placetype":"venue"
},
  "geometry": {"coordinates":[14.0269441605,48.2480888367],"type":"Point"}
}