{
  "type": "Feature",
  "properties": {
    "addr:full":"T\u00fcrkenstr 27 Wien Wien 1090",
    "addr:housenumber":"27",
    "addr:postcode":"1090",
    "addr:street":"Tuerkenstr",
    "iso:country":"AT",
    "sg:address":"T\u00fcrkenstr 27",
    "sg:city":"Wien",
    "sg:classifiers":[
        {
            "category":"Travel",
            "subcategory":"Hotels & Motels",
            "type":"Entertainment"
        }
    ],
    "sg:phone":"+43 1 31751110",
    "sg:postcode":"1090",
    "sg:province":"Wien",
    "wof:name":"Hotel Goldener B\u00e4r",
    "wof:placetype":"venue"
},
  "geometry": {"coordinates":[16.351474762,48.2234115601],"type":"Point"}
}