{
  "type": "Feature",
  "properties": {
    "addr:full":"Breitenfeldstr Mitterdorf im M\u00fcrztal Steiermark 8662",
    "addr:postcode":"8662",
    "iso:country":"AT",
    "sg:address":"Breitenfeldstr",
    "sg:city":"Mitterdorf im M\u00fcrztal",
    "sg:orig_category":"Alteisen U Altmetalle",
    "sg:phone":"+43 4338 5821910",
    "sg:postcode":"8662",
    "sg:province":"Steiermark",
    "wof:name":"Schaufler GesmbH",
    "wof:placetype":"venue"
},
  "geometry": {"coordinates":[15.5114984512,47.5356292725],"type":"Point"}
}