{
  "type": "Feature",
  "properties": {
    "iso:country":"AT",
    "sg:address":"Walserweg 12",
    "sg:city":"Bludenz",
    "sg:orig_category":"Rettungsdienste",
    "sg:phone":"+43 5552 69191",
    "sg:postcode":"6700",
    "sg:province":"Vorarlberg",
    "wof:name":"\u00f6sterr Bergrettungsdienst",
    "wof:placetype":"venue"
},
  "geometry": {"coordinates":[9.8201370239,47.1596336365],"type":"Point"}
}