{
  "type": "Feature",
  "properties": {
    "addr:full":"Walserweg 12 Bludenz Vorarlberg 6700",
    "addr:housenumber":"12",
    "addr:postcode":"6700",
    "addr:street":"Walserweg",
    "iso:country":"AT",
    "sg:address":"Walserweg 12",
    "sg:city":"Bludenz",
    "sg:orig_category":"Rettungsdienste",
    "sg:phone":"+43 5552 69191",
    "sg:postcode":"6700",
    "sg:province":"Vorarlberg",
    "wof:name":"\u00f6sterr Bergrettungsdienst",
    "wof:placetype":"venue"
},
  "geometry": {"coordinates":[9.8201370239,47.1596336365],"type":"Point"}
}