{
  "type": "Feature",
  "properties": {
    "addr:full":"Untere Hauptstr 11 Gols Burgenland 7122",
    "addr:housenumber":"11",
    "addr:postcode":"7122",
    "addr:street":"Untere Hauptstr",
    "iso:country":"AT",
    "sg:address":"Untere Hauptstr 11",
    "sg:city":"Gols",
    "sg:orig_category":"Tischlereien",
    "sg:phone":"+43 4321 732397",
    "sg:postcode":"7122",
    "sg:province":"Burgenland",
    "wof:name":"Moser Gerhard",
    "wof:placetype":"venue"
},
  "geometry": {"coordinates":[16.9093055725,47.898109436],"type":"Point"}
}