{
  "type": "Feature",
  "properties": {
    "iso:country":"AT",
    "sg:address":"Burgg 24",
    "sg:city":"Judenburg",
    "sg:orig_category":"Non-Classified Establishments",
    "sg:phone":"+43 3572 831670",
    "sg:postcode":"8750",
    "sg:province":"Steiermark",
    "wof:name":"Justizanstalt Leoben Au\u00dfenstelle Judenburg",
    "wof:placetype":"venue"
},
  "geometry": {"coordinates":[14.6585054398,47.1682167053],"type":"Point"}
}