{
  "type": "Feature",
  "properties": {
    "addr:full":"Burgg 24 Judenburg Steiermark 8750",
    "addr:housenumber":"24",
    "addr:postcode":"8750",
    "addr:street":"Burgg",
    "iso:country":"AT",
    "sg:address":"Burgg 24",
    "sg:city":"Judenburg",
    "sg:orig_category":"Non-Classified Establishments",
    "sg:phone":"+43 3572 831670",
    "sg:postcode":"8750",
    "sg:province":"Steiermark",
    "wof:name":"Justizanstalt Leoben Au\u00dfenstelle Judenburg",
    "wof:placetype":"venue"
},
  "geometry": {"coordinates":[14.6585054398,47.1682167053],"type":"Point"}
}