{
  "type": "Feature",
  "properties": {
    "addr:full":"Andromeda Tower - Donau - City - Strasse, 6 -  Wien Wien 1220",
    "addr:housenumber":"6",
    "addr:postcode":"1220",
    "addr:street":"City Strasse",
    "iso:country":"AT",
    "sg:address":"Andromeda Tower - Donau - City - Strasse, 6 - ",
    "sg:city":"Wien",
    "sg:classifiers":[
        {
            "category":"Professional",
            "subcategory":"Art Services",
            "type":"Services"
        }
    ],
    "sg:phone":"+43 1 260630",
    "sg:postcode":"1220",
    "sg:province":"Wien",
    "sg:tags":[
        "export-import"
    ],
    "sg:website":"http://www.embjapan.at/embjapan/",
    "wof:name":"Japan Embassy",
    "wof:placetype":"venue"
},
  "geometry": {"coordinates":[16.444606781,48.2497138977],"type":"Point"}
}