{
  "type": "Feature",
  "properties": {
    "addr:full":"Nr 113 Kirchberg an der Raab Steiermark 8324",
    "addr:postcode":"8324",
    "addr:street":"Nr 113",
    "iso:country":"AT",
    "sg:address":"Nr 113",
    "sg:city":"Kirchberg an der Raab",
    "sg:orig_category":"Installationsunternehmen",
    "sg:phone":"+43 3115 37350",
    "sg:postcode":"8324",
    "sg:province":"Steiermark",
    "wof:name":"Kubica GesmbH & Co KG",
    "wof:placetype":"venue"
},
  "geometry": {"coordinates":[15.7642307281,46.9871444702],"type":"Point"}
}