{
  "type": "Feature",
  "properties": {
    "addr:full":"Erlachpl 1 Wien Wien 1100",
    "addr:housenumber":"1",
    "addr:postcode":"1100",
    "addr:street":"Erlachpl",
    "iso:country":"AT",
    "sg:address":"Erlachpl 1",
    "sg:city":"Wien",
    "sg:orig_category":"Holdinggesellschaften",
    "sg:phone":"+43 4316 045658",
    "sg:postcode":"1100",
    "sg:province":"Wien",
    "wof:name":"AMH Akquisition- Managementcoaching u HoldinggesmbH",
    "wof:placetype":"venue"
},
  "geometry": {"coordinates":[16.3696079254,48.1784896851],"type":"Point"}
}