{
  "type": "Feature",
  "properties": {
    "addr:full":"Am Graben 11 Stetteldorf am Wagram Nieder\u00f6sterreich 3463",
    "addr:housenumber":"11",
    "addr:postcode":"3463",
    "addr:street":"Am Graben;Niederoesterreich",
    "iso:country":"AT",
    "sg:address":"Am Graben 11",
    "sg:city":"Stetteldorf am Wagram",
    "sg:orig_category":"Drogerien",
    "sg:phone":"+43 4322 7828308",
    "sg:postcode":"3463",
    "sg:province":"Nieder\u00f6sterreich",
    "wof:name":"dm drogerie markt GmbH",
    "wof:placetype":"venue"
},
  "geometry": {"coordinates":[16.0303096771,48.4050445557],"type":"Point"}
}