{
  "type": "Feature",
  "properties": {
    "addr:full":"Wilhelminenstrasse 19 Wien Wien 1160",
    "addr:housenumber":"19",
    "addr:postcode":"1160",
    "addr:street":"Wilhelminenstrasse",
    "iso:country":"AT",
    "sg:address":"Wilhelminenstrasse 19",
    "sg:city":"Wien",
    "sg:classifiers":[
        {
            "category":"Building & Trades",
            "subcategory":"Electrical",
            "type":"Services"
        }
    ],
    "sg:phone":"+43 1 4890999",
    "sg:postcode":"1160",
    "sg:province":"Wien",
    "sg:tags":[
        "work",
        "installation"
    ],
    "wof:name":"Elektro Jurina GmbH",
    "wof:placetype":"venue"
},
  "geometry": {"coordinates":[16.3192024231,48.2160797119],"type":"Point"}
}