{
  "type": "Feature",
  "properties": {
    "addr:full":"Schremser Str 6 Gm\u00fcnd Nieder\u00f6sterreich 3950",
    "addr:housenumber":"6",
    "addr:postcode":"3950",
    "addr:street":"Str;Niederoesterreich",
    "iso:country":"AT",
    "sg:address":"Schremser Str 6",
    "sg:city":"Gm\u00fcnd",
    "sg:orig_category":"Polizei U Gendarmerie",
    "sg:phone":"+43 2852 52506131",
    "sg:postcode":"3950",
    "sg:province":"Nieder\u00f6sterreich",
    "wof:name":"Polizei",
    "wof:placetype":"venue"
},
  "geometry": {"coordinates":[14.9859819412,48.7716522217],"type":"Point"}
}