{
  "type": "Feature",
  "properties": {
    "iso:country":"AT",
    "sg:address":"Kirchenpl 2",
    "sg:city":"Bad Hall",
    "sg:orig_category":"Papier- U Schreibwaren / Einzelhandel",
    "sg:phone":"+43 4372 5825050",
    "sg:postcode":"4540",
    "sg:province":"Ober\u00f6sterreich",
    "wof:name":"Mayrhofer Franz",
    "wof:placetype":"venue"
},
  "geometry": {"coordinates":[14.205696106,48.0355224609],"type":"Point"}
}