{
  "type": "Feature",
  "properties": {
    "addr:full":"Obere Landstr 31 Krems an der Donau Nieder\u00f6sterreich 3500",
    "addr:housenumber":"31",
    "addr:postcode":"3500",
    "addr:street":"Obere Landstr",
    "iso:country":"AT",
    "sg:address":"Obere Landstr 31",
    "sg:city":"Krems an der Donau",
    "sg:orig_category":"Friseure U Frisiersalons",
    "sg:phone":"+43 4327 32831271",
    "sg:postcode":"3500",
    "sg:province":"Nieder\u00f6sterreich",
    "wof:name":"Frisiersalon Scheichl",
    "wof:placetype":"venue"
},
  "geometry": {"coordinates":[15.597035408,48.4099731445],"type":"Point"}
}