{
  "type": "Feature",
  "properties": {
    "addr:full":"Bahnhofstr 4 Arbing Ober\u00f6sterreich 4341",
    "addr:housenumber":"4",
    "addr:postcode":"4341",
    "addr:street":"Bahnhofstr",
    "iso:country":"AT",
    "sg:address":"Bahnhofstr 4",
    "sg:city":"Arbing",
    "sg:orig_category":"Spielwaren U Spiele",
    "sg:phone":"+43 4372 696630",
    "sg:postcode":"4341",
    "sg:province":"Ober\u00f6sterreich",
    "wof:name":"Spielwaren Breiteneder",
    "wof:placetype":"venue"
},
  "geometry": {"coordinates":[14.7017450333,48.2264556885],"type":"Point"}
}