{
  "type": "Feature",
  "properties": {
    "addr:full":"Ehrenhausener Str 6 Klagenfurt K\u00e4rnten 9020",
    "addr:housenumber":"6",
    "addr:postcode":"9020",
    "addr:street":"Str;Kaernten",
    "iso:country":"AT",
    "sg:address":"Ehrenhausener Str 6",
    "sg:city":"Klagenfurt",
    "sg:orig_category":"Spenglereien",
    "sg:phone":"+43 4346 343439",
    "sg:postcode":"9020",
    "sg:province":"K\u00e4rnten",
    "wof:name":"Dorfer Johann Dachdeckungs- u Spenglereiunternehmen GesmbH",
    "wof:placetype":"venue"
},
  "geometry": {"coordinates":[14.3128461838,46.6513595581],"type":"Point"}
}