{
  "type": "Feature",
  "properties": {
    "addr:full":"Alte Hauptstr 19 Alkoven Ober\u00f6sterreich 4072",
    "addr:housenumber":"19",
    "addr:postcode":"4072",
    "addr:street":"Alte Hauptstr",
    "iso:country":"AT",
    "sg:address":"Alte Hauptstr 19",
    "sg:city":"Alkoven",
    "sg:orig_category":"Lebensmittel / Einzelhandel",
    "sg:phone":"+43 7274 6313",
    "sg:postcode":"4072",
    "sg:province":"Ober\u00f6sterreich",
    "wof:name":"Spar-Markt Inh Helga Schatzl-Huemer",
    "wof:placetype":"venue"
},
  "geometry": {"coordinates":[14.1067638397,48.2875404358],"type":"Point"}
}