{
  "type": "Feature",
  "properties": {
    "addr:full":"Sparkassenpl 3 Innsbruck Tirol 6020",
    "addr:housenumber":"3",
    "addr:postcode":"6020",
    "addr:street":"Sparkassenpl;Tirol",
    "iso:country":"AT",
    "sg:address":"Sparkassenpl 3",
    "sg:city":"Innsbruck",
    "sg:orig_category":"Trachtenbekleidung",
    "sg:phone":"+43 512 574791",
    "sg:postcode":"6020",
    "sg:province":"Tirol",
    "wof:name":"Hubertus Moden Steinbock",
    "wof:placetype":"venue"
},
  "geometry": {"coordinates":[11.39478302,47.2661781311],"type":"Point"}
}