{
  "type": "Feature",
  "properties": {
    "addr:full":"Feldbacher Str 13 St. Stefan im Rosental Steiermark 8083",
    "addr:housenumber":"13",
    "addr:postcode":"8083",
    "addr:street":"Str",
    "iso:country":"AT",
    "sg:address":"Feldbacher Str 13",
    "sg:city":"St. Stefan im Rosental",
    "sg:orig_category":"Tischlereien",
    "sg:phone":"+43 4331 168358",
    "sg:postcode":"8083",
    "sg:province":"Steiermark",
    "wof:name":"Ladenstein Franz KEG",
    "wof:placetype":"venue"
},
  "geometry": {"coordinates":[15.7116451263,46.9075126648],"type":"Point"}
}