{
  "type": "Feature",
  "properties": {
    "addr:full":"Tendlerg 6/5 Wien Wien 1090",
    "addr:housenumber":"6 / 5",
    "addr:postcode":"1090",
    "addr:street":"Tendlerg",
    "iso:country":"AT",
    "sg:address":"Tendlerg 6/5",
    "sg:city":"Wien",
    "sg:orig_category":"Psychotherapie",
    "sg:phone":"+43 1 7991390",
    "sg:postcode":"1090",
    "sg:province":"Wien",
    "wof:name":"Oberegelsbacher Dorothea Dr phil",
    "wof:placetype":"venue"
},
  "geometry": {"coordinates":[16.3520183563,48.2211532593],"type":"Point"}
}