{
  "type": "Feature",
  "properties": {
    "addr:full":"Neuer Markt 10-11 Wien Wien 1010",
    "addr:postcode":"10-11;1010",
    "addr:street":"Neuer Markt",
    "iso:country":"AT",
    "sg:address":"Neuer Markt 10-11",
    "sg:city":"Wien",
    "sg:orig_category":"Lebensmittel / Einzelhandel",
    "sg:phone":"+43 1 5138281",
    "sg:postcode":"1010",
    "sg:province":"Wien",
    "wof:name":"culinarium oesterreich Vertrieb GmbH",
    "wof:placetype":"venue"
},
  "geometry": {"coordinates":[16.3701248169,48.205821991],"type":"Point"}
}