{
  "type": "Feature",
  "properties": {
    "addr:full":"Wagram an der Donau 64 Orth an der Donau Nieder\u00f6sterreich 2304",
    "addr:housenumber":"64",
    "addr:postcode":"2304",
    "addr:street":"Wagram An Der Donau",
    "iso:country":"AT",
    "sg:address":"Wagram an der Donau 64",
    "sg:city":"Orth an der Donau",
    "sg:classifiers":[
        {
            "category":"Retail",
            "subcategory":"Storage",
            "type":"Services"
        }
    ],
    "sg:phone":"+43 2212 3102",
    "sg:postcode":"2304",
    "sg:province":"Nieder\u00f6sterreich",
    "sg:tags":[
        "archiving",
        "file"
    ],
    "sg:website":"heiss-transporte.at",
    "wof:name":"Fam. Karl Heiss Transport GmbH",
    "wof:placetype":"venue"
},
  "geometry": {"coordinates":[16.7011756897,48.1448936462],"type":"Point"}
}