{
  "type": "Feature",
  "properties": {
    "iso:country":"AT",
    "sg:address":"Krichbaumgasse 9a ",
    "sg:city":"Wien",
    "sg:classifiers":[
        {
            "category":"Government",
            "subcategory":"Fire Station",
            "type":"Public Place"
        }
    ],
    "sg:phone":"+43 1 8158570",
    "sg:postcode":"1120",
    "sg:province":"Wien",
    "sg:tags":[
        "supraregional",
        "plant",
        "installation",
        "heating"
    ],
    "wof:name":"Franz Zinkl",
    "wof:placetype":"venue"
},
  "geometry": {"coordinates":[16.3348255157,48.1791305542],"type":"Point"}
}