{
  "type": "Feature",
  "properties": {
    "addr:full":"Sandg 3 Ternitz Nieder\u00f6sterreich 2630",
    "addr:housenumber":"3",
    "addr:postcode":"2630",
    "addr:street":"Sandg",
    "iso:country":"AT",
    "sg:address":"Sandg 3",
    "sg:city":"Ternitz",
    "sg:orig_category":"Tischlereien",
    "sg:phone":"+43 2630 30715",
    "sg:postcode":"2630",
    "sg:province":"Nieder\u00f6sterreich",
    "wof:name":"Madler Matthias",
    "wof:placetype":"venue"
},
  "geometry": {"coordinates":[16.0209465027,47.7058067322],"type":"Point"}
}