{
  "type": "Feature",
  "properties": {
    "iso:country":"AT",
    "sg:address":"Kaiser-Josef-Pl 35/1",
    "sg:city":"Wels",
    "sg:orig_category":"Datenverarbeitung",
    "sg:phone":"+43 7242 78280",
    "sg:postcode":"4600",
    "sg:province":"Ober\u00f6sterreich",
    "wof:name":"Datakom Austria GmbH",
    "wof:placetype":"venue"
},
  "geometry": {"coordinates":[14.0214529037,48.1590080261],"type":"Point"}
}