{
  "type": "Feature",
  "properties": {
    "addr:full":"Linzer Str 25 Sieghartskirchen Nieder\u00f6sterreich 3443",
    "addr:housenumber":"25",
    "addr:postcode":"3443",
    "addr:street":"Linzer Str",
    "iso:country":"AT",
    "sg:address":"Linzer Str 25",
    "sg:city":"Sieghartskirchen",
    "sg:orig_category":"Autoreparatur",
    "sg:phone":"+43 2274 2190",
    "sg:postcode":"3443",
    "sg:province":"Nieder\u00f6sterreich",
    "wof:name":"Scharf's Garage",
    "wof:placetype":"venue"
},
  "geometry": {"coordinates":[16.0065345764,48.2568016052],"type":"Point"}
}