{
  "type": "Feature",
  "properties": {
    "addr:full":"Dorfbahnstr 41 Serfaus Tirol 6534",
    "addr:housenumber":"41",
    "addr:postcode":"6534",
    "addr:street":"Dorfbahnstr;Tirol",
    "iso:country":"AT",
    "sg:address":"Dorfbahnstr 41",
    "sg:city":"Serfaus",
    "sg:orig_category":"Drogerien",
    "sg:phone":"+43 5476 6386",
    "sg:postcode":"6534",
    "sg:province":"Tirol",
    "wof:name":"Drogerie Serfaus",
    "wof:placetype":"venue"
},
  "geometry": {"coordinates":[10.6054754257,47.0385627747],"type":"Point"}
}