{
  "type": "Feature",
  "properties": {
    "addr:full":"Himberger Strasse 66 Schwechat Nieder\u00f6sterreich 2320",
    "addr:housenumber":"66",
    "addr:postcode":"2320",
    "addr:street":"Himberger Strasse;Niederoesterreich",
    "iso:country":"AT",
    "sg:address":"Himberger Strasse 66",
    "sg:city":"Schwechat",
    "sg:classifiers":[
        {
            "category":"Manufacturing",
            "subcategory":"Metals",
            "type":"Manufacturing & Wholesale Goods"
        }
    ],
    "sg:phone":"+43 1 70764720",
    "sg:postcode":"2320",
    "sg:province":"Nieder\u00f6sterreich",
    "sg:tags":[
        "aluminium"
    ],
    "wof:name":"Helmut Stein Ges.m.b.H.",
    "wof:placetype":"venue"
},
  "geometry": {"coordinates":[16.4718017578,48.1247291565],"type":"Point"}
}