{
  "type": "Feature",
  "properties": {
    "iso:country":"AT",
    "sg:address":"Wiener Str 247",
    "sg:city":"Linz",
    "sg:classifiers":[
        {
            "category":"Utilities",
            "subcategory":"Recycling",
            "type":"Services"
        }
    ],
    "sg:phone":"+43 732 3498160",
    "sg:postcode":"4020",
    "sg:province":"Ober\u00f6sterreich",
    "wof:name":"Basar HandelsgesmbH",
    "wof:placetype":"venue"
},
  "geometry": {"coordinates":[14.3146791458,48.2723655701],"type":"Point"}
}