{
  "type": "Feature",
  "properties": {
    "addr:full":"Glockeng 6 Salzburg Salzburg 5020",
    "addr:housenumber":"6",
    "addr:postcode":"5020",
    "addr:street":"Glockeng;Salzburg",
    "iso:country":"AT",
    "sg:address":"Glockeng 6",
    "sg:city":"Salzburg",
    "sg:orig_category":"Beratungsstellen",
    "sg:phone":"+43 662 882929",
    "sg:postcode":"5020",
    "sg:province":"Salzburg",
    "wof:name":"Initiative 40 Beratungsstelle f \u00e4ltere Arbeitsuchende",
    "wof:placetype":"venue"
},
  "geometry": {"coordinates":[13.0517454147,47.8048667908],"type":"Point"}
}