{
  "type": "Feature",
  "properties": {
    "iso:country":"AT",
    "sg:address":"Jagdweg 6",
    "sg:city":"Mils",
    "sg:classifiers":[
        {
            "category":"Utilities",
            "subcategory":"Water",
            "type":"Services"
        }
    ],
    "sg:phone":"+43 5223 53751",
    "sg:postcode":"6068",
    "sg:province":"Tirol",
    "sg:tags":[
        "waste",
        "wetland",
        "treatment",
        "artificial"
    ],
    "sg:website":"p-i-m.com",
    "wof:name":"PIM Patente Innovationen Marken Ges.m.b.H.",
    "wof:placetype":"venue"
},
  "geometry": {"coordinates":[-99.4334869385,42.926410675],"type":"Point"}
}