{
  "type": "Feature",
  "properties": {
    "iso:country":"AT",
    "sg:address":"Heiterestr 9",
    "sg:city":"Lustenau",
    "sg:orig_category":"Werbeagenturen",
    "sg:phone":"+43 5577 88188",
    "sg:postcode":"6890",
    "sg:province":"Vorarlberg",
    "wof:name":"Media Agentur K+H",
    "wof:placetype":"venue"
},
  "geometry": {"coordinates":[9.6678409576,47.414100647],"type":"Point"}
}