{
  "type": "Feature",
  "properties": {
    "iso:country":"AT",
    "sg:address":"R\u00f6hrbrunnstr 17",
    "sg:city":"Langenlois",
    "sg:orig_category":"Tonstudios",
    "sg:phone":"+43 2734 8090",
    "sg:postcode":"3550",
    "sg:province":"Nieder\u00f6sterreich",
    "wof:name":"NO A STUDIO Musikproduktion - Treiber & Plass OEG",
    "wof:placetype":"venue"
},
  "geometry": {"coordinates":[15.6682252884,48.4724693298],"type":"Point"}
}