{
  "type": "Feature",
  "properties": {
    "addr:full":"Herzog-Ernst-G 28 Bruck an der Mur Steiermark 8600",
    "addr:housenumber":"28",
    "addr:postcode":"8600",
    "addr:street":"Herzog-Ernst-G",
    "iso:country":"AT",
    "sg:address":"Herzog-Ernst-G 28",
    "sg:city":"Bruck an der Mur",
    "sg:orig_category":"Immobilienverwaltungen",
    "sg:phone":"+43 4366 45023920",
    "sg:postcode":"8600",
    "sg:province":"Steiermark",
    "wof:name":"RP Immobilien Percht Roswitha",
    "wof:placetype":"venue"
},
  "geometry": {"coordinates":[15.2726697922,47.4114494324],"type":"Point"}
}