{
  "type": "Feature",
  "properties": {
    "addr:full":"Seigweg 343 Saalbach Salzburg 5753",
    "addr:housenumber":"343",
    "addr:postcode":"5753",
    "addr:street":"Saalbach Salzburg",
    "iso:country":"AT",
    "sg:address":"Seigweg 343",
    "sg:city":"Saalbach",
    "sg:classifiers":[
        {
            "category":"Taxi",
            "type":"Transportation"
        }
    ],
    "sg:phone":"+43 6541 6620",
    "sg:postcode":"5753",
    "sg:province":"Salzburg",
    "sg:tags":[
        "personentransporte",
        "u"
    ],
    "wof:name":"TAXI 6620 GmbH & Co KEG",
    "wof:placetype":"venue"
},
  "geometry": {"coordinates":[12.6367301941,47.3899307251],"type":"Point"}
}