{
  "type": "Feature",
  "properties": {
    "addr:full":"Streberg 23 Andau Burgenland 7163",
    "addr:housenumber":"23",
    "addr:postcode":"7163",
    "addr:street":"Streberg",
    "iso:country":"AT",
    "sg:address":"Streberg 23",
    "sg:city":"Andau",
    "sg:orig_category":"Holzbau",
    "sg:phone":"+43 2176 36122",
    "sg:postcode":"7163",
    "sg:province":"Burgenland",
    "wof:name":"Holzbau Rommer GesmbH",
    "wof:placetype":"venue"
},
  "geometry": {"coordinates":[17.0281448364,47.7804412842],"type":"Point"}
}