{
  "type": "Feature",
  "properties": {
    "iso:country":"AT",
    "sg:address":"Streberg 23",
    "sg:city":"Andau",
    "sg:orig_category":"Holzbau",
    "sg:phone":"+43 2176 36122",
    "sg:postcode":"7163",
    "sg:province":"Burgenland",
    "wof:name":"Holzbau Rommer GesmbH",
    "wof:placetype":"venue"
},
  "geometry": {"coordinates":[17.0281448364,47.7804412842],"type":"Point"}
}