{
  "type": "Feature",
  "properties": {
    "iso:country":"AT",
    "sg:address":"Nr 53",
    "sg:city":"Wimpassing im Schwarzatale",
    "sg:orig_category":"Hafnereien",
    "sg:phone":"+43 2630 3842730",
    "sg:postcode":"2632",
    "sg:province":"Nieder\u00f6sterreich",
    "wof:name":"Ganser Josef",
    "wof:placetype":"venue"
},
  "geometry": {"coordinates":[166.9221496582,-0.5282999873],"type":"Point"}
}