{
  "type": "Feature",
  "properties": {
    "addr:full":"Diepoldpl 12 Wien Wien 1170",
    "addr:housenumber":"12",
    "addr:postcode":"1170",
    "addr:street":"Diepoldpl",
    "iso:country":"AT",
    "sg:address":"Diepoldpl 12",
    "sg:city":"Wien",
    "sg:classifiers":[
        {
            "category":"Restaurant",
            "type":"Food & Drink"
        }
    ],
    "sg:phone":"+43 1 4840955",
    "sg:postcode":"1170",
    "sg:province":"Wien",
    "sg:tags":[
        "pizzeria"
    ],
    "wof:name":"Pizzeria La-Ventura",
    "wof:placetype":"venue"
},
  "geometry": {"coordinates":[16.3309955597,48.2230567932],"type":"Point"}
}