{
  "type": "Feature",
  "properties": {
    "iso:country":"AT",
    "sg:address":"Innerleiten 6",
    "sg:city":"Ampflwang im Hausruckwald",
    "sg:orig_category":"Metallbau",
    "sg:phone":"+43 4376 7525560",
    "sg:postcode":"4843",
    "sg:province":"Ober\u00f6sterreich",
    "wof:name":"Fellinger Metallbau GmbH",
    "wof:placetype":"venue"
},
  "geometry": {"coordinates":[13.5434246063,48.074546814],"type":"Point"}
}