{
  "type": "Feature",
  "properties": {
    "addr:full":"Gaisberg 5 Aigen Salzburg 5026",
    "addr:housenumber":"5",
    "addr:postcode":"5026",
    "addr:street":"Gaisberg;Salzburg",
    "iso:country":"AT",
    "sg:address":"Gaisberg 5",
    "sg:city":"Aigen",
    "sg:orig_category":"Schlossereien",
    "sg:phone":"+43 662 6498840",
    "sg:postcode":"5026",
    "sg:province":"Salzburg",
    "wof:name":"MTE Metalltechnik Elsenhuber GmbH",
    "wof:placetype":"venue"
},
  "geometry": {"coordinates":[13.101231575,47.7912750244],"type":"Point"}
}