{
  "type": "Feature",
  "properties": {
    "addr:full":"Nr 42 Gf\u00f6hl Nieder\u00f6sterreich 3542",
    "addr:postcode":"3542",
    "addr:street":"Nr 42 Gfoehl",
    "iso:country":"AT",
    "sg:address":"Nr 42",
    "sg:city":"Gf\u00f6hl",
    "sg:orig_category":"Autohandel",
    "sg:phone":"+43 4327 1620143",
    "sg:postcode":"3542",
    "sg:province":"Nieder\u00f6sterreich",
    "wof:name":"Ecker & Sinhuber OEG",
    "wof:placetype":"venue"
},
  "geometry": {"coordinates":[15.4903745651,48.5168418884],"type":"Point"}
}