{
  "type": "Feature",
  "properties": {
    "addr:full":"Linzer Str 311 Wien Wien 1140",
    "addr:housenumber":"311",
    "addr:postcode":"1140",
    "addr:street":"Linzer Str",
    "iso:country":"AT",
    "sg:address":"Linzer Str 311",
    "sg:city":"Wien",
    "sg:orig_category":"Juwelen, Gold- U Silberwaren / Einzelhandel",
    "sg:phone":"+43 4319 148314",
    "sg:postcode":"1140",
    "sg:province":"Wien",
    "wof:name":"Fiala Peter",
    "wof:placetype":"venue"
},
  "geometry": {"coordinates":[16.2706985474,48.1987991333],"type":"Point"}
}