{
  "type": "Feature",
  "properties": {
    "addr:full":"Ortenburger Str 4 Mattighofen Ober\u00f6sterreich 5230",
    "addr:housenumber":"4",
    "addr:postcode":"5230",
    "addr:street":"Str",
    "iso:country":"AT",
    "sg:address":"Ortenburger Str 4",
    "sg:city":"Mattighofen",
    "sg:orig_category":"Unternehmensberatung",
    "sg:phone":"+43 7742 6102",
    "sg:postcode":"5230",
    "sg:province":"Ober\u00f6sterreich",
    "wof:name":"Hinterdorfer Anton",
    "wof:placetype":"venue"
},
  "geometry": {"coordinates":[13.1499357224,48.1096611023],"type":"Point"}
}