{
  "type": "Feature",
  "properties": {
    "iso:country":"AT",
    "sg:address":"Amraser Str 42",
    "sg:city":"Innsbruck",
    "sg:orig_category":"Physiotherapie",
    "sg:phone":"+43 512 348221",
    "sg:postcode":"6020",
    "sg:province":"Tirol",
    "wof:name":"Habermann Hajnalka Dipl-PT",
    "wof:placetype":"venue"
},
  "geometry": {"coordinates":[11.407081604,47.263923645],"type":"Point"}
}