{
  "type": "Feature",
  "properties": {
    "addr:full":"Bundesstrasse 45 Unterrabnitz Burgenland 7371",
    "addr:housenumber":"45",
    "addr:postcode":"7371",
    "addr:street":"Bundesstrasse",
    "iso:country":"AT",
    "sg:address":"Bundesstrasse 45",
    "sg:city":"Unterrabnitz",
    "sg:classifiers":[
        {
            "category":"Food & Beverages",
            "subcategory":"Groceries & Convenience Stores",
            "type":"Retail Goods"
        }
    ],
    "sg:phone":"+43 2616 8740",
    "sg:postcode":"7371",
    "sg:province":"Burgenland",
    "sg:tags":[
        "frozen",
        "goods",
        "baked"
    ],
    "wof:name":"Backstube Hauser OEG",
    "wof:placetype":"venue"
},
  "geometry": {"coordinates":[16.4189662933,47.4479675293],"type":"Point"}
}