{
  "type": "Feature",
  "properties": {
    "addr:full":"Favoritenstr 149 Wien Wien 1100",
    "addr:housenumber":"149",
    "addr:postcode":"1100",
    "iso:country":"AT",
    "sg:address":"Favoritenstr 149",
    "sg:city":"Wien",
    "sg:orig_category":"Installationsunternehmen",
    "sg:phone":"+43 1 6044681",
    "sg:postcode":"1100",
    "sg:province":"Wien",
    "wof:name":"Mikyska Franz",
    "wof:placetype":"venue"
},
  "geometry": {"coordinates":[16.3803062439,48.1700057983],"type":"Point"}
}