{
  "type": "Feature",
  "properties": {
    "addr:full":"Omesberg 175 Lech Vorarlberg 6764",
    "addr:housenumber":"175",
    "addr:postcode":"6764",
    "addr:street":"Omesberg",
    "iso:country":"AT",
    "sg:address":"Omesberg 175",
    "sg:city":"Lech",
    "sg:orig_category":"Appartements / Ferienwohnungen",
    "sg:phone":"+43 4355 832729",
    "sg:postcode":"6764",
    "sg:province":"Vorarlberg",
    "wof:name":"Appartement Haus Margarethe",
    "wof:placetype":"venue"
},
  "geometry": {"coordinates":[10.1405553818,47.2066993713],"type":"Point"}
}