{
  "type": "Feature",
  "properties": {
    "addr:full":"Krenglbacher Str 7 Krenglbach Ober\u00f6sterreich 4631",
    "addr:housenumber":"7",
    "addr:postcode":"4631",
    "addr:street":"Str",
    "iso:country":"AT",
    "sg:address":"Krenglbacher Str 7",
    "sg:city":"Krenglbach",
    "sg:orig_category":"Polizei U Gendarmerie",
    "sg:phone":"+43 4359 1334182",
    "sg:postcode":"4631",
    "sg:province":"Ober\u00f6sterreich",
    "wof:name":"Gendarmerie",
    "wof:placetype":"venue"
},
  "geometry": {"coordinates":[13.9554862976,48.2051467896],"type":"Point"}
}