{
  "type": "Feature",
  "properties": {
    "iso:country":"AT",
    "sg:address":"Sparkassegasse 11-13 ",
    "sg:city":"Hollabrunn",
    "sg:classifiers":[
        {
            "category":"Shopping",
            "subcategory":"Computers & Home Electronics",
            "type":"Retail Goods"
        }
    ],
    "sg:phone":"+43 4329 5224400",
    "sg:postcode":"2020",
    "sg:province":"Nieder\u00f6sterreich",
    "sg:tags":[
        "electronic",
        "electrical",
        "equipment"
    ],
    "wof:name":"ING. ALFRED STENZL GES.MBH",
    "wof:placetype":"venue"
},
  "geometry": {"coordinates":[16.0794715881,48.5640602112],"type":"Point"}
}