{
  "type": "Feature",
  "properties": {
    "iso:country":"AT",
    "sg:address":"Luegerstrasse 27",
    "sg:city":"Klagenfurt",
    "sg:classifiers":[
        {
            "category":"Shopping",
            "subcategory":"Bridal",
            "type":"Retail Goods"
        }
    ],
    "sg:phone":"+43 463 22600",
    "sg:postcode":"9020",
    "sg:province":"K\u00e4rnten",
    "sg:tags":[
        "wreath",
        "communion"
    ],
    "sg:website":"brommer.at",
    "wof:name":"Blumen Brommer GesmbH & Co KG",
    "wof:placetype":"venue"
},
  "geometry": {"coordinates":[14.2837543488,46.6176147461],"type":"Point"}
}