{
  "type": "Feature",
  "properties": {
    "addr:full":"Floridsdorfer Hptstr 41 Wien Wien 1210",
    "addr:housenumber":"41",
    "addr:postcode":"1210",
    "iso:country":"AT",
    "sg:address":"Floridsdorfer Hptstr 41",
    "sg:city":"Wien",
    "sg:orig_category":"Personalbereitstellung",
    "sg:phone":"+43 1 2700127",
    "sg:postcode":"1210",
    "sg:province":"Wien",
    "wof:name":"HPS Higer Personalservice",
    "wof:placetype":"venue"
},
  "geometry": {"coordinates":[16.396604538,48.2566642761],"type":"Point"}
}