{
  "type": "Feature",
  "properties": {
    "iso:country":"AT",
    "sg:address":"Stadtpl 24",
    "sg:city":"Schwanenstadt",
    "sg:orig_category":"Bauunternehmen",
    "sg:phone":"+43 767324760",
    "sg:postcode":"4690",
    "sg:province":"Ober\u00f6sterreich",
    "wof:name":"Wagner Franz Ing GmbH & Co KG",
    "wof:placetype":"venue"
},
  "geometry": {"coordinates":[13.7755432129,48.0556640625],"type":"Point"}
}