{
  "type": "Feature",
  "properties": {
    "addr:full":"Margaretenstr 67 Wien Wien 1050",
    "addr:housenumber":"67",
    "addr:postcode":"1050",
    "addr:street":"Margaretenstr",
    "iso:country":"AT",
    "sg:address":"Margaretenstr 67",
    "sg:city":"Wien",
    "sg:orig_category":"Lebensmittel / Einzelhandel",
    "sg:phone":"+43 1 9610513",
    "sg:postcode":"1050",
    "sg:province":"Wien",
    "wof:name":"Billa AG",
    "wof:placetype":"venue"
},
  "geometry": {"coordinates":[16.3601913452,48.192237854],"type":"Point"}
}