{
  "type": "Feature",
  "properties": {
    "addr:full":"Nr 124 Loibichl Ober\u00f6sterreich 5311",
    "addr:housenumber":"5311",
    "addr:street":"Nr 124 Loibichl Oberoesterreich",
    "iso:country":"AT",
    "sg:address":"Nr 124",
    "sg:city":"Loibichl",
    "sg:orig_category":"Appartements / Ferienwohnungen",
    "sg:phone":"+43 4362 324983",
    "sg:postcode":"5311",
    "sg:province":"Ober\u00f6sterreich",
    "wof:name":"Landhaus Edtmayer",
    "wof:placetype":"venue"
},
  "geometry": {"coordinates":[13.4032068253,47.8300895691],"type":"Point"}
}