{
  "type": "Feature",
  "properties": {
    "addr:full":"Klagenfurter Str 21 St. Veit an der Glan K\u00e4rnten 9300",
    "addr:housenumber":"21",
    "addr:postcode":"9300",
    "addr:street":"Str;Kaernten",
    "iso:country":"AT",
    "sg:address":"Klagenfurter Str 21",
    "sg:city":"St. Veit an der Glan",
    "sg:orig_category":"Salze",
    "sg:phone":"+43 4342 1233533",
    "sg:postcode":"9300",
    "sg:province":"K\u00e4rnten",
    "wof:name":"karpasa Vertriebs GmbH",
    "wof:placetype":"venue"
},
  "geometry": {"coordinates":[14.3601036072,46.7664756775],"type":"Point"}
}