{
  "type": "Feature",
  "properties": {
    "iso:country":"AT",
    "sg:address":"Triesterstrasse 44",
    "sg:city":"Wimpassing im Schwarzatale",
    "sg:classifiers":[
        {
            "category":"Building & Trades",
            "subcategory":"Electrical",
            "type":"Services"
        }
    ],
    "sg:phone":"+43 2630 36260",
    "sg:postcode":"2632",
    "sg:province":"Nieder\u00f6sterreich",
    "sg:tags":[
        "installation"
    ],
    "sg:website":"atiscompany.com",
    "wof:name":"Atis Elektroinstallationen GesmbH",
    "wof:placetype":"venue"
},
  "geometry": {"coordinates":[16.0058555603,47.6837768555],"type":"Point"}
}