{
  "type": "Feature",
  "properties": {
    "iso:country":"AT",
    "sg:address":"Schulg 43a",
    "sg:city":"Wien",
    "sg:orig_category":"Fernsehservice",
    "sg:phone":"+43 1 4082645",
    "sg:postcode":"1180",
    "sg:province":"Wien",
    "wof:name":"Bruckner Walter",
    "wof:placetype":"venue"
},
  "geometry": {"coordinates":[16.3412036896,48.2250518799],"type":"Point"}
}