{
  "type": "Feature",
  "properties": {
    "iso:country":"AT",
    "sg:address":"Hauptstr 21-23",
    "sg:city":"Oberpullendorf",
    "sg:orig_category":"Babyausstattung",
    "sg:phone":"+43 2612 42131",
    "sg:postcode":"7350",
    "sg:province":"Burgenland",
    "wof:name":"Fritz Norbert Ing",
    "wof:placetype":"venue"
},
  "geometry": {"coordinates":[16.5058250427,47.5006256104],"type":"Point"}
}