{
  "type": "Feature",
  "properties": {
    "addr:full":"Steinerkirchen an der Traun Ober\u00f6sterreich 4652",
    "addr:postcode":"4652",
    "iso:country":"AT",
    "sg:city":"Steinerkirchen an der Traun",
    "sg:orig_category":"Feuerwehren",
    "sg:phone":"+43 7241 2445",
    "sg:postcode":"4652",
    "sg:province":"Ober\u00f6sterreich",
    "wof:name":"Freiwillige Feuerwehr Fischlham",
    "wof:placetype":"venue"
},
  "geometry": {"coordinates":[13.9492607117,48.0879707336],"type":"Point"}
}