{
  "type": "Feature",
  "properties": {
    "addr:full":"Lothringerpl 1 Hollabrunn Nieder\u00f6sterreich 2020",
    "addr:housenumber":"1",
    "addr:postcode":"2020",
    "addr:street":"Lothringerpl",
    "iso:country":"AT",
    "sg:address":"Lothringerpl 1",
    "sg:city":"Hollabrunn",
    "sg:orig_category":"Bandagen U Bandagisten",
    "sg:phone":"+43 2952 30006",
    "sg:postcode":"2020",
    "sg:province":"Nieder\u00f6sterreich",
    "wof:name":"Sanit\u00e4tshaus - Orthop\u00e4disches Institut Novotny & Pistora GmbH",
    "wof:placetype":"venue"
},
  "geometry": {"coordinates":[16.0804595947,48.5664901733],"type":"Point"}
}