{
  "type": "Feature",
  "properties": {
    "addr:full":"Wiesingerstr 3/16 Bad Ischl Ober\u00f6sterreich 4820",
    "addr:housenumber":"3 / 16",
    "addr:postcode":"4820",
    "addr:street":"Wiesingerstr",
    "iso:country":"AT",
    "sg:address":"Wiesingerstr 3/16",
    "sg:city":"Bad Ischl",
    "sg:orig_category":"Brandschutz",
    "sg:phone":"+43 6132 26036",
    "sg:postcode":"4820",
    "sg:province":"Ober\u00f6sterreich",
    "wof:name":"BSS Brandschutzisolierungen GesmbH",
    "wof:placetype":"venue"
},
  "geometry": {"coordinates":[13.6194248199,47.7122612],"type":"Point"}
}