{
  "type": "Feature",
  "properties": {
    "addr:full":"Unterfresen 55 Schwanberg Steiermark 8541",
    "addr:housenumber":"55",
    "addr:postcode":"8541",
    "addr:street":"Unterfresen",
    "iso:country":"AT",
    "sg:address":"Unterfresen 55",
    "sg:city":"Schwanberg",
    "sg:orig_category":"Zimmereien",
    "sg:phone":"+43 3468 317",
    "sg:postcode":"8541",
    "sg:province":"Steiermark",
    "wof:name":"Zimmerei Krasser GmbH",
    "wof:placetype":"venue"
},
  "geometry": {"coordinates":[15.181145668,46.7477760315],"type":"Point"}
}