{
  "type": "Feature",
  "properties": {
    "addr:full":"Musterhofg 2 Brunn am Gebirge Nieder\u00f6sterreich 2345",
    "addr:housenumber":"2",
    "addr:postcode":"2345",
    "addr:street":"Musterhofg",
    "iso:country":"AT",
    "sg:address":"Musterhofg 2",
    "sg:city":"Brunn am Gebirge",
    "sg:orig_category":"Fiaker",
    "sg:phone":"+43 2236 31752",
    "sg:postcode":"2345",
    "sg:province":"Nieder\u00f6sterreich",
    "wof:name":"Fischer Ludwig",
    "wof:placetype":"venue"
},
  "geometry": {"coordinates":[16.2868881226,48.1052627563],"type":"Point"}
}