{
  "type": "Feature",
  "properties": {
    "addr:full":"S\u00fcdtiroler Pl 4/3 Innsbruck Tirol 6020",
    "addr:housenumber":"4 / 3",
    "addr:postcode":"6020",
    "addr:street":"Suedtiroler Pl;Tirol",
    "iso:country":"AT",
    "sg:address":"S\u00fcdtiroler Pl 4/3",
    "sg:city":"Innsbruck",
    "sg:orig_category":"Energieberatung U -Untersuchung",
    "sg:phone":"+43 4351 25899130",
    "sg:postcode":"6020",
    "sg:province":"Tirol",
    "sg:website":"energie-tirol.at",
    "wof:name":"Energie Tirol Beratung-Forschung-F\u00f6rderung",
    "wof:placetype":"venue"
},
  "geometry": {"coordinates":[11.3913040161,47.2679977417],"type":"Point"}
}