{
  "type": "Feature",
  "properties": {
    "addr:full":"Glockm\u00fchlstr 6 Gnigl Salzburg 5023",
    "addr:housenumber":"6",
    "addr:postcode":"5023",
    "addr:street":"Glockmuehlstr",
    "iso:country":"AT",
    "sg:address":"Glockm\u00fchlstr 6",
    "sg:city":"Gnigl",
    "sg:orig_category":"Fiaker",
    "sg:phone":"+43 662 643838",
    "sg:postcode":"5023",
    "sg:province":"Salzburg",
    "wof:name":"Schmeisser Ernst",
    "wof:placetype":"venue"
},
  "geometry": {"coordinates":[13.1081838608,47.8200416565],"type":"Point"}
}