{
  "type": "Feature",
  "properties": {
    "addr:full":"Im Tannenfeld 4 Meiningen Vorarlberg 6812",
    "addr:housenumber":"4",
    "addr:postcode":"6812",
    "addr:street":"Im Tannenfeld",
    "iso:country":"AT",
    "sg:address":"Im Tannenfeld 4",
    "sg:city":"Meiningen",
    "sg:orig_category":"Handelsagenturen",
    "sg:phone":"+43 5522 71746",
    "sg:postcode":"6812",
    "sg:province":"Vorarlberg",
    "wof:name":"P\u00fcmpel Werner",
    "wof:placetype":"venue"
},
  "geometry": {"coordinates":[9.5799064636,47.2919921875],"type":"Point"}
}