{
  "type": "Feature",
  "properties": {
    "addr:full":"Kaltenbrunner Str 54 Leoben Steiermark 8700",
    "addr:housenumber":"54",
    "addr:postcode":"8700",
    "addr:street":"Str",
    "iso:country":"AT",
    "sg:address":"Kaltenbrunner Str 54",
    "sg:city":"Leoben",
    "sg:orig_category":"Transportunternehmen",
    "sg:phone":"+43 4338 4222163",
    "sg:postcode":"8700",
    "sg:province":"Steiermark",
    "wof:name":"Kr\u00f6ll Gottfried",
    "wof:placetype":"venue"
},
  "geometry": {"coordinates":[15.1022701263,47.3620910645],"type":"Point"}
}