{
  "type": "Feature",
  "properties": {
    "iso:country":"AT",
    "sg:address":"Braunhirscheng 46-48",
    "sg:city":"Wien",
    "sg:orig_category":"Offsetdruckereien",
    "sg:phone":"+43 1 89361420",
    "sg:postcode":"1150",
    "sg:province":"Wien",
    "wof:name":"Druck-Knab - Joseph A Knab GesmbH",
    "wof:placetype":"venue"
},
  "geometry": {"coordinates":[16.3265285492,48.1900100708],"type":"Point"}
}