{
  "type": "Feature",
  "properties": {
    "iso:country":"AT",
    "sg:address":"Michaelerpl 6",
    "sg:city":"Wien",
    "sg:orig_category":"Bilderrahmen",
    "sg:phone":"+43 4315 331049",
    "sg:postcode":"1010",
    "sg:province":"Wien",
    "sg:website":"buehlmayer.at",
    "wof:name":"B\u00fchlmayer C Inh Dr M Haider",
    "wof:placetype":"venue"
},
  "geometry": {"coordinates":[16.3668460846,48.2078323364],"type":"Point"}
}