{
  "type": "Feature",
  "properties": {
    "addr:full":"Viaduktg 14 Bruck an der Leitha Nieder\u00f6sterreich 2460",
    "addr:housenumber":"14",
    "addr:postcode":"2460",
    "addr:street":"Viaduktg",
    "iso:country":"AT",
    "sg:address":"Viaduktg 14",
    "sg:city":"Bruck an der Leitha",
    "sg:orig_category":"Finanz- U Wirtschaftsberatung",
    "sg:phone":"+43 699 12035203",
    "sg:postcode":"2460",
    "sg:province":"Nieder\u00f6sterreich",
    "wof:name":"Hummel Michael",
    "wof:placetype":"venue"
},
  "geometry": {"coordinates":[16.7873477936,48.0193595886],"type":"Point"}
}