{
  "type": "Feature",
  "properties": {
    "addr:full":"Gerberweg 30 Klagenfurt K\u00e4rnten 9020",
    "addr:housenumber":"30",
    "addr:postcode":"9020",
    "addr:street":"Gerberweg;Kaernten",
    "iso:country":"AT",
    "sg:address":"Gerberweg 30",
    "sg:city":"Klagenfurt",
    "sg:orig_category":"Bekleidung / Einzelhandel",
    "sg:phone":"+43 4346 3320156",
    "sg:postcode":"9020",
    "sg:province":"K\u00e4rnten",
    "wof:name":"BIG SALE Textilhandel GmbH",
    "wof:placetype":"venue"
},
  "geometry": {"coordinates":[14.3244419098,46.6112670898],"type":"Point"}
}