{
  "type": "Feature",
  "properties": {
    "iso:country":"AT",
    "sg:address":"Waldheimstr 6",
    "sg:city":"Landskron",
    "sg:orig_category":"Bauunternehmen",
    "sg:phone":"+43 4242 41260",
    "sg:postcode":"9523",
    "sg:province":"K\u00e4rnten",
    "wof:name":"Wind Bau GmbH",
    "wof:placetype":"venue"
},
  "geometry": {"coordinates":[13.8738708496,46.6268081665],"type":"Point"}
}