{
  "type": "Feature",
  "properties": {
    "addr:full":"Nr 16 Zwettl Nieder\u00f6sterreich 3910",
    "addr:postcode":"3910",
    "addr:street":"Nr;Niederoesterreich",
    "iso:country":"AT",
    "sg:address":"Nr 16",
    "sg:city":"Zwettl",
    "sg:classifiers":[
        {
            "category":"Restaurant",
            "type":"Food & Drink"
        }
    ],
    "sg:phone":"+43 4328 2255036",
    "sg:postcode":"3910",
    "sg:province":"Nieder\u00f6sterreich",
    "wof:name":"Taverne Stift Zwettl",
    "wof:placetype":"venue"
},
  "geometry": {"coordinates":[15.1681003571,48.6041564941],"type":"Point"}
}