{
  "type": "Feature",
  "properties": {
    "iso:country":"AT",
    "sg:address":"Salzburger Str 235",
    "sg:city":"Linz",
    "sg:orig_category":"Elektroinstallationsunternehmen",
    "sg:phone":"+43 732 372903",
    "sg:postcode":"4030",
    "sg:province":"Ober\u00f6sterreich",
    "wof:name":"Weilguny & Weilguny Elektro GmbH",
    "wof:placetype":"venue"
},
  "geometry": {"coordinates":[14.2846603394,48.2542610168],"type":"Point"}
}