{
  "type": "Feature",
  "properties": {
    "addr:full":"Neuruppersdorf 26 Wildend\u00fcrnbach Nieder\u00f6sterreich 2164",
    "addr:housenumber":"26",
    "addr:postcode":"2164",
    "addr:street":"Neuruppersdorf;Niederoesterreich",
    "iso:country":"AT",
    "sg:address":"Neuruppersdorf 26",
    "sg:city":"Wildend\u00fcrnbach",
    "sg:orig_category":"Handarbeiten",
    "sg:phone":"+43 2523 8700",
    "sg:postcode":"2164",
    "sg:province":"Nieder\u00f6sterreich",
    "wof:name":"Leisser Barbara",
    "wof:placetype":"venue"
},
  "geometry": {"coordinates":[16.5179100037,48.7525787354],"type":"Point"}
}