{
  "type": "Feature",
  "properties": {
    "iso:country":"AT",
    "sg:address":"Hafnerpl 2",
    "sg:city":"Krems an der Donau",
    "sg:orig_category":"Hauptschulen",
    "sg:phone":"+43 2732 83081",
    "sg:postcode":"3500",
    "sg:province":"Nieder\u00f6sterreich",
    "wof:name":"Hauptschule 2",
    "wof:placetype":"venue"
},
  "geometry": {"coordinates":[15.5993051529,48.4095458984],"type":"Point"}
}