{
  "type": "Feature",
  "properties": {
    "addr:full":"Huben 227b L\u00e4ngenfeld Tirol 6444",
    "addr:housenumber":"227b",
    "addr:postcode":"6444",
    "addr:street":"Huben;Tirol",
    "iso:country":"AT",
    "sg:address":"Huben 227b",
    "sg:city":"L\u00e4ngenfeld",
    "sg:orig_category":"Appartements / Ferienwohnungen",
    "sg:phone":"+43 4352 535713",
    "sg:postcode":"6444",
    "sg:province":"Tirol",
    "wof:name":"Appartement Jasmin",
    "wof:placetype":"venue"
},
  "geometry": {"coordinates":[10.9775476456,47.0403251648],"type":"Point"}
}