{
  "type": "Feature",
  "properties": {
    "addr:full":"Raiffeiseng\u00fcrtel 27 Bruck an der Leitha Nieder\u00f6sterreich 2460",
    "addr:housenumber":"27",
    "addr:postcode":"2460",
    "addr:street":"Raiffeisenguertel",
    "iso:country":"AT",
    "sg:address":"Raiffeiseng\u00fcrtel 27",
    "sg:city":"Bruck an der Leitha",
    "sg:classifiers":[
        {
            "category":"Professional",
            "subcategory":"Computer Services",
            "type":"Services"
        }
    ],
    "sg:phone":"+43 2162 67972",
    "sg:postcode":"2460",
    "sg:province":"Nieder\u00f6sterreich",
    "sg:tags":[
        "software"
    ],
    "wof:name":"Pimpel GesmbH",
    "wof:placetype":"venue"
},
  "geometry": {"coordinates":[16.7784805298,48.0248832703],"type":"Point"}
}