{
  "type": "Feature",
  "properties": {
    "iso:country":"AT",
    "sg:address":"Bayernstr 4",
    "sg:city":"Salzburg",
    "sg:classifiers":[
        {
            "category":"Organizations",
            "subcategory":"Community Association",
            "type":"Services"
        }
    ],
    "sg:phone":"+43 662 8834350",
    "sg:postcode":"5020",
    "sg:province":"Salzburg",
    "sg:tags":[
        "relation",
        "public"
    ],
    "wof:name":"Public Relations- Werbegraphik Schwarz Andrea",
    "wof:placetype":"venue"
},
  "geometry": {"coordinates":[13.0296678543,47.7982788086],"type":"Point"}
}