{
  "type": "Feature",
  "properties": {
    "addr:full":"Pillweinstrasse 16 Salzburg Salzburg 5020",
    "addr:housenumber":"16",
    "addr:postcode":"5020",
    "addr:street":"Pillweinstrasse;Salzburg",
    "iso:country":"AT",
    "sg:address":"Pillweinstrasse 16",
    "sg:city":"Salzburg",
    "sg:classifiers":[
        {
            "category":"Professional",
            "subcategory":"Advertising",
            "type":"Services"
        }
    ],
    "sg:phone":"+43 662 887538",
    "sg:postcode":"5020",
    "sg:province":"Salzburg",
    "sg:tags":[
        "agency"
    ],
    "sg:website":"prokom.com",
    "wof:name":"Prokom Internet-Marketing GmbH",
    "wof:placetype":"venue"
},
  "geometry": {"coordinates":[13.0235834122,47.7990150452],"type":"Point"}
}