{
  "type": "Feature",
  "properties": {
    "iso:country":"AT",
    "sg:address":"Schmiedg 3",
    "sg:city":"Reutte",
    "sg:orig_category":"Friseure U Frisiersalons",
    "sg:phone":"+43 4356 7262645",
    "sg:postcode":"6600",
    "sg:province":"Tirol",
    "wof:name":"Kofler Josef",
    "wof:placetype":"venue"
},
  "geometry": {"coordinates":[10.7171268463,47.4920272827],"type":"Point"}
}