{
  "type": "Feature",
  "properties": {
    "addr:full":"Koglerg 2 F\u00fcrstenfeld Steiermark 8280",
    "addr:housenumber":"2",
    "addr:postcode":"8280",
    "addr:street":"Koglerg",
    "iso:country":"AT",
    "sg:address":"Koglerg 2",
    "sg:city":"F\u00fcrstenfeld",
    "sg:orig_category":"Immobilienverwaltungen",
    "sg:phone":"+43 3382 52628",
    "sg:postcode":"8280",
    "sg:province":"Steiermark",
    "wof:name":"Wohnen & Wert Immobilien GmbH",
    "wof:placetype":"venue"
},
  "geometry": {"coordinates":[16.0826931,47.0424766541],"type":"Point"}
}