{
  "type": "Feature",
  "properties": {
    "addr:full":"Alkoven Ober\u00f6sterreich 4072",
    "addr:postcode":"4072",
    "addr:street":"Oberoesterreich",
    "iso:country":"AT",
    "sg:city":"Alkoven",
    "sg:orig_category":"Feuerwehren",
    "sg:phone":"+43 7274 6300",
    "sg:postcode":"4072",
    "sg:province":"Ober\u00f6sterreich",
    "wof:name":"Freiwillige Feuerwehr Polsing",
    "wof:placetype":"venue"
},
  "geometry": {"coordinates":[14.0852069855,48.2670936584],"type":"Point"}
}