{
  "type": "Feature",
  "properties": {
    "iso:country":"AT",
    "sg:address":"Schremser Str 9",
    "sg:city":"Gm\u00fcnd",
    "sg:orig_category":"Gerichte",
    "sg:phone":"+43 2852 522910",
    "sg:postcode":"3950",
    "sg:province":"Nieder\u00f6sterreich",
    "wof:name":"Bezirksgericht Gm\u00fcnd in Nieder\u00f6sterreich",
    "wof:placetype":"venue"
},
  "geometry": {"coordinates":[14.9870271683,48.7719726562],"type":"Point"}
}