{
  "type": "Feature",
  "properties": {
    "iso:country":"AT",
    "sg:address":"Hauptpl 37",
    "sg:city":"Amstetten",
    "sg:orig_category":"Bankomat-Standorte",
    "sg:phone":"+43 7472 631000",
    "sg:postcode":"3300",
    "sg:province":"Nieder\u00f6sterreich",
    "wof:name":"Bankomat d Raiffeisenbank Amstetten-Ybbs regGenmbH",
    "wof:placetype":"venue"
},
  "geometry": {"coordinates":[14.8711585999,48.1232757568],"type":"Point"}
}