{
  "type": "Feature",
  "properties": {
    "addr:full":"Ebreichsdorfer Str 18  Tribuswinkel Nieder\u00f6sterreich 2512",
    "addr:postcode":"2512",
    "addr:street":"Str;Niederoesterreich",
    "iso:country":"AT",
    "sg:address":"Ebreichsdorfer Str 18 ",
    "sg:city":"Tribuswinkel",
    "sg:classifiers":[
        {
            "category":"Manufacturing",
            "subcategory":"Metals",
            "type":"Manufacturing & Wholesale Goods"
        }
    ],
    "sg:phone":"+43 4322 52802330",
    "sg:postcode":"2512",
    "sg:province":"Nieder\u00f6sterreich",
    "sg:tags":[
        "metallurgy",
        "metalworking"
    ],
    "wof:name":"HTP AG",
    "wof:placetype":"venue"
},
  "geometry": {"coordinates":[16.2946853638,47.9884490967],"type":"Point"}
}