{
  "type": "Feature",
  "properties": {
    "addr:full":"Dornach 12 Axams Tirol 6094",
    "addr:housenumber":"12",
    "addr:postcode":"6094",
    "addr:street":"Dornach;Tirol",
    "iso:country":"AT",
    "sg:address":"Dornach 12",
    "sg:city":"Axams",
    "sg:orig_category":"Transportunternehmen",
    "sg:phone":"+43 5234 68290",
    "sg:postcode":"6094",
    "sg:province":"Tirol",
    "wof:name":"Schilcher Gottfried",
    "wof:placetype":"venue"
},
  "geometry": {"coordinates":[11.2832345963,47.2316055298],"type":"Point"}
}