{
  "type": "Feature",
  "properties": {
    "addr:full":"Hauptstr 53 Leibnitz Steiermark 8430",
    "addr:housenumber":"53",
    "addr:postcode":"8430",
    "addr:street":"Hauptstr;Steiermark",
    "iso:country":"AT",
    "sg:address":"Hauptstr 53",
    "sg:city":"Leibnitz",
    "sg:orig_category":"Gastronomie- U Hoteleinrichtungen",
    "sg:phone":"+43 3452 85400",
    "sg:postcode":"8430",
    "sg:province":"Steiermark",
    "wof:name":"GCS Service Zwirn GmbH",
    "wof:placetype":"venue"
},
  "geometry": {"coordinates":[15.5656785965,46.779094696],"type":"Point"}
}