{
  "type": "Feature",
  "properties": {
    "addr:full":"Kircheng 6 Wien Wien 1070",
    "addr:housenumber":"6",
    "addr:postcode":"1070",
    "addr:street":"Kircheng",
    "iso:country":"AT",
    "sg:address":"Kircheng 6",
    "sg:city":"Wien",
    "sg:orig_category":"Boutiquen",
    "sg:phone":"+43 1 5241616",
    "sg:postcode":"1070",
    "sg:province":"Wien",
    "wof:name":"Boutique Wolford",
    "wof:placetype":"venue"
},
  "geometry": {"coordinates":[16.352853775,48.1999969482],"type":"Point"}
}