{
  "type": "Feature",
  "properties": {
    "addr:full":"Stallburgg 2 Wien Wien 1010",
    "addr:housenumber":"2",
    "addr:postcode":"1010",
    "addr:street":"Stallburgg",
    "iso:country":"AT",
    "sg:address":"Stallburgg 2",
    "sg:city":"Wien",
    "sg:orig_category":"Hygienepapiere",
    "sg:phone":"+43 1 51273390",
    "sg:postcode":"1010",
    "sg:province":"Wien",
    "wof:name":"Hauser Franz KG",
    "wof:placetype":"venue"
},
  "geometry": {"coordinates":[16.3687801361,48.2072067261],"type":"Point"}
}