{
  "type": "Feature",
  "properties": {
    "addr:full":"Terrassenweg 52 St. Kanzian am Klopeiner See K\u00e4rnten 9122",
    "addr:housenumber":"52",
    "addr:postcode":"9122",
    "addr:street":"Terrassenweg;Kaernten",
    "iso:country":"AT",
    "sg:address":"Terrassenweg 52",
    "sg:city":"St. Kanzian am Klopeiner See",
    "sg:orig_category":"Pensionen / Privatzimmer",
    "sg:phone":"+43 4342 392344",
    "sg:postcode":"9122",
    "sg:province":"K\u00e4rnten",
    "wof:name":"Pension Fini",
    "wof:placetype":"venue"
},
  "geometry": {"coordinates":[14.5981588364,46.6080436707],"type":"Point"}
}