{
  "type": "Feature",
  "properties": {
    "addr:full":"Hohe Warte 50-54 Wien Wien 1190",
    "addr:postcode":"50-54;1190",
    "addr:street":"Hohe Warte",
    "iso:country":"AT",
    "sg:address":"Hohe Warte 50-54",
    "sg:city":"Wien",
    "sg:orig_category":"Botschaften",
    "sg:phone":"+43 1 3708104",
    "sg:postcode":"1190",
    "sg:province":"Wien",
    "wof:name":"Botschaft der Arabischen Republik \u00e4gypten",
    "wof:placetype":"venue"
},
  "geometry": {"coordinates":[16.3552246094,48.2501068115],"type":"Point"}
}