{
  "type": "Feature",
  "properties": {
    "addr:full":"Hauptpl 58 Neulengbach Nieder\u00f6sterreich 3040",
    "addr:housenumber":"58",
    "addr:postcode":"3040",
    "addr:street":"Hauptpl",
    "iso:country":"AT",
    "sg:address":"Hauptpl 58",
    "sg:city":"Neulengbach",
    "sg:orig_category":"Bekleidung / Einzelhandel",
    "sg:phone":"+43 2772 523290",
    "sg:postcode":"3040",
    "sg:province":"Nieder\u00f6sterreich",
    "wof:name":"Frank Br\u00fcder",
    "wof:placetype":"venue"
},
  "geometry": {"coordinates":[15.908039093,48.198425293],"type":"Point"}
}