{
  "type": "Feature",
  "properties": {
    "addr:full":"Triester Str 2 Graz Steiermark 8020",
    "addr:housenumber":"2",
    "addr:postcode":"8020",
    "addr:street":"Str",
    "iso:country":"AT",
    "sg:address":"Triester Str 2",
    "sg:city":"Graz",
    "sg:orig_category":"Friseure U Frisiersalons",
    "sg:phone":"+43 4331 6712527",
    "sg:postcode":"8020",
    "sg:province":"Steiermark",
    "wof:name":"Spezial-Haarstudio - Karin Schreiner",
    "wof:placetype":"venue"
},
  "geometry": {"coordinates":[15.43039608,47.0584106445],"type":"Point"}
}