{
  "type": "Feature",
  "properties": {
    "addr:full":"Christalnickstr 8 Treibach-Althofen K\u00e4rnten 9330",
    "addr:housenumber":"8",
    "addr:postcode":"9330",
    "addr:street":"Christalnickstr;Kaernten",
    "iso:country":"AT",
    "sg:address":"Christalnickstr 8",
    "sg:city":"Treibach-Althofen",
    "sg:orig_category":"Glasereien",
    "sg:phone":"+43 4342 622369",
    "sg:postcode":"9330",
    "sg:province":"K\u00e4rnten",
    "wof:name":"Glas & Galerie Sch\u00f6nfelder GmbH",
    "wof:placetype":"venue"
},
  "geometry": {"coordinates":[14.4668159485,46.8724937439],"type":"Point"}
}