{
  "type": "Feature",
  "properties": {
    "addr:full":"Hauptplatz 2 Oberpullendorf Burgenland 7350",
    "addr:housenumber":"2",
    "addr:postcode":"7350",
    "addr:street":"Hauptplatz",
    "iso:country":"AT",
    "sg:address":"Hauptplatz 2",
    "sg:city":"Oberpullendorf",
    "sg:classifiers":[
        {
            "category":"Shopping",
            "subcategory":"Antiques",
            "type":"Retail Goods"
        }
    ],
    "sg:phone":"+43 2612 42322",
    "sg:postcode":"7350",
    "sg:province":"Burgenland",
    "wof:name":"Ladislaus Koger",
    "wof:placetype":"venue"
},
  "geometry": {"coordinates":[16.5044670105,47.5030937195],"type":"Point"}
}