{
  "type": "Feature",
  "properties": {
    "addr:full":"Aigner Str 18 Irdning Steiermark 8952",
    "addr:housenumber":"18",
    "addr:postcode":"8952",
    "addr:street":"Str",
    "iso:country":"AT",
    "sg:address":"Aigner Str 18",
    "sg:city":"Irdning",
    "sg:orig_category":"Eisenwaren",
    "sg:phone":"+43 4336 82227780",
    "sg:postcode":"8952",
    "sg:province":"Steiermark",
    "wof:name":"H\u00f6pflinger Helfried Eisenwaren GesmbH",
    "wof:placetype":"venue"
},
  "geometry": {"coordinates":[14.1031150818,47.5052604675],"type":"Point"}
}