{
  "type": "Feature",
  "properties": {
    "addr:full":"Stadtpl 1 Grein Ober\u00f6sterreich 4360",
    "addr:housenumber":"1",
    "addr:postcode":"4360",
    "addr:street":"Stadtpl",
    "iso:country":"AT",
    "sg:address":"Stadtpl 1",
    "sg:city":"Grein",
    "sg:orig_category":"Optiker",
    "sg:phone":"+43 7268 7770",
    "sg:postcode":"4360",
    "sg:province":"Ober\u00f6sterreich",
    "wof:name":"Theuer Wolfgang GesmbH - Optik-Uhren-Schmuck",
    "wof:placetype":"venue"
},
  "geometry": {"coordinates":[14.8549289703,48.2274665833],"type":"Point"}
}