{
  "type": "Feature",
  "properties": {
    "iso:country":"AT",
    "sg:address":"Nr 20",
    "sg:city":"Gummern",
    "sg:orig_category":"Maschinenbau",
    "sg:phone":"+43 4258 784",
    "sg:postcode":"9722",
    "sg:province":"K\u00e4rnten",
    "wof:name":"K\u00e4rntner Maschinenfabriken Egger GesmbH",
    "wof:placetype":"venue"
},
  "geometry": {"coordinates":[13.7566080093,46.6640281677],"type":"Point"}
}