{
  "type": "Feature",
  "properties": {
    "iso:country":"AT",
    "sg:address":"Hoyossdlg 1",
    "sg:city":"Kernhof",
    "sg:orig_category":"Elektroinstallationsunternehmen",
    "sg:phone":"+43 2768 25160",
    "sg:postcode":"3195",
    "sg:province":"Nieder\u00f6sterreich",
    "wof:name":"Pomberger GesmbH",
    "wof:placetype":"venue"
},
  "geometry": {"coordinates":[15.5427570343,47.8159713745],"type":"Point"}
}