{
  "type": "Feature",
  "properties": {
    "iso:country":"AT",
    "sg:address":"St.-Peter-Str 25",
    "sg:city":"Linz",
    "sg:orig_category":"Anlagenbau U -Technik",
    "sg:phone":"+43 4373 2600093",
    "sg:postcode":"4020",
    "sg:province":"Ober\u00f6sterreich",
    "wof:name":"Zeta Anlagenbau GesmbH",
    "wof:placetype":"venue"
},
  "geometry": {"coordinates":[14.3216533661,48.2888450623],"type":"Point"}
}