{
  "type": "Feature",
  "properties": {
    "addr:full":"Hausfeldstr 2 Wien Wien 1220",
    "addr:housenumber":"2",
    "addr:postcode":"1220",
    "addr:street":"Hausfeldstr",
    "iso:country":"AT",
    "sg:address":"Hausfeldstr 2",
    "sg:city":"Wien",
    "sg:orig_category":"Banken U Sparkassen",
    "sg:phone":"+43 5 010020223",
    "sg:postcode":"1220",
    "sg:province":"Wien",
    "wof:name":"Erste Bank d oesterreichischen Sparkassen AG",
    "wof:placetype":"venue"
},
  "geometry": {"coordinates":[16.4816532135,48.2202033997],"type":"Point"}
}