{
  "type": "Feature",
  "properties": {
    "addr:full":"Prager Str 12 Wien Wien 1210",
    "addr:postcode":"1210",
    "addr:street":"Str 12",
    "iso:country":"AT",
    "sg:address":"Prager Str 12",
    "sg:city":"Wien",
    "sg:orig_category":"Fenster",
    "sg:phone":"+43 1 2706263",
    "sg:postcode":"1210",
    "sg:province":"Wien",
    "wof:name":"Actual-Rodler",
    "wof:placetype":"venue"
},
  "geometry": {"coordinates":[16.3962516785,48.2596969604],"type":"Point"}
}