{
  "type": "Feature",
  "properties": {
    "iso:country":"AT",
    "sg:address":"Hauptpl 16",
    "sg:city":"Pinggau",
    "sg:orig_category":"Fleischhauereien",
    "sg:phone":"+43 3339 22458",
    "sg:postcode":"8243",
    "sg:province":"Steiermark",
    "wof:name":"Riedl KG",
    "wof:placetype":"venue"
},
  "geometry": {"coordinates":[16.066450119,47.4446411133],"type":"Point"}
}