{
  "type": "Feature",
  "properties": {
    "addr:full":"Graben 21 Linz Ober\u00f6sterreich 4020",
    "addr:housenumber":"21",
    "addr:postcode":"4020",
    "addr:street":"Graben",
    "iso:country":"AT",
    "sg:address":"Graben 21",
    "sg:city":"Linz",
    "sg:orig_category":"Friseure U Frisiersalons",
    "sg:phone":"+43 732 771808",
    "sg:postcode":"4020",
    "sg:province":"Ober\u00f6sterreich",
    "wof:name":"Traxler Angelika",
    "wof:placetype":"venue"
},
  "geometry": {"coordinates":[14.2893457413,48.3047599792],"type":"Point"}
}