{
  "type": "Feature",
  "properties": {
    "addr:full":"Wichnerstr 4 Dornbirn Vorarlberg 6850",
    "addr:housenumber":"4",
    "addr:postcode":"6850",
    "addr:street":"Wichnerstr",
    "iso:country":"AT",
    "sg:address":"Wichnerstr 4",
    "sg:city":"Dornbirn",
    "sg:orig_category":"Filmproduktionen",
    "sg:phone":"+43 5572 28527",
    "sg:postcode":"6850",
    "sg:province":"Vorarlberg",
    "wof:name":"Video Brugger Ernst",
    "wof:placetype":"venue"
},
  "geometry": {"coordinates":[9.7334089279,47.4229125977],"type":"Point"}
}