{
  "type": "Feature",
  "properties": {
    "addr:full":"Paniglg 19a Wien Wien 1040",
    "addr:housenumber":"19a",
    "addr:postcode":"1040",
    "addr:street":"Paniglg",
    "iso:country":"AT",
    "sg:address":"Paniglg 19a",
    "sg:city":"Wien",
    "sg:orig_category":"Notare",
    "sg:phone":"+43 1 50540210",
    "sg:postcode":"1040",
    "sg:province":"Wien",
    "wof:name":"Stockinger Helfried Dr",
    "wof:placetype":"venue"
},
  "geometry": {"coordinates":[16.3679256439,48.1980438232],"type":"Point"}
}