{
  "type": "Feature",
  "properties": {
    "iso:country":"AT",
    "sg:address":"Neusetzg 4/2",
    "sg:city":"Wien",
    "sg:orig_category":"Feldenkraismethode",
    "sg:phone":"+43 4369 919415263",
    "sg:postcode":"1100",
    "sg:province":"Wien",
    "wof:name":"M\u00fcllner Matthias - Physiotherapeut & Feldenkreisdiplom",
    "wof:placetype":"venue"
},
  "geometry": {"coordinates":[16.3775978088,48.1727676392],"type":"Point"}
}