{
  "type": "Feature",
  "properties": {
    "addr:full":"Ungerbach 10 Mooskirchen Steiermark 8562",
    "addr:housenumber":"10",
    "addr:postcode":"8562",
    "addr:street":"Ungerbach",
    "iso:country":"AT",
    "sg:address":"Ungerbach 10",
    "sg:city":"Mooskirchen",
    "sg:orig_category":"Weine / Einzelhandel",
    "sg:phone":"+43 3137 4121",
    "sg:postcode":"8562",
    "sg:province":"Steiermark",
    "wof:name":"Zweiger Ferdinand",
    "wof:placetype":"venue"
},
  "geometry": {"coordinates":[15.2833070755,46.9657592773],"type":"Point"}
}