{
  "type": "Feature",
  "properties": {
    "iso:country":"AT",
    "sg:address":"Gaswerkstr 1a",
    "sg:city":"Graz",
    "sg:orig_category":"Ingenieurkonsulenten / Zivilingenieure",
    "sg:phone":"+43 316 5840740",
    "sg:postcode":"8020",
    "sg:province":"Steiermark",
    "wof:name":"Daninger Walter Dipl-Ing",
    "wof:placetype":"venue"
},
  "geometry": {"coordinates":[15.402970314,47.0687713623],"type":"Point"}
}