{
  "type": "Feature",
  "properties": {
    "addr:full":"Hof 1 Maria Anzbach Nieder\u00f6sterreich 3034",
    "addr:housenumber":"1",
    "addr:postcode":"3034",
    "addr:street":"Hof",
    "iso:country":"AT",
    "sg:address":"Hof 1",
    "sg:city":"Maria Anzbach",
    "sg:orig_category":"Beleuchtungsanlagen",
    "sg:phone":"+43 2772 51917",
    "sg:postcode":"3034",
    "sg:province":"Nieder\u00f6sterreich",
    "wof:name":"Agentur f\u00fcr Licht & Design",
    "wof:placetype":"venue"
},
  "geometry": {"coordinates":[15.9550952911,48.1957435608],"type":"Point"}
}