{
  "type": "Feature",
  "properties": {
    "addr:full":"Lainzer Strasse 54 Wien Wien 1130",
    "addr:housenumber":"54",
    "addr:postcode":"1130",
    "addr:street":"Lainzer Strasse",
    "iso:country":"AT",
    "sg:address":"Lainzer Strasse 54",
    "sg:city":"Wien",
    "sg:classifiers":[
        {
            "category":"Organizations",
            "subcategory":"Non-profit Organization",
            "type":"Services"
        }
    ],
    "sg:phone":"+43 1 8767050",
    "sg:postcode":"1130",
    "sg:province":"Wien",
    "sg:tags":[
        "alarm",
        "system"
    ],
    "sg:website":"alarmcom.com",
    "wof:name":"Siemens Fire & Securityproducts GmbH",
    "wof:placetype":"venue"
},
  "geometry": {"coordinates":[16.2876853943,48.1827659607],"type":"Point"}
}