{
  "type": "Feature",
  "properties": {
    "iso:country":"AT",
    "sg:address":"Sch\u00e4flestr. 2 ",
    "sg:city":"Altach",
    "sg:classifiers":[
        {
            "category":"Shopping",
            "subcategory":"Crafts & Fabrics",
            "type":"Retail Goods"
        }
    ],
    "sg:phone":"+43 4355 7672562",
    "sg:postcode":"6844",
    "sg:province":"Vorarlberg",
    "wof:name":"ALBERT KOPF GESMBH & CO",
    "wof:placetype":"venue"
},
  "geometry": {"coordinates":[9.6567316055,47.3546600342],"type":"Point"}
}