{
  "type": "Feature",
  "properties": {
    "addr:full":"Honauerstr 37 Linz Ober\u00f6sterreich 4020",
    "addr:housenumber":"37",
    "addr:postcode":"4020",
    "addr:street":"Honauerstr",
    "iso:country":"AT",
    "sg:address":"Honauerstr 37",
    "sg:city":"Linz",
    "sg:orig_category":"Steuerberatung",
    "sg:phone":"+43 732 7835020",
    "sg:postcode":"4020",
    "sg:province":"Ober\u00f6sterreich",
    "wof:name":"Wegerer Karl Mag",
    "wof:placetype":"venue"
},
  "geometry": {"coordinates":[14.2981443405,48.3073997498],"type":"Point"}
}