{
  "type": "Feature",
  "properties": {
    "addr:full":"Hauptstr 15 Alberndorf in der Riedmark Ober\u00f6sterreich 4211",
    "addr:housenumber":"15",
    "addr:postcode":"4211",
    "addr:street":"Hauptstr",
    "iso:country":"AT",
    "sg:address":"Hauptstr 15",
    "sg:city":"Alberndorf in der Riedmark",
    "sg:orig_category":"Raumausstattung",
    "sg:phone":"+43 4372 357196",
    "sg:postcode":"4211",
    "sg:province":"Ober\u00f6sterreich",
    "wof:name":"Watzinger Andreas",
    "wof:placetype":"venue"
},
  "geometry": {"coordinates":[14.4180135727,48.4056282043],"type":"Point"}
}