{
  "type": "Feature",
  "properties": {
    "iso:country":"AT",
    "sg:address":"Nonntaler Hauptstr 88",
    "sg:city":"Salzburg",
    "sg:orig_category":"Textilreinigung",
    "sg:phone":"+43 676 84819420",
    "sg:postcode":"5020",
    "sg:province":"Salzburg",
    "wof:name":"Mirabell Counde Textilpflege GesmbH",
    "wof:placetype":"venue"
},
  "geometry": {"coordinates":[13.0520706177,47.7846450806],"type":"Point"}
}