{
  "type": "Feature",
  "properties": {
    "iso:country":"AT",
    "sg:address":"Senderweg 10",
    "sg:city":"Aldrans",
    "sg:orig_category":"Appartements / Ferienwohnungen",
    "sg:phone":"+43 4351 2347014",
    "sg:postcode":"6071",
    "sg:province":"Tirol",
    "wof:name":"Haus Purtscher",
    "wof:placetype":"venue"
},
  "geometry": {"coordinates":[11.4483089447,47.2529602051],"type":"Point"}
}