{
  "type": "Feature",
  "properties": {
    "addr:full":"K\u00e4rntner Str 66 Arnoldstein K\u00e4rnten 9601",
    "addr:postcode":"9601",
    "addr:street":"Str 66;Kaernten",
    "iso:country":"AT",
    "sg:address":"K\u00e4rntner Str 66",
    "sg:city":"Arnoldstein",
    "sg:orig_category":"Tabaktrafiken",
    "sg:phone":"+43 4255 2357",
    "sg:postcode":"9601",
    "sg:province":"K\u00e4rnten",
    "wof:name":"Taurer Ilse",
    "wof:placetype":"venue"
},
  "geometry": {"coordinates":[13.701584816,46.5500564575],"type":"Point"}
}