{
  "type": "Feature",
  "properties": {
    "addr:full":"Rochusg 3-5 Wien Wien 1030",
    "addr:housenumber":"3-5",
    "addr:postcode":"1030",
    "addr:street":"Rochusg",
    "iso:country":"AT",
    "sg:address":"Rochusg 3-5",
    "sg:city":"Wien",
    "sg:orig_category":"Friseure U Frisiersalons",
    "sg:phone":"+43 1 7146725",
    "sg:postcode":"1030",
    "sg:province":"Wien",
    "wof:name":"Pr\u00f6diger Christa",
    "wof:placetype":"venue"
},
  "geometry": {"coordinates":[16.3911190033,48.2015037537],"type":"Point"}
}