{
  "type": "Feature",
  "properties": {
    "iso:country":"AT",
    "sg:address":"Laxenburger Str. 256",
    "sg:city":"Wien",
    "sg:classifiers":[
        {
            "category":"Food & Beverages",
            "subcategory":"Groceries & Convenience Stores",
            "type":"Retail Goods"
        }
    ],
    "sg:phone":"+43 4316 14150",
    "sg:postcode":"1230",
    "sg:province":"Wien",
    "sg:tags":[
        "product",
        "related"
    ],
    "wof:name":"WIESBAUER \u00d6STERR. WURST- SPEZIALIT\u00c4TEN GES.MBH",
    "wof:placetype":"venue"
},
  "geometry": {"coordinates":[16.3553390503,48.1326141357],"type":"Point"}
}