{
  "type": "Feature",
  "properties": {
    "addr:full":"Pf\u00e4nder Berghaus 4 Lochau Vorarlberg 6911",
    "addr:housenumber":"4",
    "addr:postcode":"6911",
    "addr:street":"Berghaus",
    "iso:country":"AT",
    "sg:address":"Pf\u00e4nder Berghaus 4",
    "sg:city":"Lochau",
    "sg:classifiers":[
        {
            "category":"Restaurant",
            "type":"Food & Drink"
        }
    ],
    "sg:phone":"+43 4355 7442184",
    "sg:postcode":"6911",
    "sg:province":"Vorarlberg",
    "wof:name":"Kinz Hans Ferdinand Mag",
    "wof:placetype":"venue"
},
  "geometry": {"coordinates":[9.7512302399,47.5298461914],"type":"Point"}
}