{
  "type": "Feature",
  "properties": {
    "addr:full":"Hinterm\u00fchle 1 Zwettl an der Rodl Ober\u00f6sterreich 4180",
    "addr:housenumber":"1",
    "addr:postcode":"4180",
    "addr:street":"Hintermuehle",
    "iso:country":"AT",
    "sg:address":"Hinterm\u00fchle 1",
    "sg:city":"Zwettl an der Rodl",
    "sg:classifiers":[
        {
            "category":"Manufacturing",
            "subcategory":"Wood Products",
            "type":"Manufacturing & Wholesale Goods"
        }
    ],
    "sg:phone":"+43 7212 65130",
    "sg:postcode":"4180",
    "sg:province":"Ober\u00f6sterreich",
    "sg:tags":[
        "gate",
        "made",
        "door"
    ],
    "wof:name":"Leberbauer GmbH",
    "wof:placetype":"venue"
},
  "geometry": {"coordinates":[14.2713985443,48.4661216736],"type":"Point"}
}