{
  "type": "Feature",
  "properties": {
    "iso:country":"AT",
    "sg:address":"St.-Martin-Str 2/18",
    "sg:city":"Dornbirn",
    "sg:orig_category":"Brautkleider U -Artikel / Vermietung",
    "sg:phone":"+43 4355 7228639",
    "sg:postcode":"6850",
    "sg:province":"Vorarlberg",
    "wof:name":"Brautservice Lisa",
    "wof:placetype":"venue"
},
  "geometry": {"coordinates":[9.7432899475,47.40858078],"type":"Point"}
}