{
  "type": "Feature",
  "properties": {
    "iso:country":"AT",
    "sg:address":"Hauptstr 21",
    "sg:city":"Grein",
    "sg:orig_category":"\u00c3\u201erzte / F Allgemeinmedizin",
    "sg:phone":"+43 7268 224",
    "sg:postcode":"4360",
    "sg:province":"Ober\u00f6sterreich",
    "wof:name":"Huemer Thomas Dr",
    "wof:placetype":"venue"
},
  "geometry": {"coordinates":[14.8559904099,48.2282791138],"type":"Point"}
}