{
  "type": "Feature",
  "properties": {
    "addr:full":"Leithastrasse 25 Wien Wien 1200",
    "addr:housenumber":"25",
    "addr:postcode":"1200",
    "addr:street":"Leithastrasse",
    "iso:country":"AT",
    "sg:address":"Leithastrasse 25",
    "sg:city":"Wien",
    "sg:orig_category":"Water Treatment Installations For Car Wash Facilities",
    "sg:phone":"+43 1 3329416",
    "sg:postcode":"1200",
    "sg:province":"Wien",
    "sg:website":"gruenbeck.de",
    "wof:name":"GR\u00dcNBECK Proze\u00dftechnik GmbH",
    "wof:placetype":"venue"
},
  "geometry": {"coordinates":[16.3771152496,48.2379226685],"type":"Point"}
}