{
  "type": "Feature",
  "properties": {
    "addr:full":"Oberrotte 66 St. Jakob in Defereggen Tirol 9963",
    "addr:housenumber":"66",
    "addr:postcode":"jakob;defereggen;9963",
    "addr:street":"Oberrotte",
    "iso:country":"AT",
    "sg:address":"Oberrotte 66",
    "sg:city":"St. Jakob in Defereggen",
    "sg:orig_category":"Pensionen / Privatzimmer",
    "sg:phone":"+43 4348 736333",
    "sg:postcode":"9963",
    "sg:province":"Tirol",
    "wof:name":"Pension L\u00e4rchenhof",
    "wof:placetype":"venue"
},
  "geometry": {"coordinates":[12.292140007,46.9098014832],"type":"Point"}
}