{
  "type": "Feature",
  "properties": {
    "iso:country":"AT",
    "sg:address":"M\u00fcllerstr 19",
    "sg:city":"Innsbruck",
    "sg:classifiers":[
        {
            "category":"Shopping",
            "subcategory":"Thrift Store",
            "type":"Retail Goods"
        }
    ],
    "sg:phone":"+43 4366 43124568",
    "sg:postcode":"6020",
    "sg:province":"Tirol",
    "sg:tags":[
        "second-hand-shops"
    ],
    "wof:name":"Kind-und-Kegel Second Hand Kinderboutique Andrea Kr\u00f6sbacher",
    "wof:placetype":"venue"
},
  "geometry": {"coordinates":[11.3913040161,47.2679977417],"type":"Point"}
}