{
  "type": "Feature",
  "properties": {
    "iso:country":"AT",
    "sg:address":"Tribuswinkler Str. 18 ",
    "sg:city":"Traiskirchen",
    "sg:classifiers":[
        {
            "category":"Bars & Pubs",
            "subcategory":"Nightclub",
            "type":"Food & Drink"
        }
    ],
    "sg:phone":"+43 4322 5252888",
    "sg:postcode":"2514",
    "sg:province":"Nieder\u00f6sterreich",
    "sg:tags":[
        "cake",
        "bread"
    ],
    "wof:name":"BLASCHKE KONDITOREI GES.MBH",
    "wof:placetype":"venue"
},
  "geometry": {"coordinates":[16.2852840424,48.0121269226],"type":"Point"}
}