{
  "type": "Feature",
  "properties": {
    "addr:full":"Stadtpl 3 Gm\u00fcnd Nieder\u00f6sterreich 3950",
    "addr:housenumber":"3",
    "addr:postcode":"3950",
    "addr:street":"Stadtpl;Niederoesterreich",
    "iso:country":"AT",
    "sg:address":"Stadtpl 3",
    "sg:city":"Gm\u00fcnd",
    "sg:orig_category":"Forstverwaltungen",
    "sg:phone":"+43 2852 523140",
    "sg:postcode":"3950",
    "sg:province":"Nieder\u00f6sterreich",
    "wof:name":"Habsburg-Lothringen'sche Gutsverwaltung",
    "wof:placetype":"venue"
},
  "geometry": {"coordinates":[14.983745575,48.7726135254],"type":"Point"}
}