{
  "type": "Feature",
  "properties": {
    "iso:country":"AT",
    "sg:address":"Kernstockg 10",
    "sg:city":"Graz",
    "sg:orig_category":"Altwaren",
    "sg:phone":"+43 316 712927",
    "sg:postcode":"8020",
    "sg:province":"Steiermark",
    "wof:name":"Zingerle Werner",
    "wof:placetype":"venue"
},
  "geometry": {"coordinates":[15.4300956726,47.0699119568],"type":"Point"}
}