{
  "type": "Feature",
  "properties": {
    "addr:full":"Wiener Bundesstr 3 Hallwang Salzburg 5300",
    "addr:housenumber":"3",
    "addr:postcode":"5300",
    "addr:street":"Salzburg",
    "iso:country":"AT",
    "sg:address":"Wiener Bundesstr 3",
    "sg:city":"Hallwang",
    "sg:orig_category":"Lebensmittel / Einzelhandel",
    "sg:phone":"+43 662 661080",
    "sg:postcode":"5300",
    "sg:province":"Salzburg",
    "wof:name":"Hofer KG",
    "wof:placetype":"venue"
},
  "geometry": {"coordinates":[13.0836086273,47.830116272],"type":"Point"}
}