{
  "type": "Feature",
  "properties": {
    "addr:full":"Cumberlandstr 63 Wien Wien 1140",
    "addr:housenumber":"63",
    "addr:postcode":"1140",
    "addr:street":"Cumberlandstr",
    "iso:country":"AT",
    "sg:address":"Cumberlandstr 63",
    "sg:city":"Wien",
    "sg:orig_category":"Immobilienmakler",
    "sg:phone":"+43 664 3953235",
    "sg:postcode":"1140",
    "sg:province":"Wien",
    "wof:name":"Posch Thomas",
    "wof:placetype":"venue"
},
  "geometry": {"coordinates":[16.2998504639,48.1919631958],"type":"Point"}
}