{
  "type": "Feature",
  "properties": {
    "addr:full":"Brunner Str 27 Waidhofen an der Thaya Nieder\u00f6sterreich 3830",
    "addr:postcode":"3830",
    "addr:street":"Str 27;An Der Thaya",
    "iso:country":"AT",
    "sg:address":"Brunner Str 27",
    "sg:city":"Waidhofen an der Thaya",
    "sg:orig_category":"Hunde- U Katzensalons",
    "sg:phone":"+43 4328 4253982",
    "sg:postcode":"3830",
    "sg:province":"Nieder\u00f6sterreich",
    "wof:name":"BOZEK - Dipl. Hundefriseurin",
    "wof:placetype":"venue"
},
  "geometry": {"coordinates":[15.2693319321,48.8113327026],"type":"Point"}
}