{
  "type": "Feature",
  "properties": {
    "addr:full":"An-der-Lan-Str 28d Innsbruck Tirol 6020",
    "addr:housenumber":"28d",
    "addr:postcode":"6020",
    "addr:street":"An-Der-Lan-Str;Tirol",
    "iso:country":"AT",
    "sg:address":"An-der-Lan-Str 28d",
    "sg:city":"Innsbruck",
    "sg:orig_category":"Bauunternehmen",
    "sg:phone":"+43 699 10019607",
    "sg:postcode":"6020",
    "sg:province":"Tirol",
    "wof:name":"Gastl Christian",
    "wof:placetype":"venue"
},
  "geometry": {"coordinates":[11.4399051666,47.2722053528],"type":"Point"}
}