{
  "type": "Feature",
  "properties": {
    "addr:full":"Oberlavieren 2 Rinn Tirol 6074",
    "addr:housenumber":"2",
    "addr:postcode":"6074",
    "addr:street":"Oberlavieren",
    "iso:country":"AT",
    "sg:address":"Oberlavieren 2",
    "sg:city":"Rinn",
    "sg:orig_category":"Installationsunternehmen",
    "sg:phone":"+43 5223 78999",
    "sg:postcode":"6074",
    "sg:province":"Tirol",
    "wof:name":"Sansystem-Fertigb\u00e4der Inh Robert Majoni",
    "wof:placetype":"venue"
},
  "geometry": {"coordinates":[11.5041694641,47.2501792908],"type":"Point"}
}