{
  "type": "Feature",
  "properties": {
    "addr:full":"Hauptstr 6 Wiener Neudorf Nieder\u00f6sterreich 2351",
    "addr:housenumber":"6",
    "addr:postcode":"2351",
    "addr:street":"Hauptstr",
    "iso:country":"AT",
    "sg:address":"Hauptstr 6",
    "sg:city":"Wiener Neudorf",
    "sg:orig_category":"Schlossereien",
    "sg:phone":"+43 2236 61746",
    "sg:postcode":"2351",
    "sg:province":"Nieder\u00f6sterreich",
    "wof:name":"Hroch Johann GesmbH",
    "wof:placetype":"venue"
},
  "geometry": {"coordinates":[16.3149757385,48.0866088867],"type":"Point"}
}