{
  "type": "Feature",
  "properties": {
    "addr:full":"Hirtlhof 23 Bad Zell Ober\u00f6sterreich 4283",
    "addr:housenumber":"23",
    "addr:postcode":"4283",
    "addr:street":"Hirtlhof",
    "iso:country":"AT",
    "sg:address":"Hirtlhof 23",
    "sg:city":"Bad Zell",
    "sg:orig_category":"Schlossereien",
    "sg:phone":"+43 7263 73200",
    "sg:postcode":"4283",
    "sg:province":"Ober\u00f6sterreich",
    "wof:name":"Grasserbauer Gerhard",
    "wof:placetype":"venue"
},
  "geometry": {"coordinates":[14.6684646606,48.3711433411],"type":"Point"}
}