{
  "type": "Feature",
  "properties": {
    "addr:full":"Nr 5 Gl\u00f6dnitz K\u00e4rnten 9346",
    "addr:postcode":"9346",
    "addr:street":"Nr;Gloednitz",
    "iso:country":"AT",
    "sg:address":"Nr 5",
    "sg:city":"Gl\u00f6dnitz",
    "sg:orig_category":"Pensionen / Privatzimmer",
    "sg:phone":"+43 4265 8131",
    "sg:postcode":"9346",
    "sg:province":"K\u00e4rnten",
    "wof:name":"Reiterer Helmut",
    "wof:placetype":"venue"
},
  "geometry": {"coordinates":[-95.7627410889,34.9322166443],"type":"Point"}
}