{
  "type": "Feature",
  "properties": {
    "addr:full":"Wildkogelbahnstr 315 Neukirchen am Gro\u00dfvenediger Salzburg 5741",
    "addr:housenumber":"315",
    "addr:postcode":"5741",
    "addr:street":"Salzburg",
    "iso:country":"AT",
    "sg:address":"Wildkogelbahnstr 315",
    "sg:city":"Neukirchen am Gro\u00dfvenediger",
    "sg:orig_category":"Bars-Cafes",
    "sg:phone":"+43 4365 6564660",
    "sg:postcode":"5741",
    "sg:province":"Salzburg",
    "wof:name":"Pinzgauer Kanne",
    "wof:placetype":"venue"
},
  "geometry": {"coordinates":[12.2814502716,47.2542686462],"type":"Point"}
}