{
  "type": "Feature",
  "properties": {
    "addr:full":"Zieglergasse 75  Wien Wien 1070",
    "addr:housenumber":"75",
    "addr:postcode":"1070",
    "addr:street":"Zieglergasse",
    "iso:country":"AT",
    "sg:address":"Zieglergasse 75 ",
    "sg:city":"Wien",
    "sg:classifiers":[
        {
            "category":"Building & Trades",
            "subcategory":"Plumbing",
            "type":"Services"
        }
    ],
    "sg:phone":"+43 1 5234336",
    "sg:postcode":"1070",
    "sg:province":"Wien",
    "sg:tags":[
        "supraregional",
        "gas"
    ],
    "wof:name":"Aschauer & Weiss Ges.m.b.H.",
    "wof:placetype":"venue"
},
  "geometry": {"coordinates":[16.3446998596,48.205997467],"type":"Point"}
}