{
  "type": "Feature",
  "properties": {
    "addr:full":"Nr 46 Anger Steiermark 8184",
    "addr:postcode":"8184",
    "addr:street":"Nr 46",
    "iso:country":"AT",
    "sg:address":"Nr 46",
    "sg:city":"Anger",
    "sg:orig_category":"Friseure U Frisiersalons",
    "sg:phone":"+43 3175 28471",
    "sg:postcode":"8184",
    "sg:province":"Steiermark",
    "wof:name":"Friseurstudio Stefanie",
    "wof:placetype":"venue"
},
  "geometry": {"coordinates":[15.7057800293,47.2626419067],"type":"Point"}
}