{
  "type": "Feature",
  "properties": {
    "addr:full":"Herzograd 4 St. Valentin Nieder\u00f6sterreich 4300",
    "addr:housenumber":"4",
    "addr:postcode":"4300",
    "addr:street":"Herzograd",
    "iso:country":"AT",
    "sg:address":"Herzograd 4",
    "sg:city":"St. Valentin",
    "sg:orig_category":"Friseure U Frisiersalons",
    "sg:phone":"+43 4374 3552176",
    "sg:postcode":"4300",
    "sg:province":"Nieder\u00f6sterreich",
    "wof:name":"Haus der Frisur - Hinterreiter",
    "wof:placetype":"venue"
},
  "geometry": {"coordinates":[14.511762619,48.1602249146],"type":"Point"}
}