{
  "type": "Feature",
  "properties": {
    "addr:full":"Strassenh\u00e4user 65 Koblach Vorarlberg 6842",
    "addr:housenumber":"65",
    "addr:postcode":"6842",
    "addr:street":"Strassenhaeuser",
    "iso:country":"AT",
    "sg:address":"Strassenh\u00e4user 65",
    "sg:city":"Koblach",
    "sg:classifiers":[
        {
            "category":"Wholesale",
            "subcategory":"Plants",
            "type":"Manufacturing & Wholesale Goods"
        }
    ],
    "sg:phone":"+43 5523 51776",
    "sg:postcode":"6842",
    "sg:province":"Vorarlberg",
    "sg:tags":[
        "supraregional",
        "geothermal",
        "installation",
        "heating"
    ],
    "wof:name":"Ebenhoch Gas-Wasser-Heizungs Installations Ges.m.b.H.",
    "wof:placetype":"venue"
},
  "geometry": {"coordinates":[9.6222696304,47.3177909851],"type":"Point"}
}