{
  "type": "Feature",
  "properties": {
    "iso:country":"AT",
    "sg:address":"Alfred-Kubin-Strasse 8",
    "sg:city":"Zell am See",
    "sg:classifiers":[
        {
            "category":"Home & Garden",
            "subcategory":"Building Materials",
            "type":"Retail Goods"
        }
    ],
    "sg:phone":"+43 6542 72517",
    "sg:postcode":"5700",
    "sg:province":"Salzburg",
    "sg:tags":[
        "glass",
        "enclosures",
        "balcony"
    ],
    "sg:website":"unterganschnigg.at",
    "wof:name":"Friedrich Unterganschnigg",
    "wof:placetype":"venue"
},
  "geometry": {"coordinates":[-98.5093917847,44.8744659424],"type":"Point"}
}