{
  "type": "Feature",
  "properties": {
    "addr:full":"Anger 50 Weyer Ober\u00f6sterreich 3335",
    "addr:housenumber":"50",
    "addr:postcode":"3335",
    "addr:street":"Anger",
    "iso:country":"AT",
    "sg:address":"Anger 50",
    "sg:city":"Weyer",
    "sg:orig_category":"Hafnereien",
    "sg:phone":"+43 7355 20054",
    "sg:postcode":"3335",
    "sg:province":"Ober\u00f6sterreich",
    "wof:name":"Katzensteiner Bernhard",
    "wof:placetype":"venue"
},
  "geometry": {"coordinates":[14.6338653564,47.8535385132],"type":"Point"}
}