{
  "type": "Feature",
  "properties": {
    "addr:full":"Triglavstrasse 16 Villach K\u00e4rnten 9500",
    "addr:housenumber":"16",
    "addr:postcode":"9500",
    "addr:street":"Triglavstrasse;Kaernten",
    "iso:country":"AT",
    "sg:address":"Triglavstrasse 16",
    "sg:city":"Villach",
    "sg:classifiers":[
        {
            "category":"Building & Trades",
            "subcategory":"Construction",
            "type":"Services"
        }
    ],
    "sg:phone":"+43 4242 30410",
    "sg:postcode":"9500",
    "sg:province":"K\u00e4rnten",
    "sg:tags":[
        "steel"
    ],
    "wof:name":"Eisenkontor Ges.m.b.H. & Co Eisen-, Stahl- und R\u00f6hren KG",
    "wof:placetype":"venue"
},
  "geometry": {"coordinates":[13.8398809433,46.5919036865],"type":"Point"}
}