{
  "type": "Feature",
  "properties": {
    "addr:full":"Strobelg 2 Wien Wien 1010",
    "addr:housenumber":"2",
    "addr:postcode":"1010",
    "addr:street":"Strobelg",
    "iso:country":"AT",
    "sg:address":"Strobelg 2",
    "sg:city":"Wien",
    "sg:orig_category":"Immobilienmakler",
    "sg:phone":"+43 1 51292000",
    "sg:postcode":"1010",
    "sg:province":"Wien",
    "wof:name":"Trestler Fritz Dr KG",
    "wof:placetype":"venue"
},
  "geometry": {"coordinates":[16.3751869202,48.2085189819],"type":"Point"}
}