{
  "type": "Feature",
  "properties": {
    "addr:full":"Feilbachstr 271 Wals Salzburg 5071",
    "addr:housenumber":"271",
    "addr:postcode":"5071",
    "addr:street":"Wals Salzburg",
    "iso:country":"AT",
    "sg:address":"Feilbachstr 271",
    "sg:city":"Wals",
    "sg:orig_category":"Blumeneinzelhandel",
    "sg:phone":"+43 662 850274",
    "sg:postcode":"5071",
    "sg:province":"Salzburg",
    "wof:name":"Holland Blumen GmbH",
    "wof:placetype":"venue"
},
  "geometry": {"coordinates":[12.9850111008,47.8138923645],"type":"Point"}
}