{
  "type": "Feature",
  "properties": {
    "addr:full":"Pezzlg 18-20 Wien Wien 1170",
    "addr:postcode":"18-20;1170",
    "iso:country":"AT",
    "sg:address":"Pezzlg 18-20",
    "sg:city":"Wien",
    "sg:orig_category":"Friseure U Frisiersalons",
    "sg:phone":"+43 4314 088826",
    "sg:postcode":"1170",
    "sg:province":"Wien",
    "wof:name":"Friseurgesch\u00e4ft Schreiber Antonia",
    "wof:placetype":"venue"
},
  "geometry": {"coordinates":[16.3355464935,48.2193374634],"type":"Point"}
}