{
  "type": "Feature",
  "properties": {
    "addr:full":"Ludham 6 M\u00fcnzkirchen Ober\u00f6sterreich 4792",
    "addr:housenumber":"6",
    "addr:postcode":"4792",
    "addr:street":"Ludham;Oberoesterreich",
    "iso:country":"AT",
    "sg:address":"Ludham 6",
    "sg:city":"M\u00fcnzkirchen",
    "sg:orig_category":"Transportunternehmen",
    "sg:phone":"+43 7716 6585",
    "sg:postcode":"4792",
    "sg:province":"Ober\u00f6sterreich",
    "wof:name":"Gruber Franz",
    "wof:placetype":"venue"
},
  "geometry": {"coordinates":[13.6003713608,48.4615364075],"type":"Point"}
}