{
  "type": "Feature",
  "properties": {
    "iso:country":"AT",
    "sg:address":"Maxglaner Hauptstr 29",
    "sg:city":"Salzburg",
    "sg:orig_category":"Pensionen / Privatzimmer",
    "sg:phone":"+43 662 834034",
    "sg:postcode":"5020",
    "sg:province":"Salzburg",
    "wof:name":"Noppinger Walter",
    "wof:placetype":"venue"
},
  "geometry": {"coordinates":[13.0224485397,47.797077179],"type":"Point"}
}