{
  "type": "Feature",
  "properties": {
    "iso:country":"AT",
    "sg:address":"Fischbach 94",
    "sg:city":"Fischbach",
    "sg:classifiers":[
        {
            "category":"Manufacturing",
            "subcategory":"Furniture",
            "type":"Manufacturing & Wholesale Goods"
        }
    ],
    "sg:phone":"+43 3170 283",
    "sg:postcode":"8654",
    "sg:province":"Steiermark",
    "sg:tags":[
        "bedroom"
    ],
    "wof:name":"Schwab Tischlerei Inh. Eva-Maria H\u00f6dl",
    "wof:placetype":"venue"
},
  "geometry": {"coordinates":[15.6506252289,47.442527771],"type":"Point"}
}