{
  "type": "Feature",
  "properties": {
    "addr:full":"Rosenauerstr 54 Linz Ober\u00f6sterreich 4040",
    "addr:housenumber":"54",
    "addr:postcode":"4040",
    "addr:street":"Rosenauerstr",
    "iso:country":"AT",
    "sg:address":"Rosenauerstr 54",
    "sg:city":"Linz",
    "sg:orig_category":"Zahntechnische Laboratorien",
    "sg:phone":"+43 732 700950",
    "sg:postcode":"4040",
    "sg:province":"Ober\u00f6sterreich",
    "wof:name":"Pro-Ceram Dental Labor GmbH Nfg KEG",
    "wof:placetype":"venue"
},
  "geometry": {"coordinates":[14.2743425369,48.3156661987],"type":"Point"}
}