{
  "type": "Feature",
  "properties": {
    "iso:country":"AT",
    "sg:address":"Leebgasse 64",
    "sg:city":"Wien",
    "sg:orig_category":"Gaskets, Washers, Seals",
    "sg:phone":"+43 1 6040171",
    "sg:postcode":"1100",
    "sg:province":"Wien",
    "sg:website":"persicaner.at",
    "wof:name":"Persicaner & Co Ges.m.b.H.",
    "wof:placetype":"venue"
},
  "geometry": {"coordinates":[16.3692054749,48.1728591919],"type":"Point"}
}