{
  "type": "Feature",
  "properties": {
    "addr:full":"Seidelwirtweg 2 St. Stefan im Lavanttal K\u00e4rnten 9431",
    "addr:housenumber":"2",
    "addr:postcode":"9431",
    "addr:street":"Seidelwirtweg",
    "iso:country":"AT",
    "sg:address":"Seidelwirtweg 2",
    "sg:city":"St. Stefan im Lavanttal",
    "sg:orig_category":"Estriche",
    "sg:phone":"+43 4343 5281512",
    "sg:postcode":"9431",
    "sg:province":"K\u00e4rnten",
    "wof:name":"Koinig Herbert",
    "wof:placetype":"venue"
},
  "geometry": {"coordinates":[14.832036972,46.8094558716],"type":"Point"}
}