{
  "type": "Feature",
  "properties": {
    "addr:full":"Zehetnerg 32/2 Wien Wien 1140",
    "addr:housenumber":"32 / 2",
    "addr:postcode":"1140",
    "addr:street":"Zehetnerg",
    "iso:country":"AT",
    "sg:address":"Zehetnerg 32/2",
    "sg:city":"Wien",
    "sg:orig_category":"Astrologie",
    "sg:phone":"+43 4314 163055",
    "sg:postcode":"1140",
    "sg:province":"Wien",
    "wof:name":"St\u00f6ger Theresia",
    "wof:placetype":"venue"
},
  "geometry": {"coordinates":[16.286687851,48.1953010559],"type":"Point"}
}