{
  "type": "Feature",
  "properties": {
    "iso:country":"AT",
    "sg:address":"Siebeckstr 7",
    "sg:city":"Wien",
    "sg:orig_category":"Physikalische Institute",
    "sg:phone":"+43 1 2032388",
    "sg:postcode":"1220",
    "sg:province":"Wien",
    "wof:name":"Physikalisches Institut Donauzentrum",
    "wof:placetype":"venue"
},
  "geometry": {"coordinates":[16.4331874847,48.2431602478],"type":"Point"}
}