{
  "type": "Feature",
  "properties": {
    "iso:country":"AT",
    "sg:address":"Schafwiesenstr 63",
    "sg:city":"Marchtrenk",
    "sg:orig_category":"Garten- U Landschaftsgestaltung",
    "sg:phone":"+43 7243 51276",
    "sg:postcode":"4614",
    "sg:province":"Ober\u00f6sterreich",
    "sg:website":"www.botanika.at",
    "wof:name":"Botanika Josef Greinegger",
    "wof:placetype":"venue"
},
  "geometry": {"coordinates":[14.0884876251,48.1818962097],"type":"Point"}
}