{
  "type": "Feature",
  "properties": {
    "addr:full":"Perfektastrasse 86 Wien Wien 1230",
    "addr:housenumber":"86",
    "addr:postcode":"1230",
    "addr:street":"Perfektastrasse",
    "iso:country":"AT",
    "sg:address":"Perfektastrasse 86",
    "sg:city":"Wien",
    "sg:classifiers":[
        {
            "category":"Wholesale",
            "subcategory":"Drugs",
            "type":"Manufacturing & Wholesale Goods"
        }
    ],
    "sg:phone":"+43 1 891220",
    "sg:postcode":"1230",
    "sg:province":"Wien",
    "sg:tags":[
        "antibiotic"
    ],
    "sg:website":"abbott.com",
    "wof:name":"Abbott Ges.m.b.H.",
    "wof:placetype":"venue"
},
  "geometry": {"coordinates":[16.3084049225,48.1368408203],"type":"Point"}
}