{
  "type": "Feature",
  "properties": {
    "addr:full":"Dr.-Viktor-Verdro\u00df-Str 3 Deutschlandsberg Steiermark 8530",
    "addr:housenumber":"3",
    "addr:postcode":"8530",
    "addr:street":"Dr.-Viktor-Verdross-Str",
    "iso:country":"AT",
    "sg:address":"Dr.-Viktor-Verdro\u00df-Str 3",
    "sg:city":"Deutschlandsberg",
    "sg:orig_category":"Maler, Anstreicher U Lackierer",
    "sg:phone":"+43 4334 625233",
    "sg:postcode":"8530",
    "sg:province":"Steiermark",
    "wof:name":"Marath Daniel",
    "wof:placetype":"venue"
},
  "geometry": {"coordinates":[15.2256717682,46.8125762939],"type":"Point"}
}