{
  "type": "Feature",
  "properties": {
    "iso:country":"AT",
    "sg:address":"Leopoldauer Pl 90",
    "sg:city":"Wien",
    "sg:classifiers":[
        {
            "category":"Restaurant",
            "type":"Food & Drink"
        }
    ],
    "sg:phone":"+43 1 2584696",
    "sg:postcode":"1210",
    "sg:province":"Wien",
    "wof:name":"Restaurant Schabanack",
    "wof:placetype":"venue"
},
  "geometry": {"coordinates":[16.4372959137,48.262878418],"type":"Point"}
}