{
  "type": "Feature",
  "properties": {
    "iso:country":"AT",
    "sg:address":"Krugerstr 11",
    "sg:city":"Wien",
    "sg:classifiers":[
        {
            "category":"Travel",
            "subcategory":"Hotels & Motels",
            "type":"Entertainment"
        }
    ],
    "sg:phone":"+43 1 51312740",
    "sg:postcode":"1010",
    "sg:province":"Wien",
    "wof:name":"Hotel Zur Wiener Staatsoper",
    "wof:placetype":"venue"
},
  "geometry": {"coordinates":[16.3717651367,48.2039718628],"type":"Point"}
}