{
  "type": "Feature",
  "properties": {
    "addr:full":"Siedlung S\u00fcd 9 Reichenfels K\u00e4rnten 9463",
    "addr:housenumber":"9",
    "addr:postcode":"9463",
    "addr:street":"Siedlung Sued;Kaernten",
    "iso:country":"AT",
    "sg:address":"Siedlung S\u00fcd 9",
    "sg:city":"Reichenfels",
    "sg:orig_category":"Fenster",
    "sg:phone":"+43 4359 28022",
    "sg:postcode":"9463",
    "sg:province":"K\u00e4rnten",
    "wof:name":"Kopp Gottfried",
    "wof:placetype":"venue"
},
  "geometry": {"coordinates":[14.7406215668,47.0075035095],"type":"Point"}
}