{
  "type": "Feature",
  "properties": {
    "iso:country":"AT",
    "sg:address":"Rautenkranzgasse 38",
    "sg:city":"Wien",
    "sg:classifiers":[
        {
            "category":"Professional",
            "subcategory":"Art Services",
            "type":"Services"
        }
    ],
    "sg:phone":"+43 1 2711668",
    "sg:postcode":"1210",
    "sg:province":"Wien",
    "sg:tags":[
        "metalwork"
    ],
    "sg:website":"members.aon.at/pach.gmbh",
    "wof:name":"Pach Ges.m.b.H.",
    "wof:placetype":"venue"
},
  "geometry": {"coordinates":[16.409828186,48.2512207031],"type":"Point"}
}