{
  "type": "Feature",
  "properties": {
    "addr:full":"Hoher Markt 5 Wien Wien 1010",
    "addr:housenumber":"5",
    "addr:postcode":"1010",
    "addr:street":"Hoher Markt",
    "iso:country":"AT",
    "sg:address":"Hoher Markt 5",
    "sg:city":"Wien",
    "sg:orig_category":"Papier- U Schreibwaren / Einzelhandel",
    "sg:phone":"+43 1 5332471",
    "sg:postcode":"1010",
    "sg:province":"Wien",
    "wof:name":"Oswald Steiner & Comp KEG",
    "wof:placetype":"venue"
},
  "geometry": {"coordinates":[16.3721065521,48.2110977173],"type":"Point"}
}