{
  "type": "Feature",
  "properties": {
    "iso:country":"AT",
    "sg:address":"Kirchenpl 13",
    "sg:city":"Gro\u00df-Enzersdorf",
    "sg:orig_category":"Dachdeckereien",
    "sg:phone":"+43 2249 2626",
    "sg:postcode":"2301",
    "sg:province":"Nieder\u00f6sterreich",
    "wof:name":"Schneider Heinz",
    "wof:placetype":"venue"
},
  "geometry": {"coordinates":[16.549829483,48.2035865784],"type":"Point"}
}