{
  "type": "Feature",
  "properties": {
    "addr:full":"Favoritenstr 41 Wien Wien 1040",
    "addr:housenumber":"41",
    "addr:postcode":"1040",
    "addr:street":"Favoritenstr",
    "iso:country":"AT",
    "sg:address":"Favoritenstr 41",
    "sg:city":"Wien",
    "sg:orig_category":"Schuhreparatur",
    "sg:phone":"+43 1 9690221",
    "sg:postcode":"1040",
    "sg:province":"Wien",
    "wof:name":"Wawrzynski Robert",
    "wof:placetype":"venue"
},
  "geometry": {"coordinates":[16.3733444214,48.18800354],"type":"Point"}
}