{
  "type": "Feature",
  "properties": {
    "addr:full":"Schleife 9 Rankweil Vorarlberg 6830",
    "addr:housenumber":"9",
    "addr:postcode":"6830",
    "addr:street":"Schleife",
    "iso:country":"AT",
    "sg:address":"Schleife 9",
    "sg:city":"Rankweil",
    "sg:orig_category":"Optiker",
    "sg:phone":"+43 4355 2243312",
    "sg:postcode":"6830",
    "sg:province":"Vorarlberg",
    "wof:name":"Der Brillenmacher - Hofbauer Thomas KEG",
    "wof:placetype":"venue"
},
  "geometry": {"coordinates":[9.6428499222,47.2721366882],"type":"Point"}
}