{
  "type": "Feature",
  "properties": {
    "addr:full":"Penzinger Str 36-38 Wien Wien 1140",
    "addr:postcode":"36-38;1140",
    "addr:street":"Str",
    "iso:country":"AT",
    "sg:address":"Penzinger Str 36-38",
    "sg:city":"Wien",
    "sg:orig_category":"Baumeister",
    "sg:phone":"+43 1 8942369",
    "sg:postcode":"1140",
    "sg:province":"Wien",
    "wof:name":"Renyi Paul Bmstr Ing",
    "wof:placetype":"venue"
},
  "geometry": {"coordinates":[16.3100280762,48.1897621155],"type":"Point"}
}