{
  "type": "Feature",
  "properties": {
    "addr:full":"Werner-Bader-Str 8 B\u00fcrmoos Salzburg 5111",
    "addr:housenumber":"8",
    "addr:postcode":"5111",
    "addr:street":"Werner-Bader-Str;Salzburg",
    "iso:country":"AT",
    "sg:address":"Werner-Bader-Str 8",
    "sg:city":"B\u00fcrmoos",
    "sg:orig_category":"Rohstoffe",
    "sg:phone":"+43 6274 20176",
    "sg:postcode":"5111",
    "sg:province":"Salzburg",
    "wof:name":"Frenkenberger Rohstoffhandels GmbH",
    "wof:placetype":"venue"
},
  "geometry": {"coordinates":[12.9329328537,47.9889907837],"type":"Point"}
}