{
  "type": "Feature",
  "properties": {
    "addr:full":"Innsbrucker Bundesstr Wals Salzburg 5071",
    "addr:postcode":"5071",
    "addr:street":"Wals",
    "iso:country":"AT",
    "sg:address":"Innsbrucker Bundesstr",
    "sg:city":"Wals",
    "sg:orig_category":"Friseure U Frisiersalons",
    "sg:phone":"+43 4366 2854969",
    "sg:postcode":"5071",
    "sg:province":"Salzburg",
    "wof:name":"Coiffeur Sturmayr",
    "wof:placetype":"venue"
},
  "geometry": {"coordinates":[12.9646148682,47.7810821533],"type":"Point"}
}