{
  "type": "Feature",
  "properties": {
    "addr:full":"Nr 20A K\u00f6ttmannsdorf K\u00e4rnten 9071",
    "addr:postcode":"9071",
    "addr:street":"Nr 20A Koettmannsdorf Kaernten",
    "iso:country":"AT",
    "sg:address":"Nr 20A",
    "sg:city":"K\u00f6ttmannsdorf",
    "sg:orig_category":"Graveure",
    "sg:phone":"+43 4220 24842",
    "sg:postcode":"9071",
    "sg:province":"K\u00e4rnten",
    "wof:name":"Binder Reinhard - Waffengraveur",
    "wof:placetype":"venue"
},
  "geometry": {"coordinates":[14.2330503464,46.5611495972],"type":"Point"}
}