{
  "type": "Feature",
  "properties": {
    "addr:full":"Opernrg. 5 Top 412 Wien Wien 1010",
    "addr:housenumber":"5 top 412",
    "addr:postcode":"1010",
    "addr:street":"Opernrg.",
    "iso:country":"AT",
    "sg:address":"Opernrg. 5 Top 412",
    "sg:city":"Wien",
    "sg:classifiers":[
        {
            "category":"Professional",
            "subcategory":"Computer Services",
            "type":"Services"
        }
    ],
    "sg:phone":"+43 4315 80170",
    "sg:postcode":"1010",
    "sg:province":"Wien",
    "sg:tags":[
        "information",
        "technology"
    ],
    "wof:name":"3COM GESMBH",
    "wof:placetype":"venue"
},
  "geometry": {"coordinates":[16.3688049316,48.2025489807],"type":"Point"}
}