{
  "type": "Feature",
  "properties": {
    "addr:full":"Hub 2 Mettmach Ober\u00f6sterreich 4931",
    "addr:housenumber":"2",
    "addr:postcode":"4931",
    "addr:street":"Hub",
    "iso:country":"AT",
    "sg:address":"Hub 2",
    "sg:city":"Mettmach",
    "sg:orig_category":"Handelsagenturen",
    "sg:phone":"+43 4377 555250",
    "sg:postcode":"4931",
    "sg:province":"Ober\u00f6sterreich",
    "wof:name":"Spindler Josef - L\u00fcftungen - Grassamen",
    "wof:placetype":"venue"
},
  "geometry": {"coordinates":[13.3344297409,48.1821708679],"type":"Point"}
}