{
  "type": "Feature",
  "properties": {
    "addr:full":"Pfelzgarten 9 Krenglbach Ober\u00f6sterreich 4631",
    "addr:housenumber":"9",
    "addr:postcode":"4631",
    "addr:street":"Pfelzgarten",
    "iso:country":"AT",
    "sg:address":"Pfelzgarten 9",
    "sg:city":"Krenglbach",
    "sg:orig_category":"Werbegrafik- U Grafik-Design",
    "sg:phone":"+43 7249 46946",
    "sg:postcode":"4631",
    "sg:province":"Ober\u00f6sterreich",
    "wof:name":"Butler-Starlinger Christa",
    "wof:placetype":"venue"
},
  "geometry": {"coordinates":[13.9726028442,48.1947288513],"type":"Point"}
}