{
  "type": "Feature",
  "properties": {
    "iso:country":"AT",
    "sg:address":"Triftstr 22",
    "sg:city":"Weiden am See",
    "sg:orig_category":"Installationsunternehmen",
    "sg:phone":"+43 2167 72030",
    "sg:postcode":"7121",
    "sg:province":"Burgenland",
    "wof:name":"Taschner Kurt GesmbH",
    "wof:placetype":"venue"
},
  "geometry": {"coordinates":[16.8733139038,47.9269104004],"type":"Point"}
}