{
  "type": "Feature",
  "properties": {
    "iso:country":"AT",
    "sg:address":"Alpendorfstr 31",
    "sg:city":"St. Johann im Pongau",
    "sg:classifiers":[
        {
            "category":"Travel",
            "subcategory":"Hotels & Motels",
            "type":"Entertainment"
        }
    ],
    "sg:phone":"+43 6412 56460",
    "sg:postcode":"5600",
    "sg:province":"Salzburg",
    "wof:name":"Hotel Restaurant Alpenhof",
    "wof:placetype":"venue"
},
  "geometry": {"coordinates":[13.2004947662,47.3166999817],"type":"Point"}
}