{
  "type": "Feature",
  "properties": {
    "addr:full":"Weitersfelden Ober\u00f6sterreich 4272",
    "addr:postcode":"4272",
    "addr:street":"Oberoesterreich",
    "iso:country":"AT",
    "sg:city":"Weitersfelden",
    "sg:orig_category":"Tankstellen",
    "sg:phone":"+43 7952 6217",
    "sg:postcode":"4272",
    "sg:province":"Ober\u00f6sterreich",
    "wof:name":"Shell Austria GmbH",
    "wof:placetype":"venue"
},
  "geometry": {"coordinates":[14.7282371521,48.4773292542],"type":"Point"}
}