{
  "type": "Feature",
  "properties": {
    "iso:country":"AT",
    "sg:address":"Markt 23 T",
    "sg:city":"M\u00fchldorf",
    "sg:classifiers":[
        {
            "category":"Home & Garden",
            "subcategory":"Building Materials",
            "type":"Retail Goods"
        }
    ],
    "sg:phone":"+43 2713 8259",
    "sg:postcode":"3622",
    "sg:province":"Nieder\u00f6sterreich",
    "sg:tags":[
        "railing",
        "balcony"
    ],
    "sg:website":"metallbau-hick.at",
    "wof:name":"Ing. Gerald Hick",
    "wof:placetype":"venue"
},
  "geometry": {"coordinates":[15.6017103195,48.0229492188],"type":"Point"}
}