{
  "type": "Feature",
  "properties": {
    "iso:country":"AT",
    "sg:address":"General Keyes-Str 28/8",
    "sg:city":"Salzburg",
    "sg:classifiers":[
        {
            "category":"Organizations",
            "subcategory":"Political Organization",
            "type":"Services"
        }
    ],
    "sg:phone":"+43 4366 2431838",
    "sg:postcode":"5020",
    "sg:province":"Salzburg",
    "sg:tags":[
        "mediation"
    ],
    "wof:name":"Ainz Gerhard MMag - Sozial- u Raumforschung - Mediation",
    "wof:placetype":"venue"
},
  "geometry": {"coordinates":[13.0233869553,47.8161277771],"type":"Point"}
}