{
  "type": "Feature",
  "properties": {
    "iso:country":"AT",
    "sg:address":"Durisolstr 1",
    "sg:city":"Wels",
    "sg:orig_category":"Bauunternehmen",
    "sg:phone":"+43 4372 42440080",
    "sg:postcode":"4600",
    "sg:province":"Ober\u00f6sterreich",
    "wof:name":"Sackmaier Bau- u InstallationsgesmbH",
    "wof:placetype":"venue"
},
  "geometry": {"coordinates":[14.0084609985,48.1513252258],"type":"Point"}
}