{
  "type": "Feature",
  "properties": {
    "iso:country":"AT",
    "sg:address":"Hauptpl 3",
    "sg:city":"Bad Hall",
    "sg:orig_category":"Altwaren",
    "sg:phone":"+43 7258 5450",
    "sg:postcode":"4540",
    "sg:province":"Ober\u00f6sterreich",
    "wof:name":"ALLERHAND ANTIKES S\u00f6llner KEG",
    "wof:placetype":"venue"
},
  "geometry": {"coordinates":[14.2082986832,48.0352668762],"type":"Point"}
}