{
  "type": "Feature",
  "properties": {
    "addr:full":"Kartause 1 Gaming Nieder\u00f6sterreich 3292",
    "addr:housenumber":"1",
    "addr:postcode":"3292",
    "addr:street":"Kartause",
    "iso:country":"AT",
    "sg:address":"Kartause 1",
    "sg:city":"Gaming",
    "sg:classifiers":[
        {
            "category":"Travel",
            "subcategory":"Hotels & Motels",
            "type":"Entertainment"
        }
    ],
    "sg:phone":"+43 7485 984660",
    "sg:postcode":"3292",
    "sg:province":"Nieder\u00f6sterreich",
    "wof:name":"Hotel Kartause Gaming",
    "wof:placetype":"venue"
},
  "geometry": {"coordinates":[15.0819988251,47.9233779907],"type":"Point"}
}