{
  "type": "Feature",
  "properties": {
    "addr:full":"Dieselstr. 2 Wels Ober\u00f6sterreich 4600",
    "addr:housenumber":"2",
    "addr:postcode":"4600",
    "addr:street":"Dieselstr.;Oberoesterreich",
    "iso:country":"AT",
    "sg:address":"Dieselstr. 2",
    "sg:city":"Wels",
    "sg:classifiers":[
        {
            "category":"Manufacturing",
            "subcategory":"Metals",
            "type":"Manufacturing & Wholesale Goods"
        }
    ],
    "sg:phone":"+43 4372 42406",
    "sg:postcode":"4600",
    "sg:province":"Ober\u00f6sterreich",
    "sg:tags":[
        "metallurgy",
        "metalworking"
    ],
    "wof:name":"VAM GMBH & CO ANLAGENTECHNIK U. MONTAGEN",
    "wof:placetype":"venue"
},
  "geometry": {"coordinates":[14.0508298874,48.1581993103],"type":"Point"}
}