{
  "type": "Feature",
  "properties": {
    "addr:full":"Rennweg 38 Wien Wien 1030",
    "addr:housenumber":"38",
    "addr:postcode":"1030",
    "addr:street":"Rennweg",
    "iso:country":"AT",
    "sg:address":"Rennweg 38",
    "sg:city":"Wien",
    "sg:orig_category":"Friseure U Frisiersalons",
    "sg:phone":"+43 1 7981096",
    "sg:postcode":"1030",
    "sg:province":"Wien",
    "wof:name":"Friseur Ma-Hair",
    "wof:placetype":"venue"
},
  "geometry": {"coordinates":[16.3891487122,48.1936836243],"type":"Point"}
}