{
  "type": "Feature",
  "properties": {
    "addr:full":"Krottendorf 17 Ettendorf K\u00e4rnten 9472",
    "addr:housenumber":"17",
    "addr:postcode":"9472",
    "addr:street":"Krottendorf;Kaernten",
    "iso:country":"AT",
    "sg:address":"Krottendorf 17",
    "sg:city":"Ettendorf",
    "sg:classifiers":[
        {
            "category":"Manufacturing",
            "subcategory":"Wood Products",
            "type":"Manufacturing & Wholesale Goods"
        }
    ],
    "sg:phone":"+43 4356 8241",
    "sg:postcode":"9472",
    "sg:province":"K\u00e4rnten",
    "sg:tags":[
        "lumber"
    ],
    "wof:name":"Cimenti KG",
    "wof:placetype":"venue"
},
  "geometry": {"coordinates":[14.9406433105,46.6682090759],"type":"Point"}
}