{
  "type": "Feature",
  "properties": {
    "iso:country":"AT",
    "sg:address":"Stadtpl 7",
    "sg:city":"Grein",
    "sg:orig_category":"Tourismusinformation U -Organisationen",
    "sg:phone":"+43 7268 7055",
    "sg:postcode":"4360",
    "sg:province":"Ober\u00f6sterreich",
    "wof:name":"Tourismusverband Grein",
    "wof:placetype":"venue"
},
  "geometry": {"coordinates":[14.8549289703,48.2274665833],"type":"Point"}
}