{
  "type": "Feature",
  "properties": {
    "iso:country":"AT",
    "sg:address":"Campus 21 F14202",
    "sg:city":"Brunn am Gebirge",
    "sg:orig_category":"Reproanstalten",
    "sg:phone":"+43 1 866702231",
    "sg:postcode":"2345",
    "sg:province":"Nieder\u00f6sterreich",
    "wof:name":"Iwaves - Cross Media Publishing GesmbH",
    "wof:placetype":"venue"
},
  "geometry": {"coordinates":[16.2839355469,48.107170105],"type":"Point"}
}