{
  "type": "Feature",
  "properties": {
    "addr:full":"Payerstetten 6 Leiben Nieder\u00f6sterreich 3652",
    "addr:housenumber":"6",
    "addr:postcode":"3652",
    "addr:street":"Payerstetten",
    "iso:country":"AT",
    "sg:address":"Payerstetten 6",
    "sg:city":"Leiben",
    "sg:classifiers":[
        {
            "category":"Home & Garden",
            "subcategory":"Building Materials",
            "type":"Retail Goods"
        }
    ],
    "sg:phone":"+43 4327 5272122",
    "sg:postcode":"3652",
    "sg:province":"Nieder\u00f6sterreich",
    "sg:tags":[
        "baustoffe",
        "-material",
        "u"
    ],
    "wof:name":"Kernstock Andreas",
    "wof:placetype":"venue"
},
  "geometry": {"coordinates":[15.2741317749,48.2452430725],"type":"Point"}
}