{
  "type": "Feature",
  "properties": {
    "iso:country":"AT",
    "sg:address":"Roseggerstr 26",
    "sg:city":"Bruck an der Mur",
    "sg:orig_category":"Schneidereien",
    "sg:phone":"+43 4338 6252643",
    "sg:postcode":"8600",
    "sg:province":"Steiermark",
    "wof:name":"Unterreiner Marlies",
    "wof:placetype":"venue"
},
  "geometry": {"coordinates":[15.2724075317,47.4100112915],"type":"Point"}
}