{
  "type": "Feature",
  "properties": {
    "addr:full":"Wiener Strasse 7 Lockenhaus Burgenland 7442",
    "addr:housenumber":"7",
    "addr:postcode":"7442",
    "addr:street":"Wiener Strasse",
    "iso:country":"AT",
    "sg:address":"Wiener Strasse 7",
    "sg:city":"Lockenhaus",
    "sg:classifiers":[
        {
            "category":"Building & Trades",
            "subcategory":"Plumbing",
            "type":"Services"
        }
    ],
    "sg:phone":"+43 2616 2000",
    "sg:postcode":"7442",
    "sg:province":"Burgenland",
    "sg:tags":[
        "supraregional",
        "gas"
    ],
    "sg:website":"joseffuchs.at",
    "wof:name":"Josef Fuchs",
    "wof:placetype":"venue"
},
  "geometry": {"coordinates":[16.4179325104,47.4097175598],"type":"Point"}
}