{
  "type": "Feature",
  "properties": {
    "addr:full":"Kuchl Salzburg 5431",
    "addr:postcode":"5431",
    "iso:country":"AT",
    "sg:city":"Kuchl",
    "sg:classifiers":[
        {
            "category":"Landmark",
            "subcategory":"Marketplace",
            "type":"Public Place"
        }
    ],
    "sg:phone":"+43 6244 6378",
    "sg:postcode":"5431",
    "sg:province":"Salzburg",
    "sg:tags":[
        "industry",
        "part",
        "bought-in",
        "furniture"
    ],
    "sg:website":"haagn.at",
    "wof:name":"Haagn Dreh- und Fr\u00e4steile aus Holz",
    "wof:placetype":"venue"
},
  "geometry": {"coordinates":[13.1438808441,47.625667572],"type":"Point"}
}