{
  "type": "Feature",
  "properties": {
    "iso:country":"AT",
    "sg:address":"Ried 27",
    "sg:city":"Koblach",
    "sg:orig_category":"Elektroinstallationsunternehmen",
    "sg:phone":"+43 5523 512050",
    "sg:postcode":"6842",
    "sg:province":"Vorarlberg",
    "wof:name":"Kopf Anton",
    "wof:placetype":"venue"
},
  "geometry": {"coordinates":[9.6151456833,47.316986084],"type":"Point"}
}