{
  "type": "Feature",
  "properties": {
    "addr:full":"Leesdorfer Hauptstr 85 Baden Nieder\u00f6sterreich 2500",
    "addr:housenumber":"85",
    "addr:postcode":"2500",
    "addr:street":"Leesdorfer Hauptstr;Niederoesterreich",
    "iso:country":"AT",
    "sg:address":"Leesdorfer Hauptstr 85",
    "sg:city":"Baden",
    "sg:orig_category":"Wasseraufbereitung U -Reinigung",
    "sg:phone":"+43 4322 5282055",
    "sg:postcode":"2500",
    "sg:province":"Nieder\u00f6sterreich",
    "sg:website":"eurowater.at",
    "wof:name":"Eurowater Wasseraufbereitung GesmbH",
    "wof:placetype":"venue"
},
  "geometry": {"coordinates":[16.2507019043,48.0075874329],"type":"Point"}
}