{
  "type": "Feature",
  "properties": {
    "addr:full":"Waltersdorfer Str 55 Baden Nieder\u00f6sterreich 2500",
    "addr:housenumber":"55",
    "addr:postcode":"2500",
    "addr:street":"Waltersdorfer Str;Niederoesterreich",
    "iso:country":"AT",
    "sg:address":"Waltersdorfer Str 55",
    "sg:city":"Baden",
    "sg:orig_category":"Fleischhauereien",
    "sg:phone":"+43 4322 52802940",
    "sg:postcode":"2500",
    "sg:province":"Nieder\u00f6sterreich",
    "wof:name":"Tr\u00fcnkel Leopold GmbH",
    "wof:placetype":"venue"
},
  "geometry": {"coordinates":[16.2515277863,47.9996414185],"type":"Point"}
}