{
  "type": "Feature",
  "properties": {
    "iso:country":"AT",
    "sg:address":"Alpenlandstr 18",
    "sg:city":"Lilienfeld",
    "sg:orig_category":"Hufschmiede",
    "sg:phone":"+43 2762 52059",
    "sg:postcode":"3180",
    "sg:province":"Nieder\u00f6sterreich",
    "wof:name":"Solomon Charles",
    "wof:placetype":"venue"
},
  "geometry": {"coordinates":[15.5839729309,48.0119857788],"type":"Point"}
}