{
  "type": "Feature",
  "properties": {
    "iso:country":"AT",
    "sg:address":"Eigenhofen 3b",
    "sg:city":"Zirl",
    "sg:orig_category":"Atemtherapie",
    "sg:phone":"+43 4352 3852192",
    "sg:postcode":"6170",
    "sg:province":"Tirol",
    "wof:name":"Kraml Ilse",
    "wof:placetype":"venue"
},
  "geometry": {"coordinates":[11.2056083679,47.281463623],"type":"Point"}
}