{
  "type": "Feature",
  "properties": {
    "addr:full":"Mariahilfstr 22/7 Innsbruck Tirol 6020",
    "addr:housenumber":"22 / 7",
    "addr:postcode":"6020",
    "addr:street":"Mariahilfstr;Tirol",
    "iso:country":"AT",
    "sg:address":"Mariahilfstr 22/7",
    "sg:city":"Innsbruck",
    "sg:orig_category":"Architekten",
    "sg:phone":"+43 512 2801800",
    "sg:postcode":"6020",
    "sg:province":"Tirol",
    "wof:name":"Benedikter-Fuchs DI ZT KEG",
    "wof:placetype":"venue"
},
  "geometry": {"coordinates":[11.3893289566,47.2684020996],"type":"Point"}
}