{
  "type": "Feature",
  "properties": {
    "addr:full":"Hasnerstr 18 Linz Ober\u00f6sterreich 4020",
    "addr:housenumber":"18",
    "addr:postcode":"4020",
    "addr:street":"Hasnerstr",
    "iso:country":"AT",
    "sg:address":"Hasnerstr 18",
    "sg:city":"Linz",
    "sg:orig_category":"Steuerberatung",
    "sg:phone":"+43 732 656051",
    "sg:postcode":"4020",
    "sg:province":"Ober\u00f6sterreich",
    "wof:name":"Schlesinger Gerhard",
    "wof:placetype":"venue"
},
  "geometry": {"coordinates":[14.2976131439,48.2858276367],"type":"Point"}
}