{
  "type": "Feature",
  "properties": {
    "iso:country":"AT",
    "sg:address":"Ringg 13",
    "sg:city":"Lasberg",
    "sg:orig_category":"Tischlereien",
    "sg:phone":"+43 4379 477240",
    "sg:postcode":"4291",
    "sg:province":"Ober\u00f6sterreich",
    "wof:name":"Prammer Karl",
    "wof:placetype":"venue"
},
  "geometry": {"coordinates":[14.5407247543,48.4710693359],"type":"Point"}
}