{
  "type": "Feature",
  "properties": {
    "iso:country":"AT",
    "sg:address":"Windhof 70",
    "sg:city":"Semriach",
    "sg:orig_category":"Pensionen / Privatzimmer",
    "sg:phone":"+43 3127 8351",
    "sg:postcode":"8102",
    "sg:province":"Steiermark",
    "wof:name":"Ponyhof",
    "wof:placetype":"venue"
},
  "geometry": {"coordinates":[15.4145851135,47.2089958191],"type":"Point"}
}