{
  "type": "Feature",
  "properties": {
    "iso:country":"AT",
    "sg:address":"Elisabethstr 1B",
    "sg:city":"Salzburg",
    "sg:orig_category":"Physiotherapie",
    "sg:phone":"+43 662 873089",
    "sg:postcode":"5020",
    "sg:province":"Salzburg",
    "wof:name":"Nie\u00dfner Andrea Dipl-PT",
    "wof:placetype":"venue"
},
  "geometry": {"coordinates":[13.0415315628,47.8100166321],"type":"Point"}
}