{
  "type": "Feature",
  "properties": {
    "addr:full":"Altachweg 501 Saalbach Salzburg 5753",
    "addr:housenumber":"501",
    "addr:postcode":"5753",
    "addr:street":"Altachweg;Salzburg",
    "iso:country":"AT",
    "sg:address":"Altachweg 501",
    "sg:city":"Saalbach",
    "sg:orig_category":"Pensionen / Privatzimmer",
    "sg:phone":"+43 6541 66780",
    "sg:postcode":"5753",
    "sg:province":"Salzburg",
    "wof:name":"Pension Gabi",
    "wof:placetype":"venue"
},
  "geometry": {"coordinates":[12.622713089,47.3903427124],"type":"Point"}
}