{
  "type": "Feature",
  "properties": {
    "addr:full":"Amstettner Str 38 Mauer-\u00d6hling Nieder\u00f6sterreich 3362",
    "addr:postcode":"3362",
    "addr:street":"Str 38 Mauer-Oehling",
    "iso:country":"AT",
    "sg:address":"Amstettner Str 38",
    "sg:city":"Mauer-\u00d6hling",
    "sg:orig_category":"Bauunternehmen",
    "sg:phone":"+43 7475 56318",
    "sg:postcode":"3362",
    "sg:province":"Nieder\u00f6sterreich",
    "sg:website":"hts-bau.at",
    "wof:name":"HTS Bau GmbH",
    "wof:placetype":"venue"
},
  "geometry": {"coordinates":[14.8065690994,48.0985298157],"type":"Point"}
}