{
  "type": "Feature",
  "properties": {
    "iso:country":"AT",
    "sg:address":"Weizer Strasse 9",
    "sg:city":"Gleisdorf",
    "sg:classifiers":[
        {
            "category":"Communications",
            "subcategory":"Film & Video Production",
            "type":"Services"
        }
    ],
    "sg:phone":"+43 3112 5411",
    "sg:postcode":"8200",
    "sg:province":"Steiermark",
    "sg:tags":[
        "photo",
        "architectural"
    ],
    "sg:website":"artfotos.at",
    "wof:name":"Schrotter GmbH",
    "wof:placetype":"venue"
},
  "geometry": {"coordinates":[15.7083806992,47.1066131592],"type":"Point"}
}