{
  "type": "Feature",
  "properties": {
    "iso:country":"AT",
    "sg:address":"Gartenaug. 5 ",
    "sg:city":"Krems an der Donau",
    "sg:classifiers":[
        {
            "category":"Banks & Credit Unions",
            "subcategory":"Bank",
            "type":"Services"
        }
    ],
    "sg:phone":"+43 4327 328830",
    "sg:postcode":"3500",
    "sg:province":"Nieder\u00f6sterreich",
    "sg:tags":[
        "banking",
        "institution"
    ],
    "wof:name":"VOLKSBANK KREMS-ZWETTL AG",
    "wof:placetype":"venue"
},
  "geometry": {"coordinates":[15.5965108871,48.4088058472],"type":"Point"}
}