{
  "type": "Feature",
  "properties": {
    "addr:full":"Laaer-Berg-Str 220 Wien Wien 1100",
    "addr:housenumber":"220",
    "addr:postcode":"1100",
    "iso:country":"AT",
    "sg:address":"Laaer-Berg-Str 220",
    "sg:city":"Wien",
    "sg:orig_category":"Lebensmittel / Einzelhandel",
    "sg:phone":"+43 1 6884661",
    "sg:postcode":"1100",
    "sg:province":"Wien",
    "wof:name":"Pratschner Herbert",
    "wof:placetype":"venue"
},
  "geometry": {"coordinates":[16.3967475891,48.1527633667],"type":"Point"}
}