{
  "type": "Feature",
  "properties": {
    "addr:full":"Am Lissl 21 Mistelbach Nieder\u00f6sterreich 2130",
    "addr:housenumber":"21",
    "addr:postcode":"2130",
    "addr:street":"Am Lissl;Niederoesterreich",
    "iso:country":"AT",
    "sg:address":"Am Lissl 21",
    "sg:city":"Mistelbach",
    "sg:orig_category":"Internet, Internetverzeichnisse U Suchmaschinen",
    "sg:phone":"+43 2572 32924",
    "sg:postcode":"2130",
    "sg:province":"Nieder\u00f6sterreich",
    "sg:website":"http://www.gewinn-spiele.at/dwIndex.htm",
    "wof:name":"www.gewinn-spiele.at",
    "wof:placetype":"venue"
},
  "geometry": {"coordinates":[16.6005096436,48.595375061],"type":"Point"}
}