{
  "type": "Feature",
  "properties": {
    "addr:full":"Poschacher Str 7 St. Georgen an der Gusen Ober\u00f6sterreich 4222",
    "addr:housenumber":"7",
    "addr:postcode":"4222",
    "addr:street":"Str",
    "iso:country":"AT",
    "sg:address":"Poschacher Str 7",
    "sg:city":"St. Georgen an der Gusen",
    "sg:orig_category":"Natursteine U -Platten",
    "sg:phone":"+43 4372 3733330",
    "sg:postcode":"4222",
    "sg:province":"Ober\u00f6sterreich",
    "wof:name":"Poschacher Natursteinwerke GmbH & Co KG",
    "wof:placetype":"venue"
},
  "geometry": {"coordinates":[14.4693050385,48.2546310425],"type":"Point"}
}