{
  "type": "Feature",
  "properties": {
    "iso:country":"AT",
    "sg:address":"Nibelungenstr 68",
    "sg:city":"Persenbeug",
    "sg:orig_category":"Tankstellen",
    "sg:phone":"+43 7412 52687",
    "sg:postcode":"3680",
    "sg:province":"Nieder\u00f6sterreich",
    "wof:name":"OMV AG",
    "wof:placetype":"venue"
},
  "geometry": {"coordinates":[15.0966682434,48.1899719238],"type":"Point"}
}