{
  "type": "Feature",
  "properties": {
    "iso:country":"AT",
    "sg:address":"Hauptstr 59",
    "sg:city":"Siegendorf im Burgenland",
    "sg:orig_category":"\u00c3\u201erzte / F Allgemeinmedizin",
    "sg:phone":"+43 2687 48111",
    "sg:postcode":"7011",
    "sg:province":"Burgenland",
    "wof:name":"Jagnjic Waltraud Maria Dr",
    "wof:placetype":"venue"
},
  "geometry": {"coordinates":[16.5184707642,47.7662391663],"type":"Point"}
}