{
  "type": "Feature",
  "properties": {
    "addr:full":"Troststr 100 Wien Wien 1100",
    "addr:housenumber":"100",
    "addr:postcode":"1100",
    "iso:country":"AT",
    "sg:address":"Troststr 100",
    "sg:city":"Wien",
    "sg:orig_category":"Waren Aller Art",
    "sg:phone":"+43 1 6040415",
    "sg:postcode":"1100",
    "sg:province":"Wien",
    "wof:name":"Lemis HandelsgesmbH",
    "wof:placetype":"venue"
},
  "geometry": {"coordinates":[16.3560638428,48.1719245911],"type":"Point"}
}