{
  "type": "Feature",
  "properties": {
    "addr:full":"Oberdorfstr Inzing Tirol 6401",
    "addr:postcode":"6401",
    "addr:street":"Oberdorfstr;Tirol",
    "iso:country":"AT",
    "sg:address":"Oberdorfstr",
    "sg:city":"Inzing",
    "sg:orig_category":"Tischlereien",
    "sg:phone":"+43 5238 88084",
    "sg:postcode":"6401",
    "sg:province":"Tirol",
    "wof:name":"Prantl Christian",
    "wof:placetype":"venue"
},
  "geometry": {"coordinates":[11.2036771774,47.2706336975],"type":"Point"}
}