{
  "type": "Feature",
  "properties": {
    "iso:country":"AT",
    "sg:address":"Hauptstr 31",
    "sg:city":"Frauenkirchen",
    "sg:orig_category":"Damenmoden",
    "sg:phone":"+43 2172 7150",
    "sg:postcode":"7132",
    "sg:province":"Burgenland",
    "wof:name":"Zimm Mode",
    "wof:placetype":"venue"
},
  "geometry": {"coordinates":[16.9242782593,47.8379745483],"type":"Point"}
}