{
  "type": "Feature",
  "properties": {
    "addr:full":"Gabelsbergerstr 1 Innsbruck Tirol 6020",
    "addr:housenumber":"1",
    "addr:postcode":"6020",
    "addr:street":"Gabelsbergerstr;Tirol",
    "iso:country":"AT",
    "sg:address":"Gabelsbergerstr 1",
    "sg:city":"Innsbruck",
    "sg:orig_category":"Hauptschulen",
    "sg:phone":"+43 512 345121",
    "sg:postcode":"6020",
    "sg:province":"Tirol",
    "wof:name":"Hauptschule Gabelsbergergasse",
    "wof:placetype":"venue"
},
  "geometry": {"coordinates":[11.4101276398,47.2693214417],"type":"Point"}
}