{
  "type": "Feature",
  "properties": {
    "addr:full":"Oggauer Strasse 12 Rust Burgenland 7071",
    "addr:housenumber":"12",
    "addr:postcode":"7071",
    "addr:street":"Oggauer Strasse",
    "iso:country":"AT",
    "sg:address":"Oggauer Strasse 12",
    "sg:city":"Rust",
    "sg:orig_category":"CarpenterS Work Supraregional",
    "sg:phone":"+43 2685 248",
    "sg:postcode":"7071",
    "sg:province":"Burgenland",
    "wof:name":"Ernst Gruber",
    "wof:placetype":"venue"
},
  "geometry": {"coordinates":[16.6722717285,47.8025054932],"type":"Point"}
}