{
  "type": "Feature",
  "properties": {
    "addr:full":"Anzengruberstr 15 Innsbruck Tirol 6020",
    "addr:housenumber":"15",
    "addr:postcode":"6020",
    "addr:street":"Anzengruberstr;Tirol",
    "iso:country":"AT",
    "sg:address":"Anzengruberstr 15",
    "sg:city":"Innsbruck",
    "sg:orig_category":"Immobilienmakler",
    "sg:phone":"+43 4351 2932576",
    "sg:postcode":"6020",
    "sg:province":"Tirol",
    "wof:name":"TIV Treuhand-Immobilien- u VerwaltungsgesmbH",
    "wof:placetype":"venue"
},
  "geometry": {"coordinates":[11.4097099304,47.2619781494],"type":"Point"}
}