{
  "type": "Feature",
  "properties": {
    "addr:full":"Keutschacher Str 150 Klagenfurt-Viktring K\u00e4rnten 9073",
    "addr:housenumber":"150",
    "addr:postcode":"9073",
    "addr:street":"Klagenfurt-Viktring Kaernten",
    "iso:country":"AT",
    "sg:address":"Keutschacher Str 150",
    "sg:city":"Klagenfurt-Viktring",
    "sg:orig_category":"Massagen",
    "sg:phone":"+43 463 281464",
    "sg:postcode":"9073",
    "sg:province":"K\u00e4rnten",
    "wof:name":"Massagefachinstitut Waltraud H\u00e4usler",
    "wof:placetype":"venue"
},
  "geometry": {"coordinates":[14.2675323486,46.5916404724],"type":"Point"}
}