{
  "type": "Feature",
  "properties": {
    "iso:country":"AT",
    "sg:address":"Brixentaler Str 13",
    "sg:city":"Brixen im Thale",
    "sg:orig_category":"Tankstellen",
    "sg:phone":"+43 5334 2880",
    "sg:postcode":"6364",
    "sg:province":"Tirol",
    "wof:name":"BP Austria Marketing GmbH",
    "wof:placetype":"venue"
},
  "geometry": {"coordinates":[12.2341909409,47.444934845],"type":"Point"}
}