{
  "type": "Feature",
  "properties": {
    "iso:country":"AT",
    "sg:address":"Nr 143",
    "sg:city":"Oed",
    "sg:orig_category":"Friseure U Frisiersalons",
    "sg:phone":"+43 4374 78814",
    "sg:postcode":"3312",
    "sg:province":"Nieder\u00f6sterreich",
    "wof:name":"Fasching Sieglinde",
    "wof:placetype":"venue"
},
  "geometry": {"coordinates":[14.7418317795,48.1214790344],"type":"Point"}
}