{
  "type": "Feature",
  "properties": {
    "addr:full":"Bischofstr 15 Linz Ober\u00f6sterreich 4020",
    "addr:housenumber":"15",
    "addr:postcode":"4020",
    "addr:street":"Bischofstr",
    "iso:country":"AT",
    "sg:address":"Bischofstr 15",
    "sg:city":"Linz",
    "sg:orig_category":"\u00c3\u201enderungsschneidereien",
    "sg:phone":"+43 732 772881",
    "sg:postcode":"4020",
    "sg:province":"Ober\u00f6sterreich",
    "wof:name":"Heinzl Maria",
    "wof:placetype":"venue"
},
  "geometry": {"coordinates":[14.2875671387,48.3013877869],"type":"Point"}
}