{
  "type": "Feature",
  "properties": {
    "iso:country":"AT",
    "sg:address":"Glasereistr 26",
    "sg:city":"Uttendorf",
    "sg:orig_category":"Transportunternehmen",
    "sg:phone":"+43 7724 2463",
    "sg:postcode":"5261",
    "sg:province":"Ober\u00f6sterreich",
    "wof:name":"Neiss Erich",
    "wof:placetype":"venue"
},
  "geometry": {"coordinates":[13.1186647415,48.1521492004],"type":"Point"}
}