{
  "type": "Feature",
  "properties": {
    "addr:full":"Alter Rathauspl 12 Loosdorf Nieder\u00f6sterreich 3382",
    "addr:housenumber":"12",
    "addr:postcode":"3382",
    "addr:street":"Loosdorf Niederoesterreich",
    "iso:country":"AT",
    "sg:address":"Alter Rathauspl 12",
    "sg:city":"Loosdorf",
    "sg:classifiers":[
        {
            "category":"Restaurant",
            "type":"Food & Drink"
        }
    ],
    "sg:phone":"+43 4367 67229889",
    "sg:postcode":"3382",
    "sg:province":"Nieder\u00f6sterreich",
    "sg:tags":[
        "pizzeria"
    ],
    "wof:name":"Pizzeria Toscana + Eisdiele",
    "wof:placetype":"venue"
},
  "geometry": {"coordinates":[15.3811845779,48.1837120056],"type":"Point"}
}