{
  "type": "Feature",
  "properties": {
    "addr:full":"Vollbadg 1a/1/5 Wien Wien 1170",
    "addr:housenumber":"1a / 1 / 5",
    "addr:postcode":"1170",
    "addr:street":"Vollbadg",
    "iso:country":"AT",
    "sg:address":"Vollbadg 1a/1/5",
    "sg:city":"Wien",
    "sg:orig_category":"Psychotherapie",
    "sg:phone":"+43 4366 45020208",
    "sg:postcode":"1170",
    "sg:province":"Wien",
    "wof:name":"Kernstock-Redl Helga Mag. - Armonia-med",
    "wof:placetype":"venue"
},
  "geometry": {"coordinates":[16.3308048248,48.2193107605],"type":"Point"}
}