{
  "type": "Feature",
  "properties": {
    "addr:full":"Herrenstr 17 Linz Ober\u00f6sterreich 4020",
    "addr:housenumber":"17",
    "addr:postcode":"4020",
    "addr:street":"Herrenstr",
    "iso:country":"AT",
    "sg:address":"Herrenstr 17",
    "sg:city":"Linz",
    "sg:orig_category":"Tabaktrafiken",
    "sg:phone":"+43 732 773666",
    "sg:postcode":"4020",
    "sg:province":"Ober\u00f6sterreich",
    "wof:name":"Ku\u00dfberger Margit",
    "wof:placetype":"venue"
},
  "geometry": {"coordinates":[14.2869882584,48.3019561768],"type":"Point"}
}