{
  "type": "Feature",
  "properties": {
    "addr:full":"Villacher Str 9 Feldkirchen in K\u00e4rnten K\u00e4rnten 9560",
    "addr:housenumber":"9",
    "addr:postcode":"9560",
    "addr:street":"Str;Kaernten",
    "iso:country":"AT",
    "sg:address":"Villacher Str 9",
    "sg:city":"Feldkirchen in K\u00e4rnten",
    "sg:orig_category":"Speditionen",
    "sg:phone":"+43 4342 7629372",
    "sg:postcode":"9560",
    "sg:province":"K\u00e4rnten",
    "wof:name":"RUK Transportagentur Reich OEG",
    "wof:placetype":"venue"
},
  "geometry": {"coordinates":[14.0911579132,46.7237892151],"type":"Point"}
}