{
  "type": "Feature",
  "properties": {
    "addr:full":"Nibelungeng 7a Tulln an der Donau Nieder\u00f6sterreich 3430",
    "addr:housenumber":"7a",
    "addr:postcode":"3430",
    "addr:street":"Nibelungeng",
    "iso:country":"AT",
    "sg:address":"Nibelungeng 7a",
    "sg:city":"Tulln an der Donau",
    "sg:orig_category":"Werbeagenturen",
    "sg:phone":"+43 2272 627260",
    "sg:postcode":"3430",
    "sg:province":"Nieder\u00f6sterreich",
    "wof:name":"Friedl + Partner GesmbH",
    "wof:placetype":"venue"
},
  "geometry": {"coordinates":[16.0543346405,48.3321228027],"type":"Point"}
}