{
  "type": "Feature",
  "properties": {
    "iso:country":"AT",
    "sg:address":"Ignaz-Glaser-Strasse 53",
    "sg:city":"B\u00fcrmoos",
    "sg:classifiers":[
        {
            "category":"Wholesale",
            "subcategory":"Office Equipment",
            "type":"Manufacturing & Wholesale Goods"
        }
    ],
    "sg:phone":"+43 6274 62360",
    "sg:postcode":"5111",
    "sg:province":"Salzburg",
    "sg:tags":[
        "dental"
    ],
    "sg:website":"wh.com",
    "wof:name":"W & H Dentalwerk B\u00fcrmoos GmbH",
    "wof:placetype":"venue"
},
  "geometry": {"coordinates":[12.9209489822,47.9830436707],"type":"Point"}
}