{
  "type": "Feature",
  "properties": {
    "addr:full":"Bahnhofstr 22 Weiz Steiermark 8160",
    "addr:housenumber":"22",
    "addr:postcode":"8160",
    "addr:street":"Bahnhofstr",
    "iso:country":"AT",
    "sg:address":"Bahnhofstr 22",
    "sg:city":"Weiz",
    "sg:classifiers":[
        {
            "category":"Travel",
            "subcategory":"Hotels & Motels",
            "type":"Entertainment"
        }
    ],
    "sg:phone":"+43 3172 2208",
    "sg:postcode":"8160",
    "sg:province":"Steiermark",
    "wof:name":"Hotel Hammer",
    "wof:placetype":"venue"
},
  "geometry": {"coordinates":[15.6298217773,47.2143363953],"type":"Point"}
}