{
  "type": "Feature",
  "properties": {
    "addr:full":"Sparkassenpl 1 Matrei in Osttirol Tirol 9971",
    "addr:housenumber":"1",
    "addr:postcode":"9971",
    "addr:street":"Sparkassenpl;Tirol",
    "iso:country":"AT",
    "sg:address":"Sparkassenpl 1",
    "sg:city":"Matrei in Osttirol",
    "sg:orig_category":"Banken U Sparkassen",
    "sg:phone":"+43 4348 756650",
    "sg:postcode":"9971",
    "sg:province":"Tirol",
    "wof:name":"Lienzer Sparkasse AG",
    "wof:placetype":"venue"
},
  "geometry": {"coordinates":[12.5383901596,47.0010795593],"type":"Point"}
}