{
  "type": "Feature",
  "properties": {
    "addr:full":"Bundesstr Heliport 1 Imst Tirol 6460",
    "addr:housenumber":"1",
    "addr:postcode":"6460",
    "addr:street":"Imst Tirol",
    "iso:country":"AT",
    "sg:address":"Bundesstr Heliport 1",
    "sg:city":"Imst",
    "sg:orig_category":"Hubschrauberflugdienste",
    "sg:phone":"+43 5412 61421",
    "sg:postcode":"6460",
    "sg:province":"Tirol",
    "wof:name":"Knaus Helicopter GmbH",
    "wof:placetype":"venue"
},
  "geometry": {"coordinates":[10.737487793,47.2392234802],"type":"Point"}
}