{
  "type": "Feature",
  "properties": {
    "addr:full":"Metzgerstrasse 66 Bergheim Salzburg 5101",
    "addr:housenumber":"66",
    "addr:postcode":"5101",
    "addr:street":"Metzgerstrasse;Salzburg",
    "iso:country":"AT",
    "sg:address":"Metzgerstrasse 66",
    "sg:city":"Bergheim",
    "sg:classifiers":[
        {
            "category":"Manufacturing",
            "subcategory":"Rubber & Plastics",
            "type":"Manufacturing & Wholesale Goods"
        }
    ],
    "sg:phone":"+43 662 450767",
    "sg:postcode":"5101",
    "sg:province":"Salzburg",
    "sg:tags":[
        "galosh",
        "boot",
        "boots",
        "polyvinyl",
        "pvc",
        "chloride"
    ],
    "wof:name":"Zoth Schuhhandelsges.m.b.H.",
    "wof:placetype":"venue"
},
  "geometry": {"coordinates":[13.01521492,47.8474998474],"type":"Point"}
}