{
  "type": "Feature",
  "properties": {
    "addr:full":"Millerg 20 Wien Wien 1060",
    "addr:housenumber":"20",
    "addr:postcode":"1060",
    "addr:street":"Millerg",
    "iso:country":"AT",
    "sg:address":"Millerg 20",
    "sg:city":"Wien",
    "sg:orig_category":"Elektroinstallationsunternehmen",
    "sg:phone":"+43 1 5976223",
    "sg:postcode":"1060",
    "sg:province":"Wien",
    "wof:name":"Almar Elektroinstallationen GesmbH & Co KG",
    "wof:placetype":"venue"
},
  "geometry": {"coordinates":[16.3438243866,48.192741394],"type":"Point"}
}