{
  "type": "Feature",
  "properties": {
    "addr:full":"Nr 5 Birnbaum K\u00e4rnten 9652",
    "addr:postcode":"9652",
    "addr:street":"Nr;Birnbaum Kaernten",
    "iso:country":"AT",
    "sg:address":"Nr 5",
    "sg:city":"Birnbaum",
    "sg:orig_category":"Musikgruppen",
    "sg:phone":"+43 4716 744",
    "sg:postcode":"9652",
    "sg:province":"K\u00e4rnten",
    "wof:name":"M\u00fcllmann Andreas - Wolayersee Echo",
    "wof:placetype":"venue"
},
  "geometry": {"coordinates":[12.8650951385,46.6859817505],"type":"Point"}
}