{
  "type": "Feature",
  "properties": {
    "addr:full":"Sonnenstr 3 Langenlois Nieder\u00f6sterreich 3550",
    "addr:housenumber":"3",
    "addr:postcode":"3550",
    "addr:street":"Sonnenstr",
    "iso:country":"AT",
    "sg:address":"Sonnenstr 3",
    "sg:city":"Langenlois",
    "sg:orig_category":"Elektroinstallationsunternehmen",
    "sg:phone":"+43 2734 32320",
    "sg:postcode":"3550",
    "sg:province":"Nieder\u00f6sterreich",
    "wof:name":"Unger Harald",
    "wof:placetype":"venue"
},
  "geometry": {"coordinates":[15.6715097427,48.4781913757],"type":"Point"}
}