{
  "type": "Feature",
  "properties": {
    "addr:full":"Kainach bei Voitsberg 53 Kainach Steiermark 8573",
    "addr:housenumber":"53",
    "addr:postcode":"8573",
    "addr:street":"Kainach Bei Voitsberg",
    "iso:country":"AT",
    "sg:address":"Kainach bei Voitsberg 53",
    "sg:city":"Kainach",
    "sg:classifiers":[
        {
            "category":"Structure",
            "subcategory":"Building",
            "type":"Public Place"
        }
    ],
    "sg:phone":"+43 3148 7256",
    "sg:postcode":"8573",
    "sg:province":"Steiermark",
    "sg:tags":[
        "delivery",
        "door",
        "inside",
        "installation"
    ],
    "sg:website":"tischlereianabith.at",
    "wof:name":"G\u00fcnter Anabith",
    "wof:placetype":"venue"
},
  "geometry": {"coordinates":[15.0845594406,47.1350593567],"type":"Point"}
}