{
  "type": "Feature",
  "properties": {
    "addr:full":"St Wendelin-Pl 5 Wien Wien 1220",
    "addr:housenumber":"5",
    "addr:postcode":"1220",
    "iso:country":"AT",
    "sg:address":"St Wendelin-Pl 5",
    "sg:city":"Wien",
    "sg:orig_category":"Fotografen",
    "sg:phone":"+43 1 2036770",
    "sg:postcode":"1220",
    "sg:province":"Wien",
    "sg:website":"fotoschuster.com",
    "wof:name":"Fotostudio Richard Schuster",
    "wof:placetype":"venue"
},
  "geometry": {"coordinates":[16.4422035217,48.2497825623],"type":"Point"}
}