{
  "type": "Feature",
  "properties": {
    "addr:full":"Neunkirchner Str 34 Neunkirchen Nieder\u00f6sterreich 2620",
    "addr:housenumber":"34",
    "addr:postcode":"2620",
    "addr:street":"Str",
    "iso:country":"AT",
    "sg:address":"Neunkirchner Str 34",
    "sg:city":"Neunkirchen",
    "sg:orig_category":"Autoreparatur",
    "sg:phone":"+43 2635 62045",
    "sg:postcode":"2620",
    "sg:province":"Nieder\u00f6sterreich",
    "sg:website":"www.seat-maurer.at",
    "wof:name":"Maurer Karl jun",
    "wof:placetype":"venue"
},
  "geometry": {"coordinates":[16.0980548859,47.7119560242],"type":"Point"}
}