{
  "type": "Feature",
  "properties": {
    "addr:full":"Nr 16 Hohenwarth Nieder\u00f6sterreich 3472",
    "addr:postcode":"3472",
    "addr:street":"Nr;Hohenwarth Niederoesterreich",
    "iso:country":"AT",
    "sg:address":"Nr 16",
    "sg:city":"Hohenwarth",
    "sg:orig_category":"Weine / Einzelhandel",
    "sg:phone":"+43 2957 220",
    "sg:postcode":"3472",
    "sg:province":"Nieder\u00f6sterreich",
    "wof:name":"Schmudermayer Anton",
    "wof:placetype":"venue"
},
  "geometry": {"coordinates":[15.827583313,48.5075111389],"type":"Point"}
}