{
  "type": "Feature",
  "properties": {
    "iso:country":"AT",
    "sg:address":"W\u00f6rther Str 134",
    "sg:city":"Gloggnitz",
    "sg:orig_category":"Maler, Anstreicher U Lackierer",
    "sg:phone":"+43 2662 428920",
    "sg:postcode":"2640",
    "sg:province":"Nieder\u00f6sterreich",
    "wof:name":"Ofenb\u00f6ck Walter GesmbH",
    "wof:placetype":"venue"
},
  "geometry": {"coordinates":[15.9365577698,47.6758956909],"type":"Point"}
}