{
  "type": "Feature",
  "properties": {
    "iso:country":"AT",
    "sg:address":"Berchtesgadner Strasse 6",
    "sg:city":"Salzburg",
    "sg:classifiers":[
        {
            "category":"Home & Garden",
            "subcategory":"Building Materials",
            "type":"Retail Goods"
        }
    ],
    "sg:phone":"+43 662 824185",
    "sg:postcode":"5020",
    "sg:province":"Salzburg",
    "sg:tags":[
        "tile",
        "ceramic"
    ],
    "sg:website":"planegger.at",
    "wof:name":"Ferdinand Planegger",
    "wof:placetype":"venue"
},
  "geometry": {"coordinates":[13.0475387573,47.7813186646],"type":"Point"}
}