{
  "type": "Feature",
  "properties": {
    "addr:full":"Ballhauspl 1 Wien Wien 1010",
    "addr:housenumber":"1",
    "addr:postcode":"1010",
    "addr:street":"Ballhauspl",
    "iso:country":"AT",
    "sg:address":"Ballhauspl 1",
    "sg:city":"Wien",
    "sg:orig_category":"Non-Classified Establishments",
    "sg:phone":"+43 1 531152525",
    "sg:postcode":"1010",
    "sg:province":"Wien",
    "wof:name":"Datenschutzkommission - Datenschutzrat",
    "wof:placetype":"venue"
},
  "geometry": {"coordinates":[16.3641033173,48.208152771],"type":"Point"}
}