{
  "type": "Feature",
  "properties": {
    "addr:full":"Bahnhofstr 124 Seefeld in Tirol Tirol 6100",
    "addr:housenumber":"124",
    "addr:postcode":"6100",
    "addr:street":"Bahnhofstr;Tirol",
    "iso:country":"AT",
    "sg:address":"Bahnhofstr 124",
    "sg:city":"Seefeld in Tirol",
    "sg:classifiers":[
        {
            "category":"Travel",
            "subcategory":"Hotels & Motels",
            "type":"Entertainment"
        }
    ],
    "sg:phone":"+43 4352 1226550",
    "sg:postcode":"6100",
    "sg:province":"Tirol",
    "wof:name":"Hotel Karwendelhof",
    "wof:placetype":"venue"
},
  "geometry": {"coordinates":[11.1881799698,47.3290138245],"type":"Point"}
}