{
  "type": "Feature",
  "properties": {
    "addr:full":"Thermenpl 3 Lutzmannsburg Burgenland 7361",
    "addr:housenumber":"3",
    "addr:postcode":"7361",
    "addr:street":"Thermenpl",
    "iso:country":"AT",
    "sg:address":"Thermenpl 3",
    "sg:city":"Lutzmannsburg",
    "sg:classifiers":[
        {
            "category":"Travel",
            "subcategory":"Hotels & Motels",
            "type":"Entertainment"
        }
    ],
    "sg:phone":"+43 2615 81300",
    "sg:postcode":"7361",
    "sg:province":"Burgenland",
    "wof:name":"Apartment-Hotel SEMI BetriebsgmbH",
    "wof:placetype":"venue"
},
  "geometry": {"coordinates":[16.6599121094,47.4650802612],"type":"Point"}
}