{
  "type": "Feature",
  "properties": {
    "iso:country":"AT",
    "sg:address":"Nr 1",
    "sg:city":"Unterkohlst\u00e4tten",
    "sg:orig_category":"Non-Classified Establishments",
    "sg:phone":"+43 3354 8223",
    "sg:postcode":"7435",
    "sg:province":"Burgenland",
    "wof:name":"Evangelisches Pfarramt AB",
    "wof:placetype":"venue"
},
  "geometry": {"coordinates":[16.3263683319,47.3749008179],"type":"Point"}
}