{
  "type": "Feature",
  "properties": {
    "addr:full":"Bundesstr 8 Wals Salzburg 5071",
    "addr:housenumber":"8",
    "addr:postcode":"5071",
    "addr:street":"Bundesstr;Salzburg",
    "iso:country":"AT",
    "sg:address":"Bundesstr 8",
    "sg:city":"Wals",
    "sg:orig_category":"Registrierkassen",
    "sg:phone":"+43 662 853485",
    "sg:postcode":"5071",
    "sg:province":"Salzburg",
    "wof:name":"HS Kassen-Shop",
    "wof:placetype":"venue"
},
  "geometry": {"coordinates":[12.979839325,47.7866706848],"type":"Point"}
}