{
  "type": "Feature",
  "properties": {
    "iso:country":"AT",
    "sg:address":"Dorfstr 32",
    "sg:city":"Lienz",
    "sg:orig_category":"Tischlereien",
    "sg:phone":"+43 4852 64930",
    "sg:postcode":"9900",
    "sg:province":"Tirol",
    "sg:website":"tischlerei-unterluggauer.at",
    "wof:name":"Unterluggauer Arnold",
    "wof:placetype":"venue"
},
  "geometry": {"coordinates":[12.7914571762,46.8183517456],"type":"Point"}
}