{
  "type": "Feature",
  "properties": {
    "addr:full":"Kirchenpl 2 Hartkirchen Ober\u00f6sterreich 4081",
    "addr:housenumber":"2",
    "addr:postcode":"4081",
    "addr:street":"Kirchenpl",
    "iso:country":"AT",
    "sg:address":"Kirchenpl 2",
    "sg:city":"Hartkirchen",
    "sg:orig_category":"Installationsunternehmen",
    "sg:phone":"+43 7273 85150",
    "sg:postcode":"4081",
    "sg:province":"Ober\u00f6sterreich",
    "wof:name":"K\u00f6nig GmbH",
    "wof:placetype":"venue"
},
  "geometry": {"coordinates":[14.0033407211,48.3629112244],"type":"Point"}
}