{
  "type": "Feature",
  "properties": {
    "iso:country":"AT",
    "sg:address":"Arlbergstrasse 123",
    "sg:city":"Bregenz",
    "sg:classifiers":[
        {
            "category":"Education",
            "subcategory":"Special Training",
            "type":"Public Place"
        }
    ],
    "sg:phone":"+43 5574 76054",
    "sg:postcode":"6900",
    "sg:province":"Vorarlberg",
    "sg:tags":[
        "bread"
    ],
    "wof:name":"Kloser's B\u00e4ckerei GmbH",
    "wof:placetype":"venue"
},
  "geometry": {"coordinates":[9.7331924438,47.4893608093],"type":"Point"}
}