{
  "type": "Feature",
  "properties": {
    "addr:full":"Castellistr 12 Lilienfeld Nieder\u00f6sterreich 3180",
    "addr:housenumber":"12",
    "addr:postcode":"3180",
    "addr:street":"Castellistr",
    "iso:country":"AT",
    "sg:address":"Castellistr 12",
    "sg:city":"Lilienfeld",
    "sg:orig_category":"Schmieden U Schmiedeeisenelemente",
    "sg:phone":"+43 2762 52392",
    "sg:postcode":"3180",
    "sg:province":"Nieder\u00f6sterreich",
    "wof:name":"Podlesnik Alfons",
    "wof:placetype":"venue"
},
  "geometry": {"coordinates":[15.5883579254,48.0126876831],"type":"Point"}
}