{
  "type": "Feature",
  "properties": {
    "addr:full":"Maurachg 15 Bregenz Vorarlberg 6900",
    "addr:housenumber":"15",
    "addr:postcode":"6900",
    "addr:street":"Maurachg",
    "iso:country":"AT",
    "sg:address":"Maurachg 15",
    "sg:city":"Bregenz",
    "sg:orig_category":"Unternehmensberatung",
    "sg:phone":"+43 4355 7444882",
    "sg:postcode":"6900",
    "sg:province":"Vorarlberg",
    "wof:name":"Jansen Stephan",
    "wof:placetype":"venue"
},
  "geometry": {"coordinates":[9.7483091354,47.5016784668],"type":"Point"}
}