{
  "type": "Feature",
  "properties": {
    "addr:full":"Dorfpl 6 St. Stefan ob Leoben Steiermark 8713",
    "addr:housenumber":"6",
    "addr:postcode":"8713",
    "addr:street":"Dorfpl",
    "iso:country":"AT",
    "sg:address":"Dorfpl 6",
    "sg:city":"St. Stefan ob Leoben",
    "sg:orig_category":"Lebensmittel / Einzelhandel",
    "sg:phone":"+43 3832 22690",
    "sg:postcode":"8713",
    "sg:province":"Steiermark",
    "wof:name":"Spar-Markt Hoisel G\u00fcnter",
    "wof:placetype":"venue"
},
  "geometry": {"coordinates":[14.9787340164,47.3178329468],"type":"Point"}
}