{
  "type": "Feature",
  "properties": {
    "addr:full":"Salzburger Pl 2 Treibach-Althofen K\u00e4rnten 9330",
    "addr:housenumber":"2",
    "addr:postcode":"9330",
    "addr:street":"Salzburger Pl;Kaernten",
    "iso:country":"AT",
    "sg:address":"Salzburger Pl 2",
    "sg:city":"Treibach-Althofen",
    "sg:orig_category":"Abfallentsorgung U -Verwertung",
    "sg:phone":"+43 4262 27171",
    "sg:postcode":"9330",
    "sg:province":"K\u00e4rnten",
    "wof:name":"PM Recovery Austria Metall Recycling GmbH",
    "wof:placetype":"venue"
},
  "geometry": {"coordinates":[14.4738092422,46.8735237122],"type":"Point"}
}