{
  "type": "Feature",
  "properties": {
    "addr:full":"Kramerg 3 Wien Wien 1010",
    "addr:housenumber":"3",
    "addr:postcode":"1010",
    "addr:street":"Kramerg",
    "iso:country":"AT",
    "sg:address":"Kramerg 3",
    "sg:city":"Wien",
    "sg:orig_category":"Waren Aller Art",
    "sg:phone":"+43 1 5334460",
    "sg:postcode":"1010",
    "sg:province":"Wien",
    "wof:name":"Bomex HandelsgesmbH",
    "wof:placetype":"venue"
},
  "geometry": {"coordinates":[16.3726158142,48.2096862793],"type":"Point"}
}