{
  "type": "Feature",
  "properties": {
    "iso:country":"AT",
    "sg:address":"Klagenfurter Str 9",
    "sg:city":"Velden am W\u00f6rther See",
    "sg:orig_category":"Lebensmittel / Einzelhandel",
    "sg:phone":"+43 4274 50725",
    "sg:postcode":"9220",
    "sg:province":"K\u00e4rnten",
    "wof:name":"SPAR \u00d6sterreichische Warenhandels-AG",
    "wof:placetype":"venue"
},
  "geometry": {"coordinates":[14.0482120514,46.6174201965],"type":"Point"}
}