{
  "type": "Feature",
  "properties": {
    "addr:full":"Achenrain 23 Kramsach Tirol 6233",
    "addr:housenumber":"23",
    "addr:postcode":"6233",
    "addr:street":"Achenrain;Tirol",
    "iso:country":"AT",
    "sg:address":"Achenrain 23",
    "sg:city":"Kramsach",
    "sg:orig_category":"Zahntechnische Laboratorien",
    "sg:phone":"+43 5337 65891",
    "sg:postcode":"6233",
    "sg:province":"Tirol",
    "wof:name":"Zahntechnisches Labor Unterpertinger",
    "wof:placetype":"venue"
},
  "geometry": {"coordinates":[11.8772058487,47.4484405518],"type":"Point"}
}