{
  "type": "Feature",
  "properties": {
    "addr:full":"Hochhausstr 3 Hofkirchen im Traunkreis Ober\u00f6sterreich 4492",
    "addr:housenumber":"3",
    "addr:postcode":"4492",
    "addr:street":"Hochhausstr",
    "iso:country":"AT",
    "sg:address":"Hochhausstr 3",
    "sg:city":"Hofkirchen im Traunkreis",
    "sg:orig_category":"Steinmetzbetriebe",
    "sg:phone":"+43 7225 7422",
    "sg:postcode":"4492",
    "sg:province":"Ober\u00f6sterreich",
    "wof:name":"Huber Granit Marmor",
    "wof:placetype":"venue"
},
  "geometry": {"coordinates":[14.379609108,48.1409263611],"type":"Point"}
}