{
  "type": "Feature",
  "properties": {
    "iso:country":"AT",
    "sg:address":"Burgg 128",
    "sg:city":"Judenburg",
    "sg:orig_category":"Autohandel",
    "sg:phone":"+43 4335 72835060",
    "sg:postcode":"8750",
    "sg:province":"Steiermark",
    "wof:name":"Autohaus Franz Ing",
    "wof:placetype":"venue"
},
  "geometry": {"coordinates":[14.6362600327,47.1713981628],"type":"Point"}
}