{
  "type": "Feature",
  "properties": {
    "iso:country":"AT",
    "sg:address":"Wittulaweg 25",
    "sg:city":"Neuhart",
    "sg:classifiers":[
        {
            "category":"Organizations",
            "subcategory":"Political Organization",
            "type":"Services"
        }
    ],
    "sg:phone":"+43 316 287619",
    "sg:postcode":"8053",
    "sg:province":"Steiermark",
    "sg:tags":[
        "agv",
        "guided",
        "automatic",
        "system",
        "vehicle"
    ],
    "wof:name":"Schmidt Trading - Trading Agency",
    "wof:placetype":"venue"
},
  "geometry": {"coordinates":[15.3982849121,47.0457611084],"type":"Point"}
}