{
  "type": "Feature",
  "properties": {
    "iso:country":"AT",
    "sg:address":"Werkstr. 13",
    "sg:city":"Ternitz",
    "sg:classifiers":[
        {
            "category":"Communications",
            "subcategory":"Television Station",
            "type":"Services"
        }
    ],
    "sg:phone":"+43 4326 3035701",
    "sg:postcode":"2630",
    "sg:province":"Nieder\u00f6sterreich",
    "sg:tags":[
        "audio-visual"
    ],
    "wof:name":"LIFT PLASTICS KUNSTSTOFF - BEARBEITUNGS GES.MBH",
    "wof:placetype":"venue"
},
  "geometry": {"coordinates":[16.0419502258,47.7136268616],"type":"Point"}
}