{
  "type": "Feature",
  "properties": {
    "addr:full":"Hauptpl 5 Deutsch Brodersdorf Nieder\u00f6sterreich 2443",
    "addr:housenumber":"5",
    "addr:postcode":"2443",
    "addr:street":"Hauptpl",
    "iso:country":"AT",
    "sg:address":"Hauptpl 5",
    "sg:city":"Deutsch Brodersdorf",
    "sg:orig_category":"Volksschulen",
    "sg:phone":"+43 4322 558219",
    "sg:postcode":"2443",
    "sg:province":"Nieder\u00f6sterreich",
    "wof:name":"Volksschule",
    "wof:placetype":"venue"
},
  "geometry": {"coordinates":[16.5152244568,47.9157180786],"type":"Point"}
}