{
  "type": "Feature",
  "properties": {
    "iso:country":"AT",
    "sg:address":"Baumkirchnerring 7",
    "sg:city":"Wiener Neustadt",
    "sg:classifiers":[
        {
            "category":"Shopping",
            "subcategory":"Thrift Store",
            "type":"Retail Goods"
        }
    ],
    "sg:phone":"+43 2622 20041",
    "sg:postcode":"2700",
    "sg:province":"Nieder\u00f6sterreich",
    "sg:tags":[
        "second-hand-shops"
    ],
    "wof:name":"Tauschzentrale Eva Stadlmayer",
    "wof:placetype":"venue"
},
  "geometry": {"coordinates":[16.2418670654,47.81665802],"type":"Point"}
}