{
  "type": "Feature",
  "properties": {
    "iso:country":"AT",
    "sg:address":"Friedrich-Thurner-Str 16",
    "sg:city":"Ried im Innkreis",
    "sg:orig_category":"Personalbereitstellung",
    "sg:phone":"+43 4377 5289900",
    "sg:postcode":"4910",
    "sg:province":"Ober\u00f6sterreich",
    "wof:name":"Roitinger Personal GesmbH",
    "wof:placetype":"venue"
},
  "geometry": {"coordinates":[13.4843053818,48.2120018005],"type":"Point"}
}