{
  "type": "Feature",
  "properties": {
    "addr:full":"Landstr 61 Zwettl Nieder\u00f6sterreich 3910",
    "addr:housenumber":"61",
    "addr:postcode":"3910",
    "addr:street":"Landstr;Niederoesterreich",
    "iso:country":"AT",
    "sg:address":"Landstr 61",
    "sg:city":"Zwettl",
    "sg:orig_category":"Geschenkartikel",
    "sg:phone":"+43 4328 2252453",
    "sg:postcode":"3910",
    "sg:province":"Nieder\u00f6sterreich",
    "wof:name":"Fr\u00fchst\u00fcckspension Franzus",
    "wof:placetype":"venue"
},
  "geometry": {"coordinates":[15.165389061,48.6063995361],"type":"Point"}
}