{
  "type": "Feature",
  "properties": {
    "addr:full":"Maximilianstr 9 Gramastetten Ober\u00f6sterreich 4201",
    "addr:housenumber":"9",
    "addr:postcode":"4201",
    "addr:street":"Maximilianstr",
    "iso:country":"AT",
    "sg:address":"Maximilianstr 9",
    "sg:city":"Gramastetten",
    "sg:orig_category":"Bestattungsunternehmen",
    "sg:phone":"+43 7239 8156",
    "sg:postcode":"4201",
    "sg:province":"Ober\u00f6sterreich",
    "wof:name":"Peterm\u00fcller Konrad",
    "wof:placetype":"venue"
},
  "geometry": {"coordinates":[14.1870174408,48.3799247742],"type":"Point"}
}