{
  "type": "Feature",
  "properties": {
    "addr:full":"Quadenstr 53 Wien Wien 1220",
    "addr:housenumber":"53",
    "addr:postcode":"1220",
    "addr:street":"Quadenstr",
    "iso:country":"AT",
    "sg:address":"Quadenstr 53",
    "sg:city":"Wien",
    "sg:classifiers":[
        {
            "category":"Professional",
            "subcategory":"Management & Consulting",
            "type":"Services"
        }
    ],
    "sg:phone":"+43 1 2823313",
    "sg:postcode":"1220",
    "sg:province":"Wien",
    "sg:tags":[
        "supervision"
    ],
    "wof:name":"Honer Erwin",
    "wof:placetype":"venue"
},
  "geometry": {"coordinates":[16.481552124,48.2381515503],"type":"Point"}
}