{
  "type": "Feature",
  "properties": {
    "iso:country":"AT",
    "sg:address":"Unterer Markt 9",
    "sg:city":"Hallein",
    "sg:orig_category":"Elektroinstallationsunternehmen",
    "sg:phone":"+43 6245 80374",
    "sg:postcode":"5400",
    "sg:province":"Salzburg",
    "wof:name":"Mayr Matthias Elektro GesmbH & Co KG",
    "wof:placetype":"venue"
},
  "geometry": {"coordinates":[13.0938262939,47.681678772],"type":"Point"}
}