{
  "type": "Feature",
  "properties": {
    "addr:full":"Austr 13 Krems an der Donau Nieder\u00f6sterreich 3500",
    "addr:housenumber":"13",
    "addr:postcode":"3500",
    "addr:street":"Austr",
    "iso:country":"AT",
    "sg:address":"Austr 13",
    "sg:city":"Krems an der Donau",
    "sg:orig_category":"Immobilienmakler",
    "sg:phone":"+43 4327 3277578",
    "sg:postcode":"3500",
    "sg:province":"Nieder\u00f6sterreich",
    "wof:name":"I V Consulting Immobilien GmbH",
    "wof:placetype":"venue"
},
  "geometry": {"coordinates":[15.6087064743,48.4088668823],"type":"Point"}
}