{
  "type": "Feature",
  "properties": {
    "addr:full":"Nr 144 M\u00fcnchendorf Nieder\u00f6sterreich 2482",
    "addr:postcode":"2482",
    "addr:street":"Nr 144 Muenchendorf",
    "iso:country":"AT",
    "sg:address":"Nr 144",
    "sg:city":"M\u00fcnchendorf",
    "sg:orig_category":"Werbeagenturen",
    "sg:phone":"+43 2259 2514",
    "sg:postcode":"2482",
    "sg:province":"Nieder\u00f6sterreich",
    "wof:name":"Navisotschnigg Otto Mag",
    "wof:placetype":"venue"
},
  "geometry": {"coordinates":[166.9221496582,-0.5282999873],"type":"Point"}
}