{
  "type": "Feature",
  "properties": {
    "iso:country":"AT",
    "sg:address":"Salzburger Str 31",
    "sg:city":"Schwanenstadt",
    "sg:orig_category":"Maschinenhandel",
    "sg:phone":"+43 76734385",
    "sg:postcode":"4690",
    "sg:province":"Ober\u00f6sterreich",
    "wof:name":"Agri Boss HandelsgesmbH",
    "wof:placetype":"venue"
},
  "geometry": {"coordinates":[13.7654457092,48.0498580933],"type":"Point"}
}