{
  "type": "Feature",
  "properties": {
    "iso:country":"AT",
    "sg:address":"Ebne 20",
    "sg:city":"Ehrwald",
    "sg:orig_category":"Architekten",
    "sg:phone":"+43 5673 2930",
    "sg:postcode":"6632",
    "sg:province":"Tirol",
    "wof:name":"Pesendorfer Martin Dipl-Ing",
    "wof:placetype":"venue"
},
  "geometry": {"coordinates":[10.9255943298,47.4093475342],"type":"Point"}
}