{
  "type": "Feature",
  "properties": {
    "addr:full":"Kaiser F Josef-Str 10a Hohenems Vorarlberg 6845",
    "addr:housenumber":"10a",
    "addr:postcode":"6845",
    "addr:street":"Josef-Str",
    "iso:country":"AT",
    "sg:address":"Kaiser F Josef-Str 10a",
    "sg:city":"Hohenems",
    "sg:orig_category":"Reisebetreuer",
    "sg:phone":"+43 5576 76038",
    "sg:postcode":"6845",
    "sg:province":"Vorarlberg",
    "wof:name":"ANB Agentur",
    "wof:placetype":"venue"
},
  "geometry": {"coordinates":[9.6845569611,47.3575668335],"type":"Point"}
}