{
  "type": "Feature",
  "properties": {
    "addr:full":"Bahnhofstr 5 Hermagor K\u00e4rnten 9620",
    "addr:housenumber":"5",
    "addr:postcode":"9620",
    "addr:street":"Bahnhofstr;Kaernten",
    "iso:country":"AT",
    "sg:address":"Bahnhofstr 5",
    "sg:city":"Hermagor",
    "sg:orig_category":"Personalbereitstellung",
    "sg:phone":"+43 4282 25128",
    "sg:postcode":"9620",
    "sg:province":"K\u00e4rnten",
    "wof:name":"APA Personalbereitstellung GmbH",
    "wof:placetype":"venue"
},
  "geometry": {"coordinates":[13.3741798401,46.6272125244],"type":"Point"}
}