{
  "type": "Feature",
  "properties": {
    "addr:full":"Siggerwiesen 15 Bergheim Salzburg 5101",
    "addr:housenumber":"15",
    "addr:postcode":"5101",
    "addr:street":"Siggerwiesen;Salzburg",
    "iso:country":"AT",
    "sg:address":"Siggerwiesen 15",
    "sg:city":"Bergheim",
    "sg:classifiers":[
        {
            "category":"Utilities",
            "subcategory":"Recycling",
            "type":"Services"
        }
    ],
    "sg:phone":"+43 662 469490",
    "sg:postcode":"5101",
    "sg:province":"Salzburg",
    "sg:tags":[
        "battery"
    ],
    "sg:website":"rhv-sab.at",
    "wof:name":"Salzburger Abfallbeseitigung Ges.m.b.H.",
    "wof:placetype":"venue"
},
  "geometry": {"coordinates":[13.0137042999,47.861492157],"type":"Point"}
}