{
  "type": "Feature",
  "properties": {
    "iso:country":"AT",
    "sg:address":"Schulstr 2",
    "sg:city":"Linz",
    "sg:orig_category":"Non-Classified Establishments",
    "sg:phone":"+43 732 731095",
    "sg:postcode":"4040",
    "sg:province":"Ober\u00f6sterreich",
    "wof:name":"Pfarramt Stadtpfarramt Urfahr",
    "wof:placetype":"venue"
},
  "geometry": {"coordinates":[14.2849855423,48.3103637695],"type":"Point"}
}