{
  "type": "Feature",
  "properties": {
    "addr:full":"Lobzeile 18 Eisenstadt Burgenland 7000",
    "addr:housenumber":"18",
    "addr:postcode":"7000",
    "addr:street":"Lobzeile",
    "iso:country":"AT",
    "sg:address":"Lobzeile 18",
    "sg:city":"Eisenstadt",
    "sg:orig_category":"Christbaumschmuck",
    "sg:phone":"+43 664 2219829",
    "sg:postcode":"7000",
    "sg:province":"Burgenland",
    "wof:name":"Wratschko Norbert",
    "wof:placetype":"venue"
},
  "geometry": {"coordinates":[16.5303573608,47.8411560059],"type":"Point"}
}