{
  "type": "Feature",
  "properties": {
    "iso:country":"AT",
    "sg:address":"Bert-K\u00f6llensperger-Str. 12",
    "sg:city":"Thaur",
    "sg:classifiers":[
        {
            "category":"Autos & Motor Vehicles",
            "subcategory":"Automobile Sales",
            "type":"Retail Goods"
        }
    ],
    "sg:phone":"+43 4352 2345400",
    "sg:postcode":"6065",
    "sg:province":"Tirol",
    "sg:tags":[
        "industrial"
    ],
    "wof:name":"TIROLTRUCK FAHRZEUG-VERTRIEB-GMBH",
    "wof:placetype":"venue"
},
  "geometry": {"coordinates":[11.4727048874,47.2938156128],"type":"Point"}
}