{
  "type": "Feature",
  "properties": {
    "iso:country":"AT",
    "sg:address":"Postgasse 16",
    "sg:city":"Wien",
    "sg:classifiers":[
        {
            "category":"Banks & Credit Unions",
            "subcategory":"Investment Brokerage",
            "type":"Services"
        }
    ],
    "sg:phone":"+43 1 5330445",
    "sg:postcode":"1010",
    "sg:province":"Wien",
    "sg:tags":[
        "equestrian",
        "items",
        "accessory",
        "equipment",
        "harness",
        "riding"
    ],
    "wof:name":"Sportl\u00f6we Ski-Tennis-Bike Warenvertriebsges.m.b.H.",
    "wof:placetype":"venue"
},
  "geometry": {"coordinates":[16.3794727325,48.2110137939],"type":"Point"}
}