{
  "type": "Feature",
  "properties": {
    "iso:country":"AT",
    "sg:address":"Feldkirchner Str 96",
    "sg:city":"Puntigam",
    "sg:orig_category":"Transportbeton",
    "sg:phone":"+43 316 2925030",
    "sg:postcode":"8055",
    "sg:province":"Steiermark",
    "wof:name":"Lieferbeton GesmbH",
    "wof:placetype":"venue"
},
  "geometry": {"coordinates":[15.4336471558,47.0124092102],"type":"Point"}
}