{
  "type": "Feature",
  "properties": {
    "iso:country":"AT",
    "sg:address":"Oberstein 165",
    "sg:city":"St. Martin am Tennengebirge",
    "sg:orig_category":"Pensionen / Privatzimmer",
    "sg:phone":"+43 6463 7426",
    "sg:postcode":"5522",
    "sg:province":"Salzburg",
    "wof:name":"Pension Verena",
    "wof:placetype":"venue"
},
  "geometry": {"coordinates":[-91.8949966431,30.1026191711],"type":"Point"}
}