{
  "type": "Feature",
  "properties": {
    "addr:full":"Prangerstr 12 Breitenbrunn Burgenland 7091",
    "addr:housenumber":"12",
    "addr:postcode":"7091",
    "addr:street":"Prangerstr",
    "iso:country":"AT",
    "sg:address":"Prangerstr 12",
    "sg:city":"Breitenbrunn",
    "sg:orig_category":"Tischlereien",
    "sg:phone":"+43 2683 2807",
    "sg:postcode":"7091",
    "sg:province":"Burgenland",
    "wof:name":"Sammer Friedrich",
    "wof:placetype":"venue"
},
  "geometry": {"coordinates":[16.7342758179,47.947227478],"type":"Point"}
}