{
  "type": "Feature",
  "properties": {
    "addr:full":"Guglg 43 Wien Wien 1030",
    "addr:housenumber":"43",
    "addr:postcode":"1030",
    "addr:street":"Guglg",
    "iso:country":"AT",
    "sg:address":"Guglg 43",
    "sg:city":"Wien",
    "sg:orig_category":"Papier- U Schreibwaren / Einzelhandel",
    "sg:phone":"+43 4317 436360",
    "sg:postcode":"1030",
    "sg:province":"Wien",
    "wof:name":"Paperworld - RePo HandelsgesmbH",
    "wof:placetype":"venue"
},
  "geometry": {"coordinates":[16.419719696,48.1855316162],"type":"Point"}
}