{
  "type": "Feature",
  "properties": {
    "iso:country":"AT",
    "sg:address":"Johann Roithner-Str 6",
    "sg:city":"Traun",
    "sg:orig_category":"Banken U Sparkassen",
    "sg:phone":"+43 732 65967853",
    "sg:postcode":"4050",
    "sg:province":"Ober\u00f6sterreich",
    "wof:name":"Raiffeisenlandesbank Ober\u00f6sterreich regGenmbH",
    "wof:placetype":"venue"
},
  "geometry": {"coordinates":[14.2397546768,48.2220649719],"type":"Point"}
}