{
  "type": "Feature",
  "properties": {
    "iso:country":"AT",
    "sg:address":"Stadtpl 36",
    "sg:city":"Eferding",
    "sg:orig_category":"Versicherungsunternehmen",
    "sg:phone":"+43 7272 4011",
    "sg:postcode":"4070",
    "sg:province":"Ober\u00f6sterreich",
    "wof:name":"Allianz Elementar Versicherungs-AG",
    "wof:placetype":"venue"
},
  "geometry": {"coordinates":[14.0231399536,48.310092926],"type":"Point"}
}