{
  "type": "Feature",
  "properties": {
    "addr:full":"Obere Lend 45 Hall in Tirol Tirol 6060",
    "addr:housenumber":"45",
    "addr:postcode":"6060",
    "addr:street":"Obere Lend;Tirol",
    "iso:country":"AT",
    "sg:address":"Obere Lend 45",
    "sg:city":"Hall in Tirol",
    "sg:orig_category":"Alteisen U Altmetalle",
    "sg:phone":"+43 4352 23521920",
    "sg:postcode":"6060",
    "sg:province":"Tirol",
    "sg:website":"ragg.at; ragg.com",
    "wof:name":"Altautoabholung Ragg GmbH",
    "wof:placetype":"venue"
},
  "geometry": {"coordinates":[11.4937114716,47.2739906311],"type":"Point"}
}