{
  "type": "Feature",
  "properties": {
    "iso:country":"AT",
    "sg:address":"Bert-K\u00f6llensperger-Str 8",
    "sg:city":"Thaur",
    "sg:orig_category":"Reifen U Reifendienste",
    "sg:phone":"+43 4352 23578000",
    "sg:postcode":"6065",
    "sg:province":"Tirol",
    "sg:website":"reifenteam.at",
    "wof:name":"Reifenteam Varga & Oberm\u00fcller GmbH",
    "wof:placetype":"venue"
},
  "geometry": {"coordinates":[11.4727048874,47.2938156128],"type":"Point"}
}