{
  "type": "Feature",
  "properties": {
    "addr:full":"K\u00e4rntner Str 40 Knittelfeld Steiermark 8720",
    "addr:housenumber":"40",
    "addr:postcode":"8720",
    "addr:street":"Str",
    "iso:country":"AT",
    "sg:address":"K\u00e4rntner Str 40",
    "sg:city":"Knittelfeld",
    "sg:orig_category":"Blumeneinzelhandel",
    "sg:phone":"+43 4335 12825693",
    "sg:postcode":"8720",
    "sg:province":"Steiermark",
    "wof:name":"Wutz Ulrike",
    "wof:placetype":"venue"
},
  "geometry": {"coordinates":[14.8291902542,47.2139434814],"type":"Point"}
}