{
  "type": "Feature",
  "properties": {
    "iso:country":"AT",
    "sg:address":"Fabrikstr 6",
    "sg:city":"Golling an der Erlauf",
    "sg:orig_category":"Rettungsdienste",
    "sg:phone":"+43 4327 5725440",
    "sg:postcode":"3381",
    "sg:province":"Nieder\u00f6sterreich",
    "wof:name":"Arbeiter Samariter Bund \u00f6sterreichs Rettungsstation P\u00f6chlarn-Neuda",
    "wof:placetype":"venue"
},
  "geometry": {"coordinates":[15.1818294525,48.2047271729],"type":"Point"}
}