{
  "type": "Feature",
  "properties": {
    "addr:full":"Willy-Graf-Str 15 Kufstein Tirol 6330",
    "addr:housenumber":"15",
    "addr:postcode":"6330",
    "addr:street":"Willy-Graf-Str;Tirol",
    "iso:country":"AT",
    "sg:address":"Willy-Graf-Str 15",
    "sg:city":"Kufstein",
    "sg:orig_category":"Reifen U Reifendienste",
    "sg:phone":"+43 4353 7262906",
    "sg:postcode":"6330",
    "sg:province":"Tirol",
    "wof:name":"Reifen John Handels-GesmbH",
    "wof:placetype":"venue"
},
  "geometry": {"coordinates":[12.1697912216,47.5917129517],"type":"Point"}
}