{
  "type": "Feature",
  "properties": {
    "addr:full":"Sonnegg 5 Fulpmes Tirol 6166",
    "addr:housenumber":"5",
    "addr:postcode":"6166",
    "addr:street":"Sonnegg;Tirol",
    "iso:country":"AT",
    "sg:address":"Sonnegg 5",
    "sg:city":"Fulpmes",
    "sg:classifiers":[
        {
            "category":"Taxi",
            "type":"Transportation"
        }
    ],
    "sg:phone":"+43 4352 2564773",
    "sg:postcode":"6166",
    "sg:province":"Tirol",
    "sg:tags":[
        "personentransporte",
        "u"
    ],
    "wof:name":"Taxi Pfurtscheller",
    "wof:placetype":"venue"
},
  "geometry": {"coordinates":[11.3417234421,47.1435050964],"type":"Point"}
}