{
  "type": "Feature",
  "properties": {
    "addr:full":"Nr 20 Rettenegg Steiermark 8674",
    "addr:postcode":"8674",
    "addr:street":"Nr",
    "iso:country":"AT",
    "sg:address":"Nr 20",
    "sg:city":"Rettenegg",
    "sg:orig_category":"Transportunternehmen",
    "sg:phone":"+43 4331 738208",
    "sg:postcode":"8674",
    "sg:province":"Steiermark",
    "wof:name":"Gruber Franz",
    "wof:placetype":"venue"
},
  "geometry": {"coordinates":[15.7791147232,47.5252799988],"type":"Point"}
}