{
  "type": "Feature",
  "properties": {
    "addr:full":"Bambergstr Kirchdorf an der Krems Ober\u00f6sterreich 4560",
    "addr:postcode":"4560",
    "addr:street":"Oberoesterreich",
    "iso:country":"AT",
    "sg:address":"Bambergstr",
    "sg:city":"Kirchdorf an der Krems",
    "sg:orig_category":"Lebensmittel / Einzelhandel",
    "sg:phone":"+43 4375 8261255",
    "sg:postcode":"4560",
    "sg:province":"Ober\u00f6sterreich",
    "wof:name":"Billa AG",
    "wof:placetype":"venue"
},
  "geometry": {"coordinates":[14.1202049255,47.9054145813],"type":"Point"}
}