{
  "type": "Feature",
  "properties": {
    "addr:full":"H\u00f6pfling 4 Eggelsberg Ober\u00f6sterreich 5142",
    "addr:housenumber":"4",
    "addr:postcode":"5142",
    "addr:street":"Hoepfling;Oberoesterreich",
    "iso:country":"AT",
    "sg:address":"H\u00f6pfling 4",
    "sg:city":"Eggelsberg",
    "sg:orig_category":"Erdarbeiten",
    "sg:phone":"+43 7748 2206",
    "sg:postcode":"5142",
    "sg:province":"Ober\u00f6sterreich",
    "wof:name":"Edes Gastst\u00e4tten GmbH",
    "wof:placetype":"venue"
},
  "geometry": {"coordinates":[12.9915065765,48.0798149109],"type":"Point"}
}