{
  "type": "Feature",
  "properties": {
    "addr:full":"R\u00f6tsch 13 Obdach Steiermark 8742",
    "addr:housenumber":"13",
    "addr:postcode":"8742",
    "addr:street":"Roetsch",
    "iso:country":"AT",
    "sg:address":"R\u00f6tsch 13",
    "sg:city":"Obdach",
    "sg:orig_category":"Elektroinstallationsunternehmen",
    "sg:phone":"+43 4335 7825670",
    "sg:postcode":"8742",
    "sg:province":"Steiermark",
    "wof:name":"HERESCHWERKE Regeltechnik GmbH",
    "wof:placetype":"venue"
},
  "geometry": {"coordinates":[14.6953725815,47.0679969788],"type":"Point"}
}