{
  "type": "Feature",
  "properties": {
    "addr:full":"Speckbacherstrasse 26 Innsbruck Tirol 6020",
    "addr:housenumber":"26",
    "addr:postcode":"6020",
    "addr:street":"Speckbacherstrasse;Tirol",
    "iso:country":"AT",
    "sg:address":"Speckbacherstrasse 26",
    "sg:city":"Innsbruck",
    "sg:classifiers":[
        {
            "category":"Utilities",
            "subcategory":"Fuel Oil & Lpg",
            "type":"Services"
        }
    ],
    "sg:phone":"+43 512 595880",
    "sg:postcode":"6020",
    "sg:province":"Tirol",
    "sg:tags":[
        "dental",
        "product"
    ],
    "wof:name":"Ortho-Dental Egg Ges.m.b.H.",
    "wof:placetype":"venue"
},
  "geometry": {"coordinates":[11.3896932602,47.2595558167],"type":"Point"}
}