{
  "type": "Feature",
  "properties": {
    "iso:country":"AT",
    "sg:address":"Mollardgasse 85",
    "sg:city":"Wien",
    "sg:classifiers":[
        {
            "category":"Home & Garden",
            "subcategory":"Furniture",
            "type":"Retail Goods"
        }
    ],
    "sg:phone":"+43 1 5961919",
    "sg:postcode":"1060",
    "sg:province":"Wien",
    "sg:tags":[
        "solid",
        "wood",
        "made",
        "childrens"
    ],
    "sg:website":"knopplegat.at",
    "wof:name":"Knopp",
    "wof:placetype":"venue"
},
  "geometry": {"coordinates":[16.3434238434,48.1895751953],"type":"Point"}
}