{
  "type": "Feature",
  "properties": {
    "iso:country":"AT",
    "sg:address":"Grubenweg 11",
    "sg:city":"Pasching",
    "sg:orig_category":"Dowels, Plugs, Screw Anchors",
    "sg:phone":"+43 7229 62251",
    "sg:postcode":"4061",
    "sg:province":"Ober\u00f6sterreich",
    "sg:website":"members.telering.at/bwe",
    "wof:name":"B.W.E. Handelsges.m.b.H.",
    "wof:placetype":"venue"
},
  "geometry": {"coordinates":[14.2504272461,48.2420845032],"type":"Point"}
}