{
  "type": "Feature",
  "properties": {
    "addr:full":"Schiedstrasse 555 Kaprun Salzburg 5710",
    "addr:housenumber":"555",
    "addr:postcode":"5710",
    "addr:street":"Schiedstrasse;Salzburg",
    "iso:country":"AT",
    "sg:address":"Schiedstrasse 555",
    "sg:city":"Kaprun",
    "sg:classifiers":[
        {
            "category":"Home & Garden",
            "subcategory":"Household Appliances",
            "type":"Retail Goods"
        }
    ],
    "sg:phone":"+43 6547 7306",
    "sg:postcode":"5710",
    "sg:province":"Salzburg",
    "sg:tags":[
        "electric"
    ],
    "wof:name":"Erwin Lackner",
    "wof:placetype":"venue"
},
  "geometry": {"coordinates":[12.7624454498,47.2706108093],"type":"Point"}
}