{
  "type": "Feature",
  "properties": {
    "addr:full":"Weinbergg 10 Siegendorf im Burgenland Burgenland 7011",
    "addr:housenumber":"10",
    "addr:postcode":"7011",
    "addr:street":"Weinbergg",
    "iso:country":"AT",
    "sg:address":"Weinbergg 10",
    "sg:city":"Siegendorf im Burgenland",
    "sg:orig_category":"Chemisch-Technische Produkte",
    "sg:phone":"+43 2687 42310",
    "sg:postcode":"7011",
    "sg:province":"Burgenland",
    "wof:name":"Pretterebner KEG",
    "wof:placetype":"venue"
},
  "geometry": {"coordinates":[16.5137901306,47.7636032104],"type":"Point"}
}