{
  "type": "Feature",
  "properties": {
    "addr:full":"Treffelsdorf St. Veit an der Glan K\u00e4rnten 9300",
    "addr:postcode":"9300",
    "addr:street":"Treffelsdorf;Kaernten",
    "iso:country":"AT",
    "sg:address":"Treffelsdorf",
    "sg:city":"St. Veit an der Glan",
    "sg:orig_category":"Feuerwehren",
    "sg:phone":"+43 4212 3203",
    "sg:postcode":"9300",
    "sg:province":"K\u00e4rnten",
    "wof:name":"Freiwillige Feuerwehr Treffelsdorf",
    "wof:placetype":"venue"
},
  "geometry": {"coordinates":[14.3367347717,46.7611961365],"type":"Point"}
}