{
  "type": "Feature",
  "properties": {
    "addr:full":"Am Arlandgrund 5 Andritz Steiermark 8045",
    "addr:housenumber":"5",
    "addr:postcode":"8045",
    "addr:street":"Am Arlandgrund",
    "iso:country":"AT",
    "sg:address":"Am Arlandgrund 5",
    "sg:city":"Andritz",
    "sg:classifiers":[
        {
            "category":"Organizations",
            "subcategory":"Political Organization",
            "type":"Services"
        }
    ],
    "sg:phone":"+43 316 687360",
    "sg:postcode":"8045",
    "sg:province":"Steiermark",
    "sg:tags":[
        "mediation"
    ],
    "wof:name":"Mediation-Konfliktregelung Mag Magdalena Wilplinger",
    "wof:placetype":"venue"
},
  "geometry": {"coordinates":[15.4160699844,47.0998840332],"type":"Point"}
}