{
  "type": "Feature",
  "properties": {
    "addr:full":"Ernst Dreefs-Str 16 Peuerbach Ober\u00f6sterreich 4722",
    "addr:housenumber":"16",
    "addr:postcode":"4722",
    "iso:country":"AT",
    "sg:address":"Ernst Dreefs-Str 16",
    "sg:city":"Peuerbach",
    "sg:orig_category":"Anlagenbau U -Technik",
    "sg:phone":"+43 7276 21300",
    "sg:postcode":"4722",
    "sg:province":"Ober\u00f6sterreich",
    "wof:name":"MAK Mohsburger GesmbH",
    "wof:placetype":"venue"
},
  "geometry": {"coordinates":[13.7667093277,48.3413734436],"type":"Point"}
}