{
  "type": "Feature",
  "properties": {
    "addr:full":"Ringelschmiedg 7 Bruck an der Mur Steiermark 8600",
    "addr:housenumber":"7",
    "addr:postcode":"8600",
    "addr:street":"Ringelschmiedg",
    "iso:country":"AT",
    "sg:address":"Ringelschmiedg 7",
    "sg:city":"Bruck an der Mur",
    "sg:orig_category":"Exporteure U Importeure",
    "sg:phone":"+43 4338 62573010",
    "sg:postcode":"8600",
    "sg:province":"Steiermark",
    "wof:name":"Liendl Edmund Ing",
    "wof:placetype":"venue"
},
  "geometry": {"coordinates":[15.270198822,47.4090423584],"type":"Point"}
}