{
  "type": "Feature",
  "properties": {
    "addr:full":"St Paul-G 12 Krems an der Donau Nieder\u00f6sterreich 3500",
    "addr:housenumber":"12",
    "addr:postcode":"3500",
    "iso:country":"AT",
    "sg:address":"St Paul-G 12",
    "sg:city":"Krems an der Donau",
    "sg:classifiers":[
        {
            "category":"Shopping",
            "subcategory":"Thrift Store",
            "type":"Retail Goods"
        }
    ],
    "sg:phone":"+43 2732 76498",
    "sg:postcode":"3500",
    "sg:province":"Nieder\u00f6sterreich",
    "sg:tags":[
        "second-hand-shops"
    ],
    "wof:name":"Second-Hand Laden d Caritas",
    "wof:placetype":"venue"
},
  "geometry": {"coordinates":[15.6190681458,48.4084777832],"type":"Point"}
}