{
  "type": "Feature",
  "properties": {
    "iso:country":"AT",
    "sg:address":"Kirchb\u00fchelg 12",
    "sg:city":"Leonding",
    "sg:orig_category":"Psychotherapie",
    "sg:phone":"+43 732 680702",
    "sg:postcode":"4060",
    "sg:province":"Ober\u00f6sterreich",
    "wof:name":"Mayr-Nowak Tanja Mag",
    "wof:placetype":"venue"
},
  "geometry": {"coordinates":[14.2491264343,48.2792434692],"type":"Point"}
}