{
  "type": "Feature",
  "properties": {
    "iso:country":"AT",
    "sg:address":"Ossiacher Bundesstr 14",
    "sg:city":"Feldkirchen in K\u00e4rnten",
    "sg:orig_category":"Autohandel",
    "sg:phone":"+43 4342 7623940",
    "sg:postcode":"9560",
    "sg:province":"K\u00e4rnten",
    "wof:name":"Truppe Reinhard",
    "wof:placetype":"venue"
},
  "geometry": {"coordinates":[14.0926561356,46.730140686],"type":"Point"}
}