{
  "type": "Feature",
  "properties": {
    "iso:country":"AT",
    "sg:address":"Auf dem Kikel 369",
    "sg:city":"Feistritz an der Drau",
    "sg:orig_category":"Autobusunternehmen",
    "sg:phone":"+43 4245 39360",
    "sg:postcode":"9710",
    "sg:province":"K\u00e4rnten",
    "wof:name":"Ratz GesmbH",
    "wof:placetype":"venue"
},
  "geometry": {"coordinates":[13.6812143326,46.6893577576],"type":"Point"}
}