{
  "type": "Feature",
  "properties": {
    "addr:full":"Hauptpl 33 u 34 Leibnitz Steiermark 8430",
    "addr:housenumber":"33 u 34",
    "addr:postcode":"8430",
    "addr:street":"Hauptpl;Steiermark",
    "iso:country":"AT",
    "sg:address":"Hauptpl 33 u 34",
    "sg:city":"Leibnitz",
    "sg:orig_category":"Papier- U Schreibwaren / Einzelhandel",
    "sg:phone":"+43 4334 52824390",
    "sg:postcode":"8430",
    "sg:province":"Steiermark",
    "wof:name":"C\u00e4sar - H\u00f6dl B\u00fcroorganisation",
    "wof:placetype":"venue"
},
  "geometry": {"coordinates":[15.5377645493,46.7811355591],"type":"Point"}
}