{
  "type": "Feature",
  "properties": {
    "addr:full":"Juchg 32 Wien Wien 1030",
    "addr:housenumber":"32",
    "addr:postcode":"1030",
    "addr:street":"Juchg",
    "iso:country":"AT",
    "sg:address":"Juchg 32",
    "sg:city":"Wien",
    "sg:classifiers":[
        {
            "category":"Restaurant",
            "type":"Food & Drink"
        }
    ],
    "sg:phone":"+43 4367 63600610",
    "sg:postcode":"1030",
    "sg:province":"Wien",
    "wof:name":"Molnar Mariana KEGf",
    "wof:placetype":"venue"
},
  "geometry": {"coordinates":[16.388967514,48.1968421936],"type":"Point"}
}