{
  "type": "Feature",
  "properties": {
    "iso:country":"AT",
    "sg:address":"Schafbergstr 31",
    "sg:city":"Wels",
    "sg:orig_category":"Stiegen U Treppen",
    "sg:phone":"+43 4372 42617950",
    "sg:postcode":"4600",
    "sg:province":"Ober\u00f6sterreich",
    "wof:name":"Treppenmeister GmbH",
    "wof:placetype":"venue"
},
  "geometry": {"coordinates":[13.9986305237,48.1882171631],"type":"Point"}
}