{
  "type": "Feature",
  "properties": {
    "addr:full":"Thurnsdorfer Str 83 St. Valentin Nieder\u00f6sterreich 4300",
    "addr:housenumber":"83",
    "addr:postcode":"4300",
    "addr:street":"Str",
    "iso:country":"AT",
    "sg:address":"Thurnsdorfer Str 83",
    "sg:city":"St. Valentin",
    "sg:orig_category":"Imkereien",
    "sg:phone":"+43 7435 535540",
    "sg:postcode":"4300",
    "sg:province":"Nieder\u00f6sterreich",
    "wof:name":"Geiblinger & Marchner KEG",
    "wof:placetype":"venue"
},
  "geometry": {"coordinates":[14.5123901367,48.1757202148],"type":"Point"}
}