{
  "type": "Feature",
  "properties": {
    "addr:full":"Scherenbrandtnerhofstr 6 Salzburg Salzburg 5020",
    "addr:housenumber":"6",
    "addr:postcode":"5020",
    "addr:street":"Scherenbrandtnerhofstr;Salzburg",
    "iso:country":"AT",
    "sg:address":"Scherenbrandtnerhofstr 6",
    "sg:city":"Salzburg",
    "sg:orig_category":"Mauertrockenlegungen",
    "sg:phone":"+43 4366 2873830",
    "sg:postcode":"5020",
    "sg:province":"Salzburg",
    "sg:website":"feuchtemauern.at",
    "wof:name":"Hab\u00f6ck & Weinzierl Holz- u Bautenschutz GmbH Nfg KEG",
    "wof:placetype":"venue"
},
  "geometry": {"coordinates":[13.0592317581,47.8237113953],"type":"Point"}
}