{
  "type": "Feature",
  "properties": {
    "addr:full":"Taugl 191 St. Koloman Salzburg 5423",
    "addr:housenumber":"191",
    "addr:postcode":"5423",
    "addr:street":"Taugl",
    "iso:country":"AT",
    "sg:address":"Taugl 191",
    "sg:city":"St. Koloman",
    "sg:orig_category":"Volksschulen",
    "sg:phone":"+43 6241 224",
    "sg:postcode":"5423",
    "sg:province":"Salzburg",
    "wof:name":"Volksschule",
    "wof:placetype":"venue"
},
  "geometry": {"coordinates":[13.2200908661,47.6502151489],"type":"Point"}
}