{
  "type": "Feature",
  "properties": {
    "addr:full":"Am Graben 12 Gmunden Ober\u00f6sterreich 4810",
    "addr:housenumber":"12",
    "addr:postcode":"4810",
    "addr:street":"Am Graben;Oberoesterreich",
    "iso:country":"AT",
    "sg:address":"Am Graben 12",
    "sg:city":"Gmunden",
    "sg:orig_category":"Blumeneinzelhandel",
    "sg:phone":"+43 761267931",
    "sg:postcode":"4810",
    "sg:province":"Ober\u00f6sterreich",
    "wof:name":"Blumen Christa",
    "wof:placetype":"venue"
},
  "geometry": {"coordinates":[13.7981233597,47.9189872742],"type":"Point"}
}