{
  "type": "Feature",
  "properties": {
    "addr:full":"Ragnitz 5 St. Georgen an der Stiefing Steiermark 8413",
    "addr:housenumber":"5",
    "addr:postcode":"8413",
    "addr:street":"Ragnitz",
    "iso:country":"AT",
    "sg:address":"Ragnitz 5",
    "sg:city":"St. Georgen an der Stiefing",
    "sg:classifiers":[
        {
            "category":"Home & Garden",
            "subcategory":"Household Appliances",
            "type":"Retail Goods"
        }
    ],
    "sg:phone":"+43 3183 82010",
    "sg:postcode":"8413",
    "sg:province":"Steiermark",
    "sg:tags":[
        "electric"
    ],
    "sg:website":"kiendler.com",
    "wof:name":"Kiendler Ges.m.b.H.",
    "wof:placetype":"venue"
},
  "geometry": {"coordinates":[15.5929555893,46.8366584778],"type":"Point"}
}