{
  "type": "Feature",
  "properties": {
    "iso:country":"AT",
    "sg:address":"Bismarckstr 10",
    "sg:city":"Linz",
    "sg:orig_category":"Marketingberatung",
    "sg:phone":"+43 4366 41054478",
    "sg:postcode":"4020",
    "sg:province":"Ober\u00f6sterreich",
    "wof:name":"Bernhard Ulrich Mag",
    "wof:placetype":"venue"
},
  "geometry": {"coordinates":[14.292427063,48.2995147705],"type":"Point"}
}