{
  "type": "Feature",
  "properties": {
    "addr:full":"Lindeng 22 Wulkaprodersdorf Burgenland 7041",
    "addr:housenumber":"22",
    "addr:postcode":"7041",
    "addr:street":"Lindeng",
    "iso:country":"AT",
    "sg:address":"Lindeng 22",
    "sg:city":"Wulkaprodersdorf",
    "sg:orig_category":"Rauchfangkehrer",
    "sg:phone":"+43 2687 62804",
    "sg:postcode":"7041",
    "sg:province":"Burgenland",
    "wof:name":"Kremsner Johann",
    "wof:placetype":"venue"
},
  "geometry": {"coordinates":[16.5110435486,47.7978172302],"type":"Point"}
}