{
  "type": "Feature",
  "properties": {
    "addr:full":"Bahnhofstr 21 Rankweil Vorarlberg 6830",
    "addr:postcode":"6830",
    "addr:street":"Bahnhofstr 21",
    "iso:country":"AT",
    "sg:address":"Bahnhofstr 21",
    "sg:city":"Rankweil",
    "sg:orig_category":"Steuerberatung",
    "sg:phone":"+43 5522 421660",
    "sg:postcode":"6830",
    "sg:province":"Vorarlberg",
    "wof:name":"Englj\u00e4hringer & Fleisch Steuerberater OEG",
    "wof:placetype":"venue"
},
  "geometry": {"coordinates":[9.6397924423,47.2712402344],"type":"Point"}
}