{
  "type": "Feature",
  "properties": {
    "addr:full":"Nr 11a Graden Steiermark 8593",
    "addr:housenumber":"11a",
    "addr:postcode":"8593",
    "addr:street":"Nr",
    "iso:country":"AT",
    "sg:address":"Nr 11a",
    "sg:city":"Graden",
    "sg:orig_category":"Feuerwehren",
    "sg:phone":"+43 3144 80080",
    "sg:postcode":"8593",
    "sg:province":"Steiermark",
    "wof:name":"Freiwillige Feuerwehr Graden",
    "wof:placetype":"venue"
},
  "geometry": {"coordinates":[15.033780098,47.132598877],"type":"Point"}
}