{
  "type": "Feature",
  "properties": {
    "addr:full":"Werksg. 57 Rottenmann Steiermark 8786",
    "addr:housenumber":"57",
    "addr:postcode":"8786",
    "addr:street":"Werksg.",
    "iso:country":"AT",
    "sg:address":"Werksg. 57",
    "sg:city":"Rottenmann",
    "sg:classifiers":[
        {
            "category":"Professional",
            "subcategory":"Engineering",
            "type":"Services"
        }
    ],
    "sg:phone":"+43 4336 1424510",
    "sg:postcode":"8786",
    "sg:province":"Steiermark",
    "sg:tags":[
        "machine",
        "-",
        "mechanical"
    ],
    "wof:name":"AUSTRIA HAUSTECHNIK AG",
    "wof:placetype":"venue"
},
  "geometry": {"coordinates":[14.3548202515,47.5259361267],"type":"Point"}
}