{
  "type": "Feature",
  "properties": {
    "addr:full":"Am Weichselgarten 3 Gerasdorf Nieder\u00f6sterreich 2201",
    "addr:housenumber":"3",
    "addr:postcode":"2201",
    "addr:street":"Am Weichselgarten",
    "iso:country":"AT",
    "sg:address":"Am Weichselgarten 3",
    "sg:city":"Gerasdorf",
    "sg:orig_category":"Transportunternehmen",
    "sg:phone":"+43 2246 20372",
    "sg:postcode":"2201",
    "sg:province":"Nieder\u00f6sterreich",
    "wof:name":"Daily Service Tiefk\u00fchllogistik GesmbH & Co KG",
    "wof:placetype":"venue"
},
  "geometry": {"coordinates":[16.4708862305,48.2990150452],"type":"Point"}
}