{
  "type": "Feature",
  "properties": {
    "addr:full":"Stroheimer Str Eferding Ober\u00f6sterreich 4070",
    "addr:postcode":"4070",
    "addr:street":"Str Eferding",
    "iso:country":"AT",
    "sg:address":"Stroheimer Str",
    "sg:city":"Eferding",
    "sg:orig_category":"Bauunternehmen",
    "sg:phone":"+43 7272 4019",
    "sg:postcode":"4070",
    "sg:province":"Ober\u00f6sterreich",
    "wof:name":"Held & Francke BaugesmbH & Co KG - Asphaltmischanlage",
    "wof:placetype":"venue"
},
  "geometry": {"coordinates":[14.0126342773,48.3156471252],"type":"Point"}
}