{
  "type": "Feature",
  "properties": {
    "addr:full":"Inffeldg 21a Graz Steiermark 8010",
    "addr:housenumber":"21a",
    "addr:postcode":"8010",
    "addr:street":"Inffeldg",
    "iso:country":"AT",
    "sg:address":"Inffeldg 21a",
    "sg:city":"Graz",
    "sg:orig_category":"Gewerbeparks",
    "sg:phone":"+43 316 8739101",
    "sg:postcode":"8010",
    "sg:province":"Steiermark",
    "wof:name":"Science Park Graz GmbH",
    "wof:placetype":"venue"
},
  "geometry": {"coordinates":[15.4609527588,47.058391571],"type":"Point"}
}