{
  "type": "Feature",
  "properties": {
    "addr:full":"Konsumg 1 Ebergassing Nieder\u00f6sterreich 2435",
    "addr:housenumber":"1",
    "addr:postcode":"2435",
    "addr:street":"Konsumg",
    "iso:country":"AT",
    "sg:address":"Konsumg 1",
    "sg:city":"Ebergassing",
    "sg:orig_category":"Sonnenstudios",
    "sg:phone":"+43 2234 72583",
    "sg:postcode":"2435",
    "sg:province":"Nieder\u00f6sterreich",
    "wof:name":"Sonnenstudio Sun Spirit - G\u00fctler Barbara",
    "wof:placetype":"venue"
},
  "geometry": {"coordinates":[16.5190811157,48.045425415],"type":"Point"}
}