{
  "type": "Feature",
  "properties": {
    "iso:country":"AT",
    "sg:address":"Peter-Jordan-Str 21/4",
    "sg:city":"Wien",
    "sg:orig_category":"Werbeartikel U -Geschenke",
    "sg:phone":"+43 4314 080808",
    "sg:postcode":"1190",
    "sg:province":"Wien",
    "wof:name":"Foccini Trade GmbH",
    "wof:placetype":"venue"
},
  "geometry": {"coordinates":[16.3455257416,48.2369880676],"type":"Point"}
}