{
  "type": "Feature",
  "properties": {
    "addr:full":"Atzelsdorf 28 Micheldorf in Ober\u00f6sterreich Ober\u00f6sterreich 4563",
    "addr:housenumber":"28",
    "addr:postcode":"4563",
    "addr:street":"Atzelsdorf",
    "iso:country":"AT",
    "sg:address":"Atzelsdorf 28",
    "sg:city":"Micheldorf in Ober\u00f6sterreich",
    "sg:orig_category":"Fotografen",
    "sg:phone":"+43 4375 8264426",
    "sg:postcode":"4563",
    "sg:province":"Ober\u00f6sterreich",
    "wof:name":"Neumeyer Gernot",
    "wof:placetype":"venue"
},
  "geometry": {"coordinates":[14.148144722,47.883972168],"type":"Point"}
}