{
  "type": "Feature",
  "properties": {
    "addr:full":"Karolingerstr 7b Salzburg Salzburg 5020",
    "addr:housenumber":"7b",
    "addr:postcode":"5020",
    "addr:street":"Karolingerstr;Salzburg",
    "iso:country":"AT",
    "sg:address":"Karolingerstr 7b",
    "sg:city":"Salzburg",
    "sg:orig_category":"Maschinenbau, Automatisierungstechnik",
    "sg:phone":"+43 662 4310020",
    "sg:postcode":"5020",
    "sg:province":"Salzburg",
    "sg:website":"copadata.at",
    "wof:name":"COPA-DATA GmbH",
    "wof:placetype":"venue"
},
  "geometry": {"coordinates":[13.0095663071,47.7956428528],"type":"Point"}
}