{
  "type": "Feature",
  "properties": {
    "iso:country":"AT",
    "sg:address":"Untermarkt 11",
    "sg:city":"Reutte",
    "sg:orig_category":"Psychotherapie",
    "sg:phone":"+43 512 587685",
    "sg:postcode":"6600",
    "sg:province":"Tirol",
    "wof:name":"Witschela Christian - Psychotherapie-Beratung-K\u00f6rperarbeit",
    "wof:placetype":"venue"
},
  "geometry": {"coordinates":[10.7173538208,47.489982605],"type":"Point"}
}