{
  "type": "Feature",
  "properties": {
    "iso:country":"AT",
    "sg:address":"Am H\u00f6ribach 31",
    "sg:city":"Mondsee",
    "sg:orig_category":"Holzhandel",
    "sg:phone":"+43 4362 323562",
    "sg:postcode":"5310",
    "sg:province":"Ober\u00f6sterreich",
    "wof:name":"Oberascher Franz",
    "wof:placetype":"venue"
},
  "geometry": {"coordinates":[13.349562645,47.855255127],"type":"Point"}
}