{
  "type": "Feature",
  "properties": {
    "addr:full":"Ortliebg 27-29 Wien Wien 1170",
    "addr:postcode":"27-29;1170",
    "iso:country":"AT",
    "sg:address":"Ortliebg 27-29",
    "sg:city":"Wien",
    "sg:orig_category":"Autohandel",
    "sg:phone":"+43 1 48634540",
    "sg:postcode":"1170",
    "sg:province":"Wien",
    "sg:website":"volvo-simscha.at",
    "wof:name":"Volvo Simscha GmbH",
    "wof:placetype":"venue"
},
  "geometry": {"coordinates":[16.3298091888,48.2172203064],"type":"Point"}
}