{
  "type": "Feature",
  "properties": {
    "addr:full":"M\u00fchlweg 18 St. P\u00f6lten Nieder\u00f6sterreich 3100",
    "addr:housenumber":"18",
    "addr:postcode":"3100",
    "addr:street":"Muehlweg",
    "iso:country":"AT",
    "sg:address":"M\u00fchlweg 18",
    "sg:city":"St. P\u00f6lten",
    "sg:orig_category":"Tapezierer U Dekorateure",
    "sg:phone":"+43 4327 42362103",
    "sg:postcode":"3100",
    "sg:province":"Nieder\u00f6sterreich",
    "wof:name":"Starkl Anton",
    "wof:placetype":"venue"
},
  "geometry": {"coordinates":[-76.07303619379999,41.7845001221],"type":"Point"}
}