{
  "type": "Feature",
  "properties": {
    "addr:full":"Schulg 51 Wien Wien 1180",
    "addr:housenumber":"51",
    "addr:postcode":"1180",
    "addr:street":"Schulg",
    "iso:country":"AT",
    "sg:address":"Schulg 51",
    "sg:city":"Wien",
    "sg:orig_category":"Restaurants: Italienisch",
    "sg:phone":"+43 1 4082246",
    "sg:postcode":"1180",
    "sg:province":"Wien",
    "wof:name":"Pizzeria Cavallo Bianco",
    "wof:placetype":"venue"
},
  "geometry": {"coordinates":[16.3398838043,48.2251777649],"type":"Point"}
}