{
  "type": "Feature",
  "properties": {
    "addr:full":"Wagnerberg 12 St. Florian Ober\u00f6sterreich 4490",
    "addr:housenumber":"12",
    "addr:postcode":"4490",
    "addr:street":"Wagnerberg",
    "iso:country":"AT",
    "sg:address":"Wagnerberg 12",
    "sg:city":"St. Florian",
    "sg:orig_category":"Physiotherapie",
    "sg:phone":"+43 7224 4567",
    "sg:postcode":"4490",
    "sg:province":"Ober\u00f6sterreich",
    "wof:name":"Fink-Schwarzmayr Ingeborg Dipl-PT",
    "wof:placetype":"venue"
},
  "geometry": {"coordinates":[14.3457288742,48.2161026001],"type":"Point"}
}