{
  "type": "Feature",
  "properties": {
    "addr:full":"Eichenweg 13b Mondsee Ober\u00f6sterreich 5310",
    "addr:housenumber":"13b",
    "addr:postcode":"5310",
    "addr:street":"Eichenweg;Oberoesterreich",
    "iso:country":"AT",
    "sg:address":"Eichenweg 13b",
    "sg:city":"Mondsee",
    "sg:orig_category":"Samen U Saatgut",
    "sg:phone":"+43 4362 326768",
    "sg:postcode":"5310",
    "sg:province":"Ober\u00f6sterreich",
    "wof:name":"Schweizer Eric Royal GmbH",
    "wof:placetype":"venue"
},
  "geometry": {"coordinates":[13.349562645,47.855255127],"type":"Point"}
}