{
  "type": "Feature",
  "properties": {
    "iso:country":"AT",
    "sg:address":"Gu\u00dfriegelstr 28",
    "sg:city":"Wien",
    "sg:orig_category":"Weiterbildungsinstitute M Allg U Berufl Bildungsangebot",
    "sg:phone":"+43 1 8122501",
    "sg:postcode":"1100",
    "sg:province":"Wien",
    "sg:website":"www.diversitytraining.at",
    "wof:name":"Wagner + Partner diversity training",
    "wof:placetype":"venue"
},
  "geometry": {"coordinates":[16.3580055237,48.1734275818],"type":"Point"}
}