{
  "type": "Feature",
  "properties": {
    "addr:full":"Versorgungsheimstr 1 Wien Wien 1130",
    "addr:housenumber":"1",
    "addr:postcode":"1130",
    "addr:street":"Versorgungsheimstr",
    "iso:country":"AT",
    "sg:address":"Versorgungsheimstr 1",
    "sg:city":"Wien",
    "sg:orig_category":"\u00c3\u201erzte / F Allgemeinmedizin",
    "sg:phone":"+43 1 8047748",
    "sg:postcode":"1130",
    "sg:province":"Wien",
    "wof:name":"Krasselt Wolfgang Dr",
    "wof:placetype":"venue"
},
  "geometry": {"coordinates":[16.2840538025,48.1748733521],"type":"Point"}
}