{
  "type": "Feature",
  "properties": {
    "addr:full":"Pfarrg 42 Imst Tirol 6460",
    "addr:housenumber":"42",
    "addr:postcode":"6460",
    "addr:street":"Pfarrg;Tirol",
    "iso:country":"AT",
    "sg:address":"Pfarrg 42",
    "sg:city":"Imst",
    "sg:orig_category":"Banken U Sparkassen",
    "sg:phone":"+43 5412 61803",
    "sg:postcode":"6460",
    "sg:province":"Tirol",
    "wof:name":"Sparkasse Imst",
    "wof:placetype":"venue"
},
  "geometry": {"coordinates":[10.7409629822,47.2448272705],"type":"Point"}
}