{
  "type": "Feature",
  "properties": {
    "addr:full":"Gurthweg 4 Schruns Vorarlberg 6780",
    "addr:housenumber":"4",
    "addr:postcode":"6780",
    "addr:street":"Gurthweg",
    "iso:country":"AT",
    "sg:address":"Gurthweg 4",
    "sg:city":"Schruns",
    "sg:orig_category":"Tischlereien",
    "sg:phone":"+43 5556 77299",
    "sg:postcode":"6780",
    "sg:province":"Vorarlberg",
    "wof:name":"Jussel Kurt",
    "wof:placetype":"venue"
},
  "geometry": {"coordinates":[-91.3424530029,38.6716003418],"type":"Point"}
}