{
  "type": "Feature",
  "properties": {
    "addr:full":"Julius Haagn-Str 10 Salzburg Salzburg 5020",
    "addr:housenumber":"10",
    "addr:postcode":"5020",
    "addr:street":"Salzburg",
    "iso:country":"AT",
    "sg:address":"Julius Haagn-Str 10",
    "sg:city":"Salzburg",
    "sg:orig_category":"Feuerwerksartikel U Feuerwerke",
    "sg:phone":"+43 662 451283",
    "sg:postcode":"5020",
    "sg:province":"Salzburg",
    "wof:name":"Fenninger Wilhelm",
    "wof:placetype":"venue"
},
  "geometry": {"coordinates":[13.0385255814,47.8169212341],"type":"Point"}
}