{
  "type": "Feature",
  "properties": {
    "iso:country":"AT",
    "sg:address":"R\u00f6merstr 66",
    "sg:city":"G\u00f6fis",
    "sg:orig_category":"Elektroinstallationsunternehmen",
    "sg:phone":"+43 5522 78060",
    "sg:postcode":"6811",
    "sg:province":"Vorarlberg",
    "wof:name":"N\u00e4gele Elektro-Installationen-Steuerungen-Service",
    "wof:placetype":"venue"
},
  "geometry": {"coordinates":[-90.20757293699999,36.779548645],"type":"Point"}
}