{
  "type": "Feature",
  "properties": {
    "addr:full":"St.-Ulrich-Str 4 G\u00f6tzis Vorarlberg 6840",
    "addr:housenumber":"4",
    "addr:postcode":"6840",
    "addr:street":"St.-Ulrich-Str",
    "iso:country":"AT",
    "sg:address":"St.-Ulrich-Str 4",
    "sg:city":"G\u00f6tzis",
    "sg:orig_category":"Blumeneinzelhandel",
    "sg:phone":"+43 5523 55277",
    "sg:postcode":"6840",
    "sg:province":"Vorarlberg",
    "wof:name":"Immergr\u00fcn Keckeis Nicolussi OEG",
    "wof:placetype":"venue"
},
  "geometry": {"coordinates":[11.6672801971,46.5735092163],"type":"Point"}
}