{
  "type": "Feature",
  "properties": {
    "iso:country":"AT",
    "sg:address":"Franz-Lederer-Str 6",
    "sg:city":"Bruck an der Gro\u00dfglocknerstra\u00dfe",
    "sg:orig_category":"Transportunternehmen",
    "sg:phone":"+43 4365 456912",
    "sg:postcode":"5671",
    "sg:province":"Salzburg",
    "wof:name":"Schernthaner Ferdinand",
    "wof:placetype":"venue"
},
  "geometry": {"coordinates":[12.8310060501,47.2819252014],"type":"Point"}
}