{
  "type": "Feature",
  "properties": {
    "addr:full":"Hauptpl 7 Jennersdorf Burgenland 8380",
    "addr:housenumber":"7",
    "addr:postcode":"8380",
    "addr:street":"Hauptpl",
    "iso:country":"AT",
    "sg:address":"Hauptpl 7",
    "sg:city":"Jennersdorf",
    "sg:orig_category":"Apotheken",
    "sg:phone":"+43 3329 452260",
    "sg:postcode":"8380",
    "sg:province":"Burgenland",
    "wof:name":"Apotheke z Salvator",
    "wof:placetype":"venue"
},
  "geometry": {"coordinates":[16.1398887634,46.9374427795],"type":"Point"}
}