{
  "type": "Feature",
  "properties": {
    "addr:full":"Rinnegger Str 16 St. Radegund Steiermark 8061",
    "addr:housenumber":"16",
    "addr:postcode":"8061",
    "addr:street":"Str",
    "iso:country":"AT",
    "sg:address":"Rinnegger Str 16",
    "sg:city":"St. Radegund",
    "sg:orig_category":"Feuerwehren",
    "sg:phone":"+43 4331 3221688",
    "sg:postcode":"8061",
    "sg:province":"Steiermark",
    "wof:name":"Freiwillige Feuerwehr Rinnegg",
    "wof:placetype":"venue"
},
  "geometry": {"coordinates":[15.48736763,47.1643218994],"type":"Point"}
}