{
  "type": "Feature",
  "properties": {
    "iso:country":"AT",
    "sg:address":"Dorfstr 1",
    "sg:city":"Westendorf",
    "sg:orig_category":"Tabaktrafiken",
    "sg:phone":"+43 5334 6313",
    "sg:postcode":"6363",
    "sg:province":"Tirol",
    "wof:name":"Ladevic Jakob",
    "wof:placetype":"venue"
},
  "geometry": {"coordinates":[12.2140274048,47.4321098328],"type":"Point"}
}