{
  "type": "Feature",
  "properties": {
    "addr:full":"Schulweg 3 Stockerau Nieder\u00f6sterreich 2000",
    "addr:housenumber":"3",
    "addr:postcode":"2000",
    "addr:street":"Schulweg",
    "iso:country":"AT",
    "sg:address":"Schulweg 3",
    "sg:city":"Stockerau",
    "sg:orig_category":"Volksschulen",
    "sg:phone":"+43 2266 620350",
    "sg:postcode":"2000",
    "sg:province":"Nieder\u00f6sterreich",
    "wof:name":"Volksschule West",
    "wof:placetype":"venue"
},
  "geometry": {"coordinates":[16.2117786407,48.388381958],"type":"Point"}
}