{
  "type": "Feature",
  "properties": {
    "addr:full":"Buchberg 61 Bischofshofen Salzburg 5500",
    "addr:housenumber":"61",
    "addr:postcode":"5500",
    "addr:street":"Buchberg;Salzburg",
    "iso:country":"AT",
    "sg:address":"Buchberg 61",
    "sg:city":"Bischofshofen",
    "sg:orig_category":"Psychologen",
    "sg:phone":"+43 4365 02201106",
    "sg:postcode":"5500",
    "sg:province":"Salzburg",
    "wof:name":"Schatzl Werner Mag",
    "wof:placetype":"venue"
},
  "geometry": {"coordinates":[13.2230949402,47.4077987671],"type":"Point"}
}