{
  "type": "Feature",
  "properties": {
    "addr:full":"Esterhazystr 24 Eisenstadt Burgenland 7000",
    "addr:housenumber":"24",
    "addr:postcode":"7000",
    "addr:street":"Esterhazystr",
    "iso:country":"AT",
    "sg:address":"Esterhazystr 24",
    "sg:city":"Eisenstadt",
    "sg:orig_category":"Blumeneinzelhandel",
    "sg:phone":"+43 2682 63284",
    "sg:postcode":"7000",
    "sg:province":"Burgenland",
    "wof:name":"Bl\u00fcten creationen - Daniela Geisendorfer",
    "wof:placetype":"venue"
},
  "geometry": {"coordinates":[16.5156879425,47.8460121155],"type":"Point"}
}