{
  "type": "Feature",
  "properties": {
    "addr:full":"Kniewas 26 Steyrling Ober\u00f6sterreich 4571",
    "addr:housenumber":"26",
    "addr:postcode":"4571",
    "addr:street":"Kniewas",
    "iso:country":"AT",
    "sg:address":"Kniewas 26",
    "sg:city":"Steyrling",
    "sg:classifiers":[
        {
            "category":"Manufacturing",
            "subcategory":"Wood Products",
            "type":"Manufacturing & Wholesale Goods"
        }
    ],
    "sg:phone":"+43 7565 201",
    "sg:postcode":"4571",
    "sg:province":"Ober\u00f6sterreich",
    "sg:tags":[
        "firewood"
    ],
    "wof:name":"Schlader-Holzhandels-KEG",
    "wof:placetype":"venue"
},
  "geometry": {"coordinates":[14.1571464539,47.831653595],"type":"Point"}
}