{
  "type": "Feature",
  "properties": {
    "addr:full":"Wahastr 25 B\u00fcrmoos Salzburg 5111",
    "addr:housenumber":"25",
    "addr:postcode":"5111",
    "addr:street":"Wahastr",
    "iso:country":"AT",
    "sg:address":"Wahastr 25",
    "sg:city":"B\u00fcrmoos",
    "sg:orig_category":"Aluminiumbe- U -Verarbeitung",
    "sg:phone":"+43 6274 47700",
    "sg:postcode":"5111",
    "sg:province":"Salzburg",
    "wof:name":"Salzburger Leichtmetallgie\u00dferei GesmbH",
    "wof:placetype":"venue"
},
  "geometry": {"coordinates":[12.9315729141,47.9873695374],"type":"Point"}
}