{
  "type": "Feature",
  "properties": {
    "iso:country":"AT",
    "sg:address":"Weinberggasse 41 ",
    "sg:city":"Wien",
    "sg:classifiers":[
        {
            "category":"Building & Trades",
            "subcategory":"Plumbing",
            "type":"Services"
        }
    ],
    "sg:phone":"+43 1 3682683",
    "sg:postcode":"1190",
    "sg:province":"Wien",
    "sg:tags":[
        "supraregional",
        "gas"
    ],
    "sg:website":"www.haunschmidt.com",
    "wof:name":"Haunschmidt GesmbH & Co KG",
    "wof:placetype":"venue"
},
  "geometry": {"coordinates":[16.3355674744,48.2432746887],"type":"Point"}
}