{
  "type": "Feature",
  "properties": {
    "addr:full":"Harl 126 Puch Steiermark 8182",
    "addr:housenumber":"126",
    "addr:postcode":"8182",
    "addr:street":"Harl",
    "iso:country":"AT",
    "sg:address":"Harl 126",
    "sg:city":"Puch",
    "sg:orig_category":"Maler, Anstreicher U Lackierer",
    "sg:phone":"+43 4331 773333",
    "sg:postcode":"8182",
    "sg:province":"Steiermark",
    "wof:name":"Haider Peter - Malermeister Fassadenanstrich Holzschutz",
    "wof:placetype":"venue"
},
  "geometry": {"coordinates":[15.7093105316,47.243473053],"type":"Point"}
}