{
  "type": "Feature",
  "properties": {
    "addr:full":"Sackg 6 Leoben Steiermark 8700",
    "addr:housenumber":"6",
    "addr:postcode":"8700",
    "addr:street":"Sackg",
    "iso:country":"AT",
    "sg:address":"Sackg 6",
    "sg:city":"Leoben",
    "sg:orig_category":"Maler, Anstreicher U Lackierer",
    "sg:phone":"+43 4338 4247833",
    "sg:postcode":"8700",
    "sg:province":"Steiermark",
    "wof:name":"Fuchs Robert Malermeister",
    "wof:placetype":"venue"
},
  "geometry": {"coordinates":[15.0984802246,47.3788909912],"type":"Point"}
}