{
  "type": "Feature",
  "properties": {
    "addr:full":"Universit\u00e4tsstr 102 Klagenfurt K\u00e4rnten 9020",
    "addr:housenumber":"102",
    "addr:postcode":"9020",
    "addr:street":"Kaernten",
    "iso:country":"AT",
    "sg:address":"Universit\u00e4tsstr 102",
    "sg:city":"Klagenfurt",
    "sg:orig_category":"Fitnesscenter",
    "sg:phone":"+43 463 250060",
    "sg:postcode":"9020",
    "sg:province":"K\u00e4rnten",
    "sg:website":"california-fitness.at",
    "wof:name":"Fitness-Wellness-Center California",
    "wof:placetype":"venue"
},
  "geometry": {"coordinates":[14.2620134354,46.6174468994],"type":"Point"}
}