{
  "type": "Feature",
  "properties": {
    "iso:country":"AT",
    "sg:address":"Mozartstra\u00dfe 1",
    "sg:city":"Feldkirchen in K\u00e4rnten",
    "sg:orig_category":"Reisen, Reiseveranstalter",
    "sg:phone":"+43 4342 7648200",
    "sg:postcode":"9560",
    "sg:province":"K\u00e4rnten",
    "sg:website":"http://www.sports.privateweb.at/yachtcharter/barbarella_xx.htm",
    "wof:name":"yachtcharter barbarella",
    "wof:placetype":"venue"
},
  "geometry": {"coordinates":[14.0920295715,46.7234268188],"type":"Point"}
}