{
  "type": "Feature",
  "properties": {
    "addr:full":"Nr 116 St. Konrad Ober\u00f6sterreich 4817",
    "addr:postcode":"4817",
    "addr:street":"Nr 116;Oberoesterreich",
    "iso:country":"AT",
    "sg:address":"Nr 116",
    "sg:city":"St. Konrad",
    "sg:orig_category":"Massagen",
    "sg:phone":"+43 76158285",
    "sg:postcode":"4817",
    "sg:province":"Ober\u00f6sterreich",
    "wof:name":"Gegenhuber Milena",
    "wof:placetype":"venue"
},
  "geometry": {"coordinates":[13.8887310028,47.9127082825],"type":"Point"}
}