{
  "type": "Feature",
  "properties": {
    "addr:full":"Brennereistr 15 Wels Ober\u00f6sterreich 4600",
    "addr:housenumber":"15",
    "addr:postcode":"4600",
    "addr:street":"Brennereistr;Oberoesterreich",
    "iso:country":"AT",
    "sg:address":"Brennereistr 15",
    "sg:city":"Wels",
    "sg:orig_category":"Suchtberatung / Alkohol, Drogen, Zigaretten",
    "sg:phone":"+43 7242 29585",
    "sg:postcode":"4600",
    "sg:province":"Ober\u00f6sterreich",
    "wof:name":"Raucherberatungsstelle",
    "wof:placetype":"venue"
},
  "geometry": {"coordinates":[14.0139541626,48.1600379944],"type":"Point"}
}