{
  "type": "Feature",
  "properties": {
    "iso:country":"AT",
    "sg:address":"Prinz Eugen Str. 12",
    "sg:city":"Oberwart",
    "sg:classifiers":[
        {
            "category":"Utilities",
            "subcategory":"Electric",
            "type":"Services"
        }
    ],
    "sg:phone":"+43 4333 52384820",
    "sg:postcode":"7400",
    "sg:province":"Burgenland",
    "sg:tags":[
        "electricity"
    ],
    "wof:name":"RM DATA DATENVERARBEITUNGSGESMBH",
    "wof:placetype":"venue"
},
  "geometry": {"coordinates":[16.2157287598,47.2900657654],"type":"Point"}
}