{
  "type": "Feature",
  "properties": {
    "iso:country":"AT",
    "sg:address":"Mantscha 160",
    "sg:city":"Wetzelsdorf",
    "sg:classifiers":[
        {
            "category":"Communications",
            "subcategory":"Television Station",
            "type":"Services"
        }
    ],
    "sg:phone":"+43 4331 6682260",
    "sg:postcode":"8052",
    "sg:province":"Steiermark",
    "sg:tags":[
        "equipment",
        "optical",
        "instrument"
    ],
    "wof:name":"FOTOSTUDIO BETRIEBS GMBH & CO. KG",
    "wof:placetype":"venue"
},
  "geometry": {"coordinates":[15.361410141,47.0497550964],"type":"Point"}
}