{
  "type": "Feature",
  "properties": {
    "addr:full":"Dr.-Bruno-Kreisky-Str 10 Kottingbrunn Nieder\u00f6sterreich 2542",
    "addr:housenumber":"10",
    "addr:postcode":"2542",
    "addr:street":"Dr.-Bruno-Kreisky-Str",
    "iso:country":"AT",
    "sg:address":"Dr.-Bruno-Kreisky-Str 10",
    "sg:city":"Kottingbrunn",
    "sg:orig_category":"Gitter",
    "sg:phone":"+43 2252 739990",
    "sg:postcode":"2542",
    "sg:province":"Nieder\u00f6sterreich",
    "wof:name":"GTI - Gitter Tore Industriez\u00e4une Industrievertretungen Eiselt Erich",
    "wof:placetype":"venue"
},
  "geometry": {"coordinates":[16.2366828918,47.9620666504],"type":"Point"}
}