{
  "type": "Feature",
  "properties": {
    "addr:full":"Wiesbergg 12 Wien Wien 1160",
    "addr:housenumber":"12",
    "addr:postcode":"1160",
    "addr:street":"Wiesbergg",
    "iso:country":"AT",
    "sg:address":"Wiesbergg 12",
    "sg:city":"Wien",
    "sg:orig_category":"Friseure U Frisiersalons",
    "sg:phone":"+43 1 4935559",
    "sg:postcode":"1160",
    "sg:province":"Wien",
    "wof:name":"Fischer Erwin",
    "wof:placetype":"venue"
},
  "geometry": {"coordinates":[16.3067455292,48.2095947266],"type":"Point"}
}