{
  "type": "Feature",
  "properties": {
    "iso:country":"AT",
    "sg:address":"Klosterwaldsdlg 660",
    "sg:city":"Seefeld in Tirol",
    "sg:classifiers":[
        {
            "category":"Taxi",
            "type":"Transportation"
        }
    ],
    "sg:phone":"+43 4352 123194",
    "sg:postcode":"6100",
    "sg:province":"Tirol",
    "sg:tags":[
        "personentransporte",
        "u"
    ],
    "wof:name":"Heigl Helmut",
    "wof:placetype":"venue"
},
  "geometry": {"coordinates":[11.1784286499,47.3336448669],"type":"Point"}
}