{
  "type": "Feature",
  "properties": {
    "iso:country":"AT",
    "sg:address":"Bauern 11",
    "sg:city":"Altach",
    "sg:orig_category":"Immobilienmakler",
    "sg:phone":"+43 5576 724740",
    "sg:postcode":"6844",
    "sg:province":"Vorarlberg",
    "sg:website":"rheintal.at",
    "wof:name":"Rheintal-Immobilien Marte + Rohrer GesmbH",
    "wof:placetype":"venue"
},
  "geometry": {"coordinates":[9.6611042023,47.353099823],"type":"Point"}
}