{
  "type": "Feature",
  "properties": {
    "addr:full":"Wollbell 17 Axams Tirol 6094",
    "addr:housenumber":"17",
    "addr:postcode":"6094",
    "addr:street":"Wollbell;Tirol",
    "iso:country":"AT",
    "sg:address":"Wollbell 17",
    "sg:city":"Axams",
    "sg:classifiers":[
        {
            "category":"Utilities",
            "subcategory":"Electric",
            "type":"Services"
        }
    ],
    "sg:phone":"+43 5234 67124",
    "sg:postcode":"6094",
    "sg:province":"Tirol",
    "sg:tags":[
        "heater",
        "storage",
        "heaters",
        "night"
    ],
    "sg:website":"ecoh.at",
    "wof:name":"Ecoh Kachelspeicher-Heizsystem",
    "wof:placetype":"venue"
},
  "geometry": {"coordinates":[11.2744178772,47.2450294495],"type":"Point"}
}