{
  "type": "Feature",
  "properties": {
    "iso:country":"AT",
    "sg:address":"Waldbachstr 3",
    "sg:city":"Asperhofen",
    "sg:orig_category":"Entsorgungen",
    "sg:phone":"+43 2772 58514",
    "sg:postcode":"3041",
    "sg:province":"Nieder\u00f6sterreich",
    "wof:name":"Leitner G\u00fcnter",
    "wof:placetype":"venue"
},
  "geometry": {"coordinates":[15.9420251846,48.2530097961],"type":"Point"}
}