{
  "type": "Feature",
  "properties": {
    "addr:full":"Volksfeststr 32 Linz Ober\u00f6sterreich 4020",
    "addr:housenumber":"32",
    "addr:postcode":"4020",
    "addr:street":"Volksfeststr",
    "iso:country":"AT",
    "sg:address":"Volksfeststr 32",
    "sg:city":"Linz",
    "sg:orig_category":"Familien / Beratung",
    "sg:phone":"+43 732 782441",
    "sg:postcode":"4020",
    "sg:province":"Ober\u00f6sterreich",
    "wof:name":"Aktion Recht des Kindes auf beide Eltern",
    "wof:placetype":"venue"
},
  "geometry": {"coordinates":[14.2990140915,48.3021507263],"type":"Point"}
}