{
  "type": "Feature",
  "properties": {
    "addr:full":"Vorlaufstrasse 1 Wien Wien 1010",
    "addr:housenumber":"1",
    "addr:postcode":"1010",
    "addr:street":"Vorlaufstrasse",
    "iso:country":"AT",
    "sg:address":"Vorlaufstrasse 1",
    "sg:city":"Wien",
    "sg:classifiers":[
        {
            "category":"Shopping",
            "subcategory":"Clothing, Apparel, & Fashions",
            "type":"Retail Goods"
        }
    ],
    "sg:phone":"+43 1 5333217",
    "sg:postcode":"1010",
    "sg:province":"Wien",
    "sg:tags":[
        "haberdashery"
    ],
    "wof:name":"Heinrich Klos KG",
    "wof:placetype":"venue"
},
  "geometry": {"coordinates":[16.3726100922,48.2121543884],"type":"Point"}
}