{
  "type": "Feature",
  "properties": {
    "iso:country":"AT",
    "sg:address":"Negrellistr 29",
    "sg:city":"Lustenau",
    "sg:orig_category":"Torantriebe",
    "sg:phone":"+43 5577 62849",
    "sg:postcode":"6890",
    "sg:province":"Vorarlberg",
    "sg:website":"elektro-fitz.at",
    "wof:name":"Fitz Elektro & Antriebstechnik",
    "wof:placetype":"venue"
},
  "geometry": {"coordinates":[9.6550788879,47.4175796509],"type":"Point"}
}