{
  "type": "Feature",
  "properties": {
    "iso:country":"AT",
    "sg:address":"Bahnhofstr 31",
    "sg:city":"Feistritz an der Drau",
    "sg:orig_category":"Glasereien",
    "sg:phone":"+43 4342 453042",
    "sg:postcode":"9710",
    "sg:province":"K\u00e4rnten",
    "wof:name":"Gasser Gerfried",
    "wof:placetype":"venue"
},
  "geometry": {"coordinates":[13.6680831909,46.7062416077],"type":"Point"}
}