{
  "type": "Feature",
  "properties": {
    "addr:full":"Fischelg 6 Wiener Neustadt Nieder\u00f6sterreich 2700",
    "addr:housenumber":"6",
    "addr:postcode":"2700",
    "addr:street":"Fischelg",
    "iso:country":"AT",
    "sg:address":"Fischelg 6",
    "sg:city":"Wiener Neustadt",
    "sg:orig_category":"Tabaktrafiken",
    "sg:phone":"+43 2622 24239",
    "sg:postcode":"2700",
    "sg:province":"Nieder\u00f6sterreich",
    "wof:name":"Gneist Christine",
    "wof:placetype":"venue"
},
  "geometry": {"coordinates":[16.2222099304,47.8069534302],"type":"Point"}
}