{
  "type": "Feature",
  "properties": {
    "addr:full":"Babenbergerstrasse 96 Graz Steiermark 8020",
    "addr:housenumber":"96",
    "addr:postcode":"8020",
    "addr:street":"Babenbergerstrasse",
    "iso:country":"AT",
    "sg:address":"Babenbergerstrasse 96",
    "sg:city":"Graz",
    "sg:classifiers":[
        {
            "category":"Military Area",
            "subcategory":"Army Base",
            "type":"Public Place"
        }
    ],
    "sg:phone":"+43 316 714145",
    "sg:postcode":"8020",
    "sg:province":"Steiermark",
    "sg:tags":[
        "cardboard"
    ],
    "wof:name":"Max Hadler Kartonagenerzeugungs-Ges.m.b.H.",
    "wof:placetype":"venue"
},
  "geometry": {"coordinates":[15.4184541702,47.0790939331],"type":"Point"}
}