{
  "type": "Feature",
  "properties": {
    "addr:full":"Leopoldstr 52a Innsbruck Tirol 6020",
    "addr:housenumber":"52a",
    "addr:postcode":"6020",
    "addr:street":"Leopoldstr;Tirol",
    "iso:country":"AT",
    "sg:address":"Leopoldstr 52a",
    "sg:city":"Innsbruck",
    "sg:orig_category":"Bauunternehmen",
    "sg:phone":"+43 512 594040",
    "sg:postcode":"6020",
    "sg:province":"Tirol",
    "wof:name":"A.S.T. BaugesmbH",
    "wof:placetype":"venue"
},
  "geometry": {"coordinates":[11.3974485397,47.2568130493],"type":"Point"}
}