{
  "type": "Feature",
  "properties": {
    "iso:country":"AT",
    "sg:address":"Pillweinstrasse 10",
    "sg:city":"Linz",
    "sg:classifiers":[
        {
            "category":"Military Area",
            "subcategory":"Coast Guard Base",
            "type":"Public Place"
        }
    ],
    "sg:phone":"+43 732 668078",
    "sg:postcode":"4020",
    "sg:province":"Ober\u00f6sterreich",
    "sg:tags":[
        "banknote",
        "slot-boxes",
        "counter",
        "cash",
        "boxes",
        "cheque",
        "banks"
    ],
    "wof:name":"Gerhard Rauscher",
    "wof:placetype":"venue"
},
  "geometry": {"coordinates":[14.2971582413,48.2883872986],"type":"Point"}
}