{
  "type": "Feature",
  "properties": {
    "iso:country":"AT",
    "sg:address":"Bulgaripl 14/1",
    "sg:city":"Linz",
    "sg:orig_category":"Personalbereitstellung",
    "sg:phone":"+43 4373 269225070",
    "sg:postcode":"4020",
    "sg:province":"Ober\u00f6sterreich",
    "wof:name":"espora. die Personalexperten GmbH",
    "wof:placetype":"venue"
},
  "geometry": {"coordinates":[14.3014659882,48.2848243713],"type":"Point"}
}