{
  "type": "Feature",
  "properties": {
    "addr:full":"Leinburger Str 11 Wartberg an der Krems Ober\u00f6sterreich 4552",
    "addr:postcode":"4552",
    "addr:street":"Str 11",
    "iso:country":"AT",
    "sg:address":"Leinburger Str 11",
    "sg:city":"Wartberg an der Krems",
    "sg:classifiers":[
        {
            "category":"Taxi",
            "type":"Transportation"
        }
    ],
    "sg:phone":"+43 676 847584201",
    "sg:postcode":"4552",
    "sg:province":"Ober\u00f6sterreich",
    "sg:tags":[
        "personentransporte",
        "u"
    ],
    "sg:website":"flydriver.com",
    "wof:name":"FLY DRIVER G\u00fcter- u Personenbef\u00f6rderungs GmbH",
    "wof:placetype":"venue"
},
  "geometry": {"coordinates":[14.1231660843,47.9861946106],"type":"Point"}
}