{
  "type": "Feature",
  "properties": {
    "addr:full":"Grazer Str 13 Peggau Steiermark 8120",
    "addr:housenumber":"13",
    "addr:postcode":"8120",
    "addr:street":"Str",
    "iso:country":"AT",
    "sg:address":"Grazer Str 13",
    "sg:city":"Peggau",
    "sg:orig_category":"Pumpen",
    "sg:phone":"+43 3127 209250",
    "sg:postcode":"8120",
    "sg:province":"Steiermark",
    "wof:name":"Wilo HandelsgesmbH EMU-Vertriebsb\u00fcro",
    "wof:placetype":"venue"
},
  "geometry": {"coordinates":[15.3457956314,47.2038345337],"type":"Point"}
}