{
  "type": "Feature",
  "properties": {
    "iso:country":"AT",
    "sg:address":"Karl-Vogt-Str 72",
    "sg:city":"Zell am See",
    "sg:orig_category":"Physikalische Institute",
    "sg:phone":"+43 6542 53447",
    "sg:postcode":"5700",
    "sg:province":"Salzburg",
    "wof:name":"Pudil Thomas",
    "wof:placetype":"venue"
},
  "geometry": {"coordinates":[12.8005123138,47.304309845],"type":"Point"}
}