{
  "type": "Feature",
  "properties": {
    "iso:country":"AT",
    "sg:address":"Bergenstammg 9b",
    "sg:city":"Wien",
    "sg:orig_category":"Gerichtsdolmetscher",
    "sg:phone":"+43 1 8766194",
    "sg:postcode":"1130",
    "sg:province":"Wien",
    "wof:name":"Jahns-Milodanovic Anna Maria Mag phil",
    "wof:placetype":"venue"
},
  "geometry": {"coordinates":[16.2721138,48.1912117004],"type":"Point"}
}