{
  "type": "Feature",
  "properties": {
    "iso:country":"AT",
    "sg:address":"Landstr 14",
    "sg:city":"Bregenz",
    "sg:orig_category":"Waagen / Einzelhandel",
    "sg:phone":"+43 5574 73577",
    "sg:postcode":"6900",
    "sg:province":"Vorarlberg",
    "wof:name":"Bizerba Waagen GesmbH & Co KG",
    "wof:placetype":"venue"
},
  "geometry": {"coordinates":[9.7381305695,47.4915466309],"type":"Point"}
}