{
  "type": "Feature",
  "properties": {
    "iso:country":"AT",
    "sg:address":"Landstra\u00dfer Hauptstr 109",
    "sg:city":"Wien",
    "sg:orig_category":"Unterhaltungselektronik / Einzelhandel",
    "sg:phone":"+43 1 7122411",
    "sg:postcode":"1030",
    "sg:province":"Wien",
    "wof:name":"RED ZAC - Lefkowits GmbH",
    "wof:placetype":"venue"
},
  "geometry": {"coordinates":[16.3957080841,48.1973571777],"type":"Point"}
}