{
  "type": "Feature",
  "properties": {
    "addr:full":"Haydnstr 8 Schwertberg Ober\u00f6sterreich 4311",
    "addr:housenumber":"8",
    "addr:postcode":"4311",
    "addr:street":"Haydnstr",
    "iso:country":"AT",
    "sg:address":"Haydnstr 8",
    "sg:city":"Schwertberg",
    "sg:orig_category":"Volkshochschulen",
    "sg:phone":"+43 7262 61336",
    "sg:postcode":"4311",
    "sg:province":"Ober\u00f6sterreich",
    "wof:name":"Volkshochschule Ober\u00f6sterreich gemeinn\u00fctzige Bildungs-GmbH d AK f O\u00d6",
    "wof:placetype":"venue"
},
  "geometry": {"coordinates":[14.5731334686,48.2725791931],"type":"Point"}
}