{
  "type": "Feature",
  "properties": {
    "addr:full":"Grazer Strasse 68 Wiener Neustadt Nieder\u00f6sterreich 2700",
    "addr:housenumber":"68",
    "addr:postcode":"2700",
    "addr:street":"Grazer Strasse",
    "iso:country":"AT",
    "sg:address":"Grazer Strasse 68",
    "sg:city":"Wiener Neustadt",
    "sg:orig_category":"Internet Terminals",
    "sg:phone":"+43 2622 88944",
    "sg:postcode":"2700",
    "sg:province":"Nieder\u00f6sterreich",
    "sg:website":"infotronik.at",
    "wof:name":"Infotronik.at",
    "wof:placetype":"venue"
},
  "geometry": {"coordinates":[16.2458724976,47.8145523071],"type":"Point"}
}