{
  "type": "Feature",
  "properties": {
    "iso:country":"AT",
    "sg:address":"Weiherstr 13A",
    "sg:city":"Lustenau",
    "sg:orig_category":"Apparatebau",
    "sg:phone":"+43 5577 85098",
    "sg:postcode":"6890",
    "sg:province":"Vorarlberg",
    "wof:name":"HSH Ger\u00e4tebau GmbH & Co KG",
    "wof:placetype":"venue"
},
  "geometry": {"coordinates":[9.6719551086,47.4320030212],"type":"Point"}
}