{
  "type": "Feature",
  "properties": {
    "addr:full":"Bahnhofstr 27 Peuerbach Ober\u00f6sterreich 4722",
    "addr:housenumber":"27",
    "addr:postcode":"4722",
    "addr:street":"Bahnhofstr",
    "iso:country":"AT",
    "sg:address":"Bahnhofstr 27",
    "sg:city":"Peuerbach",
    "sg:orig_category":"Autohandel",
    "sg:phone":"+43 7276 2206",
    "sg:postcode":"4722",
    "sg:province":"Ober\u00f6sterreich",
    "wof:name":"KFZ-Handel Klaffenb\u00f6ck",
    "wof:placetype":"venue"
},
  "geometry": {"coordinates":[13.7717208862,48.3390655518],"type":"Point"}
}