{
  "type": "Feature",
  "properties": {
    "iso:country":"AT",
    "sg:address":"Garnisong 10",
    "sg:city":"Wien",
    "sg:orig_category":"Restaurants: Indisch",
    "sg:phone":"+43 1 4074234",
    "sg:postcode":"1090",
    "sg:province":"Wien",
    "wof:name":"Restaurant Safran",
    "wof:placetype":"venue"
},
  "geometry": {"coordinates":[16.3569602966,48.215927124],"type":"Point"}
}