{
  "type": "Feature",
  "properties": {
    "addr:full":"Wehrg 5a Salzburg Salzburg 5020",
    "addr:housenumber":"5a",
    "addr:postcode":"5020",
    "addr:street":"Wehrg;Salzburg",
    "iso:country":"AT",
    "sg:address":"Wehrg 5a",
    "sg:city":"Salzburg",
    "sg:orig_category":"Fliesen- U Plattenverlegungen",
    "sg:phone":"+43 4366 28323770",
    "sg:postcode":"5020",
    "sg:province":"Salzburg",
    "wof:name":"P\u00f6schl Hans GesmbH",
    "wof:placetype":"venue"
},
  "geometry": {"coordinates":[13.0204906464,47.7983818054],"type":"Point"}
}