{
  "type": "Feature",
  "properties": {
    "iso:country":"AT",
    "sg:address":"Karolingerstr 29",
    "sg:city":"Salzburg",
    "sg:orig_category":"Pensionen / Privatzimmer",
    "sg:phone":"+43 662 827469",
    "sg:postcode":"5020",
    "sg:province":"Salzburg",
    "wof:name":"Haus Kernstock - bed&breakfast",
    "wof:placetype":"venue"
},
  "geometry": {"coordinates":[13.0117883682,47.7939796448],"type":"Point"}
}