{
  "type": "Feature",
  "properties": {
    "iso:country":"AT",
    "sg:address":"Zemannstr 19",
    "sg:city":"Freistadt",
    "sg:classifiers":[
        {
            "category":"Restaurant",
            "type":"Food & Drink"
        }
    ],
    "sg:phone":"+43 4379 4273640",
    "sg:postcode":"4240",
    "sg:province":"Ober\u00f6sterreich",
    "sg:tags":[
        "pizzeria"
    ],
    "wof:name":"Pizzeria Sole Mare Inh. Mag. H. Hinedi",
    "wof:placetype":"venue"
},
  "geometry": {"coordinates":[14.5040435791,48.5084190369],"type":"Point"}
}