{
  "type": "Feature",
  "properties": {
    "addr:full":"Bergmanng Graz Steiermark 8010",
    "addr:postcode":"8010",
    "iso:country":"AT",
    "sg:address":"Bergmanng",
    "sg:city":"Graz",
    "sg:orig_category":"Tankstellen",
    "sg:phone":"+43 316 3240560",
    "sg:postcode":"8010",
    "sg:province":"Steiermark",
    "wof:name":"Shell Austria GmbH",
    "wof:placetype":"venue"
},
  "geometry": {"coordinates":[15.4373922348,47.0856933594],"type":"Point"}
}