{
  "type": "Feature",
  "properties": {
    "iso:country":"AT",
    "sg:address":"Zehnerg\u00fcrtel/Brunner Stra\u00dfe",
    "sg:city":"Wiener Neustadt",
    "sg:classifiers":[
        {
            "category":"Manufacturing",
            "subcategory":"Wood Products",
            "type":"Manufacturing & Wholesale Goods"
        }
    ],
    "sg:phone":"+43 2622 212120",
    "sg:postcode":"2700",
    "sg:province":"Nieder\u00f6sterreich",
    "sg:tags":[
        "gate",
        "made",
        "door"
    ],
    "sg:website":"holzwurm.at",
    "wof:name":"Zum Holzwurm Lechner Johann, Holzhandel",
    "wof:placetype":"venue"
},
  "geometry": {"coordinates":[16.2455158234,47.8128814697],"type":"Point"}
}