{
  "type": "Feature",
  "properties": {
    "addr:full":"Hauptpl 12 Tulln an der Donau Nieder\u00f6sterreich 3430",
    "addr:housenumber":"12",
    "addr:postcode":"3430",
    "addr:street":"Hauptpl",
    "iso:country":"AT",
    "sg:address":"Hauptpl 12",
    "sg:city":"Tulln an der Donau",
    "sg:classifiers":[
        {
            "category":"Restaurant",
            "type":"Food & Drink"
        }
    ],
    "sg:phone":"+43 4322 7261670",
    "sg:postcode":"3430",
    "sg:province":"Nieder\u00f6sterreich",
    "wof:name":"Restaurant S'Pfandl",
    "wof:placetype":"venue"
},
  "geometry": {"coordinates":[16.0508003235,48.330745697],"type":"Point"}
}