{
  "type": "Feature",
  "properties": {
    "addr:full":"Tiroler Str 80 Villach K\u00e4rnten 9500",
    "addr:housenumber":"80",
    "addr:postcode":"9500",
    "addr:street":"Str;Kaernten",
    "iso:country":"AT",
    "sg:address":"Tiroler Str 80",
    "sg:city":"Villach",
    "sg:orig_category":"Elektronik",
    "sg:phone":"+43 4242 580300",
    "sg:postcode":"9500",
    "sg:province":"K\u00e4rnten",
    "wof:name":"active photonics AG - Visualisierungs- und Kommunikationssysteme",
    "wof:placetype":"venue"
},
  "geometry": {"coordinates":[13.8260374069,46.6157226562],"type":"Point"}
}