{
  "type": "Feature",
  "properties": {
    "addr:full":"Kardinalpl 2 Klagenfurt K\u00e4rnten 9020",
    "addr:housenumber":"2",
    "addr:postcode":"9020",
    "addr:street":"Kardinalpl;Kaernten",
    "iso:country":"AT",
    "sg:address":"Kardinalpl 2",
    "sg:city":"Klagenfurt",
    "sg:orig_category":"Installationsunternehmen",
    "sg:phone":"+43 463 54194",
    "sg:postcode":"9020",
    "sg:province":"K\u00e4rnten",
    "wof:name":"Wank Johann & S\u00f6hne Sanit\u00e4r- und Heizungsanlagen GesmbH",
    "wof:placetype":"venue"
},
  "geometry": {"coordinates":[14.3117637634,46.6238021851],"type":"Point"}
}