{
  "type": "Feature",
  "properties": {
    "addr:full":"Schuppeng 24 Wien Wien 1230",
    "addr:housenumber":"24",
    "addr:postcode":"1230",
    "addr:street":"Schuppeng",
    "iso:country":"AT",
    "sg:address":"Schuppeng 24",
    "sg:city":"Wien",
    "sg:classifiers":[
        {
            "category":"Professional",
            "type":"Services"
        }
    ],
    "sg:phone":"+43 4367 64748487",
    "sg:postcode":"1230",
    "sg:province":"Wien",
    "sg:tags":[
        "relocation"
    ],
    "wof:name":"TL Relocation",
    "wof:placetype":"venue"
},
  "geometry": {"coordinates":[16.3238296509,48.1500396729],"type":"Point"}
}