{
  "type": "Feature",
  "properties": {
    "addr:full":"Waltenbachstr. 9 Leoben Steiermark 8700",
    "addr:housenumber":"9",
    "addr:postcode":"8700",
    "addr:street":"Waltenbachstr.",
    "iso:country":"AT",
    "sg:address":"Waltenbachstr. 9",
    "sg:city":"Leoben",
    "sg:classifiers":[
        {
            "category":"Professional",
            "subcategory":"Business Services",
            "type":"Services"
        }
    ],
    "sg:phone":"+43 4338 428050",
    "sg:postcode":"8700",
    "sg:province":"Steiermark",
    "sg:tags":[
        "advice"
    ],
    "wof:name":"KNAPP SYSTEMINTEGRATION GMBH",
    "wof:placetype":"venue"
},
  "geometry": {"coordinates":[15.1310968399,47.3851470947],"type":"Point"}
}