{
  "type": "Feature",
  "properties": {
    "addr:full":"Leonsteiner Str 21 Leonstein Ober\u00f6sterreich 4592",
    "addr:postcode":"4592",
    "addr:street":"Str;Oberoesterreich",
    "iso:country":"AT",
    "sg:address":"Leonsteiner Str 21",
    "sg:city":"Leonstein",
    "sg:orig_category":"Tankstellen",
    "sg:phone":"+43 7584 2594",
    "sg:postcode":"4592",
    "sg:province":"Ober\u00f6sterreich",
    "wof:name":"OMV AG",
    "wof:placetype":"venue"
},
  "geometry": {"coordinates":[14.2307786942,47.8972206116],"type":"Point"}
}