{
  "type": "Feature",
  "properties": {
    "addr:full":"Klagenfurter Str 15 Villach K\u00e4rnten 9500",
    "addr:housenumber":"15",
    "addr:postcode":"9500",
    "addr:street":"Str;Kaernten",
    "iso:country":"AT",
    "sg:address":"Klagenfurter Str 15",
    "sg:city":"Villach",
    "sg:orig_category":"Installationsunternehmen",
    "sg:phone":"+43 4242 246970",
    "sg:postcode":"9500",
    "sg:province":"K\u00e4rnten",
    "wof:name":"Graf Fritz & Co GmbH",
    "wof:placetype":"venue"
},
  "geometry": {"coordinates":[13.850528717,46.6174468994],"type":"Point"}
}