{
  "type": "Feature",
  "properties": {
    "iso:country":"AT",
    "sg:address":"Hackeng 5",
    "sg:city":"Wien",
    "sg:orig_category":"Psychotherapie",
    "sg:phone":"+43 1 9850529",
    "sg:postcode":"1150",
    "sg:province":"Wien",
    "wof:name":"Wyckoff Paul",
    "wof:placetype":"venue"
},
  "geometry": {"coordinates":[16.3342590332,48.1977653503],"type":"Point"}
}