{
  "type": "Feature",
  "properties": {
    "iso:country":"AT",
    "sg:address":"Sankt-Peter-Strasse 31",
    "sg:city":"Hausmannst\u00e4tten",
    "sg:orig_category":"Antique Stoves, Period Stoves",
    "sg:phone":"+43 3135 46914",
    "sg:postcode":"8071",
    "sg:province":"Steiermark",
    "wof:name":"Ilse Kurz Keramikatelier",
    "wof:placetype":"venue"
},
  "geometry": {"coordinates":[6.4325399399,51.3476600647],"type":"Point"}
}