{
  "type": "Feature",
  "properties": {
    "addr:full":"Lambacher Str 29a Haag am Hausruck Ober\u00f6sterreich 4680",
    "addr:postcode":"4680",
    "addr:street":"Str 29A",
    "iso:country":"AT",
    "sg:address":"Lambacher Str 29a",
    "sg:city":"Haag am Hausruck",
    "sg:orig_category":"Hauptschulen",
    "sg:phone":"+43 4377 3222430",
    "sg:postcode":"4680",
    "sg:province":"Ober\u00f6sterreich",
    "wof:name":"Hauptschule u Polytechnische Schule",
    "wof:placetype":"venue"
},
  "geometry": {"coordinates":[13.644241333,48.1827583313],"type":"Point"}
}