{
  "type": "Feature",
  "properties": {
    "iso:country":"AT",
    "sg:address":"Harreiterweg 15",
    "sg:city":"Rohrmoos-Untertal",
    "sg:orig_category":"Appartements / Ferienwohnungen",
    "sg:phone":"+43 4336 8722827",
    "sg:postcode":"8971",
    "sg:province":"Steiermark",
    "wof:name":"Harreiterhof",
    "wof:placetype":"venue"
},
  "geometry": {"coordinates":[13.6993532181,47.3868865967],"type":"Point"}
}