{
  "type": "Feature",
  "properties": {
    "addr:full":"Dinghoferstr 69 Linz Ober\u00f6sterreich 4020",
    "addr:housenumber":"69",
    "addr:postcode":"4020",
    "addr:street":"Dinghoferstr",
    "iso:country":"AT",
    "sg:address":"Dinghoferstr 69",
    "sg:city":"Linz",
    "sg:orig_category":"Bilder",
    "sg:phone":"+43 732 653536",
    "sg:postcode":"4020",
    "sg:province":"Ober\u00f6sterreich",
    "wof:name":"Bilder Eigl GmbH & Co KG",
    "wof:placetype":"venue"
},
  "geometry": {"coordinates":[14.2989501953,48.2971000671],"type":"Point"}
}