{
  "type": "Feature",
  "properties": {
    "addr:full":"Eicheng 1 Leopoldsdorf Nieder\u00f6sterreich 2333",
    "addr:housenumber":"1",
    "addr:postcode":"2333",
    "addr:street":"Eicheng",
    "iso:country":"AT",
    "sg:address":"Eicheng 1",
    "sg:city":"Leopoldsdorf",
    "sg:orig_category":"Schwei\u00c3\u0178- U Schneidetechnik",
    "sg:phone":"+43 4367 63268801",
    "sg:postcode":"2333",
    "sg:province":"Nieder\u00f6sterreich",
    "wof:name":"Riemann Johannes",
    "wof:placetype":"venue"
},
  "geometry": {"coordinates":[16.3879985809,48.1121101379],"type":"Point"}
}