{
  "type": "Feature",
  "properties": {
    "addr:full":"Brucker Str 98 Bruck an der Mur Steiermark 8600",
    "addr:postcode":"8600",
    "addr:street":"Str 98",
    "iso:country":"AT",
    "sg:address":"Brucker Str 98",
    "sg:city":"Bruck an der Mur",
    "sg:orig_category":"Gartencenter",
    "sg:phone":"+43 3862 55699",
    "sg:postcode":"8600",
    "sg:province":"Steiermark",
    "wof:name":"Bellaflora Gartencenter GmbH",
    "wof:placetype":"venue"
},
  "geometry": {"coordinates":[15.2266998291,47.4033203125],"type":"Point"}
}