{
  "type": "Feature",
  "properties": {
    "addr:full":"Gersthofer Str 75-77 Wien Wien 1180",
    "addr:postcode":"75-77;1180",
    "addr:street":"Str",
    "iso:country":"AT",
    "sg:address":"Gersthofer Str 75-77",
    "sg:city":"Wien",
    "sg:orig_category":"Elektroinstallationsunternehmen",
    "sg:phone":"+43 1 4704525",
    "sg:postcode":"1180",
    "sg:province":"Wien",
    "wof:name":"Lahmer Herbert",
    "wof:placetype":"venue"
},
  "geometry": {"coordinates":[16.3273296356,48.2343940735],"type":"Point"}
}