{
  "type": "Feature",
  "properties": {
    "addr:full":"Zeller Bundesstr 1a Saalfelden am Steinernen Meer Salzburg 5760",
    "addr:housenumber":"1a",
    "addr:postcode":"5760",
    "addr:street":"Bundesstr",
    "iso:country":"AT",
    "sg:address":"Zeller Bundesstr 1a",
    "sg:city":"Saalfelden am Steinernen Meer",
    "sg:orig_category":"Tankstellen",
    "sg:phone":"+43 4365 82732580",
    "sg:postcode":"5760",
    "sg:province":"Salzburg",
    "wof:name":"Agip Tankstelle",
    "wof:placetype":"venue"
},
  "geometry": {"coordinates":[12.8415632248,47.4275360107],"type":"Point"}
}