{
  "type": "Feature",
  "properties": {
    "iso:country":"AT",
    "sg:address":"Ebelsberg Schlo\u00dfweg 7",
    "sg:city":"Linz",
    "sg:orig_category":"Gutsverwaltungen",
    "sg:phone":"+43 732 3076320",
    "sg:postcode":"4030",
    "sg:province":"Ober\u00f6sterreich",
    "wof:name":"Kast'sche Gutsverwaltung",
    "wof:placetype":"venue"
},
  "geometry": {"coordinates":[14.328168869,48.2466239929],"type":"Point"}
}