{
  "type": "Feature",
  "properties": {
    "iso:country":"AT",
    "sg:address":"Nr 40",
    "sg:city":"Taufkirchen an der Trattnach",
    "sg:orig_category":"Waren Aller Art",
    "sg:phone":"+43 4377 3434043",
    "sg:postcode":"4715",
    "sg:province":"Ober\u00f6sterreich",
    "wof:name":"Knusperh\u00e4uschen HandelsgmbH",
    "wof:placetype":"venue"
},
  "geometry": {"coordinates":[13.7491598129,48.2472038269],"type":"Point"}
}