{
  "type": "Feature",
  "properties": {
    "iso:country":"AT",
    "sg:address":"Vierthalerstr 10",
    "sg:city":"Salzburg",
    "sg:orig_category":"Architekten",
    "sg:phone":"+43 662 8738080",
    "sg:postcode":"5020",
    "sg:province":"Salzburg",
    "wof:name":"Flir Erich Dipl-Ing",
    "wof:placetype":"venue"
},
  "geometry": {"coordinates":[13.0494823456,47.8053359985],"type":"Point"}
}