{
  "type": "Feature",
  "properties": {
    "iso:country":"AT",
    "sg:address":"Wachaustr 30",
    "sg:city":"Krems an der Donau",
    "sg:orig_category":"Autolackierereien",
    "sg:phone":"+43 2732 82433",
    "sg:postcode":"3500",
    "sg:province":"Nieder\u00f6sterreich",
    "wof:name":"Chips Away",
    "wof:placetype":"venue"
},
  "geometry": {"coordinates":[15.609957695,48.4122695923],"type":"Point"}
}