{
  "type": "Feature",
  "properties": {
    "addr:full":"Platz am Graben 1 St. Veit an der Glan K\u00e4rnten 9300",
    "addr:housenumber":"1",
    "addr:postcode":"9300",
    "addr:street":"Platz Am Graben;Kaernten",
    "iso:country":"AT",
    "sg:address":"Platz am Graben 1",
    "sg:city":"St. Veit an der Glan",
    "sg:orig_category":"Psychologen",
    "sg:phone":"+43 4212 30366",
    "sg:postcode":"9300",
    "sg:province":"K\u00e4rnten",
    "wof:name":"Psychologisches Zentrum",
    "wof:placetype":"venue"
},
  "geometry": {"coordinates":[14.3603067398,46.7668228149],"type":"Point"}
}