{
  "type": "Feature",
  "properties": {
    "iso:country":"AT",
    "sg:address":"Michaelerstr 25",
    "sg:city":"Wien",
    "sg:orig_category":"Berufsschulen",
    "sg:phone":"+43 4314 7969240",
    "sg:postcode":"1180",
    "sg:province":"Wien",
    "wof:name":"Private Berufsschule f Brauer, M\u00e4lzer u Destillateure",
    "wof:placetype":"venue"
},
  "geometry": {"coordinates":[16.3458805084,48.2290077209],"type":"Point"}
}