{
  "type": "Feature",
  "properties": {
    "iso:country":"AT",
    "sg:address":"Billrothstr 8-10",
    "sg:city":"Wien",
    "sg:orig_category":"Unterhaltungselektronik / Einzelhandel",
    "sg:phone":"+43 4313 696075",
    "sg:postcode":"1190",
    "sg:province":"Wien",
    "wof:name":"R. Padalewski",
    "wof:placetype":"venue"
},
  "geometry": {"coordinates":[16.3503608704,48.2356948853],"type":"Point"}
}