{
  "type": "Feature",
  "properties": {
    "iso:country":"AT",
    "sg:address":"Haitzingallee 20",
    "sg:city":"Bad Hofgastein",
    "sg:orig_category":"Pensionen / Privatzimmer",
    "sg:phone":"+43 6432 6648",
    "sg:postcode":"5630",
    "sg:province":"Salzburg",
    "wof:name":"Haus Ganschitter",
    "wof:placetype":"venue"
},
  "geometry": {"coordinates":[13.0964269638,47.1762619019],"type":"Point"}
}