{
  "type": "Feature",
  "properties": {
    "addr:full":"Industriepark 5 M\u00fcrzzuschlag-H\u00f6nigsberg Steiermark 8682",
    "addr:housenumber":"5",
    "addr:postcode":"8682",
    "addr:street":"Industriepark",
    "iso:country":"AT",
    "sg:address":"Industriepark 5",
    "sg:city":"M\u00fcrzzuschlag-H\u00f6nigsberg",
    "sg:orig_category":"Personalbereitstellung",
    "sg:phone":"+43 3852 30676",
    "sg:postcode":"8682",
    "sg:province":"Steiermark",
    "wof:name":"REMI-Personalleasing GmbH",
    "wof:placetype":"venue"
},
  "geometry": {"coordinates":[15.6469602585,47.5819358826],"type":"Point"}
}