{
  "type": "Feature",
  "properties": {
    "addr:full":"Oberdorf 96 Stans Tirol 6135",
    "addr:housenumber":"96",
    "addr:postcode":"6135",
    "addr:street":"Oberdorf;Tirol",
    "iso:country":"AT",
    "sg:address":"Oberdorf 96",
    "sg:city":"Stans",
    "sg:orig_category":"Volksschulen",
    "sg:phone":"+43 5242 71766",
    "sg:postcode":"6135",
    "sg:province":"Tirol",
    "wof:name":"Volksschule",
    "wof:placetype":"venue"
},
  "geometry": {"coordinates":[11.7170000076,47.36977005],"type":"Point"}
}