{
  "type": "Feature",
  "properties": {
    "iso:country":"AT",
    "sg:address":"Geigenberg 6",
    "sg:city":"St. Leonhard am Forst",
    "sg:orig_category":"Ingenieurkonsulenten / Zivilingenieure",
    "sg:phone":"+43 4327 562249",
    "sg:postcode":"3243",
    "sg:province":"Nieder\u00f6sterreich",
    "wof:name":"Lueger Josef Dr phil",
    "wof:placetype":"venue"
},
  "geometry": {"coordinates":[15.2806892395,48.1264533997],"type":"Point"}
}