{
  "type": "Feature",
  "properties": {
    "addr:full":"Anna-Hensler-Str 15 Klaus-Weiler Vorarlberg 6833",
    "addr:housenumber":"15",
    "addr:postcode":"6833",
    "addr:street":"Anna-Hensler-Str",
    "iso:country":"AT",
    "sg:address":"Anna-Hensler-Str 15",
    "sg:city":"Klaus-Weiler",
    "sg:orig_category":"Gemeinden",
    "sg:phone":"+43 4355 23625360",
    "sg:postcode":"6833",
    "sg:province":"Vorarlberg",
    "wof:name":"Gemeindeamt Klaus",
    "wof:placetype":"venue"
},
  "geometry": {"coordinates":[9.646771431,47.3094062805],"type":"Point"}
}