{
  "type": "Feature",
  "properties": {
    "addr:full":"Hauptstr Zwentendorf an der Donau Nieder\u00f6sterreich 3435",
    "addr:postcode":"3435",
    "iso:country":"AT",
    "sg:address":"Hauptstr",
    "sg:city":"Zwentendorf an der Donau",
    "sg:orig_category":"Feuerwehren",
    "sg:phone":"+43 4322 773545",
    "sg:postcode":"3435",
    "sg:province":"Nieder\u00f6sterreich",
    "wof:name":"Freiwillige Feuerwehr Kleinsch\u00f6nbichl",
    "wof:placetype":"venue"
},
  "geometry": {"coordinates":[15.910369873,48.3454666138],"type":"Point"}
}