{
  "type": "Feature",
  "properties": {
    "addr:full":"Thern 14 St. Georgen im Attergau Ober\u00f6sterreich 4880",
    "addr:housenumber":"14",
    "addr:postcode":"4880",
    "addr:street":"Thern",
    "iso:country":"AT",
    "sg:address":"Thern 14",
    "sg:city":"St. Georgen im Attergau",
    "sg:orig_category":"Blumeneinzelhandel",
    "sg:phone":"+43 4376 675123",
    "sg:postcode":"4880",
    "sg:province":"Ober\u00f6sterreich",
    "wof:name":"Blumen-G\u00e4rtnerei Mayer",
    "wof:placetype":"venue"
},
  "geometry": {"coordinates":[13.4955282211,47.9320335388],"type":"Point"}
}