{
  "type": "Feature",
  "properties": {
    "addr:full":"Lilli Lehmann-G 4 Salzburg Salzburg 5020",
    "addr:housenumber":"4",
    "addr:postcode":"5020",
    "addr:street":"Lehmann-G;Salzburg",
    "iso:country":"AT",
    "sg:address":"Lilli Lehmann-G 4",
    "sg:city":"Salzburg",
    "sg:orig_category":"Geographische Informationssysteme",
    "sg:phone":"+43 662 624496",
    "sg:postcode":"5020",
    "sg:province":"Salzburg",
    "wof:name":"ICRA Institut f computergest\u00fctzte Raumanalytik",
    "wof:placetype":"venue"
},
  "geometry": {"coordinates":[13.0633649826,47.7974510193],"type":"Point"}
}