{
  "type": "Feature",
  "properties": {
    "iso:country":"AT",
    "sg:address":"Wiesenstrasse 32",
    "sg:city":"Klaus-Weiler",
    "sg:orig_category":"Repair Services For Refrigeration Systems And Air-Conditioning Systems",
    "sg:phone":"+43 5523 64026",
    "sg:postcode":"6833",
    "sg:province":"Vorarlberg",
    "wof:name":"Hake Service Thomas Koch",
    "wof:placetype":"venue"
},
  "geometry": {"coordinates":[9.6444625854,47.3017501831],"type":"Point"}
}