{
  "type": "Feature",
  "properties": {
    "addr:full":"Rathauspl 7 Stockerau Nieder\u00f6sterreich 2000",
    "addr:housenumber":"7",
    "addr:postcode":"2000",
    "addr:street":"Rathauspl",
    "iso:country":"AT",
    "sg:address":"Rathauspl 7",
    "sg:city":"Stockerau",
    "sg:orig_category":"Stoffe / Erzeugung U Gro\u00c3\u0178handel",
    "sg:phone":"+43 4322 6668157",
    "sg:postcode":"2000",
    "sg:province":"Nieder\u00f6sterreich",
    "wof:name":"Stoffparadies Inh Brigitte Schiefer",
    "wof:placetype":"venue"
},
  "geometry": {"coordinates":[16.2080478668,48.38514328],"type":"Point"}
}