{
  "type": "Feature",
  "properties": {
    "addr:full":"Weinzierlstr 2 Steyr Ober\u00f6sterreich 4400",
    "addr:housenumber":"2",
    "addr:postcode":"4400",
    "addr:street":"Weinzierlstr;Oberoesterreich",
    "iso:country":"AT",
    "sg:address":"Weinzierlstr 2",
    "sg:city":"Steyr",
    "sg:orig_category":"Ziegeleien",
    "sg:phone":"+43 7252 720750",
    "sg:postcode":"4400",
    "sg:province":"Ober\u00f6sterreich",
    "wof:name":"Weindl GesmbH",
    "wof:placetype":"venue"
},
  "geometry": {"coordinates":[14.4090738297,48.0481262207],"type":"Point"}
}