{
  "type": "Feature",
  "properties": {
    "iso:country":"AT",
    "sg:address":"Hammerweg 18",
    "sg:city":"Micheldorf in Ober\u00f6sterreich",
    "sg:orig_category":"Waren Aller Art",
    "sg:phone":"+43 7582 62634",
    "sg:postcode":"4563",
    "sg:province":"Ober\u00f6sterreich",
    "wof:name":"Oberndorfinger KEG",
    "wof:placetype":"venue"
},
  "geometry": {"coordinates":[14.1321172714,47.8774681091],"type":"Point"}
}