{
  "type": "Feature",
  "properties": {
    "iso:country":"AT",
    "sg:address":"Kellerbauerweg 41",
    "sg:city":"Bad Vigaun",
    "sg:classifiers":[
        {
            "category":"Restaurant",
            "type":"Food & Drink"
        }
    ],
    "sg:phone":"+43 6245 834740",
    "sg:postcode":"5424",
    "sg:province":"Salzburg",
    "wof:name":"Restaurant Kellerbauer",
    "wof:placetype":"venue"
},
  "geometry": {"coordinates":[13.1331987381,47.6710777283],"type":"Point"}
}