{
  "type": "Feature",
  "properties": {
    "addr:full":"Ferdinand-Benischke-Str 16 Hainfeld Nieder\u00f6sterreich 3170",
    "addr:housenumber":"16",
    "addr:postcode":"3170",
    "addr:street":"Ferdinand-Benischke-Str",
    "iso:country":"AT",
    "sg:address":"Ferdinand-Benischke-Str 16",
    "sg:city":"Hainfeld",
    "sg:orig_category":"Bestattungsunternehmen",
    "sg:phone":"+43 4327 6467138",
    "sg:postcode":"3170",
    "sg:province":"Nieder\u00f6sterreich",
    "wof:name":"Farcher GesmbH",
    "wof:placetype":"venue"
},
  "geometry": {"coordinates":[15.7614383698,48.0395774841],"type":"Point"}
}