{
  "type": "Feature",
  "properties": {
    "iso:country":"AT",
    "sg:address":"Amerlingstr 17",
    "sg:city":"Wien",
    "sg:classifiers":[
        {
            "category":"Manufacturing",
            "subcategory":"Rubber & Plastics",
            "type":"Manufacturing & Wholesale Goods"
        }
    ],
    "sg:phone":"+43 1 5873210",
    "sg:postcode":"1060",
    "sg:province":"Wien",
    "sg:tags":[
        "safe",
        "u",
        "tresore"
    ],
    "wof:name":"Putz A Kassen- und B\u00fcrostahlm\u00f6belbau",
    "wof:placetype":"venue"
},
  "geometry": {"coordinates":[16.3503723145,48.1977081299],"type":"Point"}
}