{
  "type": "Feature",
  "properties": {
    "addr:full":"Hauptpl 23 St. Leonhard am Forst Nieder\u00f6sterreich 3243",
    "addr:housenumber":"23",
    "addr:postcode":"3243",
    "addr:street":"Hauptpl",
    "iso:country":"AT",
    "sg:address":"Hauptpl 23",
    "sg:city":"St. Leonhard am Forst",
    "sg:classifiers":[
        {
            "category":"Restaurant",
            "type":"Food & Drink"
        }
    ],
    "sg:phone":"+43 4327 5677085",
    "sg:postcode":"3243",
    "sg:province":"Nieder\u00f6sterreich",
    "sg:tags":[
        "pizzeria"
    ],
    "wof:name":"Pizzeria Giovanni",
    "wof:placetype":"venue"
},
  "geometry": {"coordinates":[15.2847690582,48.1428871155],"type":"Point"}
}