{
  "type": "Feature",
  "properties": {
    "addr:full":"Dr.-Stumpf-Str 10a/5 Innsbruck Tirol 6020",
    "addr:housenumber":"10a / 5",
    "addr:postcode":"6020",
    "addr:street":"Dr.-Stumpf-Str;Tirol",
    "iso:country":"AT",
    "sg:address":"Dr.-Stumpf-Str 10a/5",
    "sg:city":"Innsbruck",
    "sg:orig_category":"Psychotherapie",
    "sg:phone":"+43 676 5486745",
    "sg:postcode":"6020",
    "sg:province":"Tirol",
    "wof:name":"Haid Margit Eleonore",
    "wof:placetype":"venue"
},
  "geometry": {"coordinates":[11.3746595383,47.2571220398],"type":"Point"}
}