{
  "type": "Feature",
  "properties": {
    "addr:full":"Pax 11 Vomp Tirol 6134",
    "addr:housenumber":"11",
    "addr:postcode":"6134",
    "addr:street":"Pax;Tirol",
    "iso:country":"AT",
    "sg:address":"Pax 11",
    "sg:city":"Vomp",
    "sg:orig_category":"Zahntechnische Laboratorien",
    "sg:phone":"+43 5242 71691",
    "sg:postcode":"6134",
    "sg:province":"Tirol",
    "wof:name":"Dentaltechnik Brandacher",
    "wof:placetype":"venue"
},
  "geometry": {"coordinates":[11.7011699677,47.3597793579],"type":"Point"}
}