{
  "type": "Feature",
  "properties": {
    "iso:country":"AT",
    "sg:address":"Nr 1",
    "sg:city":"Hausleiten",
    "sg:orig_category":"Forstverwaltungen",
    "sg:phone":"+43 2265 7430",
    "sg:postcode":"3464",
    "sg:province":"Nieder\u00f6sterreich",
    "wof:name":"Stradiot Georg Forst und Gutsverwaltung",
    "wof:placetype":"venue"
},
  "geometry": {"coordinates":[16.1025238037,48.393989563],"type":"Point"}
}