{
  "type": "Feature",
  "properties": {
    "addr:full":"Speckbacherg 32 Wien Wien 1160",
    "addr:housenumber":"32",
    "addr:postcode":"1160",
    "addr:street":"Speckbacherg",
    "iso:country":"AT",
    "sg:address":"Speckbacherg 32",
    "sg:city":"Wien",
    "sg:orig_category":"Personalbereitstellung",
    "sg:phone":"+43 699 10091551",
    "sg:postcode":"1160",
    "sg:province":"Wien",
    "wof:name":"STG Transport- und Personalleasing GmbH",
    "wof:placetype":"venue"
},
  "geometry": {"coordinates":[16.3168697357,48.2166175842],"type":"Point"}
}