{
  "type": "Feature",
  "properties": {
    "iso:country":"AT",
    "sg:address":"Bahnhofstr 7",
    "sg:city":"Litschau",
    "sg:orig_category":"Installationsunternehmen",
    "sg:phone":"+43 2865 3420",
    "sg:postcode":"3874",
    "sg:province":"Nieder\u00f6sterreich",
    "wof:name":"Hauer GmbH",
    "wof:placetype":"venue"
},
  "geometry": {"coordinates":[15.0438785553,48.9425468445],"type":"Point"}
}