{
  "type": "Feature",
  "properties": {
    "addr:full":"Sechsschimmelg 3/10 Wien Wien 1090",
    "addr:housenumber":"3 / 10",
    "addr:postcode":"1090",
    "addr:street":"Sechsschimmelg",
    "iso:country":"AT",
    "sg:address":"Sechsschimmelg 3/10",
    "sg:city":"Wien",
    "sg:classifiers":[
        {
            "category":"Communications",
            "subcategory":"Film & Video Production",
            "type":"Services"
        }
    ],
    "sg:phone":"+43 1 3193124",
    "sg:postcode":"1090",
    "sg:province":"Wien",
    "sg:tags":[
        "multimedia"
    ],
    "wof:name":"L\u00f6blich Christoph",
    "wof:placetype":"venue"
},
  "geometry": {"coordinates":[16.351474762,48.2234115601],"type":"Point"}
}