{
  "type": "Feature",
  "properties": {
    "iso:country":"AT",
    "sg:address":"M\u00fchlbachg 222",
    "sg:city":"Lanzenkirchen",
    "sg:orig_category":"Zimmereien",
    "sg:phone":"+43 2627 45782",
    "sg:postcode":"2821",
    "sg:province":"Nieder\u00f6sterreich",
    "wof:name":"Gobauer Gerhard",
    "wof:placetype":"venue"
},
  "geometry": {"coordinates":[16.2391223907,47.7426261902],"type":"Point"}
}