{
  "type": "Feature",
  "properties": {
    "addr:full":"Pembaurstr 30 Innsbruck Tirol 6020",
    "addr:housenumber":"30",
    "addr:postcode":"6020",
    "addr:street":"Pembaurstr;Tirol",
    "iso:country":"AT",
    "sg:address":"Pembaurstr 30",
    "sg:city":"Innsbruck",
    "sg:orig_category":"Tankstellen",
    "sg:phone":"+43 512 343216",
    "sg:postcode":"6020",
    "sg:province":"Tirol",
    "wof:name":"BP Austria Marketing GmbH",
    "wof:placetype":"venue"
},
  "geometry": {"coordinates":[11.4118242264,47.2678871155],"type":"Point"}
}