{
  "type": "Feature",
  "properties": {
    "addr:full":"Albrechtsg 15 Tulln an der Donau Nieder\u00f6sterreich 3430",
    "addr:housenumber":"15",
    "addr:postcode":"3430",
    "addr:street":"Albrechtsg",
    "iso:country":"AT",
    "sg:address":"Albrechtsg 15",
    "sg:city":"Tulln an der Donau",
    "sg:classifiers":[
        {
            "category":"Restaurant",
            "type":"Food & Drink"
        }
    ],
    "sg:phone":"+43 2272 63173",
    "sg:postcode":"3430",
    "sg:province":"Nieder\u00f6sterreich",
    "sg:tags":[
        "pizzeria"
    ],
    "wof:name":"Pizzeria Rusticana",
    "wof:placetype":"venue"
},
  "geometry": {"coordinates":[16.0521678925,48.3325233459],"type":"Point"}
}