{
  "type": "Feature",
  "properties": {
    "addr:full":"Erdbergstr. 131  Wien Wien 1030",
    "addr:housenumber":"131",
    "addr:postcode":"1030",
    "iso:country":"AT",
    "sg:address":"Erdbergstr. 131 ",
    "sg:city":"Wien",
    "sg:classifiers":[
        {
            "category":"Autos & Motor Vehicles",
            "subcategory":"Automobile Sales",
            "type":"Retail Goods"
        }
    ],
    "sg:phone":"+43 4317 9891910",
    "sg:postcode":"1030",
    "sg:province":"Wien",
    "sg:tags":[
        "industrial"
    ],
    "wof:name":"AUTOHAUS KARL GROSSE GMBH",
    "wof:placetype":"venue"
},
  "geometry": {"coordinates":[16.4101200104,48.1938285828],"type":"Point"}
}