{
  "type": "Feature",
  "properties": {
    "addr:full":"Itzlinger Hauptstr 93a Salzburg Salzburg 5020",
    "addr:housenumber":"93a",
    "addr:postcode":"5020",
    "addr:street":"Itzlinger Hauptstr;Salzburg",
    "iso:country":"AT",
    "sg:address":"Itzlinger Hauptstr 93a",
    "sg:city":"Salzburg",
    "sg:orig_category":"Telekommunikation",
    "sg:phone":"+43 800 664300",
    "sg:postcode":"5020",
    "sg:province":"Salzburg",
    "wof:name":"A1-Shop Salzburg",
    "wof:placetype":"venue"
},
  "geometry": {"coordinates":[13.0374183655,47.8264923096],"type":"Point"}
}