{
  "type": "Feature",
  "properties": {
    "addr:full":"St Magdalener Str 35 Villach K\u00e4rnten 9500",
    "addr:housenumber":"35",
    "addr:postcode":"9500",
    "addr:street":"St;Str;Kaernten",
    "iso:country":"AT",
    "sg:address":"St Magdalener Str 35",
    "sg:city":"Villach",
    "sg:orig_category":"Waren Aller Art",
    "sg:phone":"+43 4242 415120",
    "sg:postcode":"9500",
    "sg:province":"K\u00e4rnten",
    "wof:name":"Hausmann A & Co",
    "wof:placetype":"venue"
},
  "geometry": {"coordinates":[13.8679132462,46.6158447266],"type":"Point"}
}