{
  "type": "Feature",
  "properties": {
    "addr:full":"Grazer Str 27 Murau Steiermark 8850",
    "addr:housenumber":"27",
    "addr:postcode":"8850",
    "addr:street":"Str",
    "iso:country":"AT",
    "sg:address":"Grazer Str 27",
    "sg:city":"Murau",
    "sg:orig_category":"Tabaktrafiken",
    "sg:phone":"+43 3532 4401",
    "sg:postcode":"8850",
    "sg:province":"Steiermark",
    "wof:name":"Hinterschweiger Friedrich",
    "wof:placetype":"venue"
},
  "geometry": {"coordinates":[14.1788711548,47.1113319397],"type":"Point"}
}