{
  "type": "Feature",
  "properties": {
    "addr:full":"Wattmanng 7/4 Wien Wien 1130",
    "addr:housenumber":"7 / 4",
    "addr:postcode":"1130",
    "addr:street":"Wattmanng",
    "iso:country":"AT",
    "sg:address":"Wattmanng 7/4",
    "sg:city":"Wien",
    "sg:orig_category":"Werbeagenturen",
    "sg:phone":"+43 1 8790281",
    "sg:postcode":"1130",
    "sg:province":"Wien",
    "wof:name":"HG-COMMUNICATION",
    "wof:placetype":"venue"
},
  "geometry": {"coordinates":[16.2980594635,48.1839332581],"type":"Point"}
}