{
  "type": "Feature",
  "properties": {
    "addr:full":"Schillerstr 8 Spittal an der Drau K\u00e4rnten 9800",
    "addr:housenumber":"8",
    "addr:postcode":"9800",
    "addr:street":"Schillerstr;Kaernten",
    "iso:country":"AT",
    "sg:address":"Schillerstr 8",
    "sg:city":"Spittal an der Drau",
    "sg:orig_category":"Psychotherapie",
    "sg:phone":"+43 4367 64103252",
    "sg:postcode":"9800",
    "sg:province":"K\u00e4rnten",
    "wof:name":"Wieser Elfriede Mag",
    "wof:placetype":"venue"
},
  "geometry": {"coordinates":[13.4927387238,46.7973098755],"type":"Point"}
}