{
  "type": "Feature",
  "properties": {
    "addr:full":"Ikea-Platz 4  Haid Ober\u00f6sterreich 4053",
    "addr:housenumber":"4",
    "addr:postcode":"4053",
    "addr:street":"Ikea-Platz",
    "iso:country":"AT",
    "sg:address":"Ikea-Platz 4 ",
    "sg:city":"Haid",
    "sg:classifiers":[
        {
            "category":"Sports & Exercise",
            "subcategory":"Playing Field",
            "type":"Entertainment"
        }
    ],
    "sg:phone":"+43 4372 2978627",
    "sg:postcode":"4053",
    "sg:province":"Ober\u00f6sterreich",
    "sg:tags":[
        "game"
    ],
    "wof:name":"TOYS 'R' US HANDELSGES.MBH",
    "wof:placetype":"venue"
},
  "geometry": {"coordinates":[14.2474946976,48.1958885193],"type":"Point"}
}