{
  "type": "Feature",
  "properties": {
    "addr:full":"Marienberg 27 Linz Ober\u00f6sterreich 4040",
    "addr:housenumber":"27",
    "addr:postcode":"4040",
    "addr:street":"Marienberg",
    "iso:country":"AT",
    "sg:address":"Marienberg 27",
    "sg:city":"Linz",
    "sg:orig_category":"Preisagenturen",
    "sg:phone":"+43 732 711555",
    "sg:postcode":"4040",
    "sg:province":"Ober\u00f6sterreich",
    "wof:name":"best-price-office Robert Hemedinger",
    "wof:placetype":"venue"
},
  "geometry": {"coordinates":[14.2977027893,48.339630127],"type":"Point"}
}