{
  "type": "Feature",
  "properties": {
    "iso:country":"AT",
    "sg:address":"Reitschulg 4",
    "sg:city":"Wien",
    "sg:orig_category":"Juweliere, Gold- U Silberschmiede",
    "sg:phone":"+43 1 5335049",
    "sg:postcode":"1010",
    "sg:province":"Wien",
    "wof:name":"Halder F",
    "wof:placetype":"venue"
},
  "geometry": {"coordinates":[16.3670787811,48.2076454163],"type":"Point"}
}