{
  "type": "Feature",
  "properties": {
    "addr:full":"Waldbadstr 4 Anif Salzburg 5081",
    "addr:housenumber":"4",
    "addr:postcode":"5081",
    "addr:street":"Waldbadstr;Salzburg",
    "iso:country":"AT",
    "sg:address":"Waldbadstr 4",
    "sg:city":"Anif",
    "sg:classifiers":[
        {
            "category":"Home & Garden",
            "subcategory":"Building Materials",
            "type":"Retail Goods"
        }
    ],
    "sg:phone":"+43 4362 46727170",
    "sg:postcode":"5081",
    "sg:province":"Salzburg",
    "sg:tags":[
        "baustoffe",
        "-material",
        "u"
    ],
    "wof:name":"Stadlbauer Baubedarfszentrum GmbH & Co KG",
    "wof:placetype":"venue"
},
  "geometry": {"coordinates":[13.0696697235,47.7372436523],"type":"Point"}
}