{
  "type": "Feature",
  "properties": {
    "addr:full":"Gablenzg 109 Wien Wien 1150",
    "addr:housenumber":"109",
    "addr:postcode":"1150",
    "iso:country":"AT",
    "sg:address":"Gablenzg 109",
    "sg:city":"Wien",
    "sg:orig_category":"Tankstellen",
    "sg:phone":"+43 1 9821210",
    "sg:postcode":"1150",
    "sg:province":"Wien",
    "wof:name":"OMV AG",
    "wof:placetype":"venue"
},
  "geometry": {"coordinates":[16.313659668,48.2069587708],"type":"Point"}
}