{
  "type": "Feature",
  "properties": {
    "addr:full":"Sportplatzstrasse 1 Steyrerm\u00fchl Ober\u00f6sterreich 4662",
    "addr:housenumber":"1",
    "addr:postcode":"4662",
    "addr:street":"Sportplatzstrasse;Oberoesterreich",
    "iso:country":"AT",
    "sg:address":"Sportplatzstrasse 1",
    "sg:city":"Steyrerm\u00fchl",
    "sg:classifiers":[
        {
            "category":"Structure",
            "subcategory":"Bridge",
            "type":"Public Place"
        }
    ],
    "sg:phone":"+43 761323910",
    "sg:postcode":"4662",
    "sg:province":"Ober\u00f6sterreich",
    "sg:tags":[
        "construction"
    ],
    "wof:name":"LAHNERBAU Ges.m.b.H.",
    "wof:placetype":"venue"
},
  "geometry": {"coordinates":[13.8113775253,47.9901809692],"type":"Point"}
}