{
  "type": "Feature",
  "properties": {
    "addr:full":"Biberstr 22/15 Wien Wien 1010",
    "addr:housenumber":"22 / 15",
    "addr:postcode":"1010",
    "addr:street":"Biberstr",
    "iso:country":"AT",
    "sg:address":"Biberstr 22/15",
    "sg:city":"Wien",
    "sg:orig_category":"Architekten",
    "sg:phone":"+43 1 5126128",
    "sg:postcode":"1010",
    "sg:province":"Wien",
    "wof:name":"Kanner Adam Dipl-Ing",
    "wof:placetype":"venue"
},
  "geometry": {"coordinates":[16.38139534,48.2103767395],"type":"Point"}
}