{
  "type": "Feature",
  "properties": {
    "iso:country":"AT",
    "sg:address":"Am Prettachfeld 1",
    "sg:city":"Leoben",
    "sg:classifiers":[
        {
            "category":"Shopping",
            "subcategory":"Computers & Home Electronics",
            "type":"Retail Goods"
        }
    ],
    "sg:phone":"+43 3842 25262",
    "sg:postcode":"8700",
    "sg:province":"Steiermark",
    "sg:tags":[
        "system",
        "automation"
    ],
    "sg:website":"tbg.at",
    "wof:name":"tbg - Ing. Gerhard Brunnthaler Maschinen - Anlagenbau",
    "wof:placetype":"venue"
},
  "geometry": {"coordinates":[15.087682724,47.356086731],"type":"Point"}
}