{
  "type": "Feature",
  "properties": {
    "iso:country":"AT",
    "sg:address":"Paris-Lodron-Strasse 5",
    "sg:city":"Salzburg",
    "sg:orig_category":"Stringed Instrument Repair Services",
    "sg:phone":"+43 662 882261",
    "sg:postcode":"5020",
    "sg:province":"Salzburg",
    "wof:name":"Peter Svatek",
    "wof:placetype":"venue"
},
  "geometry": {"coordinates":[13.0455131531,47.8050689697],"type":"Point"}
}