{
  "type": "Feature",
  "properties": {
    "addr:full":"Dornhof 15 St. Veit an der Glan K\u00e4rnten 9300",
    "addr:housenumber":"15",
    "addr:postcode":"9300",
    "addr:street":"Dornhof;Kaernten",
    "iso:country":"AT",
    "sg:address":"Dornhof 15",
    "sg:city":"St. Veit an der Glan",
    "sg:orig_category":"Papier / Erzeugung U Gro\u00c3\u0178handel",
    "sg:phone":"+43 4342 126988",
    "sg:postcode":"9300",
    "sg:province":"K\u00e4rnten",
    "wof:name":"Institut f pers\u00f6nliche Erfolgstechnik Verm\u00f6gensberatung",
    "wof:placetype":"venue"
},
  "geometry": {"coordinates":[14.3591928482,46.7664413452],"type":"Point"}
}