{
  "type": "Feature",
  "properties": {
    "addr:full":"Dorfpl 1 G\u00f6tzens Tirol 6091",
    "addr:housenumber":"1",
    "addr:postcode":"6091",
    "addr:street":"Dorfpl;Tirol",
    "iso:country":"AT",
    "sg:address":"Dorfpl 1",
    "sg:city":"G\u00f6tzens",
    "sg:orig_category":"Volksschulen",
    "sg:phone":"+43 4352 343323316",
    "sg:postcode":"6091",
    "sg:province":"Tirol",
    "wof:name":"Volksschule",
    "wof:placetype":"venue"
},
  "geometry": {"coordinates":[11.2989969254,47.2356796265],"type":"Point"}
}