{
  "type": "Feature",
  "properties": {
    "addr:full":"Scheibe 76 Neustift im Stubaital Tirol 6167",
    "addr:housenumber":"76",
    "addr:postcode":"6167",
    "addr:street":"Scheibe;Tirol",
    "iso:country":"AT",
    "sg:address":"Scheibe 76",
    "sg:city":"Neustift im Stubaital",
    "sg:orig_category":"Appartements / Ferienwohnungen",
    "sg:phone":"+43 4352 262327",
    "sg:postcode":"6167",
    "sg:province":"Tirol",
    "wof:name":"G\u00e4stehaus Barbara",
    "wof:placetype":"venue"
},
  "geometry": {"coordinates":[11.2951879501,47.1072921753],"type":"Point"}
}