{
  "type": "Feature",
  "properties": {
    "addr:full":"Strandweg Bregenz Vorarlberg 6900",
    "addr:postcode":"6900",
    "addr:street":"Strandweg",
    "iso:country":"AT",
    "sg:address":"Strandweg",
    "sg:city":"Bregenz",
    "sg:classifiers":[
        {
            "category":"Restaurant",
            "type":"Food & Drink"
        }
    ],
    "sg:phone":"+43 5574 79259",
    "sg:postcode":"6900",
    "sg:province":"Vorarlberg",
    "wof:name":"Clubrestaurant Bregenzer Segel - Club",
    "wof:placetype":"venue"
},
  "geometry": {"coordinates":[9.7270479202,47.5059623718],"type":"Point"}
}