{
  "type": "Feature",
  "properties": {
    "iso:country":"AT",
    "sg:address":"Gro\u00dfmarktstr 16",
    "sg:city":"Wien",
    "sg:orig_category":"Rechenzentren",
    "sg:phone":"+43 4316 1636060",
    "sg:postcode":"1230",
    "sg:province":"Wien",
    "sg:website":"rz-vostrovsky.at",
    "wof:name":"Rechenzentrum Vostrovsky GmbH",
    "wof:placetype":"venue"
},
  "geometry": {"coordinates":[16.3635101318,48.14087677],"type":"Point"}
}