{
  "type": "Feature",
  "properties": {
    "iso:country":"AT",
    "sg:address":"Brucker Allee 16",
    "sg:city":"Zell am See",
    "sg:classifiers":[
        {
            "category":"Restaurant",
            "type":"Food & Drink"
        }
    ],
    "sg:phone":"+43 6542 579380",
    "sg:postcode":"5700",
    "sg:province":"Salzburg",
    "wof:name":"Kleingolfst\u00fcberl",
    "wof:placetype":"venue"
},
  "geometry": {"coordinates":[12.7943868637,47.3052787781],"type":"Point"}
}