{
  "type": "Feature",
  "properties": {
    "iso:country":"AT",
    "sg:address":"Nr 64",
    "sg:city":"Stainz",
    "sg:orig_category":"Lebensmittel / Einzelhandel",
    "sg:phone":"+43 3463 2576",
    "sg:postcode":"8510",
    "sg:province":"Steiermark",
    "wof:name":"Reinbacher Rudolf",
    "wof:placetype":"venue"
},
  "geometry": {"coordinates":[15.2647809982,46.8937683105],"type":"Point"}
}