{
  "type": "Feature",
  "properties": {
    "iso:country":"AT",
    "sg:address":"Kaiserstrasse 5/30",
    "sg:city":"Wien",
    "sg:classifiers":[
        {
            "category":"Shopping",
            "subcategory":"Computers & Home Electronics",
            "type":"Retail Goods"
        }
    ],
    "sg:phone":"+43 1 5265575",
    "sg:postcode":"1070",
    "sg:province":"Wien",
    "sg:tags":[
        "layout",
        "electronic",
        "multi-media"
    ],
    "wof:name":"Redaktionsb\u00fcro Flie\u00dftext Dr. Klaus H\u00f6glinger KEG",
    "wof:placetype":"venue"
},
  "geometry": {"coordinates":[16.3412342072,48.1970672607],"type":"Point"}
}