{
  "type": "Feature",
  "properties": {
    "addr:full":"Wiener Str 23 Loosdorf Nieder\u00f6sterreich 3382",
    "addr:postcode":"3382",
    "addr:street":"Loosdorf",
    "iso:country":"AT",
    "sg:address":"Wiener Str 23",
    "sg:city":"Loosdorf",
    "sg:orig_category":"Tischlereien",
    "sg:phone":"+43 2754 73320",
    "sg:postcode":"3382",
    "sg:province":"Nieder\u00f6sterreich",
    "wof:name":"Brachtl W - M\u00f6belhandel",
    "wof:placetype":"venue"
},
  "geometry": {"coordinates":[15.3811845779,48.1837120056],"type":"Point"}
}