{
  "type": "Feature",
  "properties": {
    "addr:full":"Wiener Str 9-13 Wiener Neustadt Nieder\u00f6sterreich 2700",
    "addr:postcode":"2700",
    "iso:country":"AT",
    "sg:address":"Wiener Str 9-13",
    "sg:city":"Wiener Neustadt",
    "sg:orig_category":"Bekleidung / Einzelhandel",
    "sg:phone":"+43 2622 61215",
    "sg:postcode":"2700",
    "sg:province":"Nieder\u00f6sterreich",
    "wof:name":"KBS Kleider Bauer Betriebs-GmbH",
    "wof:placetype":"venue"
},
  "geometry": {"coordinates":[16.2436714172,47.81407547],"type":"Point"}
}