{
  "type": "Feature",
  "properties": {
    "iso:country":"AT",
    "sg:address":"Oberreitweg 44",
    "sg:city":"Zams",
    "sg:orig_category":"Abwasseraufbereitung U -Reinigung",
    "sg:phone":"+43 4354 4265556",
    "sg:postcode":"6511",
    "sg:province":"Tirol",
    "wof:name":"FREYLIT Umwelttechnik GesmbH",
    "wof:placetype":"venue"
},
  "geometry": {"coordinates":[10.5832834244,47.1586227417],"type":"Point"}
}