{
  "type": "Feature",
  "properties": {
    "addr:full":"Ahrain 5 Maishofen Salzburg 5751",
    "addr:housenumber":"5",
    "addr:postcode":"5751",
    "addr:street":"Ahrain;Salzburg",
    "iso:country":"AT",
    "sg:address":"Ahrain 5",
    "sg:city":"Maishofen",
    "sg:orig_category":"Appartements / Ferienwohnungen",
    "sg:phone":"+43 6542 68538",
    "sg:postcode":"5751",
    "sg:province":"Salzburg",
    "wof:name":"Unterkirchner Erika",
    "wof:placetype":"venue"
},
  "geometry": {"coordinates":[12.8082847595,47.3721351624],"type":"Point"}
}