{
  "type": "Feature",
  "properties": {
    "addr:full":"Mariahilfer Str 1 Graz Steiermark 8020",
    "addr:housenumber":"1",
    "addr:postcode":"8020",
    "addr:street":"Str",
    "iso:country":"AT",
    "sg:address":"Mariahilfer Str 1",
    "sg:city":"Graz",
    "sg:orig_category":"Schneidereien",
    "sg:phone":"+43 4366 455009113",
    "sg:postcode":"8020",
    "sg:province":"Steiermark",
    "wof:name":"La Foggia",
    "wof:placetype":"venue"
},
  "geometry": {"coordinates":[15.4334306717,47.0708732605],"type":"Point"}
}