{
  "type": "Feature",
  "properties": {
    "iso:country":"AT",
    "sg:address":"Greit 3",
    "sg:city":"Fulpmes",
    "sg:orig_category":"Lebensmittel / Einzelhandel",
    "sg:phone":"+43 5225 64612",
    "sg:postcode":"6166",
    "sg:province":"Tirol",
    "wof:name":"Kainz Rudolf",
    "wof:placetype":"venue"
},
  "geometry": {"coordinates":[11.3422079086,47.1393814087],"type":"Point"}
}