{
  "type": "Feature",
  "properties": {
    "addr:full":"Klagenfurter Str 62 Villach K\u00e4rnten 9500",
    "addr:housenumber":"62",
    "addr:postcode":"9500",
    "addr:street":"Str;Kaernten",
    "iso:country":"AT",
    "sg:address":"Klagenfurter Str 62",
    "sg:city":"Villach",
    "sg:orig_category":"Tabaktrafiken",
    "sg:phone":"+43 4242 24221",
    "sg:postcode":"9500",
    "sg:province":"K\u00e4rnten",
    "wof:name":"Plankenauer Kurt",
    "wof:placetype":"venue"
},
  "geometry": {"coordinates":[13.8573246002,46.6187744141],"type":"Point"}
}