{
  "type": "Feature",
  "properties": {
    "addr:full":"Doblhoffg 7/7 Wien Wien 1010",
    "addr:housenumber":"7 / 7",
    "addr:postcode":"1010",
    "addr:street":"Doblhoffg",
    "iso:country":"AT",
    "sg:address":"Doblhoffg 7/7",
    "sg:city":"Wien",
    "sg:orig_category":"Steuerberatung",
    "sg:phone":"+43 4314 064349",
    "sg:postcode":"1010",
    "sg:province":"Wien",
    "wof:name":"Bohle Bruno Dkfm",
    "wof:placetype":"venue"
},
  "geometry": {"coordinates":[16.3688049316,48.2025489807],"type":"Point"}
}