{
  "type": "Feature",
  "properties": {
    "addr:full":"Roseng 2 Lienz Tirol 9900",
    "addr:housenumber":"2",
    "addr:postcode":"9900",
    "addr:street":"Roseng;Tirol",
    "iso:country":"AT",
    "sg:address":"Roseng 2",
    "sg:city":"Lienz",
    "sg:orig_category":"Zahntechnische Laboratorien",
    "sg:phone":"+43 4852 64040",
    "sg:postcode":"9900",
    "sg:province":"Tirol",
    "wof:name":"Klammer Dental-Technik",
    "wof:placetype":"venue"
},
  "geometry": {"coordinates":[12.7656745911,46.8295822144],"type":"Point"}
}