{
  "type": "Feature",
  "properties": {
    "addr:full":"Mariahilfer Str 203 Wien Wien 1150",
    "addr:housenumber":"203",
    "addr:postcode":"1150",
    "iso:country":"AT",
    "sg:address":"Mariahilfer Str 203",
    "sg:city":"Wien",
    "sg:orig_category":"Lederwaren / Einzelhandel",
    "sg:phone":"+43 1 8936231",
    "sg:postcode":"1150",
    "sg:province":"Wien",
    "wof:name":"Didi-Lederwaren",
    "wof:placetype":"venue"
},
  "geometry": {"coordinates":[16.3289794922,48.1913108826],"type":"Point"}
}