{
  "type": "Feature",
  "properties": {
    "addr:full":"Arthur-Krupp-Strasse 10a Amstetten Nieder\u00f6sterreich 3300",
    "addr:housenumber":"10a",
    "addr:postcode":"3300",
    "addr:street":"Arthur-Krupp-Strasse;Niederoesterreich",
    "iso:country":"AT",
    "sg:address":"Arthur-Krupp-Strasse 10a",
    "sg:city":"Amstetten",
    "sg:classifiers":[
        {
            "category":"Home & Garden",
            "subcategory":"Garden Supply",
            "type":"Retail Goods"
        }
    ],
    "sg:phone":"+43 7472 620710",
    "sg:postcode":"3300",
    "sg:province":"Nieder\u00f6sterreich",
    "sg:tags":[
        "aerator"
    ],
    "sg:website":"howi.at",
    "wof:name":"Hopferwieser International GmbH",
    "wof:placetype":"venue"
},
  "geometry": {"coordinates":[14.8936958313,48.1155929565],"type":"Point"}
}