{
  "type": "Feature",
  "properties": {
    "addr:full":"Uferstr 5 Wilhelmsburg an der Traisen Nieder\u00f6sterreich 3150",
    "addr:housenumber":"5",
    "addr:postcode":"3150",
    "addr:street":"Uferstr",
    "iso:country":"AT",
    "sg:address":"Uferstr 5",
    "sg:city":"Wilhelmsburg an der Traisen",
    "sg:orig_category":"Ingenieurkonsulenten / Zivilingenieure",
    "sg:phone":"+43 4327 46603770",
    "sg:postcode":"3150",
    "sg:province":"Nieder\u00f6sterreich",
    "wof:name":"S & E Consulting Engineers",
    "wof:placetype":"venue"
},
  "geometry": {"coordinates":[15.6012878418,48.095413208],"type":"Point"}
}