{
  "type": "Feature",
  "properties": {
    "addr:full":"Oberberg 441 Bizau Vorarlberg 6874",
    "addr:housenumber":"441",
    "addr:postcode":"6874",
    "addr:street":"Oberberg",
    "iso:country":"AT",
    "sg:address":"Oberberg 441",
    "sg:city":"Bizau",
    "sg:orig_category":"Filmproduktionen",
    "sg:phone":"+43 4355 143467",
    "sg:postcode":"6874",
    "sg:province":"Vorarlberg",
    "wof:name":"Reich Johannes",
    "wof:placetype":"venue"
},
  "geometry": {"coordinates":[9.9270410538,47.3717269897],"type":"Point"}
}