{
  "type": "Feature",
  "properties": {
    "addr:full":"Madlschenterweg 5 Traun Ober\u00f6sterreich 4050",
    "addr:housenumber":"5",
    "addr:postcode":"4050",
    "addr:street":"Madlschenterweg",
    "iso:country":"AT",
    "sg:address":"Madlschenterweg 5",
    "sg:city":"Traun",
    "sg:orig_category":"Fahrschulen",
    "sg:phone":"+43 7229 72683",
    "sg:postcode":"4050",
    "sg:province":"Ober\u00f6sterreich",
    "wof:name":"Fahrschule Rauch",
    "wof:placetype":"venue"
},
  "geometry": {"coordinates":[14.2399196625,48.2196044922],"type":"Point"}
}