{
  "type": "Feature",
  "properties": {
    "addr:full":"Grazer Str 4 Feldbach Steiermark 8330",
    "addr:housenumber":"4",
    "addr:postcode":"8330",
    "addr:street":"Str",
    "iso:country":"AT",
    "sg:address":"Grazer Str 4",
    "sg:city":"Feldbach",
    "sg:classifiers":[
        {
            "category":"Shopping",
            "subcategory":"Bicycles & Sporting Goods",
            "type":"Retail Goods"
        }
    ],
    "sg:phone":"+43 3152 3523",
    "sg:postcode":"8330",
    "sg:province":"Steiermark",
    "sg:tags":[
        "munition",
        "u",
        "waffen"
    ],
    "wof:name":"Rossmann Johann",
    "wof:placetype":"venue"
},
  "geometry": {"coordinates":[15.8865833282,46.9531517029],"type":"Point"}
}