{
  "type": "Feature",
  "properties": {
    "addr:full":"Korngasse 7 Gro\u00df-Enzersdorf Nieder\u00f6sterreich 2301",
    "addr:housenumber":"7",
    "addr:postcode":"2301",
    "addr:street":"Korngasse;Niederoesterreich",
    "iso:country":"AT",
    "sg:address":"Korngasse 7",
    "sg:city":"Gro\u00df-Enzersdorf",
    "sg:classifiers":[
        {
            "category":"Shopping",
            "subcategory":"Books",
            "type":"Retail Goods"
        }
    ],
    "sg:phone":"+43 2249 28801",
    "sg:postcode":"2301",
    "sg:province":"Nieder\u00f6sterreich",
    "sg:website":"brautinfo.at",
    "wof:name":"Verlag Ing. Ursula Effenberger",
    "wof:placetype":"venue"
},
  "geometry": {"coordinates":[16.5559139252,48.2021827698],"type":"Point"}
}