{
  "type": "Feature",
  "properties": {
    "addr:full":"Johann-Sebastian-Bach-Gasse 1 Graz Steiermark 8010",
    "addr:housenumber":"1",
    "addr:postcode":"8010",
    "addr:street":"Johann-Sebastian-Bach-Gasse",
    "iso:country":"AT",
    "sg:address":"Johann-Sebastian-Bach-Gasse 1",
    "sg:city":"Graz",
    "sg:orig_category":"Bicycle Valves",
    "sg:phone":"+43 316 46760",
    "sg:postcode":"8010",
    "sg:province":"Steiermark",
    "sg:website":"ventrex.com",
    "wof:name":"Ventrex Automotive GmbH",
    "wof:placetype":"venue"
},
  "geometry": {"coordinates":[15.4543142319,47.0498199463],"type":"Point"}
}