{
  "type": "Feature",
  "properties": {
    "addr:full":"Ludlgasse 19  Linz Ober\u00f6sterreich 4020",
    "addr:housenumber":"19",
    "addr:postcode":"4020",
    "addr:street":"Ludlgasse",
    "iso:country":"AT",
    "sg:address":"Ludlgasse 19 ",
    "sg:city":"Linz",
    "sg:classifiers":[
        {
            "category":"Shopping",
            "subcategory":"Gifts & Souvenirs",
            "type":"Retail Goods"
        }
    ],
    "sg:phone":"+43 4373 2772272",
    "sg:postcode":"4020",
    "sg:province":"Ober\u00f6sterreich",
    "wof:name":"AUSTRIA TABAKWERKE AG & CO KG",
    "wof:placetype":"venue"
},
  "geometry": {"coordinates":[14.298664093,48.3114204407],"type":"Point"}
}