{
  "type": "Feature",
  "properties": {
    "addr:full":"Dornbacher Strasse 89 Wien Wien 1170",
    "addr:housenumber":"89",
    "addr:postcode":"1170",
    "addr:street":"Dornbacher Strasse",
    "iso:country":"AT",
    "sg:address":"Dornbacher Strasse 89",
    "sg:city":"Wien",
    "sg:classifiers":[
        {
            "category":"Home & Garden",
            "subcategory":"Home Furnishings",
            "type":"Retail Goods"
        }
    ],
    "sg:phone":"+43 1 4861188",
    "sg:postcode":"1170",
    "sg:province":"Wien",
    "sg:tags":[
        "bathroom",
        "wc",
        "fitting"
    ],
    "wof:name":"A. Schwendt Sanit\u00e4rstudio",
    "wof:placetype":"venue"
},
  "geometry": {"coordinates":[16.2943744659,48.2312011719],"type":"Point"}
}