{
  "type": "Feature",
  "properties": {
    "addr:full":"Linzer Str 1 Amstetten Nieder\u00f6sterreich 3300",
    "addr:housenumber":"1",
    "addr:postcode":"3300",
    "addr:street":"Linzer Str;Niederoesterreich",
    "iso:country":"AT",
    "sg:address":"Linzer Str 1",
    "sg:city":"Amstetten",
    "sg:orig_category":"Cd, Dvd,Musikkassetten U Schallplatten",
    "sg:phone":"+43 4374 7261456",
    "sg:postcode":"3300",
    "sg:province":"Nieder\u00f6sterreich",
    "wof:name":"Zum Kuckuck",
    "wof:placetype":"venue"
},
  "geometry": {"coordinates":[14.8707437515,48.1240501404],"type":"Point"}
}