{
  "type": "Feature",
  "properties": {
    "addr:full":"Rathauspl 10 Weitra Nieder\u00f6sterreich 3970",
    "addr:housenumber":"10",
    "addr:postcode":"3970",
    "addr:street":"Rathauspl",
    "iso:country":"AT",
    "sg:address":"Rathauspl 10",
    "sg:city":"Weitra",
    "sg:orig_category":"Boutiquen",
    "sg:phone":"+43 4328 562037",
    "sg:postcode":"3970",
    "sg:province":"Nieder\u00f6sterreich",
    "wof:name":"Boutique Armano",
    "wof:placetype":"venue"
},
  "geometry": {"coordinates":[14.8945846558,48.7009773254],"type":"Point"}
}