{
  "type": "Feature",
  "properties": {
    "addr:full":"Hans Zach-Str 11 Gallneukirchen Ober\u00f6sterreich 4210",
    "addr:housenumber":"11",
    "addr:postcode":"4210",
    "addr:street":"Oberoesterreich",
    "iso:country":"AT",
    "sg:address":"Hans Zach-Str 11",
    "sg:city":"Gallneukirchen",
    "sg:orig_category":"Abfallentsorgung U -Verwertung",
    "sg:phone":"+43 7235 64118",
    "sg:postcode":"4210",
    "sg:province":"Ober\u00f6sterreich",
    "wof:name":"Altstoffsammelzentrum Gallneukirchen",
    "wof:placetype":"venue"
},
  "geometry": {"coordinates":[14.4160146713,48.3530960083],"type":"Point"}
}