{
  "type": "Feature",
  "properties": {
    "addr:full":"Sternwaldstrasse 18 Haslach an der M\u00fchl Ober\u00f6sterreich 4170",
    "addr:housenumber":"18",
    "addr:postcode":"4170",
    "addr:street":"Sternwaldstrasse;Oberoesterreich",
    "iso:country":"AT",
    "sg:address":"Sternwaldstrasse 18",
    "sg:city":"Haslach an der M\u00fchl",
    "sg:classifiers":[
        {
            "category":"Building & Trades",
            "subcategory":"Cleaning & Sanitation",
            "type":"Services"
        }
    ],
    "sg:phone":"+43 7289 712550",
    "sg:postcode":"4170",
    "sg:province":"Ober\u00f6sterreich",
    "sg:tags":[
        "repair",
        "installation",
        "sanitary"
    ],
    "wof:name":"Florian Wiplinger Ges.m.b.H. & Co KG",
    "wof:placetype":"venue"
},
  "geometry": {"coordinates":[14.1033849716,48.5675315857],"type":"Point"}
}