{
  "type": "Feature",
  "properties": {
    "iso:country":"AT",
    "sg:address":"Sierninger Str 170",
    "sg:city":"Steyr",
    "sg:orig_category":"Banken U Sparkassen",
    "sg:phone":"+43 4372 5271174",
    "sg:postcode":"4400",
    "sg:province":"Ober\u00f6sterreich",
    "wof:name":"Hypo-Bank Ober\u00f6sterreichische Landesbank AG",
    "wof:placetype":"venue"
},
  "geometry": {"coordinates":[14.3914213181,48.0439872742],"type":"Point"}
}