{
  "type": "Feature",
  "properties": {
    "addr:full":"Sebastianstr 4 Oggau Burgenland 7063",
    "addr:housenumber":"4",
    "addr:postcode":"oggau;7063",
    "addr:street":"Sebastianstr",
    "iso:country":"AT",
    "sg:address":"Sebastianstr 4",
    "sg:city":"Oggau",
    "sg:orig_category":"Feuerwehren",
    "sg:phone":"+43 2685 7422",
    "sg:postcode":"7063",
    "sg:province":"Burgenland",
    "wof:name":"Freiwillige Feuerwehr Oggau",
    "wof:placetype":"venue"
},
  "geometry": {"coordinates":[16.6671619415,47.8329200745],"type":"Point"}
}