{
  "type": "Feature",
  "properties": {
    "addr:full":"Hauptstrasse 10 Rottenmann Steiermark 8786",
    "addr:housenumber":"10",
    "addr:postcode":"8786",
    "addr:street":"Hauptstrasse",
    "iso:country":"AT",
    "sg:address":"Hauptstrasse 10",
    "sg:city":"Rottenmann",
    "sg:classifiers":[
        {
            "category":"Home & Garden",
            "subcategory":"Building Materials",
            "type":"Retail Goods"
        }
    ],
    "sg:phone":"+43 3614 23210",
    "sg:postcode":"8786",
    "sg:province":"Steiermark",
    "sg:tags":[
        "installation",
        "electric"
    ],
    "wof:name":"Helmut Matlschweiger",
    "wof:placetype":"venue"
},
  "geometry": {"coordinates":[14.3599815369,47.5254554749],"type":"Point"}
}