{
  "type": "Feature",
  "properties": {
    "addr:full":"Zieglerg 31 Wien Wien 1070",
    "addr:housenumber":"31",
    "addr:postcode":"1070",
    "addr:street":"Zieglerg",
    "iso:country":"AT",
    "sg:address":"Zieglerg 31",
    "sg:city":"Wien",
    "sg:orig_category":"\u00c3\u201enderungsschneidereien",
    "sg:phone":"+43 4319 904230",
    "sg:postcode":"1070",
    "sg:province":"Wien",
    "wof:name":"Prio KEG",
    "wof:placetype":"venue"
},
  "geometry": {"coordinates":[16.344865799,48.2012367249],"type":"Point"}
}