{
  "type": "Feature",
  "properties": {
    "addr:full":"Badstubenweg 93 Villach K\u00e4rnten 9500",
    "addr:housenumber":"93",
    "addr:postcode":"9500",
    "addr:street":"Badstubenweg;Kaernten",
    "iso:country":"AT",
    "sg:address":"Badstubenweg 93",
    "sg:city":"Villach",
    "sg:orig_category":"Tabaktrafiken",
    "sg:phone":"+43 664 1520109",
    "sg:postcode":"9500",
    "sg:province":"K\u00e4rnten",
    "wof:name":"Auer Helmut",
    "wof:placetype":"venue"
},
  "geometry": {"coordinates":[13.824048996,46.6300125122],"type":"Point"}
}