{
  "type": "Feature",
  "properties": {
    "iso:country":"AT",
    "sg:address":"Egererstr 36A",
    "sg:city":"Tullnerbach",
    "sg:orig_category":"Automaten",
    "sg:phone":"+43 2233 54698",
    "sg:postcode":"3013",
    "sg:province":"Nieder\u00f6sterreich",
    "wof:name":"Hummer Rudolf - Spielautomaten",
    "wof:placetype":"venue"
},
  "geometry": {"coordinates":[16.0981845856,48.1843643188],"type":"Point"}
}