{
  "type": "Feature",
  "properties": {
    "iso:country":"AT",
    "sg:address":"Wiener Str B57",
    "sg:city":"G\u00fcssing",
    "sg:orig_category":"Lebensmittel / Einzelhandel",
    "sg:phone":"+43 3322 43690",
    "sg:postcode":"7540",
    "sg:province":"Burgenland",
    "wof:name":"Hofer KG",
    "wof:placetype":"venue"
},
  "geometry": {"coordinates":[16.3176727295,47.0723075867],"type":"Point"}
}