{
  "type": "Feature",
  "properties": {
    "iso:country":"AT",
    "sg:address":"Mosern 19",
    "sg:city":"Grundlsee",
    "sg:orig_category":"Fischerei",
    "sg:phone":"+43 4336 228513",
    "sg:postcode":"8993",
    "sg:province":"Steiermark",
    "wof:name":"\u00f6sterreichische Bundesforste AG - Fischereibetrieb",
    "wof:placetype":"venue"
},
  "geometry": {"coordinates":[13.8275775909,47.622718811],"type":"Point"}
}