{
  "type": "Feature",
  "properties": {
    "addr:full":"Rottweg 119 Salzburg Salzburg 5020",
    "addr:housenumber":"119",
    "addr:postcode":"5020",
    "addr:street":"Rottweg;Salzburg",
    "iso:country":"AT",
    "sg:address":"Rottweg 119",
    "sg:city":"Salzburg",
    "sg:classifiers":[
        {
            "category":"Parking",
            "subcategory":"Lot",
            "type":"Transportation"
        }
    ],
    "sg:phone":"+43 4366 24332290",
    "sg:postcode":"5020",
    "sg:province":"Salzburg",
    "sg:tags":[
        "transport",
        "road"
    ],
    "wof:name":"WALTER SEBERT GESMBH",
    "wof:placetype":"venue"
},
  "geometry": {"coordinates":[12.9965839386,47.8292427063],"type":"Point"}
}