{
  "type": "Feature",
  "properties": {
    "iso:country":"AT",
    "sg:address":"Unionstr 98-100",
    "sg:city":"Linz",
    "sg:orig_category":"Maler, Anstreicher U Lackierer",
    "sg:phone":"+43 732 6831320",
    "sg:postcode":"4020",
    "sg:province":"Ober\u00f6sterreich",
    "sg:website":"www.happy-maler.at",
    "wof:name":"Happy-Maler GesmbH",
    "wof:placetype":"venue"
},
  "geometry": {"coordinates":[14.282242775,48.2804412842],"type":"Point"}
}