{
  "type": "Feature",
  "properties": {
    "addr:full":"W\u00e4hringer Str 120 Wien Wien 1180",
    "addr:housenumber":"120",
    "addr:postcode":"1180",
    "addr:street":"Str",
    "iso:country":"AT",
    "sg:address":"W\u00e4hringer Str 120",
    "sg:city":"Wien",
    "sg:orig_category":"Fotoapparate U -Artikel / Einzelhandel",
    "sg:phone":"+43 4314 7968050",
    "sg:postcode":"1180",
    "sg:province":"Wien",
    "wof:name":"Hartlauer HandelsgesmbH",
    "wof:placetype":"venue"
},
  "geometry": {"coordinates":[16.3432598114,48.226650238],"type":"Point"}
}