{
  "type": "Feature",
  "properties": {
    "addr:full":"Franz-Dinhobl-Str 17 Ternitz Nieder\u00f6sterreich 2630",
    "addr:housenumber":"17",
    "addr:postcode":"2630",
    "addr:street":"Franz-Dinhobl-Str",
    "iso:country":"AT",
    "sg:address":"Franz-Dinhobl-Str 17",
    "sg:city":"Ternitz",
    "sg:orig_category":"Tabaktrafiken",
    "sg:phone":"+43 2630 38551",
    "sg:postcode":"2630",
    "sg:province":"Nieder\u00f6sterreich",
    "wof:name":"Wirth Brigitte",
    "wof:placetype":"venue"
},
  "geometry": {"coordinates":[16.0316925049,47.7131958008],"type":"Point"}
}