{
  "type": "Feature",
  "properties": {
    "addr:full":"Klagenfurter Str 553 Bad St. Leonhard im Lavanttal K\u00e4rnten 9462",
    "addr:postcode":"9462",
    "addr:street":"Bad",
    "iso:country":"AT",
    "sg:address":"Klagenfurter Str 553",
    "sg:city":"Bad St. Leonhard im Lavanttal",
    "sg:orig_category":"Lebensmittel / Einzelhandel",
    "sg:phone":"+43 4343 5041030",
    "sg:postcode":"9462",
    "sg:province":"K\u00e4rnten",
    "wof:name":"SPAR \u00f6sterreichische Warenhandels-AG",
    "wof:placetype":"venue"
},
  "geometry": {"coordinates":[14.7947530746,46.9607276917],"type":"Point"}
}