{
  "type": "Feature",
  "properties": {
    "addr:full":"Kaiserstr 6a Bregenz Vorarlberg 6900",
    "addr:housenumber":"6a",
    "addr:postcode":"6900",
    "addr:street":"Kaiserstr",
    "iso:country":"AT",
    "sg:address":"Kaiserstr 6a",
    "sg:city":"Bregenz",
    "sg:orig_category":"Telekommunikation",
    "sg:phone":"+43 800 664300",
    "sg:postcode":"6900",
    "sg:province":"Vorarlberg",
    "wof:name":"A1-Shop Bregenz",
    "wof:placetype":"venue"
},
  "geometry": {"coordinates":[9.7467765808,47.5027160645],"type":"Point"}
}