{
  "type": "Feature",
  "properties": {
    "addr:full":"Wiener Str 4 Linz Ober\u00f6sterreich 4020",
    "addr:housenumber":"4",
    "addr:postcode":"4020",
    "iso:country":"AT",
    "sg:address":"Wiener Str 4",
    "sg:city":"Linz",
    "sg:orig_category":"Juweliere, Gold- U Silberschmiede",
    "sg:phone":"+43 732 652524",
    "sg:postcode":"4020",
    "sg:province":"Ober\u00f6sterreich",
    "wof:name":"Gerner GesmbH",
    "wof:placetype":"venue"
},
  "geometry": {"coordinates":[14.2973566055,48.2901611328],"type":"Point"}
}