{
  "type": "Feature",
  "properties": {
    "addr:full":"Rudolfstr 1 Linz Ober\u00f6sterreich 4040",
    "addr:housenumber":"1",
    "addr:postcode":"4040",
    "addr:street":"Rudolfstr",
    "iso:country":"AT",
    "sg:address":"Rudolfstr 1",
    "sg:city":"Linz",
    "sg:classifiers":[
        {
            "category":"Restaurant",
            "type":"Food & Drink"
        }
    ],
    "sg:phone":"+43 732 711795",
    "sg:postcode":"4040",
    "sg:province":"Ober\u00f6sterreich",
    "wof:name":"Schnitzel-Express",
    "wof:placetype":"venue"
},
  "geometry": {"coordinates":[14.2822561264,48.3110275269],"type":"Point"}
}