{
  "type": "Feature",
  "properties": {
    "addr:full":"Wexstr 19-23 Wien Wien 1200",
    "addr:postcode":"19-23;1200",
    "iso:country":"AT",
    "sg:address":"Wexstr 19-23",
    "sg:city":"Wien",
    "sg:orig_category":"Versuchsanstalten",
    "sg:phone":"+43 1 33126410",
    "sg:postcode":"1200",
    "sg:province":"Wien",
    "wof:name":"Versuchsanstalt f Heizung und L\u00fcftung",
    "wof:placetype":"venue"
},
  "geometry": {"coordinates":[16.3679065704,48.2361450195],"type":"Point"}
}