{
  "type": "Feature",
  "properties": {
    "addr:full":"Linzer Str 38 Marchtrenk Ober\u00f6sterreich 4614",
    "addr:housenumber":"38",
    "addr:postcode":"4614",
    "addr:street":"Linzer Str",
    "iso:country":"AT",
    "sg:address":"Linzer Str 38",
    "sg:city":"Marchtrenk",
    "sg:orig_category":"\u00c3\u201erzte / F Allgemeinmedizin",
    "sg:phone":"+43 7243 58570",
    "sg:postcode":"4614",
    "sg:province":"Ober\u00f6sterreich",
    "wof:name":"Asb\u00f6ck Bruno Dr",
    "wof:placetype":"venue"
},
  "geometry": {"coordinates":[14.1151666641,48.1907310486],"type":"Point"}
}