{
  "type": "Feature",
  "properties": {
    "addr:full":"Bergstr 5 Elixhausen Salzburg 5161",
    "addr:housenumber":"5",
    "addr:postcode":"5161",
    "addr:street":"Bergstr;Salzburg",
    "iso:country":"AT",
    "sg:address":"Bergstr 5",
    "sg:city":"Elixhausen",
    "sg:orig_category":"Tischlereien",
    "sg:phone":"+43 662 480669",
    "sg:postcode":"5161",
    "sg:province":"Salzburg",
    "wof:name":"Schickbauer Stefan",
    "wof:placetype":"venue"
},
  "geometry": {"coordinates":[13.054441452,47.865032196],"type":"Point"}
}