{
  "type": "Feature",
  "properties": {
    "addr:full":"Salzburger Str 4 Oberndorf Salzburg 5110",
    "addr:housenumber":"4",
    "addr:postcode":"5110",
    "addr:street":"Salzburger Str",
    "iso:country":"AT",
    "sg:address":"Salzburger Str 4",
    "sg:city":"Oberndorf",
    "sg:orig_category":"Tankstellen",
    "sg:phone":"+43 4362 7273182",
    "sg:postcode":"5110",
    "sg:province":"Salzburg",
    "wof:name":"Shell Austria GmbH",
    "wof:placetype":"venue"
},
  "geometry": {"coordinates":[12.9469137192,47.9339065552],"type":"Point"}
}