{
  "type": "Feature",
  "properties": {
    "addr:full":"B\u00fcrgerspitalpl 2-4 Ybbs an der Donau Nieder\u00f6sterreich 3370",
    "addr:housenumber":"2-4",
    "addr:postcode":"3370",
    "addr:street":"Buergerspitalpl",
    "iso:country":"AT",
    "sg:address":"B\u00fcrgerspitalpl 2-4",
    "sg:city":"Ybbs an der Donau",
    "sg:classifiers":[
        {
            "category":"Internet Cafe",
            "subcategory":"None",
            "type":"Food & Drink"
        }
    ],
    "sg:phone":"+43 4366 44461664",
    "sg:postcode":"3370",
    "sg:province":"Nieder\u00f6sterreich",
    "wof:name":"Internetservice Slavihodek - PURtel.at",
    "wof:placetype":"venue"
},
  "geometry": {"coordinates":[15.0850696564,48.1771202087],"type":"Point"}
}