{
  "type": "Feature",
  "properties": {
    "addr:full":"Wiener Str 59 Kapfenberg Steiermark 8605",
    "addr:postcode":"8605",
    "addr:street":"59",
    "iso:country":"AT",
    "sg:address":"Wiener Str 59",
    "sg:city":"Kapfenberg",
    "sg:orig_category":"Versicherungsunternehmen",
    "sg:phone":"+43 3862 220540",
    "sg:postcode":"8605",
    "sg:province":"Steiermark",
    "wof:name":"Z\u00fcrich Versicherungs-AG",
    "wof:placetype":"venue"
},
  "geometry": {"coordinates":[15.2970094681,47.4456253052],"type":"Point"}
}