{
  "type": "Feature",
  "properties": {
    "addr:full":"Stelzhamerstr 8 Linz Ober\u00f6sterreich 4020",
    "addr:housenumber":"8",
    "addr:postcode":"4020",
    "addr:street":"Stelzhamerstr",
    "iso:country":"AT",
    "sg:address":"Stelzhamerstr 8",
    "sg:city":"Linz",
    "sg:orig_category":"Banken U Sparkassen",
    "sg:phone":"+43 4350 10040009",
    "sg:postcode":"4020",
    "sg:province":"Ober\u00f6sterreich",
    "wof:name":"Allgemeine Sparkasse Ober\u00f6sterreich Bank AG",
    "wof:placetype":"venue"
},
  "geometry": {"coordinates":[14.2907571793,48.2960166931],"type":"Point"}
}