{
  "type": "Feature",
  "properties": {
    "iso:country":"AT",
    "sg:address":"Moosham 40",
    "sg:city":"Geinberg",
    "sg:classifiers":[
        {
            "category":"Utilities",
            "subcategory":"Fuel Oil & Lpg",
            "type":"Services"
        }
    ],
    "sg:phone":"+43 7723 42305",
    "sg:postcode":"4943",
    "sg:province":"Ober\u00f6sterreich",
    "sg:tags":[
        "dental",
        "product"
    ],
    "wof:name":"Mag. Hoeveler & Co Ges.m.b.H.",
    "wof:placetype":"venue"
},
  "geometry": {"coordinates":[13.2623634338,48.2635116577],"type":"Point"}
}