{
  "type": "Feature",
  "properties": {
    "addr:full":"Sparkassenweg 1 Ach Ober\u00f6sterreich 5122",
    "addr:housenumber":"1",
    "addr:postcode":"5122",
    "addr:street":"Sparkassenweg;Ach Oberoesterreich",
    "iso:country":"AT",
    "sg:address":"Sparkassenweg 1",
    "sg:city":"Ach",
    "sg:orig_category":"Banken U Sparkassen",
    "sg:phone":"+43 4350 10041069",
    "sg:postcode":"5122",
    "sg:province":"Ober\u00f6sterreich",
    "wof:name":"Salzburger Sparkasse Bank AG",
    "wof:placetype":"venue"
},
  "geometry": {"coordinates":[12.8391447067,48.1589889526],"type":"Point"}
}