{
  "type": "Feature",
  "properties": {
    "iso:country":"AT",
    "sg:address":"Schulstr 1",
    "sg:city":"Kremsm\u00fcnster",
    "sg:orig_category":"Polizei U Gendarmerie",
    "sg:phone":"+43 4359 1334124",
    "sg:postcode":"4550",
    "sg:province":"Ober\u00f6sterreich",
    "wof:name":"Gendarmerie",
    "wof:placetype":"venue"
},
  "geometry": {"coordinates":[14.1274738312,48.051990509],"type":"Point"}
}