{
  "type": "Feature",
  "properties": {
    "addr:full":"Nr 7 Strengberg Nieder\u00f6sterreich 3314",
    "addr:postcode":"3314",
    "addr:street":"Nr;Niederoesterreich",
    "iso:country":"AT",
    "sg:address":"Nr 7",
    "sg:city":"Strengberg",
    "sg:orig_category":"Autobusunternehmen",
    "sg:phone":"+43 7432 2375",
    "sg:postcode":"3314",
    "sg:province":"Nieder\u00f6sterreich",
    "wof:name":"Kitzberger Leopold",
    "wof:placetype":"venue"
},
  "geometry": {"coordinates":[14.6513147354,48.1428489685],"type":"Point"}
}