{
  "type": "Feature",
  "properties": {
    "addr:full":"Waidern 40 Schiedlberg Ober\u00f6sterreich 4521",
    "addr:housenumber":"40",
    "addr:postcode":"4521",
    "addr:street":"Waidern",
    "iso:country":"AT",
    "sg:address":"Waidern 40",
    "sg:city":"Schiedlberg",
    "sg:orig_category":"Modellbahnen",
    "sg:phone":"+43 7251 22277",
    "sg:postcode":"4521",
    "sg:province":"Ober\u00f6sterreich",
    "wof:name":"HOBBY-SOMMER GmbH - Modellbahnversand",
    "wof:placetype":"venue"
},
  "geometry": {"coordinates":[14.2754955292,48.0695610046],"type":"Point"}
}