{
  "type": "Feature",
  "properties": {
    "iso:country":"AT",
    "sg:address":"Wiener Strasse 39",
    "sg:city":"Wolkersdorf im Weinviertel",
    "sg:classifiers":[
        {
            "category":"Wholesale",
            "subcategory":"Scrap",
            "type":"Manufacturing & Wholesale Goods"
        }
    ],
    "sg:phone":"+43 2245 83800",
    "sg:postcode":"2120",
    "sg:province":"Nieder\u00f6sterreich",
    "sg:tags":[
        "metal"
    ],
    "sg:website":"optimist.co.at",
    "wof:name":"Optimist",
    "wof:placetype":"venue"
},
  "geometry": {"coordinates":[16.5096511841,48.3773193359],"type":"Point"}
}