{
  "type": "Feature",
  "properties": {
    "addr:full":"Nr 69a Kl\u00f6sterle Vorarlberg 6754",
    "addr:postcode":"6754",
    "addr:street":"Nr 69A Kloesterle",
    "iso:country":"AT",
    "sg:address":"Nr 69a",
    "sg:city":"Kl\u00f6sterle",
    "sg:orig_category":"Pensionen / Privatzimmer",
    "sg:phone":"+43 5582 429",
    "sg:postcode":"6754",
    "sg:province":"Vorarlberg",
    "wof:name":"Pension Brunner",
    "wof:placetype":"venue"
},
  "geometry": {"coordinates":[-101.40701293950001,34.2146606445],"type":"Point"}
}