{
  "type": "Feature",
  "properties": {
    "iso:country":"AT",
    "sg:address":"Wohlfahrt 133",
    "sg:city":"S\u00f6lden",
    "sg:orig_category":"Pensionen / Privatzimmer",
    "sg:phone":"+43 5254 2201",
    "sg:postcode":"6450",
    "sg:province":"Tirol",
    "wof:name":"Haus Anton",
    "wof:placetype":"venue"
},
  "geometry": {"coordinates":[11.0130348206,46.9578552246],"type":"Point"}
}