{
  "type": "Feature",
  "properties": {
    "addr:full":"Eichenstr 2b Wien Wien 1120",
    "addr:housenumber":"2b",
    "addr:postcode":"1120",
    "addr:street":"Eichenstr",
    "iso:country":"AT",
    "sg:address":"Eichenstr 2b",
    "sg:city":"Wien",
    "sg:orig_category":"Tankstellen",
    "sg:phone":"+43 1 8151346",
    "sg:postcode":"1120",
    "sg:province":"Wien",
    "wof:name":"BP Austria Marketing GmbH",
    "wof:placetype":"venue"
},
  "geometry": {"coordinates":[16.344335556,48.1778869629],"type":"Point"}
}