{
  "type": "Feature",
  "properties": {
    "iso:country":"AT",
    "sg:address":"Kle\u00dfheimer Allee 19",
    "sg:city":"Salzburg",
    "sg:orig_category":"Baumeister",
    "sg:phone":"+43 662 437832",
    "sg:postcode":"5020",
    "sg:province":"Salzburg",
    "wof:name":"Heinz Peter Bmstr Ing",
    "wof:placetype":"venue"
},
  "geometry": {"coordinates":[13.0180196762,47.8071250916],"type":"Point"}
}