{
  "type": "Feature",
  "properties": {
    "iso:country":"AT",
    "sg:address":"Leopoldstr 7",
    "sg:city":"Dornbirn",
    "sg:orig_category":"Volksschulen",
    "sg:phone":"+43 5572 249890",
    "sg:postcode":"6850",
    "sg:province":"Vorarlberg",
    "wof:name":"Volksschule",
    "wof:placetype":"venue"
},
  "geometry": {"coordinates":[9.7359199524,47.4023628235],"type":"Point"}
}