{
  "type": "Feature",
  "properties": {
    "iso:country":"AT",
    "sg:address":"Plaickhofweg 289",
    "sg:city":"Golling an der Salzach",
    "sg:orig_category":"Papier / Erzeugung U Gro\u00c3\u0178handel",
    "sg:phone":"+43 4362 447110",
    "sg:postcode":"5440",
    "sg:province":"Salzburg",
    "wof:name":"Papiermanufaktur Kornprobst Sepp - Handgesch\u00f6pftes B\u00fcttenpapier",
    "wof:placetype":"venue"
},
  "geometry": {"coordinates":[13.170589447,47.5917243958],"type":"Point"}
}