{
  "type": "Feature",
  "properties": {
    "addr:full":"K\u00f6rnerstr. 19 Spittal an der Drau K\u00e4rnten 9800",
    "addr:housenumber":"19",
    "addr:postcode":"9800",
    "addr:street":"Koernerstr.;Kaernten",
    "iso:country":"AT",
    "sg:address":"K\u00f6rnerstr. 19",
    "sg:city":"Spittal an der Drau",
    "sg:classifiers":[
        {
            "category":"Utilities",
            "subcategory":"Electric",
            "type":"Services"
        }
    ],
    "sg:phone":"+43 4347 6240220",
    "sg:postcode":"9800",
    "sg:province":"K\u00e4rnten",
    "sg:tags":[
        "component",
        "electronic"
    ],
    "wof:name":"EPI COMPONENTS TRADE GMBH",
    "wof:placetype":"venue"
},
  "geometry": {"coordinates":[13.486869812,46.8216552734],"type":"Point"}
}