{
  "type": "Feature",
  "properties": {
    "addr:full":"Industriestr. 12  Meiningen Vorarlberg 6812",
    "addr:housenumber":"12",
    "addr:postcode":"6812",
    "addr:street":"Industriestr.",
    "iso:country":"AT",
    "sg:address":"Industriestr. 12 ",
    "sg:city":"Meiningen",
    "sg:classifiers":[
        {
            "category":"Food & Beverages",
            "subcategory":"Groceries & Convenience Stores",
            "type":"Retail Goods"
        }
    ],
    "sg:phone":"+43 4355 227138711",
    "sg:postcode":"6812",
    "sg:province":"Vorarlberg",
    "sg:tags":[
        "product",
        "related"
    ],
    "wof:name":"WALSER OHG",
    "wof:placetype":"venue"
},
  "geometry": {"coordinates":[9.582159996,47.3049697876],"type":"Point"}
}