{
  "type": "Feature",
  "properties": {
    "addr:full":"Adnet Salzburg 5421",
    "addr:housenumber":"5421",
    "iso:country":"AT",
    "sg:city":"Adnet",
    "sg:classifiers":[
        {
            "category":"Manufacturing",
            "subcategory":"Wood Products",
            "type":"Manufacturing & Wholesale Goods"
        }
    ],
    "sg:phone":"+43 6245 80205",
    "sg:postcode":"5421",
    "sg:province":"Salzburg",
    "sg:tags":[
        "pallet",
        "made"
    ],
    "wof:name":"Dipl.-Kfm. Rupert Deisl",
    "wof:placetype":"venue"
},
  "geometry": {"coordinates":[13.1305770874,47.696975708],"type":"Point"}
}