{
  "type": "Feature",
  "properties": {
    "addr:full":"Nr 121 Hollenstein an der Ybbs Nieder\u00f6sterreich 3343",
    "addr:postcode":"3343",
    "addr:street":"Nr 121;Niederoesterreich",
    "iso:country":"AT",
    "sg:address":"Nr 121",
    "sg:city":"Hollenstein an der Ybbs",
    "sg:orig_category":"Rettungsdienste",
    "sg:phone":"+43 7445 414",
    "sg:postcode":"3343",
    "sg:province":"Nieder\u00f6sterreich",
    "wof:name":"Rotes Kreuz",
    "wof:placetype":"venue"
},
  "geometry": {"coordinates":[14.7712230682,47.8051452637],"type":"Point"}
}