{
  "type": "Feature",
  "properties": {
    "iso:country":"AT",
    "sg:address":"Nr 16",
    "sg:city":"St. Peter am Ottersbach",
    "sg:orig_category":"Landwirtschaftliche Produkte",
    "sg:phone":"+43 4334 772527",
    "sg:postcode":"8093",
    "sg:province":"Steiermark",
    "wof:name":"Ploder Anna Kern\u00f6l v Bauernhof",
    "wof:placetype":"venue"
},
  "geometry": {"coordinates":[15.7936754227,46.8288803101],"type":"Point"}
}