{
  "type": "Feature",
  "properties": {
    "addr:full":"Hauptstr 24 Gerasdorf Nieder\u00f6sterreich 2201",
    "addr:housenumber":"24",
    "addr:postcode":"2201",
    "addr:street":"Hauptstr",
    "iso:country":"AT",
    "sg:address":"Hauptstr 24",
    "sg:city":"Gerasdorf",
    "sg:classifiers":[
        {
            "category":"Travel",
            "subcategory":"Hotels & Motels",
            "type":"Entertainment"
        }
    ],
    "sg:phone":"+43 4322 4623980",
    "sg:postcode":"2201",
    "sg:province":"Nieder\u00f6sterreich",
    "wof:name":"Hotel Michael J u H Kutscha",
    "wof:placetype":"venue"
},
  "geometry": {"coordinates":[16.4692611694,48.297077179],"type":"Point"}
}