{
  "type": "Feature",
  "properties": {
    "iso:country":"AT",
    "sg:address":"Arnezhoferstr 4",
    "sg:city":"Wien",
    "sg:orig_category":"Installationsunternehmen",
    "sg:phone":"+43 1 7280798",
    "sg:postcode":"1020",
    "sg:province":"Wien",
    "wof:name":"GAWAS Gas- und Wasserleitungsinstallations GmbH",
    "wof:placetype":"venue"
},
  "geometry": {"coordinates":[16.3973884583,48.2194747925],"type":"Point"}
}