{
  "type": "Feature",
  "properties": {
    "addr:full":"Kautzener Str 198 Dobersberg Nieder\u00f6sterreich 3843",
    "addr:housenumber":"198",
    "addr:postcode":"3843",
    "addr:street":"Dobersberg Niederoesterreich",
    "iso:country":"AT",
    "sg:address":"Kautzener Str 198",
    "sg:city":"Dobersberg",
    "sg:orig_category":"Non-Classified Establishments",
    "sg:phone":"+43 2843 22490",
    "sg:postcode":"3843",
    "sg:province":"Nieder\u00f6sterreich",
    "wof:name":"Stra\u00dfenmeisterei Dobersberg",
    "wof:placetype":"venue"
},
  "geometry": {"coordinates":[15.3144798279,48.9170417786],"type":"Point"}
}