{
  "type": "Feature",
  "properties": {
    "addr:full":"Nr 107 Oberweis Ober\u00f6sterreich 4664",
    "addr:postcode":"4664",
    "addr:street":"Nr 107",
    "iso:country":"AT",
    "sg:address":"Nr 107",
    "sg:city":"Oberweis",
    "sg:orig_category":"Edelstahl",
    "sg:phone":"+43 664 3502343",
    "sg:postcode":"4664",
    "sg:province":"Ober\u00f6sterreich",
    "wof:name":"Winkler Richard",
    "wof:placetype":"venue"
},
  "geometry": {"coordinates":[13.8193435669,47.9532546997],"type":"Point"}
}