{
  "type": "Feature",
  "properties": {
    "addr:full":"Nr 101 Markt Allhau Burgenland 7411",
    "addr:postcode":"7411",
    "addr:street":"Nr",
    "iso:country":"AT",
    "sg:address":"Nr 101",
    "sg:city":"Markt Allhau",
    "sg:orig_category":"Beton- U Betonsteinwerke",
    "sg:phone":"+43 4333 592238",
    "sg:postcode":"7411",
    "sg:province":"Burgenland",
    "wof:name":"Kremnitzer GmbH",
    "wof:placetype":"venue"
},
  "geometry": {"coordinates":[16.0806007385,47.2934417725],"type":"Point"}
}