{
  "type": "Feature",
  "properties": {
    "addr:full":"Fronwaldstr 2 Schardenberg Ober\u00f6sterreich 4784",
    "addr:housenumber":"2",
    "addr:postcode":"4784",
    "addr:street":"Fronwaldstr",
    "iso:country":"AT",
    "sg:address":"Fronwaldstr 2",
    "sg:city":"Schardenberg",
    "sg:orig_category":"Non-Classified Establishments",
    "sg:phone":"+43 5 91334276",
    "sg:postcode":"4784",
    "sg:province":"Ober\u00f6sterreich",
    "wof:name":"Gendarmerieposten",
    "wof:placetype":"venue"
},
  "geometry": {"coordinates":[13.4966459274,48.5206832886],"type":"Point"}
}