{
  "type": "Feature",
  "properties": {
    "addr:full":"Nr 19 Ried im Innkreis Ober\u00f6sterreich 4910",
    "addr:postcode":"4910",
    "addr:street":"Nr 19",
    "iso:country":"AT",
    "sg:address":"Nr 19",
    "sg:city":"Ried im Innkreis",
    "sg:orig_category":"Polizei U Gendarmerie",
    "sg:phone":"+43 4359 1334245",
    "sg:postcode":"4910",
    "sg:province":"Ober\u00f6sterreich",
    "wof:name":"Gendarmerie Verkehrsabteilung Au\u00dfenstelle",
    "wof:placetype":"venue"
},
  "geometry": {"coordinates":[13.4900550842,48.2098655701],"type":"Point"}
}