{
  "type": "Feature",
  "properties": {
    "iso:country":"AT",
    "sg:address":"Nr 85",
    "sg:city":"Donnersbach",
    "sg:orig_category":"Banken U Sparkassen",
    "sg:phone":"+43 3680 390",
    "sg:postcode":"8953",
    "sg:province":"Steiermark",
    "wof:name":"Steierm\u00e4rkische Bank und Sparkassen AG",
    "wof:placetype":"venue"
},
  "geometry": {"coordinates":[14.1177520752,47.3823890686],"type":"Point"}
}