{
  "type": "Feature",
  "properties": {
    "iso:country":"AT",
    "sg:address":"F\u00fcrbachweg 12",
    "sg:city":"Wagrain",
    "sg:classifiers":[
        {
            "category":"Travel",
            "subcategory":"Hotels & Motels",
            "type":"Entertainment"
        }
    ],
    "sg:phone":"+43 4364 138626",
    "sg:postcode":"5602",
    "sg:province":"Salzburg",
    "wof:name":"Jugendhotel Striedlhof",
    "wof:placetype":"venue"
},
  "geometry": {"coordinates":[13.2964773178,47.3332366943],"type":"Point"}
}