{
  "type": "Feature",
  "properties": {
    "addr:full":"Hirzegg 16 Ramsau am Dachstein Steiermark 8972",
    "addr:housenumber":"16",
    "addr:postcode":"8972",
    "addr:street":"Hirzegg",
    "iso:country":"AT",
    "sg:address":"Hirzegg 16",
    "sg:city":"Ramsau am Dachstein",
    "sg:orig_category":"Appartements / Ferienwohnungen",
    "sg:phone":"+43 3687 81209",
    "sg:postcode":"8972",
    "sg:province":"Steiermark",
    "wof:name":"Knaushof",
    "wof:placetype":"venue"
},
  "geometry": {"coordinates":[13.6063156128,47.4438285828],"type":"Point"}
}