{
  "type": "Feature",
  "properties": {
    "addr:full":"Hauptpl 8 F\u00fcrstenfeld Steiermark 8280",
    "addr:housenumber":"8",
    "addr:postcode":"8280",
    "addr:street":"Hauptpl",
    "iso:country":"AT",
    "sg:address":"Hauptpl 8",
    "sg:city":"F\u00fcrstenfeld",
    "sg:orig_category":"Juwelen, Gold- U Silberwaren / Einzelhandel",
    "sg:phone":"+43 4333 8251959",
    "sg:postcode":"8280",
    "sg:province":"Steiermark",
    "wof:name":"Purkarthofer Ingrid",
    "wof:placetype":"venue"
},
  "geometry": {"coordinates":[16.076921463,47.0513877869],"type":"Point"}
}