{
  "type": "Feature",
  "properties": {
    "iso:country":"AT",
    "sg:address":"Clemens Krauss-Str 21",
    "sg:city":"Salzburg",
    "sg:classifiers":[
        {
            "category":"Professional",
            "subcategory":"Computer Services",
            "type":"Services"
        }
    ],
    "sg:phone":"+43 662 643003",
    "sg:postcode":"5020",
    "sg:province":"Salzburg",
    "sg:tags":[
        "software"
    ],
    "wof:name":"InterPhace Technologies Software GesmbH",
    "wof:placetype":"venue"
},
  "geometry": {"coordinates":[13.0758085251,47.8002624512],"type":"Point"}
}