{
  "type": "Feature",
  "properties": {
    "addr:full":"Aum\u00fchlweg 21/2/Top 215 Leobersdorf Nieder\u00f6sterreich 2544",
    "addr:housenumber":"21 / 2 / top 215",
    "addr:postcode":"2544",
    "addr:street":"Aumuehlweg",
    "iso:country":"AT",
    "sg:address":"Aum\u00fchlweg 21/2/Top 215",
    "sg:city":"Leobersdorf",
    "sg:classifiers":[
        {
            "category":"Professional",
            "subcategory":"Art Services",
            "type":"Services"
        }
    ],
    "sg:phone":"+43 2256 65550",
    "sg:postcode":"2544",
    "sg:province":"Nieder\u00f6sterreich",
    "sg:tags":[
        "materials",
        "advertising",
        "customer-designed"
    ],
    "sg:website":"heko-dress-promotion.com",
    "wof:name":"HEKO dress & promotion",
    "wof:placetype":"venue"
},
  "geometry": {"coordinates":[16.2165107727,47.9286613464],"type":"Point"}
}