{
  "type": "Feature",
  "properties": {
    "iso:country":"AT",
    "sg:address":"Porzellang 44-46",
    "sg:city":"Wien",
    "sg:orig_category":"Textilreinigung",
    "sg:phone":"+43 1 3199663",
    "sg:postcode":"1090",
    "sg:province":"Wien",
    "wof:name":"Gottschalk Eva",
    "wof:placetype":"venue"
},
  "geometry": {"coordinates":[16.361656189,48.2232246399],"type":"Point"}
}