{
  "type": "Feature",
  "properties": {
    "addr:full":"Rosentaler Strasse 127 Klagenfurt K\u00e4rnten 9020",
    "addr:housenumber":"127",
    "addr:postcode":"9020",
    "addr:street":"Rosentaler Strasse;Kaernten",
    "iso:country":"AT",
    "sg:address":"Rosentaler Strasse 127",
    "sg:city":"Klagenfurt",
    "sg:classifiers":[
        {
            "category":"Social Services",
            "subcategory":"Retirement Home",
            "type":"Services"
        }
    ],
    "sg:phone":"+43 463 219812",
    "sg:postcode":"9020",
    "sg:province":"K\u00e4rnten",
    "sg:tags":[
        "car",
        "number",
        "plate",
        "registration"
    ],
    "wof:name":"Rabitsch Ges.m.b.H.",
    "wof:placetype":"venue"
},
  "geometry": {"coordinates":[14.2992162704,46.6075325012],"type":"Point"}
}