{
  "type": "Feature",
  "properties": {
    "addr:full":"Blumeng. 3 Steinabr\u00fcckl Nieder\u00f6sterreich 2751",
    "addr:housenumber":"3",
    "addr:postcode":"2751",
    "addr:street":"Blumeng.;Niederoesterreich",
    "iso:country":"AT",
    "sg:address":"Blumeng. 3",
    "sg:city":"Steinabr\u00fcckl",
    "sg:classifiers":[
        {
            "category":"Parking",
            "subcategory":"Lot",
            "type":"Transportation"
        }
    ],
    "sg:phone":"+43 4326 2243094",
    "sg:postcode":"2751",
    "sg:province":"Nieder\u00f6sterreich",
    "sg:tags":[
        "transport",
        "road"
    ],
    "wof:name":"KARL KAINDL",
    "wof:placetype":"venue"
},
  "geometry": {"coordinates":[16.201713562,47.8727607727],"type":"Point"}
}