{
  "type": "Feature",
  "properties": {
    "addr:full":"Breiteng 12 Schrems Nieder\u00f6sterreich 3943",
    "addr:housenumber":"12",
    "addr:postcode":"3943",
    "addr:street":"Breiteng",
    "iso:country":"AT",
    "sg:address":"Breiteng 12",
    "sg:city":"Schrems",
    "sg:orig_category":"Grafische Bedarfsartikel",
    "sg:phone":"+43 4328 53765180",
    "sg:postcode":"3943",
    "sg:province":"Nieder\u00f6sterreich",
    "wof:name":"Korherr F.R. Graphischer Fachhandel GmbH",
    "wof:placetype":"venue"
},
  "geometry": {"coordinates":[15.0589942932,48.7934074402],"type":"Point"}
}