{
  "type": "Feature",
  "properties": {
    "addr:full":"Kirchenpl 17 Maria Laach am Jauerling Nieder\u00f6sterreich 3643",
    "addr:housenumber":"17",
    "addr:postcode":"3643",
    "addr:street":"Kirchenpl;Laach Am Jauerling",
    "iso:country":"AT",
    "sg:address":"Kirchenpl 17",
    "sg:city":"Maria Laach am Jauerling",
    "sg:orig_category":"Friseure U Frisiersalons",
    "sg:phone":"+43 4327 128598",
    "sg:postcode":"3643",
    "sg:province":"Nieder\u00f6sterreich",
    "wof:name":"Frisiersalon Petronella",
    "wof:placetype":"venue"
},
  "geometry": {"coordinates":[15.3425111771,48.3045310974],"type":"Point"}
}