{
  "type": "Feature",
  "properties": {
    "iso:country":"AT",
    "sg:address":"Nr 41",
    "sg:city":"Jenig",
    "sg:orig_category":"Pensionen / Privatzimmer",
    "sg:phone":"+43 4342 852270",
    "sg:postcode":"9631",
    "sg:province":"K\u00e4rnten",
    "wof:name":"Fr\u00fchst\u00fcckspension Oberj\u00f6rg KG",
    "wof:placetype":"venue"
},
  "geometry": {"coordinates":[13.2537050247,46.6278686523],"type":"Point"}
}