{
  "type": "Feature",
  "properties": {
    "addr:full":"Im Wingat 19 Bregenz Vorarlberg 6900",
    "addr:housenumber":"19",
    "addr:postcode":"6900",
    "addr:street":"Im Wingat",
    "iso:country":"AT",
    "sg:address":"Im Wingat 19",
    "sg:city":"Bregenz",
    "sg:orig_category":"Lebens- U Sozialberatung",
    "sg:phone":"+43 4366 41848848",
    "sg:postcode":"6900",
    "sg:province":"Vorarlberg",
    "wof:name":"Heil Johannes Christoph",
    "wof:placetype":"venue"
},
  "geometry": {"coordinates":[9.7314691544,47.4872627258],"type":"Point"}
}