{
  "type": "Feature",
  "properties": {
    "addr:full":"Stiglingen 3 Dornbirn Vorarlberg 6850",
    "addr:housenumber":"3",
    "addr:postcode":"6850",
    "addr:street":"Stiglingen",
    "iso:country":"AT",
    "sg:address":"Stiglingen 3",
    "sg:city":"Dornbirn",
    "sg:orig_category":"Montagen U Montagetechnik",
    "sg:phone":"+43 664 5020420",
    "sg:postcode":"6850",
    "sg:province":"Vorarlberg",
    "wof:name":"St\u00f6by Peter",
    "wof:placetype":"venue"
},
  "geometry": {"coordinates":[9.7551202774,47.4308815002],"type":"Point"}
}