{
  "type": "Feature",
  "properties": {
    "addr:full":"Merang 58 Graz Steiermark 8010",
    "addr:housenumber":"58",
    "addr:postcode":"8010",
    "addr:street":"Merang",
    "iso:country":"AT",
    "sg:address":"Merang 58",
    "sg:city":"Graz",
    "sg:orig_category":"Dachdeckereien",
    "sg:phone":"+43 316 3230100",
    "sg:postcode":"8010",
    "sg:province":"Steiermark",
    "wof:name":"Simmet Oskar GesmbH",
    "wof:placetype":"venue"
},
  "geometry": {"coordinates":[15.4563407898,47.0716781616],"type":"Point"}
}