{
  "type": "Feature",
  "properties": {
    "addr:full":"Michaelsg 22 Lienz Tirol 9900",
    "addr:housenumber":"22",
    "addr:postcode":"9900",
    "addr:street":"Michaelsg;Tirol",
    "iso:country":"AT",
    "sg:address":"Michaelsg 22",
    "sg:city":"Lienz",
    "sg:orig_category":"Beschriftungen",
    "sg:phone":"+43 4852 68270",
    "sg:postcode":"9900",
    "sg:province":"Tirol",
    "wof:name":"M\u00fchlthau Alfred jun",
    "wof:placetype":"venue"
},
  "geometry": {"coordinates":[12.7675657272,46.8336105347],"type":"Point"}
}