{
  "type": "Feature",
  "properties": {
    "addr:full":"Wickenburggasse 20 Graz Steiermark 8010",
    "addr:housenumber":"20",
    "addr:postcode":"8010",
    "addr:street":"Wickenburggasse",
    "iso:country":"AT",
    "sg:address":"Wickenburggasse 20",
    "sg:city":"Graz",
    "sg:classifiers":[
        {
            "category":"Insurance",
            "subcategory":"Life Insurance",
            "type":"Services"
        }
    ],
    "sg:phone":"+43 316 683185",
    "sg:postcode":"8010",
    "sg:province":"Steiermark",
    "sg:tags":[
        "felt",
        "hat"
    ],
    "sg:website":"kepka.at",
    "wof:name":"Josef Kepka & S\u00f6hne Hutfabrikation",
    "wof:placetype":"venue"
},
  "geometry": {"coordinates":[15.4366006851,47.0789146423],"type":"Point"}
}