{
  "type": "Feature",
  "properties": {
    "addr:full":"Hauptpl 13 Hartberg Steiermark 8230",
    "addr:housenumber":"13",
    "addr:postcode":"8230",
    "addr:street":"Hauptpl",
    "iso:country":"AT",
    "sg:address":"Hauptpl 13",
    "sg:city":"Hartberg",
    "sg:orig_category":"Non-Classified Establishments",
    "sg:phone":"+43 3332 622800",
    "sg:postcode":"8230",
    "sg:province":"Steiermark",
    "wof:name":"Kirchenbeitragsstelle",
    "wof:placetype":"venue"
},
  "geometry": {"coordinates":[15.9694471359,47.2807998657],"type":"Point"}
}