{
  "type": "Feature",
  "properties": {
    "iso:country":"AT",
    "sg:address":"Mitterweg 16",
    "sg:city":"Innsbruck",
    "sg:orig_category":"Blut- U Plasmaspenden",
    "sg:phone":"+43 512 274332",
    "sg:postcode":"6020",
    "sg:province":"Tirol",
    "wof:name":"Baxter AG - Plasmazentrum",
    "wof:placetype":"venue"
},
  "geometry": {"coordinates":[11.3758935928,47.2589454651],"type":"Point"}
}