{
  "type": "Feature",
  "properties": {
    "iso:country":"AT",
    "sg:address":"Nr 200",
    "sg:city":"Stubenberg am See",
    "sg:orig_category":"Betonbohr- U -Schneidedienst",
    "sg:phone":"+43 4331 7620089",
    "sg:postcode":"8223",
    "sg:province":"Steiermark",
    "wof:name":"Hirberger Peter",
    "wof:placetype":"venue"
},
  "geometry": {"coordinates":[15.8004598618,47.243724823],"type":"Point"}
}