{
  "type": "Feature",
  "properties": {
    "iso:country":"AT",
    "sg:address":"Nr 17",
    "sg:city":"Ottnang am Hausruck",
    "sg:orig_category":"Tankstellen",
    "sg:phone":"+43 76767424",
    "sg:postcode":"4901",
    "sg:province":"Ober\u00f6sterreich",
    "wof:name":"AVIA Tankstelle",
    "wof:placetype":"venue"
},
  "geometry": {"coordinates":[7.7895898819,47.2121009827],"type":"Point"}
}