{
  "type": "Feature",
  "properties": {
    "iso:country":"AT",
    "sg:address":"Stadtpl 12-14",
    "sg:city":"Wels",
    "sg:orig_category":"Apotheken",
    "sg:phone":"+43 7242 49016",
    "sg:postcode":"4600",
    "sg:province":"Ober\u00f6sterreich",
    "wof:name":"Adler Apotheke",
    "wof:placetype":"venue"
},
  "geometry": {"coordinates":[14.0260343552,48.1571464539],"type":"Point"}
}