{
  "type": "Feature",
  "properties": {
    "addr:full":"Kaiserweg 115 Going am Wilden Kaiser Tirol 6353",
    "addr:housenumber":"115",
    "addr:postcode":"6353",
    "addr:street":"Kaiserweg;Tirol",
    "iso:country":"AT",
    "sg:address":"Kaiserweg 115",
    "sg:city":"Going am Wilden Kaiser",
    "sg:orig_category":"Pensionen / Privatzimmer",
    "sg:phone":"+43 4353 582448",
    "sg:postcode":"6353",
    "sg:province":"Tirol",
    "wof:name":"Pension Glasererhof",
    "wof:placetype":"venue"
},
  "geometry": {"coordinates":[12.3368663788,47.5225219727],"type":"Point"}
}