{
  "type": "Feature",
  "properties": {
    "addr:full":"Birkeng 33 Leopoldsdorf Nieder\u00f6sterreich 2333",
    "addr:housenumber":"33",
    "addr:postcode":"2333",
    "addr:street":"Birkeng",
    "iso:country":"AT",
    "sg:address":"Birkeng 33",
    "sg:city":"Leopoldsdorf",
    "sg:orig_category":"Steuerberatung",
    "sg:phone":"+43 4322 3543615",
    "sg:postcode":"2333",
    "sg:province":"Nieder\u00f6sterreich",
    "wof:name":"Habicher Herbert Mag",
    "wof:placetype":"venue"
},
  "geometry": {"coordinates":[16.395357132,48.1202087402],"type":"Point"}
}