{
  "type": "Feature",
  "properties": {
    "addr:full":"Klagenfurter Str 545 Bad St. Leonhard im Lavanttal K\u00e4rnten 9462",
    "addr:housenumber":"545",
    "addr:postcode":"9462",
    "iso:country":"AT",
    "sg:address":"Klagenfurter Str 545",
    "sg:city":"Bad St. Leonhard im Lavanttal",
    "sg:orig_category":"Installationsunternehmen",
    "sg:phone":"+43 4343 5035240",
    "sg:postcode":"9462",
    "sg:province":"K\u00e4rnten",
    "wof:name":"Pletz Installationstechnik GmbH,",
    "wof:placetype":"venue"
},
  "geometry": {"coordinates":[14.7983703613,46.9574890137],"type":"Point"}
}