{
  "type": "Feature",
  "properties": {
    "addr:full":"Weinbergg 47 Wien Wien 1190",
    "addr:housenumber":"47",
    "addr:postcode":"1190",
    "addr:street":"Weinbergg",
    "iso:country":"AT",
    "sg:address":"Weinbergg 47",
    "sg:city":"Wien",
    "sg:orig_category":"Friseure U Frisiersalons",
    "sg:phone":"+43 1 3684792",
    "sg:postcode":"1190",
    "sg:province":"Wien",
    "wof:name":"Orth Elfriede",
    "wof:placetype":"venue"
},
  "geometry": {"coordinates":[16.33452034,48.2433395386],"type":"Point"}
}