{
  "type": "Feature",
  "properties": {
    "addr:full":"Auggenthal 158 Haugsdorf Nieder\u00f6sterreich 2054",
    "addr:housenumber":"158",
    "addr:postcode":"2054",
    "addr:street":"Auggenthal",
    "iso:country":"AT",
    "sg:address":"Auggenthal 158",
    "sg:city":"Haugsdorf",
    "sg:classifiers":[
        {
            "category":"Banks & Credit Unions",
            "subcategory":"Financial Services",
            "type":"Services"
        }
    ],
    "sg:phone":"+43 2944 26250",
    "sg:postcode":"2054",
    "sg:province":"Nieder\u00f6sterreich",
    "sg:tags":[
        "fork",
        "lift",
        "truck",
        "tyre"
    ],
    "sg:website":"tiptop.at",
    "wof:name":"Tip-Top A. S. International Ameuro-Group",
    "wof:placetype":"venue"
},
  "geometry": {"coordinates":[16.0652236938,48.7221450806],"type":"Point"}
}