{
  "type": "Feature",
  "properties": {
    "addr:full":"Meidlinger Markt 9-12 Wien Wien 1120",
    "addr:housenumber":"9-12",
    "addr:postcode":"1120",
    "addr:street":"Meidlinger Markt",
    "iso:country":"AT",
    "sg:address":"Meidlinger Markt 9-12",
    "sg:city":"Wien",
    "sg:orig_category":"Feinkost",
    "sg:phone":"+43 1 8124019",
    "sg:postcode":"1120",
    "sg:province":"Wien",
    "wof:name":"Araxi WarenhandelsgesmbH",
    "wof:placetype":"venue"
},
  "geometry": {"coordinates":[16.3467445374,48.1800994873],"type":"Point"}
}