{
  "type": "Feature",
  "properties": {
    "addr:full":"Redtenbacherg 25 Steyr Ober\u00f6sterreich 4400",
    "addr:housenumber":"25",
    "addr:postcode":"4400",
    "addr:street":"Redtenbacherg;Oberoesterreich",
    "iso:country":"AT",
    "sg:address":"Redtenbacherg 25",
    "sg:city":"Steyr",
    "sg:orig_category":"Maler, Anstreicher U Lackierer",
    "sg:phone":"+43 4372 5251171",
    "sg:postcode":"4400",
    "sg:province":"Ober\u00f6sterreich",
    "wof:name":"ARTA - Die Marke im Handwerk - Maler B\u00f6hm & Kornberger",
    "wof:placetype":"venue"
},
  "geometry": {"coordinates":[14.4064359665,48.0390319824],"type":"Point"}
}