{
  "type": "Feature",
  "properties": {
    "iso:country":"AT",
    "sg:address":"Franz Peyerl-Str 13/6",
    "sg:city":"Salzburg",
    "sg:orig_category":"Psychotherapie",
    "sg:phone":"+43 662 456911",
    "sg:postcode":"5020",
    "sg:province":"Salzburg",
    "wof:name":"Gr\u00fcner Regina Mag",
    "wof:placetype":"venue"
},
  "geometry": {"coordinates":[13.0301704407,47.7907905579],"type":"Point"}
}