{
  "type": "Feature",
  "properties": {
    "iso:country":"AT",
    "sg:address":"Pater-Bernhard-Rodlberger-Str 12",
    "sg:city":"Wels",
    "sg:orig_category":"\u00c3\u201erzte / F Allgemeinmedizin",
    "sg:phone":"+43 4372 4261311",
    "sg:postcode":"4600",
    "sg:province":"Ober\u00f6sterreich",
    "wof:name":"Scharinger Rudolf Dr",
    "wof:placetype":"venue"
},
  "geometry": {"coordinates":[14.0291795731,48.1528930664],"type":"Point"}
}