{
  "type": "Feature",
  "properties": {
    "addr:full":"Schulg 63 Lanzenkirchen Nieder\u00f6sterreich 2821",
    "addr:housenumber":"63",
    "addr:postcode":"2821",
    "addr:street":"Schulg",
    "iso:country":"AT",
    "sg:address":"Schulg 63",
    "sg:city":"Lanzenkirchen",
    "sg:orig_category":"Gemeinden",
    "sg:phone":"+43 2627 454320",
    "sg:postcode":"2821",
    "sg:province":"Nieder\u00f6sterreich",
    "wof:name":"Gemeindeamt Lanzenkirchen",
    "wof:placetype":"venue"
},
  "geometry": {"coordinates":[16.2382774353,47.7442855835],"type":"Point"}
}