{
  "type": "Feature",
  "properties": {
    "addr:full":"Hauptpl 159 Neudorf Nieder\u00f6sterreich 2135",
    "addr:housenumber":"159",
    "addr:postcode":"2135",
    "iso:country":"AT",
    "sg:address":"Hauptpl 159",
    "sg:city":"Neudorf",
    "sg:orig_category":"Banken U Sparkassen",
    "sg:phone":"+43 4325 238200",
    "sg:postcode":"2135",
    "sg:province":"Nieder\u00f6sterreich",
    "wof:name":"Raiffeisen-Bezirksbank Laa an der Thaya regGenmbH",
    "wof:placetype":"venue"
},
  "geometry": {"coordinates":[16.4915943146,48.7205314636],"type":"Point"}
}