{
  "type": "Feature",
  "properties": {
    "iso:country":"AT",
    "sg:address":"Untertweng Bundesstr 13",
    "sg:city":"Radenthein",
    "sg:orig_category":"Installationsunternehmen",
    "sg:phone":"+43 4246 4320",
    "sg:postcode":"9545",
    "sg:province":"K\u00e4rnten",
    "wof:name":"Steinwender Bernhard",
    "wof:placetype":"venue"
},
  "geometry": {"coordinates":[13.7050790787,46.8011779785],"type":"Point"}
}