{
  "type": "Feature",
  "properties": {
    "addr:full":"Prantlweg 15a Inzing Tirol 6401",
    "addr:housenumber":"15a",
    "addr:postcode":"6401",
    "addr:street":"Prantlweg;Tirol",
    "iso:country":"AT",
    "sg:address":"Prantlweg 15a",
    "sg:city":"Inzing",
    "sg:orig_category":"Ingenieurkonsulenten / Zivilingenieure",
    "sg:phone":"+43 5238 86466",
    "sg:postcode":"6401",
    "sg:province":"Tirol",
    "wof:name":"Fleisch Bernadette Dipl-Ing",
    "wof:placetype":"venue"
},
  "geometry": {"coordinates":[11.191119194,47.2710914612],"type":"Point"}
}