{
  "type": "Feature",
  "properties": {
    "addr:full":"Neilreichgasse 113  Wien Wien 1100",
    "addr:housenumber":"113",
    "addr:postcode":"1100",
    "addr:street":"Neilreichgasse",
    "iso:country":"AT",
    "sg:address":"Neilreichgasse 113 ",
    "sg:city":"Wien",
    "sg:classifiers":[
        {
            "category":"Government",
            "subcategory":"Fire Station",
            "type":"Public Place"
        }
    ],
    "sg:phone":"+43 1 6151491",
    "sg:postcode":"1100",
    "sg:province":"Wien",
    "sg:tags":[
        "supraregional",
        "plant",
        "installation",
        "heating"
    ],
    "sg:website":"members.aon.at/energy/magnetfeld.htm",
    "wof:name":"Ing. Werner Mitterb\u00f6ck Solarsysteme",
    "wof:placetype":"venue"
},
  "geometry": {"coordinates":[16.3617706299,48.1608657837],"type":"Point"}
}