{
  "type": "Feature",
  "properties": {
    "addr:full":"Veichter 13 Hagenberg im M\u00fchlkreis Ober\u00f6sterreich 4232",
    "addr:housenumber":"13",
    "addr:postcode":"4232",
    "addr:street":"Veichter;Im Muehlkreis Oberoesterreich",
    "iso:country":"AT",
    "sg:address":"Veichter 13",
    "sg:city":"Hagenberg im M\u00fchlkreis",
    "sg:orig_category":"Tischlereien",
    "sg:phone":"+43 4372 362515",
    "sg:postcode":"4232",
    "sg:province":"Ober\u00f6sterreich",
    "wof:name":"Datl Karl - Tischlerei - Wasserbetten",
    "wof:placetype":"venue"
},
  "geometry": {"coordinates":[14.5217189789,48.3750114441],"type":"Point"}
}