{
  "type": "Feature",
  "properties": {
    "addr:full":"Grazer Str 18 Kindberg Steiermark 8650",
    "addr:postcode":"8650",
    "addr:street":"Str 18",
    "iso:country":"AT",
    "sg:address":"Grazer Str 18",
    "sg:city":"Kindberg",
    "sg:orig_category":"Maler, Anstreicher U Lackierer",
    "sg:phone":"+43 4366 41059740",
    "sg:postcode":"8650",
    "sg:province":"Steiermark",
    "wof:name":"Hoch\u00f6rtler G\u00fcnther",
    "wof:placetype":"venue"
},
  "geometry": {"coordinates":[15.441614151,47.5040245056],"type":"Point"}
}