{
  "type": "Feature",
  "properties": {
    "addr:full":"Marktpl 25 Kirchberg am Wagram Nieder\u00f6sterreich 3470",
    "addr:housenumber":"25",
    "addr:postcode":"3470",
    "addr:street":"Marktpl",
    "iso:country":"AT",
    "sg:address":"Marktpl 25",
    "sg:city":"Kirchberg am Wagram",
    "sg:orig_category":"\u00c3\u201erzte / F Allgemeinmedizin",
    "sg:phone":"+43 2279 23500",
    "sg:postcode":"3470",
    "sg:province":"Nieder\u00f6sterreich",
    "wof:name":"Schober Norbert Dr",
    "wof:placetype":"venue"
},
  "geometry": {"coordinates":[15.89752388,48.4345932007],"type":"Point"}
}