{
  "type": "Feature",
  "properties": {
    "addr:full":"Nr 48 Stuben Vorarlberg 6762",
    "addr:postcode":"6762",
    "addr:street":"Nr;Stuben",
    "iso:country":"AT",
    "sg:address":"Nr 48",
    "sg:city":"Stuben",
    "sg:classifiers":[
        {
            "category":"Travel",
            "subcategory":"Hotels & Motels",
            "type":"Entertainment"
        }
    ],
    "sg:phone":"+43 4355 82771",
    "sg:postcode":"6762",
    "sg:province":"Vorarlberg",
    "sg:website":"hubihof.at",
    "wof:name":"Hubertushof - Familien und Seminarhotel",
    "wof:placetype":"venue"
},
  "geometry": {"coordinates":[10.1580495834,47.1391792297],"type":"Point"}
}