{
  "type": "Feature",
  "properties": {
    "addr:full":"Grazer Str 17 Bad Ischl Ober\u00f6sterreich 4820",
    "addr:housenumber":"17",
    "addr:postcode":"4820",
    "addr:street":"Str",
    "iso:country":"AT",
    "sg:address":"Grazer Str 17",
    "sg:city":"Bad Ischl",
    "sg:orig_category":"Immobilienmakler",
    "sg:phone":"+43 6132 265250",
    "sg:postcode":"4820",
    "sg:province":"Ober\u00f6sterreich",
    "wof:name":"Immobilien Ritzinger",
    "wof:placetype":"venue"
},
  "geometry": {"coordinates":[13.6231241226,47.709148407],"type":"Point"}
}