{
  "type": "Feature",
  "properties": {
    "addr:full":"Nordwestbahnstr 75 Wien Wien 1200",
    "addr:housenumber":"75",
    "addr:postcode":"1200",
    "addr:street":"Nordwestbahnstr",
    "iso:country":"AT",
    "sg:address":"Nordwestbahnstr 75",
    "sg:city":"Wien",
    "sg:orig_category":"Installationsunternehmen",
    "sg:phone":"+43 4313 329046",
    "sg:postcode":"1200",
    "sg:province":"Wien",
    "sg:website":"pausmagyar.at",
    "wof:name":"Magyar Paul Bauspenglerei",
    "wof:placetype":"venue"
},
  "geometry": {"coordinates":[16.3775691986,48.2321586609],"type":"Point"}
}