{
  "type": "Feature",
  "properties": {
    "addr:full":"Rechte Wienzeile 9a Wien Wien 1040",
    "addr:housenumber":"9a",
    "addr:postcode":"1040",
    "addr:street":"Rechte Wienzeile",
    "iso:country":"AT",
    "sg:address":"Rechte Wienzeile 9a",
    "sg:city":"Wien",
    "sg:orig_category":"Psychologen",
    "sg:phone":"+43 1 58525553",
    "sg:postcode":"1040",
    "sg:province":"Wien",
    "wof:name":"Haag Beatrix Dr",
    "wof:placetype":"venue"
},
  "geometry": {"coordinates":[16.364900589,48.1988792419],"type":"Point"}
}