{
  "type": "Feature",
  "properties": {
    "iso:country":"AT",
    "sg:address":"Nr 15",
    "sg:city":"Aschau",
    "sg:orig_category":"Fleischhauereien",
    "sg:phone":"+43 5282 2906",
    "sg:postcode":"6274",
    "sg:province":"Tirol",
    "wof:name":"Gasser Walter",
    "wof:placetype":"venue"
},
  "geometry": {"coordinates":[11.8959445953,47.2627754211],"type":"Point"}
}