{
  "type": "Feature",
  "properties": {
    "addr:full":"Krottenseestr 45Top35 Gmunden Ober\u00f6sterreich 4810",
    "addr:postcode":"4810",
    "addr:street":"Oberoesterreich",
    "iso:country":"AT",
    "sg:address":"Krottenseestr 45Top35",
    "sg:city":"Gmunden",
    "sg:orig_category":"Cad/Cae/Cam/Cim-Systeme",
    "sg:phone":"+43 761290032401",
    "sg:postcode":"4810",
    "sg:province":"Ober\u00f6sterreich",
    "wof:name":"CAD/Cam Walter Schwarz",
    "wof:placetype":"venue"
},
  "geometry": {"coordinates":[13.8145132065,47.9281044006],"type":"Point"}
}