{
  "type": "Feature",
  "properties": {
    "addr:full":"Harter Str 8 Gratkorn Steiermark 8101",
    "addr:housenumber":"8",
    "addr:postcode":"8101",
    "addr:street":"Str",
    "iso:country":"AT",
    "sg:address":"Harter Str 8",
    "sg:city":"Gratkorn",
    "sg:orig_category":"Tankstellen",
    "sg:phone":"+43 3124 290291",
    "sg:postcode":"8101",
    "sg:province":"Steiermark",
    "wof:name":"BP Austria Marketing GmbH",
    "wof:placetype":"venue"
},
  "geometry": {"coordinates":[15.3592224121,47.1220550537],"type":"Point"}
}