{
  "type": "Feature",
  "properties": {
    "addr:full":"Bahnhofstr 12 Kindberg Steiermark 8650",
    "addr:housenumber":"12",
    "addr:postcode":"8650",
    "addr:street":"Bahnhofstr",
    "iso:country":"AT",
    "sg:address":"Bahnhofstr 12",
    "sg:city":"Kindberg",
    "sg:orig_category":"Banken U Sparkassen",
    "sg:phone":"+43 4338 6531200",
    "sg:postcode":"8650",
    "sg:province":"Steiermark",
    "wof:name":"Bankomat Raiffeisenbank Kindberg-Stadt Bankst d Raiffeisenbank Mittleres M\u00fcrztal regGenmbH",
    "wof:placetype":"venue"
},
  "geometry": {"coordinates":[15.4452924728,47.50258255],"type":"Point"}
}