{
  "type": "Feature",
  "properties": {
    "addr:full":"Ringstr 402/TopII/4u5 Bad Gleichenberg Steiermark 8344",
    "addr:housenumber":"402",
    "addr:postcode":"8344",
    "iso:country":"AT",
    "sg:address":"Ringstr 402/TopII/4u5",
    "sg:city":"Bad Gleichenberg",
    "sg:orig_category":"Bastelbedarf",
    "sg:phone":"+43 3159 45578",
    "sg:postcode":"8344",
    "sg:province":"Steiermark",
    "wof:name":"Schadler GmbH",
    "wof:placetype":"venue"
},
  "geometry": {"coordinates":[15.9038906097,46.8549499512],"type":"Point"}
}