{
  "type": "Feature",
  "properties": {
    "addr:full":"Unterer Kirchweg 7 Dornbirn Vorarlberg 6850",
    "addr:housenumber":"7",
    "addr:postcode":"6850",
    "addr:street":"Unterer Kirchweg",
    "iso:country":"AT",
    "sg:address":"Unterer Kirchweg 7",
    "sg:city":"Dornbirn",
    "sg:orig_category":"Zeitungen U Zeitschriften",
    "sg:phone":"+43 4355 7221250",
    "sg:postcode":"6850",
    "sg:province":"Vorarlberg",
    "wof:name":"Dornbirner Pfarrblatt",
    "wof:placetype":"venue"
},
  "geometry": {"coordinates":[9.7402486801,47.4022712708],"type":"Point"}
}