{
  "type": "Feature",
  "properties": {
    "addr:full":"Niedergleinker Str 18 Gleink Ober\u00f6sterreich 4407",
    "addr:housenumber":"18",
    "addr:postcode":"4407",
    "addr:street":"Str",
    "iso:country":"AT",
    "sg:address":"Niedergleinker Str 18",
    "sg:city":"Gleink",
    "sg:orig_category":"Spenglereien",
    "sg:phone":"+43 7252 81955",
    "sg:postcode":"4407",
    "sg:province":"Ober\u00f6sterreich",
    "wof:name":"Eder Hubert",
    "wof:placetype":"venue"
},
  "geometry": {"coordinates":[14.4131603241,48.0867958069],"type":"Point"}
}