{
  "type": "Feature",
  "properties": {
    "addr:full":"Rathauspl 9 Kremsm\u00fcnster Ober\u00f6sterreich 4550",
    "addr:housenumber":"9",
    "addr:postcode":"4550",
    "addr:street":"Rathauspl;Oberoesterreich",
    "iso:country":"AT",
    "sg:address":"Rathauspl 9",
    "sg:city":"Kremsm\u00fcnster",
    "sg:orig_category":"Banken U Sparkassen",
    "sg:phone":"+43 7583 72660",
    "sg:postcode":"4550",
    "sg:province":"Ober\u00f6sterreich",
    "wof:name":"Sparkasse Kremstal-Pyhrn AG",
    "wof:placetype":"venue"
},
  "geometry": {"coordinates":[14.1284265518,48.0530090332],"type":"Point"}
}