{
  "type": "Feature",
  "properties": {
    "addr:full":"Vogelweidpl 3 Wien Wien 1150",
    "addr:housenumber":"3",
    "addr:postcode":"1150",
    "addr:street":"Vogelweidpl",
    "iso:country":"AT",
    "sg:address":"Vogelweidpl 3",
    "sg:city":"Wien",
    "sg:orig_category":"Installationsunternehmen",
    "sg:phone":"+43 1 9826114",
    "sg:postcode":"1150",
    "sg:province":"Wien",
    "wof:name":"Stanicky Eduard",
    "wof:placetype":"venue"
},
  "geometry": {"coordinates":[16.3313159943,48.2012672424],"type":"Point"}
}