{
  "type": "Feature",
  "properties": {
    "iso:country":"AT",
    "sg:address":"Radlpa\u00dfstrasse 7",
    "sg:city":"Lannach",
    "sg:classifiers":[
        {
            "category":"Manufacturing",
            "subcategory":"Tools & Machinery",
            "type":"Manufacturing & Wholesale Goods"
        }
    ],
    "sg:phone":"+43 3136 821310",
    "sg:postcode":"8502",
    "sg:province":"Steiermark",
    "sg:tags":[
        "machining",
        "cnc"
    ],
    "sg:website":"hinkel.at",
    "wof:name":"Hinkel Anlagen und Maschinenbau Ges.m.b.H.",
    "wof:placetype":"venue"
},
  "geometry": {"coordinates":[15.3429498672,46.9536094666],"type":"Point"}
}