{
  "type": "Feature",
  "properties": {
    "addr:full":"Schmiedg 40/2 Graz Steiermark 8010",
    "addr:housenumber":"40 / 2",
    "addr:postcode":"8010",
    "addr:street":"Schmiedg",
    "iso:country":"AT",
    "sg:address":"Schmiedg 40/2",
    "sg:city":"Graz",
    "sg:orig_category":"Non-Classified Establishments",
    "sg:phone":"+43 316 813888",
    "sg:postcode":"8010",
    "sg:province":"Steiermark",
    "wof:name":"SINOplex HandelsgesmbH",
    "wof:placetype":"venue"
},
  "geometry": {"coordinates":[15.4403047562,47.0670623779],"type":"Point"}
}