{
  "type": "Feature",
  "properties": {
    "addr:full":"Taborstr 38 Wien Wien 1020",
    "addr:postcode":"1020",
    "iso:country":"AT",
    "sg:address":"Taborstr 38",
    "sg:city":"Wien",
    "sg:orig_category":"Tanzcafes",
    "sg:phone":"+43 1 2163701",
    "sg:postcode":"1020",
    "sg:province":"Wien",
    "wof:name":"Bricks - Gottfried Pertot",
    "wof:placetype":"venue"
},
  "geometry": {"coordinates":[16.3809528351,48.2186813354],"type":"Point"}
}