{
  "type": "Feature",
  "properties": {
    "addr:full":"Mandarfen 23 St. Leonhard im Pitztal Tirol 6481",
    "addr:housenumber":"23",
    "addr:postcode":"6481",
    "addr:street":"Mandarfen;Tirol",
    "iso:country":"AT",
    "sg:address":"Mandarfen 23",
    "sg:city":"St. Leonhard im Pitztal",
    "sg:orig_category":"Lebensmittel / Einzelhandel",
    "sg:phone":"+43 4354 138621413",
    "sg:postcode":"6481",
    "sg:province":"Tirol",
    "wof:name":"ADEG Mandarfen",
    "wof:placetype":"venue"
},
  "geometry": {"coordinates":[10.8719778061,46.9653015137],"type":"Point"}
}