{
  "type": "Feature",
  "properties": {
    "addr:full":"Bahnstr 41 Mattersburg Burgenland 7210",
    "addr:housenumber":"41",
    "addr:postcode":"7210",
    "addr:street":"Bahnstr",
    "iso:country":"AT",
    "sg:address":"Bahnstr 41",
    "sg:city":"Mattersburg",
    "sg:orig_category":"Berufsschulen",
    "sg:phone":"+43 2626 62275",
    "sg:postcode":"7210",
    "sg:province":"Burgenland",
    "wof:name":"Berufsschule",
    "wof:placetype":"venue"
},
  "geometry": {"coordinates":[16.4045543671,47.736995697],"type":"Point"}
}