{
  "type": "Feature",
  "properties": {
    "addr:full":"Madstein 1 St. Michael in Obersteiermark Steiermark 8770",
    "addr:housenumber":"1",
    "addr:postcode":"8770",
    "addr:street":"Madstein",
    "iso:country":"AT",
    "sg:address":"Madstein 1",
    "sg:city":"St. Michael in Obersteiermark",
    "sg:orig_category":"Paketdienste",
    "sg:phone":"+43 3843 93000430",
    "sg:postcode":"8770",
    "sg:province":"Steiermark",
    "wof:name":"\u00f6BB-G\u00fcterverkehr - Rail Cargo Austria",
    "wof:placetype":"venue"
},
  "geometry": {"coordinates":[15.007976532,47.3519058228],"type":"Point"}
}