{
  "type": "Feature",
  "properties": {
    "addr:full":"Nr 13 Ravelsbach Nieder\u00f6sterreich 3720",
    "addr:postcode":"3720",
    "addr:street":"Nr;Niederoesterreich",
    "iso:country":"AT",
    "sg:address":"Nr 13",
    "sg:city":"Ravelsbach",
    "sg:orig_category":"Lebens- U Sozialberatung",
    "sg:phone":"+43 2958 8607",
    "sg:postcode":"3720",
    "sg:province":"Nieder\u00f6sterreich",
    "wof:name":"TABEA - Hof f Kinder und Tiere",
    "wof:placetype":"venue"
},
  "geometry": {"coordinates":[15.8505048752,48.5516395569],"type":"Point"}
}