{
  "type": "Feature",
  "properties": {
    "addr:full":"Eben 1a Gro\u00dfarl Salzburg 5611",
    "addr:housenumber":"1a",
    "addr:postcode":"5611",
    "addr:street":"Eben;Salzburg",
    "iso:country":"AT",
    "sg:address":"Eben 1a",
    "sg:city":"Gro\u00dfarl",
    "sg:orig_category":"Rauchfangkehrer",
    "sg:phone":"+43 6414 8263",
    "sg:postcode":"5611",
    "sg:province":"Salzburg",
    "wof:name":"Schartner Norbert",
    "wof:placetype":"venue"
},
  "geometry": {"coordinates":[13.20291996,47.2038116455],"type":"Point"}
}