{
  "type": "Feature",
  "properties": {
    "addr:full":"Bahnstr 8 Haslach an der M\u00fchl Ober\u00f6sterreich 4170",
    "addr:housenumber":"8",
    "addr:postcode":"4170",
    "addr:street":"Bahnstr;Oberoesterreich",
    "iso:country":"AT",
    "sg:address":"Bahnstr 8",
    "sg:city":"Haslach an der M\u00fchl",
    "sg:orig_category":"Bestattungsunternehmen",
    "sg:phone":"+43 7289 71390",
    "sg:postcode":"4170",
    "sg:province":"Ober\u00f6sterreich",
    "wof:name":"Wakolbinger Emil",
    "wof:placetype":"venue"
},
  "geometry": {"coordinates":[14.0358104706,48.5758857727],"type":"Point"}
}