{
  "type": "Feature",
  "properties": {
    "iso:country":"AT",
    "sg:address":"Reitdorf 167",
    "sg:city":"Flachau",
    "sg:classifiers":[
        {
            "category":"Manufacturing",
            "subcategory":"Furniture",
            "type":"Manufacturing & Wholesale Goods"
        }
    ],
    "sg:phone":"+43 6452 4803",
    "sg:postcode":"5542",
    "sg:province":"Salzburg",
    "sg:tags":[
        "design"
    ],
    "sg:website":"a-buchsteiner.at",
    "wof:name":"Alois Buchsteiner",
    "wof:placetype":"venue"
},
  "geometry": {"coordinates":[13.3865442276,47.3692092896],"type":"Point"}
}