{
  "type": "Feature",
  "properties": {
    "addr:full":"Obstgarten 23 Zurndorf Burgenland 2424",
    "addr:housenumber":"23",
    "addr:postcode":"2424",
    "addr:street":"Obstgarten",
    "iso:country":"AT",
    "sg:address":"Obstgarten 23",
    "sg:city":"Zurndorf",
    "sg:orig_category":"Maler, Anstreicher U Lackierer",
    "sg:phone":"+43 4321 472267",
    "sg:postcode":"2424",
    "sg:province":"Burgenland",
    "wof:name":"Horvath Josef",
    "wof:placetype":"venue"
},
  "geometry": {"coordinates":[17.0118026733,47.9858970642],"type":"Point"}
}