{
  "type": "Feature",
  "properties": {
    "iso:country":"AT",
    "sg:address":"Wipflerbergstr 1",
    "sg:city":"Linz",
    "sg:orig_category":"Abfallentsorgung U -Verwertung",
    "sg:phone":"+43 4372 3920141",
    "sg:postcode":"4040",
    "sg:province":"Ober\u00f6sterreich",
    "wof:name":"Altstoffsammelzentrum",
    "wof:placetype":"venue"
},
  "geometry": {"coordinates":[14.3393220901,48.3345298767],"type":"Point"}
}