{
  "type": "Feature",
  "properties": {
    "addr:full":"Johann-Thys-Zeile 2 Klagenfurt K\u00e4rnten 9020",
    "addr:housenumber":"2",
    "addr:postcode":"9020",
    "addr:street":"Johann-Thys-Zeile;Kaernten",
    "iso:country":"AT",
    "sg:address":"Johann-Thys-Zeile 2",
    "sg:city":"Klagenfurt",
    "sg:classifiers":[
        {
            "category":"Shopping",
            "subcategory":"Party Supplies",
            "type":"Retail Goods"
        }
    ],
    "sg:phone":"+43 4366 41817841",
    "sg:postcode":"9020",
    "sg:province":"K\u00e4rnten",
    "sg:tags":[
        "u",
        "lichtanlagen",
        "ton-"
    ],
    "wof:name":"Two 4 You - Event & Multimediatechnik",
    "wof:placetype":"venue"
},
  "geometry": {"coordinates":[14.3171930313,46.630607605],"type":"Point"}
}