{
  "type": "Feature",
  "properties": {
    "addr:full":"Fischbacher Str 5 Birkfeld Steiermark 8190",
    "addr:housenumber":"5",
    "addr:postcode":"8190",
    "addr:street":"Fischbacher Str",
    "iso:country":"AT",
    "sg:address":"Fischbacher Str 5",
    "sg:city":"Birkfeld",
    "sg:orig_category":"Autohandel",
    "sg:phone":"+43 3174 46320",
    "sg:postcode":"8190",
    "sg:province":"Steiermark",
    "wof:name":"Auto Gr\u00fcnanger GmbH & Co KG",
    "wof:placetype":"venue"
},
  "geometry": {"coordinates":[15.6890878677,47.3587875366],"type":"Point"}
}