{
  "type": "Feature",
  "properties": {
    "addr:full":"Krefftstr 3  Loosdorf Nieder\u00f6sterreich 3382",
    "addr:housenumber":"3",
    "addr:postcode":"3382",
    "addr:street":"Krefftstr",
    "iso:country":"AT",
    "sg:address":"Krefftstr 3 ",
    "sg:city":"Loosdorf",
    "sg:classifiers":[
        {
            "category":"Parking",
            "subcategory":"Lot",
            "type":"Transportation"
        }
    ],
    "sg:phone":"+43 4327 5462250",
    "sg:postcode":"3382",
    "sg:province":"Nieder\u00f6sterreich",
    "sg:tags":[
        "transport",
        "road"
    ],
    "wof:name":"ALOIS MAIERHOFER GMBH",
    "wof:placetype":"venue"
},
  "geometry": {"coordinates":[15.4111604691,48.1970710754],"type":"Point"}
}