{
  "type": "Feature",
  "properties": {
    "addr:full":"Gustererg 19A Wien Wien 1140",
    "addr:housenumber":"19a",
    "addr:postcode":"1140",
    "addr:street":"Gustererg",
    "iso:country":"AT",
    "sg:address":"Gustererg 19A",
    "sg:city":"Wien",
    "sg:orig_category":"Fotografen",
    "sg:phone":"+43 1 9115798",
    "sg:postcode":"1140",
    "sg:province":"Wien",
    "wof:name":"Vogel Klaus - Reprofotograf",
    "wof:placetype":"venue"
},
  "geometry": {"coordinates":[16.2881069183,48.2042961121],"type":"Point"}
}