{
  "type": "Feature",
  "properties": {
    "addr:full":"Birkenstrasse 2 Hallwang Salzburg 5300",
    "addr:housenumber":"2",
    "addr:postcode":"5300",
    "addr:street":"Birkenstrasse;Salzburg",
    "iso:country":"AT",
    "sg:address":"Birkenstrasse 2",
    "sg:city":"Hallwang",
    "sg:classifiers":[
        {
            "category":"Organizations",
            "subcategory":"Professional Association",
            "type":"Services"
        }
    ],
    "sg:phone":"+43 662 66860",
    "sg:postcode":"5300",
    "sg:province":"Salzburg",
    "sg:tags":[
        "call"
    ],
    "sg:website":"bitoffice.at",
    "wof:name":"b.it B\u00fcroservice-Center",
    "wof:placetype":"venue"
},
  "geometry": {"coordinates":[13.0838956833,47.8324584961],"type":"Point"}
}