{
  "type": "Feature",
  "properties": {
    "addr:full":"Rebenweg 19 Stra\u00dfgang Steiermark 8054",
    "addr:housenumber":"19",
    "addr:postcode":"8054",
    "addr:street":"Rebenweg",
    "iso:country":"AT",
    "sg:address":"Rebenweg 19",
    "sg:city":"Stra\u00dfgang",
    "sg:orig_category":"Personalberatung",
    "sg:phone":"+43 4366 41422592",
    "sg:postcode":"8054",
    "sg:province":"Steiermark",
    "wof:name":"Arcus Personalberatungs & Service GmbH",
    "wof:placetype":"venue"
},
  "geometry": {"coordinates":[15.3868713379,47.0132293701],"type":"Point"}
}