{
  "type": "Feature",
  "properties": {
    "addr:full":"Industriestr 23 Zwettl Nieder\u00f6sterreich 3910",
    "addr:housenumber":"23",
    "addr:postcode":"3910",
    "addr:street":"Industriestr;Niederoesterreich",
    "iso:country":"AT",
    "sg:address":"Industriestr 23",
    "sg:city":"Zwettl",
    "sg:orig_category":"Drogerien",
    "sg:phone":"+43 2822 51707",
    "sg:postcode":"3910",
    "sg:province":"Nieder\u00f6sterreich",
    "wof:name":"dm drogerie markt GmbH",
    "wof:placetype":"venue"
},
  "geometry": {"coordinates":[15.190779686,48.6002082825],"type":"Point"}
}