{
  "type": "Feature",
  "properties": {
    "addr:full":"Wilhering Ober\u00f6sterreich 4073",
    "addr:postcode":"4073",
    "addr:street":"Oberoesterreich",
    "iso:country":"AT",
    "sg:city":"Wilhering",
    "sg:orig_category":"Feuerwehren",
    "sg:phone":"+43 7226 2135",
    "sg:postcode":"4073",
    "sg:province":"Ober\u00f6sterreich",
    "wof:name":"Freiwillige Feuerwehr Edramsberg",
    "wof:placetype":"venue"
},
  "geometry": {"coordinates":[14.1722249985,48.3119354248],"type":"Point"}
}