{
  "type": "Feature",
  "properties": {
    "iso:country":"AT",
    "sg:address":"Obermarkt 43",
    "sg:city":"Telfs",
    "sg:orig_category":"Musikunterricht",
    "sg:phone":"+43 5262 621990",
    "sg:postcode":"6410",
    "sg:province":"Tirol",
    "wof:name":"Musikschule",
    "wof:placetype":"venue"
},
  "geometry": {"coordinates":[11.0665569305,47.3086967468],"type":"Point"}
}