{
  "type": "Feature",
  "properties": {
    "addr:full":"Fasangarteng 3 Wien Wien 1130",
    "addr:housenumber":"3",
    "addr:postcode":"1130",
    "addr:street":"Fasangarteng",
    "iso:country":"AT",
    "sg:address":"Fasangarteng 3",
    "sg:city":"Wien",
    "sg:orig_category":"Unterhaltungselektronik / Einzelhandel",
    "sg:phone":"+43 1 8031671",
    "sg:postcode":"1130",
    "sg:province":"Wien",
    "wof:name":"Bang & Olufsen Teuchmann",
    "wof:placetype":"venue"
},
  "geometry": {"coordinates":[16.2848701477,48.1761169434],"type":"Point"}
}