{
  "type": "Feature",
  "properties": {
    "iso:country":"AT",
    "sg:address":"Wickenburgg 3/15",
    "sg:city":"Wien",
    "sg:orig_category":"\u00c3\u201erzte / F Allgemeinmedizin",
    "sg:phone":"+43 1 4089991",
    "sg:postcode":"1080",
    "sg:province":"Wien",
    "wof:name":"Sch\u00f6n Elisabeth Dr",
    "wof:placetype":"venue"
},
  "geometry": {"coordinates":[16.3541316986,48.2119941711],"type":"Point"}
}