{
  "type": "Feature",
  "properties": {
    "iso:country":"AT",
    "sg:address":"Lobgrundstrasse 3",
    "sg:city":"Wien",
    "sg:classifiers":[
        {
            "category":"Autos & Motor Vehicles",
            "subcategory":"Fuel & Gas Station",
            "type":"Retail Goods"
        }
    ],
    "sg:phone":"+43 1 53346180",
    "sg:postcode":"1220",
    "sg:province":"Wien",
    "sg:tags":[
        "lubricant"
    ],
    "wof:name":"DEA Mineraloel Ges.m.b.H.",
    "wof:placetype":"venue"
},
  "geometry": {"coordinates":[16.5027332306,48.1747932434],"type":"Point"}
}