{
  "type": "Feature",
  "properties": {
    "addr:full":"Landstr 50 Linz Ober\u00f6sterreich 4020",
    "addr:housenumber":"50",
    "addr:postcode":"4020",
    "addr:street":"Landstr",
    "iso:country":"AT",
    "sg:address":"Landstr 50",
    "sg:city":"Linz",
    "sg:orig_category":"Friseure U Frisiersalons",
    "sg:phone":"+43 732 783910",
    "sg:postcode":"4020",
    "sg:province":"Ober\u00f6sterreich",
    "wof:name":"Coiffeur Huemer",
    "wof:placetype":"venue"
},
  "geometry": {"coordinates":[14.2907648087,48.3002090454],"type":"Point"}
}