{
  "type": "Feature",
  "properties": {
    "addr:full":"Bahnhofstr 26 Dornbirn Vorarlberg 6850",
    "addr:housenumber":"26",
    "addr:postcode":"6850",
    "addr:street":"Bahnhofstr",
    "iso:country":"AT",
    "sg:address":"Bahnhofstr 26",
    "sg:city":"Dornbirn",
    "sg:orig_category":"\u00c3\u201erzte / F Allgemeinmedizin",
    "sg:phone":"+43 664 2820424",
    "sg:postcode":"6850",
    "sg:province":"Vorarlberg",
    "wof:name":"Czuba Claudia Dr",
    "wof:placetype":"venue"
},
  "geometry": {"coordinates":[9.739443779,47.4165802002],"type":"Point"}
}