{
  "type": "Feature",
  "properties": {
    "addr:full":"Nr 32 Weyregg am Attersee Ober\u00f6sterreich 4852",
    "addr:postcode":"4852",
    "addr:street":"Nr 32",
    "iso:country":"AT",
    "sg:address":"Nr 32",
    "sg:city":"Weyregg am Attersee",
    "sg:orig_category":"Pensionen / Privatzimmer",
    "sg:phone":"+43 76642246",
    "sg:postcode":"4852",
    "sg:province":"Ober\u00f6sterreich",
    "wof:name":"Melhorn Wilhelm",
    "wof:placetype":"venue"
},
  "geometry": {"coordinates":[13.5697870255,47.9012641907],"type":"Point"}
}