{
  "type": "Feature",
  "properties": {
    "addr:full":"Dr.-Arthur-Lemisch-Str 4 V\u00f6lkermarkt K\u00e4rnten 9100",
    "addr:housenumber":"4",
    "addr:postcode":"9100",
    "addr:street":"Dr.-Arthur-Lemisch-Str;Kaernten",
    "iso:country":"AT",
    "sg:address":"Dr.-Arthur-Lemisch-Str 4",
    "sg:city":"V\u00f6lkermarkt",
    "sg:orig_category":"Raumausstattung",
    "sg:phone":"+43 4342 323875",
    "sg:postcode":"9100",
    "sg:province":"K\u00e4rnten",
    "wof:name":"Raummode Hirm",
    "wof:placetype":"venue"
},
  "geometry": {"coordinates":[9.1929798126,48.6895484924],"type":"Point"}
}