{
  "type": "Feature",
  "properties": {
    "addr:full":"Kremsegger Strasse 17  Kremsm\u00fcnster Ober\u00f6sterreich 4550",
    "addr:housenumber":"17",
    "addr:postcode":"4550",
    "addr:street":"Kremsegger Strasse;Oberoesterreich",
    "iso:country":"AT",
    "sg:address":"Kremsegger Strasse 17 ",
    "sg:city":"Kremsm\u00fcnster",
    "sg:classifiers":[
        {
            "category":"Banks & Credit Unions",
            "subcategory":"Atm",
            "type":"Services"
        }
    ],
    "sg:phone":"+43 7583 7471",
    "sg:postcode":"4550",
    "sg:province":"Ober\u00f6sterreich",
    "sg:tags":[
        "closure",
        "pack"
    ],
    "sg:website":"www.kwk.at",
    "wof:name":"Kunststoffwerk Kremsm\u00fcnster Ges.m.b.H. & Co KG",
    "wof:placetype":"venue"
},
  "geometry": {"coordinates":[7.4943199158,50.8699913025],"type":"Point"}
}