{
  "type": "Feature",
  "properties": {
    "addr:full":"Simon-Redtenbacher-Pl 14 Kirchdorf an der Krems Ober\u00f6sterreich 4560",
    "addr:housenumber":"14",
    "addr:postcode":"4560",
    "addr:street":"Simon-Redtenbacher-Pl",
    "iso:country":"AT",
    "sg:address":"Simon-Redtenbacher-Pl 14",
    "sg:city":"Kirchdorf an der Krems",
    "sg:orig_category":"Fleischhauereien",
    "sg:phone":"+43 4375 8262130",
    "sg:postcode":"4560",
    "sg:province":"Ober\u00f6sterreich",
    "wof:name":"Z\u00f6l\u00df Gerhard",
    "wof:placetype":"venue"
},
  "geometry": {"coordinates":[14.1220550537,47.906829834],"type":"Point"}
}