{
  "type": "Feature",
  "properties": {
    "addr:full":"Gewerbestrasse 10 Uttendorf Ober\u00f6sterreich 5261",
    "addr:housenumber":"10",
    "addr:postcode":"5261",
    "addr:street":"Gewerbestrasse",
    "iso:country":"AT",
    "sg:address":"Gewerbestrasse 10",
    "sg:city":"Uttendorf",
    "sg:classifiers":[
        {
            "category":"Professional",
            "type":"Services"
        }
    ],
    "sg:phone":"+43 7724 22390",
    "sg:postcode":"5261",
    "sg:province":"Ober\u00f6sterreich",
    "sg:tags":[
        "mould",
        "construction"
    ],
    "sg:website":"esterbauer.org",
    "wof:name":"Esterbauer Kunststoffverarbeitung- und Formenbau Ges.m.b.H. & Co KG",
    "wof:placetype":"venue"
},
  "geometry": {"coordinates":[13.1211032867,48.1652984619],"type":"Point"}
}