{
  "type": "Feature",
  "properties": {
    "addr:full":"Franz-Josef-Str 2 Mistelbach Nieder\u00f6sterreich 2130",
    "addr:housenumber":"2",
    "addr:postcode":"2130",
    "addr:street":"Franz-Josef-Str;Niederoesterreich",
    "iso:country":"AT",
    "sg:address":"Franz-Josef-Str 2",
    "sg:city":"Mistelbach",
    "sg:orig_category":"Elektroinstallationsunternehmen",
    "sg:phone":"+43 2572 24810",
    "sg:postcode":"2130",
    "sg:province":"Nieder\u00f6sterreich",
    "wof:name":"expert KRAUS GmbH",
    "wof:placetype":"venue"
},
  "geometry": {"coordinates":[16.5714359283,48.5674362183],"type":"Point"}
}