{
  "type": "Feature",
  "properties": {
    "iso:country":"AT",
    "sg:address":"Seeblickstr 78",
    "sg:city":"Drobollach am Faaker See",
    "sg:orig_category":"Tourismusinformation U -Organisationen",
    "sg:phone":"+43 4342 5421850",
    "sg:postcode":"9580",
    "sg:province":"K\u00e4rnten",
    "wof:name":"Tourismusinformation Drobollach",
    "wof:placetype":"venue"
},
  "geometry": {"coordinates":[13.9175033569,46.5877037048],"type":"Point"}
}