{
  "type": "Feature",
  "properties": {
    "iso:country":"AT",
    "sg:address":"Linzer Str 16/3",
    "sg:city":"Wien",
    "sg:orig_category":"Umweltschutz",
    "sg:phone":"+43 1 80332320",
    "sg:postcode":"1140",
    "sg:province":"Wien",
    "wof:name":"Die Umweltberatung in Wien",
    "wof:placetype":"venue"
},
  "geometry": {"coordinates":[16.3147106171,48.1929283142],"type":"Point"}
}