{
  "type": "Feature",
  "properties": {
    "addr:full":"Kaplanstr 1 Mauthausen Ober\u00f6sterreich 4310",
    "addr:housenumber":"1",
    "addr:postcode":"4310",
    "addr:street":"Kaplanstr",
    "iso:country":"AT",
    "sg:address":"Kaplanstr 1",
    "sg:city":"Mauthausen",
    "sg:orig_category":"Schwimmbecken",
    "sg:phone":"+43 4372 3828549",
    "sg:postcode":"4310",
    "sg:province":"Ober\u00f6sterreich",
    "wof:name":"Sonne & Wasser",
    "wof:placetype":"venue"
},
  "geometry": {"coordinates":[14.5499067307,48.2438430786],"type":"Point"}
}