{
  "type": "Feature",
  "properties": {
    "iso:country":"AT",
    "sg:address":"Weyerng 41",
    "sg:city":"Knittelfeld",
    "sg:orig_category":"Modellbau",
    "sg:phone":"+43 3512 71742",
    "sg:postcode":"8720",
    "sg:province":"Steiermark",
    "wof:name":"H\u00e4usl Brigitte",
    "wof:placetype":"venue"
},
  "geometry": {"coordinates":[14.8257627487,47.2051277161],"type":"Point"}
}