{
  "type": "Feature",
  "properties": {
    "addr:full":"Dr Rasper-Str 19 Ebensee Ober\u00f6sterreich 4802",
    "addr:housenumber":"19",
    "addr:postcode":"4802",
    "iso:country":"AT",
    "sg:address":"Dr Rasper-Str 19",
    "sg:city":"Ebensee",
    "sg:orig_category":"Abfallentsorgung U -Verwertung",
    "sg:phone":"+43 6133 6472",
    "sg:postcode":"4802",
    "sg:province":"Ober\u00f6sterreich",
    "wof:name":"Bezirksabfallverband Gmunden",
    "wof:placetype":"venue"
},
  "geometry": {"coordinates":[13.7730560303,47.7989616394],"type":"Point"}
}