{
  "type": "Feature",
  "properties": {
    "addr:full":"Obermarkt 30 Mauerkirchen Ober\u00f6sterreich 5270",
    "addr:housenumber":"30",
    "addr:postcode":"5270",
    "addr:street":"Obermarkt",
    "iso:country":"AT",
    "sg:address":"Obermarkt 30",
    "sg:city":"Mauerkirchen",
    "sg:orig_category":"Banken U Sparkassen",
    "sg:phone":"+43 7724 31000",
    "sg:postcode":"5270",
    "sg:province":"Ober\u00f6sterreich",
    "wof:name":"Raiffeisenbank Mattigtal regGenmbH",
    "wof:placetype":"venue"
},
  "geometry": {"coordinates":[13.134267807,48.1902198792],"type":"Point"}
}