{
  "type": "Feature",
  "properties": {
    "addr:full":"Handelsstr 10 Gerasdorf Nieder\u00f6sterreich 2201",
    "addr:housenumber":"10",
    "addr:postcode":"2201",
    "addr:street":"Handelsstr",
    "iso:country":"AT",
    "sg:address":"Handelsstr 10",
    "sg:city":"Gerasdorf",
    "sg:classifiers":[
        {
            "category":"Professional",
            "subcategory":"Art Services",
            "type":"Services"
        }
    ],
    "sg:phone":"+43 2246 20737",
    "sg:postcode":"2201",
    "sg:province":"Nieder\u00f6sterreich",
    "sg:tags":[
        "designer"
    ],
    "wof:name":"AV-Design Alfred Vitovec",
    "wof:placetype":"venue"
},
  "geometry": {"coordinates":[16.4633178711,48.336681366],"type":"Point"}
}