{
  "type": "Feature",
  "properties": {
    "addr:full":"Neu Industriegebiet Breitenau am Steinfelde Nieder\u00f6sterreich 2624",
    "addr:postcode":"2624",
    "addr:street":"Neu Industriegebiet Breitenau;Niederoesterreich",
    "iso:country":"AT",
    "sg:address":"Neu Industriegebiet",
    "sg:city":"Breitenau am Steinfelde",
    "sg:orig_category":"Transportunternehmen",
    "sg:phone":"+43 2635 69888",
    "sg:postcode":"2624",
    "sg:province":"Nieder\u00f6sterreich",
    "wof:name":"Duskanich Karl Ing",
    "wof:placetype":"venue"
},
  "geometry": {"coordinates":[16.1426620483,47.7335510254],"type":"Point"}
}