{
  "type": "Feature",
  "properties": {
    "addr:full":"Kagraner Pl. 20-21  Wien Wien 1220",
    "addr:housenumber":"20-21",
    "addr:postcode":"1220",
    "addr:street":"Kagraner Pl.",
    "iso:country":"AT",
    "sg:address":"Kagraner Pl. 20-21 ",
    "sg:city":"Wien",
    "sg:orig_category":"Miscellaneous Products",
    "sg:phone":"+43 4312 0456090",
    "sg:postcode":"1220",
    "sg:province":"Wien",
    "wof:name":"IS 21 HANDELSGESMBH",
    "wof:placetype":"venue"
},
  "geometry": {"coordinates":[16.4494304657,48.2486343384],"type":"Point"}
}