{
  "type": "Feature",
  "properties": {
    "iso:country":"AT",
    "sg:address":"Am Modenapark 8-9",
    "sg:city":"Wien",
    "sg:classifiers":[
        {
            "category":"Utilities",
            "subcategory":"Natural Gas",
            "type":"Services"
        }
    ],
    "sg:phone":"+43 1 7142279",
    "sg:postcode":"1030",
    "sg:province":"Wien",
    "sg:tags":[
        "heater",
        "electric"
    ],
    "sg:website":"tronner.at",
    "wof:name":"Tronner Ges.m.b.H.",
    "wof:placetype":"venue"
},
  "geometry": {"coordinates":[16.3827533722,48.1989860535],"type":"Point"}
}