{
  "type": "Feature",
  "properties": {
    "iso:country":"AT",
    "sg:address":"Judenburger Str 34",
    "sg:city":"Fohnsdorf",
    "sg:orig_category":"Automatisierungstechnik",
    "sg:phone":"+43 3573 34008",
    "sg:postcode":"8753",
    "sg:province":"Steiermark",
    "wof:name":"OTTRONIC Regeltechnik GesmbH",
    "wof:placetype":"venue"
},
  "geometry": {"coordinates":[14.6783304214,47.2035598755],"type":"Point"}
}