{
  "type": "Feature",
  "properties": {
    "addr:full":"Nr 102 Loibichl Ober\u00f6sterreich 5311",
    "addr:housenumber":"5311",
    "addr:street":"Nr 102 Loibichl Oberoesterreich",
    "iso:country":"AT",
    "sg:address":"Nr 102",
    "sg:city":"Loibichl",
    "sg:orig_category":"Gastronomie- U Hoteleinrichtungen",
    "sg:phone":"+43 4369 912536333",
    "sg:postcode":"5311",
    "sg:province":"Ober\u00f6sterreich",
    "wof:name":"TSE Technischer Service und Equipment - Hasenschwandtner Peter",
    "wof:placetype":"venue"
},
  "geometry": {"coordinates":[13.4032068253,47.8300895691],"type":"Point"}
}