{
  "type": "Feature",
  "properties": {
    "iso:country":"AT",
    "sg:address":"Mariazeller Str 33",
    "sg:city":"Traisen",
    "sg:orig_category":"Tankstellen",
    "sg:phone":"+43 2762 62291",
    "sg:postcode":"3160",
    "sg:province":"Nieder\u00f6sterreich",
    "wof:name":"Agip Tankstelle",
    "wof:placetype":"venue"
},
  "geometry": {"coordinates":[15.6092329025,48.0447845459],"type":"Point"}
}