{
  "type": "Feature",
  "properties": {
    "addr:full":"Simon-Denk-G 9/3 Wien Wien 1090",
    "addr:housenumber":"9 / 3",
    "addr:postcode":"1090",
    "addr:street":"Simon-Denk-G",
    "iso:country":"AT",
    "sg:address":"Simon-Denk-G 9/3",
    "sg:city":"Wien",
    "sg:orig_category":"Online-Service",
    "sg:phone":"+43 4366 44367452",
    "sg:postcode":"1090",
    "sg:province":"Wien",
    "wof:name":"PH- Design Hollergschwandtner Phillip",
    "wof:placetype":"venue"
},
  "geometry": {"coordinates":[16.3591327667,48.2260360718],"type":"Point"}
}