{
  "type": "Feature",
  "properties": {
    "iso:country":"AT",
    "sg:address":"Baumgartnerstr 2",
    "sg:city":"Kufstein",
    "sg:orig_category":"Friseure U Frisiersalons",
    "sg:phone":"+43 5372 62291",
    "sg:postcode":"6330",
    "sg:province":"Tirol",
    "wof:name":"Harmonie - Elisabeth Gridling",
    "wof:placetype":"venue"
},
  "geometry": {"coordinates":[12.1699304581,47.5799865723],"type":"Point"}
}