{
  "type": "Feature",
  "properties": {
    "addr:full":"Nr 61 Altaussee Steiermark 8992",
    "addr:postcode":"8992",
    "addr:street":"Nr",
    "iso:country":"AT",
    "sg:address":"Nr 61",
    "sg:city":"Altaussee",
    "sg:orig_category":"Flugschulen",
    "sg:phone":"+43 4366 41116099",
    "sg:postcode":"8992",
    "sg:province":"Steiermark",
    "wof:name":"Drachen- u Para-Flugschule Salzkammergut GesmbH",
    "wof:placetype":"venue"
},
  "geometry": {"coordinates":[13.764960289,47.6403694153],"type":"Point"}
}