{
  "type": "Feature",
  "properties": {
    "iso:country":"AT",
    "sg:address":"Johann-Roithner-Strasse 21",
    "sg:city":"Traun",
    "sg:classifiers":[
        {
            "category":"Manufacturing",
            "subcategory":"Furniture",
            "type":"Manufacturing & Wholesale Goods"
        }
    ],
    "sg:phone":"+43 7229 72032",
    "sg:postcode":"4050",
    "sg:province":"Ober\u00f6sterreich",
    "sg:tags":[
        "design"
    ],
    "wof:name":"Prammer KG",
    "wof:placetype":"venue"
},
  "geometry": {"coordinates":[14.2416496277,48.2230682373],"type":"Point"}
}