{
  "type": "Feature",
  "properties": {
    "iso:country":"AT",
    "sg:address":"Bahnhofstr 124",
    "sg:city":"Deutschfeistritz",
    "sg:orig_category":"Fleischhauereien",
    "sg:phone":"+43 3127 41182",
    "sg:postcode":"8121",
    "sg:province":"Steiermark",
    "wof:name":"Eibinger Peter",
    "wof:placetype":"venue"
},
  "geometry": {"coordinates":[15.3357686996,47.1987991333],"type":"Point"}
}