{
  "type": "Feature",
  "properties": {
    "addr:full":"Eisenst\u00e4dter Str 61 Breitenbrunn Burgenland 7091",
    "addr:postcode":"7091",
    "addr:street":"Str 61",
    "iso:country":"AT",
    "sg:address":"Eisenst\u00e4dter Str 61",
    "sg:city":"Breitenbrunn",
    "sg:orig_category":"Autovermietung",
    "sg:phone":"+43 2683 5292",
    "sg:postcode":"7091",
    "sg:province":"Burgenland",
    "wof:name":"Egrieder Herbert",
    "wof:placetype":"venue"
},
  "geometry": {"coordinates":[16.7286624908,47.9404067993],"type":"Point"}
}