{
  "type": "Feature",
  "properties": {
    "addr:full":"Annaberg 105 Annaberg Salzburg 5524",
    "addr:housenumber":"105",
    "addr:postcode":"5524",
    "addr:street":"Annaberg;Salzburg",
    "iso:country":"AT",
    "sg:address":"Annaberg 105",
    "sg:city":"Annaberg",
    "sg:classifiers":[
        {
            "category":"Utilities",
            "subcategory":"Natural Gas",
            "type":"Services"
        }
    ],
    "sg:phone":"+43 6463 8600",
    "sg:postcode":"5524",
    "sg:province":"Salzburg",
    "sg:tags":[
        "heater",
        "direct",
        "electric"
    ],
    "wof:name":"Manfred Rettenbacher",
    "wof:placetype":"venue"
},
  "geometry": {"coordinates":[14.1333465576,48.2787399292],"type":"Point"}
}