{
  "type": "Feature",
  "properties": {
    "addr:full":"Mitterfeld 30 Bergheim Salzburg 5101",
    "addr:housenumber":"30",
    "addr:postcode":"5101",
    "addr:street":"Mitterfeld;Salzburg",
    "iso:country":"AT",
    "sg:address":"Mitterfeld 30",
    "sg:city":"Bergheim",
    "sg:orig_category":"Psychotherapie",
    "sg:phone":"+43 662 457111",
    "sg:postcode":"5101",
    "sg:province":"Salzburg",
    "wof:name":"Kreuzberger Maximilian Mag",
    "wof:placetype":"venue"
},
  "geometry": {"coordinates":[13.0336408615,47.8314437866],"type":"Point"}
}