{
  "type": "Feature",
  "properties": {
    "addr:full":"Wilhelm Jentsch-Str 2 Peggau Steiermark 8120",
    "addr:housenumber":"2",
    "addr:postcode":"8120",
    "iso:country":"AT",
    "sg:address":"Wilhelm Jentsch-Str 2",
    "sg:city":"Peggau",
    "sg:orig_category":"Hufschmiede",
    "sg:phone":"+43 3127 2229",
    "sg:postcode":"8120",
    "sg:province":"Steiermark",
    "wof:name":"Hufkonzept Mag Peter Kramberger",
    "wof:placetype":"venue"
},
  "geometry": {"coordinates":[15.3418970108,47.2034454346],"type":"Point"}
}