{
  "type": "Feature",
  "properties": {
    "addr:full":"Gaminger Str 9 Gresten Nieder\u00f6sterreich 3264",
    "addr:housenumber":"9",
    "addr:postcode":"3264",
    "addr:street":"Str",
    "iso:country":"AT",
    "sg:address":"Gaminger Str 9",
    "sg:city":"Gresten",
    "sg:classifiers":[
        {
            "category":"Home & Garden",
            "subcategory":"Garden Supply",
            "type":"Retail Goods"
        }
    ],
    "sg:phone":"+43 7487 7532",
    "sg:postcode":"3264",
    "sg:province":"Nieder\u00f6sterreich",
    "sg:tags":[
        "schotter",
        "sand",
        "u"
    ],
    "wof:name":"Harreither Herbert",
    "wof:placetype":"venue"
},
  "geometry": {"coordinates":[15.0233402252,47.9658088684],"type":"Point"}
}