{
  "type": "Feature",
  "properties": {
    "addr:full":"Schulstr 9 Julbach Ober\u00f6sterreich 4162",
    "addr:housenumber":"9",
    "addr:postcode":"4162",
    "addr:street":"Schulstr",
    "iso:country":"AT",
    "sg:address":"Schulstr 9",
    "sg:city":"Julbach",
    "sg:orig_category":"\u00c3\u201erzte / F Allgemeinmedizin",
    "sg:phone":"+43 7288 8293",
    "sg:postcode":"4162",
    "sg:province":"Ober\u00f6sterreich",
    "wof:name":"Kautz Helmut Dr",
    "wof:placetype":"venue"
},
  "geometry": {"coordinates":[13.8822278976,48.6442604065],"type":"Point"}
}