{
  "type": "Feature",
  "properties": {
    "addr:full":"Markt 11  Neufelden Ober\u00f6sterreich 4120",
    "addr:housenumber":"11",
    "addr:postcode":"4120",
    "addr:street":"Markt",
    "iso:country":"AT",
    "sg:address":"Markt 11 ",
    "sg:city":"Neufelden",
    "sg:classifiers":[
        {
            "category":"Utilities",
            "subcategory":"Electric",
            "type":"Services"
        }
    ],
    "sg:phone":"+43 4372 8262400",
    "sg:postcode":"4120",
    "sg:province":"Ober\u00f6sterreich",
    "sg:tags":[
        "component",
        "electronic"
    ],
    "wof:name":"JOHANN GAHLEITNER GES.MBH & CO KG",
    "wof:placetype":"venue"
},
  "geometry": {"coordinates":[14.0012741089,48.4847793579],"type":"Point"}
}