{
  "type": "Feature",
  "properties": {
    "addr:full":"Wallensteinstr 15 Wien Wien 1200",
    "addr:housenumber":"15",
    "addr:postcode":"1200",
    "addr:street":"Wallensteinstr",
    "iso:country":"AT",
    "sg:address":"Wallensteinstr 15",
    "sg:city":"Wien",
    "sg:orig_category":"Waren Aller Art",
    "sg:phone":"+43 1 9447788",
    "sg:postcode":"1200",
    "sg:province":"Wien",
    "wof:name":"Jaka Handels GesmbH",
    "wof:placetype":"venue"
},
  "geometry": {"coordinates":[16.3679637909,48.2287101746],"type":"Point"}
}