{
  "type": "Feature",
  "properties": {
    "addr:full":"Am R\u00f6hrbrunn 1 Langenlois Nieder\u00f6sterreich 3550",
    "addr:housenumber":"1",
    "addr:postcode":"3550",
    "addr:street":"Am Roehrbrunn",
    "iso:country":"AT",
    "sg:address":"Am R\u00f6hrbrunn 1",
    "sg:city":"Langenlois",
    "sg:orig_category":"Nachhilfe U Lernbetreuung",
    "sg:phone":"+43 4327 34351821",
    "sg:postcode":"3550",
    "sg:province":"Nieder\u00f6sterreich",
    "wof:name":"Hilfswerk Langenlois - Rund ums Lernen",
    "wof:placetype":"venue"
},
  "geometry": {"coordinates":[15.67689991,48.4733161926],"type":"Point"}
}