{
  "type": "Feature",
  "properties": {
    "addr:full":"Piccostrasse 14 Villach K\u00e4rnten 9500",
    "addr:housenumber":"14",
    "addr:postcode":"9500",
    "addr:street":"Piccostrasse;Kaernten",
    "iso:country":"AT",
    "sg:address":"Piccostrasse 14",
    "sg:city":"Villach",
    "sg:classifiers":[
        {
            "category":"Building & Trades",
            "subcategory":"Plumbing",
            "type":"Services"
        }
    ],
    "sg:phone":"+43 4242 416610",
    "sg:postcode":"9500",
    "sg:province":"K\u00e4rnten",
    "sg:tags":[
        "repair",
        "crane",
        "construction",
        "machinery"
    ],
    "wof:name":"Nino De Martiis Ges.m.b.H.",
    "wof:placetype":"venue"
},
  "geometry": {"coordinates":[13.8593769073,46.6204528809],"type":"Point"}
}