{
  "type": "Feature",
  "properties": {
    "addr:full":"Grazer Str 249 Frauental an der La\u00dfnitz Steiermark 8523",
    "addr:housenumber":"249",
    "addr:postcode":"8523",
    "iso:country":"AT",
    "sg:address":"Grazer Str 249",
    "sg:city":"Frauental an der La\u00dfnitz",
    "sg:orig_category":"Fleisch-, Wurst- U Selchwaren / Erzeugung U Gro\u00c3\u0178handel",
    "sg:phone":"+43 4334 6223020",
    "sg:postcode":"8523",
    "sg:province":"Steiermark",
    "wof:name":"Sorger Wurst- u Schinkenspezialit\u00e4ten GmbH",
    "wof:placetype":"venue"
},
  "geometry": {"coordinates":[15.2557220459,46.8260574341],"type":"Point"}
}