{
  "type": "Feature",
  "properties": {
    "iso:country":"AT",
    "sg:address":"Kirchenpl 7",
    "sg:city":"Guntramsdorf",
    "sg:orig_category":"Tabaktrafiken",
    "sg:phone":"+43 2236 52041",
    "sg:postcode":"2353",
    "sg:province":"Nieder\u00f6sterreich",
    "wof:name":"Hrdina Nadja",
    "wof:placetype":"venue"
},
  "geometry": {"coordinates":[16.3138065338,48.0476036072],"type":"Point"}
}