{
  "type": "Feature",
  "properties": {
    "iso:country":"AT",
    "sg:address":"Grillparzerstr 58",
    "sg:city":"Graz",
    "sg:orig_category":"Holzhandel",
    "sg:phone":"+43 4331 6325420",
    "sg:postcode":"8010",
    "sg:province":"Steiermark",
    "wof:name":"sinecortex Holzhandel GmbH",
    "wof:placetype":"venue"
},
  "geometry": {"coordinates":[15.4403419495,47.0851745605],"type":"Point"}
}