{
  "type": "Feature",
  "properties": {
    "iso:country":"AT",
    "sg:address":"Abt Otker-G 6",
    "sg:city":"Mariazell",
    "sg:orig_category":"Gartenpflege",
    "sg:phone":"+43 664 3209214",
    "sg:postcode":"8630",
    "sg:province":"Steiermark",
    "wof:name":"Garten- und Rasenpflege Helmut Gamsj\u00e4ger",
    "wof:placetype":"venue"
},
  "geometry": {"coordinates":[15.3240747452,47.7685813904],"type":"Point"}
}