{
  "type": "Feature",
  "properties": {
    "addr:full":"Mozartstr 5 Linz Ober\u00f6sterreich 4020",
    "addr:housenumber":"5",
    "addr:postcode":"4020",
    "addr:street":"Mozartstr",
    "iso:country":"AT",
    "sg:address":"Mozartstr 5",
    "sg:city":"Linz",
    "sg:orig_category":"Fotografen",
    "sg:phone":"+43 732 770800",
    "sg:postcode":"4020",
    "sg:province":"Ober\u00f6sterreich",
    "wof:name":"Foto Atelier Mozart",
    "wof:placetype":"venue"
},
  "geometry": {"coordinates":[14.2914009094,48.3012580872],"type":"Point"}
}