{
  "type": "Feature",
  "properties": {
    "addr:full":"Kraelitzgasse 1 Wien Wien 1130",
    "addr:housenumber":"1",
    "addr:postcode":"1130",
    "addr:street":"Kraelitzgasse",
    "iso:country":"AT",
    "sg:address":"Kraelitzgasse 1",
    "sg:city":"Wien",
    "sg:classifiers":[
        {
            "category":"Banks & Credit Unions",
            "subcategory":"Investment Brokerage",
            "type":"Services"
        }
    ],
    "sg:phone":"+43 1 8045137",
    "sg:postcode":"1130",
    "sg:province":"Wien",
    "sg:tags":[
        "scale",
        "solvent",
        "boiler"
    ],
    "wof:name":"Dr. Ing. Franz B\u00f6hm Erzeugung chem. Produkte Ges.m.b.H.",
    "wof:placetype":"venue"
},
  "geometry": {"coordinates":[16.2928905487,48.1665992737],"type":"Point"}
}