{
  "type": "Feature",
  "properties": {
    "iso:country":"AT",
    "sg:address":"Hofm\u00fchle 146",
    "sg:city":"Hoheneich",
    "sg:orig_category":"Erdarbeiten",
    "sg:phone":"+43 2852 54316",
    "sg:postcode":"3945",
    "sg:province":"Nieder\u00f6sterreich",
    "wof:name":"Schmid Herbert",
    "wof:placetype":"venue"
},
  "geometry": {"coordinates":[15.0258569717,48.7716026306],"type":"Point"}
}