{
  "type": "Feature",
  "properties": {
    "iso:country":"AT",
    "sg:address":"Sankt Johanner Strasse 85",
    "sg:city":"Kitzb\u00fchel",
    "sg:classifiers":[
        {
            "category":"Manufacturing",
            "subcategory":"Furniture",
            "type":"Manufacturing & Wholesale Goods"
        }
    ],
    "sg:phone":"+43 5356 65885",
    "sg:postcode":"6370",
    "sg:province":"Tirol",
    "sg:tags":[
        "bedroom"
    ],
    "wof:name":"Tischlerei Toni Ober Ges.m.b.H.",
    "wof:placetype":"venue"
},
  "geometry": {"coordinates":[12.3862228394,47.4634628296],"type":"Point"}
}