{
  "type": "Feature",
  "properties": {
    "iso:country":"AT",
    "sg:address":"Exlg 14",
    "sg:city":"Innsbruck",
    "sg:orig_category":"Autospenglereien",
    "sg:phone":"+43 512 281700",
    "sg:postcode":"6020",
    "sg:province":"Tirol",
    "sg:website":"karosserie-lindner.at",
    "wof:name":"Lindner Franz",
    "wof:placetype":"venue"
},
  "geometry": {"coordinates":[11.3733949661,47.257774353],"type":"Point"}
}