{
  "type": "Feature",
  "properties": {
    "addr:full":"Hohenauerweg 11 Koppl Salzburg 5321",
    "addr:housenumber":"11",
    "addr:postcode":"5321",
    "addr:street":"Hohenauerweg;Salzburg",
    "iso:country":"AT",
    "sg:address":"Hohenauerweg 11",
    "sg:city":"Koppl",
    "sg:orig_category":"Tischlereien",
    "sg:phone":"+43 6221 7607",
    "sg:postcode":"5321",
    "sg:province":"Salzburg",
    "wof:name":"Kornauer Rudolf",
    "wof:placetype":"venue"
},
  "geometry": {"coordinates":[13.1490707397,47.8143844604],"type":"Point"}
}