{
  "type": "Feature",
  "properties": {
    "addr:full":"Max-Bader-Pl 1 Schwarzach im Pongau Salzburg 5620",
    "addr:housenumber":"1",
    "addr:postcode":"5620",
    "addr:street":"Max-Bader-Pl;Salzburg",
    "iso:country":"AT",
    "sg:address":"Max-Bader-Pl 1",
    "sg:city":"Schwarzach im Pongau",
    "sg:orig_category":"Hauptschulen",
    "sg:phone":"+43 4364 154395",
    "sg:postcode":"5620",
    "sg:province":"Salzburg",
    "wof:name":"Hauptschule",
    "wof:placetype":"venue"
},
  "geometry": {"coordinates":[13.1549530029,47.3218612671],"type":"Point"}
}