{
  "type": "Feature",
  "properties": {
    "addr:full":"Bundesstr 52 Lauterach Vorarlberg 6923",
    "addr:housenumber":"52",
    "addr:postcode":"6923",
    "addr:street":"Bundesstr",
    "iso:country":"AT",
    "sg:address":"Bundesstr 52",
    "sg:city":"Lauterach",
    "sg:orig_category":"Blumeneinzelhandel",
    "sg:phone":"+43 5574 63320",
    "sg:postcode":"6923",
    "sg:province":"Vorarlberg",
    "wof:name":"ROSENK\u00f6NIG Aichhorn Walter",
    "wof:placetype":"venue"
},
  "geometry": {"coordinates":[9.7311315536,47.4768829346],"type":"Point"}
}