{
  "type": "Feature",
  "properties": {
    "iso:country":"AT",
    "sg:address":"Resselstrasse 18/4",
    "sg:city":"Innsbruck",
    "sg:classifiers":[
        {
            "category":"Parking",
            "subcategory":"Garage",
            "type":"Transportation"
        }
    ],
    "sg:phone":"+43 512 3901100",
    "sg:postcode":"6020",
    "sg:province":"Tirol",
    "sg:tags":[
        "dental",
        "floss"
    ],
    "sg:website":"gsk-consumer.at",
    "wof:name":"GlaxoSmithKline Markenartikel GmbH",
    "wof:placetype":"venue"
},
  "geometry": {"coordinates":[11.409989357,47.2610931396],"type":"Point"}
}