{
  "type": "Feature",
  "properties": {
    "iso:country":"AT",
    "sg:address":"Trillerg 8",
    "sg:city":"Wien",
    "sg:orig_category":"Eisenwaren",
    "sg:phone":"+43 4312 922580",
    "sg:postcode":"1210",
    "sg:province":"Wien",
    "wof:name":"Weyland GmbH",
    "wof:placetype":"venue"
},
  "geometry": {"coordinates":[16.405790329,48.2729492188],"type":"Point"}
}