{
  "type": "Feature",
  "properties": {
    "iso:country":"AT",
    "sg:address":"J\u00f6sser Str 12",
    "sg:city":"Leibnitz",
    "sg:orig_category":"Autohandel",
    "sg:phone":"+43 4334 52843620",
    "sg:postcode":"8430",
    "sg:province":"Steiermark",
    "wof:name":"Temmer Walter GmbH",
    "wof:placetype":"venue"
},
  "geometry": {"coordinates":[15.5309410095,46.8067626953],"type":"Point"}
}