{
  "type": "Feature",
  "properties": {
    "addr:full":"Schwandter Str 28 Freistadt Ober\u00f6sterreich 4240",
    "addr:housenumber":"28",
    "addr:postcode":"4240",
    "addr:street":"Str",
    "iso:country":"AT",
    "sg:address":"Schwandter Str 28",
    "sg:city":"Freistadt",
    "sg:orig_category":"Tierschutz",
    "sg:phone":"+43 4379 4272261",
    "sg:postcode":"4240",
    "sg:province":"Ober\u00f6sterreich",
    "wof:name":"Binder Karin - Tierschutzstelle",
    "wof:placetype":"venue"
},
  "geometry": {"coordinates":[14.4782323837,48.5018424988],"type":"Point"}
}