{
  "type": "Feature",
  "properties": {
    "iso:country":"AT",
    "sg:address":"Hofsteigstr 34",
    "sg:city":"Wolfurt",
    "sg:orig_category":"Alternativtherapie",
    "sg:phone":"+43 5574 85565",
    "sg:postcode":"6922",
    "sg:province":"Vorarlberg",
    "wof:name":"Mitgutsch Karl Leo",
    "wof:placetype":"venue"
},
  "geometry": {"coordinates":[9.751458168,47.4628753662],"type":"Point"}
}