{
  "type": "Feature",
  "properties": {
    "addr:full":"Mariahilfer G\u00fcrtel 11 Wien Wien 1150",
    "addr:housenumber":"11",
    "addr:postcode":"1150",
    "iso:country":"AT",
    "sg:address":"Mariahilfer G\u00fcrtel 11",
    "sg:city":"Wien",
    "sg:orig_category":"Non-Classified Establishments",
    "sg:phone":"+43 1 8934279",
    "sg:postcode":"1150",
    "sg:province":"Wien",
    "wof:name":"Missionarinnen der N\u00e4chstenliebe der Zweigniederlassung in Wien",
    "wof:placetype":"venue"
},
  "geometry": {"coordinates":[16.3320903778,48.2006416321],"type":"Point"}
}