{
  "type": "Feature",
  "properties": {
    "addr:full":"Ponigl 18 Werndorf Steiermark 8402",
    "addr:housenumber":"18",
    "addr:postcode":"8402",
    "addr:street":"Ponigl",
    "iso:country":"AT",
    "sg:address":"Ponigl 18",
    "sg:city":"Werndorf",
    "sg:classifiers":[
        {
            "category":"Home & Garden",
            "subcategory":"Building Materials",
            "type":"Retail Goods"
        }
    ],
    "sg:phone":"+43 4331 3550916",
    "sg:postcode":"8402",
    "sg:province":"Steiermark",
    "sg:tags":[
        "baustoffe",
        "-material",
        "u"
    ],
    "wof:name":"Fr\u00fchwald GesmbH & Co KG",
    "wof:placetype":"venue"
},
  "geometry": {"coordinates":[15.4903116226,46.9242973328],"type":"Point"}
}