{
  "type": "Feature",
  "properties": {
    "addr:full":"Mauthausener Str 6 St. Georgen an der Gusen Ober\u00f6sterreich 4222",
    "addr:housenumber":"6",
    "addr:postcode":"4222",
    "addr:street":"Str",
    "iso:country":"AT",
    "sg:address":"Mauthausener Str 6",
    "sg:city":"St. Georgen an der Gusen",
    "sg:classifiers":[
        {
            "category":"Professional",
            "subcategory":"Art Services",
            "type":"Services"
        }
    ],
    "sg:phone":"+43 7237 2489",
    "sg:postcode":"4222",
    "sg:province":"Ober\u00f6sterreich",
    "sg:tags":[
        "designer"
    ],
    "wof:name":"Geiblinger Gudrun Mag GG DESIGN",
    "wof:placetype":"venue"
},
  "geometry": {"coordinates":[14.4499158859,48.2717475891],"type":"Point"}
}