{
  "type": "Feature",
  "properties": {
    "addr:full":"Pruggererberg 233 Pruggern Steiermark 8965",
    "addr:housenumber":"233",
    "addr:postcode":"8965",
    "addr:street":"Pruggererberg",
    "iso:country":"AT",
    "sg:address":"Pruggererberg 233",
    "sg:city":"Pruggern",
    "sg:orig_category":"Appartements / Ferienwohnungen",
    "sg:phone":"+43 4336 8522185",
    "sg:postcode":"8965",
    "sg:province":"Steiermark",
    "wof:name":"Stocker Burgi",
    "wof:placetype":"venue"
},
  "geometry": {"coordinates":[13.8609476089,47.4110946655],"type":"Point"}
}