{
  "type": "Feature",
  "properties": {
    "addr:full":"Goldschlagstr 102 Wien Wien 1150",
    "addr:housenumber":"102",
    "addr:postcode":"1150",
    "iso:country":"AT",
    "sg:address":"Goldschlagstr 102",
    "sg:city":"Wien",
    "sg:orig_category":"Apotheken",
    "sg:phone":"+43 1 9824382",
    "sg:postcode":"1150",
    "sg:province":"Wien",
    "wof:name":"St Rudolf Apotheke Mag pharm Ernst Puchinger",
    "wof:placetype":"venue"
},
  "geometry": {"coordinates":[16.3180160522,48.1943588257],"type":"Point"}
}