{
  "type": "Feature",
  "properties": {
    "iso:country":"AT",
    "sg:address":"Semerweg 25",
    "sg:city":"W\u00f6lfnitz",
    "sg:classifiers":[
        {
            "category":"Professional",
            "subcategory":"Computer Services",
            "type":"Services"
        }
    ],
    "sg:phone":"+43 463 329370",
    "sg:postcode":"9061",
    "sg:province":"K\u00e4rnten",
    "sg:tags":[
        "software"
    ],
    "wof:name":"Kutschera Datentechnik GesmbH",
    "wof:placetype":"venue"
},
  "geometry": {"coordinates":[14.2841749191,46.6672096252],"type":"Point"}
}