{
  "type": "Feature",
  "properties": {
    "addr:full":"Litschauer Str 38 Gm\u00fcnd Nieder\u00f6sterreich 3950",
    "addr:postcode":"3950",
    "addr:street":"Str 38 Gmuend",
    "iso:country":"AT",
    "sg:address":"Litschauer Str 38",
    "sg:city":"Gm\u00fcnd",
    "sg:orig_category":"Tischlereien",
    "sg:phone":"+43 2852 52457",
    "sg:postcode":"3950",
    "sg:province":"Nieder\u00f6sterreich",
    "wof:name":"Karasek Kurt",
    "wof:placetype":"venue"
},
  "geometry": {"coordinates":[14.9832782745,48.7778968811],"type":"Point"}
}