{
  "type": "Feature",
  "properties": {
    "addr:full":"Schiferpl 9 Eferding Ober\u00f6sterreich 4070",
    "addr:housenumber":"9",
    "addr:postcode":"4070",
    "addr:street":"Schiferpl",
    "iso:country":"AT",
    "sg:address":"Schiferpl 9",
    "sg:city":"Eferding",
    "sg:orig_category":"Bierlokale-Pubs",
    "sg:phone":"+43 664 3936842",
    "sg:postcode":"4070",
    "sg:province":"Ober\u00f6sterreich",
    "wof:name":"Pub Le Figaro",
    "wof:placetype":"venue"
},
  "geometry": {"coordinates":[14.0247058868,48.3073768616],"type":"Point"}
}