{
  "type": "Feature",
  "properties": {
    "addr:full":"Leopold Werndl-Str 44 Steyr Ober\u00f6sterreich 4400",
    "addr:housenumber":"44",
    "addr:postcode":"4400",
    "addr:street":"Oberoesterreich",
    "iso:country":"AT",
    "sg:address":"Leopold Werndl-Str 44",
    "sg:city":"Steyr",
    "sg:orig_category":"Lebens- U Sozialberatung",
    "sg:phone":"+43 699 12224843",
    "sg:postcode":"4400",
    "sg:province":"Ober\u00f6sterreich",
    "wof:name":"Kaiserreiner Sandra",
    "wof:placetype":"venue"
},
  "geometry": {"coordinates":[14.4101066589,48.0301132202],"type":"Point"}
}