{
  "type": "Feature",
  "properties": {
    "addr:full":"Waasenstr 12 Leoben Steiermark 8700",
    "addr:housenumber":"12",
    "addr:postcode":"8700",
    "addr:street":"Waasenstr",
    "iso:country":"AT",
    "sg:address":"Waasenstr 12",
    "sg:city":"Leoben",
    "sg:orig_category":"Juwelen, Gold- U Silberwaren / Einzelhandel",
    "sg:phone":"+43 4338 4223778",
    "sg:postcode":"8700",
    "sg:province":"Steiermark",
    "wof:name":"Pergold - Inh Pergovnik Silvia",
    "wof:placetype":"venue"
},
  "geometry": {"coordinates":[15.0914373398,47.3786697388],"type":"Point"}
}