{
  "type": "Feature",
  "properties": {
    "addr:full":"Mainersbergstr 1 G\u00f6sting Steiermark 8051",
    "addr:housenumber":"1",
    "addr:postcode":"8051",
    "addr:street":"Mainersbergstr",
    "iso:country":"AT",
    "sg:address":"Mainersbergstr 1",
    "sg:city":"G\u00f6sting",
    "sg:classifiers":[
        {
            "category":"Travel",
            "subcategory":"Hotels & Motels",
            "type":"Entertainment"
        }
    ],
    "sg:phone":"+43 4331 6571434",
    "sg:postcode":"8051",
    "sg:province":"Steiermark",
    "sg:website":"bokan-exclusiv.at",
    "wof:name":"Bokan exclusiv Hotel-Gasthof",
    "wof:placetype":"venue"
},
  "geometry": {"coordinates":[15.4049654007,47.0851516724],"type":"Point"}
}