{
  "type": "Feature",
  "properties": {
    "iso:country":"AT",
    "sg:address":"Gaisbergstr 38",
    "sg:city":"Salzburg",
    "sg:orig_category":"Innenarchitekten",
    "sg:phone":"+43 662 640920",
    "sg:postcode":"5020",
    "sg:province":"Salzburg",
    "wof:name":"Czipf Gabriele Dipl-Ing",
    "wof:placetype":"venue"
},
  "geometry": {"coordinates":[13.0738935471,47.8021430969],"type":"Point"}
}