{
  "type": "Feature",
  "properties": {
    "addr:full":"Viktor-Christ-G 24 Wien Wien 1050",
    "addr:housenumber":"24",
    "addr:postcode":"1050",
    "addr:street":"Viktor-Christ-G",
    "iso:country":"AT",
    "sg:address":"Viktor-Christ-G 24",
    "sg:city":"Wien",
    "sg:orig_category":"Hauptschulen",
    "sg:phone":"+43 1 5448356",
    "sg:postcode":"1050",
    "sg:province":"Wien",
    "wof:name":"Schulen d Stadt Wien",
    "wof:placetype":"venue"
},
  "geometry": {"coordinates":[16.3567619324,48.1880493164],"type":"Point"}
}