{
  "type": "Feature",
  "properties": {
    "iso:country":"AT",
    "sg:address":"Maximilianstr 8",
    "sg:city":"Innsbruck",
    "sg:orig_category":"Fernseh- U Radiogesellschaften",
    "sg:phone":"+43 4351 2581899",
    "sg:postcode":"6020",
    "sg:province":"Tirol",
    "wof:name":"Radio Maria Tirol",
    "wof:placetype":"venue"
},
  "geometry": {"coordinates":[11.3898172379,47.2623405457],"type":"Point"}
}