{
  "type": "Feature",
  "properties": {
    "addr:full":"Industriehafenstr 25 Enns Ober\u00f6sterreich 4470",
    "addr:housenumber":"25",
    "addr:postcode":"4470",
    "addr:street":"Industriehafenstr",
    "iso:country":"AT",
    "sg:address":"Industriehafenstr 25",
    "sg:city":"Enns",
    "sg:orig_category":"Chemikalien",
    "sg:phone":"+43 4372 23861310",
    "sg:postcode":"4470",
    "sg:province":"Ober\u00f6sterreich",
    "wof:name":"Biomontan Chemische Produkte Handels GmbH",
    "wof:placetype":"venue"
},
  "geometry": {"coordinates":[14.4979639053,48.2295608521],"type":"Point"}
}