{
  "type": "Feature",
  "properties": {
    "iso:country":"AT",
    "sg:address":"Kremsdorf 7",
    "sg:city":"Micheldorf in Ober\u00f6sterreich",
    "sg:orig_category":"Mietautos",
    "sg:phone":"+43 7582 62553",
    "sg:postcode":"4563",
    "sg:province":"Ober\u00f6sterreich",
    "wof:name":"Spernbauer Hermann",
    "wof:placetype":"venue"
},
  "geometry": {"coordinates":[14.1215114594,47.8874664307],"type":"Point"}
}