{
  "type": "Feature",
  "properties": {
    "iso:country":"AT",
    "sg:address":"Vinzenz Pallotti-Pl 2",
    "sg:city":"Salzburg",
    "sg:orig_category":"Non-Classified Establishments",
    "sg:phone":"+43 662 4316200",
    "sg:postcode":"5020",
    "sg:province":"Salzburg",
    "wof:name":"Pfarramt Lehen",
    "wof:placetype":"venue"
},
  "geometry": {"coordinates":[13.0285196304,47.8122749329],"type":"Point"}
}