{
  "type": "Feature",
  "properties": {
    "addr:full":"Sixtleiteng 369 Bad Aussee Steiermark 8990",
    "addr:housenumber":"369",
    "addr:postcode":"8990",
    "iso:country":"AT",
    "sg:address":"Sixtleiteng 369",
    "sg:city":"Bad Aussee",
    "sg:orig_category":"Briefmarken Philatelie",
    "sg:phone":"+43 3622 54075",
    "sg:postcode":"8990",
    "sg:province":"Steiermark",
    "wof:name":"Lipburger Horst",
    "wof:placetype":"venue"
},
  "geometry": {"coordinates":[13.7811584473,47.6067237854],"type":"Point"}
}