{
  "type": "Feature",
  "properties": {
    "addr:full":"Bahnhofstr 35 St. Paul im Lavanttal K\u00e4rnten 9470",
    "addr:housenumber":"35",
    "addr:postcode":"9470",
    "addr:street":"Bahnhofstr",
    "iso:country":"AT",
    "sg:address":"Bahnhofstr 35",
    "sg:city":"St. Paul im Lavanttal",
    "sg:orig_category":"Maler, Anstreicher U Lackierer",
    "sg:phone":"+43 4343 573764",
    "sg:postcode":"9470",
    "sg:province":"K\u00e4rnten",
    "wof:name":"Maier Herbert",
    "wof:placetype":"venue"
},
  "geometry": {"coordinates":[14.8643026352,46.7112388611],"type":"Point"}
}