{
  "type": "Feature",
  "properties": {
    "addr:full":"Weitmoserstr 3 Salzburg Salzburg 5020",
    "addr:housenumber":"3",
    "addr:postcode":"5020",
    "addr:street":"Weitmoserstr;Salzburg",
    "iso:country":"AT",
    "sg:address":"Weitmoserstr 3",
    "sg:city":"Salzburg",
    "sg:orig_category":"Handelsagenturen",
    "sg:phone":"+43 662 872343",
    "sg:postcode":"5020",
    "sg:province":"Salzburg",
    "wof:name":"Intercontact HandelsgesmbH",
    "wof:placetype":"venue"
},
  "geometry": {"coordinates":[13.0496072769,47.8096504211],"type":"Point"}
}