{
  "type": "Feature",
  "properties": {
    "addr:full":"Ruster Str 8 Eisenstadt Burgenland 7000",
    "addr:housenumber":"8",
    "addr:postcode":"7000",
    "addr:street":"Str",
    "iso:country":"AT",
    "sg:address":"Ruster Str 8",
    "sg:city":"Eisenstadt",
    "sg:orig_category":"Fitnesscenter",
    "sg:phone":"+43 2682 66654",
    "sg:postcode":"7000",
    "sg:province":"Burgenland",
    "wof:name":"Club Aktiv Gesund",
    "wof:placetype":"venue"
},
  "geometry": {"coordinates":[16.5196990967,47.8447189331],"type":"Point"}
}