{
  "type": "Feature",
  "properties": {
    "addr:full":"J\u00e4gerhausgasse 18 Schwechat Nieder\u00f6sterreich 2320",
    "addr:housenumber":"18",
    "addr:postcode":"2320",
    "addr:street":"Jaegerhausgasse;Niederoesterreich",
    "iso:country":"AT",
    "sg:address":"J\u00e4gerhausgasse 18",
    "sg:city":"Schwechat",
    "sg:classifiers":[
        {
            "category":"Personal",
            "subcategory":"Skin Care",
            "type":"Services"
        }
    ],
    "sg:phone":"+43 1 7078578",
    "sg:postcode":"2320",
    "sg:province":"Nieder\u00f6sterreich",
    "sg:tags":[
        "plug",
        "defender",
        "ear"
    ],
    "wof:name":"Ing. Franz Stadler Arbeitsschutz",
    "wof:placetype":"venue"
},
  "geometry": {"coordinates":[16.5243358612,48.1444015503],"type":"Point"}
}