{
  "type": "Feature",
  "properties": {
    "addr:full":"Am Riegel 11 Kohfidisch Burgenland 7512",
    "addr:housenumber":"11",
    "addr:postcode":"7512",
    "addr:street":"Am Riegel",
    "iso:country":"AT",
    "sg:address":"Am Riegel 11",
    "sg:city":"Kohfidisch",
    "sg:orig_category":"Handelsagenturen",
    "sg:phone":"+43 4333 6677256",
    "sg:postcode":"7512",
    "sg:province":"Burgenland",
    "wof:name":"Holzhacker Michael Ing",
    "wof:placetype":"venue"
},
  "geometry": {"coordinates":[16.3575592041,47.1757698059],"type":"Point"}
}