{
  "type": "Feature",
  "properties": {
    "addr:full":"Rosegger Str 24 Rosegg K\u00e4rnten 9232",
    "addr:postcode":"9232",
    "addr:street":"Str 24;Kaernten",
    "iso:country":"AT",
    "sg:address":"Rosegger Str 24",
    "sg:city":"Rosegg",
    "sg:orig_category":"Friseure U Frisiersalons",
    "sg:phone":"+43 4274 50692",
    "sg:postcode":"9232",
    "sg:province":"K\u00e4rnten",
    "wof:name":"Klemenjak Susanne",
    "wof:placetype":"venue"
},
  "geometry": {"coordinates":[14.0182304382,46.5896911621],"type":"Point"}
}