{
  "type": "Feature",
  "properties": {
    "addr:full":"Oberer Markt 125 Wildon Steiermark 8410",
    "addr:housenumber":"125",
    "addr:postcode":"8410",
    "addr:street":"Oberer Markt;Steiermark",
    "iso:country":"AT",
    "sg:address":"Oberer Markt 125",
    "sg:city":"Wildon",
    "sg:orig_category":"Reinigungsservice",
    "sg:phone":"+43 3182 27190",
    "sg:postcode":"8410",
    "sg:province":"Steiermark",
    "wof:name":"Weisse Rose Reinigungsservice GmbH",
    "wof:placetype":"venue"
},
  "geometry": {"coordinates":[15.5030565262,46.8864860535],"type":"Point"}
}