{
  "type": "Feature",
  "properties": {
    "addr:full":"Attergaustr St. Georgen im Attergau Ober\u00f6sterreich 4880",
    "addr:postcode":"4880",
    "iso:country":"AT",
    "sg:address":"Attergaustr",
    "sg:city":"St. Georgen im Attergau",
    "sg:orig_category":"Tankstellen",
    "sg:phone":"+43 4376 676488",
    "sg:postcode":"4880",
    "sg:province":"Ober\u00f6sterreich",
    "wof:name":"OMV AG",
    "wof:placetype":"venue"
},
  "geometry": {"coordinates":[13.4930019379,47.9324951172],"type":"Point"}
}