{
  "type": "Feature",
  "properties": {
    "addr:full":"Hauptstr 9 Peuerbach Ober\u00f6sterreich 4722",
    "addr:housenumber":"9",
    "addr:postcode":"4722",
    "addr:street":"Hauptstr",
    "iso:country":"AT",
    "sg:address":"Hauptstr 9",
    "sg:city":"Peuerbach",
    "sg:orig_category":"Optiker",
    "sg:phone":"+43 7276 50020",
    "sg:postcode":"4722",
    "sg:province":"Ober\u00f6sterreich",
    "wof:name":"Aigner Rudolf",
    "wof:placetype":"venue"
},
  "geometry": {"coordinates":[13.7720165253,48.3436737061],"type":"Point"}
}