{
  "type": "Feature",
  "properties": {
    "addr:full":"Stadionstr 23 Radenthein K\u00e4rnten 9545",
    "addr:housenumber":"23",
    "addr:postcode":"9545",
    "addr:street":"Stadionstr;Kaernten",
    "iso:country":"AT",
    "sg:address":"Stadionstr 23",
    "sg:city":"Radenthein",
    "sg:orig_category":"Damenmoden",
    "sg:phone":"+43 4342 4629081",
    "sg:postcode":"9545",
    "sg:province":"K\u00e4rnten",
    "wof:name":"Kik Textilien u Non-Food GesmbH",
    "wof:placetype":"venue"
},
  "geometry": {"coordinates":[13.7113037109,46.7982711792],"type":"Point"}
}