{
  "type": "Feature",
  "properties": {
    "iso:country":"AT",
    "sg:address":"Ramsauer Str 40",
    "sg:city":"Linz",
    "sg:orig_category":"Werbeagenturen",
    "sg:phone":"+43 732 336118",
    "sg:postcode":"4020",
    "sg:province":"Ober\u00f6sterreich",
    "wof:name":"Wimberger Regina Drphil - smart support/pharma marketing",
    "wof:placetype":"venue"
},
  "geometry": {"coordinates":[14.2879419327,48.2742614746],"type":"Point"}
}