{
  "type": "Feature",
  "properties": {
    "iso:country":"AT",
    "sg:address":"Sankt Anton Am Arlberg 485",
    "sg:city":"St. Anton am Arlberg",
    "sg:classifiers":[
        {
            "category":"Wholesale",
            "subcategory":"Drugs",
            "type":"Manufacturing & Wholesale Goods"
        }
    ],
    "sg:phone":"+43 4354 4620610",
    "sg:postcode":"6580",
    "sg:province":"Tirol",
    "sg:tags":[
        "chemical",
        "pharmaceutical"
    ],
    "wof:name":"ARLBERG-APOTHEKE",
    "wof:placetype":"venue"
},
  "geometry": {"coordinates":[10.2630138397,47.1247138977],"type":"Point"}
}