{
  "type": "Feature",
  "properties": {
    "addr:full":"Theodor-K\u00f6rner-Str 146 Graz Steiermark 8010",
    "addr:housenumber":"146",
    "addr:postcode":"8010",
    "iso:country":"AT",
    "sg:address":"Theodor-K\u00f6rner-Str 146",
    "sg:city":"Graz",
    "sg:orig_category":"Ingenieurkonsulenten / Zivilingenieure",
    "sg:phone":"+43 316 681367",
    "sg:postcode":"8010",
    "sg:province":"Steiermark",
    "wof:name":"Perchthaler Heinz DI Dr techn",
    "wof:placetype":"venue"
},
  "geometry": {"coordinates":[15.4270105362,47.091091156],"type":"Point"}
}