{
  "type": "Feature",
  "properties": {
    "addr:full":"Dorfbahnstr 43 Serfaus Tirol 6534",
    "addr:housenumber":"43",
    "addr:postcode":"6534",
    "addr:street":"Dorfbahnstr;Tirol",
    "iso:country":"AT",
    "sg:address":"Dorfbahnstr 43",
    "sg:city":"Serfaus",
    "sg:orig_category":"Banken U Sparkassen",
    "sg:phone":"+43 5476 62410",
    "sg:postcode":"6534",
    "sg:province":"Tirol",
    "wof:name":"Raiffeisenbank Serfaus regGenmbH",
    "wof:placetype":"venue"
},
  "geometry": {"coordinates":[10.6052074432,47.0385665894],"type":"Point"}
}