{
  "type": "Feature",
  "properties": {
    "addr:full":"Nr 84 Kottes Nieder\u00f6sterreich 3623",
    "addr:postcode":"3623",
    "addr:street":"Nr;Kottes Niederoesterreich",
    "iso:country":"AT",
    "sg:address":"Nr 84",
    "sg:city":"Kottes",
    "sg:orig_category":"Tankstellen",
    "sg:phone":"+43 2873 72250",
    "sg:postcode":"3623",
    "sg:province":"Nieder\u00f6sterreich",
    "wof:name":"Shell Austria GmbH",
    "wof:placetype":"venue"
},
  "geometry": {"coordinates":[15.3025751114,48.4154853821],"type":"Point"}
}