{
  "type": "Feature",
  "properties": {
    "iso:country":"AT",
    "sg:address":"Pechh\u00fcttenbrunneng 4-10",
    "sg:city":"Brunn am Gebirge",
    "sg:orig_category":"Autohandel",
    "sg:phone":"+43 2236 313350",
    "sg:postcode":"2345",
    "sg:province":"Nieder\u00f6sterreich",
    "wof:name":"Narowetz GmbH",
    "wof:placetype":"venue"
},
  "geometry": {"coordinates":[16.2839355469,48.107170105],"type":"Point"}
}