{
  "type": "Feature",
  "properties": {
    "addr:full":"Nr 26 Mooskirchen Steiermark 8562",
    "addr:postcode":"8562",
    "addr:street":"Nr",
    "iso:country":"AT",
    "sg:address":"Nr 26",
    "sg:city":"Mooskirchen",
    "sg:orig_category":"Handelsagenturen",
    "sg:phone":"+43 664 1630840",
    "sg:postcode":"8562",
    "sg:province":"Steiermark",
    "wof:name":"Schwab & Schwab Austria",
    "wof:placetype":"venue"
},
  "geometry": {"coordinates":[15.2820587158,46.9887542725],"type":"Point"}
}