{
  "type": "Feature",
  "properties": {
    "iso:country":"AT",
    "sg:address":"Wiener Str 44",
    "sg:city":"Oberwart",
    "sg:orig_category":"Zeitungen U Zeitschriften",
    "sg:phone":"+43 4333 5235001",
    "sg:postcode":"7400",
    "sg:province":"Burgenland",
    "wof:name":"OZ Oberwarter Zeitung - Die Unabh\u00e4ngige",
    "wof:placetype":"venue"
},
  "geometry": {"coordinates":[16.2070522308,47.2922706604],"type":"Point"}
}