{
  "type": "Feature",
  "properties": {
    "addr:full":"Eichendorffstr 68 Linz Ober\u00f6sterreich 4020",
    "addr:housenumber":"68",
    "addr:postcode":"4020",
    "addr:street":"Eichendorffstr",
    "iso:country":"AT",
    "sg:address":"Eichendorffstr 68",
    "sg:city":"Linz",
    "sg:orig_category":"Biologische Produkte",
    "sg:phone":"+43 4373 2342643",
    "sg:postcode":"4020",
    "sg:province":"Ober\u00f6sterreich",
    "wof:name":"Kr\u00e4uterparadies Eichenauer",
    "wof:placetype":"venue"
},
  "geometry": {"coordinates":[14.2918787003,48.266910553],"type":"Point"}
}