{
  "type": "Feature",
  "properties": {
    "addr:full":"Schachenweg 25 Werndorf Steiermark 8402",
    "addr:housenumber":"25",
    "addr:postcode":"8402",
    "addr:street":"Schachenweg",
    "iso:country":"AT",
    "sg:address":"Schachenweg 25",
    "sg:city":"Werndorf",
    "sg:orig_category":"Luftburgen",
    "sg:phone":"+43 4366 45345099",
    "sg:postcode":"8402",
    "sg:province":"Steiermark",
    "sg:website":"kirchenweb.at/kinderanimation",
    "wof:name":"Hupfburg Kronawetter",
    "wof:placetype":"venue"
},
  "geometry": {"coordinates":[15.486120224,46.9362373352],"type":"Point"}
}