{
  "type": "Feature",
  "properties": {
    "addr:full":"Kornmarktstr 14 Bregenz Vorarlberg 6900",
    "addr:housenumber":"14",
    "addr:postcode":"6900",
    "addr:street":"Kornmarktstr",
    "iso:country":"AT",
    "sg:address":"Kornmarktstr 14",
    "sg:city":"Bregenz",
    "sg:orig_category":"Banken U Sparkassen",
    "sg:phone":"+43 4355 7443885",
    "sg:postcode":"6900",
    "sg:province":"Vorarlberg",
    "wof:name":"Raiffeisen Direkt Service Vlbg GmbH",
    "wof:placetype":"venue"
},
  "geometry": {"coordinates":[9.7481813431,47.5045585632],"type":"Point"}
}