{
  "type": "Feature",
  "properties": {
    "iso:country":"AT",
    "sg:address":"Bahnhofstrasse 22",
    "sg:city":"Wels",
    "sg:classifiers":[
        {
            "category":"Utilities",
            "subcategory":"Mobile Phone",
            "type":"Services"
        }
    ],
    "sg:phone":"+43 7242 46839",
    "sg:postcode":"4600",
    "sg:province":"Ober\u00f6sterreich",
    "sg:tags":[
        "battery",
        "operated",
        "clock"
    ],
    "wof:name":"Krabath GmbH",
    "wof:placetype":"venue"
},
  "geometry": {"coordinates":[14.0251331329,48.1622085571],"type":"Point"}
}