{
  "type": "Feature",
  "properties": {
    "addr:full":"Dippersdorfer Str 24 Ziersdorf Nieder\u00f6sterreich 3710",
    "addr:housenumber":"24",
    "addr:postcode":"3710",
    "addr:street":"Str",
    "iso:country":"AT",
    "sg:address":"Dippersdorfer Str 24",
    "sg:city":"Ziersdorf",
    "sg:orig_category":"Kosmetikanwendungsberatung",
    "sg:phone":"+43 2956 3229",
    "sg:postcode":"3710",
    "sg:province":"Nieder\u00f6sterreich",
    "wof:name":"Engelmaier Gertrude",
    "wof:placetype":"venue"
},
  "geometry": {"coordinates":[15.9337596893,48.5250167847],"type":"Point"}
}