{
  "type": "Feature",
  "properties": {
    "addr:full":"Rudolf-Biebl-Str 26 Salzburg Salzburg 5020",
    "addr:housenumber":"26",
    "addr:postcode":"5020",
    "addr:street":"Rudolf-Biebl-Str;Salzburg",
    "iso:country":"AT",
    "sg:address":"Rudolf-Biebl-Str 26",
    "sg:city":"Salzburg",
    "sg:orig_category":"Geschenkartikel",
    "sg:phone":"+43 4367 63063092",
    "sg:postcode":"5020",
    "sg:province":"Salzburg",
    "wof:name":"Schatzkistl - Bernjus Marcel",
    "wof:placetype":"venue"
},
  "geometry": {"coordinates":[13.0267190933,47.8092269897],"type":"Point"}
}