{
  "type": "Feature",
  "properties": {
    "addr:full":"Engerthstr 152 Wien Wien 1020",
    "addr:housenumber":"152",
    "addr:postcode":"1020",
    "iso:country":"AT",
    "sg:address":"Engerthstr 152",
    "sg:city":"Wien",
    "sg:orig_category":"Botendienste",
    "sg:phone":"+43 4312 166262",
    "sg:postcode":"1020",
    "sg:province":"Wien",
    "sg:website":"merkur-trans.at",
    "wof:name":"MERKUR-TRANS Funkbotendienst GmbH",
    "wof:placetype":"venue"
},
  "geometry": {"coordinates":[16.3968048096,48.2296905518],"type":"Point"}
}