{
  "type": "Feature",
  "properties": {
    "addr:full":"Rembrandtstr 17/7 Wien Wien 1020",
    "addr:housenumber":"17 / 7",
    "addr:postcode":"1020",
    "addr:street":"Rembrandtstr",
    "iso:country":"AT",
    "sg:address":"Rembrandtstr 17/7",
    "sg:city":"Wien",
    "sg:orig_category":"Astrologie",
    "sg:phone":"+43 1 3333407",
    "sg:postcode":"1020",
    "sg:province":"Wien",
    "wof:name":"Brandhuber Werner",
    "wof:placetype":"venue"
},
  "geometry": {"coordinates":[16.3713493347,48.2216186523],"type":"Point"}
}