{
  "type": "Feature",
  "properties": {
    "iso:country":"AT",
    "sg:address":"Unterrotte 57",
    "sg:city":"St. Jakob in Defereggen",
    "sg:orig_category":"Fleischhauereien",
    "sg:phone":"+43 4348 735170",
    "sg:postcode":"9963",
    "sg:province":"Tirol",
    "wof:name":"Schett Ernst",
    "wof:placetype":"venue"
},
  "geometry": {"coordinates":[12.3313846588,46.9159965515],"type":"Point"}
}