{
  "type": "Feature",
  "properties": {
    "addr:full":"Vassacher Str 20 Villach K\u00e4rnten 9500",
    "addr:housenumber":"20",
    "addr:postcode":"9500",
    "addr:street":"Str;Kaernten",
    "iso:country":"AT",
    "sg:address":"Vassacher Str 20",
    "sg:city":"Villach",
    "sg:classifiers":[
        {
            "category":"Taxi",
            "type":"Transportation"
        }
    ],
    "sg:phone":"+43 4242 22233",
    "sg:postcode":"9500",
    "sg:province":"K\u00e4rnten",
    "sg:tags":[
        "personentransporte",
        "u"
    ],
    "wof:name":"Taxi Oman",
    "wof:placetype":"venue"
},
  "geometry": {"coordinates":[13.8452119827,46.6256980896],"type":"Point"}
}