{
  "type": "Feature",
  "properties": {
    "iso:country":"AT",
    "sg:address":"Michael Bernhard-G 3",
    "sg:city":"Wien",
    "sg:orig_category":"Non-Classified Establishments",
    "sg:phone":"+43 1 8174700",
    "sg:postcode":"1120",
    "sg:province":"Wien",
    "wof:name":"Pfingstgemeinde neutest-christl Kephas-Gemeinde",
    "wof:placetype":"venue"
},
  "geometry": {"coordinates":[16.3336296082,48.1835632324],"type":"Point"}
}