{
  "type": "Feature",
  "properties": {
    "addr:full":"Bahnhofstrasse 16 Aschach an der Steyr Ober\u00f6sterreich 4421",
    "addr:housenumber":"16",
    "addr:postcode":"4421",
    "addr:street":"Bahnhofstrasse",
    "iso:country":"AT",
    "sg:address":"Bahnhofstrasse 16",
    "sg:city":"Aschach an der Steyr",
    "sg:orig_category":"Cutter Heads For Woodworking",
    "sg:phone":"+43 7259 24770",
    "sg:postcode":"4421",
    "sg:province":"Ober\u00f6sterreich",
    "wof:name":"Walter M. Strasek Stern - Werkzeugfabrik",
    "wof:placetype":"venue"
},
  "geometry": {"coordinates":[14.3250331879,48.019695282],"type":"Point"}
}