{
  "type": "Feature",
  "properties": {
    "iso:country":"AT",
    "sg:address":"Klostergasse 5",
    "sg:city":"Dornbirn",
    "sg:orig_category":"Houses, Ecological",
    "sg:phone":"+43 5572 26911",
    "sg:postcode":"6850",
    "sg:province":"Vorarlberg",
    "sg:website":"pro-vital.at",
    "wof:name":"Pro Vital",
    "wof:placetype":"venue"
},
  "geometry": {"coordinates":[9.7406663895,47.415309906],"type":"Point"}
}