{
  "type": "Feature",
  "properties": {
    "addr:full":"Hauptstr 53 Wien Wien 1140",
    "addr:housenumber":"53",
    "addr:postcode":"1140",
    "addr:street":"Hauptstr",
    "iso:country":"AT",
    "sg:address":"Hauptstr 53",
    "sg:city":"Wien",
    "sg:orig_category":"Autoreparatur",
    "sg:phone":"+43 1 9796959",
    "sg:postcode":"1140",
    "sg:province":"Wien",
    "wof:name":"Z.M. Markovic KEG",
    "wof:placetype":"venue"
},
  "geometry": {"coordinates":[16.2210502625,48.2093925476],"type":"Point"}
}