{
  "type": "Feature",
  "properties": {
    "addr:full":"Karlsg 11/126 Wien Wien 1040",
    "addr:housenumber":"11 / 126",
    "addr:postcode":"1040",
    "addr:street":"Karlsg",
    "iso:country":"AT",
    "sg:address":"Karlsg 11/126",
    "sg:city":"Wien",
    "sg:orig_category":"Institute",
    "sg:phone":"+43 4315 880112601",
    "sg:postcode":"1040",
    "sg:province":"Wien",
    "wof:name":"Inst f Kartographie u Geo-Medientechnik TU Wien",
    "wof:placetype":"venue"
},
  "geometry": {"coordinates":[16.3671455383,48.1940345764],"type":"Point"}
}