{
  "type": "Feature",
  "properties": {
    "iso:country":"AT",
    "sg:address":"Nr 190",
    "sg:city":"Lochen",
    "sg:orig_category":"Lebensmittel / Einzelhandel",
    "sg:phone":"+43 7745 8696",
    "sg:postcode":"5221",
    "sg:province":"Ober\u00f6sterreich",
    "wof:name":"Spar-Markt Inh Bernhard P\u00f6schl",
    "wof:placetype":"venue"
},
  "geometry": {"coordinates":[13.1802692413,48.0075187683],"type":"Point"}
}