{
  "type": "Feature",
  "properties": {
    "addr:full":"Margaritenweg 5 Bad Kleinkirchheim K\u00e4rnten 9546",
    "addr:housenumber":"5",
    "addr:postcode":"9546",
    "addr:street":"Margaritenweg",
    "iso:country":"AT",
    "sg:address":"Margaritenweg 5",
    "sg:city":"Bad Kleinkirchheim",
    "sg:orig_category":"Volksschulen",
    "sg:phone":"+43 4240 818215",
    "sg:postcode":"9546",
    "sg:province":"K\u00e4rnten",
    "wof:name":"Volksschule",
    "wof:placetype":"venue"
},
  "geometry": {"coordinates":[13.7968873978,46.8150367737],"type":"Point"}
}