{
  "type": "Feature",
  "properties": {
    "addr:full":"M\u00fcsinenstr 53 Sulz-R\u00f6this Vorarlberg 6832",
    "addr:housenumber":"53",
    "addr:postcode":"6832",
    "addr:street":"Muesinenstr",
    "iso:country":"AT",
    "sg:address":"M\u00fcsinenstr 53",
    "sg:city":"Sulz-R\u00f6this",
    "sg:orig_category":"Behinderungen / Leben Mit Behinderungen",
    "sg:phone":"+43 4355 22411680",
    "sg:postcode":"6832",
    "sg:province":"Vorarlberg",
    "wof:name":"Lebenshilfe Vorderland - Fachwerkst\u00e4tte Sulz",
    "wof:placetype":"venue"
},
  "geometry": {"coordinates":[9.6658267975,47.2794189453],"type":"Point"}
}