{
  "type": "Feature",
  "properties": {
    "iso:country":"AT",
    "sg:address":"Goldschlagstr 135/37",
    "sg:city":"Wien",
    "sg:orig_category":"Reinigungsservice",
    "sg:phone":"+43 1 9852054",
    "sg:postcode":"1140",
    "sg:province":"Wien",
    "wof:name":"PBL Schankservice GesmbH",
    "wof:placetype":"venue"
},
  "geometry": {"coordinates":[16.3120708466,48.1954841614],"type":"Point"}
}