{
  "type": "Feature",
  "properties": {
    "addr:full":"Jakob Jehly-Str 12a Bludenz Vorarlberg 6700",
    "addr:housenumber":"12a",
    "addr:postcode":"6700",
    "iso:country":"AT",
    "sg:address":"Jakob Jehly-Str 12a",
    "sg:city":"Bludenz",
    "sg:orig_category":"Maler, Anstreicher U Lackierer, Fassadenanstriche",
    "sg:phone":"+43 4355 52667170",
    "sg:postcode":"6700",
    "sg:province":"Vorarlberg",
    "wof:name":"Bartenbach Hanno",
    "wof:placetype":"venue"
},
  "geometry": {"coordinates":[9.8124523163,47.1607627869],"type":"Point"}
}