{
  "type": "Feature",
  "properties": {
    "addr:full":"Wohlmayrg 2 Ried im Innkreis Ober\u00f6sterreich 4910",
    "addr:housenumber":"2",
    "addr:postcode":"4910",
    "addr:street":"Wohlmayrg",
    "iso:country":"AT",
    "sg:address":"Wohlmayrg 2",
    "sg:city":"Ried im Innkreis",
    "sg:orig_category":"Friseure U Frisiersalons",
    "sg:phone":"+43 4377 5284243",
    "sg:postcode":"4910",
    "sg:province":"Ober\u00f6sterreich",
    "wof:name":"Schnittpunkt",
    "wof:placetype":"venue"
},
  "geometry": {"coordinates":[13.4877319336,48.2076721191],"type":"Point"}
}