{
  "type": "Feature",
  "properties": {
    "addr:full":"Salzachuferstr 27-35 Zell am See Salzburg 5700",
    "addr:postcode":"5700",
    "addr:street":"Salzburg",
    "iso:country":"AT",
    "sg:address":"Salzachuferstr 27-35",
    "sg:city":"Zell am See",
    "sg:orig_category":"Abfall-, Entsorgungs- U Deponietechnik",
    "sg:phone":"+43 4365 4257971",
    "sg:postcode":"5700",
    "sg:province":"Salzburg",
    "wof:name":"Zemka Zentrale M\u00fcllkl\u00e4rschlammverwertungsanlagen GesmbH",
    "wof:placetype":"venue"
},
  "geometry": {"coordinates":[12.7908649445,47.282459259],"type":"Point"}
}