{
  "type": "Feature",
  "properties": {
    "addr:full":"Raiffeisenstr 258 Tamsweg Salzburg 5580",
    "addr:housenumber":"258",
    "addr:postcode":"5580",
    "addr:street":"Tamsweg Salzburg",
    "iso:country":"AT",
    "sg:address":"Raiffeisenstr 258",
    "sg:city":"Tamsweg",
    "sg:orig_category":"Tiefbau",
    "sg:phone":"+43 4364 742256",
    "sg:postcode":"5580",
    "sg:province":"Salzburg",
    "wof:name":"Forsttechnischer Dienst f Wildbach- u Lawinenverbauung",
    "wof:placetype":"venue"
},
  "geometry": {"coordinates":[13.8101902008,47.1263389587],"type":"Point"}
}