{
  "type": "Feature",
  "properties": {
    "addr:full":"Hackeng 20 Wien Wien 1150",
    "addr:housenumber":"20",
    "addr:postcode":"1150",
    "addr:street":"Hackeng",
    "iso:country":"AT",
    "sg:address":"Hackeng 20",
    "sg:city":"Wien",
    "sg:classifiers":[
        {
            "category":"Travel",
            "subcategory":"Hotels & Motels",
            "type":"Entertainment"
        }
    ],
    "sg:phone":"+43 4319 8242720",
    "sg:postcode":"1150",
    "sg:province":"Wien",
    "wof:name":"Hotel Stadthalle",
    "wof:placetype":"venue"
},
  "geometry": {"coordinates":[16.3337879181,48.1992225647],"type":"Point"}
}