{
  "type": "Feature",
  "properties": {
    "addr:full":"Friedhofstr 7 Hohenems Vorarlberg 6845",
    "addr:housenumber":"7",
    "addr:postcode":"6845",
    "addr:street":"Friedhofstr",
    "iso:country":"AT",
    "sg:address":"Friedhofstr 7",
    "sg:city":"Hohenems",
    "sg:orig_category":"Stickereien",
    "sg:phone":"+43 4355 7673335",
    "sg:postcode":"6845",
    "sg:province":"Vorarlberg",
    "wof:name":"Hermann, Hagen & Sarac Stickerei GmbH",
    "wof:placetype":"venue"
},
  "geometry": {"coordinates":[9.6871061325,47.3584899902],"type":"Point"}
}