{
  "type": "Feature",
  "properties": {
    "iso:country":"AT",
    "sg:address":"Nr 33",
    "sg:city":"Maria Neustift",
    "sg:orig_category":"Lebensmittel / Einzelhandel",
    "sg:phone":"+43 7250 216",
    "sg:postcode":"4443",
    "sg:province":"Ober\u00f6sterreich",
    "wof:name":"Sport und Kaufhaus Stubauer Ferdinand",
    "wof:placetype":"venue"
},
  "geometry": {"coordinates":[14.6069536209,47.9375648499],"type":"Point"}
}