{
  "type": "Feature",
  "properties": {
    "addr:full":"Veiderfeldweg 9 Rauris Salzburg 5661",
    "addr:housenumber":"9",
    "addr:postcode":"5661",
    "addr:street":"Veiderfeldweg;Salzburg",
    "iso:country":"AT",
    "sg:address":"Veiderfeldweg 9",
    "sg:city":"Rauris",
    "sg:orig_category":"Tischlereien",
    "sg:phone":"+43 4365 446375",
    "sg:postcode":"5661",
    "sg:province":"Salzburg",
    "wof:name":"Potche Johann",
    "wof:placetype":"venue"
},
  "geometry": {"coordinates":[12.9958734512,47.225353241],"type":"Point"}
}