{
  "type": "Feature",
  "properties": {
    "addr:full":"Hauptstr 39 Raggendorf Nieder\u00f6sterreich 2215",
    "addr:housenumber":"39",
    "addr:postcode":"2215",
    "addr:street":"Hauptstr",
    "iso:country":"AT",
    "sg:address":"Hauptstr 39",
    "sg:city":"Raggendorf",
    "sg:orig_category":"Non-Classified Establishments",
    "sg:phone":"+43 2289 2306",
    "sg:postcode":"2215",
    "sg:province":"Nieder\u00f6sterreich",
    "wof:name":"Pfarramt",
    "wof:placetype":"venue"
},
  "geometry": {"coordinates":[16.6566905975,48.3948173523],"type":"Point"}
}