{
  "type": "Feature",
  "properties": {
    "addr:full":"Svetelskystr 16/9 Wien Wien 1110",
    "addr:housenumber":"16 / 9",
    "addr:postcode":"1110",
    "addr:street":"Svetelskystr",
    "iso:country":"AT",
    "sg:address":"Svetelskystr 16/9",
    "sg:city":"Wien",
    "sg:orig_category":"Innenausbau",
    "sg:phone":"+43 1 3344988",
    "sg:postcode":"1110",
    "sg:province":"Wien",
    "wof:name":"RASKOV Innenausbau KEG",
    "wof:placetype":"venue"
},
  "geometry": {"coordinates":[16.4658222198,48.1540641785],"type":"Point"}
}