{
  "type": "Feature",
  "properties": {
    "addr:full":"Fabrikstra\u00dfe 15 Deutschlandsberg Steiermark 8530",
    "addr:housenumber":"15",
    "addr:postcode":"8530",
    "addr:street":"Fabrikstrasse",
    "iso:country":"AT",
    "sg:address":"Fabrikstra\u00dfe 15",
    "sg:city":"Deutschlandsberg",
    "sg:orig_category":"Dienstleistungen, Druck U Beschriftungen",
    "sg:postcode":"8530",
    "sg:province":"Steiermark",
    "sg:website":"http://www.simadruck.at/",
    "wof:name":"Simadruck - Weststeirische Rundschau",
    "wof:placetype":"venue"
},
  "geometry": {"coordinates":[15.2145681381,46.8173942566],"type":"Point"}
}