{
  "type": "Feature",
  "properties": {
    "addr:full":"Matznergasse 17 Wien Wien 1140",
    "addr:housenumber":"17",
    "addr:postcode":"1140",
    "addr:street":"Matznergasse",
    "iso:country":"AT",
    "sg:address":"Matznergasse 17",
    "sg:city":"Wien",
    "sg:classifiers":[
        {
            "category":"Landmark",
            "subcategory":"City Walls",
            "type":"Public Place"
        }
    ],
    "sg:phone":"+43 1 98116400",
    "sg:postcode":"1140",
    "sg:province":"Wien",
    "sg:tags":[
        "map"
    ],
    "sg:website":"plan.at/",
    "wof:name":"plan.at Ges. f\u00fcr geographische InternetanwendungenmbH",
    "wof:placetype":"venue"
},
  "geometry": {"coordinates":[16.3035850525,48.1971244812],"type":"Point"}
}