{
  "type": "Feature",
  "properties": {
    "addr:full":"Schuhmeierstr 23 Wilhelmsburg an der Traisen Nieder\u00f6sterreich 3150",
    "addr:housenumber":"23",
    "addr:postcode":"3150",
    "addr:street":"Schuhmeierstr;An",
    "iso:country":"AT",
    "sg:address":"Schuhmeierstr 23",
    "sg:city":"Wilhelmsburg an der Traisen",
    "sg:orig_category":"Autohandel",
    "sg:phone":"+43 4327 463583",
    "sg:postcode":"3150",
    "sg:province":"Nieder\u00f6sterreich",
    "wof:name":"Auto Spitzer",
    "wof:placetype":"venue"
},
  "geometry": {"coordinates":[15.5997419357,48.0950965881],"type":"Point"}
}