{
  "type": "Feature",
  "properties": {
    "addr:full":"Ruckerg 59 Wien Wien 1120",
    "addr:housenumber":"59",
    "addr:postcode":"1120",
    "addr:street":"Ruckerg",
    "iso:country":"AT",
    "sg:address":"Ruckerg 59",
    "sg:city":"Wien",
    "sg:orig_category":"Webdesign",
    "sg:phone":"+43 699 11874074",
    "sg:postcode":"1120",
    "sg:province":"Wien",
    "wof:name":"TP-Media",
    "wof:placetype":"venue"
},
  "geometry": {"coordinates":[16.3264122009,48.1760025024],"type":"Point"}
}