{
  "type": "Feature",
  "properties": {
    "addr:full":"Brandauerweg 9 Stra\u00dfgang Steiermark 8054",
    "addr:housenumber":"9",
    "addr:postcode":"8054",
    "addr:street":"Brandauerweg",
    "iso:country":"AT",
    "sg:address":"Brandauerweg 9",
    "sg:city":"Stra\u00dfgang",
    "sg:orig_category":"Lasertechnik",
    "sg:phone":"+43 316 284331",
    "sg:postcode":"8054",
    "sg:province":"Steiermark",
    "wof:name":"Edelsbrunner Helmut Ing",
    "wof:placetype":"venue"
},
  "geometry": {"coordinates":[15.4076147079,47.0265960693],"type":"Point"}
}