{
  "type": "Feature",
  "properties": {
    "addr:full":"Nr 198 Weitensfeld K\u00e4rnten 9344",
    "addr:postcode":"9344",
    "addr:street":"Nr 198 Weitensfeld Kaernten",
    "iso:country":"AT",
    "sg:address":"Nr 198",
    "sg:city":"Weitensfeld",
    "sg:orig_category":"Banken U Sparkassen",
    "sg:phone":"+43 5 010030869",
    "sg:postcode":"9344",
    "sg:province":"K\u00e4rnten",
    "wof:name":"K\u00e4rntner Sparkasse AG",
    "wof:placetype":"venue"
},
  "geometry": {"coordinates":[14.193403244,46.8474197388],"type":"Point"}
}