{
  "type": "Feature",
  "properties": {
    "iso:country":"AT",
    "sg:address":"Lung\u00f6tzer Landesstr 108",
    "sg:city":"Annaberg",
    "sg:orig_category":"Tankstellen",
    "sg:phone":"+43 6463 60036",
    "sg:postcode":"5524",
    "sg:province":"Salzburg",
    "wof:name":"BP Austria Marketing GmbH",
    "wof:placetype":"venue"
},
  "geometry": {"coordinates":[13.4312047958,47.513458252],"type":"Point"}
}