{
  "type": "Feature",
  "properties": {
    "iso:country":"AT",
    "sg:address":"Bichlweg 19",
    "sg:city":"Fiss",
    "sg:orig_category":"Pensionen / Privatzimmer",
    "sg:phone":"+43 5476 6292",
    "sg:postcode":"6533",
    "sg:province":"Tirol",
    "wof:name":"Tilg Christian Ing",
    "wof:placetype":"venue"
},
  "geometry": {"coordinates":[10.6241168976,47.0546913147],"type":"Point"}
}