{
  "type": "Feature",
  "properties": {
    "addr:full":"Wiedner Hauptstr 65 Wien Wien 1040",
    "addr:housenumber":"65",
    "addr:postcode":"1040",
    "addr:street":"Hauptstr",
    "iso:country":"AT",
    "sg:address":"Wiedner Hauptstr 65",
    "sg:city":"Wien",
    "sg:orig_category":"Banken U Sparkassen",
    "sg:phone":"+43 5 050538670",
    "sg:postcode":"1040",
    "sg:province":"Wien",
    "wof:name":"Bank Austria Creditanstalt AG",
    "wof:placetype":"venue"
},
  "geometry": {"coordinates":[16.3664455414,48.1898422241],"type":"Point"}
}