{
  "type": "Feature",
  "properties": {
    "addr:full":"Nikolaus Gassner-Str 565 Kaprun Salzburg 5710",
    "addr:housenumber":"565",
    "addr:postcode":"5710",
    "addr:street":"Kaprun Salzburg",
    "iso:country":"AT",
    "sg:address":"Nikolaus Gassner-Str 565",
    "sg:city":"Kaprun",
    "sg:orig_category":"Pensionen / Privatzimmer",
    "sg:phone":"+43 6547 8601",
    "sg:postcode":"5710",
    "sg:province":"Salzburg",
    "wof:name":"Salzburgerhof Fr\u00fchst\u00fcckspension",
    "wof:placetype":"venue"
},
  "geometry": {"coordinates":[12.7514266968,47.2672996521],"type":"Point"}
}