{
  "type": "Feature",
  "properties": {
    "addr:full":"Langg 30 Imst Tirol 6460",
    "addr:housenumber":"30",
    "addr:postcode":"6460",
    "addr:street":"Langg;Tirol",
    "iso:country":"AT",
    "sg:address":"Langg 30",
    "sg:city":"Imst",
    "sg:orig_category":"Lebensmittel / Einzelhandel",
    "sg:phone":"+43 4354 1263184",
    "sg:postcode":"6460",
    "sg:province":"Tirol",
    "wof:name":"Hofer KG",
    "wof:placetype":"venue"
},
  "geometry": {"coordinates":[10.737487793,47.2392234802],"type":"Point"}
}