{
  "type": "Feature",
  "properties": {
    "addr:full":"Wildgansg 16 Wieselburg an der Erlauf Nieder\u00f6sterreich 3250",
    "addr:housenumber":"16",
    "addr:postcode":"3250",
    "addr:street":"Wildgansg",
    "iso:country":"AT",
    "sg:address":"Wildgansg 16",
    "sg:city":"Wieselburg an der Erlauf",
    "sg:orig_category":"Psychotherapie",
    "sg:phone":"+43 4374 1654488",
    "sg:postcode":"3250",
    "sg:province":"Nieder\u00f6sterreich",
    "wof:name":"Oppolzer-Graf Hedwig",
    "wof:placetype":"venue"
},
  "geometry": {"coordinates":[15.1365604401,48.1347618103],"type":"Point"}
}