{
  "type": "Feature",
  "properties": {
    "iso:country":"AT",
    "sg:address":"Mariahilfpark 1/105",
    "sg:city":"Innsbruck",
    "sg:orig_category":"Gesundheit / Allgemeine Informationsstellen",
    "sg:phone":"+43 512 287445",
    "sg:postcode":"6020",
    "sg:province":"Tirol",
    "wof:name":"Feldenkrais Methode - Mag Heidelinde Androschin",
    "wof:placetype":"venue"
},
  "geometry": {"coordinates":[11.3869123459,47.2676620483],"type":"Point"}
}