{
  "type": "Feature",
  "properties": {
    "addr:full":"Dorfstr 36 Kaltenbach Tirol 6272",
    "addr:housenumber":"36",
    "addr:postcode":"6272",
    "addr:street":"Dorfstr",
    "iso:country":"AT",
    "sg:address":"Dorfstr 36",
    "sg:city":"Kaltenbach",
    "sg:classifiers":[
        {
            "category":"Restaurant",
            "type":"Food & Drink"
        }
    ],
    "sg:phone":"+43 5283 2215",
    "sg:postcode":"6272",
    "sg:province":"Tirol",
    "wof:name":"La Pasta Nudelbar",
    "wof:placetype":"venue"
},
  "geometry": {"coordinates":[11.8865890503,47.291305542],"type":"Point"}
}