{
  "type": "Feature",
  "properties": {
    "addr:full":"Lichtenbergstr 67 Linz Ober\u00f6sterreich 4040",
    "addr:housenumber":"67",
    "addr:postcode":"4040",
    "addr:street":"Lichtenbergstr",
    "iso:country":"AT",
    "sg:address":"Lichtenbergstr 67",
    "sg:city":"Linz",
    "sg:orig_category":"Sonnenschutzanlagen",
    "sg:phone":"+43 7239 20210",
    "sg:postcode":"4040",
    "sg:province":"Ober\u00f6sterreich",
    "wof:name":"Kragl GmbH",
    "wof:placetype":"venue"
},
  "geometry": {"coordinates":[14.3393220901,48.3345298767],"type":"Point"}
}