{
  "type": "Feature",
  "properties": {
    "addr:full":"Nr 39d Pertisau Tirol 6213",
    "addr:postcode":"6213",
    "addr:street":"Nr;Pertisau",
    "iso:country":"AT",
    "sg:address":"Nr 39d",
    "sg:city":"Pertisau",
    "sg:orig_category":"Appartements / Ferienwohnungen",
    "sg:phone":"+43 5243 5841",
    "sg:postcode":"6213",
    "sg:province":"Tirol",
    "wof:name":"Appatmenthaus Gabi",
    "wof:placetype":"venue"
},
  "geometry": {"coordinates":[11.6961479187,47.4396896362],"type":"Point"}
}