{
  "type": "Feature",
  "properties": {
    "addr:full":"W\u00fcsteg 65 Pfaffst\u00e4tten Nieder\u00f6sterreich 2511",
    "addr:housenumber":"65",
    "addr:postcode":"2511",
    "addr:street":"Wuesteg;Niederoesterreich",
    "iso:country":"AT",
    "sg:address":"W\u00fcsteg 65",
    "sg:city":"Pfaffst\u00e4tten",
    "sg:orig_category":"Pensionen / Privatzimmer",
    "sg:phone":"+43 2252 243960",
    "sg:postcode":"2511",
    "sg:province":"Nieder\u00f6sterreich",
    "wof:name":"Pension Ursula",
    "wof:placetype":"venue"
},
  "geometry": {"coordinates":[-80.22747802729999,40.6339416504],"type":"Point"}
}