{
  "type": "Feature",
  "properties": {
    "iso:country":"AT",
    "sg:address":"Rosennockstr 16",
    "sg:city":"Bad Kleinkirchheim",
    "sg:orig_category":"Pensionen / Privatzimmer",
    "sg:phone":"+43 4240 537",
    "sg:postcode":"9546",
    "sg:province":"K\u00e4rnten",
    "wof:name":"Landhaus Zwatz",
    "wof:placetype":"venue"
},
  "geometry": {"coordinates":[13.7642822266,46.8358955383],"type":"Point"}
}