{
  "type": "Feature",
  "properties": {
    "addr:full":"Rechte Wienzeile 33 Wien Wien 1040",
    "addr:housenumber":"33",
    "addr:postcode":"1040",
    "addr:street":"Rechte Wienzeile",
    "iso:country":"AT",
    "sg:address":"Rechte Wienzeile 33",
    "sg:city":"Wien",
    "sg:orig_category":"Bierlokale-Pubs",
    "sg:phone":"+43 1 5869466",
    "sg:postcode":"1040",
    "sg:province":"Wien",
    "wof:name":"Omega Pub",
    "wof:placetype":"venue"
},
  "geometry": {"coordinates":[16.3612670898,48.197013855],"type":"Point"}
}