{
  "type": "Feature",
  "properties": {
    "iso:country":"AT",
    "sg:address":"Anzengruberstr 39",
    "sg:city":"Klagenfurt",
    "sg:orig_category":"Werbeagenturen",
    "sg:phone":"+43 463 242426",
    "sg:postcode":"9020",
    "sg:province":"K\u00e4rnten",
    "wof:name":"TXT B\u00fcro",
    "wof:placetype":"venue"
},
  "geometry": {"coordinates":[14.2759618759,46.6210823059],"type":"Point"}
}