{
  "type": "Feature",
  "properties": {
    "iso:country":"AT",
    "sg:address":"Postgasse 1+3",
    "sg:city":"Hallein",
    "sg:orig_category":"Freizeit, Sport",
    "sg:postcode":"5400",
    "sg:province":"Salzburg",
    "sg:website":"http://www.tauchschule.com/tauchsch.htm",
    "wof:name":"Tauchschule Kaisermayr",
    "wof:placetype":"venue"
},
  "geometry": {"coordinates":[13.0937538147,47.682094574],"type":"Point"}
}