{
  "type": "Feature",
  "properties": {
    "addr:full":"Hauptpl 1 Melk Nieder\u00f6sterreich 3390",
    "addr:housenumber":"1",
    "addr:postcode":"3390",
    "addr:street":"Hauptpl",
    "iso:country":"AT",
    "sg:address":"Hauptpl 1",
    "sg:city":"Melk",
    "sg:classifiers":[
        {
            "category":"Travel",
            "subcategory":"Hotels & Motels",
            "type":"Entertainment"
        }
    ],
    "sg:phone":"+43 2752 524750",
    "sg:postcode":"3390",
    "sg:province":"Nieder\u00f6sterreich",
    "wof:name":"Hotel Stadt Melk Stallberger GesmbH & Co KG",
    "wof:placetype":"venue"
},
  "geometry": {"coordinates":[15.3295240402,48.2272186279],"type":"Point"}
}