{
  "type": "Feature",
  "properties": {
    "iso:country":"AT",
    "sg:address":"Hauptstr 29",
    "sg:city":"Gro\u00dfru\u00dfbach",
    "sg:orig_category":"Feuerwehren",
    "sg:phone":"+43 2263 6622",
    "sg:postcode":"2114",
    "sg:province":"Nieder\u00f6sterreich",
    "wof:name":"Freiwillige Feuerwehr Gro\u00dfru\u00dfbach",
    "wof:placetype":"venue"
},
  "geometry": {"coordinates":[-83.3486022949,43.8284263611],"type":"Point"}
}