{
  "type": "Feature",
  "properties": {
    "addr:full":"Edmund-Hofbauer-Str 22 Krems an der Donau Nieder\u00f6sterreich 3500",
    "addr:housenumber":"22",
    "addr:postcode":"3500",
    "addr:street":"Edmund-Hofbauer-Str",
    "iso:country":"AT",
    "sg:address":"Edmund-Hofbauer-Str 22",
    "sg:city":"Krems an der Donau",
    "sg:orig_category":"Handelsagenturen",
    "sg:phone":"+43 2732 72549",
    "sg:postcode":"3500",
    "sg:province":"Nieder\u00f6sterreich",
    "wof:name":"Netzberger Renate",
    "wof:placetype":"venue"
},
  "geometry": {"coordinates":[15.5984296799,48.4072189331],"type":"Point"}
}