{
  "type": "Feature",
  "properties": {
    "addr:full":"Bandg 2 Wien Wien 1070",
    "addr:housenumber":"2",
    "addr:postcode":"1070",
    "addr:street":"Bandg",
    "iso:country":"AT",
    "sg:address":"Bandg 2",
    "sg:city":"Wien",
    "sg:classifiers":[
        {
            "category":"Internet Cafe",
            "subcategory":"None",
            "type":"Food & Drink"
        }
    ],
    "sg:phone":"+43 1 5237288",
    "sg:postcode":"1070",
    "sg:province":"Wien",
    "wof:name":"BluePlanet Information & Communication Systems GmbH",
    "wof:placetype":"venue"
},
  "geometry": {"coordinates":[16.3383293152,48.2016792297],"type":"Point"}
}