{
  "type": "Feature",
  "properties": {
    "iso:country":"AT",
    "sg:address":"Seestr 8",
    "sg:city":"Kirchberg in Tirol",
    "sg:orig_category":"Pensionen / Privatzimmer",
    "sg:phone":"+43 5357 2416",
    "sg:postcode":"6365",
    "sg:province":"Tirol",
    "wof:name":"Pension Achrainer",
    "wof:placetype":"venue"
},
  "geometry": {"coordinates":[12.3169717789,47.4455566406],"type":"Point"}
}