{
  "type": "Feature",
  "properties": {
    "addr:full":"Hauptstr 104 Krumpendorf K\u00e4rnten 9201",
    "addr:housenumber":"104",
    "addr:postcode":"9201",
    "addr:street":"Hauptstr;Kaernten",
    "iso:country":"AT",
    "sg:address":"Hauptstr 104",
    "sg:city":"Krumpendorf",
    "sg:classifiers":[
        {
            "category":"Travel",
            "subcategory":"Hotels & Motels",
            "type":"Entertainment"
        }
    ],
    "sg:phone":"+43 4229 2279",
    "sg:postcode":"9201",
    "sg:province":"K\u00e4rnten",
    "wof:name":"Hotel K\u00e4rntnerhof",
    "wof:placetype":"venue"
},
  "geometry": {"coordinates":[14.2220096588,46.6270980835],"type":"Point"}
}