{
  "type": "Feature",
  "properties": {
    "addr:full":"Raiffeiseng 3 W\u00fcrnitz Nieder\u00f6sterreich 2112",
    "addr:housenumber":"3",
    "addr:postcode":"2112",
    "addr:street":"Raiffeiseng;Niederoesterreich",
    "iso:country":"AT",
    "sg:address":"Raiffeiseng 3",
    "sg:city":"W\u00fcrnitz",
    "sg:orig_category":"Postservicestellen",
    "sg:phone":"+43 2263 76117",
    "sg:postcode":"2112",
    "sg:province":"Nieder\u00f6sterreich",
    "wof:name":"Postservicestelle W\u00fcrnitz",
    "wof:placetype":"venue"
},
  "geometry": {"coordinates":[16.4248027802,48.4297790527],"type":"Point"}
}