{
  "type": "Feature",
  "properties": {
    "iso:country":"AT",
    "sg:address":"Raiffeiseng 3",
    "sg:city":"W\u00fcrnitz",
    "sg:orig_category":"Postservicestellen",
    "sg:phone":"+43 2263 76117",
    "sg:postcode":"2112",
    "sg:province":"Nieder\u00f6sterreich",
    "wof:name":"Postservicestelle W\u00fcrnitz",
    "wof:placetype":"venue"
},
  "geometry": {"coordinates":[16.4248027802,48.4297790527],"type":"Point"}
}