{
  "type": "Feature",
  "properties": {
    "iso:country":"AT",
    "sg:address":"Bad Haller Strasse 32",
    "sg:city":"Kremsm\u00fcnster",
    "sg:classifiers":[
        {
            "category":"Health Services",
            "subcategory":"Medical Lab",
            "type":"Services"
        }
    ],
    "sg:phone":"+43 7583 67910",
    "sg:postcode":"4550",
    "sg:province":"Ober\u00f6sterreich",
    "sg:tags":[
        "blood",
        "drawing",
        "system"
    ],
    "sg:website":"gbo.com",
    "wof:name":"Greiner Bio-One GmbH",
    "wof:placetype":"venue"
},
  "geometry": {"coordinates":[7.4943199158,50.8699913025],"type":"Point"}
}