{
  "type": "Feature",
  "properties": {
    "addr:full":"Wagnastr 1/1 Leibnitz Steiermark 8430",
    "addr:housenumber":"1 / 1",
    "addr:postcode":"8430",
    "addr:street":"Wagnastr;Steiermark",
    "iso:country":"AT",
    "sg:address":"Wagnastr 1/1",
    "sg:city":"Leibnitz",
    "sg:orig_category":"Suchtberatung / Alkohol, Drogen, Zigaretten",
    "sg:phone":"+43 4334 5272647",
    "sg:postcode":"8430",
    "sg:province":"Steiermark",
    "wof:name":"b a s steirische Gesellschaft f Suchtfragen",
    "wof:placetype":"venue"
},
  "geometry": {"coordinates":[15.5416498184,46.7783699036],"type":"Point"}
}