{
  "type": "Feature",
  "properties": {
    "addr:full":"Neusiedler Str 1 Podersdorf am See Burgenland 7141",
    "addr:housenumber":"1",
    "addr:postcode":"7141",
    "addr:street":"Str",
    "iso:country":"AT",
    "sg:address":"Neusiedler Str 1",
    "sg:city":"Podersdorf am See",
    "sg:orig_category":"Bars-Cafes",
    "sg:phone":"+43 4321 772221",
    "sg:postcode":"7141",
    "sg:province":"Burgenland",
    "wof:name":"Urban Bar",
    "wof:placetype":"venue"
},
  "geometry": {"coordinates":[16.8370933533,47.8546104431],"type":"Point"}
}