{
  "type": "Feature",
  "properties": {
    "iso:country":"AT",
    "sg:address":"Maximilianstr 5",
    "sg:city":"Innsbruck",
    "sg:orig_category":"Fahrschulen",
    "sg:phone":"+43 512 583636",
    "sg:postcode":"6020",
    "sg:province":"Tirol",
    "sg:website":"eigenstiller.at",
    "wof:name":"Eigenstiller Hans Ing",
    "wof:placetype":"venue"
},
  "geometry": {"coordinates":[11.3937034607,47.2624359131],"type":"Point"}
}