{
  "type": "Feature",
  "properties": {
    "addr:full":"Wei\u00dfenbachg 6 Telfs Tirol 6410",
    "addr:housenumber":"6",
    "addr:postcode":"6410",
    "addr:street":"Weissenbachg;Tirol",
    "iso:country":"AT",
    "sg:address":"Wei\u00dfenbachg 6",
    "sg:city":"Telfs",
    "sg:orig_category":"Friseure U Frisiersalons",
    "sg:phone":"+43 5262 62020",
    "sg:postcode":"6410",
    "sg:province":"Tirol",
    "wof:name":"Gabl Hermann",
    "wof:placetype":"venue"
},
  "geometry": {"coordinates":[11.072218895,47.3066978455],"type":"Point"}
}