{
  "type": "Feature",
  "properties": {
    "addr:full":"Strozzig 3 Wien Wien 1080",
    "addr:housenumber":"3",
    "addr:postcode":"1080",
    "addr:street":"Strozzig",
    "iso:country":"AT",
    "sg:address":"Strozzig 3",
    "sg:city":"Wien",
    "sg:classifiers":[
        {
            "category":"Restaurant",
            "type":"Food & Drink"
        }
    ],
    "sg:phone":"+43 1 4029357",
    "sg:postcode":"1080",
    "sg:province":"Wien",
    "wof:name":"Flamm Verena Mag",
    "wof:placetype":"venue"
},
  "geometry": {"coordinates":[16.3491134644,48.2067108154],"type":"Point"}
}