{
  "type": "Feature",
  "properties": {
    "addr:full":"Steinrieglstr 196 Klosterneuburg Nieder\u00f6sterreich 3400",
    "addr:housenumber":"196",
    "addr:postcode":"3400",
    "addr:street":"Niederoesterreich",
    "iso:country":"AT",
    "sg:address":"Steinrieglstr 196",
    "sg:city":"Klosterneuburg",
    "sg:orig_category":"Feuerwehren",
    "sg:phone":"+43 2243 30581",
    "sg:postcode":"3400",
    "sg:province":"Nieder\u00f6sterreich",
    "wof:name":"Freiwillige Feuerwehr Klosterneuburg-Weidlingbach",
    "wof:placetype":"venue"
},
  "geometry": {"coordinates":[16.2368869781,48.2676582336],"type":"Point"}
}