{
  "type": "Feature",
  "properties": {
    "addr:full":"Saglstrasse 16 Telfs Tirol 6410",
    "addr:housenumber":"16",
    "addr:postcode":"6410",
    "addr:street":"Saglstrasse;Tirol",
    "iso:country":"AT",
    "sg:address":"Saglstrasse 16",
    "sg:city":"Telfs",
    "sg:classifiers":[
        {
            "category":"Building & Trades",
            "subcategory":"Plumbing",
            "type":"Services"
        }
    ],
    "sg:phone":"+43 5262 62581",
    "sg:postcode":"6410",
    "sg:province":"Tirol",
    "sg:tags":[
        "pipe",
        "stove",
        "chimney"
    ],
    "sg:website":"kaminkehrer.at",
    "wof:name":"Rudolf Rohowsky",
    "wof:placetype":"venue"
},
  "geometry": {"coordinates":[11.0772781372,47.3104934692],"type":"Point"}
}