{
  "type": "Feature",
  "properties": {
    "addr:full":"Wiener Bundesstr 7 Hallwang Salzburg 5300",
    "addr:housenumber":"7",
    "addr:postcode":"5300",
    "addr:street":"Salzburg",
    "iso:country":"AT",
    "sg:address":"Wiener Bundesstr 7",
    "sg:city":"Hallwang",
    "sg:classifiers":[
        {
            "category":"Restaurant",
            "type":"Food & Drink"
        }
    ],
    "sg:phone":"+43 662 665824",
    "sg:postcode":"5300",
    "sg:province":"Salzburg",
    "sg:website":"santafe.at",
    "wof:name":"Restaurant Santa Fe",
    "wof:placetype":"venue"
},
  "geometry": {"coordinates":[13.0847539902,47.8312988281],"type":"Point"}
}