{
  "type": "Feature",
  "properties": {
    "addr:full":"Hauserstr 16 Linz Ober\u00f6sterreich 4040",
    "addr:housenumber":"16",
    "addr:postcode":"4040",
    "addr:street":"Hauserstr",
    "iso:country":"AT",
    "sg:address":"Hauserstr 16",
    "sg:city":"Linz",
    "sg:orig_category":"Ingenieurkonsulenten / Zivilingenieure",
    "sg:phone":"+43 732 732001",
    "sg:postcode":"4040",
    "sg:province":"Ober\u00f6sterreich",
    "wof:name":"Greindl Johann Prof Dipl-Ing",
    "wof:placetype":"venue"
},
  "geometry": {"coordinates":[14.2832183838,48.3256797791],"type":"Point"}
}