{
  "type": "Feature",
  "properties": {
    "addr:full":"Nr 135 Teufenbach Steiermark 8833",
    "addr:postcode":"8833",
    "addr:street":"Nr 135",
    "iso:country":"AT",
    "sg:address":"Nr 135",
    "sg:city":"Teufenbach",
    "sg:orig_category":"Feuerwehren",
    "sg:phone":"+43 3582 2218",
    "sg:postcode":"8833",
    "sg:province":"Steiermark",
    "wof:name":"Freiwillige Feuerwehr Teufenbach",
    "wof:placetype":"venue"
},
  "geometry": {"coordinates":[14.3591108322,47.1285476685],"type":"Point"}
}