{
  "type": "Feature",
  "properties": {
    "addr:full":"Steinbruchstr 60 Wien Wien 1160",
    "addr:housenumber":"60",
    "addr:postcode":"1160",
    "addr:street":"Steinbruchstr",
    "iso:country":"AT",
    "sg:address":"Steinbruchstr 60",
    "sg:city":"Wien",
    "sg:orig_category":"Werbeagenturen",
    "sg:phone":"+43 1 4164380",
    "sg:postcode":"1160",
    "sg:province":"Wien",
    "wof:name":"Neumayr Marketing Kommunikation und Public Relation",
    "wof:placetype":"venue"
},
  "geometry": {"coordinates":[16.2984790802,48.2056770325],"type":"Point"}
}