{
  "type": "Feature",
  "properties": {
    "addr:full":"Marxerg 39 Wien Wien 1030",
    "addr:housenumber":"39",
    "addr:postcode":"1030",
    "addr:street":"Marxerg",
    "iso:country":"AT",
    "sg:address":"Marxerg 39",
    "sg:city":"Wien",
    "sg:orig_category":"Immobilienmakler",
    "sg:phone":"+43 1 71321600",
    "sg:postcode":"1030",
    "sg:province":"Wien",
    "wof:name":"Leitner Real Immobilientreuhand GesmbH",
    "wof:placetype":"venue"
},
  "geometry": {"coordinates":[16.3954029083,48.2052497864],"type":"Point"}
}