{
  "type": "Feature",
  "properties": {
    "addr:full":"Maisberg 47 Ybbsitz Nieder\u00f6sterreich 3341",
    "addr:housenumber":"47",
    "addr:postcode":"3341",
    "addr:street":"Maisberg",
    "iso:country":"AT",
    "sg:address":"Maisberg 47",
    "sg:city":"Ybbsitz",
    "sg:classifiers":[
        {
            "category":"Manufacturing",
            "subcategory":"Metals",
            "type":"Manufacturing & Wholesale Goods"
        }
    ],
    "sg:phone":"+43 4374 43863150",
    "sg:postcode":"3341",
    "sg:province":"Nieder\u00f6sterreich",
    "sg:tags":[
        "processing"
    ],
    "wof:name":"RIESS GMBH & CO. KG",
    "wof:placetype":"venue"
},
  "geometry": {"coordinates":[14.8485641479,47.9385795593],"type":"Point"}
}