{
  "type": "Feature",
  "properties": {
    "addr:full":"Holunderstr 3 Asten Ober\u00f6sterreich 4481",
    "addr:housenumber":"3",
    "addr:postcode":"4481",
    "addr:street":"Holunderstr",
    "iso:country":"AT",
    "sg:address":"Holunderstr 3",
    "sg:city":"Asten",
    "sg:orig_category":"Botendienste",
    "sg:phone":"+43 4367 69499162",
    "sg:postcode":"4481",
    "sg:province":"Ober\u00f6sterreich",
    "wof:name":"VoFe Expressdienste",
    "wof:placetype":"venue"
},
  "geometry": {"coordinates":[14.4233703613,48.2211875916],"type":"Point"}
}