{
  "type": "Feature",
  "properties": {
    "addr:full":"Feldg 402 P\u00f6llau Steiermark 8225",
    "addr:housenumber":"402",
    "addr:postcode":"8225",
    "addr:street":"Poellau Steiermark",
    "iso:country":"AT",
    "sg:address":"Feldg 402",
    "sg:city":"P\u00f6llau",
    "sg:orig_category":"Hauptschulen",
    "sg:phone":"+43 3335 27630",
    "sg:postcode":"8225",
    "sg:province":"Steiermark",
    "wof:name":"Hauptschule 2",
    "wof:placetype":"venue"
},
  "geometry": {"coordinates":[15.8337945938,47.301990509],"type":"Point"}
}