{
  "type": "Feature",
  "properties": {
    "addr:full":"Nr 153 \u00d6blarn Steiermark 8960",
    "addr:postcode":"8960",
    "addr:street":"Nr 153",
    "iso:country":"AT",
    "sg:address":"Nr 153",
    "sg:city":"\u00d6blarn",
    "sg:orig_category":"Volksschulen",
    "sg:phone":"+43 3684 2227",
    "sg:postcode":"8960",
    "sg:province":"Steiermark",
    "wof:name":"Volksschule",
    "wof:placetype":"venue"
},
  "geometry": {"coordinates":[166.9221496582,-0.5282999873],"type":"Point"}
}