{
  "type": "Feature",
  "properties": {
    "iso:country":"AT",
    "sg:address":"Kirchenpl 368",
    "sg:city":"Neulengbach",
    "sg:orig_category":"Fotografen",
    "sg:phone":"+43 4369 910109154",
    "sg:postcode":"3040",
    "sg:province":"Nieder\u00f6sterreich",
    "wof:name":"Luger Martin",
    "wof:placetype":"venue"
},
  "geometry": {"coordinates":[15.9113178253,48.2010231018],"type":"Point"}
}