{
  "type": "Feature",
  "properties": {
    "addr:full":"Furth 46 Weissenbach an der Triesting Nieder\u00f6sterreich 2564",
    "addr:housenumber":"46",
    "addr:postcode":"2564",
    "addr:street":"Furth",
    "iso:country":"AT",
    "sg:address":"Furth 46",
    "sg:city":"Weissenbach an der Triesting",
    "sg:classifiers":[
        {
            "category":"Manufacturing",
            "subcategory":"Wood Products",
            "type":"Manufacturing & Wholesale Goods"
        }
    ],
    "sg:phone":"+43 2674 87335",
    "sg:postcode":"2564",
    "sg:province":"Nieder\u00f6sterreich",
    "sg:tags":[
        "lumber"
    ],
    "sg:website":"karner-holz.at",
    "wof:name":"Franz Karner",
    "wof:placetype":"venue"
},
  "geometry": {"coordinates":[16.0380496979,47.9819335938],"type":"Point"}
}