{
  "type": "Feature",
  "properties": {
    "iso:country":"AT",
    "sg:address":"Brown Boveri-Str 8/1",
    "sg:city":"Wiener Neudorf",
    "sg:classifiers":[
        {
            "category":"Internet Cafe",
            "subcategory":"None",
            "type":"Food & Drink"
        }
    ],
    "sg:phone":"+43 2236 43300",
    "sg:postcode":"2351",
    "sg:province":"Nieder\u00f6sterreich",
    "wof:name":"CodeWerk Software Services and Development GmbH",
    "wof:placetype":"venue"
},
  "geometry": {"coordinates":[16.3103790283,48.0747413635],"type":"Point"}
}