{
  "type": "Feature",
  "properties": {
    "addr:full":"Steiner Landstr 21 Krems an der Donau Nieder\u00f6sterreich 3500",
    "addr:housenumber":"21",
    "addr:postcode":"3500",
    "addr:street":"Steiner Landstr",
    "iso:country":"AT",
    "sg:address":"Steiner Landstr 21",
    "sg:city":"Krems an der Donau",
    "sg:orig_category":"Schuhreparatur",
    "sg:phone":"+43 2732 82953",
    "sg:postcode":"3500",
    "sg:province":"Nieder\u00f6sterreich",
    "wof:name":"Schmalko Johann",
    "wof:placetype":"venue"
},
  "geometry": {"coordinates":[15.5862550735,48.4035606384],"type":"Point"}
}