{
  "type": "Feature",
  "properties": {
    "iso:country":"AT",
    "sg:address":"Alserbachstr 23",
    "sg:city":"Wien",
    "sg:classifiers":[
        {
            "category":"Professional",
            "subcategory":"Computer Services",
            "type":"Services"
        }
    ],
    "sg:phone":"+43 1 5358876",
    "sg:postcode":"1090",
    "sg:province":"Wien",
    "sg:tags":[
        "software"
    ],
    "wof:name":"Integro Informationssysteme GesmbH",
    "wof:placetype":"venue"
},
  "geometry": {"coordinates":[16.3587989807,48.2251853943],"type":"Point"}
}