{
  "type": "Feature",
  "properties": {
    "addr:full":"Spiegelg 4 Wien Wien 1010",
    "addr:housenumber":"4",
    "addr:postcode":"1010",
    "addr:street":"Spiegelg",
    "iso:country":"AT",
    "sg:address":"Spiegelg 4",
    "sg:city":"Wien",
    "sg:orig_category":"Friseure U Frisiersalons",
    "sg:phone":"+43 1 5123194",
    "sg:postcode":"1010",
    "sg:province":"Wien",
    "wof:name":"City Coiffeur Agopian Suren",
    "wof:placetype":"venue"
},
  "geometry": {"coordinates":[16.3701858521,48.2077674866],"type":"Point"}
}