{
  "type": "Feature",
  "properties": {
    "addr:full":"Anton-Bauer-G 75 Friedberg Steiermark 8240",
    "addr:housenumber":"75",
    "addr:postcode":"8240",
    "addr:street":"Anton-Bauer-G",
    "iso:country":"AT",
    "sg:address":"Anton-Bauer-G 75",
    "sg:city":"Friedberg",
    "sg:orig_category":"Volksschulen",
    "sg:phone":"+43 4333 3925143",
    "sg:postcode":"8240",
    "sg:province":"Steiermark",
    "wof:name":"Volksschule",
    "wof:placetype":"venue"
},
  "geometry": {"coordinates":[16.0569381714,47.4413566589],"type":"Point"}
}