{
  "type": "Feature",
  "properties": {
    "addr:full":"Im Doblerholz 22 Leonding Ober\u00f6sterreich 4060",
    "addr:housenumber":"22",
    "addr:postcode":"4060",
    "addr:street":"Im Doblerholz",
    "iso:country":"AT",
    "sg:address":"Im Doblerholz 22",
    "sg:city":"Leonding",
    "sg:orig_category":"Installationsunternehmen",
    "sg:phone":"+43 676 3301522",
    "sg:postcode":"4060",
    "sg:province":"Ober\u00f6sterreich",
    "wof:name":"Metzl Harald",
    "wof:placetype":"venue"
},
  "geometry": {"coordinates":[14.2517614365,48.2574653625],"type":"Point"}
}