{
  "type": "Feature",
  "properties": {
    "addr:full":"Ganglbauerg 19 Wien Wien 1160",
    "addr:housenumber":"19",
    "addr:postcode":"1160",
    "addr:street":"Ganglbauerg",
    "iso:country":"AT",
    "sg:address":"Ganglbauerg 19",
    "sg:city":"Wien",
    "sg:orig_category":"Bilderrahmen",
    "sg:phone":"+43 1 49349260",
    "sg:postcode":"1160",
    "sg:province":"Wien",
    "wof:name":"Brunner Alfred",
    "wof:placetype":"venue"
},
  "geometry": {"coordinates":[16.325252533,48.2085113525],"type":"Point"}
}