{
  "type": "Feature",
  "properties": {
    "addr:full":"D\u00f6blerhofstr. 16  Wien Wien 1110",
    "addr:housenumber":"16",
    "addr:postcode":"1110",
    "addr:street":"Doeblerhofstr.",
    "iso:country":"AT",
    "sg:address":"D\u00f6blerhofstr. 16 ",
    "sg:city":"Wien",
    "sg:classifiers":[
        {
            "category":"Shopping",
            "subcategory":"Clothing, Apparel, & Fashions",
            "type":"Retail Goods"
        }
    ],
    "sg:phone":"+43 4317 40250",
    "sg:postcode":"1110",
    "sg:province":"Wien",
    "sg:tags":[
        "clothes"
    ],
    "wof:name":"JOSEF BEIL GMBH",
    "wof:placetype":"venue"
},
  "geometry": {"coordinates":[16.4155445099,48.1850814819],"type":"Point"}
}