{
  "type": "Feature",
  "properties": {
    "iso:country":"AT",
    "sg:address":"Kirchenzeile 3",
    "sg:city":"Ladendorf",
    "sg:orig_category":"Non-Classified Establishments",
    "sg:phone":"+43 2575 2200",
    "sg:postcode":"2126",
    "sg:province":"Nieder\u00f6sterreich",
    "wof:name":"Pfarramt",
    "wof:placetype":"venue"
},
  "geometry": {"coordinates":[16.4923267365,48.5359115601],"type":"Point"}
}