{
  "type": "Feature",
  "properties": {
    "addr:full":"Landertsham 5 Attnang-Puchheim Ober\u00f6sterreich 4800",
    "addr:housenumber":"5",
    "addr:postcode":"4800",
    "addr:street":"Landertsham",
    "iso:country":"AT",
    "sg:address":"Landertsham 5",
    "sg:city":"Attnang-Puchheim",
    "sg:orig_category":"Transportunternehmen",
    "sg:phone":"+43 767463132",
    "sg:postcode":"4800",
    "sg:province":"Ober\u00f6sterreich",
    "wof:name":"Kletzmayr Transport- und Botendienst GesmbH",
    "wof:placetype":"venue"
},
  "geometry": {"coordinates":[13.7326183319,48.0233039856],"type":"Point"}
}