{
  "type": "Feature",
  "properties": {
    "addr:full":"Siegespl 5 Wien Wien 1220",
    "addr:housenumber":"5",
    "addr:postcode":"1220",
    "addr:street":"Siegespl",
    "iso:country":"AT",
    "sg:address":"Siegespl 5",
    "sg:city":"Wien",
    "sg:orig_category":"Rettungsdienste",
    "sg:phone":"+43 1 2858130",
    "sg:postcode":"1220",
    "sg:province":"Wien",
    "wof:name":"\u00f6sterreichische Rettungshundebrigade \u00f6RHB",
    "wof:placetype":"venue"
},
  "geometry": {"coordinates":[16.4854812622,48.2177391052],"type":"Point"}
}