{
  "type": "Feature",
  "properties": {
    "addr:full":"Neuer Rathauspl Liezen Steiermark 8940",
    "addr:postcode":"8940",
    "iso:country":"AT",
    "sg:address":"Neuer Rathauspl",
    "sg:city":"Liezen",
    "sg:orig_category":"Lebensmittel / Einzelhandel",
    "sg:phone":"+43 3612 22827",
    "sg:postcode":"8940",
    "sg:province":"Steiermark",
    "wof:name":"SPAR \u00f6sterreichische Warenhandels-AG",
    "wof:placetype":"venue"
},
  "geometry": {"coordinates":[14.2423257828,47.5677032471],"type":"Point"}
}