{
  "type": "Feature",
  "properties": {
    "iso:country":"AT",
    "sg:address":"Braunauer Str",
    "sg:city":"Mattighofen",
    "sg:orig_category":"Autohandel",
    "sg:phone":"+43 7742 24520",
    "sg:postcode":"5230",
    "sg:province":"Ober\u00f6sterreich",
    "wof:name":"Bucheder Autohaus KG",
    "wof:placetype":"venue"
},
  "geometry": {"coordinates":[13.1521453857,48.1142082214],"type":"Point"}
}