{
  "type": "Feature",
  "properties": {
    "iso:country":"AT",
    "sg:address":"Buchbergg 27",
    "sg:city":"Klosterneuburg",
    "sg:orig_category":"Restaurants: Griechisch",
    "sg:phone":"+43 2243 22930",
    "sg:postcode":"3400",
    "sg:province":"Nieder\u00f6sterreich",
    "wof:name":"Santorini Griechisches Spezialit\u00e4tenrestaurant",
    "wof:placetype":"venue"
},
  "geometry": {"coordinates":[16.3204250336,48.3036766052],"type":"Point"}
}