{
  "type": "Feature",
  "properties": {
    "iso:country":"AT",
    "sg:address":"Oberndorfer Str 390",
    "sg:city":"Altenmarkt im Pongau",
    "sg:orig_category":"Tapezierer U Dekorateure",
    "sg:phone":"+43 4364 525800",
    "sg:postcode":"5541",
    "sg:province":"Salzburg",
    "wof:name":"Palzenberger Hermann",
    "wof:placetype":"venue"
},
  "geometry": {"coordinates":[13.4138402939,47.3864593506],"type":"Point"}
}