{
  "type": "Feature",
  "properties": {
    "addr:full":"Schubertstr 39 Korneuburg Nieder\u00f6sterreich 2100",
    "addr:housenumber":"39",
    "addr:postcode":"2100",
    "addr:street":"Schubertstr;Niederoesterreich",
    "iso:country":"AT",
    "sg:address":"Schubertstr 39",
    "sg:city":"Korneuburg",
    "sg:orig_category":"Lebensmittel / Einzelhandel",
    "sg:phone":"+43 2262 74330",
    "sg:postcode":"2100",
    "sg:province":"Nieder\u00f6sterreich",
    "wof:name":"Spar-Markt Mantl",
    "wof:placetype":"venue"
},
  "geometry": {"coordinates":[16.3402786255,48.3396072388],"type":"Point"}
}