{
  "type": "Feature",
  "properties": {
    "iso:country":"AT",
    "sg:address":"Allee 12",
    "sg:city":"Pernegg an der Mur",
    "sg:orig_category":"Tischlereien",
    "sg:phone":"+43 3867 8026",
    "sg:postcode":"8132",
    "sg:province":"Steiermark",
    "wof:name":"Pichler Dietmar",
    "wof:placetype":"venue"
},
  "geometry": {"coordinates":[15.3423252106,47.3582878113],"type":"Point"}
}