{
  "type": "Feature",
  "properties": {
    "addr:full":"Johannesfeldstr 17 Volders Tirol 6111",
    "addr:housenumber":"17",
    "addr:postcode":"6111",
    "addr:street":"Johannesfeldstr;Tirol",
    "iso:country":"AT",
    "sg:address":"Johannesfeldstr 17",
    "sg:city":"Volders",
    "sg:orig_category":"Anlagenbau U -Technik",
    "sg:phone":"+43 4352 24527610",
    "sg:postcode":"6111",
    "sg:province":"Tirol",
    "wof:name":"Heizkessel u Stahlbau GesmbH",
    "wof:placetype":"venue"
},
  "geometry": {"coordinates":[11.5731744766,47.2907905579],"type":"Point"}
}