{
  "type": "Feature",
  "properties": {
    "addr:full":"Riedlestr 14 Klaus-Weiler Vorarlberg 6833",
    "addr:housenumber":"14",
    "addr:postcode":"6833",
    "addr:street":"Riedlestr",
    "iso:country":"AT",
    "sg:address":"Riedlestr 14",
    "sg:city":"Klaus-Weiler",
    "sg:orig_category":"Hunde U Hundeartikel",
    "sg:phone":"+43 4355 2353003",
    "sg:postcode":"6833",
    "sg:province":"Vorarlberg",
    "wof:name":"Ritter Albert",
    "wof:placetype":"venue"
},
  "geometry": {"coordinates":[9.6539640427,47.306098938],"type":"Point"}
}