{
  "type": "Feature",
  "properties": {
    "addr:full":"Lochau Vorarlberg 6911",
    "addr:postcode":"6911",
    "iso:country":"AT",
    "sg:city":"Lochau",
    "sg:orig_category":"Feuerwehren",
    "sg:phone":"+43 5574 421320",
    "sg:postcode":"6911",
    "sg:province":"Vorarlberg",
    "wof:name":"Feuerwehr Lochau",
    "wof:placetype":"venue"
},
  "geometry": {"coordinates":[9.7512302399,47.5298461914],"type":"Point"}
}