{
  "type": "Feature",
  "properties": {
    "addr:full":"Saalfeldner Str 10 Zell am See Salzburg 5700",
    "addr:housenumber":"10",
    "addr:postcode":"5700",
    "addr:street":"Str;Salzburg",
    "iso:country":"AT",
    "sg:address":"Saalfeldner Str 10",
    "sg:city":"Zell am See",
    "sg:orig_category":"Familien / Beratung",
    "sg:phone":"+43 4366 48284179",
    "sg:postcode":"5700",
    "sg:province":"Salzburg",
    "wof:name":"Forum Familie Pinzgau - Familienreferat Land Salzburg",
    "wof:placetype":"venue"
},
  "geometry": {"coordinates":[12.7997369766,47.3252220154],"type":"Point"}
}