{
  "type": "Feature",
  "properties": {
    "addr:full":"Heinrich-Gruber-Str 3 Traun Ober\u00f6sterreich 4050",
    "addr:housenumber":"3",
    "addr:postcode":"4050",
    "addr:street":"Heinrich-Gruber-Str",
    "iso:country":"AT",
    "sg:address":"Heinrich-Gruber-Str 3",
    "sg:city":"Traun",
    "sg:orig_category":"Blumeneinzelhandel",
    "sg:phone":"+43 7229 73065",
    "sg:postcode":"4050",
    "sg:province":"Ober\u00f6sterreich",
    "wof:name":"Hydrokultur Ing Edgar Weitmann GmbH",
    "wof:placetype":"venue"
},
  "geometry": {"coordinates":[14.2392673492,48.2200584412],"type":"Point"}
}