{
  "type": "Feature",
  "properties": {
    "iso:country":"AT",
    "sg:address":"Nr 20",
    "sg:city":"Stadl an der Mur",
    "sg:orig_category":"Gemeinden",
    "sg:phone":"+43 3534 27050",
    "sg:postcode":"8862",
    "sg:province":"Steiermark",
    "wof:name":"Gemeindeamt Falkendorf",
    "wof:placetype":"venue"
},
  "geometry": {"coordinates":[13.9805088043,47.0870246887],"type":"Point"}
}