{
  "type": "Feature",
  "properties": {
    "addr:full":"Nr 16 M\u00fcnzkirchen Ober\u00f6sterreich 4792",
    "addr:postcode":"4792",
    "addr:street":"Nr 16 Muenzkirchen Oberoesterreich",
    "iso:country":"AT",
    "sg:address":"Nr 16",
    "sg:city":"M\u00fcnzkirchen",
    "sg:orig_category":"Non-Classified Establishments",
    "sg:phone":"+43 7716 7220",
    "sg:postcode":"4792",
    "sg:province":"Ober\u00f6sterreich",
    "wof:name":"G\u00fcterwegmeisterei M\u00fcnzkirchen",
    "wof:placetype":"venue"
},
  "geometry": {"coordinates":[13.5696516037,48.484172821],"type":"Point"}
}