{
  "type": "Feature",
  "properties": {
    "iso:country":"AT",
    "sg:address":"Raubergasse 9",
    "sg:city":"Graz",
    "sg:classifiers":[
        {
            "category":"Shopping",
            "subcategory":"Jewelry",
            "type":"Retail Goods"
        }
    ],
    "sg:phone":"+43 316 826032",
    "sg:postcode":"8010",
    "sg:province":"Steiermark",
    "sg:tags":[
        "gemstone",
        "jewellery"
    ],
    "wof:name":"Rudolf Kreuzig",
    "wof:placetype":"venue"
},
  "geometry": {"coordinates":[15.4385900497,47.0691223145],"type":"Point"}
}