{
  "type": "Feature",
  "properties": {
    "iso:country":"AT",
    "sg:address":"Hauptpl 6",
    "sg:city":"Friesach",
    "sg:orig_category":"Offsetdruckereien",
    "sg:phone":"+43 4268 3695",
    "sg:postcode":"9360",
    "sg:province":"K\u00e4rnten",
    "wof:name":"Ploder-Drucke Druck & Grafik",
    "wof:placetype":"venue"
},
  "geometry": {"coordinates":[14.4055213928,46.9502677917],"type":"Point"}
}