{
  "type": "Feature",
  "properties": {
    "addr:full":"Br\u00fcndl 3 Dienten am Hochk\u00f6nig Salzburg 5652",
    "addr:housenumber":"3",
    "addr:postcode":"5652",
    "addr:street":"Bruendl;Salzburg",
    "iso:country":"AT",
    "sg:address":"Br\u00fcndl 3",
    "sg:city":"Dienten am Hochk\u00f6nig",
    "sg:orig_category":"Forstverwaltungen",
    "sg:phone":"+43 6461 545",
    "sg:postcode":"5652",
    "sg:province":"Salzburg",
    "wof:name":"H\u00f6llwart Georg",
    "wof:placetype":"venue"
},
  "geometry": {"coordinates":[13.0039300919,47.3835105896],"type":"Point"}
}