{
  "type": "Feature",
  "properties": {
    "addr:full":"Pfarrg 22 Hollabrunn Nieder\u00f6sterreich 2020",
    "addr:housenumber":"22",
    "addr:postcode":"2020",
    "addr:street":"Pfarrg",
    "iso:country":"AT",
    "sg:address":"Pfarrg 22",
    "sg:city":"Hollabrunn",
    "sg:orig_category":"Baumeister",
    "sg:phone":"+43 2952 2139",
    "sg:postcode":"2020",
    "sg:province":"Nieder\u00f6sterreich",
    "wof:name":"Schubrig GesmbH",
    "wof:placetype":"venue"
},
  "geometry": {"coordinates":[16.0794029236,48.5600357056],"type":"Point"}
}