{
  "type": "Feature",
  "properties": {
    "addr:full":"Burgg 28-32 Wien Wien 1070",
    "addr:postcode":"28-32;1070",
    "iso:country":"AT",
    "sg:address":"Burgg 28-32",
    "sg:city":"Wien",
    "sg:classifiers":[
        {
            "category":"Restaurant",
            "type":"Food & Drink"
        }
    ],
    "sg:phone":"+43 664 3502510",
    "sg:postcode":"1070",
    "sg:province":"Wien",
    "wof:name":"Burgcafe",
    "wof:placetype":"venue"
},
  "geometry": {"coordinates":[16.3513908386,48.2044715881],"type":"Point"}
}