{
  "type": "Feature",
  "properties": {
    "addr:full":"Kammern 172 Egg Vorarlberg 6863",
    "addr:housenumber":"172",
    "addr:postcode":"6863",
    "addr:street":"Kammern",
    "iso:country":"AT",
    "sg:address":"Kammern 172",
    "sg:city":"Egg",
    "sg:orig_category":"Holzbau",
    "sg:phone":"+43 5512 22480",
    "sg:postcode":"6863",
    "sg:province":"Vorarlberg",
    "wof:name":"Fetz Holzbau GmbH",
    "wof:placetype":"venue"
},
  "geometry": {"coordinates":[9.8822011948,47.4344024658],"type":"Point"}
}