{
  "type": "Feature",
  "properties": {
    "iso:country":"AT",
    "sg:address":"Nr 32",
    "sg:city":"Annaberg",
    "sg:orig_category":"Hauptschulen",
    "sg:phone":"+43 6463 8110",
    "sg:postcode":"5524",
    "sg:province":"Salzburg",
    "wof:name":"Hauptschule Annaberg im Lammertal",
    "wof:placetype":"venue"
},
  "geometry": {"coordinates":[13.4312047958,47.513458252],"type":"Point"}
}