{
  "type": "Feature",
  "properties": {
    "addr:full":"Wei\u00dfkirchner Str 5 Marchtrenk Ober\u00f6sterreich 4614",
    "addr:housenumber":"5",
    "addr:postcode":"4614",
    "addr:street":"Str",
    "iso:country":"AT",
    "sg:address":"Wei\u00dfkirchner Str 5",
    "sg:city":"Marchtrenk",
    "sg:orig_category":"Fenster",
    "sg:phone":"+43 7243 52369",
    "sg:postcode":"4614",
    "sg:province":"Ober\u00f6sterreich",
    "wof:name":"Bender Karl",
    "wof:placetype":"venue"
},
  "geometry": {"coordinates":[14.1112260818,48.1892433167],"type":"Point"}
}