{
  "type": "Feature",
  "properties": {
    "addr:full":"Innerberg 50 Weerberg Tirol 6133",
    "addr:housenumber":"50",
    "addr:postcode":"6133",
    "addr:street":"Innerberg;Tirol",
    "iso:country":"AT",
    "sg:address":"Innerberg 50",
    "sg:city":"Weerberg",
    "sg:orig_category":"Appartements / Ferienwohnungen",
    "sg:phone":"+43 5224 66230",
    "sg:postcode":"6133",
    "sg:province":"Tirol",
    "wof:name":"Floachhof",
    "wof:placetype":"venue"
},
  "geometry": {"coordinates":[11.6749801636,47.2763786316],"type":"Point"}
}