{
  "type": "Feature",
  "properties": {
    "addr:full":"Unterbings 12 Bludenz Vorarlberg 6700",
    "addr:housenumber":"12",
    "addr:postcode":"6700",
    "addr:street":"Unterbings",
    "iso:country":"AT",
    "sg:address":"Unterbings 12",
    "sg:city":"Bludenz",
    "sg:orig_category":"Transportunternehmen",
    "sg:phone":"+43 4355 52640730",
    "sg:postcode":"6700",
    "sg:province":"Vorarlberg",
    "wof:name":"Stag Staubgut-Transport GesmbH",
    "wof:placetype":"venue"
},
  "geometry": {"coordinates":[9.8560152054,47.144859314],"type":"Point"}
}