{
  "type": "Feature",
  "properties": {
    "addr:full":"Linzer Str 34 Wels Ober\u00f6sterreich 4600",
    "addr:housenumber":"34",
    "addr:postcode":"4600",
    "addr:street":"Linzer Str;Oberoesterreich",
    "iso:country":"AT",
    "sg:address":"Linzer Str 34",
    "sg:city":"Wels",
    "sg:orig_category":"Bauunternehmen",
    "sg:phone":"+43 7242 79795",
    "sg:postcode":"4600",
    "sg:province":"Ober\u00f6sterreich",
    "wof:name":"Hadzic & Co OEG",
    "wof:placetype":"venue"
},
  "geometry": {"coordinates":[14.0323495865,48.162399292],"type":"Point"}
}