{
  "type": "Feature",
  "properties": {
    "iso:country":"AT",
    "sg:address":"Bahnhofstr 1a",
    "sg:city":"Saalfelden am Steinernen Meer",
    "sg:orig_category":"Apotheken",
    "sg:phone":"+43 6582 72257",
    "sg:postcode":"5760",
    "sg:province":"Salzburg",
    "wof:name":"Antonius-Apotheke Mag pharm Dietmar Ablinger",
    "wof:placetype":"venue"
},
  "geometry": {"coordinates":[12.8468427658,47.4270591736],"type":"Point"}
}