{
  "type": "Feature",
  "properties": {
    "addr:full":"Nr 110 Staatz-Kautendorf Nieder\u00f6sterreich 2134",
    "addr:postcode":"2134",
    "addr:street":"Nr;Staatz-Kautendorf",
    "iso:country":"AT",
    "sg:address":"Nr 110",
    "sg:city":"Staatz-Kautendorf",
    "sg:orig_category":"Heurigen / Buschenschank",
    "sg:phone":"+43 2524 3591",
    "sg:postcode":"2134",
    "sg:province":"Nieder\u00f6sterreich",
    "wof:name":"Stadlschenke Peter Pernold",
    "wof:placetype":"venue"
},
  "geometry": {"coordinates":[16.486240387,48.6759986877],"type":"Point"}
}