{
  "type": "Feature",
  "properties": {
    "addr:full":"Haritzmeierstrasse 2 Kapfenberg Steiermark 8605",
    "addr:housenumber":"2",
    "addr:postcode":"8605",
    "addr:street":"Haritzmeierstrasse",
    "iso:country":"AT",
    "sg:address":"Haritzmeierstrasse 2",
    "sg:city":"Kapfenberg",
    "sg:classifiers":[
        {
            "category":"Building & Trades",
            "subcategory":"Electrical",
            "type":"Services"
        }
    ],
    "sg:phone":"+43 3862 34557",
    "sg:postcode":"8605",
    "sg:province":"Steiermark",
    "sg:tags":[
        "disassembly",
        "assembly",
        "stand",
        "fair"
    ],
    "sg:website":"mcg-montagen.com",
    "wof:name":"McG. Regal Montage GmbH",
    "wof:placetype":"venue"
},
  "geometry": {"coordinates":[15.2912454605,47.4438438416],"type":"Point"}
}