{
  "type": "Feature",
  "properties": {
    "addr:full":"Piccostr 20 Villach K\u00e4rnten 9500",
    "addr:housenumber":"20",
    "addr:postcode":"9500",
    "addr:street":"Piccostr;Kaernten",
    "iso:country":"AT",
    "sg:address":"Piccostr 20",
    "sg:city":"Villach",
    "sg:orig_category":"Lebensmittel / Einzelhandel",
    "sg:phone":"+43 4242 412320",
    "sg:postcode":"9500",
    "sg:province":"K\u00e4rnten",
    "wof:name":"SPAR \u00f6sterreichische Warenhandels-AG",
    "wof:placetype":"venue"
},
  "geometry": {"coordinates":[13.858250618,46.6204490662],"type":"Point"}
}