{
  "type": "Feature",
  "properties": {
    "addr:full":"Herzog-Friedrich-Str 34 Innsbruck Tirol 6020",
    "addr:housenumber":"34",
    "addr:postcode":"6020",
    "addr:street":"Herzog-Friedrich-Str;Tirol",
    "iso:country":"AT",
    "sg:address":"Herzog-Friedrich-Str 34",
    "sg:city":"Innsbruck",
    "sg:orig_category":"Geschenkartikel",
    "sg:phone":"+43 512 578192",
    "sg:postcode":"6020",
    "sg:province":"Tirol",
    "wof:name":"Br\u00fcggler KEG",
    "wof:placetype":"venue"
},
  "geometry": {"coordinates":[11.3933153152,47.2674026489],"type":"Point"}
}