{
  "type": "Feature",
  "properties": {
    "iso:country":"AT",
    "sg:address":"Aguntstr 5",
    "sg:city":"Lienz",
    "sg:orig_category":"Dachdeckereien",
    "sg:phone":"+43 4348 5264090",
    "sg:postcode":"9900",
    "sg:province":"Tirol",
    "sg:website":"dig-info.at",
    "wof:name":"DIG Dachdeckungs- Isolierungs- u Spenglerei GesmbH & Co KG",
    "wof:placetype":"venue"
},
  "geometry": {"coordinates":[12.788277626,46.826210022],"type":"Point"}
}