{
  "type": "Feature",
  "properties": {
    "addr:full":"Maiffredyg 4 Graz Steiermark 8010",
    "addr:housenumber":"4",
    "addr:postcode":"8010",
    "addr:street":"Maiffredyg",
    "iso:country":"AT",
    "sg:address":"Maiffredyg 4",
    "sg:city":"Graz",
    "sg:orig_category":"Psychologen",
    "sg:phone":"+43 316 38213115",
    "sg:postcode":"8010",
    "sg:province":"Steiermark",
    "wof:name":"Hutter Sonja Mag Dr",
    "wof:placetype":"venue"
},
  "geometry": {"coordinates":[15.4482889175,47.0708503723],"type":"Point"}
}