{
  "type": "Feature",
  "properties": {
    "addr:full":"Triester Str 12/1/9 Wiener Neudorf Nieder\u00f6sterreich 2351",
    "addr:housenumber":"12 / 1 / 9",
    "addr:postcode":"2351",
    "addr:street":"Str",
    "iso:country":"AT",
    "sg:address":"Triester Str 12/1/9",
    "sg:city":"Wiener Neudorf",
    "sg:orig_category":"Immobilienmakler",
    "sg:phone":"+43 664 2631264",
    "sg:postcode":"2351",
    "sg:province":"Nieder\u00f6sterreich",
    "wof:name":"TD Immobilien GesmbH",
    "wof:placetype":"venue"
},
  "geometry": {"coordinates":[16.3183326721,48.0863113403],"type":"Point"}
}