{
  "type": "Feature",
  "properties": {
    "addr:full":"Waldweg 5 Pernegg an der Mur Steiermark 8132",
    "addr:housenumber":"5",
    "addr:postcode":"8132",
    "addr:street":"Waldweg",
    "iso:country":"AT",
    "sg:address":"Waldweg 5",
    "sg:city":"Pernegg an der Mur",
    "sg:orig_category":"Installationsunternehmen",
    "sg:phone":"+43 3867 5050",
    "sg:postcode":"8132",
    "sg:province":"Steiermark",
    "sg:website":"eder-installationen.at",
    "wof:name":"Eder Fritz",
    "wof:placetype":"venue"
},
  "geometry": {"coordinates":[15.3306293488,47.362865448],"type":"Point"}
}