{
  "type": "Feature",
  "properties": {
    "iso:country":"AT",
    "sg:address":"Eisplatzg 5",
    "sg:city":"Dornbirn",
    "sg:orig_category":"Berufsschulen",
    "sg:phone":"+43 5572 243170",
    "sg:postcode":"6850",
    "sg:province":"Vorarlberg",
    "wof:name":"Landesberufschule Dornbirn 2",
    "wof:placetype":"venue"
},
  "geometry": {"coordinates":[9.7488956451,47.42004776],"type":"Point"}
}