{
  "type": "Feature",
  "properties": {
    "addr:full":"Untere Postg 115 Tamsweg Salzburg 5580",
    "addr:housenumber":"115",
    "addr:postcode":"5580",
    "addr:street":"Untere Postg;Salzburg",
    "iso:country":"AT",
    "sg:address":"Untere Postg 115",
    "sg:city":"Tamsweg",
    "sg:orig_category":"Immobilienverwaltungen",
    "sg:phone":"+43 6474 6404",
    "sg:postcode":"5580",
    "sg:province":"Salzburg",
    "wof:name":"Rohringer Marianne Mag",
    "wof:placetype":"venue"
},
  "geometry": {"coordinates":[13.8081188202,47.1258583069],"type":"Point"}
}