{
  "type": "Feature",
  "properties": {
    "addr:full":"Raiffeisenstr Kiosk Trumau Nieder\u00f6sterreich 2521",
    "addr:postcode":"2521",
    "addr:street":"Niederoesterreich",
    "iso:country":"AT",
    "sg:address":"Raiffeisenstr Kiosk",
    "sg:city":"Trumau",
    "sg:orig_category":"Tabaktrafiken",
    "sg:phone":"+43 2253 7788",
    "sg:postcode":"2521",
    "sg:province":"Nieder\u00f6sterreich",
    "wof:name":"Rauch Hanni",
    "wof:placetype":"venue"
},
  "geometry": {"coordinates":[16.3423233032,47.9932975769],"type":"Point"}
}