{
  "type": "Feature",
  "properties": {
    "addr:full":"Georg-Erber-Str 5 Ach Ober\u00f6sterreich 5122",
    "addr:housenumber":"5",
    "addr:postcode":"5122",
    "addr:street":"Georg-Erber-Str;Ach Oberoesterreich",
    "iso:country":"AT",
    "sg:address":"Georg-Erber-Str 5",
    "sg:city":"Ach",
    "sg:orig_category":"Fu\u00c3\u0178pflege U Fu\u00c3\u0178pflegesalons",
    "sg:phone":"+43 4377 272510",
    "sg:postcode":"5122",
    "sg:province":"Ober\u00f6sterreich",
    "wof:name":"Reichenauer Marietta",
    "wof:placetype":"venue"
},
  "geometry": {"coordinates":[12.8384571075,48.1508712769],"type":"Point"}
}