{
  "type": "Feature",
  "properties": {
    "addr:full":"Geierau 1 Haag am Hausruck Ober\u00f6sterreich 4680",
    "addr:housenumber":"1",
    "addr:postcode":"4680",
    "addr:street":"Geierau",
    "iso:country":"AT",
    "sg:address":"Geierau 1",
    "sg:city":"Haag am Hausruck",
    "sg:classifiers":[
        {
            "category":"Parking",
            "subcategory":"Lot",
            "type":"Transportation"
        }
    ],
    "sg:phone":"+43 4377 3222460",
    "sg:postcode":"4680",
    "sg:province":"Ober\u00f6sterreich",
    "sg:tags":[
        "transport",
        "road"
    ],
    "wof:name":"ALBERT AIGNER GESMBH",
    "wof:placetype":"venue"
},
  "geometry": {"coordinates":[13.6453533173,48.200592041],"type":"Point"}
}