{
  "type": "Feature",
  "properties": {
    "addr:full":"IZ N\u00d6 S\u00fcd Str 10 Obj 60 2355",
    "addr:housenumber":"obj 60",
    "addr:postcode":"2355",
    "addr:street":"Str 10",
    "iso:country":"AT",
    "sg:address":"IZ N\u00d6 S\u00fcd Str 10 Obj 60",
    "sg:orig_category":"Schleif- U Poliermittel",
    "sg:phone":"+43 4322 36637750",
    "sg:postcode":"2355",
    "wof:name":"Lukas Fr\u00e4sen-Schleifen-Polieren VertriebsgesmbH",
    "wof:placetype":"venue"
},
  "geometry": {"coordinates":[16.3183326721,48.0863113403],"type":"Point"}
}