{
  "type": "Feature",
  "properties": {
    "iso:country":"AT",
    "sg:address":"Judeng 8",
    "sg:city":"Mattersburg",
    "sg:orig_category":"Blumeneinzelhandel",
    "sg:phone":"+43 2626 62531",
    "sg:postcode":"7210",
    "sg:province":"Burgenland",
    "wof:name":"Meissl Karin",
    "wof:placetype":"venue"
},
  "geometry": {"coordinates":[16.3997211456,47.7385482788],"type":"Point"}
}