{
  "type": "Feature",
  "properties": {
    "addr:full":"Leuthnersdlg Hadersdorf am Kamp Nieder\u00f6sterreich 3493",
    "addr:postcode":"3493",
    "addr:street":"Niederoesterreich",
    "iso:country":"AT",
    "sg:address":"Leuthnersdlg",
    "sg:city":"Hadersdorf am Kamp",
    "sg:orig_category":"Feuerwehren",
    "sg:phone":"+43 2735 2222",
    "sg:postcode":"3493",
    "sg:province":"Nieder\u00f6sterreich",
    "wof:name":"Freiwillige Feuerwehr Hadersdorf",
    "wof:placetype":"venue"
},
  "geometry": {"coordinates":[15.7206754684,48.4590759277],"type":"Point"}
}