{
  "type": "Feature",
  "properties": {
    "addr:full":"Nr 282 Gratwein Steiermark 8112",
    "addr:postcode":"8112",
    "addr:street":"Nr",
    "iso:country":"AT",
    "sg:address":"Nr 282",
    "sg:city":"Gratwein",
    "sg:orig_category":"Massagen",
    "sg:phone":"+43 4331 2453068",
    "sg:postcode":"8112",
    "sg:province":"Steiermark",
    "wof:name":"Massagefachinstitut Karin Jamnik",
    "wof:placetype":"venue"
},
  "geometry": {"coordinates":[15.3184213638,47.1293487549],"type":"Point"}
}