{
  "type": "Feature",
  "properties": {
    "iso:country":"AT",
    "sg:address":"Marienstrasse 23",
    "sg:city":"Eichgraben",
    "sg:orig_category":"Illumination Design, Planning, And Architecture",
    "sg:phone":"+43 2773 43534",
    "sg:postcode":"3032",
    "sg:province":"Nieder\u00f6sterreich",
    "wof:name":"Lichttechnische Planung Techn. B\u00fcro f. Lichtplanung",
    "wof:placetype":"venue"
},
  "geometry": {"coordinates":[15.9790668488,48.1884841919],"type":"Point"}
}