{
  "type": "Feature",
  "properties": {
    "iso:country":"AT",
    "sg:address":"Hadikg 54",
    "sg:city":"Wien",
    "sg:orig_category":"Tapezierer U Dekorateure",
    "sg:phone":"+43 1 8945403",
    "sg:postcode":"1140",
    "sg:province":"Wien",
    "wof:name":"Mischek Erich",
    "wof:placetype":"venue"
},
  "geometry": {"coordinates":[16.3058776855,48.1883163452],"type":"Point"}
}