{
  "type": "Feature",
  "properties": {
    "addr:full":"Graben 32b Linz Ober\u00f6sterreich 4020",
    "addr:housenumber":"32b",
    "addr:postcode":"4020",
    "addr:street":"Graben",
    "iso:country":"AT",
    "sg:address":"Graben 32b",
    "sg:city":"Linz",
    "sg:orig_category":"Beteiligungen U Finanzierungen",
    "sg:phone":"+43 4373 27954540",
    "sg:postcode":"4020",
    "sg:province":"Ober\u00f6sterreich",
    "wof:name":"\u00f6ko-Plan Wirtschaftsberatungs GesmbH",
    "wof:placetype":"venue"
},
  "geometry": {"coordinates":[14.2885694504,48.3047523499],"type":"Point"}
}