{
  "type": "Feature",
  "properties": {
    "iso:country":"AT",
    "sg:address":"Dorfstr 93D",
    "sg:city":"Rattenberg",
    "sg:classifiers":[
        {
            "category":"Professional",
            "subcategory":"Art Services",
            "type":"Services"
        }
    ],
    "sg:phone":"+43 5337 66533",
    "sg:postcode":"6240",
    "sg:province":"Tirol",
    "sg:tags":[
        "designer"
    ],
    "wof:name":"Design & Concept",
    "wof:placetype":"venue"
},
  "geometry": {"coordinates":[11.9041719437,47.4463653564],"type":"Point"}
}