{
  "type": "Feature",
  "properties": {
    "addr:full":"Pichlhofstr 62 Altm\u00fcnster Ober\u00f6sterreich 4813",
    "addr:housenumber":"62",
    "addr:postcode":"4813",
    "addr:street":"Pichlhofstr;Oberoesterreich",
    "iso:country":"AT",
    "sg:address":"Pichlhofstr 62",
    "sg:city":"Altm\u00fcnster",
    "sg:orig_category":"Berufsschulen",
    "sg:phone":"+43 7612872630",
    "sg:postcode":"4813",
    "sg:province":"Ober\u00f6sterreich",
    "wof:name":"Landwirtschaftsschule des Landes Ober\u00f6sterreich",
    "wof:placetype":"venue"
},
  "geometry": {"coordinates":[13.7714529037,47.879486084],"type":"Point"}
}