{
  "type": "Feature",
  "properties": {
    "addr:full":"Laudongasse 52 Wien Wien 1080",
    "addr:housenumber":"52",
    "addr:postcode":"1080",
    "addr:street":"Laudongasse",
    "iso:country":"AT",
    "sg:address":"Laudongasse 52",
    "sg:city":"Wien",
    "sg:classifiers":[
        {
            "category":"Shopping",
            "subcategory":"Books",
            "type":"Retail Goods"
        }
    ],
    "sg:phone":"+43 664 3004307",
    "sg:postcode":"1080",
    "sg:province":"Wien",
    "wof:name":"Alfred Bobik Ges.m.b.H.",
    "wof:placetype":"venue"
},
  "geometry": {"coordinates":[16.3430728912,48.2132797241],"type":"Point"}
}