{
  "type": "Feature",
  "properties": {
    "addr:full":"D\u00f6rfl 16 Waldhausen im Strudengau Ober\u00f6sterreich 4391",
    "addr:housenumber":"16",
    "addr:postcode":"4391",
    "addr:street":"Doerfl",
    "iso:country":"AT",
    "sg:address":"D\u00f6rfl 16",
    "sg:city":"Waldhausen im Strudengau",
    "sg:orig_category":"Textildruckereien",
    "sg:phone":"+43 4372 604116",
    "sg:postcode":"4391",
    "sg:province":"Ober\u00f6sterreich",
    "wof:name":"Gamerith Werner u Tatjana",
    "wof:placetype":"venue"
},
  "geometry": {"coordinates":[14.9481801987,48.2729988098],"type":"Point"}
}