{
  "type": "Feature",
  "properties": {
    "iso:country":"AT",
    "sg:address":"Regensburger Strasse 9",
    "sg:city":"Linz",
    "sg:classifiers":[
        {
            "category":"Professional",
            "subcategory":"Management & Consulting",
            "type":"Services"
        }
    ],
    "sg:phone":"+43 732 7716270",
    "sg:postcode":"4020",
    "sg:province":"Ober\u00f6sterreich",
    "sg:tags":[
        "logistics"
    ],
    "wof:name":"DDSG-Cargo GmbH",
    "wof:placetype":"venue"
},
  "geometry": {"coordinates":[14.3180809021,48.3124809265],"type":"Point"}
}