{
  "type": "Feature",
  "properties": {
    "iso:country":"AT",
    "sg:address":"Dorf 500",
    "sg:city":"Kitzb\u00fchel",
    "sg:orig_category":"Tourismusinformation U -Organisationen",
    "sg:phone":"+43 4353 566215535",
    "sg:postcode":"6370",
    "sg:province":"Tirol",
    "wof:name":"Tourismusverband Reith-Aurach",
    "wof:placetype":"venue"
},
  "geometry": {"coordinates":[12.3446426392,47.4752044678],"type":"Point"}
}