{
  "type": "Feature",
  "properties": {
    "addr:full":"Jakling 110 St. Andr\u00e4 K\u00e4rnten 9433",
    "addr:housenumber":"110",
    "addr:postcode":"9433",
    "addr:street":"Jakling;Kaernten",
    "iso:country":"AT",
    "sg:address":"Jakling 110",
    "sg:city":"St. Andr\u00e4",
    "sg:classifiers":[
        {
            "category":"Building & Trades",
            "subcategory":"Construction",
            "type":"Services"
        }
    ],
    "sg:phone":"+43 4358 2341",
    "sg:postcode":"9433",
    "sg:province":"K\u00e4rnten",
    "sg:tags":[
        "installation",
        "air-conditioning",
        "system"
    ],
    "wof:name":"Josef Sagorz",
    "wof:placetype":"venue"
},
  "geometry": {"coordinates":[14.8385267258,46.7631072998],"type":"Point"}
}