{
  "type": "Feature",
  "properties": {
    "addr:full":"Lehner 446 Neustift im Stubaital Tirol 6167",
    "addr:housenumber":"446",
    "addr:postcode":"6167",
    "addr:street":"Lehner;Tirol",
    "iso:country":"AT",
    "sg:address":"Lehner 446",
    "sg:city":"Neustift im Stubaital",
    "sg:orig_category":"Musikgruppen",
    "sg:phone":"+43 4366 45653237",
    "sg:postcode":"6167",
    "sg:province":"Tirol",
    "wof:name":"Die Stubaitaler - Christian Neunhauserer",
    "wof:placetype":"venue"
},
  "geometry": {"coordinates":[11.306022644,47.1065368652],"type":"Point"}
}