{
  "type": "Feature",
  "properties": {
    "addr:full":"Steing 10-14/2 Wien Wien 1030",
    "addr:housenumber":"10-14 / 2",
    "addr:postcode":"1030",
    "iso:country":"AT",
    "sg:address":"Steing 10-14/2",
    "sg:city":"Wien",
    "sg:orig_category":"\u00c3\u201erzte / F Allgemeinmedizin",
    "sg:phone":"+43 1 7148304",
    "sg:postcode":"1030",
    "sg:province":"Wien",
    "wof:name":"Irmak Seng\u00fcl Dr",
    "wof:placetype":"venue"
},
  "geometry": {"coordinates":[16.4025096893,48.1936683655],"type":"Point"}
}