{
  "type": "Feature",
  "properties": {
    "addr:full":"Metzentaler 7 Axams Tirol 6094",
    "addr:housenumber":"7",
    "addr:postcode":"6094",
    "addr:street":"Metzentaler;Tirol",
    "iso:country":"AT",
    "sg:address":"Metzentaler 7",
    "sg:city":"Axams",
    "sg:orig_category":"Installationsunternehmen",
    "sg:phone":"+43 5234 68147",
    "sg:postcode":"6094",
    "sg:province":"Tirol",
    "wof:name":"Nagl & S\u00f6hne GesmbH",
    "wof:placetype":"venue"
},
  "geometry": {"coordinates":[11.2855176926,47.2312049866],"type":"Point"}
}