{
  "type": "Feature",
  "properties": {
    "addr:full":"Erdbergstrasse 170 Wien Wien 1030",
    "addr:housenumber":"170",
    "addr:postcode":"1030",
    "addr:street":"Erdbergstrasse",
    "iso:country":"AT",
    "sg:address":"Erdbergstrasse 170",
    "sg:city":"Wien",
    "sg:orig_category":"Hair Nets",
    "sg:phone":"+43 1 7989548",
    "sg:postcode":"1030",
    "sg:province":"Wien",
    "wof:name":"Scheitz & Nagler KEG",
    "wof:placetype":"venue"
},
  "geometry": {"coordinates":[16.4091129303,48.1941986084],"type":"Point"}
}