{
  "type": "Feature",
  "properties": {
    "addr:full":"Marktpl 4 B\u00f6heimkirchen Nieder\u00f6sterreich 3071",
    "addr:housenumber":"4",
    "addr:postcode":"3071",
    "addr:street":"Marktpl;Niederoesterreich",
    "iso:country":"AT",
    "sg:address":"Marktpl 4",
    "sg:city":"B\u00f6heimkirchen",
    "sg:orig_category":"Blumeneinzelhandel",
    "sg:phone":"+43 2743 3659",
    "sg:postcode":"3071",
    "sg:province":"Nieder\u00f6sterreich",
    "wof:name":"M\u00fcller Ernst",
    "wof:placetype":"venue"
},
  "geometry": {"coordinates":[7.7521400452,47.9156341553],"type":"Point"}
}