{
  "type": "Feature",
  "properties": {
    "addr:full":"R\u00e4tikonstr 40 Vandans Vorarlberg 6773",
    "addr:housenumber":"40",
    "addr:postcode":"6773",
    "addr:street":"Raetikonstr",
    "iso:country":"AT",
    "sg:address":"R\u00e4tikonstr 40",
    "sg:city":"Vandans",
    "sg:orig_category":"Pensionen / Privatzimmer",
    "sg:phone":"+43 5556 735880",
    "sg:postcode":"6773",
    "sg:province":"Vorarlberg",
    "wof:name":"G\u00e4stehaus Banella",
    "wof:placetype":"venue"
},
  "geometry": {"coordinates":[9.8607311249,47.0943145752],"type":"Point"}
}