{
  "type": "Feature",
  "properties": {
    "iso:country":"AT",
    "sg:address":"M\u00fcnchner Str 114",
    "sg:city":"Seefeld in Tirol",
    "sg:classifiers":[
        {
            "category":"Travel",
            "subcategory":"Hotels & Motels",
            "type":"Entertainment"
        }
    ],
    "sg:phone":"+43 5212 2221",
    "sg:postcode":"6100",
    "sg:province":"Tirol",
    "wof:name":"Hotel Tyrol",
    "wof:placetype":"venue"
},
  "geometry": {"coordinates":[11.1889953613,47.3294143677],"type":"Point"}
}