{
  "type": "Feature",
  "properties": {
    "addr:full":"Hammerfestweg 3 Wien Wien 1220",
    "addr:housenumber":"3",
    "addr:postcode":"1220",
    "addr:street":"Hammerfestweg",
    "iso:country":"AT",
    "sg:address":"Hammerfestweg 3",
    "sg:city":"Wien",
    "sg:orig_category":"Ambulatorien",
    "sg:phone":"+43 1 2807008",
    "sg:postcode":"1220",
    "sg:province":"Wien",
    "wof:name":"Sonderp\u00e4dagogische Ambulanzen der Stadt Wien (MA 11A)",
    "wof:placetype":"venue"
},
  "geometry": {"coordinates":[16.4712257385,48.2150039673],"type":"Point"}
}