{
  "type": "Feature",
  "properties": {
    "addr:full":"Malta 91 Malta K\u00e4rnten 9854",
    "addr:housenumber":"91",
    "addr:postcode":"9854",
    "addr:street":"Malta;Kaernten",
    "iso:country":"AT",
    "sg:address":"Malta 91",
    "sg:city":"Malta",
    "sg:classifiers":[
        {
            "category":"Home & Garden",
            "subcategory":"Furniture",
            "type":"Retail Goods"
        }
    ],
    "sg:phone":"+43 4733 223",
    "sg:postcode":"9854",
    "sg:province":"K\u00e4rnten",
    "sg:tags":[
        "bathroom"
    ],
    "wof:name":"Gerhard Truskaller",
    "wof:placetype":"venue"
},
  "geometry": {"coordinates":[13.5123491287,46.9512329102],"type":"Point"}
}