{
  "type": "Feature",
  "properties": {
    "iso:country":"AT",
    "sg:address":"Zweil\u00e4nderstr 8",
    "sg:city":"Gm\u00fcnd",
    "sg:orig_category":"Beratungsstellen",
    "sg:phone":"+43 2852 5434345",
    "sg:postcode":"3950",
    "sg:province":"Nieder\u00f6sterreich",
    "wof:name":"Arge Grenznutzen - Erwin Kreuzwieser",
    "wof:placetype":"venue"
},
  "geometry": {"coordinates":[14.9799671173,48.7841682434],"type":"Point"}
}