{
  "type": "Feature",
  "properties": {
    "addr:full":"Kornpl 5 Langenlois Nieder\u00f6sterreich 3550",
    "addr:housenumber":"5",
    "addr:postcode":"3550",
    "addr:street":"Kornpl",
    "iso:country":"AT",
    "sg:address":"Kornpl 5",
    "sg:city":"Langenlois",
    "sg:orig_category":"Bars-Cafes",
    "sg:phone":"+43 4327 3420002",
    "sg:postcode":"3550",
    "sg:province":"Nieder\u00f6sterreich",
    "wof:name":"Cafe & Wein Ursin Haus",
    "wof:placetype":"venue"
},
  "geometry": {"coordinates":[15.6769189835,48.4736824036],"type":"Point"}
}