{
  "type": "Feature",
  "properties": {
    "iso:country":"AT",
    "sg:address":"Waldhofweg 27",
    "sg:city":"Klagenfurt",
    "sg:orig_category":"Rauchfangkehrer",
    "sg:phone":"+43 463 42750",
    "sg:postcode":"9020",
    "sg:province":"K\u00e4rnten",
    "wof:name":"Jeschofnig Harry Prof",
    "wof:placetype":"venue"
},
  "geometry": {"coordinates":[14.293387413,46.6376495361],"type":"Point"}
}