{
  "type": "Feature",
  "properties": {
    "addr:full":"Kapruner-Generator-Str 29 Weiz Steiermark 8160",
    "addr:housenumber":"29",
    "addr:postcode":"8160",
    "addr:street":"Kapruner-Generator-Str",
    "iso:country":"AT",
    "sg:address":"Kapruner-Generator-Str 29",
    "sg:city":"Weiz",
    "sg:orig_category":"Musikgruppen",
    "sg:phone":"+43 4331 7238666",
    "sg:postcode":"8160",
    "sg:province":"Steiermark",
    "wof:name":"Elin-Stadtkapelle Weiz",
    "wof:placetype":"venue"
},
  "geometry": {"coordinates":[15.6264476776,47.2196121216],"type":"Point"}
}