{
  "type": "Feature",
  "properties": {
    "addr:full":"Hauptstr 32 Gallneukirchen Ober\u00f6sterreich 4210",
    "addr:housenumber":"32",
    "addr:postcode":"4210",
    "addr:street":"Hauptstr;Oberoesterreich",
    "iso:country":"AT",
    "sg:address":"Hauptstr 32",
    "sg:city":"Gallneukirchen",
    "sg:orig_category":"Optiker",
    "sg:phone":"+43 4372 3562456",
    "sg:postcode":"4210",
    "sg:province":"Ober\u00f6sterreich",
    "wof:name":"Brillen-Kontaktlinsen Oppenborn GesmbH",
    "wof:placetype":"venue"
},
  "geometry": {"coordinates":[14.4172143936,48.3539810181],"type":"Point"}
}