{
  "type": "Feature",
  "properties": {
    "addr:full":"Nr 13a Stuben Vorarlberg 6762",
    "addr:postcode":"6762",
    "addr:street":"Nr;Stuben",
    "iso:country":"AT",
    "sg:address":"Nr 13a",
    "sg:city":"Stuben",
    "sg:orig_category":"Lebensmittel / Einzelhandel",
    "sg:phone":"+43 5582 739",
    "sg:postcode":"6762",
    "sg:province":"Vorarlberg",
    "wof:name":"Herbert's Dorf-Laden",
    "wof:placetype":"venue"
},
  "geometry": {"coordinates":[10.1580495834,47.1391792297],"type":"Point"}
}