{
  "type": "Feature",
  "properties": {
    "addr:full":"\u00dcbergangrotte 24 Frankenfels Nieder\u00f6sterreich 3213",
    "addr:housenumber":"24",
    "addr:postcode":"3213",
    "addr:street":"U\u0308Bergangrotte;Niederoesterreich",
    "iso:country":"AT",
    "sg:address":"\u00dcbergangrotte 24",
    "sg:city":"Frankenfels",
    "sg:orig_category":"Transportunternehmen",
    "sg:phone":"+43 2725 7343",
    "sg:postcode":"3213",
    "sg:province":"Nieder\u00f6sterreich",
    "wof:name":"Enner Karl",
    "wof:placetype":"venue"
},
  "geometry": {"coordinates":[15.3225898743,47.9807357788],"type":"Point"}
}