{
  "type": "Feature",
  "properties": {
    "addr:full":"Ennserstrasse 76 Gleink Ober\u00f6sterreich 4407",
    "addr:housenumber":"76",
    "addr:postcode":"4407",
    "addr:street":"Ennserstrasse",
    "iso:country":"AT",
    "sg:address":"Ennserstrasse 76",
    "sg:city":"Gleink",
    "sg:classifiers":[
        {
            "category":"Manufacturing",
            "subcategory":"Wood Products",
            "type":"Manufacturing & Wholesale Goods"
        }
    ],
    "sg:phone":"+43 7252 728210",
    "sg:postcode":"4407",
    "sg:province":"Ober\u00f6sterreich",
    "sg:tags":[
        "firewood"
    ],
    "wof:name":"Hans Moidl Laubholz-S\u00e4gewerk u. Holzhandel Ges.m.b.H.",
    "wof:placetype":"venue"
},
  "geometry": {"coordinates":[14.4243116379,48.0731010437],"type":"Point"}
}