{
  "type": "Feature",
  "properties": {
    "iso:country":"AT",
    "sg:address":"L\u00f6weng 1",
    "sg:city":"Altach",
    "sg:classifiers":[
        {
            "category":"Home & Garden",
            "subcategory":"Garden Supply",
            "type":"Retail Goods"
        }
    ],
    "sg:phone":"+43 5576 725740",
    "sg:postcode":"6844",
    "sg:province":"Vorarlberg",
    "sg:tags":[
        "schotter",
        "sand",
        "u"
    ],
    "wof:name":"Kopf Hermann KG",
    "wof:placetype":"venue"
},
  "geometry": {"coordinates":[9.6511898041,47.3536758423],"type":"Point"}
}