{
  "type": "Feature",
  "properties": {
    "iso:country":"AT",
    "sg:address":"Moosweg 4",
    "sg:city":"Hartkirchen",
    "sg:orig_category":"Tischlereien",
    "sg:phone":"+43 7273 8110",
    "sg:postcode":"4081",
    "sg:province":"Ober\u00f6sterreich",
    "wof:name":"Breit Alfred jun",
    "wof:placetype":"venue"
},
  "geometry": {"coordinates":[14.0027256012,48.3642959595],"type":"Point"}
}