{
  "type": "Feature",
  "properties": {
    "addr:full":"Schubertring 4 Wien Wien 1010",
    "addr:housenumber":"4",
    "addr:postcode":"1010",
    "addr:street":"Schubertring",
    "iso:country":"AT",
    "sg:address":"Schubertring 4",
    "sg:city":"Wien",
    "sg:orig_category":"Friseure U Frisiersalons",
    "sg:phone":"+43 4315 133959",
    "sg:postcode":"1010",
    "sg:province":"Wien",
    "wof:name":"Frisiersalon Willy",
    "wof:placetype":"venue"
},
  "geometry": {"coordinates":[16.3759117126,48.2030754089],"type":"Point"}
}