{
  "type": "Feature",
  "properties": {
    "iso:country":"AT",
    "sg:address":"Kremser Str 22a",
    "sg:city":"Herzogenburg",
    "sg:orig_category":"Transportunternehmen",
    "sg:phone":"+43 2782 83237",
    "sg:postcode":"3130",
    "sg:province":"Nieder\u00f6sterreich",
    "wof:name":"Willach GesmbH & Co KG",
    "wof:placetype":"venue"
},
  "geometry": {"coordinates":[15.6932344437,48.2882728577],"type":"Point"}
}