{
  "type": "Feature",
  "properties": {
    "addr:full":"Zemannstr 26a Freistadt Ober\u00f6sterreich 4240",
    "addr:housenumber":"26a",
    "addr:postcode":"4240",
    "addr:street":"Zemannstr",
    "iso:country":"AT",
    "sg:address":"Zemannstr 26a",
    "sg:city":"Freistadt",
    "sg:orig_category":"Versicherungsunternehmen",
    "sg:phone":"+43 7942 72655",
    "sg:postcode":"4240",
    "sg:province":"Ober\u00f6sterreich",
    "wof:name":"Grazer Wechselseitige Versicherung AG",
    "wof:placetype":"venue"
},
  "geometry": {"coordinates":[14.5041790009,48.5069465637],"type":"Point"}
}