{
  "type": "Feature",
  "properties": {
    "addr:full":"Johann-Galler-Str 3 Wolkersdorf im Weinviertel Nieder\u00f6sterreich 2120",
    "addr:housenumber":"3",
    "addr:postcode":"2120",
    "addr:street":"Johann-Galler-Str",
    "iso:country":"AT",
    "sg:address":"Johann-Galler-Str 3",
    "sg:city":"Wolkersdorf im Weinviertel",
    "sg:orig_category":"Maler, Anstreicher U Lackierer",
    "sg:phone":"+43 4322 456051",
    "sg:postcode":"2120",
    "sg:province":"Nieder\u00f6sterreich",
    "wof:name":"Regber Christian GmbH",
    "wof:placetype":"venue"
},
  "geometry": {"coordinates":[16.5102272034,48.3766860962],"type":"Point"}
}