{
  "type": "Feature",
  "properties": {
    "addr:full":"Lendkai 95 Graz Steiermark 8020",
    "addr:housenumber":"95",
    "addr:postcode":"8020",
    "addr:street":"Lendkai",
    "iso:country":"AT",
    "sg:address":"Lendkai 95",
    "sg:city":"Graz",
    "sg:orig_category":"Spenglereien, Schwarzdeckereien, Dachdeckereien",
    "sg:phone":"+43 316 723130",
    "sg:postcode":"8020",
    "sg:province":"Steiermark",
    "wof:name":"Bau & Dach GmbH Spenglerei-Dachdeckerei",
    "wof:placetype":"venue"
},
  "geometry": {"coordinates":[15.4307098389,47.07970047],"type":"Point"}
}