{
  "type": "Feature",
  "properties": {
    "addr:full":"Niclas-Strobl-Weg 3 Neuhart Steiermark 8053",
    "addr:housenumber":"3",
    "addr:postcode":"8053",
    "addr:street":"Niclas-Strobl-Weg",
    "iso:country":"AT",
    "sg:address":"Niclas-Strobl-Weg 3",
    "sg:city":"Neuhart",
    "sg:orig_category":"Exporteure U Importeure",
    "sg:phone":"+43 4331 6271882",
    "sg:postcode":"8053",
    "sg:province":"Steiermark",
    "wof:name":"H. L. Handels- u Beteilungs GmbH",
    "wof:placetype":"venue"
},
  "geometry": {"coordinates":[15.4159431458,47.0478172302],"type":"Point"}
}