{
  "type": "Feature",
  "properties": {
    "addr:full":"Stollenstr 8 Thaur Tirol 6065",
    "addr:housenumber":"8",
    "addr:postcode":"6065",
    "addr:street":"Stollenstr;Tirol",
    "iso:country":"AT",
    "sg:address":"Stollenstr 8",
    "sg:city":"Thaur",
    "sg:orig_category":"Zimmereien",
    "sg:phone":"+43 5223 492846",
    "sg:postcode":"6065",
    "sg:province":"Tirol",
    "wof:name":"M\u00f6sslacher Walter",
    "wof:placetype":"venue"
},
  "geometry": {"coordinates":[11.4722518921,47.2955627441],"type":"Point"}
}