{
  "type": "Feature",
  "properties": {
    "iso:country":"AT",
    "sg:address":"Neubaug 29",
    "sg:city":"Wien",
    "sg:orig_category":"Immobilienverwaltungen",
    "sg:phone":"+43 1 52384340",
    "sg:postcode":"1070",
    "sg:province":"Wien",
    "wof:name":"Maltschnig-Gebauer Edith",
    "wof:placetype":"venue"
},
  "geometry": {"coordinates":[16.3383293152,48.2016792297],"type":"Point"}
}