{
  "type": "Feature",
  "properties": {
    "addr:full":"Prossegg 9 Matrei in Osttirol Tirol 9971",
    "addr:housenumber":"9",
    "addr:postcode":"9971",
    "addr:street":"Prossegg;Tirol",
    "iso:country":"AT",
    "sg:address":"Prossegg 9",
    "sg:city":"Matrei in Osttirol",
    "sg:orig_category":"Pensionen / Privatzimmer",
    "sg:phone":"+43 4348 756211",
    "sg:postcode":"9971",
    "sg:province":"Tirol",
    "wof:name":"Ortner Josef",
    "wof:placetype":"venue"
},
  "geometry": {"coordinates":[12.538105011,47.0025177002],"type":"Point"}
}