{
  "type": "Feature",
  "properties": {
    "addr:full":"Wolfholzg. 18 Brunn am Gebirge Nieder\u00f6sterreich 2345",
    "addr:housenumber":"18",
    "addr:postcode":"2345",
    "addr:street":"Wolfholzg.",
    "iso:country":"AT",
    "sg:address":"Wolfholzg. 18",
    "sg:city":"Brunn am Gebirge",
    "sg:classifiers":[
        {
            "category":"Parking",
            "subcategory":"Lot",
            "type":"Transportation"
        }
    ],
    "sg:phone":"+43 4322 3631500",
    "sg:postcode":"2345",
    "sg:province":"Nieder\u00f6sterreich",
    "sg:tags":[
        "transport",
        "road"
    ],
    "wof:name":"KARL AUGUSTIN GMBH",
    "wof:placetype":"venue"
},
  "geometry": {"coordinates":[16.2931842804,48.1189994812],"type":"Point"}
}