{
  "type": "Feature",
  "properties": {
    "addr:full":"Meiselstr 45 Wien Wien 1150",
    "addr:housenumber":"45",
    "addr:postcode":"1150",
    "addr:street":"Meiselstr",
    "iso:country":"AT",
    "sg:address":"Meiselstr 45",
    "sg:city":"Wien",
    "sg:orig_category":"Installationsunternehmen",
    "sg:phone":"+43 1 7862211",
    "sg:postcode":"1150",
    "sg:province":"Wien",
    "sg:website":"weg-i.at",
    "wof:name":"Wegscheider Peter GmbH",
    "wof:placetype":"venue"
},
  "geometry": {"coordinates":[16.3144283295,48.1978645325],"type":"Point"}
}