{
  "type": "Feature",
  "properties": {
    "iso:country":"AT",
    "sg:address":"Oed 48",
    "sg:city":"Markt Hartmannsdorf",
    "sg:classifiers":[
        {
            "category":"Home & Garden",
            "subcategory":"Home Furnishings",
            "type":"Retail Goods"
        }
    ],
    "sg:phone":"+43 4331 142305",
    "sg:postcode":"8311",
    "sg:province":"Steiermark",
    "sg:tags":[
        "household"
    ],
    "wof:name":"BAUER GERHARD GESMBH",
    "wof:placetype":"venue"
},
  "geometry": {"coordinates":[15.7954015732,47.0541229248],"type":"Point"}
}