{
  "type": "Feature",
  "properties": {
    "iso:country":"AT",
    "sg:address":"Mallitschweg 5",
    "sg:city":"St. Peter",
    "sg:orig_category":"Tonstudios",
    "sg:phone":"+43 316 464208",
    "sg:postcode":"8042",
    "sg:province":"Steiermark",
    "wof:name":"Burghard Herwig",
    "wof:placetype":"venue"
},
  "geometry": {"coordinates":[15.4923429489,47.0711898804],"type":"Point"}
}