{
  "type": "Feature",
  "properties": {
    "addr:full":"Bahnstrasse 25 Neunkirchen Nieder\u00f6sterreich 2620",
    "addr:housenumber":"25",
    "addr:postcode":"2620",
    "addr:street":"Bahnstrasse",
    "iso:country":"AT",
    "sg:address":"Bahnstrasse 25",
    "sg:city":"Neunkirchen",
    "sg:classifiers":[
        {
            "category":"Structure",
            "subcategory":"Office Building",
            "type":"Public Place"
        }
    ],
    "sg:phone":"+43 2635 647560",
    "sg:postcode":"2620",
    "sg:province":"Nieder\u00f6sterreich",
    "sg:tags":[
        "construction",
        "apartment"
    ],
    "sg:website":"sgn.at",
    "wof:name":"Gemeinn\u00fctzige Wohnungs- und Siedlungsgenossenschaft Neunkirchen eg.Gen.m.b.H.",
    "wof:placetype":"venue"
},
  "geometry": {"coordinates":[16.0818786621,47.728717804],"type":"Point"}
}