{
  "type": "Feature",
  "properties": {
    "addr:full":"Wipplingerstr 30 Wien Wien 1010",
    "addr:housenumber":"30",
    "addr:postcode":"1010",
    "addr:street":"Wipplingerstr",
    "iso:country":"AT",
    "sg:address":"Wipplingerstr 30",
    "sg:city":"Wien",
    "sg:orig_category":"Holdinggesellschaften",
    "sg:phone":"+43 4315 134159",
    "sg:postcode":"1010",
    "sg:province":"Wien",
    "wof:name":"COALCO HOLDING GesmbH",
    "wof:placetype":"venue"
},
  "geometry": {"coordinates":[16.3676376343,48.2134742737],"type":"Point"}
}