{
  "type": "Feature",
  "properties": {
    "iso:country":"AT",
    "sg:address":"Markt 18",
    "sg:city":"St. Peter am Wimberg",
    "sg:orig_category":"Banken U Sparkassen",
    "sg:phone":"+43 4372 828004",
    "sg:postcode":"4171",
    "sg:province":"Ober\u00f6sterreich",
    "wof:name":"Raiffeisenbank M\u00fchltal regGenmbH",
    "wof:placetype":"venue"
},
  "geometry": {"coordinates":[14.085600853,48.5019416809],"type":"Point"}
}