{
  "type": "Feature",
  "properties": {
    "addr:full":"Bichling 6 Westendorf Tirol 6363",
    "addr:housenumber":"6",
    "addr:postcode":"6363",
    "addr:street":"Bichling",
    "iso:country":"AT",
    "sg:address":"Bichling 6",
    "sg:city":"Westendorf",
    "sg:classifiers":[
        {
            "category":"Professional",
            "subcategory":"Computer Services",
            "type":"Services"
        }
    ],
    "sg:phone":"+43 5334 28000",
    "sg:postcode":"6363",
    "sg:province":"Tirol",
    "sg:tags":[
        "software"
    ],
    "wof:name":"Lazzerini Jonni",
    "wof:placetype":"venue"
},
  "geometry": {"coordinates":[12.2231359482,47.4357528687],"type":"Point"}
}