{
  "type": "Feature",
  "properties": {
    "iso:country":"AT",
    "sg:address":"Karl-Morre-G 66",
    "sg:city":"Krieglach",
    "sg:orig_category":"Elektroinstallationsunternehmen",
    "sg:phone":"+43 3855 3697",
    "sg:postcode":"8670",
    "sg:province":"Steiermark",
    "wof:name":"Grabner Elektro Service",
    "wof:placetype":"venue"
},
  "geometry": {"coordinates":[15.5672521591,47.5419921875],"type":"Point"}
}