{
  "type": "Feature",
  "properties": {
    "iso:country":"AT",
    "sg:address":"Maria-Theresien-Str 4",
    "sg:city":"Innsbruck",
    "sg:classifiers":[
        {
            "category":"Professional",
            "type":"Services"
        }
    ],
    "sg:phone":"+43 4351 257596411",
    "sg:postcode":"6020",
    "sg:province":"Tirol",
    "sg:tags":[
        "leasing"
    ],
    "wof:name":"LEASFINANZ Aktiengesellschaft",
    "wof:placetype":"venue"
},
  "geometry": {"coordinates":[11.3935604095,47.2669029236],"type":"Point"}
}