{
  "type": "Feature",
  "properties": {
    "addr:full":"Gilmstr 4 B\u00fcrs Vorarlberg 6706",
    "addr:housenumber":"4",
    "addr:postcode":"6706",
    "addr:street":"Gilmstr",
    "iso:country":"AT",
    "sg:address":"Gilmstr 4",
    "sg:city":"B\u00fcrs",
    "sg:orig_category":"Dialyseinstitute",
    "sg:phone":"+43 5552 642740",
    "sg:postcode":"6706",
    "sg:province":"Vorarlberg",
    "wof:name":"Dialysestation B\u00fcrs GmbH",
    "wof:placetype":"venue"
},
  "geometry": {"coordinates":[9.8007211685,47.1571731567],"type":"Point"}
}