{
  "type": "Feature",
  "properties": {
    "addr:full":"Salcherstr 40A St. P\u00f6lten-Harland Nieder\u00f6sterreich 3104",
    "addr:housenumber":"40a",
    "addr:postcode":"3104",
    "addr:street":"Salcherstr",
    "iso:country":"AT",
    "sg:address":"Salcherstr 40A",
    "sg:city":"St. P\u00f6lten-Harland",
    "sg:orig_category":"Beschichtungen",
    "sg:phone":"+43 2742 882401",
    "sg:postcode":"3104",
    "sg:province":"Nieder\u00f6sterreich",
    "wof:name":"H\u00f6dl Manfred - Team Work Beschichtungstechnik",
    "wof:placetype":"venue"
},
  "geometry": {"coordinates":[15.6385211945,48.1689834595],"type":"Point"}
}