{
  "type": "Feature",
  "properties": {
    "addr:full":"Moosbauerweg 2 Kuchl Salzburg 5431",
    "addr:housenumber":"2",
    "addr:postcode":"5431",
    "addr:street":"Moosbauerweg;Salzburg",
    "iso:country":"AT",
    "sg:address":"Moosbauerweg 2",
    "sg:city":"Kuchl",
    "sg:orig_category":"Appartements / Ferienwohnungen",
    "sg:phone":"+43 6244 6255",
    "sg:postcode":"5431",
    "sg:province":"Salzburg",
    "wof:name":"Appartements-Ferienwohnungen Moosbauer - Fam E\u00dfl",
    "wof:placetype":"venue"
},
  "geometry": {"coordinates":[13.1590366364,47.6395835876],"type":"Point"}
}