{
  "type": "Feature",
  "properties": {
    "iso:country":"AT",
    "sg:address":"Nr 1",
    "sg:city":"Waldenstein",
    "sg:orig_category":"Non-Classified Establishments",
    "sg:phone":"+43 2855 203",
    "sg:postcode":"3961",
    "sg:province":"Nieder\u00f6sterreich",
    "wof:name":"Pfarramt",
    "wof:placetype":"venue"
},
  "geometry": {"coordinates":[15.0196552277,48.7288703918],"type":"Point"}
}