{
  "type": "Feature",
  "properties": {
    "addr:full":"Bertschingerstr 8 Krems an der Donau Nieder\u00f6sterreich 3500",
    "addr:housenumber":"8",
    "addr:postcode":"3500",
    "addr:street":"Bertschingerstr",
    "iso:country":"AT",
    "sg:address":"Bertschingerstr 8",
    "sg:city":"Krems an der Donau",
    "sg:orig_category":"Tankstellen",
    "sg:phone":"+43 2732 761700",
    "sg:postcode":"3500",
    "sg:province":"Nieder\u00f6sterreich",
    "wof:name":"Agip Station",
    "wof:placetype":"venue"
},
  "geometry": {"coordinates":[15.6014919281,48.4061355591],"type":"Point"}
}