{
  "type": "Feature",
  "properties": {
    "addr:full":"Emmy-Stradal-Str 32 Hollabrunn Nieder\u00f6sterreich 2020",
    "addr:housenumber":"32",
    "addr:postcode":"2020",
    "addr:street":"Emmy-Stradal-Str",
    "iso:country":"AT",
    "sg:address":"Emmy-Stradal-Str 32",
    "sg:city":"Hollabrunn",
    "sg:orig_category":"Lebensmittel / Einzelhandel",
    "sg:phone":"+43 2952 2473",
    "sg:postcode":"2020",
    "sg:province":"Nieder\u00f6sterreich",
    "wof:name":"Spar-Markt Duschet Wolfgang",
    "wof:placetype":"venue"
},
  "geometry": {"coordinates":[16.0806827545,48.5502891541],"type":"Point"}
}