{
  "type": "Feature",
  "properties": {
    "addr:full":"Senninger Str. 1 Stockerau Nieder\u00f6sterreich 2000",
    "addr:housenumber":"1",
    "addr:postcode":"2000",
    "addr:street":"Str.",
    "iso:country":"AT",
    "sg:address":"Senninger Str. 1",
    "sg:city":"Stockerau",
    "sg:classifiers":[
        {
            "category":"Utilities",
            "subcategory":"Electric",
            "type":"Services"
        }
    ],
    "sg:phone":"+43 4322 66624290",
    "sg:postcode":"2000",
    "sg:province":"Nieder\u00f6sterreich",
    "sg:tags":[
        "electricity"
    ],
    "wof:name":"STADTWERKE STOCKERAU",
    "wof:placetype":"venue"
},
  "geometry": {"coordinates":[16.2058391571,48.3942375183],"type":"Point"}
}