{
  "type": "Feature",
  "properties": {
    "addr:full":"Weyregger Str 89 Weyregg am Attersee Ober\u00f6sterreich 4852",
    "addr:postcode":"4852",
    "addr:street":"Str 89",
    "iso:country":"AT",
    "sg:address":"Weyregger Str 89",
    "sg:city":"Weyregg am Attersee",
    "sg:orig_category":"Gutsverwaltungen",
    "sg:phone":"+43 76642251",
    "sg:postcode":"4852",
    "sg:province":"Ober\u00f6sterreich",
    "wof:name":"Lennkh Gutsverwaltung",
    "wof:placetype":"venue"
},
  "geometry": {"coordinates":[13.5698814392,47.9001121521],"type":"Point"}
}