{
  "type": "Feature",
  "properties": {
    "addr:full":"Bayernstr 376 Wals Salzburg 5071",
    "addr:housenumber":"376",
    "addr:postcode":"5071",
    "addr:street":"Wals Salzburg",
    "iso:country":"AT",
    "sg:address":"Bayernstr 376",
    "sg:city":"Wals",
    "sg:orig_category":"Bauunternehmen",
    "sg:phone":"+43 662 8533370",
    "sg:postcode":"5071",
    "sg:province":"Salzburg",
    "wof:name":"Fritz & Co BaugesmbH",
    "wof:placetype":"venue"
},
  "geometry": {"coordinates":[12.9830379486,47.8185081482],"type":"Point"}
}