{
  "type": "Feature",
  "properties": {
    "addr:full":"Neustiftg 13 Wien Wien 1070",
    "addr:housenumber":"13",
    "addr:postcode":"1070",
    "addr:street":"Neustiftg",
    "iso:country":"AT",
    "sg:address":"Neustiftg 13",
    "sg:city":"Wien",
    "sg:orig_category":"Friseure U Frisiersalons",
    "sg:phone":"+43 1 5223293",
    "sg:postcode":"1070",
    "sg:province":"Wien",
    "wof:name":"AKWABA Gnagora KEG african center - afro-Frisuren",
    "wof:placetype":"venue"
},
  "geometry": {"coordinates":[16.3545303345,48.205368042],"type":"Point"}
}