{
  "type": "Feature",
  "properties": {
    "addr:full":"Fenzlg 42 Wien Wien 1150",
    "addr:housenumber":"42",
    "addr:postcode":"1150",
    "addr:street":"Fenzlg",
    "iso:country":"AT",
    "sg:address":"Fenzlg 42",
    "sg:city":"Wien",
    "sg:orig_category":"Rauchfangsanierungen U -Ausschleifungen",
    "sg:phone":"+43 4319 8255800",
    "sg:postcode":"1150",
    "sg:province":"Wien",
    "wof:name":"Ahrens Schornsteintechnik GesmbH",
    "wof:placetype":"venue"
},
  "geometry": {"coordinates":[16.3130893707,48.1944732666],"type":"Point"}
}