{
  "type": "Feature",
  "properties": {
    "iso:country":"AT",
    "sg:address":"Kirchenpl 5",
    "sg:city":"Wolfern",
    "sg:orig_category":"Polizei U Gendarmerie",
    "sg:phone":"+43 4359 1334157",
    "sg:postcode":"4493",
    "sg:province":"Ober\u00f6sterreich",
    "wof:name":"Gendarmerie",
    "wof:placetype":"venue"
},
  "geometry": {"coordinates":[14.3775043488,48.0834274292],"type":"Point"}
}