{
  "type": "Feature",
  "properties": {
    "addr:full":"Karl-Sch\u00f6nherr-Str 3 Lienz Tirol 9900",
    "addr:housenumber":"3",
    "addr:postcode":"9900",
    "addr:street":"Karl-Schoenherr-Str;Tirol",
    "iso:country":"AT",
    "sg:address":"Karl-Sch\u00f6nherr-Str 3",
    "sg:city":"Lienz",
    "sg:orig_category":"Tischlereien",
    "sg:phone":"+43 664 2103073",
    "sg:postcode":"9900",
    "sg:province":"Tirol",
    "wof:name":"Fritz & Obersteiner GmbH",
    "wof:placetype":"venue"
},
  "geometry": {"coordinates":[12.7684783936,46.8281173706],"type":"Point"}
}