{
  "type": "Feature",
  "properties": {
    "addr:full":"Karl-Vogt-Str 65 Zell am See Salzburg 5700",
    "addr:housenumber":"65",
    "addr:postcode":"5700",
    "addr:street":"Karl-Vogt-Str;Salzburg",
    "iso:country":"AT",
    "sg:address":"Karl-Vogt-Str 65",
    "sg:city":"Zell am See",
    "sg:orig_category":"Unternehmensberatung",
    "sg:phone":"+43 4365 42724950",
    "sg:postcode":"5700",
    "sg:province":"Salzburg",
    "sg:website":"gfb.at",
    "wof:name":"GFB & Partner Unternehmensberatung Ges f Betriebswirtschaftl Beratung GesmbH",
    "wof:placetype":"venue"
},
  "geometry": {"coordinates":[12.801407814,47.3041191101],"type":"Point"}
}