{
  "type": "Feature",
  "properties": {
    "addr:full":"Oswalderstr 12 Lasberg Ober\u00f6sterreich 4291",
    "addr:housenumber":"12",
    "addr:postcode":"4291",
    "addr:street":"Oswalderstr",
    "iso:country":"AT",
    "sg:address":"Oswalderstr 12",
    "sg:city":"Lasberg",
    "sg:orig_category":"Feuerwehren",
    "sg:phone":"+43 7947 7222",
    "sg:postcode":"4291",
    "sg:province":"Ober\u00f6sterreich",
    "wof:name":"Freiwillige Feuerwehr Lasberg",
    "wof:placetype":"venue"
},
  "geometry": {"coordinates":[14.5425615311,48.4726333618],"type":"Point"}
}