{
  "type": "Feature",
  "properties": {
    "addr:full":"Landstr 20 Hard Vorarlberg 6971",
    "addr:housenumber":"20",
    "addr:postcode":"6971",
    "addr:street":"Landstr",
    "iso:country":"AT",
    "sg:address":"Landstr 20",
    "sg:city":"Hard",
    "sg:orig_category":"Tischlereien",
    "sg:phone":"+43 4355 74725780",
    "sg:postcode":"6971",
    "sg:province":"Vorarlberg",
    "wof:name":"D\u00f6rler Herbert",
    "wof:placetype":"venue"
},
  "geometry": {"coordinates":[9.6878957748,47.4874954224],"type":"Point"}
}