{
  "type": "Feature",
  "properties": {
    "addr:full":"Nr 19 St. Veit in Defereggen Tirol 9962",
    "addr:postcode":"9962",
    "addr:street":"Nr 19;Tirol",
    "iso:country":"AT",
    "sg:address":"Nr 19",
    "sg:city":"St. Veit in Defereggen",
    "sg:orig_category":"Pensionen / Privatzimmer",
    "sg:phone":"+43 4348 79282",
    "sg:postcode":"9962",
    "sg:province":"Tirol",
    "wof:name":"Defereggerhof",
    "wof:placetype":"venue"
},
  "geometry": {"coordinates":[12.3779096603,46.9154701233],"type":"Point"}
}