{
  "type": "Feature",
  "properties": {
    "iso:country":"AT",
    "sg:address":"Breitenbuch 100",
    "sg:city":"Kirchbach in Steiermark",
    "sg:orig_category":"Feuerwehren",
    "sg:phone":"+43 664 9832615",
    "sg:postcode":"8082",
    "sg:province":"Steiermark",
    "wof:name":"Freiwillige Feuerwehr Breitenbuch",
    "wof:placetype":"venue"
},
  "geometry": {"coordinates":[15.6700839996,46.9780960083],"type":"Point"}
}