{
  "type": "Feature",
  "properties": {
    "addr:full":"Rechte Wienzeile 15 Wien Wien 1040",
    "addr:housenumber":"15",
    "addr:postcode":"1040",
    "addr:street":"Rechte Wienzeile",
    "iso:country":"AT",
    "sg:address":"Rechte Wienzeile 15",
    "sg:city":"Wien",
    "sg:orig_category":"Friseure U Frisiersalons",
    "sg:phone":"+43 1 5867782",
    "sg:postcode":"1040",
    "sg:province":"Wien",
    "wof:name":"Fortschnitt Frisuren mbH Inh Bertsch Ulli",
    "wof:placetype":"venue"
},
  "geometry": {"coordinates":[16.364156723,48.1984710693],"type":"Point"}
}