{
  "type": "Feature",
  "properties": {
    "addr:full":"Stattegger Str 131a Andritz Steiermark 8045",
    "addr:postcode":"8045",
    "addr:street":"Str 131A",
    "iso:country":"AT",
    "sg:address":"Stattegger Str 131a",
    "sg:city":"Andritz",
    "sg:orig_category":"Massagen",
    "sg:phone":"+43 664 3054089",
    "sg:postcode":"8045",
    "sg:province":"Steiermark",
    "wof:name":"Shiatsu - Profant Gundtraut",
    "wof:placetype":"venue"
},
  "geometry": {"coordinates":[15.4244775772,47.1242332458],"type":"Point"}
}