{
  "type": "Feature",
  "properties": {
    "addr:full":"Dornbacher Str 91 Wien Wien 1170",
    "addr:postcode":"1170",
    "addr:street":"Str 91",
    "iso:country":"AT",
    "sg:address":"Dornbacher Str 91",
    "sg:city":"Wien",
    "sg:orig_category":"Etiketten",
    "sg:phone":"+43 4314 816747",
    "sg:postcode":"1170",
    "sg:province":"Wien",
    "wof:name":"BC - Print Bohacek Christoph",
    "wof:placetype":"venue"
},
  "geometry": {"coordinates":[16.2942142487,48.2313117981],"type":"Point"}
}