{
  "type": "Feature",
  "properties": {
    "addr:full":"Neutorg 48 Graz Steiermark 8010",
    "addr:housenumber":"48",
    "addr:postcode":"8010",
    "addr:street":"Neutorg",
    "iso:country":"AT",
    "sg:address":"Neutorg 48",
    "sg:city":"Graz",
    "sg:classifiers":[
        {
            "category":"Restaurant",
            "type":"Food & Drink"
        }
    ],
    "sg:phone":"+43 316 8299090",
    "sg:postcode":"8010",
    "sg:province":"Steiermark",
    "wof:name":"G\u00f6sser Br\u00e4u",
    "wof:placetype":"venue"
},
  "geometry": {"coordinates":[15.4378137589,47.0669174194],"type":"Point"}
}