{
  "type": "Feature",
  "properties": {
    "iso:country":"AT",
    "sg:address":"Linzer Str 297",
    "sg:city":"Wien",
    "sg:orig_category":"Tonstudios",
    "sg:phone":"+43 1 9146221",
    "sg:postcode":"1140",
    "sg:province":"Wien",
    "wof:name":"Preiser Otto G & Co GesmbH",
    "wof:placetype":"venue"
},
  "geometry": {"coordinates":[16.2765293121,48.1969413757],"type":"Point"}
}