{
  "type": "Feature",
  "properties": {
    "iso:country":"AT",
    "sg:address":"Gumpendorfer Strasse 25",
    "sg:city":"Wien",
    "sg:classifiers":[
        {
            "category":"Professional",
            "subcategory":"Art Services",
            "type":"Services"
        }
    ],
    "sg:phone":"+43 1 5874404",
    "sg:postcode":"1060",
    "sg:province":"Wien",
    "sg:tags":[
        "design"
    ],
    "wof:name":"Atelier Fuhrherr",
    "wof:placetype":"venue"
},
  "geometry": {"coordinates":[16.3592700958,48.199092865],"type":"Point"}
}