{
  "type": "Feature",
  "properties": {
    "addr:full":"Eisenmengerg 39 Wien Wien 1100",
    "addr:housenumber":"39",
    "addr:postcode":"1100",
    "addr:street":"Eisenmengerg",
    "iso:country":"AT",
    "sg:address":"Eisenmengerg 39",
    "sg:city":"Wien",
    "sg:orig_category":"Montagen U Montagetechnik",
    "sg:phone":"+43 664 3514235",
    "sg:postcode":"1100",
    "sg:province":"Wien",
    "wof:name":"DG Tischlermontagen - M\u00f6belmontage",
    "wof:placetype":"venue"
},
  "geometry": {"coordinates":[16.3575439453,48.1535301208],"type":"Point"}
}