{
  "type": "Feature",
  "properties": {
    "addr:full":"Oberweg 1b Matrei am Brenner Tirol 6143",
    "addr:housenumber":"1b",
    "addr:postcode":"6143",
    "addr:street":"Oberweg;Brenner",
    "iso:country":"AT",
    "sg:address":"Oberweg 1b",
    "sg:city":"Matrei am Brenner",
    "sg:orig_category":"Pensionen / Privatzimmer",
    "sg:phone":"+43 5278 6219",
    "sg:postcode":"6143",
    "sg:province":"Tirol",
    "wof:name":"Haus Hubertus",
    "wof:placetype":"venue"
},
  "geometry": {"coordinates":[11.5056276321,47.128704071],"type":"Point"}
}