{
  "type": "Feature",
  "properties": {
    "addr:full":"Freytagg 1-14/35/12 Wien Wien 1210",
    "addr:housenumber":"1-14 / 35 / 12",
    "addr:postcode":"1210",
    "iso:country":"AT",
    "sg:address":"Freytagg 1-14/35/12",
    "sg:city":"Wien",
    "sg:orig_category":"Dachdeckereien",
    "sg:phone":"+43 676 3035059",
    "sg:postcode":"1210",
    "sg:province":"Wien",
    "sg:website":"babos.at",
    "wof:name":"Babos Andreas",
    "wof:placetype":"venue"
},
  "geometry": {"coordinates":[16.3978404999,48.2579994202],"type":"Point"}
}