{
  "type": "Feature",
  "properties": {
    "addr:full":"Sportplatzstr 486 Altenmarkt im Pongau Salzburg 5541",
    "addr:housenumber":"486",
    "addr:postcode":"5541",
    "addr:street":"Salzburg",
    "iso:country":"AT",
    "sg:address":"Sportplatzstr 486",
    "sg:city":"Altenmarkt im Pongau",
    "sg:orig_category":"Tourismusinformation U -Organisationen",
    "sg:phone":"+43 4364 5255110",
    "sg:postcode":"5541",
    "sg:province":"Salzburg",
    "wof:name":"Tourismusverband Altenmarkt-Zauchensee",
    "wof:placetype":"venue"
},
  "geometry": {"coordinates":[13.4189987183,47.3798141479],"type":"Point"}
}