{
  "type": "Feature",
  "properties": {
    "addr:full":"Nr 70 Neuhaus am Klausenbach Burgenland 8385",
    "addr:postcode":"8385",
    "addr:street":"Nr",
    "iso:country":"AT",
    "sg:address":"Nr 70",
    "sg:city":"Neuhaus am Klausenbach",
    "sg:orig_category":"Banken U Sparkassen",
    "sg:phone":"+43 4333 292427",
    "sg:postcode":"8385",
    "sg:province":"Burgenland",
    "wof:name":"Raiffeisenbank Neuhaus am Klausenbach regGenmbH",
    "wof:placetype":"venue"
},
  "geometry": {"coordinates":[16.0294303894,46.8676452637],"type":"Point"}
}