{
  "type": "Feature",
  "properties": {
    "iso:country":"AT",
    "sg:address":"Im \u00d6ko- und Gewerbezentrum",
    "sg:city":"Kirchdorf an der Krems",
    "sg:classifiers":[
        {
            "category":"Building & Trades",
            "subcategory":"Pest Control",
            "type":"Services"
        }
    ],
    "sg:phone":"+43 7582 51677",
    "sg:postcode":"4560",
    "sg:province":"Ober\u00f6sterreich",
    "sg:tags":[
        "storage",
        "energy",
        "technology",
        "conversion",
        "direct"
    ],
    "wof:name":"B\u00f6hm Energietechnik GmbH",
    "wof:placetype":"venue"
},
  "geometry": {"coordinates":[14.1225223541,47.9058189392],"type":"Point"}
}