{
  "type": "Feature",
  "properties": {
    "addr:full":"Nr 52 Stadl an der Mur Steiermark 8862",
    "addr:postcode":"der mur;8862",
    "addr:street":"Nr;An",
    "iso:country":"AT",
    "sg:address":"Nr 52",
    "sg:city":"Stadl an der Mur",
    "sg:orig_category":"Raumgestaltung",
    "sg:phone":"+43 3534 2343",
    "sg:postcode":"8862",
    "sg:province":"Steiermark",
    "wof:name":"Moser Herbert",
    "wof:placetype":"venue"
},
  "geometry": {"coordinates":[14.0248670578,47.111530304],"type":"Point"}
}