{
  "type": "Feature",
  "properties": {
    "iso:country":"AT",
    "sg:address":"Pesendorf 10",
    "sg:city":"Weibern",
    "sg:orig_category":"Sauna U Dampfbad / Bau U Ausstattung",
    "sg:phone":"+43 4377 3238110",
    "sg:postcode":"4675",
    "sg:province":"Ober\u00f6sterreich",
    "wof:name":"Polytherm Kunststoff- u Metalltechnik GesmbH",
    "wof:placetype":"venue"
},
  "geometry": {"coordinates":[13.684419632,48.1780090332],"type":"Point"}
}