{
  "type": "Feature",
  "properties": {
    "addr:full":"Hainzenbachstr 31 Leonding Ober\u00f6sterreich 4060",
    "addr:housenumber":"31",
    "addr:postcode":"4060",
    "addr:street":"Hainzenbachstr",
    "iso:country":"AT",
    "sg:address":"Hainzenbachstr 31",
    "sg:city":"Leonding",
    "sg:orig_category":"Waren Aller Art",
    "sg:phone":"+43 732 673226",
    "sg:postcode":"4060",
    "sg:province":"Ober\u00f6sterreich",
    "wof:name":"Gruber Josef",
    "wof:placetype":"venue"
},
  "geometry": {"coordinates":[14.2450141907,48.2808265686],"type":"Point"}
}