{
  "type": "Feature",
  "properties": {
    "addr:full":"Hauptstr 8 Leiben Nieder\u00f6sterreich 3652",
    "addr:housenumber":"8",
    "addr:postcode":"3652",
    "addr:street":"Hauptstr",
    "iso:country":"AT",
    "sg:address":"Hauptstr 8",
    "sg:city":"Leiben",
    "sg:orig_category":"Friseure U Frisiersalons",
    "sg:phone":"+43 2752 71256",
    "sg:postcode":"3652",
    "sg:province":"Nieder\u00f6sterreich",
    "wof:name":"Engl Brigitte",
    "wof:placetype":"venue"
},
  "geometry": {"coordinates":[15.2792463303,48.2432594299],"type":"Point"}
}