{
  "type": "Feature",
  "properties": {
    "addr:full":"Hauptstr 1 F\u00fcgen Tirol 6263",
    "addr:housenumber":"1",
    "addr:postcode":"6263",
    "addr:street":"Hauptstr;Tirol",
    "iso:country":"AT",
    "sg:address":"Hauptstr 1",
    "sg:city":"F\u00fcgen",
    "sg:orig_category":"Friseure U Frisiersalons",
    "sg:phone":"+43 5288 62245",
    "sg:postcode":"6263",
    "sg:province":"Tirol",
    "wof:name":"H\u00f6llwarth Walter",
    "wof:placetype":"venue"
},
  "geometry": {"coordinates":[11.8493499756,47.3477859497],"type":"Point"}
}