{
  "type": "Feature",
  "properties": {
    "addr:full":"Ottakringer Str 180 Wien Wien 1160",
    "addr:housenumber":"180",
    "addr:postcode":"1160",
    "iso:country":"AT",
    "sg:address":"Ottakringer Str 180",
    "sg:city":"Wien",
    "sg:orig_category":"Garten- U Landschaftsgestaltung",
    "sg:phone":"+43 1 4708044",
    "sg:postcode":"1160",
    "sg:province":"Wien",
    "wof:name":"DACHGR\u00dcN Objektbegr\u00fcnungen GmbH",
    "wof:placetype":"venue"
},
  "geometry": {"coordinates":[16.3138504028,48.2135848999],"type":"Point"}
}