{
  "type": "Feature",
  "properties": {
    "addr:full":"Klausener Weg 3 Lienz Tirol 9900",
    "addr:housenumber":"3",
    "addr:postcode":"9900",
    "addr:street":"Klausener Weg;Tirol",
    "iso:country":"AT",
    "sg:address":"Klausener Weg 3",
    "sg:city":"Lienz",
    "sg:orig_category":"Genossenschaften",
    "sg:phone":"+43 4348 5265086",
    "sg:postcode":"9900",
    "sg:province":"Tirol",
    "wof:name":"Frieden Gemeinn\u00fctzige Bau- u Siedlungsgenossenschaft",
    "wof:placetype":"venue"
},
  "geometry": {"coordinates":[12.7575464249,46.8207969666],"type":"Point"}
}