{
  "type": "Feature",
  "properties": {
    "addr:full":"Langenzersdorfer Str 50a Wien Wien 1210",
    "addr:housenumber":"50a",
    "addr:postcode":"1210",
    "addr:street":"Str",
    "iso:country":"AT",
    "sg:address":"Langenzersdorfer Str 50a",
    "sg:city":"Wien",
    "sg:orig_category":"Heurigen / Buschenschank",
    "sg:phone":"+43 1 2925341",
    "sg:postcode":"1210",
    "sg:province":"Wien",
    "wof:name":"Strauch Helga",
    "wof:placetype":"venue"
},
  "geometry": {"coordinates":[16.3845844269,48.2985267639],"type":"Point"}
}