{
  "type": "Feature",
  "properties": {
    "addr:full":"Bergg 26 Nikitsch Burgenland 7302",
    "addr:housenumber":"26",
    "addr:postcode":"7302",
    "addr:street":"Bergg",
    "iso:country":"AT",
    "sg:address":"Bergg 26",
    "sg:city":"Nikitsch",
    "sg:orig_category":"Weiterbildungsinstitute M Allg U Berufl Bildungsangebot",
    "sg:phone":"+43 4326 147103",
    "sg:postcode":"7302",
    "sg:province":"Burgenland",
    "wof:name":"Energiem\u00fchle Seminarhaus",
    "wof:placetype":"venue"
},
  "geometry": {"coordinates":[16.656917572,47.5335350037],"type":"Point"}
}