{
  "type": "Feature",
  "properties": {
    "addr:full":"Znaimer Str 46 Hollabrunn Nieder\u00f6sterreich 2020",
    "addr:housenumber":"46",
    "addr:postcode":"2020",
    "addr:street":"Str",
    "iso:country":"AT",
    "sg:address":"Znaimer Str 46",
    "sg:city":"Hollabrunn",
    "sg:orig_category":"Spenglereien",
    "sg:phone":"+43 2952 2287",
    "sg:postcode":"2020",
    "sg:province":"Nieder\u00f6sterreich",
    "wof:name":"Holzer Josef",
    "wof:placetype":"venue"
},
  "geometry": {"coordinates":[16.0768146515,48.568447113],"type":"Point"}
}