{
  "type": "Feature",
  "properties": {
    "iso:country":"AT",
    "sg:address":"Zeilg 1",
    "sg:city":"Wiesmath",
    "sg:orig_category":"Forstverwaltungen",
    "sg:phone":"+43 2645 2216",
    "sg:postcode":"2811",
    "sg:province":"Nieder\u00f6sterreich",
    "wof:name":"Limberger Maria",
    "wof:placetype":"venue"
},
  "geometry": {"coordinates":[16.2872505188,47.6179008484],"type":"Point"}
}