{
  "type": "Feature",
  "properties": {
    "addr:full":"Garteng 28 Graz Steiermark 8010",
    "addr:housenumber":"28",
    "addr:postcode":"8010",
    "addr:street":"Garteng",
    "iso:country":"AT",
    "sg:address":"Garteng 28",
    "sg:city":"Graz",
    "sg:classifiers":[
        {
            "category":"Internet Cafe",
            "subcategory":"None",
            "type":"Food & Drink"
        }
    ],
    "sg:phone":"+43 316 3210000",
    "sg:postcode":"8010",
    "sg:province":"Steiermark",
    "wof:name":"eyeCatch Dipl-Ing Burgsteiner - Hofer OEG",
    "wof:placetype":"venue"
},
  "geometry": {"coordinates":[15.4510011673,47.0696563721],"type":"Point"}
}