{
  "type": "Feature",
  "properties": {
    "iso:country":"AT",
    "sg:address":"Leopoldskronstr 30",
    "sg:city":"Salzburg",
    "sg:orig_category":"Forschungsinstitute",
    "sg:phone":"+43 662 834602",
    "sg:postcode":"5020",
    "sg:province":"Salzburg",
    "wof:name":"ARC Seibersdorf research GmbH - Research Studios Austria",
    "wof:placetype":"venue"
},
  "geometry": {"coordinates":[13.0318899155,47.7919540405],"type":"Point"}
}