{
  "type": "Feature",
  "properties": {
    "addr:full":"Donaul\u00e4nde 3-5 3504",
    "addr:housenumber":"3-5",
    "addr:postcode":"3504",
    "addr:street":"Donaulaende",
    "iso:country":"AT",
    "sg:address":"Donaul\u00e4nde 3-5",
    "sg:classifiers":[
        {
            "category":"Autos & Motor Vehicles",
            "subcategory":"Automobile Sales",
            "type":"Retail Goods"
        }
    ],
    "sg:phone":"+43 4327 328910",
    "sg:postcode":"3504",
    "sg:tags":[
        "motor-cars"
    ],
    "wof:name":"ARBINGRUBER & CO GMBH",
    "wof:placetype":"venue"
},
  "geometry": {"coordinates":[15.5881900787,48.426410675],"type":"Point"}
}