{
  "type": "Feature",
  "properties": {
    "addr:full":"Hauptstr 96 St. P\u00f6lten Nieder\u00f6sterreich 3100",
    "addr:housenumber":"96",
    "addr:postcode":"3100",
    "addr:street":"Hauptstr",
    "iso:country":"AT",
    "sg:address":"Hauptstr 96",
    "sg:city":"St. P\u00f6lten",
    "sg:orig_category":"Hafnereien",
    "sg:phone":"+43 2742 21055",
    "sg:postcode":"3100",
    "sg:province":"Nieder\u00f6sterreich",
    "wof:name":"Fantasia Raumgestaltung GmbH",
    "wof:placetype":"venue"
},
  "geometry": {"coordinates":[15.6240940094,48.2076377869],"type":"Point"}
}