{
  "type": "Feature",
  "properties": {
    "addr:full":"Mahlerstr 9 Wien Wien 1010",
    "addr:housenumber":"9",
    "addr:postcode":"1010",
    "addr:street":"Mahlerstr",
    "iso:country":"AT",
    "sg:address":"Mahlerstr 9",
    "sg:city":"Wien",
    "sg:orig_category":"Bars-Cafes",
    "sg:phone":"+43 1 5127753",
    "sg:postcode":"1010",
    "sg:province":"Wien",
    "wof:name":"Belmar Bar",
    "wof:placetype":"venue"
},
  "geometry": {"coordinates":[16.3723201752,48.2026748657],"type":"Point"}
}