{
  "type": "Feature",
  "properties": {
    "addr:full":"Sinnhubstr 4 Salzburg Salzburg 5020",
    "addr:housenumber":"4",
    "addr:postcode":"5020",
    "addr:street":"Sinnhubstr;Salzburg",
    "iso:country":"AT",
    "sg:address":"Sinnhubstr 4",
    "sg:city":"Salzburg",
    "sg:orig_category":"Sonnenschutzanlagen",
    "sg:phone":"+43 662 8290110",
    "sg:postcode":"5020",
    "sg:province":"Salzburg",
    "wof:name":"Dolenz Sonnen- und Wetterschutzanlagen GmbH",
    "wof:placetype":"venue"
},
  "geometry": {"coordinates":[13.0301504135,47.7948875427],"type":"Point"}
}