{
  "type": "Feature",
  "properties": {
    "addr:full":"Tamariskeng 102 Wien Wien 1220",
    "addr:housenumber":"102",
    "addr:postcode":"1220",
    "iso:country":"AT",
    "sg:address":"Tamariskeng 102",
    "sg:city":"Wien",
    "sg:classifiers":[
        {
            "category":"Taxi",
            "type":"Transportation"
        }
    ],
    "sg:phone":"+43 664 2521752",
    "sg:postcode":"1220",
    "sg:province":"Wien",
    "sg:tags":[
        "personentransporte",
        "u"
    ],
    "wof:name":"Ubl Roland",
    "wof:placetype":"venue"
},
  "geometry": {"coordinates":[16.4689331055,48.2218360901],"type":"Point"}
}