{
  "type": "Feature",
  "properties": {
    "iso:country":"AT",
    "sg:address":"Blumauer Str 29/2.OG",
    "sg:city":"Linz",
    "sg:orig_category":"Personalbereitstellung",
    "sg:phone":"+43 4357 0907300",
    "sg:postcode":"4020",
    "sg:province":"Ober\u00f6sterreich",
    "sg:website":"getwork.at",
    "wof:name":"GetWork Personaldienstleistungen GmbH",
    "wof:placetype":"venue"
},
  "geometry": {"coordinates":[14.2451400757,48.3018455505],"type":"Point"}
}