{
  "type": "Feature",
  "properties": {
    "addr:full":"Halleiner Landesstr 54 Oberalm Salzburg 5411",
    "addr:housenumber":"54",
    "addr:postcode":"5411",
    "addr:street":"Salzburg",
    "iso:country":"AT",
    "sg:address":"Halleiner Landesstr 54",
    "sg:city":"Oberalm",
    "sg:orig_category":"Lebensmittel / Einzelhandel",
    "sg:phone":"+43 664 2401038",
    "sg:postcode":"5411",
    "sg:province":"Salzburg",
    "wof:name":"G\u00fcnd\u00fcz Feinkost KEG",
    "wof:placetype":"venue"
},
  "geometry": {"coordinates":[13.0993118286,47.6999855042],"type":"Point"}
}