{
  "type": "Feature",
  "properties": {
    "addr:full":"Gemsleweg 4 Vandans Vorarlberg 6773",
    "addr:housenumber":"4",
    "addr:postcode":"6773",
    "addr:street":"Gemsleweg",
    "iso:country":"AT",
    "sg:address":"Gemsleweg 4",
    "sg:city":"Vandans",
    "sg:orig_category":"Handelsagenturen",
    "sg:phone":"+43 5556 74928",
    "sg:postcode":"6773",
    "sg:province":"Vorarlberg",
    "wof:name":"Eschenweck Alexander",
    "wof:placetype":"venue"
},
  "geometry": {"coordinates":[9.8571863174,47.0943908691],"type":"Point"}
}