{
  "type": "Feature",
  "properties": {
    "addr:full":"Lagerg 334 Puntigam Steiermark 8055",
    "addr:housenumber":"334",
    "addr:postcode":"8055",
    "iso:country":"AT",
    "sg:address":"Lagerg 334",
    "sg:city":"Puntigam",
    "sg:orig_category":"Garten- U Landschaftsgestaltung",
    "sg:phone":"+43 316 291375",
    "sg:postcode":"8055",
    "sg:province":"Steiermark",
    "wof:name":"Komander Wilhelm",
    "wof:placetype":"venue"
},
  "geometry": {"coordinates":[15.4420099258,47.0409889221],"type":"Point"}
}