{
  "type": "Feature",
  "properties": {
    "addr:full":"Haltestelleng 3 5503",
    "addr:housenumber":"3",
    "addr:postcode":"5503",
    "addr:street":"Haltestelleng",
    "iso:country":"AT",
    "sg:address":"Haltestelleng 3",
    "sg:orig_category":"Tischlereien",
    "sg:phone":"+43 6462 2701",
    "sg:postcode":"5503",
    "wof:name":"Lienbacher Alois",
    "wof:placetype":"venue"
},
  "geometry": {"coordinates":[107.0046386719,27.0754508972],"type":"Point"}
}