{
  "type": "Feature",
  "properties": {
    "addr:full":"Innsbrucker Str 49 Brixlegg Tirol 6230",
    "addr:postcode":"6230",
    "addr:street":"Str 49;Tirol",
    "iso:country":"AT",
    "sg:address":"Innsbrucker Str 49",
    "sg:city":"Brixlegg",
    "sg:orig_category":"Fliesen U Platten",
    "sg:phone":"+43 5337 62202",
    "sg:postcode":"6230",
    "sg:province":"Tirol",
    "wof:name":"Toni's abc Fliesen- und Handels GmbH",
    "wof:placetype":"venue"
},
  "geometry": {"coordinates":[11.88306427,47.4346923828],"type":"Point"}
}