{
  "type": "Feature",
  "properties": {
    "addr:full":"Weikersdorfer Str Parz/966 Wiener Neustadt Nieder\u00f6sterreich 2700",
    "addr:housenumber":"966",
    "addr:postcode":"2700",
    "addr:street":"Str Parz /",
    "iso:country":"AT",
    "sg:address":"Weikersdorfer Str Parz/966",
    "sg:city":"Wiener Neustadt",
    "sg:classifiers":[
        {
            "category":"Home & Garden",
            "subcategory":"Garden Supply",
            "type":"Retail Goods"
        }
    ],
    "sg:phone":"+43 4326 2227933",
    "sg:postcode":"2700",
    "sg:province":"Nieder\u00f6sterreich",
    "sg:tags":[
        "schotter",
        "sand",
        "u"
    ],
    "wof:name":"Kies-Union GmbH",
    "wof:placetype":"venue"
},
  "geometry": {"coordinates":[16.2455158234,47.8128814697],"type":"Point"}
}