{
  "type": "Feature",
  "properties": {
    "addr:full":"Niesenbergerg 37/1 Graz Steiermark 8020",
    "addr:housenumber":"37 / 1",
    "addr:postcode":"8020",
    "addr:street":"Niesenbergerg",
    "iso:country":"AT",
    "sg:address":"Niesenbergerg 37/1",
    "sg:city":"Graz",
    "sg:orig_category":"Versicherungsunternehmen",
    "sg:phone":"+43 316 8037411",
    "sg:postcode":"8020",
    "sg:province":"Steiermark",
    "wof:name":"Grazer Wechselseitige Versicherung AG",
    "wof:placetype":"venue"
},
  "geometry": {"coordinates":[15.4229469299,47.0701980591],"type":"Point"}
}