{
  "type": "Feature",
  "properties": {
    "iso:country":"AT",
    "sg:address":"Winklinger Str 14",
    "sg:city":"Gleink",
    "sg:orig_category":"Autoglas",
    "sg:phone":"+43 4372 5238624",
    "sg:postcode":"4407",
    "sg:province":"Ober\u00f6sterreich",
    "wof:name":"autoglas4all",
    "wof:placetype":"venue"
},
  "geometry": {"coordinates":[14.4159860611,48.0908508301],"type":"Point"}
}