{
  "type": "Feature",
  "properties": {
    "addr:full":"Bahnstr 5 Klagenfurt K\u00e4rnten 9020",
    "addr:housenumber":"5",
    "addr:postcode":"9020",
    "addr:street":"Bahnstr;Kaernten",
    "iso:country":"AT",
    "sg:address":"Bahnstr 5",
    "sg:city":"Klagenfurt",
    "sg:classifiers":[
        {
            "category":"Restaurant",
            "type":"Food & Drink"
        }
    ],
    "sg:phone":"+43 463 37300",
    "sg:postcode":"9020",
    "sg:province":"K\u00e4rnten",
    "wof:name":"Restaurant TONINO",
    "wof:placetype":"venue"
},
  "geometry": {"coordinates":[14.317946434,46.6151809692],"type":"Point"}
}