{
  "type": "Feature",
  "properties": {
    "addr:full":"Teilenstr 23 Lustenau Vorarlberg 6890",
    "addr:housenumber":"23",
    "addr:postcode":"6890",
    "addr:street":"Teilenstr",
    "iso:country":"AT",
    "sg:address":"Teilenstr 23",
    "sg:city":"Lustenau",
    "sg:orig_category":"Transportunternehmen",
    "sg:phone":"+43 5577 85055",
    "sg:postcode":"6890",
    "sg:province":"Vorarlberg",
    "wof:name":"Fitz Manfred",
    "wof:placetype":"venue"
},
  "geometry": {"coordinates":[9.6665563583,47.4298744202],"type":"Point"}
}