{
  "type": "Feature",
  "properties": {
    "iso:country":"AT",
    "sg:address":"Bundesstr 13",
    "sg:city":"Mariazell",
    "sg:orig_category":"Waren Aller Art",
    "sg:phone":"+43 3882 34073",
    "sg:postcode":"8630",
    "sg:province":"Steiermark",
    "wof:name":"Quelle Shop",
    "wof:placetype":"venue"
},
  "geometry": {"coordinates":[15.3113451004,47.7807998657],"type":"Point"}
}