{
  "type": "Feature",
  "properties": {
    "iso:country":"AT",
    "sg:address":"Hof 18",
    "sg:city":"Alberschwende",
    "sg:orig_category":"Drogerien",
    "sg:phone":"+43 5579 4371",
    "sg:postcode":"6861",
    "sg:province":"Vorarlberg",
    "wof:name":"W\u00e4lder - Drogerien Mitterberger GesmbH & Co KG",
    "wof:placetype":"venue"
},
  "geometry": {"coordinates":[9.8315839767,47.4503974915],"type":"Point"}
}