{
  "type": "Feature",
  "properties": {
    "addr:full":"Rudgerg 11 Wiener Neustadt Nieder\u00f6sterreich 2700",
    "addr:housenumber":"11",
    "addr:postcode":"2700",
    "addr:street":"Rudgerg",
    "iso:country":"AT",
    "sg:address":"Rudgerg 11",
    "sg:city":"Wiener Neustadt",
    "sg:orig_category":"Ergotherapie",
    "sg:phone":"+43 4326 2221795",
    "sg:postcode":"2700",
    "sg:province":"Nieder\u00f6sterreich",
    "wof:name":"Bauer Maria Dipl-ET",
    "wof:placetype":"venue"
},
  "geometry": {"coordinates":[16.2177886963,47.8050498962],"type":"Point"}
}