{
  "type": "Feature",
  "properties": {
    "addr:full":"Marktpl 4 Linz Ober\u00f6sterreich 4020",
    "addr:housenumber":"4",
    "addr:postcode":"4020",
    "addr:street":"Marktpl",
    "iso:country":"AT",
    "sg:address":"Marktpl 4",
    "sg:city":"Linz",
    "sg:orig_category":"Fleischhauereien",
    "sg:phone":"+43 732 602110",
    "sg:postcode":"4020",
    "sg:province":"Ober\u00f6sterreich",
    "wof:name":"Gonaus Karl",
    "wof:placetype":"venue"
},
  "geometry": {"coordinates":[14.2999095917,48.301197052],"type":"Point"}
}