{
  "type": "Feature",
  "properties": {
    "iso:country":"AT",
    "sg:address":"Nikolaus August Ottostr. 5",
    "sg:city":"Wiener Neustadt",
    "sg:classifiers":[
        {
            "category":"Manufacturing",
            "subcategory":"Aerospace",
            "type":"Manufacturing & Wholesale Goods"
        }
    ],
    "sg:phone":"+43 4326 22267000",
    "sg:postcode":"2700",
    "sg:province":"Nieder\u00f6sterreich",
    "sg:tags":[
        "aeronautic"
    ],
    "wof:name":"DIAMOND AIRCRAFT INDUSTRIE GMBH",
    "wof:placetype":"venue"
},
  "geometry": {"coordinates":[16.2492141724,47.8430023193],"type":"Point"}
}