{
  "type": "Feature",
  "properties": {
    "iso:country":"AT",
    "sg:address":"St. Margarethen 618",
    "sg:city":"Wenns",
    "sg:orig_category":"Friseure U Frisiersalons",
    "sg:phone":"+43 4354 1487306",
    "sg:postcode":"6473",
    "sg:province":"Tirol",
    "wof:name":"Ihr Friseur Fink Claudia",
    "wof:placetype":"venue"
},
  "geometry": {"coordinates":[10.7312002182,47.1684265137],"type":"Point"}
}