{
  "type": "Feature",
  "properties": {
    "addr:full":"Salzburger Str 323 Linz Ober\u00f6sterreich 4020",
    "addr:housenumber":"323",
    "addr:postcode":"4020",
    "addr:street":"Salzburger Str",
    "iso:country":"AT",
    "sg:address":"Salzburger Str 323",
    "sg:city":"Linz",
    "sg:classifiers":[
        {
            "category":"Home & Garden",
            "subcategory":"Building Materials",
            "type":"Retail Goods"
        }
    ],
    "sg:phone":"+43 4373 23731",
    "sg:postcode":"4020",
    "sg:province":"Ober\u00f6sterreich",
    "sg:tags":[
        "baustoffe",
        "-material",
        "u"
    ],
    "wof:name":"Asphaltmischwerk Steyregg GmbH & Co KG",
    "wof:placetype":"venue"
},
  "geometry": {"coordinates":[14.2875900269,48.25522995],"type":"Point"}
}