{
  "type": "Feature",
  "properties": {
    "addr:full":"Hollerweg 2 Langenlois Nieder\u00f6sterreich 3550",
    "addr:housenumber":"2",
    "addr:postcode":"3550",
    "addr:street":"Hollerweg",
    "iso:country":"AT",
    "sg:address":"Hollerweg 2",
    "sg:city":"Langenlois",
    "sg:orig_category":"\u00c3\u201erzte / F Allgemeinmedizin",
    "sg:phone":"+43 2734 2828",
    "sg:postcode":"3550",
    "sg:province":"Nieder\u00f6sterreich",
    "wof:name":"Faltl Heidelinde Dr",
    "wof:placetype":"venue"
},
  "geometry": {"coordinates":[15.6871109009,48.4713897705],"type":"Point"}
}