{
  "type": "Feature",
  "properties": {
    "iso:country":"AT",
    "sg:address":"Wallensteinstr 14",
    "sg:city":"Wien",
    "sg:orig_category":"Banken U Sparkassen",
    "sg:phone":"+43 5 050531280",
    "sg:postcode":"1200",
    "sg:province":"Wien",
    "wof:name":"Bank Austria Creditanstalt AG",
    "wof:placetype":"venue"
},
  "geometry": {"coordinates":[16.368265152,48.2283782959],"type":"Point"}
}