{
  "type": "Feature",
  "properties": {
    "addr:full":"Laxenburger Str 83 Wien Wien 1100",
    "addr:housenumber":"83",
    "addr:postcode":"1100",
    "addr:street":"Laxenburger Str",
    "iso:country":"AT",
    "sg:address":"Laxenburger Str 83",
    "sg:city":"Wien",
    "sg:orig_category":"Restaurants: Chinesisch",
    "sg:phone":"+43 1 6065320",
    "sg:postcode":"1100",
    "sg:province":"Wien",
    "wof:name":"China-Restaurant Himalaya",
    "wof:placetype":"venue"
},
  "geometry": {"coordinates":[16.3730754852,48.173915863],"type":"Point"}
}