{
  "type": "Feature",
  "properties": {
    "addr:full":"Hauptpl 23 Bad St. Leonhard im Lavanttal K\u00e4rnten 9462",
    "addr:housenumber":"23",
    "addr:postcode":"9462",
    "addr:street":"Hauptpl",
    "iso:country":"AT",
    "sg:address":"Hauptpl 23",
    "sg:city":"Bad St. Leonhard im Lavanttal",
    "sg:orig_category":"Blumeneinzelhandel",
    "sg:phone":"+43 4343 502335",
    "sg:postcode":"9462",
    "sg:province":"K\u00e4rnten",
    "wof:name":"Maurer Maria",
    "wof:placetype":"venue"
},
  "geometry": {"coordinates":[14.7921438217,46.963054657],"type":"Point"}
}