{
  "type": "Feature",
  "properties": {
    "addr:full":"Willersdorfer Str 2 St. Radegund Steiermark 8061",
    "addr:housenumber":"2",
    "addr:postcode":"8061",
    "addr:street":"Str",
    "iso:country":"AT",
    "sg:address":"Willersdorfer Str 2",
    "sg:city":"St. Radegund",
    "sg:orig_category":"Non-Classified Establishments",
    "sg:phone":"+43 5 91336149",
    "sg:postcode":"8061",
    "sg:province":"Steiermark",
    "wof:name":"Gendarmerie",
    "wof:placetype":"venue"
},
  "geometry": {"coordinates":[15.4898471832,47.1837348938],"type":"Point"}
}