{
  "type": "Feature",
  "properties": {
    "iso:country":"AT",
    "sg:address":"Nr 31",
    "sg:city":"Seeboden",
    "sg:orig_category":"Pensionen / Privatzimmer",
    "sg:phone":"+43 4762 81178",
    "sg:postcode":"9871",
    "sg:province":"K\u00e4rnten",
    "wof:name":"Landhaus-Pension Richter",
    "wof:placetype":"venue"
},
  "geometry": {"coordinates":[13.5192050934,46.8188858032],"type":"Point"}
}