{
  "type": "Feature",
  "properties": {
    "addr:full":"Hatler Strasse 72 Dornbirn Vorarlberg 6850",
    "addr:housenumber":"72",
    "addr:postcode":"6850",
    "addr:street":"Hatler Strasse",
    "iso:country":"AT",
    "sg:address":"Hatler Strasse 72",
    "sg:city":"Dornbirn",
    "sg:classifiers":[
        {
            "category":"Structure",
            "subcategory":"Restrooms",
            "type":"Public Place"
        }
    ],
    "sg:phone":"+43 5572 29184",
    "sg:postcode":"6850",
    "sg:province":"Vorarlberg",
    "sg:tags":[
        "prefabricated",
        "bathroom"
    ],
    "sg:website":"dusch-design.com",
    "wof:name":"Hefel Hubert GmbH",
    "wof:placetype":"venue"
},
  "geometry": {"coordinates":[9.731470108,47.3971405029],"type":"Point"}
}