{
  "type": "Feature",
  "properties": {
    "addr:full":"Kwizdastrasse 11 Korneuburg Nieder\u00f6sterreich 2100",
    "addr:housenumber":"11",
    "addr:postcode":"2100",
    "addr:street":"Kwizdastrasse;Niederoesterreich",
    "iso:country":"AT",
    "sg:address":"Kwizdastrasse 11",
    "sg:city":"Korneuburg",
    "sg:orig_category":"Medien, Sonstige Mediendienstleistungen",
    "sg:phone":"+43 4302 262648280",
    "sg:postcode":"2100",
    "sg:province":"Nieder\u00f6sterreich",
    "sg:website":"http://www.eventpartner.at",
    "wof:name":"Event Partner Austria KEG",
    "wof:placetype":"venue"
},
  "geometry": {"coordinates":[16.3327102661,48.3387794495],"type":"Point"}
}