{
  "type": "Feature",
  "properties": {
    "addr:full":"Felix-Dahn-Str 1a Salzburg Salzburg 5020",
    "addr:housenumber":"1a",
    "addr:postcode":"5020",
    "addr:street":"Felix-Dahn-Str;Salzburg",
    "iso:country":"AT",
    "sg:address":"Felix-Dahn-Str 1a",
    "sg:city":"Salzburg",
    "sg:orig_category":"Steuerberatung",
    "sg:phone":"+43 4366 26455550",
    "sg:postcode":"5020",
    "sg:province":"Salzburg",
    "sg:website":"treuhand-union.com",
    "wof:name":"Zeitheim Dkfm & Reichl Mag Steuerberatungs OEG - Treuhand Union",
    "wof:placetype":"venue"
},
  "geometry": {"coordinates":[13.0707769394,47.8049850464],"type":"Point"}
}