{
  "type": "Feature",
  "properties": {
    "addr:full":"Bahnhofstr 12 Hermagor K\u00e4rnten 9620",
    "addr:housenumber":"12",
    "addr:postcode":"9620",
    "addr:street":"Bahnhofstr;Kaernten",
    "iso:country":"AT",
    "sg:address":"Bahnhofstr 12",
    "sg:city":"Hermagor",
    "sg:orig_category":"Bankomat-Standorte",
    "sg:phone":"+43 4282 37440",
    "sg:postcode":"9620",
    "sg:province":"K\u00e4rnten",
    "wof:name":"Bankomat d Volksbank K\u00f6tschach-Mauthen",
    "wof:placetype":"venue"
},
  "geometry": {"coordinates":[13.3748512268,46.6265945435],"type":"Point"}
}