{
  "type": "Feature",
  "properties": {
    "addr:full":"Badstr 14 Eggersdorf Steiermark 8063",
    "addr:housenumber":"14",
    "addr:postcode":"8063",
    "addr:street":"Badstr",
    "iso:country":"AT",
    "sg:address":"Badstr 14",
    "sg:city":"Eggersdorf",
    "sg:orig_category":"Raumausstattung",
    "sg:phone":"+43 4369 912318181",
    "sg:postcode":"8063",
    "sg:province":"Steiermark",
    "wof:name":"Ferlitsch Otto",
    "wof:placetype":"venue"
},
  "geometry": {"coordinates":[15.5946531296,47.1184310913],"type":"Point"}
}