{
  "type": "Feature",
  "properties": {
    "iso:country":"AT",
    "sg:address":"Senng 2",
    "sg:city":"Wien",
    "sg:classifiers":[
        {
            "category":"Professional",
            "subcategory":"Testing Lab",
            "type":"Services"
        }
    ],
    "sg:phone":"+43 4317 97750",
    "sg:postcode":"1110",
    "sg:province":"Wien",
    "sg:tags":[
        "magistrate"
    ],
    "wof:name":"Magistrat d Stadt Wien - MA 33 - \u00f6ffentliche Beleuchtung",
    "wof:placetype":"venue"
},
  "geometry": {"coordinates":[16.3980350494,48.1782531738],"type":"Point"}
}