{
  "type": "Feature",
  "properties": {
    "addr:full":"Nr 201 Gerlos Tirol 6281",
    "addr:postcode":"6281",
    "addr:street":"Nr;Gerlos",
    "iso:country":"AT",
    "sg:address":"Nr 201",
    "sg:city":"Gerlos",
    "sg:classifiers":[
        {
            "category":"Travel",
            "subcategory":"Hotels & Motels",
            "type":"Entertainment"
        }
    ],
    "sg:phone":"+43 5284 52320",
    "sg:postcode":"6281",
    "sg:province":"Tirol",
    "wof:name":"Hotel-Pension Waldhof",
    "wof:placetype":"venue"
},
  "geometry": {"coordinates":[12.0359144211,47.2256088257],"type":"Point"}
}