{
  "type": "Feature",
  "properties": {
    "iso:country":"AT",
    "sg:address":"Valentin-Zeileis-Strasse 4",
    "sg:city":"Gallspach",
    "sg:classifiers":[
        {
            "category":"Home & Garden",
            "subcategory":"Home Furnishings",
            "type":"Retail Goods"
        }
    ],
    "sg:phone":"+43 7248 62315",
    "sg:postcode":"4713",
    "sg:province":"Ober\u00f6sterreich",
    "sg:tags":[
        "track",
        "curtain"
    ],
    "wof:name":"Josef Breitwieser",
    "wof:placetype":"venue"
},
  "geometry": {"coordinates":[13.8127937317,48.2075767517],"type":"Point"}
}