{
  "type": "Feature",
  "properties": {
    "addr:full":"Fabriksstr 61 Enns Ober\u00f6sterreich 4470",
    "addr:housenumber":"61",
    "addr:postcode":"4470",
    "addr:street":"Fabriksstr",
    "iso:country":"AT",
    "sg:address":"Fabriksstr 61",
    "sg:city":"Enns",
    "sg:orig_category":"Drogerien",
    "sg:phone":"+43 7223 8840",
    "sg:postcode":"4470",
    "sg:province":"Ober\u00f6sterreich",
    "wof:name":"dm drogerie markt GmbH - Verteilzentrum Kristein",
    "wof:placetype":"venue"
},
  "geometry": {"coordinates":[14.4456663132,48.2202682495],"type":"Point"}
}