{
  "type": "Feature",
  "properties": {
    "iso:country":"AT",
    "sg:address":"Fabriksstr 61",
    "sg:city":"Enns",
    "sg:orig_category":"Drogerien",
    "sg:phone":"+43 7223 8840",
    "sg:postcode":"4470",
    "sg:province":"Ober\u00f6sterreich",
    "wof:name":"dm drogerie markt GmbH - Verteilzentrum Kristein",
    "wof:placetype":"venue"
},
  "geometry": {"coordinates":[14.4456663132,48.2202682495],"type":"Point"}
}