{
  "type": "Feature",
  "properties": {
    "addr:full":"Klosterg 4 Innsbruck Tirol 6020",
    "addr:housenumber":"4",
    "addr:postcode":"6020",
    "addr:street":"Klosterg;Tirol",
    "iso:country":"AT",
    "sg:address":"Klosterg 4",
    "sg:city":"Innsbruck",
    "sg:orig_category":"\u00c3\u201erzte / F Allgemeinmedizin",
    "sg:phone":"+43 512 572775",
    "sg:postcode":"6020",
    "sg:province":"Tirol",
    "wof:name":"Handle Martina Dr",
    "wof:placetype":"venue"
},
  "geometry": {"coordinates":[11.3996839523,47.2531929016],"type":"Point"}
}