{
  "type": "Feature",
  "properties": {
    "addr:full":"Bichlstr 18 Kitzb\u00fchel Tirol 6370",
    "addr:housenumber":"18",
    "addr:postcode":"6370",
    "addr:street":"Bichlstr;Tirol",
    "iso:country":"AT",
    "sg:address":"Bichlstr 18",
    "sg:city":"Kitzb\u00fchel",
    "sg:orig_category":"Tabaktrafiken",
    "sg:phone":"+43 5356 62403",
    "sg:postcode":"6370",
    "sg:province":"Tirol",
    "wof:name":"Egger Horst",
    "wof:placetype":"venue"
},
  "geometry": {"coordinates":[12.3924150467,47.4448547363],"type":"Point"}
}