{
  "type": "Feature",
  "properties": {
    "addr:full":"Inzersdorfer Str 36 Wien Wien 1100",
    "addr:postcode":"1100",
    "addr:street":"Str 36",
    "iso:country":"AT",
    "sg:address":"Inzersdorfer Str 36",
    "sg:city":"Wien",
    "sg:orig_category":"Restaurants: Chinesisch",
    "sg:phone":"+43 1 6030820",
    "sg:postcode":"1100",
    "sg:province":"Wien",
    "wof:name":"Restaurant Yang",
    "wof:placetype":"venue"
},
  "geometry": {"coordinates":[16.3698997498,48.1719360352],"type":"Point"}
}