{
  "type": "Feature",
  "properties": {
    "addr:full":"Kurbadstr 10 Wien Wien 1100",
    "addr:housenumber":"10",
    "addr:postcode":"1100",
    "addr:street":"Kurbadstr",
    "iso:country":"AT",
    "sg:address":"Kurbadstr 10",
    "sg:city":"Wien",
    "sg:orig_category":"Forschungsinstitute",
    "sg:phone":"+43 1 680099230",
    "sg:postcode":"1100",
    "sg:province":"Wien",
    "wof:name":"Ludwig Boltzmann Institut f Rheumatologie und Balneologie",
    "wof:placetype":"venue"
},
  "geometry": {"coordinates":[16.4054965973,48.1418838501],"type":"Point"}
}