{
  "type": "Feature",
  "properties": {
    "addr:full":"Burgfriedweg 13a Graz Steiermark 8010",
    "addr:housenumber":"13a",
    "addr:postcode":"8010",
    "addr:street":"Burgfriedweg",
    "iso:country":"AT",
    "sg:address":"Burgfriedweg 13a",
    "sg:city":"Graz",
    "sg:classifiers":[
        {
            "category":"Structure",
            "subcategory":"Building",
            "type":"Public Place"
        }
    ],
    "sg:phone":"+43 316 3817930",
    "sg:postcode":"8010",
    "sg:province":"Steiermark",
    "sg:tags":[
        "apartment"
    ],
    "sg:website":"abk.co.at",
    "wof:name":"Ardemo Produktentwicklung f\u00fcr den Hochbau GmbH",
    "wof:placetype":"venue"
},
  "geometry": {"coordinates":[15.4737930298,47.075920105],"type":"Point"}
}