{
  "type": "Feature",
  "properties": {
    "addr:full":"Gmundner Strasse 20 Schwanenstadt Ober\u00f6sterreich 4690",
    "addr:housenumber":"20",
    "addr:postcode":"4690",
    "addr:street":"Gmundner Strasse",
    "iso:country":"AT",
    "sg:address":"Gmundner Strasse 20",
    "sg:city":"Schwanenstadt",
    "sg:classifiers":[
        {
            "category":"Juice Bar",
            "subcategory":"None",
            "type":"Food & Drink"
        }
    ],
    "sg:phone":"+43 767369200",
    "sg:postcode":"4690",
    "sg:province":"Ober\u00f6sterreich",
    "sg:tags":[
        "furnishing"
    ],
    "sg:website":"schwan.at",
    "wof:name":"Schwan K\u00f6ck GmbH & CO KG",
    "wof:placetype":"venue"
},
  "geometry": {"coordinates":[13.7774219513,48.0517539978],"type":"Point"}
}