{
  "type": "Feature",
  "properties": {
    "iso:country":"AT",
    "sg:address":"Kirchenpl 8",
    "sg:city":"Villach",
    "sg:orig_category":"Non-Classified Establishments",
    "sg:phone":"+43 4242 24066",
    "sg:postcode":"9500",
    "sg:province":"K\u00e4rnten",
    "wof:name":"Katholische Pfarr\u00e4mter St. Jakob",
    "wof:placetype":"venue"
},
  "geometry": {"coordinates":[13.844625473,46.6129837036],"type":"Point"}
}