{
  "type": "Feature",
  "properties": {
    "addr:full":"Wiener Str 253 G\u00f6sting Steiermark 8051",
    "addr:housenumber":"253",
    "addr:postcode":"8051",
    "addr:street":"Goesting Steiermark",
    "iso:country":"AT",
    "sg:address":"Wiener Str 253",
    "sg:city":"G\u00f6sting",
    "sg:orig_category":"Bauunternehmen",
    "sg:phone":"+43 316 684555",
    "sg:postcode":"8051",
    "sg:province":"Steiermark",
    "wof:name":"SUP'E das fertige Haus Bau- und HandelsgesmbH",
    "wof:placetype":"venue"
},
  "geometry": {"coordinates":[15.4057188034,47.0936279297],"type":"Point"}
}