{
  "type": "Feature",
  "properties": {
    "iso:country":"AT",
    "sg:address":"Hauptstr 16",
    "sg:city":"Radenthein",
    "sg:orig_category":"Friseure U Frisiersalons",
    "sg:phone":"+43 4246 2084",
    "sg:postcode":"9545",
    "sg:province":"K\u00e4rnten",
    "wof:name":"Friseursalon Harald Schmied",
    "wof:placetype":"venue"
},
  "geometry": {"coordinates":[13.7062225342,46.8017196655],"type":"Point"}
}