{
  "type": "Feature",
  "properties": {
    "addr:full":"Altenmarkter Str 3 Wies Steiermark 8551",
    "addr:housenumber":"3",
    "addr:postcode":"8551",
    "addr:street":"Str",
    "iso:country":"AT",
    "sg:address":"Altenmarkter Str 3",
    "sg:city":"Wies",
    "sg:orig_category":"Blumeneinzelhandel",
    "sg:phone":"+43 4334 653431",
    "sg:postcode":"8551",
    "sg:province":"Steiermark",
    "wof:name":"Knotz Gertrude",
    "wof:placetype":"venue"
},
  "geometry": {"coordinates":[15.266954422,46.717010498],"type":"Point"}
}