{
  "type": "Feature",
  "properties": {
    "iso:country":"AT",
    "sg:address":"Seisg 18",
    "sg:city":"Wien",
    "sg:classifiers":[
        {
            "category":"Sports & Exercise",
            "subcategory":"Gym",
            "type":"Entertainment"
        }
    ],
    "sg:phone":"+43 676 9466744",
    "sg:postcode":"1040",
    "sg:province":"Wien",
    "sg:tags":[
        "meditation"
    ],
    "wof:name":"Maringer Dagmar",
    "wof:placetype":"venue"
},
  "geometry": {"coordinates":[16.3671455383,48.1940345764],"type":"Point"}
}