{
  "type": "Feature",
  "properties": {
    "addr:full":"Nr 67 Frohnleiten Steiermark 8130",
    "addr:postcode":"8130",
    "addr:street":"Nr",
    "iso:country":"AT",
    "sg:address":"Nr 67",
    "sg:city":"Frohnleiten",
    "sg:orig_category":"Erdarbeiten",
    "sg:phone":"+43 4331 268211",
    "sg:postcode":"8130",
    "sg:province":"Steiermark",
    "wof:name":"Eckhart Siegfried",
    "wof:placetype":"venue"
},
  "geometry": {"coordinates":[15.3627090454,47.2798576355],"type":"Point"}
}