{
  "type": "Feature",
  "properties": {
    "iso:country":"AT",
    "sg:address":"Bahnhofstr 10",
    "sg:city":"Villach",
    "sg:classifiers":[
        {
            "category":"Travel",
            "subcategory":"Hotels & Motels",
            "type":"Entertainment"
        }
    ],
    "sg:phone":"+43 4242 26766",
    "sg:postcode":"9500",
    "sg:province":"K\u00e4rnten",
    "wof:name":"Europa Hotel",
    "wof:placetype":"venue"
},
  "geometry": {"coordinates":[13.8490495682,46.6169815063],"type":"Point"}
}