{
  "type": "Feature",
  "properties": {
    "iso:country":"AT",
    "sg:address":"Wehrg 1/1",
    "sg:city":"Wien",
    "sg:classifiers":[
        {
            "category":"Internet Cafe",
            "subcategory":"None",
            "type":"Food & Drink"
        }
    ],
    "sg:phone":"+43 1 98213510",
    "sg:postcode":"1050",
    "sg:province":"Wien",
    "wof:name":"m3plus.com Internet Solutions Trimmel, Kunerth & Co KEG",
    "wof:placetype":"venue"
},
  "geometry": {"coordinates":[16.3604717255,48.1930465698],"type":"Point"}
}