{
  "type": "Feature",
  "properties": {
    "addr:full":"St. Peter Hauptstr 96 St. Peter Steiermark 8042",
    "addr:housenumber":"96",
    "addr:postcode":"8042",
    "addr:street":"Hauptstr",
    "iso:country":"AT",
    "sg:address":"St. Peter Hauptstr 96",
    "sg:city":"St. Peter",
    "sg:orig_category":"Steinmetzbetriebe",
    "sg:phone":"+43 316 4650020",
    "sg:postcode":"8042",
    "sg:province":"Steiermark",
    "wof:name":"Bayer Josef",
    "wof:placetype":"venue"
},
  "geometry": {"coordinates":[15.4774971008,47.0514259338],"type":"Point"}
}