{
  "type": "Feature",
  "properties": {
    "iso:country":"AT",
    "sg:address":"Watzenegg 66",
    "sg:city":"Dornbirn",
    "sg:classifiers":[
        {
            "category":"Organizations",
            "subcategory":"Community Association",
            "type":"Services"
        }
    ],
    "sg:phone":"+43 5572 386450",
    "sg:postcode":"6850",
    "sg:province":"Vorarlberg",
    "sg:tags":[
        "relation",
        "public"
    ],
    "wof:name":"B\u00f6hler Angelika Dr",
    "wof:placetype":"venue"
},
  "geometry": {"coordinates":[9.7646751404,47.4127845764],"type":"Point"}
}