{
  "type": "Feature",
  "properties": {
    "addr:full":"Fabrikstr. 6 Schwarzach Vorarlberg 6858",
    "addr:housenumber":"6",
    "addr:postcode":"6858",
    "addr:street":"Fabrikstr.",
    "iso:country":"AT",
    "sg:address":"Fabrikstr. 6",
    "sg:city":"Schwarzach",
    "sg:classifiers":[
        {
            "category":"Professional",
            "subcategory":"Engineering",
            "type":"Services"
        }
    ],
    "sg:phone":"+43 4355 72581770",
    "sg:postcode":"6858",
    "sg:province":"Vorarlberg",
    "sg:tags":[
        "machine",
        "-",
        "mechanical"
    ],
    "wof:name":"MBM MASCHINENBAU GES.MBH",
    "wof:placetype":"venue"
},
  "geometry": {"coordinates":[9.7614002228,47.4455604553],"type":"Point"}
}