{
  "type": "Feature",
  "properties": {
    "addr:full":"Wiener Str 53 Langenlois Nieder\u00f6sterreich 3550",
    "addr:postcode":"3550",
    "addr:street":"Niederoesterreich",
    "iso:country":"AT",
    "sg:address":"Wiener Str 53",
    "sg:city":"Langenlois",
    "sg:orig_category":"Tankstellen",
    "sg:phone":"+43 4327 342687",
    "sg:postcode":"3550",
    "sg:province":"Nieder\u00f6sterreich",
    "wof:name":"AVANTI TankstellenbetriebsgesmbH",
    "wof:placetype":"venue"
},
  "geometry": {"coordinates":[15.6982727051,48.4761734009],"type":"Point"}
}