{
  "type": "Feature",
  "properties": {
    "addr:full":"Klosterwiesg 36/1 Graz Steiermark 8010",
    "addr:housenumber":"36 / 1",
    "addr:postcode":"8010",
    "addr:street":"Klosterwiesg",
    "iso:country":"AT",
    "sg:address":"Klosterwiesg 36/1",
    "sg:city":"Graz",
    "sg:orig_category":"Segel- U Seefahrtschulen",
    "sg:phone":"+43 316 8135170",
    "sg:postcode":"8010",
    "sg:province":"Steiermark",
    "sg:website":"www.vows.at",
    "wof:name":"V\u00d6WS Vereinigung d \u00d6sterr Windsurf und Segelschulen",
    "wof:placetype":"venue"
},
  "geometry": {"coordinates":[15.4451646805,47.0640716553],"type":"Point"}
}