{
  "type": "Feature",
  "properties": {
    "addr:full":"Bahnstr 7 Wiener Neudorf Nieder\u00f6sterreich 2351",
    "addr:housenumber":"7",
    "addr:postcode":"2351",
    "addr:street":"Bahnstr",
    "iso:country":"AT",
    "sg:address":"Bahnstr 7",
    "sg:city":"Wiener Neudorf",
    "sg:orig_category":"\u00c3\u201erzte / F Allgemeinmedizin",
    "sg:phone":"+43 4322 3624298",
    "sg:postcode":"2351",
    "sg:province":"Nieder\u00f6sterreich",
    "wof:name":"Eipeltauer Eduard Dr",
    "wof:placetype":"venue"
},
  "geometry": {"coordinates":[16.3114719391,48.0870361328],"type":"Point"}
}