{
  "type": "Feature",
  "properties": {
    "addr:full":"Edelhofg 15 Wien Wien 1180",
    "addr:housenumber":"15",
    "addr:postcode":"1180",
    "addr:street":"Edelhofg",
    "iso:country":"AT",
    "sg:address":"Edelhofg 15",
    "sg:city":"Wien",
    "sg:orig_category":"Antiquariate",
    "sg:phone":"+43 1 47967290",
    "sg:postcode":"1180",
    "sg:province":"Wien",
    "wof:name":"Krikl Andreas",
    "wof:placetype":"venue"
},
  "geometry": {"coordinates":[16.3445625305,48.2262420654],"type":"Point"}
}