{
  "type": "Feature",
  "properties": {
    "iso:country":"AT",
    "sg:address":"Fisching 45",
    "sg:city":"Wei\u00dfkirchen in Steiermark",
    "sg:orig_category":"Abfallentsorgung U -Verwertung",
    "sg:phone":"+43 4335 7781615",
    "sg:postcode":"8741",
    "sg:province":"Steiermark",
    "wof:name":".A.S.A. Abfall Service AG",
    "wof:placetype":"venue"
},
  "geometry": {"coordinates":[14.7387571335,47.1541213989],"type":"Point"}
}