{
  "type": "Feature",
  "properties": {
    "iso:country":"AT",
    "sg:address":"Bruckdorf 476",
    "sg:city":"Mariapfarr",
    "sg:orig_category":"Lebensmittel / Einzelhandel",
    "sg:phone":"+43 6473 20160",
    "sg:postcode":"5571",
    "sg:province":"Salzburg",
    "wof:name":"Billa AG",
    "wof:placetype":"venue"
},
  "geometry": {"coordinates":[13.7240209579,47.153678894],"type":"Point"}
}