{
  "type": "Feature",
  "properties": {
    "addr:full":"Herreng 1 Knittelfeld Steiermark 8720",
    "addr:housenumber":"1",
    "addr:postcode":"8720",
    "addr:street":"Herreng",
    "iso:country":"AT",
    "sg:address":"Herreng 1",
    "sg:city":"Knittelfeld",
    "sg:orig_category":"Blumeneinzelhandel",
    "sg:phone":"+43 3512 822140",
    "sg:postcode":"8720",
    "sg:province":"Steiermark",
    "wof:name":"Tropp Hans",
    "wof:placetype":"venue"
},
  "geometry": {"coordinates":[14.8288402557,47.2139892578],"type":"Point"}
}