{
  "type": "Feature",
  "properties": {
    "addr:full":"Ernst-Swatek-Str 4 Wolfsberg K\u00e4rnten 9400",
    "addr:housenumber":"4;kaernten",
    "addr:postcode":"9400",
    "addr:street":"Ernst-Swatek-Str",
    "iso:country":"AT",
    "sg:address":"Ernst-Swatek-Str 4",
    "sg:city":"Wolfsberg",
    "sg:orig_category":"Elektroinstallationsunternehmen",
    "sg:phone":"+43 4352 23410",
    "sg:postcode":"9400",
    "sg:province":"K\u00e4rnten",
    "wof:name":"Pichler Johann Elektrounternehmen GesmbH",
    "wof:placetype":"venue"
},
  "geometry": {"coordinates":[14.8413438797,46.8384857178],"type":"Point"}
}