{
  "type": "Feature",
  "properties": {
    "addr:full":"Raffeldinger Str 35 Eferding Ober\u00f6sterreich 4070",
    "addr:postcode":"4070",
    "addr:street":"Str 35",
    "iso:country":"AT",
    "sg:address":"Raffeldinger Str 35",
    "sg:city":"Eferding",
    "sg:orig_category":"Landwirtschaftliche Produkte",
    "sg:phone":"+43 7272 2450",
    "sg:postcode":"4070",
    "sg:province":"Ober\u00f6sterreich",
    "wof:name":"Fuchshuber Agrarhandel GmbH",
    "wof:placetype":"venue"
},
  "geometry": {"coordinates":[14.0383691788,48.2862014771],"type":"Point"}
}