{
  "type": "Feature",
  "properties": {
    "addr:full":"Thimigg 58 Wien Wien 1180",
    "addr:housenumber":"58",
    "addr:postcode":"1180",
    "addr:street":"Thimigg",
    "iso:country":"AT",
    "sg:address":"Thimigg 58",
    "sg:city":"Wien",
    "sg:orig_category":"Werbegrafik- U Grafik-Design",
    "sg:phone":"+43 4314 706243",
    "sg:postcode":"1180",
    "sg:province":"Wien",
    "wof:name":"Lacher Alfred",
    "wof:placetype":"venue"
},
  "geometry": {"coordinates":[16.3215293884,48.2315406799],"type":"Point"}
}