{
  "type": "Feature",
  "properties": {
    "addr:full":"Leesdorfer Hauptstrasse 16-18  Baden Nieder\u00f6sterreich 2500",
    "addr:postcode":"16-18;2500",
    "addr:street":"Leesdorfer Hauptstrasse;Niederoesterreich",
    "iso:country":"AT",
    "sg:address":"Leesdorfer Hauptstrasse 16-18 ",
    "sg:city":"Baden",
    "sg:orig_category":"Paintwork Supraregional",
    "sg:phone":"+43 2252 71759",
    "sg:postcode":"2500",
    "sg:province":"Nieder\u00f6sterreich",
    "sg:website":"www.maler-schaefer.at",
    "wof:name":"Ferdinand Sch\u00e4fer Ges.m.b.H.",
    "wof:placetype":"venue"
},
  "geometry": {"coordinates":[16.2455234528,48.0024185181],"type":"Point"}
}