{
  "type": "Feature",
  "properties": {
    "addr:full":"Pichl 12 Mariapfarr Salzburg 5571",
    "addr:housenumber":"12",
    "addr:postcode":"5571",
    "addr:street":"Pichl;Salzburg",
    "iso:country":"AT",
    "sg:address":"Pichl 12",
    "sg:city":"Mariapfarr",
    "sg:orig_category":"Appartements / Ferienwohnungen",
    "sg:phone":"+43 4364 738213",
    "sg:postcode":"5571",
    "sg:province":"Salzburg",
    "wof:name":"Bogensperger Elisabeth",
    "wof:placetype":"venue"
},
  "geometry": {"coordinates":[13.7375202179,47.1415710449],"type":"Point"}
}