{
  "type": "Feature",
  "properties": {
    "addr:full":"Nr 30 Taufkirchen an der Trattnach Ober\u00f6sterreich 4715",
    "addr:postcode":"4715",
    "addr:street":"Nr 30",
    "iso:country":"AT",
    "sg:address":"Nr 30",
    "sg:city":"Taufkirchen an der Trattnach",
    "sg:orig_category":"Tischlereien",
    "sg:phone":"+43 7734 26130",
    "sg:postcode":"4715",
    "sg:province":"Ober\u00f6sterreich",
    "wof:name":"Sch\u00f6nbauer Ernst",
    "wof:placetype":"venue"
},
  "geometry": {"coordinates":[13.7773637772,48.2517318726],"type":"Point"}
}