{
  "type": "Feature",
  "properties": {
    "iso:country":"AT",
    "sg:address":"Bachstrasse 11",
    "sg:city":"Steinerkirchen an der Traun",
    "sg:classifiers":[
        {
            "category":"Organizations",
            "subcategory":"Labor Organization",
            "type":"Services"
        }
    ],
    "sg:phone":"+43 7241 5988",
    "sg:postcode":"4652",
    "sg:province":"Ober\u00f6sterreich",
    "sg:tags":[
        "work",
        "assembling",
        "assembly",
        "contract"
    ],
    "wof:name":"K\u00fcchen Kienbauer",
    "wof:placetype":"venue"
},
  "geometry": {"coordinates":[13.9564161301,48.0752906799],"type":"Point"}
}