{
  "type": "Feature",
  "properties": {
    "addr:full":"Eggenberger Allee 34 Graz Steiermark 8020",
    "addr:housenumber":"34",
    "addr:postcode":"8020",
    "addr:street":"Eggenberger Allee",
    "iso:country":"AT",
    "sg:address":"Eggenberger Allee 34",
    "sg:city":"Graz",
    "sg:orig_category":"Banken U Sparkassen",
    "sg:phone":"+43 5 050529330",
    "sg:postcode":"8020",
    "sg:province":"Steiermark",
    "wof:name":"Bank Austria Creditanstalt AG",
    "wof:placetype":"venue"
},
  "geometry": {"coordinates":[15.4033708572,47.0705871582],"type":"Point"}
}