{
  "type": "Feature",
  "properties": {
    "addr:full":"Auer-von-Welsbach-Str 16 Salzburg Salzburg 5020",
    "addr:housenumber":"16",
    "addr:postcode":"5020",
    "addr:street":"Auer-Von-Welsbach-Str;Salzburg",
    "iso:country":"AT",
    "sg:address":"Auer-von-Welsbach-Str 16",
    "sg:city":"Salzburg",
    "sg:orig_category":"Garten- U Landschaftsgestaltung",
    "sg:phone":"+43 4366 2423201",
    "sg:postcode":"5020",
    "sg:province":"Salzburg",
    "wof:name":"Gartengestaltung Garstenauer",
    "wof:placetype":"venue"
},
  "geometry": {"coordinates":[13.0057821274,47.8135681152],"type":"Point"}
}