{
  "type": "Feature",
  "properties": {
    "iso:country":"AT",
    "sg:address":"M\u00fchlbergweg 24a",
    "sg:city":"Reith",
    "sg:classifiers":[
        {
            "category":"Taxi",
            "type":"Transportation"
        }
    ],
    "sg:phone":"+43 4352 123222",
    "sg:postcode":"6103",
    "sg:province":"Tirol",
    "sg:tags":[
        "personentransporte",
        "u"
    ],
    "wof:name":"Seelos Gabriele",
    "wof:placetype":"venue"
},
  "geometry": {"coordinates":[11.2038106918,47.2989349365],"type":"Point"}
}