{
  "type": "Feature",
  "properties": {
    "addr:full":"Arnsdorfer Str 5 Oberndorf Salzburg 5110",
    "addr:housenumber":"5",
    "addr:postcode":"5110",
    "addr:street":"Str",
    "iso:country":"AT",
    "sg:address":"Arnsdorfer Str 5",
    "sg:city":"Oberndorf",
    "sg:orig_category":"Hafnereien",
    "sg:phone":"+43 4362 725454",
    "sg:postcode":"5110",
    "sg:province":"Salzburg",
    "wof:name":"Weiss Ofen- u Kaminbau GesmbH",
    "wof:placetype":"venue"
},
  "geometry": {"coordinates":[12.9388217926,47.9525947571],"type":"Point"}
}