{
  "type": "Feature",
  "properties": {
    "iso:country":"AT",
    "sg:address":"Alteichweg 1",
    "sg:city":"Altach",
    "sg:orig_category":"Fleischhauereien",
    "sg:phone":"+43 5576 72546",
    "sg:postcode":"6844",
    "sg:province":"Vorarlberg",
    "wof:name":"Kopf Ernst",
    "wof:placetype":"venue"
},
  "geometry": {"coordinates":[9.6481027603,47.3543624878],"type":"Point"}
}