{
  "type": "Feature",
  "properties": {
    "addr:full":"Pfarrg 5 Lichtenegg Nieder\u00f6sterreich 2813",
    "addr:housenumber":"5",
    "addr:postcode":"2813",
    "addr:street":"Pfarrg",
    "iso:country":"AT",
    "sg:address":"Pfarrg 5",
    "sg:city":"Lichtenegg",
    "sg:orig_category":"Elektroinstallationsunternehmen",
    "sg:phone":"+43 2643 2256",
    "sg:postcode":"2813",
    "sg:province":"Nieder\u00f6sterreich",
    "wof:name":"Spenger Johann",
    "wof:placetype":"venue"
},
  "geometry": {"coordinates":[16.1955661774,47.6003341675],"type":"Point"}
}