{
  "type": "Feature",
  "properties": {
    "addr:full":"Roseggerstr 36 Innsbruck Tirol 6020",
    "addr:housenumber":"36",
    "addr:postcode":"6020",
    "addr:street":"Roseggerstr;Tirol",
    "iso:country":"AT",
    "sg:address":"Roseggerstr 36",
    "sg:city":"Innsbruck",
    "sg:orig_category":"Lichtwerbung",
    "sg:phone":"+43 512 367945",
    "sg:postcode":"6020",
    "sg:province":"Tirol",
    "wof:name":"Mann & Mul OEG - Neonpoint",
    "wof:placetype":"venue"
},
  "geometry": {"coordinates":[11.412194252,47.2598381042],"type":"Point"}
}