{
  "type": "Feature",
  "properties": {
    "addr:full":"Hauptpl 32 Retz Nieder\u00f6sterreich 2070",
    "addr:housenumber":"32",
    "addr:postcode":"2070",
    "addr:street":"Hauptpl",
    "iso:country":"AT",
    "sg:address":"Hauptpl 32",
    "sg:city":"Retz",
    "sg:orig_category":"Fleischhauereien",
    "sg:phone":"+43 2942 28088",
    "sg:postcode":"2070",
    "sg:province":"Nieder\u00f6sterreich",
    "wof:name":"Hofmann Franz Weinviertler Fleischerei",
    "wof:placetype":"venue"
},
  "geometry": {"coordinates":[15.9513998032,48.7571487427],"type":"Point"}
}