{
  "type": "Feature",
  "properties": {
    "addr:full":"Kallbrunnerg 8 Wien Wien 1210",
    "addr:housenumber":"8",
    "addr:postcode":"1210",
    "addr:street":"Kallbrunnerg",
    "iso:country":"AT",
    "sg:address":"Kallbrunnerg 8",
    "sg:city":"Wien",
    "sg:orig_category":"Sprachschulen U -Unterricht",
    "sg:phone":"+43 4312 922282",
    "sg:postcode":"1210",
    "sg:province":"Wien",
    "wof:name":"Executive Education Weissg\u00e4rber KEG",
    "wof:placetype":"venue"
},
  "geometry": {"coordinates":[16.3798103333,48.2896194458],"type":"Point"}
}