{
  "type": "Feature",
  "properties": {
    "addr:full":"Nr 40 Behamberg Nieder\u00f6sterreich 4441",
    "addr:postcode":"4441",
    "addr:street":"Nr;Behamberg",
    "iso:country":"AT",
    "sg:address":"Nr 40",
    "sg:city":"Behamberg",
    "sg:orig_category":"Banken U Sparkassen",
    "sg:phone":"+43 4350 10020017",
    "sg:postcode":"4441",
    "sg:province":"Nieder\u00f6sterreich",
    "wof:name":"Erste Bank d oesterreichischen Sparkassen AG",
    "wof:placetype":"venue"
},
  "geometry": {"coordinates":[14.4976663589,48.0339317322],"type":"Point"}
}