{
  "type": "Feature",
  "properties": {
    "addr:full":"Martinhofg 1 Apetlon Burgenland 7143",
    "addr:housenumber":"1",
    "addr:postcode":"7143",
    "addr:street":"Martinhofg",
    "iso:country":"AT",
    "sg:address":"Martinhofg 1",
    "sg:city":"Apetlon",
    "sg:orig_category":"Appartements / Ferienwohnungen",
    "sg:phone":"+43 2175 3132",
    "sg:postcode":"7143",
    "sg:province":"Burgenland",
    "wof:name":"G\u00e4stehaus Pilles",
    "wof:placetype":"venue"
},
  "geometry": {"coordinates":[16.8416442871,47.7485046387],"type":"Point"}
}