{
  "type": "Feature",
  "properties": {
    "iso:country":"AT",
    "sg:address":"Stra\u00dfganger Str 210b",
    "sg:city":"Wetzelsdorf",
    "sg:orig_category":"Bibliotheken",
    "sg:phone":"+43 4331 628332930",
    "sg:postcode":"8052",
    "sg:province":"Steiermark",
    "wof:name":"Stadtbibliothek d Magistrates",
    "wof:placetype":"venue"
},
  "geometry": {"coordinates":[15.394525528,47.050075531],"type":"Point"}
}