{
  "type": "Feature",
  "properties": {
    "addr:full":"Markt 23 Ybbsitz Nieder\u00f6sterreich 3341",
    "addr:housenumber":"23",
    "addr:postcode":"3341",
    "addr:street":"Markt",
    "iso:country":"AT",
    "sg:address":"Markt 23",
    "sg:city":"Ybbsitz",
    "sg:orig_category":"Friseure U Frisiersalons",
    "sg:phone":"+43 4374 4388383",
    "sg:postcode":"3341",
    "sg:province":"Nieder\u00f6sterreich",
    "wof:name":"Kreativ Haarstudio",
    "wof:placetype":"venue"
},
  "geometry": {"coordinates":[14.8952503204,47.9474754333],"type":"Point"}
}