{
  "type": "Feature",
  "properties": {
    "addr:full":"Paniglg 17a Wien Wien 1040",
    "addr:housenumber":"17a",
    "addr:postcode":"1040",
    "addr:street":"Paniglg",
    "iso:country":"AT",
    "sg:address":"Paniglg 17a",
    "sg:city":"Wien",
    "sg:orig_category":"Dolmetscher",
    "sg:phone":"+43 1 5050272",
    "sg:postcode":"1040",
    "sg:province":"Wien",
    "wof:name":"Hofmann Elisabeth Dr med",
    "wof:placetype":"venue"
},
  "geometry": {"coordinates":[16.3683013916,48.1979789734],"type":"Point"}
}