{
  "type": "Feature",
  "properties": {
    "addr:full":"Fl\u00f6tzerweg 9 Lauterach Vorarlberg 6923",
    "addr:housenumber":"9",
    "addr:postcode":"6923",
    "addr:street":"Floetzerweg",
    "iso:country":"AT",
    "sg:address":"Fl\u00f6tzerweg 9",
    "sg:city":"Lauterach",
    "sg:orig_category":"Gartenpflege",
    "sg:phone":"+43 5574 63970",
    "sg:postcode":"6923",
    "sg:province":"Vorarlberg",
    "wof:name":"Siess Josef",
    "wof:placetype":"venue"
},
  "geometry": {"coordinates":[9.7221498489,47.4848175049],"type":"Point"}
}