{
  "type": "Feature",
  "properties": {
    "addr:full":"Josefst\u00e4dter Str 62 Wien Wien 1080",
    "addr:postcode":"1080",
    "addr:street":"Str 62",
    "iso:country":"AT",
    "sg:address":"Josefst\u00e4dter Str 62",
    "sg:city":"Wien",
    "sg:orig_category":"Bars-Cafes",
    "sg:phone":"+43 1 4063641",
    "sg:postcode":"1080",
    "sg:province":"Wien",
    "wof:name":"Espresso Arosa",
    "wof:placetype":"venue"
},
  "geometry": {"coordinates":[16.3430690765,48.2106552124],"type":"Point"}
}