{
  "type": "Feature",
  "properties": {
    "iso:country":"AT",
    "sg:address":"Albrecht-D\u00fcrer-Str 1",
    "sg:city":"Wolfern",
    "sg:orig_category":"Industriereinigung",
    "sg:phone":"+43 4372 5320561",
    "sg:postcode":"4493",
    "sg:province":"Ober\u00f6sterreich",
    "wof:name":"Fuchs Helfried Maschinen u Anlagenreinigung",
    "wof:placetype":"venue"
},
  "geometry": {"coordinates":[14.3778066635,48.0832176208],"type":"Point"}
}