{
  "type": "Feature",
  "properties": {
    "addr:full":"Goethestr 1 Ried im Innkreis Ober\u00f6sterreich 4910",
    "addr:housenumber":"1",
    "addr:postcode":"4910",
    "addr:street":"Goethestr",
    "iso:country":"AT",
    "sg:address":"Goethestr 1",
    "sg:city":"Ried im Innkreis",
    "sg:orig_category":"Lebensmittel / Einzelhandel",
    "sg:phone":"+43 7752 83653",
    "sg:postcode":"4910",
    "sg:province":"Ober\u00f6sterreich",
    "wof:name":"Hofer KG",
    "wof:placetype":"venue"
},
  "geometry": {"coordinates":[13.4857721329,48.2132148743],"type":"Point"}
}