{
  "type": "Feature",
  "properties": {
    "addr:full":"Stadtplatz 24/2 Wels Ober\u00f6sterreich 4600",
    "addr:housenumber":"24 / 2",
    "addr:postcode":"4600",
    "addr:street":"Stadtplatz;Oberoesterreich",
    "iso:country":"AT",
    "sg:address":"Stadtplatz 24/2",
    "sg:city":"Wels",
    "sg:classifiers":[
        {
            "category":"Shopping",
            "subcategory":"Clothing, Apparel, & Fashions",
            "type":"Retail Goods"
        }
    ],
    "sg:phone":"+43 7242 47204",
    "sg:postcode":"4600",
    "sg:province":"Ober\u00f6sterreich",
    "sg:tags":[
        "dress",
        "dirndl"
    ],
    "wof:name":"WERKST\u00c4TTE BEURLE Trachten Ges.m.b.H.",
    "wof:placetype":"venue"
},
  "geometry": {"coordinates":[14.0273180008,48.157535553],"type":"Point"}
}