{
  "type": "Feature",
  "properties": {
    "addr:full":"Wiedeng 9 Zistersdorf Nieder\u00f6sterreich 2225",
    "addr:housenumber":"9",
    "addr:postcode":"2225",
    "addr:street":"Wiedeng;Niederoesterreich",
    "iso:country":"AT",
    "sg:address":"Wiedeng 9",
    "sg:city":"Zistersdorf",
    "sg:orig_category":"Fitnesscenter",
    "sg:phone":"+43 2532 3280",
    "sg:postcode":"2225",
    "sg:province":"Nieder\u00f6sterreich",
    "wof:name":"Slender You",
    "wof:placetype":"venue"
},
  "geometry": {"coordinates":[16.7668075562,48.54504776],"type":"Point"}
}