{
  "type": "Feature",
  "properties": {
    "addr:full":"Stauwerkstr 22 Ybbs an der Donau Nieder\u00f6sterreich 3370",
    "addr:housenumber":"22",
    "addr:postcode":"3370",
    "addr:street":"Stauwerkstr",
    "iso:country":"AT",
    "sg:address":"Stauwerkstr 22",
    "sg:city":"Ybbs an der Donau",
    "sg:orig_category":"Lebensmittel / Einzelhandel",
    "sg:phone":"+43 7412 52649",
    "sg:postcode":"3370",
    "sg:province":"Nieder\u00f6sterreich",
    "wof:name":"Spar Markt - Anton Brandstetter",
    "wof:placetype":"venue"
},
  "geometry": {"coordinates":[15.0802440643,48.1791954041],"type":"Point"}
}