{
  "type": "Feature",
  "properties": {
    "addr:full":"Ossiacher Zeile 52 Villach K\u00e4rnten 9500",
    "addr:housenumber":"52",
    "addr:postcode":"9500",
    "addr:street":"Ossiacher Zeile;Kaernten",
    "iso:country":"AT",
    "sg:address":"Ossiacher Zeile 52",
    "sg:city":"Villach",
    "sg:orig_category":"Textilreinigung",
    "sg:phone":"+43 4242 22875",
    "sg:postcode":"9500",
    "sg:province":"K\u00e4rnten",
    "wof:name":"Berger Georg",
    "wof:placetype":"venue"
},
  "geometry": {"coordinates":[13.8577432632,46.613193512],"type":"Point"}
}