{
  "type": "Feature",
  "properties": {
    "addr:full":"Obere Dorfstr 1 K\u00f6stendorf Salzburg 5203",
    "addr:housenumber":"1",
    "addr:postcode":"5203",
    "addr:street":"Obere Dorfstr;Salzburg",
    "iso:country":"AT",
    "sg:address":"Obere Dorfstr 1",
    "sg:city":"K\u00f6stendorf",
    "sg:orig_category":"Textilwaren / Einzelhandel",
    "sg:phone":"+43 4362 166528",
    "sg:postcode":"5203",
    "sg:province":"Salzburg",
    "wof:name":"Melitzer Matthias",
    "wof:placetype":"venue"
},
  "geometry": {"coordinates":[13.1981563568,47.9566192627],"type":"Point"}
}