{
  "type": "Feature",
  "properties": {
    "addr:full":"Kirchweg 5 Hall in Tirol Tirol 6060",
    "addr:housenumber":"5",
    "addr:postcode":"6060",
    "addr:street":"Kirchweg;Tirol",
    "iso:country":"AT",
    "sg:address":"Kirchweg 5",
    "sg:city":"Hall in Tirol",
    "sg:orig_category":"Glasereien",
    "sg:phone":"+43 512 341600",
    "sg:postcode":"6060",
    "sg:province":"Tirol",
    "wof:name":"Riepler Josef",
    "wof:placetype":"venue"
},
  "geometry": {"coordinates":[11.459980011,47.2613945007],"type":"Point"}
}