{
  "type": "Feature",
  "properties": {
    "addr:full":"Im Lagerfeld 11 Leibnitz Steiermark 8430",
    "addr:housenumber":"11",
    "addr:postcode":"8430",
    "addr:street":"Im Lagerfeld;Steiermark",
    "iso:country":"AT",
    "sg:address":"Im Lagerfeld 11",
    "sg:city":"Leibnitz",
    "sg:orig_category":"Biologische Produkte",
    "sg:phone":"+43 3452 74511",
    "sg:postcode":"8430",
    "sg:province":"Steiermark",
    "wof:name":"FRISCHeHOF naturbelassen & erntefrisch auf den Tisch...",
    "wof:placetype":"venue"
},
  "geometry": {"coordinates":[15.5571403503,46.7981987],"type":"Point"}
}