{
  "type": "Feature",
  "properties": {
    "addr:full":"Kurhausstr 10/4 Bad Ischl Ober\u00f6sterreich 4820",
    "addr:housenumber":"10 / 4",
    "addr:postcode":"4820",
    "addr:street":"Kurhausstr",
    "iso:country":"AT",
    "sg:address":"Kurhausstr 10/4",
    "sg:city":"Bad Ischl",
    "sg:orig_category":"Ingenieurkonsulenten / Zivilingenieure",
    "sg:phone":"+43 6132 25284",
    "sg:postcode":"4820",
    "sg:province":"Ober\u00f6sterreich",
    "wof:name":"Oberdammer Helmut Dipl-Ing",
    "wof:placetype":"venue"
},
  "geometry": {"coordinates":[13.6179733276,47.7115135193],"type":"Point"}
}