{
  "type": "Feature",
  "properties": {
    "addr:full":"Russenweg 5  Dornbirn Vorarlberg 6850",
    "addr:housenumber":"5",
    "addr:postcode":"6850",
    "addr:street":"Russenweg",
    "iso:country":"AT",
    "sg:address":"Russenweg 5 ",
    "sg:city":"Dornbirn",
    "sg:classifiers":[
        {
            "category":"Manufacturing",
            "subcategory":"Metals",
            "type":"Manufacturing & Wholesale Goods"
        }
    ],
    "sg:phone":"+43 4355 7224433",
    "sg:postcode":"6850",
    "sg:province":"Vorarlberg",
    "sg:tags":[
        "processing"
    ],
    "wof:name":"SCHWEIGER LASERSCHNITTE GES.MBH & CO",
    "wof:placetype":"venue"
},
  "geometry": {"coordinates":[9.7509832382,47.4161529541],"type":"Point"}
}