{
  "type": "Feature",
  "properties": {
    "addr:full":"St.-Ulrich-Str 8 G\u00f6tzis Vorarlberg 6840",
    "addr:housenumber":"8",
    "addr:postcode":"6840",
    "addr:street":"St.-Ulrich-Str",
    "iso:country":"AT",
    "sg:address":"St.-Ulrich-Str 8",
    "sg:city":"G\u00f6tzis",
    "sg:orig_category":"Rauchfangkehrer",
    "sg:phone":"+43 4355 2362519",
    "sg:postcode":"6840",
    "sg:province":"Vorarlberg",
    "wof:name":"Gst\u00f6hl G\u00fcnter",
    "wof:placetype":"venue"
},
  "geometry": {"coordinates":[11.6672801971,46.5735092163],"type":"Point"}
}