{
  "type": "Feature",
  "properties": {
    "iso:country":"AT",
    "sg:address":"Janzg 14",
    "sg:city":"Graz",
    "sg:orig_category":"Bauunternehmen",
    "sg:phone":"+43 4331 6571596",
    "sg:postcode":"8020",
    "sg:province":"Steiermark",
    "wof:name":"City Wohnbau GesmbH Baunternehmen u Bautr\u00e4ger",
    "wof:placetype":"venue"
},
  "geometry": {"coordinates":[15.4016246796,47.0716705322],"type":"Point"}
}