{
  "type": "Feature",
  "properties": {
    "addr:full":"Krichbaumg 1 Wien Wien 1120",
    "addr:housenumber":"1",
    "addr:postcode":"1120",
    "addr:street":"Krichbaumg",
    "iso:country":"AT",
    "sg:address":"Krichbaumg 1",
    "sg:city":"Wien",
    "sg:classifiers":[
        {
            "category":"Retail",
            "subcategory":"Event Space",
            "type":"Services"
        }
    ],
    "sg:phone":"+43 1 8153584",
    "sg:postcode":"1120",
    "sg:province":"Wien",
    "sg:tags":[
        "hand-",
        "u",
        "fu\u00c3\u0178pflege"
    ],
    "wof:name":"Hadek Maria",
    "wof:placetype":"venue"
},
  "geometry": {"coordinates":[16.3362007141,48.1793174744],"type":"Point"}
}