{
  "type": "Feature",
  "properties": {
    "iso:country":"AT",
    "sg:address":"Jakob-Gr\u00fcnwald-G 9a",
    "sg:city":"Deutsch Wagram",
    "sg:orig_category":"Holdinggesellschaften",
    "sg:phone":"+43 4322 4734946",
    "sg:postcode":"2232",
    "sg:province":"Nieder\u00f6sterreich",
    "wof:name":"Kentlex Holding GmbH",
    "wof:placetype":"venue"
},
  "geometry": {"coordinates":[16.5652046204,48.2991485596],"type":"Point"}
}