{
  "type": "Feature",
  "properties": {
    "addr:full":"Neunkirchner Str 12/2 Wiener Neustadt Nieder\u00f6sterreich 2700",
    "addr:housenumber":"12 / 2",
    "addr:postcode":"2700",
    "addr:street":"Str",
    "iso:country":"AT",
    "sg:address":"Neunkirchner Str 12/2",
    "sg:city":"Wiener Neustadt",
    "sg:orig_category":"Blut- U Plasmaspenden",
    "sg:phone":"+43 4326 22255770",
    "sg:postcode":"2700",
    "sg:province":"Nieder\u00f6sterreich",
    "wof:name":"Plasmazentrum Baxter AG",
    "wof:placetype":"venue"
},
  "geometry": {"coordinates":[16.2435684204,47.8117294312],"type":"Point"}
}