{
  "type": "Feature",
  "properties": {
    "addr:full":"T\u00fcrkenstrasse 12 Purbach am Neusiedler See Burgenland 7083",
    "addr:housenumber":"12",
    "addr:postcode":"7083",
    "addr:street":"Tuerkenstrasse",
    "iso:country":"AT",
    "sg:address":"T\u00fcrkenstrasse 12",
    "sg:city":"Purbach am Neusiedler See",
    "sg:classifiers":[
        {
            "category":"Organizations",
            "subcategory":"Political Organization",
            "type":"Services"
        }
    ],
    "sg:phone":"+43 2683 5130",
    "sg:postcode":"7083",
    "sg:province":"Burgenland",
    "sg:tags":[
        "cabling",
        "system"
    ],
    "wof:name":"Ing. Richard Gmeiner",
    "wof:placetype":"venue"
},
  "geometry": {"coordinates":[16.6935596466,47.9143562317],"type":"Point"}
}