{
  "type": "Feature",
  "properties": {
    "addr:full":"Baiernstr 24/12 Graz Steiermark 8020",
    "addr:housenumber":"24 / 12",
    "addr:postcode":"8020",
    "addr:street":"Baiernstr",
    "iso:country":"AT",
    "sg:address":"Baiernstr 24/12",
    "sg:city":"Graz",
    "sg:orig_category":"Psychotherapie",
    "sg:phone":"+43 316 576480",
    "sg:postcode":"8020",
    "sg:province":"Steiermark",
    "wof:name":"Filipic Colette MMag",
    "wof:placetype":"venue"
},
  "geometry": {"coordinates":[15.390255928,47.0749397278],"type":"Point"}
}