{
  "type": "Feature",
  "properties": {
    "addr:full":"Neudorfer Str 16 Marchtrenk Ober\u00f6sterreich 4614",
    "addr:postcode":"4614",
    "addr:street":"Str 16",
    "iso:country":"AT",
    "sg:address":"Neudorfer Str 16",
    "sg:city":"Marchtrenk",
    "sg:orig_category":"Spenglereien",
    "sg:phone":"+43 664 3220935",
    "sg:postcode":"4614",
    "sg:province":"Ober\u00f6sterreich",
    "wof:name":"Ebner Roland",
    "wof:placetype":"venue"
},
  "geometry": {"coordinates":[14.1243896484,48.1956062317],"type":"Point"}
}