{
  "type": "Feature",
  "properties": {
    "addr:full":"Karnerau 15 Gm\u00fcnd K\u00e4rnten 9853",
    "addr:housenumber":"15",
    "addr:postcode":"9853",
    "addr:street":"Karnerau;Kaernten",
    "iso:country":"AT",
    "sg:address":"Karnerau 15",
    "sg:city":"Gm\u00fcnd",
    "sg:orig_category":"Werbegestalter",
    "sg:phone":"+43 4347 323178",
    "sg:postcode":"9853",
    "sg:province":"K\u00e4rnten",
    "wof:name":"Lackner Herbert",
    "wof:placetype":"venue"
},
  "geometry": {"coordinates":[13.525229454,46.9326705933],"type":"Point"}
}