{
  "type": "Feature",
  "properties": {
    "iso:country":"AT",
    "sg:address":"Ohlsdorfer Str 18",
    "sg:city":"Gmunden",
    "sg:orig_category":"Banken U Sparkassen",
    "sg:phone":"+43 761265495",
    "sg:postcode":"4810",
    "sg:province":"Ober\u00f6sterreich",
    "wof:name":"Raiffeisenbank Ohlsdorf regGenmbH",
    "wof:placetype":"venue"
},
  "geometry": {"coordinates":[13.7960319519,47.9289093018],"type":"Point"}
}