{
  "type": "Feature",
  "properties": {
    "iso:country":"AT",
    "sg:address":"Kuffern 87",
    "sg:city":"Statzendorf",
    "sg:orig_category":"Druckereien",
    "sg:phone":"+43 2786 21940",
    "sg:postcode":"3125",
    "sg:province":"Nieder\u00f6sterreich",
    "wof:name":"Dockner GesmbH",
    "wof:placetype":"venue"
},
  "geometry": {"coordinates":[15.6513996124,48.3281211853],"type":"Point"}
}