{
  "type": "Feature",
  "properties": {
    "addr:full":"Alt Ossiach 2 Ossiach K\u00e4rnten 9570",
    "addr:housenumber":"2",
    "addr:postcode":"9570",
    "addr:street":"Ossiach;Kaernten",
    "iso:country":"AT",
    "sg:address":"Alt Ossiach 2",
    "sg:city":"Ossiach",
    "sg:orig_category":"Appartements / Ferienwohnungen",
    "sg:phone":"+43 4243 8226",
    "sg:postcode":"9570",
    "sg:province":"K\u00e4rnten",
    "wof:name":"Haus Prefeling",
    "wof:placetype":"venue"
},
  "geometry": {"coordinates":[14.0019350052,46.683139801],"type":"Point"}
}