{
  "type": "Feature",
  "properties": {
    "addr:full":"Hauptplatz 7 Tulln an der Donau Nieder\u00f6sterreich 3430",
    "addr:housenumber":"7",
    "addr:postcode":"3430",
    "addr:street":"Hauptplatz",
    "iso:country":"AT",
    "sg:address":"Hauptplatz 7",
    "sg:city":"Tulln an der Donau",
    "sg:classifiers":[
        {
            "category":"Banks & Credit Unions",
            "subcategory":"Investment Brokerage",
            "type":"Services"
        }
    ],
    "sg:phone":"+43 1 87809300",
    "sg:postcode":"3430",
    "sg:province":"Nieder\u00f6sterreich",
    "sg:tags":[
        "audio",
        "accessory"
    ],
    "sg:website":"bang-olufsen.com",
    "wof:name":"Bang & Olufsen Ges.m.b.H.",
    "wof:placetype":"venue"
},
  "geometry": {"coordinates":[16.0516090393,48.3309364319],"type":"Point"}
}