{
  "type": "Feature",
  "properties": {
    "iso:country":"AT",
    "sg:address":"Weingartenstr 2",
    "sg:city":"Horitschon",
    "sg:orig_category":"Banken U Sparkassen",
    "sg:phone":"+43 2610 42130",
    "sg:postcode":"7312",
    "sg:province":"Burgenland",
    "wof:name":"Raiffeisenkasse Horitschon und Umgebung regGenmbH",
    "wof:placetype":"venue"
},
  "geometry": {"coordinates":[16.5820999146,47.5907440186],"type":"Point"}
}