{
  "type": "Feature",
  "properties": {
    "iso:country":"AT",
    "sg:address":"Rupertuspl 1/2",
    "sg:city":"Wien",
    "sg:classifiers":[
        {
            "category":"Wholesale",
            "subcategory":"Vending Machines",
            "type":"Manufacturing & Wholesale Goods"
        }
    ],
    "sg:phone":"+43 1 4803772",
    "sg:postcode":"1170",
    "sg:province":"Wien",
    "sg:tags":[
        "filter"
    ],
    "sg:website":"haywardfiltration.com",
    "wof:name":"HAYWARD Industrial Products GmbH",
    "wof:placetype":"venue"
},
  "geometry": {"coordinates":[16.2979316711,48.2290153503],"type":"Point"}
}