{
  "type": "Feature",
  "properties": {
    "addr:full":"Feldgasse 3 Mitterdorf im M\u00fcrztal Steiermark 8662",
    "addr:housenumber":"3;im",
    "addr:postcode":"8662",
    "addr:street":"Feldgasse;Muerztal Steiermark",
    "iso:country":"AT",
    "sg:address":"Feldgasse 3",
    "sg:city":"Mitterdorf im M\u00fcrztal",
    "sg:classifiers":[
        {
            "category":"Wholesale",
            "subcategory":"Machinery & Supplies",
            "type":"Manufacturing & Wholesale Goods"
        }
    ],
    "sg:phone":"+43 3858 34510",
    "sg:postcode":"8662",
    "sg:province":"Steiermark",
    "sg:tags":[
        "forestry"
    ],
    "wof:name":"Knabl Consulting & Engineering",
    "wof:placetype":"venue"
},
  "geometry": {"coordinates":[15.5094919205,47.534778595],"type":"Point"}
}