{
  "type": "Feature",
  "properties": {
    "addr:full":"Steinbockallee 31/1 Rum Tirol 6063",
    "addr:housenumber":"31 / 1",
    "addr:postcode":"6063",
    "addr:street":"Steinbockallee;Tirol",
    "iso:country":"AT",
    "sg:address":"Steinbockallee 31/1",
    "sg:city":"Rum",
    "sg:orig_category":"Physiotherapie",
    "sg:phone":"+43 512 200575",
    "sg:postcode":"6063",
    "sg:province":"Tirol",
    "wof:name":"Huber Reinhard Dipl-PT",
    "wof:placetype":"venue"
},
  "geometry": {"coordinates":[11.4515810013,47.2712059021],"type":"Point"}
}