{
  "type": "Feature",
  "properties": {
    "iso:country":"AT",
    "sg:address":"Adamg 23",
    "sg:city":"Innsbruck",
    "sg:orig_category":"Werbeagenturen",
    "sg:phone":"+43 512 520050",
    "sg:postcode":"6020",
    "sg:province":"Tirol",
    "wof:name":"ACC Agentur f Creative Communication Werbe- und Marketing GesmbH",
    "wof:placetype":"venue"
},
  "geometry": {"coordinates":[11.3987722397,47.260597229],"type":"Point"}
}