{
  "type": "Feature",
  "properties": {
    "addr:full":"Gleichenberger Str 4 Feldbach Steiermark 8330",
    "addr:housenumber":"4",
    "addr:postcode":"8330",
    "addr:street":"Str",
    "iso:country":"AT",
    "sg:address":"Gleichenberger Str 4",
    "sg:city":"Feldbach",
    "sg:orig_category":"Institute",
    "sg:phone":"+43 3152 37149",
    "sg:postcode":"8330",
    "sg:province":"Steiermark",
    "wof:name":"L\u00e4ndliches Fortbildungsinstitut (LFI) Steiermark",
    "wof:placetype":"venue"
},
  "geometry": {"coordinates":[15.89133358,46.9504089355],"type":"Point"}
}