{
  "type": "Feature",
  "properties": {
    "addr:full":"Schulweg 1 Neustift im Stubaital Tirol 6167",
    "addr:housenumber":"1",
    "addr:postcode":"6167",
    "addr:street":"Schulweg;Tirol",
    "iso:country":"AT",
    "sg:address":"Schulweg 1",
    "sg:city":"Neustift im Stubaital",
    "sg:orig_category":"Hauptschulen",
    "sg:phone":"+43 4352 262332",
    "sg:postcode":"6167",
    "sg:province":"Tirol",
    "wof:name":"Haupt- u Skihauptschule Neustift",
    "wof:placetype":"venue"
},
  "geometry": {"coordinates":[11.3109426498,47.1137657166],"type":"Point"}
}