{
  "type": "Feature",
  "properties": {
    "addr:full":"Ennser Str 150 Gleink Ober\u00f6sterreich 4407",
    "addr:housenumber":"150",
    "addr:postcode":"4407",
    "iso:country":"AT",
    "sg:address":"Ennser Str 150",
    "sg:city":"Gleink",
    "sg:orig_category":"Abschleppdienste",
    "sg:phone":"+43 4372 52383380",
    "sg:postcode":"4407",
    "sg:province":"Ober\u00f6sterreich",
    "wof:name":"Prinz Oliver",
    "wof:placetype":"venue"
},
  "geometry": {"coordinates":[14.4400911331,48.0986976624],"type":"Point"}
}