{
  "type": "Feature",
  "properties": {
    "iso:country":"AT",
    "sg:address":"Mengerg 26",
    "sg:city":"Wien",
    "sg:orig_category":"Schilder",
    "sg:phone":"+43 1 2708070",
    "sg:postcode":"1210",
    "sg:province":"Wien",
    "wof:name":"Mach Kurt",
    "wof:placetype":"venue"
},
  "geometry": {"coordinates":[16.4084033966,48.2565841675],"type":"Point"}
}