{
  "type": "Feature",
  "properties": {
    "iso:country":"AT",
    "sg:address":"Karl-Berg-Gasse 18",
    "sg:city":"Radstadt",
    "sg:classifiers":[
        {
            "category":"Shopping",
            "subcategory":"Clothing, Apparel, & Fashions",
            "type":"Retail Goods"
        }
    ],
    "sg:phone":"+43 6452 4338",
    "sg:postcode":"5550",
    "sg:province":"Salzburg",
    "sg:tags":[
        "clothing",
        "leisure"
    ],
    "sg:website":"obertauern-sport.at",
    "wof:name":"Gef\u00e4ll GmbH",
    "wof:placetype":"venue"
},
  "geometry": {"coordinates":[13.4650278091,47.385219574],"type":"Point"}
}