{
  "type": "Feature",
  "properties": {
    "addr:full":"Klammstr 30 Kufstein Tirol 6330",
    "addr:housenumber":"30",
    "addr:postcode":"6330",
    "addr:street":"Klammstr;Tirol",
    "iso:country":"AT",
    "sg:address":"Klammstr 30",
    "sg:city":"Kufstein",
    "sg:orig_category":"Behinderungen / Leben Mit Behinderungen",
    "sg:phone":"+43 5372 64990",
    "sg:postcode":"6330",
    "sg:province":"Tirol",
    "wof:name":"Lebenshilfe Tirol - Werkst\u00e4tte",
    "wof:placetype":"venue"
},
  "geometry": {"coordinates":[12.1572141647,47.5674209595],"type":"Point"}
}