{
  "type": "Feature",
  "properties": {
    "addr:full":"Kapuzinerg 6 Waidhofen an der Ybbs Nieder\u00f6sterreich 3340",
    "addr:housenumber":"6",
    "addr:postcode":"3340",
    "addr:street":"Kapuzinerg",
    "iso:country":"AT",
    "sg:address":"Kapuzinerg 6",
    "sg:city":"Waidhofen an der Ybbs",
    "sg:orig_category":"Personalberatung",
    "sg:phone":"+43 7442 551552137",
    "sg:postcode":"3340",
    "sg:province":"Nieder\u00f6sterreich",
    "wof:name":"Konnex Personalberatung",
    "wof:placetype":"venue"
},
  "geometry": {"coordinates":[14.7766208649,47.9588241577],"type":"Point"}
}