{
  "type": "Feature",
  "properties": {
    "iso:country":"AT",
    "sg:address":"Wolf-Dietrich-Str 7",
    "sg:city":"Salzburg",
    "sg:classifiers":[
        {
            "category":"Restaurant",
            "type":"Food & Drink"
        }
    ],
    "sg:phone":"+43 662 87127539",
    "sg:postcode":"5020",
    "sg:province":"Salzburg",
    "wof:name":"Restaurant \u00e4hrlich",
    "wof:placetype":"venue"
},
  "geometry": {"coordinates":[13.0479803085,47.8046913147],"type":"Point"}
}