{
  "type": "Feature",
  "properties": {
    "iso:country":"AT",
    "sg:address":"Bahng 9",
    "sg:city":"Baden",
    "sg:orig_category":"Versicherungsunternehmen",
    "sg:phone":"+43 2252 444110",
    "sg:postcode":"2500",
    "sg:province":"Nieder\u00f6sterreich",
    "wof:name":"Wiener St\u00e4dtische Allgemeine Versicherung AG",
    "wof:placetype":"venue"
},
  "geometry": {"coordinates":[16.2385578156,48.0048599243],"type":"Point"}
}