{
  "type": "Feature",
  "properties": {
    "iso:country":"AT",
    "sg:address":"Argentinierstr 40",
    "sg:city":"Wien",
    "sg:orig_category":"Tabaktrafiken",
    "sg:phone":"+43 1 5056189",
    "sg:postcode":"1040",
    "sg:province":"Wien",
    "wof:name":"Richter Herbert",
    "wof:placetype":"venue"
},
  "geometry": {"coordinates":[16.3749904633,48.1910934448],"type":"Point"}
}