{
  "type": "Feature",
  "properties": {
    "addr:full":"Wiener Str 201 Traiskirchen Nieder\u00f6sterreich 2514",
    "addr:housenumber":"201",
    "addr:postcode":"2514",
    "addr:street":"Niederoesterreich",
    "iso:country":"AT",
    "sg:address":"Wiener Str 201",
    "sg:city":"Traiskirchen",
    "sg:orig_category":"Speditionen",
    "sg:phone":"+43 2252 6020",
    "sg:postcode":"2514",
    "sg:province":"Nieder\u00f6sterreich",
    "wof:name":"Marian Elisabeth GesmbH",
    "wof:placetype":"venue"
},
  "geometry": {"coordinates":[16.3024597168,48.0357894897],"type":"Point"}
}