{
  "type": "Feature",
  "properties": {
    "addr:full":"Eintrachtg 54 Liebenau Steiermark 8041",
    "addr:housenumber":"54",
    "addr:postcode":"8041",
    "addr:street":"Eintrachtg",
    "iso:country":"AT",
    "sg:address":"Eintrachtg 54",
    "sg:city":"Liebenau",
    "sg:orig_category":"Molkereien U Molkereiprodukte",
    "sg:phone":"+43 316 401448",
    "sg:postcode":"8041",
    "sg:province":"Steiermark",
    "wof:name":"Hartinger Herbert",
    "wof:placetype":"venue"
},
  "geometry": {"coordinates":[15.4581956863,47.0196914673],"type":"Point"}
}