{
  "type": "Feature",
  "properties": {
    "addr:full":"Twintower Wienerberg 11/12A Wien Wien 1100",
    "addr:housenumber":"11 / 12a",
    "addr:postcode":"1100",
    "iso:country":"AT",
    "sg:address":"Twintower Wienerberg 11/12A",
    "sg:city":"Wien",
    "sg:orig_category":"Frottierwaren",
    "sg:phone":"+43 1 994606214",
    "sg:postcode":"1100",
    "sg:province":"Wien",
    "sg:website":"www.vossen.com",
    "wof:name":"Vossen AG",
    "wof:placetype":"venue"
},
  "geometry": {"coordinates":[16.3744049072,48.1782684326],"type":"Point"}
}