{
  "type": "Feature",
  "properties": {
    "addr:full":"Zweil\u00e4nderstr 4 Gm\u00fcnd Nieder\u00f6sterreich 3950",
    "addr:housenumber":"4",
    "addr:postcode":"3950",
    "addr:street":"Zweilaenderstr;Niederoesterreich",
    "iso:country":"AT",
    "sg:address":"Zweil\u00e4nderstr 4",
    "sg:city":"Gm\u00fcnd",
    "sg:orig_category":"Bewachungsunternehmen",
    "sg:phone":"+43 2852 20490",
    "sg:postcode":"3950",
    "sg:province":"Nieder\u00f6sterreich",
    "wof:name":"Skorpion BewachungsgesmbH",
    "wof:placetype":"venue"
},
  "geometry": {"coordinates":[14.9799671173,48.7841682434],"type":"Point"}
}