{
  "type": "Feature",
  "properties": {
    "addr:full":"Br\u00e4unlichg 16 Wiener Neustadt Nieder\u00f6sterreich 2700",
    "addr:housenumber":"16",
    "addr:postcode":"2700",
    "addr:street":"Braeunlichg",
    "iso:country":"AT",
    "sg:address":"Br\u00e4unlichg 16",
    "sg:city":"Wiener Neustadt",
    "sg:orig_category":"Reitsportartikel",
    "sg:phone":"+43 2622 24949",
    "sg:postcode":"2700",
    "sg:province":"Nieder\u00f6sterreich",
    "wof:name":"Benesch Beatrix Reitsport",
    "wof:placetype":"venue"
},
  "geometry": {"coordinates":[16.2334022522,47.8062362671],"type":"Point"}
}