{
  "type": "Feature",
  "properties": {
    "addr:full":"Sillg 21 Innsbruck Tirol 6020",
    "addr:housenumber":"21",
    "addr:postcode":"6020",
    "addr:street":"Sillg;Tirol",
    "iso:country":"AT",
    "sg:address":"Sillg 21",
    "sg:city":"Innsbruck",
    "sg:classifiers":[
        {
            "category":"Restaurant",
            "type":"Food & Drink"
        }
    ],
    "sg:phone":"+43 512 571600",
    "sg:postcode":"6020",
    "sg:province":"Tirol",
    "sg:tags":[
        "pizzeria"
    ],
    "wof:name":"Pizzeria Palermo",
    "wof:placetype":"venue"
},
  "geometry": {"coordinates":[11.3913040161,47.2679977417],"type":"Point"}
}