{
  "type": "Feature",
  "properties": {
    "addr:full":"Schwarzenbergpl 6 Wien Wien 1030",
    "addr:housenumber":"6",
    "addr:postcode":"1030",
    "addr:street":"Schwarzenbergpl",
    "iso:country":"AT",
    "sg:address":"Schwarzenbergpl 6",
    "sg:city":"Wien",
    "sg:orig_category":"Werbeagenturen",
    "sg:phone":"+43 1 7163567",
    "sg:postcode":"1030",
    "sg:province":"Wien",
    "wof:name":"MPG Media Planning Group GmbH",
    "wof:placetype":"venue"
},
  "geometry": {"coordinates":[16.3769416809,48.1987724304],"type":"Point"}
}