{
  "type": "Feature",
  "properties": {
    "addr:full":"Linzer Str. 58 Perg Ober\u00f6sterreich 4320",
    "addr:housenumber":"58",
    "addr:postcode":"4320",
    "addr:street":"Linzer Str.",
    "iso:country":"AT",
    "sg:address":"Linzer Str. 58",
    "sg:city":"Perg",
    "sg:classifiers":[
        {
            "category":"Autos & Motor Vehicles",
            "subcategory":"Automobile Sales",
            "type":"Retail Goods"
        }
    ],
    "sg:phone":"+43 4372 6252550",
    "sg:postcode":"4320",
    "sg:province":"Ober\u00f6sterreich",
    "sg:tags":[
        "motor-cars"
    ],
    "wof:name":"HEINZ G\u00dcNTHER",
    "wof:placetype":"venue"
},
  "geometry": {"coordinates":[14.6245193481,48.2510414124],"type":"Point"}
}