{
  "type": "Feature",
  "properties": {
    "addr:full":"Am Platzl 15 Garsten Ober\u00f6sterreich 4451",
    "addr:housenumber":"15",
    "addr:postcode":"4451",
    "addr:street":"Am Platzl",
    "iso:country":"AT",
    "sg:address":"Am Platzl 15",
    "sg:city":"Garsten",
    "sg:orig_category":"Banken U Sparkassen",
    "sg:phone":"+43 4372 524848410",
    "sg:postcode":"4451",
    "sg:province":"Ober\u00f6sterreich",
    "wof:name":"Bankomat d Raiffeisenbank Region Steyr regGenmbH",
    "wof:placetype":"venue"
},
  "geometry": {"coordinates":[14.4079647064,48.0218849182],"type":"Point"}
}