{
  "type": "Feature",
  "properties": {
    "iso:country":"AT",
    "sg:address":"Lindau 13 + 14",
    "sg:city":"Fieberbrunn",
    "sg:orig_category":"Pensionen / Privatzimmer",
    "sg:phone":"+43 5354 568600",
    "sg:postcode":"6391",
    "sg:province":"Tirol",
    "wof:name":"G\u00e4stehaus Lichtmannegger",
    "wof:placetype":"venue"
},
  "geometry": {"coordinates":[12.550743103,47.4688301086],"type":"Point"}
}