{
  "type": "Feature",
  "properties": {
    "addr:full":"Dorfstr 19 Vandans Vorarlberg 6773",
    "addr:housenumber":"19",
    "addr:postcode":"6773",
    "addr:street":"Dorfstr",
    "iso:country":"AT",
    "sg:address":"Dorfstr 19",
    "sg:city":"Vandans",
    "sg:orig_category":"Elektroinstallationsunternehmen",
    "sg:phone":"+43 5556 72857",
    "sg:postcode":"6773",
    "sg:province":"Vorarlberg",
    "wof:name":"Egele Josef",
    "wof:placetype":"venue"
},
  "geometry": {"coordinates":[9.8637180328,47.097984314],"type":"Point"}
}