{
  "type": "Feature",
  "properties": {
    "addr:full":"Schwefel 67/Gasser Park Dornbirn Vorarlberg 6850",
    "addr:housenumber":"67 / gasser",
    "addr:postcode":"6850",
    "addr:street":"Schwefel;Park",
    "iso:country":"AT",
    "sg:address":"Schwefel 67/Gasser Park",
    "sg:city":"Dornbirn",
    "sg:orig_category":"Unterhaltungselektronik / Einzelhandel",
    "sg:phone":"+43 5572 517801",
    "sg:postcode":"6850",
    "sg:province":"Vorarlberg",
    "wof:name":"Technik-Quelle",
    "wof:placetype":"venue"
},
  "geometry": {"coordinates":[9.7437801361,47.4131889343],"type":"Point"}
}