{
  "type": "Feature",
  "properties": {
    "addr:full":"Grenzg 11 St. P\u00f6lten Nieder\u00f6sterreich 3100",
    "addr:housenumber":"11",
    "addr:postcode":"3100",
    "addr:street":"Grenzg",
    "iso:country":"AT",
    "sg:address":"Grenzg 11",
    "sg:city":"St. P\u00f6lten",
    "sg:orig_category":"Immobilienverwaltungen",
    "sg:phone":"+43 4327 42312200",
    "sg:postcode":"3100",
    "sg:province":"Nieder\u00f6sterreich",
    "wof:name":"Fr\u00fchwald Mag Immobiliendienstleistungen",
    "wof:placetype":"venue"
},
  "geometry": {"coordinates":[-76.07303619379999,41.7845001221],"type":"Point"}
}