{
  "type": "Feature",
  "properties": {
    "iso:country":"AT",
    "sg:address":"Achenrain 58",
    "sg:city":"Kramsach",
    "sg:classifiers":[
        {
            "category":"Travel",
            "subcategory":"Hotels & Motels",
            "type":"Entertainment"
        }
    ],
    "sg:phone":"+43 4353 37629130",
    "sg:postcode":"6233",
    "sg:province":"Tirol",
    "wof:name":"Hotel Schlo\u00dfhof",
    "wof:placetype":"venue"
},
  "geometry": {"coordinates":[11.8755283356,47.4491729736],"type":"Point"}
}