{
  "type": "Feature",
  "properties": {
    "iso:country":"AT",
    "sg:address":"Vinzenz-Muchitsch-Strasse 2-4",
    "sg:city":"Graz",
    "sg:classifiers":[
        {
            "category":"Professional",
            "subcategory":"Printing & Photocopies",
            "type":"Services"
        }
    ],
    "sg:phone":"+43 316 261426",
    "sg:postcode":"8020",
    "sg:province":"Steiermark",
    "sg:tags":[
        "digital"
    ],
    "sg:website":"schilderhaus.at",
    "wof:name":"Schilder- & Stempelhaus",
    "wof:placetype":"venue"
},
  "geometry": {"coordinates":[15.4272766113,47.0546340942],"type":"Point"}
}