{
  "type": "Feature",
  "properties": {
    "addr:full":"Goethestr 12 Lustenau Vorarlberg 6890",
    "addr:housenumber":"12",
    "addr:postcode":"6890",
    "addr:street":"Goethestr",
    "iso:country":"AT",
    "sg:address":"Goethestr 12",
    "sg:city":"Lustenau",
    "sg:orig_category":"Haushaltsartikel",
    "sg:phone":"+43 5577 82413",
    "sg:postcode":"6890",
    "sg:province":"Vorarlberg",
    "wof:name":"B\u00f6sch Bernd",
    "wof:placetype":"venue"
},
  "geometry": {"coordinates":[9.6532907486,47.4317512512],"type":"Point"}
}