{
  "type": "Feature",
  "properties": {
    "addr:full":"Industriestr 23 Haid Ober\u00f6sterreich 4053",
    "addr:housenumber":"23",
    "addr:postcode":"4053",
    "addr:street":"Industriestr",
    "iso:country":"AT",
    "sg:address":"Industriestr 23",
    "sg:city":"Haid",
    "sg:orig_category":"Hydraulik",
    "sg:phone":"+43 7229 80098",
    "sg:postcode":"4053",
    "sg:province":"Ober\u00f6sterreich",
    "wof:name":"SK Industrietechnik und HandelsgesmbH",
    "wof:placetype":"venue"
},
  "geometry": {"coordinates":[14.2602996826,48.2097244263],"type":"Point"}
}