{
  "type": "Feature",
  "properties": {
    "iso:country":"AT",
    "sg:address":"Tobelbader Str 182",
    "sg:city":"Tobelbad",
    "sg:orig_category":"Banken U Sparkassen",
    "sg:phone":"+43 4331 36521200",
    "sg:postcode":"8144",
    "sg:province":"Steiermark",
    "wof:name":"Raiffeisenbank Lieboch-Stainz regGenmbH",
    "wof:placetype":"venue"
},
  "geometry": {"coordinates":[15.3538351059,46.9890975952],"type":"Point"}
}