{
  "type": "Feature",
  "properties": {
    "addr:full":"Industriestr 2 Gro\u00df-Enzersdorf Nieder\u00f6sterreich 2301",
    "addr:housenumber":"2",
    "addr:postcode":"2301",
    "addr:street":"Industriestr;Niederoesterreich",
    "iso:country":"AT",
    "sg:address":"Industriestr 2",
    "sg:city":"Gro\u00df-Enzersdorf",
    "sg:orig_category":"Hallenvermietung",
    "sg:phone":"+43 4322 497446",
    "sg:postcode":"2301",
    "sg:province":"Nieder\u00f6sterreich",
    "wof:name":"Intertransit Lager- u Verkaufshallen GesmbH & Co KG",
    "wof:placetype":"venue"
},
  "geometry": {"coordinates":[16.5697555542,48.1935386658],"type":"Point"}
}