{
  "type": "Feature",
  "properties": {
    "addr:full":"Steinackerstrasse 7 Lustenau Vorarlberg 6890",
    "addr:housenumber":"7",
    "addr:postcode":"6890",
    "addr:street":"Steinackerstrasse",
    "iso:country":"AT",
    "sg:address":"Steinackerstrasse 7",
    "sg:city":"Lustenau",
    "sg:classifiers":[
        {
            "category":"Transit Center",
            "subcategory":"Freight",
            "type":"Transportation"
        }
    ],
    "sg:phone":"+43 5577 82374",
    "sg:postcode":"6890",
    "sg:province":"Vorarlberg",
    "sg:tags":[
        "forwarding",
        "agency"
    ],
    "wof:name":"Sperger Spedition GmbH",
    "wof:placetype":"venue"
},
  "geometry": {"coordinates":[9.6587934494,47.4327125549],"type":"Point"}
}