{
  "type": "Feature",
  "properties": {
    "iso:country":"AT",
    "sg:address":"E\u00dflinger Hauptstr 170",
    "sg:city":"Wien",
    "sg:classifiers":[
        {
            "category":"Restaurant",
            "type":"Food & Drink"
        }
    ],
    "sg:phone":"+43 1 7741764",
    "sg:postcode":"1220",
    "sg:province":"Wien",
    "sg:tags":[
        "pizzeria"
    ],
    "wof:name":"Pizzeria Don Nicola",
    "wof:placetype":"venue"
},
  "geometry": {"coordinates":[16.5361537933,48.2097511292],"type":"Point"}
}