{
  "type": "Feature",
  "properties": {
    "addr:full":"Ing Julius Raab-Str 7 Eisenstadt Burgenland 7000",
    "addr:housenumber":"7",
    "addr:postcode":"7000",
    "addr:street":"Raab-Str",
    "iso:country":"AT",
    "sg:address":"Ing Julius Raab-Str 7",
    "sg:city":"Eisenstadt",
    "sg:orig_category":"Politische Parteien",
    "sg:phone":"+43 2682 79948",
    "sg:postcode":"7000",
    "sg:province":"Burgenland",
    "wof:name":"Junge Volkspartei Bgld",
    "wof:placetype":"venue"
},
  "geometry": {"coordinates":[16.5277557373,47.8476295471],"type":"Point"}
}