{
  "type": "Feature",
  "properties": {
    "iso:country":"AT",
    "sg:address":"Marktstr 3",
    "sg:city":"Eisenstadt",
    "sg:orig_category":"Online-Service",
    "sg:phone":"+43 4359 01026430",
    "sg:postcode":"7000",
    "sg:province":"Burgenland",
    "wof:name":"m-price Service GmbH",
    "wof:placetype":"venue"
},
  "geometry": {"coordinates":[16.5320110321,47.8292007446],"type":"Point"}
}