{
  "type": "Feature",
  "properties": {
    "addr:full":"Eck 23 Gmunden Ober\u00f6sterreich 4810",
    "addr:housenumber":"23",
    "addr:postcode":"4810",
    "addr:street":"Eck;Oberoesterreich",
    "iso:country":"AT",
    "sg:address":"Eck 23",
    "sg:city":"Gmunden",
    "sg:orig_category":"Behinderungen / Leben Mit Behinderungen",
    "sg:phone":"+43 4376 12794208",
    "sg:postcode":"4810",
    "sg:province":"Ober\u00f6sterreich",
    "wof:name":"\u00f6ZIV - \u00f6sterreichischer Zivil-Invalidenverband",
    "wof:placetype":"venue"
},
  "geometry": {"coordinates":[13.7981462479,47.918598175],"type":"Point"}
}