{
  "type": "Feature",
  "properties": {
    "addr:full":"Amraser Str 56 Innsbruck Tirol 6020",
    "addr:housenumber":"56",
    "addr:postcode":"6020",
    "addr:street":"Amraser Str;Tirol",
    "iso:country":"AT",
    "sg:address":"Amraser Str 56",
    "sg:city":"Innsbruck",
    "sg:orig_category":"Massagen",
    "sg:phone":"+43 512 364900",
    "sg:postcode":"6020",
    "sg:province":"Tirol",
    "sg:website":"junwin.at",
    "wof:name":"Ganzheitliches Gesundheitszentrum Anton Jungmann & Norbert Winkler OEG",
    "wof:placetype":"venue"
},
  "geometry": {"coordinates":[11.4106330872,47.2627296448],"type":"Point"}
}