{
  "type": "Feature",
  "properties": {
    "addr:full":"Garteng 4 Hornstein Burgenland 7053",
    "addr:housenumber":"4",
    "addr:postcode":"7053",
    "addr:street":"Garteng",
    "iso:country":"AT",
    "sg:address":"Garteng 4",
    "sg:city":"Hornstein",
    "sg:orig_category":"Datenverarbeitung",
    "sg:phone":"+43 2689 3333",
    "sg:postcode":"7053",
    "sg:province":"Burgenland",
    "wof:name":"Jaitz Maria-Autom Datenverarbeitung",
    "wof:placetype":"venue"
},
  "geometry": {"coordinates":[16.4447917938,47.8832244873],"type":"Point"}
}