{
  "type": "Feature",
  "properties": {
    "addr:full":"Postgassl 35 Pfunds Tirol 6542",
    "addr:housenumber":"35",
    "addr:postcode":"6542",
    "addr:street":"Postgassl;Tirol",
    "iso:country":"AT",
    "sg:address":"Postgassl 35",
    "sg:city":"Pfunds",
    "sg:orig_category":"Tabaktrafiken",
    "sg:phone":"+43 4354 745209",
    "sg:postcode":"6542",
    "sg:province":"Tirol",
    "wof:name":"Trafik Zangerle",
    "wof:placetype":"venue"
},
  "geometry": {"coordinates":[10.5369300842,46.9696540833],"type":"Point"}
}