{
  "type": "Feature",
  "properties": {
    "iso:country":"AT",
    "sg:address":"Glanfeldstr 44/2",
    "sg:city":"Salzburg",
    "sg:orig_category":"Steuerberatung",
    "sg:phone":"+43 4366 2828564",
    "sg:postcode":"5020",
    "sg:province":"Salzburg",
    "wof:name":"Wirtschaftstreuhand & BeratungsgesmbH",
    "wof:placetype":"venue"
},
  "geometry": {"coordinates":[13.0047502518,47.7777061462],"type":"Point"}
}