{
  "type": "Feature",
  "properties": {
    "iso:country":"AT",
    "sg:address":"Waltenbachstr. 6",
    "sg:city":"Leoben",
    "sg:classifiers":[
        {
            "category":"Parking",
            "subcategory":"Lot",
            "type":"Transportation"
        }
    ],
    "sg:phone":"+43 4338 42833440",
    "sg:postcode":"8700",
    "sg:province":"Steiermark",
    "sg:tags":[
        "transport",
        "road"
    ],
    "wof:name":"TRANSPORT UND SPEDITIONS GESMBH (TSG)",
    "wof:placetype":"venue"
},
  "geometry": {"coordinates":[15.1293497086,47.384311676],"type":"Point"}
}