{
  "type": "Feature",
  "properties": {
    "iso:country":"AT",
    "sg:address":"Unterkaltberg 252",
    "sg:city":"Schwarzenberg",
    "sg:orig_category":"Appartements / Ferienwohnungen",
    "sg:phone":"+43 4355 1226228",
    "sg:postcode":"6867",
    "sg:province":"Vorarlberg",
    "wof:name":"Roy-Drozd Bettina u Louis",
    "wof:placetype":"venue"
},
  "geometry": {"coordinates":[9.8466720581,47.411403656],"type":"Point"}
}