{
  "type": "Feature",
  "properties": {
    "iso:country":"AT",
    "sg:address":"Marktstr 12/1",
    "sg:city":"Dornbirn",
    "sg:orig_category":"Architekten",
    "sg:phone":"+43 4355 72331980",
    "sg:postcode":"6850",
    "sg:province":"Vorarlberg",
    "wof:name":"Huber PlanungsgesmbH",
    "wof:placetype":"venue"
},
  "geometry": {"coordinates":[9.7424907684,47.4125709534],"type":"Point"}
}