{
  "type": "Feature",
  "properties": {
    "iso:country":"AT",
    "sg:address":"Johann-Joseph-Fux-G 2",
    "sg:city":"Feldkirchen",
    "sg:orig_category":"Transportunternehmen",
    "sg:phone":"+43 3135 54826",
    "sg:postcode":"8073",
    "sg:province":"Steiermark",
    "wof:name":"Absenger Felix",
    "wof:placetype":"venue"
},
  "geometry": {"coordinates":[15.4597539902,46.9853286743],"type":"Point"}
}