{
  "type": "Feature",
  "properties": {
    "addr:full":"Prankhg 2 Oberalm Salzburg 5411",
    "addr:housenumber":"2",
    "addr:postcode":"5411",
    "addr:street":"Prankhg;Salzburg",
    "iso:country":"AT",
    "sg:address":"Prankhg 2",
    "sg:city":"Oberalm",
    "sg:orig_category":"Diamanten U -Werkzeuge / F Industrie U Gewerbe",
    "sg:phone":"+43 4362 4580337",
    "sg:postcode":"5411",
    "sg:province":"Salzburg",
    "wof:name":"K\u00f6pf Bernd Inh Renate K\u00f6pf",
    "wof:placetype":"venue"
},
  "geometry": {"coordinates":[13.1027851105,47.6956138611],"type":"Point"}
}