{
  "type": "Feature",
  "properties": {
    "addr:full":"Maurachfeld 25 Kitzb\u00fchel Tirol 6370",
    "addr:housenumber":"25",
    "addr:postcode":"6370",
    "addr:street":"Maurachfeld;Tirol",
    "iso:country":"AT",
    "sg:address":"Maurachfeld 25",
    "sg:city":"Kitzb\u00fchel",
    "sg:orig_category":"Appartements / Ferienwohnungen",
    "sg:phone":"+43 5356 72358",
    "sg:postcode":"6370",
    "sg:province":"Tirol",
    "wof:name":"Maurachbauer",
    "wof:placetype":"venue"
},
  "geometry": {"coordinates":[12.3889970779,47.4414215088],"type":"Point"}
}