{
  "type": "Feature",
  "properties": {
    "addr:full":"Stefan-Fadinger-Str 24 St. Agatha Ober\u00f6sterreich 4084",
    "addr:housenumber":"24",
    "addr:postcode":"4084",
    "addr:street":"Stefan-Fadinger-Str",
    "iso:country":"AT",
    "sg:address":"Stefan-Fadinger-Str 24",
    "sg:city":"St. Agatha",
    "sg:orig_category":"Autohandel",
    "sg:phone":"+43 7277 87000",
    "sg:postcode":"4084",
    "sg:province":"Ober\u00f6sterreich",
    "wof:name":"Baschinger G\u00fcnther Ing GmbH",
    "wof:placetype":"venue"
},
  "geometry": {"coordinates":[13.8795642853,48.3826904297],"type":"Point"}
}