{
  "type": "Feature",
  "properties": {
    "iso:country":"AT",
    "sg:address":"Hauptstr 10",
    "sg:city":"St. Veit an der G\u00f6lsen",
    "sg:orig_category":"Banken U Sparkassen",
    "sg:phone":"+43 4327 6323310",
    "sg:postcode":"3161",
    "sg:province":"Nieder\u00f6sterreich",
    "wof:name":"Raiffeisenbank Lilienfeld regGenmbH - Bankst St. Veit",
    "wof:placetype":"venue"
},
  "geometry": {"coordinates":[15.6685533524,48.0434761047],"type":"Point"}
}