{
  "type": "Feature",
  "properties": {
    "addr:full":"Siemensstrasse 4 Neunkirchen Nieder\u00f6sterreich 2620",
    "addr:housenumber":"4",
    "addr:postcode":"2620",
    "addr:street":"Siemensstrasse",
    "iso:country":"AT",
    "sg:address":"Siemensstrasse 4",
    "sg:city":"Neunkirchen",
    "sg:classifiers":[
        {
            "category":"Manufacturing",
            "subcategory":"Rubber & Plastics",
            "type":"Manufacturing & Wholesale Goods"
        }
    ],
    "sg:phone":"+43 2635 71610",
    "sg:postcode":"2620",
    "sg:province":"Nieder\u00f6sterreich",
    "sg:tags":[
        "injection",
        "part",
        "moulded"
    ],
    "sg:website":"members.magnet.at/molnar",
    "wof:name":"Michael Molnar",
    "wof:placetype":"venue"
},
  "geometry": {"coordinates":[16.0825557709,47.7204246521],"type":"Point"}
}