{
  "type": "Feature",
  "properties": {
    "addr:full":"Gewerb Litzelsdorf 218 Tamsweg Salzburg 5580",
    "addr:housenumber":"218",
    "addr:postcode":"5580",
    "addr:street":"Tamsweg Salzburg",
    "iso:country":"AT",
    "sg:address":"Gewerb Litzelsdorf 218",
    "sg:city":"Tamsweg",
    "sg:orig_category":"Installationsunternehmen",
    "sg:phone":"+43 6474 22300",
    "sg:postcode":"5580",
    "sg:province":"Salzburg",
    "wof:name":"Wieland GesmbH",
    "wof:placetype":"venue"
},
  "geometry": {"coordinates":[13.8101902008,47.1263389587],"type":"Point"}
}