{
  "type": "Feature",
  "properties": {
    "iso:country":"AT",
    "sg:address":"Kaiser-Franz-Josef-Str 1",
    "sg:city":"Millstatt",
    "sg:classifiers":[
        {
            "category":"Shopping",
            "subcategory":"Gifts & Souvenirs",
            "type":"Retail Goods"
        }
    ],
    "sg:phone":"+43 4347 663484",
    "sg:postcode":"9872",
    "sg:province":"K\u00e4rnten",
    "wof:name":"FIAN Souvenir u Sport",
    "wof:placetype":"venue"
},
  "geometry": {"coordinates":[13.571723938,46.8024559021],"type":"Point"}
}