{
  "type": "Feature",
  "properties": {
    "addr:full":"Linzer Str 10 Traun Ober\u00f6sterreich 4050",
    "addr:housenumber":"10",
    "addr:postcode":"4050",
    "addr:street":"Linzer Str",
    "iso:country":"AT",
    "sg:address":"Linzer Str 10",
    "sg:city":"Traun",
    "sg:orig_category":"Personalbereitstellung",
    "sg:phone":"+43 4372 2967575",
    "sg:postcode":"4050",
    "sg:province":"Ober\u00f6sterreich",
    "wof:name":"Manforce Tempor\u00e4rpersonal\u00fcberlassung GesmbH",
    "wof:placetype":"venue"
},
  "geometry": {"coordinates":[14.2386331558,48.2215499878],"type":"Point"}
}