{
  "type": "Feature",
  "properties": {
    "addr:full":"Nr 89 Yspertal Nieder\u00f6sterreich 3683",
    "addr:postcode":"3683",
    "addr:street":"Nr;Yspertal",
    "iso:country":"AT",
    "sg:address":"Nr 89",
    "sg:city":"Yspertal",
    "sg:orig_category":"Holzhandel",
    "sg:phone":"+43 7415 7302",
    "sg:postcode":"3683",
    "sg:province":"Nieder\u00f6sterreich",
    "wof:name":"Kreuzer Rudolf",
    "wof:placetype":"venue"
},
  "geometry": {"coordinates":[15.065489769,48.282119751],"type":"Point"}
}