{
  "type": "Feature",
  "properties": {
    "iso:country":"AT",
    "sg:address":"Zellerberg 10",
    "sg:city":"Kufstein",
    "sg:orig_category":"Transportunternehmen",
    "sg:phone":"+43 5372 64371",
    "sg:postcode":"6330",
    "sg:province":"Tirol",
    "wof:name":"Baumgartner Josef",
    "wof:placetype":"venue"
},
  "geometry": {"coordinates":[12.1507148743,47.5770187378],"type":"Point"}
}