{
  "type": "Feature",
  "properties": {
    "addr:full":"Mozartstr 12 Timelkam Ober\u00f6sterreich 4850",
    "addr:housenumber":"12",
    "addr:postcode":"4850",
    "addr:street":"Mozartstr",
    "iso:country":"AT",
    "sg:address":"Mozartstr 12",
    "sg:city":"Timelkam",
    "sg:orig_category":"Fotografen",
    "sg:phone":"+43 767295266",
    "sg:postcode":"4850",
    "sg:province":"Ober\u00f6sterreich",
    "wof:name":"Fettinger Andreas",
    "wof:placetype":"venue"
},
  "geometry": {"coordinates":[13.6131944656,47.9997749329],"type":"Point"}
}