{
  "type": "Feature",
  "properties": {
    "iso:country":"AT",
    "sg:address":"Nr 48",
    "sg:city":"Bad Gams",
    "sg:classifiers":[
        {
            "category":"Taxi",
            "type":"Transportation"
        }
    ],
    "sg:phone":"+43 3463 25910",
    "sg:postcode":"8524",
    "sg:province":"Steiermark",
    "sg:tags":[
        "personentransporte",
        "u"
    ],
    "wof:name":"Aldrian Taxi",
    "wof:placetype":"venue"
},
  "geometry": {"coordinates":[15.222864151,46.8697814941],"type":"Point"}
}