{
  "type": "Feature",
  "properties": {
    "addr:full":"Mittersiller Bundesstr 106 Piesendorf Salzburg 5721",
    "addr:housenumber":"106",
    "addr:postcode":"5721",
    "addr:street":"Salzburg",
    "iso:country":"AT",
    "sg:address":"Mittersiller Bundesstr 106",
    "sg:city":"Piesendorf",
    "sg:orig_category":"Raumausstattung",
    "sg:phone":"+43 4365 4920210",
    "sg:postcode":"5721",
    "sg:province":"Salzburg",
    "wof:name":"AMADE Hotel- u Raumausstattungs GmbH",
    "wof:placetype":"venue"
},
  "geometry": {"coordinates":[12.7207517624,47.2909622192],"type":"Point"}
}