{
  "type": "Feature",
  "properties": {
    "addr:full":"Tobersbach 18  Uttendorf Salzburg 5723",
    "addr:housenumber":"18",
    "addr:postcode":"5723",
    "addr:street":"Tobersbach;Salzburg",
    "iso:country":"AT",
    "sg:address":"Tobersbach 18 ",
    "sg:city":"Uttendorf",
    "sg:orig_category":"Miscellaneous Products",
    "sg:phone":"+43 4365 6382030",
    "sg:postcode":"5723",
    "sg:province":"Salzburg",
    "wof:name":"KEIL - NINDL GES.MBH & CO KG",
    "wof:placetype":"venue"
},
  "geometry": {"coordinates":[12.5895786285,47.2854118347],"type":"Point"}
}