{
  "type": "Feature",
  "properties": {
    "addr:full":"Laaer Berg-Str 168 Wien Wien 1100",
    "addr:housenumber":"168",
    "addr:postcode":"1100",
    "addr:street":"Berg-Str",
    "iso:country":"AT",
    "sg:address":"Laaer Berg-Str 168",
    "sg:city":"Wien",
    "sg:orig_category":"Apotheken",
    "sg:phone":"+43 1 68901660",
    "sg:postcode":"1100",
    "sg:province":"Wien",
    "wof:name":"Laaerberg Apotheke",
    "wof:placetype":"venue"
},
  "geometry": {"coordinates":[16.3956661224,48.1555862427],"type":"Point"}
}