{
  "type": "Feature",
  "properties": {
    "addr:full":"Gutensteiner Str 283 Waldegg an der Piesting Nieder\u00f6sterreich 2754",
    "addr:housenumber":"283",
    "addr:postcode":"2754",
    "addr:street":"Waldegg",
    "iso:country":"AT",
    "sg:address":"Gutensteiner Str 283",
    "sg:city":"Waldegg an der Piesting",
    "sg:orig_category":"Maler, Anstreicher U Lackierer",
    "sg:phone":"+43 4326 3348226",
    "sg:postcode":"2754",
    "sg:province":"Nieder\u00f6sterreich",
    "wof:name":"Reindl Peter",
    "wof:placetype":"venue"
},
  "geometry": {"coordinates":[16.0579948425,47.8691902161],"type":"Point"}
}