{
  "type": "Feature",
  "properties": {
    "addr:full":"Vordernberger Str 58 Eisenerz Steiermark 8790",
    "addr:postcode":"8790",
    "addr:street":"Str 58",
    "iso:country":"AT",
    "sg:address":"Vordernberger Str 58",
    "sg:city":"Eisenerz",
    "sg:orig_category":"Friseure U Frisiersalons",
    "sg:phone":"+43 4338 482425",
    "sg:postcode":"8790",
    "sg:province":"Steiermark",
    "wof:name":"Rieck Kurt",
    "wof:placetype":"venue"
},
  "geometry": {"coordinates":[14.9013137817,47.5420951843],"type":"Point"}
}