{
  "type": "Feature",
  "properties": {
    "iso:country":"AT",
    "sg:address":"Auerspergstr 11",
    "sg:city":"Linz",
    "sg:orig_category":"Orientteppiche",
    "sg:phone":"+43 664 5155750",
    "sg:postcode":"4020",
    "sg:province":"Ober\u00f6sterreich",
    "wof:name":"Aschari KEG",
    "wof:placetype":"venue"
},
  "geometry": {"coordinates":[14.2898283005,48.2973709106],"type":"Point"}
}