{
  "type": "Feature",
  "properties": {
    "addr:full":"Oberdorf 232 Saalbach Salzburg 5753",
    "addr:housenumber":"232",
    "addr:postcode":"5753",
    "addr:street":"Oberdorf;Salzburg",
    "iso:country":"AT",
    "sg:address":"Oberdorf 232",
    "sg:city":"Saalbach",
    "sg:classifiers":[
        {
            "category":"Travel",
            "subcategory":"Hotels & Motels",
            "type":"Entertainment"
        }
    ],
    "sg:phone":"+43 4365 4162130",
    "sg:postcode":"5753",
    "sg:province":"Salzburg",
    "wof:name":"Hotel Bauer",
    "wof:placetype":"venue"
},
  "geometry": {"coordinates":[12.6374940872,47.3920097351],"type":"Point"}
}