{
  "type": "Feature",
  "properties": {
    "addr:full":"Griechengasse 7 Wien Wien 1010",
    "addr:housenumber":"7",
    "addr:postcode":"1010",
    "addr:street":"Griechengasse",
    "iso:country":"AT",
    "sg:address":"Griechengasse 7",
    "sg:city":"Wien",
    "sg:classifiers":[
        {
            "category":"Communications",
            "subcategory":"Film & Video Production",
            "type":"Services"
        }
    ],
    "sg:phone":"+43 1 5336137",
    "sg:postcode":"1010",
    "sg:province":"Wien",
    "sg:website":"schukoff.com",
    "wof:name":"Alexander Schukoff - Film",
    "wof:placetype":"venue"
},
  "geometry": {"coordinates":[16.3773002625,48.2110176086],"type":"Point"}
}