{
  "type": "Feature",
  "properties": {
    "addr:full":"Almer Str 12 Saalfelden am Steinernen Meer Salzburg 5760",
    "addr:postcode":"5760",
    "addr:street":"Str 12;Salzburg",
    "iso:country":"AT",
    "sg:address":"Almer Str 12",
    "sg:city":"Saalfelden am Steinernen Meer",
    "sg:orig_category":"Schlossereien",
    "sg:phone":"+43 4365 8272692",
    "sg:postcode":"5760",
    "sg:province":"Salzburg",
    "wof:name":"Leitner Reinhard",
    "wof:placetype":"venue"
},
  "geometry": {"coordinates":[12.8479719162,47.4255943298],"type":"Point"}
}