{
  "type": "Feature",
  "properties": {
    "addr:full":"Waldeben 2 Weerberg Tirol 6133",
    "addr:housenumber":"2",
    "addr:postcode":"6133",
    "addr:street":"Waldeben;Tirol",
    "iso:country":"AT",
    "sg:address":"Waldeben 2",
    "sg:city":"Weerberg",
    "sg:orig_category":"Tischlereien",
    "sg:phone":"+43 5224 67838",
    "sg:postcode":"6133",
    "sg:province":"Tirol",
    "wof:name":"Knapp Thomas",
    "wof:placetype":"venue"
},
  "geometry": {"coordinates":[11.678273201,47.3140869141],"type":"Point"}
}