{
  "type": "Feature",
  "properties": {
    "addr:full":"Gerasdorfer Strasse 151 Wien Wien 1210",
    "addr:housenumber":"151",
    "addr:postcode":"1210",
    "addr:street":"Gerasdorfer Strasse",
    "iso:country":"AT",
    "sg:address":"Gerasdorfer Strasse 151",
    "sg:city":"Wien",
    "sg:classifiers":[
        {
            "category":"Recreation",
            "subcategory":"Water Park",
            "type":"Entertainment"
        }
    ],
    "sg:phone":"+43 4255 2728",
    "sg:postcode":"1210",
    "sg:province":"Wien",
    "sg:tags":[
        "remediation",
        "soil"
    ],
    "sg:website":"altec.at",
    "wof:name":"ALTEC Umwelttechnik GmbH",
    "wof:placetype":"venue"
},
  "geometry": {"coordinates":[16.4322814941,48.2863464355],"type":"Point"}
}