{
  "type": "Feature",
  "properties": {
    "iso:country":"AT",
    "sg:address":"Dr Koss-Str 2",
    "sg:city":"Wels",
    "sg:orig_category":"Brautkleider U -Artikel",
    "sg:phone":"+43 7242 35166",
    "sg:postcode":"4600",
    "sg:province":"Ober\u00f6sterreich",
    "wof:name":"Brautmoden Sissi",
    "wof:placetype":"venue"
},
  "geometry": {"coordinates":[14.0204229355,48.1587791443],"type":"Point"}
}