{
  "type": "Feature",
  "properties": {
    "iso:country":"AT",
    "sg:address":"Rilkepl 7",
    "sg:city":"Wien",
    "sg:orig_category":"Pensionen / Privatzimmer",
    "sg:phone":"+43 1 58661830",
    "sg:postcode":"1040",
    "sg:province":"Wien",
    "wof:name":"Hotel Shermin Apartments",
    "wof:placetype":"venue"
},
  "geometry": {"coordinates":[16.367395401,48.1980361938],"type":"Point"}
}