{
  "type": "Feature",
  "properties": {
    "iso:country":"AT",
    "sg:address":"Rading 79",
    "sg:city":"Ro\u00dfleithen",
    "sg:classifiers":[
        {
            "category":"Home & Garden",
            "subcategory":"Garden Supply",
            "type":"Retail Goods"
        }
    ],
    "sg:phone":"+43 4375 6284450",
    "sg:postcode":"4575",
    "sg:province":"Ober\u00f6sterreich",
    "sg:tags":[
        "schotter",
        "sand",
        "u"
    ],
    "wof:name":"Polz Walter",
    "wof:placetype":"venue"
},
  "geometry": {"coordinates":[14.2730884552,47.7020835876],"type":"Point"}
}