{
  "type": "Feature",
  "properties": {
    "iso:country":"AT",
    "sg:address":"Kochstr 5",
    "sg:city":"Innsbruck",
    "sg:orig_category":"\u00c3\u201erzte / F Allgemeinmedizin",
    "sg:phone":"+43 4351 2576690",
    "sg:postcode":"6020",
    "sg:province":"Tirol",
    "wof:name":"Geir Walter DDr",
    "wof:placetype":"venue"
},
  "geometry": {"coordinates":[11.4018535614,47.2719917297],"type":"Point"}
}