{
  "type": "Feature",
  "properties": {
    "addr:full":"Hauptstr 39 Donnerskirchen Burgenland 7082",
    "addr:housenumber":"39",
    "addr:postcode":"7082",
    "addr:street":"Hauptstr",
    "iso:country":"AT",
    "sg:address":"Hauptstr 39",
    "sg:city":"Donnerskirchen",
    "sg:orig_category":"Bankomat-Standorte",
    "sg:phone":"+43 2683 8686",
    "sg:postcode":"7082",
    "sg:province":"Burgenland",
    "wof:name":"Bankomat d Raiffeisenbank Donnerskirchen-Oggau-Sch\u00fctzen regGenmbH",
    "wof:placetype":"venue"
},
  "geometry": {"coordinates":[16.6438446045,47.8966598511],"type":"Point"}
}