{
  "type": "Feature",
  "properties": {
    "addr:full":"Dr.-Dollfu\u00df-Pl 2 Mank Nieder\u00f6sterreich 3240",
    "addr:housenumber":"2",
    "addr:postcode":"3240",
    "addr:street":"Dr.-Dollfuss-Pl;Niederoesterreich",
    "iso:country":"AT",
    "sg:address":"Dr.-Dollfu\u00df-Pl 2",
    "sg:city":"Mank",
    "sg:orig_category":"Blumeneinzelhandel",
    "sg:phone":"+43 2755 2247",
    "sg:postcode":"3240",
    "sg:province":"Nieder\u00f6sterreich",
    "wof:name":"Blumen Gasser OEG",
    "wof:placetype":"venue"
},
  "geometry": {"coordinates":[15.3406190872,48.1110343933],"type":"Point"}
}