{
  "type": "Feature",
  "properties": {
    "addr:full":"Bahnhofpl 1 Leobersdorf Nieder\u00f6sterreich 2544",
    "addr:housenumber":"1",
    "addr:postcode":"2544",
    "addr:street":"Bahnhofpl",
    "iso:country":"AT",
    "sg:address":"Bahnhofpl 1",
    "sg:city":"Leobersdorf",
    "sg:orig_category":"Blechbe- U -Verarbeitung",
    "sg:phone":"+43 4322 5665362",
    "sg:postcode":"2544",
    "sg:province":"Nieder\u00f6sterreich",
    "wof:name":"Neuberger Ing V & Sohn KG",
    "wof:placetype":"venue"
},
  "geometry": {"coordinates":[16.2309989929,47.9370956421],"type":"Point"}
}