{
  "type": "Feature",
  "properties": {
    "addr:full":"G\u00e4rtnerg 19 Schwechat Nieder\u00f6sterreich 2320",
    "addr:housenumber":"19",
    "addr:postcode":"2320",
    "addr:street":"Gaertnerg;Niederoesterreich",
    "iso:country":"AT",
    "sg:address":"G\u00e4rtnerg 19",
    "sg:city":"Schwechat",
    "sg:orig_category":"Blumeneinzelhandel",
    "sg:phone":"+43 1 7072555",
    "sg:postcode":"2320",
    "sg:province":"Nieder\u00f6sterreich",
    "wof:name":"Matheisz Michaela KEG",
    "wof:placetype":"venue"
},
  "geometry": {"coordinates":[16.4436378479,48.133014679],"type":"Point"}
}