{
  "type": "Feature",
  "properties": {
    "iso:country":"AT",
    "sg:address":"Breitenweg 4",
    "sg:city":"St. Peter",
    "sg:orig_category":"Friseure U Frisiersalons",
    "sg:phone":"+43 316 423515",
    "sg:postcode":"8042",
    "sg:province":"Steiermark",
    "wof:name":"Atmosphair - Musyl",
    "wof:placetype":"venue"
},
  "geometry": {"coordinates":[15.4753828049,47.0578689575],"type":"Point"}
}