{
  "type": "Feature",
  "properties": {
    "addr:full":"Friedhofstr 3 Offenhausen Ober\u00f6sterreich 4625",
    "addr:housenumber":"3",
    "addr:postcode":"4625",
    "addr:street":"Friedhofstr",
    "iso:country":"AT",
    "sg:address":"Friedhofstr 3",
    "sg:city":"Offenhausen",
    "sg:orig_category":"Lebensmittel / Einzelhandel",
    "sg:phone":"+43 7247 6154",
    "sg:postcode":"4625",
    "sg:province":"Ober\u00f6sterreich",
    "wof:name":"Spar-Markt Inh Bernhard Poschacher",
    "wof:placetype":"venue"
},
  "geometry": {"coordinates":[13.8355989456,48.1568222046],"type":"Point"}
}