{
  "type": "Feature",
  "properties": {
    "iso:country":"AT",
    "sg:address":"Liebhartstalstr 20-24",
    "sg:city":"Wien",
    "sg:orig_category":"Waren Aller Art",
    "sg:phone":"+43 4317 861825",
    "sg:postcode":"1160",
    "sg:province":"Wien",
    "wof:name":"VEMIMPEX HandelsgesmbH",
    "wof:placetype":"venue"
},
  "geometry": {"coordinates":[16.2914009094,48.2165222168],"type":"Point"}
}