{
  "type": "Feature",
  "properties": {
    "addr:full":"Ruster Str 144/FMZ/Eisenstadt Eisenstadt Burgenland 7000",
    "addr:housenumber":"144 / fmz",
    "addr:postcode":"7000",
    "iso:country":"AT",
    "sg:address":"Ruster Str 144/FMZ/Eisenstadt",
    "sg:city":"Eisenstadt",
    "sg:orig_category":"Lederwaren / Einzelhandel",
    "sg:phone":"+43 4326 8268029",
    "sg:postcode":"7000",
    "sg:province":"Burgenland",
    "wof:name":"Bag - Lederwaren Prikler Gerhard",
    "wof:placetype":"venue"
},
  "geometry": {"coordinates":[16.5189552307,47.8455657959],"type":"Point"}
}