{
  "type": "Feature",
  "properties": {
    "addr:full":"B\u00f6sendorferstr 4 Wien Wien 1010",
    "addr:housenumber":"4",
    "addr:postcode":"1010",
    "addr:street":"Boesendorferstr",
    "iso:country":"AT",
    "sg:address":"B\u00f6sendorferstr 4",
    "sg:city":"Wien",
    "sg:orig_category":"Friseure U Frisiersalons",
    "sg:phone":"+43 1 5051006",
    "sg:postcode":"1010",
    "sg:province":"Wien",
    "wof:name":"Rachle' Friseur",
    "wof:placetype":"venue"
},
  "geometry": {"coordinates":[16.3700027466,48.2013244629],"type":"Point"}
}