{
  "type": "Feature",
  "properties": {
    "addr:full":"Neuwaldegger Str 3076 Wien Wien 1170",
    "addr:postcode":"3076;1170",
    "addr:street":"Str",
    "iso:country":"AT",
    "sg:address":"Neuwaldegger Str 3076",
    "sg:city":"Wien",
    "sg:orig_category":"Webdesign",
    "sg:phone":"+43 699 11090588",
    "sg:postcode":"1170",
    "sg:province":"Wien",
    "wof:name":"Redboxoffice new Media Solutions- new Media Solutions",
    "wof:placetype":"venue"
},
  "geometry": {"coordinates":[16.2796897888,48.2404708862],"type":"Point"}
}