{
  "type": "Feature",
  "properties": {
    "addr:full":"Tanngrabenstr 2 Amstetten Nieder\u00f6sterreich 3300",
    "addr:housenumber":"2",
    "addr:postcode":"3300",
    "addr:street":"Tanngrabenstr;Niederoesterreich",
    "iso:country":"AT",
    "sg:address":"Tanngrabenstr 2",
    "sg:city":"Amstetten",
    "sg:orig_category":"Gemeinden",
    "sg:phone":"+43 7472 643190",
    "sg:postcode":"3300",
    "sg:province":"Nieder\u00f6sterreich",
    "wof:name":"Gemeindeamt Winklarn",
    "wof:placetype":"venue"
},
  "geometry": {"coordinates":[14.8480186462,48.0907897949],"type":"Point"}
}