{
  "type": "Feature",
  "properties": {
    "addr:full":"Gradnerstr 92 Puntigam Steiermark 8055",
    "addr:housenumber":"92",
    "addr:postcode":"8055",
    "addr:street":"Gradnerstr",
    "iso:country":"AT",
    "sg:address":"Gradnerstr 92",
    "sg:city":"Puntigam",
    "sg:orig_category":"Isolierungen",
    "sg:phone":"+43 316 2956460",
    "sg:postcode":"8055",
    "sg:province":"Steiermark",
    "wof:name":"Isolit-Isolier GesmbH",
    "wof:placetype":"venue"
},
  "geometry": {"coordinates":[15.4180965424,47.0219917297],"type":"Point"}
}