{
  "type": "Feature",
  "properties": {
    "addr:full":"Florianig 16 Wien Wien 1080",
    "addr:housenumber":"16",
    "addr:postcode":"1080",
    "addr:street":"Florianig",
    "iso:country":"AT",
    "sg:address":"Florianig 16",
    "sg:city":"Wien",
    "sg:orig_category":"Gewerkschaften",
    "sg:phone":"+43 1 4025171",
    "sg:postcode":"1080",
    "sg:province":"Wien",
    "wof:name":"FG\u00f6 Freie Gewerkschaft \u00f6sterreich",
    "wof:placetype":"venue"
},
  "geometry": {"coordinates":[16.3522891998,48.2120704651],"type":"Point"}
}