{
  "type": "Feature",
  "properties": {
    "addr:full":"Golling 31 Golling an der Salzach Salzburg 5440",
    "addr:housenumber":"31",
    "addr:postcode":"5440",
    "addr:street":"Golling",
    "iso:country":"AT",
    "sg:address":"Golling 31",
    "sg:city":"Golling an der Salzach",
    "sg:classifiers":[
        {
            "category":"Banks & Credit Unions",
            "subcategory":"Bureau De Change",
            "type":"Services"
        }
    ],
    "sg:phone":"+43 6244 43690",
    "sg:postcode":"5440",
    "sg:province":"Salzburg",
    "sg:tags":[
        "flat",
        "construction",
        "roof"
    ],
    "wof:name":"HSG - Schattauer GesmbH & Co KG",
    "wof:placetype":"venue"
},
  "geometry": {"coordinates":[13.2115449905,47.5899581909],"type":"Point"}
}