{
  "type": "Feature",
  "properties": {
    "addr:full":"Ressavarstr 23 Hartberg Steiermark 8230",
    "addr:housenumber":"23",
    "addr:postcode":"8230",
    "addr:street":"Ressavarstr",
    "iso:country":"AT",
    "sg:address":"Ressavarstr 23",
    "sg:city":"Hartberg",
    "sg:orig_category":"Tourismusinformation U -Organisationen",
    "sg:phone":"+43 4333 3264213",
    "sg:postcode":"8230",
    "sg:province":"Steiermark",
    "wof:name":"Tourismusregionalverband Oststeiermark",
    "wof:placetype":"venue"
},
  "geometry": {"coordinates":[15.9711837769,47.2806434631],"type":"Point"}
}