{
  "type": "Feature",
  "properties": {
    "addr:full":"Triester Str 222 Feldkirchen Steiermark 8073",
    "addr:housenumber":"222",
    "addr:postcode":"8073",
    "iso:country":"AT",
    "sg:address":"Triester Str 222",
    "sg:city":"Feldkirchen",
    "sg:orig_category":"Transportunternehmen",
    "sg:phone":"+43 699 10940447",
    "sg:postcode":"8073",
    "sg:province":"Steiermark",
    "wof:name":"Fischer Harald",
    "wof:placetype":"venue"
},
  "geometry": {"coordinates":[15.4545507431,46.9933738708],"type":"Point"}
}