{
  "type": "Feature",
  "properties": {
    "addr:full":"Hauptpl 16 Irdning Steiermark 8952",
    "addr:housenumber":"16",
    "addr:postcode":"8952",
    "addr:street":"Hauptpl",
    "iso:country":"AT",
    "sg:address":"Hauptpl 16",
    "sg:city":"Irdning",
    "sg:orig_category":"Automaten",
    "sg:phone":"+43 676 7558304",
    "sg:postcode":"8952",
    "sg:province":"Steiermark",
    "wof:name":"Automatenaufstellung Napetschnig",
    "wof:placetype":"venue"
},
  "geometry": {"coordinates":[14.1046161652,47.5055541992],"type":"Point"}
}