{
  "type": "Feature",
  "properties": {
    "addr:full":"Neusch\u00f6nauer Hauptstr 3 Steyr Ober\u00f6sterreich 4400",
    "addr:housenumber":"3",
    "addr:postcode":"4400",
    "addr:street":"Hauptstr;Oberoesterreich",
    "iso:country":"AT",
    "sg:address":"Neusch\u00f6nauer Hauptstr 3",
    "sg:city":"Steyr",
    "sg:orig_category":"Steuerberatung",
    "sg:phone":"+43 4372 5252098",
    "sg:postcode":"4400",
    "sg:province":"Ober\u00f6sterreich",
    "wof:name":"Eberharter Peter",
    "wof:placetype":"venue"
},
  "geometry": {"coordinates":[14.4170379639,48.0326004028],"type":"Point"}
}