{
  "type": "Feature",
  "properties": {
    "iso:country":"AT",
    "sg:address":"Wetterherrenweg 14a",
    "sg:city":"Innsbruck",
    "sg:orig_category":"\u00c3\u201erzte / F Allgemeinmedizin",
    "sg:phone":"+43 512 361665",
    "sg:postcode":"6020",
    "sg:province":"Tirol",
    "wof:name":"Fassl Alexander Dr",
    "wof:placetype":"venue"
},
  "geometry": {"coordinates":[11.4139442444,47.2569541931],"type":"Point"}
}