{
  "type": "Feature",
  "properties": {
    "iso:country":"AT",
    "sg:address":"Neubaug 15",
    "sg:city":"Hartberg",
    "sg:orig_category":"Sprengungen",
    "sg:phone":"+43 3332 63375",
    "sg:postcode":"8230",
    "sg:province":"Steiermark",
    "wof:name":"Reichel Erich",
    "wof:placetype":"venue"
},
  "geometry": {"coordinates":[15.9727478027,47.2819519043],"type":"Point"}
}