{
  "type": "Feature",
  "properties": {
    "addr:full":"Bahnhofstr 44 Klagenfurt K\u00e4rnten 9020",
    "addr:housenumber":"44",
    "addr:postcode":"9020",
    "addr:street":"Bahnhofstr;Kaernten",
    "iso:country":"AT",
    "sg:address":"Bahnhofstr 44",
    "sg:city":"Klagenfurt",
    "sg:orig_category":"Gewerkschaften",
    "sg:phone":"+43 463 58700",
    "sg:postcode":"9020",
    "sg:province":"K\u00e4rnten",
    "wof:name":"Gewerkschaft Bau - Holz",
    "wof:placetype":"venue"
},
  "geometry": {"coordinates":[14.3126573563,46.6173667908],"type":"Point"}
}