{
  "type": "Feature",
  "properties": {
    "addr:full":"Werk- Vi- Str. 59  Kapfenberg Steiermark 8605",
    "addr:housenumber":"59",
    "addr:postcode":"8605",
    "addr:street":"Werk Vi Str.",
    "iso:country":"AT",
    "sg:address":"Werk- Vi- Str. 59 ",
    "sg:city":"Kapfenberg",
    "sg:classifiers":[
        {
            "category":"Autos & Motor Vehicles",
            "subcategory":"Automobile Sales",
            "type":"Retail Goods"
        }
    ],
    "sg:phone":"+43 4338 62337770",
    "sg:postcode":"8605",
    "sg:province":"Steiermark",
    "sg:tags":[
        "motor-cars"
    ],
    "wof:name":"COLLINS & AIKMAN PRODUCTS GMBH",
    "wof:placetype":"venue"
},
  "geometry": {"coordinates":[15.33411026,47.4523010254],"type":"Point"}
}