{
  "type": "Feature",
  "properties": {
    "addr:full":"Selzthaler Str 15 Liezen Steiermark 8940",
    "addr:postcode":"8940",
    "addr:street":"Str 15",
    "iso:country":"AT",
    "sg:address":"Selzthaler Str 15",
    "sg:city":"Liezen",
    "sg:orig_category":"Technische Gase",
    "sg:phone":"+43 3612 26002",
    "sg:postcode":"8940",
    "sg:province":"Steiermark",
    "wof:name":"Linde Gas GmbH - Auslieferungslager",
    "wof:placetype":"venue"
},
  "geometry": {"coordinates":[14.2467279434,47.5588493347],"type":"Point"}
}