{
  "type": "Feature",
  "properties": {
    "addr:full":"Jenbach Tirol 6200",
    "addr:postcode":"6200",
    "addr:street":"Tirol",
    "iso:country":"AT",
    "sg:city":"Jenbach",
    "sg:orig_category":"Feuerwehren",
    "sg:phone":"+43 5244 6262314",
    "sg:postcode":"6200",
    "sg:province":"Tirol",
    "wof:name":"Freiwillige Feuerwehr Wiesing",
    "wof:placetype":"venue"
},
  "geometry": {"coordinates":[11.7983427048,47.4045028687],"type":"Point"}
}