{
  "type": "Feature",
  "properties": {
    "iso:country":"AT",
    "sg:address":"Pressackerweg 23",
    "sg:city":"Moosburg",
    "sg:orig_category":"Waren Aller Art",
    "sg:phone":"+43 699 11368781",
    "sg:postcode":"9062",
    "sg:province":"K\u00e4rnten",
    "wof:name":"K\u00f6ssldorfer WarenhandelsgesmbH",
    "wof:placetype":"venue"
},
  "geometry": {"coordinates":[14.2055635452,46.6680297852],"type":"Point"}
}