{
  "type": "Feature",
  "properties": {
    "addr:full":"Unterdorf 4 Bezau Vorarlberg 6870",
    "addr:housenumber":"4",
    "addr:postcode":"6870",
    "addr:street":"Unterdorf",
    "iso:country":"AT",
    "sg:address":"Unterdorf 4",
    "sg:city":"Bezau",
    "sg:orig_category":"Fahrzeugbau",
    "sg:phone":"+43 5514 22580",
    "sg:postcode":"6870",
    "sg:province":"Vorarlberg",
    "wof:name":"Meusburger Fahrzeugbau GesmbH",
    "wof:placetype":"venue"
},
  "geometry": {"coordinates":[9.8937549591,47.3854064941],"type":"Point"}
}