{
  "type": "Feature",
  "properties": {
    "addr:full":"Fischeraustr 56 G\u00f6sting Steiermark 8051",
    "addr:housenumber":"56",
    "addr:postcode":"8051",
    "addr:street":"Fischeraustr",
    "iso:country":"AT",
    "sg:address":"Fischeraustr 56",
    "sg:city":"G\u00f6sting",
    "sg:orig_category":"Schlossereien",
    "sg:phone":"+43 316 675350",
    "sg:postcode":"8051",
    "sg:province":"Steiermark",
    "wof:name":"Turek Erhard",
    "wof:placetype":"venue"
},
  "geometry": {"coordinates":[15.4076929092,47.0987815857],"type":"Point"}
}