{
  "type": "Feature",
  "properties": {
    "iso:country":"AT",
    "sg:address":"Bichlnweg 20",
    "sg:city":"Kitzb\u00fchel",
    "sg:classifiers":[
        {
            "category":"Internet Cafe",
            "subcategory":"None",
            "type":"Food & Drink"
        }
    ],
    "sg:phone":"+43 4366 42052385",
    "sg:postcode":"6370",
    "sg:province":"Tirol",
    "wof:name":"Werbeagentur & Websolution BHL/CMR",
    "wof:placetype":"venue"
},
  "geometry": {"coordinates":[12.4068832397,47.4372253418],"type":"Point"}
}