{
  "type": "Feature",
  "properties": {
    "addr:full":"Schie\u00dfstattg 25 Tulln an der Donau Nieder\u00f6sterreich 3430",
    "addr:housenumber":"25",
    "addr:postcode":"3430",
    "addr:street":"Schiessstattg",
    "iso:country":"AT",
    "sg:address":"Schie\u00dfstattg 25",
    "sg:city":"Tulln an der Donau",
    "sg:orig_category":"Pensionen / Privatzimmer",
    "sg:phone":"+43 2272 63692",
    "sg:postcode":"3430",
    "sg:province":"Nieder\u00f6sterreich",
    "wof:name":"Haus Erika",
    "wof:placetype":"venue"
},
  "geometry": {"coordinates":[16.0442657471,48.3301849365],"type":"Point"}
}