{
  "type": "Feature",
  "properties": {
    "iso:country":"AT",
    "sg:address":"Grabenstr 10",
    "sg:city":"St. Veit an der Glan",
    "sg:orig_category":"\u00c3\u201erzte / F Allgemeinmedizin",
    "sg:phone":"+43 4342 125413",
    "sg:postcode":"9300",
    "sg:province":"K\u00e4rnten",
    "wof:name":"Dornkasch Raimund Dr",
    "wof:placetype":"venue"
},
  "geometry": {"coordinates":[14.358537674,46.7695159912],"type":"Point"}
}