{
  "type": "Feature",
  "properties": {
    "addr:full":"Ratschkyg 4 Wien Wien 1120",
    "addr:housenumber":"4",
    "addr:postcode":"1120",
    "addr:street":"Ratschkyg",
    "iso:country":"AT",
    "sg:address":"Ratschkyg 4",
    "sg:city":"Wien",
    "sg:orig_category":"Rauchfangsanierungen U -Ausschleifungen",
    "sg:phone":"+43 1 9669259",
    "sg:postcode":"1120",
    "sg:province":"Wien",
    "sg:website":"www.seydi.at",
    "wof:name":"S.E.Y.D.I. Kaminsanierungs- und Bauprofi GesmbH",
    "wof:placetype":"venue"
},
  "geometry": {"coordinates":[16.3295097351,48.177116394],"type":"Point"}
}