{
  "type": "Feature",
  "properties": {
    "addr:full":"Finkleiten 31 K\u00f6stendorf Salzburg 5203",
    "addr:housenumber":"31",
    "addr:postcode":"5203",
    "addr:street":"Finkleiten;Salzburg",
    "iso:country":"AT",
    "sg:address":"Finkleiten 31",
    "sg:city":"K\u00f6stendorf",
    "sg:classifiers":[
        {
            "category":"Shopping",
            "subcategory":"Party Supplies",
            "type":"Retail Goods"
        }
    ],
    "sg:phone":"+43 4366 45003406",
    "sg:postcode":"5203",
    "sg:province":"Salzburg",
    "sg:tags":[
        "u",
        "lichtanlagen",
        "ton-"
    ],
    "wof:name":"Eggenhofer G\u00fcnther - Power Station",
    "wof:placetype":"venue"
},
  "geometry": {"coordinates":[13.1981563568,47.9566192627],"type":"Point"}
}