{
  "type": "Feature",
  "properties": {
    "iso:country":"AT",
    "sg:address":"Kienzlstr 30",
    "sg:city":"Waizenkirchen",
    "sg:orig_category":"Fotografen",
    "sg:phone":"+43 7277 2358",
    "sg:postcode":"4730",
    "sg:province":"Ober\u00f6sterreich",
    "wof:name":"Fotostudio Gerhard Humer",
    "wof:placetype":"venue"
},
  "geometry": {"coordinates":[13.8544569016,48.3322715759],"type":"Point"}
}