{
  "type": "Feature",
  "properties": {
    "addr:full":"Nr 31 Pfarrkirchen im M\u00fchlkreis Ober\u00f6sterreich 4141",
    "addr:postcode":"4141",
    "addr:street":"Nr 31;Oberoesterreich",
    "iso:country":"AT",
    "sg:address":"Nr 31",
    "sg:city":"Pfarrkirchen im M\u00fchlkreis",
    "sg:orig_category":"Volksschulen",
    "sg:phone":"+43 7285 425",
    "sg:postcode":"4141",
    "sg:province":"Ober\u00f6sterreich",
    "wof:name":"Volksschule",
    "wof:placetype":"venue"
},
  "geometry": {"coordinates":[13.8582963943,48.5014801025],"type":"Point"}
}