{
  "type": "Feature",
  "properties": {
    "addr:full":"Nr 90 Lochen Ober\u00f6sterreich 5221",
    "addr:postcode":"5221",
    "addr:street":"Nr 90",
    "iso:country":"AT",
    "sg:address":"Nr 90",
    "sg:city":"Lochen",
    "sg:orig_category":"Tourismusinformation U -Organisationen",
    "sg:phone":"+43 4377 458255",
    "sg:postcode":"5221",
    "sg:province":"Ober\u00f6sterreich",
    "wof:name":"Tourismusverband Lochen",
    "wof:placetype":"venue"
},
  "geometry": {"coordinates":[13.1802692413,48.0075187683],"type":"Point"}
}