{
  "type": "Feature",
  "properties": {
    "addr:full":"Favoritenstr Wien Wien 1100",
    "addr:postcode":"1100",
    "iso:country":"AT",
    "sg:address":"Favoritenstr",
    "sg:city":"Wien",
    "sg:orig_category":"Garagen Parkgaragen",
    "sg:phone":"+43 1 6881260",
    "sg:postcode":"1100",
    "sg:province":"Wien",
    "wof:name":"APCOA Parking Austria AG",
    "wof:placetype":"venue"
},
  "geometry": {"coordinates":[16.3742847443,48.1838150024],"type":"Point"}
}