{
  "type": "Feature",
  "properties": {
    "addr:full":"Josef Hutterer-Str 34 Wolfsgraben Nieder\u00f6sterreich 3012",
    "addr:housenumber":"34",
    "addr:postcode":"3012",
    "addr:street":"Wolfsgraben Niederoesterreich",
    "iso:country":"AT",
    "sg:address":"Josef Hutterer-Str 34",
    "sg:city":"Wolfsgraben",
    "sg:classifiers":[
        {
            "category":"Government",
            "subcategory":"Post Office",
            "type":"Public Place"
        }
    ],
    "sg:phone":"+43 2233 7110",
    "sg:postcode":"3012",
    "sg:province":"Nieder\u00f6sterreich",
    "sg:tags":[
        "-handel",
        "tierzucht",
        "u"
    ],
    "wof:name":"Grabec Franz",
    "wof:placetype":"venue"
},
  "geometry": {"coordinates":[16.1172504425,48.1607131958],"type":"Point"}
}