{
  "type": "Feature",
  "properties": {
    "iso:country":"AT",
    "sg:address":"Josef Hutterer-Str 34",
    "sg:city":"Wolfsgraben",
    "sg:classifiers":[
        {
            "category":"Government",
            "subcategory":"Post Office",
            "type":"Public Place"
        }
    ],
    "sg:phone":"+43 2233 7110",
    "sg:postcode":"3012",
    "sg:province":"Nieder\u00f6sterreich",
    "sg:tags":[
        "-handel",
        "tierzucht",
        "u"
    ],
    "wof:name":"Grabec Franz",
    "wof:placetype":"venue"
},
  "geometry": {"coordinates":[16.1172504425,48.1607131958],"type":"Point"}
}