{
  "type": "Feature",
  "properties": {
    "addr:full":"Stafflerstr 15 Innsbruck Tirol 6020",
    "addr:housenumber":"15",
    "addr:postcode":"6020",
    "addr:street":"Stafflerstr;Tirol",
    "iso:country":"AT",
    "sg:address":"Stafflerstr 15",
    "sg:city":"Innsbruck",
    "sg:orig_category":"Maler, Anstreicher U Lackierer",
    "sg:phone":"+43 512 576947",
    "sg:postcode":"6020",
    "sg:province":"Tirol",
    "wof:name":"Malerei Laner Anton",
    "wof:placetype":"venue"
},
  "geometry": {"coordinates":[11.3922624588,47.2571678162],"type":"Point"}
}