{
  "type": "Feature",
  "properties": {
    "addr:full":"Engelhofstr 32 Villach K\u00e4rnten 9500",
    "addr:housenumber":"32",
    "addr:postcode":"9500",
    "addr:street":"Engelhofstr;Kaernten",
    "iso:country":"AT",
    "sg:address":"Engelhofstr 32",
    "sg:city":"Villach",
    "sg:classifiers":[
        {
            "category":"Taxi",
            "type":"Transportation"
        }
    ],
    "sg:phone":"+43 650 5555130",
    "sg:postcode":"9500",
    "sg:province":"K\u00e4rnten",
    "sg:tags":[
        "personentransporte",
        "u"
    ],
    "wof:name":"Villacher Expresstaxi",
    "wof:placetype":"venue"
},
  "geometry": {"coordinates":[13.8511104584,46.6055183411],"type":"Point"}
}