{
  "type": "Feature",
  "properties": {
    "addr:full":"Wachaustr 15 Krems an der Donau Nieder\u00f6sterreich 3500",
    "addr:housenumber":"15",
    "addr:postcode":"3500",
    "addr:street":"Wachaustr",
    "iso:country":"AT",
    "sg:address":"Wachaustr 15",
    "sg:city":"Krems an der Donau",
    "sg:orig_category":"Autoglas",
    "sg:phone":"+43 2732 8243316",
    "sg:postcode":"3500",
    "sg:province":"Nieder\u00f6sterreich",
    "wof:name":"Becker F GmbH",
    "wof:placetype":"venue"
},
  "geometry": {"coordinates":[15.6090393066,48.4122772217],"type":"Point"}
}