{
  "type": "Feature",
  "properties": {
    "addr:full":"Landesbahnstr 2 Mistelbach Nieder\u00f6sterreich 2130",
    "addr:housenumber":"2",
    "addr:postcode":"2130",
    "addr:street":"Landesbahnstr;Niederoesterreich",
    "iso:country":"AT",
    "sg:address":"Landesbahnstr 2",
    "sg:city":"Mistelbach",
    "sg:classifiers":[
        {
            "category":"Restaurant",
            "type":"Food & Drink"
        }
    ],
    "sg:phone":"+43 2572 32057",
    "sg:postcode":"2130",
    "sg:province":"Nieder\u00f6sterreich",
    "wof:name":"Diesner Restaurant-Kegelbahnen-Partyservice",
    "wof:placetype":"venue"
},
  "geometry": {"coordinates":[16.5649204254,48.5641098022],"type":"Point"}
}