{
  "type": "Feature",
  "properties": {
    "addr:full":"Hofstattg 5 Wien Wien 1180",
    "addr:housenumber":"5",
    "addr:postcode":"1180",
    "addr:street":"Hofstattg",
    "iso:country":"AT",
    "sg:address":"Hofstattg 5",
    "sg:city":"Wien",
    "sg:orig_category":"Immobilienmakler",
    "sg:phone":"+43 1 4708603",
    "sg:postcode":"1180",
    "sg:province":"Wien",
    "wof:name":"Engelmann Ursula",
    "wof:placetype":"venue"
},
  "geometry": {"coordinates":[16.3405532837,48.2281837463],"type":"Point"}
}