{
  "type": "Feature",
  "properties": {
    "addr:full":"Hauptstr 38 Kirchberg in Tirol Tirol 6365",
    "addr:housenumber":"38",
    "addr:postcode":"6365",
    "addr:street":"Hauptstr;Tirol",
    "iso:country":"AT",
    "sg:address":"Hauptstr 38",
    "sg:city":"Kirchberg in Tirol",
    "sg:orig_category":"Pensionen / Privatzimmer",
    "sg:phone":"+43 5357 2203",
    "sg:postcode":"6365",
    "sg:province":"Tirol",
    "wof:name":"Fr\u00fchst\u00fcckspension Margreiter",
    "wof:placetype":"venue"
},
  "geometry": {"coordinates":[12.3127174377,47.4486236572],"type":"Point"}
}