{
  "type": "Feature",
  "properties": {
    "addr:full":"Hauptpl 7 Deutschlandsberg Steiermark 8530",
    "addr:housenumber":"7",
    "addr:postcode":"8530",
    "addr:street":"Hauptpl",
    "iso:country":"AT",
    "sg:address":"Hauptpl 7",
    "sg:city":"Deutschlandsberg",
    "sg:orig_category":"Ingenieurkonsulenten / Zivilingenieure",
    "sg:phone":"+43 3462 20520",
    "sg:postcode":"8530",
    "sg:province":"Steiermark",
    "wof:name":"Kahlen Peter Dipl-Ing",
    "wof:placetype":"venue"
},
  "geometry": {"coordinates":[15.2155704498,46.8150482178],"type":"Point"}
}