{
  "type": "Feature",
  "properties": {
    "addr:full":"Ascheter Strasse 44 Wels Ober\u00f6sterreich 4600",
    "addr:housenumber":"44",
    "addr:postcode":"4600",
    "addr:street":"Ascheter Strasse;Oberoesterreich",
    "iso:country":"AT",
    "sg:address":"Ascheter Strasse 44",
    "sg:city":"Wels",
    "sg:classifiers":[
        {
            "category":"Home & Garden",
            "subcategory":"Building Materials",
            "type":"Retail Goods"
        }
    ],
    "sg:phone":"+43 7242 47271",
    "sg:postcode":"4600",
    "sg:province":"Ober\u00f6sterreich",
    "sg:tags":[
        "aluminium",
        "window"
    ],
    "sg:website":"ipm-schober.com",
    "wof:name":"IPM Schober Fenster Ges.m.b.H.",
    "wof:placetype":"venue"
},
  "geometry": {"coordinates":[14.0215759277,48.1498756409],"type":"Point"}
}