{
  "type": "Feature",
  "properties": {
    "addr:full":"Shuttleworthstr 11-15 Wien Wien 1210",
    "addr:postcode":"11-15;1210",
    "iso:country":"AT",
    "sg:address":"Shuttleworthstr 11-15",
    "sg:city":"Wien",
    "sg:orig_category":"Lebensmittel / Einzelhandel",
    "sg:phone":"+43 4312 901526",
    "sg:postcode":"1210",
    "sg:province":"Wien",
    "wof:name":"Hofer KG",
    "wof:placetype":"venue"
},
  "geometry": {"coordinates":[16.4082698822,48.2713165283],"type":"Point"}
}