{
  "type": "Feature",
  "properties": {
    "addr:full":"Wiener Str 39 Baden Nieder\u00f6sterreich 2500",
    "addr:housenumber":"39",
    "addr:postcode":"2500",
    "addr:street":"Niederoesterreich",
    "iso:country":"AT",
    "sg:address":"Wiener Str 39",
    "sg:city":"Baden",
    "sg:orig_category":"Fotografen",
    "sg:phone":"+43 2252 89139",
    "sg:postcode":"2500",
    "sg:province":"Nieder\u00f6sterreich",
    "wof:name":"Olko Max GesmbH",
    "wof:placetype":"venue"
},
  "geometry": {"coordinates":[16.2454128265,48.0114898682],"type":"Point"}
}