{
  "type": "Feature",
  "properties": {
    "addr:full":"Grazer Str 155a Kumberg Steiermark 8062",
    "addr:postcode":"8062",
    "addr:street":"Str 155A",
    "iso:country":"AT",
    "sg:address":"Grazer Str 155a",
    "sg:city":"Kumberg",
    "sg:orig_category":"Installationsunternehmen",
    "sg:phone":"+43 4331 322918",
    "sg:postcode":"8062",
    "sg:province":"Steiermark",
    "wof:name":"Schinnerl Herbert GesmbH",
    "wof:placetype":"venue"
},
  "geometry": {"coordinates":[15.5747404099,47.1679191589],"type":"Point"}
}