{
  "type": "Feature",
  "properties": {
    "iso:country":"AT",
    "sg:address":"Renng 4/3",
    "sg:city":"Wien",
    "sg:orig_category":"Betriebsbeteiligungen",
    "sg:phone":"+43 4315 358666",
    "sg:postcode":"1010",
    "sg:province":"Wien",
    "wof:name":"DEXCO Mangement u BeteiligungsgesmbH",
    "wof:placetype":"venue"
},
  "geometry": {"coordinates":[16.3666400909,48.2120018005],"type":"Point"}
}