{
  "type": "Feature",
  "properties": {
    "iso:country":"AT",
    "sg:address":"R\u00f6ntgeng 28/4",
    "sg:city":"Oberwart",
    "sg:orig_category":"\u00c3\u201erzte / F Allgemeinmedizin",
    "sg:phone":"+43 3352 3372971",
    "sg:postcode":"7400",
    "sg:province":"Burgenland",
    "wof:name":"Fr\u00fchwirth Ilse Dr",
    "wof:placetype":"venue"
},
  "geometry": {"coordinates":[16.2014636993,47.2805328369],"type":"Point"}
}