{
  "type": "Feature",
  "properties": {
    "addr:full":"Hauptplatz 29 Postf. 470 4010",
    "addr:housenumber":"29;470",
    "addr:postcode":"4010",
    "addr:street":"Hauptplatz",
    "iso:country":"AT",
    "sg:address":"Hauptplatz 29 Postf. 470",
    "sg:orig_category":"Immobilien U Baugewerbe, Immobilienmarkt U Kleinanzeigen",
    "sg:phone":"+43 732 795878",
    "sg:postcode":"4010",
    "sg:website":"http://www.via.at/bipool",
    "wof:name":"BusinessImmobilien-POOL",
    "wof:placetype":"venue"
},
  "geometry": {"coordinates":[14.2881698608,48.3042411804],"type":"Point"}
}