{
  "type": "Feature",
  "properties": {
    "addr:full":"Althauser Str 5 Pregarten Ober\u00f6sterreich 4230",
    "addr:housenumber":"5",
    "addr:postcode":"4230",
    "addr:street":"Str",
    "iso:country":"AT",
    "sg:address":"Althauser Str 5",
    "sg:city":"Pregarten",
    "sg:orig_category":"Erdarbeiten",
    "sg:phone":"+43 7236 3320",
    "sg:postcode":"4230",
    "sg:province":"Ober\u00f6sterreich",
    "wof:name":"Binder Bagger- und TransportgmbH",
    "wof:placetype":"venue"
},
  "geometry": {"coordinates":[14.5338973999,48.3524093628],"type":"Point"}
}