{
  "type": "Feature",
  "properties": {
    "iso:country":"AT",
    "sg:address":"Spazg 4",
    "sg:city":"Linz",
    "sg:classifiers":[
        {
            "category":"Professional",
            "subcategory":"Computer Services",
            "type":"Services"
        }
    ],
    "sg:phone":"+43 4373 2736423",
    "sg:postcode":"4040",
    "sg:province":"Ober\u00f6sterreich",
    "sg:tags":[
        "software"
    ],
    "wof:name":"BOI Beratungsunternehmen f Operations Research u Informationsverarbeitung GesmbH",
    "wof:placetype":"venue"
},
  "geometry": {"coordinates":[14.2730417252,48.3102493286],"type":"Point"}
}