{
  "type": "Feature",
  "properties": {
    "addr:full":"Langgasse 1 Hartberg Steiermark 8230",
    "addr:housenumber":"1",
    "addr:postcode":"8230",
    "addr:street":"Langgasse",
    "iso:country":"AT",
    "sg:address":"Langgasse 1",
    "sg:city":"Hartberg",
    "sg:classifiers":[
        {
            "category":"Government",
            "subcategory":"Post Office",
            "type":"Public Place"
        }
    ],
    "sg:phone":"+43 3332 615110",
    "sg:postcode":"8230",
    "sg:province":"Steiermark",
    "sg:tags":[
        "protective",
        "clothing",
        "special"
    ],
    "sg:website":"awa-handel.at",
    "wof:name":"AWA Fiedler KG",
    "wof:placetype":"venue"
},
  "geometry": {"coordinates":[15.966709137,47.2672386169],"type":"Point"}
}