{
  "type": "Feature",
  "properties": {
    "addr:full":"Alois Kaltenbruner-S 27a Gmunden Ober\u00f6sterreich 4810",
    "addr:housenumber":"27a",
    "addr:postcode":"4810",
    "addr:street":"Oberoesterreich",
    "iso:country":"AT",
    "sg:address":"Alois Kaltenbruner-S 27a",
    "sg:city":"Gmunden",
    "sg:orig_category":"Steinmetzbetriebe",
    "sg:phone":"+43 761271404",
    "sg:postcode":"4810",
    "sg:province":"Ober\u00f6sterreich",
    "sg:website":"natursteine-huemer.at",
    "wof:name":"Huemer Wolfgang - Steinmetzmeister",
    "wof:placetype":"venue"
},
  "geometry": {"coordinates":[13.7870769501,47.9210243225],"type":"Point"}
}