{
  "type": "Feature",
  "properties": {
    "iso:country":"AT",
    "sg:address":"Haasg 6",
    "sg:city":"Wolkersdorf im Weinviertel",
    "sg:orig_category":"Digitaldruck",
    "sg:phone":"+43 2245 4828",
    "sg:postcode":"2120",
    "sg:province":"Nieder\u00f6sterreich",
    "wof:name":"Fabikan & Partner GmbH",
    "wof:placetype":"venue"
},
  "geometry": {"coordinates":[16.5247249603,48.368560791],"type":"Point"}
}