{
  "type": "Feature",
  "properties": {
    "addr:full":"Haasg 6 Wolkersdorf im Weinviertel Nieder\u00f6sterreich 2120",
    "addr:housenumber":"6",
    "addr:postcode":"2120",
    "addr:street":"Haasg",
    "iso:country":"AT",
    "sg:address":"Haasg 6",
    "sg:city":"Wolkersdorf im Weinviertel",
    "sg:orig_category":"Digitaldruck",
    "sg:phone":"+43 2245 4828",
    "sg:postcode":"2120",
    "sg:province":"Nieder\u00f6sterreich",
    "wof:name":"Fabikan & Partner GmbH",
    "wof:placetype":"venue"
},
  "geometry": {"coordinates":[16.5247249603,48.368560791],"type":"Point"}
}