{
  "type": "Feature",
  "properties": {
    "addr:full":"Walterstr 2 Untertullnerbach Nieder\u00f6sterreich 3011",
    "addr:housenumber":"2",
    "addr:postcode":"3011",
    "addr:street":"Walterstr",
    "iso:country":"AT",
    "sg:address":"Walterstr 2",
    "sg:city":"Untertullnerbach",
    "sg:orig_category":"Spielwaren U Spiele",
    "sg:phone":"+43 4322 3353156",
    "sg:postcode":"3011",
    "sg:province":"Nieder\u00f6sterreich",
    "wof:name":"Wienerwald Holzspielwaren - Herbert Walter",
    "wof:placetype":"venue"
},
  "geometry": {"coordinates":[16.0971660614,48.2024688721],"type":"Point"}
}