{
  "type": "Feature",
  "properties": {
    "iso:country":"AT",
    "sg:address":"Nr 30",
    "sg:city":"Anthering",
    "sg:orig_category":"Blumeneinzelhandel",
    "sg:phone":"+43 6223 2819",
    "sg:postcode":"5102",
    "sg:province":"Salzburg",
    "wof:name":"Blumen Sch\u00f6rghofer",
    "wof:placetype":"venue"
},
  "geometry": {"coordinates":[12.9971446991,47.8926010132],"type":"Point"}
}