{
  "type": "Feature",
  "properties": {
    "addr:full":"Lieferinger Hauptstrasse 102 Salzburg Salzburg 5020",
    "addr:housenumber":"102",
    "addr:postcode":"5020",
    "addr:street":"Lieferinger Hauptstrasse;Salzburg",
    "iso:country":"AT",
    "sg:address":"Lieferinger Hauptstrasse 102",
    "sg:city":"Salzburg",
    "sg:orig_category":"Non-Classified Establishments",
    "sg:phone":"+43 662 433625",
    "sg:postcode":"5020",
    "sg:province":"Salzburg",
    "sg:website":"dorfmetzgerei-karl.at",
    "wof:name":"Helmut Karl",
    "wof:placetype":"venue"
},
  "geometry": {"coordinates":[13.0093851089,47.8234214783],"type":"Point"}
}