{
  "type": "Feature",
  "properties": {
    "addr:full":"Tsch\u00f6raner Weg 29 Bodensdorf K\u00e4rnten 9551",
    "addr:housenumber":"29",
    "addr:postcode":"9551",
    "addr:street":"Tschoeraner Weg;Kaernten",
    "iso:country":"AT",
    "sg:address":"Tsch\u00f6raner Weg 29",
    "sg:city":"Bodensdorf",
    "sg:orig_category":"Appartements / Ferienwohnungen",
    "sg:phone":"+43 4342 432956",
    "sg:postcode":"9551",
    "sg:province":"K\u00e4rnten",
    "wof:name":"Opriessnig Erwin",
    "wof:placetype":"venue"
},
  "geometry": {"coordinates":[13.9635829926,46.6833114624],"type":"Point"}
}