{
  "type": "Feature",
  "properties": {
    "iso:country":"AT",
    "sg:address":"Linzer Strasse 42",
    "sg:city":"Steyregg",
    "sg:orig_category":"Non-Classified Establishments",
    "sg:phone":"+43 732 640034",
    "sg:postcode":"4221",
    "sg:province":"Ober\u00f6sterreich",
    "sg:website":"wegschaider.fleischer.at",
    "wof:name":"Adolf Wegschaider - Der Fleischermeister GmbH & Co KG",
    "wof:placetype":"venue"
},
  "geometry": {"coordinates":[14.3594837189,48.2838668823],"type":"Point"}
}