{
  "type": "Feature",
  "properties": {
    "addr:full":"Dorf 55a Elbigenalp Tirol 6652",
    "addr:housenumber":"55a",
    "addr:postcode":"6652",
    "addr:street":"Dorf;Tirol",
    "iso:country":"AT",
    "sg:address":"Dorf 55a",
    "sg:city":"Elbigenalp",
    "sg:orig_category":"Gemeinden",
    "sg:phone":"+43 5634 6210",
    "sg:postcode":"6652",
    "sg:province":"Tirol",
    "wof:name":"Gemeindeamt Elbigenalp",
    "wof:placetype":"venue"
},
  "geometry": {"coordinates":[10.4392967224,47.2927627563],"type":"Point"}
}