{
  "type": "Feature",
  "properties": {
    "addr:full":"Anzing 44 St. Martin im M\u00fchlkreis Ober\u00f6sterreich 4113",
    "addr:housenumber":"44",
    "addr:postcode":"4113",
    "addr:street":"Anzing",
    "iso:country":"AT",
    "sg:address":"Anzing 44",
    "sg:city":"St. Martin im M\u00fchlkreis",
    "sg:orig_category":"Freizeitangebote U -Einrichtungen",
    "sg:phone":"+43 4372 322533",
    "sg:postcode":"4113",
    "sg:province":"Ober\u00f6sterreich",
    "wof:name":"Martinstube - Alfred Ulreich",
    "wof:placetype":"venue"
},
  "geometry": {"coordinates":[14.0710344315,48.4015235901],"type":"Point"}
}