{
  "type": "Feature",
  "properties": {
    "addr:full":"Bahnhofstr 1 Steyr Ober\u00f6sterreich 4400",
    "addr:housenumber":"1",
    "addr:postcode":"4400",
    "addr:street":"Bahnhofstr;Oberoesterreich",
    "iso:country":"AT",
    "sg:address":"Bahnhofstr 1",
    "sg:city":"Steyr",
    "sg:orig_category":"Ingenieurkonsulenten / Zivilingenieure",
    "sg:phone":"+43 7252 421250",
    "sg:postcode":"4400",
    "sg:province":"Ober\u00f6sterreich",
    "wof:name":"Ingenieurb\u00fcro f Kraftfahrzeugtechnik Kordon Hubert Dipl-Ing Dr",
    "wof:placetype":"venue"
},
  "geometry": {"coordinates":[14.4230184555,48.0415763855],"type":"Point"}
}