{
  "type": "Feature",
  "properties": {
    "addr:full":"Jochberger Str 98 Kitzb\u00fchel Tirol 6370",
    "addr:postcode":"6370",
    "addr:street":"Str 98 Kitzbuehel Tirol",
    "iso:country":"AT",
    "sg:address":"Jochberger Str 98",
    "sg:city":"Kitzb\u00fchel",
    "sg:orig_category":"Friseure U Frisiersalons",
    "sg:phone":"+43 5356 65825",
    "sg:postcode":"6370",
    "sg:province":"Tirol",
    "wof:name":"Sartori Helga",
    "wof:placetype":"venue"
},
  "geometry": {"coordinates":[12.4031295776,47.4368743896],"type":"Point"}
}