{
  "type": "Feature",
  "properties": {
    "addr:full":"Th\u00f6rleweg 38 Ehrwald Tirol 6632",
    "addr:housenumber":"38",
    "addr:postcode":"6632",
    "addr:street":"Thoerleweg;Tirol",
    "iso:country":"AT",
    "sg:address":"Th\u00f6rleweg 38",
    "sg:city":"Ehrwald",
    "sg:orig_category":"Pensionen / Privatzimmer",
    "sg:phone":"+43 5673 2674",
    "sg:postcode":"6632",
    "sg:province":"Tirol",
    "wof:name":"Haus Marianne",
    "wof:placetype":"venue"
},
  "geometry": {"coordinates":[10.921298027,47.4086341858],"type":"Point"}
}