{
  "type": "Feature",
  "properties": {
    "addr:full":"Die Wimmerstr. 10a Seekirchen am Wallersee Salzburg 5201",
    "addr:housenumber":"10a",
    "addr:postcode":"5201",
    "addr:street":"Salzburg",
    "iso:country":"AT",
    "sg:address":"Die Wimmerstr. 10a",
    "sg:city":"Seekirchen am Wallersee",
    "sg:classifiers":[
        {
            "category":"Professional",
            "subcategory":"Engineering",
            "type":"Services"
        }
    ],
    "sg:phone":"+43 4362 1230100",
    "sg:postcode":"5201",
    "sg:province":"Salzburg",
    "sg:tags":[
        "machine",
        "-",
        "mechanical"
    ],
    "wof:name":"GASTRONOMIESYSTEME ROIDER RICHARD",
    "wof:placetype":"venue"
},
  "geometry": {"coordinates":[13.1259298325,47.8936500549],"type":"Point"}
}