{
  "type": "Feature",
  "properties": {
    "addr:full":"Piccolominig 4 Linz Ober\u00f6sterreich 4030",
    "addr:housenumber":"4",
    "addr:postcode":"4030",
    "addr:street":"Piccolominig",
    "iso:country":"AT",
    "sg:address":"Piccolominig 4",
    "sg:city":"Linz",
    "sg:orig_category":"Werbeagenturen",
    "sg:phone":"+43 676 3609818",
    "sg:postcode":"4030",
    "sg:province":"Ober\u00f6sterreich",
    "wof:name":"Kommunikation's Agentur Scherzinger",
    "wof:placetype":"venue"
},
  "geometry": {"coordinates":[14.3279409409,48.2441444397],"type":"Point"}
}