{
  "type": "Feature",
  "properties": {
    "addr:full":"Pierlstr 35 Klagenfurt K\u00e4rnten 9020",
    "addr:housenumber":"35",
    "addr:postcode":"9020",
    "addr:street":"Pierlstr;Kaernten",
    "iso:country":"AT",
    "sg:address":"Pierlstr 35",
    "sg:city":"Klagenfurt",
    "sg:orig_category":"Baumeister",
    "sg:phone":"+43 463 513895",
    "sg:postcode":"9020",
    "sg:province":"K\u00e4rnten",
    "wof:name":"Sorz Otmar Ing",
    "wof:placetype":"venue"
},
  "geometry": {"coordinates":[14.2931175232,46.6267433167],"type":"Point"}
}