{
  "type": "Feature",
  "properties": {
    "addr:full":"Bahnstr 3a Pamhagen Burgenland 7152",
    "addr:housenumber":"3a",
    "addr:postcode":"7152",
    "addr:street":"Bahnstr",
    "iso:country":"AT",
    "sg:address":"Bahnstr 3a",
    "sg:city":"Pamhagen",
    "sg:orig_category":"Genossenschaften",
    "sg:phone":"+43 2174 2189",
    "sg:postcode":"7152",
    "sg:province":"Burgenland",
    "wof:name":"Winzerkeller Seewinkel regGenmbH",
    "wof:placetype":"venue"
},
  "geometry": {"coordinates":[16.9038829803,47.701461792],"type":"Point"}
}