{
  "type": "Feature",
  "properties": {
    "iso:country":"AT",
    "sg:address":"Hollergasse 8",
    "sg:city":"Wien",
    "sg:classifiers":[
        {
            "category":"Building & Trades",
            "subcategory":"Locksmith",
            "type":"Services"
        }
    ],
    "sg:phone":"+43 1 8949911",
    "sg:postcode":"1150",
    "sg:province":"Wien",
    "sg:tags":[
        "shop",
        "assembly"
    ],
    "wof:name":"Wilhelm Schafhauser",
    "wof:placetype":"venue"
},
  "geometry": {"coordinates":[16.3253173828,48.185382843],"type":"Point"}
}