{
  "type": "Feature",
  "properties": {
    "addr:full":"Gmeineckweg 2 Seeboden K\u00e4rnten 9871",
    "addr:housenumber":"2",
    "addr:postcode":"9871",
    "addr:street":"Gmeineckweg;Kaernten",
    "iso:country":"AT",
    "sg:address":"Gmeineckweg 2",
    "sg:city":"Seeboden",
    "sg:orig_category":"Pensionen / Privatzimmer",
    "sg:phone":"+43 4762 81493",
    "sg:postcode":"9871",
    "sg:province":"K\u00e4rnten",
    "wof:name":"Oberlerchner Franz",
    "wof:placetype":"venue"
},
  "geometry": {"coordinates":[13.5352621078,46.8228187561],"type":"Point"}
}