{
  "type": "Feature",
  "properties": {
    "addr:full":"Nockalmblick 3 Feldkirchen in K\u00e4rnten K\u00e4rnten 9560",
    "addr:housenumber":"3",
    "addr:postcode":"9560",
    "addr:street":"Nockalmblick;Kaernten",
    "iso:country":"AT",
    "sg:address":"Nockalmblick 3",
    "sg:city":"Feldkirchen in K\u00e4rnten",
    "sg:orig_category":"Tonstudios",
    "sg:phone":"+43 4367 69311422",
    "sg:postcode":"9560",
    "sg:province":"K\u00e4rnten",
    "wof:name":"chorstudio ebner",
    "wof:placetype":"venue"
},
  "geometry": {"coordinates":[14.0997247696,46.7166519165],"type":"Point"}
}