{
  "type": "Feature",
  "properties": {
    "addr:full":"Lustenauer Strasse 74 Dornbirn Vorarlberg 6850",
    "addr:housenumber":"74",
    "addr:postcode":"6850",
    "addr:street":"Lustenauer Strasse",
    "iso:country":"AT",
    "sg:address":"Lustenauer Strasse 74",
    "sg:city":"Dornbirn",
    "sg:classifiers":[
        {
            "category":"Home & Garden",
            "subcategory":"Building Materials",
            "type":"Retail Goods"
        }
    ],
    "sg:phone":"+43 5572 233390",
    "sg:postcode":"6850",
    "sg:province":"Vorarlberg",
    "sg:tags":[
        "window",
        "cellar"
    ],
    "sg:website":"vol.at/rusch",
    "wof:name":"M. u. E. Rusch Ges.m.b.H.",
    "wof:placetype":"venue"
},
  "geometry": {"coordinates":[9.7173318863,47.4108848572],"type":"Point"}
}