{
  "type": "Feature",
  "properties": {
    "addr:full":"Breitenfurter Str 201 Wien Wien 1230",
    "addr:housenumber":"201",
    "addr:postcode":"1230",
    "addr:street":"Str",
    "iso:country":"AT",
    "sg:address":"Breitenfurter Str 201",
    "sg:city":"Wien",
    "sg:orig_category":"Autospenglereien",
    "sg:phone":"+43 1 8042156",
    "sg:postcode":"1230",
    "sg:province":"Wien",
    "wof:name":"Auto-Grath",
    "wof:placetype":"venue"
},
  "geometry": {"coordinates":[16.307138443,48.1582565308],"type":"Point"}
}