{
  "type": "Feature",
  "properties": {
    "iso:country":"AT",
    "sg:address":"Markt 87",
    "sg:city":"T\u00fcrnitz",
    "sg:orig_category":"Volksschulen",
    "sg:phone":"+43 2769 8232",
    "sg:postcode":"3184",
    "sg:province":"Nieder\u00f6sterreich",
    "wof:name":"Volksschule",
    "wof:placetype":"venue"
},
  "geometry": {"coordinates":[-76.4168395996,37.452419281],"type":"Point"}
}