{
  "type": "Feature",
  "properties": {
    "addr:full":"Wallpachg 10 Hall in Tirol Tirol 6060",
    "addr:housenumber":"10",
    "addr:postcode":"6060",
    "addr:street":"Wallpachg;Tirol",
    "iso:country":"AT",
    "sg:address":"Wallpachg 10",
    "sg:city":"Hall in Tirol",
    "sg:orig_category":"Fleischhauereien",
    "sg:phone":"+43 5223 542940",
    "sg:postcode":"6060",
    "sg:province":"Tirol",
    "wof:name":"H\u00f6rtnagl Andr\u00e4 Produktion und Handel GmbH",
    "wof:placetype":"venue"
},
  "geometry": {"coordinates":[11.5081453323,47.282875061],"type":"Point"}
}