{
  "type": "Feature",
  "properties": {
    "addr:full":"Schr\u00f6tterg 50/2/20 Wien Wien 1100",
    "addr:housenumber":"50 / 2 / 20",
    "addr:postcode":"1100",
    "addr:street":"Schroetterg",
    "iso:country":"AT",
    "sg:address":"Schr\u00f6tterg 50/2/20",
    "sg:city":"Wien",
    "sg:orig_category":"Webdesign",
    "sg:phone":"+43 1 6048977",
    "sg:postcode":"1100",
    "sg:province":"Wien",
    "sg:website":"fullscreen.at",
    "wof:name":"fullscreen cOMPUTERgRAFIK+mEDIENdESIGN Sabine Petrzelka",
    "wof:placetype":"venue"
},
  "geometry": {"coordinates":[16.3744049072,48.1782684326],"type":"Point"}
}