{
  "type": "Feature",
  "properties": {
    "addr:full":"Neuhauserweg 14 Pasching Ober\u00f6sterreich 4061",
    "addr:housenumber":"14",
    "addr:postcode":"4061",
    "addr:street":"Neuhauserweg;Oberoesterreich",
    "iso:country":"AT",
    "sg:address":"Neuhauserweg 14",
    "sg:city":"Pasching",
    "sg:orig_category":"Medizintechnik",
    "sg:phone":"+43 7229 714150",
    "sg:postcode":"4061",
    "sg:province":"Ober\u00f6sterreich",
    "wof:name":"Clinimed medizinische Ger\u00e4te GesmbH",
    "wof:placetype":"venue"
},
  "geometry": {"coordinates":[14.2307310104,48.2361450195],"type":"Point"}
}