{
  "type": "Feature",
  "properties": {
    "addr:full":"Hauptstr 11 Pinkafeld Burgenland 7423",
    "addr:housenumber":"11",
    "addr:postcode":"7423",
    "addr:street":"Hauptstr",
    "iso:country":"AT",
    "sg:address":"Hauptstr 11",
    "sg:city":"Pinkafeld",
    "sg:orig_category":"Waren Aller Art",
    "sg:phone":"+43 4333 5743250",
    "sg:postcode":"7423",
    "sg:province":"Burgenland",
    "wof:name":"Weltladen",
    "wof:placetype":"venue"
},
  "geometry": {"coordinates":[16.12317276,47.3697509766],"type":"Point"}
}