{
  "type": "Feature",
  "properties": {
    "addr:full":"Rauhholzstr 8 Hard Vorarlberg 6971",
    "addr:housenumber":"8",
    "addr:postcode":"6971",
    "addr:street":"Rauhholzstr",
    "iso:country":"AT",
    "sg:address":"Rauhholzstr 8",
    "sg:city":"Hard",
    "sg:orig_category":"Plachen U Planen",
    "sg:phone":"+43 5574 83405",
    "sg:postcode":"6971",
    "sg:province":"Vorarlberg",
    "wof:name":"Reissfest Inh Ayaz Saldiray",
    "wof:placetype":"venue"
},
  "geometry": {"coordinates":[9.6990213394,47.4897918701],"type":"Point"}
}