{
  "type": "Feature",
  "properties": {
    "addr:full":"Waxenbergstrasse 10 St. Veit im M\u00fchlkreis Ober\u00f6sterreich 4173",
    "addr:housenumber":"10",
    "addr:postcode":"4173",
    "addr:street":"Waxenbergstrasse",
    "iso:country":"AT",
    "sg:address":"Waxenbergstrasse 10",
    "sg:city":"St. Veit im M\u00fchlkreis",
    "sg:orig_category":"Furniture, General",
    "sg:phone":"+43 7217 6580",
    "sg:postcode":"4173",
    "sg:province":"Ober\u00f6sterreich",
    "sg:website":"tischlerei-mayrhofer.at",
    "wof:name":"Josef Mayrhofer",
    "wof:placetype":"venue"
},
  "geometry": {"coordinates":[14.1647911072,48.4699058533],"type":"Point"}
}