{
  "type": "Feature",
  "properties": {
    "addr:full":"Grazer Str 3 Kapfenberg Steiermark 8605",
    "addr:housenumber":"3",
    "addr:postcode":"8605",
    "addr:street":"Str",
    "iso:country":"AT",
    "sg:address":"Grazer Str 3",
    "sg:city":"Kapfenberg",
    "sg:orig_category":"Beratungsstellen",
    "sg:phone":"+43 3862 21500",
    "sg:postcode":"8605",
    "sg:province":"Steiermark",
    "wof:name":"Volkshilfe Kapfenberg",
    "wof:placetype":"venue"
},
  "geometry": {"coordinates":[15.2891159058,47.4389839172],"type":"Point"}
}