{
  "type": "Feature",
  "properties": {
    "addr:full":"Ramingtalstr 1 Behamberg Nieder\u00f6sterreich 4441",
    "addr:housenumber":"1",
    "addr:postcode":"4441",
    "addr:street":"Ramingtalstr;Behamberg Niederoesterreich",
    "iso:country":"AT",
    "sg:address":"Ramingtalstr 1",
    "sg:city":"Behamberg",
    "sg:orig_category":"Pensionen / Privatzimmer",
    "sg:phone":"+43 4372 5280992",
    "sg:postcode":"4441",
    "sg:province":"Nieder\u00f6sterreich",
    "wof:name":"Urlaub am Bauernhof - Merkinger Johann jun",
    "wof:placetype":"venue"
},
  "geometry": {"coordinates":[14.4581699371,48.0429916382],"type":"Point"}
}