{
  "type": "Feature",
  "properties": {
    "addr:full":"Industriestr. 2  Marz Burgenland 7221",
    "addr:housenumber":"2",
    "addr:postcode":"7221",
    "addr:street":"Industriestr.",
    "iso:country":"AT",
    "sg:address":"Industriestr. 2 ",
    "sg:city":"Marz",
    "sg:classifiers":[
        {
            "category":"Shopping",
            "subcategory":"Clothing, Apparel, & Fashions",
            "type":"Retail Goods"
        }
    ],
    "sg:phone":"+43 4326 26624050",
    "sg:postcode":"7221",
    "sg:province":"Burgenland",
    "sg:tags":[
        "clothing",
        "accessory"
    ],
    "wof:name":"YKK AUSTRIA GESMBH",
    "wof:placetype":"venue"
},
  "geometry": {"coordinates":[16.4114952087,47.7252235413],"type":"Point"}
}