{
  "type": "Feature",
  "properties": {
    "iso:country":"AT",
    "sg:address":"Biberstrasse 11/8",
    "sg:city":"Wien",
    "sg:classifiers":[
        {
            "category":"Banks & Credit Unions",
            "subcategory":"Investment Brokerage",
            "type":"Services"
        }
    ],
    "sg:phone":"+43 1 516710",
    "sg:postcode":"1010",
    "sg:province":"Wien",
    "sg:tags":[
        "ocean-going",
        "vessel"
    ],
    "sg:website":"alsphere.at",
    "wof:name":"Alsphere Engineering Schiffbau & Architektur GmbH",
    "wof:placetype":"venue"
},
  "geometry": {"coordinates":[16.3808116913,48.2091407776],"type":"Point"}
}