{
  "type": "Feature",
  "properties": {
    "iso:country":"AT",
    "sg:address":"Josefspl 16",
    "sg:city":"Poysdorf",
    "sg:orig_category":"Damenmoden",
    "sg:phone":"+43 2552 29312",
    "sg:postcode":"2170",
    "sg:province":"Nieder\u00f6sterreich",
    "wof:name":"Kaufstrasse Helmut Pemsel GesmbH",
    "wof:placetype":"venue"
},
  "geometry": {"coordinates":[16.6295967102,48.6690788269],"type":"Point"}
}