{
  "type": "Feature",
  "properties": {
    "addr:full":"Feldweg 8 Wies Steiermark 8551",
    "addr:housenumber":"8",
    "addr:postcode":"8551",
    "addr:street":"Feldweg",
    "iso:country":"AT",
    "sg:address":"Feldweg 8",
    "sg:city":"Wies",
    "sg:orig_category":"Steinmetzbetriebe",
    "sg:phone":"+43 3465 23280",
    "sg:postcode":"8551",
    "sg:province":"Steiermark",
    "wof:name":"Hutter-Schwab Ilse",
    "wof:placetype":"venue"
},
  "geometry": {"coordinates":[15.2743558884,46.7178001404],"type":"Point"}
}