{
  "type": "Feature",
  "properties": {
    "iso:country":"AT",
    "sg:address":"Rasumofskyg 10",
    "sg:city":"Wien",
    "sg:orig_category":"Steuerberatung",
    "sg:phone":"+43 1 7144216",
    "sg:postcode":"1030",
    "sg:province":"Wien",
    "sg:website":"www.res-wth.at",
    "wof:name":"RES WirtschaftstreuhandgesmbH",
    "wof:placetype":"venue"
},
  "geometry": {"coordinates":[16.3938388824,48.2056465149],"type":"Point"}
}