{
  "type": "Feature",
  "properties": {
    "addr:full":"Feldg 7 Bruck an der Leitha Nieder\u00f6sterreich 2460",
    "addr:housenumber":"7",
    "addr:postcode":"2460",
    "addr:street":"Feldg",
    "iso:country":"AT",
    "sg:address":"Feldg 7",
    "sg:city":"Bruck an der Leitha",
    "sg:orig_category":"Stillberatung",
    "sg:phone":"+43 2162 66205",
    "sg:postcode":"2460",
    "sg:province":"Nieder\u00f6sterreich",
    "wof:name":"Stillberatung - La Leche Liga N\u00d6 - Maria Windholz",
    "wof:placetype":"venue"
},
  "geometry": {"coordinates":[16.7784805298,48.0248832703],"type":"Point"}
}