{
  "type": "Feature",
  "properties": {
    "iso:country":"AT",
    "sg:address":"Modecenterstrasse 14",
    "sg:city":"Wien",
    "sg:classifiers":[
        {
            "category":"Building & Trades",
            "subcategory":"Plumbing",
            "type":"Services"
        }
    ],
    "sg:phone":"+43 1 2034532",
    "sg:postcode":"1030",
    "sg:province":"Wien",
    "sg:tags":[
        "flow-meters"
    ],
    "sg:website":"krohne.at",
    "wof:name":"Krohne Ges.m.b.H.",
    "wof:placetype":"venue"
},
  "geometry": {"coordinates":[16.4151210785,48.1857070923],"type":"Point"}
}