{
  "type": "Feature",
  "properties": {
    "addr:full":"Dieselstrasse 7 Wels Ober\u00f6sterreich 4600",
    "addr:housenumber":"7",
    "addr:postcode":"4600",
    "addr:street":"Dieselstrasse;Oberoesterreich",
    "iso:country":"AT",
    "sg:address":"Dieselstrasse 7",
    "sg:city":"Wels",
    "sg:orig_category":"Skinning Machines",
    "sg:phone":"+43 7242 677030",
    "sg:postcode":"4600",
    "sg:province":"Ober\u00f6sterreich",
    "sg:website":"banss.at",
    "wof:name":"BANSS Maschinenfabrik Ges.m.b.H.",
    "wof:placetype":"venue"
},
  "geometry": {"coordinates":[14.0485019684,48.1581878662],"type":"Point"}
}