{
  "type": "Feature",
  "properties": {
    "addr:full":"Gradnerstr 34c Puntigam Steiermark 8055",
    "addr:housenumber":"34c",
    "addr:postcode":"8055",
    "addr:street":"Gradnerstr",
    "iso:country":"AT",
    "sg:address":"Gradnerstr 34c",
    "sg:city":"Puntigam",
    "sg:orig_category":"Werbeagenturen",
    "sg:phone":"+43 316 398950",
    "sg:postcode":"8055",
    "sg:province":"Steiermark",
    "wof:name":"come consulting",
    "wof:placetype":"venue"
},
  "geometry": {"coordinates":[15.426322937,47.0228042603],"type":"Point"}
}