{
  "type": "Feature",
  "properties": {
    "addr:full":"Sterneckstr 31-33 Salzburg Salzburg 5020",
    "addr:postcode":"31-33;5020",
    "addr:street":"Salzburg",
    "iso:country":"AT",
    "sg:address":"Sterneckstr 31-33",
    "sg:city":"Salzburg",
    "sg:classifiers":[
        {
            "category":"Restaurant",
            "type":"Food & Drink"
        }
    ],
    "sg:phone":"+43 662 873816",
    "sg:postcode":"5020",
    "sg:province":"Salzburg",
    "wof:name":"Tran GesmbH",
    "wof:placetype":"venue"
},
  "geometry": {"coordinates":[13.055565834,47.8090400696],"type":"Point"}
}