{
  "type": "Feature",
  "properties": {
    "addr:full":"Dietersdorf 64 Wundschuh Steiermark 8142",
    "addr:housenumber":"64",
    "addr:postcode":"8142",
    "addr:street":"Dietersdorf",
    "iso:country":"AT",
    "sg:address":"Dietersdorf 64",
    "sg:city":"Wundschuh",
    "sg:classifiers":[
        {
            "category":"Building & Trades",
            "subcategory":"Electrical",
            "type":"Services"
        }
    ],
    "sg:phone":"+43 3136 52661",
    "sg:postcode":"8142",
    "sg:province":"Steiermark",
    "sg:tags":[
        "shopfitting",
        "work",
        "installation"
    ],
    "wof:name":"W. Paulus GesmbH",
    "wof:placetype":"venue"
},
  "geometry": {"coordinates":[15.4498796463,46.9254493713],"type":"Point"}
}