{
  "type": "Feature",
  "properties": {
    "addr:full":"Marktstr 6 Neustadtl Nieder\u00f6sterreich 3323",
    "addr:housenumber":"6",
    "addr:postcode":"3323",
    "addr:street":"Marktstr",
    "iso:country":"AT",
    "sg:address":"Marktstr 6",
    "sg:city":"Neustadtl",
    "sg:orig_category":"Volksschulen",
    "sg:phone":"+43 7471 2217",
    "sg:postcode":"3323",
    "sg:province":"Nieder\u00f6sterreich",
    "wof:name":"Volksschule",
    "wof:placetype":"venue"
},
  "geometry": {"coordinates":[20.3330097198,47.9864997864],"type":"Point"}
}