{
  "type": "Feature",
  "properties": {
    "addr:full":"Leopoldstr 4 Innsbruck Tirol 6020",
    "addr:housenumber":"4",
    "addr:postcode":"6020",
    "addr:street":"Leopoldstr;Tirol",
    "iso:country":"AT",
    "sg:address":"Leopoldstr 4",
    "sg:city":"Innsbruck",
    "sg:orig_category":"Handelsagenturen",
    "sg:phone":"+43 512 344810",
    "sg:postcode":"6020",
    "sg:province":"Tirol",
    "wof:name":"Kohl Trend Agent",
    "wof:placetype":"venue"
},
  "geometry": {"coordinates":[11.3947048187,47.2622070312],"type":"Point"}
}