{
  "type": "Feature",
  "properties": {
    "addr:full":"Gabelsbergerstr 11 Salzburg Salzburg 5020",
    "addr:housenumber":"11",
    "addr:postcode":"5020",
    "addr:street":"Gabelsbergerstr;Salzburg",
    "iso:country":"AT",
    "sg:address":"Gabelsbergerstr 11",
    "sg:city":"Salzburg",
    "sg:orig_category":"Diskothekenanlagen U -Vermietung",
    "sg:phone":"+43 4366 2884545",
    "sg:postcode":"5020",
    "sg:province":"Salzburg",
    "sg:website":"astrolite.at",
    "wof:name":"Astrolite Eric Geiger",
    "wof:placetype":"venue"
},
  "geometry": {"coordinates":[13.0479640961,47.8094406128],"type":"Point"}
}