{
  "type": "Feature",
  "properties": {
    "addr:full":"Kirchenpl 5 Sierning Ober\u00f6sterreich 4522",
    "addr:housenumber":"5",
    "addr:postcode":"4522",
    "addr:street":"Kirchenpl",
    "iso:country":"AT",
    "sg:address":"Kirchenpl 5",
    "sg:city":"Sierning",
    "sg:orig_category":"Textilreinigung",
    "sg:phone":"+43 7259 2037",
    "sg:postcode":"4522",
    "sg:province":"Ober\u00f6sterreich",
    "wof:name":"W\u00e4chter Elisabeth",
    "wof:placetype":"venue"
},
  "geometry": {"coordinates":[14.3100671768,48.0438919067],"type":"Point"}
}