{
  "type": "Feature",
  "properties": {
    "addr:full":"Lagerg 82 Graz Steiermark 8020",
    "addr:housenumber":"82",
    "addr:postcode":"8020",
    "addr:street":"Lagerg",
    "iso:country":"AT",
    "sg:address":"Lagerg 82",
    "sg:city":"Graz",
    "sg:orig_category":"Fu\u00c3\u0178pflege U Fu\u00c3\u0178pflegesalons",
    "sg:phone":"+43 316 710863",
    "sg:postcode":"8020",
    "sg:province":"Steiermark",
    "wof:name":"Prutsch Ursula",
    "wof:placetype":"venue"
},
  "geometry": {"coordinates":[15.4329919815,47.0598373413],"type":"Point"}
}