{
  "type": "Feature",
  "properties": {
    "addr:full":"Karmeliterpl 2 Graz Steiermark 8010",
    "addr:housenumber":"2",
    "addr:postcode":"8010",
    "addr:street":"Karmeliterpl",
    "iso:country":"AT",
    "sg:address":"Karmeliterpl 2",
    "sg:city":"Graz",
    "sg:orig_category":"Beratungsstellen",
    "sg:phone":"+43 316 8772642",
    "sg:postcode":"8010",
    "sg:province":"Steiermark",
    "wof:name":"Aktion Film Stmk b Landesjugendreferat",
    "wof:placetype":"venue"
},
  "geometry": {"coordinates":[15.4406270981,47.0740127563],"type":"Point"}
}