{
  "type": "Feature",
  "properties": {
    "addr:full":"Kirchenstr 21 Ober-Grafendorf Nieder\u00f6sterreich 3200",
    "addr:housenumber":"21",
    "addr:postcode":"3200",
    "addr:street":"Kirchenstr",
    "iso:country":"AT",
    "sg:address":"Kirchenstr 21",
    "sg:city":"Ober-Grafendorf",
    "sg:orig_category":"Volksschulen",
    "sg:phone":"+43 2747 2634",
    "sg:postcode":"3200",
    "sg:province":"Nieder\u00f6sterreich",
    "wof:name":"Volksschule",
    "wof:placetype":"venue"
},
  "geometry": {"coordinates":[15.5199317932,48.1162757874],"type":"Point"}
}