{
  "type": "Feature",
  "properties": {
    "addr:full":"Preinsbacher Str 9 Amstetten Nieder\u00f6sterreich 3300",
    "addr:housenumber":"9",
    "addr:postcode":"3300",
    "addr:street":"Str;Niederoesterreich",
    "iso:country":"AT",
    "sg:address":"Preinsbacher Str 9",
    "sg:city":"Amstetten",
    "sg:orig_category":"Psychotherapie",
    "sg:phone":"+43 4369 914836325",
    "sg:postcode":"3300",
    "sg:province":"Nieder\u00f6sterreich",
    "wof:name":"Krejcar Helene",
    "wof:placetype":"venue"
},
  "geometry": {"coordinates":[14.8744697571,48.1241264343],"type":"Point"}
}