{
  "type": "Feature",
  "properties": {
    "addr:full":"Hauptstr 77/4 Linz Ober\u00f6sterreich 4040",
    "addr:housenumber":"77 / 4",
    "addr:postcode":"4040",
    "addr:street":"Hauptstr",
    "iso:country":"AT",
    "sg:address":"Hauptstr 77/4",
    "sg:city":"Linz",
    "sg:classifiers":[
        {
            "category":"Professional",
            "subcategory":"Computer Services",
            "type":"Services"
        }
    ],
    "sg:phone":"+43 732 917619",
    "sg:postcode":"4040",
    "sg:province":"Ober\u00f6sterreich",
    "sg:tags":[
        "software"
    ],
    "wof:name":"Martin Mittendorfer Philosophtware",
    "wof:placetype":"venue"
},
  "geometry": {"coordinates":[14.2805709839,48.3148956299],"type":"Point"}
}