{
  "type": "Feature",
  "properties": {
    "addr:full":"Nr 38 Thiersee Tirol 6335",
    "addr:postcode":"6335",
    "addr:street":"Nr 38;Tirol",
    "iso:country":"AT",
    "sg:address":"Nr 38",
    "sg:city":"Thiersee",
    "sg:orig_category":"Fleischhauereien",
    "sg:phone":"+43 5376 5236",
    "sg:postcode":"6335",
    "sg:province":"Tirol",
    "wof:name":"Pfluger Hans GesmbH & Co KG - EU Zerlege und Produktionsbetrieb",
    "wof:placetype":"venue"
},
  "geometry": {"coordinates":[12.1183481216,47.5942153931],"type":"Point"}
}