{
  "type": "Feature",
  "properties": {
    "addr:full":"Quellenstr 3 Bregenz Vorarlberg 6900",
    "addr:housenumber":"3",
    "addr:postcode":"6900",
    "addr:street":"Quellenstr",
    "iso:country":"AT",
    "sg:address":"Quellenstr 3",
    "sg:city":"Bregenz",
    "sg:orig_category":"Personalberatung",
    "sg:phone":"+43 5574 529100",
    "sg:postcode":"6900",
    "sg:province":"Vorarlberg",
    "wof:name":"Kriz & Partner OEG",
    "wof:placetype":"venue"
},
  "geometry": {"coordinates":[9.7357406616,47.501663208],"type":"Point"}
}