{
  "type": "Feature",
  "properties": {
    "iso:country":"AT",
    "sg:address":"Lutherpl 1",
    "sg:city":"Wien",
    "sg:orig_category":"Non-Classified Establishments",
    "sg:phone":"+43 1 59734300",
    "sg:postcode":"1060",
    "sg:province":"Wien",
    "wof:name":"Evangelische Pfarre - Gumpendorf",
    "wof:placetype":"venue"
},
  "geometry": {"coordinates":[16.3435955048,48.1907806396],"type":"Point"}
}