{
  "type": "Feature",
  "properties": {
    "addr:full":"Hauptstr 20 Tulln an der Donau Nieder\u00f6sterreich 3430",
    "addr:housenumber":"20",
    "addr:postcode":"3430",
    "addr:street":"Hauptstr",
    "iso:country":"AT",
    "sg:address":"Hauptstr 20",
    "sg:city":"Tulln an der Donau",
    "sg:orig_category":"Non-Classified Establishments",
    "sg:phone":"+43 2272 61588",
    "sg:postcode":"3430",
    "sg:province":"Nieder\u00f6sterreich",
    "wof:name":"Pfarramt",
    "wof:placetype":"venue"
},
  "geometry": {"coordinates":[16.0239925385,48.3647003174],"type":"Point"}
}