{
  "type": "Feature",
  "properties": {
    "addr:full":"Gewerbezone 3 Flaurling Tirol 6403",
    "addr:housenumber":"3",
    "addr:postcode":"6403",
    "addr:street":"Gewerbezone;Tirol",
    "iso:country":"AT",
    "sg:address":"Gewerbezone 3",
    "sg:city":"Flaurling",
    "sg:classifiers":[
        {
            "category":"Government",
            "subcategory":"Fire Station",
            "type":"Public Place"
        }
    ],
    "sg:phone":"+43 5238 86362",
    "sg:postcode":"6403",
    "sg:province":"Tirol",
    "sg:tags":[
        "alloy",
        "light",
        "aluminium",
        "processing"
    ],
    "sg:website":"waf.at",
    "wof:name":"WAF-Fassadenelemente GmbH",
    "wof:placetype":"venue"
},
  "geometry": {"coordinates":[11.1503076553,47.281337738],"type":"Point"}
}