{
  "type": "Feature",
  "properties": {
    "addr:full":"Brunnfeldweg 3 Oetz Tirol 6433",
    "addr:housenumber":"3",
    "addr:postcode":"6433",
    "addr:street":"Brunnfeldweg;Tirol",
    "iso:country":"AT",
    "sg:address":"Brunnfeldweg 3",
    "sg:city":"Oetz",
    "sg:orig_category":"Pensionen / Privatzimmer",
    "sg:phone":"+43 5252 6373",
    "sg:postcode":"6433",
    "sg:province":"Tirol",
    "wof:name":"Haus Regina",
    "wof:placetype":"venue"
},
  "geometry": {"coordinates":[10.8924303055,47.2060585022],"type":"Point"}
}