{
  "type": "Feature",
  "properties": {
    "addr:full":"Nr 18 Weitra Nieder\u00f6sterreich 3970",
    "addr:postcode":"3970",
    "addr:street":"Nr;Niederoesterreich",
    "iso:country":"AT",
    "sg:address":"Nr 18",
    "sg:city":"Weitra",
    "sg:orig_category":"Feng-Shui",
    "sg:phone":"+43 4328 5675188",
    "sg:postcode":"3970",
    "sg:province":"Nieder\u00f6sterreich",
    "wof:name":"Feng Shui Praxis f gesundes Bauen Wohnen u Arbeiten - Gerald Kaufmann",
    "wof:placetype":"venue"
},
  "geometry": {"coordinates":[14.8928060532,48.7005844116],"type":"Point"}
}