{
  "type": "Feature",
  "properties": {
    "addr:full":"Wiener Str 57 M\u00fcrzzuschlag Steiermark 8680",
    "addr:postcode":"8680",
    "addr:street":"57",
    "iso:country":"AT",
    "sg:address":"Wiener Str 57",
    "sg:city":"M\u00fcrzzuschlag",
    "sg:classifiers":[
        {
            "category":"Restaurant",
            "type":"Food & Drink"
        }
    ],
    "sg:phone":"+43 4366 45748362",
    "sg:postcode":"8680",
    "sg:province":"Steiermark",
    "wof:name":"Kulesa Claudia",
    "wof:placetype":"venue"
},
  "geometry": {"coordinates":[16.3542709351,48.159198761],"type":"Point"}
}