{
  "type": "Feature",
  "properties": {
    "addr:full":"Felix-Ennemoser-Weg 3 Elsbethen-Glasenbach Salzburg 5061",
    "addr:housenumber":"3",
    "addr:postcode":"5061",
    "addr:street":"Felix-Ennemoser-Weg;Salzburg",
    "iso:country":"AT",
    "sg:address":"Felix-Ennemoser-Weg 3",
    "sg:city":"Elsbethen-Glasenbach",
    "sg:orig_category":"Holzgro\u00c3\u0178handel",
    "sg:phone":"+43 662 625837",
    "sg:postcode":"5061",
    "sg:province":"Salzburg",
    "wof:name":"G\u00f6tz Carl GmbH - Platten, Furniere, T\u00fcren, Holz",
    "wof:placetype":"venue"
},
  "geometry": {"coordinates":[13.0805807114,47.7641563416],"type":"Point"}
}