{
  "type": "Feature",
  "properties": {
    "iso:country":"AT",
    "sg:address":"Am Bachanger 62",
    "sg:city":"Piesendorf",
    "sg:orig_category":"Friseure U Frisiersalons",
    "sg:phone":"+43 6549 20174",
    "sg:postcode":"5721",
    "sg:province":"Salzburg",
    "wof:name":"Haarwerkst\u00e4tte Martina Wallner",
    "wof:placetype":"venue"
},
  "geometry": {"coordinates":[6.2247400284,49.5246315002],"type":"Point"}
}