{
  "type": "Feature",
  "properties": {
    "iso:country":"AT",
    "sg:address":"D\u00f6llach 13",
    "sg:city":"Liezen",
    "sg:orig_category":"Maler, Anstreicher U Lackierer",
    "sg:phone":"+43 4336 1282111",
    "sg:postcode":"8940",
    "sg:province":"Steiermark",
    "wof:name":"Reiter & Pichler OEG",
    "wof:placetype":"venue"
},
  "geometry": {"coordinates":[14.2413349152,47.5672111511],"type":"Point"}
}