{
  "type": "Feature",
  "properties": {
    "addr:full":"Ulrichsh\u00f6glweg 27 Salzburg Salzburg 5020",
    "addr:housenumber":"27",
    "addr:postcode":"5020",
    "addr:street":"Ulrichshoeglweg;Salzburg",
    "iso:country":"AT",
    "sg:address":"Ulrichsh\u00f6glweg 27",
    "sg:city":"Salzburg",
    "sg:classifiers":[
        {
            "category":"Taxi",
            "type":"Transportation"
        }
    ],
    "sg:phone":"+43 4366 2820979",
    "sg:postcode":"5020",
    "sg:province":"Salzburg",
    "sg:tags":[
        "personentransporte",
        "u"
    ],
    "wof:name":"Reischl Heinz",
    "wof:placetype":"venue"
},
  "geometry": {"coordinates":[13.0377836227,47.7740631104],"type":"Point"}
}