{
  "type": "Feature",
  "properties": {
    "addr:full":"Wiener Str 515 Linz Ober\u00f6sterreich 4030",
    "addr:housenumber":"515",
    "addr:postcode":"4030",
    "iso:country":"AT",
    "sg:address":"Wiener Str 515",
    "sg:city":"Linz",
    "sg:orig_category":"Elektroinstallationsunternehmen",
    "sg:phone":"+43 732 300135",
    "sg:postcode":"4030",
    "sg:province":"Ober\u00f6sterreich",
    "wof:name":"Stadler-Elektro GesmbH",
    "wof:placetype":"venue"
},
  "geometry": {"coordinates":[14.3315973282,48.2441635132],"type":"Point"}
}