{
  "type": "Feature",
  "properties": {
    "addr:full":"Gr\u00fcnmarkt 14-16 Steyr Ober\u00f6sterreich 4400",
    "addr:postcode":"14-16;4400",
    "addr:street":"Oberoesterreich",
    "iso:country":"AT",
    "sg:address":"Gr\u00fcnmarkt 14-16",
    "sg:city":"Steyr",
    "sg:orig_category":"Banken U Sparkassen",
    "sg:phone":"+43 4372 52592400",
    "sg:postcode":"4400",
    "sg:province":"Ober\u00f6sterreich",
    "wof:name":"Oberbank AG",
    "wof:placetype":"venue"
},
  "geometry": {"coordinates":[14.4193296432,48.0391807556],"type":"Point"}
}