{
  "type": "Feature",
  "properties": {
    "addr:full":"Hauptstr 65 Bludesch Vorarlberg 6719",
    "addr:housenumber":"65",
    "addr:postcode":"6719",
    "addr:street":"Hauptstr",
    "iso:country":"AT",
    "sg:address":"Hauptstr 65",
    "sg:city":"Bludesch",
    "sg:orig_category":"Maler, Anstreicher U Lackierer",
    "sg:phone":"+43 5550 3338",
    "sg:postcode":"6719",
    "sg:province":"Vorarlberg",
    "wof:name":"Schuster Norbert",
    "wof:placetype":"venue"
},
  "geometry": {"coordinates":[9.755364418,47.1993598938],"type":"Point"}
}