{
  "type": "Feature",
  "properties": {
    "addr:full":"Brunnleiten 2 Kleinarl Salzburg 5603",
    "addr:housenumber":"2",
    "addr:postcode":"5603",
    "addr:street":"Brunnleiten;Salzburg",
    "iso:country":"AT",
    "sg:address":"Brunnleiten 2",
    "sg:city":"Kleinarl",
    "sg:orig_category":"Appartements / Ferienwohnungen",
    "sg:phone":"+43 4364 18293",
    "sg:postcode":"5603",
    "sg:province":"Salzburg",
    "wof:name":"Schwarzenbacher Emma",
    "wof:placetype":"venue"
},
  "geometry": {"coordinates":[13.3171548843,47.27551651],"type":"Point"}
}