{
  "type": "Feature",
  "properties": {
    "addr:full":"Erlenweg 5 Krumpendorf K\u00e4rnten 9201",
    "addr:housenumber":"5",
    "addr:postcode":"9201",
    "addr:street":"Erlenweg;Kaernten",
    "iso:country":"AT",
    "sg:address":"Erlenweg 5",
    "sg:city":"Krumpendorf",
    "sg:orig_category":"Appartements / Ferienwohnungen",
    "sg:phone":"+43 4229 22920",
    "sg:postcode":"9201",
    "sg:province":"K\u00e4rnten",
    "wof:name":"Gruber-Schasche Pauline",
    "wof:placetype":"venue"
},
  "geometry": {"coordinates":[14.2185239792,46.6224822998],"type":"Point"}
}