{
  "type": "Feature",
  "properties": {
    "addr:full":"Koschatstr 2 H Klagenfurt K\u00e4rnten 9020",
    "addr:housenumber":"2 h",
    "addr:postcode":"9020",
    "addr:street":"Koschatstr;Kaernten",
    "iso:country":"AT",
    "sg:address":"Koschatstr 2 H",
    "sg:city":"Klagenfurt",
    "sg:orig_category":"Druckereien",
    "sg:phone":"+43 463 551760",
    "sg:postcode":"9020",
    "sg:province":"K\u00e4rnten",
    "wof:name":"Gaugeler Rudolf Ing Druck-Center & Werbetechnik",
    "wof:placetype":"venue"
},
  "geometry": {"coordinates":[14.3274202347,46.6254196167],"type":"Point"}
}