{
  "type": "Feature",
  "properties": {
    "addr:full":"Draschestr 91 Wien Wien 1230",
    "addr:housenumber":"91",
    "addr:postcode":"1230",
    "addr:street":"Draschestr",
    "iso:country":"AT",
    "sg:address":"Draschestr 91",
    "sg:city":"Wien",
    "sg:orig_category":"Bauunternehmen",
    "sg:phone":"+43 1 61556050",
    "sg:postcode":"1230",
    "sg:province":"Wien",
    "wof:name":"Gu BaugesmbH",
    "wof:placetype":"venue"
},
  "geometry": {"coordinates":[16.349105835,48.1492004395],"type":"Point"}
}