{
  "type": "Feature",
  "properties": {
    "addr:full":"Hauptstr 6a St. Peter-Freienstein Steiermark 8792",
    "addr:housenumber":"6a",
    "addr:postcode":"8792",
    "addr:street":"Hauptstr;St.",
    "iso:country":"AT",
    "sg:address":"Hauptstr 6a",
    "sg:city":"St. Peter-Freienstein",
    "sg:orig_category":"Autoreparatur",
    "sg:phone":"+43 4338 42227330",
    "sg:postcode":"8792",
    "sg:province":"Steiermark",
    "wof:name":"Neubauer Albert KG",
    "wof:placetype":"venue"
},
  "geometry": {"coordinates":[15.0340166092,47.3971252441],"type":"Point"}
}