{
  "type": "Feature",
  "properties": {
    "addr:full":"F\u00e4rberstr 10 Bludenz Vorarlberg 6700",
    "addr:housenumber":"10",
    "addr:postcode":"6700",
    "addr:street":"Faerberstr",
    "iso:country":"AT",
    "sg:address":"F\u00e4rberstr 10",
    "sg:city":"Bludenz",
    "sg:orig_category":"Physiotherapie",
    "sg:phone":"+43 5552 31044",
    "sg:postcode":"6700",
    "sg:province":"Vorarlberg",
    "wof:name":"Radakovics Michaela",
    "wof:placetype":"venue"
},
  "geometry": {"coordinates":[9.8177118301,47.1538696289],"type":"Point"}
}