{
  "type": "Feature",
  "properties": {
    "iso:country":"AT",
    "sg:address":"Dorf 135",
    "sg:city":"Breitenbach am Inn",
    "sg:orig_category":"Gemeinden",
    "sg:phone":"+43 5338 72740",
    "sg:postcode":"6252",
    "sg:province":"Tirol",
    "wof:name":"Gemeindeamt Breitenbach am Inn",
    "wof:placetype":"venue"
},
  "geometry": {"coordinates":[11.9796380997,47.4805908203],"type":"Point"}
}