{
  "type": "Feature",
  "properties": {
    "iso:country":"AT",
    "sg:address":"Oberhub 17",
    "sg:city":"Haibach ob der Donau",
    "sg:classifiers":[
        {
            "category":"Professional",
            "subcategory":"Computer Services",
            "type":"Services"
        }
    ],
    "sg:phone":"+43 7279 8322",
    "sg:postcode":"4083",
    "sg:province":"Ober\u00f6sterreich",
    "sg:tags":[
        "software"
    ],
    "wof:name":"Huemer Lothar",
    "wof:placetype":"venue"
},
  "geometry": {"coordinates":[13.9061203003,48.4302978516],"type":"Point"}
}