{
  "type": "Feature",
  "properties": {
    "addr:full":"Brixenbach 1 Brixen im Thale Tirol 6364",
    "addr:housenumber":"1",
    "addr:postcode":"6364",
    "addr:street":"Brixenbach;Tirol",
    "iso:country":"AT",
    "sg:address":"Brixenbach 1",
    "sg:city":"Brixen im Thale",
    "sg:orig_category":"Canalisation",
    "sg:phone":"+43 5334 8149",
    "sg:postcode":"6364",
    "sg:province":"Tirol",
    "sg:website":"strobltransag.com",
    "wof:name":"Gebr\u00fcder Strobl GmbH",
    "wof:placetype":"venue"
},
  "geometry": {"coordinates":[12.2611970901,47.4486351013],"type":"Point"}
}