{
  "type": "Feature",
  "properties": {
    "addr:full":"Frein Frankenburg am Hausruck Ober\u00f6sterreich 4873",
    "addr:postcode":"4873",
    "addr:street":"Frein",
    "iso:country":"AT",
    "sg:address":"Frein",
    "sg:city":"Frankenburg am Hausruck",
    "sg:orig_category":"Autohandel",
    "sg:phone":"+43 76837480",
    "sg:postcode":"4873",
    "sg:province":"Ober\u00f6sterreich",
    "wof:name":"Stockinger Raimund",
    "wof:placetype":"venue"
},
  "geometry": {"coordinates":[13.4651069641,48.0878677368],"type":"Point"}
}