{
  "type": "Feature",
  "properties": {
    "addr:full":"Bahnhof 9 Hochfilzen Tirol 6395",
    "addr:housenumber":"9",
    "addr:postcode":"6395",
    "addr:street":"Bahnhof;Tirol",
    "iso:country":"AT",
    "sg:address":"Bahnhof 9",
    "sg:city":"Hochfilzen",
    "sg:classifiers":[
        {
            "category":"Travel",
            "subcategory":"Hotels & Motels",
            "type":"Entertainment"
        }
    ],
    "sg:phone":"+43 5359 219",
    "sg:postcode":"6395",
    "sg:province":"Tirol",
    "wof:name":"Hotel Hochfilzner Hof",
    "wof:placetype":"venue"
},
  "geometry": {"coordinates":[12.6256923676,47.4674491882],"type":"Point"}
}