{
  "type": "Feature",
  "properties": {
    "addr:full":"Werksgel\u00e4nde 32 Bischofshofen Salzburg 5500",
    "addr:housenumber":"32",
    "addr:postcode":"5500",
    "addr:street":"Werksgelaende;Salzburg",
    "iso:country":"AT",
    "sg:address":"Werksgel\u00e4nde 32",
    "sg:city":"Bischofshofen",
    "sg:classifiers":[
        {
            "category":"Professional",
            "subcategory":"Art Services",
            "type":"Services"
        }
    ],
    "sg:phone":"+43 6462 8128",
    "sg:postcode":"5500",
    "sg:province":"Salzburg",
    "sg:tags":[
        "homepage",
        "designing"
    ],
    "sg:website":"inteco.co.at",
    "wof:name":"INTECO Technologie & Computer Training GmbH",
    "wof:placetype":"venue"
},
  "geometry": {"coordinates":[8.679690361,6.0750899315],"type":"Point"}
}