{
  "type": "Feature",
  "properties": {
    "iso:country":"AT",
    "sg:address":"Bismarckstr 18",
    "sg:city":"Linz",
    "sg:orig_category":"Waren Aller Art",
    "sg:phone":"+43 732 785608",
    "sg:postcode":"4020",
    "sg:province":"Ober\u00f6sterreich",
    "wof:name":"PILZ KEG",
    "wof:placetype":"venue"
},
  "geometry": {"coordinates":[14.293182373,48.2997055054],"type":"Point"}
}