{
  "type": "Feature",
  "properties": {
    "addr:full":"Bundesstr 20a Spital am Semmering Steiermark 8684",
    "addr:housenumber":"20a",
    "addr:postcode":"8684",
    "addr:street":"Bundesstr",
    "iso:country":"AT",
    "sg:address":"Bundesstr 20a",
    "sg:city":"Spital am Semmering",
    "sg:orig_category":"Banken U Sparkassen",
    "sg:phone":"+43 4338 532770",
    "sg:postcode":"8684",
    "sg:province":"Steiermark",
    "wof:name":"Bankomat d Raiffeisenbank Oberes M\u00fcrztal regGenmbH",
    "wof:placetype":"venue"
},
  "geometry": {"coordinates":[15.7530908585,47.6157226562],"type":"Point"}
}