{
  "type": "Feature",
  "properties": {
    "addr:full":"Jochberger Str 89 Kitzb\u00fchel Tirol 6370",
    "addr:postcode":"6370",
    "addr:street":"Str 89 Kitzbuehel Tirol",
    "iso:country":"AT",
    "sg:address":"Jochberger Str 89",
    "sg:city":"Kitzb\u00fchel",
    "sg:orig_category":"Werbeagenturen",
    "sg:phone":"+43 5356 71216",
    "sg:postcode":"6370",
    "sg:province":"Tirol",
    "wof:name":"ImpalaWolfmitBiss Werbeagentur",
    "wof:placetype":"venue"
},
  "geometry": {"coordinates":[12.4036026001,47.4370193481],"type":"Point"}
}