{
  "type": "Feature",
  "properties": {
    "addr:full":"Ringstr 144 Dorfgastein Salzburg 5632",
    "addr:housenumber":"144",
    "addr:postcode":"5632",
    "addr:street":"Salzburg",
    "iso:country":"AT",
    "sg:address":"Ringstr 144",
    "sg:city":"Dorfgastein",
    "sg:orig_category":"Pensionen / Privatzimmer",
    "sg:phone":"+43 6433 7334",
    "sg:postcode":"5632",
    "sg:province":"Salzburg",
    "wof:name":"Haus Bergkristall",
    "wof:placetype":"venue"
},
  "geometry": {"coordinates":[13.1046924591,47.2430953979],"type":"Point"}
}