{
  "type": "Feature",
  "properties": {
    "addr:full":"Brucknerstr 3 Innsbruck Tirol 6020",
    "addr:housenumber":"3",
    "addr:postcode":"6020",
    "addr:street":"Brucknerstr;Tirol",
    "iso:country":"AT",
    "sg:address":"Brucknerstr 3",
    "sg:city":"Innsbruck",
    "sg:orig_category":"Alternativtherapie",
    "sg:phone":"+43 4366 44456854",
    "sg:postcode":"6020",
    "sg:province":"Tirol",
    "wof:name":"Rolfing Praxis - Andrea Felgitscher",
    "wof:placetype":"venue"
},
  "geometry": {"coordinates":[11.4091558456,47.2779960632],"type":"Point"}
}