{
  "type": "Feature",
  "properties": {
    "addr:full":"Roseng 1 Salzburg Salzburg 5020",
    "addr:housenumber":"1",
    "addr:postcode":"5020",
    "addr:street":"Roseng;Salzburg",
    "iso:country":"AT",
    "sg:address":"Roseng 1",
    "sg:city":"Salzburg",
    "sg:orig_category":"Lebensmittel / Einzelhandel",
    "sg:phone":"+43 662 434326",
    "sg:postcode":"5020",
    "sg:province":"Salzburg",
    "wof:name":"Billa AG",
    "wof:placetype":"venue"
},
  "geometry": {"coordinates":[13.0315513611,47.8133354187],"type":"Point"}
}