{
  "type": "Feature",
  "properties": {
    "addr:full":"Wiener Strasse 391  Linz Ober\u00f6sterreich 4030",
    "addr:housenumber":"391",
    "addr:postcode":"4030",
    "addr:street":"Wiener Strasse",
    "iso:country":"AT",
    "sg:address":"Wiener Strasse 391 ",
    "sg:city":"Linz",
    "sg:classifiers":[
        {
            "category":"Building & Trades",
            "subcategory":"Plumbing",
            "type":"Services"
        }
    ],
    "sg:phone":"+43 732 307316",
    "sg:postcode":"4030",
    "sg:province":"Ober\u00f6sterreich",
    "sg:tags":[
        "supraregional",
        "gas"
    ],
    "wof:name":"Franz Greiner",
    "wof:placetype":"venue"
},
  "geometry": {"coordinates":[14.3220186234,48.256816864],"type":"Point"}
}