{
  "type": "Feature",
  "properties": {
    "iso:country":"AT",
    "sg:address":"Hirschkreitg 1A",
    "sg:city":"Mattersburg",
    "sg:orig_category":"Graveure",
    "sg:phone":"+43 2626 64544",
    "sg:postcode":"7210",
    "sg:province":"Burgenland",
    "wof:name":"Steingraveur Michael Reiss",
    "wof:placetype":"venue"
},
  "geometry": {"coordinates":[16.3888339996,47.730922699],"type":"Point"}
}