{
  "type": "Feature",
  "properties": {
    "addr:full":"Nr 2 Jennersdorf Burgenland 8380",
    "addr:postcode":"8380",
    "addr:street":"Nr",
    "iso:country":"AT",
    "sg:address":"Nr 2",
    "sg:city":"Jennersdorf",
    "sg:orig_category":"Landwirtschaftliche Produkte",
    "sg:phone":"+43 3329 45252",
    "sg:postcode":"8380",
    "sg:province":"Burgenland",
    "wof:name":"Ehrenhofer Josef jun",
    "wof:placetype":"venue"
},
  "geometry": {"coordinates":[16.1399803162,46.9372177124],"type":"Point"}
}