{
  "type": "Feature",
  "properties": {
    "addr:full":"Wiener Str 131 Linz Ober\u00f6sterreich 4020",
    "addr:housenumber":"131",
    "addr:postcode":"4020",
    "iso:country":"AT",
    "sg:address":"Wiener Str 131",
    "sg:city":"Linz",
    "sg:orig_category":"Sprachschulen U -Unterricht",
    "sg:phone":"+43 4373 2345306",
    "sg:postcode":"4020",
    "sg:province":"Ober\u00f6sterreich",
    "sg:website":"dialogica-linz.at",
    "wof:name":"Dialogica Europa-Akademie Linz",
    "wof:placetype":"venue"
},
  "geometry": {"coordinates":[14.3080005646,48.2819824219],"type":"Point"}
}