{
  "type": "Feature",
  "properties": {
    "addr:full":"Ottensheimer Str 58 Linz Ober\u00f6sterreich 4040",
    "addr:postcode":"4040",
    "addr:street":"Str 58",
    "iso:country":"AT",
    "sg:address":"Ottensheimer Str 58",
    "sg:city":"Linz",
    "sg:orig_category":"Architekten",
    "sg:phone":"+43 732 733084",
    "sg:postcode":"4040",
    "sg:province":"Ober\u00f6sterreich",
    "wof:name":"Architekturgruppe H + B Schremmer-Jell Dipl-Ing",
    "wof:placetype":"venue"
},
  "geometry": {"coordinates":[14.2785301208,48.3079299927],"type":"Point"}
}