{
  "type": "Feature",
  "properties": {
    "iso:country":"AT",
    "sg:address":"Wechslerg 261",
    "sg:city":"Flachau",
    "sg:orig_category":"Appartements / Ferienwohnungen",
    "sg:phone":"+43 4364 527048",
    "sg:postcode":"5542",
    "sg:province":"Salzburg",
    "wof:name":"Appartement Dertnig - Gerhard Dertnig",
    "wof:placetype":"venue"
},
  "geometry": {"coordinates":[13.3927116394,47.3475189209],"type":"Point"}
}