{
  "type": "Feature",
  "properties": {
    "iso:country":"AT",
    "sg:address":"Reitle 377",
    "sg:city":"Sautens",
    "sg:orig_category":"Innenarchitekten",
    "sg:phone":"+43 5252 20083",
    "sg:postcode":"6432",
    "sg:province":"Tirol",
    "wof:name":"Inn - Takt, Ing Georg C Hueber",
    "wof:placetype":"venue"
},
  "geometry": {"coordinates":[10.8566970825,47.2152252197],"type":"Point"}
}