{
  "type": "Feature",
  "properties": {
    "addr:full":"Nr 70 Seefeld in Tirol Tirol 6100",
    "addr:postcode":"6100",
    "addr:street":"Nr;Seefeld;Tirol",
    "iso:country":"AT",
    "sg:address":"Nr 70",
    "sg:city":"Seefeld in Tirol",
    "sg:classifiers":[
        {
            "category":"Professional",
            "subcategory":"Management & Consulting",
            "type":"Services"
        }
    ],
    "sg:phone":"+43 5212 323920",
    "sg:postcode":"6100",
    "sg:province":"Tirol",
    "wof:name":"Schmid Josef Tourismusmanagement",
    "wof:placetype":"venue"
},
  "geometry": {"coordinates":[166.9221496582,-0.5282999873],"type":"Point"}
}