{
  "type": "Feature",
  "properties": {
    "addr:full":"Brunneng 45 Wien Wien 1160",
    "addr:housenumber":"45",
    "addr:postcode":"1160",
    "addr:street":"Brunneng",
    "iso:country":"AT",
    "sg:address":"Brunneng 45",
    "sg:city":"Wien",
    "sg:orig_category":"Feinkost",
    "sg:phone":"+43 1 4061298",
    "sg:postcode":"1160",
    "sg:province":"Wien",
    "wof:name":"DENIZ - Orientalische Spezialit\u00e4ten",
    "wof:placetype":"venue"
},
  "geometry": {"coordinates":[16.3355255127,48.2101631165],"type":"Point"}
}