{
  "type": "Feature",
  "properties": {
    "iso:country":"AT",
    "sg:address":"Loiblstr 6",
    "sg:city":"Ferlach",
    "sg:orig_category":"Polizei U Gendarmerie",
    "sg:phone":"+43 5 91332100",
    "sg:postcode":"9170",
    "sg:province":"K\u00e4rnten",
    "wof:name":"Bezirksgendarmariekommando Klagenfurt",
    "wof:placetype":"venue"
},
  "geometry": {"coordinates":[14.3000926971,46.5233001709],"type":"Point"}
}