{
  "type": "Feature",
  "properties": {
    "addr:full":"Salzachtal Bundesstr 39 Zell am See Salzburg 5700",
    "addr:housenumber":"39",
    "addr:postcode":"5700",
    "addr:street":"Salzburg",
    "iso:country":"AT",
    "sg:address":"Salzachtal Bundesstr 39",
    "sg:city":"Zell am See",
    "sg:classifiers":[
        {
            "category":"Travel",
            "subcategory":"Hotels & Motels",
            "type":"Entertainment"
        }
    ],
    "sg:phone":"+43 6542 570480",
    "sg:postcode":"5700",
    "sg:province":"Salzburg",
    "wof:name":"Gletscherblick",
    "wof:placetype":"venue"
},
  "geometry": {"coordinates":[12.7759389877,47.2957038879],"type":"Point"}
}