{
  "type": "Feature",
  "properties": {
    "addr:full":"St.-Peter-Str 1 Bludenz Vorarlberg 6700",
    "addr:housenumber":"1",
    "addr:postcode":"6700",
    "addr:street":"St.-Peter-Str",
    "iso:country":"AT",
    "sg:address":"St.-Peter-Str 1",
    "sg:city":"Bludenz",
    "sg:orig_category":"Volksschulen",
    "sg:phone":"+43 5552 30980",
    "sg:postcode":"6700",
    "sg:province":"Vorarlberg",
    "wof:name":"Volksschule Mitte",
    "wof:placetype":"venue"
},
  "geometry": {"coordinates":[9.8227357864,47.153503418],"type":"Point"}
}