{
  "type": "Feature",
  "properties": {
    "addr:full":"An der Bundesstr 41 Weitensfeld K\u00e4rnten 9344",
    "addr:housenumber":"41",
    "addr:postcode":"9344",
    "addr:street":"An Der Bundesstr;Kaernten",
    "iso:country":"AT",
    "sg:address":"An der Bundesstr 41",
    "sg:city":"Weitensfeld",
    "sg:orig_category":"Trachtenbekleidung",
    "sg:phone":"+43 4265 425",
    "sg:postcode":"9344",
    "sg:province":"K\u00e4rnten",
    "wof:name":"K\u00e4RNTNER TRACHTENHAUS Mag. Ernst Strohmaier",
    "wof:placetype":"venue"
},
  "geometry": {"coordinates":[14.193403244,46.8474197388],"type":"Point"}
}