{
  "type": "Feature",
  "properties": {
    "addr:full":"Pilgram 18 M\u00fcnzbach Ober\u00f6sterreich 4323",
    "addr:housenumber":"18",
    "addr:postcode":"4323",
    "addr:street":"Pilgram;Oberoesterreich",
    "iso:country":"AT",
    "sg:address":"Pilgram 18",
    "sg:city":"M\u00fcnzbach",
    "sg:orig_category":"Bildhauer",
    "sg:phone":"+43 7264 4370",
    "sg:postcode":"4323",
    "sg:province":"Ober\u00f6sterreich",
    "wof:name":"Langeder Heinrich",
    "wof:placetype":"venue"
},
  "geometry": {"coordinates":[14.7503252029,48.255279541],"type":"Point"}
}