{
  "type": "Feature",
  "properties": {
    "iso:country":"AT",
    "sg:address":"Ullmannstr 53",
    "sg:city":"Wien",
    "sg:classifiers":[
        {
            "category":"Professional",
            "subcategory":"Computer Services",
            "type":"Services"
        }
    ],
    "sg:phone":"+43 4318 972348",
    "sg:postcode":"1150",
    "sg:province":"Wien",
    "sg:tags":[
        "software"
    ],
    "wof:name":"spherecast IT Dienstleistung & Entwicklung GmbH",
    "wof:placetype":"venue"
},
  "geometry": {"coordinates":[16.3311367035,48.1861228943],"type":"Point"}
}