{
  "type": "Feature",
  "properties": {
    "addr:full":"Oberwei\u00dfburg 124 St. Michael im Lungau Salzburg 5582",
    "addr:housenumber":"124",
    "addr:postcode":"5582",
    "addr:street":"Oberweissburg;Salzburg",
    "iso:country":"AT",
    "sg:address":"Oberwei\u00dfburg 124",
    "sg:city":"St. Michael im Lungau",
    "sg:orig_category":"Stra\u00c3\u0178enbau",
    "sg:phone":"+43 4364 7784710",
    "sg:postcode":"5582",
    "sg:province":"Salzburg",
    "wof:name":"\u00f6sterreichische Autobahnen- u Schnellstra\u00dfen GesmbH",
    "wof:placetype":"venue"
},
  "geometry": {"coordinates":[13.5904722214,47.1096229553],"type":"Point"}
}