{
  "type": "Feature",
  "properties": {
    "addr:full":"Dreifaltigkeitsg 4/2 Salzburg Salzburg 5020",
    "addr:housenumber":"4 / 2",
    "addr:postcode":"5020",
    "addr:street":"Dreifaltigkeitsg;Salzburg",
    "iso:country":"AT",
    "sg:address":"Dreifaltigkeitsg 4/2",
    "sg:city":"Salzburg",
    "sg:orig_category":"Psychologen",
    "sg:phone":"+43 662 887667",
    "sg:postcode":"5020",
    "sg:province":"Salzburg",
    "wof:name":"Wendtner Franz Mag",
    "wof:placetype":"venue"
},
  "geometry": {"coordinates":[13.045003891,47.8022842407],"type":"Point"}
}