{
  "type": "Feature",
  "properties": {
    "addr:full":"Magdalenenstr 3-7 Wien Wien 1060",
    "addr:housenumber":"3-7",
    "addr:postcode":"1060",
    "addr:street":"Magdalenenstr",
    "iso:country":"AT",
    "sg:address":"Magdalenenstr 3-7",
    "sg:city":"Wien",
    "sg:classifiers":[
        {
            "category":"Taxi",
            "type":"Transportation"
        }
    ],
    "sg:phone":"+43 1 5878329",
    "sg:postcode":"1060",
    "sg:province":"Wien",
    "sg:tags":[
        "personentransporte",
        "u"
    ],
    "wof:name":"Damjanovic KEG",
    "wof:placetype":"venue"
},
  "geometry": {"coordinates":[16.3550777435,48.1962051392],"type":"Point"}
}