{
  "type": "Feature",
  "properties": {
    "iso:country":"AT",
    "sg:address":"Mureckerstr. 1",
    "sg:city":"St. Stefan im Rosental",
    "sg:classifiers":[
        {
            "category":"Food & Beverages",
            "subcategory":"Groceries & Convenience Stores",
            "type":"Retail Goods"
        }
    ],
    "sg:phone":"+43 4331 168994",
    "sg:postcode":"8083",
    "sg:province":"Steiermark",
    "sg:tags":[
        "product",
        "related"
    ],
    "wof:name":"H. LOIDL WURSTPRODUKTIONS- U. VERTRIEBSGESELLSCHAFT MBH & CO KG",
    "wof:placetype":"venue"
},
  "geometry": {"coordinates":[15.7116918564,46.9037322998],"type":"Point"}
}