{
  "type": "Feature",
  "properties": {
    "iso:country":"AT",
    "sg:address":"Murm\u00fchlweg 2",
    "sg:city":"Gratwein",
    "sg:orig_category":"Holzhandel",
    "sg:phone":"+43 4331 24231230",
    "sg:postcode":"8112",
    "sg:province":"Steiermark",
    "wof:name":"Papierholz Austria GesmbH",
    "wof:placetype":"venue"
},
  "geometry": {"coordinates":[15.3184213638,47.1293487549],"type":"Point"}
}