{
  "type": "Feature",
  "properties": {
    "iso:country":"AT",
    "sg:address":"Freyung 6/2",
    "sg:city":"Wien",
    "sg:orig_category":"Immobilienverwaltungen",
    "sg:phone":"+43 1 9610407",
    "sg:postcode":"1010",
    "sg:province":"Wien",
    "wof:name":"PROFECT Immobilienverwaltung GmbH",
    "wof:placetype":"venue"
},
  "geometry": {"coordinates":[16.3643989563,48.2120018005],"type":"Point"}
}