{
  "type": "Feature",
  "properties": {
    "addr:full":"Dorfgastein Salzburg 5632",
    "addr:postcode":"5632",
    "iso:country":"AT",
    "sg:city":"Dorfgastein",
    "sg:orig_category":"Museen / Ausstellungen",
    "sg:phone":"+43 4364 337603",
    "sg:postcode":"5632",
    "sg:province":"Salzburg",
    "wof:name":"Historie-Erlebnis Burg Klammstein",
    "wof:placetype":"venue"
},
  "geometry": {"coordinates":[13.1046924591,47.2430953979],"type":"Point"}
}