{
  "type": "Feature",
  "properties": {
    "addr:full":"Margaretenstr 80/1 Wien Wien 1050",
    "addr:housenumber":"80 / 1",
    "addr:postcode":"1050",
    "addr:street":"Margaretenstr",
    "iso:country":"AT",
    "sg:address":"Margaretenstr 80/1",
    "sg:city":"Wien",
    "sg:orig_category":"Immobilienverwaltungen, Immobilienmakler, Datenverarbeitung",
    "sg:phone":"+43 1 5855550",
    "sg:postcode":"1050",
    "sg:province":"Wien",
    "wof:name":"DVI Immobilien GesmbH",
    "wof:placetype":"venue"
},
  "geometry": {"coordinates":[16.3596096039,48.1922454834],"type":"Point"}
}