{
  "type": "Feature",
  "properties": {
    "addr:full":"Franzosenhausweg 36 Linz Ober\u00f6sterreich 4030",
    "addr:housenumber":"36",
    "addr:postcode":"4030",
    "addr:street":"Franzosenhausweg",
    "iso:country":"AT",
    "sg:address":"Franzosenhausweg 36",
    "sg:city":"Linz",
    "sg:classifiers":[
        {
            "category":"Personal",
            "subcategory":"Hair Removal",
            "type":"Services"
        }
    ],
    "sg:phone":"+43 732 3857210",
    "sg:postcode":"4030",
    "sg:province":"Ober\u00f6sterreich",
    "sg:tags":[
        "brush"
    ],
    "sg:website":"goldwell.at",
    "wof:name":"GOLDWELL Handelsges.m.b.H.",
    "wof:placetype":"venue"
},
  "geometry": {"coordinates":[14.2936201096,48.2455673218],"type":"Point"}
}