{
  "type": "Feature",
  "properties": {
    "addr:full":"Nr 30 Rastenfeld Nieder\u00f6sterreich 3532",
    "addr:postcode":"3532",
    "addr:street":"Nr;Rastenfeld",
    "iso:country":"AT",
    "sg:address":"Nr 30",
    "sg:city":"Rastenfeld",
    "sg:orig_category":"Non-Classified Establishments",
    "sg:phone":"+43 5 91333449",
    "sg:postcode":"3532",
    "sg:province":"Nieder\u00f6sterreich",
    "wof:name":"Gendarmerie",
    "wof:placetype":"venue"
},
  "geometry": {"coordinates":[15.3316497803,48.5734481812],"type":"Point"}
}