{
  "type": "Feature",
  "properties": {
    "addr:full":"Ebnerstr 30 Traisen Nieder\u00f6sterreich 3160",
    "addr:housenumber":"30",
    "addr:postcode":"3160",
    "addr:street":"Ebnerstr",
    "iso:country":"AT",
    "sg:address":"Ebnerstr 30",
    "sg:city":"Traisen",
    "sg:classifiers":[
        {
            "category":"Professional",
            "subcategory":"Computer Services",
            "type":"Services"
        }
    ],
    "sg:phone":"+43 2762 62507",
    "sg:postcode":"3160",
    "sg:province":"Nieder\u00f6sterreich",
    "sg:tags":[
        "software"
    ],
    "wof:name":"Optamed GesmbH",
    "wof:placetype":"venue"
},
  "geometry": {"coordinates":[15.6266918182,48.0477142334],"type":"Point"}
}