{
  "type": "Feature",
  "properties": {
    "addr:full":"Nr 148 Gleisdorf Steiermark 8200",
    "addr:postcode":"8200",
    "addr:street":"Nr 148",
    "iso:country":"AT",
    "sg:address":"Nr 148",
    "sg:city":"Gleisdorf",
    "sg:orig_category":"Me\u00c3\u0178-, Steuer- U Regeltechnik",
    "sg:phone":"+43 3112 61200",
    "sg:postcode":"8200",
    "sg:province":"Steiermark",
    "wof:name":"Schaller Me\u00dftechnik",
    "wof:placetype":"venue"
},
  "geometry": {"coordinates":[15.6912050247,47.103477478],"type":"Point"}
}