{
  "type": "Feature",
  "properties": {
    "addr:full":"Raxstr 3 Wien Wien 1100",
    "addr:housenumber":"3",
    "addr:postcode":"1100",
    "addr:street":"Raxstr",
    "iso:country":"AT",
    "sg:address":"Raxstr 3",
    "sg:city":"Wien",
    "sg:orig_category":"Tankstellen",
    "sg:phone":"+43 1 6171265",
    "sg:postcode":"1100",
    "sg:province":"Wien",
    "wof:name":"OMV AG",
    "wof:placetype":"venue"
},
  "geometry": {"coordinates":[16.365978241,48.1651611328],"type":"Point"}
}