{
  "type": "Feature",
  "properties": {
    "addr:full":"Nr 316a Hadres Nieder\u00f6sterreich 2061",
    "addr:postcode":"2061",
    "addr:street":"Nr",
    "iso:country":"AT",
    "sg:address":"Nr 316a",
    "sg:city":"Hadres",
    "sg:orig_category":"Rebschulen",
    "sg:phone":"+43 2943 3544",
    "sg:postcode":"2061",
    "sg:province":"Nieder\u00f6sterreich",
    "wof:name":"Schmid Werner",
    "wof:placetype":"venue"
},
  "geometry": {"coordinates":[16.1328372955,48.7088470459],"type":"Point"}
}