{
  "type": "Feature",
  "properties": {
    "addr:full":"Bahnhofstr 24 Lebring Steiermark 8403",
    "addr:housenumber":"24",
    "addr:postcode":"8403",
    "addr:street":"Bahnhofstr",
    "iso:country":"AT",
    "sg:address":"Bahnhofstr 24",
    "sg:city":"Lebring",
    "sg:orig_category":"Bibliotheken",
    "sg:phone":"+43 4331 8252060",
    "sg:postcode":"8403",
    "sg:province":"Steiermark",
    "wof:name":"B\u00fccherei",
    "wof:placetype":"venue"
},
  "geometry": {"coordinates":[15.530582428,46.8551864624],"type":"Point"}
}