{
  "type": "Feature",
  "properties": {
    "addr:full":"Hauptstr 12 Karlstein an der Thaya Nieder\u00f6sterreich 3822",
    "addr:housenumber":"12",
    "addr:postcode":"3822",
    "addr:street":"Hauptstr",
    "iso:country":"AT",
    "sg:address":"Hauptstr 12",
    "sg:city":"Karlstein an der Thaya",
    "sg:orig_category":"Gemeinden",
    "sg:phone":"+43 4328 44279",
    "sg:postcode":"3822",
    "sg:province":"Nieder\u00f6sterreich",
    "wof:name":"Gemeindeamt Karlstein",
    "wof:placetype":"venue"
},
  "geometry": {"coordinates":[15.404091835,48.8832931519],"type":"Point"}
}