{
  "type": "Feature",
  "properties": {
    "addr:full":"Roseng 16 Gramatneusiedl Nieder\u00f6sterreich 2440",
    "addr:housenumber":"16",
    "addr:postcode":"2440",
    "addr:street":"Roseng",
    "iso:country":"AT",
    "sg:address":"Roseng 16",
    "sg:city":"Gramatneusiedl",
    "sg:orig_category":"Elektronotdienste, Elektroinstallationsunternehmen",
    "sg:phone":"+43 2234 50002",
    "sg:postcode":"2440",
    "sg:province":"Nieder\u00f6sterreich",
    "sg:website":"elektro-hartl.at",
    "wof:name":"Hartl & Bayer OEG",
    "wof:placetype":"venue"
},
  "geometry": {"coordinates":[16.5298805237,47.9985847473],"type":"Point"}
}