{
  "type": "Feature",
  "properties": {
    "addr:full":"Salzburger Str 24b Haid Ober\u00f6sterreich 4053",
    "addr:housenumber":"24b",
    "addr:postcode":"4053",
    "addr:street":"Salzburger Str",
    "iso:country":"AT",
    "sg:address":"Salzburger Str 24b",
    "sg:city":"Haid",
    "sg:orig_category":"Polizei U Gendarmerie",
    "sg:phone":"+43 4359 1334131",
    "sg:postcode":"4053",
    "sg:province":"Ober\u00f6sterreich",
    "wof:name":"Gendarmerie",
    "wof:placetype":"venue"
},
  "geometry": {"coordinates":[14.2506628036,48.2011604309],"type":"Point"}
}