{
  "type": "Feature",
  "properties": {
    "addr:full":"Salzgasse 20 Freistadt Ober\u00f6sterreich 4240",
    "addr:housenumber":"20",
    "addr:postcode":"4240",
    "addr:street":"Salzgasse",
    "iso:country":"AT",
    "sg:address":"Salzgasse 20",
    "sg:city":"Freistadt",
    "sg:classifiers":[
        {
            "category":"Shopping",
            "subcategory":"Musical Instruments",
            "type":"Retail Goods"
        }
    ],
    "sg:phone":"+43 7942 723930",
    "sg:postcode":"4240",
    "sg:province":"Ober\u00f6sterreich",
    "sg:tags":[
        "bag",
        "cases",
        "sheathes"
    ],
    "wof:name":"Josef Werner Lorenz",
    "wof:placetype":"venue"
},
  "geometry": {"coordinates":[14.5035915375,48.5122261047],"type":"Point"}
}