{
  "type": "Feature",
  "properties": {
    "addr:full":"Kircheng 11 Altheim Ober\u00f6sterreich 4950",
    "addr:housenumber":"11",
    "addr:postcode":"4950",
    "addr:street":"Kircheng",
    "iso:country":"AT",
    "sg:address":"Kircheng 11",
    "sg:city":"Altheim",
    "sg:orig_category":"Maschinenhandel",
    "sg:phone":"+43 7723 424520",
    "sg:postcode":"4950",
    "sg:province":"Ober\u00f6sterreich",
    "wof:name":"Wagner Klaus",
    "wof:placetype":"venue"
},
  "geometry": {"coordinates":[13.2340736389,48.2499084473],"type":"Point"}
}