{
  "type": "Feature",
  "properties": {
    "addr:full":"Hainfelder Str 3 Weissenbach an der Triesting Nieder\u00f6sterreich 2564",
    "addr:housenumber":"3",
    "addr:postcode":"2564",
    "addr:street":"Str;Niederoesterreich",
    "iso:country":"AT",
    "sg:address":"Hainfelder Str 3",
    "sg:city":"Weissenbach an der Triesting",
    "sg:orig_category":"Torantriebe",
    "sg:phone":"+43 2674 81005",
    "sg:postcode":"2564",
    "sg:province":"Nieder\u00f6sterreich",
    "wof:name":"TORtechnik Stockreiter",
    "wof:placetype":"venue"
},
  "geometry": {"coordinates":[15.9736728668,47.9732284546],"type":"Point"}
}