{
  "type": "Feature",
  "properties": {
    "addr:full":"Almstr 6 Schwarzenau Nieder\u00f6sterreich 3900",
    "addr:housenumber":"6",
    "addr:postcode":"3900",
    "addr:street":"Almstr",
    "iso:country":"AT",
    "sg:address":"Almstr 6",
    "sg:city":"Schwarzenau",
    "sg:orig_category":"Appartements / Ferienwohnungen",
    "sg:phone":"+43 2849 2547",
    "sg:postcode":"3900",
    "sg:province":"Nieder\u00f6sterreich",
    "wof:name":"Weissensteiner Johann",
    "wof:placetype":"venue"
},
  "geometry": {"coordinates":[15.2558727264,48.7462310791],"type":"Point"}
}