{
  "type": "Feature",
  "properties": {
    "addr:full":"Gartenauer Str 8 Gartenau-St. Leonhard Salzburg 5083",
    "addr:housenumber":"8;5083",
    "addr:street":"Str;Leonhard Salzburg",
    "iso:country":"AT",
    "sg:address":"Gartenauer Str 8",
    "sg:city":"Gartenau-St. Leonhard",
    "sg:orig_category":"Tourismusinformation U -Organisationen",
    "sg:phone":"+43 6246 735700",
    "sg:postcode":"5083",
    "sg:province":"Salzburg",
    "wof:name":"Fremdenverkehrsverband Gr\u00f6dig",
    "wof:placetype":"venue"
},
  "geometry": {"coordinates":[13.0432071686,47.7266578674],"type":"Point"}
}