{
  "type": "Feature",
  "properties": {
    "iso:country":"AT",
    "sg:address":"Nr 12C",
    "sg:city":"Mayrhofen",
    "sg:orig_category":"Pensionen / Privatzimmer",
    "sg:phone":"+43 4352 8563180",
    "sg:postcode":"6290",
    "sg:province":"Tirol",
    "wof:name":"Pension Stock",
    "wof:placetype":"venue"
},
  "geometry": {"coordinates":[11.8624277115,47.1670684814],"type":"Point"}
}