{
  "type": "Feature",
  "properties": {
    "addr:full":"Klostertaler Str 100 Dalaas Vorarlberg 6752",
    "addr:housenumber":"100",
    "addr:postcode":"6752",
    "addr:street":"Str",
    "iso:country":"AT",
    "sg:address":"Klostertaler Str 100",
    "sg:city":"Dalaas",
    "sg:orig_category":"Tankstellen",
    "sg:phone":"+43 5585 7283",
    "sg:postcode":"6752",
    "sg:province":"Vorarlberg",
    "wof:name":"Avia Tankstelle",
    "wof:placetype":"venue"
},
  "geometry": {"coordinates":[9.9998960495,47.1229896545],"type":"Point"}
}