{
  "type": "Feature",
  "properties": {
    "iso:country":"AT",
    "sg:address":"Seitenstetteng 5/14",
    "sg:city":"Wien",
    "sg:orig_category":"Immobilienmakler",
    "sg:phone":"+43 1 5332990",
    "sg:postcode":"1010",
    "sg:province":"Wien",
    "sg:website":"pn-immo.at",
    "wof:name":"Neumayer Peter",
    "wof:placetype":"venue"
},
  "geometry": {"coordinates":[16.3749866486,48.2118263245],"type":"Point"}
}