{
  "type": "Feature",
  "properties": {
    "iso:country":"AT",
    "sg:address":"Hauptpl 11",
    "sg:city":"Jennersdorf",
    "sg:classifiers":[
        {
            "category":"Restaurant",
            "type":"Food & Drink"
        }
    ],
    "sg:phone":"+43 4333 29480930",
    "sg:postcode":"8380",
    "sg:province":"Burgenland",
    "wof:name":"Heurigen Restaurant Weihs",
    "wof:placetype":"venue"
},
  "geometry": {"coordinates":[16.1404380798,46.9371147156],"type":"Point"}
}