{
  "type": "Feature",
  "properties": {
    "iso:country":"AT",
    "sg:address":"Am Viehmarkt 4",
    "sg:city":"Stainz",
    "sg:orig_category":"Psychotherapie",
    "sg:phone":"+43 699 11990001",
    "sg:postcode":"8510",
    "sg:province":"Steiermark",
    "wof:name":"Fasching Andrea",
    "wof:placetype":"venue"
},
  "geometry": {"coordinates":[15.2615785599,46.8920440674],"type":"Point"}
}