{
  "type": "Feature",
  "properties": {
    "addr:full":"Raiffeisenweg 1 Gratkorn Steiermark 8101",
    "addr:housenumber":"1",
    "addr:postcode":"8101",
    "addr:street":"Raiffeisenweg",
    "iso:country":"AT",
    "sg:address":"Raiffeisenweg 1",
    "sg:city":"Gratkorn",
    "sg:orig_category":"Friseure U Frisiersalons",
    "sg:phone":"+43 3124 23391",
    "sg:postcode":"8101",
    "sg:province":"Steiermark",
    "wof:name":"Fris\u00f6r Edmund",
    "wof:placetype":"venue"
},
  "geometry": {"coordinates":[15.3520174026,47.1343917847],"type":"Point"}
}