{
  "type": "Feature",
  "properties": {
    "addr:full":"Emme 8c Altach Vorarlberg 6844",
    "addr:housenumber":"8c",
    "addr:postcode":"6844",
    "addr:street":"Emme",
    "iso:country":"AT",
    "sg:address":"Emme 8c",
    "sg:city":"Altach",
    "sg:orig_category":"Tischlereien",
    "sg:phone":"+43 5576 746010",
    "sg:postcode":"6844",
    "sg:province":"Vorarlberg",
    "wof:name":"Bell Arno",
    "wof:placetype":"venue"
},
  "geometry": {"coordinates":[9.6438970566,47.3557243347],"type":"Point"}
}