{
  "type": "Feature",
  "properties": {
    "addr:full":"Stubnerkogelstr 44 Bad Gastein Salzburg 5640",
    "addr:housenumber":"44",
    "addr:postcode":"5640",
    "addr:street":"Stubnerkogelstr;Salzburg",
    "iso:country":"AT",
    "sg:address":"Stubnerkogelstr 44",
    "sg:city":"Bad Gastein",
    "sg:orig_category":"Installationsunternehmen",
    "sg:phone":"+43 4364 342689",
    "sg:postcode":"5640",
    "sg:province":"Salzburg",
    "wof:name":"Fasching Ernst",
    "wof:placetype":"venue"
},
  "geometry": {"coordinates":[13.1349925995,47.1088218689],"type":"Point"}
}