{
  "type": "Feature",
  "properties": {
    "addr:full":"Nordwestbahnstrasse 75 Wien Wien 1200",
    "addr:housenumber":"75",
    "addr:postcode":"1200",
    "addr:street":"Nordwestbahnstrasse",
    "iso:country":"AT",
    "sg:address":"Nordwestbahnstrasse 75",
    "sg:city":"Wien",
    "sg:classifiers":[
        {
            "category":"Building & Trades",
            "subcategory":"Plumbing",
            "type":"Services"
        }
    ],
    "sg:phone":"+43 1 3329046",
    "sg:postcode":"1200",
    "sg:province":"Wien",
    "sg:tags":[
        "tub",
        "bath"
    ],
    "wof:name":"Paul Magyar",
    "wof:placetype":"venue"
},
  "geometry": {"coordinates":[16.3775691986,48.2321586609],"type":"Point"}
}