{
  "type": "Feature",
  "properties": {
    "addr:full":"Hauptstr 44 Leibnitz Steiermark 8430",
    "addr:housenumber":"44",
    "addr:postcode":"8430",
    "addr:street":"Hauptstr;Steiermark",
    "iso:country":"AT",
    "sg:address":"Hauptstr 44",
    "sg:city":"Leibnitz",
    "sg:orig_category":"Fenster",
    "sg:phone":"+43 4334 52749650",
    "sg:postcode":"8430",
    "sg:province":"Steiermark",
    "wof:name":"Zitz Walter GmbH",
    "wof:placetype":"venue"
},
  "geometry": {"coordinates":[15.5665903091,46.7781105042],"type":"Point"}
}