{
  "type": "Feature",
  "properties": {
    "iso:country":"AT",
    "sg:address":"Maria-Theresien-Str 24",
    "sg:city":"Wien",
    "sg:orig_category":"Forschungsinstitute",
    "sg:phone":"+43 1 3195750",
    "sg:postcode":"1010",
    "sg:province":"Wien",
    "wof:name":"Sozial\u00f6konomische Forschungsstelle SFS",
    "wof:placetype":"venue"
},
  "geometry": {"coordinates":[16.3671703339,48.2168617249],"type":"Point"}
}