{
  "type": "Feature",
  "properties": {
    "addr:full":"Nr 15 Prutz Tirol 6522",
    "addr:postcode":"6522",
    "addr:street":"Nr 15;Tirol",
    "iso:country":"AT",
    "sg:address":"Nr 15",
    "sg:city":"Prutz",
    "sg:orig_category":"Pensionen / Privatzimmer",
    "sg:phone":"+43 5472 6689",
    "sg:postcode":"6522",
    "sg:province":"Tirol",
    "wof:name":"Haus Schullehrer",
    "wof:placetype":"venue"
},
  "geometry": {"coordinates":[10.6638202667,47.0765533447],"type":"Point"}
}