{
  "type": "Feature",
  "properties": {
    "addr:full":"Sudetenpl 7 Gmunden Ober\u00f6sterreich 4810",
    "addr:housenumber":"7",
    "addr:postcode":"4810",
    "addr:street":"Sudetenpl;Oberoesterreich",
    "iso:country":"AT",
    "sg:address":"Sudetenpl 7",
    "sg:city":"Gmunden",
    "sg:orig_category":"Fleischhauereien",
    "sg:phone":"+43 761264257",
    "sg:postcode":"4810",
    "sg:province":"Ober\u00f6sterreich",
    "wof:name":"Gruber Hermann",
    "wof:placetype":"venue"
},
  "geometry": {"coordinates":[13.7884616852,47.9188079834],"type":"Point"}
}