{
  "type": "Feature",
  "properties": {
    "addr:full":"Nr 26 Tainach K\u00e4rnten 9121",
    "addr:postcode":"9121",
    "addr:street":"Nr 26 Tainach Kaernten",
    "iso:country":"AT",
    "sg:address":"Nr 26",
    "sg:city":"Tainach",
    "sg:orig_category":"Volksschulen",
    "sg:phone":"+43 4342 2481437",
    "sg:postcode":"9121",
    "sg:province":"K\u00e4rnten",
    "wof:name":"Volksschule",
    "wof:placetype":"venue"
},
  "geometry": {"coordinates":[14.5084590912,46.6561851501],"type":"Point"}
}