{
  "type": "Feature",
  "properties": {
    "addr:full":"Englen 155 Langenegg Vorarlberg 6941",
    "addr:housenumber":"155",
    "addr:postcode":"6941",
    "addr:street":"Langenegg Vorarlberg",
    "iso:country":"AT",
    "sg:address":"Englen 155",
    "sg:city":"Langenegg",
    "sg:orig_category":"Handelsagenturen",
    "sg:phone":"+43 4355 1330070",
    "sg:postcode":"6941",
    "sg:province":"Vorarlberg",
    "wof:name":"Krottenhammer Kurt",
    "wof:placetype":"venue"
},
  "geometry": {"coordinates":[9.8731508255,47.4696922302],"type":"Point"}
}