{
  "type": "Feature",
  "properties": {
    "addr:full":"Nr 48 Leogang Salzburg 5771",
    "addr:postcode":"5771",
    "addr:street":"Nr;Leogang",
    "iso:country":"AT",
    "sg:address":"Nr 48",
    "sg:city":"Leogang",
    "sg:orig_category":"Friseure U Frisiersalons",
    "sg:phone":"+43 6583 8230",
    "sg:postcode":"5771",
    "sg:province":"Salzburg",
    "wof:name":"Gruber Gertrude",
    "wof:placetype":"venue"
},
  "geometry": {"coordinates":[12.7606391907,47.4386634827],"type":"Point"}
}