{
  "type": "Feature",
  "properties": {
    "iso:country":"AT",
    "sg:address":"F\u00e4rberg 15/Rhombergs/Fabrik",
    "sg:city":"Dornbirn",
    "sg:orig_category":"Autovermietung",
    "sg:phone":"+43 5572 20901",
    "sg:postcode":"6850",
    "sg:province":"Vorarlberg",
    "wof:name":"Charter Line Autovermietung GmbH",
    "wof:placetype":"venue"
},
  "geometry": {"coordinates":[9.7437801361,47.4131889343],"type":"Point"}
}