{
  "type": "Feature",
  "properties": {
    "iso:country":"AT",
    "sg:address":"Bundesstr 101",
    "sg:city":"Lauterach",
    "sg:orig_category":"Rohrleitungen U Rohrleitungsbau",
    "sg:phone":"+43 4355 74840550",
    "sg:postcode":"6923",
    "sg:province":"Vorarlberg",
    "wof:name":"\u00d6sterle Edelstahlverarbeitung OHG",
    "wof:placetype":"venue"
},
  "geometry": {"coordinates":[9.7287549973,47.469455719],"type":"Point"}
}