{
  "type": "Feature",
  "properties": {
    "addr:full":"Gro\u00dfwiesenhart 22 St. Marienkirchen Ober\u00f6sterreich 4774",
    "addr:housenumber":"22",
    "addr:postcode":"4774",
    "addr:street":"Grosswiesenhart",
    "iso:country":"AT",
    "sg:address":"Gro\u00dfwiesenhart 22",
    "sg:city":"St. Marienkirchen",
    "sg:orig_category":"CarpenterS Work Supraregional",
    "sg:phone":"+43 7711 2827",
    "sg:postcode":"4774",
    "sg:province":"Ober\u00f6sterreich",
    "sg:website":"haderer.holzbau.at",
    "wof:name":"Wolfgang Haderer Zimmerei -Dachdeckerei-Holzbau",
    "wof:placetype":"venue"
},
  "geometry": {"coordinates":[13.4512290955,48.3879585266],"type":"Point"}
}