{
  "type": "Feature",
  "properties": {
    "addr:full":"Arbeiterg 6 Wien Wien 1050",
    "addr:housenumber":"6",
    "addr:postcode":"1050",
    "addr:street":"Arbeiterg",
    "iso:country":"AT",
    "sg:address":"Arbeiterg 6",
    "sg:city":"Wien",
    "sg:orig_category":"Elektroinstallationsunternehmen",
    "sg:phone":"+43 4315 445343",
    "sg:postcode":"1050",
    "sg:province":"Wien",
    "wof:name":"Elektro-Menhardt Elektroinstallations- u HandelsgesmbH",
    "wof:placetype":"venue"
},
  "geometry": {"coordinates":[16.3541622162,48.1870193481],"type":"Point"}
}