{
  "type": "Feature",
  "properties": {
    "addr:full":"Haunspergstrasse 36 Salzburg Salzburg 5020",
    "addr:housenumber":"36",
    "addr:postcode":"5020",
    "addr:street":"Haunspergstrasse;Salzburg",
    "iso:country":"AT",
    "sg:address":"Haunspergstrasse 36",
    "sg:city":"Salzburg",
    "sg:classifiers":[
        {
            "category":"Health Services",
            "subcategory":"Medical Lab",
            "type":"Services"
        }
    ],
    "sg:phone":"+43 662 8781150",
    "sg:postcode":"5020",
    "sg:province":"Salzburg",
    "sg:tags":[
        "disinfection",
        "room",
        "cleaning"
    ],
    "sg:website":"hectas.de",
    "wof:name":"Hectas Geb\u00e4udedienste Ges.m.b.H. & Co KG",
    "wof:placetype":"venue"
},
  "geometry": {"coordinates":[13.0392246246,47.8144760132],"type":"Point"}
}