{
  "type": "Feature",
  "properties": {
    "iso:country":"AT",
    "sg:address":"Am Klammbach 1a ",
    "sg:city":"Mariatrost",
    "sg:classifiers":[
        {
            "category":"Communications",
            "subcategory":"Newspaper",
            "type":"Services"
        }
    ],
    "sg:phone":"+43 4331 68142230",
    "sg:postcode":"8044",
    "sg:province":"Steiermark",
    "sg:tags":[
        "advertising"
    ],
    "wof:name":"ROBERT SCHAUER FILMPROD. GMBH",
    "wof:placetype":"venue"
},
  "geometry": {"coordinates":[15.4794616699,47.1017150879],"type":"Point"}
}