{
  "type": "Feature",
  "properties": {
    "addr:full":"D\u00f6llerhof 99 Abtenau Salzburg 5441",
    "addr:housenumber":"99",
    "addr:postcode":"5441",
    "addr:street":"Doellerhof;Salzburg",
    "iso:country":"AT",
    "sg:address":"D\u00f6llerhof 99",
    "sg:city":"Abtenau",
    "sg:orig_category":"Maler, Anstreicher U Lackierer",
    "sg:phone":"+43 6243 2734",
    "sg:postcode":"5441",
    "sg:province":"Salzburg",
    "wof:name":"Sch\u00f6rghofer Rudolf",
    "wof:placetype":"venue"
},
  "geometry": {"coordinates":[13.3463459015,47.5636177063],"type":"Point"}
}