{
  "type": "Feature",
  "properties": {
    "addr:full":"Dr.-Schroll-Str 15 Klagenfurt-Viktring K\u00e4rnten 9073",
    "addr:housenumber":"15",
    "addr:postcode":"9073",
    "addr:street":"Dr.-Schroll-Str;Kaernten",
    "iso:country":"AT",
    "sg:address":"Dr.-Schroll-Str 15",
    "sg:city":"Klagenfurt-Viktring",
    "sg:orig_category":"Handelsagenturen",
    "sg:phone":"+43 463 281114",
    "sg:postcode":"9073",
    "sg:province":"K\u00e4rnten",
    "wof:name":"Moritz Hans",
    "wof:placetype":"venue"
},
  "geometry": {"coordinates":[14.2719192505,46.5955963135],"type":"Point"}
}