{
  "type": "Feature",
  "properties": {
    "addr:full":"Nr 118 Traismauer Nieder\u00f6sterreich 3133",
    "addr:postcode":"3133",
    "addr:street":"Nr 118",
    "iso:country":"AT",
    "sg:address":"Nr 118",
    "sg:city":"Traismauer",
    "sg:classifiers":[
        {
            "category":"Home & Garden",
            "subcategory":"Building Materials",
            "type":"Retail Goods"
        }
    ],
    "sg:phone":"+43 4366 42734440",
    "sg:postcode":"3133",
    "sg:province":"Nieder\u00f6sterreich",
    "sg:tags":[
        "baustoffe",
        "-material",
        "u"
    ],
    "wof:name":"SKZ - Anwendungstechnik GmbH",
    "wof:placetype":"venue"
},
  "geometry": {"coordinates":[15.7439002991,48.34973526],"type":"Point"}
}