{
  "type": "Feature",
  "properties": {
    "addr:full":"Elisabethstr 61 Salzburg Salzburg 5020",
    "addr:housenumber":"61",
    "addr:postcode":"5020",
    "addr:street":"Elisabethstr;Salzburg",
    "iso:country":"AT",
    "sg:address":"Elisabethstr 61",
    "sg:city":"Salzburg",
    "sg:orig_category":"Blumeneinzelhandel",
    "sg:phone":"+43 662 824919",
    "sg:postcode":"5020",
    "sg:province":"Salzburg",
    "wof:name":"Knolly Bernadette",
    "wof:placetype":"venue"
},
  "geometry": {"coordinates":[13.0442371368,47.8183097839],"type":"Point"}
}