{
  "type": "Feature",
  "properties": {
    "addr:full":"Raiffeisenweg 2 Wilhering Ober\u00f6sterreich 4073",
    "addr:housenumber":"2",
    "addr:postcode":"4073",
    "addr:street":"Raiffeisenweg",
    "iso:country":"AT",
    "sg:address":"Raiffeisenweg 2",
    "sg:city":"Wilhering",
    "sg:orig_category":"Banken U Sparkassen",
    "sg:phone":"+43 4372 2622210",
    "sg:postcode":"4073",
    "sg:province":"Ober\u00f6sterreich",
    "wof:name":"Raiffeisenbank Eferding-Alkoven-Wilhering regGenmbH",
    "wof:placetype":"venue"
},
  "geometry": {"coordinates":[14.1664571762,48.2986488342],"type":"Point"}
}