{
  "type": "Feature",
  "properties": {
    "addr:full":"Rankg 12 Wien Wien 1160",
    "addr:housenumber":"12",
    "addr:postcode":"1160",
    "addr:street":"Rankg",
    "iso:country":"AT",
    "sg:address":"Rankg 12",
    "sg:city":"Wien",
    "sg:orig_category":"Tischlereien",
    "sg:phone":"+43 1 4931355",
    "sg:postcode":"1160",
    "sg:province":"Wien",
    "wof:name":"Beck Leopold GesmbH",
    "wof:placetype":"venue"
},
  "geometry": {"coordinates":[16.3085079193,48.2105941772],"type":"Point"}
}