{
  "type": "Feature",
  "properties": {
    "addr:full":"Haberlg 8 Tribuswinkel Nieder\u00f6sterreich 2512",
    "addr:housenumber":"8",
    "addr:postcode":"2512",
    "addr:street":"Haberlg",
    "iso:country":"AT",
    "sg:address":"Haberlg 8",
    "sg:city":"Tribuswinkel",
    "sg:orig_category":"Behindertenhilfsmittel",
    "sg:phone":"+43 2252 86473",
    "sg:postcode":"2512",
    "sg:province":"Nieder\u00f6sterreich",
    "wof:name":"BKI - Remus GmbH",
    "wof:placetype":"venue"
},
  "geometry": {"coordinates":[16.2946853638,47.9884490967],"type":"Point"}
}