{
  "type": "Feature",
  "properties": {
    "addr:full":"R Baum-Promenade 3 Mondsee Ober\u00f6sterreich 5310",
    "addr:housenumber":"3",
    "addr:postcode":"5310",
    "addr:street":"Oberoesterreich",
    "iso:country":"AT",
    "sg:address":"R Baum-Promenade 3",
    "sg:city":"Mondsee",
    "sg:orig_category":"Segel- U Seefahrtschulen",
    "sg:phone":"+43 6232 3548200",
    "sg:postcode":"5310",
    "sg:province":"Ober\u00f6sterreich",
    "wof:name":"Segelschule Mondsee",
    "wof:placetype":"venue"
},
  "geometry": {"coordinates":[13.3507919312,47.8514099121],"type":"Point"}
}