{
  "type": "Feature",
  "properties": {
    "addr:full":"Nr 41 Prinzersdorf Nieder\u00f6sterreich 3385",
    "addr:postcode":"3385",
    "addr:street":"Nr;Prinzersdorf",
    "iso:country":"AT",
    "sg:address":"Nr 41",
    "sg:city":"Prinzersdorf",
    "sg:orig_category":"Tankstellen",
    "sg:phone":"+43 2749 2343",
    "sg:postcode":"3385",
    "sg:province":"Nieder\u00f6sterreich",
    "wof:name":"OMV AG",
    "wof:placetype":"venue"
},
  "geometry": {"coordinates":[15.5011911392,48.1929016113],"type":"Point"}
}