{
  "type": "Feature",
  "properties": {
    "iso:country":"AT",
    "sg:address":"Eckwaldweg 105",
    "sg:city":"Altenmarkt im Pongau",
    "sg:classifiers":[
        {
            "category":"Taxi",
            "type":"Transportation"
        }
    ],
    "sg:phone":"+43 4364 5256560",
    "sg:postcode":"5541",
    "sg:province":"Salzburg",
    "sg:tags":[
        "personentransporte",
        "u"
    ],
    "wof:name":"Schober Karl OEG",
    "wof:placetype":"venue"
},
  "geometry": {"coordinates":[13.4419317245,47.3724594116],"type":"Point"}
}