{
  "type": "Feature",
  "properties": {
    "addr:full":"Pofelweg 3 G\u00f6fis Vorarlberg 6811",
    "addr:housenumber":"3",
    "addr:postcode":"6811",
    "addr:street":"Pofelweg",
    "iso:country":"AT",
    "sg:address":"Pofelweg 3",
    "sg:city":"G\u00f6fis",
    "sg:orig_category":"Baumeister",
    "sg:phone":"+43 5522 82317",
    "sg:postcode":"6811",
    "sg:province":"Vorarlberg",
    "wof:name":"Begle Josef Bmstr Ing",
    "wof:placetype":"venue"
},
  "geometry": {"coordinates":[-90.2027206421,36.7817497253],"type":"Point"}
}