{
  "type": "Feature",
  "properties": {
    "addr:full":"Feldkirchner Strasse 102 Klagenfurt K\u00e4rnten 9020",
    "addr:housenumber":"102",
    "addr:postcode":"9020",
    "addr:street":"Feldkirchner Strasse;Kaernten",
    "iso:country":"AT",
    "sg:address":"Feldkirchner Strasse 102",
    "sg:city":"Klagenfurt",
    "sg:classifiers":[
        {
            "category":"Structure",
            "subcategory":"Office Building",
            "type":"Public Place"
        }
    ],
    "sg:phone":"+43 463 23285",
    "sg:postcode":"9020",
    "sg:province":"K\u00e4rnten",
    "sg:tags":[
        "compact",
        "systems",
        "air conditioning"
    ],
    "wof:name":"Eduard Hohl Inh. G\u00fcnther Kr\u00f6ll",
    "wof:placetype":"venue"
},
  "geometry": {"coordinates":[14.2946243286,46.6377334595],"type":"Point"}
}