{
  "type": "Feature",
  "properties": {
    "addr:full":"Wiener Str 53 Hainfeld Nieder\u00f6sterreich 3170",
    "addr:postcode":"3170",
    "addr:street":"Niederoesterreich",
    "iso:country":"AT",
    "sg:address":"Wiener Str 53",
    "sg:city":"Hainfeld",
    "sg:orig_category":"Tischlereien",
    "sg:phone":"+43 2764 2628",
    "sg:postcode":"3170",
    "sg:province":"Nieder\u00f6sterreich",
    "wof:name":"H\u00f6fler Heinz",
    "wof:placetype":"venue"
},
  "geometry": {"coordinates":[15.7827243805,48.0337791443],"type":"Point"}
}