{
  "type": "Feature",
  "properties": {
    "addr:full":"Seilerg 5 Innsbruck Tirol 6020",
    "addr:housenumber":"5",
    "addr:postcode":"6020",
    "addr:street":"Seilerg;Tirol",
    "iso:country":"AT",
    "sg:address":"Seilerg 5",
    "sg:city":"Innsbruck",
    "sg:orig_category":"Juweliere, Gold- U Silberschmiede",
    "sg:phone":"+43 512 575817",
    "sg:postcode":"6020",
    "sg:province":"Tirol",
    "wof:name":"Zur Goldschmiedin",
    "wof:placetype":"venue"
},
  "geometry": {"coordinates":[11.3928918839,47.2679214478],"type":"Point"}
}