{
  "type": "Feature",
  "properties": {
    "iso:country":"AT",
    "sg:address":"Schlossparkstrasse 15",
    "sg:city":"Obersiebenbrunn",
    "sg:orig_category":"Pumps For Terotechnology",
    "sg:phone":"+43 2286 21110",
    "sg:postcode":"2283",
    "sg:province":"Nieder\u00f6sterreich",
    "wof:name":"Brunnenbau und Bodenaufschlie\u00dfungs Ges.m.b.H.",
    "wof:placetype":"venue"
},
  "geometry": {"coordinates":[16.7142887115,48.2722587585],"type":"Point"}
}