{
  "type": "Feature",
  "properties": {
    "addr:full":"Reininghausstr 5 Graz Steiermark 8020",
    "addr:housenumber":"5",
    "addr:postcode":"8020",
    "addr:street":"Reininghausstr",
    "iso:country":"AT",
    "sg:address":"Reininghausstr 5",
    "sg:city":"Graz",
    "sg:orig_category":"Unternehmensberatung",
    "sg:phone":"+43 4331 6319992",
    "sg:postcode":"8020",
    "sg:province":"Steiermark",
    "wof:name":"advirtual Unternehmensberatung GmbH",
    "wof:placetype":"venue"
},
  "geometry": {"coordinates":[15.4100351334,47.0659866333],"type":"Point"}
}