{
  "type": "Feature",
  "properties": {
    "addr:full":"Ampfererstr 44 Innsbruck Tirol 6020",
    "addr:housenumber":"44",
    "addr:postcode":"6020",
    "addr:street":"Ampfererstr;Tirol",
    "iso:country":"AT",
    "sg:address":"Ampfererstr 44",
    "sg:city":"Innsbruck",
    "sg:orig_category":"Restaurants: Persisch",
    "sg:phone":"+43 512 286006",
    "sg:postcode":"6020",
    "sg:province":"Tirol",
    "wof:name":"Shiraz Cafe-Restaurant",
    "wof:placetype":"venue"
},
  "geometry": {"coordinates":[11.3781309128,47.2624893188],"type":"Point"}
}