{
  "type": "Feature",
  "properties": {
    "iso:country":"AT",
    "sg:address":"Schildbach 60",
    "sg:city":"Hartberg",
    "sg:classifiers":[
        {
            "category":"Home & Garden",
            "subcategory":"Building Materials",
            "type":"Retail Goods"
        }
    ],
    "sg:phone":"+43 3332 62974",
    "sg:postcode":"8230",
    "sg:province":"Steiermark",
    "sg:tags":[
        "steel",
        "balcony"
    ],
    "wof:name":"Metallbau Wilfinger GmbH",
    "wof:placetype":"venue"
},
  "geometry": {"coordinates":[15.9492521286,47.2827720642],"type":"Point"}
}