{
  "type": "Feature",
  "properties": {
    "addr:full":"Karl-Sch\u00f6nherr-Str 10 Telfs Tirol 6410",
    "addr:housenumber":"10",
    "addr:postcode":"6410",
    "addr:street":"Karl-Schoenherr-Str;Tirol",
    "iso:country":"AT",
    "sg:address":"Karl-Sch\u00f6nherr-Str 10",
    "sg:city":"Telfs",
    "sg:orig_category":"Friseure U Frisiersalons",
    "sg:phone":"+43 4352 6263351",
    "sg:postcode":"6410",
    "sg:province":"Tirol",
    "wof:name":"Salon International",
    "wof:placetype":"venue"
},
  "geometry": {"coordinates":[11.0773630142,47.3149452209],"type":"Point"}
}