{
  "type": "Feature",
  "properties": {
    "addr:full":"Markt 74 St. Wolfgang im Salzkammergut Ober\u00f6sterreich 5360",
    "addr:housenumber":"74",
    "addr:postcode":"5360",
    "addr:street":"Markt",
    "iso:country":"AT",
    "sg:address":"Markt 74",
    "sg:city":"St. Wolfgang im Salzkammergut",
    "sg:classifiers":[
        {
            "category":"Travel",
            "subcategory":"Hotels & Motels",
            "type":"Entertainment"
        }
    ],
    "sg:phone":"+43 4361 3823060",
    "sg:postcode":"5360",
    "sg:province":"Ober\u00f6sterreich",
    "wof:name":"Weissen R\u00f6ssl Romantikhotel",
    "wof:placetype":"venue"
},
  "geometry": {"coordinates":[13.4466266632,47.7386398315],"type":"Point"}
}