{
  "type": "Feature",
  "properties": {
    "addr:full":"Aspangbahnstr 2 Laxenburg Nieder\u00f6sterreich 2361",
    "addr:housenumber":"2",
    "addr:postcode":"2361",
    "addr:street":"Aspangbahnstr",
    "iso:country":"AT",
    "sg:address":"Aspangbahnstr 2",
    "sg:city":"Laxenburg",
    "sg:orig_category":"Me\u00c3\u0178-, Steuer- U Regeltechnik",
    "sg:phone":"+43 2236 864136",
    "sg:postcode":"2361",
    "sg:province":"Nieder\u00f6sterreich",
    "wof:name":"Finder Relais Vertriebs GmbH",
    "wof:placetype":"venue"
},
  "geometry": {"coordinates":[16.3530426025,48.0751571655],"type":"Point"}
}