{
  "type": "Feature",
  "properties": {
    "addr:full":"Sparkassenpl. 1 Innsbruck Tirol 6020",
    "addr:housenumber":"1",
    "addr:postcode":"6020",
    "addr:street":"Sparkassenpl.;Tirol",
    "iso:country":"AT",
    "sg:address":"Sparkassenpl. 1",
    "sg:city":"Innsbruck",
    "sg:classifiers":[
        {
            "category":"Banks & Credit Unions",
            "subcategory":"Bank",
            "type":"Services"
        }
    ],
    "sg:phone":"+43 4351 25910271",
    "sg:postcode":"6020",
    "sg:province":"Tirol",
    "sg:tags":[
        "banking",
        "institution"
    ],
    "wof:name":"TIROLER SPARKASSE BANK AG",
    "wof:placetype":"venue"
},
  "geometry": {"coordinates":[11.3950386047,47.2662124634],"type":"Point"}
}