{
  "type": "Feature",
  "properties": {
    "addr:full":"Kilianstr 11 Wartberg an der Krems Ober\u00f6sterreich 4552",
    "addr:housenumber":"11",
    "addr:postcode":"4552",
    "addr:street":"Kilianstr",
    "iso:country":"AT",
    "sg:address":"Kilianstr 11",
    "sg:city":"Wartberg an der Krems",
    "sg:orig_category":"Innenausbau",
    "sg:phone":"+43 4375 877962",
    "sg:postcode":"4552",
    "sg:province":"Ober\u00f6sterreich",
    "sg:website":"wb-stuck.at",
    "wof:name":"Bachl Alfred Stuck- u Innenausbau GmbH",
    "wof:placetype":"venue"
},
  "geometry": {"coordinates":[14.1198348999,47.9904747009],"type":"Point"}
}