{
  "type": "Feature",
  "properties": {
    "addr:full":"Ramsau Hauptstr 21 Strengberg Nieder\u00f6sterreich 3314",
    "addr:housenumber":"21",
    "addr:postcode":"3314",
    "addr:street":"Ramsau Hauptstr",
    "iso:country":"AT",
    "sg:address":"Ramsau Hauptstr 21",
    "sg:city":"Strengberg",
    "sg:orig_category":"Elektroinstallationsunternehmen",
    "sg:phone":"+43 4374 3222830",
    "sg:postcode":"3314",
    "sg:province":"Nieder\u00f6sterreich",
    "wof:name":"Pfaffeneder Ilse",
    "wof:placetype":"venue"
},
  "geometry": {"coordinates":[14.6389818192,48.122089386],"type":"Point"}
}