{
  "type": "Feature",
  "properties": {
    "iso:country":"AT",
    "sg:address":"Kirchg 12",
    "sg:city":"Feldkirchen in K\u00e4rnten",
    "sg:orig_category":"Handarbeiten",
    "sg:phone":"+43 4276 2865",
    "sg:postcode":"9560",
    "sg:province":"K\u00e4rnten",
    "wof:name":"Arnold Christine",
    "wof:placetype":"venue"
},
  "geometry": {"coordinates":[14.0932769775,46.7253036499],"type":"Point"}
}