{
  "type": "Feature",
  "properties": {
    "addr:full":"Hauptstr 120 Reintal Nieder\u00f6sterreich 2276",
    "addr:housenumber":"120;2276",
    "addr:street":"Hauptstr;Reintal Niederoesterreich",
    "iso:country":"AT",
    "sg:address":"Hauptstr 120",
    "sg:city":"Reintal",
    "sg:orig_category":"Banken U Sparkassen",
    "sg:phone":"+43 4325 578412",
    "sg:postcode":"2276",
    "sg:province":"Nieder\u00f6sterreich",
    "wof:name":"Raiffeisenbank Bernhardsthal-Gro\u00dfkrut-Altlichtenwarth regGenmbH",
    "wof:placetype":"venue"
},
  "geometry": {"coordinates":[16.7853393555,48.6979141235],"type":"Point"}
}