{
  "type": "Feature",
  "properties": {
    "addr:full":"Parkstr 2 Biedermannsdorf Nieder\u00f6sterreich 2362",
    "addr:housenumber":"2",
    "addr:postcode":"2362",
    "addr:street":"Parkstr",
    "iso:country":"AT",
    "sg:address":"Parkstr 2",
    "sg:city":"Biedermannsdorf",
    "sg:orig_category":"\u00c3\u201erzte / F Allgemeinmedizin",
    "sg:phone":"+43 2236 73237",
    "sg:postcode":"2362",
    "sg:province":"Nieder\u00f6sterreich",
    "wof:name":"Fuhrich Hana MedR Dr",
    "wof:placetype":"venue"
},
  "geometry": {"coordinates":[16.3498439789,48.0844802856],"type":"Point"}
}