{
  "type": "Feature",
  "properties": {
    "addr:full":"Kircheng 2a Kirchschlag in der Buckligen Welt Nieder\u00f6sterreich 2860",
    "addr:housenumber":"2a",
    "addr:postcode":"2860",
    "addr:street":"Kircheng",
    "iso:country":"AT",
    "sg:address":"Kircheng 2a",
    "sg:city":"Kirchschlag in der Buckligen Welt",
    "sg:orig_category":"Fleischhauereien",
    "sg:phone":"+43 2646 2272",
    "sg:postcode":"2860",
    "sg:province":"Nieder\u00f6sterreich",
    "wof:name":"Fleischerei Imbi\u00df Partyservice - Peter Schermann",
    "wof:placetype":"venue"
},
  "geometry": {"coordinates":[16.2964286804,47.502407074],"type":"Point"}
}