{
  "type": "Feature",
  "properties": {
    "addr:full":"Laxenburger Strasse 151  Wien Wien 1100",
    "addr:housenumber":"151",
    "addr:postcode":"1100",
    "addr:street":"Laxenburger Strasse",
    "iso:country":"AT",
    "sg:address":"Laxenburger Strasse 151 ",
    "sg:city":"Wien",
    "sg:classifiers":[
        {
            "category":"Personal",
            "subcategory":"Beauty Salon",
            "type":"Services"
        }
    ],
    "sg:phone":"+43 1 614000",
    "sg:postcode":"1100",
    "sg:province":"Wien",
    "sg:tags":[
        "hair",
        "shampoo"
    ],
    "sg:website":"www.guhl.at",
    "wof:name":"Guhl Ikebana Kosmetika Gesellschaft m.b.H.",
    "wof:placetype":"venue"
},
  "geometry": {"coordinates":[16.3681735992,48.1636924744],"type":"Point"}
}