{
  "type": "Feature",
  "properties": {
    "addr:full":"Andreas Hofer-Str 3 Linz Ober\u00f6sterreich 4020",
    "addr:housenumber":"3",
    "addr:postcode":"4020",
    "iso:country":"AT",
    "sg:address":"Andreas Hofer-Str 3",
    "sg:city":"Linz",
    "sg:orig_category":"Matten U Mattenvermietung",
    "sg:phone":"+43 732 609466",
    "sg:postcode":"4020",
    "sg:province":"Ober\u00f6sterreich",
    "wof:name":"CITY MATS - LINDMOSER ReinigungsgesmbH",
    "wof:placetype":"venue"
},
  "geometry": {"coordinates":[14.2980480194,48.2858963013],"type":"Point"}
}