{
  "type": "Feature",
  "properties": {
    "addr:full":"Rauchfangkehrergasse 37 Wien Wien 1150",
    "addr:housenumber":"37",
    "addr:postcode":"1150",
    "addr:street":"Rauchfangkehrergasse",
    "iso:country":"AT",
    "sg:address":"Rauchfangkehrergasse 37",
    "sg:city":"Wien",
    "sg:classifiers":[
        {
            "category":"Food & Beverages",
            "subcategory":"Groceries & Convenience Stores",
            "type":"Retail Goods"
        }
    ],
    "sg:phone":"+43 1 89361590",
    "sg:postcode":"1150",
    "sg:province":"Wien",
    "sg:tags":[
        "cap",
        "bottle"
    ],
    "sg:website":"alka.at",
    "wof:name":"ALKA Verschluss GmbH",
    "wof:placetype":"venue"
},
  "geometry": {"coordinates":[16.326051712,48.1851844788],"type":"Point"}
}