{
  "type": "Feature",
  "properties": {
    "addr:full":"Siedlerstrasse 7 St. Valentin Nieder\u00f6sterreich 4300",
    "addr:housenumber":"7",
    "addr:postcode":"4300",
    "addr:street":"Siedlerstrasse",
    "iso:country":"AT",
    "sg:address":"Siedlerstrasse 7",
    "sg:city":"St. Valentin",
    "sg:classifiers":[
        {
            "category":"Banks & Credit Unions",
            "subcategory":"Bureau De Change",
            "type":"Services"
        }
    ],
    "sg:phone":"+43 664 3370537",
    "sg:postcode":"4300",
    "sg:province":"Nieder\u00f6sterreich",
    "sg:tags":[
        "solution",
        "complete",
        "internet"
    ],
    "sg:website":"global-webservice.at",
    "wof:name":"Global-Werbeservice",
    "wof:placetype":"venue"
},
  "geometry": {"coordinates":[14.5203409195,48.1732330322],"type":"Point"}
}