{
  "type": "Feature",
  "properties": {
    "iso:country":"AT",
    "sg:address":"Naglerg 25",
    "sg:city":"Wien",
    "sg:orig_category":"Badezimmer U Badezimmereinrichtungen",
    "sg:phone":"+43 1 5331209",
    "sg:postcode":"1010",
    "sg:province":"Wien",
    "wof:name":"Klomfar Helmut F A GesmbH",
    "wof:placetype":"venue"
},
  "geometry": {"coordinates":[16.3666324615,48.2106628418],"type":"Point"}
}