{
  "type": "Feature",
  "properties": {
    "iso:country":"AT",
    "sg:address":"Kaplanweg 2",
    "sg:city":"Weiz",
    "sg:orig_category":"Lebensmittel / Einzelhandel",
    "sg:phone":"+43 3172 44900",
    "sg:postcode":"8160",
    "sg:province":"Steiermark",
    "wof:name":"MONDO Lebensmitteldiskonter",
    "wof:placetype":"venue"
},
  "geometry": {"coordinates":[15.6377468109,47.2065696716],"type":"Point"}
}