{
  "type": "Feature",
  "properties": {
    "iso:country":"AT",
    "sg:address":"Reinholdweg 7",
    "sg:city":"Klagenfurt",
    "sg:orig_category":"Alarmanlagen U Sicherheitssysteme",
    "sg:phone":"+43 4346 3235500",
    "sg:postcode":"9020",
    "sg:province":"K\u00e4rnten",
    "wof:name":"AARES Handels- u WartungsgesmbH",
    "wof:placetype":"venue"
},
  "geometry": {"coordinates":[14.3007354736,46.6084976196],"type":"Point"}
}