{
  "type": "Feature",
  "properties": {
    "addr:full":"Erzabtei St. Peter 5010",
    "addr:postcode":"5010",
    "addr:street":"St. Peter",
    "iso:country":"AT",
    "sg:address":"Erzabtei St. Peter",
    "sg:orig_category":"Medien, Verlage",
    "sg:postcode":"5010",
    "sg:website":"http://members.aon.at/lkoe/",
    "wof:name":"Verlag St. Peter",
    "wof:placetype":"venue"
},
  "geometry": {"coordinates":[13.0433702469,47.8006706238],"type":"Point"}
}