{
  "type": "Feature",
  "properties": {
    "iso:country":"AT",
    "sg:address":"Europastr 5",
    "sg:city":"Leobersdorf",
    "sg:orig_category":"Lebensmittel / Einzelhandel",
    "sg:phone":"+43 2256 20346",
    "sg:postcode":"2544",
    "sg:province":"Nieder\u00f6sterreich",
    "wof:name":"R\u00f6ssler-Lichtenauer GesmbH",
    "wof:placetype":"venue"
},
  "geometry": {"coordinates":[16.2040557861,47.9309577942],"type":"Point"}
}