{
  "type": "Feature",
  "properties": {
    "addr:full":"Hauptstr 25a St. Johann im Pongau Salzburg 5600",
    "addr:housenumber":"25a",
    "addr:postcode":"5600",
    "addr:street":"Hauptstr;Salzburg",
    "iso:country":"AT",
    "sg:address":"Hauptstr 25a",
    "sg:city":"St. Johann im Pongau",
    "sg:orig_category":"Osteopathie",
    "sg:phone":"+43 4364 126686",
    "sg:postcode":"5600",
    "sg:province":"Salzburg",
    "wof:name":"Geisler Marita Dipl-Phys",
    "wof:placetype":"venue"
},
  "geometry": {"coordinates":[13.204000473,47.3491287231],"type":"Point"}
}