{
  "type": "Feature",
  "properties": {
    "addr:full":"Gr\u00fcneg 7 Wiener Neudorf Nieder\u00f6sterreich 2351",
    "addr:housenumber":"7",
    "addr:postcode":"2351",
    "addr:street":"Grueneg",
    "iso:country":"AT",
    "sg:address":"Gr\u00fcneg 7",
    "sg:city":"Wiener Neudorf",
    "sg:orig_category":"Installationsunternehmen",
    "sg:phone":"+43 2236 61944",
    "sg:postcode":"2351",
    "sg:province":"Nieder\u00f6sterreich",
    "wof:name":"Brandau & Faustmann GesmbH",
    "wof:placetype":"venue"
},
  "geometry": {"coordinates":[16.3183326721,48.0863113403],"type":"Point"}
}