{
  "type": "Feature",
  "properties": {
    "addr:full":"Prutz Tirol 6522",
    "addr:postcode":"6522",
    "addr:street":"Tirol",
    "iso:country":"AT",
    "sg:city":"Prutz",
    "sg:classifiers":[
        {
            "category":"Park",
            "subcategory":"Provincial",
            "type":"Public Place"
        }
    ],
    "sg:phone":"+43 4354 726546",
    "sg:postcode":"6522",
    "sg:province":"Tirol",
    "sg:tags":[
        "u",
        "ski-",
        "snowboardschulen"
    ],
    "wof:name":"Schischule Top",
    "wof:placetype":"venue"
},
  "geometry": {"coordinates":[10.6765298843,47.0538902283],"type":"Point"}
}