{
  "type": "Feature",
  "properties": {
    "addr:full":"Scherenbrandtnerhofstr 5 Salzburg Salzburg 5020",
    "addr:housenumber":"5",
    "addr:postcode":"5020",
    "addr:street":"Scherenbrandtnerhofstr;Salzburg",
    "iso:country":"AT",
    "sg:address":"Scherenbrandtnerhofstr 5",
    "sg:city":"Salzburg",
    "sg:classifiers":[
        {
            "category":"Utilities",
            "subcategory":"Recycling",
            "type":"Services"
        }
    ],
    "sg:phone":"+43 4366 246955",
    "sg:postcode":"5020",
    "sg:province":"Salzburg",
    "wof:name":"Salzburger Reststoffverwertung GmbH",
    "wof:placetype":"venue"
},
  "geometry": {"coordinates":[13.0593452454,47.8234367371],"type":"Point"}
}