{
  "type": "Feature",
  "properties": {
    "addr:full":"W\u00e4hringer Str 102 Wien Wien 1180",
    "addr:housenumber":"102",
    "addr:postcode":"1180",
    "addr:street":"Str",
    "iso:country":"AT",
    "sg:address":"W\u00e4hringer Str 102",
    "sg:city":"Wien",
    "sg:orig_category":"Boutiquen",
    "sg:phone":"+43 1 4783988",
    "sg:postcode":"1180",
    "sg:province":"Wien",
    "wof:name":"Splendid Check Out",
    "wof:placetype":"venue"
},
  "geometry": {"coordinates":[16.3457431793,48.2258377075],"type":"Point"}
}