{
  "type": "Feature",
  "properties": {
    "iso:country":"AT",
    "sg:address":"Feldg 8",
    "sg:city":"Kapfenberg",
    "sg:orig_category":"Politische Parteien",
    "sg:phone":"+43 3862 22417",
    "sg:postcode":"8605",
    "sg:province":"Steiermark",
    "wof:name":"Kommunistische Partei \u00f6sterreichs Bezirksltg Bruck a Mur, Kapfenberg",
    "wof:placetype":"venue"
},
  "geometry": {"coordinates":[15.2912454605,47.4438438416],"type":"Point"}
}