{
  "type": "Feature",
  "properties": {
    "addr:full":"Oberkirchbacher Str 11 Hintersdorf Nieder\u00f6sterreich 3413",
    "addr:housenumber":"11",
    "addr:postcode":"3413",
    "addr:street":"Str;Niederoesterreich",
    "iso:country":"AT",
    "sg:address":"Oberkirchbacher Str 11",
    "sg:city":"Hintersdorf",
    "sg:orig_category":"Pensionen / Privatzimmer",
    "sg:phone":"+43 4322 426549",
    "sg:postcode":"3413",
    "sg:province":"Nieder\u00f6sterreich",
    "wof:name":"Enzelsberger Anton u Brigitte",
    "wof:placetype":"venue"
},
  "geometry": {"coordinates":[16.1952419281,48.2916107178],"type":"Point"}
}