{
  "type": "Feature",
  "properties": {
    "iso:country":"AT",
    "sg:address":"Josef-Kr\u00e4nzl-Str",
    "sg:city":"Ried im Innkreis",
    "sg:orig_category":"Kinderbetreuung",
    "sg:phone":"+43 7752 901511",
    "sg:postcode":"4910",
    "sg:province":"Ober\u00f6sterreich",
    "wof:name":"Kindergarten d Stadtgemeinde Ried",
    "wof:placetype":"venue"
},
  "geometry": {"coordinates":[13.4837503433,48.203414917],"type":"Point"}
}