{
  "type": "Feature",
  "properties": {
    "addr:full":"Obermarkt 81 Reutte Tirol 6600",
    "addr:housenumber":"81",
    "addr:postcode":"6600",
    "addr:street":"Obermarkt;Tirol",
    "iso:country":"AT",
    "sg:address":"Obermarkt 81",
    "sg:city":"Reutte",
    "sg:orig_category":"Blumeneinzelhandel",
    "sg:phone":"+43 5672 64310",
    "sg:postcode":"6600",
    "sg:province":"Tirol",
    "wof:name":"Sax Helmut",
    "wof:placetype":"venue"
},
  "geometry": {"coordinates":[10.720990181,47.4847259521],"type":"Point"}
}