{
  "type": "Feature",
  "properties": {
    "addr:full":"Mitterland 100 Thiersee Tirol 6335",
    "addr:housenumber":"100",
    "addr:postcode":"6335",
    "addr:street":"Mitterland;Tirol",
    "iso:country":"AT",
    "sg:address":"Mitterland 100",
    "sg:city":"Thiersee",
    "sg:classifiers":[
        {
            "category":"Professional",
            "subcategory":"Computer Services",
            "type":"Services"
        }
    ],
    "sg:phone":"+43 5376 431411",
    "sg:postcode":"6335",
    "sg:province":"Tirol",
    "sg:tags":[
        "software"
    ],
    "wof:name":"ASKO Software Gesellschaft m.b.H.",
    "wof:placetype":"venue"
},
  "geometry": {"coordinates":[12.079744339,47.5801620483],"type":"Point"}
}