{
  "type": "Feature",
  "properties": {
    "addr:full":"10.Oktober-Str 11 Treibach-Althofen K\u00e4rnten 9330",
    "addr:housenumber":"11",
    "addr:postcode":"9330",
    "addr:street":"10.Oktober-Str;Kaernten",
    "iso:country":"AT",
    "sg:address":"10.Oktober-Str 11",
    "sg:city":"Treibach-Althofen",
    "sg:orig_category":"Tankstellen",
    "sg:phone":"+43 4262 22380",
    "sg:postcode":"9330",
    "sg:province":"K\u00e4rnten",
    "wof:name":"OMV AG",
    "wof:placetype":"venue"
},
  "geometry": {"coordinates":[14.4673042297,46.8717651367],"type":"Point"}
}