{
  "type": "Feature",
  "properties": {
    "addr:full":"Swarovskistr 13 Schwaz Tirol 6130",
    "addr:housenumber":"13",
    "addr:postcode":"6130",
    "addr:street":"Swarovskistr;Tirol",
    "iso:country":"AT",
    "sg:address":"Swarovskistr 13",
    "sg:city":"Schwaz",
    "sg:orig_category":"Blumeneinzelhandel",
    "sg:phone":"+43 5242 74003",
    "sg:postcode":"6130",
    "sg:province":"Tirol",
    "wof:name":"Blumenservice",
    "wof:placetype":"venue"
},
  "geometry": {"coordinates":[11.703701973,47.3451690674],"type":"Point"}
}