{
  "type": "Feature",
  "properties": {
    "iso:country":"AT",
    "sg:address":"Swarovskistr 13",
    "sg:city":"Schwaz",
    "sg:orig_category":"Blumeneinzelhandel",
    "sg:phone":"+43 5242 74003",
    "sg:postcode":"6130",
    "sg:province":"Tirol",
    "wof:name":"Blumenservice",
    "wof:placetype":"venue"
},
  "geometry": {"coordinates":[11.703701973,47.3451690674],"type":"Point"}
}