{
  "type": "Feature",
  "properties": {
    "addr:full":"Schillerstr 23 Hadersdorf am Kamp Nieder\u00f6sterreich 3493",
    "addr:housenumber":"23",
    "addr:postcode":"3493",
    "addr:street":"Schillerstr;Niederoesterreich",
    "iso:country":"AT",
    "sg:address":"Schillerstr 23",
    "sg:city":"Hadersdorf am Kamp",
    "sg:orig_category":"Friseure U Frisiersalons",
    "sg:phone":"+43 4327 355745",
    "sg:postcode":"3493",
    "sg:province":"Nieder\u00f6sterreich",
    "wof:name":"Jurasek Gabriele",
    "wof:placetype":"venue"
},
  "geometry": {"coordinates":[15.7250871658,48.4547271729],"type":"Point"}
}