{
  "type": "Feature",
  "properties": {
    "addr:full":"Viktringer Ring 43 Klagenfurt K\u00e4rnten 9020",
    "addr:housenumber":"43",
    "addr:postcode":"9020",
    "addr:street":"Viktringer Ring;Kaernten",
    "iso:country":"AT",
    "sg:address":"Viktringer Ring 43",
    "sg:city":"Klagenfurt",
    "sg:orig_category":"Personalbereitstellung",
    "sg:phone":"+43 463 504688",
    "sg:postcode":"9020",
    "sg:province":"K\u00e4rnten",
    "wof:name":"TTI Personaldienstleistung GmbH",
    "wof:placetype":"venue"
},
  "geometry": {"coordinates":[14.3066558838,46.6205177307],"type":"Point"}
}