{
  "type": "Feature",
  "properties": {
    "addr:full":"Schulg 34 Dornbirn Vorarlberg 6850",
    "addr:housenumber":"34",
    "addr:postcode":"6850",
    "addr:street":"Schulg",
    "iso:country":"AT",
    "sg:address":"Schulg 34",
    "sg:city":"Dornbirn",
    "sg:orig_category":"Eissalons",
    "sg:phone":"+43 5572 23221",
    "sg:postcode":"6850",
    "sg:province":"Vorarlberg",
    "wof:name":"Eisdiele-Silvretta",
    "wof:placetype":"venue"
},
  "geometry": {"coordinates":[9.7406358719,47.4127807617],"type":"Point"}
}