{
  "type": "Feature",
  "properties": {
    "addr:full":"Brunnleitweg 18a St. Gilgen Salzburg 5340",
    "addr:housenumber":"18a",
    "addr:postcode":"5340",
    "addr:street":"Brunnleitweg",
    "iso:country":"AT",
    "sg:address":"Brunnleitweg 18a",
    "sg:city":"St. Gilgen",
    "sg:classifiers":[
        {
            "category":"Building & Trades",
            "subcategory":"Plumbing",
            "type":"Services"
        }
    ],
    "sg:phone":"+43 6227 7157",
    "sg:postcode":"5340",
    "sg:province":"Salzburg",
    "sg:tags":[
        "supraregional",
        "gas"
    ],
    "wof:name":"Heinrich Nobis",
    "wof:placetype":"venue"
},
  "geometry": {"coordinates":[13.3651885986,47.769859314],"type":"Point"}
}