{
  "type": "Feature",
  "properties": {
    "addr:full":"Salzburger Str 5 St. Gilgen Salzburg 5340",
    "addr:housenumber":"5",
    "addr:postcode":"5340",
    "addr:street":"Salzburger Str",
    "iso:country":"AT",
    "sg:address":"Salzburger Str 5",
    "sg:city":"St. Gilgen",
    "sg:orig_category":"Tischlereien",
    "sg:phone":"+43 6227 2155",
    "sg:postcode":"5340",
    "sg:province":"Salzburg",
    "wof:name":"Luschan Michael",
    "wof:placetype":"venue"
},
  "geometry": {"coordinates":[13.3632535934,47.7671356201],"type":"Point"}
}