{
  "type": "Feature",
  "properties": {
    "addr:full":"Eurofunkstrasse 2 St. Johann im Pongau Salzburg 5600",
    "addr:housenumber":"2",
    "addr:postcode":"5600",
    "addr:street":"Eurofunkstrasse;Salzburg",
    "iso:country":"AT",
    "sg:address":"Eurofunkstrasse 2",
    "sg:city":"St. Johann im Pongau",
    "sg:classifiers":[
        {
            "category":"Professional",
            "subcategory":"Computer Services",
            "type":"Services"
        }
    ],
    "sg:phone":"+43 6412 62230",
    "sg:postcode":"5600",
    "sg:province":"Salzburg",
    "sg:tags":[
        "administration",
        "software"
    ],
    "sg:website":"eurofunk.com",
    "wof:name":"eurofunk KAPPACHER Ges.m.b.H.",
    "wof:placetype":"venue"
},
  "geometry": {"coordinates":[13.2003879547,47.3432731628],"type":"Point"}
}