{
  "type": "Feature",
  "properties": {
    "addr:full":"Sparkassengasse 3 Krems an der Donau Nieder\u00f6sterreich 3500",
    "addr:housenumber":"3",
    "addr:postcode":"3500",
    "addr:street":"Sparkassengasse",
    "iso:country":"AT",
    "sg:address":"Sparkassengasse 3",
    "sg:city":"Krems an der Donau",
    "sg:classifiers":[
        {
            "category":"Shopping",
            "subcategory":"Mobile Phones",
            "type":"Retail Goods"
        }
    ],
    "sg:phone":"+43 699 10917869",
    "sg:postcode":"3500",
    "sg:province":"Nieder\u00f6sterreich",
    "sg:tags":[
        "trade",
        "accessory"
    ],
    "sg:website":"handymillenium.com",
    "wof:name":"Kocaman KEG",
    "wof:placetype":"venue"
},
  "geometry": {"coordinates":[15.5986223221,48.4102935791],"type":"Point"}
}