{
  "type": "Feature",
  "properties": {
    "addr:full":"Gudrunstr 143/2/10 Wien Wien 1100",
    "addr:housenumber":"143 / 2 / 10",
    "addr:postcode":"1100",
    "iso:country":"AT",
    "sg:address":"Gudrunstr 143/2/10",
    "sg:city":"Wien",
    "sg:orig_category":"Besonderes",
    "sg:phone":"+43 4366 44730868",
    "sg:postcode":"1100",
    "sg:province":"Wien",
    "sg:website":"beziehungsweise.biz",
    "wof:name":"Beziehungsweise - Konfliktl\u00f6sungen Mag Gabriela Sticht-Truchlik",
    "wof:placetype":"venue"
},
  "geometry": {"coordinates":[16.3744049072,48.1782684326],"type":"Point"}
}