{
  "type": "Feature",
  "properties": {
    "addr:full":"Nr 47 Galt\u00fcr Tirol 6563",
    "addr:postcode":"6563",
    "addr:street":"Nr 47 Galtuer Tirol",
    "iso:country":"AT",
    "sg:address":"Nr 47",
    "sg:city":"Galt\u00fcr",
    "sg:classifiers":[
        {
            "category":"Travel",
            "subcategory":"Hotels & Motels",
            "type":"Entertainment"
        }
    ],
    "sg:phone":"+43 5443 82320",
    "sg:postcode":"6563",
    "sg:province":"Tirol",
    "wof:name":"Hotel - Gasthof zum R\u00f6ssle",
    "wof:placetype":"venue"
},
  "geometry": {"coordinates":[9.2292995453,46.4031715393],"type":"Point"}
}