{
  "type": "Feature",
  "properties": {
    "iso:country":"AT",
    "sg:address":"K\u00fchbachstr. 4",
    "sg:city":"Neukirchen am Walde",
    "sg:classifiers":[
        {
            "category":"Food & Beverages",
            "subcategory":"Groceries & Convenience Stores",
            "type":"Retail Goods"
        }
    ],
    "sg:phone":"+43 4372 783362",
    "sg:postcode":"4724",
    "sg:province":"Ober\u00f6sterreich",
    "sg:tags":[
        "product",
        "related"
    ],
    "wof:name":"RUDOLF BERGHAMMER",
    "wof:placetype":"venue"
},
  "geometry": {"coordinates":[13.7808732986,48.4049911499],"type":"Point"}
}