{
  "type": "Feature",
  "properties": {
    "addr:full":"Donaufelder Str 128 Wien Wien 1210",
    "addr:housenumber":"128",
    "addr:postcode":"1210",
    "iso:country":"AT",
    "sg:address":"Donaufelder Str 128",
    "sg:city":"Wien",
    "sg:orig_category":"Tankstellen",
    "sg:phone":"+43 1 2565517",
    "sg:postcode":"1210",
    "sg:province":"Wien",
    "wof:name":"Shell Austria GmbH",
    "wof:placetype":"venue"
},
  "geometry": {"coordinates":[16.4252853394,48.2523956299],"type":"Point"}
}