{
  "type": "Feature",
  "properties": {
    "addr:full":"Puchberger Str 64 Wels Ober\u00f6sterreich 4600",
    "addr:housenumber":"64",
    "addr:postcode":"4600",
    "addr:street":"Str;Oberoesterreich",
    "iso:country":"AT",
    "sg:address":"Puchberger Str 64",
    "sg:city":"Wels",
    "sg:orig_category":"Blumeneinzelhandel",
    "sg:phone":"+43 7242 910676",
    "sg:postcode":"4600",
    "sg:province":"Ober\u00f6sterreich",
    "wof:name":"Adam Friedrich",
    "wof:placetype":"venue"
},
  "geometry": {"coordinates":[14.0234489441,48.1812515259],"type":"Point"}
}