{
  "type": "Feature",
  "properties": {
    "addr:full":"St.-Peter-Str 22 Klagenfurt K\u00e4rnten 9020",
    "addr:housenumber":"22",
    "addr:postcode":"9020",
    "addr:street":"St.-Peter-Str;Kaernten",
    "iso:country":"AT",
    "sg:address":"St.-Peter-Str 22",
    "sg:city":"Klagenfurt",
    "sg:orig_category":"Gasversorgungsunternehmen",
    "sg:phone":"+43 463 521312",
    "sg:postcode":"9020",
    "sg:province":"K\u00e4rnten",
    "wof:name":"Stadtwerke Klagenfurt AG - Gaswerk",
    "wof:placetype":"venue"
},
  "geometry": {"coordinates":[14.3249149323,46.6185264587],"type":"Point"}
}