{
  "type": "Feature",
  "properties": {
    "iso:country":"AT",
    "sg:address":"Hauptstr 40",
    "sg:city":"G\u00f6tzendorf an der Leitha",
    "sg:orig_category":"Fleischhauereien",
    "sg:phone":"+43 4321 692281",
    "sg:postcode":"2434",
    "sg:province":"Nieder\u00f6sterreich",
    "wof:name":"Danzinger Josef",
    "wof:placetype":"venue"
},
  "geometry": {"coordinates":[-101.6332702637,46.3577537537],"type":"Point"}
}