{
  "type": "Feature",
  "properties": {
    "addr:full":"Mariahilfer Str 9/4 Wien Wien 1060",
    "addr:housenumber":"9 / 4",
    "addr:postcode":"1060",
    "addr:street":"Str",
    "iso:country":"AT",
    "sg:address":"Mariahilfer Str 9/4",
    "sg:city":"Wien",
    "sg:orig_category":"Architekten",
    "sg:phone":"+43 1 5851868",
    "sg:postcode":"1060",
    "sg:province":"Wien",
    "wof:name":"Driendl Georg Arch Mag",
    "wof:placetype":"venue"
},
  "geometry": {"coordinates":[16.3599224091,48.201259613],"type":"Point"}
}