{
  "type": "Feature",
  "properties": {
    "iso:country":"AT",
    "sg:address":"Nr 37",
    "sg:city":"Kl\u00f6ch",
    "sg:orig_category":"Rebschulen",
    "sg:phone":"+43 3475 2248",
    "sg:postcode":"8493",
    "sg:province":"Steiermark",
    "wof:name":"Lamprecht Fritz",
    "wof:placetype":"venue"
},
  "geometry": {"coordinates":[15.9466428757,46.7218742371],"type":"Point"}
}