{
  "type": "Feature",
  "properties": {
    "addr:full":"Rheinstr 42 Bregenz Vorarlberg 6900",
    "addr:housenumber":"42",
    "addr:postcode":"6900",
    "addr:street":"Rheinstr",
    "iso:country":"AT",
    "sg:address":"Rheinstr 42",
    "sg:city":"Bregenz",
    "sg:orig_category":"Versicherungsunternehmen",
    "sg:phone":"+43 5574 738880",
    "sg:postcode":"6900",
    "sg:province":"Vorarlberg",
    "wof:name":"Wiener St\u00e4dtische Allgemeine Versicherung AG",
    "wof:placetype":"venue"
},
  "geometry": {"coordinates":[9.7236356735,47.4968833923],"type":"Point"}
}