{
  "type": "Feature",
  "properties": {
    "addr:full":"Prager Str 133 Wien Wien 1210",
    "addr:housenumber":"133",
    "addr:postcode":"1210",
    "iso:country":"AT",
    "sg:address":"Prager Str 133",
    "sg:city":"Wien",
    "sg:orig_category":"Autoreparatur, Autohandel",
    "sg:phone":"+43 1 277140",
    "sg:postcode":"1210",
    "sg:province":"Wien",
    "wof:name":"Porsche Inter Auto KG - Zweigniederlassung Porsche Wien Pragerstra\u00dfe",
    "wof:placetype":"venue"
},
  "geometry": {"coordinates":[16.3892307281,48.2741012573],"type":"Point"}
}