{
  "type": "Feature",
  "properties": {
    "addr:full":"Hofriedenstr 2 Lochau Vorarlberg 6911",
    "addr:housenumber":"2",
    "addr:postcode":"6911",
    "addr:street":"Hofriedenstr",
    "iso:country":"AT",
    "sg:address":"Hofriedenstr 2",
    "sg:city":"Lochau",
    "sg:orig_category":"Lottokollekturen",
    "sg:phone":"+43 5574 43717",
    "sg:postcode":"6911",
    "sg:province":"Vorarlberg",
    "wof:name":"Schimacek Franz",
    "wof:placetype":"venue"
},
  "geometry": {"coordinates":[9.7518844604,47.5312004089],"type":"Point"}
}