{
  "type": "Feature",
  "properties": {
    "addr:full":"Bauernstr 11 Wels Ober\u00f6sterreich 4600",
    "addr:housenumber":"11",
    "addr:postcode":"4600",
    "addr:street":"Bauernstr;Oberoesterreich",
    "iso:country":"AT",
    "sg:address":"Bauernstr 11",
    "sg:city":"Wels",
    "sg:orig_category":"Reinigungsbedarf U Reinigungsmittel",
    "sg:phone":"+43 7242 428990",
    "sg:postcode":"4600",
    "sg:province":"Ober\u00f6sterreich",
    "wof:name":"Kleencare Hygiene GesmbH",
    "wof:placetype":"venue"
},
  "geometry": {"coordinates":[14.0100107193,48.1511917114],"type":"Point"}
}