{
  "type": "Feature",
  "properties": {
    "addr:full":"Schildbach 78 Hartberg Steiermark 8230",
    "addr:housenumber":"78",
    "addr:postcode":"8230",
    "addr:street":"Schildbach",
    "iso:country":"AT",
    "sg:address":"Schildbach 78",
    "sg:city":"Hartberg",
    "sg:orig_category":"Autohandel",
    "sg:phone":"+43 3332 614000",
    "sg:postcode":"8230",
    "sg:province":"Steiermark",
    "wof:name":"Auto Center Hartberg GmbH",
    "wof:placetype":"venue"
},
  "geometry": {"coordinates":[15.9531183243,47.270072937],"type":"Point"}
}