{
  "type": "Feature",
  "properties": {
    "addr:full":"Hauptstr 13 Warth Nieder\u00f6sterreich 2831",
    "addr:housenumber":"13",
    "addr:postcode":"2831",
    "addr:street":"Hauptstr",
    "iso:country":"AT",
    "sg:address":"Hauptstr 13",
    "sg:city":"Warth",
    "sg:orig_category":"Banken U Sparkassen",
    "sg:phone":"+43 4326 292370",
    "sg:postcode":"2831",
    "sg:province":"Nieder\u00f6sterreich",
    "wof:name":"Raiffeisenbank Warth regGenmbH - Zweigstelle Scheiblingkirchen",
    "wof:placetype":"venue"
},
  "geometry": {"coordinates":[16.1305046082,47.6614608765],"type":"Point"}
}