{
  "type": "Feature",
  "properties": {
    "addr:full":"Gernlandweg 26 Leonding Ober\u00f6sterreich 4060",
    "addr:housenumber":"26",
    "addr:postcode":"4060",
    "addr:street":"Gernlandweg",
    "iso:country":"AT",
    "sg:address":"Gernlandweg 26",
    "sg:city":"Leonding",
    "sg:orig_category":"Wasseraufbereitung U -Reinigung",
    "sg:phone":"+43 4373 26736620",
    "sg:postcode":"4060",
    "sg:province":"Ober\u00f6sterreich",
    "wof:name":"STEFCO-engineering Austria",
    "wof:placetype":"venue"
},
  "geometry": {"coordinates":[14.2542638779,48.2784461975],"type":"Point"}
}