{
  "type": "Feature",
  "properties": {
    "iso:country":"AT",
    "sg:address":"G\u00f6rtschitztalstr 22",
    "sg:city":"Klagenfurt",
    "sg:orig_category":"Waren Aller Art",
    "sg:phone":"+43 463 717700",
    "sg:postcode":"9020",
    "sg:province":"K\u00e4rnten",
    "wof:name":"METRO Cash & Carry \u00f6sterreich GmbH",
    "wof:placetype":"venue"
},
  "geometry": {"coordinates":[14.3711395264,46.6371154785],"type":"Point"}
}