{
  "type": "Feature",
  "properties": {
    "iso:country":"AT",
    "sg:address":"Seideng 26",
    "sg:city":"Wien",
    "sg:classifiers":[
        {
            "category":"Professional",
            "subcategory":"Computer Services",
            "type":"Services"
        }
    ],
    "sg:phone":"+43 1 52329460",
    "sg:postcode":"1070",
    "sg:province":"Wien",
    "sg:tags":[
        "software"
    ],
    "wof:name":"Fontshop HandelsgesmbH",
    "wof:placetype":"venue"
},
  "geometry": {"coordinates":[16.3421497345,48.200553894],"type":"Point"}
}