{
  "type": "Feature",
  "properties": {
    "addr:full":"Sch\u00f6pfstr 4 Innsbruck Tirol 6020",
    "addr:housenumber":"4",
    "addr:postcode":"6020",
    "addr:street":"Schoepfstr;Tirol",
    "iso:country":"AT",
    "sg:address":"Sch\u00f6pfstr 4",
    "sg:city":"Innsbruck",
    "sg:orig_category":"Architekten",
    "sg:phone":"+43 512 583323",
    "sg:postcode":"6020",
    "sg:province":"Tirol",
    "wof:name":"Maiacher Werner Arch Dipl-Ing",
    "wof:placetype":"venue"
},
  "geometry": {"coordinates":[11.3925733566,47.2600402832],"type":"Point"}
}