{
  "type": "Feature",
  "properties": {
    "iso:country":"AT",
    "sg:address":"Nr 2",
    "sg:city":"Windigsteig",
    "sg:orig_category":"Baumschulen",
    "sg:phone":"+43 2842 528910",
    "sg:postcode":"3841",
    "sg:province":"Nieder\u00f6sterreich",
    "wof:name":"Bauer Leopold",
    "wof:placetype":"venue"
},
  "geometry": {"coordinates":[146.41244506839999,-38.3386192322],"type":"Point"}
}