{
  "type": "Feature",
  "properties": {
    "iso:country":"AT",
    "sg:address":"B\u00fcrgerg 1",
    "sg:city":"Gleisdorf",
    "sg:orig_category":"Glasereien",
    "sg:phone":"+43 4331 122323",
    "sg:postcode":"8200",
    "sg:province":"Steiermark",
    "wof:name":"Lenz Josef KG",
    "wof:placetype":"venue"
},
  "geometry": {"coordinates":[15.6912050247,47.103477478],"type":"Point"}
}