{
  "type": "Feature",
  "properties": {
    "addr:full":"Gumpendorfer Str 3 Wien Wien 1060",
    "addr:housenumber":"3",
    "addr:postcode":"1060",
    "addr:street":"Str",
    "iso:country":"AT",
    "sg:address":"Gumpendorfer Str 3",
    "sg:city":"Wien",
    "sg:orig_category":"Lebensmittel / Einzelhandel",
    "sg:phone":"+43 1 5878417",
    "sg:postcode":"1060",
    "sg:province":"Wien",
    "wof:name":"Ghobreyal Nader - Feinkost",
    "wof:placetype":"venue"
},
  "geometry": {"coordinates":[16.3620891571,48.2007751465],"type":"Point"}
}