{
  "type": "Feature",
  "properties": {
    "addr:full":"Ebentaler Str 149 Klagenfurt K\u00e4rnten 9020",
    "addr:housenumber":"149",
    "addr:postcode":"9020",
    "addr:street":"Kaernten",
    "iso:country":"AT",
    "sg:address":"Ebentaler Str 149",
    "sg:city":"Klagenfurt",
    "sg:classifiers":[
        {
            "category":"Restaurant",
            "type":"Food & Drink"
        }
    ],
    "sg:phone":"+43 463 345343",
    "sg:postcode":"9020",
    "sg:province":"K\u00e4rnten",
    "sg:tags":[
        "pizzeria"
    ],
    "wof:name":"Pizzeria XXL",
    "wof:placetype":"venue"
},
  "geometry": {"coordinates":[14.3408298492,46.6142082214],"type":"Point"}
}