{
  "type": "Feature",
  "properties": {
    "iso:country":"AT",
    "sg:address":"Hauptstr 45",
    "sg:city":"Nagelberg",
    "sg:orig_category":"Logistik",
    "sg:phone":"+43 4328 5975310",
    "sg:postcode":"3871",
    "sg:province":"Nieder\u00f6sterreich",
    "wof:name":"CO-PAL Container- u Palettenlager GmbH",
    "wof:placetype":"venue"
},
  "geometry": {"coordinates":[14.9954853058,48.8410797119],"type":"Point"}
}