{
  "type": "Feature",
  "properties": {
    "iso:country":"AT",
    "sg:address":"Nr 58",
    "sg:city":"Dalaas",
    "sg:orig_category":"Pensionen / Privatzimmer",
    "sg:phone":"+43 5585 7382",
    "sg:postcode":"6752",
    "sg:province":"Vorarlberg",
    "wof:name":"Th\u00f6ny Pension",
    "wof:placetype":"venue"
},
  "geometry": {"coordinates":[9.9998960495,47.1229896545],"type":"Point"}
}