{
  "type": "Feature",
  "properties": {
    "iso:country":"AT",
    "sg:address":"Obermamau 35",
    "sg:city":"Karlstetten",
    "sg:orig_category":"Metallbau",
    "sg:phone":"+43 2742 311003",
    "sg:postcode":"3121",
    "sg:province":"Nieder\u00f6sterreich",
    "wof:name":"Fuchs Metallbau",
    "wof:placetype":"venue"
},
  "geometry": {"coordinates":[15.5960636139,48.2442970276],"type":"Point"}
}