{
  "type": "Feature",
  "properties": {
    "iso:country":"AT",
    "sg:address":"Eckperg 14",
    "sg:city":"Wien",
    "sg:orig_category":"Unternehmensberatung",
    "sg:phone":"+43 1 4780054",
    "sg:postcode":"1180",
    "sg:province":"Wien",
    "wof:name":"Faustenhammer Alfred Mag iur",
    "wof:placetype":"venue"
},
  "geometry": {"coordinates":[16.3161029816,48.2338447571],"type":"Point"}
}