{
  "type": "Feature",
  "properties": {
    "addr:full":"Nr 6 Randegg Nieder\u00f6sterreich 3263",
    "addr:postcode":"3263",
    "addr:street":"Nr;Randegg",
    "iso:country":"AT",
    "sg:address":"Nr 6",
    "sg:city":"Randegg",
    "sg:orig_category":"Wasseraufbereitung U -Reinigung",
    "sg:phone":"+43 4367 69544246",
    "sg:postcode":"3263",
    "sg:province":"Nieder\u00f6sterreich",
    "wof:name":"Mayrhofer Umwelt-Energie-Technik",
    "wof:placetype":"venue"
},
  "geometry": {"coordinates":[14.9729251862,48.0112915039],"type":"Point"}
}