{
  "type": "Feature",
  "properties": {
    "addr:full":"Marktgraben 7-9 Innsbruck Tirol 6020",
    "addr:housenumber":"7-9",
    "addr:postcode":"6020",
    "addr:street":"Marktgraben;Tirol",
    "iso:country":"AT",
    "sg:address":"Marktgraben 7-9",
    "sg:city":"Innsbruck",
    "sg:classifiers":[
        {
            "category":"Travel",
            "subcategory":"Hotels & Motels",
            "type":"Entertainment"
        }
    ],
    "sg:phone":"+43 4351 2599670",
    "sg:postcode":"6020",
    "sg:province":"Tirol",
    "wof:name":"Maximilian Hotel",
    "wof:placetype":"venue"
},
  "geometry": {"coordinates":[11.3920574188,47.2671394348],"type":"Point"}
}