{
  "type": "Feature",
  "properties": {
    "addr:full":"Auweg 200 Burgau Steiermark 8291",
    "addr:housenumber":"200",
    "addr:postcode":"8291",
    "addr:street":"Auweg",
    "iso:country":"AT",
    "sg:address":"Auweg 200",
    "sg:city":"Burgau",
    "sg:classifiers":[
        {
            "category":"Building & Trades",
            "subcategory":"Plumbing",
            "type":"Services"
        }
    ],
    "sg:phone":"+43 3383 2971",
    "sg:postcode":"8291",
    "sg:province":"Steiermark",
    "sg:tags":[
        "supraregional",
        "gas"
    ],
    "wof:name":"HTK Haustechnik Klenner",
    "wof:placetype":"venue"
},
  "geometry": {"coordinates":[16.1011009216,47.1462059021],"type":"Point"}
}