{
  "type": "Feature",
  "properties": {
    "iso:country":"AT",
    "sg:address":"Wiener Str 94A",
    "sg:city":"Gloggnitz",
    "sg:orig_category":"Tischlereien",
    "sg:phone":"+43 2662 44470",
    "sg:postcode":"2640",
    "sg:province":"Nieder\u00f6sterreich",
    "wof:name":"Tischlerei Manfred Schneider",
    "wof:placetype":"venue"
},
  "geometry": {"coordinates":[15.9555473328,47.6728134155],"type":"Point"}
}