{
  "type": "Feature",
  "properties": {
    "addr:full":"Emanuel-von-Hibler-Str 10 Lienz Tirol 9900",
    "addr:housenumber":"10",
    "addr:postcode":"9900",
    "addr:street":"Emanuel-Von-Hibler-Str;Tirol",
    "iso:country":"AT",
    "sg:address":"Emanuel-von-Hibler-Str 10",
    "sg:city":"Lienz",
    "sg:orig_category":"Volksschulen",
    "sg:phone":"+43 4348 5262737",
    "sg:postcode":"9900",
    "sg:province":"Tirol",
    "wof:name":"Volksschule Nord",
    "wof:placetype":"venue"
},
  "geometry": {"coordinates":[12.7652015686,46.8357963562],"type":"Point"}
}