{
  "type": "Feature",
  "properties": {
    "addr:full":"Waagg 18 Klagenfurt K\u00e4rnten 9020",
    "addr:housenumber":"18",
    "addr:postcode":"9020",
    "addr:street":"Waagg;Kaernten",
    "iso:country":"AT",
    "sg:address":"Waagg 18",
    "sg:city":"Klagenfurt",
    "sg:orig_category":"Unternehmensberatung",
    "sg:phone":"+43 463 55264",
    "sg:postcode":"9020",
    "sg:province":"K\u00e4rnten",
    "wof:name":"BUB B\u00e4uerliche Unternehmensberatung GmbH",
    "wof:placetype":"venue"
},
  "geometry": {"coordinates":[14.3110198975,46.6261444092],"type":"Point"}
}