{
  "type": "Feature",
  "properties": {
    "addr:full":"Brennerg 13-15 Wien Wien 1230",
    "addr:postcode":"13-15;1230",
    "iso:country":"AT",
    "sg:address":"Brennerg 13-15",
    "sg:city":"Wien",
    "sg:orig_category":"Transportunternehmen",
    "sg:phone":"+43 1 86987690",
    "sg:postcode":"1230",
    "sg:province":"Wien",
    "wof:name":"Kornherr H TransportgesmbH",
    "wof:placetype":"venue"
},
  "geometry": {"coordinates":[16.3006858826,48.144821167],"type":"Point"}
}