{
  "type": "Feature",
  "properties": {
    "addr:full":"Kugelberg 42 Judendorf-Stra\u00dfengel Steiermark 8111",
    "addr:housenumber":"42",
    "addr:postcode":"8111",
    "addr:street":"Kugelberg",
    "iso:country":"AT",
    "sg:address":"Kugelberg 42",
    "sg:city":"Judendorf-Stra\u00dfengel",
    "sg:orig_category":"Magnetfeldtherapie",
    "sg:phone":"+43 3124 55217",
    "sg:postcode":"8111",
    "sg:province":"Steiermark",
    "wof:name":"Agentur G.Jopp",
    "wof:placetype":"venue"
},
  "geometry": {"coordinates":[15.3052968979,47.1005477905],"type":"Point"}
}