{
  "type": "Feature",
  "properties": {
    "addr:full":"Sportallee 60 Neuhofen an der Krems Ober\u00f6sterreich 4501",
    "addr:housenumber":"60",
    "addr:postcode":"4501",
    "addr:street":"Sportallee",
    "iso:country":"AT",
    "sg:address":"Sportallee 60",
    "sg:city":"Neuhofen an der Krems",
    "sg:orig_category":"Fitnesscenter",
    "sg:phone":"+43 4372 2760187",
    "sg:postcode":"4501",
    "sg:province":"Ober\u00f6sterreich",
    "wof:name":"bmi-fitness GesmbH",
    "wof:placetype":"venue"
},
  "geometry": {"coordinates":[14.2314910889,48.1319885254],"type":"Point"}
}