{
  "type": "Feature",
  "properties": {
    "addr:full":"Kagraner Platz 35 Wien Wien 1220",
    "addr:housenumber":"35",
    "addr:postcode":"1220",
    "addr:street":"Kagraner Platz",
    "iso:country":"AT",
    "sg:address":"Kagraner Platz 35",
    "sg:city":"Wien",
    "sg:classifiers":[
        {
            "category":"Utilities",
            "subcategory":"Mobile Phone",
            "type":"Services"
        }
    ],
    "sg:phone":"+43 1 2032151",
    "sg:postcode":"1220",
    "sg:province":"Wien",
    "sg:tags":[
        "cylinder",
        "workshop",
        "grinding"
    ],
    "wof:name":"G\u00fcnther Haas Ges.m.b.H. Nfg. KEG",
    "wof:placetype":"venue"
},
  "geometry": {"coordinates":[16.4485588074,48.2483177185],"type":"Point"}
}