{
  "type": "Feature",
  "properties": {
    "addr:full":"Kaiserj\u00e4gerstr 29 Kufstein Tirol 6330",
    "addr:housenumber":"29",
    "addr:postcode":"6330",
    "addr:street":"Kaiserjaegerstr;Tirol",
    "iso:country":"AT",
    "sg:address":"Kaiserj\u00e4gerstr 29",
    "sg:city":"Kufstein",
    "sg:classifiers":[
        {
            "category":"Internet Cafe",
            "subcategory":"None",
            "type":"Food & Drink"
        }
    ],
    "sg:phone":"+43 676 7349151",
    "sg:postcode":"6330",
    "sg:province":"Tirol",
    "wof:name":"Aru Internet Consulting GmbH",
    "wof:placetype":"venue"
},
  "geometry": {"coordinates":[12.1746816635,47.5919342041],"type":"Point"}
}