{
  "type": "Feature",
  "properties": {
    "iso:country":"AT",
    "sg:city":"Obersulz",
    "sg:orig_category":"Museen / Ausstellungen",
    "sg:phone":"+43 4325 343330",
    "sg:postcode":"2224",
    "sg:province":"Nieder\u00f6sterreich",
    "wof:name":"Weinviertler Museumsdorf Niedersulz",
    "wof:placetype":"venue"
},
  "geometry": {"coordinates":[16.6783123016,48.4856414795],"type":"Point"}
}