{
  "type": "Feature",
  "properties": {
    "addr:full":"Hauptstr 24 Rust Burgenland 7071",
    "addr:housenumber":"24",
    "addr:postcode":"7071",
    "addr:street":"Hauptstr",
    "iso:country":"AT",
    "sg:address":"Hauptstr 24",
    "sg:city":"Rust",
    "sg:orig_category":"Bestattungsunternehmen",
    "sg:phone":"+43 2685 262",
    "sg:postcode":"7071",
    "sg:province":"Burgenland",
    "wof:name":"Bestattung Repay-Wedl",
    "wof:placetype":"venue"
},
  "geometry": {"coordinates":[16.6772613525,47.801525116],"type":"Point"}
}