{
  "type": "Feature",
  "properties": {
    "iso:country":"AT",
    "sg:address":"Schubertstr 7",
    "sg:city":"Villach",
    "sg:orig_category":"Bauunternehmen",
    "sg:phone":"+43 4342 42290800",
    "sg:postcode":"9500",
    "sg:province":"K\u00e4rnten",
    "wof:name":"AZ-Bau GesmbH",
    "wof:placetype":"venue"
},
  "geometry": {"coordinates":[13.8564081192,46.613899231],"type":"Point"}
}