{
  "type": "Feature",
  "properties": {
    "iso:country":"AT",
    "sg:address":"Annenstr 18",
    "sg:city":"Graz",
    "sg:orig_category":"Lederwaren / Einzelhandel",
    "sg:phone":"+43 316 713338",
    "sg:postcode":"8020",
    "sg:province":"Steiermark",
    "wof:name":"Radkohl Friedrich KG",
    "wof:placetype":"venue"
},
  "geometry": {"coordinates":[15.4291601181,47.0711975098],"type":"Point"}
}