{
  "type": "Feature",
  "properties": {
    "addr:full":"Gentzg 166 Wien Wien 1180",
    "addr:housenumber":"166",
    "addr:postcode":"1180",
    "iso:country":"AT",
    "sg:address":"Gentzg 166",
    "sg:city":"Wien",
    "sg:orig_category":"Dachdeckereien",
    "sg:phone":"+43 1 4853816",
    "sg:postcode":"1180",
    "sg:province":"Wien",
    "wof:name":"K & S Dacherrichtungs GesmbH",
    "wof:placetype":"venue"
},
  "geometry": {"coordinates":[16.3293743134,48.2316207886],"type":"Point"}
}