{
  "type": "Feature",
  "properties": {
    "addr:full":"Hauptpl 18 Radenthein K\u00e4rnten 9545",
    "addr:housenumber":"18",
    "addr:postcode":"9545",
    "addr:street":"Hauptpl;Kaernten",
    "iso:country":"AT",
    "sg:address":"Hauptpl 18",
    "sg:city":"Radenthein",
    "sg:orig_category":"Versicherungsunternehmen",
    "sg:phone":"+43 4246 3088",
    "sg:postcode":"9545",
    "sg:province":"K\u00e4rnten",
    "wof:name":"K\u00e4rntner Landesversicherung auf Gegenseitigkeit",
    "wof:placetype":"venue"
},
  "geometry": {"coordinates":[13.7054052353,46.8016204834],"type":"Point"}
}