{
  "type": "Feature",
  "properties": {
    "addr:full":"Untere Landstr 56 Krems an der Donau Nieder\u00f6sterreich 3500",
    "addr:housenumber":"56",
    "addr:postcode":"3500",
    "addr:street":"Untere Landstr",
    "iso:country":"AT",
    "sg:address":"Untere Landstr 56",
    "sg:city":"Krems an der Donau",
    "sg:orig_category":"Apotheken",
    "sg:phone":"+43 2732 828250",
    "sg:postcode":"3500",
    "sg:province":"Nieder\u00f6sterreich",
    "wof:name":"Apotheke Wienertor",
    "wof:placetype":"venue"
},
  "geometry": {"coordinates":[15.604842186,48.4120674133],"type":"Point"}
}