{
  "type": "Feature",
  "properties": {
    "addr:full":"Obere Dorfstr 23 Gattendorf Burgenland 2474",
    "addr:housenumber":"23",
    "addr:postcode":"2474",
    "addr:street":"Obere Dorfstr",
    "iso:country":"AT",
    "sg:address":"Obere Dorfstr 23",
    "sg:city":"Gattendorf",
    "sg:orig_category":"Gutsverwaltungen",
    "sg:phone":"+43 2142 525111",
    "sg:postcode":"2474",
    "sg:province":"Burgenland",
    "wof:name":"Czell'sche Gutsverwaltung - Inh Vivian Czell",
    "wof:placetype":"venue"
},
  "geometry": {"coordinates":[16.9806594849,48.0170783997],"type":"Point"}
}