{
  "type": "Feature",
  "properties": {
    "addr:full":"Einfang 33 Schwaz Tirol 6130",
    "addr:housenumber":"33",
    "addr:postcode":"6130",
    "addr:street":"Einfang;Tirol",
    "iso:country":"AT",
    "sg:address":"Einfang 33",
    "sg:city":"Schwaz",
    "sg:orig_category":"Spenglereien",
    "sg:phone":"+43 5242 72334",
    "sg:postcode":"6130",
    "sg:province":"Tirol",
    "wof:name":"Saringer GmbH",
    "wof:placetype":"venue"
},
  "geometry": {"coordinates":[11.7219171524,47.3590965271],"type":"Point"}
}