{
  "type": "Feature",
  "properties": {
    "iso:country":"AT",
    "sg:address":"Brunnwies 25",
    "sg:city":"Sch\u00e4rding",
    "sg:orig_category":"Logistik",
    "sg:phone":"+43 7712 7780",
    "sg:postcode":"4780",
    "sg:province":"Ober\u00f6sterreich",
    "wof:name":"Hans Glas Logistik GmbH",
    "wof:placetype":"venue"
},
  "geometry": {"coordinates":[13.4304552078,48.4575538635],"type":"Point"}
}