{
  "type": "Feature",
  "properties": {
    "addr:full":"Strobelg 1 Wien Wien 1010",
    "addr:housenumber":"1",
    "addr:postcode":"1010",
    "addr:street":"Strobelg",
    "iso:country":"AT",
    "sg:address":"Strobelg 1",
    "sg:city":"Wien",
    "sg:orig_category":"Briefmarken Philatelie",
    "sg:phone":"+43 1 5136825",
    "sg:postcode":"1010",
    "sg:province":"Wien",
    "wof:name":"Wieser Maria GesmbH",
    "wof:placetype":"venue"
},
  "geometry": {"coordinates":[16.3748531342,48.2086715698],"type":"Point"}
}