{
  "type": "Feature",
  "properties": {
    "addr:full":"Br\u00e4uhausstr 2a/2/20 Salzburg Salzburg 5020",
    "addr:housenumber":"2a / 2 / 20",
    "addr:postcode":"5020",
    "addr:street":"Braeuhausstr;Salzburg",
    "iso:country":"AT",
    "sg:address":"Br\u00e4uhausstr 2a/2/20",
    "sg:city":"Salzburg",
    "sg:orig_category":"Handelsagenturen",
    "sg:phone":"+43 662 833712",
    "sg:postcode":"5020",
    "sg:province":"Salzburg",
    "wof:name":"I.T.A. Robert Halas",
    "wof:placetype":"venue"
},
  "geometry": {"coordinates":[13.0433769226,47.8006744385],"type":"Point"}
}