{
  "type": "Feature",
  "properties": {
    "iso:country":"AT",
    "sg:address":"Riedstr 14",
    "sg:city":"Frastanz",
    "sg:orig_category":"Spenglereien",
    "sg:phone":"+43 4355 22513100",
    "sg:postcode":"6820",
    "sg:province":"Vorarlberg",
    "wof:name":"H\u00e4rtenberger Thomas GesmbH & Co KG",
    "wof:placetype":"venue"
},
  "geometry": {"coordinates":[9.6303749084,47.2169532776],"type":"Point"}
}