{
  "type": "Feature",
  "properties": {
    "addr:full":"Bundesstr 96 Wimpassing im Schwarzatale Nieder\u00f6sterreich 2632",
    "addr:housenumber":"96",
    "addr:postcode":"2632",
    "addr:street":"Bundesstr",
    "iso:country":"AT",
    "sg:address":"Bundesstr 96",
    "sg:city":"Wimpassing im Schwarzatale",
    "sg:orig_category":"Tapeten",
    "sg:phone":"+43 4326 3037380",
    "sg:postcode":"2632",
    "sg:province":"Nieder\u00f6sterreich",
    "wof:name":"all color F Windisch GmbH",
    "wof:placetype":"venue"
},
  "geometry": {"coordinates":[16.0206813812,47.6963386536],"type":"Point"}
}