{
  "type": "Feature",
  "properties": {
    "iso:country":"AT",
    "sg:address":"Rudersdorfer Str 6",
    "sg:city":"Neumarkt im M\u00fchlkreis",
    "sg:orig_category":"Schlossereien",
    "sg:phone":"+43 4379 4120518",
    "sg:postcode":"4212",
    "sg:province":"Ober\u00f6sterreich",
    "wof:name":"Manzenreiter KEG",
    "wof:placetype":"venue"
},
  "geometry": {"coordinates":[14.4929161072,48.4262695312],"type":"Point"}
}