{
  "type": "Feature",
  "properties": {
    "addr:full":"Nonntaler Hauptstr 110/2 Salzburg Salzburg 5020",
    "addr:housenumber":"110 / 2",
    "addr:postcode":"5020",
    "addr:street":"Nonntaler Hauptstr;Salzburg",
    "iso:country":"AT",
    "sg:address":"Nonntaler Hauptstr 110/2",
    "sg:city":"Salzburg",
    "sg:orig_category":"Psychotherapie",
    "sg:phone":"+43 662 825750",
    "sg:postcode":"5020",
    "sg:province":"Salzburg",
    "wof:name":"Tempfli Ulrike Mag phil",
    "wof:placetype":"venue"
},
  "geometry": {"coordinates":[13.0502977371,47.7826843262],"type":"Point"}
}