{
  "type": "Feature",
  "properties": {
    "addr:full":"Anton-Glas-Str 22 Eferding Ober\u00f6sterreich 4070",
    "addr:housenumber":"22",
    "addr:postcode":"4070",
    "addr:street":"Anton-Glas-Str",
    "iso:country":"AT",
    "sg:address":"Anton-Glas-Str 22",
    "sg:city":"Eferding",
    "sg:orig_category":"Estriche",
    "sg:phone":"+43 7272 7408",
    "sg:postcode":"4070",
    "sg:province":"Ober\u00f6sterreich",
    "sg:website":"www.feichtinger-estriche.at",
    "wof:name":"Feichtinger Erich KEG",
    "wof:placetype":"venue"
},
  "geometry": {"coordinates":[14.0083198547,48.3059234619],"type":"Point"}
}