{
  "type": "Feature",
  "properties": {
    "iso:country":"AT",
    "sg:address":"Marktstr 3",
    "sg:city":"Mittersill",
    "sg:orig_category":"\u00c3\u201enderungsschneidereien",
    "sg:phone":"+43 4366 43326911",
    "sg:postcode":"5730",
    "sg:province":"Salzburg",
    "wof:name":"\u00e4nderungs- u Ma\u00dfschneiderei - Nadel & Zwirn - Kemmether Karin",
    "wof:placetype":"venue"
},
  "geometry": {"coordinates":[12.4818754196,47.2814064026],"type":"Point"}
}