{
  "type": "Feature",
  "properties": {
    "iso:country":"AT",
    "sg:address":"Alpenstrasse 85",
    "sg:city":"Salzburg",
    "sg:classifiers":[
        {
            "category":"Social Services",
            "subcategory":"Job Training",
            "type":"Services"
        }
    ],
    "sg:phone":"+43 6306303420",
    "sg:postcode":"5020",
    "sg:province":"Salzburg",
    "sg:tags":[
        "software",
        "database"
    ],
    "sg:website":"ocs.de",
    "wof:name":"ACS Anwendungs- Computer- und Softwareberatungs Ges.m.b.H.",
    "wof:placetype":"venue"
},
  "geometry": {"coordinates":[13.0682420731,47.7788696289],"type":"Point"}
}