{
  "type": "Feature",
  "properties": {
    "iso:country":"AT",
    "sg:address":"Dorfstr 5",
    "sg:city":"F\u00fcgen",
    "sg:orig_category":"Transportunternehmen",
    "sg:phone":"+43 664 4234551",
    "sg:postcode":"6263",
    "sg:province":"Tirol",
    "wof:name":"Emberger Johann",
    "wof:placetype":"venue"
},
  "geometry": {"coordinates":[7.9469609261,47.2189712524],"type":"Point"}
}