{
  "type": "Feature",
  "properties": {
    "addr:full":"Kundmanng 33 Wien Wien 1030",
    "addr:housenumber":"33",
    "addr:postcode":"1030",
    "addr:street":"Kundmanng",
    "iso:country":"AT",
    "sg:address":"Kundmanng 33",
    "sg:city":"Wien",
    "sg:orig_category":"Digitaldruck",
    "sg:phone":"+43 1 712959912",
    "sg:postcode":"1030",
    "sg:province":"Wien",
    "wof:name":"digiDruck Ges.m.b.H.",
    "wof:placetype":"venue"
},
  "geometry": {"coordinates":[16.3925209045,48.2022361755],"type":"Point"}
}