{
  "type": "Feature",
  "properties": {
    "addr:full":"Hugo-Wolf-G 6a Graz Steiermark 8010",
    "addr:housenumber":"6a",
    "addr:postcode":"8010",
    "addr:street":"Hugo-Wolf-G",
    "iso:country":"AT",
    "sg:address":"Hugo-Wolf-G 6a",
    "sg:city":"Graz",
    "sg:orig_category":"Unternehmensberatung",
    "sg:phone":"+43 316 9192290",
    "sg:postcode":"8010",
    "sg:province":"Steiermark",
    "wof:name":"isn - innovation service network GmbH",
    "wof:placetype":"venue"
},
  "geometry": {"coordinates":[15.4495191574,47.0750961304],"type":"Point"}
}