{
  "type": "Feature",
  "properties": {
    "addr:full":"Winzerweg 1/SCM/beim \u00f6AMTC Eisenstadt Burgenland 7000",
    "addr:housenumber":"1 / scm",
    "addr:postcode":"7000",
    "addr:street":"Winzerweg",
    "iso:country":"AT",
    "sg:address":"Winzerweg 1/SCM/beim \u00f6AMTC",
    "sg:city":"Eisenstadt",
    "sg:classifiers":[
        {
            "category":"Personal",
            "subcategory":"Adult",
            "type":"Services"
        }
    ],
    "sg:phone":"+43 2682 65655",
    "sg:postcode":"7000",
    "sg:province":"Burgenland",
    "sg:tags":[
        "sex-shops"
    ],
    "wof:name":"ART-X Erotiksupermarkt",
    "wof:placetype":"venue"
},
  "geometry": {"coordinates":[16.5189552307,47.8455657959],"type":"Point"}
}