{
  "type": "Feature",
  "properties": {
    "iso:country":"AT",
    "sg:address":"Ried 23",
    "sg:city":"Koblach",
    "sg:orig_category":"Autovermietung",
    "sg:phone":"+43 664 3413619",
    "sg:postcode":"6842",
    "sg:province":"Vorarlberg",
    "wof:name":"Fahrzeugvermietung und Aushilfsfahrer Raineri",
    "wof:placetype":"venue"
},
  "geometry": {"coordinates":[9.6163272858,47.3162536621],"type":"Point"}
}