{
  "type": "Feature",
  "properties": {
    "addr:full":"Loeschenkohlg 2 Wien Wien 1150",
    "addr:housenumber":"2",
    "addr:postcode":"1150",
    "addr:street":"Loeschenkohlg",
    "iso:country":"AT",
    "sg:address":"Loeschenkohlg 2",
    "sg:city":"Wien",
    "sg:orig_category":"Druckereimaschinen U -Bedarf",
    "sg:phone":"+43 4317 865249",
    "sg:postcode":"1150",
    "sg:province":"Wien",
    "sg:website":"maschinenmesser.at",
    "wof:name":"Karner Manfred - Maschinenmesserschleiferei",
    "wof:placetype":"venue"
},
  "geometry": {"coordinates":[16.3311882019,48.201171875],"type":"Point"}
}