{
  "type": "Feature",
  "properties": {
    "addr:full":"Gemeindehausstr 7 Wagna Steiermark 8435",
    "addr:housenumber":"7",
    "addr:postcode":"8435",
    "addr:street":"Gemeindehausstr",
    "iso:country":"AT",
    "sg:address":"Gemeindehausstr 7",
    "sg:city":"Wagna",
    "sg:orig_category":"Volksschulen",
    "sg:phone":"+43 3452 86288",
    "sg:postcode":"8435",
    "sg:province":"Steiermark",
    "wof:name":"Volksschule",
    "wof:placetype":"venue"
},
  "geometry": {"coordinates":[15.5550117493,46.7656211853],"type":"Point"}
}