{
  "type": "Feature",
  "properties": {
    "iso:country":"AT",
    "sg:address":"Syrnauer Pl 3",
    "sg:city":"Zwettl",
    "sg:orig_category":"Tankstellen",
    "sg:phone":"+43 2822 50661",
    "sg:postcode":"3910",
    "sg:province":"Nieder\u00f6sterreich",
    "wof:name":"Shell Austria GmbH",
    "wof:placetype":"venue"
},
  "geometry": {"coordinates":[15.1681003571,48.6041564941],"type":"Point"}
}