{
  "type": "Feature",
  "properties": {
    "addr:full":"Neutorg 27 Graz Steiermark 8010",
    "addr:housenumber":"27",
    "addr:postcode":"8010",
    "addr:street":"Neutorg",
    "iso:country":"AT",
    "sg:address":"Neutorg 27",
    "sg:city":"Graz",
    "sg:orig_category":"Zeitungen U Zeitschriften",
    "sg:phone":"+43 316 82288314",
    "sg:postcode":"8010",
    "sg:province":"Steiermark",
    "wof:name":"KORSO Zeitschriften-Verlag",
    "wof:placetype":"venue"
},
  "geometry": {"coordinates":[15.4363203049,47.0699768066],"type":"Point"}
}