{
  "type": "Feature",
  "properties": {
    "iso:country":"AT",
    "sg:address":"Wiedner Hauptstr 26",
    "sg:city":"Wien",
    "sg:orig_category":"Optiker",
    "sg:phone":"+43 1 5856363",
    "sg:postcode":"1040",
    "sg:province":"Wien",
    "wof:name":"SichtBar",
    "wof:placetype":"venue"
},
  "geometry": {"coordinates":[16.3670043945,48.1959877014],"type":"Point"}
}