{
  "type": "Feature",
  "properties": {
    "addr:full":"Eckperg 47 Wien Wien 1180",
    "addr:housenumber":"47",
    "addr:postcode":"1180",
    "addr:street":"Eckperg",
    "iso:country":"AT",
    "sg:address":"Eckperg 47",
    "sg:city":"Wien",
    "sg:orig_category":"Immobilienmakler",
    "sg:phone":"+43 1 47941170",
    "sg:postcode":"1180",
    "sg:province":"Wien",
    "wof:name":"Mayerl Hildegard Realkanzlei P\u00e4chterin Eva Krulis",
    "wof:placetype":"venue"
},
  "geometry": {"coordinates":[16.3169345856,48.2367477417],"type":"Point"}
}