{
  "type": "Feature",
  "properties": {
    "addr:full":"Klagenfurter Str 17 Velden am W\u00f6rther See K\u00e4rnten 9220",
    "addr:postcode":"9220",
    "addr:street":"Str 17;Kaernten",
    "iso:country":"AT",
    "sg:address":"Klagenfurter Str 17",
    "sg:city":"Velden am W\u00f6rther See",
    "sg:orig_category":"Diskotheken",
    "sg:phone":"+43 4342 742034",
    "sg:postcode":"9220",
    "sg:province":"K\u00e4rnten",
    "wof:name":"Discothek Crazy Bull",
    "wof:placetype":"venue"
},
  "geometry": {"coordinates":[14.0499200821,46.6179084778],"type":"Point"}
}