{
  "type": "Feature",
  "properties": {
    "addr:full":"Krenng 28 Graz Steiermark 8010",
    "addr:housenumber":"28",
    "addr:postcode":"8010",
    "addr:street":"Krenng",
    "iso:country":"AT",
    "sg:address":"Krenng 28",
    "sg:city":"Graz",
    "sg:classifiers":[
        {
            "category":"Internet Cafe",
            "subcategory":"None",
            "type":"Food & Drink"
        }
    ],
    "sg:phone":"+43 316 815544",
    "sg:postcode":"8010",
    "sg:province":"Steiermark",
    "wof:name":"Netconomy Online Beratungs-Management GmbH & Co KG",
    "wof:placetype":"venue"
},
  "geometry": {"coordinates":[15.4591779709,47.0673294067],"type":"Point"}
}