{
  "type": "Feature",
  "properties": {
    "addr:full":"Badhausweg 19-21 Brixen im Thale Tirol 6364",
    "addr:postcode":"19-21;6364",
    "addr:street":"Badhausweg;Tirol",
    "iso:country":"AT",
    "sg:address":"Badhausweg 19-21",
    "sg:city":"Brixen im Thale",
    "sg:orig_category":"Pensionen / Privatzimmer",
    "sg:phone":"+43 5334 8153",
    "sg:postcode":"6364",
    "sg:province":"Tirol",
    "wof:name":"Pensionshaus Tirol",
    "wof:placetype":"venue"
},
  "geometry": {"coordinates":[12.2540903091,47.4454879761],"type":"Point"}
}