{
  "type": "Feature",
  "properties": {
    "iso:country":"AT",
    "sg:address":"Irrsdorf 135",
    "sg:city":"Stra\u00dfwalchen",
    "sg:orig_category":"Kinderbetreuung",
    "sg:phone":"+43 6215 61080",
    "sg:postcode":"5204",
    "sg:province":"Salzburg",
    "wof:name":"Kindergarten d Marktgemeinde Stra\u00dfwalchen",
    "wof:placetype":"venue"
},
  "geometry": {"coordinates":[13.2546854019,47.9797363281],"type":"Point"}
}