{
  "type": "Feature",
  "properties": {
    "iso:country":"AT",
    "sg:address":"Bahnweg 90",
    "sg:city":"Pfaffenhofen",
    "sg:orig_category":"Lebensmittel / Einzelhandel",
    "sg:phone":"+43 5262 65941",
    "sg:postcode":"6405",
    "sg:province":"Tirol",
    "wof:name":"MPREIS WarenvertriebsgesmbH",
    "wof:placetype":"venue"
},
  "geometry": {"coordinates":[11.0840406418,47.3006706238],"type":"Point"}
}