{
  "type": "Feature",
  "properties": {
    "addr:full":"Wiener Neust\u00e4dter Strasse 9 Bad Erlach Nieder\u00f6sterreich 2822",
    "addr:housenumber":"9",
    "addr:postcode":"2822",
    "addr:street":"Strasse",
    "iso:country":"AT",
    "sg:address":"Wiener Neust\u00e4dter Strasse 9",
    "sg:city":"Bad Erlach",
    "sg:classifiers":[
        {
            "category":"Banks & Credit Unions",
            "subcategory":"Investment Brokerage",
            "type":"Services"
        }
    ],
    "sg:phone":"+43 2627 82295",
    "sg:postcode":"2822",
    "sg:province":"Nieder\u00f6sterreich",
    "sg:tags":[
        "discharge",
        "pipes",
        "piping"
    ],
    "wof:name":"Kremsl GesmbH",
    "wof:placetype":"venue"
},
  "geometry": {"coordinates":[16.2160301208,47.7281303406],"type":"Point"}
}