{
  "type": "Feature",
  "properties": {
    "iso:country":"AT",
    "sg:address":"Wiener Str 1",
    "sg:city":"Maria Lanzendorf",
    "sg:orig_category":"Blumeneinzelhandel",
    "sg:phone":"+43 4322 3543747",
    "sg:postcode":"2326",
    "sg:province":"Nieder\u00f6sterreich",
    "wof:name":"Blumen B & B R Bigl GesmbH",
    "wof:placetype":"venue"
},
  "geometry": {"coordinates":[16.4181404114,48.099067688],"type":"Point"}
}