{
  "type": "Feature",
  "properties": {
    "iso:country":"AT",
    "sg:address":"Julius-Ficker-Str 87",
    "sg:city":"Wien",
    "sg:orig_category":"Armaturen / Erzeugung U Gro\u00c3\u0178handel",
    "sg:phone":"+43 4312 5655550",
    "sg:postcode":"1210",
    "sg:province":"Wien",
    "wof:name":"Auro Armaturen u RohrhandelsgesmbH",
    "wof:placetype":"venue"
},
  "geometry": {"coordinates":[16.451374054,48.2662658691],"type":"Point"}
}