{
  "type": "Feature",
  "properties": {
    "iso:country":"AT",
    "sg:address":"Mautner Markhof-G 49",
    "sg:city":"Wien",
    "sg:orig_category":"Reifen U Reifendienste",
    "sg:phone":"+43 1 74913680",
    "sg:postcode":"1110",
    "sg:province":"Wien",
    "sg:website":"www.hohler.at",
    "wof:name":"Hohler und Co GmbH",
    "wof:placetype":"venue"
},
  "geometry": {"coordinates":[16.4206581116,48.1750526428],"type":"Point"}
}