{
  "type": "Feature",
  "properties": {
    "iso:country":"AT",
    "sg:address":"Schmitteng 7",
    "sg:city":"Frastanz",
    "sg:orig_category":"Bastelbedarf",
    "sg:phone":"+43 4355 2251748",
    "sg:postcode":"6820",
    "sg:province":"Vorarlberg",
    "wof:name":"Welte Alfred",
    "wof:placetype":"venue"
},
  "geometry": {"coordinates":[9.6303653717,47.218082428],"type":"Point"}
}