{
  "type": "Feature",
  "properties": {
    "addr:full":"Schlaininger Str 44 Gro\u00dfpetersdorf Burgenland 7503",
    "addr:postcode":"7503",
    "addr:street":"Str 44",
    "iso:country":"AT",
    "sg:address":"Schlaininger Str 44",
    "sg:city":"Gro\u00dfpetersdorf",
    "sg:orig_category":"Tischlereien",
    "sg:phone":"+43 3362 2379",
    "sg:postcode":"7503",
    "sg:province":"Burgenland",
    "wof:name":"Zlatarits Stefan",
    "wof:placetype":"venue"
},
  "geometry": {"coordinates":[12.1167001724,54.1500015259],"type":"Point"}
}