{
  "type": "Feature",
  "properties": {
    "addr:full":"Karl F\u00fcrnschu\u00df-Weg 166 Burgau Steiermark 8291",
    "addr:housenumber":"166",
    "addr:postcode":"8291",
    "iso:country":"AT",
    "sg:address":"Karl F\u00fcrnschu\u00df-Weg 166",
    "sg:city":"Burgau",
    "sg:orig_category":"Immobilienmakler",
    "sg:phone":"+43 3383 2538",
    "sg:postcode":"8291",
    "sg:province":"Steiermark",
    "wof:name":"SB Immobilien GmbH - Johannes Hackl",
    "wof:placetype":"venue"
},
  "geometry": {"coordinates":[16.0987606049,47.143081665],"type":"Point"}
}