{
  "type": "Feature",
  "properties": {
    "iso:country":"AT",
    "sg:address":"Zentrum.3",
    "sg:city":"Kramsach",
    "sg:classifiers":[
        {
            "category":"Home & Garden",
            "subcategory":"Home Furnishings",
            "type":"Retail Goods"
        }
    ],
    "sg:phone":"+43 4353 3762218",
    "sg:postcode":"6233",
    "sg:province":"Tirol",
    "sg:tags":[
        "household"
    ],
    "wof:name":"SALZBURGER BAU- U. M\u00d6BELTISCHLEREI",
    "wof:placetype":"venue"
},
  "geometry": {"coordinates":[11.8828849792,47.4485740662],"type":"Point"}
}