{
  "type": "Feature",
  "properties": {
    "addr:full":"Nr 64 St. Georgen an der Stiefing Steiermark 8413",
    "addr:postcode":"8413",
    "addr:street":"Nr 64",
    "iso:country":"AT",
    "sg:address":"Nr 64",
    "sg:city":"St. Georgen an der Stiefing",
    "sg:orig_category":"Gemeinden",
    "sg:phone":"+43 4331 8382550",
    "sg:postcode":"8413",
    "sg:province":"Steiermark",
    "wof:name":"Marktgemeindeamt St Georgen an der Stiefing",
    "wof:placetype":"venue"
},
  "geometry": {"coordinates":[15.5929555893,46.8366584778],"type":"Point"}
}