{
  "type": "Feature",
  "properties": {
    "addr:full":"Neilreichg 12 Wien Wien 1100",
    "addr:housenumber":"12",
    "addr:postcode":"1100",
    "addr:street":"Neilreichg",
    "iso:country":"AT",
    "sg:address":"Neilreichg 12",
    "sg:city":"Wien",
    "sg:orig_category":"Raumgestaltung",
    "sg:phone":"+43 1 6064450",
    "sg:postcode":"1100",
    "sg:province":"Wien",
    "wof:name":"Tischlerei K\u00f6ninger GesmbH",
    "wof:placetype":"venue"
},
  "geometry": {"coordinates":[16.3656234741,48.17735672],"type":"Point"}
}