{
  "type": "Feature",
  "properties": {
    "addr:full":"Scheiterbodenstr 16-20 Leoben Steiermark 8700",
    "addr:postcode":"8700",
    "iso:country":"AT",
    "sg:address":"Scheiterbodenstr 16-20",
    "sg:city":"Leoben",
    "sg:orig_category":"Schlossereien",
    "sg:phone":"+43 4338 42812340",
    "sg:postcode":"8700",
    "sg:province":"Steiermark",
    "wof:name":"V\u00f6lkl G GesmbH",
    "wof:placetype":"venue"
},
  "geometry": {"coordinates":[15.1091279984,47.3849411011],"type":"Point"}
}