{
  "type": "Feature",
  "properties": {
    "addr:full":"Nr 4 Schwertberg Ober\u00f6sterreich 4311",
    "addr:postcode":"4311",
    "addr:street":"Nr;Schwertberg",
    "iso:country":"AT",
    "sg:address":"Nr 4",
    "sg:city":"Schwertberg",
    "sg:orig_category":"Stiegen U Treppen",
    "sg:phone":"+43 7262 63079",
    "sg:postcode":"4311",
    "sg:province":"Ober\u00f6sterreich",
    "wof:name":"Reindl Christian",
    "wof:placetype":"venue"
},
  "geometry": {"coordinates":[14.5817127228,48.2739906311],"type":"Point"}
}