{
  "type": "Feature",
  "properties": {
    "addr:full":"Am Tabor 32 Wien Wien 1020",
    "addr:housenumber":"32",
    "addr:postcode":"1020",
    "addr:street":"Am Tabor",
    "iso:country":"AT",
    "sg:address":"Am Tabor 32",
    "sg:city":"Wien",
    "sg:orig_category":"Bootsmotoren, Autoersatzteile, Autohandel",
    "sg:phone":"+43 1 2145146",
    "sg:postcode":"1020",
    "sg:province":"Wien",
    "wof:name":"Beran OHG US-Automobil- und Ersatzteilhandel",
    "wof:placetype":"venue"
},
  "geometry": {"coordinates":[16.3887138367,48.2236061096],"type":"Point"}
}