{
  "type": "Feature",
  "properties": {
    "iso:country":"AT",
    "sg:address":"Krottental 21",
    "sg:city":"Hofkirchen im Traunkreis",
    "sg:orig_category":"Maschinenbau, Hydraulik",
    "sg:phone":"+43 7225 6095",
    "sg:postcode":"4492",
    "sg:province":"Ober\u00f6sterreich",
    "sg:website":"www.hydcom.com",
    "wof:name":"MBH Maschinenbau und Handels GmbH",
    "wof:placetype":"venue"
},
  "geometry": {"coordinates":[14.3419122696,48.1362037659],"type":"Point"}
}