{
  "type": "Feature",
  "properties": {
    "iso:country":"AT",
    "sg:address":"Halbleheng 28",
    "sg:city":"Gerasdorf",
    "sg:classifiers":[
        {
            "category":"Home & Garden",
            "subcategory":"Building Materials",
            "type":"Retail Goods"
        }
    ],
    "sg:phone":"+43 4322 464327",
    "sg:postcode":"2201",
    "sg:province":"Nieder\u00f6sterreich",
    "sg:tags":[
        "baustoffe",
        "-material",
        "u"
    ],
    "wof:name":"MIPO Bau- u HandelsgesmbH",
    "wof:placetype":"venue"
},
  "geometry": {"coordinates":[16.4752960205,48.2911529541],"type":"Point"}
}