{
  "type": "Feature",
  "properties": {
    "addr:full":"Schwarzviertler Str 12 St. Paul im Lavanttal K\u00e4rnten 9470",
    "addr:housenumber":"12",
    "addr:postcode":"9470",
    "addr:street":"Str",
    "iso:country":"AT",
    "sg:address":"Schwarzviertler Str 12",
    "sg:city":"St. Paul im Lavanttal",
    "sg:orig_category":"Tabaktrafiken",
    "sg:phone":"+43 4357 2412",
    "sg:postcode":"9470",
    "sg:province":"K\u00e4rnten",
    "wof:name":"Grillitsch Helga",
    "wof:placetype":"venue"
},
  "geometry": {"coordinates":[14.8702106476,46.6988067627],"type":"Point"}
}