{
  "type": "Feature",
  "properties": {
    "addr:full":"Schwarzstr 33 Salzburg Salzburg 5020",
    "addr:housenumber":"33",
    "addr:postcode":"5020",
    "addr:street":"Schwarzstr;Salzburg",
    "iso:country":"AT",
    "sg:address":"Schwarzstr 33",
    "sg:city":"Salzburg",
    "sg:orig_category":"Zahntechnische Laboratorien",
    "sg:phone":"+43 662 8737370",
    "sg:postcode":"5020",
    "sg:province":"Salzburg",
    "wof:name":"Dentaltechnik Friedrich Deu",
    "wof:placetype":"venue"
},
  "geometry": {"coordinates":[13.0391921997,47.8056488037],"type":"Point"}
}