{
  "type": "Feature",
  "properties": {
    "addr:full":"Nr 10 Oberhofen am Irrsee Ober\u00f6sterreich 4894",
    "addr:postcode":"4894",
    "addr:street":"Nr 10",
    "iso:country":"AT",
    "sg:address":"Nr 10",
    "sg:city":"Oberhofen am Irrsee",
    "sg:orig_category":"Appartements / Ferienwohnungen",
    "sg:phone":"+43 6213 8294",
    "sg:postcode":"4894",
    "sg:province":"Ober\u00f6sterreich",
    "wof:name":"Ferienhof Wildenegg Fam Lettner",
    "wof:placetype":"venue"
},
  "geometry": {"coordinates":[13.3063650131,47.9511909485],"type":"Point"}
}