{
  "type": "Feature",
  "properties": {
    "iso:country":"AT",
    "sg:address":"Marktpl 25",
    "sg:city":"Steinakirchen am Forst",
    "sg:orig_category":"Fleischhauereien",
    "sg:phone":"+43 4374 8871310",
    "sg:postcode":"3261",
    "sg:province":"Nieder\u00f6sterreich",
    "wof:name":"Weidinger Anton",
    "wof:placetype":"venue"
},
  "geometry": {"coordinates":[15.0490922928,48.0688972473],"type":"Point"}
}