{
  "type": "Feature",
  "properties": {
    "iso:country":"AT",
    "sg:address":"Egger-Lienz-Pl 3",
    "sg:city":"Lienz",
    "sg:orig_category":"Friseure U Frisiersalons",
    "sg:phone":"+43 4348 5270046",
    "sg:postcode":"9900",
    "sg:province":"Tirol",
    "wof:name":"Skalp Friseurstudio - Pl\u00f6ssnig OEG",
    "wof:placetype":"venue"
},
  "geometry": {"coordinates":[12.7644062042,46.8304824829],"type":"Point"}
}