{
  "type": "Feature",
  "properties": {
    "addr:full":"Gobernitz 14 Knittelfeld Steiermark 8720",
    "addr:housenumber":"14",
    "addr:postcode":"8720",
    "addr:street":"Gobernitz",
    "iso:country":"AT",
    "sg:address":"Gobernitz 14",
    "sg:city":"Knittelfeld",
    "sg:classifiers":[
        {
            "category":"Manufacturing",
            "subcategory":"Wood Products",
            "type":"Manufacturing & Wholesale Goods"
        }
    ],
    "sg:phone":"+43 3512 82288",
    "sg:postcode":"8720",
    "sg:province":"Steiermark",
    "sg:tags":[
        "case"
    ],
    "wof:name":"Hubert Schwarz",
    "wof:placetype":"venue"
},
  "geometry": {"coordinates":[14.8475036621,47.2144622803],"type":"Point"}
}