{
  "type": "Feature",
  "properties": {
    "addr:full":"Mitterweg 190 G\u00f6llersdorf Nieder\u00f6sterreich 2013",
    "addr:housenumber":"190",
    "addr:postcode":"2013",
    "addr:street":"Mitterweg;Niederoesterreich",
    "iso:country":"AT",
    "sg:address":"Mitterweg 190",
    "sg:city":"G\u00f6llersdorf",
    "sg:classifiers":[
        {
            "category":"Bars & Pubs",
            "subcategory":"Oxygen Bar",
            "type":"Food & Drink"
        }
    ],
    "sg:phone":"+43 4329 542106",
    "sg:postcode":"2013",
    "sg:province":"Nieder\u00f6sterreich",
    "sg:tags":[
        "biofeedback"
    ],
    "wof:name":"Aichinger Karin - Biofeedback und Bioresonanz",
    "wof:placetype":"venue"
},
  "geometry": {"coordinates":[12.1719198227,47.8375587463],"type":"Point"}
}