{
  "type": "Feature",
  "properties": {
    "iso:country":"AT",
    "sg:address":"Kogler Str 7",
    "sg:city":"Sieghartskirchen",
    "sg:orig_category":"Bestattungsunternehmen",
    "sg:phone":"+43 2274 2229",
    "sg:postcode":"3443",
    "sg:province":"Nieder\u00f6sterreich",
    "wof:name":"Geiger Hermann Mag",
    "wof:placetype":"venue"
},
  "geometry": {"coordinates":[16.0116348267,48.2488479614],"type":"Point"}
}