{
  "type": "Feature",
  "properties": {
    "addr:full":"Nr 3 Aflenz Kurort Steiermark 8623",
    "addr:postcode":"8623",
    "addr:street":"Nr",
    "iso:country":"AT",
    "sg:address":"Nr 3",
    "sg:city":"Aflenz Kurort",
    "sg:orig_category":"Blumeneinzelhandel",
    "sg:phone":"+43 3861 2205",
    "sg:postcode":"8623",
    "sg:province":"Steiermark",
    "wof:name":"Blumenshop Claudia",
    "wof:placetype":"venue"
},
  "geometry": {"coordinates":[15.2384824753,47.5437736511],"type":"Point"}
}