{
  "type": "Feature",
  "properties": {
    "addr:full":"Ignaz Pleyel-G 4/33 Wien Wien 1100",
    "addr:housenumber":"4 / 33",
    "addr:postcode":"1100",
    "addr:street":"Ignaz Pleyel-G",
    "iso:country":"AT",
    "sg:address":"Ignaz Pleyel-G 4/33",
    "sg:city":"Wien",
    "sg:orig_category":"Handelsagenturen",
    "sg:phone":"+43 1 9712271",
    "sg:postcode":"1100",
    "sg:province":"Wien",
    "wof:name":"Rosenberg Franz",
    "wof:placetype":"venue"
},
  "geometry": {"coordinates":[16.3633365631,48.1568641663],"type":"Point"}
}