{
  "type": "Feature",
  "properties": {
    "addr:full":"Wiener G 104 Perchtoldsdorf Nieder\u00f6sterreich 2380",
    "addr:housenumber":"104",
    "addr:postcode":"2380",
    "addr:street":"Wiener G",
    "iso:country":"AT",
    "sg:address":"Wiener G 104",
    "sg:city":"Perchtoldsdorf",
    "sg:orig_category":"Werbeagenturen",
    "sg:phone":"+43 1 86745230",
    "sg:postcode":"2380",
    "sg:province":"Nieder\u00f6sterreich",
    "wof:name":"Sterba Berenika",
    "wof:placetype":"venue"
},
  "geometry": {"coordinates":[16.2740211487,48.1263618469],"type":"Point"}
}