{
  "type": "Feature",
  "properties": {
    "addr:full":"Ischlerbahnstr 1 Salzburg Salzburg 5020",
    "addr:housenumber":"1",
    "addr:postcode":"5020",
    "addr:street":"Ischlerbahnstr;Salzburg",
    "iso:country":"AT",
    "sg:address":"Ischlerbahnstr 1",
    "sg:city":"Salzburg",
    "sg:orig_category":"Friseure U Frisiersalons",
    "sg:phone":"+43 662 460571",
    "sg:postcode":"5020",
    "sg:province":"Salzburg",
    "wof:name":"Frisiersalon Trude",
    "wof:placetype":"venue"
},
  "geometry": {"coordinates":[13.0470113754,47.8188858032],"type":"Point"}
}