{
  "type": "Feature",
  "properties": {
    "addr:full":"Schmiedlstr 16 St. Peter Steiermark 8042",
    "addr:housenumber":"16",
    "addr:postcode":"8042",
    "addr:street":"Schmiedlstr",
    "iso:country":"AT",
    "sg:address":"Schmiedlstr 16",
    "sg:city":"St. Peter",
    "sg:orig_category":"Fahrzeugbau",
    "sg:phone":"+43 4331 641070",
    "sg:postcode":"8042",
    "sg:province":"Steiermark",
    "wof:name":"Johnson Controls Austria GmbH & Co OHG",
    "wof:placetype":"venue"
},
  "geometry": {"coordinates":[15.4808797836,47.0453147888],"type":"Point"}
}