{
  "type": "Feature",
  "properties": {
    "addr:full":"Humboldtstr 33b Linz Ober\u00f6sterreich 4020",
    "addr:housenumber":"33b",
    "addr:postcode":"4020",
    "addr:street":"Humboldtstr",
    "iso:country":"AT",
    "sg:address":"Humboldtstr 33b",
    "sg:city":"Linz",
    "sg:orig_category":"Webdesign",
    "sg:phone":"+43 4366 02130934",
    "sg:postcode":"4020",
    "sg:province":"Ober\u00f6sterreich",
    "wof:name":"Webprofis Design",
    "wof:placetype":"venue"
},
  "geometry": {"coordinates":[14.2957296371,48.2975349426],"type":"Point"}
}