{
  "type": "Feature",
  "properties": {
    "iso:country":"AT",
    "sg:address":"Jahnstr 9",
    "sg:city":"Linz",
    "sg:classifiers":[
        {
            "category":"Restaurant",
            "type":"Food & Drink"
        }
    ],
    "sg:phone":"+43 732 732097",
    "sg:postcode":"4040",
    "sg:province":"Ober\u00f6sterreich",
    "wof:name":"Golden Pub & Snack",
    "wof:placetype":"venue"
},
  "geometry": {"coordinates":[14.2826890945,48.3129653931],"type":"Point"}
}