{
  "type": "Feature",
  "properties": {
    "iso:country":"AT",
    "sg:address":"Johannesstr 94",
    "sg:city":"Maria Enzersdorf",
    "sg:classifiers":[
        {
            "category":"Travel",
            "subcategory":"Hotels & Motels",
            "type":"Entertainment"
        }
    ],
    "sg:phone":"+43 2236 224030",
    "sg:postcode":"2344",
    "sg:province":"Nieder\u00f6sterreich",
    "wof:name":"Hotel-Restaurant Hotwagner",
    "wof:placetype":"venue"
},
  "geometry": {"coordinates":[16.2667331696,48.0928688049],"type":"Point"}
}