{
  "type": "Feature",
  "properties": {
    "addr:full":"Technologiezentrum Marktstr 3 Eisenstadt Burgenland 7000",
    "addr:housenumber":"3",
    "addr:postcode":"7000",
    "iso:country":"AT",
    "sg:address":"Technologiezentrum Marktstr 3",
    "sg:city":"Eisenstadt",
    "sg:classifiers":[
        {
            "category":"Banks & Credit Unions",
            "subcategory":"Investment Brokerage",
            "type":"Services"
        }
    ],
    "sg:phone":"+43 4359 010940",
    "sg:postcode":"7000",
    "sg:province":"Burgenland",
    "sg:tags":[
        "management",
        "facility"
    ],
    "wof:name":"FMB Facility Management Burgenland GmbH",
    "wof:placetype":"venue"
},
  "geometry": {"coordinates":[16.5189552307,47.8455657959],"type":"Point"}
}