{
  "type": "Feature",
  "properties": {
    "iso:country":"AT",
    "sg:address":"Nr 194",
    "sg:city":"Ottenthal",
    "sg:orig_category":"Gemeinden",
    "sg:phone":"+43 4325 548181",
    "sg:postcode":"2163",
    "sg:province":"Nieder\u00f6sterreich",
    "wof:name":"Gemeindeamt Ottenthal",
    "wof:placetype":"venue"
},
  "geometry": {"coordinates":[16.5781784058,48.7612380981],"type":"Point"}
}