{
  "type": "Feature",
  "properties": {
    "addr:full":"Brunnenfeldg 18 Peuerbach Ober\u00f6sterreich 4722",
    "addr:housenumber":"18",
    "addr:postcode":"4722",
    "addr:street":"Brunnenfeldg",
    "iso:country":"AT",
    "sg:address":"Brunnenfeldg 18",
    "sg:city":"Peuerbach",
    "sg:orig_category":"Rauchfangkehrer",
    "sg:phone":"+43 7276 2384",
    "sg:postcode":"4722",
    "sg:province":"Ober\u00f6sterreich",
    "wof:name":"Wallnegger Martin",
    "wof:placetype":"venue"
},
  "geometry": {"coordinates":[13.7688970566,48.3472290039],"type":"Point"}
}