{
  "type": "Feature",
  "properties": {
    "iso:country":"AT",
    "sg:address":"Brunnenfeldg 18",
    "sg:city":"Peuerbach",
    "sg:orig_category":"Rauchfangkehrer",
    "sg:phone":"+43 7276 2384",
    "sg:postcode":"4722",
    "sg:province":"Ober\u00f6sterreich",
    "wof:name":"Wallnegger Martin",
    "wof:placetype":"venue"
},
  "geometry": {"coordinates":[13.7688970566,48.3472290039],"type":"Point"}
}