{
  "type": "Feature",
  "properties": {
    "iso:country":"AT",
    "sg:address":"Hauptstr 62",
    "sg:city":"St. Johann im Pongau",
    "sg:orig_category":"Siebdruckereien",
    "sg:phone":"+43 6412 7486",
    "sg:postcode":"5600",
    "sg:province":"Salzburg",
    "wof:name":"Pongauer Siebdruck",
    "wof:placetype":"venue"
},
  "geometry": {"coordinates":[13.1988716125,47.345413208],"type":"Point"}
}