{
  "type": "Feature",
  "properties": {
    "addr:full":"Seizer Str. 2  Trofaiach Steiermark 8793",
    "addr:housenumber":"2",
    "addr:postcode":"8793",
    "addr:street":"Str.",
    "iso:country":"AT",
    "sg:address":"Seizer Str. 2 ",
    "sg:city":"Trofaiach",
    "sg:classifiers":[
        {
            "category":"Professional",
            "subcategory":"Engineering",
            "type":"Services"
        }
    ],
    "sg:phone":"+43 4338 472365",
    "sg:postcode":"8793",
    "sg:province":"Steiermark",
    "sg:tags":[
        "machine",
        "-",
        "mechanical"
    ],
    "wof:name":"TSCHINKEL MASCHINEN UND ANLAGENBAU GESMBH",
    "wof:placetype":"venue"
},
  "geometry": {"coordinates":[14.969628334,47.4129219055],"type":"Point"}
}