{
  "type": "Feature",
  "properties": {
    "addr:full":"Diehlgasse 35 Wien Wien 1050",
    "addr:housenumber":"35",
    "addr:postcode":"1050",
    "addr:street":"Diehlgasse",
    "iso:country":"AT",
    "sg:address":"Diehlgasse 35",
    "sg:city":"Wien",
    "sg:classifiers":[
        {
            "category":"Building & Trades",
            "subcategory":"Electrical",
            "type":"Services"
        }
    ],
    "sg:phone":"+43 1 5483904",
    "sg:postcode":"1050",
    "sg:province":"Wien",
    "sg:tags":[
        "industry",
        "installation"
    ],
    "wof:name":"Andreas Moser",
    "wof:placetype":"venue"
},
  "geometry": {"coordinates":[16.3481998444,48.18516922],"type":"Point"}
}