{
  "type": "Feature",
  "properties": {
    "addr:full":"Gartenweg 109 Strobl Salzburg 5350",
    "addr:housenumber":"109",
    "addr:postcode":"5350",
    "addr:street":"Gartenweg;Salzburg",
    "iso:country":"AT",
    "sg:address":"Gartenweg 109",
    "sg:city":"Strobl",
    "sg:orig_category":"Pensionen / Privatzimmer",
    "sg:phone":"+43 6137 7396",
    "sg:postcode":"5350",
    "sg:province":"Salzburg",
    "wof:name":"Pension Barbara",
    "wof:placetype":"venue"
},
  "geometry": {"coordinates":[13.4785995483,47.7162055969],"type":"Point"}
}