{
  "type": "Feature",
  "properties": {
    "addr:full":"Einsiedlerstr 22 Asten Ober\u00f6sterreich 4481",
    "addr:housenumber":"22",
    "addr:postcode":"4481",
    "addr:street":"Einsiedlerstr",
    "iso:country":"AT",
    "sg:address":"Einsiedlerstr 22",
    "sg:city":"Asten",
    "sg:orig_category":"Lebens- U Sozialberatung",
    "sg:phone":"+43 7224 65868",
    "sg:postcode":"4481",
    "sg:province":"Ober\u00f6sterreich",
    "wof:name":"Prinz Maria",
    "wof:placetype":"venue"
},
  "geometry": {"coordinates":[14.4270410538,48.2259597778],"type":"Point"}
}