{
  "type": "Feature",
  "properties": {
    "addr:full":"Perschling 3 Frankenburg am Hausruck Ober\u00f6sterreich 4873",
    "addr:housenumber":"3",
    "addr:postcode":"4873",
    "iso:country":"AT",
    "sg:address":"Perschling 3",
    "sg:city":"Frankenburg am Hausruck",
    "sg:orig_category":"Elektromotoren / Reparatur U Wicklerei",
    "sg:phone":"+43 4376 835005",
    "sg:postcode":"4873",
    "sg:province":"Ober\u00f6sterreich",
    "wof:name":"Kr\u00f6ll Josef",
    "wof:placetype":"venue"
},
  "geometry": {"coordinates":[13.4651069641,48.0878677368],"type":"Point"}
}