{
  "type": "Feature",
  "properties": {
    "addr:full":"Haselbach 17 Altenfelden Ober\u00f6sterreich 4121",
    "addr:housenumber":"17",
    "addr:postcode":"4121",
    "addr:street":"Haselbach",
    "iso:country":"AT",
    "sg:address":"Haselbach 17",
    "sg:city":"Altenfelden",
    "sg:classifiers":[
        {
            "category":"Farming",
            "subcategory":"Livestock Farm",
            "type":"Manufacturing & Wholesale Goods"
        }
    ],
    "sg:phone":"+43 4372 825569",
    "sg:postcode":"4121",
    "sg:province":"Ober\u00f6sterreich",
    "sg:tags":[
        "-handel",
        "viehzucht",
        "u"
    ],
    "wof:name":"Zauner Maria",
    "wof:placetype":"venue"
},
  "geometry": {"coordinates":[13.9686498642,48.4965286255],"type":"Point"}
}