{
  "type": "Feature",
  "properties": {
    "iso:country":"AT",
    "sg:address":"Rathausstr 10",
    "sg:city":"Krummnu\u00dfbaum",
    "sg:orig_category":"Hauptschulen",
    "sg:phone":"+43 2757 2424",
    "sg:postcode":"3375",
    "sg:province":"Nieder\u00f6sterreich",
    "wof:name":"Hauptschule",
    "wof:placetype":"venue"
},
  "geometry": {"coordinates":[-90.31578063960001,39.3304100037],"type":"Point"}
}