{
  "type": "Feature",
  "properties": {
    "addr:full":"Stadtpl 37 Gm\u00fcnd Nieder\u00f6sterreich 3950",
    "addr:housenumber":"37",
    "addr:postcode":"3950",
    "addr:street":"Stadtpl;Niederoesterreich",
    "iso:country":"AT",
    "sg:address":"Stadtpl 37",
    "sg:city":"Gm\u00fcnd",
    "sg:orig_category":"Apotheken",
    "sg:phone":"+43 2852 523040",
    "sg:postcode":"3950",
    "sg:province":"Nieder\u00f6sterreich",
    "wof:name":"Apotheke Zum Auge Gottes",
    "wof:placetype":"venue"
},
  "geometry": {"coordinates":[14.9865989685,48.7731819153],"type":"Point"}
}