{
  "type": "Feature",
  "properties": {
    "addr:full":"Gleinker G 32 Steyr Ober\u00f6sterreich 4400",
    "addr:housenumber":"32",
    "addr:postcode":"4400",
    "addr:street":"Gleinker G;Oberoesterreich",
    "iso:country":"AT",
    "sg:address":"Gleinker G 32",
    "sg:city":"Steyr",
    "sg:orig_category":"Steinmetzbetriebe",
    "sg:phone":"+43 7252 73323",
    "sg:postcode":"4400",
    "sg:province":"Ober\u00f6sterreich",
    "wof:name":"Strasser Steinbau GmbH",
    "wof:placetype":"venue"
},
  "geometry": {"coordinates":[14.4179086685,48.0453529358],"type":"Point"}
}