{
  "type": "Feature",
  "properties": {
    "addr:full":"Teisenberggasse 43 Salzburg Salzburg 5020",
    "addr:housenumber":"43",
    "addr:postcode":"5020",
    "addr:street":"Teisenberggasse;Salzburg",
    "iso:country":"AT",
    "sg:address":"Teisenberggasse 43",
    "sg:city":"Salzburg",
    "sg:classifiers":[
        {
            "category":"Banks & Credit Unions",
            "subcategory":"Financial Services",
            "type":"Services"
        }
    ],
    "sg:phone":"+43 662 434392",
    "sg:postcode":"5020",
    "sg:province":"Salzburg",
    "sg:tags":[
        "disposal",
        "barrel",
        "used",
        "filters",
        "oil"
    ],
    "sg:website":"kirchgassner.at",
    "wof:name":"H. Kirchga\u00dfner Ges.m.b.H.",
    "wof:placetype":"venue"
},
  "geometry": {"coordinates":[13.0073432922,47.8037071228],"type":"Point"}
}