{
  "type": "Feature",
  "properties": {
    "addr:full":"Horner Bundesstr. 103  Stockerau Nieder\u00f6sterreich 2000",
    "addr:housenumber":"103",
    "addr:postcode":"2000",
    "iso:country":"AT",
    "sg:address":"Horner Bundesstr. 103 ",
    "sg:city":"Stockerau",
    "sg:classifiers":[
        {
            "category":"Home & Garden",
            "subcategory":"Home Furnishings",
            "type":"Retail Goods"
        }
    ],
    "sg:phone":"+43 4322 66640810",
    "sg:postcode":"2000",
    "sg:province":"Nieder\u00f6sterreich",
    "sg:tags":[
        "household"
    ],
    "wof:name":"FIFTY SELBSTBAUM\u00d6BEL GESMBH",
    "wof:placetype":"venue"
},
  "geometry": {"coordinates":[16.1787166595,48.3894119263],"type":"Point"}
}