{
  "type": "Feature",
  "properties": {
    "addr:full":"Stadtpl 7 Steyr Ober\u00f6sterreich 4400",
    "addr:housenumber":"7",
    "addr:postcode":"4400",
    "addr:street":"Stadtpl;Oberoesterreich",
    "iso:country":"AT",
    "sg:address":"Stadtpl 7",
    "sg:city":"Steyr",
    "sg:orig_category":"Apotheken",
    "sg:phone":"+43 7252 52020",
    "sg:postcode":"4400",
    "sg:province":"Ober\u00f6sterreich",
    "wof:name":"Alte Stadtapotheke",
    "wof:placetype":"venue"
},
  "geometry": {"coordinates":[14.42004776,48.0399971008],"type":"Point"}
}