{
  "type": "Feature",
  "properties": {
    "addr:full":"Hauptstr 31 Zillingtal Burgenland 7034",
    "addr:housenumber":"31",
    "addr:postcode":"7034",
    "addr:street":"Hauptstr",
    "iso:country":"AT",
    "sg:address":"Hauptstr 31",
    "sg:city":"Zillingtal",
    "sg:orig_category":"Gutsverwaltungen",
    "sg:phone":"+43 2688 72163",
    "sg:postcode":"7034",
    "sg:province":"Burgenland",
    "wof:name":"Pinterits Alexander Ing",
    "wof:placetype":"venue"
},
  "geometry": {"coordinates":[16.405828476,47.8152885437],"type":"Point"}
}