{
  "type": "Feature",
  "properties": {
    "iso:country":"AT",
    "sg:address":"Heiligenst\u00e4dter Str 35-43",
    "sg:city":"Wien",
    "sg:orig_category":"Spirituosen / Erzeugung U Gro\u00c3\u0178handel",
    "sg:phone":"+43 4313 6822580",
    "sg:postcode":"1190",
    "sg:province":"Wien",
    "wof:name":"Rossbacher Vertriebs GmbH",
    "wof:placetype":"venue"
},
  "geometry": {"coordinates":[16.3571529388,48.2369689941],"type":"Point"}
}