{
  "type": "Feature",
  "properties": {
    "iso:country":"AT",
    "sg:address":"Thallener Ortsstr 13",
    "sg:city":"Sitzenberg-Reidling",
    "sg:orig_category":"Hunde- U Katzensalons",
    "sg:phone":"+43 4322 766562",
    "sg:postcode":"3454",
    "sg:province":"Nieder\u00f6sterreich",
    "wof:name":"Hunde- und Katzensalon Johanna Klinger",
    "wof:placetype":"venue"
},
  "geometry": {"coordinates":[15.8009738922,48.3223686218],"type":"Point"}
}