{
  "type": "Feature",
  "properties": {
    "iso:country":"AT",
    "sg:address":"Wiener Str 69",
    "sg:city":"Bruck an der Mur",
    "sg:classifiers":[
        {
            "category":"Restaurant",
            "type":"Food & Drink"
        }
    ],
    "sg:phone":"+43 3862 588110",
    "sg:postcode":"8600",
    "sg:province":"Steiermark",
    "sg:tags":[
        "pizzeria"
    ],
    "sg:website":"lapizza.at",
    "wof:name":"Pizzeria La Pizza",
    "wof:placetype":"venue"
},
  "geometry": {"coordinates":[15.2737178802,47.4208602905],"type":"Point"}
}