{
  "type": "Feature",
  "properties": {
    "addr:full":"Hauptstr 3 Willendorf am Steinfelde Nieder\u00f6sterreich 2732",
    "addr:housenumber":"3",
    "addr:postcode":"2732",
    "addr:street":"Hauptstr;Niederoesterreich",
    "iso:country":"AT",
    "sg:address":"Hauptstr 3",
    "sg:city":"Willendorf am Steinfelde",
    "sg:orig_category":"Spenglereien",
    "sg:phone":"+43 2620 2216",
    "sg:postcode":"2732",
    "sg:province":"Nieder\u00f6sterreich",
    "wof:name":"Gerhartl Johannes",
    "wof:placetype":"venue"
},
  "geometry": {"coordinates":[16.0571155548,47.7895393372],"type":"Point"}
}