{
  "type": "Feature",
  "properties": {
    "iso:country":"AT",
    "sg:address":"Himberger Str 8",
    "sg:city":"Wien",
    "sg:orig_category":"Friseure U Frisiersalons",
    "sg:phone":"+43 4316 885556",
    "sg:postcode":"1100",
    "sg:province":"Wien",
    "wof:name":"Aigner Ernst",
    "wof:placetype":"venue"
},
  "geometry": {"coordinates":[16.3824138641,48.1443824768],"type":"Point"}
}