{
  "type": "Feature",
  "properties": {
    "addr:full":"Marktpl 3 Mattsee Salzburg 5163",
    "addr:housenumber":"3",
    "addr:postcode":"5163",
    "addr:street":"Marktpl;Salzburg",
    "iso:country":"AT",
    "sg:address":"Marktpl 3",
    "sg:city":"Mattsee",
    "sg:orig_category":"Juweliere, Gold- U Silberschmiede",
    "sg:phone":"+43 4366 44345476",
    "sg:postcode":"5163",
    "sg:province":"Salzburg",
    "wof:name":"Schmuckatelier Eder Rosemarie",
    "wof:placetype":"venue"
},
  "geometry": {"coordinates":[13.1047401428,47.9702911377],"type":"Point"}
}