{
  "type": "Feature",
  "properties": {
    "iso:country":"AT",
    "sg:address":"Hauptstr 4",
    "sg:city":"Wallern im Burgenland",
    "sg:orig_category":"Feuerwehren",
    "sg:phone":"+43 2174 2784",
    "sg:postcode":"7151",
    "sg:province":"Burgenland",
    "wof:name":"Freiwillige Feuerwehr Wallern im Burgenland",
    "wof:placetype":"venue"
},
  "geometry": {"coordinates":[16.9368896484,47.725276947],"type":"Point"}
}