{
  "type": "Feature",
  "properties": {
    "iso:country":"AT",
    "sg:address":"Nr 157",
    "sg:city":"Turnau",
    "sg:orig_category":"Friseure U Frisiersalons",
    "sg:phone":"+43 3863 2929",
    "sg:postcode":"8625",
    "sg:province":"Steiermark",
    "wof:name":"Praschl Christine",
    "wof:placetype":"venue"
},
  "geometry": {"coordinates":[-0.1163489968,45.6774291992],"type":"Point"}
}