{
  "type": "Feature",
  "properties": {
    "iso:country":"AT",
    "sg:address":"Markt 158",
    "sg:city":"Wagrain",
    "sg:orig_category":"Appartements / Ferienwohnungen",
    "sg:phone":"+43 4364 138379",
    "sg:postcode":"5602",
    "sg:province":"Salzburg",
    "wof:name":"Seer Isolde u Stefan",
    "wof:placetype":"venue"
},
  "geometry": {"coordinates":[13.295126915,47.3341255188],"type":"Point"}
}