{
  "type": "Feature",
  "properties": {
    "addr:full":"Badstr 17 Bad Schallerbach Ober\u00f6sterreich 4701",
    "addr:housenumber":"17",
    "addr:postcode":"4701",
    "addr:street":"Badstr",
    "iso:country":"AT",
    "sg:address":"Badstr 17",
    "sg:city":"Bad Schallerbach",
    "sg:orig_category":"Pensionen / Privatzimmer",
    "sg:phone":"+43 7249 48169",
    "sg:postcode":"4701",
    "sg:province":"Ober\u00f6sterreich",
    "wof:name":"Baumgartner Barbara",
    "wof:placetype":"venue"
},
  "geometry": {"coordinates":[13.9195642471,48.2299766541],"type":"Point"}
}