{
  "type": "Feature",
  "properties": {
    "iso:country":"AT",
    "sg:address":"Sch\u00f6nau an der Donau 32",
    "sg:city":"Gro\u00df-Enzersdorf",
    "sg:classifiers":[
        {
            "category":"Retail",
            "subcategory":"Auto Rental",
            "type":"Services"
        }
    ],
    "sg:phone":"+43 2215 2193",
    "sg:postcode":"2301",
    "sg:province":"Nieder\u00f6sterreich",
    "sg:tags":[
        "machine",
        "hedge",
        "electric",
        "clipping"
    ],
    "sg:website":"kommendisch-enz.at",
    "wof:name":"Kommendisch-Enz KEG",
    "wof:placetype":"venue"
},
  "geometry": {"coordinates":[16.6139736176,48.1453094482],"type":"Point"}
}