{
  "type": "Feature",
  "properties": {
    "addr:full":"Roittnerstr 26 Salzburg Salzburg 5020",
    "addr:housenumber":"26",
    "addr:postcode":"5020",
    "addr:street":"Roittnerstr;Salzburg",
    "iso:country":"AT",
    "sg:address":"Roittnerstr 26",
    "sg:city":"Salzburg",
    "sg:orig_category":"Unterhaltungselektronik / Reparatur",
    "sg:phone":"+43 662 882157",
    "sg:postcode":"5020",
    "sg:province":"Salzburg",
    "wof:name":"Fernseh & Videoservice Peter Laudenbach",
    "wof:placetype":"venue"
},
  "geometry": {"coordinates":[13.0579376221,47.8125953674],"type":"Point"}
}