{
  "type": "Feature",
  "properties": {
    "addr:full":"Hof 12 Schwarzenberg Vorarlberg 6867",
    "addr:housenumber":"12",
    "addr:postcode":"6867",
    "addr:street":"Hof",
    "iso:country":"AT",
    "sg:address":"Hof 12",
    "sg:city":"Schwarzenberg",
    "sg:orig_category":"Tischlereien",
    "sg:phone":"+43 4355 122924",
    "sg:postcode":"6867",
    "sg:province":"Vorarlberg",
    "wof:name":"Z\u00fcndel Anton",
    "wof:placetype":"venue"
},
  "geometry": {"coordinates":[9.8520126343,47.414352417],"type":"Point"}
}