{
  "type": "Feature",
  "properties": {
    "addr:full":"Kaufpark 6 Walding Ober\u00f6sterreich 4111",
    "addr:housenumber":"6",
    "addr:postcode":"4111",
    "addr:street":"Kaufpark",
    "iso:country":"AT",
    "sg:address":"Kaufpark 6",
    "sg:city":"Walding",
    "sg:orig_category":"Bekleidung / Einzelhandel",
    "sg:phone":"+43 7234 84867",
    "sg:postcode":"4111",
    "sg:province":"Ober\u00f6sterreich",
    "wof:name":"Takko ModeMarkt GmbH",
    "wof:placetype":"venue"
},
  "geometry": {"coordinates":[14.1604337692,48.3448028564],"type":"Point"}
}