{
  "type": "Feature",
  "properties": {
    "addr:full":"Innrain 25 Innsbruck Tirol 6020",
    "addr:housenumber":"25",
    "addr:postcode":"6020",
    "addr:street":"Innrain;Tirol",
    "iso:country":"AT",
    "sg:address":"Innrain 25",
    "sg:city":"Innsbruck",
    "sg:orig_category":"Steuerberatung",
    "sg:phone":"+43 4351 2599660",
    "sg:postcode":"6020",
    "sg:province":"Tirol",
    "wof:name":"Alpina Treuhand SteuerberatungsgesmbH",
    "wof:placetype":"venue"
},
  "geometry": {"coordinates":[11.3894109726,47.2656211853],"type":"Point"}
}