{
  "type": "Feature",
  "properties": {
    "addr:full":"Bahnhofplatz 8 Bad Gastein Salzburg 5640",
    "addr:housenumber":"8",
    "addr:postcode":"5640",
    "addr:street":"Bahnhofplatz;Salzburg",
    "iso:country":"AT",
    "sg:address":"Bahnhofplatz 8",
    "sg:city":"Bad Gastein",
    "sg:orig_category":"Reisen, Reiseveranstalter",
    "sg:phone":"+43 6434 2330",
    "sg:postcode":"5640",
    "sg:province":"Salzburg",
    "sg:website":"hotelkrone.gastein.at",
    "wof:name":"Hotel Krone Badgastein",
    "wof:placetype":"venue"
},
  "geometry": {"coordinates":[13.1334447861,47.1097793579],"type":"Point"}
}