{
  "type": "Feature",
  "properties": {
    "addr:full":"Schidlachstr 3 Innsbruck Tirol 6020",
    "addr:housenumber":"3",
    "addr:postcode":"6020",
    "addr:street":"Schidlachstr;Tirol",
    "iso:country":"AT",
    "sg:address":"Schidlachstr 3",
    "sg:city":"Innsbruck",
    "sg:orig_category":"Psychotherapie",
    "sg:phone":"+43 699 10478453",
    "sg:postcode":"6020",
    "sg:province":"Tirol",
    "wof:name":"R\u00f6ssler Silvia Mag",
    "wof:placetype":"venue"
},
  "geometry": {"coordinates":[11.3971586227,47.2583656311],"type":"Point"}
}