{
  "type": "Feature",
  "properties": {
    "addr:full":"Ferdinand-Jergitsch-Str 15 Klagenfurt K\u00e4rnten 9020",
    "addr:housenumber":"15",
    "addr:postcode":"9020",
    "addr:street":"Ferdinand-Jergitsch-Str;Kaernten",
    "iso:country":"AT",
    "sg:address":"Ferdinand-Jergitsch-Str 15",
    "sg:city":"Klagenfurt",
    "sg:classifiers":[
        {
            "category":"Home & Garden",
            "subcategory":"Building Materials",
            "type":"Retail Goods"
        }
    ],
    "sg:phone":"+43 4346 3566760",
    "sg:postcode":"9020",
    "sg:province":"K\u00e4rnten",
    "sg:tags":[
        "baustoffe",
        "-material",
        "u"
    ],
    "wof:name":"Knoch, Kern & Co",
    "wof:placetype":"venue"
},
  "geometry": {"coordinates":[14.295592308,46.6252212524],"type":"Point"}
}