{
  "type": "Feature",
  "properties": {
    "iso:country":"AT",
    "sg:address":"Oberhoferstr 2",
    "sg:city":"Mistelbach",
    "sg:orig_category":"Bekleidung / Einzelhandel",
    "sg:phone":"+43 2572 322060",
    "sg:postcode":"2130",
    "sg:province":"Nieder\u00f6sterreich",
    "wof:name":"KBS Kleider Bauer Betriebs-GmbH",
    "wof:placetype":"venue"
},
  "geometry": {"coordinates":[16.5728168488,48.5707511902],"type":"Point"}
}