{
  "type": "Feature",
  "properties": {
    "addr:full":"Schwimmbadweg 1 Braz Vorarlberg 6751",
    "addr:housenumber":"1",
    "addr:postcode":"6751",
    "addr:street":"Schwimmbadweg",
    "iso:country":"AT",
    "sg:address":"Schwimmbadweg 1",
    "sg:city":"Braz",
    "sg:orig_category":"Blumeneinzelhandel",
    "sg:phone":"+43 5552 28161",
    "sg:postcode":"6751",
    "sg:province":"Vorarlberg",
    "wof:name":"Sowhemo Blumen Atelier",
    "wof:placetype":"venue"
},
  "geometry": {"coordinates":[9.9180688858,47.144695282],"type":"Point"}
}