{
  "type": "Feature",
  "properties": {
    "addr:full":"Zugallistr 7 Salzburg Salzburg 5020",
    "addr:housenumber":"7",
    "addr:postcode":"5020",
    "addr:street":"Zugallistr;Salzburg",
    "iso:country":"AT",
    "sg:address":"Zugallistr 7",
    "sg:city":"Salzburg",
    "sg:classifiers":[
        {
            "category":"Restaurant",
            "type":"Food & Drink"
        }
    ],
    "sg:phone":"+43 662 848843",
    "sg:postcode":"5020",
    "sg:province":"Salzburg",
    "wof:name":"Restaurant Purzelbaum",
    "wof:placetype":"venue"
},
  "geometry": {"coordinates":[13.05119133,47.7941055298],"type":"Point"}
}