{
  "type": "Feature",
  "properties": {
    "iso:country":"AT",
    "sg:address":"Leopold Resch-Weg 9",
    "sg:city":"Drobollach am Faaker See",
    "sg:orig_category":"Pensionen / Privatzimmer",
    "sg:phone":"+43 4254 24150",
    "sg:postcode":"9580",
    "sg:province":"K\u00e4rnten",
    "wof:name":"G\u00e4stehaus Ulbing",
    "wof:placetype":"venue"
},
  "geometry": {"coordinates":[-89.92952728269999,37.2506599426],"type":"Point"}
}