{
  "type": "Feature",
  "properties": {
    "addr:full":"Augartenstr 49 Lustenau Vorarlberg 6890",
    "addr:housenumber":"49",
    "addr:postcode":"6890",
    "addr:street":"Augartenstr",
    "iso:country":"AT",
    "sg:address":"Augartenstr 49",
    "sg:city":"Lustenau",
    "sg:orig_category":"Stickereien",
    "sg:phone":"+43 5577 84147",
    "sg:postcode":"6890",
    "sg:province":"Vorarlberg",
    "wof:name":"B\u00f6sch Peter & Teresa",
    "wof:placetype":"venue"
},
  "geometry": {"coordinates":[9.6551361084,47.4429397583],"type":"Point"}
}