{
  "type": "Feature",
  "properties": {
    "addr:full":"Hauptpl 8 Gaweinstal Nieder\u00f6sterreich 2191",
    "addr:housenumber":"8",
    "addr:postcode":"2191",
    "addr:street":"Hauptpl",
    "iso:country":"AT",
    "sg:address":"Hauptpl 8",
    "sg:city":"Gaweinstal",
    "sg:orig_category":"Friseure U Frisiersalons",
    "sg:phone":"+43 2574 2144",
    "sg:postcode":"2191",
    "sg:province":"Nieder\u00f6sterreich",
    "wof:name":"Anton's Frisierstube",
    "wof:placetype":"venue"
},
  "geometry": {"coordinates":[16.590139389,48.4765129089],"type":"Point"}
}