{
  "type": "Feature",
  "properties": {
    "iso:country":"AT",
    "sg:address":"Sebastian-Brunner-G 3",
    "sg:city":"Wien",
    "sg:orig_category":"Ingenieurkonsulenten / Zivilingenieure",
    "sg:phone":"+43 1 87705560",
    "sg:postcode":"1130",
    "sg:province":"Wien",
    "sg:website":"machu.co.at",
    "wof:name":"Machu Dipl-Ing Dr techn Erich H FIMechE",
    "wof:placetype":"venue"
},
  "geometry": {"coordinates":[16.282245636,48.179599762],"type":"Point"}
}