{
  "type": "Feature",
  "properties": {
    "addr:full":"Kinkstrasse 5  Kufstein Tirol 6330",
    "addr:housenumber":"5",
    "addr:postcode":"6330",
    "addr:street":"Kinkstrasse;Tirol",
    "iso:country":"AT",
    "sg:address":"Kinkstrasse 5 ",
    "sg:city":"Kufstein",
    "sg:classifiers":[
        {
            "category":"Arts & Performance",
            "subcategory":"Art Gallery",
            "type":"Entertainment"
        }
    ],
    "sg:phone":"+43 5335 2207",
    "sg:postcode":"6330",
    "sg:province":"Tirol",
    "sg:tags":[
        "painting"
    ],
    "sg:website":"www.galerie-merci.at",
    "wof:name":"Galerie Merci Inh. Margit Ainberger",
    "wof:placetype":"venue"
},
  "geometry": {"coordinates":[12.1706142426,47.5812492371],"type":"Point"}
}