{
  "type": "Feature",
  "properties": {
    "iso:country":"AT",
    "sg:address":"Hauptpl 15",
    "sg:city":"Jennersdorf",
    "sg:orig_category":"Bildungsservice / Allgemeine Informationsstellen",
    "sg:phone":"+43 3329 489100",
    "sg:postcode":"8380",
    "sg:province":"Burgenland",
    "wof:name":"Bezirksschulrat Jennersdorf",
    "wof:placetype":"venue"
},
  "geometry": {"coordinates":[16.1414546967,46.9369392395],"type":"Point"}
}