{
  "type": "Feature",
  "properties": {
    "addr:full":"Walser Str 60 Riezlern Vorarlberg 6991",
    "addr:postcode":"6991",
    "addr:street":"Str 60",
    "iso:country":"AT",
    "sg:address":"Walser Str 60",
    "sg:city":"Riezlern",
    "sg:classifiers":[
        {
            "category":"Restaurant",
            "type":"Food & Drink"
        }
    ],
    "sg:phone":"+43 4355 173261",
    "sg:postcode":"6991",
    "sg:province":"Vorarlberg",
    "wof:name":"Cafe-Restaurant Gondelstube",
    "wof:placetype":"venue"
},
  "geometry": {"coordinates":[10.1853942871,47.3571624756],"type":"Point"}
}