{
  "type": "Feature",
  "properties": {
    "addr:full":"St.-Peter-Str 10 Gurk K\u00e4rnten 9342",
    "addr:housenumber":"10",
    "addr:postcode":"9342",
    "addr:street":"St.-Peter-Str;Kaernten",
    "iso:country":"AT",
    "sg:address":"St.-Peter-Str 10",
    "sg:city":"Gurk",
    "sg:orig_category":"Gefahrguttransporte",
    "sg:phone":"+43 4266 81630",
    "sg:postcode":"9342",
    "sg:province":"K\u00e4rnten",
    "wof:name":"Isopp Kathi GesmbH",
    "wof:placetype":"venue"
},
  "geometry": {"coordinates":[14.2865037918,46.8744697571],"type":"Point"}
}