{
  "type": "Feature",
  "properties": {
    "addr:full":"Salzburger Pl 6 Treibach-Althofen K\u00e4rnten 9330",
    "addr:housenumber":"6",
    "addr:postcode":"9330",
    "addr:street":"Salzburger Pl;Kaernten",
    "iso:country":"AT",
    "sg:address":"Salzburger Pl 6",
    "sg:city":"Treibach-Althofen",
    "sg:orig_category":"Immobilienmakler",
    "sg:phone":"+43 4262 3230",
    "sg:postcode":"9330",
    "sg:province":"K\u00e4rnten",
    "wof:name":"Nova Realit\u00e4ten GesmbH",
    "wof:placetype":"venue"
},
  "geometry": {"coordinates":[14.4744224548,46.8737792969],"type":"Point"}
}