{
  "type": "Feature",
  "properties": {
    "addr:full":"Triester Str 86 Ternitz Nieder\u00f6sterreich 2630",
    "addr:postcode":"2630",
    "addr:street":"Str 86",
    "iso:country":"AT",
    "sg:address":"Triester Str 86",
    "sg:city":"Ternitz",
    "sg:orig_category":"Lebensmittel / Einzelhandel",
    "sg:phone":"+43 2630 33437",
    "sg:postcode":"2630",
    "sg:province":"Nieder\u00f6sterreich",
    "wof:name":"Billa AG",
    "wof:placetype":"venue"
},
  "geometry": {"coordinates":[16.0390892029,47.7067909241],"type":"Point"}
}