{
  "type": "Feature",
  "properties": {
    "addr:full":"Schulg 13 Scheibbs Nieder\u00f6sterreich 3270",
    "addr:housenumber":"13",
    "addr:postcode":"3270",
    "addr:street":"Schulg",
    "iso:country":"AT",
    "sg:address":"Schulg 13",
    "sg:city":"Scheibbs",
    "sg:classifiers":[
        {
            "category":"Restaurant",
            "type":"Food & Drink"
        }
    ],
    "sg:phone":"+43 7482 43130",
    "sg:postcode":"3270",
    "sg:province":"Nieder\u00f6sterreich",
    "wof:name":"Restaurant Zum schwarzen Elefanten",
    "wof:placetype":"venue"
},
  "geometry": {"coordinates":[15.1679286957,48.00573349],"type":"Point"}
}