{
  "type": "Feature",
  "properties": {
    "iso:country":"AT",
    "sg:address":"Petzoldstr. 11",
    "sg:city":"Wels",
    "sg:classifiers":[
        {
            "category":"Wholesale",
            "subcategory":"Drugs",
            "type":"Manufacturing & Wholesale Goods"
        }
    ],
    "sg:phone":"+43 4372 42668110",
    "sg:postcode":"4600",
    "sg:province":"Ober\u00f6sterreich",
    "sg:tags":[
        "chemical",
        "pharmaceutical"
    ],
    "wof:name":"KLINGER GEBETSROITHER GES.MBH & CO. KG",
    "wof:placetype":"venue"
},
  "geometry": {"coordinates":[14.0658187866,48.1828918457],"type":"Point"}
}