{
  "type": "Feature",
  "properties": {
    "addr:full":"Markt 17 Wagrain Salzburg 5602",
    "addr:housenumber":"17",
    "addr:postcode":"5602",
    "addr:street":"Markt;Salzburg",
    "iso:country":"AT",
    "sg:address":"Markt 17",
    "sg:city":"Wagrain",
    "sg:orig_category":"Pensionen / Privatzimmer",
    "sg:phone":"+43 6413 8231",
    "sg:postcode":"5602",
    "sg:province":"Salzburg",
    "wof:name":"H\u00f6ller Frieda - Fr\u00fchst\u00fcckspension",
    "wof:placetype":"venue"
},
  "geometry": {"coordinates":[13.2967300415,47.3329200745],"type":"Point"}
}