{
  "type": "Feature",
  "properties": {
    "addr:full":"H\u00f6chster Str 8 Dornbirn Vorarlberg 6850",
    "addr:housenumber":"8",
    "addr:postcode":"6850",
    "addr:street":"Str",
    "iso:country":"AT",
    "sg:address":"H\u00f6chster Str 8",
    "sg:city":"Dornbirn",
    "sg:orig_category":"Holdinggesellschaften",
    "sg:phone":"+43 5572 5090",
    "sg:postcode":"6850",
    "sg:province":"Vorarlberg",
    "wof:name":"Zumtobel AG",
    "wof:placetype":"venue"
},
  "geometry": {"coordinates":[9.73554039,47.4072227478],"type":"Point"}
}