{
  "type": "Feature",
  "properties": {
    "addr:full":"Zeltinger Str 11 Bad Radkersburg Steiermark 8490",
    "addr:housenumber":"11",
    "addr:postcode":"8490",
    "addr:street":"Str",
    "iso:country":"AT",
    "sg:address":"Zeltinger Str 11",
    "sg:city":"Bad Radkersburg",
    "sg:orig_category":"Appartements / Ferienwohnungen",
    "sg:phone":"+43 3476 2178",
    "sg:postcode":"8490",
    "sg:province":"Steiermark",
    "wof:name":"Ferienhaus Manuel - Jauschnig-Kecht",
    "wof:placetype":"venue"
},
  "geometry": {"coordinates":[15.9992761612,46.6992073059],"type":"Point"}
}