{
  "type": "Feature",
  "properties": {
    "iso:country":"AT",
    "sg:address":"Radetzkystr 12",
    "sg:city":"Wien",
    "sg:orig_category":"Nachhilfe U Lernbetreuung",
    "sg:phone":"+43 4317 152263",
    "sg:postcode":"1030",
    "sg:province":"Wien",
    "wof:name":"Nachhilfezentrum",
    "wof:placetype":"venue"
},
  "geometry": {"coordinates":[16.3896560669,48.2108726501],"type":"Point"}
}