{
  "type": "Feature",
  "properties": {
    "iso:country":"AT",
    "sg:address":"Bahnhofstr 5",
    "sg:city":"Natters",
    "sg:orig_category":"\u00c3\u201erzte / F Allgemeinmedizin",
    "sg:phone":"+43 512 546725",
    "sg:postcode":"6161",
    "sg:province":"Tirol",
    "wof:name":"Abentung Johann Dr",
    "wof:placetype":"venue"
},
  "geometry": {"coordinates":[11.3760414124,47.2330131531],"type":"Point"}
}