{
  "type": "Feature",
  "properties": {
    "addr:full":"Hauptstr 293 Bad Mitterndorf Steiermark 8983",
    "addr:housenumber":"293",
    "addr:postcode":"8983",
    "addr:street":"Hauptstr",
    "iso:country":"AT",
    "sg:address":"Hauptstr 293",
    "sg:city":"Bad Mitterndorf",
    "sg:orig_category":"Werbeagenturen",
    "sg:phone":"+43 3623 6055",
    "sg:postcode":"8983",
    "sg:province":"Steiermark",
    "wof:name":"Demmerer Martin Mag",
    "wof:placetype":"venue"
},
  "geometry": {"coordinates":[13.9318876266,47.5550498962],"type":"Point"}
}