{
  "type": "Feature",
  "properties": {
    "addr:full":"Obere Postg 62 Tamsweg Salzburg 5580",
    "addr:housenumber":"62",
    "addr:postcode":"5580",
    "addr:street":"Obere Postg;Salzburg",
    "iso:country":"AT",
    "sg:address":"Obere Postg 62",
    "sg:city":"Tamsweg",
    "sg:orig_category":"Unterhaltungselektronik / Einzelhandel",
    "sg:phone":"+43 6474 2566",
    "sg:postcode":"5580",
    "sg:province":"Salzburg",
    "wof:name":"Gugg Siegfried",
    "wof:placetype":"venue"
},
  "geometry": {"coordinates":[13.8079776764,47.1271057129],"type":"Point"}
}