{
  "type": "Feature",
  "properties": {
    "addr:full":"Eggersdorfer Str 51 Amstetten Nieder\u00f6sterreich 3300",
    "addr:housenumber":"51",
    "addr:postcode":"3300",
    "addr:street":"Str;Niederoesterreich",
    "iso:country":"AT",
    "sg:address":"Eggersdorfer Str 51",
    "sg:city":"Amstetten",
    "sg:orig_category":"Bauunternehmen",
    "sg:phone":"+43 7472 20010",
    "sg:postcode":"3300",
    "sg:province":"Nieder\u00f6sterreich",
    "wof:name":"RAI-BAU BaugesmbH",
    "wof:placetype":"venue"
},
  "geometry": {"coordinates":[14.8800039291,48.1197891235],"type":"Point"}
}