{
  "type": "Feature",
  "properties": {
    "addr:full":"Nr 5 K\u00f6stenberg K\u00e4rnten 9231",
    "addr:postcode":"9231",
    "addr:street":"Nr;Koestenberg",
    "iso:country":"AT",
    "sg:address":"Nr 5",
    "sg:city":"K\u00f6stenberg",
    "sg:orig_category":"Pensionen / Privatzimmer",
    "sg:phone":"+43 4274 7004",
    "sg:postcode":"9231",
    "sg:province":"K\u00e4rnten",
    "wof:name":"Pension Ball",
    "wof:placetype":"venue"
},
  "geometry": {"coordinates":[14.0460224152,46.6471824646],"type":"Point"}
}