{
  "type": "Feature",
  "properties": {
    "addr:full":"Leopold-Breinschmid-Str 37 Baden Nieder\u00f6sterreich 2500",
    "addr:housenumber":"37",
    "addr:postcode":"2500",
    "addr:street":"Leopold-Breinschmid-Str;Niederoesterreich",
    "iso:country":"AT",
    "sg:address":"Leopold-Breinschmid-Str 37",
    "sg:city":"Baden",
    "sg:orig_category":"Massagen",
    "sg:phone":"+43 4322 5246277",
    "sg:postcode":"2500",
    "sg:province":"Nieder\u00f6sterreich",
    "wof:name":"T\u00fcrk Richard",
    "wof:placetype":"venue"
},
  "geometry": {"coordinates":[16.2332496643,47.9965019226],"type":"Point"}
}