{
  "type": "Feature",
  "properties": {
    "iso:country":"AT",
    "sg:address":"Schattau 8",
    "sg:city":"Unterwei\u00dfenbach",
    "sg:orig_category":"Tischlereien",
    "sg:phone":"+43 7956 75710",
    "sg:postcode":"4273",
    "sg:province":"Ober\u00f6sterreich",
    "wof:name":"P\u00f6tscher Gottfried",
    "wof:placetype":"venue"
},
  "geometry": {"coordinates":[14.7811594009,48.4358215332],"type":"Point"}
}