{
  "type": "Feature",
  "properties": {
    "addr:full":"Singerstr 27 Wien Wien 1010",
    "addr:housenumber":"27",
    "addr:postcode":"1010",
    "addr:street":"Singerstr",
    "iso:country":"AT",
    "sg:address":"Singerstr 27",
    "sg:city":"Wien",
    "sg:orig_category":"Fleischhauereien",
    "sg:phone":"+43 1 5129622",
    "sg:postcode":"1010",
    "sg:province":"Wien",
    "wof:name":"Schirnhofer-Breisler GesmbH - Shop in Shop",
    "wof:placetype":"venue"
},
  "geometry": {"coordinates":[16.3764572144,48.2063751221],"type":"Point"}
}