{
  "type": "Feature",
  "properties": {
    "addr:full":"Lange G 9 Volders Tirol 6111",
    "addr:housenumber":"9",
    "addr:postcode":"6111",
    "addr:street":"Lange G;Tirol",
    "iso:country":"AT",
    "sg:address":"Lange G 9",
    "sg:city":"Volders",
    "sg:orig_category":"Schlossereien",
    "sg:phone":"+43 5224 54515",
    "sg:postcode":"6111",
    "sg:province":"Tirol",
    "wof:name":"Daxl Siegfried",
    "wof:placetype":"venue"
},
  "geometry": {"coordinates":[11.5694046021,47.2867012024],"type":"Point"}
}