{
  "type": "Feature",
  "properties": {
    "addr:full":"Hauptpl 9-11 Zwentendorf an der Donau Nieder\u00f6sterreich 3435",
    "addr:housenumber":"9-11",
    "addr:postcode":"3435",
    "iso:country":"AT",
    "sg:address":"Hauptpl 9-11",
    "sg:city":"Zwentendorf an der Donau",
    "sg:orig_category":"Lebensmittel / Einzelhandel",
    "sg:phone":"+43 4322 7772672",
    "sg:postcode":"3435",
    "sg:province":"Nieder\u00f6sterreich",
    "wof:name":"Spar Markt - Johannes Bartaun",
    "wof:placetype":"venue"
},
  "geometry": {"coordinates":[15.9102058411,48.3446998596],"type":"Point"}
}