{
  "type": "Feature",
  "properties": {
    "addr:full":"Heideweg 19 Gm\u00fcnd Nieder\u00f6sterreich 3950",
    "addr:housenumber":"19",
    "addr:postcode":"3950",
    "addr:street":"Heideweg;Niederoesterreich",
    "iso:country":"AT",
    "sg:address":"Heideweg 19",
    "sg:city":"Gm\u00fcnd",
    "sg:orig_category":"Pensionen / Privatzimmer",
    "sg:phone":"+43 2852 54415",
    "sg:postcode":"3950",
    "sg:province":"Nieder\u00f6sterreich",
    "wof:name":"Meindl Harald",
    "wof:placetype":"venue"
},
  "geometry": {"coordinates":[14.9940452576,48.7745170593],"type":"Point"}
}