{
  "type": "Feature",
  "properties": {
    "addr:full":"Maierhof 125 Riefensberg Vorarlberg 6943",
    "addr:housenumber":"125",
    "addr:postcode":"6943",
    "addr:street":"Maierhof",
    "iso:country":"AT",
    "sg:address":"Maierhof 125",
    "sg:city":"Riefensberg",
    "sg:orig_category":"Fenster",
    "sg:phone":"+43 4355 1381170",
    "sg:postcode":"6943",
    "sg:province":"Vorarlberg",
    "wof:name":"Hirschb\u00fchl Dietmar",
    "wof:placetype":"venue"
},
  "geometry": {"coordinates":[9.9460391998,47.4956207275],"type":"Point"}
}