{
  "type": "Feature",
  "properties": {
    "iso:country":"AT",
    "sg:address":"Grabenstr 2",
    "sg:city":"Schwanberg",
    "sg:orig_category":"\u00c3\u201erzte / F Allgemeinmedizin",
    "sg:phone":"+43 3467 8182",
    "sg:postcode":"8541",
    "sg:province":"Steiermark",
    "wof:name":"Fromm Gerhard Dr",
    "wof:placetype":"venue"
},
  "geometry": {"coordinates":[15.1991844177,46.758972168],"type":"Point"}
}