{
  "type": "Feature",
  "properties": {
    "addr:full":"Maria-Theresien-Str 6 Lustenau Vorarlberg 6890",
    "addr:housenumber":"6",
    "addr:postcode":"6890",
    "addr:street":"Maria-Theresien-Str",
    "iso:country":"AT",
    "sg:address":"Maria-Theresien-Str 6",
    "sg:city":"Lustenau",
    "sg:orig_category":"\u00c3\u201erzte / F Allgemeinmedizin",
    "sg:phone":"+43 5577 83210",
    "sg:postcode":"6890",
    "sg:province":"Vorarlberg",
    "wof:name":"Schlemmer Udo Dr",
    "wof:placetype":"venue"
},
  "geometry": {"coordinates":[9.6586284637,47.4272270203],"type":"Point"}
}