{
  "type": "Feature",
  "properties": {
    "addr:full":"Nr 6 Vitis Nieder\u00f6sterreich 3902",
    "addr:postcode":"3902",
    "addr:street":"Nr;Niederoesterreich",
    "iso:country":"AT",
    "sg:address":"Nr 6",
    "sg:city":"Vitis",
    "sg:classifiers":[
        {
            "category":"Farming",
            "subcategory":"Livestock Farm",
            "type":"Manufacturing & Wholesale Goods"
        }
    ],
    "sg:phone":"+43 2841 8951",
    "sg:postcode":"3902",
    "sg:province":"Nieder\u00f6sterreich",
    "sg:tags":[
        "-handel",
        "viehzucht",
        "u"
    ],
    "wof:name":"Honeder Josef Nutz- und Stechviehhandel",
    "wof:placetype":"venue"
},
  "geometry": {"coordinates":[15.183391571,48.7590255737],"type":"Point"}
}