{
  "type": "Feature",
  "properties": {
    "addr:full":"Industriestr 21 Eisenstadt Burgenland 7000",
    "addr:housenumber":"21",
    "addr:postcode":"7000",
    "addr:street":"Industriestr",
    "iso:country":"AT",
    "sg:address":"Industriestr 21",
    "sg:city":"Eisenstadt",
    "sg:orig_category":"Autoreparatur",
    "sg:phone":"+43 2682 644520",
    "sg:postcode":"7000",
    "sg:province":"Burgenland",
    "wof:name":"Autohaus Bauer",
    "wof:placetype":"venue"
},
  "geometry": {"coordinates":[16.5359554291,47.8327140808],"type":"Point"}
}