{
  "type": "Feature",
  "properties": {
    "iso:country":"AT",
    "sg:address":"Bahnhofstr. 9",
    "sg:city":"Schlins",
    "sg:classifiers":[
        {
            "category":"Shopping",
            "type":"Retail Goods"
        }
    ],
    "sg:phone":"+43 4355 248291",
    "sg:postcode":"6824",
    "sg:province":"Vorarlberg",
    "sg:tags":[
        "finished",
        "-",
        "metallic"
    ],
    "wof:name":"LOR\u00dcNSER LEICHTMETALLWERK GESMBH",
    "wof:placetype":"venue"
},
  "geometry": {"coordinates":[9.6928892136,47.2006225586],"type":"Point"}
}