{
  "type": "Feature",
  "properties": {
    "addr:full":"Welser Str 2 Marchtrenk Ober\u00f6sterreich 4614",
    "addr:housenumber":"2",
    "addr:postcode":"4614",
    "addr:street":"Str",
    "iso:country":"AT",
    "sg:address":"Welser Str 2",
    "sg:city":"Marchtrenk",
    "sg:orig_category":"Apotheken",
    "sg:phone":"+43 4372 43522750",
    "sg:postcode":"4614",
    "sg:province":"Ober\u00f6sterreich",
    "wof:name":"Apotheke z Welser Heide - Mag pharm Christa Prillinger KG",
    "wof:placetype":"venue"
},
  "geometry": {"coordinates":[14.1110973358,48.1905860901],"type":"Point"}
}