{
  "type": "Feature",
  "properties": {
    "addr:full":"Marktstr 45 Pamhagen Burgenland 7152",
    "addr:housenumber":"45",
    "addr:postcode":"7152",
    "addr:street":"Marktstr",
    "iso:country":"AT",
    "sg:address":"Marktstr 45",
    "sg:city":"Pamhagen",
    "sg:orig_category":"Musikgruppen",
    "sg:phone":"+43 664 3242664",
    "sg:postcode":"7152",
    "sg:province":"Burgenland",
    "wof:name":"Seewinkl Rebellen",
    "wof:placetype":"venue"
},
  "geometry": {"coordinates":[16.9098625183,47.7019920349],"type":"Point"}
}