{
  "type": "Feature",
  "properties": {
    "addr:full":"Siedlungsgasse 4 Prellenkirchen Nieder\u00f6sterreich 2472",
    "addr:housenumber":"4",
    "addr:postcode":"2472",
    "addr:street":"Siedlungsgasse",
    "iso:country":"AT",
    "sg:address":"Siedlungsgasse 4",
    "sg:city":"Prellenkirchen",
    "sg:classifiers":[
        {
            "category":"Transit Center",
            "subcategory":"Freight",
            "type":"Transportation"
        }
    ],
    "sg:phone":"+43 2145 2147",
    "sg:postcode":"2472",
    "sg:province":"Nieder\u00f6sterreich",
    "sg:tags":[
        "elevator"
    ],
    "sg:website":"meisteraufzuege.at",
    "wof:name":"Meisteraufz\u00fcge Herbert Horvath",
    "wof:placetype":"venue"
},
  "geometry": {"coordinates":[16.948633194,48.0780563354],"type":"Point"}
}