{
  "type": "Feature",
  "properties": {
    "addr:full":"Kagraner Pl 7 Wien Wien 1220",
    "addr:housenumber":"7",
    "addr:postcode":"1220",
    "addr:street":"Kagraner Pl",
    "iso:country":"AT",
    "sg:address":"Kagraner Pl 7",
    "sg:city":"Wien",
    "sg:orig_category":"Transportunternehmen",
    "sg:phone":"+43 1 2031105",
    "sg:postcode":"1220",
    "sg:province":"Wien",
    "wof:name":"Maizner Transporte GmbH",
    "wof:placetype":"venue"
},
  "geometry": {"coordinates":[16.4454174042,48.2496757507],"type":"Point"}
}