{
  "type": "Feature",
  "properties": {
    "addr:full":"Reininghausstr 49 Graz Steiermark 8020",
    "addr:housenumber":"49",
    "addr:postcode":"8020",
    "addr:street":"Reininghausstr",
    "iso:country":"AT",
    "sg:address":"Reininghausstr 49",
    "sg:city":"Graz",
    "sg:orig_category":"Nagelstudios",
    "sg:phone":"+43 316 576030",
    "sg:postcode":"8020",
    "sg:province":"Steiermark",
    "wof:name":"Top Nails - Silvia Posch",
    "wof:placetype":"venue"
},
  "geometry": {"coordinates":[15.4018201828,47.0634460449],"type":"Point"}
}