{
  "type": "Feature",
  "properties": {
    "addr:full":"Hofbauerstr 7 Bad Schallerbach Ober\u00f6sterreich 4701",
    "addr:housenumber":"7",
    "addr:postcode":"4701",
    "addr:street":"Hofbauerstr",
    "iso:country":"AT",
    "sg:address":"Hofbauerstr 7",
    "sg:city":"Bad Schallerbach",
    "sg:orig_category":"Werbeagenturen",
    "sg:phone":"+43 4372 49426380",
    "sg:postcode":"4701",
    "sg:province":"Ober\u00f6sterreich",
    "wof:name":"Beham Wolfgang Mag",
    "wof:placetype":"venue"
},
  "geometry": {"coordinates":[13.9252071381,48.2299804688],"type":"Point"}
}