{
  "type": "Feature",
  "properties": {
    "addr:full":"K\u00e4rntner Str 69 Knittelfeld Steiermark 8720",
    "addr:housenumber":"69",
    "addr:postcode":"8720",
    "addr:street":"Str",
    "iso:country":"AT",
    "sg:address":"K\u00e4rntner Str 69",
    "sg:city":"Knittelfeld",
    "sg:orig_category":"Lebensmittel / Einzelhandel",
    "sg:phone":"+43 4335 1271393",
    "sg:postcode":"8720",
    "sg:province":"Steiermark",
    "wof:name":"Hofer KG",
    "wof:placetype":"venue"
},
  "geometry": {"coordinates":[14.8291902542,47.2139434814],"type":"Point"}
}