{
  "type": "Feature",
  "properties": {
    "addr:full":"Nr 41 Dellach im Drautal K\u00e4rnten 9772",
    "addr:postcode":"9772",
    "addr:street":"Nr;Dellach",
    "iso:country":"AT",
    "sg:address":"Nr 41",
    "sg:city":"Dellach im Drautal",
    "sg:classifiers":[
        {
            "category":"Restaurant",
            "type":"Food & Drink"
        }
    ],
    "sg:phone":"+43 4714 2230",
    "sg:postcode":"9772",
    "sg:province":"K\u00e4rnten",
    "sg:tags":[
        "pizzeria"
    ],
    "wof:name":"Pizzeria El Macho",
    "wof:placetype":"venue"
},
  "geometry": {"coordinates":[13.0824251175,46.7413406372],"type":"Point"}
}