{
  "type": "Feature",
  "properties": {
    "addr:full":"Gassergasse 34 Wien Wien 1050",
    "addr:housenumber":"34",
    "addr:postcode":"1050",
    "addr:street":"Gassergasse",
    "iso:country":"AT",
    "sg:address":"Gassergasse 34",
    "sg:city":"Wien",
    "sg:classifiers":[
        {
            "category":"Retail",
            "subcategory":"Car Wash",
            "type":"Services"
        }
    ],
    "sg:phone":"+43 1 5452292",
    "sg:postcode":"1050",
    "sg:province":"Wien",
    "sg:tags":[
        "anti-corrosive",
        "coating"
    ],
    "sg:website":"sonnek.com",
    "wof:name":"Sonnek Engineering GmbH",
    "wof:placetype":"venue"
},
  "geometry": {"coordinates":[16.3628749847,48.1832962036],"type":"Point"}
}