{
  "type": "Feature",
  "properties": {
    "addr:full":"Pyburg 67 Ennsdorf Nieder\u00f6sterreich 4482",
    "addr:housenumber":"67",
    "addr:postcode":"4482",
    "addr:street":"Pyburg",
    "iso:country":"AT",
    "sg:address":"Pyburg 67",
    "sg:city":"Ennsdorf",
    "sg:orig_category":"Friseure U Frisiersalons",
    "sg:phone":"+43 4372 2384570",
    "sg:postcode":"4482",
    "sg:province":"Nieder\u00f6sterreich",
    "wof:name":"Salon Fredi",
    "wof:placetype":"venue"
},
  "geometry": {"coordinates":[14.52643013,48.2330284119],"type":"Point"}
}