{
  "type": "Feature",
  "properties": {
    "addr:full":"Brandhofg 11 Graz Steiermark 8010",
    "addr:housenumber":"11",
    "addr:postcode":"8010",
    "addr:street":"Brandhofg",
    "iso:country":"AT",
    "sg:address":"Brandhofg 11",
    "sg:city":"Graz",
    "sg:orig_category":"Unterhaltungselektronik / Erzeugung U Gro\u00c3\u0178handel",
    "sg:phone":"+43 4331 6337175",
    "sg:postcode":"8010",
    "sg:province":"Steiermark",
    "wof:name":"Gaudios Kovacevic KEG",
    "wof:placetype":"venue"
},
  "geometry": {"coordinates":[15.4480886459,47.0737037659],"type":"Point"}
}