{
  "type": "Feature",
  "properties": {
    "addr:full":"Gumpendorfer Str 59-61 Wien Wien 1060",
    "addr:postcode":"59-61;1060",
    "addr:street":"Str",
    "iso:country":"AT",
    "sg:address":"Gumpendorfer Str 59-61",
    "sg:city":"Wien",
    "sg:orig_category":"Bibliotheken",
    "sg:phone":"+43 1 5872830",
    "sg:postcode":"1060",
    "sg:province":"Wien",
    "wof:name":"B\u00fcchereien St\u00e4dtische",
    "wof:placetype":"venue"
},
  "geometry": {"coordinates":[16.3547058105,48.1976852417],"type":"Point"}
}