{
  "type": "Feature",
  "properties": {
    "addr:full":"Freyweg 29 Bergheim Salzburg 5101",
    "addr:housenumber":"29",
    "addr:postcode":"5101",
    "addr:street":"Freyweg;Salzburg",
    "iso:country":"AT",
    "sg:address":"Freyweg 29",
    "sg:city":"Bergheim",
    "sg:orig_category":"Werbeartikel U -Geschenke",
    "sg:phone":"+43 4366 43360201",
    "sg:postcode":"5101",
    "sg:province":"Salzburg",
    "wof:name":"Lang Erwin",
    "wof:placetype":"venue"
},
  "geometry": {"coordinates":[13.0316400528,47.8325653076],"type":"Point"}
}