{
  "type": "Feature",
  "properties": {
    "iso:country":"AT",
    "sg:address":"K\u00fchbachstrasse 4",
    "sg:city":"Neukirchen am Walde",
    "sg:classifiers":[
        {
            "category":"Education",
            "subcategory":"School",
            "type":"Public Place"
        }
    ],
    "sg:phone":"+43 7278 3362",
    "sg:postcode":"4724",
    "sg:province":"Ober\u00f6sterreich",
    "sg:tags":[
        "breeding",
        "livestock",
        "cattle"
    ],
    "wof:name":"Rudolf Berghamer GmbH",
    "wof:placetype":"venue"
},
  "geometry": {"coordinates":[13.7808732986,48.4049911499],"type":"Point"}
}