{
  "type": "Feature",
  "properties": {
    "iso:country":"AT",
    "sg:address":"Schmiedg 19",
    "sg:city":"Leibnitz",
    "sg:orig_category":"Spenglereien",
    "sg:phone":"+43 4334 52823630",
    "sg:postcode":"8430",
    "sg:province":"Steiermark",
    "wof:name":"Hagen GesmbH Dach-Wand-Spenglerei",
    "wof:placetype":"venue"
},
  "geometry": {"coordinates":[15.5396728516,46.7801361084],"type":"Point"}
}