{
  "type": "Feature",
  "properties": {
    "iso:country":"AT",
    "sg:address":"Neubaug 76",
    "sg:city":"Weiden am See",
    "sg:orig_category":"Werbegrafik- U Grafik-Design",
    "sg:phone":"+43 4321 677969",
    "sg:postcode":"7121",
    "sg:province":"Burgenland",
    "wof:name":"Himmler Martina",
    "wof:placetype":"venue"
},
  "geometry": {"coordinates":[16.8681316376,47.926235199],"type":"Point"}
}