{
  "type": "Feature",
  "properties": {
    "addr:full":"Nr 190 F\u00fcrstenfeld Steiermark 8280",
    "addr:postcode":"8280",
    "addr:street":"Nr;Fuerstenfeld",
    "iso:country":"AT",
    "sg:address":"Nr 190",
    "sg:city":"F\u00fcrstenfeld",
    "sg:orig_category":"Autohandel",
    "sg:phone":"+43 4333 82541580",
    "sg:postcode":"8280",
    "sg:province":"Steiermark",
    "wof:name":"Himler Horst GesmbH",
    "wof:placetype":"venue"
},
  "geometry": {"coordinates":[16.0478401184,47.0652618408],"type":"Point"}
}