{
  "type": "Feature",
  "properties": {
    "addr:full":"Wilhelminenstr 78 Wien Wien 1160",
    "addr:housenumber":"78",
    "addr:postcode":"1160",
    "addr:street":"Wilhelminenstr",
    "iso:country":"AT",
    "sg:address":"Wilhelminenstr 78",
    "sg:city":"Wien",
    "sg:orig_category":"Friseure U Frisiersalons",
    "sg:phone":"+43 1 4806414",
    "sg:postcode":"1160",
    "sg:province":"Wien",
    "wof:name":"Salon Susi",
    "wof:placetype":"venue"
},
  "geometry": {"coordinates":[16.3099040985,48.2175941467],"type":"Point"}
}