{
  "type": "Feature",
  "properties": {
    "addr:full":"Nr 251 Loipersdorf Steiermark 8282",
    "addr:postcode":"8282",
    "addr:street":"Nr",
    "iso:country":"AT",
    "sg:address":"Nr 251",
    "sg:city":"Loipersdorf",
    "sg:orig_category":"Esoterik",
    "sg:phone":"+43 664 2743841",
    "sg:postcode":"8282",
    "sg:province":"Steiermark",
    "wof:name":"Mineralien Onlineshop",
    "wof:placetype":"venue"
},
  "geometry": {"coordinates":[16.1014671326,47.0128898621],"type":"Point"}
}