{
  "type": "Feature",
  "properties": {
    "iso:country":"AT",
    "sg:address":"Wolfgang-Schm\u00e4lzl-G 16",
    "sg:city":"Wien",
    "sg:orig_category":"Papier- U Schreibwaren / Einzelhandel",
    "sg:phone":"+43 4317 262693",
    "sg:postcode":"1020",
    "sg:province":"Wien",
    "wof:name":"L\u00f6scher Helga",
    "wof:placetype":"venue"
},
  "geometry": {"coordinates":[16.398607254,48.2200775146],"type":"Point"}
}