{
  "type": "Feature",
  "properties": {
    "addr:full":"Traxenbichl 5  Scharnstein Ober\u00f6sterreich 4644",
    "addr:housenumber":"5",
    "addr:postcode":"4644",
    "addr:street":"Traxenbichl",
    "iso:country":"AT",
    "sg:address":"Traxenbichl 5 ",
    "sg:city":"Scharnstein",
    "sg:classifiers":[
        {
            "category":"Sports & Exercise",
            "subcategory":"Playing Field",
            "type":"Entertainment"
        }
    ],
    "sg:phone":"+43 4376 168305",
    "sg:postcode":"4644",
    "sg:province":"Ober\u00f6sterreich",
    "sg:tags":[
        "game"
    ],
    "wof:name":"PERNER PRODUKTIONS GMBH",
    "wof:placetype":"venue"
},
  "geometry": {"coordinates":[13.9363241196,47.8760108948],"type":"Point"}
}