{
  "type": "Feature",
  "properties": {
    "addr:full":"Hackherg 36 Graz Steiermark 8020",
    "addr:housenumber":"36",
    "addr:postcode":"8020",
    "addr:street":"Hackherg",
    "iso:country":"AT",
    "sg:address":"Hackherg 36",
    "sg:city":"Graz",
    "sg:orig_category":"Hausbetreuung",
    "sg:phone":"+43 4367 64747755",
    "sg:postcode":"8020",
    "sg:province":"Steiermark",
    "wof:name":"Heim & Haus Dienstleistungsservice",
    "wof:placetype":"venue"
},
  "geometry": {"coordinates":[15.4194011688,47.0837173462],"type":"Point"}
}