{
  "type": "Feature",
  "properties": {
    "addr:full":"Spittelauer L\u00e4nde 13/11 Wien Wien 1090",
    "addr:housenumber":"13 / 11",
    "addr:postcode":"1090",
    "iso:country":"AT",
    "sg:address":"Spittelauer L\u00e4nde 13/11",
    "sg:city":"Wien",
    "sg:orig_category":"Osteopathie",
    "sg:phone":"+43 1 3196445",
    "sg:postcode":"1090",
    "sg:province":"Wien",
    "wof:name":"Hansak Sylvia",
    "wof:placetype":"venue"
},
  "geometry": {"coordinates":[16.3630886078,48.2280807495],"type":"Point"}
}