{
  "type": "Feature",
  "properties": {
    "addr:full":"Alte Str 2 Nenzing Vorarlberg 6710",
    "addr:housenumber":"2",
    "addr:postcode":"6710",
    "addr:street":"Alte Str",
    "iso:country":"AT",
    "sg:address":"Alte Str 2",
    "sg:city":"Nenzing",
    "sg:classifiers":[
        {
            "category":"Utilities",
            "subcategory":"Refuse",
            "type":"Services"
        }
    ],
    "sg:phone":"+43 4355 256439020",
    "sg:postcode":"6710",
    "sg:province":"Vorarlberg",
    "sg:tags":[
        "catering"
    ],
    "wof:name":"Gamon u Partner",
    "wof:placetype":"venue"
},
  "geometry": {"coordinates":[9.7021093369,47.1844139099],"type":"Point"}
}