{
  "type": "Feature",
  "properties": {
    "addr:full":"Quadrella 15 B\u00fcrs Vorarlberg 6706",
    "addr:housenumber":"15",
    "addr:postcode":"6706",
    "addr:street":"Quadrella",
    "iso:country":"AT",
    "sg:address":"Quadrella 15",
    "sg:city":"B\u00fcrs",
    "sg:orig_category":"Transportunternehmen",
    "sg:phone":"+43 5552 65246",
    "sg:postcode":"6706",
    "sg:province":"Vorarlberg",
    "wof:name":"Micheli Artur",
    "wof:placetype":"venue"
},
  "geometry": {"coordinates":[9.8065433502,47.1574134827],"type":"Point"}
}