{
  "type": "Feature",
  "properties": {
    "addr:full":"Wehrg 4 Wien Wien 1050",
    "addr:housenumber":"4",
    "addr:postcode":"1050",
    "addr:street":"Wehrg",
    "iso:country":"AT",
    "sg:address":"Wehrg 4",
    "sg:city":"Wien",
    "sg:orig_category":"Umweltschutz",
    "sg:phone":"+43 4315 854488",
    "sg:postcode":"1050",
    "sg:province":"Wien",
    "wof:name":"Green Network Umweltschutz- u Handel GmbH",
    "wof:placetype":"venue"
},
  "geometry": {"coordinates":[16.3604812622,48.1933746338],"type":"Point"}
}