{
  "type": "Feature",
  "properties": {
    "addr:full":"Naschmarkt 74-75 Wien Wien 1040",
    "addr:postcode":"74-75;1040",
    "addr:street":"Naschmarkt",
    "iso:country":"AT",
    "sg:address":"Naschmarkt 74-75",
    "sg:city":"Wien",
    "sg:orig_category":"Restaurants: Indisch",
    "sg:phone":"+43 1 5878561",
    "sg:postcode":"1040",
    "sg:province":"Wien",
    "wof:name":"Restaurant Indian Pavilion",
    "wof:placetype":"venue"
},
  "geometry": {"coordinates":[16.3660907745,48.1996917725],"type":"Point"}
}