{
  "type": "Feature",
  "properties": {
    "addr:full":"Singerstr 4 Wien Wien 1010",
    "addr:housenumber":"4",
    "addr:postcode":"1010",
    "addr:street":"Singerstr",
    "iso:country":"AT",
    "sg:address":"Singerstr 4",
    "sg:city":"Wien",
    "sg:orig_category":"Restaurants: Amerikanisch",
    "sg:phone":"+43 1 5139279",
    "sg:postcode":"1010",
    "sg:province":"Wien",
    "wof:name":"McDonald's Restaurant",
    "wof:placetype":"venue"
},
  "geometry": {"coordinates":[16.3721542358,48.2077026367],"type":"Point"}
}