{
  "type": "Feature",
  "properties": {
    "addr:full":"Marschnerg 6 Wien Wien 1160",
    "addr:housenumber":"6",
    "addr:postcode":"1160",
    "addr:street":"Marschnerg",
    "iso:country":"AT",
    "sg:address":"Marschnerg 6",
    "sg:city":"Wien",
    "sg:orig_category":"Ingenieurkonsulenten / Zivilingenieure",
    "sg:phone":"+43 1 49319810",
    "sg:postcode":"1160",
    "sg:province":"Wien",
    "wof:name":"Hazivar Wolfgang DI Dr techn",
    "wof:placetype":"venue"
},
  "geometry": {"coordinates":[16.305513382,48.2130737305],"type":"Point"}
}