{
  "type": "Feature",
  "properties": {
    "addr:full":"Herreng 24 Wiener Neustadt Nieder\u00f6sterreich 2700",
    "addr:housenumber":"24",
    "addr:postcode":"2700",
    "addr:street":"Herreng",
    "iso:country":"AT",
    "sg:address":"Herreng 24",
    "sg:city":"Wiener Neustadt",
    "sg:orig_category":"Medizinische Beratung",
    "sg:phone":"+43 2622 26741",
    "sg:postcode":"2700",
    "sg:province":"Nieder\u00f6sterreich",
    "wof:name":"Knapil Herta",
    "wof:placetype":"venue"
},
  "geometry": {"coordinates":[16.2406692505,47.8146896362],"type":"Point"}
}