{
  "type": "Feature",
  "properties": {
    "iso:country":"AT",
    "sg:address":"Landstr 16",
    "sg:city":"Linz",
    "sg:orig_category":"Apotheken",
    "sg:phone":"+43 732 772430",
    "sg:postcode":"4020",
    "sg:province":"Ober\u00f6sterreich",
    "wof:name":"Apotheke z schwarzen Adler",
    "wof:placetype":"venue"
},
  "geometry": {"coordinates":[14.2883501053,48.3035774231],"type":"Point"}
}