{
  "type": "Feature",
  "properties": {
    "iso:country":"AT",
    "sg:address":"Kirchfeld 30",
    "sg:city":"Rattenberg",
    "sg:classifiers":[
        {
            "category":"Farming",
            "subcategory":"Livestock Farm",
            "type":"Manufacturing & Wholesale Goods"
        }
    ],
    "sg:phone":"+43 4353 3763631",
    "sg:postcode":"6240",
    "sg:province":"Tirol",
    "sg:tags":[
        "-handel",
        "viehzucht",
        "u"
    ],
    "wof:name":"W\u00f6ll Anton",
    "wof:placetype":"venue"
},
  "geometry": {"coordinates":[11.9094696045,47.4501419067],"type":"Point"}
}