{
  "type": "Feature",
  "properties": {
    "addr:full":"Hauptstr 118 Breitenfurt Nieder\u00f6sterreich 2384",
    "addr:housenumber":"118",
    "addr:postcode":"2384",
    "addr:street":"Hauptstr",
    "iso:country":"AT",
    "sg:address":"Hauptstr 118",
    "sg:city":"Breitenfurt",
    "sg:orig_category":"Banken U Sparkassen",
    "sg:phone":"+43 4322 3922640",
    "sg:postcode":"2384",
    "sg:province":"Nieder\u00f6sterreich",
    "wof:name":"Bankomat der Raiffeisenbank Pressbaum-Breitenfurt regGenmbH - Bankstelle Breitenfurt",
    "wof:placetype":"venue"
},
  "geometry": {"coordinates":[16.2083091736,48.1380805969],"type":"Point"}
}