{
  "type": "Feature",
  "properties": {
    "iso:country":"AT",
    "sg:address":"Klammerm\u00fchle 3",
    "sg:city":"Obsteig",
    "sg:orig_category":"Bauunternehmen",
    "sg:phone":"+43 4367 69773687",
    "sg:postcode":"6416",
    "sg:province":"Tirol",
    "wof:name":"Bau-Hai LTD & Co KG",
    "wof:placetype":"venue"
},
  "geometry": {"coordinates":[10.9270277023,47.2980957031],"type":"Point"}
}