{
  "type": "Feature",
  "properties": {
    "addr:full":"Klammerm\u00fchle 3 Obsteig Tirol 6416",
    "addr:housenumber":"3",
    "addr:postcode":"6416",
    "addr:street":"Klammermuehle;Tirol",
    "iso:country":"AT",
    "sg:address":"Klammerm\u00fchle 3",
    "sg:city":"Obsteig",
    "sg:orig_category":"Bauunternehmen",
    "sg:phone":"+43 4367 69773687",
    "sg:postcode":"6416",
    "sg:province":"Tirol",
    "wof:name":"Bau-Hai LTD & Co KG",
    "wof:placetype":"venue"
},
  "geometry": {"coordinates":[10.9270277023,47.2980957031],"type":"Point"}
}