{
  "type": "Feature",
  "properties": {
    "addr:full":"Hauptpl 22 Retz Nieder\u00f6sterreich 2070",
    "addr:housenumber":"22",
    "addr:postcode":"2070",
    "addr:street":"Hauptpl",
    "iso:country":"AT",
    "sg:address":"Hauptpl 22",
    "sg:city":"Retz",
    "sg:orig_category":"Fotoausarbeitungen",
    "sg:phone":"+43 2942 28290",
    "sg:postcode":"2070",
    "sg:province":"Nieder\u00f6sterreich",
    "wof:name":"Fotolabor Franz Stagl",
    "wof:placetype":"venue"
},
  "geometry": {"coordinates":[15.950340271,48.7568092346],"type":"Point"}
}