{
  "type": "Feature",
  "properties": {
    "addr:full":"Fallnhauserhofstr 8/17 Hallein Salzburg 5400",
    "addr:housenumber":"8 / 17",
    "addr:postcode":"5400",
    "addr:street":"Fallnhauserhofstr;Salzburg",
    "iso:country":"AT",
    "sg:address":"Fallnhauserhofstr 8/17",
    "sg:city":"Hallein",
    "sg:orig_category":"Speditionen",
    "sg:phone":"+43 676 84554711",
    "sg:postcode":"5400",
    "sg:province":"Salzburg",
    "wof:name":"A & L Logistik Rene Lurger",
    "wof:placetype":"venue"
},
  "geometry": {"coordinates":[13.1153802872,47.6790885925],"type":"Point"}
}