{
  "type": "Feature",
  "properties": {
    "addr:full":"Kreuzmoos 18 Axams Tirol 6094",
    "addr:housenumber":"18",
    "addr:postcode":"6094",
    "addr:street":"Kreuzmoos;Tirol",
    "iso:country":"AT",
    "sg:address":"Kreuzmoos 18",
    "sg:city":"Axams",
    "sg:orig_category":"Tischlereien",
    "sg:phone":"+43 5234 67972",
    "sg:postcode":"6094",
    "sg:province":"Tirol",
    "wof:name":"F\u00fcrdank Kurt",
    "wof:placetype":"venue"
},
  "geometry": {"coordinates":[11.2900800705,47.2308692932],"type":"Point"}
}