{
  "type": "Feature",
  "properties": {
    "addr:full":"Korneuburger Str 21 Bisamberg Nieder\u00f6sterreich 2102",
    "addr:postcode":"2102",
    "addr:street":"Str 21",
    "iso:country":"AT",
    "sg:address":"Korneuburger Str 21",
    "sg:city":"Bisamberg",
    "sg:orig_category":"Werbeagenturen",
    "sg:phone":"+43 2262 736660",
    "sg:postcode":"2102",
    "sg:province":"Nieder\u00f6sterreich",
    "wof:name":"Vogel Medien GmbH",
    "wof:placetype":"venue"
},
  "geometry": {"coordinates":[16.3596839905,48.3329200745],"type":"Point"}
}