{
  "type": "Feature",
  "properties": {
    "iso:country":"AT",
    "sg:address":"Feldsberger Strasse 29",
    "sg:city":"Poysdorf",
    "sg:orig_category":"Furniture, General",
    "sg:phone":"+43 2552 2466",
    "sg:postcode":"2170",
    "sg:province":"Nieder\u00f6sterreich",
    "sg:website":"schlemmer.at",
    "wof:name":"Martin Schlemmer",
    "wof:placetype":"venue"
},
  "geometry": {"coordinates":[16.6372947693,48.6686172485],"type":"Point"}
}