{
  "type": "Feature",
  "properties": {
    "addr:full":"Kreuth 16 Zell am Pettenfirst Ober\u00f6sterreich 4842",
    "addr:housenumber":"16",
    "addr:postcode":"4842",
    "addr:street":"Kreuth",
    "iso:country":"AT",
    "sg:address":"Kreuth 16",
    "sg:city":"Zell am Pettenfirst",
    "sg:orig_category":"Lebensmittel / Einzelhandel",
    "sg:phone":"+43 76753838",
    "sg:postcode":"4842",
    "sg:province":"Ober\u00f6sterreich",
    "wof:name":"Brandst\u00e4tter Kurt",
    "wof:placetype":"venue"
},
  "geometry": {"coordinates":[13.6009435654,48.0826225281],"type":"Point"}
}