{
  "type": "Feature",
  "properties": {
    "iso:country":"AT",
    "sg:address":"Hauptstr 28",
    "sg:city":"Peuerbach",
    "sg:orig_category":"Optiker",
    "sg:phone":"+43 7276 2127",
    "sg:postcode":"4722",
    "sg:province":"Ober\u00f6sterreich",
    "wof:name":"Jobst Hermann",
    "wof:placetype":"venue"
},
  "geometry": {"coordinates":[13.7702713013,48.3452529907],"type":"Point"}
}