{
  "type": "Feature",
  "properties": {
    "addr:full":"Gerlosstrasse 7 Mittersill Salzburg 5730",
    "addr:housenumber":"7",
    "addr:postcode":"5730",
    "addr:street":"Gerlosstrasse;Salzburg",
    "iso:country":"AT",
    "sg:address":"Gerlosstrasse 7",
    "sg:city":"Mittersill",
    "sg:classifiers":[
        {
            "category":"Banks & Credit Unions",
            "subcategory":"Atm",
            "type":"Services"
        }
    ],
    "sg:phone":"+43 6562 47470",
    "sg:postcode":"5730",
    "sg:province":"Salzburg",
    "sg:tags":[
        "screed",
        "floor"
    ],
    "sg:website":"wohntraeume.info",
    "wof:name":"Bruno Berger Ges.m.b.H.",
    "wof:placetype":"venue"
},
  "geometry": {"coordinates":[12.4807634354,47.2804641724],"type":"Point"}
}