{
  "type": "Feature",
  "properties": {
    "addr:full":"Nr 20D Maurach Tirol 6212",
    "addr:postcode":"6212",
    "addr:street":"Nr;Tirol",
    "iso:country":"AT",
    "sg:address":"Nr 20D",
    "sg:city":"Maurach",
    "sg:orig_category":"Baumeister",
    "sg:phone":"+43 5243 20122",
    "sg:postcode":"6212",
    "sg:province":"Tirol",
    "wof:name":"Saurer Elmar Bmstr",
    "wof:placetype":"venue"
},
  "geometry": {"coordinates":[11.7518672943,47.4225006104],"type":"Point"}
}