{
  "type": "Feature",
  "properties": {
    "addr:full":"Stadtplatz 39 Mattighofen Ober\u00f6sterreich 5230",
    "addr:housenumber":"39",
    "addr:postcode":"5230",
    "addr:street":"Stadtplatz",
    "iso:country":"AT",
    "sg:address":"Stadtplatz 39",
    "sg:city":"Mattighofen",
    "sg:classifiers":[
        {
            "category":"Banks & Credit Unions",
            "subcategory":"Bank",
            "type":"Services"
        }
    ],
    "sg:phone":"+43 4377 4228010",
    "sg:postcode":"5230",
    "sg:province":"Ober\u00f6sterreich",
    "sg:tags":[
        "banking",
        "institution"
    ],
    "wof:name":"SALZBURGER SPARKASSE BANK AG",
    "wof:placetype":"venue"
},
  "geometry": {"coordinates":[13.1504364014,48.1030464172],"type":"Point"}
}