{
  "type": "Feature",
  "properties": {
    "addr:full":"Lindenauer Strasse 60 Lochau Vorarlberg 6911",
    "addr:housenumber":"60",
    "addr:postcode":"6911",
    "addr:street":"Lindenauer Strasse",
    "iso:country":"AT",
    "sg:address":"Lindenauer Strasse 60",
    "sg:city":"Lochau",
    "sg:orig_category":"Immobilien U Baugewerbe, Architektur U Design",
    "sg:phone":"+43 4355 7442874",
    "sg:postcode":"6911",
    "sg:province":"Vorarlberg",
    "sg:website":"http://www.vrz.net/diem",
    "wof:name":"Diem Werke Alfred Diem GmbH & Co",
    "wof:placetype":"venue"
},
  "geometry": {"coordinates":[9.7427310944,47.5303421021],"type":"Point"}
}