{
  "type": "Feature",
  "properties": {
    "addr:full":"Laaer Str 137 Poysdorf Nieder\u00f6sterreich 2170",
    "addr:housenumber":"137",
    "addr:postcode":"2170",
    "addr:street":"Str",
    "iso:country":"AT",
    "sg:address":"Laaer Str 137",
    "sg:city":"Poysdorf",
    "sg:orig_category":"Baumeister",
    "sg:phone":"+43 2552 28380",
    "sg:postcode":"2170",
    "sg:province":"Nieder\u00f6sterreich",
    "wof:name":"Ederer Kurt Ing",
    "wof:placetype":"venue"
},
  "geometry": {"coordinates":[16.6123409271,48.6643943787],"type":"Point"}
}