{
  "type": "Feature",
  "properties": {
    "addr:full":"Innstr 5 Langkampfen Tirol 6336",
    "addr:housenumber":"5",
    "addr:postcode":"6336",
    "addr:street":"Innstr;Tirol",
    "iso:country":"AT",
    "sg:address":"Innstr 5",
    "sg:city":"Langkampfen",
    "sg:orig_category":"Volksschulen",
    "sg:phone":"+43 5332 87191",
    "sg:postcode":"6336",
    "sg:province":"Tirol",
    "wof:name":"Volksschule",
    "wof:placetype":"venue"
},
  "geometry": {"coordinates":[12.0900154114,47.5235824585],"type":"Point"}
}