{
  "type": "Feature",
  "properties": {
    "addr:full":"Josef-Bauer-Str 6 Biedermannsdorf Nieder\u00f6sterreich 2362",
    "addr:housenumber":"6",
    "addr:postcode":"2362",
    "addr:street":"Josef-Bauer-Str",
    "iso:country":"AT",
    "sg:address":"Josef-Bauer-Str 6",
    "sg:city":"Biedermannsdorf",
    "sg:orig_category":"Tabaktrafiken",
    "sg:phone":"+43 2236 72331",
    "sg:postcode":"2362",
    "sg:province":"Nieder\u00f6sterreich",
    "wof:name":"Franke Gertrude",
    "wof:placetype":"venue"
},
  "geometry": {"coordinates":[16.3446235657,48.0849304199],"type":"Point"}
}