{
  "type": "Feature",
  "properties": {
    "iso:country":"AT",
    "sg:address":"Theodor K\u00f6rner-Str 182",
    "sg:city":"Graz",
    "sg:classifiers":[
        {
            "category":"Restaurant",
            "type":"Food & Drink"
        }
    ],
    "sg:phone":"+43 316 675611",
    "sg:postcode":"8010",
    "sg:province":"Steiermark",
    "sg:tags":[
        "pizzeria"
    ],
    "wof:name":"Pizza Stadl",
    "wof:placetype":"venue"
},
  "geometry": {"coordinates":[15.4241390228,47.093372345],"type":"Point"}
}