{
  "type": "Feature",
  "properties": {
    "addr:full":"Welser Strasse 75 Leonding Ober\u00f6sterreich 4060",
    "addr:housenumber":"75",
    "addr:postcode":"4060",
    "addr:street":"Welser Strasse",
    "iso:country":"AT",
    "sg:address":"Welser Strasse 75",
    "sg:city":"Leonding",
    "sg:classifiers":[
        {
            "category":"Shopping",
            "subcategory":"Department Store",
            "type":"Retail Goods"
        }
    ],
    "sg:phone":"+43 732 6721500",
    "sg:postcode":"4060",
    "sg:province":"Ober\u00f6sterreich",
    "sg:tags":[
        "linen",
        "bed"
    ],
    "wof:name":"Christian Dierig Ges.m.b.H.",
    "wof:placetype":"venue"
},
  "geometry": {"coordinates":[14.2632303238,48.266330719],"type":"Point"}
}