{
  "type": "Feature",
  "properties": {
    "addr:full":"Unterbergg Flachau Salzburg 5542",
    "addr:postcode":"5542",
    "addr:street":"Unterbergg Flachau Salzburg",
    "iso:country":"AT",
    "sg:address":"Unterbergg",
    "sg:city":"Flachau",
    "sg:classifiers":[
        {
            "category":"Park",
            "subcategory":"Provincial",
            "type":"Public Place"
        }
    ],
    "sg:phone":"+43 6457 3322",
    "sg:postcode":"5542",
    "sg:province":"Salzburg",
    "sg:tags":[
        "u",
        "ski-",
        "snowboardschulen"
    ],
    "wof:name":"Skischule Hermann Maier",
    "wof:placetype":"venue"
},
  "geometry": {"coordinates":[13.3884096146,47.3557853699],"type":"Point"}
}