{
  "type": "Feature",
  "properties": {
    "addr:full":"Spiegelgasse 21 Wien Wien 1010",
    "addr:housenumber":"21",
    "addr:postcode":"1010",
    "addr:street":"Spiegelgasse",
    "iso:country":"AT",
    "sg:address":"Spiegelgasse 21",
    "sg:city":"Wien",
    "sg:classifiers":[
        {
            "category":"Home & Garden",
            "subcategory":"Home Furnishings",
            "type":"Retail Goods"
        }
    ],
    "sg:phone":"+43 1 5124414",
    "sg:postcode":"1010",
    "sg:province":"Wien",
    "sg:tags":[
        "consulting"
    ],
    "sg:website":"prause.at",
    "wof:name":"Wohnklassik Werner Prause",
    "wof:placetype":"venue"
},
  "geometry": {"coordinates":[16.3694496155,48.2061576843],"type":"Point"}
}