{
  "type": "Feature",
  "properties": {
    "addr:full":"Kaiserstr 32c St. Johann in Tirol Tirol 6380",
    "addr:housenumber":"32c",
    "addr:postcode":"6380",
    "addr:street":"Kaiserstr;Tirol",
    "iso:country":"AT",
    "sg:address":"Kaiserstr 32c",
    "sg:city":"St. Johann in Tirol",
    "sg:orig_category":"Massagen",
    "sg:phone":"+43 5352 63899",
    "sg:postcode":"6380",
    "sg:province":"Tirol",
    "wof:name":"Vital Energy",
    "wof:placetype":"venue"
},
  "geometry": {"coordinates":[12.4225931168,47.5230979919],"type":"Point"}
}