{
  "type": "Feature",
  "properties": {
    "addr:full":"Bleiburger Str 7 Eberndorf K\u00e4rnten 9141",
    "addr:housenumber":"7",
    "addr:postcode":"9141",
    "addr:street":"Str;Kaernten",
    "iso:country":"AT",
    "sg:address":"Bleiburger Str 7",
    "sg:city":"Eberndorf",
    "sg:orig_category":"Glasereien",
    "sg:phone":"+43 4236 2063",
    "sg:postcode":"9141",
    "sg:province":"K\u00e4rnten",
    "wof:name":"Struckl Manfred",
    "wof:placetype":"venue"
},
  "geometry": {"coordinates":[14.6403398514,46.5905761719],"type":"Point"}
}