{
  "type": "Feature",
  "properties": {
    "addr:full":"Wasserg 14 Baden Nieder\u00f6sterreich 2500",
    "addr:housenumber":"14",
    "addr:postcode":"2500",
    "addr:street":"Wasserg;Niederoesterreich",
    "iso:country":"AT",
    "sg:address":"Wasserg 14",
    "sg:city":"Baden",
    "sg:orig_category":"Lebensmittel / Einzelhandel",
    "sg:phone":"+43 2252 41257",
    "sg:postcode":"2500",
    "sg:province":"Nieder\u00f6sterreich",
    "wof:name":"Billa AG",
    "wof:placetype":"venue"
},
  "geometry": {"coordinates":[16.2360782623,48.006023407],"type":"Point"}
}