{
  "type": "Feature",
  "properties": {
    "iso:country":"AT",
    "sg:address":"Nr 14",
    "sg:city":"Feistritz am Wechsel",
    "sg:orig_category":"Lebensmittel / Einzelhandel",
    "sg:phone":"+43 2641 2154",
    "sg:postcode":"2873",
    "sg:province":"Nieder\u00f6sterreich",
    "wof:name":"Spar-Markt Nothnagel Claudia",
    "wof:placetype":"venue"
},
  "geometry": {"coordinates":[16.0537948608,47.5992774963],"type":"Point"}
}