{
  "type": "Feature",
  "properties": {
    "addr:full":"Im Gries 34 Kitzb\u00fchel Tirol 6370",
    "addr:housenumber":"34",
    "addr:postcode":"6370",
    "addr:street":"Im Gries;Tirol",
    "iso:country":"AT",
    "sg:address":"Im Gries 34",
    "sg:city":"Kitzb\u00fchel",
    "sg:orig_category":"Textilwaren / Einzelhandel",
    "sg:phone":"+43 4353 5662237",
    "sg:postcode":"6370",
    "sg:province":"Tirol",
    "wof:name":"NKD",
    "wof:placetype":"venue"
},
  "geometry": {"coordinates":[12.3931903839,47.445728302],"type":"Point"}
}