{
  "type": "Feature",
  "properties": {
    "iso:country":"AT",
    "sg:address":"Grazer Str 467",
    "sg:city":"Deutschfeistritz",
    "sg:orig_category":"Feinmechanik",
    "sg:phone":"+43 3127 40930",
    "sg:postcode":"8121",
    "sg:province":"Steiermark",
    "wof:name":"Stadler Sensorik GmbH",
    "wof:placetype":"venue"
},
  "geometry": {"coordinates":[15.3356399536,47.1943855286],"type":"Point"}
}