{
  "type": "Feature",
  "properties": {
    "addr:full":"Trappeng 26 Stra\u00dfgang Steiermark 8054",
    "addr:housenumber":"26",
    "addr:postcode":"8054",
    "addr:street":"Trappeng",
    "iso:country":"AT",
    "sg:address":"Trappeng 26",
    "sg:city":"Stra\u00dfgang",
    "sg:orig_category":"Datenverarbeitung",
    "sg:phone":"+43 650 4826266",
    "sg:postcode":"8054",
    "sg:province":"Steiermark",
    "wof:name":"Hubmann Michael",
    "wof:placetype":"venue"
},
  "geometry": {"coordinates":[15.4130172729,47.0355262756],"type":"Point"}
}