{
  "type": "Feature",
  "properties": {
    "addr:full":"L\u00e4mmerbichl 16 Hollersbach im Pinzgau Salzburg 5731",
    "addr:housenumber":"16",
    "addr:postcode":"5731",
    "addr:street":"Laemmerbichl;Salzburg",
    "iso:country":"AT",
    "sg:address":"L\u00e4mmerbichl 16",
    "sg:city":"Hollersbach im Pinzgau",
    "sg:orig_category":"Pensionen / Privatzimmer",
    "sg:phone":"+43 4365 6285480",
    "sg:postcode":"5731",
    "sg:province":"Salzburg",
    "wof:name":"Pension Torlehen",
    "wof:placetype":"venue"
},
  "geometry": {"coordinates":[12.4173345566,47.2826347351],"type":"Point"}
}