{
  "type": "Feature",
  "properties": {
    "iso:country":"AT",
    "sg:address":"Nr 8",
    "sg:city":"Sch\u00e4rding",
    "sg:orig_category":"Weine / Einzelhandel",
    "sg:phone":"+43 7712 62520",
    "sg:postcode":"4780",
    "sg:province":"Ober\u00f6sterreich",
    "wof:name":"Schmierer Harald GmbH",
    "wof:placetype":"venue"
},
  "geometry": {"coordinates":[13.4304552078,48.4575538635],"type":"Point"}
}