{
  "type": "Feature",
  "properties": {
    "addr:full":"Laxenburger Str 305 Wien Wien 1230",
    "addr:housenumber":"305",
    "addr:postcode":"1230",
    "addr:street":"Laxenburger Str",
    "iso:country":"AT",
    "sg:address":"Laxenburger Str 305",
    "sg:city":"Wien",
    "sg:orig_category":"Exporteure U Importeure",
    "sg:phone":"+43 4315 8138000",
    "sg:postcode":"1230",
    "sg:province":"Wien",
    "wof:name":"Jecom HandelsgesmbH",
    "wof:placetype":"venue"
},
  "geometry": {"coordinates":[16.3609542847,48.1433639526],"type":"Point"}
}