{
  "type": "Feature",
  "properties": {
    "addr:full":"Friedrich-Thurner-Str 10 Ried im Innkreis Ober\u00f6sterreich 4910",
    "addr:housenumber":"10",
    "addr:postcode":"4910",
    "addr:street":"Friedrich-Thurner-Str",
    "iso:country":"AT",
    "sg:address":"Friedrich-Thurner-Str 10",
    "sg:city":"Ried im Innkreis",
    "sg:orig_category":"Fahrschulen",
    "sg:phone":"+43 4377 5289070",
    "sg:postcode":"4910",
    "sg:province":"Ober\u00f6sterreich",
    "wof:name":"Fahrschule Burgstaller",
    "wof:placetype":"venue"
},
  "geometry": {"coordinates":[13.4855928421,48.2107963562],"type":"Point"}
}