{
  "type": "Feature",
  "properties": {
    "addr:full":"Sch\u00f6nbrunner Strasse 13 1052",
    "addr:housenumber":"13",
    "addr:postcode":"1052",
    "addr:street":"Schoenbrunner Strasse",
    "iso:country":"AT",
    "sg:address":"Sch\u00f6nbrunner Strasse 13",
    "sg:orig_category":"Bridge Drains",
    "sg:phone":"+43 1 588130",
    "sg:postcode":"1052",
    "sg:website":"pwn.at",
    "wof:name":"Wallner & Neubert Gesellschaft m.b.H. - Purator Wallner & Neubert Umwelttechnik",
    "wof:placetype":"venue"
},
  "geometry": {"coordinates":[16.3605384827,48.1945037842],"type":"Point"}
}