{
  "type": "Feature",
  "properties": {
    "addr:full":"Wiener Str 87 Gumpoldskirchen Nieder\u00f6sterreich 2352",
    "addr:housenumber":"2352",
    "addr:street":"Niederoesterreich",
    "iso:country":"AT",
    "sg:address":"Wiener Str 87",
    "sg:city":"Gumpoldskirchen",
    "sg:orig_category":"Heurigen / Buschenschank",
    "sg:phone":"+43 2252 62702",
    "sg:postcode":"2352",
    "sg:province":"Nieder\u00f6sterreich",
    "wof:name":"Veigl-H\u00fctte am Beethovenwanderweg",
    "wof:placetype":"venue"
},
  "geometry": {"coordinates":[16.2840461731,48.0426177979],"type":"Point"}
}