{
  "type": "Feature",
  "properties": {
    "iso:country":"AT",
    "sg:address":"Nr 197",
    "sg:city":"W\u00f6rth an der Lafnitz",
    "sg:orig_category":"Maler, Anstreicher U Lackierer",
    "sg:phone":"+43 3358 3094",
    "sg:postcode":"8293",
    "sg:province":"Steiermark",
    "wof:name":"Schuster Wolfgang",
    "wof:placetype":"venue"
},
  "geometry": {"coordinates":[166.9221496582,-0.5282999873],"type":"Point"}
}