{
  "type": "Feature",
  "properties": {
    "addr:full":"Europastr 1 Salzburg Salzburg 5020",
    "addr:housenumber":"1",
    "addr:postcode":"5020",
    "addr:street":"Europastr;Salzburg",
    "iso:country":"AT",
    "sg:address":"Europastr 1",
    "sg:city":"Salzburg",
    "sg:orig_category":"Friseure U Frisiersalons",
    "sg:phone":"+43 662 425143",
    "sg:postcode":"5020",
    "sg:province":"Salzburg",
    "wof:name":"Coiffeure Sturmayr & Leitner",
    "wof:placetype":"venue"
},
  "geometry": {"coordinates":[13.0063295364,47.8161811829],"type":"Point"}
}