{
  "type": "Feature",
  "properties": {
    "addr:full":"Hauptstr 9 Seekirchen am Wallersee Salzburg 5201",
    "addr:housenumber":"9",
    "addr:postcode":"5201",
    "addr:street":"Hauptstr;Salzburg",
    "iso:country":"AT",
    "sg:address":"Hauptstr 9",
    "sg:city":"Seekirchen am Wallersee",
    "sg:orig_category":"Textilreinigung",
    "sg:phone":"+43 4362 122259",
    "sg:postcode":"5201",
    "sg:province":"Salzburg",
    "wof:name":"Textilreinigung Klanfar",
    "wof:placetype":"venue"
},
  "geometry": {"coordinates":[13.126083374,47.8923835754],"type":"Point"}
}