{
  "type": "Feature",
  "properties": {
    "addr:full":"Cottagegasse 7 Wien Wien 1180",
    "addr:housenumber":"7",
    "addr:postcode":"1180",
    "addr:street":"Cottagegasse",
    "iso:country":"AT",
    "sg:address":"Cottagegasse 7",
    "sg:city":"Wien",
    "sg:classifiers":[
        {
            "category":"Building & Trades",
            "subcategory":"Construction",
            "type":"Services"
        }
    ],
    "sg:phone":"+43 1 4706891",
    "sg:postcode":"1180",
    "sg:province":"Wien",
    "sg:tags":[
        "steel"
    ],
    "wof:name":"Gerhard SMRCEK & Sohn GmbH",
    "wof:placetype":"venue"
},
  "geometry": {"coordinates":[16.3396167755,48.2283859253],"type":"Point"}
}