{
  "type": "Feature",
  "properties": {
    "addr:full":"Naderstr 28 Wien Wien 1100",
    "addr:housenumber":"28",
    "addr:postcode":"1100",
    "addr:street":"Naderstr",
    "iso:country":"AT",
    "sg:address":"Naderstr 28",
    "sg:city":"Wien",
    "sg:orig_category":"Webdesign",
    "sg:phone":"+43 4369 911504851",
    "sg:postcode":"1100",
    "sg:province":"Wien",
    "wof:name":"seven - webdesign & IT services",
    "wof:placetype":"venue"
},
  "geometry": {"coordinates":[16.4120750427,48.1618461609],"type":"Point"}
}