{
  "type": "Feature",
  "properties": {
    "iso:country":"AT",
    "sg:address":"Bahnhofweg 1",
    "sg:city":"Liezen",
    "sg:orig_category":"Telekommunikation",
    "sg:phone":"+43 3612 30208",
    "sg:postcode":"8940",
    "sg:province":"Steiermark",
    "wof:name":"Telering-Shop",
    "wof:placetype":"venue"
},
  "geometry": {"coordinates":[14.2429161072,47.5654678345],"type":"Point"}
}