{
  "type": "Feature",
  "properties": {
    "addr:full":"Nr 22 Liesing K\u00e4rnten 9653",
    "addr:housenumber":"22",
    "addr:postcode":"9653",
    "addr:street":"Nr;Kaernten",
    "iso:country":"AT",
    "sg:address":"Nr 22",
    "sg:city":"Liesing",
    "sg:orig_category":"Appartements / Ferienwohnungen",
    "sg:phone":"+43 4716 435",
    "sg:postcode":"9653",
    "sg:province":"K\u00e4rnten",
    "wof:name":"Haus Mesner",
    "wof:placetype":"venue"
},
  "geometry": {"coordinates":[12.8082408905,46.694065094],"type":"Point"}
}