{
  "type": "Feature",
  "properties": {
    "addr:full":"Lamezanstr. 11 Wien Wien 1230",
    "addr:housenumber":"11",
    "addr:postcode":"1230",
    "addr:street":"Lamezanstr.",
    "iso:country":"AT",
    "sg:address":"Lamezanstr. 11",
    "sg:city":"Wien",
    "sg:classifiers":[
        {
            "category":"Professional",
            "subcategory":"Engineering",
            "type":"Services"
        }
    ],
    "sg:phone":"+43 4316 1616610",
    "sg:postcode":"1230",
    "sg:province":"Wien",
    "sg:tags":[
        "machine",
        "-",
        "mechanical"
    ],
    "wof:name":"SERVO KING KLIMAANLAGEN U. K\u00dcHLTRANSPORT-SERVICE GES.MBH",
    "wof:placetype":"venue"
},
  "geometry": {"coordinates":[16.3393955231,48.1394538879],"type":"Point"}
}