{
  "type": "Feature",
  "properties": {
    "addr:full":"Dorf 7 Neukirchen an der Enknach Ober\u00f6sterreich 5145",
    "addr:housenumber":"7",
    "addr:postcode":"5145",
    "addr:street":"Dorf",
    "iso:country":"AT",
    "sg:address":"Dorf 7",
    "sg:city":"Neukirchen an der Enknach",
    "sg:orig_category":"Handarbeiten",
    "sg:phone":"+43 4377 292482",
    "sg:postcode":"5145",
    "sg:province":"Ober\u00f6sterreich",
    "wof:name":"Gerlinde's N\u00e4hstube",
    "wof:placetype":"venue"
},
  "geometry": {"coordinates":[13.0270986557,48.1755638123],"type":"Point"}
}