{
  "type": "Feature",
  "properties": {
    "iso:country":"AT",
    "sg:address":"Am Brunnenfeld 1",
    "sg:city":"Gramatneusiedl",
    "sg:orig_category":"Wasserwerke",
    "sg:phone":"+43 2234 78381",
    "sg:postcode":"2440",
    "sg:province":"Nieder\u00f6sterreich",
    "wof:name":"evn wasser GesmbH",
    "wof:placetype":"venue"
},
  "geometry": {"coordinates":[16.5092182159,48.015625],"type":"Point"}
}