{
  "type": "Feature",
  "properties": {
    "addr:full":"Hagau 4 Kramsach Tirol 6233",
    "addr:housenumber":"4",
    "addr:postcode":"6233",
    "addr:street":"Hagau;Tirol",
    "iso:country":"AT",
    "sg:address":"Hagau 4",
    "sg:city":"Kramsach",
    "sg:orig_category":"Maler, Anstreicher U Lackierer",
    "sg:phone":"+43 4353 3763779",
    "sg:postcode":"6233",
    "sg:province":"Tirol",
    "wof:name":"Malerei-Farbenhandel Franz Bieber",
    "wof:placetype":"venue"
},
  "geometry": {"coordinates":[11.8722829819,47.4349479675],"type":"Point"}
}