{
  "type": "Feature",
  "properties": {
    "addr:full":"Landstr. 3 Zwettl Nieder\u00f6sterreich 3910",
    "addr:housenumber":"3",
    "addr:postcode":"3910",
    "addr:street":"Landstr.;Niederoesterreich",
    "iso:country":"AT",
    "sg:address":"Landstr. 3",
    "sg:city":"Zwettl",
    "sg:classifiers":[
        {
            "category":"Manufacturing",
            "subcategory":"Metals",
            "type":"Manufacturing & Wholesale Goods"
        }
    ],
    "sg:phone":"+43 4328 22528430",
    "sg:postcode":"3910",
    "sg:province":"Nieder\u00f6sterreich",
    "sg:tags":[
        "metallurgy",
        "metalworking"
    ],
    "wof:name":"HERMANN KASTNER GMBH",
    "wof:placetype":"venue"
},
  "geometry": {"coordinates":[15.1683454514,48.6028366089],"type":"Point"}
}