{
  "type": "Feature",
  "properties": {
    "addr:full":"Rosennockstr 4 Bad Kleinkirchheim K\u00e4rnten 9546",
    "addr:housenumber":"4",
    "addr:postcode":"9546",
    "addr:street":"Rosennockstr",
    "iso:country":"AT",
    "sg:address":"Rosennockstr 4",
    "sg:city":"Bad Kleinkirchheim",
    "sg:classifiers":[
        {
            "category":"Travel",
            "subcategory":"Hotels & Motels",
            "type":"Entertainment"
        }
    ],
    "sg:phone":"+43 4240 4010",
    "sg:postcode":"9546",
    "sg:province":"K\u00e4rnten",
    "wof:name":"Alpenhotel Schneewei\u00df",
    "wof:placetype":"venue"
},
  "geometry": {"coordinates":[13.7641029358,46.8351974487],"type":"Point"}
}