{
  "type": "Feature",
  "properties": {
    "addr:full":"Merbodg 4 Bregenz Vorarlberg 6900",
    "addr:housenumber":"4",
    "addr:postcode":"6900",
    "addr:street":"Merbodg",
    "iso:country":"AT",
    "sg:address":"Merbodg 4",
    "sg:city":"Bregenz",
    "sg:orig_category":"Yachtcharter",
    "sg:phone":"+43 5574 47088",
    "sg:postcode":"6900",
    "sg:province":"Vorarlberg",
    "wof:name":"Alphard-Sailing",
    "wof:placetype":"venue"
},
  "geometry": {"coordinates":[9.7436752319,47.5037956238],"type":"Point"}
}