{
  "type": "Feature",
  "properties": {
    "addr:full":"Haid 29 Saalfelden am Steinernen Meer Salzburg 5760",
    "addr:housenumber":"29",
    "addr:postcode":"5760",
    "addr:street":"Haid;Salzburg",
    "iso:country":"AT",
    "sg:address":"Haid 29",
    "sg:city":"Saalfelden am Steinernen Meer",
    "sg:orig_category":"Pensionen / Privatzimmer",
    "sg:phone":"+43 6582 70436",
    "sg:postcode":"5760",
    "sg:province":"Salzburg",
    "wof:name":"Pension Schorn",
    "wof:placetype":"venue"
},
  "geometry": {"coordinates":[12.8211736679,47.4097671509],"type":"Point"}
}