{
  "type": "Feature",
  "properties": {
    "addr:full":"Schmiedg 34 Leibnitz Steiermark 8430",
    "addr:housenumber":"34",
    "addr:postcode":"8430",
    "addr:street":"Schmiedg;Steiermark",
    "iso:country":"AT",
    "sg:address":"Schmiedg 34",
    "sg:city":"Leibnitz",
    "sg:orig_category":"Bestattungsunternehmen",
    "sg:phone":"+43 4334 52824600",
    "sg:postcode":"8430",
    "sg:province":"Steiermark",
    "wof:name":"Kada Rudolf",
    "wof:placetype":"venue"
},
  "geometry": {"coordinates":[15.540473938,46.7792892456],"type":"Point"}
}