{
  "type": "Feature",
  "properties": {
    "iso:country":"AT",
    "sg:address":"Bahnhofpl 1",
    "sg:city":"Leoben",
    "sg:orig_category":"Pensionen / Privatzimmer",
    "sg:phone":"+43 4338 4242262",
    "sg:postcode":"8700",
    "sg:province":"Steiermark",
    "wof:name":"Pension zur S\u00fcdbahn",
    "wof:placetype":"venue"
},
  "geometry": {"coordinates":[15.0902862549,47.3862113953],"type":"Point"}
}