{
  "type": "Feature",
  "properties": {
    "iso:country":"AT",
    "sg:address":"Bischof-Schneider-Str 10",
    "sg:city":"Gaweinstal",
    "sg:orig_category":"Lebensmittel / Einzelhandel",
    "sg:phone":"+43 4325 7421070",
    "sg:postcode":"2191",
    "sg:province":"Nieder\u00f6sterreich",
    "wof:name":"Spar-Markt Plach",
    "wof:placetype":"venue"
},
  "geometry": {"coordinates":[16.588684082,48.4780540466],"type":"Point"}
}