{
  "type": "Feature",
  "properties": {
    "iso:country":"AT",
    "sg:address":"Thurnhofg 4",
    "sg:city":"Horn",
    "sg:orig_category":"Nachhilfe U Lernbetreuung",
    "sg:phone":"+43 4329 8220660",
    "sg:postcode":"3580",
    "sg:province":"Nieder\u00f6sterreich",
    "wof:name":"AUF ZACK - Lernhilfe-Institut",
    "wof:placetype":"venue"
},
  "geometry": {"coordinates":[15.6574287415,48.6637763977],"type":"Point"}
}