{
  "type": "Feature",
  "properties": {
    "addr:full":"B\u00f6ckhg 2-4 Wien Wien 1120",
    "addr:housenumber":"2-4",
    "addr:postcode":"1120",
    "addr:street":"Boeckhg",
    "iso:country":"AT",
    "sg:address":"B\u00f6ckhg 2-4",
    "sg:city":"Wien",
    "sg:orig_category":"Lebensmittel / Einzelhandel",
    "sg:phone":"+43 1 8153683",
    "sg:postcode":"1120",
    "sg:province":"Wien",
    "wof:name":"Billa AG",
    "wof:placetype":"venue"
},
  "geometry": {"coordinates":[16.3290939331,48.1824874878],"type":"Point"}
}