{
  "type": "Feature",
  "properties": {
    "iso:country":"AT",
    "sg:address":"Universit\u00e4tsstr 14",
    "sg:city":"Innsbruck",
    "sg:orig_category":"Friseure U Frisiersalons",
    "sg:phone":"+43 4351 2573888",
    "sg:postcode":"6020",
    "sg:province":"Tirol",
    "wof:name":"Frisiersalon Franz Claudia",
    "wof:placetype":"venue"
},
  "geometry": {"coordinates":[11.399564743,47.2690010071],"type":"Point"}
}