{
  "type": "Feature",
  "properties": {
    "addr:full":"Franz Josef-Str 9 Perchtoldsdorf Nieder\u00f6sterreich 2380",
    "addr:housenumber":"9",
    "addr:postcode":"2380",
    "addr:street":"Franz Josef-Str",
    "iso:country":"AT",
    "sg:address":"Franz Josef-Str 9",
    "sg:city":"Perchtoldsdorf",
    "sg:classifiers":[
        {
            "category":"Retail",
            "subcategory":"Event Space",
            "type":"Services"
        }
    ],
    "sg:phone":"+43 1 8697360",
    "sg:postcode":"2380",
    "sg:province":"Nieder\u00f6sterreich",
    "sg:tags":[
        "hand-",
        "u",
        "fu\u00c3\u0178pflege"
    ],
    "wof:name":"Preyer Leopoldine GmbH",
    "wof:placetype":"venue"
},
  "geometry": {"coordinates":[16.2671413422,48.1201400757],"type":"Point"}
}