{
  "type": "Feature",
  "properties": {
    "iso:country":"AT",
    "sg:address":"Kremser Str. 8",
    "sg:city":"Eggenburg",
    "sg:classifiers":[
        {
            "category":"Travel",
            "subcategory":"Travel Agent",
            "type":"Entertainment"
        }
    ],
    "sg:phone":"+43 4329 843531",
    "sg:postcode":"3730",
    "sg:province":"Nieder\u00f6sterreich",
    "sg:tags":[
        "business"
    ],
    "wof:name":"STADTHOTEL EGGENBURG WERNER OPPITZ",
    "wof:placetype":"venue"
},
  "geometry": {"coordinates":[15.8172426224,48.6414794922],"type":"Point"}
}