{
  "type": "Feature",
  "properties": {
    "addr:full":"Dorfstr 25 St. Anton am Arlberg Tirol 6580",
    "addr:housenumber":"25",
    "addr:postcode":"6580",
    "addr:street":"Dorfstr;Tirol",
    "iso:country":"AT",
    "sg:address":"Dorfstr 25",
    "sg:city":"St. Anton am Arlberg",
    "sg:classifiers":[
        {
            "category":"Travel",
            "subcategory":"Hotels & Motels",
            "type":"Entertainment"
        }
    ],
    "sg:phone":"+43 5446 32620",
    "sg:postcode":"6580",
    "sg:province":"Tirol",
    "wof:name":"Hotel-garni Seeberger",
    "wof:placetype":"venue"
},
  "geometry": {"coordinates":[10.2660741806,47.1294212341],"type":"Point"}
}