{
  "type": "Feature",
  "properties": {
    "iso:country":"AT",
    "sg:address":"Greiner Str 70",
    "sg:city":"Kremsm\u00fcnster",
    "sg:classifiers":[
        {
            "category":"Professional",
            "type":"Services"
        }
    ],
    "sg:phone":"+43 7583 72510",
    "sg:postcode":"4550",
    "sg:province":"Ober\u00f6sterreich",
    "sg:tags":[
        "leasing"
    ],
    "wof:name":"Greiner KG",
    "wof:placetype":"venue"
},
  "geometry": {"coordinates":[14.120349884,48.0394210815],"type":"Point"}
}