{
  "type": "Feature",
  "properties": {
    "addr:full":"Gallanderstr 15 Linz Ober\u00f6sterreich 4020",
    "addr:housenumber":"15",
    "addr:postcode":"4020",
    "addr:street":"Gallanderstr",
    "iso:country":"AT",
    "sg:address":"Gallanderstr 15",
    "sg:city":"Linz",
    "sg:orig_category":"Anlagenbau U -Technik",
    "sg:phone":"+43 4373 2371707",
    "sg:postcode":"4020",
    "sg:province":"Ober\u00f6sterreich",
    "wof:name":"Telekom Building Systems GmbH",
    "wof:placetype":"venue"
},
  "geometry": {"coordinates":[14.3060331345,48.3156051636],"type":"Point"}
}