{
  "type": "Feature",
  "properties": {
    "addr:full":"Villacher Str 19 Feldkirchen in K\u00e4rnten K\u00e4rnten 9560",
    "addr:postcode":"9560",
    "addr:street":"Str 19;Kaernten",
    "iso:country":"AT",
    "sg:address":"Villacher Str 19",
    "sg:city":"Feldkirchen in K\u00e4rnten",
    "sg:orig_category":"Transportunternehmen",
    "sg:phone":"+43 4342 7642000",
    "sg:postcode":"9560",
    "sg:province":"K\u00e4rnten",
    "wof:name":"G\u00e4rtner Transport & Handels GmbH",
    "wof:placetype":"venue"
},
  "geometry": {"coordinates":[14.0920295715,46.7234268188],"type":"Point"}
}