{
  "type": "Feature",
  "properties": {
    "addr:full":"Innsbrucker Strasse 48 Kirchdorf in Tirol Tirol 6382",
    "addr:housenumber":"48",
    "addr:postcode":"6382",
    "addr:street":"Innsbrucker Strasse;Tirol",
    "iso:country":"AT",
    "sg:address":"Innsbrucker Strasse 48",
    "sg:city":"Kirchdorf in Tirol",
    "sg:orig_category":"Car Radios, Car Hi-Fi Systems",
    "sg:phone":"+43 5352 63149",
    "sg:postcode":"6382",
    "sg:province":"Tirol",
    "sg:website":"redzac-gruendler.at",
    "wof:name":"Elektro-Center Gr\u00fcndler GesmbH & Co KG",
    "wof:placetype":"venue"
},
  "geometry": {"coordinates":[12.4490499496,47.5451469421],"type":"Point"}
}