{
  "type": "Feature",
  "properties": {
    "addr:full":"Salzburger Str Schladming Steiermark 8970",
    "addr:postcode":"8970",
    "addr:street":"Salzburger Str",
    "iso:country":"AT",
    "sg:address":"Salzburger Str",
    "sg:city":"Schladming",
    "sg:orig_category":"Tankstellen",
    "sg:phone":"+43 4336 8722689",
    "sg:postcode":"8970",
    "sg:province":"Steiermark",
    "wof:name":"Shell Austria GmbH",
    "wof:placetype":"venue"
},
  "geometry": {"coordinates":[13.6604976654,47.3911476135],"type":"Point"}
}