{
  "type": "Feature",
  "properties": {
    "addr:full":"Hauptpl 1 Niklasdorf Steiermark 8712",
    "addr:housenumber":"1",
    "addr:postcode":"8712",
    "addr:street":"Hauptpl",
    "iso:country":"AT",
    "sg:address":"Hauptpl 1",
    "sg:city":"Niklasdorf",
    "sg:orig_category":"Gemeinden",
    "sg:phone":"+43 3842 813110",
    "sg:postcode":"8712",
    "sg:province":"Steiermark",
    "wof:name":"Marktgemeindeamt Niklasdorf",
    "wof:placetype":"venue"
},
  "geometry": {"coordinates":[15.1574487686,47.3976745605],"type":"Point"}
}