{
  "type": "Feature",
  "properties": {
    "addr:full":"Haller Strasse 178 Innsbruck Tirol 6020",
    "addr:housenumber":"178",
    "addr:postcode":"6020",
    "addr:street":"Haller Strasse;Tirol",
    "iso:country":"AT",
    "sg:address":"Haller Strasse 178",
    "sg:city":"Innsbruck",
    "sg:classifiers":[
        {
            "category":"Shopping",
            "subcategory":"Department Store",
            "type":"Retail Goods"
        }
    ],
    "sg:phone":"+43 512 247930",
    "sg:postcode":"6020",
    "sg:province":"Tirol",
    "sg:tags":[
        "linen",
        "bed"
    ],
    "sg:website":"pollo.at",
    "wof:name":"Pollo Textil-Handelsges.m.b.H.",
    "wof:placetype":"venue"
},
  "geometry": {"coordinates":[11.4360904694,47.2759208679],"type":"Point"}
}