{
  "type": "Feature",
  "properties": {
    "addr:full":"Freist\u00e4dter Strasse 236 Linz Ober\u00f6sterreich 4040",
    "addr:housenumber":"236",
    "addr:postcode":"4040",
    "addr:street":"Freistaedter Strasse",
    "iso:country":"AT",
    "sg:address":"Freist\u00e4dter Strasse 236",
    "sg:city":"Linz",
    "sg:classifiers":[
        {
            "category":"Shopping",
            "subcategory":"Beauty & Cosmetics",
            "type":"Retail Goods"
        }
    ],
    "sg:phone":"+43 732 757167",
    "sg:postcode":"4040",
    "sg:province":"Ober\u00f6sterreich",
    "sg:tags":[
        "natural"
    ],
    "sg:website":"paracelsus.at",
    "wof:name":"PARACELSUS HAUS Handels- u. Dienstleistungs GmbH",
    "wof:placetype":"venue"
},
  "geometry": {"coordinates":[14.3033847809,48.3268241882],"type":"Point"}
}