{
  "type": "Feature",
  "properties": {
    "addr:full":"Schiffamtsg 10A Wien Wien 1020",
    "addr:housenumber":"10a",
    "addr:postcode":"1020",
    "addr:street":"Schiffamtsg",
    "iso:country":"AT",
    "sg:address":"Schiffamtsg 10A",
    "sg:city":"Wien",
    "sg:orig_category":"Bauleitung U -Betreuung",
    "sg:phone":"+43 1 5320543",
    "sg:postcode":"1020",
    "sg:province":"Wien",
    "wof:name":"DG-Baumanagement GesmbH",
    "wof:placetype":"venue"
},
  "geometry": {"coordinates":[16.3740215302,48.2187461853],"type":"Point"}
}