{
  "type": "Feature",
  "properties": {
    "addr:full":"Italiener Str 21 Villach K\u00e4rnten 9500",
    "addr:housenumber":"21",
    "addr:postcode":"9500",
    "addr:street":"Str;Kaernten",
    "iso:country":"AT",
    "sg:address":"Italiener Str 21",
    "sg:city":"Villach",
    "sg:orig_category":"Aquarien U Aquarienbedarf",
    "sg:phone":"+43 4242 219201",
    "sg:postcode":"9500",
    "sg:province":"K\u00e4rnten",
    "wof:name":"Aqua Shop S\u00fc\u00df- und Salzwasseraquaristik",
    "wof:placetype":"venue"
},
  "geometry": {"coordinates":[13.8434228897,46.6099205017],"type":"Point"}
}