{
  "type": "Feature",
  "properties": {
    "addr:full":"Burgg 122 Wien Wien 1070",
    "addr:housenumber":"122",
    "addr:postcode":"1070",
    "iso:country":"AT",
    "sg:address":"Burgg 122",
    "sg:city":"Wien",
    "sg:orig_category":"Lebensmittel / Einzelhandel",
    "sg:phone":"+43 1 5229768",
    "sg:postcode":"1070",
    "sg:province":"Wien",
    "wof:name":"F\u00fchrer Alfred",
    "wof:placetype":"venue"
},
  "geometry": {"coordinates":[16.3396472931,48.2045059204],"type":"Point"}
}