{
  "type": "Feature",
  "properties": {
    "iso:country":"AT",
    "sg:address":"Gro\u00dfendorf 92",
    "sg:city":"Ried im Traunkreis",
    "sg:orig_category":"Speditionen",
    "sg:phone":"+43 7588 656560",
    "sg:postcode":"4551",
    "sg:province":"Ober\u00f6sterreich",
    "wof:name":"Rumplmayr KG",
    "wof:placetype":"venue"
},
  "geometry": {"coordinates":[14.0738592148,48.0253601074],"type":"Point"}
}