{
  "type": "Feature",
  "properties": {
    "addr:full":"Altlassing 21 Lassing Steiermark 8903",
    "addr:housenumber":"21",
    "addr:postcode":"8903",
    "addr:street":"Altlassing",
    "iso:country":"AT",
    "sg:address":"Altlassing 21",
    "sg:city":"Lassing",
    "sg:orig_category":"Tonstudios",
    "sg:phone":"+43 4336 12824170",
    "sg:postcode":"8903",
    "sg:province":"Steiermark",
    "sg:website":"aufnahmestudio.at; solid-werbeton.com; solid-werbeton.com",
    "wof:name":"solid-werbeton",
    "wof:placetype":"venue"
},
  "geometry": {"coordinates":[14.2599620819,47.5367584229],"type":"Point"}
}