{
  "type": "Feature",
  "properties": {
    "iso:country":"AT",
    "sg:address":"Nr 9",
    "sg:city":"Bad Mitterndorf",
    "sg:orig_category":"Restaurants: Chinesisch",
    "sg:phone":"+43 3623 2273",
    "sg:postcode":"8983",
    "sg:province":"Steiermark",
    "wof:name":"PENG LAI GesmbH",
    "wof:placetype":"venue"
},
  "geometry": {"coordinates":[13.9318876266,47.5550498962],"type":"Point"}
}