{
  "type": "Feature",
  "properties": {
    "iso:country":"AT",
    "sg:address":"Linzer Str 5",
    "sg:city":"Rohrbach in Ober\u00f6sterreich",
    "sg:orig_category":"Bekleidung / Einzelhandel",
    "sg:phone":"+43 4372 894839",
    "sg:postcode":"4150",
    "sg:province":"Ober\u00f6sterreich",
    "wof:name":"FUSSL FLY - FUSSL MODESTRASSE Mayr GmbH",
    "wof:placetype":"venue"
},
  "geometry": {"coordinates":[13.9951534271,48.5746955872],"type":"Point"}
}