{
  "type": "Feature",
  "properties": {
    "addr:full":"Ernstbrunner Strasse 31-33 Stockerau Nieder\u00f6sterreich 2000",
    "addr:postcode":"31-33;2000",
    "addr:street":"Ernstbrunner Strasse",
    "iso:country":"AT",
    "sg:address":"Ernstbrunner Strasse 31-33",
    "sg:city":"Stockerau",
    "sg:classifiers":[
        {
            "category":"Utilities",
            "subcategory":"Natural Gas",
            "type":"Services"
        }
    ],
    "sg:phone":"+43 2266 61133",
    "sg:postcode":"2000",
    "sg:province":"Nieder\u00f6sterreich",
    "sg:tags":[
        "cutting",
        "system"
    ],
    "sg:website":"schweisstech.com",
    "wof:name":"Ing. Lager Robotersysteme & Schwei\u00dftechnik Ges.m.b.H.",
    "wof:placetype":"venue"
},
  "geometry": {"coordinates":[16.2228107452,48.3940582275],"type":"Point"}
}