{
  "type": "Feature",
  "properties": {
    "iso:country":"AT",
    "sg:address":"Bahnhofstr 19",
    "sg:city":"St. Georgen an der Gusen",
    "sg:orig_category":"Bauunternehmen",
    "sg:phone":"+43 7237 60600",
    "sg:postcode":"4222",
    "sg:province":"Ober\u00f6sterreich",
    "wof:name":"Hentschl\u00e4ger-Stross BaugesmbH",
    "wof:placetype":"venue"
},
  "geometry": {"coordinates":[14.4460773468,48.2691383362],"type":"Point"}
}