{
  "type": "Feature",
  "properties": {
    "iso:country":"AT",
    "sg:address":"Vbg Wirtschaftspark 1",
    "sg:city":"G\u00f6tzis",
    "sg:classifiers":[
        {
            "category":"Internet Cafe",
            "subcategory":"None",
            "type":"Food & Drink"
        }
    ],
    "sg:phone":"+43 5523 5491971",
    "sg:postcode":"6840",
    "sg:province":"Vorarlberg",
    "wof:name":"Procell EDV & Internet",
    "wof:placetype":"venue"
},
  "geometry": {"coordinates":[9.665719986,47.3356399536],"type":"Point"}
}