{
  "type": "Feature",
  "properties": {
    "addr:full":"Sch\u00f6merg 28 Klosterneuburg Nieder\u00f6sterreich 3400",
    "addr:housenumber":"28",
    "addr:postcode":"3400",
    "addr:street":"Schoemerg;Niederoesterreich",
    "iso:country":"AT",
    "sg:address":"Sch\u00f6merg 28",
    "sg:city":"Klosterneuburg",
    "sg:orig_category":"Unternehmensberatung",
    "sg:phone":"+43 2243 34477",
    "sg:postcode":"3400",
    "sg:province":"Nieder\u00f6sterreich",
    "wof:name":"EMC BeratungsgesmbH",
    "wof:placetype":"venue"
},
  "geometry": {"coordinates":[16.3027324677,48.3058929443],"type":"Point"}
}