{
  "type": "Feature",
  "properties": {
    "addr:full":"Loferer Bundesstr 2 Zell am See Salzburg 5700",
    "addr:housenumber":"2",
    "addr:postcode":"5700",
    "addr:street":"Bundesstr;Salzburg",
    "iso:country":"AT",
    "sg:address":"Loferer Bundesstr 2",
    "sg:city":"Zell am See",
    "sg:orig_category":"Lederbekleidung",
    "sg:phone":"+43 6542 73728",
    "sg:postcode":"5700",
    "sg:province":"Salzburg",
    "wof:name":"Wieser Lederbekleidung",
    "wof:placetype":"venue"
},
  "geometry": {"coordinates":[12.7967834473,47.3239631653],"type":"Point"}
}