{
  "type": "Feature",
  "properties": {
    "addr:full":"Hellwagstr 18a Wien Wien 1200",
    "addr:housenumber":"18a",
    "addr:postcode":"1200",
    "addr:street":"Hellwagstr",
    "iso:country":"AT",
    "sg:address":"Hellwagstr 18a",
    "sg:city":"Wien",
    "sg:classifiers":[
        {
            "category":"Retail",
            "subcategory":"Event Space",
            "type":"Services"
        }
    ],
    "sg:phone":"+43 1 3305784",
    "sg:postcode":"1200",
    "sg:province":"Wien",
    "sg:tags":[
        "hand-",
        "u",
        "fu\u00c3\u0178pflege"
    ],
    "wof:name":"Fu\u00dfpflege Anni",
    "wof:placetype":"venue"
},
  "geometry": {"coordinates":[16.3821125031,48.2380409241],"type":"Point"}
}