{
  "type": "Feature",
  "properties": {
    "addr:full":"Trattfelderstr 12 Stra\u00dfgang Steiermark 8054",
    "addr:housenumber":"12",
    "addr:postcode":"8054",
    "addr:street":"Trattfelderstr",
    "iso:country":"AT",
    "sg:address":"Trattfelderstr 12",
    "sg:city":"Stra\u00dfgang",
    "sg:orig_category":"Orgel- U Harmoniumbau",
    "sg:phone":"+43 316 252012",
    "sg:postcode":"8054",
    "sg:province":"Steiermark",
    "wof:name":"Hartinger Christian",
    "wof:placetype":"venue"
},
  "geometry": {"coordinates":[15.4086933136,47.0356826782],"type":"Point"}
}