{
  "type": "Feature",
  "properties": {
    "iso:country":"AT",
    "sg:address":"Geym\u00fcllerg 22/10",
    "sg:city":"Wien",
    "sg:classifiers":[
        {
            "category":"Internet Cafe",
            "subcategory":"None",
            "type":"Food & Drink"
        }
    ],
    "sg:phone":"+43 4369 911337005",
    "sg:postcode":"1180",
    "sg:province":"Wien",
    "sg:website":"ewerkstatt.com",
    "wof:name":"Duschanek Heinz DI Dr",
    "wof:placetype":"venue"
},
  "geometry": {"coordinates":[16.3445625305,48.2262420654],"type":"Point"}
}