{
  "type": "Feature",
  "properties": {
    "iso:country":"AT",
    "sg:address":"Alfred-Kubin-Pl 4",
    "sg:city":"Wien",
    "sg:classifiers":[
        {
            "category":"Taxi",
            "type":"Transportation"
        }
    ],
    "sg:phone":"+43 4366 42240471",
    "sg:postcode":"1220",
    "sg:province":"Wien",
    "sg:tags":[
        "personentransporte",
        "u"
    ],
    "wof:name":"Kowalski Gregor",
    "wof:placetype":"venue"
},
  "geometry": {"coordinates":[16.4412593842,48.2603034973],"type":"Point"}
}