{
  "type": "Feature",
  "properties": {
    "addr:full":"Kirchenstr 42 Schiefling am See K\u00e4rnten 9535",
    "addr:housenumber":"42",
    "addr:postcode":"9535",
    "addr:street":"Kirchenstr",
    "iso:country":"AT",
    "sg:address":"Kirchenstr 42",
    "sg:city":"Schiefling am See",
    "sg:orig_category":"Maler, Anstreicher U Lackierer",
    "sg:phone":"+43 4342 743730",
    "sg:postcode":"9535",
    "sg:province":"K\u00e4rnten",
    "wof:name":"Siebert Fritz jr",
    "wof:placetype":"venue"
},
  "geometry": {"coordinates":[14.0962686539,46.6048545837],"type":"Point"}
}