{
  "type": "Feature",
  "properties": {
    "iso:country":"AT",
    "sg:address":"Liechtensteinstr 126/2",
    "sg:city":"Wien",
    "sg:orig_category":"Elektroinstallationsunternehmen",
    "sg:phone":"+43 1 3192271",
    "sg:postcode":"1090",
    "sg:province":"Wien",
    "wof:name":"Elektroinstallationen G.T.A. Gesellschaft f techn Anlagen",
    "wof:placetype":"venue"
},
  "geometry": {"coordinates":[16.3561859131,48.2319526672],"type":"Point"}
}