{
  "type": "Feature",
  "properties": {
    "iso:country":"AT",
    "sg:address":"Nr 105",
    "sg:city":"Unterstinkenbrunn",
    "sg:classifiers":[
        {
            "category":"Retail",
            "subcategory":"Event Space",
            "type":"Services"
        }
    ],
    "sg:phone":"+43 2526 6377",
    "sg:postcode":"2154",
    "sg:province":"Nieder\u00f6sterreich",
    "sg:tags":[
        "hand-",
        "u",
        "fu\u00c3\u0178pflege"
    ],
    "wof:name":"Hagen Anna",
    "wof:placetype":"venue"
},
  "geometry": {"coordinates":[16.3802204132,48.6551513672],"type":"Point"}
}