{
  "type": "Feature",
  "properties": {
    "addr:full":"Eggenwaldweg 48 Innsbruck Tirol 6020",
    "addr:housenumber":"48",
    "addr:postcode":"6020",
    "addr:street":"Eggenwaldweg;Tirol",
    "iso:country":"AT",
    "sg:address":"Eggenwaldweg 48",
    "sg:city":"Innsbruck",
    "sg:orig_category":"Werbeagenturen",
    "sg:phone":"+43 512 201035",
    "sg:postcode":"6020",
    "sg:province":"Tirol",
    "wof:name":"TW-Promotion",
    "wof:placetype":"venue"
},
  "geometry": {"coordinates":[11.4296598434,47.2883911133],"type":"Point"}
}