{
  "type": "Feature",
  "properties": {
    "addr:full":"Erzherzog-Karl-Str 12 Wien Wien 1220",
    "addr:housenumber":"12",
    "addr:postcode":"1220",
    "addr:street":"Erzherzog-Karl-Str",
    "iso:country":"AT",
    "sg:address":"Erzherzog-Karl-Str 12",
    "sg:city":"Wien",
    "sg:orig_category":"Tankstellen",
    "sg:phone":"+43 1 2038131",
    "sg:postcode":"1220",
    "sg:province":"Wien",
    "wof:name":"Weiss & Prokes GesmbH",
    "wof:placetype":"venue"
},
  "geometry": {"coordinates":[16.4321250916,48.2382621765],"type":"Point"}
}