{
  "type": "Feature",
  "properties": {
    "addr:full":"Im Langfeld 33 Wildon Steiermark 8410",
    "addr:housenumber":"33",
    "addr:postcode":"8410",
    "addr:street":"Im Langfeld;Steiermark",
    "iso:country":"AT",
    "sg:address":"Im Langfeld 33",
    "sg:city":"Wildon",
    "sg:orig_category":"Tonstudios",
    "sg:phone":"+43 3182 2799",
    "sg:postcode":"8410",
    "sg:province":"Steiermark",
    "wof:name":"Mandl Wolfgang",
    "wof:placetype":"venue"
},
  "geometry": {"coordinates":[15.522351265,46.889629364],"type":"Point"}
}