{
  "type": "Feature",
  "properties": {
    "addr:full":"Kollonitschg 10 Wiener Neustadt Nieder\u00f6sterreich 2700",
    "addr:housenumber":"10",
    "addr:postcode":"2700",
    "addr:street":"Kollonitschg",
    "iso:country":"AT",
    "sg:address":"Kollonitschg 10",
    "sg:city":"Wiener Neustadt",
    "sg:orig_category":"Getriebe",
    "sg:phone":"+43 4326 2222430",
    "sg:postcode":"2700",
    "sg:province":"Nieder\u00f6sterreich",
    "sg:website":"zahnrad-stainer.at",
    "wof:name":"Stainer Robert Ing GmbH",
    "wof:placetype":"venue"
},
  "geometry": {"coordinates":[16.236497879,47.8131866455],"type":"Point"}
}