{
  "type": "Feature",
  "properties": {
    "iso:country":"AT",
    "sg:address":"Biberstr 22/Mezz",
    "sg:city":"Wien",
    "sg:classifiers":[
        {
            "category":"Sports & Exercise",
            "subcategory":"Gym",
            "type":"Entertainment"
        }
    ],
    "sg:phone":"+43 1 5127859",
    "sg:postcode":"1010",
    "sg:province":"Wien",
    "sg:tags":[
        "meditation"
    ],
    "wof:name":"\u00d6sterr Gesellschaft f Maharishis Vedische Wissenschaft",
    "wof:placetype":"venue"
},
  "geometry": {"coordinates":[16.3688049316,48.2025489807],"type":"Point"}
}