{
  "type": "Feature",
  "properties": {
    "addr:full":"Seebach 74 Au Steiermark 8624",
    "addr:housenumber":"74",
    "addr:postcode":"8624",
    "addr:street":"Seebach",
    "iso:country":"AT",
    "sg:address":"Seebach 74",
    "sg:city":"Au",
    "sg:classifiers":[
        {
            "category":"Manufacturing",
            "subcategory":"Tools & Machinery",
            "type":"Manufacturing & Wholesale Goods"
        }
    ],
    "sg:phone":"+43 3863 22730",
    "sg:postcode":"8624",
    "sg:province":"Steiermark",
    "sg:tags":[
        "part",
        "turned",
        "cnc"
    ],
    "sg:website":"mb-koller.at",
    "wof:name":"Maschinenbau Koller Ges.m.b.H.",
    "wof:placetype":"venue"
},
  "geometry": {"coordinates":[15.296705246,47.5503921509],"type":"Point"}
}