{
  "type": "Feature",
  "properties": {
    "addr:full":"Hallstatt Ober\u00f6sterreich 4830",
    "addr:postcode":"4830",
    "iso:country":"AT",
    "sg:city":"Hallstatt",
    "sg:orig_category":"Rettungsdienste",
    "sg:phone":"+43 4366 44215564",
    "sg:postcode":"4830",
    "sg:province":"Ober\u00f6sterreich",
    "wof:name":"\u00f6sterreichische Wasser-Rettung Einsatzleitung",
    "wof:placetype":"venue"
},
  "geometry": {"coordinates":[13.6493902206,47.5622138977],"type":"Point"}
}