{
  "type": "Feature",
  "properties": {
    "addr:full":"Hohenfeldstr 6 Wilhering Ober\u00f6sterreich 4073",
    "addr:housenumber":"6",
    "addr:postcode":"4073",
    "addr:street":"Hohenfeldstr",
    "iso:country":"AT",
    "sg:address":"Hohenfeldstr 6",
    "sg:city":"Wilhering",
    "sg:orig_category":"Vinotheken",
    "sg:phone":"+43 7226 2236",
    "sg:postcode":"4073",
    "sg:province":"Ober\u00f6sterreich",
    "wof:name":"Rathmair Albert Dipl-Ing",
    "wof:placetype":"venue"
},
  "geometry": {"coordinates":[14.1728477478,48.3105163574],"type":"Point"}
}