{
  "type": "Feature",
  "properties": {
    "addr:full":"Freizell 4  Wesenufer Ober\u00f6sterreich 4085",
    "addr:housenumber":"4",
    "addr:postcode":"4085",
    "addr:street":"Freizell",
    "iso:country":"AT",
    "sg:address":"Freizell 4 ",
    "sg:city":"Wesenufer",
    "sg:classifiers":[
        {
            "category":"Train Station",
            "subcategory":"Light Rail",
            "type":"Transportation"
        }
    ],
    "sg:phone":"+43 7285 6390",
    "sg:postcode":"4085",
    "sg:province":"Ober\u00f6sterreich",
    "sg:tags":[
        "lighter",
        "barge"
    ],
    "sg:website":"www.witti.co.at",
    "wof:name":"ZILLENBAUER Anton Witti",
    "wof:placetype":"venue"
},
  "geometry": {"coordinates":[13.82264328,48.4403686523],"type":"Point"}
}