{
  "type": "Feature",
  "properties": {
    "iso:country":"AT",
    "sg:address":"Stadtpl 19",
    "sg:city":"Mattighofen",
    "sg:orig_category":"Notare",
    "sg:phone":"+43 7742 2237",
    "sg:postcode":"5230",
    "sg:province":"Ober\u00f6sterreich",
    "wof:name":"Notariat Dr",
    "wof:placetype":"venue"
},
  "geometry": {"coordinates":[13.1499347687,48.1043052673],"type":"Point"}
}