{
  "type": "Feature",
  "properties": {
    "addr:full":"Brucker Bundesstr 35 Zell am See Salzburg 5700",
    "addr:housenumber":"35",
    "addr:postcode":"5700",
    "addr:street":"Salzburg",
    "iso:country":"AT",
    "sg:address":"Brucker Bundesstr 35",
    "sg:city":"Zell am See",
    "sg:orig_category":"Elektroinstallationsunternehmen",
    "sg:phone":"+43 6542 573880",
    "sg:postcode":"5700",
    "sg:province":"Salzburg",
    "wof:name":"Mayrhofer Peter",
    "wof:placetype":"venue"
},
  "geometry": {"coordinates":[12.792963028,47.3058853149],"type":"Point"}
}