{
  "type": "Feature",
  "properties": {
    "addr:full":"Maria-Theresien-Str 55-57 Innsbruck Tirol 6020",
    "addr:housenumber":"55-57",
    "addr:postcode":"6020",
    "addr:street":"Tirol",
    "iso:country":"AT",
    "sg:address":"Maria-Theresien-Str 55-57",
    "sg:city":"Innsbruck",
    "sg:classifiers":[
        {
            "category":"Professional",
            "subcategory":"Computer Services",
            "type":"Services"
        }
    ],
    "sg:phone":"+43 4351 253510",
    "sg:postcode":"6020",
    "sg:province":"Tirol",
    "sg:tags":[
        "software"
    ],
    "wof:name":"Tiscover AG",
    "wof:placetype":"venue"
},
  "geometry": {"coordinates":[11.394952774,47.2628517151],"type":"Point"}
}