{
  "type": "Feature",
  "properties": {
    "iso:country":"AT",
    "sg:address":"Georg-Pirmoser-Str 7",
    "sg:city":"Kufstein",
    "sg:orig_category":"Steinmetzbetriebe",
    "sg:phone":"+43 5372 62676",
    "sg:postcode":"6330",
    "sg:province":"Tirol",
    "sg:website":"schilcher.kufnet.at",
    "wof:name":"Schilcher OEG Steinmetzbetrieb",
    "wof:placetype":"venue"
},
  "geometry": {"coordinates":[12.1720523834,47.5829086304],"type":"Point"}
}