{
  "type": "Feature",
  "properties": {
    "iso:country":"AT",
    "sg:address":"Bahnhofstr 17",
    "sg:city":"Hopfgarten im Brixental",
    "sg:orig_category":"Transportunternehmen",
    "sg:phone":"+43 4353 3544050",
    "sg:postcode":"6361",
    "sg:province":"Tirol",
    "wof:name":"Fohringer GmbH Spezial-Transporte",
    "wof:placetype":"venue"
},
  "geometry": {"coordinates":[12.1513175964,47.4534034729],"type":"Point"}
}