{
  "type": "Feature",
  "properties": {
    "addr:full":"Michael-Jank-G 6 Ottenschlag Nieder\u00f6sterreich 3631",
    "addr:housenumber":"6",
    "addr:postcode":"3631",
    "addr:street":"Michael-Jank-G",
    "iso:country":"AT",
    "sg:address":"Michael-Jank-G 6",
    "sg:city":"Ottenschlag",
    "sg:orig_category":"Hauptschulen",
    "sg:phone":"+43 4328 7272680",
    "sg:postcode":"3631",
    "sg:province":"Nieder\u00f6sterreich",
    "wof:name":"Hauptschule Ottenschlag",
    "wof:placetype":"venue"
},
  "geometry": {"coordinates":[15.2211875916,48.4223632812],"type":"Point"}
}