{
  "type": "Feature",
  "properties": {
    "iso:country":"AT",
    "sg:address":"Friedensgasse 11",
    "sg:city":"Klagenfurt",
    "sg:classifiers":[
        {
            "category":"Building & Trades",
            "subcategory":"Construction",
            "type":"Services"
        }
    ],
    "sg:phone":"+43 4346 335522",
    "sg:postcode":"9020",
    "sg:province":"K\u00e4rnten",
    "sg:tags":[
        "work",
        "public"
    ],
    "wof:name":"KAROLINE WORNIK",
    "wof:placetype":"venue"
},
  "geometry": {"coordinates":[14.3411931992,46.6244544983],"type":"Point"}
}