{
  "type": "Feature",
  "properties": {
    "addr:full":"Schwindstr 49 Linz Ober\u00f6sterreich 4020",
    "addr:housenumber":"49",
    "addr:postcode":"4020",
    "addr:street":"Schwindstr",
    "iso:country":"AT",
    "sg:address":"Schwindstr 49",
    "sg:city":"Linz",
    "sg:orig_category":"Brandschutz",
    "sg:phone":"+43 732 372674",
    "sg:postcode":"4020",
    "sg:province":"Ober\u00f6sterreich",
    "wof:name":"INDU-LIGHT Tageslicht- und Brandschutz-Technik Vertriebs GmbH",
    "wof:placetype":"venue"
},
  "geometry": {"coordinates":[14.3062610626,48.2693252563],"type":"Point"}
}