{
  "type": "Feature",
  "properties": {
    "addr:full":"Annenstr 26 Graz Steiermark 8020",
    "addr:housenumber":"26",
    "addr:postcode":"8020",
    "addr:street":"Annenstr",
    "iso:country":"AT",
    "sg:address":"Annenstr 26",
    "sg:city":"Graz",
    "sg:classifiers":[
        {
            "category":"Retail",
            "subcategory":"Storage",
            "type":"Services"
        }
    ],
    "sg:phone":"+43 316 716311",
    "sg:postcode":"8020",
    "sg:province":"Steiermark",
    "sg:tags":[
        "archive"
    ],
    "wof:name":"\u00f6sterr Kabarett-Archiv",
    "wof:placetype":"venue"
},
  "geometry": {"coordinates":[15.4275417328,47.0712585449],"type":"Point"}
}