{
  "type": "Feature",
  "properties": {
    "iso:country":"AT",
    "sg:address":"Ikeapl 8/Top 1",
    "sg:city":"Haid",
    "sg:orig_category":"Bekleidung / Einzelhandel",
    "sg:phone":"+43 7229 78597",
    "sg:postcode":"4053",
    "sg:province":"Ober\u00f6sterreich",
    "wof:name":"FUSSL MODESTRASSE Mayr GmbH",
    "wof:placetype":"venue"
},
  "geometry": {"coordinates":[14.2510099411,48.2047348022],"type":"Point"}
}