{
  "type": "Feature",
  "properties": {
    "iso:country":"AT",
    "sg:address":"Nassereiner G 3",
    "sg:city":"St. Anton am Arlberg",
    "sg:orig_category":"Maler, Anstreicher U Lackierer",
    "sg:phone":"+43 4354 463264",
    "sg:postcode":"6580",
    "sg:province":"Tirol",
    "wof:name":"Gabl - inh Kurt Strau\u00df",
    "wof:placetype":"venue"
},
  "geometry": {"coordinates":[10.2740516663,47.13539505],"type":"Point"}
}