{
  "type": "Feature",
  "properties": {
    "addr:full":"Elisabethstr 31 Salzburg Salzburg 5020",
    "addr:housenumber":"31",
    "addr:postcode":"5020",
    "addr:street":"Elisabethstr;Salzburg",
    "iso:country":"AT",
    "sg:address":"Elisabethstr 31",
    "sg:city":"Salzburg",
    "sg:orig_category":"Pensionen / Privatzimmer",
    "sg:phone":"+43 662 871405",
    "sg:postcode":"5020",
    "sg:province":"Salzburg",
    "wof:name":"Pension Jahn",
    "wof:placetype":"venue"
},
  "geometry": {"coordinates":[13.0417957306,47.8139839172],"type":"Point"}
}