{
  "type": "Feature",
  "properties": {
    "iso:country":"AT",
    "sg:address":"Leopoldstr 37",
    "sg:city":"Innsbruck",
    "sg:orig_category":"Lebensmittel / Einzelhandel",
    "sg:phone":"+43 512 560873",
    "sg:postcode":"6020",
    "sg:province":"Tirol",
    "wof:name":"MPREIS WarenvertriebsgesmbH",
    "wof:placetype":"venue"
},
  "geometry": {"coordinates":[11.3971605301,47.2580375671],"type":"Point"}
}