{
  "type": "Feature",
  "properties": {
    "addr:full":"Nr 204 Bad St. Leonhard im Lavanttal K\u00e4rnten 9462",
    "addr:postcode":"9462",
    "addr:street":"Nr",
    "iso:country":"AT",
    "sg:address":"Nr 204",
    "sg:city":"Bad St. Leonhard im Lavanttal",
    "sg:orig_category":"Automatisierungstechnik",
    "sg:phone":"+43 4366 42140367",
    "sg:postcode":"9462",
    "sg:province":"K\u00e4rnten",
    "wof:name":"Automatisierungstechnik Pichler - ATP",
    "wof:placetype":"venue"
},
  "geometry": {"coordinates":[14.7903852463,46.9638404846],"type":"Point"}
}