{
  "type": "Feature",
  "properties": {
    "addr:full":"Franz-Mair-Weg 3 Weikendorf Nieder\u00f6sterreich 2253",
    "addr:housenumber":"3",
    "addr:postcode":"2253",
    "addr:street":"Franz-Mair-Weg",
    "iso:country":"AT",
    "sg:address":"Franz-Mair-Weg 3",
    "sg:city":"Weikendorf",
    "sg:orig_category":"Volksschulen",
    "sg:phone":"+43 4322 823655",
    "sg:postcode":"2253",
    "sg:province":"Nieder\u00f6sterreich",
    "wof:name":"Volksschule",
    "wof:placetype":"venue"
},
  "geometry": {"coordinates":[16.7629680634,48.3438072205],"type":"Point"}
}