{
  "type": "Feature",
  "properties": {
    "addr:full":"Nr 203 Bad Gleichenberg Steiermark 8344",
    "addr:postcode":"8344",
    "addr:street":"Nr",
    "iso:country":"AT",
    "sg:address":"Nr 203",
    "sg:city":"Bad Gleichenberg",
    "sg:orig_category":"Fotografen",
    "sg:phone":"+43 4331 592208",
    "sg:postcode":"8344",
    "sg:province":"Steiermark",
    "wof:name":"Foto Wurm - Nagl",
    "wof:placetype":"venue"
},
  "geometry": {"coordinates":[15.9038906097,46.8549499512],"type":"Point"}
}