{
  "type": "Feature",
  "properties": {
    "addr:full":"Migazzipl. 1  Wien Wien 1120",
    "addr:housenumber":"1",
    "addr:postcode":"1120",
    "addr:street":"Migazzipl.",
    "iso:country":"AT",
    "sg:address":"Migazzipl. 1 ",
    "sg:city":"Wien",
    "sg:classifiers":[
        {
            "category":"Food & Beverages",
            "subcategory":"Groceries & Convenience Stores",
            "type":"Retail Goods"
        }
    ],
    "sg:phone":"+43 4318 1381960",
    "sg:postcode":"1120",
    "sg:province":"Wien",
    "sg:tags":[
        "drink"
    ],
    "wof:name":"FERDINAND GRASL GMBH",
    "wof:placetype":"venue"
},
  "geometry": {"coordinates":[16.3358364105,48.181602478],"type":"Point"}
}