{
  "type": "Feature",
  "properties": {
    "iso:country":"AT",
    "sg:address":"Kapellenweg 6",
    "sg:city":"Imst",
    "sg:orig_category":"Volkshochschulen",
    "sg:phone":"+43 4365 07484944",
    "sg:postcode":"6460",
    "sg:province":"Tirol",
    "wof:name":"Volkshochschule Imst Mag Birgit u Mag Nikolaus Meze",
    "wof:placetype":"venue"
},
  "geometry": {"coordinates":[10.7415313721,47.2319068909],"type":"Point"}
}