{
  "type": "Feature",
  "properties": {
    "iso:country":"AT",
    "sg:address":"Ludwig-Binder-Str 1/1",
    "sg:city":"Gleisdorf",
    "sg:orig_category":"Versicherungsunternehmen",
    "sg:phone":"+43 3112 36036",
    "sg:postcode":"8200",
    "sg:province":"Steiermark",
    "wof:name":"Z\u00fcrich Versicherungs-AG",
    "wof:placetype":"venue"
},
  "geometry": {"coordinates":[15.7082157135,47.1060714722],"type":"Point"}
}