{
  "type": "Feature",
  "properties": {
    "iso:country":"AT",
    "sg:address":"Wiener Str 77",
    "sg:city":"Bruck an der Mur",
    "sg:orig_category":"Volksschulen",
    "sg:phone":"+43 3862 51803",
    "sg:postcode":"8600",
    "sg:province":"Steiermark",
    "wof:name":"Volksschule",
    "wof:placetype":"venue"
},
  "geometry": {"coordinates":[15.2706317902,47.4255371094],"type":"Point"}
}