{
  "type": "Feature",
  "properties": {
    "addr:full":"Nr 62 Bleiburg K\u00e4rnten 9150",
    "addr:housenumber":"9150",
    "addr:street":"Nr",
    "iso:country":"AT",
    "sg:address":"Nr 62",
    "sg:city":"Bleiburg",
    "sg:orig_category":"Appartements / Ferienwohnungen",
    "sg:phone":"+43 4235 2622",
    "sg:postcode":"9150",
    "sg:province":"K\u00e4rnten",
    "wof:name":"Ferienwohnungen Monika",
    "wof:placetype":"venue"
},
  "geometry": {"coordinates":[14.799115181,46.5901870728],"type":"Point"}
}