{
  "type": "Feature",
  "properties": {
    "addr:full":"Buchenweg 4 Krumpendorf K\u00e4rnten 9201",
    "addr:housenumber":"4",
    "addr:postcode":"9201",
    "addr:street":"Buchenweg;Kaernten",
    "iso:country":"AT",
    "sg:address":"Buchenweg 4",
    "sg:city":"Krumpendorf",
    "sg:orig_category":"Immobilienmakler",
    "sg:phone":"+43 4342 292983",
    "sg:postcode":"9201",
    "sg:province":"K\u00e4rnten",
    "wof:name":"Macher Walter Dr",
    "wof:placetype":"venue"
},
  "geometry": {"coordinates":[14.2333784103,46.6282157898],"type":"Point"}
}