{
  "type": "Feature",
  "properties": {
    "addr:full":"Spittelauer L\u00e4nde 9/27 Wien Wien 1090",
    "addr:housenumber":"9 / 27",
    "addr:postcode":"1090",
    "addr:street":"Laende",
    "iso:country":"AT",
    "sg:address":"Spittelauer L\u00e4nde 9/27",
    "sg:city":"Wien",
    "sg:orig_category":"Telefonmarketing",
    "sg:phone":"+43 1 31739290",
    "sg:postcode":"1090",
    "sg:province":"Wien",
    "wof:name":"P & W Phone Agency Paschinger R & A Wozniak GesnbR",
    "wof:placetype":"venue"
},
  "geometry": {"coordinates":[16.3634281158,48.2277488708],"type":"Point"}
}