{
  "type": "Feature",
  "properties": {
    "iso:country":"AT",
    "sg:address":"Mozartstr 8a",
    "sg:city":"Hohenems",
    "sg:orig_category":"Fliesen- U Plattenverlegungen",
    "sg:phone":"+43 4355 7673394",
    "sg:postcode":"6845",
    "sg:province":"Vorarlberg",
    "sg:website":"fliesen-liftinger.com",
    "wof:name":"Fliesen Liftinger",
    "wof:placetype":"venue"
},
  "geometry": {"coordinates":[9.6860761642,47.357749939],"type":"Point"}
}