{
  "type": "Feature",
  "properties": {
    "addr:full":"Marie Gailer Str 38 Villach K\u00e4rnten 9500",
    "addr:housenumber":"38",
    "addr:postcode":"9500",
    "addr:street":"Marie Gailer Str;Kaernten",
    "iso:country":"AT",
    "sg:address":"Marie Gailer Str 38",
    "sg:city":"Villach",
    "sg:classifiers":[
        {
            "category":"Manufacturing",
            "subcategory":"Glass & Minerals",
            "type":"Manufacturing & Wholesale Goods"
        }
    ],
    "sg:phone":"+43 4342 4233635",
    "sg:postcode":"9500",
    "sg:province":"K\u00e4rnten",
    "sg:tags":[
        "building",
        "material"
    ],
    "wof:name":"K\u00d6LL KERAMIK GESMBH",
    "wof:placetype":"venue"
},
  "geometry": {"coordinates":[13.8683185577,46.6034584045],"type":"Point"}
}