{
  "type": "Feature",
  "properties": {
    "addr:full":"Flachgasse 14-16 Wien Wien 1150",
    "addr:postcode":"14-16;1150",
    "addr:street":"Flachgasse",
    "iso:country":"AT",
    "sg:address":"Flachgasse 14-16",
    "sg:city":"Wien",
    "sg:classifiers":[
        {
            "category":"Government",
            "subcategory":"Police Station",
            "type":"Public Place"
        }
    ],
    "sg:phone":"+43 1 9822418",
    "sg:postcode":"1150",
    "sg:province":"Wien",
    "sg:tags":[
        "anodizing"
    ],
    "sg:website":"chromdesign.at",
    "wof:name":"Kudrna Ges.m.b.H. Metallveredelung",
    "wof:placetype":"venue"
},
  "geometry": {"coordinates":[16.3140945435,48.1946182251],"type":"Point"}
}