{
  "type": "Feature",
  "properties": {
    "addr:full":"Grazer Str 301 Deutschfeistritz Steiermark 8121",
    "addr:housenumber":"301",
    "addr:postcode":"8121",
    "iso:country":"AT",
    "sg:address":"Grazer Str 301",
    "sg:city":"Deutschfeistritz",
    "sg:orig_category":"Tischlereien",
    "sg:phone":"+43 4331 27418440",
    "sg:postcode":"8121",
    "sg:province":"Steiermark",
    "wof:name":"Loidl Tischlerei- u LadenbaugesmbH",
    "wof:placetype":"venue"
},
  "geometry": {"coordinates":[15.3356399536,47.1943855286],"type":"Point"}
}