{
  "type": "Feature",
  "properties": {
    "addr:full":"Grafisweg 21 Ludesch Vorarlberg 6713",
    "addr:housenumber":"21",
    "addr:postcode":"6713",
    "addr:street":"Grafisweg",
    "iso:country":"AT",
    "sg:address":"Grafisweg 21",
    "sg:city":"Ludesch",
    "sg:orig_category":"Trockenausbauer",
    "sg:phone":"+43 5550 21730",
    "sg:postcode":"6713",
    "sg:province":"Vorarlberg",
    "wof:name":"Kaufmann Karl",
    "wof:placetype":"venue"
},
  "geometry": {"coordinates":[9.7708768845,47.1844749451],"type":"Point"}
}