{
  "type": "Feature",
  "properties": {
    "addr:full":"Nr 50 Loich Nieder\u00f6sterreich 3211",
    "addr:postcode":"3211",
    "addr:street":"Nr;Loich",
    "iso:country":"AT",
    "sg:address":"Nr 50",
    "sg:city":"Loich",
    "sg:orig_category":"Feuerwehren",
    "sg:phone":"+43 2722 8222",
    "sg:postcode":"3211",
    "sg:province":"Nieder\u00f6sterreich",
    "wof:name":"Freiwillige Feuerwehr Loich",
    "wof:placetype":"venue"
},
  "geometry": {"coordinates":[15.4015102386,47.9959754944],"type":"Point"}
}