{
  "type": "Feature",
  "properties": {
    "addr:full":"Dorfstr 11 Fieberbrunn Tirol 6391",
    "addr:housenumber":"11",
    "addr:postcode":"6391",
    "addr:street":"Dorfstr;Tirol",
    "iso:country":"AT",
    "sg:address":"Dorfstr 11",
    "sg:city":"Fieberbrunn",
    "sg:orig_category":"Textilwaren / Einzelhandel",
    "sg:phone":"+43 5354 56654",
    "sg:postcode":"6391",
    "sg:province":"Tirol",
    "wof:name":"M &M Monitzer Moden KEG",
    "wof:placetype":"venue"
},
  "geometry": {"coordinates":[12.543504715,47.4769706726],"type":"Point"}
}