{
  "type": "Feature",
  "properties": {
    "addr:full":"Bader-Moser-Str 26 Micheldorf in Ober\u00f6sterreich Ober\u00f6sterreich 4563",
    "addr:housenumber":"26",
    "addr:postcode":"4563",
    "addr:street":"Bader-Moser-Str",
    "iso:country":"AT",
    "sg:address":"Bader-Moser-Str 26",
    "sg:city":"Micheldorf in Ober\u00f6sterreich",
    "sg:orig_category":"Lichtwerbung",
    "sg:phone":"+43 7582 625440",
    "sg:postcode":"4563",
    "sg:province":"Ober\u00f6sterreich",
    "sg:website":"lichtwerbung.at",
    "wof:name":"Stockinger Adolf Ing GesmbH",
    "wof:placetype":"venue"
},
  "geometry": {"coordinates":[14.1305761337,47.8753471375],"type":"Point"}
}