{
  "type": "Feature",
  "properties": {
    "addr:full":"Werksgel\u00e4nder 32 5503",
    "addr:housenumber":"32",
    "addr:postcode":"5503",
    "addr:street":"Werksgelaender",
    "iso:country":"AT",
    "sg:address":"Werksgel\u00e4nder 32",
    "sg:classifiers":[
        {
            "category":"Professional",
            "subcategory":"Art Services",
            "type":"Services"
        }
    ],
    "sg:phone":"+43 6462 32632",
    "sg:postcode":"5503",
    "sg:tags":[
        "homepage",
        "designing"
    ],
    "sg:website":"ihr-internetauftritt.at",
    "wof:name":"Erwin J. Huber Webtrade",
    "wof:placetype":"venue"
},
  "geometry": {"coordinates":[107.0046386719,27.0754508972],"type":"Point"}
}