{
  "type": "Feature",
  "properties": {
    "addr:full":"Gettsdorf 64 Ziersdorf Nieder\u00f6sterreich 3710",
    "addr:housenumber":"64",
    "addr:postcode":"3710",
    "addr:street":"Gettsdorf",
    "iso:country":"AT",
    "sg:address":"Gettsdorf 64",
    "sg:city":"Ziersdorf",
    "sg:classifiers":[
        {
            "category":"Arena",
            "subcategory":"Horse Racetrack",
            "type":"Entertainment"
        }
    ],
    "sg:phone":"+43 2956 22550",
    "sg:postcode":"3710",
    "sg:province":"Nieder\u00f6sterreich",
    "sg:tags":[
        "fodder"
    ],
    "wof:name":"Guggenberger-M\u00fchle Ges.m.b.H.",
    "wof:placetype":"venue"
},
  "geometry": {"coordinates":[15.9166603088,48.5535621643],"type":"Point"}
}