{
  "type": "Feature",
  "properties": {
    "addr:full":"null Grenze Nickelsdorf Burgenland 2425",
    "addr:postcode":"2425",
    "iso:country":"AT",
    "sg:address":"null Grenze",
    "sg:city":"Nickelsdorf",
    "sg:orig_category":"Speditionen",
    "sg:phone":"+43 4321 4631620",
    "sg:postcode":"2425",
    "sg:province":"Burgenland",
    "wof:name":"VERAG Spedition AG",
    "wof:placetype":"venue"
},
  "geometry": {"coordinates":[17.0690803528,47.9404525757],"type":"Point"}
}