{
  "type": "Feature",
  "properties": {
    "addr:full":"Hauptstr 49 Oetz Tirol 6433",
    "addr:housenumber":"49",
    "addr:postcode":"6433",
    "addr:street":"Hauptstr;Tirol",
    "iso:country":"AT",
    "sg:address":"Hauptstr 49",
    "sg:city":"Oetz",
    "sg:orig_category":"Tabaktrafiken",
    "sg:phone":"+43 5252 6028",
    "sg:postcode":"6433",
    "sg:province":"Tirol",
    "wof:name":"Haid Josef",
    "wof:placetype":"venue"
},
  "geometry": {"coordinates":[10.8969783783,47.2029037476],"type":"Point"}
}