{
  "type": "Feature",
  "properties": {
    "iso:country":"AT",
    "sg:address":"Dr.-Karl-Renner-G 5",
    "sg:city":"Weiz",
    "sg:orig_category":"Spirituosen / Erzeugung U Gro\u00c3\u0178handel",
    "sg:phone":"+43 4331 7224750",
    "sg:postcode":"8160",
    "sg:province":"Steiermark",
    "wof:name":"Haas Adolf KG",
    "wof:placetype":"venue"
},
  "geometry": {"coordinates":[15.6234903336,47.2174682617],"type":"Point"}
}