{
  "type": "Feature",
  "properties": {
    "addr:full":"Linzer Str 13 Gallneukirchen Ober\u00f6sterreich 4210",
    "addr:housenumber":"13",
    "addr:postcode":"4210",
    "addr:street":"Linzer Str;Oberoesterreich",
    "iso:country":"AT",
    "sg:address":"Linzer Str 13",
    "sg:city":"Gallneukirchen",
    "sg:orig_category":"Tankstellen",
    "sg:phone":"+43 4372 3562270",
    "sg:postcode":"4210",
    "sg:province":"Ober\u00f6sterreich",
    "wof:name":"BP Austria Marketing GmbH",
    "wof:placetype":"venue"
},
  "geometry": {"coordinates":[14.412528038,48.3506202698],"type":"Point"}
}