{
  "type": "Feature",
  "properties": {
    "addr:full":"Grottenhofstr 94 Neuhart Steiermark 8053",
    "addr:housenumber":"94",
    "addr:postcode":"8053",
    "addr:street":"Grottenhofstr",
    "iso:country":"AT",
    "sg:address":"Grottenhofstr 94",
    "sg:city":"Neuhart",
    "sg:orig_category":"Lebensmittel / Einzelhandel",
    "sg:phone":"+43 316 281694",
    "sg:postcode":"8053",
    "sg:province":"Steiermark",
    "wof:name":"Billa AG",
    "wof:placetype":"venue"
},
  "geometry": {"coordinates":[15.3924016953,47.0465240479],"type":"Point"}
}