{
  "type": "Feature",
  "properties": {
    "addr:full":"Dorfstrasse  1",
    "addr:housenumber":"1",
    "addr:street":"Dorfstrasse",
    "iso:country":"AT",
    "sg:address":"Dorfstrasse ",
    "sg:classifiers":[
        {
            "category":"Travel",
            "subcategory":"Travel Agent",
            "type":"Entertainment"
        }
    ],
    "sg:postcode":"1",
    "wof:name":"Best Western Hotel Ammerhauser",
    "wof:placetype":"venue"
},
  "geometry": {"coordinates":[13.0129919052,47.8789253235],"type":"Point"}
}