{
  "type": "Feature",
  "properties": {
    "iso:country":"AT",
    "sg:address":"Werner v Siemens-Str 21",
    "sg:city":"Steyr",
    "sg:orig_category":"Mauertrockenlegungen",
    "sg:phone":"+43 7252 31066",
    "sg:postcode":"4400",
    "sg:province":"Ober\u00f6sterreich",
    "wof:name":"Gs\u00f6llpointner Peter - Abtrocknung v feuchten Mauern",
    "wof:placetype":"venue"
},
  "geometry": {"coordinates":[14.4193296432,48.0391807556],"type":"Point"}
}