{
  "type": "Feature",
  "properties": {
    "iso:country":"AT",
    "sg:address":"Lawieser Str 37a",
    "sg:city":"Tullnerbach",
    "sg:orig_category":"Architekten",
    "sg:phone":"+43 2233 540850",
    "sg:postcode":"3013",
    "sg:province":"Nieder\u00f6sterreich",
    "wof:name":"Zuna-Kratky Dieter Mag arch",
    "wof:placetype":"venue"
},
  "geometry": {"coordinates":[16.0918521881,48.1901016235],"type":"Point"}
}