{
  "type": "Feature",
  "properties": {
    "iso:country":"AT",
    "sg:address":"Pichlwang 44",
    "sg:city":"St. Marien",
    "sg:orig_category":"Schlossereien",
    "sg:phone":"+43 7227 4022",
    "sg:postcode":"4502",
    "sg:province":"Ober\u00f6sterreich",
    "wof:name":"Novak Stefan",
    "wof:placetype":"venue"
},
  "geometry": {"coordinates":[14.2565040588,48.1270217896],"type":"Point"}
}