{
  "type": "Feature",
  "properties": {
    "iso:country":"AT",
    "sg:address":"Kehlbach 61",
    "sg:city":"Saalfelden am Steinernen Meer",
    "sg:orig_category":"Installationsunternehmen",
    "sg:phone":"+43 4365 82705500",
    "sg:postcode":"5760",
    "sg:province":"Salzburg",
    "wof:name":"Miesl Johannes Haustechnik GmbH",
    "wof:placetype":"venue"
},
  "geometry": {"coordinates":[12.7906999588,47.420589447],"type":"Point"}
}