{
  "type": "Feature",
  "properties": {
    "addr:full":"Heiligwasserwiese 8 Innsbruck-Igls Tirol 6080",
    "addr:housenumber":"8",
    "addr:postcode":"6080",
    "addr:street":"Heiligwasserwiese",
    "iso:country":"AT",
    "sg:address":"Heiligwasserwiese 8",
    "sg:city":"Innsbruck-Igls",
    "sg:orig_category":"Physiotherapie",
    "sg:phone":"+43 512 3785100",
    "sg:postcode":"6080",
    "sg:province":"Tirol",
    "wof:name":"Physiotherapeutisches Zentrum Igls - Hubert Burtscher",
    "wof:placetype":"venue"
},
  "geometry": {"coordinates":[11.4049882889,47.2309532166],"type":"Point"}
}