{
  "type": "Feature",
  "properties": {
    "addr:full":"Quelleng 3/10 Knittelfeld Steiermark 8720",
    "addr:housenumber":"3 / 10",
    "addr:postcode":"8720",
    "addr:street":"Quelleng",
    "iso:country":"AT",
    "sg:address":"Quelleng 3/10",
    "sg:city":"Knittelfeld",
    "sg:classifiers":[
        {
            "category":"Taxi",
            "type":"Transportation"
        }
    ],
    "sg:phone":"+43 3512 44400",
    "sg:postcode":"8720",
    "sg:province":"Steiermark",
    "sg:tags":[
        "personentransporte",
        "u"
    ],
    "wof:name":"Kopenetz Karl-Blasius Ing",
    "wof:placetype":"venue"
},
  "geometry": {"coordinates":[14.8326349258,47.215171814],"type":"Point"}
}