{
  "type": "Feature",
  "properties": {
    "addr:full":"Hietzinger Hauptstr 46 Wien Wien 1130",
    "addr:housenumber":"46",
    "addr:postcode":"1130",
    "addr:street":"Hietzinger Hauptstr",
    "iso:country":"AT",
    "sg:address":"Hietzinger Hauptstr 46",
    "sg:city":"Wien",
    "sg:orig_category":"Papier- U Schreibwaren / Einzelhandel",
    "sg:phone":"+43 1 8773572",
    "sg:postcode":"1130",
    "sg:province":"Wien",
    "wof:name":"Pfleger Elisabeth",
    "wof:placetype":"venue"
},
  "geometry": {"coordinates":[16.288482666,48.1873130798],"type":"Point"}
}