{
  "type": "Feature",
  "properties": {
    "addr:full":"Nr 282 Litzelsdorf Burgenland 7532",
    "addr:postcode":"7532",
    "addr:street":"Nr",
    "iso:country":"AT",
    "sg:address":"Nr 282",
    "sg:city":"Litzelsdorf",
    "sg:orig_category":"Landwirtschaftliche Produkte",
    "sg:phone":"+43 3358 22540",
    "sg:postcode":"7532",
    "sg:province":"Burgenland",
    "wof:name":"Fassl GmbH & Co KG",
    "wof:placetype":"venue"
},
  "geometry": {"coordinates":[16.1620330811,47.2079315186],"type":"Point"}
}