{
  "type": "Feature",
  "properties": {
    "addr:full":"Stiftg 4 Wien Wien 1070",
    "addr:housenumber":"4",
    "addr:postcode":"1070",
    "addr:street":"Stiftg",
    "iso:country":"AT",
    "sg:address":"Stiftg 4",
    "sg:city":"Wien",
    "sg:orig_category":"Immobilienverwaltungen",
    "sg:phone":"+43 1 5240675",
    "sg:postcode":"1070",
    "sg:province":"Wien",
    "wof:name":"Fischer Ingeborg",
    "wof:placetype":"venue"
},
  "geometry": {"coordinates":[16.3546848297,48.2025718689],"type":"Point"}
}