{
  "type": "Feature",
  "properties": {
    "addr:full":"Glaser Str 28 Aigen Salzburg 5026",
    "addr:postcode":"5026",
    "addr:street":"Str 28;Salzburg",
    "iso:country":"AT",
    "sg:address":"Glaser Str 28",
    "sg:city":"Aigen",
    "sg:orig_category":"Brunnen U Brunnenbau",
    "sg:phone":"+43 4366 2621049",
    "sg:postcode":"5026",
    "sg:province":"Salzburg",
    "sg:website":"schrofner-installationen.at",
    "wof:name":"Schrofner Heinrich",
    "wof:placetype":"venue"
},
  "geometry": {"coordinates":[13.0863208771,47.7778701782],"type":"Point"}
}