{
  "type": "Feature",
  "properties": {
    "iso:country":"AT",
    "sg:address":"Nr 18",
    "sg:city":"Turnau",
    "sg:orig_category":"Pensionen / Privatzimmer",
    "sg:phone":"+43 3863 2202",
    "sg:postcode":"8625",
    "sg:province":"Steiermark",
    "wof:name":"J\u00f6rgbauer-Lindenhof",
    "wof:placetype":"venue"
},
  "geometry": {"coordinates":[-0.1163489968,45.6774291992],"type":"Point"}
}