{
  "type": "Feature",
  "properties": {
    "addr:full":"Goldschlagstr 50 Wien Wien 1150",
    "addr:housenumber":"50",
    "addr:postcode":"1150",
    "addr:street":"Goldschlagstr",
    "iso:country":"AT",
    "sg:address":"Goldschlagstr 50",
    "sg:city":"Wien",
    "sg:orig_category":"Immobilienmakler",
    "sg:phone":"+43 676 7254949",
    "sg:postcode":"1150",
    "sg:province":"Wien",
    "wof:name":"Fundamenta Immobilien GmbH",
    "wof:placetype":"venue"
},
  "geometry": {"coordinates":[16.3284435272,48.1970863342],"type":"Point"}
}