{
  "type": "Feature",
  "properties": {
    "addr:full":"Mitterweg 18 Wals Salzburg 5071",
    "addr:housenumber":"18",
    "addr:postcode":"5071",
    "addr:street":"Mitterweg;Salzburg",
    "iso:country":"AT",
    "sg:address":"Mitterweg 18",
    "sg:city":"Wals",
    "sg:orig_category":"Hafnereien",
    "sg:phone":"+43 4366 2852085",
    "sg:postcode":"5071",
    "sg:province":"Salzburg",
    "wof:name":"Reischl Rupert",
    "wof:placetype":"venue"
},
  "geometry": {"coordinates":[12.980881691,47.7797050476],"type":"Point"}
}