{
  "type": "Feature",
  "properties": {
    "iso:country":"AT",
    "sg:address":"Ritzenseestr 35",
    "sg:city":"Saalfelden am Steinernen Meer",
    "sg:classifiers":[
        {
            "category":"Personal",
            "subcategory":"Sauna",
            "type":"Services"
        }
    ],
    "sg:phone":"+43 4365 82721280",
    "sg:postcode":"5760",
    "sg:province":"Salzburg",
    "sg:tags":[
        "u",
        "dampfbad"
    ],
    "wof:name":"Wagner Rupert",
    "wof:placetype":"venue"
},
  "geometry": {"coordinates":[12.8472290039,47.4207077026],"type":"Point"}
}