{
  "type": "Feature",
  "properties": {
    "addr:full":"Iglaseegasse 72 Wien Wien 1190",
    "addr:housenumber":"72",
    "addr:postcode":"1190",
    "addr:street":"Iglaseegasse",
    "iso:country":"AT",
    "sg:address":"Iglaseegasse 72",
    "sg:city":"Wien",
    "sg:orig_category":"Internet, Alle Internetdienstleistungen",
    "sg:phone":"+43 4313 205758",
    "sg:postcode":"1190",
    "sg:province":"Wien",
    "sg:website":"http://www.world-wide-shop.at/domain/",
    "wof:name":"world-wide-shop.at",
    "wof:placetype":"venue"
},
  "geometry": {"coordinates":[16.3406162262,48.2478561401],"type":"Point"}
}