{
  "type": "Feature",
  "properties": {
    "iso:country":"AT",
    "sg:address":"Rechbauerstr 6",
    "sg:city":"Graz",
    "sg:orig_category":"Osteopathie",
    "sg:phone":"+43 316 830163",
    "sg:postcode":"8010",
    "sg:province":"Steiermark",
    "wof:name":"F\u00fcrpa\u00df Elke Dipl-PT",
    "wof:placetype":"venue"
},
  "geometry": {"coordinates":[15.4492788315,47.069896698],"type":"Point"}
}