{
  "type": "Feature",
  "properties": {
    "addr:full":"Gschwandt 340 Gschwandt Ober\u00f6sterreich 4816",
    "addr:housenumber":"340",
    "addr:postcode":"4816",
    "addr:street":"Gschwandt",
    "iso:country":"AT",
    "sg:address":"Gschwandt 340",
    "sg:city":"Gschwandt",
    "sg:classifiers":[
        {
            "category":"Home & Garden",
            "subcategory":"Home Furnishings",
            "type":"Retail Goods"
        }
    ],
    "sg:phone":"+43 7612626050",
    "sg:postcode":"4816",
    "sg:province":"Ober\u00f6sterreich",
    "sg:tags":[
        "decorative",
        "lighting",
        "system"
    ],
    "sg:website":"lichtland.at",
    "wof:name":"Elektro Rittenschober OHG",
    "wof:placetype":"venue"
},
  "geometry": {"coordinates":[13.8428173065,47.9331359863],"type":"Point"}
}