{
  "type": "Feature",
  "properties": {
    "addr:full":"Sch\u00f6nbrunng 65 Graz Steiermark 8010",
    "addr:housenumber":"65",
    "addr:postcode":"8010",
    "addr:street":"Schoenbrunng",
    "iso:country":"AT",
    "sg:address":"Sch\u00f6nbrunng 65",
    "sg:city":"Graz",
    "sg:orig_category":"Psychotherapie",
    "sg:phone":"+43 316 382827",
    "sg:postcode":"8010",
    "sg:province":"Steiermark",
    "wof:name":"Micolini Renata-Nives",
    "wof:placetype":"venue"
},
  "geometry": {"coordinates":[15.449511528,47.0926971436],"type":"Point"}
}