{
  "type": "Feature",
  "properties": {
    "addr:full":"Wiener Str 281 G\u00f6sting Steiermark 8051",
    "addr:housenumber":"281",
    "addr:postcode":"8051",
    "addr:street":"Goesting Steiermark",
    "iso:country":"AT",
    "sg:address":"Wiener Str 281",
    "sg:city":"G\u00f6sting",
    "sg:classifiers":[
        {
            "category":"Taxi",
            "type":"Transportation"
        }
    ],
    "sg:phone":"+43 664 3361769",
    "sg:postcode":"8051",
    "sg:province":"Steiermark",
    "sg:tags":[
        "personentransporte",
        "u"
    ],
    "wof:name":"Pusch Michael OEG",
    "wof:placetype":"venue"
},
  "geometry": {"coordinates":[15.4041252136,47.0962486267],"type":"Point"}
}