{
  "type": "Feature",
  "properties": {
    "iso:country":"AT",
    "sg:address":"Karl-Heinrich-Waggerl-Str 5",
    "sg:city":"Bad Gastein",
    "sg:classifiers":[
        {
            "category":"Travel",
            "subcategory":"Hotels & Motels",
            "type":"Entertainment"
        }
    ],
    "sg:phone":"+43 4364 342161",
    "sg:postcode":"5640",
    "sg:province":"Salzburg",
    "wof:name":"Hotel Regina",
    "wof:placetype":"venue"
},
  "geometry": {"coordinates":[13.1340408325,47.1162605286],"type":"Point"}
}