{
  "type": "Feature",
  "properties": {
    "addr:full":"Alm 12 Faistenau Salzburg 5324",
    "addr:housenumber":"12",
    "addr:postcode":"5324",
    "addr:street":"Alm;Salzburg",
    "iso:country":"AT",
    "sg:address":"Alm 12",
    "sg:city":"Faistenau",
    "sg:orig_category":"Appartements / Ferienwohnungen",
    "sg:phone":"+43 6228 2298",
    "sg:postcode":"5324",
    "sg:province":"Salzburg",
    "wof:name":"Almgut",
    "wof:placetype":"venue"
},
  "geometry": {"coordinates":[13.2155818939,47.762260437],"type":"Point"}
}