{
  "type": "Feature",
  "properties": {
    "addr:full":"Schmidgunstg 75 Wien Wien 1110",
    "addr:housenumber":"75",
    "addr:postcode":"1110",
    "addr:street":"Schmidgunstg",
    "iso:country":"AT",
    "sg:address":"Schmidgunstg 75",
    "sg:city":"Wien",
    "sg:orig_category":"Blumeneinzelhandel",
    "sg:phone":"+43 1 7698416",
    "sg:postcode":"1110",
    "sg:province":"Wien",
    "wof:name":"Brigitte Inh Weber Brigitte",
    "wof:placetype":"venue"
},
  "geometry": {"coordinates":[16.4695644379,48.1605377197],"type":"Point"}
}