{
  "type": "Feature",
  "properties": {
    "addr:full":"Tambergau 1 Hinterstoder Ober\u00f6sterreich 4573",
    "addr:housenumber":"1",
    "addr:postcode":"4573",
    "addr:street":"Tambergau",
    "iso:country":"AT",
    "sg:address":"Tambergau 1",
    "sg:city":"Hinterstoder",
    "sg:orig_category":"Bildhauer",
    "sg:phone":"+43 7564 20141",
    "sg:postcode":"4573",
    "sg:province":"Ober\u00f6sterreich",
    "wof:name":"Blaickner Theo Mag",
    "wof:placetype":"venue"
},
  "geometry": {"coordinates":[14.1690826416,47.7146873474],"type":"Point"}
}