{
  "type": "Feature",
  "properties": {
    "addr:full":"Europaring F10102, campus 21 Brunn am Gebirge Nieder\u00f6sterreich 2345",
    "addr:housenumber":"21",
    "addr:postcode":"2345",
    "addr:street":"Europaring",
    "iso:country":"AT",
    "sg:address":"Europaring F10102, campus 21",
    "sg:city":"Brunn am Gebirge",
    "sg:orig_category":"Pump Repair Services",
    "sg:phone":"+43 1 8667022169",
    "sg:postcode":"2345",
    "sg:province":"Nieder\u00f6sterreich",
    "wof:name":"A.RADA GmbH - ALLWEILER Pumpservice",
    "wof:placetype":"venue"
},
  "geometry": {"coordinates":[16.2839355469,48.107170105],"type":"Point"}
}