{
  "type": "Feature",
  "properties": {
    "iso:country":"AT",
    "sg:address":"Untere Kellerg 58",
    "sg:city":"Deutsch Sch\u00fctzen",
    "sg:orig_category":"Pensionen / Privatzimmer",
    "sg:phone":"+43 4333 652240",
    "sg:postcode":"7474",
    "sg:province":"Burgenland",
    "wof:name":"Hetfleisch Erika",
    "wof:placetype":"venue"
},
  "geometry": {"coordinates":[16.4103622437,47.1919403076],"type":"Point"}
}