{
  "type": "Feature",
  "properties": {
    "iso:country":"AT",
    "sg:address":"Reichenauer Str 40b",
    "sg:city":"Gallneukirchen",
    "sg:orig_category":"Massagen",
    "sg:phone":"+43 7235 63852",
    "sg:postcode":"4210",
    "sg:province":"Ober\u00f6sterreich",
    "wof:name":"Massageinstitut Pendlmayr",
    "wof:placetype":"venue"
},
  "geometry": {"coordinates":[14.4113464355,48.357749939],"type":"Point"}
}