{
  "type": "Feature",
  "properties": {
    "iso:country":"AT",
    "sg:address":"Eduard-Kittenberger-Gasse 56",
    "sg:city":"Wien",
    "sg:classifiers":[
        {
            "category":"Home & Garden",
            "subcategory":"Carpets & Floor Coverings",
            "type":"Retail Goods"
        }
    ],
    "sg:phone":"+43 1 8693171",
    "sg:postcode":"1230",
    "sg:province":"Wien",
    "sg:tags":[
        "screed",
        "floating"
    ],
    "wof:name":"Erich Sch\u00fctz GesmbH",
    "wof:placetype":"venue"
},
  "geometry": {"coordinates":[16.3035163879,48.1381149292],"type":"Point"}
}