{
  "type": "Feature",
  "properties": {
    "iso:country":"AT",
    "sg:address":"Hauptpl 12",
    "sg:city":"Eggenburg",
    "sg:orig_category":"Tischlereien",
    "sg:phone":"+43 2984 3223",
    "sg:postcode":"3730",
    "sg:province":"Nieder\u00f6sterreich",
    "wof:name":"Voglsinger Franz",
    "wof:placetype":"venue"
},
  "geometry": {"coordinates":[15.8158035278,48.6430969238],"type":"Point"}
}