{
  "type": "Feature",
  "properties": {
    "addr:full":"Breitenfurter Str 281 Wien Wien 1230",
    "addr:housenumber":"281",
    "addr:postcode":"1230",
    "addr:street":"Str",
    "iso:country":"AT",
    "sg:address":"Breitenfurter Str 281",
    "sg:city":"Wien",
    "sg:orig_category":"Maler, Anstreicher U Lackierer",
    "sg:phone":"+43 4318 695169",
    "sg:postcode":"1230",
    "sg:province":"Wien",
    "wof:name":"Schlechta & Fiala GmbH",
    "wof:placetype":"venue"
},
  "geometry": {"coordinates":[16.2973003387,48.1471672058],"type":"Point"}
}