{
  "type": "Feature",
  "properties": {
    "iso:country":"AT",
    "sg:address":"Villacher Strasse 17",
    "sg:city":"Klagenfurt",
    "sg:classifiers":[
        {
            "category":"Building & Trades",
            "subcategory":"Plumbing",
            "type":"Services"
        }
    ],
    "sg:phone":"+43 463 503121",
    "sg:postcode":"9020",
    "sg:province":"K\u00e4rnten",
    "sg:tags":[
        "tub",
        "bath"
    ],
    "wof:name":"ECCONA Rohrtechnik und Montage GmbH",
    "wof:placetype":"venue"
},
  "geometry": {"coordinates":[14.3013715744,46.623210907],"type":"Point"}
}