{
  "type": "Feature",
  "properties": {
    "addr:full":"Matzleinsdorfer Pl 2 Wien Wien 1050",
    "addr:housenumber":"2",
    "addr:postcode":"1050",
    "addr:street":"Matzleinsdorfer Pl",
    "iso:country":"AT",
    "sg:address":"Matzleinsdorfer Pl 2",
    "sg:city":"Wien",
    "sg:orig_category":"Fassaden",
    "sg:phone":"+43 4315 489160",
    "sg:postcode":"1050",
    "sg:province":"Wien",
    "sg:website":"stuck-krumboeck.at",
    "wof:name":"Krumb\u00f6ck E Stuck & Fassadenornamente Erzeugungs- u VertriebsgesmbH",
    "wof:placetype":"venue"
},
  "geometry": {"coordinates":[16.3583774567,48.1812744141],"type":"Point"}
}