{
  "type": "Feature",
  "properties": {
    "iso:country":"AT",
    "sg:address":"Landgutg 26",
    "sg:city":"Wien",
    "sg:orig_category":"\u00c3\u201erzte / F Allgemeinmedizin",
    "sg:phone":"+43 1 6041739",
    "sg:postcode":"1100",
    "sg:province":"Wien",
    "wof:name":"El-Azzeh Usama Dr",
    "wof:placetype":"venue"
},
  "geometry": {"coordinates":[16.3740444183,48.1813583374],"type":"Point"}
}