{
  "type": "Feature",
  "properties": {
    "addr:full":"Starchantg 12a Wien Wien 1160",
    "addr:housenumber":"12a",
    "addr:postcode":"1160",
    "addr:street":"Starchantg",
    "iso:country":"AT",
    "sg:address":"Starchantg 12a",
    "sg:city":"Wien",
    "sg:orig_category":"Transportunternehmen",
    "sg:phone":"+43 1 9148208",
    "sg:postcode":"1160",
    "sg:province":"Wien",
    "wof:name":"B\u00f6hm Leonhard TransportgesmbH & Co KG",
    "wof:placetype":"venue"
},
  "geometry": {"coordinates":[16.2869663239,48.2165679932],"type":"Point"}
}