{
  "type": "Feature",
  "properties": {
    "addr:full":"Wiesingerstr 20 Bad Ischl Ober\u00f6sterreich 4820",
    "addr:housenumber":"20",
    "addr:postcode":"4820",
    "addr:street":"Wiesingerstr",
    "iso:country":"AT",
    "sg:address":"Wiesingerstr 20",
    "sg:city":"Bad Ischl",
    "sg:orig_category":"Versicherungsunternehmen",
    "sg:phone":"+43 6132 25265",
    "sg:postcode":"4820",
    "sg:province":"Ober\u00f6sterreich",
    "wof:name":"Victoria Volksbanken Versicherungs-AG",
    "wof:placetype":"venue"
},
  "geometry": {"coordinates":[13.6178283691,47.7122116089],"type":"Point"}
}