{
  "type": "Feature",
  "properties": {
    "addr:full":"Hintstein 35 Gro\u00dframing Ober\u00f6sterreich 4463",
    "addr:housenumber":"35",
    "addr:postcode":"4463",
    "addr:street":"Hintstein",
    "iso:country":"AT",
    "sg:address":"Hintstein 35",
    "sg:city":"Gro\u00dframing",
    "sg:orig_category":"Bauunternehmen",
    "sg:phone":"+43 7254 8290",
    "sg:postcode":"4463",
    "sg:province":"Ober\u00f6sterreich",
    "wof:name":"Haider Gebr Bauunternehmung GesmbH & Co KG",
    "wof:placetype":"venue"
},
  "geometry": {"coordinates":[14.5909013748,47.881439209],"type":"Point"}
}