{
  "type": "Feature",
  "properties": {
    "addr:full":"Schallmooser Hauptstrasse 85a Salzburg Salzburg 5020",
    "addr:housenumber":"85a",
    "addr:postcode":"5020",
    "addr:street":"Schallmooser Hauptstrasse;Salzburg",
    "iso:country":"AT",
    "sg:address":"Schallmooser Hauptstrasse 85a",
    "sg:city":"Salzburg",
    "sg:classifiers":[
        {
            "category":"Professional",
            "subcategory":"Advertising",
            "type":"Services"
        }
    ],
    "sg:phone":"+43 662 643126",
    "sg:postcode":"5020",
    "sg:province":"Salzburg",
    "sg:tags":[
        "marketing",
        "direct"
    ],
    "sg:website":"adwerba.at",
    "wof:name":"Adwerba Gesellschaft f\u00fcr Verkaufsf\u00f6rderung und Werbung Ges.m.b.H.",
    "wof:placetype":"venue"
},
  "geometry": {"coordinates":[13.0608329773,47.8075942993],"type":"Point"}
}