{
  "type": "Feature",
  "properties": {
    "addr:full":"Virgener Str 13 Matrei in Osttirol Tirol 9971",
    "addr:postcode":"9971",
    "addr:street":"Str 13;Tirol",
    "iso:country":"AT",
    "sg:address":"Virgener Str 13",
    "sg:city":"Matrei in Osttirol",
    "sg:orig_category":"Installationsunternehmen",
    "sg:phone":"+43 4875 66010",
    "sg:postcode":"9971",
    "sg:province":"Tirol",
    "wof:name":"Egger Gudrun",
    "wof:placetype":"venue"
},
  "geometry": {"coordinates":[12.5362005234,46.9992980957],"type":"Point"}
}