{
  "type": "Feature",
  "properties": {
    "iso:country":"AT",
    "sg:address":"Harl 42",
    "sg:city":"Puch",
    "sg:orig_category":"Marketingberatung",
    "sg:phone":"+43 3177 40055",
    "sg:postcode":"8182",
    "sg:province":"Steiermark",
    "wof:name":"Frey KEG",
    "wof:placetype":"venue"
},
  "geometry": {"coordinates":[15.7093105316,47.243473053],"type":"Point"}
}