{
  "type": "Feature",
  "properties": {
    "addr:full":"Veilcheng 7 Breitenfurt Nieder\u00f6sterreich 2384",
    "addr:housenumber":"7",
    "addr:postcode":"2384",
    "addr:street":"Veilcheng",
    "iso:country":"AT",
    "sg:address":"Veilcheng 7",
    "sg:city":"Breitenfurt",
    "sg:orig_category":"Lebensmittel / Erzeugung U Gro\u00c3\u0178handel",
    "sg:phone":"+43 4366 41004437",
    "sg:postcode":"2384",
    "sg:province":"Nieder\u00f6sterreich",
    "wof:name":"Lisner Feinkost GmbH",
    "wof:placetype":"venue"
},
  "geometry": {"coordinates":[16.193605423,48.1392211914],"type":"Point"}
}