{
  "type": "Feature",
  "properties": {
    "addr:full":"Josef-Wolfik-Str 2 Stockerau Nieder\u00f6sterreich 2000",
    "addr:housenumber":"2",
    "addr:postcode":"2000",
    "addr:street":"Josef-Wolfik-Str",
    "iso:country":"AT",
    "sg:address":"Josef-Wolfik-Str 2",
    "sg:city":"Stockerau",
    "sg:orig_category":"Textilreinigung",
    "sg:phone":"+43 2266 68354",
    "sg:postcode":"2000",
    "sg:province":"Nieder\u00f6sterreich",
    "wof:name":"Stadtputzerei",
    "wof:placetype":"venue"
},
  "geometry": {"coordinates":[16.2067737579,48.384803772],"type":"Point"}
}