{
  "type": "Feature",
  "properties": {
    "iso:country":"AT",
    "sg:address":"Lengried 7",
    "sg:city":"Schleedorf",
    "sg:orig_category":"Tischlereien",
    "sg:phone":"+43 6216 6014",
    "sg:postcode":"5205",
    "sg:province":"Salzburg",
    "wof:name":"Altmann Josef",
    "wof:placetype":"venue"
},
  "geometry": {"coordinates":[13.1526231766,47.9531707764],"type":"Point"}
}