{
  "type": "Feature",
  "properties": {
    "addr:full":"Birkenstr 5 Bad Schallerbach Ober\u00f6sterreich 4701",
    "addr:housenumber":"5",
    "addr:postcode":"4701",
    "addr:street":"Birkenstr",
    "iso:country":"AT",
    "sg:address":"Birkenstr 5",
    "sg:city":"Bad Schallerbach",
    "sg:classifiers":[
        {
            "category":"Home & Garden",
            "subcategory":"Building Materials",
            "type":"Retail Goods"
        }
    ],
    "sg:phone":"+43 4372 4948817",
    "sg:postcode":"4701",
    "sg:province":"Ober\u00f6sterreich",
    "sg:tags":[
        "baustoffe",
        "-material",
        "u"
    ],
    "wof:name":"Kreuzmayr Robert Ing",
    "wof:placetype":"venue"
},
  "geometry": {"coordinates":[13.9277629852,48.2273788452],"type":"Point"}
}