{
  "type": "Feature",
  "properties": {
    "addr:full":"Kircheng 9 Siegendorf im Burgenland Burgenland 7011",
    "addr:housenumber":"9",
    "addr:postcode":"7011",
    "addr:street":"Kircheng",
    "iso:country":"AT",
    "sg:address":"Kircheng 9",
    "sg:city":"Siegendorf im Burgenland",
    "sg:orig_category":"Fenster",
    "sg:phone":"+43 2687 48887",
    "sg:postcode":"7011",
    "sg:province":"Burgenland",
    "wof:name":"Korsos Julius",
    "wof:placetype":"venue"
},
  "geometry": {"coordinates":[16.5153503418,47.7649040222],"type":"Point"}
}