{
  "type": "Feature",
  "properties": {
    "addr:full":"Geymannstrasse 5 Gallspach Ober\u00f6sterreich 4713",
    "addr:housenumber":"5",
    "addr:postcode":"4713",
    "addr:street":"Geymannstrasse",
    "iso:country":"AT",
    "sg:address":"Geymannstrasse 5",
    "sg:city":"Gallspach",
    "sg:classifiers":[
        {
            "category":"Home & Garden",
            "subcategory":"Furniture",
            "type":"Retail Goods"
        }
    ],
    "sg:phone":"+43 7248 655550",
    "sg:postcode":"4713",
    "sg:province":"Ober\u00f6sterreich",
    "sg:tags":[
        "bathroom"
    ],
    "wof:name":"Friedrich Breslmayr",
    "wof:placetype":"venue"
},
  "geometry": {"coordinates":[13.8113975525,48.2051544189],"type":"Point"}
}