{
  "type": "Feature",
  "properties": {
    "addr:full":"Handelskai 346 Wien Wien 1020",
    "addr:housenumber":"346",
    "addr:postcode":"1020",
    "addr:street":"Handelskai",
    "iso:country":"AT",
    "sg:address":"Handelskai 346",
    "sg:city":"Wien",
    "sg:orig_category":"Tankstellen",
    "sg:phone":"+43 1 7280051",
    "sg:postcode":"1020",
    "sg:province":"Wien",
    "wof:name":"Shell Austria GmbH",
    "wof:placetype":"venue"
},
  "geometry": {"coordinates":[16.4314079285,48.2061729431],"type":"Point"}
}