{
  "type": "Feature",
  "properties": {
    "iso:country":"AT",
    "sg:address":"Kirchenpl 2",
    "sg:city":"Hafnerbach",
    "sg:orig_category":"Reiseveranstalter",
    "sg:phone":"+43 2749 21470",
    "sg:postcode":"3386",
    "sg:province":"Nieder\u00f6sterreich",
    "wof:name":"Datzinger Franz",
    "wof:placetype":"venue"
},
  "geometry": {"coordinates":[15.4880743027,48.2166900635],"type":"Point"}
}