{
  "type": "Feature",
  "properties": {
    "addr:full":"Oberlaaer Str 91-93 Wien Wien 1100",
    "addr:postcode":"91-93;1100",
    "addr:street":"Str",
    "iso:country":"AT",
    "sg:address":"Oberlaaer Str 91-93",
    "sg:city":"Wien",
    "sg:orig_category":"Farben U Lacke / Einzelhandel, Farben U Lacke / Erzeugung U Gro\u00c3\u0178handel",
    "sg:phone":"+43 1 68851280",
    "sg:postcode":"1100",
    "sg:province":"Wien",
    "sg:website":"www.allcolor.at",
    "wof:name":"all-color F Windisch GesmbH",
    "wof:placetype":"venue"
},
  "geometry": {"coordinates":[16.3968544006,48.138092041],"type":"Point"}
}