{
  "type": "Feature",
  "properties": {
    "addr:full":"Hans Gasser-Pl 1 Villach K\u00e4rnten 9500",
    "addr:housenumber":"1",
    "addr:postcode":"9500",
    "addr:street":"Gasser-Pl;Kaernten",
    "iso:country":"AT",
    "sg:address":"Hans Gasser-Pl 1",
    "sg:city":"Villach",
    "sg:orig_category":"Juweliere, Gold- U Silberschmiede",
    "sg:phone":"+43 4242 216404",
    "sg:postcode":"9500",
    "sg:province":"K\u00e4rnten",
    "wof:name":"Schmuck Victoria - Victoria v Vranjes",
    "wof:placetype":"venue"
},
  "geometry": {"coordinates":[13.8438644409,46.612071991],"type":"Point"}
}