{
  "type": "Feature",
  "properties": {
    "addr:full":"Hauptstrasse 86 Kindberg Steiermark 8650",
    "addr:housenumber":"86",
    "addr:postcode":"8650",
    "addr:street":"Hauptstrasse",
    "iso:country":"AT",
    "sg:address":"Hauptstrasse 86",
    "sg:city":"Kindberg",
    "sg:classifiers":[
        {
            "category":"Home & Garden",
            "subcategory":"Carpets & Floor Coverings",
            "type":"Retail Goods"
        }
    ],
    "sg:phone":"+43 3865 2234",
    "sg:postcode":"8650",
    "sg:province":"Steiermark",
    "sg:tags":[
        "carpeting"
    ],
    "wof:name":"Peter Deschmann",
    "wof:placetype":"venue"
},
  "geometry": {"coordinates":[15.4465351105,47.5040130615],"type":"Point"}
}