{
  "type": "Feature",
  "properties": {
    "addr:full":"Meraner Str 1 Kufstein Tirol 6330",
    "addr:housenumber":"1",
    "addr:postcode":"6330",
    "addr:street":"Str;Tirol",
    "iso:country":"AT",
    "sg:address":"Meraner Str 1",
    "sg:city":"Kufstein",
    "sg:orig_category":"Immobilienmakler",
    "sg:phone":"+43 5372 68660",
    "sg:postcode":"6330",
    "sg:province":"Tirol",
    "wof:name":"Immo-Stein Rudolf Steiner Immobilientreuhand",
    "wof:placetype":"venue"
},
  "geometry": {"coordinates":[12.1751651764,47.5898666382],"type":"Point"}
}