{
  "type": "Feature",
  "properties": {
    "addr:full":"Bahnhofstr 3 Klagenfurt K\u00e4rnten 9020",
    "addr:housenumber":"3",
    "addr:postcode":"9020",
    "addr:street":"Bahnhofstr;Kaernten",
    "iso:country":"AT",
    "sg:address":"Bahnhofstr 3",
    "sg:city":"Klagenfurt",
    "sg:orig_category":"Bankomat-Standorte",
    "sg:phone":"+43 463 5126660",
    "sg:postcode":"9020",
    "sg:province":"K\u00e4rnten",
    "wof:name":"Bankomat d Raiffeisen-Bezirksbank Klagenfurt",
    "wof:placetype":"venue"
},
  "geometry": {"coordinates":[14.3107118607,46.6253662109],"type":"Point"}
}