{
  "type": "Feature",
  "properties": {
    "addr:full":"Adolf-Loos-G 2 Wien Wien 1210",
    "addr:housenumber":"2",
    "addr:postcode":"1210",
    "addr:street":"Adolf-Loos-G",
    "iso:country":"AT",
    "sg:address":"Adolf-Loos-G 2",
    "sg:city":"Wien",
    "sg:orig_category":"Volksschulen",
    "sg:phone":"+43 1 2568727",
    "sg:postcode":"1210",
    "sg:province":"Wien",
    "wof:name":"Schulen d Stadt Wien",
    "wof:placetype":"venue"
},
  "geometry": {"coordinates":[16.453130722,48.2693405151],"type":"Point"}
}