{
  "type": "Feature",
  "properties": {
    "addr:full":"Hauptpl 4 Illmitz Burgenland 7142",
    "addr:housenumber":"4",
    "addr:postcode":"7142",
    "addr:street":"Hauptpl",
    "iso:country":"AT",
    "sg:address":"Hauptpl 4",
    "sg:city":"Illmitz",
    "sg:orig_category":"Banken U Sparkassen",
    "sg:phone":"+43 4321 7523270",
    "sg:postcode":"7142",
    "sg:province":"Burgenland",
    "wof:name":"Raiffeisenbank Illmitz regGenmbH",
    "wof:placetype":"venue"
},
  "geometry": {"coordinates":[16.7995262146,47.7615356445],"type":"Point"}
}