{
  "type": "Feature",
  "properties": {
    "addr:full":"Bahnhofstr 5/16 Klagenfurt K\u00e4rnten 9020",
    "addr:housenumber":"5 / 16",
    "addr:postcode":"9020",
    "addr:street":"Bahnhofstr;Kaernten",
    "iso:country":"AT",
    "sg:address":"Bahnhofstr 5/16",
    "sg:city":"Klagenfurt",
    "sg:orig_category":"Friseure U Frisiersalons",
    "sg:phone":"+43 463 56586",
    "sg:postcode":"9020",
    "sg:province":"K\u00e4rnten",
    "wof:name":"Coiffeur Barbara",
    "wof:placetype":"venue"
},
  "geometry": {"coordinates":[14.3107481003,46.6251411438],"type":"Point"}
}