{
  "type": "Feature",
  "properties": {
    "addr:full":"Hauptstr 83 Frankenmarkt Ober\u00f6sterreich 4890",
    "addr:housenumber":"83",
    "addr:postcode":"4890",
    "addr:street":"Hauptstr;Oberoesterreich",
    "iso:country":"AT",
    "sg:address":"Hauptstr 83",
    "sg:city":"Frankenmarkt",
    "sg:orig_category":"Polizei U Gendarmerie",
    "sg:phone":"+43 4359 1334165",
    "sg:postcode":"4890",
    "sg:province":"Ober\u00f6sterreich",
    "wof:name":"Gendarmerie",
    "wof:placetype":"venue"
},
  "geometry": {"coordinates":[13.4181909561,47.9852104187],"type":"Point"}
}