{
  "type": "Feature",
  "properties": {
    "addr:full":"Blumenweg 3 Fohnsdorf Steiermark 8753",
    "addr:housenumber":"3",
    "addr:postcode":"8753",
    "addr:street":"Blumenweg",
    "iso:country":"AT",
    "sg:address":"Blumenweg 3",
    "sg:city":"Fohnsdorf",
    "sg:orig_category":"Tischlereien",
    "sg:phone":"+43 4335 732265",
    "sg:postcode":"8753",
    "sg:province":"Steiermark",
    "wof:name":"Resch Walter",
    "wof:placetype":"venue"
},
  "geometry": {"coordinates":[14.6764173508,47.2066307068],"type":"Point"}
}