{
  "type": "Feature",
  "properties": {
    "addr:full":"Nr 3-5 Dobl Steiermark 8143",
    "addr:postcode":"8143",
    "addr:street":"Nr",
    "iso:country":"AT",
    "sg:address":"Nr 3-5",
    "sg:city":"Dobl",
    "sg:orig_category":"Hauptschulen",
    "sg:phone":"+43 3136 52610",
    "sg:postcode":"8143",
    "sg:province":"Steiermark",
    "wof:name":"Hauptschule und Volksschule d Barmherzigen Schwestern",
    "wof:placetype":"venue"
},
  "geometry": {"coordinates":[8.0983495712,48.5770339966],"type":"Point"}
}