{
  "type": "Feature",
  "properties": {
    "iso:country":"AT",
    "sg:address":"Weyerstr 354",
    "sg:city":"Bramberg am Wildkogel",
    "sg:classifiers":[
        {
            "category":"Taxi",
            "type":"Transportation"
        }
    ],
    "sg:phone":"+43 4366 44452415",
    "sg:postcode":"5733",
    "sg:province":"Salzburg",
    "sg:tags":[
        "personentransporte",
        "u"
    ],
    "wof:name":"Taxi Sepp",
    "wof:placetype":"venue"
},
  "geometry": {"coordinates":[12.3337306976,47.2665176392],"type":"Point"}
}