{
  "type": "Feature",
  "properties": {
    "iso:country":"AT",
    "sg:address":"Wollzeile 25/30",
    "sg:city":"Wien",
    "sg:orig_category":"Steuerberatung",
    "sg:phone":"+43 4315 126918",
    "sg:postcode":"1010",
    "sg:province":"Wien",
    "wof:name":"Schodl-Pecina Beatrix Dr",
    "wof:placetype":"venue"
},
  "geometry": {"coordinates":[16.3772506714,48.2082214355],"type":"Point"}
}