{
  "type": "Feature",
  "properties": {
    "addr:full":"Bertha-von-Suttner-G 3 Wiener Neustadt Nieder\u00f6sterreich 2700",
    "addr:housenumber":"3",
    "addr:postcode":"2700",
    "addr:street":"Bertha-Von-Suttner-G",
    "iso:country":"AT",
    "sg:address":"Bertha-von-Suttner-G 3",
    "sg:city":"Wiener Neustadt",
    "sg:orig_category":"Montagen U Montagetechnik",
    "sg:phone":"+43 4326 2284750",
    "sg:postcode":"2700",
    "sg:province":"Nieder\u00f6sterreich",
    "wof:name":"Montage Technik GesmbH",
    "wof:placetype":"venue"
},
  "geometry": {"coordinates":[16.233997345,47.8452377319],"type":"Point"}
}