{
  "type": "Feature",
  "properties": {
    "addr:full":"Haidmannweg 9 Pasching Ober\u00f6sterreich 4061",
    "addr:housenumber":"9",
    "addr:postcode":"4061",
    "addr:street":"Haidmannweg;Oberoesterreich",
    "iso:country":"AT",
    "sg:address":"Haidmannweg 9",
    "sg:city":"Pasching",
    "sg:orig_category":"Cell Cultures",
    "sg:phone":"+43 7229 64865",
    "sg:postcode":"4061",
    "sg:province":"Ober\u00f6sterreich",
    "sg:website":"paa.at",
    "wof:name":"PAA Laboratories Ges.m.b.H.",
    "wof:placetype":"venue"
},
  "geometry": {"coordinates":[14.2328462601,48.2363891602],"type":"Point"}
}