{
  "type": "Feature",
  "properties": {
    "addr:full":"Ratschendorf 62 Deutsch Goritz Steiermark 8483",
    "addr:housenumber":"62",
    "addr:postcode":"8483",
    "addr:street":"Ratschendorf",
    "iso:country":"AT",
    "sg:address":"Ratschendorf 62",
    "sg:city":"Deutsch Goritz",
    "sg:classifiers":[
        {
            "category":"Manufacturing",
            "subcategory":"Metals",
            "type":"Manufacturing & Wholesale Goods"
        }
    ],
    "sg:phone":"+43 4334 7471010",
    "sg:postcode":"8483",
    "sg:province":"Steiermark",
    "sg:tags":[
        "processing"
    ],
    "wof:name":"SAKO-STAHL GMBH",
    "wof:placetype":"venue"
},
  "geometry": {"coordinates":[15.8294000626,46.7518081665],"type":"Point"}
}