{
  "type": "Feature",
  "properties": {
    "addr:full":"Eduard-R\u00f6sch-Str 48 Stockerau Nieder\u00f6sterreich 2000",
    "addr:housenumber":"48",
    "addr:postcode":"2000",
    "addr:street":"Eduard-Roesch-Str",
    "iso:country":"AT",
    "sg:address":"Eduard-R\u00f6sch-Str 48",
    "sg:city":"Stockerau",
    "sg:orig_category":"Apotheken",
    "sg:phone":"+43 2266 66002",
    "sg:postcode":"2000",
    "sg:province":"Nieder\u00f6sterreich",
    "wof:name":"L\u00f6wenapotheke Mag Huschka",
    "wof:placetype":"venue"
},
  "geometry": {"coordinates":[16.2255249023,48.386554718],"type":"Point"}
}