{
  "type": "Feature",
  "properties": {
    "addr:full":"Nr 182 Teufenbach Steiermark 8833",
    "addr:postcode":"8833",
    "addr:street":"Nr 182",
    "iso:country":"AT",
    "sg:address":"Nr 182",
    "sg:city":"Teufenbach",
    "sg:orig_category":"Tonstudios",
    "sg:phone":"+43 3582 866880",
    "sg:postcode":"8833",
    "sg:province":"Steiermark",
    "wof:name":"STALL-RECORDS Tonstudio Betriebs GmbH",
    "wof:placetype":"venue"
},
  "geometry": {"coordinates":[14.3591108322,47.1285476685],"type":"Point"}
}