{
  "type": "Feature",
  "properties": {
    "iso:country":"AT",
    "sg:address":"Theresienfelder G 13",
    "sg:city":"Wiener Neustadt",
    "sg:orig_category":"Friseure U Frisiersalons",
    "sg:phone":"+43 4326 2266100",
    "sg:postcode":"2700",
    "sg:province":"Nieder\u00f6sterreich",
    "wof:name":"Haarstudio Andrea",
    "wof:placetype":"venue"
},
  "geometry": {"coordinates":[16.2393245697,47.8399543762],"type":"Point"}
}