{
  "type": "Feature",
  "properties": {
    "addr:full":"Lorettoweg 18 Thaur Tirol 6065",
    "addr:housenumber":"18",
    "addr:postcode":"6065",
    "addr:street":"Lorettoweg;Tirol",
    "iso:country":"AT",
    "sg:address":"Lorettoweg 18",
    "sg:city":"Thaur",
    "sg:orig_category":"Sportmedizin",
    "sg:phone":"+43 512 5909213",
    "sg:postcode":"6065",
    "sg:province":"Tirol",
    "wof:name":"GM Trainingsberatung",
    "wof:placetype":"venue"
},
  "geometry": {"coordinates":[11.4731035233,47.290473938],"type":"Point"}
}