{
  "type": "Feature",
  "properties": {
    "addr:full":"Neub\u00f6ckweg 22 St. Peter Steiermark 8042",
    "addr:housenumber":"22",
    "addr:postcode":"8042",
    "addr:street":"Neuboeckweg",
    "iso:country":"AT",
    "sg:address":"Neub\u00f6ckweg 22",
    "sg:city":"St. Peter",
    "sg:orig_category":"Internet Studies, Online Studies For Market Research, Online Studies",
    "sg:phone":"+43 316 4734922",
    "sg:postcode":"8042",
    "sg:province":"Steiermark",
    "sg:website":"wsts.org",
    "wof:name":"WSTS GmbH",
    "wof:placetype":"venue"
},
  "geometry": {"coordinates":[15.4871263504,47.051322937],"type":"Point"}
}