{
  "type": "Feature",
  "properties": {
    "addr:full":"Nr 7a Leopoldsdorf im Marchfelde Nieder\u00f6sterreich 2285",
    "addr:housenumber":"7a",
    "addr:postcode":"2285",
    "addr:street":"Nr",
    "iso:country":"AT",
    "sg:address":"Nr 7a",
    "sg:city":"Leopoldsdorf im Marchfelde",
    "sg:orig_category":"Tischlereien",
    "sg:phone":"+43 2216 8273",
    "sg:postcode":"2285",
    "sg:province":"Nieder\u00f6sterreich",
    "wof:name":"Pazelt Josef",
    "wof:placetype":"venue"
},
  "geometry": {"coordinates":[16.688999176,48.2236976624],"type":"Point"}
}