{
  "type": "Feature",
  "properties": {
    "addr:full":"Hauptpl 1 Frohnleiten Steiermark 8130",
    "addr:housenumber":"1",
    "addr:postcode":"8130",
    "addr:street":"Hauptpl",
    "iso:country":"AT",
    "sg:address":"Hauptpl 1",
    "sg:city":"Frohnleiten",
    "sg:orig_category":"Non-Classified Establishments",
    "sg:phone":"+43 3126 24880",
    "sg:postcode":"8130",
    "sg:province":"Steiermark",
    "wof:name":"Pfarramt",
    "wof:placetype":"venue"
},
  "geometry": {"coordinates":[15.3244762421,47.2700004578],"type":"Point"}
}