{
  "type": "Feature",
  "properties": {
    "addr:full":"Nr 70 Eggenburg Nieder\u00f6sterreich 3730",
    "addr:postcode":"3730",
    "addr:street":"Nr;Niederoesterreich",
    "iso:country":"AT",
    "sg:address":"Nr 70",
    "sg:city":"Eggenburg",
    "sg:orig_category":"Edelstahl",
    "sg:phone":"+43 2984 26840",
    "sg:postcode":"3730",
    "sg:province":"Nieder\u00f6sterreich",
    "wof:name":"B\u00f6ck Martina",
    "wof:placetype":"venue"
},
  "geometry": {"coordinates":[15.8164758682,48.64320755],"type":"Point"}
}