{
  "type": "Feature",
  "properties": {
    "addr:full":"Grafendorfstrasse 20 Frohnleiten Steiermark 8130",
    "addr:housenumber":"20",
    "addr:postcode":"8130",
    "addr:street":"Grafendorfstrasse",
    "iso:country":"AT",
    "sg:address":"Grafendorfstrasse 20",
    "sg:city":"Frohnleiten",
    "sg:classifiers":[
        {
            "category":"Manufacturing",
            "subcategory":"Wood Products",
            "type":"Manufacturing & Wholesale Goods"
        }
    ],
    "sg:phone":"+43 3126 2427",
    "sg:postcode":"8130",
    "sg:province":"Steiermark",
    "sg:tags":[
        "gate",
        "made",
        "door"
    ],
    "wof:name":"Tischlerei Dominikus Holzapfel",
    "wof:placetype":"venue"
},
  "geometry": {"coordinates":[15.3297405243,47.2688484192],"type":"Point"}
}