{
  "type": "Feature",
  "properties": {
    "iso:country":"AT",
    "sg:address":"Bahnzeile 9",
    "sg:city":"Mistelbach",
    "sg:orig_category":"Steuerberatung",
    "sg:phone":"+43 4325 7223270",
    "sg:postcode":"2130",
    "sg:province":"Nieder\u00f6sterreich",
    "sg:website":"frei-steuern.at",
    "wof:name":"Frei Wilhelm Dr",
    "wof:placetype":"venue"
},
  "geometry": {"coordinates":[16.5683612823,48.5719490051],"type":"Point"}
}