{
  "type": "Feature",
  "properties": {
    "iso:country":"AT",
    "sg:address":"Engerthstr 92",
    "sg:city":"Wien",
    "sg:orig_category":"Schlossereien",
    "sg:phone":"+43 1 3324397",
    "sg:postcode":"1200",
    "sg:province":"Wien",
    "wof:name":"Eles Heinrich",
    "wof:placetype":"venue"
},
  "geometry": {"coordinates":[16.3854084015,48.2395095825],"type":"Point"}
}