{
  "type": "Feature",
  "properties": {
    "addr:full":"Leonfeldner Strasse 14 Linz Ober\u00f6sterreich 4040",
    "addr:housenumber":"14",
    "addr:postcode":"4040",
    "addr:street":"Leonfeldner Strasse",
    "iso:country":"AT",
    "sg:address":"Leonfeldner Strasse 14",
    "sg:city":"Linz",
    "sg:classifiers":[
        {
            "category":"Farming",
            "subcategory":"Aquatic Farm",
            "type":"Manufacturing & Wholesale Goods"
        }
    ],
    "sg:phone":"+43 732 738084",
    "sg:postcode":"4040",
    "sg:province":"Ober\u00f6sterreich",
    "sg:tags":[
        "bath-robes"
    ],
    "sg:website":"ruckerbauer.com",
    "wof:name":"CAW\u00d6 Frottier - K. + J. Ruckerbauer",
    "wof:placetype":"venue"
},
  "geometry": {"coordinates":[14.2834148407,48.3192329407],"type":"Point"}
}