{
  "type": "Feature",
  "properties": {
    "iso:country":"AT",
    "sg:address":"Fanny-von-Lehnert-Str 1",
    "sg:city":"Salzburg",
    "sg:orig_category":"Suchtberatung / Alkohol, Drogen, Zigaretten",
    "sg:phone":"+43 4366 280423624",
    "sg:postcode":"5020",
    "sg:province":"Salzburg",
    "wof:name":"Alkoholkrankenberatung Amt d Sbg Landesregierung",
    "wof:placetype":"venue"
},
  "geometry": {"coordinates":[13.043466568,47.8145866394],"type":"Point"}
}