{
  "type": "Feature",
  "properties": {
    "addr:full":"Michaelsbergstr 5 Leonding Ober\u00f6sterreich 4060",
    "addr:housenumber":"5",
    "addr:postcode":"4060",
    "addr:street":"Michaelsbergstr",
    "iso:country":"AT",
    "sg:address":"Michaelsbergstr 5",
    "sg:city":"Leonding",
    "sg:orig_category":"Versicherungsunternehmen",
    "sg:phone":"+43 732 683686",
    "sg:postcode":"4060",
    "sg:province":"Ober\u00f6sterreich",
    "wof:name":"Wiener St\u00e4dtische Allgemeine Versicherung AG",
    "wof:placetype":"venue"
},
  "geometry": {"coordinates":[14.2498006821,48.2777824402],"type":"Point"}
}