{
  "type": "Feature",
  "properties": {
    "addr:full":"Lochlehn 389 S\u00f6lden Tirol 6450",
    "addr:housenumber":"389",
    "addr:postcode":"6450",
    "addr:street":"Lochlehn;Tirol",
    "iso:country":"AT",
    "sg:address":"Lochlehn 389",
    "sg:city":"S\u00f6lden",
    "sg:orig_category":"Appartements / Ferienwohnungen",
    "sg:phone":"+43 5254 2427",
    "sg:postcode":"6450",
    "sg:province":"Tirol",
    "wof:name":"Haus Olympia",
    "wof:placetype":"venue"
},
  "geometry": {"coordinates":[11.0076303482,46.9779510498],"type":"Point"}
}