{
  "type": "Feature",
  "properties": {
    "addr:full":"Bahnhofstr 155 Stainach Steiermark 8950",
    "addr:housenumber":"155",
    "addr:postcode":"8950",
    "addr:street":"Bahnhofstr",
    "iso:country":"AT",
    "sg:address":"Bahnhofstr 155",
    "sg:city":"Stainach",
    "sg:orig_category":"Banken U Sparkassen",
    "sg:phone":"+43 3682 22011",
    "sg:postcode":"8950",
    "sg:province":"Steiermark",
    "wof:name":"Raiffeisenbank Stainach regGenmbH",
    "wof:placetype":"venue"
},
  "geometry": {"coordinates":[14.1107378006,47.5302696228],"type":"Point"}
}