{
  "type": "Feature",
  "properties": {
    "addr:full":"Grazer Str 186 Pischelsdorf in Steiermark Steiermark 8212",
    "addr:housenumber":"186",
    "addr:postcode":"8212",
    "addr:street":"Pischelsdorf In",
    "iso:country":"AT",
    "sg:address":"Grazer Str 186",
    "sg:city":"Pischelsdorf in Steiermark",
    "sg:orig_category":"Elektroinstallationsunternehmen",
    "sg:phone":"+43 4331 1385550",
    "sg:postcode":"8212",
    "sg:province":"Steiermark",
    "wof:name":"Spindler & Spindler OHG",
    "wof:placetype":"venue"
},
  "geometry": {"coordinates":[15.8019390106,47.170124054],"type":"Point"}
}