{
  "type": "Feature",
  "properties": {
    "addr:full":"Brunnhof 13a Frohnleiten Steiermark 8130",
    "addr:housenumber":"13a",
    "addr:postcode":"8130",
    "addr:street":"Brunnhof",
    "iso:country":"AT",
    "sg:address":"Brunnhof 13a",
    "sg:city":"Frohnleiten",
    "sg:orig_category":"Schlossereien",
    "sg:phone":"+43 3126 4688",
    "sg:postcode":"8130",
    "sg:province":"Steiermark",
    "wof:name":"Deutsch Eduard",
    "wof:placetype":"venue"
},
  "geometry": {"coordinates":[15.3302841187,47.2704086304],"type":"Point"}
}