{
  "type": "Feature",
  "properties": {
    "addr:full":"Kalvarienbergg 12-14 Wien Wien 1170",
    "addr:postcode":"12-14;1170",
    "iso:country":"AT",
    "sg:address":"Kalvarienbergg 12-14",
    "sg:city":"Wien",
    "sg:orig_category":"Dekorationen",
    "sg:phone":"+43 1 40828380",
    "sg:postcode":"1170",
    "sg:province":"Wien",
    "wof:name":"STUDIO OBJEKTIV Ateliervermietungs- und Dekorationsbau GmbH",
    "wof:placetype":"venue"
},
  "geometry": {"coordinates":[16.3320178986,48.2153739929],"type":"Point"}
}