{
  "type": "Feature",
  "properties": {
    "addr:full":"Steirerg 11 Kilb Nieder\u00f6sterreich 3233",
    "addr:housenumber":"11",
    "addr:postcode":"3233",
    "addr:street":"Steirerg",
    "iso:country":"AT",
    "sg:address":"Steirerg 11",
    "sg:city":"Kilb",
    "sg:orig_category":"Glasereien",
    "sg:phone":"+43 4327 4873920",
    "sg:postcode":"3233",
    "sg:province":"Nieder\u00f6sterreich",
    "wof:name":"Gigl Karl",
    "wof:placetype":"venue"
},
  "geometry": {"coordinates":[15.4067249298,48.0991477966],"type":"Point"}
}