{
  "type": "Feature",
  "properties": {
    "iso:country":"AT",
    "sg:address":"Friedlg 1",
    "sg:city":"Marchegg Bahnhof",
    "sg:orig_category":"Bestattungsunternehmen",
    "sg:phone":"+43 2285 6161",
    "sg:postcode":"2294",
    "sg:province":"Nieder\u00f6sterreich",
    "wof:name":"Haberfellner Rudolf GesmbH",
    "wof:placetype":"venue"
},
  "geometry": {"coordinates":[16.9022254944,48.2217140198],"type":"Point"}
}