{
  "type": "Feature",
  "properties": {
    "addr:full":"Schulstr 9 Schwertberg Ober\u00f6sterreich 4311",
    "addr:housenumber":"9",
    "addr:postcode":"4311",
    "addr:street":"Schulstr",
    "iso:country":"AT",
    "sg:address":"Schulstr 9",
    "sg:city":"Schwertberg",
    "sg:orig_category":"Volksschulen",
    "sg:phone":"+43 4372 6261455",
    "sg:postcode":"4311",
    "sg:province":"Ober\u00f6sterreich",
    "wof:name":"Volksschule",
    "wof:placetype":"venue"
},
  "geometry": {"coordinates":[14.5817127228,48.2739906311],"type":"Point"}
}