{
  "type": "Feature",
  "properties": {
    "addr:full":"Nr 20 Rottenmann Steiermark 8786",
    "addr:postcode":"8786",
    "addr:street":"Nr",
    "iso:country":"AT",
    "sg:address":"Nr 20",
    "sg:city":"Rottenmann",
    "sg:orig_category":"Speditionen",
    "sg:phone":"+43 4336 1428970",
    "sg:postcode":"8786",
    "sg:province":"Steiermark",
    "wof:name":"I.R.I.T. Transport- u SpeditionsgesmbH",
    "wof:placetype":"venue"
},
  "geometry": {"coordinates":[14.35779953,47.5251693726],"type":"Point"}
}