{
  "type": "Feature",
  "properties": {
    "iso:country":"AT",
    "sg:address":"Neudorfer Str 83",
    "sg:city":"Parndorf",
    "sg:orig_category":"Autohandel",
    "sg:phone":"+43 4321 662514",
    "sg:postcode":"7111",
    "sg:province":"Burgenland",
    "wof:name":"Dikovits Johannes - Kfz-Technik u Handel",
    "wof:placetype":"venue"
},
  "geometry": {"coordinates":[16.8712005615,47.9997711182],"type":"Point"}
}