{
  "type": "Feature",
  "properties": {
    "addr:full":"Schweizer G 1 Lienz Tirol 9900",
    "addr:housenumber":"1",
    "addr:postcode":"9900",
    "addr:street":"Schweizer G;Tirol",
    "iso:country":"AT",
    "sg:address":"Schweizer G 1",
    "sg:city":"Lienz",
    "sg:orig_category":"Friseure U Frisiersalons",
    "sg:phone":"+43 4348 5267001",
    "sg:postcode":"9900",
    "sg:province":"Tirol",
    "wof:name":"Salon Jutta Inh Egger Jutta",
    "wof:placetype":"venue"
},
  "geometry": {"coordinates":[12.7639322281,46.8305740356],"type":"Point"}
}