{
  "type": "Feature",
  "properties": {
    "addr:full":"Kirchenstr 36 Velden am W\u00f6rther See K\u00e4rnten 9220",
    "addr:housenumber":"36",
    "addr:postcode":"9220",
    "addr:street":"Kirchenstr;Kaernten",
    "iso:country":"AT",
    "sg:address":"Kirchenstr 36",
    "sg:city":"Velden am W\u00f6rther See",
    "sg:classifiers":[
        {
            "category":"Travel",
            "subcategory":"Hotels & Motels",
            "type":"Entertainment"
        }
    ],
    "sg:phone":"+43 4342 7424980",
    "sg:postcode":"9220",
    "sg:province":"K\u00e4rnten",
    "wof:name":"G\u00e4stehaus Michaela",
    "wof:placetype":"venue"
},
  "geometry": {"coordinates":[14.0377454758,46.6159744263],"type":"Point"}
}