{
  "type": "Feature",
  "properties": {
    "addr:full":"Nr 1 Uttendorf Ober\u00f6sterreich 5261",
    "addr:postcode":"5261",
    "addr:street":"Nr;Uttendorf",
    "iso:country":"AT",
    "sg:address":"Nr 1",
    "sg:city":"Uttendorf",
    "sg:orig_category":"Non-Classified Establishments",
    "sg:phone":"+43 7724 2035",
    "sg:postcode":"5261",
    "sg:province":"Ober\u00f6sterreich",
    "wof:name":"Pfarramt",
    "wof:placetype":"venue"
},
  "geometry": {"coordinates":[13.1269302368,48.1575241089],"type":"Point"}
}