{
  "type": "Feature",
  "properties": {
    "addr:full":"Neilreichg 100 Wien Wien 1100",
    "addr:housenumber":"100",
    "addr:postcode":"1100",
    "iso:country":"AT",
    "sg:address":"Neilreichg 100",
    "sg:city":"Wien",
    "sg:orig_category":"\u00c3\u201erzte / F Allgemeinmedizin",
    "sg:phone":"+43 1 61722440",
    "sg:postcode":"1100",
    "sg:province":"Wien",
    "wof:name":"Sellner Cornelius Dr",
    "wof:placetype":"venue"
},
  "geometry": {"coordinates":[16.3632907867,48.1654586792],"type":"Point"}
}