{
  "type": "Feature",
  "properties": {
    "addr:full":"Wiener Strasse 21 Purkersdorf Nieder\u00f6sterreich 3002",
    "addr:housenumber":"21",
    "addr:postcode":"3002",
    "addr:street":"Wiener Strasse",
    "iso:country":"AT",
    "sg:address":"Wiener Strasse 21",
    "sg:city":"Purkersdorf",
    "sg:orig_category":"CarpenterS Work Supraregional",
    "sg:phone":"+43 2231 62149",
    "sg:postcode":"3002",
    "sg:province":"Nieder\u00f6sterreich",
    "wof:name":"Wanas GesmbH & Co KG",
    "wof:placetype":"venue"
},
  "geometry": {"coordinates":[16.1876983643,48.2064437866],"type":"Point"}
}