{
  "type": "Feature",
  "properties": {
    "addr:full":"Huben 210a L\u00e4ngenfeld Tirol 6444",
    "addr:housenumber":"210a",
    "addr:postcode":"6444",
    "addr:street":"Huben;Tirol",
    "iso:country":"AT",
    "sg:address":"Huben 210a",
    "sg:city":"L\u00e4ngenfeld",
    "sg:orig_category":"Appartements / Ferienwohnungen",
    "sg:phone":"+43 4352 536371",
    "sg:postcode":"6444",
    "sg:province":"Tirol",
    "wof:name":"Ferienwohnungen Frischmann Silvia",
    "wof:placetype":"venue"
},
  "geometry": {"coordinates":[10.9786863327,47.0399131775],"type":"Point"}
}