{
  "type": "Feature",
  "properties": {
    "addr:full":"Messestr 1-2 Dornbirn Vorarlberg 6850",
    "addr:housenumber":"1-2",
    "addr:postcode":"6850",
    "addr:street":"Messestr",
    "iso:country":"AT",
    "sg:address":"Messestr 1-2",
    "sg:city":"Dornbirn",
    "sg:orig_category":"Telekommunikation",
    "sg:phone":"+43 699 16999010",
    "sg:postcode":"6850",
    "sg:province":"Vorarlberg",
    "wof:name":"ONE World Dornbirn Messepark",
    "wof:placetype":"venue"
},
  "geometry": {"coordinates":[9.7132663727,47.4119987488],"type":"Point"}
}