{
  "type": "Feature",
  "properties": {
    "addr:full":"Nr 37 St. P\u00f6lten-Traisenpark Nieder\u00f6sterreich 3107",
    "addr:postcode":"3107",
    "addr:street":"Nr 37",
    "iso:country":"AT",
    "sg:address":"Nr 37",
    "sg:city":"St. P\u00f6lten-Traisenpark",
    "sg:classifiers":[
        {
            "category":"Professional",
            "subcategory":"Computer Services",
            "type":"Services"
        }
    ],
    "sg:phone":"+43 2742 3680550",
    "sg:postcode":"3107",
    "sg:province":"Nieder\u00f6sterreich",
    "sg:tags":[
        "software"
    ],
    "wof:name":"HDT Hovezak-Datentechnik",
    "wof:placetype":"venue"
},
  "geometry": {"coordinates":[15.6436395645,48.2288246155],"type":"Point"}
}