{
  "type": "Feature",
  "properties": {
    "addr:full":"Nr 203 St. Gallenkirch Vorarlberg 6791",
    "addr:postcode":"6791",
    "addr:street":"Nr 203",
    "iso:country":"AT",
    "sg:address":"Nr 203",
    "sg:city":"St. Gallenkirch",
    "sg:orig_category":"Pensionen / Privatzimmer",
    "sg:phone":"+43 5557 6165",
    "sg:postcode":"6791",
    "sg:province":"Vorarlberg",
    "wof:name":"Haus Olga",
    "wof:placetype":"venue"
},
  "geometry": {"coordinates":[9.9691953659,47.0225639343],"type":"Point"}
}