{
  "type": "Feature",
  "properties": {
    "addr:full":"Missindorfstr 29/Top 26 Wien Wien 1140",
    "addr:housenumber":"29 / top 26",
    "addr:postcode":"1140",
    "addr:street":"Missindorfstr",
    "iso:country":"AT",
    "sg:address":"Missindorfstr 29/Top 26",
    "sg:city":"Wien",
    "sg:orig_category":"Filmproduktionen",
    "sg:phone":"+43 1 9670145",
    "sg:postcode":"1140",
    "sg:province":"Wien",
    "wof:name":"SPECTRUM Trickfilm GmbH",
    "wof:placetype":"venue"
},
  "geometry": {"coordinates":[16.2696990967,48.1994247437],"type":"Point"}
}