{
  "type": "Feature",
  "properties": {
    "iso:country":"AT",
    "sg:address":"Tragweiner Strasse 71 ",
    "sg:city":"Pregarten",
    "sg:orig_category":"CarpenterS Work Supraregional",
    "sg:phone":"+43 7236 33130",
    "sg:postcode":"4230",
    "sg:province":"Ober\u00f6sterreich",
    "sg:website":"www.dachprofi.cc",
    "wof:name":"Aigner Leopold Ges.m.b.H. & Co KG",
    "wof:placetype":"venue"
},
  "geometry": {"coordinates":[14.5412807465,48.3487510681],"type":"Point"}
}