{
  "type": "Feature",
  "properties": {
    "addr:full":"Sturzg 42 Wien Wien 1150",
    "addr:housenumber":"42",
    "addr:postcode":"1150",
    "addr:street":"Sturzg",
    "iso:country":"AT",
    "sg:address":"Sturzg 42",
    "sg:city":"Wien",
    "sg:orig_category":"Autospenglereien",
    "sg:phone":"+43 1 9821334",
    "sg:postcode":"1150",
    "sg:province":"Wien",
    "wof:name":"Marx Helmut",
    "wof:placetype":"venue"
},
  "geometry": {"coordinates":[16.31782341,48.1983261108],"type":"Point"}
}