{
  "type": "Feature",
  "properties": {
    "addr:full":"Nr 45 Sch\u00f6nbach Nieder\u00f6sterreich 3633",
    "addr:postcode":"3633",
    "addr:street":"Nr 45 Schoenbach",
    "iso:country":"AT",
    "sg:address":"Nr 45",
    "sg:city":"Sch\u00f6nbach",
    "sg:orig_category":"Erdarbeiten",
    "sg:phone":"+43 2827 307",
    "sg:postcode":"3633",
    "sg:province":"Nieder\u00f6sterreich",
    "wof:name":"Steinbauer Josef",
    "wof:placetype":"venue"
},
  "geometry": {"coordinates":[15.0391149521,48.4534187317],"type":"Point"}
}