{
  "type": "Feature",
  "properties": {
    "addr:full":"Kirchg 1 Jenbach Tirol 6200",
    "addr:housenumber":"1",
    "addr:postcode":"6200",
    "addr:street":"Kirchg;Tirol",
    "iso:country":"AT",
    "sg:address":"Kirchg 1",
    "sg:city":"Jenbach",
    "sg:orig_category":"Banken U Sparkassen",
    "sg:phone":"+43 4352 4469990",
    "sg:postcode":"6200",
    "sg:province":"Tirol",
    "wof:name":"Raiffeisenbank Jenbach-Wiesing regGenmbH",
    "wof:placetype":"venue"
},
  "geometry": {"coordinates":[11.7726373672,47.3921432495],"type":"Point"}
}