{
  "type": "Feature",
  "properties": {
    "addr:full":"Kirchg 4-8 Th\u00fcringen Vorarlberg 6712",
    "addr:housenumber":"4-8",
    "addr:postcode":"6712",
    "addr:street":"Kirchg",
    "iso:country":"AT",
    "sg:address":"Kirchg 4-8",
    "sg:city":"Th\u00fcringen",
    "sg:orig_category":"Volksschulen",
    "sg:phone":"+43 5550 3059",
    "sg:postcode":"6712",
    "sg:province":"Vorarlberg",
    "wof:name":"Volksschule",
    "wof:placetype":"venue"
},
  "geometry": {"coordinates":[9.7677116394,47.1999893188],"type":"Point"}
}