{
  "type": "Feature",
  "properties": {
    "addr:full":"B\u00fcrgerg 28 Feldbach Steiermark 8330",
    "addr:housenumber":"28",
    "addr:postcode":"8330",
    "addr:street":"Buergerg",
    "iso:country":"AT",
    "sg:address":"B\u00fcrgerg 28",
    "sg:city":"Feldbach",
    "sg:orig_category":"Fleischhauereien",
    "sg:phone":"+43 3152 2549",
    "sg:postcode":"8330",
    "sg:province":"Steiermark",
    "wof:name":"Pfeiler Walter",
    "wof:placetype":"venue"
},
  "geometry": {"coordinates":[15.8557338715,46.9628982544],"type":"Point"}
}