{
  "type": "Feature",
  "properties": {
    "addr:full":"Schubertstrasse 104 Neulengbach Nieder\u00f6sterreich 3040",
    "addr:housenumber":"104",
    "addr:postcode":"3040",
    "addr:street":"Schubertstrasse",
    "iso:country":"AT",
    "sg:address":"Schubertstrasse 104",
    "sg:city":"Neulengbach",
    "sg:classifiers":[
        {
            "category":"Shopping",
            "subcategory":"Computers & Home Electronics",
            "type":"Retail Goods"
        }
    ],
    "sg:phone":"+43 2772 51170",
    "sg:postcode":"3040",
    "sg:province":"Nieder\u00f6sterreich",
    "sg:tags":[
        "code",
        "bar",
        "scanner",
        "decoder"
    ],
    "sg:website":"kimball.at",
    "wof:name":"KIMBALL Warenerfassungssysteme Handelsges.m.b.H.",
    "wof:placetype":"venue"
},
  "geometry": {"coordinates":[15.910984993,48.1948394775],"type":"Point"}
}