{
  "type": "Feature",
  "properties": {
    "addr:full":"Johann-Strau\u00df-G 28 Wiener Neustadt Nieder\u00f6sterreich 2700",
    "addr:housenumber":"28",
    "addr:postcode":"2700",
    "addr:street":"Johann-Strauss-G",
    "iso:country":"AT",
    "sg:address":"Johann-Strau\u00df-G 28",
    "sg:city":"Wiener Neustadt",
    "sg:orig_category":"Rauchfangkehrer",
    "sg:phone":"+43 2622 84584",
    "sg:postcode":"2700",
    "sg:province":"Nieder\u00f6sterreich",
    "wof:name":"Major Gertrude",
    "wof:placetype":"venue"
},
  "geometry": {"coordinates":[16.2587585449,47.819568634],"type":"Point"}
}