{
  "type": "Feature",
  "properties": {
    "addr:full":"Nr 26 Telfs Tirol 6410",
    "addr:postcode":"6410",
    "addr:street":"Nr 26;Tirol",
    "iso:country":"AT",
    "sg:address":"Nr 26",
    "sg:city":"Telfs",
    "sg:orig_category":"Postservicestellen",
    "sg:phone":"+43 5238 88294",
    "sg:postcode":"6410",
    "sg:province":"Tirol",
    "wof:name":"Postservicestelle Pettnau",
    "wof:placetype":"venue"
},
  "geometry": {"coordinates":[11.072218895,47.3066978455],"type":"Point"}
}