{
  "type": "Feature",
  "properties": {
    "addr:full":"Metzgerweg 414 Wals Salzburg 5071",
    "addr:housenumber":"414",
    "addr:postcode":"5071",
    "addr:street":"Metzgerweg;Salzburg",
    "iso:country":"AT",
    "sg:address":"Metzgerweg 414",
    "sg:city":"Wals",
    "sg:orig_category":"Banken U Sparkassen",
    "sg:phone":"+43 4350 10041049",
    "sg:postcode":"5071",
    "sg:province":"Salzburg",
    "wof:name":"Salzburger Sparkasse Bank AG",
    "wof:placetype":"venue"
},
  "geometry": {"coordinates":[12.976477623,47.7887001038],"type":"Point"}
}