{
  "type": "Feature",
  "properties": {
    "iso:country":"AT",
    "sg:address":"Bahnhofstr. 35 ",
    "sg:classifiers":[
        {
            "category":"Banks & Credit Unions",
            "subcategory":"Financial Services",
            "type":"Services"
        }
    ],
    "sg:phone":"+43 4355 744120",
    "sg:postcode":"6901",
    "sg:tags":[
        "banking",
        "finance",
        "insurance"
    ],
    "wof:name":"VORARLBERGER LANDES-VERSICHERUNG V.A.G.",
    "wof:placetype":"venue"
},
  "geometry": {"coordinates":[9.7415552139,47.5023460388],"type":"Point"}
}