{
  "type": "Feature",
  "properties": {
    "addr:full":"Hafnerriegel 37/III Graz Steiermark 8010",
    "addr:housenumber":"37 / iii",
    "addr:postcode":"8010",
    "addr:street":"Hafnerriegel",
    "iso:country":"AT",
    "sg:address":"Hafnerriegel 37/III",
    "sg:city":"Graz",
    "sg:orig_category":"\u00c3\u201erzte / F Allgemeinmedizin",
    "sg:phone":"+43 316 848776",
    "sg:postcode":"8010",
    "sg:province":"Steiermark",
    "wof:name":"Sedaghat Parviz Dr",
    "wof:placetype":"venue"
},
  "geometry": {"coordinates":[15.4431800842,47.0685653687],"type":"Point"}
}