{
  "type": "Feature",
  "properties": {
    "iso:country":"AT",
    "sg:city":"Timelkam",
    "sg:orig_category":"Feuerwehren",
    "sg:phone":"+43 767294122",
    "sg:postcode":"4850",
    "sg:province":"Ober\u00f6sterreich",
    "wof:name":"Freiwillige Feuerwehr Timelkam",
    "wof:placetype":"venue"
},
  "geometry": {"coordinates":[13.6127004623,48.00157547],"type":"Point"}
}