{
  "type": "Feature",
  "properties": {
    "addr:full":"Jubil\u00e4umsstr 23 Gumpoldskirchen Nieder\u00f6sterreich 2352",
    "addr:housenumber":"23",
    "addr:postcode":"2352",
    "addr:street":"Jubilaeumsstr",
    "iso:country":"AT",
    "sg:address":"Jubil\u00e4umsstr 23",
    "sg:city":"Gumpoldskirchen",
    "sg:orig_category":"Volksschulen",
    "sg:phone":"+43 2252 62975",
    "sg:postcode":"2352",
    "sg:province":"Nieder\u00f6sterreich",
    "wof:name":"Volksschule",
    "wof:placetype":"venue"
},
  "geometry": {"coordinates":[16.2799549103,48.0457496643],"type":"Point"}
}