{
  "type": "Feature",
  "properties": {
    "addr:full":"Schiffmanngasse 25 Salzburg Salzburg 5020",
    "addr:housenumber":"25",
    "addr:postcode":"5020",
    "addr:street":"Schiffmanngasse;Salzburg",
    "iso:country":"AT",
    "sg:address":"Schiffmanngasse 25",
    "sg:city":"Salzburg",
    "sg:classifiers":[
        {
            "category":"Health Services",
            "subcategory":"Medical Lab",
            "type":"Services"
        }
    ],
    "sg:phone":"+43 662 6350500",
    "sg:postcode":"5020",
    "sg:province":"Salzburg",
    "sg:tags":[
        "equipment",
        "use",
        "electronic"
    ],
    "wof:name":"Dr. Lahner GmbH - Medizintechnik",
    "wof:placetype":"venue"
},
  "geometry": {"coordinates":[13.0680656433,47.7827377319],"type":"Point"}
}