{
  "type": "Feature",
  "properties": {
    "addr:full":"Technikerstr 13 Graz Steiermark 8010",
    "addr:housenumber":"13",
    "addr:postcode":"8010",
    "addr:street":"Technikerstr",
    "iso:country":"AT",
    "sg:address":"Technikerstr 13",
    "sg:city":"Graz",
    "sg:orig_category":"Ingenieurkonsulenten / Zivilingenieure",
    "sg:phone":"+43 316 831511",
    "sg:postcode":"8010",
    "sg:province":"Steiermark",
    "wof:name":"Mohadjer Michael Dipl-Ing",
    "wof:placetype":"venue"
},
  "geometry": {"coordinates":[15.4505252838,47.0677146912],"type":"Point"}
}