{
  "type": "Feature",
  "properties": {
    "iso:country":"AT",
    "sg:address":"St.-Leonharderstr. 10",
    "sg:city":"Anif",
    "sg:classifiers":[
        {
            "category":"Manufacturing",
            "subcategory":"Printing",
            "type":"Manufacturing & Wholesale Goods"
        }
    ],
    "sg:phone":"+43 4362 468820",
    "sg:postcode":"5081",
    "sg:province":"Salzburg",
    "sg:tags":[
        "publishing"
    ],
    "wof:name":"PRESSEGRO\u00dfVERTRIEB SALZBURG GESMBH",
    "wof:placetype":"venue"
},
  "geometry": {"coordinates":[13.056555748,47.7246818542],"type":"Point"}
}