{
  "type": "Feature",
  "properties": {
    "addr:full":"M\u00fchleistr 18 Anif Salzburg 5081",
    "addr:housenumber":"18",
    "addr:postcode":"5081",
    "addr:street":"Muehleistr;Salzburg",
    "iso:country":"AT",
    "sg:address":"M\u00fchleistr 18",
    "sg:city":"Anif",
    "sg:orig_category":"Gesundheitsvorsorge",
    "sg:phone":"+43 699 18820001",
    "sg:postcode":"5081",
    "sg:province":"Salzburg",
    "wof:name":"Muhr Michaela - Aloe Vera",
    "wof:placetype":"venue"
},
  "geometry": {"coordinates":[13.0639257431,47.7499694824],"type":"Point"}
}